Compiled from "DeliverOrder.java"
public abstract class org.infinispan.remoting.inboundhandler.DeliverOrder extends java.lang.Enum<org.infinispan.remoting.inboundhandler.DeliverOrder> {
  public static final org.infinispan.remoting.inboundhandler.DeliverOrder NONE;

  public static final org.infinispan.remoting.inboundhandler.DeliverOrder PER_SENDER;

  public static final org.infinispan.remoting.inboundhandler.DeliverOrder TOTAL;

  private static final org.infinispan.remoting.inboundhandler.DeliverOrder[] $VALUES;

  public static org.infinispan.remoting.inboundhandler.DeliverOrder[] values();
    Code:
       0: getstatic     #2                  // Field $VALUES:[Lorg/infinispan/remoting/inboundhandler/DeliverOrder;
       3: invokevirtual #3                  // Method "[Lorg/infinispan/remoting/inboundhandler/DeliverOrder;".clone:()Ljava/lang/Object;
       6: checkcast     #4                  // class "[Lorg/infinispan/remoting/inboundhandler/DeliverOrder;"
       9: areturn

  public static org.infinispan.remoting.inboundhandler.DeliverOrder valueOf(java.lang.String);
    Code:
       0: ldc           #5                  // class org/infinispan/remoting/inboundhandler/DeliverOrder
       2: aload_0
       3: invokestatic  #6                  // Method java/lang/Enum.valueOf:(Ljava/lang/Class;Ljava/lang/String;)Ljava/lang/Enum;
       6: checkcast     #5                  // class org/infinispan/remoting/inboundhandler/DeliverOrder
       9: areturn

  private org.infinispan.remoting.inboundhandler.DeliverOrder();
    Code:
       0: aload_0
       1: aload_1
       2: iload_2
       3: invokespecial #7                  // Method java/lang/Enum."<init>":(Ljava/lang/String;I)V
       6: return

  public abstract boolean preserveOrder();

  org.infinispan.remoting.inboundhandler.DeliverOrder(java.lang.String, int, org.infinispan.remoting.inboundhandler.DeliverOrder$1);
    Code:
       0: aload_0
       1: aload_1
       2: iload_2
       3: invokespecial #1                  // Method "<init>":(Ljava/lang/String;I)V
       6: return

  static {};
    Code:
       0: new           #8                  // class org/infinispan/remoting/inboundhandler/DeliverOrder$1
       3: dup
       4: ldc           #9                  // String NONE
       6: iconst_0
       7: invokespecial #10                 // Method org/infinispan/remoting/inboundhandler/DeliverOrder$1."<init>":(Ljava/lang/String;I)V
      10: putstatic     #11                 // Field NONE:Lorg/infinispan/remoting/inboundhandler/DeliverOrder;
      13: new           #12                 // class org/infinispan/remoting/inboundhandler/DeliverOrder$2
      16: dup
      17: ldc           #13                 // String PER_SENDER
      19: iconst_1
      20: invokespecial #14                 // Method org/infinispan/remoting/inboundhandler/DeliverOrder$2."<init>":(Ljava/lang/String;I)V
      23: putstatic     #15                 // Field PER_SENDER:Lorg/infinispan/remoting/inboundhandler/DeliverOrder;
      26: new           #16                 // class org/infinispan/remoting/inboundhandler/DeliverOrder$3
      29: dup
      30: ldc           #17                 // String TOTAL
      32: iconst_2
      33: invokespecial #18                 // Method org/infinispan/remoting/inboundhandler/DeliverOrder$3."<init>":(Ljava/lang/String;I)V
      36: putstatic     #19                 // Field TOTAL:Lorg/infinispan/remoting/inboundhandler/DeliverOrder;
      39: iconst_3
      40: anewarray     #5                  // class org/infinispan/remoting/inboundhandler/DeliverOrder
      43: dup
      44: iconst_0
      45: getstatic     #11                 // Field NONE:Lorg/infinispan/remoting/inboundhandler/DeliverOrder;
      48: aastore
      49: dup
      50: iconst_1
      51: getstatic     #15                 // Field PER_SENDER:Lorg/infinispan/remoting/inboundhandler/DeliverOrder;
      54: aastore
      55: dup
      56: iconst_2
      57: getstatic     #19                 // Field TOTAL:Lorg/infinispan/remoting/inboundhandler/DeliverOrder;
      60: aastore
      61: putstatic     #2                  // Field $VALUES:[Lorg/infinispan/remoting/inboundhandler/DeliverOrder;
      64: return
}
