Compiled from "KinesisConsumer.java"
public class org.apache.camel.component.aws.kinesis.KinesisConsumer extends org.apache.camel.impl.ScheduledBatchPollingConsumer {
  private static final org.slf4j.Logger LOG;

  private java.lang.String currentShardIterator;

  public org.apache.camel.component.aws.kinesis.KinesisConsumer(org.apache.camel.component.aws.kinesis.KinesisEndpoint, org.apache.camel.Processor);
    Code:
       0: aload_0
       1: aload_1
       2: aload_2
       3: invokespecial #2                  // Method org/apache/camel/impl/ScheduledBatchPollingConsumer."<init>":(Lorg/apache/camel/Endpoint;Lorg/apache/camel/Processor;)V
       6: return

  protected int poll() throws java.lang.Exception;
    Code:
       0: new           #3                  // class com/amazonaws/services/kinesis/model/GetRecordsRequest
       3: dup
       4: invokespecial #4                  // Method com/amazonaws/services/kinesis/model/GetRecordsRequest."<init>":()V
       7: aload_0
       8: invokespecial #5                  // Method getShardItertor:()Ljava/lang/String;
      11: invokevirtual #6                  // Method com/amazonaws/services/kinesis/model/GetRecordsRequest.withShardIterator:(Ljava/lang/String;)Lcom/amazonaws/services/kinesis/model/GetRecordsRequest;
      14: aload_0
      15: invokevirtual #7                  // Method getEndpoint:()Lorg/apache/camel/component/aws/kinesis/KinesisEndpoint;
      18: invokevirtual #8                  // Method org/apache/camel/component/aws/kinesis/KinesisEndpoint.getMaxResultsPerRequest:()I
      21: invokestatic  #9                  // Method java/lang/Integer.valueOf:(I)Ljava/lang/Integer;
      24: invokevirtual #10                 // Method com/amazonaws/services/kinesis/model/GetRecordsRequest.withLimit:(Ljava/lang/Integer;)Lcom/amazonaws/services/kinesis/model/GetRecordsRequest;
      27: astore_1
      28: aload_0
      29: invokespecial #11                 // Method getClient:()Lcom/amazonaws/services/kinesis/AmazonKinesis;
      32: aload_1
      33: invokeinterface #12,  2           // InterfaceMethod com/amazonaws/services/kinesis/AmazonKinesis.getRecords:(Lcom/amazonaws/services/kinesis/model/GetRecordsRequest;)Lcom/amazonaws/services/kinesis/model/GetRecordsResult;
      38: astore_2
      39: aload_0
      40: aload_2
      41: invokevirtual #13                 // Method com/amazonaws/services/kinesis/model/GetRecordsResult.getRecords:()Ljava/util/List;
      44: invokespecial #14                 // Method createExchanges:(Ljava/util/List;)Ljava/util/Queue;
      47: astore_3
      48: aload_0
      49: aload_3
      50: invokestatic  #15                 // Method org/apache/camel/util/CastUtils.cast:(Ljava/util/Queue;)Ljava/util/Queue;
      53: invokevirtual #16                 // Method processBatch:(Ljava/util/Queue;)I
      56: istore        4
      58: aload_0
      59: aload_2
      60: invokevirtual #17                 // Method com/amazonaws/services/kinesis/model/GetRecordsResult.getNextShardIterator:()Ljava/lang/String;
      63: putfield      #18                 // Field currentShardIterator:Ljava/lang/String;
      66: iload         4
      68: ireturn

  public int processBatch(java.util.Queue<java.lang.Object>) throws java.lang.Exception;
    Code:
       0: iconst_0
       1: istore_2
       2: aload_1
       3: invokeinterface #19,  1           // InterfaceMethod java/util/Queue.isEmpty:()Z
       8: ifne          63
      11: ldc           #20                 // class org/apache/camel/Exchange
      13: aload_1
      14: invokeinterface #21,  1           // InterfaceMethod java/util/Queue.poll:()Ljava/lang/Object;
      19: invokestatic  #22                 // Method org/apache/camel/util/ObjectHelper.cast:(Ljava/lang/Class;Ljava/lang/Object;)Ljava/lang/Object;
      22: checkcast     #20                 // class org/apache/camel/Exchange
      25: astore_3
      26: getstatic     #1                  // Field LOG:Lorg/slf4j/Logger;
      29: ldc           #23                 // String Processing exchange [{}] started.
      31: aload_3
      32: invokeinterface #24,  3           // InterfaceMethod org/slf4j/Logger.trace:(Ljava/lang/String;Ljava/lang/Object;)V
      37: aload_0
      38: invokevirtual #25                 // Method getAsyncProcessor:()Lorg/apache/camel/AsyncProcessor;
      41: aload_3
      42: new           #26                 // class org/apache/camel/component/aws/kinesis/KinesisConsumer$1
      45: dup
      46: aload_0
      47: aload_3
      48: invokespecial #27                 // Method org/apache/camel/component/aws/kinesis/KinesisConsumer$1."<init>":(Lorg/apache/camel/component/aws/kinesis/KinesisConsumer;Lorg/apache/camel/Exchange;)V
      51: invokeinterface #28,  3           // InterfaceMethod org/apache/camel/AsyncProcessor.process:(Lorg/apache/camel/Exchange;Lorg/apache/camel/AsyncCallback;)Z
      56: pop
      57: iinc          2, 1
      60: goto          2
      63: iload_2
      64: ireturn

  private com.amazonaws.services.kinesis.AmazonKinesis getClient();
    Code:
       0: aload_0
       1: invokevirtual #7                  // Method getEndpoint:()Lorg/apache/camel/component/aws/kinesis/KinesisEndpoint;
       4: invokevirtual #29                 // Method org/apache/camel/component/aws/kinesis/KinesisEndpoint.getClient:()Lcom/amazonaws/services/kinesis/AmazonKinesis;
       7: areturn

  public org.apache.camel.component.aws.kinesis.KinesisEndpoint getEndpoint();
    Code:
       0: aload_0
       1: invokespecial #30                 // Method org/apache/camel/impl/ScheduledBatchPollingConsumer.getEndpoint:()Lorg/apache/camel/Endpoint;
       4: checkcast     #31                 // class org/apache/camel/component/aws/kinesis/KinesisEndpoint
       7: areturn

  private java.lang.String getShardItertor();
    Code:
       0: aload_0
       1: getfield      #18                 // Field currentShardIterator:Ljava/lang/String;
       4: ifnonnull     161
       7: aload_0
       8: invokevirtual #7                  // Method getEndpoint:()Lorg/apache/camel/component/aws/kinesis/KinesisEndpoint;
      11: invokevirtual #32                 // Method org/apache/camel/component/aws/kinesis/KinesisEndpoint.getShardId:()Ljava/lang/String;
      14: invokevirtual #33                 // Method java/lang/String.isEmpty:()Z
      17: ifne          31
      20: aload_0
      21: invokevirtual #7                  // Method getEndpoint:()Lorg/apache/camel/component/aws/kinesis/KinesisEndpoint;
      24: invokevirtual #32                 // Method org/apache/camel/component/aws/kinesis/KinesisEndpoint.getShardId:()Ljava/lang/String;
      27: astore_1
      28: goto          80
      31: new           #34                 // class com/amazonaws/services/kinesis/model/DescribeStreamRequest
      34: dup
      35: invokespecial #35                 // Method com/amazonaws/services/kinesis/model/DescribeStreamRequest."<init>":()V
      38: aload_0
      39: invokevirtual #7                  // Method getEndpoint:()Lorg/apache/camel/component/aws/kinesis/KinesisEndpoint;
      42: invokevirtual #36                 // Method org/apache/camel/component/aws/kinesis/KinesisEndpoint.getStreamName:()Ljava/lang/String;
      45: invokevirtual #37                 // Method com/amazonaws/services/kinesis/model/DescribeStreamRequest.withStreamName:(Ljava/lang/String;)Lcom/amazonaws/services/kinesis/model/DescribeStreamRequest;
      48: astore_2
      49: aload_0
      50: invokespecial #11                 // Method getClient:()Lcom/amazonaws/services/kinesis/AmazonKinesis;
      53: aload_2
      54: invokeinterface #38,  2           // InterfaceMethod com/amazonaws/services/kinesis/AmazonKinesis.describeStream:(Lcom/amazonaws/services/kinesis/model/DescribeStreamRequest;)Lcom/amazonaws/services/kinesis/model/DescribeStreamResult;
      59: astore_3
      60: aload_3
      61: invokevirtual #39                 // Method com/amazonaws/services/kinesis/model/DescribeStreamResult.getStreamDescription:()Lcom/amazonaws/services/kinesis/model/StreamDescription;
      64: invokevirtual #40                 // Method com/amazonaws/services/kinesis/model/StreamDescription.getShards:()Ljava/util/List;
      67: iconst_0
      68: invokeinterface #41,  2           // InterfaceMethod java/util/List.get:(I)Ljava/lang/Object;
      73: checkcast     #42                 // class com/amazonaws/services/kinesis/model/Shard
      76: invokevirtual #43                 // Method com/amazonaws/services/kinesis/model/Shard.getShardId:()Ljava/lang/String;
      79: astore_1
      80: getstatic     #1                  // Field LOG:Lorg/slf4j/Logger;
      83: ldc           #44                 // String ShardId is: {}
      85: aload_1
      86: invokeinterface #45,  3           // InterfaceMethod org/slf4j/Logger.debug:(Ljava/lang/String;Ljava/lang/Object;)V
      91: new           #46                 // class com/amazonaws/services/kinesis/model/GetShardIteratorRequest
      94: dup
      95: invokespecial #47                 // Method com/amazonaws/services/kinesis/model/GetShardIteratorRequest."<init>":()V
      98: aload_0
      99: invokevirtual #7                  // Method getEndpoint:()Lorg/apache/camel/component/aws/kinesis/KinesisEndpoint;
     102: invokevirtual #36                 // Method org/apache/camel/component/aws/kinesis/KinesisEndpoint.getStreamName:()Ljava/lang/String;
     105: invokevirtual #48                 // Method com/amazonaws/services/kinesis/model/GetShardIteratorRequest.withStreamName:(Ljava/lang/String;)Lcom/amazonaws/services/kinesis/model/GetShardIteratorRequest;
     108: aload_1
     109: invokevirtual #49                 // Method com/amazonaws/services/kinesis/model/GetShardIteratorRequest.withShardId:(Ljava/lang/String;)Lcom/amazonaws/services/kinesis/model/GetShardIteratorRequest;
     112: aload_0
     113: invokevirtual #7                  // Method getEndpoint:()Lorg/apache/camel/component/aws/kinesis/KinesisEndpoint;
     116: invokevirtual #50                 // Method org/apache/camel/component/aws/kinesis/KinesisEndpoint.getIteratorType:()Lcom/amazonaws/services/kinesis/model/ShardIteratorType;
     119: invokevirtual #51                 // Method com/amazonaws/services/kinesis/model/GetShardIteratorRequest.withShardIteratorType:(Lcom/amazonaws/services/kinesis/model/ShardIteratorType;)Lcom/amazonaws/services/kinesis/model/GetShardIteratorRequest;
     122: astore_2
     123: aload_0
     124: invokespecial #52                 // Method hasSequenceNumber:()Z
     127: ifeq          142
     130: aload_2
     131: aload_0
     132: invokevirtual #7                  // Method getEndpoint:()Lorg/apache/camel/component/aws/kinesis/KinesisEndpoint;
     135: invokevirtual #53                 // Method org/apache/camel/component/aws/kinesis/KinesisEndpoint.getSequenceNumber:()Ljava/lang/String;
     138: invokevirtual #54                 // Method com/amazonaws/services/kinesis/model/GetShardIteratorRequest.withStartingSequenceNumber:(Ljava/lang/String;)Lcom/amazonaws/services/kinesis/model/GetShardIteratorRequest;
     141: pop
     142: aload_0
     143: invokespecial #11                 // Method getClient:()Lcom/amazonaws/services/kinesis/AmazonKinesis;
     146: aload_2
     147: invokeinterface #55,  2           // InterfaceMethod com/amazonaws/services/kinesis/AmazonKinesis.getShardIterator:(Lcom/amazonaws/services/kinesis/model/GetShardIteratorRequest;)Lcom/amazonaws/services/kinesis/model/GetShardIteratorResult;
     152: astore_3
     153: aload_0
     154: aload_3
     155: invokevirtual #56                 // Method com/amazonaws/services/kinesis/model/GetShardIteratorResult.getShardIterator:()Ljava/lang/String;
     158: putfield      #18                 // Field currentShardIterator:Ljava/lang/String;
     161: getstatic     #1                  // Field LOG:Lorg/slf4j/Logger;
     164: ldc           #57                 // String Shard Iterator is: {}
     166: aload_0
     167: getfield      #18                 // Field currentShardIterator:Ljava/lang/String;
     170: invokeinterface #45,  3           // InterfaceMethod org/slf4j/Logger.debug:(Ljava/lang/String;Ljava/lang/Object;)V
     175: aload_0
     176: getfield      #18                 // Field currentShardIterator:Ljava/lang/String;
     179: areturn

  private java.util.Queue<org.apache.camel.Exchange> createExchanges(java.util.List<com.amazonaws.services.kinesis.model.Record>);
    Code:
       0: new           #58                 // class java/util/ArrayDeque
       3: dup
       4: invokespecial #59                 // Method java/util/ArrayDeque."<init>":()V
       7: astore_2
       8: aload_1
       9: invokeinterface #60,  1           // InterfaceMethod java/util/List.iterator:()Ljava/util/Iterator;
      14: astore_3
      15: aload_3
      16: invokeinterface #61,  1           // InterfaceMethod java/util/Iterator.hasNext:()Z
      21: ifeq          54
      24: aload_3
      25: invokeinterface #62,  1           // InterfaceMethod java/util/Iterator.next:()Ljava/lang/Object;
      30: checkcast     #63                 // class com/amazonaws/services/kinesis/model/Record
      33: astore        4
      35: aload_2
      36: aload_0
      37: invokevirtual #7                  // Method getEndpoint:()Lorg/apache/camel/component/aws/kinesis/KinesisEndpoint;
      40: aload         4
      42: invokevirtual #64                 // Method org/apache/camel/component/aws/kinesis/KinesisEndpoint.createExchange:(Lcom/amazonaws/services/kinesis/model/Record;)Lorg/apache/camel/Exchange;
      45: invokeinterface #65,  2           // InterfaceMethod java/util/Queue.add:(Ljava/lang/Object;)Z
      50: pop
      51: goto          15
      54: aload_2
      55: areturn

  private boolean hasSequenceNumber();
    Code:
       0: aload_0
       1: invokevirtual #7                  // Method getEndpoint:()Lorg/apache/camel/component/aws/kinesis/KinesisEndpoint;
       4: invokevirtual #53                 // Method org/apache/camel/component/aws/kinesis/KinesisEndpoint.getSequenceNumber:()Ljava/lang/String;
       7: invokevirtual #33                 // Method java/lang/String.isEmpty:()Z
      10: ifne          49
      13: aload_0
      14: invokevirtual #7                  // Method getEndpoint:()Lorg/apache/camel/component/aws/kinesis/KinesisEndpoint;
      17: invokevirtual #50                 // Method org/apache/camel/component/aws/kinesis/KinesisEndpoint.getIteratorType:()Lcom/amazonaws/services/kinesis/model/ShardIteratorType;
      20: getstatic     #66                 // Field com/amazonaws/services/kinesis/model/ShardIteratorType.AFTER_SEQUENCE_NUMBER:Lcom/amazonaws/services/kinesis/model/ShardIteratorType;
      23: invokevirtual #67                 // Method com/amazonaws/services/kinesis/model/ShardIteratorType.equals:(Ljava/lang/Object;)Z
      26: ifne          45
      29: aload_0
      30: invokevirtual #7                  // Method getEndpoint:()Lorg/apache/camel/component/aws/kinesis/KinesisEndpoint;
      33: invokevirtual #50                 // Method org/apache/camel/component/aws/kinesis/KinesisEndpoint.getIteratorType:()Lcom/amazonaws/services/kinesis/model/ShardIteratorType;
      36: getstatic     #68                 // Field com/amazonaws/services/kinesis/model/ShardIteratorType.AT_SEQUENCE_NUMBER:Lcom/amazonaws/services/kinesis/model/ShardIteratorType;
      39: invokevirtual #67                 // Method com/amazonaws/services/kinesis/model/ShardIteratorType.equals:(Ljava/lang/Object;)Z
      42: ifeq          49
      45: iconst_1
      46: goto          50
      49: iconst_0
      50: ireturn

  public org.apache.camel.Endpoint getEndpoint();
    Code:
       0: aload_0
       1: invokevirtual #7                  // Method getEndpoint:()Lorg/apache/camel/component/aws/kinesis/KinesisEndpoint;
       4: areturn

  static org.slf4j.Logger access$000();
    Code:
       0: getstatic     #1                  // Field LOG:Lorg/slf4j/Logger;
       3: areturn

  static {};
    Code:
       0: ldc           #69                 // class org/apache/camel/component/aws/kinesis/KinesisConsumer
       2: invokestatic  #70                 // Method org/slf4j/LoggerFactory.getLogger:(Ljava/lang/Class;)Lorg/slf4j/Logger;
       5: putstatic     #1                  // Field LOG:Lorg/slf4j/Logger;
       8: return
}
