Compiled from "BasicEofSensorWatcher.java"
public class org.apache.http.conn.BasicEofSensorWatcher implements org.apache.http.conn.EofSensorWatcher {
  protected final org.apache.http.conn.ManagedClientConnection managedConn;

  protected final boolean attemptReuse;

  public org.apache.http.conn.BasicEofSensorWatcher(org.apache.http.conn.ManagedClientConnection, boolean);
    Code:
       0: aload_0
       1: invokespecial #1                  // Method java/lang/Object."<init>":()V
       4: aload_1
       5: ifnonnull     18
       8: new           #2                  // class java/lang/IllegalArgumentException
      11: dup
      12: ldc           #3                  // String Connection may not be null.
      14: invokespecial #4                  // Method java/lang/IllegalArgumentException."<init>":(Ljava/lang/String;)V
      17: athrow
      18: aload_0
      19: aload_1
      20: putfield      #5                  // Field managedConn:Lorg/apache/http/conn/ManagedClientConnection;
      23: aload_0
      24: iload_2
      25: putfield      #6                  // Field attemptReuse:Z
      28: return

  public boolean eofDetected(java.io.InputStream) throws java.io.IOException;
    Code:
       0: aload_0
       1: getfield      #6                  // Field attemptReuse:Z
       4: ifeq          20
       7: aload_1
       8: invokevirtual #7                  // Method java/io/InputStream.close:()V
      11: aload_0
      12: getfield      #5                  // Field managedConn:Lorg/apache/http/conn/ManagedClientConnection;
      15: invokeinterface #8,  1            // InterfaceMethod org/apache/http/conn/ManagedClientConnection.markReusable:()V
      20: aload_0
      21: getfield      #5                  // Field managedConn:Lorg/apache/http/conn/ManagedClientConnection;
      24: invokeinterface #9,  1            // InterfaceMethod org/apache/http/conn/ManagedClientConnection.releaseConnection:()V
      29: goto          44
      32: astore_2
      33: aload_0
      34: getfield      #5                  // Field managedConn:Lorg/apache/http/conn/ManagedClientConnection;
      37: invokeinterface #9,  1            // InterfaceMethod org/apache/http/conn/ManagedClientConnection.releaseConnection:()V
      42: aload_2
      43: athrow
      44: iconst_0
      45: ireturn
    Exception table:
       from    to  target type
           0    20    32   any
          32    33    32   any

  public boolean streamClosed(java.io.InputStream) throws java.io.IOException;
    Code:
       0: aload_0
       1: getfield      #6                  // Field attemptReuse:Z
       4: ifeq          20
       7: aload_1
       8: invokevirtual #7                  // Method java/io/InputStream.close:()V
      11: aload_0
      12: getfield      #5                  // Field managedConn:Lorg/apache/http/conn/ManagedClientConnection;
      15: invokeinterface #8,  1            // InterfaceMethod org/apache/http/conn/ManagedClientConnection.markReusable:()V
      20: aload_0
      21: getfield      #5                  // Field managedConn:Lorg/apache/http/conn/ManagedClientConnection;
      24: invokeinterface #9,  1            // InterfaceMethod org/apache/http/conn/ManagedClientConnection.releaseConnection:()V
      29: goto          44
      32: astore_2
      33: aload_0
      34: getfield      #5                  // Field managedConn:Lorg/apache/http/conn/ManagedClientConnection;
      37: invokeinterface #9,  1            // InterfaceMethod org/apache/http/conn/ManagedClientConnection.releaseConnection:()V
      42: aload_2
      43: athrow
      44: iconst_0
      45: ireturn
    Exception table:
       from    to  target type
           0    20    32   any
          32    33    32   any

  public boolean streamAbort(java.io.InputStream) throws java.io.IOException;
    Code:
       0: aload_0
       1: getfield      #5                  // Field managedConn:Lorg/apache/http/conn/ManagedClientConnection;
       4: invokeinterface #10,  1           // InterfaceMethod org/apache/http/conn/ManagedClientConnection.abortConnection:()V
       9: iconst_0
      10: ireturn
}
