Compiled from "WebMetaDataCreator.java"
final class org.jboss.as.webservices.tomcat.WebMetaDataCreator {
  private static final java.lang.String EJB_WEBSERVICE_REALM;

  private final org.jboss.as.webservices.tomcat.SecurityMetaDataAccessorEJB ejb3SecurityAccessor;

  org.jboss.as.webservices.tomcat.WebMetaDataCreator();
    Code:
       0: aload_0
       1: invokespecial #1                  // Method java/lang/Object."<init>":()V
       4: aload_0
       5: new           #2                  // class org/jboss/as/webservices/tomcat/SecurityMetaDataAccessorEJB3
       8: dup
       9: invokespecial #3                  // Method org/jboss/as/webservices/tomcat/SecurityMetaDataAccessorEJB3."<init>":()V
      12: putfield      #4                  // Field ejb3SecurityAccessor:Lorg/jboss/as/webservices/tomcat/SecurityMetaDataAccessorEJB;
      15: return

  void create(org.jboss.wsf.spi.deployment.Deployment);
    Code:
       0: aload_1
       1: ldc           #5                  // class org/jboss/as/server/deployment/DeploymentUnit
       3: invokestatic  #6                  // Method org/jboss/ws/common/integration/WSHelper.getRequiredAttachment:(Lorg/jboss/wsf/spi/deployment/Deployment;Ljava/lang/Class;)Ljava/lang/Object;
       6: checkcast     #5                  // class org/jboss/as/server/deployment/DeploymentUnit
       9: astore_2
      10: aload_2
      11: getstatic     #7                  // Field org/jboss/as/web/common/WarMetaData.ATTACHMENT_KEY:Lorg/jboss/as/server/deployment/AttachmentKey;
      14: invokestatic  #8                  // Method org/jboss/as/webservices/util/ASHelper.getOptionalAttachment:(Lorg/jboss/as/server/deployment/DeploymentUnit;Lorg/jboss/as/server/deployment/AttachmentKey;)Ljava/lang/Object;
      17: checkcast     #9                  // class org/jboss/as/web/common/WarMetaData
      20: astore_3
      21: aload_3
      22: ifnull        32
      25: aload_3
      26: invokevirtual #10                 // Method org/jboss/as/web/common/WarMetaData.getMergedJBossWebMetaData:()Lorg/jboss/metadata/web/jboss/JBossWebMetaData;
      29: goto          33
      32: aconst_null
      33: astore        4
      35: aload_3
      36: ifnonnull     47
      39: new           #9                  // class org/jboss/as/web/common/WarMetaData
      42: dup
      43: invokespecial #11                 // Method org/jboss/as/web/common/WarMetaData."<init>":()V
      46: astore_3
      47: aload         4
      49: ifnonnull     78
      52: new           #12                 // class org/jboss/metadata/web/jboss/JBossWebMetaData
      55: dup
      56: invokespecial #13                 // Method org/jboss/metadata/web/jboss/JBossWebMetaData."<init>":()V
      59: astore        4
      61: aload_3
      62: aload         4
      64: invokevirtual #14                 // Method org/jboss/as/web/common/WarMetaData.setMergedJBossWebMetaData:(Lorg/jboss/metadata/web/jboss/JBossWebMetaData;)V
      67: aload_2
      68: getstatic     #7                  // Field org/jboss/as/web/common/WarMetaData.ATTACHMENT_KEY:Lorg/jboss/as/server/deployment/AttachmentKey;
      71: aload_3
      72: invokeinterface #15,  3           // InterfaceMethod org/jboss/as/server/deployment/DeploymentUnit.putAttachment:(Lorg/jboss/as/server/deployment/AttachmentKey;Ljava/lang/Object;)Ljava/lang/Object;
      77: pop
      78: aload_0
      79: aload_1
      80: aload         4
      82: invokespecial #16                 // Method createWebAppDescriptor:(Lorg/jboss/wsf/spi/deployment/Deployment;Lorg/jboss/metadata/web/jboss/JBossWebMetaData;)V
      85: aload_0
      86: aload_1
      87: aload         4
      89: invokespecial #17                 // Method createJBossWebAppDescriptor:(Lorg/jboss/wsf/spi/deployment/Deployment;Lorg/jboss/metadata/web/jboss/JBossWebMetaData;)V
      92: aload_1
      93: ldc           #12                 // class org/jboss/metadata/web/jboss/JBossWebMetaData
      95: aload         4
      97: invokeinterface #18,  3           // InterfaceMethod org/jboss/wsf/spi/deployment/Deployment.addAttachment:(Ljava/lang/Class;Ljava/lang/Object;)Ljava/lang/Object;
     102: pop
     103: return

  private void createWebAppDescriptor(org.jboss.wsf.spi.deployment.Deployment, org.jboss.metadata.web.jboss.JBossWebMetaData);
    Code:
       0: getstatic     #19                 // Field org/jboss/as/webservices/logging/WSLogger.ROOT_LOGGER:Lorg/jboss/as/webservices/logging/WSLogger;
       3: ldc           #20                 // String Creating web.xml descriptor
       5: invokeinterface #21,  2           // InterfaceMethod org/jboss/as/webservices/logging/WSLogger.trace:(Ljava/lang/Object;)V
      10: aload_0
      11: aload_1
      12: aload_2
      13: invokespecial #22                 // Method createServlets:(Lorg/jboss/wsf/spi/deployment/Deployment;Lorg/jboss/metadata/web/jboss/JBossWebMetaData;)V
      16: aload_0
      17: aload_1
      18: aload_2
      19: invokespecial #23                 // Method createServletMappings:(Lorg/jboss/wsf/spi/deployment/Deployment;Lorg/jboss/metadata/web/jboss/JBossWebMetaData;)V
      22: aload_0
      23: aload_1
      24: aload_2
      25: invokespecial #24                 // Method createSecurityConstraints:(Lorg/jboss/wsf/spi/deployment/Deployment;Lorg/jboss/metadata/web/jboss/JBossWebMetaData;)V
      28: aload_0
      29: aload_1
      30: aload_2
      31: invokespecial #25                 // Method createLoginConfig:(Lorg/jboss/wsf/spi/deployment/Deployment;Lorg/jboss/metadata/web/jboss/JBossWebMetaData;)V
      34: aload_0
      35: aload_1
      36: aload_2
      37: invokespecial #26                 // Method createSecurityRoles:(Lorg/jboss/wsf/spi/deployment/Deployment;Lorg/jboss/metadata/web/jboss/JBossWebMetaData;)V
      40: return

  private void createJBossWebAppDescriptor(org.jboss.wsf.spi.deployment.Deployment, org.jboss.metadata.web.jboss.JBossWebMetaData);
    Code:
       0: getstatic     #19                 // Field org/jboss/as/webservices/logging/WSLogger.ROOT_LOGGER:Lorg/jboss/as/webservices/logging/WSLogger;
       3: ldc           #27                 // String Creating jboss-web.xml descriptor
       5: invokeinterface #21,  2           // InterfaceMethod org/jboss/as/webservices/logging/WSLogger.trace:(Ljava/lang/Object;)V
      10: aload_0
      11: getfield      #4                  // Field ejb3SecurityAccessor:Lorg/jboss/as/webservices/tomcat/SecurityMetaDataAccessorEJB;
      14: aload_1
      15: invokeinterface #28,  2           // InterfaceMethod org/jboss/as/webservices/tomcat/SecurityMetaDataAccessorEJB.getSecurityDomain:(Lorg/jboss/wsf/spi/deployment/Deployment;)Ljava/lang/String;
      20: astore_3
      21: aload_3
      22: ifnull        29
      25: iconst_1
      26: goto          30
      29: iconst_0
      30: istore        4
      32: iload         4
      34: ifeq          53
      37: getstatic     #19                 // Field org/jboss/as/webservices/logging/WSLogger.ROOT_LOGGER:Lorg/jboss/as/webservices/logging/WSLogger;
      40: ldc           #29                 // String Setting security domain: %s
      42: aload_3
      43: invokeinterface #30,  3           // InterfaceMethod org/jboss/as/webservices/logging/WSLogger.tracef:(Ljava/lang/String;Ljava/lang/Object;)V
      48: aload_2
      49: aload_3
      50: invokevirtual #31                 // Method org/jboss/metadata/web/jboss/JBossWebMetaData.setSecurityDomain:(Ljava/lang/String;)V
      53: aload_1
      54: invokeinterface #32,  1           // InterfaceMethod org/jboss/wsf/spi/deployment/Deployment.getService:()Lorg/jboss/wsf/spi/deployment/Service;
      59: invokeinterface #33,  1           // InterfaceMethod org/jboss/wsf/spi/deployment/Service.getVirtualHost:()Ljava/lang/String;
      64: astore        5
      66: new           #34                 // class org/jboss/as/webservices/config/ServerHostInfo
      69: dup
      70: aload         5
      72: invokespecial #35                 // Method org/jboss/as/webservices/config/ServerHostInfo."<init>":(Ljava/lang/String;)V
      75: astore        6
      77: aload         6
      79: invokevirtual #36                 // Method org/jboss/as/webservices/config/ServerHostInfo.getHost:()Ljava/lang/String;
      82: ifnull        136
      85: getstatic     #19                 // Field org/jboss/as/webservices/logging/WSLogger.ROOT_LOGGER:Lorg/jboss/as/webservices/logging/WSLogger;
      88: ldc           #37                 // String Setting virtual host: %s
      90: aload         6
      92: invokevirtual #36                 // Method org/jboss/as/webservices/config/ServerHostInfo.getHost:()Ljava/lang/String;
      95: invokeinterface #30,  3           // InterfaceMethod org/jboss/as/webservices/logging/WSLogger.tracef:(Ljava/lang/String;Ljava/lang/Object;)V
     100: aload_2
     101: iconst_1
     102: anewarray     #38                 // class java/lang/String
     105: dup
     106: iconst_0
     107: aload         6
     109: invokevirtual #36                 // Method org/jboss/as/webservices/config/ServerHostInfo.getHost:()Ljava/lang/String;
     112: aastore
     113: invokestatic  #39                 // Method java/util/Arrays.asList:([Ljava/lang/Object;)Ljava/util/List;
     116: invokevirtual #40                 // Method org/jboss/metadata/web/jboss/JBossWebMetaData.setVirtualHosts:(Ljava/util/List;)V
     119: aload         6
     121: invokevirtual #41                 // Method org/jboss/as/webservices/config/ServerHostInfo.getServerInstanceName:()Ljava/lang/String;
     124: ifnull        136
     127: aload_2
     128: aload         6
     130: invokevirtual #41                 // Method org/jboss/as/webservices/config/ServerHostInfo.getServerInstanceName:()Ljava/lang/String;
     133: invokevirtual #42                 // Method org/jboss/metadata/web/jboss/JBossWebMetaData.setServerInstanceName:(Ljava/lang/String;)V
     136: return

  private void createServlets(org.jboss.wsf.spi.deployment.Deployment, org.jboss.metadata.web.jboss.JBossWebMetaData);
    Code:
       0: getstatic     #19                 // Field org/jboss/as/webservices/logging/WSLogger.ROOT_LOGGER:Lorg/jboss/as/webservices/logging/WSLogger;
       3: ldc           #43                 // String Creating servlets
       5: invokeinterface #21,  2           // InterfaceMethod org/jboss/as/webservices/logging/WSLogger.trace:(Ljava/lang/Object;)V
      10: aload_2
      11: invokestatic  #44                 // Method org/jboss/as/webservices/util/WebMetaDataHelper.getServlets:(Lorg/jboss/metadata/web/jboss/JBossWebMetaData;)Lorg/jboss/metadata/web/jboss/JBossServletsMetaData;
      14: astore_3
      15: aload_1
      16: invokeinterface #32,  1           // InterfaceMethod org/jboss/wsf/spi/deployment/Deployment.getService:()Lorg/jboss/wsf/spi/deployment/Service;
      21: invokeinterface #45,  1           // InterfaceMethod org/jboss/wsf/spi/deployment/Service.getEndpoints:()Ljava/util/List;
      26: invokeinterface #46,  1           // InterfaceMethod java/util/List.iterator:()Ljava/util/Iterator;
      31: astore        4
      33: aload         4
      35: invokeinterface #47,  1           // InterfaceMethod java/util/Iterator.hasNext:()Z
      40: ifeq          99
      43: aload         4
      45: invokeinterface #48,  1           // InterfaceMethod java/util/Iterator.next:()Ljava/lang/Object;
      50: checkcast     #49                 // class org/jboss/wsf/spi/deployment/Endpoint
      53: astore        5
      55: aload         5
      57: invokeinterface #50,  1           // InterfaceMethod org/jboss/wsf/spi/deployment/Endpoint.getShortName:()Ljava/lang/String;
      62: astore        6
      64: aload         5
      66: invokeinterface #51,  1           // InterfaceMethod org/jboss/wsf/spi/deployment/Endpoint.getTargetBeanName:()Ljava/lang/String;
      71: astore        7
      73: getstatic     #19                 // Field org/jboss/as/webservices/logging/WSLogger.ROOT_LOGGER:Lorg/jboss/as/webservices/logging/WSLogger;
      76: ldc           #52                 // String Servlet name: %s, class: %s
      78: aload         6
      80: aload         7
      82: invokeinterface #53,  4           // InterfaceMethod org/jboss/as/webservices/logging/WSLogger.tracef:(Ljava/lang/String;Ljava/lang/Object;Ljava/lang/Object;)V
      87: aload         6
      89: aload         7
      91: aload_3
      92: invokestatic  #54                 // Method org/jboss/as/webservices/util/WebMetaDataHelper.newServlet:(Ljava/lang/String;Ljava/lang/String;Lorg/jboss/metadata/web/jboss/JBossServletsMetaData;)Lorg/jboss/metadata/web/jboss/JBossServletMetaData;
      95: pop
      96: goto          33
      99: return

  private void createServletMappings(org.jboss.wsf.spi.deployment.Deployment, org.jboss.metadata.web.jboss.JBossWebMetaData);
    Code:
       0: getstatic     #19                 // Field org/jboss/as/webservices/logging/WSLogger.ROOT_LOGGER:Lorg/jboss/as/webservices/logging/WSLogger;
       3: ldc           #55                 // String Creating servlet mappings
       5: invokeinterface #21,  2           // InterfaceMethod org/jboss/as/webservices/logging/WSLogger.trace:(Ljava/lang/Object;)V
      10: aload_2
      11: invokestatic  #56                 // Method org/jboss/as/webservices/util/WebMetaDataHelper.getServletMappings:(Lorg/jboss/metadata/web/jboss/JBossWebMetaData;)Ljava/util/List;
      14: astore_3
      15: aload_1
      16: invokeinterface #32,  1           // InterfaceMethod org/jboss/wsf/spi/deployment/Deployment.getService:()Lorg/jboss/wsf/spi/deployment/Service;
      21: invokeinterface #45,  1           // InterfaceMethod org/jboss/wsf/spi/deployment/Service.getEndpoints:()Ljava/util/List;
      26: invokeinterface #46,  1           // InterfaceMethod java/util/List.iterator:()Ljava/util/Iterator;
      31: astore        4
      33: aload         4
      35: invokeinterface #47,  1           // InterfaceMethod java/util/Iterator.hasNext:()Z
      40: ifeq          113
      43: aload         4
      45: invokeinterface #48,  1           // InterfaceMethod java/util/Iterator.next:()Ljava/lang/Object;
      50: checkcast     #49                 // class org/jboss/wsf/spi/deployment/Endpoint
      53: astore        5
      55: aload         5
      57: instanceof    #57                 // class org/jboss/wsf/spi/deployment/HttpEndpoint
      60: ifeq          110
      63: aload         5
      65: invokeinterface #50,  1           // InterfaceMethod org/jboss/wsf/spi/deployment/Endpoint.getShortName:()Ljava/lang/String;
      70: astore        6
      72: aload         5
      74: checkcast     #57                 // class org/jboss/wsf/spi/deployment/HttpEndpoint
      77: invokeinterface #58,  1           // InterfaceMethod org/jboss/wsf/spi/deployment/HttpEndpoint.getURLPattern:()Ljava/lang/String;
      82: invokestatic  #59                 // Method org/jboss/as/webservices/util/WebMetaDataHelper.getUrlPatterns:(Ljava/lang/String;)Ljava/util/List;
      85: astore        7
      87: getstatic     #19                 // Field org/jboss/as/webservices/logging/WSLogger.ROOT_LOGGER:Lorg/jboss/as/webservices/logging/WSLogger;
      90: ldc           #60                 // String Servlet name: %s, URL patterns: %s
      92: aload         6
      94: aload         7
      96: invokeinterface #53,  4           // InterfaceMethod org/jboss/as/webservices/logging/WSLogger.tracef:(Ljava/lang/String;Ljava/lang/Object;Ljava/lang/Object;)V
     101: aload         6
     103: aload         7
     105: aload_3
     106: invokestatic  #61                 // Method org/jboss/as/webservices/util/WebMetaDataHelper.newServletMapping:(Ljava/lang/String;Ljava/util/List;Ljava/util/List;)Lorg/jboss/metadata/web/spec/ServletMappingMetaData;
     109: pop
     110: goto          33
     113: return

  private void createSecurityConstraints(org.jboss.wsf.spi.deployment.Deployment, org.jboss.metadata.web.jboss.JBossWebMetaData);
    Code:
       0: getstatic     #19                 // Field org/jboss/as/webservices/logging/WSLogger.ROOT_LOGGER:Lorg/jboss/as/webservices/logging/WSLogger;
       3: ldc           #62                 // String Creating security constraints
       5: invokeinterface #21,  2           // InterfaceMethod org/jboss/as/webservices/logging/WSLogger.trace:(Ljava/lang/Object;)V
      10: aload_1
      11: invokeinterface #32,  1           // InterfaceMethod org/jboss/wsf/spi/deployment/Deployment.getService:()Lorg/jboss/wsf/spi/deployment/Service;
      16: invokeinterface #45,  1           // InterfaceMethod org/jboss/wsf/spi/deployment/Service.getEndpoints:()Ljava/util/List;
      21: invokeinterface #46,  1           // InterfaceMethod java/util/List.iterator:()Ljava/util/Iterator;
      26: astore_3
      27: aload_3
      28: invokeinterface #47,  1           // InterfaceMethod java/util/Iterator.hasNext:()Z
      33: ifeq          251
      36: aload_3
      37: invokeinterface #48,  1           // InterfaceMethod java/util/Iterator.next:()Ljava/lang/Object;
      42: checkcast     #49                 // class org/jboss/wsf/spi/deployment/Endpoint
      45: astore        4
      47: aload_0
      48: getfield      #4                  // Field ejb3SecurityAccessor:Lorg/jboss/as/webservices/tomcat/SecurityMetaDataAccessorEJB;
      51: aload         4
      53: invokeinterface #63,  2           // InterfaceMethod org/jboss/as/webservices/tomcat/SecurityMetaDataAccessorEJB.isSecureWsdlAccess:(Lorg/jboss/wsf/spi/deployment/Endpoint;)Z
      58: istore        5
      60: aload_0
      61: getfield      #4                  // Field ejb3SecurityAccessor:Lorg/jboss/as/webservices/tomcat/SecurityMetaDataAccessorEJB;
      64: aload         4
      66: invokeinterface #64,  2           // InterfaceMethod org/jboss/as/webservices/tomcat/SecurityMetaDataAccessorEJB.getTransportGuarantee:(Lorg/jboss/wsf/spi/deployment/Endpoint;)Ljava/lang/String;
      71: astore        6
      73: aload         6
      75: ifnull        82
      78: iconst_1
      79: goto          83
      82: iconst_0
      83: istore        7
      85: aload_0
      86: getfield      #4                  // Field ejb3SecurityAccessor:Lorg/jboss/as/webservices/tomcat/SecurityMetaDataAccessorEJB;
      89: aload         4
      91: invokeinterface #65,  2           // InterfaceMethod org/jboss/as/webservices/tomcat/SecurityMetaDataAccessorEJB.getAuthMethod:(Lorg/jboss/wsf/spi/deployment/Endpoint;)Ljava/lang/String;
      96: astore        8
      98: aload         8
     100: ifnull        107
     103: iconst_1
     104: goto          108
     107: iconst_0
     108: istore        9
     110: aload         4
     112: instanceof    #57                 // class org/jboss/wsf/spi/deployment/HttpEndpoint
     115: ifeq          248
     118: iload         9
     120: ifne          128
     123: iload         7
     125: ifeq          248
     128: aload_2
     129: invokestatic  #66                 // Method org/jboss/as/webservices/util/WebMetaDataHelper.getSecurityConstraints:(Lorg/jboss/metadata/web/jboss/JBossWebMetaData;)Ljava/util/List;
     132: astore        10
     134: aload         10
     136: invokestatic  #67                 // Method org/jboss/as/webservices/util/WebMetaDataHelper.newSecurityConstraint:(Ljava/util/List;)Lorg/jboss/metadata/web/spec/SecurityConstraintMetaData;
     139: astore        11
     141: aload         11
     143: invokestatic  #68                 // Method org/jboss/as/webservices/util/WebMetaDataHelper.getWebResourceCollections:(Lorg/jboss/metadata/web/spec/SecurityConstraintMetaData;)Lorg/jboss/metadata/web/spec/WebResourceCollectionsMetaData;
     146: astore        12
     148: aload         4
     150: invokeinterface #50,  1           // InterfaceMethod org/jboss/wsf/spi/deployment/Endpoint.getShortName:()Ljava/lang/String;
     155: astore        13
     157: aload         4
     159: checkcast     #57                 // class org/jboss/wsf/spi/deployment/HttpEndpoint
     162: invokeinterface #58,  1           // InterfaceMethod org/jboss/wsf/spi/deployment/HttpEndpoint.getURLPattern:()Ljava/lang/String;
     167: astore        14
     169: getstatic     #19                 // Field org/jboss/as/webservices/logging/WSLogger.ROOT_LOGGER:Lorg/jboss/as/webservices/logging/WSLogger;
     172: ldc           #69                 // String Creating web resource collection for endpoint: %s, URL pattern: %s
     174: aload         13
     176: aload         14
     178: invokeinterface #53,  4           // InterfaceMethod org/jboss/as/webservices/logging/WSLogger.tracef:(Ljava/lang/String;Ljava/lang/Object;Ljava/lang/Object;)V
     183: aload         13
     185: aload         14
     187: iload         5
     189: aload         12
     191: invokestatic  #70                 // Method org/jboss/as/webservices/util/WebMetaDataHelper.newWebResourceCollection:(Ljava/lang/String;Ljava/lang/String;ZLorg/jboss/metadata/web/spec/WebResourceCollectionsMetaData;)Lorg/jboss/metadata/web/spec/WebResourceCollectionMetaData;
     194: pop
     195: iload         9
     197: ifeq          221
     200: getstatic     #19                 // Field org/jboss/as/webservices/logging/WSLogger.ROOT_LOGGER:Lorg/jboss/as/webservices/logging/WSLogger;
     203: ldc           #71                 // String Creating auth constraint for endpoint: %s
     205: aload         13
     207: invokeinterface #30,  3           // InterfaceMethod org/jboss/as/webservices/logging/WSLogger.tracef:(Ljava/lang/String;Ljava/lang/Object;)V
     212: invokestatic  #72                 // Method org/jboss/as/webservices/util/WebMetaDataHelper.getAllRoles:()Ljava/util/List;
     215: aload         11
     217: invokestatic  #73                 // Method org/jboss/as/webservices/util/WebMetaDataHelper.newAuthConstraint:(Ljava/util/List;Lorg/jboss/metadata/web/spec/SecurityConstraintMetaData;)Lorg/jboss/metadata/web/spec/AuthConstraintMetaData;
     220: pop
     221: iload         7
     223: ifeq          248
     226: getstatic     #19                 // Field org/jboss/as/webservices/logging/WSLogger.ROOT_LOGGER:Lorg/jboss/as/webservices/logging/WSLogger;
     229: ldc           #74                 // String Creating new user data constraint for endpoint: %s, transport guarantee: %s
     231: aload         13
     233: aload         6
     235: invokeinterface #53,  4           // InterfaceMethod org/jboss/as/webservices/logging/WSLogger.tracef:(Ljava/lang/String;Ljava/lang/Object;Ljava/lang/Object;)V
     240: aload         6
     242: aload         11
     244: invokestatic  #75                 // Method org/jboss/as/webservices/util/WebMetaDataHelper.newUserDataConstraint:(Ljava/lang/String;Lorg/jboss/metadata/web/spec/SecurityConstraintMetaData;)Lorg/jboss/metadata/web/spec/UserDataConstraintMetaData;
     247: pop
     248: goto          27
     251: return

  private void createLoginConfig(org.jboss.wsf.spi.deployment.Deployment, org.jboss.metadata.web.jboss.JBossWebMetaData);
    Code:
       0: aload_0
       1: aload_1
       2: invokespecial #76                 // Method getAuthMethod:(Lorg/jboss/wsf/spi/deployment/Deployment;)Ljava/lang/String;
       5: astore_3
       6: aload_3
       7: ifnull        14
      10: iconst_1
      11: goto          15
      14: iconst_0
      15: istore        4
      17: aload_0
      18: aload_1
      19: invokespecial #77                 // Method getRealmName:(Lorg/jboss/wsf/spi/deployment/Deployment;)Ljava/lang/String;
      22: astore        5
      24: iload         4
      26: ifeq          76
      29: getstatic     #19                 // Field org/jboss/as/webservices/logging/WSLogger.ROOT_LOGGER:Lorg/jboss/as/webservices/logging/WSLogger;
      32: ldc           #78                 // String Creating new login config: %s, auth method: %s
      34: ldc           #80                 // String EJBWebServiceEndpointServlet Realm
      36: aload_3
      37: invokeinterface #53,  4           // InterfaceMethod org/jboss/as/webservices/logging/WSLogger.tracef:(Ljava/lang/String;Ljava/lang/Object;Ljava/lang/Object;)V
      42: aload_2
      43: invokestatic  #81                 // Method org/jboss/as/webservices/util/WebMetaDataHelper.getLoginConfig:(Lorg/jboss/metadata/web/jboss/JBossWebMetaData;)Lorg/jboss/metadata/web/spec/LoginConfigMetaData;
      46: astore        6
      48: aload         5
      50: ifnull        63
      53: aload         6
      55: aload         5
      57: invokevirtual #82                 // Method org/jboss/metadata/web/spec/LoginConfigMetaData.setRealmName:(Ljava/lang/String;)V
      60: goto          70
      63: aload         6
      65: ldc           #80                 // String EJBWebServiceEndpointServlet Realm
      67: invokevirtual #82                 // Method org/jboss/metadata/web/spec/LoginConfigMetaData.setRealmName:(Ljava/lang/String;)V
      70: aload         6
      72: aload_3
      73: invokevirtual #83                 // Method org/jboss/metadata/web/spec/LoginConfigMetaData.setAuthMethod:(Ljava/lang/String;)V
      76: return

  private void createSecurityRoles(org.jboss.wsf.spi.deployment.Deployment, org.jboss.metadata.web.jboss.JBossWebMetaData);
    Code:
       0: aload_0
       1: aload_1
       2: invokespecial #76                 // Method getAuthMethod:(Lorg/jboss/wsf/spi/deployment/Deployment;)Ljava/lang/String;
       5: astore_3
       6: aload_3
       7: ifnull        14
      10: iconst_1
      11: goto          15
      14: iconst_0
      15: istore        4
      17: iload         4
      19: ifeq          75
      22: aload_0
      23: getfield      #4                  // Field ejb3SecurityAccessor:Lorg/jboss/as/webservices/tomcat/SecurityMetaDataAccessorEJB;
      26: aload_1
      27: invokeinterface #84,  2           // InterfaceMethod org/jboss/as/webservices/tomcat/SecurityMetaDataAccessorEJB.getSecurityRoles:(Lorg/jboss/wsf/spi/deployment/Deployment;)Lorg/jboss/metadata/javaee/spec/SecurityRolesMetaData;
      32: astore        5
      34: aload         5
      36: ifnull        51
      39: aload         5
      41: invokevirtual #85                 // Method org/jboss/metadata/javaee/spec/SecurityRolesMetaData.isEmpty:()Z
      44: ifne          51
      47: iconst_1
      48: goto          52
      51: iconst_0
      52: istore        6
      54: iload         6
      56: ifeq          75
      59: getstatic     #19                 // Field org/jboss/as/webservices/logging/WSLogger.ROOT_LOGGER:Lorg/jboss/as/webservices/logging/WSLogger;
      62: ldc           #86                 // String Setting security roles
      64: invokeinterface #21,  2           // InterfaceMethod org/jboss/as/webservices/logging/WSLogger.trace:(Ljava/lang/Object;)V
      69: aload_2
      70: aload         5
      72: invokevirtual #87                 // Method org/jboss/metadata/web/jboss/JBossWebMetaData.setSecurityRoles:(Lorg/jboss/metadata/javaee/spec/SecurityRolesMetaData;)V
      75: aload_1
      76: ldc           #5                  // class org/jboss/as/server/deployment/DeploymentUnit
      78: invokeinterface #88,  2           // InterfaceMethod org/jboss/wsf/spi/deployment/Deployment.getAttachment:(Ljava/lang/Class;)Ljava/lang/Object;
      83: checkcast     #5                  // class org/jboss/as/server/deployment/DeploymentUnit
      86: astore        5
      88: aload         5
      90: invokeinterface #89,  1           // InterfaceMethod org/jboss/as/server/deployment/DeploymentUnit.getParent:()Lorg/jboss/as/server/deployment/DeploymentUnit;
      95: astore        6
      97: aload         6
      99: ifnull        165
     102: aload         6
     104: getstatic     #90                 // Field org/jboss/as/ee/structure/Attachments.EAR_METADATA:Lorg/jboss/as/server/deployment/AttachmentKey;
     107: invokeinterface #91,  2           // InterfaceMethod org/jboss/as/server/deployment/DeploymentUnit.getAttachment:(Lorg/jboss/as/server/deployment/AttachmentKey;)Ljava/lang/Object;
     112: checkcast     #92                 // class org/jboss/metadata/ear/spec/EarMetaData
     115: astore        7
     117: aload         7
     119: ifnull        165
     122: aload_2
     123: invokevirtual #93                 // Method org/jboss/metadata/web/jboss/JBossWebMetaData.getSecurityRoles:()Lorg/jboss/metadata/javaee/spec/SecurityRolesMetaData;
     126: ifnonnull     140
     129: aload_2
     130: new           #94                 // class org/jboss/metadata/javaee/spec/SecurityRolesMetaData
     133: dup
     134: invokespecial #95                 // Method org/jboss/metadata/javaee/spec/SecurityRolesMetaData."<init>":()V
     137: invokevirtual #87                 // Method org/jboss/metadata/web/jboss/JBossWebMetaData.setSecurityRoles:(Lorg/jboss/metadata/javaee/spec/SecurityRolesMetaData;)V
     140: aload         7
     142: invokevirtual #96                 // Method org/jboss/metadata/ear/spec/EarMetaData.getSecurityRoles:()Lorg/jboss/metadata/javaee/spec/SecurityRolesMetaData;
     145: astore        8
     147: aload         8
     149: ifnull        165
     152: aload_2
     153: invokevirtual #93                 // Method org/jboss/metadata/web/jboss/JBossWebMetaData.getSecurityRoles:()Lorg/jboss/metadata/javaee/spec/SecurityRolesMetaData;
     156: aload_2
     157: invokevirtual #93                 // Method org/jboss/metadata/web/jboss/JBossWebMetaData.getSecurityRoles:()Lorg/jboss/metadata/javaee/spec/SecurityRolesMetaData;
     160: aload         8
     162: invokestatic  #97                 // Method org/jboss/metadata/merge/javaee/spec/SecurityRolesMetaDataMerger.merge:(Lorg/jboss/metadata/javaee/spec/SecurityRolesMetaData;Lorg/jboss/metadata/javaee/spec/SecurityRolesMetaData;Lorg/jboss/metadata/javaee/spec/SecurityRolesMetaData;)V
     165: return

  private java.lang.String getAuthMethod(org.jboss.wsf.spi.deployment.Deployment);
    Code:
       0: aload_1
       1: invokeinterface #32,  1           // InterfaceMethod org/jboss/wsf/spi/deployment/Deployment.getService:()Lorg/jboss/wsf/spi/deployment/Service;
       6: invokeinterface #45,  1           // InterfaceMethod org/jboss/wsf/spi/deployment/Service.getEndpoints:()Ljava/util/List;
      11: invokeinterface #46,  1           // InterfaceMethod java/util/List.iterator:()Ljava/util/Iterator;
      16: astore_2
      17: aload_2
      18: invokeinterface #47,  1           // InterfaceMethod java/util/Iterator.hasNext:()Z
      23: ifeq          71
      26: aload_2
      27: invokeinterface #48,  1           // InterfaceMethod java/util/Iterator.next:()Ljava/lang/Object;
      32: checkcast     #49                 // class org/jboss/wsf/spi/deployment/Endpoint
      35: astore_3
      36: aload_0
      37: getfield      #4                  // Field ejb3SecurityAccessor:Lorg/jboss/as/webservices/tomcat/SecurityMetaDataAccessorEJB;
      40: aload_3
      41: invokeinterface #65,  2           // InterfaceMethod org/jboss/as/webservices/tomcat/SecurityMetaDataAccessorEJB.getAuthMethod:(Lorg/jboss/wsf/spi/deployment/Endpoint;)Ljava/lang/String;
      46: astore        4
      48: aload         4
      50: ifnull        57
      53: iconst_1
      54: goto          58
      57: iconst_0
      58: istore        5
      60: iload         5
      62: ifeq          68
      65: aload         4
      67: areturn
      68: goto          17
      71: aconst_null
      72: areturn

  private java.lang.String getRealmName(org.jboss.wsf.spi.deployment.Deployment);
    Code:
       0: aload_1
       1: invokeinterface #32,  1           // InterfaceMethod org/jboss/wsf/spi/deployment/Deployment.getService:()Lorg/jboss/wsf/spi/deployment/Service;
       6: invokeinterface #45,  1           // InterfaceMethod org/jboss/wsf/spi/deployment/Service.getEndpoints:()Ljava/util/List;
      11: invokeinterface #46,  1           // InterfaceMethod java/util/List.iterator:()Ljava/util/Iterator;
      16: astore_2
      17: aload_2
      18: invokeinterface #47,  1           // InterfaceMethod java/util/Iterator.hasNext:()Z
      23: ifeq          71
      26: aload_2
      27: invokeinterface #48,  1           // InterfaceMethod java/util/Iterator.next:()Ljava/lang/Object;
      32: checkcast     #49                 // class org/jboss/wsf/spi/deployment/Endpoint
      35: astore_3
      36: aload_0
      37: getfield      #4                  // Field ejb3SecurityAccessor:Lorg/jboss/as/webservices/tomcat/SecurityMetaDataAccessorEJB;
      40: aload_3
      41: invokeinterface #98,  2           // InterfaceMethod org/jboss/as/webservices/tomcat/SecurityMetaDataAccessorEJB.getRealmName:(Lorg/jboss/wsf/spi/deployment/Endpoint;)Ljava/lang/String;
      46: astore        4
      48: aload         4
      50: ifnull        57
      53: iconst_1
      54: goto          58
      57: iconst_0
      58: istore        5
      60: iload         5
      62: ifeq          68
      65: aload         4
      67: areturn
      68: goto          17
      71: aconst_null
      72: areturn
}
