Compiled from "NoIndentWriter.java"
public class org.stringtemplate.v4.NoIndentWriter extends org.stringtemplate.v4.AutoIndentWriter {
  public org.stringtemplate.v4.NoIndentWriter(java.io.Writer);
    Code:
       0: aload_0
       1: aload_1
       2: invokespecial #1                  // Method org/stringtemplate/v4/AutoIndentWriter."<init>":(Ljava/io/Writer;)V
       5: return

  public int write(java.lang.String) throws java.io.IOException;
    Code:
       0: aload_0
       1: getfield      #2                  // Field out:Ljava/io/Writer;
       4: aload_1
       5: invokevirtual #3                  // Method java/io/Writer.write:(Ljava/lang/String;)V
       8: aload_1
       9: invokevirtual #4                  // Method java/lang/String.length:()I
      12: ireturn
}
