Compiled from "STGroupDir.java"
public class org.stringtemplate.v4.STGroupDir extends org.stringtemplate.v4.STGroup {
  public java.lang.String groupDirName;

  public java.net.URL root;

  public org.stringtemplate.v4.STGroupDir(java.lang.String);
    Code:
       0: aload_0
       1: aload_1
       2: bipush        60
       4: bipush        62
       6: invokespecial #1                  // Method "<init>":(Ljava/lang/String;CC)V
       9: return

  public org.stringtemplate.v4.STGroupDir(java.lang.String, char, char);
    Code:
       0: aload_0
       1: iload_2
       2: iload_3
       3: invokespecial #2                  // Method org/stringtemplate/v4/STGroup."<init>":(CC)V
       6: aload_0
       7: aload_1
       8: putfield      #3                  // Field groupDirName:Ljava/lang/String;
      11: new           #4                  // class java/io/File
      14: dup
      15: aload_1
      16: invokespecial #5                  // Method java/io/File."<init>":(Ljava/lang/String;)V
      19: astore        4
      21: aload         4
      23: invokevirtual #6                  // Method java/io/File.exists:()Z
      26: ifeq          129
      29: aload         4
      31: invokevirtual #7                  // Method java/io/File.isDirectory:()Z
      34: ifeq          129
      37: aload_0
      38: aload         4
      40: invokevirtual #8                  // Method java/io/File.toURI:()Ljava/net/URI;
      43: invokevirtual #9                  // Method java/net/URI.toURL:()Ljava/net/URL;
      46: putfield      #10                 // Field root:Ljava/net/URL;
      49: goto          83
      52: astore        5
      54: new           #12                 // class org/stringtemplate/v4/compiler/STException
      57: dup
      58: new           #13                 // class java/lang/StringBuilder
      61: dup
      62: invokespecial #14                 // Method java/lang/StringBuilder."<init>":()V
      65: ldc           #15                 // String can\'t load dir
      67: invokevirtual #16                 // Method java/lang/StringBuilder.append:(Ljava/lang/String;)Ljava/lang/StringBuilder;
      70: aload_1
      71: invokevirtual #16                 // Method java/lang/StringBuilder.append:(Ljava/lang/String;)Ljava/lang/StringBuilder;
      74: invokevirtual #17                 // Method java/lang/StringBuilder.toString:()Ljava/lang/String;
      77: aload         5
      79: invokespecial #18                 // Method org/stringtemplate/v4/compiler/STException."<init>":(Ljava/lang/String;Ljava/lang/Exception;)V
      82: athrow
      83: getstatic     #19                 // Field verbose:Z
      86: ifeq          250
      89: getstatic     #20                 // Field java/lang/System.out:Ljava/io/PrintStream;
      92: new           #13                 // class java/lang/StringBuilder
      95: dup
      96: invokespecial #14                 // Method java/lang/StringBuilder."<init>":()V
      99: ldc           #21                 // String STGroupDir(
     101: invokevirtual #16                 // Method java/lang/StringBuilder.append:(Ljava/lang/String;)Ljava/lang/StringBuilder;
     104: aload_1
     105: invokevirtual #16                 // Method java/lang/StringBuilder.append:(Ljava/lang/String;)Ljava/lang/StringBuilder;
     108: ldc           #22                 // String ) found at
     110: invokevirtual #16                 // Method java/lang/StringBuilder.append:(Ljava/lang/String;)Ljava/lang/StringBuilder;
     113: aload_0
     114: getfield      #10                 // Field root:Ljava/net/URL;
     117: invokevirtual #23                 // Method java/lang/StringBuilder.append:(Ljava/lang/Object;)Ljava/lang/StringBuilder;
     120: invokevirtual #17                 // Method java/lang/StringBuilder.toString:()Ljava/lang/String;
     123: invokevirtual #24                 // Method java/io/PrintStream.println:(Ljava/lang/String;)V
     126: goto          250
     129: invokestatic  #25                 // Method java/lang/Thread.currentThread:()Ljava/lang/Thread;
     132: invokevirtual #26                 // Method java/lang/Thread.getContextClassLoader:()Ljava/lang/ClassLoader;
     135: astore        5
     137: aload_0
     138: aload         5
     140: aload_1
     141: invokevirtual #27                 // Method java/lang/ClassLoader.getResource:(Ljava/lang/String;)Ljava/net/URL;
     144: putfield      #10                 // Field root:Ljava/net/URL;
     147: aload_0
     148: getfield      #10                 // Field root:Ljava/net/URL;
     151: ifnonnull     173
     154: aload_0
     155: invokevirtual #28                 // Method java/lang/Object.getClass:()Ljava/lang/Class;
     158: invokevirtual #29                 // Method java/lang/Class.getClassLoader:()Ljava/lang/ClassLoader;
     161: astore        5
     163: aload_0
     164: aload         5
     166: aload_1
     167: invokevirtual #27                 // Method java/lang/ClassLoader.getResource:(Ljava/lang/String;)Ljava/net/URL;
     170: putfield      #10                 // Field root:Ljava/net/URL;
     173: getstatic     #19                 // Field verbose:Z
     176: ifeq          216
     179: getstatic     #20                 // Field java/lang/System.out:Ljava/io/PrintStream;
     182: new           #13                 // class java/lang/StringBuilder
     185: dup
     186: invokespecial #14                 // Method java/lang/StringBuilder."<init>":()V
     189: ldc           #21                 // String STGroupDir(
     191: invokevirtual #16                 // Method java/lang/StringBuilder.append:(Ljava/lang/String;)Ljava/lang/StringBuilder;
     194: aload_1
     195: invokevirtual #16                 // Method java/lang/StringBuilder.append:(Ljava/lang/String;)Ljava/lang/StringBuilder;
     198: ldc           #30                 // String ) found via CLASSPATH at
     200: invokevirtual #16                 // Method java/lang/StringBuilder.append:(Ljava/lang/String;)Ljava/lang/StringBuilder;
     203: aload_0
     204: getfield      #10                 // Field root:Ljava/net/URL;
     207: invokevirtual #23                 // Method java/lang/StringBuilder.append:(Ljava/lang/Object;)Ljava/lang/StringBuilder;
     210: invokevirtual #17                 // Method java/lang/StringBuilder.toString:()Ljava/lang/String;
     213: invokevirtual #24                 // Method java/io/PrintStream.println:(Ljava/lang/String;)V
     216: aload_0
     217: getfield      #10                 // Field root:Ljava/net/URL;
     220: ifnonnull     250
     223: new           #31                 // class java/lang/IllegalArgumentException
     226: dup
     227: new           #13                 // class java/lang/StringBuilder
     230: dup
     231: invokespecial #14                 // Method java/lang/StringBuilder."<init>":()V
     234: ldc           #32                 // String No such directory:
     236: invokevirtual #16                 // Method java/lang/StringBuilder.append:(Ljava/lang/String;)Ljava/lang/StringBuilder;
     239: aload_1
     240: invokevirtual #16                 // Method java/lang/StringBuilder.append:(Ljava/lang/String;)Ljava/lang/StringBuilder;
     243: invokevirtual #17                 // Method java/lang/StringBuilder.toString:()Ljava/lang/String;
     246: invokespecial #33                 // Method java/lang/IllegalArgumentException."<init>":(Ljava/lang/String;)V
     249: athrow
     250: return
    Exception table:
       from    to  target type
          37    49    52   Class java/net/MalformedURLException

  public org.stringtemplate.v4.STGroupDir(java.lang.String, java.lang.String);
    Code:
       0: aload_0
       1: aload_1
       2: aload_2
       3: bipush        60
       5: bipush        62
       7: invokespecial #34                 // Method "<init>":(Ljava/lang/String;Ljava/lang/String;CC)V
      10: return

  public org.stringtemplate.v4.STGroupDir(java.lang.String, java.lang.String, char, char);
    Code:
       0: aload_0
       1: aload_1
       2: iload_3
       3: iload         4
       5: invokespecial #1                  // Method "<init>":(Ljava/lang/String;CC)V
       8: aload_0
       9: aload_2
      10: putfield      #35                 // Field encoding:Ljava/lang/String;
      13: return

  public org.stringtemplate.v4.STGroupDir(java.net.URL, java.lang.String, char, char);
    Code:
       0: aload_0
       1: iload_3
       2: iload         4
       4: invokespecial #2                  // Method org/stringtemplate/v4/STGroup."<init>":(CC)V
       7: aload_0
       8: new           #4                  // class java/io/File
      11: dup
      12: aload_1
      13: invokevirtual #36                 // Method java/net/URL.getFile:()Ljava/lang/String;
      16: invokespecial #5                  // Method java/io/File."<init>":(Ljava/lang/String;)V
      19: invokevirtual #37                 // Method java/io/File.getName:()Ljava/lang/String;
      22: putfield      #3                  // Field groupDirName:Ljava/lang/String;
      25: aload_0
      26: aload_1
      27: putfield      #10                 // Field root:Ljava/net/URL;
      30: aload_0
      31: aload_2
      32: putfield      #35                 // Field encoding:Ljava/lang/String;
      35: return

  public void importTemplates(org.antlr.runtime.Token);
    Code:
       0: new           #13                 // class java/lang/StringBuilder
       3: dup
       4: invokespecial #14                 // Method java/lang/StringBuilder."<init>":()V
       7: ldc           #38                 // String import illegal in group files embedded in STGroupDirs; import
       9: invokevirtual #16                 // Method java/lang/StringBuilder.append:(Ljava/lang/String;)Ljava/lang/StringBuilder;
      12: aload_1
      13: invokeinterface #39,  1           // InterfaceMethod org/antlr/runtime/Token.getText:()Ljava/lang/String;
      18: invokevirtual #16                 // Method java/lang/StringBuilder.append:(Ljava/lang/String;)Ljava/lang/StringBuilder;
      21: ldc           #40                 // String  in STGroupDir
      23: invokevirtual #16                 // Method java/lang/StringBuilder.append:(Ljava/lang/String;)Ljava/lang/StringBuilder;
      26: aload_0
      27: invokevirtual #41                 // Method getName:()Ljava/lang/String;
      30: invokevirtual #16                 // Method java/lang/StringBuilder.append:(Ljava/lang/String;)Ljava/lang/StringBuilder;
      33: invokevirtual #17                 // Method java/lang/StringBuilder.toString:()Ljava/lang/String;
      36: astore_2
      37: new           #42                 // class java/lang/UnsupportedOperationException
      40: dup
      41: aload_2
      42: invokespecial #43                 // Method java/lang/UnsupportedOperationException."<init>":(Ljava/lang/String;)V
      45: athrow

  protected org.stringtemplate.v4.compiler.CompiledST load(java.lang.String);
    Code:
       0: getstatic     #19                 // Field verbose:Z
       3: ifeq          36
       6: getstatic     #20                 // Field java/lang/System.out:Ljava/io/PrintStream;
       9: new           #13                 // class java/lang/StringBuilder
      12: dup
      13: invokespecial #14                 // Method java/lang/StringBuilder."<init>":()V
      16: ldc           #44                 // String STGroupDir.load(
      18: invokevirtual #16                 // Method java/lang/StringBuilder.append:(Ljava/lang/String;)Ljava/lang/StringBuilder;
      21: aload_1
      22: invokevirtual #16                 // Method java/lang/StringBuilder.append:(Ljava/lang/String;)Ljava/lang/StringBuilder;
      25: ldc           #45                 // String )
      27: invokevirtual #16                 // Method java/lang/StringBuilder.append:(Ljava/lang/String;)Ljava/lang/StringBuilder;
      30: invokevirtual #17                 // Method java/lang/StringBuilder.toString:()Ljava/lang/String;
      33: invokevirtual #24                 // Method java/io/PrintStream.println:(Ljava/lang/String;)V
      36: aload_1
      37: invokestatic  #46                 // Method org/stringtemplate/v4/misc/Misc.getParent:(Ljava/lang/String;)Ljava/lang/String;
      40: astore_2
      41: aload_1
      42: invokestatic  #47                 // Method org/stringtemplate/v4/misc/Misc.getPrefix:(Ljava/lang/String;)Ljava/lang/String;
      45: astore_3
      46: new           #48                 // class java/net/URL
      49: dup
      50: new           #13                 // class java/lang/StringBuilder
      53: dup
      54: invokespecial #14                 // Method java/lang/StringBuilder."<init>":()V
      57: aload_0
      58: getfield      #10                 // Field root:Ljava/net/URL;
      61: invokevirtual #23                 // Method java/lang/StringBuilder.append:(Ljava/lang/Object;)Ljava/lang/StringBuilder;
      64: aload_2
      65: invokevirtual #16                 // Method java/lang/StringBuilder.append:(Ljava/lang/String;)Ljava/lang/StringBuilder;
      68: getstatic     #49                 // Field GROUP_FILE_EXTENSION:Ljava/lang/String;
      71: invokevirtual #16                 // Method java/lang/StringBuilder.append:(Ljava/lang/String;)Ljava/lang/StringBuilder;
      74: invokevirtual #17                 // Method java/lang/StringBuilder.toString:()Ljava/lang/String;
      77: invokespecial #50                 // Method java/net/URL."<init>":(Ljava/lang/String;)V
      80: astore        4
      82: goto          131
      85: astore        5
      87: aload_0
      88: getfield      #51                 // Field errMgr:Lorg/stringtemplate/v4/misc/ErrorManager;
      91: aconst_null
      92: new           #13                 // class java/lang/StringBuilder
      95: dup
      96: invokespecial #14                 // Method java/lang/StringBuilder."<init>":()V
      99: ldc           #52                 // String bad URL:
     101: invokevirtual #16                 // Method java/lang/StringBuilder.append:(Ljava/lang/String;)Ljava/lang/StringBuilder;
     104: aload_0
     105: getfield      #10                 // Field root:Ljava/net/URL;
     108: invokevirtual #23                 // Method java/lang/StringBuilder.append:(Ljava/lang/Object;)Ljava/lang/StringBuilder;
     111: aload_2
     112: invokevirtual #16                 // Method java/lang/StringBuilder.append:(Ljava/lang/String;)Ljava/lang/StringBuilder;
     115: getstatic     #49                 // Field GROUP_FILE_EXTENSION:Ljava/lang/String;
     118: invokevirtual #16                 // Method java/lang/StringBuilder.append:(Ljava/lang/String;)Ljava/lang/StringBuilder;
     121: invokevirtual #17                 // Method java/lang/StringBuilder.toString:()Ljava/lang/String;
     124: aload         5
     126: invokevirtual #53                 // Method org/stringtemplate/v4/misc/ErrorManager.internalError:(Lorg/stringtemplate/v4/ST;Ljava/lang/String;Ljava/lang/Throwable;)V
     129: aconst_null
     130: areturn
     131: aconst_null
     132: astore        5
     134: aload         4
     136: invokevirtual #54                 // Method java/net/URL.openStream:()Ljava/io/InputStream;
     139: astore        5
     141: aload         5
     143: ifnull        151
     146: aload         5
     148: invokevirtual #55                 // Method java/io/InputStream.close:()V
     151: goto          320
     154: astore        6
     156: aload_0
     157: getfield      #51                 // Field errMgr:Lorg/stringtemplate/v4/misc/ErrorManager;
     160: aconst_null
     161: new           #13                 // class java/lang/StringBuilder
     164: dup
     165: invokespecial #14                 // Method java/lang/StringBuilder."<init>":()V
     168: ldc           #57                 // String can\'t close template file stream
     170: invokevirtual #16                 // Method java/lang/StringBuilder.append:(Ljava/lang/String;)Ljava/lang/StringBuilder;
     173: aload_1
     174: invokevirtual #16                 // Method java/lang/StringBuilder.append:(Ljava/lang/String;)Ljava/lang/StringBuilder;
     177: invokevirtual #17                 // Method java/lang/StringBuilder.toString:()Ljava/lang/String;
     180: aload         6
     182: invokevirtual #53                 // Method org/stringtemplate/v4/misc/ErrorManager.internalError:(Lorg/stringtemplate/v4/ST;Ljava/lang/String;Ljava/lang/Throwable;)V
     185: goto          320
     188: astore        6
     190: aload_1
     191: invokestatic  #58                 // Method org/stringtemplate/v4/misc/Misc.getFileName:(Ljava/lang/String;)Ljava/lang/String;
     194: astore        7
     196: aload_0
     197: aload_3
     198: new           #13                 // class java/lang/StringBuilder
     201: dup
     202: invokespecial #14                 // Method java/lang/StringBuilder."<init>":()V
     205: aload         7
     207: invokevirtual #16                 // Method java/lang/StringBuilder.append:(Ljava/lang/String;)Ljava/lang/StringBuilder;
     210: getstatic     #59                 // Field TEMPLATE_FILE_EXTENSION:Ljava/lang/String;
     213: invokevirtual #16                 // Method java/lang/StringBuilder.append:(Ljava/lang/String;)Ljava/lang/StringBuilder;
     216: invokevirtual #17                 // Method java/lang/StringBuilder.toString:()Ljava/lang/String;
     219: invokevirtual #60                 // Method loadTemplateFile:(Ljava/lang/String;Ljava/lang/String;)Lorg/stringtemplate/v4/compiler/CompiledST;
     222: astore        8
     224: aload         5
     226: ifnull        234
     229: aload         5
     231: invokevirtual #55                 // Method java/io/InputStream.close:()V
     234: goto          268
     237: astore        9
     239: aload_0
     240: getfield      #51                 // Field errMgr:Lorg/stringtemplate/v4/misc/ErrorManager;
     243: aconst_null
     244: new           #13                 // class java/lang/StringBuilder
     247: dup
     248: invokespecial #14                 // Method java/lang/StringBuilder."<init>":()V
     251: ldc           #57                 // String can\'t close template file stream
     253: invokevirtual #16                 // Method java/lang/StringBuilder.append:(Ljava/lang/String;)Ljava/lang/StringBuilder;
     256: aload_1
     257: invokevirtual #16                 // Method java/lang/StringBuilder.append:(Ljava/lang/String;)Ljava/lang/StringBuilder;
     260: invokevirtual #17                 // Method java/lang/StringBuilder.toString:()Ljava/lang/String;
     263: aload         9
     265: invokevirtual #53                 // Method org/stringtemplate/v4/misc/ErrorManager.internalError:(Lorg/stringtemplate/v4/ST;Ljava/lang/String;Ljava/lang/Throwable;)V
     268: aload         8
     270: areturn
     271: astore        10
     273: aload         5
     275: ifnull        283
     278: aload         5
     280: invokevirtual #55                 // Method java/io/InputStream.close:()V
     283: goto          317
     286: astore        11
     288: aload_0
     289: getfield      #51                 // Field errMgr:Lorg/stringtemplate/v4/misc/ErrorManager;
     292: aconst_null
     293: new           #13                 // class java/lang/StringBuilder
     296: dup
     297: invokespecial #14                 // Method java/lang/StringBuilder."<init>":()V
     300: ldc           #57                 // String can\'t close template file stream
     302: invokevirtual #16                 // Method java/lang/StringBuilder.append:(Ljava/lang/String;)Ljava/lang/StringBuilder;
     305: aload_1
     306: invokevirtual #16                 // Method java/lang/StringBuilder.append:(Ljava/lang/String;)Ljava/lang/StringBuilder;
     309: invokevirtual #17                 // Method java/lang/StringBuilder.toString:()Ljava/lang/String;
     312: aload         11
     314: invokevirtual #53                 // Method org/stringtemplate/v4/misc/ErrorManager.internalError:(Lorg/stringtemplate/v4/ST;Ljava/lang/String;Ljava/lang/Throwable;)V
     317: aload         10
     319: athrow
     320: aload_0
     321: aload_3
     322: new           #13                 // class java/lang/StringBuilder
     325: dup
     326: invokespecial #14                 // Method java/lang/StringBuilder."<init>":()V
     329: aload_0
     330: getfield      #10                 // Field root:Ljava/net/URL;
     333: invokevirtual #23                 // Method java/lang/StringBuilder.append:(Ljava/lang/Object;)Ljava/lang/StringBuilder;
     336: aload_2
     337: invokevirtual #16                 // Method java/lang/StringBuilder.append:(Ljava/lang/String;)Ljava/lang/StringBuilder;
     340: getstatic     #49                 // Field GROUP_FILE_EXTENSION:Ljava/lang/String;
     343: invokevirtual #16                 // Method java/lang/StringBuilder.append:(Ljava/lang/String;)Ljava/lang/StringBuilder;
     346: invokevirtual #17                 // Method java/lang/StringBuilder.toString:()Ljava/lang/String;
     349: invokevirtual #61                 // Method loadGroupFile:(Ljava/lang/String;Ljava/lang/String;)V
     352: aload_0
     353: aload_1
     354: invokevirtual #62                 // Method rawGetTemplate:(Ljava/lang/String;)Lorg/stringtemplate/v4/compiler/CompiledST;
     357: areturn
    Exception table:
       from    to  target type
          46    82    85   Class java/net/MalformedURLException
         141   151   154   Class java/io/IOException
         134   141   188   Class java/io/IOException
         224   234   237   Class java/io/IOException
         134   141   271   any
         188   224   271   any
         273   283   286   Class java/io/IOException
         271   273   271   any

  public org.stringtemplate.v4.compiler.CompiledST loadTemplateFile(java.lang.String, java.lang.String);
    Code:
       0: getstatic     #19                 // Field verbose:Z
       3: ifeq          52
       6: getstatic     #20                 // Field java/lang/System.out:Ljava/io/PrintStream;
       9: new           #13                 // class java/lang/StringBuilder
      12: dup
      13: invokespecial #14                 // Method java/lang/StringBuilder."<init>":()V
      16: ldc           #63                 // String loadTemplateFile(
      18: invokevirtual #16                 // Method java/lang/StringBuilder.append:(Ljava/lang/String;)Ljava/lang/StringBuilder;
      21: aload_2
      22: invokevirtual #16                 // Method java/lang/StringBuilder.append:(Ljava/lang/String;)Ljava/lang/StringBuilder;
      25: ldc           #64                 // String ) in groupdir from
      27: invokevirtual #16                 // Method java/lang/StringBuilder.append:(Ljava/lang/String;)Ljava/lang/StringBuilder;
      30: aload_0
      31: getfield      #10                 // Field root:Ljava/net/URL;
      34: invokevirtual #23                 // Method java/lang/StringBuilder.append:(Ljava/lang/Object;)Ljava/lang/StringBuilder;
      37: ldc           #65                 // String  prefix=
      39: invokevirtual #16                 // Method java/lang/StringBuilder.append:(Ljava/lang/String;)Ljava/lang/StringBuilder;
      42: aload_1
      43: invokevirtual #16                 // Method java/lang/StringBuilder.append:(Ljava/lang/String;)Ljava/lang/StringBuilder;
      46: invokevirtual #17                 // Method java/lang/StringBuilder.toString:()Ljava/lang/String;
      49: invokevirtual #24                 // Method java/io/PrintStream.println:(Ljava/lang/String;)V
      52: new           #48                 // class java/net/URL
      55: dup
      56: new           #13                 // class java/lang/StringBuilder
      59: dup
      60: invokespecial #14                 // Method java/lang/StringBuilder."<init>":()V
      63: aload_0
      64: getfield      #10                 // Field root:Ljava/net/URL;
      67: invokevirtual #23                 // Method java/lang/StringBuilder.append:(Ljava/lang/Object;)Ljava/lang/StringBuilder;
      70: aload_1
      71: invokevirtual #16                 // Method java/lang/StringBuilder.append:(Ljava/lang/String;)Ljava/lang/StringBuilder;
      74: aload_2
      75: invokevirtual #16                 // Method java/lang/StringBuilder.append:(Ljava/lang/String;)Ljava/lang/StringBuilder;
      78: invokevirtual #17                 // Method java/lang/StringBuilder.toString:()Ljava/lang/String;
      81: invokespecial #50                 // Method java/net/URL."<init>":(Ljava/lang/String;)V
      84: astore_3
      85: goto          127
      88: astore        4
      90: aload_0
      91: getfield      #51                 // Field errMgr:Lorg/stringtemplate/v4/misc/ErrorManager;
      94: aconst_null
      95: aconst_null
      96: getstatic     #66                 // Field org/stringtemplate/v4/misc/ErrorType.INVALID_TEMPLATE_NAME:Lorg/stringtemplate/v4/misc/ErrorType;
      99: aload         4
     101: new           #13                 // class java/lang/StringBuilder
     104: dup
     105: invokespecial #14                 // Method java/lang/StringBuilder."<init>":()V
     108: aload_0
     109: getfield      #10                 // Field root:Ljava/net/URL;
     112: invokevirtual #23                 // Method java/lang/StringBuilder.append:(Ljava/lang/Object;)Ljava/lang/StringBuilder;
     115: aload_2
     116: invokevirtual #16                 // Method java/lang/StringBuilder.append:(Ljava/lang/String;)Ljava/lang/StringBuilder;
     119: invokevirtual #17                 // Method java/lang/StringBuilder.toString:()Ljava/lang/String;
     122: invokevirtual #67                 // Method org/stringtemplate/v4/misc/ErrorManager.runTimeError:(Lorg/stringtemplate/v4/Interpreter;Lorg/stringtemplate/v4/InstanceScope;Lorg/stringtemplate/v4/misc/ErrorType;Ljava/lang/Throwable;Ljava/lang/Object;)V
     125: aconst_null
     126: areturn
     127: new           #68                 // class org/antlr/runtime/ANTLRInputStream
     130: dup
     131: aload_3
     132: invokevirtual #54                 // Method java/net/URL.openStream:()Ljava/io/InputStream;
     135: aload_0
     136: getfield      #35                 // Field encoding:Ljava/lang/String;
     139: invokespecial #69                 // Method org/antlr/runtime/ANTLRInputStream."<init>":(Ljava/io/InputStream;Ljava/lang/String;)V
     142: astore        4
     144: aload         4
     146: aload_2
     147: putfield      #70                 // Field org/antlr/runtime/ANTLRInputStream.name:Ljava/lang/String;
     150: goto          200
     153: astore        5
     155: getstatic     #19                 // Field verbose:Z
     158: ifeq          198
     161: getstatic     #20                 // Field java/lang/System.out:Ljava/io/PrintStream;
     164: new           #13                 // class java/lang/StringBuilder
     167: dup
     168: invokespecial #14                 // Method java/lang/StringBuilder."<init>":()V
     171: aload_0
     172: getfield      #10                 // Field root:Ljava/net/URL;
     175: invokevirtual #23                 // Method java/lang/StringBuilder.append:(Ljava/lang/Object;)Ljava/lang/StringBuilder;
     178: ldc           #71                 // String /
     180: invokevirtual #16                 // Method java/lang/StringBuilder.append:(Ljava/lang/String;)Ljava/lang/StringBuilder;
     183: aload_2
     184: invokevirtual #16                 // Method java/lang/StringBuilder.append:(Ljava/lang/String;)Ljava/lang/StringBuilder;
     187: ldc           #72                 // String  doesn\'t exist
     189: invokevirtual #16                 // Method java/lang/StringBuilder.append:(Ljava/lang/String;)Ljava/lang/StringBuilder;
     192: invokevirtual #17                 // Method java/lang/StringBuilder.toString:()Ljava/lang/String;
     195: invokevirtual #24                 // Method java/io/PrintStream.println:(Ljava/lang/String;)V
     198: aconst_null
     199: areturn
     200: aload_0
     201: aload_1
     202: aload_2
     203: aload         4
     205: invokevirtual #73                 // Method loadTemplateFile:(Ljava/lang/String;Ljava/lang/String;Lorg/antlr/runtime/CharStream;)Lorg/stringtemplate/v4/compiler/CompiledST;
     208: areturn
    Exception table:
       from    to  target type
          52    85    88   Class java/net/MalformedURLException
         127   150   153   Class java/io/IOException

  public java.lang.String getName();
    Code:
       0: aload_0
       1: getfield      #3                  // Field groupDirName:Ljava/lang/String;
       4: areturn

  public java.lang.String getFileName();
    Code:
       0: aload_0
       1: getfield      #10                 // Field root:Ljava/net/URL;
       4: invokevirtual #36                 // Method java/net/URL.getFile:()Ljava/lang/String;
       7: areturn

  public java.net.URL getRootDirURL();
    Code:
       0: aload_0
       1: getfield      #10                 // Field root:Ljava/net/URL;
       4: areturn
}
