Compiled from "ControlFlag.java"
public class org.jboss.security.config.ControlFlag {
  private java.lang.String flag;

  public static final org.jboss.security.config.ControlFlag REQUIRED;

  public static final org.jboss.security.config.ControlFlag REQUISITE;

  public static final org.jboss.security.config.ControlFlag SUFFICIENT;

  public static final org.jboss.security.config.ControlFlag OPTIONAL;

  public org.jboss.security.config.ControlFlag(java.lang.String);
    Code:
       0: aload_0
       1: invokespecial #1                  // Method java/lang/Object."<init>":()V
       4: aload_0
       5: aload_1
       6: putfield      #2                  // Field flag:Ljava/lang/String;
       9: return

  public java.lang.String toString();
    Code:
       0: aload_0
       1: getfield      #2                  // Field flag:Ljava/lang/String;
       4: areturn

  public boolean equals(java.lang.Object);
    Code:
       0: aload_1
       1: instanceof    #3                  // class org/jboss/security/config/ControlFlag
       4: ifne          9
       7: iconst_0
       8: ireturn
       9: aload_1
      10: checkcast     #3                  // class org/jboss/security/config/ControlFlag
      13: astore_2
      14: aload_0
      15: getfield      #2                  // Field flag:Ljava/lang/String;
      18: aload_2
      19: getfield      #2                  // Field flag:Ljava/lang/String;
      22: invokevirtual #4                  // Method java/lang/String.equals:(Ljava/lang/Object;)Z
      25: ireturn

  public int hashCode();
    Code:
       0: aload_0
       1: getfield      #2                  // Field flag:Ljava/lang/String;
       4: invokevirtual #5                  // Method java/lang/String.hashCode:()I
       7: ireturn

  public static org.jboss.security.config.ControlFlag valueOf(java.lang.String);
    Code:
       0: ldc           #6                  // String REQUIRED
       2: aload_0
       3: invokevirtual #7                  // Method java/lang/String.equalsIgnoreCase:(Ljava/lang/String;)Z
       6: ifeq          13
       9: getstatic     #8                  // Field REQUIRED:Lorg/jboss/security/config/ControlFlag;
      12: areturn
      13: ldc           #9                  // String REQUISITE
      15: aload_0
      16: invokevirtual #7                  // Method java/lang/String.equalsIgnoreCase:(Ljava/lang/String;)Z
      19: ifeq          26
      22: getstatic     #10                 // Field REQUISITE:Lorg/jboss/security/config/ControlFlag;
      25: areturn
      26: ldc           #11                 // String SUFFICIENT
      28: aload_0
      29: invokevirtual #7                  // Method java/lang/String.equalsIgnoreCase:(Ljava/lang/String;)Z
      32: ifeq          39
      35: getstatic     #12                 // Field SUFFICIENT:Lorg/jboss/security/config/ControlFlag;
      38: areturn
      39: ldc           #13                 // String OPTIONAL
      41: aload_0
      42: invokevirtual #7                  // Method java/lang/String.equalsIgnoreCase:(Ljava/lang/String;)Z
      45: ifeq          52
      48: getstatic     #14                 // Field OPTIONAL:Lorg/jboss/security/config/ControlFlag;
      51: areturn
      52: getstatic     #15                 // Field org/jboss/security/PicketBoxMessages.MESSAGES:Lorg/jboss/security/PicketBoxMessages;
      55: aload_0
      56: invokeinterface #16,  2           // InterfaceMethod org/jboss/security/PicketBoxMessages.invalidControlFlag:(Ljava/lang/String;)Ljava/lang/IllegalArgumentException;
      61: athrow

  static {};
    Code:
       0: new           #3                  // class org/jboss/security/config/ControlFlag
       3: dup
       4: ldc           #6                  // String REQUIRED
       6: invokespecial #17                 // Method "<init>":(Ljava/lang/String;)V
       9: putstatic     #8                  // Field REQUIRED:Lorg/jboss/security/config/ControlFlag;
      12: new           #3                  // class org/jboss/security/config/ControlFlag
      15: dup
      16: ldc           #9                  // String REQUISITE
      18: invokespecial #17                 // Method "<init>":(Ljava/lang/String;)V
      21: putstatic     #10                 // Field REQUISITE:Lorg/jboss/security/config/ControlFlag;
      24: new           #3                  // class org/jboss/security/config/ControlFlag
      27: dup
      28: ldc           #11                 // String SUFFICIENT
      30: invokespecial #17                 // Method "<init>":(Ljava/lang/String;)V
      33: putstatic     #12                 // Field SUFFICIENT:Lorg/jboss/security/config/ControlFlag;
      36: new           #3                  // class org/jboss/security/config/ControlFlag
      39: dup
      40: ldc           #13                 // String OPTIONAL
      42: invokespecial #17                 // Method "<init>":(Ljava/lang/String;)V
      45: putstatic     #14                 // Field OPTIONAL:Lorg/jboss/security/config/ControlFlag;
      48: return
}
