Compiled from "SecretKeyData.java"
public class org.adorsys.jkeygen.keystore.SecretKeyData extends org.adorsys.jkeygen.keystore.KeyEntryData implements org.adorsys.jkeygen.keystore.SecretKeyEntry {
  private final javax.crypto.SecretKey secretKey;

  private final java.lang.String keyAlgo;

  private org.adorsys.jkeygen.keystore.SecretKeyData(javax.security.auth.callback.CallbackHandler, java.lang.String, javax.crypto.SecretKey, java.lang.String);
    Code:
       0: aload_0
       1: aload_1
       2: aload_2
       3: invokespecial #2                  // Method org/adorsys/jkeygen/keystore/KeyEntryData."<init>":(Ljavax/security/auth/callback/CallbackHandler;Ljava/lang/String;)V
       6: aload_0
       7: aload_3
       8: putfield      #3                  // Field secretKey:Ljavax/crypto/SecretKey;
      11: aload_0
      12: aload         4
      14: putfield      #4                  // Field keyAlgo:Ljava/lang/String;
      17: return

  public static org.adorsys.jkeygen.keystore.SecretKeyData$SecretKeyDataBuilder builder();
    Code:
       0: new           #5                  // class org/adorsys/jkeygen/keystore/SecretKeyData$SecretKeyDataBuilder
       3: dup
       4: invokespecial #6                  // Method org/adorsys/jkeygen/keystore/SecretKeyData$SecretKeyDataBuilder."<init>":()V
       7: areturn

  public javax.crypto.SecretKey getSecretKey();
    Code:
       0: aload_0
       1: getfield      #3                  // Field secretKey:Ljavax/crypto/SecretKey;
       4: areturn

  public java.lang.String getKeyAlgo();
    Code:
       0: aload_0
       1: getfield      #4                  // Field keyAlgo:Ljava/lang/String;
       4: areturn

  public java.lang.String getAlias();
    Code:
       0: aload_0
       1: invokespecial #7                  // Method org/adorsys/jkeygen/keystore/KeyEntryData.getAlias:()Ljava/lang/String;
       4: areturn

  public javax.security.auth.callback.CallbackHandler getPasswordSource();
    Code:
       0: aload_0
       1: invokespecial #8                  // Method org/adorsys/jkeygen/keystore/KeyEntryData.getPasswordSource:()Ljavax/security/auth/callback/CallbackHandler;
       4: areturn

  org.adorsys.jkeygen.keystore.SecretKeyData(javax.security.auth.callback.CallbackHandler, java.lang.String, javax.crypto.SecretKey, java.lang.String, org.adorsys.jkeygen.keystore.SecretKeyData$1);
    Code:
       0: aload_0
       1: aload_1
       2: aload_2
       3: aload_3
       4: aload         4
       6: invokespecial #1                  // Method "<init>":(Ljavax/security/auth/callback/CallbackHandler;Ljava/lang/String;Ljavax/crypto/SecretKey;Ljava/lang/String;)V
       9: return
}
