Compiled from "DoublesPmfCdfImpl.java"
class com.yahoo.sketches.quantiles.DoublesPmfCdfImpl {
  static final boolean $assertionsDisabled;

  com.yahoo.sketches.quantiles.DoublesPmfCdfImpl();
    Code:
       0: aload_0
       1: invokespecial #1                  // Method java/lang/Object."<init>":()V
       4: return

  static double[] getPMFOrCDF(com.yahoo.sketches.quantiles.DoublesSketch, double[], boolean);
    Code:
       0: aload_0
       1: aload_1
       2: invokestatic  #2                  // Method internalBuildHistogram:(Lcom/yahoo/sketches/quantiles/DoublesSketch;[D)[J
       5: astore_3
       6: aload_3
       7: arraylength
       8: istore        4
      10: iload         4
      12: newarray       double
      14: astore        5
      16: aload_0
      17: invokevirtual #3                  // Method com/yahoo/sketches/quantiles/DoublesSketch.getN:()J
      20: l2d
      21: dstore        6
      23: lconst_0
      24: lstore        8
      26: iload_2
      27: ifeq          73
      30: iconst_0
      31: istore        10
      33: iload         10
      35: iload         4
      37: if_icmpge     70
      40: aload_3
      41: iload         10
      43: laload
      44: lstore        11
      46: lload         8
      48: lload         11
      50: ladd
      51: lstore        8
      53: aload         5
      55: iload         10
      57: lload         8
      59: l2d
      60: dload         6
      62: ddiv
      63: dastore
      64: iinc          10, 1
      67: goto          33
      70: goto          113
      73: iconst_0
      74: istore        10
      76: iload         10
      78: iload         4
      80: if_icmpge     113
      83: aload_3
      84: iload         10
      86: laload
      87: lstore        11
      89: lload         8
      91: lload         11
      93: ladd
      94: lstore        8
      96: aload         5
      98: iload         10
     100: lload         11
     102: l2d
     103: dload         6
     105: ddiv
     106: dastore
     107: iinc          10, 1
     110: goto          76
     113: getstatic     #4                  // Field $assertionsDisabled:Z
     116: ifne          136
     119: lload         8
     121: l2d
     122: dload         6
     124: dcmpl
     125: ifeq          136
     128: new           #5                  // class java/lang/AssertionError
     131: dup
     132: invokespecial #6                  // Method java/lang/AssertionError."<init>":()V
     135: athrow
     136: aload         5
     138: areturn

  static long[] internalBuildHistogram(com.yahoo.sketches.quantiles.DoublesSketch, double[]);
    Code:
       0: aload_0
       1: invokevirtual #7                  // Method com/yahoo/sketches/quantiles/DoublesSketch.getCombinedBuffer:()[D
       4: astore_2
       5: aload_2
       6: astore_3
       7: aload_0
       8: invokevirtual #8                  // Method com/yahoo/sketches/quantiles/DoublesSketch.getBaseBufferCount:()I
      11: istore        4
      13: aload_1
      14: invokestatic  #9                  // Method com/yahoo/sketches/quantiles/Util.validateValues:([D)V
      17: aload_1
      18: arraylength
      19: istore        5
      21: iload         5
      23: iconst_1
      24: iadd
      25: istore        6
      27: iload         6
      29: newarray       long
      31: astore        7
      33: lconst_1
      34: lstore        8
      36: iload         5
      38: bipush        50
      40: if_icmpge     58
      43: aload_3
      44: iconst_0
      45: iload         4
      47: lload         8
      49: aload_1
      50: aload         7
      52: invokestatic  #10                 // Method bilinearTimeIncrementHistogramCounters:([DIIJ[D[J)V
      55: goto          77
      58: aload_3
      59: iconst_0
      60: iload         4
      62: invokestatic  #11                 // Method java/util/Arrays.sort:([DII)V
      65: aload_3
      66: iconst_0
      67: iload         4
      69: lload         8
      71: aload_1
      72: aload         7
      74: invokestatic  #12                 // Method linearTimeIncrementHistogramCounters:([DIIJ[D[J)V
      77: aload_0
      78: invokevirtual #13                 // Method com/yahoo/sketches/quantiles/DoublesSketch.getBitPattern:()J
      81: lstore        10
      83: aload_0
      84: invokevirtual #14                 // Method com/yahoo/sketches/quantiles/DoublesSketch.getK:()I
      87: istore        12
      89: getstatic     #4                  // Field $assertionsDisabled:Z
      92: ifne          121
      95: lload         10
      97: aload_0
      98: invokevirtual #3                  // Method com/yahoo/sketches/quantiles/DoublesSketch.getN:()J
     101: ldc2_w        #15                 // long 2l
     104: iload         12
     106: i2l
     107: lmul
     108: ldiv
     109: lcmp
     110: ifeq          121
     113: new           #5                  // class java/lang/AssertionError
     116: dup
     117: invokespecial #6                  // Method java/lang/AssertionError."<init>":()V
     120: athrow
     121: iconst_0
     122: istore        13
     124: lload         10
     126: lconst_0
     127: lcmp
     128: ifeq          177
     131: lload         8
     133: lload         8
     135: ladd
     136: lstore        8
     138: lload         10
     140: lconst_1
     141: land
     142: lconst_0
     143: lcmp
     144: ifle          165
     147: aload_2
     148: iconst_2
     149: iload         13
     151: iadd
     152: iload         12
     154: imul
     155: iload         12
     157: lload         8
     159: aload_1
     160: aload         7
     162: invokestatic  #12                 // Method linearTimeIncrementHistogramCounters:([DIIJ[D[J)V
     165: iinc          13, 1
     168: lload         10
     170: iconst_1
     171: lushr
     172: lstore        10
     174: goto          124
     177: aload         7
     179: areturn

  static void bilinearTimeIncrementHistogramCounters(double[], int, int, long, double[], long[]);
    Code:
       0: getstatic     #4                  // Field $assertionsDisabled:Z
       3: ifne          25
       6: aload         5
       8: arraylength
       9: iconst_1
      10: iadd
      11: aload         6
      13: arraylength
      14: if_icmpeq     25
      17: new           #5                  // class java/lang/AssertionError
      20: dup
      21: invokespecial #6                  // Method java/lang/AssertionError."<init>":()V
      24: athrow
      25: iconst_0
      26: istore        7
      28: iload         7
      30: iload_2
      31: if_icmpge     117
      34: aload_0
      35: iload         7
      37: iload_1
      38: iadd
      39: daload
      40: dstore        8
      42: iconst_0
      43: istore        10
      45: iconst_0
      46: istore        10
      48: iload         10
      50: aload         5
      52: arraylength
      53: if_icmpge     80
      56: aload         5
      58: iload         10
      60: daload
      61: dstore        11
      63: dload         8
      65: dload         11
      67: dcmpg
      68: ifge          74
      71: goto          80
      74: iinc          10, 1
      77: goto          48
      80: getstatic     #4                  // Field $assertionsDisabled:Z
      83: ifne          102
      86: iload         10
      88: aload         6
      90: arraylength
      91: if_icmplt     102
      94: new           #5                  // class java/lang/AssertionError
      97: dup
      98: invokespecial #6                  // Method java/lang/AssertionError."<init>":()V
     101: athrow
     102: aload         6
     104: iload         10
     106: dup2
     107: laload
     108: lload_3
     109: ladd
     110: lastore
     111: iinc          7, 1
     114: goto          28
     117: return

  static void linearTimeIncrementHistogramCounters(double[], int, int, long, double[], long[]);
    Code:
       0: iconst_0
       1: istore        7
       3: iconst_0
       4: istore        8
       6: iload         7
       8: iload_2
       9: if_icmpge     56
      12: iload         8
      14: aload         5
      16: arraylength
      17: if_icmpge     56
      20: aload_0
      21: iload         7
      23: iload_1
      24: iadd
      25: daload
      26: aload         5
      28: iload         8
      30: daload
      31: dcmpg
      32: ifge          50
      35: aload         6
      37: iload         8
      39: dup2
      40: laload
      41: lload_3
      42: ladd
      43: lastore
      44: iinc          7, 1
      47: goto          6
      50: iinc          8, 1
      53: goto          6
      56: iload         8
      58: aload         5
      60: arraylength
      61: if_icmpne     79
      64: aload         6
      66: iload         8
      68: dup2
      69: laload
      70: lload_3
      71: iload_2
      72: iload         7
      74: isub
      75: i2l
      76: lmul
      77: ladd
      78: lastore
      79: return

  static {};
    Code:
       0: ldc           #17                 // class com/yahoo/sketches/quantiles/DoublesPmfCdfImpl
       2: invokevirtual #18                 // Method java/lang/Class.desiredAssertionStatus:()Z
       5: ifne          12
       8: iconst_1
       9: goto          13
      12: iconst_0
      13: putstatic     #4                  // Field $assertionsDisabled:Z
      16: return
}
