Compiled from "TestScheduler.scala"
public class monix.execution.schedulers.TestScheduler$Task implements scala.Product,scala.Serializable {
  private final long id;

  private final java.lang.Runnable task;

  private final scala.concurrent.duration.FiniteDuration runsAt;

  public long id();
    Code:
       0: aload_0
       1: getfield      #18                 // Field id:J
       4: lreturn

  public java.lang.Runnable task();
    Code:
       0: aload_0
       1: getfield      #23                 // Field task:Ljava/lang/Runnable;
       4: areturn

  public scala.concurrent.duration.FiniteDuration runsAt();
    Code:
       0: aload_0
       1: getfield      #26                 // Field runsAt:Lscala/concurrent/duration/FiniteDuration;
       4: areturn

  public monix.execution.schedulers.TestScheduler$Task copy(long, java.lang.Runnable, scala.concurrent.duration.FiniteDuration);
    Code:
       0: new           #2                  // class monix/execution/schedulers/TestScheduler$Task
       3: dup
       4: lload_1
       5: aload_3
       6: aload         4
       8: invokespecial #32                 // Method "<init>":(JLjava/lang/Runnable;Lscala/concurrent/duration/FiniteDuration;)V
      11: areturn

  public long copy$default$1();
    Code:
       0: aload_0
       1: invokevirtual #35                 // Method id:()J
       4: lreturn

  public java.lang.Runnable copy$default$2();
    Code:
       0: aload_0
       1: invokevirtual #38                 // Method task:()Ljava/lang/Runnable;
       4: areturn

  public scala.concurrent.duration.FiniteDuration copy$default$3();
    Code:
       0: aload_0
       1: invokevirtual #41                 // Method runsAt:()Lscala/concurrent/duration/FiniteDuration;
       4: areturn

  public java.lang.String productPrefix();
    Code:
       0: ldc           #45                 // String Task
       2: areturn

  public int productArity();
    Code:
       0: iconst_3
       1: ireturn

  public java.lang.Object productElement(int);
    Code:
       0: iload_1
       1: istore_2
       2: iload_2
       3: tableswitch   { // 0 to 2
                     0: 57
                     1: 50
                     2: 43
               default: 28
          }
      28: new           #51                 // class java/lang/IndexOutOfBoundsException
      31: dup
      32: iload_1
      33: invokestatic  #57                 // Method scala/runtime/BoxesRunTime.boxToInteger:(I)Ljava/lang/Integer;
      36: invokevirtual #60                 // Method java/lang/Object.toString:()Ljava/lang/String;
      39: invokespecial #63                 // Method java/lang/IndexOutOfBoundsException."<init>":(Ljava/lang/String;)V
      42: athrow
      43: aload_0
      44: invokevirtual #41                 // Method runsAt:()Lscala/concurrent/duration/FiniteDuration;
      47: goto          64
      50: aload_0
      51: invokevirtual #38                 // Method task:()Ljava/lang/Runnable;
      54: goto          64
      57: aload_0
      58: invokevirtual #35                 // Method id:()J
      61: invokestatic  #67                 // Method scala/runtime/BoxesRunTime.boxToLong:(J)Ljava/lang/Long;
      64: areturn

  public scala.collection.Iterator<java.lang.Object> productIterator();
    Code:
       0: getstatic     #77                 // Field scala/runtime/ScalaRunTime$.MODULE$:Lscala/runtime/ScalaRunTime$;
       3: aload_0
       4: invokevirtual #81                 // Method scala/runtime/ScalaRunTime$.typedProductIterator:(Lscala/Product;)Lscala/collection/Iterator;
       7: areturn

  public boolean canEqual(java.lang.Object);
    Code:
       0: aload_1
       1: instanceof    #2                  // class monix/execution/schedulers/TestScheduler$Task
       4: ireturn

  public int hashCode();
    Code:
       0: ldc           #86                 // int -889275714
       2: istore_1
       3: iload_1
       4: aload_0
       5: invokevirtual #35                 // Method id:()J
       8: invokestatic  #92                 // Method scala/runtime/Statics.longHash:(J)I
      11: invokestatic  #96                 // Method scala/runtime/Statics.mix:(II)I
      14: istore_1
      15: iload_1
      16: aload_0
      17: invokevirtual #38                 // Method task:()Ljava/lang/Runnable;
      20: invokestatic  #100                // Method scala/runtime/Statics.anyHash:(Ljava/lang/Object;)I
      23: invokestatic  #96                 // Method scala/runtime/Statics.mix:(II)I
      26: istore_1
      27: iload_1
      28: aload_0
      29: invokevirtual #41                 // Method runsAt:()Lscala/concurrent/duration/FiniteDuration;
      32: invokestatic  #100                // Method scala/runtime/Statics.anyHash:(Ljava/lang/Object;)I
      35: invokestatic  #96                 // Method scala/runtime/Statics.mix:(II)I
      38: istore_1
      39: iload_1
      40: iconst_3
      41: invokestatic  #103                // Method scala/runtime/Statics.finalizeHash:(II)I
      44: ireturn

  public java.lang.String toString();
    Code:
       0: getstatic     #77                 // Field scala/runtime/ScalaRunTime$.MODULE$:Lscala/runtime/ScalaRunTime$;
       3: aload_0
       4: invokevirtual #107                // Method scala/runtime/ScalaRunTime$._toString:(Lscala/Product;)Ljava/lang/String;
       7: areturn

  public boolean equals(java.lang.Object);
    Code:
       0: aload_0
       1: aload_1
       2: if_acmpeq     125
       5: aload_1
       6: astore_2
       7: aload_2
       8: instanceof    #2                  // class monix/execution/schedulers/TestScheduler$Task
      11: ifeq          19
      14: iconst_1
      15: istore_3
      16: goto          21
      19: iconst_0
      20: istore_3
      21: iload_3
      22: ifeq          129
      25: aload_1
      26: checkcast     #2                  // class monix/execution/schedulers/TestScheduler$Task
      29: astore        4
      31: aload_0
      32: invokevirtual #35                 // Method id:()J
      35: aload         4
      37: invokevirtual #35                 // Method id:()J
      40: lcmp
      41: ifne          121
      44: aload_0
      45: invokevirtual #38                 // Method task:()Ljava/lang/Runnable;
      48: aload         4
      50: invokevirtual #38                 // Method task:()Ljava/lang/Runnable;
      53: astore        5
      55: dup
      56: ifnonnull     68
      59: pop
      60: aload         5
      62: ifnull        76
      65: goto          121
      68: aload         5
      70: invokevirtual #110                // Method java/lang/Object.equals:(Ljava/lang/Object;)Z
      73: ifeq          121
      76: aload_0
      77: invokevirtual #41                 // Method runsAt:()Lscala/concurrent/duration/FiniteDuration;
      80: aload         4
      82: invokevirtual #41                 // Method runsAt:()Lscala/concurrent/duration/FiniteDuration;
      85: astore        6
      87: dup
      88: ifnonnull     100
      91: pop
      92: aload         6
      94: ifnull        108
      97: goto          121
     100: aload         6
     102: invokevirtual #110                // Method java/lang/Object.equals:(Ljava/lang/Object;)Z
     105: ifeq          121
     108: aload         4
     110: aload_0
     111: invokevirtual #112                // Method canEqual:(Ljava/lang/Object;)Z
     114: ifeq          121
     117: iconst_1
     118: goto          122
     121: iconst_0
     122: ifeq          129
     125: iconst_1
     126: goto          130
     129: iconst_0
     130: ireturn

  public monix.execution.schedulers.TestScheduler$Task(long, java.lang.Runnable, scala.concurrent.duration.FiniteDuration);
    Code:
       0: aload_0
       1: lload_1
       2: putfield      #18                 // Field id:J
       5: aload_0
       6: aload_3
       7: putfield      #23                 // Field task:Ljava/lang/Runnable;
      10: aload_0
      11: aload         4
      13: putfield      #26                 // Field runsAt:Lscala/concurrent/duration/FiniteDuration;
      16: aload_0
      17: invokespecial #119                // Method java/lang/Object."<init>":()V
      20: aload_0
      21: invokestatic  #125                // Method scala/Product$class.$init$:(Lscala/Product;)V
      24: return
}
