Compiled from "TestScheduler.scala"
public class monix.execution.schedulers.TestScheduler$Task$ implements scala.Serializable {
  public static final monix.execution.schedulers.TestScheduler$Task$ MODULE$;

  private final scala.math.Ordering<monix.execution.schedulers.TestScheduler$Task> ordering;

  public static {};
    Code:
       0: new           #2                  // class monix/execution/schedulers/TestScheduler$Task$
       3: invokespecial #14                 // Method "<init>":()V
       6: return

  public scala.math.Ordering<monix.execution.schedulers.TestScheduler$Task> ordering();
    Code:
       0: aload_0
       1: getfield      #20                 // Field ordering:Lscala/math/Ordering;
       4: areturn

  public monix.execution.schedulers.TestScheduler$Task apply(long, java.lang.Runnable, scala.concurrent.duration.FiniteDuration);
    Code:
       0: new           #25                 // class monix/execution/schedulers/TestScheduler$Task
       3: dup
       4: lload_1
       5: aload_3
       6: aload         4
       8: invokespecial #28                 // Method monix/execution/schedulers/TestScheduler$Task."<init>":(JLjava/lang/Runnable;Lscala/concurrent/duration/FiniteDuration;)V
      11: areturn

  public scala.Option<scala.Tuple3<java.lang.Object, java.lang.Runnable, scala.concurrent.duration.FiniteDuration>> unapply(monix.execution.schedulers.TestScheduler$Task);
    Code:
       0: aload_1
       1: ifnonnull     10
       4: getstatic     #41                 // Field scala/None$.MODULE$:Lscala/None$;
       7: goto          39
      10: new           #43                 // class scala/Some
      13: dup
      14: new           #45                 // class scala/Tuple3
      17: dup
      18: aload_1
      19: invokevirtual #48                 // Method monix/execution/schedulers/TestScheduler$Task.id:()J
      22: invokestatic  #54                 // Method scala/runtime/BoxesRunTime.boxToLong:(J)Ljava/lang/Long;
      25: aload_1
      26: invokevirtual #57                 // Method monix/execution/schedulers/TestScheduler$Task.task:()Ljava/lang/Runnable;
      29: aload_1
      30: invokevirtual #60                 // Method monix/execution/schedulers/TestScheduler$Task.runsAt:()Lscala/concurrent/duration/FiniteDuration;
      33: invokespecial #63                 // Method scala/Tuple3."<init>":(Ljava/lang/Object;Ljava/lang/Object;Ljava/lang/Object;)V
      36: invokespecial #66                 // Method scala/Some."<init>":(Ljava/lang/Object;)V
      39: areturn

  private java.lang.Object readResolve();
    Code:
       0: getstatic     #74                 // Field MODULE$:Lmonix/execution/schedulers/TestScheduler$Task$;
       3: areturn

  public monix.execution.schedulers.TestScheduler$Task$();
    Code:
       0: aload_0
       1: invokespecial #75                 // Method java/lang/Object."<init>":()V
       4: aload_0
       5: putstatic     #74                 // Field MODULE$:Lmonix/execution/schedulers/TestScheduler$Task$;
       8: aload_0
       9: new           #77                 // class monix/execution/schedulers/TestScheduler$Task$$anon$1
      12: dup
      13: invokespecial #78                 // Method monix/execution/schedulers/TestScheduler$Task$$anon$1."<init>":()V
      16: putfield      #20                 // Field ordering:Lscala/math/Ordering;
      19: return
}
