Compiled from "TestScheduler.scala"
public final class monix.execution.schedulers.TestScheduler$ implements scala.Serializable {
  public static final monix.execution.schedulers.TestScheduler$ MODULE$;

  public static {};
    Code:
       0: new           #2                  // class monix/execution/schedulers/TestScheduler$
       3: invokespecial #14                 // Method "<init>":()V
       6: return

  public monix.execution.schedulers.TestScheduler apply();
    Code:
       0: new           #18                 // class monix/execution/schedulers/TestScheduler
       3: dup
       4: getstatic     #23                 // Field monix/execution/schedulers/ExecutionModel$.MODULE$:Lmonix/execution/schedulers/ExecutionModel$;
       7: invokevirtual #27                 // Method monix/execution/schedulers/ExecutionModel$.Default:()Lmonix/execution/schedulers/ExecutionModel;
      10: invokespecial #30                 // Method monix/execution/schedulers/TestScheduler."<init>":(Lmonix/execution/schedulers/ExecutionModel;)V
      13: areturn

  public monix.execution.schedulers.TestScheduler apply(monix.execution.schedulers.ExecutionModel);
    Code:
       0: new           #18                 // class monix/execution/schedulers/TestScheduler
       3: dup
       4: aload_1
       5: invokespecial #30                 // Method monix/execution/schedulers/TestScheduler."<init>":(Lmonix/execution/schedulers/ExecutionModel;)V
       8: areturn

  private java.lang.Object readResolve();
    Code:
       0: getstatic     #38                 // Field MODULE$:Lmonix/execution/schedulers/TestScheduler$;
       3: areturn

  private monix.execution.schedulers.TestScheduler$();
    Code:
       0: aload_0
       1: invokespecial #39                 // Method java/lang/Object."<init>":()V
       4: aload_0
       5: putstatic     #38                 // Field MODULE$:Lmonix/execution/schedulers/TestScheduler$;
       8: return
}
