Compiled from "AbstractObjectProvider.java"
public abstract class org.glassfish.jersey.message.filtering.spi.AbstractObjectProvider<T> implements org.glassfish.jersey.message.filtering.spi.ObjectProvider<T>, org.glassfish.jersey.message.filtering.spi.ObjectGraphTransformer<T> {
  private static final int PROVIDER_CACHE_SIZE;

  private final org.glassfish.jersey.internal.guava.Cache<org.glassfish.jersey.message.filtering.spi.AbstractObjectProvider$EntityContext, T> filteringObjects;

  private org.glassfish.jersey.message.filtering.spi.ScopeProvider scopeProvider;

  private org.glassfish.jersey.message.filtering.spi.EntityInspector entityInspector;

  private org.glassfish.jersey.message.filtering.spi.EntityGraphProvider graphProvider;

  public org.glassfish.jersey.message.filtering.spi.AbstractObjectProvider();
    Code:
       0: aload_0
       1: invokespecial #1                  // Method java/lang/Object."<init>":()V
       4: aload_0
       5: invokestatic  #2                  // Method org/glassfish/jersey/internal/guava/CacheBuilder.newBuilder:()Lorg/glassfish/jersey/internal/guava/CacheBuilder;
       8: ldc2_w        #4                  // long 1000l
      11: invokevirtual #6                  // Method org/glassfish/jersey/internal/guava/CacheBuilder.maximumSize:(J)Lorg/glassfish/jersey/internal/guava/CacheBuilder;
      14: invokevirtual #7                  // Method org/glassfish/jersey/internal/guava/CacheBuilder.build:()Lorg/glassfish/jersey/internal/guava/Cache;
      17: putfield      #8                  // Field filteringObjects:Lorg/glassfish/jersey/internal/guava/Cache;
      20: return

  public final T getFilteringObject(java.lang.reflect.Type, boolean, java.lang.annotation.Annotation...);
    Code:
       0: aload_0
       1: aload_1
       2: invokestatic  #9                  // Method org/glassfish/jersey/message/filtering/spi/FilteringHelper.getEntityClass:(Ljava/lang/reflect/Type;)Ljava/lang/Class;
       5: iload_2
       6: aload_3
       7: invokespecial #10                 // Method getFilteringObject:(Ljava/lang/Class;Z[Ljava/lang/annotation/Annotation;)Ljava/lang/Object;
      10: areturn

  private T getFilteringObject(java.lang.Class<?>, boolean, java.lang.annotation.Annotation...);
    Code:
       0: aload_1
       1: invokestatic  #11                 // Method org/glassfish/jersey/message/filtering/spi/FilteringHelper.filterableEntityClass:(Ljava/lang/Class;)Z
       4: ifeq          92
       7: aload_0
       8: getfield      #12                 // Field entityInspector:Lorg/glassfish/jersey/message/filtering/spi/EntityInspector;
      11: aload_1
      12: iload_2
      13: invokeinterface #13,  3           // InterfaceMethod org/glassfish/jersey/message/filtering/spi/EntityInspector.inspect:(Ljava/lang/Class;Z)V
      18: aload_0
      19: getfield      #14                 // Field scopeProvider:Lorg/glassfish/jersey/message/filtering/spi/ScopeProvider;
      22: aload_0
      23: aload_3
      24: invokespecial #15                 // Method getEntityAnnotations:([Ljava/lang/annotation/Annotation;)[Ljava/lang/annotation/Annotation;
      27: iconst_1
      28: invokeinterface #16,  3           // InterfaceMethod org/glassfish/jersey/message/filtering/spi/ScopeProvider.getFilteringScopes:([Ljava/lang/annotation/Annotation;Z)Ljava/util/Set;
      33: astore        4
      35: new           #17                 // class org/glassfish/jersey/message/filtering/spi/AbstractObjectProvider$EntityContext
      38: dup
      39: aload_1
      40: aload         4
      42: aconst_null
      43: invokespecial #18                 // Method org/glassfish/jersey/message/filtering/spi/AbstractObjectProvider$EntityContext."<init>":(Ljava/lang/Class;Ljava/util/Set;Lorg/glassfish/jersey/message/filtering/spi/AbstractObjectProvider$1;)V
      46: astore        5
      48: aload_0
      49: getfield      #8                  // Field filteringObjects:Lorg/glassfish/jersey/internal/guava/Cache;
      52: aload         5
      54: invokeinterface #19,  2           // InterfaceMethod org/glassfish/jersey/internal/guava/Cache.getIfPresent:(Ljava/lang/Object;)Ljava/lang/Object;
      59: astore        6
      61: aload         6
      63: ifnonnull     89
      66: aload_0
      67: aload_1
      68: aload         4
      70: iload_2
      71: invokespecial #20                 // Method createFilteringObject:(Ljava/lang/Class;Ljava/util/Set;Z)Ljava/lang/Object;
      74: astore        6
      76: aload_0
      77: getfield      #8                  // Field filteringObjects:Lorg/glassfish/jersey/internal/guava/Cache;
      80: aload         5
      82: aload         6
      84: invokeinterface #21,  3           // InterfaceMethod org/glassfish/jersey/internal/guava/Cache.put:(Ljava/lang/Object;Ljava/lang/Object;)V
      89: aload         6
      91: areturn
      92: aconst_null
      93: areturn

  private java.lang.annotation.Annotation[] getEntityAnnotations(java.lang.annotation.Annotation[]);
    Code:
       0: new           #22                 // class java/util/ArrayList
       3: dup
       4: invokespecial #23                 // Method java/util/ArrayList."<init>":()V
       7: astore_2
       8: aload_1
       9: astore_3
      10: aload_3
      11: arraylength
      12: istore        4
      14: iconst_0
      15: istore        5
      17: iload         5
      19: iload         4
      21: if_icmpge     51
      24: aload_3
      25: iload         5
      27: aaload
      28: astore        6
      30: aload         6
      32: instanceof    #24                 // class java/lang/reflect/Proxy
      35: ifne          45
      38: aload_2
      39: aload         6
      41: invokevirtual #25                 // Method java/util/ArrayList.add:(Ljava/lang/Object;)Z
      44: pop
      45: iinc          5, 1
      48: goto          17
      51: aload_2
      52: aload_2
      53: invokevirtual #26                 // Method java/util/ArrayList.size:()I
      56: anewarray     #27                 // class java/lang/annotation/Annotation
      59: invokevirtual #28                 // Method java/util/ArrayList.toArray:([Ljava/lang/Object;)[Ljava/lang/Object;
      62: checkcast     #29                 // class "[Ljava/lang/annotation/Annotation;"
      65: areturn

  private T createFilteringObject(java.lang.Class<?>, java.util.Set<java.lang.String>, boolean);
    Code:
       0: aload_0
       1: aload_0
       2: getfield      #30                 // Field graphProvider:Lorg/glassfish/jersey/message/filtering/spi/EntityGraphProvider;
       5: aload_1
       6: aload_2
       7: iload_3
       8: invokeinterface #31,  4           // InterfaceMethod org/glassfish/jersey/message/filtering/spi/EntityGraphProvider.createObjectGraph:(Ljava/lang/Class;Ljava/util/Set;Z)Lorg/glassfish/jersey/message/filtering/spi/ObjectGraph;
      13: invokevirtual #32                 // Method transform:(Lorg/glassfish/jersey/message/filtering/spi/ObjectGraph;)Ljava/lang/Object;
      16: areturn

  protected java.util.Set<java.lang.String> immutableSetOf(java.util.Set<java.lang.String>, java.lang.String);
    Code:
       0: new           #33                 // class java/util/HashSet
       3: dup
       4: aload_1
       5: invokespecial #34                 // Method java/util/HashSet."<init>":(Ljava/util/Collection;)V
       8: astore_3
       9: aload_3
      10: aload_2
      11: invokeinterface #35,  2           // InterfaceMethod java/util/Set.add:(Ljava/lang/Object;)Z
      16: pop
      17: aload_3
      18: invokestatic  #36                 // Method java/util/Collections.unmodifiableSet:(Ljava/util/Set;)Ljava/util/Set;
      21: areturn

  protected java.lang.String subgraphIdentifier(java.lang.Class<?>, java.lang.String, java.lang.Class<?>);
    Code:
       0: new           #37                 // class java/lang/StringBuilder
       3: dup
       4: invokespecial #38                 // Method java/lang/StringBuilder."<init>":()V
       7: aload_1
       8: invokevirtual #39                 // Method java/lang/Class.getName:()Ljava/lang/String;
      11: invokevirtual #40                 // Method java/lang/StringBuilder.append:(Ljava/lang/String;)Ljava/lang/StringBuilder;
      14: ldc           #41                 // String _
      16: invokevirtual #40                 // Method java/lang/StringBuilder.append:(Ljava/lang/String;)Ljava/lang/StringBuilder;
      19: aload_2
      20: invokevirtual #40                 // Method java/lang/StringBuilder.append:(Ljava/lang/String;)Ljava/lang/StringBuilder;
      23: ldc           #41                 // String _
      25: invokevirtual #40                 // Method java/lang/StringBuilder.append:(Ljava/lang/String;)Ljava/lang/StringBuilder;
      28: aload_3
      29: invokevirtual #39                 // Method java/lang/Class.getName:()Ljava/lang/String;
      32: invokevirtual #40                 // Method java/lang/StringBuilder.append:(Ljava/lang/String;)Ljava/lang/StringBuilder;
      35: invokevirtual #42                 // Method java/lang/StringBuilder.toString:()Ljava/lang/String;
      38: areturn
}
