Compiled from "ThymeleafProperties.java"
public class org.springframework.boot.autoconfigure.thymeleaf.ThymeleafProperties {
  private static final java.nio.charset.Charset DEFAULT_ENCODING;

  public static final java.lang.String DEFAULT_PREFIX;

  public static final java.lang.String DEFAULT_SUFFIX;

  private boolean checkTemplate;

  private boolean checkTemplateLocation;

  private java.lang.String prefix;

  private java.lang.String suffix;

  private java.lang.String mode;

  private java.nio.charset.Charset encoding;

  private boolean cache;

  private java.lang.Integer templateResolverOrder;

  private java.lang.String[] viewNames;

  private java.lang.String[] excludedViewNames;

  private boolean enableSpringElCompiler;

  private boolean renderHiddenMarkersBeforeCheckboxes;

  private boolean enabled;

  private final org.springframework.boot.autoconfigure.thymeleaf.ThymeleafProperties$Servlet servlet;

  private final org.springframework.boot.autoconfigure.thymeleaf.ThymeleafProperties$Reactive reactive;

  public org.springframework.boot.autoconfigure.thymeleaf.ThymeleafProperties();
    Code:
       0: aload_0
       1: invokespecial #1                  // Method java/lang/Object."<init>":()V
       4: aload_0
       5: iconst_1
       6: putfield      #2                  // Field checkTemplate:Z
       9: aload_0
      10: iconst_1
      11: putfield      #3                  // Field checkTemplateLocation:Z
      14: aload_0
      15: ldc           #5                  // String classpath:/templates/
      17: putfield      #6                  // Field prefix:Ljava/lang/String;
      20: aload_0
      21: ldc           #7                  // String .html
      23: putfield      #8                  // Field suffix:Ljava/lang/String;
      26: aload_0
      27: ldc           #9                  // String HTML
      29: putfield      #10                 // Field mode:Ljava/lang/String;
      32: aload_0
      33: getstatic     #11                 // Field DEFAULT_ENCODING:Ljava/nio/charset/Charset;
      36: putfield      #12                 // Field encoding:Ljava/nio/charset/Charset;
      39: aload_0
      40: iconst_1
      41: putfield      #13                 // Field cache:Z
      44: aload_0
      45: iconst_0
      46: putfield      #14                 // Field renderHiddenMarkersBeforeCheckboxes:Z
      49: aload_0
      50: iconst_1
      51: putfield      #15                 // Field enabled:Z
      54: aload_0
      55: new           #16                 // class org/springframework/boot/autoconfigure/thymeleaf/ThymeleafProperties$Servlet
      58: dup
      59: invokespecial #17                 // Method org/springframework/boot/autoconfigure/thymeleaf/ThymeleafProperties$Servlet."<init>":()V
      62: putfield      #18                 // Field servlet:Lorg/springframework/boot/autoconfigure/thymeleaf/ThymeleafProperties$Servlet;
      65: aload_0
      66: new           #19                 // class org/springframework/boot/autoconfigure/thymeleaf/ThymeleafProperties$Reactive
      69: dup
      70: invokespecial #20                 // Method org/springframework/boot/autoconfigure/thymeleaf/ThymeleafProperties$Reactive."<init>":()V
      73: putfield      #21                 // Field reactive:Lorg/springframework/boot/autoconfigure/thymeleaf/ThymeleafProperties$Reactive;
      76: return

  public boolean isEnabled();
    Code:
       0: aload_0
       1: getfield      #15                 // Field enabled:Z
       4: ireturn

  public void setEnabled(boolean);
    Code:
       0: aload_0
       1: iload_1
       2: putfield      #15                 // Field enabled:Z
       5: return

  public boolean isCheckTemplate();
    Code:
       0: aload_0
       1: getfield      #2                  // Field checkTemplate:Z
       4: ireturn

  public void setCheckTemplate(boolean);
    Code:
       0: aload_0
       1: iload_1
       2: putfield      #2                  // Field checkTemplate:Z
       5: return

  public boolean isCheckTemplateLocation();
    Code:
       0: aload_0
       1: getfield      #3                  // Field checkTemplateLocation:Z
       4: ireturn

  public void setCheckTemplateLocation(boolean);
    Code:
       0: aload_0
       1: iload_1
       2: putfield      #3                  // Field checkTemplateLocation:Z
       5: return

  public java.lang.String getPrefix();
    Code:
       0: aload_0
       1: getfield      #6                  // Field prefix:Ljava/lang/String;
       4: areturn

  public void setPrefix(java.lang.String);
    Code:
       0: aload_0
       1: aload_1
       2: putfield      #6                  // Field prefix:Ljava/lang/String;
       5: return

  public java.lang.String getSuffix();
    Code:
       0: aload_0
       1: getfield      #8                  // Field suffix:Ljava/lang/String;
       4: areturn

  public void setSuffix(java.lang.String);
    Code:
       0: aload_0
       1: aload_1
       2: putfield      #8                  // Field suffix:Ljava/lang/String;
       5: return

  public java.lang.String getMode();
    Code:
       0: aload_0
       1: getfield      #10                 // Field mode:Ljava/lang/String;
       4: areturn

  public void setMode(java.lang.String);
    Code:
       0: aload_0
       1: aload_1
       2: putfield      #10                 // Field mode:Ljava/lang/String;
       5: return

  public java.nio.charset.Charset getEncoding();
    Code:
       0: aload_0
       1: getfield      #12                 // Field encoding:Ljava/nio/charset/Charset;
       4: areturn

  public void setEncoding(java.nio.charset.Charset);
    Code:
       0: aload_0
       1: aload_1
       2: putfield      #12                 // Field encoding:Ljava/nio/charset/Charset;
       5: return

  public boolean isCache();
    Code:
       0: aload_0
       1: getfield      #13                 // Field cache:Z
       4: ireturn

  public void setCache(boolean);
    Code:
       0: aload_0
       1: iload_1
       2: putfield      #13                 // Field cache:Z
       5: return

  public java.lang.Integer getTemplateResolverOrder();
    Code:
       0: aload_0
       1: getfield      #22                 // Field templateResolverOrder:Ljava/lang/Integer;
       4: areturn

  public void setTemplateResolverOrder(java.lang.Integer);
    Code:
       0: aload_0
       1: aload_1
       2: putfield      #22                 // Field templateResolverOrder:Ljava/lang/Integer;
       5: return

  public java.lang.String[] getExcludedViewNames();
    Code:
       0: aload_0
       1: getfield      #23                 // Field excludedViewNames:[Ljava/lang/String;
       4: areturn

  public void setExcludedViewNames(java.lang.String[]);
    Code:
       0: aload_0
       1: aload_1
       2: putfield      #23                 // Field excludedViewNames:[Ljava/lang/String;
       5: return

  public java.lang.String[] getViewNames();
    Code:
       0: aload_0
       1: getfield      #24                 // Field viewNames:[Ljava/lang/String;
       4: areturn

  public void setViewNames(java.lang.String[]);
    Code:
       0: aload_0
       1: aload_1
       2: putfield      #24                 // Field viewNames:[Ljava/lang/String;
       5: return

  public boolean isEnableSpringElCompiler();
    Code:
       0: aload_0
       1: getfield      #25                 // Field enableSpringElCompiler:Z
       4: ireturn

  public void setEnableSpringElCompiler(boolean);
    Code:
       0: aload_0
       1: iload_1
       2: putfield      #25                 // Field enableSpringElCompiler:Z
       5: return

  public boolean isRenderHiddenMarkersBeforeCheckboxes();
    Code:
       0: aload_0
       1: getfield      #14                 // Field renderHiddenMarkersBeforeCheckboxes:Z
       4: ireturn

  public void setRenderHiddenMarkersBeforeCheckboxes(boolean);
    Code:
       0: aload_0
       1: iload_1
       2: putfield      #14                 // Field renderHiddenMarkersBeforeCheckboxes:Z
       5: return

  public org.springframework.boot.autoconfigure.thymeleaf.ThymeleafProperties$Reactive getReactive();
    Code:
       0: aload_0
       1: getfield      #21                 // Field reactive:Lorg/springframework/boot/autoconfigure/thymeleaf/ThymeleafProperties$Reactive;
       4: areturn

  public org.springframework.boot.autoconfigure.thymeleaf.ThymeleafProperties$Servlet getServlet();
    Code:
       0: aload_0
       1: getfield      #18                 // Field servlet:Lorg/springframework/boot/autoconfigure/thymeleaf/ThymeleafProperties$Servlet;
       4: areturn

  static {};
    Code:
       0: getstatic     #26                 // Field java/nio/charset/StandardCharsets.UTF_8:Ljava/nio/charset/Charset;
       3: putstatic     #11                 // Field DEFAULT_ENCODING:Ljava/nio/charset/Charset;
       6: return
}
