Compiled from "BeanDefinitionStoreException.java"
public class org.springframework.beans.factory.BeanDefinitionStoreException extends org.springframework.beans.FatalBeanException {
  private java.lang.String resourceDescription;

  private java.lang.String beanName;

  public org.springframework.beans.factory.BeanDefinitionStoreException(java.lang.String);
    Code:
       0: aload_0
       1: aload_1
       2: invokespecial #1                  // Method org/springframework/beans/FatalBeanException."<init>":(Ljava/lang/String;)V
       5: return

  public org.springframework.beans.factory.BeanDefinitionStoreException(java.lang.String, java.lang.Throwable);
    Code:
       0: aload_0
       1: aload_1
       2: aload_2
       3: invokespecial #2                  // Method org/springframework/beans/FatalBeanException."<init>":(Ljava/lang/String;Ljava/lang/Throwable;)V
       6: return

  public org.springframework.beans.factory.BeanDefinitionStoreException(java.lang.String, java.lang.String);
    Code:
       0: aload_0
       1: aload_2
       2: invokespecial #1                  // Method org/springframework/beans/FatalBeanException."<init>":(Ljava/lang/String;)V
       5: aload_0
       6: aload_1
       7: putfield      #3                  // Field resourceDescription:Ljava/lang/String;
      10: return

  public org.springframework.beans.factory.BeanDefinitionStoreException(java.lang.String, java.lang.String, java.lang.Throwable);
    Code:
       0: aload_0
       1: aload_2
       2: aload_3
       3: invokespecial #2                  // Method org/springframework/beans/FatalBeanException."<init>":(Ljava/lang/String;Ljava/lang/Throwable;)V
       6: aload_0
       7: aload_1
       8: putfield      #3                  // Field resourceDescription:Ljava/lang/String;
      11: return

  public org.springframework.beans.factory.BeanDefinitionStoreException(java.lang.String, java.lang.String, java.lang.String);
    Code:
       0: aload_0
       1: aload_1
       2: aload_2
       3: aload_3
       4: aconst_null
       5: invokespecial #4                  // Method "<init>":(Ljava/lang/String;Ljava/lang/String;Ljava/lang/String;Ljava/lang/Throwable;)V
       8: return

  public org.springframework.beans.factory.BeanDefinitionStoreException(java.lang.String, java.lang.String, java.lang.String, java.lang.Throwable);
    Code:
       0: aload_0
       1: new           #5                  // class java/lang/StringBuilder
       4: dup
       5: invokespecial #6                  // Method java/lang/StringBuilder."<init>":()V
       8: ldc           #7                  // String Invalid bean definition with name \'
      10: invokevirtual #8                  // Method java/lang/StringBuilder.append:(Ljava/lang/String;)Ljava/lang/StringBuilder;
      13: aload_2
      14: invokevirtual #8                  // Method java/lang/StringBuilder.append:(Ljava/lang/String;)Ljava/lang/StringBuilder;
      17: ldc           #9                  // String \' defined in
      19: invokevirtual #8                  // Method java/lang/StringBuilder.append:(Ljava/lang/String;)Ljava/lang/StringBuilder;
      22: aload_1
      23: invokevirtual #8                  // Method java/lang/StringBuilder.append:(Ljava/lang/String;)Ljava/lang/StringBuilder;
      26: ldc           #10                 // String :
      28: invokevirtual #8                  // Method java/lang/StringBuilder.append:(Ljava/lang/String;)Ljava/lang/StringBuilder;
      31: aload_3
      32: invokevirtual #8                  // Method java/lang/StringBuilder.append:(Ljava/lang/String;)Ljava/lang/StringBuilder;
      35: invokevirtual #11                 // Method java/lang/StringBuilder.toString:()Ljava/lang/String;
      38: aload         4
      40: invokespecial #2                  // Method org/springframework/beans/FatalBeanException."<init>":(Ljava/lang/String;Ljava/lang/Throwable;)V
      43: aload_0
      44: aload_1
      45: putfield      #3                  // Field resourceDescription:Ljava/lang/String;
      48: aload_0
      49: aload_2
      50: putfield      #12                 // Field beanName:Ljava/lang/String;
      53: return

  public java.lang.String getResourceDescription();
    Code:
       0: aload_0
       1: getfield      #3                  // Field resourceDescription:Ljava/lang/String;
       4: areturn

  public java.lang.String getBeanName();
    Code:
       0: aload_0
       1: getfield      #12                 // Field beanName:Ljava/lang/String;
       4: areturn
}
