Compiled from "JavaType.java"
public final class net.bytebuddy.utility.JavaType extends java.lang.Enum<net.bytebuddy.utility.JavaType> {
  public static final net.bytebuddy.utility.JavaType CONSTABLE;

  public static final net.bytebuddy.utility.JavaType TYPE_DESCRIPTOR;

  public static final net.bytebuddy.utility.JavaType TYPE_DESCRIPTOR_OF_FIELD;

  public static final net.bytebuddy.utility.JavaType TYPE_DESCRIPTOR_OF_METHOD;

  public static final net.bytebuddy.utility.JavaType CONSTANT_DESCRIPTION;

  public static final net.bytebuddy.utility.JavaType DYNAMIC_CONSTANT_DESCRIPTION;

  public static final net.bytebuddy.utility.JavaType CLASS_DESCRIPTION;

  public static final net.bytebuddy.utility.JavaType METHOD_TYPE_DESCRIPTION;

  public static final net.bytebuddy.utility.JavaType METHOD_HANDLE_DESCRIPTION;

  public static final net.bytebuddy.utility.JavaType DIRECT_METHOD_HANDLE_DESCRIPTION;

  public static final net.bytebuddy.utility.JavaType METHOD_HANDLE;

  public static final net.bytebuddy.utility.JavaType METHOD_HANDLES;

  public static final net.bytebuddy.utility.JavaType METHOD_TYPE;

  public static final net.bytebuddy.utility.JavaType METHOD_HANDLES_LOOKUP;

  public static final net.bytebuddy.utility.JavaType CALL_SITE;

  public static final net.bytebuddy.utility.JavaType VAR_HANDLE;

  public static final net.bytebuddy.utility.JavaType PARAMETER;

  public static final net.bytebuddy.utility.JavaType EXECUTABLE;

  public static final net.bytebuddy.utility.JavaType MODULE;

  private final net.bytebuddy.description.type.TypeDescription typeDescription;

  private static final net.bytebuddy.utility.JavaType[] $VALUES;

  private transient java.lang.Class load_bMCqooUK;

  private transient boolean isAvailable_niKjRqEX;

  public static net.bytebuddy.utility.JavaType[] values();
    Code:
       0: getstatic     #69                 // Field $VALUES:[Lnet/bytebuddy/utility/JavaType;
       3: invokevirtual #74                 // Method "[Lnet/bytebuddy/utility/JavaType;".clone:()Ljava/lang/Object;
       6: checkcast     #70                 // class "[Lnet/bytebuddy/utility/JavaType;"
       9: areturn

  public static net.bytebuddy.utility.JavaType valueOf(java.lang.String);
    Code:
       0: ldc           #2                  // class net/bytebuddy/utility/JavaType
       2: aload_0
       3: invokestatic  #79                 // Method java/lang/Enum.valueOf:(Ljava/lang/Class;Ljava/lang/String;)Ljava/lang/Enum;
       6: checkcast     #2                  // class net/bytebuddy/utility/JavaType
       9: areturn

  private net.bytebuddy.utility.JavaType(java.lang.String, int, java.lang.reflect.Type, java.lang.reflect.Type...);
    Code:
       0: aload_0
       1: aload_1
       2: iload_2
       3: aload_3
       4: iload         4
       6: aload         5
       8: ifnonnull     17
      11: getstatic     #88                 // Field net/bytebuddy/description/type/TypeDescription$Generic.UNDEFINED:Lnet/bytebuddy/description/type/TypeDescription$Generic;
      14: goto          22
      17: aload         5
      19: invokestatic  #92                 // Method net/bytebuddy/description/type/TypeDefinition$Sort.describe:(Ljava/lang/reflect/Type;)Lnet/bytebuddy/description/type/TypeDescription$Generic;
      22: new           #22                 // class net/bytebuddy/description/type/TypeList$Generic$ForLoadedTypes
      25: dup
      26: aload         6
      28: invokespecial #95                 // Method net/bytebuddy/description/type/TypeList$Generic$ForLoadedTypes."<init>":([Ljava/lang/reflect/Type;)V
      31: invokespecial #98                 // Method "<init>":(Ljava/lang/String;ILjava/lang/String;ILnet/bytebuddy/description/type/TypeDescription$Generic;Lnet/bytebuddy/description/type/TypeList$Generic;)V
      34: return

  private net.bytebuddy.utility.JavaType(java.lang.String, int, net.bytebuddy.description.type.TypeDefinition, net.bytebuddy.description.type.TypeDefinition...);
    Code:
       0: aload_0
       1: aload_1
       2: iload_2
       3: aload_3
       4: iload         4
       6: aload         5
       8: ifnonnull     17
      11: getstatic     #88                 // Field net/bytebuddy/description/type/TypeDescription$Generic.UNDEFINED:Lnet/bytebuddy/description/type/TypeDescription$Generic;
      14: goto          24
      17: aload         5
      19: invokeinterface #112,  1          // InterfaceMethod net/bytebuddy/description/type/TypeDefinition.asGenericType:()Lnet/bytebuddy/description/type/TypeDescription$Generic;
      24: new           #25                 // class net/bytebuddy/description/type/TypeList$Generic$Explicit
      27: dup
      28: aload         6
      30: invokespecial #115                // Method net/bytebuddy/description/type/TypeList$Generic$Explicit."<init>":([Lnet/bytebuddy/description/type/TypeDefinition;)V
      33: invokespecial #98                 // Method "<init>":(Ljava/lang/String;ILjava/lang/String;ILnet/bytebuddy/description/type/TypeDescription$Generic;Lnet/bytebuddy/description/type/TypeList$Generic;)V
      36: return

  private net.bytebuddy.utility.JavaType(java.lang.String, int, net.bytebuddy.description.type.TypeDescription$Generic, net.bytebuddy.description.type.TypeList$Generic);
    Code:
       0: aload_0
       1: aload_1
       2: iload_2
       3: invokespecial #121                // Method java/lang/Enum."<init>":(Ljava/lang/String;I)V
       6: aload_0
       7: new           #28                 // class net/bytebuddy/description/type/TypeDescription$Latent
      10: dup
      11: aload_3
      12: iload         4
      14: aload         5
      16: aload         6
      18: invokespecial #124                // Method net/bytebuddy/description/type/TypeDescription$Latent."<init>":(Ljava/lang/String;ILnet/bytebuddy/description/type/TypeDescription$Generic;Ljava/util/List;)V
      21: putfield      #126                // Field typeDescription:Lnet/bytebuddy/description/type/TypeDescription;
      24: return

  public net.bytebuddy.description.type.TypeDescription getTypeStub();
    Code:
       0: aload_0
       1: getfield      #126                // Field typeDescription:Lnet/bytebuddy/description/type/TypeDescription;
       4: areturn

  public java.lang.Class<?> load() throws java.lang.ClassNotFoundException;
    Code:
       0: aload_0
       1: getfield      #138                // Field load_bMCqooUK:Ljava/lang/Class;
       4: goto          7
       7: astore_1
       8: aload_1
       9: ifnull        16
      12: aconst_null
      13: goto          37
      16: aload_0
      17: astore_2
      18: aload_2
      19: getfield      #126                // Field typeDescription:Lnet/bytebuddy/description/type/TypeDescription;
      22: invokeinterface #142,  1          // InterfaceMethod net/bytebuddy/description/type/TypeDescription.getName:()Ljava/lang/String;
      27: iconst_0
      28: getstatic     #148                // Field net/bytebuddy/dynamic/loading/ClassLoadingStrategy.BOOTSTRAP_LOADER:Ljava/lang/ClassLoader;
      31: invokestatic  #154                // Method java/lang/Class.forName:(Ljava/lang/String;ZLjava/lang/ClassLoader;)Ljava/lang/Class;
      34: goto          37
      37: astore_2
      38: aload_2
      39: ifnonnull     53
      42: aload_0
      43: getfield      #138                // Field load_bMCqooUK:Ljava/lang/Class;
      46: checkcast     #150                // class java/lang/Class
      49: astore_2
      50: goto          60
      53: aload_2
      54: aload_0
      55: dup_x1
      56: pop
      57: putfield      #138                // Field load_bMCqooUK:Ljava/lang/Class;
      60: goto          63
      63: aload_2
      64: areturn

  public net.bytebuddy.description.type.TypeDescription loadAsDescription() throws java.lang.ClassNotFoundException;
    Code:
       0: aload_0
       1: invokevirtual #157                // Method load:()Ljava/lang/Class;
       4: invokestatic  #161                // Method net/bytebuddy/description/type/TypeDescription$ForLoadedType.of:(Ljava/lang/Class;)Lnet/bytebuddy/description/type/TypeDescription;
       7: areturn

  public boolean isAvailable();
    Code:
       0: aload_0
       1: getfield      #165                // Field isAvailable_niKjRqEX:Z
       4: goto          7
       7: istore_1
       8: iload_1
       9: ifeq          16
      12: iconst_0
      13: goto          32
      16: aload_0
      17: astore_2
      18: aload_2
      19: invokevirtual #157                // Method load:()Ljava/lang/Class;
      22: pop
      23: iconst_1
      24: goto          32
      27: astore_3
      28: iconst_0
      29: goto          32
      32: istore_2
      33: iload_2
      34: ifeq          47
      37: iconst_1
      38: aload_0
      39: dup_x1
      40: pop
      41: putfield      #165                // Field isAvailable_niKjRqEX:Z
      44: goto          49
      47: iconst_1
      48: istore_2
      49: goto          52
      52: iload_2
      53: ireturn
    Exception table:
       from    to  target type
          18    24    27   Class java/lang/ClassNotFoundException

  public boolean isInstance(java.lang.Object);
    Code:
       0: aload_0
       1: invokevirtual #171                // Method isAvailable:()Z
       4: ifne          9
       7: iconst_0
       8: ireturn
       9: aload_0
      10: invokevirtual #157                // Method load:()Ljava/lang/Class;
      13: aload_1
      14: invokevirtual #173                // Method java/lang/Class.isInstance:(Ljava/lang/Object;)Z
      17: ireturn
      18: astore_2
      19: iconst_0
      20: ireturn
    Exception table:
       from    to  target type
           9    17    18   Class java/lang/ClassNotFoundException

  static {};
    Code:
       0: goto          778
       3: new           #2                  // class net/bytebuddy/utility/JavaType
       6: dup
       7: ldc           #178                // String CONSTABLE
       9: iconst_0
      10: ldc           #180                // String java.lang.constant.Constable
      12: sipush        1537
      15: getstatic     #182                // Field net/bytebuddy/description/type/TypeDescription.UNDEFINED:Lnet/bytebuddy/description/type/TypeDescription;
      18: iconst_0
      19: anewarray     #33                 // class net/bytebuddy/description/type/TypeDefinition
      22: invokespecial #184                // Method "<init>":(Ljava/lang/String;ILjava/lang/String;ILnet/bytebuddy/description/type/TypeDefinition;[Lnet/bytebuddy/description/type/TypeDefinition;)V
      25: putstatic     #186                // Field CONSTABLE:Lnet/bytebuddy/utility/JavaType;
      28: new           #2                  // class net/bytebuddy/utility/JavaType
      31: dup
      32: ldc           #187                // String TYPE_DESCRIPTOR
      34: iconst_1
      35: ldc           #189                // String java.lang.invoke.TypeDescriptor
      37: sipush        1537
      40: getstatic     #182                // Field net/bytebuddy/description/type/TypeDescription.UNDEFINED:Lnet/bytebuddy/description/type/TypeDescription;
      43: iconst_0
      44: anewarray     #33                 // class net/bytebuddy/description/type/TypeDefinition
      47: invokespecial #184                // Method "<init>":(Ljava/lang/String;ILjava/lang/String;ILnet/bytebuddy/description/type/TypeDefinition;[Lnet/bytebuddy/description/type/TypeDefinition;)V
      50: putstatic     #191                // Field TYPE_DESCRIPTOR:Lnet/bytebuddy/utility/JavaType;
      53: new           #2                  // class net/bytebuddy/utility/JavaType
      56: dup
      57: ldc           #192                // String TYPE_DESCRIPTOR_OF_FIELD
      59: iconst_2
      60: ldc           #194                // String java.lang.invoke.TypeDescriptor$OfField
      62: sipush        1537
      65: getstatic     #182                // Field net/bytebuddy/description/type/TypeDescription.UNDEFINED:Lnet/bytebuddy/description/type/TypeDescription;
      68: iconst_1
      69: anewarray     #33                 // class net/bytebuddy/description/type/TypeDefinition
      72: dup
      73: iconst_0
      74: getstatic     #191                // Field TYPE_DESCRIPTOR:Lnet/bytebuddy/utility/JavaType;
      77: invokevirtual #196                // Method getTypeStub:()Lnet/bytebuddy/description/type/TypeDescription;
      80: aastore
      81: invokespecial #184                // Method "<init>":(Ljava/lang/String;ILjava/lang/String;ILnet/bytebuddy/description/type/TypeDefinition;[Lnet/bytebuddy/description/type/TypeDefinition;)V
      84: putstatic     #198                // Field TYPE_DESCRIPTOR_OF_FIELD:Lnet/bytebuddy/utility/JavaType;
      87: new           #2                  // class net/bytebuddy/utility/JavaType
      90: dup
      91: ldc           #199                // String TYPE_DESCRIPTOR_OF_METHOD
      93: iconst_3
      94: ldc           #201                // String java.lang.invoke.TypeDescriptor$OfMethod
      96: sipush        1537
      99: getstatic     #182                // Field net/bytebuddy/description/type/TypeDescription.UNDEFINED:Lnet/bytebuddy/description/type/TypeDescription;
     102: iconst_1
     103: anewarray     #33                 // class net/bytebuddy/description/type/TypeDefinition
     106: dup
     107: iconst_0
     108: getstatic     #191                // Field TYPE_DESCRIPTOR:Lnet/bytebuddy/utility/JavaType;
     111: invokevirtual #196                // Method getTypeStub:()Lnet/bytebuddy/description/type/TypeDescription;
     114: aastore
     115: invokespecial #184                // Method "<init>":(Ljava/lang/String;ILjava/lang/String;ILnet/bytebuddy/description/type/TypeDefinition;[Lnet/bytebuddy/description/type/TypeDefinition;)V
     118: putstatic     #203                // Field TYPE_DESCRIPTOR_OF_METHOD:Lnet/bytebuddy/utility/JavaType;
     121: new           #2                  // class net/bytebuddy/utility/JavaType
     124: dup
     125: ldc           #204                // String CONSTANT_DESCRIPTION
     127: iconst_4
     128: ldc           #206                // String java.lang.constant.ConstantDesc
     130: sipush        1537
     133: getstatic     #182                // Field net/bytebuddy/description/type/TypeDescription.UNDEFINED:Lnet/bytebuddy/description/type/TypeDescription;
     136: iconst_0
     137: anewarray     #33                 // class net/bytebuddy/description/type/TypeDefinition
     140: invokespecial #184                // Method "<init>":(Ljava/lang/String;ILjava/lang/String;ILnet/bytebuddy/description/type/TypeDefinition;[Lnet/bytebuddy/description/type/TypeDefinition;)V
     143: putstatic     #208                // Field CONSTANT_DESCRIPTION:Lnet/bytebuddy/utility/JavaType;
     146: new           #2                  // class net/bytebuddy/utility/JavaType
     149: dup
     150: ldc           #209                // String DYNAMIC_CONSTANT_DESCRIPTION
     152: iconst_5
     153: ldc           #211                // String java.lang.constant.DynamicConstantDesc
     155: sipush        1025
     158: getstatic     #214                // Field net/bytebuddy/description/type/TypeDescription.OBJECT:Lnet/bytebuddy/description/type/TypeDescription;
     161: iconst_1
     162: anewarray     #33                 // class net/bytebuddy/description/type/TypeDefinition
     165: dup
     166: iconst_0
     167: getstatic     #208                // Field CONSTANT_DESCRIPTION:Lnet/bytebuddy/utility/JavaType;
     170: invokevirtual #196                // Method getTypeStub:()Lnet/bytebuddy/description/type/TypeDescription;
     173: aastore
     174: invokespecial #184                // Method "<init>":(Ljava/lang/String;ILjava/lang/String;ILnet/bytebuddy/description/type/TypeDefinition;[Lnet/bytebuddy/description/type/TypeDefinition;)V
     177: putstatic     #216                // Field DYNAMIC_CONSTANT_DESCRIPTION:Lnet/bytebuddy/utility/JavaType;
     180: new           #2                  // class net/bytebuddy/utility/JavaType
     183: dup
     184: ldc           #217                // String CLASS_DESCRIPTION
     186: bipush        6
     188: ldc           #219                // String java.lang.constant.ClassDesc
     190: sipush        1537
     193: getstatic     #182                // Field net/bytebuddy/description/type/TypeDescription.UNDEFINED:Lnet/bytebuddy/description/type/TypeDescription;
     196: iconst_2
     197: anewarray     #33                 // class net/bytebuddy/description/type/TypeDefinition
     200: dup
     201: iconst_0
     202: getstatic     #208                // Field CONSTANT_DESCRIPTION:Lnet/bytebuddy/utility/JavaType;
     205: invokevirtual #196                // Method getTypeStub:()Lnet/bytebuddy/description/type/TypeDescription;
     208: aastore
     209: dup
     210: iconst_1
     211: getstatic     #198                // Field TYPE_DESCRIPTOR_OF_FIELD:Lnet/bytebuddy/utility/JavaType;
     214: invokevirtual #196                // Method getTypeStub:()Lnet/bytebuddy/description/type/TypeDescription;
     217: aastore
     218: invokespecial #184                // Method "<init>":(Ljava/lang/String;ILjava/lang/String;ILnet/bytebuddy/description/type/TypeDefinition;[Lnet/bytebuddy/description/type/TypeDefinition;)V
     221: putstatic     #221                // Field CLASS_DESCRIPTION:Lnet/bytebuddy/utility/JavaType;
     224: new           #2                  // class net/bytebuddy/utility/JavaType
     227: dup
     228: ldc           #222                // String METHOD_TYPE_DESCRIPTION
     230: bipush        7
     232: ldc           #224                // String java.lang.constant.MethodTypeDesc
     234: sipush        1537
     237: getstatic     #182                // Field net/bytebuddy/description/type/TypeDescription.UNDEFINED:Lnet/bytebuddy/description/type/TypeDescription;
     240: iconst_2
     241: anewarray     #33                 // class net/bytebuddy/description/type/TypeDefinition
     244: dup
     245: iconst_0
     246: getstatic     #208                // Field CONSTANT_DESCRIPTION:Lnet/bytebuddy/utility/JavaType;
     249: invokevirtual #196                // Method getTypeStub:()Lnet/bytebuddy/description/type/TypeDescription;
     252: aastore
     253: dup
     254: iconst_1
     255: getstatic     #203                // Field TYPE_DESCRIPTOR_OF_METHOD:Lnet/bytebuddy/utility/JavaType;
     258: invokevirtual #196                // Method getTypeStub:()Lnet/bytebuddy/description/type/TypeDescription;
     261: aastore
     262: invokespecial #184                // Method "<init>":(Ljava/lang/String;ILjava/lang/String;ILnet/bytebuddy/description/type/TypeDefinition;[Lnet/bytebuddy/description/type/TypeDefinition;)V
     265: putstatic     #226                // Field METHOD_TYPE_DESCRIPTION:Lnet/bytebuddy/utility/JavaType;
     268: new           #2                  // class net/bytebuddy/utility/JavaType
     271: dup
     272: ldc           #227                // String METHOD_HANDLE_DESCRIPTION
     274: bipush        8
     276: ldc           #229                // String java.lang.constant.MethodHandleDesc
     278: sipush        1537
     281: getstatic     #182                // Field net/bytebuddy/description/type/TypeDescription.UNDEFINED:Lnet/bytebuddy/description/type/TypeDescription;
     284: iconst_1
     285: anewarray     #33                 // class net/bytebuddy/description/type/TypeDefinition
     288: dup
     289: iconst_0
     290: getstatic     #208                // Field CONSTANT_DESCRIPTION:Lnet/bytebuddy/utility/JavaType;
     293: invokevirtual #196                // Method getTypeStub:()Lnet/bytebuddy/description/type/TypeDescription;
     296: aastore
     297: invokespecial #184                // Method "<init>":(Ljava/lang/String;ILjava/lang/String;ILnet/bytebuddy/description/type/TypeDefinition;[Lnet/bytebuddy/description/type/TypeDefinition;)V
     300: putstatic     #231                // Field METHOD_HANDLE_DESCRIPTION:Lnet/bytebuddy/utility/JavaType;
     303: new           #2                  // class net/bytebuddy/utility/JavaType
     306: dup
     307: ldc           #232                // String DIRECT_METHOD_HANDLE_DESCRIPTION
     309: bipush        9
     311: ldc           #234                // String java.lang.constant.DirectMethodHandleDesc
     313: sipush        1537
     316: getstatic     #182                // Field net/bytebuddy/description/type/TypeDescription.UNDEFINED:Lnet/bytebuddy/description/type/TypeDescription;
     319: iconst_1
     320: anewarray     #33                 // class net/bytebuddy/description/type/TypeDefinition
     323: dup
     324: iconst_0
     325: getstatic     #231                // Field METHOD_HANDLE_DESCRIPTION:Lnet/bytebuddy/utility/JavaType;
     328: invokevirtual #196                // Method getTypeStub:()Lnet/bytebuddy/description/type/TypeDescription;
     331: aastore
     332: invokespecial #184                // Method "<init>":(Ljava/lang/String;ILjava/lang/String;ILnet/bytebuddy/description/type/TypeDefinition;[Lnet/bytebuddy/description/type/TypeDefinition;)V
     335: putstatic     #236                // Field DIRECT_METHOD_HANDLE_DESCRIPTION:Lnet/bytebuddy/utility/JavaType;
     338: new           #2                  // class net/bytebuddy/utility/JavaType
     341: dup
     342: ldc           #237                // String METHOD_HANDLE
     344: bipush        10
     346: ldc           #239                // String java.lang.invoke.MethodHandle
     348: sipush        1025
     351: getstatic     #214                // Field net/bytebuddy/description/type/TypeDescription.OBJECT:Lnet/bytebuddy/description/type/TypeDescription;
     354: iconst_1
     355: anewarray     #33                 // class net/bytebuddy/description/type/TypeDefinition
     358: dup
     359: iconst_0
     360: getstatic     #186                // Field CONSTABLE:Lnet/bytebuddy/utility/JavaType;
     363: invokevirtual #196                // Method getTypeStub:()Lnet/bytebuddy/description/type/TypeDescription;
     366: aastore
     367: invokespecial #184                // Method "<init>":(Ljava/lang/String;ILjava/lang/String;ILnet/bytebuddy/description/type/TypeDefinition;[Lnet/bytebuddy/description/type/TypeDefinition;)V
     370: putstatic     #241                // Field METHOD_HANDLE:Lnet/bytebuddy/utility/JavaType;
     373: new           #2                  // class net/bytebuddy/utility/JavaType
     376: dup
     377: ldc           #242                // String METHOD_HANDLES
     379: bipush        11
     381: ldc           #244                // String java.lang.invoke.MethodHandles
     383: iconst_1
     384: ldc           #246                // class java/lang/Object
     386: iconst_0
     387: anewarray     #248                // class java/lang/reflect/Type
     390: invokespecial #250                // Method "<init>":(Ljava/lang/String;ILjava/lang/String;ILjava/lang/reflect/Type;[Ljava/lang/reflect/Type;)V
     393: putstatic     #252                // Field METHOD_HANDLES:Lnet/bytebuddy/utility/JavaType;
     396: new           #2                  // class net/bytebuddy/utility/JavaType
     399: dup
     400: ldc           #253                // String METHOD_TYPE
     402: bipush        12
     404: ldc           #255                // String java.lang.invoke.MethodType
     406: bipush        17
     408: getstatic     #214                // Field net/bytebuddy/description/type/TypeDescription.OBJECT:Lnet/bytebuddy/description/type/TypeDescription;
     411: iconst_3
     412: anewarray     #33                 // class net/bytebuddy/description/type/TypeDefinition
     415: dup
     416: iconst_0
     417: getstatic     #186                // Field CONSTABLE:Lnet/bytebuddy/utility/JavaType;
     420: invokevirtual #196                // Method getTypeStub:()Lnet/bytebuddy/description/type/TypeDescription;
     423: aastore
     424: dup
     425: iconst_1
     426: getstatic     #203                // Field TYPE_DESCRIPTOR_OF_METHOD:Lnet/bytebuddy/utility/JavaType;
     429: invokevirtual #196                // Method getTypeStub:()Lnet/bytebuddy/description/type/TypeDescription;
     432: aastore
     433: dup
     434: iconst_2
     435: ldc_w         #257                // class java/io/Serializable
     438: invokestatic  #161                // Method net/bytebuddy/description/type/TypeDescription$ForLoadedType.of:(Ljava/lang/Class;)Lnet/bytebuddy/description/type/TypeDescription;
     441: aastore
     442: invokespecial #184                // Method "<init>":(Ljava/lang/String;ILjava/lang/String;ILnet/bytebuddy/description/type/TypeDefinition;[Lnet/bytebuddy/description/type/TypeDefinition;)V
     445: putstatic     #259                // Field METHOD_TYPE:Lnet/bytebuddy/utility/JavaType;
     448: new           #2                  // class net/bytebuddy/utility/JavaType
     451: dup
     452: ldc_w         #260                // String METHOD_HANDLES_LOOKUP
     455: bipush        13
     457: ldc_w         #262                // String java.lang.invoke.MethodHandles$Lookup
     460: bipush        25
     462: ldc           #246                // class java/lang/Object
     464: iconst_0
     465: anewarray     #248                // class java/lang/reflect/Type
     468: invokespecial #250                // Method "<init>":(Ljava/lang/String;ILjava/lang/String;ILjava/lang/reflect/Type;[Ljava/lang/reflect/Type;)V
     471: putstatic     #264                // Field METHOD_HANDLES_LOOKUP:Lnet/bytebuddy/utility/JavaType;
     474: new           #2                  // class net/bytebuddy/utility/JavaType
     477: dup
     478: ldc_w         #265                // String CALL_SITE
     481: bipush        14
     483: ldc_w         #267                // String java.lang.invoke.CallSite
     486: sipush        1025
     489: ldc           #246                // class java/lang/Object
     491: iconst_0
     492: anewarray     #248                // class java/lang/reflect/Type
     495: invokespecial #250                // Method "<init>":(Ljava/lang/String;ILjava/lang/String;ILjava/lang/reflect/Type;[Ljava/lang/reflect/Type;)V
     498: putstatic     #269                // Field CALL_SITE:Lnet/bytebuddy/utility/JavaType;
     501: new           #2                  // class net/bytebuddy/utility/JavaType
     504: dup
     505: ldc_w         #270                // String VAR_HANDLE
     508: bipush        15
     510: ldc_w         #272                // String java.lang.invoke.VarHandle
     513: sipush        1025
     516: getstatic     #274                // Field net/bytebuddy/description/type/TypeDescription$Generic.OBJECT:Lnet/bytebuddy/description/type/TypeDescription$Generic;
     519: iconst_1
     520: anewarray     #33                 // class net/bytebuddy/description/type/TypeDefinition
     523: dup
     524: iconst_0
     525: getstatic     #186                // Field CONSTABLE:Lnet/bytebuddy/utility/JavaType;
     528: invokevirtual #196                // Method getTypeStub:()Lnet/bytebuddy/description/type/TypeDescription;
     531: aastore
     532: invokespecial #184                // Method "<init>":(Ljava/lang/String;ILjava/lang/String;ILnet/bytebuddy/description/type/TypeDefinition;[Lnet/bytebuddy/description/type/TypeDefinition;)V
     535: putstatic     #276                // Field VAR_HANDLE:Lnet/bytebuddy/utility/JavaType;
     538: new           #2                  // class net/bytebuddy/utility/JavaType
     541: dup
     542: ldc_w         #277                // String PARAMETER
     545: bipush        16
     547: ldc_w         #279                // String java.lang.reflect.Parameter
     550: bipush        17
     552: ldc           #246                // class java/lang/Object
     554: iconst_1
     555: anewarray     #248                // class java/lang/reflect/Type
     558: dup
     559: iconst_0
     560: ldc_w         #281                // class java/lang/reflect/AnnotatedElement
     563: aastore
     564: invokespecial #250                // Method "<init>":(Ljava/lang/String;ILjava/lang/String;ILjava/lang/reflect/Type;[Ljava/lang/reflect/Type;)V
     567: putstatic     #283                // Field PARAMETER:Lnet/bytebuddy/utility/JavaType;
     570: new           #2                  // class net/bytebuddy/utility/JavaType
     573: dup
     574: ldc_w         #284                // String EXECUTABLE
     577: bipush        17
     579: ldc_w         #286                // String java.lang.reflect.Executable
     582: sipush        1025
     585: ldc_w         #288                // class java/lang/reflect/AccessibleObject
     588: iconst_2
     589: anewarray     #248                // class java/lang/reflect/Type
     592: dup
     593: iconst_0
     594: ldc_w         #290                // class java/lang/reflect/Member
     597: aastore
     598: dup
     599: iconst_1
     600: ldc_w         #292                // class java/lang/reflect/GenericDeclaration
     603: aastore
     604: invokespecial #250                // Method "<init>":(Ljava/lang/String;ILjava/lang/String;ILjava/lang/reflect/Type;[Ljava/lang/reflect/Type;)V
     607: putstatic     #294                // Field EXECUTABLE:Lnet/bytebuddy/utility/JavaType;
     610: new           #2                  // class net/bytebuddy/utility/JavaType
     613: dup
     614: ldc_w         #295                // String MODULE
     617: bipush        18
     619: ldc_w         #297                // String java.lang.Module
     622: bipush        17
     624: ldc           #246                // class java/lang/Object
     626: iconst_1
     627: anewarray     #248                // class java/lang/reflect/Type
     630: dup
     631: iconst_0
     632: ldc_w         #281                // class java/lang/reflect/AnnotatedElement
     635: aastore
     636: invokespecial #250                // Method "<init>":(Ljava/lang/String;ILjava/lang/String;ILjava/lang/reflect/Type;[Ljava/lang/reflect/Type;)V
     639: putstatic     #299                // Field MODULE:Lnet/bytebuddy/utility/JavaType;
     642: bipush        19
     644: anewarray     #2                  // class net/bytebuddy/utility/JavaType
     647: dup
     648: iconst_0
     649: getstatic     #186                // Field CONSTABLE:Lnet/bytebuddy/utility/JavaType;
     652: aastore
     653: dup
     654: iconst_1
     655: getstatic     #191                // Field TYPE_DESCRIPTOR:Lnet/bytebuddy/utility/JavaType;
     658: aastore
     659: dup
     660: iconst_2
     661: getstatic     #198                // Field TYPE_DESCRIPTOR_OF_FIELD:Lnet/bytebuddy/utility/JavaType;
     664: aastore
     665: dup
     666: iconst_3
     667: getstatic     #203                // Field TYPE_DESCRIPTOR_OF_METHOD:Lnet/bytebuddy/utility/JavaType;
     670: aastore
     671: dup
     672: iconst_4
     673: getstatic     #208                // Field CONSTANT_DESCRIPTION:Lnet/bytebuddy/utility/JavaType;
     676: aastore
     677: dup
     678: iconst_5
     679: getstatic     #216                // Field DYNAMIC_CONSTANT_DESCRIPTION:Lnet/bytebuddy/utility/JavaType;
     682: aastore
     683: dup
     684: bipush        6
     686: getstatic     #221                // Field CLASS_DESCRIPTION:Lnet/bytebuddy/utility/JavaType;
     689: aastore
     690: dup
     691: bipush        7
     693: getstatic     #226                // Field METHOD_TYPE_DESCRIPTION:Lnet/bytebuddy/utility/JavaType;
     696: aastore
     697: dup
     698: bipush        8
     700: getstatic     #231                // Field METHOD_HANDLE_DESCRIPTION:Lnet/bytebuddy/utility/JavaType;
     703: aastore
     704: dup
     705: bipush        9
     707: getstatic     #236                // Field DIRECT_METHOD_HANDLE_DESCRIPTION:Lnet/bytebuddy/utility/JavaType;
     710: aastore
     711: dup
     712: bipush        10
     714: getstatic     #241                // Field METHOD_HANDLE:Lnet/bytebuddy/utility/JavaType;
     717: aastore
     718: dup
     719: bipush        11
     721: getstatic     #252                // Field METHOD_HANDLES:Lnet/bytebuddy/utility/JavaType;
     724: aastore
     725: dup
     726: bipush        12
     728: getstatic     #259                // Field METHOD_TYPE:Lnet/bytebuddy/utility/JavaType;
     731: aastore
     732: dup
     733: bipush        13
     735: getstatic     #264                // Field METHOD_HANDLES_LOOKUP:Lnet/bytebuddy/utility/JavaType;
     738: aastore
     739: dup
     740: bipush        14
     742: getstatic     #269                // Field CALL_SITE:Lnet/bytebuddy/utility/JavaType;
     745: aastore
     746: dup
     747: bipush        15
     749: getstatic     #276                // Field VAR_HANDLE:Lnet/bytebuddy/utility/JavaType;
     752: aastore
     753: dup
     754: bipush        16
     756: getstatic     #283                // Field PARAMETER:Lnet/bytebuddy/utility/JavaType;
     759: aastore
     760: dup
     761: bipush        17
     763: getstatic     #294                // Field EXECUTABLE:Lnet/bytebuddy/utility/JavaType;
     766: aastore
     767: dup
     768: bipush        18
     770: getstatic     #299                // Field MODULE:Lnet/bytebuddy/utility/JavaType;
     773: aastore
     774: putstatic     #69                 // Field $VALUES:[Lnet/bytebuddy/utility/JavaType;
     777: return
     778: goto          3
}
