Compiled from "JavaConstant.java"
public class net.bytebuddy.utility.JavaConstant$MethodType implements net.bytebuddy.utility.JavaConstant {
  private static final net.bytebuddy.utility.JavaConstant$MethodType$Dispatcher DISPATCHER;

  private final net.bytebuddy.description.type.TypeDescription returnType;

  private final java.util.List<? extends net.bytebuddy.description.type.TypeDescription> parameterTypes;

  protected net.bytebuddy.utility.JavaConstant$MethodType(net.bytebuddy.description.type.TypeDescription, java.util.List<? extends net.bytebuddy.description.type.TypeDescription>);
    Code:
       0: aload_0
       1: invokespecial #58                 // Method java/lang/Object."<init>":()V
       4: aload_0
       5: aload_1
       6: putfield      #60                 // Field returnType:Lnet/bytebuddy/description/type/TypeDescription;
       9: aload_0
      10: aload_2
      11: putfield      #62                 // Field parameterTypes:Ljava/util/List;
      14: return

  public static net.bytebuddy.utility.JavaConstant$MethodType ofLoaded(java.lang.Object);
    Code:
       0: getstatic     #72                 // Field net/bytebuddy/utility/JavaType.METHOD_TYPE:Lnet/bytebuddy/utility/JavaType;
       3: aload_0
       4: invokevirtual #76                 // Method net/bytebuddy/utility/JavaType.isInstance:(Ljava/lang/Object;)Z
       7: ifne          37
      10: new           #78                 // class java/lang/IllegalArgumentException
      13: dup
      14: new           #80                 // class java/lang/StringBuilder
      17: dup
      18: invokespecial #81                 // Method java/lang/StringBuilder."<init>":()V
      21: ldc           #83                 // String Expected method type object:
      23: invokevirtual #87                 // Method java/lang/StringBuilder.append:(Ljava/lang/String;)Ljava/lang/StringBuilder;
      26: aload_0
      27: invokevirtual #90                 // Method java/lang/StringBuilder.append:(Ljava/lang/Object;)Ljava/lang/StringBuilder;
      30: invokevirtual #94                 // Method java/lang/StringBuilder.toString:()Ljava/lang/String;
      33: invokespecial #97                 // Method java/lang/IllegalArgumentException."<init>":(Ljava/lang/String;)V
      36: athrow
      37: getstatic     #99                 // Field DISPATCHER:Lnet/bytebuddy/utility/JavaConstant$MethodType$Dispatcher;
      40: aload_0
      41: invokeinterface #102,  2          // InterfaceMethod net/bytebuddy/utility/JavaConstant$MethodType$Dispatcher.returnType:(Ljava/lang/Object;)Ljava/lang/Class;
      46: getstatic     #99                 // Field DISPATCHER:Lnet/bytebuddy/utility/JavaConstant$MethodType$Dispatcher;
      49: aload_0
      50: invokeinterface #106,  2          // InterfaceMethod net/bytebuddy/utility/JavaConstant$MethodType$Dispatcher.parameterArray:(Ljava/lang/Object;)[Ljava/lang/Class;
      55: invokestatic  #110                // Method of:(Ljava/lang/Class;[Ljava/lang/Class;)Lnet/bytebuddy/utility/JavaConstant$MethodType;
      58: areturn

  public static net.bytebuddy.utility.JavaConstant$MethodType of(java.lang.Class<?>, java.lang.Class<?>...);
    Code:
       0: aload_0
       1: invokestatic  #116                // Method net/bytebuddy/description/type/TypeDescription$ForLoadedType.of:(Ljava/lang/Class;)Lnet/bytebuddy/description/type/TypeDescription;
       4: new           #13                 // class net/bytebuddy/description/type/TypeList$ForLoadedTypes
       7: dup
       8: aload_1
       9: invokespecial #119                // Method net/bytebuddy/description/type/TypeList$ForLoadedTypes."<init>":([Ljava/lang/Class;)V
      12: invokestatic  #122                // Method of:(Lnet/bytebuddy/description/type/TypeDescription;Ljava/util/List;)Lnet/bytebuddy/utility/JavaConstant$MethodType;
      15: areturn

  public static net.bytebuddy.utility.JavaConstant$MethodType of(net.bytebuddy.description.type.TypeDescription, java.util.List<? extends net.bytebuddy.description.type.TypeDescription>);
    Code:
       0: new           #2                  // class net/bytebuddy/utility/JavaConstant$MethodType
       3: dup
       4: aload_0
       5: aload_1
       6: invokespecial #130                // Method "<init>":(Lnet/bytebuddy/description/type/TypeDescription;Ljava/util/List;)V
       9: areturn

  public static net.bytebuddy.utility.JavaConstant$MethodType of(java.lang.reflect.Method);
    Code:
       0: new           #18                 // class net/bytebuddy/description/method/MethodDescription$ForLoadedMethod
       3: dup
       4: aload_0
       5: invokespecial #134                // Method net/bytebuddy/description/method/MethodDescription$ForLoadedMethod."<init>":(Ljava/lang/reflect/Method;)V
       8: invokestatic  #137                // Method of:(Lnet/bytebuddy/description/method/MethodDescription;)Lnet/bytebuddy/utility/JavaConstant$MethodType;
      11: areturn

  public static net.bytebuddy.utility.JavaConstant$MethodType of(java.lang.reflect.Constructor<?>);
    Code:
       0: new           #23                 // class net/bytebuddy/description/method/MethodDescription$ForLoadedConstructor
       3: dup
       4: aload_0
       5: invokespecial #144                // Method net/bytebuddy/description/method/MethodDescription$ForLoadedConstructor."<init>":(Ljava/lang/reflect/Constructor;)V
       8: invokestatic  #137                // Method of:(Lnet/bytebuddy/description/method/MethodDescription;)Lnet/bytebuddy/utility/JavaConstant$MethodType;
      11: areturn

  public static net.bytebuddy.utility.JavaConstant$MethodType of(net.bytebuddy.description.method.MethodDescription);
    Code:
       0: new           #2                  // class net/bytebuddy/utility/JavaConstant$MethodType
       3: dup
       4: aload_0
       5: invokeinterface #151,  1          // InterfaceMethod net/bytebuddy/description/method/MethodDescription.getReturnType:()Lnet/bytebuddy/description/type/TypeDescription$Generic;
      10: invokeinterface #155,  1          // InterfaceMethod net/bytebuddy/description/type/TypeDescription$Generic.asErasure:()Lnet/bytebuddy/description/type/TypeDescription;
      15: aload_0
      16: invokeinterface #159,  1          // InterfaceMethod net/bytebuddy/description/method/MethodDescription.getParameters:()Lnet/bytebuddy/description/method/ParameterList;
      21: invokeinterface #165,  1          // InterfaceMethod net/bytebuddy/description/method/ParameterList.asTypeList:()Lnet/bytebuddy/description/type/TypeList$Generic;
      26: invokeinterface #169,  1          // InterfaceMethod net/bytebuddy/description/type/TypeList$Generic.asErasures:()Lnet/bytebuddy/description/type/TypeList;
      31: invokespecial #130                // Method "<init>":(Lnet/bytebuddy/description/type/TypeDescription;Ljava/util/List;)V
      34: areturn

  public static net.bytebuddy.utility.JavaConstant$MethodType ofSetter(java.lang.reflect.Field);
    Code:
       0: new           #26                 // class net/bytebuddy/description/field/FieldDescription$ForLoadedField
       3: dup
       4: aload_0
       5: invokespecial #176                // Method net/bytebuddy/description/field/FieldDescription$ForLoadedField."<init>":(Ljava/lang/reflect/Field;)V
       8: invokestatic  #179                // Method ofSetter:(Lnet/bytebuddy/description/field/FieldDescription;)Lnet/bytebuddy/utility/JavaConstant$MethodType;
      11: areturn

  public static net.bytebuddy.utility.JavaConstant$MethodType ofSetter(net.bytebuddy.description.field.FieldDescription);
    Code:
       0: new           #2                  // class net/bytebuddy/utility/JavaConstant$MethodType
       3: dup
       4: getstatic     #184                // Field net/bytebuddy/description/type/TypeDescription.VOID:Lnet/bytebuddy/description/type/TypeDescription;
       7: aload_0
       8: invokeinterface #187,  1          // InterfaceMethod net/bytebuddy/description/field/FieldDescription.getType:()Lnet/bytebuddy/description/type/TypeDescription$Generic;
      13: invokeinterface #155,  1          // InterfaceMethod net/bytebuddy/description/type/TypeDescription$Generic.asErasure:()Lnet/bytebuddy/description/type/TypeDescription;
      18: invokestatic  #193                // Method java/util/Collections.singletonList:(Ljava/lang/Object;)Ljava/util/List;
      21: invokespecial #130                // Method "<init>":(Lnet/bytebuddy/description/type/TypeDescription;Ljava/util/List;)V
      24: areturn

  public static net.bytebuddy.utility.JavaConstant$MethodType ofGetter(java.lang.reflect.Field);
    Code:
       0: new           #26                 // class net/bytebuddy/description/field/FieldDescription$ForLoadedField
       3: dup
       4: aload_0
       5: invokespecial #176                // Method net/bytebuddy/description/field/FieldDescription$ForLoadedField."<init>":(Ljava/lang/reflect/Field;)V
       8: invokestatic  #198                // Method ofGetter:(Lnet/bytebuddy/description/field/FieldDescription;)Lnet/bytebuddy/utility/JavaConstant$MethodType;
      11: areturn

  public static net.bytebuddy.utility.JavaConstant$MethodType ofGetter(net.bytebuddy.description.field.FieldDescription);
    Code:
       0: new           #2                  // class net/bytebuddy/utility/JavaConstant$MethodType
       3: dup
       4: aload_0
       5: invokeinterface #187,  1          // InterfaceMethod net/bytebuddy/description/field/FieldDescription.getType:()Lnet/bytebuddy/description/type/TypeDescription$Generic;
      10: invokeinterface #155,  1          // InterfaceMethod net/bytebuddy/description/type/TypeDescription$Generic.asErasure:()Lnet/bytebuddy/description/type/TypeDescription;
      15: invokestatic  #202                // Method java/util/Collections.emptyList:()Ljava/util/List;
      18: invokespecial #130                // Method "<init>":(Lnet/bytebuddy/description/type/TypeDescription;Ljava/util/List;)V
      21: areturn

  public static net.bytebuddy.utility.JavaConstant$MethodType ofConstant(java.lang.Object);
    Code:
       0: aload_0
       1: invokevirtual #207                // Method java/lang/Object.getClass:()Ljava/lang/Class;
       4: invokestatic  #210                // Method ofConstant:(Ljava/lang/Class;)Lnet/bytebuddy/utility/JavaConstant$MethodType;
       7: areturn

  public static net.bytebuddy.utility.JavaConstant$MethodType ofConstant(java.lang.Class<?>);
    Code:
       0: aload_0
       1: invokestatic  #116                // Method net/bytebuddy/description/type/TypeDescription$ForLoadedType.of:(Ljava/lang/Class;)Lnet/bytebuddy/description/type/TypeDescription;
       4: invokestatic  #215                // Method ofConstant:(Lnet/bytebuddy/description/type/TypeDescription;)Lnet/bytebuddy/utility/JavaConstant$MethodType;
       7: areturn

  public static net.bytebuddy.utility.JavaConstant$MethodType ofConstant(net.bytebuddy.description.type.TypeDescription);
    Code:
       0: new           #2                  // class net/bytebuddy/utility/JavaConstant$MethodType
       3: dup
       4: aload_0
       5: invokestatic  #202                // Method java/util/Collections.emptyList:()Ljava/util/List;
       8: invokespecial #130                // Method "<init>":(Lnet/bytebuddy/description/type/TypeDescription;Ljava/util/List;)V
      11: areturn

  public net.bytebuddy.description.type.TypeDescription getReturnType();
    Code:
       0: aload_0
       1: getfield      #60                 // Field returnType:Lnet/bytebuddy/description/type/TypeDescription;
       4: areturn

  public net.bytebuddy.description.type.TypeList getParameterTypes();
    Code:
       0: new           #31                 // class net/bytebuddy/description/type/TypeList$Explicit
       3: dup
       4: aload_0
       5: getfield      #62                 // Field parameterTypes:Ljava/util/List;
       8: invokespecial #221                // Method net/bytebuddy/description/type/TypeList$Explicit."<init>":(Ljava/util/List;)V
      11: areturn

  public java.lang.String getDescriptor();
    Code:
       0: new           #80                 // class java/lang/StringBuilder
       3: dup
       4: ldc           #224                // String (
       6: invokespecial #225                // Method java/lang/StringBuilder."<init>":(Ljava/lang/String;)V
       9: astore_1
      10: aload_0
      11: getfield      #62                 // Field parameterTypes:Ljava/util/List;
      14: invokeinterface #231,  1          // InterfaceMethod java/util/List.iterator:()Ljava/util/Iterator;
      19: astore_2
      20: aload_2
      21: invokeinterface #237,  1          // InterfaceMethod java/util/Iterator.hasNext:()Z
      26: ifeq          53
      29: aload_2
      30: invokeinterface #241,  1          // InterfaceMethod java/util/Iterator.next:()Ljava/lang/Object;
      35: checkcast     #36                 // class net/bytebuddy/description/type/TypeDescription
      38: astore_3
      39: aload_1
      40: aload_3
      41: invokeinterface #243,  1          // InterfaceMethod net/bytebuddy/description/type/TypeDescription.getDescriptor:()Ljava/lang/String;
      46: invokevirtual #87                 // Method java/lang/StringBuilder.append:(Ljava/lang/String;)Ljava/lang/StringBuilder;
      49: pop
      50: goto          20
      53: aload_1
      54: bipush        41
      56: invokevirtual #246                // Method java/lang/StringBuilder.append:(C)Ljava/lang/StringBuilder;
      59: aload_0
      60: getfield      #60                 // Field returnType:Lnet/bytebuddy/description/type/TypeDescription;
      63: invokeinterface #243,  1          // InterfaceMethod net/bytebuddy/description/type/TypeDescription.getDescriptor:()Ljava/lang/String;
      68: invokevirtual #87                 // Method java/lang/StringBuilder.append:(Ljava/lang/String;)Ljava/lang/StringBuilder;
      71: invokevirtual #94                 // Method java/lang/StringBuilder.toString:()Ljava/lang/String;
      74: areturn

  public java.lang.Object asConstantPoolValue();
    Code:
       0: new           #80                 // class java/lang/StringBuilder
       3: dup
       4: invokespecial #81                 // Method java/lang/StringBuilder."<init>":()V
       7: bipush        40
       9: invokevirtual #246                // Method java/lang/StringBuilder.append:(C)Ljava/lang/StringBuilder;
      12: astore_1
      13: aload_0
      14: invokevirtual #251                // Method getParameterTypes:()Lnet/bytebuddy/description/type/TypeList;
      17: invokeinterface #252,  1          // InterfaceMethod net/bytebuddy/description/type/TypeList.iterator:()Ljava/util/Iterator;
      22: astore_2
      23: aload_2
      24: invokeinterface #237,  1          // InterfaceMethod java/util/Iterator.hasNext:()Z
      29: ifeq          56
      32: aload_2
      33: invokeinterface #241,  1          // InterfaceMethod java/util/Iterator.next:()Ljava/lang/Object;
      38: checkcast     #36                 // class net/bytebuddy/description/type/TypeDescription
      41: astore_3
      42: aload_1
      43: aload_3
      44: invokeinterface #243,  1          // InterfaceMethod net/bytebuddy/description/type/TypeDescription.getDescriptor:()Ljava/lang/String;
      49: invokevirtual #87                 // Method java/lang/StringBuilder.append:(Ljava/lang/String;)Ljava/lang/StringBuilder;
      52: pop
      53: goto          23
      56: aload_1
      57: bipush        41
      59: invokevirtual #246                // Method java/lang/StringBuilder.append:(C)Ljava/lang/StringBuilder;
      62: aload_0
      63: invokevirtual #254                // Method getReturnType:()Lnet/bytebuddy/description/type/TypeDescription;
      66: invokeinterface #243,  1          // InterfaceMethod net/bytebuddy/description/type/TypeDescription.getDescriptor:()Ljava/lang/String;
      71: invokevirtual #87                 // Method java/lang/StringBuilder.append:(Ljava/lang/String;)Ljava/lang/StringBuilder;
      74: invokevirtual #94                 // Method java/lang/StringBuilder.toString:()Ljava/lang/String;
      77: invokestatic  #260                // Method net/bytebuddy/jar/asm/Type.getMethodType:(Ljava/lang/String;)Lnet/bytebuddy/jar/asm/Type;
      80: areturn

  public net.bytebuddy.description.type.TypeDescription getType();
    Code:
       0: getstatic     #72                 // Field net/bytebuddy/utility/JavaType.METHOD_TYPE:Lnet/bytebuddy/utility/JavaType;
       3: invokevirtual #263                // Method net/bytebuddy/utility/JavaType.getTypeStub:()Lnet/bytebuddy/description/type/TypeDescription;
       6: areturn

  public int hashCode();
    Code:
       0: aload_0
       1: getfield      #60                 // Field returnType:Lnet/bytebuddy/description/type/TypeDescription;
       4: invokevirtual #267                // Method java/lang/Object.hashCode:()I
       7: istore_1
       8: bipush        31
      10: iload_1
      11: imul
      12: aload_0
      13: getfield      #62                 // Field parameterTypes:Ljava/util/List;
      16: invokeinterface #268,  1          // InterfaceMethod java/util/List.hashCode:()I
      21: iadd
      22: istore_1
      23: iload_1
      24: ireturn

  public boolean equals(java.lang.Object);
    Code:
       0: aload_0
       1: aload_1
       2: if_acmpne     7
       5: iconst_1
       6: ireturn
       7: aload_1
       8: instanceof    #2                  // class net/bytebuddy/utility/JavaConstant$MethodType
      11: ifne          16
      14: iconst_0
      15: ireturn
      16: aload_1
      17: checkcast     #2                  // class net/bytebuddy/utility/JavaConstant$MethodType
      20: astore_2
      21: aload_0
      22: getfield      #62                 // Field parameterTypes:Ljava/util/List;
      25: aload_2
      26: getfield      #62                 // Field parameterTypes:Ljava/util/List;
      29: invokeinterface #273,  2          // InterfaceMethod java/util/List.equals:(Ljava/lang/Object;)Z
      34: ifeq          55
      37: aload_0
      38: getfield      #60                 // Field returnType:Lnet/bytebuddy/description/type/TypeDescription;
      41: aload_2
      42: getfield      #60                 // Field returnType:Lnet/bytebuddy/description/type/TypeDescription;
      45: invokevirtual #274                // Method java/lang/Object.equals:(Ljava/lang/Object;)Z
      48: ifeq          55
      51: iconst_1
      52: goto          56
      55: iconst_0
      56: ireturn

  static {};
    Code:
       0: getstatic     #280                // Field net/bytebuddy/utility/JavaConstant$MethodType$Dispatcher$CreationAction.INSTANCE:Lnet/bytebuddy/utility/JavaConstant$MethodType$Dispatcher$CreationAction;
       3: invokestatic  #286                // Method java/security/AccessController.doPrivileged:(Ljava/security/PrivilegedAction;)Ljava/lang/Object;
       6: checkcast     #10                 // class net/bytebuddy/utility/JavaConstant$MethodType$Dispatcher
       9: putstatic     #99                 // Field DISPATCHER:Lnet/bytebuddy/utility/JavaConstant$MethodType$Dispatcher;
      12: return
}
