Compiled from "PlatformDependent0.java"
final class io.netty.util.internal.PlatformDependent0$7 implements java.security.PrivilegedAction<java.lang.Object> {
  final java.lang.Object val$finalInternalUnsafe;

  io.netty.util.internal.PlatformDependent0$7(java.lang.Object);
    Code:
       0: aload_0
       1: aload_1
       2: putfield      #16                 // Field val$finalInternalUnsafe:Ljava/lang/Object;
       5: aload_0
       6: invokespecial #19                 // Method java/lang/Object."<init>":()V
       9: return

  public java.lang.Object run();
    Code:
       0: aload_0
       1: getfield      #16                 // Field val$finalInternalUnsafe:Ljava/lang/Object;
       4: invokevirtual #31                 // Method java/lang/Object.getClass:()Ljava/lang/Class;
       7: ldc           #33                 // String allocateUninitializedArray
       9: iconst_2
      10: anewarray     #35                 // class java/lang/Class
      13: dup
      14: iconst_0
      15: ldc           #35                 // class java/lang/Class
      17: aastore
      18: dup
      19: iconst_1
      20: getstatic     #41                 // Field java/lang/Integer.TYPE:Ljava/lang/Class;
      23: aastore
      24: invokevirtual #45                 // Method java/lang/Class.getDeclaredMethod:(Ljava/lang/String;[Ljava/lang/Class;)Ljava/lang/reflect/Method;
      27: areturn
      28: astore_1
      29: aload_1
      30: areturn
      31: astore_1
      32: aload_1
      33: areturn
    Exception table:
       from    to  target type
           0    27    28   Class java/lang/NoSuchMethodException
           0    27    31   Class java/lang/SecurityException
}
