Compiled from "CompactionStopStyle.java"
public final class org.rocksdb.CompactionStopStyle extends java.lang.Enum<org.rocksdb.CompactionStopStyle> {
  public static final org.rocksdb.CompactionStopStyle CompactionStopStyleSimilarSize;

  public static final org.rocksdb.CompactionStopStyle CompactionStopStyleTotalSize;

  private final byte value;

  private static final org.rocksdb.CompactionStopStyle[] $VALUES;

  public static org.rocksdb.CompactionStopStyle[] values();
    Code:
       0: getstatic     #1                  // Field $VALUES:[Lorg/rocksdb/CompactionStopStyle;
       3: invokevirtual #2                  // Method "[Lorg/rocksdb/CompactionStopStyle;".clone:()Ljava/lang/Object;
       6: checkcast     #3                  // class "[Lorg/rocksdb/CompactionStopStyle;"
       9: areturn

  public static org.rocksdb.CompactionStopStyle valueOf(java.lang.String);
    Code:
       0: ldc_w         #4                  // class org/rocksdb/CompactionStopStyle
       3: aload_0
       4: invokestatic  #5                  // Method java/lang/Enum.valueOf:(Ljava/lang/Class;Ljava/lang/String;)Ljava/lang/Enum;
       7: checkcast     #4                  // class org/rocksdb/CompactionStopStyle
      10: areturn

  private org.rocksdb.CompactionStopStyle(byte);
    Code:
       0: aload_0
       1: aload_1
       2: iload_2
       3: invokespecial #6                  // Method java/lang/Enum."<init>":(Ljava/lang/String;I)V
       6: aload_0
       7: iload_3
       8: putfield      #7                  // Field value:B
      11: return

  public byte getValue();
    Code:
       0: aload_0
       1: getfield      #7                  // Field value:B
       4: ireturn

  public static org.rocksdb.CompactionStopStyle getCompactionStopStyle(byte);
    Code:
       0: invokestatic  #8                  // Method values:()[Lorg/rocksdb/CompactionStopStyle;
       3: astore_1
       4: aload_1
       5: arraylength
       6: istore_2
       7: iconst_0
       8: istore_3
       9: iload_3
      10: iload_2
      11: if_icmpge     37
      14: aload_1
      15: iload_3
      16: aaload
      17: astore        4
      19: aload         4
      21: invokevirtual #9                  // Method getValue:()B
      24: iload_0
      25: if_icmpne     31
      28: aload         4
      30: areturn
      31: iinc          3, 1
      34: goto          9
      37: new           #10                 // class java/lang/IllegalArgumentException
      40: dup
      41: ldc           #11                 // String Illegal value provided for CompactionStopStyle.
      43: invokespecial #12                 // Method java/lang/IllegalArgumentException."<init>":(Ljava/lang/String;)V
      46: athrow

  static {};
    Code:
       0: new           #4                  // class org/rocksdb/CompactionStopStyle
       3: dup
       4: ldc           #13                 // String CompactionStopStyleSimilarSize
       6: iconst_0
       7: iconst_0
       8: invokespecial #14                 // Method "<init>":(Ljava/lang/String;IB)V
      11: putstatic     #15                 // Field CompactionStopStyleSimilarSize:Lorg/rocksdb/CompactionStopStyle;
      14: new           #4                  // class org/rocksdb/CompactionStopStyle
      17: dup
      18: ldc           #16                 // String CompactionStopStyleTotalSize
      20: iconst_1
      21: iconst_1
      22: invokespecial #14                 // Method "<init>":(Ljava/lang/String;IB)V
      25: putstatic     #17                 // Field CompactionStopStyleTotalSize:Lorg/rocksdb/CompactionStopStyle;
      28: iconst_2
      29: anewarray     #4                  // class org/rocksdb/CompactionStopStyle
      32: dup
      33: iconst_0
      34: getstatic     #15                 // Field CompactionStopStyleSimilarSize:Lorg/rocksdb/CompactionStopStyle;
      37: aastore
      38: dup
      39: iconst_1
      40: getstatic     #17                 // Field CompactionStopStyleTotalSize:Lorg/rocksdb/CompactionStopStyle;
      43: aastore
      44: putstatic     #1                  // Field $VALUES:[Lorg/rocksdb/CompactionStopStyle;
      47: return
}
