Compiled from "LRUCache.java"
public class org.rocksdb.LRUCache extends org.rocksdb.Cache {
  public org.rocksdb.LRUCache(long);
    Code:
       0: aload_0
       1: lload_1
       2: iconst_m1
       3: iconst_0
       4: dconst_0
       5: invokespecial #1                  // Method "<init>":(JIZD)V
       8: return

  public org.rocksdb.LRUCache(long, int);
    Code:
       0: aload_0
       1: lload_1
       2: iload_3
       3: iconst_0
       4: dconst_0
       5: invokestatic  #2                  // Method newLRUCache:(JIZD)J
       8: invokespecial #3                  // Method org/rocksdb/Cache."<init>":(J)V
      11: return

  public org.rocksdb.LRUCache(long, int, boolean);
    Code:
       0: aload_0
       1: lload_1
       2: iload_3
       3: iload         4
       5: dconst_0
       6: invokestatic  #2                  // Method newLRUCache:(JIZD)J
       9: invokespecial #3                  // Method org/rocksdb/Cache."<init>":(J)V
      12: return

  public org.rocksdb.LRUCache(long, int, boolean, double);
    Code:
       0: aload_0
       1: lload_1
       2: iload_3
       3: iload         4
       5: dload         5
       7: invokestatic  #2                  // Method newLRUCache:(JIZD)J
      10: invokespecial #3                  // Method org/rocksdb/Cache."<init>":(J)V
      13: return

  private static native long newLRUCache(long, int, boolean, double);

  protected final native void disposeInternal(long);
}
