Compiled from "TestMapReduceExamples.java"
class org.apache.hadoop.hbase.mapreduce.TestMapReduceExamples$2 implements org.mockito.stubbing.Answer<java.lang.Void> {
  final org.apache.hadoop.hbase.mapreduce.TestMapReduceExamples this$0;

  org.apache.hadoop.hbase.mapreduce.TestMapReduceExamples$2(org.apache.hadoop.hbase.mapreduce.TestMapReduceExamples);
    Code:
       0: aload_0
       1: aload_1
       2: putfield      #1                  // Field this$0:Lorg/apache/hadoop/hbase/mapreduce/TestMapReduceExamples;
       5: aload_0
       6: invokespecial #2                  // Method java/lang/Object."<init>":()V
       9: return

  public java.lang.Void answer(org.mockito.invocation.InvocationOnMock) throws java.lang.Throwable;
    Code:
       0: aload_1
       1: iconst_0
       2: invokeinterface #3,  2            // InterfaceMethod org/mockito/invocation/InvocationOnMock.getArgument:(I)Ljava/lang/Object;
       7: checkcast     #4                  // class org/apache/hadoop/hbase/io/ImmutableBytesWritable
      10: astore_2
      11: aload_1
      12: iconst_1
      13: invokeinterface #3,  2            // InterfaceMethod org/mockito/invocation/InvocationOnMock.getArgument:(I)Ljava/lang/Object;
      18: checkcast     #5                  // class org/apache/hadoop/hbase/client/Put
      21: astore_3
      22: ldc           #6                  // String tableName-column1
      24: aload_2
      25: invokevirtual #7                  // Method org/apache/hadoop/hbase/io/ImmutableBytesWritable.get:()[B
      28: invokestatic  #8                  // Method org/apache/hadoop/hbase/util/Bytes.toString:([B)Ljava/lang/String;
      31: invokestatic  #9                  // Method org/junit/Assert.assertEquals:(Ljava/lang/Object;Ljava/lang/Object;)V
      34: ldc           #10                 // String test
      36: aload_3
      37: invokevirtual #11                 // Method org/apache/hadoop/hbase/client/Put.getRow:()[B
      40: invokestatic  #8                  // Method org/apache/hadoop/hbase/util/Bytes.toString:([B)Ljava/lang/String;
      43: invokestatic  #9                  // Method org/junit/Assert.assertEquals:(Ljava/lang/Object;Ljava/lang/Object;)V
      46: aconst_null
      47: areturn

  public java.lang.Object answer(org.mockito.invocation.InvocationOnMock) throws java.lang.Throwable;
    Code:
       0: aload_0
       1: aload_1
       2: invokevirtual #12                 // Method answer:(Lorg/mockito/invocation/InvocationOnMock;)Ljava/lang/Void;
       5: areturn
}
