public abstract class org.bouncycastle.crypto.fpe.FPEEngine {
  protected final org.bouncycastle.crypto.BlockCipher baseCipher;

  protected boolean forEncryption;

  protected org.bouncycastle.crypto.params.FPEParameters fpeParameters;

  protected org.bouncycastle.crypto.fpe.FPEEngine(org.bouncycastle.crypto.BlockCipher);
    Code:
       0: aload_0
       1: invokespecial #70                 // Method java/lang/Object."<init>":()V
       4: aload_0
       5: aload_1
       6: putfield      #65                 // Field baseCipher:Lorg/bouncycastle/crypto/BlockCipher;
       9: return

  public int processBlock(byte[], int, int, byte[], int);
    Code:
       0: aload_0
       1: getfield      #66                 // Field fpeParameters:Lorg/bouncycastle/crypto/params/FPEParameters;
       4: ifnonnull     17
       7: new           #42                 // class java/lang/IllegalStateException
      10: dup
      11: ldc           #1                  // String FPE engine not initialized
      13: invokespecial #68                 // Method java/lang/IllegalStateException."<init>":(Ljava/lang/String;)V
      16: athrow
      17: iload_3
      18: ifge          31
      21: new           #41                 // class java/lang/IllegalArgumentException
      24: dup
      25: ldc           #5                  // String input length cannot be negative
      27: invokespecial #67                 // Method java/lang/IllegalArgumentException."<init>":(Ljava/lang/String;)V
      30: athrow
      31: aload_1
      32: ifnull        40
      35: aload         4
      37: ifnonnull     50
      40: new           #43                 // class java/lang/NullPointerException
      43: dup
      44: ldc           #2                  // String buffer value is null
      46: invokespecial #69                 // Method java/lang/NullPointerException."<init>":(Ljava/lang/String;)V
      49: athrow
      50: aload_1
      51: arraylength
      52: iload_2
      53: iload_3
      54: iadd
      55: if_icmpge     68
      58: new           #45                 // class org/bouncycastle/crypto/DataLengthException
      61: dup
      62: ldc           #4                  // String input buffer too short
      64: invokespecial #71                 // Method org/bouncycastle/crypto/DataLengthException."<init>":(Ljava/lang/String;)V
      67: athrow
      68: aload         4
      70: arraylength
      71: iload         5
      73: iload_3
      74: iadd
      75: if_icmpge     88
      78: new           #46                 // class org/bouncycastle/crypto/OutputLengthException
      81: dup
      82: ldc           #6                  // String output buffer too short
      84: invokespecial #72                 // Method org/bouncycastle/crypto/OutputLengthException."<init>":(Ljava/lang/String;)V
      87: athrow
      88: aload_0
      89: getfield      #64                 // Field forEncryption:Z
      92: ifeq          107
      95: aload_0
      96: aload_1
      97: iload_2
      98: iload_3
      99: aload         4
     101: iload         5
     103: invokevirtual #74                 // Method encryptBlock:([BII[BI)I
     106: ireturn
     107: aload_0
     108: aload_1
     109: iload_2
     110: iload_3
     111: aload         4
     113: iload         5
     115: invokevirtual #73                 // Method decryptBlock:([BII[BI)I
     118: ireturn

  protected static short[] toShortArray(byte[]);
    Code:
       0: aload_0
       1: arraylength
       2: iconst_1
       3: iand
       4: ifeq          17
       7: new           #41                 // class java/lang/IllegalArgumentException
      10: dup
      11: ldc           #3                  // String data must be an even number of bytes for a wide radix
      13: invokespecial #67                 // Method java/lang/IllegalArgumentException."<init>":(Ljava/lang/String;)V
      16: athrow
      17: aload_0
      18: arraylength
      19: iconst_2
      20: idiv
      21: newarray       short
      23: astore_1
      24: iconst_0
      25: istore_2
      26: iload_2
      27: aload_1
      28: arraylength
      29: if_icmpeq     48
      32: aload_1
      33: iload_2
      34: aload_0
      35: iload_2
      36: iconst_2
      37: imul
      38: invokestatic  #76                 // Method org/bouncycastle/util/Pack.bigEndianToShort:([BI)S
      41: sastore
      42: iinc          2, 1
      45: goto          26
      48: aload_1
      49: areturn

  protected static byte[] toByteArray(short[]);
    Code:
       0: aload_0
       1: arraylength
       2: iconst_2
       3: imul
       4: newarray       byte
       6: astore_1
       7: iconst_0
       8: istore_2
       9: iload_2
      10: aload_0
      11: arraylength
      12: if_icmpeq     31
      15: aload_0
      16: iload_2
      17: saload
      18: aload_1
      19: iload_2
      20: iconst_2
      21: imul
      22: invokestatic  #75                 // Method org/bouncycastle/util/Pack.shortToBigEndian:(S[BI)V
      25: iinc          2, 1
      28: goto          9
      31: aload_1
      32: areturn

  public abstract void init(boolean, org.bouncycastle.crypto.CipherParameters);

  public abstract java.lang.String getAlgorithmName();

  protected abstract int encryptBlock(byte[], int, int, byte[], int);

  protected abstract int decryptBlock(byte[], int, int, byte[], int);
}
