Compiled from "LocalDateTimeUtils.java"
public class org.h2.util.LocalDateTimeUtils {
  public static final java.lang.Class<?> LOCAL_DATE;

  public static final java.lang.Class<?> LOCAL_TIME;

  public static final java.lang.Class<?> LOCAL_DATE_TIME;

  public static final java.lang.Class<?> INSTANT;

  public static final java.lang.Class<?> OFFSET_DATE_TIME;

  private static final java.lang.Class<?> ZONE_OFFSET;

  private static final java.lang.reflect.Method LOCAL_TIME_OF_NANO;

  private static final java.lang.reflect.Method LOCAL_TIME_TO_NANO;

  private static final java.lang.reflect.Method LOCAL_DATE_OF_YEAR_MONTH_DAY;

  private static final java.lang.reflect.Method LOCAL_DATE_PARSE;

  private static final java.lang.reflect.Method LOCAL_DATE_GET_YEAR;

  private static final java.lang.reflect.Method LOCAL_DATE_GET_MONTH_VALUE;

  private static final java.lang.reflect.Method LOCAL_DATE_GET_DAY_OF_MONTH;

  private static final java.lang.reflect.Method LOCAL_DATE_AT_START_OF_DAY;

  private static final java.lang.reflect.Method INSTANT_GET_EPOCH_SECOND;

  private static final java.lang.reflect.Method INSTANT_GET_NANO;

  private static final java.lang.reflect.Method TIMESTAMP_TO_INSTANT;

  private static final java.lang.reflect.Method LOCAL_TIME_PARSE;

  private static final java.lang.reflect.Method LOCAL_DATE_TIME_PLUS_NANOS;

  private static final java.lang.reflect.Method LOCAL_DATE_TIME_TO_LOCAL_DATE;

  private static final java.lang.reflect.Method LOCAL_DATE_TIME_TO_LOCAL_TIME;

  private static final java.lang.reflect.Method LOCAL_DATE_TIME_PARSE;

  private static final java.lang.reflect.Method ZONE_OFFSET_OF_TOTAL_SECONDS;

  private static final java.lang.reflect.Method OFFSET_DATE_TIME_OF_LOCAL_DATE_TIME_ZONE_OFFSET;

  private static final java.lang.reflect.Method OFFSET_DATE_TIME_PARSE;

  private static final java.lang.reflect.Method OFFSET_DATE_TIME_TO_LOCAL_DATE_TIME;

  private static final java.lang.reflect.Method OFFSET_DATE_TIME_GET_OFFSET;

  private static final java.lang.reflect.Method ZONE_OFFSET_GET_TOTAL_SECONDS;

  private static final boolean IS_JAVA8_DATE_API_PRESENT;

  private org.h2.util.LocalDateTimeUtils();
    Code:
       0: aload_0
       1: invokespecial #1                  // Method java/lang/Object."<init>":()V
       4: return

  public static boolean isJava8DateApiPresent();
    Code:
       0: getstatic     #2                  // Field IS_JAVA8_DATE_API_PRESENT:Z
       3: ireturn

  public static java.lang.Object parseLocalDate(java.lang.CharSequence);
    Code:
       0: getstatic     #3                  // Field LOCAL_DATE_PARSE:Ljava/lang/reflect/Method;
       3: aconst_null
       4: iconst_1
       5: anewarray     #4                  // class java/lang/Object
       8: dup
       9: iconst_0
      10: aload_0
      11: aastore
      12: invokevirtual #5                  // Method java/lang/reflect/Method.invoke:(Ljava/lang/Object;[Ljava/lang/Object;)Ljava/lang/Object;
      15: areturn
      16: astore_1
      17: new           #8                  // class java/lang/IllegalArgumentException
      20: dup
      21: new           #9                  // class java/lang/StringBuilder
      24: dup
      25: invokespecial #10                 // Method java/lang/StringBuilder."<init>":()V
      28: ldc           #11                 // String error when parsing text \'
      30: invokevirtual #12                 // Method java/lang/StringBuilder.append:(Ljava/lang/String;)Ljava/lang/StringBuilder;
      33: aload_0
      34: invokevirtual #13                 // Method java/lang/StringBuilder.append:(Ljava/lang/Object;)Ljava/lang/StringBuilder;
      37: ldc           #14                 // String \'
      39: invokevirtual #12                 // Method java/lang/StringBuilder.append:(Ljava/lang/String;)Ljava/lang/StringBuilder;
      42: invokevirtual #15                 // Method java/lang/StringBuilder.toString:()Ljava/lang/String;
      45: aload_1
      46: invokespecial #16                 // Method java/lang/IllegalArgumentException."<init>":(Ljava/lang/String;Ljava/lang/Throwable;)V
      49: athrow
    Exception table:
       from    to  target type
           0    15    16   Class java/lang/IllegalAccessException
           0    15    16   Class java/lang/reflect/InvocationTargetException

  public static java.lang.Object parseLocalTime(java.lang.CharSequence);
    Code:
       0: getstatic     #17                 // Field LOCAL_TIME_PARSE:Ljava/lang/reflect/Method;
       3: aconst_null
       4: iconst_1
       5: anewarray     #4                  // class java/lang/Object
       8: dup
       9: iconst_0
      10: aload_0
      11: aastore
      12: invokevirtual #5                  // Method java/lang/reflect/Method.invoke:(Ljava/lang/Object;[Ljava/lang/Object;)Ljava/lang/Object;
      15: areturn
      16: astore_1
      17: new           #8                  // class java/lang/IllegalArgumentException
      20: dup
      21: new           #9                  // class java/lang/StringBuilder
      24: dup
      25: invokespecial #10                 // Method java/lang/StringBuilder."<init>":()V
      28: ldc           #11                 // String error when parsing text \'
      30: invokevirtual #12                 // Method java/lang/StringBuilder.append:(Ljava/lang/String;)Ljava/lang/StringBuilder;
      33: aload_0
      34: invokevirtual #13                 // Method java/lang/StringBuilder.append:(Ljava/lang/Object;)Ljava/lang/StringBuilder;
      37: ldc           #14                 // String \'
      39: invokevirtual #12                 // Method java/lang/StringBuilder.append:(Ljava/lang/String;)Ljava/lang/StringBuilder;
      42: invokevirtual #15                 // Method java/lang/StringBuilder.toString:()Ljava/lang/String;
      45: aload_1
      46: invokespecial #16                 // Method java/lang/IllegalArgumentException."<init>":(Ljava/lang/String;Ljava/lang/Throwable;)V
      49: athrow
    Exception table:
       from    to  target type
           0    15    16   Class java/lang/IllegalAccessException
           0    15    16   Class java/lang/reflect/InvocationTargetException

  public static java.lang.Object parseLocalDateTime(java.lang.CharSequence);
    Code:
       0: getstatic     #18                 // Field LOCAL_DATE_TIME_PARSE:Ljava/lang/reflect/Method;
       3: aconst_null
       4: iconst_1
       5: anewarray     #4                  // class java/lang/Object
       8: dup
       9: iconst_0
      10: aload_0
      11: aastore
      12: invokevirtual #5                  // Method java/lang/reflect/Method.invoke:(Ljava/lang/Object;[Ljava/lang/Object;)Ljava/lang/Object;
      15: areturn
      16: astore_1
      17: new           #8                  // class java/lang/IllegalArgumentException
      20: dup
      21: new           #9                  // class java/lang/StringBuilder
      24: dup
      25: invokespecial #10                 // Method java/lang/StringBuilder."<init>":()V
      28: ldc           #11                 // String error when parsing text \'
      30: invokevirtual #12                 // Method java/lang/StringBuilder.append:(Ljava/lang/String;)Ljava/lang/StringBuilder;
      33: aload_0
      34: invokevirtual #13                 // Method java/lang/StringBuilder.append:(Ljava/lang/Object;)Ljava/lang/StringBuilder;
      37: ldc           #14                 // String \'
      39: invokevirtual #12                 // Method java/lang/StringBuilder.append:(Ljava/lang/String;)Ljava/lang/StringBuilder;
      42: invokevirtual #15                 // Method java/lang/StringBuilder.toString:()Ljava/lang/String;
      45: aload_1
      46: invokespecial #16                 // Method java/lang/IllegalArgumentException."<init>":(Ljava/lang/String;Ljava/lang/Throwable;)V
      49: athrow
    Exception table:
       from    to  target type
           0    15    16   Class java/lang/IllegalAccessException
           0    15    16   Class java/lang/reflect/InvocationTargetException

  public static java.lang.Object parseOffsetDateTime(java.lang.CharSequence);
    Code:
       0: getstatic     #19                 // Field OFFSET_DATE_TIME_PARSE:Ljava/lang/reflect/Method;
       3: aconst_null
       4: iconst_1
       5: anewarray     #4                  // class java/lang/Object
       8: dup
       9: iconst_0
      10: aload_0
      11: aastore
      12: invokevirtual #5                  // Method java/lang/reflect/Method.invoke:(Ljava/lang/Object;[Ljava/lang/Object;)Ljava/lang/Object;
      15: areturn
      16: astore_1
      17: new           #8                  // class java/lang/IllegalArgumentException
      20: dup
      21: new           #9                  // class java/lang/StringBuilder
      24: dup
      25: invokespecial #10                 // Method java/lang/StringBuilder."<init>":()V
      28: ldc           #11                 // String error when parsing text \'
      30: invokevirtual #12                 // Method java/lang/StringBuilder.append:(Ljava/lang/String;)Ljava/lang/StringBuilder;
      33: aload_0
      34: invokevirtual #13                 // Method java/lang/StringBuilder.append:(Ljava/lang/Object;)Ljava/lang/StringBuilder;
      37: ldc           #14                 // String \'
      39: invokevirtual #12                 // Method java/lang/StringBuilder.append:(Ljava/lang/String;)Ljava/lang/StringBuilder;
      42: invokevirtual #15                 // Method java/lang/StringBuilder.toString:()Ljava/lang/String;
      45: aload_1
      46: invokespecial #16                 // Method java/lang/IllegalArgumentException."<init>":(Ljava/lang/String;Ljava/lang/Throwable;)V
      49: athrow
    Exception table:
       from    to  target type
           0    15    16   Class java/lang/IllegalAccessException
           0    15    16   Class java/lang/reflect/InvocationTargetException

  private static java.lang.Class<?> tryGetClass(java.lang.String);
    Code:
       0: aload_0
       1: invokestatic  #20                 // Method java/lang/Class.forName:(Ljava/lang/String;)Ljava/lang/Class;
       4: areturn
       5: astore_1
       6: aconst_null
       7: areturn
    Exception table:
       from    to  target type
           0     4     5   Class java/lang/ClassNotFoundException

  private static java.lang.reflect.Method getMethod(java.lang.Class<?>, java.lang.String, java.lang.Class<?>...);
    Code:
       0: aload_0
       1: aload_1
       2: aload_2
       3: invokevirtual #22                 // Method java/lang/Class.getMethod:(Ljava/lang/String;[Ljava/lang/Class;)Ljava/lang/reflect/Method;
       6: areturn
       7: astore_3
       8: new           #24                 // class java/lang/IllegalStateException
      11: dup
      12: new           #9                  // class java/lang/StringBuilder
      15: dup
      16: invokespecial #10                 // Method java/lang/StringBuilder."<init>":()V
      19: ldc           #25                 // String Java 8 or later but method
      21: invokevirtual #12                 // Method java/lang/StringBuilder.append:(Ljava/lang/String;)Ljava/lang/StringBuilder;
      24: aload_0
      25: invokevirtual #26                 // Method java/lang/Class.getName:()Ljava/lang/String;
      28: invokevirtual #12                 // Method java/lang/StringBuilder.append:(Ljava/lang/String;)Ljava/lang/StringBuilder;
      31: ldc           #27                 // String #
      33: invokevirtual #12                 // Method java/lang/StringBuilder.append:(Ljava/lang/String;)Ljava/lang/StringBuilder;
      36: aload_1
      37: invokevirtual #12                 // Method java/lang/StringBuilder.append:(Ljava/lang/String;)Ljava/lang/StringBuilder;
      40: ldc           #28                 // String (
      42: invokevirtual #12                 // Method java/lang/StringBuilder.append:(Ljava/lang/String;)Ljava/lang/StringBuilder;
      45: aload_2
      46: invokestatic  #29                 // Method java/util/Arrays.toString:([Ljava/lang/Object;)Ljava/lang/String;
      49: invokevirtual #12                 // Method java/lang/StringBuilder.append:(Ljava/lang/String;)Ljava/lang/StringBuilder;
      52: ldc           #30                 // String ) is missing
      54: invokevirtual #12                 // Method java/lang/StringBuilder.append:(Ljava/lang/String;)Ljava/lang/StringBuilder;
      57: invokevirtual #15                 // Method java/lang/StringBuilder.toString:()Ljava/lang/String;
      60: aload_3
      61: invokespecial #31                 // Method java/lang/IllegalStateException."<init>":(Ljava/lang/String;Ljava/lang/Throwable;)V
      64: athrow
    Exception table:
       from    to  target type
           0     6     7   Class java/lang/NoSuchMethodException

  public static java.lang.Object valueToLocalDate(org.h2.value.Value);
    Code:
       0: aload_0
       1: bipush        10
       3: invokevirtual #32                 // Method org/h2/value/Value.convertTo:(I)Lorg/h2/value/Value;
       6: checkcast     #33                 // class org/h2/value/ValueDate
       9: invokevirtual #34                 // Method org/h2/value/ValueDate.getDateValue:()J
      12: invokestatic  #35                 // Method localDateFromDateValue:(J)Ljava/lang/Object;
      15: areturn
      16: astore_1
      17: aload_1
      18: invokestatic  #36                 // Method org/h2/message/DbException.convert:(Ljava/lang/Throwable;)Lorg/h2/message/DbException;
      21: athrow
      22: astore_1
      23: aload_1
      24: ldc           #37                 // String date conversion failed
      26: invokestatic  #38                 // Method org/h2/message/DbException.convertInvocation:(Ljava/lang/reflect/InvocationTargetException;Ljava/lang/String;)Lorg/h2/message/DbException;
      29: athrow
    Exception table:
       from    to  target type
           0    15    16   Class java/lang/IllegalAccessException
           0    15    22   Class java/lang/reflect/InvocationTargetException

  public static java.lang.Object valueToLocalTime(org.h2.value.Value);
    Code:
       0: getstatic     #39                 // Field LOCAL_TIME_OF_NANO:Ljava/lang/reflect/Method;
       3: aconst_null
       4: iconst_1
       5: anewarray     #4                  // class java/lang/Object
       8: dup
       9: iconst_0
      10: aload_0
      11: bipush        9
      13: invokevirtual #32                 // Method org/h2/value/Value.convertTo:(I)Lorg/h2/value/Value;
      16: checkcast     #40                 // class org/h2/value/ValueTime
      19: invokevirtual #41                 // Method org/h2/value/ValueTime.getNanos:()J
      22: invokestatic  #42                 // Method java/lang/Long.valueOf:(J)Ljava/lang/Long;
      25: aastore
      26: invokevirtual #5                  // Method java/lang/reflect/Method.invoke:(Ljava/lang/Object;[Ljava/lang/Object;)Ljava/lang/Object;
      29: areturn
      30: astore_1
      31: aload_1
      32: invokestatic  #36                 // Method org/h2/message/DbException.convert:(Ljava/lang/Throwable;)Lorg/h2/message/DbException;
      35: athrow
      36: astore_1
      37: aload_1
      38: ldc           #43                 // String time conversion failed
      40: invokestatic  #38                 // Method org/h2/message/DbException.convertInvocation:(Ljava/lang/reflect/InvocationTargetException;Ljava/lang/String;)Lorg/h2/message/DbException;
      43: athrow
    Exception table:
       from    to  target type
           0    29    30   Class java/lang/IllegalAccessException
           0    29    36   Class java/lang/reflect/InvocationTargetException

  public static java.lang.Object valueToLocalDateTime(org.h2.value.Value);
    Code:
       0: aload_0
       1: bipush        11
       3: invokevirtual #32                 // Method org/h2/value/Value.convertTo:(I)Lorg/h2/value/Value;
       6: checkcast     #44                 // class org/h2/value/ValueTimestamp
       9: astore_1
      10: aload_1
      11: invokevirtual #45                 // Method org/h2/value/ValueTimestamp.getDateValue:()J
      14: lstore_2
      15: aload_1
      16: invokevirtual #46                 // Method org/h2/value/ValueTimestamp.getTimeNanos:()J
      19: lstore        4
      21: lload_2
      22: lload         4
      24: invokestatic  #47                 // Method localDateTimeFromDateNanos:(JJ)Ljava/lang/Object;
      27: areturn
      28: astore        6
      30: aload         6
      32: invokestatic  #36                 // Method org/h2/message/DbException.convert:(Ljava/lang/Throwable;)Lorg/h2/message/DbException;
      35: athrow
      36: astore        6
      38: aload         6
      40: ldc           #48                 // String timestamp conversion failed
      42: invokestatic  #38                 // Method org/h2/message/DbException.convertInvocation:(Ljava/lang/reflect/InvocationTargetException;Ljava/lang/String;)Lorg/h2/message/DbException;
      45: athrow
    Exception table:
       from    to  target type
          21    27    28   Class java/lang/IllegalAccessException
          21    27    36   Class java/lang/reflect/InvocationTargetException

  public static java.lang.Object valueToInstant(org.h2.value.Value);
    Code:
       0: getstatic     #49                 // Field TIMESTAMP_TO_INSTANT:Ljava/lang/reflect/Method;
       3: aload_0
       4: invokevirtual #50                 // Method org/h2/value/Value.getTimestamp:()Ljava/sql/Timestamp;
       7: iconst_0
       8: anewarray     #4                  // class java/lang/Object
      11: invokevirtual #5                  // Method java/lang/reflect/Method.invoke:(Ljava/lang/Object;[Ljava/lang/Object;)Ljava/lang/Object;
      14: areturn
      15: astore_1
      16: aload_1
      17: invokestatic  #36                 // Method org/h2/message/DbException.convert:(Ljava/lang/Throwable;)Lorg/h2/message/DbException;
      20: athrow
      21: astore_1
      22: aload_1
      23: ldc           #48                 // String timestamp conversion failed
      25: invokestatic  #38                 // Method org/h2/message/DbException.convertInvocation:(Ljava/lang/reflect/InvocationTargetException;Ljava/lang/String;)Lorg/h2/message/DbException;
      28: athrow
    Exception table:
       from    to  target type
           0    14    15   Class java/lang/IllegalAccessException
           0    14    21   Class java/lang/reflect/InvocationTargetException

  public static java.lang.Object valueToOffsetDateTime(org.h2.value.Value);
    Code:
       0: aload_0
       1: bipush        24
       3: invokevirtual #32                 // Method org/h2/value/Value.convertTo:(I)Lorg/h2/value/Value;
       6: checkcast     #51                 // class org/h2/value/ValueTimestampTimeZone
       9: astore_1
      10: aload_1
      11: invokevirtual #52                 // Method org/h2/value/ValueTimestampTimeZone.getDateValue:()J
      14: lstore_2
      15: aload_1
      16: invokevirtual #53                 // Method org/h2/value/ValueTimestampTimeZone.getTimeNanos:()J
      19: lstore        4
      21: lload_2
      22: lload         4
      24: invokestatic  #47                 // Method localDateTimeFromDateNanos:(JJ)Ljava/lang/Object;
      27: astore        6
      29: aload_1
      30: invokevirtual #54                 // Method org/h2/value/ValueTimestampTimeZone.getTimeZoneOffsetMins:()S
      33: istore        7
      35: getstatic     #55                 // Field java/util/concurrent/TimeUnit.MINUTES:Ljava/util/concurrent/TimeUnit;
      38: iload         7
      40: i2l
      41: invokevirtual #56                 // Method java/util/concurrent/TimeUnit.toSeconds:(J)J
      44: l2i
      45: istore        8
      47: getstatic     #57                 // Field ZONE_OFFSET_OF_TOTAL_SECONDS:Ljava/lang/reflect/Method;
      50: aconst_null
      51: iconst_1
      52: anewarray     #4                  // class java/lang/Object
      55: dup
      56: iconst_0
      57: iload         8
      59: invokestatic  #58                 // Method java/lang/Integer.valueOf:(I)Ljava/lang/Integer;
      62: aastore
      63: invokevirtual #5                  // Method java/lang/reflect/Method.invoke:(Ljava/lang/Object;[Ljava/lang/Object;)Ljava/lang/Object;
      66: astore        9
      68: getstatic     #59                 // Field OFFSET_DATE_TIME_OF_LOCAL_DATE_TIME_ZONE_OFFSET:Ljava/lang/reflect/Method;
      71: aconst_null
      72: iconst_2
      73: anewarray     #4                  // class java/lang/Object
      76: dup
      77: iconst_0
      78: aload         6
      80: aastore
      81: dup
      82: iconst_1
      83: aload         9
      85: aastore
      86: invokevirtual #5                  // Method java/lang/reflect/Method.invoke:(Ljava/lang/Object;[Ljava/lang/Object;)Ljava/lang/Object;
      89: areturn
      90: astore        6
      92: aload         6
      94: invokestatic  #36                 // Method org/h2/message/DbException.convert:(Ljava/lang/Throwable;)Lorg/h2/message/DbException;
      97: athrow
      98: astore        6
     100: aload         6
     102: ldc           #60                 // String timestamp with time zone conversion failed
     104: invokestatic  #38                 // Method org/h2/message/DbException.convertInvocation:(Ljava/lang/reflect/InvocationTargetException;Ljava/lang/String;)Lorg/h2/message/DbException;
     107: athrow
    Exception table:
       from    to  target type
          21    89    90   Class java/lang/IllegalAccessException
          21    89    98   Class java/lang/reflect/InvocationTargetException

  public static org.h2.value.Value localDateToDateValue(java.lang.Object);
    Code:
       0: aload_0
       1: invokestatic  #61                 // Method dateValueFromLocalDate:(Ljava/lang/Object;)J
       4: invokestatic  #62                 // Method org/h2/value/ValueDate.fromDateValue:(J)Lorg/h2/value/ValueDate;
       7: areturn
       8: astore_1
       9: aload_1
      10: invokestatic  #36                 // Method org/h2/message/DbException.convert:(Ljava/lang/Throwable;)Lorg/h2/message/DbException;
      13: athrow
      14: astore_1
      15: aload_1
      16: ldc           #37                 // String date conversion failed
      18: invokestatic  #38                 // Method org/h2/message/DbException.convertInvocation:(Ljava/lang/reflect/InvocationTargetException;Ljava/lang/String;)Lorg/h2/message/DbException;
      21: athrow
    Exception table:
       from    to  target type
           0     7     8   Class java/lang/IllegalAccessException
           0     7    14   Class java/lang/reflect/InvocationTargetException

  public static org.h2.value.Value localTimeToTimeValue(java.lang.Object);
    Code:
       0: getstatic     #63                 // Field LOCAL_TIME_TO_NANO:Ljava/lang/reflect/Method;
       3: aload_0
       4: iconst_0
       5: anewarray     #4                  // class java/lang/Object
       8: invokevirtual #5                  // Method java/lang/reflect/Method.invoke:(Ljava/lang/Object;[Ljava/lang/Object;)Ljava/lang/Object;
      11: checkcast     #64                 // class java/lang/Long
      14: invokevirtual #65                 // Method java/lang/Long.longValue:()J
      17: invokestatic  #66                 // Method org/h2/value/ValueTime.fromNanos:(J)Lorg/h2/value/ValueTime;
      20: areturn
      21: astore_1
      22: aload_1
      23: invokestatic  #36                 // Method org/h2/message/DbException.convert:(Ljava/lang/Throwable;)Lorg/h2/message/DbException;
      26: athrow
      27: astore_1
      28: aload_1
      29: ldc           #43                 // String time conversion failed
      31: invokestatic  #38                 // Method org/h2/message/DbException.convertInvocation:(Ljava/lang/reflect/InvocationTargetException;Ljava/lang/String;)Lorg/h2/message/DbException;
      34: athrow
    Exception table:
       from    to  target type
           0    20    21   Class java/lang/IllegalAccessException
           0    20    27   Class java/lang/reflect/InvocationTargetException

  public static org.h2.value.Value localDateTimeToValue(java.lang.Object);
    Code:
       0: getstatic     #67                 // Field LOCAL_DATE_TIME_TO_LOCAL_DATE:Ljava/lang/reflect/Method;
       3: aload_0
       4: iconst_0
       5: anewarray     #4                  // class java/lang/Object
       8: invokevirtual #5                  // Method java/lang/reflect/Method.invoke:(Ljava/lang/Object;[Ljava/lang/Object;)Ljava/lang/Object;
      11: astore_1
      12: aload_1
      13: invokestatic  #61                 // Method dateValueFromLocalDate:(Ljava/lang/Object;)J
      16: lstore_2
      17: aload_0
      18: invokestatic  #68                 // Method timeNanosFromLocalDateTime:(Ljava/lang/Object;)J
      21: lstore        4
      23: lload_2
      24: lload         4
      26: invokestatic  #69                 // Method org/h2/value/ValueTimestamp.fromDateValueAndNanos:(JJ)Lorg/h2/value/ValueTimestamp;
      29: areturn
      30: astore_1
      31: aload_1
      32: invokestatic  #36                 // Method org/h2/message/DbException.convert:(Ljava/lang/Throwable;)Lorg/h2/message/DbException;
      35: athrow
      36: astore_1
      37: aload_1
      38: ldc           #70                 // String local date time conversion failed
      40: invokestatic  #38                 // Method org/h2/message/DbException.convertInvocation:(Ljava/lang/reflect/InvocationTargetException;Ljava/lang/String;)Lorg/h2/message/DbException;
      43: athrow
    Exception table:
       from    to  target type
           0    29    30   Class java/lang/IllegalAccessException
           0    29    36   Class java/lang/reflect/InvocationTargetException

  public static org.h2.value.Value instantToValue(java.lang.Object);
    Code:
       0: getstatic     #71                 // Field INSTANT_GET_EPOCH_SECOND:Ljava/lang/reflect/Method;
       3: aload_0
       4: iconst_0
       5: anewarray     #4                  // class java/lang/Object
       8: invokevirtual #5                  // Method java/lang/reflect/Method.invoke:(Ljava/lang/Object;[Ljava/lang/Object;)Ljava/lang/Object;
      11: checkcast     #64                 // class java/lang/Long
      14: invokevirtual #65                 // Method java/lang/Long.longValue:()J
      17: lstore_1
      18: getstatic     #72                 // Field INSTANT_GET_NANO:Ljava/lang/reflect/Method;
      21: aload_0
      22: iconst_0
      23: anewarray     #4                  // class java/lang/Object
      26: invokevirtual #5                  // Method java/lang/reflect/Method.invoke:(Ljava/lang/Object;[Ljava/lang/Object;)Ljava/lang/Object;
      29: checkcast     #73                 // class java/lang/Integer
      32: invokevirtual #74                 // Method java/lang/Integer.intValue:()I
      35: istore_3
      36: lload_1
      37: ldc2_w        #75                 // long 86400l
      40: ldiv
      41: lstore        4
      43: lload_1
      44: lconst_0
      45: lcmp
      46: ifge          66
      49: lload         4
      51: ldc2_w        #75                 // long 86400l
      54: lmul
      55: lload_1
      56: lcmp
      57: ifeq          66
      60: lload         4
      62: lconst_1
      63: lsub
      64: lstore        4
      66: lload_1
      67: lload         4
      69: ldc2_w        #75                 // long 86400l
      72: lmul
      73: lsub
      74: ldc2_w        #77                 // long 1000000000l
      77: lmul
      78: iload_3
      79: i2l
      80: ladd
      81: lstore        6
      83: lload         4
      85: invokestatic  #79                 // Method org/h2/util/DateTimeUtils.dateValueFromAbsoluteDay:(J)J
      88: lload         6
      90: iconst_0
      91: invokestatic  #80                 // Method org/h2/value/ValueTimestampTimeZone.fromDateValueAndNanos:(JJS)Lorg/h2/value/ValueTimestampTimeZone;
      94: areturn
      95: astore_1
      96: aload_1
      97: invokestatic  #36                 // Method org/h2/message/DbException.convert:(Ljava/lang/Throwable;)Lorg/h2/message/DbException;
     100: athrow
     101: astore_1
     102: aload_1
     103: ldc           #81                 // String instant conversion failed
     105: invokestatic  #38                 // Method org/h2/message/DbException.convertInvocation:(Ljava/lang/reflect/InvocationTargetException;Ljava/lang/String;)Lorg/h2/message/DbException;
     108: athrow
    Exception table:
       from    to  target type
           0    94    95   Class java/lang/IllegalAccessException
           0    94   101   Class java/lang/reflect/InvocationTargetException

  public static org.h2.value.Value offsetDateTimeToValue(java.lang.Object);
    Code:
       0: getstatic     #82                 // Field OFFSET_DATE_TIME_TO_LOCAL_DATE_TIME:Ljava/lang/reflect/Method;
       3: aload_0
       4: iconst_0
       5: anewarray     #4                  // class java/lang/Object
       8: invokevirtual #5                  // Method java/lang/reflect/Method.invoke:(Ljava/lang/Object;[Ljava/lang/Object;)Ljava/lang/Object;
      11: astore_1
      12: getstatic     #67                 // Field LOCAL_DATE_TIME_TO_LOCAL_DATE:Ljava/lang/reflect/Method;
      15: aload_1
      16: iconst_0
      17: anewarray     #4                  // class java/lang/Object
      20: invokevirtual #5                  // Method java/lang/reflect/Method.invoke:(Ljava/lang/Object;[Ljava/lang/Object;)Ljava/lang/Object;
      23: astore_2
      24: getstatic     #83                 // Field OFFSET_DATE_TIME_GET_OFFSET:Ljava/lang/reflect/Method;
      27: aload_0
      28: iconst_0
      29: anewarray     #4                  // class java/lang/Object
      32: invokevirtual #5                  // Method java/lang/reflect/Method.invoke:(Ljava/lang/Object;[Ljava/lang/Object;)Ljava/lang/Object;
      35: astore_3
      36: aload_2
      37: invokestatic  #61                 // Method dateValueFromLocalDate:(Ljava/lang/Object;)J
      40: lstore        4
      42: aload_1
      43: invokestatic  #68                 // Method timeNanosFromLocalDateTime:(Ljava/lang/Object;)J
      46: lstore        6
      48: aload_3
      49: invokestatic  #84                 // Method zoneOffsetToOffsetMinute:(Ljava/lang/Object;)S
      52: istore        8
      54: lload         4
      56: lload         6
      58: iload         8
      60: invokestatic  #80                 // Method org/h2/value/ValueTimestampTimeZone.fromDateValueAndNanos:(JJS)Lorg/h2/value/ValueTimestampTimeZone;
      63: areturn
      64: astore_1
      65: aload_1
      66: invokestatic  #36                 // Method org/h2/message/DbException.convert:(Ljava/lang/Throwable;)Lorg/h2/message/DbException;
      69: athrow
      70: astore_1
      71: aload_1
      72: ldc           #43                 // String time conversion failed
      74: invokestatic  #38                 // Method org/h2/message/DbException.convertInvocation:(Ljava/lang/reflect/InvocationTargetException;Ljava/lang/String;)Lorg/h2/message/DbException;
      77: athrow
    Exception table:
       from    to  target type
           0    63    64   Class java/lang/IllegalAccessException
           0    63    70   Class java/lang/reflect/InvocationTargetException

  private static long dateValueFromLocalDate(java.lang.Object) throws java.lang.IllegalAccessException, java.lang.reflect.InvocationTargetException;
    Code:
       0: getstatic     #85                 // Field LOCAL_DATE_GET_YEAR:Ljava/lang/reflect/Method;
       3: aload_0
       4: iconst_0
       5: anewarray     #4                  // class java/lang/Object
       8: invokevirtual #5                  // Method java/lang/reflect/Method.invoke:(Ljava/lang/Object;[Ljava/lang/Object;)Ljava/lang/Object;
      11: checkcast     #73                 // class java/lang/Integer
      14: invokevirtual #74                 // Method java/lang/Integer.intValue:()I
      17: istore_1
      18: getstatic     #86                 // Field LOCAL_DATE_GET_MONTH_VALUE:Ljava/lang/reflect/Method;
      21: aload_0
      22: iconst_0
      23: anewarray     #4                  // class java/lang/Object
      26: invokevirtual #5                  // Method java/lang/reflect/Method.invoke:(Ljava/lang/Object;[Ljava/lang/Object;)Ljava/lang/Object;
      29: checkcast     #73                 // class java/lang/Integer
      32: invokevirtual #74                 // Method java/lang/Integer.intValue:()I
      35: istore_2
      36: getstatic     #87                 // Field LOCAL_DATE_GET_DAY_OF_MONTH:Ljava/lang/reflect/Method;
      39: aload_0
      40: iconst_0
      41: anewarray     #4                  // class java/lang/Object
      44: invokevirtual #5                  // Method java/lang/reflect/Method.invoke:(Ljava/lang/Object;[Ljava/lang/Object;)Ljava/lang/Object;
      47: checkcast     #73                 // class java/lang/Integer
      50: invokevirtual #74                 // Method java/lang/Integer.intValue:()I
      53: istore_3
      54: iload_1
      55: i2l
      56: iload_2
      57: iload_3
      58: invokestatic  #88                 // Method org/h2/util/DateTimeUtils.dateValue:(JII)J
      61: lreturn

  private static long timeNanosFromLocalDateTime(java.lang.Object) throws java.lang.IllegalAccessException, java.lang.reflect.InvocationTargetException;
    Code:
       0: getstatic     #89                 // Field LOCAL_DATE_TIME_TO_LOCAL_TIME:Ljava/lang/reflect/Method;
       3: aload_0
       4: iconst_0
       5: anewarray     #4                  // class java/lang/Object
       8: invokevirtual #5                  // Method java/lang/reflect/Method.invoke:(Ljava/lang/Object;[Ljava/lang/Object;)Ljava/lang/Object;
      11: astore_1
      12: getstatic     #63                 // Field LOCAL_TIME_TO_NANO:Ljava/lang/reflect/Method;
      15: aload_1
      16: iconst_0
      17: anewarray     #4                  // class java/lang/Object
      20: invokevirtual #5                  // Method java/lang/reflect/Method.invoke:(Ljava/lang/Object;[Ljava/lang/Object;)Ljava/lang/Object;
      23: checkcast     #64                 // class java/lang/Long
      26: invokevirtual #65                 // Method java/lang/Long.longValue:()J
      29: lreturn

  private static short zoneOffsetToOffsetMinute(java.lang.Object) throws java.lang.IllegalAccessException, java.lang.reflect.InvocationTargetException;
    Code:
       0: getstatic     #90                 // Field ZONE_OFFSET_GET_TOTAL_SECONDS:Ljava/lang/reflect/Method;
       3: aload_0
       4: iconst_0
       5: anewarray     #4                  // class java/lang/Object
       8: invokevirtual #5                  // Method java/lang/reflect/Method.invoke:(Ljava/lang/Object;[Ljava/lang/Object;)Ljava/lang/Object;
      11: checkcast     #73                 // class java/lang/Integer
      14: invokevirtual #74                 // Method java/lang/Integer.intValue:()I
      17: istore_1
      18: getstatic     #91                 // Field java/util/concurrent/TimeUnit.SECONDS:Ljava/util/concurrent/TimeUnit;
      21: iload_1
      22: i2l
      23: invokevirtual #92                 // Method java/util/concurrent/TimeUnit.toMinutes:(J)J
      26: l2i
      27: i2s
      28: ireturn

  private static java.lang.Object localDateFromDateValue(long) throws java.lang.IllegalAccessException, java.lang.reflect.InvocationTargetException;
    Code:
       0: lload_0
       1: invokestatic  #93                 // Method org/h2/util/DateTimeUtils.yearFromDateValue:(J)I
       4: istore_2
       5: lload_0
       6: invokestatic  #94                 // Method org/h2/util/DateTimeUtils.monthFromDateValue:(J)I
       9: istore_3
      10: lload_0
      11: invokestatic  #95                 // Method org/h2/util/DateTimeUtils.dayFromDateValue:(J)I
      14: istore        4
      16: getstatic     #96                 // Field LOCAL_DATE_OF_YEAR_MONTH_DAY:Ljava/lang/reflect/Method;
      19: aconst_null
      20: iconst_3
      21: anewarray     #4                  // class java/lang/Object
      24: dup
      25: iconst_0
      26: iload_2
      27: invokestatic  #58                 // Method java/lang/Integer.valueOf:(I)Ljava/lang/Integer;
      30: aastore
      31: dup
      32: iconst_1
      33: iload_3
      34: invokestatic  #58                 // Method java/lang/Integer.valueOf:(I)Ljava/lang/Integer;
      37: aastore
      38: dup
      39: iconst_2
      40: iload         4
      42: invokestatic  #58                 // Method java/lang/Integer.valueOf:(I)Ljava/lang/Integer;
      45: aastore
      46: invokevirtual #5                  // Method java/lang/reflect/Method.invoke:(Ljava/lang/Object;[Ljava/lang/Object;)Ljava/lang/Object;
      49: areturn
      50: astore        5
      52: iload_2
      53: sipush        1500
      56: if_icmpgt     110
      59: iload_2
      60: iconst_3
      61: iand
      62: ifne          110
      65: iload_3
      66: iconst_2
      67: if_icmpne     110
      70: iload         4
      72: bipush        29
      74: if_icmpne     110
      77: getstatic     #96                 // Field LOCAL_DATE_OF_YEAR_MONTH_DAY:Ljava/lang/reflect/Method;
      80: aconst_null
      81: iconst_3
      82: anewarray     #4                  // class java/lang/Object
      85: dup
      86: iconst_0
      87: iload_2
      88: invokestatic  #58                 // Method java/lang/Integer.valueOf:(I)Ljava/lang/Integer;
      91: aastore
      92: dup
      93: iconst_1
      94: iconst_3
      95: invokestatic  #58                 // Method java/lang/Integer.valueOf:(I)Ljava/lang/Integer;
      98: aastore
      99: dup
     100: iconst_2
     101: iconst_1
     102: invokestatic  #58                 // Method java/lang/Integer.valueOf:(I)Ljava/lang/Integer;
     105: aastore
     106: invokevirtual #5                  // Method java/lang/reflect/Method.invoke:(Ljava/lang/Object;[Ljava/lang/Object;)Ljava/lang/Object;
     109: areturn
     110: aload         5
     112: athrow
    Exception table:
       from    to  target type
          16    49    50   Class java/lang/reflect/InvocationTargetException

  private static java.lang.Object localDateTimeFromDateNanos(long, long) throws java.lang.IllegalAccessException, java.lang.reflect.InvocationTargetException;
    Code:
       0: lload_0
       1: invokestatic  #35                 // Method localDateFromDateValue:(J)Ljava/lang/Object;
       4: astore        4
       6: getstatic     #97                 // Field LOCAL_DATE_AT_START_OF_DAY:Ljava/lang/reflect/Method;
       9: aload         4
      11: iconst_0
      12: anewarray     #4                  // class java/lang/Object
      15: invokevirtual #5                  // Method java/lang/reflect/Method.invoke:(Ljava/lang/Object;[Ljava/lang/Object;)Ljava/lang/Object;
      18: astore        5
      20: getstatic     #98                 // Field LOCAL_DATE_TIME_PLUS_NANOS:Ljava/lang/reflect/Method;
      23: aload         5
      25: iconst_1
      26: anewarray     #4                  // class java/lang/Object
      29: dup
      30: iconst_0
      31: lload_2
      32: invokestatic  #42                 // Method java/lang/Long.valueOf:(J)Ljava/lang/Long;
      35: aastore
      36: invokevirtual #5                  // Method java/lang/reflect/Method.invoke:(Ljava/lang/Object;[Ljava/lang/Object;)Ljava/lang/Object;
      39: areturn

  static {};
    Code:
       0: ldc           #99                 // String java.time.LocalDate
       2: invokestatic  #100                // Method tryGetClass:(Ljava/lang/String;)Ljava/lang/Class;
       5: putstatic     #101                // Field LOCAL_DATE:Ljava/lang/Class;
       8: ldc           #102                // String java.time.LocalTime
      10: invokestatic  #100                // Method tryGetClass:(Ljava/lang/String;)Ljava/lang/Class;
      13: putstatic     #103                // Field LOCAL_TIME:Ljava/lang/Class;
      16: ldc           #104                // String java.time.LocalDateTime
      18: invokestatic  #100                // Method tryGetClass:(Ljava/lang/String;)Ljava/lang/Class;
      21: putstatic     #105                // Field LOCAL_DATE_TIME:Ljava/lang/Class;
      24: ldc           #106                // String java.time.Instant
      26: invokestatic  #100                // Method tryGetClass:(Ljava/lang/String;)Ljava/lang/Class;
      29: putstatic     #107                // Field INSTANT:Ljava/lang/Class;
      32: ldc           #108                // String java.time.OffsetDateTime
      34: invokestatic  #100                // Method tryGetClass:(Ljava/lang/String;)Ljava/lang/Class;
      37: putstatic     #109                // Field OFFSET_DATE_TIME:Ljava/lang/Class;
      40: ldc           #110                // String java.time.ZoneOffset
      42: invokestatic  #100                // Method tryGetClass:(Ljava/lang/String;)Ljava/lang/Class;
      45: putstatic     #111                // Field ZONE_OFFSET:Ljava/lang/Class;
      48: getstatic     #101                // Field LOCAL_DATE:Ljava/lang/Class;
      51: ifnull        88
      54: getstatic     #103                // Field LOCAL_TIME:Ljava/lang/Class;
      57: ifnull        88
      60: getstatic     #105                // Field LOCAL_DATE_TIME:Ljava/lang/Class;
      63: ifnull        88
      66: getstatic     #107                // Field INSTANT:Ljava/lang/Class;
      69: ifnull        88
      72: getstatic     #109                // Field OFFSET_DATE_TIME:Ljava/lang/Class;
      75: ifnull        88
      78: getstatic     #111                // Field ZONE_OFFSET:Ljava/lang/Class;
      81: ifnull        88
      84: iconst_1
      85: goto          89
      88: iconst_0
      89: putstatic     #2                  // Field IS_JAVA8_DATE_API_PRESENT:Z
      92: getstatic     #2                  // Field IS_JAVA8_DATE_API_PRESENT:Z
      95: ifeq          503
      98: getstatic     #103                // Field LOCAL_TIME:Ljava/lang/Class;
     101: ldc           #112                // String ofNanoOfDay
     103: iconst_1
     104: anewarray     #113                // class java/lang/Class
     107: dup
     108: iconst_0
     109: getstatic     #114                // Field java/lang/Long.TYPE:Ljava/lang/Class;
     112: aastore
     113: invokestatic  #115                // Method getMethod:(Ljava/lang/Class;Ljava/lang/String;[Ljava/lang/Class;)Ljava/lang/reflect/Method;
     116: putstatic     #39                 // Field LOCAL_TIME_OF_NANO:Ljava/lang/reflect/Method;
     119: getstatic     #103                // Field LOCAL_TIME:Ljava/lang/Class;
     122: ldc           #116                // String toNanoOfDay
     124: iconst_0
     125: anewarray     #113                // class java/lang/Class
     128: invokestatic  #115                // Method getMethod:(Ljava/lang/Class;Ljava/lang/String;[Ljava/lang/Class;)Ljava/lang/reflect/Method;
     131: putstatic     #63                 // Field LOCAL_TIME_TO_NANO:Ljava/lang/reflect/Method;
     134: getstatic     #101                // Field LOCAL_DATE:Ljava/lang/Class;
     137: ldc           #117                // String of
     139: iconst_3
     140: anewarray     #113                // class java/lang/Class
     143: dup
     144: iconst_0
     145: getstatic     #118                // Field java/lang/Integer.TYPE:Ljava/lang/Class;
     148: aastore
     149: dup
     150: iconst_1
     151: getstatic     #118                // Field java/lang/Integer.TYPE:Ljava/lang/Class;
     154: aastore
     155: dup
     156: iconst_2
     157: getstatic     #118                // Field java/lang/Integer.TYPE:Ljava/lang/Class;
     160: aastore
     161: invokestatic  #115                // Method getMethod:(Ljava/lang/Class;Ljava/lang/String;[Ljava/lang/Class;)Ljava/lang/reflect/Method;
     164: putstatic     #96                 // Field LOCAL_DATE_OF_YEAR_MONTH_DAY:Ljava/lang/reflect/Method;
     167: getstatic     #101                // Field LOCAL_DATE:Ljava/lang/Class;
     170: ldc           #119                // String parse
     172: iconst_1
     173: anewarray     #113                // class java/lang/Class
     176: dup
     177: iconst_0
     178: ldc_w         #120                // class java/lang/CharSequence
     181: aastore
     182: invokestatic  #115                // Method getMethod:(Ljava/lang/Class;Ljava/lang/String;[Ljava/lang/Class;)Ljava/lang/reflect/Method;
     185: putstatic     #3                  // Field LOCAL_DATE_PARSE:Ljava/lang/reflect/Method;
     188: getstatic     #101                // Field LOCAL_DATE:Ljava/lang/Class;
     191: ldc           #121                // String getYear
     193: iconst_0
     194: anewarray     #113                // class java/lang/Class
     197: invokestatic  #115                // Method getMethod:(Ljava/lang/Class;Ljava/lang/String;[Ljava/lang/Class;)Ljava/lang/reflect/Method;
     200: putstatic     #85                 // Field LOCAL_DATE_GET_YEAR:Ljava/lang/reflect/Method;
     203: getstatic     #101                // Field LOCAL_DATE:Ljava/lang/Class;
     206: ldc           #122                // String getMonthValue
     208: iconst_0
     209: anewarray     #113                // class java/lang/Class
     212: invokestatic  #115                // Method getMethod:(Ljava/lang/Class;Ljava/lang/String;[Ljava/lang/Class;)Ljava/lang/reflect/Method;
     215: putstatic     #86                 // Field LOCAL_DATE_GET_MONTH_VALUE:Ljava/lang/reflect/Method;
     218: getstatic     #101                // Field LOCAL_DATE:Ljava/lang/Class;
     221: ldc           #123                // String getDayOfMonth
     223: iconst_0
     224: anewarray     #113                // class java/lang/Class
     227: invokestatic  #115                // Method getMethod:(Ljava/lang/Class;Ljava/lang/String;[Ljava/lang/Class;)Ljava/lang/reflect/Method;
     230: putstatic     #87                 // Field LOCAL_DATE_GET_DAY_OF_MONTH:Ljava/lang/reflect/Method;
     233: getstatic     #101                // Field LOCAL_DATE:Ljava/lang/Class;
     236: ldc           #124                // String atStartOfDay
     238: iconst_0
     239: anewarray     #113                // class java/lang/Class
     242: invokestatic  #115                // Method getMethod:(Ljava/lang/Class;Ljava/lang/String;[Ljava/lang/Class;)Ljava/lang/reflect/Method;
     245: putstatic     #97                 // Field LOCAL_DATE_AT_START_OF_DAY:Ljava/lang/reflect/Method;
     248: getstatic     #107                // Field INSTANT:Ljava/lang/Class;
     251: ldc           #125                // String getEpochSecond
     253: iconst_0
     254: anewarray     #113                // class java/lang/Class
     257: invokestatic  #115                // Method getMethod:(Ljava/lang/Class;Ljava/lang/String;[Ljava/lang/Class;)Ljava/lang/reflect/Method;
     260: putstatic     #71                 // Field INSTANT_GET_EPOCH_SECOND:Ljava/lang/reflect/Method;
     263: getstatic     #107                // Field INSTANT:Ljava/lang/Class;
     266: ldc           #126                // String getNano
     268: iconst_0
     269: anewarray     #113                // class java/lang/Class
     272: invokestatic  #115                // Method getMethod:(Ljava/lang/Class;Ljava/lang/String;[Ljava/lang/Class;)Ljava/lang/reflect/Method;
     275: putstatic     #72                 // Field INSTANT_GET_NANO:Ljava/lang/reflect/Method;
     278: ldc_w         #127                // class java/sql/Timestamp
     281: ldc           #128                // String toInstant
     283: iconst_0
     284: anewarray     #113                // class java/lang/Class
     287: invokestatic  #115                // Method getMethod:(Ljava/lang/Class;Ljava/lang/String;[Ljava/lang/Class;)Ljava/lang/reflect/Method;
     290: putstatic     #49                 // Field TIMESTAMP_TO_INSTANT:Ljava/lang/reflect/Method;
     293: getstatic     #103                // Field LOCAL_TIME:Ljava/lang/Class;
     296: ldc           #119                // String parse
     298: iconst_1
     299: anewarray     #113                // class java/lang/Class
     302: dup
     303: iconst_0
     304: ldc_w         #120                // class java/lang/CharSequence
     307: aastore
     308: invokestatic  #115                // Method getMethod:(Ljava/lang/Class;Ljava/lang/String;[Ljava/lang/Class;)Ljava/lang/reflect/Method;
     311: putstatic     #17                 // Field LOCAL_TIME_PARSE:Ljava/lang/reflect/Method;
     314: getstatic     #105                // Field LOCAL_DATE_TIME:Ljava/lang/Class;
     317: ldc           #129                // String plusNanos
     319: iconst_1
     320: anewarray     #113                // class java/lang/Class
     323: dup
     324: iconst_0
     325: getstatic     #114                // Field java/lang/Long.TYPE:Ljava/lang/Class;
     328: aastore
     329: invokestatic  #115                // Method getMethod:(Ljava/lang/Class;Ljava/lang/String;[Ljava/lang/Class;)Ljava/lang/reflect/Method;
     332: putstatic     #98                 // Field LOCAL_DATE_TIME_PLUS_NANOS:Ljava/lang/reflect/Method;
     335: getstatic     #105                // Field LOCAL_DATE_TIME:Ljava/lang/Class;
     338: ldc           #130                // String toLocalDate
     340: iconst_0
     341: anewarray     #113                // class java/lang/Class
     344: invokestatic  #115                // Method getMethod:(Ljava/lang/Class;Ljava/lang/String;[Ljava/lang/Class;)Ljava/lang/reflect/Method;
     347: putstatic     #67                 // Field LOCAL_DATE_TIME_TO_LOCAL_DATE:Ljava/lang/reflect/Method;
     350: getstatic     #105                // Field LOCAL_DATE_TIME:Ljava/lang/Class;
     353: ldc           #131                // String toLocalTime
     355: iconst_0
     356: anewarray     #113                // class java/lang/Class
     359: invokestatic  #115                // Method getMethod:(Ljava/lang/Class;Ljava/lang/String;[Ljava/lang/Class;)Ljava/lang/reflect/Method;
     362: putstatic     #89                 // Field LOCAL_DATE_TIME_TO_LOCAL_TIME:Ljava/lang/reflect/Method;
     365: getstatic     #105                // Field LOCAL_DATE_TIME:Ljava/lang/Class;
     368: ldc           #119                // String parse
     370: iconst_1
     371: anewarray     #113                // class java/lang/Class
     374: dup
     375: iconst_0
     376: ldc_w         #120                // class java/lang/CharSequence
     379: aastore
     380: invokestatic  #115                // Method getMethod:(Ljava/lang/Class;Ljava/lang/String;[Ljava/lang/Class;)Ljava/lang/reflect/Method;
     383: putstatic     #18                 // Field LOCAL_DATE_TIME_PARSE:Ljava/lang/reflect/Method;
     386: getstatic     #111                // Field ZONE_OFFSET:Ljava/lang/Class;
     389: ldc           #132                // String ofTotalSeconds
     391: iconst_1
     392: anewarray     #113                // class java/lang/Class
     395: dup
     396: iconst_0
     397: getstatic     #118                // Field java/lang/Integer.TYPE:Ljava/lang/Class;
     400: aastore
     401: invokestatic  #115                // Method getMethod:(Ljava/lang/Class;Ljava/lang/String;[Ljava/lang/Class;)Ljava/lang/reflect/Method;
     404: putstatic     #57                 // Field ZONE_OFFSET_OF_TOTAL_SECONDS:Ljava/lang/reflect/Method;
     407: getstatic     #109                // Field OFFSET_DATE_TIME:Ljava/lang/Class;
     410: ldc           #133                // String toLocalDateTime
     412: iconst_0
     413: anewarray     #113                // class java/lang/Class
     416: invokestatic  #115                // Method getMethod:(Ljava/lang/Class;Ljava/lang/String;[Ljava/lang/Class;)Ljava/lang/reflect/Method;
     419: putstatic     #82                 // Field OFFSET_DATE_TIME_TO_LOCAL_DATE_TIME:Ljava/lang/reflect/Method;
     422: getstatic     #109                // Field OFFSET_DATE_TIME:Ljava/lang/Class;
     425: ldc           #134                // String getOffset
     427: iconst_0
     428: anewarray     #113                // class java/lang/Class
     431: invokestatic  #115                // Method getMethod:(Ljava/lang/Class;Ljava/lang/String;[Ljava/lang/Class;)Ljava/lang/reflect/Method;
     434: putstatic     #83                 // Field OFFSET_DATE_TIME_GET_OFFSET:Ljava/lang/reflect/Method;
     437: getstatic     #109                // Field OFFSET_DATE_TIME:Ljava/lang/Class;
     440: ldc           #117                // String of
     442: iconst_2
     443: anewarray     #113                // class java/lang/Class
     446: dup
     447: iconst_0
     448: getstatic     #105                // Field LOCAL_DATE_TIME:Ljava/lang/Class;
     451: aastore
     452: dup
     453: iconst_1
     454: getstatic     #111                // Field ZONE_OFFSET:Ljava/lang/Class;
     457: aastore
     458: invokestatic  #115                // Method getMethod:(Ljava/lang/Class;Ljava/lang/String;[Ljava/lang/Class;)Ljava/lang/reflect/Method;
     461: putstatic     #59                 // Field OFFSET_DATE_TIME_OF_LOCAL_DATE_TIME_ZONE_OFFSET:Ljava/lang/reflect/Method;
     464: getstatic     #109                // Field OFFSET_DATE_TIME:Ljava/lang/Class;
     467: ldc           #119                // String parse
     469: iconst_1
     470: anewarray     #113                // class java/lang/Class
     473: dup
     474: iconst_0
     475: ldc_w         #120                // class java/lang/CharSequence
     478: aastore
     479: invokestatic  #115                // Method getMethod:(Ljava/lang/Class;Ljava/lang/String;[Ljava/lang/Class;)Ljava/lang/reflect/Method;
     482: putstatic     #19                 // Field OFFSET_DATE_TIME_PARSE:Ljava/lang/reflect/Method;
     485: getstatic     #111                // Field ZONE_OFFSET:Ljava/lang/Class;
     488: ldc           #135                // String getTotalSeconds
     490: iconst_0
     491: anewarray     #113                // class java/lang/Class
     494: invokestatic  #115                // Method getMethod:(Ljava/lang/Class;Ljava/lang/String;[Ljava/lang/Class;)Ljava/lang/reflect/Method;
     497: putstatic     #90                 // Field ZONE_OFFSET_GET_TOTAL_SECONDS:Ljava/lang/reflect/Method;
     500: goto          591
     503: aconst_null
     504: putstatic     #39                 // Field LOCAL_TIME_OF_NANO:Ljava/lang/reflect/Method;
     507: aconst_null
     508: putstatic     #63                 // Field LOCAL_TIME_TO_NANO:Ljava/lang/reflect/Method;
     511: aconst_null
     512: putstatic     #96                 // Field LOCAL_DATE_OF_YEAR_MONTH_DAY:Ljava/lang/reflect/Method;
     515: aconst_null
     516: putstatic     #3                  // Field LOCAL_DATE_PARSE:Ljava/lang/reflect/Method;
     519: aconst_null
     520: putstatic     #85                 // Field LOCAL_DATE_GET_YEAR:Ljava/lang/reflect/Method;
     523: aconst_null
     524: putstatic     #86                 // Field LOCAL_DATE_GET_MONTH_VALUE:Ljava/lang/reflect/Method;
     527: aconst_null
     528: putstatic     #87                 // Field LOCAL_DATE_GET_DAY_OF_MONTH:Ljava/lang/reflect/Method;
     531: aconst_null
     532: putstatic     #97                 // Field LOCAL_DATE_AT_START_OF_DAY:Ljava/lang/reflect/Method;
     535: aconst_null
     536: putstatic     #71                 // Field INSTANT_GET_EPOCH_SECOND:Ljava/lang/reflect/Method;
     539: aconst_null
     540: putstatic     #72                 // Field INSTANT_GET_NANO:Ljava/lang/reflect/Method;
     543: aconst_null
     544: putstatic     #49                 // Field TIMESTAMP_TO_INSTANT:Ljava/lang/reflect/Method;
     547: aconst_null
     548: putstatic     #17                 // Field LOCAL_TIME_PARSE:Ljava/lang/reflect/Method;
     551: aconst_null
     552: putstatic     #98                 // Field LOCAL_DATE_TIME_PLUS_NANOS:Ljava/lang/reflect/Method;
     555: aconst_null
     556: putstatic     #67                 // Field LOCAL_DATE_TIME_TO_LOCAL_DATE:Ljava/lang/reflect/Method;
     559: aconst_null
     560: putstatic     #89                 // Field LOCAL_DATE_TIME_TO_LOCAL_TIME:Ljava/lang/reflect/Method;
     563: aconst_null
     564: putstatic     #18                 // Field LOCAL_DATE_TIME_PARSE:Ljava/lang/reflect/Method;
     567: aconst_null
     568: putstatic     #57                 // Field ZONE_OFFSET_OF_TOTAL_SECONDS:Ljava/lang/reflect/Method;
     571: aconst_null
     572: putstatic     #82                 // Field OFFSET_DATE_TIME_TO_LOCAL_DATE_TIME:Ljava/lang/reflect/Method;
     575: aconst_null
     576: putstatic     #83                 // Field OFFSET_DATE_TIME_GET_OFFSET:Ljava/lang/reflect/Method;
     579: aconst_null
     580: putstatic     #59                 // Field OFFSET_DATE_TIME_OF_LOCAL_DATE_TIME_ZONE_OFFSET:Ljava/lang/reflect/Method;
     583: aconst_null
     584: putstatic     #19                 // Field OFFSET_DATE_TIME_PARSE:Ljava/lang/reflect/Method;
     587: aconst_null
     588: putstatic     #90                 // Field ZONE_OFFSET_GET_TOTAL_SECONDS:Ljava/lang/reflect/Method;
     591: return
}
