Compiled from "SmallMap.java"
public class org.h2.util.SmallMap {
  private final java.util.HashMap<java.lang.Integer, java.lang.Object> map;

  private java.lang.Object cache;

  private int cacheId;

  private int lastId;

  private final int maxElements;

  public org.h2.util.SmallMap(int);
    Code:
       0: aload_0
       1: invokespecial #1                  // Method java/lang/Object."<init>":()V
       4: aload_0
       5: new           #2                  // class java/util/HashMap
       8: dup
       9: invokespecial #3                  // Method java/util/HashMap."<init>":()V
      12: putfield      #4                  // Field map:Ljava/util/HashMap;
      15: aload_0
      16: iload_1
      17: putfield      #5                  // Field maxElements:I
      20: return

  public int addObject(int, java.lang.Object);
    Code:
       0: aload_0
       1: getfield      #4                  // Field map:Ljava/util/HashMap;
       4: invokevirtual #6                  // Method java/util/HashMap.size:()I
       7: aload_0
       8: getfield      #5                  // Field maxElements:I
      11: iconst_2
      12: imul
      13: if_icmple     75
      16: aload_0
      17: getfield      #4                  // Field map:Ljava/util/HashMap;
      20: invokevirtual #7                  // Method java/util/HashMap.keySet:()Ljava/util/Set;
      23: invokeinterface #8,  1            // InterfaceMethod java/util/Set.iterator:()Ljava/util/Iterator;
      28: astore_3
      29: aload_3
      30: invokeinterface #9,  1            // InterfaceMethod java/util/Iterator.hasNext:()Z
      35: ifeq          75
      38: aload_3
      39: invokeinterface #10,  1           // InterfaceMethod java/util/Iterator.next:()Ljava/lang/Object;
      44: checkcast     #11                 // class java/lang/Integer
      47: astore        4
      49: aload         4
      51: invokevirtual #12                 // Method java/lang/Integer.intValue:()I
      54: aload_0
      55: getfield      #5                  // Field maxElements:I
      58: iadd
      59: aload_0
      60: getfield      #13                 // Field lastId:I
      63: if_icmpge     72
      66: aload_3
      67: invokeinterface #14,  1           // InterfaceMethod java/util/Iterator.remove:()V
      72: goto          29
      75: iload_1
      76: aload_0
      77: getfield      #13                 // Field lastId:I
      80: if_icmple     88
      83: aload_0
      84: iload_1
      85: putfield      #13                 // Field lastId:I
      88: aload_0
      89: getfield      #4                  // Field map:Ljava/util/HashMap;
      92: iload_1
      93: invokestatic  #15                 // Method java/lang/Integer.valueOf:(I)Ljava/lang/Integer;
      96: aload_2
      97: invokevirtual #16                 // Method java/util/HashMap.put:(Ljava/lang/Object;Ljava/lang/Object;)Ljava/lang/Object;
     100: pop
     101: aload_0
     102: iload_1
     103: putfield      #17                 // Field cacheId:I
     106: aload_0
     107: aload_2
     108: putfield      #18                 // Field cache:Ljava/lang/Object;
     111: iload_1
     112: ireturn

  public void freeObject(int);
    Code:
       0: aload_0
       1: getfield      #17                 // Field cacheId:I
       4: iload_1
       5: if_icmpne     18
       8: aload_0
       9: iconst_m1
      10: putfield      #17                 // Field cacheId:I
      13: aload_0
      14: aconst_null
      15: putfield      #18                 // Field cache:Ljava/lang/Object;
      18: aload_0
      19: getfield      #4                  // Field map:Ljava/util/HashMap;
      22: iload_1
      23: invokestatic  #15                 // Method java/lang/Integer.valueOf:(I)Ljava/lang/Integer;
      26: invokevirtual #19                 // Method java/util/HashMap.remove:(Ljava/lang/Object;)Ljava/lang/Object;
      29: pop
      30: return

  public java.lang.Object getObject(int, boolean);
    Code:
       0: iload_1
       1: aload_0
       2: getfield      #17                 // Field cacheId:I
       5: if_icmpne     13
       8: aload_0
       9: getfield      #18                 // Field cache:Ljava/lang/Object;
      12: areturn
      13: aload_0
      14: getfield      #4                  // Field map:Ljava/util/HashMap;
      17: iload_1
      18: invokestatic  #15                 // Method java/lang/Integer.valueOf:(I)Ljava/lang/Integer;
      21: invokevirtual #20                 // Method java/util/HashMap.get:(Ljava/lang/Object;)Ljava/lang/Object;
      24: astore_3
      25: aload_3
      26: ifnonnull     39
      29: iload_2
      30: ifne          39
      33: ldc           #21                 // int 90007
      35: invokestatic  #22                 // Method org/h2/message/DbException.get:(I)Lorg/h2/message/DbException;
      38: athrow
      39: aload_3
      40: areturn
}
