Compiled from "SourceCompiler.java"
class org.h2.util.SourceCompiler$ClassFileManager$1 extends java.security.SecureClassLoader {
  final org.h2.util.SourceCompiler$ClassFileManager this$0;

  org.h2.util.SourceCompiler$ClassFileManager$1(org.h2.util.SourceCompiler$ClassFileManager);
    Code:
       0: aload_0
       1: aload_1
       2: putfield      #1                  // Field this$0:Lorg/h2/util/SourceCompiler$ClassFileManager;
       5: aload_0
       6: invokespecial #2                  // Method java/security/SecureClassLoader."<init>":()V
       9: return

  protected java.lang.Class<?> findClass(java.lang.String) throws java.lang.ClassNotFoundException;
    Code:
       0: aload_0
       1: getfield      #1                  // Field this$0:Lorg/h2/util/SourceCompiler$ClassFileManager;
       4: getfield      #3                  // Field org/h2/util/SourceCompiler$ClassFileManager.classObject:Lorg/h2/util/SourceCompiler$JavaClassObject;
       7: invokevirtual #4                  // Method org/h2/util/SourceCompiler$JavaClassObject.getBytes:()[B
      10: astore_2
      11: aload_0
      12: aload_1
      13: aload_2
      14: iconst_0
      15: aload_2
      16: arraylength
      17: invokespecial #5                  // Method java/security/SecureClassLoader.defineClass:(Ljava/lang/String;[BII)Ljava/lang/Class;
      20: areturn
}
