Compiled from "ServletResourceManager.java"
public class org.wildfly.extension.undertow.deployment.ServletResourceManager implements io.undertow.server.handlers.resource.ResourceManager {
  private final io.undertow.server.handlers.resource.PathResourceManager deploymentResourceManager;

  private final java.util.Collection<org.jboss.vfs.VirtualFile> overlays;

  private final boolean explodedDeployment;

  public org.wildfly.extension.undertow.deployment.ServletResourceManager(org.jboss.vfs.VirtualFile, java.util.Collection<org.jboss.vfs.VirtualFile>, boolean, boolean) throws java.io.IOException;
    Code:
       0: aload_0
       1: invokespecial #1                  // Method java/lang/Object."<init>":()V
       4: aload_0
       5: iload_3
       6: putfield      #2                  // Field explodedDeployment:Z
       9: aload_1
      10: invokevirtual #3                  // Method org/jboss/vfs/VirtualFile.getPhysicalFile:()Ljava/io/File;
      13: invokevirtual #4                  // Method java/io/File.toPath:()Ljava/nio/file/Path;
      16: iconst_0
      17: anewarray     #5                  // class java/nio/file/LinkOption
      20: invokeinterface #6,  2            // InterfaceMethod java/nio/file/Path.toRealPath:([Ljava/nio/file/LinkOption;)Ljava/nio/file/Path;
      25: astore        5
      27: aload_0
      28: new           #7                  // class io/undertow/server/handlers/resource/PathResourceManager
      31: dup
      32: aload         5
      34: ldc2_w        #8                  // long 1048576l
      37: iload         4
      39: iconst_1
      40: anewarray     #10                 // class java/lang/String
      43: dup
      44: iconst_0
      45: ldc           #11                 // String /
      47: aastore
      48: invokespecial #12                 // Method io/undertow/server/handlers/resource/PathResourceManager."<init>":(Ljava/nio/file/Path;JZ[Ljava/lang/String;)V
      51: putfield      #13                 // Field deploymentResourceManager:Lio/undertow/server/handlers/resource/PathResourceManager;
      54: aload_0
      55: aload_2
      56: putfield      #14                 // Field overlays:Ljava/util/Collection;
      59: return

  public io.undertow.server.handlers.resource.Resource getResource(java.lang.String) throws java.io.IOException;
    Code:
       0: aload_0
       1: getfield      #13                 // Field deploymentResourceManager:Lio/undertow/server/handlers/resource/PathResourceManager;
       4: aload_1
       5: invokevirtual #15                 // Method io/undertow/server/handlers/resource/PathResourceManager.getResource:(Ljava/lang/String;)Lio/undertow/server/handlers/resource/Resource;
       8: astore_2
       9: aload_2
      10: ifnull        23
      13: new           #16                 // class org/wildfly/extension/undertow/deployment/ServletResource
      16: dup
      17: aload_0
      18: aload_2
      19: invokespecial #17                 // Method org/wildfly/extension/undertow/deployment/ServletResource."<init>":(Lorg/wildfly/extension/undertow/deployment/ServletResourceManager;Lio/undertow/server/handlers/resource/Resource;)V
      22: areturn
      23: aload_1
      24: astore_3
      25: aload_3
      26: ldc           #11                 // String /
      28: invokevirtual #18                 // Method java/lang/String.startsWith:(Ljava/lang/String;)Z
      31: ifeq          40
      34: aload_3
      35: iconst_1
      36: invokevirtual #19                 // Method java/lang/String.substring:(I)Ljava/lang/String;
      39: astore_3
      40: aload_0
      41: getfield      #14                 // Field overlays:Ljava/util/Collection;
      44: ifnull        123
      47: aload_0
      48: getfield      #14                 // Field overlays:Ljava/util/Collection;
      51: invokeinterface #20,  1           // InterfaceMethod java/util/Collection.iterator:()Ljava/util/Iterator;
      56: astore        4
      58: aload         4
      60: invokeinterface #21,  1           // InterfaceMethod java/util/Iterator.hasNext:()Z
      65: ifeq          123
      68: aload         4
      70: invokeinterface #22,  1           // InterfaceMethod java/util/Iterator.next:()Ljava/lang/Object;
      75: checkcast     #23                 // class org/jboss/vfs/VirtualFile
      78: astore        5
      80: aload         5
      82: aload_3
      83: invokevirtual #24                 // Method org/jboss/vfs/VirtualFile.getChild:(Ljava/lang/String;)Lorg/jboss/vfs/VirtualFile;
      86: astore        6
      88: aload         6
      90: invokevirtual #25                 // Method org/jboss/vfs/VirtualFile.exists:()Z
      93: ifeq          120
      96: new           #16                 // class org/wildfly/extension/undertow/deployment/ServletResource
      99: dup
     100: aload_0
     101: new           #26                 // class org/wildfly/extension/undertow/deployment/VirtualFileResource
     104: dup
     105: aload         5
     107: invokevirtual #3                  // Method org/jboss/vfs/VirtualFile.getPhysicalFile:()Ljava/io/File;
     110: aload         6
     112: aload_1
     113: invokespecial #27                 // Method org/wildfly/extension/undertow/deployment/VirtualFileResource."<init>":(Ljava/io/File;Lorg/jboss/vfs/VirtualFile;Ljava/lang/String;)V
     116: invokespecial #17                 // Method org/wildfly/extension/undertow/deployment/ServletResource."<init>":(Lorg/wildfly/extension/undertow/deployment/ServletResourceManager;Lio/undertow/server/handlers/resource/Resource;)V
     119: areturn
     120: goto          58
     123: aconst_null
     124: areturn

  public boolean isResourceChangeListenerSupported();
    Code:
       0: aload_0
       1: getfield      #2                  // Field explodedDeployment:Z
       4: ireturn

  public void registerResourceChangeListener(io.undertow.server.handlers.resource.ResourceChangeListener);
    Code:
       0: aload_0
       1: getfield      #13                 // Field deploymentResourceManager:Lio/undertow/server/handlers/resource/PathResourceManager;
       4: aload_1
       5: invokevirtual #28                 // Method io/undertow/server/handlers/resource/PathResourceManager.registerResourceChangeListener:(Lio/undertow/server/handlers/resource/ResourceChangeListener;)V
       8: return

  public void removeResourceChangeListener(io.undertow.server.handlers.resource.ResourceChangeListener);
    Code:
       0: aload_0
       1: getfield      #13                 // Field deploymentResourceManager:Lio/undertow/server/handlers/resource/PathResourceManager;
       4: aload_1
       5: invokevirtual #29                 // Method io/undertow/server/handlers/resource/PathResourceManager.removeResourceChangeListener:(Lio/undertow/server/handlers/resource/ResourceChangeListener;)V
       8: return

  public void close() throws java.io.IOException;
    Code:
       0: aload_0
       1: getfield      #13                 // Field deploymentResourceManager:Lio/undertow/server/handlers/resource/PathResourceManager;
       4: invokevirtual #30                 // Method io/undertow/server/handlers/resource/PathResourceManager.close:()V
       7: return

  public java.util.List<io.undertow.server.handlers.resource.Resource> list(java.lang.String);
    Code:
       0: new           #31                 // class java/util/ArrayList
       3: dup
       4: invokespecial #32                 // Method java/util/ArrayList."<init>":()V
       7: astore_2
       8: aload_0
       9: getfield      #13                 // Field deploymentResourceManager:Lio/undertow/server/handlers/resource/PathResourceManager;
      12: aload_1
      13: invokevirtual #15                 // Method io/undertow/server/handlers/resource/PathResourceManager.getResource:(Ljava/lang/String;)Lio/undertow/server/handlers/resource/Resource;
      16: astore_3
      17: aload_3
      18: ifnull        76
      21: aload_3
      22: invokeinterface #33,  1           // InterfaceMethod io/undertow/server/handlers/resource/Resource.list:()Ljava/util/List;
      27: invokeinterface #34,  1           // InterfaceMethod java/util/List.iterator:()Ljava/util/Iterator;
      32: astore        4
      34: aload         4
      36: invokeinterface #21,  1           // InterfaceMethod java/util/Iterator.hasNext:()Z
      41: ifeq          76
      44: aload         4
      46: invokeinterface #22,  1           // InterfaceMethod java/util/Iterator.next:()Ljava/lang/Object;
      51: checkcast     #35                 // class io/undertow/server/handlers/resource/Resource
      54: astore        5
      56: aload_2
      57: new           #16                 // class org/wildfly/extension/undertow/deployment/ServletResource
      60: dup
      61: aload_0
      62: aload         5
      64: invokespecial #17                 // Method org/wildfly/extension/undertow/deployment/ServletResource."<init>":(Lorg/wildfly/extension/undertow/deployment/ServletResourceManager;Lio/undertow/server/handlers/resource/Resource;)V
      67: invokeinterface #36,  2           // InterfaceMethod java/util/List.add:(Ljava/lang/Object;)Z
      72: pop
      73: goto          34
      76: aload_1
      77: astore        4
      79: aload         4
      81: ldc           #11                 // String /
      83: invokevirtual #18                 // Method java/lang/String.startsWith:(Ljava/lang/String;)Z
      86: ifeq          97
      89: aload         4
      91: iconst_1
      92: invokevirtual #19                 // Method java/lang/String.substring:(I)Ljava/lang/String;
      95: astore        4
      97: aload_0
      98: getfield      #14                 // Field overlays:Ljava/util/Collection;
     101: ifnull        228
     104: aload_0
     105: getfield      #14                 // Field overlays:Ljava/util/Collection;
     108: invokeinterface #20,  1           // InterfaceMethod java/util/Collection.iterator:()Ljava/util/Iterator;
     113: astore        5
     115: aload         5
     117: invokeinterface #21,  1           // InterfaceMethod java/util/Iterator.hasNext:()Z
     122: ifeq          228
     125: aload         5
     127: invokeinterface #22,  1           // InterfaceMethod java/util/Iterator.next:()Ljava/lang/Object;
     132: checkcast     #23                 // class org/jboss/vfs/VirtualFile
     135: astore        6
     137: aload         6
     139: aload         4
     141: invokevirtual #24                 // Method org/jboss/vfs/VirtualFile.getChild:(Ljava/lang/String;)Lorg/jboss/vfs/VirtualFile;
     144: astore        7
     146: aload         7
     148: invokevirtual #25                 // Method org/jboss/vfs/VirtualFile.exists:()Z
     151: ifeq          225
     154: new           #26                 // class org/wildfly/extension/undertow/deployment/VirtualFileResource
     157: dup
     158: aload         6
     160: invokevirtual #3                  // Method org/jboss/vfs/VirtualFile.getPhysicalFile:()Ljava/io/File;
     163: aload         7
     165: aload_1
     166: invokespecial #27                 // Method org/wildfly/extension/undertow/deployment/VirtualFileResource."<init>":(Ljava/io/File;Lorg/jboss/vfs/VirtualFile;Ljava/lang/String;)V
     169: astore        8
     171: aload         8
     173: invokevirtual #37                 // Method org/wildfly/extension/undertow/deployment/VirtualFileResource.list:()Ljava/util/List;
     176: invokeinterface #34,  1           // InterfaceMethod java/util/List.iterator:()Ljava/util/Iterator;
     181: astore        9
     183: aload         9
     185: invokeinterface #21,  1           // InterfaceMethod java/util/Iterator.hasNext:()Z
     190: ifeq          225
     193: aload         9
     195: invokeinterface #22,  1           // InterfaceMethod java/util/Iterator.next:()Ljava/lang/Object;
     200: checkcast     #35                 // class io/undertow/server/handlers/resource/Resource
     203: astore        10
     205: aload_2
     206: new           #16                 // class org/wildfly/extension/undertow/deployment/ServletResource
     209: dup
     210: aload_0
     211: aload         10
     213: invokespecial #17                 // Method org/wildfly/extension/undertow/deployment/ServletResource."<init>":(Lorg/wildfly/extension/undertow/deployment/ServletResourceManager;Lio/undertow/server/handlers/resource/Resource;)V
     216: invokeinterface #36,  2           // InterfaceMethod java/util/List.add:(Ljava/lang/Object;)Z
     221: pop
     222: goto          183
     225: goto          115
     228: aload_2
     229: areturn
     230: astore_2
     231: new           #39                 // class java/lang/RuntimeException
     234: dup
     235: aload_2
     236: invokespecial #40                 // Method java/lang/RuntimeException."<init>":(Ljava/lang/Throwable;)V
     239: athrow
    Exception table:
       from    to  target type
           0   229   230   Class java/io/IOException
}
