Compiled from "ArrayMapOwner.kt"
public abstract class kotlin.reflect.jvm.internal.impl.util.AbstractArrayMapOwner<K, V> implements java.lang.Iterable<V>, kotlin.jvm.internal.markers.KMappedMarker {
  public kotlin.reflect.jvm.internal.impl.util.AbstractArrayMapOwner();
    Code:
       0: aload_0
       1: invokespecial #11                 // Method java/lang/Object."<init>":()V
       4: return

  protected abstract kotlin.reflect.jvm.internal.impl.util.ArrayMap<V> getArrayMap();

  protected abstract kotlin.reflect.jvm.internal.impl.util.TypeRegistry<K, V> getTypeRegistry();

  protected abstract void registerComponent(java.lang.String, V);

  protected final void registerComponent(kotlin.reflect.KClass<? extends K>, V);
    Code:
       0: aload_1
       1: ldc           #1                  // String tClass
       3: invokestatic  #13                 // Method kotlin/jvm/internal/Intrinsics.checkNotNullParameter:(Ljava/lang/Object;Ljava/lang/String;)V
       6: aload_2
       7: ldc           #2                  // String value
       9: invokestatic  #13                 // Method kotlin/jvm/internal/Intrinsics.checkNotNullParameter:(Ljava/lang/Object;Ljava/lang/String;)V
      12: aload_0
      13: aload_1
      14: invokeinterface #18,  1           // InterfaceMethod kotlin/reflect/KClass.getQualifiedName:()Ljava/lang/String;
      19: dup
      20: invokestatic  #12                 // Method kotlin/jvm/internal/Intrinsics.checkNotNull:(Ljava/lang/Object;)V
      23: aload_2
      24: invokevirtual #15                 // Method registerComponent:(Ljava/lang/String;Ljava/lang/Object;)V
      27: return

  public final java.util.Iterator<V> iterator();
    Code:
       0: aload_0
       1: invokevirtual #14                 // Method getArrayMap:()Lkotlin/reflect/jvm/internal/impl/util/ArrayMap;
       4: invokevirtual #17                 // Method kotlin/reflect/jvm/internal/impl/util/ArrayMap.iterator:()Ljava/util/Iterator;
       7: areturn

  public final boolean isEmpty();
    Code:
       0: aload_0
       1: invokevirtual #14                 // Method getArrayMap:()Lkotlin/reflect/jvm/internal/impl/util/ArrayMap;
       4: invokevirtual #16                 // Method kotlin/reflect/jvm/internal/impl/util/ArrayMap.getSize:()I
       7: ifne          14
      10: iconst_1
      11: goto          15
      14: iconst_0
      15: ireturn
}
