Compiled from "ArrayMap.kt"
public final class kotlin.reflect.jvm.internal.impl.util.ArrayMapImpl<T> extends kotlin.reflect.jvm.internal.impl.util.ArrayMap<T> {
  public static final kotlin.reflect.jvm.internal.impl.util.ArrayMapImpl$Companion Companion;

  private java.lang.Object[] data;

  private int size;

  private kotlin.reflect.jvm.internal.impl.util.ArrayMapImpl(java.lang.Object[], int);
    Code:
       0: aload_0
       1: aconst_null
       2: invokespecial #19                 // Method kotlin/reflect/jvm/internal/impl/util/ArrayMap."<init>":(Lkotlin/jvm/internal/DefaultConstructorMarker;)V
       5: aload_0
       6: aload_1
       7: putfield      #13                 // Field data:[Ljava/lang/Object;
      10: aload_0
      11: iload_2
      12: putfield      #14                 // Field size:I
      15: return

  public kotlin.reflect.jvm.internal.impl.util.ArrayMapImpl();
    Code:
       0: aload_0
       1: bipush        20
       3: anewarray     #3                  // class java/lang/Object
       6: iconst_0
       7: invokespecial #20                 // Method "<init>":([Ljava/lang/Object;I)V
      10: return

  public int getSize();
    Code:
       0: aload_0
       1: getfield      #14                 // Field size:I
       4: ireturn

  private final void ensureCapacity(int);
    Code:
       0: aload_0
       1: getfield      #13                 // Field data:[Ljava/lang/Object;
       4: arraylength
       5: iload_1
       6: if_icmple     10
       9: return
      10: aload_0
      11: getfield      #13                 // Field data:[Ljava/lang/Object;
      14: arraylength
      15: istore_2
      16: iload_2
      17: iconst_2
      18: imul
      19: istore_2
      20: iload_2
      21: iload_1
      22: if_icmple     16
      25: aload_0
      26: aload_0
      27: getfield      #13                 // Field data:[Ljava/lang/Object;
      30: iload_2
      31: invokestatic  #15                 // Method java/util/Arrays.copyOf:([Ljava/lang/Object;I)[Ljava/lang/Object;
      34: dup
      35: ldc           #1                  // String copyOf(this, newSize)
      37: invokestatic  #17                 // Method kotlin/jvm/internal/Intrinsics.checkNotNullExpressionValue:(Ljava/lang/Object;Ljava/lang/String;)V
      40: putfield      #13                 // Field data:[Ljava/lang/Object;
      43: return

  public void set(int, T);
    Code:
       0: aload_2
       1: ldc           #2                  // String value
       3: invokestatic  #18                 // Method kotlin/jvm/internal/Intrinsics.checkNotNullParameter:(Ljava/lang/Object;Ljava/lang/String;)V
       6: aload_0
       7: iload_1
       8: invokespecial #21                 // Method ensureCapacity:(I)V
      11: aload_0
      12: getfield      #13                 // Field data:[Ljava/lang/Object;
      15: iload_1
      16: aaload
      17: ifnonnull     32
      20: aload_0
      21: invokevirtual #22                 // Method getSize:()I
      24: istore_3
      25: aload_0
      26: iload_3
      27: iconst_1
      28: iadd
      29: putfield      #14                 // Field size:I
      32: aload_0
      33: getfield      #13                 // Field data:[Ljava/lang/Object;
      36: iload_1
      37: aload_2
      38: aastore
      39: return

  public T get(int);
    Code:
       0: aload_0
       1: getfield      #13                 // Field data:[Ljava/lang/Object;
       4: iload_1
       5: invokestatic  #16                 // Method kotlin/collections/ArraysKt.getOrNull:([Ljava/lang/Object;I)Ljava/lang/Object;
       8: areturn

  public java.util.Iterator<T> iterator();
    Code:
       0: new           #11                 // class kotlin/reflect/jvm/internal/impl/util/ArrayMapImpl$iterator$1
       3: dup
       4: aload_0
       5: invokespecial #24                 // Method kotlin/reflect/jvm/internal/impl/util/ArrayMapImpl$iterator$1."<init>":(Lkotlin/reflect/jvm/internal/impl/util/ArrayMapImpl;)V
       8: checkcast     #5                  // class java/util/Iterator
      11: areturn

  public static final java.lang.Object[] access$getData$p(kotlin.reflect.jvm.internal.impl.util.ArrayMapImpl);
    Code:
       0: aload_0
       1: getfield      #13                 // Field data:[Ljava/lang/Object;
       4: areturn

  static {};
    Code:
       0: new           #10                 // class kotlin/reflect/jvm/internal/impl/util/ArrayMapImpl$Companion
       3: dup
       4: aconst_null
       5: invokespecial #23                 // Method kotlin/reflect/jvm/internal/impl/util/ArrayMapImpl$Companion."<init>":(Lkotlin/jvm/internal/DefaultConstructorMarker;)V
       8: putstatic     #12                 // Field Companion:Lkotlin/reflect/jvm/internal/impl/util/ArrayMapImpl$Companion;
      11: return
}
