Compiled from "ArrayMap.kt"
public final class kotlin.reflect.jvm.internal.impl.util.EmptyArrayMap$iterator$1 implements java.util.Iterator,kotlin.jvm.internal.markers.KMappedMarker {
  kotlin.reflect.jvm.internal.impl.util.EmptyArrayMap$iterator$1();
    Code:
       0: aload_0
       1: invokespecial #9                  // Method java/lang/Object."<init>":()V
       4: return

  public boolean hasNext();
    Code:
       0: iconst_0
       1: ireturn

  public java.lang.Void next();
    Code:
       0: new           #5                  // class java/util/NoSuchElementException
       3: dup
       4: invokespecial #11                 // Method java/util/NoSuchElementException."<init>":()V
       7: athrow

  public void remove();
    Code:
       0: new           #3                  // class java/lang/UnsupportedOperationException
       3: dup
       4: ldc           #1                  // String Operation is not supported for read-only collection
       6: invokespecial #10                 // Method java/lang/UnsupportedOperationException."<init>":(Ljava/lang/String;)V
       9: athrow

  public java.lang.Object next();
    Code:
       0: aload_0
       1: invokevirtual #12                 // Method next:()Ljava/lang/Void;
       4: areturn
}
