Compiled from "StrippedConcurrentLinkedDeque.java"
abstract class org.infinispan.commons.util.concurrent.jdk8backported.StrippedConcurrentLinkedDeque$AbstractItr implements java.util.Iterator<org.infinispan.commons.util.concurrent.jdk8backported.StrippedConcurrentLinkedDeque$DequeNode<E>> {
  private org.infinispan.commons.util.concurrent.jdk8backported.StrippedConcurrentLinkedDeque$DequeNode<E> nextNode;

  private org.infinispan.commons.util.concurrent.jdk8backported.StrippedConcurrentLinkedDeque$DequeNode<E> lastRet;

  final org.infinispan.commons.util.concurrent.jdk8backported.StrippedConcurrentLinkedDeque this$0;

  abstract org.infinispan.commons.util.concurrent.jdk8backported.StrippedConcurrentLinkedDeque$DequeNode<E> startNode();

  abstract org.infinispan.commons.util.concurrent.jdk8backported.StrippedConcurrentLinkedDeque$DequeNode<E> nextNode(org.infinispan.commons.util.concurrent.jdk8backported.StrippedConcurrentLinkedDeque$DequeNode<E>);

  org.infinispan.commons.util.concurrent.jdk8backported.StrippedConcurrentLinkedDeque$AbstractItr(org.infinispan.commons.util.concurrent.jdk8backported.StrippedConcurrentLinkedDeque);
    Code:
       0: aload_0
       1: aload_1
       2: putfield      #1                  // Field this$0:Lorg/infinispan/commons/util/concurrent/jdk8backported/StrippedConcurrentLinkedDeque;
       5: aload_0
       6: invokespecial #2                  // Method java/lang/Object."<init>":()V
       9: aload_0
      10: invokespecial #3                  // Method advance:()V
      13: return

  private void advance();
    Code:
       0: aload_0
       1: aload_0
       2: getfield      #4                  // Field nextNode:Lorg/infinispan/commons/util/concurrent/jdk8backported/StrippedConcurrentLinkedDeque$DequeNode;
       5: putfield      #5                  // Field lastRet:Lorg/infinispan/commons/util/concurrent/jdk8backported/StrippedConcurrentLinkedDeque$DequeNode;
       8: aload_0
       9: getfield      #4                  // Field nextNode:Lorg/infinispan/commons/util/concurrent/jdk8backported/StrippedConcurrentLinkedDeque$DequeNode;
      12: ifnonnull     22
      15: aload_0
      16: invokevirtual #6                  // Method startNode:()Lorg/infinispan/commons/util/concurrent/jdk8backported/StrippedConcurrentLinkedDeque$DequeNode;
      19: goto          30
      22: aload_0
      23: aload_0
      24: getfield      #4                  // Field nextNode:Lorg/infinispan/commons/util/concurrent/jdk8backported/StrippedConcurrentLinkedDeque$DequeNode;
      27: invokevirtual #7                  // Method nextNode:(Lorg/infinispan/commons/util/concurrent/jdk8backported/StrippedConcurrentLinkedDeque$DequeNode;)Lorg/infinispan/commons/util/concurrent/jdk8backported/StrippedConcurrentLinkedDeque$DequeNode;
      30: astore_1
      31: aload_1
      32: ifnonnull     43
      35: aload_0
      36: aconst_null
      37: putfield      #4                  // Field nextNode:Lorg/infinispan/commons/util/concurrent/jdk8backported/StrippedConcurrentLinkedDeque$DequeNode;
      40: goto          69
      43: aload_1
      44: getfield      #8                  // Field org/infinispan/commons/util/concurrent/jdk8backported/StrippedConcurrentLinkedDeque$DequeNode.item:Ljava/lang/Object;
      47: astore_2
      48: aload_2
      49: ifnull        60
      52: aload_0
      53: aload_1
      54: putfield      #4                  // Field nextNode:Lorg/infinispan/commons/util/concurrent/jdk8backported/StrippedConcurrentLinkedDeque$DequeNode;
      57: goto          69
      60: aload_0
      61: aload_1
      62: invokevirtual #7                  // Method nextNode:(Lorg/infinispan/commons/util/concurrent/jdk8backported/StrippedConcurrentLinkedDeque$DequeNode;)Lorg/infinispan/commons/util/concurrent/jdk8backported/StrippedConcurrentLinkedDeque$DequeNode;
      65: astore_1
      66: goto          31
      69: return

  public boolean hasNext();
    Code:
       0: aload_0
       1: getfield      #4                  // Field nextNode:Lorg/infinispan/commons/util/concurrent/jdk8backported/StrippedConcurrentLinkedDeque$DequeNode;
       4: ifnull        11
       7: iconst_1
       8: goto          12
      11: iconst_0
      12: ireturn

  public org.infinispan.commons.util.concurrent.jdk8backported.StrippedConcurrentLinkedDeque$DequeNode<E> next();
    Code:
       0: aload_0
       1: getfield      #4                  // Field nextNode:Lorg/infinispan/commons/util/concurrent/jdk8backported/StrippedConcurrentLinkedDeque$DequeNode;
       4: astore_1
       5: aload_1
       6: ifnonnull     17
       9: new           #9                  // class java/util/NoSuchElementException
      12: dup
      13: invokespecial #10                 // Method java/util/NoSuchElementException."<init>":()V
      16: athrow
      17: aload_0
      18: invokespecial #3                  // Method advance:()V
      21: aload_1
      22: areturn

  public void remove();
    Code:
       0: aload_0
       1: getfield      #5                  // Field lastRet:Lorg/infinispan/commons/util/concurrent/jdk8backported/StrippedConcurrentLinkedDeque$DequeNode;
       4: astore_1
       5: aload_1
       6: ifnonnull     17
       9: new           #11                 // class java/lang/IllegalStateException
      12: dup
      13: invokespecial #12                 // Method java/lang/IllegalStateException."<init>":()V
      16: athrow
      17: aload_1
      18: aconst_null
      19: putfield      #8                  // Field org/infinispan/commons/util/concurrent/jdk8backported/StrippedConcurrentLinkedDeque$DequeNode.item:Ljava/lang/Object;
      22: aload_0
      23: getfield      #1                  // Field this$0:Lorg/infinispan/commons/util/concurrent/jdk8backported/StrippedConcurrentLinkedDeque;
      26: aload_1
      27: invokevirtual #13                 // Method org/infinispan/commons/util/concurrent/jdk8backported/StrippedConcurrentLinkedDeque.unlink:(Lorg/infinispan/commons/util/concurrent/jdk8backported/StrippedConcurrentLinkedDeque$DequeNode;)V
      30: aload_0
      31: aconst_null
      32: putfield      #5                  // Field lastRet:Lorg/infinispan/commons/util/concurrent/jdk8backported/StrippedConcurrentLinkedDeque$DequeNode;
      35: return

  public java.lang.Object next();
    Code:
       0: aload_0
       1: invokevirtual #14                 // Method next:()Lorg/infinispan/commons/util/concurrent/jdk8backported/StrippedConcurrentLinkedDeque$DequeNode;
       4: areturn
}
