Compiled from "CleanerServiceLocator.java"
public final class net.openhft.chronicle.core.cleaner.CleanerServiceLocator {
  private static final org.slf4j.Logger LOGGER;

  private static boolean initialised;

  private static net.openhft.chronicle.core.cleaner.spi.ByteBufferCleanerService instance;

  public net.openhft.chronicle.core.cleaner.CleanerServiceLocator();
    Code:
       0: aload_0
       1: invokespecial #1                  // Method java/lang/Object."<init>":()V
       4: return

  public static synchronized net.openhft.chronicle.core.cleaner.spi.ByteBufferCleanerService cleanerService();
    Code:
       0: getstatic     #2                  // Field initialised:Z
       3: ifne          123
       6: ldc           #3                  // class net/openhft/chronicle/core/cleaner/spi/ByteBufferCleanerService
       8: invokestatic  #4                  // Method java/lang/Thread.currentThread:()Ljava/lang/Thread;
      11: invokevirtual #5                  // Method java/lang/Thread.getContextClassLoader:()Ljava/lang/ClassLoader;
      14: invokestatic  #6                  // Method java/util/ServiceLoader.load:(Ljava/lang/Class;Ljava/lang/ClassLoader;)Ljava/util/ServiceLoader;
      17: astore_0
      18: aconst_null
      19: astore_1
      20: aload_0
      21: invokevirtual #7                  // Method java/util/ServiceLoader.iterator:()Ljava/util/Iterator;
      24: astore_2
      25: aload_2
      26: invokeinterface #8,  1            // InterfaceMethod java/util/Iterator.hasNext:()Z
      31: ifeq          78
      34: aload_2
      35: invokeinterface #9,  1            // InterfaceMethod java/util/Iterator.next:()Ljava/lang/Object;
      40: checkcast     #3                  // class net/openhft/chronicle/core/cleaner/spi/ByteBufferCleanerService
      43: astore_3
      44: aload_3
      45: invokestatic  #10                 // Method isAllowedInThisMajorVersion:(Lnet/openhft/chronicle/core/cleaner/spi/ByteBufferCleanerService;)Z
      48: ifeq          75
      51: aload_1
      52: ifnull        73
      55: aload_3
      56: invokeinterface #11,  1           // InterfaceMethod net/openhft/chronicle/core/cleaner/spi/ByteBufferCleanerService.impact:()Lnet/openhft/chronicle/core/cleaner/spi/ByteBufferCleanerService$Impact;
      61: aload_1
      62: invokeinterface #11,  1           // InterfaceMethod net/openhft/chronicle/core/cleaner/spi/ByteBufferCleanerService.impact:()Lnet/openhft/chronicle/core/cleaner/spi/ByteBufferCleanerService$Impact;
      67: invokevirtual #12                 // Method net/openhft/chronicle/core/cleaner/spi/ByteBufferCleanerService$Impact.compareTo:(Ljava/lang/Enum;)I
      70: ifge          75
      73: aload_3
      74: astore_1
      75: goto          25
      78: goto          93
      81: astore_2
      82: getstatic     #14                 // Field LOGGER:Lorg/slf4j/Logger;
      85: ldc           #15                 // String Error while trying to load service providers
      87: aload_2
      88: invokeinterface #16,  3           // InterfaceMethod org/slf4j/Logger.warn:(Ljava/lang/String;Ljava/lang/Throwable;)V
      93: aload_1
      94: ifnonnull     115
      97: new           #17                 // class net/openhft/chronicle/core/cleaner/impl/reflect/ReflectionBasedByteBufferCleanerService
     100: dup
     101: invokespecial #18                 // Method net/openhft/chronicle/core/cleaner/impl/reflect/ReflectionBasedByteBufferCleanerService."<init>":()V
     104: astore_1
     105: getstatic     #14                 // Field LOGGER:Lorg/slf4j/Logger;
     108: ldc           #19                 // String Unable to find suitable cleaner service, falling back to using reflection
     110: invokeinterface #20,  2           // InterfaceMethod org/slf4j/Logger.info:(Ljava/lang/String;)V
     115: aload_1
     116: putstatic     #21                 // Field instance:Lnet/openhft/chronicle/core/cleaner/spi/ByteBufferCleanerService;
     119: iconst_1
     120: putstatic     #2                  // Field initialised:Z
     123: getstatic     #21                 // Field instance:Lnet/openhft/chronicle/core/cleaner/spi/ByteBufferCleanerService;
     126: areturn
    Exception table:
       from    to  target type
          20    78    81   Class java/util/ServiceConfigurationError

  private static boolean isAllowedInThisMajorVersion(net.openhft.chronicle.core.cleaner.spi.ByteBufferCleanerService);
    Code:
       0: aload_0
       1: invokevirtual #22                 // Method java/lang/Object.getClass:()Ljava/lang/Class;
       4: ldc           #23                 // class net/openhft/chronicle/core/annotation/TargetMajorVersion
       6: invokevirtual #24                 // Method java/lang/Class.getDeclaredAnnotation:(Ljava/lang/Class;)Ljava/lang/annotation/Annotation;
       9: checkcast     #23                 // class net/openhft/chronicle/core/annotation/TargetMajorVersion
      12: astore_1
      13: aload_1
      14: ifnull        80
      17: aload_1
      18: invokeinterface #25,  1           // InterfaceMethod net/openhft/chronicle/core/annotation/TargetMajorVersion.majorVersion:()I
      23: ifeq          80
      26: aload_1
      27: invokeinterface #25,  1           // InterfaceMethod net/openhft/chronicle/core/annotation/TargetMajorVersion.majorVersion:()I
      32: invokestatic  #26                 // Method net/openhft/chronicle/core/Jvm.majorVersion:()I
      35: if_icmpeq     80
      38: aload_1
      39: invokeinterface #27,  1           // InterfaceMethod net/openhft/chronicle/core/annotation/TargetMajorVersion.includeNewer:()Z
      44: ifeq          59
      47: invokestatic  #26                 // Method net/openhft/chronicle/core/Jvm.majorVersion:()I
      50: aload_1
      51: invokeinterface #25,  1           // InterfaceMethod net/openhft/chronicle/core/annotation/TargetMajorVersion.majorVersion:()I
      56: if_icmpgt     80
      59: aload_1
      60: invokeinterface #28,  1           // InterfaceMethod net/openhft/chronicle/core/annotation/TargetMajorVersion.includeOlder:()Z
      65: ifeq          84
      68: invokestatic  #26                 // Method net/openhft/chronicle/core/Jvm.majorVersion:()I
      71: aload_1
      72: invokeinterface #25,  1           // InterfaceMethod net/openhft/chronicle/core/annotation/TargetMajorVersion.majorVersion:()I
      77: if_icmpge     84
      80: iconst_1
      81: goto          85
      84: iconst_0
      85: ireturn

  static {};
    Code:
       0: ldc           #29                 // class net/openhft/chronicle/core/cleaner/CleanerServiceLocator
       2: invokestatic  #30                 // Method org/slf4j/LoggerFactory.getLogger:(Ljava/lang/Class;)Lorg/slf4j/Logger;
       5: putstatic     #14                 // Field LOGGER:Lorg/slf4j/Logger;
       8: iconst_0
       9: putstatic     #2                  // Field initialised:Z
      12: return
}
