Compiled from "Cflow.java"
public class javassist.runtime.Cflow$Depth {
  private int depth;

  javassist.runtime.Cflow$Depth();
    Code:
       0: aload_0
       1: invokespecial #1                  // Method java/lang/Object."<init>":()V
       4: aload_0
       5: iconst_0
       6: putfield      #2                  // Field depth:I
       9: return

  int value();
    Code:
       0: aload_0
       1: getfield      #2                  // Field depth:I
       4: ireturn

  void inc();
    Code:
       0: aload_0
       1: dup
       2: getfield      #2                  // Field depth:I
       5: iconst_1
       6: iadd
       7: putfield      #2                  // Field depth:I
      10: return

  void dec();
    Code:
       0: aload_0
       1: dup
       2: getfield      #2                  // Field depth:I
       5: iconst_1
       6: isub
       7: putfield      #2                  // Field depth:I
      10: return
}
