Compiled from "CreateEndpointRequest.java"
public interface software.amazon.awssdk.services.s3outposts.model.CreateEndpointRequest$Builder extends software.amazon.awssdk.services.s3outposts.model.S3OutpostsRequest$Builder, software.amazon.awssdk.core.SdkPojo, software.amazon.awssdk.utils.builder.CopyableBuilder<software.amazon.awssdk.services.s3outposts.model.CreateEndpointRequest$Builder, software.amazon.awssdk.services.s3outposts.model.CreateEndpointRequest> {
  public abstract software.amazon.awssdk.services.s3outposts.model.CreateEndpointRequest$Builder outpostId(java.lang.String);

  public abstract software.amazon.awssdk.services.s3outposts.model.CreateEndpointRequest$Builder subnetId(java.lang.String);

  public abstract software.amazon.awssdk.services.s3outposts.model.CreateEndpointRequest$Builder securityGroupId(java.lang.String);

  public abstract software.amazon.awssdk.services.s3outposts.model.CreateEndpointRequest$Builder overrideConfiguration(software.amazon.awssdk.awscore.AwsRequestOverrideConfiguration);

  public abstract software.amazon.awssdk.services.s3outposts.model.CreateEndpointRequest$Builder overrideConfiguration(java.util.function.Consumer<software.amazon.awssdk.awscore.AwsRequestOverrideConfiguration$Builder>);

  public default software.amazon.awssdk.awscore.AwsRequest$Builder overrideConfiguration(java.util.function.Consumer);
    Code:
       0: aload_0
       1: aload_1
       2: invokeinterface #1,  2            // InterfaceMethod overrideConfiguration:(Ljava/util/function/Consumer;)Lsoftware/amazon/awssdk/services/s3outposts/model/CreateEndpointRequest$Builder;
       7: areturn

  public default software.amazon.awssdk.awscore.AwsRequest$Builder overrideConfiguration(software.amazon.awssdk.awscore.AwsRequestOverrideConfiguration);
    Code:
       0: aload_0
       1: aload_1
       2: invokeinterface #2,  2            // InterfaceMethod overrideConfiguration:(Lsoftware/amazon/awssdk/awscore/AwsRequestOverrideConfiguration;)Lsoftware/amazon/awssdk/services/s3outposts/model/CreateEndpointRequest$Builder;
       7: areturn
}
