Compiled from "HttpUpgrade.java"
class org.xnio.http.HttpUpgrade$HttpUpgradeState$FailureNotifier extends org.xnio.IoFuture$HandlingNotifier<org.xnio.StreamConnection, java.lang.Object> {
  final org.xnio.http.HttpUpgrade$HttpUpgradeState this$0;

  private org.xnio.http.HttpUpgrade$HttpUpgradeState$FailureNotifier(org.xnio.http.HttpUpgrade$HttpUpgradeState);
    Code:
       0: aload_0
       1: aload_1
       2: putfield      #23                 // Field this$0:Lorg/xnio/http/HttpUpgrade$HttpUpgradeState;
       5: aload_0
       6: invokespecial #26                 // Method org/xnio/IoFuture$HandlingNotifier."<init>":()V
       9: return

  public void handleFailed(java.io.IOException, java.lang.Object);
    Code:
       0: aload_0
       1: getfield      #23                 // Field this$0:Lorg/xnio/http/HttpUpgrade$HttpUpgradeState;
       4: invokestatic  #35                 // Method org/xnio/http/HttpUpgrade$HttpUpgradeState.access$800:(Lorg/xnio/http/HttpUpgrade$HttpUpgradeState;)Lorg/xnio/FutureResult;
       7: aload_1
       8: invokevirtual #41                 // Method org/xnio/FutureResult.setException:(Ljava/io/IOException;)Z
      11: pop
      12: return

  public void handleCancelled(java.lang.Object);
    Code:
       0: aload_0
       1: getfield      #23                 // Field this$0:Lorg/xnio/http/HttpUpgrade$HttpUpgradeState;
       4: invokestatic  #35                 // Method org/xnio/http/HttpUpgrade$HttpUpgradeState.access$800:(Lorg/xnio/http/HttpUpgrade$HttpUpgradeState;)Lorg/xnio/FutureResult;
       7: invokevirtual #51                 // Method org/xnio/FutureResult.setCancelled:()Z
      10: pop
      11: return

  org.xnio.http.HttpUpgrade$HttpUpgradeState$FailureNotifier(org.xnio.http.HttpUpgrade$HttpUpgradeState, org.xnio.http.HttpUpgrade$1);
    Code:
       0: aload_0
       1: aload_1
       2: invokespecial #54                 // Method "<init>":(Lorg/xnio/http/HttpUpgrade$HttpUpgradeState;)V
       5: return
}
