Compiled from "CoreXMLSerializers.java"
public class io.dekorate.deps.jackson.databind.ext.CoreXMLSerializers extends io.dekorate.deps.jackson.databind.ser.Serializers$Base {
  public io.dekorate.deps.jackson.databind.ext.CoreXMLSerializers();
    Code:
       0: aload_0
       1: invokespecial #15                 // Method io/dekorate/deps/jackson/databind/ser/Serializers$Base."<init>":()V
       4: return

  public io.dekorate.deps.jackson.databind.JsonSerializer<?> findSerializer(io.dekorate.deps.jackson.databind.SerializationConfig, io.dekorate.deps.jackson.databind.JavaType, io.dekorate.deps.jackson.databind.BeanDescription);
    Code:
       0: aload_2
       1: invokevirtual #26                 // Method io/dekorate/deps/jackson/databind/JavaType.getRawClass:()Ljava/lang/Class;
       4: astore        4
       6: ldc           #28                 // class javax/xml/datatype/Duration
       8: aload         4
      10: invokevirtual #34                 // Method java/lang/Class.isAssignableFrom:(Ljava/lang/Class;)Z
      13: ifne          26
      16: ldc           #36                 // class javax/xml/namespace/QName
      18: aload         4
      20: invokevirtual #34                 // Method java/lang/Class.isAssignableFrom:(Ljava/lang/Class;)Z
      23: ifeq          30
      26: getstatic     #42                 // Field io/dekorate/deps/jackson/databind/ser/std/ToStringSerializer.instance:Lio/dekorate/deps/jackson/databind/ser/std/ToStringSerializer;
      29: areturn
      30: ldc           #44                 // class javax/xml/datatype/XMLGregorianCalendar
      32: aload         4
      34: invokevirtual #34                 // Method java/lang/Class.isAssignableFrom:(Ljava/lang/Class;)Z
      37: ifeq          44
      40: getstatic     #47                 // Field io/dekorate/deps/jackson/databind/ext/CoreXMLSerializers$XMLGregorianCalendarSerializer.instance:Lio/dekorate/deps/jackson/databind/ext/CoreXMLSerializers$XMLGregorianCalendarSerializer;
      43: areturn
      44: aconst_null
      45: areturn
}
