Compiled from "PrecomputePreferencesTableModel.java"
public class org.protege.editor.owl.ui.inference.PrecomputePreferencesTableModel extends javax.swing.table.AbstractTableModel {
  private static final long serialVersionUID;

  private java.util.Set<org.semanticweb.owlapi.reasoner.InferenceType> required;

  private java.util.Set<org.semanticweb.owlapi.reasoner.InferenceType> disallowed;

  public org.protege.editor.owl.ui.inference.PrecomputePreferencesTableModel(java.util.Set<org.semanticweb.owlapi.reasoner.InferenceType>, java.util.Set<org.semanticweb.owlapi.reasoner.InferenceType>);
    Code:
       0: aload_0
       1: invokespecial #1                  // Method javax/swing/table/AbstractTableModel."<init>":()V
       4: aload_0
       5: aload_1
       6: putfield      #2                  // Field required:Ljava/util/Set;
       9: aload_0
      10: aload_2
      11: putfield      #3                  // Field disallowed:Ljava/util/Set;
      14: return

  public int getRowCount();
    Code:
       0: invokestatic  #4                  // Method org/semanticweb/owlapi/reasoner/InferenceType.values:()[Lorg/semanticweb/owlapi/reasoner/InferenceType;
       3: arraylength
       4: ireturn

  public int getColumnCount();
    Code:
       0: invokestatic  #5                  // Method org/protege/editor/owl/ui/inference/PrecomputePreferencesTableModel$Column.values:()[Lorg/protege/editor/owl/ui/inference/PrecomputePreferencesTableModel$Column;
       3: arraylength
       4: ireturn

  public java.lang.String getColumnName(int);
    Code:
       0: invokestatic  #5                  // Method org/protege/editor/owl/ui/inference/PrecomputePreferencesTableModel$Column.values:()[Lorg/protege/editor/owl/ui/inference/PrecomputePreferencesTableModel$Column;
       3: iload_1
       4: aaload
       5: invokevirtual #6                  // Method org/protege/editor/owl/ui/inference/PrecomputePreferencesTableModel$Column.getColumnName:()Ljava/lang/String;
       8: areturn

  public java.lang.Class<?> getColumnClass(int);
    Code:
       0: invokestatic  #5                  // Method org/protege/editor/owl/ui/inference/PrecomputePreferencesTableModel$Column.values:()[Lorg/protege/editor/owl/ui/inference/PrecomputePreferencesTableModel$Column;
       3: iload_1
       4: aaload
       5: astore_2
       6: getstatic     #7                  // Field org/protege/editor/owl/ui/inference/PrecomputePreferencesTableModel$1.$SwitchMap$org$protege$editor$owl$ui$inference$PrecomputePreferencesTableModel$Column:[I
       9: aload_2
      10: invokevirtual #8                  // Method org/protege/editor/owl/ui/inference/PrecomputePreferencesTableModel$Column.ordinal:()I
      13: iaload
      14: tableswitch   { // 1 to 3
                     1: 40
                     2: 43
                     3: 43
               default: 46
          }
      40: ldc           #9                  // class java/lang/String
      42: areturn
      43: ldc           #10                 // class java/lang/Boolean
      45: areturn
      46: new           #11                 // class java/lang/UnsupportedOperationException
      49: dup
      50: ldc           #12                 // String Programmer Error: missed a case
      52: invokespecial #13                 // Method java/lang/UnsupportedOperationException."<init>":(Ljava/lang/String;)V
      55: athrow

  public boolean isCellEditable(int, int);
    Code:
       0: invokestatic  #5                  // Method org/protege/editor/owl/ui/inference/PrecomputePreferencesTableModel$Column.values:()[Lorg/protege/editor/owl/ui/inference/PrecomputePreferencesTableModel$Column;
       3: iload_2
       4: aaload
       5: astore_3
       6: getstatic     #7                  // Field org/protege/editor/owl/ui/inference/PrecomputePreferencesTableModel$1.$SwitchMap$org$protege$editor$owl$ui$inference$PrecomputePreferencesTableModel$Column:[I
       9: aload_3
      10: invokevirtual #8                  // Method org/protege/editor/owl/ui/inference/PrecomputePreferencesTableModel$Column.ordinal:()I
      13: iaload
      14: tableswitch   { // 1 to 3
                     1: 40
                     2: 42
                     3: 42
               default: 44
          }
      40: iconst_0
      41: ireturn
      42: iconst_1
      43: ireturn
      44: new           #11                 // class java/lang/UnsupportedOperationException
      47: dup
      48: ldc           #12                 // String Programmer Error: missed a case
      50: invokespecial #13                 // Method java/lang/UnsupportedOperationException."<init>":(Ljava/lang/String;)V
      53: athrow

  public java.lang.Object getValueAt(int, int);
    Code:
       0: invokestatic  #4                  // Method org/semanticweb/owlapi/reasoner/InferenceType.values:()[Lorg/semanticweb/owlapi/reasoner/InferenceType;
       3: iload_1
       4: aaload
       5: astore_3
       6: invokestatic  #5                  // Method org/protege/editor/owl/ui/inference/PrecomputePreferencesTableModel$Column.values:()[Lorg/protege/editor/owl/ui/inference/PrecomputePreferencesTableModel$Column;
       9: iload_2
      10: aaload
      11: astore        4
      13: getstatic     #7                  // Field org/protege/editor/owl/ui/inference/PrecomputePreferencesTableModel$1.$SwitchMap$org$protege$editor$owl$ui$inference$PrecomputePreferencesTableModel$Column:[I
      16: aload         4
      18: invokevirtual #8                  // Method org/protege/editor/owl/ui/inference/PrecomputePreferencesTableModel$Column.ordinal:()I
      21: iaload
      22: tableswitch   { // 1 to 3
                     1: 48
                     2: 53
                     3: 67
               default: 81
          }
      48: aload_3
      49: invokestatic  #14                 // Method org/protege/editor/owl/ui/inference/PrecomputePreferencesPanel.getInferenceTypeName:(Lorg/semanticweb/owlapi/reasoner/InferenceType;)Ljava/lang/String;
      52: areturn
      53: aload_0
      54: getfield      #2                  // Field required:Ljava/util/Set;
      57: aload_3
      58: invokeinterface #15,  2           // InterfaceMethod java/util/Set.contains:(Ljava/lang/Object;)Z
      63: invokestatic  #16                 // Method java/lang/Boolean.valueOf:(Z)Ljava/lang/Boolean;
      66: areturn
      67: aload_0
      68: getfield      #3                  // Field disallowed:Ljava/util/Set;
      71: aload_3
      72: invokeinterface #15,  2           // InterfaceMethod java/util/Set.contains:(Ljava/lang/Object;)Z
      77: invokestatic  #16                 // Method java/lang/Boolean.valueOf:(Z)Ljava/lang/Boolean;
      80: areturn
      81: new           #11                 // class java/lang/UnsupportedOperationException
      84: dup
      85: ldc           #12                 // String Programmer Error: missed a case
      87: invokespecial #13                 // Method java/lang/UnsupportedOperationException."<init>":(Ljava/lang/String;)V
      90: athrow

  public void setValueAt(java.lang.Object, int, int);
    Code:
       0: aload_1
       1: checkcast     #10                 // class java/lang/Boolean
       4: astore        4
       6: invokestatic  #4                  // Method org/semanticweb/owlapi/reasoner/InferenceType.values:()[Lorg/semanticweb/owlapi/reasoner/InferenceType;
       9: iload_2
      10: aaload
      11: astore        5
      13: invokestatic  #5                  // Method org/protege/editor/owl/ui/inference/PrecomputePreferencesTableModel$Column.values:()[Lorg/protege/editor/owl/ui/inference/PrecomputePreferencesTableModel$Column;
      16: iload_3
      17: aaload
      18: astore        6
      20: getstatic     #7                  // Field org/protege/editor/owl/ui/inference/PrecomputePreferencesTableModel$1.$SwitchMap$org$protege$editor$owl$ui$inference$PrecomputePreferencesTableModel$Column:[I
      23: aload         6
      25: invokevirtual #8                  // Method org/protege/editor/owl/ui/inference/PrecomputePreferencesTableModel$Column.ordinal:()I
      28: iaload
      29: lookupswitch  { // 2
                     2: 56
                     3: 97
               default: 138
          }
      56: aload_0
      57: aload         5
      59: aload         4
      61: invokevirtual #17                 // Method java/lang/Boolean.booleanValue:()Z
      64: invokespecial #18                 // Method setRequired:(Lorg/semanticweb/owlapi/reasoner/InferenceType;Z)V
      67: aload         4
      69: invokevirtual #17                 // Method java/lang/Boolean.booleanValue:()Z
      72: ifeq          148
      75: aload_0
      76: aload         5
      78: aload         4
      80: invokevirtual #17                 // Method java/lang/Boolean.booleanValue:()Z
      83: ifne          90
      86: iconst_1
      87: goto          91
      90: iconst_0
      91: invokespecial #19                 // Method setDisallowed:(Lorg/semanticweb/owlapi/reasoner/InferenceType;Z)V
      94: goto          148
      97: aload_0
      98: aload         5
     100: aload         4
     102: invokevirtual #17                 // Method java/lang/Boolean.booleanValue:()Z
     105: invokespecial #19                 // Method setDisallowed:(Lorg/semanticweb/owlapi/reasoner/InferenceType;Z)V
     108: aload         4
     110: invokevirtual #17                 // Method java/lang/Boolean.booleanValue:()Z
     113: ifeq          148
     116: aload_0
     117: aload         5
     119: aload         4
     121: invokevirtual #17                 // Method java/lang/Boolean.booleanValue:()Z
     124: ifne          131
     127: iconst_1
     128: goto          132
     131: iconst_0
     132: invokespecial #18                 // Method setRequired:(Lorg/semanticweb/owlapi/reasoner/InferenceType;Z)V
     135: goto          148
     138: new           #11                 // class java/lang/UnsupportedOperationException
     141: dup
     142: ldc           #20                 // String Programmer Error: shouldn\'t happen
     144: invokespecial #13                 // Method java/lang/UnsupportedOperationException."<init>":(Ljava/lang/String;)V
     147: athrow
     148: aload_0
     149: iload_2
     150: iload_2
     151: invokevirtual #21                 // Method fireTableRowsUpdated:(II)V
     154: return

  private void setRequired(org.semanticweb.owlapi.reasoner.InferenceType, boolean);
    Code:
       0: iload_2
       1: ifeq          18
       4: aload_0
       5: getfield      #2                  // Field required:Ljava/util/Set;
       8: aload_1
       9: invokeinterface #22,  2           // InterfaceMethod java/util/Set.add:(Ljava/lang/Object;)Z
      14: pop
      15: goto          29
      18: aload_0
      19: getfield      #2                  // Field required:Ljava/util/Set;
      22: aload_1
      23: invokeinterface #23,  2           // InterfaceMethod java/util/Set.remove:(Ljava/lang/Object;)Z
      28: pop
      29: return

  private void setDisallowed(org.semanticweb.owlapi.reasoner.InferenceType, boolean);
    Code:
       0: iload_2
       1: ifeq          18
       4: aload_0
       5: getfield      #3                  // Field disallowed:Ljava/util/Set;
       8: aload_1
       9: invokeinterface #22,  2           // InterfaceMethod java/util/Set.add:(Ljava/lang/Object;)Z
      14: pop
      15: goto          29
      18: aload_0
      19: getfield      #3                  // Field disallowed:Ljava/util/Set;
      22: aload_1
      23: invokeinterface #23,  2           // InterfaceMethod java/util/Set.remove:(Ljava/lang/Object;)Z
      28: pop
      29: return
}
