Compiled from "DomainRemoteFileRequestAndHandler.java"
final class org.jboss.as.host.controller.mgmt.DomainRemoteFileRequestAndHandler$1 implements org.jboss.as.repository.RemoteFileRequestAndHandler$RemoteFileProtocolIdMapper {
  org.jboss.as.host.controller.mgmt.DomainRemoteFileRequestAndHandler$1();
    Code:
       0: aload_0
       1: invokespecial #1                  // Method java/lang/Object."<init>":()V
       4: return

  public byte paramRootId();
    Code:
       0: bipush        36
       2: ireturn

  public byte paramFilePath();
    Code:
       0: bipush        37
       2: ireturn

  public byte paramNumFiles();
    Code:
       0: bipush        41
       2: ireturn

  public byte fileStart();
    Code:
       0: bipush        48
       2: ireturn

  public byte paramFileSize();
    Code:
       0: bipush        49
       2: ireturn

  public byte fileEnd();
    Code:
       0: bipush        50
       2: ireturn
}
