Compiled from "MasterDomainControllerOperationHandlerService.java"
class org.jboss.as.host.controller.mgmt.MasterDomainControllerOperationHandlerService$DomainTransactionalProtocolOperationHandler$1 implements org.jboss.as.controller.OperationStepHandler {
  final org.jboss.as.controller.OperationStepHandler val$handler;

  final org.jboss.as.host.controller.mgmt.MasterDomainControllerOperationHandlerService$DomainTransactionalProtocolOperationHandler this$1;

  org.jboss.as.host.controller.mgmt.MasterDomainControllerOperationHandlerService$DomainTransactionalProtocolOperationHandler$1(org.jboss.as.host.controller.mgmt.MasterDomainControllerOperationHandlerService$DomainTransactionalProtocolOperationHandler, org.jboss.as.controller.OperationStepHandler);
    Code:
       0: aload_0
       1: aload_1
       2: putfield      #1                  // Field this$1:Lorg/jboss/as/host/controller/mgmt/MasterDomainControllerOperationHandlerService$DomainTransactionalProtocolOperationHandler;
       5: aload_0
       6: aload_2
       7: putfield      #2                  // Field val$handler:Lorg/jboss/as/controller/OperationStepHandler;
      10: aload_0
      11: invokespecial #3                  // Method java/lang/Object."<init>":()V
      14: return

  public void execute(org.jboss.as.controller.OperationContext, org.jboss.dmr.ModelNode) throws org.jboss.as.controller.OperationFailedException;
    Code:
       0: invokestatic  #4                  // Method org/jboss/as/controller/CurrentOperationIdHolder.getCurrentOperationID:()Ljava/lang/Integer;
       3: astore_3
       4: aload_0
       5: dup
       6: astore        4
       8: monitorenter
       9: aload_0
      10: getfield      #1                  // Field this$1:Lorg/jboss/as/host/controller/mgmt/MasterDomainControllerOperationHandlerService$DomainTransactionalProtocolOperationHandler;
      13: new           #5                  // class org/jboss/as/host/controller/mgmt/MasterDomainControllerOperationHandlerService$SlaveRequest
      16: dup
      17: aload_0
      18: getfield      #1                  // Field this$1:Lorg/jboss/as/host/controller/mgmt/MasterDomainControllerOperationHandlerService$DomainTransactionalProtocolOperationHandler;
      21: getfield      #6                  // Field org/jboss/as/host/controller/mgmt/MasterDomainControllerOperationHandlerService$DomainTransactionalProtocolOperationHandler.this$0:Lorg/jboss/as/host/controller/mgmt/MasterDomainControllerOperationHandlerService;
      24: aload_3
      25: invokevirtual #7                  // Method java/lang/Integer.intValue:()I
      28: invokespecial #8                  // Method org/jboss/as/host/controller/mgmt/MasterDomainControllerOperationHandlerService$SlaveRequest."<init>":(Lorg/jboss/as/host/controller/mgmt/MasterDomainControllerOperationHandlerService;I)V
      31: invokestatic  #9                  // Method org/jboss/as/host/controller/mgmt/MasterDomainControllerOperationHandlerService$DomainTransactionalProtocolOperationHandler.access$302:(Lorg/jboss/as/host/controller/mgmt/MasterDomainControllerOperationHandlerService$DomainTransactionalProtocolOperationHandler;Lorg/jboss/as/host/controller/mgmt/MasterDomainControllerOperationHandlerService$SlaveRequest;)Lorg/jboss/as/host/controller/mgmt/MasterDomainControllerOperationHandlerService$SlaveRequest;
      34: pop
      35: aload         4
      37: monitorexit
      38: goto          49
      41: astore        5
      43: aload         4
      45: monitorexit
      46: aload         5
      48: athrow
      49: aload_1
      50: aload_2
      51: aload_0
      52: getfield      #2                  // Field val$handler:Lorg/jboss/as/controller/OperationStepHandler;
      55: getstatic     #10                 // Field org/jboss/as/controller/OperationContext$Stage.MODEL:Lorg/jboss/as/controller/OperationContext$Stage;
      58: invokeinterface #11,  4           // InterfaceMethod org/jboss/as/controller/OperationContext.addStep:(Lorg/jboss/dmr/ModelNode;Lorg/jboss/as/controller/OperationStepHandler;Lorg/jboss/as/controller/OperationContext$Stage;)V
      63: return
    Exception table:
       from    to  target type
           9    38    41   any
          41    46    41   any
}
