Compiled from "ServerToHostProtocolHandler.java"
class org.jboss.as.host.controller.mgmt.ServerToHostProtocolHandler$GetFileOperation implements org.jboss.as.protocol.mgmt.ManagementRequestHandler<java.lang.Void, java.lang.Void> {
  final org.jboss.as.host.controller.mgmt.ServerToHostProtocolHandler this$0;

  private org.jboss.as.host.controller.mgmt.ServerToHostProtocolHandler$GetFileOperation(org.jboss.as.host.controller.mgmt.ServerToHostProtocolHandler);
    Code:
       0: aload_0
       1: aload_1
       2: putfield      #2                  // Field this$0:Lorg/jboss/as/host/controller/mgmt/ServerToHostProtocolHandler;
       5: aload_0
       6: invokespecial #3                  // Method java/lang/Object."<init>":()V
       9: return

  public void handleRequest(java.io.DataInput, org.jboss.as.protocol.mgmt.ActiveOperation$ResultHandler<java.lang.Void>, org.jboss.as.protocol.mgmt.ManagementRequestContext<java.lang.Void>) throws java.io.IOException;
    Code:
       0: getstatic     #4                  // Field org/jboss/as/host/controller/logging/HostControllerLogger.ROOT_LOGGER:Lorg/jboss/as/host/controller/logging/HostControllerLogger;
       3: ldc           #5                  // String Handling GetFileOperation with id %d
       5: aload_3
       6: invokeinterface #6,  1            // InterfaceMethod org/jboss/as/protocol/mgmt/ManagementRequestContext.getOperationId:()Ljava/lang/Integer;
      11: invokeinterface #7,  3            // InterfaceMethod org/jboss/as/host/controller/logging/HostControllerLogger.tracef:(Ljava/lang/String;Ljava/lang/Object;)V
      16: new           #8                  // class org/jboss/as/host/controller/mgmt/ServerToHostProtocolHandler$GetFileOperation$1
      19: dup
      20: aload_0
      21: invokespecial #9                  // Method org/jboss/as/host/controller/mgmt/ServerToHostProtocolHandler$GetFileOperation$1."<init>":(Lorg/jboss/as/host/controller/mgmt/ServerToHostProtocolHandler$GetFileOperation;)V
      24: astore        4
      26: getstatic     #10                 // Field org/jboss/as/server/mgmt/domain/ServerToHostRemoteFileRequestAndHandler.INSTANCE:Lorg/jboss/as/server/mgmt/domain/ServerToHostRemoteFileRequestAndHandler;
      29: aload_1
      30: aload         4
      32: aload_2
      33: aload_3
      34: invokevirtual #11                 // Method org/jboss/as/server/mgmt/domain/ServerToHostRemoteFileRequestAndHandler.handleRequest:(Ljava/io/DataInput;Lorg/jboss/as/repository/RemoteFileRequestAndHandler$RootFileReader;Lorg/jboss/as/protocol/mgmt/ActiveOperation$ResultHandler;Lorg/jboss/as/protocol/mgmt/ManagementRequestContext;)V
      37: return

  org.jboss.as.host.controller.mgmt.ServerToHostProtocolHandler$GetFileOperation(org.jboss.as.host.controller.mgmt.ServerToHostProtocolHandler, org.jboss.as.host.controller.mgmt.ServerToHostProtocolHandler$1);
    Code:
       0: aload_0
       1: aload_1
       2: invokespecial #1                  // Method "<init>":(Lorg/jboss/as/host/controller/mgmt/ServerToHostProtocolHandler;)V
       5: return
}
