Compiled from "ServerToHostProtocolHandler.java"
class org.jboss.as.host.controller.mgmt.ServerToHostProtocolHandler$ServerReconnectRequestHandler$1$1 implements org.jboss.as.controller.OperationStepHandler {
  final org.jboss.as.protocol.mgmt.ManagementRequestContext val$requestContext;

  final org.jboss.as.host.controller.mgmt.ServerToHostProtocolHandler$ServerReconnectRequestHandler$1 this$2;

  org.jboss.as.host.controller.mgmt.ServerToHostProtocolHandler$ServerReconnectRequestHandler$1$1(org.jboss.as.host.controller.mgmt.ServerToHostProtocolHandler$ServerReconnectRequestHandler$1, org.jboss.as.protocol.mgmt.ManagementRequestContext);
    Code:
       0: aload_0
       1: aload_1
       2: putfield      #1                  // Field this$2:Lorg/jboss/as/host/controller/mgmt/ServerToHostProtocolHandler$ServerReconnectRequestHandler$1;
       5: aload_0
       6: aload_2
       7: putfield      #2                  // Field val$requestContext:Lorg/jboss/as/protocol/mgmt/ManagementRequestContext;
      10: aload_0
      11: invokespecial #3                  // Method java/lang/Object."<init>":()V
      14: return

  public void execute(org.jboss.as.controller.OperationContext, org.jboss.dmr.ModelNode) throws org.jboss.as.controller.OperationFailedException;
    Code:
       0: aload_1
       1: invokeinterface #4,  1            // InterfaceMethod org/jboss/as/controller/OperationContext.acquireControllerLock:()V
       6: aload_0
       7: getfield      #1                  // Field this$2:Lorg/jboss/as/host/controller/mgmt/ServerToHostProtocolHandler$ServerReconnectRequestHandler$1;
      10: getfield      #5                  // Field org/jboss/as/host/controller/mgmt/ServerToHostProtocolHandler$ServerReconnectRequestHandler$1.this$1:Lorg/jboss/as/host/controller/mgmt/ServerToHostProtocolHandler$ServerReconnectRequestHandler;
      13: getfield      #6                  // Field org/jboss/as/host/controller/mgmt/ServerToHostProtocolHandler$ServerReconnectRequestHandler.this$0:Lorg/jboss/as/host/controller/mgmt/ServerToHostProtocolHandler;
      16: invokestatic  #7                  // Method org/jboss/as/host/controller/mgmt/ServerToHostProtocolHandler.access$500:(Lorg/jboss/as/host/controller/mgmt/ServerToHostProtocolHandler;)Lorg/jboss/as/host/controller/ServerInventory;
      19: aload_0
      20: getfield      #1                  // Field this$2:Lorg/jboss/as/host/controller/mgmt/ServerToHostProtocolHandler$ServerReconnectRequestHandler$1;
      23: getfield      #8                  // Field org/jboss/as/host/controller/mgmt/ServerToHostProtocolHandler$ServerReconnectRequestHandler$1.val$serverName:Ljava/lang/String;
      26: aload_0
      27: getfield      #1                  // Field this$2:Lorg/jboss/as/host/controller/mgmt/ServerToHostProtocolHandler$ServerReconnectRequestHandler$1;
      30: getfield      #5                  // Field org/jboss/as/host/controller/mgmt/ServerToHostProtocolHandler$ServerReconnectRequestHandler$1.this$1:Lorg/jboss/as/host/controller/mgmt/ServerToHostProtocolHandler$ServerReconnectRequestHandler;
      33: getfield      #6                  // Field org/jboss/as/host/controller/mgmt/ServerToHostProtocolHandler$ServerReconnectRequestHandler.this$0:Lorg/jboss/as/host/controller/mgmt/ServerToHostProtocolHandler;
      36: invokestatic  #9                  // Method org/jboss/as/host/controller/mgmt/ServerToHostProtocolHandler.access$800:(Lorg/jboss/as/host/controller/mgmt/ServerToHostProtocolHandler;)Lorg/jboss/as/protocol/mgmt/ManagementChannelHandler;
      39: invokeinterface #10,  3           // InterfaceMethod org/jboss/as/host/controller/ServerInventory.serverReconnected:(Ljava/lang/String;Lorg/jboss/as/protocol/mgmt/ManagementChannelHandler;)Z
      44: ifeq          53
      47: bipush        33
      49: istore_3
      50: goto          56
      53: bipush        34
      55: istore_3
      56: aload_0
      57: getfield      #1                  // Field this$2:Lorg/jboss/as/host/controller/mgmt/ServerToHostProtocolHandler$ServerReconnectRequestHandler$1;
      60: getfield      #12                 // Field org/jboss/as/host/controller/mgmt/ServerToHostProtocolHandler$ServerReconnectRequestHandler$1.val$channel:Lorg/jboss/remoting3/Channel;
      63: aload_0
      64: getfield      #2                  // Field val$requestContext:Lorg/jboss/as/protocol/mgmt/ManagementRequestContext;
      67: invokeinterface #13,  1           // InterfaceMethod org/jboss/as/protocol/mgmt/ManagementRequestContext.getRequestHeader:()Lorg/jboss/as/protocol/mgmt/ManagementProtocolHeader;
      72: iload_3
      73: invokestatic  #14                 // Method org/jboss/as/host/controller/mgmt/ServerToHostProtocolHandler.safeWriteResponse:(Lorg/jboss/remoting3/Channel;Lorg/jboss/as/protocol/mgmt/ManagementProtocolHeader;B)V
      76: aload_1
      77: getstatic     #15                 // Field org/jboss/as/controller/OperationContext$RollbackHandler.NOOP_ROLLBACK_HANDLER:Lorg/jboss/as/controller/OperationContext$RollbackHandler;
      80: invokeinterface #16,  2           // InterfaceMethod org/jboss/as/controller/OperationContext.completeStep:(Lorg/jboss/as/controller/OperationContext$RollbackHandler;)V
      85: return
}
