Compiled from "DomainRolloutStepHandler.java"
class org.jboss.as.domain.controller.operations.coordination.DomainRolloutStepHandler$1 implements org.jboss.as.controller.OperationContext$ResultHandler {
  final java.util.Map val$submittedTasks;

  final java.util.List val$preparedResults;

  final org.jboss.as.controller.BlockingTimeout val$blockingTimeout;

  final org.jboss.as.domain.controller.operations.coordination.DomainRolloutStepHandler this$0;

  org.jboss.as.domain.controller.operations.coordination.DomainRolloutStepHandler$1(org.jboss.as.domain.controller.operations.coordination.DomainRolloutStepHandler, java.util.Map, java.util.List, org.jboss.as.controller.BlockingTimeout);
    Code:
       0: aload_0
       1: aload_1
       2: putfield      #1                  // Field this$0:Lorg/jboss/as/domain/controller/operations/coordination/DomainRolloutStepHandler;
       5: aload_0
       6: aload_2
       7: putfield      #2                  // Field val$submittedTasks:Ljava/util/Map;
      10: aload_0
      11: aload_3
      12: putfield      #3                  // Field val$preparedResults:Ljava/util/List;
      15: aload_0
      16: aload         4
      18: putfield      #4                  // Field val$blockingTimeout:Lorg/jboss/as/controller/BlockingTimeout;
      21: aload_0
      22: invokespecial #5                  // Method java/lang/Object."<init>":()V
      25: return

  public void handleResult(org.jboss.as.controller.OperationContext$ResultAction, org.jboss.as.controller.OperationContext, org.jboss.dmr.ModelNode);
    Code:
       0: aload_0
       1: getfield      #1                  // Field this$0:Lorg/jboss/as/domain/controller/operations/coordination/DomainRolloutStepHandler;
       4: aload_2
       5: aload_0
       6: getfield      #2                  // Field val$submittedTasks:Ljava/util/Map;
       9: aload_0
      10: getfield      #3                  // Field val$preparedResults:Ljava/util/List;
      13: aload_0
      14: getfield      #4                  // Field val$blockingTimeout:Lorg/jboss/as/controller/BlockingTimeout;
      17: invokestatic  #6                  // Method org/jboss/as/domain/controller/operations/coordination/DomainRolloutStepHandler.access$000:(Lorg/jboss/as/domain/controller/operations/coordination/DomainRolloutStepHandler;Lorg/jboss/as/controller/OperationContext;Ljava/util/Map;Ljava/util/List;Lorg/jboss/as/controller/BlockingTimeout;)V
      20: return
}
