Compiled from "PropertiesSubqueryExpression.java"
public class org.hibernate.criterion.PropertiesSubqueryExpression extends org.hibernate.criterion.SubqueryExpression {
  private final java.lang.String[] propertyNames;

  protected org.hibernate.criterion.PropertiesSubqueryExpression(java.lang.String[], java.lang.String, org.hibernate.criterion.DetachedCriteria);
    Code:
       0: aload_0
       1: aload_2
       2: aconst_null
       3: aload_3
       4: invokespecial #1                  // Method org/hibernate/criterion/SubqueryExpression."<init>":(Ljava/lang/String;Ljava/lang/String;Lorg/hibernate/criterion/DetachedCriteria;)V
       7: aload_0
       8: aload_1
       9: putfield      #2                  // Field propertyNames:[Ljava/lang/String;
      12: return

  protected java.lang.String toLeftSqlString(org.hibernate.Criteria, org.hibernate.criterion.CriteriaQuery);
    Code:
       0: new           #3                  // class java/lang/StringBuilder
       3: dup
       4: ldc           #4                  // String (
       6: invokespecial #5                  // Method java/lang/StringBuilder."<init>":(Ljava/lang/String;)V
       9: astore_3
      10: aload_0
      11: getfield      #2                  // Field propertyNames:[Ljava/lang/String;
      14: arraylength
      15: anewarray     #6                  // class java/lang/String
      18: astore        4
      20: iconst_0
      21: istore        5
      23: iload         5
      25: aload         4
      27: arraylength
      28: if_icmpge     56
      31: aload         4
      33: iload         5
      35: aload_2
      36: aload_1
      37: aload_0
      38: getfield      #2                  // Field propertyNames:[Ljava/lang/String;
      41: iload         5
      43: aaload
      44: invokeinterface #7,  3            // InterfaceMethod org/hibernate/criterion/CriteriaQuery.getColumn:(Lorg/hibernate/Criteria;Ljava/lang/String;)Ljava/lang/String;
      49: aastore
      50: iinc          5, 1
      53: goto          23
      56: aload_3
      57: ldc           #8                  // String ,
      59: aload         4
      61: invokestatic  #9                  // Method java/lang/String.join:(Ljava/lang/CharSequence;[Ljava/lang/CharSequence;)Ljava/lang/String;
      64: invokevirtual #10                 // Method java/lang/StringBuilder.append:(Ljava/lang/String;)Ljava/lang/StringBuilder;
      67: pop
      68: aload_3
      69: ldc           #11                 // String )
      71: invokevirtual #10                 // Method java/lang/StringBuilder.append:(Ljava/lang/String;)Ljava/lang/StringBuilder;
      74: invokevirtual #12                 // Method java/lang/StringBuilder.toString:()Ljava/lang/String;
      77: areturn
}
