Compiled from "JmsListenerContainerParser.java"
class org.springframework.jms.config.JmsListenerContainerParser extends org.springframework.jms.config.AbstractListenerContainerParser {
  private static final java.lang.String CONTAINER_TYPE_ATTRIBUTE;

  private static final java.lang.String CONTAINER_CLASS_ATTRIBUTE;

  private static final java.lang.String CONNECTION_FACTORY_ATTRIBUTE;

  private static final java.lang.String TASK_EXECUTOR_ATTRIBUTE;

  private static final java.lang.String ERROR_HANDLER_ATTRIBUTE;

  private static final java.lang.String CACHE_ATTRIBUTE;

  private static final java.lang.String RECEIVE_TIMEOUT_ATTRIBUTE;

  private static final java.lang.String RECOVERY_INTERVAL_ATTRIBUTE;

  private static final java.lang.String BACK_OFF_ATTRIBUTE;

  org.springframework.jms.config.JmsListenerContainerParser();
    Code:
       0: aload_0
       1: invokespecial #1                  // Method org/springframework/jms/config/AbstractListenerContainerParser."<init>":()V
       4: return

  protected org.springframework.beans.factory.support.RootBeanDefinition createContainerFactory(java.lang.String, org.w3c.dom.Element, org.springframework.beans.factory.xml.ParserContext, org.springframework.beans.PropertyValues, org.springframework.beans.PropertyValues);
    Code:
       0: new           #2                  // class org/springframework/beans/factory/support/RootBeanDefinition
       3: dup
       4: invokespecial #3                  // Method org/springframework/beans/factory/support/RootBeanDefinition."<init>":()V
       7: astore        6
       9: aload_2
      10: ldc           #5                  // String container-type
      12: invokeinterface #6,  2            // InterfaceMethod org/w3c/dom/Element.getAttribute:(Ljava/lang/String;)Ljava/lang/String;
      17: astore        7
      19: aload_2
      20: ldc           #7                  // String container-class
      22: invokeinterface #6,  2            // InterfaceMethod org/w3c/dom/Element.getAttribute:(Ljava/lang/String;)Ljava/lang/String;
      27: astore        8
      29: ldc           #8                  // String
      31: aload         8
      33: invokevirtual #9                  // Method java/lang/String.equals:(Ljava/lang/Object;)Z
      36: ifne          41
      39: aconst_null
      40: areturn
      41: ldc           #8                  // String
      43: aload         7
      45: invokevirtual #9                  // Method java/lang/String.equals:(Ljava/lang/Object;)Z
      48: ifne          61
      51: aload         7
      53: ldc           #10                 // String default
      55: invokevirtual #11                 // Method java/lang/String.startsWith:(Ljava/lang/String;)Z
      58: ifeq          71
      61: aload         6
      63: ldc           #12                 // String org.springframework.jms.config.DefaultJmsListenerContainerFactory
      65: invokevirtual #13                 // Method org/springframework/beans/factory/support/RootBeanDefinition.setBeanClassName:(Ljava/lang/String;)V
      68: goto          88
      71: aload         7
      73: ldc           #14                 // String simple
      75: invokevirtual #11                 // Method java/lang/String.startsWith:(Ljava/lang/String;)Z
      78: ifeq          88
      81: aload         6
      83: ldc           #15                 // String org.springframework.jms.config.SimpleJmsListenerContainerFactory
      85: invokevirtual #13                 // Method org/springframework/beans/factory/support/RootBeanDefinition.setBeanClassName:(Ljava/lang/String;)V
      88: aload         6
      90: invokevirtual #16                 // Method org/springframework/beans/factory/support/RootBeanDefinition.getPropertyValues:()Lorg/springframework/beans/MutablePropertyValues;
      93: aload         4
      95: invokevirtual #17                 // Method org/springframework/beans/MutablePropertyValues.addPropertyValues:(Lorg/springframework/beans/PropertyValues;)Lorg/springframework/beans/MutablePropertyValues;
      98: pop
      99: aload         6
     101: invokevirtual #16                 // Method org/springframework/beans/factory/support/RootBeanDefinition.getPropertyValues:()Lorg/springframework/beans/MutablePropertyValues;
     104: aload         5
     106: invokevirtual #17                 // Method org/springframework/beans/MutablePropertyValues.addPropertyValues:(Lorg/springframework/beans/PropertyValues;)Lorg/springframework/beans/MutablePropertyValues;
     109: pop
     110: aload         6
     112: areturn

  protected org.springframework.beans.factory.support.RootBeanDefinition createContainer(org.w3c.dom.Element, org.w3c.dom.Element, org.springframework.beans.factory.xml.ParserContext, org.springframework.beans.PropertyValues, org.springframework.beans.PropertyValues);
    Code:
       0: new           #2                  // class org/springframework/beans/factory/support/RootBeanDefinition
       3: dup
       4: invokespecial #3                  // Method org/springframework/beans/factory/support/RootBeanDefinition."<init>":()V
       7: astore        6
       9: aload         6
      11: aload_3
      12: aload_1
      13: invokevirtual #18                 // Method org/springframework/beans/factory/xml/ParserContext.extractSource:(Ljava/lang/Object;)Ljava/lang/Object;
      16: invokevirtual #19                 // Method org/springframework/beans/factory/support/RootBeanDefinition.setSource:(Ljava/lang/Object;)V
      19: aload         6
      21: invokevirtual #16                 // Method org/springframework/beans/factory/support/RootBeanDefinition.getPropertyValues:()Lorg/springframework/beans/MutablePropertyValues;
      24: aload         4
      26: invokevirtual #17                 // Method org/springframework/beans/MutablePropertyValues.addPropertyValues:(Lorg/springframework/beans/PropertyValues;)Lorg/springframework/beans/MutablePropertyValues;
      29: pop
      30: aload         6
      32: invokevirtual #16                 // Method org/springframework/beans/factory/support/RootBeanDefinition.getPropertyValues:()Lorg/springframework/beans/MutablePropertyValues;
      35: aload         5
      37: invokevirtual #17                 // Method org/springframework/beans/MutablePropertyValues.addPropertyValues:(Lorg/springframework/beans/PropertyValues;)Lorg/springframework/beans/MutablePropertyValues;
      40: pop
      41: aload_1
      42: ldc           #5                  // String container-type
      44: invokeinterface #6,  2            // InterfaceMethod org/w3c/dom/Element.getAttribute:(Ljava/lang/String;)Ljava/lang/String;
      49: astore        7
      51: aload_1
      52: ldc           #7                  // String container-class
      54: invokeinterface #6,  2            // InterfaceMethod org/w3c/dom/Element.getAttribute:(Ljava/lang/String;)Ljava/lang/String;
      59: astore        8
      61: ldc           #8                  // String
      63: aload         8
      65: invokevirtual #9                  // Method java/lang/String.equals:(Ljava/lang/Object;)Z
      68: ifne          81
      71: aload         6
      73: aload         8
      75: invokevirtual #13                 // Method org/springframework/beans/factory/support/RootBeanDefinition.setBeanClassName:(Ljava/lang/String;)V
      78: goto          141
      81: ldc           #8                  // String
      83: aload         7
      85: invokevirtual #9                  // Method java/lang/String.equals:(Ljava/lang/Object;)Z
      88: ifne          101
      91: aload         7
      93: ldc           #10                 // String default
      95: invokevirtual #11                 // Method java/lang/String.startsWith:(Ljava/lang/String;)Z
      98: ifeq          111
     101: aload         6
     103: ldc           #20                 // String org.springframework.jms.listener.DefaultMessageListenerContainer
     105: invokevirtual #13                 // Method org/springframework/beans/factory/support/RootBeanDefinition.setBeanClassName:(Ljava/lang/String;)V
     108: goto          141
     111: aload         7
     113: ldc           #14                 // String simple
     115: invokevirtual #11                 // Method java/lang/String.startsWith:(Ljava/lang/String;)Z
     118: ifeq          131
     121: aload         6
     123: ldc           #21                 // String org.springframework.jms.listener.SimpleMessageListenerContainer
     125: invokevirtual #13                 // Method org/springframework/beans/factory/support/RootBeanDefinition.setBeanClassName:(Ljava/lang/String;)V
     128: goto          141
     131: aload_3
     132: invokevirtual #22                 // Method org/springframework/beans/factory/xml/ParserContext.getReaderContext:()Lorg/springframework/beans/factory/xml/XmlReaderContext;
     135: ldc           #23                 // String Invalid \'container-type\' attribute: only \"default\" and \"simple\" supported.
     137: aload_1
     138: invokevirtual #24                 // Method org/springframework/beans/factory/xml/XmlReaderContext.error:(Ljava/lang/String;Ljava/lang/Object;)V
     141: aload_0
     142: aload_2
     143: aload_3
     144: aload         6
     146: invokevirtual #16                 // Method org/springframework/beans/factory/support/RootBeanDefinition.getPropertyValues:()Lorg/springframework/beans/MutablePropertyValues;
     149: invokevirtual #25                 // Method parseListenerConfiguration:(Lorg/w3c/dom/Element;Lorg/springframework/beans/factory/xml/ParserContext;Lorg/springframework/beans/MutablePropertyValues;)V
     152: aload         6
     154: areturn

  protected org.springframework.beans.MutablePropertyValues parseSpecificContainerProperties(org.w3c.dom.Element, org.springframework.beans.factory.xml.ParserContext);
    Code:
       0: new           #26                 // class org/springframework/beans/MutablePropertyValues
       3: dup
       4: invokespecial #27                 // Method org/springframework/beans/MutablePropertyValues."<init>":()V
       7: astore_3
       8: aload_1
       9: ldc           #5                  // String container-type
      11: invokeinterface #6,  2            // InterfaceMethod org/w3c/dom/Element.getAttribute:(Ljava/lang/String;)Ljava/lang/String;
      16: ldc           #14                 // String simple
      18: invokevirtual #11                 // Method java/lang/String.startsWith:(Ljava/lang/String;)Z
      21: istore        4
      23: ldc           #28                 // String connectionFactory
      25: astore        5
      27: aload_1
      28: ldc           #29                 // String connection-factory
      30: invokeinterface #30,  2           // InterfaceMethod org/w3c/dom/Element.hasAttribute:(Ljava/lang/String;)Z
      35: ifeq          66
      38: aload_1
      39: ldc           #29                 // String connection-factory
      41: invokeinterface #6,  2            // InterfaceMethod org/w3c/dom/Element.getAttribute:(Ljava/lang/String;)Ljava/lang/String;
      46: astore        5
      48: aload         5
      50: invokestatic  #31                 // Method org/springframework/util/StringUtils.hasText:(Ljava/lang/String;)Z
      53: ifne          66
      56: aload_2
      57: invokevirtual #22                 // Method org/springframework/beans/factory/xml/ParserContext.getReaderContext:()Lorg/springframework/beans/factory/xml/XmlReaderContext;
      60: ldc           #32                 // String Listener container \'connection-factory\' attribute contains empty value.
      62: aload_1
      63: invokevirtual #24                 // Method org/springframework/beans/factory/xml/XmlReaderContext.error:(Ljava/lang/String;Ljava/lang/Object;)V
      66: aload         5
      68: invokestatic  #31                 // Method org/springframework/util/StringUtils.hasText:(Ljava/lang/String;)Z
      71: ifeq          90
      74: aload_3
      75: ldc           #28                 // String connectionFactory
      77: new           #33                 // class org/springframework/beans/factory/config/RuntimeBeanReference
      80: dup
      81: aload         5
      83: invokespecial #34                 // Method org/springframework/beans/factory/config/RuntimeBeanReference."<init>":(Ljava/lang/String;)V
      86: invokevirtual #35                 // Method org/springframework/beans/MutablePropertyValues.add:(Ljava/lang/String;Ljava/lang/Object;)Lorg/springframework/beans/MutablePropertyValues;
      89: pop
      90: aload_1
      91: ldc           #36                 // String task-executor
      93: invokeinterface #6,  2            // InterfaceMethod org/w3c/dom/Element.getAttribute:(Ljava/lang/String;)Ljava/lang/String;
      98: astore        6
     100: aload         6
     102: invokestatic  #31                 // Method org/springframework/util/StringUtils.hasText:(Ljava/lang/String;)Z
     105: ifeq          124
     108: aload_3
     109: ldc           #37                 // String taskExecutor
     111: new           #33                 // class org/springframework/beans/factory/config/RuntimeBeanReference
     114: dup
     115: aload         6
     117: invokespecial #34                 // Method org/springframework/beans/factory/config/RuntimeBeanReference."<init>":(Ljava/lang/String;)V
     120: invokevirtual #35                 // Method org/springframework/beans/MutablePropertyValues.add:(Ljava/lang/String;Ljava/lang/Object;)Lorg/springframework/beans/MutablePropertyValues;
     123: pop
     124: aload_1
     125: ldc           #38                 // String error-handler
     127: invokeinterface #6,  2            // InterfaceMethod org/w3c/dom/Element.getAttribute:(Ljava/lang/String;)Ljava/lang/String;
     132: astore        7
     134: aload         7
     136: invokestatic  #31                 // Method org/springframework/util/StringUtils.hasText:(Ljava/lang/String;)Z
     139: ifeq          158
     142: aload_3
     143: ldc           #39                 // String errorHandler
     145: new           #33                 // class org/springframework/beans/factory/config/RuntimeBeanReference
     148: dup
     149: aload         7
     151: invokespecial #34                 // Method org/springframework/beans/factory/config/RuntimeBeanReference."<init>":(Ljava/lang/String;)V
     154: invokevirtual #35                 // Method org/springframework/beans/MutablePropertyValues.add:(Ljava/lang/String;Ljava/lang/Object;)Lorg/springframework/beans/MutablePropertyValues;
     157: pop
     158: aload_1
     159: ldc           #41                 // String destination-resolver
     161: invokeinterface #6,  2            // InterfaceMethod org/w3c/dom/Element.getAttribute:(Ljava/lang/String;)Ljava/lang/String;
     166: astore        8
     168: aload         8
     170: invokestatic  #31                 // Method org/springframework/util/StringUtils.hasText:(Ljava/lang/String;)Z
     173: ifeq          192
     176: aload_3
     177: ldc           #42                 // String destinationResolver
     179: new           #33                 // class org/springframework/beans/factory/config/RuntimeBeanReference
     182: dup
     183: aload         8
     185: invokespecial #34                 // Method org/springframework/beans/factory/config/RuntimeBeanReference."<init>":(Ljava/lang/String;)V
     188: invokevirtual #35                 // Method org/springframework/beans/MutablePropertyValues.add:(Ljava/lang/String;Ljava/lang/Object;)Lorg/springframework/beans/MutablePropertyValues;
     191: pop
     192: aload_1
     193: ldc           #43                 // String cache
     195: invokeinterface #6,  2            // InterfaceMethod org/w3c/dom/Element.getAttribute:(Ljava/lang/String;)Ljava/lang/String;
     200: astore        9
     202: aload         9
     204: invokestatic  #31                 // Method org/springframework/util/StringUtils.hasText:(Ljava/lang/String;)Z
     207: ifeq          278
     210: iload         4
     212: ifeq          248
     215: ldc           #44                 // String auto
     217: aload         9
     219: invokevirtual #9                  // Method java/lang/String.equals:(Ljava/lang/Object;)Z
     222: ifne          278
     225: ldc           #45                 // String consumer
     227: aload         9
     229: invokevirtual #9                  // Method java/lang/String.equals:(Ljava/lang/Object;)Z
     232: ifne          278
     235: aload_2
     236: invokevirtual #22                 // Method org/springframework/beans/factory/xml/ParserContext.getReaderContext:()Lorg/springframework/beans/factory/xml/XmlReaderContext;
     239: ldc           #46                 // String \'cache\' attribute not actively supported for listener container of type \"simple\". Effective runtime behavior will be equivalent to \"consumer\" / \"auto\".
     241: aload_1
     242: invokevirtual #47                 // Method org/springframework/beans/factory/xml/XmlReaderContext.warning:(Ljava/lang/String;Ljava/lang/Object;)V
     245: goto          278
     248: aload_3
     249: ldc           #48                 // String cacheLevelName
     251: new           #49                 // class java/lang/StringBuilder
     254: dup
     255: invokespecial #50                 // Method java/lang/StringBuilder."<init>":()V
     258: ldc           #51                 // String CACHE_
     260: invokevirtual #52                 // Method java/lang/StringBuilder.append:(Ljava/lang/String;)Ljava/lang/StringBuilder;
     263: aload         9
     265: invokevirtual #53                 // Method java/lang/String.toUpperCase:()Ljava/lang/String;
     268: invokevirtual #52                 // Method java/lang/StringBuilder.append:(Ljava/lang/String;)Ljava/lang/StringBuilder;
     271: invokevirtual #54                 // Method java/lang/StringBuilder.toString:()Ljava/lang/String;
     274: invokevirtual #35                 // Method org/springframework/beans/MutablePropertyValues.add:(Ljava/lang/String;Ljava/lang/Object;)Lorg/springframework/beans/MutablePropertyValues;
     277: pop
     278: aload_0
     279: aload_1
     280: aload_2
     281: invokevirtual #55                 // Method parseAcknowledgeMode:(Lorg/w3c/dom/Element;Lorg/springframework/beans/factory/xml/ParserContext;)Ljava/lang/Integer;
     284: astore        10
     286: aload         10
     288: ifnull        321
     291: aload         10
     293: invokevirtual #56                 // Method java/lang/Integer.intValue:()I
     296: ifne          312
     299: aload_3
     300: ldc           #57                 // String sessionTransacted
     302: getstatic     #58                 // Field java/lang/Boolean.TRUE:Ljava/lang/Boolean;
     305: invokevirtual #35                 // Method org/springframework/beans/MutablePropertyValues.add:(Ljava/lang/String;Ljava/lang/Object;)Lorg/springframework/beans/MutablePropertyValues;
     308: pop
     309: goto          321
     312: aload_3
     313: ldc           #59                 // String sessionAcknowledgeMode
     315: aload         10
     317: invokevirtual #35                 // Method org/springframework/beans/MutablePropertyValues.add:(Ljava/lang/String;Ljava/lang/Object;)Lorg/springframework/beans/MutablePropertyValues;
     320: pop
     321: aload_1
     322: ldc           #60                 // String transaction-manager
     324: invokeinterface #6,  2            // InterfaceMethod org/w3c/dom/Element.getAttribute:(Ljava/lang/String;)Ljava/lang/String;
     329: astore        11
     331: aload         11
     333: invokestatic  #31                 // Method org/springframework/util/StringUtils.hasText:(Ljava/lang/String;)Z
     336: ifeq          373
     339: iload         4
     341: ifeq          357
     344: aload_2
     345: invokevirtual #22                 // Method org/springframework/beans/factory/xml/ParserContext.getReaderContext:()Lorg/springframework/beans/factory/xml/XmlReaderContext;
     348: ldc           #61                 // String \'transaction-manager\' attribute not supported for listener container of type \"simple\".
     350: aload_1
     351: invokevirtual #24                 // Method org/springframework/beans/factory/xml/XmlReaderContext.error:(Ljava/lang/String;Ljava/lang/Object;)V
     354: goto          373
     357: aload_3
     358: ldc           #62                 // String transactionManager
     360: new           #33                 // class org/springframework/beans/factory/config/RuntimeBeanReference
     363: dup
     364: aload         11
     366: invokespecial #34                 // Method org/springframework/beans/factory/config/RuntimeBeanReference."<init>":(Ljava/lang/String;)V
     369: invokevirtual #35                 // Method org/springframework/beans/MutablePropertyValues.add:(Ljava/lang/String;Ljava/lang/Object;)Lorg/springframework/beans/MutablePropertyValues;
     372: pop
     373: aload_1
     374: ldc           #63                 // String concurrency
     376: invokeinterface #6,  2            // InterfaceMethod org/w3c/dom/Element.getAttribute:(Ljava/lang/String;)Ljava/lang/String;
     381: astore        12
     383: aload         12
     385: invokestatic  #31                 // Method org/springframework/util/StringUtils.hasText:(Ljava/lang/String;)Z
     388: ifeq          400
     391: aload_3
     392: ldc           #63                 // String concurrency
     394: aload         12
     396: invokevirtual #35                 // Method org/springframework/beans/MutablePropertyValues.add:(Ljava/lang/String;Ljava/lang/Object;)Lorg/springframework/beans/MutablePropertyValues;
     399: pop
     400: aload_1
     401: ldc           #64                 // String prefetch
     403: invokeinterface #6,  2            // InterfaceMethod org/w3c/dom/Element.getAttribute:(Ljava/lang/String;)Ljava/lang/String;
     408: astore        13
     410: aload         13
     412: invokestatic  #31                 // Method org/springframework/util/StringUtils.hasText:(Ljava/lang/String;)Z
     415: ifeq          432
     418: iload         4
     420: ifne          432
     423: aload_3
     424: ldc           #65                 // String maxMessagesPerTask
     426: aload         13
     428: invokevirtual #35                 // Method org/springframework/beans/MutablePropertyValues.add:(Ljava/lang/String;Ljava/lang/Object;)Lorg/springframework/beans/MutablePropertyValues;
     431: pop
     432: aload_1
     433: ldc           #66                 // String phase
     435: invokeinterface #6,  2            // InterfaceMethod org/w3c/dom/Element.getAttribute:(Ljava/lang/String;)Ljava/lang/String;
     440: astore        14
     442: aload         14
     444: invokestatic  #31                 // Method org/springframework/util/StringUtils.hasText:(Ljava/lang/String;)Z
     447: ifeq          459
     450: aload_3
     451: ldc           #66                 // String phase
     453: aload         14
     455: invokevirtual #35                 // Method org/springframework/beans/MutablePropertyValues.add:(Ljava/lang/String;Ljava/lang/Object;)Lorg/springframework/beans/MutablePropertyValues;
     458: pop
     459: aload_1
     460: ldc           #67                 // String receive-timeout
     462: invokeinterface #6,  2            // InterfaceMethod org/w3c/dom/Element.getAttribute:(Ljava/lang/String;)Ljava/lang/String;
     467: astore        15
     469: aload         15
     471: invokestatic  #31                 // Method org/springframework/util/StringUtils.hasText:(Ljava/lang/String;)Z
     474: ifeq          491
     477: iload         4
     479: ifne          491
     482: aload_3
     483: ldc           #68                 // String receiveTimeout
     485: aload         15
     487: invokevirtual #35                 // Method org/springframework/beans/MutablePropertyValues.add:(Ljava/lang/String;Ljava/lang/Object;)Lorg/springframework/beans/MutablePropertyValues;
     490: pop
     491: aload_1
     492: ldc           #69                 // String back-off
     494: invokeinterface #6,  2            // InterfaceMethod org/w3c/dom/Element.getAttribute:(Ljava/lang/String;)Ljava/lang/String;
     499: astore        16
     501: aload         16
     503: invokestatic  #31                 // Method org/springframework/util/StringUtils.hasText:(Ljava/lang/String;)Z
     506: ifeq          533
     509: iload         4
     511: ifne          565
     514: aload_3
     515: ldc           #70                 // String backOff
     517: new           #33                 // class org/springframework/beans/factory/config/RuntimeBeanReference
     520: dup
     521: aload         16
     523: invokespecial #34                 // Method org/springframework/beans/factory/config/RuntimeBeanReference."<init>":(Ljava/lang/String;)V
     526: invokevirtual #35                 // Method org/springframework/beans/MutablePropertyValues.add:(Ljava/lang/String;Ljava/lang/Object;)Lorg/springframework/beans/MutablePropertyValues;
     529: pop
     530: goto          565
     533: aload_1
     534: ldc           #71                 // String recovery-interval
     536: invokeinterface #6,  2            // InterfaceMethod org/w3c/dom/Element.getAttribute:(Ljava/lang/String;)Ljava/lang/String;
     541: astore        17
     543: aload         17
     545: invokestatic  #31                 // Method org/springframework/util/StringUtils.hasText:(Ljava/lang/String;)Z
     548: ifeq          565
     551: iload         4
     553: ifne          565
     556: aload_3
     557: ldc           #72                 // String recoveryInterval
     559: aload         17
     561: invokevirtual #35                 // Method org/springframework/beans/MutablePropertyValues.add:(Ljava/lang/String;Ljava/lang/Object;)Lorg/springframework/beans/MutablePropertyValues;
     564: pop
     565: aload_3
     566: areturn
}
