Compiled from "SimpleJmsListenerContainerFactory.java"
public class org.springframework.jms.config.SimpleJmsListenerContainerFactory extends org.springframework.jms.config.AbstractJmsListenerContainerFactory<org.springframework.jms.listener.SimpleMessageListenerContainer> {
  public org.springframework.jms.config.SimpleJmsListenerContainerFactory();
    Code:
       0: aload_0
       1: invokespecial #1                  // Method org/springframework/jms/config/AbstractJmsListenerContainerFactory."<init>":()V
       4: return

  protected org.springframework.jms.listener.SimpleMessageListenerContainer createContainerInstance();
    Code:
       0: new           #2                  // class org/springframework/jms/listener/SimpleMessageListenerContainer
       3: dup
       4: invokespecial #3                  // Method org/springframework/jms/listener/SimpleMessageListenerContainer."<init>":()V
       7: areturn

  protected org.springframework.jms.listener.AbstractMessageListenerContainer createContainerInstance();
    Code:
       0: aload_0
       1: invokevirtual #4                  // Method createContainerInstance:()Lorg/springframework/jms/listener/SimpleMessageListenerContainer;
       4: areturn
}
