Compiled from "AbstractConduit.java"
public abstract class org.apache.cxf.transport.AbstractConduit extends org.apache.cxf.transport.AbstractObservable implements org.apache.cxf.transport.Conduit {
  protected final org.apache.cxf.ws.addressing.EndpointReferenceType target;

  public org.apache.cxf.transport.AbstractConduit(org.apache.cxf.ws.addressing.EndpointReferenceType);
    Code:
       0: aload_0
       1: invokespecial #1                  // Method org/apache/cxf/transport/AbstractObservable."<init>":()V
       4: aload_0
       5: aload_1
       6: putfield      #2                  // Field target:Lorg/apache/cxf/ws/addressing/EndpointReferenceType;
       9: return

  public org.apache.cxf.ws.addressing.EndpointReferenceType getTarget();
    Code:
       0: aload_0
       1: getfield      #2                  // Field target:Lorg/apache/cxf/ws/addressing/EndpointReferenceType;
       4: areturn

  public void close(org.apache.cxf.message.Message) throws java.io.IOException;
    Code:
       0: aload_1
       1: ldc_w         #3                  // class java/io/OutputStream
       4: invokeinterface #4,  2            // InterfaceMethod org/apache/cxf/message/Message.getContent:(Ljava/lang/Class;)Ljava/lang/Object;
       9: checkcast     #3                  // class java/io/OutputStream
      12: astore_2
      13: aload_2
      14: ifnull        21
      17: aload_2
      18: invokevirtual #5                  // Method java/io/OutputStream.close:()V
      21: aload_1
      22: ldc_w         #6                  // class java/io/InputStream
      25: invokeinterface #4,  2            // InterfaceMethod org/apache/cxf/message/Message.getContent:(Ljava/lang/Class;)Ljava/lang/Object;
      30: checkcast     #6                  // class java/io/InputStream
      33: astore_3
      34: aload_3
      35: ifnull        42
      38: aload_3
      39: invokevirtual #7                  // Method java/io/InputStream.close:()V
      42: return

  public void close();
    Code:
       0: return

  public java.lang.String toString();
    Code:
       0: new           #8                  // class java/lang/StringBuilder
       3: dup
       4: invokespecial #9                  // Method java/lang/StringBuilder."<init>":()V
       7: ldc           #10                 // String conduit:
       9: invokevirtual #11                 // Method java/lang/StringBuilder.append:(Ljava/lang/String;)Ljava/lang/StringBuilder;
      12: aload_0
      13: invokevirtual #12                 // Method java/lang/Object.getClass:()Ljava/lang/Class;
      16: invokevirtual #13                 // Method java/lang/StringBuilder.append:(Ljava/lang/Object;)Ljava/lang/StringBuilder;
      19: aload_0
      20: invokestatic  #14                 // Method java/lang/System.identityHashCode:(Ljava/lang/Object;)I
      23: invokevirtual #15                 // Method java/lang/StringBuilder.append:(I)Ljava/lang/StringBuilder;
      26: ldc           #16                 // String target:
      28: invokevirtual #11                 // Method java/lang/StringBuilder.append:(Ljava/lang/String;)Ljava/lang/StringBuilder;
      31: aload_0
      32: invokevirtual #17                 // Method getTarget:()Lorg/apache/cxf/ws/addressing/EndpointReferenceType;
      35: ifnull        61
      38: aload_0
      39: invokevirtual #17                 // Method getTarget:()Lorg/apache/cxf/ws/addressing/EndpointReferenceType;
      42: invokevirtual #18                 // Method org/apache/cxf/ws/addressing/EndpointReferenceType.getAddress:()Lorg/apache/cxf/ws/addressing/AttributedURIType;
      45: ifnull        61
      48: aload_0
      49: invokevirtual #17                 // Method getTarget:()Lorg/apache/cxf/ws/addressing/EndpointReferenceType;
      52: invokevirtual #18                 // Method org/apache/cxf/ws/addressing/EndpointReferenceType.getAddress:()Lorg/apache/cxf/ws/addressing/AttributedURIType;
      55: invokevirtual #19                 // Method org/apache/cxf/ws/addressing/AttributedURIType.getValue:()Ljava/lang/String;
      58: goto          63
      61: ldc           #20                 // String null
      63: invokevirtual #11                 // Method java/lang/StringBuilder.append:(Ljava/lang/String;)Ljava/lang/StringBuilder;
      66: invokevirtual #21                 // Method java/lang/StringBuilder.toString:()Ljava/lang/String;
      69: areturn
}
