Compiled from "DeserializerFactory.java"
public abstract class org.codehaus.jackson.map.DeserializerFactory {
  protected static final org.codehaus.jackson.map.Deserializers[] NO_DESERIALIZERS;

  public org.codehaus.jackson.map.DeserializerFactory();
    Code:
       0: aload_0
       1: invokespecial #1                  // Method java/lang/Object."<init>":()V
       4: return

  public abstract org.codehaus.jackson.map.DeserializerFactory$Config getConfig();

  public abstract org.codehaus.jackson.map.DeserializerFactory withConfig(org.codehaus.jackson.map.DeserializerFactory$Config);

  public final org.codehaus.jackson.map.DeserializerFactory withAdditionalDeserializers(org.codehaus.jackson.map.Deserializers);
    Code:
       0: aload_0
       1: aload_0
       2: invokevirtual #2                  // Method getConfig:()Lorg/codehaus/jackson/map/DeserializerFactory$Config;
       5: aload_1
       6: invokevirtual #3                  // Method org/codehaus/jackson/map/DeserializerFactory$Config.withAdditionalDeserializers:(Lorg/codehaus/jackson/map/Deserializers;)Lorg/codehaus/jackson/map/DeserializerFactory$Config;
       9: invokevirtual #4                  // Method withConfig:(Lorg/codehaus/jackson/map/DeserializerFactory$Config;)Lorg/codehaus/jackson/map/DeserializerFactory;
      12: areturn

  public final org.codehaus.jackson.map.DeserializerFactory withAdditionalKeyDeserializers(org.codehaus.jackson.map.KeyDeserializers);
    Code:
       0: aload_0
       1: aload_0
       2: invokevirtual #2                  // Method getConfig:()Lorg/codehaus/jackson/map/DeserializerFactory$Config;
       5: aload_1
       6: invokevirtual #5                  // Method org/codehaus/jackson/map/DeserializerFactory$Config.withAdditionalKeyDeserializers:(Lorg/codehaus/jackson/map/KeyDeserializers;)Lorg/codehaus/jackson/map/DeserializerFactory$Config;
       9: invokevirtual #4                  // Method withConfig:(Lorg/codehaus/jackson/map/DeserializerFactory$Config;)Lorg/codehaus/jackson/map/DeserializerFactory;
      12: areturn

  public final org.codehaus.jackson.map.DeserializerFactory withDeserializerModifier(org.codehaus.jackson.map.deser.BeanDeserializerModifier);
    Code:
       0: aload_0
       1: aload_0
       2: invokevirtual #2                  // Method getConfig:()Lorg/codehaus/jackson/map/DeserializerFactory$Config;
       5: aload_1
       6: invokevirtual #6                  // Method org/codehaus/jackson/map/DeserializerFactory$Config.withDeserializerModifier:(Lorg/codehaus/jackson/map/deser/BeanDeserializerModifier;)Lorg/codehaus/jackson/map/DeserializerFactory$Config;
       9: invokevirtual #4                  // Method withConfig:(Lorg/codehaus/jackson/map/DeserializerFactory$Config;)Lorg/codehaus/jackson/map/DeserializerFactory;
      12: areturn

  public final org.codehaus.jackson.map.DeserializerFactory withAbstractTypeResolver(org.codehaus.jackson.map.AbstractTypeResolver);
    Code:
       0: aload_0
       1: aload_0
       2: invokevirtual #2                  // Method getConfig:()Lorg/codehaus/jackson/map/DeserializerFactory$Config;
       5: aload_1
       6: invokevirtual #7                  // Method org/codehaus/jackson/map/DeserializerFactory$Config.withAbstractTypeResolver:(Lorg/codehaus/jackson/map/AbstractTypeResolver;)Lorg/codehaus/jackson/map/DeserializerFactory$Config;
       9: invokevirtual #4                  // Method withConfig:(Lorg/codehaus/jackson/map/DeserializerFactory$Config;)Lorg/codehaus/jackson/map/DeserializerFactory;
      12: areturn

  public final org.codehaus.jackson.map.DeserializerFactory withValueInstantiators(org.codehaus.jackson.map.deser.ValueInstantiators);
    Code:
       0: aload_0
       1: aload_0
       2: invokevirtual #2                  // Method getConfig:()Lorg/codehaus/jackson/map/DeserializerFactory$Config;
       5: aload_1
       6: invokevirtual #8                  // Method org/codehaus/jackson/map/DeserializerFactory$Config.withValueInstantiators:(Lorg/codehaus/jackson/map/deser/ValueInstantiators;)Lorg/codehaus/jackson/map/DeserializerFactory$Config;
       9: invokevirtual #4                  // Method withConfig:(Lorg/codehaus/jackson/map/DeserializerFactory$Config;)Lorg/codehaus/jackson/map/DeserializerFactory;
      12: areturn

  public abstract org.codehaus.jackson.type.JavaType mapAbstractType(org.codehaus.jackson.map.DeserializationConfig, org.codehaus.jackson.type.JavaType) throws org.codehaus.jackson.map.JsonMappingException;

  public abstract org.codehaus.jackson.map.deser.ValueInstantiator findValueInstantiator(org.codehaus.jackson.map.DeserializationConfig, org.codehaus.jackson.map.introspect.BasicBeanDescription) throws org.codehaus.jackson.map.JsonMappingException;

  public abstract org.codehaus.jackson.map.JsonDeserializer<java.lang.Object> createBeanDeserializer(org.codehaus.jackson.map.DeserializationConfig, org.codehaus.jackson.map.DeserializerProvider, org.codehaus.jackson.type.JavaType, org.codehaus.jackson.map.BeanProperty) throws org.codehaus.jackson.map.JsonMappingException;

  public abstract org.codehaus.jackson.map.JsonDeserializer<?> createArrayDeserializer(org.codehaus.jackson.map.DeserializationConfig, org.codehaus.jackson.map.DeserializerProvider, org.codehaus.jackson.map.type.ArrayType, org.codehaus.jackson.map.BeanProperty) throws org.codehaus.jackson.map.JsonMappingException;

  public abstract org.codehaus.jackson.map.JsonDeserializer<?> createCollectionDeserializer(org.codehaus.jackson.map.DeserializationConfig, org.codehaus.jackson.map.DeserializerProvider, org.codehaus.jackson.map.type.CollectionType, org.codehaus.jackson.map.BeanProperty) throws org.codehaus.jackson.map.JsonMappingException;

  public abstract org.codehaus.jackson.map.JsonDeserializer<?> createCollectionLikeDeserializer(org.codehaus.jackson.map.DeserializationConfig, org.codehaus.jackson.map.DeserializerProvider, org.codehaus.jackson.map.type.CollectionLikeType, org.codehaus.jackson.map.BeanProperty) throws org.codehaus.jackson.map.JsonMappingException;

  public abstract org.codehaus.jackson.map.JsonDeserializer<?> createEnumDeserializer(org.codehaus.jackson.map.DeserializationConfig, org.codehaus.jackson.map.DeserializerProvider, org.codehaus.jackson.type.JavaType, org.codehaus.jackson.map.BeanProperty) throws org.codehaus.jackson.map.JsonMappingException;

  public abstract org.codehaus.jackson.map.JsonDeserializer<?> createMapDeserializer(org.codehaus.jackson.map.DeserializationConfig, org.codehaus.jackson.map.DeserializerProvider, org.codehaus.jackson.map.type.MapType, org.codehaus.jackson.map.BeanProperty) throws org.codehaus.jackson.map.JsonMappingException;

  public abstract org.codehaus.jackson.map.JsonDeserializer<?> createMapLikeDeserializer(org.codehaus.jackson.map.DeserializationConfig, org.codehaus.jackson.map.DeserializerProvider, org.codehaus.jackson.map.type.MapLikeType, org.codehaus.jackson.map.BeanProperty) throws org.codehaus.jackson.map.JsonMappingException;

  public abstract org.codehaus.jackson.map.JsonDeserializer<?> createTreeDeserializer(org.codehaus.jackson.map.DeserializationConfig, org.codehaus.jackson.map.DeserializerProvider, org.codehaus.jackson.type.JavaType, org.codehaus.jackson.map.BeanProperty) throws org.codehaus.jackson.map.JsonMappingException;

  public org.codehaus.jackson.map.KeyDeserializer createKeyDeserializer(org.codehaus.jackson.map.DeserializationConfig, org.codehaus.jackson.type.JavaType, org.codehaus.jackson.map.BeanProperty) throws org.codehaus.jackson.map.JsonMappingException;
    Code:
       0: aconst_null
       1: areturn

  public org.codehaus.jackson.map.TypeDeserializer findTypeDeserializer(org.codehaus.jackson.map.DeserializationConfig, org.codehaus.jackson.type.JavaType, org.codehaus.jackson.map.BeanProperty) throws org.codehaus.jackson.map.JsonMappingException;
    Code:
       0: aconst_null
       1: areturn

  static {};
    Code:
       0: iconst_0
       1: anewarray     #9                  // class org/codehaus/jackson/map/Deserializers
       4: putstatic     #10                 // Field NO_DESERIALIZERS:[Lorg/codehaus/jackson/map/Deserializers;
       7: return
}
