Compiled from "JpaBaseConfiguration.java"
class org.springframework.boot.autoconfigure.orm.jpa.JpaBaseConfiguration$JpaWebConfiguration$1 implements org.springframework.web.servlet.config.annotation.WebMvcConfigurer {
  final org.springframework.orm.jpa.support.OpenEntityManagerInViewInterceptor val$interceptor;

  final org.springframework.boot.autoconfigure.orm.jpa.JpaBaseConfiguration$JpaWebConfiguration this$0;

  org.springframework.boot.autoconfigure.orm.jpa.JpaBaseConfiguration$JpaWebConfiguration$1(org.springframework.boot.autoconfigure.orm.jpa.JpaBaseConfiguration$JpaWebConfiguration, org.springframework.orm.jpa.support.OpenEntityManagerInViewInterceptor);
    Code:
       0: aload_0
       1: aload_1
       2: putfield      #1                  // Field this$0:Lorg/springframework/boot/autoconfigure/orm/jpa/JpaBaseConfiguration$JpaWebConfiguration;
       5: aload_0
       6: aload_2
       7: putfield      #2                  // Field val$interceptor:Lorg/springframework/orm/jpa/support/OpenEntityManagerInViewInterceptor;
      10: aload_0
      11: invokespecial #3                  // Method java/lang/Object."<init>":()V
      14: return

  public void addInterceptors(org.springframework.web.servlet.config.annotation.InterceptorRegistry);
    Code:
       0: aload_1
       1: aload_0
       2: getfield      #2                  // Field val$interceptor:Lorg/springframework/orm/jpa/support/OpenEntityManagerInViewInterceptor;
       5: invokevirtual #4                  // Method org/springframework/web/servlet/config/annotation/InterceptorRegistry.addWebRequestInterceptor:(Lorg/springframework/web/context/request/WebRequestInterceptor;)Lorg/springframework/web/servlet/config/annotation/InterceptorRegistration;
       8: pop
       9: return
}
