Compiled from "MetadataTools.java"
public final class org.hibernate.envers.configuration.internal.metadata.MetadataTools {
  private org.hibernate.envers.configuration.internal.metadata.MetadataTools();
    Code:
       0: aload_0
       1: invokespecial #1                  // Method java/lang/Object."<init>":()V
       4: return

  public static org.dom4j.Element addNativelyGeneratedId(org.dom4j.Element, java.lang.String, java.lang.String, boolean);
    Code:
       0: aload_0
       1: ldc           #2                  // String id
       3: invokeinterface #3,  2            // InterfaceMethod org/dom4j/Element.addElement:(Ljava/lang/String;)Lorg/dom4j/Element;
       8: astore        4
      10: aload         4
      12: ldc           #4                  // String name
      14: aload_1
      15: invokeinterface #5,  3            // InterfaceMethod org/dom4j/Element.addAttribute:(Ljava/lang/String;Ljava/lang/String;)Lorg/dom4j/Element;
      20: ldc           #6                  // String type
      22: aload_2
      23: invokeinterface #5,  3            // InterfaceMethod org/dom4j/Element.addAttribute:(Ljava/lang/String;Ljava/lang/String;)Lorg/dom4j/Element;
      28: pop
      29: aload         4
      31: ldc           #7                  // String generator
      33: invokeinterface #3,  2            // InterfaceMethod org/dom4j/Element.addElement:(Ljava/lang/String;)Lorg/dom4j/Element;
      38: astore        5
      40: iload_3
      41: ifeq          59
      44: aload         5
      46: ldc           #8                  // String class
      48: ldc           #9                  // String native
      50: invokeinterface #5,  3            // InterfaceMethod org/dom4j/Element.addAttribute:(Ljava/lang/String;Ljava/lang/String;)Lorg/dom4j/Element;
      55: pop
      56: goto          171
      59: aload         5
      61: ldc           #8                  // String class
      63: ldc           #10                 // String org.hibernate.envers.enhanced.OrderedSequenceGenerator
      65: invokeinterface #5,  3            // InterfaceMethod org/dom4j/Element.addAttribute:(Ljava/lang/String;Ljava/lang/String;)Lorg/dom4j/Element;
      70: pop
      71: aload         5
      73: ldc           #11                 // String param
      75: invokeinterface #3,  2            // InterfaceMethod org/dom4j/Element.addElement:(Ljava/lang/String;)Lorg/dom4j/Element;
      80: ldc           #4                  // String name
      82: ldc           #12                 // String sequence_name
      84: invokeinterface #5,  3            // InterfaceMethod org/dom4j/Element.addAttribute:(Ljava/lang/String;Ljava/lang/String;)Lorg/dom4j/Element;
      89: ldc           #13                 // String REVISION_GENERATOR
      91: invokeinterface #14,  2           // InterfaceMethod org/dom4j/Element.setText:(Ljava/lang/String;)V
      96: aload         5
      98: ldc           #11                 // String param
     100: invokeinterface #3,  2            // InterfaceMethod org/dom4j/Element.addElement:(Ljava/lang/String;)Lorg/dom4j/Element;
     105: ldc           #4                  // String name
     107: ldc           #15                 // String table_name
     109: invokeinterface #5,  3            // InterfaceMethod org/dom4j/Element.addAttribute:(Ljava/lang/String;Ljava/lang/String;)Lorg/dom4j/Element;
     114: ldc           #13                 // String REVISION_GENERATOR
     116: invokeinterface #14,  2           // InterfaceMethod org/dom4j/Element.setText:(Ljava/lang/String;)V
     121: aload         5
     123: ldc           #11                 // String param
     125: invokeinterface #3,  2            // InterfaceMethod org/dom4j/Element.addElement:(Ljava/lang/String;)Lorg/dom4j/Element;
     130: ldc           #4                  // String name
     132: ldc           #16                 // String initial_value
     134: invokeinterface #5,  3            // InterfaceMethod org/dom4j/Element.addAttribute:(Ljava/lang/String;Ljava/lang/String;)Lorg/dom4j/Element;
     139: ldc           #17                 // String 1
     141: invokeinterface #14,  2           // InterfaceMethod org/dom4j/Element.setText:(Ljava/lang/String;)V
     146: aload         5
     148: ldc           #11                 // String param
     150: invokeinterface #3,  2            // InterfaceMethod org/dom4j/Element.addElement:(Ljava/lang/String;)Lorg/dom4j/Element;
     155: ldc           #4                  // String name
     157: ldc           #18                 // String increment_size
     159: invokeinterface #5,  3            // InterfaceMethod org/dom4j/Element.addAttribute:(Ljava/lang/String;Ljava/lang/String;)Lorg/dom4j/Element;
     164: ldc           #17                 // String 1
     166: invokeinterface #14,  2           // InterfaceMethod org/dom4j/Element.setText:(Ljava/lang/String;)V
     171: aload         4
     173: areturn

  public static org.dom4j.Element addProperty(org.dom4j.Element, java.lang.String, java.lang.String, boolean, boolean, boolean);
    Code:
       0: iload         5
       2: ifeq          18
       5: aload_0
       6: ldc           #19                 // String key-property
       8: invokeinterface #3,  2            // InterfaceMethod org/dom4j/Element.addElement:(Ljava/lang/String;)Lorg/dom4j/Element;
      13: astore        6
      15: goto          57
      18: aload_0
      19: ldc           #20                 // String property
      21: invokeinterface #3,  2            // InterfaceMethod org/dom4j/Element.addElement:(Ljava/lang/String;)Lorg/dom4j/Element;
      26: astore        6
      28: aload         6
      30: ldc           #21                 // String insert
      32: iload_3
      33: invokestatic  #22                 // Method java/lang/Boolean.toString:(Z)Ljava/lang/String;
      36: invokeinterface #5,  3            // InterfaceMethod org/dom4j/Element.addAttribute:(Ljava/lang/String;Ljava/lang/String;)Lorg/dom4j/Element;
      41: pop
      42: aload         6
      44: ldc           #23                 // String update
      46: iload         4
      48: invokestatic  #22                 // Method java/lang/Boolean.toString:(Z)Ljava/lang/String;
      51: invokeinterface #5,  3            // InterfaceMethod org/dom4j/Element.addAttribute:(Ljava/lang/String;Ljava/lang/String;)Lorg/dom4j/Element;
      56: pop
      57: aload         6
      59: ldc           #4                  // String name
      61: aload_1
      62: invokeinterface #5,  3            // InterfaceMethod org/dom4j/Element.addAttribute:(Ljava/lang/String;Ljava/lang/String;)Lorg/dom4j/Element;
      67: pop
      68: aload_2
      69: ifnull        83
      72: aload         6
      74: ldc           #6                  // String type
      76: aload_2
      77: invokeinterface #5,  3            // InterfaceMethod org/dom4j/Element.addAttribute:(Ljava/lang/String;Ljava/lang/String;)Lorg/dom4j/Element;
      82: pop
      83: aload         6
      85: areturn

  public static org.dom4j.Element addProperty(org.dom4j.Element, java.lang.String, java.lang.String, boolean, boolean);
    Code:
       0: aload_0
       1: aload_1
       2: aload_2
       3: iload_3
       4: iconst_0
       5: iload         4
       7: invokestatic  #24                 // Method addProperty:(Lorg/dom4j/Element;Ljava/lang/String;Ljava/lang/String;ZZZ)Lorg/dom4j/Element;
      10: areturn

  public static org.dom4j.Element addModifiedFlagProperty(org.dom4j.Element, java.lang.String, java.lang.String, java.lang.String);
    Code:
       0: aload_0
       1: aload_3
       2: ifnull        9
       5: aload_3
       6: goto          14
       9: aload_1
      10: aload_2
      11: invokestatic  #25                 // Method getModifiedFlagPropertyName:(Ljava/lang/String;Ljava/lang/String;)Ljava/lang/String;
      14: ldc           #26                 // String boolean
      16: iconst_1
      17: iconst_0
      18: iconst_0
      19: invokestatic  #24                 // Method addProperty:(Lorg/dom4j/Element;Ljava/lang/String;Ljava/lang/String;ZZZ)Lorg/dom4j/Element;
      22: areturn

  public static java.lang.String getModifiedFlagPropertyName(java.lang.String, java.lang.String);
    Code:
       0: new           #27                 // class java/lang/StringBuilder
       3: dup
       4: invokespecial #28                 // Method java/lang/StringBuilder."<init>":()V
       7: aload_0
       8: invokevirtual #29                 // Method java/lang/StringBuilder.append:(Ljava/lang/String;)Ljava/lang/StringBuilder;
      11: aload_1
      12: invokevirtual #29                 // Method java/lang/StringBuilder.append:(Ljava/lang/String;)Ljava/lang/StringBuilder;
      15: invokevirtual #30                 // Method java/lang/StringBuilder.toString:()Ljava/lang/String;
      18: areturn

  private static void addOrModifyAttribute(org.dom4j.Element, java.lang.String, java.lang.String);
    Code:
       0: aload_0
       1: aload_1
       2: invokeinterface #31,  2           // InterfaceMethod org/dom4j/Element.attribute:(Ljava/lang/String;)Lorg/dom4j/Attribute;
       7: astore_3
       8: aload_3
       9: ifnonnull     24
      12: aload_0
      13: aload_1
      14: aload_2
      15: invokeinterface #5,  3            // InterfaceMethod org/dom4j/Element.addAttribute:(Ljava/lang/String;Ljava/lang/String;)Lorg/dom4j/Element;
      20: pop
      21: goto          31
      24: aload_3
      25: aload_2
      26: invokeinterface #32,  2           // InterfaceMethod org/dom4j/Attribute.setValue:(Ljava/lang/String;)V
      31: return

  public static org.dom4j.Element addOrModifyColumn(org.dom4j.Element, java.lang.String);
    Code:
       0: aload_0
       1: ldc           #33                 // String column
       3: invokeinterface #34,  2           // InterfaceMethod org/dom4j/Element.element:(Ljava/lang/String;)Lorg/dom4j/Element;
       8: astore_2
       9: aload_2
      10: ifnonnull     25
      13: aload_0
      14: aload_1
      15: aconst_null
      16: aconst_null
      17: aconst_null
      18: aconst_null
      19: aconst_null
      20: aconst_null
      21: invokestatic  #35                 // Method addColumn:(Lorg/dom4j/Element;Ljava/lang/String;Ljava/lang/Integer;Ljava/lang/Integer;Ljava/lang/Integer;Ljava/lang/String;Ljava/lang/String;Ljava/lang/String;)Lorg/dom4j/Element;
      24: areturn
      25: aload_1
      26: invokestatic  #36                 // Method org/hibernate/envers/internal/tools/StringTools.isEmpty:(Ljava/lang/String;)Z
      29: ifne          39
      32: aload_2
      33: ldc           #4                  // String name
      35: aload_1
      36: invokestatic  #37                 // Method addOrModifyAttribute:(Lorg/dom4j/Element;Ljava/lang/String;Ljava/lang/String;)V
      39: aload_2
      40: areturn

  public static org.dom4j.Element addColumn(org.dom4j.Element, java.lang.String, java.lang.Integer, java.lang.Integer, java.lang.Integer, java.lang.String, java.lang.String, java.lang.String);
    Code:
       0: aload_0
       1: aload_1
       2: aload_2
       3: aload_3
       4: aload         4
       6: aload         5
       8: aload         6
      10: aload         7
      12: iconst_0
      13: invokestatic  #38                 // Method addColumn:(Lorg/dom4j/Element;Ljava/lang/String;Ljava/lang/Integer;Ljava/lang/Integer;Ljava/lang/Integer;Ljava/lang/String;Ljava/lang/String;Ljava/lang/String;Z)Lorg/dom4j/Element;
      16: areturn

  public static org.dom4j.Element addColumn(org.dom4j.Element, java.lang.String, java.lang.Integer, java.lang.Integer, java.lang.Integer, java.lang.String, java.lang.String, java.lang.String, boolean);
    Code:
       0: aload_0
       1: ldc           #33                 // String column
       3: invokeinterface #3,  2            // InterfaceMethod org/dom4j/Element.addElement:(Ljava/lang/String;)Lorg/dom4j/Element;
       8: astore        9
      10: aload         9
      12: ldc           #4                  // String name
      14: iload         8
      16: ifeq          46
      19: new           #27                 // class java/lang/StringBuilder
      22: dup
      23: invokespecial #28                 // Method java/lang/StringBuilder."<init>":()V
      26: ldc           #39                 // String `
      28: invokevirtual #29                 // Method java/lang/StringBuilder.append:(Ljava/lang/String;)Ljava/lang/StringBuilder;
      31: aload_1
      32: invokevirtual #29                 // Method java/lang/StringBuilder.append:(Ljava/lang/String;)Ljava/lang/StringBuilder;
      35: ldc           #39                 // String `
      37: invokevirtual #29                 // Method java/lang/StringBuilder.append:(Ljava/lang/String;)Ljava/lang/StringBuilder;
      40: invokevirtual #30                 // Method java/lang/StringBuilder.toString:()Ljava/lang/String;
      43: goto          47
      46: aload_1
      47: invokeinterface #5,  3            // InterfaceMethod org/dom4j/Element.addAttribute:(Ljava/lang/String;Ljava/lang/String;)Lorg/dom4j/Element;
      52: pop
      53: aload_2
      54: ifnull        71
      57: aload         9
      59: ldc           #40                 // String length
      61: aload_2
      62: invokevirtual #41                 // Method java/lang/Integer.toString:()Ljava/lang/String;
      65: invokeinterface #5,  3            // InterfaceMethod org/dom4j/Element.addAttribute:(Ljava/lang/String;Ljava/lang/String;)Lorg/dom4j/Element;
      70: pop
      71: aload_3
      72: ifnull        92
      75: aload         9
      77: ldc           #42                 // String scale
      79: aload_3
      80: invokevirtual #43                 // Method java/lang/Integer.intValue:()I
      83: invokestatic  #44                 // Method java/lang/Integer.toString:(I)Ljava/lang/String;
      86: invokeinterface #5,  3            // InterfaceMethod org/dom4j/Element.addAttribute:(Ljava/lang/String;Ljava/lang/String;)Lorg/dom4j/Element;
      91: pop
      92: aload         4
      94: ifnull        115
      97: aload         9
      99: ldc           #45                 // String precision
     101: aload         4
     103: invokevirtual #43                 // Method java/lang/Integer.intValue:()I
     106: invokestatic  #44                 // Method java/lang/Integer.toString:(I)Ljava/lang/String;
     109: invokeinterface #5,  3            // InterfaceMethod org/dom4j/Element.addAttribute:(Ljava/lang/String;Ljava/lang/String;)Lorg/dom4j/Element;
     114: pop
     115: aload         5
     117: invokestatic  #36                 // Method org/hibernate/envers/internal/tools/StringTools.isEmpty:(Ljava/lang/String;)Z
     120: ifne          135
     123: aload         9
     125: ldc           #46                 // String sql-type
     127: aload         5
     129: invokeinterface #5,  3            // InterfaceMethod org/dom4j/Element.addAttribute:(Ljava/lang/String;Ljava/lang/String;)Lorg/dom4j/Element;
     134: pop
     135: aload         6
     137: invokestatic  #36                 // Method org/hibernate/envers/internal/tools/StringTools.isEmpty:(Ljava/lang/String;)Z
     140: ifne          155
     143: aload         9
     145: ldc           #47                 // String read
     147: aload         6
     149: invokeinterface #5,  3            // InterfaceMethod org/dom4j/Element.addAttribute:(Ljava/lang/String;Ljava/lang/String;)Lorg/dom4j/Element;
     154: pop
     155: aload         7
     157: invokestatic  #36                 // Method org/hibernate/envers/internal/tools/StringTools.isEmpty:(Ljava/lang/String;)Z
     160: ifne          175
     163: aload         9
     165: ldc           #48                 // String write
     167: aload         7
     169: invokeinterface #5,  3            // InterfaceMethod org/dom4j/Element.addAttribute:(Ljava/lang/String;Ljava/lang/String;)Lorg/dom4j/Element;
     174: pop
     175: aload         9
     177: areturn

  private static org.dom4j.Element createEntityCommon(org.dom4j.Document, java.lang.String, org.hibernate.envers.configuration.internal.metadata.AuditTableData, java.lang.String, java.lang.Boolean);
    Code:
       0: aload_0
       1: ldc           #49                 // String hibernate-mapping
       3: invokeinterface #50,  2           // InterfaceMethod org/dom4j/Document.addElement:(Ljava/lang/String;)Lorg/dom4j/Element;
       8: astore        5
      10: aload         5
      12: ldc           #51                 // String auto-import
      14: ldc           #52                 // String false
      16: invokeinterface #5,  3            // InterfaceMethod org/dom4j/Element.addAttribute:(Ljava/lang/String;Ljava/lang/String;)Lorg/dom4j/Element;
      21: pop
      22: aload         5
      24: aload_1
      25: invokeinterface #3,  2            // InterfaceMethod org/dom4j/Element.addElement:(Ljava/lang/String;)Lorg/dom4j/Element;
      30: astore        6
      32: aload_2
      33: invokevirtual #53                 // Method org/hibernate/envers/configuration/internal/metadata/AuditTableData.getAuditEntityName:()Ljava/lang/String;
      36: ifnull        53
      39: aload         6
      41: ldc           #54                 // String entity-name
      43: aload_2
      44: invokevirtual #53                 // Method org/hibernate/envers/configuration/internal/metadata/AuditTableData.getAuditEntityName:()Ljava/lang/String;
      47: invokeinterface #5,  3            // InterfaceMethod org/dom4j/Element.addAttribute:(Ljava/lang/String;Ljava/lang/String;)Lorg/dom4j/Element;
      52: pop
      53: aload_3
      54: ifnull        68
      57: aload         6
      59: ldc           #55                 // String discriminator-value
      61: aload_3
      62: invokeinterface #5,  3            // InterfaceMethod org/dom4j/Element.addAttribute:(Ljava/lang/String;Ljava/lang/String;)Lorg/dom4j/Element;
      67: pop
      68: aload_2
      69: invokevirtual #56                 // Method org/hibernate/envers/configuration/internal/metadata/AuditTableData.getAuditTableName:()Ljava/lang/String;
      72: invokestatic  #36                 // Method org/hibernate/envers/internal/tools/StringTools.isEmpty:(Ljava/lang/String;)Z
      75: ifne          92
      78: aload         6
      80: ldc           #57                 // String table
      82: aload_2
      83: invokevirtual #56                 // Method org/hibernate/envers/configuration/internal/metadata/AuditTableData.getAuditTableName:()Ljava/lang/String;
      86: invokeinterface #5,  3            // InterfaceMethod org/dom4j/Element.addAttribute:(Ljava/lang/String;Ljava/lang/String;)Lorg/dom4j/Element;
      91: pop
      92: aload_2
      93: invokevirtual #58                 // Method org/hibernate/envers/configuration/internal/metadata/AuditTableData.getSchema:()Ljava/lang/String;
      96: invokestatic  #36                 // Method org/hibernate/envers/internal/tools/StringTools.isEmpty:(Ljava/lang/String;)Z
      99: ifne          116
     102: aload         6
     104: ldc           #59                 // String schema
     106: aload_2
     107: invokevirtual #58                 // Method org/hibernate/envers/configuration/internal/metadata/AuditTableData.getSchema:()Ljava/lang/String;
     110: invokeinterface #5,  3            // InterfaceMethod org/dom4j/Element.addAttribute:(Ljava/lang/String;Ljava/lang/String;)Lorg/dom4j/Element;
     115: pop
     116: aload_2
     117: invokevirtual #60                 // Method org/hibernate/envers/configuration/internal/metadata/AuditTableData.getCatalog:()Ljava/lang/String;
     120: invokestatic  #36                 // Method org/hibernate/envers/internal/tools/StringTools.isEmpty:(Ljava/lang/String;)Z
     123: ifne          140
     126: aload         6
     128: ldc           #61                 // String catalog
     130: aload_2
     131: invokevirtual #60                 // Method org/hibernate/envers/configuration/internal/metadata/AuditTableData.getCatalog:()Ljava/lang/String;
     134: invokeinterface #5,  3            // InterfaceMethod org/dom4j/Element.addAttribute:(Ljava/lang/String;Ljava/lang/String;)Lorg/dom4j/Element;
     139: pop
     140: aload         4
     142: ifnull        160
     145: aload         6
     147: ldc           #62                 // String abstract
     149: aload         4
     151: invokevirtual #63                 // Method java/lang/Boolean.toString:()Ljava/lang/String;
     154: invokeinterface #5,  3            // InterfaceMethod org/dom4j/Element.addAttribute:(Ljava/lang/String;Ljava/lang/String;)Lorg/dom4j/Element;
     159: pop
     160: aload         6
     162: areturn

  public static org.dom4j.Element createEntity(org.dom4j.Document, org.hibernate.envers.configuration.internal.metadata.AuditTableData, java.lang.String, java.lang.Boolean);
    Code:
       0: aload_0
       1: ldc           #8                  // String class
       3: aload_1
       4: aload_2
       5: aload_3
       6: invokestatic  #64                 // Method createEntityCommon:(Lorg/dom4j/Document;Ljava/lang/String;Lorg/hibernate/envers/configuration/internal/metadata/AuditTableData;Ljava/lang/String;Ljava/lang/Boolean;)Lorg/dom4j/Element;
       9: areturn

  public static org.dom4j.Element createSubclassEntity(org.dom4j.Document, java.lang.String, org.hibernate.envers.configuration.internal.metadata.AuditTableData, java.lang.String, java.lang.String, java.lang.Boolean);
    Code:
       0: aload_0
       1: aload_1
       2: aload_2
       3: aload         4
       5: aload         5
       7: invokestatic  #64                 // Method createEntityCommon:(Lorg/dom4j/Document;Ljava/lang/String;Lorg/hibernate/envers/configuration/internal/metadata/AuditTableData;Ljava/lang/String;Ljava/lang/Boolean;)Lorg/dom4j/Element;
      10: astore        6
      12: aload         6
      14: ldc           #65                 // String extends
      16: aload_3
      17: invokeinterface #5,  3            // InterfaceMethod org/dom4j/Element.addAttribute:(Ljava/lang/String;Ljava/lang/String;)Lorg/dom4j/Element;
      22: pop
      23: aload         6
      25: areturn

  public static org.dom4j.Element createJoin(org.dom4j.Element, java.lang.String, java.lang.String, java.lang.String);
    Code:
       0: aload_0
       1: ldc           #66                 // String join
       3: invokeinterface #3,  2            // InterfaceMethod org/dom4j/Element.addElement:(Ljava/lang/String;)Lorg/dom4j/Element;
       8: astore        4
      10: aload         4
      12: ldc           #57                 // String table
      14: aload_1
      15: invokeinterface #5,  3            // InterfaceMethod org/dom4j/Element.addAttribute:(Ljava/lang/String;Ljava/lang/String;)Lorg/dom4j/Element;
      20: pop
      21: aload_2
      22: invokestatic  #36                 // Method org/hibernate/envers/internal/tools/StringTools.isEmpty:(Ljava/lang/String;)Z
      25: ifne          39
      28: aload         4
      30: ldc           #59                 // String schema
      32: aload_2
      33: invokeinterface #5,  3            // InterfaceMethod org/dom4j/Element.addAttribute:(Ljava/lang/String;Ljava/lang/String;)Lorg/dom4j/Element;
      38: pop
      39: aload_3
      40: invokestatic  #36                 // Method org/hibernate/envers/internal/tools/StringTools.isEmpty:(Ljava/lang/String;)Z
      43: ifne          57
      46: aload         4
      48: ldc           #61                 // String catalog
      50: aload_3
      51: invokeinterface #5,  3            // InterfaceMethod org/dom4j/Element.addAttribute:(Ljava/lang/String;Ljava/lang/String;)Lorg/dom4j/Element;
      56: pop
      57: aload         4
      59: areturn

  public static void addColumns(org.dom4j.Element, java.util.Iterator);
    Code:
       0: aload_1
       1: invokeinterface #67,  1           // InterfaceMethod java/util/Iterator.hasNext:()Z
       6: ifeq          47
       9: aload_1
      10: invokeinterface #68,  1           // InterfaceMethod java/util/Iterator.next:()Ljava/lang/Object;
      15: checkcast     #69                 // class org/hibernate/mapping/Selectable
      18: astore_2
      19: aload_2
      20: invokeinterface #70,  1           // InterfaceMethod org/hibernate/mapping/Selectable.isFormula:()Z
      25: ifeq          36
      28: new           #71                 // class org/hibernate/envers/configuration/internal/metadata/FormulaNotSupportedException
      31: dup
      32: invokespecial #72                 // Method org/hibernate/envers/configuration/internal/metadata/FormulaNotSupportedException."<init>":()V
      35: athrow
      36: aload_0
      37: aload_2
      38: checkcast     #73                 // class org/hibernate/mapping/Column
      41: invokestatic  #74                 // Method addColumn:(Lorg/dom4j/Element;Lorg/hibernate/mapping/Column;)V
      44: goto          0
      47: return

  public static void addColumn(org.dom4j.Element, org.hibernate.mapping.Column);
    Code:
       0: aload_0
       1: aload_1
       2: invokevirtual #75                 // Method org/hibernate/mapping/Column.getName:()Ljava/lang/String;
       5: aload_1
       6: invokevirtual #76                 // Method org/hibernate/mapping/Column.getLength:()I
       9: invokestatic  #77                 // Method java/lang/Integer.valueOf:(I)Ljava/lang/Integer;
      12: aload_1
      13: invokevirtual #78                 // Method org/hibernate/mapping/Column.getScale:()I
      16: invokestatic  #77                 // Method java/lang/Integer.valueOf:(I)Ljava/lang/Integer;
      19: aload_1
      20: invokevirtual #79                 // Method org/hibernate/mapping/Column.getPrecision:()I
      23: invokestatic  #77                 // Method java/lang/Integer.valueOf:(I)Ljava/lang/Integer;
      26: aload_1
      27: invokevirtual #80                 // Method org/hibernate/mapping/Column.getSqlType:()Ljava/lang/String;
      30: aload_1
      31: invokevirtual #81                 // Method org/hibernate/mapping/Column.getCustomRead:()Ljava/lang/String;
      34: aload_1
      35: invokevirtual #82                 // Method org/hibernate/mapping/Column.getCustomWrite:()Ljava/lang/String;
      38: aload_1
      39: invokevirtual #83                 // Method org/hibernate/mapping/Column.isQuoted:()Z
      42: invokestatic  #38                 // Method addColumn:(Lorg/dom4j/Element;Ljava/lang/String;Ljava/lang/Integer;Ljava/lang/Integer;Ljava/lang/Integer;Ljava/lang/String;Ljava/lang/String;Ljava/lang/String;Z)Lorg/dom4j/Element;
      45: pop
      46: return

  private static void changeNamesInColumnElement(org.dom4j.Element, org.hibernate.envers.configuration.internal.metadata.MetadataTools$ColumnNameIterator);
    Code:
       0: aload_0
       1: invokeinterface #84,  1           // InterfaceMethod org/dom4j/Element.elementIterator:()Ljava/util/Iterator;
       6: astore_2
       7: aload_2
       8: invokeinterface #67,  1           // InterfaceMethod java/util/Iterator.hasNext:()Z
      13: ifeq          72
      16: aload_2
      17: invokeinterface #68,  1           // InterfaceMethod java/util/Iterator.next:()Ljava/lang/Object;
      22: checkcast     #85                 // class org/dom4j/Element
      25: astore_3
      26: ldc           #33                 // String column
      28: aload_3
      29: invokeinterface #86,  1           // InterfaceMethod org/dom4j/Element.getName:()Ljava/lang/String;
      34: invokevirtual #87                 // Method java/lang/String.equals:(Ljava/lang/Object;)Z
      37: ifeq          69
      40: aload_3
      41: ldc           #4                  // String name
      43: invokeinterface #31,  2           // InterfaceMethod org/dom4j/Element.attribute:(Ljava/lang/String;)Lorg/dom4j/Attribute;
      48: astore        4
      50: aload         4
      52: ifnull        69
      55: aload         4
      57: aload_1
      58: invokevirtual #88                 // Method org/hibernate/envers/configuration/internal/metadata/MetadataTools$ColumnNameIterator.next:()Ljava/lang/Object;
      61: checkcast     #89                 // class java/lang/String
      64: invokeinterface #90,  2           // InterfaceMethod org/dom4j/Attribute.setText:(Ljava/lang/String;)V
      69: goto          7
      72: return

  public static void prefixNamesInPropertyElement(org.dom4j.Element, java.lang.String, org.hibernate.envers.configuration.internal.metadata.MetadataTools$ColumnNameIterator, boolean, boolean);
    Code:
       0: aload_0
       1: invokeinterface #84,  1           // InterfaceMethod org/dom4j/Element.elementIterator:()Ljava/util/Iterator;
       6: astore        5
       8: aload         5
      10: invokeinterface #67,  1           // InterfaceMethod java/util/Iterator.hasNext:()Z
      15: ifeq          190
      18: aload         5
      20: invokeinterface #68,  1           // InterfaceMethod java/util/Iterator.next:()Ljava/lang/Object;
      25: checkcast     #85                 // class org/dom4j/Element
      28: astore        6
      30: ldc           #20                 // String property
      32: aload         6
      34: invokeinterface #86,  1           // InterfaceMethod org/dom4j/Element.getName:()Ljava/lang/String;
      39: invokevirtual #87                 // Method java/lang/String.equals:(Ljava/lang/Object;)Z
      42: ifne          60
      45: ldc           #91                 // String many-to-one
      47: aload         6
      49: invokeinterface #86,  1           // InterfaceMethod org/dom4j/Element.getName:()Ljava/lang/String;
      54: invokevirtual #87                 // Method java/lang/String.equals:(Ljava/lang/Object;)Z
      57: ifeq          187
      60: aload         6
      62: ldc           #4                  // String name
      64: invokeinterface #31,  2           // InterfaceMethod org/dom4j/Element.attribute:(Ljava/lang/String;)Lorg/dom4j/Attribute;
      69: astore        7
      71: aload         7
      73: ifnull        107
      76: aload         7
      78: new           #27                 // class java/lang/StringBuilder
      81: dup
      82: invokespecial #28                 // Method java/lang/StringBuilder."<init>":()V
      85: aload_1
      86: invokevirtual #29                 // Method java/lang/StringBuilder.append:(Ljava/lang/String;)Ljava/lang/StringBuilder;
      89: aload         7
      91: invokeinterface #92,  1           // InterfaceMethod org/dom4j/Attribute.getText:()Ljava/lang/String;
      96: invokevirtual #29                 // Method java/lang/StringBuilder.append:(Ljava/lang/String;)Ljava/lang/StringBuilder;
      99: invokevirtual #30                 // Method java/lang/StringBuilder.toString:()Ljava/lang/String;
     102: invokeinterface #90,  2           // InterfaceMethod org/dom4j/Attribute.setText:(Ljava/lang/String;)V
     107: aload         6
     109: aload_2
     110: invokestatic  #93                 // Method changeNamesInColumnElement:(Lorg/dom4j/Element;Lorg/hibernate/envers/configuration/internal/metadata/MetadataTools$ColumnNameIterator;)V
     113: iload_3
     114: ifeq          149
     117: aload         6
     119: new           #27                 // class java/lang/StringBuilder
     122: dup
     123: invokespecial #28                 // Method java/lang/StringBuilder."<init>":()V
     126: ldc           #94                 // String key-
     128: invokevirtual #29                 // Method java/lang/StringBuilder.append:(Ljava/lang/String;)Ljava/lang/StringBuilder;
     131: aload         6
     133: invokeinterface #86,  1           // InterfaceMethod org/dom4j/Element.getName:()Ljava/lang/String;
     138: invokevirtual #29                 // Method java/lang/StringBuilder.append:(Ljava/lang/String;)Ljava/lang/StringBuilder;
     141: invokevirtual #30                 // Method java/lang/StringBuilder.toString:()Ljava/lang/String;
     144: invokeinterface #95,  2           // InterfaceMethod org/dom4j/Element.setName:(Ljava/lang/String;)V
     149: ldc           #20                 // String property
     151: aload         6
     153: invokeinterface #86,  1           // InterfaceMethod org/dom4j/Element.getName:()Ljava/lang/String;
     158: invokevirtual #87                 // Method java/lang/String.equals:(Ljava/lang/Object;)Z
     161: ifeq          187
     164: aload         6
     166: ldc           #21                 // String insert
     168: invokeinterface #31,  2           // InterfaceMethod org/dom4j/Element.attribute:(Ljava/lang/String;)Lorg/dom4j/Attribute;
     173: astore        8
     175: aload         8
     177: iload         4
     179: invokestatic  #22                 // Method java/lang/Boolean.toString:(Z)Ljava/lang/String;
     182: invokeinterface #90,  2           // InterfaceMethod org/dom4j/Attribute.setText:(Ljava/lang/String;)V
     187: goto          8
     190: return

  public static void addFormula(org.dom4j.Element, org.hibernate.mapping.Formula);
    Code:
       0: aload_0
       1: ldc           #96                 // String formula
       3: invokeinterface #3,  2            // InterfaceMethod org/dom4j/Element.addElement:(Ljava/lang/String;)Lorg/dom4j/Element;
       8: aload_1
       9: invokevirtual #97                 // Method org/hibernate/mapping/Formula.getText:()Ljava/lang/String;
      12: invokeinterface #14,  2           // InterfaceMethod org/dom4j/Element.setText:(Ljava/lang/String;)V
      17: return

  public static void addColumnsOrFormulas(org.dom4j.Element, java.util.Iterator);
    Code:
       0: aload_1
       1: invokeinterface #67,  1           // InterfaceMethod java/util/Iterator.hasNext:()Z
       6: ifeq          52
       9: aload_1
      10: invokeinterface #68,  1           // InterfaceMethod java/util/Iterator.next:()Ljava/lang/Object;
      15: astore_2
      16: aload_2
      17: instanceof    #73                 // class org/hibernate/mapping/Column
      20: ifeq          34
      23: aload_0
      24: aload_2
      25: checkcast     #73                 // class org/hibernate/mapping/Column
      28: invokestatic  #74                 // Method addColumn:(Lorg/dom4j/Element;Lorg/hibernate/mapping/Column;)V
      31: goto          49
      34: aload_2
      35: instanceof    #98                 // class org/hibernate/mapping/Formula
      38: ifeq          49
      41: aload_0
      42: aload_2
      43: checkcast     #98                 // class org/hibernate/mapping/Formula
      46: invokestatic  #99                 // Method addFormula:(Lorg/dom4j/Element;Lorg/hibernate/mapping/Formula;)V
      49: goto          0
      52: return

  public static org.hibernate.envers.configuration.internal.metadata.MetadataTools$ColumnNameIterator getColumnNameIterator(java.util.Iterator<org.hibernate.mapping.Selectable>);
    Code:
       0: new           #100                // class org/hibernate/envers/configuration/internal/metadata/MetadataTools$1
       3: dup
       4: aload_0
       5: invokespecial #101                // Method org/hibernate/envers/configuration/internal/metadata/MetadataTools$1."<init>":(Ljava/util/Iterator;)V
       8: areturn

  public static org.hibernate.envers.configuration.internal.metadata.MetadataTools$ColumnNameIterator getColumnNameIterator(javax.persistence.JoinColumn[]);
    Code:
       0: new           #102                // class org/hibernate/envers/configuration/internal/metadata/MetadataTools$2
       3: dup
       4: aload_0
       5: invokespecial #103                // Method org/hibernate/envers/configuration/internal/metadata/MetadataTools$2."<init>":([Ljavax/persistence/JoinColumn;)V
       8: areturn
}
