Compiled from "ServerConfig.scala"
public final class io.youi.server.SessionConfig$ extends scala.runtime.AbstractFunction4<java.lang.String, scala.Option<java.lang.Object>, scala.Option<java.lang.String>, java.lang.Object, io.youi.server.SessionConfig> implements scala.Serializable {
  public static final io.youi.server.SessionConfig$ MODULE$;

  public static {};
    Code:
       0: new           #2                  // class io/youi/server/SessionConfig$
       3: invokespecial #15                 // Method "<init>":()V
       6: return

  public final java.lang.String toString();
    Code:
       0: ldc           #19                 // String SessionConfig
       2: areturn

  public io.youi.server.SessionConfig apply(java.lang.String, scala.Option<java.lang.Object>, scala.Option<java.lang.String>, boolean);
    Code:
       0: new           #24                 // class io/youi/server/SessionConfig
       3: dup
       4: aload_1
       5: aload_2
       6: aload_3
       7: iload         4
       9: invokespecial #27                 // Method io/youi/server/SessionConfig."<init>":(Ljava/lang/String;Lscala/Option;Lscala/Option;Z)V
      12: areturn

  public scala.Option<scala.Tuple4<java.lang.String, scala.Option<java.lang.Object>, scala.Option<java.lang.String>, java.lang.Object>> unapply(io.youi.server.SessionConfig);
    Code:
       0: aload_1
       1: ifnonnull     10
       4: getstatic     #41                 // Field scala/None$.MODULE$:Lscala/None$;
       7: goto          43
      10: new           #43                 // class scala/Some
      13: dup
      14: new           #45                 // class scala/Tuple4
      17: dup
      18: aload_1
      19: invokevirtual #47                 // Method io/youi/server/SessionConfig.name:()Ljava/lang/String;
      22: aload_1
      23: invokevirtual #50                 // Method io/youi/server/SessionConfig.maxAge:()Lscala/Option;
      26: aload_1
      27: invokevirtual #52                 // Method io/youi/server/SessionConfig.domain:()Lscala/Option;
      30: aload_1
      31: invokevirtual #55                 // Method io/youi/server/SessionConfig.secure:()Z
      34: invokestatic  #61                 // Method scala/runtime/BoxesRunTime.boxToBoolean:(Z)Ljava/lang/Boolean;
      37: invokespecial #64                 // Method scala/Tuple4."<init>":(Ljava/lang/Object;Ljava/lang/Object;Ljava/lang/Object;Ljava/lang/Object;)V
      40: invokespecial #67                 // Method scala/Some."<init>":(Ljava/lang/Object;)V
      43: areturn

  public java.lang.String $lessinit$greater$default$1();
    Code:
       0: ldc           #74                 // String JSESSIONID
       2: areturn

  public scala.Option<java.lang.Object> $lessinit$greater$default$2();
    Code:
       0: getstatic     #41                 // Field scala/None$.MODULE$:Lscala/None$;
       3: areturn

  public scala.Option<java.lang.String> $lessinit$greater$default$3();
    Code:
       0: getstatic     #41                 // Field scala/None$.MODULE$:Lscala/None$;
       3: areturn

  public boolean $lessinit$greater$default$4();
    Code:
       0: iconst_0
       1: ireturn

  public java.lang.String apply$default$1();
    Code:
       0: ldc           #74                 // String JSESSIONID
       2: areturn

  public scala.Option<java.lang.Object> apply$default$2();
    Code:
       0: getstatic     #41                 // Field scala/None$.MODULE$:Lscala/None$;
       3: areturn

  public scala.Option<java.lang.String> apply$default$3();
    Code:
       0: getstatic     #41                 // Field scala/None$.MODULE$:Lscala/None$;
       3: areturn

  public boolean apply$default$4();
    Code:
       0: iconst_0
       1: ireturn

  private java.lang.Object readResolve();
    Code:
       0: getstatic     #85                 // Field MODULE$:Lio/youi/server/SessionConfig$;
       3: areturn

  public java.lang.Object apply(java.lang.Object, java.lang.Object, java.lang.Object, java.lang.Object);
    Code:
       0: aload_0
       1: aload_1
       2: checkcast     #88                 // class java/lang/String
       5: aload_2
       6: checkcast     #71                 // class scala/Option
       9: aload_3
      10: checkcast     #71                 // class scala/Option
      13: aload         4
      15: invokestatic  #92                 // Method scala/runtime/BoxesRunTime.unboxToBoolean:(Ljava/lang/Object;)Z
      18: invokevirtual #94                 // Method apply:(Ljava/lang/String;Lscala/Option;Lscala/Option;Z)Lio/youi/server/SessionConfig;
      21: areturn

  private io.youi.server.SessionConfig$();
    Code:
       0: aload_0
       1: invokespecial #100                // Method scala/runtime/AbstractFunction4."<init>":()V
       4: aload_0
       5: putstatic     #85                 // Field MODULE$:Lio/youi/server/SessionConfig$;
       8: return
}
