Compiled from "StandardPersistenceManagerProxyBean.java"
public class org.springframework.orm.jdo.support.StandardPersistenceManagerProxyBean implements org.springframework.beans.factory.FactoryBean<javax.jdo.PersistenceManager> {
  private javax.jdo.PersistenceManager proxy;

  public org.springframework.orm.jdo.support.StandardPersistenceManagerProxyBean();
    Code:
       0: aload_0
       1: invokespecial #1                  // Method java/lang/Object."<init>":()V
       4: return

  public void setPersistenceManagerFactory(javax.jdo.PersistenceManagerFactory);
    Code:
       0: aload_1
       1: ldc           #2                  // String PersistenceManagerFactory must not be null
       3: invokestatic  #3                  // Method org/springframework/util/Assert.notNull:(Ljava/lang/Object;Ljava/lang/String;)V
       6: aload_0
       7: aload_1
       8: invokeinterface #4,  1            // InterfaceMethod javax/jdo/PersistenceManagerFactory.getPersistenceManagerProxy:()Ljavax/jdo/PersistenceManager;
      13: putfield      #5                  // Field proxy:Ljavax/jdo/PersistenceManager;
      16: return

  public javax.jdo.PersistenceManager getObject();
    Code:
       0: aload_0
       1: getfield      #5                  // Field proxy:Ljavax/jdo/PersistenceManager;
       4: areturn

  public java.lang.Class<? extends javax.jdo.PersistenceManager> getObjectType();
    Code:
       0: aload_0
       1: getfield      #5                  // Field proxy:Ljavax/jdo/PersistenceManager;
       4: ifnull        17
       7: aload_0
       8: getfield      #5                  // Field proxy:Ljavax/jdo/PersistenceManager;
      11: invokevirtual #6                  // Method java/lang/Object.getClass:()Ljava/lang/Class;
      14: goto          19
      17: ldc           #7                  // class javax/jdo/PersistenceManager
      19: areturn

  public boolean isSingleton();
    Code:
       0: iconst_1
       1: ireturn

  public java.lang.Object getObject() throws java.lang.Exception;
    Code:
       0: aload_0
       1: invokevirtual #8                  // Method getObject:()Ljavax/jdo/PersistenceManager;
       4: areturn
}
