Compiled from "BasicComponentParameter.java"
public class org.sonarsource.sonarlint.shaded.org.picocontainer.parameters.BasicComponentParameter extends org.sonarsource.sonarlint.shaded.org.picocontainer.parameters.AbstractParameter implements org.sonarsource.sonarlint.shaded.org.picocontainer.Parameter,java.io.Serializable {
  public static final org.sonarsource.sonarlint.shaded.org.picocontainer.parameters.BasicComponentParameter BASIC_DEFAULT;

  private java.lang.Object componentKey;

  static final boolean $assertionsDisabled;

  public org.sonarsource.sonarlint.shaded.org.picocontainer.parameters.BasicComponentParameter(java.lang.Object);
    Code:
       0: aload_0
       1: invokespecial #36                 // Method org/sonarsource/sonarlint/shaded/org/picocontainer/parameters/AbstractParameter."<init>":()V
       4: aload_0
       5: aload_1
       6: putfield      #38                 // Field componentKey:Ljava/lang/Object;
       9: return

  public org.sonarsource.sonarlint.shaded.org.picocontainer.parameters.BasicComponentParameter();
    Code:
       0: aload_0
       1: invokespecial #36                 // Method org/sonarsource/sonarlint/shaded/org/picocontainer/parameters/AbstractParameter."<init>":()V
       4: return

  public org.sonarsource.sonarlint.shaded.org.picocontainer.Parameter$Resolver resolve(org.sonarsource.sonarlint.shaded.org.picocontainer.PicoContainer, org.sonarsource.sonarlint.shaded.org.picocontainer.ComponentAdapter<?>, org.sonarsource.sonarlint.shaded.org.picocontainer.ComponentAdapter<?>, java.lang.reflect.Type, org.sonarsource.sonarlint.shaded.org.picocontainer.NameBinding, boolean, java.lang.annotation.Annotation);
    Code:
       0: aconst_null
       1: astore        8
       3: aload         4
       5: instanceof    #44                 // class java/lang/Class
       8: ifne          45
      11: aload         4
      13: instanceof    #46                 // class java/lang/reflect/ParameterizedType
      16: ifeq          37
      19: aload         4
      21: checkcast     #46                 // class java/lang/reflect/ParameterizedType
      24: invokeinterface #50,  1           // InterfaceMethod java/lang/reflect/ParameterizedType.getRawType:()Ljava/lang/reflect/Type;
      29: checkcast     #44                 // class java/lang/Class
      32: astore        8
      34: goto          52
      37: new           #21                 // class org/sonarsource/sonarlint/shaded/org/picocontainer/Parameter$NotResolved
      40: dup
      41: invokespecial #51                 // Method org/sonarsource/sonarlint/shaded/org/picocontainer/Parameter$NotResolved."<init>":()V
      44: areturn
      45: aload         4
      47: checkcast     #44                 // class java/lang/Class
      50: astore        8
      52: getstatic     #53                 // Field $assertionsDisabled:Z
      55: ifne          71
      58: aload         8
      60: ifnonnull     71
      63: new           #55                 // class java/lang/AssertionError
      66: dup
      67: invokespecial #56                 // Method java/lang/AssertionError."<init>":()V
      70: athrow
      71: aload_3
      72: ifnonnull     94
      75: aload_0
      76: aload_1
      77: aload_2
      78: aload         8
      80: aload         5
      82: iload         6
      84: aload         7
      86: invokevirtual #60                 // Method resolveAdapter:(Lorg/sonarsource/sonarlint/shaded/org/picocontainer/PicoContainer;Lorg/sonarsource/sonarlint/shaded/org/picocontainer/ComponentAdapter;Ljava/lang/Class;Lorg/sonarsource/sonarlint/shaded/org/picocontainer/NameBinding;ZLjava/lang/annotation/Annotation;)Lorg/sonarsource/sonarlint/shaded/org/picocontainer/ComponentAdapter;
      89: astore        9
      91: goto          97
      94: aload_3
      95: astore        9
      97: aload         9
      99: astore        10
     101: new           #11                 // class org/sonarsource/sonarlint/shaded/org/picocontainer/parameters/BasicComponentParameter$1
     104: dup
     105: aload_0
     106: aload         10
     108: aload_1
     109: aload         4
     111: aload_2
     112: invokespecial #63                 // Method org/sonarsource/sonarlint/shaded/org/picocontainer/parameters/BasicComponentParameter$1."<init>":(Lorg/sonarsource/sonarlint/shaded/org/picocontainer/parameters/BasicComponentParameter;Lorg/sonarsource/sonarlint/shaded/org/picocontainer/ComponentAdapter;Lorg/sonarsource/sonarlint/shaded/org/picocontainer/PicoContainer;Ljava/lang/reflect/Type;Lorg/sonarsource/sonarlint/shaded/org/picocontainer/ComponentAdapter;)V
     115: areturn

  private org.sonarsource.sonarlint.shaded.org.picocontainer.Converters getConverters(org.sonarsource.sonarlint.shaded.org.picocontainer.PicoContainer);
    Code:
       0: aload_1
       1: instanceof    #85                 // class org/sonarsource/sonarlint/shaded/org/picocontainer/Converting
       4: ifeq          19
       7: aload_1
       8: checkcast     #85                 // class org/sonarsource/sonarlint/shaded/org/picocontainer/Converting
      11: invokeinterface #88,  1           // InterfaceMethod org/sonarsource/sonarlint/shaded/org/picocontainer/Converting.getConverters:()Lorg/sonarsource/sonarlint/shaded/org/picocontainer/Converters;
      16: goto          20
      19: aconst_null
      20: areturn

  private static org.sonarsource.sonarlint.shaded.org.picocontainer.injectors.InjectInto makeInjectInto(org.sonarsource.sonarlint.shaded.org.picocontainer.ComponentAdapter<?>);
    Code:
       0: new           #93                 // class org/sonarsource/sonarlint/shaded/org/picocontainer/injectors/InjectInto
       3: dup
       4: aload_0
       5: invokeinterface #99,  1           // InterfaceMethod org/sonarsource/sonarlint/shaded/org/picocontainer/ComponentAdapter.getComponentImplementation:()Ljava/lang/Class;
      10: aload_0
      11: invokeinterface #103,  1          // InterfaceMethod org/sonarsource/sonarlint/shaded/org/picocontainer/ComponentAdapter.getComponentKey:()Ljava/lang/Object;
      16: invokespecial #106                // Method org/sonarsource/sonarlint/shaded/org/picocontainer/injectors/InjectInto."<init>":(Ljava/lang/reflect/Type;Ljava/lang/Object;)V
      19: areturn

  private static java.lang.Object convert(org.sonarsource.sonarlint.shaded.org.picocontainer.Converters, java.lang.Object, java.lang.reflect.Type);
    Code:
       0: aload_1
       1: instanceof    #110                // class java/lang/String
       4: ifeq          25
       7: aload_2
       8: ldc           #110                // class java/lang/String
      10: if_acmpeq     25
      13: aload_0
      14: aload_1
      15: checkcast     #110                // class java/lang/String
      18: aload_2
      19: invokeinterface #115,  3          // InterfaceMethod org/sonarsource/sonarlint/shaded/org/picocontainer/Converters.convert:(Ljava/lang/String;Ljava/lang/reflect/Type;)Ljava/lang/Object;
      24: astore_1
      25: aload_1
      26: areturn

  public void verify(org.sonarsource.sonarlint.shaded.org.picocontainer.PicoContainer, org.sonarsource.sonarlint.shaded.org.picocontainer.ComponentAdapter<?>, java.lang.reflect.Type, org.sonarsource.sonarlint.shaded.org.picocontainer.NameBinding, boolean, java.lang.annotation.Annotation);
    Code:
       0: aload_0
       1: aload_1
       2: aload_2
       3: aload_3
       4: checkcast     #44                 // class java/lang/Class
       7: aload         4
       9: iload         5
      11: aload         6
      13: invokevirtual #60                 // Method resolveAdapter:(Lorg/sonarsource/sonarlint/shaded/org/picocontainer/PicoContainer;Lorg/sonarsource/sonarlint/shaded/org/picocontainer/ComponentAdapter;Ljava/lang/Class;Lorg/sonarsource/sonarlint/shaded/org/picocontainer/NameBinding;ZLjava/lang/annotation/Annotation;)Lorg/sonarsource/sonarlint/shaded/org/picocontainer/ComponentAdapter;
      16: astore        7
      18: aload         7
      20: ifnonnull     90
      23: new           #123                // class java/util/HashSet
      26: dup
      27: invokespecial #124                // Method java/util/HashSet."<init>":()V
      30: astore        8
      32: aload         8
      34: aload_3
      35: invokeinterface #130,  2          // InterfaceMethod java/util/Set.add:(Ljava/lang/Object;)Z
      40: pop
      41: new           #24                 // class org/sonarsource/sonarlint/shaded/org/picocontainer/injectors/AbstractInjector$UnsatisfiableDependenciesException
      44: dup
      45: new           #132                // class java/lang/StringBuilder
      48: dup
      49: invokespecial #133                // Method java/lang/StringBuilder."<init>":()V
      52: aload_2
      53: invokeinterface #99,  1           // InterfaceMethod org/sonarsource/sonarlint/shaded/org/picocontainer/ComponentAdapter.getComponentImplementation:()Ljava/lang/Class;
      58: invokevirtual #137                // Method java/lang/Class.getName:()Ljava/lang/String;
      61: invokevirtual #141                // Method java/lang/StringBuilder.append:(Ljava/lang/String;)Ljava/lang/StringBuilder;
      64: ldc           #143                // String  has unsatisfied dependencies:
      66: invokevirtual #141                // Method java/lang/StringBuilder.append:(Ljava/lang/String;)Ljava/lang/StringBuilder;
      69: aload         8
      71: invokevirtual #146                // Method java/lang/StringBuilder.append:(Ljava/lang/Object;)Ljava/lang/StringBuilder;
      74: ldc           #148                // String  from
      76: invokevirtual #141                // Method java/lang/StringBuilder.append:(Ljava/lang/String;)Ljava/lang/StringBuilder;
      79: aload_1
      80: invokevirtual #146                // Method java/lang/StringBuilder.append:(Ljava/lang/Object;)Ljava/lang/StringBuilder;
      83: invokevirtual #151                // Method java/lang/StringBuilder.toString:()Ljava/lang/String;
      86: invokespecial #154                // Method org/sonarsource/sonarlint/shaded/org/picocontainer/injectors/AbstractInjector$UnsatisfiableDependenciesException."<init>":(Ljava/lang/String;)V
      89: athrow
      90: aload         7
      92: aload_1
      93: invokeinterface #157,  2          // InterfaceMethod org/sonarsource/sonarlint/shaded/org/picocontainer/ComponentAdapter.verify:(Lorg/sonarsource/sonarlint/shaded/org/picocontainer/PicoContainer;)V
      98: return

  public void accept(org.sonarsource.sonarlint.shaded.org.picocontainer.PicoVisitor);
    Code:
       0: aload_1
       1: aload_0
       2: invokeinterface #168,  2          // InterfaceMethod org/sonarsource/sonarlint/shaded/org/picocontainer/PicoVisitor.visitParameter:(Lorg/sonarsource/sonarlint/shaded/org/picocontainer/Parameter;)V
       7: return

  protected <T> org.sonarsource.sonarlint.shaded.org.picocontainer.ComponentAdapter<T> resolveAdapter(org.sonarsource.sonarlint.shaded.org.picocontainer.PicoContainer, org.sonarsource.sonarlint.shaded.org.picocontainer.ComponentAdapter, java.lang.Class<T>, org.sonarsource.sonarlint.shaded.org.picocontainer.NameBinding, boolean, java.lang.annotation.Annotation);
    Code:
       0: aload_3
       1: astore        7
       3: aload         7
       5: invokevirtual #175                // Method java/lang/Class.isPrimitive:()Z
       8: ifeq          126
      11: aload_3
      12: invokevirtual #137                // Method java/lang/Class.getName:()Ljava/lang/String;
      15: astore        8
      17: aload         8
      19: ldc           #177                // String int
      21: if_acmpne     31
      24: ldc           #179                // class java/lang/Integer
      26: astore        7
      28: goto          126
      31: aload         8
      33: ldc           #181                // String long
      35: if_acmpne     45
      38: ldc           #183                // class java/lang/Long
      40: astore        7
      42: goto          126
      45: aload         8
      47: ldc           #185                // String float
      49: if_acmpne     59
      52: ldc           #187                // class java/lang/Float
      54: astore        7
      56: goto          126
      59: aload         8
      61: ldc           #189                // String double
      63: if_acmpne     73
      66: ldc           #191                // class java/lang/Double
      68: astore        7
      70: goto          126
      73: aload         8
      75: ldc           #193                // String boolean
      77: if_acmpne     87
      80: ldc           #195                // class java/lang/Boolean
      82: astore        7
      84: goto          126
      87: aload         8
      89: ldc           #197                // String char
      91: if_acmpne     101
      94: ldc           #199                // class java/lang/Character
      96: astore        7
      98: goto          126
     101: aload         8
     103: ldc           #201                // String short
     105: if_acmpne     115
     108: ldc           #203                // class java/lang/Short
     110: astore        7
     112: goto          126
     115: aload         8
     117: ldc           #205                // String byte
     119: if_acmpne     126
     122: ldc           #207                // class java/lang/Byte
     124: astore        7
     126: aconst_null
     127: astore        8
     129: aload_0
     130: getfield      #38                 // Field componentKey:Ljava/lang/Object;
     133: ifnull        154
     136: aload_1
     137: aload_0
     138: getfield      #38                 // Field componentKey:Ljava/lang/Object;
     141: invokeinterface #213,  2          // InterfaceMethod org/sonarsource/sonarlint/shaded/org/picocontainer/PicoContainer.getComponentAdapter:(Ljava/lang/Object;)Lorg/sonarsource/sonarlint/shaded/org/picocontainer/ComponentAdapter;
     146: invokestatic  #217                // Method typeComponentAdapter:(Lorg/sonarsource/sonarlint/shaded/org/picocontainer/ComponentAdapter;)Lorg/sonarsource/sonarlint/shaded/org/picocontainer/ComponentAdapter;
     149: astore        8
     151: goto          374
     154: aload_2
     155: ifnonnull     175
     158: aload_1
     159: aload         7
     161: aconst_null
     162: checkcast     #219                // class org/sonarsource/sonarlint/shaded/org/picocontainer/NameBinding
     165: invokeinterface #222,  3          // InterfaceMethod org/sonarsource/sonarlint/shaded/org/picocontainer/PicoContainer.getComponentAdapter:(Ljava/lang/Class;Lorg/sonarsource/sonarlint/shaded/org/picocontainer/NameBinding;)Lorg/sonarsource/sonarlint/shaded/org/picocontainer/ComponentAdapter;
     170: astore        8
     172: goto          374
     175: aload_2
     176: invokeinterface #103,  1          // InterfaceMethod org/sonarsource/sonarlint/shaded/org/picocontainer/ComponentAdapter.getComponentKey:()Ljava/lang/Object;
     181: astore        9
     183: aload_1
     184: aload_3
     185: invokeinterface #213,  2          // InterfaceMethod org/sonarsource/sonarlint/shaded/org/picocontainer/PicoContainer.getComponentAdapter:(Ljava/lang/Object;)Lorg/sonarsource/sonarlint/shaded/org/picocontainer/ComponentAdapter;
     190: astore        10
     192: aload         10
     194: ifnull        219
     197: aload         9
     199: aload         10
     201: invokeinterface #103,  1          // InterfaceMethod org/sonarsource/sonarlint/shaded/org/picocontainer/ComponentAdapter.getComponentKey:()Ljava/lang/Object;
     206: invokevirtual #227                // Method java/lang/Object.equals:(Ljava/lang/Object;)Z
     209: ifne          219
     212: aload         10
     214: invokestatic  #217                // Method typeComponentAdapter:(Lorg/sonarsource/sonarlint/shaded/org/picocontainer/ComponentAdapter;)Lorg/sonarsource/sonarlint/shaded/org/picocontainer/ComponentAdapter;
     217: astore        8
     219: aload         8
     221: ifnonnull     270
     224: iload         5
     226: ifeq          270
     229: aload_1
     230: aload         4
     232: invokeinterface #228,  1          // InterfaceMethod org/sonarsource/sonarlint/shaded/org/picocontainer/NameBinding.getName:()Ljava/lang/String;
     237: invokeinterface #213,  2          // InterfaceMethod org/sonarsource/sonarlint/shaded/org/picocontainer/PicoContainer.getComponentAdapter:(Ljava/lang/Object;)Lorg/sonarsource/sonarlint/shaded/org/picocontainer/ComponentAdapter;
     242: astore        11
     244: aload         11
     246: ifnull        270
     249: aload_0
     250: aload_1
     251: aload_3
     252: aload         11
     254: invokespecial #232                // Method areCompatible:(Lorg/sonarsource/sonarlint/shaded/org/picocontainer/PicoContainer;Ljava/lang/Class;Lorg/sonarsource/sonarlint/shaded/org/picocontainer/ComponentAdapter;)Z
     257: ifeq          270
     260: aload         11
     262: aload_2
     263: if_acmpeq     270
     266: aload         11
     268: astore        8
     270: aload         8
     272: ifnonnull     374
     275: aload         6
     277: ifnonnull     290
     280: aload_1
     281: aload_3
     282: invokeinterface #236,  2          // InterfaceMethod org/sonarsource/sonarlint/shaded/org/picocontainer/PicoContainer.getComponentAdapters:(Ljava/lang/Class;)Ljava/util/List;
     287: goto          304
     290: aload_1
     291: aload_3
     292: aload         6
     294: invokeinterface #241,  1          // InterfaceMethod java/lang/annotation/Annotation.annotationType:()Ljava/lang/Class;
     299: invokeinterface #244,  3          // InterfaceMethod org/sonarsource/sonarlint/shaded/org/picocontainer/PicoContainer.getComponentAdapters:(Ljava/lang/Class;Ljava/lang/Class;)Ljava/util/List;
     304: astore        11
     306: aload_0
     307: aload         9
     309: aload         11
     311: invokespecial #248                // Method removeExcludedAdapterIfApplicable:(Ljava/lang/Object;Ljava/util/List;)V
     314: aload         11
     316: invokeinterface #254,  1          // InterfaceMethod java/util/List.size:()I
     321: ifne          339
     324: aload_0
     325: aload_1
     326: aload_3
     327: aload         4
     329: aload         6
     331: invokespecial #258                // Method noMatchingAdaptersFound:(Lorg/sonarsource/sonarlint/shaded/org/picocontainer/PicoContainer;Ljava/lang/Class;Lorg/sonarsource/sonarlint/shaded/org/picocontainer/NameBinding;Ljava/lang/annotation/Annotation;)Lorg/sonarsource/sonarlint/shaded/org/picocontainer/ComponentAdapter;
     334: astore        8
     336: goto          374
     339: aload         11
     341: invokeinterface #254,  1          // InterfaceMethod java/util/List.size:()I
     346: iconst_1
     347: if_icmpne     366
     350: aload         11
     352: iconst_0
     353: invokeinterface #262,  2          // InterfaceMethod java/util/List.get:(I)Ljava/lang/Object;
     358: checkcast     #95                 // class org/sonarsource/sonarlint/shaded/org/picocontainer/ComponentAdapter
     361: astore        8
     363: goto          374
     366: aload_0
     367: aload_3
     368: aload         11
     370: invokespecial #266                // Method tooManyMatchingAdaptersFound:(Ljava/lang/Class;Ljava/util/List;)Lorg/sonarsource/sonarlint/shaded/org/picocontainer/injectors/AbstractInjector$AmbiguousComponentResolutionException;
     373: athrow
     374: aload         8
     376: ifnonnull     381
     379: aconst_null
     380: areturn
     381: aload         7
     383: aload         8
     385: invokeinterface #99,  1           // InterfaceMethod org/sonarsource/sonarlint/shaded/org/picocontainer/ComponentAdapter.getComponentImplementation:()Ljava/lang/Class;
     390: invokevirtual #270                // Method java/lang/Class.isAssignableFrom:(Ljava/lang/Class;)Z
     393: ifne          425
     396: aload         8
     398: invokeinterface #99,  1           // InterfaceMethod org/sonarsource/sonarlint/shaded/org/picocontainer/ComponentAdapter.getComponentImplementation:()Ljava/lang/Class;
     403: ldc           #110                // class java/lang/String
     405: if_acmpne     423
     408: aload_0
     409: aload_1
     410: invokespecial #272                // Method getConverters:(Lorg/sonarsource/sonarlint/shaded/org/picocontainer/PicoContainer;)Lorg/sonarsource/sonarlint/shaded/org/picocontainer/Converters;
     413: aload         7
     415: invokeinterface #276,  2          // InterfaceMethod org/sonarsource/sonarlint/shaded/org/picocontainer/Converters.canConvert:(Ljava/lang/reflect/Type;)Z
     420: ifne          425
     423: aconst_null
     424: areturn
     425: aload         8
     427: areturn

  private static <T> org.sonarsource.sonarlint.shaded.org.picocontainer.ComponentAdapter<T> typeComponentAdapter(org.sonarsource.sonarlint.shaded.org.picocontainer.ComponentAdapter<?>);
    Code:
       0: aload_0
       1: areturn

  private <T> org.sonarsource.sonarlint.shaded.org.picocontainer.ComponentAdapter<T> noMatchingAdaptersFound(org.sonarsource.sonarlint.shaded.org.picocontainer.PicoContainer, java.lang.Class<T>, org.sonarsource.sonarlint.shaded.org.picocontainer.NameBinding, java.lang.annotation.Annotation);
    Code:
       0: aload_1
       1: invokeinterface #294,  1          // InterfaceMethod org/sonarsource/sonarlint/shaded/org/picocontainer/PicoContainer.getParent:()Lorg/sonarsource/sonarlint/shaded/org/picocontainer/PicoContainer;
       6: ifnull        46
       9: aload         4
      11: ifnull        32
      14: aload_1
      15: invokeinterface #294,  1          // InterfaceMethod org/sonarsource/sonarlint/shaded/org/picocontainer/PicoContainer.getParent:()Lorg/sonarsource/sonarlint/shaded/org/picocontainer/PicoContainer;
      20: aload_2
      21: aload         4
      23: invokevirtual #297                // Method java/lang/Object.getClass:()Ljava/lang/Class;
      26: invokeinterface #300,  3          // InterfaceMethod org/sonarsource/sonarlint/shaded/org/picocontainer/PicoContainer.getComponentAdapter:(Ljava/lang/Class;Ljava/lang/Class;)Lorg/sonarsource/sonarlint/shaded/org/picocontainer/ComponentAdapter;
      31: areturn
      32: aload_1
      33: invokeinterface #294,  1          // InterfaceMethod org/sonarsource/sonarlint/shaded/org/picocontainer/PicoContainer.getParent:()Lorg/sonarsource/sonarlint/shaded/org/picocontainer/PicoContainer;
      38: aload_2
      39: aload_3
      40: invokeinterface #222,  3          // InterfaceMethod org/sonarsource/sonarlint/shaded/org/picocontainer/PicoContainer.getComponentAdapter:(Ljava/lang/Class;Lorg/sonarsource/sonarlint/shaded/org/picocontainer/NameBinding;)Lorg/sonarsource/sonarlint/shaded/org/picocontainer/ComponentAdapter;
      45: areturn
      46: aconst_null
      47: areturn

  private <T> org.sonarsource.sonarlint.shaded.org.picocontainer.injectors.AbstractInjector$AmbiguousComponentResolutionException tooManyMatchingAdaptersFound(java.lang.Class<T>, java.util.List<org.sonarsource.sonarlint.shaded.org.picocontainer.ComponentAdapter<T>>);
    Code:
       0: aload_2
       1: invokestatic  #305                // Method makeFoundAmbiguousStrings:(Ljava/util/Collection;)[Ljava/lang/String;
       4: astore_3
       5: new           #16                 // class org/sonarsource/sonarlint/shaded/org/picocontainer/injectors/AbstractInjector$AmbiguousComponentResolutionException
       8: dup
       9: aload_1
      10: aload_3
      11: invokespecial #308                // Method org/sonarsource/sonarlint/shaded/org/picocontainer/injectors/AbstractInjector$AmbiguousComponentResolutionException."<init>":(Ljava/lang/Class;[Ljava/lang/String;)V
      14: areturn

  public static <T> java.lang.String[] makeFoundAmbiguousStrings(java.util.Collection<org.sonarsource.sonarlint.shaded.org.picocontainer.ComponentAdapter<T>>);
    Code:
       0: aload_0
       1: invokeinterface #314,  1          // InterfaceMethod java/util/Collection.size:()I
       6: anewarray     #110                // class java/lang/String
       9: astore_1
      10: iconst_0
      11: istore_2
      12: aload_0
      13: invokeinterface #318,  1          // InterfaceMethod java/util/Collection.iterator:()Ljava/util/Iterator;
      18: astore_3
      19: aload_3
      20: invokeinterface #323,  1          // InterfaceMethod java/util/Iterator.hasNext:()Z
      25: ifeq          60
      28: aload_3
      29: invokeinterface #326,  1          // InterfaceMethod java/util/Iterator.next:()Ljava/lang/Object;
      34: checkcast     #95                 // class org/sonarsource/sonarlint/shaded/org/picocontainer/ComponentAdapter
      37: astore        4
      39: aload         4
      41: invokestatic  #329                // Method findInjectorOrInstanceAdapter:(Lorg/sonarsource/sonarlint/shaded/org/picocontainer/ComponentAdapter;)Lorg/sonarsource/sonarlint/shaded/org/picocontainer/ComponentAdapter;
      44: astore        4
      46: aload_1
      47: iload_2
      48: iinc          2, 1
      51: aload         4
      53: invokevirtual #330                // Method java/lang/Object.toString:()Ljava/lang/String;
      56: aastore
      57: goto          19
      60: aload_1
      61: areturn

  public static org.sonarsource.sonarlint.shaded.org.picocontainer.ComponentAdapter<?> findInjectorOrInstanceAdapter(org.sonarsource.sonarlint.shaded.org.picocontainer.ComponentAdapter<?>);
    Code:
       0: aload_0
       1: instanceof    #340                // class org/sonarsource/sonarlint/shaded/org/picocontainer/Behavior
       4: ifne          28
       7: aload_0
       8: instanceof    #342                // class org/sonarsource/sonarlint/shaded/org/picocontainer/LifecycleStrategy
      11: ifeq          38
      14: aload_0
      15: instanceof    #344                // class org/sonarsource/sonarlint/shaded/org/picocontainer/adapters/InstanceAdapter
      18: ifne          38
      21: aload_0
      22: instanceof    #346                // class org/sonarsource/sonarlint/shaded/org/picocontainer/injectors/Provider
      25: ifne          38
      28: aload_0
      29: invokeinterface #350,  1          // InterfaceMethod org/sonarsource/sonarlint/shaded/org/picocontainer/ComponentAdapter.getDelegate:()Lorg/sonarsource/sonarlint/shaded/org/picocontainer/ComponentAdapter;
      34: astore_0
      35: goto          0
      38: aload_0
      39: areturn

  private <T> void removeExcludedAdapterIfApplicable(java.lang.Object, java.util.List<org.sonarsource.sonarlint.shaded.org.picocontainer.ComponentAdapter<T>>);
    Code:
       0: aconst_null
       1: astore_3
       2: aload_2
       3: invokeinterface #352,  1          // InterfaceMethod java/util/List.iterator:()Ljava/util/Iterator;
       8: astore        4
      10: aload         4
      12: invokeinterface #323,  1          // InterfaceMethod java/util/Iterator.hasNext:()Z
      17: ifeq          55
      20: aload         4
      22: invokeinterface #326,  1          // InterfaceMethod java/util/Iterator.next:()Ljava/lang/Object;
      27: checkcast     #95                 // class org/sonarsource/sonarlint/shaded/org/picocontainer/ComponentAdapter
      30: astore        5
      32: aload         5
      34: invokeinterface #103,  1          // InterfaceMethod org/sonarsource/sonarlint/shaded/org/picocontainer/ComponentAdapter.getComponentKey:()Ljava/lang/Object;
      39: aload_1
      40: invokevirtual #227                // Method java/lang/Object.equals:(Ljava/lang/Object;)Z
      43: ifeq          52
      46: aload         5
      48: astore_3
      49: goto          55
      52: goto          10
      55: aload_2
      56: aload_3
      57: invokeinterface #355,  2          // InterfaceMethod java/util/List.remove:(Ljava/lang/Object;)Z
      62: pop
      63: return

  private <T> boolean areCompatible(org.sonarsource.sonarlint.shaded.org.picocontainer.PicoContainer, java.lang.Class<T>, org.sonarsource.sonarlint.shaded.org.picocontainer.ComponentAdapter);
    Code:
       0: aload_3
       1: invokeinterface #99,  1           // InterfaceMethod org/sonarsource/sonarlint/shaded/org/picocontainer/ComponentAdapter.getComponentImplementation:()Ljava/lang/Class;
       6: astore        4
       8: aload_2
       9: aload         4
      11: invokevirtual #270                // Method java/lang/Class.isAssignableFrom:(Ljava/lang/Class;)Z
      14: ifne          46
      17: aload         4
      19: ldc           #110                // class java/lang/String
      21: if_acmpne     50
      24: aload_0
      25: aload_1
      26: invokespecial #272                // Method getConverters:(Lorg/sonarsource/sonarlint/shaded/org/picocontainer/PicoContainer;)Lorg/sonarsource/sonarlint/shaded/org/picocontainer/Converters;
      29: ifnull        50
      32: aload_0
      33: aload_1
      34: invokespecial #272                // Method getConverters:(Lorg/sonarsource/sonarlint/shaded/org/picocontainer/PicoContainer;)Lorg/sonarsource/sonarlint/shaded/org/picocontainer/Converters;
      37: aload_2
      38: invokeinterface #276,  2          // InterfaceMethod org/sonarsource/sonarlint/shaded/org/picocontainer/Converters.canConvert:(Ljava/lang/reflect/Type;)Z
      43: ifeq          50
      46: iconst_1
      47: goto          51
      50: iconst_0
      51: ireturn

  static org.sonarsource.sonarlint.shaded.org.picocontainer.Converters access$000(org.sonarsource.sonarlint.shaded.org.picocontainer.parameters.BasicComponentParameter, org.sonarsource.sonarlint.shaded.org.picocontainer.PicoContainer);
    Code:
       0: aload_0
       1: aload_1
       2: invokespecial #272                // Method getConverters:(Lorg/sonarsource/sonarlint/shaded/org/picocontainer/PicoContainer;)Lorg/sonarsource/sonarlint/shaded/org/picocontainer/Converters;
       5: areturn

  static java.lang.Object access$100(org.sonarsource.sonarlint.shaded.org.picocontainer.Converters, java.lang.Object, java.lang.reflect.Type);
    Code:
       0: aload_0
       1: aload_1
       2: aload_2
       3: invokestatic  #366                // Method convert:(Lorg/sonarsource/sonarlint/shaded/org/picocontainer/Converters;Ljava/lang/Object;Ljava/lang/reflect/Type;)Ljava/lang/Object;
       6: areturn

  static org.sonarsource.sonarlint.shaded.org.picocontainer.injectors.InjectInto access$200(org.sonarsource.sonarlint.shaded.org.picocontainer.ComponentAdapter);
    Code:
       0: aload_0
       1: invokestatic  #370                // Method makeInjectInto:(Lorg/sonarsource/sonarlint/shaded/org/picocontainer/ComponentAdapter;)Lorg/sonarsource/sonarlint/shaded/org/picocontainer/injectors/InjectInto;
       4: areturn

  static {};
    Code:
       0: ldc           #2                  // class org/sonarsource/sonarlint/shaded/org/picocontainer/parameters/BasicComponentParameter
       2: invokevirtual #374                // Method java/lang/Class.desiredAssertionStatus:()Z
       5: ifne          12
       8: iconst_1
       9: goto          13
      12: iconst_0
      13: putstatic     #53                 // Field $assertionsDisabled:Z
      16: new           #2                  // class org/sonarsource/sonarlint/shaded/org/picocontainer/parameters/BasicComponentParameter
      19: dup
      20: invokespecial #375                // Method "<init>":()V
      23: putstatic     #377                // Field BASIC_DEFAULT:Lorg/sonarsource/sonarlint/shaded/org/picocontainer/parameters/BasicComponentParameter;
      26: return
}
