Compiled from "CollectionComponentParameter.java"
public class org.sonarsource.sonarlint.shaded.org.picocontainer.parameters.CollectionComponentParameter extends org.sonarsource.sonarlint.shaded.org.picocontainer.parameters.AbstractParameter implements org.sonarsource.sonarlint.shaded.org.picocontainer.Parameter,java.io.Serializable {
  public static final org.sonarsource.sonarlint.shaded.org.picocontainer.parameters.CollectionComponentParameter ARRAY;

  public static final org.sonarsource.sonarlint.shaded.org.picocontainer.parameters.CollectionComponentParameter ARRAY_ALLOW_EMPTY;

  private final boolean emptyCollection;

  private final java.lang.Class componentKeyType;

  private final java.lang.Class componentValueType;

  public org.sonarsource.sonarlint.shaded.org.picocontainer.parameters.CollectionComponentParameter();
    Code:
       0: aload_0
       1: iconst_0
       2: invokespecial #35                 // Method "<init>":(Z)V
       5: return

  public org.sonarsource.sonarlint.shaded.org.picocontainer.parameters.CollectionComponentParameter(boolean);
    Code:
       0: aload_0
       1: getstatic     #41                 // Field java/lang/Void.TYPE:Ljava/lang/Class;
       4: iload_1
       5: invokespecial #44                 // Method "<init>":(Ljava/lang/Class;Z)V
       8: return

  public org.sonarsource.sonarlint.shaded.org.picocontainer.parameters.CollectionComponentParameter(java.lang.Class, boolean);
    Code:
       0: aload_0
       1: ldc           #46                 // class java/lang/Object
       3: aload_1
       4: iload_2
       5: invokespecial #49                 // Method "<init>":(Ljava/lang/Class;Ljava/lang/Class;Z)V
       8: return

  public org.sonarsource.sonarlint.shaded.org.picocontainer.parameters.CollectionComponentParameter(java.lang.Class, java.lang.Class, boolean);
    Code:
       0: aload_0
       1: invokespecial #51                 // Method org/sonarsource/sonarlint/shaded/org/picocontainer/parameters/AbstractParameter."<init>":()V
       4: aload_0
       5: iload_3
       6: putfield      #53                 // Field emptyCollection:Z
       9: aload_0
      10: aload_1
      11: putfield      #55                 // Field componentKeyType:Ljava/lang/Class;
      14: aload_0
      15: aload_2
      16: putfield      #57                 // Field componentValueType:Ljava/lang/Class;
      19: return

  public org.sonarsource.sonarlint.shaded.org.picocontainer.Parameter$Resolver resolve(org.sonarsource.sonarlint.shaded.org.picocontainer.PicoContainer, org.sonarsource.sonarlint.shaded.org.picocontainer.ComponentAdapter<?>, org.sonarsource.sonarlint.shaded.org.picocontainer.ComponentAdapter<?>, java.lang.reflect.Type, org.sonarsource.sonarlint.shaded.org.picocontainer.NameBinding, boolean, java.lang.annotation.Annotation);
    Code:
       0: aload_0
       1: aload         4
       3: invokespecial #64                 // Method getCollectionType:(Ljava/lang/reflect/Type;)Ljava/lang/Class;
       6: astore        8
       8: aload         8
      10: ifnull        51
      13: aload_0
      14: aload_1
      15: aload_2
      16: aload_0
      17: getfield      #55                 // Field componentKeyType:Ljava/lang/Class;
      20: aload_0
      21: aload         4
      23: invokespecial #67                 // Method getValueType:(Ljava/lang/reflect/Type;)Ljava/lang/Class;
      26: invokevirtual #71                 // Method getMatchingComponentAdapters:(Lorg/sonarsource/sonarlint/shaded/org/picocontainer/PicoContainer;Lorg/sonarsource/sonarlint/shaded/org/picocontainer/ComponentAdapter;Ljava/lang/Class;Ljava/lang/Class;)Ljava/util/Map;
      29: astore        9
      31: new           #11                 // class org/sonarsource/sonarlint/shaded/org/picocontainer/parameters/CollectionComponentParameter$1
      34: dup
      35: aload_0
      36: aload         9
      38: aload         8
      40: aload_1
      41: aload         5
      43: iload         6
      45: aload         4
      47: invokespecial #74                 // Method org/sonarsource/sonarlint/shaded/org/picocontainer/parameters/CollectionComponentParameter$1."<init>":(Lorg/sonarsource/sonarlint/shaded/org/picocontainer/parameters/CollectionComponentParameter;Ljava/util/Map;Ljava/lang/Class;Lorg/sonarsource/sonarlint/shaded/org/picocontainer/PicoContainer;Lorg/sonarsource/sonarlint/shaded/org/picocontainer/NameBinding;ZLjava/lang/reflect/Type;)V
      50: areturn
      51: new           #21                 // class org/sonarsource/sonarlint/shaded/org/picocontainer/Parameter$NotResolved
      54: dup
      55: invokespecial #75                 // Method org/sonarsource/sonarlint/shaded/org/picocontainer/Parameter$NotResolved."<init>":()V
      58: areturn

  private java.lang.Class getCollectionType(java.lang.reflect.Type);
    Code:
       0: aload_1
       1: instanceof    #94                 // class java/lang/Class
       4: ifeq          16
       7: aload_0
       8: aload_1
       9: checkcast     #94                 // class java/lang/Class
      12: invokespecial #97                 // Method getCollectionType:(Ljava/lang/Class;)Ljava/lang/Class;
      15: areturn
      16: aload_1
      17: instanceof    #99                 // class java/lang/reflect/ParameterizedType
      20: ifeq          39
      23: aload_1
      24: checkcast     #99                 // class java/lang/reflect/ParameterizedType
      27: astore_2
      28: aload_0
      29: aload_2
      30: invokeinterface #103,  1          // InterfaceMethod java/lang/reflect/ParameterizedType.getRawType:()Ljava/lang/reflect/Type;
      35: invokespecial #64                 // Method getCollectionType:(Ljava/lang/reflect/Type;)Ljava/lang/Class;
      38: areturn
      39: aload_1
      40: instanceof    #105                // class java/lang/reflect/GenericArrayType
      43: ifeq          71
      46: aload_1
      47: checkcast     #105                // class java/lang/reflect/GenericArrayType
      50: astore_2
      51: aload_0
      52: aload_2
      53: invokeinterface #108,  1          // InterfaceMethod java/lang/reflect/GenericArrayType.getGenericComponentType:()Ljava/lang/reflect/Type;
      58: invokespecial #111                // Method getGenericArrayBaseType:(Ljava/lang/reflect/Type;)Ljava/lang/Class;
      61: astore_3
      62: aload_3
      63: iconst_0
      64: invokestatic  #117                // Method java/lang/reflect/Array.newInstance:(Ljava/lang/Class;I)Ljava/lang/Object;
      67: invokevirtual #121                // Method java/lang/Object.getClass:()Ljava/lang/Class;
      70: areturn
      71: new           #123                // class java/lang/IllegalArgumentException
      74: dup
      75: new           #125                // class java/lang/StringBuilder
      78: dup
      79: invokespecial #126                // Method java/lang/StringBuilder."<init>":()V
      82: ldc           #128                // String Unable to get collection type from
      84: invokevirtual #132                // Method java/lang/StringBuilder.append:(Ljava/lang/String;)Ljava/lang/StringBuilder;
      87: aload_1
      88: invokevirtual #135                // Method java/lang/StringBuilder.append:(Ljava/lang/Object;)Ljava/lang/StringBuilder;
      91: invokevirtual #139                // Method java/lang/StringBuilder.toString:()Ljava/lang/String;
      94: invokespecial #142                // Method java/lang/IllegalArgumentException."<init>":(Ljava/lang/String;)V
      97: athrow

  private java.lang.Class getGenericArrayBaseType(java.lang.reflect.Type);
    Code:
       0: aload_1
       1: instanceof    #94                 // class java/lang/Class
       4: ifeq          14
       7: aload_1
       8: checkcast     #94                 // class java/lang/Class
      11: astore_2
      12: aload_2
      13: areturn
      14: aload_1
      15: instanceof    #99                 // class java/lang/reflect/ParameterizedType
      18: ifeq          37
      21: aload_1
      22: checkcast     #99                 // class java/lang/reflect/ParameterizedType
      25: astore_2
      26: aload_0
      27: aload_2
      28: invokeinterface #103,  1          // InterfaceMethod java/lang/reflect/ParameterizedType.getRawType:()Ljava/lang/reflect/Type;
      33: invokespecial #111                // Method getGenericArrayBaseType:(Ljava/lang/reflect/Type;)Ljava/lang/Class;
      36: areturn
      37: new           #123                // class java/lang/IllegalArgumentException
      40: dup
      41: new           #125                // class java/lang/StringBuilder
      44: dup
      45: invokespecial #126                // Method java/lang/StringBuilder."<init>":()V
      48: ldc           #128                // String Unable to get collection type from
      50: invokevirtual #132                // Method java/lang/StringBuilder.append:(Ljava/lang/String;)Ljava/lang/StringBuilder;
      53: aload_1
      54: invokevirtual #135                // Method java/lang/StringBuilder.append:(Ljava/lang/Object;)Ljava/lang/StringBuilder;
      57: invokevirtual #139                // Method java/lang/StringBuilder.toString:()Ljava/lang/String;
      60: invokespecial #142                // Method java/lang/IllegalArgumentException."<init>":(Ljava/lang/String;)V
      63: athrow

  public void verify(org.sonarsource.sonarlint.shaded.org.picocontainer.PicoContainer, org.sonarsource.sonarlint.shaded.org.picocontainer.ComponentAdapter<?>, java.lang.reflect.Type, org.sonarsource.sonarlint.shaded.org.picocontainer.NameBinding, boolean, java.lang.annotation.Annotation);
    Code:
       0: aload_0
       1: aload_3
       2: invokespecial #64                 // Method getCollectionType:(Ljava/lang/reflect/Type;)Ljava/lang/Class;
       5: astore        7
       7: aload         7
       9: ifnull        144
      12: aload_0
      13: aload_3
      14: invokespecial #67                 // Method getValueType:(Ljava/lang/reflect/Type;)Ljava/lang/Class;
      17: astore        8
      19: aload_0
      20: aload_1
      21: aload_2
      22: aload_0
      23: getfield      #55                 // Field componentKeyType:Ljava/lang/Class;
      26: aload         8
      28: invokevirtual #71                 // Method getMatchingComponentAdapters:(Lorg/sonarsource/sonarlint/shaded/org/picocontainer/PicoContainer;Lorg/sonarsource/sonarlint/shaded/org/picocontainer/ComponentAdapter;Ljava/lang/Class;Ljava/lang/Class;)Ljava/util/Map;
      31: invokeinterface #153,  1          // InterfaceMethod java/util/Map.values:()Ljava/util/Collection;
      36: astore        9
      38: aload         9
      40: invokeinterface #159,  1          // InterfaceMethod java/util/Collection.isEmpty:()Z
      45: ifeq          95
      48: aload_0
      49: getfield      #53                 // Field emptyCollection:Z
      52: ifne          141
      55: new           #161                // class org/sonarsource/sonarlint/shaded/org/picocontainer/PicoCompositionException
      58: dup
      59: new           #125                // class java/lang/StringBuilder
      62: dup
      63: invokespecial #126                // Method java/lang/StringBuilder."<init>":()V
      66: aload_3
      67: invokevirtual #135                // Method java/lang/StringBuilder.append:(Ljava/lang/Object;)Ljava/lang/StringBuilder;
      70: ldc           #163                // String  not resolvable, no components of type
      72: invokevirtual #132                // Method java/lang/StringBuilder.append:(Ljava/lang/String;)Ljava/lang/StringBuilder;
      75: aload         8
      77: invokevirtual #166                // Method java/lang/Class.getName:()Ljava/lang/String;
      80: invokevirtual #132                // Method java/lang/StringBuilder.append:(Ljava/lang/String;)Ljava/lang/StringBuilder;
      83: ldc           #168                // String  available
      85: invokevirtual #132                // Method java/lang/StringBuilder.append:(Ljava/lang/String;)Ljava/lang/StringBuilder;
      88: invokevirtual #139                // Method java/lang/StringBuilder.toString:()Ljava/lang/String;
      91: invokespecial #169                // Method org/sonarsource/sonarlint/shaded/org/picocontainer/PicoCompositionException."<init>":(Ljava/lang/String;)V
      94: athrow
      95: aload         9
      97: invokeinterface #173,  1          // InterfaceMethod java/util/Collection.iterator:()Ljava/util/Iterator;
     102: astore        10
     104: aload         10
     106: invokeinterface #178,  1          // InterfaceMethod java/util/Iterator.hasNext:()Z
     111: ifeq          141
     114: aload         10
     116: invokeinterface #182,  1          // InterfaceMethod java/util/Iterator.next:()Ljava/lang/Object;
     121: astore        11
     123: aload         11
     125: checkcast     #184                // class org/sonarsource/sonarlint/shaded/org/picocontainer/ComponentAdapter
     128: astore        12
     130: aload         12
     132: aload_1
     133: invokeinterface #187,  2          // InterfaceMethod org/sonarsource/sonarlint/shaded/org/picocontainer/ComponentAdapter.verify:(Lorg/sonarsource/sonarlint/shaded/org/picocontainer/PicoContainer;)V
     138: goto          104
     141: goto          171
     144: new           #161                // class org/sonarsource/sonarlint/shaded/org/picocontainer/PicoCompositionException
     147: dup
     148: new           #125                // class java/lang/StringBuilder
     151: dup
     152: invokespecial #126                // Method java/lang/StringBuilder."<init>":()V
     155: aload_3
     156: invokevirtual #135                // Method java/lang/StringBuilder.append:(Ljava/lang/Object;)Ljava/lang/StringBuilder;
     159: ldc           #189                // String  is not a collective type
     161: invokevirtual #132                // Method java/lang/StringBuilder.append:(Ljava/lang/String;)Ljava/lang/StringBuilder;
     164: invokevirtual #139                // Method java/lang/StringBuilder.toString:()Ljava/lang/String;
     167: invokespecial #169                // Method org/sonarsource/sonarlint/shaded/org/picocontainer/PicoCompositionException."<init>":(Ljava/lang/String;)V
     170: athrow
     171: return

  public void accept(org.sonarsource.sonarlint.shaded.org.picocontainer.PicoVisitor);
    Code:
       0: aload_1
       1: aload_0
       2: invokeinterface #205,  2          // InterfaceMethod org/sonarsource/sonarlint/shaded/org/picocontainer/PicoVisitor.visitParameter:(Lorg/sonarsource/sonarlint/shaded/org/picocontainer/Parameter;)V
       7: return

  protected boolean evaluate(org.sonarsource.sonarlint.shaded.org.picocontainer.ComponentAdapter);
    Code:
       0: aload_1
       1: ifnull        8
       4: iconst_1
       5: goto          9
       8: iconst_0
       9: ireturn

  protected java.util.Map<java.lang.Object, org.sonarsource.sonarlint.shaded.org.picocontainer.ComponentAdapter<?>> getMatchingComponentAdapters(org.sonarsource.sonarlint.shaded.org.picocontainer.PicoContainer, org.sonarsource.sonarlint.shaded.org.picocontainer.ComponentAdapter, java.lang.Class, java.lang.Class);
    Code:
       0: new           #212                // class java/util/LinkedHashMap
       3: dup
       4: invokespecial #213                // Method java/util/LinkedHashMap."<init>":()V
       7: astore        5
       9: aload_1
      10: invokeinterface #219,  1          // InterfaceMethod org/sonarsource/sonarlint/shaded/org/picocontainer/PicoContainer.getParent:()Lorg/sonarsource/sonarlint/shaded/org/picocontainer/PicoContainer;
      15: astore        6
      17: aload         6
      19: ifnull        39
      22: aload         5
      24: aload_0
      25: aload         6
      27: aload_2
      28: aload_3
      29: aload         4
      31: invokevirtual #71                 // Method getMatchingComponentAdapters:(Lorg/sonarsource/sonarlint/shaded/org/picocontainer/PicoContainer;Lorg/sonarsource/sonarlint/shaded/org/picocontainer/ComponentAdapter;Ljava/lang/Class;Ljava/lang/Class;)Ljava/util/Map;
      34: invokeinterface #223,  2          // InterfaceMethod java/util/Map.putAll:(Ljava/util/Map;)V
      39: aload_1
      40: invokeinterface #226,  1          // InterfaceMethod org/sonarsource/sonarlint/shaded/org/picocontainer/PicoContainer.getComponentAdapters:()Ljava/util/Collection;
      45: astore        7
      47: aload         7
      49: invokeinterface #173,  1          // InterfaceMethod java/util/Collection.iterator:()Ljava/util/Iterator;
      54: astore        8
      56: aload         8
      58: invokeinterface #178,  1          // InterfaceMethod java/util/Iterator.hasNext:()Z
      63: ifeq          96
      66: aload         8
      68: invokeinterface #182,  1          // InterfaceMethod java/util/Iterator.next:()Ljava/lang/Object;
      73: checkcast     #184                // class org/sonarsource/sonarlint/shaded/org/picocontainer/ComponentAdapter
      76: astore        9
      78: aload         5
      80: aload         9
      82: invokeinterface #229,  1          // InterfaceMethod org/sonarsource/sonarlint/shaded/org/picocontainer/ComponentAdapter.getComponentKey:()Ljava/lang/Object;
      87: invokeinterface #233,  2          // InterfaceMethod java/util/Map.remove:(Ljava/lang/Object;)Ljava/lang/Object;
      92: pop
      93: goto          56
      96: ldc           #235                // class java/util/List
      98: aload_1
      99: aload         4
     101: invokeinterface #238,  2          // InterfaceMethod org/sonarsource/sonarlint/shaded/org/picocontainer/PicoContainer.getComponentAdapters:(Ljava/lang/Class;)Ljava/util/List;
     106: invokevirtual #241                // Method java/lang/Class.cast:(Ljava/lang/Object;)Ljava/lang/Object;
     109: checkcast     #235                // class java/util/List
     112: astore        8
     114: aload         8
     116: invokeinterface #242,  1          // InterfaceMethod java/util/List.iterator:()Ljava/util/Iterator;
     121: astore        9
     123: aload         9
     125: invokeinterface #178,  1          // InterfaceMethod java/util/Iterator.hasNext:()Z
     130: ifeq          211
     133: aload         9
     135: invokeinterface #182,  1          // InterfaceMethod java/util/Iterator.next:()Ljava/lang/Object;
     140: checkcast     #184                // class org/sonarsource/sonarlint/shaded/org/picocontainer/ComponentAdapter
     143: astore        10
     145: aload         10
     147: invokeinterface #229,  1          // InterfaceMethod org/sonarsource/sonarlint/shaded/org/picocontainer/ComponentAdapter.getComponentKey:()Ljava/lang/Object;
     152: astore        11
     154: aload_2
     155: ifnull        175
     158: aload         11
     160: aload_2
     161: invokeinterface #229,  1          // InterfaceMethod org/sonarsource/sonarlint/shaded/org/picocontainer/ComponentAdapter.getComponentKey:()Ljava/lang/Object;
     166: invokevirtual #246                // Method java/lang/Object.equals:(Ljava/lang/Object;)Z
     169: ifeq          175
     172: goto          123
     175: aload_3
     176: aload         11
     178: invokevirtual #121                // Method java/lang/Object.getClass:()Ljava/lang/Class;
     181: invokevirtual #250                // Method java/lang/Class.isAssignableFrom:(Ljava/lang/Class;)Z
     184: ifeq          208
     187: aload_0
     188: aload         10
     190: invokevirtual #252                // Method evaluate:(Lorg/sonarsource/sonarlint/shaded/org/picocontainer/ComponentAdapter;)Z
     193: ifeq          208
     196: aload         5
     198: aload         11
     200: aload         10
     202: invokeinterface #256,  3          // InterfaceMethod java/util/Map.put:(Ljava/lang/Object;Ljava/lang/Object;)Ljava/lang/Object;
     207: pop
     208: goto          123
     211: aload         5
     213: areturn

  private java.lang.Class getCollectionType(java.lang.Class);
    Code:
       0: aload_1
       1: invokevirtual #268                // Method java/lang/Class.isArray:()Z
       4: ifne          25
       7: ldc           #18                 // class java/util/Map
       9: aload_1
      10: invokevirtual #250                // Method java/lang/Class.isAssignableFrom:(Ljava/lang/Class;)Z
      13: ifne          25
      16: ldc           #155                // class java/util/Collection
      18: aload_1
      19: invokevirtual #250                // Method java/lang/Class.isAssignableFrom:(Ljava/lang/Class;)Z
      22: ifeq          27
      25: aload_1
      26: areturn
      27: aconst_null
      28: areturn

  private java.lang.Class getValueType(java.lang.reflect.Type);
    Code:
       0: aload_1
       1: instanceof    #94                 // class java/lang/Class
       4: ifeq          16
       7: aload_0
       8: aload_1
       9: checkcast     #94                 // class java/lang/Class
      12: invokespecial #270                // Method getValueType:(Ljava/lang/Class;)Ljava/lang/Class;
      15: areturn
      16: aload_1
      17: instanceof    #99                 // class java/lang/reflect/ParameterizedType
      20: ifeq          32
      23: aload_0
      24: aload_1
      25: checkcast     #99                 // class java/lang/reflect/ParameterizedType
      28: invokespecial #273                // Method getValueType:(Ljava/lang/reflect/ParameterizedType;)Ljava/lang/Class;
      31: areturn
      32: aload_1
      33: instanceof    #105                // class java/lang/reflect/GenericArrayType
      36: ifeq          55
      39: aload_1
      40: checkcast     #105                // class java/lang/reflect/GenericArrayType
      43: astore_2
      44: aload_0
      45: aload_2
      46: invokeinterface #108,  1          // InterfaceMethod java/lang/reflect/GenericArrayType.getGenericComponentType:()Ljava/lang/reflect/Type;
      51: invokespecial #111                // Method getGenericArrayBaseType:(Ljava/lang/reflect/Type;)Ljava/lang/Class;
      54: areturn
      55: new           #123                // class java/lang/IllegalArgumentException
      58: dup
      59: new           #125                // class java/lang/StringBuilder
      62: dup
      63: invokespecial #126                // Method java/lang/StringBuilder."<init>":()V
      66: ldc_w         #275                // String Unable to determine collection type from
      69: invokevirtual #132                // Method java/lang/StringBuilder.append:(Ljava/lang/String;)Ljava/lang/StringBuilder;
      72: aload_1
      73: invokevirtual #135                // Method java/lang/StringBuilder.append:(Ljava/lang/Object;)Ljava/lang/StringBuilder;
      76: invokevirtual #139                // Method java/lang/StringBuilder.toString:()Ljava/lang/String;
      79: invokespecial #142                // Method java/lang/IllegalArgumentException."<init>":(Ljava/lang/String;)V
      82: athrow

  private java.lang.Class getValueType(java.lang.Class);
    Code:
       0: aload_0
       1: getfield      #57                 // Field componentValueType:Ljava/lang/Class;
       4: astore_2
       5: aload_1
       6: invokevirtual #268                // Method java/lang/Class.isArray:()Z
       9: ifeq          17
      12: aload_1
      13: invokevirtual #279                // Method java/lang/Class.getComponentType:()Ljava/lang/Class;
      16: astore_2
      17: aload_2
      18: areturn

  private java.lang.Class getValueType(java.lang.reflect.ParameterizedType);
    Code:
       0: aload_0
       1: getfield      #57                 // Field componentValueType:Ljava/lang/Class;
       4: astore_2
       5: ldc           #155                // class java/util/Collection
       7: aload_1
       8: invokeinterface #103,  1          // InterfaceMethod java/lang/reflect/ParameterizedType.getRawType:()Ljava/lang/reflect/Type;
      13: checkcast     #94                 // class java/lang/Class
      16: invokevirtual #250                // Method java/lang/Class.isAssignableFrom:(Ljava/lang/Class;)Z
      19: ifeq          56
      22: aload_1
      23: invokeinterface #283,  1          // InterfaceMethod java/lang/reflect/ParameterizedType.getActualTypeArguments:()[Ljava/lang/reflect/Type;
      28: iconst_0
      29: aaload
      30: astore_3
      31: aload_3
      32: instanceof    #94                 // class java/lang/Class
      35: ifeq          56
      38: aload_3
      39: checkcast     #94                 // class java/lang/Class
      42: aload_2
      43: invokevirtual #250                // Method java/lang/Class.isAssignableFrom:(Ljava/lang/Class;)Z
      46: ifeq          51
      49: aload_2
      50: areturn
      51: aload_3
      52: checkcast     #94                 // class java/lang/Class
      55: astore_2
      56: aload_2
      57: areturn

  private java.lang.Object[] getArrayInstance(org.sonarsource.sonarlint.shaded.org.picocontainer.PicoContainer, java.lang.Class, java.util.Map<java.lang.Object, org.sonarsource.sonarlint.shaded.org.picocontainer.ComponentAdapter<?>>);
    Code:
       0: aload_2
       1: invokevirtual #279                // Method java/lang/Class.getComponentType:()Ljava/lang/Class;
       4: aload_3
       5: invokeinterface #290,  1          // InterfaceMethod java/util/Map.size:()I
      10: invokestatic  #117                // Method java/lang/reflect/Array.newInstance:(Ljava/lang/Class;I)Ljava/lang/Object;
      13: checkcast     #292                // class "[Ljava/lang/Object;"
      16: checkcast     #292                // class "[Ljava/lang/Object;"
      19: astore        4
      21: iconst_0
      22: istore        5
      24: aload_3
      25: invokeinterface #153,  1          // InterfaceMethod java/util/Map.values:()Ljava/util/Collection;
      30: invokeinterface #173,  1          // InterfaceMethod java/util/Collection.iterator:()Ljava/util/Iterator;
      35: astore        6
      37: aload         6
      39: invokeinterface #178,  1          // InterfaceMethod java/util/Iterator.hasNext:()Z
      44: ifeq          83
      47: aload         6
      49: invokeinterface #182,  1          // InterfaceMethod java/util/Iterator.next:()Ljava/lang/Object;
      54: checkcast     #184                // class org/sonarsource/sonarlint/shaded/org/picocontainer/ComponentAdapter
      57: astore        7
      59: aload         4
      61: iload         5
      63: aload_1
      64: aload         7
      66: invokeinterface #229,  1          // InterfaceMethod org/sonarsource/sonarlint/shaded/org/picocontainer/ComponentAdapter.getComponentKey:()Ljava/lang/Object;
      71: invokeinterface #295,  2          // InterfaceMethod org/sonarsource/sonarlint/shaded/org/picocontainer/PicoContainer.getComponent:(Ljava/lang/Object;)Ljava/lang/Object;
      76: aastore
      77: iinc          5, 1
      80: goto          37
      83: aload         4
      85: areturn

  private java.util.Collection getCollectionInstance(org.sonarsource.sonarlint.shaded.org.picocontainer.PicoContainer, java.lang.Class<? extends java.util.Collection>, java.util.Map<java.lang.Object, org.sonarsource.sonarlint.shaded.org.picocontainer.ComponentAdapter<?>>, org.sonarsource.sonarlint.shaded.org.picocontainer.NameBinding, boolean);
    Code:
       0: aload_2
       1: astore        6
       3: aload         6
       5: invokevirtual #308                // Method java/lang/Class.isInterface:()Z
       8: ifeq          82
      11: ldc           #235                // class java/util/List
      13: aload         6
      15: invokevirtual #250                // Method java/lang/Class.isAssignableFrom:(Ljava/lang/Class;)Z
      18: ifeq          29
      21: ldc_w         #310                // class java/util/ArrayList
      24: astore        6
      26: goto          82
      29: ldc_w         #312                // class java/util/SortedSet
      32: aload         6
      34: invokevirtual #250                // Method java/lang/Class.isAssignableFrom:(Ljava/lang/Class;)Z
      37: ifeq          48
      40: ldc_w         #314                // class java/util/TreeSet
      43: astore        6
      45: goto          82
      48: ldc_w         #316                // class java/util/Set
      51: aload         6
      53: invokevirtual #250                // Method java/lang/Class.isAssignableFrom:(Ljava/lang/Class;)Z
      56: ifeq          67
      59: ldc_w         #318                // class java/util/HashSet
      62: astore        6
      64: goto          82
      67: ldc           #155                // class java/util/Collection
      69: aload         6
      71: invokevirtual #250                // Method java/lang/Class.isAssignableFrom:(Ljava/lang/Class;)Z
      74: ifeq          82
      77: ldc_w         #310                // class java/util/ArrayList
      80: astore        6
      82: aload         6
      84: invokevirtual #320                // Method java/lang/Class.newInstance:()Ljava/lang/Object;
      87: checkcast     #155                // class java/util/Collection
      90: astore        7
      92: aload_3
      93: invokeinterface #153,  1          // InterfaceMethod java/util/Map.values:()Ljava/util/Collection;
      98: invokeinterface #173,  1          // InterfaceMethod java/util/Collection.iterator:()Ljava/util/Iterator;
     103: astore        8
     105: aload         8
     107: invokeinterface #178,  1          // InterfaceMethod java/util/Iterator.hasNext:()Z
     112: ifeq          168
     115: aload         8
     117: invokeinterface #182,  1          // InterfaceMethod java/util/Iterator.next:()Ljava/lang/Object;
     122: checkcast     #184                // class org/sonarsource/sonarlint/shaded/org/picocontainer/ComponentAdapter
     125: astore        9
     127: iload         5
     129: ifeq          144
     132: aload         9
     134: invokeinterface #229,  1          // InterfaceMethod org/sonarsource/sonarlint/shaded/org/picocontainer/ComponentAdapter.getComponentKey:()Ljava/lang/Object;
     139: aload         4
     141: if_acmpne     165
     144: aload         7
     146: aload_1
     147: aload         9
     149: invokeinterface #229,  1          // InterfaceMethod org/sonarsource/sonarlint/shaded/org/picocontainer/ComponentAdapter.getComponentKey:()Ljava/lang/Object;
     154: invokeinterface #295,  2          // InterfaceMethod org/sonarsource/sonarlint/shaded/org/picocontainer/PicoContainer.getComponent:(Ljava/lang/Object;)Ljava/lang/Object;
     159: invokeinterface #323,  2          // InterfaceMethod java/util/Collection.add:(Ljava/lang/Object;)Z
     164: pop
     165: goto          105
     168: aload         7
     170: areturn
     171: astore        7
     173: new           #161                // class org/sonarsource/sonarlint/shaded/org/picocontainer/PicoCompositionException
     176: dup
     177: aload         7
     179: invokespecial #326                // Method org/sonarsource/sonarlint/shaded/org/picocontainer/PicoCompositionException."<init>":(Ljava/lang/Throwable;)V
     182: athrow
     183: astore        7
     185: new           #161                // class org/sonarsource/sonarlint/shaded/org/picocontainer/PicoCompositionException
     188: dup
     189: aload         7
     191: invokespecial #326                // Method org/sonarsource/sonarlint/shaded/org/picocontainer/PicoCompositionException."<init>":(Ljava/lang/Throwable;)V
     194: athrow
    Exception table:
       from    to  target type
          82   170   171   Class java/lang/InstantiationException
          82   170   183   Class java/lang/IllegalAccessException

  private java.util.Map getMapInstance(org.sonarsource.sonarlint.shaded.org.picocontainer.PicoContainer, java.lang.Class<? extends java.util.Map>, java.util.Map<java.lang.Object, org.sonarsource.sonarlint.shaded.org.picocontainer.ComponentAdapter<?>>);
    Code:
       0: aload_2
       1: astore        4
       3: aload         4
       5: invokevirtual #308                // Method java/lang/Class.isInterface:()Z
       8: ifeq          45
      11: ldc_w         #335                // class java/util/SortedMap
      14: aload         4
      16: invokevirtual #250                // Method java/lang/Class.isAssignableFrom:(Ljava/lang/Class;)Z
      19: ifeq          30
      22: ldc_w         #337                // class java/util/TreeMap
      25: astore        4
      27: goto          45
      30: ldc           #18                 // class java/util/Map
      32: aload         4
      34: invokevirtual #250                // Method java/lang/Class.isAssignableFrom:(Ljava/lang/Class;)Z
      37: ifeq          45
      40: ldc_w         #339                // class java/util/HashMap
      43: astore        4
      45: aload         4
      47: invokevirtual #320                // Method java/lang/Class.newInstance:()Ljava/lang/Object;
      50: checkcast     #18                 // class java/util/Map
      53: astore        5
      55: aload_3
      56: invokeinterface #343,  1          // InterfaceMethod java/util/Map.entrySet:()Ljava/util/Set;
      61: invokeinterface #344,  1          // InterfaceMethod java/util/Set.iterator:()Ljava/util/Iterator;
      66: astore        6
      68: aload         6
      70: invokeinterface #178,  1          // InterfaceMethod java/util/Iterator.hasNext:()Z
      75: ifeq          120
      78: aload         6
      80: invokeinterface #182,  1          // InterfaceMethod java/util/Iterator.next:()Ljava/lang/Object;
      85: checkcast     #16                 // class java/util/Map$Entry
      88: astore        7
      90: aload         7
      92: invokeinterface #347,  1          // InterfaceMethod java/util/Map$Entry.getKey:()Ljava/lang/Object;
      97: astore        8
      99: aload         5
     101: aload         8
     103: aload_1
     104: aload         8
     106: invokeinterface #295,  2          // InterfaceMethod org/sonarsource/sonarlint/shaded/org/picocontainer/PicoContainer.getComponent:(Ljava/lang/Object;)Ljava/lang/Object;
     111: invokeinterface #256,  3          // InterfaceMethod java/util/Map.put:(Ljava/lang/Object;Ljava/lang/Object;)Ljava/lang/Object;
     116: pop
     117: goto          68
     120: aload         5
     122: areturn
     123: astore        5
     125: new           #161                // class org/sonarsource/sonarlint/shaded/org/picocontainer/PicoCompositionException
     128: dup
     129: aload         5
     131: invokespecial #326                // Method org/sonarsource/sonarlint/shaded/org/picocontainer/PicoCompositionException."<init>":(Ljava/lang/Throwable;)V
     134: athrow
     135: astore        5
     137: new           #161                // class org/sonarsource/sonarlint/shaded/org/picocontainer/PicoCompositionException
     140: dup
     141: aload         5
     143: invokespecial #326                // Method org/sonarsource/sonarlint/shaded/org/picocontainer/PicoCompositionException."<init>":(Ljava/lang/Throwable;)V
     146: athrow
    Exception table:
       from    to  target type
          45   122   123   Class java/lang/InstantiationException
          45   122   135   Class java/lang/IllegalAccessException

  static boolean access$000(org.sonarsource.sonarlint.shaded.org.picocontainer.parameters.CollectionComponentParameter);
    Code:
       0: aload_0
       1: getfield      #53                 // Field emptyCollection:Z
       4: ireturn

  static java.lang.Object[] access$100(org.sonarsource.sonarlint.shaded.org.picocontainer.parameters.CollectionComponentParameter, org.sonarsource.sonarlint.shaded.org.picocontainer.PicoContainer, java.lang.Class, java.util.Map);
    Code:
       0: aload_0
       1: aload_1
       2: aload_2
       3: aload_3
       4: invokespecial #358                // Method getArrayInstance:(Lorg/sonarsource/sonarlint/shaded/org/picocontainer/PicoContainer;Ljava/lang/Class;Ljava/util/Map;)[Ljava/lang/Object;
       7: areturn

  static java.util.Map access$200(org.sonarsource.sonarlint.shaded.org.picocontainer.parameters.CollectionComponentParameter, org.sonarsource.sonarlint.shaded.org.picocontainer.PicoContainer, java.lang.Class, java.util.Map);
    Code:
       0: aload_0
       1: aload_1
       2: aload_2
       3: aload_3
       4: invokespecial #365                // Method getMapInstance:(Lorg/sonarsource/sonarlint/shaded/org/picocontainer/PicoContainer;Ljava/lang/Class;Ljava/util/Map;)Ljava/util/Map;
       7: areturn

  static java.util.Collection access$300(org.sonarsource.sonarlint.shaded.org.picocontainer.parameters.CollectionComponentParameter, org.sonarsource.sonarlint.shaded.org.picocontainer.PicoContainer, java.lang.Class, java.util.Map, org.sonarsource.sonarlint.shaded.org.picocontainer.NameBinding, boolean);
    Code:
       0: aload_0
       1: aload_1
       2: aload_2
       3: aload_3
       4: aload         4
       6: iload         5
       8: invokespecial #369                // Method getCollectionInstance:(Lorg/sonarsource/sonarlint/shaded/org/picocontainer/PicoContainer;Ljava/lang/Class;Ljava/util/Map;Lorg/sonarsource/sonarlint/shaded/org/picocontainer/NameBinding;Z)Ljava/util/Collection;
      11: areturn

  static {};
    Code:
       0: new           #2                  // class org/sonarsource/sonarlint/shaded/org/picocontainer/parameters/CollectionComponentParameter
       3: dup
       4: invokespecial #373                // Method "<init>":()V
       7: putstatic     #375                // Field ARRAY:Lorg/sonarsource/sonarlint/shaded/org/picocontainer/parameters/CollectionComponentParameter;
      10: new           #2                  // class org/sonarsource/sonarlint/shaded/org/picocontainer/parameters/CollectionComponentParameter
      13: dup
      14: iconst_1
      15: invokespecial #35                 // Method "<init>":(Z)V
      18: putstatic     #377                // Field ARRAY_ALLOW_EMPTY:Lorg/sonarsource/sonarlint/shaded/org/picocontainer/parameters/CollectionComponentParameter;
      21: return
}
