Compiled from "JavaTypeEnhancementState.kt"
final class kotlin.reflect.jvm.internal.impl.load.java.JavaTypeEnhancementState$Companion$DEFAULT$1 extends kotlin.jvm.internal.FunctionReference implements kotlin.jvm.functions.Function1<kotlin.reflect.jvm.internal.impl.name.FqName, kotlin.reflect.jvm.internal.impl.load.java.ReportLevel> {
  public static final kotlin.reflect.jvm.internal.impl.load.java.JavaTypeEnhancementState$Companion$DEFAULT$1 INSTANCE;

  kotlin.reflect.jvm.internal.impl.load.java.JavaTypeEnhancementState$Companion$DEFAULT$1();
    Code:
       0: aload_0
       1: iconst_1
       2: invokespecial #14                 // Method kotlin/jvm/internal/FunctionReference."<init>":(I)V
       5: return

  public final kotlin.reflect.jvm.internal.impl.load.java.ReportLevel invoke(kotlin.reflect.jvm.internal.impl.name.FqName);
    Code:
       0: aload_1
       1: ldc           #4                  // String p0
       3: invokestatic  #15                 // Method kotlin/jvm/internal/Intrinsics.checkNotNullParameter:(Ljava/lang/Object;Ljava/lang/String;)V
       6: aload_1
       7: invokestatic  #17                 // Method kotlin/reflect/jvm/internal/impl/load/java/JavaNullabilityAnnotationSettingsKt.getDefaultReportLevelForAnnotation:(Lkotlin/reflect/jvm/internal/impl/name/FqName;)Lkotlin/reflect/jvm/internal/impl/load/java/ReportLevel;
      10: areturn

  public final java.lang.String getSignature();
    Code:
       0: ldc           #3                  // String getDefaultReportLevelForAnnotation(Lorg/jetbrains/kotlin/name/FqName;)Lorg/jetbrains/kotlin/load/java/ReportLevel;
       2: areturn

  public final java.lang.String getName();
    Code:
       0: ldc           #2                  // String getDefaultReportLevelForAnnotation
       2: areturn

  public final kotlin.reflect.KDeclarationContainer getOwner();
    Code:
       0: ldc           #9                  // class kotlin/reflect/jvm/internal/impl/load/java/JavaNullabilityAnnotationSettingsKt
       2: ldc           #1                  // String compiler.common.jvm
       4: invokestatic  #16                 // Method kotlin/jvm/internal/Reflection.getOrCreateKotlinPackage:(Ljava/lang/Class;Ljava/lang/String;)Lkotlin/reflect/KDeclarationContainer;
       7: areturn

  public java.lang.Object invoke(java.lang.Object);
    Code:
       0: aload_0
       1: aload_1
       2: checkcast     #12                 // class kotlin/reflect/jvm/internal/impl/name/FqName
       5: invokevirtual #19                 // Method invoke:(Lkotlin/reflect/jvm/internal/impl/name/FqName;)Lkotlin/reflect/jvm/internal/impl/load/java/ReportLevel;
       8: areturn

  static {};
    Code:
       0: new           #11                 // class kotlin/reflect/jvm/internal/impl/load/java/JavaTypeEnhancementState$Companion$DEFAULT$1
       3: dup
       4: invokespecial #18                 // Method "<init>":()V
       7: putstatic     #13                 // Field INSTANCE:Lkotlin/reflect/jvm/internal/impl/load/java/JavaTypeEnhancementState$Companion$DEFAULT$1;
      10: return
}
