Compiled from "Jsr305Settings.kt"
final class kotlin.reflect.jvm.internal.impl.load.java.Jsr305Settings$description$2 extends kotlin.jvm.internal.Lambda implements kotlin.jvm.functions.Function0<java.lang.String[]> {
  final kotlin.reflect.jvm.internal.impl.load.java.Jsr305Settings this$0;

  kotlin.reflect.jvm.internal.impl.load.java.Jsr305Settings$description$2(kotlin.reflect.jvm.internal.impl.load.java.Jsr305Settings);
    Code:
       0: aload_0
       1: aload_1
       2: putfield      #17                 // Field this$0:Lkotlin/reflect/jvm/internal/impl/load/java/Jsr305Settings;
       5: aload_0
       6: iconst_0
       7: invokespecial #25                 // Method kotlin/jvm/internal/Lambda."<init>":(I)V
      10: return

  public final java.lang.String[] invoke();
    Code:
       0: aload_0
       1: getfield      #17                 // Field this$0:Lkotlin/reflect/jvm/internal/impl/load/java/Jsr305Settings;
       4: astore_1
       5: invokestatic  #24                 // Method kotlin/collections/CollectionsKt.createListBuilder:()Ljava/util/List;
       8: astore_2
       9: aload_2
      10: astore_3
      11: iconst_0
      12: istore        4
      14: aload_3
      15: aload_1
      16: invokevirtual #26                 // Method kotlin/reflect/jvm/internal/impl/load/java/Jsr305Settings.getGlobalLevel:()Lkotlin/reflect/jvm/internal/impl/load/java/ReportLevel;
      19: invokevirtual #30                 // Method kotlin/reflect/jvm/internal/impl/load/java/ReportLevel.getDescription:()Ljava/lang/String;
      22: invokeinterface #34,  2           // InterfaceMethod java/util/List.add:(Ljava/lang/Object;)Z
      27: pop
      28: aload_1
      29: invokevirtual #27                 // Method kotlin/reflect/jvm/internal/impl/load/java/Jsr305Settings.getMigrationLevel:()Lkotlin/reflect/jvm/internal/impl/load/java/ReportLevel;
      32: dup
      33: ifnull        74
      36: astore        5
      38: iconst_0
      39: istore        6
      41: aload_3
      42: new           #4                  // class java/lang/StringBuilder
      45: dup
      46: invokespecial #18                 // Method java/lang/StringBuilder."<init>":()V
      49: ldc           #1                  // String under-migration:
      51: invokevirtual #21                 // Method java/lang/StringBuilder.append:(Ljava/lang/String;)Ljava/lang/StringBuilder;
      54: aload         5
      56: invokevirtual #30                 // Method kotlin/reflect/jvm/internal/impl/load/java/ReportLevel.getDescription:()Ljava/lang/String;
      59: invokevirtual #21                 // Method java/lang/StringBuilder.append:(Ljava/lang/String;)Ljava/lang/StringBuilder;
      62: invokevirtual #22                 // Method java/lang/StringBuilder.toString:()Ljava/lang/String;
      65: invokeinterface #34,  2           // InterfaceMethod java/util/List.add:(Ljava/lang/Object;)Z
      70: pop
      71: goto          76
      74: pop
      75: nop
      76: aload_1
      77: invokevirtual #28                 // Method kotlin/reflect/jvm/internal/impl/load/java/Jsr305Settings.getUserDefinedLevelForSpecificAnnotation:()Ljava/util/Map;
      80: astore        7
      82: iconst_0
      83: istore        8
      85: aload         7
      87: invokeinterface #35,  1           // InterfaceMethod java/util/Map.entrySet:()Ljava/util/Set;
      92: invokeinterface #38,  1           // InterfaceMethod java/util/Set.iterator:()Ljava/util/Iterator;
      97: astore        5
      99: aload         5
     101: invokeinterface #32,  1           // InterfaceMethod java/util/Iterator.hasNext:()Z
     106: ifeq          185
     109: aload         5
     111: invokeinterface #33,  1           // InterfaceMethod java/util/Iterator.next:()Ljava/lang/Object;
     116: checkcast     #9                  // class java/util/Map$Entry
     119: astore        6
     121: aload         6
     123: astore        9
     125: iconst_0
     126: istore        10
     128: aload_3
     129: new           #4                  // class java/lang/StringBuilder
     132: dup
     133: invokespecial #18                 // Method java/lang/StringBuilder."<init>":()V
     136: bipush        64
     138: invokevirtual #19                 // Method java/lang/StringBuilder.append:(C)Ljava/lang/StringBuilder;
     141: aload         9
     143: invokeinterface #36,  1           // InterfaceMethod java/util/Map$Entry.getKey:()Ljava/lang/Object;
     148: invokevirtual #20                 // Method java/lang/StringBuilder.append:(Ljava/lang/Object;)Ljava/lang/StringBuilder;
     151: bipush        58
     153: invokevirtual #19                 // Method java/lang/StringBuilder.append:(C)Ljava/lang/StringBuilder;
     156: aload         9
     158: invokeinterface #37,  1           // InterfaceMethod java/util/Map$Entry.getValue:()Ljava/lang/Object;
     163: checkcast     #16                 // class kotlin/reflect/jvm/internal/impl/load/java/ReportLevel
     166: invokevirtual #30                 // Method kotlin/reflect/jvm/internal/impl/load/java/ReportLevel.getDescription:()Ljava/lang/String;
     169: invokevirtual #21                 // Method java/lang/StringBuilder.append:(Ljava/lang/String;)Ljava/lang/StringBuilder;
     172: invokevirtual #22                 // Method java/lang/StringBuilder.toString:()Ljava/lang/String;
     175: invokeinterface #34,  2           // InterfaceMethod java/util/List.add:(Ljava/lang/Object;)Z
     180: pop
     181: nop
     182: goto          99
     185: nop
     186: nop
     187: aload_2
     188: invokestatic  #23                 // Method kotlin/collections/CollectionsKt.build:(Ljava/util/List;)Ljava/util/List;
     191: checkcast     #5                  // class java/util/Collection
     194: astore_1
     195: nop
     196: iconst_0
     197: istore_2
     198: aload_1
     199: astore_3
     200: aload_3
     201: iconst_0
     202: anewarray     #3                  // class java/lang/String
     205: invokeinterface #31,  2           // InterfaceMethod java/util/Collection.toArray:([Ljava/lang/Object;)[Ljava/lang/Object;
     210: checkcast     #2                  // class "[Ljava/lang/String;"
     213: areturn

  public java.lang.Object invoke();
    Code:
       0: aload_0
       1: invokevirtual #29                 // Method invoke:()[Ljava/lang/String;
       4: areturn
}
