Compiled from "AbstractClassGenerator.java"
class org.mockito.cglib.core.AbstractClassGenerator$1 implements org.mockito.cglib.core.Predicate {
  final java.util.Set val$nameCache;

  final org.mockito.cglib.core.AbstractClassGenerator this$0;

  org.mockito.cglib.core.AbstractClassGenerator$1(org.mockito.cglib.core.AbstractClassGenerator, java.util.Set);
    Code:
       0: aload_0
       1: aload_1
       2: putfield      #1                  // Field this$0:Lorg/mockito/cglib/core/AbstractClassGenerator;
       5: aload_0
       6: aload_2
       7: putfield      #2                  // Field val$nameCache:Ljava/util/Set;
      10: aload_0
      11: invokespecial #3                  // Method java/lang/Object."<init>":()V
      14: return

  public boolean evaluate(java.lang.Object);
    Code:
       0: aload_0
       1: getfield      #2                  // Field val$nameCache:Ljava/util/Set;
       4: aload_1
       5: invokeinterface #4,  2            // InterfaceMethod java/util/Set.contains:(Ljava/lang/Object;)Z
      10: ireturn
}
