Compiled from "DuplicatesPredicate.java"
public class org.mockito.cglib.core.DuplicatesPredicate implements org.mockito.cglib.core.Predicate {
  private java.util.Set unique;

  public org.mockito.cglib.core.DuplicatesPredicate();
    Code:
       0: aload_0
       1: invokespecial #1                  // Method java/lang/Object."<init>":()V
       4: aload_0
       5: new           #2                  // class java/util/HashSet
       8: dup
       9: invokespecial #3                  // Method java/util/HashSet."<init>":()V
      12: putfield      #4                  // Field unique:Ljava/util/Set;
      15: return

  public boolean evaluate(java.lang.Object);
    Code:
       0: aload_0
       1: getfield      #4                  // Field unique:Ljava/util/Set;
       4: aload_1
       5: checkcast     #5                  // class java/lang/reflect/Method
       8: invokestatic  #6                  // Method org/mockito/cglib/core/MethodWrapper.create:(Ljava/lang/reflect/Method;)Ljava/lang/Object;
      11: invokeinterface #7,  2            // InterfaceMethod java/util/Set.add:(Ljava/lang/Object;)Z
      16: ireturn
}
