Compiled from "WSDependenciesProcessor.java"
public final class org.jboss.as.webservices.deployers.WSDependenciesProcessor implements org.jboss.as.server.deployment.DeploymentUnitProcessor {
  public static final org.jboss.modules.ModuleIdentifier JBOSSWS_API;

  public static final org.jboss.modules.ModuleIdentifier JBOSSWS_SPI;

  public static final org.jboss.modules.ModuleIdentifier[] JAVAEE_APIS;

  private final boolean addJBossWSDependencies;

  public org.jboss.as.webservices.deployers.WSDependenciesProcessor(boolean);
    Code:
       0: aload_0
       1: invokespecial #1                  // Method java/lang/Object."<init>":()V
       4: aload_0
       5: iload_1
       6: putfield      #2                  // Field addJBossWSDependencies:Z
       9: return

  public void deploy(org.jboss.as.server.deployment.DeploymentPhaseContext) throws org.jboss.as.server.deployment.DeploymentUnitProcessingException;
    Code:
       0: aload_1
       1: invokeinterface #3,  1            // InterfaceMethod org/jboss/as/server/deployment/DeploymentPhaseContext.getDeploymentUnit:()Lorg/jboss/as/server/deployment/DeploymentUnit;
       6: astore_2
       7: invokestatic  #4                  // Method org/jboss/modules/Module.getBootModuleLoader:()Lorg/jboss/modules/ModuleLoader;
      10: astore_3
      11: aload_2
      12: getstatic     #5                  // Field org/jboss/as/server/deployment/Attachments.MODULE_SPECIFICATION:Lorg/jboss/as/server/deployment/AttachmentKey;
      15: invokeinterface #6,  2            // InterfaceMethod org/jboss/as/server/deployment/DeploymentUnit.getAttachment:(Lorg/jboss/as/server/deployment/AttachmentKey;)Ljava/lang/Object;
      20: checkcast     #7                  // class org/jboss/as/server/deployment/module/ModuleSpecification
      23: astore        4
      25: aload_0
      26: getfield      #2                  // Field addJBossWSDependencies:Z
      29: ifeq          72
      32: aload         4
      34: new           #8                  // class org/jboss/as/server/deployment/module/ModuleDependency
      37: dup
      38: aload_3
      39: getstatic     #9                  // Field JBOSSWS_API:Lorg/jboss/modules/ModuleIdentifier;
      42: iconst_0
      43: iconst_1
      44: iconst_1
      45: iconst_0
      46: invokespecial #10                 // Method org/jboss/as/server/deployment/module/ModuleDependency."<init>":(Lorg/jboss/modules/ModuleLoader;Lorg/jboss/modules/ModuleIdentifier;ZZZZ)V
      49: invokevirtual #11                 // Method org/jboss/as/server/deployment/module/ModuleSpecification.addSystemDependency:(Lorg/jboss/as/server/deployment/module/ModuleDependency;)V
      52: aload         4
      54: new           #8                  // class org/jboss/as/server/deployment/module/ModuleDependency
      57: dup
      58: aload_3
      59: getstatic     #12                 // Field JBOSSWS_SPI:Lorg/jboss/modules/ModuleIdentifier;
      62: iconst_0
      63: iconst_1
      64: iconst_1
      65: iconst_0
      66: invokespecial #10                 // Method org/jboss/as/server/deployment/module/ModuleDependency."<init>":(Lorg/jboss/modules/ModuleLoader;Lorg/jboss/modules/ModuleIdentifier;ZZZZ)V
      69: invokevirtual #11                 // Method org/jboss/as/server/deployment/module/ModuleSpecification.addSystemDependency:(Lorg/jboss/as/server/deployment/module/ModuleDependency;)V
      72: getstatic     #13                 // Field JAVAEE_APIS:[Lorg/jboss/modules/ModuleIdentifier;
      75: astore        5
      77: aload         5
      79: arraylength
      80: istore        6
      82: iconst_0
      83: istore        7
      85: iload         7
      87: iload         6
      89: if_icmpge     124
      92: aload         5
      94: iload         7
      96: aaload
      97: astore        8
      99: aload         4
     101: new           #8                  // class org/jboss/as/server/deployment/module/ModuleDependency
     104: dup
     105: aload_3
     106: aload         8
     108: iconst_0
     109: iconst_0
     110: iconst_1
     111: iconst_0
     112: invokespecial #10                 // Method org/jboss/as/server/deployment/module/ModuleDependency."<init>":(Lorg/jboss/modules/ModuleLoader;Lorg/jboss/modules/ModuleIdentifier;ZZZZ)V
     115: invokevirtual #11                 // Method org/jboss/as/server/deployment/module/ModuleSpecification.addSystemDependency:(Lorg/jboss/as/server/deployment/module/ModuleDependency;)V
     118: iinc          7, 1
     121: goto          85
     124: return

  public void undeploy(org.jboss.as.server.deployment.DeploymentUnit);
    Code:
       0: return

  static {};
    Code:
       0: ldc           #14                 // String org.jboss.ws.api
       2: invokestatic  #15                 // Method org/jboss/modules/ModuleIdentifier.create:(Ljava/lang/String;)Lorg/jboss/modules/ModuleIdentifier;
       5: putstatic     #9                  // Field JBOSSWS_API:Lorg/jboss/modules/ModuleIdentifier;
       8: ldc           #16                 // String org.jboss.ws.spi
      10: invokestatic  #15                 // Method org/jboss/modules/ModuleIdentifier.create:(Ljava/lang/String;)Lorg/jboss/modules/ModuleIdentifier;
      13: putstatic     #12                 // Field JBOSSWS_SPI:Lorg/jboss/modules/ModuleIdentifier;
      16: iconst_3
      17: anewarray     #17                 // class org/jboss/modules/ModuleIdentifier
      20: dup
      21: iconst_0
      22: ldc           #18                 // String javax.jws.api
      24: invokestatic  #15                 // Method org/jboss/modules/ModuleIdentifier.create:(Ljava/lang/String;)Lorg/jboss/modules/ModuleIdentifier;
      27: aastore
      28: dup
      29: iconst_1
      30: ldc           #19                 // String javax.xml.soap.api
      32: invokestatic  #15                 // Method org/jboss/modules/ModuleIdentifier.create:(Ljava/lang/String;)Lorg/jboss/modules/ModuleIdentifier;
      35: aastore
      36: dup
      37: iconst_2
      38: ldc           #20                 // String javax.xml.ws.api
      40: invokestatic  #15                 // Method org/jboss/modules/ModuleIdentifier.create:(Ljava/lang/String;)Lorg/jboss/modules/ModuleIdentifier;
      43: aastore
      44: putstatic     #13                 // Field JAVAEE_APIS:[Lorg/jboss/modules/ModuleIdentifier;
      47: return
}
