Compiled from "WSIntegrationProcessorJAXWS_POJO.java"
public class org.jboss.as.webservices.deployers.WSIntegrationProcessorJAXWS_POJO extends org.jboss.as.webservices.deployers.AbstractIntegrationProcessorJAXWS {
  public org.jboss.as.webservices.deployers.WSIntegrationProcessorJAXWS_POJO();
    Code:
       0: aload_0
       1: invokespecial #1                  // Method org/jboss/as/webservices/deployers/AbstractIntegrationProcessorJAXWS."<init>":()V
       4: return

  protected void processAnnotation(org.jboss.as.server.deployment.DeploymentUnit, org.jboss.as.ee.component.EEModuleDescription) throws org.jboss.as.server.deployment.DeploymentUnitProcessingException;
    Code:
       0: getstatic     #2                  // Field org/jboss/as/ee/structure/DeploymentType.WAR:Lorg/jboss/as/ee/structure/DeploymentType;
       3: aload_1
       4: invokestatic  #3                  // Method org/jboss/as/ee/structure/DeploymentTypeMarker.isType:(Lorg/jboss/as/ee/structure/DeploymentType;Lorg/jboss/as/server/deployment/DeploymentUnit;)Z
       7: ifne          11
      10: return
      11: new           #4                  // class java/util/HashMap
      14: dup
      15: invokespecial #5                  // Method java/util/HashMap."<init>":()V
      18: astore_3
      19: aload_1
      20: getstatic     #6                  // Field org/jboss/as/server/deployment/Attachments.COMPOSITE_ANNOTATION_INDEX:Lorg/jboss/as/server/deployment/AttachmentKey;
      23: invokeinterface #7,  2            // InterfaceMethod org/jboss/as/server/deployment/DeploymentUnit.getAttachment:(Lorg/jboss/as/server/deployment/AttachmentKey;)Ljava/lang/Object;
      28: checkcast     #8                  // class org/jboss/as/server/deployment/annotation/CompositeIndex
      31: astore        4
      33: aload_2
      34: invokevirtual #9                  // Method org/jboss/as/ee/component/EEModuleDescription.getClassDescriptions:()Ljava/util/Collection;
      37: invokeinterface #10,  1           // InterfaceMethod java/util/Collection.iterator:()Ljava/util/Iterator;
      42: astore        5
      44: aload         5
      46: invokeinterface #11,  1           // InterfaceMethod java/util/Iterator.hasNext:()Z
      51: ifeq          103
      54: aload         5
      56: invokeinterface #12,  1           // InterfaceMethod java/util/Iterator.next:()Ljava/lang/Object;
      61: checkcast     #13                 // class org/jboss/as/ee/component/EEModuleClassDescription
      64: astore        6
      66: aload         6
      68: aload         4
      70: invokestatic  #14                 // Method org/jboss/as/webservices/util/ASHelper.isJaxwsEndpoint:(Lorg/jboss/as/ee/component/EEModuleClassDescription;Lorg/jboss/as/server/deployment/annotation/CompositeIndex;)Z
      73: ifeq          100
      76: aload_0
      77: aload_1
      78: aload         6
      80: invokespecial #15                 // Method exclude:(Lorg/jboss/as/server/deployment/DeploymentUnit;Lorg/jboss/as/ee/component/EEModuleClassDescription;)Z
      83: ifne          100
      86: aload_3
      87: aload         6
      89: invokevirtual #16                 // Method org/jboss/as/ee/component/EEModuleClassDescription.getClassName:()Ljava/lang/String;
      92: aload         6
      94: invokeinterface #17,  3           // InterfaceMethod java/util/Map.put:(Ljava/lang/Object;Ljava/lang/Object;)Ljava/lang/Object;
      99: pop
     100: goto          44
     103: aload_1
     104: invokestatic  #18                 // Method org/jboss/as/webservices/util/ASHelper.getJBossWebMetaData:(Lorg/jboss/as/server/deployment/DeploymentUnit;)Lorg/jboss/metadata/web/jboss/JBossWebMetaData;
     107: astore        5
     109: aload_1
     110: invokestatic  #19                 // Method org/jboss/as/webservices/util/ASHelper.getJaxwsDeployment:(Lorg/jboss/as/server/deployment/DeploymentUnit;)Lorg/jboss/as/webservices/metadata/model/JAXWSDeployment;
     113: astore        6
     115: aload         5
     117: ifnull        443
     120: new           #20                 // class java/util/HashSet
     123: dup
     124: invokespecial #21                 // Method java/util/HashSet."<init>":()V
     127: astore        7
     129: aload         5
     131: invokestatic  #22                 // Method org/jboss/as/webservices/util/WebMetaDataHelper.getServlets:(Lorg/jboss/metadata/web/jboss/JBossWebMetaData;)Lorg/jboss/metadata/web/jboss/JBossServletsMetaData;
     134: invokevirtual #23                 // Method org/jboss/metadata/web/jboss/JBossServletsMetaData.iterator:()Ljava/util/Iterator;
     137: astore        8
     139: aload         8
     141: invokeinterface #11,  1           // InterfaceMethod java/util/Iterator.hasNext:()Z
     146: ifeq          443
     149: aload         8
     151: invokeinterface #12,  1           // InterfaceMethod java/util/Iterator.next:()Ljava/lang/Object;
     156: checkcast     #24                 // class org/jboss/metadata/web/spec/ServletMetaData
     159: astore        9
     161: aload         9
     163: invokestatic  #25                 // Method org/jboss/as/webservices/util/ASHelper.getEndpointClassName:(Lorg/jboss/metadata/web/spec/ServletMetaData;)Ljava/lang/String;
     166: astore        10
     168: aload         9
     170: invokestatic  #26                 // Method org/jboss/as/webservices/util/ASHelper.getEndpointName:(Lorg/jboss/metadata/web/spec/ServletMetaData;)Ljava/lang/String;
     173: astore        11
     175: aload_3
     176: aload         10
     178: invokeinterface #27,  2           // InterfaceMethod java/util/Map.containsKey:(Ljava/lang/Object;)Z
     183: ifne          198
     186: aload         7
     188: aload         10
     190: invokeinterface #28,  2           // InterfaceMethod java/util/Set.contains:(Ljava/lang/Object;)Z
     195: ifeq          269
     198: aload_1
     199: aload         11
     201: aload         10
     203: aload         11
     205: invokestatic  #29                 // Method createComponentDescription:(Lorg/jboss/as/server/deployment/DeploymentUnit;Ljava/lang/String;Ljava/lang/String;Ljava/lang/String;)Lorg/jboss/as/ee/component/ComponentDescription;
     208: astore        12
     210: aload         12
     212: aload         10
     214: invokestatic  #30                 // Method registerView:(Lorg/jboss/as/ee/component/ComponentDescription;Ljava/lang/String;)Lorg/jboss/msc/service/ServiceName;
     217: astore        13
     219: aload         11
     221: aload_1
     222: invokestatic  #31                 // Method getUrlPattern:(Ljava/lang/String;Lorg/jboss/as/server/deployment/DeploymentUnit;)Ljava/lang/String;
     225: astore        14
     227: aload         6
     229: new           #32                 // class org/jboss/as/webservices/metadata/model/POJOEndpoint
     232: dup
     233: aload         11
     235: aload         10
     237: aload         13
     239: aload         14
     241: invokespecial #33                 // Method org/jboss/as/webservices/metadata/model/POJOEndpoint."<init>":(Ljava/lang/String;Ljava/lang/String;Lorg/jboss/msc/service/ServiceName;Ljava/lang/String;)V
     244: invokevirtual #34                 // Method org/jboss/as/webservices/metadata/model/JAXWSDeployment.addEndpoint:(Lorg/jboss/as/webservices/metadata/model/POJOEndpoint;)V
     247: aload_3
     248: aload         10
     250: invokeinterface #35,  2           // InterfaceMethod java/util/Map.remove:(Ljava/lang/Object;)Ljava/lang/Object;
     255: pop
     256: aload         7
     258: aload         10
     260: invokeinterface #36,  2           // InterfaceMethod java/util/Set.add:(Ljava/lang/Object;)Z
     265: pop
     266: goto          440
     269: aload_1
     270: invokeinterface #37,  1           // InterfaceMethod org/jboss/as/server/deployment/DeploymentUnit.getParent:()Lorg/jboss/as/server/deployment/DeploymentUnit;
     275: ifnull        440
     278: getstatic     #38                 // Field org/jboss/as/ee/structure/DeploymentType.EAR:Lorg/jboss/as/ee/structure/DeploymentType;
     281: aload_1
     282: invokeinterface #37,  1           // InterfaceMethod org/jboss/as/server/deployment/DeploymentUnit.getParent:()Lorg/jboss/as/server/deployment/DeploymentUnit;
     287: invokestatic  #3                  // Method org/jboss/as/ee/structure/DeploymentTypeMarker.isType:(Lorg/jboss/as/ee/structure/DeploymentType;Lorg/jboss/as/server/deployment/DeploymentUnit;)Z
     290: ifeq          440
     293: aload_1
     294: invokeinterface #37,  1           // InterfaceMethod org/jboss/as/server/deployment/DeploymentUnit.getParent:()Lorg/jboss/as/server/deployment/DeploymentUnit;
     299: getstatic     #39                 // Field org/jboss/as/ee/component/Attachments.EE_MODULE_DESCRIPTION:Lorg/jboss/as/server/deployment/AttachmentKey;
     302: invokeinterface #7,  2            // InterfaceMethod org/jboss/as/server/deployment/DeploymentUnit.getAttachment:(Lorg/jboss/as/server/deployment/AttachmentKey;)Ljava/lang/Object;
     307: checkcast     #40                 // class org/jboss/as/ee/component/EEModuleDescription
     310: astore        12
     312: aload_1
     313: invokeinterface #37,  1           // InterfaceMethod org/jboss/as/server/deployment/DeploymentUnit.getParent:()Lorg/jboss/as/server/deployment/DeploymentUnit;
     318: getstatic     #6                  // Field org/jboss/as/server/deployment/Attachments.COMPOSITE_ANNOTATION_INDEX:Lorg/jboss/as/server/deployment/AttachmentKey;
     321: invokeinterface #7,  2            // InterfaceMethod org/jboss/as/server/deployment/DeploymentUnit.getAttachment:(Lorg/jboss/as/server/deployment/AttachmentKey;)Ljava/lang/Object;
     326: checkcast     #8                  // class org/jboss/as/server/deployment/annotation/CompositeIndex
     329: astore        13
     331: aload         12
     333: invokevirtual #9                  // Method org/jboss/as/ee/component/EEModuleDescription.getClassDescriptions:()Ljava/util/Collection;
     336: invokeinterface #10,  1           // InterfaceMethod java/util/Collection.iterator:()Ljava/util/Iterator;
     341: astore        14
     343: aload         14
     345: invokeinterface #11,  1           // InterfaceMethod java/util/Iterator.hasNext:()Z
     350: ifeq          440
     353: aload         14
     355: invokeinterface #12,  1           // InterfaceMethod java/util/Iterator.next:()Ljava/lang/Object;
     360: checkcast     #13                 // class org/jboss/as/ee/component/EEModuleClassDescription
     363: astore        15
     365: aload         15
     367: invokevirtual #16                 // Method org/jboss/as/ee/component/EEModuleClassDescription.getClassName:()Ljava/lang/String;
     370: aload         10
     372: invokevirtual #41                 // Method java/lang/String.equals:(Ljava/lang/Object;)Z
     375: ifeq          437
     378: aload         15
     380: aload         13
     382: invokestatic  #14                 // Method org/jboss/as/webservices/util/ASHelper.isJaxwsEndpoint:(Lorg/jboss/as/ee/component/EEModuleClassDescription;Lorg/jboss/as/server/deployment/annotation/CompositeIndex;)Z
     385: ifeq          437
     388: aload_1
     389: aload         11
     391: aload         10
     393: aload         11
     395: invokestatic  #29                 // Method createComponentDescription:(Lorg/jboss/as/server/deployment/DeploymentUnit;Ljava/lang/String;Ljava/lang/String;Ljava/lang/String;)Lorg/jboss/as/ee/component/ComponentDescription;
     398: astore        16
     400: aload         16
     402: aload         10
     404: invokestatic  #30                 // Method registerView:(Lorg/jboss/as/ee/component/ComponentDescription;Ljava/lang/String;)Lorg/jboss/msc/service/ServiceName;
     407: astore        17
     409: aload         11
     411: aload_1
     412: invokestatic  #31                 // Method getUrlPattern:(Ljava/lang/String;Lorg/jboss/as/server/deployment/DeploymentUnit;)Ljava/lang/String;
     415: astore        18
     417: aload         6
     419: new           #32                 // class org/jboss/as/webservices/metadata/model/POJOEndpoint
     422: dup
     423: aload         11
     425: aload         10
     427: aload         17
     429: aload         18
     431: invokespecial #33                 // Method org/jboss/as/webservices/metadata/model/POJOEndpoint."<init>":(Ljava/lang/String;Ljava/lang/String;Lorg/jboss/msc/service/ServiceName;Ljava/lang/String;)V
     434: invokevirtual #34                 // Method org/jboss/as/webservices/metadata/model/JAXWSDeployment.addEndpoint:(Lorg/jboss/as/webservices/metadata/model/POJOEndpoint;)V
     437: goto          343
     440: goto          139
     443: aload_3
     444: invokeinterface #42,  1           // InterfaceMethod java/util/Map.values:()Ljava/util/Collection;
     449: invokeinterface #10,  1           // InterfaceMethod java/util/Collection.iterator:()Ljava/util/Iterator;
     454: astore        7
     456: aload         7
     458: invokeinterface #11,  1           // InterfaceMethod java/util/Iterator.hasNext:()Z
     463: ifeq          797
     466: aload         7
     468: invokeinterface #12,  1           // InterfaceMethod java/util/Iterator.next:()Ljava/lang/Object;
     473: checkcast     #13                 // class org/jboss/as/ee/component/EEModuleClassDescription
     476: astore        8
     478: aconst_null
     479: astore        9
     481: aconst_null
     482: astore        10
     484: aconst_null
     485: astore        11
     487: aload         6
     489: aload         8
     491: invokevirtual #16                 // Method org/jboss/as/ee/component/EEModuleClassDescription.getClassName:()Ljava/lang/String;
     494: invokestatic  #43                 // Method org/jboss/as/webservices/util/ASHelper.getWebserviceMetadataEJBEndpoint:(Lorg/jboss/as/webservices/metadata/model/JAXWSDeployment;Ljava/lang/String;)Lorg/jboss/as/webservices/metadata/model/EJBEndpoint;
     497: astore        12
     499: aload         12
     501: ifnull        518
     504: aload_1
     505: aload         12
     507: invokevirtual #44                 // Method org/jboss/as/webservices/metadata/model/EJBEndpoint.getName:()Ljava/lang/String;
     510: invokestatic  #45                 // Method org/jboss/as/webservices/util/ASHelper.getJBossWebserviceMetaDataPortComponent:(Lorg/jboss/as/server/deployment/DeploymentUnit;Ljava/lang/String;)Lorg/jboss/wsf/spi/metadata/webservices/JBossPortComponentMetaData;
     513: invokestatic  #46                 // Method org/jboss/ws/common/utils/UrlPatternUtils.getUrlPatternByPortComponentURI:(Lorg/jboss/wsf/spi/metadata/webservices/JBossPortComponentMetaData;)Ljava/lang/String;
     516: astore        11
     518: aload         11
     520: ifnonnull     576
     523: aload         8
     525: ldc           #47                 // class org/jboss/ws/api/annotation/WebContext
     527: invokevirtual #48                 // Method org/jboss/as/ee/component/EEModuleClassDescription.getAnnotationInformation:(Ljava/lang/Class;)Lorg/jboss/as/ee/metadata/ClassAnnotationInformation;
     530: astore        13
     532: aload         13
     534: ifnull        576
     537: aload         13
     539: invokevirtual #49                 // Method org/jboss/as/ee/metadata/ClassAnnotationInformation.getClassLevelAnnotations:()Ljava/util/List;
     542: iconst_0
     543: invokeinterface #50,  2           // InterfaceMethod java/util/List.get:(I)Ljava/lang/Object;
     548: checkcast     #51                 // class org/jboss/as/webservices/deployers/WebContextAnnotationInfo
     551: astore        14
     553: aload         14
     555: ifnull        576
     558: aload         14
     560: invokevirtual #52                 // Method org/jboss/as/webservices/deployers/WebContextAnnotationInfo.getUrlPattern:()Ljava/lang/String;
     563: invokevirtual #53                 // Method java/lang/String.length:()I
     566: ifle          576
     569: aload         14
     571: invokevirtual #52                 // Method org/jboss/as/webservices/deployers/WebContextAnnotationInfo.getUrlPattern:()Ljava/lang/String;
     574: astore        11
     576: aload         11
     578: ifnonnull     720
     581: aload         8
     583: ldc           #54                 // class javax/jws/WebService
     585: invokevirtual #48                 // Method org/jboss/as/ee/component/EEModuleClassDescription.getAnnotationInformation:(Ljava/lang/Class;)Lorg/jboss/as/ee/metadata/ClassAnnotationInformation;
     588: astore        13
     590: aload         13
     592: ifnull        673
     595: aload         13
     597: invokevirtual #49                 // Method org/jboss/as/ee/metadata/ClassAnnotationInformation.getClassLevelAnnotations:()Ljava/util/List;
     600: iconst_0
     601: invokeinterface #50,  2           // InterfaceMethod java/util/List.get:(I)Ljava/lang/Object;
     606: checkcast     #55                 // class org/jboss/as/webservices/deployers/WebServiceAnnotationInfo
     609: astore        14
     611: aload         14
     613: invokevirtual #56                 // Method org/jboss/as/webservices/deployers/WebServiceAnnotationInfo.getServiceName:()Ljava/lang/String;
     616: astore        10
     618: aload         14
     620: invokevirtual #57                 // Method org/jboss/as/webservices/deployers/WebServiceAnnotationInfo.getTarget:()Lorg/jboss/jandex/AnnotationTarget;
     623: checkcast     #58                 // class org/jboss/jandex/ClassInfo
     626: astore        9
     628: aload         9
     630: invokevirtual #59                 // Method org/jboss/jandex/ClassInfo.name:()Lorg/jboss/jandex/DotName;
     633: invokevirtual #60                 // Method org/jboss/jandex/DotName.local:()Ljava/lang/String;
     636: aload         10
     638: invokestatic  #61                 // Method org/jboss/ws/common/utils/UrlPatternUtils.getUrlPattern:(Ljava/lang/String;Ljava/lang/String;)Ljava/lang/String;
     641: astore        11
     643: aload         6
     645: aload         11
     647: invokevirtual #62                 // Method org/jboss/as/webservices/metadata/model/JAXWSDeployment.contains:(Ljava/lang/String;)Z
     650: ifeq          673
     653: aload         9
     655: invokevirtual #59                 // Method org/jboss/jandex/ClassInfo.name:()Lorg/jboss/jandex/DotName;
     658: invokevirtual #60                 // Method org/jboss/jandex/DotName.local:()Ljava/lang/String;
     661: aload         10
     663: aload         14
     665: invokevirtual #63                 // Method org/jboss/as/webservices/deployers/WebServiceAnnotationInfo.getName:()Ljava/lang/String;
     668: invokestatic  #64                 // Method org/jboss/ws/common/utils/UrlPatternUtils.getUrlPattern:(Ljava/lang/String;Ljava/lang/String;Ljava/lang/String;)Ljava/lang/String;
     671: astore        11
     673: aload         8
     675: ldc           #65                 // class javax/xml/ws/WebServiceProvider
     677: invokevirtual #48                 // Method org/jboss/as/ee/component/EEModuleClassDescription.getAnnotationInformation:(Ljava/lang/Class;)Lorg/jboss/as/ee/metadata/ClassAnnotationInformation;
     680: astore        14
     682: aload         14
     684: ifnull        720
     687: aload         14
     689: invokevirtual #49                 // Method org/jboss/as/ee/metadata/ClassAnnotationInformation.getClassLevelAnnotations:()Ljava/util/List;
     692: iconst_0
     693: invokeinterface #50,  2           // InterfaceMethod java/util/List.get:(I)Ljava/lang/Object;
     698: checkcast     #66                 // class org/jboss/as/webservices/deployers/WebServiceProviderAnnotationInfo
     701: astore        15
     703: aload         15
     705: invokevirtual #67                 // Method org/jboss/as/webservices/deployers/WebServiceProviderAnnotationInfo.getServiceName:()Ljava/lang/String;
     708: astore        10
     710: aload         15
     712: invokevirtual #68                 // Method org/jboss/as/webservices/deployers/WebServiceProviderAnnotationInfo.getTarget:()Lorg/jboss/jandex/AnnotationTarget;
     715: checkcast     #58                 // class org/jboss/jandex/ClassInfo
     718: astore        9
     720: aload         9
     722: ifnull        794
     725: aload         8
     727: invokevirtual #16                 // Method org/jboss/as/ee/component/EEModuleClassDescription.getClassName:()Ljava/lang/String;
     730: astore        13
     732: aload_1
     733: aload         13
     735: aload         13
     737: aload         13
     739: invokestatic  #29                 // Method createComponentDescription:(Lorg/jboss/as/server/deployment/DeploymentUnit;Ljava/lang/String;Ljava/lang/String;Ljava/lang/String;)Lorg/jboss/as/ee/component/ComponentDescription;
     742: astore        14
     744: aload         14
     746: aload         13
     748: invokestatic  #30                 // Method registerView:(Lorg/jboss/as/ee/component/ComponentDescription;Ljava/lang/String;)Lorg/jboss/msc/service/ServiceName;
     751: astore        15
     753: aload         11
     755: ifnonnull     773
     758: aload         9
     760: invokevirtual #59                 // Method org/jboss/jandex/ClassInfo.name:()Lorg/jboss/jandex/DotName;
     763: invokevirtual #60                 // Method org/jboss/jandex/DotName.local:()Ljava/lang/String;
     766: aload         10
     768: invokestatic  #61                 // Method org/jboss/ws/common/utils/UrlPatternUtils.getUrlPattern:(Ljava/lang/String;Ljava/lang/String;)Ljava/lang/String;
     771: astore        11
     773: aload         6
     775: new           #32                 // class org/jboss/as/webservices/metadata/model/POJOEndpoint
     778: dup
     779: aload         13
     781: aload         15
     783: aload         11
     785: invokestatic  #69                 // Method org/jboss/ws/common/utils/UrlPatternUtils.getUrlPattern:(Ljava/lang/String;)Ljava/lang/String;
     788: invokespecial #70                 // Method org/jboss/as/webservices/metadata/model/POJOEndpoint."<init>":(Ljava/lang/String;Lorg/jboss/msc/service/ServiceName;Ljava/lang/String;)V
     791: invokevirtual #34                 // Method org/jboss/as/webservices/metadata/model/JAXWSDeployment.addEndpoint:(Lorg/jboss/as/webservices/metadata/model/POJOEndpoint;)V
     794: goto          456
     797: return

  private boolean exclude(org.jboss.as.server.deployment.DeploymentUnit, org.jboss.as.ee.component.EEModuleClassDescription);
    Code:
       0: aconst_null
       1: astore_3
       2: aload_2
       3: ldc           #54                 // class javax/jws/WebService
       5: invokevirtual #48                 // Method org/jboss/as/ee/component/EEModuleClassDescription.getAnnotationInformation:(Ljava/lang/Class;)Lorg/jboss/as/ee/metadata/ClassAnnotationInformation;
       8: astore        4
      10: aload         4
      12: ifnull        39
      15: aload         4
      17: invokevirtual #49                 // Method org/jboss/as/ee/metadata/ClassAnnotationInformation.getClassLevelAnnotations:()Ljava/util/List;
      20: iconst_0
      21: invokeinterface #50,  2           // InterfaceMethod java/util/List.get:(I)Ljava/lang/Object;
      26: checkcast     #55                 // class org/jboss/as/webservices/deployers/WebServiceAnnotationInfo
      29: invokevirtual #57                 // Method org/jboss/as/webservices/deployers/WebServiceAnnotationInfo.getTarget:()Lorg/jboss/jandex/AnnotationTarget;
      32: checkcast     #58                 // class org/jboss/jandex/ClassInfo
      35: astore_3
      36: goto          68
      39: aload_2
      40: ldc           #65                 // class javax/xml/ws/WebServiceProvider
      42: invokevirtual #48                 // Method org/jboss/as/ee/component/EEModuleClassDescription.getAnnotationInformation:(Ljava/lang/Class;)Lorg/jboss/as/ee/metadata/ClassAnnotationInformation;
      45: astore        5
      47: aload         5
      49: invokevirtual #49                 // Method org/jboss/as/ee/metadata/ClassAnnotationInformation.getClassLevelAnnotations:()Ljava/util/List;
      52: iconst_0
      53: invokeinterface #50,  2           // InterfaceMethod java/util/List.get:(I)Ljava/lang/Object;
      58: checkcast     #66                 // class org/jboss/as/webservices/deployers/WebServiceProviderAnnotationInfo
      61: invokevirtual #68                 // Method org/jboss/as/webservices/deployers/WebServiceProviderAnnotationInfo.getTarget:()Lorg/jboss/jandex/AnnotationTarget;
      64: checkcast     #58                 // class org/jboss/jandex/ClassInfo
      67: astore_3
      68: aload_3
      69: invokestatic  #71                 // Method isEjb3:(Lorg/jboss/jandex/ClassInfo;)Z
      72: ifne          83
      75: aload_1
      76: aload_3
      77: invokestatic  #72                 // Method isJmsEndpoint:(Lorg/jboss/as/server/deployment/DeploymentUnit;Lorg/jboss/jandex/ClassInfo;)Z
      80: ifeq          85
      83: iconst_1
      84: ireturn
      85: iconst_0
      86: ireturn

  private static java.lang.String getUrlPattern(java.lang.String, org.jboss.as.server.deployment.DeploymentUnit);
    Code:
       0: aload_1
       1: invokestatic  #18                 // Method org/jboss/as/webservices/util/ASHelper.getJBossWebMetaData:(Lorg/jboss/as/server/deployment/DeploymentUnit;)Lorg/jboss/metadata/web/jboss/JBossWebMetaData;
       4: astore_2
       5: aload_2
       6: invokevirtual #73                 // Method org/jboss/metadata/web/jboss/JBossWebMetaData.getServletMappings:()Ljava/util/List;
       9: invokeinterface #74,  1           // InterfaceMethod java/util/List.iterator:()Ljava/util/Iterator;
      14: astore_3
      15: aload_3
      16: invokeinterface #11,  1           // InterfaceMethod java/util/Iterator.hasNext:()Z
      21: ifeq          65
      24: aload_3
      25: invokeinterface #12,  1           // InterfaceMethod java/util/Iterator.next:()Ljava/lang/Object;
      30: checkcast     #75                 // class org/jboss/metadata/web/spec/ServletMappingMetaData
      33: astore        4
      35: aload_0
      36: aload         4
      38: invokevirtual #76                 // Method org/jboss/metadata/web/spec/ServletMappingMetaData.getServletName:()Ljava/lang/String;
      41: invokevirtual #41                 // Method java/lang/String.equals:(Ljava/lang/Object;)Z
      44: ifeq          62
      47: aload         4
      49: invokevirtual #77                 // Method org/jboss/metadata/web/spec/ServletMappingMetaData.getUrlPatterns:()Ljava/util/List;
      52: iconst_0
      53: invokeinterface #50,  2           // InterfaceMethod java/util/List.get:(I)Ljava/lang/Object;
      58: checkcast     #78                 // class java/lang/String
      61: areturn
      62: goto          15
      65: new           #79                 // class java/lang/IllegalStateException
      68: dup
      69: invokespecial #80                 // Method java/lang/IllegalStateException."<init>":()V
      72: athrow

  private static boolean isJmsEndpoint(org.jboss.as.server.deployment.DeploymentUnit, org.jboss.jandex.ClassInfo);
    Code:
       0: aload_1
       1: invokevirtual #59                 // Method org/jboss/jandex/ClassInfo.name:()Lorg/jboss/jandex/DotName;
       4: invokevirtual #81                 // Method org/jboss/jandex/DotName.toString:()Ljava/lang/String;
       7: astore_2
       8: aload_0
       9: getstatic     #82                 // Field org/jboss/as/webservices/util/WSAttachmentKeys.JMS_ENDPOINT_METADATA_KEY:Lorg/jboss/as/server/deployment/AttachmentKey;
      12: invokestatic  #83                 // Method org/jboss/as/webservices/util/ASHelper.getRequiredAttachment:(Lorg/jboss/as/server/deployment/DeploymentUnit;Lorg/jboss/as/server/deployment/AttachmentKey;)Ljava/lang/Object;
      15: checkcast     #84                 // class org/jboss/wsf/spi/metadata/jms/JMSEndpointsMetaData
      18: astore_3
      19: aload_3
      20: invokevirtual #85                 // Method org/jboss/wsf/spi/metadata/jms/JMSEndpointsMetaData.getEndpointsMetaData:()Ljava/util/List;
      23: invokeinterface #74,  1           // InterfaceMethod java/util/List.iterator:()Ljava/util/Iterator;
      28: astore        4
      30: aload         4
      32: invokeinterface #11,  1           // InterfaceMethod java/util/Iterator.hasNext:()Z
      37: ifeq          69
      40: aload         4
      42: invokeinterface #12,  1           // InterfaceMethod java/util/Iterator.next:()Ljava/lang/Object;
      47: checkcast     #86                 // class org/jboss/wsf/spi/metadata/jms/JMSEndpointMetaData
      50: astore        5
      52: aload_2
      53: aload         5
      55: invokevirtual #87                 // Method org/jboss/wsf/spi/metadata/jms/JMSEndpointMetaData.getImplementor:()Ljava/lang/String;
      58: invokevirtual #41                 // Method java/lang/String.equals:(Ljava/lang/Object;)Z
      61: ifeq          66
      64: iconst_1
      65: ireturn
      66: goto          30
      69: iconst_0
      70: ireturn
}
