Compiled from "DefaultClientCodecConfigurer.java"
public class org.springframework.http.codec.support.DefaultClientCodecConfigurer extends org.springframework.http.codec.support.BaseCodecConfigurer implements org.springframework.http.codec.ClientCodecConfigurer {
  public org.springframework.http.codec.support.DefaultClientCodecConfigurer();
    Code:
       0: aload_0
       1: new           #1                  // class org/springframework/http/codec/support/ClientDefaultCodecsImpl
       4: dup
       5: invokespecial #2                  // Method org/springframework/http/codec/support/ClientDefaultCodecsImpl."<init>":()V
       8: invokespecial #3                  // Method org/springframework/http/codec/support/BaseCodecConfigurer."<init>":(Lorg/springframework/http/codec/support/BaseDefaultCodecs;)V
      11: aload_0
      12: invokevirtual #4                  // Method defaultCodecs:()Lorg/springframework/http/codec/ClientCodecConfigurer$ClientDefaultCodecs;
      15: checkcast     #1                  // class org/springframework/http/codec/support/ClientDefaultCodecsImpl
      18: aload_0
      19: invokedynamic #5,  0              // InvokeDynamic #0:get:(Lorg/springframework/http/codec/support/DefaultClientCodecConfigurer;)Ljava/util/function/Supplier;
      24: invokevirtual #6                  // Method org/springframework/http/codec/support/ClientDefaultCodecsImpl.setPartWritersSupplier:(Ljava/util/function/Supplier;)V
      27: return

  private org.springframework.http.codec.support.DefaultClientCodecConfigurer(org.springframework.http.codec.support.DefaultClientCodecConfigurer);
    Code:
       0: aload_0
       1: aload_1
       2: invokespecial #7                  // Method org/springframework/http/codec/support/BaseCodecConfigurer."<init>":(Lorg/springframework/http/codec/support/BaseCodecConfigurer;)V
       5: aload_0
       6: invokevirtual #4                  // Method defaultCodecs:()Lorg/springframework/http/codec/ClientCodecConfigurer$ClientDefaultCodecs;
       9: checkcast     #1                  // class org/springframework/http/codec/support/ClientDefaultCodecsImpl
      12: aload_0
      13: invokedynamic #5,  0              // InvokeDynamic #0:get:(Lorg/springframework/http/codec/support/DefaultClientCodecConfigurer;)Ljava/util/function/Supplier;
      18: invokevirtual #6                  // Method org/springframework/http/codec/support/ClientDefaultCodecsImpl.setPartWritersSupplier:(Ljava/util/function/Supplier;)V
      21: return

  public org.springframework.http.codec.ClientCodecConfigurer$ClientDefaultCodecs defaultCodecs();
    Code:
       0: aload_0
       1: invokespecial #8                  // Method org/springframework/http/codec/support/BaseCodecConfigurer.defaultCodecs:()Lorg/springframework/http/codec/CodecConfigurer$DefaultCodecs;
       4: checkcast     #9                  // class org/springframework/http/codec/ClientCodecConfigurer$ClientDefaultCodecs
       7: areturn

  public org.springframework.http.codec.support.DefaultClientCodecConfigurer clone();
    Code:
       0: new           #10                 // class org/springframework/http/codec/support/DefaultClientCodecConfigurer
       3: dup
       4: aload_0
       5: invokespecial #11                 // Method "<init>":(Lorg/springframework/http/codec/support/DefaultClientCodecConfigurer;)V
       8: areturn

  protected org.springframework.http.codec.support.BaseDefaultCodecs cloneDefaultCodecs();
    Code:
       0: new           #1                  // class org/springframework/http/codec/support/ClientDefaultCodecsImpl
       3: dup
       4: aload_0
       5: invokevirtual #4                  // Method defaultCodecs:()Lorg/springframework/http/codec/ClientCodecConfigurer$ClientDefaultCodecs;
       8: checkcast     #1                  // class org/springframework/http/codec/support/ClientDefaultCodecsImpl
      11: invokespecial #12                 // Method org/springframework/http/codec/support/ClientDefaultCodecsImpl."<init>":(Lorg/springframework/http/codec/support/ClientDefaultCodecsImpl;)V
      14: areturn

  private java.util.List<org.springframework.http.codec.HttpMessageWriter<?>> getPartWriters();
    Code:
       0: new           #13                 // class java/util/ArrayList
       3: dup
       4: invokespecial #14                 // Method java/util/ArrayList."<init>":()V
       7: astore_1
       8: aload_1
       9: aload_0
      10: getfield      #15                 // Field customCodecs:Lorg/springframework/http/codec/support/BaseCodecConfigurer$DefaultCustomCodecs;
      13: invokevirtual #16                 // Method org/springframework/http/codec/support/BaseCodecConfigurer$DefaultCustomCodecs.getTypedWriters:()Ljava/util/Map;
      16: invokeinterface #17,  1           // InterfaceMethod java/util/Map.keySet:()Ljava/util/Set;
      21: invokeinterface #18,  2           // InterfaceMethod java/util/List.addAll:(Ljava/util/Collection;)Z
      26: pop
      27: aload_1
      28: aload_0
      29: getfield      #19                 // Field defaultCodecs:Lorg/springframework/http/codec/support/BaseDefaultCodecs;
      32: invokevirtual #20                 // Method org/springframework/http/codec/support/BaseDefaultCodecs.getBaseTypedWriters:()Ljava/util/List;
      35: invokeinterface #18,  2           // InterfaceMethod java/util/List.addAll:(Ljava/util/Collection;)Z
      40: pop
      41: aload_1
      42: aload_0
      43: getfield      #15                 // Field customCodecs:Lorg/springframework/http/codec/support/BaseCodecConfigurer$DefaultCustomCodecs;
      46: invokevirtual #21                 // Method org/springframework/http/codec/support/BaseCodecConfigurer$DefaultCustomCodecs.getObjectWriters:()Ljava/util/Map;
      49: invokeinterface #17,  1           // InterfaceMethod java/util/Map.keySet:()Ljava/util/Set;
      54: invokeinterface #18,  2           // InterfaceMethod java/util/List.addAll:(Ljava/util/Collection;)Z
      59: pop
      60: aload_1
      61: aload_0
      62: getfield      #19                 // Field defaultCodecs:Lorg/springframework/http/codec/support/BaseDefaultCodecs;
      65: invokevirtual #22                 // Method org/springframework/http/codec/support/BaseDefaultCodecs.getBaseObjectWriters:()Ljava/util/List;
      68: invokeinterface #18,  2           // InterfaceMethod java/util/List.addAll:(Ljava/util/Collection;)Z
      73: pop
      74: aload_1
      75: aload_0
      76: getfield      #19                 // Field defaultCodecs:Lorg/springframework/http/codec/support/BaseDefaultCodecs;
      79: invokevirtual #23                 // Method org/springframework/http/codec/support/BaseDefaultCodecs.getCatchAllWriters:()Ljava/util/List;
      82: invokeinterface #18,  2           // InterfaceMethod java/util/List.addAll:(Ljava/util/Collection;)Z
      87: pop
      88: aload_1
      89: areturn

  public org.springframework.http.codec.CodecConfigurer clone();
    Code:
       0: aload_0
       1: invokevirtual #24                 // Method clone:()Lorg/springframework/http/codec/support/DefaultClientCodecConfigurer;
       4: areturn

  public java.util.List getWriters();
    Code:
       0: aload_0
       1: invokespecial #25                 // Method org/springframework/http/codec/support/BaseCodecConfigurer.getWriters:()Ljava/util/List;
       4: areturn

  public java.util.List getReaders();
    Code:
       0: aload_0
       1: invokespecial #26                 // Method org/springframework/http/codec/support/BaseCodecConfigurer.getReaders:()Ljava/util/List;
       4: areturn

  public org.springframework.http.codec.CodecConfigurer$CustomCodecs customCodecs();
    Code:
       0: aload_0
       1: invokespecial #27                 // Method org/springframework/http/codec/support/BaseCodecConfigurer.customCodecs:()Lorg/springframework/http/codec/CodecConfigurer$CustomCodecs;
       4: areturn

  public void registerDefaults(boolean);
    Code:
       0: aload_0
       1: iload_1
       2: invokespecial #28                 // Method org/springframework/http/codec/support/BaseCodecConfigurer.registerDefaults:(Z)V
       5: return

  public org.springframework.http.codec.CodecConfigurer$DefaultCodecs defaultCodecs();
    Code:
       0: aload_0
       1: invokevirtual #4                  // Method defaultCodecs:()Lorg/springframework/http/codec/ClientCodecConfigurer$ClientDefaultCodecs;
       4: areturn

  public java.lang.Object clone() throws java.lang.CloneNotSupportedException;
    Code:
       0: aload_0
       1: invokevirtual #24                 // Method clone:()Lorg/springframework/http/codec/support/DefaultClientCodecConfigurer;
       4: areturn

  public org.springframework.http.codec.ClientCodecConfigurer clone();
    Code:
       0: aload_0
       1: invokevirtual #24                 // Method clone:()Lorg/springframework/http/codec/support/DefaultClientCodecConfigurer;
       4: areturn
}
