Compiled from "SockJSSocket.kt"
public final class io.vertx.kotlin.ext.web.handler.sockjs.SockJSSocketKt {
  public static final java.lang.Object endAwait(io.vertx.ext.web.handler.sockjs.SockJSSocket, kotlin.coroutines.Continuation<? super kotlin.Unit>);
    Code:
       0: new           #11                 // class io/vertx/kotlin/ext/web/handler/sockjs/SockJSSocketKt$endAwait$2
       3: dup
       4: aload_0
       5: invokespecial #15                 // Method io/vertx/kotlin/ext/web/handler/sockjs/SockJSSocketKt$endAwait$2."<init>":(Lio/vertx/ext/web/handler/sockjs/SockJSSocket;)V
       8: checkcast     #17                 // class kotlin/jvm/functions/Function1
      11: aload_1
      12: invokestatic  #23                 // Method io/vertx/kotlin/coroutines/VertxCoroutineKt.awaitResult:(Lkotlin/jvm/functions/Function1;Lkotlin/coroutines/Continuation;)Ljava/lang/Object;
      15: areturn

  public static final java.lang.Object endAwait(io.vertx.ext.web.handler.sockjs.SockJSSocket, io.vertx.core.buffer.Buffer, kotlin.coroutines.Continuation<? super kotlin.Unit>);
    Code:
       0: new           #31                 // class io/vertx/kotlin/ext/web/handler/sockjs/SockJSSocketKt$endAwait$4
       3: dup
       4: aload_0
       5: aload_1
       6: invokespecial #34                 // Method io/vertx/kotlin/ext/web/handler/sockjs/SockJSSocketKt$endAwait$4."<init>":(Lio/vertx/ext/web/handler/sockjs/SockJSSocket;Lio/vertx/core/buffer/Buffer;)V
       9: checkcast     #17                 // class kotlin/jvm/functions/Function1
      12: aload_2
      13: invokestatic  #23                 // Method io/vertx/kotlin/coroutines/VertxCoroutineKt.awaitResult:(Lkotlin/jvm/functions/Function1;Lkotlin/coroutines/Continuation;)Ljava/lang/Object;
      16: areturn

  public static final java.lang.Object pipeToAwait(io.vertx.ext.web.handler.sockjs.SockJSSocket, io.vertx.core.streams.WriteStream<io.vertx.core.buffer.Buffer>, kotlin.coroutines.Continuation<? super kotlin.Unit>);
    Code:
       0: new           #41                 // class io/vertx/kotlin/ext/web/handler/sockjs/SockJSSocketKt$pipeToAwait$2
       3: dup
       4: aload_0
       5: aload_1
       6: invokespecial #44                 // Method io/vertx/kotlin/ext/web/handler/sockjs/SockJSSocketKt$pipeToAwait$2."<init>":(Lio/vertx/ext/web/handler/sockjs/SockJSSocket;Lio/vertx/core/streams/WriteStream;)V
       9: checkcast     #17                 // class kotlin/jvm/functions/Function1
      12: aload_2
      13: invokestatic  #23                 // Method io/vertx/kotlin/coroutines/VertxCoroutineKt.awaitResult:(Lkotlin/jvm/functions/Function1;Lkotlin/coroutines/Continuation;)Ljava/lang/Object;
      16: areturn

  public static final java.lang.Object writeAwait(io.vertx.ext.web.handler.sockjs.SockJSSocket, java.lang.String, kotlin.coroutines.Continuation<? super kotlin.Unit>);
    Code:
       0: new           #52                 // class io/vertx/kotlin/ext/web/handler/sockjs/SockJSSocketKt$writeAwait$2
       3: dup
       4: aload_0
       5: aload_1
       6: invokespecial #55                 // Method io/vertx/kotlin/ext/web/handler/sockjs/SockJSSocketKt$writeAwait$2."<init>":(Lio/vertx/ext/web/handler/sockjs/SockJSSocket;Ljava/lang/String;)V
       9: checkcast     #17                 // class kotlin/jvm/functions/Function1
      12: aload_2
      13: invokestatic  #23                 // Method io/vertx/kotlin/coroutines/VertxCoroutineKt.awaitResult:(Lkotlin/jvm/functions/Function1;Lkotlin/coroutines/Continuation;)Ljava/lang/Object;
      16: areturn

  public static final java.lang.Object writeAwait(io.vertx.ext.web.handler.sockjs.SockJSSocket, io.vertx.core.buffer.Buffer, kotlin.coroutines.Continuation<? super kotlin.Unit>);
    Code:
       0: new           #59                 // class io/vertx/kotlin/ext/web/handler/sockjs/SockJSSocketKt$writeAwait$4
       3: dup
       4: aload_0
       5: aload_1
       6: invokespecial #60                 // Method io/vertx/kotlin/ext/web/handler/sockjs/SockJSSocketKt$writeAwait$4."<init>":(Lio/vertx/ext/web/handler/sockjs/SockJSSocket;Lio/vertx/core/buffer/Buffer;)V
       9: checkcast     #17                 // class kotlin/jvm/functions/Function1
      12: aload_2
      13: invokestatic  #23                 // Method io/vertx/kotlin/coroutines/VertxCoroutineKt.awaitResult:(Lkotlin/jvm/functions/Function1;Lkotlin/coroutines/Continuation;)Ljava/lang/Object;
      16: areturn
}
