Compiled from "FixedElapsedTime.java"
public class org.apache.commons.math3.genetics.FixedElapsedTime implements org.apache.commons.math3.genetics.StoppingCondition {
  private final long maxTimePeriod;

  private long endTime;

  public org.apache.commons.math3.genetics.FixedElapsedTime(long) throws org.apache.commons.math3.exception.NumberIsTooSmallException;
    Code:
       0: aload_0
       1: lload_1
       2: getstatic     #1                  // Field java/util/concurrent/TimeUnit.SECONDS:Ljava/util/concurrent/TimeUnit;
       5: invokespecial #2                  // Method "<init>":(JLjava/util/concurrent/TimeUnit;)V
       8: return

  public org.apache.commons.math3.genetics.FixedElapsedTime(long, java.util.concurrent.TimeUnit) throws org.apache.commons.math3.exception.NumberIsTooSmallException;
    Code:
       0: aload_0
       1: invokespecial #3                  // Method java/lang/Object."<init>":()V
       4: aload_0
       5: ldc2_w        #4                  // long -1l
       8: putfield      #6                  // Field endTime:J
      11: lload_1
      12: lconst_0
      13: lcmp
      14: ifge          34
      17: new           #7                  // class org/apache/commons/math3/exception/NumberIsTooSmallException
      20: dup
      21: lload_1
      22: invokestatic  #8                  // Method java/lang/Long.valueOf:(J)Ljava/lang/Long;
      25: iconst_0
      26: invokestatic  #9                  // Method java/lang/Integer.valueOf:(I)Ljava/lang/Integer;
      29: iconst_1
      30: invokespecial #10                 // Method org/apache/commons/math3/exception/NumberIsTooSmallException."<init>":(Ljava/lang/Number;Ljava/lang/Number;Z)V
      33: athrow
      34: aload_0
      35: aload_3
      36: lload_1
      37: invokevirtual #11                 // Method java/util/concurrent/TimeUnit.toNanos:(J)J
      40: putfield      #12                 // Field maxTimePeriod:J
      43: return

  public boolean isSatisfied(org.apache.commons.math3.genetics.Population);
    Code:
       0: aload_0
       1: getfield      #6                  // Field endTime:J
       4: lconst_0
       5: lcmp
       6: ifge          21
       9: aload_0
      10: invokestatic  #13                 // Method java/lang/System.nanoTime:()J
      13: aload_0
      14: getfield      #12                 // Field maxTimePeriod:J
      17: ladd
      18: putfield      #6                  // Field endTime:J
      21: invokestatic  #13                 // Method java/lang/System.nanoTime:()J
      24: aload_0
      25: getfield      #6                  // Field endTime:J
      28: lcmp
      29: iflt          36
      32: iconst_1
      33: goto          37
      36: iconst_0
      37: ireturn
}
