Compiled from "AbstractTypeChecker.kt"
public final class kotlin.reflect.jvm.internal.impl.types.AbstractNullabilityChecker {
  public static final kotlin.reflect.jvm.internal.impl.types.AbstractNullabilityChecker INSTANCE;

  private kotlin.reflect.jvm.internal.impl.types.AbstractNullabilityChecker();
    Code:
       0: aload_0
       1: invokespecial #46                 // Method java/lang/Object."<init>":()V
       4: return

  public final boolean isPossibleSubtype(kotlin.reflect.jvm.internal.impl.types.TypeCheckerState, kotlin.reflect.jvm.internal.impl.types.model.SimpleTypeMarker, kotlin.reflect.jvm.internal.impl.types.model.SimpleTypeMarker);
    Code:
       0: aload_1
       1: ldc           #9                  // String state
       3: invokestatic  #59                 // Method kotlin/jvm/internal/Intrinsics.checkNotNullParameter:(Ljava/lang/Object;Ljava/lang/String;)V
       6: aload_2
       7: ldc           #10                 // String subType
       9: invokestatic  #59                 // Method kotlin/jvm/internal/Intrinsics.checkNotNullParameter:(Ljava/lang/Object;Ljava/lang/String;)V
      12: aload_3
      13: ldc           #11                 // String superType
      15: invokestatic  #59                 // Method kotlin/jvm/internal/Intrinsics.checkNotNullParameter:(Ljava/lang/Object;Ljava/lang/String;)V
      18: aload_0
      19: aload_1
      20: aload_2
      21: aload_3
      22: invokespecial #64                 // Method runIsPossibleSubtype:(Lkotlin/reflect/jvm/internal/impl/types/TypeCheckerState;Lkotlin/reflect/jvm/internal/impl/types/model/SimpleTypeMarker;Lkotlin/reflect/jvm/internal/impl/types/model/SimpleTypeMarker;)Z
      25: ireturn

  private final boolean runIsPossibleSubtype(kotlin.reflect.jvm.internal.impl.types.TypeCheckerState, kotlin.reflect.jvm.internal.impl.types.model.SimpleTypeMarker, kotlin.reflect.jvm.internal.impl.types.model.SimpleTypeMarker);
    Code:
       0: aload_1
       1: invokevirtual #68                 // Method kotlin/reflect/jvm/internal/impl/types/TypeCheckerState.getTypeSystemContext:()Lkotlin/reflect/jvm/internal/impl/types/model/TypeSystemContext;
       4: astore        4
       6: iconst_0
       7: istore        5
       9: getstatic     #40                 // Field kotlin/reflect/jvm/internal/impl/types/AbstractTypeChecker.RUN_SLOW_ASSERTIONS:Z
      12: ifeq          181
      15: aload         4
      17: aload_2
      18: invokeinterface #87,  2           // InterfaceMethod kotlin/reflect/jvm/internal/impl/types/model/TypeSystemContext.isSingleClassifierType:(Lkotlin/reflect/jvm/internal/impl/types/model/SimpleTypeMarker;)Z
      23: ifne          55
      26: aload         4
      28: aload         4
      30: aload_2
      31: invokeinterface #90,  2           // InterfaceMethod kotlin/reflect/jvm/internal/impl/types/model/TypeSystemContext.typeConstructor:(Lkotlin/reflect/jvm/internal/impl/types/model/SimpleTypeMarker;)Lkotlin/reflect/jvm/internal/impl/types/model/TypeConstructorMarker;
      36: invokeinterface #82,  2           // InterfaceMethod kotlin/reflect/jvm/internal/impl/types/model/TypeSystemContext.isIntersection:(Lkotlin/reflect/jvm/internal/impl/types/model/TypeConstructorMarker;)Z
      41: ifne          55
      44: aload_1
      45: aload_2
      46: checkcast     #34                 // class kotlin/reflect/jvm/internal/impl/types/model/KotlinTypeMarker
      49: invokevirtual #70                 // Method kotlin/reflect/jvm/internal/impl/types/TypeCheckerState.isAllowedTypeVariable:(Lkotlin/reflect/jvm/internal/impl/types/model/KotlinTypeMarker;)Z
      52: ifeq          59
      55: iconst_1
      56: goto          60
      59: iconst_0
      60: istore        6
      62: getstatic     #38                 // Field kotlin/_Assertions.ENABLED:Z
      65: ifeq          107
      68: iload         6
      70: ifne          107
      73: iconst_0
      74: istore        7
      76: new           #18                 // class java/lang/StringBuilder
      79: dup
      80: invokespecial #48                 // Method java/lang/StringBuilder."<init>":()V
      83: ldc           #3                  // String Not singleClassifierType and not intersection subType:
      85: invokevirtual #50                 // Method java/lang/StringBuilder.append:(Ljava/lang/String;)Ljava/lang/StringBuilder;
      88: aload_2
      89: invokevirtual #49                 // Method java/lang/StringBuilder.append:(Ljava/lang/Object;)Ljava/lang/StringBuilder;
      92: invokevirtual #51                 // Method java/lang/StringBuilder.toString:()Ljava/lang/String;
      95: astore        7
      97: new           #14                 // class java/lang/AssertionError
     100: dup
     101: aload         7
     103: invokespecial #44                 // Method java/lang/AssertionError."<init>":(Ljava/lang/Object;)V
     106: athrow
     107: aload         4
     109: aload_3
     110: invokeinterface #87,  2           // InterfaceMethod kotlin/reflect/jvm/internal/impl/types/model/TypeSystemContext.isSingleClassifierType:(Lkotlin/reflect/jvm/internal/impl/types/model/SimpleTypeMarker;)Z
     115: ifne          129
     118: aload_1
     119: aload_3
     120: checkcast     #34                 // class kotlin/reflect/jvm/internal/impl/types/model/KotlinTypeMarker
     123: invokevirtual #70                 // Method kotlin/reflect/jvm/internal/impl/types/TypeCheckerState.isAllowedTypeVariable:(Lkotlin/reflect/jvm/internal/impl/types/model/KotlinTypeMarker;)Z
     126: ifeq          133
     129: iconst_1
     130: goto          134
     133: iconst_0
     134: istore        6
     136: getstatic     #38                 // Field kotlin/_Assertions.ENABLED:Z
     139: ifeq          181
     142: iload         6
     144: ifne          181
     147: iconst_0
     148: istore        7
     150: new           #18                 // class java/lang/StringBuilder
     153: dup
     154: invokespecial #48                 // Method java/lang/StringBuilder."<init>":()V
     157: ldc           #4                  // String Not singleClassifierType superType:
     159: invokevirtual #50                 // Method java/lang/StringBuilder.append:(Ljava/lang/String;)Ljava/lang/StringBuilder;
     162: aload_3
     163: invokevirtual #49                 // Method java/lang/StringBuilder.append:(Ljava/lang/Object;)Ljava/lang/StringBuilder;
     166: invokevirtual #51                 // Method java/lang/StringBuilder.toString:()Ljava/lang/String;
     169: astore        7
     171: new           #14                 // class java/lang/AssertionError
     174: dup
     175: aload         7
     177: invokespecial #44                 // Method java/lang/AssertionError."<init>":(Ljava/lang/Object;)V
     180: athrow
     181: aload         4
     183: aload_3
     184: invokeinterface #83,  2           // InterfaceMethod kotlin/reflect/jvm/internal/impl/types/model/TypeSystemContext.isMarkedNullable:(Lkotlin/reflect/jvm/internal/impl/types/model/SimpleTypeMarker;)Z
     189: ifeq          194
     192: iconst_1
     193: ireturn
     194: aload         4
     196: aload_2
     197: checkcast     #34                 // class kotlin/reflect/jvm/internal/impl/types/model/KotlinTypeMarker
     200: invokeinterface #81,  2           // InterfaceMethod kotlin/reflect/jvm/internal/impl/types/model/TypeSystemContext.isDefinitelyNotNullType:(Lkotlin/reflect/jvm/internal/impl/types/model/KotlinTypeMarker;)Z
     205: ifne          222
     208: aload         4
     210: aload_2
     211: checkcast     #34                 // class kotlin/reflect/jvm/internal/impl/types/model/KotlinTypeMarker
     214: invokeinterface #84,  2           // InterfaceMethod kotlin/reflect/jvm/internal/impl/types/model/TypeSystemContext.isNotNullTypeParameter:(Lkotlin/reflect/jvm/internal/impl/types/model/KotlinTypeMarker;)Z
     219: ifeq          224
     222: iconst_1
     223: ireturn
     224: aload_2
     225: instanceof    #33                 // class kotlin/reflect/jvm/internal/impl/types/model/CapturedTypeMarker
     228: ifeq          247
     231: aload         4
     233: aload_2
     234: checkcast     #33                 // class kotlin/reflect/jvm/internal/impl/types/model/CapturedTypeMarker
     237: invokeinterface #86,  2           // InterfaceMethod kotlin/reflect/jvm/internal/impl/types/model/TypeSystemContext.isProjectionNotNull:(Lkotlin/reflect/jvm/internal/impl/types/model/CapturedTypeMarker;)Z
     242: ifeq          247
     245: iconst_1
     246: ireturn
     247: getstatic     #39                 // Field INSTANCE:Lkotlin/reflect/jvm/internal/impl/types/AbstractNullabilityChecker;
     250: aload_1
     251: aload_2
     252: getstatic     #41                 // Field kotlin/reflect/jvm/internal/impl/types/TypeCheckerState$SupertypesPolicy$LowerIfFlexible.INSTANCE:Lkotlin/reflect/jvm/internal/impl/types/TypeCheckerState$SupertypesPolicy$LowerIfFlexible;
     255: checkcast     #29                 // class kotlin/reflect/jvm/internal/impl/types/TypeCheckerState$SupertypesPolicy
     258: invokevirtual #61                 // Method hasNotNullSupertype:(Lkotlin/reflect/jvm/internal/impl/types/TypeCheckerState;Lkotlin/reflect/jvm/internal/impl/types/model/SimpleTypeMarker;Lkotlin/reflect/jvm/internal/impl/types/TypeCheckerState$SupertypesPolicy;)Z
     261: ifeq          266
     264: iconst_1
     265: ireturn
     266: aload         4
     268: aload_3
     269: checkcast     #34                 // class kotlin/reflect/jvm/internal/impl/types/model/KotlinTypeMarker
     272: invokeinterface #81,  2           // InterfaceMethod kotlin/reflect/jvm/internal/impl/types/model/TypeSystemContext.isDefinitelyNotNullType:(Lkotlin/reflect/jvm/internal/impl/types/model/KotlinTypeMarker;)Z
     277: ifeq          282
     280: iconst_0
     281: ireturn
     282: getstatic     #39                 // Field INSTANCE:Lkotlin/reflect/jvm/internal/impl/types/AbstractNullabilityChecker;
     285: aload_1
     286: aload_3
     287: getstatic     #43                 // Field kotlin/reflect/jvm/internal/impl/types/TypeCheckerState$SupertypesPolicy$UpperIfFlexible.INSTANCE:Lkotlin/reflect/jvm/internal/impl/types/TypeCheckerState$SupertypesPolicy$UpperIfFlexible;
     290: checkcast     #29                 // class kotlin/reflect/jvm/internal/impl/types/TypeCheckerState$SupertypesPolicy
     293: invokevirtual #61                 // Method hasNotNullSupertype:(Lkotlin/reflect/jvm/internal/impl/types/TypeCheckerState;Lkotlin/reflect/jvm/internal/impl/types/model/SimpleTypeMarker;Lkotlin/reflect/jvm/internal/impl/types/TypeCheckerState$SupertypesPolicy;)Z
     296: ifeq          301
     299: iconst_0
     300: ireturn
     301: aload         4
     303: aload_2
     304: invokeinterface #80,  2           // InterfaceMethod kotlin/reflect/jvm/internal/impl/types/model/TypeSystemContext.isClassType:(Lkotlin/reflect/jvm/internal/impl/types/model/SimpleTypeMarker;)Z
     309: ifeq          314
     312: iconst_0
     313: ireturn
     314: getstatic     #39                 // Field INSTANCE:Lkotlin/reflect/jvm/internal/impl/types/AbstractNullabilityChecker;
     317: aload_1
     318: aload_2
     319: aload         4
     321: aload_3
     322: invokeinterface #90,  2           // InterfaceMethod kotlin/reflect/jvm/internal/impl/types/model/TypeSystemContext.typeConstructor:(Lkotlin/reflect/jvm/internal/impl/types/model/SimpleTypeMarker;)Lkotlin/reflect/jvm/internal/impl/types/model/TypeConstructorMarker;
     327: invokevirtual #62                 // Method hasPathByNotMarkedNullableNodes:(Lkotlin/reflect/jvm/internal/impl/types/TypeCheckerState;Lkotlin/reflect/jvm/internal/impl/types/model/SimpleTypeMarker;Lkotlin/reflect/jvm/internal/impl/types/model/TypeConstructorMarker;)Z
     330: ireturn

  public final boolean hasNotNullSupertype(kotlin.reflect.jvm.internal.impl.types.TypeCheckerState, kotlin.reflect.jvm.internal.impl.types.model.SimpleTypeMarker, kotlin.reflect.jvm.internal.impl.types.TypeCheckerState$SupertypesPolicy);
    Code:
       0: aload_1
       1: ldc           #2                  // String <this>
       3: invokestatic  #59                 // Method kotlin/jvm/internal/Intrinsics.checkNotNullParameter:(Ljava/lang/Object;Ljava/lang/String;)V
       6: aload_2
       7: ldc           #13                 // String type
       9: invokestatic  #59                 // Method kotlin/jvm/internal/Intrinsics.checkNotNullParameter:(Ljava/lang/Object;Ljava/lang/String;)V
      12: aload_3
      13: ldc           #12                 // String supertypesPolicy
      15: invokestatic  #59                 // Method kotlin/jvm/internal/Intrinsics.checkNotNullParameter:(Ljava/lang/Object;Ljava/lang/String;)V
      18: aload_1
      19: invokevirtual #68                 // Method kotlin/reflect/jvm/internal/impl/types/TypeCheckerState.getTypeSystemContext:()Lkotlin/reflect/jvm/internal/impl/types/model/TypeSystemContext;
      22: astore        4
      24: iconst_0
      25: istore        5
      27: aload_1
      28: astore        6
      30: iconst_0
      31: istore        7
      33: aload_2
      34: astore        8
      36: iconst_0
      37: istore        9
      39: aload         4
      41: aload         8
      43: invokeinterface #80,  2           // InterfaceMethod kotlin/reflect/jvm/internal/impl/types/model/TypeSystemContext.isClassType:(Lkotlin/reflect/jvm/internal/impl/types/model/SimpleTypeMarker;)Z
      48: ifeq          63
      51: aload         4
      53: aload         8
      55: invokeinterface #83,  2           // InterfaceMethod kotlin/reflect/jvm/internal/impl/types/model/TypeSystemContext.isMarkedNullable:(Lkotlin/reflect/jvm/internal/impl/types/model/SimpleTypeMarker;)Z
      60: ifeq          78
      63: aload         4
      65: aload         8
      67: checkcast     #34                 // class kotlin/reflect/jvm/internal/impl/types/model/KotlinTypeMarker
      70: invokeinterface #81,  2           // InterfaceMethod kotlin/reflect/jvm/internal/impl/types/model/TypeSystemContext.isDefinitelyNotNullType:(Lkotlin/reflect/jvm/internal/impl/types/model/KotlinTypeMarker;)Z
      75: ifeq          82
      78: iconst_1
      79: goto          83
      82: iconst_0
      83: ifeq          90
      86: iconst_1
      87: goto          465
      90: aload         6
      92: invokevirtual #69                 // Method kotlin/reflect/jvm/internal/impl/types/TypeCheckerState.initialize:()V
      95: aload         6
      97: invokevirtual #66                 // Method kotlin/reflect/jvm/internal/impl/types/TypeCheckerState.getSupertypesDeque:()Ljava/util/ArrayDeque;
     100: dup
     101: invokestatic  #57                 // Method kotlin/jvm/internal/Intrinsics.checkNotNull:(Ljava/lang/Object;)V
     104: astore        10
     106: aload         6
     108: invokevirtual #67                 // Method kotlin/reflect/jvm/internal/impl/types/TypeCheckerState.getSupertypesSet:()Ljava/util/Set;
     111: dup
     112: invokestatic  #57                 // Method kotlin/jvm/internal/Intrinsics.checkNotNull:(Ljava/lang/Object;)V
     115: astore        11
     117: aload         10
     119: aload_2
     120: invokevirtual #54                 // Method java/util/ArrayDeque.push:(Ljava/lang/Object;)V
     123: aload         10
     125: checkcast     #20                 // class java/util/Collection
     128: invokeinterface #73,  1           // InterfaceMethod java/util/Collection.isEmpty:()Z
     133: ifne          140
     136: iconst_1
     137: goto          141
     140: iconst_0
     141: ifeq          459
     144: aload         11
     146: invokeinterface #78,  1           // InterfaceMethod java/util/Set.size:()I
     151: sipush        1000
     154: if_icmple     212
     157: new           #15                 // class java/lang/IllegalStateException
     160: dup
     161: new           #18                 // class java/lang/StringBuilder
     164: dup
     165: invokespecial #48                 // Method java/lang/StringBuilder."<init>":()V
     168: ldc           #5                  // String Too many supertypes for type:
     170: invokevirtual #50                 // Method java/lang/StringBuilder.append:(Ljava/lang/String;)Ljava/lang/StringBuilder;
     173: aload_2
     174: invokevirtual #49                 // Method java/lang/StringBuilder.append:(Ljava/lang/Object;)Ljava/lang/StringBuilder;
     177: ldc           #1                  // String . Supertypes =
     179: invokevirtual #50                 // Method java/lang/StringBuilder.append:(Ljava/lang/String;)Ljava/lang/StringBuilder;
     182: aload         11
     184: checkcast     #16                 // class java/lang/Iterable
     187: aconst_null
     188: aconst_null
     189: aconst_null
     190: iconst_0
     191: aconst_null
     192: aconst_null
     193: bipush        63
     195: aconst_null
     196: invokestatic  #55                 // Method kotlin/collections/CollectionsKt.joinToString$default:(Ljava/lang/Iterable;Ljava/lang/CharSequence;Ljava/lang/CharSequence;Ljava/lang/CharSequence;ILjava/lang/CharSequence;Lkotlin/jvm/functions/Function1;ILjava/lang/Object;)Ljava/lang/String;
     199: invokevirtual #50                 // Method java/lang/StringBuilder.append:(Ljava/lang/String;)Ljava/lang/StringBuilder;
     202: invokevirtual #51                 // Method java/lang/StringBuilder.toString:()Ljava/lang/String;
     205: invokevirtual #47                 // Method java/lang/Object.toString:()Ljava/lang/String;
     208: invokespecial #45                 // Method java/lang/IllegalStateException."<init>":(Ljava/lang/String;)V
     211: athrow
     212: aload         10
     214: invokevirtual #53                 // Method java/util/ArrayDeque.pop:()Ljava/lang/Object;
     217: checkcast     #35                 // class kotlin/reflect/jvm/internal/impl/types/model/SimpleTypeMarker
     220: astore        12
     222: aload         11
     224: aload         12
     226: ldc           #6                  // String current
     228: invokestatic  #58                 // Method kotlin/jvm/internal/Intrinsics.checkNotNullExpressionValue:(Ljava/lang/Object;Ljava/lang/String;)V
     231: aload         12
     233: invokeinterface #77,  2           // InterfaceMethod java/util/Set.add:(Ljava/lang/Object;)Z
     238: ifeq          123
     241: aload         12
     243: astore        8
     245: iconst_0
     246: istore        9
     248: aload         4
     250: aload         8
     252: invokeinterface #83,  2           // InterfaceMethod kotlin/reflect/jvm/internal/impl/types/model/TypeSystemContext.isMarkedNullable:(Lkotlin/reflect/jvm/internal/impl/types/model/SimpleTypeMarker;)Z
     257: ifeq          269
     260: getstatic     #42                 // Field kotlin/reflect/jvm/internal/impl/types/TypeCheckerState$SupertypesPolicy$None.INSTANCE:Lkotlin/reflect/jvm/internal/impl/types/TypeCheckerState$SupertypesPolicy$None;
     263: checkcast     #29                 // class kotlin/reflect/jvm/internal/impl/types/TypeCheckerState$SupertypesPolicy
     266: goto          270
     269: aload_3
     270: astore        13
     272: aload         13
     274: astore        14
     276: iconst_0
     277: istore        15
     279: aload         14
     281: getstatic     #42                 // Field kotlin/reflect/jvm/internal/impl/types/TypeCheckerState$SupertypesPolicy$None.INSTANCE:Lkotlin/reflect/jvm/internal/impl/types/TypeCheckerState$SupertypesPolicy$None;
     284: invokestatic  #56                 // Method kotlin/jvm/internal/Intrinsics.areEqual:(Ljava/lang/Object;Ljava/lang/Object;)Z
     287: ifne          294
     290: iconst_1
     291: goto          295
     294: iconst_0
     295: ifeq          303
     298: aload         13
     300: goto          304
     303: aconst_null
     304: dup
     305: ifnonnull     312
     308: pop
     309: goto          123
     312: astore        16
     314: aload         6
     316: invokevirtual #68                 // Method kotlin/reflect/jvm/internal/impl/types/TypeCheckerState.getTypeSystemContext:()Lkotlin/reflect/jvm/internal/impl/types/model/TypeSystemContext;
     319: astore        14
     321: iconst_0
     322: istore        15
     324: aload         14
     326: aload         14
     328: aload         12
     330: invokeinterface #90,  2           // InterfaceMethod kotlin/reflect/jvm/internal/impl/types/model/TypeSystemContext.typeConstructor:(Lkotlin/reflect/jvm/internal/impl/types/model/SimpleTypeMarker;)Lkotlin/reflect/jvm/internal/impl/types/model/TypeConstructorMarker;
     335: invokeinterface #89,  2           // InterfaceMethod kotlin/reflect/jvm/internal/impl/types/model/TypeSystemContext.supertypes:(Lkotlin/reflect/jvm/internal/impl/types/model/TypeConstructorMarker;)Ljava/util/Collection;
     340: nop
     341: astore        17
     343: aload         17
     345: invokeinterface #74,  1           // InterfaceMethod java/util/Collection.iterator:()Ljava/util/Iterator;
     350: astore        13
     352: aload         13
     354: invokeinterface #75,  1           // InterfaceMethod java/util/Iterator.hasNext:()Z
     359: ifeq          123
     362: aload         13
     364: invokeinterface #76,  1           // InterfaceMethod java/util/Iterator.next:()Ljava/lang/Object;
     369: checkcast     #34                 // class kotlin/reflect/jvm/internal/impl/types/model/KotlinTypeMarker
     372: astore        14
     374: aload         16
     376: aload         6
     378: aload         14
     380: invokevirtual #72                 // Method kotlin/reflect/jvm/internal/impl/types/TypeCheckerState$SupertypesPolicy.transformType:(Lkotlin/reflect/jvm/internal/impl/types/TypeCheckerState;Lkotlin/reflect/jvm/internal/impl/types/model/KotlinTypeMarker;)Lkotlin/reflect/jvm/internal/impl/types/model/SimpleTypeMarker;
     383: astore        15
     385: aload         15
     387: astore        8
     389: iconst_0
     390: istore        9
     392: aload         4
     394: aload         8
     396: invokeinterface #80,  2           // InterfaceMethod kotlin/reflect/jvm/internal/impl/types/model/TypeSystemContext.isClassType:(Lkotlin/reflect/jvm/internal/impl/types/model/SimpleTypeMarker;)Z
     401: ifeq          416
     404: aload         4
     406: aload         8
     408: invokeinterface #83,  2           // InterfaceMethod kotlin/reflect/jvm/internal/impl/types/model/TypeSystemContext.isMarkedNullable:(Lkotlin/reflect/jvm/internal/impl/types/model/SimpleTypeMarker;)Z
     413: ifeq          431
     416: aload         4
     418: aload         8
     420: checkcast     #34                 // class kotlin/reflect/jvm/internal/impl/types/model/KotlinTypeMarker
     423: invokeinterface #81,  2           // InterfaceMethod kotlin/reflect/jvm/internal/impl/types/model/TypeSystemContext.isDefinitelyNotNullType:(Lkotlin/reflect/jvm/internal/impl/types/model/KotlinTypeMarker;)Z
     428: ifeq          435
     431: iconst_1
     432: goto          436
     435: iconst_0
     436: ifeq          448
     439: aload         6
     441: invokevirtual #65                 // Method kotlin/reflect/jvm/internal/impl/types/TypeCheckerState.clear:()V
     444: iconst_1
     445: goto          465
     448: aload         10
     450: aload         15
     452: invokevirtual #52                 // Method java/util/ArrayDeque.add:(Ljava/lang/Object;)Z
     455: pop
     456: goto          352
     459: aload         6
     461: invokevirtual #65                 // Method kotlin/reflect/jvm/internal/impl/types/TypeCheckerState.clear:()V
     464: iconst_0
     465: nop
     466: nop
     467: ireturn

  public final boolean hasPathByNotMarkedNullableNodes(kotlin.reflect.jvm.internal.impl.types.TypeCheckerState, kotlin.reflect.jvm.internal.impl.types.model.SimpleTypeMarker, kotlin.reflect.jvm.internal.impl.types.model.TypeConstructorMarker);
    Code:
       0: aload_1
       1: ldc           #9                  // String state
       3: invokestatic  #59                 // Method kotlin/jvm/internal/Intrinsics.checkNotNullParameter:(Ljava/lang/Object;Ljava/lang/String;)V
       6: aload_2
       7: ldc           #8                  // String start
       9: invokestatic  #59                 // Method kotlin/jvm/internal/Intrinsics.checkNotNullParameter:(Ljava/lang/Object;Ljava/lang/String;)V
      12: aload_3
      13: ldc           #7                  // String end
      15: invokestatic  #59                 // Method kotlin/jvm/internal/Intrinsics.checkNotNullParameter:(Ljava/lang/Object;Ljava/lang/String;)V
      18: aload_1
      19: invokevirtual #68                 // Method kotlin/reflect/jvm/internal/impl/types/TypeCheckerState.getTypeSystemContext:()Lkotlin/reflect/jvm/internal/impl/types/model/TypeSystemContext;
      22: astore        4
      24: iconst_0
      25: istore        5
      27: aload_1
      28: astore        6
      30: iconst_0
      31: istore        7
      33: aload_2
      34: astore        8
      36: iconst_0
      37: istore        9
      39: getstatic     #39                 // Field INSTANCE:Lkotlin/reflect/jvm/internal/impl/types/AbstractNullabilityChecker;
      42: aload_1
      43: aload         8
      45: aload_3
      46: invokespecial #63                 // Method isApplicableAsEndNode:(Lkotlin/reflect/jvm/internal/impl/types/TypeCheckerState;Lkotlin/reflect/jvm/internal/impl/types/model/SimpleTypeMarker;Lkotlin/reflect/jvm/internal/impl/types/model/TypeConstructorMarker;)Z
      49: ifeq          56
      52: iconst_1
      53: goto          402
      56: aload         6
      58: invokevirtual #69                 // Method kotlin/reflect/jvm/internal/impl/types/TypeCheckerState.initialize:()V
      61: aload         6
      63: invokevirtual #66                 // Method kotlin/reflect/jvm/internal/impl/types/TypeCheckerState.getSupertypesDeque:()Ljava/util/ArrayDeque;
      66: dup
      67: invokestatic  #57                 // Method kotlin/jvm/internal/Intrinsics.checkNotNull:(Ljava/lang/Object;)V
      70: astore        10
      72: aload         6
      74: invokevirtual #67                 // Method kotlin/reflect/jvm/internal/impl/types/TypeCheckerState.getSupertypesSet:()Ljava/util/Set;
      77: dup
      78: invokestatic  #57                 // Method kotlin/jvm/internal/Intrinsics.checkNotNull:(Ljava/lang/Object;)V
      81: astore        11
      83: aload         10
      85: aload_2
      86: invokevirtual #54                 // Method java/util/ArrayDeque.push:(Ljava/lang/Object;)V
      89: aload         10
      91: checkcast     #20                 // class java/util/Collection
      94: invokeinterface #73,  1           // InterfaceMethod java/util/Collection.isEmpty:()Z
      99: ifne          106
     102: iconst_1
     103: goto          107
     106: iconst_0
     107: ifeq          396
     110: aload         11
     112: invokeinterface #78,  1           // InterfaceMethod java/util/Set.size:()I
     117: sipush        1000
     120: if_icmple     178
     123: new           #15                 // class java/lang/IllegalStateException
     126: dup
     127: new           #18                 // class java/lang/StringBuilder
     130: dup
     131: invokespecial #48                 // Method java/lang/StringBuilder."<init>":()V
     134: ldc           #5                  // String Too many supertypes for type:
     136: invokevirtual #50                 // Method java/lang/StringBuilder.append:(Ljava/lang/String;)Ljava/lang/StringBuilder;
     139: aload_2
     140: invokevirtual #49                 // Method java/lang/StringBuilder.append:(Ljava/lang/Object;)Ljava/lang/StringBuilder;
     143: ldc           #1                  // String . Supertypes =
     145: invokevirtual #50                 // Method java/lang/StringBuilder.append:(Ljava/lang/String;)Ljava/lang/StringBuilder;
     148: aload         11
     150: checkcast     #16                 // class java/lang/Iterable
     153: aconst_null
     154: aconst_null
     155: aconst_null
     156: iconst_0
     157: aconst_null
     158: aconst_null
     159: bipush        63
     161: aconst_null
     162: invokestatic  #55                 // Method kotlin/collections/CollectionsKt.joinToString$default:(Ljava/lang/Iterable;Ljava/lang/CharSequence;Ljava/lang/CharSequence;Ljava/lang/CharSequence;ILjava/lang/CharSequence;Lkotlin/jvm/functions/Function1;ILjava/lang/Object;)Ljava/lang/String;
     165: invokevirtual #50                 // Method java/lang/StringBuilder.append:(Ljava/lang/String;)Ljava/lang/StringBuilder;
     168: invokevirtual #51                 // Method java/lang/StringBuilder.toString:()Ljava/lang/String;
     171: invokevirtual #47                 // Method java/lang/Object.toString:()Ljava/lang/String;
     174: invokespecial #45                 // Method java/lang/IllegalStateException."<init>":(Ljava/lang/String;)V
     177: athrow
     178: aload         10
     180: invokevirtual #53                 // Method java/util/ArrayDeque.pop:()Ljava/lang/Object;
     183: checkcast     #35                 // class kotlin/reflect/jvm/internal/impl/types/model/SimpleTypeMarker
     186: astore        12
     188: aload         11
     190: aload         12
     192: ldc           #6                  // String current
     194: invokestatic  #58                 // Method kotlin/jvm/internal/Intrinsics.checkNotNullExpressionValue:(Ljava/lang/Object;Ljava/lang/String;)V
     197: aload         12
     199: invokeinterface #77,  2           // InterfaceMethod java/util/Set.add:(Ljava/lang/Object;)Z
     204: ifeq          89
     207: aload         12
     209: astore        8
     211: iconst_0
     212: istore        9
     214: aload         4
     216: aload         8
     218: invokeinterface #83,  2           // InterfaceMethod kotlin/reflect/jvm/internal/impl/types/model/TypeSystemContext.isMarkedNullable:(Lkotlin/reflect/jvm/internal/impl/types/model/SimpleTypeMarker;)Z
     223: ifeq          235
     226: getstatic     #42                 // Field kotlin/reflect/jvm/internal/impl/types/TypeCheckerState$SupertypesPolicy$None.INSTANCE:Lkotlin/reflect/jvm/internal/impl/types/TypeCheckerState$SupertypesPolicy$None;
     229: checkcast     #29                 // class kotlin/reflect/jvm/internal/impl/types/TypeCheckerState$SupertypesPolicy
     232: goto          241
     235: getstatic     #41                 // Field kotlin/reflect/jvm/internal/impl/types/TypeCheckerState$SupertypesPolicy$LowerIfFlexible.INSTANCE:Lkotlin/reflect/jvm/internal/impl/types/TypeCheckerState$SupertypesPolicy$LowerIfFlexible;
     238: checkcast     #29                 // class kotlin/reflect/jvm/internal/impl/types/TypeCheckerState$SupertypesPolicy
     241: astore        13
     243: aload         13
     245: astore        14
     247: iconst_0
     248: istore        15
     250: aload         14
     252: getstatic     #42                 // Field kotlin/reflect/jvm/internal/impl/types/TypeCheckerState$SupertypesPolicy$None.INSTANCE:Lkotlin/reflect/jvm/internal/impl/types/TypeCheckerState$SupertypesPolicy$None;
     255: invokestatic  #56                 // Method kotlin/jvm/internal/Intrinsics.areEqual:(Ljava/lang/Object;Ljava/lang/Object;)Z
     258: ifne          265
     261: iconst_1
     262: goto          266
     265: iconst_0
     266: ifeq          274
     269: aload         13
     271: goto          275
     274: aconst_null
     275: dup
     276: ifnonnull     283
     279: pop
     280: goto          89
     283: astore        16
     285: aload         6
     287: invokevirtual #68                 // Method kotlin/reflect/jvm/internal/impl/types/TypeCheckerState.getTypeSystemContext:()Lkotlin/reflect/jvm/internal/impl/types/model/TypeSystemContext;
     290: astore        14
     292: iconst_0
     293: istore        15
     295: aload         14
     297: aload         14
     299: aload         12
     301: invokeinterface #90,  2           // InterfaceMethod kotlin/reflect/jvm/internal/impl/types/model/TypeSystemContext.typeConstructor:(Lkotlin/reflect/jvm/internal/impl/types/model/SimpleTypeMarker;)Lkotlin/reflect/jvm/internal/impl/types/model/TypeConstructorMarker;
     306: invokeinterface #89,  2           // InterfaceMethod kotlin/reflect/jvm/internal/impl/types/model/TypeSystemContext.supertypes:(Lkotlin/reflect/jvm/internal/impl/types/model/TypeConstructorMarker;)Ljava/util/Collection;
     311: nop
     312: astore        17
     314: aload         17
     316: invokeinterface #74,  1           // InterfaceMethod java/util/Collection.iterator:()Ljava/util/Iterator;
     321: astore        13
     323: aload         13
     325: invokeinterface #75,  1           // InterfaceMethod java/util/Iterator.hasNext:()Z
     330: ifeq          89
     333: aload         13
     335: invokeinterface #76,  1           // InterfaceMethod java/util/Iterator.next:()Ljava/lang/Object;
     340: checkcast     #34                 // class kotlin/reflect/jvm/internal/impl/types/model/KotlinTypeMarker
     343: astore        14
     345: aload         16
     347: aload         6
     349: aload         14
     351: invokevirtual #72                 // Method kotlin/reflect/jvm/internal/impl/types/TypeCheckerState$SupertypesPolicy.transformType:(Lkotlin/reflect/jvm/internal/impl/types/TypeCheckerState;Lkotlin/reflect/jvm/internal/impl/types/model/KotlinTypeMarker;)Lkotlin/reflect/jvm/internal/impl/types/model/SimpleTypeMarker;
     354: astore        15
     356: aload         15
     358: astore        8
     360: iconst_0
     361: istore        9
     363: getstatic     #39                 // Field INSTANCE:Lkotlin/reflect/jvm/internal/impl/types/AbstractNullabilityChecker;
     366: aload_1
     367: aload         8
     369: aload_3
     370: invokespecial #63                 // Method isApplicableAsEndNode:(Lkotlin/reflect/jvm/internal/impl/types/TypeCheckerState;Lkotlin/reflect/jvm/internal/impl/types/model/SimpleTypeMarker;Lkotlin/reflect/jvm/internal/impl/types/model/TypeConstructorMarker;)Z
     373: ifeq          385
     376: aload         6
     378: invokevirtual #65                 // Method kotlin/reflect/jvm/internal/impl/types/TypeCheckerState.clear:()V
     381: iconst_1
     382: goto          402
     385: aload         10
     387: aload         15
     389: invokevirtual #52                 // Method java/util/ArrayDeque.add:(Ljava/lang/Object;)Z
     392: pop
     393: goto          323
     396: aload         6
     398: invokevirtual #65                 // Method kotlin/reflect/jvm/internal/impl/types/TypeCheckerState.clear:()V
     401: iconst_0
     402: nop
     403: nop
     404: ireturn

  private final boolean isApplicableAsEndNode(kotlin.reflect.jvm.internal.impl.types.TypeCheckerState, kotlin.reflect.jvm.internal.impl.types.model.SimpleTypeMarker, kotlin.reflect.jvm.internal.impl.types.model.TypeConstructorMarker);
    Code:
       0: aload_1
       1: invokevirtual #68                 // Method kotlin/reflect/jvm/internal/impl/types/TypeCheckerState.getTypeSystemContext:()Lkotlin/reflect/jvm/internal/impl/types/model/TypeSystemContext;
       4: astore        4
       6: iconst_0
       7: istore        5
       9: aload         4
      11: aload_2
      12: checkcast     #34                 // class kotlin/reflect/jvm/internal/impl/types/model/KotlinTypeMarker
      15: invokeinterface #85,  2           // InterfaceMethod kotlin/reflect/jvm/internal/impl/types/model/TypeSystemContext.isNothing:(Lkotlin/reflect/jvm/internal/impl/types/model/KotlinTypeMarker;)Z
      20: ifeq          25
      23: iconst_1
      24: ireturn
      25: aload         4
      27: aload_2
      28: invokeinterface #83,  2           // InterfaceMethod kotlin/reflect/jvm/internal/impl/types/model/TypeSystemContext.isMarkedNullable:(Lkotlin/reflect/jvm/internal/impl/types/model/SimpleTypeMarker;)Z
      33: ifeq          38
      36: iconst_0
      37: ireturn
      38: aload_1
      39: invokevirtual #71                 // Method kotlin/reflect/jvm/internal/impl/types/TypeCheckerState.isStubTypeEqualsToAnything:()Z
      42: ifeq          58
      45: aload         4
      47: aload_2
      48: invokeinterface #88,  2           // InterfaceMethod kotlin/reflect/jvm/internal/impl/types/model/TypeSystemContext.isStubType:(Lkotlin/reflect/jvm/internal/impl/types/model/SimpleTypeMarker;)Z
      53: ifeq          58
      56: iconst_1
      57: ireturn
      58: aload         4
      60: aload         4
      62: aload_2
      63: invokeinterface #90,  2           // InterfaceMethod kotlin/reflect/jvm/internal/impl/types/model/TypeSystemContext.typeConstructor:(Lkotlin/reflect/jvm/internal/impl/types/model/SimpleTypeMarker;)Lkotlin/reflect/jvm/internal/impl/types/model/TypeConstructorMarker;
      68: aload_3
      69: invokeinterface #79,  3           // InterfaceMethod kotlin/reflect/jvm/internal/impl/types/model/TypeSystemContext.areEqualTypeConstructors:(Lkotlin/reflect/jvm/internal/impl/types/model/TypeConstructorMarker;Lkotlin/reflect/jvm/internal/impl/types/model/TypeConstructorMarker;)Z
      74: ireturn

  static {};
    Code:
       0: new           #26                 // class kotlin/reflect/jvm/internal/impl/types/AbstractNullabilityChecker
       3: dup
       4: invokespecial #60                 // Method "<init>":()V
       7: putstatic     #39                 // Field INSTANCE:Lkotlin/reflect/jvm/internal/impl/types/AbstractNullabilityChecker;
      10: return
}
