Compiled from "AnnotationsTypeAttribute.kt"
public final class kotlin.reflect.jvm.internal.impl.types.AnnotationsTypeAttribute extends kotlin.reflect.jvm.internal.impl.types.TypeAttribute<kotlin.reflect.jvm.internal.impl.types.AnnotationsTypeAttribute> {
  private final kotlin.reflect.jvm.internal.impl.descriptors.annotations.Annotations annotations;

  public kotlin.reflect.jvm.internal.impl.types.AnnotationsTypeAttribute(kotlin.reflect.jvm.internal.impl.descriptors.annotations.Annotations);
    Code:
       0: aload_1
       1: ldc           #1                  // String annotations
       3: invokestatic  #11                 // Method kotlin/jvm/internal/Intrinsics.checkNotNullParameter:(Ljava/lang/Object;Ljava/lang/String;)V
       6: aload_0
       7: invokespecial #17                 // Method kotlin/reflect/jvm/internal/impl/types/TypeAttribute."<init>":()V
      10: aload_0
      11: aload_1
      12: putfield      #8                  // Field annotations:Lkotlin/reflect/jvm/internal/impl/descriptors/annotations/Annotations;
      15: return

  public final kotlin.reflect.jvm.internal.impl.descriptors.annotations.Annotations getAnnotations();
    Code:
       0: aload_0
       1: getfield      #8                  // Field annotations:Lkotlin/reflect/jvm/internal/impl/descriptors/annotations/Annotations;
       4: areturn

  public kotlin.reflect.jvm.internal.impl.types.AnnotationsTypeAttribute intersect(kotlin.reflect.jvm.internal.impl.types.AnnotationsTypeAttribute);
    Code:
       0: aload_1
       1: aload_0
       2: invokestatic  #10                 // Method kotlin/jvm/internal/Intrinsics.areEqual:(Ljava/lang/Object;Ljava/lang/Object;)Z
       5: ifeq          12
       8: aload_0
       9: goto          13
      12: aconst_null
      13: areturn

  public kotlin.reflect.jvm.internal.impl.types.AnnotationsTypeAttribute add(kotlin.reflect.jvm.internal.impl.types.AnnotationsTypeAttribute);
    Code:
       0: aload_1
       1: ifnonnull     6
       4: aload_0
       5: areturn
       6: new           #6                  // class kotlin/reflect/jvm/internal/impl/types/AnnotationsTypeAttribute
       9: dup
      10: aload_0
      11: getfield      #8                  // Field annotations:Lkotlin/reflect/jvm/internal/impl/descriptors/annotations/Annotations;
      14: aload_1
      15: getfield      #8                  // Field annotations:Lkotlin/reflect/jvm/internal/impl/descriptors/annotations/Annotations;
      18: invokestatic  #13                 // Method kotlin/reflect/jvm/internal/impl/descriptors/annotations/AnnotationsKt.composeAnnotations:(Lkotlin/reflect/jvm/internal/impl/descriptors/annotations/Annotations;Lkotlin/reflect/jvm/internal/impl/descriptors/annotations/Annotations;)Lkotlin/reflect/jvm/internal/impl/descriptors/annotations/Annotations;
      21: invokespecial #14                 // Method "<init>":(Lkotlin/reflect/jvm/internal/impl/descriptors/annotations/Annotations;)V
      24: areturn

  public kotlin.reflect.KClass<? extends kotlin.reflect.jvm.internal.impl.types.AnnotationsTypeAttribute> getKey();
    Code:
       0: ldc           #6                  // class kotlin/reflect/jvm/internal/impl/types/AnnotationsTypeAttribute
       2: invokestatic  #12                 // Method kotlin/jvm/internal/Reflection.getOrCreateKotlinClass:(Ljava/lang/Class;)Lkotlin/reflect/KClass;
       5: areturn

  public boolean equals(java.lang.Object);
    Code:
       0: aload_1
       1: instanceof    #6                  // class kotlin/reflect/jvm/internal/impl/types/AnnotationsTypeAttribute
       4: ifne          9
       7: iconst_0
       8: ireturn
       9: aload_1
      10: checkcast     #6                  // class kotlin/reflect/jvm/internal/impl/types/AnnotationsTypeAttribute
      13: getfield      #8                  // Field annotations:Lkotlin/reflect/jvm/internal/impl/descriptors/annotations/Annotations;
      16: aload_0
      17: getfield      #8                  // Field annotations:Lkotlin/reflect/jvm/internal/impl/descriptors/annotations/Annotations;
      20: invokestatic  #10                 // Method kotlin/jvm/internal/Intrinsics.areEqual:(Ljava/lang/Object;Ljava/lang/Object;)Z
      23: ireturn

  public int hashCode();
    Code:
       0: aload_0
       1: getfield      #8                  // Field annotations:Lkotlin/reflect/jvm/internal/impl/descriptors/annotations/Annotations;
       4: invokevirtual #9                  // Method java/lang/Object.hashCode:()I
       7: ireturn

  public kotlin.reflect.jvm.internal.impl.types.TypeAttribute intersect(kotlin.reflect.jvm.internal.impl.types.TypeAttribute);
    Code:
       0: aload_0
       1: aload_1
       2: checkcast     #6                  // class kotlin/reflect/jvm/internal/impl/types/AnnotationsTypeAttribute
       5: invokevirtual #16                 // Method intersect:(Lkotlin/reflect/jvm/internal/impl/types/AnnotationsTypeAttribute;)Lkotlin/reflect/jvm/internal/impl/types/AnnotationsTypeAttribute;
       8: checkcast     #7                  // class kotlin/reflect/jvm/internal/impl/types/TypeAttribute
      11: areturn

  public kotlin.reflect.jvm.internal.impl.types.TypeAttribute add(kotlin.reflect.jvm.internal.impl.types.TypeAttribute);
    Code:
       0: aload_0
       1: aload_1
       2: checkcast     #6                  // class kotlin/reflect/jvm/internal/impl/types/AnnotationsTypeAttribute
       5: invokevirtual #15                 // Method add:(Lkotlin/reflect/jvm/internal/impl/types/AnnotationsTypeAttribute;)Lkotlin/reflect/jvm/internal/impl/types/AnnotationsTypeAttribute;
       8: checkcast     #7                  // class kotlin/reflect/jvm/internal/impl/types/TypeAttribute
      11: areturn
}
