Compiled from "AnnotationsTypeAttribute.kt"
public final class kotlin.reflect.jvm.internal.impl.types.AnnotationsTypeAttributeKt {
  static final kotlin.reflect.KProperty<java.lang.Object>[] $$delegatedProperties;

  private static final kotlin.properties.ReadOnlyProperty annotationsAttribute$delegate;

  public static final kotlin.reflect.jvm.internal.impl.types.AnnotationsTypeAttribute getAnnotationsAttribute(kotlin.reflect.jvm.internal.impl.types.TypeAttributes);
    Code:
       0: aload_0
       1: ldc           #1                  // String <this>
       3: invokestatic  #24                 // Method kotlin/jvm/internal/Intrinsics.checkNotNullParameter:(Ljava/lang/Object;Ljava/lang/String;)V
       6: getstatic     #21                 // Field annotationsAttribute$delegate:Lkotlin/properties/ReadOnlyProperty;
       9: aload_0
      10: getstatic     #20                 // Field $$delegatedProperties:[Lkotlin/reflect/KProperty;
      13: iconst_0
      14: aaload
      15: invokeinterface #33,  3           // InterfaceMethod kotlin/properties/ReadOnlyProperty.getValue:(Ljava/lang/Object;Lkotlin/reflect/KProperty;)Ljava/lang/Object;
      20: checkcast     #15                 // class kotlin/reflect/jvm/internal/impl/types/AnnotationsTypeAttribute
      23: areturn

  public static final kotlin.reflect.jvm.internal.impl.descriptors.annotations.Annotations getAnnotations(kotlin.reflect.jvm.internal.impl.types.TypeAttributes);
    Code:
       0: aload_0
       1: ldc           #1                  // String <this>
       3: invokestatic  #24                 // Method kotlin/jvm/internal/Intrinsics.checkNotNullParameter:(Ljava/lang/Object;Ljava/lang/String;)V
       6: aload_0
       7: invokestatic  #31                 // Method getAnnotationsAttribute:(Lkotlin/reflect/jvm/internal/impl/types/TypeAttributes;)Lkotlin/reflect/jvm/internal/impl/types/AnnotationsTypeAttribute;
      10: dup
      11: ifnull        21
      14: invokevirtual #30                 // Method kotlin/reflect/jvm/internal/impl/types/AnnotationsTypeAttribute.getAnnotations:()Lkotlin/reflect/jvm/internal/impl/descriptors/annotations/Annotations;
      17: dup
      18: ifnonnull     28
      21: pop
      22: getstatic     #19                 // Field kotlin/reflect/jvm/internal/impl/descriptors/annotations/Annotations.Companion:Lkotlin/reflect/jvm/internal/impl/descriptors/annotations/Annotations$Companion;
      25: invokevirtual #29                 // Method kotlin/reflect/jvm/internal/impl/descriptors/annotations/Annotations$Companion.getEMPTY:()Lkotlin/reflect/jvm/internal/impl/descriptors/annotations/Annotations;
      28: areturn

  static {};
    Code:
       0: iconst_1
       1: anewarray     #12                 // class kotlin/reflect/KProperty
       4: astore_0
       5: aload_0
       6: iconst_0
       7: new           #9                  // class kotlin/jvm/internal/PropertyReference1Impl
      10: dup
      11: ldc           #16                 // class kotlin/reflect/jvm/internal/impl/types/AnnotationsTypeAttributeKt
      13: ldc           #3                  // String descriptors
      15: invokestatic  #27                 // Method kotlin/jvm/internal/Reflection.getOrCreateKotlinPackage:(Ljava/lang/Class;Ljava/lang/String;)Lkotlin/reflect/KDeclarationContainer;
      18: ldc           #2                  // String annotationsAttribute
      20: ldc           #4                  // String getAnnotationsAttribute(Lorg/jetbrains/kotlin/types/TypeAttributes;)Lorg/jetbrains/kotlin/types/AnnotationsTypeAttribute;
      22: invokespecial #25                 // Method kotlin/jvm/internal/PropertyReference1Impl."<init>":(Lkotlin/reflect/KDeclarationContainer;Ljava/lang/String;Ljava/lang/String;)V
      25: checkcast     #8                  // class kotlin/jvm/internal/PropertyReference1
      28: invokestatic  #28                 // Method kotlin/jvm/internal/Reflection.property1:(Lkotlin/jvm/internal/PropertyReference1;)Lkotlin/reflect/KProperty1;
      31: aastore
      32: aload_0
      33: putstatic     #20                 // Field $$delegatedProperties:[Lkotlin/reflect/KProperty;
      36: getstatic     #22                 // Field kotlin/reflect/jvm/internal/impl/types/TypeAttributes.Companion:Lkotlin/reflect/jvm/internal/impl/types/TypeAttributes$Companion;
      39: astore_0
      40: iconst_0
      41: istore_1
      42: aload_0
      43: ldc           #15                 // class kotlin/reflect/jvm/internal/impl/types/AnnotationsTypeAttribute
      45: invokestatic  #26                 // Method kotlin/jvm/internal/Reflection.getOrCreateKotlinClass:(Ljava/lang/Class;)Lkotlin/reflect/KClass;
      48: invokevirtual #32                 // Method kotlin/reflect/jvm/internal/impl/types/TypeAttributes$Companion.generateNullableAccessor:(Lkotlin/reflect/KClass;)Lkotlin/reflect/jvm/internal/impl/util/NullableArrayMapAccessor;
      51: dup
      52: ldc           #5                  // String null cannot be cast to non-null type kotlin.properties.ReadOnlyProperty<org.jetbrains.kotlin.types.TypeAttributes, T of org.jetbrains.kotlin.types.TypeAttributes.Companion.attributeAccessor?>
      54: invokestatic  #23                 // Method kotlin/jvm/internal/Intrinsics.checkNotNull:(Ljava/lang/Object;Ljava/lang/String;)V
      57: checkcast     #11                 // class kotlin/properties/ReadOnlyProperty
      60: putstatic     #21                 // Field annotationsAttribute$delegate:Lkotlin/properties/ReadOnlyProperty;
      63: return
}
