Compiled from "TypeSubstitution.kt"
public abstract class kotlin.reflect.jvm.internal.impl.types.TypeSubstitution {
  public static final kotlin.reflect.jvm.internal.impl.types.TypeSubstitution$Companion Companion;

  public static final kotlin.reflect.jvm.internal.impl.types.TypeSubstitution EMPTY;

  public kotlin.reflect.jvm.internal.impl.types.TypeSubstitution();
    Code:
       0: aload_0
       1: invokespecial #14                 // Method java/lang/Object."<init>":()V
       4: return

  public abstract kotlin.reflect.jvm.internal.impl.types.TypeProjection get(kotlin.reflect.jvm.internal.impl.types.KotlinType);

  public kotlin.reflect.jvm.internal.impl.types.KotlinType prepareTopLevelType(kotlin.reflect.jvm.internal.impl.types.KotlinType, kotlin.reflect.jvm.internal.impl.types.Variance);
    Code:
       0: aload_1
       1: ldc           #4                  // String topLevelType
       3: invokestatic  #16                 // Method kotlin/jvm/internal/Intrinsics.checkNotNullParameter:(Ljava/lang/Object;Ljava/lang/String;)V
       6: aload_2
       7: ldc           #3                  // String position
       9: invokestatic  #16                 // Method kotlin/jvm/internal/Intrinsics.checkNotNullParameter:(Ljava/lang/Object;Ljava/lang/String;)V
      12: aload_1
      13: areturn

  public boolean isEmpty();
    Code:
       0: iconst_0
       1: ireturn

  public boolean approximateCapturedTypes();
    Code:
       0: iconst_0
       1: ireturn

  public boolean approximateContravariantCapturedTypes();
    Code:
       0: iconst_0
       1: ireturn

  public kotlin.reflect.jvm.internal.impl.descriptors.annotations.Annotations filterAnnotations(kotlin.reflect.jvm.internal.impl.descriptors.annotations.Annotations);
    Code:
       0: aload_1
       1: ldc           #1                  // String annotations
       3: invokestatic  #16                 // Method kotlin/jvm/internal/Intrinsics.checkNotNullParameter:(Ljava/lang/Object;Ljava/lang/String;)V
       6: aload_1
       7: areturn

  public final kotlin.reflect.jvm.internal.impl.types.TypeSubstitutor buildSubstitutor();
    Code:
       0: aload_0
       1: invokestatic  #20                 // Method kotlin/reflect/jvm/internal/impl/types/TypeSubstitutor.create:(Lkotlin/reflect/jvm/internal/impl/types/TypeSubstitution;)Lkotlin/reflect/jvm/internal/impl/types/TypeSubstitutor;
       4: dup
       5: ldc           #2                  // String create(this)
       7: invokestatic  #15                 // Method kotlin/jvm/internal/Intrinsics.checkNotNullExpressionValue:(Ljava/lang/Object;Ljava/lang/String;)V
      10: areturn

  public final kotlin.reflect.jvm.internal.impl.types.TypeSubstitution replaceWithNonApproximating();
    Code:
       0: new           #10                 // class kotlin/reflect/jvm/internal/impl/types/TypeSubstitution$replaceWithNonApproximating$1
       3: dup
       4: aload_0
       5: invokespecial #19                 // Method kotlin/reflect/jvm/internal/impl/types/TypeSubstitution$replaceWithNonApproximating$1."<init>":(Lkotlin/reflect/jvm/internal/impl/types/TypeSubstitution;)V
       8: checkcast     #7                  // class kotlin/reflect/jvm/internal/impl/types/TypeSubstitution
      11: areturn

  static {};
    Code:
       0: new           #8                  // class kotlin/reflect/jvm/internal/impl/types/TypeSubstitution$Companion
       3: dup
       4: aconst_null
       5: invokespecial #17                 // Method kotlin/reflect/jvm/internal/impl/types/TypeSubstitution$Companion."<init>":(Lkotlin/jvm/internal/DefaultConstructorMarker;)V
       8: putstatic     #12                 // Field Companion:Lkotlin/reflect/jvm/internal/impl/types/TypeSubstitution$Companion;
      11: new           #9                  // class kotlin/reflect/jvm/internal/impl/types/TypeSubstitution$Companion$EMPTY$1
      14: dup
      15: invokespecial #18                 // Method kotlin/reflect/jvm/internal/impl/types/TypeSubstitution$Companion$EMPTY$1."<init>":()V
      18: checkcast     #7                  // class kotlin/reflect/jvm/internal/impl/types/TypeSubstitution
      21: putstatic     #13                 // Field EMPTY:Lkotlin/reflect/jvm/internal/impl/types/TypeSubstitution;
      24: return
}
