Compiled from "NettyServerConnection.java"
public class org.apache.activemq.artemis.core.remoting.impl.netty.NettyServerConnection extends org.apache.activemq.artemis.core.remoting.impl.netty.NettyConnection {
  public org.apache.activemq.artemis.core.remoting.impl.netty.NettyServerConnection(java.util.Map<java.lang.String, java.lang.Object>, io.netty.channel.Channel, org.apache.activemq.artemis.spi.core.remoting.ConnectionLifeCycleListener, boolean, boolean);
    Code:
       0: aload_0
       1: aload_1
       2: aload_2
       3: aload_3
       4: iload         4
       6: iload         5
       8: invokespecial #1                  // Method org/apache/activemq/artemis/core/remoting/impl/netty/NettyConnection."<init>":(Ljava/util/Map;Lio/netty/channel/Channel;Lorg/apache/activemq/artemis/spi/core/remoting/ConnectionLifeCycleListener;ZZ)V
      11: return

  public org.apache.activemq.artemis.api.core.ActiveMQBuffer createTransportBuffer(int);
    Code:
       0: new           #2                  // class org/apache/activemq/artemis/core/buffers/impl/ChannelBufferWrapper
       3: dup
       4: aload_0
       5: getfield      #3                  // Field channel:Lio/netty/channel/Channel;
       8: invokeinterface #4,  1            // InterfaceMethod io/netty/channel/Channel.alloc:()Lio/netty/buffer/ByteBufAllocator;
      13: iload_1
      14: invokeinterface #5,  2            // InterfaceMethod io/netty/buffer/ByteBufAllocator.directBuffer:(I)Lio/netty/buffer/ByteBuf;
      19: iconst_1
      20: invokespecial #6                  // Method org/apache/activemq/artemis/core/buffers/impl/ChannelBufferWrapper."<init>":(Lio/netty/buffer/ByteBuf;Z)V
      23: areturn
}
