Compiled from "PropertyChangeProxyTargetBinding.java"
public class org.codehaus.groovy.binding.PropertyChangeProxyTargetBinding implements org.codehaus.groovy.binding.TargetBinding {
  java.lang.Object proxyObject;

  java.lang.String propertyName;

  java.beans.PropertyChangeListener listener;

  public org.codehaus.groovy.binding.PropertyChangeProxyTargetBinding(java.lang.Object, java.lang.String, java.beans.PropertyChangeListener);
    Code:
       0: aload_0
       1: invokespecial #18                 // Method java/lang/Object."<init>":()V
       4: aload_0
       5: aload_1
       6: putfield      #20                 // Field proxyObject:Ljava/lang/Object;
       9: aload_0
      10: aload_2
      11: putfield      #22                 // Field propertyName:Ljava/lang/String;
      14: aload_0
      15: aload_3
      16: putfield      #24                 // Field listener:Ljava/beans/PropertyChangeListener;
      19: return

  public void updateTargetValue(java.lang.Object);
    Code:
       0: aload_0
       1: getfield      #24                 // Field listener:Ljava/beans/PropertyChangeListener;
       4: new           #30                 // class java/beans/PropertyChangeEvent
       7: dup
       8: aload_0
       9: getfield      #20                 // Field proxyObject:Ljava/lang/Object;
      12: aload_0
      13: getfield      #22                 // Field propertyName:Ljava/lang/String;
      16: aload_0
      17: getfield      #20                 // Field proxyObject:Ljava/lang/Object;
      20: aload_0
      21: getfield      #22                 // Field propertyName:Ljava/lang/String;
      24: invokestatic  #36                 // Method org/codehaus/groovy/runtime/InvokerHelper.getProperty:(Ljava/lang/Object;Ljava/lang/String;)Ljava/lang/Object;
      27: aload_1
      28: invokespecial #39                 // Method java/beans/PropertyChangeEvent."<init>":(Ljava/lang/Object;Ljava/lang/String;Ljava/lang/Object;Ljava/lang/Object;)V
      31: invokeinterface #45,  2           // InterfaceMethod java/beans/PropertyChangeListener.propertyChange:(Ljava/beans/PropertyChangeEvent;)V
      36: return
}
