Compiled from "CharacterPredicates.java"
final class org.apache.commons.text.CharacterPredicates$3 extends org.apache.commons.text.CharacterPredicates {
  org.apache.commons.text.CharacterPredicates$3(java.lang.String, int);
    Code:
       0: aload_0
       1: aload_1
       2: iload_2
       3: aconst_null
       4: invokespecial #1                  // Method org/apache/commons/text/CharacterPredicates."<init>":(Ljava/lang/String;ILorg/apache/commons/text/CharacterPredicates$1;)V
       7: return

  public boolean test(int);
    Code:
       0: iload_1
       1: bipush        48
       3: if_icmplt     16
       6: iload_1
       7: bipush        57
       9: if_icmpgt     16
      12: iconst_1
      13: goto          17
      16: iconst_0
      17: ireturn
}
