Compiled from "ProgramRunId.java"
public class co.cask.cdap.proto.id.ProgramRunId extends co.cask.cdap.proto.id.NamespacedEntityId implements co.cask.cdap.proto.id.ParentedId<co.cask.cdap.proto.id.ProgramId> {
  private final java.lang.String application;

  private final java.lang.String version;

  private final co.cask.cdap.proto.ProgramType type;

  private final java.lang.String program;

  private final java.lang.String run;

  private transient java.lang.Integer hashCode;

  public co.cask.cdap.proto.id.ProgramRunId(java.lang.String, java.lang.String, co.cask.cdap.proto.ProgramType, java.lang.String, java.lang.String);
    Code:
       0: aload_0
       1: new           #1                  // class co/cask/cdap/proto/id/ApplicationId
       4: dup
       5: aload_1
       6: aload_2
       7: invokespecial #2                  // Method co/cask/cdap/proto/id/ApplicationId."<init>":(Ljava/lang/String;Ljava/lang/String;)V
      10: aload_3
      11: aload         4
      13: aload         5
      15: invokespecial #3                  // Method "<init>":(Lco/cask/cdap/proto/id/ApplicationId;Lco/cask/cdap/proto/ProgramType;Ljava/lang/String;Ljava/lang/String;)V
      18: return

  public co.cask.cdap.proto.id.ProgramRunId(co.cask.cdap.proto.id.ApplicationId, co.cask.cdap.proto.ProgramType, java.lang.String, java.lang.String);
    Code:
       0: aload_0
       1: aload_1
       2: invokevirtual #4                  // Method co/cask/cdap/proto/id/ApplicationId.getNamespace:()Ljava/lang/String;
       5: getstatic     #5                  // Field co/cask/cdap/proto/element/EntityType.PROGRAM_RUN:Lco/cask/cdap/proto/element/EntityType;
       8: invokespecial #6                  // Method co/cask/cdap/proto/id/NamespacedEntityId."<init>":(Ljava/lang/String;Lco/cask/cdap/proto/element/EntityType;)V
      11: aload_2
      12: ifnonnull     25
      15: new           #7                  // class java/lang/NullPointerException
      18: dup
      19: ldc           #8                  // String Program type cannot be null.
      21: invokespecial #9                  // Method java/lang/NullPointerException."<init>":(Ljava/lang/String;)V
      24: athrow
      25: aload_3
      26: ifnonnull     39
      29: new           #7                  // class java/lang/NullPointerException
      32: dup
      33: ldc           #10                 // String Program ID cannot be null.
      35: invokespecial #9                  // Method java/lang/NullPointerException."<init>":(Ljava/lang/String;)V
      38: athrow
      39: aload         4
      41: ifnonnull     54
      44: new           #7                  // class java/lang/NullPointerException
      47: dup
      48: ldc           #11                 // String Run cannot be null.
      50: invokespecial #9                  // Method java/lang/NullPointerException."<init>":(Ljava/lang/String;)V
      53: athrow
      54: aload_0
      55: aload_1
      56: invokevirtual #12                 // Method co/cask/cdap/proto/id/ApplicationId.getApplication:()Ljava/lang/String;
      59: putfield      #13                 // Field application:Ljava/lang/String;
      62: aload_0
      63: aload_1
      64: invokevirtual #14                 // Method co/cask/cdap/proto/id/ApplicationId.getVersion:()Ljava/lang/String;
      67: putfield      #15                 // Field version:Ljava/lang/String;
      70: aload_0
      71: aload_2
      72: putfield      #16                 // Field type:Lco/cask/cdap/proto/ProgramType;
      75: aload_0
      76: aload_3
      77: putfield      #17                 // Field program:Ljava/lang/String;
      80: aload_0
      81: aload         4
      83: putfield      #18                 // Field run:Ljava/lang/String;
      86: return

  public java.lang.String getApplication();
    Code:
       0: aload_0
       1: getfield      #13                 // Field application:Ljava/lang/String;
       4: areturn

  public java.lang.String getVersion();
    Code:
       0: aload_0
       1: getfield      #15                 // Field version:Ljava/lang/String;
       4: areturn

  public co.cask.cdap.proto.ProgramType getType();
    Code:
       0: aload_0
       1: getfield      #16                 // Field type:Lco/cask/cdap/proto/ProgramType;
       4: areturn

  public java.lang.String getProgram();
    Code:
       0: aload_0
       1: getfield      #17                 // Field program:Ljava/lang/String;
       4: areturn

  public java.lang.String getEntityName();
    Code:
       0: aload_0
       1: getfield      #18                 // Field run:Ljava/lang/String;
       4: areturn

  public java.lang.String getRun();
    Code:
       0: aload_0
       1: getfield      #18                 // Field run:Ljava/lang/String;
       4: areturn

  public co.cask.cdap.proto.id.ProgramId getParent();
    Code:
       0: new           #19                 // class co/cask/cdap/proto/id/ProgramId
       3: dup
       4: new           #1                  // class co/cask/cdap/proto/id/ApplicationId
       7: dup
       8: aload_0
       9: invokevirtual #20                 // Method getNamespace:()Ljava/lang/String;
      12: aload_0
      13: invokevirtual #21                 // Method getApplication:()Ljava/lang/String;
      16: aload_0
      17: invokevirtual #22                 // Method getVersion:()Ljava/lang/String;
      20: invokespecial #23                 // Method co/cask/cdap/proto/id/ApplicationId."<init>":(Ljava/lang/String;Ljava/lang/String;Ljava/lang/String;)V
      23: aload_0
      24: invokevirtual #24                 // Method getType:()Lco/cask/cdap/proto/ProgramType;
      27: aload_0
      28: invokevirtual #25                 // Method getProgram:()Ljava/lang/String;
      31: invokespecial #26                 // Method co/cask/cdap/proto/id/ProgramId."<init>":(Lco/cask/cdap/proto/id/ApplicationId;Lco/cask/cdap/proto/ProgramType;Ljava/lang/String;)V
      34: areturn

  public boolean equals(java.lang.Object);
    Code:
       0: aload_0
       1: aload_1
       2: invokespecial #27                 // Method co/cask/cdap/proto/id/NamespacedEntityId.equals:(Ljava/lang/Object;)Z
       5: ifne          10
       8: iconst_0
       9: ireturn
      10: aload_1
      11: checkcast     #28                 // class co/cask/cdap/proto/id/ProgramRunId
      14: astore_2
      15: aload_0
      16: invokevirtual #29                 // Method getParent:()Lco/cask/cdap/proto/id/ProgramId;
      19: aload_2
      20: invokevirtual #29                 // Method getParent:()Lco/cask/cdap/proto/id/ProgramId;
      23: invokestatic  #30                 // Method java/util/Objects.equals:(Ljava/lang/Object;Ljava/lang/Object;)Z
      26: ifeq          47
      29: aload_0
      30: getfield      #18                 // Field run:Ljava/lang/String;
      33: aload_2
      34: getfield      #18                 // Field run:Ljava/lang/String;
      37: invokestatic  #30                 // Method java/util/Objects.equals:(Ljava/lang/Object;Ljava/lang/Object;)Z
      40: ifeq          47
      43: iconst_1
      44: goto          48
      47: iconst_0
      48: ireturn

  public int hashCode();
    Code:
       0: aload_0
       1: getfield      #31                 // Field hashCode:Ljava/lang/Integer;
       4: astore_1
       5: aload_1
       6: ifnonnull     79
       9: aload_0
      10: bipush        7
      12: anewarray     #32                 // class java/lang/Object
      15: dup
      16: iconst_0
      17: aload_0
      18: invokespecial #33                 // Method co/cask/cdap/proto/id/NamespacedEntityId.hashCode:()I
      21: invokestatic  #34                 // Method java/lang/Integer.valueOf:(I)Ljava/lang/Integer;
      24: aastore
      25: dup
      26: iconst_1
      27: aload_0
      28: invokevirtual #20                 // Method getNamespace:()Ljava/lang/String;
      31: aastore
      32: dup
      33: iconst_2
      34: aload_0
      35: invokevirtual #21                 // Method getApplication:()Ljava/lang/String;
      38: aastore
      39: dup
      40: iconst_3
      41: aload_0
      42: invokevirtual #22                 // Method getVersion:()Ljava/lang/String;
      45: aastore
      46: dup
      47: iconst_4
      48: aload_0
      49: invokevirtual #24                 // Method getType:()Lco/cask/cdap/proto/ProgramType;
      52: aastore
      53: dup
      54: iconst_5
      55: aload_0
      56: invokevirtual #25                 // Method getProgram:()Ljava/lang/String;
      59: aastore
      60: dup
      61: bipush        6
      63: aload_0
      64: getfield      #18                 // Field run:Ljava/lang/String;
      67: aastore
      68: invokestatic  #35                 // Method java/util/Objects.hash:([Ljava/lang/Object;)I
      71: invokestatic  #34                 // Method java/lang/Integer.valueOf:(I)Ljava/lang/Integer;
      74: dup
      75: astore_1
      76: putfield      #31                 // Field hashCode:Ljava/lang/Integer;
      79: aload_1
      80: invokevirtual #36                 // Method java/lang/Integer.intValue:()I
      83: ireturn

  public co.cask.cdap.proto.Id$Run toId();
    Code:
       0: new           #37                 // class co/cask/cdap/proto/Id$Run
       3: dup
       4: aload_0
       5: invokevirtual #20                 // Method getNamespace:()Ljava/lang/String;
       8: aload_0
       9: invokevirtual #21                 // Method getApplication:()Ljava/lang/String;
      12: aload_0
      13: invokevirtual #24                 // Method getType:()Lco/cask/cdap/proto/ProgramType;
      16: aload_0
      17: invokevirtual #25                 // Method getProgram:()Ljava/lang/String;
      20: invokestatic  #38                 // Method co/cask/cdap/proto/Id$Program.from:(Ljava/lang/String;Ljava/lang/String;Lco/cask/cdap/proto/ProgramType;Ljava/lang/String;)Lco/cask/cdap/proto/Id$Program;
      23: aload_0
      24: getfield      #18                 // Field run:Ljava/lang/String;
      27: invokespecial #39                 // Method co/cask/cdap/proto/Id$Run."<init>":(Lco/cask/cdap/proto/Id$Program;Ljava/lang/String;)V
      30: areturn

  public static co.cask.cdap.proto.id.ProgramRunId fromIdParts(java.lang.Iterable<java.lang.String>);
    Code:
       0: aload_0
       1: invokeinterface #40,  1           // InterfaceMethod java/lang/Iterable.iterator:()Ljava/util/Iterator;
       6: astore_1
       7: new           #28                 // class co/cask/cdap/proto/id/ProgramRunId
      10: dup
      11: new           #1                  // class co/cask/cdap/proto/id/ApplicationId
      14: dup
      15: aload_1
      16: ldc           #41                 // String namespace
      18: invokestatic  #42                 // Method next:(Ljava/util/Iterator;Ljava/lang/String;)Ljava/lang/String;
      21: aload_1
      22: ldc           #43                 // String application
      24: invokestatic  #42                 // Method next:(Ljava/util/Iterator;Ljava/lang/String;)Ljava/lang/String;
      27: aload_1
      28: ldc           #44                 // String version
      30: invokestatic  #42                 // Method next:(Ljava/util/Iterator;Ljava/lang/String;)Ljava/lang/String;
      33: invokespecial #23                 // Method co/cask/cdap/proto/id/ApplicationId."<init>":(Ljava/lang/String;Ljava/lang/String;Ljava/lang/String;)V
      36: aload_1
      37: ldc           #45                 // String type
      39: invokestatic  #42                 // Method next:(Ljava/util/Iterator;Ljava/lang/String;)Ljava/lang/String;
      42: invokestatic  #46                 // Method co/cask/cdap/proto/ProgramType.valueOfPrettyName:(Ljava/lang/String;)Lco/cask/cdap/proto/ProgramType;
      45: aload_1
      46: ldc           #47                 // String program
      48: invokestatic  #42                 // Method next:(Ljava/util/Iterator;Ljava/lang/String;)Ljava/lang/String;
      51: aload_1
      52: ldc           #48                 // String run
      54: invokestatic  #49                 // Method nextAndEnd:(Ljava/util/Iterator;Ljava/lang/String;)Ljava/lang/String;
      57: invokespecial #3                  // Method "<init>":(Lco/cask/cdap/proto/id/ApplicationId;Lco/cask/cdap/proto/ProgramType;Ljava/lang/String;Ljava/lang/String;)V
      60: areturn

  protected java.lang.Iterable<java.lang.String> toIdParts();
    Code:
       0: bipush        6
       2: anewarray     #50                 // class java/lang/String
       5: dup
       6: iconst_0
       7: aload_0
       8: invokevirtual #20                 // Method getNamespace:()Ljava/lang/String;
      11: aastore
      12: dup
      13: iconst_1
      14: aload_0
      15: invokevirtual #21                 // Method getApplication:()Ljava/lang/String;
      18: aastore
      19: dup
      20: iconst_2
      21: aload_0
      22: invokevirtual #22                 // Method getVersion:()Ljava/lang/String;
      25: aastore
      26: dup
      27: iconst_3
      28: aload_0
      29: invokevirtual #24                 // Method getType:()Lco/cask/cdap/proto/ProgramType;
      32: invokevirtual #51                 // Method co/cask/cdap/proto/ProgramType.getPrettyName:()Ljava/lang/String;
      35: invokevirtual #52                 // Method java/lang/String.toLowerCase:()Ljava/lang/String;
      38: aastore
      39: dup
      40: iconst_4
      41: aload_0
      42: invokevirtual #25                 // Method getProgram:()Ljava/lang/String;
      45: aastore
      46: dup
      47: iconst_5
      48: aload_0
      49: getfield      #18                 // Field run:Ljava/lang/String;
      52: aastore
      53: invokestatic  #53                 // Method java/util/Arrays.asList:([Ljava/lang/Object;)Ljava/util/List;
      56: invokestatic  #54                 // Method java/util/Collections.unmodifiableList:(Ljava/util/List;)Ljava/util/List;
      59: areturn

  public static co.cask.cdap.proto.id.ProgramRunId fromString(java.lang.String);
    Code:
       0: aload_0
       1: ldc_w         #28                 // class co/cask/cdap/proto/id/ProgramRunId
       4: invokestatic  #55                 // Method co/cask/cdap/proto/id/EntityId.fromString:(Ljava/lang/String;Ljava/lang/Class;)Lco/cask/cdap/proto/id/EntityId;
       7: checkcast     #28                 // class co/cask/cdap/proto/id/ProgramRunId
      10: areturn

  public co.cask.cdap.proto.Id toId();
    Code:
       0: aload_0
       1: invokevirtual #56                 // Method toId:()Lco/cask/cdap/proto/Id$Run;
       4: areturn

  public co.cask.cdap.proto.id.EntityId getParent();
    Code:
       0: aload_0
       1: invokevirtual #29                 // Method getParent:()Lco/cask/cdap/proto/id/ProgramId;
       4: areturn
}
