Compiled from "StdKeyDeserializer.java"
final class io.dekorate.deps.jackson.databind.deser.std.StdKeyDeserializer$StringKD extends io.dekorate.deps.jackson.databind.deser.std.StdKeyDeserializer {
  private static final long serialVersionUID;

  private static final io.dekorate.deps.jackson.databind.deser.std.StdKeyDeserializer$StringKD sString;

  private static final io.dekorate.deps.jackson.databind.deser.std.StdKeyDeserializer$StringKD sObject;

  private io.dekorate.deps.jackson.databind.deser.std.StdKeyDeserializer$StringKD(java.lang.Class<?>);
    Code:
       0: aload_0
       1: iconst_m1
       2: aload_1
       3: invokespecial #20                 // Method io/dekorate/deps/jackson/databind/deser/std/StdKeyDeserializer."<init>":(ILjava/lang/Class;)V
       6: return

  public static io.dekorate.deps.jackson.databind.deser.std.StdKeyDeserializer$StringKD forType(java.lang.Class<?>);
    Code:
       0: aload_0
       1: ldc           #29                 // class java/lang/String
       3: if_acmpne     10
       6: getstatic     #31                 // Field sString:Lio/dekorate/deps/jackson/databind/deser/std/StdKeyDeserializer$StringKD;
       9: areturn
      10: aload_0
      11: ldc           #33                 // class java/lang/Object
      13: if_acmpne     20
      16: getstatic     #35                 // Field sObject:Lio/dekorate/deps/jackson/databind/deser/std/StdKeyDeserializer$StringKD;
      19: areturn
      20: new           #2                  // class io/dekorate/deps/jackson/databind/deser/std/StdKeyDeserializer$StringKD
      23: dup
      24: aload_0
      25: invokespecial #37                 // Method "<init>":(Ljava/lang/Class;)V
      28: areturn

  public java.lang.Object deserializeKey(java.lang.String, io.dekorate.deps.jackson.databind.DeserializationContext) throws java.io.IOException, io.dekorate.deps.jackson.core.JsonProcessingException;
    Code:
       0: aload_1
       1: areturn

  static {};
    Code:
       0: new           #2                  // class io/dekorate/deps/jackson/databind/deser/std/StdKeyDeserializer$StringKD
       3: dup
       4: ldc           #29                 // class java/lang/String
       6: invokespecial #37                 // Method "<init>":(Ljava/lang/Class;)V
       9: putstatic     #31                 // Field sString:Lio/dekorate/deps/jackson/databind/deser/std/StdKeyDeserializer$StringKD;
      12: new           #2                  // class io/dekorate/deps/jackson/databind/deser/std/StdKeyDeserializer$StringKD
      15: dup
      16: ldc           #33                 // class java/lang/Object
      18: invokespecial #37                 // Method "<init>":(Ljava/lang/Class;)V
      21: putstatic     #35                 // Field sObject:Lio/dekorate/deps/jackson/databind/deser/std/StdKeyDeserializer$StringKD;
      24: return
}
