Compiled from "Either.scala"
public final class scalaz.std.EitherInstances$$anon$5 implements scalaz.Associative<scala.util.Either> {
  private final scalaz.syntax.AssociativeSyntax<scala.util.Either> associativeSyntax;

  public <A, B, C> scalaz.Isomorphisms$Iso<scala.Function1, scala.util.Either<scala.util.Either<A, B>, C>, scala.util.Either<A, scala.util.Either<B, C>>> reassociateIso();
    Code:
       0: aload_0
       1: invokestatic  #36                 // InterfaceMethod scalaz/Associative.reassociateIso$:(Lscalaz/Associative;)Lscalaz/Isomorphisms$Iso;
       4: areturn

  public scalaz.Associative<scala.util.Either>.AssociativeLaw associativeLaw();
    Code:
       0: aload_0
       1: invokestatic  #45                 // InterfaceMethod scalaz/Associative.associativeLaw$:(Lscalaz/Associative;)Lscalaz/Associative$AssociativeLaw;
       4: areturn

  public scalaz.syntax.AssociativeSyntax<scala.util.Either> associativeSyntax();
    Code:
       0: aload_0
       1: getfield      #49                 // Field associativeSyntax:Lscalaz/syntax/AssociativeSyntax;
       4: areturn

  public void scalaz$Associative$_setter_$associativeSyntax_$eq(scalaz.syntax.AssociativeSyntax<scala.util.Either>);
    Code:
       0: aload_0
       1: aload_1
       2: putfield      #49                 // Field associativeSyntax:Lscalaz/syntax/AssociativeSyntax;
       5: return

  public <A, B, C> scala.util.Either<scala.util.Either<A, B>, C> reassociateLeft(scala.util.Either<A, scala.util.Either<B, C>>);
    Code:
       0: aload_1
       1: invokedynamic #80,  0             // InvokeDynamic #0:apply:()Lscala/Function1;
       6: invokedynamic #86,  0             // InvokeDynamic #1:apply:()Lscala/Function1;
      11: invokevirtual #92                 // Method scala/util/Either.fold:(Lscala/Function1;Lscala/Function1;)Ljava/lang/Object;
      14: checkcast     #88                 // class scala/util/Either
      17: areturn

  public <A, B, C> scala.util.Either<A, scala.util.Either<B, C>> reassociateRight(scala.util.Either<scala.util.Either<A, B>, C>);
    Code:
       0: aload_1
       1: invokedynamic #100,  0            // InvokeDynamic #2:apply:()Lscala/Function1;
       6: invokedynamic #107,  0            // InvokeDynamic #3:apply:()Lscala/Function1;
      11: invokevirtual #92                 // Method scala/util/Either.fold:(Lscala/Function1;Lscala/Function1;)Ljava/lang/Object;
      14: checkcast     #88                 // class scala/util/Either
      17: areturn

  public java.lang.Object reassociateRight(java.lang.Object);
    Code:
       0: aload_0
       1: aload_1
       2: checkcast     #88                 // class scala/util/Either
       5: invokevirtual #109                // Method reassociateRight:(Lscala/util/Either;)Lscala/util/Either;
       8: areturn

  public java.lang.Object reassociateLeft(java.lang.Object);
    Code:
       0: aload_0
       1: aload_1
       2: checkcast     #88                 // class scala/util/Either
       5: invokevirtual #112                // Method reassociateLeft:(Lscala/util/Either;)Lscala/util/Either;
       8: areturn

  public static final scala.util.Left $anonfun$reassociateLeft$1(java.lang.Object);
    Code:
       0: getstatic     #119                // Field scala/package$.MODULE$:Lscala/package$;
       3: invokevirtual #123                // Method scala/package$.Left:()Lscala/util/Left$;
       6: getstatic     #119                // Field scala/package$.MODULE$:Lscala/package$;
       9: invokevirtual #123                // Method scala/package$.Left:()Lscala/util/Left$;
      12: aload_0
      13: invokevirtual #127                // Method scala/util/Left$.apply:(Ljava/lang/Object;)Lscala/util/Left;
      16: invokevirtual #127                // Method scala/util/Left$.apply:(Ljava/lang/Object;)Lscala/util/Left;
      19: areturn

  public static final scala.util.Left $anonfun$reassociateLeft$3(java.lang.Object);
    Code:
       0: getstatic     #119                // Field scala/package$.MODULE$:Lscala/package$;
       3: invokevirtual #123                // Method scala/package$.Left:()Lscala/util/Left$;
       6: getstatic     #119                // Field scala/package$.MODULE$:Lscala/package$;
       9: invokevirtual #133                // Method scala/package$.Right:()Lscala/util/Right$;
      12: aload_0
      13: invokevirtual #137                // Method scala/util/Right$.apply:(Ljava/lang/Object;)Lscala/util/Right;
      16: invokevirtual #127                // Method scala/util/Left$.apply:(Ljava/lang/Object;)Lscala/util/Left;
      19: areturn

  public static final scala.util.Right $anonfun$reassociateLeft$4(java.lang.Object);
    Code:
       0: getstatic     #119                // Field scala/package$.MODULE$:Lscala/package$;
       3: invokevirtual #133                // Method scala/package$.Right:()Lscala/util/Right$;
       6: aload_0
       7: invokevirtual #137                // Method scala/util/Right$.apply:(Ljava/lang/Object;)Lscala/util/Right;
      10: areturn

  public static final scala.util.Either $anonfun$reassociateLeft$2(scala.util.Either);
    Code:
       0: aload_0
       1: invokedynamic #144,  0            // InvokeDynamic #4:apply:()Lscala/Function1;
       6: invokedynamic #148,  0            // InvokeDynamic #5:apply:()Lscala/Function1;
      11: invokevirtual #92                 // Method scala/util/Either.fold:(Lscala/Function1;Lscala/Function1;)Ljava/lang/Object;
      14: checkcast     #88                 // class scala/util/Either
      17: areturn

  public static final scala.util.Left $anonfun$reassociateRight$2(java.lang.Object);
    Code:
       0: getstatic     #119                // Field scala/package$.MODULE$:Lscala/package$;
       3: invokevirtual #123                // Method scala/package$.Left:()Lscala/util/Left$;
       6: aload_0
       7: invokevirtual #127                // Method scala/util/Left$.apply:(Ljava/lang/Object;)Lscala/util/Left;
      10: areturn

  public static final scala.util.Right $anonfun$reassociateRight$3(java.lang.Object);
    Code:
       0: getstatic     #119                // Field scala/package$.MODULE$:Lscala/package$;
       3: invokevirtual #133                // Method scala/package$.Right:()Lscala/util/Right$;
       6: getstatic     #119                // Field scala/package$.MODULE$:Lscala/package$;
       9: invokevirtual #123                // Method scala/package$.Left:()Lscala/util/Left$;
      12: aload_0
      13: invokevirtual #127                // Method scala/util/Left$.apply:(Ljava/lang/Object;)Lscala/util/Left;
      16: invokevirtual #137                // Method scala/util/Right$.apply:(Ljava/lang/Object;)Lscala/util/Right;
      19: areturn

  public static final scala.util.Either $anonfun$reassociateRight$1(scala.util.Either);
    Code:
       0: aload_0
       1: invokedynamic #156,  0            // InvokeDynamic #6:apply:()Lscala/Function1;
       6: invokedynamic #160,  0            // InvokeDynamic #7:apply:()Lscala/Function1;
      11: invokevirtual #92                 // Method scala/util/Either.fold:(Lscala/Function1;Lscala/Function1;)Ljava/lang/Object;
      14: checkcast     #88                 // class scala/util/Either
      17: areturn

  public static final scala.util.Right $anonfun$reassociateRight$4(java.lang.Object);
    Code:
       0: getstatic     #119                // Field scala/package$.MODULE$:Lscala/package$;
       3: invokevirtual #133                // Method scala/package$.Right:()Lscala/util/Right$;
       6: getstatic     #119                // Field scala/package$.MODULE$:Lscala/package$;
       9: invokevirtual #133                // Method scala/package$.Right:()Lscala/util/Right$;
      12: aload_0
      13: invokevirtual #137                // Method scala/util/Right$.apply:(Ljava/lang/Object;)Lscala/util/Right;
      16: invokevirtual #137                // Method scala/util/Right$.apply:(Ljava/lang/Object;)Lscala/util/Right;
      19: areturn

  public scalaz.std.EitherInstances$$anon$5(scalaz.std.EitherInstances);
    Code:
       0: aload_0
       1: invokespecial #167                // Method java/lang/Object."<init>":()V
       4: aload_0
       5: invokestatic  #171                // InterfaceMethod scalaz/Associative.$init$:(Lscalaz/Associative;)V
       8: return

  private static java.lang.Object $deserializeLambda$(java.lang.invoke.SerializedLambda);
    Code:
       0: aload_0
       1: invokedynamic #184,  0            // InvokeDynamic #8:lambdaDeserialize:(Ljava/lang/invoke/SerializedLambda;)Ljava/lang/Object;
       6: areturn
}
