Compiled from "Option.scala"
public interface scalaz.std.OptionEqual<A> extends scalaz.Equal<scala.Option<A>> {
  public abstract scalaz.Equal<A> A();

  public static boolean equalIsNatural$(scalaz.std.OptionEqual);
    Code:
       0: aload_0
       1: invokespecial #21                 // InterfaceMethod equalIsNatural:()Z
       4: ireturn

  public default boolean equalIsNatural();
    Code:
       0: aload_0
       1: invokeinterface #24,  1           // InterfaceMethod A:()Lscalaz/Equal;
       6: invokeinterface #25,  1           // InterfaceMethod scalaz/Equal.equalIsNatural:()Z
      11: ireturn

  public static boolean equal$(scalaz.std.OptionEqual, scala.Option, scala.Option);
    Code:
       0: aload_0
       1: aload_1
       2: aload_2
       3: invokespecial #34                 // InterfaceMethod equal:(Lscala/Option;Lscala/Option;)Z
       6: ireturn

  public default boolean equal(scala.Option<A>, scala.Option<A>);
    Code:
       0: new           #38                 // class scala/Tuple2
       3: dup
       4: aload_1
       5: aload_2
       6: invokespecial #42                 // Method scala/Tuple2."<init>":(Ljava/lang/Object;Ljava/lang/Object;)V
       9: astore        4
      11: aload_1
      12: astore        5
      14: aload_2
      15: astore        6
      17: aload         5
      19: instanceof    #44                 // class scala/Some
      22: ifeq          72
      25: aload         5
      27: checkcast     #44                 // class scala/Some
      30: invokevirtual #48                 // Method scala/Some.value:()Ljava/lang/Object;
      33: astore        7
      35: aload         6
      37: instanceof    #44                 // class scala/Some
      40: ifeq          72
      43: aload         6
      45: checkcast     #44                 // class scala/Some
      48: invokevirtual #48                 // Method scala/Some.value:()Ljava/lang/Object;
      51: astore        8
      53: aload_0
      54: invokeinterface #24,  1           // InterfaceMethod A:()Lscalaz/Equal;
      59: aload         7
      61: aload         8
      63: invokeinterface #51,  3           // InterfaceMethod scalaz/Equal.equal:(Ljava/lang/Object;Ljava/lang/Object;)Z
      68: istore_3
      69: goto          175
      72: aload_1
      73: astore        9
      75: aload_2
      76: astore        10
      78: getstatic     #57                 // Field scala/None$.MODULE$:Lscala/None$;
      81: aload         9
      83: invokevirtual #61                 // Method java/lang/Object.equals:(Ljava/lang/Object;)Z
      86: ifeq          105
      89: getstatic     #57                 // Field scala/None$.MODULE$:Lscala/None$;
      92: aload         10
      94: invokevirtual #61                 // Method java/lang/Object.equals:(Ljava/lang/Object;)Z
      97: ifeq          105
     100: iconst_1
     101: istore_3
     102: goto          175
     105: aload_1
     106: astore        11
     108: aload_2
     109: astore        12
     111: getstatic     #57                 // Field scala/None$.MODULE$:Lscala/None$;
     114: aload         11
     116: invokevirtual #61                 // Method java/lang/Object.equals:(Ljava/lang/Object;)Z
     119: ifeq          135
     122: aload         12
     124: instanceof    #44                 // class scala/Some
     127: ifeq          135
     130: iconst_0
     131: istore_3
     132: goto          175
     135: aload_1
     136: astore        13
     138: aload_2
     139: astore        14
     141: aload         13
     143: instanceof    #44                 // class scala/Some
     146: ifeq          165
     149: getstatic     #57                 // Field scala/None$.MODULE$:Lscala/None$;
     152: aload         14
     154: invokevirtual #61                 // Method java/lang/Object.equals:(Ljava/lang/Object;)Z
     157: ifeq          165
     160: iconst_0
     161: istore_3
     162: goto          175
     165: new           #63                 // class scala/MatchError
     168: dup
     169: aload         4
     171: invokespecial #66                 // Method scala/MatchError."<init>":(Ljava/lang/Object;)V
     174: athrow
     175: iload_3
     176: ireturn

  public static void $init$(scalaz.std.OptionEqual);
    Code:
       0: return
}
