Compiled from "Set.scala"
public interface scalaz.std.SetInstances {
  public abstract void scalaz$std$SetInstances$_setter_$setInstance_$eq(scalaz.Foldable<scala.collection.immutable.Set>);

  public abstract scalaz.Foldable<scala.collection.immutable.Set> setInstance();

  public static scalaz.Order setOrder$(scalaz.std.SetInstances, scalaz.Order);
    Code:
       0: aload_0
       1: aload_1
       2: invokespecial #52                 // InterfaceMethod setOrder:(Lscalaz/Order;)Lscalaz/Order;
       5: areturn

  public default <A> scalaz.Order<scala.collection.immutable.Set<A>> setOrder(scalaz.Order<A>);
    Code:
       0: new           #30                 // class scalaz/std/SetInstances$$anon$2
       3: dup
       4: aconst_null
       5: aload_1
       6: invokespecial #59                 // Method scalaz/std/SetInstances$$anon$2."<init>":(Lscalaz/std/SetInstances;Lscalaz/Order;)V
       9: areturn

  public static scalaz.Monoid setMonoid$(scalaz.std.SetInstances);
    Code:
       0: aload_0
       1: invokespecial #66                 // InterfaceMethod setMonoid:()Lscalaz/Monoid;
       4: areturn

  public default <A> scalaz.Monoid<scala.collection.immutable.Set<A>> setMonoid();
    Code:
       0: new           #32                 // class scalaz/std/SetInstances$$anon$3
       3: dup
       4: aconst_null
       5: invokespecial #70                 // Method scalaz/std/SetInstances$$anon$3."<init>":(Lscalaz/std/SetInstances;)V
       8: areturn

  public static scalaz.Show setShow$(scalaz.std.SetInstances, scalaz.Show);
    Code:
       0: aload_0
       1: aload_1
       2: invokespecial #77                 // InterfaceMethod setShow:(Lscalaz/Show;)Lscalaz/Show;
       5: areturn

  public default <A> scalaz.Show<scala.collection.immutable.Set<A>> setShow(scalaz.Show<A>);
    Code:
       0: getstatic     #85                 // Field scalaz/Show$.MODULE$:Lscalaz/Show$;
       3: aload_0
       4: aload_1
       5: invokedynamic #109,  0            // InvokeDynamic #0:apply:(Lscalaz/std/SetInstances;Lscalaz/Show;)Lscala/Function1;
      10: astore_2
      11: ifnonnull     16
      14: aconst_null
      15: athrow
      16: new           #26                 // class scalaz/Show$$anon$4
      19: dup
      20: aload_2
      21: invokespecial #112                // Method scalaz/Show$$anon$4."<init>":(Lscala/Function1;)V
      24: areturn

  public static scalaz.Cord $anonfun$setShow$2(scalaz.Show, java.lang.Object);
    Code:
       0: aload_0
       1: aload_1
       2: invokeinterface #126,  2          // InterfaceMethod scalaz/Show.show:(Ljava/lang/Object;)Lscalaz/Cord;
       7: areturn

  public static scalaz.Cord $anonfun$setShow$1(scalaz.std.SetInstances, scalaz.Show, scala.collection.immutable.Set);
    Code:
       0: getstatic     #133                // Field scalaz/Foldable$.MODULE$:Lscalaz/Foldable$;
       3: aload_0
       4: invokeinterface #135,  1          // InterfaceMethod setInstance:()Lscalaz/Foldable;
       9: astore        4
      11: ifnonnull     16
      14: aconst_null
      15: athrow
      16: aload         4
      18: aload_2
      19: aload_1
      20: invokedynamic #142,  0            // InvokeDynamic #1:apply:(Lscalaz/Show;)Lscala/Function1;
      25: getstatic     #147                // Field scala/collection/immutable/Set$.MODULE$:Lscala/collection/immutable/Set$;
      28: invokevirtual #151                // Method scala/collection/immutable/Set$.canBuildFrom:()Lscala/collection/generic/CanBuildFrom;
      31: invokeinterface #157,  3          // InterfaceMethod scala/collection/immutable/Set.map:(Lscala/Function1;Lscala/collection/generic/CanBuildFrom;)Ljava/lang/Object;
      36: getstatic     #162                // Field scalaz/Cord$.MODULE$:Lscalaz/Cord$;
      39: ldc           #164                // String ,
      41: invokevirtual #167                // Method scalaz/Cord$.apply:(Ljava/lang/String;)Lscalaz/Cord;
      44: getstatic     #162                // Field scalaz/Cord$.MODULE$:Lscalaz/Cord$;
      47: invokevirtual #170                // Method scalaz/Cord$.monoid:()Lscalaz/Monoid;
      50: invokeinterface #176,  4          // InterfaceMethod scalaz/Foldable.intercalate:(Ljava/lang/Object;Ljava/lang/Object;Lscalaz/Monoid;)Ljava/lang/Object;
      55: checkcast     #17                 // class scalaz/Cord
      58: astore_3
      59: getstatic     #179                // Field scalaz/Cord$CordInterpolator$.MODULE$:Lscalaz/Cord$CordInterpolator$;
      62: getstatic     #184                // Field scalaz/syntax/package$.MODULE$:Lscalaz/syntax/package$;
      65: invokevirtual #187                // Method scalaz/syntax/package$.show:()Lscalaz/syntax/Syntaxes$show$;
      68: new           #189                // class scala/StringContext
      71: dup
      72: getstatic     #194                // Field scala/Predef$.MODULE$:Lscala/Predef$;
      75: iconst_2
      76: anewarray     #196                // class java/lang/String
      79: dup
      80: iconst_0
      81: ldc           #198                // String Set(
      83: aastore
      84: dup
      85: iconst_1
      86: ldc           #200                // String )
      88: aastore
      89: checkcast     #202                // class "[Ljava/lang/Object;"
      92: invokevirtual #206                // Method scala/Predef$.wrapRefArray:([Ljava/lang/Object;)Lscala/collection/mutable/WrappedArray;
      95: invokespecial #209                // Method scala/StringContext."<init>":(Lscala/collection/Seq;)V
      98: invokevirtual #213                // Method scalaz/syntax/Syntaxes$show$.cordInterpolator:(Lscala/StringContext;)Lscala/StringContext;
     101: getstatic     #194                // Field scala/Predef$.MODULE$:Lscala/Predef$;
     104: iconst_1
     105: anewarray     #20                 // class scalaz/Cord$CordInterpolator$Cords
     108: dup
     109: iconst_0
     110: new           #20                 // class scalaz/Cord$CordInterpolator$Cords
     113: dup
     114: getstatic     #216                // Field scalaz/Cord$CordInterpolator$Cords$.MODULE$:Lscalaz/Cord$CordInterpolator$Cords$;
     117: aload_3
     118: invokevirtual #220                // Method scalaz/Cord$CordInterpolator$Cords$.trivial:(Lscalaz/Cord;)Lscalaz/Cord;
     121: invokespecial #223                // Method scalaz/Cord$CordInterpolator$Cords."<init>":(Lscalaz/Cord;)V
     124: aastore
     125: invokevirtual #227                // Method scala/Predef$.genericWrapArray:(Ljava/lang/Object;)Lscala/collection/mutable/WrappedArray;
     128: invokevirtual #231                // Method scalaz/Cord$CordInterpolator$.cord$extension:(Lscala/StringContext;Lscala/collection/Seq;)Lscalaz/Cord;
     131: areturn

  public static void $init$(scalaz.std.SetInstances);
    Code:
       0: aload_0
       1: new           #28                 // class scalaz/std/SetInstances$$anon$1
       4: dup
       5: aconst_null
       6: invokespecial #236                // Method scalaz/std/SetInstances$$anon$1."<init>":(Lscalaz/std/SetInstances;)V
       9: invokeinterface #238,  2          // InterfaceMethod scalaz$std$SetInstances$_setter_$setInstance_$eq:(Lscalaz/Foldable;)V
      14: return

  private static java.lang.Object $deserializeLambda$(java.lang.invoke.SerializedLambda);
    Code:
       0: aload_0
       1: invokedynamic #250,  0            // InvokeDynamic #2:lambdaDeserialize:(Ljava/lang/invoke/SerializedLambda;)Ljava/lang/Object;
       6: areturn
}
