Compiled from "TupleNInstances.scala"
public interface scalaz.std.Tuple6Functor<A1, A2, A3, A4, A5> extends scalaz.Traverse<?> {
  public static scala.Tuple6 map$(scalaz.std.Tuple6Functor, scala.Tuple6, scala.Function1);
    Code:
       0: aload_0
       1: aload_1
       2: aload_2
       3: invokespecial #25                 // InterfaceMethod map:(Lscala/Tuple6;Lscala/Function1;)Lscala/Tuple6;
       6: areturn

  public default <A, B> scala.Tuple6<A1, A2, A3, A4, A5, B> map(scala.Tuple6<A1, A2, A3, A4, A5, A>, scala.Function1<A, B>);
    Code:
       0: new           #31                 // class scala/Tuple6
       3: dup
       4: aload_1
       5: invokevirtual #35                 // Method scala/Tuple6._1:()Ljava/lang/Object;
       8: aload_1
       9: invokevirtual #38                 // Method scala/Tuple6._2:()Ljava/lang/Object;
      12: aload_1
      13: invokevirtual #41                 // Method scala/Tuple6._3:()Ljava/lang/Object;
      16: aload_1
      17: invokevirtual #44                 // Method scala/Tuple6._4:()Ljava/lang/Object;
      20: aload_1
      21: invokevirtual #47                 // Method scala/Tuple6._5:()Ljava/lang/Object;
      24: aload_2
      25: aload_1
      26: invokevirtual #50                 // Method scala/Tuple6._6:()Ljava/lang/Object;
      29: invokeinterface #56,  2           // InterfaceMethod scala/Function1.apply:(Ljava/lang/Object;)Ljava/lang/Object;
      34: invokespecial #60                 // Method scala/Tuple6."<init>":(Ljava/lang/Object;Ljava/lang/Object;Ljava/lang/Object;Ljava/lang/Object;Ljava/lang/Object;Ljava/lang/Object;)V
      37: areturn

  public static java.lang.Object traverseImpl$(scalaz.std.Tuple6Functor, scala.Tuple6, scala.Function1, scalaz.Applicative);
    Code:
       0: aload_0
       1: aload_1
       2: aload_2
       3: aload_3
       4: invokespecial #68                 // InterfaceMethod traverseImpl:(Lscala/Tuple6;Lscala/Function1;Lscalaz/Applicative;)Ljava/lang/Object;
       7: areturn

  public default <G, A, B> G traverseImpl(scala.Tuple6<A1, A2, A3, A4, A5, A>, scala.Function1<A, G>, scalaz.Applicative<G>);
    Code:
       0: aload_3
       1: aload_2
       2: aload_1
       3: invokevirtual #50                 // Method scala/Tuple6._6:()Ljava/lang/Object;
       6: invokeinterface #56,  2           // InterfaceMethod scala/Function1.apply:(Ljava/lang/Object;)Ljava/lang/Object;
      11: aload_1
      12: invokedynamic #92,  0             // InvokeDynamic #0:apply:(Lscala/Tuple6;)Lscala/Function1;
      17: invokeinterface #97,  3           // InterfaceMethod scalaz/Applicative.map:(Ljava/lang/Object;Lscala/Function1;)Ljava/lang/Object;
      22: areturn

  public static scala.Tuple6 $anonfun$traverseImpl$5(scala.Tuple6, java.lang.Object);
    Code:
       0: new           #31                 // class scala/Tuple6
       3: dup
       4: aload_0
       5: invokevirtual #35                 // Method scala/Tuple6._1:()Ljava/lang/Object;
       8: aload_0
       9: invokevirtual #38                 // Method scala/Tuple6._2:()Ljava/lang/Object;
      12: aload_0
      13: invokevirtual #41                 // Method scala/Tuple6._3:()Ljava/lang/Object;
      16: aload_0
      17: invokevirtual #44                 // Method scala/Tuple6._4:()Ljava/lang/Object;
      20: aload_0
      21: invokevirtual #47                 // Method scala/Tuple6._5:()Ljava/lang/Object;
      24: aload_1
      25: invokespecial #60                 // Method scala/Tuple6."<init>":(Ljava/lang/Object;Ljava/lang/Object;Ljava/lang/Object;Ljava/lang/Object;Ljava/lang/Object;Ljava/lang/Object;)V
      28: areturn

  public static void $init$(scalaz.std.Tuple6Functor);
    Code:
       0: return

  private static java.lang.Object $deserializeLambda$(java.lang.invoke.SerializedLambda);
    Code:
       0: aload_0
       1: invokedynamic #114,  0            // InvokeDynamic #1:lambdaDeserialize:(Ljava/lang/invoke/SerializedLambda;)Ljava/lang/Object;
       6: areturn
}
