Compiled from "Tuple.scala"
public interface scalaz.std.Tuple6Monoid<A1, A2, A3, A4, A5, A6> extends scalaz.Monoid<scala.Tuple6<A1, A2, A3, A4, A5, A6>>, scalaz.std.Tuple6Semigroup<A1, A2, A3, A4, A5, A6> {
  public abstract scalaz.Monoid<A1> _1();

  public abstract scalaz.Monoid<A2> _2();

  public abstract scalaz.Monoid<A3> _3();

  public abstract scalaz.Monoid<A4> _4();

  public abstract scalaz.Monoid<A5> _5();

  public abstract scalaz.Monoid<A6> _6();

  public static scala.Tuple6 zero$(scalaz.std.Tuple6Monoid);
    Code:
       0: aload_0
       1: invokespecial #33                 // InterfaceMethod zero:()Lscala/Tuple6;
       4: areturn

  public default scala.Tuple6<A1, A2, A3, A4, A5, A6> zero();
    Code:
       0: new           #37                 // class scala/Tuple6
       3: dup
       4: aload_0
       5: invokeinterface #39,  1           // InterfaceMethod _1:()Lscalaz/Monoid;
      10: invokeinterface #42,  1           // InterfaceMethod scalaz/Monoid.zero:()Ljava/lang/Object;
      15: aload_0
      16: invokeinterface #44,  1           // InterfaceMethod _2:()Lscalaz/Monoid;
      21: invokeinterface #42,  1           // InterfaceMethod scalaz/Monoid.zero:()Ljava/lang/Object;
      26: aload_0
      27: invokeinterface #46,  1           // InterfaceMethod _3:()Lscalaz/Monoid;
      32: invokeinterface #42,  1           // InterfaceMethod scalaz/Monoid.zero:()Ljava/lang/Object;
      37: aload_0
      38: invokeinterface #48,  1           // InterfaceMethod _4:()Lscalaz/Monoid;
      43: invokeinterface #42,  1           // InterfaceMethod scalaz/Monoid.zero:()Ljava/lang/Object;
      48: aload_0
      49: invokeinterface #50,  1           // InterfaceMethod _5:()Lscalaz/Monoid;
      54: invokeinterface #42,  1           // InterfaceMethod scalaz/Monoid.zero:()Ljava/lang/Object;
      59: aload_0
      60: invokeinterface #52,  1           // InterfaceMethod _6:()Lscalaz/Monoid;
      65: invokeinterface #42,  1           // InterfaceMethod scalaz/Monoid.zero:()Ljava/lang/Object;
      70: invokespecial #56                 // Method scala/Tuple6."<init>":(Ljava/lang/Object;Ljava/lang/Object;Ljava/lang/Object;Ljava/lang/Object;Ljava/lang/Object;Ljava/lang/Object;)V
      73: areturn

  public static void $init$(scalaz.std.Tuple6Monoid);
    Code:
       0: return
}
