Compiled from "GafferResultCacheUtil.java"
public final class uk.gov.gchq.gaffer.operation.export.resultcache.handler.util.GafferResultCacheUtil {
  public static final long ONE_DAY_IN_MILLISECONDS;

  public static final long DEFAULT_TIME_TO_LIVE;

  private static final org.slf4j.Logger LOGGER;

  private uk.gov.gchq.gaffer.operation.export.resultcache.handler.util.GafferResultCacheUtil();
    Code:
       0: aload_0
       1: invokespecial #2                  // Method java/lang/Object."<init>":()V
       4: return

  public static uk.gov.gchq.gaffer.graph.Graph createGraph(java.lang.String, java.lang.Long);
    Code:
       0: aconst_null
       1: aload_0
       2: if_acmpne     15
       5: new           #3                  // class java/lang/IllegalArgumentException
       8: dup
       9: ldc           #4                  // String Gaffer result uk.gov.gchq.gaffer.cache Store properties are required
      11: invokespecial #5                  // Method java/lang/IllegalArgumentException."<init>":(Ljava/lang/String;)V
      14: athrow
      15: new           #6                  // class uk/gov/gchq/gaffer/graph/Graph$Builder
      18: dup
      19: invokespecial #7                  // Method uk/gov/gchq/gaffer/graph/Graph$Builder."<init>":()V
      22: aload_0
      23: invokevirtual #8                  // Method uk/gov/gchq/gaffer/graph/Graph$Builder.storeProperties:(Ljava/lang/String;)Luk/gov/gchq/gaffer/graph/Graph$Builder;
      26: aload_1
      27: invokestatic  #9                  // Method createSchema:(Ljava/lang/Long;)Luk/gov/gchq/gaffer/store/schema/Schema;
      30: invokevirtual #10                 // Method uk/gov/gchq/gaffer/graph/Graph$Builder.addSchema:(Luk/gov/gchq/gaffer/store/schema/Schema;)Luk/gov/gchq/gaffer/graph/Graph$Builder;
      33: astore_2
      34: aload_2
      35: invokevirtual #11                 // Method uk/gov/gchq/gaffer/graph/Graph$Builder.build:()Luk/gov/gchq/gaffer/graph/Graph;
      38: astore_3
      39: aload_3
      40: getstatic     #12                 // Field uk/gov/gchq/gaffer/store/StoreTrait.STORE_VALIDATION:Luk/gov/gchq/gaffer/store/StoreTrait;
      43: invokevirtual #13                 // Method uk/gov/gchq/gaffer/graph/Graph.hasTrait:(Luk/gov/gchq/gaffer/store/StoreTrait;)Z
      46: ifne          65
      49: getstatic     #14                 // Field LOGGER:Lorg/slf4j/Logger;
      52: ldc           #15                 // String Gaffer JSON export graph does not have {} trait so results may not be aged off.
      54: getstatic     #12                 // Field uk/gov/gchq/gaffer/store/StoreTrait.STORE_VALIDATION:Luk/gov/gchq/gaffer/store/StoreTrait;
      57: invokevirtual #16                 // Method uk/gov/gchq/gaffer/store/StoreTrait.name:()Ljava/lang/String;
      60: invokeinterface #17,  3           // InterfaceMethod org/slf4j/Logger.warn:(Ljava/lang/String;Ljava/lang/Object;)V
      65: aload_3
      66: areturn

  public static uk.gov.gchq.gaffer.store.schema.Schema createSchema(java.lang.Long);
    Code:
       0: new           #18                 // class uk/gov/gchq/gaffer/store/schema/Schema$Builder
       3: dup
       4: invokespecial #19                 // Method uk/gov/gchq/gaffer/store/schema/Schema$Builder."<init>":()V
       7: ldc           #1                  // class uk/gov/gchq/gaffer/operation/export/resultcache/handler/util/GafferResultCacheUtil
       9: ldc           #20                 // String gafferResultCache/schema
      11: invokestatic  #21                 // Method uk/gov/gchq/gaffer/commonutil/StreamUtil.openStreams:(Ljava/lang/Class;Ljava/lang/String;)[Ljava/io/InputStream;
      14: invokevirtual #22                 // Method uk/gov/gchq/gaffer/store/schema/Schema$Builder.json:([Ljava/io/InputStream;)Luk/gov/gchq/gaffer/store/schema/Schema$BaseBuilder;
      17: checkcast     #18                 // class uk/gov/gchq/gaffer/store/schema/Schema$Builder
      20: astore_1
      21: aconst_null
      22: aload_0
      23: if_acmpeq     80
      26: aload_1
      27: new           #18                 // class uk/gov/gchq/gaffer/store/schema/Schema$Builder
      30: dup
      31: invokespecial #19                 // Method uk/gov/gchq/gaffer/store/schema/Schema$Builder."<init>":()V
      34: ldc           #23                 // String timestamp
      36: new           #24                 // class uk/gov/gchq/gaffer/store/schema/TypeDefinition$Builder
      39: dup
      40: invokespecial #25                 // Method uk/gov/gchq/gaffer/store/schema/TypeDefinition$Builder."<init>":()V
      43: iconst_1
      44: anewarray     #26                 // class java/util/function/Predicate
      47: dup
      48: iconst_0
      49: new           #27                 // class uk/gov/gchq/koryphe/impl/predicate/AgeOff
      52: dup
      53: aload_0
      54: invokevirtual #28                 // Method java/lang/Long.longValue:()J
      57: invokespecial #29                 // Method uk/gov/gchq/koryphe/impl/predicate/AgeOff."<init>":(J)V
      60: aastore
      61: invokevirtual #30                 // Method uk/gov/gchq/gaffer/store/schema/TypeDefinition$Builder.validateFunctions:([Ljava/util/function/Predicate;)Luk/gov/gchq/gaffer/store/schema/TypeDefinition$Builder;
      64: invokevirtual #31                 // Method uk/gov/gchq/gaffer/store/schema/TypeDefinition$Builder.build:()Luk/gov/gchq/gaffer/store/schema/TypeDefinition;
      67: invokevirtual #32                 // Method uk/gov/gchq/gaffer/store/schema/Schema$Builder.type:(Ljava/lang/String;Luk/gov/gchq/gaffer/store/schema/TypeDefinition;)Luk/gov/gchq/gaffer/store/schema/Schema$BaseBuilder;
      70: checkcast     #18                 // class uk/gov/gchq/gaffer/store/schema/Schema$Builder
      73: invokevirtual #33                 // Method uk/gov/gchq/gaffer/store/schema/Schema$Builder.build:()Luk/gov/gchq/gaffer/store/schema/Schema;
      76: invokevirtual #34                 // Method uk/gov/gchq/gaffer/store/schema/Schema$Builder.merge:(Luk/gov/gchq/gaffer/store/schema/Schema;)Luk/gov/gchq/gaffer/store/schema/Schema$BaseBuilder;
      79: pop
      80: aload_1
      81: invokevirtual #33                 // Method uk/gov/gchq/gaffer/store/schema/Schema$Builder.build:()Luk/gov/gchq/gaffer/store/schema/Schema;
      84: areturn

  static {};
    Code:
       0: ldc           #1                  // class uk/gov/gchq/gaffer/operation/export/resultcache/handler/util/GafferResultCacheUtil
       2: invokestatic  #35                 // Method org/slf4j/LoggerFactory.getLogger:(Ljava/lang/Class;)Lorg/slf4j/Logger;
       5: putstatic     #14                 // Field LOGGER:Lorg/slf4j/Logger;
       8: return
}
