Compiled from "TypeChecker.java"
public class javassist.compiler.TypeChecker extends javassist.compiler.ast.Visitor implements javassist.bytecode.Opcode,javassist.compiler.TokenId {
  static final java.lang.String javaLangObject;

  static final java.lang.String jvmJavaLangObject;

  static final java.lang.String jvmJavaLangString;

  static final java.lang.String jvmJavaLangClass;

  protected int exprType;

  protected int arrayDim;

  protected java.lang.String className;

  protected javassist.compiler.MemberResolver resolver;

  protected javassist.CtClass thisClass;

  protected javassist.bytecode.MethodInfo thisMethod;

  public javassist.compiler.TypeChecker(javassist.CtClass, javassist.ClassPool);
    Code:
       0: aload_0
       1: invokespecial #1                  // Method javassist/compiler/ast/Visitor."<init>":()V
       4: aload_0
       5: new           #2                  // class javassist/compiler/MemberResolver
       8: dup
       9: aload_2
      10: invokespecial #3                  // Method javassist/compiler/MemberResolver."<init>":(Ljavassist/ClassPool;)V
      13: putfield      #4                  // Field resolver:Ljavassist/compiler/MemberResolver;
      16: aload_0
      17: aload_1
      18: putfield      #5                  // Field thisClass:Ljavassist/CtClass;
      21: aload_0
      22: aconst_null
      23: putfield      #6                  // Field thisMethod:Ljavassist/bytecode/MethodInfo;
      26: return

  protected static java.lang.String argTypesToString(int[], int[], java.lang.String[]);
    Code:
       0: new           #7                  // class java/lang/StringBuffer
       3: dup
       4: invokespecial #8                  // Method java/lang/StringBuffer."<init>":()V
       7: astore_3
       8: aload_3
       9: bipush        40
      11: invokevirtual #9                  // Method java/lang/StringBuffer.append:(C)Ljava/lang/StringBuffer;
      14: pop
      15: aload_0
      16: arraylength
      17: istore        4
      19: iload         4
      21: ifle          64
      24: iconst_0
      25: istore        5
      27: aload_3
      28: aload_0
      29: iload         5
      31: iaload
      32: aload_1
      33: iload         5
      35: iaload
      36: aload_2
      37: iload         5
      39: aaload
      40: invokestatic  #10                 // Method typeToString:(Ljava/lang/StringBuffer;IILjava/lang/String;)Ljava/lang/StringBuffer;
      43: pop
      44: iinc          5, 1
      47: iload         5
      49: iload         4
      51: if_icmpge     64
      54: aload_3
      55: bipush        44
      57: invokevirtual #9                  // Method java/lang/StringBuffer.append:(C)Ljava/lang/StringBuffer;
      60: pop
      61: goto          27
      64: aload_3
      65: bipush        41
      67: invokevirtual #9                  // Method java/lang/StringBuffer.append:(C)Ljava/lang/StringBuffer;
      70: pop
      71: aload_3
      72: invokevirtual #11                 // Method java/lang/StringBuffer.toString:()Ljava/lang/String;
      75: areturn

  protected static java.lang.StringBuffer typeToString(java.lang.StringBuffer, int, int, java.lang.String);
    Code:
       0: iload_1
       1: sipush        307
       4: if_icmpne     16
       7: aload_3
       8: invokestatic  #13                 // Method javassist/compiler/MemberResolver.jvmToJavaName:(Ljava/lang/String;)Ljava/lang/String;
      11: astore        4
      13: goto          45
      16: iload_1
      17: sipush        412
      20: if_icmpne     30
      23: ldc           #14                 // String Object
      25: astore        4
      27: goto          45
      30: iload_1
      31: invokestatic  #15                 // Method javassist/compiler/MemberResolver.getTypeName:(I)Ljava/lang/String;
      34: astore        4
      36: goto          45
      39: astore        5
      41: ldc           #17                 // String ?
      43: astore        4
      45: aload_0
      46: aload         4
      48: invokevirtual #18                 // Method java/lang/StringBuffer.append:(Ljava/lang/String;)Ljava/lang/StringBuffer;
      51: pop
      52: iload_2
      53: iinc          2, -1
      56: ifle          69
      59: aload_0
      60: ldc           #19                 // String []
      62: invokevirtual #18                 // Method java/lang/StringBuffer.append:(Ljava/lang/String;)Ljava/lang/StringBuffer;
      65: pop
      66: goto          52
      69: aload_0
      70: areturn
    Exception table:
       from    to  target type
          30    36    39   Class javassist/compiler/CompileError

  public void setThisMethod(javassist.bytecode.MethodInfo);
    Code:
       0: aload_0
       1: aload_1
       2: putfield      #6                  // Field thisMethod:Ljavassist/bytecode/MethodInfo;
       5: return

  protected static void fatal() throws javassist.compiler.CompileError;
    Code:
       0: new           #16                 // class javassist/compiler/CompileError
       3: dup
       4: ldc           #20                 // String fatal
       6: invokespecial #21                 // Method javassist/compiler/CompileError."<init>":(Ljava/lang/String;)V
       9: athrow

  protected java.lang.String getThisName();
    Code:
       0: aload_0
       1: getfield      #5                  // Field thisClass:Ljavassist/CtClass;
       4: invokevirtual #22                 // Method javassist/CtClass.getName:()Ljava/lang/String;
       7: invokestatic  #23                 // Method javassist/compiler/MemberResolver.javaToJvmName:(Ljava/lang/String;)Ljava/lang/String;
      10: areturn

  protected java.lang.String getSuperName() throws javassist.compiler.CompileError;
    Code:
       0: aload_0
       1: getfield      #5                  // Field thisClass:Ljavassist/CtClass;
       4: invokestatic  #24                 // Method javassist/compiler/MemberResolver.getSuperclass:(Ljavassist/CtClass;)Ljavassist/CtClass;
       7: invokevirtual #22                 // Method javassist/CtClass.getName:()Ljava/lang/String;
      10: invokestatic  #23                 // Method javassist/compiler/MemberResolver.javaToJvmName:(Ljava/lang/String;)Ljava/lang/String;
      13: areturn

  protected java.lang.String resolveClassName(javassist.compiler.ast.ASTList) throws javassist.compiler.CompileError;
    Code:
       0: aload_0
       1: getfield      #4                  // Field resolver:Ljavassist/compiler/MemberResolver;
       4: aload_1
       5: invokevirtual #25                 // Method javassist/compiler/MemberResolver.resolveClassName:(Ljavassist/compiler/ast/ASTList;)Ljava/lang/String;
       8: areturn

  protected java.lang.String resolveClassName(java.lang.String) throws javassist.compiler.CompileError;
    Code:
       0: aload_0
       1: getfield      #4                  // Field resolver:Ljavassist/compiler/MemberResolver;
       4: aload_1
       5: invokevirtual #26                 // Method javassist/compiler/MemberResolver.resolveJvmClassName:(Ljava/lang/String;)Ljava/lang/String;
       8: areturn

  public void atNewExpr(javassist.compiler.ast.NewExpr) throws javassist.compiler.CompileError;
    Code:
       0: aload_1
       1: invokevirtual #27                 // Method javassist/compiler/ast/NewExpr.isArray:()Z
       4: ifeq          15
       7: aload_0
       8: aload_1
       9: invokevirtual #28                 // Method atNewArrayExpr:(Ljavassist/compiler/ast/NewExpr;)V
      12: goto          68
      15: aload_0
      16: getfield      #4                  // Field resolver:Ljavassist/compiler/MemberResolver;
      19: aload_1
      20: invokevirtual #29                 // Method javassist/compiler/ast/NewExpr.getClassName:()Ljavassist/compiler/ast/ASTList;
      23: invokevirtual #30                 // Method javassist/compiler/MemberResolver.lookupClassByName:(Ljavassist/compiler/ast/ASTList;)Ljavassist/CtClass;
      26: astore_2
      27: aload_2
      28: invokevirtual #22                 // Method javassist/CtClass.getName:()Ljava/lang/String;
      31: astore_3
      32: aload_1
      33: invokevirtual #31                 // Method javassist/compiler/ast/NewExpr.getArguments:()Ljavassist/compiler/ast/ASTList;
      36: astore        4
      38: aload_0
      39: aload_2
      40: ldc           #33                 // String <init>
      42: aload         4
      44: invokevirtual #34                 // Method atMethodCallCore:(Ljavassist/CtClass;Ljava/lang/String;Ljavassist/compiler/ast/ASTList;)Ljavassist/compiler/MemberResolver$Method;
      47: pop
      48: aload_0
      49: sipush        307
      52: putfield      #35                 // Field exprType:I
      55: aload_0
      56: iconst_0
      57: putfield      #36                 // Field arrayDim:I
      60: aload_0
      61: aload_3
      62: invokestatic  #23                 // Method javassist/compiler/MemberResolver.javaToJvmName:(Ljava/lang/String;)Ljava/lang/String;
      65: putfield      #37                 // Field className:Ljava/lang/String;
      68: return

  public void atNewArrayExpr(javassist.compiler.ast.NewExpr) throws javassist.compiler.CompileError;
    Code:
       0: aload_1
       1: invokevirtual #38                 // Method javassist/compiler/ast/NewExpr.getArrayType:()I
       4: istore_2
       5: aload_1
       6: invokevirtual #39                 // Method javassist/compiler/ast/NewExpr.getArraySize:()Ljavassist/compiler/ast/ASTList;
       9: astore_3
      10: aload_1
      11: invokevirtual #29                 // Method javassist/compiler/ast/NewExpr.getClassName:()Ljavassist/compiler/ast/ASTList;
      14: astore        4
      16: aload_1
      17: invokevirtual #40                 // Method javassist/compiler/ast/NewExpr.getInitializer:()Ljavassist/compiler/ast/ArrayInit;
      20: astore        5
      22: aload         5
      24: ifnull        33
      27: aload         5
      29: aload_0
      30: invokevirtual #41                 // Method javassist/compiler/ast/ASTree.accept:(Ljavassist/compiler/ast/Visitor;)V
      33: aload_3
      34: invokevirtual #42                 // Method javassist/compiler/ast/ASTList.length:()I
      37: iconst_1
      38: if_icmple     52
      41: aload_0
      42: iload_2
      43: aload         4
      45: aload_3
      46: invokevirtual #43                 // Method atMultiNewArray:(ILjavassist/compiler/ast/ASTList;Ljavassist/compiler/ast/ASTList;)V
      49: goto          104
      52: aload_3
      53: invokevirtual #44                 // Method javassist/compiler/ast/ASTList.head:()Ljavassist/compiler/ast/ASTree;
      56: astore        6
      58: aload         6
      60: ifnull        69
      63: aload         6
      65: aload_0
      66: invokevirtual #41                 // Method javassist/compiler/ast/ASTree.accept:(Ljavassist/compiler/ast/Visitor;)V
      69: aload_0
      70: iload_2
      71: putfield      #35                 // Field exprType:I
      74: aload_0
      75: iconst_1
      76: putfield      #36                 // Field arrayDim:I
      79: iload_2
      80: sipush        307
      83: if_icmpne     99
      86: aload_0
      87: aload_0
      88: aload         4
      90: invokevirtual #45                 // Method resolveClassName:(Ljavassist/compiler/ast/ASTList;)Ljava/lang/String;
      93: putfield      #37                 // Field className:Ljava/lang/String;
      96: goto          104
      99: aload_0
     100: aconst_null
     101: putfield      #37                 // Field className:Ljava/lang/String;
     104: return

  public void atArrayInit(javassist.compiler.ast.ArrayInit) throws javassist.compiler.CompileError;
    Code:
       0: aload_1
       1: astore_2
       2: aload_2
       3: ifnull        28
       6: aload_2
       7: invokevirtual #44                 // Method javassist/compiler/ast/ASTList.head:()Ljavassist/compiler/ast/ASTree;
      10: astore_3
      11: aload_2
      12: invokevirtual #46                 // Method javassist/compiler/ast/ASTList.tail:()Ljavassist/compiler/ast/ASTList;
      15: astore_2
      16: aload_3
      17: ifnull        25
      20: aload_3
      21: aload_0
      22: invokevirtual #41                 // Method javassist/compiler/ast/ASTree.accept:(Ljavassist/compiler/ast/Visitor;)V
      25: goto          2
      28: return

  protected void atMultiNewArray(int, javassist.compiler.ast.ASTList, javassist.compiler.ast.ASTList) throws javassist.compiler.CompileError;
    Code:
       0: aload_3
       1: invokevirtual #42                 // Method javassist/compiler/ast/ASTList.length:()I
       4: istore        5
       6: iconst_0
       7: istore        4
       9: aload_3
      10: ifnull        44
      13: aload_3
      14: invokevirtual #44                 // Method javassist/compiler/ast/ASTList.head:()Ljavassist/compiler/ast/ASTree;
      17: astore        6
      19: aload         6
      21: ifnonnull     27
      24: goto          44
      27: iinc          4, 1
      30: aload         6
      32: aload_0
      33: invokevirtual #41                 // Method javassist/compiler/ast/ASTree.accept:(Ljavassist/compiler/ast/Visitor;)V
      36: aload_3
      37: invokevirtual #46                 // Method javassist/compiler/ast/ASTList.tail:()Ljavassist/compiler/ast/ASTList;
      40: astore_3
      41: goto          9
      44: aload_0
      45: iload_1
      46: putfield      #35                 // Field exprType:I
      49: aload_0
      50: iload         5
      52: putfield      #36                 // Field arrayDim:I
      55: iload_1
      56: sipush        307
      59: if_icmpne     74
      62: aload_0
      63: aload_0
      64: aload_2
      65: invokevirtual #45                 // Method resolveClassName:(Ljavassist/compiler/ast/ASTList;)Ljava/lang/String;
      68: putfield      #37                 // Field className:Ljava/lang/String;
      71: goto          79
      74: aload_0
      75: aconst_null
      76: putfield      #37                 // Field className:Ljava/lang/String;
      79: return

  public void atAssignExpr(javassist.compiler.ast.AssignExpr) throws javassist.compiler.CompileError;
    Code:
       0: aload_1
       1: invokevirtual #47                 // Method javassist/compiler/ast/AssignExpr.getOperator:()I
       4: istore_2
       5: aload_1
       6: invokevirtual #48                 // Method javassist/compiler/ast/AssignExpr.oprand1:()Ljavassist/compiler/ast/ASTree;
       9: astore_3
      10: aload_1
      11: invokevirtual #49                 // Method javassist/compiler/ast/AssignExpr.oprand2:()Ljavassist/compiler/ast/ASTree;
      14: astore        4
      16: aload_3
      17: instanceof    #50                 // class javassist/compiler/ast/Variable
      20: ifeq          45
      23: aload_0
      24: aload_1
      25: iload_2
      26: aload_3
      27: checkcast     #50                 // class javassist/compiler/ast/Variable
      30: aload_3
      31: checkcast     #50                 // class javassist/compiler/ast/Variable
      34: invokevirtual #51                 // Method javassist/compiler/ast/Variable.getDeclarator:()Ljavassist/compiler/ast/Declarator;
      37: aload         4
      39: invokespecial #52                 // Method atVariableAssign:(Ljavassist/compiler/ast/Expr;ILjavassist/compiler/ast/Variable;Ljavassist/compiler/ast/Declarator;Ljavassist/compiler/ast/ASTree;)V
      42: goto          90
      45: aload_3
      46: instanceof    #53                 // class javassist/compiler/ast/Expr
      49: ifeq          81
      52: aload_3
      53: checkcast     #53                 // class javassist/compiler/ast/Expr
      56: astore        5
      58: aload         5
      60: invokevirtual #54                 // Method javassist/compiler/ast/Expr.getOperator:()I
      63: bipush        65
      65: if_icmpne     81
      68: aload_0
      69: aload_1
      70: iload_2
      71: aload_3
      72: checkcast     #53                 // class javassist/compiler/ast/Expr
      75: aload         4
      77: invokespecial #55                 // Method atArrayAssign:(Ljavassist/compiler/ast/Expr;ILjavassist/compiler/ast/Expr;Ljavassist/compiler/ast/ASTree;)V
      80: return
      81: aload_0
      82: aload_1
      83: iload_2
      84: aload_3
      85: aload         4
      87: invokevirtual #56                 // Method atFieldAssign:(Ljavassist/compiler/ast/Expr;ILjavassist/compiler/ast/ASTree;Ljavassist/compiler/ast/ASTree;)V
      90: return

  private void atVariableAssign(javassist.compiler.ast.Expr, int, javassist.compiler.ast.Variable, javassist.compiler.ast.Declarator, javassist.compiler.ast.ASTree) throws javassist.compiler.CompileError;
    Code:
       0: aload         4
       2: invokevirtual #57                 // Method javassist/compiler/ast/Declarator.getType:()I
       5: istore        6
       7: aload         4
       9: invokevirtual #58                 // Method javassist/compiler/ast/Declarator.getArrayDim:()I
      12: istore        7
      14: aload         4
      16: invokevirtual #59                 // Method javassist/compiler/ast/Declarator.getClassName:()Ljava/lang/String;
      19: astore        8
      21: iload_2
      22: bipush        61
      24: if_icmpeq     32
      27: aload_0
      28: aload_3
      29: invokevirtual #60                 // Method atVariable:(Ljavassist/compiler/ast/Variable;)V
      32: aload         5
      34: aload_0
      35: invokevirtual #41                 // Method javassist/compiler/ast/ASTree.accept:(Ljavassist/compiler/ast/Visitor;)V
      38: aload_0
      39: iload         6
      41: putfield      #35                 // Field exprType:I
      44: aload_0
      45: iload         7
      47: putfield      #36                 // Field arrayDim:I
      50: aload_0
      51: aload         8
      53: putfield      #37                 // Field className:Ljava/lang/String;
      56: return

  private void atArrayAssign(javassist.compiler.ast.Expr, int, javassist.compiler.ast.Expr, javassist.compiler.ast.ASTree) throws javassist.compiler.CompileError;
    Code:
       0: aload_0
       1: aload_3
       2: invokevirtual #61                 // Method javassist/compiler/ast/Expr.oprand1:()Ljavassist/compiler/ast/ASTree;
       5: aload_3
       6: invokevirtual #62                 // Method javassist/compiler/ast/Expr.oprand2:()Ljavassist/compiler/ast/ASTree;
       9: invokevirtual #63                 // Method atArrayRead:(Ljavassist/compiler/ast/ASTree;Ljavassist/compiler/ast/ASTree;)V
      12: aload_0
      13: getfield      #35                 // Field exprType:I
      16: istore        5
      18: aload_0
      19: getfield      #36                 // Field arrayDim:I
      22: istore        6
      24: aload_0
      25: getfield      #37                 // Field className:Ljava/lang/String;
      28: astore        7
      30: aload         4
      32: aload_0
      33: invokevirtual #41                 // Method javassist/compiler/ast/ASTree.accept:(Ljavassist/compiler/ast/Visitor;)V
      36: aload_0
      37: iload         5
      39: putfield      #35                 // Field exprType:I
      42: aload_0
      43: iload         6
      45: putfield      #36                 // Field arrayDim:I
      48: aload_0
      49: aload         7
      51: putfield      #37                 // Field className:Ljava/lang/String;
      54: return

  protected void atFieldAssign(javassist.compiler.ast.Expr, int, javassist.compiler.ast.ASTree, javassist.compiler.ast.ASTree) throws javassist.compiler.CompileError;
    Code:
       0: aload_0
       1: aload_3
       2: invokevirtual #64                 // Method fieldAccess:(Ljavassist/compiler/ast/ASTree;)Ljavassist/CtField;
       5: astore        5
       7: aload_0
       8: aload         5
      10: invokespecial #65                 // Method atFieldRead:(Ljavassist/CtField;)V
      13: aload_0
      14: getfield      #35                 // Field exprType:I
      17: istore        6
      19: aload_0
      20: getfield      #36                 // Field arrayDim:I
      23: istore        7
      25: aload_0
      26: getfield      #37                 // Field className:Ljava/lang/String;
      29: astore        8
      31: aload         4
      33: aload_0
      34: invokevirtual #41                 // Method javassist/compiler/ast/ASTree.accept:(Ljavassist/compiler/ast/Visitor;)V
      37: aload_0
      38: iload         6
      40: putfield      #35                 // Field exprType:I
      43: aload_0
      44: iload         7
      46: putfield      #36                 // Field arrayDim:I
      49: aload_0
      50: aload         8
      52: putfield      #37                 // Field className:Ljava/lang/String;
      55: return

  public void atCondExpr(javassist.compiler.ast.CondExpr) throws javassist.compiler.CompileError;
    Code:
       0: aload_0
       1: aload_1
       2: invokevirtual #66                 // Method javassist/compiler/ast/CondExpr.condExpr:()Ljavassist/compiler/ast/ASTree;
       5: invokespecial #67                 // Method booleanExpr:(Ljavassist/compiler/ast/ASTree;)V
       8: aload_1
       9: invokevirtual #68                 // Method javassist/compiler/ast/CondExpr.thenExpr:()Ljavassist/compiler/ast/ASTree;
      12: aload_0
      13: invokevirtual #41                 // Method javassist/compiler/ast/ASTree.accept:(Ljavassist/compiler/ast/Visitor;)V
      16: aload_0
      17: getfield      #35                 // Field exprType:I
      20: istore_2
      21: aload_0
      22: getfield      #36                 // Field arrayDim:I
      25: istore_3
      26: aload_0
      27: getfield      #37                 // Field className:Ljava/lang/String;
      30: astore        4
      32: aload_1
      33: invokevirtual #69                 // Method javassist/compiler/ast/CondExpr.elseExpr:()Ljavassist/compiler/ast/ASTree;
      36: aload_0
      37: invokevirtual #41                 // Method javassist/compiler/ast/ASTree.accept:(Ljavassist/compiler/ast/Visitor;)V
      40: iload_3
      41: ifne          119
      44: iload_3
      45: aload_0
      46: getfield      #36                 // Field arrayDim:I
      49: if_icmpne     119
      52: iload_2
      53: aload_0
      54: getfield      #35                 // Field exprType:I
      57: invokestatic  #70                 // Method javassist/compiler/CodeGen.rightIsStrong:(II)Z
      60: ifeq          86
      63: aload_1
      64: new           #71                 // class javassist/compiler/ast/CastExpr
      67: dup
      68: aload_0
      69: getfield      #35                 // Field exprType:I
      72: iconst_0
      73: aload_1
      74: invokevirtual #68                 // Method javassist/compiler/ast/CondExpr.thenExpr:()Ljavassist/compiler/ast/ASTree;
      77: invokespecial #72                 // Method javassist/compiler/ast/CastExpr."<init>":(IILjavassist/compiler/ast/ASTree;)V
      80: invokevirtual #73                 // Method javassist/compiler/ast/CondExpr.setThen:(Ljavassist/compiler/ast/ASTree;)V
      83: goto          119
      86: aload_0
      87: getfield      #35                 // Field exprType:I
      90: iload_2
      91: invokestatic  #70                 // Method javassist/compiler/CodeGen.rightIsStrong:(II)Z
      94: ifeq          119
      97: aload_1
      98: new           #71                 // class javassist/compiler/ast/CastExpr
     101: dup
     102: iload_2
     103: iconst_0
     104: aload_1
     105: invokevirtual #69                 // Method javassist/compiler/ast/CondExpr.elseExpr:()Ljavassist/compiler/ast/ASTree;
     108: invokespecial #72                 // Method javassist/compiler/ast/CastExpr."<init>":(IILjavassist/compiler/ast/ASTree;)V
     111: invokevirtual #74                 // Method javassist/compiler/ast/CondExpr.setElse:(Ljavassist/compiler/ast/ASTree;)V
     114: aload_0
     115: iload_2
     116: putfield      #35                 // Field exprType:I
     119: return

  public void atBinExpr(javassist.compiler.ast.BinExpr) throws javassist.compiler.CompileError;
    Code:
       0: aload_1
       1: invokevirtual #75                 // Method javassist/compiler/ast/BinExpr.getOperator:()I
       4: istore_2
       5: iload_2
       6: invokestatic  #76                 // Method javassist/compiler/CodeGen.lookupBinOp:(I)I
       9: istore_3
      10: iload_3
      11: iflt          128
      14: iload_2
      15: bipush        43
      17: if_icmpne     74
      20: aload_0
      21: aload_1
      22: invokespecial #77                 // Method atPlusExpr:(Ljavassist/compiler/ast/BinExpr;)Ljavassist/compiler/ast/Expr;
      25: astore        4
      27: aload         4
      29: ifnull        71
      32: bipush        46
      34: aload         4
      36: new           #78                 // class javassist/compiler/ast/Member
      39: dup
      40: ldc           #79                 // String toString
      42: invokespecial #80                 // Method javassist/compiler/ast/Member."<init>":(Ljava/lang/String;)V
      45: invokestatic  #81                 // Method javassist/compiler/ast/Expr.make:(ILjavassist/compiler/ast/ASTree;Ljavassist/compiler/ast/ASTree;)Ljavassist/compiler/ast/Expr;
      48: aconst_null
      49: invokestatic  #82                 // Method javassist/compiler/ast/CallExpr.makeCall:(Ljavassist/compiler/ast/ASTree;Ljavassist/compiler/ast/ASTree;)Ljavassist/compiler/ast/CallExpr;
      52: astore        4
      54: aload_1
      55: aload         4
      57: invokevirtual #83                 // Method javassist/compiler/ast/BinExpr.setOprand1:(Ljavassist/compiler/ast/ASTree;)V
      60: aload_1
      61: aconst_null
      62: invokevirtual #84                 // Method javassist/compiler/ast/BinExpr.setOprand2:(Ljavassist/compiler/ast/ASTree;)V
      65: aload_0
      66: ldc           #86                 // String java/lang/String
      68: putfield      #37                 // Field className:Ljava/lang/String;
      71: goto          133
      74: aload_1
      75: invokevirtual #87                 // Method javassist/compiler/ast/BinExpr.oprand1:()Ljavassist/compiler/ast/ASTree;
      78: astore        4
      80: aload_1
      81: invokevirtual #88                 // Method javassist/compiler/ast/BinExpr.oprand2:()Ljavassist/compiler/ast/ASTree;
      84: astore        5
      86: aload         4
      88: aload_0
      89: invokevirtual #41                 // Method javassist/compiler/ast/ASTree.accept:(Ljavassist/compiler/ast/Visitor;)V
      92: aload_0
      93: getfield      #35                 // Field exprType:I
      96: istore        6
      98: aload         5
     100: aload_0
     101: invokevirtual #41                 // Method javassist/compiler/ast/ASTree.accept:(Ljavassist/compiler/ast/Visitor;)V
     104: aload_0
     105: aload_1
     106: iload_2
     107: aload         4
     109: aload         5
     111: invokespecial #89                 // Method isConstant:(Ljavassist/compiler/ast/BinExpr;ILjavassist/compiler/ast/ASTree;Ljavassist/compiler/ast/ASTree;)Z
     114: ifne          125
     117: aload_0
     118: aload_1
     119: iload_2
     120: iload         6
     122: invokespecial #90                 // Method computeBinExprType:(Ljavassist/compiler/ast/BinExpr;II)V
     125: goto          133
     128: aload_0
     129: aload_1
     130: invokespecial #67                 // Method booleanExpr:(Ljavassist/compiler/ast/ASTree;)V
     133: return

  private javassist.compiler.ast.Expr atPlusExpr(javassist.compiler.ast.BinExpr) throws javassist.compiler.CompileError;
    Code:
       0: aload_1
       1: invokevirtual #87                 // Method javassist/compiler/ast/BinExpr.oprand1:()Ljavassist/compiler/ast/ASTree;
       4: astore_2
       5: aload_1
       6: invokevirtual #88                 // Method javassist/compiler/ast/BinExpr.oprand2:()Ljavassist/compiler/ast/ASTree;
       9: astore_3
      10: aload_3
      11: ifnonnull     21
      14: aload_2
      15: aload_0
      16: invokevirtual #41                 // Method javassist/compiler/ast/ASTree.accept:(Ljavassist/compiler/ast/Visitor;)V
      19: aconst_null
      20: areturn
      21: aload_2
      22: invokestatic  #91                 // Method isPlusExpr:(Ljavassist/compiler/ast/ASTree;)Z
      25: ifeq          76
      28: aload_0
      29: aload_2
      30: checkcast     #92                 // class javassist/compiler/ast/BinExpr
      33: invokespecial #77                 // Method atPlusExpr:(Ljavassist/compiler/ast/BinExpr;)Ljavassist/compiler/ast/Expr;
      36: astore        4
      38: aload         4
      40: ifnull        73
      43: aload_3
      44: aload_0
      45: invokevirtual #41                 // Method javassist/compiler/ast/ASTree.accept:(Ljavassist/compiler/ast/Visitor;)V
      48: aload_0
      49: sipush        307
      52: putfield      #35                 // Field exprType:I
      55: aload_0
      56: iconst_0
      57: putfield      #36                 // Field arrayDim:I
      60: aload_0
      61: ldc           #93                 // String java/lang/StringBuffer
      63: putfield      #37                 // Field className:Ljava/lang/String;
      66: aload         4
      68: aload_3
      69: invokestatic  #94                 // Method makeAppendCall:(Ljavassist/compiler/ast/ASTree;Ljavassist/compiler/ast/ASTree;)Ljavassist/compiler/ast/Expr;
      72: areturn
      73: goto          81
      76: aload_2
      77: aload_0
      78: invokevirtual #41                 // Method javassist/compiler/ast/ASTree.accept:(Ljavassist/compiler/ast/Visitor;)V
      81: aload_0
      82: getfield      #35                 // Field exprType:I
      85: istore        4
      87: aload_0
      88: getfield      #36                 // Field arrayDim:I
      91: istore        5
      93: aload_0
      94: getfield      #37                 // Field className:Ljava/lang/String;
      97: astore        6
      99: aload_3
     100: aload_0
     101: invokevirtual #41                 // Method javassist/compiler/ast/ASTree.accept:(Ljavassist/compiler/ast/Visitor;)V
     104: aload_0
     105: aload_1
     106: bipush        43
     108: aload_2
     109: aload_3
     110: invokespecial #89                 // Method isConstant:(Ljavassist/compiler/ast/BinExpr;ILjavassist/compiler/ast/ASTree;Ljavassist/compiler/ast/ASTree;)Z
     113: ifeq          118
     116: aconst_null
     117: areturn
     118: iload         4
     120: sipush        307
     123: if_icmpne     141
     126: iload         5
     128: ifne          141
     131: ldc           #86                 // String java/lang/String
     133: aload         6
     135: invokevirtual #95                 // Method java/lang/String.equals:(Ljava/lang/Object;)Z
     138: ifne          170
     141: aload_0
     142: getfield      #35                 // Field exprType:I
     145: sipush        307
     148: if_icmpne     243
     151: aload_0
     152: getfield      #36                 // Field arrayDim:I
     155: ifne          243
     158: ldc           #86                 // String java/lang/String
     160: aload_0
     161: getfield      #37                 // Field className:Ljava/lang/String;
     164: invokevirtual #95                 // Method java/lang/String.equals:(Ljava/lang/Object;)Z
     167: ifeq          243
     170: new           #96                 // class javassist/compiler/ast/Symbol
     173: dup
     174: ldc           #97                 // String java
     176: invokespecial #98                 // Method javassist/compiler/ast/Symbol."<init>":(Ljava/lang/String;)V
     179: new           #96                 // class javassist/compiler/ast/Symbol
     182: dup
     183: ldc           #99                 // String lang
     185: invokespecial #98                 // Method javassist/compiler/ast/Symbol."<init>":(Ljava/lang/String;)V
     188: new           #96                 // class javassist/compiler/ast/Symbol
     191: dup
     192: ldc           #100                // String StringBuffer
     194: invokespecial #98                 // Method javassist/compiler/ast/Symbol."<init>":(Ljava/lang/String;)V
     197: invokestatic  #101                // Method javassist/compiler/ast/ASTList.make:(Ljavassist/compiler/ast/ASTree;Ljavassist/compiler/ast/ASTree;Ljavassist/compiler/ast/ASTree;)Ljavassist/compiler/ast/ASTList;
     200: astore        7
     202: new           #102                // class javassist/compiler/ast/NewExpr
     205: dup
     206: aload         7
     208: aconst_null
     209: invokespecial #103                // Method javassist/compiler/ast/NewExpr."<init>":(Ljavassist/compiler/ast/ASTList;Ljavassist/compiler/ast/ASTList;)V
     212: astore        8
     214: aload_0
     215: sipush        307
     218: putfield      #35                 // Field exprType:I
     221: aload_0
     222: iconst_0
     223: putfield      #36                 // Field arrayDim:I
     226: aload_0
     227: ldc           #93                 // String java/lang/StringBuffer
     229: putfield      #37                 // Field className:Ljava/lang/String;
     232: aload         8
     234: aload_2
     235: invokestatic  #94                 // Method makeAppendCall:(Ljavassist/compiler/ast/ASTree;Ljavassist/compiler/ast/ASTree;)Ljavassist/compiler/ast/Expr;
     238: aload_3
     239: invokestatic  #94                 // Method makeAppendCall:(Ljavassist/compiler/ast/ASTree;Ljavassist/compiler/ast/ASTree;)Ljavassist/compiler/ast/Expr;
     242: areturn
     243: aload_0
     244: aload_1
     245: bipush        43
     247: iload         4
     249: invokespecial #90                 // Method computeBinExprType:(Ljavassist/compiler/ast/BinExpr;II)V
     252: aconst_null
     253: areturn

  private boolean isConstant(javassist.compiler.ast.BinExpr, int, javassist.compiler.ast.ASTree, javassist.compiler.ast.ASTree) throws javassist.compiler.CompileError;
    Code:
       0: aload_3
       1: invokestatic  #104                // Method stripPlusExpr:(Ljavassist/compiler/ast/ASTree;)Ljavassist/compiler/ast/ASTree;
       4: astore_3
       5: aload         4
       7: invokestatic  #104                // Method stripPlusExpr:(Ljavassist/compiler/ast/ASTree;)Ljavassist/compiler/ast/ASTree;
      10: astore        4
      12: aconst_null
      13: astore        5
      15: aload_3
      16: instanceof    #105                // class javassist/compiler/ast/StringL
      19: ifeq          79
      22: aload         4
      24: instanceof    #105                // class javassist/compiler/ast/StringL
      27: ifeq          79
      30: iload_2
      31: bipush        43
      33: if_icmpne     79
      36: new           #105                // class javassist/compiler/ast/StringL
      39: dup
      40: new           #106                // class java/lang/StringBuilder
      43: dup
      44: invokespecial #107                // Method java/lang/StringBuilder."<init>":()V
      47: aload_3
      48: checkcast     #105                // class javassist/compiler/ast/StringL
      51: invokevirtual #108                // Method javassist/compiler/ast/StringL.get:()Ljava/lang/String;
      54: invokevirtual #109                // Method java/lang/StringBuilder.append:(Ljava/lang/String;)Ljava/lang/StringBuilder;
      57: aload         4
      59: checkcast     #105                // class javassist/compiler/ast/StringL
      62: invokevirtual #108                // Method javassist/compiler/ast/StringL.get:()Ljava/lang/String;
      65: invokevirtual #109                // Method java/lang/StringBuilder.append:(Ljava/lang/String;)Ljava/lang/StringBuilder;
      68: invokevirtual #110                // Method java/lang/StringBuilder.toString:()Ljava/lang/String;
      71: invokespecial #111                // Method javassist/compiler/ast/StringL."<init>":(Ljava/lang/String;)V
      74: astore        5
      76: goto          120
      79: aload_3
      80: instanceof    #112                // class javassist/compiler/ast/IntConst
      83: ifeq          101
      86: aload_3
      87: checkcast     #112                // class javassist/compiler/ast/IntConst
      90: iload_2
      91: aload         4
      93: invokevirtual #113                // Method javassist/compiler/ast/IntConst.compute:(ILjavassist/compiler/ast/ASTree;)Ljavassist/compiler/ast/ASTree;
      96: astore        5
      98: goto          120
     101: aload_3
     102: instanceof    #114                // class javassist/compiler/ast/DoubleConst
     105: ifeq          120
     108: aload_3
     109: checkcast     #114                // class javassist/compiler/ast/DoubleConst
     112: iload_2
     113: aload         4
     115: invokevirtual #115                // Method javassist/compiler/ast/DoubleConst.compute:(ILjavassist/compiler/ast/ASTree;)Ljavassist/compiler/ast/ASTree;
     118: astore        5
     120: aload         5
     122: ifnonnull     127
     125: iconst_0
     126: ireturn
     127: aload_1
     128: bipush        43
     130: invokevirtual #116                // Method javassist/compiler/ast/BinExpr.setOperator:(I)V
     133: aload_1
     134: aload         5
     136: invokevirtual #83                 // Method javassist/compiler/ast/BinExpr.setOprand1:(Ljavassist/compiler/ast/ASTree;)V
     139: aload_1
     140: aconst_null
     141: invokevirtual #84                 // Method javassist/compiler/ast/BinExpr.setOprand2:(Ljavassist/compiler/ast/ASTree;)V
     144: aload         5
     146: aload_0
     147: invokevirtual #41                 // Method javassist/compiler/ast/ASTree.accept:(Ljavassist/compiler/ast/Visitor;)V
     150: iconst_1
     151: ireturn

  static javassist.compiler.ast.ASTree stripPlusExpr(javassist.compiler.ast.ASTree);
    Code:
       0: aload_0
       1: instanceof    #92                 // class javassist/compiler/ast/BinExpr
       4: ifeq          36
       7: aload_0
       8: checkcast     #92                 // class javassist/compiler/ast/BinExpr
      11: astore_1
      12: aload_1
      13: invokevirtual #75                 // Method javassist/compiler/ast/BinExpr.getOperator:()I
      16: bipush        43
      18: if_icmpne     33
      21: aload_1
      22: invokevirtual #88                 // Method javassist/compiler/ast/BinExpr.oprand2:()Ljavassist/compiler/ast/ASTree;
      25: ifnonnull     33
      28: aload_1
      29: invokevirtual #117                // Method javassist/compiler/ast/BinExpr.getLeft:()Ljavassist/compiler/ast/ASTree;
      32: areturn
      33: goto          121
      36: aload_0
      37: instanceof    #53                 // class javassist/compiler/ast/Expr
      40: ifeq          100
      43: aload_0
      44: checkcast     #53                 // class javassist/compiler/ast/Expr
      47: astore_1
      48: aload_1
      49: invokevirtual #54                 // Method javassist/compiler/ast/Expr.getOperator:()I
      52: istore_2
      53: iload_2
      54: bipush        35
      56: if_icmpne     79
      59: aload_1
      60: invokevirtual #62                 // Method javassist/compiler/ast/Expr.oprand2:()Ljavassist/compiler/ast/ASTree;
      63: checkcast     #78                 // class javassist/compiler/ast/Member
      66: invokestatic  #118                // Method getConstantFieldValue:(Ljavassist/compiler/ast/Member;)Ljavassist/compiler/ast/ASTree;
      69: astore_3
      70: aload_3
      71: ifnull        76
      74: aload_3
      75: areturn
      76: goto          97
      79: iload_2
      80: bipush        43
      82: if_icmpne     97
      85: aload_1
      86: invokevirtual #119                // Method javassist/compiler/ast/Expr.getRight:()Ljavassist/compiler/ast/ASTree;
      89: ifnonnull     97
      92: aload_1
      93: invokevirtual #120                // Method javassist/compiler/ast/Expr.getLeft:()Ljavassist/compiler/ast/ASTree;
      96: areturn
      97: goto          121
     100: aload_0
     101: instanceof    #78                 // class javassist/compiler/ast/Member
     104: ifeq          121
     107: aload_0
     108: checkcast     #78                 // class javassist/compiler/ast/Member
     111: invokestatic  #118                // Method getConstantFieldValue:(Ljavassist/compiler/ast/Member;)Ljavassist/compiler/ast/ASTree;
     114: astore_1
     115: aload_1
     116: ifnull        121
     119: aload_1
     120: areturn
     121: aload_0
     122: areturn

  private static javassist.compiler.ast.ASTree getConstantFieldValue(javassist.compiler.ast.Member);
    Code:
       0: aload_0
       1: invokevirtual #121                // Method javassist/compiler/ast/Member.getField:()Ljavassist/CtField;
       4: invokestatic  #122                // Method getConstantFieldValue:(Ljavassist/CtField;)Ljavassist/compiler/ast/ASTree;
       7: areturn

  public static javassist.compiler.ast.ASTree getConstantFieldValue(javassist.CtField);
    Code:
       0: aload_0
       1: ifnonnull     6
       4: aconst_null
       5: areturn
       6: aload_0
       7: invokevirtual #123                // Method javassist/CtField.getConstantValue:()Ljava/lang/Object;
      10: astore_1
      11: aload_1
      12: ifnonnull     17
      15: aconst_null
      16: areturn
      17: aload_1
      18: instanceof    #124                // class java/lang/String
      21: ifeq          36
      24: new           #105                // class javassist/compiler/ast/StringL
      27: dup
      28: aload_1
      29: checkcast     #124                // class java/lang/String
      32: invokespecial #111                // Method javassist/compiler/ast/StringL."<init>":(Ljava/lang/String;)V
      35: areturn
      36: aload_1
      37: instanceof    #125                // class java/lang/Double
      40: ifne          50
      43: aload_1
      44: instanceof    #126                // class java/lang/Float
      47: ifeq          83
      50: aload_1
      51: instanceof    #125                // class java/lang/Double
      54: ifeq          63
      57: sipush        405
      60: goto          66
      63: sipush        404
      66: istore_2
      67: new           #114                // class javassist/compiler/ast/DoubleConst
      70: dup
      71: aload_1
      72: checkcast     #127                // class java/lang/Number
      75: invokevirtual #128                // Method java/lang/Number.doubleValue:()D
      78: iload_2
      79: invokespecial #129                // Method javassist/compiler/ast/DoubleConst."<init>":(DI)V
      82: areturn
      83: aload_1
      84: instanceof    #127                // class java/lang/Number
      87: ifeq          123
      90: aload_1
      91: instanceof    #130                // class java/lang/Long
      94: ifeq          103
      97: sipush        403
     100: goto          106
     103: sipush        402
     106: istore_2
     107: new           #112                // class javassist/compiler/ast/IntConst
     110: dup
     111: aload_1
     112: checkcast     #127                // class java/lang/Number
     115: invokevirtual #131                // Method java/lang/Number.longValue:()J
     118: iload_2
     119: invokespecial #132                // Method javassist/compiler/ast/IntConst."<init>":(JI)V
     122: areturn
     123: aload_1
     124: instanceof    #133                // class java/lang/Boolean
     127: ifeq          157
     130: new           #134                // class javassist/compiler/ast/Keyword
     133: dup
     134: aload_1
     135: checkcast     #133                // class java/lang/Boolean
     138: invokevirtual #135                // Method java/lang/Boolean.booleanValue:()Z
     141: ifeq          150
     144: sipush        410
     147: goto          153
     150: sipush        411
     153: invokespecial #136                // Method javassist/compiler/ast/Keyword."<init>":(I)V
     156: areturn
     157: aconst_null
     158: areturn

  private static boolean isPlusExpr(javassist.compiler.ast.ASTree);
    Code:
       0: aload_0
       1: instanceof    #92                 // class javassist/compiler/ast/BinExpr
       4: ifeq          29
       7: aload_0
       8: checkcast     #92                 // class javassist/compiler/ast/BinExpr
      11: astore_1
      12: aload_1
      13: invokevirtual #75                 // Method javassist/compiler/ast/BinExpr.getOperator:()I
      16: istore_2
      17: iload_2
      18: bipush        43
      20: if_icmpne     27
      23: iconst_1
      24: goto          28
      27: iconst_0
      28: ireturn
      29: iconst_0
      30: ireturn

  private static javassist.compiler.ast.Expr makeAppendCall(javassist.compiler.ast.ASTree, javassist.compiler.ast.ASTree);
    Code:
       0: bipush        46
       2: aload_0
       3: new           #78                 // class javassist/compiler/ast/Member
       6: dup
       7: ldc           #137                // String append
       9: invokespecial #80                 // Method javassist/compiler/ast/Member."<init>":(Ljava/lang/String;)V
      12: invokestatic  #81                 // Method javassist/compiler/ast/Expr.make:(ILjavassist/compiler/ast/ASTree;Ljavassist/compiler/ast/ASTree;)Ljavassist/compiler/ast/Expr;
      15: new           #138                // class javassist/compiler/ast/ASTList
      18: dup
      19: aload_1
      20: invokespecial #139                // Method javassist/compiler/ast/ASTList."<init>":(Ljavassist/compiler/ast/ASTree;)V
      23: invokestatic  #82                 // Method javassist/compiler/ast/CallExpr.makeCall:(Ljavassist/compiler/ast/ASTree;Ljavassist/compiler/ast/ASTree;)Ljavassist/compiler/ast/CallExpr;
      26: areturn

  private void computeBinExprType(javassist.compiler.ast.BinExpr, int, int) throws javassist.compiler.CompileError;
    Code:
       0: aload_0
       1: getfield      #35                 // Field exprType:I
       4: istore        4
       6: iload_2
       7: sipush        364
      10: if_icmpeq     27
      13: iload_2
      14: sipush        366
      17: if_icmpeq     27
      20: iload_2
      21: sipush        370
      24: if_icmpne     35
      27: aload_0
      28: iload_3
      29: putfield      #35                 // Field exprType:I
      32: goto          43
      35: aload_0
      36: aload_1
      37: iload_3
      38: iload         4
      40: invokespecial #140                // Method insertCast:(Ljavassist/compiler/ast/BinExpr;II)V
      43: aload_0
      44: getfield      #35                 // Field exprType:I
      47: invokestatic  #141                // Method javassist/compiler/CodeGen.isP_INT:(I)Z
      50: ifeq          60
      53: aload_0
      54: sipush        324
      57: putfield      #35                 // Field exprType:I
      60: return

  private void booleanExpr(javassist.compiler.ast.ASTree) throws javassist.compiler.CompileError;
    Code:
       0: aload_1
       1: invokestatic  #142                // Method javassist/compiler/CodeGen.getCompOperator:(Ljavassist/compiler/ast/ASTree;)I
       4: istore_2
       5: iload_2
       6: sipush        358
       9: if_icmpne     71
      12: aload_1
      13: checkcast     #92                 // class javassist/compiler/ast/BinExpr
      16: astore_3
      17: aload_3
      18: invokevirtual #87                 // Method javassist/compiler/ast/BinExpr.oprand1:()Ljavassist/compiler/ast/ASTree;
      21: aload_0
      22: invokevirtual #41                 // Method javassist/compiler/ast/ASTree.accept:(Ljavassist/compiler/ast/Visitor;)V
      25: aload_0
      26: getfield      #35                 // Field exprType:I
      29: istore        4
      31: aload_0
      32: getfield      #36                 // Field arrayDim:I
      35: istore        5
      37: aload_3
      38: invokevirtual #88                 // Method javassist/compiler/ast/BinExpr.oprand2:()Ljavassist/compiler/ast/ASTree;
      41: aload_0
      42: invokevirtual #41                 // Method javassist/compiler/ast/ASTree.accept:(Ljavassist/compiler/ast/Visitor;)V
      45: iload         5
      47: ifne          68
      50: aload_0
      51: getfield      #36                 // Field arrayDim:I
      54: ifne          68
      57: aload_0
      58: aload_3
      59: iload         4
      61: aload_0
      62: getfield      #35                 // Field exprType:I
      65: invokespecial #140                // Method insertCast:(Ljavassist/compiler/ast/BinExpr;II)V
      68: goto          134
      71: iload_2
      72: bipush        33
      74: if_icmpne     91
      77: aload_1
      78: checkcast     #53                 // class javassist/compiler/ast/Expr
      81: invokevirtual #61                 // Method javassist/compiler/ast/Expr.oprand1:()Ljavassist/compiler/ast/ASTree;
      84: aload_0
      85: invokevirtual #41                 // Method javassist/compiler/ast/ASTree.accept:(Ljavassist/compiler/ast/Visitor;)V
      88: goto          134
      91: iload_2
      92: sipush        369
      95: if_icmpeq     105
      98: iload_2
      99: sipush        368
     102: if_icmpne     129
     105: aload_1
     106: checkcast     #92                 // class javassist/compiler/ast/BinExpr
     109: astore_3
     110: aload_3
     111: invokevirtual #87                 // Method javassist/compiler/ast/BinExpr.oprand1:()Ljavassist/compiler/ast/ASTree;
     114: aload_0
     115: invokevirtual #41                 // Method javassist/compiler/ast/ASTree.accept:(Ljavassist/compiler/ast/Visitor;)V
     118: aload_3
     119: invokevirtual #88                 // Method javassist/compiler/ast/BinExpr.oprand2:()Ljavassist/compiler/ast/ASTree;
     122: aload_0
     123: invokevirtual #41                 // Method javassist/compiler/ast/ASTree.accept:(Ljavassist/compiler/ast/Visitor;)V
     126: goto          134
     129: aload_1
     130: aload_0
     131: invokevirtual #41                 // Method javassist/compiler/ast/ASTree.accept:(Ljavassist/compiler/ast/Visitor;)V
     134: aload_0
     135: sipush        301
     138: putfield      #35                 // Field exprType:I
     141: aload_0
     142: iconst_0
     143: putfield      #36                 // Field arrayDim:I
     146: return

  private void insertCast(javassist.compiler.ast.BinExpr, int, int) throws javassist.compiler.CompileError;
    Code:
       0: iload_2
       1: iload_3
       2: invokestatic  #70                 // Method javassist/compiler/CodeGen.rightIsStrong:(II)Z
       5: ifeq          28
       8: aload_1
       9: new           #71                 // class javassist/compiler/ast/CastExpr
      12: dup
      13: iload_3
      14: iconst_0
      15: aload_1
      16: invokevirtual #87                 // Method javassist/compiler/ast/BinExpr.oprand1:()Ljavassist/compiler/ast/ASTree;
      19: invokespecial #72                 // Method javassist/compiler/ast/CastExpr."<init>":(IILjavassist/compiler/ast/ASTree;)V
      22: invokevirtual #143                // Method javassist/compiler/ast/BinExpr.setLeft:(Ljavassist/compiler/ast/ASTree;)V
      25: goto          33
      28: aload_0
      29: iload_2
      30: putfield      #35                 // Field exprType:I
      33: return

  public void atCastExpr(javassist.compiler.ast.CastExpr) throws javassist.compiler.CompileError;
    Code:
       0: aload_0
       1: aload_1
       2: invokevirtual #144                // Method javassist/compiler/ast/CastExpr.getClassName:()Ljavassist/compiler/ast/ASTList;
       5: invokevirtual #45                 // Method resolveClassName:(Ljavassist/compiler/ast/ASTList;)Ljava/lang/String;
       8: astore_2
       9: aload_1
      10: invokevirtual #145                // Method javassist/compiler/ast/CastExpr.getOprand:()Ljavassist/compiler/ast/ASTree;
      13: aload_0
      14: invokevirtual #41                 // Method javassist/compiler/ast/ASTree.accept:(Ljavassist/compiler/ast/Visitor;)V
      17: aload_0
      18: aload_1
      19: invokevirtual #146                // Method javassist/compiler/ast/CastExpr.getType:()I
      22: putfield      #35                 // Field exprType:I
      25: aload_0
      26: aload_1
      27: invokevirtual #147                // Method javassist/compiler/ast/CastExpr.getArrayDim:()I
      30: putfield      #36                 // Field arrayDim:I
      33: aload_0
      34: aload_2
      35: putfield      #37                 // Field className:Ljava/lang/String;
      38: return

  public void atInstanceOfExpr(javassist.compiler.ast.InstanceOfExpr) throws javassist.compiler.CompileError;
    Code:
       0: aload_1
       1: invokevirtual #148                // Method javassist/compiler/ast/InstanceOfExpr.getOprand:()Ljavassist/compiler/ast/ASTree;
       4: aload_0
       5: invokevirtual #41                 // Method javassist/compiler/ast/ASTree.accept:(Ljavassist/compiler/ast/Visitor;)V
       8: aload_0
       9: sipush        301
      12: putfield      #35                 // Field exprType:I
      15: aload_0
      16: iconst_0
      17: putfield      #36                 // Field arrayDim:I
      20: return

  public void atExpr(javassist.compiler.ast.Expr) throws javassist.compiler.CompileError;
    Code:
       0: aload_1
       1: invokevirtual #54                 // Method javassist/compiler/ast/Expr.getOperator:()I
       4: istore_2
       5: aload_1
       6: invokevirtual #61                 // Method javassist/compiler/ast/Expr.oprand1:()Ljavassist/compiler/ast/ASTree;
       9: astore_3
      10: iload_2
      11: bipush        46
      13: if_icmpne     82
      16: aload_1
      17: invokevirtual #62                 // Method javassist/compiler/ast/Expr.oprand2:()Ljavassist/compiler/ast/ASTree;
      20: checkcast     #96                 // class javassist/compiler/ast/Symbol
      23: invokevirtual #149                // Method javassist/compiler/ast/Symbol.get:()Ljava/lang/String;
      26: astore        4
      28: aload         4
      30: ldc           #150                // String length
      32: invokevirtual #95                 // Method java/lang/String.equals:(Ljava/lang/Object;)Z
      35: ifeq          56
      38: aload_0
      39: aload_1
      40: invokevirtual #151                // Method atArrayLength:(Ljavassist/compiler/ast/Expr;)V
      43: goto          79
      46: astore        5
      48: aload_0
      49: aload_1
      50: invokespecial #153                // Method atFieldRead:(Ljavassist/compiler/ast/ASTree;)V
      53: goto          79
      56: aload         4
      58: ldc           #154                // String class
      60: invokevirtual #95                 // Method java/lang/String.equals:(Ljava/lang/Object;)Z
      63: ifeq          74
      66: aload_0
      67: aload_1
      68: invokevirtual #155                // Method atClassObject:(Ljavassist/compiler/ast/Expr;)V
      71: goto          79
      74: aload_0
      75: aload_1
      76: invokespecial #153                // Method atFieldRead:(Ljavassist/compiler/ast/ASTree;)V
      79: goto          238
      82: iload_2
      83: bipush        35
      85: if_icmpne     126
      88: aload_1
      89: invokevirtual #62                 // Method javassist/compiler/ast/Expr.oprand2:()Ljavassist/compiler/ast/ASTree;
      92: checkcast     #96                 // class javassist/compiler/ast/Symbol
      95: invokevirtual #149                // Method javassist/compiler/ast/Symbol.get:()Ljava/lang/String;
      98: astore        4
     100: aload         4
     102: ldc           #154                // String class
     104: invokevirtual #95                 // Method java/lang/String.equals:(Ljava/lang/Object;)Z
     107: ifeq          118
     110: aload_0
     111: aload_1
     112: invokevirtual #155                // Method atClassObject:(Ljavassist/compiler/ast/Expr;)V
     115: goto          123
     118: aload_0
     119: aload_1
     120: invokespecial #153                // Method atFieldRead:(Ljavassist/compiler/ast/ASTree;)V
     123: goto          238
     126: iload_2
     127: bipush        65
     129: if_icmpne     144
     132: aload_0
     133: aload_3
     134: aload_1
     135: invokevirtual #62                 // Method javassist/compiler/ast/Expr.oprand2:()Ljavassist/compiler/ast/ASTree;
     138: invokevirtual #63                 // Method atArrayRead:(Ljavassist/compiler/ast/ASTree;Ljavassist/compiler/ast/ASTree;)V
     141: goto          238
     144: iload_2
     145: sipush        362
     148: if_icmpeq     158
     151: iload_2
     152: sipush        363
     155: if_icmpne     168
     158: aload_0
     159: iload_2
     160: aload_3
     161: aload_1
     162: invokespecial #156                // Method atPlusPlus:(ILjavassist/compiler/ast/ASTree;Ljavassist/compiler/ast/Expr;)V
     165: goto          238
     168: iload_2
     169: bipush        33
     171: if_icmpne     182
     174: aload_0
     175: aload_1
     176: invokespecial #67                 // Method booleanExpr:(Ljavassist/compiler/ast/ASTree;)V
     179: goto          238
     182: iload_2
     183: bipush        67
     185: if_icmpne     194
     188: invokestatic  #157                // Method fatal:()V
     191: goto          238
     194: aload_3
     195: aload_0
     196: invokevirtual #41                 // Method javassist/compiler/ast/ASTree.accept:(Ljavassist/compiler/ast/Visitor;)V
     199: aload_0
     200: aload_1
     201: iload_2
     202: aload_3
     203: invokespecial #158                // Method isConstant:(Ljavassist/compiler/ast/Expr;ILjavassist/compiler/ast/ASTree;)Z
     206: ifne          238
     209: iload_2
     210: bipush        45
     212: if_icmpeq     221
     215: iload_2
     216: bipush        126
     218: if_icmpne     238
     221: aload_0
     222: getfield      #35                 // Field exprType:I
     225: invokestatic  #141                // Method javassist/compiler/CodeGen.isP_INT:(I)Z
     228: ifeq          238
     231: aload_0
     232: sipush        324
     235: putfield      #35                 // Field exprType:I
     238: return
    Exception table:
       from    to  target type
          38    43    46   Class javassist/compiler/NoFieldException

  private boolean isConstant(javassist.compiler.ast.Expr, int, javassist.compiler.ast.ASTree);
    Code:
       0: aload_3
       1: invokestatic  #104                // Method stripPlusExpr:(Ljavassist/compiler/ast/ASTree;)Ljavassist/compiler/ast/ASTree;
       4: astore_3
       5: aload_3
       6: instanceof    #112                // class javassist/compiler/ast/IntConst
       9: ifeq          68
      12: aload_3
      13: checkcast     #112                // class javassist/compiler/ast/IntConst
      16: astore        4
      18: aload         4
      20: invokevirtual #159                // Method javassist/compiler/ast/IntConst.get:()J
      23: lstore        5
      25: iload_2
      26: bipush        45
      28: if_icmpne     39
      31: lload         5
      33: lneg
      34: lstore        5
      36: goto          58
      39: iload_2
      40: bipush        126
      42: if_icmpne     56
      45: lload         5
      47: ldc2_w        #160                // long -1l
      50: lxor
      51: lstore        5
      53: goto          58
      56: iconst_0
      57: ireturn
      58: aload         4
      60: lload         5
      62: invokevirtual #162                // Method javassist/compiler/ast/IntConst.set:(J)V
      65: goto          108
      68: aload_3
      69: instanceof    #114                // class javassist/compiler/ast/DoubleConst
      72: ifeq          106
      75: aload_3
      76: checkcast     #114                // class javassist/compiler/ast/DoubleConst
      79: astore        4
      81: iload_2
      82: bipush        45
      84: if_icmpne     101
      87: aload         4
      89: aload         4
      91: invokevirtual #163                // Method javassist/compiler/ast/DoubleConst.get:()D
      94: dneg
      95: invokevirtual #164                // Method javassist/compiler/ast/DoubleConst.set:(D)V
      98: goto          103
     101: iconst_0
     102: ireturn
     103: goto          108
     106: iconst_0
     107: ireturn
     108: aload_1
     109: bipush        43
     111: invokevirtual #165                // Method javassist/compiler/ast/Expr.setOperator:(I)V
     114: iconst_1
     115: ireturn

  public void atCallExpr(javassist.compiler.ast.CallExpr) throws javassist.compiler.CompileError;
    Code:
       0: aconst_null
       1: astore_2
       2: aconst_null
       3: astore_3
       4: aload_1
       5: invokevirtual #166                // Method javassist/compiler/ast/CallExpr.oprand1:()Ljavassist/compiler/ast/ASTree;
       8: astore        4
      10: aload_1
      11: invokevirtual #167                // Method javassist/compiler/ast/CallExpr.oprand2:()Ljavassist/compiler/ast/ASTree;
      14: checkcast     #138                // class javassist/compiler/ast/ASTList
      17: astore        5
      19: aload         4
      21: instanceof    #78                 // class javassist/compiler/ast/Member
      24: ifeq          44
      27: aload         4
      29: checkcast     #78                 // class javassist/compiler/ast/Member
      32: invokevirtual #168                // Method javassist/compiler/ast/Member.get:()Ljava/lang/String;
      35: astore_2
      36: aload_0
      37: getfield      #5                  // Field thisClass:Ljavassist/CtClass;
      40: astore_3
      41: goto          323
      44: aload         4
      46: instanceof    #134                // class javassist/compiler/ast/Keyword
      49: ifeq          88
      52: ldc           #33                 // String <init>
      54: astore_2
      55: aload         4
      57: checkcast     #134                // class javassist/compiler/ast/Keyword
      60: invokevirtual #169                // Method javassist/compiler/ast/Keyword.get:()I
      63: sipush        336
      66: if_icmpne     80
      69: aload_0
      70: getfield      #5                  // Field thisClass:Ljavassist/CtClass;
      73: invokestatic  #24                 // Method javassist/compiler/MemberResolver.getSuperclass:(Ljavassist/CtClass;)Ljavassist/CtClass;
      76: astore_3
      77: goto          323
      80: aload_0
      81: getfield      #5                  // Field thisClass:Ljavassist/CtClass;
      84: astore_3
      85: goto          323
      88: aload         4
      90: instanceof    #53                 // class javassist/compiler/ast/Expr
      93: ifeq          320
      96: aload         4
      98: checkcast     #53                 // class javassist/compiler/ast/Expr
     101: astore        6
     103: aload         6
     105: invokevirtual #62                 // Method javassist/compiler/ast/Expr.oprand2:()Ljavassist/compiler/ast/ASTree;
     108: checkcast     #96                 // class javassist/compiler/ast/Symbol
     111: invokevirtual #149                // Method javassist/compiler/ast/Symbol.get:()Ljava/lang/String;
     114: astore_2
     115: aload         6
     117: invokevirtual #54                 // Method javassist/compiler/ast/Expr.getOperator:()I
     120: istore        7
     122: iload         7
     124: bipush        35
     126: if_icmpne     152
     129: aload_0
     130: getfield      #4                  // Field resolver:Ljavassist/compiler/MemberResolver;
     133: aload         6
     135: invokevirtual #61                 // Method javassist/compiler/ast/Expr.oprand1:()Ljavassist/compiler/ast/ASTree;
     138: checkcast     #96                 // class javassist/compiler/ast/Symbol
     141: invokevirtual #149                // Method javassist/compiler/ast/Symbol.get:()Ljava/lang/String;
     144: iconst_0
     145: invokevirtual #170                // Method javassist/compiler/MemberResolver.lookupClass:(Ljava/lang/String;Z)Ljavassist/CtClass;
     148: astore_3
     149: goto          317
     152: iload         7
     154: bipush        46
     156: if_icmpne     314
     159: aload         6
     161: invokevirtual #61                 // Method javassist/compiler/ast/Expr.oprand1:()Ljavassist/compiler/ast/ASTree;
     164: astore        8
     166: aload         8
     168: invokestatic  #171                // Method isDotSuper:(Ljavassist/compiler/ast/ASTree;)Ljava/lang/String;
     171: astore        9
     173: aload         9
     175: ifnull        191
     178: aload_0
     179: getfield      #5                  // Field thisClass:Ljavassist/CtClass;
     182: aload         9
     184: invokestatic  #172                // Method javassist/compiler/MemberResolver.getSuperInterface:(Ljavassist/CtClass;Ljava/lang/String;)Ljavassist/CtClass;
     187: astore_3
     188: goto          311
     191: aload         8
     193: aload_0
     194: invokevirtual #41                 // Method javassist/compiler/ast/ASTree.accept:(Ljavassist/compiler/ast/Visitor;)V
     197: goto          262
     200: astore        10
     202: aload         10
     204: invokevirtual #173                // Method javassist/compiler/NoFieldException.getExpr:()Ljavassist/compiler/ast/ASTree;
     207: aload         8
     209: if_acmpeq     215
     212: aload         10
     214: athrow
     215: aload_0
     216: sipush        307
     219: putfield      #35                 // Field exprType:I
     222: aload_0
     223: iconst_0
     224: putfield      #36                 // Field arrayDim:I
     227: aload_0
     228: aload         10
     230: invokevirtual #174                // Method javassist/compiler/NoFieldException.getField:()Ljava/lang/String;
     233: putfield      #37                 // Field className:Ljava/lang/String;
     236: aload         6
     238: bipush        35
     240: invokevirtual #165                // Method javassist/compiler/ast/Expr.setOperator:(I)V
     243: aload         6
     245: new           #96                 // class javassist/compiler/ast/Symbol
     248: dup
     249: aload_0
     250: getfield      #37                 // Field className:Ljava/lang/String;
     253: invokestatic  #13                 // Method javassist/compiler/MemberResolver.jvmToJavaName:(Ljava/lang/String;)Ljava/lang/String;
     256: invokespecial #98                 // Method javassist/compiler/ast/Symbol."<init>":(Ljava/lang/String;)V
     259: invokevirtual #175                // Method javassist/compiler/ast/Expr.setOprand1:(Ljavassist/compiler/ast/ASTree;)V
     262: aload_0
     263: getfield      #36                 // Field arrayDim:I
     266: ifle          283
     269: aload_0
     270: getfield      #4                  // Field resolver:Ljavassist/compiler/MemberResolver;
     273: ldc           #176                // String java.lang.Object
     275: iconst_1
     276: invokevirtual #170                // Method javassist/compiler/MemberResolver.lookupClass:(Ljava/lang/String;Z)Ljavassist/CtClass;
     279: astore_3
     280: goto          311
     283: aload_0
     284: getfield      #35                 // Field exprType:I
     287: sipush        307
     290: if_icmpne     308
     293: aload_0
     294: getfield      #4                  // Field resolver:Ljavassist/compiler/MemberResolver;
     297: aload_0
     298: getfield      #37                 // Field className:Ljava/lang/String;
     301: invokevirtual #177                // Method javassist/compiler/MemberResolver.lookupClassByJvmName:(Ljava/lang/String;)Ljavassist/CtClass;
     304: astore_3
     305: goto          311
     308: invokestatic  #178                // Method badMethod:()V
     311: goto          317
     314: invokestatic  #178                // Method badMethod:()V
     317: goto          323
     320: invokestatic  #157                // Method fatal:()V
     323: aload_0
     324: aload_3
     325: aload_2
     326: aload         5
     328: invokevirtual #34                 // Method atMethodCallCore:(Ljavassist/CtClass;Ljava/lang/String;Ljavassist/compiler/ast/ASTList;)Ljavassist/compiler/MemberResolver$Method;
     331: astore        6
     333: aload_1
     334: aload         6
     336: invokevirtual #179                // Method javassist/compiler/ast/CallExpr.setMethod:(Ljavassist/compiler/MemberResolver$Method;)V
     339: return
    Exception table:
       from    to  target type
         191   197   200   Class javassist/compiler/NoFieldException

  private static void badMethod() throws javassist.compiler.CompileError;
    Code:
       0: new           #16                 // class javassist/compiler/CompileError
       3: dup
       4: ldc           #180                // String bad method
       6: invokespecial #21                 // Method javassist/compiler/CompileError."<init>":(Ljava/lang/String;)V
       9: athrow

  static java.lang.String isDotSuper(javassist.compiler.ast.ASTree);
    Code:
       0: aload_0
       1: instanceof    #53                 // class javassist/compiler/ast/Expr
       4: ifeq          57
       7: aload_0
       8: checkcast     #53                 // class javassist/compiler/ast/Expr
      11: astore_1
      12: aload_1
      13: invokevirtual #54                 // Method javassist/compiler/ast/Expr.getOperator:()I
      16: bipush        46
      18: if_icmpne     57
      21: aload_1
      22: invokevirtual #62                 // Method javassist/compiler/ast/Expr.oprand2:()Ljavassist/compiler/ast/ASTree;
      25: astore_2
      26: aload_2
      27: instanceof    #134                // class javassist/compiler/ast/Keyword
      30: ifeq          57
      33: aload_2
      34: checkcast     #134                // class javassist/compiler/ast/Keyword
      37: invokevirtual #169                // Method javassist/compiler/ast/Keyword.get:()I
      40: sipush        336
      43: if_icmpne     57
      46: aload_1
      47: invokevirtual #61                 // Method javassist/compiler/ast/Expr.oprand1:()Ljavassist/compiler/ast/ASTree;
      50: checkcast     #96                 // class javassist/compiler/ast/Symbol
      53: invokevirtual #149                // Method javassist/compiler/ast/Symbol.get:()Ljava/lang/String;
      56: areturn
      57: aconst_null
      58: areturn

  public javassist.compiler.MemberResolver$Method atMethodCallCore(javassist.CtClass, java.lang.String, javassist.compiler.ast.ASTList) throws javassist.compiler.CompileError;
    Code:
       0: aload_0
       1: aload_3
       2: invokevirtual #181                // Method getMethodArgsLength:(Ljavassist/compiler/ast/ASTList;)I
       5: istore        4
       7: iload         4
       9: newarray       int
      11: astore        5
      13: iload         4
      15: newarray       int
      17: astore        6
      19: iload         4
      21: anewarray     #124                // class java/lang/String
      24: astore        7
      26: aload_0
      27: aload_3
      28: aload         5
      30: aload         6
      32: aload         7
      34: invokevirtual #182                // Method atMethodArgs:(Ljavassist/compiler/ast/ASTList;[I[I[Ljava/lang/String;)V
      37: aload_0
      38: getfield      #4                  // Field resolver:Ljavassist/compiler/MemberResolver;
      41: aload_1
      42: aload_0
      43: getfield      #5                  // Field thisClass:Ljavassist/CtClass;
      46: aload_0
      47: getfield      #6                  // Field thisMethod:Ljavassist/bytecode/MethodInfo;
      50: aload_2
      51: aload         5
      53: aload         6
      55: aload         7
      57: invokevirtual #183                // Method javassist/compiler/MemberResolver.lookupMethod:(Ljavassist/CtClass;Ljavassist/CtClass;Ljavassist/bytecode/MethodInfo;Ljava/lang/String;[I[I[Ljava/lang/String;)Ljavassist/compiler/MemberResolver$Method;
      60: astore        8
      62: aload         8
      64: ifnonnull     164
      67: aload_1
      68: invokevirtual #22                 // Method javassist/CtClass.getName:()Ljava/lang/String;
      71: astore        9
      73: aload         5
      75: aload         6
      77: aload         7
      79: invokestatic  #184                // Method argTypesToString:([I[I[Ljava/lang/String;)Ljava/lang/String;
      82: astore        10
      84: aload_2
      85: ldc           #33                 // String <init>
      87: invokevirtual #95                 // Method java/lang/String.equals:(Ljava/lang/Object;)Z
      90: ifeq          123
      93: new           #106                // class java/lang/StringBuilder
      96: dup
      97: invokespecial #107                // Method java/lang/StringBuilder."<init>":()V
     100: ldc           #185                // String cannot find constructor
     102: invokevirtual #109                // Method java/lang/StringBuilder.append:(Ljava/lang/String;)Ljava/lang/StringBuilder;
     105: aload         9
     107: invokevirtual #109                // Method java/lang/StringBuilder.append:(Ljava/lang/String;)Ljava/lang/StringBuilder;
     110: aload         10
     112: invokevirtual #109                // Method java/lang/StringBuilder.append:(Ljava/lang/String;)Ljava/lang/StringBuilder;
     115: invokevirtual #110                // Method java/lang/StringBuilder.toString:()Ljava/lang/String;
     118: astore        11
     120: goto          154
     123: new           #106                // class java/lang/StringBuilder
     126: dup
     127: invokespecial #107                // Method java/lang/StringBuilder."<init>":()V
     130: aload_2
     131: invokevirtual #109                // Method java/lang/StringBuilder.append:(Ljava/lang/String;)Ljava/lang/StringBuilder;
     134: aload         10
     136: invokevirtual #109                // Method java/lang/StringBuilder.append:(Ljava/lang/String;)Ljava/lang/StringBuilder;
     139: ldc           #186                // String  not found in
     141: invokevirtual #109                // Method java/lang/StringBuilder.append:(Ljava/lang/String;)Ljava/lang/StringBuilder;
     144: aload         9
     146: invokevirtual #109                // Method java/lang/StringBuilder.append:(Ljava/lang/String;)Ljava/lang/StringBuilder;
     149: invokevirtual #110                // Method java/lang/StringBuilder.toString:()Ljava/lang/String;
     152: astore        11
     154: new           #16                 // class javassist/compiler/CompileError
     157: dup
     158: aload         11
     160: invokespecial #21                 // Method javassist/compiler/CompileError."<init>":(Ljava/lang/String;)V
     163: athrow
     164: aload         8
     166: getfield      #187                // Field javassist/compiler/MemberResolver$Method.info:Ljavassist/bytecode/MethodInfo;
     169: invokevirtual #188                // Method javassist/bytecode/MethodInfo.getDescriptor:()Ljava/lang/String;
     172: astore        9
     174: aload_0
     175: aload         9
     177: invokevirtual #189                // Method setReturnType:(Ljava/lang/String;)V
     180: aload         8
     182: areturn

  public int getMethodArgsLength(javassist.compiler.ast.ASTList);
    Code:
       0: aload_1
       1: invokestatic  #190                // Method javassist/compiler/ast/ASTList.length:(Ljavassist/compiler/ast/ASTList;)I
       4: ireturn

  public void atMethodArgs(javassist.compiler.ast.ASTList, int[], int[], java.lang.String[]) throws javassist.compiler.CompileError;
    Code:
       0: iconst_0
       1: istore        5
       3: aload_1
       4: ifnull        55
       7: aload_1
       8: invokevirtual #44                 // Method javassist/compiler/ast/ASTList.head:()Ljavassist/compiler/ast/ASTree;
      11: astore        6
      13: aload         6
      15: aload_0
      16: invokevirtual #41                 // Method javassist/compiler/ast/ASTree.accept:(Ljavassist/compiler/ast/Visitor;)V
      19: aload_2
      20: iload         5
      22: aload_0
      23: getfield      #35                 // Field exprType:I
      26: iastore
      27: aload_3
      28: iload         5
      30: aload_0
      31: getfield      #36                 // Field arrayDim:I
      34: iastore
      35: aload         4
      37: iload         5
      39: aload_0
      40: getfield      #37                 // Field className:Ljava/lang/String;
      43: aastore
      44: iinc          5, 1
      47: aload_1
      48: invokevirtual #46                 // Method javassist/compiler/ast/ASTList.tail:()Ljavassist/compiler/ast/ASTList;
      51: astore_1
      52: goto          3
      55: return

  void setReturnType(java.lang.String) throws javassist.compiler.CompileError;
    Code:
       0: aload_1
       1: bipush        41
       3: invokevirtual #191                // Method java/lang/String.indexOf:(I)I
       6: istore_2
       7: iload_2
       8: ifge          14
      11: invokestatic  #178                // Method badMethod:()V
      14: aload_1
      15: iinc          2, 1
      18: iload_2
      19: invokevirtual #192                // Method java/lang/String.charAt:(I)C
      22: istore_3
      23: iconst_0
      24: istore        4
      26: iload_3
      27: bipush        91
      29: if_icmpne     47
      32: iinc          4, 1
      35: aload_1
      36: iinc          2, 1
      39: iload_2
      40: invokevirtual #192                // Method java/lang/String.charAt:(I)C
      43: istore_3
      44: goto          26
      47: aload_0
      48: iload         4
      50: putfield      #36                 // Field arrayDim:I
      53: iload_3
      54: bipush        76
      56: if_icmpne     101
      59: aload_1
      60: bipush        59
      62: iload_2
      63: iconst_1
      64: iadd
      65: invokevirtual #193                // Method java/lang/String.indexOf:(II)I
      68: istore        5
      70: iload         5
      72: ifge          78
      75: invokestatic  #178                // Method badMethod:()V
      78: aload_0
      79: sipush        307
      82: putfield      #35                 // Field exprType:I
      85: aload_0
      86: aload_1
      87: iload_2
      88: iconst_1
      89: iadd
      90: iload         5
      92: invokevirtual #194                // Method java/lang/String.substring:(II)Ljava/lang/String;
      95: putfield      #37                 // Field className:Ljava/lang/String;
      98: goto          114
     101: aload_0
     102: iload_3
     103: invokestatic  #195                // Method javassist/compiler/MemberResolver.descToType:(C)I
     106: putfield      #35                 // Field exprType:I
     109: aload_0
     110: aconst_null
     111: putfield      #37                 // Field className:Ljava/lang/String;
     114: return

  private void atFieldRead(javassist.compiler.ast.ASTree) throws javassist.compiler.CompileError;
    Code:
       0: aload_0
       1: aload_0
       2: aload_1
       3: invokevirtual #64                 // Method fieldAccess:(Ljavassist/compiler/ast/ASTree;)Ljavassist/CtField;
       6: invokespecial #65                 // Method atFieldRead:(Ljavassist/CtField;)V
       9: return

  private void atFieldRead(javassist.CtField) throws javassist.compiler.CompileError;
    Code:
       0: aload_1
       1: invokevirtual #196                // Method javassist/CtField.getFieldInfo2:()Ljavassist/bytecode/FieldInfo;
       4: astore_2
       5: aload_2
       6: invokevirtual #197                // Method javassist/bytecode/FieldInfo.getDescriptor:()Ljava/lang/String;
       9: astore_3
      10: iconst_0
      11: istore        4
      13: iconst_0
      14: istore        5
      16: aload_3
      17: iload         4
      19: invokevirtual #192                // Method java/lang/String.charAt:(I)C
      22: istore        6
      24: iload         6
      26: bipush        91
      28: if_icmpne     48
      31: iinc          5, 1
      34: aload_3
      35: iinc          4, 1
      38: iload         4
      40: invokevirtual #192                // Method java/lang/String.charAt:(I)C
      43: istore        6
      45: goto          24
      48: aload_0
      49: iload         5
      51: putfield      #36                 // Field arrayDim:I
      54: aload_0
      55: iload         6
      57: invokestatic  #195                // Method javassist/compiler/MemberResolver.descToType:(C)I
      60: putfield      #35                 // Field exprType:I
      63: iload         6
      65: bipush        76
      67: if_icmpne     95
      70: aload_0
      71: aload_3
      72: iload         4
      74: iconst_1
      75: iadd
      76: aload_3
      77: bipush        59
      79: iload         4
      81: iconst_1
      82: iadd
      83: invokevirtual #193                // Method java/lang/String.indexOf:(II)I
      86: invokevirtual #194                // Method java/lang/String.substring:(II)Ljava/lang/String;
      89: putfield      #37                 // Field className:Ljava/lang/String;
      92: goto          100
      95: aload_0
      96: aconst_null
      97: putfield      #37                 // Field className:Ljava/lang/String;
     100: return

  protected javassist.CtField fieldAccess(javassist.compiler.ast.ASTree) throws javassist.compiler.CompileError;
    Code:
       0: aload_1
       1: instanceof    #78                 // class javassist/compiler/ast/Member
       4: ifeq          59
       7: aload_1
       8: checkcast     #78                 // class javassist/compiler/ast/Member
      11: astore_2
      12: aload_2
      13: invokevirtual #168                // Method javassist/compiler/ast/Member.get:()Ljava/lang/String;
      16: astore_3
      17: aload_0
      18: getfield      #5                  // Field thisClass:Ljavassist/CtClass;
      21: aload_3
      22: invokevirtual #198                // Method javassist/CtClass.getField:(Ljava/lang/String;)Ljavassist/CtField;
      25: astore        4
      27: aload         4
      29: invokevirtual #199                // Method javassist/CtField.getModifiers:()I
      32: invokestatic  #200                // Method javassist/Modifier.isStatic:(I)Z
      35: ifeq          44
      38: aload_2
      39: aload         4
      41: invokevirtual #201                // Method javassist/compiler/ast/Member.setField:(Ljavassist/CtField;)V
      44: aload         4
      46: areturn
      47: astore        4
      49: new           #152                // class javassist/compiler/NoFieldException
      52: dup
      53: aload_3
      54: aload_1
      55: invokespecial #203                // Method javassist/compiler/NoFieldException."<init>":(Ljava/lang/String;Ljavassist/compiler/ast/ASTree;)V
      58: athrow
      59: aload_1
      60: instanceof    #53                 // class javassist/compiler/ast/Expr
      63: ifeq          251
      66: aload_1
      67: checkcast     #53                 // class javassist/compiler/ast/Expr
      70: astore_2
      71: aload_2
      72: invokevirtual #54                 // Method javassist/compiler/ast/Expr.getOperator:()I
      75: istore_3
      76: iload_3
      77: bipush        35
      79: if_icmpne     122
      82: aload_2
      83: invokevirtual #62                 // Method javassist/compiler/ast/Expr.oprand2:()Ljavassist/compiler/ast/ASTree;
      86: checkcast     #78                 // class javassist/compiler/ast/Member
      89: astore        4
      91: aload_0
      92: getfield      #4                  // Field resolver:Ljavassist/compiler/MemberResolver;
      95: aload_2
      96: invokevirtual #61                 // Method javassist/compiler/ast/Expr.oprand1:()Ljavassist/compiler/ast/ASTree;
      99: checkcast     #96                 // class javassist/compiler/ast/Symbol
     102: invokevirtual #149                // Method javassist/compiler/ast/Symbol.get:()Ljava/lang/String;
     105: aload         4
     107: invokevirtual #204                // Method javassist/compiler/MemberResolver.lookupField:(Ljava/lang/String;Ljavassist/compiler/ast/Symbol;)Ljavassist/CtField;
     110: astore        5
     112: aload         4
     114: aload         5
     116: invokevirtual #201                // Method javassist/compiler/ast/Member.setField:(Ljavassist/CtField;)V
     119: aload         5
     121: areturn
     122: iload_3
     123: bipush        46
     125: if_icmpne     251
     128: aload_2
     129: invokevirtual #61                 // Method javassist/compiler/ast/Expr.oprand1:()Ljavassist/compiler/ast/ASTree;
     132: aload_0
     133: invokevirtual #41                 // Method javassist/compiler/ast/ASTree.accept:(Ljavassist/compiler/ast/Visitor;)V
     136: goto          167
     139: astore        4
     141: aload         4
     143: invokevirtual #173                // Method javassist/compiler/NoFieldException.getExpr:()Ljavassist/compiler/ast/ASTree;
     146: aload_2
     147: invokevirtual #61                 // Method javassist/compiler/ast/Expr.oprand1:()Ljavassist/compiler/ast/ASTree;
     150: if_acmpeq     156
     153: aload         4
     155: athrow
     156: aload_0
     157: aload_2
     158: aload         4
     160: invokevirtual #174                // Method javassist/compiler/NoFieldException.getField:()Ljava/lang/String;
     163: invokespecial #205                // Method fieldAccess2:(Ljavassist/compiler/ast/Expr;Ljava/lang/String;)Ljavassist/CtField;
     166: areturn
     167: aconst_null
     168: astore        4
     170: aload_0
     171: getfield      #35                 // Field exprType:I
     174: sipush        307
     177: if_icmpne     206
     180: aload_0
     181: getfield      #36                 // Field arrayDim:I
     184: ifne          206
     187: aload_0
     188: getfield      #4                  // Field resolver:Ljavassist/compiler/MemberResolver;
     191: aload_0
     192: getfield      #37                 // Field className:Ljava/lang/String;
     195: aload_2
     196: invokevirtual #62                 // Method javassist/compiler/ast/Expr.oprand2:()Ljavassist/compiler/ast/ASTree;
     199: checkcast     #96                 // class javassist/compiler/ast/Symbol
     202: invokevirtual #206                // Method javassist/compiler/MemberResolver.lookupFieldByJvmName:(Ljava/lang/String;Ljavassist/compiler/ast/Symbol;)Ljavassist/CtField;
     205: areturn
     206: goto          215
     209: astore        5
     211: aload         5
     213: astore        4
     215: aload_2
     216: invokevirtual #61                 // Method javassist/compiler/ast/Expr.oprand1:()Ljavassist/compiler/ast/ASTree;
     219: astore        5
     221: aload         5
     223: instanceof    #96                 // class javassist/compiler/ast/Symbol
     226: ifeq          243
     229: aload_0
     230: aload_2
     231: aload         5
     233: checkcast     #96                 // class javassist/compiler/ast/Symbol
     236: invokevirtual #149                // Method javassist/compiler/ast/Symbol.get:()Ljava/lang/String;
     239: invokespecial #205                // Method fieldAccess2:(Ljavassist/compiler/ast/Expr;Ljava/lang/String;)Ljavassist/CtField;
     242: areturn
     243: aload         4
     245: ifnull        251
     248: aload         4
     250: athrow
     251: new           #16                 // class javassist/compiler/CompileError
     254: dup
     255: ldc           #207                // String bad filed access
     257: invokespecial #21                 // Method javassist/compiler/CompileError."<init>":(Ljava/lang/String;)V
     260: athrow
    Exception table:
       from    to  target type
          17    46    47   Class javassist/NotFoundException
         128   136   139   Class javassist/compiler/NoFieldException
         170   205   209   Class javassist/compiler/CompileError

  private javassist.CtField fieldAccess2(javassist.compiler.ast.Expr, java.lang.String) throws javassist.compiler.CompileError;
    Code:
       0: aload_1
       1: invokevirtual #62                 // Method javassist/compiler/ast/Expr.oprand2:()Ljavassist/compiler/ast/ASTree;
       4: checkcast     #78                 // class javassist/compiler/ast/Member
       7: astore_3
       8: aload_0
       9: getfield      #4                  // Field resolver:Ljavassist/compiler/MemberResolver;
      12: aload_2
      13: aload_3
      14: aload_1
      15: invokevirtual #208                // Method javassist/compiler/MemberResolver.lookupFieldByJvmName2:(Ljava/lang/String;Ljavassist/compiler/ast/Symbol;Ljavassist/compiler/ast/ASTree;)Ljavassist/CtField;
      18: astore        4
      20: aload_1
      21: bipush        35
      23: invokevirtual #165                // Method javassist/compiler/ast/Expr.setOperator:(I)V
      26: aload_1
      27: new           #96                 // class javassist/compiler/ast/Symbol
      30: dup
      31: aload_2
      32: invokestatic  #13                 // Method javassist/compiler/MemberResolver.jvmToJavaName:(Ljava/lang/String;)Ljava/lang/String;
      35: invokespecial #98                 // Method javassist/compiler/ast/Symbol."<init>":(Ljava/lang/String;)V
      38: invokevirtual #175                // Method javassist/compiler/ast/Expr.setOprand1:(Ljavassist/compiler/ast/ASTree;)V
      41: aload_3
      42: aload         4
      44: invokevirtual #201                // Method javassist/compiler/ast/Member.setField:(Ljavassist/CtField;)V
      47: aload         4
      49: areturn

  public void atClassObject(javassist.compiler.ast.Expr) throws javassist.compiler.CompileError;
    Code:
       0: aload_0
       1: sipush        307
       4: putfield      #35                 // Field exprType:I
       7: aload_0
       8: iconst_0
       9: putfield      #36                 // Field arrayDim:I
      12: aload_0
      13: ldc           #209                // String java/lang/Class
      15: putfield      #37                 // Field className:Ljava/lang/String;
      18: return

  public void atArrayLength(javassist.compiler.ast.Expr) throws javassist.compiler.CompileError;
    Code:
       0: aload_1
       1: invokevirtual #61                 // Method javassist/compiler/ast/Expr.oprand1:()Ljavassist/compiler/ast/ASTree;
       4: aload_0
       5: invokevirtual #41                 // Method javassist/compiler/ast/ASTree.accept:(Ljavassist/compiler/ast/Visitor;)V
       8: aload_0
       9: getfield      #36                 // Field arrayDim:I
      12: ifne          26
      15: new           #152                // class javassist/compiler/NoFieldException
      18: dup
      19: ldc           #150                // String length
      21: aload_1
      22: invokespecial #203                // Method javassist/compiler/NoFieldException."<init>":(Ljava/lang/String;Ljavassist/compiler/ast/ASTree;)V
      25: athrow
      26: aload_0
      27: sipush        324
      30: putfield      #35                 // Field exprType:I
      33: aload_0
      34: iconst_0
      35: putfield      #36                 // Field arrayDim:I
      38: return

  public void atArrayRead(javassist.compiler.ast.ASTree, javassist.compiler.ast.ASTree) throws javassist.compiler.CompileError;
    Code:
       0: aload_1
       1: aload_0
       2: invokevirtual #41                 // Method javassist/compiler/ast/ASTree.accept:(Ljavassist/compiler/ast/Visitor;)V
       5: aload_0
       6: getfield      #35                 // Field exprType:I
       9: istore_3
      10: aload_0
      11: getfield      #36                 // Field arrayDim:I
      14: istore        4
      16: aload_0
      17: getfield      #37                 // Field className:Ljava/lang/String;
      20: astore        5
      22: aload_2
      23: aload_0
      24: invokevirtual #41                 // Method javassist/compiler/ast/ASTree.accept:(Ljavassist/compiler/ast/Visitor;)V
      27: aload_0
      28: iload_3
      29: putfield      #35                 // Field exprType:I
      32: aload_0
      33: iload         4
      35: iconst_1
      36: isub
      37: putfield      #36                 // Field arrayDim:I
      40: aload_0
      41: aload         5
      43: putfield      #37                 // Field className:Ljava/lang/String;
      46: return

  private void atPlusPlus(int, javassist.compiler.ast.ASTree, javassist.compiler.ast.Expr) throws javassist.compiler.CompileError;
    Code:
       0: aload_2
       1: ifnonnull     8
       4: iconst_1
       5: goto          9
       8: iconst_0
       9: istore        4
      11: iload         4
      13: ifeq          21
      16: aload_3
      17: invokevirtual #62                 // Method javassist/compiler/ast/Expr.oprand2:()Ljavassist/compiler/ast/ASTree;
      20: astore_2
      21: aload_2
      22: instanceof    #50                 // class javassist/compiler/ast/Variable
      25: ifeq          58
      28: aload_2
      29: checkcast     #50                 // class javassist/compiler/ast/Variable
      32: invokevirtual #51                 // Method javassist/compiler/ast/Variable.getDeclarator:()Ljavassist/compiler/ast/Declarator;
      35: astore        5
      37: aload_0
      38: aload         5
      40: invokevirtual #57                 // Method javassist/compiler/ast/Declarator.getType:()I
      43: putfield      #35                 // Field exprType:I
      46: aload_0
      47: aload         5
      49: invokevirtual #58                 // Method javassist/compiler/ast/Declarator.getArrayDim:()I
      52: putfield      #36                 // Field arrayDim:I
      55: goto          146
      58: aload_2
      59: instanceof    #53                 // class javassist/compiler/ast/Expr
      62: ifeq          141
      65: aload_2
      66: checkcast     #53                 // class javassist/compiler/ast/Expr
      69: astore        5
      71: aload         5
      73: invokevirtual #54                 // Method javassist/compiler/ast/Expr.getOperator:()I
      76: bipush        65
      78: if_icmpne     141
      81: aload_0
      82: aload         5
      84: invokevirtual #61                 // Method javassist/compiler/ast/Expr.oprand1:()Ljavassist/compiler/ast/ASTree;
      87: aload         5
      89: invokevirtual #62                 // Method javassist/compiler/ast/Expr.oprand2:()Ljavassist/compiler/ast/ASTree;
      92: invokevirtual #63                 // Method atArrayRead:(Ljavassist/compiler/ast/ASTree;Ljavassist/compiler/ast/ASTree;)V
      95: aload_0
      96: getfield      #35                 // Field exprType:I
      99: istore        6
     101: iload         6
     103: sipush        324
     106: if_icmpeq     133
     109: iload         6
     111: sipush        303
     114: if_icmpeq     133
     117: iload         6
     119: sipush        306
     122: if_icmpeq     133
     125: iload         6
     127: sipush        334
     130: if_icmpne     140
     133: aload_0
     134: sipush        324
     137: putfield      #35                 // Field exprType:I
     140: return
     141: aload_0
     142: aload_2
     143: invokevirtual #210                // Method atFieldPlusPlus:(Ljavassist/compiler/ast/ASTree;)V
     146: return

  protected void atFieldPlusPlus(javassist.compiler.ast.ASTree) throws javassist.compiler.CompileError;
    Code:
       0: aload_0
       1: aload_1
       2: invokevirtual #64                 // Method fieldAccess:(Ljavassist/compiler/ast/ASTree;)Ljavassist/CtField;
       5: astore_2
       6: aload_0
       7: aload_2
       8: invokespecial #65                 // Method atFieldRead:(Ljavassist/CtField;)V
      11: aload_0
      12: getfield      #35                 // Field exprType:I
      15: istore_3
      16: iload_3
      17: sipush        324
      20: if_icmpeq     44
      23: iload_3
      24: sipush        303
      27: if_icmpeq     44
      30: iload_3
      31: sipush        306
      34: if_icmpeq     44
      37: iload_3
      38: sipush        334
      41: if_icmpne     51
      44: aload_0
      45: sipush        324
      48: putfield      #35                 // Field exprType:I
      51: return

  public void atMember(javassist.compiler.ast.Member) throws javassist.compiler.CompileError;
    Code:
       0: aload_0
       1: aload_1
       2: invokespecial #153                // Method atFieldRead:(Ljavassist/compiler/ast/ASTree;)V
       5: return

  public void atVariable(javassist.compiler.ast.Variable) throws javassist.compiler.CompileError;
    Code:
       0: aload_1
       1: invokevirtual #51                 // Method javassist/compiler/ast/Variable.getDeclarator:()Ljavassist/compiler/ast/Declarator;
       4: astore_2
       5: aload_0
       6: aload_2
       7: invokevirtual #57                 // Method javassist/compiler/ast/Declarator.getType:()I
      10: putfield      #35                 // Field exprType:I
      13: aload_0
      14: aload_2
      15: invokevirtual #58                 // Method javassist/compiler/ast/Declarator.getArrayDim:()I
      18: putfield      #36                 // Field arrayDim:I
      21: aload_0
      22: aload_2
      23: invokevirtual #59                 // Method javassist/compiler/ast/Declarator.getClassName:()Ljava/lang/String;
      26: putfield      #37                 // Field className:Ljava/lang/String;
      29: return

  public void atKeyword(javassist.compiler.ast.Keyword) throws javassist.compiler.CompileError;
    Code:
       0: aload_0
       1: iconst_0
       2: putfield      #36                 // Field arrayDim:I
       5: aload_1
       6: invokevirtual #169                // Method javassist/compiler/ast/Keyword.get:()I
       9: istore_2
      10: iload_2
      11: lookupswitch  { // 5
                   336: 80
                   339: 80
                   410: 60
                   411: 60
                   412: 70
               default: 116
          }
      60: aload_0
      61: sipush        301
      64: putfield      #35                 // Field exprType:I
      67: goto          119
      70: aload_0
      71: sipush        412
      74: putfield      #35                 // Field exprType:I
      77: goto          119
      80: aload_0
      81: sipush        307
      84: putfield      #35                 // Field exprType:I
      87: iload_2
      88: sipush        339
      91: if_icmpne     105
      94: aload_0
      95: aload_0
      96: invokevirtual #211                // Method getThisName:()Ljava/lang/String;
      99: putfield      #37                 // Field className:Ljava/lang/String;
     102: goto          119
     105: aload_0
     106: aload_0
     107: invokevirtual #212                // Method getSuperName:()Ljava/lang/String;
     110: putfield      #37                 // Field className:Ljava/lang/String;
     113: goto          119
     116: invokestatic  #157                // Method fatal:()V
     119: return

  public void atStringL(javassist.compiler.ast.StringL) throws javassist.compiler.CompileError;
    Code:
       0: aload_0
       1: sipush        307
       4: putfield      #35                 // Field exprType:I
       7: aload_0
       8: iconst_0
       9: putfield      #36                 // Field arrayDim:I
      12: aload_0
      13: ldc           #86                 // String java/lang/String
      15: putfield      #37                 // Field className:Ljava/lang/String;
      18: return

  public void atIntConst(javassist.compiler.ast.IntConst) throws javassist.compiler.CompileError;
    Code:
       0: aload_0
       1: iconst_0
       2: putfield      #36                 // Field arrayDim:I
       5: aload_1
       6: invokevirtual #213                // Method javassist/compiler/ast/IntConst.getType:()I
       9: istore_2
      10: iload_2
      11: sipush        402
      14: if_icmpeq     24
      17: iload_2
      18: sipush        401
      21: if_icmpne     47
      24: aload_0
      25: iload_2
      26: sipush        402
      29: if_icmpne     38
      32: sipush        324
      35: goto          41
      38: sipush        306
      41: putfield      #35                 // Field exprType:I
      44: goto          54
      47: aload_0
      48: sipush        326
      51: putfield      #35                 // Field exprType:I
      54: return

  public void atDoubleConst(javassist.compiler.ast.DoubleConst) throws javassist.compiler.CompileError;
    Code:
       0: aload_0
       1: iconst_0
       2: putfield      #36                 // Field arrayDim:I
       5: aload_1
       6: invokevirtual #214                // Method javassist/compiler/ast/DoubleConst.getType:()I
       9: sipush        405
      12: if_icmpne     25
      15: aload_0
      16: sipush        312
      19: putfield      #35                 // Field exprType:I
      22: goto          32
      25: aload_0
      26: sipush        317
      29: putfield      #35                 // Field exprType:I
      32: return
}
