Compiled from "NamingExtension.java"
public class org.jboss.as.naming.subsystem.NamingExtension implements org.jboss.as.controller.Extension {
  public static final java.lang.String SUBSYSTEM_NAME;

  private static final java.lang.String NAMESPACE_1_0;

  private static final java.lang.String NAMESPACE_1_1;

  private static final java.lang.String NAMESPACE_1_2;

  private static final java.lang.String NAMESPACE_1_3;

  private static final java.lang.String NAMESPACE_1_4;

  static final java.lang.String NAMESPACE_2_0;

  private static final org.jboss.as.controller.ModelVersion CURRENT_MODEL_VERSION;

  static final java.lang.String RESOURCE_NAME;

  static final org.jboss.as.controller.PathElement SUBSYSTEM_PATH;

  static final org.jboss.as.controller.access.management.SensitiveTargetAccessConstraintDefinition JNDI_VIEW_CONSTRAINT;

  static final org.jboss.as.controller.access.management.SensitiveTargetAccessConstraintDefinition NAMING_BINDING_SENSITIVITY_CONSTRAINT;

  static final org.jboss.as.controller.access.management.ApplicationTypeAccessConstraintDefinition NAMING_BINDING_APPLICATION_CONSTRAINT;

  public org.jboss.as.naming.subsystem.NamingExtension();
    Code:
       0: aload_0
       1: invokespecial #2                  // Method java/lang/Object."<init>":()V
       4: return

  public static org.jboss.as.controller.descriptions.ResourceDescriptionResolver getResourceDescriptionResolver(java.lang.String);
    Code:
       0: new           #3                  // class org/jboss/as/controller/descriptions/StandardResourceDescriptionResolver
       3: dup
       4: aload_0
       5: getstatic     #4                  // Field RESOURCE_NAME:Ljava/lang/String;
       8: ldc           #5                  // class org/jboss/as/naming/subsystem/NamingExtension
      10: invokevirtual #6                  // Method java/lang/Class.getClassLoader:()Ljava/lang/ClassLoader;
      13: iconst_1
      14: iconst_1
      15: invokespecial #7                  // Method org/jboss/as/controller/descriptions/StandardResourceDescriptionResolver."<init>":(Ljava/lang/String;Ljava/lang/String;Ljava/lang/ClassLoader;ZZ)V
      18: areturn

  public void initialize(org.jboss.as.controller.ExtensionContext);
    Code:
       0: aload_1
       1: ldc           #8                  // String naming
       3: getstatic     #9                  // Field CURRENT_MODEL_VERSION:Lorg/jboss/as/controller/ModelVersion;
       6: invokeinterface #10,  3           // InterfaceMethod org/jboss/as/controller/ExtensionContext.registerSubsystem:(Ljava/lang/String;Lorg/jboss/as/controller/ModelVersion;)Lorg/jboss/as/controller/SubsystemRegistration;
      11: astore_2
      12: aload_2
      13: getstatic     #11                 // Field org/jboss/as/naming/subsystem/NamingSubsystemRootResourceDefinition.INSTANCE:Lorg/jboss/as/naming/subsystem/NamingSubsystemRootResourceDefinition;
      16: invokeinterface #12,  2           // InterfaceMethod org/jboss/as/controller/SubsystemRegistration.registerSubsystemModel:(Lorg/jboss/as/controller/ResourceDefinition;)Lorg/jboss/as/controller/registry/ManagementResourceRegistration;
      21: astore_3
      22: aload_3
      23: getstatic     #13                 // Field org/jboss/as/controller/operations/common/GenericSubsystemDescribeHandler.DEFINITION:Lorg/jboss/as/controller/SimpleOperationDefinition;
      26: getstatic     #14                 // Field org/jboss/as/controller/operations/common/GenericSubsystemDescribeHandler.INSTANCE:Lorg/jboss/as/controller/operations/common/GenericSubsystemDescribeHandler;
      29: invokeinterface #15,  3           // InterfaceMethod org/jboss/as/controller/registry/ManagementResourceRegistration.registerOperationHandler:(Lorg/jboss/as/controller/OperationDefinition;Lorg/jboss/as/controller/OperationStepHandler;)V
      34: aload_3
      35: getstatic     #16                 // Field org/jboss/as/naming/subsystem/NamingBindingResourceDefinition.INSTANCE:Lorg/jboss/as/naming/subsystem/NamingBindingResourceDefinition;
      38: invokeinterface #17,  2           // InterfaceMethod org/jboss/as/controller/registry/ManagementResourceRegistration.registerSubModel:(Lorg/jboss/as/controller/ResourceDefinition;)Lorg/jboss/as/controller/registry/ManagementResourceRegistration;
      43: pop
      44: aload_3
      45: getstatic     #18                 // Field org/jboss/as/naming/subsystem/RemoteNamingResourceDefinition.INSTANCE:Lorg/jboss/as/naming/subsystem/RemoteNamingResourceDefinition;
      48: invokeinterface #17,  2           // InterfaceMethod org/jboss/as/controller/registry/ManagementResourceRegistration.registerSubModel:(Lorg/jboss/as/controller/ResourceDefinition;)Lorg/jboss/as/controller/registry/ManagementResourceRegistration;
      53: pop
      54: aload_1
      55: invokeinterface #19,  1           // InterfaceMethod org/jboss/as/controller/ExtensionContext.isRuntimeOnlyRegistrationValid:()Z
      60: ifeq          76
      63: aload_3
      64: getstatic     #20                 // Field org/jboss/as/naming/subsystem/NamingSubsystemRootResourceDefinition.JNDI_VIEW:Lorg/jboss/as/controller/SimpleOperationDefinition;
      67: getstatic     #21                 // Field org/jboss/as/naming/management/JndiViewOperation.INSTANCE:Lorg/jboss/as/naming/management/JndiViewOperation;
      70: iconst_0
      71: invokeinterface #22,  4           // InterfaceMethod org/jboss/as/controller/registry/ManagementResourceRegistration.registerOperationHandler:(Lorg/jboss/as/controller/OperationDefinition;Lorg/jboss/as/controller/OperationStepHandler;Z)V
      76: aload_2
      77: getstatic     #23                 // Field org/jboss/as/naming/subsystem/NamingSubsystemXMLPersister.INSTANCE:Lorg/jboss/as/naming/subsystem/NamingSubsystemXMLPersister;
      80: invokeinterface #24,  2           // InterfaceMethod org/jboss/as/controller/SubsystemRegistration.registerXMLElementWriter:(Lorg/jboss/staxmapper/XMLElementWriter;)V
      85: return

  public void initializeParsers(org.jboss.as.controller.parsing.ExtensionParsingContext);
    Code:
       0: aload_1
       1: ldc           #8                  // String naming
       3: ldc           #25                 // String urn:jboss:domain:naming:1.0
       5: new           #26                 // class org/jboss/as/naming/subsystem/NamingSubsystem10Parser
       8: dup
       9: aload_1
      10: invokeinterface #27,  1           // InterfaceMethod org/jboss/as/controller/parsing/ExtensionParsingContext.getProcessType:()Lorg/jboss/as/controller/ProcessType;
      15: getstatic     #28                 // Field org/jboss/as/controller/ProcessType.APPLICATION_CLIENT:Lorg/jboss/as/controller/ProcessType;
      18: if_acmpne     25
      21: iconst_1
      22: goto          26
      25: iconst_0
      26: invokespecial #29                 // Method org/jboss/as/naming/subsystem/NamingSubsystem10Parser."<init>":(Z)V
      29: invokeinterface #30,  4           // InterfaceMethod org/jboss/as/controller/parsing/ExtensionParsingContext.setSubsystemXmlMapping:(Ljava/lang/String;Ljava/lang/String;Lorg/jboss/staxmapper/XMLElementReader;)V
      34: aload_1
      35: ldc           #8                  // String naming
      37: ldc           #31                 // String urn:jboss:domain:naming:1.1
      39: getstatic     #32                 // Field org/jboss/as/naming/subsystem/NamingSubsystem11Parser.INSTANCE:Lorg/jboss/as/naming/subsystem/NamingSubsystem11Parser;
      42: invokeinterface #30,  4           // InterfaceMethod org/jboss/as/controller/parsing/ExtensionParsingContext.setSubsystemXmlMapping:(Ljava/lang/String;Ljava/lang/String;Lorg/jboss/staxmapper/XMLElementReader;)V
      47: aload_1
      48: ldc           #8                  // String naming
      50: ldc           #33                 // String urn:jboss:domain:naming:1.2
      52: getstatic     #34                 // Field org/jboss/as/naming/subsystem/NamingSubsystem12Parser.INSTANCE:Lorg/jboss/as/naming/subsystem/NamingSubsystem12Parser;
      55: invokeinterface #30,  4           // InterfaceMethod org/jboss/as/controller/parsing/ExtensionParsingContext.setSubsystemXmlMapping:(Ljava/lang/String;Ljava/lang/String;Lorg/jboss/staxmapper/XMLElementReader;)V
      60: aload_1
      61: ldc           #8                  // String naming
      63: ldc           #35                 // String urn:jboss:domain:naming:1.3
      65: getstatic     #36                 // Field org/jboss/as/naming/subsystem/NamingSubsystem13Parser.INSTANCE:Lorg/jboss/as/naming/subsystem/NamingSubsystem13Parser;
      68: invokeinterface #30,  4           // InterfaceMethod org/jboss/as/controller/parsing/ExtensionParsingContext.setSubsystemXmlMapping:(Ljava/lang/String;Ljava/lang/String;Lorg/jboss/staxmapper/XMLElementReader;)V
      73: aload_1
      74: ldc           #8                  // String naming
      76: ldc           #37                 // String urn:jboss:domain:naming:1.4
      78: getstatic     #38                 // Field org/jboss/as/naming/subsystem/NamingSubsystem14Parser.INSTANCE:Lorg/jboss/as/naming/subsystem/NamingSubsystem14Parser;
      81: invokeinterface #30,  4           // InterfaceMethod org/jboss/as/controller/parsing/ExtensionParsingContext.setSubsystemXmlMapping:(Ljava/lang/String;Ljava/lang/String;Lorg/jboss/staxmapper/XMLElementReader;)V
      86: aload_1
      87: ldc           #8                  // String naming
      89: ldc           #39                 // String urn:jboss:domain:naming:2.0
      91: getstatic     #40                 // Field org/jboss/as/naming/subsystem/NamingSubsystem20Parser.INSTANCE:Lorg/jboss/as/naming/subsystem/NamingSubsystem20Parser;
      94: invokeinterface #30,  4           // InterfaceMethod org/jboss/as/controller/parsing/ExtensionParsingContext.setSubsystemXmlMapping:(Ljava/lang/String;Ljava/lang/String;Lorg/jboss/staxmapper/XMLElementReader;)V
      99: return

  static {};
    Code:
       0: iconst_2
       1: iconst_0
       2: iconst_0
       3: invokestatic  #41                 // Method org/jboss/as/controller/ModelVersion.create:(III)Lorg/jboss/as/controller/ModelVersion;
       6: putstatic     #9                  // Field CURRENT_MODEL_VERSION:Lorg/jboss/as/controller/ModelVersion;
       9: new           #42                 // class java/lang/StringBuilder
      12: dup
      13: invokespecial #43                 // Method java/lang/StringBuilder."<init>":()V
      16: ldc           #5                  // class org/jboss/as/naming/subsystem/NamingExtension
      18: invokevirtual #44                 // Method java/lang/Class.getPackage:()Ljava/lang/Package;
      21: invokevirtual #45                 // Method java/lang/Package.getName:()Ljava/lang/String;
      24: invokevirtual #46                 // Method java/lang/StringBuilder.append:(Ljava/lang/String;)Ljava/lang/StringBuilder;
      27: ldc           #47                 // String .LocalDescriptions
      29: invokevirtual #46                 // Method java/lang/StringBuilder.append:(Ljava/lang/String;)Ljava/lang/StringBuilder;
      32: invokevirtual #48                 // Method java/lang/StringBuilder.toString:()Ljava/lang/String;
      35: putstatic     #4                  // Field RESOURCE_NAME:Ljava/lang/String;
      38: ldc           #49                 // String subsystem
      40: ldc           #8                  // String naming
      42: invokestatic  #50                 // Method org/jboss/as/controller/PathElement.pathElement:(Ljava/lang/String;Ljava/lang/String;)Lorg/jboss/as/controller/PathElement;
      45: putstatic     #51                 // Field SUBSYSTEM_PATH:Lorg/jboss/as/controller/PathElement;
      48: new           #52                 // class org/jboss/as/controller/access/management/SensitiveTargetAccessConstraintDefinition
      51: dup
      52: new           #53                 // class org/jboss/as/controller/access/constraint/SensitivityClassification
      55: dup
      56: ldc           #8                  // String naming
      58: ldc           #54                 // String jndi-view
      60: iconst_0
      61: iconst_1
      62: iconst_1
      63: invokespecial #55                 // Method org/jboss/as/controller/access/constraint/SensitivityClassification."<init>":(Ljava/lang/String;Ljava/lang/String;ZZZ)V
      66: invokespecial #56                 // Method org/jboss/as/controller/access/management/SensitiveTargetAccessConstraintDefinition."<init>":(Lorg/jboss/as/controller/access/constraint/SensitivityClassification;)V
      69: putstatic     #57                 // Field JNDI_VIEW_CONSTRAINT:Lorg/jboss/as/controller/access/management/SensitiveTargetAccessConstraintDefinition;
      72: new           #52                 // class org/jboss/as/controller/access/management/SensitiveTargetAccessConstraintDefinition
      75: dup
      76: new           #53                 // class org/jboss/as/controller/access/constraint/SensitivityClassification
      79: dup
      80: ldc           #8                  // String naming
      82: ldc           #58                 // String naming-binding
      84: iconst_0
      85: iconst_0
      86: iconst_0
      87: invokespecial #55                 // Method org/jboss/as/controller/access/constraint/SensitivityClassification."<init>":(Ljava/lang/String;Ljava/lang/String;ZZZ)V
      90: invokespecial #56                 // Method org/jboss/as/controller/access/management/SensitiveTargetAccessConstraintDefinition."<init>":(Lorg/jboss/as/controller/access/constraint/SensitivityClassification;)V
      93: putstatic     #59                 // Field NAMING_BINDING_SENSITIVITY_CONSTRAINT:Lorg/jboss/as/controller/access/management/SensitiveTargetAccessConstraintDefinition;
      96: new           #60                 // class org/jboss/as/controller/access/management/ApplicationTypeAccessConstraintDefinition
      99: dup
     100: new           #61                 // class org/jboss/as/controller/access/constraint/ApplicationTypeConfig
     103: dup
     104: ldc           #8                  // String naming
     106: ldc           #63                 // String binding
     108: invokespecial #64                 // Method org/jboss/as/controller/access/constraint/ApplicationTypeConfig."<init>":(Ljava/lang/String;Ljava/lang/String;)V
     111: invokespecial #65                 // Method org/jboss/as/controller/access/management/ApplicationTypeAccessConstraintDefinition."<init>":(Lorg/jboss/as/controller/access/constraint/ApplicationTypeConfig;)V
     114: putstatic     #66                 // Field NAMING_BINDING_APPLICATION_CONSTRAINT:Lorg/jboss/as/controller/access/management/ApplicationTypeAccessConstraintDefinition;
     117: return
}
