Compiled from "Transport.java"
public class org.wildfly.swarm.config.jgroups.stack.Transport<T extends org.wildfly.swarm.config.jgroups.stack.Transport<T>> extends java.util.HashMap {
  private java.lang.String key;

  private java.beans.PropertyChangeSupport pcs;

  private org.wildfly.swarm.config.jgroups.stack.Transport$TransportResources subresources;

  private java.lang.String diagnosticsSocketBinding;

  private java.lang.String machine;

  private java.lang.String module;

  private java.util.Map properties;

  private java.lang.String rack;

  private java.lang.String site;

  private java.lang.String socketBinding;

  public org.wildfly.swarm.config.jgroups.stack.Transport(java.lang.String);
    Code:
       0: aload_0
       1: invokespecial #1                  // Method java/util/HashMap."<init>":()V
       4: aload_0
       5: new           #2                  // class org/wildfly/swarm/config/jgroups/stack/Transport$TransportResources
       8: dup
       9: invokespecial #3                  // Method org/wildfly/swarm/config/jgroups/stack/Transport$TransportResources."<init>":()V
      12: putfield      #4                  // Field subresources:Lorg/wildfly/swarm/config/jgroups/stack/Transport$TransportResources;
      15: aload_0
      16: aload_1
      17: putfield      #5                  // Field key:Ljava/lang/String;
      20: return

  public java.lang.String getKey();
    Code:
       0: aload_0
       1: getfield      #5                  // Field key:Ljava/lang/String;
       4: areturn

  public void addPropertyChangeListener(java.beans.PropertyChangeListener);
    Code:
       0: aconst_null
       1: aload_0
       2: getfield      #6                  // Field pcs:Ljava/beans/PropertyChangeSupport;
       5: if_acmpne     20
       8: aload_0
       9: new           #7                  // class java/beans/PropertyChangeSupport
      12: dup
      13: aload_0
      14: invokespecial #8                  // Method java/beans/PropertyChangeSupport."<init>":(Ljava/lang/Object;)V
      17: putfield      #6                  // Field pcs:Ljava/beans/PropertyChangeSupport;
      20: aload_0
      21: getfield      #6                  // Field pcs:Ljava/beans/PropertyChangeSupport;
      24: aload_1
      25: invokevirtual #9                  // Method java/beans/PropertyChangeSupport.addPropertyChangeListener:(Ljava/beans/PropertyChangeListener;)V
      28: return

  public void removePropertyChangeListener(java.beans.PropertyChangeListener);
    Code:
       0: aload_0
       1: getfield      #6                  // Field pcs:Ljava/beans/PropertyChangeSupport;
       4: ifnull        15
       7: aload_0
       8: getfield      #6                  // Field pcs:Ljava/beans/PropertyChangeSupport;
      11: aload_1
      12: invokevirtual #10                 // Method java/beans/PropertyChangeSupport.removePropertyChangeListener:(Ljava/beans/PropertyChangeListener;)V
      15: return

  public org.wildfly.swarm.config.jgroups.stack.Transport$TransportResources subresources();
    Code:
       0: aload_0
       1: getfield      #4                  // Field subresources:Lorg/wildfly/swarm/config/jgroups/stack/Transport$TransportResources;
       4: areturn

  public T properties(java.util.List<org.wildfly.swarm.config.jgroups.Property>);
    Code:
       0: aload_0
       1: getfield      #4                  // Field subresources:Lorg/wildfly/swarm/config/jgroups/stack/Transport$TransportResources;
       4: aload_1
       5: invokestatic  #11                 // Method org/wildfly/swarm/config/jgroups/stack/Transport$TransportResources.access$002:(Lorg/wildfly/swarm/config/jgroups/stack/Transport$TransportResources;Ljava/util/List;)Ljava/util/List;
       8: pop
       9: aload_0
      10: areturn

  public T property(org.wildfly.swarm.config.jgroups.Property);
    Code:
       0: aload_0
       1: getfield      #4                  // Field subresources:Lorg/wildfly/swarm/config/jgroups/stack/Transport$TransportResources;
       4: invokestatic  #12                 // Method org/wildfly/swarm/config/jgroups/stack/Transport$TransportResources.access$000:(Lorg/wildfly/swarm/config/jgroups/stack/Transport$TransportResources;)Ljava/util/List;
       7: aload_1
       8: invokeinterface #13,  2           // InterfaceMethod java/util/List.add:(Ljava/lang/Object;)Z
      13: pop
      14: aload_0
      15: areturn

  public T property(java.lang.String, org.wildfly.swarm.config.jgroups.PropertyConsumer);
    Code:
       0: new           #14                 // class org/wildfly/swarm/config/jgroups/Property
       3: dup
       4: aload_1
       5: invokespecial #15                 // Method org/wildfly/swarm/config/jgroups/Property."<init>":(Ljava/lang/String;)V
       8: astore_3
       9: aload_2
      10: ifnull        20
      13: aload_2
      14: aload_3
      15: invokeinterface #16,  2           // InterfaceMethod org/wildfly/swarm/config/jgroups/PropertyConsumer.accept:(Lorg/wildfly/swarm/config/jgroups/Property;)V
      20: aload_0
      21: aload_3
      22: invokevirtual #17                 // Method property:(Lorg/wildfly/swarm/config/jgroups/Property;)Lorg/wildfly/swarm/config/jgroups/stack/Transport;
      25: pop
      26: aload_0
      27: areturn

  public T property(java.lang.String);
    Code:
       0: aload_0
       1: aload_1
       2: aconst_null
       3: invokevirtual #18                 // Method property:(Ljava/lang/String;Lorg/wildfly/swarm/config/jgroups/PropertyConsumer;)Lorg/wildfly/swarm/config/jgroups/stack/Transport;
       6: pop
       7: aload_0
       8: areturn

  public T property(org.wildfly.swarm.config.jgroups.PropertySupplier);
    Code:
       0: aload_0
       1: aload_1
       2: invokeinterface #19,  1           // InterfaceMethod org/wildfly/swarm/config/jgroups/PropertySupplier.get:()Lorg/wildfly/swarm/config/jgroups/Property;
       7: invokevirtual #17                 // Method property:(Lorg/wildfly/swarm/config/jgroups/Property;)Lorg/wildfly/swarm/config/jgroups/stack/Transport;
      10: pop
      11: aload_0
      12: areturn

  public T oobThreadPool(org.wildfly.swarm.config.jgroups.stack.transport.OobThreadPool);
    Code:
       0: aload_0
       1: getfield      #4                  // Field subresources:Lorg/wildfly/swarm/config/jgroups/stack/Transport$TransportResources;
       4: aload_1
       5: invokestatic  #20                 // Method org/wildfly/swarm/config/jgroups/stack/Transport$TransportResources.access$102:(Lorg/wildfly/swarm/config/jgroups/stack/Transport$TransportResources;Lorg/wildfly/swarm/config/jgroups/stack/transport/OobThreadPool;)Lorg/wildfly/swarm/config/jgroups/stack/transport/OobThreadPool;
       8: pop
       9: aload_0
      10: areturn

  public T oobThreadPool(org.wildfly.swarm.config.jgroups.stack.transport.OobThreadPoolConsumer);
    Code:
       0: new           #21                 // class org/wildfly/swarm/config/jgroups/stack/transport/OobThreadPool
       3: dup
       4: invokespecial #22                 // Method org/wildfly/swarm/config/jgroups/stack/transport/OobThreadPool."<init>":()V
       7: astore_2
       8: aload_1
       9: ifnull        19
      12: aload_1
      13: aload_2
      14: invokeinterface #23,  2           // InterfaceMethod org/wildfly/swarm/config/jgroups/stack/transport/OobThreadPoolConsumer.accept:(Lorg/wildfly/swarm/config/jgroups/stack/transport/OobThreadPool;)V
      19: aload_0
      20: getfield      #4                  // Field subresources:Lorg/wildfly/swarm/config/jgroups/stack/Transport$TransportResources;
      23: aload_2
      24: invokestatic  #20                 // Method org/wildfly/swarm/config/jgroups/stack/Transport$TransportResources.access$102:(Lorg/wildfly/swarm/config/jgroups/stack/Transport$TransportResources;Lorg/wildfly/swarm/config/jgroups/stack/transport/OobThreadPool;)Lorg/wildfly/swarm/config/jgroups/stack/transport/OobThreadPool;
      27: pop
      28: aload_0
      29: areturn

  public T oobThreadPool();
    Code:
       0: new           #21                 // class org/wildfly/swarm/config/jgroups/stack/transport/OobThreadPool
       3: dup
       4: invokespecial #22                 // Method org/wildfly/swarm/config/jgroups/stack/transport/OobThreadPool."<init>":()V
       7: astore_1
       8: aload_0
       9: getfield      #4                  // Field subresources:Lorg/wildfly/swarm/config/jgroups/stack/Transport$TransportResources;
      12: aload_1
      13: invokestatic  #20                 // Method org/wildfly/swarm/config/jgroups/stack/Transport$TransportResources.access$102:(Lorg/wildfly/swarm/config/jgroups/stack/Transport$TransportResources;Lorg/wildfly/swarm/config/jgroups/stack/transport/OobThreadPool;)Lorg/wildfly/swarm/config/jgroups/stack/transport/OobThreadPool;
      16: pop
      17: aload_0
      18: areturn

  public T oobThreadPool(org.wildfly.swarm.config.jgroups.stack.transport.OobThreadPoolSupplier);
    Code:
       0: aload_0
       1: getfield      #4                  // Field subresources:Lorg/wildfly/swarm/config/jgroups/stack/Transport$TransportResources;
       4: aload_1
       5: invokeinterface #24,  1           // InterfaceMethod org/wildfly/swarm/config/jgroups/stack/transport/OobThreadPoolSupplier.get:()Lorg/wildfly/swarm/config/jgroups/stack/transport/OobThreadPool;
      10: invokestatic  #20                 // Method org/wildfly/swarm/config/jgroups/stack/Transport$TransportResources.access$102:(Lorg/wildfly/swarm/config/jgroups/stack/Transport$TransportResources;Lorg/wildfly/swarm/config/jgroups/stack/transport/OobThreadPool;)Lorg/wildfly/swarm/config/jgroups/stack/transport/OobThreadPool;
      13: pop
      14: aload_0
      15: areturn

  public T internalThreadPool(org.wildfly.swarm.config.jgroups.stack.transport.InternalThreadPool);
    Code:
       0: aload_0
       1: getfield      #4                  // Field subresources:Lorg/wildfly/swarm/config/jgroups/stack/Transport$TransportResources;
       4: aload_1
       5: invokestatic  #25                 // Method org/wildfly/swarm/config/jgroups/stack/Transport$TransportResources.access$202:(Lorg/wildfly/swarm/config/jgroups/stack/Transport$TransportResources;Lorg/wildfly/swarm/config/jgroups/stack/transport/InternalThreadPool;)Lorg/wildfly/swarm/config/jgroups/stack/transport/InternalThreadPool;
       8: pop
       9: aload_0
      10: areturn

  public T internalThreadPool(org.wildfly.swarm.config.jgroups.stack.transport.InternalThreadPoolConsumer);
    Code:
       0: new           #26                 // class org/wildfly/swarm/config/jgroups/stack/transport/InternalThreadPool
       3: dup
       4: invokespecial #27                 // Method org/wildfly/swarm/config/jgroups/stack/transport/InternalThreadPool."<init>":()V
       7: astore_2
       8: aload_1
       9: ifnull        19
      12: aload_1
      13: aload_2
      14: invokeinterface #28,  2           // InterfaceMethod org/wildfly/swarm/config/jgroups/stack/transport/InternalThreadPoolConsumer.accept:(Lorg/wildfly/swarm/config/jgroups/stack/transport/InternalThreadPool;)V
      19: aload_0
      20: getfield      #4                  // Field subresources:Lorg/wildfly/swarm/config/jgroups/stack/Transport$TransportResources;
      23: aload_2
      24: invokestatic  #25                 // Method org/wildfly/swarm/config/jgroups/stack/Transport$TransportResources.access$202:(Lorg/wildfly/swarm/config/jgroups/stack/Transport$TransportResources;Lorg/wildfly/swarm/config/jgroups/stack/transport/InternalThreadPool;)Lorg/wildfly/swarm/config/jgroups/stack/transport/InternalThreadPool;
      27: pop
      28: aload_0
      29: areturn

  public T internalThreadPool();
    Code:
       0: new           #26                 // class org/wildfly/swarm/config/jgroups/stack/transport/InternalThreadPool
       3: dup
       4: invokespecial #27                 // Method org/wildfly/swarm/config/jgroups/stack/transport/InternalThreadPool."<init>":()V
       7: astore_1
       8: aload_0
       9: getfield      #4                  // Field subresources:Lorg/wildfly/swarm/config/jgroups/stack/Transport$TransportResources;
      12: aload_1
      13: invokestatic  #25                 // Method org/wildfly/swarm/config/jgroups/stack/Transport$TransportResources.access$202:(Lorg/wildfly/swarm/config/jgroups/stack/Transport$TransportResources;Lorg/wildfly/swarm/config/jgroups/stack/transport/InternalThreadPool;)Lorg/wildfly/swarm/config/jgroups/stack/transport/InternalThreadPool;
      16: pop
      17: aload_0
      18: areturn

  public T internalThreadPool(org.wildfly.swarm.config.jgroups.stack.transport.InternalThreadPoolSupplier);
    Code:
       0: aload_0
       1: getfield      #4                  // Field subresources:Lorg/wildfly/swarm/config/jgroups/stack/Transport$TransportResources;
       4: aload_1
       5: invokeinterface #29,  1           // InterfaceMethod org/wildfly/swarm/config/jgroups/stack/transport/InternalThreadPoolSupplier.get:()Lorg/wildfly/swarm/config/jgroups/stack/transport/InternalThreadPool;
      10: invokestatic  #25                 // Method org/wildfly/swarm/config/jgroups/stack/Transport$TransportResources.access$202:(Lorg/wildfly/swarm/config/jgroups/stack/Transport$TransportResources;Lorg/wildfly/swarm/config/jgroups/stack/transport/InternalThreadPool;)Lorg/wildfly/swarm/config/jgroups/stack/transport/InternalThreadPool;
      13: pop
      14: aload_0
      15: areturn

  public T defaultThreadPool(org.wildfly.swarm.config.jgroups.stack.transport.DefaultThreadPool);
    Code:
       0: aload_0
       1: getfield      #4                  // Field subresources:Lorg/wildfly/swarm/config/jgroups/stack/Transport$TransportResources;
       4: aload_1
       5: invokestatic  #30                 // Method org/wildfly/swarm/config/jgroups/stack/Transport$TransportResources.access$302:(Lorg/wildfly/swarm/config/jgroups/stack/Transport$TransportResources;Lorg/wildfly/swarm/config/jgroups/stack/transport/DefaultThreadPool;)Lorg/wildfly/swarm/config/jgroups/stack/transport/DefaultThreadPool;
       8: pop
       9: aload_0
      10: areturn

  public T defaultThreadPool(org.wildfly.swarm.config.jgroups.stack.transport.DefaultThreadPoolConsumer);
    Code:
       0: new           #31                 // class org/wildfly/swarm/config/jgroups/stack/transport/DefaultThreadPool
       3: dup
       4: invokespecial #32                 // Method org/wildfly/swarm/config/jgroups/stack/transport/DefaultThreadPool."<init>":()V
       7: astore_2
       8: aload_1
       9: ifnull        19
      12: aload_1
      13: aload_2
      14: invokeinterface #33,  2           // InterfaceMethod org/wildfly/swarm/config/jgroups/stack/transport/DefaultThreadPoolConsumer.accept:(Lorg/wildfly/swarm/config/jgroups/stack/transport/DefaultThreadPool;)V
      19: aload_0
      20: getfield      #4                  // Field subresources:Lorg/wildfly/swarm/config/jgroups/stack/Transport$TransportResources;
      23: aload_2
      24: invokestatic  #30                 // Method org/wildfly/swarm/config/jgroups/stack/Transport$TransportResources.access$302:(Lorg/wildfly/swarm/config/jgroups/stack/Transport$TransportResources;Lorg/wildfly/swarm/config/jgroups/stack/transport/DefaultThreadPool;)Lorg/wildfly/swarm/config/jgroups/stack/transport/DefaultThreadPool;
      27: pop
      28: aload_0
      29: areturn

  public T defaultThreadPool();
    Code:
       0: new           #31                 // class org/wildfly/swarm/config/jgroups/stack/transport/DefaultThreadPool
       3: dup
       4: invokespecial #32                 // Method org/wildfly/swarm/config/jgroups/stack/transport/DefaultThreadPool."<init>":()V
       7: astore_1
       8: aload_0
       9: getfield      #4                  // Field subresources:Lorg/wildfly/swarm/config/jgroups/stack/Transport$TransportResources;
      12: aload_1
      13: invokestatic  #30                 // Method org/wildfly/swarm/config/jgroups/stack/Transport$TransportResources.access$302:(Lorg/wildfly/swarm/config/jgroups/stack/Transport$TransportResources;Lorg/wildfly/swarm/config/jgroups/stack/transport/DefaultThreadPool;)Lorg/wildfly/swarm/config/jgroups/stack/transport/DefaultThreadPool;
      16: pop
      17: aload_0
      18: areturn

  public T defaultThreadPool(org.wildfly.swarm.config.jgroups.stack.transport.DefaultThreadPoolSupplier);
    Code:
       0: aload_0
       1: getfield      #4                  // Field subresources:Lorg/wildfly/swarm/config/jgroups/stack/Transport$TransportResources;
       4: aload_1
       5: invokeinterface #34,  1           // InterfaceMethod org/wildfly/swarm/config/jgroups/stack/transport/DefaultThreadPoolSupplier.get:()Lorg/wildfly/swarm/config/jgroups/stack/transport/DefaultThreadPool;
      10: invokestatic  #30                 // Method org/wildfly/swarm/config/jgroups/stack/Transport$TransportResources.access$302:(Lorg/wildfly/swarm/config/jgroups/stack/Transport$TransportResources;Lorg/wildfly/swarm/config/jgroups/stack/transport/DefaultThreadPool;)Lorg/wildfly/swarm/config/jgroups/stack/transport/DefaultThreadPool;
      13: pop
      14: aload_0
      15: areturn

  public T timerThreadPool(org.wildfly.swarm.config.jgroups.stack.transport.TimerThreadPool);
    Code:
       0: aload_0
       1: getfield      #4                  // Field subresources:Lorg/wildfly/swarm/config/jgroups/stack/Transport$TransportResources;
       4: aload_1
       5: invokestatic  #35                 // Method org/wildfly/swarm/config/jgroups/stack/Transport$TransportResources.access$402:(Lorg/wildfly/swarm/config/jgroups/stack/Transport$TransportResources;Lorg/wildfly/swarm/config/jgroups/stack/transport/TimerThreadPool;)Lorg/wildfly/swarm/config/jgroups/stack/transport/TimerThreadPool;
       8: pop
       9: aload_0
      10: areturn

  public T timerThreadPool(org.wildfly.swarm.config.jgroups.stack.transport.TimerThreadPoolConsumer);
    Code:
       0: new           #36                 // class org/wildfly/swarm/config/jgroups/stack/transport/TimerThreadPool
       3: dup
       4: invokespecial #37                 // Method org/wildfly/swarm/config/jgroups/stack/transport/TimerThreadPool."<init>":()V
       7: astore_2
       8: aload_1
       9: ifnull        19
      12: aload_1
      13: aload_2
      14: invokeinterface #38,  2           // InterfaceMethod org/wildfly/swarm/config/jgroups/stack/transport/TimerThreadPoolConsumer.accept:(Lorg/wildfly/swarm/config/jgroups/stack/transport/TimerThreadPool;)V
      19: aload_0
      20: getfield      #4                  // Field subresources:Lorg/wildfly/swarm/config/jgroups/stack/Transport$TransportResources;
      23: aload_2
      24: invokestatic  #35                 // Method org/wildfly/swarm/config/jgroups/stack/Transport$TransportResources.access$402:(Lorg/wildfly/swarm/config/jgroups/stack/Transport$TransportResources;Lorg/wildfly/swarm/config/jgroups/stack/transport/TimerThreadPool;)Lorg/wildfly/swarm/config/jgroups/stack/transport/TimerThreadPool;
      27: pop
      28: aload_0
      29: areturn

  public T timerThreadPool();
    Code:
       0: new           #36                 // class org/wildfly/swarm/config/jgroups/stack/transport/TimerThreadPool
       3: dup
       4: invokespecial #37                 // Method org/wildfly/swarm/config/jgroups/stack/transport/TimerThreadPool."<init>":()V
       7: astore_1
       8: aload_0
       9: getfield      #4                  // Field subresources:Lorg/wildfly/swarm/config/jgroups/stack/Transport$TransportResources;
      12: aload_1
      13: invokestatic  #35                 // Method org/wildfly/swarm/config/jgroups/stack/Transport$TransportResources.access$402:(Lorg/wildfly/swarm/config/jgroups/stack/Transport$TransportResources;Lorg/wildfly/swarm/config/jgroups/stack/transport/TimerThreadPool;)Lorg/wildfly/swarm/config/jgroups/stack/transport/TimerThreadPool;
      16: pop
      17: aload_0
      18: areturn

  public T timerThreadPool(org.wildfly.swarm.config.jgroups.stack.transport.TimerThreadPoolSupplier);
    Code:
       0: aload_0
       1: getfield      #4                  // Field subresources:Lorg/wildfly/swarm/config/jgroups/stack/Transport$TransportResources;
       4: aload_1
       5: invokeinterface #39,  1           // InterfaceMethod org/wildfly/swarm/config/jgroups/stack/transport/TimerThreadPoolSupplier.get:()Lorg/wildfly/swarm/config/jgroups/stack/transport/TimerThreadPool;
      10: invokestatic  #35                 // Method org/wildfly/swarm/config/jgroups/stack/Transport$TransportResources.access$402:(Lorg/wildfly/swarm/config/jgroups/stack/Transport$TransportResources;Lorg/wildfly/swarm/config/jgroups/stack/transport/TimerThreadPool;)Lorg/wildfly/swarm/config/jgroups/stack/transport/TimerThreadPool;
      13: pop
      14: aload_0
      15: areturn

  public java.lang.String diagnosticsSocketBinding();
    Code:
       0: aload_0
       1: getfield      #40                 // Field diagnosticsSocketBinding:Ljava/lang/String;
       4: areturn

  public T diagnosticsSocketBinding(java.lang.String);
    Code:
       0: aload_0
       1: getfield      #40                 // Field diagnosticsSocketBinding:Ljava/lang/String;
       4: astore_2
       5: aload_0
       6: aload_1
       7: putfield      #40                 // Field diagnosticsSocketBinding:Ljava/lang/String;
      10: aload_0
      11: getfield      #6                  // Field pcs:Ljava/beans/PropertyChangeSupport;
      14: ifnull        28
      17: aload_0
      18: getfield      #6                  // Field pcs:Ljava/beans/PropertyChangeSupport;
      21: ldc           #41                 // String diagnosticsSocketBinding
      23: aload_2
      24: aload_1
      25: invokevirtual #42                 // Method java/beans/PropertyChangeSupport.firePropertyChange:(Ljava/lang/String;Ljava/lang/Object;Ljava/lang/Object;)V
      28: aload_0
      29: areturn

  public java.lang.String machine();
    Code:
       0: aload_0
       1: getfield      #43                 // Field machine:Ljava/lang/String;
       4: areturn

  public T machine(java.lang.String);
    Code:
       0: aload_0
       1: getfield      #43                 // Field machine:Ljava/lang/String;
       4: astore_2
       5: aload_0
       6: aload_1
       7: putfield      #43                 // Field machine:Ljava/lang/String;
      10: aload_0
      11: getfield      #6                  // Field pcs:Ljava/beans/PropertyChangeSupport;
      14: ifnull        28
      17: aload_0
      18: getfield      #6                  // Field pcs:Ljava/beans/PropertyChangeSupport;
      21: ldc           #44                 // String machine
      23: aload_2
      24: aload_1
      25: invokevirtual #42                 // Method java/beans/PropertyChangeSupport.firePropertyChange:(Ljava/lang/String;Ljava/lang/Object;Ljava/lang/Object;)V
      28: aload_0
      29: areturn

  public java.lang.String module();
    Code:
       0: aload_0
       1: getfield      #45                 // Field module:Ljava/lang/String;
       4: areturn

  public T module(java.lang.String);
    Code:
       0: aload_0
       1: getfield      #45                 // Field module:Ljava/lang/String;
       4: astore_2
       5: aload_0
       6: aload_1
       7: putfield      #45                 // Field module:Ljava/lang/String;
      10: aload_0
      11: getfield      #6                  // Field pcs:Ljava/beans/PropertyChangeSupport;
      14: ifnull        28
      17: aload_0
      18: getfield      #6                  // Field pcs:Ljava/beans/PropertyChangeSupport;
      21: ldc           #46                 // String module
      23: aload_2
      24: aload_1
      25: invokevirtual #42                 // Method java/beans/PropertyChangeSupport.firePropertyChange:(Ljava/lang/String;Ljava/lang/Object;Ljava/lang/Object;)V
      28: aload_0
      29: areturn

  public java.util.Map properties();
    Code:
       0: aload_0
       1: getfield      #47                 // Field properties:Ljava/util/Map;
       4: areturn

  public T properties(java.util.Map);
    Code:
       0: aload_0
       1: getfield      #47                 // Field properties:Ljava/util/Map;
       4: astore_2
       5: aload_0
       6: aload_1
       7: putfield      #47                 // Field properties:Ljava/util/Map;
      10: aload_0
      11: getfield      #6                  // Field pcs:Ljava/beans/PropertyChangeSupport;
      14: ifnull        28
      17: aload_0
      18: getfield      #6                  // Field pcs:Ljava/beans/PropertyChangeSupport;
      21: ldc           #48                 // String properties
      23: aload_2
      24: aload_1
      25: invokevirtual #42                 // Method java/beans/PropertyChangeSupport.firePropertyChange:(Ljava/lang/String;Ljava/lang/Object;Ljava/lang/Object;)V
      28: aload_0
      29: areturn

  public T property(java.lang.String, java.lang.Object);
    Code:
       0: aload_0
       1: getfield      #47                 // Field properties:Ljava/util/Map;
       4: ifnonnull     18
       7: aload_0
       8: new           #49                 // class java/util/HashMap
      11: dup
      12: invokespecial #1                  // Method java/util/HashMap."<init>":()V
      15: putfield      #47                 // Field properties:Ljava/util/Map;
      18: aload_0
      19: getfield      #47                 // Field properties:Ljava/util/Map;
      22: aload_1
      23: aload_2
      24: invokeinterface #50,  3           // InterfaceMethod java/util/Map.put:(Ljava/lang/Object;Ljava/lang/Object;)Ljava/lang/Object;
      29: pop
      30: aload_0
      31: areturn

  public java.lang.String rack();
    Code:
       0: aload_0
       1: getfield      #51                 // Field rack:Ljava/lang/String;
       4: areturn

  public T rack(java.lang.String);
    Code:
       0: aload_0
       1: getfield      #51                 // Field rack:Ljava/lang/String;
       4: astore_2
       5: aload_0
       6: aload_1
       7: putfield      #51                 // Field rack:Ljava/lang/String;
      10: aload_0
      11: getfield      #6                  // Field pcs:Ljava/beans/PropertyChangeSupport;
      14: ifnull        28
      17: aload_0
      18: getfield      #6                  // Field pcs:Ljava/beans/PropertyChangeSupport;
      21: ldc           #52                 // String rack
      23: aload_2
      24: aload_1
      25: invokevirtual #42                 // Method java/beans/PropertyChangeSupport.firePropertyChange:(Ljava/lang/String;Ljava/lang/Object;Ljava/lang/Object;)V
      28: aload_0
      29: areturn

  public java.lang.String site();
    Code:
       0: aload_0
       1: getfield      #53                 // Field site:Ljava/lang/String;
       4: areturn

  public T site(java.lang.String);
    Code:
       0: aload_0
       1: getfield      #53                 // Field site:Ljava/lang/String;
       4: astore_2
       5: aload_0
       6: aload_1
       7: putfield      #53                 // Field site:Ljava/lang/String;
      10: aload_0
      11: getfield      #6                  // Field pcs:Ljava/beans/PropertyChangeSupport;
      14: ifnull        28
      17: aload_0
      18: getfield      #6                  // Field pcs:Ljava/beans/PropertyChangeSupport;
      21: ldc           #54                 // String site
      23: aload_2
      24: aload_1
      25: invokevirtual #42                 // Method java/beans/PropertyChangeSupport.firePropertyChange:(Ljava/lang/String;Ljava/lang/Object;Ljava/lang/Object;)V
      28: aload_0
      29: areturn

  public java.lang.String socketBinding();
    Code:
       0: aload_0
       1: getfield      #55                 // Field socketBinding:Ljava/lang/String;
       4: areturn

  public T socketBinding(java.lang.String);
    Code:
       0: aload_0
       1: getfield      #55                 // Field socketBinding:Ljava/lang/String;
       4: astore_2
       5: aload_0
       6: aload_1
       7: putfield      #55                 // Field socketBinding:Ljava/lang/String;
      10: aload_0
      11: getfield      #6                  // Field pcs:Ljava/beans/PropertyChangeSupport;
      14: ifnull        28
      17: aload_0
      18: getfield      #6                  // Field pcs:Ljava/beans/PropertyChangeSupport;
      21: ldc           #56                 // String socketBinding
      23: aload_2
      24: aload_1
      25: invokevirtual #42                 // Method java/beans/PropertyChangeSupport.firePropertyChange:(Ljava/lang/String;Ljava/lang/Object;Ljava/lang/Object;)V
      28: aload_0
      29: areturn
}
