Compiled from "Parameter.java"
public final class io.fabric8.swagger.model.Parameter$ParamType extends java.lang.Enum<io.fabric8.swagger.model.Parameter$ParamType> {
  public static final io.fabric8.swagger.model.Parameter$ParamType PATH;

  public static final io.fabric8.swagger.model.Parameter$ParamType QUERY;

  public static final io.fabric8.swagger.model.Parameter$ParamType BODY;

  public static final io.fabric8.swagger.model.Parameter$ParamType HEADER;

  public static final io.fabric8.swagger.model.Parameter$ParamType FORM;

  private final java.lang.String value;

  private static java.util.Map<java.lang.String, io.fabric8.swagger.model.Parameter$ParamType> constants;

  private static final io.fabric8.swagger.model.Parameter$ParamType[] $VALUES;

  public static io.fabric8.swagger.model.Parameter$ParamType[] values();
    Code:
       0: getstatic     #1                  // Field $VALUES:[Lio/fabric8/swagger/model/Parameter$ParamType;
       3: invokevirtual #2                  // Method "[Lio/fabric8/swagger/model/Parameter$ParamType;".clone:()Ljava/lang/Object;
       6: checkcast     #3                  // class "[Lio/fabric8/swagger/model/Parameter$ParamType;"
       9: areturn

  public static io.fabric8.swagger.model.Parameter$ParamType valueOf(java.lang.String);
    Code:
       0: ldc_w         #4                  // class io/fabric8/swagger/model/Parameter$ParamType
       3: aload_0
       4: invokestatic  #5                  // Method java/lang/Enum.valueOf:(Ljava/lang/Class;Ljava/lang/String;)Ljava/lang/Enum;
       7: checkcast     #4                  // class io/fabric8/swagger/model/Parameter$ParamType
      10: areturn

  private io.fabric8.swagger.model.Parameter$ParamType(java.lang.String);
    Code:
       0: aload_0
       1: aload_1
       2: iload_2
       3: invokespecial #6                  // Method java/lang/Enum."<init>":(Ljava/lang/String;I)V
       6: aload_0
       7: aload_3
       8: putfield      #7                  // Field value:Ljava/lang/String;
      11: return

  public java.lang.String toString();
    Code:
       0: aload_0
       1: getfield      #7                  // Field value:Ljava/lang/String;
       4: areturn

  public static io.fabric8.swagger.model.Parameter$ParamType fromValue(java.lang.String);
    Code:
       0: getstatic     #8                  // Field constants:Ljava/util/Map;
       3: aload_0
       4: invokeinterface #9,  2            // InterfaceMethod java/util/Map.get:(Ljava/lang/Object;)Ljava/lang/Object;
       9: checkcast     #4                  // class io/fabric8/swagger/model/Parameter$ParamType
      12: astore_1
      13: aload_1
      14: ifnonnull     26
      17: new           #10                 // class java/lang/IllegalArgumentException
      20: dup
      21: aload_0
      22: invokespecial #11                 // Method java/lang/IllegalArgumentException."<init>":(Ljava/lang/String;)V
      25: athrow
      26: aload_1
      27: areturn

  static {};
    Code:
       0: new           #4                  // class io/fabric8/swagger/model/Parameter$ParamType
       3: dup
       4: ldc           #12                 // String PATH
       6: iconst_0
       7: ldc           #13                 // String path
       9: invokespecial #14                 // Method "<init>":(Ljava/lang/String;ILjava/lang/String;)V
      12: putstatic     #15                 // Field PATH:Lio/fabric8/swagger/model/Parameter$ParamType;
      15: new           #4                  // class io/fabric8/swagger/model/Parameter$ParamType
      18: dup
      19: ldc           #16                 // String QUERY
      21: iconst_1
      22: ldc           #17                 // String query
      24: invokespecial #14                 // Method "<init>":(Ljava/lang/String;ILjava/lang/String;)V
      27: putstatic     #18                 // Field QUERY:Lio/fabric8/swagger/model/Parameter$ParamType;
      30: new           #4                  // class io/fabric8/swagger/model/Parameter$ParamType
      33: dup
      34: ldc           #19                 // String BODY
      36: iconst_2
      37: ldc           #20                 // String body
      39: invokespecial #14                 // Method "<init>":(Ljava/lang/String;ILjava/lang/String;)V
      42: putstatic     #21                 // Field BODY:Lio/fabric8/swagger/model/Parameter$ParamType;
      45: new           #4                  // class io/fabric8/swagger/model/Parameter$ParamType
      48: dup
      49: ldc           #22                 // String HEADER
      51: iconst_3
      52: ldc           #23                 // String header
      54: invokespecial #14                 // Method "<init>":(Ljava/lang/String;ILjava/lang/String;)V
      57: putstatic     #24                 // Field HEADER:Lio/fabric8/swagger/model/Parameter$ParamType;
      60: new           #4                  // class io/fabric8/swagger/model/Parameter$ParamType
      63: dup
      64: ldc           #25                 // String FORM
      66: iconst_4
      67: ldc           #26                 // String form
      69: invokespecial #14                 // Method "<init>":(Ljava/lang/String;ILjava/lang/String;)V
      72: putstatic     #27                 // Field FORM:Lio/fabric8/swagger/model/Parameter$ParamType;
      75: iconst_5
      76: anewarray     #4                  // class io/fabric8/swagger/model/Parameter$ParamType
      79: dup
      80: iconst_0
      81: getstatic     #15                 // Field PATH:Lio/fabric8/swagger/model/Parameter$ParamType;
      84: aastore
      85: dup
      86: iconst_1
      87: getstatic     #18                 // Field QUERY:Lio/fabric8/swagger/model/Parameter$ParamType;
      90: aastore
      91: dup
      92: iconst_2
      93: getstatic     #21                 // Field BODY:Lio/fabric8/swagger/model/Parameter$ParamType;
      96: aastore
      97: dup
      98: iconst_3
      99: getstatic     #24                 // Field HEADER:Lio/fabric8/swagger/model/Parameter$ParamType;
     102: aastore
     103: dup
     104: iconst_4
     105: getstatic     #27                 // Field FORM:Lio/fabric8/swagger/model/Parameter$ParamType;
     108: aastore
     109: putstatic     #1                  // Field $VALUES:[Lio/fabric8/swagger/model/Parameter$ParamType;
     112: new           #28                 // class java/util/HashMap
     115: dup
     116: invokespecial #29                 // Method java/util/HashMap."<init>":()V
     119: putstatic     #8                  // Field constants:Ljava/util/Map;
     122: invokestatic  #30                 // Method values:()[Lio/fabric8/swagger/model/Parameter$ParamType;
     125: astore_0
     126: aload_0
     127: arraylength
     128: istore_1
     129: iconst_0
     130: istore_2
     131: iload_2
     132: iload_1
     133: if_icmpge     160
     136: aload_0
     137: iload_2
     138: aaload
     139: astore_3
     140: getstatic     #8                  // Field constants:Ljava/util/Map;
     143: aload_3
     144: getfield      #7                  // Field value:Ljava/lang/String;
     147: aload_3
     148: invokeinterface #31,  3           // InterfaceMethod java/util/Map.put:(Ljava/lang/Object;Ljava/lang/Object;)Ljava/lang/Object;
     153: pop
     154: iinc          2, 1
     157: goto          131
     160: return
}
