Compiled from "renderingIntent.scala"
public final class slinky.web.svg._renderingIntent_attr {
  public static slinky.core.OptionalAttrPair<slinky.web.svg.$times$tag$> tostarOptionalApplied(slinky.core.OptionalAttrPair<slinky.web.svg._renderingIntent_attr$>);
    Code:
       0: getstatic     #315                // Field slinky/web/svg/_renderingIntent_attr$.MODULE$:Lslinky/web/svg/_renderingIntent_attr$;
       3: aload_0
       4: invokevirtual #317                // Method slinky/web/svg/_renderingIntent_attr$.tostarOptionalApplied:(Lslinky/core/OptionalAttrPair;)Lslinky/core/OptionalAttrPair;
       7: areturn

  public static slinky.core.AttrPair<slinky.web.svg.$times$tag$> tostarApplied(slinky.core.AttrPair<slinky.web.svg._renderingIntent_attr$>);
    Code:
       0: getstatic     #315                // Field slinky/web/svg/_renderingIntent_attr$.MODULE$:Lslinky/web/svg/_renderingIntent_attr$;
       3: aload_0
       4: invokevirtual #322                // Method slinky/web/svg/_renderingIntent_attr$.tostarApplied:(Lslinky/core/AttrPair;)Lslinky/core/AttrPair;
       7: areturn

  public static slinky.core.OptionalAttrPair<slinky.web.svg.vkern$tag$> tovkernOptionalApplied(slinky.core.OptionalAttrPair<slinky.web.svg._renderingIntent_attr$>);
    Code:
       0: getstatic     #315                // Field slinky/web/svg/_renderingIntent_attr$.MODULE$:Lslinky/web/svg/_renderingIntent_attr$;
       3: aload_0
       4: invokevirtual #326                // Method slinky/web/svg/_renderingIntent_attr$.tovkernOptionalApplied:(Lslinky/core/OptionalAttrPair;)Lslinky/core/OptionalAttrPair;
       7: areturn

  public static slinky.core.AttrPair<slinky.web.svg.vkern$tag$> tovkernApplied(slinky.core.AttrPair<slinky.web.svg._renderingIntent_attr$>);
    Code:
       0: getstatic     #315                // Field slinky/web/svg/_renderingIntent_attr$.MODULE$:Lslinky/web/svg/_renderingIntent_attr$;
       3: aload_0
       4: invokevirtual #330                // Method slinky/web/svg/_renderingIntent_attr$.tovkernApplied:(Lslinky/core/AttrPair;)Lslinky/core/AttrPair;
       7: areturn

  public static slinky.core.OptionalAttrPair<slinky.web.svg.view$tag$> toviewOptionalApplied(slinky.core.OptionalAttrPair<slinky.web.svg._renderingIntent_attr$>);
    Code:
       0: getstatic     #315                // Field slinky/web/svg/_renderingIntent_attr$.MODULE$:Lslinky/web/svg/_renderingIntent_attr$;
       3: aload_0
       4: invokevirtual #334                // Method slinky/web/svg/_renderingIntent_attr$.toviewOptionalApplied:(Lslinky/core/OptionalAttrPair;)Lslinky/core/OptionalAttrPair;
       7: areturn

  public static slinky.core.AttrPair<slinky.web.svg.view$tag$> toviewApplied(slinky.core.AttrPair<slinky.web.svg._renderingIntent_attr$>);
    Code:
       0: getstatic     #315                // Field slinky/web/svg/_renderingIntent_attr$.MODULE$:Lslinky/web/svg/_renderingIntent_attr$;
       3: aload_0
       4: invokevirtual #338                // Method slinky/web/svg/_renderingIntent_attr$.toviewApplied:(Lslinky/core/AttrPair;)Lslinky/core/AttrPair;
       7: areturn

  public static slinky.core.OptionalAttrPair<slinky.web.svg.use$tag$> touseOptionalApplied(slinky.core.OptionalAttrPair<slinky.web.svg._renderingIntent_attr$>);
    Code:
       0: getstatic     #315                // Field slinky/web/svg/_renderingIntent_attr$.MODULE$:Lslinky/web/svg/_renderingIntent_attr$;
       3: aload_0
       4: invokevirtual #342                // Method slinky/web/svg/_renderingIntent_attr$.touseOptionalApplied:(Lslinky/core/OptionalAttrPair;)Lslinky/core/OptionalAttrPair;
       7: areturn

  public static slinky.core.AttrPair<slinky.web.svg.use$tag$> touseApplied(slinky.core.AttrPair<slinky.web.svg._renderingIntent_attr$>);
    Code:
       0: getstatic     #315                // Field slinky/web/svg/_renderingIntent_attr$.MODULE$:Lslinky/web/svg/_renderingIntent_attr$;
       3: aload_0
       4: invokevirtual #346                // Method slinky/web/svg/_renderingIntent_attr$.touseApplied:(Lslinky/core/AttrPair;)Lslinky/core/AttrPair;
       7: areturn

  public static slinky.core.OptionalAttrPair<slinky.web.svg.tspan$tag$> totspanOptionalApplied(slinky.core.OptionalAttrPair<slinky.web.svg._renderingIntent_attr$>);
    Code:
       0: getstatic     #315                // Field slinky/web/svg/_renderingIntent_attr$.MODULE$:Lslinky/web/svg/_renderingIntent_attr$;
       3: aload_0
       4: invokevirtual #350                // Method slinky/web/svg/_renderingIntent_attr$.totspanOptionalApplied:(Lslinky/core/OptionalAttrPair;)Lslinky/core/OptionalAttrPair;
       7: areturn

  public static slinky.core.AttrPair<slinky.web.svg.tspan$tag$> totspanApplied(slinky.core.AttrPair<slinky.web.svg._renderingIntent_attr$>);
    Code:
       0: getstatic     #315                // Field slinky/web/svg/_renderingIntent_attr$.MODULE$:Lslinky/web/svg/_renderingIntent_attr$;
       3: aload_0
       4: invokevirtual #354                // Method slinky/web/svg/_renderingIntent_attr$.totspanApplied:(Lslinky/core/AttrPair;)Lslinky/core/AttrPair;
       7: areturn

  public static slinky.core.OptionalAttrPair<slinky.web.svg.tref$tag$> totrefOptionalApplied(slinky.core.OptionalAttrPair<slinky.web.svg._renderingIntent_attr$>);
    Code:
       0: getstatic     #315                // Field slinky/web/svg/_renderingIntent_attr$.MODULE$:Lslinky/web/svg/_renderingIntent_attr$;
       3: aload_0
       4: invokevirtual #358                // Method slinky/web/svg/_renderingIntent_attr$.totrefOptionalApplied:(Lslinky/core/OptionalAttrPair;)Lslinky/core/OptionalAttrPair;
       7: areturn

  public static slinky.core.AttrPair<slinky.web.svg.tref$tag$> totrefApplied(slinky.core.AttrPair<slinky.web.svg._renderingIntent_attr$>);
    Code:
       0: getstatic     #315                // Field slinky/web/svg/_renderingIntent_attr$.MODULE$:Lslinky/web/svg/_renderingIntent_attr$;
       3: aload_0
       4: invokevirtual #362                // Method slinky/web/svg/_renderingIntent_attr$.totrefApplied:(Lslinky/core/AttrPair;)Lslinky/core/AttrPair;
       7: areturn

  public static slinky.core.OptionalAttrPair<slinky.web.svg.title$tag$> totitleOptionalApplied(slinky.core.OptionalAttrPair<slinky.web.svg._renderingIntent_attr$>);
    Code:
       0: getstatic     #315                // Field slinky/web/svg/_renderingIntent_attr$.MODULE$:Lslinky/web/svg/_renderingIntent_attr$;
       3: aload_0
       4: invokevirtual #366                // Method slinky/web/svg/_renderingIntent_attr$.totitleOptionalApplied:(Lslinky/core/OptionalAttrPair;)Lslinky/core/OptionalAttrPair;
       7: areturn

  public static slinky.core.AttrPair<slinky.web.svg.title$tag$> totitleApplied(slinky.core.AttrPair<slinky.web.svg._renderingIntent_attr$>);
    Code:
       0: getstatic     #315                // Field slinky/web/svg/_renderingIntent_attr$.MODULE$:Lslinky/web/svg/_renderingIntent_attr$;
       3: aload_0
       4: invokevirtual #370                // Method slinky/web/svg/_renderingIntent_attr$.totitleApplied:(Lslinky/core/AttrPair;)Lslinky/core/AttrPair;
       7: areturn

  public static slinky.core.OptionalAttrPair<slinky.web.svg.textPath$tag$> totextPathOptionalApplied(slinky.core.OptionalAttrPair<slinky.web.svg._renderingIntent_attr$>);
    Code:
       0: getstatic     #315                // Field slinky/web/svg/_renderingIntent_attr$.MODULE$:Lslinky/web/svg/_renderingIntent_attr$;
       3: aload_0
       4: invokevirtual #374                // Method slinky/web/svg/_renderingIntent_attr$.totextPathOptionalApplied:(Lslinky/core/OptionalAttrPair;)Lslinky/core/OptionalAttrPair;
       7: areturn

  public static slinky.core.AttrPair<slinky.web.svg.textPath$tag$> totextPathApplied(slinky.core.AttrPair<slinky.web.svg._renderingIntent_attr$>);
    Code:
       0: getstatic     #315                // Field slinky/web/svg/_renderingIntent_attr$.MODULE$:Lslinky/web/svg/_renderingIntent_attr$;
       3: aload_0
       4: invokevirtual #378                // Method slinky/web/svg/_renderingIntent_attr$.totextPathApplied:(Lslinky/core/AttrPair;)Lslinky/core/AttrPair;
       7: areturn

  public static slinky.core.OptionalAttrPair<slinky.web.svg.text$tag$> totextOptionalApplied(slinky.core.OptionalAttrPair<slinky.web.svg._renderingIntent_attr$>);
    Code:
       0: getstatic     #315                // Field slinky/web/svg/_renderingIntent_attr$.MODULE$:Lslinky/web/svg/_renderingIntent_attr$;
       3: aload_0
       4: invokevirtual #382                // Method slinky/web/svg/_renderingIntent_attr$.totextOptionalApplied:(Lslinky/core/OptionalAttrPair;)Lslinky/core/OptionalAttrPair;
       7: areturn

  public static slinky.core.AttrPair<slinky.web.svg.text$tag$> totextApplied(slinky.core.AttrPair<slinky.web.svg._renderingIntent_attr$>);
    Code:
       0: getstatic     #315                // Field slinky/web/svg/_renderingIntent_attr$.MODULE$:Lslinky/web/svg/_renderingIntent_attr$;
       3: aload_0
       4: invokevirtual #386                // Method slinky/web/svg/_renderingIntent_attr$.totextApplied:(Lslinky/core/AttrPair;)Lslinky/core/AttrPair;
       7: areturn

  public static slinky.core.OptionalAttrPair<slinky.web.svg.symbol$tag$> tosymbolOptionalApplied(slinky.core.OptionalAttrPair<slinky.web.svg._renderingIntent_attr$>);
    Code:
       0: getstatic     #315                // Field slinky/web/svg/_renderingIntent_attr$.MODULE$:Lslinky/web/svg/_renderingIntent_attr$;
       3: aload_0
       4: invokevirtual #390                // Method slinky/web/svg/_renderingIntent_attr$.tosymbolOptionalApplied:(Lslinky/core/OptionalAttrPair;)Lslinky/core/OptionalAttrPair;
       7: areturn

  public static slinky.core.AttrPair<slinky.web.svg.symbol$tag$> tosymbolApplied(slinky.core.AttrPair<slinky.web.svg._renderingIntent_attr$>);
    Code:
       0: getstatic     #315                // Field slinky/web/svg/_renderingIntent_attr$.MODULE$:Lslinky/web/svg/_renderingIntent_attr$;
       3: aload_0
       4: invokevirtual #394                // Method slinky/web/svg/_renderingIntent_attr$.tosymbolApplied:(Lslinky/core/AttrPair;)Lslinky/core/AttrPair;
       7: areturn

  public static slinky.core.OptionalAttrPair<slinky.web.svg.switch$tag$> toswitchOptionalApplied(slinky.core.OptionalAttrPair<slinky.web.svg._renderingIntent_attr$>);
    Code:
       0: getstatic     #315                // Field slinky/web/svg/_renderingIntent_attr$.MODULE$:Lslinky/web/svg/_renderingIntent_attr$;
       3: aload_0
       4: invokevirtual #398                // Method slinky/web/svg/_renderingIntent_attr$.toswitchOptionalApplied:(Lslinky/core/OptionalAttrPair;)Lslinky/core/OptionalAttrPair;
       7: areturn

  public static slinky.core.AttrPair<slinky.web.svg.switch$tag$> toswitchApplied(slinky.core.AttrPair<slinky.web.svg._renderingIntent_attr$>);
    Code:
       0: getstatic     #315                // Field slinky/web/svg/_renderingIntent_attr$.MODULE$:Lslinky/web/svg/_renderingIntent_attr$;
       3: aload_0
       4: invokevirtual #402                // Method slinky/web/svg/_renderingIntent_attr$.toswitchApplied:(Lslinky/core/AttrPair;)Lslinky/core/AttrPair;
       7: areturn

  public static slinky.core.OptionalAttrPair<slinky.web.svg.svg$tag$> tosvgOptionalApplied(slinky.core.OptionalAttrPair<slinky.web.svg._renderingIntent_attr$>);
    Code:
       0: getstatic     #315                // Field slinky/web/svg/_renderingIntent_attr$.MODULE$:Lslinky/web/svg/_renderingIntent_attr$;
       3: aload_0
       4: invokevirtual #406                // Method slinky/web/svg/_renderingIntent_attr$.tosvgOptionalApplied:(Lslinky/core/OptionalAttrPair;)Lslinky/core/OptionalAttrPair;
       7: areturn

  public static slinky.core.AttrPair<slinky.web.svg.svg$tag$> tosvgApplied(slinky.core.AttrPair<slinky.web.svg._renderingIntent_attr$>);
    Code:
       0: getstatic     #315                // Field slinky/web/svg/_renderingIntent_attr$.MODULE$:Lslinky/web/svg/_renderingIntent_attr$;
       3: aload_0
       4: invokevirtual #410                // Method slinky/web/svg/_renderingIntent_attr$.tosvgApplied:(Lslinky/core/AttrPair;)Lslinky/core/AttrPair;
       7: areturn

  public static slinky.core.OptionalAttrPair<slinky.web.svg.style$tag$> tostyleOptionalApplied(slinky.core.OptionalAttrPair<slinky.web.svg._renderingIntent_attr$>);
    Code:
       0: getstatic     #315                // Field slinky/web/svg/_renderingIntent_attr$.MODULE$:Lslinky/web/svg/_renderingIntent_attr$;
       3: aload_0
       4: invokevirtual #414                // Method slinky/web/svg/_renderingIntent_attr$.tostyleOptionalApplied:(Lslinky/core/OptionalAttrPair;)Lslinky/core/OptionalAttrPair;
       7: areturn

  public static slinky.core.AttrPair<slinky.web.svg.style$tag$> tostyleApplied(slinky.core.AttrPair<slinky.web.svg._renderingIntent_attr$>);
    Code:
       0: getstatic     #315                // Field slinky/web/svg/_renderingIntent_attr$.MODULE$:Lslinky/web/svg/_renderingIntent_attr$;
       3: aload_0
       4: invokevirtual #418                // Method slinky/web/svg/_renderingIntent_attr$.tostyleApplied:(Lslinky/core/AttrPair;)Lslinky/core/AttrPair;
       7: areturn

  public static slinky.core.OptionalAttrPair<slinky.web.svg.stop$tag$> tostopOptionalApplied(slinky.core.OptionalAttrPair<slinky.web.svg._renderingIntent_attr$>);
    Code:
       0: getstatic     #315                // Field slinky/web/svg/_renderingIntent_attr$.MODULE$:Lslinky/web/svg/_renderingIntent_attr$;
       3: aload_0
       4: invokevirtual #422                // Method slinky/web/svg/_renderingIntent_attr$.tostopOptionalApplied:(Lslinky/core/OptionalAttrPair;)Lslinky/core/OptionalAttrPair;
       7: areturn

  public static slinky.core.AttrPair<slinky.web.svg.stop$tag$> tostopApplied(slinky.core.AttrPair<slinky.web.svg._renderingIntent_attr$>);
    Code:
       0: getstatic     #315                // Field slinky/web/svg/_renderingIntent_attr$.MODULE$:Lslinky/web/svg/_renderingIntent_attr$;
       3: aload_0
       4: invokevirtual #426                // Method slinky/web/svg/_renderingIntent_attr$.tostopApplied:(Lslinky/core/AttrPair;)Lslinky/core/AttrPair;
       7: areturn

  public static slinky.core.OptionalAttrPair<slinky.web.svg.set$tag$> tosetOptionalApplied(slinky.core.OptionalAttrPair<slinky.web.svg._renderingIntent_attr$>);
    Code:
       0: getstatic     #315                // Field slinky/web/svg/_renderingIntent_attr$.MODULE$:Lslinky/web/svg/_renderingIntent_attr$;
       3: aload_0
       4: invokevirtual #430                // Method slinky/web/svg/_renderingIntent_attr$.tosetOptionalApplied:(Lslinky/core/OptionalAttrPair;)Lslinky/core/OptionalAttrPair;
       7: areturn

  public static slinky.core.AttrPair<slinky.web.svg.set$tag$> tosetApplied(slinky.core.AttrPair<slinky.web.svg._renderingIntent_attr$>);
    Code:
       0: getstatic     #315                // Field slinky/web/svg/_renderingIntent_attr$.MODULE$:Lslinky/web/svg/_renderingIntent_attr$;
       3: aload_0
       4: invokevirtual #434                // Method slinky/web/svg/_renderingIntent_attr$.tosetApplied:(Lslinky/core/AttrPair;)Lslinky/core/AttrPair;
       7: areturn

  public static slinky.core.OptionalAttrPair<slinky.web.svg.script$tag$> toscriptOptionalApplied(slinky.core.OptionalAttrPair<slinky.web.svg._renderingIntent_attr$>);
    Code:
       0: getstatic     #315                // Field slinky/web/svg/_renderingIntent_attr$.MODULE$:Lslinky/web/svg/_renderingIntent_attr$;
       3: aload_0
       4: invokevirtual #438                // Method slinky/web/svg/_renderingIntent_attr$.toscriptOptionalApplied:(Lslinky/core/OptionalAttrPair;)Lslinky/core/OptionalAttrPair;
       7: areturn

  public static slinky.core.AttrPair<slinky.web.svg.script$tag$> toscriptApplied(slinky.core.AttrPair<slinky.web.svg._renderingIntent_attr$>);
    Code:
       0: getstatic     #315                // Field slinky/web/svg/_renderingIntent_attr$.MODULE$:Lslinky/web/svg/_renderingIntent_attr$;
       3: aload_0
       4: invokevirtual #442                // Method slinky/web/svg/_renderingIntent_attr$.toscriptApplied:(Lslinky/core/AttrPair;)Lslinky/core/AttrPair;
       7: areturn

  public static slinky.core.OptionalAttrPair<slinky.web.svg.rect$tag$> torectOptionalApplied(slinky.core.OptionalAttrPair<slinky.web.svg._renderingIntent_attr$>);
    Code:
       0: getstatic     #315                // Field slinky/web/svg/_renderingIntent_attr$.MODULE$:Lslinky/web/svg/_renderingIntent_attr$;
       3: aload_0
       4: invokevirtual #446                // Method slinky/web/svg/_renderingIntent_attr$.torectOptionalApplied:(Lslinky/core/OptionalAttrPair;)Lslinky/core/OptionalAttrPair;
       7: areturn

  public static slinky.core.AttrPair<slinky.web.svg.rect$tag$> torectApplied(slinky.core.AttrPair<slinky.web.svg._renderingIntent_attr$>);
    Code:
       0: getstatic     #315                // Field slinky/web/svg/_renderingIntent_attr$.MODULE$:Lslinky/web/svg/_renderingIntent_attr$;
       3: aload_0
       4: invokevirtual #450                // Method slinky/web/svg/_renderingIntent_attr$.torectApplied:(Lslinky/core/AttrPair;)Lslinky/core/AttrPair;
       7: areturn

  public static slinky.core.OptionalAttrPair<slinky.web.svg.radialGradient$tag$> toradialGradientOptionalApplied(slinky.core.OptionalAttrPair<slinky.web.svg._renderingIntent_attr$>);
    Code:
       0: getstatic     #315                // Field slinky/web/svg/_renderingIntent_attr$.MODULE$:Lslinky/web/svg/_renderingIntent_attr$;
       3: aload_0
       4: invokevirtual #454                // Method slinky/web/svg/_renderingIntent_attr$.toradialGradientOptionalApplied:(Lslinky/core/OptionalAttrPair;)Lslinky/core/OptionalAttrPair;
       7: areturn

  public static slinky.core.AttrPair<slinky.web.svg.radialGradient$tag$> toradialGradientApplied(slinky.core.AttrPair<slinky.web.svg._renderingIntent_attr$>);
    Code:
       0: getstatic     #315                // Field slinky/web/svg/_renderingIntent_attr$.MODULE$:Lslinky/web/svg/_renderingIntent_attr$;
       3: aload_0
       4: invokevirtual #458                // Method slinky/web/svg/_renderingIntent_attr$.toradialGradientApplied:(Lslinky/core/AttrPair;)Lslinky/core/AttrPair;
       7: areturn

  public static slinky.core.OptionalAttrPair<slinky.web.svg.polyline$tag$> topolylineOptionalApplied(slinky.core.OptionalAttrPair<slinky.web.svg._renderingIntent_attr$>);
    Code:
       0: getstatic     #315                // Field slinky/web/svg/_renderingIntent_attr$.MODULE$:Lslinky/web/svg/_renderingIntent_attr$;
       3: aload_0
       4: invokevirtual #462                // Method slinky/web/svg/_renderingIntent_attr$.topolylineOptionalApplied:(Lslinky/core/OptionalAttrPair;)Lslinky/core/OptionalAttrPair;
       7: areturn

  public static slinky.core.AttrPair<slinky.web.svg.polyline$tag$> topolylineApplied(slinky.core.AttrPair<slinky.web.svg._renderingIntent_attr$>);
    Code:
       0: getstatic     #315                // Field slinky/web/svg/_renderingIntent_attr$.MODULE$:Lslinky/web/svg/_renderingIntent_attr$;
       3: aload_0
       4: invokevirtual #466                // Method slinky/web/svg/_renderingIntent_attr$.topolylineApplied:(Lslinky/core/AttrPair;)Lslinky/core/AttrPair;
       7: areturn

  public static slinky.core.OptionalAttrPair<slinky.web.svg.polygon$tag$> topolygonOptionalApplied(slinky.core.OptionalAttrPair<slinky.web.svg._renderingIntent_attr$>);
    Code:
       0: getstatic     #315                // Field slinky/web/svg/_renderingIntent_attr$.MODULE$:Lslinky/web/svg/_renderingIntent_attr$;
       3: aload_0
       4: invokevirtual #470                // Method slinky/web/svg/_renderingIntent_attr$.topolygonOptionalApplied:(Lslinky/core/OptionalAttrPair;)Lslinky/core/OptionalAttrPair;
       7: areturn

  public static slinky.core.AttrPair<slinky.web.svg.polygon$tag$> topolygonApplied(slinky.core.AttrPair<slinky.web.svg._renderingIntent_attr$>);
    Code:
       0: getstatic     #315                // Field slinky/web/svg/_renderingIntent_attr$.MODULE$:Lslinky/web/svg/_renderingIntent_attr$;
       3: aload_0
       4: invokevirtual #474                // Method slinky/web/svg/_renderingIntent_attr$.topolygonApplied:(Lslinky/core/AttrPair;)Lslinky/core/AttrPair;
       7: areturn

  public static slinky.core.OptionalAttrPair<slinky.web.svg.pattern$tag$> topatternOptionalApplied(slinky.core.OptionalAttrPair<slinky.web.svg._renderingIntent_attr$>);
    Code:
       0: getstatic     #315                // Field slinky/web/svg/_renderingIntent_attr$.MODULE$:Lslinky/web/svg/_renderingIntent_attr$;
       3: aload_0
       4: invokevirtual #478                // Method slinky/web/svg/_renderingIntent_attr$.topatternOptionalApplied:(Lslinky/core/OptionalAttrPair;)Lslinky/core/OptionalAttrPair;
       7: areturn

  public static slinky.core.AttrPair<slinky.web.svg.pattern$tag$> topatternApplied(slinky.core.AttrPair<slinky.web.svg._renderingIntent_attr$>);
    Code:
       0: getstatic     #315                // Field slinky/web/svg/_renderingIntent_attr$.MODULE$:Lslinky/web/svg/_renderingIntent_attr$;
       3: aload_0
       4: invokevirtual #482                // Method slinky/web/svg/_renderingIntent_attr$.topatternApplied:(Lslinky/core/AttrPair;)Lslinky/core/AttrPair;
       7: areturn

  public static slinky.core.OptionalAttrPair<slinky.web.svg.path$tag$> topathOptionalApplied(slinky.core.OptionalAttrPair<slinky.web.svg._renderingIntent_attr$>);
    Code:
       0: getstatic     #315                // Field slinky/web/svg/_renderingIntent_attr$.MODULE$:Lslinky/web/svg/_renderingIntent_attr$;
       3: aload_0
       4: invokevirtual #486                // Method slinky/web/svg/_renderingIntent_attr$.topathOptionalApplied:(Lslinky/core/OptionalAttrPair;)Lslinky/core/OptionalAttrPair;
       7: areturn

  public static slinky.core.AttrPair<slinky.web.svg.path$tag$> topathApplied(slinky.core.AttrPair<slinky.web.svg._renderingIntent_attr$>);
    Code:
       0: getstatic     #315                // Field slinky/web/svg/_renderingIntent_attr$.MODULE$:Lslinky/web/svg/_renderingIntent_attr$;
       3: aload_0
       4: invokevirtual #490                // Method slinky/web/svg/_renderingIntent_attr$.topathApplied:(Lslinky/core/AttrPair;)Lslinky/core/AttrPair;
       7: areturn

  public static slinky.core.OptionalAttrPair<slinky.web.svg.mpath$tag$> tompathOptionalApplied(slinky.core.OptionalAttrPair<slinky.web.svg._renderingIntent_attr$>);
    Code:
       0: getstatic     #315                // Field slinky/web/svg/_renderingIntent_attr$.MODULE$:Lslinky/web/svg/_renderingIntent_attr$;
       3: aload_0
       4: invokevirtual #494                // Method slinky/web/svg/_renderingIntent_attr$.tompathOptionalApplied:(Lslinky/core/OptionalAttrPair;)Lslinky/core/OptionalAttrPair;
       7: areturn

  public static slinky.core.AttrPair<slinky.web.svg.mpath$tag$> tompathApplied(slinky.core.AttrPair<slinky.web.svg._renderingIntent_attr$>);
    Code:
       0: getstatic     #315                // Field slinky/web/svg/_renderingIntent_attr$.MODULE$:Lslinky/web/svg/_renderingIntent_attr$;
       3: aload_0
       4: invokevirtual #498                // Method slinky/web/svg/_renderingIntent_attr$.tompathApplied:(Lslinky/core/AttrPair;)Lslinky/core/AttrPair;
       7: areturn

  public static slinky.core.OptionalAttrPair<slinky.web.svg.metadata$tag$> tometadataOptionalApplied(slinky.core.OptionalAttrPair<slinky.web.svg._renderingIntent_attr$>);
    Code:
       0: getstatic     #315                // Field slinky/web/svg/_renderingIntent_attr$.MODULE$:Lslinky/web/svg/_renderingIntent_attr$;
       3: aload_0
       4: invokevirtual #502                // Method slinky/web/svg/_renderingIntent_attr$.tometadataOptionalApplied:(Lslinky/core/OptionalAttrPair;)Lslinky/core/OptionalAttrPair;
       7: areturn

  public static slinky.core.AttrPair<slinky.web.svg.metadata$tag$> tometadataApplied(slinky.core.AttrPair<slinky.web.svg._renderingIntent_attr$>);
    Code:
       0: getstatic     #315                // Field slinky/web/svg/_renderingIntent_attr$.MODULE$:Lslinky/web/svg/_renderingIntent_attr$;
       3: aload_0
       4: invokevirtual #506                // Method slinky/web/svg/_renderingIntent_attr$.tometadataApplied:(Lslinky/core/AttrPair;)Lslinky/core/AttrPair;
       7: areturn

  public static slinky.core.OptionalAttrPair<slinky.web.svg.mask$tag$> tomaskOptionalApplied(slinky.core.OptionalAttrPair<slinky.web.svg._renderingIntent_attr$>);
    Code:
       0: getstatic     #315                // Field slinky/web/svg/_renderingIntent_attr$.MODULE$:Lslinky/web/svg/_renderingIntent_attr$;
       3: aload_0
       4: invokevirtual #510                // Method slinky/web/svg/_renderingIntent_attr$.tomaskOptionalApplied:(Lslinky/core/OptionalAttrPair;)Lslinky/core/OptionalAttrPair;
       7: areturn

  public static slinky.core.AttrPair<slinky.web.svg.mask$tag$> tomaskApplied(slinky.core.AttrPair<slinky.web.svg._renderingIntent_attr$>);
    Code:
       0: getstatic     #315                // Field slinky/web/svg/_renderingIntent_attr$.MODULE$:Lslinky/web/svg/_renderingIntent_attr$;
       3: aload_0
       4: invokevirtual #514                // Method slinky/web/svg/_renderingIntent_attr$.tomaskApplied:(Lslinky/core/AttrPair;)Lslinky/core/AttrPair;
       7: areturn

  public static slinky.core.OptionalAttrPair<slinky.web.svg.marker$tag$> tomarkerOptionalApplied(slinky.core.OptionalAttrPair<slinky.web.svg._renderingIntent_attr$>);
    Code:
       0: getstatic     #315                // Field slinky/web/svg/_renderingIntent_attr$.MODULE$:Lslinky/web/svg/_renderingIntent_attr$;
       3: aload_0
       4: invokevirtual #518                // Method slinky/web/svg/_renderingIntent_attr$.tomarkerOptionalApplied:(Lslinky/core/OptionalAttrPair;)Lslinky/core/OptionalAttrPair;
       7: areturn

  public static slinky.core.AttrPair<slinky.web.svg.marker$tag$> tomarkerApplied(slinky.core.AttrPair<slinky.web.svg._renderingIntent_attr$>);
    Code:
       0: getstatic     #315                // Field slinky/web/svg/_renderingIntent_attr$.MODULE$:Lslinky/web/svg/_renderingIntent_attr$;
       3: aload_0
       4: invokevirtual #522                // Method slinky/web/svg/_renderingIntent_attr$.tomarkerApplied:(Lslinky/core/AttrPair;)Lslinky/core/AttrPair;
       7: areturn

  public static slinky.core.OptionalAttrPair<slinky.web.svg.linearGradient$tag$> tolinearGradientOptionalApplied(slinky.core.OptionalAttrPair<slinky.web.svg._renderingIntent_attr$>);
    Code:
       0: getstatic     #315                // Field slinky/web/svg/_renderingIntent_attr$.MODULE$:Lslinky/web/svg/_renderingIntent_attr$;
       3: aload_0
       4: invokevirtual #526                // Method slinky/web/svg/_renderingIntent_attr$.tolinearGradientOptionalApplied:(Lslinky/core/OptionalAttrPair;)Lslinky/core/OptionalAttrPair;
       7: areturn

  public static slinky.core.AttrPair<slinky.web.svg.linearGradient$tag$> tolinearGradientApplied(slinky.core.AttrPair<slinky.web.svg._renderingIntent_attr$>);
    Code:
       0: getstatic     #315                // Field slinky/web/svg/_renderingIntent_attr$.MODULE$:Lslinky/web/svg/_renderingIntent_attr$;
       3: aload_0
       4: invokevirtual #530                // Method slinky/web/svg/_renderingIntent_attr$.tolinearGradientApplied:(Lslinky/core/AttrPair;)Lslinky/core/AttrPair;
       7: areturn

  public static slinky.core.OptionalAttrPair<slinky.web.svg.line$tag$> tolineOptionalApplied(slinky.core.OptionalAttrPair<slinky.web.svg._renderingIntent_attr$>);
    Code:
       0: getstatic     #315                // Field slinky/web/svg/_renderingIntent_attr$.MODULE$:Lslinky/web/svg/_renderingIntent_attr$;
       3: aload_0
       4: invokevirtual #534                // Method slinky/web/svg/_renderingIntent_attr$.tolineOptionalApplied:(Lslinky/core/OptionalAttrPair;)Lslinky/core/OptionalAttrPair;
       7: areturn

  public static slinky.core.AttrPair<slinky.web.svg.line$tag$> tolineApplied(slinky.core.AttrPair<slinky.web.svg._renderingIntent_attr$>);
    Code:
       0: getstatic     #315                // Field slinky/web/svg/_renderingIntent_attr$.MODULE$:Lslinky/web/svg/_renderingIntent_attr$;
       3: aload_0
       4: invokevirtual #538                // Method slinky/web/svg/_renderingIntent_attr$.tolineApplied:(Lslinky/core/AttrPair;)Lslinky/core/AttrPair;
       7: areturn

  public static slinky.core.OptionalAttrPair<slinky.web.svg.image$tag$> toimageOptionalApplied(slinky.core.OptionalAttrPair<slinky.web.svg._renderingIntent_attr$>);
    Code:
       0: getstatic     #315                // Field slinky/web/svg/_renderingIntent_attr$.MODULE$:Lslinky/web/svg/_renderingIntent_attr$;
       3: aload_0
       4: invokevirtual #542                // Method slinky/web/svg/_renderingIntent_attr$.toimageOptionalApplied:(Lslinky/core/OptionalAttrPair;)Lslinky/core/OptionalAttrPair;
       7: areturn

  public static slinky.core.AttrPair<slinky.web.svg.image$tag$> toimageApplied(slinky.core.AttrPair<slinky.web.svg._renderingIntent_attr$>);
    Code:
       0: getstatic     #315                // Field slinky/web/svg/_renderingIntent_attr$.MODULE$:Lslinky/web/svg/_renderingIntent_attr$;
       3: aload_0
       4: invokevirtual #546                // Method slinky/web/svg/_renderingIntent_attr$.toimageApplied:(Lslinky/core/AttrPair;)Lslinky/core/AttrPair;
       7: areturn

  public static slinky.core.OptionalAttrPair<slinky.web.svg.hkern$tag$> tohkernOptionalApplied(slinky.core.OptionalAttrPair<slinky.web.svg._renderingIntent_attr$>);
    Code:
       0: getstatic     #315                // Field slinky/web/svg/_renderingIntent_attr$.MODULE$:Lslinky/web/svg/_renderingIntent_attr$;
       3: aload_0
       4: invokevirtual #550                // Method slinky/web/svg/_renderingIntent_attr$.tohkernOptionalApplied:(Lslinky/core/OptionalAttrPair;)Lslinky/core/OptionalAttrPair;
       7: areturn

  public static slinky.core.AttrPair<slinky.web.svg.hkern$tag$> tohkernApplied(slinky.core.AttrPair<slinky.web.svg._renderingIntent_attr$>);
    Code:
       0: getstatic     #315                // Field slinky/web/svg/_renderingIntent_attr$.MODULE$:Lslinky/web/svg/_renderingIntent_attr$;
       3: aload_0
       4: invokevirtual #554                // Method slinky/web/svg/_renderingIntent_attr$.tohkernApplied:(Lslinky/core/AttrPair;)Lslinky/core/AttrPair;
       7: areturn

  public static slinky.core.OptionalAttrPair<slinky.web.svg.glyphRef$tag$> toglyphRefOptionalApplied(slinky.core.OptionalAttrPair<slinky.web.svg._renderingIntent_attr$>);
    Code:
       0: getstatic     #315                // Field slinky/web/svg/_renderingIntent_attr$.MODULE$:Lslinky/web/svg/_renderingIntent_attr$;
       3: aload_0
       4: invokevirtual #558                // Method slinky/web/svg/_renderingIntent_attr$.toglyphRefOptionalApplied:(Lslinky/core/OptionalAttrPair;)Lslinky/core/OptionalAttrPair;
       7: areturn

  public static slinky.core.AttrPair<slinky.web.svg.glyphRef$tag$> toglyphRefApplied(slinky.core.AttrPair<slinky.web.svg._renderingIntent_attr$>);
    Code:
       0: getstatic     #315                // Field slinky/web/svg/_renderingIntent_attr$.MODULE$:Lslinky/web/svg/_renderingIntent_attr$;
       3: aload_0
       4: invokevirtual #562                // Method slinky/web/svg/_renderingIntent_attr$.toglyphRefApplied:(Lslinky/core/AttrPair;)Lslinky/core/AttrPair;
       7: areturn

  public static slinky.core.OptionalAttrPair<slinky.web.svg.glyph$tag$> toglyphOptionalApplied(slinky.core.OptionalAttrPair<slinky.web.svg._renderingIntent_attr$>);
    Code:
       0: getstatic     #315                // Field slinky/web/svg/_renderingIntent_attr$.MODULE$:Lslinky/web/svg/_renderingIntent_attr$;
       3: aload_0
       4: invokevirtual #566                // Method slinky/web/svg/_renderingIntent_attr$.toglyphOptionalApplied:(Lslinky/core/OptionalAttrPair;)Lslinky/core/OptionalAttrPair;
       7: areturn

  public static slinky.core.AttrPair<slinky.web.svg.glyph$tag$> toglyphApplied(slinky.core.AttrPair<slinky.web.svg._renderingIntent_attr$>);
    Code:
       0: getstatic     #315                // Field slinky/web/svg/_renderingIntent_attr$.MODULE$:Lslinky/web/svg/_renderingIntent_attr$;
       3: aload_0
       4: invokevirtual #570                // Method slinky/web/svg/_renderingIntent_attr$.toglyphApplied:(Lslinky/core/AttrPair;)Lslinky/core/AttrPair;
       7: areturn

  public static slinky.core.OptionalAttrPair<slinky.web.svg.g$tag$> togOptionalApplied(slinky.core.OptionalAttrPair<slinky.web.svg._renderingIntent_attr$>);
    Code:
       0: getstatic     #315                // Field slinky/web/svg/_renderingIntent_attr$.MODULE$:Lslinky/web/svg/_renderingIntent_attr$;
       3: aload_0
       4: invokevirtual #574                // Method slinky/web/svg/_renderingIntent_attr$.togOptionalApplied:(Lslinky/core/OptionalAttrPair;)Lslinky/core/OptionalAttrPair;
       7: areturn

  public static slinky.core.AttrPair<slinky.web.svg.g$tag$> togApplied(slinky.core.AttrPair<slinky.web.svg._renderingIntent_attr$>);
    Code:
       0: getstatic     #315                // Field slinky/web/svg/_renderingIntent_attr$.MODULE$:Lslinky/web/svg/_renderingIntent_attr$;
       3: aload_0
       4: invokevirtual #578                // Method slinky/web/svg/_renderingIntent_attr$.togApplied:(Lslinky/core/AttrPair;)Lslinky/core/AttrPair;
       7: areturn

  public static slinky.core.OptionalAttrPair<slinky.web.svg.foreignObject$tag$> toforeignObjectOptionalApplied(slinky.core.OptionalAttrPair<slinky.web.svg._renderingIntent_attr$>);
    Code:
       0: getstatic     #315                // Field slinky/web/svg/_renderingIntent_attr$.MODULE$:Lslinky/web/svg/_renderingIntent_attr$;
       3: aload_0
       4: invokevirtual #582                // Method slinky/web/svg/_renderingIntent_attr$.toforeignObjectOptionalApplied:(Lslinky/core/OptionalAttrPair;)Lslinky/core/OptionalAttrPair;
       7: areturn

  public static slinky.core.AttrPair<slinky.web.svg.foreignObject$tag$> toforeignObjectApplied(slinky.core.AttrPair<slinky.web.svg._renderingIntent_attr$>);
    Code:
       0: getstatic     #315                // Field slinky/web/svg/_renderingIntent_attr$.MODULE$:Lslinky/web/svg/_renderingIntent_attr$;
       3: aload_0
       4: invokevirtual #586                // Method slinky/web/svg/_renderingIntent_attr$.toforeignObjectApplied:(Lslinky/core/AttrPair;)Lslinky/core/AttrPair;
       7: areturn

  public static slinky.core.OptionalAttrPair<slinky.web.svg.font$tag$> tofontOptionalApplied(slinky.core.OptionalAttrPair<slinky.web.svg._renderingIntent_attr$>);
    Code:
       0: getstatic     #315                // Field slinky/web/svg/_renderingIntent_attr$.MODULE$:Lslinky/web/svg/_renderingIntent_attr$;
       3: aload_0
       4: invokevirtual #590                // Method slinky/web/svg/_renderingIntent_attr$.tofontOptionalApplied:(Lslinky/core/OptionalAttrPair;)Lslinky/core/OptionalAttrPair;
       7: areturn

  public static slinky.core.AttrPair<slinky.web.svg.font$tag$> tofontApplied(slinky.core.AttrPair<slinky.web.svg._renderingIntent_attr$>);
    Code:
       0: getstatic     #315                // Field slinky/web/svg/_renderingIntent_attr$.MODULE$:Lslinky/web/svg/_renderingIntent_attr$;
       3: aload_0
       4: invokevirtual #594                // Method slinky/web/svg/_renderingIntent_attr$.tofontApplied:(Lslinky/core/AttrPair;)Lslinky/core/AttrPair;
       7: areturn

  public static slinky.core.OptionalAttrPair<slinky.web.svg.filter$tag$> tofilterOptionalApplied(slinky.core.OptionalAttrPair<slinky.web.svg._renderingIntent_attr$>);
    Code:
       0: getstatic     #315                // Field slinky/web/svg/_renderingIntent_attr$.MODULE$:Lslinky/web/svg/_renderingIntent_attr$;
       3: aload_0
       4: invokevirtual #598                // Method slinky/web/svg/_renderingIntent_attr$.tofilterOptionalApplied:(Lslinky/core/OptionalAttrPair;)Lslinky/core/OptionalAttrPair;
       7: areturn

  public static slinky.core.AttrPair<slinky.web.svg.filter$tag$> tofilterApplied(slinky.core.AttrPair<slinky.web.svg._renderingIntent_attr$>);
    Code:
       0: getstatic     #315                // Field slinky/web/svg/_renderingIntent_attr$.MODULE$:Lslinky/web/svg/_renderingIntent_attr$;
       3: aload_0
       4: invokevirtual #602                // Method slinky/web/svg/_renderingIntent_attr$.tofilterApplied:(Lslinky/core/AttrPair;)Lslinky/core/AttrPair;
       7: areturn

  public static slinky.core.OptionalAttrPair<slinky.web.svg.feTurbulence$tag$> tofeTurbulenceOptionalApplied(slinky.core.OptionalAttrPair<slinky.web.svg._renderingIntent_attr$>);
    Code:
       0: getstatic     #315                // Field slinky/web/svg/_renderingIntent_attr$.MODULE$:Lslinky/web/svg/_renderingIntent_attr$;
       3: aload_0
       4: invokevirtual #606                // Method slinky/web/svg/_renderingIntent_attr$.tofeTurbulenceOptionalApplied:(Lslinky/core/OptionalAttrPair;)Lslinky/core/OptionalAttrPair;
       7: areturn

  public static slinky.core.AttrPair<slinky.web.svg.feTurbulence$tag$> tofeTurbulenceApplied(slinky.core.AttrPair<slinky.web.svg._renderingIntent_attr$>);
    Code:
       0: getstatic     #315                // Field slinky/web/svg/_renderingIntent_attr$.MODULE$:Lslinky/web/svg/_renderingIntent_attr$;
       3: aload_0
       4: invokevirtual #610                // Method slinky/web/svg/_renderingIntent_attr$.tofeTurbulenceApplied:(Lslinky/core/AttrPair;)Lslinky/core/AttrPair;
       7: areturn

  public static slinky.core.OptionalAttrPair<slinky.web.svg.feTile$tag$> tofeTileOptionalApplied(slinky.core.OptionalAttrPair<slinky.web.svg._renderingIntent_attr$>);
    Code:
       0: getstatic     #315                // Field slinky/web/svg/_renderingIntent_attr$.MODULE$:Lslinky/web/svg/_renderingIntent_attr$;
       3: aload_0
       4: invokevirtual #614                // Method slinky/web/svg/_renderingIntent_attr$.tofeTileOptionalApplied:(Lslinky/core/OptionalAttrPair;)Lslinky/core/OptionalAttrPair;
       7: areturn

  public static slinky.core.AttrPair<slinky.web.svg.feTile$tag$> tofeTileApplied(slinky.core.AttrPair<slinky.web.svg._renderingIntent_attr$>);
    Code:
       0: getstatic     #315                // Field slinky/web/svg/_renderingIntent_attr$.MODULE$:Lslinky/web/svg/_renderingIntent_attr$;
       3: aload_0
       4: invokevirtual #618                // Method slinky/web/svg/_renderingIntent_attr$.tofeTileApplied:(Lslinky/core/AttrPair;)Lslinky/core/AttrPair;
       7: areturn

  public static slinky.core.OptionalAttrPair<slinky.web.svg.feSpotLight$tag$> tofeSpotLightOptionalApplied(slinky.core.OptionalAttrPair<slinky.web.svg._renderingIntent_attr$>);
    Code:
       0: getstatic     #315                // Field slinky/web/svg/_renderingIntent_attr$.MODULE$:Lslinky/web/svg/_renderingIntent_attr$;
       3: aload_0
       4: invokevirtual #622                // Method slinky/web/svg/_renderingIntent_attr$.tofeSpotLightOptionalApplied:(Lslinky/core/OptionalAttrPair;)Lslinky/core/OptionalAttrPair;
       7: areturn

  public static slinky.core.AttrPair<slinky.web.svg.feSpotLight$tag$> tofeSpotLightApplied(slinky.core.AttrPair<slinky.web.svg._renderingIntent_attr$>);
    Code:
       0: getstatic     #315                // Field slinky/web/svg/_renderingIntent_attr$.MODULE$:Lslinky/web/svg/_renderingIntent_attr$;
       3: aload_0
       4: invokevirtual #626                // Method slinky/web/svg/_renderingIntent_attr$.tofeSpotLightApplied:(Lslinky/core/AttrPair;)Lslinky/core/AttrPair;
       7: areturn

  public static slinky.core.OptionalAttrPair<slinky.web.svg.feSpecularLighting$tag$> tofeSpecularLightingOptionalApplied(slinky.core.OptionalAttrPair<slinky.web.svg._renderingIntent_attr$>);
    Code:
       0: getstatic     #315                // Field slinky/web/svg/_renderingIntent_attr$.MODULE$:Lslinky/web/svg/_renderingIntent_attr$;
       3: aload_0
       4: invokevirtual #630                // Method slinky/web/svg/_renderingIntent_attr$.tofeSpecularLightingOptionalApplied:(Lslinky/core/OptionalAttrPair;)Lslinky/core/OptionalAttrPair;
       7: areturn

  public static slinky.core.AttrPair<slinky.web.svg.feSpecularLighting$tag$> tofeSpecularLightingApplied(slinky.core.AttrPair<slinky.web.svg._renderingIntent_attr$>);
    Code:
       0: getstatic     #315                // Field slinky/web/svg/_renderingIntent_attr$.MODULE$:Lslinky/web/svg/_renderingIntent_attr$;
       3: aload_0
       4: invokevirtual #634                // Method slinky/web/svg/_renderingIntent_attr$.tofeSpecularLightingApplied:(Lslinky/core/AttrPair;)Lslinky/core/AttrPair;
       7: areturn

  public static slinky.core.OptionalAttrPair<slinky.web.svg.fePointLight$tag$> tofePointLightOptionalApplied(slinky.core.OptionalAttrPair<slinky.web.svg._renderingIntent_attr$>);
    Code:
       0: getstatic     #315                // Field slinky/web/svg/_renderingIntent_attr$.MODULE$:Lslinky/web/svg/_renderingIntent_attr$;
       3: aload_0
       4: invokevirtual #638                // Method slinky/web/svg/_renderingIntent_attr$.tofePointLightOptionalApplied:(Lslinky/core/OptionalAttrPair;)Lslinky/core/OptionalAttrPair;
       7: areturn

  public static slinky.core.AttrPair<slinky.web.svg.fePointLight$tag$> tofePointLightApplied(slinky.core.AttrPair<slinky.web.svg._renderingIntent_attr$>);
    Code:
       0: getstatic     #315                // Field slinky/web/svg/_renderingIntent_attr$.MODULE$:Lslinky/web/svg/_renderingIntent_attr$;
       3: aload_0
       4: invokevirtual #642                // Method slinky/web/svg/_renderingIntent_attr$.tofePointLightApplied:(Lslinky/core/AttrPair;)Lslinky/core/AttrPair;
       7: areturn

  public static slinky.core.OptionalAttrPair<slinky.web.svg.feOffset$tag$> tofeOffsetOptionalApplied(slinky.core.OptionalAttrPair<slinky.web.svg._renderingIntent_attr$>);
    Code:
       0: getstatic     #315                // Field slinky/web/svg/_renderingIntent_attr$.MODULE$:Lslinky/web/svg/_renderingIntent_attr$;
       3: aload_0
       4: invokevirtual #646                // Method slinky/web/svg/_renderingIntent_attr$.tofeOffsetOptionalApplied:(Lslinky/core/OptionalAttrPair;)Lslinky/core/OptionalAttrPair;
       7: areturn

  public static slinky.core.AttrPair<slinky.web.svg.feOffset$tag$> tofeOffsetApplied(slinky.core.AttrPair<slinky.web.svg._renderingIntent_attr$>);
    Code:
       0: getstatic     #315                // Field slinky/web/svg/_renderingIntent_attr$.MODULE$:Lslinky/web/svg/_renderingIntent_attr$;
       3: aload_0
       4: invokevirtual #650                // Method slinky/web/svg/_renderingIntent_attr$.tofeOffsetApplied:(Lslinky/core/AttrPair;)Lslinky/core/AttrPair;
       7: areturn

  public static slinky.core.OptionalAttrPair<slinky.web.svg.feMorphology$tag$> tofeMorphologyOptionalApplied(slinky.core.OptionalAttrPair<slinky.web.svg._renderingIntent_attr$>);
    Code:
       0: getstatic     #315                // Field slinky/web/svg/_renderingIntent_attr$.MODULE$:Lslinky/web/svg/_renderingIntent_attr$;
       3: aload_0
       4: invokevirtual #654                // Method slinky/web/svg/_renderingIntent_attr$.tofeMorphologyOptionalApplied:(Lslinky/core/OptionalAttrPair;)Lslinky/core/OptionalAttrPair;
       7: areturn

  public static slinky.core.AttrPair<slinky.web.svg.feMorphology$tag$> tofeMorphologyApplied(slinky.core.AttrPair<slinky.web.svg._renderingIntent_attr$>);
    Code:
       0: getstatic     #315                // Field slinky/web/svg/_renderingIntent_attr$.MODULE$:Lslinky/web/svg/_renderingIntent_attr$;
       3: aload_0
       4: invokevirtual #658                // Method slinky/web/svg/_renderingIntent_attr$.tofeMorphologyApplied:(Lslinky/core/AttrPair;)Lslinky/core/AttrPair;
       7: areturn

  public static slinky.core.OptionalAttrPair<slinky.web.svg.feMergeNode$tag$> tofeMergeNodeOptionalApplied(slinky.core.OptionalAttrPair<slinky.web.svg._renderingIntent_attr$>);
    Code:
       0: getstatic     #315                // Field slinky/web/svg/_renderingIntent_attr$.MODULE$:Lslinky/web/svg/_renderingIntent_attr$;
       3: aload_0
       4: invokevirtual #662                // Method slinky/web/svg/_renderingIntent_attr$.tofeMergeNodeOptionalApplied:(Lslinky/core/OptionalAttrPair;)Lslinky/core/OptionalAttrPair;
       7: areturn

  public static slinky.core.AttrPair<slinky.web.svg.feMergeNode$tag$> tofeMergeNodeApplied(slinky.core.AttrPair<slinky.web.svg._renderingIntent_attr$>);
    Code:
       0: getstatic     #315                // Field slinky/web/svg/_renderingIntent_attr$.MODULE$:Lslinky/web/svg/_renderingIntent_attr$;
       3: aload_0
       4: invokevirtual #666                // Method slinky/web/svg/_renderingIntent_attr$.tofeMergeNodeApplied:(Lslinky/core/AttrPair;)Lslinky/core/AttrPair;
       7: areturn

  public static slinky.core.OptionalAttrPair<slinky.web.svg.feMerge$tag$> tofeMergeOptionalApplied(slinky.core.OptionalAttrPair<slinky.web.svg._renderingIntent_attr$>);
    Code:
       0: getstatic     #315                // Field slinky/web/svg/_renderingIntent_attr$.MODULE$:Lslinky/web/svg/_renderingIntent_attr$;
       3: aload_0
       4: invokevirtual #670                // Method slinky/web/svg/_renderingIntent_attr$.tofeMergeOptionalApplied:(Lslinky/core/OptionalAttrPair;)Lslinky/core/OptionalAttrPair;
       7: areturn

  public static slinky.core.AttrPair<slinky.web.svg.feMerge$tag$> tofeMergeApplied(slinky.core.AttrPair<slinky.web.svg._renderingIntent_attr$>);
    Code:
       0: getstatic     #315                // Field slinky/web/svg/_renderingIntent_attr$.MODULE$:Lslinky/web/svg/_renderingIntent_attr$;
       3: aload_0
       4: invokevirtual #674                // Method slinky/web/svg/_renderingIntent_attr$.tofeMergeApplied:(Lslinky/core/AttrPair;)Lslinky/core/AttrPair;
       7: areturn

  public static slinky.core.OptionalAttrPair<slinky.web.svg.feImage$tag$> tofeImageOptionalApplied(slinky.core.OptionalAttrPair<slinky.web.svg._renderingIntent_attr$>);
    Code:
       0: getstatic     #315                // Field slinky/web/svg/_renderingIntent_attr$.MODULE$:Lslinky/web/svg/_renderingIntent_attr$;
       3: aload_0
       4: invokevirtual #678                // Method slinky/web/svg/_renderingIntent_attr$.tofeImageOptionalApplied:(Lslinky/core/OptionalAttrPair;)Lslinky/core/OptionalAttrPair;
       7: areturn

  public static slinky.core.AttrPair<slinky.web.svg.feImage$tag$> tofeImageApplied(slinky.core.AttrPair<slinky.web.svg._renderingIntent_attr$>);
    Code:
       0: getstatic     #315                // Field slinky/web/svg/_renderingIntent_attr$.MODULE$:Lslinky/web/svg/_renderingIntent_attr$;
       3: aload_0
       4: invokevirtual #682                // Method slinky/web/svg/_renderingIntent_attr$.tofeImageApplied:(Lslinky/core/AttrPair;)Lslinky/core/AttrPair;
       7: areturn

  public static slinky.core.OptionalAttrPair<slinky.web.svg.feGaussianBlur$tag$> tofeGaussianBlurOptionalApplied(slinky.core.OptionalAttrPair<slinky.web.svg._renderingIntent_attr$>);
    Code:
       0: getstatic     #315                // Field slinky/web/svg/_renderingIntent_attr$.MODULE$:Lslinky/web/svg/_renderingIntent_attr$;
       3: aload_0
       4: invokevirtual #686                // Method slinky/web/svg/_renderingIntent_attr$.tofeGaussianBlurOptionalApplied:(Lslinky/core/OptionalAttrPair;)Lslinky/core/OptionalAttrPair;
       7: areturn

  public static slinky.core.AttrPair<slinky.web.svg.feGaussianBlur$tag$> tofeGaussianBlurApplied(slinky.core.AttrPair<slinky.web.svg._renderingIntent_attr$>);
    Code:
       0: getstatic     #315                // Field slinky/web/svg/_renderingIntent_attr$.MODULE$:Lslinky/web/svg/_renderingIntent_attr$;
       3: aload_0
       4: invokevirtual #690                // Method slinky/web/svg/_renderingIntent_attr$.tofeGaussianBlurApplied:(Lslinky/core/AttrPair;)Lslinky/core/AttrPair;
       7: areturn

  public static slinky.core.OptionalAttrPair<slinky.web.svg.feFuncR$tag$> tofeFuncROptionalApplied(slinky.core.OptionalAttrPair<slinky.web.svg._renderingIntent_attr$>);
    Code:
       0: getstatic     #315                // Field slinky/web/svg/_renderingIntent_attr$.MODULE$:Lslinky/web/svg/_renderingIntent_attr$;
       3: aload_0
       4: invokevirtual #694                // Method slinky/web/svg/_renderingIntent_attr$.tofeFuncROptionalApplied:(Lslinky/core/OptionalAttrPair;)Lslinky/core/OptionalAttrPair;
       7: areturn

  public static slinky.core.AttrPair<slinky.web.svg.feFuncR$tag$> tofeFuncRApplied(slinky.core.AttrPair<slinky.web.svg._renderingIntent_attr$>);
    Code:
       0: getstatic     #315                // Field slinky/web/svg/_renderingIntent_attr$.MODULE$:Lslinky/web/svg/_renderingIntent_attr$;
       3: aload_0
       4: invokevirtual #698                // Method slinky/web/svg/_renderingIntent_attr$.tofeFuncRApplied:(Lslinky/core/AttrPair;)Lslinky/core/AttrPair;
       7: areturn

  public static slinky.core.OptionalAttrPair<slinky.web.svg.feFuncG$tag$> tofeFuncGOptionalApplied(slinky.core.OptionalAttrPair<slinky.web.svg._renderingIntent_attr$>);
    Code:
       0: getstatic     #315                // Field slinky/web/svg/_renderingIntent_attr$.MODULE$:Lslinky/web/svg/_renderingIntent_attr$;
       3: aload_0
       4: invokevirtual #702                // Method slinky/web/svg/_renderingIntent_attr$.tofeFuncGOptionalApplied:(Lslinky/core/OptionalAttrPair;)Lslinky/core/OptionalAttrPair;
       7: areturn

  public static slinky.core.AttrPair<slinky.web.svg.feFuncG$tag$> tofeFuncGApplied(slinky.core.AttrPair<slinky.web.svg._renderingIntent_attr$>);
    Code:
       0: getstatic     #315                // Field slinky/web/svg/_renderingIntent_attr$.MODULE$:Lslinky/web/svg/_renderingIntent_attr$;
       3: aload_0
       4: invokevirtual #706                // Method slinky/web/svg/_renderingIntent_attr$.tofeFuncGApplied:(Lslinky/core/AttrPair;)Lslinky/core/AttrPair;
       7: areturn

  public static slinky.core.OptionalAttrPair<slinky.web.svg.feFuncB$tag$> tofeFuncBOptionalApplied(slinky.core.OptionalAttrPair<slinky.web.svg._renderingIntent_attr$>);
    Code:
       0: getstatic     #315                // Field slinky/web/svg/_renderingIntent_attr$.MODULE$:Lslinky/web/svg/_renderingIntent_attr$;
       3: aload_0
       4: invokevirtual #710                // Method slinky/web/svg/_renderingIntent_attr$.tofeFuncBOptionalApplied:(Lslinky/core/OptionalAttrPair;)Lslinky/core/OptionalAttrPair;
       7: areturn

  public static slinky.core.AttrPair<slinky.web.svg.feFuncB$tag$> tofeFuncBApplied(slinky.core.AttrPair<slinky.web.svg._renderingIntent_attr$>);
    Code:
       0: getstatic     #315                // Field slinky/web/svg/_renderingIntent_attr$.MODULE$:Lslinky/web/svg/_renderingIntent_attr$;
       3: aload_0
       4: invokevirtual #714                // Method slinky/web/svg/_renderingIntent_attr$.tofeFuncBApplied:(Lslinky/core/AttrPair;)Lslinky/core/AttrPair;
       7: areturn

  public static slinky.core.OptionalAttrPair<slinky.web.svg.feFuncA$tag$> tofeFuncAOptionalApplied(slinky.core.OptionalAttrPair<slinky.web.svg._renderingIntent_attr$>);
    Code:
       0: getstatic     #315                // Field slinky/web/svg/_renderingIntent_attr$.MODULE$:Lslinky/web/svg/_renderingIntent_attr$;
       3: aload_0
       4: invokevirtual #718                // Method slinky/web/svg/_renderingIntent_attr$.tofeFuncAOptionalApplied:(Lslinky/core/OptionalAttrPair;)Lslinky/core/OptionalAttrPair;
       7: areturn

  public static slinky.core.AttrPair<slinky.web.svg.feFuncA$tag$> tofeFuncAApplied(slinky.core.AttrPair<slinky.web.svg._renderingIntent_attr$>);
    Code:
       0: getstatic     #315                // Field slinky/web/svg/_renderingIntent_attr$.MODULE$:Lslinky/web/svg/_renderingIntent_attr$;
       3: aload_0
       4: invokevirtual #722                // Method slinky/web/svg/_renderingIntent_attr$.tofeFuncAApplied:(Lslinky/core/AttrPair;)Lslinky/core/AttrPair;
       7: areturn

  public static slinky.core.OptionalAttrPair<slinky.web.svg.feFlood$tag$> tofeFloodOptionalApplied(slinky.core.OptionalAttrPair<slinky.web.svg._renderingIntent_attr$>);
    Code:
       0: getstatic     #315                // Field slinky/web/svg/_renderingIntent_attr$.MODULE$:Lslinky/web/svg/_renderingIntent_attr$;
       3: aload_0
       4: invokevirtual #726                // Method slinky/web/svg/_renderingIntent_attr$.tofeFloodOptionalApplied:(Lslinky/core/OptionalAttrPair;)Lslinky/core/OptionalAttrPair;
       7: areturn

  public static slinky.core.AttrPair<slinky.web.svg.feFlood$tag$> tofeFloodApplied(slinky.core.AttrPair<slinky.web.svg._renderingIntent_attr$>);
    Code:
       0: getstatic     #315                // Field slinky/web/svg/_renderingIntent_attr$.MODULE$:Lslinky/web/svg/_renderingIntent_attr$;
       3: aload_0
       4: invokevirtual #730                // Method slinky/web/svg/_renderingIntent_attr$.tofeFloodApplied:(Lslinky/core/AttrPair;)Lslinky/core/AttrPair;
       7: areturn

  public static slinky.core.OptionalAttrPair<slinky.web.svg.feDistantLight$tag$> tofeDistantLightOptionalApplied(slinky.core.OptionalAttrPair<slinky.web.svg._renderingIntent_attr$>);
    Code:
       0: getstatic     #315                // Field slinky/web/svg/_renderingIntent_attr$.MODULE$:Lslinky/web/svg/_renderingIntent_attr$;
       3: aload_0
       4: invokevirtual #734                // Method slinky/web/svg/_renderingIntent_attr$.tofeDistantLightOptionalApplied:(Lslinky/core/OptionalAttrPair;)Lslinky/core/OptionalAttrPair;
       7: areturn

  public static slinky.core.AttrPair<slinky.web.svg.feDistantLight$tag$> tofeDistantLightApplied(slinky.core.AttrPair<slinky.web.svg._renderingIntent_attr$>);
    Code:
       0: getstatic     #315                // Field slinky/web/svg/_renderingIntent_attr$.MODULE$:Lslinky/web/svg/_renderingIntent_attr$;
       3: aload_0
       4: invokevirtual #738                // Method slinky/web/svg/_renderingIntent_attr$.tofeDistantLightApplied:(Lslinky/core/AttrPair;)Lslinky/core/AttrPair;
       7: areturn

  public static slinky.core.OptionalAttrPair<slinky.web.svg.feDisplacementMap$tag$> tofeDisplacementMapOptionalApplied(slinky.core.OptionalAttrPair<slinky.web.svg._renderingIntent_attr$>);
    Code:
       0: getstatic     #315                // Field slinky/web/svg/_renderingIntent_attr$.MODULE$:Lslinky/web/svg/_renderingIntent_attr$;
       3: aload_0
       4: invokevirtual #742                // Method slinky/web/svg/_renderingIntent_attr$.tofeDisplacementMapOptionalApplied:(Lslinky/core/OptionalAttrPair;)Lslinky/core/OptionalAttrPair;
       7: areturn

  public static slinky.core.AttrPair<slinky.web.svg.feDisplacementMap$tag$> tofeDisplacementMapApplied(slinky.core.AttrPair<slinky.web.svg._renderingIntent_attr$>);
    Code:
       0: getstatic     #315                // Field slinky/web/svg/_renderingIntent_attr$.MODULE$:Lslinky/web/svg/_renderingIntent_attr$;
       3: aload_0
       4: invokevirtual #746                // Method slinky/web/svg/_renderingIntent_attr$.tofeDisplacementMapApplied:(Lslinky/core/AttrPair;)Lslinky/core/AttrPair;
       7: areturn

  public static slinky.core.OptionalAttrPair<slinky.web.svg.feDiffuseLighting$tag$> tofeDiffuseLightingOptionalApplied(slinky.core.OptionalAttrPair<slinky.web.svg._renderingIntent_attr$>);
    Code:
       0: getstatic     #315                // Field slinky/web/svg/_renderingIntent_attr$.MODULE$:Lslinky/web/svg/_renderingIntent_attr$;
       3: aload_0
       4: invokevirtual #750                // Method slinky/web/svg/_renderingIntent_attr$.tofeDiffuseLightingOptionalApplied:(Lslinky/core/OptionalAttrPair;)Lslinky/core/OptionalAttrPair;
       7: areturn

  public static slinky.core.AttrPair<slinky.web.svg.feDiffuseLighting$tag$> tofeDiffuseLightingApplied(slinky.core.AttrPair<slinky.web.svg._renderingIntent_attr$>);
    Code:
       0: getstatic     #315                // Field slinky/web/svg/_renderingIntent_attr$.MODULE$:Lslinky/web/svg/_renderingIntent_attr$;
       3: aload_0
       4: invokevirtual #754                // Method slinky/web/svg/_renderingIntent_attr$.tofeDiffuseLightingApplied:(Lslinky/core/AttrPair;)Lslinky/core/AttrPair;
       7: areturn

  public static slinky.core.OptionalAttrPair<slinky.web.svg.feConvolveMatrix$tag$> tofeConvolveMatrixOptionalApplied(slinky.core.OptionalAttrPair<slinky.web.svg._renderingIntent_attr$>);
    Code:
       0: getstatic     #315                // Field slinky/web/svg/_renderingIntent_attr$.MODULE$:Lslinky/web/svg/_renderingIntent_attr$;
       3: aload_0
       4: invokevirtual #758                // Method slinky/web/svg/_renderingIntent_attr$.tofeConvolveMatrixOptionalApplied:(Lslinky/core/OptionalAttrPair;)Lslinky/core/OptionalAttrPair;
       7: areturn

  public static slinky.core.AttrPair<slinky.web.svg.feConvolveMatrix$tag$> tofeConvolveMatrixApplied(slinky.core.AttrPair<slinky.web.svg._renderingIntent_attr$>);
    Code:
       0: getstatic     #315                // Field slinky/web/svg/_renderingIntent_attr$.MODULE$:Lslinky/web/svg/_renderingIntent_attr$;
       3: aload_0
       4: invokevirtual #762                // Method slinky/web/svg/_renderingIntent_attr$.tofeConvolveMatrixApplied:(Lslinky/core/AttrPair;)Lslinky/core/AttrPair;
       7: areturn

  public static slinky.core.OptionalAttrPair<slinky.web.svg.feComposite$tag$> tofeCompositeOptionalApplied(slinky.core.OptionalAttrPair<slinky.web.svg._renderingIntent_attr$>);
    Code:
       0: getstatic     #315                // Field slinky/web/svg/_renderingIntent_attr$.MODULE$:Lslinky/web/svg/_renderingIntent_attr$;
       3: aload_0
       4: invokevirtual #766                // Method slinky/web/svg/_renderingIntent_attr$.tofeCompositeOptionalApplied:(Lslinky/core/OptionalAttrPair;)Lslinky/core/OptionalAttrPair;
       7: areturn

  public static slinky.core.AttrPair<slinky.web.svg.feComposite$tag$> tofeCompositeApplied(slinky.core.AttrPair<slinky.web.svg._renderingIntent_attr$>);
    Code:
       0: getstatic     #315                // Field slinky/web/svg/_renderingIntent_attr$.MODULE$:Lslinky/web/svg/_renderingIntent_attr$;
       3: aload_0
       4: invokevirtual #770                // Method slinky/web/svg/_renderingIntent_attr$.tofeCompositeApplied:(Lslinky/core/AttrPair;)Lslinky/core/AttrPair;
       7: areturn

  public static slinky.core.OptionalAttrPair<slinky.web.svg.feComponentTransfer$tag$> tofeComponentTransferOptionalApplied(slinky.core.OptionalAttrPair<slinky.web.svg._renderingIntent_attr$>);
    Code:
       0: getstatic     #315                // Field slinky/web/svg/_renderingIntent_attr$.MODULE$:Lslinky/web/svg/_renderingIntent_attr$;
       3: aload_0
       4: invokevirtual #774                // Method slinky/web/svg/_renderingIntent_attr$.tofeComponentTransferOptionalApplied:(Lslinky/core/OptionalAttrPair;)Lslinky/core/OptionalAttrPair;
       7: areturn

  public static slinky.core.AttrPair<slinky.web.svg.feComponentTransfer$tag$> tofeComponentTransferApplied(slinky.core.AttrPair<slinky.web.svg._renderingIntent_attr$>);
    Code:
       0: getstatic     #315                // Field slinky/web/svg/_renderingIntent_attr$.MODULE$:Lslinky/web/svg/_renderingIntent_attr$;
       3: aload_0
       4: invokevirtual #778                // Method slinky/web/svg/_renderingIntent_attr$.tofeComponentTransferApplied:(Lslinky/core/AttrPair;)Lslinky/core/AttrPair;
       7: areturn

  public static slinky.core.OptionalAttrPair<slinky.web.svg.feColorMatrix$tag$> tofeColorMatrixOptionalApplied(slinky.core.OptionalAttrPair<slinky.web.svg._renderingIntent_attr$>);
    Code:
       0: getstatic     #315                // Field slinky/web/svg/_renderingIntent_attr$.MODULE$:Lslinky/web/svg/_renderingIntent_attr$;
       3: aload_0
       4: invokevirtual #782                // Method slinky/web/svg/_renderingIntent_attr$.tofeColorMatrixOptionalApplied:(Lslinky/core/OptionalAttrPair;)Lslinky/core/OptionalAttrPair;
       7: areturn

  public static slinky.core.AttrPair<slinky.web.svg.feColorMatrix$tag$> tofeColorMatrixApplied(slinky.core.AttrPair<slinky.web.svg._renderingIntent_attr$>);
    Code:
       0: getstatic     #315                // Field slinky/web/svg/_renderingIntent_attr$.MODULE$:Lslinky/web/svg/_renderingIntent_attr$;
       3: aload_0
       4: invokevirtual #786                // Method slinky/web/svg/_renderingIntent_attr$.tofeColorMatrixApplied:(Lslinky/core/AttrPair;)Lslinky/core/AttrPair;
       7: areturn

  public static slinky.core.OptionalAttrPair<slinky.web.svg.feBlend$tag$> tofeBlendOptionalApplied(slinky.core.OptionalAttrPair<slinky.web.svg._renderingIntent_attr$>);
    Code:
       0: getstatic     #315                // Field slinky/web/svg/_renderingIntent_attr$.MODULE$:Lslinky/web/svg/_renderingIntent_attr$;
       3: aload_0
       4: invokevirtual #790                // Method slinky/web/svg/_renderingIntent_attr$.tofeBlendOptionalApplied:(Lslinky/core/OptionalAttrPair;)Lslinky/core/OptionalAttrPair;
       7: areturn

  public static slinky.core.AttrPair<slinky.web.svg.feBlend$tag$> tofeBlendApplied(slinky.core.AttrPair<slinky.web.svg._renderingIntent_attr$>);
    Code:
       0: getstatic     #315                // Field slinky/web/svg/_renderingIntent_attr$.MODULE$:Lslinky/web/svg/_renderingIntent_attr$;
       3: aload_0
       4: invokevirtual #794                // Method slinky/web/svg/_renderingIntent_attr$.tofeBlendApplied:(Lslinky/core/AttrPair;)Lslinky/core/AttrPair;
       7: areturn

  public static slinky.core.OptionalAttrPair<slinky.web.svg.ellipse$tag$> toellipseOptionalApplied(slinky.core.OptionalAttrPair<slinky.web.svg._renderingIntent_attr$>);
    Code:
       0: getstatic     #315                // Field slinky/web/svg/_renderingIntent_attr$.MODULE$:Lslinky/web/svg/_renderingIntent_attr$;
       3: aload_0
       4: invokevirtual #798                // Method slinky/web/svg/_renderingIntent_attr$.toellipseOptionalApplied:(Lslinky/core/OptionalAttrPair;)Lslinky/core/OptionalAttrPair;
       7: areturn

  public static slinky.core.AttrPair<slinky.web.svg.ellipse$tag$> toellipseApplied(slinky.core.AttrPair<slinky.web.svg._renderingIntent_attr$>);
    Code:
       0: getstatic     #315                // Field slinky/web/svg/_renderingIntent_attr$.MODULE$:Lslinky/web/svg/_renderingIntent_attr$;
       3: aload_0
       4: invokevirtual #802                // Method slinky/web/svg/_renderingIntent_attr$.toellipseApplied:(Lslinky/core/AttrPair;)Lslinky/core/AttrPair;
       7: areturn

  public static slinky.core.OptionalAttrPair<slinky.web.svg.desc$tag$> todescOptionalApplied(slinky.core.OptionalAttrPair<slinky.web.svg._renderingIntent_attr$>);
    Code:
       0: getstatic     #315                // Field slinky/web/svg/_renderingIntent_attr$.MODULE$:Lslinky/web/svg/_renderingIntent_attr$;
       3: aload_0
       4: invokevirtual #806                // Method slinky/web/svg/_renderingIntent_attr$.todescOptionalApplied:(Lslinky/core/OptionalAttrPair;)Lslinky/core/OptionalAttrPair;
       7: areturn

  public static slinky.core.AttrPair<slinky.web.svg.desc$tag$> todescApplied(slinky.core.AttrPair<slinky.web.svg._renderingIntent_attr$>);
    Code:
       0: getstatic     #315                // Field slinky/web/svg/_renderingIntent_attr$.MODULE$:Lslinky/web/svg/_renderingIntent_attr$;
       3: aload_0
       4: invokevirtual #810                // Method slinky/web/svg/_renderingIntent_attr$.todescApplied:(Lslinky/core/AttrPair;)Lslinky/core/AttrPair;
       7: areturn

  public static slinky.core.OptionalAttrPair<slinky.web.svg.defs$tag$> todefsOptionalApplied(slinky.core.OptionalAttrPair<slinky.web.svg._renderingIntent_attr$>);
    Code:
       0: getstatic     #315                // Field slinky/web/svg/_renderingIntent_attr$.MODULE$:Lslinky/web/svg/_renderingIntent_attr$;
       3: aload_0
       4: invokevirtual #814                // Method slinky/web/svg/_renderingIntent_attr$.todefsOptionalApplied:(Lslinky/core/OptionalAttrPair;)Lslinky/core/OptionalAttrPair;
       7: areturn

  public static slinky.core.AttrPair<slinky.web.svg.defs$tag$> todefsApplied(slinky.core.AttrPair<slinky.web.svg._renderingIntent_attr$>);
    Code:
       0: getstatic     #315                // Field slinky/web/svg/_renderingIntent_attr$.MODULE$:Lslinky/web/svg/_renderingIntent_attr$;
       3: aload_0
       4: invokevirtual #818                // Method slinky/web/svg/_renderingIntent_attr$.todefsApplied:(Lslinky/core/AttrPair;)Lslinky/core/AttrPair;
       7: areturn

  public static slinky.core.OptionalAttrPair<slinky.web.svg.cursor$tag$> tocursorOptionalApplied(slinky.core.OptionalAttrPair<slinky.web.svg._renderingIntent_attr$>);
    Code:
       0: getstatic     #315                // Field slinky/web/svg/_renderingIntent_attr$.MODULE$:Lslinky/web/svg/_renderingIntent_attr$;
       3: aload_0
       4: invokevirtual #822                // Method slinky/web/svg/_renderingIntent_attr$.tocursorOptionalApplied:(Lslinky/core/OptionalAttrPair;)Lslinky/core/OptionalAttrPair;
       7: areturn

  public static slinky.core.AttrPair<slinky.web.svg.cursor$tag$> tocursorApplied(slinky.core.AttrPair<slinky.web.svg._renderingIntent_attr$>);
    Code:
       0: getstatic     #315                // Field slinky/web/svg/_renderingIntent_attr$.MODULE$:Lslinky/web/svg/_renderingIntent_attr$;
       3: aload_0
       4: invokevirtual #826                // Method slinky/web/svg/_renderingIntent_attr$.tocursorApplied:(Lslinky/core/AttrPair;)Lslinky/core/AttrPair;
       7: areturn

  public static slinky.core.OptionalAttrPair<slinky.web.svg.clipPath$tag$> toclipPathOptionalApplied(slinky.core.OptionalAttrPair<slinky.web.svg._renderingIntent_attr$>);
    Code:
       0: getstatic     #315                // Field slinky/web/svg/_renderingIntent_attr$.MODULE$:Lslinky/web/svg/_renderingIntent_attr$;
       3: aload_0
       4: invokevirtual #830                // Method slinky/web/svg/_renderingIntent_attr$.toclipPathOptionalApplied:(Lslinky/core/OptionalAttrPair;)Lslinky/core/OptionalAttrPair;
       7: areturn

  public static slinky.core.AttrPair<slinky.web.svg.clipPath$tag$> toclipPathApplied(slinky.core.AttrPair<slinky.web.svg._renderingIntent_attr$>);
    Code:
       0: getstatic     #315                // Field slinky/web/svg/_renderingIntent_attr$.MODULE$:Lslinky/web/svg/_renderingIntent_attr$;
       3: aload_0
       4: invokevirtual #834                // Method slinky/web/svg/_renderingIntent_attr$.toclipPathApplied:(Lslinky/core/AttrPair;)Lslinky/core/AttrPair;
       7: areturn

  public static slinky.core.OptionalAttrPair<slinky.web.svg.circle$tag$> tocircleOptionalApplied(slinky.core.OptionalAttrPair<slinky.web.svg._renderingIntent_attr$>);
    Code:
       0: getstatic     #315                // Field slinky/web/svg/_renderingIntent_attr$.MODULE$:Lslinky/web/svg/_renderingIntent_attr$;
       3: aload_0
       4: invokevirtual #838                // Method slinky/web/svg/_renderingIntent_attr$.tocircleOptionalApplied:(Lslinky/core/OptionalAttrPair;)Lslinky/core/OptionalAttrPair;
       7: areturn

  public static slinky.core.AttrPair<slinky.web.svg.circle$tag$> tocircleApplied(slinky.core.AttrPair<slinky.web.svg._renderingIntent_attr$>);
    Code:
       0: getstatic     #315                // Field slinky/web/svg/_renderingIntent_attr$.MODULE$:Lslinky/web/svg/_renderingIntent_attr$;
       3: aload_0
       4: invokevirtual #842                // Method slinky/web/svg/_renderingIntent_attr$.tocircleApplied:(Lslinky/core/AttrPair;)Lslinky/core/AttrPair;
       7: areturn

  public static slinky.core.OptionalAttrPair<slinky.web.svg.animateTransform$tag$> toanimateTransformOptionalApplied(slinky.core.OptionalAttrPair<slinky.web.svg._renderingIntent_attr$>);
    Code:
       0: getstatic     #315                // Field slinky/web/svg/_renderingIntent_attr$.MODULE$:Lslinky/web/svg/_renderingIntent_attr$;
       3: aload_0
       4: invokevirtual #846                // Method slinky/web/svg/_renderingIntent_attr$.toanimateTransformOptionalApplied:(Lslinky/core/OptionalAttrPair;)Lslinky/core/OptionalAttrPair;
       7: areturn

  public static slinky.core.AttrPair<slinky.web.svg.animateTransform$tag$> toanimateTransformApplied(slinky.core.AttrPair<slinky.web.svg._renderingIntent_attr$>);
    Code:
       0: getstatic     #315                // Field slinky/web/svg/_renderingIntent_attr$.MODULE$:Lslinky/web/svg/_renderingIntent_attr$;
       3: aload_0
       4: invokevirtual #850                // Method slinky/web/svg/_renderingIntent_attr$.toanimateTransformApplied:(Lslinky/core/AttrPair;)Lslinky/core/AttrPair;
       7: areturn

  public static slinky.core.OptionalAttrPair<slinky.web.svg.animateMotion$tag$> toanimateMotionOptionalApplied(slinky.core.OptionalAttrPair<slinky.web.svg._renderingIntent_attr$>);
    Code:
       0: getstatic     #315                // Field slinky/web/svg/_renderingIntent_attr$.MODULE$:Lslinky/web/svg/_renderingIntent_attr$;
       3: aload_0
       4: invokevirtual #854                // Method slinky/web/svg/_renderingIntent_attr$.toanimateMotionOptionalApplied:(Lslinky/core/OptionalAttrPair;)Lslinky/core/OptionalAttrPair;
       7: areturn

  public static slinky.core.AttrPair<slinky.web.svg.animateMotion$tag$> toanimateMotionApplied(slinky.core.AttrPair<slinky.web.svg._renderingIntent_attr$>);
    Code:
       0: getstatic     #315                // Field slinky/web/svg/_renderingIntent_attr$.MODULE$:Lslinky/web/svg/_renderingIntent_attr$;
       3: aload_0
       4: invokevirtual #858                // Method slinky/web/svg/_renderingIntent_attr$.toanimateMotionApplied:(Lslinky/core/AttrPair;)Lslinky/core/AttrPair;
       7: areturn

  public static slinky.core.OptionalAttrPair<slinky.web.svg.animateColor$tag$> toanimateColorOptionalApplied(slinky.core.OptionalAttrPair<slinky.web.svg._renderingIntent_attr$>);
    Code:
       0: getstatic     #315                // Field slinky/web/svg/_renderingIntent_attr$.MODULE$:Lslinky/web/svg/_renderingIntent_attr$;
       3: aload_0
       4: invokevirtual #862                // Method slinky/web/svg/_renderingIntent_attr$.toanimateColorOptionalApplied:(Lslinky/core/OptionalAttrPair;)Lslinky/core/OptionalAttrPair;
       7: areturn

  public static slinky.core.AttrPair<slinky.web.svg.animateColor$tag$> toanimateColorApplied(slinky.core.AttrPair<slinky.web.svg._renderingIntent_attr$>);
    Code:
       0: getstatic     #315                // Field slinky/web/svg/_renderingIntent_attr$.MODULE$:Lslinky/web/svg/_renderingIntent_attr$;
       3: aload_0
       4: invokevirtual #866                // Method slinky/web/svg/_renderingIntent_attr$.toanimateColorApplied:(Lslinky/core/AttrPair;)Lslinky/core/AttrPair;
       7: areturn

  public static slinky.core.OptionalAttrPair<slinky.web.svg.animate$tag$> toanimateOptionalApplied(slinky.core.OptionalAttrPair<slinky.web.svg._renderingIntent_attr$>);
    Code:
       0: getstatic     #315                // Field slinky/web/svg/_renderingIntent_attr$.MODULE$:Lslinky/web/svg/_renderingIntent_attr$;
       3: aload_0
       4: invokevirtual #870                // Method slinky/web/svg/_renderingIntent_attr$.toanimateOptionalApplied:(Lslinky/core/OptionalAttrPair;)Lslinky/core/OptionalAttrPair;
       7: areturn

  public static slinky.core.AttrPair<slinky.web.svg.animate$tag$> toanimateApplied(slinky.core.AttrPair<slinky.web.svg._renderingIntent_attr$>);
    Code:
       0: getstatic     #315                // Field slinky/web/svg/_renderingIntent_attr$.MODULE$:Lslinky/web/svg/_renderingIntent_attr$;
       3: aload_0
       4: invokevirtual #874                // Method slinky/web/svg/_renderingIntent_attr$.toanimateApplied:(Lslinky/core/AttrPair;)Lslinky/core/AttrPair;
       7: areturn

  public static slinky.core.OptionalAttrPair<slinky.web.svg.altGlyphItem$tag$> toaltGlyphItemOptionalApplied(slinky.core.OptionalAttrPair<slinky.web.svg._renderingIntent_attr$>);
    Code:
       0: getstatic     #315                // Field slinky/web/svg/_renderingIntent_attr$.MODULE$:Lslinky/web/svg/_renderingIntent_attr$;
       3: aload_0
       4: invokevirtual #878                // Method slinky/web/svg/_renderingIntent_attr$.toaltGlyphItemOptionalApplied:(Lslinky/core/OptionalAttrPair;)Lslinky/core/OptionalAttrPair;
       7: areturn

  public static slinky.core.AttrPair<slinky.web.svg.altGlyphItem$tag$> toaltGlyphItemApplied(slinky.core.AttrPair<slinky.web.svg._renderingIntent_attr$>);
    Code:
       0: getstatic     #315                // Field slinky/web/svg/_renderingIntent_attr$.MODULE$:Lslinky/web/svg/_renderingIntent_attr$;
       3: aload_0
       4: invokevirtual #882                // Method slinky/web/svg/_renderingIntent_attr$.toaltGlyphItemApplied:(Lslinky/core/AttrPair;)Lslinky/core/AttrPair;
       7: areturn

  public static slinky.core.OptionalAttrPair<slinky.web.svg.altGlyphDef$tag$> toaltGlyphDefOptionalApplied(slinky.core.OptionalAttrPair<slinky.web.svg._renderingIntent_attr$>);
    Code:
       0: getstatic     #315                // Field slinky/web/svg/_renderingIntent_attr$.MODULE$:Lslinky/web/svg/_renderingIntent_attr$;
       3: aload_0
       4: invokevirtual #886                // Method slinky/web/svg/_renderingIntent_attr$.toaltGlyphDefOptionalApplied:(Lslinky/core/OptionalAttrPair;)Lslinky/core/OptionalAttrPair;
       7: areturn

  public static slinky.core.AttrPair<slinky.web.svg.altGlyphDef$tag$> toaltGlyphDefApplied(slinky.core.AttrPair<slinky.web.svg._renderingIntent_attr$>);
    Code:
       0: getstatic     #315                // Field slinky/web/svg/_renderingIntent_attr$.MODULE$:Lslinky/web/svg/_renderingIntent_attr$;
       3: aload_0
       4: invokevirtual #890                // Method slinky/web/svg/_renderingIntent_attr$.toaltGlyphDefApplied:(Lslinky/core/AttrPair;)Lslinky/core/AttrPair;
       7: areturn

  public static slinky.core.OptionalAttrPair<slinky.web.svg.altGlyph$tag$> toaltGlyphOptionalApplied(slinky.core.OptionalAttrPair<slinky.web.svg._renderingIntent_attr$>);
    Code:
       0: getstatic     #315                // Field slinky/web/svg/_renderingIntent_attr$.MODULE$:Lslinky/web/svg/_renderingIntent_attr$;
       3: aload_0
       4: invokevirtual #894                // Method slinky/web/svg/_renderingIntent_attr$.toaltGlyphOptionalApplied:(Lslinky/core/OptionalAttrPair;)Lslinky/core/OptionalAttrPair;
       7: areturn

  public static slinky.core.AttrPair<slinky.web.svg.altGlyph$tag$> toaltGlyphApplied(slinky.core.AttrPair<slinky.web.svg._renderingIntent_attr$>);
    Code:
       0: getstatic     #315                // Field slinky/web/svg/_renderingIntent_attr$.MODULE$:Lslinky/web/svg/_renderingIntent_attr$;
       3: aload_0
       4: invokevirtual #898                // Method slinky/web/svg/_renderingIntent_attr$.toaltGlyphApplied:(Lslinky/core/AttrPair;)Lslinky/core/AttrPair;
       7: areturn

  public static slinky.core.OptionalAttrPair<slinky.web.svg.a$tag$> toaOptionalApplied(slinky.core.OptionalAttrPair<slinky.web.svg._renderingIntent_attr$>);
    Code:
       0: getstatic     #315                // Field slinky/web/svg/_renderingIntent_attr$.MODULE$:Lslinky/web/svg/_renderingIntent_attr$;
       3: aload_0
       4: invokevirtual #902                // Method slinky/web/svg/_renderingIntent_attr$.toaOptionalApplied:(Lslinky/core/OptionalAttrPair;)Lslinky/core/OptionalAttrPair;
       7: areturn

  public static slinky.core.AttrPair<slinky.web.svg.a$tag$> toaApplied(slinky.core.AttrPair<slinky.web.svg._renderingIntent_attr$>);
    Code:
       0: getstatic     #315                // Field slinky/web/svg/_renderingIntent_attr$.MODULE$:Lslinky/web/svg/_renderingIntent_attr$;
       3: aload_0
       4: invokevirtual #906                // Method slinky/web/svg/_renderingIntent_attr$.toaApplied:(Lslinky/core/AttrPair;)Lslinky/core/AttrPair;
       7: areturn
}
