Compiled from "DelegatorOutputStream.java"
public class org.ow2.util.stream.impl.delegator.DelegatorOutputStream extends java.io.FileOutputStream {
  private org.ow2.util.stream.impl.delegator.DelegatorStreamAccessor delegatorFileAccessor;

  private java.io.File temporaryFile;

  public org.ow2.util.stream.impl.delegator.DelegatorOutputStream(org.ow2.util.stream.impl.delegator.DelegatorStreamAccessor, java.io.File, boolean) throws java.io.FileNotFoundException;
    Code:
       0: aload_0
       1: aload_2
       2: invokespecial #1                  // Method java/io/FileOutputStream."<init>":(Ljava/io/File;)V
       5: iload_3
       6: ifeq          14
       9: aload_0
      10: aload_2
      11: putfield      #2                  // Field temporaryFile:Ljava/io/File;
      14: return

  public void flush() throws java.io.IOException;
    Code:
       0: aload_0
       1: invokespecial #3                  // Method java/io/FileOutputStream.flush:()V
       4: aload_0
       5: getfield      #2                  // Field temporaryFile:Ljava/io/File;
       8: ifnonnull     18
      11: aload_0
      12: getfield      #4                  // Field delegatorFileAccessor:Lorg/ow2/util/stream/impl/delegator/DelegatorStreamAccessor;
      15: invokevirtual #5                  // Method org/ow2/util/stream/impl/delegator/DelegatorStreamAccessor.doWrite:()V
      18: return

  public void close() throws java.io.IOException;
    Code:
       0: aload_0
       1: invokespecial #3                  // Method java/io/FileOutputStream.flush:()V
       4: aload_0
       5: invokespecial #6                  // Method java/io/FileOutputStream.close:()V
       8: aload_0
       9: getfield      #2                  // Field temporaryFile:Ljava/io/File;
      12: ifnull        29
      15: aload_0
      16: getfield      #4                  // Field delegatorFileAccessor:Lorg/ow2/util/stream/impl/delegator/DelegatorStreamAccessor;
      19: aload_0
      20: getfield      #2                  // Field temporaryFile:Ljava/io/File;
      23: invokevirtual #7                  // Method org/ow2/util/stream/impl/delegator/DelegatorStreamAccessor.doWrite:(Ljava/io/File;)V
      26: goto          36
      29: aload_0
      30: getfield      #4                  // Field delegatorFileAccessor:Lorg/ow2/util/stream/impl/delegator/DelegatorStreamAccessor;
      33: invokevirtual #5                  // Method org/ow2/util/stream/impl/delegator/DelegatorStreamAccessor.doWrite:()V
      36: return

  protected void finalize();
    Code:
       0: aload_0
       1: getfield      #2                  // Field temporaryFile:Ljava/io/File;
       4: ifnull        15
       7: aload_0
       8: getfield      #2                  // Field temporaryFile:Ljava/io/File;
      11: invokevirtual #8                  // Method java/io/File.delete:()Z
      14: pop
      15: return
}
