Compiled from "CpuCoolers.java"
final class net.openhft.chronicle.core.cooler.CpuCoolers$19 extends net.openhft.chronicle.core.cooler.CpuCoolers {
  net.openhft.chronicle.core.cooler.CpuCoolers$19(java.lang.String, int);
    Code:
       0: aload_0
       1: aload_1
       2: iload_2
       3: aconst_null
       4: invokespecial #1                  // Method net/openhft/chronicle/core/cooler/CpuCoolers."<init>":(Ljava/lang/String;ILnet/openhft/chronicle/core/cooler/CpuCoolers$1;)V
       7: return

  public void disturb();
    Code:
       0: new           #2                  // class java/io/ByteArrayOutputStream
       3: dup
       4: invokespecial #3                  // Method java/io/ByteArrayOutputStream."<init>":()V
       7: astore_1
       8: new           #4                  // class java/beans/XMLEncoder
      11: dup
      12: aload_1
      13: invokespecial #5                  // Method java/beans/XMLEncoder."<init>":(Ljava/io/OutputStream;)V
      16: astore_2
      17: aload_2
      18: invokestatic  #6                  // Method java/lang/System.getProperties:()Ljava/util/Properties;
      21: invokevirtual #7                  // Method java/beans/XMLEncoder.writeObject:(Ljava/lang/Object;)V
      24: aload_2
      25: invokevirtual #8                  // Method java/beans/XMLEncoder.close:()V
      28: new           #9                  // class java/beans/XMLDecoder
      31: dup
      32: new           #10                 // class java/io/ByteArrayInputStream
      35: dup
      36: aload_1
      37: invokevirtual #11                 // Method java/io/ByteArrayOutputStream.toByteArray:()[B
      40: invokespecial #12                 // Method java/io/ByteArrayInputStream."<init>":([B)V
      43: invokespecial #13                 // Method java/beans/XMLDecoder."<init>":(Ljava/io/InputStream;)V
      46: astore_3
      47: aload_3
      48: invokevirtual #14                 // Method java/beans/XMLDecoder.readObject:()Ljava/lang/Object;
      51: putstatic     #15                 // Field blackhole:Ljava/lang/Object;
      54: return
}
