Compiled from "RequestAbortedException.java"
public class org.apache.hc.client5.http.impl.classic.RequestAbortedException extends java.io.InterruptedIOException {
  private static final long serialVersionUID;

  public org.apache.hc.client5.http.impl.classic.RequestAbortedException(java.lang.String);
    Code:
       0: aload_0
       1: aload_1
       2: invokespecial #1                  // Method java/io/InterruptedIOException."<init>":(Ljava/lang/String;)V
       5: return

  public org.apache.hc.client5.http.impl.classic.RequestAbortedException(java.lang.String, java.lang.Throwable);
    Code:
       0: aload_0
       1: aload_1
       2: invokespecial #1                  // Method java/io/InterruptedIOException."<init>":(Ljava/lang/String;)V
       5: aload_2
       6: ifnull        15
       9: aload_0
      10: aload_2
      11: invokevirtual #2                  // Method initCause:(Ljava/lang/Throwable;)Ljava/lang/Throwable;
      14: pop
      15: return
}
