Compiled from "NoopTags.java"
final class io.opencensus.tags.NoopTags$NoopTagger extends io.opencensus.tags.Tagger {
  static final io.opencensus.tags.Tagger INSTANCE;

  private io.opencensus.tags.NoopTags$NoopTagger();
    Code:
       0: aload_0
       1: invokespecial #1                  // Method io/opencensus/tags/Tagger."<init>":()V
       4: return

  public io.opencensus.tags.TagContext empty();
    Code:
       0: invokestatic  #2                  // Method io/opencensus/tags/NoopTags.getNoopTagContext:()Lio/opencensus/tags/TagContext;
       3: areturn

  public io.opencensus.tags.TagContext getCurrentTagContext();
    Code:
       0: invokestatic  #2                  // Method io/opencensus/tags/NoopTags.getNoopTagContext:()Lio/opencensus/tags/TagContext;
       3: areturn

  public io.opencensus.tags.TagContextBuilder emptyBuilder();
    Code:
       0: invokestatic  #3                  // Method io/opencensus/tags/NoopTags.getNoopTagContextBuilder:()Lio/opencensus/tags/TagContextBuilder;
       3: areturn

  public io.opencensus.tags.TagContextBuilder toBuilder(io.opencensus.tags.TagContext);
    Code:
       0: aload_1
       1: ldc           #4                  // String tags
       3: invokestatic  #5                  // Method io/opencensus/internal/Utils.checkNotNull:(Ljava/lang/Object;Ljava/lang/Object;)Ljava/lang/Object;
       6: pop
       7: invokestatic  #3                  // Method io/opencensus/tags/NoopTags.getNoopTagContextBuilder:()Lio/opencensus/tags/TagContextBuilder;
      10: areturn

  public io.opencensus.tags.TagContextBuilder currentBuilder();
    Code:
       0: invokestatic  #3                  // Method io/opencensus/tags/NoopTags.getNoopTagContextBuilder:()Lio/opencensus/tags/TagContextBuilder;
       3: areturn

  public io.opencensus.common.Scope withTagContext(io.opencensus.tags.TagContext);
    Code:
       0: aload_1
       1: ldc           #4                  // String tags
       3: invokestatic  #5                  // Method io/opencensus/internal/Utils.checkNotNull:(Ljava/lang/Object;Ljava/lang/Object;)Ljava/lang/Object;
       6: pop
       7: invokestatic  #6                  // Method io/opencensus/internal/NoopScope.getInstance:()Lio/opencensus/common/Scope;
      10: areturn

  static {};
    Code:
       0: new           #7                  // class io/opencensus/tags/NoopTags$NoopTagger
       3: dup
       4: invokespecial #8                  // Method "<init>":()V
       7: putstatic     #9                  // Field INSTANCE:Lio/opencensus/tags/Tagger;
      10: return
}
