Compiled from "TagContext.java"
public abstract class io.opencensus.tags.TagContext {
  public io.opencensus.tags.TagContext();
    Code:
       0: aload_0
       1: invokespecial #1                  // Method java/lang/Object."<init>":()V
       4: return

  protected abstract java.util.Iterator<io.opencensus.tags.Tag> getIterator();

  public java.lang.String toString();
    Code:
       0: ldc           #2                  // String TagContext
       2: areturn

  public boolean equals(java.lang.Object);
    Code:
       0: aload_1
       1: instanceof    #3                  // class io/opencensus/tags/TagContext
       4: ifne          9
       7: iconst_0
       8: ireturn
       9: aload_1
      10: checkcast     #3                  // class io/opencensus/tags/TagContext
      13: astore_2
      14: aload_0
      15: invokevirtual #4                  // Method getIterator:()Ljava/util/Iterator;
      18: astore_3
      19: aload_2
      20: invokevirtual #4                  // Method getIterator:()Ljava/util/Iterator;
      23: astore        4
      25: new           #5                  // class java/util/HashMap
      28: dup
      29: invokespecial #6                  // Method java/util/HashMap."<init>":()V
      32: astore        5
      34: aload_3
      35: ifnull        112
      38: aload_3
      39: invokeinterface #7,  1            // InterfaceMethod java/util/Iterator.hasNext:()Z
      44: ifeq          112
      47: aload_3
      48: invokeinterface #8,  1            // InterfaceMethod java/util/Iterator.next:()Ljava/lang/Object;
      53: checkcast     #9                  // class io/opencensus/tags/Tag
      56: astore        6
      58: aload         5
      60: aload         6
      62: invokevirtual #10                 // Method java/util/HashMap.containsKey:(Ljava/lang/Object;)Z
      65: ifeq          97
      68: aload         5
      70: aload         6
      72: aload         5
      74: aload         6
      76: invokevirtual #11                 // Method java/util/HashMap.get:(Ljava/lang/Object;)Ljava/lang/Object;
      79: checkcast     #12                 // class java/lang/Integer
      82: invokevirtual #13                 // Method java/lang/Integer.intValue:()I
      85: iconst_1
      86: iadd
      87: invokestatic  #14                 // Method java/lang/Integer.valueOf:(I)Ljava/lang/Integer;
      90: invokevirtual #15                 // Method java/util/HashMap.put:(Ljava/lang/Object;Ljava/lang/Object;)Ljava/lang/Object;
      93: pop
      94: goto          109
      97: aload         5
      99: aload         6
     101: iconst_1
     102: invokestatic  #14                 // Method java/lang/Integer.valueOf:(I)Ljava/lang/Integer;
     105: invokevirtual #15                 // Method java/util/HashMap.put:(Ljava/lang/Object;Ljava/lang/Object;)Ljava/lang/Object;
     108: pop
     109: goto          34
     112: aload         4
     114: ifnull        201
     117: aload         4
     119: invokeinterface #7,  1            // InterfaceMethod java/util/Iterator.hasNext:()Z
     124: ifeq          201
     127: aload         4
     129: invokeinterface #8,  1            // InterfaceMethod java/util/Iterator.next:()Ljava/lang/Object;
     134: checkcast     #9                  // class io/opencensus/tags/Tag
     137: astore        6
     139: aload         5
     141: aload         6
     143: invokevirtual #10                 // Method java/util/HashMap.containsKey:(Ljava/lang/Object;)Z
     146: ifne          151
     149: iconst_0
     150: ireturn
     151: aload         5
     153: aload         6
     155: invokevirtual #11                 // Method java/util/HashMap.get:(Ljava/lang/Object;)Ljava/lang/Object;
     158: checkcast     #12                 // class java/lang/Integer
     161: invokevirtual #13                 // Method java/lang/Integer.intValue:()I
     164: istore        7
     166: iload         7
     168: iconst_1
     169: if_icmple     190
     172: aload         5
     174: aload         6
     176: iload         7
     178: iconst_1
     179: isub
     180: invokestatic  #14                 // Method java/lang/Integer.valueOf:(I)Ljava/lang/Integer;
     183: invokevirtual #15                 // Method java/util/HashMap.put:(Ljava/lang/Object;Ljava/lang/Object;)Ljava/lang/Object;
     186: pop
     187: goto          198
     190: aload         5
     192: aload         6
     194: invokevirtual #16                 // Method java/util/HashMap.remove:(Ljava/lang/Object;)Ljava/lang/Object;
     197: pop
     198: goto          112
     201: aload         5
     203: invokevirtual #17                 // Method java/util/HashMap.isEmpty:()Z
     206: ireturn

  public final int hashCode();
    Code:
       0: iconst_0
       1: istore_1
       2: aload_0
       3: invokevirtual #4                  // Method getIterator:()Ljava/util/Iterator;
       6: astore_2
       7: aload_2
       8: ifnonnull     13
      11: iload_1
      12: ireturn
      13: aload_2
      14: invokeinterface #7,  1            // InterfaceMethod java/util/Iterator.hasNext:()Z
      19: ifeq          46
      22: aload_2
      23: invokeinterface #8,  1            // InterfaceMethod java/util/Iterator.next:()Ljava/lang/Object;
      28: checkcast     #9                  // class io/opencensus/tags/Tag
      31: astore_3
      32: aload_3
      33: ifnull        43
      36: iload_1
      37: aload_3
      38: invokevirtual #18                 // Method java/lang/Object.hashCode:()I
      41: iadd
      42: istore_1
      43: goto          13
      46: iload_1
      47: ireturn
}
