Compiled from "PasswordPolicyResponseControl.java"
class org.springframework.security.ldap.ppolicy.PasswordPolicyResponseControl$NetscapeDecoder implements org.springframework.security.ldap.ppolicy.PasswordPolicyResponseControl$PPolicyDecoder {
  final org.springframework.security.ldap.ppolicy.PasswordPolicyResponseControl this$0;

  private org.springframework.security.ldap.ppolicy.PasswordPolicyResponseControl$NetscapeDecoder(org.springframework.security.ldap.ppolicy.PasswordPolicyResponseControl);
    Code:
       0: aload_0
       1: aload_1
       2: putfield      #2                  // Field this$0:Lorg/springframework/security/ldap/ppolicy/PasswordPolicyResponseControl;
       5: aload_0
       6: invokespecial #3                  // Method java/lang/Object."<init>":()V
       9: return

  public void decode() throws java.io.IOException;
    Code:
       0: iconst_1
       1: newarray       int
       3: dup
       4: iconst_0
       5: iconst_0
       6: iastore
       7: astore_1
       8: new           #4                  // class org/springframework/security/ldap/ppolicy/PasswordPolicyResponseControl$NetscapeDecoder$SpecificTagDecoder
      11: dup
      12: aload_0
      13: invokespecial #5                  // Method org/springframework/security/ldap/ppolicy/PasswordPolicyResponseControl$NetscapeDecoder$SpecificTagDecoder."<init>":(Lorg/springframework/security/ldap/ppolicy/PasswordPolicyResponseControl$NetscapeDecoder;)V
      16: new           #6                  // class java/io/ByteArrayInputStream
      19: dup
      20: aload_0
      21: getfield      #2                  // Field this$0:Lorg/springframework/security/ldap/ppolicy/PasswordPolicyResponseControl;
      24: invokestatic  #7                  // Method org/springframework/security/ldap/ppolicy/PasswordPolicyResponseControl.access$100:(Lorg/springframework/security/ldap/ppolicy/PasswordPolicyResponseControl;)[B
      27: invokespecial #8                  // Method java/io/ByteArrayInputStream."<init>":([B)V
      30: aload_1
      31: invokestatic  #9                  // Method netscape/ldap/ber/stream/BERElement.getElement:(Lnetscape/ldap/ber/stream/BERTagDecoder;Ljava/io/InputStream;[I)Lnetscape/ldap/ber/stream/BERElement;
      34: checkcast     #10                 // class netscape/ldap/ber/stream/BERSequence
      37: astore_2
      38: aload_2
      39: invokevirtual #11                 // Method netscape/ldap/ber/stream/BERSequence.size:()I
      42: istore_3
      43: invokestatic  #12                 // Method org/springframework/security/ldap/ppolicy/PasswordPolicyResponseControl.access$200:()Lorg/apache/commons/logging/Log;
      46: invokeinterface #13,  1           // InterfaceMethod org/apache/commons/logging/Log.isDebugEnabled:()Z
      51: ifeq          86
      54: invokestatic  #12                 // Method org/springframework/security/ldap/ppolicy/PasswordPolicyResponseControl.access$200:()Lorg/apache/commons/logging/Log;
      57: new           #14                 // class java/lang/StringBuilder
      60: dup
      61: invokespecial #15                 // Method java/lang/StringBuilder."<init>":()V
      64: ldc           #16                 // String PasswordPolicyResponse, ASN.1 sequence has
      66: invokevirtual #17                 // Method java/lang/StringBuilder.append:(Ljava/lang/String;)Ljava/lang/StringBuilder;
      69: iload_3
      70: invokevirtual #18                 // Method java/lang/StringBuilder.append:(I)Ljava/lang/StringBuilder;
      73: ldc           #19                 // String  elements
      75: invokevirtual #17                 // Method java/lang/StringBuilder.append:(Ljava/lang/String;)Ljava/lang/StringBuilder;
      78: invokevirtual #20                 // Method java/lang/StringBuilder.toString:()Ljava/lang/String;
      81: invokeinterface #21,  2           // InterfaceMethod org/apache/commons/logging/Log.debug:(Ljava/lang/Object;)V
      86: iconst_0
      87: istore        4
      89: iload         4
      91: aload_2
      92: invokevirtual #11                 // Method netscape/ldap/ber/stream/BERSequence.size:()I
      95: if_icmpge     233
      98: aload_2
      99: iload         4
     101: invokevirtual #22                 // Method netscape/ldap/ber/stream/BERSequence.elementAt:(I)Lnetscape/ldap/ber/stream/BERElement;
     104: checkcast     #23                 // class netscape/ldap/ber/stream/BERTag
     107: astore        5
     109: aload         5
     111: invokevirtual #24                 // Method netscape/ldap/ber/stream/BERTag.getTag:()I
     114: bipush        31
     116: iand
     117: istore        6
     119: iload         6
     121: ifne          194
     124: aload         5
     126: invokevirtual #25                 // Method netscape/ldap/ber/stream/BERTag.getValue:()Lnetscape/ldap/ber/stream/BERElement;
     129: checkcast     #26                 // class netscape/ldap/ber/stream/BERChoice
     132: astore        7
     134: aload         7
     136: invokevirtual #27                 // Method netscape/ldap/ber/stream/BERChoice.getValue:()Lnetscape/ldap/ber/stream/BERElement;
     139: checkcast     #23                 // class netscape/ldap/ber/stream/BERTag
     142: astore        8
     144: aload         8
     146: invokevirtual #25                 // Method netscape/ldap/ber/stream/BERTag.getValue:()Lnetscape/ldap/ber/stream/BERElement;
     149: checkcast     #28                 // class netscape/ldap/ber/stream/BERInteger
     152: invokevirtual #29                 // Method netscape/ldap/ber/stream/BERInteger.getValue:()I
     155: istore        9
     157: aload         8
     159: invokevirtual #24                 // Method netscape/ldap/ber/stream/BERTag.getTag:()I
     162: bipush        31
     164: iand
     165: ifne          181
     168: aload_0
     169: getfield      #2                  // Field this$0:Lorg/springframework/security/ldap/ppolicy/PasswordPolicyResponseControl;
     172: iload         9
     174: invokestatic  #30                 // Method org/springframework/security/ldap/ppolicy/PasswordPolicyResponseControl.access$302:(Lorg/springframework/security/ldap/ppolicy/PasswordPolicyResponseControl;I)I
     177: pop
     178: goto          191
     181: aload_0
     182: getfield      #2                  // Field this$0:Lorg/springframework/security/ldap/ppolicy/PasswordPolicyResponseControl;
     185: iload         9
     187: invokestatic  #31                 // Method org/springframework/security/ldap/ppolicy/PasswordPolicyResponseControl.access$402:(Lorg/springframework/security/ldap/ppolicy/PasswordPolicyResponseControl;I)I
     190: pop
     191: goto          227
     194: iload         6
     196: iconst_1
     197: if_icmpne     227
     200: aload         5
     202: invokevirtual #25                 // Method netscape/ldap/ber/stream/BERTag.getValue:()Lnetscape/ldap/ber/stream/BERElement;
     205: checkcast     #32                 // class netscape/ldap/ber/stream/BERIntegral
     208: astore        7
     210: aload_0
     211: getfield      #2                  // Field this$0:Lorg/springframework/security/ldap/ppolicy/PasswordPolicyResponseControl;
     214: invokestatic  #33                 // Method org/springframework/security/ldap/ppolicy/PasswordPolicyErrorStatus.values:()[Lorg/springframework/security/ldap/ppolicy/PasswordPolicyErrorStatus;
     217: aload         7
     219: invokevirtual #34                 // Method netscape/ldap/ber/stream/BERIntegral.getValue:()I
     222: aaload
     223: invokestatic  #35                 // Method org/springframework/security/ldap/ppolicy/PasswordPolicyResponseControl.access$502:(Lorg/springframework/security/ldap/ppolicy/PasswordPolicyResponseControl;Lorg/springframework/security/ldap/ppolicy/PasswordPolicyErrorStatus;)Lorg/springframework/security/ldap/ppolicy/PasswordPolicyErrorStatus;
     226: pop
     227: iinc          4, 1
     230: goto          89
     233: return

  org.springframework.security.ldap.ppolicy.PasswordPolicyResponseControl$NetscapeDecoder(org.springframework.security.ldap.ppolicy.PasswordPolicyResponseControl, org.springframework.security.ldap.ppolicy.PasswordPolicyResponseControl$1);
    Code:
       0: aload_0
       1: aload_1
       2: invokespecial #1                  // Method "<init>":(Lorg/springframework/security/ldap/ppolicy/PasswordPolicyResponseControl;)V
       5: return
}
