Compiled from "PatternDef.java"
public class org.hibernate.validator.cfg.defs.PatternDef extends org.hibernate.validator.cfg.ConstraintDef<org.hibernate.validator.cfg.defs.PatternDef, jakarta.validation.constraints.Pattern> {
  public org.hibernate.validator.cfg.defs.PatternDef();
    Code:
       0: aload_0
       1: ldc           #1                  // class jakarta/validation/constraints/Pattern
       3: invokespecial #3                  // Method org/hibernate/validator/cfg/ConstraintDef."<init>":(Ljava/lang/Class;)V
       6: return

  public org.hibernate.validator.cfg.defs.PatternDef flags(jakarta.validation.constraints.Pattern$Flag[]);
    Code:
       0: aload_0
       1: ldc           #9                  // String flags
       3: aload_1
       4: invokevirtual #11                 // Method addParameter:(Ljava/lang/String;Ljava/lang/Object;)Lorg/hibernate/validator/cfg/AnnotationDef;
       7: pop
       8: aload_0
       9: areturn

  public org.hibernate.validator.cfg.defs.PatternDef regexp(java.lang.String);
    Code:
       0: aload_0
       1: ldc           #17                 // String regexp
       3: aload_1
       4: invokevirtual #11                 // Method addParameter:(Ljava/lang/String;Ljava/lang/Object;)Lorg/hibernate/validator/cfg/AnnotationDef;
       7: pop
       8: aload_0
       9: areturn
}
