Compiled from "OpenSslX509TrustManagerWrapper.java"
final class io.netty.handler.ssl.OpenSslX509TrustManagerWrapper {
  private static final io.netty.util.internal.logging.InternalLogger LOGGER;

  private static final io.netty.handler.ssl.OpenSslX509TrustManagerWrapper$TrustManagerWrapper WRAPPER;

  private io.netty.handler.ssl.OpenSslX509TrustManagerWrapper();
    Code:
       0: aload_0
       1: invokespecial #2                  // Method java/lang/Object."<init>":()V
       4: return

  static javax.net.ssl.X509TrustManager wrapIfNeeded(javax.net.ssl.X509TrustManager);
    Code:
       0: getstatic     #3                  // Field WRAPPER:Lio/netty/handler/ssl/OpenSslX509TrustManagerWrapper$TrustManagerWrapper;
       3: aload_0
       4: invokeinterface #4,  2            // InterfaceMethod io/netty/handler/ssl/OpenSslX509TrustManagerWrapper$TrustManagerWrapper.wrapIfNeeded:(Ljavax/net/ssl/X509TrustManager;)Ljavax/net/ssl/X509TrustManager;
       9: areturn

  private static javax.net.ssl.SSLContext newSSLContext() throws java.security.NoSuchAlgorithmException, java.security.NoSuchProviderException;
    Code:
       0: ldc           #5                  // String TLS
       2: ldc           #6                  // String SunJSSE
       4: invokestatic  #7                  // Method javax/net/ssl/SSLContext.getInstance:(Ljava/lang/String;Ljava/lang/String;)Ljavax/net/ssl/SSLContext;
       7: areturn

  static javax.net.ssl.SSLContext access$000() throws java.security.NoSuchAlgorithmException, java.security.NoSuchProviderException;
    Code:
       0: invokestatic  #1                  // Method newSSLContext:()Ljavax/net/ssl/SSLContext;
       3: areturn

  static {};
    Code:
       0: ldc           #8                  // class io/netty/handler/ssl/OpenSslX509TrustManagerWrapper
       2: invokestatic  #9                  // Method io/netty/util/internal/logging/InternalLoggerFactory.getInstance:(Ljava/lang/Class;)Lio/netty/util/internal/logging/InternalLogger;
       5: putstatic     #10                 // Field LOGGER:Lio/netty/util/internal/logging/InternalLogger;
       8: new           #11                 // class io/netty/handler/ssl/OpenSslX509TrustManagerWrapper$1
      11: dup
      12: invokespecial #12                 // Method io/netty/handler/ssl/OpenSslX509TrustManagerWrapper$1."<init>":()V
      15: astore_0
      16: aconst_null
      17: astore_1
      18: invokestatic  #13                 // Method io/netty/util/internal/PlatformDependent.getUnsafeUnavailabilityCause:()Ljava/lang/Throwable;
      21: astore_2
      22: aload_2
      23: ifnonnull     130
      26: invokestatic  #1                  // Method newSSLContext:()Ljavax/net/ssl/SSLContext;
      29: astore_3
      30: aload_3
      31: aconst_null
      32: iconst_1
      33: anewarray     #14                 // class javax/net/ssl/TrustManager
      36: dup
      37: iconst_0
      38: new           #15                 // class io/netty/handler/ssl/OpenSslX509TrustManagerWrapper$2
      41: dup
      42: invokespecial #16                 // Method io/netty/handler/ssl/OpenSslX509TrustManagerWrapper$2."<init>":()V
      45: aastore
      46: aconst_null
      47: invokevirtual #17                 // Method javax/net/ssl/SSLContext.init:([Ljavax/net/ssl/KeyManager;[Ljavax/net/ssl/TrustManager;Ljava/security/SecureRandom;)V
      50: goto          60
      53: astore        4
      55: aconst_null
      56: astore_3
      57: aload         4
      59: astore_1
      60: aload_1
      61: ifnull        78
      64: getstatic     #10                 // Field LOGGER:Lio/netty/util/internal/logging/InternalLogger;
      67: ldc           #19                 // String Unable to access wrapped TrustManager
      69: aload_1
      70: invokeinterface #20,  3           // InterfaceMethod io/netty/util/internal/logging/InternalLogger.debug:(Ljava/lang/String;Ljava/lang/Throwable;)V
      75: goto          127
      78: aload_3
      79: astore        4
      81: new           #21                 // class io/netty/handler/ssl/OpenSslX509TrustManagerWrapper$3
      84: dup
      85: aload         4
      87: invokespecial #22                 // Method io/netty/handler/ssl/OpenSslX509TrustManagerWrapper$3."<init>":(Ljavax/net/ssl/SSLContext;)V
      90: invokestatic  #23                 // Method java/security/AccessController.doPrivileged:(Ljava/security/PrivilegedAction;)Ljava/lang/Object;
      93: astore        5
      95: aload         5
      97: instanceof    #18                 // class java/lang/Throwable
     100: ifeq          121
     103: getstatic     #10                 // Field LOGGER:Lio/netty/util/internal/logging/InternalLogger;
     106: ldc           #19                 // String Unable to access wrapped TrustManager
     108: aload         5
     110: checkcast     #18                 // class java/lang/Throwable
     113: invokeinterface #20,  3           // InterfaceMethod io/netty/util/internal/logging/InternalLogger.debug:(Ljava/lang/String;Ljava/lang/Throwable;)V
     118: goto          127
     121: aload         5
     123: checkcast     #24                 // class io/netty/handler/ssl/OpenSslX509TrustManagerWrapper$TrustManagerWrapper
     126: astore_0
     127: goto          141
     130: getstatic     #10                 // Field LOGGER:Lio/netty/util/internal/logging/InternalLogger;
     133: ldc           #19                 // String Unable to access wrapped TrustManager
     135: aload_1
     136: invokeinterface #20,  3           // InterfaceMethod io/netty/util/internal/logging/InternalLogger.debug:(Ljava/lang/String;Ljava/lang/Throwable;)V
     141: aload_0
     142: putstatic     #3                  // Field WRAPPER:Lio/netty/handler/ssl/OpenSslX509TrustManagerWrapper$TrustManagerWrapper;
     145: return
    Exception table:
       from    to  target type
          26    50    53   Class java/lang/Throwable
}
