Compiled from "ELEvaluator.java"
class org.apache.taglibs.standard.lang.jstl.ELEvaluator$1 extends java.util.LinkedHashMap {
  final int val$maxSize;

  final org.apache.taglibs.standard.lang.jstl.ELEvaluator this$0;

  org.apache.taglibs.standard.lang.jstl.ELEvaluator$1(org.apache.taglibs.standard.lang.jstl.ELEvaluator, int);
    Code:
       0: aload_0
       1: aload_1
       2: putfield      #1                  // Field this$0:Lorg/apache/taglibs/standard/lang/jstl/ELEvaluator;
       5: aload_0
       6: iload_2
       7: putfield      #2                  // Field val$maxSize:I
      10: aload_0
      11: invokespecial #3                  // Method java/util/LinkedHashMap."<init>":()V
      14: return

  protected boolean removeEldestEntry(java.util.Map$Entry);
    Code:
       0: aload_0
       1: invokevirtual #4                  // Method size:()I
       4: aload_0
       5: getfield      #2                  // Field val$maxSize:I
       8: if_icmple     15
      11: iconst_1
      12: goto          16
      15: iconst_0
      16: ireturn
}
