Compiled from "ExpressionString.java"
public class org.apache.taglibs.standard.lang.jstl.ExpressionString {
  java.lang.Object[] mElements;

  public java.lang.Object[] getElements();
    Code:
       0: aload_0
       1: getfield      #1                  // Field mElements:[Ljava/lang/Object;
       4: areturn

  public void setElements(java.lang.Object[]);
    Code:
       0: aload_0
       1: aload_1
       2: putfield      #1                  // Field mElements:[Ljava/lang/Object;
       5: return

  public org.apache.taglibs.standard.lang.jstl.ExpressionString(java.lang.Object[]);
    Code:
       0: aload_0
       1: invokespecial #2                  // Method java/lang/Object."<init>":()V
       4: aload_0
       5: aload_1
       6: putfield      #1                  // Field mElements:[Ljava/lang/Object;
       9: return

  public java.lang.String evaluate(java.lang.Object, org.apache.taglibs.standard.lang.jstl.VariableResolver, java.util.Map, java.lang.String, org.apache.taglibs.standard.lang.jstl.Logger) throws org.apache.taglibs.standard.lang.jstl.ELException;
    Code:
       0: new           #3                  // class java/lang/StringBuffer
       3: dup
       4: invokespecial #4                  // Method java/lang/StringBuffer."<init>":()V
       7: astore        6
       9: iconst_0
      10: istore        7
      12: iload         7
      14: aload_0
      15: getfield      #1                  // Field mElements:[Ljava/lang/Object;
      18: arraylength
      19: if_icmpge     100
      22: aload_0
      23: getfield      #1                  // Field mElements:[Ljava/lang/Object;
      26: iload         7
      28: aaload
      29: astore        8
      31: aload         8
      33: instanceof    #5                  // class java/lang/String
      36: ifeq          53
      39: aload         6
      41: aload         8
      43: checkcast     #5                  // class java/lang/String
      46: invokevirtual #6                  // Method java/lang/StringBuffer.append:(Ljava/lang/String;)Ljava/lang/StringBuffer;
      49: pop
      50: goto          94
      53: aload         8
      55: instanceof    #7                  // class org/apache/taglibs/standard/lang/jstl/Expression
      58: ifeq          94
      61: aload         8
      63: checkcast     #7                  // class org/apache/taglibs/standard/lang/jstl/Expression
      66: aload_1
      67: aload_2
      68: aload_3
      69: aload         4
      71: aload         5
      73: invokevirtual #8                  // Method org/apache/taglibs/standard/lang/jstl/Expression.evaluate:(Ljava/lang/Object;Lorg/apache/taglibs/standard/lang/jstl/VariableResolver;Ljava/util/Map;Ljava/lang/String;Lorg/apache/taglibs/standard/lang/jstl/Logger;)Ljava/lang/Object;
      76: astore        9
      78: aload         9
      80: ifnull        94
      83: aload         6
      85: aload         9
      87: invokevirtual #9                  // Method java/lang/Object.toString:()Ljava/lang/String;
      90: invokevirtual #6                  // Method java/lang/StringBuffer.append:(Ljava/lang/String;)Ljava/lang/StringBuffer;
      93: pop
      94: iinc          7, 1
      97: goto          12
     100: aload         6
     102: invokevirtual #10                 // Method java/lang/StringBuffer.toString:()Ljava/lang/String;
     105: areturn

  public java.lang.String getExpressionString();
    Code:
       0: new           #3                  // class java/lang/StringBuffer
       3: dup
       4: invokespecial #4                  // Method java/lang/StringBuffer."<init>":()V
       7: astore_1
       8: iconst_0
       9: istore_2
      10: iload_2
      11: aload_0
      12: getfield      #1                  // Field mElements:[Ljava/lang/Object;
      15: arraylength
      16: if_icmpge     84
      19: aload_0
      20: getfield      #1                  // Field mElements:[Ljava/lang/Object;
      23: iload_2
      24: aaload
      25: astore_3
      26: aload_3
      27: instanceof    #5                  // class java/lang/String
      30: ifeq          45
      33: aload_1
      34: aload_3
      35: checkcast     #5                  // class java/lang/String
      38: invokevirtual #6                  // Method java/lang/StringBuffer.append:(Ljava/lang/String;)Ljava/lang/StringBuffer;
      41: pop
      42: goto          78
      45: aload_3
      46: instanceof    #7                  // class org/apache/taglibs/standard/lang/jstl/Expression
      49: ifeq          78
      52: aload_1
      53: ldc           #11                 // String ${
      55: invokevirtual #6                  // Method java/lang/StringBuffer.append:(Ljava/lang/String;)Ljava/lang/StringBuffer;
      58: pop
      59: aload_1
      60: aload_3
      61: checkcast     #7                  // class org/apache/taglibs/standard/lang/jstl/Expression
      64: invokevirtual #12                 // Method org/apache/taglibs/standard/lang/jstl/Expression.getExpressionString:()Ljava/lang/String;
      67: invokevirtual #6                  // Method java/lang/StringBuffer.append:(Ljava/lang/String;)Ljava/lang/StringBuffer;
      70: pop
      71: aload_1
      72: ldc           #13                 // String }
      74: invokevirtual #6                  // Method java/lang/StringBuffer.append:(Ljava/lang/String;)Ljava/lang/StringBuffer;
      77: pop
      78: iinc          2, 1
      81: goto          10
      84: aload_1
      85: invokevirtual #10                 // Method java/lang/StringBuffer.toString:()Ljava/lang/String;
      88: areturn
}
