Compiled from "Serialization.scala"
public class akka.serialization.Serialization$Settings {
  private final com.typesafe.config.Config config;

  private final scala.collection.immutable.Map<java.lang.String, java.lang.String> Serializers;

  private final scala.collection.immutable.Map<java.lang.String, java.lang.String> SerializationBindings;

  public com.typesafe.config.Config config();
    Code:
       0: aload_0
       1: getfield      #14                 // Field config:Lcom/typesafe/config/Config;
       4: areturn

  public scala.collection.immutable.Map<java.lang.String, java.lang.String> Serializers();
    Code:
       0: aload_0
       1: getfield      #19                 // Field Serializers:Lscala/collection/immutable/Map;
       4: areturn

  public scala.collection.immutable.Map<java.lang.String, java.lang.String> SerializationBindings();
    Code:
       0: aload_0
       1: getfield      #21                 // Field SerializationBindings:Lscala/collection/immutable/Map;
       4: areturn

  private final scala.collection.immutable.Map<java.lang.String, java.lang.String> configToMap(com.typesafe.config.Config);
    Code:
       0: getstatic     #29                 // Field scala/collection/JavaConverters$.MODULE$:Lscala/collection/JavaConverters$;
       3: aload_1
       4: invokeinterface #35,  1           // InterfaceMethod com/typesafe/config/Config.root:()Lcom/typesafe/config/ConfigObject;
       9: invokeinterface #41,  1           // InterfaceMethod com/typesafe/config/ConfigObject.unwrapped:()Ljava/util/Map;
      14: invokevirtual #45                 // Method scala/collection/JavaConverters$.mapAsScalaMapConverter:(Ljava/util/Map;)Lscala/collection/convert/Decorators$AsScala;
      17: invokevirtual #51                 // Method scala/collection/convert/Decorators$AsScala.asScala:()Ljava/lang/Object;
      20: checkcast     #53                 // class scala/collection/TraversableOnce
      23: getstatic     #58                 // Field scala/Predef$.MODULE$:Lscala/Predef$;
      26: invokevirtual #62                 // Method scala/Predef$.$conforms:()Lscala/Predef$$less$colon$less;
      29: invokeinterface #66,  2           // InterfaceMethod scala/collection/TraversableOnce.toMap:(Lscala/Predef$$less$colon$less;)Lscala/collection/immutable/Map;
      34: new           #68                 // class akka/serialization/Serialization$Settings$$anonfun$configToMap$1
      37: dup
      38: aload_0
      39: invokespecial #72                 // Method akka/serialization/Serialization$Settings$$anonfun$configToMap$1."<init>":(Lakka/serialization/Serialization$Settings;)V
      42: getstatic     #77                 // Field scala/collection/immutable/Map$.MODULE$:Lscala/collection/immutable/Map$;
      45: invokevirtual #81                 // Method scala/collection/immutable/Map$.canBuildFrom:()Lscala/collection/generic/CanBuildFrom;
      48: invokeinterface #87,  3           // InterfaceMethod scala/collection/immutable/Map.map:(Lscala/Function1;Lscala/collection/generic/CanBuildFrom;)Ljava/lang/Object;
      53: checkcast     #83                 // class scala/collection/immutable/Map
      56: areturn

  public akka.serialization.Serialization$Settings(com.typesafe.config.Config);
    Code:
       0: aload_0
       1: aload_1
       2: putfield      #14                 // Field config:Lcom/typesafe/config/Config;
       5: aload_0
       6: invokespecial #92                 // Method java/lang/Object."<init>":()V
       9: aload_0
      10: aload_0
      11: aload_1
      12: ldc           #94                 // String akka.actor.serializers
      14: invokeinterface #98,  2           // InterfaceMethod com/typesafe/config/Config.getConfig:(Ljava/lang/String;)Lcom/typesafe/config/Config;
      19: invokespecial #100                // Method configToMap:(Lcom/typesafe/config/Config;)Lscala/collection/immutable/Map;
      22: putfield      #19                 // Field Serializers:Lscala/collection/immutable/Map;
      25: aload_0
      26: aload_1
      27: ldc           #102                // String akka.actor.serialization-bindings
      29: invokeinterface #98,  2           // InterfaceMethod com/typesafe/config/Config.getConfig:(Ljava/lang/String;)Lcom/typesafe/config/Config;
      34: astore_2
      35: aload_1
      36: ldc           #104                // String akka.actor.enable-additional-serialization-bindings
      38: invokeinterface #108,  2          // InterfaceMethod com/typesafe/config/Config.getBoolean:(Ljava/lang/String;)Z
      43: ifne          68
      46: aload_1
      47: ldc           #110                // String akka.remote.artery.enabled
      49: invokeinterface #113,  2          // InterfaceMethod com/typesafe/config/Config.hasPath:(Ljava/lang/String;)Z
      54: ifeq          85
      57: aload_1
      58: ldc           #110                // String akka.remote.artery.enabled
      60: invokeinterface #108,  2          // InterfaceMethod com/typesafe/config/Config.getBoolean:(Ljava/lang/String;)Z
      65: ifeq          85
      68: aload_2
      69: aload_1
      70: ldc           #115                // String akka.actor.additional-serialization-bindings
      72: invokeinterface #98,  2           // InterfaceMethod com/typesafe/config/Config.getConfig:(Ljava/lang/String;)Lcom/typesafe/config/Config;
      77: invokeinterface #119,  2          // InterfaceMethod com/typesafe/config/Config.withFallback:(Lcom/typesafe/config/ConfigMergeable;)Lcom/typesafe/config/Config;
      82: goto          86
      85: aload_2
      86: astore_3
      87: aload_0
      88: aload_3
      89: invokespecial #100                // Method configToMap:(Lcom/typesafe/config/Config;)Lscala/collection/immutable/Map;
      92: putfield      #21                 // Field SerializationBindings:Lscala/collection/immutable/Map;
      95: return
}
