Compiled from "DualTreeBidiMap.java"
public class org.apache.commons.collections4.bidimap.DualTreeBidiMap$ViewMap<K, V> extends org.apache.commons.collections4.map.AbstractSortedMapDecorator<K, V> {
  protected org.apache.commons.collections4.bidimap.DualTreeBidiMap$ViewMap(org.apache.commons.collections4.bidimap.DualTreeBidiMap<K, V>, java.util.SortedMap<K, V>);
    Code:
       0: aload_0
       1: new           #1                  // class org/apache/commons/collections4/bidimap/DualTreeBidiMap
       4: dup
       5: aload_2
       6: aload_1
       7: getfield      #2                  // Field org/apache/commons/collections4/bidimap/DualTreeBidiMap.reverseMap:Ljava/util/Map;
      10: aload_1
      11: getfield      #3                  // Field org/apache/commons/collections4/bidimap/DualTreeBidiMap.inverseBidiMap:Lorg/apache/commons/collections4/BidiMap;
      14: invokespecial #4                  // Method org/apache/commons/collections4/bidimap/DualTreeBidiMap."<init>":(Ljava/util/Map;Ljava/util/Map;Lorg/apache/commons/collections4/BidiMap;)V
      17: invokespecial #5                  // Method org/apache/commons/collections4/map/AbstractSortedMapDecorator."<init>":(Ljava/util/SortedMap;)V
      20: return

  public boolean containsValue(java.lang.Object);
    Code:
       0: aload_0
       1: invokevirtual #6                  // Method decorated:()Lorg/apache/commons/collections4/bidimap/DualTreeBidiMap;
       4: getfield      #7                  // Field org/apache/commons/collections4/bidimap/DualTreeBidiMap.normalMap:Ljava/util/Map;
       7: aload_1
       8: invokeinterface #8,  2            // InterfaceMethod java/util/Map.containsValue:(Ljava/lang/Object;)Z
      13: ireturn

  public void clear();
    Code:
       0: aload_0
       1: invokevirtual #9                  // Method keySet:()Ljava/util/Set;
       4: invokeinterface #10,  1           // InterfaceMethod java/util/Set.iterator:()Ljava/util/Iterator;
       9: astore_1
      10: aload_1
      11: invokeinterface #11,  1           // InterfaceMethod java/util/Iterator.hasNext:()Z
      16: ifeq          35
      19: aload_1
      20: invokeinterface #12,  1           // InterfaceMethod java/util/Iterator.next:()Ljava/lang/Object;
      25: pop
      26: aload_1
      27: invokeinterface #13,  1           // InterfaceMethod java/util/Iterator.remove:()V
      32: goto          10
      35: return

  public java.util.SortedMap<K, V> headMap(K);
    Code:
       0: new           #14                 // class org/apache/commons/collections4/bidimap/DualTreeBidiMap$ViewMap
       3: dup
       4: aload_0
       5: invokevirtual #6                  // Method decorated:()Lorg/apache/commons/collections4/bidimap/DualTreeBidiMap;
       8: aload_0
       9: aload_1
      10: invokespecial #15                 // Method org/apache/commons/collections4/map/AbstractSortedMapDecorator.headMap:(Ljava/lang/Object;)Ljava/util/SortedMap;
      13: invokespecial #16                 // Method "<init>":(Lorg/apache/commons/collections4/bidimap/DualTreeBidiMap;Ljava/util/SortedMap;)V
      16: areturn

  public java.util.SortedMap<K, V> tailMap(K);
    Code:
       0: new           #14                 // class org/apache/commons/collections4/bidimap/DualTreeBidiMap$ViewMap
       3: dup
       4: aload_0
       5: invokevirtual #6                  // Method decorated:()Lorg/apache/commons/collections4/bidimap/DualTreeBidiMap;
       8: aload_0
       9: aload_1
      10: invokespecial #17                 // Method org/apache/commons/collections4/map/AbstractSortedMapDecorator.tailMap:(Ljava/lang/Object;)Ljava/util/SortedMap;
      13: invokespecial #16                 // Method "<init>":(Lorg/apache/commons/collections4/bidimap/DualTreeBidiMap;Ljava/util/SortedMap;)V
      16: areturn

  public java.util.SortedMap<K, V> subMap(K, K);
    Code:
       0: new           #14                 // class org/apache/commons/collections4/bidimap/DualTreeBidiMap$ViewMap
       3: dup
       4: aload_0
       5: invokevirtual #6                  // Method decorated:()Lorg/apache/commons/collections4/bidimap/DualTreeBidiMap;
       8: aload_0
       9: aload_1
      10: aload_2
      11: invokespecial #18                 // Method org/apache/commons/collections4/map/AbstractSortedMapDecorator.subMap:(Ljava/lang/Object;Ljava/lang/Object;)Ljava/util/SortedMap;
      14: invokespecial #16                 // Method "<init>":(Lorg/apache/commons/collections4/bidimap/DualTreeBidiMap;Ljava/util/SortedMap;)V
      17: areturn

  protected org.apache.commons.collections4.bidimap.DualTreeBidiMap<K, V> decorated();
    Code:
       0: aload_0
       1: invokespecial #19                 // Method org/apache/commons/collections4/map/AbstractSortedMapDecorator.decorated:()Ljava/util/SortedMap;
       4: checkcast     #1                  // class org/apache/commons/collections4/bidimap/DualTreeBidiMap
       7: areturn

  public K previousKey(K);
    Code:
       0: aload_0
       1: invokevirtual #6                  // Method decorated:()Lorg/apache/commons/collections4/bidimap/DualTreeBidiMap;
       4: aload_1
       5: invokevirtual #20                 // Method org/apache/commons/collections4/bidimap/DualTreeBidiMap.previousKey:(Ljava/lang/Object;)Ljava/lang/Object;
       8: areturn

  public K nextKey(K);
    Code:
       0: aload_0
       1: invokevirtual #6                  // Method decorated:()Lorg/apache/commons/collections4/bidimap/DualTreeBidiMap;
       4: aload_1
       5: invokevirtual #21                 // Method org/apache/commons/collections4/bidimap/DualTreeBidiMap.nextKey:(Ljava/lang/Object;)Ljava/lang/Object;
       8: areturn

  protected java.util.SortedMap decorated();
    Code:
       0: aload_0
       1: invokevirtual #6                  // Method decorated:()Lorg/apache/commons/collections4/bidimap/DualTreeBidiMap;
       4: areturn

  protected java.util.Map decorated();
    Code:
       0: aload_0
       1: invokevirtual #6                  // Method decorated:()Lorg/apache/commons/collections4/bidimap/DualTreeBidiMap;
       4: areturn
}
