Compiled from "Text.java"
class javafx.scene.text.Text$TextAttribute$4 extends javafx.css.StyleableObjectProperty<javafx.scene.text.TextAlignment> {
  final javafx.scene.text.Text$TextAttribute this$1;

  javafx.scene.text.Text$TextAttribute$4(javafx.scene.text.Text$TextAttribute, javafx.scene.text.TextAlignment);
    Code:
       0: aload_0
       1: aload_1
       2: putfield      #1                  // Field this$1:Ljavafx/scene/text/Text$TextAttribute;
       5: aload_0
       6: aload_2
       7: invokespecial #2                  // Method javafx/css/StyleableObjectProperty."<init>":(Ljava/lang/Object;)V
      10: return

  public java.lang.Object getBean();
    Code:
       0: aload_0
       1: getfield      #1                  // Field this$1:Ljavafx/scene/text/Text$TextAttribute;
       4: getfield      #3                  // Field javafx/scene/text/Text$TextAttribute.this$0:Ljavafx/scene/text/Text;
       7: areturn

  public java.lang.String getName();
    Code:
       0: ldc           #4                  // String textAlignment
       2: areturn

  public javafx.css.CssMetaData getCssMetaData();
    Code:
       0: invokestatic  #5                  // Method javafx/scene/text/Text$StyleableProperties.access$3900:()Ljavafx/css/CssMetaData;
       3: areturn

  public void invalidated();
    Code:
       0: aload_0
       1: getfield      #1                  // Field this$1:Ljavafx/scene/text/Text$TextAttribute;
       4: getfield      #3                  // Field javafx/scene/text/Text$TextAttribute.this$0:Ljavafx/scene/text/Text;
       7: invokestatic  #6                  // Method javafx/scene/text/Text.access$1600:(Ljavafx/scene/text/Text;)Z
      10: ifne          63
      13: aload_0
      14: invokevirtual #7                  // Method get:()Ljava/lang/Object;
      17: checkcast     #8                  // class javafx/scene/text/TextAlignment
      20: astore_1
      21: aload_1
      22: ifnonnull     29
      25: invokestatic  #9                  // Method javafx/scene/text/Text.access$3800:()Ljavafx/scene/text/TextAlignment;
      28: astore_1
      29: aload_0
      30: getfield      #1                  // Field this$1:Ljavafx/scene/text/Text$TextAttribute;
      33: getfield      #3                  // Field javafx/scene/text/Text$TextAttribute.this$0:Ljavafx/scene/text/Text;
      36: invokestatic  #10                 // Method javafx/scene/text/Text.access$1300:(Ljavafx/scene/text/Text;)Lcom/sun/javafx/scene/text/TextLayout;
      39: astore_2
      40: aload_2
      41: aload_1
      42: invokevirtual #11                 // Method javafx/scene/text/TextAlignment.ordinal:()I
      45: invokeinterface #12,  2           // InterfaceMethod com/sun/javafx/scene/text/TextLayout.setAlignment:(I)Z
      50: ifeq          63
      53: aload_0
      54: getfield      #1                  // Field this$1:Ljavafx/scene/text/Text$TextAttribute;
      57: getfield      #3                  // Field javafx/scene/text/Text$TextAttribute.this$0:Ljavafx/scene/text/Text;
      60: invokestatic  #13                 // Method javafx/scene/text/Text.access$1500:(Ljavafx/scene/text/Text;)V
      63: return
}
