Compiled from "Text.java"
class javafx.scene.text.Text$4 extends javafx.beans.property.DoublePropertyBase {
  final javafx.scene.text.Text this$0;

  javafx.scene.text.Text$4(javafx.scene.text.Text);
    Code:
       0: aload_0
       1: aload_1
       2: putfield      #1                  // Field this$0:Ljavafx/scene/text/Text;
       5: aload_0
       6: invokespecial #2                  // Method javafx/beans/property/DoublePropertyBase."<init>":()V
       9: return

  public java.lang.Object getBean();
    Code:
       0: aload_0
       1: getfield      #1                  // Field this$0:Ljavafx/scene/text/Text;
       4: areturn

  public java.lang.String getName();
    Code:
       0: ldc           #3                  // String x
       2: areturn

  public void invalidated();
    Code:
       0: aload_0
       1: getfield      #1                  // Field this$0:Ljavafx/scene/text/Text;
       4: invokestatic  #4                  // Method com/sun/javafx/scene/NodeHelper.geomChanged:(Ljavafx/scene/Node;)V
       7: return
}
