Compiled from "InternalState.java"
class org.apache.http.impl.nio.client.InternalState {
  private final long id;

  private final org.apache.http.nio.protocol.HttpAsyncRequestProducer requestProducer;

  private final org.apache.http.nio.protocol.HttpAsyncResponseConsumer<?> responseConsumer;

  private final org.apache.http.client.protocol.HttpClientContext localContext;

  private org.apache.http.client.methods.HttpRequestWrapper mainRequest;

  private org.apache.http.HttpResponse finalResponse;

  private java.nio.ByteBuffer tmpbuf;

  private boolean requestContentProduced;

  private int execCount;

  private int redirectCount;

  private org.apache.http.client.methods.HttpUriRequest redirect;

  public org.apache.http.impl.nio.client.InternalState(long, org.apache.http.nio.protocol.HttpAsyncRequestProducer, org.apache.http.nio.protocol.HttpAsyncResponseConsumer<?>, org.apache.http.client.protocol.HttpClientContext);
    Code:
       0: aload_0
       1: invokespecial #1                  // Method java/lang/Object."<init>":()V
       4: aload_0
       5: lload_1
       6: putfield      #2                  // Field id:J
       9: aload_0
      10: aload_3
      11: putfield      #3                  // Field requestProducer:Lorg/apache/http/nio/protocol/HttpAsyncRequestProducer;
      14: aload_0
      15: aload         4
      17: putfield      #4                  // Field responseConsumer:Lorg/apache/http/nio/protocol/HttpAsyncResponseConsumer;
      20: aload_0
      21: aload         5
      23: putfield      #5                  // Field localContext:Lorg/apache/http/client/protocol/HttpClientContext;
      26: return

  public long getId();
    Code:
       0: aload_0
       1: getfield      #2                  // Field id:J
       4: lreturn

  public org.apache.http.nio.protocol.HttpAsyncRequestProducer getRequestProducer();
    Code:
       0: aload_0
       1: getfield      #3                  // Field requestProducer:Lorg/apache/http/nio/protocol/HttpAsyncRequestProducer;
       4: areturn

  public org.apache.http.nio.protocol.HttpAsyncResponseConsumer<?> getResponseConsumer();
    Code:
       0: aload_0
       1: getfield      #4                  // Field responseConsumer:Lorg/apache/http/nio/protocol/HttpAsyncResponseConsumer;
       4: areturn

  public org.apache.http.client.protocol.HttpClientContext getLocalContext();
    Code:
       0: aload_0
       1: getfield      #5                  // Field localContext:Lorg/apache/http/client/protocol/HttpClientContext;
       4: areturn

  public org.apache.http.client.methods.HttpRequestWrapper getMainRequest();
    Code:
       0: aload_0
       1: getfield      #6                  // Field mainRequest:Lorg/apache/http/client/methods/HttpRequestWrapper;
       4: areturn

  public void setMainRequest(org.apache.http.client.methods.HttpRequestWrapper);
    Code:
       0: aload_0
       1: aload_1
       2: putfield      #6                  // Field mainRequest:Lorg/apache/http/client/methods/HttpRequestWrapper;
       5: return

  public org.apache.http.HttpResponse getFinalResponse();
    Code:
       0: aload_0
       1: getfield      #7                  // Field finalResponse:Lorg/apache/http/HttpResponse;
       4: areturn

  public void setFinalResponse(org.apache.http.HttpResponse);
    Code:
       0: aload_0
       1: aload_1
       2: putfield      #7                  // Field finalResponse:Lorg/apache/http/HttpResponse;
       5: return

  public java.nio.ByteBuffer getTmpbuf();
    Code:
       0: aload_0
       1: getfield      #8                  // Field tmpbuf:Ljava/nio/ByteBuffer;
       4: ifnonnull     17
       7: aload_0
       8: sipush        4096
      11: invokestatic  #9                  // Method java/nio/ByteBuffer.allocate:(I)Ljava/nio/ByteBuffer;
      14: putfield      #8                  // Field tmpbuf:Ljava/nio/ByteBuffer;
      17: aload_0
      18: getfield      #8                  // Field tmpbuf:Ljava/nio/ByteBuffer;
      21: areturn

  public boolean isRequestContentProduced();
    Code:
       0: aload_0
       1: getfield      #10                 // Field requestContentProduced:Z
       4: ireturn

  public void setRequestContentProduced();
    Code:
       0: aload_0
       1: iconst_1
       2: putfield      #10                 // Field requestContentProduced:Z
       5: return

  public int getExecCount();
    Code:
       0: aload_0
       1: getfield      #11                 // Field execCount:I
       4: ireturn

  public void incrementExecCount();
    Code:
       0: aload_0
       1: dup
       2: getfield      #11                 // Field execCount:I
       5: iconst_1
       6: iadd
       7: putfield      #11                 // Field execCount:I
      10: return

  public int getRedirectCount();
    Code:
       0: aload_0
       1: getfield      #12                 // Field redirectCount:I
       4: ireturn

  public void incrementRedirectCount();
    Code:
       0: aload_0
       1: dup
       2: getfield      #12                 // Field redirectCount:I
       5: iconst_1
       6: iadd
       7: putfield      #12                 // Field redirectCount:I
      10: return

  public org.apache.http.client.methods.HttpUriRequest getRedirect();
    Code:
       0: aload_0
       1: getfield      #13                 // Field redirect:Lorg/apache/http/client/methods/HttpUriRequest;
       4: areturn

  public void setRedirect(org.apache.http.client.methods.HttpUriRequest);
    Code:
       0: aload_0
       1: aload_1
       2: putfield      #13                 // Field redirect:Lorg/apache/http/client/methods/HttpUriRequest;
       5: return

  public java.lang.String toString();
    Code:
       0: aload_0
       1: getfield      #2                  // Field id:J
       4: invokestatic  #14                 // Method java/lang/Long.toString:(J)Ljava/lang/String;
       7: areturn
}
