Compiled from "AbstractActiveOntologyViewComponent.java"
public abstract class org.protege.editor.owl.ui.view.AbstractActiveOntologyViewComponent extends org.protege.editor.owl.ui.view.AbstractOWLViewComponent {
  private org.protege.editor.owl.model.event.OWLModelManagerListener owlModelManagerListener;

  private org.semanticweb.owlapi.model.OWLOntologyChangeListener owlOntologyChangeListener;

  private java.awt.event.HierarchyListener hierarchyListener;

  private boolean updateView;

  public org.protege.editor.owl.ui.view.AbstractActiveOntologyViewComponent();
    Code:
       0: aload_0
       1: invokespecial #1                  // Method org/protege/editor/owl/ui/view/AbstractOWLViewComponent."<init>":()V
       4: return

  protected final void initialiseOWLView() throws java.lang.Exception;
    Code:
       0: aload_0
       1: aload_0
       2: invokedynamic #2,  0              // InvokeDynamic #0:handleChange:(Lorg/protege/editor/owl/ui/view/AbstractActiveOntologyViewComponent;)Lorg/protege/editor/owl/model/event/OWLModelManagerListener;
       7: putfield      #3                  // Field owlModelManagerListener:Lorg/protege/editor/owl/model/event/OWLModelManagerListener;
      10: aload_0
      11: invokevirtual #4                  // Method getOWLModelManager:()Lorg/protege/editor/owl/model/OWLModelManager;
      14: aload_0
      15: getfield      #3                  // Field owlModelManagerListener:Lorg/protege/editor/owl/model/event/OWLModelManagerListener;
      18: invokeinterface #5,  2            // InterfaceMethod org/protege/editor/owl/model/OWLModelManager.addListener:(Lorg/protege/editor/owl/model/event/OWLModelManagerListener;)V
      23: aload_0
      24: aload_0
      25: invokedynamic #6,  0              // InvokeDynamic #1:ontologiesChanged:(Lorg/protege/editor/owl/ui/view/AbstractActiveOntologyViewComponent;)Lorg/semanticweb/owlapi/model/OWLOntologyChangeListener;
      30: putfield      #7                  // Field owlOntologyChangeListener:Lorg/semanticweb/owlapi/model/OWLOntologyChangeListener;
      33: aload_0
      34: invokevirtual #4                  // Method getOWLModelManager:()Lorg/protege/editor/owl/model/OWLModelManager;
      37: aload_0
      38: getfield      #7                  // Field owlOntologyChangeListener:Lorg/semanticweb/owlapi/model/OWLOntologyChangeListener;
      41: invokeinterface #8,  2            // InterfaceMethod org/protege/editor/owl/model/OWLModelManager.addOntologyChangeListener:(Lorg/semanticweb/owlapi/model/OWLOntologyChangeListener;)V
      46: aload_0
      47: aload_0
      48: invokedynamic #9,  0              // InvokeDynamic #2:hierarchyChanged:(Lorg/protege/editor/owl/ui/view/AbstractActiveOntologyViewComponent;)Ljava/awt/event/HierarchyListener;
      53: putfield      #10                 // Field hierarchyListener:Ljava/awt/event/HierarchyListener;
      56: aload_0
      57: aload_0
      58: getfield      #10                 // Field hierarchyListener:Ljava/awt/event/HierarchyListener;
      61: invokevirtual #11                 // Method addHierarchyListener:(Ljava/awt/event/HierarchyListener;)V
      64: aload_0
      65: invokevirtual #12                 // Method initialiseOntologyView:()V
      68: return

  protected abstract void initialiseOntologyView() throws java.lang.Exception;

  protected final void disposeOWLView();
    Code:
       0: aload_0
       1: invokevirtual #4                  // Method getOWLModelManager:()Lorg/protege/editor/owl/model/OWLModelManager;
       4: aload_0
       5: getfield      #3                  // Field owlModelManagerListener:Lorg/protege/editor/owl/model/event/OWLModelManagerListener;
       8: invokeinterface #13,  2           // InterfaceMethod org/protege/editor/owl/model/OWLModelManager.removeListener:(Lorg/protege/editor/owl/model/event/OWLModelManagerListener;)V
      13: aload_0
      14: invokevirtual #4                  // Method getOWLModelManager:()Lorg/protege/editor/owl/model/OWLModelManager;
      17: aload_0
      18: getfield      #7                  // Field owlOntologyChangeListener:Lorg/semanticweb/owlapi/model/OWLOntologyChangeListener;
      21: invokeinterface #14,  2           // InterfaceMethod org/protege/editor/owl/model/OWLModelManager.removeOntologyChangeListener:(Lorg/semanticweb/owlapi/model/OWLOntologyChangeListener;)V
      26: aload_0
      27: invokevirtual #15                 // Method disposeOntologyView:()V
      30: return

  protected abstract void disposeOntologyView();

  private void markForUpdate();
    Code:
       0: aload_0
       1: invokevirtual #16                 // Method isShowing:()Z
       4: ifeq          55
       7: aload_0
       8: getfield      #17                 // Field updateView:Z
      11: ifeq          55
      14: aload_0
      15: invokevirtual #18                 // Method isSynchronizing:()Z
      18: ifeq          34
      21: aload_0
      22: aload_0
      23: invokevirtual #4                  // Method getOWLModelManager:()Lorg/protege/editor/owl/model/OWLModelManager;
      26: invokeinterface #19,  1           // InterfaceMethod org/protege/editor/owl/model/OWLModelManager.getActiveOntology:()Lorg/semanticweb/owlapi/model/OWLOntology;
      31: invokevirtual #20                 // Method updateView:(Lorg/semanticweb/owlapi/model/OWLOntology;)V
      34: goto          47
      37: astore_1
      38: new           #22                 // class java/lang/RuntimeException
      41: dup
      42: aload_1
      43: invokespecial #23                 // Method java/lang/RuntimeException."<init>":(Ljava/lang/Throwable;)V
      46: athrow
      47: aload_0
      48: iconst_0
      49: putfield      #17                 // Field updateView:Z
      52: goto          60
      55: aload_0
      56: iconst_1
      57: putfield      #17                 // Field updateView:Z
      60: return
    Exception table:
       from    to  target type
          14    34    37   Class java/lang/Exception

  protected abstract void updateView(org.semanticweb.owlapi.model.OWLOntology) throws java.lang.Exception;

  private void lambda$initialiseOWLView$2(java.awt.event.HierarchyEvent);
    Code:
       0: aload_0
       1: invokespecial #24                 // Method markForUpdate:()V
       4: return

  private void lambda$initialiseOWLView$1(java.util.List) throws org.semanticweb.owlapi.model.OWLException;
    Code:
       0: aload_1
       1: invokeinterface #25,  1           // InterfaceMethod java/util/List.iterator:()Ljava/util/Iterator;
       6: astore_2
       7: aload_2
       8: invokeinterface #26,  1           // InterfaceMethod java/util/Iterator.hasNext:()Z
      13: ifeq          60
      16: aload_2
      17: invokeinterface #27,  1           // InterfaceMethod java/util/Iterator.next:()Ljava/lang/Object;
      22: checkcast     #28                 // class org/semanticweb/owlapi/model/OWLOntologyChange
      25: astore_3
      26: aload_3
      27: invokevirtual #29                 // Method org/semanticweb/owlapi/model/OWLOntologyChange.getOntology:()Lorg/semanticweb/owlapi/model/OWLOntology;
      30: aload_0
      31: invokevirtual #4                  // Method getOWLModelManager:()Lorg/protege/editor/owl/model/OWLModelManager;
      34: invokeinterface #19,  1           // InterfaceMethod org/protege/editor/owl/model/OWLModelManager.getActiveOntology:()Lorg/semanticweb/owlapi/model/OWLOntology;
      39: invokevirtual #30                 // Method java/lang/Object.equals:(Ljava/lang/Object;)Z
      42: ifeq          57
      45: aload_0
      46: iconst_1
      47: putfield      #17                 // Field updateView:Z
      50: aload_0
      51: invokespecial #24                 // Method markForUpdate:()V
      54: goto          60
      57: goto          7
      60: return

  private void lambda$initialiseOWLView$0(org.protege.editor.owl.model.event.OWLModelManagerChangeEvent);
    Code:
       0: aload_1
       1: getstatic     #31                 // Field org/protege/editor/owl/model/event/EventType.ACTIVE_ONTOLOGY_CHANGED:Lorg/protege/editor/owl/model/event/EventType;
       4: invokevirtual #32                 // Method org/protege/editor/owl/model/event/OWLModelManagerChangeEvent.isType:(Lorg/protege/editor/owl/model/event/EventType;)Z
       7: ifeq          19
      10: aload_0
      11: iconst_1
      12: putfield      #17                 // Field updateView:Z
      15: aload_0
      16: invokespecial #24                 // Method markForUpdate:()V
      19: return
}
