Compiled from "BeanNameViewResolver.java"
public class org.springframework.web.servlet.view.BeanNameViewResolver extends org.springframework.web.context.support.WebApplicationObjectSupport implements org.springframework.web.servlet.ViewResolver,org.springframework.core.Ordered {
  private int order;

  public org.springframework.web.servlet.view.BeanNameViewResolver();
    Code:
       0: aload_0
       1: invokespecial #1                  // Method org/springframework/web/context/support/WebApplicationObjectSupport."<init>":()V
       4: aload_0
       5: ldc           #3                  // int 2147483647
       7: putfield      #4                  // Field order:I
      10: return

  public void setOrder(int);
    Code:
       0: aload_0
       1: iload_1
       2: putfield      #4                  // Field order:I
       5: return

  public int getOrder();
    Code:
       0: aload_0
       1: getfield      #4                  // Field order:I
       4: ireturn

  public org.springframework.web.servlet.View resolveViewName(java.lang.String, java.util.Locale) throws org.springframework.beans.BeansException;
    Code:
       0: aload_0
       1: invokevirtual #5                  // Method obtainApplicationContext:()Lorg/springframework/context/ApplicationContext;
       4: astore_3
       5: aload_3
       6: aload_1
       7: invokeinterface #6,  2            // InterfaceMethod org/springframework/context/ApplicationContext.containsBean:(Ljava/lang/String;)Z
      12: ifne          17
      15: aconst_null
      16: areturn
      17: aload_3
      18: aload_1
      19: ldc           #7                  // class org/springframework/web/servlet/View
      21: invokeinterface #8,  3            // InterfaceMethod org/springframework/context/ApplicationContext.isTypeMatch:(Ljava/lang/String;Ljava/lang/Class;)Z
      26: ifne          76
      29: aload_0
      30: getfield      #9                  // Field logger:Lorg/apache/commons/logging/Log;
      33: invokeinterface #10,  1           // InterfaceMethod org/apache/commons/logging/Log.isDebugEnabled:()Z
      38: ifeq          74
      41: aload_0
      42: getfield      #9                  // Field logger:Lorg/apache/commons/logging/Log;
      45: new           #11                 // class java/lang/StringBuilder
      48: dup
      49: invokespecial #12                 // Method java/lang/StringBuilder."<init>":()V
      52: ldc           #13                 // String Found bean named \'
      54: invokevirtual #14                 // Method java/lang/StringBuilder.append:(Ljava/lang/String;)Ljava/lang/StringBuilder;
      57: aload_1
      58: invokevirtual #14                 // Method java/lang/StringBuilder.append:(Ljava/lang/String;)Ljava/lang/StringBuilder;
      61: ldc           #15                 // String \' but it does not implement View
      63: invokevirtual #14                 // Method java/lang/StringBuilder.append:(Ljava/lang/String;)Ljava/lang/StringBuilder;
      66: invokevirtual #16                 // Method java/lang/StringBuilder.toString:()Ljava/lang/String;
      69: invokeinterface #17,  2           // InterfaceMethod org/apache/commons/logging/Log.debug:(Ljava/lang/Object;)V
      74: aconst_null
      75: areturn
      76: aload_3
      77: aload_1
      78: ldc           #7                  // class org/springframework/web/servlet/View
      80: invokeinterface #18,  3           // InterfaceMethod org/springframework/context/ApplicationContext.getBean:(Ljava/lang/String;Ljava/lang/Class;)Ljava/lang/Object;
      85: checkcast     #7                  // class org/springframework/web/servlet/View
      88: areturn
}
