Compiled from "JstlView.java"
public class org.springframework.web.servlet.view.JstlView extends org.springframework.web.servlet.view.InternalResourceView {
  private org.springframework.context.MessageSource messageSource;

  public org.springframework.web.servlet.view.JstlView();
    Code:
       0: aload_0
       1: invokespecial #1                  // Method org/springframework/web/servlet/view/InternalResourceView."<init>":()V
       4: return

  public org.springframework.web.servlet.view.JstlView(java.lang.String);
    Code:
       0: aload_0
       1: aload_1
       2: invokespecial #2                  // Method org/springframework/web/servlet/view/InternalResourceView."<init>":(Ljava/lang/String;)V
       5: return

  public org.springframework.web.servlet.view.JstlView(java.lang.String, org.springframework.context.MessageSource);
    Code:
       0: aload_0
       1: aload_1
       2: invokespecial #3                  // Method "<init>":(Ljava/lang/String;)V
       5: aload_0
       6: aload_2
       7: putfield      #4                  // Field messageSource:Lorg/springframework/context/MessageSource;
      10: return

  protected void initServletContext(javax.servlet.ServletContext);
    Code:
       0: aload_0
       1: getfield      #4                  // Field messageSource:Lorg/springframework/context/MessageSource;
       4: ifnull        19
       7: aload_0
       8: aload_1
       9: aload_0
      10: getfield      #4                  // Field messageSource:Lorg/springframework/context/MessageSource;
      13: invokestatic  #5                  // Method org/springframework/web/servlet/support/JstlUtils.getJstlAwareMessageSource:(Ljavax/servlet/ServletContext;Lorg/springframework/context/MessageSource;)Lorg/springframework/context/MessageSource;
      16: putfield      #4                  // Field messageSource:Lorg/springframework/context/MessageSource;
      19: aload_0
      20: aload_1
      21: invokespecial #6                  // Method org/springframework/web/servlet/view/InternalResourceView.initServletContext:(Ljavax/servlet/ServletContext;)V
      24: return

  protected void exposeHelpers(javax.servlet.http.HttpServletRequest) throws java.lang.Exception;
    Code:
       0: aload_0
       1: getfield      #4                  // Field messageSource:Lorg/springframework/context/MessageSource;
       4: ifnull        18
       7: aload_1
       8: aload_0
       9: getfield      #4                  // Field messageSource:Lorg/springframework/context/MessageSource;
      12: invokestatic  #7                  // Method org/springframework/web/servlet/support/JstlUtils.exposeLocalizationContext:(Ljavax/servlet/http/HttpServletRequest;Lorg/springframework/context/MessageSource;)V
      15: goto          33
      18: new           #8                  // class org/springframework/web/servlet/support/RequestContext
      21: dup
      22: aload_1
      23: aload_0
      24: invokevirtual #9                  // Method getServletContext:()Ljavax/servlet/ServletContext;
      27: invokespecial #10                 // Method org/springframework/web/servlet/support/RequestContext."<init>":(Ljavax/servlet/http/HttpServletRequest;Ljavax/servlet/ServletContext;)V
      30: invokestatic  #11                 // Method org/springframework/web/servlet/support/JstlUtils.exposeLocalizationContext:(Lorg/springframework/web/servlet/support/RequestContext;)V
      33: return
}
