Compiled from "Action.java"
public final class org.jboss.as.controller.access.Action {
  private static final java.util.List<org.jboss.as.controller.access.management.AccessConstraintDefinition> NO_CONSTRAINTS;

  private final org.jboss.dmr.ModelNode operation;

  private final org.jboss.as.controller.registry.OperationEntry operationEntry;

  private final java.util.Set<org.jboss.as.controller.access.Action$ActionEffect> actionEffects;

  public org.jboss.as.controller.access.Action(org.jboss.dmr.ModelNode, org.jboss.as.controller.registry.OperationEntry);
    Code:
       0: aload_0
       1: invokespecial #1                  // Method java/lang/Object."<init>":()V
       4: aload_0
       5: aload_1
       6: putfield      #2                  // Field operation:Lorg/jboss/dmr/ModelNode;
       9: aload_0
      10: aload_2
      11: putfield      #3                  // Field operationEntry:Lorg/jboss/as/controller/registry/OperationEntry;
      14: aload_0
      15: aload_2
      16: invokestatic  #4                  // Method determineActionEffects:(Lorg/jboss/as/controller/registry/OperationEntry;)Ljava/util/Set;
      19: invokestatic  #5                  // Method java/util/Collections.unmodifiableSet:(Ljava/util/Set;)Ljava/util/Set;
      22: putfield      #6                  // Field actionEffects:Ljava/util/Set;
      25: return

  public org.jboss.as.controller.access.Action(org.jboss.dmr.ModelNode, org.jboss.as.controller.registry.OperationEntry, java.util.Set<org.jboss.as.controller.access.Action$ActionEffect>);
    Code:
       0: aload_0
       1: invokespecial #1                  // Method java/lang/Object."<init>":()V
       4: aload_0
       5: aload_1
       6: putfield      #2                  // Field operation:Lorg/jboss/dmr/ModelNode;
       9: aload_0
      10: aload_2
      11: putfield      #3                  // Field operationEntry:Lorg/jboss/as/controller/registry/OperationEntry;
      14: aload_0
      15: aload_3
      16: invokestatic  #5                  // Method java/util/Collections.unmodifiableSet:(Ljava/util/Set;)Ljava/util/Set;
      19: putfield      #6                  // Field actionEffects:Ljava/util/Set;
      22: return

  private static java.util.Set<org.jboss.as.controller.access.Action$ActionEffect> determineActionEffects(org.jboss.as.controller.registry.OperationEntry);
    Code:
       0: aload_0
       1: ifnonnull     8
       4: invokestatic  #7                  // Method java/util/Collections.emptySet:()Ljava/util/Set;
       7: areturn
       8: aload_0
       9: invokevirtual #8                  // Method org/jboss/as/controller/registry/OperationEntry.getFlags:()Ljava/util/EnumSet;
      12: astore_2
      13: aload_2
      14: getstatic     #9                  // Field org/jboss/as/controller/registry/OperationEntry$Flag.RUNTIME_ONLY:Lorg/jboss/as/controller/registry/OperationEntry$Flag;
      17: invokevirtual #10                 // Method java/util/EnumSet.contains:(Ljava/lang/Object;)Z
      20: ifeq          54
      23: getstatic     #11                 // Field org/jboss/as/controller/access/Action$ActionEffect.ADDRESS:Lorg/jboss/as/controller/access/Action$ActionEffect;
      26: getstatic     #12                 // Field org/jboss/as/controller/access/Action$ActionEffect.READ_RUNTIME:Lorg/jboss/as/controller/access/Action$ActionEffect;
      29: invokestatic  #13                 // Method java/util/EnumSet.of:(Ljava/lang/Enum;Ljava/lang/Enum;)Ljava/util/EnumSet;
      32: astore_1
      33: aload_2
      34: getstatic     #14                 // Field org/jboss/as/controller/registry/OperationEntry$Flag.READ_ONLY:Lorg/jboss/as/controller/registry/OperationEntry$Flag;
      37: invokevirtual #10                 // Method java/util/EnumSet.contains:(Ljava/lang/Object;)Z
      40: ifne          86
      43: aload_1
      44: getstatic     #15                 // Field org/jboss/as/controller/access/Action$ActionEffect.WRITE_RUNTIME:Lorg/jboss/as/controller/access/Action$ActionEffect;
      47: invokevirtual #16                 // Method java/util/EnumSet.add:(Ljava/lang/Object;)Z
      50: pop
      51: goto          86
      54: aload_2
      55: getstatic     #14                 // Field org/jboss/as/controller/registry/OperationEntry$Flag.READ_ONLY:Lorg/jboss/as/controller/registry/OperationEntry$Flag;
      58: invokevirtual #10                 // Method java/util/EnumSet.contains:(Ljava/lang/Object;)Z
      61: ifeq          80
      64: getstatic     #11                 // Field org/jboss/as/controller/access/Action$ActionEffect.ADDRESS:Lorg/jboss/as/controller/access/Action$ActionEffect;
      67: getstatic     #17                 // Field org/jboss/as/controller/access/Action$ActionEffect.READ_CONFIG:Lorg/jboss/as/controller/access/Action$ActionEffect;
      70: getstatic     #12                 // Field org/jboss/as/controller/access/Action$ActionEffect.READ_RUNTIME:Lorg/jboss/as/controller/access/Action$ActionEffect;
      73: invokestatic  #18                 // Method java/util/EnumSet.of:(Ljava/lang/Enum;Ljava/lang/Enum;Ljava/lang/Enum;)Ljava/util/EnumSet;
      76: astore_1
      77: goto          86
      80: ldc           #19                 // class org/jboss/as/controller/access/Action$ActionEffect
      82: invokestatic  #20                 // Method java/util/EnumSet.allOf:(Ljava/lang/Class;)Ljava/util/EnumSet;
      85: astore_1
      86: aload_1
      87: areturn

  public org.jboss.dmr.ModelNode getOperation();
    Code:
       0: aload_0
       1: getfield      #2                  // Field operation:Lorg/jboss/dmr/ModelNode;
       4: areturn

  public java.util.Set<org.jboss.as.controller.access.Action$ActionEffect> getActionEffects();
    Code:
       0: aload_0
       1: getfield      #6                  // Field actionEffects:Ljava/util/Set;
       4: areturn

  public java.util.EnumSet<org.jboss.as.controller.registry.OperationEntry$Flag> getFlags();
    Code:
       0: aload_0
       1: getfield      #3                  // Field operationEntry:Lorg/jboss/as/controller/registry/OperationEntry;
       4: ifnull        17
       7: aload_0
       8: getfield      #3                  // Field operationEntry:Lorg/jboss/as/controller/registry/OperationEntry;
      11: invokevirtual #8                  // Method org/jboss/as/controller/registry/OperationEntry.getFlags:()Ljava/util/EnumSet;
      14: goto          22
      17: ldc           #21                 // class org/jboss/as/controller/registry/OperationEntry$Flag
      19: invokestatic  #22                 // Method java/util/EnumSet.noneOf:(Ljava/lang/Class;)Ljava/util/EnumSet;
      22: areturn

  public java.util.List<org.jboss.as.controller.access.management.AccessConstraintDefinition> getAccessConstraints();
    Code:
       0: aload_0
       1: getfield      #3                  // Field operationEntry:Lorg/jboss/as/controller/registry/OperationEntry;
       4: ifnull        17
       7: aload_0
       8: getfield      #3                  // Field operationEntry:Lorg/jboss/as/controller/registry/OperationEntry;
      11: invokevirtual #23                 // Method org/jboss/as/controller/registry/OperationEntry.getAccessConstraints:()Ljava/util/List;
      14: goto          20
      17: getstatic     #24                 // Field NO_CONSTRAINTS:Ljava/util/List;
      20: areturn

  public org.jboss.as.controller.access.Action limitAction(org.jboss.as.controller.access.Action$ActionEffect);
    Code:
       0: aload_0
       1: getfield      #6                  // Field actionEffects:Ljava/util/Set;
       4: aload_1
       5: invokeinterface #25,  2           // InterfaceMethod java/util/Set.contains:(Ljava/lang/Object;)Z
      10: ifeq          28
      13: aload_0
      14: getfield      #6                  // Field actionEffects:Ljava/util/Set;
      17: invokeinterface #26,  1           // InterfaceMethod java/util/Set.size:()I
      22: iconst_1
      23: if_icmpne     28
      26: aload_0
      27: areturn
      28: new           #27                 // class org/jboss/as/controller/access/Action
      31: dup
      32: aload_0
      33: getfield      #2                  // Field operation:Lorg/jboss/dmr/ModelNode;
      36: aload_0
      37: getfield      #3                  // Field operationEntry:Lorg/jboss/as/controller/registry/OperationEntry;
      40: aload_1
      41: invokestatic  #28                 // Method java/util/EnumSet.of:(Ljava/lang/Enum;)Ljava/util/EnumSet;
      44: invokespecial #29                 // Method "<init>":(Lorg/jboss/dmr/ModelNode;Lorg/jboss/as/controller/registry/OperationEntry;Ljava/util/Set;)V
      47: areturn

  static {};
    Code:
       0: invokestatic  #30                 // Method java/util/Collections.emptyList:()Ljava/util/List;
       3: putstatic     #24                 // Field NO_CONSTRAINTS:Ljava/util/List;
       6: return
}
