Compiled from "AuthorizerConfiguration.java"
public final class org.jboss.as.controller.access.AuthorizerConfiguration$ScopedRole {
  private final java.lang.String name;

  private final java.lang.String baseRoleName;

  private final org.jboss.as.controller.access.constraint.ScopingConstraint scopingConstraint;

  public org.jboss.as.controller.access.AuthorizerConfiguration$ScopedRole(java.lang.String, java.lang.String, org.jboss.as.controller.access.constraint.ScopingConstraint);
    Code:
       0: aload_0
       1: invokespecial #1                  // Method java/lang/Object."<init>":()V
       4: aload_0
       5: aload_1
       6: putfield      #2                  // Field name:Ljava/lang/String;
       9: aload_0
      10: aload_2
      11: putfield      #3                  // Field baseRoleName:Ljava/lang/String;
      14: aload_0
      15: aload_3
      16: putfield      #4                  // Field scopingConstraint:Lorg/jboss/as/controller/access/constraint/ScopingConstraint;
      19: return

  public java.lang.String getName();
    Code:
       0: aload_0
       1: getfield      #2                  // Field name:Ljava/lang/String;
       4: areturn

  public java.lang.String getBaseRoleName();
    Code:
       0: aload_0
       1: getfield      #3                  // Field baseRoleName:Ljava/lang/String;
       4: areturn

  public org.jboss.as.controller.access.constraint.ScopingConstraint getScopingConstraint();
    Code:
       0: aload_0
       1: getfield      #4                  // Field scopingConstraint:Lorg/jboss/as/controller/access/constraint/ScopingConstraint;
       4: areturn
}
