Compiled from "WordCharacterHandler.java"
public class org.jboss.as.cli.parsing.WordCharacterHandler extends org.jboss.as.cli.parsing.LineBreakHandler {
  public static final org.jboss.as.cli.parsing.WordCharacterHandler IGNORE_LB_ESCAPE_ON;

  public static final org.jboss.as.cli.parsing.WordCharacterHandler IGNORE_LB_ESCAPE_OFF;

  public static final org.jboss.as.cli.parsing.WordCharacterHandler LB_LEAVE_ESCAPE_ON;

  public org.jboss.as.cli.parsing.WordCharacterHandler(boolean, boolean);
    Code:
       0: aload_0
       1: iload_1
       2: iload_2
       3: invokespecial #1                  // Method org/jboss/as/cli/parsing/LineBreakHandler."<init>":(ZZ)V
       6: return

  public void doHandle(org.jboss.as.cli.parsing.ParsingContext) throws org.jboss.as.cli.CommandFormatException;
    Code:
       0: aload_1
       1: invokeinterface #2,  1            // InterfaceMethod org/jboss/as/cli/parsing/ParsingContext.getCallbackHandler:()Lorg/jboss/as/cli/parsing/ParsingStateCallbackHandler;
       6: aload_1
       7: invokeinterface #3,  2            // InterfaceMethod org/jboss/as/cli/parsing/ParsingStateCallbackHandler.character:(Lorg/jboss/as/cli/parsing/ParsingContext;)V
      12: return

  static {};
    Code:
       0: new           #4                  // class org/jboss/as/cli/parsing/WordCharacterHandler
       3: dup
       4: iconst_0
       5: iconst_1
       6: invokespecial #5                  // Method "<init>":(ZZ)V
       9: putstatic     #6                  // Field IGNORE_LB_ESCAPE_ON:Lorg/jboss/as/cli/parsing/WordCharacterHandler;
      12: new           #4                  // class org/jboss/as/cli/parsing/WordCharacterHandler
      15: dup
      16: iconst_0
      17: iconst_0
      18: invokespecial #5                  // Method "<init>":(ZZ)V
      21: putstatic     #7                  // Field IGNORE_LB_ESCAPE_OFF:Lorg/jboss/as/cli/parsing/WordCharacterHandler;
      24: new           #4                  // class org/jboss/as/cli/parsing/WordCharacterHandler
      27: dup
      28: iconst_1
      29: iconst_1
      30: invokespecial #5                  // Method "<init>":(ZZ)V
      33: putstatic     #8                  // Field LB_LEAVE_ESCAPE_ON:Lorg/jboss/as/cli/parsing/WordCharacterHandler;
      36: return
}
