Compiled from "BlockingBuffer.java"
public class org.apache.commons.collections.buffer.BlockingBuffer extends org.apache.commons.collections.buffer.SynchronizedBuffer {
  private static final long serialVersionUID;

  private final long timeout;

  public static org.apache.commons.collections.Buffer decorate(org.apache.commons.collections.Buffer);
    Code:
       0: new           #1                  // class org/apache/commons/collections/buffer/BlockingBuffer
       3: dup
       4: aload_0
       5: invokespecial #2                  // Method "<init>":(Lorg/apache/commons/collections/Buffer;)V
       8: areturn

  public static org.apache.commons.collections.Buffer decorate(org.apache.commons.collections.Buffer, long);
    Code:
       0: new           #1                  // class org/apache/commons/collections/buffer/BlockingBuffer
       3: dup
       4: aload_0
       5: lload_1
       6: invokespecial #3                  // Method "<init>":(Lorg/apache/commons/collections/Buffer;J)V
       9: areturn

  protected org.apache.commons.collections.buffer.BlockingBuffer(org.apache.commons.collections.Buffer);
    Code:
       0: aload_0
       1: aload_1
       2: invokespecial #4                  // Method org/apache/commons/collections/buffer/SynchronizedBuffer."<init>":(Lorg/apache/commons/collections/Buffer;)V
       5: aload_0
       6: lconst_0
       7: putfield      #5                  // Field timeout:J
      10: return

  protected org.apache.commons.collections.buffer.BlockingBuffer(org.apache.commons.collections.Buffer, long);
    Code:
       0: aload_0
       1: aload_1
       2: invokespecial #4                  // Method org/apache/commons/collections/buffer/SynchronizedBuffer."<init>":(Lorg/apache/commons/collections/Buffer;)V
       5: aload_0
       6: lload_2
       7: lconst_0
       8: lcmp
       9: ifge          16
      12: lconst_0
      13: goto          17
      16: lload_2
      17: putfield      #5                  // Field timeout:J
      20: return

  public boolean add(java.lang.Object);
    Code:
       0: aload_0
       1: getfield      #6                  // Field lock:Ljava/lang/Object;
       4: dup
       5: astore_2
       6: monitorenter
       7: aload_0
       8: getfield      #7                  // Field collection:Ljava/util/Collection;
      11: aload_1
      12: invokeinterface #8,  2            // InterfaceMethod java/util/Collection.add:(Ljava/lang/Object;)Z
      17: istore_3
      18: aload_0
      19: getfield      #6                  // Field lock:Ljava/lang/Object;
      22: invokevirtual #9                  // Method java/lang/Object.notifyAll:()V
      25: iload_3
      26: aload_2
      27: monitorexit
      28: ireturn
      29: astore        4
      31: aload_2
      32: monitorexit
      33: aload         4
      35: athrow
    Exception table:
       from    to  target type
           7    28    29   any
          29    33    29   any

  public boolean addAll(java.util.Collection);
    Code:
       0: aload_0
       1: getfield      #6                  // Field lock:Ljava/lang/Object;
       4: dup
       5: astore_2
       6: monitorenter
       7: aload_0
       8: getfield      #7                  // Field collection:Ljava/util/Collection;
      11: aload_1
      12: invokeinterface #10,  2           // InterfaceMethod java/util/Collection.addAll:(Ljava/util/Collection;)Z
      17: istore_3
      18: aload_0
      19: getfield      #6                  // Field lock:Ljava/lang/Object;
      22: invokevirtual #9                  // Method java/lang/Object.notifyAll:()V
      25: iload_3
      26: aload_2
      27: monitorexit
      28: ireturn
      29: astore        4
      31: aload_2
      32: monitorexit
      33: aload         4
      35: athrow
    Exception table:
       from    to  target type
           7    28    29   any
          29    33    29   any

  public java.lang.Object get();
    Code:
       0: aload_0
       1: getfield      #6                  // Field lock:Ljava/lang/Object;
       4: dup
       5: astore_1
       6: monitorenter
       7: aload_0
       8: getfield      #7                  // Field collection:Ljava/util/Collection;
      11: invokeinterface #11,  1           // InterfaceMethod java/util/Collection.isEmpty:()Z
      16: ifeq          103
      19: aload_0
      20: getfield      #5                  // Field timeout:J
      23: lconst_0
      24: lcmp
      25: ifgt          38
      28: aload_0
      29: getfield      #6                  // Field lock:Ljava/lang/Object;
      32: invokevirtual #12                 // Method java/lang/Object.wait:()V
      35: goto          49
      38: aload_0
      39: aload_0
      40: getfield      #5                  // Field timeout:J
      43: invokevirtual #13                 // Method get:(J)Ljava/lang/Object;
      46: aload_1
      47: monitorexit
      48: areturn
      49: goto          7
      52: astore_2
      53: new           #15                 // class java/io/PrintWriter
      56: dup
      57: new           #16                 // class java/io/StringWriter
      60: dup
      61: invokespecial #17                 // Method java/io/StringWriter."<init>":()V
      64: invokespecial #18                 // Method java/io/PrintWriter."<init>":(Ljava/io/Writer;)V
      67: astore_3
      68: aload_2
      69: aload_3
      70: invokevirtual #19                 // Method java/lang/InterruptedException.printStackTrace:(Ljava/io/PrintWriter;)V
      73: new           #20                 // class org/apache/commons/collections/BufferUnderflowException
      76: dup
      77: new           #21                 // class java/lang/StringBuffer
      80: dup
      81: invokespecial #22                 // Method java/lang/StringBuffer."<init>":()V
      84: ldc           #23                 // String Caused by InterruptedException:
      86: invokevirtual #24                 // Method java/lang/StringBuffer.append:(Ljava/lang/String;)Ljava/lang/StringBuffer;
      89: aload_3
      90: invokevirtual #25                 // Method java/lang/Object.toString:()Ljava/lang/String;
      93: invokevirtual #24                 // Method java/lang/StringBuffer.append:(Ljava/lang/String;)Ljava/lang/StringBuffer;
      96: invokevirtual #26                 // Method java/lang/StringBuffer.toString:()Ljava/lang/String;
      99: invokespecial #27                 // Method org/apache/commons/collections/BufferUnderflowException."<init>":(Ljava/lang/String;)V
     102: athrow
     103: aload_0
     104: invokevirtual #28                 // Method getBuffer:()Lorg/apache/commons/collections/Buffer;
     107: invokeinterface #29,  1           // InterfaceMethod org/apache/commons/collections/Buffer.get:()Ljava/lang/Object;
     112: aload_1
     113: monitorexit
     114: areturn
     115: astore        4
     117: aload_1
     118: monitorexit
     119: aload         4
     121: athrow
    Exception table:
       from    to  target type
          19    46    52   Class java/lang/InterruptedException
           7    48   115   any
          49   114   115   any
         115   119   115   any

  public java.lang.Object get(long);
    Code:
       0: aload_0
       1: getfield      #6                  // Field lock:Ljava/lang/Object;
       4: dup
       5: astore_3
       6: monitorenter
       7: invokestatic  #30                 // Method java/lang/System.currentTimeMillis:()J
      10: lload_1
      11: ladd
      12: lstore        4
      14: lload         4
      16: invokestatic  #30                 // Method java/lang/System.currentTimeMillis:()J
      19: lsub
      20: lstore        6
      22: lload         6
      24: lconst_0
      25: lcmp
      26: ifle          117
      29: aload_0
      30: getfield      #7                  // Field collection:Ljava/util/Collection;
      33: invokeinterface #11,  1           // InterfaceMethod java/util/Collection.isEmpty:()Z
      38: ifeq          117
      41: aload_0
      42: getfield      #6                  // Field lock:Ljava/lang/Object;
      45: lload         6
      47: invokevirtual #31                 // Method java/lang/Object.wait:(J)V
      50: lload         4
      52: invokestatic  #30                 // Method java/lang/System.currentTimeMillis:()J
      55: lsub
      56: lstore        6
      58: goto          22
      61: astore        8
      63: new           #15                 // class java/io/PrintWriter
      66: dup
      67: new           #16                 // class java/io/StringWriter
      70: dup
      71: invokespecial #17                 // Method java/io/StringWriter."<init>":()V
      74: invokespecial #18                 // Method java/io/PrintWriter."<init>":(Ljava/io/Writer;)V
      77: astore        9
      79: aload         8
      81: aload         9
      83: invokevirtual #19                 // Method java/lang/InterruptedException.printStackTrace:(Ljava/io/PrintWriter;)V
      86: new           #20                 // class org/apache/commons/collections/BufferUnderflowException
      89: dup
      90: new           #21                 // class java/lang/StringBuffer
      93: dup
      94: invokespecial #22                 // Method java/lang/StringBuffer."<init>":()V
      97: ldc           #23                 // String Caused by InterruptedException:
      99: invokevirtual #24                 // Method java/lang/StringBuffer.append:(Ljava/lang/String;)Ljava/lang/StringBuffer;
     102: aload         9
     104: invokevirtual #25                 // Method java/lang/Object.toString:()Ljava/lang/String;
     107: invokevirtual #24                 // Method java/lang/StringBuffer.append:(Ljava/lang/String;)Ljava/lang/StringBuffer;
     110: invokevirtual #26                 // Method java/lang/StringBuffer.toString:()Ljava/lang/String;
     113: invokespecial #27                 // Method org/apache/commons/collections/BufferUnderflowException."<init>":(Ljava/lang/String;)V
     116: athrow
     117: aload_0
     118: getfield      #7                  // Field collection:Ljava/util/Collection;
     121: invokeinterface #11,  1           // InterfaceMethod java/util/Collection.isEmpty:()Z
     126: ifeq          139
     129: new           #20                 // class org/apache/commons/collections/BufferUnderflowException
     132: dup
     133: ldc           #32                 // String Timeout expired
     135: invokespecial #27                 // Method org/apache/commons/collections/BufferUnderflowException."<init>":(Ljava/lang/String;)V
     138: athrow
     139: aload_0
     140: invokevirtual #28                 // Method getBuffer:()Lorg/apache/commons/collections/Buffer;
     143: invokeinterface #29,  1           // InterfaceMethod org/apache/commons/collections/Buffer.get:()Ljava/lang/Object;
     148: aload_3
     149: monitorexit
     150: areturn
     151: astore        10
     153: aload_3
     154: monitorexit
     155: aload         10
     157: athrow
    Exception table:
       from    to  target type
          41    58    61   Class java/lang/InterruptedException
           7   150   151   any
         151   155   151   any

  public java.lang.Object remove();
    Code:
       0: aload_0
       1: getfield      #6                  // Field lock:Ljava/lang/Object;
       4: dup
       5: astore_1
       6: monitorenter
       7: aload_0
       8: getfield      #7                  // Field collection:Ljava/util/Collection;
      11: invokeinterface #11,  1           // InterfaceMethod java/util/Collection.isEmpty:()Z
      16: ifeq          103
      19: aload_0
      20: getfield      #5                  // Field timeout:J
      23: lconst_0
      24: lcmp
      25: ifgt          38
      28: aload_0
      29: getfield      #6                  // Field lock:Ljava/lang/Object;
      32: invokevirtual #12                 // Method java/lang/Object.wait:()V
      35: goto          49
      38: aload_0
      39: aload_0
      40: getfield      #5                  // Field timeout:J
      43: invokevirtual #33                 // Method remove:(J)Ljava/lang/Object;
      46: aload_1
      47: monitorexit
      48: areturn
      49: goto          7
      52: astore_2
      53: new           #15                 // class java/io/PrintWriter
      56: dup
      57: new           #16                 // class java/io/StringWriter
      60: dup
      61: invokespecial #17                 // Method java/io/StringWriter."<init>":()V
      64: invokespecial #18                 // Method java/io/PrintWriter."<init>":(Ljava/io/Writer;)V
      67: astore_3
      68: aload_2
      69: aload_3
      70: invokevirtual #19                 // Method java/lang/InterruptedException.printStackTrace:(Ljava/io/PrintWriter;)V
      73: new           #20                 // class org/apache/commons/collections/BufferUnderflowException
      76: dup
      77: new           #21                 // class java/lang/StringBuffer
      80: dup
      81: invokespecial #22                 // Method java/lang/StringBuffer."<init>":()V
      84: ldc           #23                 // String Caused by InterruptedException:
      86: invokevirtual #24                 // Method java/lang/StringBuffer.append:(Ljava/lang/String;)Ljava/lang/StringBuffer;
      89: aload_3
      90: invokevirtual #25                 // Method java/lang/Object.toString:()Ljava/lang/String;
      93: invokevirtual #24                 // Method java/lang/StringBuffer.append:(Ljava/lang/String;)Ljava/lang/StringBuffer;
      96: invokevirtual #26                 // Method java/lang/StringBuffer.toString:()Ljava/lang/String;
      99: invokespecial #27                 // Method org/apache/commons/collections/BufferUnderflowException."<init>":(Ljava/lang/String;)V
     102: athrow
     103: aload_0
     104: invokevirtual #28                 // Method getBuffer:()Lorg/apache/commons/collections/Buffer;
     107: invokeinterface #34,  1           // InterfaceMethod org/apache/commons/collections/Buffer.remove:()Ljava/lang/Object;
     112: aload_1
     113: monitorexit
     114: areturn
     115: astore        4
     117: aload_1
     118: monitorexit
     119: aload         4
     121: athrow
    Exception table:
       from    to  target type
          19    46    52   Class java/lang/InterruptedException
           7    48   115   any
          49   114   115   any
         115   119   115   any

  public java.lang.Object remove(long);
    Code:
       0: aload_0
       1: getfield      #6                  // Field lock:Ljava/lang/Object;
       4: dup
       5: astore_3
       6: monitorenter
       7: invokestatic  #30                 // Method java/lang/System.currentTimeMillis:()J
      10: lload_1
      11: ladd
      12: lstore        4
      14: lload         4
      16: invokestatic  #30                 // Method java/lang/System.currentTimeMillis:()J
      19: lsub
      20: lstore        6
      22: lload         6
      24: lconst_0
      25: lcmp
      26: ifle          117
      29: aload_0
      30: getfield      #7                  // Field collection:Ljava/util/Collection;
      33: invokeinterface #11,  1           // InterfaceMethod java/util/Collection.isEmpty:()Z
      38: ifeq          117
      41: aload_0
      42: getfield      #6                  // Field lock:Ljava/lang/Object;
      45: lload         6
      47: invokevirtual #31                 // Method java/lang/Object.wait:(J)V
      50: lload         4
      52: invokestatic  #30                 // Method java/lang/System.currentTimeMillis:()J
      55: lsub
      56: lstore        6
      58: goto          22
      61: astore        8
      63: new           #15                 // class java/io/PrintWriter
      66: dup
      67: new           #16                 // class java/io/StringWriter
      70: dup
      71: invokespecial #17                 // Method java/io/StringWriter."<init>":()V
      74: invokespecial #18                 // Method java/io/PrintWriter."<init>":(Ljava/io/Writer;)V
      77: astore        9
      79: aload         8
      81: aload         9
      83: invokevirtual #19                 // Method java/lang/InterruptedException.printStackTrace:(Ljava/io/PrintWriter;)V
      86: new           #20                 // class org/apache/commons/collections/BufferUnderflowException
      89: dup
      90: new           #21                 // class java/lang/StringBuffer
      93: dup
      94: invokespecial #22                 // Method java/lang/StringBuffer."<init>":()V
      97: ldc           #23                 // String Caused by InterruptedException:
      99: invokevirtual #24                 // Method java/lang/StringBuffer.append:(Ljava/lang/String;)Ljava/lang/StringBuffer;
     102: aload         9
     104: invokevirtual #25                 // Method java/lang/Object.toString:()Ljava/lang/String;
     107: invokevirtual #24                 // Method java/lang/StringBuffer.append:(Ljava/lang/String;)Ljava/lang/StringBuffer;
     110: invokevirtual #26                 // Method java/lang/StringBuffer.toString:()Ljava/lang/String;
     113: invokespecial #27                 // Method org/apache/commons/collections/BufferUnderflowException."<init>":(Ljava/lang/String;)V
     116: athrow
     117: aload_0
     118: getfield      #7                  // Field collection:Ljava/util/Collection;
     121: invokeinterface #11,  1           // InterfaceMethod java/util/Collection.isEmpty:()Z
     126: ifeq          139
     129: new           #20                 // class org/apache/commons/collections/BufferUnderflowException
     132: dup
     133: ldc           #32                 // String Timeout expired
     135: invokespecial #27                 // Method org/apache/commons/collections/BufferUnderflowException."<init>":(Ljava/lang/String;)V
     138: athrow
     139: aload_0
     140: invokevirtual #28                 // Method getBuffer:()Lorg/apache/commons/collections/Buffer;
     143: invokeinterface #34,  1           // InterfaceMethod org/apache/commons/collections/Buffer.remove:()Ljava/lang/Object;
     148: aload_3
     149: monitorexit
     150: areturn
     151: astore        10
     153: aload_3
     154: monitorexit
     155: aload         10
     157: athrow
    Exception table:
       from    to  target type
          41    58    61   Class java/lang/InterruptedException
           7   150   151   any
         151   155   151   any
}
