Compiled from "LocalCacheConsumer.java"
public interface org.wildfly.swarm.config.infinispan.cache_container.LocalCacheConsumer<T extends org.wildfly.swarm.config.infinispan.cache_container.LocalCache<T>> {
  public abstract void accept(T);

  public default org.wildfly.swarm.config.infinispan.cache_container.LocalCacheConsumer<T> andThen(org.wildfly.swarm.config.infinispan.cache_container.LocalCacheConsumer<T>);
    Code:
       0: aload_0
       1: aload_1
       2: invokedynamic #1,  0              // InvokeDynamic #0:accept:(Lorg/wildfly/swarm/config/infinispan/cache_container/LocalCacheConsumer;Lorg/wildfly/swarm/config/infinispan/cache_container/LocalCacheConsumer;)Lorg/wildfly/swarm/config/infinispan/cache_container/LocalCacheConsumer;
       7: areturn

  private void lambda$andThen$54(org.wildfly.swarm.config.infinispan.cache_container.LocalCacheConsumer, org.wildfly.swarm.config.infinispan.cache_container.LocalCache);
    Code:
       0: aload_0
       1: aload_2
       2: invokeinterface #2,  2            // InterfaceMethod accept:(Lorg/wildfly/swarm/config/infinispan/cache_container/LocalCache;)V
       7: aload_1
       8: aload_2
       9: invokeinterface #2,  2            // InterfaceMethod accept:(Lorg/wildfly/swarm/config/infinispan/cache_container/LocalCache;)V
      14: return
}
