Compiled from "TransportThreadPoolConsumer.java"
public interface org.wildfly.swarm.config.infinispan.cache_container.TransportThreadPoolConsumer<T extends org.wildfly.swarm.config.infinispan.cache_container.TransportThreadPool<T>> {
  public abstract void accept(T);

  public default org.wildfly.swarm.config.infinispan.cache_container.TransportThreadPoolConsumer<T> andThen(org.wildfly.swarm.config.infinispan.cache_container.TransportThreadPoolConsumer<T>);
    Code:
       0: aload_0
       1: aload_1
       2: invokedynamic #1,  0              // InvokeDynamic #0:accept:(Lorg/wildfly/swarm/config/infinispan/cache_container/TransportThreadPoolConsumer;Lorg/wildfly/swarm/config/infinispan/cache_container/TransportThreadPoolConsumer;)Lorg/wildfly/swarm/config/infinispan/cache_container/TransportThreadPoolConsumer;
       7: areturn

  private void lambda$andThen$61(org.wildfly.swarm.config.infinispan.cache_container.TransportThreadPoolConsumer, org.wildfly.swarm.config.infinispan.cache_container.TransportThreadPool);
    Code:
       0: aload_0
       1: aload_2
       2: invokeinterface #2,  2            // InterfaceMethod accept:(Lorg/wildfly/swarm/config/infinispan/cache_container/TransportThreadPool;)V
       7: aload_1
       8: aload_2
       9: invokeinterface #2,  2            // InterfaceMethod accept:(Lorg/wildfly/swarm/config/infinispan/cache_container/TransportThreadPool;)V
      14: return
}
