Compiled from "OpenSSL.java"
public class org.apache.commons.ssl.OpenSSL$CipherInfo {
  public final java.lang.String javaCipher;

  public final java.lang.String blockMode;

  public final int keySize;

  public final int ivSize;

  public final boolean des2;

  public org.apache.commons.ssl.OpenSSL$CipherInfo(java.lang.String, java.lang.String, int, int, boolean);
    Code:
       0: aload_0
       1: invokespecial #1                  // Method java/lang/Object."<init>":()V
       4: aload_0
       5: aload_1
       6: putfield      #2                  // Field javaCipher:Ljava/lang/String;
       9: aload_0
      10: aload_2
      11: putfield      #3                  // Field blockMode:Ljava/lang/String;
      14: aload_0
      15: iload_3
      16: putfield      #4                  // Field keySize:I
      19: aload_0
      20: iload         4
      22: putfield      #5                  // Field ivSize:I
      25: aload_0
      26: iload         5
      28: putfield      #6                  // Field des2:Z
      31: return

  public java.lang.String toString();
    Code:
       0: new           #7                  // class java/lang/StringBuffer
       3: dup
       4: invokespecial #8                  // Method java/lang/StringBuffer."<init>":()V
       7: aload_0
       8: getfield      #2                  // Field javaCipher:Ljava/lang/String;
      11: invokevirtual #9                  // Method java/lang/StringBuffer.append:(Ljava/lang/String;)Ljava/lang/StringBuffer;
      14: ldc           #10                 // String /
      16: invokevirtual #9                  // Method java/lang/StringBuffer.append:(Ljava/lang/String;)Ljava/lang/StringBuffer;
      19: aload_0
      20: getfield      #3                  // Field blockMode:Ljava/lang/String;
      23: invokevirtual #9                  // Method java/lang/StringBuffer.append:(Ljava/lang/String;)Ljava/lang/StringBuffer;
      26: ldc           #11                 // String
      28: invokevirtual #9                  // Method java/lang/StringBuffer.append:(Ljava/lang/String;)Ljava/lang/StringBuffer;
      31: aload_0
      32: getfield      #4                  // Field keySize:I
      35: invokevirtual #12                 // Method java/lang/StringBuffer.append:(I)Ljava/lang/StringBuffer;
      38: ldc           #13                 // String bit  des2=
      40: invokevirtual #9                  // Method java/lang/StringBuffer.append:(Ljava/lang/String;)Ljava/lang/StringBuffer;
      43: aload_0
      44: getfield      #6                  // Field des2:Z
      47: invokevirtual #14                 // Method java/lang/StringBuffer.append:(Z)Ljava/lang/StringBuffer;
      50: invokevirtual #15                 // Method java/lang/StringBuffer.toString:()Ljava/lang/String;
      53: areturn
}
