Compiled from "PKCS8Key.java"
public class org.apache.commons.ssl.PKCS8Key {
  public static final java.lang.String RSA_OID;

  public static final java.lang.String DSA_OID;

  public static final java.lang.String PKCS8_UNENCRYPTED;

  public static final java.lang.String PKCS8_ENCRYPTED;

  public static final java.lang.String OPENSSL_RSA;

  public static final java.lang.String OPENSSL_DSA;

  private final java.security.PrivateKey privateKey;

  private final byte[] decryptedBytes;

  private final java.lang.String transformation;

  private final int keySize;

  private final boolean isDSA;

  private final boolean isRSA;

  public org.apache.commons.ssl.PKCS8Key(java.io.InputStream, char[]) throws java.security.GeneralSecurityException, java.io.IOException;
    Code:
       0: aload_0
       1: aload_1
       2: invokestatic  #1                  // Method org/apache/commons/ssl/Util.streamToBytes:(Ljava/io/InputStream;)[B
       5: aload_2
       6: invokespecial #2                  // Method "<init>":([B[C)V
       9: return

  public org.apache.commons.ssl.PKCS8Key(java.io.ByteArrayInputStream, char[]) throws java.security.GeneralSecurityException;
    Code:
       0: aload_0
       1: aload_1
       2: invokestatic  #3                  // Method org/apache/commons/ssl/Util.streamToBytes:(Ljava/io/ByteArrayInputStream;)[B
       5: aload_2
       6: invokespecial #2                  // Method "<init>":([B[C)V
       9: return

  public org.apache.commons.ssl.PKCS8Key(byte[], char[]) throws java.security.GeneralSecurityException;
    Code:
       0: aload_0
       1: invokespecial #4                  // Method java/lang/Object."<init>":()V
       4: new           #5                  // class org/apache/commons/ssl/PKCS8Key$DecryptResult
       7: dup
       8: ldc           #6                  // String UNENCRYPTED
      10: iconst_0
      11: aload_1
      12: invokespecial #7                  // Method org/apache/commons/ssl/PKCS8Key$DecryptResult."<init>":(Ljava/lang/String;I[B)V
      15: astore_3
      16: aload_1
      17: invokestatic  #8                  // Method org/apache/commons/ssl/PEMUtil.decode:([B)Ljava/util/List;
      20: astore        4
      22: aconst_null
      23: astore        5
      25: aconst_null
      26: astore        6
      28: aload         4
      30: invokeinterface #9,  1            // InterfaceMethod java/util/List.isEmpty:()Z
      35: ifeq          44
      38: aload_1
      39: astore        6
      41: goto          351
      44: aload         4
      46: invokeinterface #10,  1           // InterfaceMethod java/util/List.iterator:()Ljava/util/Iterator;
      51: astore        7
      53: iconst_0
      54: istore        8
      56: iconst_0
      57: istore        9
      59: aload         7
      61: invokeinterface #11,  1           // InterfaceMethod java/util/Iterator.hasNext:()Z
      66: ifeq          226
      69: aload         7
      71: invokeinterface #12,  1           // InterfaceMethod java/util/Iterator.next:()Ljava/lang/Object;
      76: checkcast     #13                 // class org/apache/commons/ssl/PEMItem
      79: astore        10
      81: aload         10
      83: getfield      #14                 // Field org/apache/commons/ssl/PEMItem.pemType:Ljava/lang/String;
      86: invokevirtual #15                 // Method java/lang/String.trim:()Ljava/lang/String;
      89: invokevirtual #16                 // Method java/lang/String.toUpperCase:()Ljava/lang/String;
      92: astore        11
      94: aload         11
      96: ldc           #17                 // String PRIVATE KEY
      98: invokevirtual #18                 // Method java/lang/String.startsWith:(Ljava/lang/String;)Z
     101: istore        12
     103: aload         11
     105: ldc           #19                 // String ENCRYPTED PRIVATE KEY
     107: invokevirtual #18                 // Method java/lang/String.startsWith:(Ljava/lang/String;)Z
     110: istore        13
     112: aload         11
     114: ldc           #20                 // String RSA PRIVATE KEY
     116: invokevirtual #18                 // Method java/lang/String.startsWith:(Ljava/lang/String;)Z
     119: istore        14
     121: aload         11
     123: ldc           #21                 // String DSA PRIVATE KEY
     125: invokevirtual #18                 // Method java/lang/String.startsWith:(Ljava/lang/String;)Z
     128: istore        15
     130: iload         12
     132: ifne          150
     135: iload         13
     137: ifne          150
     140: iload         14
     142: ifne          150
     145: iload         15
     147: ifeq          223
     150: iload         8
     152: ifne          160
     155: iload         14
     157: ifeq          164
     160: iconst_1
     161: goto          165
     164: iconst_0
     165: istore        8
     167: iload         9
     169: ifne          177
     172: iload         15
     174: ifeq          181
     177: iconst_1
     178: goto          182
     181: iconst_0
     182: istore        9
     184: aload         6
     186: ifnull        199
     189: new           #22                 // class org/apache/commons/ssl/ProbablyNotPKCS8Exception
     192: dup
     193: ldc           #23                 // String More than one pkcs8 or OpenSSL key found in the supplied PEM Base64 stream
     195: invokespecial #24                 // Method org/apache/commons/ssl/ProbablyNotPKCS8Exception."<init>":(Ljava/lang/String;)V
     198: athrow
     199: aload         10
     201: invokevirtual #25                 // Method org/apache/commons/ssl/PEMItem.getDerBytes:()[B
     204: astore        6
     206: aload         10
     208: astore        5
     210: new           #5                  // class org/apache/commons/ssl/PKCS8Key$DecryptResult
     213: dup
     214: ldc           #6                  // String UNENCRYPTED
     216: iconst_0
     217: aload         6
     219: invokespecial #7                  // Method org/apache/commons/ssl/PKCS8Key$DecryptResult."<init>":(Ljava/lang/String;I[B)V
     222: astore_3
     223: goto          59
     226: aload         6
     228: ifnonnull     241
     231: new           #22                 // class org/apache/commons/ssl/ProbablyNotPKCS8Exception
     234: dup
     235: ldc           #26                 // String No pkcs8 or OpenSSL key found in the supplied PEM Base64 stream
     237: invokespecial #24                 // Method org/apache/commons/ssl/ProbablyNotPKCS8Exception."<init>":(Ljava/lang/String;)V
     240: athrow
     241: iload         9
     243: ifne          251
     246: iload         8
     248: ifeq          351
     251: aload         5
     253: getfield      #27                 // Field org/apache/commons/ssl/PEMItem.cipher:Ljava/lang/String;
     256: invokevirtual #15                 // Method java/lang/String.trim:()Ljava/lang/String;
     259: astore        10
     261: ldc           #28                 // String UNKNOWN
     263: aload         10
     265: invokevirtual #29                 // Method java/lang/String.equals:(Ljava/lang/Object;)Z
     268: ifne          285
     271: ldc           #30                 // String
     273: aload         10
     275: invokevirtual #29                 // Method java/lang/String.equals:(Ljava/lang/Object;)Z
     278: ifne          285
     281: iconst_1
     282: goto          286
     285: iconst_0
     286: istore        11
     288: iload         11
     290: ifeq          300
     293: aload         5
     295: aload_2
     296: invokestatic  #31                 // Method opensslDecrypt:(Lorg/apache/commons/ssl/PEMItem;[C)Lorg/apache/commons/ssl/PKCS8Key$DecryptResult;
     299: astore_3
     300: ldc           #32                 // String 1.2.840.113549.1.1.1
     302: astore        12
     304: iload         9
     306: ifeq          313
     309: ldc           #33                 // String 1.2.840.10040.4.1
     311: astore        12
     313: aload_3
     314: getfield      #34                 // Field org/apache/commons/ssl/PKCS8Key$DecryptResult.bytes:[B
     317: aload         12
     319: aconst_null
     320: invokestatic  #35                 // Method formatAsPKCS8:([BLjava/lang/String;Lorg/apache/commons/ssl/ASN1Structure;)[B
     323: astore        6
     325: aload_3
     326: getfield      #36                 // Field org/apache/commons/ssl/PKCS8Key$DecryptResult.transformation:Ljava/lang/String;
     329: astore        13
     331: aload_3
     332: getfield      #37                 // Field org/apache/commons/ssl/PKCS8Key$DecryptResult.keySize:I
     335: istore        14
     337: new           #5                  // class org/apache/commons/ssl/PKCS8Key$DecryptResult
     340: dup
     341: aload         13
     343: iload         14
     345: aload         6
     347: invokespecial #7                  // Method org/apache/commons/ssl/PKCS8Key$DecryptResult."<init>":(Ljava/lang/String;I[B)V
     350: astore_3
     351: aload         6
     353: invokestatic  #38                 // Method org/apache/commons/ssl/ASN1Util.analyze:([B)Lorg/apache/commons/ssl/ASN1Structure;
     356: astore        7
     358: goto          391
     361: astore        8
     363: new           #22                 // class org/apache/commons/ssl/ProbablyNotPKCS8Exception
     366: dup
     367: new           #40                 // class java/lang/StringBuffer
     370: dup
     371: invokespecial #41                 // Method java/lang/StringBuffer."<init>":()V
     374: ldc           #42                 // String asn1 parse failure:
     376: invokevirtual #43                 // Method java/lang/StringBuffer.append:(Ljava/lang/String;)Ljava/lang/StringBuffer;
     379: aload         8
     381: invokevirtual #44                 // Method java/lang/StringBuffer.append:(Ljava/lang/Object;)Ljava/lang/StringBuffer;
     384: invokevirtual #45                 // Method java/lang/StringBuffer.toString:()Ljava/lang/String;
     387: invokespecial #24                 // Method org/apache/commons/ssl/ProbablyNotPKCS8Exception."<init>":(Ljava/lang/String;)V
     390: athrow
     391: ldc           #32                 // String 1.2.840.113549.1.1.1
     393: astore        8
     395: iconst_m1
     396: istore        9
     398: aload         7
     400: getfield      #46                 // Field org/apache/commons/ssl/ASN1Structure.derIntegers:Ljava/util/List;
     403: ifnull        418
     406: aload         7
     408: getfield      #46                 // Field org/apache/commons/ssl/ASN1Structure.derIntegers:Ljava/util/List;
     411: invokeinterface #47,  1           // InterfaceMethod java/util/List.size:()I
     416: istore        9
     418: iload         9
     420: lookupswitch  { // 2
                     6: 448
                     9: 452
               default: 499
          }
     448: ldc           #33                 // String 1.2.840.10040.4.1
     450: astore        8
     452: aload         6
     454: aload         8
     456: aload         7
     458: invokestatic  #35                 // Method formatAsPKCS8:([BLjava/lang/String;Lorg/apache/commons/ssl/ASN1Structure;)[B
     461: astore        6
     463: aload         7
     465: aload         8
     467: putfield      #48                 // Field org/apache/commons/ssl/ASN1Structure.oid1:Ljava/lang/String;
     470: aload_3
     471: getfield      #36                 // Field org/apache/commons/ssl/PKCS8Key$DecryptResult.transformation:Ljava/lang/String;
     474: astore        10
     476: aload_3
     477: getfield      #37                 // Field org/apache/commons/ssl/PKCS8Key$DecryptResult.keySize:I
     480: istore        11
     482: new           #5                  // class org/apache/commons/ssl/PKCS8Key$DecryptResult
     485: dup
     486: aload         10
     488: iload         11
     490: aload         6
     492: invokespecial #7                  // Method org/apache/commons/ssl/PKCS8Key$DecryptResult."<init>":(Ljava/lang/String;I[B)V
     495: astore_3
     496: goto          499
     499: aload         7
     501: getfield      #48                 // Field org/apache/commons/ssl/ASN1Structure.oid1:Ljava/lang/String;
     504: astore        8
     506: aload         8
     508: ldc           #49                 // String 1.2.840.113549.1
     510: invokevirtual #18                 // Method java/lang/String.startsWith:(Ljava/lang/String;)Z
     513: ifne          621
     516: iconst_0
     517: istore        10
     519: aload         8
     521: ldc           #50                 // String 1.2.840.10040.4.
     523: invokevirtual #18                 // Method java/lang/String.startsWith:(Ljava/lang/String;)Z
     526: ifeq          588
     529: aload         8
     531: ldc           #50                 // String 1.2.840.10040.4.
     533: invokevirtual #51                 // Method java/lang/String.length:()I
     536: invokevirtual #52                 // Method java/lang/String.substring:(I)Ljava/lang/String;
     539: astore        11
     541: aload         11
     543: ldc           #53                 // String 1
     545: invokevirtual #29                 // Method java/lang/String.equals:(Ljava/lang/Object;)Z
     548: ifne          581
     551: aload         11
     553: ldc           #54                 // String 1.
     555: invokevirtual #18                 // Method java/lang/String.startsWith:(Ljava/lang/String;)Z
     558: ifne          581
     561: aload         11
     563: ldc           #55                 // String 3
     565: invokevirtual #29                 // Method java/lang/String.equals:(Ljava/lang/Object;)Z
     568: ifne          581
     571: aload         11
     573: ldc           #56                 // String 3.
     575: invokevirtual #18                 // Method java/lang/String.startsWith:(Ljava/lang/String;)Z
     578: ifeq          585
     581: iconst_1
     582: goto          586
     585: iconst_0
     586: istore        10
     588: iload         10
     590: ifne          621
     593: new           #22                 // class org/apache/commons/ssl/ProbablyNotPKCS8Exception
     596: dup
     597: new           #40                 // class java/lang/StringBuffer
     600: dup
     601: invokespecial #41                 // Method java/lang/StringBuffer."<init>":()V
     604: ldc           #57                 // String Valid ASN.1, but not PKCS8 or OpenSSL format.  OID=
     606: invokevirtual #43                 // Method java/lang/StringBuffer.append:(Ljava/lang/String;)Ljava/lang/StringBuffer;
     609: aload         8
     611: invokevirtual #43                 // Method java/lang/StringBuffer.append:(Ljava/lang/String;)Ljava/lang/StringBuffer;
     614: invokevirtual #45                 // Method java/lang/StringBuffer.toString:()Ljava/lang/String;
     617: invokespecial #24                 // Method org/apache/commons/ssl/ProbablyNotPKCS8Exception."<init>":(Ljava/lang/String;)V
     620: athrow
     621: ldc           #32                 // String 1.2.840.113549.1.1.1
     623: aload         8
     625: invokevirtual #29                 // Method java/lang/String.equals:(Ljava/lang/Object;)Z
     628: istore        10
     630: ldc           #33                 // String 1.2.840.10040.4.1
     632: aload         8
     634: invokevirtual #29                 // Method java/lang/String.equals:(Ljava/lang/Object;)Z
     637: istore        11
     639: iload         10
     641: ifne          653
     644: iload         11
     646: ifne          653
     649: iconst_1
     650: goto          654
     653: iconst_0
     654: istore        12
     656: iload         12
     658: ifeq          665
     661: aconst_null
     662: goto          667
     665: aload         6
     667: astore        13
     669: iload         12
     671: ifeq          687
     674: aload         7
     676: aload_2
     677: invokestatic  #58                 // Method decryptPKCS8:(Lorg/apache/commons/ssl/ASN1Structure;[C)Lorg/apache/commons/ssl/PKCS8Key$DecryptResult;
     680: astore_3
     681: aload_3
     682: getfield      #34                 // Field org/apache/commons/ssl/PKCS8Key$DecryptResult.bytes:[B
     685: astore        13
     687: iload         12
     689: ifeq          730
     692: aload         13
     694: invokestatic  #38                 // Method org/apache/commons/ssl/ASN1Util.analyze:([B)Lorg/apache/commons/ssl/ASN1Structure;
     697: astore        7
     699: goto          714
     702: astore        14
     704: new           #59                 // class org/apache/commons/ssl/ProbablyBadPasswordException
     707: dup
     708: ldc           #60                 // String Decrypted stream not ASN.1.  Probably bad decryption password.
     710: invokespecial #61                 // Method org/apache/commons/ssl/ProbablyBadPasswordException."<init>":(Ljava/lang/String;)V
     713: athrow
     714: aload         7
     716: getfield      #48                 // Field org/apache/commons/ssl/ASN1Structure.oid1:Ljava/lang/String;
     719: astore        8
     721: ldc           #33                 // String 1.2.840.10040.4.1
     723: aload         8
     725: invokevirtual #29                 // Method java/lang/String.equals:(Ljava/lang/Object;)Z
     728: istore        11
     730: new           #62                 // class java/security/spec/PKCS8EncodedKeySpec
     733: dup
     734: aload         13
     736: invokespecial #63                 // Method java/security/spec/PKCS8EncodedKeySpec."<init>":([B)V
     739: astore        14
     741: ldc           #64                 // String RSA
     743: astore        15
     745: iload         11
     747: ifeq          764
     750: ldc           #65                 // String DSA
     752: astore        15
     754: ldc           #65                 // String DSA
     756: invokestatic  #66                 // Method java/security/KeyFactory.getInstance:(Ljava/lang/String;)Ljava/security/KeyFactory;
     759: astore        17
     761: goto          771
     764: ldc           #64                 // String RSA
     766: invokestatic  #66                 // Method java/security/KeyFactory.getInstance:(Ljava/lang/String;)Ljava/security/KeyFactory;
     769: astore        17
     771: aload         17
     773: aload         14
     775: invokevirtual #67                 // Method java/security/KeyFactory.generatePrivate:(Ljava/security/spec/KeySpec;)Ljava/security/PrivateKey;
     778: astore        16
     780: goto          823
     783: astore        17
     785: new           #59                 // class org/apache/commons/ssl/ProbablyBadPasswordException
     788: dup
     789: new           #40                 // class java/lang/StringBuffer
     792: dup
     793: invokespecial #41                 // Method java/lang/StringBuffer."<init>":()V
     796: ldc           #68                 // String Cannot create
     798: invokevirtual #43                 // Method java/lang/StringBuffer.append:(Ljava/lang/String;)Ljava/lang/StringBuffer;
     801: aload         15
     803: invokevirtual #43                 // Method java/lang/StringBuffer.append:(Ljava/lang/String;)Ljava/lang/StringBuffer;
     806: ldc           #69                 // String  private key from decrypted stream.  Probably bad decryption password.
     808: invokevirtual #43                 // Method java/lang/StringBuffer.append:(Ljava/lang/String;)Ljava/lang/StringBuffer;
     811: aload         17
     813: invokevirtual #44                 // Method java/lang/StringBuffer.append:(Ljava/lang/Object;)Ljava/lang/StringBuffer;
     816: invokevirtual #45                 // Method java/lang/StringBuffer.toString:()Ljava/lang/String;
     819: invokespecial #61                 // Method org/apache/commons/ssl/ProbablyBadPasswordException."<init>":(Ljava/lang/String;)V
     822: athrow
     823: aload         16
     825: ifnull        879
     828: aload_0
     829: aload         16
     831: putfield      #70                 // Field privateKey:Ljava/security/PrivateKey;
     834: aload_0
     835: iload         11
     837: putfield      #71                 // Field isDSA:Z
     840: aload_0
     841: iload         11
     843: ifne          850
     846: iconst_1
     847: goto          851
     850: iconst_0
     851: putfield      #72                 // Field isRSA:Z
     854: aload_0
     855: aload         13
     857: putfield      #73                 // Field decryptedBytes:[B
     860: aload_0
     861: aload_3
     862: getfield      #36                 // Field org/apache/commons/ssl/PKCS8Key$DecryptResult.transformation:Ljava/lang/String;
     865: putfield      #74                 // Field transformation:Ljava/lang/String;
     868: aload_0
     869: aload_3
     870: getfield      #37                 // Field org/apache/commons/ssl/PKCS8Key$DecryptResult.keySize:I
     873: putfield      #75                 // Field keySize:I
     876: goto          889
     879: new           #76                 // class java/security/GeneralSecurityException
     882: dup
     883: ldc           #77                 // String KeyFactory.generatePrivate() returned null and didn\'t throw exception!
     885: invokespecial #78                 // Method java/security/GeneralSecurityException."<init>":(Ljava/lang/String;)V
     888: athrow
     889: return
    Exception table:
       from    to  target type
         351   358   361   Class java/lang/Exception
         692   699   702   Class java/lang/Exception
         745   780   783   Class java/lang/Exception

  public boolean isRSA();
    Code:
       0: aload_0
       1: getfield      #72                 // Field isRSA:Z
       4: ireturn

  public boolean isDSA();
    Code:
       0: aload_0
       1: getfield      #71                 // Field isDSA:Z
       4: ireturn

  public java.lang.String getTransformation();
    Code:
       0: aload_0
       1: getfield      #74                 // Field transformation:Ljava/lang/String;
       4: areturn

  public int getKeySize();
    Code:
       0: aload_0
       1: getfield      #75                 // Field keySize:I
       4: ireturn

  public byte[] getDecryptedBytes();
    Code:
       0: aload_0
       1: getfield      #73                 // Field decryptedBytes:[B
       4: areturn

  public java.security.PrivateKey getPrivateKey();
    Code:
       0: aload_0
       1: getfield      #70                 // Field privateKey:Ljava/security/PrivateKey;
       4: areturn

  private static org.apache.commons.ssl.PKCS8Key$DecryptResult opensslDecrypt(org.apache.commons.ssl.PEMItem, char[]) throws java.security.GeneralSecurityException;
    Code:
       0: aload_0
       1: getfield      #27                 // Field org/apache/commons/ssl/PEMItem.cipher:Ljava/lang/String;
       4: astore_2
       5: aload_0
       6: getfield      #79                 // Field org/apache/commons/ssl/PEMItem.mode:Ljava/lang/String;
       9: astore_3
      10: aload_0
      11: getfield      #80                 // Field org/apache/commons/ssl/PEMItem.keySizeInBits:I
      14: istore        4
      16: aload_0
      17: getfield      #81                 // Field org/apache/commons/ssl/PEMItem.iv:[B
      20: astore        5
      22: aload_0
      23: getfield      #82                 // Field org/apache/commons/ssl/PEMItem.des2:Z
      26: istore        6
      28: aload_1
      29: aload         5
      31: iload         4
      33: iload         6
      35: invokestatic  #83                 // Method org/apache/commons/ssl/OpenSSL.deriveKey:([C[BIZ)Lorg/apache/commons/ssl/DerivedKey;
      38: astore        7
      40: aload_2
      41: aload_3
      42: aload         7
      44: iload         6
      46: aconst_null
      47: aload_0
      48: invokevirtual #25                 // Method org/apache/commons/ssl/PEMItem.getDerBytes:()[B
      51: invokestatic  #84                 // Method decrypt:(Ljava/lang/String;Ljava/lang/String;Lorg/apache/commons/ssl/DerivedKey;Z[B[B)Lorg/apache/commons/ssl/PKCS8Key$DecryptResult;
      54: areturn

  public static javax.crypto.Cipher generateCipher(java.lang.String, java.lang.String, org.apache.commons.ssl.DerivedKey, boolean, byte[], boolean) throws java.security.NoSuchAlgorithmException, javax.crypto.NoSuchPaddingException, java.security.InvalidKeyException, java.security.InvalidAlgorithmParameterException;
    Code:
       0: iload_3
       1: ifeq          30
       4: aload_2
       5: getfield      #85                 // Field org/apache/commons/ssl/DerivedKey.key:[B
       8: arraylength
       9: bipush        24
      11: if_icmplt     30
      14: aload_2
      15: getfield      #85                 // Field org/apache/commons/ssl/DerivedKey.key:[B
      18: iconst_0
      19: aload_2
      20: getfield      #85                 // Field org/apache/commons/ssl/DerivedKey.key:[B
      23: bipush        16
      25: bipush        8
      27: invokestatic  #86                 // Method java/lang/System.arraycopy:(Ljava/lang/Object;ILjava/lang/Object;II)V
      30: aload_2
      31: getfield      #85                 // Field org/apache/commons/ssl/DerivedKey.key:[B
      34: arraylength
      35: bipush        8
      37: imul
      38: istore        6
      40: aload_0
      41: invokevirtual #15                 // Method java/lang/String.trim:()Ljava/lang/String;
      44: astore_0
      45: aload_0
      46: invokevirtual #16                 // Method java/lang/String.toUpperCase:()Ljava/lang/String;
      49: astore        7
      51: aload_1
      52: invokevirtual #15                 // Method java/lang/String.trim:()Ljava/lang/String;
      55: invokevirtual #16                 // Method java/lang/String.toUpperCase:()Ljava/lang/String;
      58: astore_1
      59: aload_0
      60: invokestatic  #87                 // Method javax/crypto/Cipher.getInstance:(Ljava/lang/String;)Ljavax/crypto/Cipher;
      63: pop
      64: ldc           #88                 // String PKCS5Padding
      66: astore        8
      68: aload_1
      69: ldc           #89                 // String CFB
      71: invokevirtual #18                 // Method java/lang/String.startsWith:(Ljava/lang/String;)Z
      74: ifne          86
      77: aload_1
      78: ldc           #90                 // String OFB
      80: invokevirtual #18                 // Method java/lang/String.startsWith:(Ljava/lang/String;)Z
      83: ifeq          90
      86: ldc           #91                 // String NoPadding
      88: astore        8
      90: new           #40                 // class java/lang/StringBuffer
      93: dup
      94: invokespecial #41                 // Method java/lang/StringBuffer."<init>":()V
      97: aload_0
      98: invokevirtual #43                 // Method java/lang/StringBuffer.append:(Ljava/lang/String;)Ljava/lang/StringBuffer;
     101: ldc           #92                 // String /
     103: invokevirtual #43                 // Method java/lang/StringBuffer.append:(Ljava/lang/String;)Ljava/lang/StringBuffer;
     106: aload_1
     107: invokevirtual #43                 // Method java/lang/StringBuffer.append:(Ljava/lang/String;)Ljava/lang/StringBuffer;
     110: ldc           #92                 // String /
     112: invokevirtual #43                 // Method java/lang/StringBuffer.append:(Ljava/lang/String;)Ljava/lang/StringBuffer;
     115: aload         8
     117: invokevirtual #43                 // Method java/lang/StringBuffer.append:(Ljava/lang/String;)Ljava/lang/StringBuffer;
     120: invokevirtual #45                 // Method java/lang/StringBuffer.toString:()Ljava/lang/String;
     123: astore        9
     125: aload         7
     127: ldc           #93                 // String RC4
     129: invokevirtual #18                 // Method java/lang/String.startsWith:(Ljava/lang/String;)Z
     132: ifeq          138
     135: aload_0
     136: astore        9
     138: new           #94                 // class javax/crypto/spec/SecretKeySpec
     141: dup
     142: aload_2
     143: getfield      #85                 // Field org/apache/commons/ssl/DerivedKey.key:[B
     146: aload_0
     147: invokespecial #95                 // Method javax/crypto/spec/SecretKeySpec."<init>":([BLjava/lang/String;)V
     150: astore        10
     152: aload         4
     154: ifnull        171
     157: new           #96                 // class javax/crypto/spec/IvParameterSpec
     160: dup
     161: aload         4
     163: invokespecial #97                 // Method javax/crypto/spec/IvParameterSpec."<init>":([B)V
     166: astore        11
     168: goto          195
     171: aload_2
     172: getfield      #98                 // Field org/apache/commons/ssl/DerivedKey.iv:[B
     175: ifnull        192
     178: new           #96                 // class javax/crypto/spec/IvParameterSpec
     181: dup
     182: aload_2
     183: getfield      #98                 // Field org/apache/commons/ssl/DerivedKey.iv:[B
     186: invokespecial #97                 // Method javax/crypto/spec/IvParameterSpec."<init>":([B)V
     189: goto          193
     192: aconst_null
     193: astore        11
     195: aload         9
     197: invokestatic  #87                 // Method javax/crypto/Cipher.getInstance:(Ljava/lang/String;)Ljavax/crypto/Cipher;
     200: astore        12
     202: iconst_1
     203: istore        13
     205: iload         5
     207: ifeq          213
     210: iconst_2
     211: istore        13
     213: aload         7
     215: ldc           #99                 // String RC2
     217: invokevirtual #18                 // Method java/lang/String.startsWith:(Ljava/lang/String;)Z
     220: ifeq          281
     223: aload_1
     224: ldc           #100                // String ECB
     226: invokevirtual #18                 // Method java/lang/String.startsWith:(Ljava/lang/String;)Z
     229: ifne          237
     232: aload         11
     234: ifnonnull     251
     237: new           #101                // class javax/crypto/spec/RC2ParameterSpec
     240: dup
     241: iload         6
     243: invokespecial #102                // Method javax/crypto/spec/RC2ParameterSpec."<init>":(I)V
     246: astore        14
     248: goto          267
     251: new           #101                // class javax/crypto/spec/RC2ParameterSpec
     254: dup
     255: iload         6
     257: aload         11
     259: invokevirtual #103                // Method javax/crypto/spec/IvParameterSpec.getIV:()[B
     262: invokespecial #104                // Method javax/crypto/spec/RC2ParameterSpec."<init>":(I[B)V
     265: astore        14
     267: aload         12
     269: iload         13
     271: aload         10
     273: aload         14
     275: invokevirtual #105                // Method javax/crypto/Cipher.init:(ILjava/security/Key;Ljava/security/spec/AlgorithmParameterSpec;)V
     278: goto          399
     281: aload         7
     283: ldc           #106                // String RC5
     285: invokevirtual #18                 // Method java/lang/String.startsWith:(Ljava/lang/String;)Z
     288: ifeq          357
     291: aload_1
     292: ldc           #100                // String ECB
     294: invokevirtual #18                 // Method java/lang/String.startsWith:(Ljava/lang/String;)Z
     297: ifne          305
     300: aload         11
     302: ifnonnull     323
     305: new           #107                // class javax/crypto/spec/RC5ParameterSpec
     308: dup
     309: bipush        16
     311: bipush        12
     313: bipush        32
     315: invokespecial #108                // Method javax/crypto/spec/RC5ParameterSpec."<init>":(III)V
     318: astore        14
     320: goto          343
     323: new           #107                // class javax/crypto/spec/RC5ParameterSpec
     326: dup
     327: bipush        16
     329: bipush        12
     331: bipush        32
     333: aload         11
     335: invokevirtual #103                // Method javax/crypto/spec/IvParameterSpec.getIV:()[B
     338: invokespecial #109                // Method javax/crypto/spec/RC5ParameterSpec."<init>":(III[B)V
     341: astore        14
     343: aload         12
     345: iload         13
     347: aload         10
     349: aload         14
     351: invokevirtual #105                // Method javax/crypto/Cipher.init:(ILjava/security/Key;Ljava/security/spec/AlgorithmParameterSpec;)V
     354: goto          399
     357: aload_1
     358: ldc           #100                // String ECB
     360: invokevirtual #18                 // Method java/lang/String.startsWith:(Ljava/lang/String;)Z
     363: ifne          376
     366: aload         7
     368: ldc           #93                 // String RC4
     370: invokevirtual #18                 // Method java/lang/String.startsWith:(Ljava/lang/String;)Z
     373: ifeq          388
     376: aload         12
     378: iload         13
     380: aload         10
     382: invokevirtual #110                // Method javax/crypto/Cipher.init:(ILjava/security/Key;)V
     385: goto          399
     388: aload         12
     390: iload         13
     392: aload         10
     394: aload         11
     396: invokevirtual #105                // Method javax/crypto/Cipher.init:(ILjava/security/Key;Ljava/security/spec/AlgorithmParameterSpec;)V
     399: aload         12
     401: areturn

  public static org.apache.commons.ssl.PKCS8Key$DecryptResult decrypt(java.lang.String, java.lang.String, org.apache.commons.ssl.DerivedKey, boolean, byte[], byte[]) throws java.security.NoSuchAlgorithmException, javax.crypto.NoSuchPaddingException, java.security.InvalidKeyException, java.security.InvalidAlgorithmParameterException, javax.crypto.IllegalBlockSizeException, javax.crypto.BadPaddingException;
    Code:
       0: aload_0
       1: aload_1
       2: aload_2
       3: iload_3
       4: aload         4
       6: iconst_1
       7: invokestatic  #111                // Method generateCipher:(Ljava/lang/String;Ljava/lang/String;Lorg/apache/commons/ssl/DerivedKey;Z[BZ)Ljavax/crypto/Cipher;
      10: astore        6
      12: aload         6
      14: invokevirtual #112                // Method javax/crypto/Cipher.getAlgorithm:()Ljava/lang/String;
      17: astore        7
      19: aload_2
      20: getfield      #85                 // Field org/apache/commons/ssl/DerivedKey.key:[B
      23: arraylength
      24: bipush        8
      26: imul
      27: istore        8
      29: aload         6
      31: aload         5
      33: invokevirtual #113                // Method javax/crypto/Cipher.doFinal:([B)[B
      36: astore        9
      38: new           #5                  // class org/apache/commons/ssl/PKCS8Key$DecryptResult
      41: dup
      42: aload         7
      44: iload         8
      46: aload         9
      48: invokespecial #7                  // Method org/apache/commons/ssl/PKCS8Key$DecryptResult."<init>":(Ljava/lang/String;I[B)V
      51: areturn

  private static org.apache.commons.ssl.PKCS8Key$DecryptResult decryptPKCS8(org.apache.commons.ssl.ASN1Structure, char[]) throws java.security.GeneralSecurityException;
    Code:
       0: iconst_1
       1: istore_2
       2: iconst_0
       3: istore_3
       4: iconst_0
       5: istore        4
       7: iconst_0
       8: istore        5
      10: aconst_null
      11: astore        6
      13: aconst_null
      14: astore        7
      16: iconst_m1
      17: istore        8
      19: ldc           #114                // String CBC
      21: astore        9
      23: iconst_0
      24: istore        10
      26: aload_0
      27: getfield      #48                 // Field org/apache/commons/ssl/ASN1Structure.oid1:Ljava/lang/String;
      30: astore        11
      32: aload         11
      34: ldc           #115                // String 1.2.840.113549.1.12.
      36: invokevirtual #18                 // Method java/lang/String.startsWith:(Ljava/lang/String;)Z
      39: ifeq          274
      42: iconst_1
      43: istore        4
      45: aload         11
      47: ldc           #115                // String 1.2.840.113549.1.12.
      49: invokevirtual #51                 // Method java/lang/String.length:()I
      52: invokevirtual #52                 // Method java/lang/String.substring:(I)Ljava/lang/String;
      55: astore        11
      57: aload         11
      59: ldc           #116                // String 1.1
      61: invokevirtual #29                 // Method java/lang/String.equals:(Ljava/lang/Object;)Z
      64: ifne          77
      67: aload         11
      69: ldc           #117                // String 1.1.
      71: invokevirtual #18                 // Method java/lang/String.startsWith:(Ljava/lang/String;)Z
      74: ifeq          93
      77: ldc           #118                // String SHA1
      79: astore        7
      81: ldc           #93                 // String RC4
      83: astore        6
      85: sipush        128
      88: istore        8
      90: goto          578
      93: aload         11
      95: ldc           #119                // String 1.2
      97: invokevirtual #29                 // Method java/lang/String.equals:(Ljava/lang/Object;)Z
     100: ifne          113
     103: aload         11
     105: ldc           #120                // String 1.2.
     107: invokevirtual #18                 // Method java/lang/String.startsWith:(Ljava/lang/String;)Z
     110: ifeq          128
     113: ldc           #118                // String SHA1
     115: astore        7
     117: ldc           #93                 // String RC4
     119: astore        6
     121: bipush        40
     123: istore        8
     125: goto          578
     128: aload         11
     130: ldc           #121                // String 1.3
     132: invokevirtual #29                 // Method java/lang/String.equals:(Ljava/lang/Object;)Z
     135: ifne          148
     138: aload         11
     140: ldc           #122                // String 1.3.
     142: invokevirtual #18                 // Method java/lang/String.startsWith:(Ljava/lang/String;)Z
     145: ifeq          164
     148: ldc           #118                // String SHA1
     150: astore        7
     152: ldc           #123                // String DESede
     154: astore        6
     156: sipush        192
     159: istore        8
     161: goto          578
     164: aload         11
     166: ldc           #124                // String 1.4
     168: invokevirtual #29                 // Method java/lang/String.equals:(Ljava/lang/Object;)Z
     171: ifne          184
     174: aload         11
     176: ldc           #125                // String 1.4.
     178: invokevirtual #18                 // Method java/lang/String.startsWith:(Ljava/lang/String;)Z
     181: ifeq          203
     184: ldc           #118                // String SHA1
     186: astore        7
     188: ldc           #123                // String DESede
     190: astore        6
     192: sipush        192
     195: istore        8
     197: iconst_1
     198: istore        5
     200: goto          578
     203: aload         11
     205: ldc           #126                // String 1.5
     207: invokevirtual #29                 // Method java/lang/String.equals:(Ljava/lang/Object;)Z
     210: ifne          223
     213: aload         11
     215: ldc           #127                // String 1.5.
     217: invokevirtual #18                 // Method java/lang/String.startsWith:(Ljava/lang/String;)Z
     220: ifeq          239
     223: ldc           #118                // String SHA1
     225: astore        7
     227: ldc           #99                 // String RC2
     229: astore        6
     231: sipush        128
     234: istore        8
     236: goto          578
     239: aload         11
     241: ldc           #128                // String 1.6
     243: invokevirtual #29                 // Method java/lang/String.equals:(Ljava/lang/Object;)Z
     246: ifne          259
     249: aload         11
     251: ldc           #129                // String 1.6.
     253: invokevirtual #18                 // Method java/lang/String.startsWith:(Ljava/lang/String;)Z
     256: ifeq          578
     259: ldc           #118                // String SHA1
     261: astore        7
     263: ldc           #99                 // String RC2
     265: astore        6
     267: bipush        40
     269: istore        8
     271: goto          578
     274: aload         11
     276: ldc           #130                // String 1.2.840.113549.1.5.
     278: invokevirtual #18                 // Method java/lang/String.startsWith:(Ljava/lang/String;)Z
     281: ifeq          578
     284: aload         11
     286: ldc           #130                // String 1.2.840.113549.1.5.
     288: invokevirtual #51                 // Method java/lang/String.length:()I
     291: invokevirtual #52                 // Method java/lang/String.substring:(I)Ljava/lang/String;
     294: astore        11
     296: aload         11
     298: ldc           #53                 // String 1
     300: invokevirtual #29                 // Method java/lang/String.equals:(Ljava/lang/Object;)Z
     303: ifne          316
     306: aload         11
     308: ldc           #54                 // String 1.
     310: invokevirtual #18                 // Method java/lang/String.startsWith:(Ljava/lang/String;)Z
     313: ifeq          331
     316: ldc           #131                // String MD2
     318: astore        7
     320: ldc           #132                // String DES
     322: astore        6
     324: bipush        64
     326: istore        8
     328: goto          578
     331: aload         11
     333: ldc           #55                 // String 3
     335: invokevirtual #29                 // Method java/lang/String.equals:(Ljava/lang/Object;)Z
     338: ifne          351
     341: aload         11
     343: ldc           #56                 // String 3.
     345: invokevirtual #18                 // Method java/lang/String.startsWith:(Ljava/lang/String;)Z
     348: ifeq          366
     351: ldc           #133                // String MD5
     353: astore        7
     355: ldc           #132                // String DES
     357: astore        6
     359: bipush        64
     361: istore        8
     363: goto          578
     366: aload         11
     368: ldc           #134                // String 4
     370: invokevirtual #29                 // Method java/lang/String.equals:(Ljava/lang/Object;)Z
     373: ifne          386
     376: aload         11
     378: ldc           #135                // String 4.
     380: invokevirtual #18                 // Method java/lang/String.startsWith:(Ljava/lang/String;)Z
     383: ifeq          401
     386: ldc           #131                // String MD2
     388: astore        7
     390: ldc           #99                 // String RC2
     392: astore        6
     394: bipush        64
     396: istore        8
     398: goto          578
     401: aload         11
     403: ldc           #136                // String 6
     405: invokevirtual #29                 // Method java/lang/String.equals:(Ljava/lang/Object;)Z
     408: ifne          421
     411: aload         11
     413: ldc           #137                // String 6.
     415: invokevirtual #18                 // Method java/lang/String.startsWith:(Ljava/lang/String;)Z
     418: ifeq          436
     421: ldc           #133                // String MD5
     423: astore        7
     425: ldc           #99                 // String RC2
     427: astore        6
     429: bipush        64
     431: istore        8
     433: goto          578
     436: aload         11
     438: ldc           #138                // String 10
     440: invokevirtual #29                 // Method java/lang/String.equals:(Ljava/lang/Object;)Z
     443: ifne          456
     446: aload         11
     448: ldc           #139                // String 10.
     450: invokevirtual #18                 // Method java/lang/String.startsWith:(Ljava/lang/String;)Z
     453: ifeq          471
     456: ldc           #118                // String SHA1
     458: astore        7
     460: ldc           #132                // String DES
     462: astore        6
     464: bipush        64
     466: istore        8
     468: goto          578
     471: aload         11
     473: ldc           #140                // String 11
     475: invokevirtual #29                 // Method java/lang/String.equals:(Ljava/lang/Object;)Z
     478: ifne          491
     481: aload         11
     483: ldc           #141                // String 11.
     485: invokevirtual #18                 // Method java/lang/String.startsWith:(Ljava/lang/String;)Z
     488: ifeq          506
     491: ldc           #118                // String SHA1
     493: astore        7
     495: ldc           #99                 // String RC2
     497: astore        6
     499: bipush        64
     501: istore        8
     503: goto          578
     506: aload         11
     508: ldc           #142                // String 12
     510: invokevirtual #29                 // Method java/lang/String.equals:(Ljava/lang/Object;)Z
     513: ifne          526
     516: aload         11
     518: ldc           #143                // String 12.
     520: invokevirtual #18                 // Method java/lang/String.startsWith:(Ljava/lang/String;)Z
     523: ifeq          531
     526: iconst_1
     527: istore_3
     528: goto          578
     531: aload         11
     533: ldc           #144                // String 13
     535: invokevirtual #29                 // Method java/lang/String.equals:(Ljava/lang/Object;)Z
     538: ifne          551
     541: aload         11
     543: ldc           #145                // String 13.
     545: invokevirtual #18                 // Method java/lang/String.startsWith:(Ljava/lang/String;)Z
     548: ifeq          556
     551: iconst_1
     552: istore_3
     553: goto          578
     556: aload         11
     558: ldc           #146                // String 14
     560: invokevirtual #29                 // Method java/lang/String.equals:(Ljava/lang/Object;)Z
     563: ifne          576
     566: aload         11
     568: ldc           #147                // String 14.
     570: invokevirtual #18                 // Method java/lang/String.startsWith:(Ljava/lang/String;)Z
     573: ifeq          578
     576: iconst_1
     577: istore_3
     578: iload_3
     579: ifeq          1274
     582: iconst_0
     583: istore_2
     584: ldc           #148                // String HmacSHA1
     586: astore        7
     588: aload_0
     589: getfield      #149                // Field org/apache/commons/ssl/ASN1Structure.oid2:Ljava/lang/String;
     592: astore        11
     594: aload_0
     595: getfield      #150                // Field org/apache/commons/ssl/ASN1Structure.oid3:Ljava/lang/String;
     598: ifnull        607
     601: aload_0
     602: getfield      #150                // Field org/apache/commons/ssl/ASN1Structure.oid3:Ljava/lang/String;
     605: astore        11
     607: aload         11
     609: ldc           #151                // String 1.3.6.1.4.1.3029.1.2
     611: invokevirtual #18                 // Method java/lang/String.startsWith:(Ljava/lang/String;)Z
     614: ifeq          633
     617: ldc           #152                // String Blowfish
     619: astore        6
     621: ldc           #114                // String CBC
     623: astore        9
     625: sipush        128
     628: istore        8
     630: goto          1274
     633: aload         11
     635: ldc           #153                // String 1.3.14.3.2.
     637: invokevirtual #18                 // Method java/lang/String.startsWith:(Ljava/lang/String;)Z
     640: ifeq          853
     643: aload         11
     645: ldc           #153                // String 1.3.14.3.2.
     647: invokevirtual #51                 // Method java/lang/String.length:()I
     650: invokevirtual #52                 // Method java/lang/String.substring:(I)Ljava/lang/String;
     653: astore        11
     655: aload         11
     657: ldc           #136                // String 6
     659: invokevirtual #29                 // Method java/lang/String.equals:(Ljava/lang/Object;)Z
     662: ifne          675
     665: aload         11
     667: ldc           #137                // String 6.
     669: invokevirtual #18                 // Method java/lang/String.startsWith:(Ljava/lang/String;)Z
     672: ifeq          690
     675: ldc           #132                // String DES
     677: astore        6
     679: ldc           #100                // String ECB
     681: astore        9
     683: bipush        64
     685: istore        8
     687: goto          1274
     690: aload         11
     692: ldc           #154                // String 7
     694: invokevirtual #29                 // Method java/lang/String.equals:(Ljava/lang/Object;)Z
     697: ifne          710
     700: aload         11
     702: ldc           #155                // String 7.
     704: invokevirtual #18                 // Method java/lang/String.startsWith:(Ljava/lang/String;)Z
     707: ifeq          725
     710: ldc           #132                // String DES
     712: astore        6
     714: ldc           #114                // String CBC
     716: astore        9
     718: bipush        64
     720: istore        8
     722: goto          1274
     725: aload         11
     727: ldc           #156                // String 8
     729: invokevirtual #29                 // Method java/lang/String.equals:(Ljava/lang/Object;)Z
     732: ifne          745
     735: aload         11
     737: ldc           #157                // String 8.
     739: invokevirtual #18                 // Method java/lang/String.startsWith:(Ljava/lang/String;)Z
     742: ifeq          760
     745: ldc           #132                // String DES
     747: astore        6
     749: ldc           #90                 // String OFB
     751: astore        9
     753: bipush        64
     755: istore        8
     757: goto          1274
     760: aload         11
     762: ldc           #158                // String 9
     764: invokevirtual #29                 // Method java/lang/String.equals:(Ljava/lang/Object;)Z
     767: ifne          780
     770: aload         11
     772: ldc           #159                // String 9.
     774: invokevirtual #18                 // Method java/lang/String.startsWith:(Ljava/lang/String;)Z
     777: ifeq          795
     780: ldc           #132                // String DES
     782: astore        6
     784: ldc           #89                 // String CFB
     786: astore        9
     788: bipush        64
     790: istore        8
     792: goto          1274
     795: aload         11
     797: ldc           #160                // String 17
     799: invokevirtual #29                 // Method java/lang/String.equals:(Ljava/lang/Object;)Z
     802: ifne          815
     805: aload         11
     807: ldc           #161                // String 17.
     809: invokevirtual #18                 // Method java/lang/String.startsWith:(Ljava/lang/String;)Z
     812: ifeq          1274
     815: ldc           #123                // String DESede
     817: astore        6
     819: ldc           #114                // String CBC
     821: astore        9
     823: sipush        192
     826: istore        8
     828: aload_0
     829: getfield      #162                // Field org/apache/commons/ssl/ASN1Structure.iv:[B
     832: invokestatic  #163                // Method allZeroes:([B)Z
     835: ifeq          1274
     838: ldc           #100                // String ECB
     840: astore        9
     842: iconst_1
     843: istore        5
     845: aload_0
     846: aconst_null
     847: putfield      #162                // Field org/apache/commons/ssl/ASN1Structure.iv:[B
     850: goto          1274
     853: aload         11
     855: ldc           #164                // String 2.16.840.1.101.3.4.1.
     857: invokevirtual #18                 // Method java/lang/String.startsWith:(Ljava/lang/String;)Z
     860: ifeq          1115
     863: ldc           #165                // String AES
     865: astore        6
     867: aload_0
     868: getfield      #162                // Field org/apache/commons/ssl/ASN1Structure.iv:[B
     871: ifnonnull     879
     874: sipush        128
     877: istore        10
     879: aload         11
     881: ldc           #164                // String 2.16.840.1.101.3.4.1.
     883: invokevirtual #51                 // Method java/lang/String.length:()I
     886: invokevirtual #52                 // Method java/lang/String.substring:(I)Ljava/lang/String;
     889: astore        11
     891: aload         11
     893: bipush        46
     895: invokevirtual #166                // Method java/lang/String.indexOf:(I)I
     898: istore        12
     900: iload         12
     902: iflt          921
     905: aload         11
     907: iconst_0
     908: iload         12
     910: invokevirtual #167                // Method java/lang/String.substring:(II)Ljava/lang/String;
     913: invokestatic  #168                // Method java/lang/Integer.parseInt:(Ljava/lang/String;)I
     916: istore        13
     918: goto          928
     921: aload         11
     923: invokestatic  #168                // Method java/lang/Integer.parseInt:(Ljava/lang/String;)I
     926: istore        13
     928: iload         13
     930: bipush        10
     932: irem
     933: tableswitch   { // 1 to 4
                     1: 964
                     2: 971
                     3: 978
                     4: 985
               default: 992
          }
     964: ldc           #100                // String ECB
     966: astore        9
     968: goto          1020
     971: ldc           #114                // String CBC
     973: astore        9
     975: goto          1020
     978: ldc           #90                 // String OFB
     980: astore        9
     982: goto          1020
     985: ldc           #89                 // String CFB
     987: astore        9
     989: goto          1020
     992: new           #169                // class java/lang/RuntimeException
     995: dup
     996: new           #40                 // class java/lang/StringBuffer
     999: dup
    1000: invokespecial #41                 // Method java/lang/StringBuffer."<init>":()V
    1003: ldc           #170                // String Unknown AES final digit:
    1005: invokevirtual #43                 // Method java/lang/StringBuffer.append:(Ljava/lang/String;)Ljava/lang/StringBuffer;
    1008: iload         13
    1010: invokevirtual #171                // Method java/lang/StringBuffer.append:(I)Ljava/lang/StringBuffer;
    1013: invokevirtual #45                 // Method java/lang/StringBuffer.toString:()Ljava/lang/String;
    1016: invokespecial #172                // Method java/lang/RuntimeException."<init>":(Ljava/lang/String;)V
    1019: athrow
    1020: iload         13
    1022: bipush        10
    1024: idiv
    1025: tableswitch   { // 0 to 4
                     0: 1060
                     1: 1084
                     2: 1068
                     3: 1084
                     4: 1076
               default: 1084
          }
    1060: sipush        128
    1063: istore        8
    1065: goto          1112
    1068: sipush        192
    1071: istore        8
    1073: goto          1112
    1076: sipush        256
    1079: istore        8
    1081: goto          1112
    1084: new           #169                // class java/lang/RuntimeException
    1087: dup
    1088: new           #40                 // class java/lang/StringBuffer
    1091: dup
    1092: invokespecial #41                 // Method java/lang/StringBuffer."<init>":()V
    1095: ldc           #170                // String Unknown AES final digit:
    1097: invokevirtual #43                 // Method java/lang/StringBuffer.append:(Ljava/lang/String;)Ljava/lang/StringBuffer;
    1100: iload         13
    1102: invokevirtual #171                // Method java/lang/StringBuffer.append:(I)Ljava/lang/StringBuffer;
    1105: invokevirtual #45                 // Method java/lang/StringBuffer.toString:()Ljava/lang/String;
    1108: invokespecial #172                // Method java/lang/RuntimeException."<init>":(Ljava/lang/String;)V
    1111: athrow
    1112: goto          1274
    1115: aload         11
    1117: ldc           #173                // String 1.2.840.113549.3.
    1119: invokevirtual #18                 // Method java/lang/String.startsWith:(Ljava/lang/String;)Z
    1122: ifeq          1274
    1125: aload         11
    1127: ldc           #173                // String 1.2.840.113549.3.
    1129: invokevirtual #51                 // Method java/lang/String.length:()I
    1132: invokevirtual #52                 // Method java/lang/String.substring:(I)Ljava/lang/String;
    1135: astore        11
    1137: aload         11
    1139: ldc           #174                // String 2
    1141: invokevirtual #29                 // Method java/lang/String.equals:(Ljava/lang/Object;)Z
    1144: ifne          1157
    1147: aload         11
    1149: ldc           #175                // String 2.
    1151: invokevirtual #18                 // Method java/lang/String.startsWith:(Ljava/lang/String;)Z
    1154: ifeq          1173
    1157: ldc           #99                 // String RC2
    1159: astore        6
    1161: aload_0
    1162: getfield      #176                // Field org/apache/commons/ssl/ASN1Structure.keySize:I
    1165: bipush        8
    1167: imul
    1168: istore        8
    1170: goto          1274
    1173: aload         11
    1175: ldc           #134                // String 4
    1177: invokevirtual #29                 // Method java/lang/String.equals:(Ljava/lang/Object;)Z
    1180: ifne          1193
    1183: aload         11
    1185: ldc           #135                // String 4.
    1187: invokevirtual #18                 // Method java/lang/String.startsWith:(Ljava/lang/String;)Z
    1190: ifeq          1209
    1193: ldc           #93                 // String RC4
    1195: astore        6
    1197: aload_0
    1198: getfield      #176                // Field org/apache/commons/ssl/ASN1Structure.keySize:I
    1201: bipush        8
    1203: imul
    1204: istore        8
    1206: goto          1274
    1209: aload         11
    1211: ldc           #154                // String 7
    1213: invokevirtual #29                 // Method java/lang/String.equals:(Ljava/lang/Object;)Z
    1216: ifne          1229
    1219: aload         11
    1221: ldc           #155                // String 7.
    1223: invokevirtual #18                 // Method java/lang/String.startsWith:(Ljava/lang/String;)Z
    1226: ifeq          1241
    1229: ldc           #123                // String DESede
    1231: astore        6
    1233: sipush        192
    1236: istore        8
    1238: goto          1274
    1241: aload         11
    1243: ldc           #158                // String 9
    1245: invokevirtual #29                 // Method java/lang/String.equals:(Ljava/lang/Object;)Z
    1248: ifne          1261
    1251: aload         11
    1253: ldc           #159                // String 9.
    1255: invokevirtual #18                 // Method java/lang/String.startsWith:(Ljava/lang/String;)Z
    1258: ifeq          1274
    1261: aload_0
    1262: getfield      #176                // Field org/apache/commons/ssl/ASN1Structure.keySize:I
    1265: bipush        8
    1267: imul
    1268: istore        8
    1270: ldc           #106                // String RC5
    1272: astore        6
    1274: aload         6
    1276: ifnull        1284
    1279: aload         7
    1281: ifnonnull     1331
    1284: new           #22                 // class org/apache/commons/ssl/ProbablyNotPKCS8Exception
    1287: dup
    1288: new           #40                 // class java/lang/StringBuffer
    1291: dup
    1292: invokespecial #41                 // Method java/lang/StringBuffer."<init>":()V
    1295: ldc           #177                // String Unsupported PKCS8 format. oid1=[
    1297: invokevirtual #43                 // Method java/lang/StringBuffer.append:(Ljava/lang/String;)Ljava/lang/StringBuffer;
    1300: aload_0
    1301: getfield      #48                 // Field org/apache/commons/ssl/ASN1Structure.oid1:Ljava/lang/String;
    1304: invokevirtual #43                 // Method java/lang/StringBuffer.append:(Ljava/lang/String;)Ljava/lang/StringBuffer;
    1307: ldc           #178                // String ], oid2=[
    1309: invokevirtual #43                 // Method java/lang/StringBuffer.append:(Ljava/lang/String;)Ljava/lang/StringBuffer;
    1312: aload_0
    1313: getfield      #149                // Field org/apache/commons/ssl/ASN1Structure.oid2:Ljava/lang/String;
    1316: invokevirtual #43                 // Method java/lang/StringBuffer.append:(Ljava/lang/String;)Ljava/lang/StringBuffer;
    1319: ldc           #179                // String ]
    1321: invokevirtual #43                 // Method java/lang/StringBuffer.append:(Ljava/lang/String;)Ljava/lang/StringBuffer;
    1324: invokevirtual #45                 // Method java/lang/StringBuffer.toString:()Ljava/lang/String;
    1327: invokespecial #24                 // Method org/apache/commons/ssl/ProbablyNotPKCS8Exception."<init>":(Ljava/lang/String;)V
    1330: athrow
    1331: aload_0
    1332: getfield      #162                // Field org/apache/commons/ssl/ASN1Structure.iv:[B
    1335: ifnonnull     1342
    1338: bipush        64
    1340: istore        10
    1342: aload_0
    1343: getfield      #180                // Field org/apache/commons/ssl/ASN1Structure.salt:[B
    1346: astore        12
    1348: aload_0
    1349: getfield      #181                // Field org/apache/commons/ssl/ASN1Structure.iterationCount:I
    1352: istore        13
    1354: aload_1
    1355: arraylength
    1356: newarray       byte
    1358: astore        14
    1360: iconst_0
    1361: istore        15
    1363: iload         15
    1365: aload         14
    1367: arraylength
    1368: if_icmpge     1387
    1371: aload         14
    1373: iload         15
    1375: aload_1
    1376: iload         15
    1378: caload
    1379: i2b
    1380: bastore
    1381: iinc          15, 1
    1384: goto          1363
    1387: iload         4
    1389: ifeq          1418
    1392: aload         7
    1394: invokestatic  #182                // Method java/security/MessageDigest.getInstance:(Ljava/lang/String;)Ljava/security/MessageDigest;
    1397: astore        16
    1399: aload_1
    1400: aload         12
    1402: iload         13
    1404: iload         8
    1406: iload         10
    1408: aload         16
    1410: invokestatic  #183                // Method deriveKeyPKCS12:([C[BIIILjava/security/MessageDigest;)Lorg/apache/commons/ssl/DerivedKey;
    1413: astore        15
    1415: goto          1473
    1418: iload_2
    1419: ifeq          1449
    1422: aload         7
    1424: invokestatic  #182                // Method java/security/MessageDigest.getInstance:(Ljava/lang/String;)Ljava/security/MessageDigest;
    1427: astore        16
    1429: aload         14
    1431: aload         12
    1433: iload         13
    1435: iload         8
    1437: iload         10
    1439: aload         16
    1441: invokestatic  #184                // Method deriveKeyV1:([B[BIIILjava/security/MessageDigest;)Lorg/apache/commons/ssl/DerivedKey;
    1444: astore        15
    1446: goto          1473
    1449: aload         7
    1451: invokestatic  #185                // Method javax/crypto/Mac.getInstance:(Ljava/lang/String;)Ljavax/crypto/Mac;
    1454: astore        16
    1456: aload         14
    1458: aload         12
    1460: iload         13
    1462: iload         8
    1464: iload         10
    1466: aload         16
    1468: invokestatic  #186                // Method deriveKeyV2:([B[BIIILjavax/crypto/Mac;)Lorg/apache/commons/ssl/DerivedKey;
    1471: astore        15
    1473: aload         6
    1475: aload         9
    1477: aload         15
    1479: iload         5
    1481: aload_0
    1482: getfield      #162                // Field org/apache/commons/ssl/ASN1Structure.iv:[B
    1485: aload_0
    1486: getfield      #187                // Field org/apache/commons/ssl/ASN1Structure.bigPayload:[B
    1489: invokestatic  #84                 // Method decrypt:(Ljava/lang/String;Ljava/lang/String;Lorg/apache/commons/ssl/DerivedKey;Z[B[B)Lorg/apache/commons/ssl/PKCS8Key$DecryptResult;
    1492: areturn

  public static org.apache.commons.ssl.DerivedKey deriveKeyV1(byte[], byte[], int, int, int, java.security.MessageDigest);
    Code:
       0: iload_3
       1: bipush        8
       3: idiv
       4: istore        6
       6: iload         4
       8: bipush        8
      10: idiv
      11: istore        7
      13: aload         5
      15: invokevirtual #188                // Method java/security/MessageDigest.reset:()V
      18: aload         5
      20: aload_0
      21: invokevirtual #189                // Method java/security/MessageDigest.update:([B)V
      24: aload         5
      26: aload_1
      27: invokevirtual #190                // Method java/security/MessageDigest.digest:([B)[B
      30: astore        8
      32: iconst_1
      33: istore        9
      35: iload         9
      37: iload_2
      38: if_icmpge     56
      41: aload         5
      43: aload         8
      45: invokevirtual #190                // Method java/security/MessageDigest.digest:([B)[B
      48: astore        8
      50: iinc          9, 1
      53: goto          35
      56: iload         6
      58: newarray       byte
      60: astore        9
      62: iload         7
      64: newarray       byte
      66: astore        10
      68: aload         8
      70: iconst_0
      71: aload         9
      73: iconst_0
      74: aload         9
      76: arraylength
      77: invokestatic  #86                 // Method java/lang/System.arraycopy:(Ljava/lang/Object;ILjava/lang/Object;II)V
      80: aload         8
      82: aload         9
      84: arraylength
      85: aload         10
      87: iconst_0
      88: aload         10
      90: arraylength
      91: invokestatic  #86                 // Method java/lang/System.arraycopy:(Ljava/lang/Object;ILjava/lang/Object;II)V
      94: new           #191                // class org/apache/commons/ssl/DerivedKey
      97: dup
      98: aload         9
     100: aload         10
     102: invokespecial #192                // Method org/apache/commons/ssl/DerivedKey."<init>":([B[B)V
     105: areturn

  public static org.apache.commons.ssl.DerivedKey deriveKeyPKCS12(char[], byte[], int, int, int, java.security.MessageDigest);
    Code:
       0: aload_0
       1: arraylength
       2: ifle          63
       5: aload_0
       6: arraylength
       7: iconst_1
       8: iadd
       9: iconst_2
      10: imul
      11: newarray       byte
      13: astore        6
      15: iconst_0
      16: istore        7
      18: iload         7
      20: aload_0
      21: arraylength
      22: if_icmpge     60
      25: aload         6
      27: iload         7
      29: iconst_2
      30: imul
      31: aload_0
      32: iload         7
      34: caload
      35: bipush        8
      37: iushr
      38: i2b
      39: bastore
      40: aload         6
      42: iload         7
      44: iconst_2
      45: imul
      46: iconst_1
      47: iadd
      48: aload_0
      49: iload         7
      51: caload
      52: i2b
      53: bastore
      54: iinc          7, 1
      57: goto          18
      60: goto          68
      63: iconst_0
      64: newarray       byte
      66: astore        6
      68: iload_3
      69: bipush        8
      71: idiv
      72: istore        7
      74: iload         4
      76: bipush        8
      78: idiv
      79: istore        8
      81: iconst_1
      82: iload         7
      84: aload_1
      85: aload         6
      87: iload_2
      88: aload         5
      90: invokestatic  #193                // Method pkcs12:(II[B[BILjava/security/MessageDigest;)[B
      93: astore        9
      95: iconst_2
      96: iload         8
      98: aload_1
      99: aload         6
     101: iload_2
     102: aload         5
     104: invokestatic  #193                // Method pkcs12:(II[B[BILjava/security/MessageDigest;)[B
     107: astore        10
     109: new           #191                // class org/apache/commons/ssl/DerivedKey
     112: dup
     113: aload         9
     115: aload         10
     117: invokespecial #192                // Method org/apache/commons/ssl/DerivedKey."<init>":([B[B)V
     120: areturn

  private static byte[] pkcs12(int, int, byte[], byte[], int, java.security.MessageDigest);
    Code:
       0: aload         5
       2: invokevirtual #194                // Method java/security/MessageDigest.getDigestLength:()I
       5: istore        6
       7: bipush        64
       9: istore        7
      11: aload         5
      13: invokevirtual #188                // Method java/security/MessageDigest.reset:()V
      16: iload         7
      18: newarray       byte
      20: astore        8
      22: iload_1
      23: newarray       byte
      25: astore        9
      27: iconst_0
      28: istore        10
      30: iload         10
      32: aload         8
      34: arraylength
      35: if_icmpeq     51
      38: aload         8
      40: iload         10
      42: iload_0
      43: i2b
      44: bastore
      45: iinc          10, 1
      48: goto          30
      51: aload_2
      52: ifnull        109
      55: aload_2
      56: arraylength
      57: ifeq          109
      60: iload         7
      62: aload_2
      63: arraylength
      64: iload         7
      66: iadd
      67: iconst_1
      68: isub
      69: iload         7
      71: idiv
      72: imul
      73: newarray       byte
      75: astore        10
      77: iconst_0
      78: istore        11
      80: iload         11
      82: aload         10
      84: arraylength
      85: if_icmpeq     106
      88: aload         10
      90: iload         11
      92: aload_2
      93: iload         11
      95: aload_2
      96: arraylength
      97: irem
      98: baload
      99: bastore
     100: iinc          11, 1
     103: goto          80
     106: goto          114
     109: iconst_0
     110: newarray       byte
     112: astore        10
     114: aload_3
     115: ifnull        172
     118: aload_3
     119: arraylength
     120: ifeq          172
     123: iload         7
     125: aload_3
     126: arraylength
     127: iload         7
     129: iadd
     130: iconst_1
     131: isub
     132: iload         7
     134: idiv
     135: imul
     136: newarray       byte
     138: astore        11
     140: iconst_0
     141: istore        12
     143: iload         12
     145: aload         11
     147: arraylength
     148: if_icmpeq     169
     151: aload         11
     153: iload         12
     155: aload_3
     156: iload         12
     158: aload_3
     159: arraylength
     160: irem
     161: baload
     162: bastore
     163: iinc          12, 1
     166: goto          143
     169: goto          177
     172: iconst_0
     173: newarray       byte
     175: astore        11
     177: aload         10
     179: arraylength
     180: aload         11
     182: arraylength
     183: iadd
     184: newarray       byte
     186: astore        12
     188: aload         10
     190: iconst_0
     191: aload         12
     193: iconst_0
     194: aload         10
     196: arraylength
     197: invokestatic  #86                 // Method java/lang/System.arraycopy:(Ljava/lang/Object;ILjava/lang/Object;II)V
     200: aload         11
     202: iconst_0
     203: aload         12
     205: aload         10
     207: arraylength
     208: aload         11
     210: arraylength
     211: invokestatic  #86                 // Method java/lang/System.arraycopy:(Ljava/lang/Object;ILjava/lang/Object;II)V
     214: iload         7
     216: newarray       byte
     218: astore        13
     220: iload_1
     221: iload         6
     223: iadd
     224: iconst_1
     225: isub
     226: iload         6
     228: idiv
     229: istore        14
     231: iconst_1
     232: istore        15
     234: iload         15
     236: iload         14
     238: if_icmpgt     514
     241: aload         5
     243: aload         8
     245: invokevirtual #189                // Method java/security/MessageDigest.update:([B)V
     248: aload         5
     250: aload         12
     252: invokevirtual #190                // Method java/security/MessageDigest.digest:([B)[B
     255: astore        16
     257: iconst_1
     258: istore        17
     260: iload         17
     262: iload         4
     264: if_icmpeq     282
     267: aload         5
     269: aload         16
     271: invokevirtual #190                // Method java/security/MessageDigest.digest:([B)[B
     274: astore        16
     276: iinc          17, 1
     279: goto          260
     282: iconst_0
     283: istore        17
     285: iload         17
     287: aload         13
     289: arraylength
     290: if_icmpeq     313
     293: aload         13
     295: iload         17
     297: aload         16
     299: iload         17
     301: aload         16
     303: arraylength
     304: irem
     305: baload
     306: bastore
     307: iinc          17, 1
     310: goto          285
     313: iconst_0
     314: istore        17
     316: iload         17
     318: aload         12
     320: arraylength
     321: iload         7
     323: idiv
     324: if_icmpge     454
     327: iload         17
     329: iload         7
     331: imul
     332: istore        18
     334: aload         13
     336: arraylength
     337: iconst_1
     338: isub
     339: istore        19
     341: aload         13
     343: iload         19
     345: baload
     346: sipush        255
     349: iand
     350: aload         12
     352: iload         18
     354: iload         19
     356: iadd
     357: baload
     358: sipush        255
     361: iand
     362: iadd
     363: iconst_1
     364: iadd
     365: istore        20
     367: aload         12
     369: iload         18
     371: iload         19
     373: iadd
     374: iload         20
     376: i2b
     377: bastore
     378: iload         20
     380: bipush        8
     382: iushr
     383: istore        20
     385: aload         13
     387: arraylength
     388: iconst_2
     389: isub
     390: istore        21
     392: iload         21
     394: iflt          448
     397: iload         20
     399: aload         13
     401: iload         21
     403: baload
     404: sipush        255
     407: iand
     408: aload         12
     410: iload         18
     412: iload         21
     414: iadd
     415: baload
     416: sipush        255
     419: iand
     420: iadd
     421: iadd
     422: istore        20
     424: aload         12
     426: iload         18
     428: iload         21
     430: iadd
     431: iload         20
     433: i2b
     434: bastore
     435: iload         20
     437: bipush        8
     439: iushr
     440: istore        20
     442: iinc          21, -1
     445: goto          392
     448: iinc          17, 1
     451: goto          316
     454: iload         15
     456: iload         14
     458: if_icmpne     490
     461: aload         16
     463: iconst_0
     464: aload         9
     466: iload         15
     468: iconst_1
     469: isub
     470: iload         6
     472: imul
     473: aload         9
     475: arraylength
     476: iload         15
     478: iconst_1
     479: isub
     480: iload         6
     482: imul
     483: isub
     484: invokestatic  #86                 // Method java/lang/System.arraycopy:(Ljava/lang/Object;ILjava/lang/Object;II)V
     487: goto          508
     490: aload         16
     492: iconst_0
     493: aload         9
     495: iload         15
     497: iconst_1
     498: isub
     499: iload         6
     501: imul
     502: aload         16
     504: arraylength
     505: invokestatic  #86                 // Method java/lang/System.arraycopy:(Ljava/lang/Object;ILjava/lang/Object;II)V
     508: iinc          15, 1
     511: goto          234
     514: aload         9
     516: areturn

  public static org.apache.commons.ssl.DerivedKey deriveKeyV2(byte[], byte[], int, int, int, javax.crypto.Mac) throws java.security.InvalidKeyException;
    Code:
       0: iload_3
       1: bipush        8
       3: idiv
       4: istore        6
       6: iload         4
       8: bipush        8
      10: idiv
      11: istore        7
      13: new           #94                 // class javax/crypto/spec/SecretKeySpec
      16: dup
      17: aload_0
      18: ldc           #195                // String N/A
      20: invokespecial #95                 // Method javax/crypto/spec/SecretKeySpec."<init>":([BLjava/lang/String;)V
      23: astore        8
      25: aload         5
      27: aload         8
      29: invokevirtual #196                // Method javax/crypto/Mac.init:(Ljava/security/Key;)V
      32: aload         5
      34: invokevirtual #197                // Method javax/crypto/Mac.getMacLength:()I
      37: istore        9
      39: iload         6
      41: iload         7
      43: iadd
      44: istore        10
      46: iload         10
      48: iload         9
      50: iadd
      51: iconst_1
      52: isub
      53: iload         9
      55: idiv
      56: istore        11
      58: iconst_4
      59: newarray       byte
      61: astore        12
      63: iload         11
      65: iload         9
      67: imul
      68: newarray       byte
      70: astore        13
      72: iconst_1
      73: istore        14
      75: iload         14
      77: iload         11
      79: if_icmpgt     230
      82: iload         14
      84: iconst_1
      85: isub
      86: iload         9
      88: imul
      89: istore        15
      91: aload         12
      93: iconst_0
      94: iload         14
      96: bipush        24
      98: iushr
      99: i2b
     100: bastore
     101: aload         12
     103: iconst_1
     104: iload         14
     106: bipush        16
     108: iushr
     109: i2b
     110: bastore
     111: aload         12
     113: iconst_2
     114: iload         14
     116: bipush        8
     118: iushr
     119: i2b
     120: bastore
     121: aload         12
     123: iconst_3
     124: iload         14
     126: i2b
     127: bastore
     128: aload         5
     130: invokevirtual #198                // Method javax/crypto/Mac.reset:()V
     133: aload         5
     135: aload_1
     136: invokevirtual #199                // Method javax/crypto/Mac.update:([B)V
     139: aload         5
     141: aload         12
     143: invokevirtual #200                // Method javax/crypto/Mac.doFinal:([B)[B
     146: astore        16
     148: aload         16
     150: iconst_0
     151: aload         13
     153: iload         15
     155: aload         16
     157: arraylength
     158: invokestatic  #86                 // Method java/lang/System.arraycopy:(Ljava/lang/Object;ILjava/lang/Object;II)V
     161: iconst_1
     162: istore        17
     164: iload         17
     166: iload_2
     167: if_icmpge     224
     170: aload         5
     172: invokevirtual #198                // Method javax/crypto/Mac.reset:()V
     175: aload         5
     177: aload         16
     179: invokevirtual #200                // Method javax/crypto/Mac.doFinal:([B)[B
     182: astore        16
     184: iconst_0
     185: istore        18
     187: iload         18
     189: aload         16
     191: arraylength
     192: if_icmpge     218
     195: aload         13
     197: iload         15
     199: iload         18
     201: iadd
     202: dup2
     203: baload
     204: aload         16
     206: iload         18
     208: baload
     209: ixor
     210: i2b
     211: bastore
     212: iinc          18, 1
     215: goto          187
     218: iinc          17, 1
     221: goto          164
     224: iinc          14, 1
     227: goto          75
     230: iload         6
     232: newarray       byte
     234: astore        14
     236: iload         7
     238: newarray       byte
     240: astore        15
     242: aload         13
     244: iconst_0
     245: aload         14
     247: iconst_0
     248: aload         14
     250: arraylength
     251: invokestatic  #86                 // Method java/lang/System.arraycopy:(Ljava/lang/Object;ILjava/lang/Object;II)V
     254: aload         13
     256: aload         14
     258: arraylength
     259: aload         15
     261: iconst_0
     262: aload         15
     264: arraylength
     265: invokestatic  #86                 // Method java/lang/System.arraycopy:(Ljava/lang/Object;ILjava/lang/Object;II)V
     268: new           #191                // class org/apache/commons/ssl/DerivedKey
     271: dup
     272: aload         14
     274: aload         15
     276: invokespecial #192                // Method org/apache/commons/ssl/DerivedKey."<init>":([B[B)V
     279: areturn

  public static byte[] formatAsPKCS8(byte[], java.lang.String, org.apache.commons.ssl.ASN1Structure);
    Code:
       0: new           #201                // class org/apache/commons/ssl/asn1/DERInteger
       3: dup
       4: getstatic     #202                // Field java/math/BigInteger.ZERO:Ljava/math/BigInteger;
       7: invokespecial #203                // Method org/apache/commons/ssl/asn1/DERInteger."<init>":(Ljava/math/BigInteger;)V
      10: astore_3
      11: new           #204                // class org/apache/commons/ssl/asn1/ASN1EncodableVector
      14: dup
      15: invokespecial #205                // Method org/apache/commons/ssl/asn1/ASN1EncodableVector."<init>":()V
      18: astore        4
      20: new           #204                // class org/apache/commons/ssl/asn1/ASN1EncodableVector
      23: dup
      24: invokespecial #205                // Method org/apache/commons/ssl/asn1/ASN1EncodableVector."<init>":()V
      27: astore        5
      29: new           #206                // class org/apache/commons/ssl/asn1/DERObjectIdentifier
      32: dup
      33: aload_1
      34: invokespecial #207                // Method org/apache/commons/ssl/asn1/DERObjectIdentifier."<init>":(Ljava/lang/String;)V
      37: astore        7
      39: aload         5
      41: aload         7
      43: invokevirtual #208                // Method org/apache/commons/ssl/asn1/DEREncodableVector.add:(Lorg/apache/commons/ssl/asn1/DEREncodable;)V
      46: ldc           #33                 // String 1.2.840.10040.4.1
      48: aload_1
      49: invokevirtual #29                 // Method java/lang/String.equals:(Ljava/lang/Object;)Z
      52: ifeq          247
      55: aload_2
      56: ifnonnull     97
      59: aload_0
      60: invokestatic  #38                 // Method org/apache/commons/ssl/ASN1Util.analyze:([B)Lorg/apache/commons/ssl/ASN1Structure;
      63: astore_2
      64: goto          97
      67: astore        8
      69: new           #169                // class java/lang/RuntimeException
      72: dup
      73: new           #40                 // class java/lang/StringBuffer
      76: dup
      77: invokespecial #41                 // Method java/lang/StringBuffer."<init>":()V
      80: ldc           #209                // String asn1 parse failure
      82: invokevirtual #43                 // Method java/lang/StringBuffer.append:(Ljava/lang/String;)Ljava/lang/StringBuffer;
      85: aload         8
      87: invokevirtual #44                 // Method java/lang/StringBuffer.append:(Ljava/lang/Object;)Ljava/lang/StringBuffer;
      90: invokevirtual #45                 // Method java/lang/StringBuffer.toString:()Ljava/lang/String;
      93: invokespecial #172                // Method java/lang/RuntimeException."<init>":(Ljava/lang/String;)V
      96: athrow
      97: aload_2
      98: getfield      #46                 // Field org/apache/commons/ssl/ASN1Structure.derIntegers:Ljava/util/List;
     101: ifnull        118
     104: aload_2
     105: getfield      #46                 // Field org/apache/commons/ssl/ASN1Structure.derIntegers:Ljava/util/List;
     108: invokeinterface #47,  1           // InterfaceMethod java/util/List.size:()I
     113: bipush        6
     115: if_icmpge     128
     118: new           #169                // class java/lang/RuntimeException
     121: dup
     122: ldc           #210                // String invalid DSA key - can\'t find P, Q, G, X
     124: invokespecial #172                // Method java/lang/RuntimeException."<init>":(Ljava/lang/String;)V
     127: athrow
     128: aload_2
     129: getfield      #46                 // Field org/apache/commons/ssl/ASN1Structure.derIntegers:Ljava/util/List;
     132: invokeinterface #47,  1           // InterfaceMethod java/util/List.size:()I
     137: anewarray     #201                // class org/apache/commons/ssl/asn1/DERInteger
     140: astore        8
     142: aload_2
     143: getfield      #46                 // Field org/apache/commons/ssl/ASN1Structure.derIntegers:Ljava/util/List;
     146: aload         8
     148: invokeinterface #211,  2          // InterfaceMethod java/util/List.toArray:([Ljava/lang/Object;)[Ljava/lang/Object;
     153: pop
     154: aload         8
     156: iconst_1
     157: aaload
     158: astore        9
     160: aload         8
     162: iconst_2
     163: aaload
     164: astore        10
     166: aload         8
     168: iconst_3
     169: aaload
     170: astore        11
     172: aload         8
     174: iconst_5
     175: aaload
     176: astore        12
     178: aload         12
     180: invokestatic  #212                // Method encode:(Lorg/apache/commons/ssl/asn1/DEREncodable;)[B
     183: astore        13
     185: new           #213                // class org/apache/commons/ssl/asn1/DEROctetString
     188: dup
     189: aload         13
     191: invokespecial #214                // Method org/apache/commons/ssl/asn1/DEROctetString."<init>":([B)V
     194: astore        6
     196: new           #204                // class org/apache/commons/ssl/asn1/ASN1EncodableVector
     199: dup
     200: invokespecial #205                // Method org/apache/commons/ssl/asn1/ASN1EncodableVector."<init>":()V
     203: astore        14
     205: aload         14
     207: aload         9
     209: invokevirtual #208                // Method org/apache/commons/ssl/asn1/DEREncodableVector.add:(Lorg/apache/commons/ssl/asn1/DEREncodable;)V
     212: aload         14
     214: aload         10
     216: invokevirtual #208                // Method org/apache/commons/ssl/asn1/DEREncodableVector.add:(Lorg/apache/commons/ssl/asn1/DEREncodable;)V
     219: aload         14
     221: aload         11
     223: invokevirtual #208                // Method org/apache/commons/ssl/asn1/DEREncodableVector.add:(Lorg/apache/commons/ssl/asn1/DEREncodable;)V
     226: new           #215                // class org/apache/commons/ssl/asn1/DERSequence
     229: dup
     230: aload         14
     232: invokespecial #216                // Method org/apache/commons/ssl/asn1/DERSequence."<init>":(Lorg/apache/commons/ssl/asn1/DEREncodableVector;)V
     235: astore        15
     237: aload         5
     239: aload         15
     241: invokevirtual #208                // Method org/apache/commons/ssl/asn1/DEREncodableVector.add:(Lorg/apache/commons/ssl/asn1/DEREncodable;)V
     244: goto          265
     247: aload         5
     249: getstatic     #217                // Field org/apache/commons/ssl/asn1/DERNull.INSTANCE:Lorg/apache/commons/ssl/asn1/DERNull;
     252: invokevirtual #208                // Method org/apache/commons/ssl/asn1/DEREncodableVector.add:(Lorg/apache/commons/ssl/asn1/DEREncodable;)V
     255: new           #213                // class org/apache/commons/ssl/asn1/DEROctetString
     258: dup
     259: aload_0
     260: invokespecial #214                // Method org/apache/commons/ssl/asn1/DEROctetString."<init>":([B)V
     263: astore        6
     265: new           #215                // class org/apache/commons/ssl/asn1/DERSequence
     268: dup
     269: aload         5
     271: invokespecial #216                // Method org/apache/commons/ssl/asn1/DERSequence."<init>":(Lorg/apache/commons/ssl/asn1/DEREncodableVector;)V
     274: astore        8
     276: aload         4
     278: aload_3
     279: invokevirtual #208                // Method org/apache/commons/ssl/asn1/DEREncodableVector.add:(Lorg/apache/commons/ssl/asn1/DEREncodable;)V
     282: aload         4
     284: aload         8
     286: invokevirtual #208                // Method org/apache/commons/ssl/asn1/DEREncodableVector.add:(Lorg/apache/commons/ssl/asn1/DEREncodable;)V
     289: aload         4
     291: aload         6
     293: invokevirtual #208                // Method org/apache/commons/ssl/asn1/DEREncodableVector.add:(Lorg/apache/commons/ssl/asn1/DEREncodable;)V
     296: new           #215                // class org/apache/commons/ssl/asn1/DERSequence
     299: dup
     300: aload         4
     302: invokespecial #216                // Method org/apache/commons/ssl/asn1/DERSequence."<init>":(Lorg/apache/commons/ssl/asn1/DEREncodableVector;)V
     305: astore        9
     307: aload         9
     309: invokestatic  #212                // Method encode:(Lorg/apache/commons/ssl/asn1/DEREncodable;)[B
     312: areturn
     313: astore        7
     315: aload         7
     317: invokestatic  #219                // Method org/apache/commons/ssl/JavaImpl.newRuntimeException:(Ljava/lang/Exception;)Ljava/lang/RuntimeException;
     320: athrow
    Exception table:
       from    to  target type
          59    64    67   Class java/lang/Exception
          29   312   313   Class java/io/IOException

  private static boolean allZeroes(byte[]);
    Code:
       0: iconst_0
       1: istore_1
       2: iload_1
       3: aload_0
       4: arraylength
       5: if_icmpge     22
       8: aload_0
       9: iload_1
      10: baload
      11: ifeq          16
      14: iconst_0
      15: ireturn
      16: iinc          1, 1
      19: goto          2
      22: iconst_1
      23: ireturn

  public static byte[] encode(org.apache.commons.ssl.asn1.DEREncodable) throws java.io.IOException;
    Code:
       0: new           #220                // class java/io/ByteArrayOutputStream
       3: dup
       4: sipush        1024
       7: invokespecial #221                // Method java/io/ByteArrayOutputStream."<init>":(I)V
      10: astore_1
      11: new           #222                // class org/apache/commons/ssl/asn1/ASN1OutputStream
      14: dup
      15: aload_1
      16: invokespecial #223                // Method org/apache/commons/ssl/asn1/ASN1OutputStream."<init>":(Ljava/io/OutputStream;)V
      19: astore_2
      20: aload_2
      21: aload_0
      22: invokevirtual #224                // Method org/apache/commons/ssl/asn1/ASN1OutputStream.writeObject:(Ljava/lang/Object;)V
      25: aload_2
      26: invokevirtual #225                // Method java/io/FilterOutputStream.close:()V
      29: aload_1
      30: invokevirtual #226                // Method java/io/ByteArrayOutputStream.toByteArray:()[B
      33: areturn

  public static void main(java.lang.String[]) throws java.lang.Exception;
    Code:
       0: ldc           #227                // String changeit
       2: astore_1
       3: aload_0
       4: arraylength
       5: ifne          35
       8: getstatic     #228                // Field java/lang/System.out:Ljava/io/PrintStream;
      11: ldc           #229                // String Usage1:  [password] [file:private-key]      Prints decrypted PKCS8 key (base64).
      13: invokevirtual #230                // Method java/io/PrintStream.println:(Ljava/lang/String;)V
      16: getstatic     #228                // Field java/lang/System.out:Ljava/io/PrintStream;
      19: ldc           #231                // String Usage2:  [password] [file1] [file2] etc...  Checks that all private keys are equal.
      21: invokevirtual #230                // Method java/io/PrintStream.println:(Ljava/lang/String;)V
      24: getstatic     #228                // Field java/lang/System.out:Ljava/io/PrintStream;
      27: ldc           #232                // String Usage2 assumes that all files can be decrypted with the same password.
      29: invokevirtual #230                // Method java/io/PrintStream.println:(Ljava/lang/String;)V
      32: goto          636
      35: aload_0
      36: arraylength
      37: iconst_1
      38: if_icmpeq     47
      41: aload_0
      42: arraylength
      43: iconst_2
      44: if_icmpne     127
      47: new           #233                // class java/io/FileInputStream
      50: dup
      51: aload_0
      52: aload_0
      53: arraylength
      54: iconst_1
      55: isub
      56: aaload
      57: invokespecial #234                // Method java/io/FileInputStream."<init>":(Ljava/lang/String;)V
      60: astore_2
      61: aload_0
      62: arraylength
      63: iconst_2
      64: if_icmpne     71
      67: aload_0
      68: iconst_0
      69: aaload
      70: astore_1
      71: aload_2
      72: invokestatic  #1                  // Method org/apache/commons/ssl/Util.streamToBytes:(Ljava/io/InputStream;)[B
      75: astore_3
      76: new           #235                // class org/apache/commons/ssl/PKCS8Key
      79: dup
      80: aload_3
      81: aload_1
      82: invokevirtual #236                // Method java/lang/String.toCharArray:()[C
      85: invokespecial #2                  // Method "<init>":([B[C)V
      88: astore        4
      90: new           #13                 // class org/apache/commons/ssl/PEMItem
      93: dup
      94: aload         4
      96: invokevirtual #237                // Method getDecryptedBytes:()[B
      99: ldc           #17                 // String PRIVATE KEY
     101: invokespecial #238                // Method org/apache/commons/ssl/PEMItem."<init>":([BLjava/lang/String;)V
     104: astore        5
     106: aload         5
     108: invokestatic  #239                // Method java/util/Collections.singleton:(Ljava/lang/Object;)Ljava/util/Set;
     111: invokestatic  #240                // Method org/apache/commons/ssl/PEMUtil.encode:(Ljava/util/Collection;)[B
     114: astore        6
     116: getstatic     #228                // Field java/lang/System.out:Ljava/io/PrintStream;
     119: aload         6
     121: invokevirtual #241                // Method java/io/FilterOutputStream.write:([B)V
     124: goto          636
     127: aconst_null
     128: astore_2
     129: new           #242                // class java/io/File
     132: dup
     133: aload_0
     134: iconst_0
     135: aaload
     136: invokespecial #243                // Method java/io/File."<init>":(Ljava/lang/String;)V
     139: astore_3
     140: iconst_0
     141: istore        4
     143: aload_3
     144: invokevirtual #244                // Method java/io/File.exists:()Z
     147: ifne          157
     150: aload_0
     151: iconst_0
     152: aaload
     153: astore_1
     154: iinc          4, 1
     157: iload         4
     159: aload_0
     160: arraylength
     161: if_icmpge     636
     164: new           #233                // class java/io/FileInputStream
     167: dup
     168: aload_0
     169: iload         4
     171: aaload
     172: invokespecial #234                // Method java/io/FileInputStream."<init>":(Ljava/lang/String;)V
     175: astore        5
     177: aload         5
     179: invokestatic  #1                  // Method org/apache/commons/ssl/Util.streamToBytes:(Ljava/io/InputStream;)[B
     182: astore        6
     184: aconst_null
     185: astore        7
     187: new           #235                // class org/apache/commons/ssl/PKCS8Key
     190: dup
     191: aload         6
     193: aload_1
     194: invokevirtual #236                // Method java/lang/String.toCharArray:()[C
     197: invokespecial #2                  // Method "<init>":([B[C)V
     200: astore        7
     202: goto          245
     205: astore        8
     207: getstatic     #228                // Field java/lang/System.out:Ljava/io/PrintStream;
     210: new           #40                 // class java/lang/StringBuffer
     213: dup
     214: invokespecial #41                 // Method java/lang/StringBuffer."<init>":()V
     217: ldc           #245                // String  FAILED!
     219: invokevirtual #43                 // Method java/lang/StringBuffer.append:(Ljava/lang/String;)Ljava/lang/StringBuffer;
     222: aload_0
     223: iload         4
     225: aaload
     226: invokevirtual #43                 // Method java/lang/StringBuffer.append:(Ljava/lang/String;)Ljava/lang/StringBuffer;
     229: ldc           #246                // String
     231: invokevirtual #43                 // Method java/lang/StringBuffer.append:(Ljava/lang/String;)Ljava/lang/StringBuffer;
     234: aload         8
     236: invokevirtual #44                 // Method java/lang/StringBuffer.append:(Ljava/lang/Object;)Ljava/lang/StringBuffer;
     239: invokevirtual #45                 // Method java/lang/StringBuffer.toString:()Ljava/lang/String;
     242: invokevirtual #230                // Method java/io/PrintStream.println:(Ljava/lang/String;)V
     245: aload         7
     247: ifnull        630
     250: aload         7
     252: invokevirtual #237                // Method getDecryptedBytes:()[B
     255: astore        8
     257: aload         7
     259: invokevirtual #247                // Method getKeySize:()I
     262: istore        9
     264: new           #40                 // class java/lang/StringBuffer
     267: dup
     268: invokespecial #41                 // Method java/lang/StringBuffer."<init>":()V
     271: ldc           #30                 // String
     273: invokevirtual #43                 // Method java/lang/StringBuffer.append:(Ljava/lang/String;)Ljava/lang/StringBuffer;
     276: iload         9
     278: invokevirtual #171                // Method java/lang/StringBuffer.append:(I)Ljava/lang/StringBuffer;
     281: invokevirtual #45                 // Method java/lang/StringBuffer.toString:()Ljava/lang/String;
     284: astore        10
     286: iload         9
     288: bipush        10
     290: if_icmpge     318
     293: new           #40                 // class java/lang/StringBuffer
     296: dup
     297: invokespecial #41                 // Method java/lang/StringBuffer."<init>":()V
     300: ldc           #248                // String
     302: invokevirtual #43                 // Method java/lang/StringBuffer.append:(Ljava/lang/String;)Ljava/lang/StringBuffer;
     305: aload         10
     307: invokevirtual #43                 // Method java/lang/StringBuffer.append:(Ljava/lang/String;)Ljava/lang/StringBuffer;
     310: invokevirtual #45                 // Method java/lang/StringBuffer.toString:()Ljava/lang/String;
     313: astore        10
     315: goto          347
     318: iload         9
     320: bipush        100
     322: if_icmpge     347
     325: new           #40                 // class java/lang/StringBuffer
     328: dup
     329: invokespecial #41                 // Method java/lang/StringBuffer."<init>":()V
     332: ldc           #246                // String
     334: invokevirtual #43                 // Method java/lang/StringBuffer.append:(Ljava/lang/String;)Ljava/lang/StringBuffer;
     337: aload         10
     339: invokevirtual #43                 // Method java/lang/StringBuffer.append:(Ljava/lang/String;)Ljava/lang/StringBuffer;
     342: invokevirtual #45                 // Method java/lang/StringBuffer.toString:()Ljava/lang/String;
     345: astore        10
     347: new           #40                 // class java/lang/StringBuffer
     350: dup
     351: aload         7
     353: invokevirtual #249                // Method getTransformation:()Ljava/lang/String;
     356: invokespecial #250                // Method java/lang/StringBuffer."<init>":(Ljava/lang/String;)V
     359: astore        11
     361: ldc           #251                // String Blowfish/CBC/PKCS5Padding
     363: invokevirtual #51                 // Method java/lang/String.length:()I
     366: istore        12
     368: aload         11
     370: invokevirtual #252                // Method java/lang/StringBuffer.length:()I
     373: istore        13
     375: iload         13
     377: iload         12
     379: if_icmpge     396
     382: aload         11
     384: bipush        32
     386: invokevirtual #253                // Method java/lang/StringBuffer.append:(C)Ljava/lang/StringBuffer;
     389: pop
     390: iinc          13, 1
     393: goto          375
     396: aload         11
     398: invokevirtual #45                 // Method java/lang/StringBuffer.toString:()Ljava/lang/String;
     401: astore        13
     403: aload         7
     405: invokevirtual #254                // Method isDSA:()Z
     408: ifeq          416
     411: ldc           #65                 // String DSA
     413: goto          418
     416: ldc           #64                 // String RSA
     418: astore        14
     420: aload_2
     421: ifnonnull     491
     424: aload         8
     426: astore_2
     427: getstatic     #228                // Field java/lang/System.out:Ljava/io/PrintStream;
     430: new           #40                 // class java/lang/StringBuffer
     433: dup
     434: invokespecial #41                 // Method java/lang/StringBuffer."<init>":()V
     437: ldc           #255                // String    SUCCESS    \t
     439: invokevirtual #43                 // Method java/lang/StringBuffer.append:(Ljava/lang/String;)Ljava/lang/StringBuffer;
     442: aload         14
     444: invokevirtual #43                 // Method java/lang/StringBuffer.append:(Ljava/lang/String;)Ljava/lang/StringBuffer;
     447: ldc_w         #256                // String \t
     450: invokevirtual #43                 // Method java/lang/StringBuffer.append:(Ljava/lang/String;)Ljava/lang/StringBuffer;
     453: aload         13
     455: invokevirtual #43                 // Method java/lang/StringBuffer.append:(Ljava/lang/String;)Ljava/lang/StringBuffer;
     458: ldc_w         #256                // String \t
     461: invokevirtual #43                 // Method java/lang/StringBuffer.append:(Ljava/lang/String;)Ljava/lang/StringBuffer;
     464: aload         10
     466: invokevirtual #43                 // Method java/lang/StringBuffer.append:(Ljava/lang/String;)Ljava/lang/StringBuffer;
     469: ldc_w         #256                // String \t
     472: invokevirtual #43                 // Method java/lang/StringBuffer.append:(Ljava/lang/String;)Ljava/lang/StringBuffer;
     475: aload_0
     476: iload         4
     478: aaload
     479: invokevirtual #43                 // Method java/lang/StringBuffer.append:(Ljava/lang/String;)Ljava/lang/StringBuffer;
     482: invokevirtual #45                 // Method java/lang/StringBuffer.toString:()Ljava/lang/String;
     485: invokevirtual #230                // Method java/io/PrintStream.println:(Ljava/lang/String;)V
     488: goto          630
     491: aload_2
     492: aload         8
     494: invokestatic  #257                // Method java/util/Arrays.equals:([B[B)Z
     497: istore        15
     499: iload         15
     501: ifne          569
     504: getstatic     #228                // Field java/lang/System.out:Ljava/io/PrintStream;
     507: new           #40                 // class java/lang/StringBuffer
     510: dup
     511: invokespecial #41                 // Method java/lang/StringBuffer."<init>":()V
     514: ldc_w         #258                // String ***FAILURE*** \t
     517: invokevirtual #43                 // Method java/lang/StringBuffer.append:(Ljava/lang/String;)Ljava/lang/StringBuffer;
     520: aload         14
     522: invokevirtual #43                 // Method java/lang/StringBuffer.append:(Ljava/lang/String;)Ljava/lang/StringBuffer;
     525: ldc_w         #256                // String \t
     528: invokevirtual #43                 // Method java/lang/StringBuffer.append:(Ljava/lang/String;)Ljava/lang/StringBuffer;
     531: aload         13
     533: invokevirtual #43                 // Method java/lang/StringBuffer.append:(Ljava/lang/String;)Ljava/lang/StringBuffer;
     536: ldc_w         #256                // String \t
     539: invokevirtual #43                 // Method java/lang/StringBuffer.append:(Ljava/lang/String;)Ljava/lang/StringBuffer;
     542: aload         10
     544: invokevirtual #43                 // Method java/lang/StringBuffer.append:(Ljava/lang/String;)Ljava/lang/StringBuffer;
     547: ldc_w         #256                // String \t
     550: invokevirtual #43                 // Method java/lang/StringBuffer.append:(Ljava/lang/String;)Ljava/lang/StringBuffer;
     553: aload_0
     554: iload         4
     556: aaload
     557: invokevirtual #43                 // Method java/lang/StringBuffer.append:(Ljava/lang/String;)Ljava/lang/StringBuffer;
     560: invokevirtual #45                 // Method java/lang/StringBuffer.toString:()Ljava/lang/String;
     563: invokevirtual #230                // Method java/io/PrintStream.println:(Ljava/lang/String;)V
     566: goto          630
     569: getstatic     #228                // Field java/lang/System.out:Ljava/io/PrintStream;
     572: new           #40                 // class java/lang/StringBuffer
     575: dup
     576: invokespecial #41                 // Method java/lang/StringBuffer."<init>":()V
     579: ldc           #255                // String    SUCCESS    \t
     581: invokevirtual #43                 // Method java/lang/StringBuffer.append:(Ljava/lang/String;)Ljava/lang/StringBuffer;
     584: aload         14
     586: invokevirtual #43                 // Method java/lang/StringBuffer.append:(Ljava/lang/String;)Ljava/lang/StringBuffer;
     589: ldc_w         #256                // String \t
     592: invokevirtual #43                 // Method java/lang/StringBuffer.append:(Ljava/lang/String;)Ljava/lang/StringBuffer;
     595: aload         13
     597: invokevirtual #43                 // Method java/lang/StringBuffer.append:(Ljava/lang/String;)Ljava/lang/StringBuffer;
     600: ldc_w         #256                // String \t
     603: invokevirtual #43                 // Method java/lang/StringBuffer.append:(Ljava/lang/String;)Ljava/lang/StringBuffer;
     606: aload         10
     608: invokevirtual #43                 // Method java/lang/StringBuffer.append:(Ljava/lang/String;)Ljava/lang/StringBuffer;
     611: ldc_w         #256                // String \t
     614: invokevirtual #43                 // Method java/lang/StringBuffer.append:(Ljava/lang/String;)Ljava/lang/StringBuffer;
     617: aload_0
     618: iload         4
     620: aaload
     621: invokevirtual #43                 // Method java/lang/StringBuffer.append:(Ljava/lang/String;)Ljava/lang/StringBuffer;
     624: invokevirtual #45                 // Method java/lang/StringBuffer.toString:()Ljava/lang/String;
     627: invokevirtual #230                // Method java/io/PrintStream.println:(Ljava/lang/String;)V
     630: iinc          4, 1
     633: goto          157
     636: return
    Exception table:
       from    to  target type
         187   202   205   Class java/lang/Exception

  static {};
    Code:
       0: invokestatic  #259                // Method org/apache/commons/ssl/JavaImpl.load:()V
       3: return
}
