Compiled from "Strings.java"
public class io.fabric8.funktion.support.Strings {
  public io.fabric8.funktion.support.Strings();
    Code:
       0: aload_0
       1: invokespecial #1                  // Method java/lang/Object."<init>":()V
       4: return

  public static boolean isEmpty(java.lang.String);
    Code:
       0: aload_0
       1: ifnull        21
       4: aload_0
       5: invokevirtual #2                  // Method java/lang/String.length:()I
       8: ifeq          21
      11: aload_0
      12: invokevirtual #3                  // Method java/lang/String.trim:()Ljava/lang/String;
      15: invokevirtual #2                  // Method java/lang/String.length:()I
      18: ifne          25
      21: iconst_1
      22: goto          26
      25: iconst_0
      26: ireturn
}
