Compiled from "ColorInput.java"
public class javafx.scene.effect.ColorInput extends javafx.scene.effect.Effect {
  private javafx.beans.property.ObjectProperty<javafx.scene.paint.Paint> paint;

  private javafx.beans.property.DoubleProperty x;

  private javafx.beans.property.DoubleProperty y;

  private javafx.beans.property.DoubleProperty width;

  private javafx.beans.property.DoubleProperty height;

  public javafx.scene.effect.ColorInput();
    Code:
       0: aload_0
       1: invokespecial #1                  // Method javafx/scene/effect/Effect."<init>":()V
       4: return

  public javafx.scene.effect.ColorInput(double, double, double, double, javafx.scene.paint.Paint);
    Code:
       0: aload_0
       1: invokespecial #1                  // Method javafx/scene/effect/Effect."<init>":()V
       4: aload_0
       5: dload_1
       6: invokevirtual #2                  // Method setX:(D)V
       9: aload_0
      10: dload_3
      11: invokevirtual #3                  // Method setY:(D)V
      14: aload_0
      15: dload         5
      17: invokevirtual #4                  // Method setWidth:(D)V
      20: aload_0
      21: dload         7
      23: invokevirtual #5                  // Method setHeight:(D)V
      26: aload_0
      27: aload         9
      29: invokevirtual #6                  // Method setPaint:(Ljavafx/scene/paint/Paint;)V
      32: return

  com.sun.scenario.effect.Flood createPeer();
    Code:
       0: new           #7                  // class com/sun/scenario/effect/Flood
       3: dup
       4: invokestatic  #8                  // Method com/sun/javafx/tk/Toolkit.getPaintAccessor:()Lcom/sun/javafx/tk/Toolkit$PaintAccessor;
       7: getstatic     #9                  // Field javafx/scene/paint/Color.RED:Ljavafx/scene/paint/Color;
      10: invokeinterface #10,  2           // InterfaceMethod com/sun/javafx/tk/Toolkit$PaintAccessor.getPlatformPaint:(Ljavafx/scene/paint/Paint;)Ljava/lang/Object;
      15: invokespecial #11                 // Method com/sun/scenario/effect/Flood."<init>":(Ljava/lang/Object;)V
      18: areturn

  public final void setPaint(javafx.scene.paint.Paint);
    Code:
       0: aload_0
       1: invokevirtual #12                 // Method paintProperty:()Ljavafx/beans/property/ObjectProperty;
       4: aload_1
       5: invokevirtual #13                 // Method javafx/beans/property/ObjectProperty.set:(Ljava/lang/Object;)V
       8: return

  public final javafx.scene.paint.Paint getPaint();
    Code:
       0: aload_0
       1: getfield      #14                 // Field paint:Ljavafx/beans/property/ObjectProperty;
       4: ifnonnull     13
       7: getstatic     #9                  // Field javafx/scene/paint/Color.RED:Ljavafx/scene/paint/Color;
      10: goto          23
      13: aload_0
      14: getfield      #14                 // Field paint:Ljavafx/beans/property/ObjectProperty;
      17: invokevirtual #15                 // Method javafx/beans/property/ObjectProperty.get:()Ljava/lang/Object;
      20: checkcast     #16                 // class javafx/scene/paint/Paint
      23: areturn

  public final javafx.beans.property.ObjectProperty<javafx.scene.paint.Paint> paintProperty();
    Code:
       0: aload_0
       1: getfield      #14                 // Field paint:Ljavafx/beans/property/ObjectProperty;
       4: ifnonnull     22
       7: aload_0
       8: new           #17                 // class javafx/scene/effect/ColorInput$1
      11: dup
      12: aload_0
      13: getstatic     #9                  // Field javafx/scene/paint/Color.RED:Ljavafx/scene/paint/Color;
      16: invokespecial #18                 // Method javafx/scene/effect/ColorInput$1."<init>":(Ljavafx/scene/effect/ColorInput;Ljavafx/scene/paint/Paint;)V
      19: putfield      #14                 // Field paint:Ljavafx/beans/property/ObjectProperty;
      22: aload_0
      23: getfield      #14                 // Field paint:Ljavafx/beans/property/ObjectProperty;
      26: areturn

  public final void setX(double);
    Code:
       0: aload_0
       1: invokevirtual #19                 // Method xProperty:()Ljavafx/beans/property/DoubleProperty;
       4: dload_1
       5: invokevirtual #20                 // Method javafx/beans/property/DoubleProperty.set:(D)V
       8: return

  public final double getX();
    Code:
       0: aload_0
       1: getfield      #21                 // Field x:Ljavafx/beans/property/DoubleProperty;
       4: ifnonnull     11
       7: dconst_0
       8: goto          18
      11: aload_0
      12: getfield      #21                 // Field x:Ljavafx/beans/property/DoubleProperty;
      15: invokevirtual #22                 // Method javafx/beans/property/DoubleProperty.get:()D
      18: dreturn

  public final javafx.beans.property.DoubleProperty xProperty();
    Code:
       0: aload_0
       1: getfield      #21                 // Field x:Ljavafx/beans/property/DoubleProperty;
       4: ifnonnull     19
       7: aload_0
       8: new           #23                 // class javafx/scene/effect/ColorInput$2
      11: dup
      12: aload_0
      13: invokespecial #24                 // Method javafx/scene/effect/ColorInput$2."<init>":(Ljavafx/scene/effect/ColorInput;)V
      16: putfield      #21                 // Field x:Ljavafx/beans/property/DoubleProperty;
      19: aload_0
      20: getfield      #21                 // Field x:Ljavafx/beans/property/DoubleProperty;
      23: areturn

  public final void setY(double);
    Code:
       0: aload_0
       1: invokevirtual #25                 // Method yProperty:()Ljavafx/beans/property/DoubleProperty;
       4: dload_1
       5: invokevirtual #20                 // Method javafx/beans/property/DoubleProperty.set:(D)V
       8: return

  public final double getY();
    Code:
       0: aload_0
       1: getfield      #26                 // Field y:Ljavafx/beans/property/DoubleProperty;
       4: ifnonnull     11
       7: dconst_0
       8: goto          18
      11: aload_0
      12: getfield      #26                 // Field y:Ljavafx/beans/property/DoubleProperty;
      15: invokevirtual #22                 // Method javafx/beans/property/DoubleProperty.get:()D
      18: dreturn

  public final javafx.beans.property.DoubleProperty yProperty();
    Code:
       0: aload_0
       1: getfield      #26                 // Field y:Ljavafx/beans/property/DoubleProperty;
       4: ifnonnull     19
       7: aload_0
       8: new           #27                 // class javafx/scene/effect/ColorInput$3
      11: dup
      12: aload_0
      13: invokespecial #28                 // Method javafx/scene/effect/ColorInput$3."<init>":(Ljavafx/scene/effect/ColorInput;)V
      16: putfield      #26                 // Field y:Ljavafx/beans/property/DoubleProperty;
      19: aload_0
      20: getfield      #26                 // Field y:Ljavafx/beans/property/DoubleProperty;
      23: areturn

  public final void setWidth(double);
    Code:
       0: aload_0
       1: invokevirtual #29                 // Method widthProperty:()Ljavafx/beans/property/DoubleProperty;
       4: dload_1
       5: invokevirtual #20                 // Method javafx/beans/property/DoubleProperty.set:(D)V
       8: return

  public final double getWidth();
    Code:
       0: aload_0
       1: getfield      #30                 // Field width:Ljavafx/beans/property/DoubleProperty;
       4: ifnonnull     11
       7: dconst_0
       8: goto          18
      11: aload_0
      12: getfield      #30                 // Field width:Ljavafx/beans/property/DoubleProperty;
      15: invokevirtual #22                 // Method javafx/beans/property/DoubleProperty.get:()D
      18: dreturn

  public final javafx.beans.property.DoubleProperty widthProperty();
    Code:
       0: aload_0
       1: getfield      #30                 // Field width:Ljavafx/beans/property/DoubleProperty;
       4: ifnonnull     19
       7: aload_0
       8: new           #31                 // class javafx/scene/effect/ColorInput$4
      11: dup
      12: aload_0
      13: invokespecial #32                 // Method javafx/scene/effect/ColorInput$4."<init>":(Ljavafx/scene/effect/ColorInput;)V
      16: putfield      #30                 // Field width:Ljavafx/beans/property/DoubleProperty;
      19: aload_0
      20: getfield      #30                 // Field width:Ljavafx/beans/property/DoubleProperty;
      23: areturn

  public final void setHeight(double);
    Code:
       0: aload_0
       1: invokevirtual #33                 // Method heightProperty:()Ljavafx/beans/property/DoubleProperty;
       4: dload_1
       5: invokevirtual #20                 // Method javafx/beans/property/DoubleProperty.set:(D)V
       8: return

  public final double getHeight();
    Code:
       0: aload_0
       1: getfield      #34                 // Field height:Ljavafx/beans/property/DoubleProperty;
       4: ifnonnull     11
       7: dconst_0
       8: goto          18
      11: aload_0
      12: getfield      #34                 // Field height:Ljavafx/beans/property/DoubleProperty;
      15: invokevirtual #22                 // Method javafx/beans/property/DoubleProperty.get:()D
      18: dreturn

  public final javafx.beans.property.DoubleProperty heightProperty();
    Code:
       0: aload_0
       1: getfield      #34                 // Field height:Ljavafx/beans/property/DoubleProperty;
       4: ifnonnull     19
       7: aload_0
       8: new           #35                 // class javafx/scene/effect/ColorInput$5
      11: dup
      12: aload_0
      13: invokespecial #36                 // Method javafx/scene/effect/ColorInput$5."<init>":(Ljavafx/scene/effect/ColorInput;)V
      16: putfield      #34                 // Field height:Ljavafx/beans/property/DoubleProperty;
      19: aload_0
      20: getfield      #34                 // Field height:Ljavafx/beans/property/DoubleProperty;
      23: areturn

  private javafx.scene.paint.Paint getPaintInternal();
    Code:
       0: aload_0
       1: invokevirtual #37                 // Method getPaint:()Ljavafx/scene/paint/Paint;
       4: astore_1
       5: aload_1
       6: ifnonnull     15
       9: getstatic     #9                  // Field javafx/scene/paint/Color.RED:Ljavafx/scene/paint/Color;
      12: goto          16
      15: aload_1
      16: areturn

  void update();
    Code:
       0: aload_0
       1: invokevirtual #38                 // Method getPeer:()Lcom/sun/scenario/effect/Effect;
       4: checkcast     #7                  // class com/sun/scenario/effect/Flood
       7: astore_1
       8: aload_1
       9: invokestatic  #8                  // Method com/sun/javafx/tk/Toolkit.getPaintAccessor:()Lcom/sun/javafx/tk/Toolkit$PaintAccessor;
      12: aload_0
      13: invokespecial #39                 // Method getPaintInternal:()Ljavafx/scene/paint/Paint;
      16: invokeinterface #10,  2           // InterfaceMethod com/sun/javafx/tk/Toolkit$PaintAccessor.getPlatformPaint:(Ljavafx/scene/paint/Paint;)Ljava/lang/Object;
      21: invokevirtual #40                 // Method com/sun/scenario/effect/Flood.setPaint:(Ljava/lang/Object;)V
      24: aload_1
      25: new           #41                 // class com/sun/javafx/geom/RectBounds
      28: dup
      29: aload_0
      30: invokevirtual #42                 // Method getX:()D
      33: d2f
      34: aload_0
      35: invokevirtual #43                 // Method getY:()D
      38: d2f
      39: aload_0
      40: invokevirtual #42                 // Method getX:()D
      43: aload_0
      44: invokevirtual #44                 // Method getWidth:()D
      47: dadd
      48: d2f
      49: aload_0
      50: invokevirtual #43                 // Method getY:()D
      53: aload_0
      54: invokevirtual #45                 // Method getHeight:()D
      57: dadd
      58: d2f
      59: invokespecial #46                 // Method com/sun/javafx/geom/RectBounds."<init>":(FFFF)V
      62: invokevirtual #47                 // Method com/sun/scenario/effect/Flood.setFloodBounds:(Lcom/sun/javafx/geom/RectBounds;)V
      65: return

  boolean checkChainContains(javafx.scene.effect.Effect);
    Code:
       0: iconst_0
       1: ireturn

  com.sun.javafx.geom.BaseBounds getBounds(com.sun.javafx.geom.BaseBounds, com.sun.javafx.geom.transform.BaseTransform, javafx.scene.Node, com.sun.javafx.scene.BoundsAccessor);
    Code:
       0: new           #41                 // class com/sun/javafx/geom/RectBounds
       3: dup
       4: aload_0
       5: invokevirtual #42                 // Method getX:()D
       8: d2f
       9: aload_0
      10: invokevirtual #43                 // Method getY:()D
      13: d2f
      14: aload_0
      15: invokevirtual #42                 // Method getX:()D
      18: aload_0
      19: invokevirtual #44                 // Method getWidth:()D
      22: dadd
      23: d2f
      24: aload_0
      25: invokevirtual #43                 // Method getY:()D
      28: aload_0
      29: invokevirtual #45                 // Method getHeight:()D
      32: dadd
      33: d2f
      34: invokespecial #46                 // Method com/sun/javafx/geom/RectBounds."<init>":(FFFF)V
      37: astore        5
      39: aload_2
      40: aload         5
      42: invokestatic  #48                 // Method transformBounds:(Lcom/sun/javafx/geom/transform/BaseTransform;Lcom/sun/javafx/geom/BaseBounds;)Lcom/sun/javafx/geom/BaseBounds;
      45: areturn

  javafx.scene.effect.Effect copy();
    Code:
       0: new           #49                 // class javafx/scene/effect/ColorInput
       3: dup
       4: aload_0
       5: invokevirtual #42                 // Method getX:()D
       8: aload_0
       9: invokevirtual #43                 // Method getY:()D
      12: aload_0
      13: invokevirtual #44                 // Method getWidth:()D
      16: aload_0
      17: invokevirtual #45                 // Method getHeight:()D
      20: aload_0
      21: invokevirtual #37                 // Method getPaint:()Ljavafx/scene/paint/Paint;
      24: invokespecial #50                 // Method "<init>":(DDDDLjavafx/scene/paint/Paint;)V
      27: areturn

  com.sun.scenario.effect.Effect createPeer();
    Code:
       0: aload_0
       1: invokevirtual #51                 // Method createPeer:()Lcom/sun/scenario/effect/Flood;
       4: areturn
}
