Compiled from "UHexExtensions.kt"
public final class kotlin.text.UHexExtensionsKt {
  private static final java.lang.String toHexString-zHuV2wU(byte[], kotlin.text.HexFormat);
    Code:
       0: aload_0
       1: ldc           #14                 // String $this$toHexString
       3: invokestatic  #20                 // Method kotlin/jvm/internal/Intrinsics.checkNotNullParameter:(Ljava/lang/Object;Ljava/lang/String;)V
       6: aload_1
       7: ldc           #22                 // String format
       9: invokestatic  #20                 // Method kotlin/jvm/internal/Intrinsics.checkNotNullParameter:(Ljava/lang/Object;Ljava/lang/String;)V
      12: aload_0
      13: aload_1
      14: invokestatic  #27                 // Method kotlin/text/HexExtensionsKt.toHexString:([BLkotlin/text/HexFormat;)Ljava/lang/String;
      17: areturn

  static java.lang.String toHexString-zHuV2wU$default(byte[], kotlin.text.HexFormat, int, java.lang.Object);
    Code:
       0: iload_2
       1: iconst_1
       2: iand
       3: ifeq          13
       6: getstatic     #38                 // Field kotlin/text/HexFormat.Companion:Lkotlin/text/HexFormat$Companion;
       9: invokevirtual #44                 // Method kotlin/text/HexFormat$Companion.getDefault:()Lkotlin/text/HexFormat;
      12: astore_1
      13: aload_0
      14: ldc           #14                 // String $this$toHexString
      16: invokestatic  #20                 // Method kotlin/jvm/internal/Intrinsics.checkNotNullParameter:(Ljava/lang/Object;Ljava/lang/String;)V
      19: aload_1
      20: ldc           #22                 // String format
      22: invokestatic  #20                 // Method kotlin/jvm/internal/Intrinsics.checkNotNullParameter:(Ljava/lang/Object;Ljava/lang/String;)V
      25: aload_0
      26: aload_1
      27: invokestatic  #27                 // Method kotlin/text/HexExtensionsKt.toHexString:([BLkotlin/text/HexFormat;)Ljava/lang/String;
      30: areturn

  private static final java.lang.String toHexString-lZCiFrA(byte[], int, int, kotlin.text.HexFormat);
    Code:
       0: aload_0
       1: ldc           #14                 // String $this$toHexString
       3: invokestatic  #20                 // Method kotlin/jvm/internal/Intrinsics.checkNotNullParameter:(Ljava/lang/Object;Ljava/lang/String;)V
       6: aload_3
       7: ldc           #22                 // String format
       9: invokestatic  #20                 // Method kotlin/jvm/internal/Intrinsics.checkNotNullParameter:(Ljava/lang/Object;Ljava/lang/String;)V
      12: aload_0
      13: iload_1
      14: iload_2
      15: aload_3
      16: invokestatic  #49                 // Method kotlin/text/HexExtensionsKt.toHexString:([BIILkotlin/text/HexFormat;)Ljava/lang/String;
      19: areturn

  static java.lang.String toHexString-lZCiFrA$default(byte[], int, int, kotlin.text.HexFormat, int, java.lang.Object);
    Code:
       0: iload         4
       2: iconst_1
       3: iand
       4: ifeq          9
       7: iconst_0
       8: istore_1
       9: iload         4
      11: iconst_2
      12: iand
      13: ifeq          21
      16: aload_0
      17: invokestatic  #61                 // Method kotlin/UByteArray."getSize-impl":([B)I
      20: istore_2
      21: iload         4
      23: iconst_4
      24: iand
      25: ifeq          35
      28: getstatic     #38                 // Field kotlin/text/HexFormat.Companion:Lkotlin/text/HexFormat$Companion;
      31: invokevirtual #44                 // Method kotlin/text/HexFormat$Companion.getDefault:()Lkotlin/text/HexFormat;
      34: astore_3
      35: aload_0
      36: ldc           #14                 // String $this$toHexString
      38: invokestatic  #20                 // Method kotlin/jvm/internal/Intrinsics.checkNotNullParameter:(Ljava/lang/Object;Ljava/lang/String;)V
      41: aload_3
      42: ldc           #22                 // String format
      44: invokestatic  #20                 // Method kotlin/jvm/internal/Intrinsics.checkNotNullParameter:(Ljava/lang/Object;Ljava/lang/String;)V
      47: aload_0
      48: iload_1
      49: iload_2
      50: aload_3
      51: invokestatic  #49                 // Method kotlin/text/HexExtensionsKt.toHexString:([BIILkotlin/text/HexFormat;)Ljava/lang/String;
      54: areturn

  private static final byte[] hexToUByteArray(java.lang.String, kotlin.text.HexFormat);
    Code:
       0: aload_0
       1: ldc           #66                 // String <this>
       3: invokestatic  #20                 // Method kotlin/jvm/internal/Intrinsics.checkNotNullParameter:(Ljava/lang/Object;Ljava/lang/String;)V
       6: aload_1
       7: ldc           #22                 // String format
       9: invokestatic  #20                 // Method kotlin/jvm/internal/Intrinsics.checkNotNullParameter:(Ljava/lang/Object;Ljava/lang/String;)V
      12: aload_0
      13: aload_1
      14: invokestatic  #69                 // Method kotlin/text/HexExtensionsKt.hexToByteArray:(Ljava/lang/String;Lkotlin/text/HexFormat;)[B
      17: invokestatic  #73                 // Method kotlin/UByteArray."constructor-impl":([B)[B
      20: areturn

  static byte[] hexToUByteArray$default(java.lang.String, kotlin.text.HexFormat, int, java.lang.Object);
    Code:
       0: iload_2
       1: iconst_1
       2: iand
       3: ifeq          13
       6: getstatic     #38                 // Field kotlin/text/HexFormat.Companion:Lkotlin/text/HexFormat$Companion;
       9: invokevirtual #44                 // Method kotlin/text/HexFormat$Companion.getDefault:()Lkotlin/text/HexFormat;
      12: astore_1
      13: aload_0
      14: ldc           #66                 // String <this>
      16: invokestatic  #20                 // Method kotlin/jvm/internal/Intrinsics.checkNotNullParameter:(Ljava/lang/Object;Ljava/lang/String;)V
      19: aload_1
      20: ldc           #22                 // String format
      22: invokestatic  #20                 // Method kotlin/jvm/internal/Intrinsics.checkNotNullParameter:(Ljava/lang/Object;Ljava/lang/String;)V
      25: aload_0
      26: aload_1
      27: invokestatic  #69                 // Method kotlin/text/HexExtensionsKt.hexToByteArray:(Ljava/lang/String;Lkotlin/text/HexFormat;)[B
      30: invokestatic  #73                 // Method kotlin/UByteArray."constructor-impl":([B)[B
      33: areturn

  private static final java.lang.String toHexString-ZQbaR00(byte, kotlin.text.HexFormat);
    Code:
       0: aload_1
       1: ldc           #22                 // String format
       3: invokestatic  #20                 // Method kotlin/jvm/internal/Intrinsics.checkNotNullParameter:(Ljava/lang/Object;Ljava/lang/String;)V
       6: iload_0
       7: aload_1
       8: invokestatic  #82                 // Method kotlin/text/HexExtensionsKt.toHexString:(BLkotlin/text/HexFormat;)Ljava/lang/String;
      11: areturn

  static java.lang.String toHexString-ZQbaR00$default(byte, kotlin.text.HexFormat, int, java.lang.Object);
    Code:
       0: iload_2
       1: iconst_1
       2: iand
       3: ifeq          13
       6: getstatic     #38                 // Field kotlin/text/HexFormat.Companion:Lkotlin/text/HexFormat$Companion;
       9: invokevirtual #44                 // Method kotlin/text/HexFormat$Companion.getDefault:()Lkotlin/text/HexFormat;
      12: astore_1
      13: aload_1
      14: ldc           #22                 // String format
      16: invokestatic  #20                 // Method kotlin/jvm/internal/Intrinsics.checkNotNullParameter:(Ljava/lang/Object;Ljava/lang/String;)V
      19: iload_0
      20: aload_1
      21: invokestatic  #82                 // Method kotlin/text/HexExtensionsKt.toHexString:(BLkotlin/text/HexFormat;)Ljava/lang/String;
      24: areturn

  private static final byte hexToUByte(java.lang.String, kotlin.text.HexFormat);
    Code:
       0: aload_0
       1: ldc           #66                 // String <this>
       3: invokestatic  #20                 // Method kotlin/jvm/internal/Intrinsics.checkNotNullParameter:(Ljava/lang/Object;Ljava/lang/String;)V
       6: aload_1
       7: ldc           #22                 // String format
       9: invokestatic  #20                 // Method kotlin/jvm/internal/Intrinsics.checkNotNullParameter:(Ljava/lang/Object;Ljava/lang/String;)V
      12: aload_0
      13: aload_1
      14: invokestatic  #92                 // Method kotlin/text/HexExtensionsKt.hexToByte:(Ljava/lang/String;Lkotlin/text/HexFormat;)B
      17: invokestatic  #97                 // Method kotlin/UByte."constructor-impl":(B)B
      20: ireturn

  static byte hexToUByte$default(java.lang.String, kotlin.text.HexFormat, int, java.lang.Object);
    Code:
       0: iload_2
       1: iconst_1
       2: iand
       3: ifeq          13
       6: getstatic     #38                 // Field kotlin/text/HexFormat.Companion:Lkotlin/text/HexFormat$Companion;
       9: invokevirtual #44                 // Method kotlin/text/HexFormat$Companion.getDefault:()Lkotlin/text/HexFormat;
      12: astore_1
      13: aload_0
      14: ldc           #66                 // String <this>
      16: invokestatic  #20                 // Method kotlin/jvm/internal/Intrinsics.checkNotNullParameter:(Ljava/lang/Object;Ljava/lang/String;)V
      19: aload_1
      20: ldc           #22                 // String format
      22: invokestatic  #20                 // Method kotlin/jvm/internal/Intrinsics.checkNotNullParameter:(Ljava/lang/Object;Ljava/lang/String;)V
      25: aload_0
      26: aload_1
      27: invokestatic  #92                 // Method kotlin/text/HexExtensionsKt.hexToByte:(Ljava/lang/String;Lkotlin/text/HexFormat;)B
      30: invokestatic  #97                 // Method kotlin/UByte."constructor-impl":(B)B
      33: ireturn

  private static final java.lang.String toHexString-r3ox_E0(short, kotlin.text.HexFormat);
    Code:
       0: aload_1
       1: ldc           #22                 // String format
       3: invokestatic  #20                 // Method kotlin/jvm/internal/Intrinsics.checkNotNullParameter:(Ljava/lang/Object;Ljava/lang/String;)V
       6: iload_0
       7: aload_1
       8: invokestatic  #105                // Method kotlin/text/HexExtensionsKt.toHexString:(SLkotlin/text/HexFormat;)Ljava/lang/String;
      11: areturn

  static java.lang.String toHexString-r3ox_E0$default(short, kotlin.text.HexFormat, int, java.lang.Object);
    Code:
       0: iload_2
       1: iconst_1
       2: iand
       3: ifeq          13
       6: getstatic     #38                 // Field kotlin/text/HexFormat.Companion:Lkotlin/text/HexFormat$Companion;
       9: invokevirtual #44                 // Method kotlin/text/HexFormat$Companion.getDefault:()Lkotlin/text/HexFormat;
      12: astore_1
      13: aload_1
      14: ldc           #22                 // String format
      16: invokestatic  #20                 // Method kotlin/jvm/internal/Intrinsics.checkNotNullParameter:(Ljava/lang/Object;Ljava/lang/String;)V
      19: iload_0
      20: aload_1
      21: invokestatic  #105                // Method kotlin/text/HexExtensionsKt.toHexString:(SLkotlin/text/HexFormat;)Ljava/lang/String;
      24: areturn

  private static final short hexToUShort(java.lang.String, kotlin.text.HexFormat);
    Code:
       0: aload_0
       1: ldc           #66                 // String <this>
       3: invokestatic  #20                 // Method kotlin/jvm/internal/Intrinsics.checkNotNullParameter:(Ljava/lang/Object;Ljava/lang/String;)V
       6: aload_1
       7: ldc           #22                 // String format
       9: invokestatic  #20                 // Method kotlin/jvm/internal/Intrinsics.checkNotNullParameter:(Ljava/lang/Object;Ljava/lang/String;)V
      12: aload_0
      13: aload_1
      14: invokestatic  #115                // Method kotlin/text/HexExtensionsKt.hexToShort:(Ljava/lang/String;Lkotlin/text/HexFormat;)S
      17: invokestatic  #120                // Method kotlin/UShort."constructor-impl":(S)S
      20: ireturn

  static short hexToUShort$default(java.lang.String, kotlin.text.HexFormat, int, java.lang.Object);
    Code:
       0: iload_2
       1: iconst_1
       2: iand
       3: ifeq          13
       6: getstatic     #38                 // Field kotlin/text/HexFormat.Companion:Lkotlin/text/HexFormat$Companion;
       9: invokevirtual #44                 // Method kotlin/text/HexFormat$Companion.getDefault:()Lkotlin/text/HexFormat;
      12: astore_1
      13: aload_0
      14: ldc           #66                 // String <this>
      16: invokestatic  #20                 // Method kotlin/jvm/internal/Intrinsics.checkNotNullParameter:(Ljava/lang/Object;Ljava/lang/String;)V
      19: aload_1
      20: ldc           #22                 // String format
      22: invokestatic  #20                 // Method kotlin/jvm/internal/Intrinsics.checkNotNullParameter:(Ljava/lang/Object;Ljava/lang/String;)V
      25: aload_0
      26: aload_1
      27: invokestatic  #115                // Method kotlin/text/HexExtensionsKt.hexToShort:(Ljava/lang/String;Lkotlin/text/HexFormat;)S
      30: invokestatic  #120                // Method kotlin/UShort."constructor-impl":(S)S
      33: ireturn

  private static final java.lang.String toHexString-8M7LxHw(int, kotlin.text.HexFormat);
    Code:
       0: aload_1
       1: ldc           #22                 // String format
       3: invokestatic  #20                 // Method kotlin/jvm/internal/Intrinsics.checkNotNullParameter:(Ljava/lang/Object;Ljava/lang/String;)V
       6: iload_0
       7: aload_1
       8: invokestatic  #128                // Method kotlin/text/HexExtensionsKt.toHexString:(ILkotlin/text/HexFormat;)Ljava/lang/String;
      11: areturn

  static java.lang.String toHexString-8M7LxHw$default(int, kotlin.text.HexFormat, int, java.lang.Object);
    Code:
       0: iload_2
       1: iconst_1
       2: iand
       3: ifeq          13
       6: getstatic     #38                 // Field kotlin/text/HexFormat.Companion:Lkotlin/text/HexFormat$Companion;
       9: invokevirtual #44                 // Method kotlin/text/HexFormat$Companion.getDefault:()Lkotlin/text/HexFormat;
      12: astore_1
      13: aload_1
      14: ldc           #22                 // String format
      16: invokestatic  #20                 // Method kotlin/jvm/internal/Intrinsics.checkNotNullParameter:(Ljava/lang/Object;Ljava/lang/String;)V
      19: iload_0
      20: aload_1
      21: invokestatic  #128                // Method kotlin/text/HexExtensionsKt.toHexString:(ILkotlin/text/HexFormat;)Ljava/lang/String;
      24: areturn

  private static final int hexToUInt(java.lang.String, kotlin.text.HexFormat);
    Code:
       0: aload_0
       1: ldc           #66                 // String <this>
       3: invokestatic  #20                 // Method kotlin/jvm/internal/Intrinsics.checkNotNullParameter:(Ljava/lang/Object;Ljava/lang/String;)V
       6: aload_1
       7: ldc           #22                 // String format
       9: invokestatic  #20                 // Method kotlin/jvm/internal/Intrinsics.checkNotNullParameter:(Ljava/lang/Object;Ljava/lang/String;)V
      12: aload_0
      13: aload_1
      14: invokestatic  #137                // Method kotlin/text/HexExtensionsKt.hexToInt:(Ljava/lang/String;Lkotlin/text/HexFormat;)I
      17: invokestatic  #142                // Method kotlin/UInt."constructor-impl":(I)I
      20: ireturn

  static int hexToUInt$default(java.lang.String, kotlin.text.HexFormat, int, java.lang.Object);
    Code:
       0: iload_2
       1: iconst_1
       2: iand
       3: ifeq          13
       6: getstatic     #38                 // Field kotlin/text/HexFormat.Companion:Lkotlin/text/HexFormat$Companion;
       9: invokevirtual #44                 // Method kotlin/text/HexFormat$Companion.getDefault:()Lkotlin/text/HexFormat;
      12: astore_1
      13: aload_0
      14: ldc           #66                 // String <this>
      16: invokestatic  #20                 // Method kotlin/jvm/internal/Intrinsics.checkNotNullParameter:(Ljava/lang/Object;Ljava/lang/String;)V
      19: aload_1
      20: ldc           #22                 // String format
      22: invokestatic  #20                 // Method kotlin/jvm/internal/Intrinsics.checkNotNullParameter:(Ljava/lang/Object;Ljava/lang/String;)V
      25: aload_0
      26: aload_1
      27: invokestatic  #137                // Method kotlin/text/HexExtensionsKt.hexToInt:(Ljava/lang/String;Lkotlin/text/HexFormat;)I
      30: invokestatic  #142                // Method kotlin/UInt."constructor-impl":(I)I
      33: ireturn

  private static final java.lang.String toHexString-8UJCm-I(long, kotlin.text.HexFormat);
    Code:
       0: aload_2
       1: ldc           #22                 // String format
       3: invokestatic  #20                 // Method kotlin/jvm/internal/Intrinsics.checkNotNullParameter:(Ljava/lang/Object;Ljava/lang/String;)V
       6: lload_0
       7: aload_2
       8: invokestatic  #150                // Method kotlin/text/HexExtensionsKt.toHexString:(JLkotlin/text/HexFormat;)Ljava/lang/String;
      11: areturn

  static java.lang.String toHexString-8UJCm-I$default(long, kotlin.text.HexFormat, int, java.lang.Object);
    Code:
       0: iload_3
       1: iconst_1
       2: iand
       3: ifeq          13
       6: getstatic     #38                 // Field kotlin/text/HexFormat.Companion:Lkotlin/text/HexFormat$Companion;
       9: invokevirtual #44                 // Method kotlin/text/HexFormat$Companion.getDefault:()Lkotlin/text/HexFormat;
      12: astore_2
      13: aload_2
      14: ldc           #22                 // String format
      16: invokestatic  #20                 // Method kotlin/jvm/internal/Intrinsics.checkNotNullParameter:(Ljava/lang/Object;Ljava/lang/String;)V
      19: lload_0
      20: aload_2
      21: invokestatic  #150                // Method kotlin/text/HexExtensionsKt.toHexString:(JLkotlin/text/HexFormat;)Ljava/lang/String;
      24: areturn

  private static final long hexToULong(java.lang.String, kotlin.text.HexFormat);
    Code:
       0: aload_0
       1: ldc           #66                 // String <this>
       3: invokestatic  #20                 // Method kotlin/jvm/internal/Intrinsics.checkNotNullParameter:(Ljava/lang/Object;Ljava/lang/String;)V
       6: aload_1
       7: ldc           #22                 // String format
       9: invokestatic  #20                 // Method kotlin/jvm/internal/Intrinsics.checkNotNullParameter:(Ljava/lang/Object;Ljava/lang/String;)V
      12: aload_0
      13: aload_1
      14: invokestatic  #160                // Method kotlin/text/HexExtensionsKt.hexToLong:(Ljava/lang/String;Lkotlin/text/HexFormat;)J
      17: invokestatic  #165                // Method kotlin/ULong."constructor-impl":(J)J
      20: lreturn

  static long hexToULong$default(java.lang.String, kotlin.text.HexFormat, int, java.lang.Object);
    Code:
       0: iload_2
       1: iconst_1
       2: iand
       3: ifeq          13
       6: getstatic     #38                 // Field kotlin/text/HexFormat.Companion:Lkotlin/text/HexFormat$Companion;
       9: invokevirtual #44                 // Method kotlin/text/HexFormat$Companion.getDefault:()Lkotlin/text/HexFormat;
      12: astore_1
      13: aload_0
      14: ldc           #66                 // String <this>
      16: invokestatic  #20                 // Method kotlin/jvm/internal/Intrinsics.checkNotNullParameter:(Ljava/lang/Object;Ljava/lang/String;)V
      19: aload_1
      20: ldc           #22                 // String format
      22: invokestatic  #20                 // Method kotlin/jvm/internal/Intrinsics.checkNotNullParameter:(Ljava/lang/Object;Ljava/lang/String;)V
      25: aload_0
      26: aload_1
      27: invokestatic  #160                // Method kotlin/text/HexExtensionsKt.hexToLong:(Ljava/lang/String;Lkotlin/text/HexFormat;)J
      30: invokestatic  #165                // Method kotlin/ULong."constructor-impl":(J)J
      33: lreturn
}
