Compiled from "IdempotentReceiverInterceptor.java"
public class org.springframework.integration.handler.advice.IdempotentReceiverInterceptor extends org.springframework.integration.handler.advice.AbstractHandleMessageAdvice {
  private final org.springframework.integration.core.MessagingTemplate messagingTemplate;

  private final org.springframework.integration.core.MessageSelector messageSelector;

  private org.springframework.messaging.MessageChannel discardChannel;

  private java.lang.String discardChannelName;

  private boolean throwExceptionOnRejection;

  public org.springframework.integration.handler.advice.IdempotentReceiverInterceptor(org.springframework.integration.core.MessageSelector);
    Code:
       0: aload_0
       1: invokespecial #1                  // Method org/springframework/integration/handler/advice/AbstractHandleMessageAdvice."<init>":()V
       4: aload_0
       5: new           #2                  // class org/springframework/integration/core/MessagingTemplate
       8: dup
       9: invokespecial #3                  // Method org/springframework/integration/core/MessagingTemplate."<init>":()V
      12: putfield      #4                  // Field messagingTemplate:Lorg/springframework/integration/core/MessagingTemplate;
      15: aload_1
      16: ldc           #5                  // String \'messageSelector\' must not be null
      18: invokestatic  #6                  // Method org/springframework/util/Assert.notNull:(Ljava/lang/Object;Ljava/lang/String;)V
      21: aload_0
      22: aload_1
      23: putfield      #7                  // Field messageSelector:Lorg/springframework/integration/core/MessageSelector;
      26: return

  public void setTimeout(long);
    Code:
       0: aload_0
       1: getfield      #4                  // Field messagingTemplate:Lorg/springframework/integration/core/MessagingTemplate;
       4: lload_1
       5: invokevirtual #8                  // Method org/springframework/integration/core/MessagingTemplate.setSendTimeout:(J)V
       8: return

  public void setThrowExceptionOnRejection(boolean);
    Code:
       0: aload_0
       1: iload_1
       2: putfield      #9                  // Field throwExceptionOnRejection:Z
       5: return

  public void setDiscardChannel(org.springframework.messaging.MessageChannel);
    Code:
       0: aload_0
       1: aload_1
       2: putfield      #10                 // Field discardChannel:Lorg/springframework/messaging/MessageChannel;
       5: return

  public void setDiscardChannelName(java.lang.String);
    Code:
       0: aload_0
       1: aload_1
       2: putfield      #11                 // Field discardChannelName:Ljava/lang/String;
       5: return

  public java.lang.String getComponentType();
    Code:
       0: ldc           #12                 // String idempotent-receiver-interceptor
       2: areturn

  protected java.lang.Object doInvoke(org.aopalliance.intercept.MethodInvocation, org.springframework.messaging.Message<?>) throws java.lang.Throwable;
    Code:
       0: aload_0
       1: getfield      #7                  // Field messageSelector:Lorg/springframework/integration/core/MessageSelector;
       4: aload_2
       5: invokeinterface #13,  2           // InterfaceMethod org/springframework/integration/core/MessageSelector.accept:(Lorg/springframework/messaging/Message;)Z
      10: istore_3
      11: iload_3
      12: ifne          126
      15: iconst_0
      16: istore        4
      18: aload_0
      19: invokespecial #14                 // Method obtainDiscardChannel:()Lorg/springframework/messaging/MessageChannel;
      22: astore        5
      24: aload         5
      26: ifnull        42
      29: aload_0
      30: getfield      #4                  // Field messagingTemplate:Lorg/springframework/integration/core/MessagingTemplate;
      33: aload         5
      35: aload_2
      36: invokevirtual #15                 // Method org/springframework/integration/core/MessagingTemplate.send:(Ljava/lang/Object;Lorg/springframework/messaging/Message;)V
      39: iconst_1
      40: istore        4
      42: aload_0
      43: getfield      #9                  // Field throwExceptionOnRejection:Z
      46: ifeq          86
      49: new           #16                 // class org/springframework/integration/MessageRejectedException
      52: dup
      53: aload_2
      54: new           #17                 // class java/lang/StringBuilder
      57: dup
      58: invokespecial #18                 // Method java/lang/StringBuilder."<init>":()V
      61: ldc           #19                 // String IdempotentReceiver \'
      63: invokevirtual #20                 // Method java/lang/StringBuilder.append:(Ljava/lang/String;)Ljava/lang/StringBuilder;
      66: aload_0
      67: invokevirtual #21                 // Method java/lang/StringBuilder.append:(Ljava/lang/Object;)Ljava/lang/StringBuilder;
      70: ldc           #22                 // String \' rejected duplicate Message:
      72: invokevirtual #20                 // Method java/lang/StringBuilder.append:(Ljava/lang/String;)Ljava/lang/StringBuilder;
      75: aload_2
      76: invokevirtual #21                 // Method java/lang/StringBuilder.append:(Ljava/lang/Object;)Ljava/lang/StringBuilder;
      79: invokevirtual #23                 // Method java/lang/StringBuilder.toString:()Ljava/lang/String;
      82: invokespecial #24                 // Method org/springframework/integration/MessageRejectedException."<init>":(Lorg/springframework/messaging/Message;Ljava/lang/String;)V
      85: athrow
      86: iload         4
      88: ifne          124
      91: aload_1
      92: invokeinterface #25,  1           // InterfaceMethod org/aopalliance/intercept/MethodInvocation.getArguments:()[Ljava/lang/Object;
      97: iconst_0
      98: aload_0
      99: invokevirtual #26                 // Method getMessageBuilderFactory:()Lorg/springframework/integration/support/MessageBuilderFactory;
     102: aload_2
     103: invokeinterface #27,  2           // InterfaceMethod org/springframework/integration/support/MessageBuilderFactory.fromMessage:(Lorg/springframework/messaging/Message;)Lorg/springframework/integration/support/AbstractIntegrationMessageBuilder;
     108: ldc           #29                 // String duplicateMessage
     110: iconst_1
     111: invokestatic  #30                 // Method java/lang/Boolean.valueOf:(Z)Ljava/lang/Boolean;
     114: invokevirtual #31                 // Method org/springframework/integration/support/AbstractIntegrationMessageBuilder.setHeader:(Ljava/lang/String;Ljava/lang/Object;)Lorg/springframework/integration/support/AbstractIntegrationMessageBuilder;
     117: invokevirtual #32                 // Method org/springframework/integration/support/AbstractIntegrationMessageBuilder.build:()Lorg/springframework/messaging/Message;
     120: aastore
     121: goto          126
     124: aconst_null
     125: areturn
     126: aload_1
     127: invokeinterface #33,  1           // InterfaceMethod org/aopalliance/intercept/MethodInvocation.proceed:()Ljava/lang/Object;
     132: areturn

  private org.springframework.messaging.MessageChannel obtainDiscardChannel();
    Code:
       0: aload_0
       1: getfield      #10                 // Field discardChannel:Lorg/springframework/messaging/MessageChannel;
       4: ifnonnull     34
       7: aload_0
       8: getfield      #11                 // Field discardChannelName:Ljava/lang/String;
      11: ifnull        34
      14: aload_0
      15: aload_0
      16: invokevirtual #34                 // Method getChannelResolver:()Lorg/springframework/messaging/core/DestinationResolver;
      19: aload_0
      20: getfield      #11                 // Field discardChannelName:Ljava/lang/String;
      23: invokeinterface #35,  2           // InterfaceMethod org/springframework/messaging/core/DestinationResolver.resolveDestination:(Ljava/lang/String;)Ljava/lang/Object;
      28: checkcast     #36                 // class org/springframework/messaging/MessageChannel
      31: putfield      #10                 // Field discardChannel:Lorg/springframework/messaging/MessageChannel;
      34: aload_0
      35: getfield      #10                 // Field discardChannel:Lorg/springframework/messaging/MessageChannel;
      38: areturn
}
