Compiled from "ResequencingMessageGroupProcessor.java"
public class org.springframework.integration.aggregator.ResequencingMessageGroupProcessor implements org.springframework.integration.aggregator.MessageGroupProcessor {
  private final java.util.Comparator<org.springframework.messaging.Message<?>> comparator;

  public org.springframework.integration.aggregator.ResequencingMessageGroupProcessor();
    Code:
       0: aload_0
       1: invokespecial #1                  // Method java/lang/Object."<init>":()V
       4: aload_0
       5: new           #2                  // class org/springframework/integration/aggregator/MessageSequenceComparator
       8: dup
       9: invokespecial #3                  // Method org/springframework/integration/aggregator/MessageSequenceComparator."<init>":()V
      12: putfield      #4                  // Field comparator:Ljava/util/Comparator;
      15: return

  public java.lang.Object processMessageGroup(org.springframework.integration.store.MessageGroup);
    Code:
       0: aload_1
       1: invokeinterface #5,  1            // InterfaceMethod org/springframework/integration/store/MessageGroup.getMessages:()Ljava/util/Collection;
       6: astore_2
       7: aload_2
       8: invokeinterface #6,  1            // InterfaceMethod java/util/Collection.size:()I
      13: ifle          136
      16: new           #7                  // class java/util/ArrayList
      19: dup
      20: aload_2
      21: invokespecial #8                  // Method java/util/ArrayList."<init>":(Ljava/util/Collection;)V
      24: astore_3
      25: aload_3
      26: aload_0
      27: getfield      #4                  // Field comparator:Ljava/util/Comparator;
      30: invokestatic  #9                  // Method java/util/Collections.sort:(Ljava/util/List;Ljava/util/Comparator;)V
      33: new           #7                  // class java/util/ArrayList
      36: dup
      37: invokespecial #10                 // Method java/util/ArrayList."<init>":()V
      40: astore        4
      42: aload_0
      43: aload_3
      44: iconst_0
      45: invokeinterface #11,  2           // InterfaceMethod java/util/List.get:(I)Ljava/lang/Object;
      50: checkcast     #12                 // class org/springframework/messaging/Message
      53: invokespecial #13                 // Method extractSequenceNumber:(Lorg/springframework/messaging/Message;)Ljava/lang/Integer;
      56: invokevirtual #14                 // Method java/lang/Integer.intValue:()I
      59: istore        5
      61: iload         5
      63: istore        6
      65: aload_3
      66: invokeinterface #15,  1           // InterfaceMethod java/util/List.iterator:()Ljava/util/Iterator;
      71: astore        7
      73: aload         7
      75: invokeinterface #16,  1           // InterfaceMethod java/util/Iterator.hasNext:()Z
      80: ifeq          133
      83: aload         7
      85: invokeinterface #17,  1           // InterfaceMethod java/util/Iterator.next:()Ljava/lang/Object;
      90: checkcast     #12                 // class org/springframework/messaging/Message
      93: astore        8
      95: iload         6
      97: istore        5
      99: aload_0
     100: aload         8
     102: invokespecial #13                 // Method extractSequenceNumber:(Lorg/springframework/messaging/Message;)Ljava/lang/Integer;
     105: invokevirtual #14                 // Method java/lang/Integer.intValue:()I
     108: istore        6
     110: iload         6
     112: iconst_1
     113: isub
     114: iload         5
     116: if_icmple     122
     119: goto          133
     122: aload         4
     124: aload         8
     126: invokevirtual #18                 // Method java/util/ArrayList.add:(Ljava/lang/Object;)Z
     129: pop
     130: goto          73
     133: aload         4
     135: areturn
     136: aconst_null
     137: areturn

  private java.lang.Integer extractSequenceNumber(org.springframework.messaging.Message<?>);
    Code:
       0: new           #19                 // class org/springframework/integration/IntegrationMessageHeaderAccessor
       3: dup
       4: aload_1
       5: invokespecial #20                 // Method org/springframework/integration/IntegrationMessageHeaderAccessor."<init>":(Lorg/springframework/messaging/Message;)V
       8: invokevirtual #21                 // Method org/springframework/integration/IntegrationMessageHeaderAccessor.getSequenceNumber:()I
      11: invokestatic  #22                 // Method java/lang/Integer.valueOf:(I)Ljava/lang/Integer;
      14: areturn
}
