Compiled from "ProblemType.scala"
public final class ai.h2o.sparkling.ml.algos.ProblemType {
  public static scala.Enumeration$Value distributionToProblemType(java.lang.String);
    Code:
       0: getstatic     #31                 // Field ai/h2o/sparkling/ml/algos/ProblemType$.MODULE$:Lai/h2o/sparkling/ml/algos/ProblemType$;
       3: aload_0
       4: invokevirtual #33                 // Method ai/h2o/sparkling/ml/algos/ProblemType$.distributionToProblemType:(Ljava/lang/String;)Lscala/Enumeration$Value;
       7: areturn

  public static scala.Enumeration$Value familyToProblemType(java.lang.String);
    Code:
       0: getstatic     #31                 // Field ai/h2o/sparkling/ml/algos/ProblemType$.MODULE$:Lai/h2o/sparkling/ml/algos/ProblemType$;
       3: aload_0
       4: invokevirtual #37                 // Method ai/h2o/sparkling/ml/algos/ProblemType$.familyToProblemType:(Ljava/lang/String;)Lscala/Enumeration$Value;
       7: areturn

  public static scala.Enumeration$Value Both();
    Code:
       0: getstatic     #31                 // Field ai/h2o/sparkling/ml/algos/ProblemType$.MODULE$:Lai/h2o/sparkling/ml/algos/ProblemType$;
       3: invokevirtual #41                 // Method ai/h2o/sparkling/ml/algos/ProblemType$.Both:()Lscala/Enumeration$Value;
       6: areturn

  public static scala.Enumeration$Value Regression();
    Code:
       0: getstatic     #31                 // Field ai/h2o/sparkling/ml/algos/ProblemType$.MODULE$:Lai/h2o/sparkling/ml/algos/ProblemType$;
       3: invokevirtual #44                 // Method ai/h2o/sparkling/ml/algos/ProblemType$.Regression:()Lscala/Enumeration$Value;
       6: areturn

  public static scala.Enumeration$Value Classification();
    Code:
       0: getstatic     #31                 // Field ai/h2o/sparkling/ml/algos/ProblemType$.MODULE$:Lai/h2o/sparkling/ml/algos/ProblemType$;
       3: invokevirtual #47                 // Method ai/h2o/sparkling/ml/algos/ProblemType$.Classification:()Lscala/Enumeration$Value;
       6: areturn

  public static scala.Enumeration$ValueSet$ ValueSet();
    Code:
       0: getstatic     #31                 // Field ai/h2o/sparkling/ml/algos/ProblemType$.MODULE$:Lai/h2o/sparkling/ml/algos/ProblemType$;
       3: invokevirtual #50                 // Method ai/h2o/sparkling/ml/algos/ProblemType$.ValueSet:()Lscala/Enumeration$ValueSet$;
       6: areturn

  public static scala.Enumeration$ValueOrdering$ ValueOrdering();
    Code:
       0: getstatic     #31                 // Field ai/h2o/sparkling/ml/algos/ProblemType$.MODULE$:Lai/h2o/sparkling/ml/algos/ProblemType$;
       3: invokevirtual #54                 // Method ai/h2o/sparkling/ml/algos/ProblemType$.ValueOrdering:()Lscala/Enumeration$ValueOrdering$;
       6: areturn

  public static scala.Enumeration$Value withName(java.lang.String);
    Code:
       0: getstatic     #31                 // Field ai/h2o/sparkling/ml/algos/ProblemType$.MODULE$:Lai/h2o/sparkling/ml/algos/ProblemType$;
       3: aload_0
       4: invokevirtual #58                 // Method ai/h2o/sparkling/ml/algos/ProblemType$.withName:(Ljava/lang/String;)Lscala/Enumeration$Value;
       7: areturn

  public static scala.Enumeration$Value apply(int);
    Code:
       0: getstatic     #31                 // Field ai/h2o/sparkling/ml/algos/ProblemType$.MODULE$:Lai/h2o/sparkling/ml/algos/ProblemType$;
       3: iload_0
       4: invokevirtual #63                 // Method ai/h2o/sparkling/ml/algos/ProblemType$.apply:(I)Lscala/Enumeration$Value;
       7: areturn

  public static int maxId();
    Code:
       0: getstatic     #31                 // Field ai/h2o/sparkling/ml/algos/ProblemType$.MODULE$:Lai/h2o/sparkling/ml/algos/ProblemType$;
       3: invokevirtual #67                 // Method ai/h2o/sparkling/ml/algos/ProblemType$.maxId:()I
       6: ireturn

  public static scala.Enumeration$ValueSet values();
    Code:
       0: getstatic     #31                 // Field ai/h2o/sparkling/ml/algos/ProblemType$.MODULE$:Lai/h2o/sparkling/ml/algos/ProblemType$;
       3: invokevirtual #71                 // Method ai/h2o/sparkling/ml/algos/ProblemType$.values:()Lscala/Enumeration$ValueSet;
       6: areturn

  public static java.lang.String toString();
    Code:
       0: getstatic     #31                 // Field ai/h2o/sparkling/ml/algos/ProblemType$.MODULE$:Lai/h2o/sparkling/ml/algos/ProblemType$;
       3: invokevirtual #75                 // Method ai/h2o/sparkling/ml/algos/ProblemType$.toString:()Ljava/lang/String;
       6: areturn
}
