Compiled from "HikariProxyConnection.java"
public class com.zaxxer.hikari.pool.HikariProxyConnection extends com.zaxxer.hikari.pool.ProxyConnection implements java.sql.Wrapper,java.lang.AutoCloseable,java.sql.Connection {
  public java.sql.Statement createStatement() throws java.sql.SQLException;
    Code:
       0: aload_0
       1: invokespecial #19                 // Method com/zaxxer/hikari/pool/ProxyConnection.createStatement:()Ljava/sql/Statement;
       4: areturn
       5: astore_1
       6: aload_0
       7: aload_1
       8: invokevirtual #23                 // Method com/zaxxer/hikari/pool/ProxyConnection.checkException:(Ljava/sql/SQLException;)Ljava/sql/SQLException;
      11: athrow
    Exception table:
       from    to  target type
           0     5     5   Class java/sql/SQLException

  public java.sql.PreparedStatement prepareStatement(java.lang.String) throws java.sql.SQLException;
    Code:
       0: aload_0
       1: aload_1
       2: invokespecial #27                 // Method com/zaxxer/hikari/pool/ProxyConnection.prepareStatement:(Ljava/lang/String;)Ljava/sql/PreparedStatement;
       5: areturn
       6: astore_2
       7: aload_0
       8: aload_2
       9: invokevirtual #23                 // Method com/zaxxer/hikari/pool/ProxyConnection.checkException:(Ljava/sql/SQLException;)Ljava/sql/SQLException;
      12: athrow
    Exception table:
       from    to  target type
           0     6     6   Class java/sql/SQLException

  public java.sql.CallableStatement prepareCall(java.lang.String) throws java.sql.SQLException;
    Code:
       0: aload_0
       1: aload_1
       2: invokespecial #31                 // Method com/zaxxer/hikari/pool/ProxyConnection.prepareCall:(Ljava/lang/String;)Ljava/sql/CallableStatement;
       5: areturn
       6: astore_2
       7: aload_0
       8: aload_2
       9: invokevirtual #23                 // Method com/zaxxer/hikari/pool/ProxyConnection.checkException:(Ljava/sql/SQLException;)Ljava/sql/SQLException;
      12: athrow
    Exception table:
       from    to  target type
           0     6     6   Class java/sql/SQLException

  public java.lang.String nativeSQL(java.lang.String) throws java.sql.SQLException;
    Code:
       0: aload_0
       1: getfield      #37                 // Field com/zaxxer/hikari/pool/ProxyConnection.delegate:Ljava/sql/Connection;
       4: aload_1
       5: invokeinterface #39,  2           // InterfaceMethod java/sql/Connection.nativeSQL:(Ljava/lang/String;)Ljava/lang/String;
      10: areturn
      11: astore_2
      12: aload_0
      13: aload_2
      14: invokevirtual #23                 // Method com/zaxxer/hikari/pool/ProxyConnection.checkException:(Ljava/sql/SQLException;)Ljava/sql/SQLException;
      17: athrow
    Exception table:
       from    to  target type
           0    11    11   Class java/sql/SQLException

  public void setAutoCommit(boolean) throws java.sql.SQLException;
    Code:
       0: aload_0
       1: iload_1
       2: invokespecial #43                 // Method com/zaxxer/hikari/pool/ProxyConnection.setAutoCommit:(Z)V
       5: goto          15
       8: astore_2
       9: aload_0
      10: aload_2
      11: invokevirtual #23                 // Method com/zaxxer/hikari/pool/ProxyConnection.checkException:(Ljava/sql/SQLException;)Ljava/sql/SQLException;
      14: athrow
      15: return
    Exception table:
       from    to  target type
           0     5     8   Class java/sql/SQLException

  public boolean getAutoCommit() throws java.sql.SQLException;
    Code:
       0: aload_0
       1: getfield      #37                 // Field com/zaxxer/hikari/pool/ProxyConnection.delegate:Ljava/sql/Connection;
       4: invokeinterface #47,  1           // InterfaceMethod java/sql/Connection.getAutoCommit:()Z
       9: ireturn
      10: astore_1
      11: aload_0
      12: aload_1
      13: invokevirtual #23                 // Method com/zaxxer/hikari/pool/ProxyConnection.checkException:(Ljava/sql/SQLException;)Ljava/sql/SQLException;
      16: athrow
    Exception table:
       from    to  target type
           0    10    10   Class java/sql/SQLException

  public void commit() throws java.sql.SQLException;
    Code:
       0: aload_0
       1: invokespecial #51                 // Method com/zaxxer/hikari/pool/ProxyConnection.commit:()V
       4: goto          14
       7: astore_1
       8: aload_0
       9: aload_1
      10: invokevirtual #23                 // Method com/zaxxer/hikari/pool/ProxyConnection.checkException:(Ljava/sql/SQLException;)Ljava/sql/SQLException;
      13: athrow
      14: return
    Exception table:
       from    to  target type
           0     4     7   Class java/sql/SQLException

  public void rollback() throws java.sql.SQLException;
    Code:
       0: aload_0
       1: invokespecial #54                 // Method com/zaxxer/hikari/pool/ProxyConnection.rollback:()V
       4: goto          14
       7: astore_1
       8: aload_0
       9: aload_1
      10: invokevirtual #23                 // Method com/zaxxer/hikari/pool/ProxyConnection.checkException:(Ljava/sql/SQLException;)Ljava/sql/SQLException;
      13: athrow
      14: return
    Exception table:
       from    to  target type
           0     4     7   Class java/sql/SQLException

  public boolean isClosed() throws java.sql.SQLException;
    Code:
       0: aload_0
       1: invokespecial #57                 // Method com/zaxxer/hikari/pool/ProxyConnection.isClosed:()Z
       4: ireturn
       5: astore_1
       6: aload_0
       7: aload_1
       8: invokevirtual #23                 // Method com/zaxxer/hikari/pool/ProxyConnection.checkException:(Ljava/sql/SQLException;)Ljava/sql/SQLException;
      11: athrow
    Exception table:
       from    to  target type
           0     5     5   Class java/sql/SQLException

  public java.sql.DatabaseMetaData getMetaData() throws java.sql.SQLException;
    Code:
       0: aload_0
       1: invokespecial #61                 // Method com/zaxxer/hikari/pool/ProxyConnection.getMetaData:()Ljava/sql/DatabaseMetaData;
       4: areturn
       5: astore_1
       6: aload_0
       7: aload_1
       8: invokevirtual #23                 // Method com/zaxxer/hikari/pool/ProxyConnection.checkException:(Ljava/sql/SQLException;)Ljava/sql/SQLException;
      11: athrow
    Exception table:
       from    to  target type
           0     5     5   Class java/sql/SQLException

  public void setReadOnly(boolean) throws java.sql.SQLException;
    Code:
       0: aload_0
       1: iload_1
       2: invokespecial #64                 // Method com/zaxxer/hikari/pool/ProxyConnection.setReadOnly:(Z)V
       5: goto          15
       8: astore_2
       9: aload_0
      10: aload_2
      11: invokevirtual #23                 // Method com/zaxxer/hikari/pool/ProxyConnection.checkException:(Ljava/sql/SQLException;)Ljava/sql/SQLException;
      14: athrow
      15: return
    Exception table:
       from    to  target type
           0     5     8   Class java/sql/SQLException

  public boolean isReadOnly() throws java.sql.SQLException;
    Code:
       0: aload_0
       1: getfield      #37                 // Field com/zaxxer/hikari/pool/ProxyConnection.delegate:Ljava/sql/Connection;
       4: invokeinterface #67,  1           // InterfaceMethod java/sql/Connection.isReadOnly:()Z
       9: ireturn
      10: astore_1
      11: aload_0
      12: aload_1
      13: invokevirtual #23                 // Method com/zaxxer/hikari/pool/ProxyConnection.checkException:(Ljava/sql/SQLException;)Ljava/sql/SQLException;
      16: athrow
    Exception table:
       from    to  target type
           0    10    10   Class java/sql/SQLException

  public void setCatalog(java.lang.String) throws java.sql.SQLException;
    Code:
       0: aload_0
       1: aload_1
       2: invokespecial #71                 // Method com/zaxxer/hikari/pool/ProxyConnection.setCatalog:(Ljava/lang/String;)V
       5: goto          15
       8: astore_2
       9: aload_0
      10: aload_2
      11: invokevirtual #23                 // Method com/zaxxer/hikari/pool/ProxyConnection.checkException:(Ljava/sql/SQLException;)Ljava/sql/SQLException;
      14: athrow
      15: return
    Exception table:
       from    to  target type
           0     5     8   Class java/sql/SQLException

  public java.lang.String getCatalog() throws java.sql.SQLException;
    Code:
       0: aload_0
       1: getfield      #37                 // Field com/zaxxer/hikari/pool/ProxyConnection.delegate:Ljava/sql/Connection;
       4: invokeinterface #75,  1           // InterfaceMethod java/sql/Connection.getCatalog:()Ljava/lang/String;
       9: areturn
      10: astore_1
      11: aload_0
      12: aload_1
      13: invokevirtual #23                 // Method com/zaxxer/hikari/pool/ProxyConnection.checkException:(Ljava/sql/SQLException;)Ljava/sql/SQLException;
      16: athrow
    Exception table:
       from    to  target type
           0    10    10   Class java/sql/SQLException

  public void setTransactionIsolation(int) throws java.sql.SQLException;
    Code:
       0: aload_0
       1: iload_1
       2: invokespecial #79                 // Method com/zaxxer/hikari/pool/ProxyConnection.setTransactionIsolation:(I)V
       5: goto          15
       8: astore_2
       9: aload_0
      10: aload_2
      11: invokevirtual #23                 // Method com/zaxxer/hikari/pool/ProxyConnection.checkException:(Ljava/sql/SQLException;)Ljava/sql/SQLException;
      14: athrow
      15: return
    Exception table:
       from    to  target type
           0     5     8   Class java/sql/SQLException

  public int getTransactionIsolation() throws java.sql.SQLException;
    Code:
       0: aload_0
       1: getfield      #37                 // Field com/zaxxer/hikari/pool/ProxyConnection.delegate:Ljava/sql/Connection;
       4: invokeinterface #83,  1           // InterfaceMethod java/sql/Connection.getTransactionIsolation:()I
       9: ireturn
      10: astore_1
      11: aload_0
      12: aload_1
      13: invokevirtual #23                 // Method com/zaxxer/hikari/pool/ProxyConnection.checkException:(Ljava/sql/SQLException;)Ljava/sql/SQLException;
      16: athrow
    Exception table:
       from    to  target type
           0    10    10   Class java/sql/SQLException

  public java.sql.SQLWarning getWarnings() throws java.sql.SQLException;
    Code:
       0: aload_0
       1: getfield      #37                 // Field com/zaxxer/hikari/pool/ProxyConnection.delegate:Ljava/sql/Connection;
       4: invokeinterface #87,  1           // InterfaceMethod java/sql/Connection.getWarnings:()Ljava/sql/SQLWarning;
       9: areturn
      10: astore_1
      11: aload_0
      12: aload_1
      13: invokevirtual #23                 // Method com/zaxxer/hikari/pool/ProxyConnection.checkException:(Ljava/sql/SQLException;)Ljava/sql/SQLException;
      16: athrow
    Exception table:
       from    to  target type
           0    10    10   Class java/sql/SQLException

  public void clearWarnings() throws java.sql.SQLException;
    Code:
       0: aload_0
       1: getfield      #37                 // Field com/zaxxer/hikari/pool/ProxyConnection.delegate:Ljava/sql/Connection;
       4: invokeinterface #90,  1           // InterfaceMethod java/sql/Connection.clearWarnings:()V
       9: goto          19
      12: astore_1
      13: aload_0
      14: aload_1
      15: invokevirtual #23                 // Method com/zaxxer/hikari/pool/ProxyConnection.checkException:(Ljava/sql/SQLException;)Ljava/sql/SQLException;
      18: athrow
      19: return
    Exception table:
       from    to  target type
           0     9    12   Class java/sql/SQLException

  public java.sql.Statement createStatement(int, int) throws java.sql.SQLException;
    Code:
       0: aload_0
       1: iload_1
       2: iload_2
       3: invokespecial #93                 // Method com/zaxxer/hikari/pool/ProxyConnection.createStatement:(II)Ljava/sql/Statement;
       6: areturn
       7: astore_3
       8: aload_0
       9: aload_3
      10: invokevirtual #23                 // Method com/zaxxer/hikari/pool/ProxyConnection.checkException:(Ljava/sql/SQLException;)Ljava/sql/SQLException;
      13: athrow
    Exception table:
       from    to  target type
           0     7     7   Class java/sql/SQLException

  public java.sql.PreparedStatement prepareStatement(java.lang.String, int, int) throws java.sql.SQLException;
    Code:
       0: aload_0
       1: aload_1
       2: iload_2
       3: iload_3
       4: invokespecial #98                 // Method com/zaxxer/hikari/pool/ProxyConnection.prepareStatement:(Ljava/lang/String;II)Ljava/sql/PreparedStatement;
       7: areturn
       8: astore        4
      10: aload_0
      11: aload         4
      13: invokevirtual #23                 // Method com/zaxxer/hikari/pool/ProxyConnection.checkException:(Ljava/sql/SQLException;)Ljava/sql/SQLException;
      16: athrow
    Exception table:
       from    to  target type
           0     8     8   Class java/sql/SQLException

  public java.sql.CallableStatement prepareCall(java.lang.String, int, int) throws java.sql.SQLException;
    Code:
       0: aload_0
       1: aload_1
       2: iload_2
       3: iload_3
       4: invokespecial #101                // Method com/zaxxer/hikari/pool/ProxyConnection.prepareCall:(Ljava/lang/String;II)Ljava/sql/CallableStatement;
       7: areturn
       8: astore        4
      10: aload_0
      11: aload         4
      13: invokevirtual #23                 // Method com/zaxxer/hikari/pool/ProxyConnection.checkException:(Ljava/sql/SQLException;)Ljava/sql/SQLException;
      16: athrow
    Exception table:
       from    to  target type
           0     8     8   Class java/sql/SQLException

  public java.util.Map getTypeMap() throws java.sql.SQLException;
    Code:
       0: aload_0
       1: getfield      #37                 // Field com/zaxxer/hikari/pool/ProxyConnection.delegate:Ljava/sql/Connection;
       4: invokeinterface #105,  1          // InterfaceMethod java/sql/Connection.getTypeMap:()Ljava/util/Map;
       9: areturn
      10: astore_1
      11: aload_0
      12: aload_1
      13: invokevirtual #23                 // Method com/zaxxer/hikari/pool/ProxyConnection.checkException:(Ljava/sql/SQLException;)Ljava/sql/SQLException;
      16: athrow
    Exception table:
       from    to  target type
           0    10    10   Class java/sql/SQLException

  public void setTypeMap(java.util.Map) throws java.sql.SQLException;
    Code:
       0: aload_0
       1: getfield      #37                 // Field com/zaxxer/hikari/pool/ProxyConnection.delegate:Ljava/sql/Connection;
       4: aload_1
       5: invokeinterface #109,  2          // InterfaceMethod java/sql/Connection.setTypeMap:(Ljava/util/Map;)V
      10: goto          20
      13: astore_2
      14: aload_0
      15: aload_2
      16: invokevirtual #23                 // Method com/zaxxer/hikari/pool/ProxyConnection.checkException:(Ljava/sql/SQLException;)Ljava/sql/SQLException;
      19: athrow
      20: return
    Exception table:
       from    to  target type
           0    10    13   Class java/sql/SQLException

  public void setHoldability(int) throws java.sql.SQLException;
    Code:
       0: aload_0
       1: getfield      #37                 // Field com/zaxxer/hikari/pool/ProxyConnection.delegate:Ljava/sql/Connection;
       4: iload_1
       5: invokeinterface #112,  2          // InterfaceMethod java/sql/Connection.setHoldability:(I)V
      10: goto          20
      13: astore_2
      14: aload_0
      15: aload_2
      16: invokevirtual #23                 // Method com/zaxxer/hikari/pool/ProxyConnection.checkException:(Ljava/sql/SQLException;)Ljava/sql/SQLException;
      19: athrow
      20: return
    Exception table:
       from    to  target type
           0    10    13   Class java/sql/SQLException

  public int getHoldability() throws java.sql.SQLException;
    Code:
       0: aload_0
       1: getfield      #37                 // Field com/zaxxer/hikari/pool/ProxyConnection.delegate:Ljava/sql/Connection;
       4: invokeinterface #115,  1          // InterfaceMethod java/sql/Connection.getHoldability:()I
       9: ireturn
      10: astore_1
      11: aload_0
      12: aload_1
      13: invokevirtual #23                 // Method com/zaxxer/hikari/pool/ProxyConnection.checkException:(Ljava/sql/SQLException;)Ljava/sql/SQLException;
      16: athrow
    Exception table:
       from    to  target type
           0    10    10   Class java/sql/SQLException

  public java.sql.Savepoint setSavepoint() throws java.sql.SQLException;
    Code:
       0: aload_0
       1: getfield      #37                 // Field com/zaxxer/hikari/pool/ProxyConnection.delegate:Ljava/sql/Connection;
       4: invokeinterface #119,  1          // InterfaceMethod java/sql/Connection.setSavepoint:()Ljava/sql/Savepoint;
       9: areturn
      10: astore_1
      11: aload_0
      12: aload_1
      13: invokevirtual #23                 // Method com/zaxxer/hikari/pool/ProxyConnection.checkException:(Ljava/sql/SQLException;)Ljava/sql/SQLException;
      16: athrow
    Exception table:
       from    to  target type
           0    10    10   Class java/sql/SQLException

  public java.sql.Savepoint setSavepoint(java.lang.String) throws java.sql.SQLException;
    Code:
       0: aload_0
       1: getfield      #37                 // Field com/zaxxer/hikari/pool/ProxyConnection.delegate:Ljava/sql/Connection;
       4: aload_1
       5: invokeinterface #122,  2          // InterfaceMethod java/sql/Connection.setSavepoint:(Ljava/lang/String;)Ljava/sql/Savepoint;
      10: areturn
      11: astore_2
      12: aload_0
      13: aload_2
      14: invokevirtual #23                 // Method com/zaxxer/hikari/pool/ProxyConnection.checkException:(Ljava/sql/SQLException;)Ljava/sql/SQLException;
      17: athrow
    Exception table:
       from    to  target type
           0    11    11   Class java/sql/SQLException

  public void rollback(java.sql.Savepoint) throws java.sql.SQLException;
    Code:
       0: aload_0
       1: aload_1
       2: invokespecial #125                // Method com/zaxxer/hikari/pool/ProxyConnection.rollback:(Ljava/sql/Savepoint;)V
       5: goto          15
       8: astore_2
       9: aload_0
      10: aload_2
      11: invokevirtual #23                 // Method com/zaxxer/hikari/pool/ProxyConnection.checkException:(Ljava/sql/SQLException;)Ljava/sql/SQLException;
      14: athrow
      15: return
    Exception table:
       from    to  target type
           0     5     8   Class java/sql/SQLException

  public void releaseSavepoint(java.sql.Savepoint) throws java.sql.SQLException;
    Code:
       0: aload_0
       1: getfield      #37                 // Field com/zaxxer/hikari/pool/ProxyConnection.delegate:Ljava/sql/Connection;
       4: aload_1
       5: invokeinterface #128,  2          // InterfaceMethod java/sql/Connection.releaseSavepoint:(Ljava/sql/Savepoint;)V
      10: goto          20
      13: astore_2
      14: aload_0
      15: aload_2
      16: invokevirtual #23                 // Method com/zaxxer/hikari/pool/ProxyConnection.checkException:(Ljava/sql/SQLException;)Ljava/sql/SQLException;
      19: athrow
      20: return
    Exception table:
       from    to  target type
           0    10    13   Class java/sql/SQLException

  public java.sql.Statement createStatement(int, int, int) throws java.sql.SQLException;
    Code:
       0: aload_0
       1: iload_1
       2: iload_2
       3: iload_3
       4: invokespecial #131                // Method com/zaxxer/hikari/pool/ProxyConnection.createStatement:(III)Ljava/sql/Statement;
       7: areturn
       8: astore        4
      10: aload_0
      11: aload         4
      13: invokevirtual #23                 // Method com/zaxxer/hikari/pool/ProxyConnection.checkException:(Ljava/sql/SQLException;)Ljava/sql/SQLException;
      16: athrow
    Exception table:
       from    to  target type
           0     8     8   Class java/sql/SQLException

  public java.sql.PreparedStatement prepareStatement(java.lang.String, int, int, int) throws java.sql.SQLException;
    Code:
       0: aload_0
       1: aload_1
       2: iload_2
       3: iload_3
       4: iload         4
       6: invokespecial #134                // Method com/zaxxer/hikari/pool/ProxyConnection.prepareStatement:(Ljava/lang/String;III)Ljava/sql/PreparedStatement;
       9: areturn
      10: astore        5
      12: aload_0
      13: aload         5
      15: invokevirtual #23                 // Method com/zaxxer/hikari/pool/ProxyConnection.checkException:(Ljava/sql/SQLException;)Ljava/sql/SQLException;
      18: athrow
    Exception table:
       from    to  target type
           0    10    10   Class java/sql/SQLException

  public java.sql.CallableStatement prepareCall(java.lang.String, int, int, int) throws java.sql.SQLException;
    Code:
       0: aload_0
       1: aload_1
       2: iload_2
       3: iload_3
       4: iload         4
       6: invokespecial #137                // Method com/zaxxer/hikari/pool/ProxyConnection.prepareCall:(Ljava/lang/String;III)Ljava/sql/CallableStatement;
       9: areturn
      10: astore        5
      12: aload_0
      13: aload         5
      15: invokevirtual #23                 // Method com/zaxxer/hikari/pool/ProxyConnection.checkException:(Ljava/sql/SQLException;)Ljava/sql/SQLException;
      18: athrow
    Exception table:
       from    to  target type
           0    10    10   Class java/sql/SQLException

  public java.sql.PreparedStatement prepareStatement(java.lang.String, int) throws java.sql.SQLException;
    Code:
       0: aload_0
       1: aload_1
       2: iload_2
       3: invokespecial #140                // Method com/zaxxer/hikari/pool/ProxyConnection.prepareStatement:(Ljava/lang/String;I)Ljava/sql/PreparedStatement;
       6: areturn
       7: astore_3
       8: aload_0
       9: aload_3
      10: invokevirtual #23                 // Method com/zaxxer/hikari/pool/ProxyConnection.checkException:(Ljava/sql/SQLException;)Ljava/sql/SQLException;
      13: athrow
    Exception table:
       from    to  target type
           0     7     7   Class java/sql/SQLException

  public java.sql.PreparedStatement prepareStatement(java.lang.String, int[]) throws java.sql.SQLException;
    Code:
       0: aload_0
       1: aload_1
       2: aload_2
       3: invokespecial #143                // Method com/zaxxer/hikari/pool/ProxyConnection.prepareStatement:(Ljava/lang/String;[I)Ljava/sql/PreparedStatement;
       6: areturn
       7: astore_3
       8: aload_0
       9: aload_3
      10: invokevirtual #23                 // Method com/zaxxer/hikari/pool/ProxyConnection.checkException:(Ljava/sql/SQLException;)Ljava/sql/SQLException;
      13: athrow
    Exception table:
       from    to  target type
           0     7     7   Class java/sql/SQLException

  public java.sql.PreparedStatement prepareStatement(java.lang.String, java.lang.String[]) throws java.sql.SQLException;
    Code:
       0: aload_0
       1: aload_1
       2: aload_2
       3: invokespecial #146                // Method com/zaxxer/hikari/pool/ProxyConnection.prepareStatement:(Ljava/lang/String;[Ljava/lang/String;)Ljava/sql/PreparedStatement;
       6: areturn
       7: astore_3
       8: aload_0
       9: aload_3
      10: invokevirtual #23                 // Method com/zaxxer/hikari/pool/ProxyConnection.checkException:(Ljava/sql/SQLException;)Ljava/sql/SQLException;
      13: athrow
    Exception table:
       from    to  target type
           0     7     7   Class java/sql/SQLException

  public java.sql.Clob createClob() throws java.sql.SQLException;
    Code:
       0: aload_0
       1: getfield      #37                 // Field com/zaxxer/hikari/pool/ProxyConnection.delegate:Ljava/sql/Connection;
       4: invokeinterface #150,  1          // InterfaceMethod java/sql/Connection.createClob:()Ljava/sql/Clob;
       9: areturn
      10: astore_1
      11: aload_0
      12: aload_1
      13: invokevirtual #23                 // Method com/zaxxer/hikari/pool/ProxyConnection.checkException:(Ljava/sql/SQLException;)Ljava/sql/SQLException;
      16: athrow
    Exception table:
       from    to  target type
           0    10    10   Class java/sql/SQLException

  public java.sql.Blob createBlob() throws java.sql.SQLException;
    Code:
       0: aload_0
       1: getfield      #37                 // Field com/zaxxer/hikari/pool/ProxyConnection.delegate:Ljava/sql/Connection;
       4: invokeinterface #154,  1          // InterfaceMethod java/sql/Connection.createBlob:()Ljava/sql/Blob;
       9: areturn
      10: astore_1
      11: aload_0
      12: aload_1
      13: invokevirtual #23                 // Method com/zaxxer/hikari/pool/ProxyConnection.checkException:(Ljava/sql/SQLException;)Ljava/sql/SQLException;
      16: athrow
    Exception table:
       from    to  target type
           0    10    10   Class java/sql/SQLException

  public java.sql.NClob createNClob() throws java.sql.SQLException;
    Code:
       0: aload_0
       1: getfield      #37                 // Field com/zaxxer/hikari/pool/ProxyConnection.delegate:Ljava/sql/Connection;
       4: invokeinterface #158,  1          // InterfaceMethod java/sql/Connection.createNClob:()Ljava/sql/NClob;
       9: areturn
      10: astore_1
      11: aload_0
      12: aload_1
      13: invokevirtual #23                 // Method com/zaxxer/hikari/pool/ProxyConnection.checkException:(Ljava/sql/SQLException;)Ljava/sql/SQLException;
      16: athrow
    Exception table:
       from    to  target type
           0    10    10   Class java/sql/SQLException

  public java.sql.SQLXML createSQLXML() throws java.sql.SQLException;
    Code:
       0: aload_0
       1: getfield      #37                 // Field com/zaxxer/hikari/pool/ProxyConnection.delegate:Ljava/sql/Connection;
       4: invokeinterface #162,  1          // InterfaceMethod java/sql/Connection.createSQLXML:()Ljava/sql/SQLXML;
       9: areturn
      10: astore_1
      11: aload_0
      12: aload_1
      13: invokevirtual #23                 // Method com/zaxxer/hikari/pool/ProxyConnection.checkException:(Ljava/sql/SQLException;)Ljava/sql/SQLException;
      16: athrow
    Exception table:
       from    to  target type
           0    10    10   Class java/sql/SQLException

  public boolean isValid(int) throws java.sql.SQLException;
    Code:
       0: aload_0
       1: getfield      #37                 // Field com/zaxxer/hikari/pool/ProxyConnection.delegate:Ljava/sql/Connection;
       4: iload_1
       5: invokeinterface #166,  2          // InterfaceMethod java/sql/Connection.isValid:(I)Z
      10: ireturn
      11: astore_2
      12: aload_0
      13: aload_2
      14: invokevirtual #23                 // Method com/zaxxer/hikari/pool/ProxyConnection.checkException:(Ljava/sql/SQLException;)Ljava/sql/SQLException;
      17: athrow
    Exception table:
       from    to  target type
           0    11    11   Class java/sql/SQLException

  public void setClientInfo(java.lang.String, java.lang.String) throws java.sql.SQLClientInfoException;
    Code:
       0: aload_0
       1: getfield      #37                 // Field com/zaxxer/hikari/pool/ProxyConnection.delegate:Ljava/sql/Connection;
       4: checkcast     #10                 // class java/sql/Connection
       7: aload_1
       8: aload_2
       9: invokeinterface #172,  3          // InterfaceMethod java/sql/Connection.setClientInfo:(Ljava/lang/String;Ljava/lang/String;)V
      14: return

  public void setClientInfo(java.util.Properties) throws java.sql.SQLClientInfoException;
    Code:
       0: aload_0
       1: getfield      #37                 // Field com/zaxxer/hikari/pool/ProxyConnection.delegate:Ljava/sql/Connection;
       4: checkcast     #10                 // class java/sql/Connection
       7: aload_1
       8: invokeinterface #175,  2          // InterfaceMethod java/sql/Connection.setClientInfo:(Ljava/util/Properties;)V
      13: return

  public java.lang.String getClientInfo(java.lang.String) throws java.sql.SQLException;
    Code:
       0: aload_0
       1: getfield      #37                 // Field com/zaxxer/hikari/pool/ProxyConnection.delegate:Ljava/sql/Connection;
       4: aload_1
       5: invokeinterface #178,  2          // InterfaceMethod java/sql/Connection.getClientInfo:(Ljava/lang/String;)Ljava/lang/String;
      10: areturn
      11: astore_2
      12: aload_0
      13: aload_2
      14: invokevirtual #23                 // Method com/zaxxer/hikari/pool/ProxyConnection.checkException:(Ljava/sql/SQLException;)Ljava/sql/SQLException;
      17: athrow
    Exception table:
       from    to  target type
           0    11    11   Class java/sql/SQLException

  public java.util.Properties getClientInfo() throws java.sql.SQLException;
    Code:
       0: aload_0
       1: getfield      #37                 // Field com/zaxxer/hikari/pool/ProxyConnection.delegate:Ljava/sql/Connection;
       4: invokeinterface #181,  1          // InterfaceMethod java/sql/Connection.getClientInfo:()Ljava/util/Properties;
       9: areturn
      10: astore_1
      11: aload_0
      12: aload_1
      13: invokevirtual #23                 // Method com/zaxxer/hikari/pool/ProxyConnection.checkException:(Ljava/sql/SQLException;)Ljava/sql/SQLException;
      16: athrow
    Exception table:
       from    to  target type
           0    10    10   Class java/sql/SQLException

  public java.sql.Array createArrayOf(java.lang.String, java.lang.Object[]) throws java.sql.SQLException;
    Code:
       0: aload_0
       1: getfield      #37                 // Field com/zaxxer/hikari/pool/ProxyConnection.delegate:Ljava/sql/Connection;
       4: aload_1
       5: aload_2
       6: invokeinterface #185,  3          // InterfaceMethod java/sql/Connection.createArrayOf:(Ljava/lang/String;[Ljava/lang/Object;)Ljava/sql/Array;
      11: areturn
      12: astore_3
      13: aload_0
      14: aload_3
      15: invokevirtual #23                 // Method com/zaxxer/hikari/pool/ProxyConnection.checkException:(Ljava/sql/SQLException;)Ljava/sql/SQLException;
      18: athrow
    Exception table:
       from    to  target type
           0    12    12   Class java/sql/SQLException

  public java.sql.Struct createStruct(java.lang.String, java.lang.Object[]) throws java.sql.SQLException;
    Code:
       0: aload_0
       1: getfield      #37                 // Field com/zaxxer/hikari/pool/ProxyConnection.delegate:Ljava/sql/Connection;
       4: aload_1
       5: aload_2
       6: invokeinterface #189,  3          // InterfaceMethod java/sql/Connection.createStruct:(Ljava/lang/String;[Ljava/lang/Object;)Ljava/sql/Struct;
      11: areturn
      12: astore_3
      13: aload_0
      14: aload_3
      15: invokevirtual #23                 // Method com/zaxxer/hikari/pool/ProxyConnection.checkException:(Ljava/sql/SQLException;)Ljava/sql/SQLException;
      18: athrow
    Exception table:
       from    to  target type
           0    12    12   Class java/sql/SQLException

  public void setSchema(java.lang.String) throws java.sql.SQLException;
    Code:
       0: aload_0
       1: aload_1
       2: invokespecial #192                // Method com/zaxxer/hikari/pool/ProxyConnection.setSchema:(Ljava/lang/String;)V
       5: goto          15
       8: astore_2
       9: aload_0
      10: aload_2
      11: invokevirtual #23                 // Method com/zaxxer/hikari/pool/ProxyConnection.checkException:(Ljava/sql/SQLException;)Ljava/sql/SQLException;
      14: athrow
      15: return
    Exception table:
       from    to  target type
           0     5     8   Class java/sql/SQLException

  public java.lang.String getSchema() throws java.sql.SQLException;
    Code:
       0: aload_0
       1: getfield      #37                 // Field com/zaxxer/hikari/pool/ProxyConnection.delegate:Ljava/sql/Connection;
       4: invokeinterface #195,  1          // InterfaceMethod java/sql/Connection.getSchema:()Ljava/lang/String;
       9: areturn
      10: astore_1
      11: aload_0
      12: aload_1
      13: invokevirtual #23                 // Method com/zaxxer/hikari/pool/ProxyConnection.checkException:(Ljava/sql/SQLException;)Ljava/sql/SQLException;
      16: athrow
    Exception table:
       from    to  target type
           0    10    10   Class java/sql/SQLException

  public void abort(java.util.concurrent.Executor) throws java.sql.SQLException;
    Code:
       0: aload_0
       1: getfield      #37                 // Field com/zaxxer/hikari/pool/ProxyConnection.delegate:Ljava/sql/Connection;
       4: aload_1
       5: invokeinterface #199,  2          // InterfaceMethod java/sql/Connection.abort:(Ljava/util/concurrent/Executor;)V
      10: goto          20
      13: astore_2
      14: aload_0
      15: aload_2
      16: invokevirtual #23                 // Method com/zaxxer/hikari/pool/ProxyConnection.checkException:(Ljava/sql/SQLException;)Ljava/sql/SQLException;
      19: athrow
      20: return
    Exception table:
       from    to  target type
           0    10    13   Class java/sql/SQLException

  public void setNetworkTimeout(java.util.concurrent.Executor, int) throws java.sql.SQLException;
    Code:
       0: aload_0
       1: aload_1
       2: iload_2
       3: invokespecial #205                // Method com/zaxxer/hikari/pool/ProxyConnection.setNetworkTimeout:(Ljava/util/concurrent/Executor;I)V
       6: goto          16
       9: astore_3
      10: aload_0
      11: aload_3
      12: invokevirtual #23                 // Method com/zaxxer/hikari/pool/ProxyConnection.checkException:(Ljava/sql/SQLException;)Ljava/sql/SQLException;
      15: athrow
      16: return
    Exception table:
       from    to  target type
           0     6     9   Class java/sql/SQLException

  public int getNetworkTimeout() throws java.sql.SQLException;
    Code:
       0: aload_0
       1: getfield      #37                 // Field com/zaxxer/hikari/pool/ProxyConnection.delegate:Ljava/sql/Connection;
       4: invokeinterface #208,  1          // InterfaceMethod java/sql/Connection.getNetworkTimeout:()I
       9: ireturn
      10: astore_1
      11: aload_0
      12: aload_1
      13: invokevirtual #23                 // Method com/zaxxer/hikari/pool/ProxyConnection.checkException:(Ljava/sql/SQLException;)Ljava/sql/SQLException;
      16: athrow
    Exception table:
       from    to  target type
           0    10    10   Class java/sql/SQLException

  protected com.zaxxer.hikari.pool.HikariProxyConnection(com.zaxxer.hikari.pool.PoolEntry, java.sql.Connection, com.zaxxer.hikari.util.FastList, com.zaxxer.hikari.pool.ProxyLeakTask, long, boolean, boolean);
    Code:
       0: aload_0
       1: aload_1
       2: aload_2
       3: aload_3
       4: aload         4
       6: lload         5
       8: iload         7
      10: iload         8
      12: invokespecial #212                // Method com/zaxxer/hikari/pool/ProxyConnection."<init>":(Lcom/zaxxer/hikari/pool/PoolEntry;Ljava/sql/Connection;Lcom/zaxxer/hikari/util/FastList;Lcom/zaxxer/hikari/pool/ProxyLeakTask;JZZ)V
      15: return
}
