Compiled from "PersistenceUnitRegistryImpl.java"
public class org.jboss.as.jpa.subsystem.PersistenceUnitRegistryImpl implements org.jipijapa.plugin.spi.PersistenceUnitServiceRegistry {
  public static final org.jboss.as.jpa.subsystem.PersistenceUnitRegistryImpl INSTANCE;

  private final java.util.Map<java.lang.String, org.jboss.as.jpa.spi.PersistenceUnitService> registry;

  public org.jboss.as.jpa.subsystem.PersistenceUnitRegistryImpl();
    Code:
       0: aload_0
       1: invokespecial #1                  // Method java/lang/Object."<init>":()V
       4: aload_0
       5: new           #2                  // class java/util/HashMap
       8: dup
       9: invokespecial #3                  // Method java/util/HashMap."<init>":()V
      12: invokestatic  #4                  // Method java/util/Collections.synchronizedMap:(Ljava/util/Map;)Ljava/util/Map;
      15: putfield      #5                  // Field registry:Ljava/util/Map;
      18: return

  public org.jboss.as.jpa.spi.PersistenceUnitService getPersistenceUnitService(java.lang.String);
    Code:
       0: aload_0
       1: getfield      #5                  // Field registry:Ljava/util/Map;
       4: aload_1
       5: invokeinterface #6,  2            // InterfaceMethod java/util/Map.get:(Ljava/lang/Object;)Ljava/lang/Object;
      10: checkcast     #7                  // class org/jboss/as/jpa/spi/PersistenceUnitService
      13: areturn

  public void add(java.lang.String, org.jboss.as.jpa.spi.PersistenceUnitService);
    Code:
       0: aload_0
       1: getfield      #5                  // Field registry:Ljava/util/Map;
       4: aload_1
       5: aload_2
       6: invokeinterface #8,  3            // InterfaceMethod java/util/Map.put:(Ljava/lang/Object;Ljava/lang/Object;)Ljava/lang/Object;
      11: pop
      12: return

  public void remove(java.lang.String);
    Code:
       0: aload_0
       1: getfield      #5                  // Field registry:Ljava/util/Map;
       4: aload_1
       5: invokeinterface #9,  2            // InterfaceMethod java/util/Map.remove:(Ljava/lang/Object;)Ljava/lang/Object;
      10: pop
      11: return

  public org.jipijapa.plugin.spi.PersistenceUnitService getPersistenceUnitService(java.lang.String);
    Code:
       0: aload_0
       1: aload_1
       2: invokevirtual #10                 // Method getPersistenceUnitService:(Ljava/lang/String;)Lorg/jboss/as/jpa/spi/PersistenceUnitService;
       5: areturn

  static {};
    Code:
       0: new           #11                 // class org/jboss/as/jpa/subsystem/PersistenceUnitRegistryImpl
       3: dup
       4: invokespecial #12                 // Method "<init>":()V
       7: putstatic     #13                 // Field INSTANCE:Lorg/jboss/as/jpa/subsystem/PersistenceUnitRegistryImpl;
      10: return
}
