Compiled from "CollectionPropertyHolder.java"
public class org.hibernate.cfg.CollectionPropertyHolder extends org.hibernate.cfg.AbstractPropertyHolder {
  private static final org.hibernate.internal.CoreMessageLogger log;

  private final org.hibernate.mapping.Collection collection;

  private boolean canElementBeConverted;

  private boolean canKeyBeConverted;

  private java.util.Map<java.lang.String, org.hibernate.cfg.AttributeConversionInfo> elementAttributeConversionInfoMap;

  private java.util.Map<java.lang.String, org.hibernate.cfg.AttributeConversionInfo> keyAttributeConversionInfoMap;

  boolean prepared;

  public org.hibernate.cfg.CollectionPropertyHolder(org.hibernate.mapping.Collection, java.lang.String, org.hibernate.annotations.common.reflection.XClass, org.hibernate.annotations.common.reflection.XProperty, org.hibernate.cfg.PropertyHolder, org.hibernate.boot.spi.MetadataBuildingContext);
    Code:
       0: aload_0
       1: aload_2
       2: aload         5
       4: aload_3
       5: aload         6
       7: invokespecial #1                  // Method org/hibernate/cfg/AbstractPropertyHolder."<init>":(Ljava/lang/String;Lorg/hibernate/cfg/PropertyHolder;Lorg/hibernate/annotations/common/reflection/XClass;Lorg/hibernate/boot/spi/MetadataBuildingContext;)V
      10: aload_0
      11: iconst_1
      12: putfield      #2                  // Field canElementBeConverted:Z
      15: aload_0
      16: iconst_1
      17: putfield      #3                  // Field canKeyBeConverted:Z
      20: aload_0
      21: aload_1
      22: putfield      #4                  // Field collection:Lorg/hibernate/mapping/Collection;
      25: aload_0
      26: aload         4
      28: invokevirtual #5                  // Method setCurrentProperty:(Lorg/hibernate/annotations/common/reflection/XProperty;)V
      31: aload_0
      32: new           #6                  // class java/util/HashMap
      35: dup
      36: invokespecial #7                  // Method java/util/HashMap."<init>":()V
      39: putfield      #8                  // Field elementAttributeConversionInfoMap:Ljava/util/Map;
      42: aload_0
      43: new           #6                  // class java/util/HashMap
      46: dup
      47: invokespecial #7                  // Method java/util/HashMap."<init>":()V
      50: putfield      #9                  // Field keyAttributeConversionInfoMap:Ljava/util/Map;
      53: return

  public org.hibernate.mapping.Collection getCollectionBinding();
    Code:
       0: aload_0
       1: getfield      #4                  // Field collection:Lorg/hibernate/mapping/Collection;
       4: areturn

  private void buildAttributeConversionInfoMaps(org.hibernate.annotations.common.reflection.XProperty, java.util.Map<java.lang.String, org.hibernate.cfg.AttributeConversionInfo>, java.util.Map<java.lang.String, org.hibernate.cfg.AttributeConversionInfo>);
    Code:
       0: aload_1
       1: ifnonnull     5
       4: return
       5: aload_1
       6: ldc           #10                 // class javax/persistence/Convert
       8: invokeinterface #11,  2           // InterfaceMethod org/hibernate/annotations/common/reflection/XProperty.getAnnotation:(Ljava/lang/Class;)Ljava/lang/annotation/Annotation;
      13: checkcast     #10                 // class javax/persistence/Convert
      16: astore        4
      18: aload         4
      20: ifnull        32
      23: aload_0
      24: aload         4
      26: aload_1
      27: aload_2
      28: aload_3
      29: invokespecial #12                 // Method applyLocalConvert:(Ljavax/persistence/Convert;Lorg/hibernate/annotations/common/reflection/XProperty;Ljava/util/Map;Ljava/util/Map;)V
      32: aload_1
      33: ldc           #13                 // class javax/persistence/Converts
      35: invokeinterface #11,  2           // InterfaceMethod org/hibernate/annotations/common/reflection/XProperty.getAnnotation:(Ljava/lang/Class;)Ljava/lang/annotation/Annotation;
      40: checkcast     #13                 // class javax/persistence/Converts
      43: astore        4
      45: aload         4
      47: ifnull        96
      50: aload         4
      52: invokeinterface #14,  1           // InterfaceMethod javax/persistence/Converts.value:()[Ljavax/persistence/Convert;
      57: astore        5
      59: aload         5
      61: arraylength
      62: istore        6
      64: iconst_0
      65: istore        7
      67: iload         7
      69: iload         6
      71: if_icmpge     96
      74: aload         5
      76: iload         7
      78: aaload
      79: astore        8
      81: aload_0
      82: aload         8
      84: aload_1
      85: aload_2
      86: aload_3
      87: invokespecial #12                 // Method applyLocalConvert:(Ljavax/persistence/Convert;Lorg/hibernate/annotations/common/reflection/XProperty;Ljava/util/Map;Ljava/util/Map;)V
      90: iinc          7, 1
      93: goto          67
      96: return

  private void applyLocalConvert(javax.persistence.Convert, org.hibernate.annotations.common.reflection.XProperty, java.util.Map<java.lang.String, org.hibernate.cfg.AttributeConversionInfo>, java.util.Map<java.lang.String, org.hibernate.cfg.AttributeConversionInfo>);
    Code:
       0: new           #15                 // class org/hibernate/cfg/AttributeConversionInfo
       3: dup
       4: aload_1
       5: aload_2
       6: invokespecial #16                 // Method org/hibernate/cfg/AttributeConversionInfo."<init>":(Ljavax/persistence/Convert;Lorg/hibernate/annotations/common/reflection/XAnnotatedElement;)V
       9: astore        5
      11: aload_0
      12: getfield      #4                  // Field collection:Lorg/hibernate/mapping/Collection;
      15: invokevirtual #17                 // Method org/hibernate/mapping/Collection.isMap:()Z
      18: ifeq          85
      21: aload         5
      23: invokevirtual #18                 // Method org/hibernate/cfg/AttributeConversionInfo.getAttributeName:()Ljava/lang/String;
      26: invokestatic  #19                 // Method org/hibernate/internal/util/StringHelper.isNotEmpty:(Ljava/lang/String;)Z
      29: ifeq          62
      32: aload         5
      34: invokevirtual #18                 // Method org/hibernate/cfg/AttributeConversionInfo.getAttributeName:()Ljava/lang/String;
      37: ldc           #20                 // String key
      39: invokevirtual #21                 // Method java/lang/String.startsWith:(Ljava/lang/String;)Z
      42: ifne          58
      45: aload         5
      47: invokevirtual #18                 // Method org/hibernate/cfg/AttributeConversionInfo.getAttributeName:()Ljava/lang/String;
      50: ldc           #22                 // String value
      52: invokevirtual #21                 // Method java/lang/String.startsWith:(Ljava/lang/String;)Z
      55: ifeq          62
      58: iconst_1
      59: goto          63
      62: iconst_0
      63: istore        6
      65: iload         6
      67: ifne          85
      70: getstatic     #23                 // Field log:Lorg/hibernate/internal/CoreMessageLogger;
      73: aload_0
      74: getfield      #4                  // Field collection:Lorg/hibernate/mapping/Collection;
      77: invokevirtual #24                 // Method org/hibernate/mapping/Collection.getRole:()Ljava/lang/String;
      80: invokeinterface #25,  2           // InterfaceMethod org/hibernate/internal/CoreMessageLogger.nonCompliantMapConversion:(Ljava/lang/String;)V
      85: aload         5
      87: invokevirtual #18                 // Method org/hibernate/cfg/AttributeConversionInfo.getAttributeName:()Ljava/lang/String;
      90: invokestatic  #26                 // Method org/hibernate/internal/util/StringHelper.isEmpty:(Ljava/lang/String;)Z
      93: ifeq          191
      96: aload_0
      97: getfield      #2                  // Field canElementBeConverted:Z
     100: ifeq          148
     103: aload_0
     104: getfield      #3                  // Field canKeyBeConverted:Z
     107: ifeq          148
     110: new           #27                 // class java/lang/IllegalStateException
     113: dup
     114: new           #28                 // class java/lang/StringBuilder
     117: dup
     118: invokespecial #29                 // Method java/lang/StringBuilder."<init>":()V
     121: ldc           #30                 // String @Convert placed on Map attribute [
     123: invokevirtual #31                 // Method java/lang/StringBuilder.append:(Ljava/lang/String;)Ljava/lang/StringBuilder;
     126: aload_0
     127: getfield      #4                  // Field collection:Lorg/hibernate/mapping/Collection;
     130: invokevirtual #24                 // Method org/hibernate/mapping/Collection.getRole:()Ljava/lang/String;
     133: invokevirtual #31                 // Method java/lang/StringBuilder.append:(Ljava/lang/String;)Ljava/lang/StringBuilder;
     136: ldc           #32                 // String ] must define attributeName of \'key\' or \'value\'
     138: invokevirtual #31                 // Method java/lang/StringBuilder.append:(Ljava/lang/String;)Ljava/lang/StringBuilder;
     141: invokevirtual #33                 // Method java/lang/StringBuilder.toString:()Ljava/lang/String;
     144: invokespecial #34                 // Method java/lang/IllegalStateException."<init>":(Ljava/lang/String;)V
     147: athrow
     148: aload_0
     149: getfield      #3                  // Field canKeyBeConverted:Z
     152: ifeq          170
     155: aload         4
     157: ldc           #35                 // String
     159: aload         5
     161: invokeinterface #36,  3           // InterfaceMethod java/util/Map.put:(Ljava/lang/Object;Ljava/lang/Object;)Ljava/lang/Object;
     166: pop
     167: goto          315
     170: aload_0
     171: getfield      #2                  // Field canElementBeConverted:Z
     174: ifeq          315
     177: aload_3
     178: ldc           #35                 // String
     180: aload         5
     182: invokeinterface #36,  3           // InterfaceMethod java/util/Map.put:(Ljava/lang/Object;Ljava/lang/Object;)Ljava/lang/Object;
     187: pop
     188: goto          315
     191: aload_0
     192: aload         5
     194: invokevirtual #18                 // Method org/hibernate/cfg/AttributeConversionInfo.getAttributeName:()Ljava/lang/String;
     197: ldc           #20                 // String key
     199: invokespecial #37                 // Method removePrefix:(Ljava/lang/String;Ljava/lang/String;)Ljava/lang/String;
     202: astore        6
     204: aload_0
     205: aload         5
     207: invokevirtual #18                 // Method org/hibernate/cfg/AttributeConversionInfo.getAttributeName:()Ljava/lang/String;
     210: ldc           #22                 // String value
     212: invokespecial #37                 // Method removePrefix:(Ljava/lang/String;Ljava/lang/String;)Ljava/lang/String;
     215: astore        7
     217: aload_0
     218: getfield      #2                  // Field canElementBeConverted:Z
     221: ifeq          279
     224: aload_0
     225: getfield      #3                  // Field canKeyBeConverted:Z
     228: ifeq          279
     231: aload         6
     233: ifnonnull     279
     236: aload         7
     238: ifnonnull     279
     241: new           #27                 // class java/lang/IllegalStateException
     244: dup
     245: new           #28                 // class java/lang/StringBuilder
     248: dup
     249: invokespecial #29                 // Method java/lang/StringBuilder."<init>":()V
     252: ldc           #30                 // String @Convert placed on Map attribute [
     254: invokevirtual #31                 // Method java/lang/StringBuilder.append:(Ljava/lang/String;)Ljava/lang/StringBuilder;
     257: aload_0
     258: getfield      #4                  // Field collection:Lorg/hibernate/mapping/Collection;
     261: invokevirtual #24                 // Method org/hibernate/mapping/Collection.getRole:()Ljava/lang/String;
     264: invokevirtual #31                 // Method java/lang/StringBuilder.append:(Ljava/lang/String;)Ljava/lang/StringBuilder;
     267: ldc           #32                 // String ] must define attributeName of \'key\' or \'value\'
     269: invokevirtual #31                 // Method java/lang/StringBuilder.append:(Ljava/lang/String;)Ljava/lang/StringBuilder;
     272: invokevirtual #33                 // Method java/lang/StringBuilder.toString:()Ljava/lang/String;
     275: invokespecial #34                 // Method java/lang/IllegalStateException."<init>":(Ljava/lang/String;)V
     278: athrow
     279: aload         6
     281: ifnull        299
     284: aload         4
     286: aload         6
     288: aload         5
     290: invokeinterface #36,  3           // InterfaceMethod java/util/Map.put:(Ljava/lang/Object;Ljava/lang/Object;)Ljava/lang/Object;
     295: pop
     296: goto          315
     299: aload         7
     301: ifnull        315
     304: aload_3
     305: aload         7
     307: aload         5
     309: invokeinterface #36,  3           // InterfaceMethod java/util/Map.put:(Ljava/lang/Object;Ljava/lang/Object;)Ljava/lang/Object;
     314: pop
     315: return

  private java.lang.String removePrefix(java.lang.String, java.lang.String);
    Code:
       0: aload_1
       1: aload_2
       2: invokevirtual #38                 // Method java/lang/String.equals:(Ljava/lang/Object;)Z
       5: ifeq          11
       8: ldc           #35                 // String
      10: areturn
      11: aload_1
      12: new           #28                 // class java/lang/StringBuilder
      15: dup
      16: invokespecial #29                 // Method java/lang/StringBuilder."<init>":()V
      19: aload_2
      20: invokevirtual #31                 // Method java/lang/StringBuilder.append:(Ljava/lang/String;)Ljava/lang/StringBuilder;
      23: ldc           #39                 // String .
      25: invokevirtual #31                 // Method java/lang/StringBuilder.append:(Ljava/lang/String;)Ljava/lang/StringBuilder;
      28: invokevirtual #33                 // Method java/lang/StringBuilder.toString:()Ljava/lang/String;
      31: invokevirtual #21                 // Method java/lang/String.startsWith:(Ljava/lang/String;)Z
      34: ifeq          48
      37: aload_1
      38: aload_2
      39: invokevirtual #40                 // Method java/lang/String.length:()I
      42: iconst_1
      43: iadd
      44: invokevirtual #41                 // Method java/lang/String.substring:(I)Ljava/lang/String;
      47: areturn
      48: aconst_null
      49: areturn

  protected java.lang.String normalizeCompositePath(java.lang.String);
    Code:
       0: aload_1
       1: areturn

  protected java.lang.String normalizeCompositePathForLogging(java.lang.String);
    Code:
       0: new           #28                 // class java/lang/StringBuilder
       3: dup
       4: invokespecial #29                 // Method java/lang/StringBuilder."<init>":()V
       7: aload_0
       8: getfield      #4                  // Field collection:Lorg/hibernate/mapping/Collection;
      11: invokevirtual #24                 // Method org/hibernate/mapping/Collection.getRole:()Ljava/lang/String;
      14: invokevirtual #31                 // Method java/lang/StringBuilder.append:(Ljava/lang/String;)Ljava/lang/StringBuilder;
      17: bipush        46
      19: invokevirtual #42                 // Method java/lang/StringBuilder.append:(C)Ljava/lang/StringBuilder;
      22: aload_1
      23: invokevirtual #31                 // Method java/lang/StringBuilder.append:(Ljava/lang/String;)Ljava/lang/StringBuilder;
      26: invokevirtual #33                 // Method java/lang/StringBuilder.toString:()Ljava/lang/String;
      29: areturn

  public void startingProperty(org.hibernate.annotations.common.reflection.XProperty);
    Code:
       0: aload_1
       1: ifnonnull     5
       4: return
       5: return

  protected org.hibernate.cfg.AttributeConversionInfo locateAttributeConversionInfo(org.hibernate.annotations.common.reflection.XProperty);
    Code:
       0: aload_0
       1: getfield      #2                  // Field canElementBeConverted:Z
       4: ifeq          17
       7: aload_0
       8: getfield      #3                  // Field canKeyBeConverted:Z
      11: ifeq          17
      14: goto          29
      17: aload_0
      18: getfield      #3                  // Field canKeyBeConverted:Z
      21: ifeq          27
      24: goto          29
      27: aconst_null
      28: areturn
      29: aconst_null
      30: areturn

  protected org.hibernate.cfg.AttributeConversionInfo locateAttributeConversionInfo(java.lang.String);
    Code:
       0: aload_0
       1: aload_1
       2: ldc           #20                 // String key
       4: invokespecial #37                 // Method removePrefix:(Ljava/lang/String;Ljava/lang/String;)Ljava/lang/String;
       7: astore_2
       8: aload_2
       9: ifnull        26
      12: aload_0
      13: getfield      #9                  // Field keyAttributeConversionInfoMap:Ljava/util/Map;
      16: aload_2
      17: invokeinterface #43,  2           // InterfaceMethod java/util/Map.get:(Ljava/lang/Object;)Ljava/lang/Object;
      22: checkcast     #15                 // class org/hibernate/cfg/AttributeConversionInfo
      25: areturn
      26: aload_0
      27: aload_1
      28: ldc           #44                 // String element
      30: invokespecial #37                 // Method removePrefix:(Ljava/lang/String;Ljava/lang/String;)Ljava/lang/String;
      33: astore_3
      34: aload_3
      35: ifnull        52
      38: aload_0
      39: getfield      #8                  // Field elementAttributeConversionInfoMap:Ljava/util/Map;
      42: aload_3
      43: invokeinterface #43,  2           // InterfaceMethod java/util/Map.get:(Ljava/lang/Object;)Ljava/lang/Object;
      48: checkcast     #15                 // class org/hibernate/cfg/AttributeConversionInfo
      51: areturn
      52: aload_0
      53: getfield      #8                  // Field elementAttributeConversionInfoMap:Ljava/util/Map;
      56: aload_1
      57: invokeinterface #43,  2           // InterfaceMethod java/util/Map.get:(Ljava/lang/Object;)Ljava/lang/Object;
      62: checkcast     #15                 // class org/hibernate/cfg/AttributeConversionInfo
      65: areturn

  public java.lang.String getClassName();
    Code:
       0: new           #45                 // class org/hibernate/AssertionFailure
       3: dup
       4: ldc           #46                 // String Collection property holder does not have a class name
       6: invokespecial #47                 // Method org/hibernate/AssertionFailure."<init>":(Ljava/lang/String;)V
       9: athrow

  public java.lang.String getEntityOwnerClassName();
    Code:
       0: aconst_null
       1: areturn

  public org.hibernate.mapping.Table getTable();
    Code:
       0: aload_0
       1: getfield      #4                  // Field collection:Lorg/hibernate/mapping/Collection;
       4: invokevirtual #48                 // Method org/hibernate/mapping/Collection.getCollectionTable:()Lorg/hibernate/mapping/Table;
       7: areturn

  public void addProperty(org.hibernate.mapping.Property, org.hibernate.annotations.common.reflection.XClass);
    Code:
       0: new           #45                 // class org/hibernate/AssertionFailure
       3: dup
       4: ldc           #49                 // String Cannot add property to a collection
       6: invokespecial #47                 // Method org/hibernate/AssertionFailure."<init>":(Ljava/lang/String;)V
       9: athrow

  public org.hibernate.mapping.KeyValue getIdentifier();
    Code:
       0: new           #45                 // class org/hibernate/AssertionFailure
       3: dup
       4: ldc           #50                 // String Identifier collection not yet managed
       6: invokespecial #47                 // Method org/hibernate/AssertionFailure."<init>":(Ljava/lang/String;)V
       9: athrow

  public boolean isOrWithinEmbeddedId();
    Code:
       0: iconst_0
       1: ireturn

  public org.hibernate.mapping.PersistentClass getPersistentClass();
    Code:
       0: aload_0
       1: getfield      #4                  // Field collection:Lorg/hibernate/mapping/Collection;
       4: invokevirtual #51                 // Method org/hibernate/mapping/Collection.getOwner:()Lorg/hibernate/mapping/PersistentClass;
       7: areturn

  public boolean isComponent();
    Code:
       0: iconst_0
       1: ireturn

  public boolean isEntity();
    Code:
       0: iconst_0
       1: ireturn

  public java.lang.String getEntityName();
    Code:
       0: aload_0
       1: getfield      #4                  // Field collection:Lorg/hibernate/mapping/Collection;
       4: invokevirtual #51                 // Method org/hibernate/mapping/Collection.getOwner:()Lorg/hibernate/mapping/PersistentClass;
       7: invokevirtual #52                 // Method org/hibernate/mapping/PersistentClass.getEntityName:()Ljava/lang/String;
      10: areturn

  public void addProperty(org.hibernate.mapping.Property, org.hibernate.cfg.Ejb3Column[], org.hibernate.annotations.common.reflection.XClass);
    Code:
       0: new           #45                 // class org/hibernate/AssertionFailure
       3: dup
       4: ldc           #53                 // String addProperty to a join table of a collection: does it make sense?
       6: invokespecial #47                 // Method org/hibernate/AssertionFailure."<init>":(Ljava/lang/String;)V
       9: athrow

  public org.hibernate.mapping.Join addJoin(javax.persistence.JoinTable, boolean);
    Code:
       0: new           #45                 // class org/hibernate/AssertionFailure
       3: dup
       4: ldc           #54                 // String Add a <join> in a second pass
       6: invokespecial #47                 // Method org/hibernate/AssertionFailure."<init>":(Ljava/lang/String;)V
       9: athrow

  public java.lang.String toString();
    Code:
       0: new           #28                 // class java/lang/StringBuilder
       3: dup
       4: invokespecial #29                 // Method java/lang/StringBuilder."<init>":()V
       7: aload_0
       8: invokespecial #55                 // Method java/lang/Object.toString:()Ljava/lang/String;
      11: invokevirtual #31                 // Method java/lang/StringBuilder.append:(Ljava/lang/String;)Ljava/lang/StringBuilder;
      14: ldc           #56                 // String (
      16: invokevirtual #31                 // Method java/lang/StringBuilder.append:(Ljava/lang/String;)Ljava/lang/StringBuilder;
      19: aload_0
      20: getfield      #4                  // Field collection:Lorg/hibernate/mapping/Collection;
      23: invokevirtual #24                 // Method org/hibernate/mapping/Collection.getRole:()Ljava/lang/String;
      26: invokevirtual #31                 // Method java/lang/StringBuilder.append:(Ljava/lang/String;)Ljava/lang/StringBuilder;
      29: ldc           #57                 // String )
      31: invokevirtual #31                 // Method java/lang/StringBuilder.append:(Ljava/lang/String;)Ljava/lang/StringBuilder;
      34: invokevirtual #33                 // Method java/lang/StringBuilder.toString:()Ljava/lang/String;
      37: areturn

  public void prepare(org.hibernate.annotations.common.reflection.XProperty);
    Code:
       0: aload_0
       1: getfield      #58                 // Field prepared:Z
       4: ifeq          8
       7: return
       8: aload_1
       9: ifnonnull     13
      12: return
      13: aload_0
      14: iconst_1
      15: putfield      #58                 // Field prepared:Z
      18: aload_0
      19: getfield      #4                  // Field collection:Lorg/hibernate/mapping/Collection;
      22: invokevirtual #17                 // Method org/hibernate/mapping/Collection.isMap:()Z
      25: ifeq          104
      28: aload_1
      29: ldc           #59                 // class javax/persistence/MapKeyEnumerated
      31: invokeinterface #60,  2           // InterfaceMethod org/hibernate/annotations/common/reflection/XProperty.isAnnotationPresent:(Ljava/lang/Class;)Z
      36: ifeq          47
      39: aload_0
      40: iconst_0
      41: putfield      #3                  // Field canKeyBeConverted:Z
      44: goto          109
      47: aload_1
      48: ldc           #61                 // class javax/persistence/MapKeyTemporal
      50: invokeinterface #60,  2           // InterfaceMethod org/hibernate/annotations/common/reflection/XProperty.isAnnotationPresent:(Ljava/lang/Class;)Z
      55: ifeq          66
      58: aload_0
      59: iconst_0
      60: putfield      #3                  // Field canKeyBeConverted:Z
      63: goto          109
      66: aload_1
      67: ldc           #62                 // class javax/persistence/MapKeyClass
      69: invokeinterface #60,  2           // InterfaceMethod org/hibernate/annotations/common/reflection/XProperty.isAnnotationPresent:(Ljava/lang/Class;)Z
      74: ifeq          85
      77: aload_0
      78: iconst_0
      79: putfield      #3                  // Field canKeyBeConverted:Z
      82: goto          109
      85: aload_1
      86: ldc           #63                 // class org/hibernate/annotations/MapKeyType
      88: invokeinterface #60,  2           // InterfaceMethod org/hibernate/annotations/common/reflection/XProperty.isAnnotationPresent:(Ljava/lang/Class;)Z
      93: ifeq          109
      96: aload_0
      97: iconst_0
      98: putfield      #3                  // Field canKeyBeConverted:Z
     101: goto          109
     104: aload_0
     105: iconst_0
     106: putfield      #3                  // Field canKeyBeConverted:Z
     109: aload_1
     110: ldc           #64                 // class org/hibernate/annotations/ManyToAny
     112: invokeinterface #60,  2           // InterfaceMethod org/hibernate/annotations/common/reflection/XProperty.isAnnotationPresent:(Ljava/lang/Class;)Z
     117: ifeq          128
     120: aload_0
     121: iconst_0
     122: putfield      #2                  // Field canElementBeConverted:Z
     125: goto          220
     128: aload_1
     129: ldc           #65                 // class javax/persistence/OneToMany
     131: invokeinterface #60,  2           // InterfaceMethod org/hibernate/annotations/common/reflection/XProperty.isAnnotationPresent:(Ljava/lang/Class;)Z
     136: ifeq          147
     139: aload_0
     140: iconst_0
     141: putfield      #2                  // Field canElementBeConverted:Z
     144: goto          220
     147: aload_1
     148: ldc           #66                 // class javax/persistence/ManyToMany
     150: invokeinterface #60,  2           // InterfaceMethod org/hibernate/annotations/common/reflection/XProperty.isAnnotationPresent:(Ljava/lang/Class;)Z
     155: ifeq          166
     158: aload_0
     159: iconst_0
     160: putfield      #2                  // Field canElementBeConverted:Z
     163: goto          220
     166: aload_1
     167: ldc           #67                 // class javax/persistence/Enumerated
     169: invokeinterface #60,  2           // InterfaceMethod org/hibernate/annotations/common/reflection/XProperty.isAnnotationPresent:(Ljava/lang/Class;)Z
     174: ifeq          185
     177: aload_0
     178: iconst_0
     179: putfield      #2                  // Field canElementBeConverted:Z
     182: goto          220
     185: aload_1
     186: ldc           #68                 // class javax/persistence/Temporal
     188: invokeinterface #60,  2           // InterfaceMethod org/hibernate/annotations/common/reflection/XProperty.isAnnotationPresent:(Ljava/lang/Class;)Z
     193: ifeq          204
     196: aload_0
     197: iconst_0
     198: putfield      #2                  // Field canElementBeConverted:Z
     201: goto          220
     204: aload_1
     205: ldc           #69                 // class org/hibernate/annotations/CollectionType
     207: invokeinterface #60,  2           // InterfaceMethod org/hibernate/annotations/common/reflection/XProperty.isAnnotationPresent:(Ljava/lang/Class;)Z
     212: ifeq          220
     215: aload_0
     216: iconst_0
     217: putfield      #2                  // Field canElementBeConverted:Z
     220: aload_0
     221: getfield      #3                  // Field canKeyBeConverted:Z
     224: ifne          234
     227: aload_0
     228: getfield      #2                  // Field canElementBeConverted:Z
     231: ifeq          247
     234: aload_0
     235: aload_1
     236: aload_0
     237: getfield      #8                  // Field elementAttributeConversionInfoMap:Ljava/util/Map;
     240: aload_0
     241: getfield      #9                  // Field keyAttributeConversionInfoMap:Ljava/util/Map;
     244: invokespecial #70                 // Method buildAttributeConversionInfoMaps:(Lorg/hibernate/annotations/common/reflection/XProperty;Ljava/util/Map;Ljava/util/Map;)V
     247: return

  public org.hibernate.cfg.AttributeConverterDefinition resolveElementAttributeConverterDefinition(org.hibernate.annotations.common.reflection.XClass);
    Code:
       0: aload_0
       1: ldc           #44                 // String element
       3: invokevirtual #71                 // Method locateAttributeConversionInfo:(Ljava/lang/String;)Lorg/hibernate/cfg/AttributeConversionInfo;
       6: astore_2
       7: aload_2
       8: ifnull        55
      11: aload_2
      12: invokevirtual #72                 // Method org/hibernate/cfg/AttributeConversionInfo.isConversionDisabled:()Z
      15: ifeq          20
      18: aconst_null
      19: areturn
      20: aload_0
      21: aload_2
      22: invokevirtual #73                 // Method makeAttributeConverterDefinition:(Lorg/hibernate/cfg/AttributeConversionInfo;)Lorg/hibernate/cfg/AttributeConverterDefinition;
      25: areturn
      26: astore_3
      27: new           #27                 // class java/lang/IllegalStateException
      30: dup
      31: ldc           #75                 // String Unable to instantiate AttributeConverter [%s
      33: iconst_1
      34: anewarray     #76                 // class java/lang/Object
      37: dup
      38: iconst_0
      39: aload_2
      40: invokevirtual #77                 // Method org/hibernate/cfg/AttributeConversionInfo.getConverterClass:()Ljava/lang/Class;
      43: invokevirtual #78                 // Method java/lang/Class.getName:()Ljava/lang/String;
      46: aastore
      47: invokestatic  #79                 // Method java/lang/String.format:(Ljava/lang/String;[Ljava/lang/Object;)Ljava/lang/String;
      50: aload_3
      51: invokespecial #80                 // Method java/lang/IllegalStateException."<init>":(Ljava/lang/String;Ljava/lang/Throwable;)V
      54: athrow
      55: getstatic     #23                 // Field log:Lorg/hibernate/internal/CoreMessageLogger;
      58: ldc           #81                 // String Attempting to locate auto-apply AttributeConverter for collection element [%s]
      60: aload_0
      61: getfield      #4                  // Field collection:Lorg/hibernate/mapping/Collection;
      64: invokevirtual #24                 // Method org/hibernate/mapping/Collection.getRole:()Ljava/lang/String;
      67: invokeinterface #82,  3           // InterfaceMethod org/hibernate/internal/CoreMessageLogger.debugf:(Ljava/lang/String;Ljava/lang/Object;)V
      72: aload_0
      73: aload_1
      74: invokespecial #83                 // Method determineElementClass:(Lorg/hibernate/annotations/common/reflection/XClass;)Ljava/lang/Class;
      77: astore_3
      78: aload_3
      79: ifnull        182
      82: aload_0
      83: invokevirtual #84                 // Method getContext:()Lorg/hibernate/boot/spi/MetadataBuildingContext;
      86: invokeinterface #85,  1           // InterfaceMethod org/hibernate/boot/spi/MetadataBuildingContext.getMetadataCollector:()Lorg/hibernate/boot/spi/InFlightMetadataCollector;
      91: invokeinterface #86,  1           // InterfaceMethod org/hibernate/boot/spi/InFlightMetadataCollector.getAttributeConverters:()Ljava/util/Collection;
      96: invokeinterface #87,  1           // InterfaceMethod java/util/Collection.iterator:()Ljava/util/Iterator;
     101: astore        4
     103: aload         4
     105: invokeinterface #88,  1           // InterfaceMethod java/util/Iterator.hasNext:()Z
     110: ifeq          182
     113: aload         4
     115: invokeinterface #89,  1           // InterfaceMethod java/util/Iterator.next:()Ljava/lang/Object;
     120: checkcast     #90                 // class org/hibernate/cfg/AttributeConverterDefinition
     123: astore        5
     125: aload         5
     127: invokevirtual #91                 // Method org/hibernate/cfg/AttributeConverterDefinition.isAutoApply:()Z
     130: ifne          136
     133: goto          103
     136: getstatic     #23                 // Field log:Lorg/hibernate/internal/CoreMessageLogger;
     139: ldc           #92                 // String Checking auto-apply AttributeConverter [%s] type [%s] for match [%s]
     141: aload         5
     143: invokevirtual #93                 // Method org/hibernate/cfg/AttributeConverterDefinition.toString:()Ljava/lang/String;
     146: aload         5
     148: invokevirtual #94                 // Method org/hibernate/cfg/AttributeConverterDefinition.getEntityAttributeType:()Ljava/lang/Class;
     151: invokevirtual #95                 // Method java/lang/Class.getSimpleName:()Ljava/lang/String;
     154: aload_3
     155: invokevirtual #95                 // Method java/lang/Class.getSimpleName:()Ljava/lang/String;
     158: invokeinterface #96,  5           // InterfaceMethod org/hibernate/internal/CoreMessageLogger.debugf:(Ljava/lang/String;Ljava/lang/Object;Ljava/lang/Object;Ljava/lang/Object;)V
     163: aload_0
     164: aload         5
     166: invokevirtual #94                 // Method org/hibernate/cfg/AttributeConverterDefinition.getEntityAttributeType:()Ljava/lang/Class;
     169: aload_3
     170: invokevirtual #97                 // Method areTypeMatch:(Ljava/lang/Class;Ljava/lang/Class;)Z
     173: ifeq          179
     176: aload         5
     178: areturn
     179: goto          103
     182: aconst_null
     183: areturn
    Exception table:
       from    to  target type
          20    25    26   Class java/lang/Exception

  private java.lang.Class determineElementClass(org.hibernate.annotations.common.reflection.XClass);
    Code:
       0: aload_1
       1: ifnull        49
       4: aload_0
       5: invokevirtual #84                 // Method getContext:()Lorg/hibernate/boot/spi/MetadataBuildingContext;
       8: invokeinterface #98,  1           // InterfaceMethod org/hibernate/boot/spi/MetadataBuildingContext.getBuildingOptions:()Lorg/hibernate/boot/spi/MetadataBuildingOptions;
      13: invokeinterface #99,  1           // InterfaceMethod org/hibernate/boot/spi/MetadataBuildingOptions.getReflectionManager:()Lorg/hibernate/annotations/common/reflection/ReflectionManager;
      18: aload_1
      19: invokeinterface #100,  2          // InterfaceMethod org/hibernate/annotations/common/reflection/ReflectionManager.toClass:(Lorg/hibernate/annotations/common/reflection/XClass;)Ljava/lang/Class;
      24: areturn
      25: astore_2
      26: getstatic     #23                 // Field log:Lorg/hibernate/internal/CoreMessageLogger;
      29: ldc           #101                // String Unable to resolve XClass [%s] to Class for collection elements [%s]
      31: aload_1
      32: invokeinterface #102,  1          // InterfaceMethod org/hibernate/annotations/common/reflection/XClass.getName:()Ljava/lang/String;
      37: aload_0
      38: getfield      #4                  // Field collection:Lorg/hibernate/mapping/Collection;
      41: invokevirtual #24                 // Method org/hibernate/mapping/Collection.getRole:()Ljava/lang/String;
      44: invokeinterface #103,  4          // InterfaceMethod org/hibernate/internal/CoreMessageLogger.debugf:(Ljava/lang/String;Ljava/lang/Object;Ljava/lang/Object;)V
      49: aload_0
      50: getfield      #4                  // Field collection:Lorg/hibernate/mapping/Collection;
      53: invokevirtual #104                // Method org/hibernate/mapping/Collection.getElement:()Lorg/hibernate/mapping/Value;
      56: ifnull        92
      59: aload_0
      60: getfield      #4                  // Field collection:Lorg/hibernate/mapping/Collection;
      63: invokevirtual #104                // Method org/hibernate/mapping/Collection.getElement:()Lorg/hibernate/mapping/Value;
      66: invokeinterface #105,  1          // InterfaceMethod org/hibernate/mapping/Value.getType:()Lorg/hibernate/type/Type;
      71: ifnull        92
      74: aload_0
      75: getfield      #4                  // Field collection:Lorg/hibernate/mapping/Collection;
      78: invokevirtual #104                // Method org/hibernate/mapping/Collection.getElement:()Lorg/hibernate/mapping/Value;
      81: invokeinterface #105,  1          // InterfaceMethod org/hibernate/mapping/Value.getType:()Lorg/hibernate/type/Type;
      86: invokeinterface #106,  1          // InterfaceMethod org/hibernate/type/Type.getReturnedClass:()Ljava/lang/Class;
      91: areturn
      92: getstatic     #23                 // Field log:Lorg/hibernate/internal/CoreMessageLogger;
      95: ldc           #107                // String Unable to resolve element information for collection [%s]
      97: aload_0
      98: getfield      #4                  // Field collection:Lorg/hibernate/mapping/Collection;
     101: invokevirtual #24                 // Method org/hibernate/mapping/Collection.getRole:()Ljava/lang/String;
     104: invokeinterface #82,  3           // InterfaceMethod org/hibernate/internal/CoreMessageLogger.debugf:(Ljava/lang/String;Ljava/lang/Object;)V
     109: aconst_null
     110: areturn
    Exception table:
       from    to  target type
           4    24    25   Class java/lang/Exception

  public org.hibernate.cfg.AttributeConverterDefinition keyElementAttributeConverterDefinition(org.hibernate.annotations.common.reflection.XClass);
    Code:
       0: aload_0
       1: ldc           #20                 // String key
       3: invokevirtual #71                 // Method locateAttributeConversionInfo:(Ljava/lang/String;)Lorg/hibernate/cfg/AttributeConversionInfo;
       6: astore_2
       7: aload_2
       8: ifnull        55
      11: aload_2
      12: invokevirtual #72                 // Method org/hibernate/cfg/AttributeConversionInfo.isConversionDisabled:()Z
      15: ifeq          20
      18: aconst_null
      19: areturn
      20: aload_0
      21: aload_2
      22: invokevirtual #73                 // Method makeAttributeConverterDefinition:(Lorg/hibernate/cfg/AttributeConversionInfo;)Lorg/hibernate/cfg/AttributeConverterDefinition;
      25: areturn
      26: astore_3
      27: new           #27                 // class java/lang/IllegalStateException
      30: dup
      31: ldc           #75                 // String Unable to instantiate AttributeConverter [%s
      33: iconst_1
      34: anewarray     #76                 // class java/lang/Object
      37: dup
      38: iconst_0
      39: aload_2
      40: invokevirtual #77                 // Method org/hibernate/cfg/AttributeConversionInfo.getConverterClass:()Ljava/lang/Class;
      43: invokevirtual #78                 // Method java/lang/Class.getName:()Ljava/lang/String;
      46: aastore
      47: invokestatic  #79                 // Method java/lang/String.format:(Ljava/lang/String;[Ljava/lang/Object;)Ljava/lang/String;
      50: aload_3
      51: invokespecial #80                 // Method java/lang/IllegalStateException."<init>":(Ljava/lang/String;Ljava/lang/Throwable;)V
      54: athrow
      55: getstatic     #23                 // Field log:Lorg/hibernate/internal/CoreMessageLogger;
      58: ldc           #108                // String Attempting to locate auto-apply AttributeConverter for collection key [%s]
      60: aload_0
      61: getfield      #4                  // Field collection:Lorg/hibernate/mapping/Collection;
      64: invokevirtual #24                 // Method org/hibernate/mapping/Collection.getRole:()Ljava/lang/String;
      67: invokeinterface #82,  3           // InterfaceMethod org/hibernate/internal/CoreMessageLogger.debugf:(Ljava/lang/String;Ljava/lang/Object;)V
      72: aload_0
      73: aload_1
      74: invokespecial #109                // Method determineKeyClass:(Lorg/hibernate/annotations/common/reflection/XClass;)Ljava/lang/Class;
      77: astore_3
      78: aload_3
      79: ifnull        182
      82: aload_0
      83: invokevirtual #84                 // Method getContext:()Lorg/hibernate/boot/spi/MetadataBuildingContext;
      86: invokeinterface #85,  1           // InterfaceMethod org/hibernate/boot/spi/MetadataBuildingContext.getMetadataCollector:()Lorg/hibernate/boot/spi/InFlightMetadataCollector;
      91: invokeinterface #86,  1           // InterfaceMethod org/hibernate/boot/spi/InFlightMetadataCollector.getAttributeConverters:()Ljava/util/Collection;
      96: invokeinterface #87,  1           // InterfaceMethod java/util/Collection.iterator:()Ljava/util/Iterator;
     101: astore        4
     103: aload         4
     105: invokeinterface #88,  1           // InterfaceMethod java/util/Iterator.hasNext:()Z
     110: ifeq          182
     113: aload         4
     115: invokeinterface #89,  1           // InterfaceMethod java/util/Iterator.next:()Ljava/lang/Object;
     120: checkcast     #90                 // class org/hibernate/cfg/AttributeConverterDefinition
     123: astore        5
     125: aload         5
     127: invokevirtual #91                 // Method org/hibernate/cfg/AttributeConverterDefinition.isAutoApply:()Z
     130: ifne          136
     133: goto          103
     136: getstatic     #23                 // Field log:Lorg/hibernate/internal/CoreMessageLogger;
     139: ldc           #92                 // String Checking auto-apply AttributeConverter [%s] type [%s] for match [%s]
     141: aload         5
     143: invokevirtual #93                 // Method org/hibernate/cfg/AttributeConverterDefinition.toString:()Ljava/lang/String;
     146: aload         5
     148: invokevirtual #94                 // Method org/hibernate/cfg/AttributeConverterDefinition.getEntityAttributeType:()Ljava/lang/Class;
     151: invokevirtual #95                 // Method java/lang/Class.getSimpleName:()Ljava/lang/String;
     154: aload_3
     155: invokevirtual #95                 // Method java/lang/Class.getSimpleName:()Ljava/lang/String;
     158: invokeinterface #96,  5           // InterfaceMethod org/hibernate/internal/CoreMessageLogger.debugf:(Ljava/lang/String;Ljava/lang/Object;Ljava/lang/Object;Ljava/lang/Object;)V
     163: aload_0
     164: aload         5
     166: invokevirtual #94                 // Method org/hibernate/cfg/AttributeConverterDefinition.getEntityAttributeType:()Ljava/lang/Class;
     169: aload_3
     170: invokevirtual #97                 // Method areTypeMatch:(Ljava/lang/Class;Ljava/lang/Class;)Z
     173: ifeq          179
     176: aload         5
     178: areturn
     179: goto          103
     182: aconst_null
     183: areturn
    Exception table:
       from    to  target type
          20    25    26   Class java/lang/Exception

  private java.lang.Class determineKeyClass(org.hibernate.annotations.common.reflection.XClass);
    Code:
       0: aload_1
       1: ifnull        49
       4: aload_0
       5: invokevirtual #84                 // Method getContext:()Lorg/hibernate/boot/spi/MetadataBuildingContext;
       8: invokeinterface #98,  1           // InterfaceMethod org/hibernate/boot/spi/MetadataBuildingContext.getBuildingOptions:()Lorg/hibernate/boot/spi/MetadataBuildingOptions;
      13: invokeinterface #99,  1           // InterfaceMethod org/hibernate/boot/spi/MetadataBuildingOptions.getReflectionManager:()Lorg/hibernate/annotations/common/reflection/ReflectionManager;
      18: aload_1
      19: invokeinterface #100,  2          // InterfaceMethod org/hibernate/annotations/common/reflection/ReflectionManager.toClass:(Lorg/hibernate/annotations/common/reflection/XClass;)Ljava/lang/Class;
      24: areturn
      25: astore_2
      26: getstatic     #23                 // Field log:Lorg/hibernate/internal/CoreMessageLogger;
      29: ldc           #110                // String Unable to resolve XClass [%s] to Class for collection key [%s]
      31: aload_1
      32: invokeinterface #102,  1          // InterfaceMethod org/hibernate/annotations/common/reflection/XClass.getName:()Ljava/lang/String;
      37: aload_0
      38: getfield      #4                  // Field collection:Lorg/hibernate/mapping/Collection;
      41: invokevirtual #24                 // Method org/hibernate/mapping/Collection.getRole:()Ljava/lang/String;
      44: invokeinterface #103,  4          // InterfaceMethod org/hibernate/internal/CoreMessageLogger.debugf:(Ljava/lang/String;Ljava/lang/Object;Ljava/lang/Object;)V
      49: aload_0
      50: getfield      #4                  // Field collection:Lorg/hibernate/mapping/Collection;
      53: checkcast     #111                // class org/hibernate/mapping/IndexedCollection
      56: astore_2
      57: aload_2
      58: invokevirtual #112                // Method org/hibernate/mapping/IndexedCollection.getIndex:()Lorg/hibernate/mapping/Value;
      61: ifnull        91
      64: aload_2
      65: invokevirtual #112                // Method org/hibernate/mapping/IndexedCollection.getIndex:()Lorg/hibernate/mapping/Value;
      68: invokeinterface #105,  1          // InterfaceMethod org/hibernate/mapping/Value.getType:()Lorg/hibernate/type/Type;
      73: ifnull        91
      76: aload_2
      77: invokevirtual #112                // Method org/hibernate/mapping/IndexedCollection.getIndex:()Lorg/hibernate/mapping/Value;
      80: invokeinterface #105,  1          // InterfaceMethod org/hibernate/mapping/Value.getType:()Lorg/hibernate/type/Type;
      85: invokeinterface #106,  1          // InterfaceMethod org/hibernate/type/Type.getReturnedClass:()Ljava/lang/Class;
      90: areturn
      91: getstatic     #23                 // Field log:Lorg/hibernate/internal/CoreMessageLogger;
      94: ldc           #113                // String Unable to resolve key information for collection [%s]
      96: aload_0
      97: getfield      #4                  // Field collection:Lorg/hibernate/mapping/Collection;
     100: invokevirtual #24                 // Method org/hibernate/mapping/Collection.getRole:()Ljava/lang/String;
     103: invokeinterface #82,  3           // InterfaceMethod org/hibernate/internal/CoreMessageLogger.debugf:(Ljava/lang/String;Ljava/lang/Object;)V
     108: aconst_null
     109: areturn
    Exception table:
       from    to  target type
           4    24    25   Class java/lang/Exception

  static {};
    Code:
       0: ldc           #114                // class org/hibernate/cfg/CollectionPropertyHolder
       2: invokestatic  #115                // Method org/hibernate/internal/CoreLogging.messageLogger:(Ljava/lang/Class;)Lorg/hibernate/internal/CoreMessageLogger;
       5: putstatic     #23                 // Field log:Lorg/hibernate/internal/CoreMessageLogger;
       8: return
}
