Compiled from "ExternalSessionFactoryConfig.java"
public abstract class org.hibernate.cfg.ExternalSessionFactoryConfig {
  private java.lang.String mapResources;

  private java.lang.String dialect;

  private java.lang.String defaultSchema;

  private java.lang.String defaultCatalog;

  private java.lang.String maximumFetchDepth;

  private java.lang.String jdbcFetchSize;

  private java.lang.String jdbcBatchSize;

  private java.lang.String batchVersionedDataEnabled;

  private java.lang.String jdbcScrollableResultSetEnabled;

  private java.lang.String getGeneratedKeysEnabled;

  private java.lang.String streamsForBinaryEnabled;

  private java.lang.String reflectionOptimizationEnabled;

  private java.lang.String querySubstitutions;

  private java.lang.String showSqlEnabled;

  private java.lang.String commentsEnabled;

  private java.lang.String cacheRegionFactory;

  private java.lang.String cacheProviderConfig;

  private java.lang.String cacheRegionPrefix;

  private java.lang.String secondLevelCacheEnabled;

  private java.lang.String minimalPutsEnabled;

  private java.lang.String queryCacheEnabled;

  private java.util.Map additionalProperties;

  private java.util.Set excludedPropertyNames;

  public org.hibernate.cfg.ExternalSessionFactoryConfig();
    Code:
       0: aload_0
       1: invokespecial #1                  // Method java/lang/Object."<init>":()V
       4: aload_0
       5: new           #2                  // class java/util/HashSet
       8: dup
       9: invokespecial #3                  // Method java/util/HashSet."<init>":()V
      12: putfield      #4                  // Field excludedPropertyNames:Ljava/util/Set;
      15: return

  protected java.util.Set getExcludedPropertyNames();
    Code:
       0: aload_0
       1: getfield      #4                  // Field excludedPropertyNames:Ljava/util/Set;
       4: areturn

  public final java.lang.String getMapResources();
    Code:
       0: aload_0
       1: getfield      #5                  // Field mapResources:Ljava/lang/String;
       4: areturn

  public final void setMapResources(java.lang.String);
    Code:
       0: aload_0
       1: aload_1
       2: putfield      #5                  // Field mapResources:Ljava/lang/String;
       5: return

  public void addMapResource(java.lang.String);
    Code:
       0: aload_0
       1: getfield      #5                  // Field mapResources:Ljava/lang/String;
       4: ifnull        17
       7: aload_0
       8: getfield      #5                  // Field mapResources:Ljava/lang/String;
      11: invokevirtual #6                  // Method java/lang/String.length:()I
      14: ifne          28
      17: aload_0
      18: aload_1
      19: invokevirtual #7                  // Method java/lang/String.trim:()Ljava/lang/String;
      22: putfield      #5                  // Field mapResources:Ljava/lang/String;
      25: goto          61
      28: new           #8                  // class java/lang/StringBuilder
      31: dup
      32: invokespecial #9                  // Method java/lang/StringBuilder."<init>":()V
      35: aload_0
      36: dup_x1
      37: getfield      #5                  // Field mapResources:Ljava/lang/String;
      40: invokevirtual #10                 // Method java/lang/StringBuilder.append:(Ljava/lang/String;)Ljava/lang/StringBuilder;
      43: ldc           #11                 // String ,
      45: invokevirtual #10                 // Method java/lang/StringBuilder.append:(Ljava/lang/String;)Ljava/lang/StringBuilder;
      48: aload_1
      49: invokevirtual #7                  // Method java/lang/String.trim:()Ljava/lang/String;
      52: invokevirtual #10                 // Method java/lang/StringBuilder.append:(Ljava/lang/String;)Ljava/lang/StringBuilder;
      55: invokevirtual #12                 // Method java/lang/StringBuilder.toString:()Ljava/lang/String;
      58: putfield      #5                  // Field mapResources:Ljava/lang/String;
      61: return

  public final java.lang.String getDialect();
    Code:
       0: aload_0
       1: getfield      #13                 // Field dialect:Ljava/lang/String;
       4: areturn

  public final void setDialect(java.lang.String);
    Code:
       0: aload_0
       1: aload_1
       2: putfield      #13                 // Field dialect:Ljava/lang/String;
       5: return

  public final java.lang.String getDefaultSchema();
    Code:
       0: aload_0
       1: getfield      #14                 // Field defaultSchema:Ljava/lang/String;
       4: areturn

  public final void setDefaultSchema(java.lang.String);
    Code:
       0: aload_0
       1: aload_1
       2: putfield      #14                 // Field defaultSchema:Ljava/lang/String;
       5: return

  public final java.lang.String getDefaultCatalog();
    Code:
       0: aload_0
       1: getfield      #15                 // Field defaultCatalog:Ljava/lang/String;
       4: areturn

  public final void setDefaultCatalog(java.lang.String);
    Code:
       0: aload_0
       1: aload_1
       2: putfield      #15                 // Field defaultCatalog:Ljava/lang/String;
       5: return

  public final java.lang.String getMaximumFetchDepth();
    Code:
       0: aload_0
       1: getfield      #16                 // Field maximumFetchDepth:Ljava/lang/String;
       4: areturn

  public final void setMaximumFetchDepth(java.lang.String);
    Code:
       0: aload_0
       1: aload_1
       2: invokespecial #17                 // Method verifyInt:(Ljava/lang/String;)V
       5: aload_0
       6: aload_1
       7: putfield      #16                 // Field maximumFetchDepth:Ljava/lang/String;
      10: return

  public final java.lang.String getJdbcFetchSize();
    Code:
       0: aload_0
       1: getfield      #18                 // Field jdbcFetchSize:Ljava/lang/String;
       4: areturn

  public final void setJdbcFetchSize(java.lang.String);
    Code:
       0: aload_0
       1: aload_1
       2: invokespecial #17                 // Method verifyInt:(Ljava/lang/String;)V
       5: aload_0
       6: aload_1
       7: putfield      #18                 // Field jdbcFetchSize:Ljava/lang/String;
      10: return

  public final java.lang.String getJdbcBatchSize();
    Code:
       0: aload_0
       1: getfield      #19                 // Field jdbcBatchSize:Ljava/lang/String;
       4: areturn

  public final void setJdbcBatchSize(java.lang.String);
    Code:
       0: aload_0
       1: aload_1
       2: invokespecial #17                 // Method verifyInt:(Ljava/lang/String;)V
       5: aload_0
       6: aload_1
       7: putfield      #19                 // Field jdbcBatchSize:Ljava/lang/String;
      10: return

  public final java.lang.String getBatchVersionedDataEnabled();
    Code:
       0: aload_0
       1: getfield      #20                 // Field batchVersionedDataEnabled:Ljava/lang/String;
       4: areturn

  public final void setBatchVersionedDataEnabled(java.lang.String);
    Code:
       0: aload_0
       1: aload_1
       2: putfield      #20                 // Field batchVersionedDataEnabled:Ljava/lang/String;
       5: return

  public final java.lang.String getJdbcScrollableResultSetEnabled();
    Code:
       0: aload_0
       1: getfield      #21                 // Field jdbcScrollableResultSetEnabled:Ljava/lang/String;
       4: areturn

  public final void setJdbcScrollableResultSetEnabled(java.lang.String);
    Code:
       0: aload_0
       1: aload_1
       2: putfield      #21                 // Field jdbcScrollableResultSetEnabled:Ljava/lang/String;
       5: return

  public final java.lang.String getGetGeneratedKeysEnabled();
    Code:
       0: aload_0
       1: getfield      #22                 // Field getGeneratedKeysEnabled:Ljava/lang/String;
       4: areturn

  public final void setGetGeneratedKeysEnabled(java.lang.String);
    Code:
       0: aload_0
       1: aload_1
       2: putfield      #22                 // Field getGeneratedKeysEnabled:Ljava/lang/String;
       5: return

  public final java.lang.String getStreamsForBinaryEnabled();
    Code:
       0: aload_0
       1: getfield      #23                 // Field streamsForBinaryEnabled:Ljava/lang/String;
       4: areturn

  public final void setStreamsForBinaryEnabled(java.lang.String);
    Code:
       0: aload_0
       1: aload_1
       2: putfield      #23                 // Field streamsForBinaryEnabled:Ljava/lang/String;
       5: return

  public final java.lang.String getReflectionOptimizationEnabled();
    Code:
       0: aload_0
       1: getfield      #24                 // Field reflectionOptimizationEnabled:Ljava/lang/String;
       4: areturn

  public final void setReflectionOptimizationEnabled(java.lang.String);
    Code:
       0: aload_0
       1: aload_1
       2: putfield      #24                 // Field reflectionOptimizationEnabled:Ljava/lang/String;
       5: return

  public final java.lang.String getQuerySubstitutions();
    Code:
       0: aload_0
       1: getfield      #25                 // Field querySubstitutions:Ljava/lang/String;
       4: areturn

  public final void setQuerySubstitutions(java.lang.String);
    Code:
       0: aload_0
       1: aload_1
       2: putfield      #25                 // Field querySubstitutions:Ljava/lang/String;
       5: return

  public final java.lang.String getShowSqlEnabled();
    Code:
       0: aload_0
       1: getfield      #26                 // Field showSqlEnabled:Ljava/lang/String;
       4: areturn

  public final void setShowSqlEnabled(java.lang.String);
    Code:
       0: aload_0
       1: aload_1
       2: putfield      #26                 // Field showSqlEnabled:Ljava/lang/String;
       5: return

  public final java.lang.String getCommentsEnabled();
    Code:
       0: aload_0
       1: getfield      #27                 // Field commentsEnabled:Ljava/lang/String;
       4: areturn

  public final void setCommentsEnabled(java.lang.String);
    Code:
       0: aload_0
       1: aload_1
       2: putfield      #27                 // Field commentsEnabled:Ljava/lang/String;
       5: return

  public final java.lang.String getSecondLevelCacheEnabled();
    Code:
       0: aload_0
       1: getfield      #28                 // Field secondLevelCacheEnabled:Ljava/lang/String;
       4: areturn

  public final void setSecondLevelCacheEnabled(java.lang.String);
    Code:
       0: aload_0
       1: aload_1
       2: putfield      #28                 // Field secondLevelCacheEnabled:Ljava/lang/String;
       5: return

  public final java.lang.String getCacheRegionFactory();
    Code:
       0: aload_0
       1: getfield      #29                 // Field cacheRegionFactory:Ljava/lang/String;
       4: areturn

  public final void setCacheRegionFactory(java.lang.String);
    Code:
       0: aload_0
       1: aload_1
       2: putfield      #29                 // Field cacheRegionFactory:Ljava/lang/String;
       5: return

  public java.lang.String getCacheProviderConfig();
    Code:
       0: aload_0
       1: getfield      #30                 // Field cacheProviderConfig:Ljava/lang/String;
       4: areturn

  public void setCacheProviderConfig(java.lang.String);
    Code:
       0: aload_0
       1: aload_1
       2: putfield      #30                 // Field cacheProviderConfig:Ljava/lang/String;
       5: return

  public final java.lang.String getCacheRegionPrefix();
    Code:
       0: aload_0
       1: getfield      #31                 // Field cacheRegionPrefix:Ljava/lang/String;
       4: areturn

  public final void setCacheRegionPrefix(java.lang.String);
    Code:
       0: aload_0
       1: aload_1
       2: putfield      #31                 // Field cacheRegionPrefix:Ljava/lang/String;
       5: return

  public final java.lang.String getMinimalPutsEnabled();
    Code:
       0: aload_0
       1: getfield      #32                 // Field minimalPutsEnabled:Ljava/lang/String;
       4: areturn

  public final void setMinimalPutsEnabled(java.lang.String);
    Code:
       0: aload_0
       1: aload_1
       2: putfield      #32                 // Field minimalPutsEnabled:Ljava/lang/String;
       5: return

  public final java.lang.String getQueryCacheEnabled();
    Code:
       0: aload_0
       1: getfield      #33                 // Field queryCacheEnabled:Ljava/lang/String;
       4: areturn

  public final void setQueryCacheEnabled(java.lang.String);
    Code:
       0: aload_0
       1: aload_1
       2: putfield      #33                 // Field queryCacheEnabled:Ljava/lang/String;
       5: return

  public final void addAdditionalProperty(java.lang.String, java.lang.String);
    Code:
       0: aload_0
       1: invokevirtual #34                 // Method getExcludedPropertyNames:()Ljava/util/Set;
       4: aload_1
       5: invokeinterface #35,  2           // InterfaceMethod java/util/Set.contains:(Ljava/lang/Object;)Z
      10: ifne          43
      13: aload_0
      14: getfield      #36                 // Field additionalProperties:Ljava/util/Map;
      17: ifnonnull     31
      20: aload_0
      21: new           #37                 // class java/util/HashMap
      24: dup
      25: invokespecial #38                 // Method java/util/HashMap."<init>":()V
      28: putfield      #36                 // Field additionalProperties:Ljava/util/Map;
      31: aload_0
      32: getfield      #36                 // Field additionalProperties:Ljava/util/Map;
      35: aload_1
      36: aload_2
      37: invokeinterface #39,  3           // InterfaceMethod java/util/Map.put:(Ljava/lang/Object;Ljava/lang/Object;)Ljava/lang/Object;
      42: pop
      43: return

  protected final org.hibernate.cfg.Configuration buildConfiguration();
    Code:
       0: new           #40                 // class org/hibernate/cfg/Configuration
       3: dup
       4: invokespecial #41                 // Method org/hibernate/cfg/Configuration."<init>":()V
       7: aload_0
       8: invokevirtual #42                 // Method buildProperties:()Ljava/util/Properties;
      11: invokevirtual #43                 // Method org/hibernate/cfg/Configuration.setProperties:(Ljava/util/Properties;)Lorg/hibernate/cfg/Configuration;
      14: astore_1
      15: aload_0
      16: getfield      #5                  // Field mapResources:Ljava/lang/String;
      19: ldc           #44                 // String  ,\n\t\r\f
      21: invokestatic  #45                 // Method org/hibernate/internal/util/config/ConfigurationHelper.toStringArray:(Ljava/lang/String;Ljava/lang/String;)[Ljava/lang/String;
      24: astore_2
      25: iconst_0
      26: istore_3
      27: iload_3
      28: aload_2
      29: arraylength
      30: if_icmpge     47
      33: aload_1
      34: aload_2
      35: iload_3
      36: aaload
      37: invokevirtual #46                 // Method org/hibernate/cfg/Configuration.addResource:(Ljava/lang/String;)Lorg/hibernate/cfg/Configuration;
      40: pop
      41: iinc          3, 1
      44: goto          27
      47: aload_1
      48: areturn

  protected final java.util.Properties buildProperties();
    Code:
       0: new           #47                 // class java/util/Properties
       3: dup
       4: invokespecial #48                 // Method java/util/Properties."<init>":()V
       7: astore_1
       8: aload_0
       9: aload_1
      10: ldc           #50                 // String hibernate.dialect
      12: aload_0
      13: getfield      #13                 // Field dialect:Ljava/lang/String;
      16: invokespecial #51                 // Method setUnlessNull:(Ljava/util/Properties;Ljava/lang/String;Ljava/lang/String;)V
      19: aload_0
      20: aload_1
      21: ldc           #52                 // String hibernate.default_schema
      23: aload_0
      24: getfield      #14                 // Field defaultSchema:Ljava/lang/String;
      27: invokespecial #51                 // Method setUnlessNull:(Ljava/util/Properties;Ljava/lang/String;Ljava/lang/String;)V
      30: aload_0
      31: aload_1
      32: ldc           #53                 // String hibernate.default_catalog
      34: aload_0
      35: getfield      #15                 // Field defaultCatalog:Ljava/lang/String;
      38: invokespecial #51                 // Method setUnlessNull:(Ljava/util/Properties;Ljava/lang/String;Ljava/lang/String;)V
      41: aload_0
      42: aload_1
      43: ldc           #54                 // String hibernate.max_fetch_depth
      45: aload_0
      46: getfield      #16                 // Field maximumFetchDepth:Ljava/lang/String;
      49: invokespecial #51                 // Method setUnlessNull:(Ljava/util/Properties;Ljava/lang/String;Ljava/lang/String;)V
      52: aload_0
      53: aload_1
      54: ldc           #55                 // String hibernate.jdbc.fetch_size
      56: aload_0
      57: getfield      #18                 // Field jdbcFetchSize:Ljava/lang/String;
      60: invokespecial #51                 // Method setUnlessNull:(Ljava/util/Properties;Ljava/lang/String;Ljava/lang/String;)V
      63: aload_0
      64: aload_1
      65: ldc           #56                 // String hibernate.jdbc.batch_size
      67: aload_0
      68: getfield      #19                 // Field jdbcBatchSize:Ljava/lang/String;
      71: invokespecial #51                 // Method setUnlessNull:(Ljava/util/Properties;Ljava/lang/String;Ljava/lang/String;)V
      74: aload_0
      75: aload_1
      76: ldc           #57                 // String hibernate.jdbc.batch_versioned_data
      78: aload_0
      79: getfield      #20                 // Field batchVersionedDataEnabled:Ljava/lang/String;
      82: invokespecial #51                 // Method setUnlessNull:(Ljava/util/Properties;Ljava/lang/String;Ljava/lang/String;)V
      85: aload_0
      86: aload_1
      87: ldc           #58                 // String hibernate.jdbc.use_scrollable_resultset
      89: aload_0
      90: getfield      #21                 // Field jdbcScrollableResultSetEnabled:Ljava/lang/String;
      93: invokespecial #51                 // Method setUnlessNull:(Ljava/util/Properties;Ljava/lang/String;Ljava/lang/String;)V
      96: aload_0
      97: aload_1
      98: ldc           #59                 // String hibernate.jdbc.use_get_generated_keys
     100: aload_0
     101: getfield      #22                 // Field getGeneratedKeysEnabled:Ljava/lang/String;
     104: invokespecial #51                 // Method setUnlessNull:(Ljava/util/Properties;Ljava/lang/String;Ljava/lang/String;)V
     107: aload_0
     108: aload_1
     109: ldc           #60                 // String hibernate.jdbc.use_streams_for_binary
     111: aload_0
     112: getfield      #23                 // Field streamsForBinaryEnabled:Ljava/lang/String;
     115: invokespecial #51                 // Method setUnlessNull:(Ljava/util/Properties;Ljava/lang/String;Ljava/lang/String;)V
     118: aload_0
     119: aload_1
     120: ldc           #61                 // String hibernate.bytecode.use_reflection_optimizer
     122: aload_0
     123: getfield      #24                 // Field reflectionOptimizationEnabled:Ljava/lang/String;
     126: invokespecial #51                 // Method setUnlessNull:(Ljava/util/Properties;Ljava/lang/String;Ljava/lang/String;)V
     129: aload_0
     130: aload_1
     131: ldc           #62                 // String hibernate.query.substitutions
     133: aload_0
     134: getfield      #25                 // Field querySubstitutions:Ljava/lang/String;
     137: invokespecial #51                 // Method setUnlessNull:(Ljava/util/Properties;Ljava/lang/String;Ljava/lang/String;)V
     140: aload_0
     141: aload_1
     142: ldc           #63                 // String hibernate.show_sql
     144: aload_0
     145: getfield      #26                 // Field showSqlEnabled:Ljava/lang/String;
     148: invokespecial #51                 // Method setUnlessNull:(Ljava/util/Properties;Ljava/lang/String;Ljava/lang/String;)V
     151: aload_0
     152: aload_1
     153: ldc           #64                 // String hibernate.use_sql_comments
     155: aload_0
     156: getfield      #27                 // Field commentsEnabled:Ljava/lang/String;
     159: invokespecial #51                 // Method setUnlessNull:(Ljava/util/Properties;Ljava/lang/String;Ljava/lang/String;)V
     162: aload_0
     163: aload_1
     164: ldc           #65                 // String hibernate.cache.region.factory_class
     166: aload_0
     167: getfield      #29                 // Field cacheRegionFactory:Ljava/lang/String;
     170: invokespecial #51                 // Method setUnlessNull:(Ljava/util/Properties;Ljava/lang/String;Ljava/lang/String;)V
     173: aload_0
     174: aload_1
     175: ldc           #66                 // String hibernate.cache.provider_configuration_file_resource_path
     177: aload_0
     178: getfield      #30                 // Field cacheProviderConfig:Ljava/lang/String;
     181: invokespecial #51                 // Method setUnlessNull:(Ljava/util/Properties;Ljava/lang/String;Ljava/lang/String;)V
     184: aload_0
     185: aload_1
     186: ldc           #67                 // String hibernate.cache.region_prefix
     188: aload_0
     189: getfield      #31                 // Field cacheRegionPrefix:Ljava/lang/String;
     192: invokespecial #51                 // Method setUnlessNull:(Ljava/util/Properties;Ljava/lang/String;Ljava/lang/String;)V
     195: aload_0
     196: aload_1
     197: ldc           #68                 // String hibernate.cache.use_minimal_puts
     199: aload_0
     200: getfield      #32                 // Field minimalPutsEnabled:Ljava/lang/String;
     203: invokespecial #51                 // Method setUnlessNull:(Ljava/util/Properties;Ljava/lang/String;Ljava/lang/String;)V
     206: aload_0
     207: aload_1
     208: ldc           #69                 // String hibernate.cache.use_second_level_cache
     210: aload_0
     211: getfield      #28                 // Field secondLevelCacheEnabled:Ljava/lang/String;
     214: invokespecial #51                 // Method setUnlessNull:(Ljava/util/Properties;Ljava/lang/String;Ljava/lang/String;)V
     217: aload_0
     218: aload_1
     219: ldc           #70                 // String hibernate.cache.use_query_cache
     221: aload_0
     222: getfield      #33                 // Field queryCacheEnabled:Ljava/lang/String;
     225: invokespecial #51                 // Method setUnlessNull:(Ljava/util/Properties;Ljava/lang/String;Ljava/lang/String;)V
     228: aload_0
     229: invokevirtual #71                 // Method getExtraProperties:()Ljava/util/Map;
     232: astore_2
     233: aload_2
     234: ifnull        243
     237: aload_0
     238: aload_1
     239: aload_2
     240: invokevirtual #72                 // Method addAll:(Ljava/util/Properties;Ljava/util/Map;)V
     243: aload_0
     244: getfield      #36                 // Field additionalProperties:Ljava/util/Map;
     247: ifnull        259
     250: aload_0
     251: aload_1
     252: aload_0
     253: getfield      #36                 // Field additionalProperties:Ljava/util/Map;
     256: invokevirtual #72                 // Method addAll:(Ljava/util/Properties;Ljava/util/Map;)V
     259: aload_1
     260: areturn

  protected void addAll(java.util.Properties, java.util.Map);
    Code:
       0: aload_2
       1: invokeinterface #73,  1           // InterfaceMethod java/util/Map.entrySet:()Ljava/util/Set;
       6: invokeinterface #74,  1           // InterfaceMethod java/util/Set.iterator:()Ljava/util/Iterator;
      11: astore_3
      12: aload_3
      13: invokeinterface #75,  1           // InterfaceMethod java/util/Iterator.hasNext:()Z
      18: ifeq          106
      21: aload_3
      22: invokeinterface #76,  1           // InterfaceMethod java/util/Iterator.next:()Ljava/lang/Object;
      27: checkcast     #77                 // class java/util/Map$Entry
      30: astore        4
      32: aload         4
      34: invokeinterface #78,  1           // InterfaceMethod java/util/Map$Entry.getKey:()Ljava/lang/Object;
      39: checkcast     #79                 // class java/lang/String
      42: astore        5
      44: aload         4
      46: invokeinterface #80,  1           // InterfaceMethod java/util/Map$Entry.getValue:()Ljava/lang/Object;
      51: checkcast     #79                 // class java/lang/String
      54: astore        6
      56: aload         5
      58: ifnull        103
      61: aload         6
      63: ifnull        103
      66: aload_1
      67: invokevirtual #81                 // Method java/util/Properties.keySet:()Ljava/util/Set;
      70: aload         5
      72: invokeinterface #35,  2           // InterfaceMethod java/util/Set.contains:(Ljava/lang/Object;)Z
      77: ifne          103
      80: aload_0
      81: invokevirtual #34                 // Method getExcludedPropertyNames:()Ljava/util/Set;
      84: aload         5
      86: invokeinterface #35,  2           // InterfaceMethod java/util/Set.contains:(Ljava/lang/Object;)Z
      91: ifne          103
      94: aload_1
      95: aload         5
      97: aload         6
      99: invokevirtual #82                 // Method java/util/Properties.put:(Ljava/lang/Object;Ljava/lang/Object;)Ljava/lang/Object;
     102: pop
     103: goto          12
     106: return

  protected java.util.Map getExtraProperties();
    Code:
       0: aconst_null
       1: areturn

  private void setUnlessNull(java.util.Properties, java.lang.String, java.lang.String);
    Code:
       0: aload_3
       1: ifnull        11
       4: aload_1
       5: aload_2
       6: aload_3
       7: invokevirtual #83                 // Method java/util/Properties.setProperty:(Ljava/lang/String;Ljava/lang/String;)Ljava/lang/Object;
      10: pop
      11: return

  private void verifyInt(java.lang.String);
    Code:
       0: aload_1
       1: ifnull        9
       4: aload_1
       5: invokestatic  #84                 // Method java/lang/Integer.parseInt:(Ljava/lang/String;)I
       8: pop
       9: return
}
