Compiled from "SecondaryTableSecondPass.java"
public class org.hibernate.cfg.SecondaryTableSecondPass implements org.hibernate.cfg.SecondPass {
  private org.hibernate.cfg.annotations.EntityBinder entityBinder;

  private org.hibernate.cfg.PropertyHolder propertyHolder;

  private org.hibernate.annotations.common.reflection.XAnnotatedElement annotatedClass;

  public org.hibernate.cfg.SecondaryTableSecondPass(org.hibernate.cfg.annotations.EntityBinder, org.hibernate.cfg.PropertyHolder, org.hibernate.annotations.common.reflection.XAnnotatedElement);
    Code:
       0: aload_0
       1: invokespecial #1                  // Method java/lang/Object."<init>":()V
       4: aload_0
       5: aload_1
       6: putfield      #2                  // Field entityBinder:Lorg/hibernate/cfg/annotations/EntityBinder;
       9: aload_0
      10: aload_2
      11: putfield      #3                  // Field propertyHolder:Lorg/hibernate/cfg/PropertyHolder;
      14: aload_0
      15: aload_3
      16: putfield      #4                  // Field annotatedClass:Lorg/hibernate/annotations/common/reflection/XAnnotatedElement;
      19: return

  public void doSecondPass(java.util.Map) throws org.hibernate.MappingException;
    Code:
       0: aload_0
       1: getfield      #2                  // Field entityBinder:Lorg/hibernate/cfg/annotations/EntityBinder;
       4: aload_0
       5: getfield      #3                  // Field propertyHolder:Lorg/hibernate/cfg/PropertyHolder;
       8: invokevirtual #5                  // Method org/hibernate/cfg/annotations/EntityBinder.finalSecondaryTableBinding:(Lorg/hibernate/cfg/PropertyHolder;)V
      11: return
}
