Compiled from "KafkaProperties.java"
class org.springframework.boot.autoconfigure.kafka.KafkaProperties$Properties extends java.util.HashMap<java.lang.String, java.lang.Object> {
  private org.springframework.boot.autoconfigure.kafka.KafkaProperties$Properties();
    Code:
       0: aload_0
       1: invokespecial #2                  // Method java/util/HashMap."<init>":()V
       4: return

  <V> java.util.function.Consumer<V> in(java.lang.String);
    Code:
       0: aload_0
       1: aload_1
       2: invokedynamic #3,  0              // InvokeDynamic #0:accept:(Lorg/springframework/boot/autoconfigure/kafka/KafkaProperties$Properties;Ljava/lang/String;)Ljava/util/function/Consumer;
       7: areturn

  org.springframework.boot.autoconfigure.kafka.KafkaProperties$Properties with(org.springframework.boot.autoconfigure.kafka.KafkaProperties$Ssl, org.springframework.boot.autoconfigure.kafka.KafkaProperties$Security, java.util.Map<java.lang.String, java.lang.String>);
    Code:
       0: aload_0
       1: aload_1
       2: invokevirtual #4                  // Method org/springframework/boot/autoconfigure/kafka/KafkaProperties$Ssl.buildProperties:()Ljava/util/Map;
       5: invokevirtual #5                  // Method putAll:(Ljava/util/Map;)V
       8: aload_0
       9: aload_2
      10: invokevirtual #6                  // Method org/springframework/boot/autoconfigure/kafka/KafkaProperties$Security.buildProperties:()Ljava/util/Map;
      13: invokevirtual #5                  // Method putAll:(Ljava/util/Map;)V
      16: aload_0
      17: aload_3
      18: invokevirtual #5                  // Method putAll:(Ljava/util/Map;)V
      21: aload_0
      22: areturn

  private void lambda$in$0(java.lang.String, java.lang.Object);
    Code:
       0: aload_0
       1: aload_1
       2: aload_2
       3: invokevirtual #7                  // Method put:(Ljava/lang/Object;Ljava/lang/Object;)Ljava/lang/Object;
       6: pop
       7: return

  org.springframework.boot.autoconfigure.kafka.KafkaProperties$Properties(org.springframework.boot.autoconfigure.kafka.KafkaProperties$1);
    Code:
       0: aload_0
       1: invokespecial #1                  // Method "<init>":()V
       4: return
}
