Compiled from "HierarchicalTableGenerator.java"
public class org.hl7.fhir.utilities.xhtml.HierarchicalTableGenerator$Row {
  private java.util.List<org.hl7.fhir.utilities.xhtml.HierarchicalTableGenerator$Row> subRows;

  private java.util.List<org.hl7.fhir.utilities.xhtml.HierarchicalTableGenerator$Cell> cells;

  private java.lang.String icon;

  private java.lang.String anchor;

  private java.lang.String hint;

  private java.lang.String color;

  private int lineColor;

  private java.lang.String id;

  private java.lang.String opacity;

  static final boolean $assertionsDisabled;

  final org.hl7.fhir.utilities.xhtml.HierarchicalTableGenerator this$0;

  public org.hl7.fhir.utilities.xhtml.HierarchicalTableGenerator$Row(org.hl7.fhir.utilities.xhtml.HierarchicalTableGenerator);
    Code:
       0: aload_0
       1: aload_1
       2: putfield      #1                  // Field this$0:Lorg/hl7/fhir/utilities/xhtml/HierarchicalTableGenerator;
       5: aload_0
       6: invokespecial #2                  // Method java/lang/Object."<init>":()V
       9: aload_0
      10: new           #3                  // class java/util/ArrayList
      13: dup
      14: invokespecial #4                  // Method java/util/ArrayList."<init>":()V
      17: putfield      #5                  // Field subRows:Ljava/util/List;
      20: aload_0
      21: new           #3                  // class java/util/ArrayList
      24: dup
      25: invokespecial #4                  // Method java/util/ArrayList."<init>":()V
      28: putfield      #6                  // Field cells:Ljava/util/List;
      31: return

  public java.util.List<org.hl7.fhir.utilities.xhtml.HierarchicalTableGenerator$Row> getSubRows();
    Code:
       0: aload_0
       1: getfield      #5                  // Field subRows:Ljava/util/List;
       4: areturn

  public java.util.List<org.hl7.fhir.utilities.xhtml.HierarchicalTableGenerator$Cell> getCells();
    Code:
       0: aload_0
       1: getfield      #6                  // Field cells:Ljava/util/List;
       4: areturn

  public java.lang.String getIcon();
    Code:
       0: aload_0
       1: getfield      #7                  // Field icon:Ljava/lang/String;
       4: areturn

  public void setIcon(java.lang.String, java.lang.String);
    Code:
       0: aload_0
       1: aload_1
       2: putfield      #7                  // Field icon:Ljava/lang/String;
       5: aload_0
       6: aload_2
       7: putfield      #8                  // Field hint:Ljava/lang/String;
      10: return

  public java.lang.String getAnchor();
    Code:
       0: aload_0
       1: getfield      #9                  // Field anchor:Ljava/lang/String;
       4: areturn

  public void setAnchor(java.lang.String);
    Code:
       0: aload_0
       1: aload_1
       2: putfield      #9                  // Field anchor:Ljava/lang/String;
       5: return

  public java.lang.String getHint();
    Code:
       0: aload_0
       1: getfield      #8                  // Field hint:Ljava/lang/String;
       4: areturn

  public java.lang.String getColor();
    Code:
       0: aload_0
       1: getfield      #10                 // Field color:Ljava/lang/String;
       4: areturn

  public void setColor(java.lang.String);
    Code:
       0: aload_0
       1: aload_1
       2: putfield      #10                 // Field color:Ljava/lang/String;
       5: return

  public int getLineColor();
    Code:
       0: aload_0
       1: getfield      #11                 // Field lineColor:I
       4: ireturn

  public void setLineColor(int);
    Code:
       0: getstatic     #12                 // Field $assertionsDisabled:Z
       3: ifne          18
       6: iload_1
       7: ifge          18
      10: new           #13                 // class java/lang/AssertionError
      13: dup
      14: invokespecial #14                 // Method java/lang/AssertionError."<init>":()V
      17: athrow
      18: getstatic     #12                 // Field $assertionsDisabled:Z
      21: ifne          37
      24: iload_1
      25: iconst_2
      26: if_icmple     37
      29: new           #13                 // class java/lang/AssertionError
      32: dup
      33: invokespecial #14                 // Method java/lang/AssertionError."<init>":()V
      36: athrow
      37: aload_0
      38: iload_1
      39: putfield      #11                 // Field lineColor:I
      42: return

  public java.lang.String getId();
    Code:
       0: aload_0
       1: getfield      #15                 // Field id:Ljava/lang/String;
       4: areturn

  public void setId(java.lang.String);
    Code:
       0: aload_0
       1: aload_1
       2: putfield      #15                 // Field id:Ljava/lang/String;
       5: return

  public java.lang.String getOpacity();
    Code:
       0: aload_0
       1: getfield      #16                 // Field opacity:Ljava/lang/String;
       4: areturn

  public void setOpacity(java.lang.String);
    Code:
       0: aload_0
       1: aload_1
       2: putfield      #16                 // Field opacity:Ljava/lang/String;
       5: return

  static {};
    Code:
       0: ldc           #17                 // class org/hl7/fhir/utilities/xhtml/HierarchicalTableGenerator
       2: invokevirtual #18                 // Method java/lang/Class.desiredAssertionStatus:()Z
       5: ifne          12
       8: iconst_1
       9: goto          13
      12: iconst_0
      13: putstatic     #12                 // Field $assertionsDisabled:Z
      16: return
}
