Compiled from "BootstrapUser.scala"
public final class net.liftmodules.FoBoBs.mapper.BootstrapMegaMetaProtoUser$$anonfun$login$1 extends scala.runtime.AbstractFunction0<scala.runtime.Nothing$> implements scala.Serializable {
  public static final long serialVersionUID;

  private final net.liftmodules.FoBoBs.mapper.BootstrapMegaMetaProtoUser $outer;

  private final scala.Function0 preLoginState$1;

  private final java.lang.String redir$1;

  public final scala.runtime.Nothing$ apply();
    Code:
       0: getstatic     #31                 // Field net/liftweb/http/S$.MODULE$:Lnet/liftweb/http/S$;
       3: aload_0
       4: getfield      #33                 // Field $outer:Lnet/liftmodules/FoBoBs/mapper/BootstrapMegaMetaProtoUser;
       7: invokeinterface #37,  1           // InterfaceMethod net/liftmodules/FoBoBs/mapper/BootstrapMegaMetaProtoUser.resLoginMsgNoticeLogedIn:()Lscala/xml/NodeSeq;
      12: invokeinterface #43,  2           // InterfaceMethod net/liftweb/http/S.notice:(Lscala/xml/NodeSeq;)V
      17: aload_0
      18: getfield      #45                 // Field preLoginState$1:Lscala/Function0;
      21: invokeinterface #51,  1           // InterfaceMethod scala/Function0.apply$mcV$sp:()V
      26: getstatic     #31                 // Field net/liftweb/http/S$.MODULE$:Lnet/liftweb/http/S$;
      29: aload_0
      30: getfield      #53                 // Field redir$1:Ljava/lang/String;
      33: invokeinterface #57,  2           // InterfaceMethod net/liftweb/http/S.redirectTo:(Ljava/lang/String;)Lscala/runtime/Nothing$;
      38: areturn

  public final java.lang.Object apply();
    Code:
       0: aload_0
       1: invokevirtual #62                 // Method apply:()Lscala/runtime/Nothing$;
       4: athrow

  public net.liftmodules.FoBoBs.mapper.BootstrapMegaMetaProtoUser$$anonfun$login$1(net.liftmodules.FoBoBs.mapper.BootstrapMegaMetaProtoUser<ModelType>);
    Code:
       0: aload_1
       1: ifnonnull     12
       4: new           #66                 // class java/lang/NullPointerException
       7: dup
       8: invokespecial #68                 // Method java/lang/NullPointerException."<init>":()V
      11: athrow
      12: aload_0
      13: aload_1
      14: putfield      #33                 // Field $outer:Lnet/liftmodules/FoBoBs/mapper/BootstrapMegaMetaProtoUser;
      17: aload_0
      18: aload_2
      19: putfield      #45                 // Field preLoginState$1:Lscala/Function0;
      22: aload_0
      23: aload_3
      24: putfield      #53                 // Field redir$1:Ljava/lang/String;
      27: aload_0
      28: invokespecial #69                 // Method scala/runtime/AbstractFunction0."<init>":()V
      31: return
}
