Compiled from "SetExecutor.java"
public abstract class org.apache.velocity.runtime.parser.node.SetExecutor {
  protected org.apache.velocity.runtime.log.Log log;

  private java.lang.reflect.Method method;

  public org.apache.velocity.runtime.parser.node.SetExecutor();
    Code:
       0: aload_0
       1: invokespecial #1                  // Method java/lang/Object."<init>":()V
       4: aload_0
       5: aconst_null
       6: putfield      #2                  // Field log:Lorg/apache/velocity/runtime/log/Log;
       9: aload_0
      10: aconst_null
      11: putfield      #3                  // Field method:Ljava/lang/reflect/Method;
      14: return

  public abstract java.lang.Object execute(java.lang.Object, java.lang.Object) throws java.lang.IllegalAccessException, java.lang.reflect.InvocationTargetException;

  public boolean isAlive();
    Code:
       0: aload_0
       1: getfield      #3                  // Field method:Ljava/lang/reflect/Method;
       4: ifnull        11
       7: iconst_1
       8: goto          12
      11: iconst_0
      12: ireturn

  public java.lang.reflect.Method getMethod();
    Code:
       0: aload_0
       1: getfield      #3                  // Field method:Ljava/lang/reflect/Method;
       4: areturn

  protected void setMethod(java.lang.reflect.Method);
    Code:
       0: aload_0
       1: aload_1
       2: putfield      #3                  // Field method:Ljava/lang/reflect/Method;
       5: return
}
