Compiled from "MetricsRecordFiltered.java"
class org.apache.hadoop.metrics2.impl.MetricsRecordFiltered$1$1 extends com.google.common.collect.AbstractIterator<org.apache.hadoop.metrics2.AbstractMetric> {
  final org.apache.hadoop.metrics2.impl.MetricsRecordFiltered$1 this$1;

  org.apache.hadoop.metrics2.impl.MetricsRecordFiltered$1$1(org.apache.hadoop.metrics2.impl.MetricsRecordFiltered$1);
    Code:
       0: aload_0
       1: aload_1
       2: putfield      #1                  // Field this$1:Lorg/apache/hadoop/metrics2/impl/MetricsRecordFiltered$1;
       5: aload_0
       6: invokespecial #2                  // Method com/google/common/collect/AbstractIterator."<init>":()V
       9: return

  public org.apache.hadoop.metrics2.AbstractMetric computeNext();
    Code:
       0: aload_0
       1: getfield      #1                  // Field this$1:Lorg/apache/hadoop/metrics2/impl/MetricsRecordFiltered$1;
       4: getfield      #3                  // Field org/apache/hadoop/metrics2/impl/MetricsRecordFiltered$1.it:Ljava/util/Iterator;
       7: invokeinterface #4,  1            // InterfaceMethod java/util/Iterator.hasNext:()Z
      12: ifeq          56
      15: aload_0
      16: getfield      #1                  // Field this$1:Lorg/apache/hadoop/metrics2/impl/MetricsRecordFiltered$1;
      19: getfield      #3                  // Field org/apache/hadoop/metrics2/impl/MetricsRecordFiltered$1.it:Ljava/util/Iterator;
      22: invokeinterface #5,  1            // InterfaceMethod java/util/Iterator.next:()Ljava/lang/Object;
      27: checkcast     #6                  // class org/apache/hadoop/metrics2/AbstractMetric
      30: astore_1
      31: aload_0
      32: getfield      #1                  // Field this$1:Lorg/apache/hadoop/metrics2/impl/MetricsRecordFiltered$1;
      35: getfield      #7                  // Field org/apache/hadoop/metrics2/impl/MetricsRecordFiltered$1.this$0:Lorg/apache/hadoop/metrics2/impl/MetricsRecordFiltered;
      38: invokestatic  #8                  // Method org/apache/hadoop/metrics2/impl/MetricsRecordFiltered.access$100:(Lorg/apache/hadoop/metrics2/impl/MetricsRecordFiltered;)Lorg/apache/hadoop/metrics2/MetricsFilter;
      41: aload_1
      42: invokevirtual #9                  // Method org/apache/hadoop/metrics2/AbstractMetric.name:()Ljava/lang/String;
      45: invokevirtual #10                 // Method org/apache/hadoop/metrics2/MetricsFilter.accepts:(Ljava/lang/String;)Z
      48: ifeq          53
      51: aload_1
      52: areturn
      53: goto          0
      56: aload_0
      57: invokevirtual #11                 // Method endOfData:()Ljava/lang/Object;
      60: checkcast     #6                  // class org/apache/hadoop/metrics2/AbstractMetric
      63: areturn

  public java.lang.Object computeNext();
    Code:
       0: aload_0
       1: invokevirtual #12                 // Method computeNext:()Lorg/apache/hadoop/metrics2/AbstractMetric;
       4: areturn
}
