Compiled from "BeanExcludeInfo.java"
public class org.apache.axis2.deployment.util.BeanExcludeInfo {
  private java.lang.String excludeProperties;

  private java.lang.String includeProperties;

  public org.apache.axis2.deployment.util.BeanExcludeInfo(java.lang.String, java.lang.String);
    Code:
       0: aload_0
       1: invokespecial #1                  // Method java/lang/Object."<init>":()V
       4: aload_0
       5: aload_1
       6: putfield      #2                  // Field excludeProperties:Ljava/lang/String;
       9: aload_0
      10: aload_2
      11: putfield      #3                  // Field includeProperties:Ljava/lang/String;
      14: return

  public java.lang.String getExcludeProperties();
    Code:
       0: aload_0
       1: getfield      #2                  // Field excludeProperties:Ljava/lang/String;
       4: areturn

  public void setExcludeProperties(java.lang.String);
    Code:
       0: aload_0
       1: aload_1
       2: putfield      #2                  // Field excludeProperties:Ljava/lang/String;
       5: return

  public java.lang.String getIncludeProperties();
    Code:
       0: aload_0
       1: getfield      #3                  // Field includeProperties:Ljava/lang/String;
       4: areturn

  public void setIncludeProperties(java.lang.String);
    Code:
       0: aload_0
       1: aload_1
       2: putfield      #3                  // Field includeProperties:Ljava/lang/String;
       5: return

  public boolean isExcludedProperty(java.lang.String);
    Code:
       0: iconst_0
       1: istore_2
       2: aload_0
       3: getfield      #2                  // Field excludeProperties:Ljava/lang/String;
       6: ifnull        68
       9: aload_0
      10: getfield      #2                  // Field excludeProperties:Ljava/lang/String;
      13: invokevirtual #4                  // Method java/lang/String.trim:()Ljava/lang/String;
      16: invokevirtual #5                  // Method java/lang/String.length:()I
      19: ifle          68
      22: aload_1
      23: aload_0
      24: getfield      #2                  // Field excludeProperties:Ljava/lang/String;
      27: invokevirtual #6                  // Method java/lang/String.matches:(Ljava/lang/String;)Z
      30: ifeq          68
      33: iconst_1
      34: istore_2
      35: aload_0
      36: getfield      #3                  // Field includeProperties:Ljava/lang/String;
      39: ifnull        68
      42: aload_0
      43: getfield      #3                  // Field includeProperties:Ljava/lang/String;
      46: invokevirtual #4                  // Method java/lang/String.trim:()Ljava/lang/String;
      49: invokevirtual #5                  // Method java/lang/String.length:()I
      52: ifle          68
      55: aload_1
      56: aload_0
      57: getfield      #3                  // Field includeProperties:Ljava/lang/String;
      60: invokevirtual #6                  // Method java/lang/String.matches:(Ljava/lang/String;)Z
      63: ifeq          68
      66: iconst_0
      67: istore_2
      68: iload_2
      69: ireturn
}
