Compiled from "ExcludeInfo.java"
public class org.apache.axis2.deployment.util.ExcludeInfo {
  private java.util.Map classNameToBeanInfoMap;

  public org.apache.axis2.deployment.util.ExcludeInfo();
    Code:
       0: aload_0
       1: invokespecial #1                  // Method java/lang/Object."<init>":()V
       4: aload_0
       5: new           #2                  // class java/util/HashMap
       8: dup
       9: invokespecial #3                  // Method java/util/HashMap."<init>":()V
      12: putfield      #4                  // Field classNameToBeanInfoMap:Ljava/util/Map;
      15: return

  public void putBeanInfo(java.lang.String, org.apache.axis2.deployment.util.BeanExcludeInfo);
    Code:
       0: aload_0
       1: getfield      #4                  // Field classNameToBeanInfoMap:Ljava/util/Map;
       4: aload_1
       5: aload_2
       6: invokeinterface #5,  3            // InterfaceMethod java/util/Map.put:(Ljava/lang/Object;Ljava/lang/Object;)Ljava/lang/Object;
      11: pop
      12: return

  public org.apache.axis2.deployment.util.BeanExcludeInfo getBeanExcludeInfoForClass(java.lang.String);
    Code:
       0: aconst_null
       1: astore_2
       2: aconst_null
       3: astore_3
       4: aload_0
       5: getfield      #4                  // Field classNameToBeanInfoMap:Ljava/util/Map;
       8: invokeinterface #6,  1            // InterfaceMethod java/util/Map.keySet:()Ljava/util/Set;
      13: invokeinterface #7,  1            // InterfaceMethod java/util/Set.iterator:()Ljava/util/Iterator;
      18: astore        4
      20: aload         4
      22: invokeinterface #8,  1            // InterfaceMethod java/util/Iterator.hasNext:()Z
      27: ifeq          66
      30: aload         4
      32: invokeinterface #9,  1            // InterfaceMethod java/util/Iterator.next:()Ljava/lang/Object;
      37: checkcast     #10                 // class java/lang/String
      40: astore_2
      41: aload_1
      42: aload_2
      43: invokevirtual #11                 // Method java/lang/String.matches:(Ljava/lang/String;)Z
      46: ifeq          20
      49: aload_0
      50: getfield      #4                  // Field classNameToBeanInfoMap:Ljava/util/Map;
      53: aload_2
      54: invokeinterface #12,  2           // InterfaceMethod java/util/Map.get:(Ljava/lang/Object;)Ljava/lang/Object;
      59: checkcast     #13                 // class org/apache/axis2/deployment/util/BeanExcludeInfo
      62: astore_3
      63: goto          66
      66: aload_3
      67: areturn
}
