Compiled from "BookieNettyServer.java"
class org.apache.bookkeeper.proto.BookieNettyServer$1$1 extends io.netty.channel.DefaultEventLoop {
  final org.apache.bookkeeper.proto.BookieNettyServer$1 this$1;

  org.apache.bookkeeper.proto.BookieNettyServer$1$1(org.apache.bookkeeper.proto.BookieNettyServer$1, io.netty.channel.EventLoopGroup, java.util.concurrent.Executor);
    Code:
       0: aload_0
       1: aload_1
       2: putfield      #1                  // Field this$1:Lorg/apache/bookkeeper/proto/BookieNettyServer$1;
       5: aload_0
       6: aload_2
       7: aload_3
       8: invokespecial #2                  // Method io/netty/channel/DefaultEventLoop."<init>":(Lio/netty/channel/EventLoopGroup;Ljava/util/concurrent/Executor;)V
      11: return

  protected java.util.Queue<java.lang.Runnable> newTaskQueue(int);
    Code:
       0: aload_0
       1: getfield      #1                  // Field this$1:Lorg/apache/bookkeeper/proto/BookieNettyServer$1;
       4: getfield      #3                  // Field org/apache/bookkeeper/proto/BookieNettyServer$1.val$conf:Lorg/apache/bookkeeper/conf/ServerConfiguration;
       7: invokevirtual #4                  // Method org/apache/bookkeeper/conf/ServerConfiguration.isBusyWaitEnabled:()Z
      10: ifeq          28
      13: new           #5                  // class org/apache/bookkeeper/common/collections/BlockingMpscQueue
      16: dup
      17: iload_1
      18: sipush        10000
      21: invokestatic  #6                  // Method java/lang/Math.min:(II)I
      24: invokespecial #7                  // Method org/apache/bookkeeper/common/collections/BlockingMpscQueue."<init>":(I)V
      27: areturn
      28: aload_0
      29: iload_1
      30: invokespecial #8                  // Method io/netty/channel/DefaultEventLoop.newTaskQueue:(I)Ljava/util/Queue;
      33: areturn
}
