Compiled from "BookieProtoEncoding.java"
public class org.apache.bookkeeper.proto.BookieProtoEncoding$ResponseEnDecoderV3 implements org.apache.bookkeeper.proto.BookieProtoEncoding$EnDecoder {
  final com.google.protobuf.ExtensionRegistry extensionRegistry;

  public org.apache.bookkeeper.proto.BookieProtoEncoding$ResponseEnDecoderV3(com.google.protobuf.ExtensionRegistry);
    Code:
       0: aload_0
       1: invokespecial #1                  // Method java/lang/Object."<init>":()V
       4: aload_0
       5: aload_1
       6: putfield      #2                  // Field extensionRegistry:Lcom/google/protobuf/ExtensionRegistry;
       9: return

  public java.lang.Object decode(io.netty.buffer.ByteBuf) throws java.lang.Exception;
    Code:
       0: new           #3                  // class io/netty/buffer/ByteBufInputStream
       3: dup
       4: aload_1
       5: invokespecial #4                  // Method io/netty/buffer/ByteBufInputStream."<init>":(Lio/netty/buffer/ByteBuf;)V
       8: aload_0
       9: getfield      #2                  // Field extensionRegistry:Lcom/google/protobuf/ExtensionRegistry;
      12: invokestatic  #5                  // Method org/apache/bookkeeper/proto/BookkeeperProtocol$Response.parseFrom:(Ljava/io/InputStream;Lcom/google/protobuf/ExtensionRegistryLite;)Lorg/apache/bookkeeper/proto/BookkeeperProtocol$Response;
      15: areturn

  public java.lang.Object encode(java.lang.Object, io.netty.buffer.ByteBufAllocator) throws java.lang.Exception;
    Code:
       0: aload_1
       1: checkcast     #6                  // class org/apache/bookkeeper/proto/BookkeeperProtocol$Response
       4: astore_3
       5: aload_3
       6: aload_2
       7: invokestatic  #7                  // Method org/apache/bookkeeper/proto/BookieProtoEncoding.access$100:(Lcom/google/protobuf/MessageLite;Lio/netty/buffer/ByteBufAllocator;)Lio/netty/buffer/ByteBuf;
      10: areturn
}
