Compiled from "BookieProtocol.java"
public class org.apache.bookkeeper.proto.BookieProtocol$AuthRequest extends org.apache.bookkeeper.proto.BookieProtocol$Request {
  final org.apache.bookkeeper.proto.BookkeeperProtocol$AuthMessage authMessage;

  org.apache.bookkeeper.proto.BookieProtocol$AuthRequest(byte, org.apache.bookkeeper.proto.BookkeeperProtocol$AuthMessage);
    Code:
       0: aload_0
       1: invokespecial #2                  // Method org/apache/bookkeeper/proto/BookieProtocol$Request."<init>":()V
       4: aload_0
       5: iload_1
       6: iconst_3
       7: ldc2_w        #3                  // long -1l
      10: ldc2_w        #3                  // long -1l
      13: iconst_0
      14: aconst_null
      15: invokevirtual #5                  // Method init:(BBJJS[B)V
      18: aload_0
      19: aload_2
      20: putfield      #6                  // Field authMessage:Lorg/apache/bookkeeper/proto/BookkeeperProtocol$AuthMessage;
      23: return

  org.apache.bookkeeper.proto.BookkeeperProtocol$AuthMessage getAuthMessage();
    Code:
       0: aload_0
       1: getfield      #6                  // Field authMessage:Lorg/apache/bookkeeper/proto/BookkeeperProtocol$AuthMessage;
       4: areturn
}
