Compiled from "BookieProtoEncoding.java"
public class org.apache.bookkeeper.proto.BookieProtoEncoding {
  private static final org.slf4j.Logger LOG;

  public org.apache.bookkeeper.proto.BookieProtoEncoding();
    Code:
       0: aload_0
       1: invokespecial #3                  // Method java/lang/Object."<init>":()V
       4: return

  private static io.netty.buffer.ByteBuf serializeProtobuf(com.google.protobuf.MessageLite, io.netty.buffer.ByteBufAllocator);
    Code:
       0: aload_0
       1: invokeinterface #4,  1            // InterfaceMethod com/google/protobuf/MessageLite.getSerializedSize:()I
       6: istore_2
       7: aload_1
       8: iload_2
       9: iload_2
      10: invokeinterface #5,  3            // InterfaceMethod io/netty/buffer/ByteBufAllocator.directBuffer:(II)Lio/netty/buffer/ByteBuf;
      15: astore_3
      16: aload_0
      17: aload_3
      18: aload_3
      19: invokevirtual #6                  // Method io/netty/buffer/ByteBuf.readerIndex:()I
      22: iload_2
      23: invokevirtual #7                  // Method io/netty/buffer/ByteBuf.nioBuffer:(II)Ljava/nio/ByteBuffer;
      26: invokestatic  #8                  // Method com/google/protobuf/CodedOutputStream.newInstance:(Ljava/nio/ByteBuffer;)Lcom/google/protobuf/CodedOutputStream;
      29: invokeinterface #9,  2            // InterfaceMethod com/google/protobuf/MessageLite.writeTo:(Lcom/google/protobuf/CodedOutputStream;)V
      34: goto          49
      37: astore        4
      39: new           #11                 // class java/lang/RuntimeException
      42: dup
      43: aload         4
      45: invokespecial #12                 // Method java/lang/RuntimeException."<init>":(Ljava/lang/Throwable;)V
      48: athrow
      49: aload_3
      50: aload_3
      51: invokevirtual #13                 // Method io/netty/buffer/ByteBuf.capacity:()I
      54: invokevirtual #14                 // Method io/netty/buffer/ByteBuf.writerIndex:(I)Lio/netty/buffer/ByteBuf;
      57: pop
      58: aload_3
      59: areturn
    Exception table:
       from    to  target type
          16    34    37   Class java/io/IOException

  static org.slf4j.Logger access$000();
    Code:
       0: getstatic     #2                  // Field LOG:Lorg/slf4j/Logger;
       3: areturn

  static io.netty.buffer.ByteBuf access$100(com.google.protobuf.MessageLite, io.netty.buffer.ByteBufAllocator);
    Code:
       0: aload_0
       1: aload_1
       2: invokestatic  #1                  // Method serializeProtobuf:(Lcom/google/protobuf/MessageLite;Lio/netty/buffer/ByteBufAllocator;)Lio/netty/buffer/ByteBuf;
       5: areturn

  static {};
    Code:
       0: ldc           #15                 // class org/apache/bookkeeper/proto/BookieProtoEncoding
       2: invokestatic  #16                 // Method org/slf4j/LoggerFactory.getLogger:(Ljava/lang/Class;)Lorg/slf4j/Logger;
       5: putstatic     #2                  // Field LOG:Lorg/slf4j/Logger;
       8: return
}
