Compiled from "ResponseBuilder.java"
class org.apache.bookkeeper.proto.ResponseBuilder {
  static final boolean $assertionsDisabled;

  org.apache.bookkeeper.proto.ResponseBuilder();
    Code:
       0: aload_0
       1: invokespecial #1                  // Method java/lang/Object."<init>":()V
       4: return

  static org.apache.bookkeeper.proto.BookieProtocol$Response buildErrorResponse(int, org.apache.bookkeeper.proto.BookieProtocol$Request);
    Code:
       0: aload_1
       1: invokevirtual #2                  // Method org/apache/bookkeeper/proto/BookieProtocol$Request.getOpCode:()B
       4: iconst_1
       5: if_icmpne     25
       8: aload_1
       9: invokevirtual #4                  // Method org/apache/bookkeeper/proto/BookieProtocol$Request.getProtocolVersion:()B
      12: iload_0
      13: aload_1
      14: invokevirtual #5                  // Method org/apache/bookkeeper/proto/BookieProtocol$Request.getLedgerId:()J
      17: aload_1
      18: invokevirtual #6                  // Method org/apache/bookkeeper/proto/BookieProtocol$Request.getEntryId:()J
      21: invokestatic  #7                  // Method org/apache/bookkeeper/proto/BookieProtocol$AddResponse.create:(BIJJ)Lorg/apache/bookkeeper/proto/BookieProtocol$AddResponse;
      24: areturn
      25: getstatic     #8                  // Field $assertionsDisabled:Z
      28: ifne          47
      31: aload_1
      32: invokevirtual #2                  // Method org/apache/bookkeeper/proto/BookieProtocol$Request.getOpCode:()B
      35: iconst_2
      36: if_icmpeq     47
      39: new           #9                  // class java/lang/AssertionError
      42: dup
      43: invokespecial #10                 // Method java/lang/AssertionError."<init>":()V
      46: athrow
      47: new           #11                 // class org/apache/bookkeeper/proto/BookieProtocol$ReadResponse
      50: dup
      51: aload_1
      52: invokevirtual #4                  // Method org/apache/bookkeeper/proto/BookieProtocol$Request.getProtocolVersion:()B
      55: iload_0
      56: aload_1
      57: invokevirtual #5                  // Method org/apache/bookkeeper/proto/BookieProtocol$Request.getLedgerId:()J
      60: aload_1
      61: invokevirtual #6                  // Method org/apache/bookkeeper/proto/BookieProtocol$Request.getEntryId:()J
      64: invokespecial #12                 // Method org/apache/bookkeeper/proto/BookieProtocol$ReadResponse."<init>":(BIJJ)V
      67: areturn

  static org.apache.bookkeeper.proto.BookieProtocol$Response buildAddResponse(org.apache.bookkeeper.proto.BookieProtocol$Request);
    Code:
       0: aload_0
       1: invokevirtual #4                  // Method org/apache/bookkeeper/proto/BookieProtocol$Request.getProtocolVersion:()B
       4: iconst_0
       5: aload_0
       6: invokevirtual #5                  // Method org/apache/bookkeeper/proto/BookieProtocol$Request.getLedgerId:()J
       9: aload_0
      10: invokevirtual #6                  // Method org/apache/bookkeeper/proto/BookieProtocol$Request.getEntryId:()J
      13: invokestatic  #7                  // Method org/apache/bookkeeper/proto/BookieProtocol$AddResponse.create:(BIJJ)Lorg/apache/bookkeeper/proto/BookieProtocol$AddResponse;
      16: areturn

  static org.apache.bookkeeper.proto.BookieProtocol$Response buildReadResponse(io.netty.buffer.ByteBuf, org.apache.bookkeeper.proto.BookieProtocol$Request);
    Code:
       0: new           #11                 // class org/apache/bookkeeper/proto/BookieProtocol$ReadResponse
       3: dup
       4: aload_1
       5: invokevirtual #4                  // Method org/apache/bookkeeper/proto/BookieProtocol$Request.getProtocolVersion:()B
       8: iconst_0
       9: aload_1
      10: invokevirtual #5                  // Method org/apache/bookkeeper/proto/BookieProtocol$Request.getLedgerId:()J
      13: aload_1
      14: invokevirtual #6                  // Method org/apache/bookkeeper/proto/BookieProtocol$Request.getEntryId:()J
      17: aload_0
      18: invokespecial #13                 // Method org/apache/bookkeeper/proto/BookieProtocol$ReadResponse."<init>":(BIJJLio/netty/buffer/ByteBuf;)V
      21: areturn

  static {};
    Code:
       0: ldc           #14                 // class org/apache/bookkeeper/proto/ResponseBuilder
       2: invokevirtual #15                 // Method java/lang/Class.desiredAssertionStatus:()Z
       5: ifne          12
       8: iconst_1
       9: goto          13
      12: iconst_0
      13: putstatic     #8                  // Field $assertionsDisabled:Z
      16: return
}
