Compiled from "ClientParametersAuthentication.java"
public class com.google.api.client.auth.oauth2.ClientParametersAuthentication implements com.google.api.client.http.HttpRequestInitializer,com.google.api.client.http.HttpExecuteInterceptor {
  private final java.lang.String clientId;

  private final java.lang.String clientSecret;

  public com.google.api.client.auth.oauth2.ClientParametersAuthentication(java.lang.String, java.lang.String);
    Code:
       0: aload_0
       1: invokespecial #1                  // Method java/lang/Object."<init>":()V
       4: aload_0
       5: aload_1
       6: invokestatic  #2                  // Method com/google/api/client/util/Preconditions.checkNotNull:(Ljava/lang/Object;)Ljava/lang/Object;
       9: checkcast     #3                  // class java/lang/String
      12: putfield      #4                  // Field clientId:Ljava/lang/String;
      15: aload_0
      16: aload_2
      17: putfield      #5                  // Field clientSecret:Ljava/lang/String;
      20: return

  public void initialize(com.google.api.client.http.HttpRequest) throws java.io.IOException;
    Code:
       0: aload_1
       1: aload_0
       2: invokevirtual #6                  // Method com/google/api/client/http/HttpRequest.setInterceptor:(Lcom/google/api/client/http/HttpExecuteInterceptor;)Lcom/google/api/client/http/HttpRequest;
       5: pop
       6: return

  public void intercept(com.google.api.client.http.HttpRequest) throws java.io.IOException;
    Code:
       0: aload_1
       1: invokestatic  #7                  // Method com/google/api/client/http/UrlEncodedContent.getContent:(Lcom/google/api/client/http/HttpRequest;)Lcom/google/api/client/http/UrlEncodedContent;
       4: invokevirtual #8                  // Method com/google/api/client/http/UrlEncodedContent.getData:()Ljava/lang/Object;
       7: invokestatic  #9                  // Method com/google/api/client/util/Data.mapOf:(Ljava/lang/Object;)Ljava/util/Map;
      10: astore_2
      11: aload_2
      12: ldc           #10                 // String client_id
      14: aload_0
      15: getfield      #4                  // Field clientId:Ljava/lang/String;
      18: invokeinterface #11,  3           // InterfaceMethod java/util/Map.put:(Ljava/lang/Object;Ljava/lang/Object;)Ljava/lang/Object;
      23: pop
      24: aload_0
      25: getfield      #5                  // Field clientSecret:Ljava/lang/String;
      28: ifnull        44
      31: aload_2
      32: ldc           #12                 // String client_secret
      34: aload_0
      35: getfield      #5                  // Field clientSecret:Ljava/lang/String;
      38: invokeinterface #11,  3           // InterfaceMethod java/util/Map.put:(Ljava/lang/Object;Ljava/lang/Object;)Ljava/lang/Object;
      43: pop
      44: return

  public final java.lang.String getClientId();
    Code:
       0: aload_0
       1: getfield      #4                  // Field clientId:Ljava/lang/String;
       4: areturn

  public final java.lang.String getClientSecret();
    Code:
       0: aload_0
       1: getfield      #5                  // Field clientSecret:Ljava/lang/String;
       4: areturn
}
