Compiled from "EntitiesDescriptorUnmarshaller.java"
public class org.opensaml.saml2.metadata.impl.EntitiesDescriptorUnmarshaller extends org.opensaml.common.impl.AbstractSAMLObjectUnmarshaller {
  public org.opensaml.saml2.metadata.impl.EntitiesDescriptorUnmarshaller();
    Code:
       0: aload_0
       1: invokespecial #1                  // Method org/opensaml/common/impl/AbstractSAMLObjectUnmarshaller."<init>":()V
       4: return

  protected void processChildElement(org.opensaml.xml.XMLObject, org.opensaml.xml.XMLObject) throws org.opensaml.xml.io.UnmarshallingException;
    Code:
       0: aload_1
       1: checkcast     #2                  // class org/opensaml/saml2/metadata/EntitiesDescriptor
       4: astore_3
       5: aload_2
       6: instanceof    #3                  // class org/opensaml/saml2/common/Extensions
       9: ifeq          25
      12: aload_3
      13: aload_2
      14: checkcast     #3                  // class org/opensaml/saml2/common/Extensions
      17: invokeinterface #4,  2            // InterfaceMethod org/opensaml/saml2/metadata/EntitiesDescriptor.setExtensions:(Lorg/opensaml/saml2/common/Extensions;)V
      22: goto          103
      25: aload_2
      26: instanceof    #2                  // class org/opensaml/saml2/metadata/EntitiesDescriptor
      29: ifeq          51
      32: aload_3
      33: invokeinterface #5,  1            // InterfaceMethod org/opensaml/saml2/metadata/EntitiesDescriptor.getEntitiesDescriptors:()Ljava/util/List;
      38: aload_2
      39: checkcast     #2                  // class org/opensaml/saml2/metadata/EntitiesDescriptor
      42: invokeinterface #6,  2            // InterfaceMethod java/util/List.add:(Ljava/lang/Object;)Z
      47: pop
      48: goto          103
      51: aload_2
      52: instanceof    #7                  // class org/opensaml/saml2/metadata/EntityDescriptor
      55: ifeq          77
      58: aload_3
      59: invokeinterface #8,  1            // InterfaceMethod org/opensaml/saml2/metadata/EntitiesDescriptor.getEntityDescriptors:()Ljava/util/List;
      64: aload_2
      65: checkcast     #7                  // class org/opensaml/saml2/metadata/EntityDescriptor
      68: invokeinterface #6,  2            // InterfaceMethod java/util/List.add:(Ljava/lang/Object;)Z
      73: pop
      74: goto          103
      77: aload_2
      78: instanceof    #9                  // class org/opensaml/xml/signature/Signature
      81: ifeq          97
      84: aload_3
      85: aload_2
      86: checkcast     #9                  // class org/opensaml/xml/signature/Signature
      89: invokeinterface #10,  2           // InterfaceMethod org/opensaml/saml2/metadata/EntitiesDescriptor.setSignature:(Lorg/opensaml/xml/signature/Signature;)V
      94: goto          103
      97: aload_0
      98: aload_1
      99: aload_2
     100: invokespecial #11                 // Method org/opensaml/common/impl/AbstractSAMLObjectUnmarshaller.processChildElement:(Lorg/opensaml/xml/XMLObject;Lorg/opensaml/xml/XMLObject;)V
     103: return

  protected void processAttribute(org.opensaml.xml.XMLObject, org.w3c.dom.Attr) throws org.opensaml.xml.io.UnmarshallingException;
    Code:
       0: aload_1
       1: checkcast     #2                  // class org/opensaml/saml2/metadata/EntitiesDescriptor
       4: astore_3
       5: aload_2
       6: invokeinterface #12,  1           // InterfaceMethod org/w3c/dom/Attr.getLocalName:()Ljava/lang/String;
      11: ldc           #13                 // String ID
      13: invokevirtual #14                 // Method java/lang/String.equals:(Ljava/lang/Object;)Z
      16: ifeq          47
      19: aload_3
      20: aload_2
      21: invokeinterface #15,  1           // InterfaceMethod org/w3c/dom/Attr.getValue:()Ljava/lang/String;
      26: invokeinterface #16,  2           // InterfaceMethod org/opensaml/saml2/metadata/EntitiesDescriptor.setID:(Ljava/lang/String;)V
      31: aload_2
      32: invokeinterface #17,  1           // InterfaceMethod org/w3c/dom/Attr.getOwnerElement:()Lorg/w3c/dom/Element;
      37: aload_2
      38: iconst_1
      39: invokeinterface #18,  3           // InterfaceMethod org/w3c/dom/Element.setIdAttributeNode:(Lorg/w3c/dom/Attr;Z)V
      44: goto          172
      47: aload_2
      48: invokeinterface #12,  1           // InterfaceMethod org/w3c/dom/Attr.getLocalName:()Ljava/lang/String;
      53: ldc           #19                 // String validUntil
      55: invokevirtual #14                 // Method java/lang/String.equals:(Ljava/lang/Object;)Z
      58: ifeq          98
      61: aload_2
      62: invokeinterface #15,  1           // InterfaceMethod org/w3c/dom/Attr.getValue:()Ljava/lang/String;
      67: invokestatic  #20                 // Method org/opensaml/xml/util/DatatypeHelper.isEmpty:(Ljava/lang/String;)Z
      70: ifne          98
      73: aload_3
      74: new           #21                 // class org/joda/time/DateTime
      77: dup
      78: aload_2
      79: invokeinterface #15,  1           // InterfaceMethod org/w3c/dom/Attr.getValue:()Ljava/lang/String;
      84: invokestatic  #22                 // Method org/joda/time/chrono/ISOChronology.getInstanceUTC:()Lorg/joda/time/chrono/ISOChronology;
      87: invokespecial #23                 // Method org/joda/time/DateTime."<init>":(Ljava/lang/Object;Lorg/joda/time/Chronology;)V
      90: invokeinterface #24,  2           // InterfaceMethod org/opensaml/saml2/metadata/EntitiesDescriptor.setValidUntil:(Lorg/joda/time/DateTime;)V
      95: goto          172
      98: aload_2
      99: invokeinterface #12,  1           // InterfaceMethod org/w3c/dom/Attr.getLocalName:()Ljava/lang/String;
     104: ldc           #25                 // String cacheDuration
     106: invokevirtual #14                 // Method java/lang/String.equals:(Ljava/lang/Object;)Z
     109: ifeq          137
     112: aload_3
     113: new           #26                 // class java/lang/Long
     116: dup
     117: aload_2
     118: invokeinterface #15,  1           // InterfaceMethod org/w3c/dom/Attr.getValue:()Ljava/lang/String;
     123: invokestatic  #27                 // Method org/opensaml/xml/util/XMLHelper.durationToLong:(Ljava/lang/String;)J
     126: invokespecial #28                 // Method java/lang/Long."<init>":(J)V
     129: invokeinterface #29,  2           // InterfaceMethod org/opensaml/saml2/metadata/EntitiesDescriptor.setCacheDuration:(Ljava/lang/Long;)V
     134: goto          172
     137: aload_2
     138: invokeinterface #12,  1           // InterfaceMethod org/w3c/dom/Attr.getLocalName:()Ljava/lang/String;
     143: ldc           #30                 // String Name
     145: invokevirtual #14                 // Method java/lang/String.equals:(Ljava/lang/Object;)Z
     148: ifeq          166
     151: aload_3
     152: aload_2
     153: invokeinterface #15,  1           // InterfaceMethod org/w3c/dom/Attr.getValue:()Ljava/lang/String;
     158: invokeinterface #31,  2           // InterfaceMethod org/opensaml/saml2/metadata/EntitiesDescriptor.setName:(Ljava/lang/String;)V
     163: goto          172
     166: aload_0
     167: aload_1
     168: aload_2
     169: invokespecial #32                 // Method org/opensaml/common/impl/AbstractSAMLObjectUnmarshaller.processAttribute:(Lorg/opensaml/xml/XMLObject;Lorg/w3c/dom/Attr;)V
     172: return
}
