Compiled from "SOAPException.java"
public class org.opensaml.soap.common.SOAPException extends java.lang.Exception {
  private static final long serialVersionUID;

  public org.opensaml.soap.common.SOAPException();
    Code:
       0: aload_0
       1: invokespecial #1                  // Method java/lang/Exception."<init>":()V
       4: return

  public org.opensaml.soap.common.SOAPException(java.lang.String);
    Code:
       0: aload_0
       1: aload_1
       2: invokespecial #2                  // Method java/lang/Exception."<init>":(Ljava/lang/String;)V
       5: return

  public org.opensaml.soap.common.SOAPException(java.lang.Exception);
    Code:
       0: aload_0
       1: aload_1
       2: invokespecial #3                  // Method java/lang/Exception."<init>":(Ljava/lang/Throwable;)V
       5: return

  public org.opensaml.soap.common.SOAPException(java.lang.String, java.lang.Exception);
    Code:
       0: aload_0
       1: aload_1
       2: aload_2
       3: invokespecial #4                  // Method java/lang/Exception."<init>":(Ljava/lang/String;Ljava/lang/Throwable;)V
       6: return
}
