Compiled from "CadaverLockRecord.java"
public class com.arjuna.ats.internal.txoj.abstractrecords.CadaverLockRecord extends com.arjuna.ats.internal.txoj.abstractrecords.LockRecord {
  private com.arjuna.ats.txoj.lockstore.LockStore cadaverLockStore;

  private java.lang.String objectTypeName;

  private boolean doRelease;

  public com.arjuna.ats.internal.txoj.abstractrecords.CadaverLockRecord(com.arjuna.ats.txoj.lockstore.LockStore, com.arjuna.ats.txoj.LockManager, com.arjuna.ats.arjuna.coordinator.BasicAction);
    Code:
       0: aload_0
       1: aload_2
       2: aload_3
       3: invokespecial #1                  // Method com/arjuna/ats/internal/txoj/abstractrecords/LockRecord."<init>":(Lcom/arjuna/ats/txoj/LockManager;Lcom/arjuna/ats/arjuna/coordinator/BasicAction;)V
       6: aload_0
       7: aload_1
       8: putfield      #2                  // Field cadaverLockStore:Lcom/arjuna/ats/txoj/lockstore/LockStore;
      11: aload_0
      12: new           #3                  // class java/lang/String
      15: dup
      16: aload_2
      17: invokevirtual #4                  // Method com/arjuna/ats/txoj/LockManager.type:()Ljava/lang/String;
      20: invokespecial #5                  // Method java/lang/String."<init>":(Ljava/lang/String;)V
      23: putfield      #6                  // Field objectTypeName:Ljava/lang/String;
      26: aload_2
      27: invokevirtual #7                  // Method com/arjuna/ats/txoj/LockManager.getObjectModel:()I
      30: ifne          41
      33: aload_0
      34: iconst_0
      35: putfield      #8                  // Field doRelease:Z
      38: goto          46
      41: aload_0
      42: iconst_1
      43: putfield      #8                  // Field doRelease:Z
      46: getstatic     #9                  // Field com/arjuna/ats/txoj/logging/txojLogger.logger:Lorg/jboss/logging/Logger;
      49: invokevirtual #10                 // Method org/jboss/logging/Logger.isTraceEnabled:()Z
      52: ifeq          97
      55: getstatic     #9                  // Field com/arjuna/ats/txoj/logging/txojLogger.logger:Lorg/jboss/logging/Logger;
      58: new           #11                 // class java/lang/StringBuilder
      61: dup
      62: invokespecial #12                 // Method java/lang/StringBuilder."<init>":()V
      65: ldc           #13                 // String CadaverLockRecord::CadaverLockRecord(
      67: invokevirtual #14                 // Method java/lang/StringBuilder.append:(Ljava/lang/String;)Ljava/lang/StringBuilder;
      70: aload_1
      71: invokevirtual #15                 // Method java/lang/StringBuilder.append:(Ljava/lang/Object;)Ljava/lang/StringBuilder;
      74: ldc           #16                 // String ,
      76: invokevirtual #14                 // Method java/lang/StringBuilder.append:(Ljava/lang/String;)Ljava/lang/StringBuilder;
      79: aload_2
      80: invokevirtual #17                 // Method com/arjuna/ats/txoj/LockManager.get_uid:()Lcom/arjuna/ats/arjuna/common/Uid;
      83: invokevirtual #15                 // Method java/lang/StringBuilder.append:(Ljava/lang/Object;)Ljava/lang/StringBuilder;
      86: ldc           #18                 // String )
      88: invokevirtual #14                 // Method java/lang/StringBuilder.append:(Ljava/lang/String;)Ljava/lang/StringBuilder;
      91: invokevirtual #19                 // Method java/lang/StringBuilder.toString:()Ljava/lang/String;
      94: invokevirtual #20                 // Method org/jboss/logging/Logger.trace:(Ljava/lang/Object;)V
      97: return

  public boolean propagateOnAbort();
    Code:
       0: iconst_1
       1: ireturn

  public int nestedAbort();
    Code:
       0: getstatic     #9                  // Field com/arjuna/ats/txoj/logging/txojLogger.logger:Lorg/jboss/logging/Logger;
       3: invokevirtual #10                 // Method org/jboss/logging/Logger.isTraceEnabled:()Z
       6: ifeq          37
       9: getstatic     #9                  // Field com/arjuna/ats/txoj/logging/txojLogger.logger:Lorg/jboss/logging/Logger;
      12: new           #11                 // class java/lang/StringBuilder
      15: dup
      16: invokespecial #12                 // Method java/lang/StringBuilder."<init>":()V
      19: ldc           #21                 // String CadaverLockRecord::nestedAbort() for
      21: invokevirtual #14                 // Method java/lang/StringBuilder.append:(Ljava/lang/String;)Ljava/lang/StringBuilder;
      24: aload_0
      25: invokevirtual #22                 // Method order:()Lcom/arjuna/ats/arjuna/common/Uid;
      28: invokevirtual #15                 // Method java/lang/StringBuilder.append:(Ljava/lang/Object;)Ljava/lang/StringBuilder;
      31: invokevirtual #19                 // Method java/lang/StringBuilder.toString:()Ljava/lang/String;
      34: invokevirtual #20                 // Method org/jboss/logging/Logger.trace:(Ljava/lang/Object;)V
      37: aload_0
      38: getfield      #8                  // Field doRelease:Z
      41: ifeq          105
      44: new           #23                 // class com/arjuna/ats/internal/txoj/abstractrecords/CadaverLockManager
      47: dup
      48: aload_0
      49: invokevirtual #22                 // Method order:()Lcom/arjuna/ats/arjuna/common/Uid;
      52: aload_0
      53: getfield      #6                  // Field objectTypeName:Ljava/lang/String;
      56: invokespecial #24                 // Method com/arjuna/ats/internal/txoj/abstractrecords/CadaverLockManager."<init>":(Lcom/arjuna/ats/arjuna/common/Uid;Ljava/lang/String;)V
      59: astore_1
      60: aload_0
      61: getfield      #25                 // Field com/arjuna/ats/internal/txoj/abstractrecords/LockRecord.actionHandle:Lcom/arjuna/ats/arjuna/coordinator/BasicAction;
      64: ifnonnull     83
      67: new           #26                 // class com/arjuna/ats/arjuna/exceptions/FatalError
      70: dup
      71: getstatic     #27                 // Field com/arjuna/ats/txoj/logging/txojLogger.i18NLogger:Lcom/arjuna/ats/txoj/logging/txojI18NLogger;
      74: invokeinterface #28,  1           // InterfaceMethod com/arjuna/ats/txoj/logging/txojI18NLogger.get_CadaverLockRecord_1:()Ljava/lang/String;
      79: invokespecial #29                 // Method com/arjuna/ats/arjuna/exceptions/FatalError."<init>":(Ljava/lang/String;)V
      82: athrow
      83: aload_1
      84: aload_0
      85: getfield      #25                 // Field com/arjuna/ats/internal/txoj/abstractrecords/LockRecord.actionHandle:Lcom/arjuna/ats/arjuna/coordinator/BasicAction;
      88: invokevirtual #30                 // Method com/arjuna/ats/arjuna/coordinator/BasicAction.get_uid:()Lcom/arjuna/ats/arjuna/common/Uid;
      91: invokevirtual #31                 // Method com/arjuna/ats/internal/txoj/abstractrecords/CadaverLockManager.releaseAll:(Lcom/arjuna/ats/arjuna/common/Uid;)Z
      94: ifeq          102
      97: bipush        7
      99: goto          104
     102: bipush        8
     104: ireturn
     105: bipush        7
     107: ireturn

  public int nestedCommit();
    Code:
       0: getstatic     #9                  // Field com/arjuna/ats/txoj/logging/txojLogger.logger:Lorg/jboss/logging/Logger;
       3: invokevirtual #10                 // Method org/jboss/logging/Logger.isTraceEnabled:()Z
       6: ifeq          37
       9: getstatic     #9                  // Field com/arjuna/ats/txoj/logging/txojLogger.logger:Lorg/jboss/logging/Logger;
      12: new           #11                 // class java/lang/StringBuilder
      15: dup
      16: invokespecial #12                 // Method java/lang/StringBuilder."<init>":()V
      19: ldc           #33                 // String CadaverLockRecord::nestedCommit() for
      21: invokevirtual #14                 // Method java/lang/StringBuilder.append:(Ljava/lang/String;)Ljava/lang/StringBuilder;
      24: aload_0
      25: invokevirtual #22                 // Method order:()Lcom/arjuna/ats/arjuna/common/Uid;
      28: invokevirtual #15                 // Method java/lang/StringBuilder.append:(Ljava/lang/Object;)Ljava/lang/StringBuilder;
      31: invokevirtual #19                 // Method java/lang/StringBuilder.toString:()Ljava/lang/String;
      34: invokevirtual #20                 // Method org/jboss/logging/Logger.trace:(Ljava/lang/Object;)V
      37: aload_0
      38: getfield      #8                  // Field doRelease:Z
      41: ifeq          115
      44: aload_0
      45: getfield      #25                 // Field com/arjuna/ats/internal/txoj/abstractrecords/LockRecord.actionHandle:Lcom/arjuna/ats/arjuna/coordinator/BasicAction;
      48: ifnonnull     67
      51: new           #26                 // class com/arjuna/ats/arjuna/exceptions/FatalError
      54: dup
      55: getstatic     #27                 // Field com/arjuna/ats/txoj/logging/txojLogger.i18NLogger:Lcom/arjuna/ats/txoj/logging/txojI18NLogger;
      58: invokeinterface #34,  1           // InterfaceMethod com/arjuna/ats/txoj/logging/txojI18NLogger.get_CadaverLockRecord_2:()Ljava/lang/String;
      63: invokespecial #29                 // Method com/arjuna/ats/arjuna/exceptions/FatalError."<init>":(Ljava/lang/String;)V
      66: athrow
      67: new           #23                 // class com/arjuna/ats/internal/txoj/abstractrecords/CadaverLockManager
      70: dup
      71: aload_0
      72: invokevirtual #22                 // Method order:()Lcom/arjuna/ats/arjuna/common/Uid;
      75: aload_0
      76: getfield      #6                  // Field objectTypeName:Ljava/lang/String;
      79: invokespecial #24                 // Method com/arjuna/ats/internal/txoj/abstractrecords/CadaverLockManager."<init>":(Lcom/arjuna/ats/arjuna/common/Uid;Ljava/lang/String;)V
      82: astore_1
      83: aload_1
      84: aload_0
      85: getfield      #25                 // Field com/arjuna/ats/internal/txoj/abstractrecords/LockRecord.actionHandle:Lcom/arjuna/ats/arjuna/coordinator/BasicAction;
      88: invokevirtual #30                 // Method com/arjuna/ats/arjuna/coordinator/BasicAction.get_uid:()Lcom/arjuna/ats/arjuna/common/Uid;
      91: aload_0
      92: getfield      #25                 // Field com/arjuna/ats/internal/txoj/abstractrecords/LockRecord.actionHandle:Lcom/arjuna/ats/arjuna/coordinator/BasicAction;
      95: invokevirtual #35                 // Method com/arjuna/ats/arjuna/coordinator/BasicAction.parent:()Lcom/arjuna/ats/arjuna/coordinator/BasicAction;
      98: invokevirtual #30                 // Method com/arjuna/ats/arjuna/coordinator/BasicAction.get_uid:()Lcom/arjuna/ats/arjuna/common/Uid;
     101: invokevirtual #36                 // Method com/arjuna/ats/internal/txoj/abstractrecords/CadaverLockManager.propagate:(Lcom/arjuna/ats/arjuna/common/Uid;Lcom/arjuna/ats/arjuna/common/Uid;)Z
     104: ifeq          112
     107: bipush        7
     109: goto          114
     112: bipush        8
     114: ireturn
     115: bipush        7
     117: ireturn

  public int topLevelAbort();
    Code:
       0: getstatic     #9                  // Field com/arjuna/ats/txoj/logging/txojLogger.logger:Lorg/jboss/logging/Logger;
       3: invokevirtual #10                 // Method org/jboss/logging/Logger.isTraceEnabled:()Z
       6: ifeq          37
       9: getstatic     #9                  // Field com/arjuna/ats/txoj/logging/txojLogger.logger:Lorg/jboss/logging/Logger;
      12: new           #11                 // class java/lang/StringBuilder
      15: dup
      16: invokespecial #12                 // Method java/lang/StringBuilder."<init>":()V
      19: ldc           #37                 // String CadaverLockRecord::topLevelAbort() for
      21: invokevirtual #14                 // Method java/lang/StringBuilder.append:(Ljava/lang/String;)Ljava/lang/StringBuilder;
      24: aload_0
      25: invokevirtual #22                 // Method order:()Lcom/arjuna/ats/arjuna/common/Uid;
      28: invokevirtual #15                 // Method java/lang/StringBuilder.append:(Ljava/lang/Object;)Ljava/lang/StringBuilder;
      31: invokevirtual #19                 // Method java/lang/StringBuilder.toString:()Ljava/lang/String;
      34: invokevirtual #20                 // Method org/jboss/logging/Logger.trace:(Ljava/lang/Object;)V
      37: aload_0
      38: getfield      #8                  // Field doRelease:Z
      41: ifeq          105
      44: aload_0
      45: getfield      #25                 // Field com/arjuna/ats/internal/txoj/abstractrecords/LockRecord.actionHandle:Lcom/arjuna/ats/arjuna/coordinator/BasicAction;
      48: ifnonnull     67
      51: new           #26                 // class com/arjuna/ats/arjuna/exceptions/FatalError
      54: dup
      55: getstatic     #27                 // Field com/arjuna/ats/txoj/logging/txojLogger.i18NLogger:Lcom/arjuna/ats/txoj/logging/txojI18NLogger;
      58: invokeinterface #38,  1           // InterfaceMethod com/arjuna/ats/txoj/logging/txojI18NLogger.get_CadaverLockRecord_3:()Ljava/lang/String;
      63: invokespecial #29                 // Method com/arjuna/ats/arjuna/exceptions/FatalError."<init>":(Ljava/lang/String;)V
      66: athrow
      67: new           #23                 // class com/arjuna/ats/internal/txoj/abstractrecords/CadaverLockManager
      70: dup
      71: aload_0
      72: invokevirtual #22                 // Method order:()Lcom/arjuna/ats/arjuna/common/Uid;
      75: aload_0
      76: getfield      #6                  // Field objectTypeName:Ljava/lang/String;
      79: invokespecial #24                 // Method com/arjuna/ats/internal/txoj/abstractrecords/CadaverLockManager."<init>":(Lcom/arjuna/ats/arjuna/common/Uid;Ljava/lang/String;)V
      82: astore_1
      83: aload_1
      84: aload_0
      85: getfield      #25                 // Field com/arjuna/ats/internal/txoj/abstractrecords/LockRecord.actionHandle:Lcom/arjuna/ats/arjuna/coordinator/BasicAction;
      88: invokevirtual #30                 // Method com/arjuna/ats/arjuna/coordinator/BasicAction.get_uid:()Lcom/arjuna/ats/arjuna/common/Uid;
      91: invokevirtual #31                 // Method com/arjuna/ats/internal/txoj/abstractrecords/CadaverLockManager.releaseAll:(Lcom/arjuna/ats/arjuna/common/Uid;)Z
      94: ifeq          102
      97: bipush        7
      99: goto          104
     102: bipush        8
     104: ireturn
     105: bipush        7
     107: ireturn

  public int topLevelCommit();
    Code:
       0: getstatic     #9                  // Field com/arjuna/ats/txoj/logging/txojLogger.logger:Lorg/jboss/logging/Logger;
       3: invokevirtual #10                 // Method org/jboss/logging/Logger.isTraceEnabled:()Z
       6: ifeq          37
       9: getstatic     #9                  // Field com/arjuna/ats/txoj/logging/txojLogger.logger:Lorg/jboss/logging/Logger;
      12: new           #11                 // class java/lang/StringBuilder
      15: dup
      16: invokespecial #12                 // Method java/lang/StringBuilder."<init>":()V
      19: ldc           #39                 // String CadaverLockRecord::topLevelCommit() for
      21: invokevirtual #14                 // Method java/lang/StringBuilder.append:(Ljava/lang/String;)Ljava/lang/StringBuilder;
      24: aload_0
      25: invokevirtual #22                 // Method order:()Lcom/arjuna/ats/arjuna/common/Uid;
      28: invokevirtual #15                 // Method java/lang/StringBuilder.append:(Ljava/lang/Object;)Ljava/lang/StringBuilder;
      31: invokevirtual #19                 // Method java/lang/StringBuilder.toString:()Ljava/lang/String;
      34: invokevirtual #20                 // Method org/jboss/logging/Logger.trace:(Ljava/lang/Object;)V
      37: aload_0
      38: getfield      #8                  // Field doRelease:Z
      41: ifeq          105
      44: aload_0
      45: getfield      #25                 // Field com/arjuna/ats/internal/txoj/abstractrecords/LockRecord.actionHandle:Lcom/arjuna/ats/arjuna/coordinator/BasicAction;
      48: ifnonnull     67
      51: new           #26                 // class com/arjuna/ats/arjuna/exceptions/FatalError
      54: dup
      55: getstatic     #27                 // Field com/arjuna/ats/txoj/logging/txojLogger.i18NLogger:Lcom/arjuna/ats/txoj/logging/txojI18NLogger;
      58: invokeinterface #40,  1           // InterfaceMethod com/arjuna/ats/txoj/logging/txojI18NLogger.get_CadaverLockRecord_4:()Ljava/lang/String;
      63: invokespecial #29                 // Method com/arjuna/ats/arjuna/exceptions/FatalError."<init>":(Ljava/lang/String;)V
      66: athrow
      67: new           #23                 // class com/arjuna/ats/internal/txoj/abstractrecords/CadaverLockManager
      70: dup
      71: aload_0
      72: invokevirtual #22                 // Method order:()Lcom/arjuna/ats/arjuna/common/Uid;
      75: aload_0
      76: getfield      #6                  // Field objectTypeName:Ljava/lang/String;
      79: invokespecial #24                 // Method com/arjuna/ats/internal/txoj/abstractrecords/CadaverLockManager."<init>":(Lcom/arjuna/ats/arjuna/common/Uid;Ljava/lang/String;)V
      82: astore_1
      83: aload_1
      84: aload_0
      85: getfield      #25                 // Field com/arjuna/ats/internal/txoj/abstractrecords/LockRecord.actionHandle:Lcom/arjuna/ats/arjuna/coordinator/BasicAction;
      88: invokevirtual #30                 // Method com/arjuna/ats/arjuna/coordinator/BasicAction.get_uid:()Lcom/arjuna/ats/arjuna/common/Uid;
      91: invokevirtual #31                 // Method com/arjuna/ats/internal/txoj/abstractrecords/CadaverLockManager.releaseAll:(Lcom/arjuna/ats/arjuna/common/Uid;)Z
      94: ifeq          102
      97: bipush        7
      99: goto          104
     102: bipush        8
     104: ireturn
     105: bipush        7
     107: ireturn

  public void print(java.io.PrintWriter);
    Code:
       0: aload_1
       1: ldc           #41                 // String CadaverLockRecord :
       3: invokevirtual #42                 // Method java/io/PrintWriter.println:(Ljava/lang/String;)V
       6: aload_0
       7: aload_1
       8: invokespecial #43                 // Method com/arjuna/ats/internal/txoj/abstractrecords/LockRecord.print:(Ljava/io/PrintWriter;)V
      11: return

  public java.lang.String type();
    Code:
       0: ldc           #44                 // String /StateManager/AbstractRecord/LockRecord/CadaverLockRecord
       2: areturn

  public boolean shouldReplace(com.arjuna.ats.arjuna.coordinator.AbstractRecord);
    Code:
       0: aload_0
       1: invokevirtual #22                 // Method order:()Lcom/arjuna/ats/arjuna/common/Uid;
       4: aload_1
       5: invokevirtual #45                 // Method com/arjuna/ats/arjuna/coordinator/AbstractRecord.order:()Lcom/arjuna/ats/arjuna/common/Uid;
       8: invokevirtual #46                 // Method com/arjuna/ats/arjuna/common/Uid.equals:(Lcom/arjuna/ats/arjuna/common/Uid;)Z
      11: ifeq          27
      14: aload_1
      15: invokevirtual #47                 // Method com/arjuna/ats/arjuna/coordinator/AbstractRecord.typeIs:()I
      18: bipush        121
      20: if_icmpne     27
      23: iconst_1
      24: goto          28
      27: iconst_0
      28: ireturn

  public void replace(com.arjuna.ats.arjuna.coordinator.AbstractRecord);
    Code:
       0: aload_1
       1: checkcast     #49                 // class com/arjuna/ats/internal/txoj/abstractrecords/LockRecord
       4: astore_2
       5: aload_0
       6: aload_2
       7: invokevirtual #50                 // Method com/arjuna/ats/internal/txoj/abstractrecords/LockRecord.lockType:()Ljava/lang/String;
      10: putfield      #6                  // Field objectTypeName:Ljava/lang/String;
      13: return

  protected com.arjuna.ats.internal.txoj.abstractrecords.CadaverLockRecord();
    Code:
       0: aload_0
       1: invokespecial #51                 // Method com/arjuna/ats/internal/txoj/abstractrecords/LockRecord."<init>":()V
       4: aload_0
       5: aconst_null
       6: putfield      #2                  // Field cadaverLockStore:Lcom/arjuna/ats/txoj/lockstore/LockStore;
       9: aload_0
      10: aconst_null
      11: putfield      #6                  // Field objectTypeName:Ljava/lang/String;
      14: aload_0
      15: iconst_0
      16: putfield      #8                  // Field doRelease:Z
      19: getstatic     #9                  // Field com/arjuna/ats/txoj/logging/txojLogger.logger:Lorg/jboss/logging/Logger;
      22: invokevirtual #10                 // Method org/jboss/logging/Logger.isTraceEnabled:()Z
      25: ifeq          36
      28: getstatic     #9                  // Field com/arjuna/ats/txoj/logging/txojLogger.logger:Lorg/jboss/logging/Logger;
      31: ldc           #52                 // String CadaverLockRecord::CadaverLockRecord ()
      33: invokevirtual #20                 // Method org/jboss/logging/Logger.trace:(Ljava/lang/Object;)V
      36: return
}
