Compiled from "ConfigMapProjectionBuilder.java"
public class io.dekorate.deps.kubernetes.api.model.ConfigMapProjectionBuilder extends io.dekorate.deps.kubernetes.api.model.ConfigMapProjectionFluentImpl<io.dekorate.deps.kubernetes.api.model.ConfigMapProjectionBuilder> implements io.dekorate.deps.kubernetes.api.builder.VisitableBuilder<io.dekorate.deps.kubernetes.api.model.ConfigMapProjection, io.dekorate.deps.kubernetes.api.model.ConfigMapProjectionBuilder> {
  io.dekorate.deps.kubernetes.api.model.ConfigMapProjectionFluent<?> fluent;

  java.lang.Boolean validationEnabled;

  public io.dekorate.deps.kubernetes.api.model.ConfigMapProjectionBuilder();
    Code:
       0: aload_0
       1: iconst_1
       2: invokestatic  #21                 // Method java/lang/Boolean.valueOf:(Z)Ljava/lang/Boolean;
       5: invokespecial #24                 // Method "<init>":(Ljava/lang/Boolean;)V
       8: return

  public io.dekorate.deps.kubernetes.api.model.ConfigMapProjectionBuilder(java.lang.Boolean);
    Code:
       0: aload_0
       1: new           #28                 // class io/dekorate/deps/kubernetes/api/model/ConfigMapProjection
       4: dup
       5: invokespecial #30                 // Method io/dekorate/deps/kubernetes/api/model/ConfigMapProjection."<init>":()V
       8: aload_1
       9: invokespecial #33                 // Method "<init>":(Lio/dekorate/deps/kubernetes/api/model/ConfigMapProjection;Ljava/lang/Boolean;)V
      12: return

  public io.dekorate.deps.kubernetes.api.model.ConfigMapProjectionBuilder(io.dekorate.deps.kubernetes.api.model.ConfigMapProjectionFluent<?>);
    Code:
       0: aload_0
       1: aload_1
       2: iconst_1
       3: invokestatic  #21                 // Method java/lang/Boolean.valueOf:(Z)Ljava/lang/Boolean;
       6: invokespecial #38                 // Method "<init>":(Lio/dekorate/deps/kubernetes/api/model/ConfigMapProjectionFluent;Ljava/lang/Boolean;)V
       9: return

  public io.dekorate.deps.kubernetes.api.model.ConfigMapProjectionBuilder(io.dekorate.deps.kubernetes.api.model.ConfigMapProjectionFluent<?>, java.lang.Boolean);
    Code:
       0: aload_0
       1: aload_1
       2: new           #28                 // class io/dekorate/deps/kubernetes/api/model/ConfigMapProjection
       5: dup
       6: invokespecial #30                 // Method io/dekorate/deps/kubernetes/api/model/ConfigMapProjection."<init>":()V
       9: aload_2
      10: invokespecial #42                 // Method "<init>":(Lio/dekorate/deps/kubernetes/api/model/ConfigMapProjectionFluent;Lio/dekorate/deps/kubernetes/api/model/ConfigMapProjection;Ljava/lang/Boolean;)V
      13: return

  public io.dekorate.deps.kubernetes.api.model.ConfigMapProjectionBuilder(io.dekorate.deps.kubernetes.api.model.ConfigMapProjectionFluent<?>, io.dekorate.deps.kubernetes.api.model.ConfigMapProjection);
    Code:
       0: aload_0
       1: aload_1
       2: aload_2
       3: iconst_1
       4: invokestatic  #21                 // Method java/lang/Boolean.valueOf:(Z)Ljava/lang/Boolean;
       7: invokespecial #42                 // Method "<init>":(Lio/dekorate/deps/kubernetes/api/model/ConfigMapProjectionFluent;Lio/dekorate/deps/kubernetes/api/model/ConfigMapProjection;Ljava/lang/Boolean;)V
      10: return

  public io.dekorate.deps.kubernetes.api.model.ConfigMapProjectionBuilder(io.dekorate.deps.kubernetes.api.model.ConfigMapProjectionFluent<?>, io.dekorate.deps.kubernetes.api.model.ConfigMapProjection, java.lang.Boolean);
    Code:
       0: aload_0
       1: invokespecial #48                 // Method io/dekorate/deps/kubernetes/api/model/ConfigMapProjectionFluentImpl."<init>":()V
       4: aload_0
       5: aload_1
       6: putfield      #50                 // Field fluent:Lio/dekorate/deps/kubernetes/api/model/ConfigMapProjectionFluent;
       9: aload_1
      10: aload_2
      11: invokevirtual #54                 // Method io/dekorate/deps/kubernetes/api/model/ConfigMapProjection.getItems:()Ljava/util/List;
      14: invokeinterface #60,  2           // InterfaceMethod io/dekorate/deps/kubernetes/api/model/ConfigMapProjectionFluent.withItems:(Ljava/util/List;)Lio/dekorate/deps/kubernetes/api/model/ConfigMapProjectionFluent;
      19: pop
      20: aload_1
      21: aload_2
      22: invokevirtual #64                 // Method io/dekorate/deps/kubernetes/api/model/ConfigMapProjection.getName:()Ljava/lang/String;
      25: invokeinterface #68,  2           // InterfaceMethod io/dekorate/deps/kubernetes/api/model/ConfigMapProjectionFluent.withName:(Ljava/lang/String;)Lio/dekorate/deps/kubernetes/api/model/ConfigMapProjectionFluent;
      30: pop
      31: aload_1
      32: aload_2
      33: invokevirtual #72                 // Method io/dekorate/deps/kubernetes/api/model/ConfigMapProjection.getOptional:()Ljava/lang/Boolean;
      36: invokeinterface #76,  2           // InterfaceMethod io/dekorate/deps/kubernetes/api/model/ConfigMapProjectionFluent.withOptional:(Ljava/lang/Boolean;)Lio/dekorate/deps/kubernetes/api/model/ConfigMapProjectionFluent;
      41: pop
      42: aload_0
      43: aload_3
      44: putfield      #78                 // Field validationEnabled:Ljava/lang/Boolean;
      47: return

  public io.dekorate.deps.kubernetes.api.model.ConfigMapProjectionBuilder(io.dekorate.deps.kubernetes.api.model.ConfigMapProjection);
    Code:
       0: aload_0
       1: aload_1
       2: iconst_1
       3: invokestatic  #21                 // Method java/lang/Boolean.valueOf:(Z)Ljava/lang/Boolean;
       6: invokespecial #33                 // Method "<init>":(Lio/dekorate/deps/kubernetes/api/model/ConfigMapProjection;Ljava/lang/Boolean;)V
       9: return

  public io.dekorate.deps.kubernetes.api.model.ConfigMapProjectionBuilder(io.dekorate.deps.kubernetes.api.model.ConfigMapProjection, java.lang.Boolean);
    Code:
       0: aload_0
       1: invokespecial #48                 // Method io/dekorate/deps/kubernetes/api/model/ConfigMapProjectionFluentImpl."<init>":()V
       4: aload_0
       5: aload_0
       6: putfield      #50                 // Field fluent:Lio/dekorate/deps/kubernetes/api/model/ConfigMapProjectionFluent;
       9: aload_0
      10: aload_1
      11: invokevirtual #54                 // Method io/dekorate/deps/kubernetes/api/model/ConfigMapProjection.getItems:()Ljava/util/List;
      14: invokevirtual #80                 // Method withItems:(Ljava/util/List;)Lio/dekorate/deps/kubernetes/api/model/ConfigMapProjectionFluent;
      17: pop
      18: aload_0
      19: aload_1
      20: invokevirtual #64                 // Method io/dekorate/deps/kubernetes/api/model/ConfigMapProjection.getName:()Ljava/lang/String;
      23: invokevirtual #81                 // Method withName:(Ljava/lang/String;)Lio/dekorate/deps/kubernetes/api/model/ConfigMapProjectionFluent;
      26: pop
      27: aload_0
      28: aload_1
      29: invokevirtual #72                 // Method io/dekorate/deps/kubernetes/api/model/ConfigMapProjection.getOptional:()Ljava/lang/Boolean;
      32: invokevirtual #82                 // Method withOptional:(Ljava/lang/Boolean;)Lio/dekorate/deps/kubernetes/api/model/ConfigMapProjectionFluent;
      35: pop
      36: aload_0
      37: aload_2
      38: putfield      #78                 // Field validationEnabled:Ljava/lang/Boolean;
      41: return

  public io.dekorate.deps.kubernetes.api.model.ConfigMapProjection build();
    Code:
       0: new           #28                 // class io/dekorate/deps/kubernetes/api/model/ConfigMapProjection
       3: dup
       4: aload_0
       5: getfield      #50                 // Field fluent:Lio/dekorate/deps/kubernetes/api/model/ConfigMapProjectionFluent;
       8: invokeinterface #85,  1           // InterfaceMethod io/dekorate/deps/kubernetes/api/model/ConfigMapProjectionFluent.getItems:()Ljava/util/List;
      13: aload_0
      14: getfield      #50                 // Field fluent:Lio/dekorate/deps/kubernetes/api/model/ConfigMapProjectionFluent;
      17: invokeinterface #86,  1           // InterfaceMethod io/dekorate/deps/kubernetes/api/model/ConfigMapProjectionFluent.getName:()Ljava/lang/String;
      22: aload_0
      23: getfield      #50                 // Field fluent:Lio/dekorate/deps/kubernetes/api/model/ConfigMapProjectionFluent;
      26: invokeinterface #89,  1           // InterfaceMethod io/dekorate/deps/kubernetes/api/model/ConfigMapProjectionFluent.isOptional:()Ljava/lang/Boolean;
      31: invokespecial #92                 // Method io/dekorate/deps/kubernetes/api/model/ConfigMapProjection."<init>":(Ljava/util/List;Ljava/lang/String;Ljava/lang/Boolean;)V
      34: astore_1
      35: aload_1
      36: areturn

  public boolean equals(java.lang.Object);
    Code:
       0: aload_0
       1: aload_1
       2: if_acmpne     7
       5: iconst_1
       6: ireturn
       7: aload_1
       8: ifnull        22
      11: aload_0
      12: invokevirtual #101                // Method java/lang/Object.getClass:()Ljava/lang/Class;
      15: aload_1
      16: invokevirtual #101                // Method java/lang/Object.getClass:()Ljava/lang/Class;
      19: if_acmpeq     24
      22: iconst_0
      23: ireturn
      24: aload_0
      25: aload_1
      26: invokespecial #103                // Method io/dekorate/deps/kubernetes/api/model/ConfigMapProjectionFluentImpl.equals:(Ljava/lang/Object;)Z
      29: ifne          34
      32: iconst_0
      33: ireturn
      34: aload_1
      35: checkcast     #2                  // class io/dekorate/deps/kubernetes/api/model/ConfigMapProjectionBuilder
      38: astore_2
      39: aload_0
      40: getfield      #50                 // Field fluent:Lio/dekorate/deps/kubernetes/api/model/ConfigMapProjectionFluent;
      43: ifnull        71
      46: aload_0
      47: getfield      #50                 // Field fluent:Lio/dekorate/deps/kubernetes/api/model/ConfigMapProjectionFluent;
      50: aload_0
      51: if_acmpeq     71
      54: aload_0
      55: getfield      #50                 // Field fluent:Lio/dekorate/deps/kubernetes/api/model/ConfigMapProjectionFluent;
      58: aload_2
      59: getfield      #50                 // Field fluent:Lio/dekorate/deps/kubernetes/api/model/ConfigMapProjectionFluent;
      62: invokevirtual #104                // Method java/lang/Object.equals:(Ljava/lang/Object;)Z
      65: ifne          88
      68: goto          86
      71: aload_2
      72: getfield      #50                 // Field fluent:Lio/dekorate/deps/kubernetes/api/model/ConfigMapProjectionFluent;
      75: ifnull        88
      78: aload_0
      79: getfield      #50                 // Field fluent:Lio/dekorate/deps/kubernetes/api/model/ConfigMapProjectionFluent;
      82: aload_0
      83: if_acmpeq     88
      86: iconst_0
      87: ireturn
      88: aload_0
      89: getfield      #78                 // Field validationEnabled:Ljava/lang/Boolean;
      92: ifnull        112
      95: aload_0
      96: getfield      #78                 // Field validationEnabled:Ljava/lang/Boolean;
      99: aload_2
     100: getfield      #78                 // Field validationEnabled:Ljava/lang/Boolean;
     103: invokevirtual #105                // Method java/lang/Boolean.equals:(Ljava/lang/Object;)Z
     106: ifne          121
     109: goto          119
     112: aload_2
     113: getfield      #78                 // Field validationEnabled:Ljava/lang/Boolean;
     116: ifnull        121
     119: iconst_0
     120: ireturn
     121: iconst_1
     122: ireturn

  public java.lang.Object build();
    Code:
       0: aload_0
       1: invokevirtual #111                // Method build:()Lio/dekorate/deps/kubernetes/api/model/ConfigMapProjection;
       4: areturn
}
