Compiled from "ConfigFluentImpl.java"
public class io.dekorate.deps.kubernetes.api.model.ConfigFluentImpl$ContextsNestedImpl<N> extends io.dekorate.deps.kubernetes.api.model.NamedContextFluentImpl<io.dekorate.deps.kubernetes.api.model.ConfigFluent$ContextsNested<N>> implements io.dekorate.deps.kubernetes.api.model.ConfigFluent$ContextsNested<N>, io.dekorate.deps.kubernetes.api.builder.Nested<N> {
  private final io.dekorate.deps.kubernetes.api.model.NamedContextBuilder builder;

  private final int index;

  final io.dekorate.deps.kubernetes.api.model.ConfigFluentImpl this$0;

  io.dekorate.deps.kubernetes.api.model.ConfigFluentImpl$ContextsNestedImpl(io.dekorate.deps.kubernetes.api.model.ConfigFluentImpl, int, io.dekorate.deps.kubernetes.api.model.NamedContext);
    Code:
       0: aload_0
       1: aload_1
       2: putfield      #26                 // Field this$0:Lio/dekorate/deps/kubernetes/api/model/ConfigFluentImpl;
       5: aload_0
       6: invokespecial #29                 // Method io/dekorate/deps/kubernetes/api/model/NamedContextFluentImpl."<init>":()V
       9: aload_0
      10: iload_2
      11: putfield      #31                 // Field index:I
      14: aload_0
      15: new           #33                 // class io/dekorate/deps/kubernetes/api/model/NamedContextBuilder
      18: dup
      19: aload_0
      20: aload_3
      21: invokespecial #36                 // Method io/dekorate/deps/kubernetes/api/model/NamedContextBuilder."<init>":(Lio/dekorate/deps/kubernetes/api/model/NamedContextFluent;Lio/dekorate/deps/kubernetes/api/model/NamedContext;)V
      24: putfield      #38                 // Field builder:Lio/dekorate/deps/kubernetes/api/model/NamedContextBuilder;
      27: return

  io.dekorate.deps.kubernetes.api.model.ConfigFluentImpl$ContextsNestedImpl(io.dekorate.deps.kubernetes.api.model.ConfigFluentImpl);
    Code:
       0: aload_0
       1: aload_1
       2: putfield      #26                 // Field this$0:Lio/dekorate/deps/kubernetes/api/model/ConfigFluentImpl;
       5: aload_0
       6: invokespecial #29                 // Method io/dekorate/deps/kubernetes/api/model/NamedContextFluentImpl."<init>":()V
       9: aload_0
      10: iconst_m1
      11: putfield      #31                 // Field index:I
      14: aload_0
      15: new           #33                 // class io/dekorate/deps/kubernetes/api/model/NamedContextBuilder
      18: dup
      19: aload_0
      20: invokespecial #47                 // Method io/dekorate/deps/kubernetes/api/model/NamedContextBuilder."<init>":(Lio/dekorate/deps/kubernetes/api/model/NamedContextFluent;)V
      23: putfield      #38                 // Field builder:Lio/dekorate/deps/kubernetes/api/model/NamedContextBuilder;
      26: return

  public N and();
    Code:
       0: aload_0
       1: getfield      #26                 // Field this$0:Lio/dekorate/deps/kubernetes/api/model/ConfigFluentImpl;
       4: aload_0
       5: getfield      #31                 // Field index:I
       8: aload_0
       9: getfield      #38                 // Field builder:Lio/dekorate/deps/kubernetes/api/model/NamedContextBuilder;
      12: invokevirtual #54                 // Method io/dekorate/deps/kubernetes/api/model/NamedContextBuilder.build:()Lio/dekorate/deps/kubernetes/api/model/NamedContext;
      15: invokevirtual #58                 // Method io/dekorate/deps/kubernetes/api/model/ConfigFluentImpl.setToContexts:(ILio/dekorate/deps/kubernetes/api/model/NamedContext;)Lio/dekorate/deps/kubernetes/api/model/ConfigFluent;
      18: areturn

  public N endContext();
    Code:
       0: aload_0
       1: invokevirtual #61                 // Method and:()Ljava/lang/Object;
       4: areturn
}
