Compiled from "ContainerStateFluentImpl.java"
public class io.dekorate.deps.kubernetes.api.model.ContainerStateFluentImpl<A extends io.dekorate.deps.kubernetes.api.model.ContainerStateFluent<A>> extends io.dekorate.deps.kubernetes.api.builder.BaseFluent<A> implements io.dekorate.deps.kubernetes.api.model.ContainerStateFluent<A> {
  private io.dekorate.deps.kubernetes.api.model.ContainerStateRunningBuilder running;

  private io.dekorate.deps.kubernetes.api.model.ContainerStateTerminatedBuilder terminated;

  private io.dekorate.deps.kubernetes.api.model.ContainerStateWaitingBuilder waiting;

  public io.dekorate.deps.kubernetes.api.model.ContainerStateFluentImpl();
    Code:
       0: aload_0
       1: invokespecial #36                 // Method io/dekorate/deps/kubernetes/api/builder/BaseFluent."<init>":()V
       4: return

  public io.dekorate.deps.kubernetes.api.model.ContainerStateFluentImpl(io.dekorate.deps.kubernetes.api.model.ContainerState);
    Code:
       0: aload_0
       1: invokespecial #36                 // Method io/dekorate/deps/kubernetes/api/builder/BaseFluent."<init>":()V
       4: aload_0
       5: aload_1
       6: invokevirtual #46                 // Method io/dekorate/deps/kubernetes/api/model/ContainerState.getRunning:()Lio/dekorate/deps/kubernetes/api/model/ContainerStateRunning;
       9: invokevirtual #50                 // Method withRunning:(Lio/dekorate/deps/kubernetes/api/model/ContainerStateRunning;)Lio/dekorate/deps/kubernetes/api/model/ContainerStateFluent;
      12: pop
      13: aload_0
      14: aload_1
      15: invokevirtual #54                 // Method io/dekorate/deps/kubernetes/api/model/ContainerState.getTerminated:()Lio/dekorate/deps/kubernetes/api/model/ContainerStateTerminated;
      18: invokevirtual #58                 // Method withTerminated:(Lio/dekorate/deps/kubernetes/api/model/ContainerStateTerminated;)Lio/dekorate/deps/kubernetes/api/model/ContainerStateFluent;
      21: pop
      22: aload_0
      23: aload_1
      24: invokevirtual #62                 // Method io/dekorate/deps/kubernetes/api/model/ContainerState.getWaiting:()Lio/dekorate/deps/kubernetes/api/model/ContainerStateWaiting;
      27: invokevirtual #66                 // Method withWaiting:(Lio/dekorate/deps/kubernetes/api/model/ContainerStateWaiting;)Lio/dekorate/deps/kubernetes/api/model/ContainerStateFluent;
      30: pop
      31: return

  public io.dekorate.deps.kubernetes.api.model.ContainerStateRunning getRunning();
    Code:
       0: aload_0
       1: getfield      #71                 // Field running:Lio/dekorate/deps/kubernetes/api/model/ContainerStateRunningBuilder;
       4: ifnull        17
       7: aload_0
       8: getfield      #71                 // Field running:Lio/dekorate/deps/kubernetes/api/model/ContainerStateRunningBuilder;
      11: invokevirtual #76                 // Method io/dekorate/deps/kubernetes/api/model/ContainerStateRunningBuilder.build:()Lio/dekorate/deps/kubernetes/api/model/ContainerStateRunning;
      14: goto          18
      17: aconst_null
      18: areturn

  public io.dekorate.deps.kubernetes.api.model.ContainerStateRunning buildRunning();
    Code:
       0: aload_0
       1: getfield      #71                 // Field running:Lio/dekorate/deps/kubernetes/api/model/ContainerStateRunningBuilder;
       4: ifnull        17
       7: aload_0
       8: getfield      #71                 // Field running:Lio/dekorate/deps/kubernetes/api/model/ContainerStateRunningBuilder;
      11: invokevirtual #76                 // Method io/dekorate/deps/kubernetes/api/model/ContainerStateRunningBuilder.build:()Lio/dekorate/deps/kubernetes/api/model/ContainerStateRunning;
      14: goto          18
      17: aconst_null
      18: areturn

  public A withRunning(io.dekorate.deps.kubernetes.api.model.ContainerStateRunning);
    Code:
       0: aload_0
       1: getfield      #84                 // Field _visitables:Lio/dekorate/deps/kubernetes/api/builder/VisitableMap;
       4: ldc           #85                 // String running
       6: invokevirtual #91                 // Method io/dekorate/deps/kubernetes/api/builder/VisitableMap.get:(Ljava/lang/Object;)Ljava/util/List;
       9: aload_0
      10: getfield      #71                 // Field running:Lio/dekorate/deps/kubernetes/api/model/ContainerStateRunningBuilder;
      13: invokeinterface #97,  2           // InterfaceMethod java/util/List.remove:(Ljava/lang/Object;)Z
      18: pop
      19: aload_1
      20: ifnull        54
      23: aload_0
      24: new           #73                 // class io/dekorate/deps/kubernetes/api/model/ContainerStateRunningBuilder
      27: dup
      28: aload_1
      29: invokespecial #100                // Method io/dekorate/deps/kubernetes/api/model/ContainerStateRunningBuilder."<init>":(Lio/dekorate/deps/kubernetes/api/model/ContainerStateRunning;)V
      32: putfield      #71                 // Field running:Lio/dekorate/deps/kubernetes/api/model/ContainerStateRunningBuilder;
      35: aload_0
      36: getfield      #84                 // Field _visitables:Lio/dekorate/deps/kubernetes/api/builder/VisitableMap;
      39: ldc           #85                 // String running
      41: invokevirtual #91                 // Method io/dekorate/deps/kubernetes/api/builder/VisitableMap.get:(Ljava/lang/Object;)Ljava/util/List;
      44: aload_0
      45: getfield      #71                 // Field running:Lio/dekorate/deps/kubernetes/api/model/ContainerStateRunningBuilder;
      48: invokeinterface #103,  2          // InterfaceMethod java/util/List.add:(Ljava/lang/Object;)Z
      53: pop
      54: aload_0
      55: areturn

  public java.lang.Boolean hasRunning();
    Code:
       0: aload_0
       1: getfield      #71                 // Field running:Lio/dekorate/deps/kubernetes/api/model/ContainerStateRunningBuilder;
       4: ifnull        11
       7: iconst_1
       8: goto          12
      11: iconst_0
      12: invokestatic  #112                // Method java/lang/Boolean.valueOf:(Z)Ljava/lang/Boolean;
      15: areturn

  public A withNewRunning(java.lang.String);
    Code:
       0: aload_0
       1: new           #78                 // class io/dekorate/deps/kubernetes/api/model/ContainerStateRunning
       4: dup
       5: aload_1
       6: invokespecial #118                // Method io/dekorate/deps/kubernetes/api/model/ContainerStateRunning."<init>":(Ljava/lang/String;)V
       9: invokevirtual #50                 // Method withRunning:(Lio/dekorate/deps/kubernetes/api/model/ContainerStateRunning;)Lio/dekorate/deps/kubernetes/api/model/ContainerStateFluent;
      12: areturn

  public io.dekorate.deps.kubernetes.api.model.ContainerStateFluent$RunningNested<A> withNewRunning();
    Code:
       0: new           #16                 // class io/dekorate/deps/kubernetes/api/model/ContainerStateFluentImpl$RunningNestedImpl
       3: dup
       4: aload_0
       5: invokespecial #125                // Method io/dekorate/deps/kubernetes/api/model/ContainerStateFluentImpl$RunningNestedImpl."<init>":(Lio/dekorate/deps/kubernetes/api/model/ContainerStateFluentImpl;)V
       8: areturn

  public io.dekorate.deps.kubernetes.api.model.ContainerStateFluent$RunningNested<A> withNewRunningLike(io.dekorate.deps.kubernetes.api.model.ContainerStateRunning);
    Code:
       0: new           #16                 // class io/dekorate/deps/kubernetes/api/model/ContainerStateFluentImpl$RunningNestedImpl
       3: dup
       4: aload_0
       5: aload_1
       6: invokespecial #131                // Method io/dekorate/deps/kubernetes/api/model/ContainerStateFluentImpl$RunningNestedImpl."<init>":(Lio/dekorate/deps/kubernetes/api/model/ContainerStateFluentImpl;Lio/dekorate/deps/kubernetes/api/model/ContainerStateRunning;)V
       9: areturn

  public io.dekorate.deps.kubernetes.api.model.ContainerStateFluent$RunningNested<A> editRunning();
    Code:
       0: aload_0
       1: aload_0
       2: invokevirtual #134                // Method getRunning:()Lio/dekorate/deps/kubernetes/api/model/ContainerStateRunning;
       5: invokevirtual #136                // Method withNewRunningLike:(Lio/dekorate/deps/kubernetes/api/model/ContainerStateRunning;)Lio/dekorate/deps/kubernetes/api/model/ContainerStateFluent$RunningNested;
       8: areturn

  public io.dekorate.deps.kubernetes.api.model.ContainerStateFluent$RunningNested<A> editOrNewRunning();
    Code:
       0: aload_0
       1: aload_0
       2: invokevirtual #134                // Method getRunning:()Lio/dekorate/deps/kubernetes/api/model/ContainerStateRunning;
       5: ifnull        15
       8: aload_0
       9: invokevirtual #134                // Method getRunning:()Lio/dekorate/deps/kubernetes/api/model/ContainerStateRunning;
      12: goto          25
      15: new           #73                 // class io/dekorate/deps/kubernetes/api/model/ContainerStateRunningBuilder
      18: dup
      19: invokespecial #138                // Method io/dekorate/deps/kubernetes/api/model/ContainerStateRunningBuilder."<init>":()V
      22: invokevirtual #76                 // Method io/dekorate/deps/kubernetes/api/model/ContainerStateRunningBuilder.build:()Lio/dekorate/deps/kubernetes/api/model/ContainerStateRunning;
      25: invokevirtual #136                // Method withNewRunningLike:(Lio/dekorate/deps/kubernetes/api/model/ContainerStateRunning;)Lio/dekorate/deps/kubernetes/api/model/ContainerStateFluent$RunningNested;
      28: areturn

  public io.dekorate.deps.kubernetes.api.model.ContainerStateFluent$RunningNested<A> editOrNewRunningLike(io.dekorate.deps.kubernetes.api.model.ContainerStateRunning);
    Code:
       0: aload_0
       1: aload_0
       2: invokevirtual #134                // Method getRunning:()Lio/dekorate/deps/kubernetes/api/model/ContainerStateRunning;
       5: ifnull        15
       8: aload_0
       9: invokevirtual #134                // Method getRunning:()Lio/dekorate/deps/kubernetes/api/model/ContainerStateRunning;
      12: goto          16
      15: aload_1
      16: invokevirtual #136                // Method withNewRunningLike:(Lio/dekorate/deps/kubernetes/api/model/ContainerStateRunning;)Lio/dekorate/deps/kubernetes/api/model/ContainerStateFluent$RunningNested;
      19: areturn

  public io.dekorate.deps.kubernetes.api.model.ContainerStateTerminated getTerminated();
    Code:
       0: aload_0
       1: getfield      #141                // Field terminated:Lio/dekorate/deps/kubernetes/api/model/ContainerStateTerminatedBuilder;
       4: ifnull        17
       7: aload_0
       8: getfield      #141                // Field terminated:Lio/dekorate/deps/kubernetes/api/model/ContainerStateTerminatedBuilder;
      11: invokevirtual #145                // Method io/dekorate/deps/kubernetes/api/model/ContainerStateTerminatedBuilder.build:()Lio/dekorate/deps/kubernetes/api/model/ContainerStateTerminated;
      14: goto          18
      17: aconst_null
      18: areturn

  public io.dekorate.deps.kubernetes.api.model.ContainerStateTerminated buildTerminated();
    Code:
       0: aload_0
       1: getfield      #141                // Field terminated:Lio/dekorate/deps/kubernetes/api/model/ContainerStateTerminatedBuilder;
       4: ifnull        17
       7: aload_0
       8: getfield      #141                // Field terminated:Lio/dekorate/deps/kubernetes/api/model/ContainerStateTerminatedBuilder;
      11: invokevirtual #145                // Method io/dekorate/deps/kubernetes/api/model/ContainerStateTerminatedBuilder.build:()Lio/dekorate/deps/kubernetes/api/model/ContainerStateTerminated;
      14: goto          18
      17: aconst_null
      18: areturn

  public A withTerminated(io.dekorate.deps.kubernetes.api.model.ContainerStateTerminated);
    Code:
       0: aload_0
       1: getfield      #84                 // Field _visitables:Lio/dekorate/deps/kubernetes/api/builder/VisitableMap;
       4: ldc           #150                // String terminated
       6: invokevirtual #91                 // Method io/dekorate/deps/kubernetes/api/builder/VisitableMap.get:(Ljava/lang/Object;)Ljava/util/List;
       9: aload_0
      10: getfield      #141                // Field terminated:Lio/dekorate/deps/kubernetes/api/model/ContainerStateTerminatedBuilder;
      13: invokeinterface #97,  2           // InterfaceMethod java/util/List.remove:(Ljava/lang/Object;)Z
      18: pop
      19: aload_1
      20: ifnull        54
      23: aload_0
      24: new           #143                // class io/dekorate/deps/kubernetes/api/model/ContainerStateTerminatedBuilder
      27: dup
      28: aload_1
      29: invokespecial #153                // Method io/dekorate/deps/kubernetes/api/model/ContainerStateTerminatedBuilder."<init>":(Lio/dekorate/deps/kubernetes/api/model/ContainerStateTerminated;)V
      32: putfield      #141                // Field terminated:Lio/dekorate/deps/kubernetes/api/model/ContainerStateTerminatedBuilder;
      35: aload_0
      36: getfield      #84                 // Field _visitables:Lio/dekorate/deps/kubernetes/api/builder/VisitableMap;
      39: ldc           #150                // String terminated
      41: invokevirtual #91                 // Method io/dekorate/deps/kubernetes/api/builder/VisitableMap.get:(Ljava/lang/Object;)Ljava/util/List;
      44: aload_0
      45: getfield      #141                // Field terminated:Lio/dekorate/deps/kubernetes/api/model/ContainerStateTerminatedBuilder;
      48: invokeinterface #103,  2          // InterfaceMethod java/util/List.add:(Ljava/lang/Object;)Z
      53: pop
      54: aload_0
      55: areturn

  public java.lang.Boolean hasTerminated();
    Code:
       0: aload_0
       1: getfield      #141                // Field terminated:Lio/dekorate/deps/kubernetes/api/model/ContainerStateTerminatedBuilder;
       4: ifnull        11
       7: iconst_1
       8: goto          12
      11: iconst_0
      12: invokestatic  #112                // Method java/lang/Boolean.valueOf:(Z)Ljava/lang/Boolean;
      15: areturn

  public io.dekorate.deps.kubernetes.api.model.ContainerStateFluent$TerminatedNested<A> withNewTerminated();
    Code:
       0: new           #13                 // class io/dekorate/deps/kubernetes/api/model/ContainerStateFluentImpl$TerminatedNestedImpl
       3: dup
       4: aload_0
       5: invokespecial #159                // Method io/dekorate/deps/kubernetes/api/model/ContainerStateFluentImpl$TerminatedNestedImpl."<init>":(Lio/dekorate/deps/kubernetes/api/model/ContainerStateFluentImpl;)V
       8: areturn

  public io.dekorate.deps.kubernetes.api.model.ContainerStateFluent$TerminatedNested<A> withNewTerminatedLike(io.dekorate.deps.kubernetes.api.model.ContainerStateTerminated);
    Code:
       0: new           #13                 // class io/dekorate/deps/kubernetes/api/model/ContainerStateFluentImpl$TerminatedNestedImpl
       3: dup
       4: aload_0
       5: aload_1
       6: invokespecial #165                // Method io/dekorate/deps/kubernetes/api/model/ContainerStateFluentImpl$TerminatedNestedImpl."<init>":(Lio/dekorate/deps/kubernetes/api/model/ContainerStateFluentImpl;Lio/dekorate/deps/kubernetes/api/model/ContainerStateTerminated;)V
       9: areturn

  public io.dekorate.deps.kubernetes.api.model.ContainerStateFluent$TerminatedNested<A> editTerminated();
    Code:
       0: aload_0
       1: aload_0
       2: invokevirtual #167                // Method getTerminated:()Lio/dekorate/deps/kubernetes/api/model/ContainerStateTerminated;
       5: invokevirtual #169                // Method withNewTerminatedLike:(Lio/dekorate/deps/kubernetes/api/model/ContainerStateTerminated;)Lio/dekorate/deps/kubernetes/api/model/ContainerStateFluent$TerminatedNested;
       8: areturn

  public io.dekorate.deps.kubernetes.api.model.ContainerStateFluent$TerminatedNested<A> editOrNewTerminated();
    Code:
       0: aload_0
       1: aload_0
       2: invokevirtual #167                // Method getTerminated:()Lio/dekorate/deps/kubernetes/api/model/ContainerStateTerminated;
       5: ifnull        15
       8: aload_0
       9: invokevirtual #167                // Method getTerminated:()Lio/dekorate/deps/kubernetes/api/model/ContainerStateTerminated;
      12: goto          25
      15: new           #143                // class io/dekorate/deps/kubernetes/api/model/ContainerStateTerminatedBuilder
      18: dup
      19: invokespecial #171                // Method io/dekorate/deps/kubernetes/api/model/ContainerStateTerminatedBuilder."<init>":()V
      22: invokevirtual #145                // Method io/dekorate/deps/kubernetes/api/model/ContainerStateTerminatedBuilder.build:()Lio/dekorate/deps/kubernetes/api/model/ContainerStateTerminated;
      25: invokevirtual #169                // Method withNewTerminatedLike:(Lio/dekorate/deps/kubernetes/api/model/ContainerStateTerminated;)Lio/dekorate/deps/kubernetes/api/model/ContainerStateFluent$TerminatedNested;
      28: areturn

  public io.dekorate.deps.kubernetes.api.model.ContainerStateFluent$TerminatedNested<A> editOrNewTerminatedLike(io.dekorate.deps.kubernetes.api.model.ContainerStateTerminated);
    Code:
       0: aload_0
       1: aload_0
       2: invokevirtual #167                // Method getTerminated:()Lio/dekorate/deps/kubernetes/api/model/ContainerStateTerminated;
       5: ifnull        15
       8: aload_0
       9: invokevirtual #167                // Method getTerminated:()Lio/dekorate/deps/kubernetes/api/model/ContainerStateTerminated;
      12: goto          16
      15: aload_1
      16: invokevirtual #169                // Method withNewTerminatedLike:(Lio/dekorate/deps/kubernetes/api/model/ContainerStateTerminated;)Lio/dekorate/deps/kubernetes/api/model/ContainerStateFluent$TerminatedNested;
      19: areturn

  public io.dekorate.deps.kubernetes.api.model.ContainerStateWaiting getWaiting();
    Code:
       0: aload_0
       1: getfield      #174                // Field waiting:Lio/dekorate/deps/kubernetes/api/model/ContainerStateWaitingBuilder;
       4: ifnull        17
       7: aload_0
       8: getfield      #174                // Field waiting:Lio/dekorate/deps/kubernetes/api/model/ContainerStateWaitingBuilder;
      11: invokevirtual #178                // Method io/dekorate/deps/kubernetes/api/model/ContainerStateWaitingBuilder.build:()Lio/dekorate/deps/kubernetes/api/model/ContainerStateWaiting;
      14: goto          18
      17: aconst_null
      18: areturn

  public io.dekorate.deps.kubernetes.api.model.ContainerStateWaiting buildWaiting();
    Code:
       0: aload_0
       1: getfield      #174                // Field waiting:Lio/dekorate/deps/kubernetes/api/model/ContainerStateWaitingBuilder;
       4: ifnull        17
       7: aload_0
       8: getfield      #174                // Field waiting:Lio/dekorate/deps/kubernetes/api/model/ContainerStateWaitingBuilder;
      11: invokevirtual #178                // Method io/dekorate/deps/kubernetes/api/model/ContainerStateWaitingBuilder.build:()Lio/dekorate/deps/kubernetes/api/model/ContainerStateWaiting;
      14: goto          18
      17: aconst_null
      18: areturn

  public A withWaiting(io.dekorate.deps.kubernetes.api.model.ContainerStateWaiting);
    Code:
       0: aload_0
       1: getfield      #84                 // Field _visitables:Lio/dekorate/deps/kubernetes/api/builder/VisitableMap;
       4: ldc           #183                // String waiting
       6: invokevirtual #91                 // Method io/dekorate/deps/kubernetes/api/builder/VisitableMap.get:(Ljava/lang/Object;)Ljava/util/List;
       9: aload_0
      10: getfield      #174                // Field waiting:Lio/dekorate/deps/kubernetes/api/model/ContainerStateWaitingBuilder;
      13: invokeinterface #97,  2           // InterfaceMethod java/util/List.remove:(Ljava/lang/Object;)Z
      18: pop
      19: aload_1
      20: ifnull        54
      23: aload_0
      24: new           #176                // class io/dekorate/deps/kubernetes/api/model/ContainerStateWaitingBuilder
      27: dup
      28: aload_1
      29: invokespecial #186                // Method io/dekorate/deps/kubernetes/api/model/ContainerStateWaitingBuilder."<init>":(Lio/dekorate/deps/kubernetes/api/model/ContainerStateWaiting;)V
      32: putfield      #174                // Field waiting:Lio/dekorate/deps/kubernetes/api/model/ContainerStateWaitingBuilder;
      35: aload_0
      36: getfield      #84                 // Field _visitables:Lio/dekorate/deps/kubernetes/api/builder/VisitableMap;
      39: ldc           #183                // String waiting
      41: invokevirtual #91                 // Method io/dekorate/deps/kubernetes/api/builder/VisitableMap.get:(Ljava/lang/Object;)Ljava/util/List;
      44: aload_0
      45: getfield      #174                // Field waiting:Lio/dekorate/deps/kubernetes/api/model/ContainerStateWaitingBuilder;
      48: invokeinterface #103,  2          // InterfaceMethod java/util/List.add:(Ljava/lang/Object;)Z
      53: pop
      54: aload_0
      55: areturn

  public java.lang.Boolean hasWaiting();
    Code:
       0: aload_0
       1: getfield      #174                // Field waiting:Lio/dekorate/deps/kubernetes/api/model/ContainerStateWaitingBuilder;
       4: ifnull        11
       7: iconst_1
       8: goto          12
      11: iconst_0
      12: invokestatic  #112                // Method java/lang/Boolean.valueOf:(Z)Ljava/lang/Boolean;
      15: areturn

  public A withNewWaiting(java.lang.String, java.lang.String);
    Code:
       0: aload_0
       1: new           #180                // class io/dekorate/deps/kubernetes/api/model/ContainerStateWaiting
       4: dup
       5: aload_1
       6: aload_2
       7: invokespecial #194                // Method io/dekorate/deps/kubernetes/api/model/ContainerStateWaiting."<init>":(Ljava/lang/String;Ljava/lang/String;)V
      10: invokevirtual #66                 // Method withWaiting:(Lio/dekorate/deps/kubernetes/api/model/ContainerStateWaiting;)Lio/dekorate/deps/kubernetes/api/model/ContainerStateFluent;
      13: areturn

  public io.dekorate.deps.kubernetes.api.model.ContainerStateFluent$WaitingNested<A> withNewWaiting();
    Code:
       0: new           #10                 // class io/dekorate/deps/kubernetes/api/model/ContainerStateFluentImpl$WaitingNestedImpl
       3: dup
       4: aload_0
       5: invokespecial #199                // Method io/dekorate/deps/kubernetes/api/model/ContainerStateFluentImpl$WaitingNestedImpl."<init>":(Lio/dekorate/deps/kubernetes/api/model/ContainerStateFluentImpl;)V
       8: areturn

  public io.dekorate.deps.kubernetes.api.model.ContainerStateFluent$WaitingNested<A> withNewWaitingLike(io.dekorate.deps.kubernetes.api.model.ContainerStateWaiting);
    Code:
       0: new           #10                 // class io/dekorate/deps/kubernetes/api/model/ContainerStateFluentImpl$WaitingNestedImpl
       3: dup
       4: aload_0
       5: aload_1
       6: invokespecial #205                // Method io/dekorate/deps/kubernetes/api/model/ContainerStateFluentImpl$WaitingNestedImpl."<init>":(Lio/dekorate/deps/kubernetes/api/model/ContainerStateFluentImpl;Lio/dekorate/deps/kubernetes/api/model/ContainerStateWaiting;)V
       9: areturn

  public io.dekorate.deps.kubernetes.api.model.ContainerStateFluent$WaitingNested<A> editWaiting();
    Code:
       0: aload_0
       1: aload_0
       2: invokevirtual #207                // Method getWaiting:()Lio/dekorate/deps/kubernetes/api/model/ContainerStateWaiting;
       5: invokevirtual #209                // Method withNewWaitingLike:(Lio/dekorate/deps/kubernetes/api/model/ContainerStateWaiting;)Lio/dekorate/deps/kubernetes/api/model/ContainerStateFluent$WaitingNested;
       8: areturn

  public io.dekorate.deps.kubernetes.api.model.ContainerStateFluent$WaitingNested<A> editOrNewWaiting();
    Code:
       0: aload_0
       1: aload_0
       2: invokevirtual #207                // Method getWaiting:()Lio/dekorate/deps/kubernetes/api/model/ContainerStateWaiting;
       5: ifnull        15
       8: aload_0
       9: invokevirtual #207                // Method getWaiting:()Lio/dekorate/deps/kubernetes/api/model/ContainerStateWaiting;
      12: goto          25
      15: new           #176                // class io/dekorate/deps/kubernetes/api/model/ContainerStateWaitingBuilder
      18: dup
      19: invokespecial #211                // Method io/dekorate/deps/kubernetes/api/model/ContainerStateWaitingBuilder."<init>":()V
      22: invokevirtual #178                // Method io/dekorate/deps/kubernetes/api/model/ContainerStateWaitingBuilder.build:()Lio/dekorate/deps/kubernetes/api/model/ContainerStateWaiting;
      25: invokevirtual #209                // Method withNewWaitingLike:(Lio/dekorate/deps/kubernetes/api/model/ContainerStateWaiting;)Lio/dekorate/deps/kubernetes/api/model/ContainerStateFluent$WaitingNested;
      28: areturn

  public io.dekorate.deps.kubernetes.api.model.ContainerStateFluent$WaitingNested<A> editOrNewWaitingLike(io.dekorate.deps.kubernetes.api.model.ContainerStateWaiting);
    Code:
       0: aload_0
       1: aload_0
       2: invokevirtual #207                // Method getWaiting:()Lio/dekorate/deps/kubernetes/api/model/ContainerStateWaiting;
       5: ifnull        15
       8: aload_0
       9: invokevirtual #207                // Method getWaiting:()Lio/dekorate/deps/kubernetes/api/model/ContainerStateWaiting;
      12: goto          16
      15: aload_1
      16: invokevirtual #209                // Method withNewWaitingLike:(Lio/dekorate/deps/kubernetes/api/model/ContainerStateWaiting;)Lio/dekorate/deps/kubernetes/api/model/ContainerStateFluent$WaitingNested;
      19: areturn

  public boolean equals(java.lang.Object);
    Code:
       0: aload_0
       1: aload_1
       2: if_acmpne     7
       5: iconst_1
       6: ireturn
       7: aload_1
       8: ifnull        22
      11: aload_0
      12: invokevirtual #219                // Method java/lang/Object.getClass:()Ljava/lang/Class;
      15: aload_1
      16: invokevirtual #219                // Method java/lang/Object.getClass:()Ljava/lang/Class;
      19: if_acmpeq     24
      22: iconst_0
      23: ireturn
      24: aload_1
      25: checkcast     #2                  // class io/dekorate/deps/kubernetes/api/model/ContainerStateFluentImpl
      28: astore_2
      29: aload_0
      30: getfield      #71                 // Field running:Lio/dekorate/deps/kubernetes/api/model/ContainerStateRunningBuilder;
      33: ifnull        53
      36: aload_0
      37: getfield      #71                 // Field running:Lio/dekorate/deps/kubernetes/api/model/ContainerStateRunningBuilder;
      40: aload_2
      41: getfield      #71                 // Field running:Lio/dekorate/deps/kubernetes/api/model/ContainerStateRunningBuilder;
      44: invokevirtual #221                // Method io/dekorate/deps/kubernetes/api/model/ContainerStateRunningBuilder.equals:(Ljava/lang/Object;)Z
      47: ifne          62
      50: goto          60
      53: aload_2
      54: getfield      #71                 // Field running:Lio/dekorate/deps/kubernetes/api/model/ContainerStateRunningBuilder;
      57: ifnull        62
      60: iconst_0
      61: ireturn
      62: aload_0
      63: getfield      #141                // Field terminated:Lio/dekorate/deps/kubernetes/api/model/ContainerStateTerminatedBuilder;
      66: ifnull        86
      69: aload_0
      70: getfield      #141                // Field terminated:Lio/dekorate/deps/kubernetes/api/model/ContainerStateTerminatedBuilder;
      73: aload_2
      74: getfield      #141                // Field terminated:Lio/dekorate/deps/kubernetes/api/model/ContainerStateTerminatedBuilder;
      77: invokevirtual #222                // Method io/dekorate/deps/kubernetes/api/model/ContainerStateTerminatedBuilder.equals:(Ljava/lang/Object;)Z
      80: ifne          95
      83: goto          93
      86: aload_2
      87: getfield      #141                // Field terminated:Lio/dekorate/deps/kubernetes/api/model/ContainerStateTerminatedBuilder;
      90: ifnull        95
      93: iconst_0
      94: ireturn
      95: aload_0
      96: getfield      #174                // Field waiting:Lio/dekorate/deps/kubernetes/api/model/ContainerStateWaitingBuilder;
      99: ifnull        119
     102: aload_0
     103: getfield      #174                // Field waiting:Lio/dekorate/deps/kubernetes/api/model/ContainerStateWaitingBuilder;
     106: aload_2
     107: getfield      #174                // Field waiting:Lio/dekorate/deps/kubernetes/api/model/ContainerStateWaitingBuilder;
     110: invokevirtual #223                // Method io/dekorate/deps/kubernetes/api/model/ContainerStateWaitingBuilder.equals:(Ljava/lang/Object;)Z
     113: ifne          128
     116: goto          126
     119: aload_2
     120: getfield      #174                // Field waiting:Lio/dekorate/deps/kubernetes/api/model/ContainerStateWaitingBuilder;
     123: ifnull        128
     126: iconst_0
     127: ireturn
     128: iconst_1
     129: ireturn
}
