Compiled from "CSIPersistentVolumeSourceFluentImpl.java"
public class io.dekorate.deps.kubernetes.api.model.CSIPersistentVolumeSourceFluentImpl<A extends io.dekorate.deps.kubernetes.api.model.CSIPersistentVolumeSourceFluent<A>> extends io.dekorate.deps.kubernetes.api.builder.BaseFluent<A> implements io.dekorate.deps.kubernetes.api.model.CSIPersistentVolumeSourceFluent<A> {
  private io.dekorate.deps.kubernetes.api.model.SecretReferenceBuilder controllerExpandSecretRef;

  private io.dekorate.deps.kubernetes.api.model.SecretReferenceBuilder controllerPublishSecretRef;

  private java.lang.String driver;

  private java.lang.String fsType;

  private io.dekorate.deps.kubernetes.api.model.SecretReferenceBuilder nodePublishSecretRef;

  private io.dekorate.deps.kubernetes.api.model.SecretReferenceBuilder nodeStageSecretRef;

  private java.lang.Boolean readOnly;

  private java.util.Map<java.lang.String, java.lang.String> volumeAttributes;

  private java.lang.String volumeHandle;

  public io.dekorate.deps.kubernetes.api.model.CSIPersistentVolumeSourceFluentImpl();
    Code:
       0: aload_0
       1: invokespecial #50                 // Method io/dekorate/deps/kubernetes/api/builder/BaseFluent."<init>":()V
       4: return

  public io.dekorate.deps.kubernetes.api.model.CSIPersistentVolumeSourceFluentImpl(io.dekorate.deps.kubernetes.api.model.CSIPersistentVolumeSource);
    Code:
       0: aload_0
       1: invokespecial #50                 // Method io/dekorate/deps/kubernetes/api/builder/BaseFluent."<init>":()V
       4: aload_0
       5: aload_1
       6: invokevirtual #60                 // Method io/dekorate/deps/kubernetes/api/model/CSIPersistentVolumeSource.getControllerExpandSecretRef:()Lio/dekorate/deps/kubernetes/api/model/SecretReference;
       9: invokevirtual #64                 // Method withControllerExpandSecretRef:(Lio/dekorate/deps/kubernetes/api/model/SecretReference;)Lio/dekorate/deps/kubernetes/api/model/CSIPersistentVolumeSourceFluent;
      12: pop
      13: aload_0
      14: aload_1
      15: invokevirtual #67                 // Method io/dekorate/deps/kubernetes/api/model/CSIPersistentVolumeSource.getControllerPublishSecretRef:()Lio/dekorate/deps/kubernetes/api/model/SecretReference;
      18: invokevirtual #70                 // Method withControllerPublishSecretRef:(Lio/dekorate/deps/kubernetes/api/model/SecretReference;)Lio/dekorate/deps/kubernetes/api/model/CSIPersistentVolumeSourceFluent;
      21: pop
      22: aload_0
      23: aload_1
      24: invokevirtual #74                 // Method io/dekorate/deps/kubernetes/api/model/CSIPersistentVolumeSource.getDriver:()Ljava/lang/String;
      27: invokevirtual #78                 // Method withDriver:(Ljava/lang/String;)Lio/dekorate/deps/kubernetes/api/model/CSIPersistentVolumeSourceFluent;
      30: pop
      31: aload_0
      32: aload_1
      33: invokevirtual #81                 // Method io/dekorate/deps/kubernetes/api/model/CSIPersistentVolumeSource.getFsType:()Ljava/lang/String;
      36: invokevirtual #84                 // Method withFsType:(Ljava/lang/String;)Lio/dekorate/deps/kubernetes/api/model/CSIPersistentVolumeSourceFluent;
      39: pop
      40: aload_0
      41: aload_1
      42: invokevirtual #87                 // Method io/dekorate/deps/kubernetes/api/model/CSIPersistentVolumeSource.getNodePublishSecretRef:()Lio/dekorate/deps/kubernetes/api/model/SecretReference;
      45: invokevirtual #90                 // Method withNodePublishSecretRef:(Lio/dekorate/deps/kubernetes/api/model/SecretReference;)Lio/dekorate/deps/kubernetes/api/model/CSIPersistentVolumeSourceFluent;
      48: pop
      49: aload_0
      50: aload_1
      51: invokevirtual #93                 // Method io/dekorate/deps/kubernetes/api/model/CSIPersistentVolumeSource.getNodeStageSecretRef:()Lio/dekorate/deps/kubernetes/api/model/SecretReference;
      54: invokevirtual #96                 // Method withNodeStageSecretRef:(Lio/dekorate/deps/kubernetes/api/model/SecretReference;)Lio/dekorate/deps/kubernetes/api/model/CSIPersistentVolumeSourceFluent;
      57: pop
      58: aload_0
      59: aload_1
      60: invokevirtual #100                // Method io/dekorate/deps/kubernetes/api/model/CSIPersistentVolumeSource.getReadOnly:()Ljava/lang/Boolean;
      63: invokevirtual #104                // Method withReadOnly:(Ljava/lang/Boolean;)Lio/dekorate/deps/kubernetes/api/model/CSIPersistentVolumeSourceFluent;
      66: pop
      67: aload_0
      68: aload_1
      69: invokevirtual #108                // Method io/dekorate/deps/kubernetes/api/model/CSIPersistentVolumeSource.getVolumeAttributes:()Ljava/util/Map;
      72: invokevirtual #112                // Method withVolumeAttributes:(Ljava/util/Map;)Lio/dekorate/deps/kubernetes/api/model/CSIPersistentVolumeSourceFluent;
      75: pop
      76: aload_0
      77: aload_1
      78: invokevirtual #115                // Method io/dekorate/deps/kubernetes/api/model/CSIPersistentVolumeSource.getVolumeHandle:()Ljava/lang/String;
      81: invokevirtual #118                // Method withVolumeHandle:(Ljava/lang/String;)Lio/dekorate/deps/kubernetes/api/model/CSIPersistentVolumeSourceFluent;
      84: pop
      85: return

  public io.dekorate.deps.kubernetes.api.model.SecretReference getControllerExpandSecretRef();
    Code:
       0: aload_0
       1: getfield      #123                // Field controllerExpandSecretRef:Lio/dekorate/deps/kubernetes/api/model/SecretReferenceBuilder;
       4: ifnull        17
       7: aload_0
       8: getfield      #123                // Field controllerExpandSecretRef:Lio/dekorate/deps/kubernetes/api/model/SecretReferenceBuilder;
      11: invokevirtual #128                // Method io/dekorate/deps/kubernetes/api/model/SecretReferenceBuilder.build:()Lio/dekorate/deps/kubernetes/api/model/SecretReference;
      14: goto          18
      17: aconst_null
      18: areturn

  public io.dekorate.deps.kubernetes.api.model.SecretReference buildControllerExpandSecretRef();
    Code:
       0: aload_0
       1: getfield      #123                // Field controllerExpandSecretRef:Lio/dekorate/deps/kubernetes/api/model/SecretReferenceBuilder;
       4: ifnull        17
       7: aload_0
       8: getfield      #123                // Field controllerExpandSecretRef:Lio/dekorate/deps/kubernetes/api/model/SecretReferenceBuilder;
      11: invokevirtual #128                // Method io/dekorate/deps/kubernetes/api/model/SecretReferenceBuilder.build:()Lio/dekorate/deps/kubernetes/api/model/SecretReference;
      14: goto          18
      17: aconst_null
      18: areturn

  public A withControllerExpandSecretRef(io.dekorate.deps.kubernetes.api.model.SecretReference);
    Code:
       0: aload_0
       1: getfield      #136                // Field _visitables:Lio/dekorate/deps/kubernetes/api/builder/VisitableMap;
       4: ldc           #137                // String controllerExpandSecretRef
       6: invokevirtual #143                // Method io/dekorate/deps/kubernetes/api/builder/VisitableMap.get:(Ljava/lang/Object;)Ljava/util/List;
       9: aload_0
      10: getfield      #123                // Field controllerExpandSecretRef:Lio/dekorate/deps/kubernetes/api/model/SecretReferenceBuilder;
      13: invokeinterface #149,  2          // InterfaceMethod java/util/List.remove:(Ljava/lang/Object;)Z
      18: pop
      19: aload_1
      20: ifnull        54
      23: aload_0
      24: new           #125                // class io/dekorate/deps/kubernetes/api/model/SecretReferenceBuilder
      27: dup
      28: aload_1
      29: invokespecial #152                // Method io/dekorate/deps/kubernetes/api/model/SecretReferenceBuilder."<init>":(Lio/dekorate/deps/kubernetes/api/model/SecretReference;)V
      32: putfield      #123                // Field controllerExpandSecretRef:Lio/dekorate/deps/kubernetes/api/model/SecretReferenceBuilder;
      35: aload_0
      36: getfield      #136                // Field _visitables:Lio/dekorate/deps/kubernetes/api/builder/VisitableMap;
      39: ldc           #137                // String controllerExpandSecretRef
      41: invokevirtual #143                // Method io/dekorate/deps/kubernetes/api/builder/VisitableMap.get:(Ljava/lang/Object;)Ljava/util/List;
      44: aload_0
      45: getfield      #123                // Field controllerExpandSecretRef:Lio/dekorate/deps/kubernetes/api/model/SecretReferenceBuilder;
      48: invokeinterface #155,  2          // InterfaceMethod java/util/List.add:(Ljava/lang/Object;)Z
      53: pop
      54: aload_0
      55: areturn

  public java.lang.Boolean hasControllerExpandSecretRef();
    Code:
       0: aload_0
       1: getfield      #123                // Field controllerExpandSecretRef:Lio/dekorate/deps/kubernetes/api/model/SecretReferenceBuilder;
       4: ifnull        11
       7: iconst_1
       8: goto          12
      11: iconst_0
      12: invokestatic  #163                // Method java/lang/Boolean.valueOf:(Z)Ljava/lang/Boolean;
      15: areturn

  public A withNewControllerExpandSecretRef(java.lang.String, java.lang.String);
    Code:
       0: aload_0
       1: new           #130                // class io/dekorate/deps/kubernetes/api/model/SecretReference
       4: dup
       5: aload_1
       6: aload_2
       7: invokespecial #169                // Method io/dekorate/deps/kubernetes/api/model/SecretReference."<init>":(Ljava/lang/String;Ljava/lang/String;)V
      10: invokevirtual #64                 // Method withControllerExpandSecretRef:(Lio/dekorate/deps/kubernetes/api/model/SecretReference;)Lio/dekorate/deps/kubernetes/api/model/CSIPersistentVolumeSourceFluent;
      13: areturn

  public io.dekorate.deps.kubernetes.api.model.CSIPersistentVolumeSourceFluent$ControllerExpandSecretRefNested<A> withNewControllerExpandSecretRef();
    Code:
       0: new           #19                 // class io/dekorate/deps/kubernetes/api/model/CSIPersistentVolumeSourceFluentImpl$ControllerExpandSecretRefNestedImpl
       3: dup
       4: aload_0
       5: invokespecial #176                // Method io/dekorate/deps/kubernetes/api/model/CSIPersistentVolumeSourceFluentImpl$ControllerExpandSecretRefNestedImpl."<init>":(Lio/dekorate/deps/kubernetes/api/model/CSIPersistentVolumeSourceFluentImpl;)V
       8: areturn

  public io.dekorate.deps.kubernetes.api.model.CSIPersistentVolumeSourceFluent$ControllerExpandSecretRefNested<A> withNewControllerExpandSecretRefLike(io.dekorate.deps.kubernetes.api.model.SecretReference);
    Code:
       0: new           #19                 // class io/dekorate/deps/kubernetes/api/model/CSIPersistentVolumeSourceFluentImpl$ControllerExpandSecretRefNestedImpl
       3: dup
       4: aload_0
       5: aload_1
       6: invokespecial #182                // Method io/dekorate/deps/kubernetes/api/model/CSIPersistentVolumeSourceFluentImpl$ControllerExpandSecretRefNestedImpl."<init>":(Lio/dekorate/deps/kubernetes/api/model/CSIPersistentVolumeSourceFluentImpl;Lio/dekorate/deps/kubernetes/api/model/SecretReference;)V
       9: areturn

  public io.dekorate.deps.kubernetes.api.model.CSIPersistentVolumeSourceFluent$ControllerExpandSecretRefNested<A> editControllerExpandSecretRef();
    Code:
       0: aload_0
       1: aload_0
       2: invokevirtual #185                // Method getControllerExpandSecretRef:()Lio/dekorate/deps/kubernetes/api/model/SecretReference;
       5: invokevirtual #187                // Method withNewControllerExpandSecretRefLike:(Lio/dekorate/deps/kubernetes/api/model/SecretReference;)Lio/dekorate/deps/kubernetes/api/model/CSIPersistentVolumeSourceFluent$ControllerExpandSecretRefNested;
       8: areturn

  public io.dekorate.deps.kubernetes.api.model.CSIPersistentVolumeSourceFluent$ControllerExpandSecretRefNested<A> editOrNewControllerExpandSecretRef();
    Code:
       0: aload_0
       1: aload_0
       2: invokevirtual #185                // Method getControllerExpandSecretRef:()Lio/dekorate/deps/kubernetes/api/model/SecretReference;
       5: ifnull        15
       8: aload_0
       9: invokevirtual #185                // Method getControllerExpandSecretRef:()Lio/dekorate/deps/kubernetes/api/model/SecretReference;
      12: goto          25
      15: new           #125                // class io/dekorate/deps/kubernetes/api/model/SecretReferenceBuilder
      18: dup
      19: invokespecial #189                // Method io/dekorate/deps/kubernetes/api/model/SecretReferenceBuilder."<init>":()V
      22: invokevirtual #128                // Method io/dekorate/deps/kubernetes/api/model/SecretReferenceBuilder.build:()Lio/dekorate/deps/kubernetes/api/model/SecretReference;
      25: invokevirtual #187                // Method withNewControllerExpandSecretRefLike:(Lio/dekorate/deps/kubernetes/api/model/SecretReference;)Lio/dekorate/deps/kubernetes/api/model/CSIPersistentVolumeSourceFluent$ControllerExpandSecretRefNested;
      28: areturn

  public io.dekorate.deps.kubernetes.api.model.CSIPersistentVolumeSourceFluent$ControllerExpandSecretRefNested<A> editOrNewControllerExpandSecretRefLike(io.dekorate.deps.kubernetes.api.model.SecretReference);
    Code:
       0: aload_0
       1: aload_0
       2: invokevirtual #185                // Method getControllerExpandSecretRef:()Lio/dekorate/deps/kubernetes/api/model/SecretReference;
       5: ifnull        15
       8: aload_0
       9: invokevirtual #185                // Method getControllerExpandSecretRef:()Lio/dekorate/deps/kubernetes/api/model/SecretReference;
      12: goto          16
      15: aload_1
      16: invokevirtual #187                // Method withNewControllerExpandSecretRefLike:(Lio/dekorate/deps/kubernetes/api/model/SecretReference;)Lio/dekorate/deps/kubernetes/api/model/CSIPersistentVolumeSourceFluent$ControllerExpandSecretRefNested;
      19: areturn

  public io.dekorate.deps.kubernetes.api.model.SecretReference getControllerPublishSecretRef();
    Code:
       0: aload_0
       1: getfield      #192                // Field controllerPublishSecretRef:Lio/dekorate/deps/kubernetes/api/model/SecretReferenceBuilder;
       4: ifnull        17
       7: aload_0
       8: getfield      #192                // Field controllerPublishSecretRef:Lio/dekorate/deps/kubernetes/api/model/SecretReferenceBuilder;
      11: invokevirtual #128                // Method io/dekorate/deps/kubernetes/api/model/SecretReferenceBuilder.build:()Lio/dekorate/deps/kubernetes/api/model/SecretReference;
      14: goto          18
      17: aconst_null
      18: areturn

  public io.dekorate.deps.kubernetes.api.model.SecretReference buildControllerPublishSecretRef();
    Code:
       0: aload_0
       1: getfield      #192                // Field controllerPublishSecretRef:Lio/dekorate/deps/kubernetes/api/model/SecretReferenceBuilder;
       4: ifnull        17
       7: aload_0
       8: getfield      #192                // Field controllerPublishSecretRef:Lio/dekorate/deps/kubernetes/api/model/SecretReferenceBuilder;
      11: invokevirtual #128                // Method io/dekorate/deps/kubernetes/api/model/SecretReferenceBuilder.build:()Lio/dekorate/deps/kubernetes/api/model/SecretReference;
      14: goto          18
      17: aconst_null
      18: areturn

  public A withControllerPublishSecretRef(io.dekorate.deps.kubernetes.api.model.SecretReference);
    Code:
       0: aload_0
       1: getfield      #136                // Field _visitables:Lio/dekorate/deps/kubernetes/api/builder/VisitableMap;
       4: ldc           #194                // String controllerPublishSecretRef
       6: invokevirtual #143                // Method io/dekorate/deps/kubernetes/api/builder/VisitableMap.get:(Ljava/lang/Object;)Ljava/util/List;
       9: aload_0
      10: getfield      #192                // Field controllerPublishSecretRef:Lio/dekorate/deps/kubernetes/api/model/SecretReferenceBuilder;
      13: invokeinterface #149,  2          // InterfaceMethod java/util/List.remove:(Ljava/lang/Object;)Z
      18: pop
      19: aload_1
      20: ifnull        54
      23: aload_0
      24: new           #125                // class io/dekorate/deps/kubernetes/api/model/SecretReferenceBuilder
      27: dup
      28: aload_1
      29: invokespecial #152                // Method io/dekorate/deps/kubernetes/api/model/SecretReferenceBuilder."<init>":(Lio/dekorate/deps/kubernetes/api/model/SecretReference;)V
      32: putfield      #192                // Field controllerPublishSecretRef:Lio/dekorate/deps/kubernetes/api/model/SecretReferenceBuilder;
      35: aload_0
      36: getfield      #136                // Field _visitables:Lio/dekorate/deps/kubernetes/api/builder/VisitableMap;
      39: ldc           #194                // String controllerPublishSecretRef
      41: invokevirtual #143                // Method io/dekorate/deps/kubernetes/api/builder/VisitableMap.get:(Ljava/lang/Object;)Ljava/util/List;
      44: aload_0
      45: getfield      #192                // Field controllerPublishSecretRef:Lio/dekorate/deps/kubernetes/api/model/SecretReferenceBuilder;
      48: invokeinterface #155,  2          // InterfaceMethod java/util/List.add:(Ljava/lang/Object;)Z
      53: pop
      54: aload_0
      55: areturn

  public java.lang.Boolean hasControllerPublishSecretRef();
    Code:
       0: aload_0
       1: getfield      #192                // Field controllerPublishSecretRef:Lio/dekorate/deps/kubernetes/api/model/SecretReferenceBuilder;
       4: ifnull        11
       7: iconst_1
       8: goto          12
      11: iconst_0
      12: invokestatic  #163                // Method java/lang/Boolean.valueOf:(Z)Ljava/lang/Boolean;
      15: areturn

  public A withNewControllerPublishSecretRef(java.lang.String, java.lang.String);
    Code:
       0: aload_0
       1: new           #130                // class io/dekorate/deps/kubernetes/api/model/SecretReference
       4: dup
       5: aload_1
       6: aload_2
       7: invokespecial #169                // Method io/dekorate/deps/kubernetes/api/model/SecretReference."<init>":(Ljava/lang/String;Ljava/lang/String;)V
      10: invokevirtual #70                 // Method withControllerPublishSecretRef:(Lio/dekorate/deps/kubernetes/api/model/SecretReference;)Lio/dekorate/deps/kubernetes/api/model/CSIPersistentVolumeSourceFluent;
      13: areturn

  public io.dekorate.deps.kubernetes.api.model.CSIPersistentVolumeSourceFluent$ControllerPublishSecretRefNested<A> withNewControllerPublishSecretRef();
    Code:
       0: new           #16                 // class io/dekorate/deps/kubernetes/api/model/CSIPersistentVolumeSourceFluentImpl$ControllerPublishSecretRefNestedImpl
       3: dup
       4: aload_0
       5: invokespecial #199                // Method io/dekorate/deps/kubernetes/api/model/CSIPersistentVolumeSourceFluentImpl$ControllerPublishSecretRefNestedImpl."<init>":(Lio/dekorate/deps/kubernetes/api/model/CSIPersistentVolumeSourceFluentImpl;)V
       8: areturn

  public io.dekorate.deps.kubernetes.api.model.CSIPersistentVolumeSourceFluent$ControllerPublishSecretRefNested<A> withNewControllerPublishSecretRefLike(io.dekorate.deps.kubernetes.api.model.SecretReference);
    Code:
       0: new           #16                 // class io/dekorate/deps/kubernetes/api/model/CSIPersistentVolumeSourceFluentImpl$ControllerPublishSecretRefNestedImpl
       3: dup
       4: aload_0
       5: aload_1
       6: invokespecial #203                // Method io/dekorate/deps/kubernetes/api/model/CSIPersistentVolumeSourceFluentImpl$ControllerPublishSecretRefNestedImpl."<init>":(Lio/dekorate/deps/kubernetes/api/model/CSIPersistentVolumeSourceFluentImpl;Lio/dekorate/deps/kubernetes/api/model/SecretReference;)V
       9: areturn

  public io.dekorate.deps.kubernetes.api.model.CSIPersistentVolumeSourceFluent$ControllerPublishSecretRefNested<A> editControllerPublishSecretRef();
    Code:
       0: aload_0
       1: aload_0
       2: invokevirtual #205                // Method getControllerPublishSecretRef:()Lio/dekorate/deps/kubernetes/api/model/SecretReference;
       5: invokevirtual #207                // Method withNewControllerPublishSecretRefLike:(Lio/dekorate/deps/kubernetes/api/model/SecretReference;)Lio/dekorate/deps/kubernetes/api/model/CSIPersistentVolumeSourceFluent$ControllerPublishSecretRefNested;
       8: areturn

  public io.dekorate.deps.kubernetes.api.model.CSIPersistentVolumeSourceFluent$ControllerPublishSecretRefNested<A> editOrNewControllerPublishSecretRef();
    Code:
       0: aload_0
       1: aload_0
       2: invokevirtual #205                // Method getControllerPublishSecretRef:()Lio/dekorate/deps/kubernetes/api/model/SecretReference;
       5: ifnull        15
       8: aload_0
       9: invokevirtual #205                // Method getControllerPublishSecretRef:()Lio/dekorate/deps/kubernetes/api/model/SecretReference;
      12: goto          25
      15: new           #125                // class io/dekorate/deps/kubernetes/api/model/SecretReferenceBuilder
      18: dup
      19: invokespecial #189                // Method io/dekorate/deps/kubernetes/api/model/SecretReferenceBuilder."<init>":()V
      22: invokevirtual #128                // Method io/dekorate/deps/kubernetes/api/model/SecretReferenceBuilder.build:()Lio/dekorate/deps/kubernetes/api/model/SecretReference;
      25: invokevirtual #207                // Method withNewControllerPublishSecretRefLike:(Lio/dekorate/deps/kubernetes/api/model/SecretReference;)Lio/dekorate/deps/kubernetes/api/model/CSIPersistentVolumeSourceFluent$ControllerPublishSecretRefNested;
      28: areturn

  public io.dekorate.deps.kubernetes.api.model.CSIPersistentVolumeSourceFluent$ControllerPublishSecretRefNested<A> editOrNewControllerPublishSecretRefLike(io.dekorate.deps.kubernetes.api.model.SecretReference);
    Code:
       0: aload_0
       1: aload_0
       2: invokevirtual #205                // Method getControllerPublishSecretRef:()Lio/dekorate/deps/kubernetes/api/model/SecretReference;
       5: ifnull        15
       8: aload_0
       9: invokevirtual #205                // Method getControllerPublishSecretRef:()Lio/dekorate/deps/kubernetes/api/model/SecretReference;
      12: goto          16
      15: aload_1
      16: invokevirtual #207                // Method withNewControllerPublishSecretRefLike:(Lio/dekorate/deps/kubernetes/api/model/SecretReference;)Lio/dekorate/deps/kubernetes/api/model/CSIPersistentVolumeSourceFluent$ControllerPublishSecretRefNested;
      19: areturn

  public java.lang.String getDriver();
    Code:
       0: aload_0
       1: getfield      #211                // Field driver:Ljava/lang/String;
       4: areturn

  public A withDriver(java.lang.String);
    Code:
       0: aload_0
       1: aload_1
       2: putfield      #211                // Field driver:Ljava/lang/String;
       5: aload_0
       6: areturn

  public java.lang.Boolean hasDriver();
    Code:
       0: aload_0
       1: getfield      #211                // Field driver:Ljava/lang/String;
       4: ifnull        11
       7: iconst_1
       8: goto          12
      11: iconst_0
      12: invokestatic  #163                // Method java/lang/Boolean.valueOf:(Z)Ljava/lang/Boolean;
      15: areturn

  public A withNewDriver(java.lang.String);
    Code:
       0: aload_0
       1: new           #216                // class java/lang/String
       4: dup
       5: aload_1
       6: invokespecial #219                // Method java/lang/String."<init>":(Ljava/lang/String;)V
       9: invokevirtual #78                 // Method withDriver:(Ljava/lang/String;)Lio/dekorate/deps/kubernetes/api/model/CSIPersistentVolumeSourceFluent;
      12: areturn

  public A withNewDriver(java.lang.StringBuilder);
    Code:
       0: aload_0
       1: new           #216                // class java/lang/String
       4: dup
       5: aload_1
       6: invokespecial #225                // Method java/lang/String."<init>":(Ljava/lang/StringBuilder;)V
       9: invokevirtual #78                 // Method withDriver:(Ljava/lang/String;)Lio/dekorate/deps/kubernetes/api/model/CSIPersistentVolumeSourceFluent;
      12: areturn

  public A withNewDriver(java.lang.StringBuffer);
    Code:
       0: aload_0
       1: new           #216                // class java/lang/String
       4: dup
       5: aload_1
       6: invokespecial #231                // Method java/lang/String."<init>":(Ljava/lang/StringBuffer;)V
       9: invokevirtual #78                 // Method withDriver:(Ljava/lang/String;)Lio/dekorate/deps/kubernetes/api/model/CSIPersistentVolumeSourceFluent;
      12: areturn

  public java.lang.String getFsType();
    Code:
       0: aload_0
       1: getfield      #234                // Field fsType:Ljava/lang/String;
       4: areturn

  public A withFsType(java.lang.String);
    Code:
       0: aload_0
       1: aload_1
       2: putfield      #234                // Field fsType:Ljava/lang/String;
       5: aload_0
       6: areturn

  public java.lang.Boolean hasFsType();
    Code:
       0: aload_0
       1: getfield      #234                // Field fsType:Ljava/lang/String;
       4: ifnull        11
       7: iconst_1
       8: goto          12
      11: iconst_0
      12: invokestatic  #163                // Method java/lang/Boolean.valueOf:(Z)Ljava/lang/Boolean;
      15: areturn

  public A withNewFsType(java.lang.String);
    Code:
       0: aload_0
       1: new           #216                // class java/lang/String
       4: dup
       5: aload_1
       6: invokespecial #219                // Method java/lang/String."<init>":(Ljava/lang/String;)V
       9: invokevirtual #84                 // Method withFsType:(Ljava/lang/String;)Lio/dekorate/deps/kubernetes/api/model/CSIPersistentVolumeSourceFluent;
      12: areturn

  public A withNewFsType(java.lang.StringBuilder);
    Code:
       0: aload_0
       1: new           #216                // class java/lang/String
       4: dup
       5: aload_1
       6: invokespecial #225                // Method java/lang/String."<init>":(Ljava/lang/StringBuilder;)V
       9: invokevirtual #84                 // Method withFsType:(Ljava/lang/String;)Lio/dekorate/deps/kubernetes/api/model/CSIPersistentVolumeSourceFluent;
      12: areturn

  public A withNewFsType(java.lang.StringBuffer);
    Code:
       0: aload_0
       1: new           #216                // class java/lang/String
       4: dup
       5: aload_1
       6: invokespecial #231                // Method java/lang/String."<init>":(Ljava/lang/StringBuffer;)V
       9: invokevirtual #84                 // Method withFsType:(Ljava/lang/String;)Lio/dekorate/deps/kubernetes/api/model/CSIPersistentVolumeSourceFluent;
      12: areturn

  public io.dekorate.deps.kubernetes.api.model.SecretReference getNodePublishSecretRef();
    Code:
       0: aload_0
       1: getfield      #238                // Field nodePublishSecretRef:Lio/dekorate/deps/kubernetes/api/model/SecretReferenceBuilder;
       4: ifnull        17
       7: aload_0
       8: getfield      #238                // Field nodePublishSecretRef:Lio/dekorate/deps/kubernetes/api/model/SecretReferenceBuilder;
      11: invokevirtual #128                // Method io/dekorate/deps/kubernetes/api/model/SecretReferenceBuilder.build:()Lio/dekorate/deps/kubernetes/api/model/SecretReference;
      14: goto          18
      17: aconst_null
      18: areturn

  public io.dekorate.deps.kubernetes.api.model.SecretReference buildNodePublishSecretRef();
    Code:
       0: aload_0
       1: getfield      #238                // Field nodePublishSecretRef:Lio/dekorate/deps/kubernetes/api/model/SecretReferenceBuilder;
       4: ifnull        17
       7: aload_0
       8: getfield      #238                // Field nodePublishSecretRef:Lio/dekorate/deps/kubernetes/api/model/SecretReferenceBuilder;
      11: invokevirtual #128                // Method io/dekorate/deps/kubernetes/api/model/SecretReferenceBuilder.build:()Lio/dekorate/deps/kubernetes/api/model/SecretReference;
      14: goto          18
      17: aconst_null
      18: areturn

  public A withNodePublishSecretRef(io.dekorate.deps.kubernetes.api.model.SecretReference);
    Code:
       0: aload_0
       1: getfield      #136                // Field _visitables:Lio/dekorate/deps/kubernetes/api/builder/VisitableMap;
       4: ldc           #240                // String nodePublishSecretRef
       6: invokevirtual #143                // Method io/dekorate/deps/kubernetes/api/builder/VisitableMap.get:(Ljava/lang/Object;)Ljava/util/List;
       9: aload_0
      10: getfield      #238                // Field nodePublishSecretRef:Lio/dekorate/deps/kubernetes/api/model/SecretReferenceBuilder;
      13: invokeinterface #149,  2          // InterfaceMethod java/util/List.remove:(Ljava/lang/Object;)Z
      18: pop
      19: aload_1
      20: ifnull        54
      23: aload_0
      24: new           #125                // class io/dekorate/deps/kubernetes/api/model/SecretReferenceBuilder
      27: dup
      28: aload_1
      29: invokespecial #152                // Method io/dekorate/deps/kubernetes/api/model/SecretReferenceBuilder."<init>":(Lio/dekorate/deps/kubernetes/api/model/SecretReference;)V
      32: putfield      #238                // Field nodePublishSecretRef:Lio/dekorate/deps/kubernetes/api/model/SecretReferenceBuilder;
      35: aload_0
      36: getfield      #136                // Field _visitables:Lio/dekorate/deps/kubernetes/api/builder/VisitableMap;
      39: ldc           #240                // String nodePublishSecretRef
      41: invokevirtual #143                // Method io/dekorate/deps/kubernetes/api/builder/VisitableMap.get:(Ljava/lang/Object;)Ljava/util/List;
      44: aload_0
      45: getfield      #238                // Field nodePublishSecretRef:Lio/dekorate/deps/kubernetes/api/model/SecretReferenceBuilder;
      48: invokeinterface #155,  2          // InterfaceMethod java/util/List.add:(Ljava/lang/Object;)Z
      53: pop
      54: aload_0
      55: areturn

  public java.lang.Boolean hasNodePublishSecretRef();
    Code:
       0: aload_0
       1: getfield      #238                // Field nodePublishSecretRef:Lio/dekorate/deps/kubernetes/api/model/SecretReferenceBuilder;
       4: ifnull        11
       7: iconst_1
       8: goto          12
      11: iconst_0
      12: invokestatic  #163                // Method java/lang/Boolean.valueOf:(Z)Ljava/lang/Boolean;
      15: areturn

  public A withNewNodePublishSecretRef(java.lang.String, java.lang.String);
    Code:
       0: aload_0
       1: new           #130                // class io/dekorate/deps/kubernetes/api/model/SecretReference
       4: dup
       5: aload_1
       6: aload_2
       7: invokespecial #169                // Method io/dekorate/deps/kubernetes/api/model/SecretReference."<init>":(Ljava/lang/String;Ljava/lang/String;)V
      10: invokevirtual #90                 // Method withNodePublishSecretRef:(Lio/dekorate/deps/kubernetes/api/model/SecretReference;)Lio/dekorate/deps/kubernetes/api/model/CSIPersistentVolumeSourceFluent;
      13: areturn

  public io.dekorate.deps.kubernetes.api.model.CSIPersistentVolumeSourceFluent$NodePublishSecretRefNested<A> withNewNodePublishSecretRef();
    Code:
       0: new           #13                 // class io/dekorate/deps/kubernetes/api/model/CSIPersistentVolumeSourceFluentImpl$NodePublishSecretRefNestedImpl
       3: dup
       4: aload_0
       5: invokespecial #245                // Method io/dekorate/deps/kubernetes/api/model/CSIPersistentVolumeSourceFluentImpl$NodePublishSecretRefNestedImpl."<init>":(Lio/dekorate/deps/kubernetes/api/model/CSIPersistentVolumeSourceFluentImpl;)V
       8: areturn

  public io.dekorate.deps.kubernetes.api.model.CSIPersistentVolumeSourceFluent$NodePublishSecretRefNested<A> withNewNodePublishSecretRefLike(io.dekorate.deps.kubernetes.api.model.SecretReference);
    Code:
       0: new           #13                 // class io/dekorate/deps/kubernetes/api/model/CSIPersistentVolumeSourceFluentImpl$NodePublishSecretRefNestedImpl
       3: dup
       4: aload_0
       5: aload_1
       6: invokespecial #249                // Method io/dekorate/deps/kubernetes/api/model/CSIPersistentVolumeSourceFluentImpl$NodePublishSecretRefNestedImpl."<init>":(Lio/dekorate/deps/kubernetes/api/model/CSIPersistentVolumeSourceFluentImpl;Lio/dekorate/deps/kubernetes/api/model/SecretReference;)V
       9: areturn

  public io.dekorate.deps.kubernetes.api.model.CSIPersistentVolumeSourceFluent$NodePublishSecretRefNested<A> editNodePublishSecretRef();
    Code:
       0: aload_0
       1: aload_0
       2: invokevirtual #251                // Method getNodePublishSecretRef:()Lio/dekorate/deps/kubernetes/api/model/SecretReference;
       5: invokevirtual #253                // Method withNewNodePublishSecretRefLike:(Lio/dekorate/deps/kubernetes/api/model/SecretReference;)Lio/dekorate/deps/kubernetes/api/model/CSIPersistentVolumeSourceFluent$NodePublishSecretRefNested;
       8: areturn

  public io.dekorate.deps.kubernetes.api.model.CSIPersistentVolumeSourceFluent$NodePublishSecretRefNested<A> editOrNewNodePublishSecretRef();
    Code:
       0: aload_0
       1: aload_0
       2: invokevirtual #251                // Method getNodePublishSecretRef:()Lio/dekorate/deps/kubernetes/api/model/SecretReference;
       5: ifnull        15
       8: aload_0
       9: invokevirtual #251                // Method getNodePublishSecretRef:()Lio/dekorate/deps/kubernetes/api/model/SecretReference;
      12: goto          25
      15: new           #125                // class io/dekorate/deps/kubernetes/api/model/SecretReferenceBuilder
      18: dup
      19: invokespecial #189                // Method io/dekorate/deps/kubernetes/api/model/SecretReferenceBuilder."<init>":()V
      22: invokevirtual #128                // Method io/dekorate/deps/kubernetes/api/model/SecretReferenceBuilder.build:()Lio/dekorate/deps/kubernetes/api/model/SecretReference;
      25: invokevirtual #253                // Method withNewNodePublishSecretRefLike:(Lio/dekorate/deps/kubernetes/api/model/SecretReference;)Lio/dekorate/deps/kubernetes/api/model/CSIPersistentVolumeSourceFluent$NodePublishSecretRefNested;
      28: areturn

  public io.dekorate.deps.kubernetes.api.model.CSIPersistentVolumeSourceFluent$NodePublishSecretRefNested<A> editOrNewNodePublishSecretRefLike(io.dekorate.deps.kubernetes.api.model.SecretReference);
    Code:
       0: aload_0
       1: aload_0
       2: invokevirtual #251                // Method getNodePublishSecretRef:()Lio/dekorate/deps/kubernetes/api/model/SecretReference;
       5: ifnull        15
       8: aload_0
       9: invokevirtual #251                // Method getNodePublishSecretRef:()Lio/dekorate/deps/kubernetes/api/model/SecretReference;
      12: goto          16
      15: aload_1
      16: invokevirtual #253                // Method withNewNodePublishSecretRefLike:(Lio/dekorate/deps/kubernetes/api/model/SecretReference;)Lio/dekorate/deps/kubernetes/api/model/CSIPersistentVolumeSourceFluent$NodePublishSecretRefNested;
      19: areturn

  public io.dekorate.deps.kubernetes.api.model.SecretReference getNodeStageSecretRef();
    Code:
       0: aload_0
       1: getfield      #257                // Field nodeStageSecretRef:Lio/dekorate/deps/kubernetes/api/model/SecretReferenceBuilder;
       4: ifnull        17
       7: aload_0
       8: getfield      #257                // Field nodeStageSecretRef:Lio/dekorate/deps/kubernetes/api/model/SecretReferenceBuilder;
      11: invokevirtual #128                // Method io/dekorate/deps/kubernetes/api/model/SecretReferenceBuilder.build:()Lio/dekorate/deps/kubernetes/api/model/SecretReference;
      14: goto          18
      17: aconst_null
      18: areturn

  public io.dekorate.deps.kubernetes.api.model.SecretReference buildNodeStageSecretRef();
    Code:
       0: aload_0
       1: getfield      #257                // Field nodeStageSecretRef:Lio/dekorate/deps/kubernetes/api/model/SecretReferenceBuilder;
       4: ifnull        17
       7: aload_0
       8: getfield      #257                // Field nodeStageSecretRef:Lio/dekorate/deps/kubernetes/api/model/SecretReferenceBuilder;
      11: invokevirtual #128                // Method io/dekorate/deps/kubernetes/api/model/SecretReferenceBuilder.build:()Lio/dekorate/deps/kubernetes/api/model/SecretReference;
      14: goto          18
      17: aconst_null
      18: areturn

  public A withNodeStageSecretRef(io.dekorate.deps.kubernetes.api.model.SecretReference);
    Code:
       0: aload_0
       1: getfield      #136                // Field _visitables:Lio/dekorate/deps/kubernetes/api/builder/VisitableMap;
       4: ldc_w         #259                // String nodeStageSecretRef
       7: invokevirtual #143                // Method io/dekorate/deps/kubernetes/api/builder/VisitableMap.get:(Ljava/lang/Object;)Ljava/util/List;
      10: aload_0
      11: getfield      #257                // Field nodeStageSecretRef:Lio/dekorate/deps/kubernetes/api/model/SecretReferenceBuilder;
      14: invokeinterface #149,  2          // InterfaceMethod java/util/List.remove:(Ljava/lang/Object;)Z
      19: pop
      20: aload_1
      21: ifnull        56
      24: aload_0
      25: new           #125                // class io/dekorate/deps/kubernetes/api/model/SecretReferenceBuilder
      28: dup
      29: aload_1
      30: invokespecial #152                // Method io/dekorate/deps/kubernetes/api/model/SecretReferenceBuilder."<init>":(Lio/dekorate/deps/kubernetes/api/model/SecretReference;)V
      33: putfield      #257                // Field nodeStageSecretRef:Lio/dekorate/deps/kubernetes/api/model/SecretReferenceBuilder;
      36: aload_0
      37: getfield      #136                // Field _visitables:Lio/dekorate/deps/kubernetes/api/builder/VisitableMap;
      40: ldc_w         #259                // String nodeStageSecretRef
      43: invokevirtual #143                // Method io/dekorate/deps/kubernetes/api/builder/VisitableMap.get:(Ljava/lang/Object;)Ljava/util/List;
      46: aload_0
      47: getfield      #257                // Field nodeStageSecretRef:Lio/dekorate/deps/kubernetes/api/model/SecretReferenceBuilder;
      50: invokeinterface #155,  2          // InterfaceMethod java/util/List.add:(Ljava/lang/Object;)Z
      55: pop
      56: aload_0
      57: areturn

  public java.lang.Boolean hasNodeStageSecretRef();
    Code:
       0: aload_0
       1: getfield      #257                // Field nodeStageSecretRef:Lio/dekorate/deps/kubernetes/api/model/SecretReferenceBuilder;
       4: ifnull        11
       7: iconst_1
       8: goto          12
      11: iconst_0
      12: invokestatic  #163                // Method java/lang/Boolean.valueOf:(Z)Ljava/lang/Boolean;
      15: areturn

  public A withNewNodeStageSecretRef(java.lang.String, java.lang.String);
    Code:
       0: aload_0
       1: new           #130                // class io/dekorate/deps/kubernetes/api/model/SecretReference
       4: dup
       5: aload_1
       6: aload_2
       7: invokespecial #169                // Method io/dekorate/deps/kubernetes/api/model/SecretReference."<init>":(Ljava/lang/String;Ljava/lang/String;)V
      10: invokevirtual #96                 // Method withNodeStageSecretRef:(Lio/dekorate/deps/kubernetes/api/model/SecretReference;)Lio/dekorate/deps/kubernetes/api/model/CSIPersistentVolumeSourceFluent;
      13: areturn

  public io.dekorate.deps.kubernetes.api.model.CSIPersistentVolumeSourceFluent$NodeStageSecretRefNested<A> withNewNodeStageSecretRef();
    Code:
       0: new           #10                 // class io/dekorate/deps/kubernetes/api/model/CSIPersistentVolumeSourceFluentImpl$NodeStageSecretRefNestedImpl
       3: dup
       4: aload_0
       5: invokespecial #264                // Method io/dekorate/deps/kubernetes/api/model/CSIPersistentVolumeSourceFluentImpl$NodeStageSecretRefNestedImpl."<init>":(Lio/dekorate/deps/kubernetes/api/model/CSIPersistentVolumeSourceFluentImpl;)V
       8: areturn

  public io.dekorate.deps.kubernetes.api.model.CSIPersistentVolumeSourceFluent$NodeStageSecretRefNested<A> withNewNodeStageSecretRefLike(io.dekorate.deps.kubernetes.api.model.SecretReference);
    Code:
       0: new           #10                 // class io/dekorate/deps/kubernetes/api/model/CSIPersistentVolumeSourceFluentImpl$NodeStageSecretRefNestedImpl
       3: dup
       4: aload_0
       5: aload_1
       6: invokespecial #268                // Method io/dekorate/deps/kubernetes/api/model/CSIPersistentVolumeSourceFluentImpl$NodeStageSecretRefNestedImpl."<init>":(Lio/dekorate/deps/kubernetes/api/model/CSIPersistentVolumeSourceFluentImpl;Lio/dekorate/deps/kubernetes/api/model/SecretReference;)V
       9: areturn

  public io.dekorate.deps.kubernetes.api.model.CSIPersistentVolumeSourceFluent$NodeStageSecretRefNested<A> editNodeStageSecretRef();
    Code:
       0: aload_0
       1: aload_0
       2: invokevirtual #270                // Method getNodeStageSecretRef:()Lio/dekorate/deps/kubernetes/api/model/SecretReference;
       5: invokevirtual #272                // Method withNewNodeStageSecretRefLike:(Lio/dekorate/deps/kubernetes/api/model/SecretReference;)Lio/dekorate/deps/kubernetes/api/model/CSIPersistentVolumeSourceFluent$NodeStageSecretRefNested;
       8: areturn

  public io.dekorate.deps.kubernetes.api.model.CSIPersistentVolumeSourceFluent$NodeStageSecretRefNested<A> editOrNewNodeStageSecretRef();
    Code:
       0: aload_0
       1: aload_0
       2: invokevirtual #270                // Method getNodeStageSecretRef:()Lio/dekorate/deps/kubernetes/api/model/SecretReference;
       5: ifnull        15
       8: aload_0
       9: invokevirtual #270                // Method getNodeStageSecretRef:()Lio/dekorate/deps/kubernetes/api/model/SecretReference;
      12: goto          25
      15: new           #125                // class io/dekorate/deps/kubernetes/api/model/SecretReferenceBuilder
      18: dup
      19: invokespecial #189                // Method io/dekorate/deps/kubernetes/api/model/SecretReferenceBuilder."<init>":()V
      22: invokevirtual #128                // Method io/dekorate/deps/kubernetes/api/model/SecretReferenceBuilder.build:()Lio/dekorate/deps/kubernetes/api/model/SecretReference;
      25: invokevirtual #272                // Method withNewNodeStageSecretRefLike:(Lio/dekorate/deps/kubernetes/api/model/SecretReference;)Lio/dekorate/deps/kubernetes/api/model/CSIPersistentVolumeSourceFluent$NodeStageSecretRefNested;
      28: areturn

  public io.dekorate.deps.kubernetes.api.model.CSIPersistentVolumeSourceFluent$NodeStageSecretRefNested<A> editOrNewNodeStageSecretRefLike(io.dekorate.deps.kubernetes.api.model.SecretReference);
    Code:
       0: aload_0
       1: aload_0
       2: invokevirtual #270                // Method getNodeStageSecretRef:()Lio/dekorate/deps/kubernetes/api/model/SecretReference;
       5: ifnull        15
       8: aload_0
       9: invokevirtual #270                // Method getNodeStageSecretRef:()Lio/dekorate/deps/kubernetes/api/model/SecretReference;
      12: goto          16
      15: aload_1
      16: invokevirtual #272                // Method withNewNodeStageSecretRefLike:(Lio/dekorate/deps/kubernetes/api/model/SecretReference;)Lio/dekorate/deps/kubernetes/api/model/CSIPersistentVolumeSourceFluent$NodeStageSecretRefNested;
      19: areturn

  public java.lang.Boolean isReadOnly();
    Code:
       0: aload_0
       1: getfield      #277                // Field readOnly:Ljava/lang/Boolean;
       4: areturn

  public A withReadOnly(java.lang.Boolean);
    Code:
       0: aload_0
       1: aload_1
       2: putfield      #277                // Field readOnly:Ljava/lang/Boolean;
       5: aload_0
       6: areturn

  public java.lang.Boolean hasReadOnly();
    Code:
       0: aload_0
       1: getfield      #277                // Field readOnly:Ljava/lang/Boolean;
       4: ifnull        11
       7: iconst_1
       8: goto          12
      11: iconst_0
      12: invokestatic  #163                // Method java/lang/Boolean.valueOf:(Z)Ljava/lang/Boolean;
      15: areturn

  public A withNewReadOnly(java.lang.String);
    Code:
       0: aload_0
       1: new           #159                // class java/lang/Boolean
       4: dup
       5: aload_1
       6: invokespecial #281                // Method java/lang/Boolean."<init>":(Ljava/lang/String;)V
       9: invokevirtual #104                // Method withReadOnly:(Ljava/lang/Boolean;)Lio/dekorate/deps/kubernetes/api/model/CSIPersistentVolumeSourceFluent;
      12: areturn

  public A withNewReadOnly(boolean);
    Code:
       0: aload_0
       1: new           #159                // class java/lang/Boolean
       4: dup
       5: iload_1
       6: invokespecial #286                // Method java/lang/Boolean."<init>":(Z)V
       9: invokevirtual #104                // Method withReadOnly:(Ljava/lang/Boolean;)Lio/dekorate/deps/kubernetes/api/model/CSIPersistentVolumeSourceFluent;
      12: areturn

  public A addToVolumeAttributes(java.lang.String, java.lang.String);
    Code:
       0: aload_0
       1: getfield      #290                // Field volumeAttributes:Ljava/util/Map;
       4: ifnonnull     26
       7: aload_1
       8: ifnull        26
      11: aload_2
      12: ifnull        26
      15: aload_0
      16: new           #292                // class java/util/LinkedHashMap
      19: dup
      20: invokespecial #293                // Method java/util/LinkedHashMap."<init>":()V
      23: putfield      #290                // Field volumeAttributes:Ljava/util/Map;
      26: aload_1
      27: ifnull        46
      30: aload_2
      31: ifnull        46
      34: aload_0
      35: getfield      #290                // Field volumeAttributes:Ljava/util/Map;
      38: aload_1
      39: aload_2
      40: invokeinterface #299,  3          // InterfaceMethod java/util/Map.put:(Ljava/lang/Object;Ljava/lang/Object;)Ljava/lang/Object;
      45: pop
      46: aload_0
      47: areturn

  public A addToVolumeAttributes(java.util.Map<java.lang.String, java.lang.String>);
    Code:
       0: aload_0
       1: getfield      #290                // Field volumeAttributes:Ljava/util/Map;
       4: ifnonnull     22
       7: aload_1
       8: ifnull        22
      11: aload_0
      12: new           #292                // class java/util/LinkedHashMap
      15: dup
      16: invokespecial #293                // Method java/util/LinkedHashMap."<init>":()V
      19: putfield      #290                // Field volumeAttributes:Ljava/util/Map;
      22: aload_1
      23: ifnull        36
      26: aload_0
      27: getfield      #290                // Field volumeAttributes:Ljava/util/Map;
      30: aload_1
      31: invokeinterface #306,  2          // InterfaceMethod java/util/Map.putAll:(Ljava/util/Map;)V
      36: aload_0
      37: areturn

  public A removeFromVolumeAttributes(java.lang.String);
    Code:
       0: aload_0
       1: getfield      #290                // Field volumeAttributes:Ljava/util/Map;
       4: ifnonnull     9
       7: aload_0
       8: areturn
       9: aload_1
      10: ifnull        31
      13: aload_0
      14: getfield      #290                // Field volumeAttributes:Ljava/util/Map;
      17: ifnull        31
      20: aload_0
      21: getfield      #290                // Field volumeAttributes:Ljava/util/Map;
      24: aload_1
      25: invokeinterface #311,  2          // InterfaceMethod java/util/Map.remove:(Ljava/lang/Object;)Ljava/lang/Object;
      30: pop
      31: aload_0
      32: areturn

  public A removeFromVolumeAttributes(java.util.Map<java.lang.String, java.lang.String>);
    Code:
       0: aload_0
       1: getfield      #290                // Field volumeAttributes:Ljava/util/Map;
       4: ifnonnull     9
       7: aload_0
       8: areturn
       9: aload_1
      10: ifnull        62
      13: aload_1
      14: invokeinterface #315,  1          // InterfaceMethod java/util/Map.keySet:()Ljava/util/Set;
      19: invokeinterface #321,  1          // InterfaceMethod java/util/Set.iterator:()Ljava/util/Iterator;
      24: astore_2
      25: aload_2
      26: invokeinterface #327,  1          // InterfaceMethod java/util/Iterator.hasNext:()Z
      31: ifeq          62
      34: aload_2
      35: invokeinterface #331,  1          // InterfaceMethod java/util/Iterator.next:()Ljava/lang/Object;
      40: astore_3
      41: aload_0
      42: getfield      #290                // Field volumeAttributes:Ljava/util/Map;
      45: ifnull        59
      48: aload_0
      49: getfield      #290                // Field volumeAttributes:Ljava/util/Map;
      52: aload_3
      53: invokeinterface #311,  2          // InterfaceMethod java/util/Map.remove:(Ljava/lang/Object;)Ljava/lang/Object;
      58: pop
      59: goto          25
      62: aload_0
      63: areturn

  public java.util.Map<java.lang.String, java.lang.String> getVolumeAttributes();
    Code:
       0: aload_0
       1: getfield      #290                // Field volumeAttributes:Ljava/util/Map;
       4: areturn

  public A withVolumeAttributes(java.util.Map<java.lang.String, java.lang.String>);
    Code:
       0: aload_1
       1: ifnonnull     12
       4: aload_0
       5: aconst_null
       6: putfield      #290                // Field volumeAttributes:Ljava/util/Map;
       9: goto          24
      12: aload_0
      13: new           #292                // class java/util/LinkedHashMap
      16: dup
      17: aload_1
      18: invokespecial #335                // Method java/util/LinkedHashMap."<init>":(Ljava/util/Map;)V
      21: putfield      #290                // Field volumeAttributes:Ljava/util/Map;
      24: aload_0
      25: areturn

  public java.lang.Boolean hasVolumeAttributes();
    Code:
       0: aload_0
       1: getfield      #290                // Field volumeAttributes:Ljava/util/Map;
       4: ifnull        11
       7: iconst_1
       8: goto          12
      11: iconst_0
      12: invokestatic  #163                // Method java/lang/Boolean.valueOf:(Z)Ljava/lang/Boolean;
      15: areturn

  public java.lang.String getVolumeHandle();
    Code:
       0: aload_0
       1: getfield      #338                // Field volumeHandle:Ljava/lang/String;
       4: areturn

  public A withVolumeHandle(java.lang.String);
    Code:
       0: aload_0
       1: aload_1
       2: putfield      #338                // Field volumeHandle:Ljava/lang/String;
       5: aload_0
       6: areturn

  public java.lang.Boolean hasVolumeHandle();
    Code:
       0: aload_0
       1: getfield      #338                // Field volumeHandle:Ljava/lang/String;
       4: ifnull        11
       7: iconst_1
       8: goto          12
      11: iconst_0
      12: invokestatic  #163                // Method java/lang/Boolean.valueOf:(Z)Ljava/lang/Boolean;
      15: areturn

  public A withNewVolumeHandle(java.lang.String);
    Code:
       0: aload_0
       1: new           #216                // class java/lang/String
       4: dup
       5: aload_1
       6: invokespecial #219                // Method java/lang/String."<init>":(Ljava/lang/String;)V
       9: invokevirtual #118                // Method withVolumeHandle:(Ljava/lang/String;)Lio/dekorate/deps/kubernetes/api/model/CSIPersistentVolumeSourceFluent;
      12: areturn

  public A withNewVolumeHandle(java.lang.StringBuilder);
    Code:
       0: aload_0
       1: new           #216                // class java/lang/String
       4: dup
       5: aload_1
       6: invokespecial #225                // Method java/lang/String."<init>":(Ljava/lang/StringBuilder;)V
       9: invokevirtual #118                // Method withVolumeHandle:(Ljava/lang/String;)Lio/dekorate/deps/kubernetes/api/model/CSIPersistentVolumeSourceFluent;
      12: areturn

  public A withNewVolumeHandle(java.lang.StringBuffer);
    Code:
       0: aload_0
       1: new           #216                // class java/lang/String
       4: dup
       5: aload_1
       6: invokespecial #231                // Method java/lang/String."<init>":(Ljava/lang/StringBuffer;)V
       9: invokevirtual #118                // Method withVolumeHandle:(Ljava/lang/String;)Lio/dekorate/deps/kubernetes/api/model/CSIPersistentVolumeSourceFluent;
      12: areturn

  public boolean equals(java.lang.Object);
    Code:
       0: aload_0
       1: aload_1
       2: if_acmpne     7
       5: iconst_1
       6: ireturn
       7: aload_1
       8: ifnull        22
      11: aload_0
      12: invokevirtual #347                // Method java/lang/Object.getClass:()Ljava/lang/Class;
      15: aload_1
      16: invokevirtual #347                // Method java/lang/Object.getClass:()Ljava/lang/Class;
      19: if_acmpeq     24
      22: iconst_0
      23: ireturn
      24: aload_1
      25: checkcast     #2                  // class io/dekorate/deps/kubernetes/api/model/CSIPersistentVolumeSourceFluentImpl
      28: astore_2
      29: aload_0
      30: getfield      #123                // Field controllerExpandSecretRef:Lio/dekorate/deps/kubernetes/api/model/SecretReferenceBuilder;
      33: ifnull        53
      36: aload_0
      37: getfield      #123                // Field controllerExpandSecretRef:Lio/dekorate/deps/kubernetes/api/model/SecretReferenceBuilder;
      40: aload_2
      41: getfield      #123                // Field controllerExpandSecretRef:Lio/dekorate/deps/kubernetes/api/model/SecretReferenceBuilder;
      44: invokevirtual #349                // Method io/dekorate/deps/kubernetes/api/model/SecretReferenceBuilder.equals:(Ljava/lang/Object;)Z
      47: ifne          62
      50: goto          60
      53: aload_2
      54: getfield      #123                // Field controllerExpandSecretRef:Lio/dekorate/deps/kubernetes/api/model/SecretReferenceBuilder;
      57: ifnull        62
      60: iconst_0
      61: ireturn
      62: aload_0
      63: getfield      #192                // Field controllerPublishSecretRef:Lio/dekorate/deps/kubernetes/api/model/SecretReferenceBuilder;
      66: ifnull        86
      69: aload_0
      70: getfield      #192                // Field controllerPublishSecretRef:Lio/dekorate/deps/kubernetes/api/model/SecretReferenceBuilder;
      73: aload_2
      74: getfield      #192                // Field controllerPublishSecretRef:Lio/dekorate/deps/kubernetes/api/model/SecretReferenceBuilder;
      77: invokevirtual #349                // Method io/dekorate/deps/kubernetes/api/model/SecretReferenceBuilder.equals:(Ljava/lang/Object;)Z
      80: ifne          95
      83: goto          93
      86: aload_2
      87: getfield      #192                // Field controllerPublishSecretRef:Lio/dekorate/deps/kubernetes/api/model/SecretReferenceBuilder;
      90: ifnull        95
      93: iconst_0
      94: ireturn
      95: aload_0
      96: getfield      #211                // Field driver:Ljava/lang/String;
      99: ifnull        119
     102: aload_0
     103: getfield      #211                // Field driver:Ljava/lang/String;
     106: aload_2
     107: getfield      #211                // Field driver:Ljava/lang/String;
     110: invokevirtual #350                // Method java/lang/String.equals:(Ljava/lang/Object;)Z
     113: ifne          128
     116: goto          126
     119: aload_2
     120: getfield      #211                // Field driver:Ljava/lang/String;
     123: ifnull        128
     126: iconst_0
     127: ireturn
     128: aload_0
     129: getfield      #234                // Field fsType:Ljava/lang/String;
     132: ifnull        152
     135: aload_0
     136: getfield      #234                // Field fsType:Ljava/lang/String;
     139: aload_2
     140: getfield      #234                // Field fsType:Ljava/lang/String;
     143: invokevirtual #350                // Method java/lang/String.equals:(Ljava/lang/Object;)Z
     146: ifne          161
     149: goto          159
     152: aload_2
     153: getfield      #234                // Field fsType:Ljava/lang/String;
     156: ifnull        161
     159: iconst_0
     160: ireturn
     161: aload_0
     162: getfield      #238                // Field nodePublishSecretRef:Lio/dekorate/deps/kubernetes/api/model/SecretReferenceBuilder;
     165: ifnull        185
     168: aload_0
     169: getfield      #238                // Field nodePublishSecretRef:Lio/dekorate/deps/kubernetes/api/model/SecretReferenceBuilder;
     172: aload_2
     173: getfield      #238                // Field nodePublishSecretRef:Lio/dekorate/deps/kubernetes/api/model/SecretReferenceBuilder;
     176: invokevirtual #349                // Method io/dekorate/deps/kubernetes/api/model/SecretReferenceBuilder.equals:(Ljava/lang/Object;)Z
     179: ifne          194
     182: goto          192
     185: aload_2
     186: getfield      #238                // Field nodePublishSecretRef:Lio/dekorate/deps/kubernetes/api/model/SecretReferenceBuilder;
     189: ifnull        194
     192: iconst_0
     193: ireturn
     194: aload_0
     195: getfield      #257                // Field nodeStageSecretRef:Lio/dekorate/deps/kubernetes/api/model/SecretReferenceBuilder;
     198: ifnull        218
     201: aload_0
     202: getfield      #257                // Field nodeStageSecretRef:Lio/dekorate/deps/kubernetes/api/model/SecretReferenceBuilder;
     205: aload_2
     206: getfield      #257                // Field nodeStageSecretRef:Lio/dekorate/deps/kubernetes/api/model/SecretReferenceBuilder;
     209: invokevirtual #349                // Method io/dekorate/deps/kubernetes/api/model/SecretReferenceBuilder.equals:(Ljava/lang/Object;)Z
     212: ifne          227
     215: goto          225
     218: aload_2
     219: getfield      #257                // Field nodeStageSecretRef:Lio/dekorate/deps/kubernetes/api/model/SecretReferenceBuilder;
     222: ifnull        227
     225: iconst_0
     226: ireturn
     227: aload_0
     228: getfield      #277                // Field readOnly:Ljava/lang/Boolean;
     231: ifnull        251
     234: aload_0
     235: getfield      #277                // Field readOnly:Ljava/lang/Boolean;
     238: aload_2
     239: getfield      #277                // Field readOnly:Ljava/lang/Boolean;
     242: invokevirtual #351                // Method java/lang/Boolean.equals:(Ljava/lang/Object;)Z
     245: ifne          260
     248: goto          258
     251: aload_2
     252: getfield      #277                // Field readOnly:Ljava/lang/Boolean;
     255: ifnull        260
     258: iconst_0
     259: ireturn
     260: aload_0
     261: getfield      #290                // Field volumeAttributes:Ljava/util/Map;
     264: ifnull        286
     267: aload_0
     268: getfield      #290                // Field volumeAttributes:Ljava/util/Map;
     271: aload_2
     272: getfield      #290                // Field volumeAttributes:Ljava/util/Map;
     275: invokeinterface #352,  2          // InterfaceMethod java/util/Map.equals:(Ljava/lang/Object;)Z
     280: ifne          295
     283: goto          293
     286: aload_2
     287: getfield      #290                // Field volumeAttributes:Ljava/util/Map;
     290: ifnull        295
     293: iconst_0
     294: ireturn
     295: aload_0
     296: getfield      #338                // Field volumeHandle:Ljava/lang/String;
     299: ifnull        319
     302: aload_0
     303: getfield      #338                // Field volumeHandle:Ljava/lang/String;
     306: aload_2
     307: getfield      #338                // Field volumeHandle:Ljava/lang/String;
     310: invokevirtual #350                // Method java/lang/String.equals:(Ljava/lang/Object;)Z
     313: ifne          328
     316: goto          326
     319: aload_2
     320: getfield      #338                // Field volumeHandle:Ljava/lang/String;
     323: ifnull        328
     326: iconst_0
     327: ireturn
     328: iconst_1
     329: ireturn
}
