Compiled from "DoneableCSIVolumeSource.java"
class io.dekorate.deps.kubernetes.api.model.DoneableCSIVolumeSource$1 implements io.dekorate.deps.kubernetes.api.builder.Function<io.dekorate.deps.kubernetes.api.model.CSIVolumeSource, io.dekorate.deps.kubernetes.api.model.CSIVolumeSource> {
  final io.dekorate.deps.kubernetes.api.model.DoneableCSIVolumeSource this$0;

  io.dekorate.deps.kubernetes.api.model.DoneableCSIVolumeSource$1(io.dekorate.deps.kubernetes.api.model.DoneableCSIVolumeSource);
    Code:
       0: aload_0
       1: aload_1
       2: putfield      #18                 // Field this$0:Lio/dekorate/deps/kubernetes/api/model/DoneableCSIVolumeSource;
       5: aload_0
       6: invokespecial #21                 // Method java/lang/Object."<init>":()V
       9: return

  public io.dekorate.deps.kubernetes.api.model.CSIVolumeSource apply(io.dekorate.deps.kubernetes.api.model.CSIVolumeSource);
    Code:
       0: aload_1
       1: areturn

  public java.lang.Object apply(java.lang.Object);
    Code:
       0: aload_0
       1: aload_1
       2: checkcast     #30                 // class io/dekorate/deps/kubernetes/api/model/CSIVolumeSource
       5: invokevirtual #32                 // Method apply:(Lio/dekorate/deps/kubernetes/api/model/CSIVolumeSource;)Lio/dekorate/deps/kubernetes/api/model/CSIVolumeSource;
       8: areturn
}
