Compiled from "DoneableScaleIOPersistentVolumeSource.java"
public class io.dekorate.deps.kubernetes.api.model.DoneableScaleIOPersistentVolumeSource extends io.dekorate.deps.kubernetes.api.model.ScaleIOPersistentVolumeSourceFluentImpl<io.dekorate.deps.kubernetes.api.model.DoneableScaleIOPersistentVolumeSource> implements io.dekorate.deps.kubernetes.api.model.Doneable<io.dekorate.deps.kubernetes.api.model.ScaleIOPersistentVolumeSource> {
  private final io.dekorate.deps.kubernetes.api.model.ScaleIOPersistentVolumeSourceBuilder builder;

  private final io.dekorate.deps.kubernetes.api.builder.Function<io.dekorate.deps.kubernetes.api.model.ScaleIOPersistentVolumeSource, io.dekorate.deps.kubernetes.api.model.ScaleIOPersistentVolumeSource> function;

  public io.dekorate.deps.kubernetes.api.model.DoneableScaleIOPersistentVolumeSource(io.dekorate.deps.kubernetes.api.builder.Function<io.dekorate.deps.kubernetes.api.model.ScaleIOPersistentVolumeSource, io.dekorate.deps.kubernetes.api.model.ScaleIOPersistentVolumeSource>);
    Code:
       0: aload_0
       1: invokespecial #21                 // Method io/dekorate/deps/kubernetes/api/model/ScaleIOPersistentVolumeSourceFluentImpl."<init>":()V
       4: aload_0
       5: new           #23                 // class io/dekorate/deps/kubernetes/api/model/ScaleIOPersistentVolumeSourceBuilder
       8: dup
       9: aload_0
      10: invokespecial #26                 // Method io/dekorate/deps/kubernetes/api/model/ScaleIOPersistentVolumeSourceBuilder."<init>":(Lio/dekorate/deps/kubernetes/api/model/ScaleIOPersistentVolumeSourceFluent;)V
      13: putfield      #28                 // Field builder:Lio/dekorate/deps/kubernetes/api/model/ScaleIOPersistentVolumeSourceBuilder;
      16: aload_0
      17: aload_1
      18: putfield      #30                 // Field function:Lio/dekorate/deps/kubernetes/api/builder/Function;
      21: return

  public io.dekorate.deps.kubernetes.api.model.DoneableScaleIOPersistentVolumeSource(io.dekorate.deps.kubernetes.api.model.ScaleIOPersistentVolumeSource, io.dekorate.deps.kubernetes.api.builder.Function<io.dekorate.deps.kubernetes.api.model.ScaleIOPersistentVolumeSource, io.dekorate.deps.kubernetes.api.model.ScaleIOPersistentVolumeSource>);
    Code:
       0: aload_0
       1: aload_1
       2: invokespecial #37                 // Method io/dekorate/deps/kubernetes/api/model/ScaleIOPersistentVolumeSourceFluentImpl."<init>":(Lio/dekorate/deps/kubernetes/api/model/ScaleIOPersistentVolumeSource;)V
       5: aload_0
       6: new           #23                 // class io/dekorate/deps/kubernetes/api/model/ScaleIOPersistentVolumeSourceBuilder
       9: dup
      10: aload_0
      11: aload_1
      12: invokespecial #40                 // Method io/dekorate/deps/kubernetes/api/model/ScaleIOPersistentVolumeSourceBuilder."<init>":(Lio/dekorate/deps/kubernetes/api/model/ScaleIOPersistentVolumeSourceFluent;Lio/dekorate/deps/kubernetes/api/model/ScaleIOPersistentVolumeSource;)V
      15: putfield      #28                 // Field builder:Lio/dekorate/deps/kubernetes/api/model/ScaleIOPersistentVolumeSourceBuilder;
      18: aload_0
      19: aload_2
      20: putfield      #30                 // Field function:Lio/dekorate/deps/kubernetes/api/builder/Function;
      23: return

  public io.dekorate.deps.kubernetes.api.model.DoneableScaleIOPersistentVolumeSource(io.dekorate.deps.kubernetes.api.model.ScaleIOPersistentVolumeSource);
    Code:
       0: aload_0
       1: aload_1
       2: invokespecial #37                 // Method io/dekorate/deps/kubernetes/api/model/ScaleIOPersistentVolumeSourceFluentImpl."<init>":(Lio/dekorate/deps/kubernetes/api/model/ScaleIOPersistentVolumeSource;)V
       5: aload_0
       6: new           #23                 // class io/dekorate/deps/kubernetes/api/model/ScaleIOPersistentVolumeSourceBuilder
       9: dup
      10: aload_0
      11: aload_1
      12: invokespecial #40                 // Method io/dekorate/deps/kubernetes/api/model/ScaleIOPersistentVolumeSourceBuilder."<init>":(Lio/dekorate/deps/kubernetes/api/model/ScaleIOPersistentVolumeSourceFluent;Lio/dekorate/deps/kubernetes/api/model/ScaleIOPersistentVolumeSource;)V
      15: putfield      #28                 // Field builder:Lio/dekorate/deps/kubernetes/api/model/ScaleIOPersistentVolumeSourceBuilder;
      18: aload_0
      19: new           #10                 // class io/dekorate/deps/kubernetes/api/model/DoneableScaleIOPersistentVolumeSource$1
      22: dup
      23: aload_0
      24: invokespecial #45                 // Method io/dekorate/deps/kubernetes/api/model/DoneableScaleIOPersistentVolumeSource$1."<init>":(Lio/dekorate/deps/kubernetes/api/model/DoneableScaleIOPersistentVolumeSource;)V
      27: putfield      #30                 // Field function:Lio/dekorate/deps/kubernetes/api/builder/Function;
      30: return

  public io.dekorate.deps.kubernetes.api.model.ScaleIOPersistentVolumeSource done();
    Code:
       0: aload_0
       1: getfield      #30                 // Field function:Lio/dekorate/deps/kubernetes/api/builder/Function;
       4: aload_0
       5: getfield      #28                 // Field builder:Lio/dekorate/deps/kubernetes/api/model/ScaleIOPersistentVolumeSourceBuilder;
       8: invokevirtual #50                 // Method io/dekorate/deps/kubernetes/api/model/ScaleIOPersistentVolumeSourceBuilder.build:()Lio/dekorate/deps/kubernetes/api/model/ScaleIOPersistentVolumeSource;
      11: invokeinterface #56,  2           // InterfaceMethod io/dekorate/deps/kubernetes/api/builder/Function.apply:(Ljava/lang/Object;)Ljava/lang/Object;
      16: checkcast     #58                 // class io/dekorate/deps/kubernetes/api/model/ScaleIOPersistentVolumeSource
      19: areturn

  public java.lang.Object done();
    Code:
       0: aload_0
       1: invokevirtual #61                 // Method done:()Lio/dekorate/deps/kubernetes/api/model/ScaleIOPersistentVolumeSource;
       4: areturn
}
