Compiled from "DownwardAPIVolumeFileFluentImpl.java"
public class io.dekorate.deps.kubernetes.api.model.DownwardAPIVolumeFileFluentImpl<A extends io.dekorate.deps.kubernetes.api.model.DownwardAPIVolumeFileFluent<A>> extends io.dekorate.deps.kubernetes.api.builder.BaseFluent<A> implements io.dekorate.deps.kubernetes.api.model.DownwardAPIVolumeFileFluent<A> {
  private io.dekorate.deps.kubernetes.api.model.ObjectFieldSelectorBuilder fieldRef;

  private java.lang.Integer mode;

  private java.lang.String path;

  private io.dekorate.deps.kubernetes.api.model.ResourceFieldSelectorBuilder resourceFieldRef;

  public io.dekorate.deps.kubernetes.api.model.DownwardAPIVolumeFileFluentImpl();
    Code:
       0: aload_0
       1: invokespecial #32                 // Method io/dekorate/deps/kubernetes/api/builder/BaseFluent."<init>":()V
       4: return

  public io.dekorate.deps.kubernetes.api.model.DownwardAPIVolumeFileFluentImpl(io.dekorate.deps.kubernetes.api.model.DownwardAPIVolumeFile);
    Code:
       0: aload_0
       1: invokespecial #32                 // Method io/dekorate/deps/kubernetes/api/builder/BaseFluent."<init>":()V
       4: aload_0
       5: aload_1
       6: invokevirtual #42                 // Method io/dekorate/deps/kubernetes/api/model/DownwardAPIVolumeFile.getFieldRef:()Lio/dekorate/deps/kubernetes/api/model/ObjectFieldSelector;
       9: invokevirtual #46                 // Method withFieldRef:(Lio/dekorate/deps/kubernetes/api/model/ObjectFieldSelector;)Lio/dekorate/deps/kubernetes/api/model/DownwardAPIVolumeFileFluent;
      12: pop
      13: aload_0
      14: aload_1
      15: invokevirtual #50                 // Method io/dekorate/deps/kubernetes/api/model/DownwardAPIVolumeFile.getMode:()Ljava/lang/Integer;
      18: invokevirtual #54                 // Method withMode:(Ljava/lang/Integer;)Lio/dekorate/deps/kubernetes/api/model/DownwardAPIVolumeFileFluent;
      21: pop
      22: aload_0
      23: aload_1
      24: invokevirtual #58                 // Method io/dekorate/deps/kubernetes/api/model/DownwardAPIVolumeFile.getPath:()Ljava/lang/String;
      27: invokevirtual #62                 // Method withPath:(Ljava/lang/String;)Lio/dekorate/deps/kubernetes/api/model/DownwardAPIVolumeFileFluent;
      30: pop
      31: aload_0
      32: aload_1
      33: invokevirtual #66                 // Method io/dekorate/deps/kubernetes/api/model/DownwardAPIVolumeFile.getResourceFieldRef:()Lio/dekorate/deps/kubernetes/api/model/ResourceFieldSelector;
      36: invokevirtual #70                 // Method withResourceFieldRef:(Lio/dekorate/deps/kubernetes/api/model/ResourceFieldSelector;)Lio/dekorate/deps/kubernetes/api/model/DownwardAPIVolumeFileFluent;
      39: pop
      40: return

  public io.dekorate.deps.kubernetes.api.model.ObjectFieldSelector getFieldRef();
    Code:
       0: aload_0
       1: getfield      #75                 // Field fieldRef:Lio/dekorate/deps/kubernetes/api/model/ObjectFieldSelectorBuilder;
       4: ifnull        17
       7: aload_0
       8: getfield      #75                 // Field fieldRef:Lio/dekorate/deps/kubernetes/api/model/ObjectFieldSelectorBuilder;
      11: invokevirtual #80                 // Method io/dekorate/deps/kubernetes/api/model/ObjectFieldSelectorBuilder.build:()Lio/dekorate/deps/kubernetes/api/model/ObjectFieldSelector;
      14: goto          18
      17: aconst_null
      18: areturn

  public io.dekorate.deps.kubernetes.api.model.ObjectFieldSelector buildFieldRef();
    Code:
       0: aload_0
       1: getfield      #75                 // Field fieldRef:Lio/dekorate/deps/kubernetes/api/model/ObjectFieldSelectorBuilder;
       4: ifnull        17
       7: aload_0
       8: getfield      #75                 // Field fieldRef:Lio/dekorate/deps/kubernetes/api/model/ObjectFieldSelectorBuilder;
      11: invokevirtual #80                 // Method io/dekorate/deps/kubernetes/api/model/ObjectFieldSelectorBuilder.build:()Lio/dekorate/deps/kubernetes/api/model/ObjectFieldSelector;
      14: goto          18
      17: aconst_null
      18: areturn

  public A withFieldRef(io.dekorate.deps.kubernetes.api.model.ObjectFieldSelector);
    Code:
       0: aload_0
       1: getfield      #88                 // Field _visitables:Lio/dekorate/deps/kubernetes/api/builder/VisitableMap;
       4: ldc           #89                 // String fieldRef
       6: invokevirtual #95                 // Method io/dekorate/deps/kubernetes/api/builder/VisitableMap.get:(Ljava/lang/Object;)Ljava/util/List;
       9: aload_0
      10: getfield      #75                 // Field fieldRef:Lio/dekorate/deps/kubernetes/api/model/ObjectFieldSelectorBuilder;
      13: invokeinterface #101,  2          // InterfaceMethod java/util/List.remove:(Ljava/lang/Object;)Z
      18: pop
      19: aload_1
      20: ifnull        54
      23: aload_0
      24: new           #77                 // class io/dekorate/deps/kubernetes/api/model/ObjectFieldSelectorBuilder
      27: dup
      28: aload_1
      29: invokespecial #104                // Method io/dekorate/deps/kubernetes/api/model/ObjectFieldSelectorBuilder."<init>":(Lio/dekorate/deps/kubernetes/api/model/ObjectFieldSelector;)V
      32: putfield      #75                 // Field fieldRef:Lio/dekorate/deps/kubernetes/api/model/ObjectFieldSelectorBuilder;
      35: aload_0
      36: getfield      #88                 // Field _visitables:Lio/dekorate/deps/kubernetes/api/builder/VisitableMap;
      39: ldc           #89                 // String fieldRef
      41: invokevirtual #95                 // Method io/dekorate/deps/kubernetes/api/builder/VisitableMap.get:(Ljava/lang/Object;)Ljava/util/List;
      44: aload_0
      45: getfield      #75                 // Field fieldRef:Lio/dekorate/deps/kubernetes/api/model/ObjectFieldSelectorBuilder;
      48: invokeinterface #107,  2          // InterfaceMethod java/util/List.add:(Ljava/lang/Object;)Z
      53: pop
      54: aload_0
      55: areturn

  public java.lang.Boolean hasFieldRef();
    Code:
       0: aload_0
       1: getfield      #75                 // Field fieldRef:Lio/dekorate/deps/kubernetes/api/model/ObjectFieldSelectorBuilder;
       4: ifnull        11
       7: iconst_1
       8: goto          12
      11: iconst_0
      12: invokestatic  #116                // Method java/lang/Boolean.valueOf:(Z)Ljava/lang/Boolean;
      15: areturn

  public A withNewFieldRef(java.lang.String, java.lang.String);
    Code:
       0: aload_0
       1: new           #82                 // class io/dekorate/deps/kubernetes/api/model/ObjectFieldSelector
       4: dup
       5: aload_1
       6: aload_2
       7: invokespecial #122                // Method io/dekorate/deps/kubernetes/api/model/ObjectFieldSelector."<init>":(Ljava/lang/String;Ljava/lang/String;)V
      10: invokevirtual #46                 // Method withFieldRef:(Lio/dekorate/deps/kubernetes/api/model/ObjectFieldSelector;)Lio/dekorate/deps/kubernetes/api/model/DownwardAPIVolumeFileFluent;
      13: areturn

  public io.dekorate.deps.kubernetes.api.model.DownwardAPIVolumeFileFluent$FieldRefNested<A> withNewFieldRef();
    Code:
       0: new           #13                 // class io/dekorate/deps/kubernetes/api/model/DownwardAPIVolumeFileFluentImpl$FieldRefNestedImpl
       3: dup
       4: aload_0
       5: invokespecial #129                // Method io/dekorate/deps/kubernetes/api/model/DownwardAPIVolumeFileFluentImpl$FieldRefNestedImpl."<init>":(Lio/dekorate/deps/kubernetes/api/model/DownwardAPIVolumeFileFluentImpl;)V
       8: areturn

  public io.dekorate.deps.kubernetes.api.model.DownwardAPIVolumeFileFluent$FieldRefNested<A> withNewFieldRefLike(io.dekorate.deps.kubernetes.api.model.ObjectFieldSelector);
    Code:
       0: new           #13                 // class io/dekorate/deps/kubernetes/api/model/DownwardAPIVolumeFileFluentImpl$FieldRefNestedImpl
       3: dup
       4: aload_0
       5: aload_1
       6: invokespecial #135                // Method io/dekorate/deps/kubernetes/api/model/DownwardAPIVolumeFileFluentImpl$FieldRefNestedImpl."<init>":(Lio/dekorate/deps/kubernetes/api/model/DownwardAPIVolumeFileFluentImpl;Lio/dekorate/deps/kubernetes/api/model/ObjectFieldSelector;)V
       9: areturn

  public io.dekorate.deps.kubernetes.api.model.DownwardAPIVolumeFileFluent$FieldRefNested<A> editFieldRef();
    Code:
       0: aload_0
       1: aload_0
       2: invokevirtual #138                // Method getFieldRef:()Lio/dekorate/deps/kubernetes/api/model/ObjectFieldSelector;
       5: invokevirtual #140                // Method withNewFieldRefLike:(Lio/dekorate/deps/kubernetes/api/model/ObjectFieldSelector;)Lio/dekorate/deps/kubernetes/api/model/DownwardAPIVolumeFileFluent$FieldRefNested;
       8: areturn

  public io.dekorate.deps.kubernetes.api.model.DownwardAPIVolumeFileFluent$FieldRefNested<A> editOrNewFieldRef();
    Code:
       0: aload_0
       1: aload_0
       2: invokevirtual #138                // Method getFieldRef:()Lio/dekorate/deps/kubernetes/api/model/ObjectFieldSelector;
       5: ifnull        15
       8: aload_0
       9: invokevirtual #138                // Method getFieldRef:()Lio/dekorate/deps/kubernetes/api/model/ObjectFieldSelector;
      12: goto          25
      15: new           #77                 // class io/dekorate/deps/kubernetes/api/model/ObjectFieldSelectorBuilder
      18: dup
      19: invokespecial #142                // Method io/dekorate/deps/kubernetes/api/model/ObjectFieldSelectorBuilder."<init>":()V
      22: invokevirtual #80                 // Method io/dekorate/deps/kubernetes/api/model/ObjectFieldSelectorBuilder.build:()Lio/dekorate/deps/kubernetes/api/model/ObjectFieldSelector;
      25: invokevirtual #140                // Method withNewFieldRefLike:(Lio/dekorate/deps/kubernetes/api/model/ObjectFieldSelector;)Lio/dekorate/deps/kubernetes/api/model/DownwardAPIVolumeFileFluent$FieldRefNested;
      28: areturn

  public io.dekorate.deps.kubernetes.api.model.DownwardAPIVolumeFileFluent$FieldRefNested<A> editOrNewFieldRefLike(io.dekorate.deps.kubernetes.api.model.ObjectFieldSelector);
    Code:
       0: aload_0
       1: aload_0
       2: invokevirtual #138                // Method getFieldRef:()Lio/dekorate/deps/kubernetes/api/model/ObjectFieldSelector;
       5: ifnull        15
       8: aload_0
       9: invokevirtual #138                // Method getFieldRef:()Lio/dekorate/deps/kubernetes/api/model/ObjectFieldSelector;
      12: goto          16
      15: aload_1
      16: invokevirtual #140                // Method withNewFieldRefLike:(Lio/dekorate/deps/kubernetes/api/model/ObjectFieldSelector;)Lio/dekorate/deps/kubernetes/api/model/DownwardAPIVolumeFileFluent$FieldRefNested;
      19: areturn

  public java.lang.Integer getMode();
    Code:
       0: aload_0
       1: getfield      #145                // Field mode:Ljava/lang/Integer;
       4: areturn

  public A withMode(java.lang.Integer);
    Code:
       0: aload_0
       1: aload_1
       2: putfield      #145                // Field mode:Ljava/lang/Integer;
       5: aload_0
       6: areturn

  public java.lang.Boolean hasMode();
    Code:
       0: aload_0
       1: getfield      #145                // Field mode:Ljava/lang/Integer;
       4: ifnull        11
       7: iconst_1
       8: goto          12
      11: iconst_0
      12: invokestatic  #116                // Method java/lang/Boolean.valueOf:(Z)Ljava/lang/Boolean;
      15: areturn

  public java.lang.String getPath();
    Code:
       0: aload_0
       1: getfield      #149                // Field path:Ljava/lang/String;
       4: areturn

  public A withPath(java.lang.String);
    Code:
       0: aload_0
       1: aload_1
       2: putfield      #149                // Field path:Ljava/lang/String;
       5: aload_0
       6: areturn

  public java.lang.Boolean hasPath();
    Code:
       0: aload_0
       1: getfield      #149                // Field path:Ljava/lang/String;
       4: ifnull        11
       7: iconst_1
       8: goto          12
      11: iconst_0
      12: invokestatic  #116                // Method java/lang/Boolean.valueOf:(Z)Ljava/lang/Boolean;
      15: areturn

  public A withNewPath(java.lang.String);
    Code:
       0: aload_0
       1: new           #154                // class java/lang/String
       4: dup
       5: aload_1
       6: invokespecial #157                // Method java/lang/String."<init>":(Ljava/lang/String;)V
       9: invokevirtual #62                 // Method withPath:(Ljava/lang/String;)Lio/dekorate/deps/kubernetes/api/model/DownwardAPIVolumeFileFluent;
      12: areturn

  public A withNewPath(java.lang.StringBuilder);
    Code:
       0: aload_0
       1: new           #154                // class java/lang/String
       4: dup
       5: aload_1
       6: invokespecial #163                // Method java/lang/String."<init>":(Ljava/lang/StringBuilder;)V
       9: invokevirtual #62                 // Method withPath:(Ljava/lang/String;)Lio/dekorate/deps/kubernetes/api/model/DownwardAPIVolumeFileFluent;
      12: areturn

  public A withNewPath(java.lang.StringBuffer);
    Code:
       0: aload_0
       1: new           #154                // class java/lang/String
       4: dup
       5: aload_1
       6: invokespecial #169                // Method java/lang/String."<init>":(Ljava/lang/StringBuffer;)V
       9: invokevirtual #62                 // Method withPath:(Ljava/lang/String;)Lio/dekorate/deps/kubernetes/api/model/DownwardAPIVolumeFileFluent;
      12: areturn

  public io.dekorate.deps.kubernetes.api.model.ResourceFieldSelector getResourceFieldRef();
    Code:
       0: aload_0
       1: getfield      #172                // Field resourceFieldRef:Lio/dekorate/deps/kubernetes/api/model/ResourceFieldSelectorBuilder;
       4: ifnull        17
       7: aload_0
       8: getfield      #172                // Field resourceFieldRef:Lio/dekorate/deps/kubernetes/api/model/ResourceFieldSelectorBuilder;
      11: invokevirtual #176                // Method io/dekorate/deps/kubernetes/api/model/ResourceFieldSelectorBuilder.build:()Lio/dekorate/deps/kubernetes/api/model/ResourceFieldSelector;
      14: goto          18
      17: aconst_null
      18: areturn

  public io.dekorate.deps.kubernetes.api.model.ResourceFieldSelector buildResourceFieldRef();
    Code:
       0: aload_0
       1: getfield      #172                // Field resourceFieldRef:Lio/dekorate/deps/kubernetes/api/model/ResourceFieldSelectorBuilder;
       4: ifnull        17
       7: aload_0
       8: getfield      #172                // Field resourceFieldRef:Lio/dekorate/deps/kubernetes/api/model/ResourceFieldSelectorBuilder;
      11: invokevirtual #176                // Method io/dekorate/deps/kubernetes/api/model/ResourceFieldSelectorBuilder.build:()Lio/dekorate/deps/kubernetes/api/model/ResourceFieldSelector;
      14: goto          18
      17: aconst_null
      18: areturn

  public A withResourceFieldRef(io.dekorate.deps.kubernetes.api.model.ResourceFieldSelector);
    Code:
       0: aload_0
       1: getfield      #88                 // Field _visitables:Lio/dekorate/deps/kubernetes/api/builder/VisitableMap;
       4: ldc           #181                // String resourceFieldRef
       6: invokevirtual #95                 // Method io/dekorate/deps/kubernetes/api/builder/VisitableMap.get:(Ljava/lang/Object;)Ljava/util/List;
       9: aload_0
      10: getfield      #172                // Field resourceFieldRef:Lio/dekorate/deps/kubernetes/api/model/ResourceFieldSelectorBuilder;
      13: invokeinterface #101,  2          // InterfaceMethod java/util/List.remove:(Ljava/lang/Object;)Z
      18: pop
      19: aload_1
      20: ifnull        54
      23: aload_0
      24: new           #174                // class io/dekorate/deps/kubernetes/api/model/ResourceFieldSelectorBuilder
      27: dup
      28: aload_1
      29: invokespecial #184                // Method io/dekorate/deps/kubernetes/api/model/ResourceFieldSelectorBuilder."<init>":(Lio/dekorate/deps/kubernetes/api/model/ResourceFieldSelector;)V
      32: putfield      #172                // Field resourceFieldRef:Lio/dekorate/deps/kubernetes/api/model/ResourceFieldSelectorBuilder;
      35: aload_0
      36: getfield      #88                 // Field _visitables:Lio/dekorate/deps/kubernetes/api/builder/VisitableMap;
      39: ldc           #181                // String resourceFieldRef
      41: invokevirtual #95                 // Method io/dekorate/deps/kubernetes/api/builder/VisitableMap.get:(Ljava/lang/Object;)Ljava/util/List;
      44: aload_0
      45: getfield      #172                // Field resourceFieldRef:Lio/dekorate/deps/kubernetes/api/model/ResourceFieldSelectorBuilder;
      48: invokeinterface #107,  2          // InterfaceMethod java/util/List.add:(Ljava/lang/Object;)Z
      53: pop
      54: aload_0
      55: areturn

  public java.lang.Boolean hasResourceFieldRef();
    Code:
       0: aload_0
       1: getfield      #172                // Field resourceFieldRef:Lio/dekorate/deps/kubernetes/api/model/ResourceFieldSelectorBuilder;
       4: ifnull        11
       7: iconst_1
       8: goto          12
      11: iconst_0
      12: invokestatic  #116                // Method java/lang/Boolean.valueOf:(Z)Ljava/lang/Boolean;
      15: areturn

  public io.dekorate.deps.kubernetes.api.model.DownwardAPIVolumeFileFluent$ResourceFieldRefNested<A> withNewResourceFieldRef();
    Code:
       0: new           #10                 // class io/dekorate/deps/kubernetes/api/model/DownwardAPIVolumeFileFluentImpl$ResourceFieldRefNestedImpl
       3: dup
       4: aload_0
       5: invokespecial #190                // Method io/dekorate/deps/kubernetes/api/model/DownwardAPIVolumeFileFluentImpl$ResourceFieldRefNestedImpl."<init>":(Lio/dekorate/deps/kubernetes/api/model/DownwardAPIVolumeFileFluentImpl;)V
       8: areturn

  public io.dekorate.deps.kubernetes.api.model.DownwardAPIVolumeFileFluent$ResourceFieldRefNested<A> withNewResourceFieldRefLike(io.dekorate.deps.kubernetes.api.model.ResourceFieldSelector);
    Code:
       0: new           #10                 // class io/dekorate/deps/kubernetes/api/model/DownwardAPIVolumeFileFluentImpl$ResourceFieldRefNestedImpl
       3: dup
       4: aload_0
       5: aload_1
       6: invokespecial #196                // Method io/dekorate/deps/kubernetes/api/model/DownwardAPIVolumeFileFluentImpl$ResourceFieldRefNestedImpl."<init>":(Lio/dekorate/deps/kubernetes/api/model/DownwardAPIVolumeFileFluentImpl;Lio/dekorate/deps/kubernetes/api/model/ResourceFieldSelector;)V
       9: areturn

  public io.dekorate.deps.kubernetes.api.model.DownwardAPIVolumeFileFluent$ResourceFieldRefNested<A> editResourceFieldRef();
    Code:
       0: aload_0
       1: aload_0
       2: invokevirtual #198                // Method getResourceFieldRef:()Lio/dekorate/deps/kubernetes/api/model/ResourceFieldSelector;
       5: invokevirtual #200                // Method withNewResourceFieldRefLike:(Lio/dekorate/deps/kubernetes/api/model/ResourceFieldSelector;)Lio/dekorate/deps/kubernetes/api/model/DownwardAPIVolumeFileFluent$ResourceFieldRefNested;
       8: areturn

  public io.dekorate.deps.kubernetes.api.model.DownwardAPIVolumeFileFluent$ResourceFieldRefNested<A> editOrNewResourceFieldRef();
    Code:
       0: aload_0
       1: aload_0
       2: invokevirtual #198                // Method getResourceFieldRef:()Lio/dekorate/deps/kubernetes/api/model/ResourceFieldSelector;
       5: ifnull        15
       8: aload_0
       9: invokevirtual #198                // Method getResourceFieldRef:()Lio/dekorate/deps/kubernetes/api/model/ResourceFieldSelector;
      12: goto          25
      15: new           #174                // class io/dekorate/deps/kubernetes/api/model/ResourceFieldSelectorBuilder
      18: dup
      19: invokespecial #202                // Method io/dekorate/deps/kubernetes/api/model/ResourceFieldSelectorBuilder."<init>":()V
      22: invokevirtual #176                // Method io/dekorate/deps/kubernetes/api/model/ResourceFieldSelectorBuilder.build:()Lio/dekorate/deps/kubernetes/api/model/ResourceFieldSelector;
      25: invokevirtual #200                // Method withNewResourceFieldRefLike:(Lio/dekorate/deps/kubernetes/api/model/ResourceFieldSelector;)Lio/dekorate/deps/kubernetes/api/model/DownwardAPIVolumeFileFluent$ResourceFieldRefNested;
      28: areturn

  public io.dekorate.deps.kubernetes.api.model.DownwardAPIVolumeFileFluent$ResourceFieldRefNested<A> editOrNewResourceFieldRefLike(io.dekorate.deps.kubernetes.api.model.ResourceFieldSelector);
    Code:
       0: aload_0
       1: aload_0
       2: invokevirtual #198                // Method getResourceFieldRef:()Lio/dekorate/deps/kubernetes/api/model/ResourceFieldSelector;
       5: ifnull        15
       8: aload_0
       9: invokevirtual #198                // Method getResourceFieldRef:()Lio/dekorate/deps/kubernetes/api/model/ResourceFieldSelector;
      12: goto          16
      15: aload_1
      16: invokevirtual #200                // Method withNewResourceFieldRefLike:(Lio/dekorate/deps/kubernetes/api/model/ResourceFieldSelector;)Lio/dekorate/deps/kubernetes/api/model/DownwardAPIVolumeFileFluent$ResourceFieldRefNested;
      19: areturn

  public boolean equals(java.lang.Object);
    Code:
       0: aload_0
       1: aload_1
       2: if_acmpne     7
       5: iconst_1
       6: ireturn
       7: aload_1
       8: ifnull        22
      11: aload_0
      12: invokevirtual #210                // Method java/lang/Object.getClass:()Ljava/lang/Class;
      15: aload_1
      16: invokevirtual #210                // Method java/lang/Object.getClass:()Ljava/lang/Class;
      19: if_acmpeq     24
      22: iconst_0
      23: ireturn
      24: aload_1
      25: checkcast     #2                  // class io/dekorate/deps/kubernetes/api/model/DownwardAPIVolumeFileFluentImpl
      28: astore_2
      29: aload_0
      30: getfield      #75                 // Field fieldRef:Lio/dekorate/deps/kubernetes/api/model/ObjectFieldSelectorBuilder;
      33: ifnull        53
      36: aload_0
      37: getfield      #75                 // Field fieldRef:Lio/dekorate/deps/kubernetes/api/model/ObjectFieldSelectorBuilder;
      40: aload_2
      41: getfield      #75                 // Field fieldRef:Lio/dekorate/deps/kubernetes/api/model/ObjectFieldSelectorBuilder;
      44: invokevirtual #212                // Method io/dekorate/deps/kubernetes/api/model/ObjectFieldSelectorBuilder.equals:(Ljava/lang/Object;)Z
      47: ifne          62
      50: goto          60
      53: aload_2
      54: getfield      #75                 // Field fieldRef:Lio/dekorate/deps/kubernetes/api/model/ObjectFieldSelectorBuilder;
      57: ifnull        62
      60: iconst_0
      61: ireturn
      62: aload_0
      63: getfield      #145                // Field mode:Ljava/lang/Integer;
      66: ifnull        86
      69: aload_0
      70: getfield      #145                // Field mode:Ljava/lang/Integer;
      73: aload_2
      74: getfield      #145                // Field mode:Ljava/lang/Integer;
      77: invokevirtual #215                // Method java/lang/Integer.equals:(Ljava/lang/Object;)Z
      80: ifne          95
      83: goto          93
      86: aload_2
      87: getfield      #145                // Field mode:Ljava/lang/Integer;
      90: ifnull        95
      93: iconst_0
      94: ireturn
      95: aload_0
      96: getfield      #149                // Field path:Ljava/lang/String;
      99: ifnull        119
     102: aload_0
     103: getfield      #149                // Field path:Ljava/lang/String;
     106: aload_2
     107: getfield      #149                // Field path:Ljava/lang/String;
     110: invokevirtual #216                // Method java/lang/String.equals:(Ljava/lang/Object;)Z
     113: ifne          128
     116: goto          126
     119: aload_2
     120: getfield      #149                // Field path:Ljava/lang/String;
     123: ifnull        128
     126: iconst_0
     127: ireturn
     128: aload_0
     129: getfield      #172                // Field resourceFieldRef:Lio/dekorate/deps/kubernetes/api/model/ResourceFieldSelectorBuilder;
     132: ifnull        152
     135: aload_0
     136: getfield      #172                // Field resourceFieldRef:Lio/dekorate/deps/kubernetes/api/model/ResourceFieldSelectorBuilder;
     139: aload_2
     140: getfield      #172                // Field resourceFieldRef:Lio/dekorate/deps/kubernetes/api/model/ResourceFieldSelectorBuilder;
     143: invokevirtual #217                // Method io/dekorate/deps/kubernetes/api/model/ResourceFieldSelectorBuilder.equals:(Ljava/lang/Object;)Z
     146: ifne          161
     149: goto          159
     152: aload_2
     153: getfield      #172                // Field resourceFieldRef:Lio/dekorate/deps/kubernetes/api/model/ResourceFieldSelectorBuilder;
     156: ifnull        161
     159: iconst_0
     160: ireturn
     161: iconst_1
     162: ireturn
}
