Compiled from "EnvVarFluentImpl.java"
public class io.dekorate.deps.kubernetes.api.model.EnvVarFluentImpl<A extends io.dekorate.deps.kubernetes.api.model.EnvVarFluent<A>> extends io.dekorate.deps.kubernetes.api.builder.BaseFluent<A> implements io.dekorate.deps.kubernetes.api.model.EnvVarFluent<A> {
  private java.lang.String name;

  private java.lang.String value;

  private io.dekorate.deps.kubernetes.api.model.EnvVarSourceBuilder valueFrom;

  public io.dekorate.deps.kubernetes.api.model.EnvVarFluentImpl();
    Code:
       0: aload_0
       1: invokespecial #23                 // Method io/dekorate/deps/kubernetes/api/builder/BaseFluent."<init>":()V
       4: return

  public io.dekorate.deps.kubernetes.api.model.EnvVarFluentImpl(io.dekorate.deps.kubernetes.api.model.EnvVar);
    Code:
       0: aload_0
       1: invokespecial #23                 // Method io/dekorate/deps/kubernetes/api/builder/BaseFluent."<init>":()V
       4: aload_0
       5: aload_1
       6: invokevirtual #33                 // Method io/dekorate/deps/kubernetes/api/model/EnvVar.getName:()Ljava/lang/String;
       9: invokevirtual #37                 // Method withName:(Ljava/lang/String;)Lio/dekorate/deps/kubernetes/api/model/EnvVarFluent;
      12: pop
      13: aload_0
      14: aload_1
      15: invokevirtual #40                 // Method io/dekorate/deps/kubernetes/api/model/EnvVar.getValue:()Ljava/lang/String;
      18: invokevirtual #43                 // Method withValue:(Ljava/lang/String;)Lio/dekorate/deps/kubernetes/api/model/EnvVarFluent;
      21: pop
      22: aload_0
      23: aload_1
      24: invokevirtual #47                 // Method io/dekorate/deps/kubernetes/api/model/EnvVar.getValueFrom:()Lio/dekorate/deps/kubernetes/api/model/EnvVarSource;
      27: invokevirtual #51                 // Method withValueFrom:(Lio/dekorate/deps/kubernetes/api/model/EnvVarSource;)Lio/dekorate/deps/kubernetes/api/model/EnvVarFluent;
      30: pop
      31: return

  public java.lang.String getName();
    Code:
       0: aload_0
       1: getfield      #55                 // Field name:Ljava/lang/String;
       4: areturn

  public A withName(java.lang.String);
    Code:
       0: aload_0
       1: aload_1
       2: putfield      #55                 // Field name:Ljava/lang/String;
       5: aload_0
       6: areturn

  public java.lang.Boolean hasName();
    Code:
       0: aload_0
       1: getfield      #55                 // Field name:Ljava/lang/String;
       4: ifnull        11
       7: iconst_1
       8: goto          12
      11: iconst_0
      12: invokestatic  #64                 // Method java/lang/Boolean.valueOf:(Z)Ljava/lang/Boolean;
      15: areturn

  public A withNewName(java.lang.String);
    Code:
       0: aload_0
       1: new           #67                 // class java/lang/String
       4: dup
       5: aload_1
       6: invokespecial #70                 // Method java/lang/String."<init>":(Ljava/lang/String;)V
       9: invokevirtual #37                 // Method withName:(Ljava/lang/String;)Lio/dekorate/deps/kubernetes/api/model/EnvVarFluent;
      12: areturn

  public A withNewName(java.lang.StringBuilder);
    Code:
       0: aload_0
       1: new           #67                 // class java/lang/String
       4: dup
       5: aload_1
       6: invokespecial #76                 // Method java/lang/String."<init>":(Ljava/lang/StringBuilder;)V
       9: invokevirtual #37                 // Method withName:(Ljava/lang/String;)Lio/dekorate/deps/kubernetes/api/model/EnvVarFluent;
      12: areturn

  public A withNewName(java.lang.StringBuffer);
    Code:
       0: aload_0
       1: new           #67                 // class java/lang/String
       4: dup
       5: aload_1
       6: invokespecial #82                 // Method java/lang/String."<init>":(Ljava/lang/StringBuffer;)V
       9: invokevirtual #37                 // Method withName:(Ljava/lang/String;)Lio/dekorate/deps/kubernetes/api/model/EnvVarFluent;
      12: areturn

  public java.lang.String getValue();
    Code:
       0: aload_0
       1: getfield      #85                 // Field value:Ljava/lang/String;
       4: areturn

  public A withValue(java.lang.String);
    Code:
       0: aload_0
       1: aload_1
       2: putfield      #85                 // Field value:Ljava/lang/String;
       5: aload_0
       6: areturn

  public java.lang.Boolean hasValue();
    Code:
       0: aload_0
       1: getfield      #85                 // Field value:Ljava/lang/String;
       4: ifnull        11
       7: iconst_1
       8: goto          12
      11: iconst_0
      12: invokestatic  #64                 // Method java/lang/Boolean.valueOf:(Z)Ljava/lang/Boolean;
      15: areturn

  public A withNewValue(java.lang.String);
    Code:
       0: aload_0
       1: new           #67                 // class java/lang/String
       4: dup
       5: aload_1
       6: invokespecial #70                 // Method java/lang/String."<init>":(Ljava/lang/String;)V
       9: invokevirtual #43                 // Method withValue:(Ljava/lang/String;)Lio/dekorate/deps/kubernetes/api/model/EnvVarFluent;
      12: areturn

  public A withNewValue(java.lang.StringBuilder);
    Code:
       0: aload_0
       1: new           #67                 // class java/lang/String
       4: dup
       5: aload_1
       6: invokespecial #76                 // Method java/lang/String."<init>":(Ljava/lang/StringBuilder;)V
       9: invokevirtual #43                 // Method withValue:(Ljava/lang/String;)Lio/dekorate/deps/kubernetes/api/model/EnvVarFluent;
      12: areturn

  public A withNewValue(java.lang.StringBuffer);
    Code:
       0: aload_0
       1: new           #67                 // class java/lang/String
       4: dup
       5: aload_1
       6: invokespecial #82                 // Method java/lang/String."<init>":(Ljava/lang/StringBuffer;)V
       9: invokevirtual #43                 // Method withValue:(Ljava/lang/String;)Lio/dekorate/deps/kubernetes/api/model/EnvVarFluent;
      12: areturn

  public io.dekorate.deps.kubernetes.api.model.EnvVarSource getValueFrom();
    Code:
       0: aload_0
       1: getfield      #90                 // Field valueFrom:Lio/dekorate/deps/kubernetes/api/model/EnvVarSourceBuilder;
       4: ifnull        17
       7: aload_0
       8: getfield      #90                 // Field valueFrom:Lio/dekorate/deps/kubernetes/api/model/EnvVarSourceBuilder;
      11: invokevirtual #95                 // Method io/dekorate/deps/kubernetes/api/model/EnvVarSourceBuilder.build:()Lio/dekorate/deps/kubernetes/api/model/EnvVarSource;
      14: goto          18
      17: aconst_null
      18: areturn

  public io.dekorate.deps.kubernetes.api.model.EnvVarSource buildValueFrom();
    Code:
       0: aload_0
       1: getfield      #90                 // Field valueFrom:Lio/dekorate/deps/kubernetes/api/model/EnvVarSourceBuilder;
       4: ifnull        17
       7: aload_0
       8: getfield      #90                 // Field valueFrom:Lio/dekorate/deps/kubernetes/api/model/EnvVarSourceBuilder;
      11: invokevirtual #95                 // Method io/dekorate/deps/kubernetes/api/model/EnvVarSourceBuilder.build:()Lio/dekorate/deps/kubernetes/api/model/EnvVarSource;
      14: goto          18
      17: aconst_null
      18: areturn

  public A withValueFrom(io.dekorate.deps.kubernetes.api.model.EnvVarSource);
    Code:
       0: aload_0
       1: getfield      #103                // Field _visitables:Lio/dekorate/deps/kubernetes/api/builder/VisitableMap;
       4: ldc           #104                // String valueFrom
       6: invokevirtual #110                // Method io/dekorate/deps/kubernetes/api/builder/VisitableMap.get:(Ljava/lang/Object;)Ljava/util/List;
       9: aload_0
      10: getfield      #90                 // Field valueFrom:Lio/dekorate/deps/kubernetes/api/model/EnvVarSourceBuilder;
      13: invokeinterface #116,  2          // InterfaceMethod java/util/List.remove:(Ljava/lang/Object;)Z
      18: pop
      19: aload_1
      20: ifnull        54
      23: aload_0
      24: new           #92                 // class io/dekorate/deps/kubernetes/api/model/EnvVarSourceBuilder
      27: dup
      28: aload_1
      29: invokespecial #119                // Method io/dekorate/deps/kubernetes/api/model/EnvVarSourceBuilder."<init>":(Lio/dekorate/deps/kubernetes/api/model/EnvVarSource;)V
      32: putfield      #90                 // Field valueFrom:Lio/dekorate/deps/kubernetes/api/model/EnvVarSourceBuilder;
      35: aload_0
      36: getfield      #103                // Field _visitables:Lio/dekorate/deps/kubernetes/api/builder/VisitableMap;
      39: ldc           #104                // String valueFrom
      41: invokevirtual #110                // Method io/dekorate/deps/kubernetes/api/builder/VisitableMap.get:(Ljava/lang/Object;)Ljava/util/List;
      44: aload_0
      45: getfield      #90                 // Field valueFrom:Lio/dekorate/deps/kubernetes/api/model/EnvVarSourceBuilder;
      48: invokeinterface #122,  2          // InterfaceMethod java/util/List.add:(Ljava/lang/Object;)Z
      53: pop
      54: aload_0
      55: areturn

  public java.lang.Boolean hasValueFrom();
    Code:
       0: aload_0
       1: getfield      #90                 // Field valueFrom:Lio/dekorate/deps/kubernetes/api/model/EnvVarSourceBuilder;
       4: ifnull        11
       7: iconst_1
       8: goto          12
      11: iconst_0
      12: invokestatic  #64                 // Method java/lang/Boolean.valueOf:(Z)Ljava/lang/Boolean;
      15: areturn

  public io.dekorate.deps.kubernetes.api.model.EnvVarFluent$ValueFromNested<A> withNewValueFrom();
    Code:
       0: new           #10                 // class io/dekorate/deps/kubernetes/api/model/EnvVarFluentImpl$ValueFromNestedImpl
       3: dup
       4: aload_0
       5: invokespecial #130                // Method io/dekorate/deps/kubernetes/api/model/EnvVarFluentImpl$ValueFromNestedImpl."<init>":(Lio/dekorate/deps/kubernetes/api/model/EnvVarFluentImpl;)V
       8: areturn

  public io.dekorate.deps.kubernetes.api.model.EnvVarFluent$ValueFromNested<A> withNewValueFromLike(io.dekorate.deps.kubernetes.api.model.EnvVarSource);
    Code:
       0: new           #10                 // class io/dekorate/deps/kubernetes/api/model/EnvVarFluentImpl$ValueFromNestedImpl
       3: dup
       4: aload_0
       5: aload_1
       6: invokespecial #136                // Method io/dekorate/deps/kubernetes/api/model/EnvVarFluentImpl$ValueFromNestedImpl."<init>":(Lio/dekorate/deps/kubernetes/api/model/EnvVarFluentImpl;Lio/dekorate/deps/kubernetes/api/model/EnvVarSource;)V
       9: areturn

  public io.dekorate.deps.kubernetes.api.model.EnvVarFluent$ValueFromNested<A> editValueFrom();
    Code:
       0: aload_0
       1: aload_0
       2: invokevirtual #139                // Method getValueFrom:()Lio/dekorate/deps/kubernetes/api/model/EnvVarSource;
       5: invokevirtual #141                // Method withNewValueFromLike:(Lio/dekorate/deps/kubernetes/api/model/EnvVarSource;)Lio/dekorate/deps/kubernetes/api/model/EnvVarFluent$ValueFromNested;
       8: areturn

  public io.dekorate.deps.kubernetes.api.model.EnvVarFluent$ValueFromNested<A> editOrNewValueFrom();
    Code:
       0: aload_0
       1: aload_0
       2: invokevirtual #139                // Method getValueFrom:()Lio/dekorate/deps/kubernetes/api/model/EnvVarSource;
       5: ifnull        15
       8: aload_0
       9: invokevirtual #139                // Method getValueFrom:()Lio/dekorate/deps/kubernetes/api/model/EnvVarSource;
      12: goto          25
      15: new           #92                 // class io/dekorate/deps/kubernetes/api/model/EnvVarSourceBuilder
      18: dup
      19: invokespecial #143                // Method io/dekorate/deps/kubernetes/api/model/EnvVarSourceBuilder."<init>":()V
      22: invokevirtual #95                 // Method io/dekorate/deps/kubernetes/api/model/EnvVarSourceBuilder.build:()Lio/dekorate/deps/kubernetes/api/model/EnvVarSource;
      25: invokevirtual #141                // Method withNewValueFromLike:(Lio/dekorate/deps/kubernetes/api/model/EnvVarSource;)Lio/dekorate/deps/kubernetes/api/model/EnvVarFluent$ValueFromNested;
      28: areturn

  public io.dekorate.deps.kubernetes.api.model.EnvVarFluent$ValueFromNested<A> editOrNewValueFromLike(io.dekorate.deps.kubernetes.api.model.EnvVarSource);
    Code:
       0: aload_0
       1: aload_0
       2: invokevirtual #139                // Method getValueFrom:()Lio/dekorate/deps/kubernetes/api/model/EnvVarSource;
       5: ifnull        15
       8: aload_0
       9: invokevirtual #139                // Method getValueFrom:()Lio/dekorate/deps/kubernetes/api/model/EnvVarSource;
      12: goto          16
      15: aload_1
      16: invokevirtual #141                // Method withNewValueFromLike:(Lio/dekorate/deps/kubernetes/api/model/EnvVarSource;)Lio/dekorate/deps/kubernetes/api/model/EnvVarFluent$ValueFromNested;
      19: areturn

  public boolean equals(java.lang.Object);
    Code:
       0: aload_0
       1: aload_1
       2: if_acmpne     7
       5: iconst_1
       6: ireturn
       7: aload_1
       8: ifnull        22
      11: aload_0
      12: invokevirtual #151                // Method java/lang/Object.getClass:()Ljava/lang/Class;
      15: aload_1
      16: invokevirtual #151                // Method java/lang/Object.getClass:()Ljava/lang/Class;
      19: if_acmpeq     24
      22: iconst_0
      23: ireturn
      24: aload_1
      25: checkcast     #2                  // class io/dekorate/deps/kubernetes/api/model/EnvVarFluentImpl
      28: astore_2
      29: aload_0
      30: getfield      #55                 // Field name:Ljava/lang/String;
      33: ifnull        53
      36: aload_0
      37: getfield      #55                 // Field name:Ljava/lang/String;
      40: aload_2
      41: getfield      #55                 // Field name:Ljava/lang/String;
      44: invokevirtual #153                // Method java/lang/String.equals:(Ljava/lang/Object;)Z
      47: ifne          62
      50: goto          60
      53: aload_2
      54: getfield      #55                 // Field name:Ljava/lang/String;
      57: ifnull        62
      60: iconst_0
      61: ireturn
      62: aload_0
      63: getfield      #85                 // Field value:Ljava/lang/String;
      66: ifnull        86
      69: aload_0
      70: getfield      #85                 // Field value:Ljava/lang/String;
      73: aload_2
      74: getfield      #85                 // Field value:Ljava/lang/String;
      77: invokevirtual #153                // Method java/lang/String.equals:(Ljava/lang/Object;)Z
      80: ifne          95
      83: goto          93
      86: aload_2
      87: getfield      #85                 // Field value:Ljava/lang/String;
      90: ifnull        95
      93: iconst_0
      94: ireturn
      95: aload_0
      96: getfield      #90                 // Field valueFrom:Lio/dekorate/deps/kubernetes/api/model/EnvVarSourceBuilder;
      99: ifnull        119
     102: aload_0
     103: getfield      #90                 // Field valueFrom:Lio/dekorate/deps/kubernetes/api/model/EnvVarSourceBuilder;
     106: aload_2
     107: getfield      #90                 // Field valueFrom:Lio/dekorate/deps/kubernetes/api/model/EnvVarSourceBuilder;
     110: invokevirtual #154                // Method io/dekorate/deps/kubernetes/api/model/EnvVarSourceBuilder.equals:(Ljava/lang/Object;)Z
     113: ifne          128
     116: goto          126
     119: aload_2
     120: getfield      #90                 // Field valueFrom:Lio/dekorate/deps/kubernetes/api/model/EnvVarSourceBuilder;
     123: ifnull        128
     126: iconst_0
     127: ireturn
     128: iconst_1
     129: ireturn
}
