Compiled from "HorizontalPodAutoscalerStatusFluentImpl.java"
public class io.dekorate.deps.kubernetes.api.model.HorizontalPodAutoscalerStatusFluentImpl<A extends io.dekorate.deps.kubernetes.api.model.HorizontalPodAutoscalerStatusFluent<A>> extends io.dekorate.deps.kubernetes.api.builder.BaseFluent<A> implements io.dekorate.deps.kubernetes.api.model.HorizontalPodAutoscalerStatusFluent<A> {
  private java.util.List<io.dekorate.deps.kubernetes.api.model.HorizontalPodAutoscalerConditionBuilder> conditions;

  private java.util.List<io.dekorate.deps.kubernetes.api.model.MetricStatusBuilder> currentMetrics;

  private java.lang.Integer currentReplicas;

  private java.lang.Integer desiredReplicas;

  private java.lang.String lastScaleTime;

  private java.lang.Long observedGeneration;

  public io.dekorate.deps.kubernetes.api.model.HorizontalPodAutoscalerStatusFluentImpl();
    Code:
       0: aload_0
       1: invokespecial #36                 // Method io/dekorate/deps/kubernetes/api/builder/BaseFluent."<init>":()V
       4: aload_0
       5: new           #38                 // class java/util/ArrayList
       8: dup
       9: invokespecial #39                 // Method java/util/ArrayList."<init>":()V
      12: putfield      #41                 // Field conditions:Ljava/util/List;
      15: aload_0
      16: new           #38                 // class java/util/ArrayList
      19: dup
      20: invokespecial #39                 // Method java/util/ArrayList."<init>":()V
      23: putfield      #43                 // Field currentMetrics:Ljava/util/List;
      26: return

  public io.dekorate.deps.kubernetes.api.model.HorizontalPodAutoscalerStatusFluentImpl(io.dekorate.deps.kubernetes.api.model.HorizontalPodAutoscalerStatus);
    Code:
       0: aload_0
       1: invokespecial #36                 // Method io/dekorate/deps/kubernetes/api/builder/BaseFluent."<init>":()V
       4: aload_0
       5: new           #38                 // class java/util/ArrayList
       8: dup
       9: invokespecial #39                 // Method java/util/ArrayList."<init>":()V
      12: putfield      #41                 // Field conditions:Ljava/util/List;
      15: aload_0
      16: new           #38                 // class java/util/ArrayList
      19: dup
      20: invokespecial #39                 // Method java/util/ArrayList."<init>":()V
      23: putfield      #43                 // Field currentMetrics:Ljava/util/List;
      26: aload_0
      27: aload_1
      28: invokevirtual #53                 // Method io/dekorate/deps/kubernetes/api/model/HorizontalPodAutoscalerStatus.getConditions:()Ljava/util/List;
      31: invokevirtual #57                 // Method withConditions:(Ljava/util/List;)Lio/dekorate/deps/kubernetes/api/model/HorizontalPodAutoscalerStatusFluent;
      34: pop
      35: aload_0
      36: aload_1
      37: invokevirtual #60                 // Method io/dekorate/deps/kubernetes/api/model/HorizontalPodAutoscalerStatus.getCurrentMetrics:()Ljava/util/List;
      40: invokevirtual #63                 // Method withCurrentMetrics:(Ljava/util/List;)Lio/dekorate/deps/kubernetes/api/model/HorizontalPodAutoscalerStatusFluent;
      43: pop
      44: aload_0
      45: aload_1
      46: invokevirtual #67                 // Method io/dekorate/deps/kubernetes/api/model/HorizontalPodAutoscalerStatus.getCurrentReplicas:()Ljava/lang/Integer;
      49: invokevirtual #71                 // Method withCurrentReplicas:(Ljava/lang/Integer;)Lio/dekorate/deps/kubernetes/api/model/HorizontalPodAutoscalerStatusFluent;
      52: pop
      53: aload_0
      54: aload_1
      55: invokevirtual #74                 // Method io/dekorate/deps/kubernetes/api/model/HorizontalPodAutoscalerStatus.getDesiredReplicas:()Ljava/lang/Integer;
      58: invokevirtual #77                 // Method withDesiredReplicas:(Ljava/lang/Integer;)Lio/dekorate/deps/kubernetes/api/model/HorizontalPodAutoscalerStatusFluent;
      61: pop
      62: aload_0
      63: aload_1
      64: invokevirtual #81                 // Method io/dekorate/deps/kubernetes/api/model/HorizontalPodAutoscalerStatus.getLastScaleTime:()Ljava/lang/String;
      67: invokevirtual #85                 // Method withLastScaleTime:(Ljava/lang/String;)Lio/dekorate/deps/kubernetes/api/model/HorizontalPodAutoscalerStatusFluent;
      70: pop
      71: aload_0
      72: aload_1
      73: invokevirtual #89                 // Method io/dekorate/deps/kubernetes/api/model/HorizontalPodAutoscalerStatus.getObservedGeneration:()Ljava/lang/Long;
      76: invokevirtual #93                 // Method withObservedGeneration:(Ljava/lang/Long;)Lio/dekorate/deps/kubernetes/api/model/HorizontalPodAutoscalerStatusFluent;
      79: pop
      80: return

  public A addToConditions(int, io.dekorate.deps.kubernetes.api.model.HorizontalPodAutoscalerCondition);
    Code:
       0: aload_0
       1: getfield      #41                 // Field conditions:Ljava/util/List;
       4: ifnonnull     18
       7: aload_0
       8: new           #38                 // class java/util/ArrayList
      11: dup
      12: invokespecial #39                 // Method java/util/ArrayList."<init>":()V
      15: putfield      #41                 // Field conditions:Ljava/util/List;
      18: new           #100                // class io/dekorate/deps/kubernetes/api/model/HorizontalPodAutoscalerConditionBuilder
      21: dup
      22: aload_2
      23: invokespecial #103                // Method io/dekorate/deps/kubernetes/api/model/HorizontalPodAutoscalerConditionBuilder."<init>":(Lio/dekorate/deps/kubernetes/api/model/HorizontalPodAutoscalerCondition;)V
      26: astore_3
      27: aload_0
      28: getfield      #107                // Field _visitables:Lio/dekorate/deps/kubernetes/api/builder/VisitableMap;
      31: ldc           #108                // String conditions
      33: invokevirtual #114                // Method io/dekorate/deps/kubernetes/api/builder/VisitableMap.get:(Ljava/lang/Object;)Ljava/util/List;
      36: iload_1
      37: iflt          44
      40: iload_1
      41: goto          58
      44: aload_0
      45: getfield      #107                // Field _visitables:Lio/dekorate/deps/kubernetes/api/builder/VisitableMap;
      48: ldc           #108                // String conditions
      50: invokevirtual #114                // Method io/dekorate/deps/kubernetes/api/builder/VisitableMap.get:(Ljava/lang/Object;)Ljava/util/List;
      53: invokeinterface #122,  1          // InterfaceMethod java/util/List.size:()I
      58: aload_3
      59: invokeinterface #126,  3          // InterfaceMethod java/util/List.add:(ILjava/lang/Object;)V
      64: aload_0
      65: getfield      #41                 // Field conditions:Ljava/util/List;
      68: iload_1
      69: iflt          76
      72: iload_1
      73: goto          85
      76: aload_0
      77: getfield      #41                 // Field conditions:Ljava/util/List;
      80: invokeinterface #122,  1          // InterfaceMethod java/util/List.size:()I
      85: aload_3
      86: invokeinterface #126,  3          // InterfaceMethod java/util/List.add:(ILjava/lang/Object;)V
      91: aload_0
      92: areturn

  public A setToConditions(int, io.dekorate.deps.kubernetes.api.model.HorizontalPodAutoscalerCondition);
    Code:
       0: aload_0
       1: getfield      #41                 // Field conditions:Ljava/util/List;
       4: ifnonnull     18
       7: aload_0
       8: new           #38                 // class java/util/ArrayList
      11: dup
      12: invokespecial #39                 // Method java/util/ArrayList."<init>":()V
      15: putfield      #41                 // Field conditions:Ljava/util/List;
      18: new           #100                // class io/dekorate/deps/kubernetes/api/model/HorizontalPodAutoscalerConditionBuilder
      21: dup
      22: aload_2
      23: invokespecial #103                // Method io/dekorate/deps/kubernetes/api/model/HorizontalPodAutoscalerConditionBuilder."<init>":(Lio/dekorate/deps/kubernetes/api/model/HorizontalPodAutoscalerCondition;)V
      26: astore_3
      27: iload_1
      28: iflt          49
      31: iload_1
      32: aload_0
      33: getfield      #107                // Field _visitables:Lio/dekorate/deps/kubernetes/api/builder/VisitableMap;
      36: ldc           #108                // String conditions
      38: invokevirtual #114                // Method io/dekorate/deps/kubernetes/api/builder/VisitableMap.get:(Ljava/lang/Object;)Ljava/util/List;
      41: invokeinterface #122,  1          // InterfaceMethod java/util/List.size:()I
      46: if_icmplt     68
      49: aload_0
      50: getfield      #107                // Field _visitables:Lio/dekorate/deps/kubernetes/api/builder/VisitableMap;
      53: ldc           #108                // String conditions
      55: invokevirtual #114                // Method io/dekorate/deps/kubernetes/api/builder/VisitableMap.get:(Ljava/lang/Object;)Ljava/util/List;
      58: aload_3
      59: invokeinterface #136,  2          // InterfaceMethod java/util/List.add:(Ljava/lang/Object;)Z
      64: pop
      65: goto          85
      68: aload_0
      69: getfield      #107                // Field _visitables:Lio/dekorate/deps/kubernetes/api/builder/VisitableMap;
      72: ldc           #108                // String conditions
      74: invokevirtual #114                // Method io/dekorate/deps/kubernetes/api/builder/VisitableMap.get:(Ljava/lang/Object;)Ljava/util/List;
      77: iload_1
      78: aload_3
      79: invokeinterface #140,  3          // InterfaceMethod java/util/List.set:(ILjava/lang/Object;)Ljava/lang/Object;
      84: pop
      85: iload_1
      86: iflt          102
      89: iload_1
      90: aload_0
      91: getfield      #41                 // Field conditions:Ljava/util/List;
      94: invokeinterface #122,  1          // InterfaceMethod java/util/List.size:()I
      99: if_icmplt     116
     102: aload_0
     103: getfield      #41                 // Field conditions:Ljava/util/List;
     106: aload_3
     107: invokeinterface #136,  2          // InterfaceMethod java/util/List.add:(Ljava/lang/Object;)Z
     112: pop
     113: goto          128
     116: aload_0
     117: getfield      #41                 // Field conditions:Ljava/util/List;
     120: iload_1
     121: aload_3
     122: invokeinterface #140,  3          // InterfaceMethod java/util/List.set:(ILjava/lang/Object;)Ljava/lang/Object;
     127: pop
     128: aload_0
     129: areturn

  public A addToConditions(io.dekorate.deps.kubernetes.api.model.HorizontalPodAutoscalerCondition...);
    Code:
       0: aload_0
       1: getfield      #41                 // Field conditions:Ljava/util/List;
       4: ifnonnull     18
       7: aload_0
       8: new           #38                 // class java/util/ArrayList
      11: dup
      12: invokespecial #39                 // Method java/util/ArrayList."<init>":()V
      15: putfield      #41                 // Field conditions:Ljava/util/List;
      18: aload_1
      19: astore_2
      20: aload_2
      21: arraylength
      22: istore_3
      23: iconst_0
      24: istore        4
      26: iload         4
      28: iload_3
      29: if_icmpge     84
      32: aload_2
      33: iload         4
      35: aaload
      36: astore        5
      38: new           #100                // class io/dekorate/deps/kubernetes/api/model/HorizontalPodAutoscalerConditionBuilder
      41: dup
      42: aload         5
      44: invokespecial #103                // Method io/dekorate/deps/kubernetes/api/model/HorizontalPodAutoscalerConditionBuilder."<init>":(Lio/dekorate/deps/kubernetes/api/model/HorizontalPodAutoscalerCondition;)V
      47: astore        6
      49: aload_0
      50: getfield      #107                // Field _visitables:Lio/dekorate/deps/kubernetes/api/builder/VisitableMap;
      53: ldc           #108                // String conditions
      55: invokevirtual #114                // Method io/dekorate/deps/kubernetes/api/builder/VisitableMap.get:(Ljava/lang/Object;)Ljava/util/List;
      58: aload         6
      60: invokeinterface #136,  2          // InterfaceMethod java/util/List.add:(Ljava/lang/Object;)Z
      65: pop
      66: aload_0
      67: getfield      #41                 // Field conditions:Ljava/util/List;
      70: aload         6
      72: invokeinterface #136,  2          // InterfaceMethod java/util/List.add:(Ljava/lang/Object;)Z
      77: pop
      78: iinc          4, 1
      81: goto          26
      84: aload_0
      85: areturn

  public A addAllToConditions(java.util.Collection<io.dekorate.deps.kubernetes.api.model.HorizontalPodAutoscalerCondition>);
    Code:
       0: aload_0
       1: getfield      #41                 // Field conditions:Ljava/util/List;
       4: ifnonnull     18
       7: aload_0
       8: new           #38                 // class java/util/ArrayList
      11: dup
      12: invokespecial #39                 // Method java/util/ArrayList."<init>":()V
      15: putfield      #41                 // Field conditions:Ljava/util/List;
      18: aload_1
      19: invokeinterface #154,  1          // InterfaceMethod java/util/Collection.iterator:()Ljava/util/Iterator;
      24: astore_2
      25: aload_2
      26: invokeinterface #160,  1          // InterfaceMethod java/util/Iterator.hasNext:()Z
      31: ifeq          86
      34: aload_2
      35: invokeinterface #164,  1          // InterfaceMethod java/util/Iterator.next:()Ljava/lang/Object;
      40: checkcast     #116                // class io/dekorate/deps/kubernetes/api/model/HorizontalPodAutoscalerCondition
      43: astore_3
      44: new           #100                // class io/dekorate/deps/kubernetes/api/model/HorizontalPodAutoscalerConditionBuilder
      47: dup
      48: aload_3
      49: invokespecial #103                // Method io/dekorate/deps/kubernetes/api/model/HorizontalPodAutoscalerConditionBuilder."<init>":(Lio/dekorate/deps/kubernetes/api/model/HorizontalPodAutoscalerCondition;)V
      52: astore        4
      54: aload_0
      55: getfield      #107                // Field _visitables:Lio/dekorate/deps/kubernetes/api/builder/VisitableMap;
      58: ldc           #108                // String conditions
      60: invokevirtual #114                // Method io/dekorate/deps/kubernetes/api/builder/VisitableMap.get:(Ljava/lang/Object;)Ljava/util/List;
      63: aload         4
      65: invokeinterface #136,  2          // InterfaceMethod java/util/List.add:(Ljava/lang/Object;)Z
      70: pop
      71: aload_0
      72: getfield      #41                 // Field conditions:Ljava/util/List;
      75: aload         4
      77: invokeinterface #136,  2          // InterfaceMethod java/util/List.add:(Ljava/lang/Object;)Z
      82: pop
      83: goto          25
      86: aload_0
      87: areturn

  public A removeFromConditions(io.dekorate.deps.kubernetes.api.model.HorizontalPodAutoscalerCondition...);
    Code:
       0: aload_1
       1: astore_2
       2: aload_2
       3: arraylength
       4: istore_3
       5: iconst_0
       6: istore        4
       8: iload         4
      10: iload_3
      11: if_icmpge     73
      14: aload_2
      15: iload         4
      17: aaload
      18: astore        5
      20: new           #100                // class io/dekorate/deps/kubernetes/api/model/HorizontalPodAutoscalerConditionBuilder
      23: dup
      24: aload         5
      26: invokespecial #103                // Method io/dekorate/deps/kubernetes/api/model/HorizontalPodAutoscalerConditionBuilder."<init>":(Lio/dekorate/deps/kubernetes/api/model/HorizontalPodAutoscalerCondition;)V
      29: astore        6
      31: aload_0
      32: getfield      #107                // Field _visitables:Lio/dekorate/deps/kubernetes/api/builder/VisitableMap;
      35: ldc           #108                // String conditions
      37: invokevirtual #114                // Method io/dekorate/deps/kubernetes/api/builder/VisitableMap.get:(Ljava/lang/Object;)Ljava/util/List;
      40: aload         6
      42: invokeinterface #170,  2          // InterfaceMethod java/util/List.remove:(Ljava/lang/Object;)Z
      47: pop
      48: aload_0
      49: getfield      #41                 // Field conditions:Ljava/util/List;
      52: ifnull        67
      55: aload_0
      56: getfield      #41                 // Field conditions:Ljava/util/List;
      59: aload         6
      61: invokeinterface #170,  2          // InterfaceMethod java/util/List.remove:(Ljava/lang/Object;)Z
      66: pop
      67: iinc          4, 1
      70: goto          8
      73: aload_0
      74: areturn

  public A removeAllFromConditions(java.util.Collection<io.dekorate.deps.kubernetes.api.model.HorizontalPodAutoscalerCondition>);
    Code:
       0: aload_1
       1: invokeinterface #154,  1          // InterfaceMethod java/util/Collection.iterator:()Ljava/util/Iterator;
       6: astore_2
       7: aload_2
       8: invokeinterface #160,  1          // InterfaceMethod java/util/Iterator.hasNext:()Z
      13: ifeq          75
      16: aload_2
      17: invokeinterface #164,  1          // InterfaceMethod java/util/Iterator.next:()Ljava/lang/Object;
      22: checkcast     #116                // class io/dekorate/deps/kubernetes/api/model/HorizontalPodAutoscalerCondition
      25: astore_3
      26: new           #100                // class io/dekorate/deps/kubernetes/api/model/HorizontalPodAutoscalerConditionBuilder
      29: dup
      30: aload_3
      31: invokespecial #103                // Method io/dekorate/deps/kubernetes/api/model/HorizontalPodAutoscalerConditionBuilder."<init>":(Lio/dekorate/deps/kubernetes/api/model/HorizontalPodAutoscalerCondition;)V
      34: astore        4
      36: aload_0
      37: getfield      #107                // Field _visitables:Lio/dekorate/deps/kubernetes/api/builder/VisitableMap;
      40: ldc           #108                // String conditions
      42: invokevirtual #114                // Method io/dekorate/deps/kubernetes/api/builder/VisitableMap.get:(Ljava/lang/Object;)Ljava/util/List;
      45: aload         4
      47: invokeinterface #170,  2          // InterfaceMethod java/util/List.remove:(Ljava/lang/Object;)Z
      52: pop
      53: aload_0
      54: getfield      #41                 // Field conditions:Ljava/util/List;
      57: ifnull        72
      60: aload_0
      61: getfield      #41                 // Field conditions:Ljava/util/List;
      64: aload         4
      66: invokeinterface #170,  2          // InterfaceMethod java/util/List.remove:(Ljava/lang/Object;)Z
      71: pop
      72: goto          7
      75: aload_0
      76: areturn

  public A removeMatchingFromConditions(io.dekorate.deps.kubernetes.api.builder.Predicate<io.dekorate.deps.kubernetes.api.model.HorizontalPodAutoscalerConditionBuilder>);
    Code:
       0: aload_0
       1: getfield      #41                 // Field conditions:Ljava/util/List;
       4: ifnonnull     9
       7: aload_0
       8: areturn
       9: aload_0
      10: getfield      #41                 // Field conditions:Ljava/util/List;
      13: invokeinterface #175,  1          // InterfaceMethod java/util/List.iterator:()Ljava/util/Iterator;
      18: astore_2
      19: aload_0
      20: getfield      #107                // Field _visitables:Lio/dekorate/deps/kubernetes/api/builder/VisitableMap;
      23: ldc           #108                // String conditions
      25: invokevirtual #114                // Method io/dekorate/deps/kubernetes/api/builder/VisitableMap.get:(Ljava/lang/Object;)Ljava/util/List;
      28: astore_3
      29: aload_2
      30: invokeinterface #160,  1          // InterfaceMethod java/util/Iterator.hasNext:()Z
      35: ifeq          81
      38: aload_2
      39: invokeinterface #164,  1          // InterfaceMethod java/util/Iterator.next:()Ljava/lang/Object;
      44: checkcast     #100                // class io/dekorate/deps/kubernetes/api/model/HorizontalPodAutoscalerConditionBuilder
      47: astore        4
      49: aload_1
      50: aload         4
      52: invokeinterface #181,  2          // InterfaceMethod io/dekorate/deps/kubernetes/api/builder/Predicate.apply:(Ljava/lang/Object;)Ljava/lang/Boolean;
      57: invokevirtual #186                // Method java/lang/Boolean.booleanValue:()Z
      60: ifeq          78
      63: aload_3
      64: aload         4
      66: invokeinterface #170,  2          // InterfaceMethod java/util/List.remove:(Ljava/lang/Object;)Z
      71: pop
      72: aload_2
      73: invokeinterface #188,  1          // InterfaceMethod java/util/Iterator.remove:()V
      78: goto          29
      81: aload_0
      82: areturn

  public java.util.List<io.dekorate.deps.kubernetes.api.model.HorizontalPodAutoscalerCondition> getConditions();
    Code:
       0: aload_0
       1: getfield      #41                 // Field conditions:Ljava/util/List;
       4: invokestatic  #201                // Method build:(Ljava/util/List;)Ljava/util/ArrayList;
       7: areturn

  public java.util.List<io.dekorate.deps.kubernetes.api.model.HorizontalPodAutoscalerCondition> buildConditions();
    Code:
       0: aload_0
       1: getfield      #41                 // Field conditions:Ljava/util/List;
       4: invokestatic  #201                // Method build:(Ljava/util/List;)Ljava/util/ArrayList;
       7: areturn

  public io.dekorate.deps.kubernetes.api.model.HorizontalPodAutoscalerCondition buildCondition(int);
    Code:
       0: aload_0
       1: getfield      #41                 // Field conditions:Ljava/util/List;
       4: iload_1
       5: invokeinterface #207,  2          // InterfaceMethod java/util/List.get:(I)Ljava/lang/Object;
      10: checkcast     #100                // class io/dekorate/deps/kubernetes/api/model/HorizontalPodAutoscalerConditionBuilder
      13: invokevirtual #210                // Method io/dekorate/deps/kubernetes/api/model/HorizontalPodAutoscalerConditionBuilder.build:()Lio/dekorate/deps/kubernetes/api/model/HorizontalPodAutoscalerCondition;
      16: areturn

  public io.dekorate.deps.kubernetes.api.model.HorizontalPodAutoscalerCondition buildFirstCondition();
    Code:
       0: aload_0
       1: getfield      #41                 // Field conditions:Ljava/util/List;
       4: iconst_0
       5: invokeinterface #207,  2          // InterfaceMethod java/util/List.get:(I)Ljava/lang/Object;
      10: checkcast     #100                // class io/dekorate/deps/kubernetes/api/model/HorizontalPodAutoscalerConditionBuilder
      13: invokevirtual #210                // Method io/dekorate/deps/kubernetes/api/model/HorizontalPodAutoscalerConditionBuilder.build:()Lio/dekorate/deps/kubernetes/api/model/HorizontalPodAutoscalerCondition;
      16: areturn

  public io.dekorate.deps.kubernetes.api.model.HorizontalPodAutoscalerCondition buildLastCondition();
    Code:
       0: aload_0
       1: getfield      #41                 // Field conditions:Ljava/util/List;
       4: aload_0
       5: getfield      #41                 // Field conditions:Ljava/util/List;
       8: invokeinterface #122,  1          // InterfaceMethod java/util/List.size:()I
      13: iconst_1
      14: isub
      15: invokeinterface #207,  2          // InterfaceMethod java/util/List.get:(I)Ljava/lang/Object;
      20: checkcast     #100                // class io/dekorate/deps/kubernetes/api/model/HorizontalPodAutoscalerConditionBuilder
      23: invokevirtual #210                // Method io/dekorate/deps/kubernetes/api/model/HorizontalPodAutoscalerConditionBuilder.build:()Lio/dekorate/deps/kubernetes/api/model/HorizontalPodAutoscalerCondition;
      26: areturn

  public io.dekorate.deps.kubernetes.api.model.HorizontalPodAutoscalerCondition buildMatchingCondition(io.dekorate.deps.kubernetes.api.builder.Predicate<io.dekorate.deps.kubernetes.api.model.HorizontalPodAutoscalerConditionBuilder>);
    Code:
       0: aload_0
       1: getfield      #41                 // Field conditions:Ljava/util/List;
       4: invokeinterface #175,  1          // InterfaceMethod java/util/List.iterator:()Ljava/util/Iterator;
       9: astore_2
      10: aload_2
      11: invokeinterface #160,  1          // InterfaceMethod java/util/Iterator.hasNext:()Z
      16: ifeq          50
      19: aload_2
      20: invokeinterface #164,  1          // InterfaceMethod java/util/Iterator.next:()Ljava/lang/Object;
      25: checkcast     #100                // class io/dekorate/deps/kubernetes/api/model/HorizontalPodAutoscalerConditionBuilder
      28: astore_3
      29: aload_1
      30: aload_3
      31: invokeinterface #181,  2          // InterfaceMethod io/dekorate/deps/kubernetes/api/builder/Predicate.apply:(Ljava/lang/Object;)Ljava/lang/Boolean;
      36: invokevirtual #186                // Method java/lang/Boolean.booleanValue:()Z
      39: ifeq          47
      42: aload_3
      43: invokevirtual #210                // Method io/dekorate/deps/kubernetes/api/model/HorizontalPodAutoscalerConditionBuilder.build:()Lio/dekorate/deps/kubernetes/api/model/HorizontalPodAutoscalerCondition;
      46: areturn
      47: goto          10
      50: aconst_null
      51: areturn

  public java.lang.Boolean hasMatchingCondition(io.dekorate.deps.kubernetes.api.builder.Predicate<io.dekorate.deps.kubernetes.api.model.HorizontalPodAutoscalerConditionBuilder>);
    Code:
       0: aload_0
       1: getfield      #41                 // Field conditions:Ljava/util/List;
       4: invokeinterface #175,  1          // InterfaceMethod java/util/List.iterator:()Ljava/util/Iterator;
       9: astore_2
      10: aload_2
      11: invokeinterface #160,  1          // InterfaceMethod java/util/Iterator.hasNext:()Z
      16: ifeq          50
      19: aload_2
      20: invokeinterface #164,  1          // InterfaceMethod java/util/Iterator.next:()Ljava/lang/Object;
      25: checkcast     #100                // class io/dekorate/deps/kubernetes/api/model/HorizontalPodAutoscalerConditionBuilder
      28: astore_3
      29: aload_1
      30: aload_3
      31: invokeinterface #181,  2          // InterfaceMethod io/dekorate/deps/kubernetes/api/builder/Predicate.apply:(Ljava/lang/Object;)Ljava/lang/Boolean;
      36: invokevirtual #186                // Method java/lang/Boolean.booleanValue:()Z
      39: ifeq          47
      42: iconst_1
      43: invokestatic  #222                // Method java/lang/Boolean.valueOf:(Z)Ljava/lang/Boolean;
      46: areturn
      47: goto          10
      50: iconst_0
      51: invokestatic  #222                // Method java/lang/Boolean.valueOf:(Z)Ljava/lang/Boolean;
      54: areturn

  public A withConditions(java.util.List<io.dekorate.deps.kubernetes.api.model.HorizontalPodAutoscalerCondition>);
    Code:
       0: aload_0
       1: getfield      #41                 // Field conditions:Ljava/util/List;
       4: ifnull        26
       7: aload_0
       8: getfield      #107                // Field _visitables:Lio/dekorate/deps/kubernetes/api/builder/VisitableMap;
      11: ldc           #108                // String conditions
      13: invokevirtual #114                // Method io/dekorate/deps/kubernetes/api/builder/VisitableMap.get:(Ljava/lang/Object;)Ljava/util/List;
      16: aload_0
      17: getfield      #41                 // Field conditions:Ljava/util/List;
      20: invokeinterface #227,  2          // InterfaceMethod java/util/List.removeAll:(Ljava/util/Collection;)Z
      25: pop
      26: aload_1
      27: ifnull        86
      30: aload_0
      31: new           #38                 // class java/util/ArrayList
      34: dup
      35: invokespecial #39                 // Method java/util/ArrayList."<init>":()V
      38: putfield      #41                 // Field conditions:Ljava/util/List;
      41: aload_1
      42: invokeinterface #175,  1          // InterfaceMethod java/util/List.iterator:()Ljava/util/Iterator;
      47: astore_2
      48: aload_2
      49: invokeinterface #160,  1          // InterfaceMethod java/util/Iterator.hasNext:()Z
      54: ifeq          83
      57: aload_2
      58: invokeinterface #164,  1          // InterfaceMethod java/util/Iterator.next:()Ljava/lang/Object;
      63: checkcast     #116                // class io/dekorate/deps/kubernetes/api/model/HorizontalPodAutoscalerCondition
      66: astore_3
      67: aload_0
      68: iconst_1
      69: anewarray     #116                // class io/dekorate/deps/kubernetes/api/model/HorizontalPodAutoscalerCondition
      72: dup
      73: iconst_0
      74: aload_3
      75: aastore
      76: invokevirtual #229                // Method addToConditions:([Lio/dekorate/deps/kubernetes/api/model/HorizontalPodAutoscalerCondition;)Lio/dekorate/deps/kubernetes/api/model/HorizontalPodAutoscalerStatusFluent;
      79: pop
      80: goto          48
      83: goto          91
      86: aload_0
      87: aconst_null
      88: putfield      #41                 // Field conditions:Ljava/util/List;
      91: aload_0
      92: areturn

  public A withConditions(io.dekorate.deps.kubernetes.api.model.HorizontalPodAutoscalerCondition...);
    Code:
       0: aload_0
       1: getfield      #41                 // Field conditions:Ljava/util/List;
       4: ifnull        16
       7: aload_0
       8: getfield      #41                 // Field conditions:Ljava/util/List;
      11: invokeinterface #233,  1          // InterfaceMethod java/util/List.clear:()V
      16: aload_1
      17: ifnull        60
      20: aload_1
      21: astore_2
      22: aload_2
      23: arraylength
      24: istore_3
      25: iconst_0
      26: istore        4
      28: iload         4
      30: iload_3
      31: if_icmpge     60
      34: aload_2
      35: iload         4
      37: aaload
      38: astore        5
      40: aload_0
      41: iconst_1
      42: anewarray     #116                // class io/dekorate/deps/kubernetes/api/model/HorizontalPodAutoscalerCondition
      45: dup
      46: iconst_0
      47: aload         5
      49: aastore
      50: invokevirtual #229                // Method addToConditions:([Lio/dekorate/deps/kubernetes/api/model/HorizontalPodAutoscalerCondition;)Lio/dekorate/deps/kubernetes/api/model/HorizontalPodAutoscalerStatusFluent;
      53: pop
      54: iinc          4, 1
      57: goto          28
      60: aload_0
      61: areturn

  public java.lang.Boolean hasConditions();
    Code:
       0: aload_0
       1: getfield      #41                 // Field conditions:Ljava/util/List;
       4: ifnull        23
       7: aload_0
       8: getfield      #41                 // Field conditions:Ljava/util/List;
      11: invokeinterface #238,  1          // InterfaceMethod java/util/List.isEmpty:()Z
      16: ifne          23
      19: iconst_1
      20: goto          24
      23: iconst_0
      24: invokestatic  #222                // Method java/lang/Boolean.valueOf:(Z)Ljava/lang/Boolean;
      27: areturn

  public A addNewCondition(java.lang.String, java.lang.String, java.lang.String, java.lang.String, java.lang.String);
    Code:
       0: aload_0
       1: iconst_1
       2: anewarray     #116                // class io/dekorate/deps/kubernetes/api/model/HorizontalPodAutoscalerCondition
       5: dup
       6: iconst_0
       7: new           #116                // class io/dekorate/deps/kubernetes/api/model/HorizontalPodAutoscalerCondition
      10: dup
      11: aload_1
      12: aload_2
      13: aload_3
      14: aload         4
      16: aload         5
      18: invokespecial #244                // Method io/dekorate/deps/kubernetes/api/model/HorizontalPodAutoscalerCondition."<init>":(Ljava/lang/String;Ljava/lang/String;Ljava/lang/String;Ljava/lang/String;Ljava/lang/String;)V
      21: aastore
      22: invokevirtual #229                // Method addToConditions:([Lio/dekorate/deps/kubernetes/api/model/HorizontalPodAutoscalerCondition;)Lio/dekorate/deps/kubernetes/api/model/HorizontalPodAutoscalerStatusFluent;
      25: areturn

  public io.dekorate.deps.kubernetes.api.model.HorizontalPodAutoscalerStatusFluent$ConditionsNested<A> addNewCondition();
    Code:
       0: new           #13                 // class io/dekorate/deps/kubernetes/api/model/HorizontalPodAutoscalerStatusFluentImpl$ConditionsNestedImpl
       3: dup
       4: aload_0
       5: invokespecial #254                // Method io/dekorate/deps/kubernetes/api/model/HorizontalPodAutoscalerStatusFluentImpl$ConditionsNestedImpl."<init>":(Lio/dekorate/deps/kubernetes/api/model/HorizontalPodAutoscalerStatusFluentImpl;)V
       8: areturn

  public io.dekorate.deps.kubernetes.api.model.HorizontalPodAutoscalerStatusFluent$ConditionsNested<A> addNewConditionLike(io.dekorate.deps.kubernetes.api.model.HorizontalPodAutoscalerCondition);
    Code:
       0: new           #13                 // class io/dekorate/deps/kubernetes/api/model/HorizontalPodAutoscalerStatusFluentImpl$ConditionsNestedImpl
       3: dup
       4: aload_0
       5: iconst_m1
       6: aload_1
       7: invokespecial #260                // Method io/dekorate/deps/kubernetes/api/model/HorizontalPodAutoscalerStatusFluentImpl$ConditionsNestedImpl."<init>":(Lio/dekorate/deps/kubernetes/api/model/HorizontalPodAutoscalerStatusFluentImpl;ILio/dekorate/deps/kubernetes/api/model/HorizontalPodAutoscalerCondition;)V
      10: areturn

  public io.dekorate.deps.kubernetes.api.model.HorizontalPodAutoscalerStatusFluent$ConditionsNested<A> setNewConditionLike(int, io.dekorate.deps.kubernetes.api.model.HorizontalPodAutoscalerCondition);
    Code:
       0: new           #13                 // class io/dekorate/deps/kubernetes/api/model/HorizontalPodAutoscalerStatusFluentImpl$ConditionsNestedImpl
       3: dup
       4: aload_0
       5: iload_1
       6: aload_2
       7: invokespecial #260                // Method io/dekorate/deps/kubernetes/api/model/HorizontalPodAutoscalerStatusFluentImpl$ConditionsNestedImpl."<init>":(Lio/dekorate/deps/kubernetes/api/model/HorizontalPodAutoscalerStatusFluentImpl;ILio/dekorate/deps/kubernetes/api/model/HorizontalPodAutoscalerCondition;)V
      10: areturn

  public io.dekorate.deps.kubernetes.api.model.HorizontalPodAutoscalerStatusFluent$ConditionsNested<A> editCondition(int);
    Code:
       0: aload_0
       1: getfield      #41                 // Field conditions:Ljava/util/List;
       4: invokeinterface #122,  1          // InterfaceMethod java/util/List.size:()I
       9: iload_1
      10: if_icmpgt     24
      13: new           #268                // class java/lang/RuntimeException
      16: dup
      17: ldc_w         #270                // String Can\'t edit conditions. Index exceeds size.
      20: invokespecial #273                // Method java/lang/RuntimeException."<init>":(Ljava/lang/String;)V
      23: athrow
      24: aload_0
      25: iload_1
      26: aload_0
      27: iload_1
      28: invokevirtual #275                // Method buildCondition:(I)Lio/dekorate/deps/kubernetes/api/model/HorizontalPodAutoscalerCondition;
      31: invokevirtual #277                // Method setNewConditionLike:(ILio/dekorate/deps/kubernetes/api/model/HorizontalPodAutoscalerCondition;)Lio/dekorate/deps/kubernetes/api/model/HorizontalPodAutoscalerStatusFluent$ConditionsNested;
      34: areturn

  public io.dekorate.deps.kubernetes.api.model.HorizontalPodAutoscalerStatusFluent$ConditionsNested<A> editFirstCondition();
    Code:
       0: aload_0
       1: getfield      #41                 // Field conditions:Ljava/util/List;
       4: invokeinterface #122,  1          // InterfaceMethod java/util/List.size:()I
       9: ifne          23
      12: new           #268                // class java/lang/RuntimeException
      15: dup
      16: ldc_w         #280                // String Can\'t edit first conditions. The list is empty.
      19: invokespecial #273                // Method java/lang/RuntimeException."<init>":(Ljava/lang/String;)V
      22: athrow
      23: aload_0
      24: iconst_0
      25: aload_0
      26: iconst_0
      27: invokevirtual #275                // Method buildCondition:(I)Lio/dekorate/deps/kubernetes/api/model/HorizontalPodAutoscalerCondition;
      30: invokevirtual #277                // Method setNewConditionLike:(ILio/dekorate/deps/kubernetes/api/model/HorizontalPodAutoscalerCondition;)Lio/dekorate/deps/kubernetes/api/model/HorizontalPodAutoscalerStatusFluent$ConditionsNested;
      33: areturn

  public io.dekorate.deps.kubernetes.api.model.HorizontalPodAutoscalerStatusFluent$ConditionsNested<A> editLastCondition();
    Code:
       0: aload_0
       1: getfield      #41                 // Field conditions:Ljava/util/List;
       4: invokeinterface #122,  1          // InterfaceMethod java/util/List.size:()I
       9: iconst_1
      10: isub
      11: istore_1
      12: iload_1
      13: ifge          27
      16: new           #268                // class java/lang/RuntimeException
      19: dup
      20: ldc_w         #283                // String Can\'t edit last conditions. The list is empty.
      23: invokespecial #273                // Method java/lang/RuntimeException."<init>":(Ljava/lang/String;)V
      26: athrow
      27: aload_0
      28: iload_1
      29: aload_0
      30: iload_1
      31: invokevirtual #275                // Method buildCondition:(I)Lio/dekorate/deps/kubernetes/api/model/HorizontalPodAutoscalerCondition;
      34: invokevirtual #277                // Method setNewConditionLike:(ILio/dekorate/deps/kubernetes/api/model/HorizontalPodAutoscalerCondition;)Lio/dekorate/deps/kubernetes/api/model/HorizontalPodAutoscalerStatusFluent$ConditionsNested;
      37: areturn

  public io.dekorate.deps.kubernetes.api.model.HorizontalPodAutoscalerStatusFluent$ConditionsNested<A> editMatchingCondition(io.dekorate.deps.kubernetes.api.builder.Predicate<io.dekorate.deps.kubernetes.api.model.HorizontalPodAutoscalerConditionBuilder>);
    Code:
       0: iconst_m1
       1: istore_2
       2: iconst_0
       3: istore_3
       4: iload_3
       5: aload_0
       6: getfield      #41                 // Field conditions:Ljava/util/List;
       9: invokeinterface #122,  1          // InterfaceMethod java/util/List.size:()I
      14: if_icmpge     50
      17: aload_1
      18: aload_0
      19: getfield      #41                 // Field conditions:Ljava/util/List;
      22: iload_3
      23: invokeinterface #207,  2          // InterfaceMethod java/util/List.get:(I)Ljava/lang/Object;
      28: invokeinterface #181,  2          // InterfaceMethod io/dekorate/deps/kubernetes/api/builder/Predicate.apply:(Ljava/lang/Object;)Ljava/lang/Boolean;
      33: invokevirtual #186                // Method java/lang/Boolean.booleanValue:()Z
      36: ifeq          44
      39: iload_3
      40: istore_2
      41: goto          50
      44: iinc          3, 1
      47: goto          4
      50: iload_2
      51: ifge          65
      54: new           #268                // class java/lang/RuntimeException
      57: dup
      58: ldc_w         #288                // String Can\'t edit matching conditions. No match found.
      61: invokespecial #273                // Method java/lang/RuntimeException."<init>":(Ljava/lang/String;)V
      64: athrow
      65: aload_0
      66: iload_2
      67: aload_0
      68: iload_2
      69: invokevirtual #275                // Method buildCondition:(I)Lio/dekorate/deps/kubernetes/api/model/HorizontalPodAutoscalerCondition;
      72: invokevirtual #277                // Method setNewConditionLike:(ILio/dekorate/deps/kubernetes/api/model/HorizontalPodAutoscalerCondition;)Lio/dekorate/deps/kubernetes/api/model/HorizontalPodAutoscalerStatusFluent$ConditionsNested;
      75: areturn

  public A addToCurrentMetrics(int, io.dekorate.deps.kubernetes.api.model.MetricStatus);
    Code:
       0: aload_0
       1: getfield      #43                 // Field currentMetrics:Ljava/util/List;
       4: ifnonnull     18
       7: aload_0
       8: new           #38                 // class java/util/ArrayList
      11: dup
      12: invokespecial #39                 // Method java/util/ArrayList."<init>":()V
      15: putfield      #43                 // Field currentMetrics:Ljava/util/List;
      18: new           #294                // class io/dekorate/deps/kubernetes/api/model/MetricStatusBuilder
      21: dup
      22: aload_2
      23: invokespecial #297                // Method io/dekorate/deps/kubernetes/api/model/MetricStatusBuilder."<init>":(Lio/dekorate/deps/kubernetes/api/model/MetricStatus;)V
      26: astore_3
      27: aload_0
      28: getfield      #107                // Field _visitables:Lio/dekorate/deps/kubernetes/api/builder/VisitableMap;
      31: ldc_w         #298                // String currentMetrics
      34: invokevirtual #114                // Method io/dekorate/deps/kubernetes/api/builder/VisitableMap.get:(Ljava/lang/Object;)Ljava/util/List;
      37: iload_1
      38: iflt          45
      41: iload_1
      42: goto          60
      45: aload_0
      46: getfield      #107                // Field _visitables:Lio/dekorate/deps/kubernetes/api/builder/VisitableMap;
      49: ldc_w         #298                // String currentMetrics
      52: invokevirtual #114                // Method io/dekorate/deps/kubernetes/api/builder/VisitableMap.get:(Ljava/lang/Object;)Ljava/util/List;
      55: invokeinterface #122,  1          // InterfaceMethod java/util/List.size:()I
      60: aload_3
      61: invokeinterface #126,  3          // InterfaceMethod java/util/List.add:(ILjava/lang/Object;)V
      66: aload_0
      67: getfield      #43                 // Field currentMetrics:Ljava/util/List;
      70: iload_1
      71: iflt          78
      74: iload_1
      75: goto          87
      78: aload_0
      79: getfield      #43                 // Field currentMetrics:Ljava/util/List;
      82: invokeinterface #122,  1          // InterfaceMethod java/util/List.size:()I
      87: aload_3
      88: invokeinterface #126,  3          // InterfaceMethod java/util/List.add:(ILjava/lang/Object;)V
      93: aload_0
      94: areturn

  public A setToCurrentMetrics(int, io.dekorate.deps.kubernetes.api.model.MetricStatus);
    Code:
       0: aload_0
       1: getfield      #43                 // Field currentMetrics:Ljava/util/List;
       4: ifnonnull     18
       7: aload_0
       8: new           #38                 // class java/util/ArrayList
      11: dup
      12: invokespecial #39                 // Method java/util/ArrayList."<init>":()V
      15: putfield      #43                 // Field currentMetrics:Ljava/util/List;
      18: new           #294                // class io/dekorate/deps/kubernetes/api/model/MetricStatusBuilder
      21: dup
      22: aload_2
      23: invokespecial #297                // Method io/dekorate/deps/kubernetes/api/model/MetricStatusBuilder."<init>":(Lio/dekorate/deps/kubernetes/api/model/MetricStatus;)V
      26: astore_3
      27: iload_1
      28: iflt          50
      31: iload_1
      32: aload_0
      33: getfield      #107                // Field _visitables:Lio/dekorate/deps/kubernetes/api/builder/VisitableMap;
      36: ldc_w         #298                // String currentMetrics
      39: invokevirtual #114                // Method io/dekorate/deps/kubernetes/api/builder/VisitableMap.get:(Ljava/lang/Object;)Ljava/util/List;
      42: invokeinterface #122,  1          // InterfaceMethod java/util/List.size:()I
      47: if_icmplt     70
      50: aload_0
      51: getfield      #107                // Field _visitables:Lio/dekorate/deps/kubernetes/api/builder/VisitableMap;
      54: ldc_w         #298                // String currentMetrics
      57: invokevirtual #114                // Method io/dekorate/deps/kubernetes/api/builder/VisitableMap.get:(Ljava/lang/Object;)Ljava/util/List;
      60: aload_3
      61: invokeinterface #136,  2          // InterfaceMethod java/util/List.add:(Ljava/lang/Object;)Z
      66: pop
      67: goto          88
      70: aload_0
      71: getfield      #107                // Field _visitables:Lio/dekorate/deps/kubernetes/api/builder/VisitableMap;
      74: ldc_w         #298                // String currentMetrics
      77: invokevirtual #114                // Method io/dekorate/deps/kubernetes/api/builder/VisitableMap.get:(Ljava/lang/Object;)Ljava/util/List;
      80: iload_1
      81: aload_3
      82: invokeinterface #140,  3          // InterfaceMethod java/util/List.set:(ILjava/lang/Object;)Ljava/lang/Object;
      87: pop
      88: iload_1
      89: iflt          105
      92: iload_1
      93: aload_0
      94: getfield      #43                 // Field currentMetrics:Ljava/util/List;
      97: invokeinterface #122,  1          // InterfaceMethod java/util/List.size:()I
     102: if_icmplt     119
     105: aload_0
     106: getfield      #43                 // Field currentMetrics:Ljava/util/List;
     109: aload_3
     110: invokeinterface #136,  2          // InterfaceMethod java/util/List.add:(Ljava/lang/Object;)Z
     115: pop
     116: goto          131
     119: aload_0
     120: getfield      #43                 // Field currentMetrics:Ljava/util/List;
     123: iload_1
     124: aload_3
     125: invokeinterface #140,  3          // InterfaceMethod java/util/List.set:(ILjava/lang/Object;)Ljava/lang/Object;
     130: pop
     131: aload_0
     132: areturn

  public A addToCurrentMetrics(io.dekorate.deps.kubernetes.api.model.MetricStatus...);
    Code:
       0: aload_0
       1: getfield      #43                 // Field currentMetrics:Ljava/util/List;
       4: ifnonnull     18
       7: aload_0
       8: new           #38                 // class java/util/ArrayList
      11: dup
      12: invokespecial #39                 // Method java/util/ArrayList."<init>":()V
      15: putfield      #43                 // Field currentMetrics:Ljava/util/List;
      18: aload_1
      19: astore_2
      20: aload_2
      21: arraylength
      22: istore_3
      23: iconst_0
      24: istore        4
      26: iload         4
      28: iload_3
      29: if_icmpge     85
      32: aload_2
      33: iload         4
      35: aaload
      36: astore        5
      38: new           #294                // class io/dekorate/deps/kubernetes/api/model/MetricStatusBuilder
      41: dup
      42: aload         5
      44: invokespecial #297                // Method io/dekorate/deps/kubernetes/api/model/MetricStatusBuilder."<init>":(Lio/dekorate/deps/kubernetes/api/model/MetricStatus;)V
      47: astore        6
      49: aload_0
      50: getfield      #107                // Field _visitables:Lio/dekorate/deps/kubernetes/api/builder/VisitableMap;
      53: ldc_w         #298                // String currentMetrics
      56: invokevirtual #114                // Method io/dekorate/deps/kubernetes/api/builder/VisitableMap.get:(Ljava/lang/Object;)Ljava/util/List;
      59: aload         6
      61: invokeinterface #136,  2          // InterfaceMethod java/util/List.add:(Ljava/lang/Object;)Z
      66: pop
      67: aload_0
      68: getfield      #43                 // Field currentMetrics:Ljava/util/List;
      71: aload         6
      73: invokeinterface #136,  2          // InterfaceMethod java/util/List.add:(Ljava/lang/Object;)Z
      78: pop
      79: iinc          4, 1
      82: goto          26
      85: aload_0
      86: areturn

  public A addAllToCurrentMetrics(java.util.Collection<io.dekorate.deps.kubernetes.api.model.MetricStatus>);
    Code:
       0: aload_0
       1: getfield      #43                 // Field currentMetrics:Ljava/util/List;
       4: ifnonnull     18
       7: aload_0
       8: new           #38                 // class java/util/ArrayList
      11: dup
      12: invokespecial #39                 // Method java/util/ArrayList."<init>":()V
      15: putfield      #43                 // Field currentMetrics:Ljava/util/List;
      18: aload_1
      19: invokeinterface #154,  1          // InterfaceMethod java/util/Collection.iterator:()Ljava/util/Iterator;
      24: astore_2
      25: aload_2
      26: invokeinterface #160,  1          // InterfaceMethod java/util/Iterator.hasNext:()Z
      31: ifeq          87
      34: aload_2
      35: invokeinterface #164,  1          // InterfaceMethod java/util/Iterator.next:()Ljava/lang/Object;
      40: checkcast     #300                // class io/dekorate/deps/kubernetes/api/model/MetricStatus
      43: astore_3
      44: new           #294                // class io/dekorate/deps/kubernetes/api/model/MetricStatusBuilder
      47: dup
      48: aload_3
      49: invokespecial #297                // Method io/dekorate/deps/kubernetes/api/model/MetricStatusBuilder."<init>":(Lio/dekorate/deps/kubernetes/api/model/MetricStatus;)V
      52: astore        4
      54: aload_0
      55: getfield      #107                // Field _visitables:Lio/dekorate/deps/kubernetes/api/builder/VisitableMap;
      58: ldc_w         #298                // String currentMetrics
      61: invokevirtual #114                // Method io/dekorate/deps/kubernetes/api/builder/VisitableMap.get:(Ljava/lang/Object;)Ljava/util/List;
      64: aload         4
      66: invokeinterface #136,  2          // InterfaceMethod java/util/List.add:(Ljava/lang/Object;)Z
      71: pop
      72: aload_0
      73: getfield      #43                 // Field currentMetrics:Ljava/util/List;
      76: aload         4
      78: invokeinterface #136,  2          // InterfaceMethod java/util/List.add:(Ljava/lang/Object;)Z
      83: pop
      84: goto          25
      87: aload_0
      88: areturn

  public A removeFromCurrentMetrics(io.dekorate.deps.kubernetes.api.model.MetricStatus...);
    Code:
       0: aload_1
       1: astore_2
       2: aload_2
       3: arraylength
       4: istore_3
       5: iconst_0
       6: istore        4
       8: iload         4
      10: iload_3
      11: if_icmpge     74
      14: aload_2
      15: iload         4
      17: aaload
      18: astore        5
      20: new           #294                // class io/dekorate/deps/kubernetes/api/model/MetricStatusBuilder
      23: dup
      24: aload         5
      26: invokespecial #297                // Method io/dekorate/deps/kubernetes/api/model/MetricStatusBuilder."<init>":(Lio/dekorate/deps/kubernetes/api/model/MetricStatus;)V
      29: astore        6
      31: aload_0
      32: getfield      #107                // Field _visitables:Lio/dekorate/deps/kubernetes/api/builder/VisitableMap;
      35: ldc_w         #298                // String currentMetrics
      38: invokevirtual #114                // Method io/dekorate/deps/kubernetes/api/builder/VisitableMap.get:(Ljava/lang/Object;)Ljava/util/List;
      41: aload         6
      43: invokeinterface #170,  2          // InterfaceMethod java/util/List.remove:(Ljava/lang/Object;)Z
      48: pop
      49: aload_0
      50: getfield      #43                 // Field currentMetrics:Ljava/util/List;
      53: ifnull        68
      56: aload_0
      57: getfield      #43                 // Field currentMetrics:Ljava/util/List;
      60: aload         6
      62: invokeinterface #170,  2          // InterfaceMethod java/util/List.remove:(Ljava/lang/Object;)Z
      67: pop
      68: iinc          4, 1
      71: goto          8
      74: aload_0
      75: areturn

  public A removeAllFromCurrentMetrics(java.util.Collection<io.dekorate.deps.kubernetes.api.model.MetricStatus>);
    Code:
       0: aload_1
       1: invokeinterface #154,  1          // InterfaceMethod java/util/Collection.iterator:()Ljava/util/Iterator;
       6: astore_2
       7: aload_2
       8: invokeinterface #160,  1          // InterfaceMethod java/util/Iterator.hasNext:()Z
      13: ifeq          76
      16: aload_2
      17: invokeinterface #164,  1          // InterfaceMethod java/util/Iterator.next:()Ljava/lang/Object;
      22: checkcast     #300                // class io/dekorate/deps/kubernetes/api/model/MetricStatus
      25: astore_3
      26: new           #294                // class io/dekorate/deps/kubernetes/api/model/MetricStatusBuilder
      29: dup
      30: aload_3
      31: invokespecial #297                // Method io/dekorate/deps/kubernetes/api/model/MetricStatusBuilder."<init>":(Lio/dekorate/deps/kubernetes/api/model/MetricStatus;)V
      34: astore        4
      36: aload_0
      37: getfield      #107                // Field _visitables:Lio/dekorate/deps/kubernetes/api/builder/VisitableMap;
      40: ldc_w         #298                // String currentMetrics
      43: invokevirtual #114                // Method io/dekorate/deps/kubernetes/api/builder/VisitableMap.get:(Ljava/lang/Object;)Ljava/util/List;
      46: aload         4
      48: invokeinterface #170,  2          // InterfaceMethod java/util/List.remove:(Ljava/lang/Object;)Z
      53: pop
      54: aload_0
      55: getfield      #43                 // Field currentMetrics:Ljava/util/List;
      58: ifnull        73
      61: aload_0
      62: getfield      #43                 // Field currentMetrics:Ljava/util/List;
      65: aload         4
      67: invokeinterface #170,  2          // InterfaceMethod java/util/List.remove:(Ljava/lang/Object;)Z
      72: pop
      73: goto          7
      76: aload_0
      77: areturn

  public A removeMatchingFromCurrentMetrics(io.dekorate.deps.kubernetes.api.builder.Predicate<io.dekorate.deps.kubernetes.api.model.MetricStatusBuilder>);
    Code:
       0: aload_0
       1: getfield      #43                 // Field currentMetrics:Ljava/util/List;
       4: ifnonnull     9
       7: aload_0
       8: areturn
       9: aload_0
      10: getfield      #43                 // Field currentMetrics:Ljava/util/List;
      13: invokeinterface #175,  1          // InterfaceMethod java/util/List.iterator:()Ljava/util/Iterator;
      18: astore_2
      19: aload_0
      20: getfield      #107                // Field _visitables:Lio/dekorate/deps/kubernetes/api/builder/VisitableMap;
      23: ldc_w         #298                // String currentMetrics
      26: invokevirtual #114                // Method io/dekorate/deps/kubernetes/api/builder/VisitableMap.get:(Ljava/lang/Object;)Ljava/util/List;
      29: astore_3
      30: aload_2
      31: invokeinterface #160,  1          // InterfaceMethod java/util/Iterator.hasNext:()Z
      36: ifeq          82
      39: aload_2
      40: invokeinterface #164,  1          // InterfaceMethod java/util/Iterator.next:()Ljava/lang/Object;
      45: checkcast     #294                // class io/dekorate/deps/kubernetes/api/model/MetricStatusBuilder
      48: astore        4
      50: aload_1
      51: aload         4
      53: invokeinterface #181,  2          // InterfaceMethod io/dekorate/deps/kubernetes/api/builder/Predicate.apply:(Ljava/lang/Object;)Ljava/lang/Boolean;
      58: invokevirtual #186                // Method java/lang/Boolean.booleanValue:()Z
      61: ifeq          79
      64: aload_3
      65: aload         4
      67: invokeinterface #170,  2          // InterfaceMethod java/util/List.remove:(Ljava/lang/Object;)Z
      72: pop
      73: aload_2
      74: invokeinterface #188,  1          // InterfaceMethod java/util/Iterator.remove:()V
      79: goto          30
      82: aload_0
      83: areturn

  public java.util.List<io.dekorate.deps.kubernetes.api.model.MetricStatus> getCurrentMetrics();
    Code:
       0: aload_0
       1: getfield      #43                 // Field currentMetrics:Ljava/util/List;
       4: invokestatic  #201                // Method build:(Ljava/util/List;)Ljava/util/ArrayList;
       7: areturn

  public java.util.List<io.dekorate.deps.kubernetes.api.model.MetricStatus> buildCurrentMetrics();
    Code:
       0: aload_0
       1: getfield      #43                 // Field currentMetrics:Ljava/util/List;
       4: invokestatic  #201                // Method build:(Ljava/util/List;)Ljava/util/ArrayList;
       7: areturn

  public io.dekorate.deps.kubernetes.api.model.MetricStatus buildCurrentMetric(int);
    Code:
       0: aload_0
       1: getfield      #43                 // Field currentMetrics:Ljava/util/List;
       4: iload_1
       5: invokeinterface #207,  2          // InterfaceMethod java/util/List.get:(I)Ljava/lang/Object;
      10: checkcast     #294                // class io/dekorate/deps/kubernetes/api/model/MetricStatusBuilder
      13: invokevirtual #323                // Method io/dekorate/deps/kubernetes/api/model/MetricStatusBuilder.build:()Lio/dekorate/deps/kubernetes/api/model/MetricStatus;
      16: areturn

  public io.dekorate.deps.kubernetes.api.model.MetricStatus buildFirstCurrentMetric();
    Code:
       0: aload_0
       1: getfield      #43                 // Field currentMetrics:Ljava/util/List;
       4: iconst_0
       5: invokeinterface #207,  2          // InterfaceMethod java/util/List.get:(I)Ljava/lang/Object;
      10: checkcast     #294                // class io/dekorate/deps/kubernetes/api/model/MetricStatusBuilder
      13: invokevirtual #323                // Method io/dekorate/deps/kubernetes/api/model/MetricStatusBuilder.build:()Lio/dekorate/deps/kubernetes/api/model/MetricStatus;
      16: areturn

  public io.dekorate.deps.kubernetes.api.model.MetricStatus buildLastCurrentMetric();
    Code:
       0: aload_0
       1: getfield      #43                 // Field currentMetrics:Ljava/util/List;
       4: aload_0
       5: getfield      #43                 // Field currentMetrics:Ljava/util/List;
       8: invokeinterface #122,  1          // InterfaceMethod java/util/List.size:()I
      13: iconst_1
      14: isub
      15: invokeinterface #207,  2          // InterfaceMethod java/util/List.get:(I)Ljava/lang/Object;
      20: checkcast     #294                // class io/dekorate/deps/kubernetes/api/model/MetricStatusBuilder
      23: invokevirtual #323                // Method io/dekorate/deps/kubernetes/api/model/MetricStatusBuilder.build:()Lio/dekorate/deps/kubernetes/api/model/MetricStatus;
      26: areturn

  public io.dekorate.deps.kubernetes.api.model.MetricStatus buildMatchingCurrentMetric(io.dekorate.deps.kubernetes.api.builder.Predicate<io.dekorate.deps.kubernetes.api.model.MetricStatusBuilder>);
    Code:
       0: aload_0
       1: getfield      #43                 // Field currentMetrics:Ljava/util/List;
       4: invokeinterface #175,  1          // InterfaceMethod java/util/List.iterator:()Ljava/util/Iterator;
       9: astore_2
      10: aload_2
      11: invokeinterface #160,  1          // InterfaceMethod java/util/Iterator.hasNext:()Z
      16: ifeq          50
      19: aload_2
      20: invokeinterface #164,  1          // InterfaceMethod java/util/Iterator.next:()Ljava/lang/Object;
      25: checkcast     #294                // class io/dekorate/deps/kubernetes/api/model/MetricStatusBuilder
      28: astore_3
      29: aload_1
      30: aload_3
      31: invokeinterface #181,  2          // InterfaceMethod io/dekorate/deps/kubernetes/api/builder/Predicate.apply:(Ljava/lang/Object;)Ljava/lang/Boolean;
      36: invokevirtual #186                // Method java/lang/Boolean.booleanValue:()Z
      39: ifeq          47
      42: aload_3
      43: invokevirtual #323                // Method io/dekorate/deps/kubernetes/api/model/MetricStatusBuilder.build:()Lio/dekorate/deps/kubernetes/api/model/MetricStatus;
      46: areturn
      47: goto          10
      50: aconst_null
      51: areturn

  public java.lang.Boolean hasMatchingCurrentMetric(io.dekorate.deps.kubernetes.api.builder.Predicate<io.dekorate.deps.kubernetes.api.model.MetricStatusBuilder>);
    Code:
       0: aload_0
       1: getfield      #43                 // Field currentMetrics:Ljava/util/List;
       4: invokeinterface #175,  1          // InterfaceMethod java/util/List.iterator:()Ljava/util/Iterator;
       9: astore_2
      10: aload_2
      11: invokeinterface #160,  1          // InterfaceMethod java/util/Iterator.hasNext:()Z
      16: ifeq          50
      19: aload_2
      20: invokeinterface #164,  1          // InterfaceMethod java/util/Iterator.next:()Ljava/lang/Object;
      25: checkcast     #294                // class io/dekorate/deps/kubernetes/api/model/MetricStatusBuilder
      28: astore_3
      29: aload_1
      30: aload_3
      31: invokeinterface #181,  2          // InterfaceMethod io/dekorate/deps/kubernetes/api/builder/Predicate.apply:(Ljava/lang/Object;)Ljava/lang/Boolean;
      36: invokevirtual #186                // Method java/lang/Boolean.booleanValue:()Z
      39: ifeq          47
      42: iconst_1
      43: invokestatic  #222                // Method java/lang/Boolean.valueOf:(Z)Ljava/lang/Boolean;
      46: areturn
      47: goto          10
      50: iconst_0
      51: invokestatic  #222                // Method java/lang/Boolean.valueOf:(Z)Ljava/lang/Boolean;
      54: areturn

  public A withCurrentMetrics(java.util.List<io.dekorate.deps.kubernetes.api.model.MetricStatus>);
    Code:
       0: aload_0
       1: getfield      #43                 // Field currentMetrics:Ljava/util/List;
       4: ifnull        27
       7: aload_0
       8: getfield      #107                // Field _visitables:Lio/dekorate/deps/kubernetes/api/builder/VisitableMap;
      11: ldc_w         #298                // String currentMetrics
      14: invokevirtual #114                // Method io/dekorate/deps/kubernetes/api/builder/VisitableMap.get:(Ljava/lang/Object;)Ljava/util/List;
      17: aload_0
      18: getfield      #43                 // Field currentMetrics:Ljava/util/List;
      21: invokeinterface #227,  2          // InterfaceMethod java/util/List.removeAll:(Ljava/util/Collection;)Z
      26: pop
      27: aload_1
      28: ifnull        87
      31: aload_0
      32: new           #38                 // class java/util/ArrayList
      35: dup
      36: invokespecial #39                 // Method java/util/ArrayList."<init>":()V
      39: putfield      #43                 // Field currentMetrics:Ljava/util/List;
      42: aload_1
      43: invokeinterface #175,  1          // InterfaceMethod java/util/List.iterator:()Ljava/util/Iterator;
      48: astore_2
      49: aload_2
      50: invokeinterface #160,  1          // InterfaceMethod java/util/Iterator.hasNext:()Z
      55: ifeq          84
      58: aload_2
      59: invokeinterface #164,  1          // InterfaceMethod java/util/Iterator.next:()Ljava/lang/Object;
      64: checkcast     #300                // class io/dekorate/deps/kubernetes/api/model/MetricStatus
      67: astore_3
      68: aload_0
      69: iconst_1
      70: anewarray     #300                // class io/dekorate/deps/kubernetes/api/model/MetricStatus
      73: dup
      74: iconst_0
      75: aload_3
      76: aastore
      77: invokevirtual #333                // Method addToCurrentMetrics:([Lio/dekorate/deps/kubernetes/api/model/MetricStatus;)Lio/dekorate/deps/kubernetes/api/model/HorizontalPodAutoscalerStatusFluent;
      80: pop
      81: goto          49
      84: goto          92
      87: aload_0
      88: aconst_null
      89: putfield      #43                 // Field currentMetrics:Ljava/util/List;
      92: aload_0
      93: areturn

  public A withCurrentMetrics(io.dekorate.deps.kubernetes.api.model.MetricStatus...);
    Code:
       0: aload_0
       1: getfield      #43                 // Field currentMetrics:Ljava/util/List;
       4: ifnull        16
       7: aload_0
       8: getfield      #43                 // Field currentMetrics:Ljava/util/List;
      11: invokeinterface #233,  1          // InterfaceMethod java/util/List.clear:()V
      16: aload_1
      17: ifnull        60
      20: aload_1
      21: astore_2
      22: aload_2
      23: arraylength
      24: istore_3
      25: iconst_0
      26: istore        4
      28: iload         4
      30: iload_3
      31: if_icmpge     60
      34: aload_2
      35: iload         4
      37: aaload
      38: astore        5
      40: aload_0
      41: iconst_1
      42: anewarray     #300                // class io/dekorate/deps/kubernetes/api/model/MetricStatus
      45: dup
      46: iconst_0
      47: aload         5
      49: aastore
      50: invokevirtual #333                // Method addToCurrentMetrics:([Lio/dekorate/deps/kubernetes/api/model/MetricStatus;)Lio/dekorate/deps/kubernetes/api/model/HorizontalPodAutoscalerStatusFluent;
      53: pop
      54: iinc          4, 1
      57: goto          28
      60: aload_0
      61: areturn

  public java.lang.Boolean hasCurrentMetrics();
    Code:
       0: aload_0
       1: getfield      #43                 // Field currentMetrics:Ljava/util/List;
       4: ifnull        23
       7: aload_0
       8: getfield      #43                 // Field currentMetrics:Ljava/util/List;
      11: invokeinterface #238,  1          // InterfaceMethod java/util/List.isEmpty:()Z
      16: ifne          23
      19: iconst_1
      20: goto          24
      23: iconst_0
      24: invokestatic  #222                // Method java/lang/Boolean.valueOf:(Z)Ljava/lang/Boolean;
      27: areturn

  public io.dekorate.deps.kubernetes.api.model.HorizontalPodAutoscalerStatusFluent$CurrentMetricsNested<A> addNewCurrentMetric();
    Code:
       0: new           #10                 // class io/dekorate/deps/kubernetes/api/model/HorizontalPodAutoscalerStatusFluentImpl$CurrentMetricsNestedImpl
       3: dup
       4: aload_0
       5: invokespecial #339                // Method io/dekorate/deps/kubernetes/api/model/HorizontalPodAutoscalerStatusFluentImpl$CurrentMetricsNestedImpl."<init>":(Lio/dekorate/deps/kubernetes/api/model/HorizontalPodAutoscalerStatusFluentImpl;)V
       8: areturn

  public io.dekorate.deps.kubernetes.api.model.HorizontalPodAutoscalerStatusFluent$CurrentMetricsNested<A> addNewCurrentMetricLike(io.dekorate.deps.kubernetes.api.model.MetricStatus);
    Code:
       0: new           #10                 // class io/dekorate/deps/kubernetes/api/model/HorizontalPodAutoscalerStatusFluentImpl$CurrentMetricsNestedImpl
       3: dup
       4: aload_0
       5: iconst_m1
       6: aload_1
       7: invokespecial #345                // Method io/dekorate/deps/kubernetes/api/model/HorizontalPodAutoscalerStatusFluentImpl$CurrentMetricsNestedImpl."<init>":(Lio/dekorate/deps/kubernetes/api/model/HorizontalPodAutoscalerStatusFluentImpl;ILio/dekorate/deps/kubernetes/api/model/MetricStatus;)V
      10: areturn

  public io.dekorate.deps.kubernetes.api.model.HorizontalPodAutoscalerStatusFluent$CurrentMetricsNested<A> setNewCurrentMetricLike(int, io.dekorate.deps.kubernetes.api.model.MetricStatus);
    Code:
       0: new           #10                 // class io/dekorate/deps/kubernetes/api/model/HorizontalPodAutoscalerStatusFluentImpl$CurrentMetricsNestedImpl
       3: dup
       4: aload_0
       5: iload_1
       6: aload_2
       7: invokespecial #345                // Method io/dekorate/deps/kubernetes/api/model/HorizontalPodAutoscalerStatusFluentImpl$CurrentMetricsNestedImpl."<init>":(Lio/dekorate/deps/kubernetes/api/model/HorizontalPodAutoscalerStatusFluentImpl;ILio/dekorate/deps/kubernetes/api/model/MetricStatus;)V
      10: areturn

  public io.dekorate.deps.kubernetes.api.model.HorizontalPodAutoscalerStatusFluent$CurrentMetricsNested<A> editCurrentMetric(int);
    Code:
       0: aload_0
       1: getfield      #43                 // Field currentMetrics:Ljava/util/List;
       4: invokeinterface #122,  1          // InterfaceMethod java/util/List.size:()I
       9: iload_1
      10: if_icmpgt     24
      13: new           #268                // class java/lang/RuntimeException
      16: dup
      17: ldc_w         #353                // String Can\'t edit currentMetrics. Index exceeds size.
      20: invokespecial #273                // Method java/lang/RuntimeException."<init>":(Ljava/lang/String;)V
      23: athrow
      24: aload_0
      25: iload_1
      26: aload_0
      27: iload_1
      28: invokevirtual #355                // Method buildCurrentMetric:(I)Lio/dekorate/deps/kubernetes/api/model/MetricStatus;
      31: invokevirtual #357                // Method setNewCurrentMetricLike:(ILio/dekorate/deps/kubernetes/api/model/MetricStatus;)Lio/dekorate/deps/kubernetes/api/model/HorizontalPodAutoscalerStatusFluent$CurrentMetricsNested;
      34: areturn

  public io.dekorate.deps.kubernetes.api.model.HorizontalPodAutoscalerStatusFluent$CurrentMetricsNested<A> editFirstCurrentMetric();
    Code:
       0: aload_0
       1: getfield      #43                 // Field currentMetrics:Ljava/util/List;
       4: invokeinterface #122,  1          // InterfaceMethod java/util/List.size:()I
       9: ifne          23
      12: new           #268                // class java/lang/RuntimeException
      15: dup
      16: ldc_w         #360                // String Can\'t edit first currentMetrics. The list is empty.
      19: invokespecial #273                // Method java/lang/RuntimeException."<init>":(Ljava/lang/String;)V
      22: athrow
      23: aload_0
      24: iconst_0
      25: aload_0
      26: iconst_0
      27: invokevirtual #355                // Method buildCurrentMetric:(I)Lio/dekorate/deps/kubernetes/api/model/MetricStatus;
      30: invokevirtual #357                // Method setNewCurrentMetricLike:(ILio/dekorate/deps/kubernetes/api/model/MetricStatus;)Lio/dekorate/deps/kubernetes/api/model/HorizontalPodAutoscalerStatusFluent$CurrentMetricsNested;
      33: areturn

  public io.dekorate.deps.kubernetes.api.model.HorizontalPodAutoscalerStatusFluent$CurrentMetricsNested<A> editLastCurrentMetric();
    Code:
       0: aload_0
       1: getfield      #43                 // Field currentMetrics:Ljava/util/List;
       4: invokeinterface #122,  1          // InterfaceMethod java/util/List.size:()I
       9: iconst_1
      10: isub
      11: istore_1
      12: iload_1
      13: ifge          27
      16: new           #268                // class java/lang/RuntimeException
      19: dup
      20: ldc_w         #363                // String Can\'t edit last currentMetrics. The list is empty.
      23: invokespecial #273                // Method java/lang/RuntimeException."<init>":(Ljava/lang/String;)V
      26: athrow
      27: aload_0
      28: iload_1
      29: aload_0
      30: iload_1
      31: invokevirtual #355                // Method buildCurrentMetric:(I)Lio/dekorate/deps/kubernetes/api/model/MetricStatus;
      34: invokevirtual #357                // Method setNewCurrentMetricLike:(ILio/dekorate/deps/kubernetes/api/model/MetricStatus;)Lio/dekorate/deps/kubernetes/api/model/HorizontalPodAutoscalerStatusFluent$CurrentMetricsNested;
      37: areturn

  public io.dekorate.deps.kubernetes.api.model.HorizontalPodAutoscalerStatusFluent$CurrentMetricsNested<A> editMatchingCurrentMetric(io.dekorate.deps.kubernetes.api.builder.Predicate<io.dekorate.deps.kubernetes.api.model.MetricStatusBuilder>);
    Code:
       0: iconst_m1
       1: istore_2
       2: iconst_0
       3: istore_3
       4: iload_3
       5: aload_0
       6: getfield      #43                 // Field currentMetrics:Ljava/util/List;
       9: invokeinterface #122,  1          // InterfaceMethod java/util/List.size:()I
      14: if_icmpge     50
      17: aload_1
      18: aload_0
      19: getfield      #43                 // Field currentMetrics:Ljava/util/List;
      22: iload_3
      23: invokeinterface #207,  2          // InterfaceMethod java/util/List.get:(I)Ljava/lang/Object;
      28: invokeinterface #181,  2          // InterfaceMethod io/dekorate/deps/kubernetes/api/builder/Predicate.apply:(Ljava/lang/Object;)Ljava/lang/Boolean;
      33: invokevirtual #186                // Method java/lang/Boolean.booleanValue:()Z
      36: ifeq          44
      39: iload_3
      40: istore_2
      41: goto          50
      44: iinc          3, 1
      47: goto          4
      50: iload_2
      51: ifge          65
      54: new           #268                // class java/lang/RuntimeException
      57: dup
      58: ldc_w         #368                // String Can\'t edit matching currentMetrics. No match found.
      61: invokespecial #273                // Method java/lang/RuntimeException."<init>":(Ljava/lang/String;)V
      64: athrow
      65: aload_0
      66: iload_2
      67: aload_0
      68: iload_2
      69: invokevirtual #355                // Method buildCurrentMetric:(I)Lio/dekorate/deps/kubernetes/api/model/MetricStatus;
      72: invokevirtual #357                // Method setNewCurrentMetricLike:(ILio/dekorate/deps/kubernetes/api/model/MetricStatus;)Lio/dekorate/deps/kubernetes/api/model/HorizontalPodAutoscalerStatusFluent$CurrentMetricsNested;
      75: areturn

  public java.lang.Integer getCurrentReplicas();
    Code:
       0: aload_0
       1: getfield      #370                // Field currentReplicas:Ljava/lang/Integer;
       4: areturn

  public A withCurrentReplicas(java.lang.Integer);
    Code:
       0: aload_0
       1: aload_1
       2: putfield      #370                // Field currentReplicas:Ljava/lang/Integer;
       5: aload_0
       6: areturn

  public java.lang.Boolean hasCurrentReplicas();
    Code:
       0: aload_0
       1: getfield      #370                // Field currentReplicas:Ljava/lang/Integer;
       4: ifnull        11
       7: iconst_1
       8: goto          12
      11: iconst_0
      12: invokestatic  #222                // Method java/lang/Boolean.valueOf:(Z)Ljava/lang/Boolean;
      15: areturn

  public java.lang.Integer getDesiredReplicas();
    Code:
       0: aload_0
       1: getfield      #374                // Field desiredReplicas:Ljava/lang/Integer;
       4: areturn

  public A withDesiredReplicas(java.lang.Integer);
    Code:
       0: aload_0
       1: aload_1
       2: putfield      #374                // Field desiredReplicas:Ljava/lang/Integer;
       5: aload_0
       6: areturn

  public java.lang.Boolean hasDesiredReplicas();
    Code:
       0: aload_0
       1: getfield      #374                // Field desiredReplicas:Ljava/lang/Integer;
       4: ifnull        11
       7: iconst_1
       8: goto          12
      11: iconst_0
      12: invokestatic  #222                // Method java/lang/Boolean.valueOf:(Z)Ljava/lang/Boolean;
      15: areturn

  public java.lang.String getLastScaleTime();
    Code:
       0: aload_0
       1: getfield      #377                // Field lastScaleTime:Ljava/lang/String;
       4: areturn

  public A withLastScaleTime(java.lang.String);
    Code:
       0: aload_0
       1: aload_1
       2: putfield      #377                // Field lastScaleTime:Ljava/lang/String;
       5: aload_0
       6: areturn

  public java.lang.Boolean hasLastScaleTime();
    Code:
       0: aload_0
       1: getfield      #377                // Field lastScaleTime:Ljava/lang/String;
       4: ifnull        11
       7: iconst_1
       8: goto          12
      11: iconst_0
      12: invokestatic  #222                // Method java/lang/Boolean.valueOf:(Z)Ljava/lang/Boolean;
      15: areturn

  public A withNewLastScaleTime(java.lang.String);
    Code:
       0: aload_0
       1: new           #382                // class java/lang/String
       4: dup
       5: aload_1
       6: invokespecial #383                // Method java/lang/String."<init>":(Ljava/lang/String;)V
       9: invokevirtual #85                 // Method withLastScaleTime:(Ljava/lang/String;)Lio/dekorate/deps/kubernetes/api/model/HorizontalPodAutoscalerStatusFluent;
      12: areturn

  public A withNewLastScaleTime(java.lang.StringBuilder);
    Code:
       0: aload_0
       1: new           #382                // class java/lang/String
       4: dup
       5: aload_1
       6: invokespecial #389                // Method java/lang/String."<init>":(Ljava/lang/StringBuilder;)V
       9: invokevirtual #85                 // Method withLastScaleTime:(Ljava/lang/String;)Lio/dekorate/deps/kubernetes/api/model/HorizontalPodAutoscalerStatusFluent;
      12: areturn

  public A withNewLastScaleTime(java.lang.StringBuffer);
    Code:
       0: aload_0
       1: new           #382                // class java/lang/String
       4: dup
       5: aload_1
       6: invokespecial #395                // Method java/lang/String."<init>":(Ljava/lang/StringBuffer;)V
       9: invokevirtual #85                 // Method withLastScaleTime:(Ljava/lang/String;)Lio/dekorate/deps/kubernetes/api/model/HorizontalPodAutoscalerStatusFluent;
      12: areturn

  public java.lang.Long getObservedGeneration();
    Code:
       0: aload_0
       1: getfield      #398                // Field observedGeneration:Ljava/lang/Long;
       4: areturn

  public A withObservedGeneration(java.lang.Long);
    Code:
       0: aload_0
       1: aload_1
       2: putfield      #398                // Field observedGeneration:Ljava/lang/Long;
       5: aload_0
       6: areturn

  public java.lang.Boolean hasObservedGeneration();
    Code:
       0: aload_0
       1: getfield      #398                // Field observedGeneration:Ljava/lang/Long;
       4: ifnull        11
       7: iconst_1
       8: goto          12
      11: iconst_0
      12: invokestatic  #222                // Method java/lang/Boolean.valueOf:(Z)Ljava/lang/Boolean;
      15: areturn

  public boolean equals(java.lang.Object);
    Code:
       0: aload_0
       1: aload_1
       2: if_acmpne     7
       5: iconst_1
       6: ireturn
       7: aload_1
       8: ifnull        22
      11: aload_0
      12: invokevirtual #407                // Method java/lang/Object.getClass:()Ljava/lang/Class;
      15: aload_1
      16: invokevirtual #407                // Method java/lang/Object.getClass:()Ljava/lang/Class;
      19: if_acmpeq     24
      22: iconst_0
      23: ireturn
      24: aload_1
      25: checkcast     #2                  // class io/dekorate/deps/kubernetes/api/model/HorizontalPodAutoscalerStatusFluentImpl
      28: astore_2
      29: aload_0
      30: getfield      #41                 // Field conditions:Ljava/util/List;
      33: ifnull        55
      36: aload_0
      37: getfield      #41                 // Field conditions:Ljava/util/List;
      40: aload_2
      41: getfield      #41                 // Field conditions:Ljava/util/List;
      44: invokeinterface #409,  2          // InterfaceMethod java/util/List.equals:(Ljava/lang/Object;)Z
      49: ifne          64
      52: goto          62
      55: aload_2
      56: getfield      #41                 // Field conditions:Ljava/util/List;
      59: ifnull        64
      62: iconst_0
      63: ireturn
      64: aload_0
      65: getfield      #43                 // Field currentMetrics:Ljava/util/List;
      68: ifnull        90
      71: aload_0
      72: getfield      #43                 // Field currentMetrics:Ljava/util/List;
      75: aload_2
      76: getfield      #43                 // Field currentMetrics:Ljava/util/List;
      79: invokeinterface #409,  2          // InterfaceMethod java/util/List.equals:(Ljava/lang/Object;)Z
      84: ifne          99
      87: goto          97
      90: aload_2
      91: getfield      #43                 // Field currentMetrics:Ljava/util/List;
      94: ifnull        99
      97: iconst_0
      98: ireturn
      99: aload_0
     100: getfield      #370                // Field currentReplicas:Ljava/lang/Integer;
     103: ifnull        123
     106: aload_0
     107: getfield      #370                // Field currentReplicas:Ljava/lang/Integer;
     110: aload_2
     111: getfield      #370                // Field currentReplicas:Ljava/lang/Integer;
     114: invokevirtual #412                // Method java/lang/Integer.equals:(Ljava/lang/Object;)Z
     117: ifne          132
     120: goto          130
     123: aload_2
     124: getfield      #370                // Field currentReplicas:Ljava/lang/Integer;
     127: ifnull        132
     130: iconst_0
     131: ireturn
     132: aload_0
     133: getfield      #374                // Field desiredReplicas:Ljava/lang/Integer;
     136: ifnull        156
     139: aload_0
     140: getfield      #374                // Field desiredReplicas:Ljava/lang/Integer;
     143: aload_2
     144: getfield      #374                // Field desiredReplicas:Ljava/lang/Integer;
     147: invokevirtual #412                // Method java/lang/Integer.equals:(Ljava/lang/Object;)Z
     150: ifne          165
     153: goto          163
     156: aload_2
     157: getfield      #374                // Field desiredReplicas:Ljava/lang/Integer;
     160: ifnull        165
     163: iconst_0
     164: ireturn
     165: aload_0
     166: getfield      #377                // Field lastScaleTime:Ljava/lang/String;
     169: ifnull        189
     172: aload_0
     173: getfield      #377                // Field lastScaleTime:Ljava/lang/String;
     176: aload_2
     177: getfield      #377                // Field lastScaleTime:Ljava/lang/String;
     180: invokevirtual #413                // Method java/lang/String.equals:(Ljava/lang/Object;)Z
     183: ifne          198
     186: goto          196
     189: aload_2
     190: getfield      #377                // Field lastScaleTime:Ljava/lang/String;
     193: ifnull        198
     196: iconst_0
     197: ireturn
     198: aload_0
     199: getfield      #398                // Field observedGeneration:Ljava/lang/Long;
     202: ifnull        222
     205: aload_0
     206: getfield      #398                // Field observedGeneration:Ljava/lang/Long;
     209: aload_2
     210: getfield      #398                // Field observedGeneration:Ljava/lang/Long;
     213: invokevirtual #416                // Method java/lang/Long.equals:(Ljava/lang/Object;)Z
     216: ifne          231
     219: goto          229
     222: aload_2
     223: getfield      #398                // Field observedGeneration:Ljava/lang/Long;
     226: ifnull        231
     229: iconst_0
     230: ireturn
     231: iconst_1
     232: ireturn
}
