Compiled from "HTTPGetActionBuilder.java"
public class io.dekorate.deps.kubernetes.api.model.HTTPGetActionBuilder extends io.dekorate.deps.kubernetes.api.model.HTTPGetActionFluentImpl<io.dekorate.deps.kubernetes.api.model.HTTPGetActionBuilder> implements io.dekorate.deps.kubernetes.api.builder.VisitableBuilder<io.dekorate.deps.kubernetes.api.model.HTTPGetAction, io.dekorate.deps.kubernetes.api.model.HTTPGetActionBuilder> {
  io.dekorate.deps.kubernetes.api.model.HTTPGetActionFluent<?> fluent;

  java.lang.Boolean validationEnabled;

  public io.dekorate.deps.kubernetes.api.model.HTTPGetActionBuilder();
    Code:
       0: aload_0
       1: iconst_1
       2: invokestatic  #21                 // Method java/lang/Boolean.valueOf:(Z)Ljava/lang/Boolean;
       5: invokespecial #24                 // Method "<init>":(Ljava/lang/Boolean;)V
       8: return

  public io.dekorate.deps.kubernetes.api.model.HTTPGetActionBuilder(java.lang.Boolean);
    Code:
       0: aload_0
       1: new           #28                 // class io/dekorate/deps/kubernetes/api/model/HTTPGetAction
       4: dup
       5: invokespecial #30                 // Method io/dekorate/deps/kubernetes/api/model/HTTPGetAction."<init>":()V
       8: aload_1
       9: invokespecial #33                 // Method "<init>":(Lio/dekorate/deps/kubernetes/api/model/HTTPGetAction;Ljava/lang/Boolean;)V
      12: return

  public io.dekorate.deps.kubernetes.api.model.HTTPGetActionBuilder(io.dekorate.deps.kubernetes.api.model.HTTPGetActionFluent<?>);
    Code:
       0: aload_0
       1: aload_1
       2: iconst_1
       3: invokestatic  #21                 // Method java/lang/Boolean.valueOf:(Z)Ljava/lang/Boolean;
       6: invokespecial #38                 // Method "<init>":(Lio/dekorate/deps/kubernetes/api/model/HTTPGetActionFluent;Ljava/lang/Boolean;)V
       9: return

  public io.dekorate.deps.kubernetes.api.model.HTTPGetActionBuilder(io.dekorate.deps.kubernetes.api.model.HTTPGetActionFluent<?>, java.lang.Boolean);
    Code:
       0: aload_0
       1: aload_1
       2: new           #28                 // class io/dekorate/deps/kubernetes/api/model/HTTPGetAction
       5: dup
       6: invokespecial #30                 // Method io/dekorate/deps/kubernetes/api/model/HTTPGetAction."<init>":()V
       9: aload_2
      10: invokespecial #42                 // Method "<init>":(Lio/dekorate/deps/kubernetes/api/model/HTTPGetActionFluent;Lio/dekorate/deps/kubernetes/api/model/HTTPGetAction;Ljava/lang/Boolean;)V
      13: return

  public io.dekorate.deps.kubernetes.api.model.HTTPGetActionBuilder(io.dekorate.deps.kubernetes.api.model.HTTPGetActionFluent<?>, io.dekorate.deps.kubernetes.api.model.HTTPGetAction);
    Code:
       0: aload_0
       1: aload_1
       2: aload_2
       3: iconst_1
       4: invokestatic  #21                 // Method java/lang/Boolean.valueOf:(Z)Ljava/lang/Boolean;
       7: invokespecial #42                 // Method "<init>":(Lio/dekorate/deps/kubernetes/api/model/HTTPGetActionFluent;Lio/dekorate/deps/kubernetes/api/model/HTTPGetAction;Ljava/lang/Boolean;)V
      10: return

  public io.dekorate.deps.kubernetes.api.model.HTTPGetActionBuilder(io.dekorate.deps.kubernetes.api.model.HTTPGetActionFluent<?>, io.dekorate.deps.kubernetes.api.model.HTTPGetAction, java.lang.Boolean);
    Code:
       0: aload_0
       1: invokespecial #48                 // Method io/dekorate/deps/kubernetes/api/model/HTTPGetActionFluentImpl."<init>":()V
       4: aload_0
       5: aload_1
       6: putfield      #50                 // Field fluent:Lio/dekorate/deps/kubernetes/api/model/HTTPGetActionFluent;
       9: aload_1
      10: aload_2
      11: invokevirtual #54                 // Method io/dekorate/deps/kubernetes/api/model/HTTPGetAction.getHost:()Ljava/lang/String;
      14: invokeinterface #60,  2           // InterfaceMethod io/dekorate/deps/kubernetes/api/model/HTTPGetActionFluent.withHost:(Ljava/lang/String;)Lio/dekorate/deps/kubernetes/api/model/HTTPGetActionFluent;
      19: pop
      20: aload_1
      21: aload_2
      22: invokevirtual #64                 // Method io/dekorate/deps/kubernetes/api/model/HTTPGetAction.getHttpHeaders:()Ljava/util/List;
      25: invokeinterface #68,  2           // InterfaceMethod io/dekorate/deps/kubernetes/api/model/HTTPGetActionFluent.withHttpHeaders:(Ljava/util/List;)Lio/dekorate/deps/kubernetes/api/model/HTTPGetActionFluent;
      30: pop
      31: aload_1
      32: aload_2
      33: invokevirtual #71                 // Method io/dekorate/deps/kubernetes/api/model/HTTPGetAction.getPath:()Ljava/lang/String;
      36: invokeinterface #74,  2           // InterfaceMethod io/dekorate/deps/kubernetes/api/model/HTTPGetActionFluent.withPath:(Ljava/lang/String;)Lio/dekorate/deps/kubernetes/api/model/HTTPGetActionFluent;
      41: pop
      42: aload_1
      43: aload_2
      44: invokevirtual #78                 // Method io/dekorate/deps/kubernetes/api/model/HTTPGetAction.getPort:()Lio/dekorate/deps/kubernetes/api/model/IntOrString;
      47: invokeinterface #82,  2           // InterfaceMethod io/dekorate/deps/kubernetes/api/model/HTTPGetActionFluent.withPort:(Lio/dekorate/deps/kubernetes/api/model/IntOrString;)Lio/dekorate/deps/kubernetes/api/model/HTTPGetActionFluent;
      52: pop
      53: aload_1
      54: aload_2
      55: invokevirtual #85                 // Method io/dekorate/deps/kubernetes/api/model/HTTPGetAction.getScheme:()Ljava/lang/String;
      58: invokeinterface #88,  2           // InterfaceMethod io/dekorate/deps/kubernetes/api/model/HTTPGetActionFluent.withScheme:(Ljava/lang/String;)Lio/dekorate/deps/kubernetes/api/model/HTTPGetActionFluent;
      63: pop
      64: aload_0
      65: aload_3
      66: putfield      #90                 // Field validationEnabled:Ljava/lang/Boolean;
      69: return

  public io.dekorate.deps.kubernetes.api.model.HTTPGetActionBuilder(io.dekorate.deps.kubernetes.api.model.HTTPGetAction);
    Code:
       0: aload_0
       1: aload_1
       2: iconst_1
       3: invokestatic  #21                 // Method java/lang/Boolean.valueOf:(Z)Ljava/lang/Boolean;
       6: invokespecial #33                 // Method "<init>":(Lio/dekorate/deps/kubernetes/api/model/HTTPGetAction;Ljava/lang/Boolean;)V
       9: return

  public io.dekorate.deps.kubernetes.api.model.HTTPGetActionBuilder(io.dekorate.deps.kubernetes.api.model.HTTPGetAction, java.lang.Boolean);
    Code:
       0: aload_0
       1: invokespecial #48                 // Method io/dekorate/deps/kubernetes/api/model/HTTPGetActionFluentImpl."<init>":()V
       4: aload_0
       5: aload_0
       6: putfield      #50                 // Field fluent:Lio/dekorate/deps/kubernetes/api/model/HTTPGetActionFluent;
       9: aload_0
      10: aload_1
      11: invokevirtual #54                 // Method io/dekorate/deps/kubernetes/api/model/HTTPGetAction.getHost:()Ljava/lang/String;
      14: invokevirtual #92                 // Method withHost:(Ljava/lang/String;)Lio/dekorate/deps/kubernetes/api/model/HTTPGetActionFluent;
      17: pop
      18: aload_0
      19: aload_1
      20: invokevirtual #64                 // Method io/dekorate/deps/kubernetes/api/model/HTTPGetAction.getHttpHeaders:()Ljava/util/List;
      23: invokevirtual #93                 // Method withHttpHeaders:(Ljava/util/List;)Lio/dekorate/deps/kubernetes/api/model/HTTPGetActionFluent;
      26: pop
      27: aload_0
      28: aload_1
      29: invokevirtual #71                 // Method io/dekorate/deps/kubernetes/api/model/HTTPGetAction.getPath:()Ljava/lang/String;
      32: invokevirtual #94                 // Method withPath:(Ljava/lang/String;)Lio/dekorate/deps/kubernetes/api/model/HTTPGetActionFluent;
      35: pop
      36: aload_0
      37: aload_1
      38: invokevirtual #78                 // Method io/dekorate/deps/kubernetes/api/model/HTTPGetAction.getPort:()Lio/dekorate/deps/kubernetes/api/model/IntOrString;
      41: invokevirtual #95                 // Method withPort:(Lio/dekorate/deps/kubernetes/api/model/IntOrString;)Lio/dekorate/deps/kubernetes/api/model/HTTPGetActionFluent;
      44: pop
      45: aload_0
      46: aload_1
      47: invokevirtual #85                 // Method io/dekorate/deps/kubernetes/api/model/HTTPGetAction.getScheme:()Ljava/lang/String;
      50: invokevirtual #96                 // Method withScheme:(Ljava/lang/String;)Lio/dekorate/deps/kubernetes/api/model/HTTPGetActionFluent;
      53: pop
      54: aload_0
      55: aload_2
      56: putfield      #90                 // Field validationEnabled:Ljava/lang/Boolean;
      59: return

  public io.dekorate.deps.kubernetes.api.model.HTTPGetAction build();
    Code:
       0: new           #28                 // class io/dekorate/deps/kubernetes/api/model/HTTPGetAction
       3: dup
       4: aload_0
       5: getfield      #50                 // Field fluent:Lio/dekorate/deps/kubernetes/api/model/HTTPGetActionFluent;
       8: invokeinterface #99,  1           // InterfaceMethod io/dekorate/deps/kubernetes/api/model/HTTPGetActionFluent.getHost:()Ljava/lang/String;
      13: aload_0
      14: getfield      #50                 // Field fluent:Lio/dekorate/deps/kubernetes/api/model/HTTPGetActionFluent;
      17: invokeinterface #100,  1          // InterfaceMethod io/dekorate/deps/kubernetes/api/model/HTTPGetActionFluent.getHttpHeaders:()Ljava/util/List;
      22: aload_0
      23: getfield      #50                 // Field fluent:Lio/dekorate/deps/kubernetes/api/model/HTTPGetActionFluent;
      26: invokeinterface #101,  1          // InterfaceMethod io/dekorate/deps/kubernetes/api/model/HTTPGetActionFluent.getPath:()Ljava/lang/String;
      31: aload_0
      32: getfield      #50                 // Field fluent:Lio/dekorate/deps/kubernetes/api/model/HTTPGetActionFluent;
      35: invokeinterface #102,  1          // InterfaceMethod io/dekorate/deps/kubernetes/api/model/HTTPGetActionFluent.getPort:()Lio/dekorate/deps/kubernetes/api/model/IntOrString;
      40: aload_0
      41: getfield      #50                 // Field fluent:Lio/dekorate/deps/kubernetes/api/model/HTTPGetActionFluent;
      44: invokeinterface #103,  1          // InterfaceMethod io/dekorate/deps/kubernetes/api/model/HTTPGetActionFluent.getScheme:()Ljava/lang/String;
      49: invokespecial #106                // Method io/dekorate/deps/kubernetes/api/model/HTTPGetAction."<init>":(Ljava/lang/String;Ljava/util/List;Ljava/lang/String;Lio/dekorate/deps/kubernetes/api/model/IntOrString;Ljava/lang/String;)V
      52: astore_1
      53: aload_1
      54: areturn

  public boolean equals(java.lang.Object);
    Code:
       0: aload_0
       1: aload_1
       2: if_acmpne     7
       5: iconst_1
       6: ireturn
       7: aload_1
       8: ifnull        22
      11: aload_0
      12: invokevirtual #115                // Method java/lang/Object.getClass:()Ljava/lang/Class;
      15: aload_1
      16: invokevirtual #115                // Method java/lang/Object.getClass:()Ljava/lang/Class;
      19: if_acmpeq     24
      22: iconst_0
      23: ireturn
      24: aload_0
      25: aload_1
      26: invokespecial #117                // Method io/dekorate/deps/kubernetes/api/model/HTTPGetActionFluentImpl.equals:(Ljava/lang/Object;)Z
      29: ifne          34
      32: iconst_0
      33: ireturn
      34: aload_1
      35: checkcast     #2                  // class io/dekorate/deps/kubernetes/api/model/HTTPGetActionBuilder
      38: astore_2
      39: aload_0
      40: getfield      #50                 // Field fluent:Lio/dekorate/deps/kubernetes/api/model/HTTPGetActionFluent;
      43: ifnull        71
      46: aload_0
      47: getfield      #50                 // Field fluent:Lio/dekorate/deps/kubernetes/api/model/HTTPGetActionFluent;
      50: aload_0
      51: if_acmpeq     71
      54: aload_0
      55: getfield      #50                 // Field fluent:Lio/dekorate/deps/kubernetes/api/model/HTTPGetActionFluent;
      58: aload_2
      59: getfield      #50                 // Field fluent:Lio/dekorate/deps/kubernetes/api/model/HTTPGetActionFluent;
      62: invokevirtual #118                // Method java/lang/Object.equals:(Ljava/lang/Object;)Z
      65: ifne          88
      68: goto          86
      71: aload_2
      72: getfield      #50                 // Field fluent:Lio/dekorate/deps/kubernetes/api/model/HTTPGetActionFluent;
      75: ifnull        88
      78: aload_0
      79: getfield      #50                 // Field fluent:Lio/dekorate/deps/kubernetes/api/model/HTTPGetActionFluent;
      82: aload_0
      83: if_acmpeq     88
      86: iconst_0
      87: ireturn
      88: aload_0
      89: getfield      #90                 // Field validationEnabled:Ljava/lang/Boolean;
      92: ifnull        112
      95: aload_0
      96: getfield      #90                 // Field validationEnabled:Ljava/lang/Boolean;
      99: aload_2
     100: getfield      #90                 // Field validationEnabled:Ljava/lang/Boolean;
     103: invokevirtual #119                // Method java/lang/Boolean.equals:(Ljava/lang/Object;)Z
     106: ifne          121
     109: goto          119
     112: aload_2
     113: getfield      #90                 // Field validationEnabled:Ljava/lang/Boolean;
     116: ifnull        121
     119: iconst_0
     120: ireturn
     121: iconst_1
     122: ireturn

  public java.lang.Object build();
    Code:
       0: aload_0
       1: invokevirtual #125                // Method build:()Lio/dekorate/deps/kubernetes/api/model/HTTPGetAction;
       4: areturn
}
