Compiled from "KubeSchemaFluentImpl.java"
public class io.dekorate.deps.kubernetes.api.model.KubeSchemaFluentImpl$PodPresetSpecNestedImpl<N> extends io.dekorate.deps.kubernetes.api.model.settings.PodPresetSpecFluentImpl<io.dekorate.deps.kubernetes.api.model.KubeSchemaFluent$PodPresetSpecNested<N>> implements io.dekorate.deps.kubernetes.api.model.KubeSchemaFluent$PodPresetSpecNested<N>, io.dekorate.deps.kubernetes.api.builder.Nested<N> {
  private final io.dekorate.deps.kubernetes.api.model.settings.PodPresetSpecBuilder builder;

  final io.dekorate.deps.kubernetes.api.model.KubeSchemaFluentImpl this$0;

  io.dekorate.deps.kubernetes.api.model.KubeSchemaFluentImpl$PodPresetSpecNestedImpl(io.dekorate.deps.kubernetes.api.model.KubeSchemaFluentImpl, io.dekorate.deps.kubernetes.api.model.settings.PodPresetSpec);
    Code:
       0: aload_0
       1: aload_1
       2: putfield      #24                 // Field this$0:Lio/dekorate/deps/kubernetes/api/model/KubeSchemaFluentImpl;
       5: aload_0
       6: invokespecial #27                 // Method io/dekorate/deps/kubernetes/api/model/settings/PodPresetSpecFluentImpl."<init>":()V
       9: aload_0
      10: new           #29                 // class io/dekorate/deps/kubernetes/api/model/settings/PodPresetSpecBuilder
      13: dup
      14: aload_0
      15: aload_2
      16: invokespecial #32                 // Method io/dekorate/deps/kubernetes/api/model/settings/PodPresetSpecBuilder."<init>":(Lio/dekorate/deps/kubernetes/api/model/settings/PodPresetSpecFluent;Lio/dekorate/deps/kubernetes/api/model/settings/PodPresetSpec;)V
      19: putfield      #34                 // Field builder:Lio/dekorate/deps/kubernetes/api/model/settings/PodPresetSpecBuilder;
      22: return

  io.dekorate.deps.kubernetes.api.model.KubeSchemaFluentImpl$PodPresetSpecNestedImpl(io.dekorate.deps.kubernetes.api.model.KubeSchemaFluentImpl);
    Code:
       0: aload_0
       1: aload_1
       2: putfield      #24                 // Field this$0:Lio/dekorate/deps/kubernetes/api/model/KubeSchemaFluentImpl;
       5: aload_0
       6: invokespecial #27                 // Method io/dekorate/deps/kubernetes/api/model/settings/PodPresetSpecFluentImpl."<init>":()V
       9: aload_0
      10: new           #29                 // class io/dekorate/deps/kubernetes/api/model/settings/PodPresetSpecBuilder
      13: dup
      14: aload_0
      15: invokespecial #43                 // Method io/dekorate/deps/kubernetes/api/model/settings/PodPresetSpecBuilder."<init>":(Lio/dekorate/deps/kubernetes/api/model/settings/PodPresetSpecFluent;)V
      18: putfield      #34                 // Field builder:Lio/dekorate/deps/kubernetes/api/model/settings/PodPresetSpecBuilder;
      21: return

  public N and();
    Code:
       0: aload_0
       1: getfield      #24                 // Field this$0:Lio/dekorate/deps/kubernetes/api/model/KubeSchemaFluentImpl;
       4: aload_0
       5: getfield      #34                 // Field builder:Lio/dekorate/deps/kubernetes/api/model/settings/PodPresetSpecBuilder;
       8: invokevirtual #50                 // Method io/dekorate/deps/kubernetes/api/model/settings/PodPresetSpecBuilder.build:()Lio/dekorate/deps/kubernetes/api/model/settings/PodPresetSpec;
      11: invokevirtual #54                 // Method io/dekorate/deps/kubernetes/api/model/KubeSchemaFluentImpl.withPodPresetSpec:(Lio/dekorate/deps/kubernetes/api/model/settings/PodPresetSpec;)Lio/dekorate/deps/kubernetes/api/model/KubeSchemaFluent;
      14: areturn

  public N endPodPresetSpec();
    Code:
       0: aload_0
       1: invokevirtual #57                 // Method and:()Ljava/lang/Object;
       4: areturn
}
