Compiled from "KubeSchemaFluentImpl.java"
public class io.dekorate.deps.kubernetes.api.model.KubeSchemaFluentImpl$NetworkPolicyListNestedImpl<N> extends io.dekorate.deps.kubernetes.api.model.networking.NetworkPolicyListFluentImpl<io.dekorate.deps.kubernetes.api.model.KubeSchemaFluent$NetworkPolicyListNested<N>> implements io.dekorate.deps.kubernetes.api.model.KubeSchemaFluent$NetworkPolicyListNested<N>, io.dekorate.deps.kubernetes.api.builder.Nested<N> {
  private final io.dekorate.deps.kubernetes.api.model.networking.NetworkPolicyListBuilder builder;

  final io.dekorate.deps.kubernetes.api.model.KubeSchemaFluentImpl this$0;

  io.dekorate.deps.kubernetes.api.model.KubeSchemaFluentImpl$NetworkPolicyListNestedImpl(io.dekorate.deps.kubernetes.api.model.KubeSchemaFluentImpl, io.dekorate.deps.kubernetes.api.model.networking.NetworkPolicyList);
    Code:
       0: aload_0
       1: aload_1
       2: putfield      #24                 // Field this$0:Lio/dekorate/deps/kubernetes/api/model/KubeSchemaFluentImpl;
       5: aload_0
       6: invokespecial #27                 // Method io/dekorate/deps/kubernetes/api/model/networking/NetworkPolicyListFluentImpl."<init>":()V
       9: aload_0
      10: new           #29                 // class io/dekorate/deps/kubernetes/api/model/networking/NetworkPolicyListBuilder
      13: dup
      14: aload_0
      15: aload_2
      16: invokespecial #32                 // Method io/dekorate/deps/kubernetes/api/model/networking/NetworkPolicyListBuilder."<init>":(Lio/dekorate/deps/kubernetes/api/model/networking/NetworkPolicyListFluent;Lio/dekorate/deps/kubernetes/api/model/networking/NetworkPolicyList;)V
      19: putfield      #34                 // Field builder:Lio/dekorate/deps/kubernetes/api/model/networking/NetworkPolicyListBuilder;
      22: return

  io.dekorate.deps.kubernetes.api.model.KubeSchemaFluentImpl$NetworkPolicyListNestedImpl(io.dekorate.deps.kubernetes.api.model.KubeSchemaFluentImpl);
    Code:
       0: aload_0
       1: aload_1
       2: putfield      #24                 // Field this$0:Lio/dekorate/deps/kubernetes/api/model/KubeSchemaFluentImpl;
       5: aload_0
       6: invokespecial #27                 // Method io/dekorate/deps/kubernetes/api/model/networking/NetworkPolicyListFluentImpl."<init>":()V
       9: aload_0
      10: new           #29                 // class io/dekorate/deps/kubernetes/api/model/networking/NetworkPolicyListBuilder
      13: dup
      14: aload_0
      15: invokespecial #43                 // Method io/dekorate/deps/kubernetes/api/model/networking/NetworkPolicyListBuilder."<init>":(Lio/dekorate/deps/kubernetes/api/model/networking/NetworkPolicyListFluent;)V
      18: putfield      #34                 // Field builder:Lio/dekorate/deps/kubernetes/api/model/networking/NetworkPolicyListBuilder;
      21: return

  public N and();
    Code:
       0: aload_0
       1: getfield      #24                 // Field this$0:Lio/dekorate/deps/kubernetes/api/model/KubeSchemaFluentImpl;
       4: aload_0
       5: getfield      #34                 // Field builder:Lio/dekorate/deps/kubernetes/api/model/networking/NetworkPolicyListBuilder;
       8: invokevirtual #50                 // Method io/dekorate/deps/kubernetes/api/model/networking/NetworkPolicyListBuilder.build:()Lio/dekorate/deps/kubernetes/api/model/networking/NetworkPolicyList;
      11: invokevirtual #54                 // Method io/dekorate/deps/kubernetes/api/model/KubeSchemaFluentImpl.withNetworkPolicyList:(Lio/dekorate/deps/kubernetes/api/model/networking/NetworkPolicyList;)Lio/dekorate/deps/kubernetes/api/model/KubeSchemaFluent;
      14: areturn

  public N endNetworkPolicyList();
    Code:
       0: aload_0
       1: invokevirtual #57                 // Method and:()Ljava/lang/Object;
       4: areturn
}
