Compiled from "NamedExtensionFluentImpl.java"
public class io.dekorate.deps.kubernetes.api.model.NamedExtensionFluentImpl$PodMetricsExtensionNestedImpl<N> extends io.dekorate.deps.kubernetes.api.model.metrics.v1beta1.PodMetricsFluentImpl<io.dekorate.deps.kubernetes.api.model.NamedExtensionFluent$PodMetricsExtensionNested<N>> implements io.dekorate.deps.kubernetes.api.model.NamedExtensionFluent$PodMetricsExtensionNested<N>, io.dekorate.deps.kubernetes.api.builder.Nested<N> {
  private final io.dekorate.deps.kubernetes.api.model.metrics.v1beta1.PodMetricsBuilder builder;

  final io.dekorate.deps.kubernetes.api.model.NamedExtensionFluentImpl this$0;

  io.dekorate.deps.kubernetes.api.model.NamedExtensionFluentImpl$PodMetricsExtensionNestedImpl(io.dekorate.deps.kubernetes.api.model.NamedExtensionFluentImpl, io.dekorate.deps.kubernetes.api.model.metrics.v1beta1.PodMetrics);
    Code:
       0: aload_0
       1: aload_1
       2: putfield      #24                 // Field this$0:Lio/dekorate/deps/kubernetes/api/model/NamedExtensionFluentImpl;
       5: aload_0
       6: invokespecial #27                 // Method io/dekorate/deps/kubernetes/api/model/metrics/v1beta1/PodMetricsFluentImpl."<init>":()V
       9: aload_0
      10: new           #29                 // class io/dekorate/deps/kubernetes/api/model/metrics/v1beta1/PodMetricsBuilder
      13: dup
      14: aload_0
      15: aload_2
      16: invokespecial #32                 // Method io/dekorate/deps/kubernetes/api/model/metrics/v1beta1/PodMetricsBuilder."<init>":(Lio/dekorate/deps/kubernetes/api/model/metrics/v1beta1/PodMetricsFluent;Lio/dekorate/deps/kubernetes/api/model/metrics/v1beta1/PodMetrics;)V
      19: putfield      #34                 // Field builder:Lio/dekorate/deps/kubernetes/api/model/metrics/v1beta1/PodMetricsBuilder;
      22: return

  io.dekorate.deps.kubernetes.api.model.NamedExtensionFluentImpl$PodMetricsExtensionNestedImpl(io.dekorate.deps.kubernetes.api.model.NamedExtensionFluentImpl);
    Code:
       0: aload_0
       1: aload_1
       2: putfield      #24                 // Field this$0:Lio/dekorate/deps/kubernetes/api/model/NamedExtensionFluentImpl;
       5: aload_0
       6: invokespecial #27                 // Method io/dekorate/deps/kubernetes/api/model/metrics/v1beta1/PodMetricsFluentImpl."<init>":()V
       9: aload_0
      10: new           #29                 // class io/dekorate/deps/kubernetes/api/model/metrics/v1beta1/PodMetricsBuilder
      13: dup
      14: aload_0
      15: invokespecial #43                 // Method io/dekorate/deps/kubernetes/api/model/metrics/v1beta1/PodMetricsBuilder."<init>":(Lio/dekorate/deps/kubernetes/api/model/metrics/v1beta1/PodMetricsFluent;)V
      18: putfield      #34                 // Field builder:Lio/dekorate/deps/kubernetes/api/model/metrics/v1beta1/PodMetricsBuilder;
      21: return

  public N and();
    Code:
       0: aload_0
       1: getfield      #24                 // Field this$0:Lio/dekorate/deps/kubernetes/api/model/NamedExtensionFluentImpl;
       4: aload_0
       5: getfield      #34                 // Field builder:Lio/dekorate/deps/kubernetes/api/model/metrics/v1beta1/PodMetricsBuilder;
       8: invokevirtual #50                 // Method io/dekorate/deps/kubernetes/api/model/metrics/v1beta1/PodMetricsBuilder.build:()Lio/dekorate/deps/kubernetes/api/model/metrics/v1beta1/PodMetrics;
      11: invokevirtual #54                 // Method io/dekorate/deps/kubernetes/api/model/NamedExtensionFluentImpl.withExtension:(Lio/dekorate/deps/kubernetes/api/model/HasMetadata;)Lio/dekorate/deps/kubernetes/api/model/NamedExtensionFluent;
      14: areturn

  public N endPodMetricsExtension();
    Code:
       0: aload_0
       1: invokevirtual #57                 // Method and:()Ljava/lang/Object;
       4: areturn
}
