Compiled from "NodeSpecFluentImpl.java"
public class io.dekorate.deps.kubernetes.api.model.NodeSpecFluentImpl<A extends io.dekorate.deps.kubernetes.api.model.NodeSpecFluent<A>> extends io.dekorate.deps.kubernetes.api.builder.BaseFluent<A> implements io.dekorate.deps.kubernetes.api.model.NodeSpecFluent<A> {
  private io.dekorate.deps.kubernetes.api.model.NodeConfigSourceBuilder configSource;

  private java.lang.String externalID;

  private java.lang.String podCIDR;

  private java.util.List<java.lang.String> podCIDRs;

  private java.lang.String providerID;

  private java.util.List<io.dekorate.deps.kubernetes.api.model.TaintBuilder> taints;

  private java.lang.Boolean unschedulable;

  public io.dekorate.deps.kubernetes.api.model.NodeSpecFluentImpl();
    Code:
       0: aload_0
       1: invokespecial #37                 // Method io/dekorate/deps/kubernetes/api/builder/BaseFluent."<init>":()V
       4: aload_0
       5: new           #39                 // class java/util/ArrayList
       8: dup
       9: invokespecial #40                 // Method java/util/ArrayList."<init>":()V
      12: putfield      #42                 // Field podCIDRs:Ljava/util/List;
      15: aload_0
      16: new           #39                 // class java/util/ArrayList
      19: dup
      20: invokespecial #40                 // Method java/util/ArrayList."<init>":()V
      23: putfield      #44                 // Field taints:Ljava/util/List;
      26: return

  public io.dekorate.deps.kubernetes.api.model.NodeSpecFluentImpl(io.dekorate.deps.kubernetes.api.model.NodeSpec);
    Code:
       0: aload_0
       1: invokespecial #37                 // Method io/dekorate/deps/kubernetes/api/builder/BaseFluent."<init>":()V
       4: aload_0
       5: new           #39                 // class java/util/ArrayList
       8: dup
       9: invokespecial #40                 // Method java/util/ArrayList."<init>":()V
      12: putfield      #42                 // Field podCIDRs:Ljava/util/List;
      15: aload_0
      16: new           #39                 // class java/util/ArrayList
      19: dup
      20: invokespecial #40                 // Method java/util/ArrayList."<init>":()V
      23: putfield      #44                 // Field taints:Ljava/util/List;
      26: aload_0
      27: aload_1
      28: invokevirtual #54                 // Method io/dekorate/deps/kubernetes/api/model/NodeSpec.getConfigSource:()Lio/dekorate/deps/kubernetes/api/model/NodeConfigSource;
      31: invokevirtual #58                 // Method withConfigSource:(Lio/dekorate/deps/kubernetes/api/model/NodeConfigSource;)Lio/dekorate/deps/kubernetes/api/model/NodeSpecFluent;
      34: pop
      35: aload_0
      36: aload_1
      37: invokevirtual #62                 // Method io/dekorate/deps/kubernetes/api/model/NodeSpec.getExternalID:()Ljava/lang/String;
      40: invokevirtual #66                 // Method withExternalID:(Ljava/lang/String;)Lio/dekorate/deps/kubernetes/api/model/NodeSpecFluent;
      43: pop
      44: aload_0
      45: aload_1
      46: invokevirtual #69                 // Method io/dekorate/deps/kubernetes/api/model/NodeSpec.getPodCIDR:()Ljava/lang/String;
      49: invokevirtual #72                 // Method withPodCIDR:(Ljava/lang/String;)Lio/dekorate/deps/kubernetes/api/model/NodeSpecFluent;
      52: pop
      53: aload_0
      54: aload_1
      55: invokevirtual #76                 // Method io/dekorate/deps/kubernetes/api/model/NodeSpec.getPodCIDRs:()Ljava/util/List;
      58: invokevirtual #80                 // Method withPodCIDRs:(Ljava/util/List;)Lio/dekorate/deps/kubernetes/api/model/NodeSpecFluent;
      61: pop
      62: aload_0
      63: aload_1
      64: invokevirtual #83                 // Method io/dekorate/deps/kubernetes/api/model/NodeSpec.getProviderID:()Ljava/lang/String;
      67: invokevirtual #86                 // Method withProviderID:(Ljava/lang/String;)Lio/dekorate/deps/kubernetes/api/model/NodeSpecFluent;
      70: pop
      71: aload_0
      72: aload_1
      73: invokevirtual #89                 // Method io/dekorate/deps/kubernetes/api/model/NodeSpec.getTaints:()Ljava/util/List;
      76: invokevirtual #92                 // Method withTaints:(Ljava/util/List;)Lio/dekorate/deps/kubernetes/api/model/NodeSpecFluent;
      79: pop
      80: aload_0
      81: aload_1
      82: invokevirtual #96                 // Method io/dekorate/deps/kubernetes/api/model/NodeSpec.getUnschedulable:()Ljava/lang/Boolean;
      85: invokevirtual #100                // Method withUnschedulable:(Ljava/lang/Boolean;)Lio/dekorate/deps/kubernetes/api/model/NodeSpecFluent;
      88: pop
      89: return

  public io.dekorate.deps.kubernetes.api.model.NodeConfigSource getConfigSource();
    Code:
       0: aload_0
       1: getfield      #105                // Field configSource:Lio/dekorate/deps/kubernetes/api/model/NodeConfigSourceBuilder;
       4: ifnull        17
       7: aload_0
       8: getfield      #105                // Field configSource:Lio/dekorate/deps/kubernetes/api/model/NodeConfigSourceBuilder;
      11: invokevirtual #110                // Method io/dekorate/deps/kubernetes/api/model/NodeConfigSourceBuilder.build:()Lio/dekorate/deps/kubernetes/api/model/NodeConfigSource;
      14: goto          18
      17: aconst_null
      18: areturn

  public io.dekorate.deps.kubernetes.api.model.NodeConfigSource buildConfigSource();
    Code:
       0: aload_0
       1: getfield      #105                // Field configSource:Lio/dekorate/deps/kubernetes/api/model/NodeConfigSourceBuilder;
       4: ifnull        17
       7: aload_0
       8: getfield      #105                // Field configSource:Lio/dekorate/deps/kubernetes/api/model/NodeConfigSourceBuilder;
      11: invokevirtual #110                // Method io/dekorate/deps/kubernetes/api/model/NodeConfigSourceBuilder.build:()Lio/dekorate/deps/kubernetes/api/model/NodeConfigSource;
      14: goto          18
      17: aconst_null
      18: areturn

  public A withConfigSource(io.dekorate.deps.kubernetes.api.model.NodeConfigSource);
    Code:
       0: aload_0
       1: getfield      #118                // Field _visitables:Lio/dekorate/deps/kubernetes/api/builder/VisitableMap;
       4: ldc           #119                // String configSource
       6: invokevirtual #125                // Method io/dekorate/deps/kubernetes/api/builder/VisitableMap.get:(Ljava/lang/Object;)Ljava/util/List;
       9: aload_0
      10: getfield      #105                // Field configSource:Lio/dekorate/deps/kubernetes/api/model/NodeConfigSourceBuilder;
      13: invokeinterface #131,  2          // InterfaceMethod java/util/List.remove:(Ljava/lang/Object;)Z
      18: pop
      19: aload_1
      20: ifnull        54
      23: aload_0
      24: new           #107                // class io/dekorate/deps/kubernetes/api/model/NodeConfigSourceBuilder
      27: dup
      28: aload_1
      29: invokespecial #134                // Method io/dekorate/deps/kubernetes/api/model/NodeConfigSourceBuilder."<init>":(Lio/dekorate/deps/kubernetes/api/model/NodeConfigSource;)V
      32: putfield      #105                // Field configSource:Lio/dekorate/deps/kubernetes/api/model/NodeConfigSourceBuilder;
      35: aload_0
      36: getfield      #118                // Field _visitables:Lio/dekorate/deps/kubernetes/api/builder/VisitableMap;
      39: ldc           #119                // String configSource
      41: invokevirtual #125                // Method io/dekorate/deps/kubernetes/api/builder/VisitableMap.get:(Ljava/lang/Object;)Ljava/util/List;
      44: aload_0
      45: getfield      #105                // Field configSource:Lio/dekorate/deps/kubernetes/api/model/NodeConfigSourceBuilder;
      48: invokeinterface #137,  2          // InterfaceMethod java/util/List.add:(Ljava/lang/Object;)Z
      53: pop
      54: aload_0
      55: areturn

  public java.lang.Boolean hasConfigSource();
    Code:
       0: aload_0
       1: getfield      #105                // Field configSource:Lio/dekorate/deps/kubernetes/api/model/NodeConfigSourceBuilder;
       4: ifnull        11
       7: iconst_1
       8: goto          12
      11: iconst_0
      12: invokestatic  #145                // Method java/lang/Boolean.valueOf:(Z)Ljava/lang/Boolean;
      15: areturn

  public io.dekorate.deps.kubernetes.api.model.NodeSpecFluent$ConfigSourceNested<A> withNewConfigSource();
    Code:
       0: new           #13                 // class io/dekorate/deps/kubernetes/api/model/NodeSpecFluentImpl$ConfigSourceNestedImpl
       3: dup
       4: aload_0
       5: invokespecial #151                // Method io/dekorate/deps/kubernetes/api/model/NodeSpecFluentImpl$ConfigSourceNestedImpl."<init>":(Lio/dekorate/deps/kubernetes/api/model/NodeSpecFluentImpl;)V
       8: areturn

  public io.dekorate.deps.kubernetes.api.model.NodeSpecFluent$ConfigSourceNested<A> withNewConfigSourceLike(io.dekorate.deps.kubernetes.api.model.NodeConfigSource);
    Code:
       0: new           #13                 // class io/dekorate/deps/kubernetes/api/model/NodeSpecFluentImpl$ConfigSourceNestedImpl
       3: dup
       4: aload_0
       5: aload_1
       6: invokespecial #157                // Method io/dekorate/deps/kubernetes/api/model/NodeSpecFluentImpl$ConfigSourceNestedImpl."<init>":(Lio/dekorate/deps/kubernetes/api/model/NodeSpecFluentImpl;Lio/dekorate/deps/kubernetes/api/model/NodeConfigSource;)V
       9: areturn

  public io.dekorate.deps.kubernetes.api.model.NodeSpecFluent$ConfigSourceNested<A> editConfigSource();
    Code:
       0: aload_0
       1: aload_0
       2: invokevirtual #160                // Method getConfigSource:()Lio/dekorate/deps/kubernetes/api/model/NodeConfigSource;
       5: invokevirtual #162                // Method withNewConfigSourceLike:(Lio/dekorate/deps/kubernetes/api/model/NodeConfigSource;)Lio/dekorate/deps/kubernetes/api/model/NodeSpecFluent$ConfigSourceNested;
       8: areturn

  public io.dekorate.deps.kubernetes.api.model.NodeSpecFluent$ConfigSourceNested<A> editOrNewConfigSource();
    Code:
       0: aload_0
       1: aload_0
       2: invokevirtual #160                // Method getConfigSource:()Lio/dekorate/deps/kubernetes/api/model/NodeConfigSource;
       5: ifnull        15
       8: aload_0
       9: invokevirtual #160                // Method getConfigSource:()Lio/dekorate/deps/kubernetes/api/model/NodeConfigSource;
      12: goto          25
      15: new           #107                // class io/dekorate/deps/kubernetes/api/model/NodeConfigSourceBuilder
      18: dup
      19: invokespecial #164                // Method io/dekorate/deps/kubernetes/api/model/NodeConfigSourceBuilder."<init>":()V
      22: invokevirtual #110                // Method io/dekorate/deps/kubernetes/api/model/NodeConfigSourceBuilder.build:()Lio/dekorate/deps/kubernetes/api/model/NodeConfigSource;
      25: invokevirtual #162                // Method withNewConfigSourceLike:(Lio/dekorate/deps/kubernetes/api/model/NodeConfigSource;)Lio/dekorate/deps/kubernetes/api/model/NodeSpecFluent$ConfigSourceNested;
      28: areturn

  public io.dekorate.deps.kubernetes.api.model.NodeSpecFluent$ConfigSourceNested<A> editOrNewConfigSourceLike(io.dekorate.deps.kubernetes.api.model.NodeConfigSource);
    Code:
       0: aload_0
       1: aload_0
       2: invokevirtual #160                // Method getConfigSource:()Lio/dekorate/deps/kubernetes/api/model/NodeConfigSource;
       5: ifnull        15
       8: aload_0
       9: invokevirtual #160                // Method getConfigSource:()Lio/dekorate/deps/kubernetes/api/model/NodeConfigSource;
      12: goto          16
      15: aload_1
      16: invokevirtual #162                // Method withNewConfigSourceLike:(Lio/dekorate/deps/kubernetes/api/model/NodeConfigSource;)Lio/dekorate/deps/kubernetes/api/model/NodeSpecFluent$ConfigSourceNested;
      19: areturn

  public java.lang.String getExternalID();
    Code:
       0: aload_0
       1: getfield      #167                // Field externalID:Ljava/lang/String;
       4: areturn

  public A withExternalID(java.lang.String);
    Code:
       0: aload_0
       1: aload_1
       2: putfield      #167                // Field externalID:Ljava/lang/String;
       5: aload_0
       6: areturn

  public java.lang.Boolean hasExternalID();
    Code:
       0: aload_0
       1: getfield      #167                // Field externalID:Ljava/lang/String;
       4: ifnull        11
       7: iconst_1
       8: goto          12
      11: iconst_0
      12: invokestatic  #145                // Method java/lang/Boolean.valueOf:(Z)Ljava/lang/Boolean;
      15: areturn

  public A withNewExternalID(java.lang.String);
    Code:
       0: aload_0
       1: new           #172                // class java/lang/String
       4: dup
       5: aload_1
       6: invokespecial #175                // Method java/lang/String."<init>":(Ljava/lang/String;)V
       9: invokevirtual #66                 // Method withExternalID:(Ljava/lang/String;)Lio/dekorate/deps/kubernetes/api/model/NodeSpecFluent;
      12: areturn

  public A withNewExternalID(java.lang.StringBuilder);
    Code:
       0: aload_0
       1: new           #172                // class java/lang/String
       4: dup
       5: aload_1
       6: invokespecial #181                // Method java/lang/String."<init>":(Ljava/lang/StringBuilder;)V
       9: invokevirtual #66                 // Method withExternalID:(Ljava/lang/String;)Lio/dekorate/deps/kubernetes/api/model/NodeSpecFluent;
      12: areturn

  public A withNewExternalID(java.lang.StringBuffer);
    Code:
       0: aload_0
       1: new           #172                // class java/lang/String
       4: dup
       5: aload_1
       6: invokespecial #187                // Method java/lang/String."<init>":(Ljava/lang/StringBuffer;)V
       9: invokevirtual #66                 // Method withExternalID:(Ljava/lang/String;)Lio/dekorate/deps/kubernetes/api/model/NodeSpecFluent;
      12: areturn

  public java.lang.String getPodCIDR();
    Code:
       0: aload_0
       1: getfield      #190                // Field podCIDR:Ljava/lang/String;
       4: areturn

  public A withPodCIDR(java.lang.String);
    Code:
       0: aload_0
       1: aload_1
       2: putfield      #190                // Field podCIDR:Ljava/lang/String;
       5: aload_0
       6: areturn

  public java.lang.Boolean hasPodCIDR();
    Code:
       0: aload_0
       1: getfield      #190                // Field podCIDR:Ljava/lang/String;
       4: ifnull        11
       7: iconst_1
       8: goto          12
      11: iconst_0
      12: invokestatic  #145                // Method java/lang/Boolean.valueOf:(Z)Ljava/lang/Boolean;
      15: areturn

  public A withNewPodCIDR(java.lang.String);
    Code:
       0: aload_0
       1: new           #172                // class java/lang/String
       4: dup
       5: aload_1
       6: invokespecial #175                // Method java/lang/String."<init>":(Ljava/lang/String;)V
       9: invokevirtual #72                 // Method withPodCIDR:(Ljava/lang/String;)Lio/dekorate/deps/kubernetes/api/model/NodeSpecFluent;
      12: areturn

  public A withNewPodCIDR(java.lang.StringBuilder);
    Code:
       0: aload_0
       1: new           #172                // class java/lang/String
       4: dup
       5: aload_1
       6: invokespecial #181                // Method java/lang/String."<init>":(Ljava/lang/StringBuilder;)V
       9: invokevirtual #72                 // Method withPodCIDR:(Ljava/lang/String;)Lio/dekorate/deps/kubernetes/api/model/NodeSpecFluent;
      12: areturn

  public A withNewPodCIDR(java.lang.StringBuffer);
    Code:
       0: aload_0
       1: new           #172                // class java/lang/String
       4: dup
       5: aload_1
       6: invokespecial #187                // Method java/lang/String."<init>":(Ljava/lang/StringBuffer;)V
       9: invokevirtual #72                 // Method withPodCIDR:(Ljava/lang/String;)Lio/dekorate/deps/kubernetes/api/model/NodeSpecFluent;
      12: areturn

  public A addToPodCIDRs(int, java.lang.String);
    Code:
       0: aload_0
       1: getfield      #42                 // Field podCIDRs:Ljava/util/List;
       4: ifnonnull     18
       7: aload_0
       8: new           #39                 // class java/util/ArrayList
      11: dup
      12: invokespecial #40                 // Method java/util/ArrayList."<init>":()V
      15: putfield      #42                 // Field podCIDRs:Ljava/util/List;
      18: aload_0
      19: getfield      #42                 // Field podCIDRs:Ljava/util/List;
      22: iload_1
      23: aload_2
      24: invokeinterface #198,  3          // InterfaceMethod java/util/List.add:(ILjava/lang/Object;)V
      29: aload_0
      30: areturn

  public A setToPodCIDRs(int, java.lang.String);
    Code:
       0: aload_0
       1: getfield      #42                 // Field podCIDRs:Ljava/util/List;
       4: ifnonnull     18
       7: aload_0
       8: new           #39                 // class java/util/ArrayList
      11: dup
      12: invokespecial #40                 // Method java/util/ArrayList."<init>":()V
      15: putfield      #42                 // Field podCIDRs:Ljava/util/List;
      18: aload_0
      19: getfield      #42                 // Field podCIDRs:Ljava/util/List;
      22: iload_1
      23: aload_2
      24: invokeinterface #205,  3          // InterfaceMethod java/util/List.set:(ILjava/lang/Object;)Ljava/lang/Object;
      29: pop
      30: aload_0
      31: areturn

  public A addToPodCIDRs(java.lang.String...);
    Code:
       0: aload_0
       1: getfield      #42                 // Field podCIDRs:Ljava/util/List;
       4: ifnonnull     18
       7: aload_0
       8: new           #39                 // class java/util/ArrayList
      11: dup
      12: invokespecial #40                 // Method java/util/ArrayList."<init>":()V
      15: putfield      #42                 // Field podCIDRs:Ljava/util/List;
      18: aload_1
      19: astore_2
      20: aload_2
      21: arraylength
      22: istore_3
      23: iconst_0
      24: istore        4
      26: iload         4
      28: iload_3
      29: if_icmpge     56
      32: aload_2
      33: iload         4
      35: aaload
      36: astore        5
      38: aload_0
      39: getfield      #42                 // Field podCIDRs:Ljava/util/List;
      42: aload         5
      44: invokeinterface #137,  2          // InterfaceMethod java/util/List.add:(Ljava/lang/Object;)Z
      49: pop
      50: iinc          4, 1
      53: goto          26
      56: aload_0
      57: areturn

  public A addAllToPodCIDRs(java.util.Collection<java.lang.String>);
    Code:
       0: aload_0
       1: getfield      #42                 // Field podCIDRs:Ljava/util/List;
       4: ifnonnull     18
       7: aload_0
       8: new           #39                 // class java/util/ArrayList
      11: dup
      12: invokespecial #40                 // Method java/util/ArrayList."<init>":()V
      15: putfield      #42                 // Field podCIDRs:Ljava/util/List;
      18: aload_1
      19: invokeinterface #219,  1          // InterfaceMethod java/util/Collection.iterator:()Ljava/util/Iterator;
      24: astore_2
      25: aload_2
      26: invokeinterface #225,  1          // InterfaceMethod java/util/Iterator.hasNext:()Z
      31: ifeq          58
      34: aload_2
      35: invokeinterface #229,  1          // InterfaceMethod java/util/Iterator.next:()Ljava/lang/Object;
      40: checkcast     #172                // class java/lang/String
      43: astore_3
      44: aload_0
      45: getfield      #42                 // Field podCIDRs:Ljava/util/List;
      48: aload_3
      49: invokeinterface #137,  2          // InterfaceMethod java/util/List.add:(Ljava/lang/Object;)Z
      54: pop
      55: goto          25
      58: aload_0
      59: areturn

  public A removeFromPodCIDRs(java.lang.String...);
    Code:
       0: aload_1
       1: astore_2
       2: aload_2
       3: arraylength
       4: istore_3
       5: iconst_0
       6: istore        4
       8: iload         4
      10: iload_3
      11: if_icmpge     45
      14: aload_2
      15: iload         4
      17: aaload
      18: astore        5
      20: aload_0
      21: getfield      #42                 // Field podCIDRs:Ljava/util/List;
      24: ifnull        39
      27: aload_0
      28: getfield      #42                 // Field podCIDRs:Ljava/util/List;
      31: aload         5
      33: invokeinterface #131,  2          // InterfaceMethod java/util/List.remove:(Ljava/lang/Object;)Z
      38: pop
      39: iinc          4, 1
      42: goto          8
      45: aload_0
      46: areturn

  public A removeAllFromPodCIDRs(java.util.Collection<java.lang.String>);
    Code:
       0: aload_1
       1: invokeinterface #219,  1          // InterfaceMethod java/util/Collection.iterator:()Ljava/util/Iterator;
       6: astore_2
       7: aload_2
       8: invokeinterface #225,  1          // InterfaceMethod java/util/Iterator.hasNext:()Z
      13: ifeq          47
      16: aload_2
      17: invokeinterface #229,  1          // InterfaceMethod java/util/Iterator.next:()Ljava/lang/Object;
      22: checkcast     #172                // class java/lang/String
      25: astore_3
      26: aload_0
      27: getfield      #42                 // Field podCIDRs:Ljava/util/List;
      30: ifnull        44
      33: aload_0
      34: getfield      #42                 // Field podCIDRs:Ljava/util/List;
      37: aload_3
      38: invokeinterface #131,  2          // InterfaceMethod java/util/List.remove:(Ljava/lang/Object;)Z
      43: pop
      44: goto          7
      47: aload_0
      48: areturn

  public java.util.List<java.lang.String> getPodCIDRs();
    Code:
       0: aload_0
       1: getfield      #42                 // Field podCIDRs:Ljava/util/List;
       4: areturn

  public java.lang.String getPodCIDR(int);
    Code:
       0: aload_0
       1: getfield      #42                 // Field podCIDRs:Ljava/util/List;
       4: iload_1
       5: invokeinterface #238,  2          // InterfaceMethod java/util/List.get:(I)Ljava/lang/Object;
      10: checkcast     #172                // class java/lang/String
      13: areturn

  public java.lang.String getFirstPodCIDR();
    Code:
       0: aload_0
       1: getfield      #42                 // Field podCIDRs:Ljava/util/List;
       4: iconst_0
       5: invokeinterface #238,  2          // InterfaceMethod java/util/List.get:(I)Ljava/lang/Object;
      10: checkcast     #172                // class java/lang/String
      13: areturn

  public java.lang.String getLastPodCIDR();
    Code:
       0: aload_0
       1: getfield      #42                 // Field podCIDRs:Ljava/util/List;
       4: aload_0
       5: getfield      #42                 // Field podCIDRs:Ljava/util/List;
       8: invokeinterface #244,  1          // InterfaceMethod java/util/List.size:()I
      13: iconst_1
      14: isub
      15: invokeinterface #238,  2          // InterfaceMethod java/util/List.get:(I)Ljava/lang/Object;
      20: checkcast     #172                // class java/lang/String
      23: areturn

  public java.lang.String getMatchingPodCIDR(io.dekorate.deps.kubernetes.api.builder.Predicate<java.lang.String>);
    Code:
       0: aload_0
       1: getfield      #42                 // Field podCIDRs:Ljava/util/List;
       4: invokeinterface #248,  1          // InterfaceMethod java/util/List.iterator:()Ljava/util/Iterator;
       9: astore_2
      10: aload_2
      11: invokeinterface #225,  1          // InterfaceMethod java/util/Iterator.hasNext:()Z
      16: ifeq          47
      19: aload_2
      20: invokeinterface #229,  1          // InterfaceMethod java/util/Iterator.next:()Ljava/lang/Object;
      25: checkcast     #172                // class java/lang/String
      28: astore_3
      29: aload_1
      30: aload_3
      31: invokeinterface #254,  2          // InterfaceMethod io/dekorate/deps/kubernetes/api/builder/Predicate.apply:(Ljava/lang/Object;)Ljava/lang/Boolean;
      36: invokevirtual #257                // Method java/lang/Boolean.booleanValue:()Z
      39: ifeq          44
      42: aload_3
      43: areturn
      44: goto          10
      47: aconst_null
      48: areturn

  public java.lang.Boolean hasMatchingPodCIDR(io.dekorate.deps.kubernetes.api.builder.Predicate<java.lang.String>);
    Code:
       0: aload_0
       1: getfield      #42                 // Field podCIDRs:Ljava/util/List;
       4: invokeinterface #248,  1          // InterfaceMethod java/util/List.iterator:()Ljava/util/Iterator;
       9: astore_2
      10: aload_2
      11: invokeinterface #225,  1          // InterfaceMethod java/util/Iterator.hasNext:()Z
      16: ifeq          50
      19: aload_2
      20: invokeinterface #229,  1          // InterfaceMethod java/util/Iterator.next:()Ljava/lang/Object;
      25: checkcast     #172                // class java/lang/String
      28: astore_3
      29: aload_1
      30: aload_3
      31: invokeinterface #254,  2          // InterfaceMethod io/dekorate/deps/kubernetes/api/builder/Predicate.apply:(Ljava/lang/Object;)Ljava/lang/Boolean;
      36: invokevirtual #257                // Method java/lang/Boolean.booleanValue:()Z
      39: ifeq          47
      42: iconst_1
      43: invokestatic  #145                // Method java/lang/Boolean.valueOf:(Z)Ljava/lang/Boolean;
      46: areturn
      47: goto          10
      50: iconst_0
      51: invokestatic  #145                // Method java/lang/Boolean.valueOf:(Z)Ljava/lang/Boolean;
      54: areturn

  public A withPodCIDRs(java.util.List<java.lang.String>);
    Code:
       0: aload_0
       1: getfield      #42                 // Field podCIDRs:Ljava/util/List;
       4: ifnull        27
       7: aload_0
       8: getfield      #118                // Field _visitables:Lio/dekorate/deps/kubernetes/api/builder/VisitableMap;
      11: ldc_w         #265                // String podCIDRs
      14: invokevirtual #125                // Method io/dekorate/deps/kubernetes/api/builder/VisitableMap.get:(Ljava/lang/Object;)Ljava/util/List;
      17: aload_0
      18: getfield      #42                 // Field podCIDRs:Ljava/util/List;
      21: invokeinterface #269,  2          // InterfaceMethod java/util/List.removeAll:(Ljava/util/Collection;)Z
      26: pop
      27: aload_1
      28: ifnull        87
      31: aload_0
      32: new           #39                 // class java/util/ArrayList
      35: dup
      36: invokespecial #40                 // Method java/util/ArrayList."<init>":()V
      39: putfield      #42                 // Field podCIDRs:Ljava/util/List;
      42: aload_1
      43: invokeinterface #248,  1          // InterfaceMethod java/util/List.iterator:()Ljava/util/Iterator;
      48: astore_2
      49: aload_2
      50: invokeinterface #225,  1          // InterfaceMethod java/util/Iterator.hasNext:()Z
      55: ifeq          84
      58: aload_2
      59: invokeinterface #229,  1          // InterfaceMethod java/util/Iterator.next:()Ljava/lang/Object;
      64: checkcast     #172                // class java/lang/String
      67: astore_3
      68: aload_0
      69: iconst_1
      70: anewarray     #172                // class java/lang/String
      73: dup
      74: iconst_0
      75: aload_3
      76: aastore
      77: invokevirtual #271                // Method addToPodCIDRs:([Ljava/lang/String;)Lio/dekorate/deps/kubernetes/api/model/NodeSpecFluent;
      80: pop
      81: goto          49
      84: goto          92
      87: aload_0
      88: aconst_null
      89: putfield      #42                 // Field podCIDRs:Ljava/util/List;
      92: aload_0
      93: areturn

  public A withPodCIDRs(java.lang.String...);
    Code:
       0: aload_0
       1: getfield      #42                 // Field podCIDRs:Ljava/util/List;
       4: ifnull        16
       7: aload_0
       8: getfield      #42                 // Field podCIDRs:Ljava/util/List;
      11: invokeinterface #274,  1          // InterfaceMethod java/util/List.clear:()V
      16: aload_1
      17: ifnull        60
      20: aload_1
      21: astore_2
      22: aload_2
      23: arraylength
      24: istore_3
      25: iconst_0
      26: istore        4
      28: iload         4
      30: iload_3
      31: if_icmpge     60
      34: aload_2
      35: iload         4
      37: aaload
      38: astore        5
      40: aload_0
      41: iconst_1
      42: anewarray     #172                // class java/lang/String
      45: dup
      46: iconst_0
      47: aload         5
      49: aastore
      50: invokevirtual #271                // Method addToPodCIDRs:([Ljava/lang/String;)Lio/dekorate/deps/kubernetes/api/model/NodeSpecFluent;
      53: pop
      54: iinc          4, 1
      57: goto          28
      60: aload_0
      61: areturn

  public java.lang.Boolean hasPodCIDRs();
    Code:
       0: aload_0
       1: getfield      #42                 // Field podCIDRs:Ljava/util/List;
       4: ifnull        23
       7: aload_0
       8: getfield      #42                 // Field podCIDRs:Ljava/util/List;
      11: invokeinterface #278,  1          // InterfaceMethod java/util/List.isEmpty:()Z
      16: ifne          23
      19: iconst_1
      20: goto          24
      23: iconst_0
      24: invokestatic  #145                // Method java/lang/Boolean.valueOf:(Z)Ljava/lang/Boolean;
      27: areturn

  public A addNewPodCIDR(java.lang.String);
    Code:
       0: aload_0
       1: iconst_1
       2: anewarray     #172                // class java/lang/String
       5: dup
       6: iconst_0
       7: new           #172                // class java/lang/String
      10: dup
      11: aload_1
      12: invokespecial #175                // Method java/lang/String."<init>":(Ljava/lang/String;)V
      15: aastore
      16: invokevirtual #271                // Method addToPodCIDRs:([Ljava/lang/String;)Lio/dekorate/deps/kubernetes/api/model/NodeSpecFluent;
      19: areturn

  public A addNewPodCIDR(java.lang.StringBuilder);
    Code:
       0: aload_0
       1: iconst_1
       2: anewarray     #172                // class java/lang/String
       5: dup
       6: iconst_0
       7: new           #172                // class java/lang/String
      10: dup
      11: aload_1
      12: invokespecial #181                // Method java/lang/String."<init>":(Ljava/lang/StringBuilder;)V
      15: aastore
      16: invokevirtual #271                // Method addToPodCIDRs:([Ljava/lang/String;)Lio/dekorate/deps/kubernetes/api/model/NodeSpecFluent;
      19: areturn

  public A addNewPodCIDR(java.lang.StringBuffer);
    Code:
       0: aload_0
       1: iconst_1
       2: anewarray     #172                // class java/lang/String
       5: dup
       6: iconst_0
       7: new           #172                // class java/lang/String
      10: dup
      11: aload_1
      12: invokespecial #187                // Method java/lang/String."<init>":(Ljava/lang/StringBuffer;)V
      15: aastore
      16: invokevirtual #271                // Method addToPodCIDRs:([Ljava/lang/String;)Lio/dekorate/deps/kubernetes/api/model/NodeSpecFluent;
      19: areturn

  public java.lang.String getProviderID();
    Code:
       0: aload_0
       1: getfield      #281                // Field providerID:Ljava/lang/String;
       4: areturn

  public A withProviderID(java.lang.String);
    Code:
       0: aload_0
       1: aload_1
       2: putfield      #281                // Field providerID:Ljava/lang/String;
       5: aload_0
       6: areturn

  public java.lang.Boolean hasProviderID();
    Code:
       0: aload_0
       1: getfield      #281                // Field providerID:Ljava/lang/String;
       4: ifnull        11
       7: iconst_1
       8: goto          12
      11: iconst_0
      12: invokestatic  #145                // Method java/lang/Boolean.valueOf:(Z)Ljava/lang/Boolean;
      15: areturn

  public A withNewProviderID(java.lang.String);
    Code:
       0: aload_0
       1: new           #172                // class java/lang/String
       4: dup
       5: aload_1
       6: invokespecial #175                // Method java/lang/String."<init>":(Ljava/lang/String;)V
       9: invokevirtual #86                 // Method withProviderID:(Ljava/lang/String;)Lio/dekorate/deps/kubernetes/api/model/NodeSpecFluent;
      12: areturn

  public A withNewProviderID(java.lang.StringBuilder);
    Code:
       0: aload_0
       1: new           #172                // class java/lang/String
       4: dup
       5: aload_1
       6: invokespecial #181                // Method java/lang/String."<init>":(Ljava/lang/StringBuilder;)V
       9: invokevirtual #86                 // Method withProviderID:(Ljava/lang/String;)Lio/dekorate/deps/kubernetes/api/model/NodeSpecFluent;
      12: areturn

  public A withNewProviderID(java.lang.StringBuffer);
    Code:
       0: aload_0
       1: new           #172                // class java/lang/String
       4: dup
       5: aload_1
       6: invokespecial #187                // Method java/lang/String."<init>":(Ljava/lang/StringBuffer;)V
       9: invokevirtual #86                 // Method withProviderID:(Ljava/lang/String;)Lio/dekorate/deps/kubernetes/api/model/NodeSpecFluent;
      12: areturn

  public A addToTaints(int, io.dekorate.deps.kubernetes.api.model.Taint);
    Code:
       0: aload_0
       1: getfield      #44                 // Field taints:Ljava/util/List;
       4: ifnonnull     18
       7: aload_0
       8: new           #39                 // class java/util/ArrayList
      11: dup
      12: invokespecial #40                 // Method java/util/ArrayList."<init>":()V
      15: putfield      #44                 // Field taints:Ljava/util/List;
      18: new           #288                // class io/dekorate/deps/kubernetes/api/model/TaintBuilder
      21: dup
      22: aload_2
      23: invokespecial #291                // Method io/dekorate/deps/kubernetes/api/model/TaintBuilder."<init>":(Lio/dekorate/deps/kubernetes/api/model/Taint;)V
      26: astore_3
      27: aload_0
      28: getfield      #118                // Field _visitables:Lio/dekorate/deps/kubernetes/api/builder/VisitableMap;
      31: ldc_w         #292                // String taints
      34: invokevirtual #125                // Method io/dekorate/deps/kubernetes/api/builder/VisitableMap.get:(Ljava/lang/Object;)Ljava/util/List;
      37: iload_1
      38: iflt          45
      41: iload_1
      42: goto          60
      45: aload_0
      46: getfield      #118                // Field _visitables:Lio/dekorate/deps/kubernetes/api/builder/VisitableMap;
      49: ldc_w         #292                // String taints
      52: invokevirtual #125                // Method io/dekorate/deps/kubernetes/api/builder/VisitableMap.get:(Ljava/lang/Object;)Ljava/util/List;
      55: invokeinterface #244,  1          // InterfaceMethod java/util/List.size:()I
      60: aload_3
      61: invokeinterface #198,  3          // InterfaceMethod java/util/List.add:(ILjava/lang/Object;)V
      66: aload_0
      67: getfield      #44                 // Field taints:Ljava/util/List;
      70: iload_1
      71: iflt          78
      74: iload_1
      75: goto          87
      78: aload_0
      79: getfield      #44                 // Field taints:Ljava/util/List;
      82: invokeinterface #244,  1          // InterfaceMethod java/util/List.size:()I
      87: aload_3
      88: invokeinterface #198,  3          // InterfaceMethod java/util/List.add:(ILjava/lang/Object;)V
      93: aload_0
      94: areturn

  public A setToTaints(int, io.dekorate.deps.kubernetes.api.model.Taint);
    Code:
       0: aload_0
       1: getfield      #44                 // Field taints:Ljava/util/List;
       4: ifnonnull     18
       7: aload_0
       8: new           #39                 // class java/util/ArrayList
      11: dup
      12: invokespecial #40                 // Method java/util/ArrayList."<init>":()V
      15: putfield      #44                 // Field taints:Ljava/util/List;
      18: new           #288                // class io/dekorate/deps/kubernetes/api/model/TaintBuilder
      21: dup
      22: aload_2
      23: invokespecial #291                // Method io/dekorate/deps/kubernetes/api/model/TaintBuilder."<init>":(Lio/dekorate/deps/kubernetes/api/model/Taint;)V
      26: astore_3
      27: iload_1
      28: iflt          50
      31: iload_1
      32: aload_0
      33: getfield      #118                // Field _visitables:Lio/dekorate/deps/kubernetes/api/builder/VisitableMap;
      36: ldc_w         #292                // String taints
      39: invokevirtual #125                // Method io/dekorate/deps/kubernetes/api/builder/VisitableMap.get:(Ljava/lang/Object;)Ljava/util/List;
      42: invokeinterface #244,  1          // InterfaceMethod java/util/List.size:()I
      47: if_icmplt     70
      50: aload_0
      51: getfield      #118                // Field _visitables:Lio/dekorate/deps/kubernetes/api/builder/VisitableMap;
      54: ldc_w         #292                // String taints
      57: invokevirtual #125                // Method io/dekorate/deps/kubernetes/api/builder/VisitableMap.get:(Ljava/lang/Object;)Ljava/util/List;
      60: aload_3
      61: invokeinterface #137,  2          // InterfaceMethod java/util/List.add:(Ljava/lang/Object;)Z
      66: pop
      67: goto          88
      70: aload_0
      71: getfield      #118                // Field _visitables:Lio/dekorate/deps/kubernetes/api/builder/VisitableMap;
      74: ldc_w         #292                // String taints
      77: invokevirtual #125                // Method io/dekorate/deps/kubernetes/api/builder/VisitableMap.get:(Ljava/lang/Object;)Ljava/util/List;
      80: iload_1
      81: aload_3
      82: invokeinterface #205,  3          // InterfaceMethod java/util/List.set:(ILjava/lang/Object;)Ljava/lang/Object;
      87: pop
      88: iload_1
      89: iflt          105
      92: iload_1
      93: aload_0
      94: getfield      #44                 // Field taints:Ljava/util/List;
      97: invokeinterface #244,  1          // InterfaceMethod java/util/List.size:()I
     102: if_icmplt     119
     105: aload_0
     106: getfield      #44                 // Field taints:Ljava/util/List;
     109: aload_3
     110: invokeinterface #137,  2          // InterfaceMethod java/util/List.add:(Ljava/lang/Object;)Z
     115: pop
     116: goto          131
     119: aload_0
     120: getfield      #44                 // Field taints:Ljava/util/List;
     123: iload_1
     124: aload_3
     125: invokeinterface #205,  3          // InterfaceMethod java/util/List.set:(ILjava/lang/Object;)Ljava/lang/Object;
     130: pop
     131: aload_0
     132: areturn

  public A addToTaints(io.dekorate.deps.kubernetes.api.model.Taint...);
    Code:
       0: aload_0
       1: getfield      #44                 // Field taints:Ljava/util/List;
       4: ifnonnull     18
       7: aload_0
       8: new           #39                 // class java/util/ArrayList
      11: dup
      12: invokespecial #40                 // Method java/util/ArrayList."<init>":()V
      15: putfield      #44                 // Field taints:Ljava/util/List;
      18: aload_1
      19: astore_2
      20: aload_2
      21: arraylength
      22: istore_3
      23: iconst_0
      24: istore        4
      26: iload         4
      28: iload_3
      29: if_icmpge     85
      32: aload_2
      33: iload         4
      35: aaload
      36: astore        5
      38: new           #288                // class io/dekorate/deps/kubernetes/api/model/TaintBuilder
      41: dup
      42: aload         5
      44: invokespecial #291                // Method io/dekorate/deps/kubernetes/api/model/TaintBuilder."<init>":(Lio/dekorate/deps/kubernetes/api/model/Taint;)V
      47: astore        6
      49: aload_0
      50: getfield      #118                // Field _visitables:Lio/dekorate/deps/kubernetes/api/builder/VisitableMap;
      53: ldc_w         #292                // String taints
      56: invokevirtual #125                // Method io/dekorate/deps/kubernetes/api/builder/VisitableMap.get:(Ljava/lang/Object;)Ljava/util/List;
      59: aload         6
      61: invokeinterface #137,  2          // InterfaceMethod java/util/List.add:(Ljava/lang/Object;)Z
      66: pop
      67: aload_0
      68: getfield      #44                 // Field taints:Ljava/util/List;
      71: aload         6
      73: invokeinterface #137,  2          // InterfaceMethod java/util/List.add:(Ljava/lang/Object;)Z
      78: pop
      79: iinc          4, 1
      82: goto          26
      85: aload_0
      86: areturn

  public A addAllToTaints(java.util.Collection<io.dekorate.deps.kubernetes.api.model.Taint>);
    Code:
       0: aload_0
       1: getfield      #44                 // Field taints:Ljava/util/List;
       4: ifnonnull     18
       7: aload_0
       8: new           #39                 // class java/util/ArrayList
      11: dup
      12: invokespecial #40                 // Method java/util/ArrayList."<init>":()V
      15: putfield      #44                 // Field taints:Ljava/util/List;
      18: aload_1
      19: invokeinterface #219,  1          // InterfaceMethod java/util/Collection.iterator:()Ljava/util/Iterator;
      24: astore_2
      25: aload_2
      26: invokeinterface #225,  1          // InterfaceMethod java/util/Iterator.hasNext:()Z
      31: ifeq          87
      34: aload_2
      35: invokeinterface #229,  1          // InterfaceMethod java/util/Iterator.next:()Ljava/lang/Object;
      40: checkcast     #294                // class io/dekorate/deps/kubernetes/api/model/Taint
      43: astore_3
      44: new           #288                // class io/dekorate/deps/kubernetes/api/model/TaintBuilder
      47: dup
      48: aload_3
      49: invokespecial #291                // Method io/dekorate/deps/kubernetes/api/model/TaintBuilder."<init>":(Lio/dekorate/deps/kubernetes/api/model/Taint;)V
      52: astore        4
      54: aload_0
      55: getfield      #118                // Field _visitables:Lio/dekorate/deps/kubernetes/api/builder/VisitableMap;
      58: ldc_w         #292                // String taints
      61: invokevirtual #125                // Method io/dekorate/deps/kubernetes/api/builder/VisitableMap.get:(Ljava/lang/Object;)Ljava/util/List;
      64: aload         4
      66: invokeinterface #137,  2          // InterfaceMethod java/util/List.add:(Ljava/lang/Object;)Z
      71: pop
      72: aload_0
      73: getfield      #44                 // Field taints:Ljava/util/List;
      76: aload         4
      78: invokeinterface #137,  2          // InterfaceMethod java/util/List.add:(Ljava/lang/Object;)Z
      83: pop
      84: goto          25
      87: aload_0
      88: areturn

  public A removeFromTaints(io.dekorate.deps.kubernetes.api.model.Taint...);
    Code:
       0: aload_1
       1: astore_2
       2: aload_2
       3: arraylength
       4: istore_3
       5: iconst_0
       6: istore        4
       8: iload         4
      10: iload_3
      11: if_icmpge     74
      14: aload_2
      15: iload         4
      17: aaload
      18: astore        5
      20: new           #288                // class io/dekorate/deps/kubernetes/api/model/TaintBuilder
      23: dup
      24: aload         5
      26: invokespecial #291                // Method io/dekorate/deps/kubernetes/api/model/TaintBuilder."<init>":(Lio/dekorate/deps/kubernetes/api/model/Taint;)V
      29: astore        6
      31: aload_0
      32: getfield      #118                // Field _visitables:Lio/dekorate/deps/kubernetes/api/builder/VisitableMap;
      35: ldc_w         #292                // String taints
      38: invokevirtual #125                // Method io/dekorate/deps/kubernetes/api/builder/VisitableMap.get:(Ljava/lang/Object;)Ljava/util/List;
      41: aload         6
      43: invokeinterface #131,  2          // InterfaceMethod java/util/List.remove:(Ljava/lang/Object;)Z
      48: pop
      49: aload_0
      50: getfield      #44                 // Field taints:Ljava/util/List;
      53: ifnull        68
      56: aload_0
      57: getfield      #44                 // Field taints:Ljava/util/List;
      60: aload         6
      62: invokeinterface #131,  2          // InterfaceMethod java/util/List.remove:(Ljava/lang/Object;)Z
      67: pop
      68: iinc          4, 1
      71: goto          8
      74: aload_0
      75: areturn

  public A removeAllFromTaints(java.util.Collection<io.dekorate.deps.kubernetes.api.model.Taint>);
    Code:
       0: aload_1
       1: invokeinterface #219,  1          // InterfaceMethod java/util/Collection.iterator:()Ljava/util/Iterator;
       6: astore_2
       7: aload_2
       8: invokeinterface #225,  1          // InterfaceMethod java/util/Iterator.hasNext:()Z
      13: ifeq          76
      16: aload_2
      17: invokeinterface #229,  1          // InterfaceMethod java/util/Iterator.next:()Ljava/lang/Object;
      22: checkcast     #294                // class io/dekorate/deps/kubernetes/api/model/Taint
      25: astore_3
      26: new           #288                // class io/dekorate/deps/kubernetes/api/model/TaintBuilder
      29: dup
      30: aload_3
      31: invokespecial #291                // Method io/dekorate/deps/kubernetes/api/model/TaintBuilder."<init>":(Lio/dekorate/deps/kubernetes/api/model/Taint;)V
      34: astore        4
      36: aload_0
      37: getfield      #118                // Field _visitables:Lio/dekorate/deps/kubernetes/api/builder/VisitableMap;
      40: ldc_w         #292                // String taints
      43: invokevirtual #125                // Method io/dekorate/deps/kubernetes/api/builder/VisitableMap.get:(Ljava/lang/Object;)Ljava/util/List;
      46: aload         4
      48: invokeinterface #131,  2          // InterfaceMethod java/util/List.remove:(Ljava/lang/Object;)Z
      53: pop
      54: aload_0
      55: getfield      #44                 // Field taints:Ljava/util/List;
      58: ifnull        73
      61: aload_0
      62: getfield      #44                 // Field taints:Ljava/util/List;
      65: aload         4
      67: invokeinterface #131,  2          // InterfaceMethod java/util/List.remove:(Ljava/lang/Object;)Z
      72: pop
      73: goto          7
      76: aload_0
      77: areturn

  public A removeMatchingFromTaints(io.dekorate.deps.kubernetes.api.builder.Predicate<io.dekorate.deps.kubernetes.api.model.TaintBuilder>);
    Code:
       0: aload_0
       1: getfield      #44                 // Field taints:Ljava/util/List;
       4: ifnonnull     9
       7: aload_0
       8: areturn
       9: aload_0
      10: getfield      #44                 // Field taints:Ljava/util/List;
      13: invokeinterface #248,  1          // InterfaceMethod java/util/List.iterator:()Ljava/util/Iterator;
      18: astore_2
      19: aload_0
      20: getfield      #118                // Field _visitables:Lio/dekorate/deps/kubernetes/api/builder/VisitableMap;
      23: ldc_w         #292                // String taints
      26: invokevirtual #125                // Method io/dekorate/deps/kubernetes/api/builder/VisitableMap.get:(Ljava/lang/Object;)Ljava/util/List;
      29: astore_3
      30: aload_2
      31: invokeinterface #225,  1          // InterfaceMethod java/util/Iterator.hasNext:()Z
      36: ifeq          82
      39: aload_2
      40: invokeinterface #229,  1          // InterfaceMethod java/util/Iterator.next:()Ljava/lang/Object;
      45: checkcast     #288                // class io/dekorate/deps/kubernetes/api/model/TaintBuilder
      48: astore        4
      50: aload_1
      51: aload         4
      53: invokeinterface #254,  2          // InterfaceMethod io/dekorate/deps/kubernetes/api/builder/Predicate.apply:(Ljava/lang/Object;)Ljava/lang/Boolean;
      58: invokevirtual #257                // Method java/lang/Boolean.booleanValue:()Z
      61: ifeq          79
      64: aload_3
      65: aload         4
      67: invokeinterface #131,  2          // InterfaceMethod java/util/List.remove:(Ljava/lang/Object;)Z
      72: pop
      73: aload_2
      74: invokeinterface #312,  1          // InterfaceMethod java/util/Iterator.remove:()V
      79: goto          30
      82: aload_0
      83: areturn

  public java.util.List<io.dekorate.deps.kubernetes.api.model.Taint> getTaints();
    Code:
       0: aload_0
       1: getfield      #44                 // Field taints:Ljava/util/List;
       4: invokestatic  #321                // Method build:(Ljava/util/List;)Ljava/util/ArrayList;
       7: areturn

  public java.util.List<io.dekorate.deps.kubernetes.api.model.Taint> buildTaints();
    Code:
       0: aload_0
       1: getfield      #44                 // Field taints:Ljava/util/List;
       4: invokestatic  #321                // Method build:(Ljava/util/List;)Ljava/util/ArrayList;
       7: areturn

  public io.dekorate.deps.kubernetes.api.model.Taint buildTaint(int);
    Code:
       0: aload_0
       1: getfield      #44                 // Field taints:Ljava/util/List;
       4: iload_1
       5: invokeinterface #238,  2          // InterfaceMethod java/util/List.get:(I)Ljava/lang/Object;
      10: checkcast     #288                // class io/dekorate/deps/kubernetes/api/model/TaintBuilder
      13: invokevirtual #327                // Method io/dekorate/deps/kubernetes/api/model/TaintBuilder.build:()Lio/dekorate/deps/kubernetes/api/model/Taint;
      16: areturn

  public io.dekorate.deps.kubernetes.api.model.Taint buildFirstTaint();
    Code:
       0: aload_0
       1: getfield      #44                 // Field taints:Ljava/util/List;
       4: iconst_0
       5: invokeinterface #238,  2          // InterfaceMethod java/util/List.get:(I)Ljava/lang/Object;
      10: checkcast     #288                // class io/dekorate/deps/kubernetes/api/model/TaintBuilder
      13: invokevirtual #327                // Method io/dekorate/deps/kubernetes/api/model/TaintBuilder.build:()Lio/dekorate/deps/kubernetes/api/model/Taint;
      16: areturn

  public io.dekorate.deps.kubernetes.api.model.Taint buildLastTaint();
    Code:
       0: aload_0
       1: getfield      #44                 // Field taints:Ljava/util/List;
       4: aload_0
       5: getfield      #44                 // Field taints:Ljava/util/List;
       8: invokeinterface #244,  1          // InterfaceMethod java/util/List.size:()I
      13: iconst_1
      14: isub
      15: invokeinterface #238,  2          // InterfaceMethod java/util/List.get:(I)Ljava/lang/Object;
      20: checkcast     #288                // class io/dekorate/deps/kubernetes/api/model/TaintBuilder
      23: invokevirtual #327                // Method io/dekorate/deps/kubernetes/api/model/TaintBuilder.build:()Lio/dekorate/deps/kubernetes/api/model/Taint;
      26: areturn

  public io.dekorate.deps.kubernetes.api.model.Taint buildMatchingTaint(io.dekorate.deps.kubernetes.api.builder.Predicate<io.dekorate.deps.kubernetes.api.model.TaintBuilder>);
    Code:
       0: aload_0
       1: getfield      #44                 // Field taints:Ljava/util/List;
       4: invokeinterface #248,  1          // InterfaceMethod java/util/List.iterator:()Ljava/util/Iterator;
       9: astore_2
      10: aload_2
      11: invokeinterface #225,  1          // InterfaceMethod java/util/Iterator.hasNext:()Z
      16: ifeq          50
      19: aload_2
      20: invokeinterface #229,  1          // InterfaceMethod java/util/Iterator.next:()Ljava/lang/Object;
      25: checkcast     #288                // class io/dekorate/deps/kubernetes/api/model/TaintBuilder
      28: astore_3
      29: aload_1
      30: aload_3
      31: invokeinterface #254,  2          // InterfaceMethod io/dekorate/deps/kubernetes/api/builder/Predicate.apply:(Ljava/lang/Object;)Ljava/lang/Boolean;
      36: invokevirtual #257                // Method java/lang/Boolean.booleanValue:()Z
      39: ifeq          47
      42: aload_3
      43: invokevirtual #327                // Method io/dekorate/deps/kubernetes/api/model/TaintBuilder.build:()Lio/dekorate/deps/kubernetes/api/model/Taint;
      46: areturn
      47: goto          10
      50: aconst_null
      51: areturn

  public java.lang.Boolean hasMatchingTaint(io.dekorate.deps.kubernetes.api.builder.Predicate<io.dekorate.deps.kubernetes.api.model.TaintBuilder>);
    Code:
       0: aload_0
       1: getfield      #44                 // Field taints:Ljava/util/List;
       4: invokeinterface #248,  1          // InterfaceMethod java/util/List.iterator:()Ljava/util/Iterator;
       9: astore_2
      10: aload_2
      11: invokeinterface #225,  1          // InterfaceMethod java/util/Iterator.hasNext:()Z
      16: ifeq          50
      19: aload_2
      20: invokeinterface #229,  1          // InterfaceMethod java/util/Iterator.next:()Ljava/lang/Object;
      25: checkcast     #288                // class io/dekorate/deps/kubernetes/api/model/TaintBuilder
      28: astore_3
      29: aload_1
      30: aload_3
      31: invokeinterface #254,  2          // InterfaceMethod io/dekorate/deps/kubernetes/api/builder/Predicate.apply:(Ljava/lang/Object;)Ljava/lang/Boolean;
      36: invokevirtual #257                // Method java/lang/Boolean.booleanValue:()Z
      39: ifeq          47
      42: iconst_1
      43: invokestatic  #145                // Method java/lang/Boolean.valueOf:(Z)Ljava/lang/Boolean;
      46: areturn
      47: goto          10
      50: iconst_0
      51: invokestatic  #145                // Method java/lang/Boolean.valueOf:(Z)Ljava/lang/Boolean;
      54: areturn

  public A withTaints(java.util.List<io.dekorate.deps.kubernetes.api.model.Taint>);
    Code:
       0: aload_0
       1: getfield      #44                 // Field taints:Ljava/util/List;
       4: ifnull        27
       7: aload_0
       8: getfield      #118                // Field _visitables:Lio/dekorate/deps/kubernetes/api/builder/VisitableMap;
      11: ldc_w         #292                // String taints
      14: invokevirtual #125                // Method io/dekorate/deps/kubernetes/api/builder/VisitableMap.get:(Ljava/lang/Object;)Ljava/util/List;
      17: aload_0
      18: getfield      #44                 // Field taints:Ljava/util/List;
      21: invokeinterface #269,  2          // InterfaceMethod java/util/List.removeAll:(Ljava/util/Collection;)Z
      26: pop
      27: aload_1
      28: ifnull        87
      31: aload_0
      32: new           #39                 // class java/util/ArrayList
      35: dup
      36: invokespecial #40                 // Method java/util/ArrayList."<init>":()V
      39: putfield      #44                 // Field taints:Ljava/util/List;
      42: aload_1
      43: invokeinterface #248,  1          // InterfaceMethod java/util/List.iterator:()Ljava/util/Iterator;
      48: astore_2
      49: aload_2
      50: invokeinterface #225,  1          // InterfaceMethod java/util/Iterator.hasNext:()Z
      55: ifeq          84
      58: aload_2
      59: invokeinterface #229,  1          // InterfaceMethod java/util/Iterator.next:()Ljava/lang/Object;
      64: checkcast     #294                // class io/dekorate/deps/kubernetes/api/model/Taint
      67: astore_3
      68: aload_0
      69: iconst_1
      70: anewarray     #294                // class io/dekorate/deps/kubernetes/api/model/Taint
      73: dup
      74: iconst_0
      75: aload_3
      76: aastore
      77: invokevirtual #337                // Method addToTaints:([Lio/dekorate/deps/kubernetes/api/model/Taint;)Lio/dekorate/deps/kubernetes/api/model/NodeSpecFluent;
      80: pop
      81: goto          49
      84: goto          92
      87: aload_0
      88: aconst_null
      89: putfield      #44                 // Field taints:Ljava/util/List;
      92: aload_0
      93: areturn

  public A withTaints(io.dekorate.deps.kubernetes.api.model.Taint...);
    Code:
       0: aload_0
       1: getfield      #44                 // Field taints:Ljava/util/List;
       4: ifnull        16
       7: aload_0
       8: getfield      #44                 // Field taints:Ljava/util/List;
      11: invokeinterface #274,  1          // InterfaceMethod java/util/List.clear:()V
      16: aload_1
      17: ifnull        60
      20: aload_1
      21: astore_2
      22: aload_2
      23: arraylength
      24: istore_3
      25: iconst_0
      26: istore        4
      28: iload         4
      30: iload_3
      31: if_icmpge     60
      34: aload_2
      35: iload         4
      37: aaload
      38: astore        5
      40: aload_0
      41: iconst_1
      42: anewarray     #294                // class io/dekorate/deps/kubernetes/api/model/Taint
      45: dup
      46: iconst_0
      47: aload         5
      49: aastore
      50: invokevirtual #337                // Method addToTaints:([Lio/dekorate/deps/kubernetes/api/model/Taint;)Lio/dekorate/deps/kubernetes/api/model/NodeSpecFluent;
      53: pop
      54: iinc          4, 1
      57: goto          28
      60: aload_0
      61: areturn

  public java.lang.Boolean hasTaints();
    Code:
       0: aload_0
       1: getfield      #44                 // Field taints:Ljava/util/List;
       4: ifnull        23
       7: aload_0
       8: getfield      #44                 // Field taints:Ljava/util/List;
      11: invokeinterface #278,  1          // InterfaceMethod java/util/List.isEmpty:()Z
      16: ifne          23
      19: iconst_1
      20: goto          24
      23: iconst_0
      24: invokestatic  #145                // Method java/lang/Boolean.valueOf:(Z)Ljava/lang/Boolean;
      27: areturn

  public A addNewTaint(java.lang.String, java.lang.String, java.lang.String, java.lang.String);
    Code:
       0: aload_0
       1: iconst_1
       2: anewarray     #294                // class io/dekorate/deps/kubernetes/api/model/Taint
       5: dup
       6: iconst_0
       7: new           #294                // class io/dekorate/deps/kubernetes/api/model/Taint
      10: dup
      11: aload_1
      12: aload_2
      13: aload_3
      14: aload         4
      16: invokespecial #345                // Method io/dekorate/deps/kubernetes/api/model/Taint."<init>":(Ljava/lang/String;Ljava/lang/String;Ljava/lang/String;Ljava/lang/String;)V
      19: aastore
      20: invokevirtual #337                // Method addToTaints:([Lio/dekorate/deps/kubernetes/api/model/Taint;)Lio/dekorate/deps/kubernetes/api/model/NodeSpecFluent;
      23: areturn

  public io.dekorate.deps.kubernetes.api.model.NodeSpecFluent$TaintsNested<A> addNewTaint();
    Code:
       0: new           #10                 // class io/dekorate/deps/kubernetes/api/model/NodeSpecFluentImpl$TaintsNestedImpl
       3: dup
       4: aload_0
       5: invokespecial #352                // Method io/dekorate/deps/kubernetes/api/model/NodeSpecFluentImpl$TaintsNestedImpl."<init>":(Lio/dekorate/deps/kubernetes/api/model/NodeSpecFluentImpl;)V
       8: areturn

  public io.dekorate.deps.kubernetes.api.model.NodeSpecFluent$TaintsNested<A> addNewTaintLike(io.dekorate.deps.kubernetes.api.model.Taint);
    Code:
       0: new           #10                 // class io/dekorate/deps/kubernetes/api/model/NodeSpecFluentImpl$TaintsNestedImpl
       3: dup
       4: aload_0
       5: iconst_m1
       6: aload_1
       7: invokespecial #358                // Method io/dekorate/deps/kubernetes/api/model/NodeSpecFluentImpl$TaintsNestedImpl."<init>":(Lio/dekorate/deps/kubernetes/api/model/NodeSpecFluentImpl;ILio/dekorate/deps/kubernetes/api/model/Taint;)V
      10: areturn

  public io.dekorate.deps.kubernetes.api.model.NodeSpecFluent$TaintsNested<A> setNewTaintLike(int, io.dekorate.deps.kubernetes.api.model.Taint);
    Code:
       0: new           #10                 // class io/dekorate/deps/kubernetes/api/model/NodeSpecFluentImpl$TaintsNestedImpl
       3: dup
       4: aload_0
       5: iload_1
       6: aload_2
       7: invokespecial #358                // Method io/dekorate/deps/kubernetes/api/model/NodeSpecFluentImpl$TaintsNestedImpl."<init>":(Lio/dekorate/deps/kubernetes/api/model/NodeSpecFluentImpl;ILio/dekorate/deps/kubernetes/api/model/Taint;)V
      10: areturn

  public io.dekorate.deps.kubernetes.api.model.NodeSpecFluent$TaintsNested<A> editTaint(int);
    Code:
       0: aload_0
       1: getfield      #44                 // Field taints:Ljava/util/List;
       4: invokeinterface #244,  1          // InterfaceMethod java/util/List.size:()I
       9: iload_1
      10: if_icmpgt     24
      13: new           #366                // class java/lang/RuntimeException
      16: dup
      17: ldc_w         #368                // String Can\'t edit taints. Index exceeds size.
      20: invokespecial #369                // Method java/lang/RuntimeException."<init>":(Ljava/lang/String;)V
      23: athrow
      24: aload_0
      25: iload_1
      26: aload_0
      27: iload_1
      28: invokevirtual #371                // Method buildTaint:(I)Lio/dekorate/deps/kubernetes/api/model/Taint;
      31: invokevirtual #373                // Method setNewTaintLike:(ILio/dekorate/deps/kubernetes/api/model/Taint;)Lio/dekorate/deps/kubernetes/api/model/NodeSpecFluent$TaintsNested;
      34: areturn

  public io.dekorate.deps.kubernetes.api.model.NodeSpecFluent$TaintsNested<A> editFirstTaint();
    Code:
       0: aload_0
       1: getfield      #44                 // Field taints:Ljava/util/List;
       4: invokeinterface #244,  1          // InterfaceMethod java/util/List.size:()I
       9: ifne          23
      12: new           #366                // class java/lang/RuntimeException
      15: dup
      16: ldc_w         #376                // String Can\'t edit first taints. The list is empty.
      19: invokespecial #369                // Method java/lang/RuntimeException."<init>":(Ljava/lang/String;)V
      22: athrow
      23: aload_0
      24: iconst_0
      25: aload_0
      26: iconst_0
      27: invokevirtual #371                // Method buildTaint:(I)Lio/dekorate/deps/kubernetes/api/model/Taint;
      30: invokevirtual #373                // Method setNewTaintLike:(ILio/dekorate/deps/kubernetes/api/model/Taint;)Lio/dekorate/deps/kubernetes/api/model/NodeSpecFluent$TaintsNested;
      33: areturn

  public io.dekorate.deps.kubernetes.api.model.NodeSpecFluent$TaintsNested<A> editLastTaint();
    Code:
       0: aload_0
       1: getfield      #44                 // Field taints:Ljava/util/List;
       4: invokeinterface #244,  1          // InterfaceMethod java/util/List.size:()I
       9: iconst_1
      10: isub
      11: istore_1
      12: iload_1
      13: ifge          27
      16: new           #366                // class java/lang/RuntimeException
      19: dup
      20: ldc_w         #379                // String Can\'t edit last taints. The list is empty.
      23: invokespecial #369                // Method java/lang/RuntimeException."<init>":(Ljava/lang/String;)V
      26: athrow
      27: aload_0
      28: iload_1
      29: aload_0
      30: iload_1
      31: invokevirtual #371                // Method buildTaint:(I)Lio/dekorate/deps/kubernetes/api/model/Taint;
      34: invokevirtual #373                // Method setNewTaintLike:(ILio/dekorate/deps/kubernetes/api/model/Taint;)Lio/dekorate/deps/kubernetes/api/model/NodeSpecFluent$TaintsNested;
      37: areturn

  public io.dekorate.deps.kubernetes.api.model.NodeSpecFluent$TaintsNested<A> editMatchingTaint(io.dekorate.deps.kubernetes.api.builder.Predicate<io.dekorate.deps.kubernetes.api.model.TaintBuilder>);
    Code:
       0: iconst_m1
       1: istore_2
       2: iconst_0
       3: istore_3
       4: iload_3
       5: aload_0
       6: getfield      #44                 // Field taints:Ljava/util/List;
       9: invokeinterface #244,  1          // InterfaceMethod java/util/List.size:()I
      14: if_icmpge     50
      17: aload_1
      18: aload_0
      19: getfield      #44                 // Field taints:Ljava/util/List;
      22: iload_3
      23: invokeinterface #238,  2          // InterfaceMethod java/util/List.get:(I)Ljava/lang/Object;
      28: invokeinterface #254,  2          // InterfaceMethod io/dekorate/deps/kubernetes/api/builder/Predicate.apply:(Ljava/lang/Object;)Ljava/lang/Boolean;
      33: invokevirtual #257                // Method java/lang/Boolean.booleanValue:()Z
      36: ifeq          44
      39: iload_3
      40: istore_2
      41: goto          50
      44: iinc          3, 1
      47: goto          4
      50: iload_2
      51: ifge          65
      54: new           #366                // class java/lang/RuntimeException
      57: dup
      58: ldc_w         #384                // String Can\'t edit matching taints. No match found.
      61: invokespecial #369                // Method java/lang/RuntimeException."<init>":(Ljava/lang/String;)V
      64: athrow
      65: aload_0
      66: iload_2
      67: aload_0
      68: iload_2
      69: invokevirtual #371                // Method buildTaint:(I)Lio/dekorate/deps/kubernetes/api/model/Taint;
      72: invokevirtual #373                // Method setNewTaintLike:(ILio/dekorate/deps/kubernetes/api/model/Taint;)Lio/dekorate/deps/kubernetes/api/model/NodeSpecFluent$TaintsNested;
      75: areturn

  public java.lang.Boolean isUnschedulable();
    Code:
       0: aload_0
       1: getfield      #388                // Field unschedulable:Ljava/lang/Boolean;
       4: areturn

  public A withUnschedulable(java.lang.Boolean);
    Code:
       0: aload_0
       1: aload_1
       2: putfield      #388                // Field unschedulable:Ljava/lang/Boolean;
       5: aload_0
       6: areturn

  public java.lang.Boolean hasUnschedulable();
    Code:
       0: aload_0
       1: getfield      #388                // Field unschedulable:Ljava/lang/Boolean;
       4: ifnull        11
       7: iconst_1
       8: goto          12
      11: iconst_0
      12: invokestatic  #145                // Method java/lang/Boolean.valueOf:(Z)Ljava/lang/Boolean;
      15: areturn

  public A withNewUnschedulable(java.lang.String);
    Code:
       0: aload_0
       1: new           #141                // class java/lang/Boolean
       4: dup
       5: aload_1
       6: invokespecial #392                // Method java/lang/Boolean."<init>":(Ljava/lang/String;)V
       9: invokevirtual #100                // Method withUnschedulable:(Ljava/lang/Boolean;)Lio/dekorate/deps/kubernetes/api/model/NodeSpecFluent;
      12: areturn

  public A withNewUnschedulable(boolean);
    Code:
       0: aload_0
       1: new           #141                // class java/lang/Boolean
       4: dup
       5: iload_1
       6: invokespecial #397                // Method java/lang/Boolean."<init>":(Z)V
       9: invokevirtual #100                // Method withUnschedulable:(Ljava/lang/Boolean;)Lio/dekorate/deps/kubernetes/api/model/NodeSpecFluent;
      12: areturn

  public boolean equals(java.lang.Object);
    Code:
       0: aload_0
       1: aload_1
       2: if_acmpne     7
       5: iconst_1
       6: ireturn
       7: aload_1
       8: ifnull        22
      11: aload_0
      12: invokevirtual #405                // Method java/lang/Object.getClass:()Ljava/lang/Class;
      15: aload_1
      16: invokevirtual #405                // Method java/lang/Object.getClass:()Ljava/lang/Class;
      19: if_acmpeq     24
      22: iconst_0
      23: ireturn
      24: aload_1
      25: checkcast     #2                  // class io/dekorate/deps/kubernetes/api/model/NodeSpecFluentImpl
      28: astore_2
      29: aload_0
      30: getfield      #105                // Field configSource:Lio/dekorate/deps/kubernetes/api/model/NodeConfigSourceBuilder;
      33: ifnull        53
      36: aload_0
      37: getfield      #105                // Field configSource:Lio/dekorate/deps/kubernetes/api/model/NodeConfigSourceBuilder;
      40: aload_2
      41: getfield      #105                // Field configSource:Lio/dekorate/deps/kubernetes/api/model/NodeConfigSourceBuilder;
      44: invokevirtual #407                // Method io/dekorate/deps/kubernetes/api/model/NodeConfigSourceBuilder.equals:(Ljava/lang/Object;)Z
      47: ifne          62
      50: goto          60
      53: aload_2
      54: getfield      #105                // Field configSource:Lio/dekorate/deps/kubernetes/api/model/NodeConfigSourceBuilder;
      57: ifnull        62
      60: iconst_0
      61: ireturn
      62: aload_0
      63: getfield      #167                // Field externalID:Ljava/lang/String;
      66: ifnull        86
      69: aload_0
      70: getfield      #167                // Field externalID:Ljava/lang/String;
      73: aload_2
      74: getfield      #167                // Field externalID:Ljava/lang/String;
      77: invokevirtual #408                // Method java/lang/String.equals:(Ljava/lang/Object;)Z
      80: ifne          95
      83: goto          93
      86: aload_2
      87: getfield      #167                // Field externalID:Ljava/lang/String;
      90: ifnull        95
      93: iconst_0
      94: ireturn
      95: aload_0
      96: getfield      #190                // Field podCIDR:Ljava/lang/String;
      99: ifnull        119
     102: aload_0
     103: getfield      #190                // Field podCIDR:Ljava/lang/String;
     106: aload_2
     107: getfield      #190                // Field podCIDR:Ljava/lang/String;
     110: invokevirtual #408                // Method java/lang/String.equals:(Ljava/lang/Object;)Z
     113: ifne          128
     116: goto          126
     119: aload_2
     120: getfield      #190                // Field podCIDR:Ljava/lang/String;
     123: ifnull        128
     126: iconst_0
     127: ireturn
     128: aload_0
     129: getfield      #42                 // Field podCIDRs:Ljava/util/List;
     132: ifnull        154
     135: aload_0
     136: getfield      #42                 // Field podCIDRs:Ljava/util/List;
     139: aload_2
     140: getfield      #42                 // Field podCIDRs:Ljava/util/List;
     143: invokeinterface #409,  2          // InterfaceMethod java/util/List.equals:(Ljava/lang/Object;)Z
     148: ifne          163
     151: goto          161
     154: aload_2
     155: getfield      #42                 // Field podCIDRs:Ljava/util/List;
     158: ifnull        163
     161: iconst_0
     162: ireturn
     163: aload_0
     164: getfield      #281                // Field providerID:Ljava/lang/String;
     167: ifnull        187
     170: aload_0
     171: getfield      #281                // Field providerID:Ljava/lang/String;
     174: aload_2
     175: getfield      #281                // Field providerID:Ljava/lang/String;
     178: invokevirtual #408                // Method java/lang/String.equals:(Ljava/lang/Object;)Z
     181: ifne          196
     184: goto          194
     187: aload_2
     188: getfield      #281                // Field providerID:Ljava/lang/String;
     191: ifnull        196
     194: iconst_0
     195: ireturn
     196: aload_0
     197: getfield      #44                 // Field taints:Ljava/util/List;
     200: ifnull        222
     203: aload_0
     204: getfield      #44                 // Field taints:Ljava/util/List;
     207: aload_2
     208: getfield      #44                 // Field taints:Ljava/util/List;
     211: invokeinterface #409,  2          // InterfaceMethod java/util/List.equals:(Ljava/lang/Object;)Z
     216: ifne          231
     219: goto          229
     222: aload_2
     223: getfield      #44                 // Field taints:Ljava/util/List;
     226: ifnull        231
     229: iconst_0
     230: ireturn
     231: aload_0
     232: getfield      #388                // Field unschedulable:Ljava/lang/Boolean;
     235: ifnull        255
     238: aload_0
     239: getfield      #388                // Field unschedulable:Ljava/lang/Boolean;
     242: aload_2
     243: getfield      #388                // Field unschedulable:Ljava/lang/Boolean;
     246: invokevirtual #410                // Method java/lang/Boolean.equals:(Ljava/lang/Object;)Z
     249: ifne          264
     252: goto          262
     255: aload_2
     256: getfield      #388                // Field unschedulable:Ljava/lang/Boolean;
     259: ifnull        264
     262: iconst_0
     263: ireturn
     264: iconst_1
     265: ireturn
}
