Compiled from "NodeSelectorFluentImpl.java"
public class io.dekorate.deps.kubernetes.api.model.NodeSelectorFluentImpl<A extends io.dekorate.deps.kubernetes.api.model.NodeSelectorFluent<A>> extends io.dekorate.deps.kubernetes.api.builder.BaseFluent<A> implements io.dekorate.deps.kubernetes.api.model.NodeSelectorFluent<A> {
  private java.util.List<io.dekorate.deps.kubernetes.api.model.NodeSelectorTermBuilder> nodeSelectorTerms;

  public io.dekorate.deps.kubernetes.api.model.NodeSelectorFluentImpl();
    Code:
       0: aload_0
       1: invokespecial #21                 // Method io/dekorate/deps/kubernetes/api/builder/BaseFluent."<init>":()V
       4: aload_0
       5: new           #23                 // class java/util/ArrayList
       8: dup
       9: invokespecial #24                 // Method java/util/ArrayList."<init>":()V
      12: putfield      #26                 // Field nodeSelectorTerms:Ljava/util/List;
      15: return

  public io.dekorate.deps.kubernetes.api.model.NodeSelectorFluentImpl(io.dekorate.deps.kubernetes.api.model.NodeSelector);
    Code:
       0: aload_0
       1: invokespecial #21                 // Method io/dekorate/deps/kubernetes/api/builder/BaseFluent."<init>":()V
       4: aload_0
       5: new           #23                 // class java/util/ArrayList
       8: dup
       9: invokespecial #24                 // Method java/util/ArrayList."<init>":()V
      12: putfield      #26                 // Field nodeSelectorTerms:Ljava/util/List;
      15: aload_0
      16: aload_1
      17: invokevirtual #36                 // Method io/dekorate/deps/kubernetes/api/model/NodeSelector.getNodeSelectorTerms:()Ljava/util/List;
      20: invokevirtual #40                 // Method withNodeSelectorTerms:(Ljava/util/List;)Lio/dekorate/deps/kubernetes/api/model/NodeSelectorFluent;
      23: pop
      24: return

  public A addToNodeSelectorTerms(int, io.dekorate.deps.kubernetes.api.model.NodeSelectorTerm);
    Code:
       0: aload_0
       1: getfield      #26                 // Field nodeSelectorTerms:Ljava/util/List;
       4: ifnonnull     18
       7: aload_0
       8: new           #23                 // class java/util/ArrayList
      11: dup
      12: invokespecial #24                 // Method java/util/ArrayList."<init>":()V
      15: putfield      #26                 // Field nodeSelectorTerms:Ljava/util/List;
      18: new           #47                 // class io/dekorate/deps/kubernetes/api/model/NodeSelectorTermBuilder
      21: dup
      22: aload_2
      23: invokespecial #50                 // Method io/dekorate/deps/kubernetes/api/model/NodeSelectorTermBuilder."<init>":(Lio/dekorate/deps/kubernetes/api/model/NodeSelectorTerm;)V
      26: astore_3
      27: aload_0
      28: getfield      #54                 // Field _visitables:Lio/dekorate/deps/kubernetes/api/builder/VisitableMap;
      31: ldc           #55                 // String nodeSelectorTerms
      33: invokevirtual #61                 // Method io/dekorate/deps/kubernetes/api/builder/VisitableMap.get:(Ljava/lang/Object;)Ljava/util/List;
      36: iload_1
      37: iflt          44
      40: iload_1
      41: goto          58
      44: aload_0
      45: getfield      #54                 // Field _visitables:Lio/dekorate/deps/kubernetes/api/builder/VisitableMap;
      48: ldc           #55                 // String nodeSelectorTerms
      50: invokevirtual #61                 // Method io/dekorate/deps/kubernetes/api/builder/VisitableMap.get:(Ljava/lang/Object;)Ljava/util/List;
      53: invokeinterface #69,  1           // InterfaceMethod java/util/List.size:()I
      58: aload_3
      59: invokeinterface #73,  3           // InterfaceMethod java/util/List.add:(ILjava/lang/Object;)V
      64: aload_0
      65: getfield      #26                 // Field nodeSelectorTerms:Ljava/util/List;
      68: iload_1
      69: iflt          76
      72: iload_1
      73: goto          85
      76: aload_0
      77: getfield      #26                 // Field nodeSelectorTerms:Ljava/util/List;
      80: invokeinterface #69,  1           // InterfaceMethod java/util/List.size:()I
      85: aload_3
      86: invokeinterface #73,  3           // InterfaceMethod java/util/List.add:(ILjava/lang/Object;)V
      91: aload_0
      92: areturn

  public A setToNodeSelectorTerms(int, io.dekorate.deps.kubernetes.api.model.NodeSelectorTerm);
    Code:
       0: aload_0
       1: getfield      #26                 // Field nodeSelectorTerms:Ljava/util/List;
       4: ifnonnull     18
       7: aload_0
       8: new           #23                 // class java/util/ArrayList
      11: dup
      12: invokespecial #24                 // Method java/util/ArrayList."<init>":()V
      15: putfield      #26                 // Field nodeSelectorTerms:Ljava/util/List;
      18: new           #47                 // class io/dekorate/deps/kubernetes/api/model/NodeSelectorTermBuilder
      21: dup
      22: aload_2
      23: invokespecial #50                 // Method io/dekorate/deps/kubernetes/api/model/NodeSelectorTermBuilder."<init>":(Lio/dekorate/deps/kubernetes/api/model/NodeSelectorTerm;)V
      26: astore_3
      27: iload_1
      28: iflt          49
      31: iload_1
      32: aload_0
      33: getfield      #54                 // Field _visitables:Lio/dekorate/deps/kubernetes/api/builder/VisitableMap;
      36: ldc           #55                 // String nodeSelectorTerms
      38: invokevirtual #61                 // Method io/dekorate/deps/kubernetes/api/builder/VisitableMap.get:(Ljava/lang/Object;)Ljava/util/List;
      41: invokeinterface #69,  1           // InterfaceMethod java/util/List.size:()I
      46: if_icmplt     68
      49: aload_0
      50: getfield      #54                 // Field _visitables:Lio/dekorate/deps/kubernetes/api/builder/VisitableMap;
      53: ldc           #55                 // String nodeSelectorTerms
      55: invokevirtual #61                 // Method io/dekorate/deps/kubernetes/api/builder/VisitableMap.get:(Ljava/lang/Object;)Ljava/util/List;
      58: aload_3
      59: invokeinterface #83,  2           // InterfaceMethod java/util/List.add:(Ljava/lang/Object;)Z
      64: pop
      65: goto          85
      68: aload_0
      69: getfield      #54                 // Field _visitables:Lio/dekorate/deps/kubernetes/api/builder/VisitableMap;
      72: ldc           #55                 // String nodeSelectorTerms
      74: invokevirtual #61                 // Method io/dekorate/deps/kubernetes/api/builder/VisitableMap.get:(Ljava/lang/Object;)Ljava/util/List;
      77: iload_1
      78: aload_3
      79: invokeinterface #87,  3           // InterfaceMethod java/util/List.set:(ILjava/lang/Object;)Ljava/lang/Object;
      84: pop
      85: iload_1
      86: iflt          102
      89: iload_1
      90: aload_0
      91: getfield      #26                 // Field nodeSelectorTerms:Ljava/util/List;
      94: invokeinterface #69,  1           // InterfaceMethod java/util/List.size:()I
      99: if_icmplt     116
     102: aload_0
     103: getfield      #26                 // Field nodeSelectorTerms:Ljava/util/List;
     106: aload_3
     107: invokeinterface #83,  2           // InterfaceMethod java/util/List.add:(Ljava/lang/Object;)Z
     112: pop
     113: goto          128
     116: aload_0
     117: getfield      #26                 // Field nodeSelectorTerms:Ljava/util/List;
     120: iload_1
     121: aload_3
     122: invokeinterface #87,  3           // InterfaceMethod java/util/List.set:(ILjava/lang/Object;)Ljava/lang/Object;
     127: pop
     128: aload_0
     129: areturn

  public A addToNodeSelectorTerms(io.dekorate.deps.kubernetes.api.model.NodeSelectorTerm...);
    Code:
       0: aload_0
       1: getfield      #26                 // Field nodeSelectorTerms:Ljava/util/List;
       4: ifnonnull     18
       7: aload_0
       8: new           #23                 // class java/util/ArrayList
      11: dup
      12: invokespecial #24                 // Method java/util/ArrayList."<init>":()V
      15: putfield      #26                 // Field nodeSelectorTerms:Ljava/util/List;
      18: aload_1
      19: astore_2
      20: aload_2
      21: arraylength
      22: istore_3
      23: iconst_0
      24: istore        4
      26: iload         4
      28: iload_3
      29: if_icmpge     84
      32: aload_2
      33: iload         4
      35: aaload
      36: astore        5
      38: new           #47                 // class io/dekorate/deps/kubernetes/api/model/NodeSelectorTermBuilder
      41: dup
      42: aload         5
      44: invokespecial #50                 // Method io/dekorate/deps/kubernetes/api/model/NodeSelectorTermBuilder."<init>":(Lio/dekorate/deps/kubernetes/api/model/NodeSelectorTerm;)V
      47: astore        6
      49: aload_0
      50: getfield      #54                 // Field _visitables:Lio/dekorate/deps/kubernetes/api/builder/VisitableMap;
      53: ldc           #55                 // String nodeSelectorTerms
      55: invokevirtual #61                 // Method io/dekorate/deps/kubernetes/api/builder/VisitableMap.get:(Ljava/lang/Object;)Ljava/util/List;
      58: aload         6
      60: invokeinterface #83,  2           // InterfaceMethod java/util/List.add:(Ljava/lang/Object;)Z
      65: pop
      66: aload_0
      67: getfield      #26                 // Field nodeSelectorTerms:Ljava/util/List;
      70: aload         6
      72: invokeinterface #83,  2           // InterfaceMethod java/util/List.add:(Ljava/lang/Object;)Z
      77: pop
      78: iinc          4, 1
      81: goto          26
      84: aload_0
      85: areturn

  public A addAllToNodeSelectorTerms(java.util.Collection<io.dekorate.deps.kubernetes.api.model.NodeSelectorTerm>);
    Code:
       0: aload_0
       1: getfield      #26                 // Field nodeSelectorTerms:Ljava/util/List;
       4: ifnonnull     18
       7: aload_0
       8: new           #23                 // class java/util/ArrayList
      11: dup
      12: invokespecial #24                 // Method java/util/ArrayList."<init>":()V
      15: putfield      #26                 // Field nodeSelectorTerms:Ljava/util/List;
      18: aload_1
      19: invokeinterface #101,  1          // InterfaceMethod java/util/Collection.iterator:()Ljava/util/Iterator;
      24: astore_2
      25: aload_2
      26: invokeinterface #107,  1          // InterfaceMethod java/util/Iterator.hasNext:()Z
      31: ifeq          86
      34: aload_2
      35: invokeinterface #111,  1          // InterfaceMethod java/util/Iterator.next:()Ljava/lang/Object;
      40: checkcast     #63                 // class io/dekorate/deps/kubernetes/api/model/NodeSelectorTerm
      43: astore_3
      44: new           #47                 // class io/dekorate/deps/kubernetes/api/model/NodeSelectorTermBuilder
      47: dup
      48: aload_3
      49: invokespecial #50                 // Method io/dekorate/deps/kubernetes/api/model/NodeSelectorTermBuilder."<init>":(Lio/dekorate/deps/kubernetes/api/model/NodeSelectorTerm;)V
      52: astore        4
      54: aload_0
      55: getfield      #54                 // Field _visitables:Lio/dekorate/deps/kubernetes/api/builder/VisitableMap;
      58: ldc           #55                 // String nodeSelectorTerms
      60: invokevirtual #61                 // Method io/dekorate/deps/kubernetes/api/builder/VisitableMap.get:(Ljava/lang/Object;)Ljava/util/List;
      63: aload         4
      65: invokeinterface #83,  2           // InterfaceMethod java/util/List.add:(Ljava/lang/Object;)Z
      70: pop
      71: aload_0
      72: getfield      #26                 // Field nodeSelectorTerms:Ljava/util/List;
      75: aload         4
      77: invokeinterface #83,  2           // InterfaceMethod java/util/List.add:(Ljava/lang/Object;)Z
      82: pop
      83: goto          25
      86: aload_0
      87: areturn

  public A removeFromNodeSelectorTerms(io.dekorate.deps.kubernetes.api.model.NodeSelectorTerm...);
    Code:
       0: aload_1
       1: astore_2
       2: aload_2
       3: arraylength
       4: istore_3
       5: iconst_0
       6: istore        4
       8: iload         4
      10: iload_3
      11: if_icmpge     73
      14: aload_2
      15: iload         4
      17: aaload
      18: astore        5
      20: new           #47                 // class io/dekorate/deps/kubernetes/api/model/NodeSelectorTermBuilder
      23: dup
      24: aload         5
      26: invokespecial #50                 // Method io/dekorate/deps/kubernetes/api/model/NodeSelectorTermBuilder."<init>":(Lio/dekorate/deps/kubernetes/api/model/NodeSelectorTerm;)V
      29: astore        6
      31: aload_0
      32: getfield      #54                 // Field _visitables:Lio/dekorate/deps/kubernetes/api/builder/VisitableMap;
      35: ldc           #55                 // String nodeSelectorTerms
      37: invokevirtual #61                 // Method io/dekorate/deps/kubernetes/api/builder/VisitableMap.get:(Ljava/lang/Object;)Ljava/util/List;
      40: aload         6
      42: invokeinterface #117,  2          // InterfaceMethod java/util/List.remove:(Ljava/lang/Object;)Z
      47: pop
      48: aload_0
      49: getfield      #26                 // Field nodeSelectorTerms:Ljava/util/List;
      52: ifnull        67
      55: aload_0
      56: getfield      #26                 // Field nodeSelectorTerms:Ljava/util/List;
      59: aload         6
      61: invokeinterface #117,  2          // InterfaceMethod java/util/List.remove:(Ljava/lang/Object;)Z
      66: pop
      67: iinc          4, 1
      70: goto          8
      73: aload_0
      74: areturn

  public A removeAllFromNodeSelectorTerms(java.util.Collection<io.dekorate.deps.kubernetes.api.model.NodeSelectorTerm>);
    Code:
       0: aload_1
       1: invokeinterface #101,  1          // InterfaceMethod java/util/Collection.iterator:()Ljava/util/Iterator;
       6: astore_2
       7: aload_2
       8: invokeinterface #107,  1          // InterfaceMethod java/util/Iterator.hasNext:()Z
      13: ifeq          75
      16: aload_2
      17: invokeinterface #111,  1          // InterfaceMethod java/util/Iterator.next:()Ljava/lang/Object;
      22: checkcast     #63                 // class io/dekorate/deps/kubernetes/api/model/NodeSelectorTerm
      25: astore_3
      26: new           #47                 // class io/dekorate/deps/kubernetes/api/model/NodeSelectorTermBuilder
      29: dup
      30: aload_3
      31: invokespecial #50                 // Method io/dekorate/deps/kubernetes/api/model/NodeSelectorTermBuilder."<init>":(Lio/dekorate/deps/kubernetes/api/model/NodeSelectorTerm;)V
      34: astore        4
      36: aload_0
      37: getfield      #54                 // Field _visitables:Lio/dekorate/deps/kubernetes/api/builder/VisitableMap;
      40: ldc           #55                 // String nodeSelectorTerms
      42: invokevirtual #61                 // Method io/dekorate/deps/kubernetes/api/builder/VisitableMap.get:(Ljava/lang/Object;)Ljava/util/List;
      45: aload         4
      47: invokeinterface #117,  2          // InterfaceMethod java/util/List.remove:(Ljava/lang/Object;)Z
      52: pop
      53: aload_0
      54: getfield      #26                 // Field nodeSelectorTerms:Ljava/util/List;
      57: ifnull        72
      60: aload_0
      61: getfield      #26                 // Field nodeSelectorTerms:Ljava/util/List;
      64: aload         4
      66: invokeinterface #117,  2          // InterfaceMethod java/util/List.remove:(Ljava/lang/Object;)Z
      71: pop
      72: goto          7
      75: aload_0
      76: areturn

  public A removeMatchingFromNodeSelectorTerms(io.dekorate.deps.kubernetes.api.builder.Predicate<io.dekorate.deps.kubernetes.api.model.NodeSelectorTermBuilder>);
    Code:
       0: aload_0
       1: getfield      #26                 // Field nodeSelectorTerms:Ljava/util/List;
       4: ifnonnull     9
       7: aload_0
       8: areturn
       9: aload_0
      10: getfield      #26                 // Field nodeSelectorTerms:Ljava/util/List;
      13: invokeinterface #122,  1          // InterfaceMethod java/util/List.iterator:()Ljava/util/Iterator;
      18: astore_2
      19: aload_0
      20: getfield      #54                 // Field _visitables:Lio/dekorate/deps/kubernetes/api/builder/VisitableMap;
      23: ldc           #55                 // String nodeSelectorTerms
      25: invokevirtual #61                 // Method io/dekorate/deps/kubernetes/api/builder/VisitableMap.get:(Ljava/lang/Object;)Ljava/util/List;
      28: astore_3
      29: aload_2
      30: invokeinterface #107,  1          // InterfaceMethod java/util/Iterator.hasNext:()Z
      35: ifeq          81
      38: aload_2
      39: invokeinterface #111,  1          // InterfaceMethod java/util/Iterator.next:()Ljava/lang/Object;
      44: checkcast     #47                 // class io/dekorate/deps/kubernetes/api/model/NodeSelectorTermBuilder
      47: astore        4
      49: aload_1
      50: aload         4
      52: invokeinterface #128,  2          // InterfaceMethod io/dekorate/deps/kubernetes/api/builder/Predicate.apply:(Ljava/lang/Object;)Ljava/lang/Boolean;
      57: invokevirtual #133                // Method java/lang/Boolean.booleanValue:()Z
      60: ifeq          78
      63: aload_3
      64: aload         4
      66: invokeinterface #117,  2          // InterfaceMethod java/util/List.remove:(Ljava/lang/Object;)Z
      71: pop
      72: aload_2
      73: invokeinterface #135,  1          // InterfaceMethod java/util/Iterator.remove:()V
      78: goto          29
      81: aload_0
      82: areturn

  public java.util.List<io.dekorate.deps.kubernetes.api.model.NodeSelectorTerm> getNodeSelectorTerms();
    Code:
       0: aload_0
       1: getfield      #26                 // Field nodeSelectorTerms:Ljava/util/List;
       4: invokestatic  #148                // Method build:(Ljava/util/List;)Ljava/util/ArrayList;
       7: areturn

  public java.util.List<io.dekorate.deps.kubernetes.api.model.NodeSelectorTerm> buildNodeSelectorTerms();
    Code:
       0: aload_0
       1: getfield      #26                 // Field nodeSelectorTerms:Ljava/util/List;
       4: invokestatic  #148                // Method build:(Ljava/util/List;)Ljava/util/ArrayList;
       7: areturn

  public io.dekorate.deps.kubernetes.api.model.NodeSelectorTerm buildNodeSelectorTerm(int);
    Code:
       0: aload_0
       1: getfield      #26                 // Field nodeSelectorTerms:Ljava/util/List;
       4: iload_1
       5: invokeinterface #154,  2          // InterfaceMethod java/util/List.get:(I)Ljava/lang/Object;
      10: checkcast     #47                 // class io/dekorate/deps/kubernetes/api/model/NodeSelectorTermBuilder
      13: invokevirtual #157                // Method io/dekorate/deps/kubernetes/api/model/NodeSelectorTermBuilder.build:()Lio/dekorate/deps/kubernetes/api/model/NodeSelectorTerm;
      16: areturn

  public io.dekorate.deps.kubernetes.api.model.NodeSelectorTerm buildFirstNodeSelectorTerm();
    Code:
       0: aload_0
       1: getfield      #26                 // Field nodeSelectorTerms:Ljava/util/List;
       4: iconst_0
       5: invokeinterface #154,  2          // InterfaceMethod java/util/List.get:(I)Ljava/lang/Object;
      10: checkcast     #47                 // class io/dekorate/deps/kubernetes/api/model/NodeSelectorTermBuilder
      13: invokevirtual #157                // Method io/dekorate/deps/kubernetes/api/model/NodeSelectorTermBuilder.build:()Lio/dekorate/deps/kubernetes/api/model/NodeSelectorTerm;
      16: areturn

  public io.dekorate.deps.kubernetes.api.model.NodeSelectorTerm buildLastNodeSelectorTerm();
    Code:
       0: aload_0
       1: getfield      #26                 // Field nodeSelectorTerms:Ljava/util/List;
       4: aload_0
       5: getfield      #26                 // Field nodeSelectorTerms:Ljava/util/List;
       8: invokeinterface #69,  1           // InterfaceMethod java/util/List.size:()I
      13: iconst_1
      14: isub
      15: invokeinterface #154,  2          // InterfaceMethod java/util/List.get:(I)Ljava/lang/Object;
      20: checkcast     #47                 // class io/dekorate/deps/kubernetes/api/model/NodeSelectorTermBuilder
      23: invokevirtual #157                // Method io/dekorate/deps/kubernetes/api/model/NodeSelectorTermBuilder.build:()Lio/dekorate/deps/kubernetes/api/model/NodeSelectorTerm;
      26: areturn

  public io.dekorate.deps.kubernetes.api.model.NodeSelectorTerm buildMatchingNodeSelectorTerm(io.dekorate.deps.kubernetes.api.builder.Predicate<io.dekorate.deps.kubernetes.api.model.NodeSelectorTermBuilder>);
    Code:
       0: aload_0
       1: getfield      #26                 // Field nodeSelectorTerms:Ljava/util/List;
       4: invokeinterface #122,  1          // InterfaceMethod java/util/List.iterator:()Ljava/util/Iterator;
       9: astore_2
      10: aload_2
      11: invokeinterface #107,  1          // InterfaceMethod java/util/Iterator.hasNext:()Z
      16: ifeq          50
      19: aload_2
      20: invokeinterface #111,  1          // InterfaceMethod java/util/Iterator.next:()Ljava/lang/Object;
      25: checkcast     #47                 // class io/dekorate/deps/kubernetes/api/model/NodeSelectorTermBuilder
      28: astore_3
      29: aload_1
      30: aload_3
      31: invokeinterface #128,  2          // InterfaceMethod io/dekorate/deps/kubernetes/api/builder/Predicate.apply:(Ljava/lang/Object;)Ljava/lang/Boolean;
      36: invokevirtual #133                // Method java/lang/Boolean.booleanValue:()Z
      39: ifeq          47
      42: aload_3
      43: invokevirtual #157                // Method io/dekorate/deps/kubernetes/api/model/NodeSelectorTermBuilder.build:()Lio/dekorate/deps/kubernetes/api/model/NodeSelectorTerm;
      46: areturn
      47: goto          10
      50: aconst_null
      51: areturn

  public java.lang.Boolean hasMatchingNodeSelectorTerm(io.dekorate.deps.kubernetes.api.builder.Predicate<io.dekorate.deps.kubernetes.api.model.NodeSelectorTermBuilder>);
    Code:
       0: aload_0
       1: getfield      #26                 // Field nodeSelectorTerms:Ljava/util/List;
       4: invokeinterface #122,  1          // InterfaceMethod java/util/List.iterator:()Ljava/util/Iterator;
       9: astore_2
      10: aload_2
      11: invokeinterface #107,  1          // InterfaceMethod java/util/Iterator.hasNext:()Z
      16: ifeq          50
      19: aload_2
      20: invokeinterface #111,  1          // InterfaceMethod java/util/Iterator.next:()Ljava/lang/Object;
      25: checkcast     #47                 // class io/dekorate/deps/kubernetes/api/model/NodeSelectorTermBuilder
      28: astore_3
      29: aload_1
      30: aload_3
      31: invokeinterface #128,  2          // InterfaceMethod io/dekorate/deps/kubernetes/api/builder/Predicate.apply:(Ljava/lang/Object;)Ljava/lang/Boolean;
      36: invokevirtual #133                // Method java/lang/Boolean.booleanValue:()Z
      39: ifeq          47
      42: iconst_1
      43: invokestatic  #169                // Method java/lang/Boolean.valueOf:(Z)Ljava/lang/Boolean;
      46: areturn
      47: goto          10
      50: iconst_0
      51: invokestatic  #169                // Method java/lang/Boolean.valueOf:(Z)Ljava/lang/Boolean;
      54: areturn

  public A withNodeSelectorTerms(java.util.List<io.dekorate.deps.kubernetes.api.model.NodeSelectorTerm>);
    Code:
       0: aload_0
       1: getfield      #26                 // Field nodeSelectorTerms:Ljava/util/List;
       4: ifnull        26
       7: aload_0
       8: getfield      #54                 // Field _visitables:Lio/dekorate/deps/kubernetes/api/builder/VisitableMap;
      11: ldc           #55                 // String nodeSelectorTerms
      13: invokevirtual #61                 // Method io/dekorate/deps/kubernetes/api/builder/VisitableMap.get:(Ljava/lang/Object;)Ljava/util/List;
      16: aload_0
      17: getfield      #26                 // Field nodeSelectorTerms:Ljava/util/List;
      20: invokeinterface #174,  2          // InterfaceMethod java/util/List.removeAll:(Ljava/util/Collection;)Z
      25: pop
      26: aload_1
      27: ifnull        86
      30: aload_0
      31: new           #23                 // class java/util/ArrayList
      34: dup
      35: invokespecial #24                 // Method java/util/ArrayList."<init>":()V
      38: putfield      #26                 // Field nodeSelectorTerms:Ljava/util/List;
      41: aload_1
      42: invokeinterface #122,  1          // InterfaceMethod java/util/List.iterator:()Ljava/util/Iterator;
      47: astore_2
      48: aload_2
      49: invokeinterface #107,  1          // InterfaceMethod java/util/Iterator.hasNext:()Z
      54: ifeq          83
      57: aload_2
      58: invokeinterface #111,  1          // InterfaceMethod java/util/Iterator.next:()Ljava/lang/Object;
      63: checkcast     #63                 // class io/dekorate/deps/kubernetes/api/model/NodeSelectorTerm
      66: astore_3
      67: aload_0
      68: iconst_1
      69: anewarray     #63                 // class io/dekorate/deps/kubernetes/api/model/NodeSelectorTerm
      72: dup
      73: iconst_0
      74: aload_3
      75: aastore
      76: invokevirtual #176                // Method addToNodeSelectorTerms:([Lio/dekorate/deps/kubernetes/api/model/NodeSelectorTerm;)Lio/dekorate/deps/kubernetes/api/model/NodeSelectorFluent;
      79: pop
      80: goto          48
      83: goto          91
      86: aload_0
      87: aconst_null
      88: putfield      #26                 // Field nodeSelectorTerms:Ljava/util/List;
      91: aload_0
      92: areturn

  public A withNodeSelectorTerms(io.dekorate.deps.kubernetes.api.model.NodeSelectorTerm...);
    Code:
       0: aload_0
       1: getfield      #26                 // Field nodeSelectorTerms:Ljava/util/List;
       4: ifnull        16
       7: aload_0
       8: getfield      #26                 // Field nodeSelectorTerms:Ljava/util/List;
      11: invokeinterface #180,  1          // InterfaceMethod java/util/List.clear:()V
      16: aload_1
      17: ifnull        60
      20: aload_1
      21: astore_2
      22: aload_2
      23: arraylength
      24: istore_3
      25: iconst_0
      26: istore        4
      28: iload         4
      30: iload_3
      31: if_icmpge     60
      34: aload_2
      35: iload         4
      37: aaload
      38: astore        5
      40: aload_0
      41: iconst_1
      42: anewarray     #63                 // class io/dekorate/deps/kubernetes/api/model/NodeSelectorTerm
      45: dup
      46: iconst_0
      47: aload         5
      49: aastore
      50: invokevirtual #176                // Method addToNodeSelectorTerms:([Lio/dekorate/deps/kubernetes/api/model/NodeSelectorTerm;)Lio/dekorate/deps/kubernetes/api/model/NodeSelectorFluent;
      53: pop
      54: iinc          4, 1
      57: goto          28
      60: aload_0
      61: areturn

  public java.lang.Boolean hasNodeSelectorTerms();
    Code:
       0: aload_0
       1: getfield      #26                 // Field nodeSelectorTerms:Ljava/util/List;
       4: ifnull        23
       7: aload_0
       8: getfield      #26                 // Field nodeSelectorTerms:Ljava/util/List;
      11: invokeinterface #185,  1          // InterfaceMethod java/util/List.isEmpty:()Z
      16: ifne          23
      19: iconst_1
      20: goto          24
      23: iconst_0
      24: invokestatic  #169                // Method java/lang/Boolean.valueOf:(Z)Ljava/lang/Boolean;
      27: areturn

  public io.dekorate.deps.kubernetes.api.model.NodeSelectorFluent$NodeSelectorTermsNested<A> addNewNodeSelectorTerm();
    Code:
       0: new           #10                 // class io/dekorate/deps/kubernetes/api/model/NodeSelectorFluentImpl$NodeSelectorTermsNestedImpl
       3: dup
       4: aload_0
       5: invokespecial #191                // Method io/dekorate/deps/kubernetes/api/model/NodeSelectorFluentImpl$NodeSelectorTermsNestedImpl."<init>":(Lio/dekorate/deps/kubernetes/api/model/NodeSelectorFluentImpl;)V
       8: areturn

  public io.dekorate.deps.kubernetes.api.model.NodeSelectorFluent$NodeSelectorTermsNested<A> addNewNodeSelectorTermLike(io.dekorate.deps.kubernetes.api.model.NodeSelectorTerm);
    Code:
       0: new           #10                 // class io/dekorate/deps/kubernetes/api/model/NodeSelectorFluentImpl$NodeSelectorTermsNestedImpl
       3: dup
       4: aload_0
       5: iconst_m1
       6: aload_1
       7: invokespecial #197                // Method io/dekorate/deps/kubernetes/api/model/NodeSelectorFluentImpl$NodeSelectorTermsNestedImpl."<init>":(Lio/dekorate/deps/kubernetes/api/model/NodeSelectorFluentImpl;ILio/dekorate/deps/kubernetes/api/model/NodeSelectorTerm;)V
      10: areturn

  public io.dekorate.deps.kubernetes.api.model.NodeSelectorFluent$NodeSelectorTermsNested<A> setNewNodeSelectorTermLike(int, io.dekorate.deps.kubernetes.api.model.NodeSelectorTerm);
    Code:
       0: new           #10                 // class io/dekorate/deps/kubernetes/api/model/NodeSelectorFluentImpl$NodeSelectorTermsNestedImpl
       3: dup
       4: aload_0
       5: iload_1
       6: aload_2
       7: invokespecial #197                // Method io/dekorate/deps/kubernetes/api/model/NodeSelectorFluentImpl$NodeSelectorTermsNestedImpl."<init>":(Lio/dekorate/deps/kubernetes/api/model/NodeSelectorFluentImpl;ILio/dekorate/deps/kubernetes/api/model/NodeSelectorTerm;)V
      10: areturn

  public io.dekorate.deps.kubernetes.api.model.NodeSelectorFluent$NodeSelectorTermsNested<A> editNodeSelectorTerm(int);
    Code:
       0: aload_0
       1: getfield      #26                 // Field nodeSelectorTerms:Ljava/util/List;
       4: invokeinterface #69,  1           // InterfaceMethod java/util/List.size:()I
       9: iload_1
      10: if_icmpgt     23
      13: new           #205                // class java/lang/RuntimeException
      16: dup
      17: ldc           #207                // String Can\'t edit nodeSelectorTerms. Index exceeds size.
      19: invokespecial #210                // Method java/lang/RuntimeException."<init>":(Ljava/lang/String;)V
      22: athrow
      23: aload_0
      24: iload_1
      25: aload_0
      26: iload_1
      27: invokevirtual #212                // Method buildNodeSelectorTerm:(I)Lio/dekorate/deps/kubernetes/api/model/NodeSelectorTerm;
      30: invokevirtual #214                // Method setNewNodeSelectorTermLike:(ILio/dekorate/deps/kubernetes/api/model/NodeSelectorTerm;)Lio/dekorate/deps/kubernetes/api/model/NodeSelectorFluent$NodeSelectorTermsNested;
      33: areturn

  public io.dekorate.deps.kubernetes.api.model.NodeSelectorFluent$NodeSelectorTermsNested<A> editFirstNodeSelectorTerm();
    Code:
       0: aload_0
       1: getfield      #26                 // Field nodeSelectorTerms:Ljava/util/List;
       4: invokeinterface #69,  1           // InterfaceMethod java/util/List.size:()I
       9: ifne          22
      12: new           #205                // class java/lang/RuntimeException
      15: dup
      16: ldc           #217                // String Can\'t edit first nodeSelectorTerms. The list is empty.
      18: invokespecial #210                // Method java/lang/RuntimeException."<init>":(Ljava/lang/String;)V
      21: athrow
      22: aload_0
      23: iconst_0
      24: aload_0
      25: iconst_0
      26: invokevirtual #212                // Method buildNodeSelectorTerm:(I)Lio/dekorate/deps/kubernetes/api/model/NodeSelectorTerm;
      29: invokevirtual #214                // Method setNewNodeSelectorTermLike:(ILio/dekorate/deps/kubernetes/api/model/NodeSelectorTerm;)Lio/dekorate/deps/kubernetes/api/model/NodeSelectorFluent$NodeSelectorTermsNested;
      32: areturn

  public io.dekorate.deps.kubernetes.api.model.NodeSelectorFluent$NodeSelectorTermsNested<A> editLastNodeSelectorTerm();
    Code:
       0: aload_0
       1: getfield      #26                 // Field nodeSelectorTerms:Ljava/util/List;
       4: invokeinterface #69,  1           // InterfaceMethod java/util/List.size:()I
       9: iconst_1
      10: isub
      11: istore_1
      12: iload_1
      13: ifge          26
      16: new           #205                // class java/lang/RuntimeException
      19: dup
      20: ldc           #220                // String Can\'t edit last nodeSelectorTerms. The list is empty.
      22: invokespecial #210                // Method java/lang/RuntimeException."<init>":(Ljava/lang/String;)V
      25: athrow
      26: aload_0
      27: iload_1
      28: aload_0
      29: iload_1
      30: invokevirtual #212                // Method buildNodeSelectorTerm:(I)Lio/dekorate/deps/kubernetes/api/model/NodeSelectorTerm;
      33: invokevirtual #214                // Method setNewNodeSelectorTermLike:(ILio/dekorate/deps/kubernetes/api/model/NodeSelectorTerm;)Lio/dekorate/deps/kubernetes/api/model/NodeSelectorFluent$NodeSelectorTermsNested;
      36: areturn

  public io.dekorate.deps.kubernetes.api.model.NodeSelectorFluent$NodeSelectorTermsNested<A> editMatchingNodeSelectorTerm(io.dekorate.deps.kubernetes.api.builder.Predicate<io.dekorate.deps.kubernetes.api.model.NodeSelectorTermBuilder>);
    Code:
       0: iconst_m1
       1: istore_2
       2: iconst_0
       3: istore_3
       4: iload_3
       5: aload_0
       6: getfield      #26                 // Field nodeSelectorTerms:Ljava/util/List;
       9: invokeinterface #69,  1           // InterfaceMethod java/util/List.size:()I
      14: if_icmpge     50
      17: aload_1
      18: aload_0
      19: getfield      #26                 // Field nodeSelectorTerms:Ljava/util/List;
      22: iload_3
      23: invokeinterface #154,  2          // InterfaceMethod java/util/List.get:(I)Ljava/lang/Object;
      28: invokeinterface #128,  2          // InterfaceMethod io/dekorate/deps/kubernetes/api/builder/Predicate.apply:(Ljava/lang/Object;)Ljava/lang/Boolean;
      33: invokevirtual #133                // Method java/lang/Boolean.booleanValue:()Z
      36: ifeq          44
      39: iload_3
      40: istore_2
      41: goto          50
      44: iinc          3, 1
      47: goto          4
      50: iload_2
      51: ifge          64
      54: new           #205                // class java/lang/RuntimeException
      57: dup
      58: ldc           #225                // String Can\'t edit matching nodeSelectorTerms. No match found.
      60: invokespecial #210                // Method java/lang/RuntimeException."<init>":(Ljava/lang/String;)V
      63: athrow
      64: aload_0
      65: iload_2
      66: aload_0
      67: iload_2
      68: invokevirtual #212                // Method buildNodeSelectorTerm:(I)Lio/dekorate/deps/kubernetes/api/model/NodeSelectorTerm;
      71: invokevirtual #214                // Method setNewNodeSelectorTermLike:(ILio/dekorate/deps/kubernetes/api/model/NodeSelectorTerm;)Lio/dekorate/deps/kubernetes/api/model/NodeSelectorFluent$NodeSelectorTermsNested;
      74: areturn

  public boolean equals(java.lang.Object);
    Code:
       0: aload_0
       1: aload_1
       2: if_acmpne     7
       5: iconst_1
       6: ireturn
       7: aload_1
       8: ifnull        22
      11: aload_0
      12: invokevirtual #233                // Method java/lang/Object.getClass:()Ljava/lang/Class;
      15: aload_1
      16: invokevirtual #233                // Method java/lang/Object.getClass:()Ljava/lang/Class;
      19: if_acmpeq     24
      22: iconst_0
      23: ireturn
      24: aload_1
      25: checkcast     #2                  // class io/dekorate/deps/kubernetes/api/model/NodeSelectorFluentImpl
      28: astore_2
      29: aload_0
      30: getfield      #26                 // Field nodeSelectorTerms:Ljava/util/List;
      33: ifnull        55
      36: aload_0
      37: getfield      #26                 // Field nodeSelectorTerms:Ljava/util/List;
      40: aload_2
      41: getfield      #26                 // Field nodeSelectorTerms:Ljava/util/List;
      44: invokeinterface #235,  2          // InterfaceMethod java/util/List.equals:(Ljava/lang/Object;)Z
      49: ifne          64
      52: goto          62
      55: aload_2
      56: getfield      #26                 // Field nodeSelectorTerms:Ljava/util/List;
      59: ifnull        64
      62: iconst_0
      63: ireturn
      64: iconst_1
      65: ireturn
}
