Compiled from "NodeAffinityFluentImpl.java"
public class io.dekorate.deps.kubernetes.api.model.NodeAffinityFluentImpl$PreferredDuringSchedulingIgnoredDuringExecutionNestedImpl<N> extends io.dekorate.deps.kubernetes.api.model.PreferredSchedulingTermFluentImpl<io.dekorate.deps.kubernetes.api.model.NodeAffinityFluent$PreferredDuringSchedulingIgnoredDuringExecutionNested<N>> implements io.dekorate.deps.kubernetes.api.model.NodeAffinityFluent$PreferredDuringSchedulingIgnoredDuringExecutionNested<N>, io.dekorate.deps.kubernetes.api.builder.Nested<N> {
  private final io.dekorate.deps.kubernetes.api.model.PreferredSchedulingTermBuilder builder;

  private final int index;

  final io.dekorate.deps.kubernetes.api.model.NodeAffinityFluentImpl this$0;

  io.dekorate.deps.kubernetes.api.model.NodeAffinityFluentImpl$PreferredDuringSchedulingIgnoredDuringExecutionNestedImpl(io.dekorate.deps.kubernetes.api.model.NodeAffinityFluentImpl, int, io.dekorate.deps.kubernetes.api.model.PreferredSchedulingTerm);
    Code:
       0: aload_0
       1: aload_1
       2: putfield      #26                 // Field this$0:Lio/dekorate/deps/kubernetes/api/model/NodeAffinityFluentImpl;
       5: aload_0
       6: invokespecial #29                 // Method io/dekorate/deps/kubernetes/api/model/PreferredSchedulingTermFluentImpl."<init>":()V
       9: aload_0
      10: iload_2
      11: putfield      #31                 // Field index:I
      14: aload_0
      15: new           #33                 // class io/dekorate/deps/kubernetes/api/model/PreferredSchedulingTermBuilder
      18: dup
      19: aload_0
      20: aload_3
      21: invokespecial #36                 // Method io/dekorate/deps/kubernetes/api/model/PreferredSchedulingTermBuilder."<init>":(Lio/dekorate/deps/kubernetes/api/model/PreferredSchedulingTermFluent;Lio/dekorate/deps/kubernetes/api/model/PreferredSchedulingTerm;)V
      24: putfield      #38                 // Field builder:Lio/dekorate/deps/kubernetes/api/model/PreferredSchedulingTermBuilder;
      27: return

  io.dekorate.deps.kubernetes.api.model.NodeAffinityFluentImpl$PreferredDuringSchedulingIgnoredDuringExecutionNestedImpl(io.dekorate.deps.kubernetes.api.model.NodeAffinityFluentImpl);
    Code:
       0: aload_0
       1: aload_1
       2: putfield      #26                 // Field this$0:Lio/dekorate/deps/kubernetes/api/model/NodeAffinityFluentImpl;
       5: aload_0
       6: invokespecial #29                 // Method io/dekorate/deps/kubernetes/api/model/PreferredSchedulingTermFluentImpl."<init>":()V
       9: aload_0
      10: iconst_m1
      11: putfield      #31                 // Field index:I
      14: aload_0
      15: new           #33                 // class io/dekorate/deps/kubernetes/api/model/PreferredSchedulingTermBuilder
      18: dup
      19: aload_0
      20: invokespecial #47                 // Method io/dekorate/deps/kubernetes/api/model/PreferredSchedulingTermBuilder."<init>":(Lio/dekorate/deps/kubernetes/api/model/PreferredSchedulingTermFluent;)V
      23: putfield      #38                 // Field builder:Lio/dekorate/deps/kubernetes/api/model/PreferredSchedulingTermBuilder;
      26: return

  public N and();
    Code:
       0: aload_0
       1: getfield      #26                 // Field this$0:Lio/dekorate/deps/kubernetes/api/model/NodeAffinityFluentImpl;
       4: aload_0
       5: getfield      #31                 // Field index:I
       8: aload_0
       9: getfield      #38                 // Field builder:Lio/dekorate/deps/kubernetes/api/model/PreferredSchedulingTermBuilder;
      12: invokevirtual #54                 // Method io/dekorate/deps/kubernetes/api/model/PreferredSchedulingTermBuilder.build:()Lio/dekorate/deps/kubernetes/api/model/PreferredSchedulingTerm;
      15: invokevirtual #58                 // Method io/dekorate/deps/kubernetes/api/model/NodeAffinityFluentImpl.setToPreferredDuringSchedulingIgnoredDuringExecution:(ILio/dekorate/deps/kubernetes/api/model/PreferredSchedulingTerm;)Lio/dekorate/deps/kubernetes/api/model/NodeAffinityFluent;
      18: areturn

  public N endPreferredDuringSchedulingIgnoredDuringExecution();
    Code:
       0: aload_0
       1: invokevirtual #61                 // Method and:()Ljava/lang/Object;
       4: areturn
}
