Compiled from "PodSecurityContextFluentImpl.java"
public class io.dekorate.deps.kubernetes.api.model.PodSecurityContextFluentImpl$SysctlsNestedImpl<N> extends io.dekorate.deps.kubernetes.api.model.SysctlFluentImpl<io.dekorate.deps.kubernetes.api.model.PodSecurityContextFluent$SysctlsNested<N>> implements io.dekorate.deps.kubernetes.api.model.PodSecurityContextFluent$SysctlsNested<N>, io.dekorate.deps.kubernetes.api.builder.Nested<N> {
  private final io.dekorate.deps.kubernetes.api.model.SysctlBuilder builder;

  private final int index;

  final io.dekorate.deps.kubernetes.api.model.PodSecurityContextFluentImpl this$0;

  io.dekorate.deps.kubernetes.api.model.PodSecurityContextFluentImpl$SysctlsNestedImpl(io.dekorate.deps.kubernetes.api.model.PodSecurityContextFluentImpl, int, io.dekorate.deps.kubernetes.api.model.Sysctl);
    Code:
       0: aload_0
       1: aload_1
       2: putfield      #26                 // Field this$0:Lio/dekorate/deps/kubernetes/api/model/PodSecurityContextFluentImpl;
       5: aload_0
       6: invokespecial #29                 // Method io/dekorate/deps/kubernetes/api/model/SysctlFluentImpl."<init>":()V
       9: aload_0
      10: iload_2
      11: putfield      #31                 // Field index:I
      14: aload_0
      15: new           #33                 // class io/dekorate/deps/kubernetes/api/model/SysctlBuilder
      18: dup
      19: aload_0
      20: aload_3
      21: invokespecial #36                 // Method io/dekorate/deps/kubernetes/api/model/SysctlBuilder."<init>":(Lio/dekorate/deps/kubernetes/api/model/SysctlFluent;Lio/dekorate/deps/kubernetes/api/model/Sysctl;)V
      24: putfield      #38                 // Field builder:Lio/dekorate/deps/kubernetes/api/model/SysctlBuilder;
      27: return

  io.dekorate.deps.kubernetes.api.model.PodSecurityContextFluentImpl$SysctlsNestedImpl(io.dekorate.deps.kubernetes.api.model.PodSecurityContextFluentImpl);
    Code:
       0: aload_0
       1: aload_1
       2: putfield      #26                 // Field this$0:Lio/dekorate/deps/kubernetes/api/model/PodSecurityContextFluentImpl;
       5: aload_0
       6: invokespecial #29                 // Method io/dekorate/deps/kubernetes/api/model/SysctlFluentImpl."<init>":()V
       9: aload_0
      10: iconst_m1
      11: putfield      #31                 // Field index:I
      14: aload_0
      15: new           #33                 // class io/dekorate/deps/kubernetes/api/model/SysctlBuilder
      18: dup
      19: aload_0
      20: invokespecial #47                 // Method io/dekorate/deps/kubernetes/api/model/SysctlBuilder."<init>":(Lio/dekorate/deps/kubernetes/api/model/SysctlFluent;)V
      23: putfield      #38                 // Field builder:Lio/dekorate/deps/kubernetes/api/model/SysctlBuilder;
      26: return

  public N and();
    Code:
       0: aload_0
       1: getfield      #26                 // Field this$0:Lio/dekorate/deps/kubernetes/api/model/PodSecurityContextFluentImpl;
       4: aload_0
       5: getfield      #31                 // Field index:I
       8: aload_0
       9: getfield      #38                 // Field builder:Lio/dekorate/deps/kubernetes/api/model/SysctlBuilder;
      12: invokevirtual #54                 // Method io/dekorate/deps/kubernetes/api/model/SysctlBuilder.build:()Lio/dekorate/deps/kubernetes/api/model/Sysctl;
      15: invokevirtual #58                 // Method io/dekorate/deps/kubernetes/api/model/PodSecurityContextFluentImpl.setToSysctls:(ILio/dekorate/deps/kubernetes/api/model/Sysctl;)Lio/dekorate/deps/kubernetes/api/model/PodSecurityContextFluent;
      18: areturn

  public N endSysctl();
    Code:
       0: aload_0
       1: invokevirtual #61                 // Method and:()Ljava/lang/Object;
       4: areturn
}
