Compiled from "PodSpecFluentImpl.java"
public class io.dekorate.deps.kubernetes.api.model.PodSpecFluentImpl$EphemeralContainersNestedImpl<N> extends io.dekorate.deps.kubernetes.api.model.EphemeralContainerFluentImpl<io.dekorate.deps.kubernetes.api.model.PodSpecFluent$EphemeralContainersNested<N>> implements io.dekorate.deps.kubernetes.api.model.PodSpecFluent$EphemeralContainersNested<N>, io.dekorate.deps.kubernetes.api.builder.Nested<N> {
  private final io.dekorate.deps.kubernetes.api.model.EphemeralContainerBuilder builder;

  private final int index;

  final io.dekorate.deps.kubernetes.api.model.PodSpecFluentImpl this$0;

  io.dekorate.deps.kubernetes.api.model.PodSpecFluentImpl$EphemeralContainersNestedImpl(io.dekorate.deps.kubernetes.api.model.PodSpecFluentImpl, int, io.dekorate.deps.kubernetes.api.model.EphemeralContainer);
    Code:
       0: aload_0
       1: aload_1
       2: putfield      #26                 // Field this$0:Lio/dekorate/deps/kubernetes/api/model/PodSpecFluentImpl;
       5: aload_0
       6: invokespecial #29                 // Method io/dekorate/deps/kubernetes/api/model/EphemeralContainerFluentImpl."<init>":()V
       9: aload_0
      10: iload_2
      11: putfield      #31                 // Field index:I
      14: aload_0
      15: new           #33                 // class io/dekorate/deps/kubernetes/api/model/EphemeralContainerBuilder
      18: dup
      19: aload_0
      20: aload_3
      21: invokespecial #36                 // Method io/dekorate/deps/kubernetes/api/model/EphemeralContainerBuilder."<init>":(Lio/dekorate/deps/kubernetes/api/model/EphemeralContainerFluent;Lio/dekorate/deps/kubernetes/api/model/EphemeralContainer;)V
      24: putfield      #38                 // Field builder:Lio/dekorate/deps/kubernetes/api/model/EphemeralContainerBuilder;
      27: return

  io.dekorate.deps.kubernetes.api.model.PodSpecFluentImpl$EphemeralContainersNestedImpl(io.dekorate.deps.kubernetes.api.model.PodSpecFluentImpl);
    Code:
       0: aload_0
       1: aload_1
       2: putfield      #26                 // Field this$0:Lio/dekorate/deps/kubernetes/api/model/PodSpecFluentImpl;
       5: aload_0
       6: invokespecial #29                 // Method io/dekorate/deps/kubernetes/api/model/EphemeralContainerFluentImpl."<init>":()V
       9: aload_0
      10: iconst_m1
      11: putfield      #31                 // Field index:I
      14: aload_0
      15: new           #33                 // class io/dekorate/deps/kubernetes/api/model/EphemeralContainerBuilder
      18: dup
      19: aload_0
      20: invokespecial #47                 // Method io/dekorate/deps/kubernetes/api/model/EphemeralContainerBuilder."<init>":(Lio/dekorate/deps/kubernetes/api/model/EphemeralContainerFluent;)V
      23: putfield      #38                 // Field builder:Lio/dekorate/deps/kubernetes/api/model/EphemeralContainerBuilder;
      26: return

  public N and();
    Code:
       0: aload_0
       1: getfield      #26                 // Field this$0:Lio/dekorate/deps/kubernetes/api/model/PodSpecFluentImpl;
       4: aload_0
       5: getfield      #31                 // Field index:I
       8: aload_0
       9: getfield      #38                 // Field builder:Lio/dekorate/deps/kubernetes/api/model/EphemeralContainerBuilder;
      12: invokevirtual #54                 // Method io/dekorate/deps/kubernetes/api/model/EphemeralContainerBuilder.build:()Lio/dekorate/deps/kubernetes/api/model/EphemeralContainer;
      15: invokevirtual #58                 // Method io/dekorate/deps/kubernetes/api/model/PodSpecFluentImpl.setToEphemeralContainers:(ILio/dekorate/deps/kubernetes/api/model/EphemeralContainer;)Lio/dekorate/deps/kubernetes/api/model/PodSpecFluent;
      18: areturn

  public N endEphemeralContainer();
    Code:
       0: aload_0
       1: invokevirtual #61                 // Method and:()Ljava/lang/Object;
       4: areturn
}
