Compiled from "PodsMetricSourceBuilder.java"
public class io.dekorate.deps.kubernetes.api.model.PodsMetricSourceBuilder extends io.dekorate.deps.kubernetes.api.model.PodsMetricSourceFluentImpl<io.dekorate.deps.kubernetes.api.model.PodsMetricSourceBuilder> implements io.dekorate.deps.kubernetes.api.builder.VisitableBuilder<io.dekorate.deps.kubernetes.api.model.PodsMetricSource, io.dekorate.deps.kubernetes.api.model.PodsMetricSourceBuilder> {
  io.dekorate.deps.kubernetes.api.model.PodsMetricSourceFluent<?> fluent;

  java.lang.Boolean validationEnabled;

  public io.dekorate.deps.kubernetes.api.model.PodsMetricSourceBuilder();
    Code:
       0: aload_0
       1: iconst_1
       2: invokestatic  #21                 // Method java/lang/Boolean.valueOf:(Z)Ljava/lang/Boolean;
       5: invokespecial #24                 // Method "<init>":(Ljava/lang/Boolean;)V
       8: return

  public io.dekorate.deps.kubernetes.api.model.PodsMetricSourceBuilder(java.lang.Boolean);
    Code:
       0: aload_0
       1: new           #28                 // class io/dekorate/deps/kubernetes/api/model/PodsMetricSource
       4: dup
       5: invokespecial #30                 // Method io/dekorate/deps/kubernetes/api/model/PodsMetricSource."<init>":()V
       8: aload_1
       9: invokespecial #33                 // Method "<init>":(Lio/dekorate/deps/kubernetes/api/model/PodsMetricSource;Ljava/lang/Boolean;)V
      12: return

  public io.dekorate.deps.kubernetes.api.model.PodsMetricSourceBuilder(io.dekorate.deps.kubernetes.api.model.PodsMetricSourceFluent<?>);
    Code:
       0: aload_0
       1: aload_1
       2: iconst_1
       3: invokestatic  #21                 // Method java/lang/Boolean.valueOf:(Z)Ljava/lang/Boolean;
       6: invokespecial #38                 // Method "<init>":(Lio/dekorate/deps/kubernetes/api/model/PodsMetricSourceFluent;Ljava/lang/Boolean;)V
       9: return

  public io.dekorate.deps.kubernetes.api.model.PodsMetricSourceBuilder(io.dekorate.deps.kubernetes.api.model.PodsMetricSourceFluent<?>, java.lang.Boolean);
    Code:
       0: aload_0
       1: aload_1
       2: new           #28                 // class io/dekorate/deps/kubernetes/api/model/PodsMetricSource
       5: dup
       6: invokespecial #30                 // Method io/dekorate/deps/kubernetes/api/model/PodsMetricSource."<init>":()V
       9: aload_2
      10: invokespecial #42                 // Method "<init>":(Lio/dekorate/deps/kubernetes/api/model/PodsMetricSourceFluent;Lio/dekorate/deps/kubernetes/api/model/PodsMetricSource;Ljava/lang/Boolean;)V
      13: return

  public io.dekorate.deps.kubernetes.api.model.PodsMetricSourceBuilder(io.dekorate.deps.kubernetes.api.model.PodsMetricSourceFluent<?>, io.dekorate.deps.kubernetes.api.model.PodsMetricSource);
    Code:
       0: aload_0
       1: aload_1
       2: aload_2
       3: iconst_1
       4: invokestatic  #21                 // Method java/lang/Boolean.valueOf:(Z)Ljava/lang/Boolean;
       7: invokespecial #42                 // Method "<init>":(Lio/dekorate/deps/kubernetes/api/model/PodsMetricSourceFluent;Lio/dekorate/deps/kubernetes/api/model/PodsMetricSource;Ljava/lang/Boolean;)V
      10: return

  public io.dekorate.deps.kubernetes.api.model.PodsMetricSourceBuilder(io.dekorate.deps.kubernetes.api.model.PodsMetricSourceFluent<?>, io.dekorate.deps.kubernetes.api.model.PodsMetricSource, java.lang.Boolean);
    Code:
       0: aload_0
       1: invokespecial #48                 // Method io/dekorate/deps/kubernetes/api/model/PodsMetricSourceFluentImpl."<init>":()V
       4: aload_0
       5: aload_1
       6: putfield      #50                 // Field fluent:Lio/dekorate/deps/kubernetes/api/model/PodsMetricSourceFluent;
       9: aload_1
      10: aload_2
      11: invokevirtual #54                 // Method io/dekorate/deps/kubernetes/api/model/PodsMetricSource.getMetric:()Lio/dekorate/deps/kubernetes/api/model/MetricIdentifier;
      14: invokeinterface #60,  2           // InterfaceMethod io/dekorate/deps/kubernetes/api/model/PodsMetricSourceFluent.withMetric:(Lio/dekorate/deps/kubernetes/api/model/MetricIdentifier;)Lio/dekorate/deps/kubernetes/api/model/PodsMetricSourceFluent;
      19: pop
      20: aload_1
      21: aload_2
      22: invokevirtual #64                 // Method io/dekorate/deps/kubernetes/api/model/PodsMetricSource.getTarget:()Lio/dekorate/deps/kubernetes/api/model/MetricTarget;
      25: invokeinterface #68,  2           // InterfaceMethod io/dekorate/deps/kubernetes/api/model/PodsMetricSourceFluent.withTarget:(Lio/dekorate/deps/kubernetes/api/model/MetricTarget;)Lio/dekorate/deps/kubernetes/api/model/PodsMetricSourceFluent;
      30: pop
      31: aload_0
      32: aload_3
      33: putfield      #70                 // Field validationEnabled:Ljava/lang/Boolean;
      36: return

  public io.dekorate.deps.kubernetes.api.model.PodsMetricSourceBuilder(io.dekorate.deps.kubernetes.api.model.PodsMetricSource);
    Code:
       0: aload_0
       1: aload_1
       2: iconst_1
       3: invokestatic  #21                 // Method java/lang/Boolean.valueOf:(Z)Ljava/lang/Boolean;
       6: invokespecial #33                 // Method "<init>":(Lio/dekorate/deps/kubernetes/api/model/PodsMetricSource;Ljava/lang/Boolean;)V
       9: return

  public io.dekorate.deps.kubernetes.api.model.PodsMetricSourceBuilder(io.dekorate.deps.kubernetes.api.model.PodsMetricSource, java.lang.Boolean);
    Code:
       0: aload_0
       1: invokespecial #48                 // Method io/dekorate/deps/kubernetes/api/model/PodsMetricSourceFluentImpl."<init>":()V
       4: aload_0
       5: aload_0
       6: putfield      #50                 // Field fluent:Lio/dekorate/deps/kubernetes/api/model/PodsMetricSourceFluent;
       9: aload_0
      10: aload_1
      11: invokevirtual #54                 // Method io/dekorate/deps/kubernetes/api/model/PodsMetricSource.getMetric:()Lio/dekorate/deps/kubernetes/api/model/MetricIdentifier;
      14: invokevirtual #72                 // Method withMetric:(Lio/dekorate/deps/kubernetes/api/model/MetricIdentifier;)Lio/dekorate/deps/kubernetes/api/model/PodsMetricSourceFluent;
      17: pop
      18: aload_0
      19: aload_1
      20: invokevirtual #64                 // Method io/dekorate/deps/kubernetes/api/model/PodsMetricSource.getTarget:()Lio/dekorate/deps/kubernetes/api/model/MetricTarget;
      23: invokevirtual #73                 // Method withTarget:(Lio/dekorate/deps/kubernetes/api/model/MetricTarget;)Lio/dekorate/deps/kubernetes/api/model/PodsMetricSourceFluent;
      26: pop
      27: aload_0
      28: aload_2
      29: putfield      #70                 // Field validationEnabled:Ljava/lang/Boolean;
      32: return

  public io.dekorate.deps.kubernetes.api.model.PodsMetricSource build();
    Code:
       0: new           #28                 // class io/dekorate/deps/kubernetes/api/model/PodsMetricSource
       3: dup
       4: aload_0
       5: getfield      #50                 // Field fluent:Lio/dekorate/deps/kubernetes/api/model/PodsMetricSourceFluent;
       8: invokeinterface #76,  1           // InterfaceMethod io/dekorate/deps/kubernetes/api/model/PodsMetricSourceFluent.getMetric:()Lio/dekorate/deps/kubernetes/api/model/MetricIdentifier;
      13: aload_0
      14: getfield      #50                 // Field fluent:Lio/dekorate/deps/kubernetes/api/model/PodsMetricSourceFluent;
      17: invokeinterface #77,  1           // InterfaceMethod io/dekorate/deps/kubernetes/api/model/PodsMetricSourceFluent.getTarget:()Lio/dekorate/deps/kubernetes/api/model/MetricTarget;
      22: invokespecial #80                 // Method io/dekorate/deps/kubernetes/api/model/PodsMetricSource."<init>":(Lio/dekorate/deps/kubernetes/api/model/MetricIdentifier;Lio/dekorate/deps/kubernetes/api/model/MetricTarget;)V
      25: astore_1
      26: aload_1
      27: areturn

  public boolean equals(java.lang.Object);
    Code:
       0: aload_0
       1: aload_1
       2: if_acmpne     7
       5: iconst_1
       6: ireturn
       7: aload_1
       8: ifnull        22
      11: aload_0
      12: invokevirtual #89                 // Method java/lang/Object.getClass:()Ljava/lang/Class;
      15: aload_1
      16: invokevirtual #89                 // Method java/lang/Object.getClass:()Ljava/lang/Class;
      19: if_acmpeq     24
      22: iconst_0
      23: ireturn
      24: aload_0
      25: aload_1
      26: invokespecial #91                 // Method io/dekorate/deps/kubernetes/api/model/PodsMetricSourceFluentImpl.equals:(Ljava/lang/Object;)Z
      29: ifne          34
      32: iconst_0
      33: ireturn
      34: aload_1
      35: checkcast     #2                  // class io/dekorate/deps/kubernetes/api/model/PodsMetricSourceBuilder
      38: astore_2
      39: aload_0
      40: getfield      #50                 // Field fluent:Lio/dekorate/deps/kubernetes/api/model/PodsMetricSourceFluent;
      43: ifnull        71
      46: aload_0
      47: getfield      #50                 // Field fluent:Lio/dekorate/deps/kubernetes/api/model/PodsMetricSourceFluent;
      50: aload_0
      51: if_acmpeq     71
      54: aload_0
      55: getfield      #50                 // Field fluent:Lio/dekorate/deps/kubernetes/api/model/PodsMetricSourceFluent;
      58: aload_2
      59: getfield      #50                 // Field fluent:Lio/dekorate/deps/kubernetes/api/model/PodsMetricSourceFluent;
      62: invokevirtual #92                 // Method java/lang/Object.equals:(Ljava/lang/Object;)Z
      65: ifne          88
      68: goto          86
      71: aload_2
      72: getfield      #50                 // Field fluent:Lio/dekorate/deps/kubernetes/api/model/PodsMetricSourceFluent;
      75: ifnull        88
      78: aload_0
      79: getfield      #50                 // Field fluent:Lio/dekorate/deps/kubernetes/api/model/PodsMetricSourceFluent;
      82: aload_0
      83: if_acmpeq     88
      86: iconst_0
      87: ireturn
      88: aload_0
      89: getfield      #70                 // Field validationEnabled:Ljava/lang/Boolean;
      92: ifnull        112
      95: aload_0
      96: getfield      #70                 // Field validationEnabled:Ljava/lang/Boolean;
      99: aload_2
     100: getfield      #70                 // Field validationEnabled:Ljava/lang/Boolean;
     103: invokevirtual #93                 // Method java/lang/Boolean.equals:(Ljava/lang/Object;)Z
     106: ifne          121
     109: goto          119
     112: aload_2
     113: getfield      #70                 // Field validationEnabled:Ljava/lang/Boolean;
     116: ifnull        121
     119: iconst_0
     120: ireturn
     121: iconst_1
     122: ireturn

  public java.lang.Object build();
    Code:
       0: aload_0
       1: invokevirtual #99                 // Method build:()Lio/dekorate/deps/kubernetes/api/model/PodsMetricSource;
       4: areturn
}
