Compiled from "VolumeFluentImpl.java"
public class io.dekorate.deps.kubernetes.api.model.VolumeFluentImpl$PersistentVolumeClaimNestedImpl<N> extends io.dekorate.deps.kubernetes.api.model.PersistentVolumeClaimVolumeSourceFluentImpl<io.dekorate.deps.kubernetes.api.model.VolumeFluent$PersistentVolumeClaimNested<N>> implements io.dekorate.deps.kubernetes.api.model.VolumeFluent$PersistentVolumeClaimNested<N>, io.dekorate.deps.kubernetes.api.builder.Nested<N> {
  private final io.dekorate.deps.kubernetes.api.model.PersistentVolumeClaimVolumeSourceBuilder builder;

  final io.dekorate.deps.kubernetes.api.model.VolumeFluentImpl this$0;

  io.dekorate.deps.kubernetes.api.model.VolumeFluentImpl$PersistentVolumeClaimNestedImpl(io.dekorate.deps.kubernetes.api.model.VolumeFluentImpl, io.dekorate.deps.kubernetes.api.model.PersistentVolumeClaimVolumeSource);
    Code:
       0: aload_0
       1: aload_1
       2: putfield      #24                 // Field this$0:Lio/dekorate/deps/kubernetes/api/model/VolumeFluentImpl;
       5: aload_0
       6: invokespecial #27                 // Method io/dekorate/deps/kubernetes/api/model/PersistentVolumeClaimVolumeSourceFluentImpl."<init>":()V
       9: aload_0
      10: new           #29                 // class io/dekorate/deps/kubernetes/api/model/PersistentVolumeClaimVolumeSourceBuilder
      13: dup
      14: aload_0
      15: aload_2
      16: invokespecial #32                 // Method io/dekorate/deps/kubernetes/api/model/PersistentVolumeClaimVolumeSourceBuilder."<init>":(Lio/dekorate/deps/kubernetes/api/model/PersistentVolumeClaimVolumeSourceFluent;Lio/dekorate/deps/kubernetes/api/model/PersistentVolumeClaimVolumeSource;)V
      19: putfield      #34                 // Field builder:Lio/dekorate/deps/kubernetes/api/model/PersistentVolumeClaimVolumeSourceBuilder;
      22: return

  io.dekorate.deps.kubernetes.api.model.VolumeFluentImpl$PersistentVolumeClaimNestedImpl(io.dekorate.deps.kubernetes.api.model.VolumeFluentImpl);
    Code:
       0: aload_0
       1: aload_1
       2: putfield      #24                 // Field this$0:Lio/dekorate/deps/kubernetes/api/model/VolumeFluentImpl;
       5: aload_0
       6: invokespecial #27                 // Method io/dekorate/deps/kubernetes/api/model/PersistentVolumeClaimVolumeSourceFluentImpl."<init>":()V
       9: aload_0
      10: new           #29                 // class io/dekorate/deps/kubernetes/api/model/PersistentVolumeClaimVolumeSourceBuilder
      13: dup
      14: aload_0
      15: invokespecial #43                 // Method io/dekorate/deps/kubernetes/api/model/PersistentVolumeClaimVolumeSourceBuilder."<init>":(Lio/dekorate/deps/kubernetes/api/model/PersistentVolumeClaimVolumeSourceFluent;)V
      18: putfield      #34                 // Field builder:Lio/dekorate/deps/kubernetes/api/model/PersistentVolumeClaimVolumeSourceBuilder;
      21: return

  public N and();
    Code:
       0: aload_0
       1: getfield      #24                 // Field this$0:Lio/dekorate/deps/kubernetes/api/model/VolumeFluentImpl;
       4: aload_0
       5: getfield      #34                 // Field builder:Lio/dekorate/deps/kubernetes/api/model/PersistentVolumeClaimVolumeSourceBuilder;
       8: invokevirtual #50                 // Method io/dekorate/deps/kubernetes/api/model/PersistentVolumeClaimVolumeSourceBuilder.build:()Lio/dekorate/deps/kubernetes/api/model/PersistentVolumeClaimVolumeSource;
      11: invokevirtual #54                 // Method io/dekorate/deps/kubernetes/api/model/VolumeFluentImpl.withPersistentVolumeClaim:(Lio/dekorate/deps/kubernetes/api/model/PersistentVolumeClaimVolumeSource;)Lio/dekorate/deps/kubernetes/api/model/VolumeFluent;
      14: areturn

  public N endPersistentVolumeClaim();
    Code:
       0: aload_0
       1: invokevirtual #57                 // Method and:()Ljava/lang/Object;
       4: areturn
}
