Compiled from "VolumeFluentImpl.java"
public class io.dekorate.deps.kubernetes.api.model.VolumeFluentImpl$AwsElasticBlockStoreNestedImpl<N> extends io.dekorate.deps.kubernetes.api.model.AWSElasticBlockStoreVolumeSourceFluentImpl<io.dekorate.deps.kubernetes.api.model.VolumeFluent$AwsElasticBlockStoreNested<N>> implements io.dekorate.deps.kubernetes.api.model.VolumeFluent$AwsElasticBlockStoreNested<N>, io.dekorate.deps.kubernetes.api.builder.Nested<N> {
  private final io.dekorate.deps.kubernetes.api.model.AWSElasticBlockStoreVolumeSourceBuilder builder;

  final io.dekorate.deps.kubernetes.api.model.VolumeFluentImpl this$0;

  io.dekorate.deps.kubernetes.api.model.VolumeFluentImpl$AwsElasticBlockStoreNestedImpl(io.dekorate.deps.kubernetes.api.model.VolumeFluentImpl, io.dekorate.deps.kubernetes.api.model.AWSElasticBlockStoreVolumeSource);
    Code:
       0: aload_0
       1: aload_1
       2: putfield      #24                 // Field this$0:Lio/dekorate/deps/kubernetes/api/model/VolumeFluentImpl;
       5: aload_0
       6: invokespecial #27                 // Method io/dekorate/deps/kubernetes/api/model/AWSElasticBlockStoreVolumeSourceFluentImpl."<init>":()V
       9: aload_0
      10: new           #29                 // class io/dekorate/deps/kubernetes/api/model/AWSElasticBlockStoreVolumeSourceBuilder
      13: dup
      14: aload_0
      15: aload_2
      16: invokespecial #32                 // Method io/dekorate/deps/kubernetes/api/model/AWSElasticBlockStoreVolumeSourceBuilder."<init>":(Lio/dekorate/deps/kubernetes/api/model/AWSElasticBlockStoreVolumeSourceFluent;Lio/dekorate/deps/kubernetes/api/model/AWSElasticBlockStoreVolumeSource;)V
      19: putfield      #34                 // Field builder:Lio/dekorate/deps/kubernetes/api/model/AWSElasticBlockStoreVolumeSourceBuilder;
      22: return

  io.dekorate.deps.kubernetes.api.model.VolumeFluentImpl$AwsElasticBlockStoreNestedImpl(io.dekorate.deps.kubernetes.api.model.VolumeFluentImpl);
    Code:
       0: aload_0
       1: aload_1
       2: putfield      #24                 // Field this$0:Lio/dekorate/deps/kubernetes/api/model/VolumeFluentImpl;
       5: aload_0
       6: invokespecial #27                 // Method io/dekorate/deps/kubernetes/api/model/AWSElasticBlockStoreVolumeSourceFluentImpl."<init>":()V
       9: aload_0
      10: new           #29                 // class io/dekorate/deps/kubernetes/api/model/AWSElasticBlockStoreVolumeSourceBuilder
      13: dup
      14: aload_0
      15: invokespecial #43                 // Method io/dekorate/deps/kubernetes/api/model/AWSElasticBlockStoreVolumeSourceBuilder."<init>":(Lio/dekorate/deps/kubernetes/api/model/AWSElasticBlockStoreVolumeSourceFluent;)V
      18: putfield      #34                 // Field builder:Lio/dekorate/deps/kubernetes/api/model/AWSElasticBlockStoreVolumeSourceBuilder;
      21: return

  public N and();
    Code:
       0: aload_0
       1: getfield      #24                 // Field this$0:Lio/dekorate/deps/kubernetes/api/model/VolumeFluentImpl;
       4: aload_0
       5: getfield      #34                 // Field builder:Lio/dekorate/deps/kubernetes/api/model/AWSElasticBlockStoreVolumeSourceBuilder;
       8: invokevirtual #50                 // Method io/dekorate/deps/kubernetes/api/model/AWSElasticBlockStoreVolumeSourceBuilder.build:()Lio/dekorate/deps/kubernetes/api/model/AWSElasticBlockStoreVolumeSource;
      11: invokevirtual #54                 // Method io/dekorate/deps/kubernetes/api/model/VolumeFluentImpl.withAwsElasticBlockStore:(Lio/dekorate/deps/kubernetes/api/model/AWSElasticBlockStoreVolumeSource;)Lio/dekorate/deps/kubernetes/api/model/VolumeFluent;
      14: areturn

  public N endAwsElasticBlockStore();
    Code:
       0: aload_0
       1: invokevirtual #57                 // Method and:()Ljava/lang/Object;
       4: areturn
}
