Compiled from "WatchEventFluentImpl.java"
public class io.dekorate.deps.kubernetes.api.model.WatchEventFluentImpl$TypeMetaObjectNestedImpl<N> extends io.dekorate.deps.kubernetes.api.model.TypeMetaFluentImpl<io.dekorate.deps.kubernetes.api.model.WatchEventFluent$TypeMetaObjectNested<N>> implements io.dekorate.deps.kubernetes.api.model.WatchEventFluent$TypeMetaObjectNested<N>, io.dekorate.deps.kubernetes.api.builder.Nested<N> {
  private final io.dekorate.deps.kubernetes.api.model.TypeMetaBuilder builder;

  final io.dekorate.deps.kubernetes.api.model.WatchEventFluentImpl this$0;

  io.dekorate.deps.kubernetes.api.model.WatchEventFluentImpl$TypeMetaObjectNestedImpl(io.dekorate.deps.kubernetes.api.model.WatchEventFluentImpl, io.dekorate.deps.kubernetes.api.model.TypeMeta);
    Code:
       0: aload_0
       1: aload_1
       2: putfield      #24                 // Field this$0:Lio/dekorate/deps/kubernetes/api/model/WatchEventFluentImpl;
       5: aload_0
       6: invokespecial #27                 // Method io/dekorate/deps/kubernetes/api/model/TypeMetaFluentImpl."<init>":()V
       9: aload_0
      10: new           #29                 // class io/dekorate/deps/kubernetes/api/model/TypeMetaBuilder
      13: dup
      14: aload_0
      15: aload_2
      16: invokespecial #32                 // Method io/dekorate/deps/kubernetes/api/model/TypeMetaBuilder."<init>":(Lio/dekorate/deps/kubernetes/api/model/TypeMetaFluent;Lio/dekorate/deps/kubernetes/api/model/TypeMeta;)V
      19: putfield      #34                 // Field builder:Lio/dekorate/deps/kubernetes/api/model/TypeMetaBuilder;
      22: return

  io.dekorate.deps.kubernetes.api.model.WatchEventFluentImpl$TypeMetaObjectNestedImpl(io.dekorate.deps.kubernetes.api.model.WatchEventFluentImpl);
    Code:
       0: aload_0
       1: aload_1
       2: putfield      #24                 // Field this$0:Lio/dekorate/deps/kubernetes/api/model/WatchEventFluentImpl;
       5: aload_0
       6: invokespecial #27                 // Method io/dekorate/deps/kubernetes/api/model/TypeMetaFluentImpl."<init>":()V
       9: aload_0
      10: new           #29                 // class io/dekorate/deps/kubernetes/api/model/TypeMetaBuilder
      13: dup
      14: aload_0
      15: invokespecial #43                 // Method io/dekorate/deps/kubernetes/api/model/TypeMetaBuilder."<init>":(Lio/dekorate/deps/kubernetes/api/model/TypeMetaFluent;)V
      18: putfield      #34                 // Field builder:Lio/dekorate/deps/kubernetes/api/model/TypeMetaBuilder;
      21: return

  public N and();
    Code:
       0: aload_0
       1: getfield      #24                 // Field this$0:Lio/dekorate/deps/kubernetes/api/model/WatchEventFluentImpl;
       4: aload_0
       5: getfield      #34                 // Field builder:Lio/dekorate/deps/kubernetes/api/model/TypeMetaBuilder;
       8: invokevirtual #50                 // Method io/dekorate/deps/kubernetes/api/model/TypeMetaBuilder.build:()Lio/dekorate/deps/kubernetes/api/model/TypeMeta;
      11: invokevirtual #54                 // Method io/dekorate/deps/kubernetes/api/model/WatchEventFluentImpl.withObject:(Lio/dekorate/deps/kubernetes/api/model/KubernetesResource;)Lio/dekorate/deps/kubernetes/api/model/WatchEventFluent;
      14: areturn

  public N endTypeMetaObject();
    Code:
       0: aload_0
       1: invokevirtual #57                 // Method and:()Ljava/lang/Object;
       4: areturn
}
