Compiled from "WatchEventFluentImpl.java"
public class io.dekorate.deps.kubernetes.api.model.WatchEventFluentImpl$ReplicationControllerConditionObjectNestedImpl<N> extends io.dekorate.deps.kubernetes.api.model.ReplicationControllerConditionFluentImpl<io.dekorate.deps.kubernetes.api.model.WatchEventFluent$ReplicationControllerConditionObjectNested<N>> implements io.dekorate.deps.kubernetes.api.model.WatchEventFluent$ReplicationControllerConditionObjectNested<N>, io.dekorate.deps.kubernetes.api.builder.Nested<N> {
  private final io.dekorate.deps.kubernetes.api.model.ReplicationControllerConditionBuilder builder;

  final io.dekorate.deps.kubernetes.api.model.WatchEventFluentImpl this$0;

  io.dekorate.deps.kubernetes.api.model.WatchEventFluentImpl$ReplicationControllerConditionObjectNestedImpl(io.dekorate.deps.kubernetes.api.model.WatchEventFluentImpl, io.dekorate.deps.kubernetes.api.model.ReplicationControllerCondition);
    Code:
       0: aload_0
       1: aload_1
       2: putfield      #24                 // Field this$0:Lio/dekorate/deps/kubernetes/api/model/WatchEventFluentImpl;
       5: aload_0
       6: invokespecial #27                 // Method io/dekorate/deps/kubernetes/api/model/ReplicationControllerConditionFluentImpl."<init>":()V
       9: aload_0
      10: new           #29                 // class io/dekorate/deps/kubernetes/api/model/ReplicationControllerConditionBuilder
      13: dup
      14: aload_0
      15: aload_2
      16: invokespecial #32                 // Method io/dekorate/deps/kubernetes/api/model/ReplicationControllerConditionBuilder."<init>":(Lio/dekorate/deps/kubernetes/api/model/ReplicationControllerConditionFluent;Lio/dekorate/deps/kubernetes/api/model/ReplicationControllerCondition;)V
      19: putfield      #34                 // Field builder:Lio/dekorate/deps/kubernetes/api/model/ReplicationControllerConditionBuilder;
      22: return

  io.dekorate.deps.kubernetes.api.model.WatchEventFluentImpl$ReplicationControllerConditionObjectNestedImpl(io.dekorate.deps.kubernetes.api.model.WatchEventFluentImpl);
    Code:
       0: aload_0
       1: aload_1
       2: putfield      #24                 // Field this$0:Lio/dekorate/deps/kubernetes/api/model/WatchEventFluentImpl;
       5: aload_0
       6: invokespecial #27                 // Method io/dekorate/deps/kubernetes/api/model/ReplicationControllerConditionFluentImpl."<init>":()V
       9: aload_0
      10: new           #29                 // class io/dekorate/deps/kubernetes/api/model/ReplicationControllerConditionBuilder
      13: dup
      14: aload_0
      15: invokespecial #43                 // Method io/dekorate/deps/kubernetes/api/model/ReplicationControllerConditionBuilder."<init>":(Lio/dekorate/deps/kubernetes/api/model/ReplicationControllerConditionFluent;)V
      18: putfield      #34                 // Field builder:Lio/dekorate/deps/kubernetes/api/model/ReplicationControllerConditionBuilder;
      21: return

  public N and();
    Code:
       0: aload_0
       1: getfield      #24                 // Field this$0:Lio/dekorate/deps/kubernetes/api/model/WatchEventFluentImpl;
       4: aload_0
       5: getfield      #34                 // Field builder:Lio/dekorate/deps/kubernetes/api/model/ReplicationControllerConditionBuilder;
       8: invokevirtual #50                 // Method io/dekorate/deps/kubernetes/api/model/ReplicationControllerConditionBuilder.build:()Lio/dekorate/deps/kubernetes/api/model/ReplicationControllerCondition;
      11: invokevirtual #54                 // Method io/dekorate/deps/kubernetes/api/model/WatchEventFluentImpl.withObject:(Lio/dekorate/deps/kubernetes/api/model/KubernetesResource;)Lio/dekorate/deps/kubernetes/api/model/WatchEventFluent;
      14: areturn

  public N endReplicationControllerConditionObject();
    Code:
       0: aload_0
       1: invokevirtual #57                 // Method and:()Ljava/lang/Object;
       4: areturn
}
