Compiled from "JavaFormatterTask.java"
public class org.hibernate.tool.ant.JavaFormatterTask extends org.apache.tools.ant.Task {
  private java.util.List fileSets;

  private boolean failOnError;

  private java.io.File configurationFile;

  public org.hibernate.tool.ant.JavaFormatterTask();
    Code:
       0: aload_0
       1: invokespecial #1                  // Method org/apache/tools/ant/Task."<init>":()V
       4: aload_0
       5: new           #2                  // class java/util/ArrayList
       8: dup
       9: invokespecial #3                  // Method java/util/ArrayList."<init>":()V
      12: putfield      #4                  // Field fileSets:Ljava/util/List;
      15: return

  public void addConfiguredFileSet(org.apache.tools.ant.types.FileSet);
    Code:
       0: aload_0
       1: getfield      #4                  // Field fileSets:Ljava/util/List;
       4: aload_1
       5: invokeinterface #5,  2            // InterfaceMethod java/util/List.add:(Ljava/lang/Object;)Z
      10: pop
      11: return

  public void setConfigurationFile(java.io.File);
    Code:
       0: aload_0
       1: aload_1
       2: putfield      #6                  // Field configurationFile:Ljava/io/File;
       5: return

  private java.util.Properties readConfig(java.io.File) throws java.io.IOException;
    Code:
       0: aconst_null
       1: astore_2
       2: new           #7                  // class java/io/BufferedInputStream
       5: dup
       6: new           #8                  // class java/io/FileInputStream
       9: dup
      10: aload_1
      11: invokespecial #9                  // Method java/io/FileInputStream."<init>":(Ljava/io/File;)V
      14: invokespecial #10                 // Method java/io/BufferedInputStream."<init>":(Ljava/io/InputStream;)V
      17: astore_2
      18: new           #11                 // class java/util/Properties
      21: dup
      22: invokespecial #12                 // Method java/util/Properties."<init>":()V
      25: astore_3
      26: aload_3
      27: aload_2
      28: invokevirtual #13                 // Method java/util/Properties.load:(Ljava/io/InputStream;)V
      31: aload_3
      32: astore        4
      34: aload_2
      35: ifnull        47
      38: aload_2
      39: invokevirtual #14                 // Method java/io/BufferedInputStream.close:()V
      42: goto          47
      45: astore        5
      47: aload         4
      49: areturn
      50: astore_3
      51: aload_3
      52: athrow
      53: astore        6
      55: aload_2
      56: ifnull        68
      59: aload_2
      60: invokevirtual #14                 // Method java/io/BufferedInputStream.close:()V
      63: goto          68
      66: astore        7
      68: aload         6
      70: athrow
    Exception table:
       from    to  target type
          38    42    45   Class java/io/IOException
           2    34    50   Class java/io/IOException
           2    34    53   any
          59    63    66   Class java/io/IOException
          50    55    53   any

  public void execute() throws org.apache.tools.ant.BuildException;
    Code:
       0: aconst_null
       1: astore_1
       2: aload_0
       3: getfield      #6                  // Field configurationFile:Ljava/io/File;
       6: ifnull        53
       9: aload_0
      10: aload_0
      11: getfield      #6                  // Field configurationFile:Ljava/io/File;
      14: invokespecial #16                 // Method readConfig:(Ljava/io/File;)Ljava/util/Properties;
      17: astore_1
      18: goto          53
      21: astore_2
      22: new           #17                 // class org/apache/tools/ant/BuildException
      25: dup
      26: new           #18                 // class java/lang/StringBuffer
      29: dup
      30: invokespecial #19                 // Method java/lang/StringBuffer."<init>":()V
      33: ldc           #20                 // String Could not read configurationfile
      35: invokevirtual #21                 // Method java/lang/StringBuffer.append:(Ljava/lang/String;)Ljava/lang/StringBuffer;
      38: aload_0
      39: getfield      #6                  // Field configurationFile:Ljava/io/File;
      42: invokevirtual #22                 // Method java/lang/StringBuffer.append:(Ljava/lang/Object;)Ljava/lang/StringBuffer;
      45: invokevirtual #23                 // Method java/lang/StringBuffer.toString:()Ljava/lang/String;
      48: aload_2
      49: invokespecial #24                 // Method org/apache/tools/ant/BuildException."<init>":(Ljava/lang/String;Ljava/lang/Throwable;)V
      52: athrow
      53: aload_0
      54: invokespecial #25                 // Method getFiles:()[Ljava/io/File;
      57: astore_2
      58: iconst_0
      59: istore_3
      60: iconst_0
      61: istore        4
      63: aload_2
      64: arraylength
      65: ifle          268
      68: new           #26                 // class org/hibernate/tool/ide/formatting/JavaFormatter
      71: dup
      72: aload_1
      73: invokespecial #27                 // Method org/hibernate/tool/ide/formatting/JavaFormatter."<init>":(Ljava/util/Map;)V
      76: astore        5
      78: iconst_0
      79: istore        6
      81: iload         6
      83: aload_2
      84: arraylength
      85: if_icmpge     268
      88: aload_2
      89: iload         6
      91: aaload
      92: astore        7
      94: aload         5
      96: aload         7
      98: invokevirtual #28                 // Method org/hibernate/tool/ide/formatting/JavaFormatter.formatFile:(Ljava/io/File;)Z
     101: istore        8
     103: iload         8
     105: ifne          143
     108: iinc          4, 1
     111: aload_0
     112: invokevirtual #29                 // Method getProject:()Lorg/apache/tools/ant/Project;
     115: aload_0
     116: new           #18                 // class java/lang/StringBuffer
     119: dup
     120: invokespecial #19                 // Method java/lang/StringBuffer."<init>":()V
     123: ldc           #30                 // String Formatting failed - skipping
     125: invokevirtual #21                 // Method java/lang/StringBuffer.append:(Ljava/lang/String;)Ljava/lang/StringBuffer;
     128: aload         7
     130: invokevirtual #22                 // Method java/lang/StringBuffer.append:(Ljava/lang/Object;)Ljava/lang/StringBuffer;
     133: invokevirtual #23                 // Method java/lang/StringBuffer.toString:()Ljava/lang/String;
     136: iconst_1
     137: invokevirtual #31                 // Method org/apache/tools/ant/Project.log:(Lorg/apache/tools/ant/Task;Ljava/lang/String;I)V
     140: goto          175
     143: iinc          3, 1
     146: aload_0
     147: invokevirtual #29                 // Method getProject:()Lorg/apache/tools/ant/Project;
     150: aload_0
     151: new           #18                 // class java/lang/StringBuffer
     154: dup
     155: invokespecial #19                 // Method java/lang/StringBuffer."<init>":()V
     158: ldc           #32                 // String Formatted
     160: invokevirtual #21                 // Method java/lang/StringBuffer.append:(Ljava/lang/String;)Ljava/lang/StringBuffer;
     163: aload         7
     165: invokevirtual #22                 // Method java/lang/StringBuffer.append:(Ljava/lang/Object;)Ljava/lang/StringBuffer;
     168: invokevirtual #23                 // Method java/lang/StringBuffer.toString:()Ljava/lang/String;
     171: iconst_3
     172: invokevirtual #31                 // Method org/apache/tools/ant/Project.log:(Lorg/apache/tools/ant/Task;Ljava/lang/String;I)V
     175: goto          262
     178: astore        8
     180: iinc          4, 1
     183: aload_0
     184: getfield      #34                 // Field failOnError:Z
     187: ifeq          220
     190: new           #17                 // class org/apache/tools/ant/BuildException
     193: dup
     194: new           #18                 // class java/lang/StringBuffer
     197: dup
     198: invokespecial #19                 // Method java/lang/StringBuffer."<init>":()V
     201: ldc           #35                 // String Java formatting failed on
     203: invokevirtual #21                 // Method java/lang/StringBuffer.append:(Ljava/lang/String;)Ljava/lang/StringBuffer;
     206: aload         7
     208: invokevirtual #22                 // Method java/lang/StringBuffer.append:(Ljava/lang/Object;)Ljava/lang/StringBuffer;
     211: invokevirtual #23                 // Method java/lang/StringBuffer.toString:()Ljava/lang/String;
     214: aload         8
     216: invokespecial #24                 // Method org/apache/tools/ant/BuildException."<init>":(Ljava/lang/String;Ljava/lang/Throwable;)V
     219: athrow
     220: aload_0
     221: invokevirtual #29                 // Method getProject:()Lorg/apache/tools/ant/Project;
     224: aload_0
     225: new           #18                 // class java/lang/StringBuffer
     228: dup
     229: invokespecial #19                 // Method java/lang/StringBuffer."<init>":()V
     232: ldc           #35                 // String Java formatting failed on
     234: invokevirtual #21                 // Method java/lang/StringBuffer.append:(Ljava/lang/String;)Ljava/lang/StringBuffer;
     237: aload         7
     239: invokevirtual #22                 // Method java/lang/StringBuffer.append:(Ljava/lang/Object;)Ljava/lang/StringBuffer;
     242: ldc           #36                 // String ,
     244: invokevirtual #21                 // Method java/lang/StringBuffer.append:(Ljava/lang/String;)Ljava/lang/StringBuffer;
     247: aload         8
     249: invokevirtual #37                 // Method org/hibernate/tool/hbm2x/ExporterException.getLocalizedMessage:()Ljava/lang/String;
     252: invokevirtual #21                 // Method java/lang/StringBuffer.append:(Ljava/lang/String;)Ljava/lang/StringBuffer;
     255: invokevirtual #23                 // Method java/lang/StringBuffer.toString:()Ljava/lang/String;
     258: iconst_0
     259: invokevirtual #31                 // Method org/apache/tools/ant/Project.log:(Lorg/apache/tools/ant/Task;Ljava/lang/String;I)V
     262: iinc          6, 1
     265: goto          81
     268: aload_0
     269: invokevirtual #29                 // Method getProject:()Lorg/apache/tools/ant/Project;
     272: aload_0
     273: new           #18                 // class java/lang/StringBuffer
     276: dup
     277: invokespecial #19                 // Method java/lang/StringBuffer."<init>":()V
     280: ldc           #38                 // String Java formatting of
     282: invokevirtual #21                 // Method java/lang/StringBuffer.append:(Ljava/lang/String;)Ljava/lang/StringBuffer;
     285: aload_2
     286: arraylength
     287: invokevirtual #39                 // Method java/lang/StringBuffer.append:(I)Ljava/lang/StringBuffer;
     290: ldc           #40                 // String  files completed. Skipped
     292: invokevirtual #21                 // Method java/lang/StringBuffer.append:(Ljava/lang/String;)Ljava/lang/StringBuffer;
     295: iload         4
     297: invokevirtual #39                 // Method java/lang/StringBuffer.append:(I)Ljava/lang/StringBuffer;
     300: ldc           #41                 // String  file(s).
     302: invokevirtual #21                 // Method java/lang/StringBuffer.append:(Ljava/lang/String;)Ljava/lang/StringBuffer;
     305: invokevirtual #23                 // Method java/lang/StringBuffer.toString:()Ljava/lang/String;
     308: iconst_2
     309: invokevirtual #31                 // Method org/apache/tools/ant/Project.log:(Lorg/apache/tools/ant/Task;Ljava/lang/String;I)V
     312: return
    Exception table:
       from    to  target type
           9    18    21   Class java/io/IOException
          94   175   178   Class org/hibernate/tool/hbm2x/ExporterException

  private java.io.File[] getFiles();
    Code:
       0: new           #42                 // class java/util/LinkedList
       3: dup
       4: invokespecial #43                 // Method java/util/LinkedList."<init>":()V
       7: astore_1
       8: aload_0
       9: getfield      #4                  // Field fileSets:Ljava/util/List;
      12: invokeinterface #44,  1           // InterfaceMethod java/util/List.iterator:()Ljava/util/Iterator;
      17: astore_2
      18: aload_2
      19: invokeinterface #45,  1           // InterfaceMethod java/util/Iterator.hasNext:()Z
      24: ifeq          124
      27: aload_2
      28: invokeinterface #46,  1           // InterfaceMethod java/util/Iterator.next:()Ljava/lang/Object;
      33: checkcast     #47                 // class org/apache/tools/ant/types/FileSet
      36: astore_3
      37: aload_3
      38: aload_0
      39: invokevirtual #29                 // Method getProject:()Lorg/apache/tools/ant/Project;
      42: invokevirtual #48                 // Method org/apache/tools/ant/types/FileSet.getDirectoryScanner:(Lorg/apache/tools/ant/Project;)Lorg/apache/tools/ant/DirectoryScanner;
      45: astore        4
      47: aload         4
      49: invokevirtual #49                 // Method org/apache/tools/ant/DirectoryScanner.getIncludedFiles:()[Ljava/lang/String;
      52: astore        5
      54: iconst_0
      55: istore        6
      57: iload         6
      59: aload         5
      61: arraylength
      62: if_icmpge     121
      65: new           #50                 // class java/io/File
      68: dup
      69: aload         5
      71: iload         6
      73: aaload
      74: invokespecial #51                 // Method java/io/File."<init>":(Ljava/lang/String;)V
      77: astore        7
      79: aload         7
      81: invokevirtual #52                 // Method java/io/File.isFile:()Z
      84: ifne          106
      87: new           #50                 // class java/io/File
      90: dup
      91: aload         4
      93: invokevirtual #53                 // Method org/apache/tools/ant/DirectoryScanner.getBasedir:()Ljava/io/File;
      96: aload         5
      98: iload         6
     100: aaload
     101: invokespecial #54                 // Method java/io/File."<init>":(Ljava/io/File;Ljava/lang/String;)V
     104: astore        7
     106: aload_1
     107: aload         7
     109: invokeinterface #5,  2            // InterfaceMethod java/util/List.add:(Ljava/lang/Object;)Z
     114: pop
     115: iinc          6, 1
     118: goto          57
     121: goto          18
     124: aload_1
     125: aload_1
     126: invokeinterface #55,  1           // InterfaceMethod java/util/List.size:()I
     131: anewarray     #50                 // class java/io/File
     134: invokeinterface #56,  2           // InterfaceMethod java/util/List.toArray:([Ljava/lang/Object;)[Ljava/lang/Object;
     139: checkcast     #57                 // class "[Ljava/io/File;"
     142: checkcast     #57                 // class "[Ljava/io/File;"
     145: areturn
}
