Compiled from "ConfigClientProperties.java"
public class org.springframework.cloud.config.client.ConfigClientProperties$Credentials {
  private java.lang.String username;

  private java.lang.String password;

  private java.lang.String uri;

  public org.springframework.cloud.config.client.ConfigClientProperties$Credentials();
    Code:
       0: aload_0
       1: invokespecial #4                  // Method java/lang/Object."<init>":()V
       4: return

  public java.lang.String getUsername();
    Code:
       0: aload_0
       1: getfield      #2                  // Field username:Ljava/lang/String;
       4: areturn

  public java.lang.String getPassword();
    Code:
       0: aload_0
       1: getfield      #1                  // Field password:Ljava/lang/String;
       4: areturn

  public java.lang.String getUri();
    Code:
       0: aload_0
       1: getfield      #3                  // Field uri:Ljava/lang/String;
       4: areturn

  static java.lang.String access$002(org.springframework.cloud.config.client.ConfigClientProperties$Credentials, java.lang.String);
    Code:
       0: aload_0
       1: aload_1
       2: dup_x1
       3: putfield      #3                  // Field uri:Ljava/lang/String;
       6: areturn

  static java.lang.String access$102(org.springframework.cloud.config.client.ConfigClientProperties$Credentials, java.lang.String);
    Code:
       0: aload_0
       1: aload_1
       2: dup_x1
       3: putfield      #2                  // Field username:Ljava/lang/String;
       6: areturn

  static java.lang.String access$100(org.springframework.cloud.config.client.ConfigClientProperties$Credentials);
    Code:
       0: aload_0
       1: getfield      #2                  // Field username:Ljava/lang/String;
       4: areturn

  static java.lang.String access$202(org.springframework.cloud.config.client.ConfigClientProperties$Credentials, java.lang.String);
    Code:
       0: aload_0
       1: aload_1
       2: dup_x1
       3: putfield      #1                  // Field password:Ljava/lang/String;
       6: areturn

  static java.lang.String access$200(org.springframework.cloud.config.client.ConfigClientProperties$Credentials);
    Code:
       0: aload_0
       1: getfield      #1                  // Field password:Ljava/lang/String;
       4: areturn
}
