Compiled from "ActiveMQIOErrorException.java"
public final class org.apache.activemq.artemis.api.core.ActiveMQIOErrorException extends org.apache.activemq.artemis.api.core.ActiveMQException {
  private static final long serialVersionUID;

  public org.apache.activemq.artemis.api.core.ActiveMQIOErrorException();
    Code:
       0: aload_0
       1: getstatic     #1                  // Field org/apache/activemq/artemis/api/core/ActiveMQExceptionType.IO_ERROR:Lorg/apache/activemq/artemis/api/core/ActiveMQExceptionType;
       4: invokespecial #2                  // Method org/apache/activemq/artemis/api/core/ActiveMQException."<init>":(Lorg/apache/activemq/artemis/api/core/ActiveMQExceptionType;)V
       7: return

  public org.apache.activemq.artemis.api.core.ActiveMQIOErrorException(java.lang.String);
    Code:
       0: aload_0
       1: getstatic     #1                  // Field org/apache/activemq/artemis/api/core/ActiveMQExceptionType.IO_ERROR:Lorg/apache/activemq/artemis/api/core/ActiveMQExceptionType;
       4: aload_1
       5: invokespecial #3                  // Method org/apache/activemq/artemis/api/core/ActiveMQException."<init>":(Lorg/apache/activemq/artemis/api/core/ActiveMQExceptionType;Ljava/lang/String;)V
       8: return

  public org.apache.activemq.artemis.api.core.ActiveMQIOErrorException(java.lang.String, java.lang.Throwable);
    Code:
       0: aload_0
       1: getstatic     #1                  // Field org/apache/activemq/artemis/api/core/ActiveMQExceptionType.IO_ERROR:Lorg/apache/activemq/artemis/api/core/ActiveMQExceptionType;
       4: aload_1
       5: aload_2
       6: invokespecial #4                  // Method org/apache/activemq/artemis/api/core/ActiveMQException."<init>":(Lorg/apache/activemq/artemis/api/core/ActiveMQExceptionType;Ljava/lang/String;Ljava/lang/Throwable;)V
       9: return
}
