Compiled from "DependencyDefinition.java"
public final class be.sysa.quartz.initializer.model.DependencyDefinition {
  private final java.lang.String name;

  private final org.quartz.JobKey childJob;

  private final int priority;

  private final int secondsDelay;

  private final be.sysa.quartz.initializer.model.ZonedTime notBefore;

  private final boolean parentErrorIgnored;

  private final java.util.Map<java.lang.String, java.lang.Object> jobDataMap;

  be.sysa.quartz.initializer.model.DependencyDefinition(java.lang.String, org.quartz.JobKey, int, int, be.sysa.quartz.initializer.model.ZonedTime, boolean, java.util.Map<java.lang.String, java.lang.Object>);
    Code:
       0: aload_0
       1: invokespecial #1                  // Method java/lang/Object."<init>":()V
       4: aload_0
       5: aload_1
       6: putfield      #7                  // Field name:Ljava/lang/String;
       9: aload_0
      10: aload_2
      11: putfield      #13                 // Field childJob:Lorg/quartz/JobKey;
      14: aload_0
      15: iload_3
      16: putfield      #17                 // Field priority:I
      19: aload_0
      20: iload         4
      22: putfield      #21                 // Field secondsDelay:I
      25: aload_0
      26: aload         5
      28: putfield      #24                 // Field notBefore:Lbe/sysa/quartz/initializer/model/ZonedTime;
      31: aload_0
      32: iload         6
      34: putfield      #28                 // Field parentErrorIgnored:Z
      37: aload_0
      38: aload         7
      40: putfield      #32                 // Field jobDataMap:Ljava/util/Map;
      43: return

  public static be.sysa.quartz.initializer.model.DependencyDefinition$DependencyDefinitionBuilder builder();
    Code:
       0: new           #36                 // class be/sysa/quartz/initializer/model/DependencyDefinition$DependencyDefinitionBuilder
       3: dup
       4: invokespecial #38                 // Method be/sysa/quartz/initializer/model/DependencyDefinition$DependencyDefinitionBuilder."<init>":()V
       7: areturn

  public be.sysa.quartz.initializer.model.DependencyDefinition$DependencyDefinitionBuilder toBuilder();
    Code:
       0: new           #36                 // class be/sysa/quartz/initializer/model/DependencyDefinition$DependencyDefinitionBuilder
       3: dup
       4: invokespecial #38                 // Method be/sysa/quartz/initializer/model/DependencyDefinition$DependencyDefinitionBuilder."<init>":()V
       7: aload_0
       8: getfield      #7                  // Field name:Ljava/lang/String;
      11: invokevirtual #39                 // Method be/sysa/quartz/initializer/model/DependencyDefinition$DependencyDefinitionBuilder.name:(Ljava/lang/String;)Lbe/sysa/quartz/initializer/model/DependencyDefinition$DependencyDefinitionBuilder;
      14: aload_0
      15: getfield      #13                 // Field childJob:Lorg/quartz/JobKey;
      18: invokevirtual #42                 // Method be/sysa/quartz/initializer/model/DependencyDefinition$DependencyDefinitionBuilder.childJob:(Lorg/quartz/JobKey;)Lbe/sysa/quartz/initializer/model/DependencyDefinition$DependencyDefinitionBuilder;
      21: aload_0
      22: getfield      #17                 // Field priority:I
      25: invokevirtual #45                 // Method be/sysa/quartz/initializer/model/DependencyDefinition$DependencyDefinitionBuilder.priority:(I)Lbe/sysa/quartz/initializer/model/DependencyDefinition$DependencyDefinitionBuilder;
      28: aload_0
      29: getfield      #21                 // Field secondsDelay:I
      32: invokevirtual #48                 // Method be/sysa/quartz/initializer/model/DependencyDefinition$DependencyDefinitionBuilder.secondsDelay:(I)Lbe/sysa/quartz/initializer/model/DependencyDefinition$DependencyDefinitionBuilder;
      35: aload_0
      36: getfield      #24                 // Field notBefore:Lbe/sysa/quartz/initializer/model/ZonedTime;
      39: invokevirtual #50                 // Method be/sysa/quartz/initializer/model/DependencyDefinition$DependencyDefinitionBuilder.notBefore:(Lbe/sysa/quartz/initializer/model/ZonedTime;)Lbe/sysa/quartz/initializer/model/DependencyDefinition$DependencyDefinitionBuilder;
      42: aload_0
      43: getfield      #28                 // Field parentErrorIgnored:Z
      46: invokevirtual #53                 // Method be/sysa/quartz/initializer/model/DependencyDefinition$DependencyDefinitionBuilder.parentErrorIgnored:(Z)Lbe/sysa/quartz/initializer/model/DependencyDefinition$DependencyDefinitionBuilder;
      49: aload_0
      50: getfield      #32                 // Field jobDataMap:Ljava/util/Map;
      53: invokevirtual #56                 // Method be/sysa/quartz/initializer/model/DependencyDefinition$DependencyDefinitionBuilder.jobDataMap:(Ljava/util/Map;)Lbe/sysa/quartz/initializer/model/DependencyDefinition$DependencyDefinitionBuilder;
      56: areturn

  public java.lang.String getName();
    Code:
       0: aload_0
       1: getfield      #7                  // Field name:Ljava/lang/String;
       4: areturn

  public org.quartz.JobKey getChildJob();
    Code:
       0: aload_0
       1: getfield      #13                 // Field childJob:Lorg/quartz/JobKey;
       4: areturn

  public int getPriority();
    Code:
       0: aload_0
       1: getfield      #17                 // Field priority:I
       4: ireturn

  public int getSecondsDelay();
    Code:
       0: aload_0
       1: getfield      #21                 // Field secondsDelay:I
       4: ireturn

  public be.sysa.quartz.initializer.model.ZonedTime getNotBefore();
    Code:
       0: aload_0
       1: getfield      #24                 // Field notBefore:Lbe/sysa/quartz/initializer/model/ZonedTime;
       4: areturn

  public boolean isParentErrorIgnored();
    Code:
       0: aload_0
       1: getfield      #28                 // Field parentErrorIgnored:Z
       4: ireturn

  public java.util.Map<java.lang.String, java.lang.Object> getJobDataMap();
    Code:
       0: aload_0
       1: getfield      #32                 // Field jobDataMap:Ljava/util/Map;
       4: areturn

  public boolean equals(java.lang.Object);
    Code:
       0: aload_1
       1: aload_0
       2: if_acmpne     7
       5: iconst_1
       6: ireturn
       7: aload_1
       8: instanceof    #8                  // class be/sysa/quartz/initializer/model/DependencyDefinition
      11: ifne          16
      14: iconst_0
      15: ireturn
      16: aload_1
      17: checkcast     #8                  // class be/sysa/quartz/initializer/model/DependencyDefinition
      20: astore_2
      21: aload_0
      22: invokevirtual #59                 // Method getPriority:()I
      25: aload_2
      26: invokevirtual #59                 // Method getPriority:()I
      29: if_icmpeq     34
      32: iconst_0
      33: ireturn
      34: aload_0
      35: invokevirtual #63                 // Method getSecondsDelay:()I
      38: aload_2
      39: invokevirtual #63                 // Method getSecondsDelay:()I
      42: if_icmpeq     47
      45: iconst_0
      46: ireturn
      47: aload_0
      48: invokevirtual #66                 // Method isParentErrorIgnored:()Z
      51: aload_2
      52: invokevirtual #66                 // Method isParentErrorIgnored:()Z
      55: if_icmpeq     60
      58: iconst_0
      59: ireturn
      60: aload_0
      61: invokevirtual #70                 // Method getName:()Ljava/lang/String;
      64: astore_3
      65: aload_2
      66: invokevirtual #70                 // Method getName:()Ljava/lang/String;
      69: astore        4
      71: aload_3
      72: ifnonnull     83
      75: aload         4
      77: ifnull        94
      80: goto          92
      83: aload_3
      84: aload         4
      86: invokevirtual #74                 // Method java/lang/Object.equals:(Ljava/lang/Object;)Z
      89: ifne          94
      92: iconst_0
      93: ireturn
      94: aload_0
      95: invokevirtual #78                 // Method getChildJob:()Lorg/quartz/JobKey;
      98: astore        5
     100: aload_2
     101: invokevirtual #78                 // Method getChildJob:()Lorg/quartz/JobKey;
     104: astore        6
     106: aload         5
     108: ifnonnull     119
     111: aload         6
     113: ifnull        131
     116: goto          129
     119: aload         5
     121: aload         6
     123: invokevirtual #74                 // Method java/lang/Object.equals:(Ljava/lang/Object;)Z
     126: ifne          131
     129: iconst_0
     130: ireturn
     131: aload_0
     132: invokevirtual #82                 // Method getNotBefore:()Lbe/sysa/quartz/initializer/model/ZonedTime;
     135: astore        7
     137: aload_2
     138: invokevirtual #82                 // Method getNotBefore:()Lbe/sysa/quartz/initializer/model/ZonedTime;
     141: astore        8
     143: aload         7
     145: ifnonnull     156
     148: aload         8
     150: ifnull        168
     153: goto          166
     156: aload         7
     158: aload         8
     160: invokevirtual #74                 // Method java/lang/Object.equals:(Ljava/lang/Object;)Z
     163: ifne          168
     166: iconst_0
     167: ireturn
     168: aload_0
     169: invokevirtual #86                 // Method getJobDataMap:()Ljava/util/Map;
     172: astore        9
     174: aload_2
     175: invokevirtual #86                 // Method getJobDataMap:()Ljava/util/Map;
     178: astore        10
     180: aload         9
     182: ifnonnull     193
     185: aload         10
     187: ifnull        205
     190: goto          203
     193: aload         9
     195: aload         10
     197: invokevirtual #74                 // Method java/lang/Object.equals:(Ljava/lang/Object;)Z
     200: ifne          205
     203: iconst_0
     204: ireturn
     205: iconst_1
     206: ireturn

  public int hashCode();
    Code:
       0: bipush        59
       2: istore_1
       3: iconst_1
       4: istore_2
       5: iload_2
       6: bipush        59
       8: imul
       9: aload_0
      10: invokevirtual #59                 // Method getPriority:()I
      13: iadd
      14: istore_2
      15: iload_2
      16: bipush        59
      18: imul
      19: aload_0
      20: invokevirtual #63                 // Method getSecondsDelay:()I
      23: iadd
      24: istore_2
      25: iload_2
      26: bipush        59
      28: imul
      29: aload_0
      30: invokevirtual #66                 // Method isParentErrorIgnored:()Z
      33: ifeq          41
      36: bipush        79
      38: goto          43
      41: bipush        97
      43: iadd
      44: istore_2
      45: aload_0
      46: invokevirtual #70                 // Method getName:()Ljava/lang/String;
      49: astore_3
      50: iload_2
      51: bipush        59
      53: imul
      54: aload_3
      55: ifnonnull     63
      58: bipush        43
      60: goto          67
      63: aload_3
      64: invokevirtual #90                 // Method java/lang/Object.hashCode:()I
      67: iadd
      68: istore_2
      69: aload_0
      70: invokevirtual #78                 // Method getChildJob:()Lorg/quartz/JobKey;
      73: astore        4
      75: iload_2
      76: bipush        59
      78: imul
      79: aload         4
      81: ifnonnull     89
      84: bipush        43
      86: goto          94
      89: aload         4
      91: invokevirtual #90                 // Method java/lang/Object.hashCode:()I
      94: iadd
      95: istore_2
      96: aload_0
      97: invokevirtual #82                 // Method getNotBefore:()Lbe/sysa/quartz/initializer/model/ZonedTime;
     100: astore        5
     102: iload_2
     103: bipush        59
     105: imul
     106: aload         5
     108: ifnonnull     116
     111: bipush        43
     113: goto          121
     116: aload         5
     118: invokevirtual #90                 // Method java/lang/Object.hashCode:()I
     121: iadd
     122: istore_2
     123: aload_0
     124: invokevirtual #86                 // Method getJobDataMap:()Ljava/util/Map;
     127: astore        6
     129: iload_2
     130: bipush        59
     132: imul
     133: aload         6
     135: ifnonnull     143
     138: bipush        43
     140: goto          148
     143: aload         6
     145: invokevirtual #90                 // Method java/lang/Object.hashCode:()I
     148: iadd
     149: istore_2
     150: iload_2
     151: ireturn

  public java.lang.String toString();
    Code:
       0: aload_0
       1: invokevirtual #70                 // Method getName:()Ljava/lang/String;
       4: aload_0
       5: invokevirtual #78                 // Method getChildJob:()Lorg/quartz/JobKey;
       8: aload_0
       9: invokevirtual #59                 // Method getPriority:()I
      12: aload_0
      13: invokevirtual #63                 // Method getSecondsDelay:()I
      16: aload_0
      17: invokevirtual #82                 // Method getNotBefore:()Lbe/sysa/quartz/initializer/model/ZonedTime;
      20: aload_0
      21: invokevirtual #66                 // Method isParentErrorIgnored:()Z
      24: aload_0
      25: invokevirtual #86                 // Method getJobDataMap:()Ljava/util/Map;
      28: invokedynamic #93,  0             // InvokeDynamic #0:makeConcatWithConstants:(Ljava/lang/String;Lorg/quartz/JobKey;IILbe/sysa/quartz/initializer/model/ZonedTime;ZLjava/util/Map;)Ljava/lang/String;
      33: areturn
}
