Compiled from "AbstractCallableInjectionPoint.java"
abstract class org.jboss.weld.injection.AbstractCallableInjectionPoint<T, X, S extends java.lang.reflect.Member> implements org.jboss.weld.injection.attributes.WeldInjectionPointAttributes<T, S> {
  private final javax.enterprise.inject.spi.Bean<?> declaringBean;

  private final java.util.List<org.jboss.weld.injection.ParameterInjectionPoint<?, X>> parameters;

  private final java.util.Set<javax.enterprise.inject.spi.InjectionPoint> injectionPoints;

  protected final boolean hasTransientReferenceParameter;

  protected org.jboss.weld.injection.AbstractCallableInjectionPoint(org.jboss.weld.annotated.enhanced.EnhancedAnnotatedCallable<T, X, S>, javax.enterprise.inject.spi.Bean<?>, java.lang.Class<?>, boolean, org.jboss.weld.injection.InjectionPointFactory, org.jboss.weld.manager.BeanManagerImpl);
    Code:
       0: aload_0
       1: invokespecial #1                  // Method java/lang/Object."<init>":()V
       4: aload_0
       5: aload_2
       6: putfield      #2                  // Field declaringBean:Ljavax/enterprise/inject/spi/Bean;
       9: aload_0
      10: aload         5
      12: aload_1
      13: aload_2
      14: aload_3
      15: aload         6
      17: iload         4
      19: invokevirtual #3                  // Method org/jboss/weld/injection/InjectionPointFactory.getParameterInjectionPoints:(Lorg/jboss/weld/annotated/enhanced/EnhancedAnnotatedCallable;Ljavax/enterprise/inject/spi/Bean;Ljava/lang/Class;Lorg/jboss/weld/manager/BeanManagerImpl;Z)Ljava/util/List;
      22: putfield      #4                  // Field parameters:Ljava/util/List;
      25: iload         4
      27: ifeq          53
      30: aload_0
      31: aload_0
      32: getfield      #4                  // Field parameters:Ljava/util/List;
      35: invokestatic  #5                  // Method org/jboss/weld/util/InjectionPoints.filterOutSpecialParameterInjectionPoints:(Ljava/util/List;)Ljava/util/Set;
      38: invokestatic  #6                  // Method org/jboss/weld/util/collections/WeldCollections.immutableGuavaSet:(Ljava/util/Set;)Ljava/util/Set;
      41: invokestatic  #7                  // Method org/jboss/weld/util/reflection/Reflections.cast:(Ljava/lang/Object;)Ljava/lang/Object;
      44: checkcast     #8                  // class java/util/Set
      47: putfield      #9                  // Field injectionPoints:Ljava/util/Set;
      50: goto          65
      53: aload_0
      54: new           #10                 // class org/jboss/weld/injection/AbstractCallableInjectionPoint$1
      57: dup
      58: aload_0
      59: invokespecial #11                 // Method org/jboss/weld/injection/AbstractCallableInjectionPoint$1."<init>":(Lorg/jboss/weld/injection/AbstractCallableInjectionPoint;)V
      62: putfield      #9                  // Field injectionPoints:Ljava/util/Set;
      65: aload_0
      66: aload_1
      67: invokeinterface #12,  1           // InterfaceMethod org/jboss/weld/annotated/enhanced/EnhancedAnnotatedCallable.getEnhancedParameters:()Ljava/util/List;
      72: invokestatic  #13                 // Method initHasTransientReference:(Ljava/util/List;)Z
      75: putfield      #14                 // Field hasTransientReferenceParameter:Z
      78: return

  private static boolean initHasTransientReference(java.util.List<? extends org.jboss.weld.annotated.enhanced.EnhancedAnnotatedParameter<?, ?>>);
    Code:
       0: aload_0
       1: invokeinterface #15,  1           // InterfaceMethod java/util/List.iterator:()Ljava/util/Iterator;
       6: astore_1
       7: aload_1
       8: invokeinterface #16,  1           // InterfaceMethod java/util/Iterator.hasNext:()Z
      13: ifeq          42
      16: aload_1
      17: invokeinterface #17,  1           // InterfaceMethod java/util/Iterator.next:()Ljava/lang/Object;
      22: checkcast     #18                 // class org/jboss/weld/annotated/enhanced/EnhancedAnnotatedParameter
      25: astore_2
      26: aload_2
      27: ldc           #19                 // class javax/enterprise/inject/TransientReference
      29: invokeinterface #20,  2           // InterfaceMethod org/jboss/weld/annotated/enhanced/EnhancedAnnotatedParameter.isAnnotationPresent:(Ljava/lang/Class;)Z
      34: ifeq          39
      37: iconst_1
      38: ireturn
      39: goto          7
      42: iconst_0
      43: ireturn

  public java.lang.reflect.Type getType();
    Code:
       0: aload_0
       1: invokevirtual #21                 // Method getAnnotated:()Ljavax/enterprise/inject/spi/AnnotatedCallable;
       4: invokeinterface #22,  1           // InterfaceMethod javax/enterprise/inject/spi/AnnotatedCallable.getBaseType:()Ljava/lang/reflect/Type;
       9: areturn

  public java.util.Set<java.lang.annotation.Annotation> getQualifiers();
    Code:
       0: new           #23                 // class org/jboss/weld/exceptions/UnsupportedOperationException
       3: dup
       4: invokespecial #24                 // Method org/jboss/weld/exceptions/UnsupportedOperationException."<init>":()V
       7: athrow

  public javax.enterprise.inject.spi.Bean<?> getBean();
    Code:
       0: aload_0
       1: getfield      #2                  // Field declaringBean:Ljavax/enterprise/inject/spi/Bean;
       4: areturn

  public boolean isDelegate();
    Code:
       0: iconst_0
       1: ireturn

  public boolean isTransient();
    Code:
       0: iconst_0
       1: ireturn

  public <A extends java.lang.annotation.Annotation> A getQualifier(java.lang.Class<A>);
    Code:
       0: aload_0
       1: invokevirtual #21                 // Method getAnnotated:()Ljavax/enterprise/inject/spi/AnnotatedCallable;
       4: aload_1
       5: invokeinterface #25,  2           // InterfaceMethod javax/enterprise/inject/spi/AnnotatedCallable.getAnnotation:(Ljava/lang/Class;)Ljava/lang/annotation/Annotation;
      10: astore_2
      11: aload_0
      12: invokevirtual #26                 // Method getQualifiers:()Ljava/util/Set;
      15: aload_2
      16: invokeinterface #27,  2           // InterfaceMethod java/util/Set.contains:(Ljava/lang/Object;)Z
      21: ifeq          26
      24: aload_2
      25: areturn
      26: aconst_null
      27: areturn

  public java.lang.reflect.Member getMember();
    Code:
       0: aload_0
       1: invokevirtual #21                 // Method getAnnotated:()Ljavax/enterprise/inject/spi/AnnotatedCallable;
       4: invokeinterface #28,  1           // InterfaceMethod javax/enterprise/inject/spi/AnnotatedCallable.getJavaMember:()Ljava/lang/reflect/Member;
       9: areturn

  public abstract javax.enterprise.inject.spi.AnnotatedCallable<X> getAnnotated();

  public java.util.List<org.jboss.weld.injection.ParameterInjectionPoint<?, X>> getParameterInjectionPoints();
    Code:
       0: aload_0
       1: getfield      #4                  // Field parameters:Ljava/util/List;
       4: areturn

  public java.util.Set<javax.enterprise.inject.spi.InjectionPoint> getInjectionPoints();
    Code:
       0: aload_0
       1: getfield      #9                  // Field injectionPoints:Ljava/util/Set;
       4: areturn

  public boolean equals(java.lang.Object);
    Code:
       0: aload_1
       1: instanceof    #29                 // class org/jboss/weld/injection/AbstractCallableInjectionPoint
       4: ifeq          28
       7: aload_1
       8: checkcast     #29                 // class org/jboss/weld/injection/AbstractCallableInjectionPoint
      11: astore_2
      12: aload_0
      13: invokevirtual #21                 // Method getAnnotated:()Ljavax/enterprise/inject/spi/AnnotatedCallable;
      16: aload_2
      17: invokevirtual #21                 // Method getAnnotated:()Ljavax/enterprise/inject/spi/AnnotatedCallable;
      20: invokestatic  #30                 // Method org/jboss/weld/util/AnnotatedTypes.compareAnnotatedCallable:(Ljavax/enterprise/inject/spi/AnnotatedCallable;Ljavax/enterprise/inject/spi/AnnotatedCallable;)Z
      23: ifeq          28
      26: iconst_1
      27: ireturn
      28: iconst_0
      29: ireturn

  public int hashCode();
    Code:
       0: aload_0
       1: invokevirtual #21                 // Method getAnnotated:()Ljavax/enterprise/inject/spi/AnnotatedCallable;
       4: invokevirtual #31                 // Method java/lang/Object.hashCode:()I
       7: ireturn

  public java.lang.String toString();
    Code:
       0: aload_0
       1: invokevirtual #21                 // Method getAnnotated:()Ljavax/enterprise/inject/spi/AnnotatedCallable;
       4: invokevirtual #32                 // Method java/lang/Object.toString:()Ljava/lang/String;
       7: areturn

  public javax.enterprise.inject.spi.Annotated getAnnotated();
    Code:
       0: aload_0
       1: invokevirtual #21                 // Method getAnnotated:()Ljavax/enterprise/inject/spi/AnnotatedCallable;
       4: areturn
}
