Compiled from "ThreadLocalStack.java"
class org.jboss.weld.injection.ThreadLocalStack$Stack<T> implements org.jboss.weld.context.cache.RequestScopedItem, org.jboss.weld.injection.ThreadLocalStack$ThreadLocalStackReference<T> {
  private final java.util.Deque<T> elements;

  private final java.lang.ThreadLocal<org.jboss.weld.injection.ThreadLocalStack$Stack<T>> interceptionContexts;

  private boolean removeWhenEmpty;

  private boolean valid;

  private org.jboss.weld.injection.ThreadLocalStack$Stack(java.lang.ThreadLocal<org.jboss.weld.injection.ThreadLocalStack$Stack<T>>);
    Code:
       0: aload_0
       1: invokespecial #3                  // Method java/lang/Object."<init>":()V
       4: aload_0
       5: aload_1
       6: putfield      #4                  // Field interceptionContexts:Ljava/lang/ThreadLocal;
       9: aload_0
      10: new           #5                  // class java/util/ArrayDeque
      13: dup
      14: invokespecial #6                  // Method java/util/ArrayDeque."<init>":()V
      17: putfield      #7                  // Field elements:Ljava/util/Deque;
      20: aload_0
      21: aload_0
      22: invokestatic  #8                  // Method org/jboss/weld/context/cache/RequestScopedCache.addItemIfActive:(Lorg/jboss/weld/context/cache/RequestScopedItem;)Z
      25: ifne          32
      28: iconst_1
      29: goto          33
      32: iconst_0
      33: putfield      #9                  // Field removeWhenEmpty:Z
      36: aload_0
      37: iconst_1
      38: putfield      #10                 // Field valid:Z
      41: return

  private void checkState();
    Code:
       0: aload_0
       1: getfield      #10                 // Field valid:Z
       4: ifne          17
       7: new           #11                 // class java/lang/IllegalStateException
      10: dup
      11: ldc           #12                 // String This ThreadLocalStack is no longer valid.
      13: invokespecial #13                 // Method java/lang/IllegalStateException."<init>":(Ljava/lang/String;)V
      16: athrow
      17: return

  public void push(T);
    Code:
       0: aload_0
       1: invokespecial #14                 // Method checkState:()V
       4: aload_0
       5: getfield      #7                  // Field elements:Ljava/util/Deque;
       8: aload_1
       9: invokeinterface #15,  2           // InterfaceMethod java/util/Deque.addFirst:(Ljava/lang/Object;)V
      14: return

  public T peek();
    Code:
       0: aload_0
       1: invokespecial #14                 // Method checkState:()V
       4: aload_0
       5: getfield      #7                  // Field elements:Ljava/util/Deque;
       8: invokeinterface #16,  1           // InterfaceMethod java/util/Deque.peekFirst:()Ljava/lang/Object;
      13: areturn

  public T pop();
    Code:
       0: aload_0
       1: invokespecial #14                 // Method checkState:()V
       4: aload_0
       5: getfield      #7                  // Field elements:Ljava/util/Deque;
       8: invokeinterface #17,  1           // InterfaceMethod java/util/Deque.removeFirst:()Ljava/lang/Object;
      13: astore_1
      14: aload_0
      15: invokespecial #1                  // Method removeIfEmpty:()V
      18: aload_1
      19: areturn

  private void removeIfEmpty();
    Code:
       0: aload_0
       1: getfield      #9                  // Field removeWhenEmpty:Z
       4: ifeq          31
       7: aload_0
       8: getfield      #7                  // Field elements:Ljava/util/Deque;
      11: invokeinterface #18,  1           // InterfaceMethod java/util/Deque.isEmpty:()Z
      16: ifeq          31
      19: aload_0
      20: getfield      #4                  // Field interceptionContexts:Ljava/lang/ThreadLocal;
      23: invokevirtual #19                 // Method java/lang/ThreadLocal.remove:()V
      26: aload_0
      27: iconst_0
      28: putfield      #10                 // Field valid:Z
      31: return

  public void invalidate();
    Code:
       0: aload_0
       1: iconst_1
       2: putfield      #9                  // Field removeWhenEmpty:Z
       5: aload_0
       6: invokespecial #1                  // Method removeIfEmpty:()V
       9: return

  org.jboss.weld.injection.ThreadLocalStack$Stack(java.lang.ThreadLocal, org.jboss.weld.injection.ThreadLocalStack$1);
    Code:
       0: aload_0
       1: aload_1
       2: invokespecial #2                  // Method "<init>":(Ljava/lang/ThreadLocal;)V
       5: return

  static void access$100(org.jboss.weld.injection.ThreadLocalStack$Stack);
    Code:
       0: aload_0
       1: invokespecial #1                  // Method removeIfEmpty:()V
       4: return
}
