Compiled from "BasicConfigurator.java"
public class ch.qos.logback.classic.BasicConfigurator {
  static final ch.qos.logback.classic.BasicConfigurator hiddenSingleton;

  private ch.qos.logback.classic.BasicConfigurator();
    Code:
       0: aload_0
       1: invokespecial #1                  // Method java/lang/Object."<init>":()V
       4: return

  public static void configure(ch.qos.logback.classic.LoggerContext);
    Code:
       0: aload_0
       1: invokevirtual #2                  // Method ch/qos/logback/classic/LoggerContext.getStatusManager:()Lch/qos/logback/core/status/StatusManager;
       4: astore_1
       5: aload_1
       6: ifnull        25
       9: aload_1
      10: new           #3                  // class ch/qos/logback/core/status/InfoStatus
      13: dup
      14: ldc           #4                  // String Setting up default configuration.
      16: aload_0
      17: invokespecial #5                  // Method ch/qos/logback/core/status/InfoStatus."<init>":(Ljava/lang/String;Ljava/lang/Object;)V
      20: invokeinterface #6,  2            // InterfaceMethod ch/qos/logback/core/status/StatusManager.add:(Lch/qos/logback/core/status/Status;)V
      25: new           #7                  // class ch/qos/logback/core/ConsoleAppender
      28: dup
      29: invokespecial #8                  // Method ch/qos/logback/core/ConsoleAppender."<init>":()V
      32: astore_2
      33: aload_2
      34: aload_0
      35: invokevirtual #9                  // Method ch/qos/logback/core/ConsoleAppender.setContext:(Lch/qos/logback/core/Context;)V
      38: aload_2
      39: ldc           #10                 // String console
      41: invokevirtual #11                 // Method ch/qos/logback/core/ConsoleAppender.setName:(Ljava/lang/String;)V
      44: new           #12                 // class ch/qos/logback/classic/encoder/PatternLayoutEncoder
      47: dup
      48: invokespecial #13                 // Method ch/qos/logback/classic/encoder/PatternLayoutEncoder."<init>":()V
      51: astore_3
      52: aload_3
      53: aload_0
      54: invokevirtual #14                 // Method ch/qos/logback/classic/encoder/PatternLayoutEncoder.setContext:(Lch/qos/logback/core/Context;)V
      57: aload_3
      58: ldc           #15                 // String %d{HH:mm:ss.SSS} [%thread] %-5level %logger{36} - %msg%n
      60: invokevirtual #16                 // Method ch/qos/logback/classic/encoder/PatternLayoutEncoder.setPattern:(Ljava/lang/String;)V
      63: aload_3
      64: invokevirtual #17                 // Method ch/qos/logback/classic/encoder/PatternLayoutEncoder.start:()V
      67: aload_2
      68: aload_3
      69: invokevirtual #18                 // Method ch/qos/logback/core/ConsoleAppender.setEncoder:(Lch/qos/logback/core/encoder/Encoder;)V
      72: aload_2
      73: invokevirtual #19                 // Method ch/qos/logback/core/ConsoleAppender.start:()V
      76: aload_0
      77: ldc           #20                 // String ROOT
      79: invokevirtual #21                 // Method ch/qos/logback/classic/LoggerContext.getLogger:(Ljava/lang/String;)Lch/qos/logback/classic/Logger;
      82: astore        4
      84: aload         4
      86: aload_2
      87: invokevirtual #22                 // Method ch/qos/logback/classic/Logger.addAppender:(Lch/qos/logback/core/Appender;)V
      90: return

  public static void configureDefaultContext();
    Code:
       0: invokestatic  #23                 // Method org/slf4j/LoggerFactory.getILoggerFactory:()Lorg/slf4j/ILoggerFactory;
       3: checkcast     #24                 // class ch/qos/logback/classic/LoggerContext
       6: astore_0
       7: aload_0
       8: invokestatic  #25                 // Method configure:(Lch/qos/logback/classic/LoggerContext;)V
      11: return

  static {};
    Code:
       0: new           #26                 // class ch/qos/logback/classic/BasicConfigurator
       3: dup
       4: invokespecial #27                 // Method "<init>":()V
       7: putstatic     #28                 // Field hiddenSingleton:Lch/qos/logback/classic/BasicConfigurator;
      10: return
}
