Compiled from "PreferredConstructorDiscoverer.java"
final class org.springframework.data.mapping.model.PreferredConstructorDiscoverer$Discoverers$2 extends org.springframework.data.mapping.model.PreferredConstructorDiscoverer$Discoverers {
  org.springframework.data.mapping.model.PreferredConstructorDiscoverer$Discoverers$2(java.lang.String, int);
    Code:
       0: aload_0
       1: aload_1
       2: iload_2
       3: aconst_null
       4: invokespecial #1                  // Method org/springframework/data/mapping/model/PreferredConstructorDiscoverer$Discoverers."<init>":(Ljava/lang/String;ILorg/springframework/data/mapping/model/PreferredConstructorDiscoverer$1;)V
       7: return

  <T, P extends org.springframework.data.mapping.PersistentProperty<P>> org.springframework.data.mapping.PreferredConstructor<T, P> discover(org.springframework.data.util.TypeInformation<T>, org.springframework.data.mapping.PersistentEntity<T, P>);
    Code:
       0: aload_1
       1: invokeinterface #2,  1            // InterfaceMethod org/springframework/data/util/TypeInformation.getType:()Ljava/lang/Class;
       6: astore_3
       7: aload_3
       8: invokevirtual #3                  // Method java/lang/Class.getDeclaredConstructors:()[Ljava/lang/reflect/Constructor;
      11: invokestatic  #4                  // Method java/util/Arrays.stream:([Ljava/lang/Object;)Ljava/util/stream/Stream;
      14: aload_1
      15: aload_2
      16: invokedynamic #5,  0              // InvokeDynamic #0:apply:(Lorg/springframework/data/util/TypeInformation;Lorg/springframework/data/mapping/PersistentEntity;)Ljava/util/function/Function;
      21: invokeinterface #6,  2            // InterfaceMethod java/util/stream/Stream.map:(Ljava/util/function/Function;)Ljava/util/stream/Stream;
      26: invokedynamic #7,  0              // InvokeDynamic #1:test:()Ljava/util/function/Predicate;
      31: invokeinterface #8,  2            // InterfaceMethod java/util/stream/Stream.filter:(Ljava/util/function/Predicate;)Ljava/util/stream/Stream;
      36: invokedynamic #9,  0              // InvokeDynamic #2:test:()Ljava/util/function/Predicate;
      41: invokeinterface #8,  2            // InterfaceMethod java/util/stream/Stream.filter:(Ljava/util/function/Predicate;)Ljava/util/stream/Stream;
      46: invokeinterface #10,  1           // InterfaceMethod java/util/stream/Stream.findFirst:()Ljava/util/Optional;
      51: aload_1
      52: aload_2
      53: invokedynamic #11,  0             // InvokeDynamic #3:get:(Lorg/springframework/data/util/TypeInformation;Lorg/springframework/data/mapping/PersistentEntity;)Ljava/util/function/Supplier;
      58: invokevirtual #12                 // Method java/util/Optional.orElseGet:(Ljava/util/function/Supplier;)Ljava/lang/Object;
      61: checkcast     #13                 // class org/springframework/data/mapping/PreferredConstructor
      64: areturn

  private static org.springframework.data.mapping.PreferredConstructor lambda$discover$2(org.springframework.data.util.TypeInformation, org.springframework.data.mapping.PersistentEntity);
    Code:
       0: aload_0
       1: invokeinterface #2,  1            // InterfaceMethod org/springframework/data/util/TypeInformation.getType:()Ljava/lang/Class;
       6: invokestatic  #14                 // Method kotlin/jvm/JvmClassMappingKt.getKotlinClass:(Ljava/lang/Class;)Lkotlin/reflect/KClass;
       9: invokestatic  #15                 // Method kotlin/reflect/full/KClasses.getPrimaryConstructor:(Lkotlin/reflect/KClass;)Lkotlin/reflect/KFunction;
      12: astore_2
      13: aload_2
      14: ifnonnull     26
      17: getstatic     #16                 // Field DEFAULT:Lorg/springframework/data/mapping/model/PreferredConstructorDiscoverer$Discoverers;
      20: aload_0
      21: aload_1
      22: invokevirtual #17                 // Method org/springframework/data/mapping/model/PreferredConstructorDiscoverer$Discoverers.discover:(Lorg/springframework/data/util/TypeInformation;Lorg/springframework/data/mapping/PersistentEntity;)Lorg/springframework/data/mapping/PreferredConstructor;
      25: areturn
      26: aload_2
      27: invokestatic  #18                 // Method kotlin/reflect/jvm/ReflectJvmMapping.getJavaConstructor:(Lkotlin/reflect/KFunction;)Ljava/lang/reflect/Constructor;
      30: astore_3
      31: aload_3
      32: ifnull        44
      35: aload_3
      36: aload_0
      37: aload_1
      38: invokestatic  #19                 // Method org/springframework/data/mapping/model/PreferredConstructorDiscoverer$Discoverers.access$200:(Ljava/lang/reflect/Constructor;Lorg/springframework/data/util/TypeInformation;Lorg/springframework/data/mapping/PersistentEntity;)Lorg/springframework/data/mapping/PreferredConstructor;
      41: goto          45
      44: aconst_null
      45: areturn

  private static boolean lambda$discover$1(org.springframework.data.mapping.PreferredConstructor);
    Code:
       0: aload_0
       1: invokevirtual #20                 // Method org/springframework/data/mapping/PreferredConstructor.getConstructor:()Ljava/lang/reflect/Constructor;
       4: invokevirtual #21                 // Method java/lang/reflect/Constructor.isSynthetic:()Z
       7: ifne          14
      10: iconst_1
      11: goto          15
      14: iconst_0
      15: ireturn

  private static org.springframework.data.mapping.PreferredConstructor lambda$discover$0(org.springframework.data.util.TypeInformation, org.springframework.data.mapping.PersistentEntity, java.lang.reflect.Constructor);
    Code:
       0: aload_2
       1: aload_0
       2: aload_1
       3: invokestatic  #19                 // Method org/springframework/data/mapping/model/PreferredConstructorDiscoverer$Discoverers.access$200:(Ljava/lang/reflect/Constructor;Lorg/springframework/data/util/TypeInformation;Lorg/springframework/data/mapping/PersistentEntity;)Lorg/springframework/data/mapping/PreferredConstructor;
       6: areturn
}
