Compiled from "JvmNameResolver.kt"
public final class kotlin.reflect.jvm.internal.impl.metadata.jvm.deserialization.JvmNameResolverKt {
  public static final java.util.List<kotlin.reflect.jvm.internal.impl.metadata.jvm.JvmProtoBuf$StringTableTypes$Record> toExpandedRecordsList(java.util.List<kotlin.reflect.jvm.internal.impl.metadata.jvm.JvmProtoBuf$StringTableTypes$Record>);
    Code:
       0: aload_0
       1: ldc           #1                  // String <this>
       3: invokestatic  #15                 // Method kotlin/jvm/internal/Intrinsics.checkNotNullParameter:(Ljava/lang/Object;Ljava/lang/String;)V
       6: new           #3                  // class java/util/ArrayList
       9: dup
      10: invokespecial #11                 // Method java/util/ArrayList."<init>":()V
      13: astore_1
      14: aload_1
      15: astore_2
      16: iconst_0
      17: istore_3
      18: aload_2
      19: aload_0
      20: invokeinterface #20,  1           // InterfaceMethod java/util/List.size:()I
      25: invokevirtual #13                 // Method java/util/ArrayList.ensureCapacity:(I)V
      28: aload_0
      29: invokeinterface #19,  1           // InterfaceMethod java/util/List.iterator:()Ljava/util/Iterator;
      34: astore        4
      36: aload         4
      38: invokeinterface #17,  1           // InterfaceMethod java/util/Iterator.hasNext:()Z
      43: ifeq          96
      46: aload         4
      48: invokeinterface #18,  1           // InterfaceMethod java/util/Iterator.next:()Ljava/lang/Object;
      53: checkcast     #9                  // class kotlin/reflect/jvm/internal/impl/metadata/jvm/JvmProtoBuf$StringTableTypes$Record
      56: astore        5
      58: aload         5
      60: invokevirtual #16                 // Method kotlin/reflect/jvm/internal/impl/metadata/jvm/JvmProtoBuf$StringTableTypes$Record.getRange:()I
      63: istore        6
      65: iconst_0
      66: istore        7
      68: iload         7
      70: iload         6
      72: if_icmpge     36
      75: iload         7
      77: istore        8
      79: iconst_0
      80: istore        9
      82: aload_2
      83: aload         5
      85: invokevirtual #12                 // Method java/util/ArrayList.add:(Ljava/lang/Object;)Z
      88: pop
      89: nop
      90: iinc          7, 1
      93: goto          68
      96: aload_2
      97: invokevirtual #14                 // Method java/util/ArrayList.trimToSize:()V
     100: nop
     101: aload_1
     102: checkcast     #5                  // class java/util/List
     105: areturn
}
