Compiled from "NavigationStub.java"
public class net.thucydides.core.webdriver.stubs.NavigationStub implements org.openqa.selenium.WebDriver$Navigation {
  public net.thucydides.core.webdriver.stubs.NavigationStub();
    Code:
       0: aload_0
       1: invokespecial #1                  // Method java/lang/Object."<init>":()V
       4: return

  public void back();
    Code:
       0: return

  public void forward();
    Code:
       0: return

  public void to(java.lang.String);
    Code:
       0: return

  public void to(java.net.URL);
    Code:
       0: return

  public void refresh();
    Code:
       0: return
}
