Compiled from "OptionsStub.java"
class net.thucydides.core.webdriver.stubs.OptionsStub$1 implements org.openqa.selenium.logging.Logs {
  final net.thucydides.core.webdriver.stubs.OptionsStub this$0;

  net.thucydides.core.webdriver.stubs.OptionsStub$1(net.thucydides.core.webdriver.stubs.OptionsStub);
    Code:
       0: aload_0
       1: aload_1
       2: putfield      #1                  // Field this$0:Lnet/thucydides/core/webdriver/stubs/OptionsStub;
       5: aload_0
       6: invokespecial #2                  // Method java/lang/Object."<init>":()V
       9: return

  public org.openqa.selenium.logging.LogEntries get(java.lang.String);
    Code:
       0: aconst_null
       1: areturn

  public java.util.Set<java.lang.String> getAvailableLogTypes();
    Code:
       0: aconst_null
       1: areturn
}
