Compiled from "WebElementFacadeStub.java"
class net.thucydides.core.webdriver.stubs.WebElementFacadeStub$2 implements org.openqa.selenium.support.ui.Wait<org.openqa.selenium.WebDriver> {
  final net.thucydides.core.webdriver.stubs.WebElementFacadeStub this$0;

  net.thucydides.core.webdriver.stubs.WebElementFacadeStub$2(net.thucydides.core.webdriver.stubs.WebElementFacadeStub);
    Code:
       0: aload_0
       1: aload_1
       2: putfield      #1                  // Field this$0:Lnet/thucydides/core/webdriver/stubs/WebElementFacadeStub;
       5: aload_0
       6: invokespecial #2                  // Method java/lang/Object."<init>":()V
       9: return

  public <T> T until(java.util.function.Function<? super org.openqa.selenium.WebDriver, T>);
    Code:
       0: aconst_null
       1: areturn
}
