Compiled from "VersionedConectionFactory.java"
class org.jboss.remotingjmx.VersionedConectionFactory {
  private static final org.jboss.logging.Logger log;

  org.jboss.remotingjmx.VersionedConectionFactory();
    Code:
       0: aload_0
       1: invokespecial #2                  // Method java/lang/Object."<init>":()V
       4: return

  static org.jboss.remotingjmx.VersionedConnection createVersionedConnection(org.jboss.remoting3.Channel, java.util.Map<java.lang.String, ?>, javax.management.remote.JMXServiceURL) throws java.io.IOException;
    Code:
       0: aload_0
       1: invokestatic  #3                  // Method org/jboss/remotingjmx/VersionedConectionFactory$ClientVersionReceiver.getInitialHeader:(Lorg/jboss/remoting3/Channel;)Lorg/xnio/IoFuture;
       4: astore_3
       5: aload_3
       6: getstatic     #4                  // Field org/jboss/remotingjmx/Util$Timeout.VERSIONED_CONNECTION:Lorg/jboss/remotingjmx/Util$Timeout;
       9: aload_1
      10: invokestatic  #5                  // Method org/jboss/remotingjmx/Util.getTimeoutValue:(Lorg/jboss/remotingjmx/Util$Timeout;Ljava/util/Map;)Ljava/lang/Integer;
      13: invokevirtual #6                  // Method java/lang/Integer.intValue:()I
      16: i2l
      17: getstatic     #7                  // Field java/util/concurrent/TimeUnit.SECONDS:Ljava/util/concurrent/TimeUnit;
      20: invokeinterface #8,  4            // InterfaceMethod org/xnio/IoFuture.await:(JLjava/util/concurrent/TimeUnit;)Lorg/xnio/IoFuture$Status;
      25: astore        4
      27: getstatic     #9                  // Field org/jboss/remotingjmx/VersionedConectionFactory$1.$SwitchMap$org$xnio$IoFuture$Status:[I
      30: aload         4
      32: invokevirtual #10                 // Method org/xnio/IoFuture$Status.ordinal:()I
      35: iaload
      36: lookupswitch  { // 2
                     1: 64
                     2: 67
               default: 74
          }
      64: goto          105
      67: aload_3
      68: invokeinterface #11,  1           // InterfaceMethod org/xnio/IoFuture.getException:()Ljava/io/IOException;
      73: athrow
      74: new           #12                 // class java/io/IOException
      77: dup
      78: new           #13                 // class java/lang/StringBuilder
      81: dup
      82: invokespecial #14                 // Method java/lang/StringBuilder."<init>":()V
      85: ldc           #15                 // String Timeout out waiting for header, status=
      87: invokevirtual #16                 // Method java/lang/StringBuilder.append:(Ljava/lang/String;)Ljava/lang/StringBuilder;
      90: aload         4
      92: invokevirtual #17                 // Method org/xnio/IoFuture$Status.toString:()Ljava/lang/String;
      95: invokevirtual #16                 // Method java/lang/StringBuilder.append:(Ljava/lang/String;)Ljava/lang/StringBuilder;
      98: invokevirtual #18                 // Method java/lang/StringBuilder.toString:()Ljava/lang/String;
     101: invokespecial #19                 // Method java/io/IOException."<init>":(Ljava/lang/String;)V
     104: athrow
     105: aload_3
     106: invokeinterface #20,  1           // InterfaceMethod org/xnio/IoFuture.get:()Ljava/lang/Object;
     111: checkcast     #21                 // class org/jboss/remotingjmx/VersionedConectionFactory$InitialHeader
     114: astore        5
     116: new           #22                 // class org/jboss/remotingjmx/protocol/Versions
     119: dup
     120: aload_1
     121: invokespecial #23                 // Method org/jboss/remotingjmx/protocol/Versions."<init>":(Ljava/util/Map;)V
     124: astore        6
     126: aload         6
     128: aload_2
     129: invokestatic  #24                 // Method getRequiredCapabilities:(Ljavax/management/remote/JMXServiceURL;)[Lorg/jboss/remotingjmx/Capability;
     132: invokevirtual #25                 // Method org/jboss/remotingjmx/protocol/Versions.getSupportedVersions:([Lorg/jboss/remotingjmx/Capability;)Ljava/util/Set;
     135: astore        7
     137: iconst_0
     138: istore        8
     140: aload         5
     142: invokestatic  #26                 // Method org/jboss/remotingjmx/VersionedConectionFactory$InitialHeader.access$000:(Lorg/jboss/remotingjmx/VersionedConectionFactory$InitialHeader;)[B
     145: astore        9
     147: aload         9
     149: arraylength
     150: istore        10
     152: iconst_0
     153: istore        11
     155: iload         11
     157: iload         10
     159: if_icmpge     201
     162: aload         9
     164: iload         11
     166: baload
     167: istore        12
     169: aload         7
     171: iload         12
     173: invokestatic  #27                 // Method java/lang/Byte.valueOf:(B)Ljava/lang/Byte;
     176: invokeinterface #28,  2           // InterfaceMethod java/util/Set.contains:(Ljava/lang/Object;)Z
     181: ifeq          195
     184: iload         12
     186: iload         8
     188: if_icmple     195
     191: iload         12
     193: istore        8
     195: iinc          11, 1
     198: goto          155
     201: iload         8
     203: ifne          216
     206: new           #29                 // class java/lang/IllegalStateException
     209: dup
     210: ldc           #30                 // String No matching supported protocol version found.
     212: invokespecial #31                 // Method java/lang/IllegalStateException."<init>":(Ljava/lang/String;)V
     215: athrow
     216: aload         6
     218: iload         8
     220: aload_0
     221: aload_2
     222: invokevirtual #32                 // Method org/jboss/remotingjmx/protocol/Versions.getVersionedConnection:(BLorg/jboss/remoting3/Channel;Ljavax/management/remote/JMXServiceURL;)Lorg/jboss/remotingjmx/VersionedConnection;
     225: areturn

  private static org.jboss.remotingjmx.Capability[] getRequiredCapabilities(javax.management.remote.JMXServiceURL);
    Code:
       0: new           #33                 // class java/util/HashSet
       3: dup
       4: invokespecial #34                 // Method java/util/HashSet."<init>":()V
       7: astore_1
       8: aload_0
       9: invokevirtual #35                 // Method javax/management/remote/JMXServiceURL.getURLPath:()Ljava/lang/String;
      12: astore_2
      13: aload_2
      14: ldc           #36                 // String ?
      16: invokevirtual #37                 // Method java/lang/String.contains:(Ljava/lang/CharSequence;)Z
      19: ifeq          32
      22: aload_1
      23: getstatic     #38                 // Field org/jboss/remotingjmx/Capability.PASS_PARAMETERS:Lorg/jboss/remotingjmx/Capability;
      26: invokeinterface #39,  2           // InterfaceMethod java/util/Set.add:(Ljava/lang/Object;)Z
      31: pop
      32: aload_1
      33: aload_1
      34: invokeinterface #40,  1           // InterfaceMethod java/util/Set.size:()I
      39: anewarray     #41                 // class org/jboss/remotingjmx/Capability
      42: invokeinterface #42,  2           // InterfaceMethod java/util/Set.toArray:([Ljava/lang/Object;)[Ljava/lang/Object;
      47: checkcast     #43                 // class "[Lorg/jboss/remotingjmx/Capability;"
      50: areturn

  static org.jboss.logging.Logger access$200();
    Code:
       0: getstatic     #1                  // Field log:Lorg/jboss/logging/Logger;
       3: areturn

  static {};
    Code:
       0: ldc_w         #44                 // class org/jboss/remotingjmx/VersionedConectionFactory
       3: invokestatic  #45                 // Method org/jboss/logging/Logger.getLogger:(Ljava/lang/Class;)Lorg/jboss/logging/Logger;
       6: putstatic     #1                  // Field log:Lorg/jboss/logging/Logger;
       9: return
}
