Compiled from "Callback.java"
public class org.eclipse.jetty.util.Callback$Nested extends org.eclipse.jetty.util.Callback$Completing {
  private final org.eclipse.jetty.util.Callback callback;

  public org.eclipse.jetty.util.Callback$Nested(org.eclipse.jetty.util.Callback);
    Code:
       0: aload_0
       1: invokespecial #1                  // Method org/eclipse/jetty/util/Callback$Completing."<init>":()V
       4: aload_0
       5: aload_1
       6: putfield      #2                  // Field callback:Lorg/eclipse/jetty/util/Callback;
       9: return

  public org.eclipse.jetty.util.Callback$Nested(org.eclipse.jetty.util.Callback$Nested);
    Code:
       0: aload_0
       1: invokespecial #1                  // Method org/eclipse/jetty/util/Callback$Completing."<init>":()V
       4: aload_0
       5: aload_1
       6: getfield      #2                  // Field callback:Lorg/eclipse/jetty/util/Callback;
       9: putfield      #2                  // Field callback:Lorg/eclipse/jetty/util/Callback;
      12: return

  public org.eclipse.jetty.util.Callback getCallback();
    Code:
       0: aload_0
       1: getfield      #2                  // Field callback:Lorg/eclipse/jetty/util/Callback;
       4: areturn

  public void succeeded();
    Code:
       0: aload_0
       1: getfield      #2                  // Field callback:Lorg/eclipse/jetty/util/Callback;
       4: invokeinterface #3,  1            // InterfaceMethod org/eclipse/jetty/util/Callback.succeeded:()V
       9: aload_0
      10: invokevirtual #4                  // Method completed:()V
      13: goto          23
      16: astore_1
      17: aload_0
      18: invokevirtual #4                  // Method completed:()V
      21: aload_1
      22: athrow
      23: return
    Exception table:
       from    to  target type
           0     9    16   any

  public void failed(java.lang.Throwable);
    Code:
       0: aload_0
       1: getfield      #2                  // Field callback:Lorg/eclipse/jetty/util/Callback;
       4: aload_1
       5: invokeinterface #5,  2            // InterfaceMethod org/eclipse/jetty/util/Callback.failed:(Ljava/lang/Throwable;)V
      10: aload_0
      11: invokevirtual #4                  // Method completed:()V
      14: goto          24
      17: astore_2
      18: aload_0
      19: invokevirtual #4                  // Method completed:()V
      22: aload_2
      23: athrow
      24: return
    Exception table:
       from    to  target type
           0    10    17   any

  public org.eclipse.jetty.util.thread.Invocable$InvocationType getInvocationType();
    Code:
       0: aload_0
       1: getfield      #2                  // Field callback:Lorg/eclipse/jetty/util/Callback;
       4: invokeinterface #6,  1            // InterfaceMethod org/eclipse/jetty/util/Callback.getInvocationType:()Lorg/eclipse/jetty/util/thread/Invocable$InvocationType;
       9: areturn
}
