Compiled from "Callback.java"
class org.eclipse.jetty.util.Callback$2 implements org.eclipse.jetty.util.Callback {
  final java.util.concurrent.CompletableFuture val$completable;

  final org.eclipse.jetty.util.thread.Invocable$InvocationType val$invocation;

  org.eclipse.jetty.util.Callback$2(java.util.concurrent.CompletableFuture, org.eclipse.jetty.util.thread.Invocable$InvocationType);
    Code:
       0: aload_0
       1: aload_1
       2: putfield      #1                  // Field val$completable:Ljava/util/concurrent/CompletableFuture;
       5: aload_0
       6: aload_2
       7: putfield      #2                  // Field val$invocation:Lorg/eclipse/jetty/util/thread/Invocable$InvocationType;
      10: aload_0
      11: invokespecial #3                  // Method java/lang/Object."<init>":()V
      14: return

  public void succeeded();
    Code:
       0: aload_0
       1: getfield      #1                  // Field val$completable:Ljava/util/concurrent/CompletableFuture;
       4: aconst_null
       5: invokevirtual #4                  // Method java/util/concurrent/CompletableFuture.complete:(Ljava/lang/Object;)Z
       8: pop
       9: return

  public void failed(java.lang.Throwable);
    Code:
       0: aload_0
       1: getfield      #1                  // Field val$completable:Ljava/util/concurrent/CompletableFuture;
       4: aload_1
       5: invokevirtual #5                  // Method java/util/concurrent/CompletableFuture.completeExceptionally:(Ljava/lang/Throwable;)Z
       8: pop
       9: return

  public org.eclipse.jetty.util.thread.Invocable$InvocationType getInvocationType();
    Code:
       0: aload_0
       1: getfield      #2                  // Field val$invocation:Lorg/eclipse/jetty/util/thread/Invocable$InvocationType;
       4: areturn
}
