Compiled from "IteratingNestedCallback.java"
public abstract class org.eclipse.jetty.util.IteratingNestedCallback extends org.eclipse.jetty.util.IteratingCallback {
  final org.eclipse.jetty.util.Callback _callback;

  public org.eclipse.jetty.util.IteratingNestedCallback(org.eclipse.jetty.util.Callback);
    Code:
       0: aload_0
       1: invokespecial #1                  // Method org/eclipse/jetty/util/IteratingCallback."<init>":()V
       4: aload_0
       5: aload_1
       6: putfield      #2                  // Field _callback:Lorg/eclipse/jetty/util/Callback;
       9: return

  public org.eclipse.jetty.util.thread.Invocable$InvocationType getInvocationType();
    Code:
       0: aload_0
       1: getfield      #2                  // Field _callback:Lorg/eclipse/jetty/util/Callback;
       4: invokeinterface #3,  1            // InterfaceMethod org/eclipse/jetty/util/Callback.getInvocationType:()Lorg/eclipse/jetty/util/thread/Invocable$InvocationType;
       9: areturn

  protected void onCompleteSuccess();
    Code:
       0: aload_0
       1: getfield      #2                  // Field _callback:Lorg/eclipse/jetty/util/Callback;
       4: invokeinterface #4,  1            // InterfaceMethod org/eclipse/jetty/util/Callback.succeeded:()V
       9: return

  protected void onCompleteFailure(java.lang.Throwable);
    Code:
       0: aload_0
       1: getfield      #2                  // Field _callback:Lorg/eclipse/jetty/util/Callback;
       4: aload_1
       5: invokeinterface #5,  2            // InterfaceMethod org/eclipse/jetty/util/Callback.failed:(Ljava/lang/Throwable;)V
      10: return

  public java.lang.String toString();
    Code:
       0: ldc           #6                  // String %s@%x
       2: iconst_2
       3: anewarray     #7                  // class java/lang/Object
       6: dup
       7: iconst_0
       8: aload_0
       9: invokevirtual #8                  // Method java/lang/Object.getClass:()Ljava/lang/Class;
      12: invokevirtual #9                  // Method java/lang/Class.getSimpleName:()Ljava/lang/String;
      15: aastore
      16: dup
      17: iconst_1
      18: aload_0
      19: invokevirtual #10                 // Method java/lang/Object.hashCode:()I
      22: invokestatic  #11                 // Method java/lang/Integer.valueOf:(I)Ljava/lang/Integer;
      25: aastore
      26: invokestatic  #12                 // Method java/lang/String.format:(Ljava/lang/String;[Ljava/lang/Object;)Ljava/lang/String;
      29: areturn
}
