Compiled from "ToOneIdMapper.java"
public class org.hibernate.envers.internal.entities.mapper.relation.ToOneIdMapper extends org.hibernate.envers.internal.entities.mapper.relation.AbstractToOneMapper {
  private final org.hibernate.envers.internal.entities.mapper.id.IdMapper delegate;

  private final java.lang.String referencedEntityName;

  private final boolean nonInsertableFake;

  public org.hibernate.envers.internal.entities.mapper.relation.ToOneIdMapper(org.hibernate.envers.internal.entities.mapper.id.IdMapper, org.hibernate.envers.internal.entities.PropertyData, java.lang.String, boolean);
    Code:
       0: aload_0
       1: aload_1
       2: invokeinterface #1,  1            // InterfaceMethod org/hibernate/envers/internal/entities/mapper/id/IdMapper.getServiceRegistry:()Lorg/hibernate/service/ServiceRegistry;
       7: aload_2
       8: invokespecial #2                  // Method org/hibernate/envers/internal/entities/mapper/relation/AbstractToOneMapper."<init>":(Lorg/hibernate/service/ServiceRegistry;Lorg/hibernate/envers/internal/entities/PropertyData;)V
      11: aload_0
      12: aload_1
      13: putfield      #3                  // Field delegate:Lorg/hibernate/envers/internal/entities/mapper/id/IdMapper;
      16: aload_0
      17: aload_3
      18: putfield      #4                  // Field referencedEntityName:Ljava/lang/String;
      21: aload_0
      22: iload         4
      24: putfield      #5                  // Field nonInsertableFake:Z
      27: return

  public boolean mapToMapFromEntity(org.hibernate.engine.spi.SessionImplementor, java.util.Map<java.lang.String, java.lang.Object>, java.lang.Object, java.lang.Object);
    Code:
       0: new           #6                  // class java/util/HashMap
       3: dup
       4: invokespecial #7                  // Method java/util/HashMap."<init>":()V
       7: astore        5
       9: aload_0
      10: getfield      #3                  // Field delegate:Lorg/hibernate/envers/internal/entities/mapper/id/IdMapper;
      13: aload         5
      15: aload_0
      16: getfield      #5                  // Field nonInsertableFake:Z
      19: ifeq          27
      22: aload         4
      24: goto          28
      27: aload_3
      28: invokeinterface #8,  3            // InterfaceMethod org/hibernate/envers/internal/entities/mapper/id/IdMapper.mapToMapFromEntity:(Ljava/util/Map;Ljava/lang/Object;)V
      33: aload         5
      35: invokevirtual #9                  // Method java/util/HashMap.entrySet:()Ljava/util/Set;
      38: invokeinterface #10,  1           // InterfaceMethod java/util/Set.iterator:()Ljava/util/Iterator;
      43: astore        6
      45: aload         6
      47: invokeinterface #11,  1           // InterfaceMethod java/util/Iterator.hasNext:()Z
      52: ifeq          91
      55: aload         6
      57: invokeinterface #12,  1           // InterfaceMethod java/util/Iterator.next:()Ljava/lang/Object;
      62: checkcast     #13                 // class java/util/Map$Entry
      65: astore        7
      67: aload_2
      68: aload         7
      70: invokeinterface #14,  1           // InterfaceMethod java/util/Map$Entry.getKey:()Ljava/lang/Object;
      75: aload         7
      77: invokeinterface #15,  1           // InterfaceMethod java/util/Map$Entry.getValue:()Ljava/lang/Object;
      82: invokeinterface #16,  3           // InterfaceMethod java/util/Map.put:(Ljava/lang/Object;Ljava/lang/Object;)Ljava/lang/Object;
      87: pop
      88: goto          45
      91: aload_0
      92: aload_1
      93: aload_3
      94: aload         4
      96: invokevirtual #17                 // Method checkModified:(Lorg/hibernate/engine/spi/SessionImplementor;Ljava/lang/Object;Ljava/lang/Object;)Z
      99: ireturn

  public void mapModifiedFlagsToMapFromEntity(org.hibernate.engine.spi.SessionImplementor, java.util.Map<java.lang.String, java.lang.Object>, java.lang.Object, java.lang.Object);
    Code:
       0: aload_0
       1: invokevirtual #18                 // Method getPropertyData:()Lorg/hibernate/envers/internal/entities/PropertyData;
       4: invokevirtual #19                 // Method org/hibernate/envers/internal/entities/PropertyData.isUsingModifiedFlag:()Z
       7: ifeq          35
      10: aload_2
      11: aload_0
      12: invokevirtual #18                 // Method getPropertyData:()Lorg/hibernate/envers/internal/entities/PropertyData;
      15: invokevirtual #20                 // Method org/hibernate/envers/internal/entities/PropertyData.getModifiedFlagPropertyName:()Ljava/lang/String;
      18: aload_0
      19: aload_1
      20: aload_3
      21: aload         4
      23: invokevirtual #17                 // Method checkModified:(Lorg/hibernate/engine/spi/SessionImplementor;Ljava/lang/Object;Ljava/lang/Object;)Z
      26: invokestatic  #21                 // Method java/lang/Boolean.valueOf:(Z)Ljava/lang/Boolean;
      29: invokeinterface #16,  3           // InterfaceMethod java/util/Map.put:(Ljava/lang/Object;Ljava/lang/Object;)Ljava/lang/Object;
      34: pop
      35: return

  public void mapModifiedFlagsToMapForCollectionChange(java.lang.String, java.util.Map<java.lang.String, java.lang.Object>);
    Code:
       0: aload_0
       1: invokevirtual #18                 // Method getPropertyData:()Lorg/hibernate/envers/internal/entities/PropertyData;
       4: invokevirtual #19                 // Method org/hibernate/envers/internal/entities/PropertyData.isUsingModifiedFlag:()Z
       7: ifeq          38
      10: aload_2
      11: aload_0
      12: invokevirtual #18                 // Method getPropertyData:()Lorg/hibernate/envers/internal/entities/PropertyData;
      15: invokevirtual #20                 // Method org/hibernate/envers/internal/entities/PropertyData.getModifiedFlagPropertyName:()Ljava/lang/String;
      18: aload_1
      19: aload_0
      20: invokevirtual #18                 // Method getPropertyData:()Lorg/hibernate/envers/internal/entities/PropertyData;
      23: invokevirtual #22                 // Method org/hibernate/envers/internal/entities/PropertyData.getName:()Ljava/lang/String;
      26: invokevirtual #23                 // Method java/lang/String.equals:(Ljava/lang/Object;)Z
      29: invokestatic  #21                 // Method java/lang/Boolean.valueOf:(Z)Ljava/lang/Boolean;
      32: invokeinterface #16,  3           // InterfaceMethod java/util/Map.put:(Ljava/lang/Object;Ljava/lang/Object;)Ljava/lang/Object;
      37: pop
      38: return

  protected boolean checkModified(org.hibernate.engine.spi.SessionImplementor, java.lang.Object, java.lang.Object);
    Code:
       0: aload_0
       1: getfield      #5                  // Field nonInsertableFake:Z
       4: ifeq          11
       7: iconst_0
       8: goto          29
      11: aload_1
      12: aload_0
      13: getfield      #4                  // Field referencedEntityName:Ljava/lang/String;
      16: aload_2
      17: aload_3
      18: invokestatic  #24                 // Method org/hibernate/envers/internal/tools/EntityTools.entitiesEqual:(Lorg/hibernate/engine/spi/SessionImplementor;Ljava/lang/String;Ljava/lang/Object;Ljava/lang/Object;)Z
      21: ifne          28
      24: iconst_1
      25: goto          29
      28: iconst_0
      29: ireturn

  public void nullSafeMapToEntityFromMap(org.hibernate.envers.boot.internal.EnversService, java.lang.Object, java.util.Map, java.lang.Object, org.hibernate.envers.internal.reader.AuditReaderImplementor, java.lang.Number);
    Code:
       0: aload_0
       1: getfield      #3                  // Field delegate:Lorg/hibernate/envers/internal/entities/mapper/id/IdMapper;
       4: aload_3
       5: invokeinterface #25,  2           // InterfaceMethod org/hibernate/envers/internal/entities/mapper/id/IdMapper.mapToIdFromMap:(Ljava/util/Map;)Ljava/lang/Object;
      10: astore        7
      12: aconst_null
      13: astore        8
      15: aload         7
      17: ifnull        223
      20: aload         5
      22: invokeinterface #26,  1           // InterfaceMethod org/hibernate/envers/internal/reader/AuditReaderImplementor.getFirstLevelCache:()Lorg/hibernate/envers/internal/reader/FirstLevelCache;
      27: aload_0
      28: getfield      #4                  // Field referencedEntityName:Ljava/lang/String;
      31: aload         6
      33: aload         7
      35: invokevirtual #27                 // Method org/hibernate/envers/internal/reader/FirstLevelCache.contains:(Ljava/lang/String;Ljava/lang/Number;Ljava/lang/Object;)Z
      38: ifeq          64
      41: aload         5
      43: invokeinterface #26,  1           // InterfaceMethod org/hibernate/envers/internal/reader/AuditReaderImplementor.getFirstLevelCache:()Lorg/hibernate/envers/internal/reader/FirstLevelCache;
      48: aload_0
      49: getfield      #4                  // Field referencedEntityName:Ljava/lang/String;
      52: aload         6
      54: aload         7
      56: invokevirtual #28                 // Method org/hibernate/envers/internal/reader/FirstLevelCache.get:(Ljava/lang/String;Ljava/lang/Number;Ljava/lang/Object;)Ljava/lang/Object;
      59: astore        8
      61: goto          223
      64: aload_0
      65: aload_1
      66: aload_0
      67: getfield      #4                  // Field referencedEntityName:Ljava/lang/String;
      70: invokevirtual #29                 // Method getEntityInfo:(Lorg/hibernate/envers/boot/internal/EnversService;Ljava/lang/String;)Lorg/hibernate/envers/internal/entities/mapper/relation/AbstractToOneMapper$EntityInfo;
      73: astore        9
      75: iconst_0
      76: istore        10
      78: aload         9
      80: invokevirtual #30                 // Method org/hibernate/envers/internal/entities/mapper/relation/AbstractToOneMapper$EntityInfo.isAudited:()Z
      83: ifne          131
      86: aload_1
      87: invokeinterface #31,  1           // InterfaceMethod org/hibernate/envers/boot/internal/EnversService.getEntitiesConfigurations:()Lorg/hibernate/envers/internal/entities/EntitiesConfigurations;
      92: aload_3
      93: ldc           #32                 // String $type$
      95: invokeinterface #33,  2           // InterfaceMethod java/util/Map.get:(Ljava/lang/Object;)Ljava/lang/Object;
     100: checkcast     #34                 // class java/lang/String
     103: invokevirtual #35                 // Method org/hibernate/envers/internal/entities/EntitiesConfigurations.getEntityNameForVersionsEntityName:(Ljava/lang/String;)Ljava/lang/String;
     106: astore        11
     108: aload_1
     109: invokeinterface #31,  1           // InterfaceMethod org/hibernate/envers/boot/internal/EnversService.getEntitiesConfigurations:()Lorg/hibernate/envers/internal/entities/EntitiesConfigurations;
     114: aload         11
     116: aload_0
     117: invokevirtual #18                 // Method getPropertyData:()Lorg/hibernate/envers/internal/entities/PropertyData;
     120: invokevirtual #22                 // Method org/hibernate/envers/internal/entities/PropertyData.getName:()Ljava/lang/String;
     123: invokevirtual #36                 // Method org/hibernate/envers/internal/entities/EntitiesConfigurations.getRelationDescription:(Ljava/lang/String;Ljava/lang/String;)Lorg/hibernate/envers/internal/entities/RelationDescription;
     126: invokevirtual #37                 // Method org/hibernate/envers/internal/entities/RelationDescription.isIgnoreNotFound:()Z
     129: istore        10
     131: iload         10
     133: ifeq          181
     136: aload         5
     138: aload         9
     140: invokevirtual #38                 // Method org/hibernate/envers/internal/entities/mapper/relation/AbstractToOneMapper$EntityInfo.getEntityClass:()Ljava/lang/Class;
     143: aload_0
     144: getfield      #4                  // Field referencedEntityName:Ljava/lang/String;
     147: aload         7
     149: aload         6
     151: getstatic     #39                 // Field org/hibernate/envers/RevisionType.DEL:Lorg/hibernate/envers/RevisionType;
     154: aload_3
     155: aload_1
     156: invokeinterface #40,  1           // InterfaceMethod org/hibernate/envers/boot/internal/EnversService.getAuditEntitiesConfiguration:()Lorg/hibernate/envers/configuration/internal/AuditEntitiesConfiguration;
     161: invokevirtual #41                 // Method org/hibernate/envers/configuration/internal/AuditEntitiesConfiguration.getRevisionTypePropName:()Ljava/lang/String;
     164: invokeinterface #33,  2           // InterfaceMethod java/util/Map.get:(Ljava/lang/Object;)Ljava/lang/Object;
     169: invokevirtual #42                 // Method org/hibernate/envers/RevisionType.equals:(Ljava/lang/Object;)Z
     172: aload_1
     173: invokestatic  #43                 // Method org/hibernate/envers/internal/entities/mapper/relation/ToOneEntityLoader.loadImmediate:(Lorg/hibernate/envers/internal/reader/AuditReaderImplementor;Ljava/lang/Class;Ljava/lang/String;Ljava/lang/Object;Ljava/lang/Number;ZLorg/hibernate/envers/boot/internal/EnversService;)Ljava/lang/Object;
     176: astore        8
     178: goto          223
     181: aload         5
     183: aload         9
     185: invokevirtual #38                 // Method org/hibernate/envers/internal/entities/mapper/relation/AbstractToOneMapper$EntityInfo.getEntityClass:()Ljava/lang/Class;
     188: aload_0
     189: getfield      #4                  // Field referencedEntityName:Ljava/lang/String;
     192: aload         7
     194: aload         6
     196: getstatic     #39                 // Field org/hibernate/envers/RevisionType.DEL:Lorg/hibernate/envers/RevisionType;
     199: aload_3
     200: aload_1
     201: invokeinterface #40,  1           // InterfaceMethod org/hibernate/envers/boot/internal/EnversService.getAuditEntitiesConfiguration:()Lorg/hibernate/envers/configuration/internal/AuditEntitiesConfiguration;
     206: invokevirtual #41                 // Method org/hibernate/envers/configuration/internal/AuditEntitiesConfiguration.getRevisionTypePropName:()Ljava/lang/String;
     209: invokeinterface #33,  2           // InterfaceMethod java/util/Map.get:(Ljava/lang/Object;)Ljava/lang/Object;
     214: invokevirtual #42                 // Method org/hibernate/envers/RevisionType.equals:(Ljava/lang/Object;)Z
     217: aload_1
     218: invokestatic  #44                 // Method org/hibernate/envers/internal/entities/mapper/relation/ToOneEntityLoader.createProxyOrLoadImmediate:(Lorg/hibernate/envers/internal/reader/AuditReaderImplementor;Ljava/lang/Class;Ljava/lang/String;Ljava/lang/Object;Ljava/lang/Number;ZLorg/hibernate/envers/boot/internal/EnversService;)Ljava/lang/Object;
     221: astore        8
     223: aload_0
     224: aload_2
     225: aload         8
     227: invokevirtual #45                 // Method setPropertyValue:(Ljava/lang/Object;Ljava/lang/Object;)V
     230: return

  public void addMiddleEqualToQuery(org.hibernate.envers.internal.tools.query.Parameters, java.lang.String, java.lang.String, java.lang.String, java.lang.String);
    Code:
       0: aload_0
       1: getfield      #3                  // Field delegate:Lorg/hibernate/envers/internal/entities/mapper/id/IdMapper;
       4: aload_1
       5: aload_3
       6: aload_0
       7: getfield      #3                  // Field delegate:Lorg/hibernate/envers/internal/entities/mapper/id/IdMapper;
      10: aload         5
      12: invokeinterface #46,  5           // InterfaceMethod org/hibernate/envers/internal/entities/mapper/id/IdMapper.addIdsEqualToQuery:(Lorg/hibernate/envers/internal/tools/query/Parameters;Ljava/lang/String;Lorg/hibernate/envers/internal/entities/mapper/id/IdMapper;Ljava/lang/String;)V
      17: return
}
