Compiled from "Axis.java"
public abstract class javafx.scene.chart.Axis<T> extends javafx.scene.layout.Region {
  javafx.scene.text.Text measure;

  private javafx.geometry.Orientation effectiveOrientation;

  private double effectiveTickLabelRotation;

  private javafx.scene.control.Label axisLabel;

  private final javafx.scene.shape.Path tickMarkPath;

  private double oldLength;

  boolean rangeValid;

  boolean measureInvalid;

  boolean tickLabelsVisibleInvalid;

  private java.util.BitSet labelsToSkip;

  private final javafx.collections.ObservableList<javafx.scene.chart.Axis$TickMark<T>> tickMarks;

  private final javafx.collections.ObservableList<javafx.scene.chart.Axis$TickMark<T>> unmodifiableTickMarks;

  private javafx.beans.property.ObjectProperty<javafx.geometry.Side> side;

  private javafx.beans.property.ObjectProperty<java.lang.String> label;

  private javafx.beans.property.BooleanProperty tickMarkVisible;

  private javafx.beans.property.BooleanProperty tickLabelsVisible;

  private javafx.beans.property.DoubleProperty tickLength;

  private javafx.beans.property.BooleanProperty autoRanging;

  private javafx.beans.property.ObjectProperty<javafx.scene.text.Font> tickLabelFont;

  private javafx.beans.property.ObjectProperty<javafx.scene.paint.Paint> tickLabelFill;

  private javafx.beans.property.DoubleProperty tickLabelGap;

  private javafx.beans.property.BooleanProperty animated;

  private javafx.beans.property.DoubleProperty tickLabelRotation;

  private static final javafx.css.PseudoClass TOP_PSEUDOCLASS_STATE;

  private static final javafx.css.PseudoClass BOTTOM_PSEUDOCLASS_STATE;

  private static final javafx.css.PseudoClass LEFT_PSEUDOCLASS_STATE;

  private static final javafx.css.PseudoClass RIGHT_PSEUDOCLASS_STATE;

  public javafx.collections.ObservableList<javafx.scene.chart.Axis$TickMark<T>> getTickMarks();
    Code:
       0: aload_0
       1: getfield      #15                 // Field unmodifiableTickMarks:Ljavafx/collections/ObservableList;
       4: areturn

  public final javafx.geometry.Side getSide();
    Code:
       0: aload_0
       1: getfield      #6                  // Field side:Ljavafx/beans/property/ObjectProperty;
       4: invokevirtual #16                 // Method javafx/beans/property/ObjectProperty.get:()Ljava/lang/Object;
       7: checkcast     #17                 // class javafx/geometry/Side
      10: areturn

  public final void setSide(javafx.geometry.Side);
    Code:
       0: aload_0
       1: getfield      #6                  // Field side:Ljavafx/beans/property/ObjectProperty;
       4: aload_1
       5: invokevirtual #18                 // Method javafx/beans/property/ObjectProperty.set:(Ljava/lang/Object;)V
       8: return

  public final javafx.beans.property.ObjectProperty<javafx.geometry.Side> sideProperty();
    Code:
       0: aload_0
       1: getfield      #6                  // Field side:Ljavafx/beans/property/ObjectProperty;
       4: areturn

  final void setEffectiveOrientation(javafx.geometry.Orientation);
    Code:
       0: aload_0
       1: aload_1
       2: putfield      #19                 // Field effectiveOrientation:Ljavafx/geometry/Orientation;
       5: return

  final javafx.geometry.Side getEffectiveSide();
    Code:
       0: aload_0
       1: invokevirtual #20                 // Method getSide:()Ljavafx/geometry/Side;
       4: astore_1
       5: aload_1
       6: ifnull        43
       9: aload_1
      10: invokevirtual #21                 // Method javafx/geometry/Side.isVertical:()Z
      13: ifeq          26
      16: aload_0
      17: getfield      #19                 // Field effectiveOrientation:Ljavafx/geometry/Orientation;
      20: getstatic     #22                 // Field javafx/geometry/Orientation.HORIZONTAL:Ljavafx/geometry/Orientation;
      23: if_acmpeq     43
      26: aload_1
      27: invokevirtual #23                 // Method javafx/geometry/Side.isHorizontal:()Z
      30: ifeq          63
      33: aload_0
      34: getfield      #19                 // Field effectiveOrientation:Ljavafx/geometry/Orientation;
      37: getstatic     #24                 // Field javafx/geometry/Orientation.VERTICAL:Ljavafx/geometry/Orientation;
      40: if_acmpne     63
      43: aload_0
      44: getfield      #19                 // Field effectiveOrientation:Ljavafx/geometry/Orientation;
      47: getstatic     #24                 // Field javafx/geometry/Orientation.VERTICAL:Ljavafx/geometry/Orientation;
      50: if_acmpne     59
      53: getstatic     #25                 // Field javafx/geometry/Side.LEFT:Ljavafx/geometry/Side;
      56: goto          62
      59: getstatic     #26                 // Field javafx/geometry/Side.BOTTOM:Ljavafx/geometry/Side;
      62: areturn
      63: aload_1
      64: areturn

  public final java.lang.String getLabel();
    Code:
       0: aload_0
       1: getfield      #27                 // Field label:Ljavafx/beans/property/ObjectProperty;
       4: invokevirtual #16                 // Method javafx/beans/property/ObjectProperty.get:()Ljava/lang/Object;
       7: checkcast     #28                 // class java/lang/String
      10: areturn

  public final void setLabel(java.lang.String);
    Code:
       0: aload_0
       1: getfield      #27                 // Field label:Ljavafx/beans/property/ObjectProperty;
       4: aload_1
       5: invokevirtual #18                 // Method javafx/beans/property/ObjectProperty.set:(Ljava/lang/Object;)V
       8: return

  public final javafx.beans.property.ObjectProperty<java.lang.String> labelProperty();
    Code:
       0: aload_0
       1: getfield      #27                 // Field label:Ljavafx/beans/property/ObjectProperty;
       4: areturn

  public final boolean isTickMarkVisible();
    Code:
       0: aload_0
       1: getfield      #2                  // Field tickMarkVisible:Ljavafx/beans/property/BooleanProperty;
       4: invokevirtual #29                 // Method javafx/beans/property/BooleanProperty.get:()Z
       7: ireturn

  public final void setTickMarkVisible(boolean);
    Code:
       0: aload_0
       1: getfield      #2                  // Field tickMarkVisible:Ljavafx/beans/property/BooleanProperty;
       4: iload_1
       5: invokevirtual #30                 // Method javafx/beans/property/BooleanProperty.set:(Z)V
       8: return

  public final javafx.beans.property.BooleanProperty tickMarkVisibleProperty();
    Code:
       0: aload_0
       1: getfield      #2                  // Field tickMarkVisible:Ljavafx/beans/property/BooleanProperty;
       4: areturn

  public final boolean isTickLabelsVisible();
    Code:
       0: aload_0
       1: getfield      #1                  // Field tickLabelsVisible:Ljavafx/beans/property/BooleanProperty;
       4: invokevirtual #29                 // Method javafx/beans/property/BooleanProperty.get:()Z
       7: ireturn

  public final void setTickLabelsVisible(boolean);
    Code:
       0: aload_0
       1: getfield      #1                  // Field tickLabelsVisible:Ljavafx/beans/property/BooleanProperty;
       4: iload_1
       5: invokevirtual #30                 // Method javafx/beans/property/BooleanProperty.set:(Z)V
       8: return

  public final javafx.beans.property.BooleanProperty tickLabelsVisibleProperty();
    Code:
       0: aload_0
       1: getfield      #1                  // Field tickLabelsVisible:Ljavafx/beans/property/BooleanProperty;
       4: areturn

  public final double getTickLength();
    Code:
       0: aload_0
       1: getfield      #7                  // Field tickLength:Ljavafx/beans/property/DoubleProperty;
       4: invokevirtual #31                 // Method javafx/beans/property/DoubleProperty.get:()D
       7: dreturn

  public final void setTickLength(double);
    Code:
       0: aload_0
       1: getfield      #7                  // Field tickLength:Ljavafx/beans/property/DoubleProperty;
       4: dload_1
       5: invokevirtual #32                 // Method javafx/beans/property/DoubleProperty.set:(D)V
       8: return

  public final javafx.beans.property.DoubleProperty tickLengthProperty();
    Code:
       0: aload_0
       1: getfield      #7                  // Field tickLength:Ljavafx/beans/property/DoubleProperty;
       4: areturn

  public final boolean isAutoRanging();
    Code:
       0: aload_0
       1: getfield      #33                 // Field autoRanging:Ljavafx/beans/property/BooleanProperty;
       4: invokevirtual #29                 // Method javafx/beans/property/BooleanProperty.get:()Z
       7: ireturn

  public final void setAutoRanging(boolean);
    Code:
       0: aload_0
       1: getfield      #33                 // Field autoRanging:Ljavafx/beans/property/BooleanProperty;
       4: iload_1
       5: invokevirtual #30                 // Method javafx/beans/property/BooleanProperty.set:(Z)V
       8: return

  public final javafx.beans.property.BooleanProperty autoRangingProperty();
    Code:
       0: aload_0
       1: getfield      #33                 // Field autoRanging:Ljavafx/beans/property/BooleanProperty;
       4: areturn

  public final javafx.scene.text.Font getTickLabelFont();
    Code:
       0: aload_0
       1: getfield      #5                  // Field tickLabelFont:Ljavafx/beans/property/ObjectProperty;
       4: invokevirtual #16                 // Method javafx/beans/property/ObjectProperty.get:()Ljava/lang/Object;
       7: checkcast     #34                 // class javafx/scene/text/Font
      10: areturn

  public final void setTickLabelFont(javafx.scene.text.Font);
    Code:
       0: aload_0
       1: getfield      #5                  // Field tickLabelFont:Ljavafx/beans/property/ObjectProperty;
       4: aload_1
       5: invokevirtual #18                 // Method javafx/beans/property/ObjectProperty.set:(Ljava/lang/Object;)V
       8: return

  public final javafx.beans.property.ObjectProperty<javafx.scene.text.Font> tickLabelFontProperty();
    Code:
       0: aload_0
       1: getfield      #5                  // Field tickLabelFont:Ljavafx/beans/property/ObjectProperty;
       4: areturn

  public final javafx.scene.paint.Paint getTickLabelFill();
    Code:
       0: aload_0
       1: getfield      #4                  // Field tickLabelFill:Ljavafx/beans/property/ObjectProperty;
       4: invokevirtual #16                 // Method javafx/beans/property/ObjectProperty.get:()Ljava/lang/Object;
       7: checkcast     #35                 // class javafx/scene/paint/Paint
      10: areturn

  public final void setTickLabelFill(javafx.scene.paint.Paint);
    Code:
       0: aload_0
       1: getfield      #4                  // Field tickLabelFill:Ljavafx/beans/property/ObjectProperty;
       4: aload_1
       5: invokevirtual #18                 // Method javafx/beans/property/ObjectProperty.set:(Ljava/lang/Object;)V
       8: return

  public final javafx.beans.property.ObjectProperty<javafx.scene.paint.Paint> tickLabelFillProperty();
    Code:
       0: aload_0
       1: getfield      #4                  // Field tickLabelFill:Ljavafx/beans/property/ObjectProperty;
       4: areturn

  public final double getTickLabelGap();
    Code:
       0: aload_0
       1: getfield      #3                  // Field tickLabelGap:Ljavafx/beans/property/DoubleProperty;
       4: invokevirtual #31                 // Method javafx/beans/property/DoubleProperty.get:()D
       7: dreturn

  public final void setTickLabelGap(double);
    Code:
       0: aload_0
       1: getfield      #3                  // Field tickLabelGap:Ljavafx/beans/property/DoubleProperty;
       4: dload_1
       5: invokevirtual #32                 // Method javafx/beans/property/DoubleProperty.set:(D)V
       8: return

  public final javafx.beans.property.DoubleProperty tickLabelGapProperty();
    Code:
       0: aload_0
       1: getfield      #3                  // Field tickLabelGap:Ljavafx/beans/property/DoubleProperty;
       4: areturn

  public final boolean getAnimated();
    Code:
       0: aload_0
       1: getfield      #36                 // Field animated:Ljavafx/beans/property/BooleanProperty;
       4: invokevirtual #29                 // Method javafx/beans/property/BooleanProperty.get:()Z
       7: ireturn

  public final void setAnimated(boolean);
    Code:
       0: aload_0
       1: getfield      #36                 // Field animated:Ljavafx/beans/property/BooleanProperty;
       4: iload_1
       5: invokevirtual #30                 // Method javafx/beans/property/BooleanProperty.set:(Z)V
       8: return

  public final javafx.beans.property.BooleanProperty animatedProperty();
    Code:
       0: aload_0
       1: getfield      #36                 // Field animated:Ljavafx/beans/property/BooleanProperty;
       4: areturn

  public final double getTickLabelRotation();
    Code:
       0: aload_0
       1: getfield      #37                 // Field tickLabelRotation:Ljavafx/beans/property/DoubleProperty;
       4: invokevirtual #38                 // Method javafx/beans/property/DoubleProperty.getValue:()Ljava/lang/Double;
       7: invokevirtual #39                 // Method java/lang/Double.doubleValue:()D
      10: dreturn

  public final void setTickLabelRotation(double);
    Code:
       0: aload_0
       1: getfield      #37                 // Field tickLabelRotation:Ljavafx/beans/property/DoubleProperty;
       4: dload_1
       5: invokestatic  #40                 // Method java/lang/Double.valueOf:(D)Ljava/lang/Double;
       8: invokevirtual #41                 // Method javafx/beans/property/DoubleProperty.setValue:(Ljava/lang/Number;)V
      11: return

  public final javafx.beans.property.DoubleProperty tickLabelRotationProperty();
    Code:
       0: aload_0
       1: getfield      #37                 // Field tickLabelRotation:Ljavafx/beans/property/DoubleProperty;
       4: areturn

  public javafx.scene.chart.Axis();
    Code:
       0: aload_0
       1: invokespecial #42                 // Method javafx/scene/layout/Region."<init>":()V
       4: aload_0
       5: new           #43                 // class javafx/scene/text/Text
       8: dup
       9: invokespecial #44                 // Method javafx/scene/text/Text."<init>":()V
      12: putfield      #45                 // Field measure:Ljavafx/scene/text/Text;
      15: aload_0
      16: ldc2_w        #47                 // double NaNd
      19: putfield      #49                 // Field effectiveTickLabelRotation:D
      22: aload_0
      23: new           #50                 // class javafx/scene/control/Label
      26: dup
      27: invokespecial #51                 // Method javafx/scene/control/Label."<init>":()V
      30: putfield      #10                 // Field axisLabel:Ljavafx/scene/control/Label;
      33: aload_0
      34: new           #52                 // class javafx/scene/shape/Path
      37: dup
      38: invokespecial #53                 // Method javafx/scene/shape/Path."<init>":()V
      41: putfield      #9                  // Field tickMarkPath:Ljavafx/scene/shape/Path;
      44: aload_0
      45: dconst_0
      46: putfield      #54                 // Field oldLength:D
      49: aload_0
      50: iconst_0
      51: putfield      #55                 // Field rangeValid:Z
      54: aload_0
      55: iconst_0
      56: putfield      #56                 // Field measureInvalid:Z
      59: aload_0
      60: iconst_0
      61: putfield      #57                 // Field tickLabelsVisibleInvalid:Z
      64: aload_0
      65: new           #58                 // class java/util/BitSet
      68: dup
      69: invokespecial #59                 // Method java/util/BitSet."<init>":()V
      72: putfield      #60                 // Field labelsToSkip:Ljava/util/BitSet;
      75: aload_0
      76: invokestatic  #61                 // Method javafx/collections/FXCollections.observableArrayList:()Ljavafx/collections/ObservableList;
      79: putfield      #8                  // Field tickMarks:Ljavafx/collections/ObservableList;
      82: aload_0
      83: aload_0
      84: getfield      #8                  // Field tickMarks:Ljavafx/collections/ObservableList;
      87: invokestatic  #62                 // Method javafx/collections/FXCollections.unmodifiableObservableList:(Ljavafx/collections/ObservableList;)Ljavafx/collections/ObservableList;
      90: putfield      #15                 // Field unmodifiableTickMarks:Ljavafx/collections/ObservableList;
      93: aload_0
      94: new           #63                 // class javafx/scene/chart/Axis$1
      97: dup
      98: aload_0
      99: invokespecial #64                 // Method javafx/scene/chart/Axis$1."<init>":(Ljavafx/scene/chart/Axis;)V
     102: putfield      #6                  // Field side:Ljavafx/beans/property/ObjectProperty;
     105: aload_0
     106: new           #65                 // class javafx/scene/chart/Axis$2
     109: dup
     110: aload_0
     111: invokespecial #66                 // Method javafx/scene/chart/Axis$2."<init>":(Ljavafx/scene/chart/Axis;)V
     114: putfield      #27                 // Field label:Ljavafx/beans/property/ObjectProperty;
     117: aload_0
     118: new           #67                 // class javafx/scene/chart/Axis$3
     121: dup
     122: aload_0
     123: iconst_1
     124: invokespecial #68                 // Method javafx/scene/chart/Axis$3."<init>":(Ljavafx/scene/chart/Axis;Z)V
     127: putfield      #2                  // Field tickMarkVisible:Ljavafx/beans/property/BooleanProperty;
     130: aload_0
     131: new           #69                 // class javafx/scene/chart/Axis$4
     134: dup
     135: aload_0
     136: iconst_1
     137: invokespecial #70                 // Method javafx/scene/chart/Axis$4."<init>":(Ljavafx/scene/chart/Axis;Z)V
     140: putfield      #1                  // Field tickLabelsVisible:Ljavafx/beans/property/BooleanProperty;
     143: aload_0
     144: new           #71                 // class javafx/scene/chart/Axis$5
     147: dup
     148: aload_0
     149: ldc2_w        #72                 // double 8.0d
     152: invokespecial #74                 // Method javafx/scene/chart/Axis$5."<init>":(Ljavafx/scene/chart/Axis;D)V
     155: putfield      #7                  // Field tickLength:Ljavafx/beans/property/DoubleProperty;
     158: aload_0
     159: new           #75                 // class javafx/scene/chart/Axis$6
     162: dup
     163: aload_0
     164: iconst_1
     165: invokespecial #76                 // Method javafx/scene/chart/Axis$6."<init>":(Ljavafx/scene/chart/Axis;Z)V
     168: putfield      #33                 // Field autoRanging:Ljavafx/beans/property/BooleanProperty;
     171: aload_0
     172: new           #77                 // class javafx/scene/chart/Axis$7
     175: dup
     176: aload_0
     177: ldc           #78                 // String System
     179: ldc2_w        #72                 // double 8.0d
     182: invokestatic  #79                 // Method javafx/scene/text/Font.font:(Ljava/lang/String;D)Ljavafx/scene/text/Font;
     185: invokespecial #80                 // Method javafx/scene/chart/Axis$7."<init>":(Ljavafx/scene/chart/Axis;Ljavafx/scene/text/Font;)V
     188: putfield      #5                  // Field tickLabelFont:Ljavafx/beans/property/ObjectProperty;
     191: aload_0
     192: new           #81                 // class javafx/scene/chart/Axis$8
     195: dup
     196: aload_0
     197: getstatic     #82                 // Field javafx/scene/paint/Color.BLACK:Ljavafx/scene/paint/Color;
     200: invokespecial #83                 // Method javafx/scene/chart/Axis$8."<init>":(Ljavafx/scene/chart/Axis;Ljavafx/scene/paint/Paint;)V
     203: putfield      #4                  // Field tickLabelFill:Ljavafx/beans/property/ObjectProperty;
     206: aload_0
     207: new           #84                 // class javafx/scene/chart/Axis$9
     210: dup
     211: aload_0
     212: ldc2_w        #85                 // double 3.0d
     215: invokespecial #87                 // Method javafx/scene/chart/Axis$9."<init>":(Ljavafx/scene/chart/Axis;D)V
     218: putfield      #3                  // Field tickLabelGap:Ljavafx/beans/property/DoubleProperty;
     221: aload_0
     222: new           #88                 // class javafx/beans/property/SimpleBooleanProperty
     225: dup
     226: aload_0
     227: ldc           #89                 // String animated
     229: iconst_1
     230: invokespecial #90                 // Method javafx/beans/property/SimpleBooleanProperty."<init>":(Ljava/lang/Object;Ljava/lang/String;Z)V
     233: putfield      #36                 // Field animated:Ljavafx/beans/property/BooleanProperty;
     236: aload_0
     237: new           #91                 // class javafx/scene/chart/Axis$10
     240: dup
     241: aload_0
     242: dconst_0
     243: invokespecial #92                 // Method javafx/scene/chart/Axis$10."<init>":(Ljavafx/scene/chart/Axis;D)V
     246: putfield      #37                 // Field tickLabelRotation:Ljavafx/beans/property/DoubleProperty;
     249: aload_0
     250: invokevirtual #93                 // Method getStyleClass:()Ljavafx/collections/ObservableList;
     253: iconst_1
     254: anewarray     #28                 // class java/lang/String
     257: dup
     258: iconst_0
     259: ldc           #94                 // String axis
     261: aastore
     262: invokeinterface #95,  2           // InterfaceMethod javafx/collections/ObservableList.setAll:([Ljava/lang/Object;)Z
     267: pop
     268: aload_0
     269: getfield      #10                 // Field axisLabel:Ljavafx/scene/control/Label;
     272: invokevirtual #96                 // Method javafx/scene/control/Label.getStyleClass:()Ljavafx/collections/ObservableList;
     275: ldc           #97                 // String axis-label
     277: invokeinterface #98,  2           // InterfaceMethod javafx/collections/ObservableList.add:(Ljava/lang/Object;)Z
     282: pop
     283: aload_0
     284: getfield      #10                 // Field axisLabel:Ljavafx/scene/control/Label;
     287: getstatic     #99                 // Field javafx/geometry/Pos.CENTER:Ljavafx/geometry/Pos;
     290: invokevirtual #100                // Method javafx/scene/control/Label.setAlignment:(Ljavafx/geometry/Pos;)V
     293: aload_0
     294: getfield      #9                  // Field tickMarkPath:Ljavafx/scene/shape/Path;
     297: invokevirtual #101                // Method javafx/scene/shape/Path.getStyleClass:()Ljavafx/collections/ObservableList;
     300: ldc           #102                // String axis-tick-mark
     302: invokeinterface #98,  2           // InterfaceMethod javafx/collections/ObservableList.add:(Ljava/lang/Object;)Z
     307: pop
     308: aload_0
     309: invokevirtual #103                // Method getChildren:()Ljavafx/collections/ObservableList;
     312: iconst_2
     313: anewarray     #104                // class javafx/scene/Node
     316: dup
     317: iconst_0
     318: aload_0
     319: getfield      #10                 // Field axisLabel:Ljavafx/scene/control/Label;
     322: aastore
     323: dup
     324: iconst_1
     325: aload_0
     326: getfield      #9                  // Field tickMarkPath:Ljavafx/scene/shape/Path;
     329: aastore
     330: invokeinterface #105,  2          // InterfaceMethod javafx/collections/ObservableList.addAll:([Ljava/lang/Object;)Z
     335: pop
     336: return

  protected final boolean isRangeValid();
    Code:
       0: aload_0
       1: getfield      #55                 // Field rangeValid:Z
       4: ireturn

  protected final void invalidateRange();
    Code:
       0: aload_0
       1: iconst_0
       2: putfield      #55                 // Field rangeValid:Z
       5: return

  protected final boolean shouldAnimate();
    Code:
       0: aload_0
       1: invokevirtual #106                // Method getAnimated:()Z
       4: ifeq          18
       7: aload_0
       8: invokestatic  #107                // Method com/sun/javafx/scene/NodeHelper.isTreeShowing:(Ljavafx/scene/Node;)Z
      11: ifeq          18
      14: iconst_1
      15: goto          19
      18: iconst_0
      19: ireturn

  public void requestLayout();
    Code:
       0: return

  public void requestAxisLayout();
    Code:
       0: aload_0
       1: invokespecial #108                // Method javafx/scene/layout/Region.requestLayout:()V
       4: return

  public void invalidateRange(java.util.List<T>);
    Code:
       0: aload_0
       1: invokevirtual #109                // Method invalidateRange:()V
       4: aload_0
       5: invokevirtual #110                // Method requestAxisLayout:()V
       8: return

  protected abstract java.lang.Object autoRange(double);

  protected abstract void setRange(java.lang.Object, boolean);

  protected abstract java.lang.Object getRange();

  public abstract double getZeroPosition();

  public abstract double getDisplayPosition(T);

  public abstract T getValueForDisplay(double);

  public abstract boolean isValueOnAxis(T);

  public abstract double toNumericValue(T);

  public abstract T toRealValue(double);

  protected abstract java.util.List<T> calculateTickValues(double, java.lang.Object);

  protected double computePrefHeight(double);
    Code:
       0: aload_0
       1: invokevirtual #111                // Method getEffectiveSide:()Ljavafx/geometry/Side;
       4: astore_3
       5: aload_3
       6: invokevirtual #21                 // Method javafx/geometry/Side.isVertical:()Z
       9: ifeq          16
      12: ldc2_w        #112                // double 100.0d
      15: dreturn
      16: aload_0
      17: dload_1
      18: invokevirtual #114                // Method autoRange:(D)Ljava/lang/Object;
      21: astore        4
      23: dconst_0
      24: dstore        5
      26: aload_0
      27: invokevirtual #115                // Method isTickLabelsVisible:()Z
      30: ifeq          91
      33: aload_0
      34: dload_1
      35: aload         4
      37: invokevirtual #116                // Method calculateTickValues:(DLjava/lang/Object;)Ljava/util/List;
      40: astore        7
      42: aload         7
      44: invokeinterface #117,  1          // InterfaceMethod java/util/List.iterator:()Ljava/util/Iterator;
      49: astore        8
      51: aload         8
      53: invokeinterface #118,  1          // InterfaceMethod java/util/Iterator.hasNext:()Z
      58: ifeq          91
      61: aload         8
      63: invokeinterface #119,  1          // InterfaceMethod java/util/Iterator.next:()Ljava/lang/Object;
      68: astore        9
      70: dload         5
      72: aload_0
      73: aload         9
      75: aload         4
      77: invokevirtual #120                // Method measureTickMarkSize:(Ljava/lang/Object;Ljava/lang/Object;)Ljavafx/geometry/Dimension2D;
      80: invokevirtual #121                // Method javafx/geometry/Dimension2D.getHeight:()D
      83: invokestatic  #122                // Method java/lang/Math.max:(DD)D
      86: dstore        5
      88: goto          51
      91: aload_0
      92: invokevirtual #123                // Method isTickMarkVisible:()Z
      95: ifeq          118
      98: aload_0
      99: invokevirtual #124                // Method getTickLength:()D
     102: dconst_0
     103: dcmpl
     104: ifle          114
     107: aload_0
     108: invokevirtual #124                // Method getTickLength:()D
     111: goto          119
     114: dconst_0
     115: goto          119
     118: dconst_0
     119: dstore        7
     121: aload_0
     122: getfield      #10                 // Field axisLabel:Ljavafx/scene/control/Label;
     125: invokevirtual #125                // Method javafx/scene/control/Label.getText:()Ljava/lang/String;
     128: ifnull        144
     131: aload_0
     132: getfield      #10                 // Field axisLabel:Ljavafx/scene/control/Label;
     135: invokevirtual #125                // Method javafx/scene/control/Label.getText:()Ljava/lang/String;
     138: invokevirtual #126                // Method java/lang/String.length:()I
     141: ifne          148
     144: dconst_0
     145: goto          158
     148: aload_0
     149: getfield      #10                 // Field axisLabel:Ljavafx/scene/control/Label;
     152: ldc2_w        #127                // double -1.0d
     155: invokevirtual #129                // Method javafx/scene/control/Label.prefHeight:(D)D
     158: dstore        9
     160: dload         5
     162: aload_0
     163: invokevirtual #130                // Method getTickLabelGap:()D
     166: dadd
     167: dload         7
     169: dadd
     170: dload         9
     172: dadd
     173: dreturn

  protected double computePrefWidth(double);
    Code:
       0: aload_0
       1: invokevirtual #111                // Method getEffectiveSide:()Ljavafx/geometry/Side;
       4: astore_3
       5: aload_3
       6: invokevirtual #21                 // Method javafx/geometry/Side.isVertical:()Z
       9: ifeq          170
      12: aload_0
      13: dload_1
      14: invokevirtual #114                // Method autoRange:(D)Ljava/lang/Object;
      17: astore        4
      19: dconst_0
      20: dstore        5
      22: aload_0
      23: invokevirtual #115                // Method isTickLabelsVisible:()Z
      26: ifeq          87
      29: aload_0
      30: dload_1
      31: aload         4
      33: invokevirtual #116                // Method calculateTickValues:(DLjava/lang/Object;)Ljava/util/List;
      36: astore        7
      38: aload         7
      40: invokeinterface #117,  1          // InterfaceMethod java/util/List.iterator:()Ljava/util/Iterator;
      45: astore        8
      47: aload         8
      49: invokeinterface #118,  1          // InterfaceMethod java/util/Iterator.hasNext:()Z
      54: ifeq          87
      57: aload         8
      59: invokeinterface #119,  1          // InterfaceMethod java/util/Iterator.next:()Ljava/lang/Object;
      64: astore        9
      66: dload         5
      68: aload_0
      69: aload         9
      71: aload         4
      73: invokevirtual #120                // Method measureTickMarkSize:(Ljava/lang/Object;Ljava/lang/Object;)Ljavafx/geometry/Dimension2D;
      76: invokevirtual #131                // Method javafx/geometry/Dimension2D.getWidth:()D
      79: invokestatic  #122                // Method java/lang/Math.max:(DD)D
      82: dstore        5
      84: goto          47
      87: aload_0
      88: invokevirtual #123                // Method isTickMarkVisible:()Z
      91: ifeq          114
      94: aload_0
      95: invokevirtual #124                // Method getTickLength:()D
      98: dconst_0
      99: dcmpl
     100: ifle          110
     103: aload_0
     104: invokevirtual #124                // Method getTickLength:()D
     107: goto          115
     110: dconst_0
     111: goto          115
     114: dconst_0
     115: dstore        7
     117: aload_0
     118: getfield      #10                 // Field axisLabel:Ljavafx/scene/control/Label;
     121: invokevirtual #125                // Method javafx/scene/control/Label.getText:()Ljava/lang/String;
     124: ifnull        140
     127: aload_0
     128: getfield      #10                 // Field axisLabel:Ljavafx/scene/control/Label;
     131: invokevirtual #125                // Method javafx/scene/control/Label.getText:()Ljava/lang/String;
     134: invokevirtual #126                // Method java/lang/String.length:()I
     137: ifne          144
     140: dconst_0
     141: goto          154
     144: aload_0
     145: getfield      #10                 // Field axisLabel:Ljavafx/scene/control/Label;
     148: ldc2_w        #127                // double -1.0d
     151: invokevirtual #129                // Method javafx/scene/control/Label.prefHeight:(D)D
     154: dstore        9
     156: dload         5
     158: aload_0
     159: invokevirtual #130                // Method getTickLabelGap:()D
     162: dadd
     163: dload         7
     165: dadd
     166: dload         9
     168: dadd
     169: dreturn
     170: ldc2_w        #112                // double 100.0d
     173: dreturn

  protected void tickMarksUpdated();
    Code:
       0: return

  protected void layoutChildren();
    Code:
       0: aload_0
       1: getfield      #54                 // Field oldLength:D
       4: dconst_0
       5: dcmpl
       6: ifne          13
       9: iconst_1
      10: goto          14
      13: iconst_0
      14: istore_1
      15: aload_0
      16: invokevirtual #111                // Method getEffectiveSide:()Ljavafx/geometry/Side;
      19: astore_2
      20: aload_2
      21: invokevirtual #21                 // Method javafx/geometry/Side.isVertical:()Z
      24: ifeq          34
      27: aload_0
      28: invokevirtual #132                // Method getHeight:()D
      31: goto          38
      34: aload_0
      35: invokevirtual #133                // Method getWidth:()D
      38: dstore_3
      39: aload_0
      40: invokevirtual #134                // Method isRangeValid:()Z
      43: ifne          50
      46: iconst_1
      47: goto          51
      50: iconst_0
      51: istore        5
      53: aload_0
      54: getfield      #54                 // Field oldLength:D
      57: dload_3
      58: dcmpl
      59: ifeq          66
      62: iconst_1
      63: goto          67
      66: iconst_0
      67: istore        6
      69: iload         6
      71: ifne          79
      74: iload         5
      76: ifeq          456
      79: aload_0
      80: invokevirtual #135                // Method isAutoRanging:()Z
      83: ifeq          130
      86: aload_0
      87: dload_3
      88: invokevirtual #114                // Method autoRange:(D)Ljava/lang/Object;
      91: astore        7
      93: aload_0
      94: aload         7
      96: aload_0
      97: invokevirtual #106                // Method getAnimated:()Z
     100: ifeq          123
     103: iload_1
     104: ifne          123
     107: aload_0
     108: invokestatic  #107                // Method com/sun/javafx/scene/NodeHelper.isTreeShowing:(Ljavafx/scene/Node;)Z
     111: ifeq          123
     114: iload         5
     116: ifeq          123
     119: iconst_1
     120: goto          124
     123: iconst_0
     124: invokevirtual #136                // Method setRange:(Ljava/lang/Object;Z)V
     127: goto          136
     130: aload_0
     131: invokevirtual #137                // Method getRange:()Ljava/lang/Object;
     134: astore        7
     136: aload_0
     137: dload_3
     138: aload         7
     140: invokevirtual #116                // Method calculateTickValues:(DLjava/lang/Object;)Ljava/util/List;
     143: astore        8
     145: aload_0
     146: getfield      #8                  // Field tickMarks:Ljavafx/collections/ObservableList;
     149: invokeinterface #138,  1          // InterfaceMethod javafx/collections/ObservableList.iterator:()Ljava/util/Iterator;
     154: astore        9
     156: aload         9
     158: invokeinterface #118,  1          // InterfaceMethod java/util/Iterator.hasNext:()Z
     163: ifeq          261
     166: aload         9
     168: invokeinterface #119,  1          // InterfaceMethod java/util/Iterator.next:()Ljava/lang/Object;
     173: checkcast     #139                // class javafx/scene/chart/Axis$TickMark
     176: astore        10
     178: aload         10
     180: astore        11
     182: aload_0
     183: invokevirtual #140                // Method shouldAnimate:()Z
     186: ifeq          236
     189: new           #141                // class javafx/animation/FadeTransition
     192: dup
     193: ldc2_w        #142                // double 250.0d
     196: invokestatic  #144                // Method javafx/util/Duration.millis:(D)Ljavafx/util/Duration;
     199: aload         10
     201: getfield      #145                // Field javafx/scene/chart/Axis$TickMark.textNode:Ljavafx/scene/text/Text;
     204: invokespecial #146                // Method javafx/animation/FadeTransition."<init>":(Ljavafx/util/Duration;Ljavafx/scene/Node;)V
     207: astore        12
     209: aload         12
     211: dconst_0
     212: invokevirtual #147                // Method javafx/animation/FadeTransition.setToValue:(D)V
     215: aload         12
     217: aload_0
     218: aload         11
     220: invokedynamic #148,  0            // InvokeDynamic #0:handle:(Ljavafx/scene/chart/Axis;Ljavafx/scene/chart/Axis$TickMark;)Ljavafx/event/EventHandler;
     225: invokevirtual #149                // Method javafx/animation/FadeTransition.setOnFinished:(Ljavafx/event/EventHandler;)V
     228: aload         12
     230: invokevirtual #150                // Method javafx/animation/FadeTransition.play:()V
     233: goto          251
     236: aload_0
     237: invokevirtual #103                // Method getChildren:()Ljavafx/collections/ObservableList;
     240: aload         11
     242: getfield      #145                // Field javafx/scene/chart/Axis$TickMark.textNode:Ljavafx/scene/text/Text;
     245: invokeinterface #151,  2          // InterfaceMethod javafx/collections/ObservableList.remove:(Ljava/lang/Object;)Z
     250: pop
     251: aload         9
     253: invokeinterface #152,  1          // InterfaceMethod java/util/Iterator.remove:()V
     258: goto          156
     261: aload         8
     263: invokeinterface #117,  1          // InterfaceMethod java/util/List.iterator:()Ljava/util/Iterator;
     268: astore        10
     270: aload         10
     272: invokeinterface #118,  1          // InterfaceMethod java/util/Iterator.hasNext:()Z
     277: ifeq          442
     280: aload         10
     282: invokeinterface #119,  1          // InterfaceMethod java/util/Iterator.next:()Ljava/lang/Object;
     287: astore        11
     289: new           #139                // class javafx/scene/chart/Axis$TickMark
     292: dup
     293: invokespecial #153                // Method javafx/scene/chart/Axis$TickMark."<init>":()V
     296: astore        12
     298: aload         12
     300: aload         11
     302: invokevirtual #154                // Method javafx/scene/chart/Axis$TickMark.setValue:(Ljava/lang/Object;)V
     305: aload         12
     307: getfield      #145                // Field javafx/scene/chart/Axis$TickMark.textNode:Ljavafx/scene/text/Text;
     310: aload_0
     311: aload         11
     313: invokevirtual #155                // Method getTickMarkLabel:(Ljava/lang/Object;)Ljava/lang/String;
     316: invokevirtual #156                // Method javafx/scene/text/Text.setText:(Ljava/lang/String;)V
     319: aload         12
     321: getfield      #145                // Field javafx/scene/chart/Axis$TickMark.textNode:Ljavafx/scene/text/Text;
     324: aload_0
     325: invokevirtual #157                // Method getTickLabelFont:()Ljavafx/scene/text/Font;
     328: invokevirtual #158                // Method javafx/scene/text/Text.setFont:(Ljavafx/scene/text/Font;)V
     331: aload         12
     333: getfield      #145                // Field javafx/scene/chart/Axis$TickMark.textNode:Ljavafx/scene/text/Text;
     336: aload_0
     337: invokevirtual #159                // Method getTickLabelFill:()Ljavafx/scene/paint/Paint;
     340: invokevirtual #160                // Method javafx/scene/text/Text.setFill:(Ljavafx/scene/paint/Paint;)V
     343: aload         12
     345: aload_0
     346: invokevirtual #115                // Method isTickLabelsVisible:()Z
     349: invokevirtual #161                // Method javafx/scene/chart/Axis$TickMark.setTextVisible:(Z)V
     352: aload_0
     353: invokevirtual #140                // Method shouldAnimate:()Z
     356: ifeq          368
     359: aload         12
     361: getfield      #145                // Field javafx/scene/chart/Axis$TickMark.textNode:Ljavafx/scene/text/Text;
     364: dconst_0
     365: invokevirtual #162                // Method javafx/scene/text/Text.setOpacity:(D)V
     368: aload_0
     369: invokevirtual #103                // Method getChildren:()Ljavafx/collections/ObservableList;
     372: aload         12
     374: getfield      #145                // Field javafx/scene/chart/Axis$TickMark.textNode:Ljavafx/scene/text/Text;
     377: invokeinterface #98,  2           // InterfaceMethod javafx/collections/ObservableList.add:(Ljava/lang/Object;)Z
     382: pop
     383: aload_0
     384: getfield      #8                  // Field tickMarks:Ljavafx/collections/ObservableList;
     387: aload         12
     389: invokeinterface #98,  2           // InterfaceMethod javafx/collections/ObservableList.add:(Ljava/lang/Object;)Z
     394: pop
     395: aload_0
     396: invokevirtual #140                // Method shouldAnimate:()Z
     399: ifeq          439
     402: new           #141                // class javafx/animation/FadeTransition
     405: dup
     406: ldc2_w        #163                // double 750.0d
     409: invokestatic  #144                // Method javafx/util/Duration.millis:(D)Ljavafx/util/Duration;
     412: aload         12
     414: getfield      #145                // Field javafx/scene/chart/Axis$TickMark.textNode:Ljavafx/scene/text/Text;
     417: invokespecial #146                // Method javafx/animation/FadeTransition."<init>":(Ljavafx/util/Duration;Ljavafx/scene/Node;)V
     420: astore        13
     422: aload         13
     424: dconst_0
     425: invokevirtual #165                // Method javafx/animation/FadeTransition.setFromValue:(D)V
     428: aload         13
     430: dconst_1
     431: invokevirtual #147                // Method javafx/animation/FadeTransition.setToValue:(D)V
     434: aload         13
     436: invokevirtual #150                // Method javafx/animation/FadeTransition.play:()V
     439: goto          270
     442: aload_0
     443: invokevirtual #166                // Method tickMarksUpdated:()V
     446: aload_0
     447: dload_3
     448: putfield      #54                 // Field oldLength:D
     451: aload_0
     452: iconst_1
     453: putfield      #55                 // Field rangeValid:Z
     456: iload         6
     458: ifne          480
     461: iload         5
     463: ifne          480
     466: aload_0
     467: getfield      #56                 // Field measureInvalid:Z
     470: ifne          480
     473: aload_0
     474: getfield      #57                 // Field tickLabelsVisibleInvalid:Z
     477: ifeq          846
     480: aload_0
     481: iconst_0
     482: putfield      #56                 // Field measureInvalid:Z
     485: aload_0
     486: iconst_0
     487: putfield      #57                 // Field tickLabelsVisibleInvalid:Z
     490: aload_0
     491: getfield      #60                 // Field labelsToSkip:Ljava/util/BitSet;
     494: invokevirtual #167                // Method java/util/BitSet.clear:()V
     497: iconst_0
     498: istore        7
     500: dconst_0
     501: dstore        8
     503: dconst_0
     504: dstore        10
     506: aload_0
     507: getfield      #8                  // Field tickMarks:Ljavafx/collections/ObservableList;
     510: invokeinterface #138,  1          // InterfaceMethod javafx/collections/ObservableList.iterator:()Ljava/util/Iterator;
     515: astore        12
     517: aload         12
     519: invokeinterface #118,  1          // InterfaceMethod java/util/Iterator.hasNext:()Z
     524: ifeq          596
     527: aload         12
     529: invokeinterface #119,  1          // InterfaceMethod java/util/Iterator.next:()Ljava/lang/Object;
     534: checkcast     #139                // class javafx/scene/chart/Axis$TickMark
     537: astore        13
     539: aload         13
     541: aload_0
     542: aload         13
     544: invokevirtual #168                // Method javafx/scene/chart/Axis$TickMark.getValue:()Ljava/lang/Object;
     547: invokevirtual #169                // Method getDisplayPosition:(Ljava/lang/Object;)D
     550: invokevirtual #170                // Method javafx/scene/chart/Axis$TickMark.setPosition:(D)V
     553: aload         13
     555: invokevirtual #171                // Method javafx/scene/chart/Axis$TickMark.isTextVisible:()Z
     558: ifeq          593
     561: aload_0
     562: aload         13
     564: invokevirtual #168                // Method javafx/scene/chart/Axis$TickMark.getValue:()Ljava/lang/Object;
     567: aload_2
     568: invokespecial #172                // Method measureTickMarkSize:(Ljava/lang/Object;Ljavafx/geometry/Side;)D
     571: dstore        14
     573: dload         8
     575: dload         14
     577: dadd
     578: dstore        8
     580: dload         10
     582: dload         14
     584: invokestatic  #122                // Method java/lang/Math.max:(DD)D
     587: invokestatic  #173                // Method java/lang/Math.round:(D)J
     590: l2d
     591: dstore        10
     593: goto          517
     596: dload         10
     598: dconst_0
     599: dcmpl
     600: ifle          630
     603: dload_3
     604: dload         8
     606: dcmpg
     607: ifge          630
     610: aload_0
     611: getfield      #8                  // Field tickMarks:Ljavafx/collections/ObservableList;
     614: invokeinterface #174,  1          // InterfaceMethod javafx/collections/ObservableList.size:()I
     619: i2d
     620: dload         10
     622: dmul
     623: dload_3
     624: ddiv
     625: d2i
     626: iconst_1
     627: iadd
     628: istore        7
     630: iload         7
     632: ifle          703
     635: iconst_0
     636: istore        12
     638: aload_0
     639: getfield      #8                  // Field tickMarks:Ljavafx/collections/ObservableList;
     642: invokeinterface #138,  1          // InterfaceMethod javafx/collections/ObservableList.iterator:()Ljava/util/Iterator;
     647: astore        13
     649: aload         13
     651: invokeinterface #118,  1          // InterfaceMethod java/util/Iterator.hasNext:()Z
     656: ifeq          703
     659: aload         13
     661: invokeinterface #119,  1          // InterfaceMethod java/util/Iterator.next:()Ljava/lang/Object;
     666: checkcast     #139                // class javafx/scene/chart/Axis$TickMark
     669: astore        14
     671: aload         14
     673: invokevirtual #171                // Method javafx/scene/chart/Axis$TickMark.isTextVisible:()Z
     676: ifeq          700
     679: aload         14
     681: iload         12
     683: iinc          12, 1
     686: iload         7
     688: irem
     689: ifne          696
     692: iconst_1
     693: goto          697
     696: iconst_0
     697: invokevirtual #161                // Method javafx/scene/chart/Axis$TickMark.setTextVisible:(Z)V
     700: goto          649
     703: aload_0
     704: getfield      #8                  // Field tickMarks:Ljavafx/collections/ObservableList;
     707: invokeinterface #174,  1          // InterfaceMethod javafx/collections/ObservableList.size:()I
     712: iconst_2
     713: if_icmple     840
     716: aload_0
     717: getfield      #8                  // Field tickMarks:Ljavafx/collections/ObservableList;
     720: iconst_0
     721: invokeinterface #175,  2          // InterfaceMethod javafx/collections/ObservableList.get:(I)Ljava/lang/Object;
     726: checkcast     #139                // class javafx/scene/chart/Axis$TickMark
     729: astore        12
     731: aload_0
     732: getfield      #8                  // Field tickMarks:Ljavafx/collections/ObservableList;
     735: iconst_1
     736: invokeinterface #175,  2          // InterfaceMethod javafx/collections/ObservableList.get:(I)Ljava/lang/Object;
     741: checkcast     #139                // class javafx/scene/chart/Axis$TickMark
     744: astore        13
     746: aload_0
     747: aload_2
     748: aload         12
     750: aload         13
     752: aload_0
     753: invokevirtual #130                // Method getTickLabelGap:()D
     756: invokespecial #176                // Method isTickLabelsOverlap:(Ljavafx/geometry/Side;Ljavafx/scene/chart/Axis$TickMark;Ljavafx/scene/chart/Axis$TickMark;D)Z
     759: ifeq          768
     762: aload         13
     764: iconst_0
     765: invokevirtual #161                // Method javafx/scene/chart/Axis$TickMark.setTextVisible:(Z)V
     768: aload_0
     769: getfield      #8                  // Field tickMarks:Ljavafx/collections/ObservableList;
     772: aload_0
     773: getfield      #8                  // Field tickMarks:Ljavafx/collections/ObservableList;
     776: invokeinterface #174,  1          // InterfaceMethod javafx/collections/ObservableList.size:()I
     781: iconst_2
     782: isub
     783: invokeinterface #175,  2          // InterfaceMethod javafx/collections/ObservableList.get:(I)Ljava/lang/Object;
     788: checkcast     #139                // class javafx/scene/chart/Axis$TickMark
     791: astore        12
     793: aload_0
     794: getfield      #8                  // Field tickMarks:Ljavafx/collections/ObservableList;
     797: aload_0
     798: getfield      #8                  // Field tickMarks:Ljavafx/collections/ObservableList;
     801: invokeinterface #174,  1          // InterfaceMethod javafx/collections/ObservableList.size:()I
     806: iconst_1
     807: isub
     808: invokeinterface #175,  2          // InterfaceMethod javafx/collections/ObservableList.get:(I)Ljava/lang/Object;
     813: checkcast     #139                // class javafx/scene/chart/Axis$TickMark
     816: astore        13
     818: aload_0
     819: aload_2
     820: aload         12
     822: aload         13
     824: aload_0
     825: invokevirtual #130                // Method getTickLabelGap:()D
     828: invokespecial #176                // Method isTickLabelsOverlap:(Ljavafx/geometry/Side;Ljavafx/scene/chart/Axis$TickMark;Ljavafx/scene/chart/Axis$TickMark;D)Z
     831: ifeq          840
     834: aload         12
     836: iconst_0
     837: invokevirtual #161                // Method javafx/scene/chart/Axis$TickMark.setTextVisible:(Z)V
     840: aload_0
     841: aload_2
     842: dload_3
     843: invokespecial #177                // Method updateTickMarks:(Ljavafx/geometry/Side;D)V
     846: return

  private void updateTickMarks(javafx.geometry.Side, double);
    Code:
       0: aload_0
       1: getfield      #9                  // Field tickMarkPath:Ljavafx/scene/shape/Path;
       4: invokevirtual #178                // Method javafx/scene/shape/Path.getElements:()Ljavafx/collections/ObservableList;
       7: invokeinterface #179,  1          // InterfaceMethod javafx/collections/ObservableList.clear:()V
      12: aload_0
      13: invokevirtual #133                // Method getWidth:()D
      16: dstore        4
      18: aload_0
      19: invokevirtual #132                // Method getHeight:()D
      22: dstore        6
      24: aload_0
      25: invokevirtual #123                // Method isTickMarkVisible:()Z
      28: ifeq          47
      31: aload_0
      32: invokevirtual #124                // Method getTickLength:()D
      35: dconst_0
      36: dcmpl
      37: ifle          47
      40: aload_0
      41: invokevirtual #124                // Method getTickLength:()D
      44: goto          48
      47: dconst_0
      48: dstore        8
      50: aload_0
      51: invokevirtual #180                // Method getEffectiveTickLabelRotation:()D
      54: dstore        10
      56: getstatic     #25                 // Field javafx/geometry/Side.LEFT:Ljavafx/geometry/Side;
      59: aload_1
      60: invokevirtual #181                // Method javafx/geometry/Side.equals:(Ljava/lang/Object;)Z
      63: ifeq          265
      66: aload_0
      67: getfield      #9                  // Field tickMarkPath:Ljavafx/scene/shape/Path;
      70: ldc2_w        #182                // double -0.5d
      73: invokevirtual #184                // Method javafx/scene/shape/Path.setLayoutX:(D)V
      76: aload_0
      77: getfield      #9                  // Field tickMarkPath:Ljavafx/scene/shape/Path;
      80: ldc2_w        #185                // double 0.5d
      83: invokevirtual #187                // Method javafx/scene/shape/Path.setLayoutY:(D)V
      86: aload_0
      87: invokevirtual #188                // Method getLabel:()Ljava/lang/String;
      90: ifnull        175
      93: aload_0
      94: getfield      #10                 // Field axisLabel:Ljavafx/scene/control/Label;
      97: invokevirtual #189                // Method javafx/scene/control/Label.getTransforms:()Ljavafx/collections/ObservableList;
     100: iconst_2
     101: anewarray     #190                // class javafx/scene/transform/Transform
     104: dup
     105: iconst_0
     106: new           #191                // class javafx/scene/transform/Translate
     109: dup
     110: dconst_0
     111: dload         6
     113: invokespecial #192                // Method javafx/scene/transform/Translate."<init>":(DD)V
     116: aastore
     117: dup
     118: iconst_1
     119: new           #193                // class javafx/scene/transform/Rotate
     122: dup
     123: ldc2_w        #194                // double -90.0d
     126: dconst_0
     127: dconst_0
     128: invokespecial #196                // Method javafx/scene/transform/Rotate."<init>":(DDD)V
     131: aastore
     132: invokeinterface #95,  2           // InterfaceMethod javafx/collections/ObservableList.setAll:([Ljava/lang/Object;)Z
     137: pop
     138: aload_0
     139: getfield      #10                 // Field axisLabel:Ljavafx/scene/control/Label;
     142: dconst_0
     143: invokevirtual #197                // Method javafx/scene/control/Label.setLayoutX:(D)V
     146: aload_0
     147: getfield      #10                 // Field axisLabel:Ljavafx/scene/control/Label;
     150: dconst_0
     151: invokevirtual #198                // Method javafx/scene/control/Label.setLayoutY:(D)V
     154: aload_0
     155: getfield      #10                 // Field axisLabel:Ljavafx/scene/control/Label;
     158: dload         6
     160: aload_0
     161: getfield      #10                 // Field axisLabel:Ljavafx/scene/control/Label;
     164: dload         4
     166: invokevirtual #129                // Method javafx/scene/control/Label.prefHeight:(D)D
     169: invokestatic  #199                // Method java/lang/Math.ceil:(D)D
     172: invokevirtual #200                // Method javafx/scene/control/Label.resize:(DD)V
     175: aload_0
     176: getfield      #8                  // Field tickMarks:Ljavafx/collections/ObservableList;
     179: invokeinterface #138,  1          // InterfaceMethod javafx/collections/ObservableList.iterator:()Ljava/util/Iterator;
     184: astore        12
     186: aload         12
     188: invokeinterface #118,  1          // InterfaceMethod java/util/Iterator.hasNext:()Z
     193: ifeq          262
     196: aload         12
     198: invokeinterface #119,  1          // InterfaceMethod java/util/Iterator.next:()Ljava/lang/Object;
     203: checkcast     #139                // class javafx/scene/chart/Axis$TickMark
     206: astore        13
     208: aload_0
     209: aload         13
     211: getfield      #145                // Field javafx/scene/chart/Axis$TickMark.textNode:Ljavafx/scene/text/Text;
     214: dload         4
     216: aload_0
     217: invokevirtual #130                // Method getTickLabelGap:()D
     220: dsub
     221: dload         8
     223: dsub
     224: aload         13
     226: invokevirtual #201                // Method javafx/scene/chart/Axis$TickMark.getPosition:()D
     229: dload         10
     231: aload_1
     232: invokespecial #202                // Method positionTextNode:(Ljavafx/scene/text/Text;DDDLjavafx/geometry/Side;)V
     235: aload_0
     236: aload         13
     238: dload_2
     239: dload         4
     241: dload         8
     243: dsub
     244: aload         13
     246: invokevirtual #201                // Method javafx/scene/chart/Axis$TickMark.getPosition:()D
     249: dload         4
     251: aload         13
     253: invokevirtual #201                // Method javafx/scene/chart/Axis$TickMark.getPosition:()D
     256: invokespecial #203                // Method updateTickMark:(Ljavafx/scene/chart/Axis$TickMark;DDDDD)V
     259: goto          186
     262: goto          815
     265: getstatic     #204                // Field javafx/geometry/Side.RIGHT:Ljavafx/geometry/Side;
     268: aload_1
     269: invokevirtual #181                // Method javafx/geometry/Side.equals:(Ljava/lang/Object;)Z
     272: ifeq          475
     275: aload_0
     276: getfield      #9                  // Field tickMarkPath:Ljavafx/scene/shape/Path;
     279: ldc2_w        #185                // double 0.5d
     282: invokevirtual #184                // Method javafx/scene/shape/Path.setLayoutX:(D)V
     285: aload_0
     286: getfield      #9                  // Field tickMarkPath:Ljavafx/scene/shape/Path;
     289: ldc2_w        #185                // double 0.5d
     292: invokevirtual #187                // Method javafx/scene/shape/Path.setLayoutY:(D)V
     295: aload_0
     296: invokevirtual #188                // Method getLabel:()Ljava/lang/String;
     299: ifnull        392
     302: aload_0
     303: getfield      #10                 // Field axisLabel:Ljavafx/scene/control/Label;
     306: dload         4
     308: invokevirtual #129                // Method javafx/scene/control/Label.prefHeight:(D)D
     311: invokestatic  #199                // Method java/lang/Math.ceil:(D)D
     314: dstore        12
     316: aload_0
     317: getfield      #10                 // Field axisLabel:Ljavafx/scene/control/Label;
     320: invokevirtual #189                // Method javafx/scene/control/Label.getTransforms:()Ljavafx/collections/ObservableList;
     323: iconst_2
     324: anewarray     #190                // class javafx/scene/transform/Transform
     327: dup
     328: iconst_0
     329: new           #191                // class javafx/scene/transform/Translate
     332: dup
     333: dconst_0
     334: dload         6
     336: invokespecial #192                // Method javafx/scene/transform/Translate."<init>":(DD)V
     339: aastore
     340: dup
     341: iconst_1
     342: new           #193                // class javafx/scene/transform/Rotate
     345: dup
     346: ldc2_w        #194                // double -90.0d
     349: dconst_0
     350: dconst_0
     351: invokespecial #196                // Method javafx/scene/transform/Rotate."<init>":(DDD)V
     354: aastore
     355: invokeinterface #95,  2           // InterfaceMethod javafx/collections/ObservableList.setAll:([Ljava/lang/Object;)Z
     360: pop
     361: aload_0
     362: getfield      #10                 // Field axisLabel:Ljavafx/scene/control/Label;
     365: dload         4
     367: dload         12
     369: dsub
     370: invokevirtual #197                // Method javafx/scene/control/Label.setLayoutX:(D)V
     373: aload_0
     374: getfield      #10                 // Field axisLabel:Ljavafx/scene/control/Label;
     377: dconst_0
     378: invokevirtual #198                // Method javafx/scene/control/Label.setLayoutY:(D)V
     381: aload_0
     382: getfield      #10                 // Field axisLabel:Ljavafx/scene/control/Label;
     385: dload         6
     387: dload         12
     389: invokevirtual #200                // Method javafx/scene/control/Label.resize:(DD)V
     392: aload_0
     393: getfield      #8                  // Field tickMarks:Ljavafx/collections/ObservableList;
     396: invokeinterface #138,  1          // InterfaceMethod javafx/collections/ObservableList.iterator:()Ljava/util/Iterator;
     401: astore        12
     403: aload         12
     405: invokeinterface #118,  1          // InterfaceMethod java/util/Iterator.hasNext:()Z
     410: ifeq          472
     413: aload         12
     415: invokeinterface #119,  1          // InterfaceMethod java/util/Iterator.next:()Ljava/lang/Object;
     420: checkcast     #139                // class javafx/scene/chart/Axis$TickMark
     423: astore        13
     425: aload_0
     426: aload         13
     428: getfield      #145                // Field javafx/scene/chart/Axis$TickMark.textNode:Ljavafx/scene/text/Text;
     431: aload_0
     432: invokevirtual #130                // Method getTickLabelGap:()D
     435: dload         8
     437: dadd
     438: aload         13
     440: invokevirtual #201                // Method javafx/scene/chart/Axis$TickMark.getPosition:()D
     443: dload         10
     445: aload_1
     446: invokespecial #202                // Method positionTextNode:(Ljavafx/scene/text/Text;DDDLjavafx/geometry/Side;)V
     449: aload_0
     450: aload         13
     452: dload_2
     453: dconst_0
     454: aload         13
     456: invokevirtual #201                // Method javafx/scene/chart/Axis$TickMark.getPosition:()D
     459: dload         8
     461: aload         13
     463: invokevirtual #201                // Method javafx/scene/chart/Axis$TickMark.getPosition:()D
     466: invokespecial #203                // Method updateTickMark:(Ljavafx/scene/chart/Axis$TickMark;DDDDD)V
     469: goto          403
     472: goto          815
     475: getstatic     #205                // Field javafx/geometry/Side.TOP:Ljavafx/geometry/Side;
     478: aload_1
     479: invokevirtual #181                // Method javafx/geometry/Side.equals:(Ljava/lang/Object;)Z
     482: ifeq          651
     485: aload_0
     486: getfield      #9                  // Field tickMarkPath:Ljavafx/scene/shape/Path;
     489: ldc2_w        #185                // double 0.5d
     492: invokevirtual #184                // Method javafx/scene/shape/Path.setLayoutX:(D)V
     495: aload_0
     496: getfield      #9                  // Field tickMarkPath:Ljavafx/scene/shape/Path;
     499: ldc2_w        #182                // double -0.5d
     502: invokevirtual #187                // Method javafx/scene/shape/Path.setLayoutY:(D)V
     505: aload_0
     506: invokevirtual #188                // Method getLabel:()Ljava/lang/String;
     509: ifnull        561
     512: aload_0
     513: getfield      #10                 // Field axisLabel:Ljavafx/scene/control/Label;
     516: invokevirtual #189                // Method javafx/scene/control/Label.getTransforms:()Ljavafx/collections/ObservableList;
     519: invokeinterface #179,  1          // InterfaceMethod javafx/collections/ObservableList.clear:()V
     524: aload_0
     525: getfield      #10                 // Field axisLabel:Ljavafx/scene/control/Label;
     528: dconst_0
     529: invokevirtual #197                // Method javafx/scene/control/Label.setLayoutX:(D)V
     532: aload_0
     533: getfield      #10                 // Field axisLabel:Ljavafx/scene/control/Label;
     536: dconst_0
     537: invokevirtual #198                // Method javafx/scene/control/Label.setLayoutY:(D)V
     540: aload_0
     541: getfield      #10                 // Field axisLabel:Ljavafx/scene/control/Label;
     544: dload         4
     546: aload_0
     547: getfield      #10                 // Field axisLabel:Ljavafx/scene/control/Label;
     550: dload         4
     552: invokevirtual #129                // Method javafx/scene/control/Label.prefHeight:(D)D
     555: invokestatic  #199                // Method java/lang/Math.ceil:(D)D
     558: invokevirtual #200                // Method javafx/scene/control/Label.resize:(DD)V
     561: aload_0
     562: getfield      #8                  // Field tickMarks:Ljavafx/collections/ObservableList;
     565: invokeinterface #138,  1          // InterfaceMethod javafx/collections/ObservableList.iterator:()Ljava/util/Iterator;
     570: astore        12
     572: aload         12
     574: invokeinterface #118,  1          // InterfaceMethod java/util/Iterator.hasNext:()Z
     579: ifeq          648
     582: aload         12
     584: invokeinterface #119,  1          // InterfaceMethod java/util/Iterator.next:()Ljava/lang/Object;
     589: checkcast     #139                // class javafx/scene/chart/Axis$TickMark
     592: astore        13
     594: aload_0
     595: aload         13
     597: getfield      #145                // Field javafx/scene/chart/Axis$TickMark.textNode:Ljavafx/scene/text/Text;
     600: aload         13
     602: invokevirtual #201                // Method javafx/scene/chart/Axis$TickMark.getPosition:()D
     605: dload         6
     607: dload         8
     609: dsub
     610: aload_0
     611: invokevirtual #130                // Method getTickLabelGap:()D
     614: dsub
     615: dload         10
     617: aload_1
     618: invokespecial #202                // Method positionTextNode:(Ljavafx/scene/text/Text;DDDLjavafx/geometry/Side;)V
     621: aload_0
     622: aload         13
     624: dload_2
     625: aload         13
     627: invokevirtual #201                // Method javafx/scene/chart/Axis$TickMark.getPosition:()D
     630: dload         6
     632: aload         13
     634: invokevirtual #201                // Method javafx/scene/chart/Axis$TickMark.getPosition:()D
     637: dload         6
     639: dload         8
     641: dsub
     642: invokespecial #203                // Method updateTickMark:(Ljavafx/scene/chart/Axis$TickMark;DDDDD)V
     645: goto          572
     648: goto          815
     651: aload_0
     652: getfield      #9                  // Field tickMarkPath:Ljavafx/scene/shape/Path;
     655: ldc2_w        #185                // double 0.5d
     658: invokevirtual #184                // Method javafx/scene/shape/Path.setLayoutX:(D)V
     661: aload_0
     662: getfield      #9                  // Field tickMarkPath:Ljavafx/scene/shape/Path;
     665: ldc2_w        #185                // double 0.5d
     668: invokevirtual #187                // Method javafx/scene/shape/Path.setLayoutY:(D)V
     671: aload_0
     672: invokevirtual #188                // Method getLabel:()Ljava/lang/String;
     675: ifnull        735
     678: aload_0
     679: getfield      #10                 // Field axisLabel:Ljavafx/scene/control/Label;
     682: invokevirtual #189                // Method javafx/scene/control/Label.getTransforms:()Ljavafx/collections/ObservableList;
     685: invokeinterface #179,  1          // InterfaceMethod javafx/collections/ObservableList.clear:()V
     690: aload_0
     691: getfield      #10                 // Field axisLabel:Ljavafx/scene/control/Label;
     694: dload         4
     696: invokevirtual #129                // Method javafx/scene/control/Label.prefHeight:(D)D
     699: invokestatic  #199                // Method java/lang/Math.ceil:(D)D
     702: dstore        12
     704: aload_0
     705: getfield      #10                 // Field axisLabel:Ljavafx/scene/control/Label;
     708: dconst_0
     709: invokevirtual #197                // Method javafx/scene/control/Label.setLayoutX:(D)V
     712: aload_0
     713: getfield      #10                 // Field axisLabel:Ljavafx/scene/control/Label;
     716: dload         6
     718: dload         12
     720: dsub
     721: invokevirtual #198                // Method javafx/scene/control/Label.setLayoutY:(D)V
     724: aload_0
     725: getfield      #10                 // Field axisLabel:Ljavafx/scene/control/Label;
     728: dload         4
     730: dload         12
     732: invokevirtual #200                // Method javafx/scene/control/Label.resize:(DD)V
     735: aload_0
     736: getfield      #8                  // Field tickMarks:Ljavafx/collections/ObservableList;
     739: invokeinterface #138,  1          // InterfaceMethod javafx/collections/ObservableList.iterator:()Ljava/util/Iterator;
     744: astore        12
     746: aload         12
     748: invokeinterface #118,  1          // InterfaceMethod java/util/Iterator.hasNext:()Z
     753: ifeq          815
     756: aload         12
     758: invokeinterface #119,  1          // InterfaceMethod java/util/Iterator.next:()Ljava/lang/Object;
     763: checkcast     #139                // class javafx/scene/chart/Axis$TickMark
     766: astore        13
     768: aload_0
     769: aload         13
     771: getfield      #145                // Field javafx/scene/chart/Axis$TickMark.textNode:Ljavafx/scene/text/Text;
     774: aload         13
     776: invokevirtual #201                // Method javafx/scene/chart/Axis$TickMark.getPosition:()D
     779: dload         8
     781: aload_0
     782: invokevirtual #130                // Method getTickLabelGap:()D
     785: dadd
     786: dload         10
     788: aload_1
     789: invokespecial #202                // Method positionTextNode:(Ljavafx/scene/text/Text;DDDLjavafx/geometry/Side;)V
     792: aload_0
     793: aload         13
     795: dload_2
     796: aload         13
     798: invokevirtual #201                // Method javafx/scene/chart/Axis$TickMark.getPosition:()D
     801: dconst_0
     802: aload         13
     804: invokevirtual #201                // Method javafx/scene/chart/Axis$TickMark.getPosition:()D
     807: dload         8
     809: invokespecial #203                // Method updateTickMark:(Ljavafx/scene/chart/Axis$TickMark;DDDDD)V
     812: goto          746
     815: return

  private boolean isTickLabelsOverlap(javafx.geometry.Side, javafx.scene.chart.Axis$TickMark<T>, javafx.scene.chart.Axis$TickMark<T>, double);
    Code:
       0: aload_2
       1: invokevirtual #171                // Method javafx/scene/chart/Axis$TickMark.isTextVisible:()Z
       4: ifeq          14
       7: aload_3
       8: invokevirtual #171                // Method javafx/scene/chart/Axis$TickMark.isTextVisible:()Z
      11: ifne          16
      14: iconst_0
      15: ireturn
      16: aload_0
      17: aload_2
      18: invokevirtual #168                // Method javafx/scene/chart/Axis$TickMark.getValue:()Ljava/lang/Object;
      21: aload_1
      22: invokespecial #172                // Method measureTickMarkSize:(Ljava/lang/Object;Ljavafx/geometry/Side;)D
      25: dstore        6
      27: aload_0
      28: aload_3
      29: invokevirtual #168                // Method javafx/scene/chart/Axis$TickMark.getValue:()Ljava/lang/Object;
      32: aload_1
      33: invokespecial #172                // Method measureTickMarkSize:(Ljava/lang/Object;Ljavafx/geometry/Side;)D
      36: dstore        8
      38: aload_2
      39: invokevirtual #201                // Method javafx/scene/chart/Axis$TickMark.getPosition:()D
      42: dload         6
      44: ldc2_w        #206                // double 2.0d
      47: ddiv
      48: dsub
      49: dstore        10
      51: aload_2
      52: invokevirtual #201                // Method javafx/scene/chart/Axis$TickMark.getPosition:()D
      55: dload         6
      57: ldc2_w        #206                // double 2.0d
      60: ddiv
      61: dadd
      62: dstore        12
      64: aload_3
      65: invokevirtual #201                // Method javafx/scene/chart/Axis$TickMark.getPosition:()D
      68: dload         8
      70: ldc2_w        #206                // double 2.0d
      73: ddiv
      74: dsub
      75: dstore        14
      77: aload_3
      78: invokevirtual #201                // Method javafx/scene/chart/Axis$TickMark.getPosition:()D
      81: dload         8
      83: ldc2_w        #206                // double 2.0d
      86: ddiv
      87: dadd
      88: dstore        16
      90: aload_1
      91: invokevirtual #21                 // Method javafx/geometry/Side.isVertical:()Z
      94: ifeq          116
      97: dload         10
      99: dload         16
     101: dsub
     102: dload         4
     104: dcmpg
     105: ifgt          112
     108: iconst_1
     109: goto          132
     112: iconst_0
     113: goto          132
     116: dload         14
     118: dload         12
     120: dsub
     121: dload         4
     123: dcmpg
     124: ifgt          131
     127: iconst_1
     128: goto          132
     131: iconst_0
     132: ireturn

  private void positionTextNode(javafx.scene.text.Text, double, double, double, javafx.geometry.Side);
    Code:
       0: aload_1
       1: dconst_0
       2: invokevirtual #208                // Method javafx/scene/text/Text.setLayoutX:(D)V
       5: aload_1
       6: dconst_0
       7: invokevirtual #209                // Method javafx/scene/text/Text.setLayoutY:(D)V
      10: aload_1
      11: dload         6
      13: invokevirtual #210                // Method javafx/scene/text/Text.setRotate:(D)V
      16: aload_1
      17: invokevirtual #211                // Method javafx/scene/text/Text.getBoundsInParent:()Ljavafx/geometry/Bounds;
      20: astore        9
      22: getstatic     #25                 // Field javafx/geometry/Side.LEFT:Ljavafx/geometry/Side;
      25: aload         8
      27: invokevirtual #181                // Method javafx/geometry/Side.equals:(Ljava/lang/Object;)Z
      30: ifeq          75
      33: aload_1
      34: dload_2
      35: aload         9
      37: invokevirtual #212                // Method javafx/geometry/Bounds.getWidth:()D
      40: dsub
      41: aload         9
      43: invokevirtual #213                // Method javafx/geometry/Bounds.getMinX:()D
      46: dsub
      47: invokevirtual #208                // Method javafx/scene/text/Text.setLayoutX:(D)V
      50: aload_1
      51: dload         4
      53: aload         9
      55: invokevirtual #214                // Method javafx/geometry/Bounds.getHeight:()D
      58: ldc2_w        #206                // double 2.0d
      61: ddiv
      62: dsub
      63: aload         9
      65: invokevirtual #215                // Method javafx/geometry/Bounds.getMinY:()D
      68: dsub
      69: invokevirtual #209                // Method javafx/scene/text/Text.setLayoutY:(D)V
      72: goto          208
      75: getstatic     #204                // Field javafx/geometry/Side.RIGHT:Ljavafx/geometry/Side;
      78: aload         8
      80: invokevirtual #181                // Method javafx/geometry/Side.equals:(Ljava/lang/Object;)Z
      83: ifeq          122
      86: aload_1
      87: dload_2
      88: aload         9
      90: invokevirtual #213                // Method javafx/geometry/Bounds.getMinX:()D
      93: dsub
      94: invokevirtual #208                // Method javafx/scene/text/Text.setLayoutX:(D)V
      97: aload_1
      98: dload         4
     100: aload         9
     102: invokevirtual #214                // Method javafx/geometry/Bounds.getHeight:()D
     105: ldc2_w        #206                // double 2.0d
     108: ddiv
     109: dsub
     110: aload         9
     112: invokevirtual #215                // Method javafx/geometry/Bounds.getMinY:()D
     115: dsub
     116: invokevirtual #209                // Method javafx/scene/text/Text.setLayoutY:(D)V
     119: goto          208
     122: getstatic     #205                // Field javafx/geometry/Side.TOP:Ljavafx/geometry/Side;
     125: aload         8
     127: invokevirtual #181                // Method javafx/geometry/Side.equals:(Ljava/lang/Object;)Z
     130: ifeq          175
     133: aload_1
     134: dload_2
     135: aload         9
     137: invokevirtual #212                // Method javafx/geometry/Bounds.getWidth:()D
     140: ldc2_w        #206                // double 2.0d
     143: ddiv
     144: dsub
     145: aload         9
     147: invokevirtual #213                // Method javafx/geometry/Bounds.getMinX:()D
     150: dsub
     151: invokevirtual #208                // Method javafx/scene/text/Text.setLayoutX:(D)V
     154: aload_1
     155: dload         4
     157: aload         9
     159: invokevirtual #214                // Method javafx/geometry/Bounds.getHeight:()D
     162: dsub
     163: aload         9
     165: invokevirtual #215                // Method javafx/geometry/Bounds.getMinY:()D
     168: dsub
     169: invokevirtual #209                // Method javafx/scene/text/Text.setLayoutY:(D)V
     172: goto          208
     175: aload_1
     176: dload_2
     177: aload         9
     179: invokevirtual #212                // Method javafx/geometry/Bounds.getWidth:()D
     182: ldc2_w        #206                // double 2.0d
     185: ddiv
     186: dsub
     187: aload         9
     189: invokevirtual #213                // Method javafx/geometry/Bounds.getMinX:()D
     192: dsub
     193: invokevirtual #208                // Method javafx/scene/text/Text.setLayoutX:(D)V
     196: aload_1
     197: dload         4
     199: aload         9
     201: invokevirtual #215                // Method javafx/geometry/Bounds.getMinY:()D
     204: dsub
     205: invokevirtual #209                // Method javafx/scene/text/Text.setLayoutY:(D)V
     208: return

  private void updateTickMark(javafx.scene.chart.Axis$TickMark<T>, double, double, double, double, double);
    Code:
       0: aload_1
       1: invokevirtual #201                // Method javafx/scene/chart/Axis$TickMark.getPosition:()D
       4: dconst_0
       5: dcmpl
       6: iflt          80
       9: aload_1
      10: invokevirtual #201                // Method javafx/scene/chart/Axis$TickMark.getPosition:()D
      13: dload_2
      14: invokestatic  #199                // Method java/lang/Math.ceil:(D)D
      17: dcmpg
      18: ifgt          80
      21: aload_1
      22: getfield      #145                // Field javafx/scene/chart/Axis$TickMark.textNode:Ljavafx/scene/text/Text;
      25: aload_1
      26: invokevirtual #171                // Method javafx/scene/chart/Axis$TickMark.isTextVisible:()Z
      29: invokevirtual #216                // Method javafx/scene/text/Text.setVisible:(Z)V
      32: aload_0
      33: getfield      #9                  // Field tickMarkPath:Ljavafx/scene/shape/Path;
      36: invokevirtual #178                // Method javafx/scene/shape/Path.getElements:()Ljavafx/collections/ObservableList;
      39: iconst_2
      40: anewarray     #217                // class javafx/scene/shape/PathElement
      43: dup
      44: iconst_0
      45: new           #218                // class javafx/scene/shape/MoveTo
      48: dup
      49: dload         4
      51: dload         6
      53: invokespecial #219                // Method javafx/scene/shape/MoveTo."<init>":(DD)V
      56: aastore
      57: dup
      58: iconst_1
      59: new           #220                // class javafx/scene/shape/LineTo
      62: dup
      63: dload         8
      65: dload         10
      67: invokespecial #221                // Method javafx/scene/shape/LineTo."<init>":(DD)V
      70: aastore
      71: invokeinterface #105,  2          // InterfaceMethod javafx/collections/ObservableList.addAll:([Ljava/lang/Object;)Z
      76: pop
      77: goto          88
      80: aload_1
      81: getfield      #145                // Field javafx/scene/chart/Axis$TickMark.textNode:Ljavafx/scene/text/Text;
      84: iconst_0
      85: invokevirtual #216                // Method javafx/scene/text/Text.setVisible:(Z)V
      88: return

  protected abstract java.lang.String getTickMarkLabel(T);

  protected final javafx.geometry.Dimension2D measureTickMarkLabelSize(java.lang.String, double);
    Code:
       0: aload_0
       1: getfield      #45                 // Field measure:Ljavafx/scene/text/Text;
       4: dload_2
       5: invokevirtual #210                // Method javafx/scene/text/Text.setRotate:(D)V
       8: aload_0
       9: getfield      #45                 // Field measure:Ljavafx/scene/text/Text;
      12: aload_1
      13: invokevirtual #156                // Method javafx/scene/text/Text.setText:(Ljava/lang/String;)V
      16: aload_0
      17: getfield      #45                 // Field measure:Ljavafx/scene/text/Text;
      20: invokevirtual #211                // Method javafx/scene/text/Text.getBoundsInParent:()Ljavafx/geometry/Bounds;
      23: astore        4
      25: new           #222                // class javafx/geometry/Dimension2D
      28: dup
      29: aload         4
      31: invokevirtual #212                // Method javafx/geometry/Bounds.getWidth:()D
      34: aload         4
      36: invokevirtual #214                // Method javafx/geometry/Bounds.getHeight:()D
      39: invokespecial #223                // Method javafx/geometry/Dimension2D."<init>":(DD)V
      42: areturn

  protected final javafx.geometry.Dimension2D measureTickMarkSize(T, double);
    Code:
       0: aload_0
       1: aload_0
       2: aload_1
       3: invokevirtual #155                // Method getTickMarkLabel:(Ljava/lang/Object;)Ljava/lang/String;
       6: dload_2
       7: invokevirtual #224                // Method measureTickMarkLabelSize:(Ljava/lang/String;D)Ljavafx/geometry/Dimension2D;
      10: areturn

  protected javafx.geometry.Dimension2D measureTickMarkSize(T, java.lang.Object);
    Code:
       0: aload_0
       1: aload_1
       2: aload_0
       3: invokevirtual #180                // Method getEffectiveTickLabelRotation:()D
       6: invokevirtual #225                // Method measureTickMarkSize:(Ljava/lang/Object;D)Ljavafx/geometry/Dimension2D;
       9: areturn

  private double measureTickMarkSize(T, javafx.geometry.Side);
    Code:
       0: aload_0
       1: aload_1
       2: aload_0
       3: invokevirtual #180                // Method getEffectiveTickLabelRotation:()D
       6: invokevirtual #225                // Method measureTickMarkSize:(Ljava/lang/Object;D)Ljavafx/geometry/Dimension2D;
       9: astore_3
      10: aload_2
      11: invokevirtual #21                 // Method javafx/geometry/Side.isVertical:()Z
      14: ifeq          24
      17: aload_3
      18: invokevirtual #121                // Method javafx/geometry/Dimension2D.getHeight:()D
      21: goto          28
      24: aload_3
      25: invokevirtual #131                // Method javafx/geometry/Dimension2D.getWidth:()D
      28: dreturn

  final double getEffectiveTickLabelRotation();
    Code:
       0: aload_0
       1: invokevirtual #135                // Method isAutoRanging:()Z
       4: ifeq          17
       7: aload_0
       8: getfield      #49                 // Field effectiveTickLabelRotation:D
      11: invokestatic  #226                // Method java/lang/Double.isNaN:(D)Z
      14: ifeq          24
      17: aload_0
      18: invokevirtual #227                // Method getTickLabelRotation:()D
      21: goto          28
      24: aload_0
      25: getfield      #49                 // Field effectiveTickLabelRotation:D
      28: dreturn

  final void setEffectiveTickLabelRotation(double);
    Code:
       0: aload_0
       1: dload_1
       2: putfield      #49                 // Field effectiveTickLabelRotation:D
       5: return

  public static java.util.List<javafx.css.CssMetaData<? extends javafx.css.Styleable, ?>> getClassCssMetaData();
    Code:
       0: invokestatic  #228                // Method javafx/scene/chart/Axis$StyleableProperties.access$2100:()Ljava/util/List;
       3: areturn

  public java.util.List<javafx.css.CssMetaData<? extends javafx.css.Styleable, ?>> getCssMetaData();
    Code:
       0: invokestatic  #229                // Method getClassCssMetaData:()Ljava/util/List;
       3: areturn

  private void lambda$layoutChildren$0(javafx.scene.chart.Axis$TickMark, javafx.event.ActionEvent);
    Code:
       0: aload_0
       1: invokevirtual #103                // Method getChildren:()Ljavafx/collections/ObservableList;
       4: aload_1
       5: getfield      #145                // Field javafx/scene/chart/Axis$TickMark.textNode:Ljavafx/scene/text/Text;
       8: invokeinterface #151,  2          // InterfaceMethod javafx/collections/ObservableList.remove:(Ljava/lang/Object;)Z
      13: pop
      14: return

  static javafx.css.PseudoClass access$000();
    Code:
       0: getstatic     #14                 // Field TOP_PSEUDOCLASS_STATE:Ljavafx/css/PseudoClass;
       3: areturn

  static javafx.css.PseudoClass access$100();
    Code:
       0: getstatic     #13                 // Field RIGHT_PSEUDOCLASS_STATE:Ljavafx/css/PseudoClass;
       3: areturn

  static javafx.css.PseudoClass access$200();
    Code:
       0: getstatic     #12                 // Field BOTTOM_PSEUDOCLASS_STATE:Ljavafx/css/PseudoClass;
       3: areturn

  static javafx.css.PseudoClass access$300();
    Code:
       0: getstatic     #11                 // Field LEFT_PSEUDOCLASS_STATE:Ljavafx/css/PseudoClass;
       3: areturn

  static javafx.scene.control.Label access$500(javafx.scene.chart.Axis);
    Code:
       0: aload_0
       1: getfield      #10                 // Field axisLabel:Ljavafx/scene/control/Label;
       4: areturn

  static javafx.scene.shape.Path access$600(javafx.scene.chart.Axis);
    Code:
       0: aload_0
       1: getfield      #9                  // Field tickMarkPath:Ljavafx/scene/shape/Path;
       4: areturn

  static javafx.collections.ObservableList access$800(javafx.scene.chart.Axis);
    Code:
       0: aload_0
       1: getfield      #8                  // Field tickMarks:Ljavafx/collections/ObservableList;
       4: areturn

  static javafx.beans.property.DoubleProperty access$1000(javafx.scene.chart.Axis);
    Code:
       0: aload_0
       1: getfield      #7                  // Field tickLength:Ljavafx/beans/property/DoubleProperty;
       4: areturn

  static javafx.beans.property.ObjectProperty access$1500(javafx.scene.chart.Axis);
    Code:
       0: aload_0
       1: getfield      #6                  // Field side:Ljavafx/beans/property/ObjectProperty;
       4: areturn

  static javafx.beans.property.ObjectProperty access$1600(javafx.scene.chart.Axis);
    Code:
       0: aload_0
       1: getfield      #5                  // Field tickLabelFont:Ljavafx/beans/property/ObjectProperty;
       4: areturn

  static javafx.beans.property.ObjectProperty access$1700(javafx.scene.chart.Axis);
    Code:
       0: aload_0
       1: getfield      #4                  // Field tickLabelFill:Ljavafx/beans/property/ObjectProperty;
       4: areturn

  static javafx.beans.property.DoubleProperty access$1800(javafx.scene.chart.Axis);
    Code:
       0: aload_0
       1: getfield      #3                  // Field tickLabelGap:Ljavafx/beans/property/DoubleProperty;
       4: areturn

  static javafx.beans.property.BooleanProperty access$1900(javafx.scene.chart.Axis);
    Code:
       0: aload_0
       1: getfield      #2                  // Field tickMarkVisible:Ljavafx/beans/property/BooleanProperty;
       4: areturn

  static javafx.beans.property.BooleanProperty access$2000(javafx.scene.chart.Axis);
    Code:
       0: aload_0
       1: getfield      #1                  // Field tickLabelsVisible:Ljavafx/beans/property/BooleanProperty;
       4: areturn

  static {};
    Code:
       0: ldc           #230                // String top
       2: invokestatic  #231                // Method javafx/css/PseudoClass.getPseudoClass:(Ljava/lang/String;)Ljavafx/css/PseudoClass;
       5: putstatic     #14                 // Field TOP_PSEUDOCLASS_STATE:Ljavafx/css/PseudoClass;
       8: ldc           #232                // String bottom
      10: invokestatic  #231                // Method javafx/css/PseudoClass.getPseudoClass:(Ljava/lang/String;)Ljavafx/css/PseudoClass;
      13: putstatic     #12                 // Field BOTTOM_PSEUDOCLASS_STATE:Ljavafx/css/PseudoClass;
      16: ldc           #233                // String left
      18: invokestatic  #231                // Method javafx/css/PseudoClass.getPseudoClass:(Ljava/lang/String;)Ljavafx/css/PseudoClass;
      21: putstatic     #11                 // Field LEFT_PSEUDOCLASS_STATE:Ljavafx/css/PseudoClass;
      24: ldc           #234                // String right
      26: invokestatic  #231                // Method javafx/css/PseudoClass.getPseudoClass:(Ljava/lang/String;)Ljavafx/css/PseudoClass;
      29: putstatic     #13                 // Field RIGHT_PSEUDOCLASS_STATE:Ljavafx/css/PseudoClass;
      32: return
}
