Compiled from "MethodMatchers.java"
public abstract class org.springframework.aop.support.MethodMatchers {
  public org.springframework.aop.support.MethodMatchers();
    Code:
       0: aload_0
       1: invokespecial #1                  // Method java/lang/Object."<init>":()V
       4: return

  public static org.springframework.aop.MethodMatcher union(org.springframework.aop.MethodMatcher, org.springframework.aop.MethodMatcher);
    Code:
       0: aload_0
       1: instanceof    #2                  // class org/springframework/aop/IntroductionAwareMethodMatcher
       4: ifne          14
       7: aload_1
       8: instanceof    #2                  // class org/springframework/aop/IntroductionAwareMethodMatcher
      11: ifeq          26
      14: new           #3                  // class org/springframework/aop/support/MethodMatchers$UnionIntroductionAwareMethodMatcher
      17: dup
      18: aload_0
      19: aload_1
      20: invokespecial #4                  // Method org/springframework/aop/support/MethodMatchers$UnionIntroductionAwareMethodMatcher."<init>":(Lorg/springframework/aop/MethodMatcher;Lorg/springframework/aop/MethodMatcher;)V
      23: goto          35
      26: new           #5                  // class org/springframework/aop/support/MethodMatchers$UnionMethodMatcher
      29: dup
      30: aload_0
      31: aload_1
      32: invokespecial #6                  // Method org/springframework/aop/support/MethodMatchers$UnionMethodMatcher."<init>":(Lorg/springframework/aop/MethodMatcher;Lorg/springframework/aop/MethodMatcher;)V
      35: areturn

  static org.springframework.aop.MethodMatcher union(org.springframework.aop.MethodMatcher, org.springframework.aop.ClassFilter, org.springframework.aop.MethodMatcher, org.springframework.aop.ClassFilter);
    Code:
       0: aload_0
       1: instanceof    #2                  // class org/springframework/aop/IntroductionAwareMethodMatcher
       4: ifne          14
       7: aload_2
       8: instanceof    #2                  // class org/springframework/aop/IntroductionAwareMethodMatcher
      11: ifeq          28
      14: new           #7                  // class org/springframework/aop/support/MethodMatchers$ClassFilterAwareUnionIntroductionAwareMethodMatcher
      17: dup
      18: aload_0
      19: aload_1
      20: aload_2
      21: aload_3
      22: invokespecial #8                  // Method org/springframework/aop/support/MethodMatchers$ClassFilterAwareUnionIntroductionAwareMethodMatcher."<init>":(Lorg/springframework/aop/MethodMatcher;Lorg/springframework/aop/ClassFilter;Lorg/springframework/aop/MethodMatcher;Lorg/springframework/aop/ClassFilter;)V
      25: goto          39
      28: new           #9                  // class org/springframework/aop/support/MethodMatchers$ClassFilterAwareUnionMethodMatcher
      31: dup
      32: aload_0
      33: aload_1
      34: aload_2
      35: aload_3
      36: invokespecial #10                 // Method org/springframework/aop/support/MethodMatchers$ClassFilterAwareUnionMethodMatcher."<init>":(Lorg/springframework/aop/MethodMatcher;Lorg/springframework/aop/ClassFilter;Lorg/springframework/aop/MethodMatcher;Lorg/springframework/aop/ClassFilter;)V
      39: areturn

  public static org.springframework.aop.MethodMatcher intersection(org.springframework.aop.MethodMatcher, org.springframework.aop.MethodMatcher);
    Code:
       0: aload_0
       1: instanceof    #2                  // class org/springframework/aop/IntroductionAwareMethodMatcher
       4: ifne          14
       7: aload_1
       8: instanceof    #2                  // class org/springframework/aop/IntroductionAwareMethodMatcher
      11: ifeq          26
      14: new           #11                 // class org/springframework/aop/support/MethodMatchers$IntersectionIntroductionAwareMethodMatcher
      17: dup
      18: aload_0
      19: aload_1
      20: invokespecial #12                 // Method org/springframework/aop/support/MethodMatchers$IntersectionIntroductionAwareMethodMatcher."<init>":(Lorg/springframework/aop/MethodMatcher;Lorg/springframework/aop/MethodMatcher;)V
      23: goto          35
      26: new           #13                 // class org/springframework/aop/support/MethodMatchers$IntersectionMethodMatcher
      29: dup
      30: aload_0
      31: aload_1
      32: invokespecial #14                 // Method org/springframework/aop/support/MethodMatchers$IntersectionMethodMatcher."<init>":(Lorg/springframework/aop/MethodMatcher;Lorg/springframework/aop/MethodMatcher;)V
      35: areturn

  public static boolean matches(org.springframework.aop.MethodMatcher, java.lang.reflect.Method, java.lang.Class<?>, boolean);
    Code:
       0: aload_0
       1: ldc           #15                 // String MethodMatcher must not be null
       3: invokestatic  #16                 // Method org/springframework/util/Assert.notNull:(Ljava/lang/Object;Ljava/lang/String;)V
       6: aload_0
       7: instanceof    #2                  // class org/springframework/aop/IntroductionAwareMethodMatcher
      10: ifeq          28
      13: aload_0
      14: checkcast     #2                  // class org/springframework/aop/IntroductionAwareMethodMatcher
      17: aload_1
      18: aload_2
      19: iload_3
      20: invokeinterface #17,  4           // InterfaceMethod org/springframework/aop/IntroductionAwareMethodMatcher.matches:(Ljava/lang/reflect/Method;Ljava/lang/Class;Z)Z
      25: goto          36
      28: aload_0
      29: aload_1
      30: aload_2
      31: invokeinterface #18,  3           // InterfaceMethod org/springframework/aop/MethodMatcher.matches:(Ljava/lang/reflect/Method;Ljava/lang/Class;)Z
      36: ireturn
}
