Compiled from "BooleanOptionCompleter.java"
public class org.jboss.aesh.cl.completer.BooleanOptionCompleter implements org.jboss.aesh.cl.completer.OptionCompleter<org.jboss.aesh.console.command.completer.CompleterInvocation> {
  public org.jboss.aesh.cl.completer.BooleanOptionCompleter();
    Code:
       0: aload_0
       1: invokespecial #1                  // Method java/lang/Object."<init>":()V
       4: return

  public void complete(org.jboss.aesh.console.command.completer.CompleterInvocation);
    Code:
       0: aload_1
       1: invokeinterface #2,  1            // InterfaceMethod org/jboss/aesh/console/command/completer/CompleterInvocation.getGivenCompleteValue:()Ljava/lang/String;
       6: invokevirtual #3                  // Method java/lang/String.length:()I
       9: ifne          31
      12: aload_1
      13: ldc           #4                  // String true
      15: invokeinterface #5,  2            // InterfaceMethod org/jboss/aesh/console/command/completer/CompleterInvocation.addCompleterValue:(Ljava/lang/String;)V
      20: aload_1
      21: ldc           #6                  // String false
      23: invokeinterface #5,  2            // InterfaceMethod org/jboss/aesh/console/command/completer/CompleterInvocation.addCompleterValue:(Ljava/lang/String;)V
      28: goto          84
      31: ldc           #4                  // String true
      33: aload_1
      34: invokeinterface #2,  1            // InterfaceMethod org/jboss/aesh/console/command/completer/CompleterInvocation.getGivenCompleteValue:()Ljava/lang/String;
      39: invokevirtual #7                  // Method java/lang/String.toLowerCase:()Ljava/lang/String;
      42: invokevirtual #8                  // Method java/lang/String.startsWith:(Ljava/lang/String;)Z
      45: ifeq          59
      48: aload_1
      49: ldc           #4                  // String true
      51: invokeinterface #5,  2            // InterfaceMethod org/jboss/aesh/console/command/completer/CompleterInvocation.addCompleterValue:(Ljava/lang/String;)V
      56: goto          84
      59: ldc           #6                  // String false
      61: aload_1
      62: invokeinterface #2,  1            // InterfaceMethod org/jboss/aesh/console/command/completer/CompleterInvocation.getGivenCompleteValue:()Ljava/lang/String;
      67: invokevirtual #7                  // Method java/lang/String.toLowerCase:()Ljava/lang/String;
      70: invokevirtual #8                  // Method java/lang/String.startsWith:(Ljava/lang/String;)Z
      73: ifeq          84
      76: aload_1
      77: ldc           #6                  // String false
      79: invokeinterface #5,  2            // InterfaceMethod org/jboss/aesh/console/command/completer/CompleterInvocation.addCompleterValue:(Ljava/lang/String;)V
      84: return
}
