Compiled from "AbstractServiceLifecycle.java"
public abstract class io.openmessaging.joyqueue.support.AbstractServiceLifecycle extends org.joyqueue.toolkit.service.Service implements io.openmessaging.ServiceLifecycle {
  public io.openmessaging.joyqueue.support.AbstractServiceLifecycle();
    Code:
       0: aload_0
       1: invokespecial #1                  // Method org/joyqueue/toolkit/service/Service."<init>":()V
       4: return

  public void start();
    Code:
       0: aload_0
       1: invokespecial #2                  // Method org/joyqueue/toolkit/service/Service.start:()V
       4: goto          13
       7: astore_1
       8: aload_1
       9: invokestatic  #4                  // Method io/openmessaging/joyqueue/config/ExceptionConverter.convertRuntimeException:(Ljava/lang/Throwable;)Lio/openmessaging/exception/OMSRuntimeException;
      12: athrow
      13: return
    Exception table:
       from    to  target type
           0     4     7   Class java/lang/Exception

  public void stop();
    Code:
       0: aload_0
       1: invokespecial #5                  // Method org/joyqueue/toolkit/service/Service.stop:()V
       4: goto          13
       7: astore_1
       8: aload_1
       9: invokestatic  #4                  // Method io/openmessaging/joyqueue/config/ExceptionConverter.convertRuntimeException:(Ljava/lang/Throwable;)Lio/openmessaging/exception/OMSRuntimeException;
      12: athrow
      13: return
    Exception table:
       from    to  target type
           0     4     7   Class java/lang/Exception

  public io.openmessaging.ServiceLifeState currentState();
    Code:
       0: aload_0
       1: invokespecial #6                  // Method org/joyqueue/toolkit/service/Service.getServiceState:()Lorg/joyqueue/toolkit/service/Activity$ServiceState;
       4: astore_1
       5: getstatic     #7                  // Field io/openmessaging/joyqueue/support/AbstractServiceLifecycle$1.$SwitchMap$org$joyqueue$toolkit$service$Activity$ServiceState:[I
       8: aload_1
       9: invokevirtual #8                  // Method org/joyqueue/toolkit/service/Activity$ServiceState.ordinal:()I
      12: iaload
      13: tableswitch   { // 1 to 7
                     1: 56
                     2: 60
                     3: 64
                     4: 64
                     5: 68
                     6: 68
                     7: 72
               default: 76
          }
      56: getstatic     #9                  // Field io/openmessaging/ServiceLifeState.INITIALIZED:Lio/openmessaging/ServiceLifeState;
      59: areturn
      60: getstatic     #10                 // Field io/openmessaging/ServiceLifeState.STARTING:Lio/openmessaging/ServiceLifeState;
      63: areturn
      64: getstatic     #11                 // Field io/openmessaging/ServiceLifeState.STARTED:Lio/openmessaging/ServiceLifeState;
      67: areturn
      68: getstatic     #12                 // Field io/openmessaging/ServiceLifeState.STOPPING:Lio/openmessaging/ServiceLifeState;
      71: areturn
      72: getstatic     #13                 // Field io/openmessaging/ServiceLifeState.STOPPED:Lio/openmessaging/ServiceLifeState;
      75: areturn
      76: new           #14                 // class io/openmessaging/exception/OMSRuntimeException
      79: dup
      80: getstatic     #15                 // Field org/joyqueue/exception/JoyQueueCode.CN_UNKNOWN_ERROR:Lorg/joyqueue/exception/JoyQueueCode;
      83: invokevirtual #16                 // Method org/joyqueue/exception/JoyQueueCode.getCode:()I
      86: ldc           #17                 // String service state error, current: %s
      88: iconst_1
      89: anewarray     #18                 // class java/lang/Object
      92: dup
      93: iconst_0
      94: aload_1
      95: aastore
      96: invokestatic  #19                 // Method java/lang/String.format:(Ljava/lang/String;[Ljava/lang/Object;)Ljava/lang/String;
      99: invokespecial #20                 // Method io/openmessaging/exception/OMSRuntimeException."<init>":(ILjava/lang/String;)V
     102: athrow
}
