Compiled from "BucketInfo.java"
public class io.nats.client.api.BucketInfo {
  private final io.nats.client.api.StreamInfo streamInfo;

  private final io.nats.client.api.BucketConfiguration config;

  public io.nats.client.api.BucketInfo(io.nats.client.api.StreamInfo);
    Code:
       0: aload_0
       1: invokespecial #1                  // Method java/lang/Object."<init>":()V
       4: aload_0
       5: aload_1
       6: putfield      #2                  // Field streamInfo:Lio/nats/client/api/StreamInfo;
       9: aload_0
      10: new           #3                  // class io/nats/client/api/BucketConfiguration
      13: dup
      14: aload_0
      15: getfield      #2                  // Field streamInfo:Lio/nats/client/api/StreamInfo;
      18: invokevirtual #4                  // Method io/nats/client/api/StreamInfo.getConfiguration:()Lio/nats/client/api/StreamConfiguration;
      21: invokespecial #5                  // Method io/nats/client/api/BucketConfiguration."<init>":(Lio/nats/client/api/StreamConfiguration;)V
      24: putfield      #6                  // Field config:Lio/nats/client/api/BucketConfiguration;
      27: return

  public io.nats.client.api.BucketConfiguration getConfiguration();
    Code:
       0: aload_0
       1: getfield      #6                  // Field config:Lio/nats/client/api/BucketConfiguration;
       4: areturn

  public long getRecordCount();
    Code:
       0: aload_0
       1: getfield      #2                  // Field streamInfo:Lio/nats/client/api/StreamInfo;
       4: invokevirtual #7                  // Method io/nats/client/api/StreamInfo.getStreamState:()Lio/nats/client/api/StreamState;
       7: invokevirtual #8                  // Method io/nats/client/api/StreamState.getMsgCount:()J
      10: lreturn

  public long getByteCount();
    Code:
       0: aload_0
       1: getfield      #2                  // Field streamInfo:Lio/nats/client/api/StreamInfo;
       4: invokevirtual #7                  // Method io/nats/client/api/StreamInfo.getStreamState:()Lio/nats/client/api/StreamState;
       7: invokevirtual #9                  // Method io/nats/client/api/StreamState.getByteCount:()J
      10: lreturn

  public long getLastSequence();
    Code:
       0: aload_0
       1: getfield      #2                  // Field streamInfo:Lio/nats/client/api/StreamInfo;
       4: invokevirtual #7                  // Method io/nats/client/api/StreamInfo.getStreamState:()Lio/nats/client/api/StreamState;
       7: invokevirtual #10                 // Method io/nats/client/api/StreamState.getLastSequence:()J
      10: lreturn

  public java.time.ZonedDateTime getCreateTime();
    Code:
       0: aload_0
       1: getfield      #2                  // Field streamInfo:Lio/nats/client/api/StreamInfo;
       4: invokevirtual #11                 // Method io/nats/client/api/StreamInfo.getCreateTime:()Ljava/time/ZonedDateTime;
       7: areturn

  public java.lang.String toString();
    Code:
       0: new           #12                 // class java/lang/StringBuilder
       3: dup
       4: invokespecial #13                 // Method java/lang/StringBuilder."<init>":()V
       7: ldc           #14                 // String BucketInfo{created=
       9: invokevirtual #15                 // Method java/lang/StringBuilder.append:(Ljava/lang/String;)Ljava/lang/StringBuilder;
      12: aload_0
      13: invokevirtual #16                 // Method getCreateTime:()Ljava/time/ZonedDateTime;
      16: invokevirtual #17                 // Method java/lang/StringBuilder.append:(Ljava/lang/Object;)Ljava/lang/StringBuilder;
      19: ldc           #18                 // String recordCount=
      21: invokevirtual #15                 // Method java/lang/StringBuilder.append:(Ljava/lang/String;)Ljava/lang/StringBuilder;
      24: aload_0
      25: invokevirtual #19                 // Method getRecordCount:()J
      28: invokevirtual #20                 // Method java/lang/StringBuilder.append:(J)Ljava/lang/StringBuilder;
      31: ldc           #21                 // String byteCount=
      33: invokevirtual #15                 // Method java/lang/StringBuilder.append:(Ljava/lang/String;)Ljava/lang/StringBuilder;
      36: aload_0
      37: invokevirtual #22                 // Method getByteCount:()J
      40: invokevirtual #20                 // Method java/lang/StringBuilder.append:(J)Ljava/lang/StringBuilder;
      43: ldc           #23                 // String lastSequence=
      45: invokevirtual #15                 // Method java/lang/StringBuilder.append:(Ljava/lang/String;)Ljava/lang/StringBuilder;
      48: aload_0
      49: invokevirtual #24                 // Method getLastSequence:()J
      52: invokevirtual #20                 // Method java/lang/StringBuilder.append:(J)Ljava/lang/StringBuilder;
      55: ldc           #25                 // String ,
      57: invokevirtual #15                 // Method java/lang/StringBuilder.append:(Ljava/lang/String;)Ljava/lang/StringBuilder;
      60: ldc           #26                 // String config
      62: aload_0
      63: getfield      #6                  // Field config:Lio/nats/client/api/BucketConfiguration;
      66: invokestatic  #27                 // Method io/nats/client/support/JsonUtils.objectString:(Ljava/lang/String;Ljava/lang/Object;)Ljava/lang/String;
      69: invokevirtual #15                 // Method java/lang/StringBuilder.append:(Ljava/lang/String;)Ljava/lang/StringBuilder;
      72: bipush        125
      74: invokevirtual #28                 // Method java/lang/StringBuilder.append:(C)Ljava/lang/StringBuilder;
      77: invokevirtual #29                 // Method java/lang/StringBuilder.toString:()Ljava/lang/String;
      80: areturn
}
