Compiled from "KvOperation.java"
public final class io.nats.client.api.KvOperation extends java.lang.Enum<io.nats.client.api.KvOperation> {
  public static final io.nats.client.api.KvOperation PUT;

  public static final io.nats.client.api.KvOperation DEL;

  private static final java.util.Map<java.lang.String, io.nats.client.api.KvOperation> strEnumHash;

  private static final io.nats.client.api.KvOperation[] $VALUES;

  public static io.nats.client.api.KvOperation[] values();
    Code:
       0: getstatic     #1                  // Field $VALUES:[Lio/nats/client/api/KvOperation;
       3: invokevirtual #2                  // Method "[Lio/nats/client/api/KvOperation;".clone:()Ljava/lang/Object;
       6: checkcast     #3                  // class "[Lio/nats/client/api/KvOperation;"
       9: areturn

  public static io.nats.client.api.KvOperation valueOf(java.lang.String);
    Code:
       0: ldc           #4                  // class io/nats/client/api/KvOperation
       2: aload_0
       3: invokestatic  #5                  // Method java/lang/Enum.valueOf:(Ljava/lang/Class;Ljava/lang/String;)Ljava/lang/Enum;
       6: checkcast     #4                  // class io/nats/client/api/KvOperation
       9: areturn

  private io.nats.client.api.KvOperation();
    Code:
       0: aload_0
       1: aload_1
       2: iload_2
       3: invokespecial #6                  // Method java/lang/Enum."<init>":(Ljava/lang/String;I)V
       6: return

  public static io.nats.client.api.KvOperation getOrDefault(java.lang.String, io.nats.client.api.KvOperation);
    Code:
       0: aload_0
       1: ifnonnull     8
       4: aconst_null
       5: goto          23
       8: getstatic     #7                  // Field strEnumHash:Ljava/util/Map;
      11: aload_0
      12: invokevirtual #8                  // Method java/lang/String.toUpperCase:()Ljava/lang/String;
      15: invokeinterface #9,  2            // InterfaceMethod java/util/Map.get:(Ljava/lang/Object;)Ljava/lang/Object;
      20: checkcast     #4                  // class io/nats/client/api/KvOperation
      23: astore_2
      24: aload_2
      25: ifnonnull     32
      28: aload_1
      29: goto          33
      32: aload_2
      33: areturn

  static {};
    Code:
       0: new           #4                  // class io/nats/client/api/KvOperation
       3: dup
       4: ldc           #10                 // String PUT
       6: iconst_0
       7: invokespecial #11                 // Method "<init>":(Ljava/lang/String;I)V
      10: putstatic     #12                 // Field PUT:Lio/nats/client/api/KvOperation;
      13: new           #4                  // class io/nats/client/api/KvOperation
      16: dup
      17: ldc           #13                 // String DEL
      19: iconst_1
      20: invokespecial #11                 // Method "<init>":(Ljava/lang/String;I)V
      23: putstatic     #14                 // Field DEL:Lio/nats/client/api/KvOperation;
      26: iconst_2
      27: anewarray     #4                  // class io/nats/client/api/KvOperation
      30: dup
      31: iconst_0
      32: getstatic     #12                 // Field PUT:Lio/nats/client/api/KvOperation;
      35: aastore
      36: dup
      37: iconst_1
      38: getstatic     #14                 // Field DEL:Lio/nats/client/api/KvOperation;
      41: aastore
      42: putstatic     #1                  // Field $VALUES:[Lio/nats/client/api/KvOperation;
      45: new           #15                 // class java/util/HashMap
      48: dup
      49: invokespecial #16                 // Method java/util/HashMap."<init>":()V
      52: putstatic     #7                  // Field strEnumHash:Ljava/util/Map;
      55: invokestatic  #17                 // Method values:()[Lio/nats/client/api/KvOperation;
      58: astore_0
      59: aload_0
      60: arraylength
      61: istore_1
      62: iconst_0
      63: istore_2
      64: iload_2
      65: iload_1
      66: if_icmpge     93
      69: aload_0
      70: iload_2
      71: aaload
      72: astore_3
      73: getstatic     #7                  // Field strEnumHash:Ljava/util/Map;
      76: aload_3
      77: invokevirtual #18                 // Method name:()Ljava/lang/String;
      80: aload_3
      81: invokeinterface #19,  3           // InterfaceMethod java/util/Map.put:(Ljava/lang/Object;Ljava/lang/Object;)Ljava/lang/Object;
      86: pop
      87: iinc          2, 1
      90: goto          64
      93: return
}
