Compiled from "NumberNumberMultiply.java"
class org.codehaus.groovy.runtime.dgmimpl.NumberNumberMultiply$IntegerInteger extends org.codehaus.groovy.runtime.dgmimpl.NumberNumberMetaMethod$NumberNumberCallSite {
  public org.codehaus.groovy.runtime.dgmimpl.NumberNumberMultiply$IntegerInteger(org.codehaus.groovy.runtime.callsite.CallSite, groovy.lang.MetaClassImpl, groovy.lang.MetaMethod, java.lang.Class[], java.lang.Object, java.lang.Object[]);
    Code:
       0: aload_0
       1: aload_1
       2: aload_2
       3: aload_3
       4: aload         4
       6: aload         5
       8: checkcast     #15                 // class java/lang/Number
      11: aload         6
      13: iconst_0
      14: aaload
      15: checkcast     #15                 // class java/lang/Number
      18: invokespecial #18                 // Method org/codehaus/groovy/runtime/dgmimpl/NumberNumberMetaMethod$NumberNumberCallSite."<init>":(Lorg/codehaus/groovy/runtime/callsite/CallSite;Lgroovy/lang/MetaClassImpl;Lgroovy/lang/MetaMethod;[Ljava/lang/Class;Ljava/lang/Number;Ljava/lang/Number;)V
      21: return

  public final java.lang.Object call(java.lang.Object, java.lang.Object) throws java.lang.Throwable;
    Code:
       0: aload_0
       1: aload_1
       2: aload_2
       3: invokevirtual #42                 // Method checkCall:(Ljava/lang/Object;Ljava/lang/Object;)Z
       6: ifeq          28
       9: aload_1
      10: checkcast     #44                 // class java/lang/Integer
      13: invokevirtual #48                 // Method java/lang/Integer.intValue:()I
      16: aload_2
      17: checkcast     #44                 // class java/lang/Integer
      20: invokevirtual #48                 // Method java/lang/Integer.intValue:()I
      23: imul
      24: invokestatic  #52                 // Method java/lang/Integer.valueOf:(I)Ljava/lang/Integer;
      27: areturn
      28: goto          32
      31: astore_3
      32: aload_0
      33: aload_1
      34: aload_2
      35: invokespecial #54                 // Method org/codehaus/groovy/runtime/dgmimpl/NumberNumberMetaMethod$NumberNumberCallSite.call:(Ljava/lang/Object;Ljava/lang/Object;)Ljava/lang/Object;
      38: areturn
    Exception table:
       from    to  target type
           0    27    31   Class java/lang/ClassCastException
}
