Compiled from "EnvironmentInfoContributor.java"
public class org.springframework.boot.actuate.info.EnvironmentInfoContributor implements org.springframework.boot.actuate.info.InfoContributor {
  private static final org.springframework.boot.context.properties.bind.Bindable<java.util.Map<java.lang.String, java.lang.Object>> STRING_OBJECT_MAP;

  private final org.springframework.core.env.ConfigurableEnvironment environment;

  public org.springframework.boot.actuate.info.EnvironmentInfoContributor(org.springframework.core.env.ConfigurableEnvironment);
    Code:
       0: aload_0
       1: invokespecial #1                  // Method java/lang/Object."<init>":()V
       4: aload_0
       5: aload_1
       6: putfield      #2                  // Field environment:Lorg/springframework/core/env/ConfigurableEnvironment;
       9: return

  public void contribute(org.springframework.boot.actuate.info.Info$Builder);
    Code:
       0: aload_0
       1: getfield      #2                  // Field environment:Lorg/springframework/core/env/ConfigurableEnvironment;
       4: invokestatic  #3                  // Method org/springframework/boot/context/properties/bind/Binder.get:(Lorg/springframework/core/env/Environment;)Lorg/springframework/boot/context/properties/bind/Binder;
       7: astore_2
       8: aload_2
       9: ldc           #4                  // String info
      11: getstatic     #5                  // Field STRING_OBJECT_MAP:Lorg/springframework/boot/context/properties/bind/Bindable;
      14: invokevirtual #6                  // Method org/springframework/boot/context/properties/bind/Binder.bind:(Ljava/lang/String;Lorg/springframework/boot/context/properties/bind/Bindable;)Lorg/springframework/boot/context/properties/bind/BindResult;
      17: aload_1
      18: dup
      19: invokevirtual #7                  // Method java/lang/Object.getClass:()Ljava/lang/Class;
      22: pop
      23: invokedynamic #8,  0              // InvokeDynamic #0:accept:(Lorg/springframework/boot/actuate/info/Info$Builder;)Ljava/util/function/Consumer;
      28: invokevirtual #9                  // Method org/springframework/boot/context/properties/bind/BindResult.ifBound:(Ljava/util/function/Consumer;)V
      31: return

  static {};
    Code:
       0: ldc           #10                 // class java/lang/String
       2: ldc           #11                 // class java/lang/Object
       4: invokestatic  #12                 // Method org/springframework/boot/context/properties/bind/Bindable.mapOf:(Ljava/lang/Class;Ljava/lang/Class;)Lorg/springframework/boot/context/properties/bind/Bindable;
       7: putstatic     #5                  // Field STRING_OBJECT_MAP:Lorg/springframework/boot/context/properties/bind/Bindable;
      10: return
}
