Compiled from "Info.java"
public class org.springframework.boot.actuate.info.Info$Builder {
  private final java.util.Map<java.lang.String, java.lang.Object> content;

  public org.springframework.boot.actuate.info.Info$Builder();
    Code:
       0: aload_0
       1: invokespecial #2                  // Method java/lang/Object."<init>":()V
       4: aload_0
       5: new           #3                  // class java/util/LinkedHashMap
       8: dup
       9: invokespecial #4                  // Method java/util/LinkedHashMap."<init>":()V
      12: putfield      #1                  // Field content:Ljava/util/Map;
      15: return

  public org.springframework.boot.actuate.info.Info$Builder withDetail(java.lang.String, java.lang.Object);
    Code:
       0: aload_0
       1: getfield      #1                  // Field content:Ljava/util/Map;
       4: aload_1
       5: aload_2
       6: invokeinterface #5,  3            // InterfaceMethod java/util/Map.put:(Ljava/lang/Object;Ljava/lang/Object;)Ljava/lang/Object;
      11: pop
      12: aload_0
      13: areturn

  public org.springframework.boot.actuate.info.Info$Builder withDetails(java.util.Map<java.lang.String, java.lang.Object>);
    Code:
       0: aload_0
       1: getfield      #1                  // Field content:Ljava/util/Map;
       4: aload_1
       5: invokeinterface #6,  2            // InterfaceMethod java/util/Map.putAll:(Ljava/util/Map;)V
      10: aload_0
      11: areturn

  public org.springframework.boot.actuate.info.Info build();
    Code:
       0: new           #7                  // class org/springframework/boot/actuate/info/Info
       3: dup
       4: aload_0
       5: aconst_null
       6: invokespecial #8                  // Method org/springframework/boot/actuate/info/Info."<init>":(Lorg/springframework/boot/actuate/info/Info$Builder;Lorg/springframework/boot/actuate/info/Info$1;)V
       9: areturn

  static java.util.Map access$000(org.springframework.boot.actuate.info.Info$Builder);
    Code:
       0: aload_0
       1: getfield      #1                  // Field content:Ljava/util/Map;
       4: areturn
}
