Compiled from "RejectDependenciesStrategy.java"
public class org.jboss.shrinkwrap.resolver.api.maven.strategy.RejectDependenciesStrategy implements org.jboss.shrinkwrap.resolver.api.maven.strategy.MavenResolutionStrategy {
  private final org.jboss.shrinkwrap.resolver.api.maven.filter.MavenResolutionFilter[] filters;

  public org.jboss.shrinkwrap.resolver.api.maven.strategy.RejectDependenciesStrategy(java.lang.String...) throws java.lang.IllegalArgumentException, org.jboss.shrinkwrap.resolver.api.CoordinateParseException;
    Code:
       0: aload_0
       1: iconst_1
       2: aload_1
       3: invokespecial #1                  // Method "<init>":(Z[Ljava/lang/String;)V
       6: return

  public org.jboss.shrinkwrap.resolver.api.maven.strategy.RejectDependenciesStrategy(boolean, java.lang.String...) throws java.lang.IllegalArgumentException, org.jboss.shrinkwrap.resolver.api.CoordinateParseException;
    Code:
       0: aload_0
       1: invokespecial #2                  // Method java/lang/Object."<init>":()V
       4: aload_2
       5: ifnull        13
       8: aload_2
       9: arraylength
      10: ifne          23
      13: new           #3                  // class java/lang/IllegalArgumentException
      16: dup
      17: ldc           #4                  // String There must be at least one coordinate specified to be rejected.
      19: invokespecial #5                  // Method java/lang/IllegalArgumentException."<init>":(Ljava/lang/String;)V
      22: athrow
      23: aload_0
      24: iconst_1
      25: anewarray     #6                  // class org/jboss/shrinkwrap/resolver/api/maven/filter/MavenResolutionFilter
      28: dup
      29: iconst_0
      30: new           #7                  // class org/jboss/shrinkwrap/resolver/api/maven/filter/RejectDependenciesFilter
      33: dup
      34: iload_1
      35: aload_2
      36: invokespecial #8                  // Method org/jboss/shrinkwrap/resolver/api/maven/filter/RejectDependenciesFilter."<init>":(Z[Ljava/lang/String;)V
      39: aastore
      40: putfield      #9                  // Field filters:[Lorg/jboss/shrinkwrap/resolver/api/maven/filter/MavenResolutionFilter;
      43: return

  public org.jboss.shrinkwrap.resolver.api.maven.filter.MavenResolutionFilter[] getResolutionFilters();
    Code:
       0: aload_0
       1: getfield      #9                  // Field filters:[Lorg/jboss/shrinkwrap/resolver/api/maven/filter/MavenResolutionFilter;
       4: areturn

  public org.jboss.shrinkwrap.resolver.api.maven.strategy.TransitiveExclusionPolicy getTransitiveExclusionPolicy();
    Code:
       0: getstatic     #10                 // Field org/jboss/shrinkwrap/resolver/api/maven/strategy/DefaultTransitiveExclusionPolicy.INSTANCE:Lorg/jboss/shrinkwrap/resolver/api/maven/strategy/DefaultTransitiveExclusionPolicy;
       3: areturn
}
