Compiled from "AdBreak.java"
public interface software.amazon.awssdk.services.mediatailor.model.AdBreak$Builder extends software.amazon.awssdk.core.SdkPojo, software.amazon.awssdk.utils.builder.CopyableBuilder<software.amazon.awssdk.services.mediatailor.model.AdBreak$Builder, software.amazon.awssdk.services.mediatailor.model.AdBreak> {
  public abstract software.amazon.awssdk.services.mediatailor.model.AdBreak$Builder messageType(java.lang.String);

  public abstract software.amazon.awssdk.services.mediatailor.model.AdBreak$Builder messageType(software.amazon.awssdk.services.mediatailor.model.MessageType);

  public abstract software.amazon.awssdk.services.mediatailor.model.AdBreak$Builder offsetMillis(java.lang.Long);

  public abstract software.amazon.awssdk.services.mediatailor.model.AdBreak$Builder slate(software.amazon.awssdk.services.mediatailor.model.SlateSource);

  public default software.amazon.awssdk.services.mediatailor.model.AdBreak$Builder slate(java.util.function.Consumer<software.amazon.awssdk.services.mediatailor.model.SlateSource$Builder>);
    Code:
       0: aload_0
       1: invokestatic  #1                  // Method software/amazon/awssdk/services/mediatailor/model/SlateSource.builder:()Lsoftware/amazon/awssdk/services/mediatailor/model/SlateSource$Builder;
       4: aload_1
       5: invokeinterface #2,  2            // InterfaceMethod software/amazon/awssdk/services/mediatailor/model/SlateSource$Builder.applyMutation:(Ljava/util/function/Consumer;)Lsoftware/amazon/awssdk/utils/builder/SdkBuilder;
      10: checkcast     #3                  // class software/amazon/awssdk/services/mediatailor/model/SlateSource$Builder
      13: invokeinterface #4,  1            // InterfaceMethod software/amazon/awssdk/services/mediatailor/model/SlateSource$Builder.build:()Ljava/lang/Object;
      18: checkcast     #5                  // class software/amazon/awssdk/services/mediatailor/model/SlateSource
      21: invokeinterface #6,  2            // InterfaceMethod slate:(Lsoftware/amazon/awssdk/services/mediatailor/model/SlateSource;)Lsoftware/amazon/awssdk/services/mediatailor/model/AdBreak$Builder;
      26: areturn

  public abstract software.amazon.awssdk.services.mediatailor.model.AdBreak$Builder spliceInsertMessage(software.amazon.awssdk.services.mediatailor.model.SpliceInsertMessage);

  public default software.amazon.awssdk.services.mediatailor.model.AdBreak$Builder spliceInsertMessage(java.util.function.Consumer<software.amazon.awssdk.services.mediatailor.model.SpliceInsertMessage$Builder>);
    Code:
       0: aload_0
       1: invokestatic  #7                  // Method software/amazon/awssdk/services/mediatailor/model/SpliceInsertMessage.builder:()Lsoftware/amazon/awssdk/services/mediatailor/model/SpliceInsertMessage$Builder;
       4: aload_1
       5: invokeinterface #8,  2            // InterfaceMethod software/amazon/awssdk/services/mediatailor/model/SpliceInsertMessage$Builder.applyMutation:(Ljava/util/function/Consumer;)Lsoftware/amazon/awssdk/utils/builder/SdkBuilder;
      10: checkcast     #9                  // class software/amazon/awssdk/services/mediatailor/model/SpliceInsertMessage$Builder
      13: invokeinterface #10,  1           // InterfaceMethod software/amazon/awssdk/services/mediatailor/model/SpliceInsertMessage$Builder.build:()Ljava/lang/Object;
      18: checkcast     #11                 // class software/amazon/awssdk/services/mediatailor/model/SpliceInsertMessage
      21: invokeinterface #12,  2           // InterfaceMethod spliceInsertMessage:(Lsoftware/amazon/awssdk/services/mediatailor/model/SpliceInsertMessage;)Lsoftware/amazon/awssdk/services/mediatailor/model/AdBreak$Builder;
      26: areturn
}
