Compiled from "CreateChannelResponse.java"
final class software.amazon.awssdk.services.mediatailor.model.CreateChannelResponse$BuilderImpl extends software.amazon.awssdk.services.mediatailor.model.MediaTailorResponse$BuilderImpl implements software.amazon.awssdk.services.mediatailor.model.CreateChannelResponse$Builder {
  private java.lang.String arn;

  private java.lang.String channelName;

  private java.lang.String channelState;

  private java.time.Instant creationTime;

  private software.amazon.awssdk.services.mediatailor.model.SlateSource fillerSlate;

  private java.time.Instant lastModifiedTime;

  private java.util.List<software.amazon.awssdk.services.mediatailor.model.ResponseOutputItem> outputs;

  private java.lang.String playbackMode;

  private java.util.Map<java.lang.String, java.lang.String> tags;

  private software.amazon.awssdk.services.mediatailor.model.CreateChannelResponse$BuilderImpl();
    Code:
       0: aload_0
       1: invokespecial #12                 // Method software/amazon/awssdk/services/mediatailor/model/MediaTailorResponse$BuilderImpl."<init>":()V
       4: aload_0
       5: invokestatic  #13                 // Method software/amazon/awssdk/core/util/DefaultSdkAutoConstructList.getInstance:()Lsoftware/amazon/awssdk/core/util/DefaultSdkAutoConstructList;
       8: putfield      #5                  // Field outputs:Ljava/util/List;
      11: aload_0
      12: invokestatic  #14                 // Method software/amazon/awssdk/core/util/DefaultSdkAutoConstructMap.getInstance:()Lsoftware/amazon/awssdk/core/util/DefaultSdkAutoConstructMap;
      15: putfield      #3                  // Field tags:Ljava/util/Map;
      18: return

  private software.amazon.awssdk.services.mediatailor.model.CreateChannelResponse$BuilderImpl(software.amazon.awssdk.services.mediatailor.model.CreateChannelResponse);
    Code:
       0: aload_0
       1: aload_1
       2: invokespecial #15                 // Method software/amazon/awssdk/services/mediatailor/model/MediaTailorResponse$BuilderImpl."<init>":(Lsoftware/amazon/awssdk/services/mediatailor/model/MediaTailorResponse;)V
       5: aload_0
       6: invokestatic  #13                 // Method software/amazon/awssdk/core/util/DefaultSdkAutoConstructList.getInstance:()Lsoftware/amazon/awssdk/core/util/DefaultSdkAutoConstructList;
       9: putfield      #5                  // Field outputs:Ljava/util/List;
      12: aload_0
      13: invokestatic  #14                 // Method software/amazon/awssdk/core/util/DefaultSdkAutoConstructMap.getInstance:()Lsoftware/amazon/awssdk/core/util/DefaultSdkAutoConstructMap;
      16: putfield      #3                  // Field tags:Ljava/util/Map;
      19: aload_0
      20: aload_1
      21: invokestatic  #16                 // Method software/amazon/awssdk/services/mediatailor/model/CreateChannelResponse.access$1100:(Lsoftware/amazon/awssdk/services/mediatailor/model/CreateChannelResponse;)Ljava/lang/String;
      24: invokevirtual #17                 // Method arn:(Ljava/lang/String;)Lsoftware/amazon/awssdk/services/mediatailor/model/CreateChannelResponse$Builder;
      27: pop
      28: aload_0
      29: aload_1
      30: invokestatic  #18                 // Method software/amazon/awssdk/services/mediatailor/model/CreateChannelResponse.access$1200:(Lsoftware/amazon/awssdk/services/mediatailor/model/CreateChannelResponse;)Ljava/lang/String;
      33: invokevirtual #19                 // Method channelName:(Ljava/lang/String;)Lsoftware/amazon/awssdk/services/mediatailor/model/CreateChannelResponse$Builder;
      36: pop
      37: aload_0
      38: aload_1
      39: invokestatic  #20                 // Method software/amazon/awssdk/services/mediatailor/model/CreateChannelResponse.access$1300:(Lsoftware/amazon/awssdk/services/mediatailor/model/CreateChannelResponse;)Ljava/lang/String;
      42: invokevirtual #21                 // Method channelState:(Ljava/lang/String;)Lsoftware/amazon/awssdk/services/mediatailor/model/CreateChannelResponse$Builder;
      45: pop
      46: aload_0
      47: aload_1
      48: invokestatic  #22                 // Method software/amazon/awssdk/services/mediatailor/model/CreateChannelResponse.access$1400:(Lsoftware/amazon/awssdk/services/mediatailor/model/CreateChannelResponse;)Ljava/time/Instant;
      51: invokevirtual #23                 // Method creationTime:(Ljava/time/Instant;)Lsoftware/amazon/awssdk/services/mediatailor/model/CreateChannelResponse$Builder;
      54: pop
      55: aload_0
      56: aload_1
      57: invokestatic  #24                 // Method software/amazon/awssdk/services/mediatailor/model/CreateChannelResponse.access$1500:(Lsoftware/amazon/awssdk/services/mediatailor/model/CreateChannelResponse;)Lsoftware/amazon/awssdk/services/mediatailor/model/SlateSource;
      60: invokevirtual #25                 // Method fillerSlate:(Lsoftware/amazon/awssdk/services/mediatailor/model/SlateSource;)Lsoftware/amazon/awssdk/services/mediatailor/model/CreateChannelResponse$Builder;
      63: pop
      64: aload_0
      65: aload_1
      66: invokestatic  #26                 // Method software/amazon/awssdk/services/mediatailor/model/CreateChannelResponse.access$1600:(Lsoftware/amazon/awssdk/services/mediatailor/model/CreateChannelResponse;)Ljava/time/Instant;
      69: invokevirtual #27                 // Method lastModifiedTime:(Ljava/time/Instant;)Lsoftware/amazon/awssdk/services/mediatailor/model/CreateChannelResponse$Builder;
      72: pop
      73: aload_0
      74: aload_1
      75: invokestatic  #28                 // Method software/amazon/awssdk/services/mediatailor/model/CreateChannelResponse.access$1700:(Lsoftware/amazon/awssdk/services/mediatailor/model/CreateChannelResponse;)Ljava/util/List;
      78: invokevirtual #29                 // Method outputs:(Ljava/util/Collection;)Lsoftware/amazon/awssdk/services/mediatailor/model/CreateChannelResponse$Builder;
      81: pop
      82: aload_0
      83: aload_1
      84: invokestatic  #30                 // Method software/amazon/awssdk/services/mediatailor/model/CreateChannelResponse.access$1800:(Lsoftware/amazon/awssdk/services/mediatailor/model/CreateChannelResponse;)Ljava/lang/String;
      87: invokevirtual #31                 // Method playbackMode:(Ljava/lang/String;)Lsoftware/amazon/awssdk/services/mediatailor/model/CreateChannelResponse$Builder;
      90: pop
      91: aload_0
      92: aload_1
      93: invokestatic  #32                 // Method software/amazon/awssdk/services/mediatailor/model/CreateChannelResponse.access$1900:(Lsoftware/amazon/awssdk/services/mediatailor/model/CreateChannelResponse;)Ljava/util/Map;
      96: invokevirtual #33                 // Method tags:(Ljava/util/Map;)Lsoftware/amazon/awssdk/services/mediatailor/model/CreateChannelResponse$Builder;
      99: pop
     100: return

  public final java.lang.String getArn();
    Code:
       0: aload_0
       1: getfield      #11                 // Field arn:Ljava/lang/String;
       4: areturn

  public final void setArn(java.lang.String);
    Code:
       0: aload_0
       1: aload_1
       2: putfield      #11                 // Field arn:Ljava/lang/String;
       5: return

  public final software.amazon.awssdk.services.mediatailor.model.CreateChannelResponse$Builder arn(java.lang.String);
    Code:
       0: aload_0
       1: aload_1
       2: putfield      #11                 // Field arn:Ljava/lang/String;
       5: aload_0
       6: areturn

  public final java.lang.String getChannelName();
    Code:
       0: aload_0
       1: getfield      #10                 // Field channelName:Ljava/lang/String;
       4: areturn

  public final void setChannelName(java.lang.String);
    Code:
       0: aload_0
       1: aload_1
       2: putfield      #10                 // Field channelName:Ljava/lang/String;
       5: return

  public final software.amazon.awssdk.services.mediatailor.model.CreateChannelResponse$Builder channelName(java.lang.String);
    Code:
       0: aload_0
       1: aload_1
       2: putfield      #10                 // Field channelName:Ljava/lang/String;
       5: aload_0
       6: areturn

  public final java.lang.String getChannelState();
    Code:
       0: aload_0
       1: getfield      #9                  // Field channelState:Ljava/lang/String;
       4: areturn

  public final void setChannelState(java.lang.String);
    Code:
       0: aload_0
       1: aload_1
       2: putfield      #9                  // Field channelState:Ljava/lang/String;
       5: return

  public final software.amazon.awssdk.services.mediatailor.model.CreateChannelResponse$Builder channelState(java.lang.String);
    Code:
       0: aload_0
       1: aload_1
       2: putfield      #9                  // Field channelState:Ljava/lang/String;
       5: aload_0
       6: areturn

  public final software.amazon.awssdk.services.mediatailor.model.CreateChannelResponse$Builder channelState(software.amazon.awssdk.services.mediatailor.model.ChannelState);
    Code:
       0: aload_0
       1: aload_1
       2: ifnonnull     9
       5: aconst_null
       6: goto          13
       9: aload_1
      10: invokevirtual #34                 // Method software/amazon/awssdk/services/mediatailor/model/ChannelState.toString:()Ljava/lang/String;
      13: invokevirtual #21                 // Method channelState:(Ljava/lang/String;)Lsoftware/amazon/awssdk/services/mediatailor/model/CreateChannelResponse$Builder;
      16: pop
      17: aload_0
      18: areturn

  public final java.time.Instant getCreationTime();
    Code:
       0: aload_0
       1: getfield      #8                  // Field creationTime:Ljava/time/Instant;
       4: areturn

  public final void setCreationTime(java.time.Instant);
    Code:
       0: aload_0
       1: aload_1
       2: putfield      #8                  // Field creationTime:Ljava/time/Instant;
       5: return

  public final software.amazon.awssdk.services.mediatailor.model.CreateChannelResponse$Builder creationTime(java.time.Instant);
    Code:
       0: aload_0
       1: aload_1
       2: putfield      #8                  // Field creationTime:Ljava/time/Instant;
       5: aload_0
       6: areturn

  public final software.amazon.awssdk.services.mediatailor.model.SlateSource$Builder getFillerSlate();
    Code:
       0: aload_0
       1: getfield      #7                  // Field fillerSlate:Lsoftware/amazon/awssdk/services/mediatailor/model/SlateSource;
       4: ifnull        17
       7: aload_0
       8: getfield      #7                  // Field fillerSlate:Lsoftware/amazon/awssdk/services/mediatailor/model/SlateSource;
      11: invokevirtual #35                 // Method software/amazon/awssdk/services/mediatailor/model/SlateSource.toBuilder:()Lsoftware/amazon/awssdk/services/mediatailor/model/SlateSource$Builder;
      14: goto          18
      17: aconst_null
      18: areturn

  public final void setFillerSlate(software.amazon.awssdk.services.mediatailor.model.SlateSource$BuilderImpl);
    Code:
       0: aload_0
       1: aload_1
       2: ifnull        12
       5: aload_1
       6: invokevirtual #36                 // Method software/amazon/awssdk/services/mediatailor/model/SlateSource$BuilderImpl.build:()Lsoftware/amazon/awssdk/services/mediatailor/model/SlateSource;
       9: goto          13
      12: aconst_null
      13: putfield      #7                  // Field fillerSlate:Lsoftware/amazon/awssdk/services/mediatailor/model/SlateSource;
      16: return

  public final software.amazon.awssdk.services.mediatailor.model.CreateChannelResponse$Builder fillerSlate(software.amazon.awssdk.services.mediatailor.model.SlateSource);
    Code:
       0: aload_0
       1: aload_1
       2: putfield      #7                  // Field fillerSlate:Lsoftware/amazon/awssdk/services/mediatailor/model/SlateSource;
       5: aload_0
       6: areturn

  public final java.time.Instant getLastModifiedTime();
    Code:
       0: aload_0
       1: getfield      #6                  // Field lastModifiedTime:Ljava/time/Instant;
       4: areturn

  public final void setLastModifiedTime(java.time.Instant);
    Code:
       0: aload_0
       1: aload_1
       2: putfield      #6                  // Field lastModifiedTime:Ljava/time/Instant;
       5: return

  public final software.amazon.awssdk.services.mediatailor.model.CreateChannelResponse$Builder lastModifiedTime(java.time.Instant);
    Code:
       0: aload_0
       1: aload_1
       2: putfield      #6                  // Field lastModifiedTime:Ljava/time/Instant;
       5: aload_0
       6: areturn

  public final java.util.List<software.amazon.awssdk.services.mediatailor.model.ResponseOutputItem$Builder> getOutputs();
    Code:
       0: aload_0
       1: getfield      #5                  // Field outputs:Ljava/util/List;
       4: invokestatic  #37                 // Method software/amazon/awssdk/services/mediatailor/model/ResponseOutputsCopier.copyToBuilder:(Ljava/util/Collection;)Ljava/util/List;
       7: astore_1
       8: aload_1
       9: instanceof    #38                 // class software/amazon/awssdk/core/util/SdkAutoConstructList
      12: ifeq          17
      15: aconst_null
      16: areturn
      17: aload_1
      18: areturn

  public final void setOutputs(java.util.Collection<software.amazon.awssdk.services.mediatailor.model.ResponseOutputItem$BuilderImpl>);
    Code:
       0: aload_0
       1: aload_1
       2: invokestatic  #39                 // Method software/amazon/awssdk/services/mediatailor/model/ResponseOutputsCopier.copyFromBuilder:(Ljava/util/Collection;)Ljava/util/List;
       5: putfield      #5                  // Field outputs:Ljava/util/List;
       8: return

  public final software.amazon.awssdk.services.mediatailor.model.CreateChannelResponse$Builder outputs(java.util.Collection<software.amazon.awssdk.services.mediatailor.model.ResponseOutputItem>);
    Code:
       0: aload_0
       1: aload_1
       2: invokestatic  #40                 // Method software/amazon/awssdk/services/mediatailor/model/ResponseOutputsCopier.copy:(Ljava/util/Collection;)Ljava/util/List;
       5: putfield      #5                  // Field outputs:Ljava/util/List;
       8: aload_0
       9: areturn

  public final software.amazon.awssdk.services.mediatailor.model.CreateChannelResponse$Builder outputs(software.amazon.awssdk.services.mediatailor.model.ResponseOutputItem...);
    Code:
       0: aload_0
       1: aload_1
       2: invokestatic  #41                 // Method java/util/Arrays.asList:([Ljava/lang/Object;)Ljava/util/List;
       5: invokevirtual #29                 // Method outputs:(Ljava/util/Collection;)Lsoftware/amazon/awssdk/services/mediatailor/model/CreateChannelResponse$Builder;
       8: pop
       9: aload_0
      10: areturn

  public final software.amazon.awssdk.services.mediatailor.model.CreateChannelResponse$Builder outputs(java.util.function.Consumer<software.amazon.awssdk.services.mediatailor.model.ResponseOutputItem$Builder>...);
    Code:
       0: aload_0
       1: aload_1
       2: invokestatic  #42                 // InterfaceMethod java/util/stream/Stream.of:([Ljava/lang/Object;)Ljava/util/stream/Stream;
       5: invokedynamic #43,  0             // InvokeDynamic #0:apply:()Ljava/util/function/Function;
      10: invokeinterface #44,  2           // InterfaceMethod java/util/stream/Stream.map:(Ljava/util/function/Function;)Ljava/util/stream/Stream;
      15: invokestatic  #45                 // Method java/util/stream/Collectors.toList:()Ljava/util/stream/Collector;
      18: invokeinterface #46,  2           // InterfaceMethod java/util/stream/Stream.collect:(Ljava/util/stream/Collector;)Ljava/lang/Object;
      23: checkcast     #47                 // class java/util/Collection
      26: invokevirtual #29                 // Method outputs:(Ljava/util/Collection;)Lsoftware/amazon/awssdk/services/mediatailor/model/CreateChannelResponse$Builder;
      29: pop
      30: aload_0
      31: areturn

  public final java.lang.String getPlaybackMode();
    Code:
       0: aload_0
       1: getfield      #4                  // Field playbackMode:Ljava/lang/String;
       4: areturn

  public final void setPlaybackMode(java.lang.String);
    Code:
       0: aload_0
       1: aload_1
       2: putfield      #4                  // Field playbackMode:Ljava/lang/String;
       5: return

  public final software.amazon.awssdk.services.mediatailor.model.CreateChannelResponse$Builder playbackMode(java.lang.String);
    Code:
       0: aload_0
       1: aload_1
       2: putfield      #4                  // Field playbackMode:Ljava/lang/String;
       5: aload_0
       6: areturn

  public final java.util.Map<java.lang.String, java.lang.String> getTags();
    Code:
       0: aload_0
       1: getfield      #3                  // Field tags:Ljava/util/Map;
       4: instanceof    #48                 // class software/amazon/awssdk/core/util/SdkAutoConstructMap
       7: ifeq          12
      10: aconst_null
      11: areturn
      12: aload_0
      13: getfield      #3                  // Field tags:Ljava/util/Map;
      16: areturn

  public final void setTags(java.util.Map<java.lang.String, java.lang.String>);
    Code:
       0: aload_0
       1: aload_1
       2: invokestatic  #49                 // Method software/amazon/awssdk/services/mediatailor/model/___mapOf__stringCopier.copy:(Ljava/util/Map;)Ljava/util/Map;
       5: putfield      #3                  // Field tags:Ljava/util/Map;
       8: return

  public final software.amazon.awssdk.services.mediatailor.model.CreateChannelResponse$Builder tags(java.util.Map<java.lang.String, java.lang.String>);
    Code:
       0: aload_0
       1: aload_1
       2: invokestatic  #49                 // Method software/amazon/awssdk/services/mediatailor/model/___mapOf__stringCopier.copy:(Ljava/util/Map;)Ljava/util/Map;
       5: putfield      #3                  // Field tags:Ljava/util/Map;
       8: aload_0
       9: areturn

  public software.amazon.awssdk.services.mediatailor.model.CreateChannelResponse build();
    Code:
       0: new           #50                 // class software/amazon/awssdk/services/mediatailor/model/CreateChannelResponse
       3: dup
       4: aload_0
       5: aconst_null
       6: invokespecial #51                 // Method software/amazon/awssdk/services/mediatailor/model/CreateChannelResponse."<init>":(Lsoftware/amazon/awssdk/services/mediatailor/model/CreateChannelResponse$BuilderImpl;Lsoftware/amazon/awssdk/services/mediatailor/model/CreateChannelResponse$1;)V
       9: areturn

  public java.util.List<software.amazon.awssdk.core.SdkField<?>> sdkFields();
    Code:
       0: invokestatic  #52                 // Method software/amazon/awssdk/services/mediatailor/model/CreateChannelResponse.access$2100:()Ljava/util/List;
       3: areturn

  public software.amazon.awssdk.services.mediatailor.model.MediaTailorResponse build();
    Code:
       0: aload_0
       1: invokevirtual #53                 // Method build:()Lsoftware/amazon/awssdk/services/mediatailor/model/CreateChannelResponse;
       4: areturn

  public software.amazon.awssdk.awscore.AwsResponse build();
    Code:
       0: aload_0
       1: invokevirtual #53                 // Method build:()Lsoftware/amazon/awssdk/services/mediatailor/model/CreateChannelResponse;
       4: areturn

  public software.amazon.awssdk.core.SdkResponse build();
    Code:
       0: aload_0
       1: invokevirtual #53                 // Method build:()Lsoftware/amazon/awssdk/services/mediatailor/model/CreateChannelResponse;
       4: areturn

  public java.lang.Object build();
    Code:
       0: aload_0
       1: invokevirtual #53                 // Method build:()Lsoftware/amazon/awssdk/services/mediatailor/model/CreateChannelResponse;
       4: areturn

  private static software.amazon.awssdk.services.mediatailor.model.ResponseOutputItem lambda$outputs$0(java.util.function.Consumer);
    Code:
       0: invokestatic  #54                 // Method software/amazon/awssdk/services/mediatailor/model/ResponseOutputItem.builder:()Lsoftware/amazon/awssdk/services/mediatailor/model/ResponseOutputItem$Builder;
       3: aload_0
       4: invokeinterface #55,  2           // InterfaceMethod software/amazon/awssdk/services/mediatailor/model/ResponseOutputItem$Builder.applyMutation:(Ljava/util/function/Consumer;)Lsoftware/amazon/awssdk/utils/builder/SdkBuilder;
       9: checkcast     #56                 // class software/amazon/awssdk/services/mediatailor/model/ResponseOutputItem$Builder
      12: invokeinterface #57,  1           // InterfaceMethod software/amazon/awssdk/services/mediatailor/model/ResponseOutputItem$Builder.build:()Ljava/lang/Object;
      17: checkcast     #58                 // class software/amazon/awssdk/services/mediatailor/model/ResponseOutputItem
      20: areturn

  static java.lang.String access$000(software.amazon.awssdk.services.mediatailor.model.CreateChannelResponse$BuilderImpl);
    Code:
       0: aload_0
       1: getfield      #11                 // Field arn:Ljava/lang/String;
       4: areturn

  static java.lang.String access$100(software.amazon.awssdk.services.mediatailor.model.CreateChannelResponse$BuilderImpl);
    Code:
       0: aload_0
       1: getfield      #10                 // Field channelName:Ljava/lang/String;
       4: areturn

  static java.lang.String access$200(software.amazon.awssdk.services.mediatailor.model.CreateChannelResponse$BuilderImpl);
    Code:
       0: aload_0
       1: getfield      #9                  // Field channelState:Ljava/lang/String;
       4: areturn

  static java.time.Instant access$300(software.amazon.awssdk.services.mediatailor.model.CreateChannelResponse$BuilderImpl);
    Code:
       0: aload_0
       1: getfield      #8                  // Field creationTime:Ljava/time/Instant;
       4: areturn

  static software.amazon.awssdk.services.mediatailor.model.SlateSource access$400(software.amazon.awssdk.services.mediatailor.model.CreateChannelResponse$BuilderImpl);
    Code:
       0: aload_0
       1: getfield      #7                  // Field fillerSlate:Lsoftware/amazon/awssdk/services/mediatailor/model/SlateSource;
       4: areturn

  static java.time.Instant access$500(software.amazon.awssdk.services.mediatailor.model.CreateChannelResponse$BuilderImpl);
    Code:
       0: aload_0
       1: getfield      #6                  // Field lastModifiedTime:Ljava/time/Instant;
       4: areturn

  static java.util.List access$600(software.amazon.awssdk.services.mediatailor.model.CreateChannelResponse$BuilderImpl);
    Code:
       0: aload_0
       1: getfield      #5                  // Field outputs:Ljava/util/List;
       4: areturn

  static java.lang.String access$700(software.amazon.awssdk.services.mediatailor.model.CreateChannelResponse$BuilderImpl);
    Code:
       0: aload_0
       1: getfield      #4                  // Field playbackMode:Ljava/lang/String;
       4: areturn

  static java.util.Map access$800(software.amazon.awssdk.services.mediatailor.model.CreateChannelResponse$BuilderImpl);
    Code:
       0: aload_0
       1: getfield      #3                  // Field tags:Ljava/util/Map;
       4: areturn

  software.amazon.awssdk.services.mediatailor.model.CreateChannelResponse$BuilderImpl(software.amazon.awssdk.services.mediatailor.model.CreateChannelResponse, software.amazon.awssdk.services.mediatailor.model.CreateChannelResponse$1);
    Code:
       0: aload_0
       1: aload_1
       2: invokespecial #2                  // Method "<init>":(Lsoftware/amazon/awssdk/services/mediatailor/model/CreateChannelResponse;)V
       5: return

  software.amazon.awssdk.services.mediatailor.model.CreateChannelResponse$BuilderImpl(software.amazon.awssdk.services.mediatailor.model.CreateChannelResponse$1);
    Code:
       0: aload_0
       1: invokespecial #1                  // Method "<init>":()V
       4: return
}
