Compiled from "ScheduleEntry.java"
final class software.amazon.awssdk.services.mediatailor.model.ScheduleEntry$BuilderImpl implements software.amazon.awssdk.services.mediatailor.model.ScheduleEntry$Builder {
  private java.lang.Long approximateDurationSeconds;

  private java.time.Instant approximateStartTime;

  private java.lang.String arn;

  private java.lang.String channelName;

  private java.lang.String programName;

  private java.util.List<software.amazon.awssdk.services.mediatailor.model.ScheduleAdBreak> scheduleAdBreaks;

  private java.lang.String scheduleEntryType;

  private java.lang.String sourceLocationName;

  private java.lang.String vodSourceName;

  private software.amazon.awssdk.services.mediatailor.model.ScheduleEntry$BuilderImpl();
    Code:
       0: aload_0
       1: invokespecial #12                 // Method java/lang/Object."<init>":()V
       4: aload_0
       5: invokestatic  #13                 // Method software/amazon/awssdk/core/util/DefaultSdkAutoConstructList.getInstance:()Lsoftware/amazon/awssdk/core/util/DefaultSdkAutoConstructList;
       8: putfield      #6                  // Field scheduleAdBreaks:Ljava/util/List;
      11: return

  private software.amazon.awssdk.services.mediatailor.model.ScheduleEntry$BuilderImpl(software.amazon.awssdk.services.mediatailor.model.ScheduleEntry);
    Code:
       0: aload_0
       1: invokespecial #12                 // Method java/lang/Object."<init>":()V
       4: aload_0
       5: invokestatic  #13                 // Method software/amazon/awssdk/core/util/DefaultSdkAutoConstructList.getInstance:()Lsoftware/amazon/awssdk/core/util/DefaultSdkAutoConstructList;
       8: putfield      #6                  // Field scheduleAdBreaks:Ljava/util/List;
      11: aload_0
      12: aload_1
      13: invokestatic  #14                 // Method software/amazon/awssdk/services/mediatailor/model/ScheduleEntry.access$1100:(Lsoftware/amazon/awssdk/services/mediatailor/model/ScheduleEntry;)Ljava/lang/Long;
      16: invokevirtual #15                 // Method approximateDurationSeconds:(Ljava/lang/Long;)Lsoftware/amazon/awssdk/services/mediatailor/model/ScheduleEntry$Builder;
      19: pop
      20: aload_0
      21: aload_1
      22: invokestatic  #16                 // Method software/amazon/awssdk/services/mediatailor/model/ScheduleEntry.access$1200:(Lsoftware/amazon/awssdk/services/mediatailor/model/ScheduleEntry;)Ljava/time/Instant;
      25: invokevirtual #17                 // Method approximateStartTime:(Ljava/time/Instant;)Lsoftware/amazon/awssdk/services/mediatailor/model/ScheduleEntry$Builder;
      28: pop
      29: aload_0
      30: aload_1
      31: invokestatic  #18                 // Method software/amazon/awssdk/services/mediatailor/model/ScheduleEntry.access$1300:(Lsoftware/amazon/awssdk/services/mediatailor/model/ScheduleEntry;)Ljava/lang/String;
      34: invokevirtual #19                 // Method arn:(Ljava/lang/String;)Lsoftware/amazon/awssdk/services/mediatailor/model/ScheduleEntry$Builder;
      37: pop
      38: aload_0
      39: aload_1
      40: invokestatic  #20                 // Method software/amazon/awssdk/services/mediatailor/model/ScheduleEntry.access$1400:(Lsoftware/amazon/awssdk/services/mediatailor/model/ScheduleEntry;)Ljava/lang/String;
      43: invokevirtual #21                 // Method channelName:(Ljava/lang/String;)Lsoftware/amazon/awssdk/services/mediatailor/model/ScheduleEntry$Builder;
      46: pop
      47: aload_0
      48: aload_1
      49: invokestatic  #22                 // Method software/amazon/awssdk/services/mediatailor/model/ScheduleEntry.access$1500:(Lsoftware/amazon/awssdk/services/mediatailor/model/ScheduleEntry;)Ljava/lang/String;
      52: invokevirtual #23                 // Method programName:(Ljava/lang/String;)Lsoftware/amazon/awssdk/services/mediatailor/model/ScheduleEntry$Builder;
      55: pop
      56: aload_0
      57: aload_1
      58: invokestatic  #24                 // Method software/amazon/awssdk/services/mediatailor/model/ScheduleEntry.access$1600:(Lsoftware/amazon/awssdk/services/mediatailor/model/ScheduleEntry;)Ljava/util/List;
      61: invokevirtual #25                 // Method scheduleAdBreaks:(Ljava/util/Collection;)Lsoftware/amazon/awssdk/services/mediatailor/model/ScheduleEntry$Builder;
      64: pop
      65: aload_0
      66: aload_1
      67: invokestatic  #26                 // Method software/amazon/awssdk/services/mediatailor/model/ScheduleEntry.access$1700:(Lsoftware/amazon/awssdk/services/mediatailor/model/ScheduleEntry;)Ljava/lang/String;
      70: invokevirtual #27                 // Method scheduleEntryType:(Ljava/lang/String;)Lsoftware/amazon/awssdk/services/mediatailor/model/ScheduleEntry$Builder;
      73: pop
      74: aload_0
      75: aload_1
      76: invokestatic  #28                 // Method software/amazon/awssdk/services/mediatailor/model/ScheduleEntry.access$1800:(Lsoftware/amazon/awssdk/services/mediatailor/model/ScheduleEntry;)Ljava/lang/String;
      79: invokevirtual #29                 // Method sourceLocationName:(Ljava/lang/String;)Lsoftware/amazon/awssdk/services/mediatailor/model/ScheduleEntry$Builder;
      82: pop
      83: aload_0
      84: aload_1
      85: invokestatic  #30                 // Method software/amazon/awssdk/services/mediatailor/model/ScheduleEntry.access$1900:(Lsoftware/amazon/awssdk/services/mediatailor/model/ScheduleEntry;)Ljava/lang/String;
      88: invokevirtual #31                 // Method vodSourceName:(Ljava/lang/String;)Lsoftware/amazon/awssdk/services/mediatailor/model/ScheduleEntry$Builder;
      91: pop
      92: return

  public final java.lang.Long getApproximateDurationSeconds();
    Code:
       0: aload_0
       1: getfield      #11                 // Field approximateDurationSeconds:Ljava/lang/Long;
       4: areturn

  public final void setApproximateDurationSeconds(java.lang.Long);
    Code:
       0: aload_0
       1: aload_1
       2: putfield      #11                 // Field approximateDurationSeconds:Ljava/lang/Long;
       5: return

  public final software.amazon.awssdk.services.mediatailor.model.ScheduleEntry$Builder approximateDurationSeconds(java.lang.Long);
    Code:
       0: aload_0
       1: aload_1
       2: putfield      #11                 // Field approximateDurationSeconds:Ljava/lang/Long;
       5: aload_0
       6: areturn

  public final java.time.Instant getApproximateStartTime();
    Code:
       0: aload_0
       1: getfield      #10                 // Field approximateStartTime:Ljava/time/Instant;
       4: areturn

  public final void setApproximateStartTime(java.time.Instant);
    Code:
       0: aload_0
       1: aload_1
       2: putfield      #10                 // Field approximateStartTime:Ljava/time/Instant;
       5: return

  public final software.amazon.awssdk.services.mediatailor.model.ScheduleEntry$Builder approximateStartTime(java.time.Instant);
    Code:
       0: aload_0
       1: aload_1
       2: putfield      #10                 // Field approximateStartTime:Ljava/time/Instant;
       5: aload_0
       6: areturn

  public final java.lang.String getArn();
    Code:
       0: aload_0
       1: getfield      #9                  // Field arn:Ljava/lang/String;
       4: areturn

  public final void setArn(java.lang.String);
    Code:
       0: aload_0
       1: aload_1
       2: putfield      #9                  // Field arn:Ljava/lang/String;
       5: return

  public final software.amazon.awssdk.services.mediatailor.model.ScheduleEntry$Builder arn(java.lang.String);
    Code:
       0: aload_0
       1: aload_1
       2: putfield      #9                  // Field arn:Ljava/lang/String;
       5: aload_0
       6: areturn

  public final java.lang.String getChannelName();
    Code:
       0: aload_0
       1: getfield      #8                  // Field channelName:Ljava/lang/String;
       4: areturn

  public final void setChannelName(java.lang.String);
    Code:
       0: aload_0
       1: aload_1
       2: putfield      #8                  // Field channelName:Ljava/lang/String;
       5: return

  public final software.amazon.awssdk.services.mediatailor.model.ScheduleEntry$Builder channelName(java.lang.String);
    Code:
       0: aload_0
       1: aload_1
       2: putfield      #8                  // Field channelName:Ljava/lang/String;
       5: aload_0
       6: areturn

  public final java.lang.String getProgramName();
    Code:
       0: aload_0
       1: getfield      #7                  // Field programName:Ljava/lang/String;
       4: areturn

  public final void setProgramName(java.lang.String);
    Code:
       0: aload_0
       1: aload_1
       2: putfield      #7                  // Field programName:Ljava/lang/String;
       5: return

  public final software.amazon.awssdk.services.mediatailor.model.ScheduleEntry$Builder programName(java.lang.String);
    Code:
       0: aload_0
       1: aload_1
       2: putfield      #7                  // Field programName:Ljava/lang/String;
       5: aload_0
       6: areturn

  public final java.util.List<software.amazon.awssdk.services.mediatailor.model.ScheduleAdBreak$Builder> getScheduleAdBreaks();
    Code:
       0: aload_0
       1: getfield      #6                  // Field scheduleAdBreaks:Ljava/util/List;
       4: invokestatic  #32                 // Method software/amazon/awssdk/services/mediatailor/model/___listOfScheduleAdBreakCopier.copyToBuilder:(Ljava/util/Collection;)Ljava/util/List;
       7: astore_1
       8: aload_1
       9: instanceof    #33                 // class software/amazon/awssdk/core/util/SdkAutoConstructList
      12: ifeq          17
      15: aconst_null
      16: areturn
      17: aload_1
      18: areturn

  public final void setScheduleAdBreaks(java.util.Collection<software.amazon.awssdk.services.mediatailor.model.ScheduleAdBreak$BuilderImpl>);
    Code:
       0: aload_0
       1: aload_1
       2: invokestatic  #34                 // Method software/amazon/awssdk/services/mediatailor/model/___listOfScheduleAdBreakCopier.copyFromBuilder:(Ljava/util/Collection;)Ljava/util/List;
       5: putfield      #6                  // Field scheduleAdBreaks:Ljava/util/List;
       8: return

  public final software.amazon.awssdk.services.mediatailor.model.ScheduleEntry$Builder scheduleAdBreaks(java.util.Collection<software.amazon.awssdk.services.mediatailor.model.ScheduleAdBreak>);
    Code:
       0: aload_0
       1: aload_1
       2: invokestatic  #35                 // Method software/amazon/awssdk/services/mediatailor/model/___listOfScheduleAdBreakCopier.copy:(Ljava/util/Collection;)Ljava/util/List;
       5: putfield      #6                  // Field scheduleAdBreaks:Ljava/util/List;
       8: aload_0
       9: areturn

  public final software.amazon.awssdk.services.mediatailor.model.ScheduleEntry$Builder scheduleAdBreaks(software.amazon.awssdk.services.mediatailor.model.ScheduleAdBreak...);
    Code:
       0: aload_0
       1: aload_1
       2: invokestatic  #36                 // Method java/util/Arrays.asList:([Ljava/lang/Object;)Ljava/util/List;
       5: invokevirtual #25                 // Method scheduleAdBreaks:(Ljava/util/Collection;)Lsoftware/amazon/awssdk/services/mediatailor/model/ScheduleEntry$Builder;
       8: pop
       9: aload_0
      10: areturn

  public final software.amazon.awssdk.services.mediatailor.model.ScheduleEntry$Builder scheduleAdBreaks(java.util.function.Consumer<software.amazon.awssdk.services.mediatailor.model.ScheduleAdBreak$Builder>...);
    Code:
       0: aload_0
       1: aload_1
       2: invokestatic  #37                 // InterfaceMethod java/util/stream/Stream.of:([Ljava/lang/Object;)Ljava/util/stream/Stream;
       5: invokedynamic #38,  0             // InvokeDynamic #0:apply:()Ljava/util/function/Function;
      10: invokeinterface #39,  2           // InterfaceMethod java/util/stream/Stream.map:(Ljava/util/function/Function;)Ljava/util/stream/Stream;
      15: invokestatic  #40                 // Method java/util/stream/Collectors.toList:()Ljava/util/stream/Collector;
      18: invokeinterface #41,  2           // InterfaceMethod java/util/stream/Stream.collect:(Ljava/util/stream/Collector;)Ljava/lang/Object;
      23: checkcast     #42                 // class java/util/Collection
      26: invokevirtual #25                 // Method scheduleAdBreaks:(Ljava/util/Collection;)Lsoftware/amazon/awssdk/services/mediatailor/model/ScheduleEntry$Builder;
      29: pop
      30: aload_0
      31: areturn

  public final java.lang.String getScheduleEntryType();
    Code:
       0: aload_0
       1: getfield      #5                  // Field scheduleEntryType:Ljava/lang/String;
       4: areturn

  public final void setScheduleEntryType(java.lang.String);
    Code:
       0: aload_0
       1: aload_1
       2: putfield      #5                  // Field scheduleEntryType:Ljava/lang/String;
       5: return

  public final software.amazon.awssdk.services.mediatailor.model.ScheduleEntry$Builder scheduleEntryType(java.lang.String);
    Code:
       0: aload_0
       1: aload_1
       2: putfield      #5                  // Field scheduleEntryType:Ljava/lang/String;
       5: aload_0
       6: areturn

  public final software.amazon.awssdk.services.mediatailor.model.ScheduleEntry$Builder scheduleEntryType(software.amazon.awssdk.services.mediatailor.model.ScheduleEntryType);
    Code:
       0: aload_0
       1: aload_1
       2: ifnonnull     9
       5: aconst_null
       6: goto          13
       9: aload_1
      10: invokevirtual #43                 // Method software/amazon/awssdk/services/mediatailor/model/ScheduleEntryType.toString:()Ljava/lang/String;
      13: invokevirtual #27                 // Method scheduleEntryType:(Ljava/lang/String;)Lsoftware/amazon/awssdk/services/mediatailor/model/ScheduleEntry$Builder;
      16: pop
      17: aload_0
      18: areturn

  public final java.lang.String getSourceLocationName();
    Code:
       0: aload_0
       1: getfield      #4                  // Field sourceLocationName:Ljava/lang/String;
       4: areturn

  public final void setSourceLocationName(java.lang.String);
    Code:
       0: aload_0
       1: aload_1
       2: putfield      #4                  // Field sourceLocationName:Ljava/lang/String;
       5: return

  public final software.amazon.awssdk.services.mediatailor.model.ScheduleEntry$Builder sourceLocationName(java.lang.String);
    Code:
       0: aload_0
       1: aload_1
       2: putfield      #4                  // Field sourceLocationName:Ljava/lang/String;
       5: aload_0
       6: areturn

  public final java.lang.String getVodSourceName();
    Code:
       0: aload_0
       1: getfield      #3                  // Field vodSourceName:Ljava/lang/String;
       4: areturn

  public final void setVodSourceName(java.lang.String);
    Code:
       0: aload_0
       1: aload_1
       2: putfield      #3                  // Field vodSourceName:Ljava/lang/String;
       5: return

  public final software.amazon.awssdk.services.mediatailor.model.ScheduleEntry$Builder vodSourceName(java.lang.String);
    Code:
       0: aload_0
       1: aload_1
       2: putfield      #3                  // Field vodSourceName:Ljava/lang/String;
       5: aload_0
       6: areturn

  public software.amazon.awssdk.services.mediatailor.model.ScheduleEntry build();
    Code:
       0: new           #44                 // class software/amazon/awssdk/services/mediatailor/model/ScheduleEntry
       3: dup
       4: aload_0
       5: aconst_null
       6: invokespecial #45                 // Method software/amazon/awssdk/services/mediatailor/model/ScheduleEntry."<init>":(Lsoftware/amazon/awssdk/services/mediatailor/model/ScheduleEntry$BuilderImpl;Lsoftware/amazon/awssdk/services/mediatailor/model/ScheduleEntry$1;)V
       9: areturn

  public java.util.List<software.amazon.awssdk.core.SdkField<?>> sdkFields();
    Code:
       0: invokestatic  #46                 // Method software/amazon/awssdk/services/mediatailor/model/ScheduleEntry.access$2100:()Ljava/util/List;
       3: areturn

  public java.lang.Object build();
    Code:
       0: aload_0
       1: invokevirtual #47                 // Method build:()Lsoftware/amazon/awssdk/services/mediatailor/model/ScheduleEntry;
       4: areturn

  private static software.amazon.awssdk.services.mediatailor.model.ScheduleAdBreak lambda$scheduleAdBreaks$0(java.util.function.Consumer);
    Code:
       0: invokestatic  #48                 // Method software/amazon/awssdk/services/mediatailor/model/ScheduleAdBreak.builder:()Lsoftware/amazon/awssdk/services/mediatailor/model/ScheduleAdBreak$Builder;
       3: aload_0
       4: invokeinterface #49,  2           // InterfaceMethod software/amazon/awssdk/services/mediatailor/model/ScheduleAdBreak$Builder.applyMutation:(Ljava/util/function/Consumer;)Lsoftware/amazon/awssdk/utils/builder/SdkBuilder;
       9: checkcast     #50                 // class software/amazon/awssdk/services/mediatailor/model/ScheduleAdBreak$Builder
      12: invokeinterface #51,  1           // InterfaceMethod software/amazon/awssdk/services/mediatailor/model/ScheduleAdBreak$Builder.build:()Ljava/lang/Object;
      17: checkcast     #52                 // class software/amazon/awssdk/services/mediatailor/model/ScheduleAdBreak
      20: areturn

  static java.lang.Long access$000(software.amazon.awssdk.services.mediatailor.model.ScheduleEntry$BuilderImpl);
    Code:
       0: aload_0
       1: getfield      #11                 // Field approximateDurationSeconds:Ljava/lang/Long;
       4: areturn

  static java.time.Instant access$100(software.amazon.awssdk.services.mediatailor.model.ScheduleEntry$BuilderImpl);
    Code:
       0: aload_0
       1: getfield      #10                 // Field approximateStartTime:Ljava/time/Instant;
       4: areturn

  static java.lang.String access$200(software.amazon.awssdk.services.mediatailor.model.ScheduleEntry$BuilderImpl);
    Code:
       0: aload_0
       1: getfield      #9                  // Field arn:Ljava/lang/String;
       4: areturn

  static java.lang.String access$300(software.amazon.awssdk.services.mediatailor.model.ScheduleEntry$BuilderImpl);
    Code:
       0: aload_0
       1: getfield      #8                  // Field channelName:Ljava/lang/String;
       4: areturn

  static java.lang.String access$400(software.amazon.awssdk.services.mediatailor.model.ScheduleEntry$BuilderImpl);
    Code:
       0: aload_0
       1: getfield      #7                  // Field programName:Ljava/lang/String;
       4: areturn

  static java.util.List access$500(software.amazon.awssdk.services.mediatailor.model.ScheduleEntry$BuilderImpl);
    Code:
       0: aload_0
       1: getfield      #6                  // Field scheduleAdBreaks:Ljava/util/List;
       4: areturn

  static java.lang.String access$600(software.amazon.awssdk.services.mediatailor.model.ScheduleEntry$BuilderImpl);
    Code:
       0: aload_0
       1: getfield      #5                  // Field scheduleEntryType:Ljava/lang/String;
       4: areturn

  static java.lang.String access$700(software.amazon.awssdk.services.mediatailor.model.ScheduleEntry$BuilderImpl);
    Code:
       0: aload_0
       1: getfield      #4                  // Field sourceLocationName:Ljava/lang/String;
       4: areturn

  static java.lang.String access$800(software.amazon.awssdk.services.mediatailor.model.ScheduleEntry$BuilderImpl);
    Code:
       0: aload_0
       1: getfield      #3                  // Field vodSourceName:Ljava/lang/String;
       4: areturn

  software.amazon.awssdk.services.mediatailor.model.ScheduleEntry$BuilderImpl(software.amazon.awssdk.services.mediatailor.model.ScheduleEntry, software.amazon.awssdk.services.mediatailor.model.ScheduleEntry$1);
    Code:
       0: aload_0
       1: aload_1
       2: invokespecial #2                  // Method "<init>":(Lsoftware/amazon/awssdk/services/mediatailor/model/ScheduleEntry;)V
       5: return

  software.amazon.awssdk.services.mediatailor.model.ScheduleEntry$BuilderImpl(software.amazon.awssdk.services.mediatailor.model.ScheduleEntry$1);
    Code:
       0: aload_0
       1: invokespecial #1                  // Method "<init>":()V
       4: return
}
