Compiled from "SimpleMapEntityPersister.groovy"
public class org.grails.datastore.mapping.simple.engine.SimpleMapEntityPersister extends org.grails.datastore.mapping.keyvalue.engine.AbstractKeyValueEntityPersister<java.util.Map, java.lang.Object> implements groovy.lang.GroovyObject {
  private java.util.Map<java.lang.String, java.util.Map> datastore;

  private java.util.Map indices;

  private java.lang.Object lastKey;

  private java.lang.String family;

  private static org.codehaus.groovy.reflection.ClassInfo $staticClassInfo;

  public static transient boolean __$stMC;

  private transient groovy.lang.MetaClass metaClass;

  private static org.codehaus.groovy.reflection.ClassInfo $staticClassInfo$;

  private static java.lang.ref.SoftReference $callSiteArray;

  public org.grails.datastore.mapping.simple.engine.SimpleMapEntityPersister(org.grails.datastore.mapping.model.MappingContext, org.grails.datastore.mapping.model.PersistentEntity, org.grails.datastore.mapping.core.Session, org.grails.datastore.mapping.simple.SimpleMapDatastore, org.springframework.context.ApplicationEventPublisher);
    Code:
       0: invokestatic  #29                 // Method $getCallSiteArray:()[Lorg/codehaus/groovy/runtime/callsite/CallSite;
       3: astore        6
       5: aload_0
       6: aload_1
       7: aload_2
       8: aload_3
       9: aload         5
      11: invokespecial #32                 // Method org/grails/datastore/mapping/keyvalue/engine/AbstractKeyValueEntityPersister."<init>":(Lorg/grails/datastore/mapping/model/MappingContext;Lorg/grails/datastore/mapping/model/PersistentEntity;Lorg/grails/datastore/mapping/core/Session;Lorg/springframework/context/ApplicationEventPublisher;)V
      14: aload_0
      15: invokevirtual #36                 // Method $getStaticMetaClass:()Lgroovy/lang/MetaClass;
      18: astore        7
      20: aload         7
      22: aload_0
      23: swap
      24: putfield      #38                 // Field metaClass:Lgroovy/lang/MetaClass;
      27: aload         7
      29: pop
      30: aload         6
      32: ldc           #39                 // int 0
      34: aaload
      35: aload         4
      37: invokeinterface #45,  2           // InterfaceMethod org/codehaus/groovy/runtime/callsite/CallSite.callGetProperty:(Ljava/lang/Object;)Ljava/lang/Object;
      42: astore        8
      44: aload         8
      46: ldc           #47                 // class java/util/Map
      48: invokestatic  #53                 // Method org/codehaus/groovy/runtime/ScriptBytecodeAdapter.castToType:(Ljava/lang/Object;Ljava/lang/Class;)Ljava/lang/Object;
      51: checkcast     #47                 // class java/util/Map
      54: aload_0
      55: swap
      56: putfield      #55                 // Field datastore:Ljava/util/Map;
      59: aload         8
      61: pop
      62: aload         6
      64: ldc           #56                 // int 1
      66: aaload
      67: aload         4
      69: invokeinterface #45,  2           // InterfaceMethod org/codehaus/groovy/runtime/callsite/CallSite.callGetProperty:(Ljava/lang/Object;)Ljava/lang/Object;
      74: astore        9
      76: aload         9
      78: ldc           #47                 // class java/util/Map
      80: invokestatic  #53                 // Method org/codehaus/groovy/runtime/ScriptBytecodeAdapter.castToType:(Ljava/lang/Object;Ljava/lang/Class;)Ljava/lang/Object;
      83: checkcast     #47                 // class java/util/Map
      86: aload_0
      87: swap
      88: putfield      #58                 // Field indices:Ljava/util/Map;
      91: aload         9
      93: pop
      94: aload         6
      96: ldc           #59                 // int 2
      98: aaload
      99: aload_0
     100: aload_2
     101: aload         6
     103: ldc           #60                 // int 3
     105: aaload
     106: aload_2
     107: invokeinterface #63,  2           // InterfaceMethod org/codehaus/groovy/runtime/callsite/CallSite.call:(Ljava/lang/Object;)Ljava/lang/Object;
     112: invokeinterface #67,  4           // InterfaceMethod org/codehaus/groovy/runtime/callsite/CallSite.callCurrent:(Lgroovy/lang/GroovyObject;Ljava/lang/Object;Ljava/lang/Object;)Ljava/lang/Object;
     117: astore        10
     119: aload         10
     121: invokestatic  #73                 // Method org/codehaus/groovy/runtime/typehandling/ShortTypeHandling.castToString:(Ljava/lang/Object;)Ljava/lang/String;
     124: checkcast     #75                 // class java/lang/String
     127: aload_0
     128: swap
     129: putfield      #77                 // Field family:Ljava/lang/String;
     132: aload         10
     134: pop
     135: aload         6
     137: ldc           #78                 // int 4
     139: aaload
     140: aload_2
     141: invokeinterface #63,  2           // InterfaceMethod org/codehaus/groovy/runtime/callsite/CallSite.call:(Ljava/lang/Object;)Ljava/lang/Object;
     146: astore        11
     148: aload         11
     150: pop
     151: aload         6
     153: ldc           #79                 // int 5
     155: aaload
     156: aload         11
     158: invokeinterface #82,  2           // InterfaceMethod org/codehaus/groovy/runtime/callsite/CallSite.callGetPropertySafe:(Ljava/lang/Object;)Ljava/lang/Object;
     163: astore        12
     165: aload         12
     167: pop
     168: aload         12
     170: ldc           #84                 // class java/lang/Integer
     172: invokestatic  #88                 // Method org/codehaus/groovy/runtime/ScriptBytecodeAdapter.compareEqual:(Ljava/lang/Object;Ljava/lang/Object;)Z
     175: ifeq          197
     178: iconst_0
     179: istore        13
     181: iload         13
     183: invokestatic  #92                 // Method java/lang/Integer.valueOf:(I)Ljava/lang/Integer;
     186: aload_0
     187: swap
     188: putfield      #94                 // Field lastKey:Ljava/lang/Object;
     191: iload         13
     193: pop
     194: goto          213
     197: lconst_0
     198: lstore        14
     200: lload         14
     202: invokestatic  #99                 // Method java/lang/Long.valueOf:(J)Ljava/lang/Long;
     205: aload_0
     206: swap
     207: putfield      #94                 // Field lastKey:Ljava/lang/Object;
     210: lload         14
     212: pop2
     213: aload         6
     215: ldc           #100                // int 6
     217: aaload
     218: aload_0
     219: getfield      #55                 // Field datastore:Ljava/util/Map;
     222: aload_0
     223: getfield      #77                 // Field family:Ljava/lang/String;
     226: invokeinterface #103,  3          // InterfaceMethod org/codehaus/groovy/runtime/callsite/CallSite.call:(Ljava/lang/Object;Ljava/lang/Object;)Ljava/lang/Object;
     231: aconst_null
     232: invokestatic  #88                 // Method org/codehaus/groovy/runtime/ScriptBytecodeAdapter.compareEqual:(Ljava/lang/Object;Ljava/lang/Object;)Z
     235: ifeq          271
     238: iconst_0
     239: anewarray     #105                // class java/lang/Object
     242: invokestatic  #109                // Method org/codehaus/groovy/runtime/ScriptBytecodeAdapter.createMap:([Ljava/lang/Object;)Ljava/util/Map;
     245: astore        16
     247: aload         6
     249: ldc           #110                // int 7
     251: aaload
     252: aload_0
     253: getfield      #55                 // Field datastore:Ljava/util/Map;
     256: aload_0
     257: getfield      #77                 // Field family:Ljava/lang/String;
     260: aload         16
     262: invokeinterface #113,  4          // InterfaceMethod org/codehaus/groovy/runtime/callsite/CallSite.call:(Ljava/lang/Object;Ljava/lang/Object;Ljava/lang/Object;)Ljava/lang/Object;
     267: pop
     268: aload         16
     270: pop
     271: return

  protected org.grails.datastore.mapping.model.PersistentEntity discriminatePersistentEntity(org.grails.datastore.mapping.model.PersistentEntity, java.util.Map);
    Code:
       0: invokestatic  #29                 // Method $getCallSiteArray:()[Lorg/codehaus/groovy/runtime/callsite/CallSite;
       3: astore_3
       4: aload_3
       5: ldc           #143                // int 8
       7: aaload
       8: aload_2
       9: invokeinterface #82,  2           // InterfaceMethod org/codehaus/groovy/runtime/callsite/CallSite.callGetPropertySafe:(Ljava/lang/Object;)Ljava/lang/Object;
      14: astore        4
      16: aload         4
      18: pop
      19: aload         4
      21: invokestatic  #149                // Method org/codehaus/groovy/runtime/typehandling/DefaultTypeTransformation.booleanUnbox:(Ljava/lang/Object;)Z
      24: ifeq          82
      27: aload_3
      28: ldc           #150                // int 9
      30: aaload
      31: aload_3
      32: ldc           #151                // int 10
      34: aaload
      35: aload_0
      36: invokeinterface #154,  2          // InterfaceMethod org/codehaus/groovy/runtime/callsite/CallSite.callCurrent:(Lgroovy/lang/GroovyObject;)Ljava/lang/Object;
      41: aload_3
      42: ldc           #155                // int 11
      44: aaload
      45: aload_1
      46: invokeinterface #45,  2           // InterfaceMethod org/codehaus/groovy/runtime/callsite/CallSite.callGetProperty:(Ljava/lang/Object;)Ljava/lang/Object;
      51: aload         4
      53: invokeinterface #113,  4          // InterfaceMethod org/codehaus/groovy/runtime/callsite/CallSite.call:(Ljava/lang/Object;Ljava/lang/Object;Ljava/lang/Object;)Ljava/lang/Object;
      58: astore        5
      60: aload         5
      62: pop
      63: aload         5
      65: invokestatic  #149                // Method org/codehaus/groovy/runtime/typehandling/DefaultTypeTransformation.booleanUnbox:(Ljava/lang/Object;)Z
      68: ifeq          82
      71: aload         5
      73: ldc           #130                // class org/grails/datastore/mapping/model/PersistentEntity
      75: invokestatic  #53                 // Method org/codehaus/groovy/runtime/ScriptBytecodeAdapter.castToType:(Ljava/lang/Object;Ljava/lang/Class;)Ljava/lang/Object;
      78: checkcast     #130                // class org/grails/datastore/mapping/model/PersistentEntity
      81: areturn
      82: aload_1
      83: areturn
      84: nop
      85: athrow

  public org.grails.datastore.mapping.query.Query createQuery();
    Code:
       0: invokestatic  #29                 // Method $getCallSiteArray:()[Lorg/codehaus/groovy/runtime/callsite/CallSite;
       3: astore_1
       4: aload_1
       5: ldc           #164                // int 12
       7: aaload
       8: ldc           #166                // class org/grails/datastore/mapping/simple/query/SimpleMapQuery
      10: aload_1
      11: ldc           #167                // int 13
      13: aaload
      14: aload_0
      15: invokeinterface #170,  2          // InterfaceMethod org/codehaus/groovy/runtime/callsite/CallSite.callGroovyObjectGetProperty:(Ljava/lang/Object;)Ljava/lang/Object;
      20: aload_1
      21: ldc           #171                // int 14
      23: aaload
      24: aload_0
      25: invokeinterface #154,  2          // InterfaceMethod org/codehaus/groovy/runtime/callsite/CallSite.callCurrent:(Lgroovy/lang/GroovyObject;)Ljava/lang/Object;
      30: aload_0
      31: invokeinterface #175,  5          // InterfaceMethod org/codehaus/groovy/runtime/callsite/CallSite.callConstructor:(Ljava/lang/Object;Ljava/lang/Object;Ljava/lang/Object;Ljava/lang/Object;)Ljava/lang/Object;
      36: ldc           #177                // class org/grails/datastore/mapping/query/Query
      38: invokestatic  #53                 // Method org/codehaus/groovy/runtime/ScriptBytecodeAdapter.castToType:(Ljava/lang/Object;Ljava/lang/Class;)Ljava/lang/Object;
      41: checkcast     #177                // class org/grails/datastore/mapping/query/Query
      44: areturn
      45: nop
      46: athrow

  protected void deleteEntry(java.lang.String, java.lang.Object, java.lang.Object);
    Code:
       0: invokestatic  #29                 // Method $getCallSiteArray:()[Lorg/codehaus/groovy/runtime/callsite/CallSite;
       3: astore        4
       5: aload         4
       7: ldc           #180                // int 15
       9: aaload
      10: aload         4
      12: ldc           #181                // int 16
      14: aaload
      15: aload_0
      16: getfield      #55                 // Field datastore:Ljava/util/Map;
      19: aload_1
      20: invokeinterface #103,  3          // InterfaceMethod org/codehaus/groovy/runtime/callsite/CallSite.call:(Ljava/lang/Object;Ljava/lang/Object;)Ljava/lang/Object;
      25: aload_2
      26: invokeinterface #103,  3          // InterfaceMethod org/codehaus/groovy/runtime/callsite/CallSite.call:(Ljava/lang/Object;Ljava/lang/Object;)Ljava/lang/Object;
      31: pop
      32: aload         4
      34: ldc           #182                // int 17
      36: aaload
      37: aload         4
      39: ldc           #183                // int 18
      41: aaload
      42: aload_0
      43: invokeinterface #170,  2          // InterfaceMethod org/codehaus/groovy/runtime/callsite/CallSite.callGroovyObjectGetProperty:(Ljava/lang/Object;)Ljava/lang/Object;
      48: invokeinterface #45,  2           // InterfaceMethod org/codehaus/groovy/runtime/callsite/CallSite.callGetProperty:(Ljava/lang/Object;)Ljava/lang/Object;
      53: astore        5
      55: aload         5
      57: pop
      58: aload         5
      60: aconst_null
      61: invokestatic  #186                // Method org/codehaus/groovy/runtime/ScriptBytecodeAdapter.compareNotEqual:(Ljava/lang/Object;Ljava/lang/Object;)Z
      64: ifeq          149
      67: aload         4
      69: ldc           #187                // int 19
      71: aaload
      72: aload_0
      73: aload         5
      75: aload         4
      77: ldc           #188                // int 20
      79: aaload
      80: aload         5
      82: invokeinterface #45,  2           // InterfaceMethod org/codehaus/groovy/runtime/callsite/CallSite.callGetProperty:(Ljava/lang/Object;)Ljava/lang/Object;
      87: invokeinterface #67,  4           // InterfaceMethod org/codehaus/groovy/runtime/callsite/CallSite.callCurrent:(Lgroovy/lang/GroovyObject;Ljava/lang/Object;Ljava/lang/Object;)Ljava/lang/Object;
      92: astore        6
      94: aload         6
      96: pop
      97: aload         4
      99: ldc           #189                // int 21
     101: aaload
     102: aload         4
     104: ldc           #190                // int 22
     106: aaload
     107: aload_0
     108: getfield      #55                 // Field datastore:Ljava/util/Map;
     111: aload         6
     113: invokeinterface #103,  3          // InterfaceMethod org/codehaus/groovy/runtime/callsite/CallSite.call:(Ljava/lang/Object;Ljava/lang/Object;)Ljava/lang/Object;
     118: aload_2
     119: invokeinterface #103,  3          // InterfaceMethod org/codehaus/groovy/runtime/callsite/CallSite.call:(Ljava/lang/Object;Ljava/lang/Object;)Ljava/lang/Object;
     124: pop
     125: aload         4
     127: ldc           #191                // int 23
     129: aaload
     130: aload         5
     132: invokeinterface #45,  2           // InterfaceMethod org/codehaus/groovy/runtime/callsite/CallSite.callGetProperty:(Ljava/lang/Object;)Ljava/lang/Object;
     137: astore        7
     139: aload         7
     141: astore        5
     143: aload         7
     145: pop
     146: goto          58
     149: return

  protected boolean isPropertyIndexed(org.grails.datastore.mapping.config.Property);
    Code:
       0: invokestatic  #29                 // Method $getCallSiteArray:()[Lorg/codehaus/groovy/runtime/callsite/CallSite;
       3: astore_2
       4: iconst_1
       5: ireturn
       6: nop
       7: nop
       8: nop
       9: nop
      10: nop
      11: nop
      12: nop
      13: nop
      14: athrow

  public org.grails.datastore.mapping.engine.PropertyValueIndexer getPropertyIndexer(org.grails.datastore.mapping.model.PersistentProperty);
    Code:
       0: aload_1
       1: new           #203                // class groovy/lang/Reference
       4: dup_x1
       5: swap
       6: invokespecial #206                // Method groovy/lang/Reference."<init>":(Ljava/lang/Object;)V
       9: astore_2
      10: invokestatic  #29                 // Method $getCallSiteArray:()[Lorg/codehaus/groovy/runtime/callsite/CallSite;
      13: astore_3
      14: new           #208                // class org/grails/datastore/mapping/simple/engine/SimpleMapEntityPersister$1
      17: dup
      18: aload_0
      19: aload_2
      20: invokespecial #211                // Method org/grails/datastore/mapping/simple/engine/SimpleMapEntityPersister$1."<init>":(Lorg/grails/datastore/mapping/simple/engine/SimpleMapEntityPersister;Lgroovy/lang/Reference;)V
      23: areturn
      24: nop
      25: athrow

  public org.grails.datastore.mapping.engine.AssociationIndexer getAssociationIndexer(java.util.Map, org.grails.datastore.mapping.model.types.Association);
    Code:
       0: aload_2
       1: new           #203                // class groovy/lang/Reference
       4: dup_x1
       5: swap
       6: invokespecial #206                // Method groovy/lang/Reference."<init>":(Ljava/lang/Object;)V
       9: astore_3
      10: invokestatic  #29                 // Method $getCallSiteArray:()[Lorg/codehaus/groovy/runtime/callsite/CallSite;
      13: astore        4
      15: aload         4
      17: ldc           #217                // int 24
      19: aaload
      20: aload_3
      21: invokevirtual #221                // Method groovy/lang/Reference.get:()Ljava/lang/Object;
      24: checkcast     #223                // class org/grails/datastore/mapping/model/types/Association
      27: invokeinterface #82,  2           // InterfaceMethod org/codehaus/groovy/runtime/callsite/CallSite.callGetPropertySafe:(Ljava/lang/Object;)Ljava/lang/Object;
      32: aconst_null
      33: invokestatic  #88                 // Method org/codehaus/groovy/runtime/ScriptBytecodeAdapter.compareEqual:(Ljava/lang/Object;Ljava/lang/Object;)Z
      36: ifeq          49
      39: aconst_null
      40: ldc           #225                // class org/grails/datastore/mapping/engine/AssociationIndexer
      42: invokestatic  #53                 // Method org/codehaus/groovy/runtime/ScriptBytecodeAdapter.castToType:(Ljava/lang/Object;Ljava/lang/Class;)Ljava/lang/Object;
      45: checkcast     #225                // class org/grails/datastore/mapping/engine/AssociationIndexer
      48: areturn
      49: new           #227                // class org/grails/datastore/mapping/simple/engine/SimpleMapEntityPersister$2
      52: dup
      53: aload_0
      54: aload_3
      55: invokespecial #228                // Method org/grails/datastore/mapping/simple/engine/SimpleMapEntityPersister$2."<init>":(Lorg/grails/datastore/mapping/simple/engine/SimpleMapEntityPersister;Lgroovy/lang/Reference;)V
      58: areturn
      59: nop
      60: athrow

  protected void setManyToMany(org.grails.datastore.mapping.model.PersistentEntity, java.lang.Object, java.util.Map, org.grails.datastore.mapping.model.types.ManyToMany, java.util.Collection, java.util.Map<org.grails.datastore.mapping.model.types.Association, java.util.List<java.io.Serializable>>);
    Code:
       0: invokestatic  #29                 // Method $getCallSiteArray:()[Lorg/codehaus/groovy/runtime/callsite/CallSite;
       3: astore        7
       5: aconst_null
       6: astore        8
       8: aload         8
      10: pop
      11: aload         7
      13: ldc           #233                // int 25
      15: aaload
      16: aload         4
      18: invokeinterface #63,  2           // InterfaceMethod org/codehaus/groovy/runtime/callsite/CallSite.call:(Ljava/lang/Object;)Ljava/lang/Object;
      23: invokestatic  #149                // Method org/codehaus/groovy/runtime/typehandling/DefaultTypeTransformation.booleanUnbox:(Ljava/lang/Object;)Z
      26: ifeq          64
      29: aload         7
      31: ldc           #234                // int 26
      33: aaload
      34: aload         7
      36: ldc           #235                // int 27
      38: aaload
      39: aload_0
      40: invokeinterface #170,  2          // InterfaceMethod org/codehaus/groovy/runtime/callsite/CallSite.callGroovyObjectGetProperty:(Ljava/lang/Object;)Ljava/lang/Object;
      45: aload         5
      47: invokeinterface #103,  3          // InterfaceMethod org/codehaus/groovy/runtime/callsite/CallSite.call:(Ljava/lang/Object;Ljava/lang/Object;)Ljava/lang/Object;
      52: astore        9
      54: aload         9
      56: astore        8
      58: aload         9
      60: pop
      61: goto          94
      64: aload         7
      66: ldc           #236                // int 28
      68: aaload
      69: aload         5
      71: new           #238                // class org/grails/datastore/mapping/simple/engine/SimpleMapEntityPersister$_setManyToMany_closure1
      74: dup
      75: aload_0
      76: aload_0
      77: invokespecial #241                // Method org/grails/datastore/mapping/simple/engine/SimpleMapEntityPersister$_setManyToMany_closure1."<init>":(Ljava/lang/Object;Ljava/lang/Object;)V
      80: invokeinterface #103,  3          // InterfaceMethod org/codehaus/groovy/runtime/callsite/CallSite.call:(Ljava/lang/Object;Ljava/lang/Object;)Ljava/lang/Object;
      85: astore        10
      87: aload         10
      89: astore        8
      91: aload         10
      93: pop
      94: aload         7
      96: ldc           #242                // int 29
      98: aaload
      99: aload         6
     101: aload         4
     103: aload         8
     105: invokeinterface #113,  4          // InterfaceMethod org/codehaus/groovy/runtime/callsite/CallSite.call:(Ljava/lang/Object;Ljava/lang/Object;Ljava/lang/Object;)Ljava/lang/Object;
     110: pop
     111: return

  protected java.util.Collection getManyToManyKeys(org.grails.datastore.mapping.model.PersistentEntity, java.lang.Object, java.io.Serializable, java.util.Map, org.grails.datastore.mapping.model.types.ManyToMany);
    Code:
       0: invokestatic  #29                 // Method $getCallSiteArray:()[Lorg/codehaus/groovy/runtime/callsite/CallSite;
       3: astore        6
       5: aload         6
       7: ldc_w         #256                // int 30
      10: aaload
      11: aload_0
      12: aload         4
      14: aload         5
      16: invokeinterface #67,  4           // InterfaceMethod org/codehaus/groovy/runtime/callsite/CallSite.callCurrent:(Lgroovy/lang/GroovyObject;Ljava/lang/Object;Ljava/lang/Object;)Ljava/lang/Object;
      21: astore        7
      23: aload         7
      25: pop
      26: aload         6
      28: ldc_w         #257                // int 31
      31: aaload
      32: aload_0
      33: aload_2
      34: invokeinterface #260,  3          // InterfaceMethod org/codehaus/groovy/runtime/callsite/CallSite.callCurrent:(Lgroovy/lang/GroovyObject;Ljava/lang/Object;)Ljava/lang/Object;
      39: astore        8
      41: aload         8
      43: pop
      44: aload         6
      46: ldc_w         #261                // int 32
      49: aaload
      50: aload         7
      52: aload         8
      54: invokeinterface #103,  3          // InterfaceMethod org/codehaus/groovy/runtime/callsite/CallSite.call:(Ljava/lang/Object;Ljava/lang/Object;)Ljava/lang/Object;
      59: ldc           #253                // class java/util/Collection
      61: invokestatic  #53                 // Method org/codehaus/groovy/runtime/ScriptBytecodeAdapter.castToType:(Ljava/lang/Object;Ljava/lang/Class;)Ljava/lang/Object;
      64: checkcast     #253                // class java/util/Collection
      67: areturn
      68: nop
      69: athrow

  protected java.util.Map createNewEntry(java.lang.String);
    Code:
       0: invokestatic  #29                 // Method $getCallSiteArray:()[Lorg/codehaus/groovy/runtime/callsite/CallSite;
       3: astore_2
       4: iconst_0
       5: anewarray     #105                // class java/lang/Object
       8: invokestatic  #109                // Method org/codehaus/groovy/runtime/ScriptBytecodeAdapter.createMap:([Ljava/lang/Object;)Ljava/util/Map;
      11: areturn
      12: nop
      13: athrow

  protected java.lang.Object getEntryValue(java.util.Map, java.lang.String);
    Code:
       0: invokestatic  #29                 // Method $getCallSiteArray:()[Lorg/codehaus/groovy/runtime/callsite/CallSite;
       3: astore_3
       4: aload_3
       5: ldc_w         #270                // int 33
       8: aaload
       9: aload_1
      10: aload_2
      11: invokeinterface #103,  3          // InterfaceMethod org/codehaus/groovy/runtime/callsite/CallSite.call:(Ljava/lang/Object;Ljava/lang/Object;)Ljava/lang/Object;
      16: areturn
      17: nop
      18: athrow

  protected void setEntryValue(java.util.Map, java.lang.String, java.lang.Object);
    Code:
       0: invokestatic  #29                 // Method $getCallSiteArray:()[Lorg/codehaus/groovy/runtime/callsite/CallSite;
       3: astore        4
       5: aload         4
       7: ldc_w         #273                // int 34
      10: aaload
      11: aload         4
      13: ldc_w         #274                // int 35
      16: aaload
      17: aload_0
      18: invokeinterface #170,  2          // InterfaceMethod org/codehaus/groovy/runtime/callsite/CallSite.callGroovyObjectGetProperty:(Ljava/lang/Object;)Ljava/lang/Object;
      23: aload_3
      24: invokeinterface #103,  3          // InterfaceMethod org/codehaus/groovy/runtime/callsite/CallSite.call:(Ljava/lang/Object;Ljava/lang/Object;)Ljava/lang/Object;
      29: invokestatic  #149                // Method org/codehaus/groovy/runtime/typehandling/DefaultTypeTransformation.booleanUnbox:(Ljava/lang/Object;)Z
      32: ifeq          95
      35: aload         4
      37: ldc_w         #275                // int 36
      40: aaload
      41: aload         4
      43: ldc_w         #276                // int 37
      46: aaload
      47: aload_0
      48: invokeinterface #170,  2          // InterfaceMethod org/codehaus/groovy/runtime/callsite/CallSite.callGroovyObjectGetProperty:(Ljava/lang/Object;)Ljava/lang/Object;
      53: aload_3
      54: invokeinterface #103,  3          // InterfaceMethod org/codehaus/groovy/runtime/callsite/CallSite.call:(Ljava/lang/Object;Ljava/lang/Object;)Ljava/lang/Object;
      59: ldc_w         #278                // class org/grails/datastore/mapping/engine/EntityPersister
      62: invokestatic  #53                 // Method org/codehaus/groovy/runtime/ScriptBytecodeAdapter.castToType:(Ljava/lang/Object;Ljava/lang/Class;)Ljava/lang/Object;
      65: checkcast     #278                // class org/grails/datastore/mapping/engine/EntityPersister
      68: astore        5
      70: aload         5
      72: pop
      73: aload         4
      75: ldc_w         #279                // int 38
      78: aaload
      79: aload         5
      81: aload_3
      82: invokeinterface #103,  3          // InterfaceMethod org/codehaus/groovy/runtime/callsite/CallSite.call:(Ljava/lang/Object;Ljava/lang/Object;)Ljava/lang/Object;
      87: astore        6
      89: aload         6
      91: astore_3
      92: aload         6
      94: pop
      95: aload_3
      96: astore        7
      98: aload         4
     100: ldc_w         #280                // int 39
     103: aaload
     104: aload_1
     105: aload_2
     106: aload         7
     108: invokeinterface #113,  4          // InterfaceMethod org/codehaus/groovy/runtime/callsite/CallSite.call:(Ljava/lang/Object;Ljava/lang/Object;Ljava/lang/Object;)Ljava/lang/Object;
     113: pop
     114: aload         7
     116: pop
     117: return

  protected void setEmbedded(java.util.Map, java.lang.String, java.util.Map);
    Code:
       0: invokestatic  #29                 // Method $getCallSiteArray:()[Lorg/codehaus/groovy/runtime/callsite/CallSite;
       3: astore        4
       5: aload_3
       6: astore        5
       8: aload         4
      10: ldc_w         #286                // int 40
      13: aaload
      14: aload_1
      15: aload_2
      16: aload         5
      18: invokeinterface #113,  4          // InterfaceMethod org/codehaus/groovy/runtime/callsite/CallSite.call:(Ljava/lang/Object;Ljava/lang/Object;Ljava/lang/Object;)Ljava/lang/Object;
      23: pop
      24: aload         5
      26: pop
      27: return

  protected java.util.Map getEmbedded(java.util.Map, java.lang.String);
    Code:
       0: invokestatic  #29                 // Method $getCallSiteArray:()[Lorg/codehaus/groovy/runtime/callsite/CallSite;
       3: astore_3
       4: aload_3
       5: ldc_w         #290                // int 41
       8: aaload
       9: aload_1
      10: aload_2
      11: invokeinterface #103,  3          // InterfaceMethod org/codehaus/groovy/runtime/callsite/CallSite.call:(Ljava/lang/Object;Ljava/lang/Object;)Ljava/lang/Object;
      16: ldc           #47                 // class java/util/Map
      18: invokestatic  #53                 // Method org/codehaus/groovy/runtime/ScriptBytecodeAdapter.castToType:(Ljava/lang/Object;Ljava/lang/Class;)Ljava/lang/Object;
      21: checkcast     #47                 // class java/util/Map
      24: areturn
      25: nop
      26: athrow

  protected java.util.Map retrieveEntry(org.grails.datastore.mapping.model.PersistentEntity, java.lang.String, java.io.Serializable);
    Code:
       0: invokestatic  #29                 // Method $getCallSiteArray:()[Lorg/codehaus/groovy/runtime/callsite/CallSite;
       3: astore        4
       5: aload         4
       7: ldc_w         #293                // int 42
      10: aaload
      11: aload         4
      13: ldc_w         #294                // int 43
      16: aaload
      17: aload_0
      18: getfield      #55                 // Field datastore:Ljava/util/Map;
      21: aload_2
      22: invokeinterface #103,  3          // InterfaceMethod org/codehaus/groovy/runtime/callsite/CallSite.call:(Ljava/lang/Object;Ljava/lang/Object;)Ljava/lang/Object;
      27: aload_3
      28: invokeinterface #103,  3          // InterfaceMethod org/codehaus/groovy/runtime/callsite/CallSite.call:(Ljava/lang/Object;Ljava/lang/Object;)Ljava/lang/Object;
      33: ldc           #47                 // class java/util/Map
      35: invokestatic  #53                 // Method org/codehaus/groovy/runtime/ScriptBytecodeAdapter.castToType:(Ljava/lang/Object;Ljava/lang/Class;)Ljava/lang/Object;
      38: checkcast     #47                 // class java/util/Map
      41: astore        5
      43: aload         5
      45: pop
      46: aload         5
      48: aconst_null
      49: invokestatic  #186                // Method org/codehaus/groovy/runtime/ScriptBytecodeAdapter.compareNotEqual:(Ljava/lang/Object;Ljava/lang/Object;)Z
      52: ifeq          80
      55: aload         4
      57: ldc_w         #295                // int 44
      60: aaload
      61: ldc_w         #297                // class java/util/LinkedHashMap
      64: aload         5
      66: invokeinterface #299,  3          // InterfaceMethod org/codehaus/groovy/runtime/callsite/CallSite.callConstructor:(Ljava/lang/Object;Ljava/lang/Object;)Ljava/lang/Object;
      71: ldc           #47                 // class java/util/Map
      73: invokestatic  #53                 // Method org/codehaus/groovy/runtime/ScriptBytecodeAdapter.castToType:(Ljava/lang/Object;Ljava/lang/Class;)Ljava/lang/Object;
      76: checkcast     #47                 // class java/util/Map
      79: areturn
      80: aconst_null
      81: ldc           #47                 // class java/util/Map
      83: invokestatic  #53                 // Method org/codehaus/groovy/runtime/ScriptBytecodeAdapter.castToType:(Ljava/lang/Object;Ljava/lang/Class;)Ljava/lang/Object;
      86: checkcast     #47                 // class java/util/Map
      89: areturn
      90: nop
      91: athrow

  protected java.lang.Object generateIdentifier(org.grails.datastore.mapping.model.PersistentEntity, java.util.Map);
    Code:
       0: invokestatic  #29                 // Method $getCallSiteArray:()[Lorg/codehaus/groovy/runtime/callsite/CallSite;
       3: astore_3
       4: aload_3
       5: ldc_w         #302                // int 45
       8: aaload
       9: aload_1
      10: invokeinterface #45,  2           // InterfaceMethod org/codehaus/groovy/runtime/callsite/CallSite.callGetProperty:(Ljava/lang/Object;)Ljava/lang/Object;
      15: astore        4
      17: aload         4
      19: pop
      20: aload         4
      22: invokestatic  #149                // Method org/codehaus/groovy/runtime/typehandling/DefaultTypeTransformation.booleanUnbox:(Ljava/lang/Object;)Z
      25: ifeq          52
      28: aload_3
      29: ldc_w         #303                // int 46
      32: aaload
      33: aload_3
      34: ldc_w         #304                // int 47
      37: aaload
      38: aload_1
      39: invokeinterface #45,  2           // InterfaceMethod org/codehaus/groovy/runtime/callsite/CallSite.callGetProperty:(Ljava/lang/Object;)Ljava/lang/Object;
      44: invokeinterface #45,  2           // InterfaceMethod org/codehaus/groovy/runtime/callsite/CallSite.callGetProperty:(Ljava/lang/Object;)Ljava/lang/Object;
      49: goto          83
      52: aload_3
      53: ldc_w         #305                // int 48
      56: aaload
      57: aload_3
      58: ldc_w         #306                // int 49
      61: aaload
      62: aload_3
      63: ldc_w         #307                // int 50
      66: aaload
      67: aload_1
      68: invokeinterface #45,  2           // InterfaceMethod org/codehaus/groovy/runtime/callsite/CallSite.callGetProperty:(Ljava/lang/Object;)Ljava/lang/Object;
      73: invokeinterface #45,  2           // InterfaceMethod org/codehaus/groovy/runtime/callsite/CallSite.callGetProperty:(Ljava/lang/Object;)Ljava/lang/Object;
      78: invokeinterface #45,  2           // InterfaceMethod org/codehaus/groovy/runtime/callsite/CallSite.callGetProperty:(Ljava/lang/Object;)Ljava/lang/Object;
      83: astore        5
      85: aload         5
      87: pop
      88: aload_3
      89: ldc_w         #308                // int 51
      92: aaload
      93: ldc           #75                 // class java/lang/String
      95: aload         5
      97: invokeinterface #103,  3          // InterfaceMethod org/codehaus/groovy/runtime/callsite/CallSite.call:(Ljava/lang/Object;Ljava/lang/Object;)Ljava/lang/Object;
     102: invokestatic  #149                // Method org/codehaus/groovy/runtime/typehandling/DefaultTypeTransformation.booleanUnbox:(Ljava/lang/Object;)Z
     105: ifne          129
     108: aload_3
     109: ldc_w         #309                // int 52
     112: aaload
     113: ldc_w         #311                // class java/lang/Number
     116: aload         5
     118: invokeinterface #103,  3          // InterfaceMethod org/codehaus/groovy/runtime/callsite/CallSite.call:(Ljava/lang/Object;Ljava/lang/Object;)Ljava/lang/Object;
     123: invokestatic  #149                // Method org/codehaus/groovy/runtime/typehandling/DefaultTypeTransformation.booleanUnbox:(Ljava/lang/Object;)Z
     126: ifeq          133
     129: iconst_1
     130: goto          134
     133: iconst_0
     134: ifeq          358
     137: aconst_null
     138: astore        6
     140: aload         6
     142: pop
     143: aload         4
     145: invokestatic  #149                // Method org/codehaus/groovy/runtime/typehandling/DefaultTypeTransformation.booleanUnbox:(Ljava/lang/Object;)Z
     148: ifeq          184
     151: aload_0
     152: getfield      #94                 // Field lastKey:Ljava/lang/Object;
     155: aload_3
     156: ldc_w         #312                // int 53
     159: aaload
     160: swap
     161: invokeinterface #63,  2           // InterfaceMethod org/codehaus/groovy/runtime/callsite/CallSite.call:(Ljava/lang/Object;)Ljava/lang/Object;
     166: dup
     167: aload_0
     168: swap
     169: putfield      #94                 // Field lastKey:Ljava/lang/Object;
     172: astore        7
     174: aload         7
     176: astore        6
     178: aload         7
     180: pop
     181: goto          327
     184: aload_3
     185: ldc_w         #313                // int 54
     188: aaload
     189: aload_1
     190: invokeinterface #45,  2           // InterfaceMethod org/codehaus/groovy/runtime/callsite/CallSite.callGetProperty:(Ljava/lang/Object;)Ljava/lang/Object;
     195: astore        8
     197: aload         8
     199: pop
     200: aload_3
     201: ldc_w         #314                // int 55
     204: aaload
     205: aload_3
     206: ldc_w         #315                // int 56
     209: aaload
     210: aload_3
     211: ldc_w         #316                // int 57
     214: aaload
     215: aload_0
     216: invokeinterface #170,  2          // InterfaceMethod org/codehaus/groovy/runtime/callsite/CallSite.callGroovyObjectGetProperty:(Ljava/lang/Object;)Ljava/lang/Object;
     221: aload         8
     223: invokeinterface #103,  3          // InterfaceMethod org/codehaus/groovy/runtime/callsite/CallSite.call:(Ljava/lang/Object;Ljava/lang/Object;)Ljava/lang/Object;
     228: invokeinterface #45,  2           // InterfaceMethod org/codehaus/groovy/runtime/callsite/CallSite.callGetProperty:(Ljava/lang/Object;)Ljava/lang/Object;
     233: dup
     234: astore        9
     236: aload_3
     237: ldc_w         #317                // int 58
     240: aaload
     241: swap
     242: invokeinterface #63,  2           // InterfaceMethod org/codehaus/groovy/runtime/callsite/CallSite.call:(Ljava/lang/Object;)Ljava/lang/Object;
     247: dup
     248: aconst_null
     249: aload_3
     250: ldc_w         #318                // int 59
     253: aaload
     254: aload_3
     255: ldc_w         #319                // int 60
     258: aaload
     259: aload_0
     260: invokeinterface #170,  2          // InterfaceMethod org/codehaus/groovy/runtime/callsite/CallSite.callGroovyObjectGetProperty:(Ljava/lang/Object;)Ljava/lang/Object;
     265: aload         8
     267: invokeinterface #103,  3          // InterfaceMethod org/codehaus/groovy/runtime/callsite/CallSite.call:(Ljava/lang/Object;Ljava/lang/Object;)Ljava/lang/Object;
     272: ldc_w         #320                // String lastKey
     275: checkcast     #75                 // class java/lang/String
     278: invokestatic  #324                // Method org/codehaus/groovy/runtime/ScriptBytecodeAdapter.setProperty:(Ljava/lang/Object;Ljava/lang/Class;Ljava/lang/Object;Ljava/lang/String;)V
     281: pop
     282: aload         9
     284: pop
     285: aload_3
     286: ldc_w         #325                // int 61
     289: aaload
     290: aload_3
     291: ldc_w         #326                // int 62
     294: aaload
     295: aload_3
     296: ldc_w         #327                // int 63
     299: aaload
     300: aload_0
     301: invokeinterface #170,  2          // InterfaceMethod org/codehaus/groovy/runtime/callsite/CallSite.callGroovyObjectGetProperty:(Ljava/lang/Object;)Ljava/lang/Object;
     306: aload         8
     308: invokeinterface #103,  3          // InterfaceMethod org/codehaus/groovy/runtime/callsite/CallSite.call:(Ljava/lang/Object;Ljava/lang/Object;)Ljava/lang/Object;
     313: invokeinterface #45,  2           // InterfaceMethod org/codehaus/groovy/runtime/callsite/CallSite.callGetProperty:(Ljava/lang/Object;)Ljava/lang/Object;
     318: astore        10
     320: aload         10
     322: astore        6
     324: aload         10
     326: pop
     327: aload         5
     329: ldc           #75                 // class java/lang/String
     331: invokestatic  #88                 // Method org/codehaus/groovy/runtime/ScriptBytecodeAdapter.compareEqual:(Ljava/lang/Object;Ljava/lang/Object;)Z
     334: ifeq          352
     337: aload_3
     338: ldc_w         #328                // int 64
     341: aaload
     342: aload         6
     344: invokeinterface #63,  2           // InterfaceMethod org/codehaus/groovy/runtime/callsite/CallSite.call:(Ljava/lang/Object;)Ljava/lang/Object;
     349: goto          354
     352: aload         6
     354: areturn
     355: nop
     356: nop
     357: athrow
     358: aload_3
     359: ldc_w         #329                // int 65
     362: aaload
     363: ldc_w         #331                // class java/util/UUID
     366: aload         5
     368: invokeinterface #103,  3          // InterfaceMethod org/codehaus/groovy/runtime/callsite/CallSite.call:(Ljava/lang/Object;Ljava/lang/Object;)Ljava/lang/Object;
     373: invokestatic  #149                // Method org/codehaus/groovy/runtime/typehandling/DefaultTypeTransformation.booleanUnbox:(Ljava/lang/Object;)Z
     376: ifeq          396
     379: aload_3
     380: ldc_w         #332                // int 66
     383: aaload
     384: ldc_w         #331                // class java/util/UUID
     387: invokeinterface #63,  2           // InterfaceMethod org/codehaus/groovy/runtime/callsite/CallSite.call:(Ljava/lang/Object;)Ljava/lang/Object;
     392: areturn
     393: nop
     394: nop
     395: athrow
     396: aload_3
     397: ldc_w         #333                // int 67
     400: aaload
     401: aload         5
     403: invokeinterface #63,  2           // InterfaceMethod org/codehaus/groovy/runtime/callsite/CallSite.call:(Ljava/lang/Object;)Ljava/lang/Object;
     408: astore        11
     410: nop
     411: nop
     412: aload         11
     414: areturn
     415: nop
     416: nop
     417: athrow
     418: astore        12
     420: aload_3
     421: ldc_w         #334                // int 68
     424: aaload
     425: ldc_w         #336                // class org/grails/datastore/mapping/core/IdentityGenerationException
     428: new           #338                // class org/codehaus/groovy/runtime/GStringImpl
     431: dup
     432: iconst_2
     433: anewarray     #105                // class java/lang/Object
     436: dup
     437: iconst_0
     438: aload_1
     439: aastore
     440: dup
     441: iconst_1
     442: aload         5
     444: aastore
     445: iconst_3
     446: anewarray     #75                 // class java/lang/String
     449: dup
     450: iconst_0
     451: ldc_w         #340                // String Cannot generator identity for entity
     454: aastore
     455: dup
     456: iconst_1
     457: ldc_w         #342                // String  with type
     460: aastore
     461: dup
     462: iconst_2
     463: ldc_w         #344                // String
     466: aastore
     467: invokespecial #347                // Method org/codehaus/groovy/runtime/GStringImpl."<init>":([Ljava/lang/Object;[Ljava/lang/String;)V
     470: invokeinterface #299,  3          // InterfaceMethod org/codehaus/groovy/runtime/callsite/CallSite.callConstructor:(Ljava/lang/Object;Ljava/lang/Object;)Ljava/lang/Object;
     475: checkcast     #161                // class java/lang/Throwable
     478: athrow
     479: athrow
     480: nop
     481: nop
     482: athrow
     483: nop
     484: nop
     485: nop
     486: athrow
     487: astore        13
     489: aload         13
     491: athrow
     492: nop
     493: athrow
    Exception table:
       from    to  target type
         396   411   418   Class java/lang/Exception
         412   415   418   Class java/lang/Exception
         396   411   487   any
         412   415   487   any
         418   479   487   any

  protected java.lang.Object storeEntry(org.grails.datastore.mapping.model.PersistentEntity, org.grails.datastore.mapping.engine.EntityAccess, java.lang.Object, java.util.Map);
    Code:
       0: invokestatic  #29                 // Method $getCallSiteArray:()[Lorg/codehaus/groovy/runtime/callsite/CallSite;
       3: astore        5
       5: aload         5
       7: ldc_w         #357                // int 69
      10: aaload
      11: aload_1
      12: invokeinterface #45,  2           // InterfaceMethod org/codehaus/groovy/runtime/callsite/CallSite.callGetProperty:(Ljava/lang/Object;)Ljava/lang/Object;
      17: invokestatic  #149                // Method org/codehaus/groovy/runtime/typehandling/DefaultTypeTransformation.booleanUnbox:(Ljava/lang/Object;)Z
      20: ifne          27
      23: iconst_1
      24: goto          28
      27: iconst_0
      28: ifeq          62
      31: aload         5
      33: ldc_w         #358                // int 70
      36: aaload
      37: aload_1
      38: invokeinterface #45,  2           // InterfaceMethod org/codehaus/groovy/runtime/callsite/CallSite.callGetProperty:(Ljava/lang/Object;)Ljava/lang/Object;
      43: astore        6
      45: aload         6
      47: aconst_null
      48: aload         4
      50: ldc_w         #360                // String discriminator
      53: checkcast     #75                 // class java/lang/String
      56: invokestatic  #324                // Method org/codehaus/groovy/runtime/ScriptBytecodeAdapter.setProperty:(Ljava/lang/Object;Ljava/lang/Class;Ljava/lang/Object;Ljava/lang/String;)V
      59: aload         6
      61: pop
      62: aload         5
      64: ldc_w         #361                // int 71
      67: aaload
      68: aload         5
      70: ldc_w         #362                // int 72
      73: aaload
      74: aload_0
      75: getfield      #55                 // Field datastore:Ljava/util/Map;
      78: aload_0
      79: getfield      #77                 // Field family:Ljava/lang/String;
      82: invokeinterface #103,  3          // InterfaceMethod org/codehaus/groovy/runtime/callsite/CallSite.call:(Ljava/lang/Object;Ljava/lang/Object;)Ljava/lang/Object;
      87: aload_3
      88: aload         4
      90: invokeinterface #113,  4          // InterfaceMethod org/codehaus/groovy/runtime/callsite/CallSite.call:(Ljava/lang/Object;Ljava/lang/Object;Ljava/lang/Object;)Ljava/lang/Object;
      95: pop
      96: aload         5
      98: ldc_w         #363                // int 73
     101: aaload
     102: aload_0
     103: aload_1
     104: aload_3
     105: invokeinterface #67,  4           // InterfaceMethod org/codehaus/groovy/runtime/callsite/CallSite.callCurrent:(Lgroovy/lang/GroovyObject;Ljava/lang/Object;Ljava/lang/Object;)Ljava/lang/Object;
     110: pop
     111: aload         5
     113: ldc_w         #364                // int 74
     116: aaload
     117: aload_0
     118: aload_1
     119: aload_3
     120: aload         4
     122: invokeinterface #367,  5          // InterfaceMethod org/codehaus/groovy/runtime/callsite/CallSite.callCurrent:(Lgroovy/lang/GroovyObject;Ljava/lang/Object;Ljava/lang/Object;Ljava/lang/Object;)Ljava/lang/Object;
     127: pop
     128: aload_3
     129: areturn
     130: nop
     131: athrow

  protected java.lang.Object indexIdentifier(org.grails.datastore.mapping.model.PersistentEntity, java.lang.Object);
    Code:
       0: invokestatic  #29                 // Method $getCallSiteArray:()[Lorg/codehaus/groovy/runtime/callsite/CallSite;
       3: astore_3
       4: aload_3
       5: ldc_w         #373                // int 75
       8: aaload
       9: aload_0
      10: aload_3
      11: ldc_w         #374                // int 76
      14: aaload
      15: aload_1
      16: invokeinterface #45,  2           // InterfaceMethod org/codehaus/groovy/runtime/callsite/CallSite.callGetProperty:(Ljava/lang/Object;)Ljava/lang/Object;
      21: invokeinterface #260,  3          // InterfaceMethod org/codehaus/groovy/runtime/callsite/CallSite.callCurrent:(Lgroovy/lang/GroovyObject;Ljava/lang/Object;)Ljava/lang/Object;
      26: astore        4
      28: aload         4
      30: pop
      31: aload_3
      32: ldc_w         #375                // int 77
      35: aaload
      36: aload         4
      38: aload_2
      39: aload_2
      40: invokeinterface #113,  4          // InterfaceMethod org/codehaus/groovy/runtime/callsite/CallSite.call:(Ljava/lang/Object;Ljava/lang/Object;Ljava/lang/Object;)Ljava/lang/Object;
      45: areturn
      46: nop
      47: athrow

  private java.lang.Object updateInheritanceHierarchy(org.grails.datastore.mapping.model.PersistentEntity, java.lang.Object, java.util.Map);
    Code:
       0: invokestatic  #29                 // Method $getCallSiteArray:()[Lorg/codehaus/groovy/runtime/callsite/CallSite;
       3: astore        4
       5: aload         4
       7: ldc_w         #378                // int 78
      10: aaload
      11: aload_1
      12: invokeinterface #45,  2           // InterfaceMethod org/codehaus/groovy/runtime/callsite/CallSite.callGetProperty:(Ljava/lang/Object;)Ljava/lang/Object;
      17: astore        5
      19: aload         5
      21: pop
      22: aload         5
      24: aconst_null
      25: invokestatic  #186                // Method org/codehaus/groovy/runtime/ScriptBytecodeAdapter.compareNotEqual:(Ljava/lang/Object;Ljava/lang/Object;)Z
      28: ifeq          178
      31: aload         4
      33: ldc_w         #379                // int 79
      36: aaload
      37: aload_0
      38: aload         5
      40: aload         4
      42: ldc_w         #380                // int 80
      45: aaload
      46: aload         5
      48: invokeinterface #45,  2           // InterfaceMethod org/codehaus/groovy/runtime/callsite/CallSite.callGetProperty:(Ljava/lang/Object;)Ljava/lang/Object;
      53: invokeinterface #67,  4           // InterfaceMethod org/codehaus/groovy/runtime/callsite/CallSite.callCurrent:(Lgroovy/lang/GroovyObject;Ljava/lang/Object;Ljava/lang/Object;)Ljava/lang/Object;
      58: astore        6
      60: aload         6
      62: pop
      63: aload         4
      65: ldc_w         #381                // int 81
      68: aaload
      69: aload_0
      70: getfield      #55                 // Field datastore:Ljava/util/Map;
      73: aload         6
      75: invokeinterface #103,  3          // InterfaceMethod org/codehaus/groovy/runtime/callsite/CallSite.call:(Ljava/lang/Object;Ljava/lang/Object;)Ljava/lang/Object;
      80: astore        7
      82: aload         7
      84: pop
      85: aload         7
      87: aconst_null
      88: invokestatic  #88                 // Method org/codehaus/groovy/runtime/ScriptBytecodeAdapter.compareEqual:(Ljava/lang/Object;Ljava/lang/Object;)Z
      91: ifeq          137
      94: iconst_0
      95: anewarray     #105                // class java/lang/Object
      98: invokestatic  #109                // Method org/codehaus/groovy/runtime/ScriptBytecodeAdapter.createMap:([Ljava/lang/Object;)Ljava/util/Map;
     101: astore        8
     103: aload         8
     105: astore        7
     107: aload         8
     109: pop
     110: aload         7
     112: astore        9
     114: aload         4
     116: ldc_w         #382                // int 82
     119: aaload
     120: aload_0
     121: getfield      #55                 // Field datastore:Ljava/util/Map;
     124: aload         6
     126: aload         9
     128: invokeinterface #113,  4          // InterfaceMethod org/codehaus/groovy/runtime/callsite/CallSite.call:(Ljava/lang/Object;Ljava/lang/Object;Ljava/lang/Object;)Ljava/lang/Object;
     133: pop
     134: aload         9
     136: pop
     137: aload         4
     139: ldc_w         #383                // int 83
     142: aaload
     143: aload         7
     145: aload_2
     146: aload_3
     147: invokeinterface #113,  4          // InterfaceMethod org/codehaus/groovy/runtime/callsite/CallSite.call:(Ljava/lang/Object;Ljava/lang/Object;Ljava/lang/Object;)Ljava/lang/Object;
     152: pop
     153: aload         4
     155: ldc_w         #384                // int 84
     158: aaload
     159: aload         5
     161: invokeinterface #45,  2           // InterfaceMethod org/codehaus/groovy/runtime/callsite/CallSite.callGetProperty:(Ljava/lang/Object;)Ljava/lang/Object;
     166: astore        10
     168: aload         10
     170: astore        5
     172: aload         10
     174: pop
     175: goto          22
     178: aconst_null
     179: areturn
     180: nop
     181: athrow

  protected void updateEntry(org.grails.datastore.mapping.model.PersistentEntity, org.grails.datastore.mapping.engine.EntityAccess, java.lang.Object, java.util.Map);
    Code:
       0: invokestatic  #29                 // Method $getCallSiteArray:()[Lorg/codehaus/groovy/runtime/callsite/CallSite;
       3: astore        5
       5: aload         5
       7: ldc_w         #388                // int 85
      10: aaload
      11: aload_0
      12: aload_1
      13: aload         5
      15: ldc_w         #389                // int 86
      18: aaload
      19: aload_1
      20: invokeinterface #63,  2           // InterfaceMethod org/codehaus/groovy/runtime/callsite/CallSite.call:(Ljava/lang/Object;)Ljava/lang/Object;
      25: invokeinterface #67,  4           // InterfaceMethod org/codehaus/groovy/runtime/callsite/CallSite.callCurrent:(Lgroovy/lang/GroovyObject;Ljava/lang/Object;Ljava/lang/Object;)Ljava/lang/Object;
      30: astore        6
      32: aload         6
      34: pop
      35: aload         5
      37: ldc_w         #390                // int 87
      40: aaload
      41: aload         5
      43: ldc_w         #391                // int 88
      46: aaload
      47: aload_0
      48: getfield      #55                 // Field datastore:Ljava/util/Map;
      51: aload         6
      53: invokeinterface #103,  3          // InterfaceMethod org/codehaus/groovy/runtime/callsite/CallSite.call:(Ljava/lang/Object;Ljava/lang/Object;)Ljava/lang/Object;
      58: aload_3
      59: invokeinterface #103,  3          // InterfaceMethod org/codehaus/groovy/runtime/callsite/CallSite.call:(Ljava/lang/Object;Ljava/lang/Object;)Ljava/lang/Object;
      64: astore        7
      66: aload         7
      68: pop
      69: aload         5
      71: ldc_w         #392                // int 89
      74: aaload
      75: aload_0
      76: aload_2
      77: invokeinterface #260,  3          // InterfaceMethod org/codehaus/groovy/runtime/callsite/CallSite.callCurrent:(Lgroovy/lang/GroovyObject;Ljava/lang/Object;)Ljava/lang/Object;
      82: invokestatic  #149                // Method org/codehaus/groovy/runtime/typehandling/DefaultTypeTransformation.booleanUnbox:(Ljava/lang/Object;)Z
      85: ifeq          649
      88: aload         7
      90: aconst_null
      91: invokestatic  #88                 // Method org/codehaus/groovy/runtime/ScriptBytecodeAdapter.compareEqual:(Ljava/lang/Object;Ljava/lang/Object;)Z
      94: ifeq          114
      97: aload         5
      99: ldc_w         #393                // int 90
     102: aaload
     103: aload_0
     104: aload_2
     105: invokeinterface #260,  3          // InterfaceMethod org/codehaus/groovy/runtime/callsite/CallSite.callCurrent:(Lgroovy/lang/GroovyObject;Ljava/lang/Object;)Ljava/lang/Object;
     110: pop
     111: goto          649
     114: aload         5
     116: ldc_w         #394                // int 91
     119: aaload
     120: aload         7
     122: invokeinterface #45,  2           // InterfaceMethod org/codehaus/groovy/runtime/callsite/CallSite.callGetProperty:(Ljava/lang/Object;)Ljava/lang/Object;
     127: astore        8
     129: aload         8
     131: pop
     132: aload         5
     134: ldc_w         #395                // int 92
     137: aaload
     138: aload_2
     139: ldc_w         #397                // String version
     142: invokeinterface #103,  3          // InterfaceMethod org/codehaus/groovy/runtime/callsite/CallSite.call:(Ljava/lang/Object;Ljava/lang/Object;)Ljava/lang/Object;
     147: astore        9
     149: aload         9
     151: pop
     152: aload         5
     154: ldc_w         #398                // int 93
     157: aaload
     158: ldc_w         #311                // class java/lang/Number
     161: aload         5
     163: ldc_w         #399                // int 94
     166: aaload
     167: aload_2
     168: ldc_w         #397                // String version
     171: invokeinterface #103,  3          // InterfaceMethod org/codehaus/groovy/runtime/callsite/CallSite.call:(Ljava/lang/Object;Ljava/lang/Object;)Ljava/lang/Object;
     176: invokeinterface #103,  3          // InterfaceMethod org/codehaus/groovy/runtime/callsite/CallSite.call:(Ljava/lang/Object;Ljava/lang/Object;)Ljava/lang/Object;
     181: invokestatic  #149                // Method org/codehaus/groovy/runtime/typehandling/DefaultTypeTransformation.booleanUnbox:(Ljava/lang/Object;)Z
     184: ifeq          445
     187: aload         5
     189: ldc_w         #400                // int 95
     192: aaload
     193: aload         5
     195: ldc_w         #401                // int 96
     198: aaload
     199: aload         7
     201: invokeinterface #45,  2           // InterfaceMethod org/codehaus/groovy/runtime/callsite/CallSite.callGetProperty:(Ljava/lang/Object;)Ljava/lang/Object;
     206: invokeinterface #404,  2          // InterfaceMethod org/codehaus/groovy/runtime/callsite/CallSite.callSafe:(Ljava/lang/Object;)Ljava/lang/Object;
     211: astore        10
     213: aload         10
     215: astore        8
     217: aload         10
     219: pop
     220: aload         5
     222: ldc_w         #405                // int 97
     225: aaload
     226: aload         5
     228: ldc_w         #406                // int 98
     231: aaload
     232: aload_2
     233: ldc_w         #397                // String version
     236: invokeinterface #103,  3          // InterfaceMethod org/codehaus/groovy/runtime/callsite/CallSite.call:(Ljava/lang/Object;Ljava/lang/Object;)Ljava/lang/Object;
     241: invokeinterface #404,  2          // InterfaceMethod org/codehaus/groovy/runtime/callsite/CallSite.callSafe:(Ljava/lang/Object;)Ljava/lang/Object;
     246: astore        11
     248: aload         11
     250: astore        9
     252: aload         11
     254: pop
     255: invokestatic  #412                // Method org/codehaus/groovy/runtime/BytecodeInterface8.isOrigZ:()Z
     258: ifeq          276
     261: getstatic     #414                // Field __$stMC:Z
     264: ifne          276
     267: invokestatic  #417                // Method org/codehaus/groovy/runtime/BytecodeInterface8.disabledStandardMetaClass:()Z
     270: ifne          276
     273: goto          362
     276: aload         9
     278: aconst_null
     279: invokestatic  #88                 // Method org/codehaus/groovy/runtime/ScriptBytecodeAdapter.compareEqual:(Ljava/lang/Object;Ljava/lang/Object;)Z
     282: ifeq          298
     285: aload         8
     287: aconst_null
     288: invokestatic  #88                 // Method org/codehaus/groovy/runtime/ScriptBytecodeAdapter.compareEqual:(Ljava/lang/Object;Ljava/lang/Object;)Z
     291: ifeq          298
     294: iconst_1
     295: goto          299
     298: iconst_0
     299: ifeq          359
     302: lconst_0
     303: lstore        12
     305: lload         12
     307: invokestatic  #99                 // Method java/lang/Long.valueOf:(J)Ljava/lang/Long;
     310: astore        9
     312: lload         12
     314: pop2
     315: aload         5
     317: ldc_w         #418                // int 99
     320: aaload
     321: aload_2
     322: ldc_w         #397                // String version
     325: aload         9
     327: invokeinterface #113,  4          // InterfaceMethod org/codehaus/groovy/runtime/callsite/CallSite.call:(Ljava/lang/Object;Ljava/lang/Object;Ljava/lang/Object;)Ljava/lang/Object;
     332: pop
     333: aload         9
     335: astore        14
     337: aload         5
     339: ldc_w         #419                // int 100
     342: aaload
     343: aload         4
     345: ldc_w         #397                // String version
     348: aload         14
     350: invokeinterface #113,  4          // InterfaceMethod org/codehaus/groovy/runtime/callsite/CallSite.call:(Ljava/lang/Object;Ljava/lang/Object;Ljava/lang/Object;)Ljava/lang/Object;
     355: pop
     356: aload         14
     358: pop
     359: goto          445
     362: aload         9
     364: aconst_null
     365: invokestatic  #88                 // Method org/codehaus/groovy/runtime/ScriptBytecodeAdapter.compareEqual:(Ljava/lang/Object;Ljava/lang/Object;)Z
     368: ifeq          384
     371: aload         8
     373: aconst_null
     374: invokestatic  #88                 // Method org/codehaus/groovy/runtime/ScriptBytecodeAdapter.compareEqual:(Ljava/lang/Object;Ljava/lang/Object;)Z
     377: ifeq          384
     380: iconst_1
     381: goto          385
     384: iconst_0
     385: ifeq          445
     388: lconst_0
     389: lstore        15
     391: lload         15
     393: invokestatic  #99                 // Method java/lang/Long.valueOf:(J)Ljava/lang/Long;
     396: astore        9
     398: lload         15
     400: pop2
     401: aload         5
     403: ldc_w         #420                // int 101
     406: aaload
     407: aload_2
     408: ldc_w         #397                // String version
     411: aload         9
     413: invokeinterface #113,  4          // InterfaceMethod org/codehaus/groovy/runtime/callsite/CallSite.call:(Ljava/lang/Object;Ljava/lang/Object;Ljava/lang/Object;)Ljava/lang/Object;
     418: pop
     419: aload         9
     421: astore        17
     423: aload         5
     425: ldc_w         #421                // int 102
     428: aaload
     429: aload         4
     431: ldc_w         #397                // String version
     434: aload         17
     436: invokeinterface #113,  4          // InterfaceMethod org/codehaus/groovy/runtime/callsite/CallSite.call:(Ljava/lang/Object;Ljava/lang/Object;Ljava/lang/Object;)Ljava/lang/Object;
     441: pop
     442: aload         17
     444: pop
     445: invokestatic  #412                // Method org/codehaus/groovy/runtime/BytecodeInterface8.isOrigZ:()Z
     448: ifeq          466
     451: getstatic     #414                // Field __$stMC:Z
     454: ifne          466
     457: invokestatic  #417                // Method org/codehaus/groovy/runtime/BytecodeInterface8.disabledStandardMetaClass:()Z
     460: ifne          466
     463: goto          552
     466: aload         8
     468: aconst_null
     469: invokestatic  #186                // Method org/codehaus/groovy/runtime/ScriptBytecodeAdapter.compareNotEqual:(Ljava/lang/Object;Ljava/lang/Object;)Z
     472: ifeq          488
     475: aload         9
     477: aconst_null
     478: invokestatic  #186                // Method org/codehaus/groovy/runtime/ScriptBytecodeAdapter.compareNotEqual:(Ljava/lang/Object;Ljava/lang/Object;)Z
     481: ifeq          488
     484: iconst_1
     485: goto          489
     488: iconst_0
     489: ifeq          525
     492: aload         5
     494: ldc_w         #422                // int 103
     497: aaload
     498: aload         8
     500: aload         9
     502: invokeinterface #103,  3          // InterfaceMethod org/codehaus/groovy/runtime/callsite/CallSite.call:(Ljava/lang/Object;Ljava/lang/Object;)Ljava/lang/Object;
     507: invokestatic  #149                // Method org/codehaus/groovy/runtime/typehandling/DefaultTypeTransformation.booleanUnbox:(Ljava/lang/Object;)Z
     510: ifne          517
     513: iconst_1
     514: goto          518
     517: iconst_0
     518: ifeq          525
     521: iconst_1
     522: goto          526
     525: iconst_0
     526: ifeq          549
     529: aload         5
     531: ldc_w         #423                // int 104
     534: aaload
     535: ldc_w         #425                // class org/grails/datastore/mapping/core/OptimisticLockingException
     538: aload_1
     539: aload_3
     540: invokeinterface #427,  4          // InterfaceMethod org/codehaus/groovy/runtime/callsite/CallSite.callConstructor:(Ljava/lang/Object;Ljava/lang/Object;Ljava/lang/Object;)Ljava/lang/Object;
     545: checkcast     #161                // class java/lang/Throwable
     548: athrow
     549: goto          635
     552: aload         8
     554: aconst_null
     555: invokestatic  #186                // Method org/codehaus/groovy/runtime/ScriptBytecodeAdapter.compareNotEqual:(Ljava/lang/Object;Ljava/lang/Object;)Z
     558: ifeq          574
     561: aload         9
     563: aconst_null
     564: invokestatic  #186                // Method org/codehaus/groovy/runtime/ScriptBytecodeAdapter.compareNotEqual:(Ljava/lang/Object;Ljava/lang/Object;)Z
     567: ifeq          574
     570: iconst_1
     571: goto          575
     574: iconst_0
     575: ifeq          611
     578: aload         5
     580: ldc_w         #428                // int 105
     583: aaload
     584: aload         8
     586: aload         9
     588: invokeinterface #103,  3          // InterfaceMethod org/codehaus/groovy/runtime/callsite/CallSite.call:(Ljava/lang/Object;Ljava/lang/Object;)Ljava/lang/Object;
     593: invokestatic  #149                // Method org/codehaus/groovy/runtime/typehandling/DefaultTypeTransformation.booleanUnbox:(Ljava/lang/Object;)Z
     596: ifne          603
     599: iconst_1
     600: goto          604
     603: iconst_0
     604: ifeq          611
     607: iconst_1
     608: goto          612
     611: iconst_0
     612: ifeq          635
     615: aload         5
     617: ldc_w         #429                // int 106
     620: aaload
     621: ldc_w         #425                // class org/grails/datastore/mapping/core/OptimisticLockingException
     624: aload_1
     625: aload_3
     626: invokeinterface #427,  4          // InterfaceMethod org/codehaus/groovy/runtime/callsite/CallSite.callConstructor:(Ljava/lang/Object;Ljava/lang/Object;Ljava/lang/Object;)Ljava/lang/Object;
     631: checkcast     #161                // class java/lang/Throwable
     634: athrow
     635: aload         5
     637: ldc_w         #430                // int 107
     640: aaload
     641: aload_0
     642: aload_2
     643: invokeinterface #260,  3          // InterfaceMethod org/codehaus/groovy/runtime/callsite/CallSite.callCurrent:(Lgroovy/lang/GroovyObject;Ljava/lang/Object;)Ljava/lang/Object;
     648: pop
     649: aload         5
     651: ldc_w         #431                // int 108
     654: aaload
     655: aload_0
     656: aload_1
     657: aload_3
     658: invokeinterface #67,  4           // InterfaceMethod org/codehaus/groovy/runtime/callsite/CallSite.callCurrent:(Lgroovy/lang/GroovyObject;Ljava/lang/Object;Ljava/lang/Object;)Ljava/lang/Object;
     663: pop
     664: aload         7
     666: aconst_null
     667: invokestatic  #88                 // Method org/codehaus/groovy/runtime/ScriptBytecodeAdapter.compareEqual:(Ljava/lang/Object;Ljava/lang/Object;)Z
     670: ifeq          708
     673: aload         5
     675: ldc_w         #432                // int 109
     678: aaload
     679: aload         5
     681: ldc_w         #433                // int 110
     684: aaload
     685: aload_0
     686: getfield      #55                 // Field datastore:Ljava/util/Map;
     689: aload         6
     691: invokeinterface #103,  3          // InterfaceMethod org/codehaus/groovy/runtime/callsite/CallSite.call:(Ljava/lang/Object;Ljava/lang/Object;)Ljava/lang/Object;
     696: aload_3
     697: aload         4
     699: invokeinterface #113,  4          // InterfaceMethod org/codehaus/groovy/runtime/callsite/CallSite.call:(Ljava/lang/Object;Ljava/lang/Object;Ljava/lang/Object;)Ljava/lang/Object;
     704: pop
     705: goto          724
     708: aload         5
     710: ldc_w         #434                // int 111
     713: aaload
     714: aload         7
     716: aload         4
     718: invokeinterface #103,  3          // InterfaceMethod org/codehaus/groovy/runtime/callsite/CallSite.call:(Ljava/lang/Object;Ljava/lang/Object;)Ljava/lang/Object;
     723: pop
     724: aload         5
     726: ldc_w         #435                // int 112
     729: aaload
     730: aload_0
     731: aload_1
     732: aload_3
     733: aload         4
     735: invokeinterface #367,  5          // InterfaceMethod org/codehaus/groovy/runtime/callsite/CallSite.callCurrent:(Lgroovy/lang/GroovyObject;Ljava/lang/Object;Ljava/lang/Object;Ljava/lang/Object;)Ljava/lang/Object;
     740: pop
     741: return

  protected void deleteEntries(java.lang.String, java.util.List<java.lang.Object>);
    Code:
       0: aload_1
       1: new           #203                // class groovy/lang/Reference
       4: dup_x1
       5: swap
       6: invokespecial #206                // Method groovy/lang/Reference."<init>":(Ljava/lang/Object;)V
       9: astore_3
      10: invokestatic  #29                 // Method $getCallSiteArray:()[Lorg/codehaus/groovy/runtime/callsite/CallSite;
      13: astore        4
      15: aload         4
      17: ldc_w         #443                // int 113
      20: aaload
      21: aload_2
      22: new           #445                // class org/grails/datastore/mapping/simple/engine/SimpleMapEntityPersister$_deleteEntries_closure2
      25: dup
      26: aload_0
      27: aload_0
      28: aload_3
      29: invokespecial #448                // Method org/grails/datastore/mapping/simple/engine/SimpleMapEntityPersister$_deleteEntries_closure2."<init>":(Ljava/lang/Object;Ljava/lang/Object;Lgroovy/lang/Reference;)V
      32: invokeinterface #450,  3          // InterfaceMethod org/codehaus/groovy/runtime/callsite/CallSite.callSafe:(Ljava/lang/Object;Ljava/lang/Object;)Ljava/lang/Object;
      37: pop
      38: return

  protected groovy.lang.MetaClass $getStaticMetaClass();
    Code:
       0: aload_0
       1: invokevirtual #456                // Method java/lang/Object.getClass:()Ljava/lang/Class;
       4: ldc           #2                  // class org/grails/datastore/mapping/simple/engine/SimpleMapEntityPersister
       6: if_acmpeq     14
       9: aload_0
      10: invokestatic  #460                // Method org/codehaus/groovy/runtime/ScriptBytecodeAdapter.initMetaClass:(Ljava/lang/Object;)Lgroovy/lang/MetaClass;
      13: areturn
      14: getstatic     #462                // Field $staticClassInfo:Lorg/codehaus/groovy/reflection/ClassInfo;
      17: astore_1
      18: aload_1
      19: ifnonnull     34
      22: aload_0
      23: invokevirtual #456                // Method java/lang/Object.getClass:()Ljava/lang/Class;
      26: invokestatic  #468                // Method org/codehaus/groovy/reflection/ClassInfo.getClassInfo:(Ljava/lang/Class;)Lorg/codehaus/groovy/reflection/ClassInfo;
      29: dup
      30: astore_1
      31: putstatic     #462                // Field $staticClassInfo:Lorg/codehaus/groovy/reflection/ClassInfo;
      34: aload_1
      35: invokevirtual #471                // Method org/codehaus/groovy/reflection/ClassInfo.getMetaClass:()Lgroovy/lang/MetaClass;
      38: areturn

  public java.lang.Object this$dist$invoke$6(java.lang.String, java.lang.Object);
    Code:
       0: invokestatic  #29                 // Method $getCallSiteArray:()[Lorg/codehaus/groovy/runtime/callsite/CallSite;
       3: astore_3
       4: ldc           #2                  // class org/grails/datastore/mapping/simple/engine/SimpleMapEntityPersister
       6: aload_0
       7: new           #338                // class org/codehaus/groovy/runtime/GStringImpl
      10: dup
      11: iconst_1
      12: anewarray     #105                // class java/lang/Object
      15: dup
      16: iconst_0
      17: aload_1
      18: aastore
      19: iconst_2
      20: anewarray     #75                 // class java/lang/String
      23: dup
      24: iconst_0
      25: ldc_w         #344                // String
      28: aastore
      29: dup
      30: iconst_1
      31: ldc_w         #344                // String
      34: aastore
      35: invokespecial #347                // Method org/codehaus/groovy/runtime/GStringImpl."<init>":([Ljava/lang/Object;[Ljava/lang/String;)V
      38: invokestatic  #73                 // Method org/codehaus/groovy/runtime/typehandling/ShortTypeHandling.castToString:(Ljava/lang/Object;)Ljava/lang/String;
      41: checkcast     #75                 // class java/lang/String
      44: iconst_0
      45: anewarray     #105                // class java/lang/Object
      48: iconst_1
      49: anewarray     #105                // class java/lang/Object
      52: dup
      53: iconst_0
      54: aload_2
      55: aastore
      56: iconst_1
      57: newarray       int
      59: dup
      60: iconst_0
      61: iconst_0
      62: iastore
      63: invokestatic  #477                // Method org/codehaus/groovy/runtime/ScriptBytecodeAdapter.despreadList:([Ljava/lang/Object;[Ljava/lang/Object;[I)[Ljava/lang/Object;
      66: invokestatic  #481                // Method org/codehaus/groovy/runtime/ScriptBytecodeAdapter.invokeMethodOnCurrentN:(Ljava/lang/Class;Lgroovy/lang/GroovyObject;Ljava/lang/String;[Ljava/lang/Object;)Ljava/lang/Object;
      69: areturn
      70: nop
      71: athrow

  public void this$dist$set$6(java.lang.String, java.lang.Object);
    Code:
       0: invokestatic  #29                 // Method $getCallSiteArray:()[Lorg/codehaus/groovy/runtime/callsite/CallSite;
       3: astore_3
       4: aload_2
       5: astore        4
       7: aload         4
       9: ldc           #2                  // class org/grails/datastore/mapping/simple/engine/SimpleMapEntityPersister
      11: aload_0
      12: new           #338                // class org/codehaus/groovy/runtime/GStringImpl
      15: dup
      16: iconst_1
      17: anewarray     #105                // class java/lang/Object
      20: dup
      21: iconst_0
      22: aload_1
      23: aastore
      24: iconst_2
      25: anewarray     #75                 // class java/lang/String
      28: dup
      29: iconst_0
      30: ldc_w         #344                // String
      33: aastore
      34: dup
      35: iconst_1
      36: ldc_w         #344                // String
      39: aastore
      40: invokespecial #347                // Method org/codehaus/groovy/runtime/GStringImpl."<init>":([Ljava/lang/Object;[Ljava/lang/String;)V
      43: invokestatic  #73                 // Method org/codehaus/groovy/runtime/typehandling/ShortTypeHandling.castToString:(Ljava/lang/Object;)Ljava/lang/String;
      46: checkcast     #75                 // class java/lang/String
      49: invokestatic  #489                // Method org/codehaus/groovy/runtime/ScriptBytecodeAdapter.setGroovyObjectProperty:(Ljava/lang/Object;Ljava/lang/Class;Lgroovy/lang/GroovyObject;Ljava/lang/String;)V
      52: aload         4
      54: pop
      55: return

  public java.lang.Object this$dist$get$6(java.lang.String);
    Code:
       0: invokestatic  #29                 // Method $getCallSiteArray:()[Lorg/codehaus/groovy/runtime/callsite/CallSite;
       3: astore_2
       4: ldc           #2                  // class org/grails/datastore/mapping/simple/engine/SimpleMapEntityPersister
       6: aload_0
       7: new           #338                // class org/codehaus/groovy/runtime/GStringImpl
      10: dup
      11: iconst_1
      12: anewarray     #105                // class java/lang/Object
      15: dup
      16: iconst_0
      17: aload_1
      18: aastore
      19: iconst_2
      20: anewarray     #75                 // class java/lang/String
      23: dup
      24: iconst_0
      25: ldc_w         #344                // String
      28: aastore
      29: dup
      30: iconst_1
      31: ldc_w         #344                // String
      34: aastore
      35: invokespecial #347                // Method org/codehaus/groovy/runtime/GStringImpl."<init>":([Ljava/lang/Object;[Ljava/lang/String;)V
      38: invokestatic  #73                 // Method org/codehaus/groovy/runtime/typehandling/ShortTypeHandling.castToString:(Ljava/lang/Object;)Ljava/lang/String;
      41: checkcast     #75                 // class java/lang/String
      44: invokestatic  #495                // Method org/codehaus/groovy/runtime/ScriptBytecodeAdapter.getGroovyObjectProperty:(Ljava/lang/Class;Lgroovy/lang/GroovyObject;Ljava/lang/String;)Ljava/lang/Object;
      47: areturn
      48: nop
      49: athrow

  public groovy.lang.MetaClass getMetaClass();
    Code:
       0: aload_0
       1: getfield      #38                 // Field metaClass:Lgroovy/lang/MetaClass;
       4: dup
       5: ifnull        9
       8: areturn
       9: pop
      10: aload_0
      11: dup
      12: invokevirtual #36                 // Method $getStaticMetaClass:()Lgroovy/lang/MetaClass;
      15: putfield      #38                 // Field metaClass:Lgroovy/lang/MetaClass;
      18: aload_0
      19: getfield      #38                 // Field metaClass:Lgroovy/lang/MetaClass;
      22: areturn

  public void setMetaClass(groovy.lang.MetaClass);
    Code:
       0: aload_0
       1: aload_1
       2: putfield      #38                 // Field metaClass:Lgroovy/lang/MetaClass;
       5: return

  public java.lang.Object invokeMethod(java.lang.String, java.lang.Object);
    Code:
       0: aload_0
       1: invokevirtual #499                // Method getMetaClass:()Lgroovy/lang/MetaClass;
       4: aload_0
       5: aload_1
       6: aload_2
       7: invokeinterface #502,  4          // InterfaceMethod groovy/lang/MetaClass.invokeMethod:(Ljava/lang/Object;Ljava/lang/String;Ljava/lang/Object;)Ljava/lang/Object;
      12: areturn

  public java.lang.Object getProperty(java.lang.String);
    Code:
       0: aload_0
       1: invokevirtual #499                // Method getMetaClass:()Lgroovy/lang/MetaClass;
       4: aload_0
       5: aload_1
       6: invokeinterface #506,  3          // InterfaceMethod groovy/lang/MetaClass.getProperty:(Ljava/lang/Object;Ljava/lang/String;)Ljava/lang/Object;
      11: areturn

  public void setProperty(java.lang.String, java.lang.Object);
    Code:
       0: aload_0
       1: invokevirtual #499                // Method getMetaClass:()Lgroovy/lang/MetaClass;
       4: aload_0
       5: aload_1
       6: aload_2
       7: invokeinterface #509,  4          // InterfaceMethod groovy/lang/MetaClass.setProperty:(Ljava/lang/Object;Ljava/lang/String;Ljava/lang/Object;)V
      12: return

  public java.util.Map<java.lang.String, java.util.Map> getDatastore();
    Code:
       0: aload_0
       1: getfield      #55                 // Field datastore:Ljava/util/Map;
       4: areturn

  public void setDatastore(java.util.Map<java.lang.String, java.util.Map>);
    Code:
       0: aload_0
       1: aload_1
       2: putfield      #55                 // Field datastore:Ljava/util/Map;
       5: return

  public java.util.Map getIndices();
    Code:
       0: aload_0
       1: getfield      #58                 // Field indices:Ljava/util/Map;
       4: areturn

  public void setIndices(java.util.Map);
    Code:
       0: aload_0
       1: aload_1
       2: putfield      #58                 // Field indices:Ljava/util/Map;
       5: return

  public java.lang.Object getLastKey();
    Code:
       0: aload_0
       1: getfield      #94                 // Field lastKey:Ljava/lang/Object;
       4: areturn

  public void setLastKey(java.lang.Object);
    Code:
       0: aload_0
       1: aload_1
       2: putfield      #94                 // Field lastKey:Ljava/lang/Object;
       5: return

  public java.lang.String getFamily();
    Code:
       0: aload_0
       1: getfield      #77                 // Field family:Ljava/lang/String;
       4: areturn

  public void setFamily(java.lang.String);
    Code:
       0: aload_0
       1: aload_1
       2: putfield      #77                 // Field family:Ljava/lang/String;
       5: return

  protected void setEntryValue(java.lang.Object, java.lang.String, java.lang.Object);
    Code:
       0: aload_0
       1: aload_1
       2: checkcast     #47                 // class java/util/Map
       5: aload_2
       6: aload_3
       7: invokevirtual #523                // Method setEntryValue:(Ljava/util/Map;Ljava/lang/String;Ljava/lang/Object;)V
      10: return

  protected java.lang.Object retrieveEntry(org.grails.datastore.mapping.model.PersistentEntity, java.lang.String, java.io.Serializable);
    Code:
       0: aload_0
       1: aload_1
       2: aload_2
       3: aload_3
       4: invokevirtual #526                // Method retrieveEntry:(Lorg/grails/datastore/mapping/model/PersistentEntity;Ljava/lang/String;Ljava/io/Serializable;)Ljava/util/Map;
       7: areturn

  protected java.lang.Object storeEntry(org.grails.datastore.mapping.model.PersistentEntity, org.grails.datastore.mapping.engine.EntityAccess, java.lang.Object, java.lang.Object);
    Code:
       0: aload_0
       1: aload_1
       2: aload_2
       3: aload_3
       4: aload         4
       6: checkcast     #47                 // class java/util/Map
       9: invokevirtual #529                // Method storeEntry:(Lorg/grails/datastore/mapping/model/PersistentEntity;Lorg/grails/datastore/mapping/engine/EntityAccess;Ljava/lang/Object;Ljava/util/Map;)Ljava/lang/Object;
      12: areturn

  protected java.lang.Object generateIdentifier(org.grails.datastore.mapping.model.PersistentEntity, java.lang.Object);
    Code:
       0: aload_0
       1: aload_1
       2: aload_2
       3: checkcast     #47                 // class java/util/Map
       6: invokevirtual #531                // Method generateIdentifier:(Lorg/grails/datastore/mapping/model/PersistentEntity;Ljava/util/Map;)Ljava/lang/Object;
       9: areturn

  protected java.util.Collection getManyToManyKeys(org.grails.datastore.mapping.model.PersistentEntity, java.lang.Object, java.io.Serializable, java.lang.Object, org.grails.datastore.mapping.model.types.ManyToMany);
    Code:
       0: aload_0
       1: aload_1
       2: aload_2
       3: aload_3
       4: aload         4
       6: checkcast     #47                 // class java/util/Map
       9: aload         5
      11: invokevirtual #534                // Method getManyToManyKeys:(Lorg/grails/datastore/mapping/model/PersistentEntity;Ljava/lang/Object;Ljava/io/Serializable;Ljava/util/Map;Lorg/grails/datastore/mapping/model/types/ManyToMany;)Ljava/util/Collection;
      14: areturn

  protected org.grails.datastore.mapping.model.PersistentEntity discriminatePersistentEntity(org.grails.datastore.mapping.model.PersistentEntity, java.lang.Object);
    Code:
       0: aload_0
       1: aload_1
       2: aload_2
       3: checkcast     #47                 // class java/util/Map
       6: invokevirtual #537                // Method discriminatePersistentEntity:(Lorg/grails/datastore/mapping/model/PersistentEntity;Ljava/util/Map;)Lorg/grails/datastore/mapping/model/PersistentEntity;
       9: areturn

  protected void updateEntry(org.grails.datastore.mapping.model.PersistentEntity, org.grails.datastore.mapping.engine.EntityAccess, java.lang.Object, java.lang.Object);
    Code:
       0: aload_0
       1: aload_1
       2: aload_2
       3: aload_3
       4: aload         4
       6: checkcast     #47                 // class java/util/Map
       9: invokevirtual #540                // Method updateEntry:(Lorg/grails/datastore/mapping/model/PersistentEntity;Lorg/grails/datastore/mapping/engine/EntityAccess;Ljava/lang/Object;Ljava/util/Map;)V
      12: return

  protected void setEmbedded(java.lang.Object, java.lang.String, java.lang.Object);
    Code:
       0: aload_0
       1: aload_1
       2: checkcast     #47                 // class java/util/Map
       5: aload_2
       6: aload_3
       7: checkcast     #47                 // class java/util/Map
      10: invokevirtual #542                // Method setEmbedded:(Ljava/util/Map;Ljava/lang/String;Ljava/util/Map;)V
      13: return

  protected java.lang.Object createNewEntry(java.lang.String);
    Code:
       0: aload_0
       1: aload_1
       2: invokevirtual #544                // Method createNewEntry:(Ljava/lang/String;)Ljava/util/Map;
       5: areturn

  protected void setManyToMany(org.grails.datastore.mapping.model.PersistentEntity, java.lang.Object, java.lang.Object, org.grails.datastore.mapping.model.types.ManyToMany, java.util.Collection, java.util.Map);
    Code:
       0: aload_0
       1: aload_1
       2: aload_2
       3: aload_3
       4: checkcast     #47                 // class java/util/Map
       7: aload         4
       9: aload         5
      11: aload         6
      13: invokevirtual #547                // Method setManyToMany:(Lorg/grails/datastore/mapping/model/PersistentEntity;Ljava/lang/Object;Ljava/util/Map;Lorg/grails/datastore/mapping/model/types/ManyToMany;Ljava/util/Collection;Ljava/util/Map;)V
      16: return

  protected java.lang.Object getEntryValue(java.lang.Object, java.lang.String);
    Code:
       0: aload_0
       1: aload_1
       2: checkcast     #47                 // class java/util/Map
       5: aload_2
       6: invokevirtual #549                // Method getEntryValue:(Ljava/util/Map;Ljava/lang/String;)Ljava/lang/Object;
       9: areturn

  protected java.lang.Object getEmbedded(java.lang.Object, java.lang.String);
    Code:
       0: aload_0
       1: aload_1
       2: checkcast     #47                 // class java/util/Map
       5: aload_2
       6: invokevirtual #551                // Method getEmbedded:(Ljava/util/Map;Ljava/lang/String;)Ljava/util/Map;
       9: areturn

  public org.grails.datastore.mapping.engine.AssociationIndexer getAssociationIndexer(java.lang.Object, org.grails.datastore.mapping.model.types.Association);
    Code:
       0: aload_0
       1: aload_1
       2: checkcast     #47                 // class java/util/Map
       5: aload_2
       6: invokevirtual #554                // Method getAssociationIndexer:(Ljava/util/Map;Lorg/grails/datastore/mapping/model/types/Association;)Lorg/grails/datastore/mapping/engine/AssociationIndexer;
       9: areturn

  public java.util.Collection super$5$getManyToManyKeys(org.grails.datastore.mapping.model.PersistentEntity, java.lang.Object, java.io.Serializable, java.lang.Object, org.grails.datastore.mapping.model.types.ManyToMany);
    Code:
       0: aload_0
       1: aload_1
       2: aload_2
       3: aload_3
       4: aload         4
       6: aload         5
       8: invokespecial #559                // Method org/grails/datastore/mapping/engine/NativeEntryEntityPersister.getManyToManyKeys:(Lorg/grails/datastore/mapping/model/PersistentEntity;Ljava/lang/Object;Ljava/io/Serializable;Ljava/lang/Object;Lorg/grails/datastore/mapping/model/types/ManyToMany;)Ljava/util/Collection;
      11: areturn

  public void super$5$setManyToMany(org.grails.datastore.mapping.model.PersistentEntity, java.lang.Object, java.lang.Object, org.grails.datastore.mapping.model.types.ManyToMany, java.util.Collection, java.util.Map);
    Code:
       0: aload_0
       1: aload_1
       2: aload_2
       3: aload_3
       4: aload         4
       6: aload         5
       8: aload         6
      10: invokespecial #562                // Method org/grails/datastore/mapping/engine/NativeEntryEntityPersister.setManyToMany:(Lorg/grails/datastore/mapping/model/PersistentEntity;Ljava/lang/Object;Ljava/lang/Object;Lorg/grails/datastore/mapping/model/types/ManyToMany;Ljava/util/Collection;Ljava/util/Map;)V
      13: return

  public org.grails.datastore.mapping.model.PersistentEntity super$5$discriminatePersistentEntity(org.grails.datastore.mapping.model.PersistentEntity, java.lang.Object);
    Code:
       0: aload_0
       1: aload_1
       2: aload_2
       3: invokespecial #565                // Method org/grails/datastore/mapping/engine/NativeEntryEntityPersister.discriminatePersistentEntity:(Lorg/grails/datastore/mapping/model/PersistentEntity;Ljava/lang/Object;)Lorg/grails/datastore/mapping/model/PersistentEntity;
       6: areturn

  public java.lang.Object super$5$getEmbedded(java.lang.Object, java.lang.String);
    Code:
       0: aload_0
       1: aload_1
       2: aload_2
       3: invokespecial #568                // Method org/grails/datastore/mapping/engine/NativeEntryEntityPersister.getEmbedded:(Ljava/lang/Object;Ljava/lang/String;)Ljava/lang/Object;
       6: areturn

  public boolean super$5$isPropertyIndexed(org.grails.datastore.mapping.config.Property);
    Code:
       0: aload_0
       1: aload_1
       2: invokespecial #571                // Method org/grails/datastore/mapping/engine/NativeEntryEntityPersister.isPropertyIndexed:(Lorg/grails/datastore/mapping/config/Property;)Z
       5: ireturn

  public void super$5$setEmbedded(java.lang.Object, java.lang.String, java.lang.Object);
    Code:
       0: aload_0
       1: aload_1
       2: aload_2
       3: aload_3
       4: invokespecial #574                // Method org/grails/datastore/mapping/engine/NativeEntryEntityPersister.setEmbedded:(Ljava/lang/Object;Ljava/lang/String;Ljava/lang/Object;)V
       7: return

  private static void $createCallSiteArray_1(java.lang.String[]);
    Code:
       0: aload_0
       1: ldc           #39                 // int 0
       3: ldc_w         #580                // String backingMap
       6: aastore
       7: aload_0
       8: ldc           #56                 // int 1
      10: ldc_w         #581                // String indices
      13: aastore
      14: aload_0
      15: ldc           #59                 // int 2
      17: ldc_w         #582                // String getFamily
      20: aastore
      21: aload_0
      22: ldc           #60                 // int 3
      24: ldc_w         #584                // String getMapping
      27: aastore
      28: aload_0
      29: ldc           #78                 // int 4
      31: ldc_w         #586                // String getIdentity
      34: aastore
      35: aload_0
      36: ldc           #79                 // int 5
      38: ldc_w         #587                // String type
      41: aastore
      42: aload_0
      43: ldc           #100                // int 6
      45: ldc_w         #589                // String getAt
      48: aastore
      49: aload_0
      50: ldc           #110                // int 7
      52: ldc_w         #591                // String putAt
      55: aastore
      56: aload_0
      57: ldc           #143                // int 8
      59: ldc_w         #360                // String discriminator
      62: aastore
      63: aload_0
      64: ldc           #150                // int 9
      66: ldc_w         #593                // String getChildEntityByDiscriminator
      69: aastore
      70: aload_0
      71: ldc           #151                // int 10
      73: ldc_w         #595                // String getMappingContext
      76: aastore
      77: aload_0
      78: ldc           #155                // int 11
      80: ldc_w         #597                // String rootEntity
      83: aastore
      84: aload_0
      85: ldc           #164                // int 12
      87: ldc_w         #599                // String <$constructor$>
      90: aastore
      91: aload_0
      92: ldc           #167                // int 13
      94: ldc_w         #600                // String session
      97: aastore
      98: aload_0
      99: ldc           #171                // int 14
     101: ldc_w         #602                // String getPersistentEntity
     104: aastore
     105: aload_0
     106: ldc           #180                // int 15
     108: ldc_w         #604                // String remove
     111: aastore
     112: aload_0
     113: ldc           #181                // int 16
     115: ldc_w         #589                // String getAt
     118: aastore
     119: aload_0
     120: ldc           #182                // int 17
     122: ldc_w         #606                // String parentEntity
     125: aastore
     126: aload_0
     127: ldc           #183                // int 18
     129: ldc_w         #607                // String persistentEntity
     132: aastore
     133: aload_0
     134: ldc           #187                // int 19
     136: ldc_w         #582                // String getFamily
     139: aastore
     140: aload_0
     141: ldc           #188                // int 20
     143: ldc_w         #609                // String mapping
     146: aastore
     147: aload_0
     148: ldc           #189                // int 21
     150: ldc_w         #604                // String remove
     153: aastore
     154: aload_0
     155: ldc           #190                // int 22
     157: ldc_w         #589                // String getAt
     160: aastore
     161: aload_0
     162: ldc           #191                // int 23
     164: ldc_w         #606                // String parentEntity
     167: aastore
     168: aload_0
     169: ldc           #217                // int 24
     171: ldc_w         #611                // String associatedEntity
     174: aastore
     175: aload_0
     176: ldc           #233                // int 25
     178: ldc_w         #613                // String isOwningSide
     181: aastore
     182: aload_0
     183: ldc           #234                // int 26
     185: ldc_w         #615                // String persist
     188: aastore
     189: aload_0
     190: ldc           #235                // int 27
     192: ldc_w         #600                // String session
     195: aastore
     196: aload_0
     197: ldc           #236                // int 28
     199: ldc_w         #617                // String collect
     202: aastore
     203: aload_0
     204: ldc           #242                // int 29
     206: ldc_w         #619                // String put
     209: aastore
     210: aload_0
     211: ldc_w         #256                // int 30
     214: ldc_w         #620                // String getAssociationIndexer
     217: aastore
     218: aload_0
     219: ldc_w         #257                // int 31
     222: ldc_w         #622                // String getObjectIdentifier
     225: aastore
     226: aload_0
     227: ldc_w         #261                // int 32
     230: ldc_w         #624                // String query
     233: aastore
     234: aload_0
     235: ldc_w         #270                // int 33
     238: ldc_w         #589                // String getAt
     241: aastore
     242: aload_0
     243: ldc_w         #273                // int 34
     246: ldc_w         #626                // String isPersistentEntity
     249: aastore
     250: aload_0
     251: ldc_w         #274                // int 35
     254: ldc_w         #628                // String mappingContext
     257: aastore
     258: aload_0
     259: ldc_w         #275                // int 36
     262: ldc_w         #630                // String getPersister
     265: aastore
     266: aload_0
     267: ldc_w         #276                // int 37
     270: ldc_w         #600                // String session
     273: aastore
     274: aload_0
     275: ldc_w         #279                // int 38
     278: ldc_w         #622                // String getObjectIdentifier
     281: aastore
     282: aload_0
     283: ldc_w         #280                // int 39
     286: ldc_w         #591                // String putAt
     289: aastore
     290: aload_0
     291: ldc_w         #286                // int 40
     294: ldc_w         #591                // String putAt
     297: aastore
     298: aload_0
     299: ldc_w         #290                // int 41
     302: ldc_w         #589                // String getAt
     305: aastore
     306: aload_0
     307: ldc_w         #293                // int 42
     310: ldc_w         #631                // String get
     313: aastore
     314: aload_0
     315: ldc_w         #294                // int 43
     318: ldc_w         #589                // String getAt
     321: aastore
     322: aload_0
     323: ldc_w         #295                // int 44
     326: ldc_w         #599                // String <$constructor$>
     329: aastore
     330: aload_0
     331: ldc_w         #302                // int 45
     334: ldc_w         #632                // String root
     337: aastore
     338: aload_0
     339: ldc_w         #303                // int 46
     342: ldc_w         #587                // String type
     345: aastore
     346: aload_0
     347: ldc_w         #304                // int 47
     350: ldc_w         #633                // String identity
     353: aastore
     354: aload_0
     355: ldc_w         #305                // int 48
     358: ldc_w         #587                // String type
     361: aastore
     362: aload_0
     363: ldc_w         #306                // int 49
     366: ldc_w         #633                // String identity
     369: aastore
     370: aload_0
     371: ldc_w         #307                // int 50
     374: ldc_w         #597                // String rootEntity
     377: aastore
     378: aload_0
     379: ldc_w         #308                // int 51
     382: ldc_w         #635                // String isAssignableFrom
     385: aastore
     386: aload_0
     387: ldc_w         #309                // int 52
     390: ldc_w         #635                // String isAssignableFrom
     393: aastore
     394: aload_0
     395: ldc_w         #312                // int 53
     398: ldc_w         #637                // String next
     401: aastore
     402: aload_0
     403: ldc_w         #313                // int 54
     406: ldc_w         #597                // String rootEntity
     409: aastore
     410: aload_0
     411: ldc_w         #314                // int 55
     414: ldc_w         #320                // String lastKey
     417: aastore
     418: aload_0
     419: ldc_w         #315                // int 56
     422: ldc_w         #630                // String getPersister
     425: aastore
     426: aload_0
     427: ldc_w         #316                // int 57
     430: ldc_w         #600                // String session
     433: aastore
     434: aload_0
     435: ldc_w         #317                // int 58
     438: ldc_w         #637                // String next
     441: aastore
     442: aload_0
     443: ldc_w         #318                // int 59
     446: ldc_w         #630                // String getPersister
     449: aastore
     450: aload_0
     451: ldc_w         #319                // int 60
     454: ldc_w         #600                // String session
     457: aastore
     458: aload_0
     459: ldc_w         #325                // int 61
     462: ldc_w         #320                // String lastKey
     465: aastore
     466: aload_0
     467: ldc_w         #326                // int 62
     470: ldc_w         #630                // String getPersister
     473: aastore
     474: aload_0
     475: ldc_w         #327                // int 63
     478: ldc_w         #600                // String session
     481: aastore
     482: aload_0
     483: ldc_w         #328                // int 64
     486: ldc_w         #639                // String toString
     489: aastore
     490: aload_0
     491: ldc_w         #329                // int 65
     494: ldc_w         #635                // String isAssignableFrom
     497: aastore
     498: aload_0
     499: ldc_w         #332                // int 66
     502: ldc_w         #641                // String randomUUID
     505: aastore
     506: aload_0
     507: ldc_w         #333                // int 67
     510: ldc_w         #643                // String newInstance
     513: aastore
     514: aload_0
     515: ldc_w         #334                // int 68
     518: ldc_w         #599                // String <$constructor$>
     521: aastore
     522: aload_0
     523: ldc_w         #357                // int 69
     526: ldc_w         #632                // String root
     529: aastore
     530: aload_0
     531: ldc_w         #358                // int 70
     534: ldc_w         #360                // String discriminator
     537: aastore
     538: aload_0
     539: ldc_w         #361                // int 71
     542: ldc_w         #619                // String put
     545: aastore
     546: aload_0
     547: ldc_w         #362                // int 72
     550: ldc_w         #589                // String getAt
     553: aastore
     554: aload_0
     555: ldc_w         #363                // int 73
     558: ldc_w         #644                // String indexIdentifier
     561: aastore
     562: aload_0
     563: ldc_w         #364                // int 74
     566: ldc_w         #645                // String updateInheritanceHierarchy
     569: aastore
     570: aload_0
     571: ldc_w         #373                // int 75
     574: ldc_w         #646                // String getPropertyIndexer
     577: aastore
     578: aload_0
     579: ldc_w         #374                // int 76
     582: ldc_w         #633                // String identity
     585: aastore
     586: aload_0
     587: ldc_w         #375                // int 77
     590: ldc_w         #648                // String index
     593: aastore
     594: aload_0
     595: ldc_w         #378                // int 78
     598: ldc_w         #606                // String parentEntity
     601: aastore
     602: aload_0
     603: ldc_w         #379                // int 79
     606: ldc_w         #582                // String getFamily
     609: aastore
     610: aload_0
     611: ldc_w         #380                // int 80
     614: ldc_w         #609                // String mapping
     617: aastore
     618: aload_0
     619: ldc_w         #381                // int 81
     622: ldc_w         #589                // String getAt
     625: aastore
     626: aload_0
     627: ldc_w         #382                // int 82
     630: ldc_w         #591                // String putAt
     633: aastore
     634: aload_0
     635: ldc_w         #383                // int 83
     638: ldc_w         #619                // String put
     641: aastore
     642: aload_0
     643: ldc_w         #384                // int 84
     646: ldc_w         #606                // String parentEntity
     649: aastore
     650: aload_0
     651: ldc_w         #388                // int 85
     654: ldc_w         #582                // String getFamily
     657: aastore
     658: aload_0
     659: ldc_w         #389                // int 86
     662: ldc_w         #584                // String getMapping
     665: aastore
     666: aload_0
     667: ldc_w         #390                // int 87
     670: ldc_w         #631                // String get
     673: aastore
     674: aload_0
     675: ldc_w         #391                // int 88
     678: ldc_w         #589                // String getAt
     681: aastore
     682: aload_0
     683: ldc_w         #392                // int 89
     686: ldc_w         #650                // String isVersioned
     689: aastore
     690: aload_0
     691: ldc_w         #393                // int 90
     694: ldc_w         #652                // String setVersion
     697: aastore
     698: aload_0
     699: ldc_w         #394                // int 91
     702: ldc_w         #397                // String version
     705: aastore
     706: aload_0
     707: ldc_w         #395                // int 92
     710: ldc_w         #653                // String getProperty
     713: aastore
     714: aload_0
     715: ldc_w         #398                // int 93
     718: ldc_w         #635                // String isAssignableFrom
     721: aastore
     722: aload_0
     723: ldc_w         #399                // int 94
     726: ldc_w         #655                // String getPropertyType
     729: aastore
     730: aload_0
     731: ldc_w         #400                // int 95
     734: ldc_w         #657                // String toLong
     737: aastore
     738: aload_0
     739: ldc_w         #401                // int 96
     742: ldc_w         #397                // String version
     745: aastore
     746: aload_0
     747: ldc_w         #405                // int 97
     750: ldc_w         #657                // String toLong
     753: aastore
     754: aload_0
     755: ldc_w         #406                // int 98
     758: ldc_w         #653                // String getProperty
     761: aastore
     762: aload_0
     763: ldc_w         #418                // int 99
     766: ldc_w         #658                // String setProperty
     769: aastore
     770: aload_0
     771: ldc_w         #419                // int 100
     774: ldc_w         #591                // String putAt
     777: aastore
     778: aload_0
     779: ldc_w         #420                // int 101
     782: ldc_w         #658                // String setProperty
     785: aastore
     786: aload_0
     787: ldc_w         #421                // int 102
     790: ldc_w         #591                // String putAt
     793: aastore
     794: aload_0
     795: ldc_w         #422                // int 103
     798: ldc_w         #660                // String equals
     801: aastore
     802: aload_0
     803: ldc_w         #423                // int 104
     806: ldc_w         #599                // String <$constructor$>
     809: aastore
     810: aload_0
     811: ldc_w         #428                // int 105
     814: ldc_w         #660                // String equals
     817: aastore
     818: aload_0
     819: ldc_w         #429                // int 106
     822: ldc_w         #599                // String <$constructor$>
     825: aastore
     826: aload_0
     827: ldc_w         #430                // int 107
     830: ldc_w         #662                // String incrementVersion
     833: aastore
     834: aload_0
     835: ldc_w         #431                // int 108
     838: ldc_w         #644                // String indexIdentifier
     841: aastore
     842: aload_0
     843: ldc_w         #432                // int 109
     846: ldc_w         #619                // String put
     849: aastore
     850: aload_0
     851: ldc_w         #433                // int 110
     854: ldc_w         #589                // String getAt
     857: aastore
     858: aload_0
     859: ldc_w         #434                // int 111
     862: ldc_w         #664                // String putAll
     865: aastore
     866: aload_0
     867: ldc_w         #435                // int 112
     870: ldc_w         #645                // String updateInheritanceHierarchy
     873: aastore
     874: aload_0
     875: ldc_w         #443                // int 113
     878: ldc_w         #666                // String each
     881: aastore
     882: return

  private static org.codehaus.groovy.runtime.callsite.CallSiteArray $createCallSiteArray();
    Code:
       0: ldc_w         #669                // int 114
       3: anewarray     #75                 // class java/lang/String
       6: astore_0
       7: aload_0
       8: invokestatic  #671                // Method $createCallSiteArray_1:([Ljava/lang/String;)V
      11: new           #673                // class org/codehaus/groovy/runtime/callsite/CallSiteArray
      14: dup
      15: ldc           #2                  // class org/grails/datastore/mapping/simple/engine/SimpleMapEntityPersister
      17: aload_0
      18: invokespecial #676                // Method org/codehaus/groovy/runtime/callsite/CallSiteArray."<init>":(Ljava/lang/Class;[Ljava/lang/String;)V
      21: areturn

  private static org.codehaus.groovy.runtime.callsite.CallSite[] $getCallSiteArray();
    Code:
       0: getstatic     #678                // Field $callSiteArray:Ljava/lang/ref/SoftReference;
       3: ifnull        20
       6: getstatic     #678                // Field $callSiteArray:Ljava/lang/ref/SoftReference;
       9: invokevirtual #681                // Method java/lang/ref/SoftReference.get:()Ljava/lang/Object;
      12: checkcast     #673                // class org/codehaus/groovy/runtime/callsite/CallSiteArray
      15: dup
      16: astore_0
      17: ifnonnull     35
      20: invokestatic  #683                // Method $createCallSiteArray:()Lorg/codehaus/groovy/runtime/callsite/CallSiteArray;
      23: astore_0
      24: new           #680                // class java/lang/ref/SoftReference
      27: dup
      28: aload_0
      29: invokespecial #684                // Method java/lang/ref/SoftReference."<init>":(Ljava/lang/Object;)V
      32: putstatic     #678                // Field $callSiteArray:Ljava/lang/ref/SoftReference;
      35: aload_0
      36: getfield      #687                // Field org/codehaus/groovy/runtime/callsite/CallSiteArray.array:[Lorg/codehaus/groovy/runtime/callsite/CallSite;
      39: areturn
}
