Compiled from "SimpleMapEntityPersister.groovy"
public class org.grails.datastore.mapping.simple.engine.SimpleMapEntityPersister$1 implements org.grails.datastore.mapping.engine.PropertyValueIndexer,groovy.lang.GroovyObject {
  public groovy.lang.Reference property;

  public org.grails.datastore.mapping.simple.engine.SimpleMapEntityPersister this$0;

  private static org.codehaus.groovy.reflection.ClassInfo $staticClassInfo;

  public static transient boolean __$stMC;

  private transient groovy.lang.MetaClass metaClass;

  private static java.lang.ref.SoftReference $callSiteArray;

  org.grails.datastore.mapping.simple.engine.SimpleMapEntityPersister$1(org.grails.datastore.mapping.simple.engine.SimpleMapEntityPersister, groovy.lang.Reference);
    Code:
       0: invokestatic  #30                 // Method $getCallSiteArray:()[Lorg/codehaus/groovy/runtime/callsite/CallSite;
       3: astore_3
       4: aload_1
       5: astore        4
       7: aload         4
       9: aload_0
      10: swap
      11: putfield      #32                 // Field this$0:Lorg/grails/datastore/mapping/simple/engine/SimpleMapEntityPersister;
      14: aload         4
      16: pop
      17: aload_0
      18: invokespecial #35                 // Method java/lang/Object."<init>":()V
      21: aload_2
      22: astore        5
      24: aload         5
      26: aload_0
      27: swap
      28: putfield      #37                 // Field property:Lgroovy/lang/Reference;
      31: aload         5
      33: pop
      34: aload_0
      35: invokevirtual #41                 // Method $getStaticMetaClass:()Lgroovy/lang/MetaClass;
      38: astore        6
      40: aload         6
      42: aload_0
      43: swap
      44: putfield      #43                 // Field metaClass:Lgroovy/lang/MetaClass;
      47: aload         6
      49: pop
      50: return

  public java.lang.String getIndexRoot();
    Code:
       0: invokestatic  #30                 // Method $getCallSiteArray:()[Lorg/codehaus/groovy/runtime/callsite/CallSite;
       3: astore_1
       4: new           #51                 // class org/codehaus/groovy/runtime/GStringImpl
       7: dup
       8: iconst_2
       9: anewarray     #4                  // class java/lang/Object
      12: dup
      13: iconst_0
      14: aload_1
      15: ldc           #52                 // int 0
      17: aaload
      18: aload_1
      19: ldc           #53                 // int 1
      21: aaload
      22: aload_1
      23: ldc           #54                 // int 2
      25: aaload
      26: aload_0
      27: getfield      #37                 // Field property:Lgroovy/lang/Reference;
      30: invokevirtual #60                 // Method groovy/lang/Reference.get:()Ljava/lang/Object;
      33: invokeinterface #66,  2           // InterfaceMethod org/codehaus/groovy/runtime/callsite/CallSite.callGetProperty:(Ljava/lang/Object;)Ljava/lang/Object;
      38: invokeinterface #66,  2           // InterfaceMethod org/codehaus/groovy/runtime/callsite/CallSite.callGetProperty:(Ljava/lang/Object;)Ljava/lang/Object;
      43: invokeinterface #66,  2           // InterfaceMethod org/codehaus/groovy/runtime/callsite/CallSite.callGetProperty:(Ljava/lang/Object;)Ljava/lang/Object;
      48: aastore
      49: dup
      50: iconst_1
      51: aload_1
      52: ldc           #67                 // int 3
      54: aaload
      55: aload_0
      56: getfield      #37                 // Field property:Lgroovy/lang/Reference;
      59: invokevirtual #60                 // Method groovy/lang/Reference.get:()Ljava/lang/Object;
      62: invokeinterface #66,  2           // InterfaceMethod org/codehaus/groovy/runtime/callsite/CallSite.callGetProperty:(Ljava/lang/Object;)Ljava/lang/Object;
      67: aastore
      68: iconst_3
      69: anewarray     #69                 // class java/lang/String
      72: dup
      73: iconst_0
      74: ldc           #71                 // String ~
      76: aastore
      77: dup
      78: iconst_1
      79: ldc           #73                 // String :
      81: aastore
      82: dup
      83: iconst_2
      84: ldc           #75                 // String
      86: aastore
      87: invokespecial #78                 // Method org/codehaus/groovy/runtime/GStringImpl."<init>":([Ljava/lang/Object;[Ljava/lang/String;)V
      90: invokestatic  #84                 // Method org/codehaus/groovy/runtime/typehandling/ShortTypeHandling.castToString:(Ljava/lang/Object;)Ljava/lang/String;
      93: checkcast     #69                 // class java/lang/String
      96: areturn
      97: nop
      98: athrow

  public void deindex(java.lang.Object, java.lang.Object);
    Code:
       0: invokestatic  #30                 // Method $getCallSiteArray:()[Lorg/codehaus/groovy/runtime/callsite/CallSite;
       3: astore_3
       4: aload_3
       5: ldc           #89                 // int 4
       7: aaload
       8: aload_0
       9: aload_1
      10: invokeinterface #93,  3           // InterfaceMethod org/codehaus/groovy/runtime/callsite/CallSite.callCurrent:(Lgroovy/lang/GroovyObject;Ljava/lang/Object;)Ljava/lang/Object;
      15: astore        4
      17: aload         4
      19: pop
      20: aload_3
      21: ldc           #94                 // int 5
      23: aaload
      24: aload_3
      25: ldc           #95                 // int 6
      27: aaload
      28: aload_0
      29: invokeinterface #98,  2           // InterfaceMethod org/codehaus/groovy/runtime/callsite/CallSite.callGroovyObjectGetProperty:(Ljava/lang/Object;)Ljava/lang/Object;
      34: aload         4
      36: invokeinterface #102,  3          // InterfaceMethod org/codehaus/groovy/runtime/callsite/CallSite.call:(Ljava/lang/Object;Ljava/lang/Object;)Ljava/lang/Object;
      41: astore        5
      43: aload         5
      45: pop
      46: aload         5
      48: invokestatic  #108                // Method org/codehaus/groovy/runtime/typehandling/DefaultTypeTransformation.booleanUnbox:(Ljava/lang/Object;)Z
      51: ifeq          67
      54: aload_3
      55: ldc           #109                // int 7
      57: aaload
      58: aload         5
      60: aload_2
      61: invokeinterface #102,  3          // InterfaceMethod org/codehaus/groovy/runtime/callsite/CallSite.call:(Ljava/lang/Object;Ljava/lang/Object;)Ljava/lang/Object;
      66: pop
      67: return

  public void index(java.lang.Object, java.lang.Object);
    Code:
       0: invokestatic  #30                 // Method $getCallSiteArray:()[Lorg/codehaus/groovy/runtime/callsite/CallSite;
       3: astore_3
       4: aload_3
       5: ldc           #117                // int 8
       7: aaload
       8: aload_0
       9: aload_1
      10: invokeinterface #93,  3           // InterfaceMethod org/codehaus/groovy/runtime/callsite/CallSite.callCurrent:(Lgroovy/lang/GroovyObject;Ljava/lang/Object;)Ljava/lang/Object;
      15: astore        4
      17: aload         4
      19: pop
      20: aload_3
      21: ldc           #118                // int 9
      23: aaload
      24: aload_3
      25: ldc           #119                // int 10
      27: aaload
      28: aload_0
      29: invokeinterface #98,  2           // InterfaceMethod org/codehaus/groovy/runtime/callsite/CallSite.callGroovyObjectGetProperty:(Ljava/lang/Object;)Ljava/lang/Object;
      34: aload         4
      36: invokeinterface #102,  3          // InterfaceMethod org/codehaus/groovy/runtime/callsite/CallSite.call:(Ljava/lang/Object;Ljava/lang/Object;)Ljava/lang/Object;
      41: astore        5
      43: aload         5
      45: pop
      46: aload         5
      48: aconst_null
      49: invokestatic  #125                // Method org/codehaus/groovy/runtime/ScriptBytecodeAdapter.compareEqual:(Ljava/lang/Object;Ljava/lang/Object;)Z
      52: ifeq          102
      55: iconst_0
      56: anewarray     #4                  // class java/lang/Object
      59: invokestatic  #129                // Method org/codehaus/groovy/runtime/ScriptBytecodeAdapter.createList:([Ljava/lang/Object;)Ljava/util/List;
      62: astore        6
      64: aload         6
      66: astore        5
      68: aload         6
      70: pop
      71: aload         5
      73: astore        7
      75: aload_3
      76: ldc           #130                // int 11
      78: aaload
      79: aload_3
      80: ldc           #131                // int 12
      82: aaload
      83: aload_0
      84: invokeinterface #98,  2           // InterfaceMethod org/codehaus/groovy/runtime/callsite/CallSite.callGroovyObjectGetProperty:(Ljava/lang/Object;)Ljava/lang/Object;
      89: aload         4
      91: aload         7
      93: invokeinterface #134,  4          // InterfaceMethod org/codehaus/groovy/runtime/callsite/CallSite.call:(Ljava/lang/Object;Ljava/lang/Object;Ljava/lang/Object;)Ljava/lang/Object;
      98: pop
      99: aload         7
     101: pop
     102: aload_3
     103: ldc           #135                // int 13
     105: aaload
     106: aload         5
     108: aload_2
     109: invokeinterface #102,  3          // InterfaceMethod org/codehaus/groovy/runtime/callsite/CallSite.call:(Ljava/lang/Object;Ljava/lang/Object;)Ljava/lang/Object;
     114: invokestatic  #108                // Method org/codehaus/groovy/runtime/typehandling/DefaultTypeTransformation.booleanUnbox:(Ljava/lang/Object;)Z
     117: ifne          124
     120: iconst_1
     121: goto          125
     124: iconst_0
     125: ifeq          141
     128: aload_3
     129: ldc           #136                // int 14
     131: aaload
     132: aload         5
     134: aload_2
     135: invokeinterface #102,  3          // InterfaceMethod org/codehaus/groovy/runtime/callsite/CallSite.call:(Ljava/lang/Object;Ljava/lang/Object;)Ljava/lang/Object;
     140: pop
     141: return

  public java.util.List query(java.lang.Object);
    Code:
       0: invokestatic  #30                 // Method $getCallSiteArray:()[Lorg/codehaus/groovy/runtime/callsite/CallSite;
       3: astore_2
       4: aload_2
       5: ldc           #139                // int 15
       7: aaload
       8: aload_0
       9: aload_1
      10: iconst_0
      11: invokestatic  #145                // Method java/lang/Integer.valueOf:(I)Ljava/lang/Integer;
      14: bipush        -1
      16: invokestatic  #145                // Method java/lang/Integer.valueOf:(I)Ljava/lang/Integer;
      19: invokeinterface #148,  5          // InterfaceMethod org/codehaus/groovy/runtime/callsite/CallSite.callCurrent:(Lgroovy/lang/GroovyObject;Ljava/lang/Object;Ljava/lang/Object;Ljava/lang/Object;)Ljava/lang/Object;
      24: ldc           #150                // class java/util/List
      26: invokestatic  #154                // Method org/codehaus/groovy/runtime/ScriptBytecodeAdapter.castToType:(Ljava/lang/Object;Ljava/lang/Class;)Ljava/lang/Object;
      29: checkcast     #150                // class java/util/List
      32: areturn
      33: nop
      34: athrow

  public java.util.List query(java.lang.Object, int, int);
    Code:
       0: invokestatic  #30                 // Method $getCallSiteArray:()[Lorg/codehaus/groovy/runtime/callsite/CallSite;
       3: astore        4
       5: aload         4
       7: ldc           #156                // int 16
       9: aaload
      10: aload_0
      11: aload_1
      12: invokeinterface #93,  3           // InterfaceMethod org/codehaus/groovy/runtime/callsite/CallSite.callCurrent:(Lgroovy/lang/GroovyObject;Ljava/lang/Object;)Ljava/lang/Object;
      17: astore        5
      19: aload         5
      21: pop
      22: aload         4
      24: ldc           #157                // int 17
      26: aaload
      27: aload         4
      29: ldc           #158                // int 18
      31: aaload
      32: aload_0
      33: invokeinterface #98,  2           // InterfaceMethod org/codehaus/groovy/runtime/callsite/CallSite.callGroovyObjectGetProperty:(Ljava/lang/Object;)Ljava/lang/Object;
      38: aload         5
      40: invokeinterface #102,  3          // InterfaceMethod org/codehaus/groovy/runtime/callsite/CallSite.call:(Ljava/lang/Object;Ljava/lang/Object;)Ljava/lang/Object;
      45: astore        6
      47: aload         6
      49: pop
      50: aload         6
      52: invokestatic  #108                // Method org/codehaus/groovy/runtime/typehandling/DefaultTypeTransformation.booleanUnbox:(Ljava/lang/Object;)Z
      55: ifne          62
      58: iconst_1
      59: goto          63
      62: iconst_0
      63: ifeq          87
      66: aload         4
      68: ldc           #159                // int 19
      70: aaload
      71: ldc           #161                // class java/util/Collections
      73: invokeinterface #163,  2          // InterfaceMethod org/codehaus/groovy/runtime/callsite/CallSite.call:(Ljava/lang/Object;)Ljava/lang/Object;
      78: ldc           #150                // class java/util/List
      80: invokestatic  #154                // Method org/codehaus/groovy/runtime/ScriptBytecodeAdapter.castToType:(Ljava/lang/Object;Ljava/lang/Class;)Ljava/lang/Object;
      83: checkcast     #150                // class java/util/List
      86: areturn
      87: aload         4
      89: ldc           #164                // int 20
      91: aaload
      92: aload         6
      94: iload_2
      95: invokestatic  #145                // Method java/lang/Integer.valueOf:(I)Ljava/lang/Integer;
      98: iload_3
      99: invokestatic  #145                // Method java/lang/Integer.valueOf:(I)Ljava/lang/Integer;
     102: ldc           #53                 // int 1
     104: invokestatic  #168                // Method org/codehaus/groovy/runtime/ScriptBytecodeAdapter.createRange:(Ljava/lang/Object;Ljava/lang/Object;Z)Ljava/util/List;
     107: invokeinterface #102,  3          // InterfaceMethod org/codehaus/groovy/runtime/callsite/CallSite.call:(Ljava/lang/Object;Ljava/lang/Object;)Ljava/lang/Object;
     112: ldc           #150                // class java/util/List
     114: invokestatic  #154                // Method org/codehaus/groovy/runtime/ScriptBytecodeAdapter.castToType:(Ljava/lang/Object;Ljava/lang/Class;)Ljava/lang/Object;
     117: checkcast     #150                // class java/util/List
     120: areturn
     121: nop
     122: athrow

  public java.lang.String getIndexName(java.lang.Object);
    Code:
       0: invokestatic  #30                 // Method $getCallSiteArray:()[Lorg/codehaus/groovy/runtime/callsite/CallSite;
       3: astore_2
       4: new           #51                 // class org/codehaus/groovy/runtime/GStringImpl
       7: dup
       8: iconst_2
       9: anewarray     #4                  // class java/lang/Object
      12: dup
      13: iconst_0
      14: aload_2
      15: ldc           #173                // int 21
      17: aaload
      18: aload_0
      19: invokeinterface #98,  2           // InterfaceMethod org/codehaus/groovy/runtime/callsite/CallSite.callGroovyObjectGetProperty:(Ljava/lang/Object;)Ljava/lang/Object;
      24: aastore
      25: dup
      26: iconst_1
      27: aload_1
      28: aastore
      29: iconst_3
      30: anewarray     #69                 // class java/lang/String
      33: dup
      34: iconst_0
      35: ldc           #75                 // String
      37: aastore
      38: dup
      39: iconst_1
      40: ldc           #73                 // String :
      42: aastore
      43: dup
      44: iconst_2
      45: ldc           #75                 // String
      47: aastore
      48: invokespecial #78                 // Method org/codehaus/groovy/runtime/GStringImpl."<init>":([Ljava/lang/Object;[Ljava/lang/String;)V
      51: invokestatic  #84                 // Method org/codehaus/groovy/runtime/typehandling/ShortTypeHandling.castToString:(Ljava/lang/Object;)Ljava/lang/String;
      54: checkcast     #69                 // class java/lang/String
      57: areturn
      58: nop
      59: athrow

  public java.lang.Object methodMissing(java.lang.String, java.lang.Object);
    Code:
       0: invokestatic  #30                 // Method $getCallSiteArray:()[Lorg/codehaus/groovy/runtime/callsite/CallSite;
       3: astore_3
       4: aload_0
       5: getfield      #32                 // Field this$0:Lorg/grails/datastore/mapping/simple/engine/SimpleMapEntityPersister;
       8: aload_1
       9: aload_2
      10: invokevirtual #178                // Method org/grails/datastore/mapping/simple/engine/SimpleMapEntityPersister.this$dist$invoke$6:(Ljava/lang/String;Ljava/lang/Object;)Ljava/lang/Object;
      13: areturn
      14: nop
      15: athrow

  public static java.lang.Object $static_methodMissing(java.lang.String, java.lang.Object);
    Code:
       0: invokestatic  #30                 // Method $getCallSiteArray:()[Lorg/codehaus/groovy/runtime/callsite/CallSite;
       3: astore_2
       4: ldc           #2                  // class org/grails/datastore/mapping/simple/engine/SimpleMapEntityPersister$1
       6: ldc           #11                 // class org/grails/datastore/mapping/simple/engine/SimpleMapEntityPersister
       8: new           #51                 // class org/codehaus/groovy/runtime/GStringImpl
      11: dup
      12: iconst_1
      13: anewarray     #4                  // class java/lang/Object
      16: dup
      17: iconst_0
      18: aload_0
      19: aastore
      20: iconst_2
      21: anewarray     #69                 // class java/lang/String
      24: dup
      25: iconst_0
      26: ldc           #75                 // String
      28: aastore
      29: dup
      30: iconst_1
      31: ldc           #75                 // String
      33: aastore
      34: invokespecial #78                 // Method org/codehaus/groovy/runtime/GStringImpl."<init>":([Ljava/lang/Object;[Ljava/lang/String;)V
      37: invokestatic  #84                 // Method org/codehaus/groovy/runtime/typehandling/ShortTypeHandling.castToString:(Ljava/lang/Object;)Ljava/lang/String;
      40: checkcast     #69                 // class java/lang/String
      43: iconst_0
      44: anewarray     #4                  // class java/lang/Object
      47: iconst_1
      48: anewarray     #4                  // class java/lang/Object
      51: dup
      52: iconst_0
      53: aload_1
      54: aastore
      55: iconst_1
      56: newarray       int
      58: dup
      59: iconst_0
      60: iconst_0
      61: iastore
      62: invokestatic  #186                // Method org/codehaus/groovy/runtime/ScriptBytecodeAdapter.despreadList:([Ljava/lang/Object;[Ljava/lang/Object;[I)[Ljava/lang/Object;
      65: invokestatic  #190                // Method org/codehaus/groovy/runtime/ScriptBytecodeAdapter.invokeMethodN:(Ljava/lang/Class;Ljava/lang/Object;Ljava/lang/String;[Ljava/lang/Object;)Ljava/lang/Object;
      68: areturn
      69: nop
      70: athrow

  public void propertyMissing(java.lang.String, java.lang.Object);
    Code:
       0: invokestatic  #30                 // Method $getCallSiteArray:()[Lorg/codehaus/groovy/runtime/callsite/CallSite;
       3: astore_3
       4: aload_0
       5: getfield      #32                 // Field this$0:Lorg/grails/datastore/mapping/simple/engine/SimpleMapEntityPersister;
       8: aload_1
       9: aload_2
      10: invokevirtual #195                // Method org/grails/datastore/mapping/simple/engine/SimpleMapEntityPersister.this$dist$set$6:(Ljava/lang/String;Ljava/lang/Object;)V
      13: return
      14: athrow

  public static void $static_propertyMissing(java.lang.String, java.lang.Object);
    Code:
       0: invokestatic  #30                 // Method $getCallSiteArray:()[Lorg/codehaus/groovy/runtime/callsite/CallSite;
       3: astore_2
       4: aload_1
       5: astore_3
       6: aload_3
       7: aconst_null
       8: ldc           #11                 // class org/grails/datastore/mapping/simple/engine/SimpleMapEntityPersister
      10: new           #51                 // class org/codehaus/groovy/runtime/GStringImpl
      13: dup
      14: iconst_1
      15: anewarray     #4                  // class java/lang/Object
      18: dup
      19: iconst_0
      20: aload_0
      21: aastore
      22: iconst_2
      23: anewarray     #69                 // class java/lang/String
      26: dup
      27: iconst_0
      28: ldc           #75                 // String
      30: aastore
      31: dup
      32: iconst_1
      33: ldc           #75                 // String
      35: aastore
      36: invokespecial #78                 // Method org/codehaus/groovy/runtime/GStringImpl."<init>":([Ljava/lang/Object;[Ljava/lang/String;)V
      39: invokestatic  #84                 // Method org/codehaus/groovy/runtime/typehandling/ShortTypeHandling.castToString:(Ljava/lang/Object;)Ljava/lang/String;
      42: checkcast     #69                 // class java/lang/String
      45: invokestatic  #201                // Method org/codehaus/groovy/runtime/ScriptBytecodeAdapter.setProperty:(Ljava/lang/Object;Ljava/lang/Class;Ljava/lang/Object;Ljava/lang/String;)V
      48: aload_3
      49: pop
      50: return

  public java.lang.Object propertyMissing(java.lang.String);
    Code:
       0: invokestatic  #30                 // Method $getCallSiteArray:()[Lorg/codehaus/groovy/runtime/callsite/CallSite;
       3: astore_2
       4: aload_0
       5: getfield      #32                 // Field this$0:Lorg/grails/datastore/mapping/simple/engine/SimpleMapEntityPersister;
       8: aload_1
       9: invokevirtual #205                // Method org/grails/datastore/mapping/simple/engine/SimpleMapEntityPersister.this$dist$get$6:(Ljava/lang/String;)Ljava/lang/Object;
      12: areturn
      13: nop
      14: athrow

  public static java.lang.Object $static_propertyMissing(java.lang.String);
    Code:
       0: invokestatic  #30                 // Method $getCallSiteArray:()[Lorg/codehaus/groovy/runtime/callsite/CallSite;
       3: astore_1
       4: ldc           #2                  // class org/grails/datastore/mapping/simple/engine/SimpleMapEntityPersister$1
       6: ldc           #11                 // class org/grails/datastore/mapping/simple/engine/SimpleMapEntityPersister
       8: new           #51                 // class org/codehaus/groovy/runtime/GStringImpl
      11: dup
      12: iconst_1
      13: anewarray     #4                  // class java/lang/Object
      16: dup
      17: iconst_0
      18: aload_0
      19: aastore
      20: iconst_2
      21: anewarray     #69                 // class java/lang/String
      24: dup
      25: iconst_0
      26: ldc           #75                 // String
      28: aastore
      29: dup
      30: iconst_1
      31: ldc           #75                 // String
      33: aastore
      34: invokespecial #78                 // Method org/codehaus/groovy/runtime/GStringImpl."<init>":([Ljava/lang/Object;[Ljava/lang/String;)V
      37: invokestatic  #84                 // Method org/codehaus/groovy/runtime/typehandling/ShortTypeHandling.castToString:(Ljava/lang/Object;)Ljava/lang/String;
      40: checkcast     #69                 // class java/lang/String
      43: invokestatic  #209                // Method org/codehaus/groovy/runtime/ScriptBytecodeAdapter.getProperty:(Ljava/lang/Class;Ljava/lang/Object;Ljava/lang/String;)Ljava/lang/Object;
      46: areturn
      47: nop
      48: athrow

  protected groovy.lang.MetaClass $getStaticMetaClass();
    Code:
       0: aload_0
       1: invokevirtual #213                // Method java/lang/Object.getClass:()Ljava/lang/Class;
       4: ldc           #2                  // class org/grails/datastore/mapping/simple/engine/SimpleMapEntityPersister$1
       6: if_acmpeq     14
       9: aload_0
      10: invokestatic  #217                // Method org/codehaus/groovy/runtime/ScriptBytecodeAdapter.initMetaClass:(Ljava/lang/Object;)Lgroovy/lang/MetaClass;
      13: areturn
      14: getstatic     #219                // Field $staticClassInfo:Lorg/codehaus/groovy/reflection/ClassInfo;
      17: astore_1
      18: aload_1
      19: ifnonnull     34
      22: aload_0
      23: invokevirtual #213                // Method java/lang/Object.getClass:()Ljava/lang/Class;
      26: invokestatic  #225                // Method org/codehaus/groovy/reflection/ClassInfo.getClassInfo:(Ljava/lang/Class;)Lorg/codehaus/groovy/reflection/ClassInfo;
      29: dup
      30: astore_1
      31: putstatic     #219                // Field $staticClassInfo:Lorg/codehaus/groovy/reflection/ClassInfo;
      34: aload_1
      35: invokevirtual #228                // Method org/codehaus/groovy/reflection/ClassInfo.getMetaClass:()Lgroovy/lang/MetaClass;
      38: areturn

  public groovy.lang.MetaClass getMetaClass();
    Code:
       0: aload_0
       1: getfield      #43                 // Field metaClass:Lgroovy/lang/MetaClass;
       4: dup
       5: ifnull        9
       8: areturn
       9: pop
      10: aload_0
      11: dup
      12: invokevirtual #41                 // Method $getStaticMetaClass:()Lgroovy/lang/MetaClass;
      15: putfield      #43                 // Field metaClass:Lgroovy/lang/MetaClass;
      18: aload_0
      19: getfield      #43                 // Field metaClass:Lgroovy/lang/MetaClass;
      22: areturn

  public void setMetaClass(groovy.lang.MetaClass);
    Code:
       0: aload_0
       1: aload_1
       2: putfield      #43                 // Field metaClass:Lgroovy/lang/MetaClass;
       5: return

  public java.lang.Object invokeMethod(java.lang.String, java.lang.Object);
    Code:
       0: aload_0
       1: invokevirtual #234                // Method getMetaClass:()Lgroovy/lang/MetaClass;
       4: aload_0
       5: aload_1
       6: aload_2
       7: invokeinterface #237,  4          // InterfaceMethod groovy/lang/MetaClass.invokeMethod:(Ljava/lang/Object;Ljava/lang/String;Ljava/lang/Object;)Ljava/lang/Object;
      12: areturn

  public java.lang.Object getProperty(java.lang.String);
    Code:
       0: aload_0
       1: invokevirtual #234                // Method getMetaClass:()Lgroovy/lang/MetaClass;
       4: aload_0
       5: aload_1
       6: invokeinterface #240,  3          // InterfaceMethod groovy/lang/MetaClass.getProperty:(Ljava/lang/Object;Ljava/lang/String;)Ljava/lang/Object;
      11: areturn

  public void setProperty(java.lang.String, java.lang.Object);
    Code:
       0: aload_0
       1: invokevirtual #234                // Method getMetaClass:()Lgroovy/lang/MetaClass;
       4: aload_0
       5: aload_1
       6: aload_2
       7: invokeinterface #243,  4          // InterfaceMethod groovy/lang/MetaClass.setProperty:(Ljava/lang/Object;Ljava/lang/String;Ljava/lang/Object;)V
      12: return

  private static void $createCallSiteArray_1(java.lang.String[]);
    Code:
       0: aload_0
       1: ldc           #52                 // int 0
       3: ldc           #248                // String name
       5: aastore
       6: aload_0
       7: ldc           #53                 // int 1
       9: ldc           #250                // String rootEntity
      11: aastore
      12: aload_0
      13: ldc           #54                 // int 2
      15: ldc           #252                // String owner
      17: aastore
      18: aload_0
      19: ldc           #67                 // int 3
      21: ldc           #248                // String name
      23: aastore
      24: aload_0
      25: ldc           #89                 // int 4
      27: ldc           #253                // String getIndexName
      29: aastore
      30: aload_0
      31: ldc           #94                 // int 5
      33: ldc           #255                // String getAt
      35: aastore
      36: aload_0
      37: ldc           #95                 // int 6
      39: ldc_w         #257                // String indices
      42: aastore
      43: aload_0
      44: ldc           #109                // int 7
      46: ldc_w         #259                // String remove
      49: aastore
      50: aload_0
      51: ldc           #117                // int 8
      53: ldc           #253                // String getIndexName
      55: aastore
      56: aload_0
      57: ldc           #118                // int 9
      59: ldc           #255                // String getAt
      61: aastore
      62: aload_0
      63: ldc           #119                // int 10
      65: ldc_w         #257                // String indices
      68: aastore
      69: aload_0
      70: ldc           #130                // int 11
      72: ldc_w         #261                // String putAt
      75: aastore
      76: aload_0
      77: ldc           #131                // int 12
      79: ldc_w         #257                // String indices
      82: aastore
      83: aload_0
      84: ldc           #135                // int 13
      86: ldc_w         #263                // String contains
      89: aastore
      90: aload_0
      91: ldc           #136                // int 14
      93: ldc_w         #265                // String leftShift
      96: aastore
      97: aload_0
      98: ldc           #139                // int 15
     100: ldc_w         #266                // String query
     103: aastore
     104: aload_0
     105: ldc           #156                // int 16
     107: ldc           #253                // String getIndexName
     109: aastore
     110: aload_0
     111: ldc           #157                // int 17
     113: ldc           #255                // String getAt
     115: aastore
     116: aload_0
     117: ldc           #158                // int 18
     119: ldc_w         #257                // String indices
     122: aastore
     123: aload_0
     124: ldc           #159                // int 19
     126: ldc_w         #268                // String emptyList
     129: aastore
     130: aload_0
     131: ldc           #164                // int 20
     133: ldc           #255                // String getAt
     135: aastore
     136: aload_0
     137: ldc           #173                // int 21
     139: ldc_w         #270                // String indexRoot
     142: aastore
     143: return

  private static org.codehaus.groovy.runtime.callsite.CallSiteArray $createCallSiteArray();
    Code:
       0: ldc_w         #273                // int 22
       3: anewarray     #69                 // class java/lang/String
       6: astore_0
       7: aload_0
       8: invokestatic  #275                // Method $createCallSiteArray_1:([Ljava/lang/String;)V
      11: new           #277                // class org/codehaus/groovy/runtime/callsite/CallSiteArray
      14: dup
      15: ldc           #2                  // class org/grails/datastore/mapping/simple/engine/SimpleMapEntityPersister$1
      17: aload_0
      18: invokespecial #280                // Method org/codehaus/groovy/runtime/callsite/CallSiteArray."<init>":(Ljava/lang/Class;[Ljava/lang/String;)V
      21: areturn

  private static org.codehaus.groovy.runtime.callsite.CallSite[] $getCallSiteArray();
    Code:
       0: getstatic     #282                // Field $callSiteArray:Ljava/lang/ref/SoftReference;
       3: ifnull        20
       6: getstatic     #282                // Field $callSiteArray:Ljava/lang/ref/SoftReference;
       9: invokevirtual #285                // Method java/lang/ref/SoftReference.get:()Ljava/lang/Object;
      12: checkcast     #277                // class org/codehaus/groovy/runtime/callsite/CallSiteArray
      15: dup
      16: astore_0
      17: ifnonnull     35
      20: invokestatic  #287                // Method $createCallSiteArray:()Lorg/codehaus/groovy/runtime/callsite/CallSiteArray;
      23: astore_0
      24: new           #284                // class java/lang/ref/SoftReference
      27: dup
      28: aload_0
      29: invokespecial #290                // Method java/lang/ref/SoftReference."<init>":(Ljava/lang/Object;)V
      32: putstatic     #282                // Field $callSiteArray:Ljava/lang/ref/SoftReference;
      35: aload_0
      36: getfield      #293                // Field org/codehaus/groovy/runtime/callsite/CallSiteArray.array:[Lorg/codehaus/groovy/runtime/callsite/CallSite;
      39: areturn
}
