Compiled from "TransformOps.scala"
public class edu.psu.sagnik.research.inkscapesvgprocessing.transformparser.model.SkewXOp implements scala.Product,scala.Serializable {
  private final java.lang.String command;

  private final edu.psu.sagnik.research.inkscapesvgprocessing.transformparser.model.SkewXOpArg args;

  public static scala.Option<scala.Tuple2<java.lang.String, edu.psu.sagnik.research.inkscapesvgprocessing.transformparser.model.SkewXOpArg>> unapply(edu.psu.sagnik.research.inkscapesvgprocessing.transformparser.model.SkewXOp);
    Code:
       0: getstatic     #20                 // Field edu/psu/sagnik/research/inkscapesvgprocessing/transformparser/model/SkewXOp$.MODULE$:Ledu/psu/sagnik/research/inkscapesvgprocessing/transformparser/model/SkewXOp$;
       3: aload_0
       4: invokevirtual #22                 // Method edu/psu/sagnik/research/inkscapesvgprocessing/transformparser/model/SkewXOp$.unapply:(Ledu/psu/sagnik/research/inkscapesvgprocessing/transformparser/model/SkewXOp;)Lscala/Option;
       7: areturn

  public static edu.psu.sagnik.research.inkscapesvgprocessing.transformparser.model.SkewXOp apply(java.lang.String, edu.psu.sagnik.research.inkscapesvgprocessing.transformparser.model.SkewXOpArg);
    Code:
       0: getstatic     #20                 // Field edu/psu/sagnik/research/inkscapesvgprocessing/transformparser/model/SkewXOp$.MODULE$:Ledu/psu/sagnik/research/inkscapesvgprocessing/transformparser/model/SkewXOp$;
       3: aload_0
       4: aload_1
       5: invokevirtual #26                 // Method edu/psu/sagnik/research/inkscapesvgprocessing/transformparser/model/SkewXOp$.apply:(Ljava/lang/String;Ledu/psu/sagnik/research/inkscapesvgprocessing/transformparser/model/SkewXOpArg;)Ledu/psu/sagnik/research/inkscapesvgprocessing/transformparser/model/SkewXOp;
       8: areturn

  public static scala.Function1<scala.Tuple2<java.lang.String, edu.psu.sagnik.research.inkscapesvgprocessing.transformparser.model.SkewXOpArg>, edu.psu.sagnik.research.inkscapesvgprocessing.transformparser.model.SkewXOp> tupled();
    Code:
       0: getstatic     #20                 // Field edu/psu/sagnik/research/inkscapesvgprocessing/transformparser/model/SkewXOp$.MODULE$:Ledu/psu/sagnik/research/inkscapesvgprocessing/transformparser/model/SkewXOp$;
       3: invokevirtual #30                 // Method edu/psu/sagnik/research/inkscapesvgprocessing/transformparser/model/SkewXOp$.tupled:()Lscala/Function1;
       6: areturn

  public static scala.Function1<java.lang.String, scala.Function1<edu.psu.sagnik.research.inkscapesvgprocessing.transformparser.model.SkewXOpArg, edu.psu.sagnik.research.inkscapesvgprocessing.transformparser.model.SkewXOp>> curried();
    Code:
       0: getstatic     #20                 // Field edu/psu/sagnik/research/inkscapesvgprocessing/transformparser/model/SkewXOp$.MODULE$:Ledu/psu/sagnik/research/inkscapesvgprocessing/transformparser/model/SkewXOp$;
       3: invokevirtual #33                 // Method edu/psu/sagnik/research/inkscapesvgprocessing/transformparser/model/SkewXOp$.curried:()Lscala/Function1;
       6: areturn

  public java.lang.String command();
    Code:
       0: aload_0
       1: getfield      #40                 // Field command:Ljava/lang/String;
       4: areturn

  public edu.psu.sagnik.research.inkscapesvgprocessing.transformparser.model.SkewXOpArg args();
    Code:
       0: aload_0
       1: getfield      #45                 // Field args:Ledu/psu/sagnik/research/inkscapesvgprocessing/transformparser/model/SkewXOpArg;
       4: areturn

  public edu.psu.sagnik.research.inkscapesvgprocessing.transformparser.model.SkewXOp copy(java.lang.String, edu.psu.sagnik.research.inkscapesvgprocessing.transformparser.model.SkewXOpArg);
    Code:
       0: new           #2                  // class edu/psu/sagnik/research/inkscapesvgprocessing/transformparser/model/SkewXOp
       3: dup
       4: aload_1
       5: aload_2
       6: invokespecial #50                 // Method "<init>":(Ljava/lang/String;Ledu/psu/sagnik/research/inkscapesvgprocessing/transformparser/model/SkewXOpArg;)V
       9: areturn

  public java.lang.String copy$default$1();
    Code:
       0: aload_0
       1: invokevirtual #53                 // Method command:()Ljava/lang/String;
       4: areturn

  public edu.psu.sagnik.research.inkscapesvgprocessing.transformparser.model.SkewXOpArg copy$default$2();
    Code:
       0: aload_0
       1: invokevirtual #56                 // Method args:()Ledu/psu/sagnik/research/inkscapesvgprocessing/transformparser/model/SkewXOpArg;
       4: areturn

  public java.lang.String productPrefix();
    Code:
       0: ldc           #59                 // String SkewXOp
       2: areturn

  public int productArity();
    Code:
       0: iconst_2
       1: ireturn

  public java.lang.Object productElement(int);
    Code:
       0: iload_1
       1: istore_2
       2: iload_2
       3: tableswitch   { // 0 to 1
                     0: 46
                     1: 39
               default: 24
          }
      24: new           #65                 // class java/lang/IndexOutOfBoundsException
      27: dup
      28: iload_1
      29: invokestatic  #71                 // Method scala/runtime/BoxesRunTime.boxToInteger:(I)Ljava/lang/Integer;
      32: invokevirtual #74                 // Method java/lang/Object.toString:()Ljava/lang/String;
      35: invokespecial #77                 // Method java/lang/IndexOutOfBoundsException."<init>":(Ljava/lang/String;)V
      38: athrow
      39: aload_0
      40: invokevirtual #56                 // Method args:()Ledu/psu/sagnik/research/inkscapesvgprocessing/transformparser/model/SkewXOpArg;
      43: goto          50
      46: aload_0
      47: invokevirtual #53                 // Method command:()Ljava/lang/String;
      50: areturn

  public scala.collection.Iterator<java.lang.Object> productIterator();
    Code:
       0: getstatic     #86                 // Field scala/runtime/ScalaRunTime$.MODULE$:Lscala/runtime/ScalaRunTime$;
       3: aload_0
       4: invokevirtual #90                 // Method scala/runtime/ScalaRunTime$.typedProductIterator:(Lscala/Product;)Lscala/collection/Iterator;
       7: areturn

  public boolean canEqual(java.lang.Object);
    Code:
       0: aload_1
       1: instanceof    #2                  // class edu/psu/sagnik/research/inkscapesvgprocessing/transformparser/model/SkewXOp
       4: ireturn

  public int hashCode();
    Code:
       0: getstatic     #86                 // Field scala/runtime/ScalaRunTime$.MODULE$:Lscala/runtime/ScalaRunTime$;
       3: aload_0
       4: invokevirtual #98                 // Method scala/runtime/ScalaRunTime$._hashCode:(Lscala/Product;)I
       7: ireturn

  public java.lang.String toString();
    Code:
       0: getstatic     #86                 // Field scala/runtime/ScalaRunTime$.MODULE$:Lscala/runtime/ScalaRunTime$;
       3: aload_0
       4: invokevirtual #102                // Method scala/runtime/ScalaRunTime$._toString:(Lscala/Product;)Ljava/lang/String;
       7: areturn

  public boolean equals(java.lang.Object);
    Code:
       0: aload_0
       1: aload_1
       2: if_acmpeq     112
       5: aload_1
       6: astore_2
       7: aload_2
       8: instanceof    #2                  // class edu/psu/sagnik/research/inkscapesvgprocessing/transformparser/model/SkewXOp
      11: ifeq          19
      14: iconst_1
      15: istore_3
      16: goto          21
      19: iconst_0
      20: istore_3
      21: iload_3
      22: ifeq          116
      25: aload_1
      26: checkcast     #2                  // class edu/psu/sagnik/research/inkscapesvgprocessing/transformparser/model/SkewXOp
      29: astore        4
      31: aload_0
      32: invokevirtual #53                 // Method command:()Ljava/lang/String;
      35: aload         4
      37: invokevirtual #53                 // Method command:()Ljava/lang/String;
      40: astore        5
      42: dup
      43: ifnonnull     55
      46: pop
      47: aload         5
      49: ifnull        63
      52: goto          108
      55: aload         5
      57: invokevirtual #105                // Method java/lang/Object.equals:(Ljava/lang/Object;)Z
      60: ifeq          108
      63: aload_0
      64: invokevirtual #56                 // Method args:()Ledu/psu/sagnik/research/inkscapesvgprocessing/transformparser/model/SkewXOpArg;
      67: aload         4
      69: invokevirtual #56                 // Method args:()Ledu/psu/sagnik/research/inkscapesvgprocessing/transformparser/model/SkewXOpArg;
      72: astore        6
      74: dup
      75: ifnonnull     87
      78: pop
      79: aload         6
      81: ifnull        95
      84: goto          108
      87: aload         6
      89: invokevirtual #105                // Method java/lang/Object.equals:(Ljava/lang/Object;)Z
      92: ifeq          108
      95: aload         4
      97: aload_0
      98: invokevirtual #107                // Method canEqual:(Ljava/lang/Object;)Z
     101: ifeq          108
     104: iconst_1
     105: goto          109
     108: iconst_0
     109: ifeq          116
     112: iconst_1
     113: goto          117
     116: iconst_0
     117: ireturn

  public edu.psu.sagnik.research.inkscapesvgprocessing.transformparser.model.SkewXOp(java.lang.String, edu.psu.sagnik.research.inkscapesvgprocessing.transformparser.model.SkewXOpArg);
    Code:
       0: aload_0
       1: aload_1
       2: putfield      #40                 // Field command:Ljava/lang/String;
       5: aload_0
       6: aload_2
       7: putfield      #45                 // Field args:Ledu/psu/sagnik/research/inkscapesvgprocessing/transformparser/model/SkewXOpArg;
      10: aload_0
      11: invokespecial #114                // Method java/lang/Object."<init>":()V
      14: aload_0
      15: invokestatic  #120                // Method scala/Product$class.$init$:(Lscala/Product;)V
      18: return
}
