Compiled from "CapacityProviderStrategyItem.java"
final class software.amazon.awssdk.services.eventbridge.model.CapacityProviderStrategyItem$BuilderImpl implements software.amazon.awssdk.services.eventbridge.model.CapacityProviderStrategyItem$Builder {
  private java.lang.String capacityProvider;

  private java.lang.Integer weight;

  private java.lang.Integer base;

  private software.amazon.awssdk.services.eventbridge.model.CapacityProviderStrategyItem$BuilderImpl();
    Code:
       0: aload_0
       1: invokespecial #6                  // Method java/lang/Object."<init>":()V
       4: return

  private software.amazon.awssdk.services.eventbridge.model.CapacityProviderStrategyItem$BuilderImpl(software.amazon.awssdk.services.eventbridge.model.CapacityProviderStrategyItem);
    Code:
       0: aload_0
       1: invokespecial #6                  // Method java/lang/Object."<init>":()V
       4: aload_0
       5: aload_1
       6: invokestatic  #7                  // Method software/amazon/awssdk/services/eventbridge/model/CapacityProviderStrategyItem.access$500:(Lsoftware/amazon/awssdk/services/eventbridge/model/CapacityProviderStrategyItem;)Ljava/lang/String;
       9: invokevirtual #8                  // Method capacityProvider:(Ljava/lang/String;)Lsoftware/amazon/awssdk/services/eventbridge/model/CapacityProviderStrategyItem$Builder;
      12: pop
      13: aload_0
      14: aload_1
      15: invokestatic  #9                  // Method software/amazon/awssdk/services/eventbridge/model/CapacityProviderStrategyItem.access$600:(Lsoftware/amazon/awssdk/services/eventbridge/model/CapacityProviderStrategyItem;)Ljava/lang/Integer;
      18: invokevirtual #10                 // Method weight:(Ljava/lang/Integer;)Lsoftware/amazon/awssdk/services/eventbridge/model/CapacityProviderStrategyItem$Builder;
      21: pop
      22: aload_0
      23: aload_1
      24: invokestatic  #11                 // Method software/amazon/awssdk/services/eventbridge/model/CapacityProviderStrategyItem.access$700:(Lsoftware/amazon/awssdk/services/eventbridge/model/CapacityProviderStrategyItem;)Ljava/lang/Integer;
      27: invokevirtual #12                 // Method base:(Ljava/lang/Integer;)Lsoftware/amazon/awssdk/services/eventbridge/model/CapacityProviderStrategyItem$Builder;
      30: pop
      31: return

  public final java.lang.String getCapacityProvider();
    Code:
       0: aload_0
       1: getfield      #5                  // Field capacityProvider:Ljava/lang/String;
       4: areturn

  public final void setCapacityProvider(java.lang.String);
    Code:
       0: aload_0
       1: aload_1
       2: putfield      #5                  // Field capacityProvider:Ljava/lang/String;
       5: return

  public final software.amazon.awssdk.services.eventbridge.model.CapacityProviderStrategyItem$Builder capacityProvider(java.lang.String);
    Code:
       0: aload_0
       1: aload_1
       2: putfield      #5                  // Field capacityProvider:Ljava/lang/String;
       5: aload_0
       6: areturn

  public final java.lang.Integer getWeight();
    Code:
       0: aload_0
       1: getfield      #4                  // Field weight:Ljava/lang/Integer;
       4: areturn

  public final void setWeight(java.lang.Integer);
    Code:
       0: aload_0
       1: aload_1
       2: putfield      #4                  // Field weight:Ljava/lang/Integer;
       5: return

  public final software.amazon.awssdk.services.eventbridge.model.CapacityProviderStrategyItem$Builder weight(java.lang.Integer);
    Code:
       0: aload_0
       1: aload_1
       2: putfield      #4                  // Field weight:Ljava/lang/Integer;
       5: aload_0
       6: areturn

  public final java.lang.Integer getBase();
    Code:
       0: aload_0
       1: getfield      #3                  // Field base:Ljava/lang/Integer;
       4: areturn

  public final void setBase(java.lang.Integer);
    Code:
       0: aload_0
       1: aload_1
       2: putfield      #3                  // Field base:Ljava/lang/Integer;
       5: return

  public final software.amazon.awssdk.services.eventbridge.model.CapacityProviderStrategyItem$Builder base(java.lang.Integer);
    Code:
       0: aload_0
       1: aload_1
       2: putfield      #3                  // Field base:Ljava/lang/Integer;
       5: aload_0
       6: areturn

  public software.amazon.awssdk.services.eventbridge.model.CapacityProviderStrategyItem build();
    Code:
       0: new           #13                 // class software/amazon/awssdk/services/eventbridge/model/CapacityProviderStrategyItem
       3: dup
       4: aload_0
       5: aconst_null
       6: invokespecial #14                 // Method software/amazon/awssdk/services/eventbridge/model/CapacityProviderStrategyItem."<init>":(Lsoftware/amazon/awssdk/services/eventbridge/model/CapacityProviderStrategyItem$BuilderImpl;Lsoftware/amazon/awssdk/services/eventbridge/model/CapacityProviderStrategyItem$1;)V
       9: areturn

  public java.util.List<software.amazon.awssdk.core.SdkField<?>> sdkFields();
    Code:
       0: invokestatic  #15                 // Method software/amazon/awssdk/services/eventbridge/model/CapacityProviderStrategyItem.access$900:()Ljava/util/List;
       3: areturn

  public java.lang.Object build();
    Code:
       0: aload_0
       1: invokevirtual #16                 // Method build:()Lsoftware/amazon/awssdk/services/eventbridge/model/CapacityProviderStrategyItem;
       4: areturn

  static java.lang.String access$000(software.amazon.awssdk.services.eventbridge.model.CapacityProviderStrategyItem$BuilderImpl);
    Code:
       0: aload_0
       1: getfield      #5                  // Field capacityProvider:Ljava/lang/String;
       4: areturn

  static java.lang.Integer access$100(software.amazon.awssdk.services.eventbridge.model.CapacityProviderStrategyItem$BuilderImpl);
    Code:
       0: aload_0
       1: getfield      #4                  // Field weight:Ljava/lang/Integer;
       4: areturn

  static java.lang.Integer access$200(software.amazon.awssdk.services.eventbridge.model.CapacityProviderStrategyItem$BuilderImpl);
    Code:
       0: aload_0
       1: getfield      #3                  // Field base:Ljava/lang/Integer;
       4: areturn

  software.amazon.awssdk.services.eventbridge.model.CapacityProviderStrategyItem$BuilderImpl(software.amazon.awssdk.services.eventbridge.model.CapacityProviderStrategyItem, software.amazon.awssdk.services.eventbridge.model.CapacityProviderStrategyItem$1);
    Code:
       0: aload_0
       1: aload_1
       2: invokespecial #2                  // Method "<init>":(Lsoftware/amazon/awssdk/services/eventbridge/model/CapacityProviderStrategyItem;)V
       5: return

  software.amazon.awssdk.services.eventbridge.model.CapacityProviderStrategyItem$BuilderImpl(software.amazon.awssdk.services.eventbridge.model.CapacityProviderStrategyItem$1);
    Code:
       0: aload_0
       1: invokespecial #1                  // Method "<init>":()V
       4: return
}
