Compiled from "DescribeConnectionResponse.java"
public interface software.amazon.awssdk.services.eventbridge.model.DescribeConnectionResponse$Builder extends software.amazon.awssdk.services.eventbridge.model.EventBridgeResponse$Builder, software.amazon.awssdk.core.SdkPojo, software.amazon.awssdk.utils.builder.CopyableBuilder<software.amazon.awssdk.services.eventbridge.model.DescribeConnectionResponse$Builder, software.amazon.awssdk.services.eventbridge.model.DescribeConnectionResponse> {
  public abstract software.amazon.awssdk.services.eventbridge.model.DescribeConnectionResponse$Builder connectionArn(java.lang.String);

  public abstract software.amazon.awssdk.services.eventbridge.model.DescribeConnectionResponse$Builder name(java.lang.String);

  public abstract software.amazon.awssdk.services.eventbridge.model.DescribeConnectionResponse$Builder description(java.lang.String);

  public abstract software.amazon.awssdk.services.eventbridge.model.DescribeConnectionResponse$Builder connectionState(java.lang.String);

  public abstract software.amazon.awssdk.services.eventbridge.model.DescribeConnectionResponse$Builder connectionState(software.amazon.awssdk.services.eventbridge.model.ConnectionState);

  public abstract software.amazon.awssdk.services.eventbridge.model.DescribeConnectionResponse$Builder stateReason(java.lang.String);

  public abstract software.amazon.awssdk.services.eventbridge.model.DescribeConnectionResponse$Builder authorizationType(java.lang.String);

  public abstract software.amazon.awssdk.services.eventbridge.model.DescribeConnectionResponse$Builder authorizationType(software.amazon.awssdk.services.eventbridge.model.ConnectionAuthorizationType);

  public abstract software.amazon.awssdk.services.eventbridge.model.DescribeConnectionResponse$Builder secretArn(java.lang.String);

  public abstract software.amazon.awssdk.services.eventbridge.model.DescribeConnectionResponse$Builder authParameters(software.amazon.awssdk.services.eventbridge.model.ConnectionAuthResponseParameters);

  public default software.amazon.awssdk.services.eventbridge.model.DescribeConnectionResponse$Builder authParameters(java.util.function.Consumer<software.amazon.awssdk.services.eventbridge.model.ConnectionAuthResponseParameters$Builder>);
    Code:
       0: aload_0
       1: invokestatic  #1                  // Method software/amazon/awssdk/services/eventbridge/model/ConnectionAuthResponseParameters.builder:()Lsoftware/amazon/awssdk/services/eventbridge/model/ConnectionAuthResponseParameters$Builder;
       4: aload_1
       5: invokeinterface #2,  2            // InterfaceMethod software/amazon/awssdk/services/eventbridge/model/ConnectionAuthResponseParameters$Builder.applyMutation:(Ljava/util/function/Consumer;)Lsoftware/amazon/awssdk/utils/builder/SdkBuilder;
      10: checkcast     #3                  // class software/amazon/awssdk/services/eventbridge/model/ConnectionAuthResponseParameters$Builder
      13: invokeinterface #4,  1            // InterfaceMethod software/amazon/awssdk/services/eventbridge/model/ConnectionAuthResponseParameters$Builder.build:()Ljava/lang/Object;
      18: checkcast     #5                  // class software/amazon/awssdk/services/eventbridge/model/ConnectionAuthResponseParameters
      21: invokeinterface #6,  2            // InterfaceMethod authParameters:(Lsoftware/amazon/awssdk/services/eventbridge/model/ConnectionAuthResponseParameters;)Lsoftware/amazon/awssdk/services/eventbridge/model/DescribeConnectionResponse$Builder;
      26: areturn

  public abstract software.amazon.awssdk.services.eventbridge.model.DescribeConnectionResponse$Builder creationTime(java.time.Instant);

  public abstract software.amazon.awssdk.services.eventbridge.model.DescribeConnectionResponse$Builder lastModifiedTime(java.time.Instant);

  public abstract software.amazon.awssdk.services.eventbridge.model.DescribeConnectionResponse$Builder lastAuthorizedTime(java.time.Instant);
}
