Compiled from "GrpcStatusFilter.java"
public final class io.grpc.xds.shaded.io.envoyproxy.envoy.config.accesslog.v3.GrpcStatusFilter$Status extends java.lang.Enum<io.grpc.xds.shaded.io.envoyproxy.envoy.config.accesslog.v3.GrpcStatusFilter$Status> implements com.google.protobuf.ProtocolMessageEnum {
  public static final io.grpc.xds.shaded.io.envoyproxy.envoy.config.accesslog.v3.GrpcStatusFilter$Status OK;

  public static final io.grpc.xds.shaded.io.envoyproxy.envoy.config.accesslog.v3.GrpcStatusFilter$Status CANCELED;

  public static final io.grpc.xds.shaded.io.envoyproxy.envoy.config.accesslog.v3.GrpcStatusFilter$Status UNKNOWN;

  public static final io.grpc.xds.shaded.io.envoyproxy.envoy.config.accesslog.v3.GrpcStatusFilter$Status INVALID_ARGUMENT;

  public static final io.grpc.xds.shaded.io.envoyproxy.envoy.config.accesslog.v3.GrpcStatusFilter$Status DEADLINE_EXCEEDED;

  public static final io.grpc.xds.shaded.io.envoyproxy.envoy.config.accesslog.v3.GrpcStatusFilter$Status NOT_FOUND;

  public static final io.grpc.xds.shaded.io.envoyproxy.envoy.config.accesslog.v3.GrpcStatusFilter$Status ALREADY_EXISTS;

  public static final io.grpc.xds.shaded.io.envoyproxy.envoy.config.accesslog.v3.GrpcStatusFilter$Status PERMISSION_DENIED;

  public static final io.grpc.xds.shaded.io.envoyproxy.envoy.config.accesslog.v3.GrpcStatusFilter$Status RESOURCE_EXHAUSTED;

  public static final io.grpc.xds.shaded.io.envoyproxy.envoy.config.accesslog.v3.GrpcStatusFilter$Status FAILED_PRECONDITION;

  public static final io.grpc.xds.shaded.io.envoyproxy.envoy.config.accesslog.v3.GrpcStatusFilter$Status ABORTED;

  public static final io.grpc.xds.shaded.io.envoyproxy.envoy.config.accesslog.v3.GrpcStatusFilter$Status OUT_OF_RANGE;

  public static final io.grpc.xds.shaded.io.envoyproxy.envoy.config.accesslog.v3.GrpcStatusFilter$Status UNIMPLEMENTED;

  public static final io.grpc.xds.shaded.io.envoyproxy.envoy.config.accesslog.v3.GrpcStatusFilter$Status INTERNAL;

  public static final io.grpc.xds.shaded.io.envoyproxy.envoy.config.accesslog.v3.GrpcStatusFilter$Status UNAVAILABLE;

  public static final io.grpc.xds.shaded.io.envoyproxy.envoy.config.accesslog.v3.GrpcStatusFilter$Status DATA_LOSS;

  public static final io.grpc.xds.shaded.io.envoyproxy.envoy.config.accesslog.v3.GrpcStatusFilter$Status UNAUTHENTICATED;

  public static final io.grpc.xds.shaded.io.envoyproxy.envoy.config.accesslog.v3.GrpcStatusFilter$Status UNRECOGNIZED;

  public static final int OK_VALUE;

  public static final int CANCELED_VALUE;

  public static final int UNKNOWN_VALUE;

  public static final int INVALID_ARGUMENT_VALUE;

  public static final int DEADLINE_EXCEEDED_VALUE;

  public static final int NOT_FOUND_VALUE;

  public static final int ALREADY_EXISTS_VALUE;

  public static final int PERMISSION_DENIED_VALUE;

  public static final int RESOURCE_EXHAUSTED_VALUE;

  public static final int FAILED_PRECONDITION_VALUE;

  public static final int ABORTED_VALUE;

  public static final int OUT_OF_RANGE_VALUE;

  public static final int UNIMPLEMENTED_VALUE;

  public static final int INTERNAL_VALUE;

  public static final int UNAVAILABLE_VALUE;

  public static final int DATA_LOSS_VALUE;

  public static final int UNAUTHENTICATED_VALUE;

  private static final com.google.protobuf.Internal$EnumLiteMap<io.grpc.xds.shaded.io.envoyproxy.envoy.config.accesslog.v3.GrpcStatusFilter$Status> internalValueMap;

  private static final io.grpc.xds.shaded.io.envoyproxy.envoy.config.accesslog.v3.GrpcStatusFilter$Status[] VALUES;

  private final int value;

  private static final io.grpc.xds.shaded.io.envoyproxy.envoy.config.accesslog.v3.GrpcStatusFilter$Status[] $VALUES;

  public static io.grpc.xds.shaded.io.envoyproxy.envoy.config.accesslog.v3.GrpcStatusFilter$Status[] values();
    Code:
       0: getstatic     #94                 // Field $VALUES:[Lio/grpc/xds/shaded/io/envoyproxy/envoy/config/accesslog/v3/GrpcStatusFilter$Status;
       3: invokevirtual #99                 // Method "[Lio/grpc/xds/shaded/io/envoyproxy/envoy/config/accesslog/v3/GrpcStatusFilter$Status;".clone:()Ljava/lang/Object;
       6: checkcast     #95                 // class "[Lio/grpc/xds/shaded/io/envoyproxy/envoy/config/accesslog/v3/GrpcStatusFilter$Status;"
       9: areturn

  public static io.grpc.xds.shaded.io.envoyproxy.envoy.config.accesslog.v3.GrpcStatusFilter$Status valueOf(java.lang.String);
    Code:
       0: ldc           #2                  // class io/grpc/xds/shaded/io/envoyproxy/envoy/config/accesslog/v3/GrpcStatusFilter$Status
       2: aload_0
       3: invokestatic  #104                // Method java/lang/Enum.valueOf:(Ljava/lang/Class;Ljava/lang/String;)Ljava/lang/Enum;
       6: checkcast     #2                  // class io/grpc/xds/shaded/io/envoyproxy/envoy/config/accesslog/v3/GrpcStatusFilter$Status
       9: areturn

  public final int getNumber();
    Code:
       0: aload_0
       1: getstatic     #110                // Field UNRECOGNIZED:Lio/grpc/xds/shaded/io/envoyproxy/envoy/config/accesslog/v3/GrpcStatusFilter$Status;
       4: if_acmpne     17
       7: new           #112                // class java/lang/IllegalArgumentException
      10: dup
      11: ldc           #114                // String Can\'t get the number of an unknown enum value.
      13: invokespecial #118                // Method java/lang/IllegalArgumentException."<init>":(Ljava/lang/String;)V
      16: athrow
      17: aload_0
      18: getfield      #120                // Field value:I
      21: ireturn

  public static io.grpc.xds.shaded.io.envoyproxy.envoy.config.accesslog.v3.GrpcStatusFilter$Status valueOf(int);
    Code:
       0: iload_0
       1: invokestatic  #126                // Method forNumber:(I)Lio/grpc/xds/shaded/io/envoyproxy/envoy/config/accesslog/v3/GrpcStatusFilter$Status;
       4: areturn

  public static io.grpc.xds.shaded.io.envoyproxy.envoy.config.accesslog.v3.GrpcStatusFilter$Status forNumber(int);
    Code:
       0: iload_0
       1: tableswitch   { // 0 to 16
                     0: 84
                     1: 88
                     2: 92
                     3: 96
                     4: 100
                     5: 104
                     6: 108
                     7: 112
                     8: 116
                     9: 120
                    10: 124
                    11: 128
                    12: 132
                    13: 136
                    14: 140
                    15: 144
                    16: 148
               default: 152
          }
      84: getstatic     #128                // Field OK:Lio/grpc/xds/shaded/io/envoyproxy/envoy/config/accesslog/v3/GrpcStatusFilter$Status;
      87: areturn
      88: getstatic     #130                // Field CANCELED:Lio/grpc/xds/shaded/io/envoyproxy/envoy/config/accesslog/v3/GrpcStatusFilter$Status;
      91: areturn
      92: getstatic     #132                // Field UNKNOWN:Lio/grpc/xds/shaded/io/envoyproxy/envoy/config/accesslog/v3/GrpcStatusFilter$Status;
      95: areturn
      96: getstatic     #134                // Field INVALID_ARGUMENT:Lio/grpc/xds/shaded/io/envoyproxy/envoy/config/accesslog/v3/GrpcStatusFilter$Status;
      99: areturn
     100: getstatic     #136                // Field DEADLINE_EXCEEDED:Lio/grpc/xds/shaded/io/envoyproxy/envoy/config/accesslog/v3/GrpcStatusFilter$Status;
     103: areturn
     104: getstatic     #138                // Field NOT_FOUND:Lio/grpc/xds/shaded/io/envoyproxy/envoy/config/accesslog/v3/GrpcStatusFilter$Status;
     107: areturn
     108: getstatic     #140                // Field ALREADY_EXISTS:Lio/grpc/xds/shaded/io/envoyproxy/envoy/config/accesslog/v3/GrpcStatusFilter$Status;
     111: areturn
     112: getstatic     #142                // Field PERMISSION_DENIED:Lio/grpc/xds/shaded/io/envoyproxy/envoy/config/accesslog/v3/GrpcStatusFilter$Status;
     115: areturn
     116: getstatic     #144                // Field RESOURCE_EXHAUSTED:Lio/grpc/xds/shaded/io/envoyproxy/envoy/config/accesslog/v3/GrpcStatusFilter$Status;
     119: areturn
     120: getstatic     #146                // Field FAILED_PRECONDITION:Lio/grpc/xds/shaded/io/envoyproxy/envoy/config/accesslog/v3/GrpcStatusFilter$Status;
     123: areturn
     124: getstatic     #148                // Field ABORTED:Lio/grpc/xds/shaded/io/envoyproxy/envoy/config/accesslog/v3/GrpcStatusFilter$Status;
     127: areturn
     128: getstatic     #150                // Field OUT_OF_RANGE:Lio/grpc/xds/shaded/io/envoyproxy/envoy/config/accesslog/v3/GrpcStatusFilter$Status;
     131: areturn
     132: getstatic     #152                // Field UNIMPLEMENTED:Lio/grpc/xds/shaded/io/envoyproxy/envoy/config/accesslog/v3/GrpcStatusFilter$Status;
     135: areturn
     136: getstatic     #154                // Field INTERNAL:Lio/grpc/xds/shaded/io/envoyproxy/envoy/config/accesslog/v3/GrpcStatusFilter$Status;
     139: areturn
     140: getstatic     #156                // Field UNAVAILABLE:Lio/grpc/xds/shaded/io/envoyproxy/envoy/config/accesslog/v3/GrpcStatusFilter$Status;
     143: areturn
     144: getstatic     #158                // Field DATA_LOSS:Lio/grpc/xds/shaded/io/envoyproxy/envoy/config/accesslog/v3/GrpcStatusFilter$Status;
     147: areturn
     148: getstatic     #160                // Field UNAUTHENTICATED:Lio/grpc/xds/shaded/io/envoyproxy/envoy/config/accesslog/v3/GrpcStatusFilter$Status;
     151: areturn
     152: aconst_null
     153: areturn

  public static com.google.protobuf.Internal$EnumLiteMap<io.grpc.xds.shaded.io.envoyproxy.envoy.config.accesslog.v3.GrpcStatusFilter$Status> internalGetValueMap();
    Code:
       0: getstatic     #165                // Field internalValueMap:Lcom/google/protobuf/Internal$EnumLiteMap;
       3: areturn

  public final com.google.protobuf.Descriptors$EnumValueDescriptor getValueDescriptor();
    Code:
       0: aload_0
       1: getstatic     #110                // Field UNRECOGNIZED:Lio/grpc/xds/shaded/io/envoyproxy/envoy/config/accesslog/v3/GrpcStatusFilter$Status;
       4: if_acmpne     17
       7: new           #169                // class java/lang/IllegalStateException
      10: dup
      11: ldc           #171                // String Can\'t get the descriptor of an unrecognized enum value.
      13: invokespecial #172                // Method java/lang/IllegalStateException."<init>":(Ljava/lang/String;)V
      16: athrow
      17: invokestatic  #176                // Method getDescriptor:()Lcom/google/protobuf/Descriptors$EnumDescriptor;
      20: invokevirtual #180                // Method com/google/protobuf/Descriptors$EnumDescriptor.getValues:()Ljava/util/List;
      23: aload_0
      24: invokevirtual #183                // Method ordinal:()I
      27: invokeinterface #189,  2          // InterfaceMethod java/util/List.get:(I)Ljava/lang/Object;
      32: checkcast     #20                 // class com/google/protobuf/Descriptors$EnumValueDescriptor
      35: areturn

  public final com.google.protobuf.Descriptors$EnumDescriptor getDescriptorForType();
    Code:
       0: invokestatic  #176                // Method getDescriptor:()Lcom/google/protobuf/Descriptors$EnumDescriptor;
       3: areturn

  public static final com.google.protobuf.Descriptors$EnumDescriptor getDescriptor();
    Code:
       0: invokestatic  #193                // Method io/grpc/xds/shaded/io/envoyproxy/envoy/config/accesslog/v3/GrpcStatusFilter.getDescriptor:()Lcom/google/protobuf/Descriptors$Descriptor;
       3: invokevirtual #196                // Method com/google/protobuf/Descriptors$Descriptor.getEnumTypes:()Ljava/util/List;
       6: iconst_0
       7: invokeinterface #189,  2          // InterfaceMethod java/util/List.get:(I)Ljava/lang/Object;
      12: checkcast     #25                 // class com/google/protobuf/Descriptors$EnumDescriptor
      15: areturn

  public static io.grpc.xds.shaded.io.envoyproxy.envoy.config.accesslog.v3.GrpcStatusFilter$Status valueOf(com.google.protobuf.Descriptors$EnumValueDescriptor);
    Code:
       0: aload_0
       1: invokevirtual #200                // Method com/google/protobuf/Descriptors$EnumValueDescriptor.getType:()Lcom/google/protobuf/Descriptors$EnumDescriptor;
       4: invokestatic  #176                // Method getDescriptor:()Lcom/google/protobuf/Descriptors$EnumDescriptor;
       7: if_acmpeq     20
      10: new           #112                // class java/lang/IllegalArgumentException
      13: dup
      14: ldc           #202                // String EnumValueDescriptor is not for this type.
      16: invokespecial #118                // Method java/lang/IllegalArgumentException."<init>":(Ljava/lang/String;)V
      19: athrow
      20: aload_0
      21: invokevirtual #205                // Method com/google/protobuf/Descriptors$EnumValueDescriptor.getIndex:()I
      24: iconst_m1
      25: if_icmpne     32
      28: getstatic     #110                // Field UNRECOGNIZED:Lio/grpc/xds/shaded/io/envoyproxy/envoy/config/accesslog/v3/GrpcStatusFilter$Status;
      31: areturn
      32: getstatic     #207                // Field VALUES:[Lio/grpc/xds/shaded/io/envoyproxy/envoy/config/accesslog/v3/GrpcStatusFilter$Status;
      35: aload_0
      36: invokevirtual #205                // Method com/google/protobuf/Descriptors$EnumValueDescriptor.getIndex:()I
      39: aaload
      40: areturn

  private io.grpc.xds.shaded.io.envoyproxy.envoy.config.accesslog.v3.GrpcStatusFilter$Status(int);
    Code:
       0: aload_0
       1: aload_1
       2: iload_2
       3: invokespecial #214                // Method java/lang/Enum."<init>":(Ljava/lang/String;I)V
       6: aload_0
       7: iload_3
       8: putfield      #120                // Field value:I
      11: return

  static {};
    Code:
       0: new           #2                  // class io/grpc/xds/shaded/io/envoyproxy/envoy/config/accesslog/v3/GrpcStatusFilter$Status
       3: dup
       4: ldc           #217                // String OK
       6: iconst_0
       7: iconst_0
       8: invokespecial #219                // Method "<init>":(Ljava/lang/String;II)V
      11: putstatic     #128                // Field OK:Lio/grpc/xds/shaded/io/envoyproxy/envoy/config/accesslog/v3/GrpcStatusFilter$Status;
      14: new           #2                  // class io/grpc/xds/shaded/io/envoyproxy/envoy/config/accesslog/v3/GrpcStatusFilter$Status
      17: dup
      18: ldc           #220                // String CANCELED
      20: iconst_1
      21: iconst_1
      22: invokespecial #219                // Method "<init>":(Ljava/lang/String;II)V
      25: putstatic     #130                // Field CANCELED:Lio/grpc/xds/shaded/io/envoyproxy/envoy/config/accesslog/v3/GrpcStatusFilter$Status;
      28: new           #2                  // class io/grpc/xds/shaded/io/envoyproxy/envoy/config/accesslog/v3/GrpcStatusFilter$Status
      31: dup
      32: ldc           #221                // String UNKNOWN
      34: iconst_2
      35: iconst_2
      36: invokespecial #219                // Method "<init>":(Ljava/lang/String;II)V
      39: putstatic     #132                // Field UNKNOWN:Lio/grpc/xds/shaded/io/envoyproxy/envoy/config/accesslog/v3/GrpcStatusFilter$Status;
      42: new           #2                  // class io/grpc/xds/shaded/io/envoyproxy/envoy/config/accesslog/v3/GrpcStatusFilter$Status
      45: dup
      46: ldc           #222                // String INVALID_ARGUMENT
      48: iconst_3
      49: iconst_3
      50: invokespecial #219                // Method "<init>":(Ljava/lang/String;II)V
      53: putstatic     #134                // Field INVALID_ARGUMENT:Lio/grpc/xds/shaded/io/envoyproxy/envoy/config/accesslog/v3/GrpcStatusFilter$Status;
      56: new           #2                  // class io/grpc/xds/shaded/io/envoyproxy/envoy/config/accesslog/v3/GrpcStatusFilter$Status
      59: dup
      60: ldc           #223                // String DEADLINE_EXCEEDED
      62: iconst_4
      63: iconst_4
      64: invokespecial #219                // Method "<init>":(Ljava/lang/String;II)V
      67: putstatic     #136                // Field DEADLINE_EXCEEDED:Lio/grpc/xds/shaded/io/envoyproxy/envoy/config/accesslog/v3/GrpcStatusFilter$Status;
      70: new           #2                  // class io/grpc/xds/shaded/io/envoyproxy/envoy/config/accesslog/v3/GrpcStatusFilter$Status
      73: dup
      74: ldc           #224                // String NOT_FOUND
      76: iconst_5
      77: iconst_5
      78: invokespecial #219                // Method "<init>":(Ljava/lang/String;II)V
      81: putstatic     #138                // Field NOT_FOUND:Lio/grpc/xds/shaded/io/envoyproxy/envoy/config/accesslog/v3/GrpcStatusFilter$Status;
      84: new           #2                  // class io/grpc/xds/shaded/io/envoyproxy/envoy/config/accesslog/v3/GrpcStatusFilter$Status
      87: dup
      88: ldc           #225                // String ALREADY_EXISTS
      90: bipush        6
      92: bipush        6
      94: invokespecial #219                // Method "<init>":(Ljava/lang/String;II)V
      97: putstatic     #140                // Field ALREADY_EXISTS:Lio/grpc/xds/shaded/io/envoyproxy/envoy/config/accesslog/v3/GrpcStatusFilter$Status;
     100: new           #2                  // class io/grpc/xds/shaded/io/envoyproxy/envoy/config/accesslog/v3/GrpcStatusFilter$Status
     103: dup
     104: ldc           #226                // String PERMISSION_DENIED
     106: bipush        7
     108: bipush        7
     110: invokespecial #219                // Method "<init>":(Ljava/lang/String;II)V
     113: putstatic     #142                // Field PERMISSION_DENIED:Lio/grpc/xds/shaded/io/envoyproxy/envoy/config/accesslog/v3/GrpcStatusFilter$Status;
     116: new           #2                  // class io/grpc/xds/shaded/io/envoyproxy/envoy/config/accesslog/v3/GrpcStatusFilter$Status
     119: dup
     120: ldc           #227                // String RESOURCE_EXHAUSTED
     122: bipush        8
     124: bipush        8
     126: invokespecial #219                // Method "<init>":(Ljava/lang/String;II)V
     129: putstatic     #144                // Field RESOURCE_EXHAUSTED:Lio/grpc/xds/shaded/io/envoyproxy/envoy/config/accesslog/v3/GrpcStatusFilter$Status;
     132: new           #2                  // class io/grpc/xds/shaded/io/envoyproxy/envoy/config/accesslog/v3/GrpcStatusFilter$Status
     135: dup
     136: ldc           #228                // String FAILED_PRECONDITION
     138: bipush        9
     140: bipush        9
     142: invokespecial #219                // Method "<init>":(Ljava/lang/String;II)V
     145: putstatic     #146                // Field FAILED_PRECONDITION:Lio/grpc/xds/shaded/io/envoyproxy/envoy/config/accesslog/v3/GrpcStatusFilter$Status;
     148: new           #2                  // class io/grpc/xds/shaded/io/envoyproxy/envoy/config/accesslog/v3/GrpcStatusFilter$Status
     151: dup
     152: ldc           #229                // String ABORTED
     154: bipush        10
     156: bipush        10
     158: invokespecial #219                // Method "<init>":(Ljava/lang/String;II)V
     161: putstatic     #148                // Field ABORTED:Lio/grpc/xds/shaded/io/envoyproxy/envoy/config/accesslog/v3/GrpcStatusFilter$Status;
     164: new           #2                  // class io/grpc/xds/shaded/io/envoyproxy/envoy/config/accesslog/v3/GrpcStatusFilter$Status
     167: dup
     168: ldc           #230                // String OUT_OF_RANGE
     170: bipush        11
     172: bipush        11
     174: invokespecial #219                // Method "<init>":(Ljava/lang/String;II)V
     177: putstatic     #150                // Field OUT_OF_RANGE:Lio/grpc/xds/shaded/io/envoyproxy/envoy/config/accesslog/v3/GrpcStatusFilter$Status;
     180: new           #2                  // class io/grpc/xds/shaded/io/envoyproxy/envoy/config/accesslog/v3/GrpcStatusFilter$Status
     183: dup
     184: ldc           #231                // String UNIMPLEMENTED
     186: bipush        12
     188: bipush        12
     190: invokespecial #219                // Method "<init>":(Ljava/lang/String;II)V
     193: putstatic     #152                // Field UNIMPLEMENTED:Lio/grpc/xds/shaded/io/envoyproxy/envoy/config/accesslog/v3/GrpcStatusFilter$Status;
     196: new           #2                  // class io/grpc/xds/shaded/io/envoyproxy/envoy/config/accesslog/v3/GrpcStatusFilter$Status
     199: dup
     200: ldc           #232                // String INTERNAL
     202: bipush        13
     204: bipush        13
     206: invokespecial #219                // Method "<init>":(Ljava/lang/String;II)V
     209: putstatic     #154                // Field INTERNAL:Lio/grpc/xds/shaded/io/envoyproxy/envoy/config/accesslog/v3/GrpcStatusFilter$Status;
     212: new           #2                  // class io/grpc/xds/shaded/io/envoyproxy/envoy/config/accesslog/v3/GrpcStatusFilter$Status
     215: dup
     216: ldc           #233                // String UNAVAILABLE
     218: bipush        14
     220: bipush        14
     222: invokespecial #219                // Method "<init>":(Ljava/lang/String;II)V
     225: putstatic     #156                // Field UNAVAILABLE:Lio/grpc/xds/shaded/io/envoyproxy/envoy/config/accesslog/v3/GrpcStatusFilter$Status;
     228: new           #2                  // class io/grpc/xds/shaded/io/envoyproxy/envoy/config/accesslog/v3/GrpcStatusFilter$Status
     231: dup
     232: ldc           #234                // String DATA_LOSS
     234: bipush        15
     236: bipush        15
     238: invokespecial #219                // Method "<init>":(Ljava/lang/String;II)V
     241: putstatic     #158                // Field DATA_LOSS:Lio/grpc/xds/shaded/io/envoyproxy/envoy/config/accesslog/v3/GrpcStatusFilter$Status;
     244: new           #2                  // class io/grpc/xds/shaded/io/envoyproxy/envoy/config/accesslog/v3/GrpcStatusFilter$Status
     247: dup
     248: ldc           #235                // String UNAUTHENTICATED
     250: bipush        16
     252: bipush        16
     254: invokespecial #219                // Method "<init>":(Ljava/lang/String;II)V
     257: putstatic     #160                // Field UNAUTHENTICATED:Lio/grpc/xds/shaded/io/envoyproxy/envoy/config/accesslog/v3/GrpcStatusFilter$Status;
     260: new           #2                  // class io/grpc/xds/shaded/io/envoyproxy/envoy/config/accesslog/v3/GrpcStatusFilter$Status
     263: dup
     264: ldc           #236                // String UNRECOGNIZED
     266: bipush        17
     268: iconst_m1
     269: invokespecial #219                // Method "<init>":(Ljava/lang/String;II)V
     272: putstatic     #110                // Field UNRECOGNIZED:Lio/grpc/xds/shaded/io/envoyproxy/envoy/config/accesslog/v3/GrpcStatusFilter$Status;
     275: bipush        18
     277: anewarray     #2                  // class io/grpc/xds/shaded/io/envoyproxy/envoy/config/accesslog/v3/GrpcStatusFilter$Status
     280: dup
     281: iconst_0
     282: getstatic     #128                // Field OK:Lio/grpc/xds/shaded/io/envoyproxy/envoy/config/accesslog/v3/GrpcStatusFilter$Status;
     285: aastore
     286: dup
     287: iconst_1
     288: getstatic     #130                // Field CANCELED:Lio/grpc/xds/shaded/io/envoyproxy/envoy/config/accesslog/v3/GrpcStatusFilter$Status;
     291: aastore
     292: dup
     293: iconst_2
     294: getstatic     #132                // Field UNKNOWN:Lio/grpc/xds/shaded/io/envoyproxy/envoy/config/accesslog/v3/GrpcStatusFilter$Status;
     297: aastore
     298: dup
     299: iconst_3
     300: getstatic     #134                // Field INVALID_ARGUMENT:Lio/grpc/xds/shaded/io/envoyproxy/envoy/config/accesslog/v3/GrpcStatusFilter$Status;
     303: aastore
     304: dup
     305: iconst_4
     306: getstatic     #136                // Field DEADLINE_EXCEEDED:Lio/grpc/xds/shaded/io/envoyproxy/envoy/config/accesslog/v3/GrpcStatusFilter$Status;
     309: aastore
     310: dup
     311: iconst_5
     312: getstatic     #138                // Field NOT_FOUND:Lio/grpc/xds/shaded/io/envoyproxy/envoy/config/accesslog/v3/GrpcStatusFilter$Status;
     315: aastore
     316: dup
     317: bipush        6
     319: getstatic     #140                // Field ALREADY_EXISTS:Lio/grpc/xds/shaded/io/envoyproxy/envoy/config/accesslog/v3/GrpcStatusFilter$Status;
     322: aastore
     323: dup
     324: bipush        7
     326: getstatic     #142                // Field PERMISSION_DENIED:Lio/grpc/xds/shaded/io/envoyproxy/envoy/config/accesslog/v3/GrpcStatusFilter$Status;
     329: aastore
     330: dup
     331: bipush        8
     333: getstatic     #144                // Field RESOURCE_EXHAUSTED:Lio/grpc/xds/shaded/io/envoyproxy/envoy/config/accesslog/v3/GrpcStatusFilter$Status;
     336: aastore
     337: dup
     338: bipush        9
     340: getstatic     #146                // Field FAILED_PRECONDITION:Lio/grpc/xds/shaded/io/envoyproxy/envoy/config/accesslog/v3/GrpcStatusFilter$Status;
     343: aastore
     344: dup
     345: bipush        10
     347: getstatic     #148                // Field ABORTED:Lio/grpc/xds/shaded/io/envoyproxy/envoy/config/accesslog/v3/GrpcStatusFilter$Status;
     350: aastore
     351: dup
     352: bipush        11
     354: getstatic     #150                // Field OUT_OF_RANGE:Lio/grpc/xds/shaded/io/envoyproxy/envoy/config/accesslog/v3/GrpcStatusFilter$Status;
     357: aastore
     358: dup
     359: bipush        12
     361: getstatic     #152                // Field UNIMPLEMENTED:Lio/grpc/xds/shaded/io/envoyproxy/envoy/config/accesslog/v3/GrpcStatusFilter$Status;
     364: aastore
     365: dup
     366: bipush        13
     368: getstatic     #154                // Field INTERNAL:Lio/grpc/xds/shaded/io/envoyproxy/envoy/config/accesslog/v3/GrpcStatusFilter$Status;
     371: aastore
     372: dup
     373: bipush        14
     375: getstatic     #156                // Field UNAVAILABLE:Lio/grpc/xds/shaded/io/envoyproxy/envoy/config/accesslog/v3/GrpcStatusFilter$Status;
     378: aastore
     379: dup
     380: bipush        15
     382: getstatic     #158                // Field DATA_LOSS:Lio/grpc/xds/shaded/io/envoyproxy/envoy/config/accesslog/v3/GrpcStatusFilter$Status;
     385: aastore
     386: dup
     387: bipush        16
     389: getstatic     #160                // Field UNAUTHENTICATED:Lio/grpc/xds/shaded/io/envoyproxy/envoy/config/accesslog/v3/GrpcStatusFilter$Status;
     392: aastore
     393: dup
     394: bipush        17
     396: getstatic     #110                // Field UNRECOGNIZED:Lio/grpc/xds/shaded/io/envoyproxy/envoy/config/accesslog/v3/GrpcStatusFilter$Status;
     399: aastore
     400: putstatic     #94                 // Field $VALUES:[Lio/grpc/xds/shaded/io/envoyproxy/envoy/config/accesslog/v3/GrpcStatusFilter$Status;
     403: new           #13                 // class io/grpc/xds/shaded/io/envoyproxy/envoy/config/accesslog/v3/GrpcStatusFilter$Status$1
     406: dup
     407: invokespecial #238                // Method io/grpc/xds/shaded/io/envoyproxy/envoy/config/accesslog/v3/GrpcStatusFilter$Status$1."<init>":()V
     410: putstatic     #165                // Field internalValueMap:Lcom/google/protobuf/Internal$EnumLiteMap;
     413: invokestatic  #240                // Method values:()[Lio/grpc/xds/shaded/io/envoyproxy/envoy/config/accesslog/v3/GrpcStatusFilter$Status;
     416: putstatic     #207                // Field VALUES:[Lio/grpc/xds/shaded/io/envoyproxy/envoy/config/accesslog/v3/GrpcStatusFilter$Status;
     419: return
}
