Compiled from "ErrorParser.java"
public class brave.ErrorParser {
  public static final brave.ErrorParser NOOP;

  public brave.ErrorParser();
    Code:
       0: aload_0
       1: invokespecial #13                 // Method java/lang/Object."<init>":()V
       4: return

  public final void error(java.lang.Throwable, brave.ScopedSpan);
    Code:
       0: aload_0
       1: aload_1
       2: aload_2
       3: invokevirtual #19                 // Method error:(Ljava/lang/Throwable;Ljava/lang/Object;)V
       6: return

  public final void error(java.lang.Throwable, brave.SpanCustomizer);
    Code:
       0: aload_0
       1: aload_1
       2: aload_2
       3: invokevirtual #19                 // Method error:(Ljava/lang/Throwable;Ljava/lang/Object;)V
       6: return

  public final void error(java.lang.Throwable, brave.handler.MutableSpan);
    Code:
       0: aload_0
       1: aload_1
       2: aload_2
       3: invokevirtual #19                 // Method error:(Ljava/lang/Throwable;Ljava/lang/Object;)V
       6: return

  protected void error(java.lang.Throwable, java.lang.Object);
    Code:
       0: aload_1
       1: invokevirtual #34                 // Method java/lang/Throwable.getMessage:()Ljava/lang/String;
       4: astore_3
       5: aload_3
       6: ifnonnull     17
       9: aload_1
      10: invokevirtual #38                 // Method java/lang/Object.getClass:()Ljava/lang/Class;
      13: invokevirtual #43                 // Method java/lang/Class.getSimpleName:()Ljava/lang/String;
      16: astore_3
      17: aload_0
      18: aload_2
      19: ldc           #46                 // String error
      21: aload_3
      22: invokevirtual #50                 // Method tag:(Ljava/lang/Object;Ljava/lang/String;Ljava/lang/String;)V
      25: return

  protected final void annotate(java.lang.Object, java.lang.String);
    Code:
       0: aload_1
       1: instanceof    #57                 // class brave/SpanCustomizer
       4: ifeq          21
       7: aload_1
       8: checkcast     #57                 // class brave/SpanCustomizer
      11: aload_2
      12: invokeinterface #60,  2           // InterfaceMethod brave/SpanCustomizer.annotate:(Ljava/lang/String;)Lbrave/SpanCustomizer;
      17: pop
      18: goto          37
      21: aload_1
      22: instanceof    #62                 // class brave/ScopedSpan
      25: ifeq          37
      28: aload_1
      29: checkcast     #62                 // class brave/ScopedSpan
      32: aload_2
      33: invokevirtual #65                 // Method brave/ScopedSpan.annotate:(Ljava/lang/String;)Lbrave/ScopedSpan;
      36: pop
      37: return

  protected final void tag(java.lang.Object, java.lang.String, java.lang.String);
    Code:
       0: aload_1
       1: instanceof    #57                 // class brave/SpanCustomizer
       4: ifeq          22
       7: aload_1
       8: checkcast     #57                 // class brave/SpanCustomizer
      11: aload_2
      12: aload_3
      13: invokeinterface #69,  3           // InterfaceMethod brave/SpanCustomizer.tag:(Ljava/lang/String;Ljava/lang/String;)Lbrave/SpanCustomizer;
      18: pop
      19: goto          58
      22: aload_1
      23: instanceof    #62                 // class brave/ScopedSpan
      26: ifeq          42
      29: aload_1
      30: checkcast     #62                 // class brave/ScopedSpan
      33: aload_2
      34: aload_3
      35: invokevirtual #72                 // Method brave/ScopedSpan.tag:(Ljava/lang/String;Ljava/lang/String;)Lbrave/ScopedSpan;
      38: pop
      39: goto          58
      42: aload_1
      43: instanceof    #74                 // class brave/handler/MutableSpan
      46: ifeq          58
      49: aload_1
      50: checkcast     #74                 // class brave/handler/MutableSpan
      53: aload_2
      54: aload_3
      55: invokevirtual #77                 // Method brave/handler/MutableSpan.tag:(Ljava/lang/String;Ljava/lang/String;)V
      58: return

  static {};
    Code:
       0: new           #7                  // class brave/ErrorParser$1
       3: dup
       4: invokespecial #80                 // Method brave/ErrorParser$1."<init>":()V
       7: putstatic     #82                 // Field NOOP:Lbrave/ErrorParser;
      10: return
}
