Compiled from "JSONLDWriter.java"
public class org.eclipse.rdf4j.rio.jsonld.JSONLDWriter extends org.eclipse.rdf4j.rio.helpers.AbstractRDFWriter implements org.eclipse.rdf4j.rio.RDFWriter {
  private final org.eclipse.rdf4j.model.Model model;

  private final org.eclipse.rdf4j.rio.helpers.StatementCollector statementCollector;

  private final java.lang.String baseURI;

  private final java.io.Writer writer;

  public org.eclipse.rdf4j.rio.jsonld.JSONLDWriter(java.io.OutputStream);
    Code:
       0: aload_0
       1: aload_1
       2: aconst_null
       3: invokespecial #1                  // Method "<init>":(Ljava/io/OutputStream;Ljava/lang/String;)V
       6: return

  public org.eclipse.rdf4j.rio.jsonld.JSONLDWriter(java.io.OutputStream, java.lang.String);
    Code:
       0: aload_0
       1: aload_1
       2: invokespecial #2                  // Method org/eclipse/rdf4j/rio/helpers/AbstractRDFWriter."<init>":(Ljava/io/OutputStream;)V
       5: aload_0
       6: new           #3                  // class org/eclipse/rdf4j/model/impl/LinkedHashModel
       9: dup
      10: invokespecial #4                  // Method org/eclipse/rdf4j/model/impl/LinkedHashModel."<init>":()V
      13: putfield      #5                  // Field model:Lorg/eclipse/rdf4j/model/Model;
      16: aload_0
      17: new           #6                  // class org/eclipse/rdf4j/rio/helpers/StatementCollector
      20: dup
      21: aload_0
      22: getfield      #5                  // Field model:Lorg/eclipse/rdf4j/model/Model;
      25: invokespecial #7                  // Method org/eclipse/rdf4j/rio/helpers/StatementCollector."<init>":(Ljava/util/Collection;)V
      28: putfield      #8                  // Field statementCollector:Lorg/eclipse/rdf4j/rio/helpers/StatementCollector;
      31: aload_0
      32: aload_2
      33: putfield      #9                  // Field baseURI:Ljava/lang/String;
      36: aload_0
      37: new           #10                 // class java/io/BufferedWriter
      40: dup
      41: new           #11                 // class java/io/OutputStreamWriter
      44: dup
      45: aload_1
      46: getstatic     #12                 // Field java/nio/charset/StandardCharsets.UTF_8:Ljava/nio/charset/Charset;
      49: invokespecial #13                 // Method java/io/OutputStreamWriter."<init>":(Ljava/io/OutputStream;Ljava/nio/charset/Charset;)V
      52: invokespecial #14                 // Method java/io/BufferedWriter."<init>":(Ljava/io/Writer;)V
      55: putfield      #15                 // Field writer:Ljava/io/Writer;
      58: return

  public org.eclipse.rdf4j.rio.jsonld.JSONLDWriter(java.io.Writer);
    Code:
       0: aload_0
       1: aload_1
       2: aconst_null
       3: invokespecial #16                 // Method "<init>":(Ljava/io/Writer;Ljava/lang/String;)V
       6: return

  public org.eclipse.rdf4j.rio.jsonld.JSONLDWriter(java.io.Writer, java.lang.String);
    Code:
       0: aload_0
       1: invokespecial #17                 // Method org/eclipse/rdf4j/rio/helpers/AbstractRDFWriter."<init>":()V
       4: aload_0
       5: new           #3                  // class org/eclipse/rdf4j/model/impl/LinkedHashModel
       8: dup
       9: invokespecial #4                  // Method org/eclipse/rdf4j/model/impl/LinkedHashModel."<init>":()V
      12: putfield      #5                  // Field model:Lorg/eclipse/rdf4j/model/Model;
      15: aload_0
      16: new           #6                  // class org/eclipse/rdf4j/rio/helpers/StatementCollector
      19: dup
      20: aload_0
      21: getfield      #5                  // Field model:Lorg/eclipse/rdf4j/model/Model;
      24: invokespecial #7                  // Method org/eclipse/rdf4j/rio/helpers/StatementCollector."<init>":(Ljava/util/Collection;)V
      27: putfield      #8                  // Field statementCollector:Lorg/eclipse/rdf4j/rio/helpers/StatementCollector;
      30: aload_0
      31: aload_2
      32: putfield      #9                  // Field baseURI:Ljava/lang/String;
      35: aload_0
      36: aload_1
      37: putfield      #15                 // Field writer:Ljava/io/Writer;
      40: return

  public void handleNamespace(java.lang.String, java.lang.String) throws org.eclipse.rdf4j.rio.RDFHandlerException;
    Code:
       0: aload_0
       1: invokevirtual #18                 // Method checkWritingStarted:()V
       4: aload_0
       5: getfield      #5                  // Field model:Lorg/eclipse/rdf4j/model/Model;
       8: aload_1
       9: aload_2
      10: invokeinterface #19,  3           // InterfaceMethod org/eclipse/rdf4j/model/Model.setNamespace:(Ljava/lang/String;Ljava/lang/String;)Lorg/eclipse/rdf4j/model/Namespace;
      15: pop
      16: return

  public void startRDF() throws org.eclipse.rdf4j.rio.RDFHandlerException;
    Code:
       0: aload_0
       1: invokespecial #20                 // Method org/eclipse/rdf4j/rio/helpers/AbstractRDFWriter.startRDF:()V
       4: aload_0
       5: getfield      #8                  // Field statementCollector:Lorg/eclipse/rdf4j/rio/helpers/StatementCollector;
       8: invokevirtual #21                 // Method org/eclipse/rdf4j/rio/helpers/StatementCollector.clear:()V
      11: aload_0
      12: getfield      #5                  // Field model:Lorg/eclipse/rdf4j/model/Model;
      15: invokeinterface #22,  1           // InterfaceMethod org/eclipse/rdf4j/model/Model.clear:()V
      20: return

  public void endRDF() throws org.eclipse.rdf4j.rio.RDFHandlerException;
    Code:
       0: aload_0
       1: invokevirtual #18                 // Method checkWritingStarted:()V
       4: new           #23                 // class org/eclipse/rdf4j/rio/jsonld/JSONLDInternalRDFParser
       7: dup
       8: invokespecial #24                 // Method org/eclipse/rdf4j/rio/jsonld/JSONLDInternalRDFParser."<init>":()V
      11: astore_1
      12: aload_0
      13: getfield      #5                  // Field model:Lorg/eclipse/rdf4j/model/Model;
      16: aload_1
      17: invokestatic  #25                 // Method com/github/jsonldjava/core/JsonLdProcessor.fromRDF:(Ljava/lang/Object;Lcom/github/jsonldjava/core/RDFParser;)Ljava/lang/Object;
      20: astore_2
      21: aload_0
      22: invokevirtual #26                 // Method getWriterConfig:()Lorg/eclipse/rdf4j/rio/WriterConfig;
      25: getstatic     #27                 // Field org/eclipse/rdf4j/rio/helpers/JSONLDSettings.JSONLD_MODE:Lorg/eclipse/rdf4j/rio/RioSetting;
      28: invokevirtual #28                 // Method org/eclipse/rdf4j/rio/WriterConfig.get:(Lorg/eclipse/rdf4j/rio/RioSetting;)Ljava/lang/Object;
      31: checkcast     #29                 // class org/eclipse/rdf4j/rio/helpers/JSONLDMode
      34: astore_3
      35: new           #30                 // class com/github/jsonldjava/core/JsonLdOptions
      38: dup
      39: invokespecial #31                 // Method com/github/jsonldjava/core/JsonLdOptions."<init>":()V
      42: astore        4
      44: aload_0
      45: invokevirtual #26                 // Method getWriterConfig:()Lorg/eclipse/rdf4j/rio/WriterConfig;
      48: astore        5
      50: aload         4
      52: aload         5
      54: getstatic     #32                 // Field org/eclipse/rdf4j/rio/helpers/JSONLDSettings.COMPACT_ARRAYS:Lorg/eclipse/rdf4j/rio/RioSetting;
      57: invokevirtual #28                 // Method org/eclipse/rdf4j/rio/WriterConfig.get:(Lorg/eclipse/rdf4j/rio/RioSetting;)Ljava/lang/Object;
      60: checkcast     #33                 // class java/lang/Boolean
      63: invokevirtual #34                 // Method com/github/jsonldjava/core/JsonLdOptions.setCompactArrays:(Ljava/lang/Boolean;)V
      66: aload         4
      68: aload         5
      70: getstatic     #35                 // Field org/eclipse/rdf4j/rio/helpers/JSONLDSettings.PRODUCE_GENERALIZED_RDF:Lorg/eclipse/rdf4j/rio/RioSetting;
      73: invokevirtual #28                 // Method org/eclipse/rdf4j/rio/WriterConfig.get:(Lorg/eclipse/rdf4j/rio/RioSetting;)Ljava/lang/Object;
      76: checkcast     #33                 // class java/lang/Boolean
      79: invokevirtual #36                 // Method com/github/jsonldjava/core/JsonLdOptions.setProduceGeneralizedRdf:(Ljava/lang/Boolean;)V
      82: aload         4
      84: aload         5
      86: getstatic     #37                 // Field org/eclipse/rdf4j/rio/helpers/JSONLDSettings.USE_RDF_TYPE:Lorg/eclipse/rdf4j/rio/RioSetting;
      89: invokevirtual #28                 // Method org/eclipse/rdf4j/rio/WriterConfig.get:(Lorg/eclipse/rdf4j/rio/RioSetting;)Ljava/lang/Object;
      92: checkcast     #33                 // class java/lang/Boolean
      95: invokevirtual #38                 // Method com/github/jsonldjava/core/JsonLdOptions.setUseRdfType:(Ljava/lang/Boolean;)V
      98: aload         4
     100: aload         5
     102: getstatic     #39                 // Field org/eclipse/rdf4j/rio/helpers/JSONLDSettings.USE_NATIVE_TYPES:Lorg/eclipse/rdf4j/rio/RioSetting;
     105: invokevirtual #28                 // Method org/eclipse/rdf4j/rio/WriterConfig.get:(Lorg/eclipse/rdf4j/rio/RioSetting;)Ljava/lang/Object;
     108: checkcast     #33                 // class java/lang/Boolean
     111: invokevirtual #40                 // Method com/github/jsonldjava/core/JsonLdOptions.setUseNativeTypes:(Ljava/lang/Boolean;)V
     114: aload         5
     116: getstatic     #41                 // Field org/eclipse/rdf4j/rio/helpers/JSONLDSettings.HIERARCHICAL_VIEW:Lorg/eclipse/rdf4j/rio/RioSetting;
     119: invokevirtual #28                 // Method org/eclipse/rdf4j/rio/WriterConfig.get:(Lorg/eclipse/rdf4j/rio/RioSetting;)Ljava/lang/Object;
     122: checkcast     #33                 // class java/lang/Boolean
     125: invokevirtual #42                 // Method java/lang/Boolean.booleanValue:()Z
     128: ifeq          136
     131: aload_2
     132: invokestatic  #43                 // Method org/eclipse/rdf4j/rio/jsonld/JSONLDHierarchicalProcessor.fromJsonLdObject:(Ljava/lang/Object;)Ljava/lang/Object;
     135: astore_2
     136: aload_0
     137: getfield      #9                  // Field baseURI:Ljava/lang/String;
     140: ifnull        169
     143: aload         5
     145: getstatic     #44                 // Field org/eclipse/rdf4j/rio/helpers/BasicWriterSettings.BASE_DIRECTIVE:Lorg/eclipse/rdf4j/rio/RioSetting;
     148: invokevirtual #28                 // Method org/eclipse/rdf4j/rio/WriterConfig.get:(Lorg/eclipse/rdf4j/rio/RioSetting;)Ljava/lang/Object;
     151: checkcast     #33                 // class java/lang/Boolean
     154: invokevirtual #42                 // Method java/lang/Boolean.booleanValue:()Z
     157: ifeq          169
     160: aload         4
     162: aload_0
     163: getfield      #9                  // Field baseURI:Ljava/lang/String;
     166: invokevirtual #45                 // Method com/github/jsonldjava/core/JsonLdOptions.setBase:(Ljava/lang/String;)V
     169: aload_3
     170: getstatic     #46                 // Field org/eclipse/rdf4j/rio/helpers/JSONLDMode.EXPAND:Lorg/eclipse/rdf4j/rio/helpers/JSONLDMode;
     173: if_acmpne     183
     176: aload_2
     177: aload         4
     179: invokestatic  #47                 // Method com/github/jsonldjava/core/JsonLdProcessor.expand:(Ljava/lang/Object;Lcom/github/jsonldjava/core/JsonLdOptions;)Ljava/util/List;
     182: astore_2
     183: aconst_null
     184: astore        6
     186: aload_3
     187: getstatic     #48                 // Field org/eclipse/rdf4j/rio/helpers/JSONLDMode.FLATTEN:Lorg/eclipse/rdf4j/rio/helpers/JSONLDMode;
     190: if_acmpne     202
     193: aload_2
     194: aload         6
     196: aload         4
     198: invokestatic  #49                 // Method com/github/jsonldjava/core/JsonLdProcessor.flatten:(Ljava/lang/Object;Ljava/lang/Object;Lcom/github/jsonldjava/core/JsonLdOptions;)Ljava/lang/Object;
     201: astore_2
     202: aload_3
     203: getstatic     #50                 // Field org/eclipse/rdf4j/rio/helpers/JSONLDMode.COMPACT:Lorg/eclipse/rdf4j/rio/helpers/JSONLDMode;
     206: if_acmpne     262
     209: new           #51                 // class java/util/LinkedHashMap
     212: dup
     213: invokespecial #52                 // Method java/util/LinkedHashMap."<init>":()V
     216: astore        7
     218: aload         7
     220: aload_0
     221: getfield      #5                  // Field model:Lorg/eclipse/rdf4j/model/Model;
     224: invokeinterface #53,  1           // InterfaceMethod org/eclipse/rdf4j/model/Model.getNamespaces:()Ljava/util/Set;
     229: invokestatic  #54                 // Method addPrefixes:(Ljava/util/Map;Ljava/util/Set;)V
     232: new           #55                 // class java/util/HashMap
     235: dup
     236: invokespecial #56                 // Method java/util/HashMap."<init>":()V
     239: astore        8
     241: aload         8
     243: ldc           #58                 // String @context
     245: aload         7
     247: invokeinterface #59,  3           // InterfaceMethod java/util/Map.put:(Ljava/lang/Object;Ljava/lang/Object;)Ljava/lang/Object;
     252: pop
     253: aload_2
     254: aload         8
     256: aload         4
     258: invokestatic  #60                 // Method com/github/jsonldjava/core/JsonLdProcessor.compact:(Ljava/lang/Object;Ljava/lang/Object;Lcom/github/jsonldjava/core/JsonLdOptions;)Ljava/util/Map;
     261: astore_2
     262: aload         5
     264: getstatic     #61                 // Field org/eclipse/rdf4j/rio/helpers/BasicWriterSettings.PRETTY_PRINT:Lorg/eclipse/rdf4j/rio/RioSetting;
     267: invokevirtual #28                 // Method org/eclipse/rdf4j/rio/WriterConfig.get:(Lorg/eclipse/rdf4j/rio/RioSetting;)Ljava/lang/Object;
     270: checkcast     #33                 // class java/lang/Boolean
     273: invokevirtual #42                 // Method java/lang/Boolean.booleanValue:()Z
     276: ifeq          290
     279: aload_0
     280: getfield      #15                 // Field writer:Ljava/io/Writer;
     283: aload_2
     284: invokestatic  #62                 // Method com/github/jsonldjava/utils/JsonUtils.writePrettyPrint:(Ljava/io/Writer;Ljava/lang/Object;)V
     287: goto          298
     290: aload_0
     291: getfield      #15                 // Field writer:Ljava/io/Writer;
     294: aload_2
     295: invokestatic  #63                 // Method com/github/jsonldjava/utils/JsonUtils.write:(Ljava/io/Writer;Ljava/lang/Object;)V
     298: goto          313
     301: astore_2
     302: new           #66                 // class org/eclipse/rdf4j/rio/RDFHandlerException
     305: dup
     306: ldc           #67                 // String Could not render JSONLD
     308: aload_2
     309: invokespecial #68                 // Method org/eclipse/rdf4j/rio/RDFHandlerException."<init>":(Ljava/lang/String;Ljava/lang/Throwable;)V
     312: athrow
     313: return
    Exception table:
       from    to  target type
          12   298   301   Class com/github/jsonldjava/core/JsonLdError
          12   298   301   Class java/io/IOException

  public void consumeStatement(org.eclipse.rdf4j.model.Statement) throws org.eclipse.rdf4j.rio.RDFHandlerException;
    Code:
       0: aload_0
       1: getfield      #8                  // Field statementCollector:Lorg/eclipse/rdf4j/rio/helpers/StatementCollector;
       4: aload_1
       5: invokevirtual #69                 // Method org/eclipse/rdf4j/rio/helpers/StatementCollector.handleStatement:(Lorg/eclipse/rdf4j/model/Statement;)V
       8: return

  public void handleComment(java.lang.String) throws org.eclipse.rdf4j.rio.RDFHandlerException;
    Code:
       0: aload_0
       1: invokevirtual #18                 // Method checkWritingStarted:()V
       4: return

  public org.eclipse.rdf4j.rio.RDFFormat getRDFFormat();
    Code:
       0: getstatic     #70                 // Field org/eclipse/rdf4j/rio/RDFFormat.JSONLD:Lorg/eclipse/rdf4j/rio/RDFFormat;
       3: areturn

  public java.util.Collection<org.eclipse.rdf4j.rio.RioSetting<?>> getSupportedSettings();
    Code:
       0: aload_0
       1: invokespecial #71                 // Method org/eclipse/rdf4j/rio/helpers/AbstractRDFWriter.getSupportedSettings:()Ljava/util/Collection;
       4: astore_1
       5: aload_1
       6: getstatic     #32                 // Field org/eclipse/rdf4j/rio/helpers/JSONLDSettings.COMPACT_ARRAYS:Lorg/eclipse/rdf4j/rio/RioSetting;
       9: invokeinterface #72,  2           // InterfaceMethod java/util/Collection.add:(Ljava/lang/Object;)Z
      14: pop
      15: aload_1
      16: getstatic     #41                 // Field org/eclipse/rdf4j/rio/helpers/JSONLDSettings.HIERARCHICAL_VIEW:Lorg/eclipse/rdf4j/rio/RioSetting;
      19: invokeinterface #72,  2           // InterfaceMethod java/util/Collection.add:(Ljava/lang/Object;)Z
      24: pop
      25: aload_1
      26: getstatic     #27                 // Field org/eclipse/rdf4j/rio/helpers/JSONLDSettings.JSONLD_MODE:Lorg/eclipse/rdf4j/rio/RioSetting;
      29: invokeinterface #72,  2           // InterfaceMethod java/util/Collection.add:(Ljava/lang/Object;)Z
      34: pop
      35: aload_1
      36: getstatic     #35                 // Field org/eclipse/rdf4j/rio/helpers/JSONLDSettings.PRODUCE_GENERALIZED_RDF:Lorg/eclipse/rdf4j/rio/RioSetting;
      39: invokeinterface #72,  2           // InterfaceMethod java/util/Collection.add:(Ljava/lang/Object;)Z
      44: pop
      45: aload_1
      46: getstatic     #37                 // Field org/eclipse/rdf4j/rio/helpers/JSONLDSettings.USE_RDF_TYPE:Lorg/eclipse/rdf4j/rio/RioSetting;
      49: invokeinterface #72,  2           // InterfaceMethod java/util/Collection.add:(Ljava/lang/Object;)Z
      54: pop
      55: aload_1
      56: getstatic     #39                 // Field org/eclipse/rdf4j/rio/helpers/JSONLDSettings.USE_NATIVE_TYPES:Lorg/eclipse/rdf4j/rio/RioSetting;
      59: invokeinterface #72,  2           // InterfaceMethod java/util/Collection.add:(Ljava/lang/Object;)Z
      64: pop
      65: aload_1
      66: areturn

  private static void addPrefixes(java.util.Map<java.lang.String, java.lang.Object>, java.util.Set<org.eclipse.rdf4j.model.Namespace>);
    Code:
       0: aload_1
       1: invokeinterface #73,  1           // InterfaceMethod java/util/Set.iterator:()Ljava/util/Iterator;
       6: astore_2
       7: aload_2
       8: invokeinterface #74,  1           // InterfaceMethod java/util/Iterator.hasNext:()Z
      13: ifeq          65
      16: aload_2
      17: invokeinterface #75,  1           // InterfaceMethod java/util/Iterator.next:()Ljava/lang/Object;
      22: checkcast     #76                 // class org/eclipse/rdf4j/model/Namespace
      25: astore_3
      26: aload_0
      27: aload_3
      28: invokeinterface #77,  1           // InterfaceMethod org/eclipse/rdf4j/model/Namespace.getPrefix:()Ljava/lang/String;
      33: invokevirtual #78                 // Method java/lang/String.isEmpty:()Z
      36: ifeq          44
      39: ldc           #79                 // String @vocab
      41: goto          50
      44: aload_3
      45: invokeinterface #77,  1           // InterfaceMethod org/eclipse/rdf4j/model/Namespace.getPrefix:()Ljava/lang/String;
      50: aload_3
      51: invokeinterface #80,  1           // InterfaceMethod org/eclipse/rdf4j/model/Namespace.getName:()Ljava/lang/String;
      56: invokeinterface #59,  3           // InterfaceMethod java/util/Map.put:(Ljava/lang/Object;Ljava/lang/Object;)Ljava/lang/Object;
      61: pop
      62: goto          7
      65: return
}
