Compiled from "StrategySelectorBuilder.java"
public class org.hibernate.boot.registry.selector.internal.StrategySelectorBuilder {
  private static final org.jboss.logging.Logger log;

  private final java.util.List<org.hibernate.boot.registry.selector.StrategyRegistration> explicitStrategyRegistrations;

  public org.hibernate.boot.registry.selector.internal.StrategySelectorBuilder();
    Code:
       0: aload_0
       1: invokespecial #1                  // Method java/lang/Object."<init>":()V
       4: aload_0
       5: new           #2                  // class java/util/ArrayList
       8: dup
       9: invokespecial #3                  // Method java/util/ArrayList."<init>":()V
      12: putfield      #4                  // Field explicitStrategyRegistrations:Ljava/util/List;
      15: return

  public <T> void addExplicitStrategyRegistration(java.lang.Class<T>, java.lang.Class<? extends T>, java.lang.String);
    Code:
       0: aload_0
       1: new           #5                  // class org/hibernate/boot/registry/selector/SimpleStrategyRegistrationImpl
       4: dup
       5: aload_1
       6: aload_2
       7: iconst_1
       8: anewarray     #6                  // class java/lang/String
      11: dup
      12: iconst_0
      13: aload_3
      14: aastore
      15: invokespecial #7                  // Method org/hibernate/boot/registry/selector/SimpleStrategyRegistrationImpl."<init>":(Ljava/lang/Class;Ljava/lang/Class;[Ljava/lang/String;)V
      18: invokevirtual #8                  // Method addExplicitStrategyRegistration:(Lorg/hibernate/boot/registry/selector/StrategyRegistration;)V
      21: return

  public <T> void addExplicitStrategyRegistration(org.hibernate.boot.registry.selector.StrategyRegistration<T>);
    Code:
       0: aload_1
       1: invokeinterface #9,  1            // InterfaceMethod org/hibernate/boot/registry/selector/StrategyRegistration.getStrategyRole:()Ljava/lang/Class;
       6: invokevirtual #10                 // Method java/lang/Class.isInterface:()Z
       9: ifne          45
      12: getstatic     #11                 // Field log:Lorg/jboss/logging/Logger;
      15: new           #12                 // class java/lang/StringBuilder
      18: dup
      19: invokespecial #13                 // Method java/lang/StringBuilder."<init>":()V
      22: ldc           #14                 // String Registering non-interface strategy :
      24: invokevirtual #15                 // Method java/lang/StringBuilder.append:(Ljava/lang/String;)Ljava/lang/StringBuilder;
      27: aload_1
      28: invokeinterface #9,  1            // InterfaceMethod org/hibernate/boot/registry/selector/StrategyRegistration.getStrategyRole:()Ljava/lang/Class;
      33: invokevirtual #16                 // Method java/lang/Class.getName:()Ljava/lang/String;
      36: invokevirtual #15                 // Method java/lang/StringBuilder.append:(Ljava/lang/String;)Ljava/lang/StringBuilder;
      39: invokevirtual #17                 // Method java/lang/StringBuilder.toString:()Ljava/lang/String;
      42: invokevirtual #18                 // Method org/jboss/logging/Logger.debug:(Ljava/lang/Object;)V
      45: aload_1
      46: invokeinterface #9,  1            // InterfaceMethod org/hibernate/boot/registry/selector/StrategyRegistration.getStrategyRole:()Ljava/lang/Class;
      51: aload_1
      52: invokeinterface #19,  1           // InterfaceMethod org/hibernate/boot/registry/selector/StrategyRegistration.getStrategyImplementation:()Ljava/lang/Class;
      57: invokevirtual #20                 // Method java/lang/Class.isAssignableFrom:(Ljava/lang/Class;)Z
      60: ifne          120
      63: new           #21                 // class org/hibernate/boot/registry/selector/spi/StrategySelectionException
      66: dup
      67: new           #12                 // class java/lang/StringBuilder
      70: dup
      71: invokespecial #13                 // Method java/lang/StringBuilder."<init>":()V
      74: ldc           #22                 // String Implementation class [
      76: invokevirtual #15                 // Method java/lang/StringBuilder.append:(Ljava/lang/String;)Ljava/lang/StringBuilder;
      79: aload_1
      80: invokeinterface #19,  1           // InterfaceMethod org/hibernate/boot/registry/selector/StrategyRegistration.getStrategyImplementation:()Ljava/lang/Class;
      85: invokevirtual #16                 // Method java/lang/Class.getName:()Ljava/lang/String;
      88: invokevirtual #15                 // Method java/lang/StringBuilder.append:(Ljava/lang/String;)Ljava/lang/StringBuilder;
      91: ldc           #23                 // String ] does not implement strategy interface [
      93: invokevirtual #15                 // Method java/lang/StringBuilder.append:(Ljava/lang/String;)Ljava/lang/StringBuilder;
      96: aload_1
      97: invokeinterface #9,  1            // InterfaceMethod org/hibernate/boot/registry/selector/StrategyRegistration.getStrategyRole:()Ljava/lang/Class;
     102: invokevirtual #16                 // Method java/lang/Class.getName:()Ljava/lang/String;
     105: invokevirtual #15                 // Method java/lang/StringBuilder.append:(Ljava/lang/String;)Ljava/lang/StringBuilder;
     108: ldc           #24                 // String ]
     110: invokevirtual #15                 // Method java/lang/StringBuilder.append:(Ljava/lang/String;)Ljava/lang/StringBuilder;
     113: invokevirtual #17                 // Method java/lang/StringBuilder.toString:()Ljava/lang/String;
     116: invokespecial #25                 // Method org/hibernate/boot/registry/selector/spi/StrategySelectionException."<init>":(Ljava/lang/String;)V
     119: athrow
     120: aload_0
     121: getfield      #4                  // Field explicitStrategyRegistrations:Ljava/util/List;
     124: aload_1
     125: invokeinterface #26,  2           // InterfaceMethod java/util/List.add:(Ljava/lang/Object;)Z
     130: pop
     131: return

  public org.hibernate.boot.registry.selector.spi.StrategySelector buildSelector(org.hibernate.boot.registry.classloading.spi.ClassLoaderService);
    Code:
       0: new           #27                 // class org/hibernate/boot/registry/selector/internal/StrategySelectorImpl
       3: dup
       4: aload_1
       5: invokespecial #28                 // Method org/hibernate/boot/registry/selector/internal/StrategySelectorImpl."<init>":(Lorg/hibernate/boot/registry/classloading/spi/ClassLoaderService;)V
       8: astore_2
       9: aload_0
      10: aload_2
      11: invokespecial #29                 // Method addDialects:(Lorg/hibernate/boot/registry/selector/internal/StrategySelectorImpl;)V
      14: aload_0
      15: aload_2
      16: invokespecial #30                 // Method addJtaPlatforms:(Lorg/hibernate/boot/registry/selector/internal/StrategySelectorImpl;)V
      19: aload_0
      20: aload_2
      21: invokespecial #31                 // Method addTransactionCoordinatorBuilders:(Lorg/hibernate/boot/registry/selector/internal/StrategySelectorImpl;)V
      24: aload_0
      25: aload_2
      26: invokespecial #32                 // Method addMultiTableBulkIdStrategies:(Lorg/hibernate/boot/registry/selector/internal/StrategySelectorImpl;)V
      29: aload_0
      30: aload_2
      31: invokespecial #33                 // Method addEntityCopyObserverStrategies:(Lorg/hibernate/boot/registry/selector/internal/StrategySelectorImpl;)V
      34: aload_0
      35: aload_2
      36: invokespecial #34                 // Method addImplicitNamingStrategies:(Lorg/hibernate/boot/registry/selector/internal/StrategySelectorImpl;)V
      39: aload_0
      40: aload_2
      41: invokespecial #35                 // Method addCacheKeysFactories:(Lorg/hibernate/boot/registry/selector/internal/StrategySelectorImpl;)V
      44: aload_1
      45: ldc           #36                 // class org/hibernate/boot/registry/selector/StrategyRegistrationProvider
      47: invokeinterface #37,  2           // InterfaceMethod org/hibernate/boot/registry/classloading/spi/ClassLoaderService.loadJavaServices:(Ljava/lang/Class;)Ljava/util/Collection;
      52: invokeinterface #38,  1           // InterfaceMethod java/util/Collection.iterator:()Ljava/util/Iterator;
      57: astore_3
      58: aload_3
      59: invokeinterface #39,  1           // InterfaceMethod java/util/Iterator.hasNext:()Z
      64: ifeq          127
      67: aload_3
      68: invokeinterface #40,  1           // InterfaceMethod java/util/Iterator.next:()Ljava/lang/Object;
      73: checkcast     #36                 // class org/hibernate/boot/registry/selector/StrategyRegistrationProvider
      76: astore        4
      78: aload         4
      80: invokeinterface #41,  1           // InterfaceMethod org/hibernate/boot/registry/selector/StrategyRegistrationProvider.getStrategyRegistrations:()Ljava/lang/Iterable;
      85: invokeinterface #42,  1           // InterfaceMethod java/lang/Iterable.iterator:()Ljava/util/Iterator;
      90: astore        5
      92: aload         5
      94: invokeinterface #39,  1           // InterfaceMethod java/util/Iterator.hasNext:()Z
      99: ifeq          124
     102: aload         5
     104: invokeinterface #40,  1           // InterfaceMethod java/util/Iterator.next:()Ljava/lang/Object;
     109: checkcast     #43                 // class org/hibernate/boot/registry/selector/StrategyRegistration
     112: astore        6
     114: aload_0
     115: aload_2
     116: aload         6
     118: invokespecial #44                 // Method applyFromStrategyRegistration:(Lorg/hibernate/boot/registry/selector/internal/StrategySelectorImpl;Lorg/hibernate/boot/registry/selector/StrategyRegistration;)V
     121: goto          92
     124: goto          58
     127: aload_0
     128: getfield      #4                  // Field explicitStrategyRegistrations:Ljava/util/List;
     131: invokeinterface #45,  1           // InterfaceMethod java/util/List.iterator:()Ljava/util/Iterator;
     136: astore_3
     137: aload_3
     138: invokeinterface #39,  1           // InterfaceMethod java/util/Iterator.hasNext:()Z
     143: ifeq          167
     146: aload_3
     147: invokeinterface #40,  1           // InterfaceMethod java/util/Iterator.next:()Ljava/lang/Object;
     152: checkcast     #43                 // class org/hibernate/boot/registry/selector/StrategyRegistration
     155: astore        4
     157: aload_0
     158: aload_2
     159: aload         4
     161: invokespecial #44                 // Method applyFromStrategyRegistration:(Lorg/hibernate/boot/registry/selector/internal/StrategySelectorImpl;Lorg/hibernate/boot/registry/selector/StrategyRegistration;)V
     164: goto          137
     167: aload_2
     168: areturn

  private <T> void applyFromStrategyRegistration(org.hibernate.boot.registry.selector.internal.StrategySelectorImpl, org.hibernate.boot.registry.selector.StrategyRegistration<T>);
    Code:
       0: aload_2
       1: invokeinterface #46,  1           // InterfaceMethod org/hibernate/boot/registry/selector/StrategyRegistration.getSelectorNames:()Ljava/lang/Iterable;
       6: invokeinterface #42,  1           // InterfaceMethod java/lang/Iterable.iterator:()Ljava/util/Iterator;
      11: astore_3
      12: aload_3
      13: invokeinterface #39,  1           // InterfaceMethod java/util/Iterator.hasNext:()Z
      18: ifeq          53
      21: aload_3
      22: invokeinterface #40,  1           // InterfaceMethod java/util/Iterator.next:()Ljava/lang/Object;
      27: checkcast     #6                  // class java/lang/String
      30: astore        4
      32: aload_1
      33: aload_2
      34: invokeinterface #9,  1            // InterfaceMethod org/hibernate/boot/registry/selector/StrategyRegistration.getStrategyRole:()Ljava/lang/Class;
      39: aload         4
      41: aload_2
      42: invokeinterface #19,  1           // InterfaceMethod org/hibernate/boot/registry/selector/StrategyRegistration.getStrategyImplementation:()Ljava/lang/Class;
      47: invokevirtual #47                 // Method org/hibernate/boot/registry/selector/internal/StrategySelectorImpl.registerStrategyImplementor:(Ljava/lang/Class;Ljava/lang/String;Ljava/lang/Class;)V
      50: goto          12
      53: return

  private void addDialects(org.hibernate.boot.registry.selector.internal.StrategySelectorImpl);
    Code:
       0: aload_0
       1: aload_1
       2: ldc           #48                 // class org/hibernate/dialect/Cache71Dialect
       4: invokespecial #49                 // Method addDialect:(Lorg/hibernate/boot/registry/selector/internal/StrategySelectorImpl;Ljava/lang/Class;)V
       7: aload_0
       8: aload_1
       9: ldc           #50                 // class org/hibernate/dialect/CUBRIDDialect
      11: invokespecial #49                 // Method addDialect:(Lorg/hibernate/boot/registry/selector/internal/StrategySelectorImpl;Ljava/lang/Class;)V
      14: aload_0
      15: aload_1
      16: ldc           #51                 // class org/hibernate/dialect/DB2Dialect
      18: invokespecial #49                 // Method addDialect:(Lorg/hibernate/boot/registry/selector/internal/StrategySelectorImpl;Ljava/lang/Class;)V
      21: aload_0
      22: aload_1
      23: ldc           #52                 // class org/hibernate/dialect/DB2390Dialect
      25: invokespecial #49                 // Method addDialect:(Lorg/hibernate/boot/registry/selector/internal/StrategySelectorImpl;Ljava/lang/Class;)V
      28: aload_0
      29: aload_1
      30: ldc           #53                 // class org/hibernate/dialect/DB2390V8Dialect
      32: invokespecial #49                 // Method addDialect:(Lorg/hibernate/boot/registry/selector/internal/StrategySelectorImpl;Ljava/lang/Class;)V
      35: aload_0
      36: aload_1
      37: ldc           #54                 // class org/hibernate/dialect/DB2400Dialect
      39: invokespecial #49                 // Method addDialect:(Lorg/hibernate/boot/registry/selector/internal/StrategySelectorImpl;Ljava/lang/Class;)V
      42: aload_0
      43: aload_1
      44: ldc           #55                 // class org/hibernate/dialect/DerbyTenFiveDialect
      46: invokespecial #49                 // Method addDialect:(Lorg/hibernate/boot/registry/selector/internal/StrategySelectorImpl;Ljava/lang/Class;)V
      49: aload_0
      50: aload_1
      51: ldc           #56                 // class org/hibernate/dialect/DerbyTenSixDialect
      53: invokespecial #49                 // Method addDialect:(Lorg/hibernate/boot/registry/selector/internal/StrategySelectorImpl;Ljava/lang/Class;)V
      56: aload_0
      57: aload_1
      58: ldc           #57                 // class org/hibernate/dialect/DerbyTenSevenDialect
      60: invokespecial #49                 // Method addDialect:(Lorg/hibernate/boot/registry/selector/internal/StrategySelectorImpl;Ljava/lang/Class;)V
      63: aload_0
      64: aload_1
      65: ldc           #58                 // class org/hibernate/dialect/FirebirdDialect
      67: invokespecial #49                 // Method addDialect:(Lorg/hibernate/boot/registry/selector/internal/StrategySelectorImpl;Ljava/lang/Class;)V
      70: aload_0
      71: aload_1
      72: ldc           #59                 // class org/hibernate/dialect/FrontBaseDialect
      74: invokespecial #49                 // Method addDialect:(Lorg/hibernate/boot/registry/selector/internal/StrategySelectorImpl;Ljava/lang/Class;)V
      77: aload_0
      78: aload_1
      79: ldc           #60                 // class org/hibernate/dialect/H2Dialect
      81: invokespecial #49                 // Method addDialect:(Lorg/hibernate/boot/registry/selector/internal/StrategySelectorImpl;Ljava/lang/Class;)V
      84: aload_0
      85: aload_1
      86: ldc           #61                 // class org/hibernate/dialect/HANAColumnStoreDialect
      88: invokespecial #49                 // Method addDialect:(Lorg/hibernate/boot/registry/selector/internal/StrategySelectorImpl;Ljava/lang/Class;)V
      91: aload_0
      92: aload_1
      93: ldc           #62                 // class org/hibernate/dialect/HANARowStoreDialect
      95: invokespecial #49                 // Method addDialect:(Lorg/hibernate/boot/registry/selector/internal/StrategySelectorImpl;Ljava/lang/Class;)V
      98: aload_0
      99: aload_1
     100: ldc           #63                 // class org/hibernate/dialect/HSQLDialect
     102: invokespecial #49                 // Method addDialect:(Lorg/hibernate/boot/registry/selector/internal/StrategySelectorImpl;Ljava/lang/Class;)V
     105: aload_0
     106: aload_1
     107: ldc           #64                 // class org/hibernate/dialect/InformixDialect
     109: invokespecial #49                 // Method addDialect:(Lorg/hibernate/boot/registry/selector/internal/StrategySelectorImpl;Ljava/lang/Class;)V
     112: aload_0
     113: aload_1
     114: ldc           #65                 // class org/hibernate/dialect/IngresDialect
     116: invokespecial #49                 // Method addDialect:(Lorg/hibernate/boot/registry/selector/internal/StrategySelectorImpl;Ljava/lang/Class;)V
     119: aload_0
     120: aload_1
     121: ldc           #66                 // class org/hibernate/dialect/Ingres9Dialect
     123: invokespecial #49                 // Method addDialect:(Lorg/hibernate/boot/registry/selector/internal/StrategySelectorImpl;Ljava/lang/Class;)V
     126: aload_0
     127: aload_1
     128: ldc           #67                 // class org/hibernate/dialect/Ingres10Dialect
     130: invokespecial #49                 // Method addDialect:(Lorg/hibernate/boot/registry/selector/internal/StrategySelectorImpl;Ljava/lang/Class;)V
     133: aload_0
     134: aload_1
     135: ldc           #68                 // class org/hibernate/dialect/InterbaseDialect
     137: invokespecial #49                 // Method addDialect:(Lorg/hibernate/boot/registry/selector/internal/StrategySelectorImpl;Ljava/lang/Class;)V
     140: aload_0
     141: aload_1
     142: ldc           #69                 // class org/hibernate/dialect/JDataStoreDialect
     144: invokespecial #49                 // Method addDialect:(Lorg/hibernate/boot/registry/selector/internal/StrategySelectorImpl;Ljava/lang/Class;)V
     147: aload_0
     148: aload_1
     149: ldc           #70                 // class org/hibernate/dialect/MckoiDialect
     151: invokespecial #49                 // Method addDialect:(Lorg/hibernate/boot/registry/selector/internal/StrategySelectorImpl;Ljava/lang/Class;)V
     154: aload_0
     155: aload_1
     156: ldc           #71                 // class org/hibernate/dialect/MimerSQLDialect
     158: invokespecial #49                 // Method addDialect:(Lorg/hibernate/boot/registry/selector/internal/StrategySelectorImpl;Ljava/lang/Class;)V
     161: aload_0
     162: aload_1
     163: ldc           #72                 // class org/hibernate/dialect/MySQL5Dialect
     165: invokespecial #49                 // Method addDialect:(Lorg/hibernate/boot/registry/selector/internal/StrategySelectorImpl;Ljava/lang/Class;)V
     168: aload_0
     169: aload_1
     170: ldc           #73                 // class org/hibernate/dialect/MySQL5InnoDBDialect
     172: invokespecial #49                 // Method addDialect:(Lorg/hibernate/boot/registry/selector/internal/StrategySelectorImpl;Ljava/lang/Class;)V
     175: aload_0
     176: aload_1
     177: ldc           #74                 // class org/hibernate/dialect/MySQL57InnoDBDialect
     179: invokespecial #49                 // Method addDialect:(Lorg/hibernate/boot/registry/selector/internal/StrategySelectorImpl;Ljava/lang/Class;)V
     182: aload_0
     183: aload_1
     184: ldc           #75                 // class org/hibernate/dialect/MySQL57Dialect
     186: invokespecial #49                 // Method addDialect:(Lorg/hibernate/boot/registry/selector/internal/StrategySelectorImpl;Ljava/lang/Class;)V
     189: aload_0
     190: aload_1
     191: ldc           #76                 // class org/hibernate/dialect/Oracle8iDialect
     193: invokespecial #49                 // Method addDialect:(Lorg/hibernate/boot/registry/selector/internal/StrategySelectorImpl;Ljava/lang/Class;)V
     196: aload_0
     197: aload_1
     198: ldc           #77                 // class org/hibernate/dialect/Oracle9iDialect
     200: invokespecial #49                 // Method addDialect:(Lorg/hibernate/boot/registry/selector/internal/StrategySelectorImpl;Ljava/lang/Class;)V
     203: aload_0
     204: aload_1
     205: ldc           #78                 // class org/hibernate/dialect/Oracle10gDialect
     207: invokespecial #49                 // Method addDialect:(Lorg/hibernate/boot/registry/selector/internal/StrategySelectorImpl;Ljava/lang/Class;)V
     210: aload_0
     211: aload_1
     212: ldc           #79                 // class org/hibernate/dialect/PointbaseDialect
     214: invokespecial #49                 // Method addDialect:(Lorg/hibernate/boot/registry/selector/internal/StrategySelectorImpl;Ljava/lang/Class;)V
     217: aload_0
     218: aload_1
     219: ldc           #80                 // class org/hibernate/dialect/PostgresPlusDialect
     221: invokespecial #49                 // Method addDialect:(Lorg/hibernate/boot/registry/selector/internal/StrategySelectorImpl;Ljava/lang/Class;)V
     224: aload_0
     225: aload_1
     226: ldc           #81                 // class org/hibernate/dialect/PostgreSQL81Dialect
     228: invokespecial #49                 // Method addDialect:(Lorg/hibernate/boot/registry/selector/internal/StrategySelectorImpl;Ljava/lang/Class;)V
     231: aload_0
     232: aload_1
     233: ldc           #82                 // class org/hibernate/dialect/PostgreSQL82Dialect
     235: invokespecial #49                 // Method addDialect:(Lorg/hibernate/boot/registry/selector/internal/StrategySelectorImpl;Ljava/lang/Class;)V
     238: aload_0
     239: aload_1
     240: ldc           #83                 // class org/hibernate/dialect/PostgreSQL9Dialect
     242: invokespecial #49                 // Method addDialect:(Lorg/hibernate/boot/registry/selector/internal/StrategySelectorImpl;Ljava/lang/Class;)V
     245: aload_0
     246: aload_1
     247: ldc           #84                 // class org/hibernate/dialect/ProgressDialect
     249: invokespecial #49                 // Method addDialect:(Lorg/hibernate/boot/registry/selector/internal/StrategySelectorImpl;Ljava/lang/Class;)V
     252: aload_0
     253: aload_1
     254: ldc           #85                 // class org/hibernate/dialect/SAPDBDialect
     256: invokespecial #49                 // Method addDialect:(Lorg/hibernate/boot/registry/selector/internal/StrategySelectorImpl;Ljava/lang/Class;)V
     259: aload_0
     260: aload_1
     261: ldc           #86                 // class org/hibernate/dialect/SQLServerDialect
     263: invokespecial #49                 // Method addDialect:(Lorg/hibernate/boot/registry/selector/internal/StrategySelectorImpl;Ljava/lang/Class;)V
     266: aload_0
     267: aload_1
     268: ldc           #87                 // class org/hibernate/dialect/SQLServer2005Dialect
     270: invokespecial #49                 // Method addDialect:(Lorg/hibernate/boot/registry/selector/internal/StrategySelectorImpl;Ljava/lang/Class;)V
     273: aload_0
     274: aload_1
     275: ldc           #88                 // class org/hibernate/dialect/SQLServer2008Dialect
     277: invokespecial #49                 // Method addDialect:(Lorg/hibernate/boot/registry/selector/internal/StrategySelectorImpl;Ljava/lang/Class;)V
     280: aload_0
     281: aload_1
     282: ldc           #89                 // class org/hibernate/dialect/Sybase11Dialect
     284: invokespecial #49                 // Method addDialect:(Lorg/hibernate/boot/registry/selector/internal/StrategySelectorImpl;Ljava/lang/Class;)V
     287: aload_0
     288: aload_1
     289: ldc           #90                 // class org/hibernate/dialect/SybaseAnywhereDialect
     291: invokespecial #49                 // Method addDialect:(Lorg/hibernate/boot/registry/selector/internal/StrategySelectorImpl;Ljava/lang/Class;)V
     294: aload_0
     295: aload_1
     296: ldc           #91                 // class org/hibernate/dialect/SybaseASE15Dialect
     298: invokespecial #49                 // Method addDialect:(Lorg/hibernate/boot/registry/selector/internal/StrategySelectorImpl;Ljava/lang/Class;)V
     301: aload_0
     302: aload_1
     303: ldc           #92                 // class org/hibernate/dialect/SybaseASE157Dialect
     305: invokespecial #49                 // Method addDialect:(Lorg/hibernate/boot/registry/selector/internal/StrategySelectorImpl;Ljava/lang/Class;)V
     308: aload_0
     309: aload_1
     310: ldc           #93                 // class org/hibernate/dialect/TeradataDialect
     312: invokespecial #49                 // Method addDialect:(Lorg/hibernate/boot/registry/selector/internal/StrategySelectorImpl;Ljava/lang/Class;)V
     315: aload_0
     316: aload_1
     317: ldc           #94                 // class org/hibernate/dialect/TimesTenDialect
     319: invokespecial #49                 // Method addDialect:(Lorg/hibernate/boot/registry/selector/internal/StrategySelectorImpl;Ljava/lang/Class;)V
     322: return

  private void addDialect(org.hibernate.boot.registry.selector.internal.StrategySelectorImpl, java.lang.Class<? extends org.hibernate.dialect.Dialect>);
    Code:
       0: aload_2
       1: invokevirtual #95                 // Method java/lang/Class.getSimpleName:()Ljava/lang/String;
       4: astore_3
       5: aload_3
       6: ldc           #96                 // String Dialect
       8: invokevirtual #97                 // Method java/lang/String.endsWith:(Ljava/lang/String;)Z
      11: ifeq          30
      14: aload_3
      15: iconst_0
      16: aload_3
      17: invokevirtual #98                 // Method java/lang/String.length:()I
      20: ldc           #96                 // String Dialect
      22: invokevirtual #98                 // Method java/lang/String.length:()I
      25: isub
      26: invokevirtual #99                 // Method java/lang/String.substring:(II)Ljava/lang/String;
      29: astore_3
      30: aload_1
      31: ldc           #100                // class org/hibernate/dialect/Dialect
      33: aload_3
      34: aload_2
      35: invokevirtual #47                 // Method org/hibernate/boot/registry/selector/internal/StrategySelectorImpl.registerStrategyImplementor:(Ljava/lang/Class;Ljava/lang/String;Ljava/lang/Class;)V
      38: return

  private void addJtaPlatforms(org.hibernate.boot.registry.selector.internal.StrategySelectorImpl);
    Code:
       0: aload_0
       1: aload_1
       2: ldc           #101                // class org/hibernate/engine/transaction/jta/platform/internal/BorlandEnterpriseServerJtaPlatform
       4: iconst_2
       5: anewarray     #6                  // class java/lang/String
       8: dup
       9: iconst_0
      10: ldc           #102                // String Borland
      12: aastore
      13: dup
      14: iconst_1
      15: ldc           #103                // String org.hibernate.service.jta.platform.internal.BorlandEnterpriseServerJtaPlatform
      17: aastore
      18: invokespecial #104                // Method addJtaPlatforms:(Lorg/hibernate/boot/registry/selector/internal/StrategySelectorImpl;Ljava/lang/Class;[Ljava/lang/String;)V
      21: aload_0
      22: aload_1
      23: ldc           #105                // class org/hibernate/engine/transaction/jta/platform/internal/BitronixJtaPlatform
      25: iconst_2
      26: anewarray     #6                  // class java/lang/String
      29: dup
      30: iconst_0
      31: ldc           #106                // String Bitronix
      33: aastore
      34: dup
      35: iconst_1
      36: ldc           #107                // String org.hibernate.service.jta.platform.internal.BitronixJtaPlatform
      38: aastore
      39: invokespecial #104                // Method addJtaPlatforms:(Lorg/hibernate/boot/registry/selector/internal/StrategySelectorImpl;Ljava/lang/Class;[Ljava/lang/String;)V
      42: aload_0
      43: aload_1
      44: ldc           #108                // class org/hibernate/engine/transaction/jta/platform/internal/JBossAppServerJtaPlatform
      46: iconst_2
      47: anewarray     #6                  // class java/lang/String
      50: dup
      51: iconst_0
      52: ldc           #109                // String JBossAS
      54: aastore
      55: dup
      56: iconst_1
      57: ldc           #110                // String org.hibernate.service.jta.platform.internal.JBossAppServerJtaPlatform
      59: aastore
      60: invokespecial #104                // Method addJtaPlatforms:(Lorg/hibernate/boot/registry/selector/internal/StrategySelectorImpl;Ljava/lang/Class;[Ljava/lang/String;)V
      63: aload_0
      64: aload_1
      65: ldc           #111                // class org/hibernate/engine/transaction/jta/platform/internal/JBossStandAloneJtaPlatform
      67: iconst_2
      68: anewarray     #6                  // class java/lang/String
      71: dup
      72: iconst_0
      73: ldc           #112                // String JBossTS
      75: aastore
      76: dup
      77: iconst_1
      78: ldc           #113                // String org.hibernate.service.jta.platform.internal.JBossStandAloneJtaPlatform
      80: aastore
      81: invokespecial #104                // Method addJtaPlatforms:(Lorg/hibernate/boot/registry/selector/internal/StrategySelectorImpl;Ljava/lang/Class;[Ljava/lang/String;)V
      84: aload_0
      85: aload_1
      86: ldc           #114                // class org/hibernate/engine/transaction/jta/platform/internal/JOnASJtaPlatform
      88: iconst_2
      89: anewarray     #6                  // class java/lang/String
      92: dup
      93: iconst_0
      94: ldc           #115                // String JOnAS
      96: aastore
      97: dup
      98: iconst_1
      99: ldc           #116                // String org.hibernate.service.jta.platform.internal.JOnASJtaPlatform
     101: aastore
     102: invokespecial #104                // Method addJtaPlatforms:(Lorg/hibernate/boot/registry/selector/internal/StrategySelectorImpl;Ljava/lang/Class;[Ljava/lang/String;)V
     105: aload_0
     106: aload_1
     107: ldc           #117                // class org/hibernate/engine/transaction/jta/platform/internal/JOTMJtaPlatform
     109: iconst_2
     110: anewarray     #6                  // class java/lang/String
     113: dup
     114: iconst_0
     115: ldc           #118                // String JOTM
     117: aastore
     118: dup
     119: iconst_1
     120: ldc           #119                // String org.hibernate.service.jta.platform.internal.JOTMJtaPlatform
     122: aastore
     123: invokespecial #104                // Method addJtaPlatforms:(Lorg/hibernate/boot/registry/selector/internal/StrategySelectorImpl;Ljava/lang/Class;[Ljava/lang/String;)V
     126: aload_0
     127: aload_1
     128: ldc           #120                // class org/hibernate/engine/transaction/jta/platform/internal/JRun4JtaPlatform
     130: iconst_2
     131: anewarray     #6                  // class java/lang/String
     134: dup
     135: iconst_0
     136: ldc           #121                // String JRun4
     138: aastore
     139: dup
     140: iconst_1
     141: ldc           #122                // String org.hibernate.service.jta.platform.internal.JRun4JtaPlatform
     143: aastore
     144: invokespecial #104                // Method addJtaPlatforms:(Lorg/hibernate/boot/registry/selector/internal/StrategySelectorImpl;Ljava/lang/Class;[Ljava/lang/String;)V
     147: aload_0
     148: aload_1
     149: ldc           #123                // class org/hibernate/engine/transaction/jta/platform/internal/OC4JJtaPlatform
     151: iconst_2
     152: anewarray     #6                  // class java/lang/String
     155: dup
     156: iconst_0
     157: ldc           #124                // String OC4J
     159: aastore
     160: dup
     161: iconst_1
     162: ldc           #125                // String org.hibernate.service.jta.platform.internal.OC4JJtaPlatform
     164: aastore
     165: invokespecial #104                // Method addJtaPlatforms:(Lorg/hibernate/boot/registry/selector/internal/StrategySelectorImpl;Ljava/lang/Class;[Ljava/lang/String;)V
     168: aload_0
     169: aload_1
     170: ldc           #126                // class org/hibernate/engine/transaction/jta/platform/internal/OrionJtaPlatform
     172: iconst_2
     173: anewarray     #6                  // class java/lang/String
     176: dup
     177: iconst_0
     178: ldc           #127                // String Orion
     180: aastore
     181: dup
     182: iconst_1
     183: ldc           #128                // String org.hibernate.service.jta.platform.internal.OrionJtaPlatform
     185: aastore
     186: invokespecial #104                // Method addJtaPlatforms:(Lorg/hibernate/boot/registry/selector/internal/StrategySelectorImpl;Ljava/lang/Class;[Ljava/lang/String;)V
     189: aload_0
     190: aload_1
     191: ldc           #129                // class org/hibernate/engine/transaction/jta/platform/internal/ResinJtaPlatform
     193: iconst_2
     194: anewarray     #6                  // class java/lang/String
     197: dup
     198: iconst_0
     199: ldc           #130                // String Resin
     201: aastore
     202: dup
     203: iconst_1
     204: ldc           #131                // String org.hibernate.service.jta.platform.internal.ResinJtaPlatform
     206: aastore
     207: invokespecial #104                // Method addJtaPlatforms:(Lorg/hibernate/boot/registry/selector/internal/StrategySelectorImpl;Ljava/lang/Class;[Ljava/lang/String;)V
     210: aload_0
     211: aload_1
     212: ldc           #132                // class org/hibernate/engine/transaction/jta/platform/internal/SapNetWeaverJtaPlatform
     214: iconst_2
     215: anewarray     #6                  // class java/lang/String
     218: dup
     219: iconst_0
     220: ldc           #133                // String SapNetWeaver
     222: aastore
     223: dup
     224: iconst_1
     225: ldc           #134                // String org.hibernate.service.jta.platform.internal.SapNetWeaverJtaPlatform
     227: aastore
     228: invokespecial #104                // Method addJtaPlatforms:(Lorg/hibernate/boot/registry/selector/internal/StrategySelectorImpl;Ljava/lang/Class;[Ljava/lang/String;)V
     231: aload_0
     232: aload_1
     233: ldc           #135                // class org/hibernate/engine/transaction/jta/platform/internal/SunOneJtaPlatform
     235: iconst_2
     236: anewarray     #6                  // class java/lang/String
     239: dup
     240: iconst_0
     241: ldc           #136                // String SunOne
     243: aastore
     244: dup
     245: iconst_1
     246: ldc           #137                // String org.hibernate.service.jta.platform.internal.SunOneJtaPlatform
     248: aastore
     249: invokespecial #104                // Method addJtaPlatforms:(Lorg/hibernate/boot/registry/selector/internal/StrategySelectorImpl;Ljava/lang/Class;[Ljava/lang/String;)V
     252: aload_0
     253: aload_1
     254: ldc           #138                // class org/hibernate/engine/transaction/jta/platform/internal/WeblogicJtaPlatform
     256: iconst_2
     257: anewarray     #6                  // class java/lang/String
     260: dup
     261: iconst_0
     262: ldc           #139                // String Weblogic
     264: aastore
     265: dup
     266: iconst_1
     267: ldc           #140                // String org.hibernate.service.jta.platform.internal.WeblogicJtaPlatform
     269: aastore
     270: invokespecial #104                // Method addJtaPlatforms:(Lorg/hibernate/boot/registry/selector/internal/StrategySelectorImpl;Ljava/lang/Class;[Ljava/lang/String;)V
     273: aload_0
     274: aload_1
     275: ldc           #141                // class org/hibernate/engine/transaction/jta/platform/internal/WebSphereLibertyJtaPlatform
     277: iconst_2
     278: anewarray     #6                  // class java/lang/String
     281: dup
     282: iconst_0
     283: ldc           #142                // String WebSphereLiberty
     285: aastore
     286: dup
     287: iconst_1
     288: ldc           #143                // String org.hibernate.engine.transaction.jta.platform.internal.WebSphereLibertyJtaPlatform
     290: aastore
     291: invokespecial #104                // Method addJtaPlatforms:(Lorg/hibernate/boot/registry/selector/internal/StrategySelectorImpl;Ljava/lang/Class;[Ljava/lang/String;)V
     294: aload_0
     295: aload_1
     296: ldc           #144                // class org/hibernate/engine/transaction/jta/platform/internal/WebSphereJtaPlatform
     298: iconst_2
     299: anewarray     #6                  // class java/lang/String
     302: dup
     303: iconst_0
     304: ldc           #145                // String WebSphere
     306: aastore
     307: dup
     308: iconst_1
     309: ldc           #146                // String org.hibernate.service.jta.platform.internal.WebSphereJtaPlatform
     311: aastore
     312: invokespecial #104                // Method addJtaPlatforms:(Lorg/hibernate/boot/registry/selector/internal/StrategySelectorImpl;Ljava/lang/Class;[Ljava/lang/String;)V
     315: aload_0
     316: aload_1
     317: ldc           #147                // class org/hibernate/engine/transaction/jta/platform/internal/WebSphereExtendedJtaPlatform
     319: iconst_2
     320: anewarray     #6                  // class java/lang/String
     323: dup
     324: iconst_0
     325: ldc           #148                // String WebSphereExtended
     327: aastore
     328: dup
     329: iconst_1
     330: ldc           #149                // String org.hibernate.service.jta.platform.internal.WebSphereExtendedJtaPlatform
     332: aastore
     333: invokespecial #104                // Method addJtaPlatforms:(Lorg/hibernate/boot/registry/selector/internal/StrategySelectorImpl;Ljava/lang/Class;[Ljava/lang/String;)V
     336: return

  private void addJtaPlatforms(org.hibernate.boot.registry.selector.internal.StrategySelectorImpl, java.lang.Class<? extends org.hibernate.engine.transaction.jta.platform.spi.JtaPlatform>, java.lang.String...);
    Code:
       0: aload_3
       1: astore        4
       3: aload         4
       5: arraylength
       6: istore        5
       8: iconst_0
       9: istore        6
      11: iload         6
      13: iload         5
      15: if_icmpge     40
      18: aload         4
      20: iload         6
      22: aaload
      23: astore        7
      25: aload_1
      26: ldc           #150                // class org/hibernate/engine/transaction/jta/platform/spi/JtaPlatform
      28: aload         7
      30: aload_2
      31: invokevirtual #47                 // Method org/hibernate/boot/registry/selector/internal/StrategySelectorImpl.registerStrategyImplementor:(Ljava/lang/Class;Ljava/lang/String;Ljava/lang/Class;)V
      34: iinc          6, 1
      37: goto          11
      40: return

  private void addTransactionCoordinatorBuilders(org.hibernate.boot.registry.selector.internal.StrategySelectorImpl);
    Code:
       0: aload_1
       1: ldc           #151                // class org/hibernate/resource/transaction/spi/TransactionCoordinatorBuilder
       3: ldc           #153                // String jdbc
       5: ldc           #152                // class org/hibernate/resource/transaction/backend/jdbc/internal/JdbcResourceLocalTransactionCoordinatorBuilderImpl
       7: invokevirtual #47                 // Method org/hibernate/boot/registry/selector/internal/StrategySelectorImpl.registerStrategyImplementor:(Ljava/lang/Class;Ljava/lang/String;Ljava/lang/Class;)V
      10: aload_1
      11: ldc           #151                // class org/hibernate/resource/transaction/spi/TransactionCoordinatorBuilder
      13: ldc           #155                // String jta
      15: ldc           #154                // class org/hibernate/resource/transaction/backend/jta/internal/JtaTransactionCoordinatorBuilderImpl
      17: invokevirtual #47                 // Method org/hibernate/boot/registry/selector/internal/StrategySelectorImpl.registerStrategyImplementor:(Ljava/lang/Class;Ljava/lang/String;Ljava/lang/Class;)V
      20: aload_1
      21: ldc           #151                // class org/hibernate/resource/transaction/spi/TransactionCoordinatorBuilder
      23: ldc           #156                // String org.hibernate.transaction.JDBCTransactionFactory
      25: ldc           #152                // class org/hibernate/resource/transaction/backend/jdbc/internal/JdbcResourceLocalTransactionCoordinatorBuilderImpl
      27: invokevirtual #47                 // Method org/hibernate/boot/registry/selector/internal/StrategySelectorImpl.registerStrategyImplementor:(Ljava/lang/Class;Ljava/lang/String;Ljava/lang/Class;)V
      30: aload_1
      31: ldc           #151                // class org/hibernate/resource/transaction/spi/TransactionCoordinatorBuilder
      33: ldc           #157                // String org.hibernate.transaction.JTATransactionFactory
      35: ldc           #154                // class org/hibernate/resource/transaction/backend/jta/internal/JtaTransactionCoordinatorBuilderImpl
      37: invokevirtual #47                 // Method org/hibernate/boot/registry/selector/internal/StrategySelectorImpl.registerStrategyImplementor:(Ljava/lang/Class;Ljava/lang/String;Ljava/lang/Class;)V
      40: aload_1
      41: ldc           #151                // class org/hibernate/resource/transaction/spi/TransactionCoordinatorBuilder
      43: ldc           #158                // String org.hibernate.transaction.CMTTransactionFactory
      45: ldc           #154                // class org/hibernate/resource/transaction/backend/jta/internal/JtaTransactionCoordinatorBuilderImpl
      47: invokevirtual #47                 // Method org/hibernate/boot/registry/selector/internal/StrategySelectorImpl.registerStrategyImplementor:(Ljava/lang/Class;Ljava/lang/String;Ljava/lang/Class;)V
      50: return

  private void addMultiTableBulkIdStrategies(org.hibernate.boot.registry.selector.internal.StrategySelectorImpl);
    Code:
       0: aload_1
       1: ldc           #159                // class org/hibernate/hql/spi/id/MultiTableBulkIdStrategy
       3: ldc           #161                // String persistent
       5: ldc           #160                // class org/hibernate/hql/spi/id/persistent/PersistentTableBulkIdStrategy
       7: invokevirtual #47                 // Method org/hibernate/boot/registry/selector/internal/StrategySelectorImpl.registerStrategyImplementor:(Ljava/lang/Class;Ljava/lang/String;Ljava/lang/Class;)V
      10: aload_1
      11: ldc           #159                // class org/hibernate/hql/spi/id/MultiTableBulkIdStrategy
      13: ldc           #163                // String global_temporary
      15: ldc           #162                // class org/hibernate/hql/spi/id/global/GlobalTemporaryTableBulkIdStrategy
      17: invokevirtual #47                 // Method org/hibernate/boot/registry/selector/internal/StrategySelectorImpl.registerStrategyImplementor:(Ljava/lang/Class;Ljava/lang/String;Ljava/lang/Class;)V
      20: aload_1
      21: ldc           #159                // class org/hibernate/hql/spi/id/MultiTableBulkIdStrategy
      23: ldc           #165                // String local_temporary
      25: ldc           #164                // class org/hibernate/hql/spi/id/local/LocalTemporaryTableBulkIdStrategy
      27: invokevirtual #47                 // Method org/hibernate/boot/registry/selector/internal/StrategySelectorImpl.registerStrategyImplementor:(Ljava/lang/Class;Ljava/lang/String;Ljava/lang/Class;)V
      30: return

  private void addEntityCopyObserverStrategies(org.hibernate.boot.registry.selector.internal.StrategySelectorImpl);
    Code:
       0: aload_1
       1: ldc           #166                // class org/hibernate/event/spi/EntityCopyObserver
       3: ldc           #168                // String disallow
       5: ldc           #167                // class org/hibernate/event/internal/EntityCopyNotAllowedObserver
       7: invokevirtual #47                 // Method org/hibernate/boot/registry/selector/internal/StrategySelectorImpl.registerStrategyImplementor:(Ljava/lang/Class;Ljava/lang/String;Ljava/lang/Class;)V
      10: aload_1
      11: ldc           #166                // class org/hibernate/event/spi/EntityCopyObserver
      13: ldc           #170                // String allow
      15: ldc           #169                // class org/hibernate/event/internal/EntityCopyAllowedObserver
      17: invokevirtual #47                 // Method org/hibernate/boot/registry/selector/internal/StrategySelectorImpl.registerStrategyImplementor:(Ljava/lang/Class;Ljava/lang/String;Ljava/lang/Class;)V
      20: aload_1
      21: ldc           #166                // class org/hibernate/event/spi/EntityCopyObserver
      23: ldc           #172                // String log
      25: ldc           #171                // class org/hibernate/event/internal/EntityCopyAllowedLoggedObserver
      27: invokevirtual #47                 // Method org/hibernate/boot/registry/selector/internal/StrategySelectorImpl.registerStrategyImplementor:(Ljava/lang/Class;Ljava/lang/String;Ljava/lang/Class;)V
      30: return

  private void addImplicitNamingStrategies(org.hibernate.boot.registry.selector.internal.StrategySelectorImpl);
    Code:
       0: aload_1
       1: ldc           #173                // class org/hibernate/boot/model/naming/ImplicitNamingStrategy
       3: ldc           #174                // String default
       5: ldc           #175                // class org/hibernate/boot/model/naming/ImplicitNamingStrategyJpaCompliantImpl
       7: invokevirtual #47                 // Method org/hibernate/boot/registry/selector/internal/StrategySelectorImpl.registerStrategyImplementor:(Ljava/lang/Class;Ljava/lang/String;Ljava/lang/Class;)V
      10: aload_1
      11: ldc           #173                // class org/hibernate/boot/model/naming/ImplicitNamingStrategy
      13: ldc           #176                // String jpa
      15: ldc           #175                // class org/hibernate/boot/model/naming/ImplicitNamingStrategyJpaCompliantImpl
      17: invokevirtual #47                 // Method org/hibernate/boot/registry/selector/internal/StrategySelectorImpl.registerStrategyImplementor:(Ljava/lang/Class;Ljava/lang/String;Ljava/lang/Class;)V
      20: aload_1
      21: ldc           #173                // class org/hibernate/boot/model/naming/ImplicitNamingStrategy
      23: ldc           #177                // String legacy-jpa
      25: ldc           #178                // class org/hibernate/boot/model/naming/ImplicitNamingStrategyLegacyJpaImpl
      27: invokevirtual #47                 // Method org/hibernate/boot/registry/selector/internal/StrategySelectorImpl.registerStrategyImplementor:(Ljava/lang/Class;Ljava/lang/String;Ljava/lang/Class;)V
      30: aload_1
      31: ldc           #173                // class org/hibernate/boot/model/naming/ImplicitNamingStrategy
      33: ldc           #179                // String legacy-hbm
      35: ldc           #180                // class org/hibernate/boot/model/naming/ImplicitNamingStrategyLegacyHbmImpl
      37: invokevirtual #47                 // Method org/hibernate/boot/registry/selector/internal/StrategySelectorImpl.registerStrategyImplementor:(Ljava/lang/Class;Ljava/lang/String;Ljava/lang/Class;)V
      40: aload_1
      41: ldc           #173                // class org/hibernate/boot/model/naming/ImplicitNamingStrategy
      43: ldc           #181                // String component-path
      45: ldc           #182                // class org/hibernate/boot/model/naming/ImplicitNamingStrategyComponentPathImpl
      47: invokevirtual #47                 // Method org/hibernate/boot/registry/selector/internal/StrategySelectorImpl.registerStrategyImplementor:(Ljava/lang/Class;Ljava/lang/String;Ljava/lang/Class;)V
      50: return

  private void addCacheKeysFactories(org.hibernate.boot.registry.selector.internal.StrategySelectorImpl);
    Code:
       0: aload_1
       1: ldc           #183                // class org/hibernate/cache/spi/CacheKeysFactory
       3: ldc           #174                // String default
       5: ldc           #184                // class org/hibernate/cache/internal/DefaultCacheKeysFactory
       7: invokevirtual #47                 // Method org/hibernate/boot/registry/selector/internal/StrategySelectorImpl.registerStrategyImplementor:(Ljava/lang/Class;Ljava/lang/String;Ljava/lang/Class;)V
      10: aload_1
      11: ldc           #183                // class org/hibernate/cache/spi/CacheKeysFactory
      13: ldc           #186                // String simple
      15: ldc           #185                // class org/hibernate/cache/internal/SimpleCacheKeysFactory
      17: invokevirtual #47                 // Method org/hibernate/boot/registry/selector/internal/StrategySelectorImpl.registerStrategyImplementor:(Ljava/lang/Class;Ljava/lang/String;Ljava/lang/Class;)V
      20: return

  static {};
    Code:
       0: ldc           #187                // class org/hibernate/boot/registry/selector/internal/StrategySelectorBuilder
       2: invokestatic  #188                // Method org/jboss/logging/Logger.getLogger:(Ljava/lang/Class;)Lorg/jboss/logging/Logger;
       5: putstatic     #11                 // Field log:Lorg/jboss/logging/Logger;
       8: return
}
