Compiled from "SOAPBindingOperationExtensionsImpl.java"
public class org.apache.woden.internal.wsdl20.extensions.soap.SOAPBindingOperationExtensionsImpl extends org.apache.woden.wsdl20.extensions.BaseComponentExtensionContext implements org.apache.woden.wsdl20.extensions.soap.SOAPBindingOperationExtensions {
  public org.apache.woden.internal.wsdl20.extensions.soap.SOAPBindingOperationExtensionsImpl(org.apache.woden.wsdl20.WSDLComponent, java.net.URI, org.apache.woden.ErrorReporter);
    Code:
       0: aload_0
       1: aload_1
       2: aload_2
       3: aload_3
       4: invokespecial #1                  // Method org/apache/woden/wsdl20/extensions/BaseComponentExtensionContext."<init>":(Lorg/apache/woden/wsdl20/WSDLComponent;Ljava/net/URI;Lorg/apache/woden/ErrorReporter;)V
       7: return

  public org.apache.woden.wsdl20.extensions.ExtensionProperty[] getProperties();
    Code:
       0: iconst_3
       1: anewarray     #2                  // class org/apache/woden/wsdl20/extensions/ExtensionProperty
       4: dup
       5: iconst_0
       6: aload_0
       7: ldc           #3                  // String soap mep
       9: invokevirtual #4                  // Method getProperty:(Ljava/lang/String;)Lorg/apache/woden/wsdl20/extensions/ExtensionProperty;
      12: aastore
      13: dup
      14: iconst_1
      15: aload_0
      16: ldc           #5                  // String soap action
      18: invokevirtual #4                  // Method getProperty:(Ljava/lang/String;)Lorg/apache/woden/wsdl20/extensions/ExtensionProperty;
      21: aastore
      22: dup
      23: iconst_2
      24: aload_0
      25: ldc           #6                  // String soap modules
      27: invokevirtual #4                  // Method getProperty:(Ljava/lang/String;)Lorg/apache/woden/wsdl20/extensions/ExtensionProperty;
      30: aastore
      31: areturn

  public org.apache.woden.wsdl20.extensions.ExtensionProperty getProperty(java.lang.String);
    Code:
       0: ldc           #3                  // String soap mep
       2: aload_1
       3: invokevirtual #7                  // Method java/lang/String.equals:(Ljava/lang/Object;)Z
       6: ifeq          20
       9: aload_0
      10: ldc           #3                  // String soap mep
      12: aload_0
      13: invokevirtual #8                  // Method getSoapMep:()Ljava/net/URI;
      16: invokevirtual #9                  // Method newExtensionProperty:(Ljava/lang/String;Ljava/lang/Object;)Lorg/apache/woden/wsdl20/extensions/ExtensionProperty;
      19: areturn
      20: ldc           #5                  // String soap action
      22: aload_1
      23: invokevirtual #7                  // Method java/lang/String.equals:(Ljava/lang/Object;)Z
      26: ifeq          40
      29: aload_0
      30: ldc           #5                  // String soap action
      32: aload_0
      33: invokevirtual #10                 // Method getSoapAction:()Ljava/net/URI;
      36: invokevirtual #9                  // Method newExtensionProperty:(Ljava/lang/String;Ljava/lang/Object;)Lorg/apache/woden/wsdl20/extensions/ExtensionProperty;
      39: areturn
      40: ldc           #6                  // String soap modules
      42: aload_1
      43: invokevirtual #7                  // Method java/lang/String.equals:(Ljava/lang/Object;)Z
      46: ifeq          60
      49: aload_0
      50: ldc           #6                  // String soap modules
      52: aload_0
      53: invokevirtual #11                 // Method getSoapModules:()[Lorg/apache/woden/wsdl20/extensions/soap/SOAPModule;
      56: invokevirtual #9                  // Method newExtensionProperty:(Ljava/lang/String;Ljava/lang/Object;)Lorg/apache/woden/wsdl20/extensions/ExtensionProperty;
      59: areturn
      60: aconst_null
      61: areturn

  public java.net.URI getSoapMep();
    Code:
       0: aload_0
       1: invokevirtual #12                 // Method getParent:()Lorg/apache/woden/wsdl20/WSDLComponent;
       4: checkcast     #13                 // class org/apache/woden/wsdl20/xml/WSDLElement
       7: getstatic     #14                 // Field org/apache/woden/wsdl20/extensions/soap/SOAPConstants.Q_ATTR_SOAP_MEP:Ljavax/xml/namespace/QName;
      10: invokeinterface #15,  2           // InterfaceMethod org/apache/woden/wsdl20/xml/WSDLElement.getExtensionAttribute:(Ljavax/xml/namespace/QName;)Lorg/apache/woden/xml/XMLAttr;
      15: checkcast     #16                 // class org/apache/woden/xml/URIAttr
      18: astore_1
      19: aload_1
      20: ifnull        32
      23: aload_1
      24: invokeinterface #17,  1           // InterfaceMethod org/apache/woden/xml/URIAttr.getURI:()Ljava/net/URI;
      29: goto          33
      32: aconst_null
      33: areturn

  public java.net.URI getSoapAction();
    Code:
       0: aload_0
       1: invokevirtual #12                 // Method getParent:()Lorg/apache/woden/wsdl20/WSDLComponent;
       4: checkcast     #13                 // class org/apache/woden/wsdl20/xml/WSDLElement
       7: getstatic     #18                 // Field org/apache/woden/wsdl20/extensions/soap/SOAPConstants.Q_ATTR_SOAP_ACTION:Ljavax/xml/namespace/QName;
      10: invokeinterface #15,  2           // InterfaceMethod org/apache/woden/wsdl20/xml/WSDLElement.getExtensionAttribute:(Ljavax/xml/namespace/QName;)Lorg/apache/woden/xml/XMLAttr;
      15: checkcast     #16                 // class org/apache/woden/xml/URIAttr
      18: astore_1
      19: aload_1
      20: ifnull        32
      23: aload_1
      24: invokeinterface #17,  1           // InterfaceMethod org/apache/woden/xml/URIAttr.getURI:()Ljava/net/URI;
      29: goto          33
      32: aconst_null
      33: areturn

  public org.apache.woden.wsdl20.extensions.soap.SOAPModule[] getSoapModules();
    Code:
       0: aload_0
       1: invokevirtual #12                 // Method getParent:()Lorg/apache/woden/wsdl20/WSDLComponent;
       4: checkcast     #13                 // class org/apache/woden/wsdl20/xml/WSDLElement
       7: getstatic     #19                 // Field org/apache/woden/wsdl20/extensions/soap/SOAPConstants.Q_ELEM_SOAP_MODULE:Ljavax/xml/namespace/QName;
      10: invokeinterface #20,  2           // InterfaceMethod org/apache/woden/wsdl20/xml/WSDLElement.getExtensionElementsOfType:(Ljavax/xml/namespace/QName;)[Lorg/apache/woden/wsdl20/extensions/ExtensionElement;
      15: astore_1
      16: aload_1
      17: arraylength
      18: istore_2
      19: iload_2
      20: anewarray     #21                 // class org/apache/woden/wsdl20/extensions/soap/SOAPModule
      23: astore_3
      24: aload_1
      25: iconst_0
      26: aload_3
      27: iconst_0
      28: iload_2
      29: invokestatic  #22                 // Method java/lang/System.arraycopy:(Ljava/lang/Object;ILjava/lang/Object;II)V
      32: aload_3
      33: areturn

  public org.apache.woden.wsdl20.extensions.http.HTTPLocation getHttpLocation();
    Code:
       0: aload_0
       1: invokevirtual #12                 // Method getParent:()Lorg/apache/woden/wsdl20/WSDLComponent;
       4: checkcast     #23                 // class org/apache/woden/wsdl20/NestedComponent
       7: invokeinterface #24,  1           // InterfaceMethod org/apache/woden/wsdl20/NestedComponent.getParent:()Lorg/apache/woden/wsdl20/WSDLComponent;
      12: checkcast     #25                 // class org/apache/woden/wsdl20/Binding
      15: astore_1
      16: aload_1
      17: getstatic     #26                 // Field org/apache/woden/wsdl20/extensions/soap/SOAPConstants.NS_URI_SOAP:Ljava/net/URI;
      20: invokeinterface #27,  2           // InterfaceMethod org/apache/woden/wsdl20/Binding.getComponentExtensionContext:(Ljava/net/URI;)Lorg/apache/woden/wsdl20/extensions/ComponentExtensionContext;
      25: checkcast     #28                 // class org/apache/woden/wsdl20/extensions/soap/SOAPBindingExtensions
      28: astore_2
      29: aload_2
      30: invokeinterface #29,  1           // InterfaceMethod org/apache/woden/wsdl20/extensions/soap/SOAPBindingExtensions.getSoapVersion:()Ljava/lang/String;
      35: astore_3
      36: aload_2
      37: invokeinterface #30,  1           // InterfaceMethod org/apache/woden/wsdl20/extensions/soap/SOAPBindingExtensions.getSoapUnderlyingProtocol:()Ljava/net/URI;
      42: astore        4
      44: aload         4
      46: ifnonnull     51
      49: aconst_null
      50: areturn
      51: ldc           #31                 // String 1.2
      53: aload_3
      54: invokevirtual #7                  // Method java/lang/String.equals:(Ljava/lang/Object;)Z
      57: ifeq          71
      60: aload         4
      62: getstatic     #32                 // Field org/apache/woden/wsdl20/extensions/soap/SOAPConstants.PROTOCOL_URI_SOAP12_HTTP:Ljava/net/URI;
      65: invokevirtual #33                 // Method java/net/URI.equals:(Ljava/lang/Object;)Z
      68: ifne          91
      71: ldc           #34                 // String 1.1
      73: aload_3
      74: invokevirtual #7                  // Method java/lang/String.equals:(Ljava/lang/Object;)Z
      77: ifeq          135
      80: aload         4
      82: getstatic     #35                 // Field org/apache/woden/wsdl20/extensions/soap/SOAPConstants.PROTOCOL_URI_SOAP11_HTTP:Ljava/net/URI;
      85: invokevirtual #33                 // Method java/net/URI.equals:(Ljava/lang/Object;)Z
      88: ifeq          135
      91: aload_0
      92: invokevirtual #12                 // Method getParent:()Lorg/apache/woden/wsdl20/WSDLComponent;
      95: checkcast     #13                 // class org/apache/woden/wsdl20/xml/WSDLElement
      98: getstatic     #36                 // Field org/apache/woden/wsdl20/extensions/http/HTTPConstants.Q_ATTR_LOCATION:Ljavax/xml/namespace/QName;
     101: invokeinterface #15,  2           // InterfaceMethod org/apache/woden/wsdl20/xml/WSDLElement.getExtensionAttribute:(Ljavax/xml/namespace/QName;)Lorg/apache/woden/xml/XMLAttr;
     106: checkcast     #37                 // class org/apache/woden/xml/StringAttr
     109: astore        5
     111: aload         5
     113: ifnull        133
     116: new           #38                 // class org/apache/woden/wsdl20/extensions/http/HTTPLocation
     119: dup
     120: aload         5
     122: invokeinterface #39,  1           // InterfaceMethod org/apache/woden/xml/StringAttr.getString:()Ljava/lang/String;
     127: invokespecial #40                 // Method org/apache/woden/wsdl20/extensions/http/HTTPLocation."<init>":(Ljava/lang/String;)V
     130: goto          134
     133: aconst_null
     134: areturn
     135: aconst_null
     136: areturn

  public java.lang.String getHttpQueryParameterSeparator();
    Code:
       0: aload_0
       1: invokevirtual #12                 // Method getParent:()Lorg/apache/woden/wsdl20/WSDLComponent;
       4: checkcast     #23                 // class org/apache/woden/wsdl20/NestedComponent
       7: invokeinterface #24,  1           // InterfaceMethod org/apache/woden/wsdl20/NestedComponent.getParent:()Lorg/apache/woden/wsdl20/WSDLComponent;
      12: checkcast     #25                 // class org/apache/woden/wsdl20/Binding
      15: astore_1
      16: aload_1
      17: getstatic     #26                 // Field org/apache/woden/wsdl20/extensions/soap/SOAPConstants.NS_URI_SOAP:Ljava/net/URI;
      20: invokeinterface #27,  2           // InterfaceMethod org/apache/woden/wsdl20/Binding.getComponentExtensionContext:(Ljava/net/URI;)Lorg/apache/woden/wsdl20/extensions/ComponentExtensionContext;
      25: checkcast     #28                 // class org/apache/woden/wsdl20/extensions/soap/SOAPBindingExtensions
      28: astore_2
      29: aload_2
      30: invokeinterface #29,  1           // InterfaceMethod org/apache/woden/wsdl20/extensions/soap/SOAPBindingExtensions.getSoapVersion:()Ljava/lang/String;
      35: astore_3
      36: aload_2
      37: invokeinterface #30,  1           // InterfaceMethod org/apache/woden/wsdl20/extensions/soap/SOAPBindingExtensions.getSoapUnderlyingProtocol:()Ljava/net/URI;
      42: astore        4
      44: aload         4
      46: ifnonnull     51
      49: aconst_null
      50: areturn
      51: ldc           #31                 // String 1.2
      53: aload_3
      54: invokevirtual #7                  // Method java/lang/String.equals:(Ljava/lang/Object;)Z
      57: ifeq          71
      60: aload         4
      62: getstatic     #32                 // Field org/apache/woden/wsdl20/extensions/soap/SOAPConstants.PROTOCOL_URI_SOAP12_HTTP:Ljava/net/URI;
      65: invokevirtual #33                 // Method java/net/URI.equals:(Ljava/lang/Object;)Z
      68: ifne          91
      71: ldc           #34                 // String 1.1
      73: aload_3
      74: invokevirtual #7                  // Method java/lang/String.equals:(Ljava/lang/Object;)Z
      77: ifeq          128
      80: aload         4
      82: getstatic     #35                 // Field org/apache/woden/wsdl20/extensions/soap/SOAPConstants.PROTOCOL_URI_SOAP11_HTTP:Ljava/net/URI;
      85: invokevirtual #33                 // Method java/net/URI.equals:(Ljava/lang/Object;)Z
      88: ifeq          128
      91: aload_0
      92: invokevirtual #12                 // Method getParent:()Lorg/apache/woden/wsdl20/WSDLComponent;
      95: checkcast     #13                 // class org/apache/woden/wsdl20/xml/WSDLElement
      98: getstatic     #41                 // Field org/apache/woden/wsdl20/extensions/http/HTTPConstants.Q_ATTR_QUERY_PARAMETER_SEPARATOR:Ljavax/xml/namespace/QName;
     101: invokeinterface #15,  2           // InterfaceMethod org/apache/woden/wsdl20/xml/WSDLElement.getExtensionAttribute:(Ljavax/xml/namespace/QName;)Lorg/apache/woden/xml/XMLAttr;
     106: checkcast     #37                 // class org/apache/woden/xml/StringAttr
     109: astore        5
     111: aload         5
     113: ifnull        126
     116: aload         5
     118: invokeinterface #39,  1           // InterfaceMethod org/apache/woden/xml/StringAttr.getString:()Ljava/lang/String;
     123: goto          127
     126: aconst_null
     127: areturn
     128: aconst_null
     129: areturn

  public java.lang.String getHttpContentEncodingDefault();
    Code:
       0: aload_0
       1: invokevirtual #12                 // Method getParent:()Lorg/apache/woden/wsdl20/WSDLComponent;
       4: checkcast     #23                 // class org/apache/woden/wsdl20/NestedComponent
       7: invokeinterface #24,  1           // InterfaceMethod org/apache/woden/wsdl20/NestedComponent.getParent:()Lorg/apache/woden/wsdl20/WSDLComponent;
      12: checkcast     #25                 // class org/apache/woden/wsdl20/Binding
      15: astore_1
      16: aload_1
      17: getstatic     #26                 // Field org/apache/woden/wsdl20/extensions/soap/SOAPConstants.NS_URI_SOAP:Ljava/net/URI;
      20: invokeinterface #27,  2           // InterfaceMethod org/apache/woden/wsdl20/Binding.getComponentExtensionContext:(Ljava/net/URI;)Lorg/apache/woden/wsdl20/extensions/ComponentExtensionContext;
      25: checkcast     #28                 // class org/apache/woden/wsdl20/extensions/soap/SOAPBindingExtensions
      28: astore_2
      29: aload_2
      30: invokeinterface #29,  1           // InterfaceMethod org/apache/woden/wsdl20/extensions/soap/SOAPBindingExtensions.getSoapVersion:()Ljava/lang/String;
      35: astore_3
      36: aload_2
      37: invokeinterface #30,  1           // InterfaceMethod org/apache/woden/wsdl20/extensions/soap/SOAPBindingExtensions.getSoapUnderlyingProtocol:()Ljava/net/URI;
      42: astore        4
      44: aload         4
      46: ifnonnull     51
      49: aconst_null
      50: areturn
      51: ldc           #31                 // String 1.2
      53: aload_3
      54: invokevirtual #7                  // Method java/lang/String.equals:(Ljava/lang/Object;)Z
      57: ifeq          71
      60: aload         4
      62: getstatic     #32                 // Field org/apache/woden/wsdl20/extensions/soap/SOAPConstants.PROTOCOL_URI_SOAP12_HTTP:Ljava/net/URI;
      65: invokevirtual #33                 // Method java/net/URI.equals:(Ljava/lang/Object;)Z
      68: ifne          91
      71: ldc           #34                 // String 1.1
      73: aload_3
      74: invokevirtual #7                  // Method java/lang/String.equals:(Ljava/lang/Object;)Z
      77: ifeq          128
      80: aload         4
      82: getstatic     #35                 // Field org/apache/woden/wsdl20/extensions/soap/SOAPConstants.PROTOCOL_URI_SOAP11_HTTP:Ljava/net/URI;
      85: invokevirtual #33                 // Method java/net/URI.equals:(Ljava/lang/Object;)Z
      88: ifeq          128
      91: aload_0
      92: invokevirtual #12                 // Method getParent:()Lorg/apache/woden/wsdl20/WSDLComponent;
      95: checkcast     #13                 // class org/apache/woden/wsdl20/xml/WSDLElement
      98: getstatic     #42                 // Field org/apache/woden/wsdl20/extensions/http/HTTPConstants.Q_ATTR_CONTENT_ENCODING_DEFAULT:Ljavax/xml/namespace/QName;
     101: invokeinterface #15,  2           // InterfaceMethod org/apache/woden/wsdl20/xml/WSDLElement.getExtensionAttribute:(Ljavax/xml/namespace/QName;)Lorg/apache/woden/xml/XMLAttr;
     106: checkcast     #37                 // class org/apache/woden/xml/StringAttr
     109: astore        5
     111: aload         5
     113: ifnull        126
     116: aload         5
     118: invokeinterface #39,  1           // InterfaceMethod org/apache/woden/xml/StringAttr.getString:()Ljava/lang/String;
     123: goto          127
     126: aconst_null
     127: areturn
     128: aconst_null
     129: areturn
}
