Compiled from "ConditionNode.java"
public class org.eclipse.milo.opcua.sdk.client.model.nodes.objects.ConditionNode extends org.eclipse.milo.opcua.sdk.client.model.nodes.objects.BaseEventNode implements org.eclipse.milo.opcua.sdk.client.model.types.objects.ConditionType {
  public org.eclipse.milo.opcua.sdk.client.model.nodes.objects.ConditionNode(org.eclipse.milo.opcua.sdk.client.OpcUaClient, org.eclipse.milo.opcua.stack.core.types.builtin.NodeId);
    Code:
       0: aload_0
       1: aload_1
       2: aload_2
       3: invokespecial #1                  // Method org/eclipse/milo/opcua/sdk/client/model/nodes/objects/BaseEventNode."<init>":(Lorg/eclipse/milo/opcua/sdk/client/OpcUaClient;Lorg/eclipse/milo/opcua/stack/core/types/builtin/NodeId;)V
       6: return

  public java.util.concurrent.CompletableFuture<org.eclipse.milo.opcua.sdk.client.model.nodes.variables.PropertyNode> conditionClassId();
    Code:
       0: aload_0
       1: getstatic     #2                  // Field org/eclipse/milo/opcua/sdk/client/model/types/objects/ConditionType.CONDITION_CLASS_ID:Lorg/eclipse/milo/opcua/sdk/core/model/Property;
       4: invokeinterface #3,  1            // InterfaceMethod org/eclipse/milo/opcua/sdk/core/model/Property.getBrowseName:()Lorg/eclipse/milo/opcua/stack/core/types/builtin/QualifiedName;
       9: invokevirtual #4                  // Method getPropertyNode:(Lorg/eclipse/milo/opcua/stack/core/types/builtin/QualifiedName;)Ljava/util/concurrent/CompletableFuture;
      12: areturn

  public java.util.concurrent.CompletableFuture<org.eclipse.milo.opcua.stack.core.types.builtin.NodeId> getConditionClassId();
    Code:
       0: aload_0
       1: getstatic     #2                  // Field org/eclipse/milo/opcua/sdk/client/model/types/objects/ConditionType.CONDITION_CLASS_ID:Lorg/eclipse/milo/opcua/sdk/core/model/Property;
       4: invokevirtual #5                  // Method getProperty:(Lorg/eclipse/milo/opcua/sdk/core/model/Property;)Ljava/util/concurrent/CompletableFuture;
       7: areturn

  public java.util.concurrent.CompletableFuture<org.eclipse.milo.opcua.stack.core.types.builtin.StatusCode> setConditionClassId(org.eclipse.milo.opcua.stack.core.types.builtin.NodeId);
    Code:
       0: aload_0
       1: getstatic     #2                  // Field org/eclipse/milo/opcua/sdk/client/model/types/objects/ConditionType.CONDITION_CLASS_ID:Lorg/eclipse/milo/opcua/sdk/core/model/Property;
       4: aload_1
       5: invokevirtual #6                  // Method setProperty:(Lorg/eclipse/milo/opcua/sdk/core/model/Property;Ljava/lang/Object;)Ljava/util/concurrent/CompletableFuture;
       8: areturn

  public java.util.concurrent.CompletableFuture<org.eclipse.milo.opcua.sdk.client.model.nodes.variables.PropertyNode> conditionClassName();
    Code:
       0: aload_0
       1: getstatic     #7                  // Field org/eclipse/milo/opcua/sdk/client/model/types/objects/ConditionType.CONDITION_CLASS_NAME:Lorg/eclipse/milo/opcua/sdk/core/model/Property;
       4: invokeinterface #3,  1            // InterfaceMethod org/eclipse/milo/opcua/sdk/core/model/Property.getBrowseName:()Lorg/eclipse/milo/opcua/stack/core/types/builtin/QualifiedName;
       9: invokevirtual #4                  // Method getPropertyNode:(Lorg/eclipse/milo/opcua/stack/core/types/builtin/QualifiedName;)Ljava/util/concurrent/CompletableFuture;
      12: areturn

  public java.util.concurrent.CompletableFuture<org.eclipse.milo.opcua.stack.core.types.builtin.LocalizedText> getConditionClassName();
    Code:
       0: aload_0
       1: getstatic     #7                  // Field org/eclipse/milo/opcua/sdk/client/model/types/objects/ConditionType.CONDITION_CLASS_NAME:Lorg/eclipse/milo/opcua/sdk/core/model/Property;
       4: invokevirtual #5                  // Method getProperty:(Lorg/eclipse/milo/opcua/sdk/core/model/Property;)Ljava/util/concurrent/CompletableFuture;
       7: areturn

  public java.util.concurrent.CompletableFuture<org.eclipse.milo.opcua.stack.core.types.builtin.StatusCode> setConditionClassName(org.eclipse.milo.opcua.stack.core.types.builtin.LocalizedText);
    Code:
       0: aload_0
       1: getstatic     #7                  // Field org/eclipse/milo/opcua/sdk/client/model/types/objects/ConditionType.CONDITION_CLASS_NAME:Lorg/eclipse/milo/opcua/sdk/core/model/Property;
       4: aload_1
       5: invokevirtual #6                  // Method setProperty:(Lorg/eclipse/milo/opcua/sdk/core/model/Property;Ljava/lang/Object;)Ljava/util/concurrent/CompletableFuture;
       8: areturn

  public java.util.concurrent.CompletableFuture<org.eclipse.milo.opcua.sdk.client.model.nodes.variables.PropertyNode> conditionName();
    Code:
       0: aload_0
       1: getstatic     #8                  // Field org/eclipse/milo/opcua/sdk/client/model/types/objects/ConditionType.CONDITION_NAME:Lorg/eclipse/milo/opcua/sdk/core/model/Property;
       4: invokeinterface #3,  1            // InterfaceMethod org/eclipse/milo/opcua/sdk/core/model/Property.getBrowseName:()Lorg/eclipse/milo/opcua/stack/core/types/builtin/QualifiedName;
       9: invokevirtual #4                  // Method getPropertyNode:(Lorg/eclipse/milo/opcua/stack/core/types/builtin/QualifiedName;)Ljava/util/concurrent/CompletableFuture;
      12: areturn

  public java.util.concurrent.CompletableFuture<java.lang.String> getConditionName();
    Code:
       0: aload_0
       1: getstatic     #8                  // Field org/eclipse/milo/opcua/sdk/client/model/types/objects/ConditionType.CONDITION_NAME:Lorg/eclipse/milo/opcua/sdk/core/model/Property;
       4: invokevirtual #5                  // Method getProperty:(Lorg/eclipse/milo/opcua/sdk/core/model/Property;)Ljava/util/concurrent/CompletableFuture;
       7: areturn

  public java.util.concurrent.CompletableFuture<org.eclipse.milo.opcua.stack.core.types.builtin.StatusCode> setConditionName(java.lang.String);
    Code:
       0: aload_0
       1: getstatic     #8                  // Field org/eclipse/milo/opcua/sdk/client/model/types/objects/ConditionType.CONDITION_NAME:Lorg/eclipse/milo/opcua/sdk/core/model/Property;
       4: aload_1
       5: invokevirtual #6                  // Method setProperty:(Lorg/eclipse/milo/opcua/sdk/core/model/Property;Ljava/lang/Object;)Ljava/util/concurrent/CompletableFuture;
       8: areturn

  public java.util.concurrent.CompletableFuture<org.eclipse.milo.opcua.sdk.client.model.nodes.variables.PropertyNode> branchId();
    Code:
       0: aload_0
       1: getstatic     #9                  // Field org/eclipse/milo/opcua/sdk/client/model/types/objects/ConditionType.BRANCH_ID:Lorg/eclipse/milo/opcua/sdk/core/model/Property;
       4: invokeinterface #3,  1            // InterfaceMethod org/eclipse/milo/opcua/sdk/core/model/Property.getBrowseName:()Lorg/eclipse/milo/opcua/stack/core/types/builtin/QualifiedName;
       9: invokevirtual #4                  // Method getPropertyNode:(Lorg/eclipse/milo/opcua/stack/core/types/builtin/QualifiedName;)Ljava/util/concurrent/CompletableFuture;
      12: areturn

  public java.util.concurrent.CompletableFuture<org.eclipse.milo.opcua.stack.core.types.builtin.NodeId> getBranchId();
    Code:
       0: aload_0
       1: getstatic     #9                  // Field org/eclipse/milo/opcua/sdk/client/model/types/objects/ConditionType.BRANCH_ID:Lorg/eclipse/milo/opcua/sdk/core/model/Property;
       4: invokevirtual #5                  // Method getProperty:(Lorg/eclipse/milo/opcua/sdk/core/model/Property;)Ljava/util/concurrent/CompletableFuture;
       7: areturn

  public java.util.concurrent.CompletableFuture<org.eclipse.milo.opcua.stack.core.types.builtin.StatusCode> setBranchId(org.eclipse.milo.opcua.stack.core.types.builtin.NodeId);
    Code:
       0: aload_0
       1: getstatic     #9                  // Field org/eclipse/milo/opcua/sdk/client/model/types/objects/ConditionType.BRANCH_ID:Lorg/eclipse/milo/opcua/sdk/core/model/Property;
       4: aload_1
       5: invokevirtual #6                  // Method setProperty:(Lorg/eclipse/milo/opcua/sdk/core/model/Property;Ljava/lang/Object;)Ljava/util/concurrent/CompletableFuture;
       8: areturn

  public java.util.concurrent.CompletableFuture<org.eclipse.milo.opcua.sdk.client.model.nodes.variables.PropertyNode> retain();
    Code:
       0: aload_0
       1: getstatic     #10                 // Field org/eclipse/milo/opcua/sdk/client/model/types/objects/ConditionType.RETAIN:Lorg/eclipse/milo/opcua/sdk/core/model/Property;
       4: invokeinterface #3,  1            // InterfaceMethod org/eclipse/milo/opcua/sdk/core/model/Property.getBrowseName:()Lorg/eclipse/milo/opcua/stack/core/types/builtin/QualifiedName;
       9: invokevirtual #4                  // Method getPropertyNode:(Lorg/eclipse/milo/opcua/stack/core/types/builtin/QualifiedName;)Ljava/util/concurrent/CompletableFuture;
      12: areturn

  public java.util.concurrent.CompletableFuture<java.lang.Boolean> getRetain();
    Code:
       0: aload_0
       1: getstatic     #10                 // Field org/eclipse/milo/opcua/sdk/client/model/types/objects/ConditionType.RETAIN:Lorg/eclipse/milo/opcua/sdk/core/model/Property;
       4: invokevirtual #5                  // Method getProperty:(Lorg/eclipse/milo/opcua/sdk/core/model/Property;)Ljava/util/concurrent/CompletableFuture;
       7: areturn

  public java.util.concurrent.CompletableFuture<org.eclipse.milo.opcua.stack.core.types.builtin.StatusCode> setRetain(java.lang.Boolean);
    Code:
       0: aload_0
       1: getstatic     #10                 // Field org/eclipse/milo/opcua/sdk/client/model/types/objects/ConditionType.RETAIN:Lorg/eclipse/milo/opcua/sdk/core/model/Property;
       4: aload_1
       5: invokevirtual #6                  // Method setProperty:(Lorg/eclipse/milo/opcua/sdk/core/model/Property;Ljava/lang/Object;)Ljava/util/concurrent/CompletableFuture;
       8: areturn

  public java.util.concurrent.CompletableFuture<org.eclipse.milo.opcua.sdk.client.model.nodes.variables.PropertyNode> clientUserId();
    Code:
       0: aload_0
       1: getstatic     #11                 // Field org/eclipse/milo/opcua/sdk/client/model/types/objects/ConditionType.CLIENT_USER_ID:Lorg/eclipse/milo/opcua/sdk/core/model/Property;
       4: invokeinterface #3,  1            // InterfaceMethod org/eclipse/milo/opcua/sdk/core/model/Property.getBrowseName:()Lorg/eclipse/milo/opcua/stack/core/types/builtin/QualifiedName;
       9: invokevirtual #4                  // Method getPropertyNode:(Lorg/eclipse/milo/opcua/stack/core/types/builtin/QualifiedName;)Ljava/util/concurrent/CompletableFuture;
      12: areturn

  public java.util.concurrent.CompletableFuture<java.lang.String> getClientUserId();
    Code:
       0: aload_0
       1: getstatic     #11                 // Field org/eclipse/milo/opcua/sdk/client/model/types/objects/ConditionType.CLIENT_USER_ID:Lorg/eclipse/milo/opcua/sdk/core/model/Property;
       4: invokevirtual #5                  // Method getProperty:(Lorg/eclipse/milo/opcua/sdk/core/model/Property;)Ljava/util/concurrent/CompletableFuture;
       7: areturn

  public java.util.concurrent.CompletableFuture<org.eclipse.milo.opcua.stack.core.types.builtin.StatusCode> setClientUserId(java.lang.String);
    Code:
       0: aload_0
       1: getstatic     #11                 // Field org/eclipse/milo/opcua/sdk/client/model/types/objects/ConditionType.CLIENT_USER_ID:Lorg/eclipse/milo/opcua/sdk/core/model/Property;
       4: aload_1
       5: invokevirtual #6                  // Method setProperty:(Lorg/eclipse/milo/opcua/sdk/core/model/Property;Ljava/lang/Object;)Ljava/util/concurrent/CompletableFuture;
       8: areturn

  public java.util.concurrent.CompletableFuture<org.eclipse.milo.opcua.sdk.client.model.nodes.variables.TwoStateVariableNode> enabledState();
    Code:
       0: aload_0
       1: ldc           #12                 // String 0:EnabledState
       3: invokestatic  #13                 // Method org/eclipse/milo/opcua/stack/core/types/builtin/QualifiedName.parse:(Ljava/lang/String;)Lorg/eclipse/milo/opcua/stack/core/types/builtin/QualifiedName;
       6: invokevirtual #14                 // Method getVariableComponent:(Lorg/eclipse/milo/opcua/stack/core/types/builtin/QualifiedName;)Ljava/util/concurrent/CompletableFuture;
       9: ldc           #15                 // class org/eclipse/milo/opcua/sdk/client/model/nodes/variables/TwoStateVariableNode
      11: dup
      12: invokevirtual #16                 // Method java/lang/Object.getClass:()Ljava/lang/Class;
      15: pop
      16: invokedynamic #17,  0             // InvokeDynamic #0:apply:(Ljava/lang/Class;)Ljava/util/function/Function;
      21: invokevirtual #18                 // Method java/util/concurrent/CompletableFuture.thenApply:(Ljava/util/function/Function;)Ljava/util/concurrent/CompletableFuture;
      24: areturn

  public java.util.concurrent.CompletableFuture<org.eclipse.milo.opcua.stack.core.types.builtin.LocalizedText> getEnabledState();
    Code:
       0: aload_0
       1: invokevirtual #19                 // Method enabledState:()Ljava/util/concurrent/CompletableFuture;
       4: invokedynamic #20,  0             // InvokeDynamic #1:apply:()Ljava/util/function/Function;
       9: invokevirtual #21                 // Method java/util/concurrent/CompletableFuture.thenCompose:(Ljava/util/function/Function;)Ljava/util/concurrent/CompletableFuture;
      12: invokedynamic #22,  0             // InvokeDynamic #2:apply:()Ljava/util/function/Function;
      17: invokevirtual #18                 // Method java/util/concurrent/CompletableFuture.thenApply:(Ljava/util/function/Function;)Ljava/util/concurrent/CompletableFuture;
      20: areturn

  public java.util.concurrent.CompletableFuture<org.eclipse.milo.opcua.stack.core.types.builtin.StatusCode> setEnabledState(org.eclipse.milo.opcua.stack.core.types.builtin.LocalizedText);
    Code:
       0: aload_0
       1: invokevirtual #19                 // Method enabledState:()Ljava/util/concurrent/CompletableFuture;
       4: aload_1
       5: invokedynamic #23,  0             // InvokeDynamic #3:apply:(Lorg/eclipse/milo/opcua/stack/core/types/builtin/LocalizedText;)Ljava/util/function/Function;
      10: invokevirtual #21                 // Method java/util/concurrent/CompletableFuture.thenCompose:(Ljava/util/function/Function;)Ljava/util/concurrent/CompletableFuture;
      13: areturn

  public java.util.concurrent.CompletableFuture<org.eclipse.milo.opcua.sdk.client.model.nodes.variables.ConditionVariableNode> quality();
    Code:
       0: aload_0
       1: ldc           #24                 // String 0:Quality
       3: invokestatic  #13                 // Method org/eclipse/milo/opcua/stack/core/types/builtin/QualifiedName.parse:(Ljava/lang/String;)Lorg/eclipse/milo/opcua/stack/core/types/builtin/QualifiedName;
       6: invokevirtual #14                 // Method getVariableComponent:(Lorg/eclipse/milo/opcua/stack/core/types/builtin/QualifiedName;)Ljava/util/concurrent/CompletableFuture;
       9: ldc           #25                 // class org/eclipse/milo/opcua/sdk/client/model/nodes/variables/ConditionVariableNode
      11: dup
      12: invokevirtual #16                 // Method java/lang/Object.getClass:()Ljava/lang/Class;
      15: pop
      16: invokedynamic #26,  0             // InvokeDynamic #4:apply:(Ljava/lang/Class;)Ljava/util/function/Function;
      21: invokevirtual #18                 // Method java/util/concurrent/CompletableFuture.thenApply:(Ljava/util/function/Function;)Ljava/util/concurrent/CompletableFuture;
      24: areturn

  public java.util.concurrent.CompletableFuture<org.eclipse.milo.opcua.stack.core.types.builtin.StatusCode> getQuality();
    Code:
       0: aload_0
       1: invokevirtual #27                 // Method quality:()Ljava/util/concurrent/CompletableFuture;
       4: invokedynamic #28,  0             // InvokeDynamic #5:apply:()Ljava/util/function/Function;
       9: invokevirtual #21                 // Method java/util/concurrent/CompletableFuture.thenCompose:(Ljava/util/function/Function;)Ljava/util/concurrent/CompletableFuture;
      12: invokedynamic #29,  0             // InvokeDynamic #6:apply:()Ljava/util/function/Function;
      17: invokevirtual #18                 // Method java/util/concurrent/CompletableFuture.thenApply:(Ljava/util/function/Function;)Ljava/util/concurrent/CompletableFuture;
      20: areturn

  public java.util.concurrent.CompletableFuture<org.eclipse.milo.opcua.stack.core.types.builtin.StatusCode> setQuality(org.eclipse.milo.opcua.stack.core.types.builtin.StatusCode);
    Code:
       0: aload_0
       1: invokevirtual #27                 // Method quality:()Ljava/util/concurrent/CompletableFuture;
       4: aload_1
       5: invokedynamic #30,  0             // InvokeDynamic #7:apply:(Lorg/eclipse/milo/opcua/stack/core/types/builtin/StatusCode;)Ljava/util/function/Function;
      10: invokevirtual #21                 // Method java/util/concurrent/CompletableFuture.thenCompose:(Ljava/util/function/Function;)Ljava/util/concurrent/CompletableFuture;
      13: areturn

  public java.util.concurrent.CompletableFuture<org.eclipse.milo.opcua.sdk.client.model.nodes.variables.ConditionVariableNode> lastSeverity();
    Code:
       0: aload_0
       1: ldc           #31                 // String 0:LastSeverity
       3: invokestatic  #13                 // Method org/eclipse/milo/opcua/stack/core/types/builtin/QualifiedName.parse:(Ljava/lang/String;)Lorg/eclipse/milo/opcua/stack/core/types/builtin/QualifiedName;
       6: invokevirtual #14                 // Method getVariableComponent:(Lorg/eclipse/milo/opcua/stack/core/types/builtin/QualifiedName;)Ljava/util/concurrent/CompletableFuture;
       9: ldc           #25                 // class org/eclipse/milo/opcua/sdk/client/model/nodes/variables/ConditionVariableNode
      11: dup
      12: invokevirtual #16                 // Method java/lang/Object.getClass:()Ljava/lang/Class;
      15: pop
      16: invokedynamic #26,  0             // InvokeDynamic #4:apply:(Ljava/lang/Class;)Ljava/util/function/Function;
      21: invokevirtual #18                 // Method java/util/concurrent/CompletableFuture.thenApply:(Ljava/util/function/Function;)Ljava/util/concurrent/CompletableFuture;
      24: areturn

  public java.util.concurrent.CompletableFuture<org.eclipse.milo.opcua.stack.core.types.builtin.unsigned.UShort> getLastSeverity();
    Code:
       0: aload_0
       1: invokevirtual #32                 // Method lastSeverity:()Ljava/util/concurrent/CompletableFuture;
       4: invokedynamic #28,  0             // InvokeDynamic #5:apply:()Ljava/util/function/Function;
       9: invokevirtual #21                 // Method java/util/concurrent/CompletableFuture.thenCompose:(Ljava/util/function/Function;)Ljava/util/concurrent/CompletableFuture;
      12: invokedynamic #33,  0             // InvokeDynamic #8:apply:()Ljava/util/function/Function;
      17: invokevirtual #18                 // Method java/util/concurrent/CompletableFuture.thenApply:(Ljava/util/function/Function;)Ljava/util/concurrent/CompletableFuture;
      20: areturn

  public java.util.concurrent.CompletableFuture<org.eclipse.milo.opcua.stack.core.types.builtin.StatusCode> setLastSeverity(org.eclipse.milo.opcua.stack.core.types.builtin.unsigned.UShort);
    Code:
       0: aload_0
       1: invokevirtual #32                 // Method lastSeverity:()Ljava/util/concurrent/CompletableFuture;
       4: aload_1
       5: invokedynamic #34,  0             // InvokeDynamic #9:apply:(Lorg/eclipse/milo/opcua/stack/core/types/builtin/unsigned/UShort;)Ljava/util/function/Function;
      10: invokevirtual #21                 // Method java/util/concurrent/CompletableFuture.thenCompose:(Ljava/util/function/Function;)Ljava/util/concurrent/CompletableFuture;
      13: areturn

  public java.util.concurrent.CompletableFuture<org.eclipse.milo.opcua.sdk.client.model.nodes.variables.ConditionVariableNode> comment();
    Code:
       0: aload_0
       1: ldc           #35                 // String 0:Comment
       3: invokestatic  #13                 // Method org/eclipse/milo/opcua/stack/core/types/builtin/QualifiedName.parse:(Ljava/lang/String;)Lorg/eclipse/milo/opcua/stack/core/types/builtin/QualifiedName;
       6: invokevirtual #14                 // Method getVariableComponent:(Lorg/eclipse/milo/opcua/stack/core/types/builtin/QualifiedName;)Ljava/util/concurrent/CompletableFuture;
       9: ldc           #25                 // class org/eclipse/milo/opcua/sdk/client/model/nodes/variables/ConditionVariableNode
      11: dup
      12: invokevirtual #16                 // Method java/lang/Object.getClass:()Ljava/lang/Class;
      15: pop
      16: invokedynamic #26,  0             // InvokeDynamic #4:apply:(Ljava/lang/Class;)Ljava/util/function/Function;
      21: invokevirtual #18                 // Method java/util/concurrent/CompletableFuture.thenApply:(Ljava/util/function/Function;)Ljava/util/concurrent/CompletableFuture;
      24: areturn

  public java.util.concurrent.CompletableFuture<org.eclipse.milo.opcua.stack.core.types.builtin.LocalizedText> getComment();
    Code:
       0: aload_0
       1: invokevirtual #36                 // Method comment:()Ljava/util/concurrent/CompletableFuture;
       4: invokedynamic #28,  0             // InvokeDynamic #5:apply:()Ljava/util/function/Function;
       9: invokevirtual #21                 // Method java/util/concurrent/CompletableFuture.thenCompose:(Ljava/util/function/Function;)Ljava/util/concurrent/CompletableFuture;
      12: invokedynamic #37,  0             // InvokeDynamic #10:apply:()Ljava/util/function/Function;
      17: invokevirtual #18                 // Method java/util/concurrent/CompletableFuture.thenApply:(Ljava/util/function/Function;)Ljava/util/concurrent/CompletableFuture;
      20: areturn

  public java.util.concurrent.CompletableFuture<org.eclipse.milo.opcua.stack.core.types.builtin.StatusCode> setComment(org.eclipse.milo.opcua.stack.core.types.builtin.LocalizedText);
    Code:
       0: aload_0
       1: invokevirtual #36                 // Method comment:()Ljava/util/concurrent/CompletableFuture;
       4: aload_1
       5: invokedynamic #38,  0             // InvokeDynamic #11:apply:(Lorg/eclipse/milo/opcua/stack/core/types/builtin/LocalizedText;)Ljava/util/function/Function;
      10: invokevirtual #21                 // Method java/util/concurrent/CompletableFuture.thenCompose:(Ljava/util/function/Function;)Ljava/util/concurrent/CompletableFuture;
      13: areturn

  private static java.util.concurrent.CompletionStage lambda$setComment$7(org.eclipse.milo.opcua.stack.core.types.builtin.LocalizedText, org.eclipse.milo.opcua.sdk.client.model.nodes.variables.ConditionVariableNode);
    Code:
       0: aload_1
       1: aload_0
       2: invokevirtual #39                 // Method org/eclipse/milo/opcua/sdk/client/model/nodes/variables/ConditionVariableNode.setValue:(Ljava/lang/Object;)Ljava/util/concurrent/CompletableFuture;
       5: areturn

  private static org.eclipse.milo.opcua.stack.core.types.builtin.LocalizedText lambda$getComment$6(java.lang.Object);
    Code:
       0: aload_0
       1: ldc           #40                 // class org/eclipse/milo/opcua/stack/core/types/builtin/LocalizedText
       3: invokestatic  #41                 // Method cast:(Ljava/lang/Object;Ljava/lang/Class;)Ljava/lang/Object;
       6: checkcast     #40                 // class org/eclipse/milo/opcua/stack/core/types/builtin/LocalizedText
       9: areturn

  private static java.util.concurrent.CompletionStage lambda$setLastSeverity$5(org.eclipse.milo.opcua.stack.core.types.builtin.unsigned.UShort, org.eclipse.milo.opcua.sdk.client.model.nodes.variables.ConditionVariableNode);
    Code:
       0: aload_1
       1: aload_0
       2: invokevirtual #39                 // Method org/eclipse/milo/opcua/sdk/client/model/nodes/variables/ConditionVariableNode.setValue:(Ljava/lang/Object;)Ljava/util/concurrent/CompletableFuture;
       5: areturn

  private static org.eclipse.milo.opcua.stack.core.types.builtin.unsigned.UShort lambda$getLastSeverity$4(java.lang.Object);
    Code:
       0: aload_0
       1: ldc           #42                 // class org/eclipse/milo/opcua/stack/core/types/builtin/unsigned/UShort
       3: invokestatic  #41                 // Method cast:(Ljava/lang/Object;Ljava/lang/Class;)Ljava/lang/Object;
       6: checkcast     #42                 // class org/eclipse/milo/opcua/stack/core/types/builtin/unsigned/UShort
       9: areturn

  private static java.util.concurrent.CompletionStage lambda$setQuality$3(org.eclipse.milo.opcua.stack.core.types.builtin.StatusCode, org.eclipse.milo.opcua.sdk.client.model.nodes.variables.ConditionVariableNode);
    Code:
       0: aload_1
       1: aload_0
       2: invokevirtual #39                 // Method org/eclipse/milo/opcua/sdk/client/model/nodes/variables/ConditionVariableNode.setValue:(Ljava/lang/Object;)Ljava/util/concurrent/CompletableFuture;
       5: areturn

  private static org.eclipse.milo.opcua.stack.core.types.builtin.StatusCode lambda$getQuality$2(java.lang.Object);
    Code:
       0: aload_0
       1: ldc           #43                 // class org/eclipse/milo/opcua/stack/core/types/builtin/StatusCode
       3: invokestatic  #41                 // Method cast:(Ljava/lang/Object;Ljava/lang/Class;)Ljava/lang/Object;
       6: checkcast     #43                 // class org/eclipse/milo/opcua/stack/core/types/builtin/StatusCode
       9: areturn

  private static java.util.concurrent.CompletionStage lambda$setEnabledState$1(org.eclipse.milo.opcua.stack.core.types.builtin.LocalizedText, org.eclipse.milo.opcua.sdk.client.model.nodes.variables.TwoStateVariableNode);
    Code:
       0: aload_1
       1: aload_0
       2: invokevirtual #44                 // Method org/eclipse/milo/opcua/sdk/client/model/nodes/variables/TwoStateVariableNode.setValue:(Ljava/lang/Object;)Ljava/util/concurrent/CompletableFuture;
       5: areturn

  private static org.eclipse.milo.opcua.stack.core.types.builtin.LocalizedText lambda$getEnabledState$0(java.lang.Object);
    Code:
       0: aload_0
       1: ldc           #40                 // class org/eclipse/milo/opcua/stack/core/types/builtin/LocalizedText
       3: invokestatic  #41                 // Method cast:(Ljava/lang/Object;Ljava/lang/Class;)Ljava/lang/Object;
       6: checkcast     #40                 // class org/eclipse/milo/opcua/stack/core/types/builtin/LocalizedText
       9: areturn
}
