Compiled from "ServerCapabilitiesNode.java"
public class org.eclipse.milo.opcua.sdk.client.model.nodes.objects.ServerCapabilitiesNode extends org.eclipse.milo.opcua.sdk.client.model.nodes.objects.BaseObjectNode implements org.eclipse.milo.opcua.sdk.client.model.types.objects.ServerCapabilitiesType {
  public org.eclipse.milo.opcua.sdk.client.model.nodes.objects.ServerCapabilitiesNode(org.eclipse.milo.opcua.sdk.client.OpcUaClient, org.eclipse.milo.opcua.stack.core.types.builtin.NodeId);
    Code:
       0: aload_0
       1: aload_1
       2: aload_2
       3: invokespecial #1                  // Method org/eclipse/milo/opcua/sdk/client/model/nodes/objects/BaseObjectNode."<init>":(Lorg/eclipse/milo/opcua/sdk/client/OpcUaClient;Lorg/eclipse/milo/opcua/stack/core/types/builtin/NodeId;)V
       6: return

  public java.util.concurrent.CompletableFuture<org.eclipse.milo.opcua.sdk.client.model.nodes.variables.PropertyNode> serverProfileArray();
    Code:
       0: aload_0
       1: getstatic     #2                  // Field org/eclipse/milo/opcua/sdk/client/model/types/objects/ServerCapabilitiesType.SERVER_PROFILE_ARRAY:Lorg/eclipse/milo/opcua/sdk/core/model/Property;
       4: invokeinterface #3,  1            // InterfaceMethod org/eclipse/milo/opcua/sdk/core/model/Property.getBrowseName:()Lorg/eclipse/milo/opcua/stack/core/types/builtin/QualifiedName;
       9: invokevirtual #4                  // Method getPropertyNode:(Lorg/eclipse/milo/opcua/stack/core/types/builtin/QualifiedName;)Ljava/util/concurrent/CompletableFuture;
      12: areturn

  public java.util.concurrent.CompletableFuture<java.lang.String[]> getServerProfileArray();
    Code:
       0: aload_0
       1: getstatic     #2                  // Field org/eclipse/milo/opcua/sdk/client/model/types/objects/ServerCapabilitiesType.SERVER_PROFILE_ARRAY:Lorg/eclipse/milo/opcua/sdk/core/model/Property;
       4: invokevirtual #5                  // Method getProperty:(Lorg/eclipse/milo/opcua/sdk/core/model/Property;)Ljava/util/concurrent/CompletableFuture;
       7: areturn

  public java.util.concurrent.CompletableFuture<org.eclipse.milo.opcua.stack.core.types.builtin.StatusCode> setServerProfileArray(java.lang.String[]);
    Code:
       0: aload_0
       1: getstatic     #2                  // Field org/eclipse/milo/opcua/sdk/client/model/types/objects/ServerCapabilitiesType.SERVER_PROFILE_ARRAY:Lorg/eclipse/milo/opcua/sdk/core/model/Property;
       4: aload_1
       5: invokevirtual #6                  // Method setProperty:(Lorg/eclipse/milo/opcua/sdk/core/model/Property;Ljava/lang/Object;)Ljava/util/concurrent/CompletableFuture;
       8: areturn

  public java.util.concurrent.CompletableFuture<org.eclipse.milo.opcua.sdk.client.model.nodes.variables.PropertyNode> localeIdArray();
    Code:
       0: aload_0
       1: getstatic     #7                  // Field org/eclipse/milo/opcua/sdk/client/model/types/objects/ServerCapabilitiesType.LOCALE_ID_ARRAY:Lorg/eclipse/milo/opcua/sdk/core/model/Property;
       4: invokeinterface #3,  1            // InterfaceMethod org/eclipse/milo/opcua/sdk/core/model/Property.getBrowseName:()Lorg/eclipse/milo/opcua/stack/core/types/builtin/QualifiedName;
       9: invokevirtual #4                  // Method getPropertyNode:(Lorg/eclipse/milo/opcua/stack/core/types/builtin/QualifiedName;)Ljava/util/concurrent/CompletableFuture;
      12: areturn

  public java.util.concurrent.CompletableFuture<java.lang.String[]> getLocaleIdArray();
    Code:
       0: aload_0
       1: getstatic     #7                  // Field org/eclipse/milo/opcua/sdk/client/model/types/objects/ServerCapabilitiesType.LOCALE_ID_ARRAY:Lorg/eclipse/milo/opcua/sdk/core/model/Property;
       4: invokevirtual #5                  // Method getProperty:(Lorg/eclipse/milo/opcua/sdk/core/model/Property;)Ljava/util/concurrent/CompletableFuture;
       7: areturn

  public java.util.concurrent.CompletableFuture<org.eclipse.milo.opcua.stack.core.types.builtin.StatusCode> setLocaleIdArray(java.lang.String[]);
    Code:
       0: aload_0
       1: getstatic     #7                  // Field org/eclipse/milo/opcua/sdk/client/model/types/objects/ServerCapabilitiesType.LOCALE_ID_ARRAY:Lorg/eclipse/milo/opcua/sdk/core/model/Property;
       4: aload_1
       5: invokevirtual #6                  // Method setProperty:(Lorg/eclipse/milo/opcua/sdk/core/model/Property;Ljava/lang/Object;)Ljava/util/concurrent/CompletableFuture;
       8: areturn

  public java.util.concurrent.CompletableFuture<org.eclipse.milo.opcua.sdk.client.model.nodes.variables.PropertyNode> minSupportedSampleRate();
    Code:
       0: aload_0
       1: getstatic     #8                  // Field org/eclipse/milo/opcua/sdk/client/model/types/objects/ServerCapabilitiesType.MIN_SUPPORTED_SAMPLE_RATE:Lorg/eclipse/milo/opcua/sdk/core/model/Property;
       4: invokeinterface #3,  1            // InterfaceMethod org/eclipse/milo/opcua/sdk/core/model/Property.getBrowseName:()Lorg/eclipse/milo/opcua/stack/core/types/builtin/QualifiedName;
       9: invokevirtual #4                  // Method getPropertyNode:(Lorg/eclipse/milo/opcua/stack/core/types/builtin/QualifiedName;)Ljava/util/concurrent/CompletableFuture;
      12: areturn

  public java.util.concurrent.CompletableFuture<java.lang.Double> getMinSupportedSampleRate();
    Code:
       0: aload_0
       1: getstatic     #8                  // Field org/eclipse/milo/opcua/sdk/client/model/types/objects/ServerCapabilitiesType.MIN_SUPPORTED_SAMPLE_RATE:Lorg/eclipse/milo/opcua/sdk/core/model/Property;
       4: invokevirtual #5                  // Method getProperty:(Lorg/eclipse/milo/opcua/sdk/core/model/Property;)Ljava/util/concurrent/CompletableFuture;
       7: areturn

  public java.util.concurrent.CompletableFuture<org.eclipse.milo.opcua.stack.core.types.builtin.StatusCode> setMinSupportedSampleRate(java.lang.Double);
    Code:
       0: aload_0
       1: getstatic     #8                  // Field org/eclipse/milo/opcua/sdk/client/model/types/objects/ServerCapabilitiesType.MIN_SUPPORTED_SAMPLE_RATE:Lorg/eclipse/milo/opcua/sdk/core/model/Property;
       4: aload_1
       5: invokevirtual #6                  // Method setProperty:(Lorg/eclipse/milo/opcua/sdk/core/model/Property;Ljava/lang/Object;)Ljava/util/concurrent/CompletableFuture;
       8: areturn

  public java.util.concurrent.CompletableFuture<org.eclipse.milo.opcua.sdk.client.model.nodes.variables.PropertyNode> maxBrowseContinuationPoints();
    Code:
       0: aload_0
       1: getstatic     #9                  // Field org/eclipse/milo/opcua/sdk/client/model/types/objects/ServerCapabilitiesType.MAX_BROWSE_CONTINUATION_POINTS:Lorg/eclipse/milo/opcua/sdk/core/model/Property;
       4: invokeinterface #3,  1            // InterfaceMethod org/eclipse/milo/opcua/sdk/core/model/Property.getBrowseName:()Lorg/eclipse/milo/opcua/stack/core/types/builtin/QualifiedName;
       9: invokevirtual #4                  // Method getPropertyNode:(Lorg/eclipse/milo/opcua/stack/core/types/builtin/QualifiedName;)Ljava/util/concurrent/CompletableFuture;
      12: areturn

  public java.util.concurrent.CompletableFuture<org.eclipse.milo.opcua.stack.core.types.builtin.unsigned.UShort> getMaxBrowseContinuationPoints();
    Code:
       0: aload_0
       1: getstatic     #9                  // Field org/eclipse/milo/opcua/sdk/client/model/types/objects/ServerCapabilitiesType.MAX_BROWSE_CONTINUATION_POINTS:Lorg/eclipse/milo/opcua/sdk/core/model/Property;
       4: invokevirtual #5                  // Method getProperty:(Lorg/eclipse/milo/opcua/sdk/core/model/Property;)Ljava/util/concurrent/CompletableFuture;
       7: areturn

  public java.util.concurrent.CompletableFuture<org.eclipse.milo.opcua.stack.core.types.builtin.StatusCode> setMaxBrowseContinuationPoints(org.eclipse.milo.opcua.stack.core.types.builtin.unsigned.UShort);
    Code:
       0: aload_0
       1: getstatic     #9                  // Field org/eclipse/milo/opcua/sdk/client/model/types/objects/ServerCapabilitiesType.MAX_BROWSE_CONTINUATION_POINTS:Lorg/eclipse/milo/opcua/sdk/core/model/Property;
       4: aload_1
       5: invokevirtual #6                  // Method setProperty:(Lorg/eclipse/milo/opcua/sdk/core/model/Property;Ljava/lang/Object;)Ljava/util/concurrent/CompletableFuture;
       8: areturn

  public java.util.concurrent.CompletableFuture<org.eclipse.milo.opcua.sdk.client.model.nodes.variables.PropertyNode> maxQueryContinuationPoints();
    Code:
       0: aload_0
       1: getstatic     #10                 // Field org/eclipse/milo/opcua/sdk/client/model/types/objects/ServerCapabilitiesType.MAX_QUERY_CONTINUATION_POINTS:Lorg/eclipse/milo/opcua/sdk/core/model/Property;
       4: invokeinterface #3,  1            // InterfaceMethod org/eclipse/milo/opcua/sdk/core/model/Property.getBrowseName:()Lorg/eclipse/milo/opcua/stack/core/types/builtin/QualifiedName;
       9: invokevirtual #4                  // Method getPropertyNode:(Lorg/eclipse/milo/opcua/stack/core/types/builtin/QualifiedName;)Ljava/util/concurrent/CompletableFuture;
      12: areturn

  public java.util.concurrent.CompletableFuture<org.eclipse.milo.opcua.stack.core.types.builtin.unsigned.UShort> getMaxQueryContinuationPoints();
    Code:
       0: aload_0
       1: getstatic     #10                 // Field org/eclipse/milo/opcua/sdk/client/model/types/objects/ServerCapabilitiesType.MAX_QUERY_CONTINUATION_POINTS:Lorg/eclipse/milo/opcua/sdk/core/model/Property;
       4: invokevirtual #5                  // Method getProperty:(Lorg/eclipse/milo/opcua/sdk/core/model/Property;)Ljava/util/concurrent/CompletableFuture;
       7: areturn

  public java.util.concurrent.CompletableFuture<org.eclipse.milo.opcua.stack.core.types.builtin.StatusCode> setMaxQueryContinuationPoints(org.eclipse.milo.opcua.stack.core.types.builtin.unsigned.UShort);
    Code:
       0: aload_0
       1: getstatic     #10                 // Field org/eclipse/milo/opcua/sdk/client/model/types/objects/ServerCapabilitiesType.MAX_QUERY_CONTINUATION_POINTS:Lorg/eclipse/milo/opcua/sdk/core/model/Property;
       4: aload_1
       5: invokevirtual #6                  // Method setProperty:(Lorg/eclipse/milo/opcua/sdk/core/model/Property;Ljava/lang/Object;)Ljava/util/concurrent/CompletableFuture;
       8: areturn

  public java.util.concurrent.CompletableFuture<org.eclipse.milo.opcua.sdk.client.model.nodes.variables.PropertyNode> maxHistoryContinuationPoints();
    Code:
       0: aload_0
       1: getstatic     #11                 // Field org/eclipse/milo/opcua/sdk/client/model/types/objects/ServerCapabilitiesType.MAX_HISTORY_CONTINUATION_POINTS:Lorg/eclipse/milo/opcua/sdk/core/model/Property;
       4: invokeinterface #3,  1            // InterfaceMethod org/eclipse/milo/opcua/sdk/core/model/Property.getBrowseName:()Lorg/eclipse/milo/opcua/stack/core/types/builtin/QualifiedName;
       9: invokevirtual #4                  // Method getPropertyNode:(Lorg/eclipse/milo/opcua/stack/core/types/builtin/QualifiedName;)Ljava/util/concurrent/CompletableFuture;
      12: areturn

  public java.util.concurrent.CompletableFuture<org.eclipse.milo.opcua.stack.core.types.builtin.unsigned.UShort> getMaxHistoryContinuationPoints();
    Code:
       0: aload_0
       1: getstatic     #11                 // Field org/eclipse/milo/opcua/sdk/client/model/types/objects/ServerCapabilitiesType.MAX_HISTORY_CONTINUATION_POINTS:Lorg/eclipse/milo/opcua/sdk/core/model/Property;
       4: invokevirtual #5                  // Method getProperty:(Lorg/eclipse/milo/opcua/sdk/core/model/Property;)Ljava/util/concurrent/CompletableFuture;
       7: areturn

  public java.util.concurrent.CompletableFuture<org.eclipse.milo.opcua.stack.core.types.builtin.StatusCode> setMaxHistoryContinuationPoints(org.eclipse.milo.opcua.stack.core.types.builtin.unsigned.UShort);
    Code:
       0: aload_0
       1: getstatic     #11                 // Field org/eclipse/milo/opcua/sdk/client/model/types/objects/ServerCapabilitiesType.MAX_HISTORY_CONTINUATION_POINTS:Lorg/eclipse/milo/opcua/sdk/core/model/Property;
       4: aload_1
       5: invokevirtual #6                  // Method setProperty:(Lorg/eclipse/milo/opcua/sdk/core/model/Property;Ljava/lang/Object;)Ljava/util/concurrent/CompletableFuture;
       8: areturn

  public java.util.concurrent.CompletableFuture<org.eclipse.milo.opcua.sdk.client.model.nodes.variables.PropertyNode> softwareCertificates();
    Code:
       0: aload_0
       1: getstatic     #12                 // Field org/eclipse/milo/opcua/sdk/client/model/types/objects/ServerCapabilitiesType.SOFTWARE_CERTIFICATES:Lorg/eclipse/milo/opcua/sdk/core/model/Property;
       4: invokeinterface #3,  1            // InterfaceMethod org/eclipse/milo/opcua/sdk/core/model/Property.getBrowseName:()Lorg/eclipse/milo/opcua/stack/core/types/builtin/QualifiedName;
       9: invokevirtual #4                  // Method getPropertyNode:(Lorg/eclipse/milo/opcua/stack/core/types/builtin/QualifiedName;)Ljava/util/concurrent/CompletableFuture;
      12: areturn

  public java.util.concurrent.CompletableFuture<org.eclipse.milo.opcua.stack.core.types.structured.SignedSoftwareCertificate[]> getSoftwareCertificates();
    Code:
       0: aload_0
       1: getstatic     #12                 // Field org/eclipse/milo/opcua/sdk/client/model/types/objects/ServerCapabilitiesType.SOFTWARE_CERTIFICATES:Lorg/eclipse/milo/opcua/sdk/core/model/Property;
       4: invokevirtual #5                  // Method getProperty:(Lorg/eclipse/milo/opcua/sdk/core/model/Property;)Ljava/util/concurrent/CompletableFuture;
       7: areturn

  public java.util.concurrent.CompletableFuture<org.eclipse.milo.opcua.stack.core.types.builtin.StatusCode> setSoftwareCertificates(org.eclipse.milo.opcua.stack.core.types.structured.SignedSoftwareCertificate[]);
    Code:
       0: aload_0
       1: getstatic     #12                 // Field org/eclipse/milo/opcua/sdk/client/model/types/objects/ServerCapabilitiesType.SOFTWARE_CERTIFICATES:Lorg/eclipse/milo/opcua/sdk/core/model/Property;
       4: aload_1
       5: invokevirtual #6                  // Method setProperty:(Lorg/eclipse/milo/opcua/sdk/core/model/Property;Ljava/lang/Object;)Ljava/util/concurrent/CompletableFuture;
       8: areturn

  public java.util.concurrent.CompletableFuture<org.eclipse.milo.opcua.sdk.client.model.nodes.variables.PropertyNode> maxArrayLength();
    Code:
       0: aload_0
       1: getstatic     #13                 // Field org/eclipse/milo/opcua/sdk/client/model/types/objects/ServerCapabilitiesType.MAX_ARRAY_LENGTH:Lorg/eclipse/milo/opcua/sdk/core/model/Property;
       4: invokeinterface #3,  1            // InterfaceMethod org/eclipse/milo/opcua/sdk/core/model/Property.getBrowseName:()Lorg/eclipse/milo/opcua/stack/core/types/builtin/QualifiedName;
       9: invokevirtual #4                  // Method getPropertyNode:(Lorg/eclipse/milo/opcua/stack/core/types/builtin/QualifiedName;)Ljava/util/concurrent/CompletableFuture;
      12: areturn

  public java.util.concurrent.CompletableFuture<org.eclipse.milo.opcua.stack.core.types.builtin.unsigned.UInteger> getMaxArrayLength();
    Code:
       0: aload_0
       1: getstatic     #13                 // Field org/eclipse/milo/opcua/sdk/client/model/types/objects/ServerCapabilitiesType.MAX_ARRAY_LENGTH:Lorg/eclipse/milo/opcua/sdk/core/model/Property;
       4: invokevirtual #5                  // Method getProperty:(Lorg/eclipse/milo/opcua/sdk/core/model/Property;)Ljava/util/concurrent/CompletableFuture;
       7: areturn

  public java.util.concurrent.CompletableFuture<org.eclipse.milo.opcua.stack.core.types.builtin.StatusCode> setMaxArrayLength(org.eclipse.milo.opcua.stack.core.types.builtin.unsigned.UInteger);
    Code:
       0: aload_0
       1: getstatic     #13                 // Field org/eclipse/milo/opcua/sdk/client/model/types/objects/ServerCapabilitiesType.MAX_ARRAY_LENGTH:Lorg/eclipse/milo/opcua/sdk/core/model/Property;
       4: aload_1
       5: invokevirtual #6                  // Method setProperty:(Lorg/eclipse/milo/opcua/sdk/core/model/Property;Ljava/lang/Object;)Ljava/util/concurrent/CompletableFuture;
       8: areturn

  public java.util.concurrent.CompletableFuture<org.eclipse.milo.opcua.sdk.client.model.nodes.variables.PropertyNode> maxStringLength();
    Code:
       0: aload_0
       1: getstatic     #14                 // Field org/eclipse/milo/opcua/sdk/client/model/types/objects/ServerCapabilitiesType.MAX_STRING_LENGTH:Lorg/eclipse/milo/opcua/sdk/core/model/Property;
       4: invokeinterface #3,  1            // InterfaceMethod org/eclipse/milo/opcua/sdk/core/model/Property.getBrowseName:()Lorg/eclipse/milo/opcua/stack/core/types/builtin/QualifiedName;
       9: invokevirtual #4                  // Method getPropertyNode:(Lorg/eclipse/milo/opcua/stack/core/types/builtin/QualifiedName;)Ljava/util/concurrent/CompletableFuture;
      12: areturn

  public java.util.concurrent.CompletableFuture<org.eclipse.milo.opcua.stack.core.types.builtin.unsigned.UInteger> getMaxStringLength();
    Code:
       0: aload_0
       1: getstatic     #14                 // Field org/eclipse/milo/opcua/sdk/client/model/types/objects/ServerCapabilitiesType.MAX_STRING_LENGTH:Lorg/eclipse/milo/opcua/sdk/core/model/Property;
       4: invokevirtual #5                  // Method getProperty:(Lorg/eclipse/milo/opcua/sdk/core/model/Property;)Ljava/util/concurrent/CompletableFuture;
       7: areturn

  public java.util.concurrent.CompletableFuture<org.eclipse.milo.opcua.stack.core.types.builtin.StatusCode> setMaxStringLength(org.eclipse.milo.opcua.stack.core.types.builtin.unsigned.UInteger);
    Code:
       0: aload_0
       1: getstatic     #14                 // Field org/eclipse/milo/opcua/sdk/client/model/types/objects/ServerCapabilitiesType.MAX_STRING_LENGTH:Lorg/eclipse/milo/opcua/sdk/core/model/Property;
       4: aload_1
       5: invokevirtual #6                  // Method setProperty:(Lorg/eclipse/milo/opcua/sdk/core/model/Property;Ljava/lang/Object;)Ljava/util/concurrent/CompletableFuture;
       8: areturn

  public java.util.concurrent.CompletableFuture<org.eclipse.milo.opcua.sdk.client.model.nodes.variables.PropertyNode> maxByteStringLength();
    Code:
       0: aload_0
       1: getstatic     #15                 // Field org/eclipse/milo/opcua/sdk/client/model/types/objects/ServerCapabilitiesType.MAX_BYTE_STRING_LENGTH:Lorg/eclipse/milo/opcua/sdk/core/model/Property;
       4: invokeinterface #3,  1            // InterfaceMethod org/eclipse/milo/opcua/sdk/core/model/Property.getBrowseName:()Lorg/eclipse/milo/opcua/stack/core/types/builtin/QualifiedName;
       9: invokevirtual #4                  // Method getPropertyNode:(Lorg/eclipse/milo/opcua/stack/core/types/builtin/QualifiedName;)Ljava/util/concurrent/CompletableFuture;
      12: areturn

  public java.util.concurrent.CompletableFuture<org.eclipse.milo.opcua.stack.core.types.builtin.unsigned.UInteger> getMaxByteStringLength();
    Code:
       0: aload_0
       1: getstatic     #15                 // Field org/eclipse/milo/opcua/sdk/client/model/types/objects/ServerCapabilitiesType.MAX_BYTE_STRING_LENGTH:Lorg/eclipse/milo/opcua/sdk/core/model/Property;
       4: invokevirtual #5                  // Method getProperty:(Lorg/eclipse/milo/opcua/sdk/core/model/Property;)Ljava/util/concurrent/CompletableFuture;
       7: areturn

  public java.util.concurrent.CompletableFuture<org.eclipse.milo.opcua.stack.core.types.builtin.StatusCode> setMaxByteStringLength(org.eclipse.milo.opcua.stack.core.types.builtin.unsigned.UInteger);
    Code:
       0: aload_0
       1: getstatic     #15                 // Field org/eclipse/milo/opcua/sdk/client/model/types/objects/ServerCapabilitiesType.MAX_BYTE_STRING_LENGTH:Lorg/eclipse/milo/opcua/sdk/core/model/Property;
       4: aload_1
       5: invokevirtual #6                  // Method setProperty:(Lorg/eclipse/milo/opcua/sdk/core/model/Property;Ljava/lang/Object;)Ljava/util/concurrent/CompletableFuture;
       8: areturn

  public java.util.concurrent.CompletableFuture<org.eclipse.milo.opcua.sdk.client.model.nodes.objects.OperationLimitsNode> operationLimits();
    Code:
       0: aload_0
       1: ldc           #16                 // String 0:OperationLimits
       3: invokestatic  #17                 // Method org/eclipse/milo/opcua/stack/core/types/builtin/QualifiedName.parse:(Ljava/lang/String;)Lorg/eclipse/milo/opcua/stack/core/types/builtin/QualifiedName;
       6: invokevirtual #18                 // Method getObjectComponent:(Lorg/eclipse/milo/opcua/stack/core/types/builtin/QualifiedName;)Ljava/util/concurrent/CompletableFuture;
       9: ldc           #19                 // class org/eclipse/milo/opcua/sdk/client/model/nodes/objects/OperationLimitsNode
      11: dup
      12: invokevirtual #20                 // Method java/lang/Object.getClass:()Ljava/lang/Class;
      15: pop
      16: invokedynamic #21,  0             // InvokeDynamic #0:apply:(Ljava/lang/Class;)Ljava/util/function/Function;
      21: invokevirtual #22                 // Method java/util/concurrent/CompletableFuture.thenApply:(Ljava/util/function/Function;)Ljava/util/concurrent/CompletableFuture;
      24: areturn

  public java.util.concurrent.CompletableFuture<org.eclipse.milo.opcua.sdk.client.model.nodes.objects.FolderNode> modellingRules();
    Code:
       0: aload_0
       1: ldc           #23                 // String 0:ModellingRules
       3: invokestatic  #17                 // Method org/eclipse/milo/opcua/stack/core/types/builtin/QualifiedName.parse:(Ljava/lang/String;)Lorg/eclipse/milo/opcua/stack/core/types/builtin/QualifiedName;
       6: invokevirtual #18                 // Method getObjectComponent:(Lorg/eclipse/milo/opcua/stack/core/types/builtin/QualifiedName;)Ljava/util/concurrent/CompletableFuture;
       9: ldc           #24                 // class org/eclipse/milo/opcua/sdk/client/model/nodes/objects/FolderNode
      11: dup
      12: invokevirtual #20                 // Method java/lang/Object.getClass:()Ljava/lang/Class;
      15: pop
      16: invokedynamic #25,  0             // InvokeDynamic #1:apply:(Ljava/lang/Class;)Ljava/util/function/Function;
      21: invokevirtual #22                 // Method java/util/concurrent/CompletableFuture.thenApply:(Ljava/util/function/Function;)Ljava/util/concurrent/CompletableFuture;
      24: areturn

  public java.util.concurrent.CompletableFuture<org.eclipse.milo.opcua.sdk.client.model.nodes.objects.FolderNode> aggregateFunctions();
    Code:
       0: aload_0
       1: ldc           #26                 // String 0:AggregateFunctions
       3: invokestatic  #17                 // Method org/eclipse/milo/opcua/stack/core/types/builtin/QualifiedName.parse:(Ljava/lang/String;)Lorg/eclipse/milo/opcua/stack/core/types/builtin/QualifiedName;
       6: invokevirtual #18                 // Method getObjectComponent:(Lorg/eclipse/milo/opcua/stack/core/types/builtin/QualifiedName;)Ljava/util/concurrent/CompletableFuture;
       9: ldc           #24                 // class org/eclipse/milo/opcua/sdk/client/model/nodes/objects/FolderNode
      11: dup
      12: invokevirtual #20                 // Method java/lang/Object.getClass:()Ljava/lang/Class;
      15: pop
      16: invokedynamic #25,  0             // InvokeDynamic #1:apply:(Ljava/lang/Class;)Ljava/util/function/Function;
      21: invokevirtual #22                 // Method java/util/concurrent/CompletableFuture.thenApply:(Ljava/util/function/Function;)Ljava/util/concurrent/CompletableFuture;
      24: areturn
}
