Compiled from "LoggingStateChangeListener.java"
public class org.apache.hadoop.service.LoggingStateChangeListener implements org.apache.hadoop.service.ServiceStateChangeListener {
  private static final org.slf4j.Logger LOG;

  private final org.slf4j.Logger log;

  public org.apache.hadoop.service.LoggingStateChangeListener(org.slf4j.Logger);
    Code:
       0: aload_0
       1: invokespecial #1                  // Method java/lang/Object."<init>":()V
       4: aload_1
       5: invokeinterface #2,  1            // InterfaceMethod org/slf4j/Logger.isDebugEnabled:()Z
      10: pop
      11: aload_0
      12: aload_1
      13: putfield      #3                  // Field log:Lorg/slf4j/Logger;
      16: return

  public org.apache.hadoop.service.LoggingStateChangeListener();
    Code:
       0: aload_0
       1: getstatic     #4                  // Field LOG:Lorg/slf4j/Logger;
       4: invokespecial #5                  // Method "<init>":(Lorg/slf4j/Logger;)V
       7: return

  public void stateChanged(org.apache.hadoop.service.Service);
    Code:
       0: aload_0
       1: getfield      #3                  // Field log:Lorg/slf4j/Logger;
       4: new           #6                  // class java/lang/StringBuilder
       7: dup
       8: invokespecial #7                  // Method java/lang/StringBuilder."<init>":()V
      11: ldc           #8                  // String Entry to state
      13: invokevirtual #9                  // Method java/lang/StringBuilder.append:(Ljava/lang/String;)Ljava/lang/StringBuilder;
      16: aload_1
      17: invokeinterface #10,  1           // InterfaceMethod org/apache/hadoop/service/Service.getServiceState:()Lorg/apache/hadoop/service/Service$STATE;
      22: invokevirtual #11                 // Method java/lang/StringBuilder.append:(Ljava/lang/Object;)Ljava/lang/StringBuilder;
      25: ldc           #12                 // String  for
      27: invokevirtual #9                  // Method java/lang/StringBuilder.append:(Ljava/lang/String;)Ljava/lang/StringBuilder;
      30: aload_1
      31: invokeinterface #13,  1           // InterfaceMethod org/apache/hadoop/service/Service.getName:()Ljava/lang/String;
      36: invokevirtual #9                  // Method java/lang/StringBuilder.append:(Ljava/lang/String;)Ljava/lang/StringBuilder;
      39: invokevirtual #14                 // Method java/lang/StringBuilder.toString:()Ljava/lang/String;
      42: invokeinterface #15,  2           // InterfaceMethod org/slf4j/Logger.info:(Ljava/lang/String;)V
      47: return

  static {};
    Code:
       0: ldc           #16                 // class org/apache/hadoop/service/LoggingStateChangeListener
       2: invokestatic  #17                 // Method org/slf4j/LoggerFactory.getLogger:(Ljava/lang/Class;)Lorg/slf4j/Logger;
       5: putstatic     #4                  // Field LOG:Lorg/slf4j/Logger;
       8: return
}
