Compiled from "ServiceStateException.java"
public class org.apache.hadoop.service.ServiceStateException extends java.lang.RuntimeException implements org.apache.hadoop.util.ExitCodeProvider {
  private static final long serialVersionUID;

  private int exitCode;

  public org.apache.hadoop.service.ServiceStateException(java.lang.String);
    Code:
       0: aload_0
       1: aload_1
       2: aconst_null
       3: invokespecial #1                  // Method "<init>":(Ljava/lang/String;Ljava/lang/Throwable;)V
       6: return

  public org.apache.hadoop.service.ServiceStateException(java.lang.String, java.lang.Throwable);
    Code:
       0: aload_0
       1: aload_1
       2: aload_2
       3: invokespecial #2                  // Method java/lang/RuntimeException."<init>":(Ljava/lang/String;Ljava/lang/Throwable;)V
       6: aload_2
       7: instanceof    #3                  // class org/apache/hadoop/util/ExitCodeProvider
      10: ifeq          29
      13: aload_0
      14: aload_2
      15: checkcast     #3                  // class org/apache/hadoop/util/ExitCodeProvider
      18: invokeinterface #4,  1            // InterfaceMethod org/apache/hadoop/util/ExitCodeProvider.getExitCode:()I
      23: putfield      #5                  // Field exitCode:I
      26: goto          35
      29: aload_0
      30: bipush        57
      32: putfield      #5                  // Field exitCode:I
      35: return

  public org.apache.hadoop.service.ServiceStateException(int, java.lang.String, java.lang.Throwable);
    Code:
       0: aload_0
       1: aload_2
       2: aload_3
       3: invokespecial #1                  // Method "<init>":(Ljava/lang/String;Ljava/lang/Throwable;)V
       6: aload_0
       7: iload_1
       8: putfield      #5                  // Field exitCode:I
      11: return

  public org.apache.hadoop.service.ServiceStateException(java.lang.Throwable);
    Code:
       0: aload_0
       1: aload_1
       2: invokespecial #7                  // Method java/lang/RuntimeException."<init>":(Ljava/lang/Throwable;)V
       5: return

  public int getExitCode();
    Code:
       0: aload_0
       1: getfield      #5                  // Field exitCode:I
       4: ireturn

  public static java.lang.RuntimeException convert(java.lang.Throwable);
    Code:
       0: aload_0
       1: instanceof    #8                  // class java/lang/RuntimeException
       4: ifeq          12
       7: aload_0
       8: checkcast     #8                  // class java/lang/RuntimeException
      11: areturn
      12: new           #9                  // class org/apache/hadoop/service/ServiceStateException
      15: dup
      16: aload_0
      17: invokespecial #10                 // Method "<init>":(Ljava/lang/Throwable;)V
      20: areturn

  public static java.lang.RuntimeException convert(java.lang.String, java.lang.Throwable);
    Code:
       0: aload_1
       1: instanceof    #8                  // class java/lang/RuntimeException
       4: ifeq          12
       7: aload_1
       8: checkcast     #8                  // class java/lang/RuntimeException
      11: areturn
      12: new           #9                  // class org/apache/hadoop/service/ServiceStateException
      15: dup
      16: aload_0
      17: aload_1
      18: invokespecial #1                  // Method "<init>":(Ljava/lang/String;Ljava/lang/Throwable;)V
      21: areturn
}
