Compiled from "BeanProviders.java"
final class org.sonatype.guice.bean.binders.BeanProvider<V> implements com.google.inject.Provider<V> {
  private org.sonatype.guice.bean.locators.BeanLocator locator;

  private final com.google.inject.Key<V> key;

  org.sonatype.guice.bean.binders.BeanProvider(com.google.inject.Key<V>);
    Code:
       0: aload_0
       1: invokespecial #1                  // Method java/lang/Object."<init>":()V
       4: aload_0
       5: aload_1
       6: putfield      #2                  // Field key:Lcom/google/inject/Key;
       9: return

  public V get();
    Code:
       0: aload_0
       1: getfield      #3                  // Field locator:Lorg/sonatype/guice/bean/locators/BeanLocator;
       4: aload_0
       5: getfield      #2                  // Field key:Lcom/google/inject/Key;
       8: invokestatic  #4                  // Method get:(Lorg/sonatype/guice/bean/locators/BeanLocator;Lcom/google/inject/Key;)Ljava/lang/Object;
      11: areturn

  static <T> T get(org.sonatype.guice.bean.locators.BeanLocator, com.google.inject.Key<T>);
    Code:
       0: aload_0
       1: aload_1
       2: invokeinterface #5,  2            // InterfaceMethod org/sonatype/guice/bean/locators/BeanLocator.locate:(Lcom/google/inject/Key;)Ljava/lang/Iterable;
       7: invokeinterface #6,  1            // InterfaceMethod java/lang/Iterable.iterator:()Ljava/util/Iterator;
      12: astore_2
      13: aload_2
      14: invokeinterface #7,  1            // InterfaceMethod java/util/Iterator.hasNext:()Z
      19: ifeq          39
      22: aload_2
      23: invokeinterface #8,  1            // InterfaceMethod java/util/Iterator.next:()Ljava/lang/Object;
      28: checkcast     #9                  // class java/util/Map$Entry
      31: invokeinterface #10,  1           // InterfaceMethod java/util/Map$Entry.getValue:()Ljava/lang/Object;
      36: goto          40
      39: aconst_null
      40: areturn
}
