Compiled from "AbstractMessageChannelBinder.java"
class org.springframework.cloud.stream.binder.AbstractMessageChannelBinder$1 extends org.springframework.cloud.stream.binder.DefaultBinding<org.springframework.messaging.MessageChannel> {
  final java.lang.String val$destination;

  final org.springframework.cloud.stream.binder.ProducerProperties val$producerProperties;

  final org.springframework.cloud.stream.provisioning.ProducerDestination val$producerDestination;

  final org.springframework.messaging.MessageHandler val$producerMessageHandler;

  final org.springframework.cloud.stream.binder.AbstractMessageChannelBinder this$0;

  org.springframework.cloud.stream.binder.AbstractMessageChannelBinder$1(org.springframework.cloud.stream.binder.AbstractMessageChannelBinder, java.lang.String, org.springframework.messaging.MessageChannel, org.springframework.context.Lifecycle, java.lang.String, org.springframework.cloud.stream.binder.ProducerProperties, org.springframework.cloud.stream.provisioning.ProducerDestination, org.springframework.messaging.MessageHandler);
    Code:
       0: aload_0
       1: aload_1
       2: putfield      #1                  // Field this$0:Lorg/springframework/cloud/stream/binder/AbstractMessageChannelBinder;
       5: aload_0
       6: aload         5
       8: putfield      #2                  // Field val$destination:Ljava/lang/String;
      11: aload_0
      12: aload         6
      14: putfield      #3                  // Field val$producerProperties:Lorg/springframework/cloud/stream/binder/ProducerProperties;
      17: aload_0
      18: aload         7
      20: putfield      #4                  // Field val$producerDestination:Lorg/springframework/cloud/stream/provisioning/ProducerDestination;
      23: aload_0
      24: aload         8
      26: putfield      #5                  // Field val$producerMessageHandler:Lorg/springframework/messaging/MessageHandler;
      29: aload_0
      30: aload_2
      31: aload_3
      32: aload         4
      34: invokespecial #6                  // Method org/springframework/cloud/stream/binder/DefaultBinding."<init>":(Ljava/lang/String;Ljava/lang/Object;Lorg/springframework/context/Lifecycle;)V
      37: return

  public java.util.Map<java.lang.String, java.lang.Object> getExtendedInfo();
    Code:
       0: aload_0
       1: getfield      #1                  // Field this$0:Lorg/springframework/cloud/stream/binder/AbstractMessageChannelBinder;
       4: aload_0
       5: getfield      #2                  // Field val$destination:Ljava/lang/String;
       8: aload_0
       9: getfield      #3                  // Field val$producerProperties:Lorg/springframework/cloud/stream/binder/ProducerProperties;
      12: invokestatic  #7                  // Method org/springframework/cloud/stream/binder/AbstractMessageChannelBinder.access$100:(Lorg/springframework/cloud/stream/binder/AbstractMessageChannelBinder;Ljava/lang/Object;Ljava/lang/Object;)Ljava/util/Map;
      15: areturn

  public boolean isInput();
    Code:
       0: iconst_0
       1: ireturn

  public void afterUnbind();
    Code:
       0: aload_0
       1: getfield      #1                  // Field this$0:Lorg/springframework/cloud/stream/binder/AbstractMessageChannelBinder;
       4: aload_0
       5: getfield      #4                  // Field val$producerDestination:Lorg/springframework/cloud/stream/provisioning/ProducerDestination;
       8: invokestatic  #8                  // Method org/springframework/cloud/stream/binder/AbstractMessageChannelBinder.access$200:(Lorg/springframework/cloud/stream/binder/AbstractMessageChannelBinder;Lorg/springframework/cloud/stream/provisioning/ProducerDestination;)V
      11: aload_0
      12: getfield      #5                  // Field val$producerMessageHandler:Lorg/springframework/messaging/MessageHandler;
      15: instanceof    #9                  // class org/springframework/beans/factory/DisposableBean
      18: ifeq          33
      21: aload_0
      22: getfield      #5                  // Field val$producerMessageHandler:Lorg/springframework/messaging/MessageHandler;
      25: checkcast     #9                  // class org/springframework/beans/factory/DisposableBean
      28: invokeinterface #10,  1           // InterfaceMethod org/springframework/beans/factory/DisposableBean.destroy:()V
      33: goto          72
      36: astore_1
      37: aload_0
      38: getfield      #1                  // Field this$0:Lorg/springframework/cloud/stream/binder/AbstractMessageChannelBinder;
      41: getfield      #12                 // Field org/springframework/cloud/stream/binder/AbstractMessageChannelBinder.logger:Lorg/apache/commons/logging/Log;
      44: new           #13                 // class java/lang/StringBuilder
      47: dup
      48: invokespecial #14                 // Method java/lang/StringBuilder."<init>":()V
      51: ldc           #15                 // String Exception thrown while unbinding
      53: invokevirtual #16                 // Method java/lang/StringBuilder.append:(Ljava/lang/String;)Ljava/lang/StringBuilder;
      56: aload_0
      57: invokevirtual #17                 // Method toString:()Ljava/lang/String;
      60: invokevirtual #16                 // Method java/lang/StringBuilder.append:(Ljava/lang/String;)Ljava/lang/StringBuilder;
      63: invokevirtual #18                 // Method java/lang/StringBuilder.toString:()Ljava/lang/String;
      66: aload_1
      67: invokeinterface #19,  3           // InterfaceMethod org/apache/commons/logging/Log.error:(Ljava/lang/Object;Ljava/lang/Throwable;)V
      72: aload_0
      73: getfield      #1                  // Field this$0:Lorg/springframework/cloud/stream/binder/AbstractMessageChannelBinder;
      76: aload_0
      77: getfield      #4                  // Field val$producerDestination:Lorg/springframework/cloud/stream/provisioning/ProducerDestination;
      80: aload_0
      81: getfield      #3                  // Field val$producerProperties:Lorg/springframework/cloud/stream/binder/ProducerProperties;
      84: invokevirtual #20                 // Method org/springframework/cloud/stream/binder/AbstractMessageChannelBinder.afterUnbindProducer:(Lorg/springframework/cloud/stream/provisioning/ProducerDestination;Lorg/springframework/cloud/stream/binder/ProducerProperties;)V
      87: return
    Exception table:
       from    to  target type
           0    33    36   Class java/lang/Exception
}
