Compiled from "AbstractKeyValueStore.java"
public class net.openhft.chronicle.engine.map.AbstractKeyValueStore<K, V> implements net.openhft.chronicle.engine.api.map.KeyValueStore<K, V> {
  public final net.openhft.chronicle.engine.api.map.KeyValueStore<K, V> kvStore;

  final net.openhft.chronicle.engine.api.tree.Asset asset;

  private final java.lang.Class<K> keyType;

  private final java.lang.Class<V> valueType;

  static final boolean $assertionsDisabled;

  net.openhft.chronicle.engine.map.AbstractKeyValueStore(net.openhft.chronicle.engine.api.tree.RequestContext, net.openhft.chronicle.engine.api.tree.Asset, net.openhft.chronicle.engine.api.map.KeyValueStore<K, V>);
    Code:
       0: aload_0
       1: invokespecial #1                  // Method java/lang/Object."<init>":()V
       4: getstatic     #2                  // Field $assertionsDisabled:Z
       7: ifne          22
      10: aload_2
      11: ifnonnull     22
      14: new           #3                  // class java/lang/AssertionError
      17: dup
      18: invokespecial #4                  // Method java/lang/AssertionError."<init>":()V
      21: athrow
      22: getstatic     #2                  // Field $assertionsDisabled:Z
      25: ifne          40
      28: aload_3
      29: ifnonnull     40
      32: new           #3                  // class java/lang/AssertionError
      35: dup
      36: invokespecial #4                  // Method java/lang/AssertionError."<init>":()V
      39: athrow
      40: aload_0
      41: aload_1
      42: invokevirtual #5                  // Method net/openhft/chronicle/engine/api/tree/RequestContext.keyType:()Ljava/lang/Class;
      45: putfield      #6                  // Field keyType:Ljava/lang/Class;
      48: aload_0
      49: aload_1
      50: invokevirtual #7                  // Method net/openhft/chronicle/engine/api/tree/RequestContext.valueType:()Ljava/lang/Class;
      53: putfield      #8                  // Field valueType:Ljava/lang/Class;
      56: aload_0
      57: aload_2
      58: putfield      #9                  // Field asset:Lnet/openhft/chronicle/engine/api/tree/Asset;
      61: aload_0
      62: aload_3
      63: putfield      #10                 // Field kvStore:Lnet/openhft/chronicle/engine/api/map/KeyValueStore;
      66: return

  public net.openhft.chronicle.engine.api.map.KeyValueStore underlying();
    Code:
       0: aload_0
       1: getfield      #10                 // Field kvStore:Lnet/openhft/chronicle/engine/api/map/KeyValueStore;
       4: areturn

  public V getAndPut(K, V);
    Code:
       0: aload_0
       1: getfield      #10                 // Field kvStore:Lnet/openhft/chronicle/engine/api/map/KeyValueStore;
       4: aload_1
       5: aload_2
       6: invokeinterface #11,  3           // InterfaceMethod net/openhft/chronicle/engine/api/map/KeyValueStore.getAndPut:(Ljava/lang/Object;Ljava/lang/Object;)Ljava/lang/Object;
      11: areturn

  public V getAndRemove(K);
    Code:
       0: aload_0
       1: getfield      #10                 // Field kvStore:Lnet/openhft/chronicle/engine/api/map/KeyValueStore;
       4: aload_1
       5: invokeinterface #12,  2           // InterfaceMethod net/openhft/chronicle/engine/api/map/KeyValueStore.getAndRemove:(Ljava/lang/Object;)Ljava/lang/Object;
      10: areturn

  public V getUsing(K, java.lang.Object);
    Code:
       0: aload_0
       1: getfield      #10                 // Field kvStore:Lnet/openhft/chronicle/engine/api/map/KeyValueStore;
       4: aload_1
       5: aload_2
       6: invokeinterface #13,  3           // InterfaceMethod net/openhft/chronicle/engine/api/map/KeyValueStore.getUsing:(Ljava/lang/Object;Ljava/lang/Object;)Ljava/lang/Object;
      11: areturn

  public java.util.Iterator<java.util.Map$Entry<K, V>> entrySetIterator();
    Code:
       0: aload_0
       1: getfield      #10                 // Field kvStore:Lnet/openhft/chronicle/engine/api/map/KeyValueStore;
       4: invokeinterface #14,  1           // InterfaceMethod net/openhft/chronicle/engine/api/map/KeyValueStore.entrySetIterator:()Ljava/util/Iterator;
       9: areturn

  public long longSize();
    Code:
       0: aload_0
       1: getfield      #10                 // Field kvStore:Lnet/openhft/chronicle/engine/api/map/KeyValueStore;
       4: invokeinterface #15,  1           // InterfaceMethod net/openhft/chronicle/engine/api/map/KeyValueStore.longSize:()J
       9: lreturn

  public void keysFor(int, net.openhft.chronicle.engine.api.pubsub.SubscriptionConsumer<K>) throws net.openhft.chronicle.engine.api.pubsub.InvalidSubscriberException;
    Code:
       0: aload_0
       1: getfield      #10                 // Field kvStore:Lnet/openhft/chronicle/engine/api/map/KeyValueStore;
       4: iload_1
       5: aload_2
       6: invokeinterface #16,  3           // InterfaceMethod net/openhft/chronicle/engine/api/map/KeyValueStore.keysFor:(ILnet/openhft/chronicle/engine/api/pubsub/SubscriptionConsumer;)V
      11: return

  public void entriesFor(int, net.openhft.chronicle.engine.api.pubsub.SubscriptionConsumer<net.openhft.chronicle.engine.api.map.MapEvent<K, V>>) throws net.openhft.chronicle.engine.api.pubsub.InvalidSubscriberException;
    Code:
       0: aload_0
       1: getfield      #10                 // Field kvStore:Lnet/openhft/chronicle/engine/api/map/KeyValueStore;
       4: iload_1
       5: aload_2
       6: invokeinterface #17,  3           // InterfaceMethod net/openhft/chronicle/engine/api/map/KeyValueStore.entriesFor:(ILnet/openhft/chronicle/engine/api/pubsub/SubscriptionConsumer;)V
      11: return

  public net.openhft.chronicle.engine.api.tree.Asset asset();
    Code:
       0: aload_0
       1: getfield      #10                 // Field kvStore:Lnet/openhft/chronicle/engine/api/map/KeyValueStore;
       4: invokeinterface #18,  1           // InterfaceMethod net/openhft/chronicle/engine/api/map/KeyValueStore.asset:()Lnet/openhft/chronicle/engine/api/tree/Asset;
       9: areturn

  public void clear();
    Code:
       0: aload_0
       1: getfield      #10                 // Field kvStore:Lnet/openhft/chronicle/engine/api/map/KeyValueStore;
       4: invokeinterface #19,  1           // InterfaceMethod net/openhft/chronicle/engine/api/map/KeyValueStore.clear:()V
       9: return

  public V replace(K, V);
    Code:
       0: aload_0
       1: getfield      #10                 // Field kvStore:Lnet/openhft/chronicle/engine/api/map/KeyValueStore;
       4: aload_1
       5: aload_2
       6: invokeinterface #20,  3           // InterfaceMethod net/openhft/chronicle/engine/api/map/KeyValueStore.replace:(Ljava/lang/Object;Ljava/lang/Object;)Ljava/lang/Object;
      11: areturn

  public void close();
    Code:
       0: aload_0
       1: getfield      #10                 // Field kvStore:Lnet/openhft/chronicle/engine/api/map/KeyValueStore;
       4: invokeinterface #21,  1           // InterfaceMethod net/openhft/chronicle/engine/api/map/KeyValueStore.close:()V
       9: return

  public boolean put(K, V);
    Code:
       0: aload_0
       1: getfield      #10                 // Field kvStore:Lnet/openhft/chronicle/engine/api/map/KeyValueStore;
       4: aload_1
       5: aload_2
       6: invokeinterface #22,  3           // InterfaceMethod net/openhft/chronicle/engine/api/map/KeyValueStore.put:(Ljava/lang/Object;Ljava/lang/Object;)Z
      11: ireturn

  public boolean remove(K);
    Code:
       0: aload_0
       1: getfield      #10                 // Field kvStore:Lnet/openhft/chronicle/engine/api/map/KeyValueStore;
       4: aload_1
       5: invokeinterface #23,  2           // InterfaceMethod net/openhft/chronicle/engine/api/map/KeyValueStore.remove:(Ljava/lang/Object;)Z
      10: ireturn

  public V get(K);
    Code:
       0: aload_0
       1: getfield      #10                 // Field kvStore:Lnet/openhft/chronicle/engine/api/map/KeyValueStore;
       4: aload_1
       5: invokeinterface #24,  2           // InterfaceMethod net/openhft/chronicle/engine/api/map/KeyValueStore.get:(Ljava/lang/Object;)Ljava/lang/Object;
      10: areturn

  public boolean containsKey(K);
    Code:
       0: aload_0
       1: getfield      #10                 // Field kvStore:Lnet/openhft/chronicle/engine/api/map/KeyValueStore;
       4: aload_1
       5: invokeinterface #25,  2           // InterfaceMethod net/openhft/chronicle/engine/api/map/KeyValueStore.containsKey:(Ljava/lang/Object;)Z
      10: ireturn

  public boolean isReadOnly();
    Code:
       0: aload_0
       1: getfield      #10                 // Field kvStore:Lnet/openhft/chronicle/engine/api/map/KeyValueStore;
       4: invokeinterface #26,  1           // InterfaceMethod net/openhft/chronicle/engine/api/map/KeyValueStore.isReadOnly:()Z
       9: ireturn

  public int segments();
    Code:
       0: aload_0
       1: getfield      #10                 // Field kvStore:Lnet/openhft/chronicle/engine/api/map/KeyValueStore;
       4: invokeinterface #27,  1           // InterfaceMethod net/openhft/chronicle/engine/api/map/KeyValueStore.segments:()I
       9: ireturn

  public int segmentFor(K);
    Code:
       0: aload_0
       1: getfield      #10                 // Field kvStore:Lnet/openhft/chronicle/engine/api/map/KeyValueStore;
       4: aload_1
       5: invokeinterface #28,  2           // InterfaceMethod net/openhft/chronicle/engine/api/map/KeyValueStore.segmentFor:(Ljava/lang/Object;)I
      10: ireturn

  public boolean replaceIfEqual(K, V, V);
    Code:
       0: aload_0
       1: getfield      #10                 // Field kvStore:Lnet/openhft/chronicle/engine/api/map/KeyValueStore;
       4: aload_1
       5: aload_2
       6: aload_3
       7: invokeinterface #29,  4           // InterfaceMethod net/openhft/chronicle/engine/api/map/KeyValueStore.replaceIfEqual:(Ljava/lang/Object;Ljava/lang/Object;Ljava/lang/Object;)Z
      12: ireturn

  public boolean removeIfEqual(K, V);
    Code:
       0: aload_0
       1: getfield      #10                 // Field kvStore:Lnet/openhft/chronicle/engine/api/map/KeyValueStore;
       4: aload_1
       5: aload_2
       6: invokeinterface #30,  3           // InterfaceMethod net/openhft/chronicle/engine/api/map/KeyValueStore.removeIfEqual:(Ljava/lang/Object;Ljava/lang/Object;)Z
      11: ireturn

  public boolean isKeyType(java.lang.Object);
    Code:
       0: aload_0
       1: getfield      #10                 // Field kvStore:Lnet/openhft/chronicle/engine/api/map/KeyValueStore;
       4: aload_1
       5: invokeinterface #31,  2           // InterfaceMethod net/openhft/chronicle/engine/api/map/KeyValueStore.isKeyType:(Ljava/lang/Object;)Z
      10: ireturn

  public V putIfAbsent(K, V);
    Code:
       0: aload_0
       1: getfield      #10                 // Field kvStore:Lnet/openhft/chronicle/engine/api/map/KeyValueStore;
       4: aload_1
       5: aload_2
       6: invokeinterface #32,  3           // InterfaceMethod net/openhft/chronicle/engine/api/map/KeyValueStore.putIfAbsent:(Ljava/lang/Object;Ljava/lang/Object;)Ljava/lang/Object;
      11: areturn

  public boolean keyedView();
    Code:
       0: aload_0
       1: getfield      #10                 // Field kvStore:Lnet/openhft/chronicle/engine/api/map/KeyValueStore;
       4: invokeinterface #33,  1           // InterfaceMethod net/openhft/chronicle/engine/api/map/KeyValueStore.keyedView:()Z
       9: ireturn

  public boolean containsValue(V);
    Code:
       0: new           #34                 // class java/lang/UnsupportedOperationException
       3: dup
       4: ldc           #35                 // String todo
       6: invokespecial #36                 // Method java/lang/UnsupportedOperationException."<init>":(Ljava/lang/String;)V
       9: athrow

  public java.util.Iterator<K> keySetIterator();
    Code:
       0: aload_0
       1: getfield      #10                 // Field kvStore:Lnet/openhft/chronicle/engine/api/map/KeyValueStore;
       4: invokeinterface #37,  1           // InterfaceMethod net/openhft/chronicle/engine/api/map/KeyValueStore.keySetIterator:()Ljava/util/Iterator;
       9: areturn

  public java.lang.Class<K> keyType();
    Code:
       0: aload_0
       1: getfield      #6                  // Field keyType:Ljava/lang/Class;
       4: areturn

  public java.lang.Class<V> valueType();
    Code:
       0: aload_0
       1: getfield      #8                  // Field valueType:Ljava/lang/Class;
       4: areturn

  public void accept(net.openhft.chronicle.engine.api.EngineReplication$ReplicationEntry);
    Code:
       0: new           #34                 // class java/lang/UnsupportedOperationException
       3: dup
       4: ldc           #35                 // String todo
       6: invokespecial #36                 // Method java/lang/UnsupportedOperationException."<init>":(Ljava/lang/String;)V
       9: athrow

  public java.lang.Object underlying();
    Code:
       0: aload_0
       1: invokevirtual #38                 // Method underlying:()Lnet/openhft/chronicle/engine/api/map/KeyValueStore;
       4: areturn

  public void accept(java.lang.Object);
    Code:
       0: aload_0
       1: aload_1
       2: checkcast     #39                 // class net/openhft/chronicle/engine/api/EngineReplication$ReplicationEntry
       5: invokevirtual #40                 // Method accept:(Lnet/openhft/chronicle/engine/api/EngineReplication$ReplicationEntry;)V
       8: return

  static {};
    Code:
       0: ldc           #41                 // class net/openhft/chronicle/engine/map/AbstractKeyValueStore
       2: invokevirtual #42                 // Method java/lang/Class.desiredAssertionStatus:()Z
       5: ifne          12
       8: iconst_1
       9: goto          13
      12: iconst_0
      13: putstatic     #2                  // Field $assertionsDisabled:Z
      16: return
}
