Compiled from "RemoteEntrySetView.java"
public class net.openhft.chronicle.engine.map.RemoteEntrySetView<K, MV, V> extends net.openhft.chronicle.engine.map.VanillaEntrySetView<K, MV, V> {
  public net.openhft.chronicle.engine.map.RemoteEntrySetView(net.openhft.chronicle.engine.api.tree.RequestContext, net.openhft.chronicle.engine.api.tree.Asset, net.openhft.chronicle.engine.api.map.MapView<K, V>) throws net.openhft.chronicle.engine.api.tree.AssetNotFoundException;
    Code:
       0: aload_0
       1: aload_1
       2: aload_2
       3: aload_3
       4: invokespecial #1                  // Method net/openhft/chronicle/engine/map/VanillaEntrySetView."<init>":(Lnet/openhft/chronicle/engine/api/tree/RequestContext;Lnet/openhft/chronicle/engine/api/tree/Asset;Lnet/openhft/chronicle/engine/api/map/MapView;)V
       7: return

  public net.openhft.chronicle.engine.api.query.Query<java.util.Map$Entry<K, V>> query();
    Code:
       0: new           #2                  // class net/openhft/chronicle/engine/query/RemoteQuery
       3: dup
       4: aload_0
       5: invokedynamic #3,  0              // InvokeDynamic #0:subscribe:(Lnet/openhft/chronicle/engine/map/RemoteEntrySetView;)Lnet/openhft/chronicle/engine/query/RemoteQuery$Subscribable;
      10: invokespecial #4                  // Method net/openhft/chronicle/engine/query/RemoteQuery."<init>":(Lnet/openhft/chronicle/engine/query/RemoteQuery$Subscribable;)V
      13: areturn

  private void lambda$query$0(net.openhft.chronicle.engine.api.pubsub.Subscriber, net.openhft.chronicle.engine.query.Filter, java.util.Set);
    Code:
       0: aload_0
       1: getfield      #5                  // Field mapView:Lnet/openhft/chronicle/engine/api/map/MapView;
       4: aload_1
       5: aload_2
       6: aload_3
       7: invokeinterface #6,  4            // InterfaceMethod net/openhft/chronicle/engine/api/map/MapView.registerSubscriber:(Lnet/openhft/chronicle/engine/api/pubsub/Subscriber;Lnet/openhft/chronicle/engine/query/Filter;Ljava/util/Set;)V
      12: return
}
