Compiled from "VanillaStringStringKeyValueStore.java"
final class net.openhft.chronicle.engine.map.VanillaStringStringKeyValueStore$BytesStoreToString extends java.lang.Enum<net.openhft.chronicle.engine.map.VanillaStringStringKeyValueStore$BytesStoreToString> implements java.util.function.Function<net.openhft.chronicle.bytes.BytesStore, java.lang.String> {
  public static final net.openhft.chronicle.engine.map.VanillaStringStringKeyValueStore$BytesStoreToString BYTES_STORE_TO_STRING;

  private static final net.openhft.chronicle.engine.map.VanillaStringStringKeyValueStore$BytesStoreToString[] $VALUES;

  public static net.openhft.chronicle.engine.map.VanillaStringStringKeyValueStore$BytesStoreToString[] values();
    Code:
       0: getstatic     #1                  // Field $VALUES:[Lnet/openhft/chronicle/engine/map/VanillaStringStringKeyValueStore$BytesStoreToString;
       3: invokevirtual #2                  // Method "[Lnet/openhft/chronicle/engine/map/VanillaStringStringKeyValueStore$BytesStoreToString;".clone:()Ljava/lang/Object;
       6: checkcast     #3                  // class "[Lnet/openhft/chronicle/engine/map/VanillaStringStringKeyValueStore$BytesStoreToString;"
       9: areturn

  public static net.openhft.chronicle.engine.map.VanillaStringStringKeyValueStore$BytesStoreToString valueOf(java.lang.String);
    Code:
       0: ldc           #4                  // class net/openhft/chronicle/engine/map/VanillaStringStringKeyValueStore$BytesStoreToString
       2: aload_0
       3: invokestatic  #5                  // Method java/lang/Enum.valueOf:(Ljava/lang/Class;Ljava/lang/String;)Ljava/lang/Enum;
       6: checkcast     #4                  // class net/openhft/chronicle/engine/map/VanillaStringStringKeyValueStore$BytesStoreToString
       9: areturn

  private net.openhft.chronicle.engine.map.VanillaStringStringKeyValueStore$BytesStoreToString();
    Code:
       0: aload_0
       1: aload_1
       2: iload_2
       3: invokespecial #6                  // Method java/lang/Enum."<init>":(Ljava/lang/String;I)V
       6: return

  public java.lang.String apply(net.openhft.chronicle.bytes.BytesStore);
    Code:
       0: aload_1
       1: ifnonnull     8
       4: aconst_null
       5: goto          14
       8: aload_1
       9: invokeinterface #7,  1            // InterfaceMethod net/openhft/chronicle/bytes/BytesStore.to8bitString:()Ljava/lang/String;
      14: areturn

  public java.lang.Object apply(java.lang.Object);
    Code:
       0: aload_0
       1: aload_1
       2: checkcast     #8                  // class net/openhft/chronicle/bytes/BytesStore
       5: invokevirtual #9                  // Method apply:(Lnet/openhft/chronicle/bytes/BytesStore;)Ljava/lang/String;
       8: areturn

  static {};
    Code:
       0: new           #4                  // class net/openhft/chronicle/engine/map/VanillaStringStringKeyValueStore$BytesStoreToString
       3: dup
       4: ldc           #10                 // String BYTES_STORE_TO_STRING
       6: iconst_0
       7: invokespecial #11                 // Method "<init>":(Ljava/lang/String;I)V
      10: putstatic     #12                 // Field BYTES_STORE_TO_STRING:Lnet/openhft/chronicle/engine/map/VanillaStringStringKeyValueStore$BytesStoreToString;
      13: iconst_1
      14: anewarray     #4                  // class net/openhft/chronicle/engine/map/VanillaStringStringKeyValueStore$BytesStoreToString
      17: dup
      18: iconst_0
      19: getstatic     #12                 // Field BYTES_STORE_TO_STRING:Lnet/openhft/chronicle/engine/map/VanillaStringStringKeyValueStore$BytesStoreToString;
      22: aastore
      23: putstatic     #1                  // Field $VALUES:[Lnet/openhft/chronicle/engine/map/VanillaStringStringKeyValueStore$BytesStoreToString;
      26: return
}
