Compiled from "GsonAutoConfiguration.java"
final class org.springframework.boot.autoconfigure.gson.GsonAutoConfiguration$StandardGsonBuilderCustomizer implements org.springframework.boot.autoconfigure.gson.GsonBuilderCustomizer,org.springframework.core.Ordered {
  private final org.springframework.boot.autoconfigure.gson.GsonProperties properties;

  org.springframework.boot.autoconfigure.gson.GsonAutoConfiguration$StandardGsonBuilderCustomizer(org.springframework.boot.autoconfigure.gson.GsonProperties);
    Code:
       0: aload_0
       1: invokespecial #1                  // Method java/lang/Object."<init>":()V
       4: aload_0
       5: aload_1
       6: putfield      #2                  // Field properties:Lorg/springframework/boot/autoconfigure/gson/GsonProperties;
       9: return

  public int getOrder();
    Code:
       0: iconst_0
       1: ireturn

  public void customize(com.google.gson.GsonBuilder);
    Code:
       0: aload_0
       1: getfield      #2                  // Field properties:Lorg/springframework/boot/autoconfigure/gson/GsonProperties;
       4: astore_2
       5: invokestatic  #3                  // Method org/springframework/boot/context/properties/PropertyMapper.get:()Lorg/springframework/boot/context/properties/PropertyMapper;
       8: invokevirtual #4                  // Method org/springframework/boot/context/properties/PropertyMapper.alwaysApplyingWhenNonNull:()Lorg/springframework/boot/context/properties/PropertyMapper;
      11: astore_3
      12: aload_3
      13: aload_2
      14: dup
      15: invokevirtual #5                  // Method java/lang/Object.getClass:()Ljava/lang/Class;
      18: pop
      19: invokedynamic #6,  0              // InvokeDynamic #0:get:(Lorg/springframework/boot/autoconfigure/gson/GsonProperties;)Ljava/util/function/Supplier;
      24: invokevirtual #7                  // Method org/springframework/boot/context/properties/PropertyMapper.from:(Ljava/util/function/Supplier;)Lorg/springframework/boot/context/properties/PropertyMapper$Source;
      27: aload_1
      28: dup
      29: invokevirtual #5                  // Method java/lang/Object.getClass:()Ljava/lang/Class;
      32: pop
      33: invokedynamic #8,  0              // InvokeDynamic #1:run:(Lcom/google/gson/GsonBuilder;)Ljava/lang/Runnable;
      38: invokevirtual #9                  // Method org/springframework/boot/context/properties/PropertyMapper$Source.toCall:(Ljava/lang/Runnable;)V
      41: aload_3
      42: aload_2
      43: dup
      44: invokevirtual #5                  // Method java/lang/Object.getClass:()Ljava/lang/Class;
      47: pop
      48: invokedynamic #10,  0             // InvokeDynamic #2:get:(Lorg/springframework/boot/autoconfigure/gson/GsonProperties;)Ljava/util/function/Supplier;
      53: invokevirtual #7                  // Method org/springframework/boot/context/properties/PropertyMapper.from:(Ljava/util/function/Supplier;)Lorg/springframework/boot/context/properties/PropertyMapper$Source;
      56: aload_1
      57: dup
      58: invokevirtual #5                  // Method java/lang/Object.getClass:()Ljava/lang/Class;
      61: pop
      62: invokedynamic #11,  0             // InvokeDynamic #3:run:(Lcom/google/gson/GsonBuilder;)Ljava/lang/Runnable;
      67: invokevirtual #9                  // Method org/springframework/boot/context/properties/PropertyMapper$Source.toCall:(Ljava/lang/Runnable;)V
      70: aload_3
      71: aload_2
      72: dup
      73: invokevirtual #5                  // Method java/lang/Object.getClass:()Ljava/lang/Class;
      76: pop
      77: invokedynamic #12,  0             // InvokeDynamic #4:get:(Lorg/springframework/boot/autoconfigure/gson/GsonProperties;)Ljava/util/function/Supplier;
      82: invokevirtual #7                  // Method org/springframework/boot/context/properties/PropertyMapper.from:(Ljava/util/function/Supplier;)Lorg/springframework/boot/context/properties/PropertyMapper$Source;
      85: invokevirtual #13                 // Method org/springframework/boot/context/properties/PropertyMapper$Source.whenTrue:()Lorg/springframework/boot/context/properties/PropertyMapper$Source;
      88: aload_1
      89: dup
      90: invokevirtual #5                  // Method java/lang/Object.getClass:()Ljava/lang/Class;
      93: pop
      94: invokedynamic #14,  0             // InvokeDynamic #5:run:(Lcom/google/gson/GsonBuilder;)Ljava/lang/Runnable;
      99: invokevirtual #9                  // Method org/springframework/boot/context/properties/PropertyMapper$Source.toCall:(Ljava/lang/Runnable;)V
     102: aload_3
     103: aload_2
     104: dup
     105: invokevirtual #5                  // Method java/lang/Object.getClass:()Ljava/lang/Class;
     108: pop
     109: invokedynamic #15,  0             // InvokeDynamic #6:get:(Lorg/springframework/boot/autoconfigure/gson/GsonProperties;)Ljava/util/function/Supplier;
     114: invokevirtual #7                  // Method org/springframework/boot/context/properties/PropertyMapper.from:(Ljava/util/function/Supplier;)Lorg/springframework/boot/context/properties/PropertyMapper$Source;
     117: aload_1
     118: dup
     119: invokevirtual #5                  // Method java/lang/Object.getClass:()Ljava/lang/Class;
     122: pop
     123: invokedynamic #16,  0             // InvokeDynamic #7:run:(Lcom/google/gson/GsonBuilder;)Ljava/lang/Runnable;
     128: invokevirtual #9                  // Method org/springframework/boot/context/properties/PropertyMapper$Source.toCall:(Ljava/lang/Runnable;)V
     131: aload_3
     132: aload_2
     133: dup
     134: invokevirtual #5                  // Method java/lang/Object.getClass:()Ljava/lang/Class;
     137: pop
     138: invokedynamic #17,  0             // InvokeDynamic #8:get:(Lorg/springframework/boot/autoconfigure/gson/GsonProperties;)Ljava/util/function/Supplier;
     143: invokevirtual #7                  // Method org/springframework/boot/context/properties/PropertyMapper.from:(Ljava/util/function/Supplier;)Lorg/springframework/boot/context/properties/PropertyMapper$Source;
     146: aload_1
     147: dup
     148: invokevirtual #5                  // Method java/lang/Object.getClass:()Ljava/lang/Class;
     151: pop
     152: invokedynamic #18,  0             // InvokeDynamic #9:run:(Lcom/google/gson/GsonBuilder;)Ljava/lang/Runnable;
     157: invokevirtual #9                  // Method org/springframework/boot/context/properties/PropertyMapper$Source.toCall:(Ljava/lang/Runnable;)V
     160: aload_3
     161: aload_2
     162: dup
     163: invokevirtual #5                  // Method java/lang/Object.getClass:()Ljava/lang/Class;
     166: pop
     167: invokedynamic #19,  0             // InvokeDynamic #10:get:(Lorg/springframework/boot/autoconfigure/gson/GsonProperties;)Ljava/util/function/Supplier;
     172: invokevirtual #7                  // Method org/springframework/boot/context/properties/PropertyMapper.from:(Ljava/util/function/Supplier;)Lorg/springframework/boot/context/properties/PropertyMapper$Source;
     175: aload_1
     176: dup
     177: invokevirtual #5                  // Method java/lang/Object.getClass:()Ljava/lang/Class;
     180: pop
     181: invokedynamic #20,  0             // InvokeDynamic #11:accept:(Lcom/google/gson/GsonBuilder;)Ljava/util/function/Consumer;
     186: invokevirtual #21                 // Method org/springframework/boot/context/properties/PropertyMapper$Source.to:(Ljava/util/function/Consumer;)V
     189: aload_3
     190: aload_2
     191: dup
     192: invokevirtual #5                  // Method java/lang/Object.getClass:()Ljava/lang/Class;
     195: pop
     196: invokedynamic #22,  0             // InvokeDynamic #12:get:(Lorg/springframework/boot/autoconfigure/gson/GsonProperties;)Ljava/util/function/Supplier;
     201: invokevirtual #7                  // Method org/springframework/boot/context/properties/PropertyMapper.from:(Ljava/util/function/Supplier;)Lorg/springframework/boot/context/properties/PropertyMapper$Source;
     204: aload_1
     205: dup
     206: invokevirtual #5                  // Method java/lang/Object.getClass:()Ljava/lang/Class;
     209: pop
     210: invokedynamic #23,  0             // InvokeDynamic #13:accept:(Lcom/google/gson/GsonBuilder;)Ljava/util/function/Consumer;
     215: invokevirtual #21                 // Method org/springframework/boot/context/properties/PropertyMapper$Source.to:(Ljava/util/function/Consumer;)V
     218: aload_3
     219: aload_2
     220: dup
     221: invokevirtual #5                  // Method java/lang/Object.getClass:()Ljava/lang/Class;
     224: pop
     225: invokedynamic #24,  0             // InvokeDynamic #14:get:(Lorg/springframework/boot/autoconfigure/gson/GsonProperties;)Ljava/util/function/Supplier;
     230: invokevirtual #7                  // Method org/springframework/boot/context/properties/PropertyMapper.from:(Ljava/util/function/Supplier;)Lorg/springframework/boot/context/properties/PropertyMapper$Source;
     233: aload_1
     234: dup
     235: invokevirtual #5                  // Method java/lang/Object.getClass:()Ljava/lang/Class;
     238: pop
     239: invokedynamic #25,  0             // InvokeDynamic #15:run:(Lcom/google/gson/GsonBuilder;)Ljava/lang/Runnable;
     244: invokevirtual #9                  // Method org/springframework/boot/context/properties/PropertyMapper$Source.toCall:(Ljava/lang/Runnable;)V
     247: aload_3
     248: aload_2
     249: dup
     250: invokevirtual #5                  // Method java/lang/Object.getClass:()Ljava/lang/Class;
     253: pop
     254: invokedynamic #26,  0             // InvokeDynamic #16:get:(Lorg/springframework/boot/autoconfigure/gson/GsonProperties;)Ljava/util/function/Supplier;
     259: invokevirtual #7                  // Method org/springframework/boot/context/properties/PropertyMapper.from:(Ljava/util/function/Supplier;)Lorg/springframework/boot/context/properties/PropertyMapper$Source;
     262: aload_1
     263: dup
     264: invokevirtual #5                  // Method java/lang/Object.getClass:()Ljava/lang/Class;
     267: pop
     268: invokedynamic #27,  0             // InvokeDynamic #17:run:(Lcom/google/gson/GsonBuilder;)Ljava/lang/Runnable;
     273: invokevirtual #9                  // Method org/springframework/boot/context/properties/PropertyMapper$Source.toCall:(Ljava/lang/Runnable;)V
     276: aload_3
     277: aload_2
     278: dup
     279: invokevirtual #5                  // Method java/lang/Object.getClass:()Ljava/lang/Class;
     282: pop
     283: invokedynamic #28,  0             // InvokeDynamic #18:get:(Lorg/springframework/boot/autoconfigure/gson/GsonProperties;)Ljava/util/function/Supplier;
     288: invokevirtual #7                  // Method org/springframework/boot/context/properties/PropertyMapper.from:(Ljava/util/function/Supplier;)Lorg/springframework/boot/context/properties/PropertyMapper$Source;
     291: aload_1
     292: dup
     293: invokevirtual #5                  // Method java/lang/Object.getClass:()Ljava/lang/Class;
     296: pop
     297: invokedynamic #29,  0             // InvokeDynamic #19:run:(Lcom/google/gson/GsonBuilder;)Ljava/lang/Runnable;
     302: invokevirtual #9                  // Method org/springframework/boot/context/properties/PropertyMapper$Source.toCall:(Ljava/lang/Runnable;)V
     305: aload_3
     306: aload_2
     307: dup
     308: invokevirtual #5                  // Method java/lang/Object.getClass:()Ljava/lang/Class;
     311: pop
     312: invokedynamic #30,  0             // InvokeDynamic #20:get:(Lorg/springframework/boot/autoconfigure/gson/GsonProperties;)Ljava/util/function/Supplier;
     317: invokevirtual #7                  // Method org/springframework/boot/context/properties/PropertyMapper.from:(Ljava/util/function/Supplier;)Lorg/springframework/boot/context/properties/PropertyMapper$Source;
     320: aload_1
     321: dup
     322: invokevirtual #5                  // Method java/lang/Object.getClass:()Ljava/lang/Class;
     325: pop
     326: invokedynamic #31,  0             // InvokeDynamic #21:accept:(Lcom/google/gson/GsonBuilder;)Ljava/util/function/Consumer;
     331: invokevirtual #21                 // Method org/springframework/boot/context/properties/PropertyMapper$Source.to:(Ljava/util/function/Consumer;)V
     334: return
}
