Compiled from "NotFiniteNumberException.java"
public class org.apache.commons.math3.exception.NotFiniteNumberException extends org.apache.commons.math3.exception.MathIllegalNumberException {
  private static final long serialVersionUID;

  public org.apache.commons.math3.exception.NotFiniteNumberException(java.lang.Number, java.lang.Object...);
    Code:
       0: aload_0
       1: getstatic     #1                  // Field org/apache/commons/math3/exception/util/LocalizedFormats.NOT_FINITE_NUMBER:Lorg/apache/commons/math3/exception/util/LocalizedFormats;
       4: aload_1
       5: aload_2
       6: invokespecial #2                  // Method "<init>":(Lorg/apache/commons/math3/exception/util/Localizable;Ljava/lang/Number;[Ljava/lang/Object;)V
       9: return

  public org.apache.commons.math3.exception.NotFiniteNumberException(org.apache.commons.math3.exception.util.Localizable, java.lang.Number, java.lang.Object...);
    Code:
       0: aload_0
       1: aload_1
       2: aload_2
       3: aload_3
       4: invokespecial #3                  // Method org/apache/commons/math3/exception/MathIllegalNumberException."<init>":(Lorg/apache/commons/math3/exception/util/Localizable;Ljava/lang/Number;[Ljava/lang/Object;)V
       7: return
}
