Compiled from "ResumeWritesTestCase.java"
public class io.undertow.server.handlers.ResumeWritesTestCase {
  public static final java.lang.String HELLO_WORLD;

  public io.undertow.server.handlers.ResumeWritesTestCase();
    Code:
       0: aload_0
       1: invokespecial #1                  // Method java/lang/Object."<init>":()V
       4: return

  public void testResumeWritesFixedLength() throws java.io.IOException;
    Code:
       0: new           #2                  // class io/undertow/server/handlers/ResumeWritesTestCase$1
       3: dup
       4: aload_0
       5: invokespecial #3                  // Method io/undertow/server/handlers/ResumeWritesTestCase$1."<init>":(Lio/undertow/server/handlers/ResumeWritesTestCase;)V
       8: invokestatic  #4                  // Method io/undertow/testutils/DefaultServer.setRootHandler:(Lio/undertow/server/HttpHandler;)V
      11: new           #5                  // class io/undertow/testutils/TestHttpClient
      14: dup
      15: invokespecial #6                  // Method io/undertow/testutils/TestHttpClient."<init>":()V
      18: astore_1
      19: new           #7                  // class org/apache/http/client/methods/HttpGet
      22: dup
      23: new           #8                  // class java/lang/StringBuilder
      26: dup
      27: invokespecial #9                  // Method java/lang/StringBuilder."<init>":()V
      30: invokestatic  #10                 // Method io/undertow/testutils/DefaultServer.getDefaultServerURL:()Ljava/lang/String;
      33: invokevirtual #11                 // Method java/lang/StringBuilder.append:(Ljava/lang/String;)Ljava/lang/StringBuilder;
      36: ldc           #12                 // String /path
      38: invokevirtual #11                 // Method java/lang/StringBuilder.append:(Ljava/lang/String;)Ljava/lang/StringBuilder;
      41: invokevirtual #13                 // Method java/lang/StringBuilder.toString:()Ljava/lang/String;
      44: invokespecial #14                 // Method org/apache/http/client/methods/HttpGet."<init>":(Ljava/lang/String;)V
      47: astore_2
      48: aload_1
      49: aload_2
      50: invokevirtual #15                 // Method io/undertow/testutils/TestHttpClient.execute:(Lorg/apache/http/client/methods/HttpUriRequest;)Lorg/apache/http/HttpResponse;
      53: astore_3
      54: ldc2_w        #17                 // long 200l
      57: aload_3
      58: invokeinterface #19,  1           // InterfaceMethod org/apache/http/HttpResponse.getStatusLine:()Lorg/apache/http/StatusLine;
      63: invokeinterface #20,  1           // InterfaceMethod org/apache/http/StatusLine.getStatusCode:()I
      68: i2l
      69: invokestatic  #21                 // Method org/junit/Assert.assertEquals:(JJ)V
      72: ldc           #23                 // String Hello World
      74: aload_3
      75: invokestatic  #24                 // Method io/undertow/testutils/HttpClientUtils.readResponse:(Lorg/apache/http/HttpResponse;)Ljava/lang/String;
      78: invokestatic  #25                 // Method org/junit/Assert.assertEquals:(Ljava/lang/Object;Ljava/lang/Object;)V
      81: aload_1
      82: aload_2
      83: invokevirtual #15                 // Method io/undertow/testutils/TestHttpClient.execute:(Lorg/apache/http/client/methods/HttpUriRequest;)Lorg/apache/http/HttpResponse;
      86: astore_3
      87: ldc2_w        #17                 // long 200l
      90: aload_3
      91: invokeinterface #19,  1           // InterfaceMethod org/apache/http/HttpResponse.getStatusLine:()Lorg/apache/http/StatusLine;
      96: invokeinterface #20,  1           // InterfaceMethod org/apache/http/StatusLine.getStatusCode:()I
     101: i2l
     102: invokestatic  #21                 // Method org/junit/Assert.assertEquals:(JJ)V
     105: ldc           #23                 // String Hello World
     107: aload_3
     108: invokestatic  #24                 // Method io/undertow/testutils/HttpClientUtils.readResponse:(Lorg/apache/http/HttpResponse;)Ljava/lang/String;
     111: invokestatic  #25                 // Method org/junit/Assert.assertEquals:(Ljava/lang/Object;Ljava/lang/Object;)V
     114: aload_1
     115: aload_2
     116: invokevirtual #15                 // Method io/undertow/testutils/TestHttpClient.execute:(Lorg/apache/http/client/methods/HttpUriRequest;)Lorg/apache/http/HttpResponse;
     119: astore_3
     120: ldc2_w        #17                 // long 200l
     123: aload_3
     124: invokeinterface #19,  1           // InterfaceMethod org/apache/http/HttpResponse.getStatusLine:()Lorg/apache/http/StatusLine;
     129: invokeinterface #20,  1           // InterfaceMethod org/apache/http/StatusLine.getStatusCode:()I
     134: i2l
     135: invokestatic  #21                 // Method org/junit/Assert.assertEquals:(JJ)V
     138: ldc           #23                 // String Hello World
     140: aload_3
     141: invokestatic  #24                 // Method io/undertow/testutils/HttpClientUtils.readResponse:(Lorg/apache/http/HttpResponse;)Ljava/lang/String;
     144: invokestatic  #25                 // Method org/junit/Assert.assertEquals:(Ljava/lang/Object;Ljava/lang/Object;)V
     147: aload_1
     148: invokevirtual #26                 // Method io/undertow/testutils/TestHttpClient.getConnectionManager:()Lorg/apache/http/conn/ClientConnectionManager;
     151: invokeinterface #27,  1           // InterfaceMethod org/apache/http/conn/ClientConnectionManager.shutdown:()V
     156: goto          173
     159: astore        4
     161: aload_1
     162: invokevirtual #26                 // Method io/undertow/testutils/TestHttpClient.getConnectionManager:()Lorg/apache/http/conn/ClientConnectionManager;
     165: invokeinterface #27,  1           // InterfaceMethod org/apache/http/conn/ClientConnectionManager.shutdown:()V
     170: aload         4
     172: athrow
     173: return
    Exception table:
       from    to  target type
          19   147   159   any
         159   161   159   any

  public void testResumeWritesChunked() throws java.io.IOException;
    Code:
       0: new           #28                 // class io/undertow/server/handlers/ResumeWritesTestCase$2
       3: dup
       4: aload_0
       5: invokespecial #29                 // Method io/undertow/server/handlers/ResumeWritesTestCase$2."<init>":(Lio/undertow/server/handlers/ResumeWritesTestCase;)V
       8: invokestatic  #4                  // Method io/undertow/testutils/DefaultServer.setRootHandler:(Lio/undertow/server/HttpHandler;)V
      11: new           #5                  // class io/undertow/testutils/TestHttpClient
      14: dup
      15: invokespecial #6                  // Method io/undertow/testutils/TestHttpClient."<init>":()V
      18: astore_1
      19: new           #7                  // class org/apache/http/client/methods/HttpGet
      22: dup
      23: new           #8                  // class java/lang/StringBuilder
      26: dup
      27: invokespecial #9                  // Method java/lang/StringBuilder."<init>":()V
      30: invokestatic  #10                 // Method io/undertow/testutils/DefaultServer.getDefaultServerURL:()Ljava/lang/String;
      33: invokevirtual #11                 // Method java/lang/StringBuilder.append:(Ljava/lang/String;)Ljava/lang/StringBuilder;
      36: ldc           #12                 // String /path
      38: invokevirtual #11                 // Method java/lang/StringBuilder.append:(Ljava/lang/String;)Ljava/lang/StringBuilder;
      41: invokevirtual #13                 // Method java/lang/StringBuilder.toString:()Ljava/lang/String;
      44: invokespecial #14                 // Method org/apache/http/client/methods/HttpGet."<init>":(Ljava/lang/String;)V
      47: astore_2
      48: aload_1
      49: aload_2
      50: invokevirtual #15                 // Method io/undertow/testutils/TestHttpClient.execute:(Lorg/apache/http/client/methods/HttpUriRequest;)Lorg/apache/http/HttpResponse;
      53: astore_3
      54: ldc2_w        #17                 // long 200l
      57: aload_3
      58: invokeinterface #19,  1           // InterfaceMethod org/apache/http/HttpResponse.getStatusLine:()Lorg/apache/http/StatusLine;
      63: invokeinterface #20,  1           // InterfaceMethod org/apache/http/StatusLine.getStatusCode:()I
      68: i2l
      69: invokestatic  #21                 // Method org/junit/Assert.assertEquals:(JJ)V
      72: ldc           #23                 // String Hello World
      74: aload_3
      75: invokestatic  #24                 // Method io/undertow/testutils/HttpClientUtils.readResponse:(Lorg/apache/http/HttpResponse;)Ljava/lang/String;
      78: invokestatic  #25                 // Method org/junit/Assert.assertEquals:(Ljava/lang/Object;Ljava/lang/Object;)V
      81: aload_1
      82: aload_2
      83: invokevirtual #15                 // Method io/undertow/testutils/TestHttpClient.execute:(Lorg/apache/http/client/methods/HttpUriRequest;)Lorg/apache/http/HttpResponse;
      86: astore_3
      87: ldc2_w        #17                 // long 200l
      90: aload_3
      91: invokeinterface #19,  1           // InterfaceMethod org/apache/http/HttpResponse.getStatusLine:()Lorg/apache/http/StatusLine;
      96: invokeinterface #20,  1           // InterfaceMethod org/apache/http/StatusLine.getStatusCode:()I
     101: i2l
     102: invokestatic  #21                 // Method org/junit/Assert.assertEquals:(JJ)V
     105: ldc           #23                 // String Hello World
     107: aload_3
     108: invokestatic  #24                 // Method io/undertow/testutils/HttpClientUtils.readResponse:(Lorg/apache/http/HttpResponse;)Ljava/lang/String;
     111: invokestatic  #25                 // Method org/junit/Assert.assertEquals:(Ljava/lang/Object;Ljava/lang/Object;)V
     114: aload_1
     115: aload_2
     116: invokevirtual #15                 // Method io/undertow/testutils/TestHttpClient.execute:(Lorg/apache/http/client/methods/HttpUriRequest;)Lorg/apache/http/HttpResponse;
     119: astore_3
     120: ldc2_w        #17                 // long 200l
     123: aload_3
     124: invokeinterface #19,  1           // InterfaceMethod org/apache/http/HttpResponse.getStatusLine:()Lorg/apache/http/StatusLine;
     129: invokeinterface #20,  1           // InterfaceMethod org/apache/http/StatusLine.getStatusCode:()I
     134: i2l
     135: invokestatic  #21                 // Method org/junit/Assert.assertEquals:(JJ)V
     138: ldc           #23                 // String Hello World
     140: aload_3
     141: invokestatic  #24                 // Method io/undertow/testutils/HttpClientUtils.readResponse:(Lorg/apache/http/HttpResponse;)Ljava/lang/String;
     144: invokestatic  #25                 // Method org/junit/Assert.assertEquals:(Ljava/lang/Object;Ljava/lang/Object;)V
     147: aload_1
     148: invokevirtual #26                 // Method io/undertow/testutils/TestHttpClient.getConnectionManager:()Lorg/apache/http/conn/ClientConnectionManager;
     151: invokeinterface #27,  1           // InterfaceMethod org/apache/http/conn/ClientConnectionManager.shutdown:()V
     156: goto          173
     159: astore        4
     161: aload_1
     162: invokevirtual #26                 // Method io/undertow/testutils/TestHttpClient.getConnectionManager:()Lorg/apache/http/conn/ClientConnectionManager;
     165: invokeinterface #27,  1           // InterfaceMethod org/apache/http/conn/ClientConnectionManager.shutdown:()V
     170: aload         4
     172: athrow
     173: return
    Exception table:
       from    to  target type
          19   147   159   any
         159   161   159   any

  public void testResumeWritesHttp10() throws java.io.IOException;
    Code:
       0: new           #30                 // class io/undertow/server/handlers/ResumeWritesTestCase$3
       3: dup
       4: aload_0
       5: invokespecial #31                 // Method io/undertow/server/handlers/ResumeWritesTestCase$3."<init>":(Lio/undertow/server/handlers/ResumeWritesTestCase;)V
       8: invokestatic  #4                  // Method io/undertow/testutils/DefaultServer.setRootHandler:(Lio/undertow/server/HttpHandler;)V
      11: new           #5                  // class io/undertow/testutils/TestHttpClient
      14: dup
      15: invokespecial #6                  // Method io/undertow/testutils/TestHttpClient."<init>":()V
      18: astore_1
      19: new           #7                  // class org/apache/http/client/methods/HttpGet
      22: dup
      23: new           #8                  // class java/lang/StringBuilder
      26: dup
      27: invokespecial #9                  // Method java/lang/StringBuilder."<init>":()V
      30: invokestatic  #10                 // Method io/undertow/testutils/DefaultServer.getDefaultServerURL:()Ljava/lang/String;
      33: invokevirtual #11                 // Method java/lang/StringBuilder.append:(Ljava/lang/String;)Ljava/lang/StringBuilder;
      36: ldc           #12                 // String /path
      38: invokevirtual #11                 // Method java/lang/StringBuilder.append:(Ljava/lang/String;)Ljava/lang/StringBuilder;
      41: invokevirtual #13                 // Method java/lang/StringBuilder.toString:()Ljava/lang/String;
      44: invokespecial #14                 // Method org/apache/http/client/methods/HttpGet."<init>":(Ljava/lang/String;)V
      47: astore_2
      48: aload_2
      49: invokevirtual #32                 // Method org/apache/http/client/methods/HttpGet.getParams:()Lorg/apache/http/params/HttpParams;
      52: ldc           #34                 // String http.protocol.version
      54: getstatic     #35                 // Field org/apache/http/HttpVersion.HTTP_1_0:Lorg/apache/http/HttpVersion;
      57: invokeinterface #36,  3           // InterfaceMethod org/apache/http/params/HttpParams.setParameter:(Ljava/lang/String;Ljava/lang/Object;)Lorg/apache/http/params/HttpParams;
      62: pop
      63: aload_1
      64: aload_2
      65: invokevirtual #15                 // Method io/undertow/testutils/TestHttpClient.execute:(Lorg/apache/http/client/methods/HttpUriRequest;)Lorg/apache/http/HttpResponse;
      68: astore_3
      69: ldc2_w        #17                 // long 200l
      72: aload_3
      73: invokeinterface #19,  1           // InterfaceMethod org/apache/http/HttpResponse.getStatusLine:()Lorg/apache/http/StatusLine;
      78: invokeinterface #20,  1           // InterfaceMethod org/apache/http/StatusLine.getStatusCode:()I
      83: i2l
      84: invokestatic  #21                 // Method org/junit/Assert.assertEquals:(JJ)V
      87: ldc           #23                 // String Hello World
      89: aload_3
      90: invokestatic  #24                 // Method io/undertow/testutils/HttpClientUtils.readResponse:(Lorg/apache/http/HttpResponse;)Ljava/lang/String;
      93: invokestatic  #25                 // Method org/junit/Assert.assertEquals:(Ljava/lang/Object;Ljava/lang/Object;)V
      96: aload_1
      97: aload_2
      98: invokevirtual #15                 // Method io/undertow/testutils/TestHttpClient.execute:(Lorg/apache/http/client/methods/HttpUriRequest;)Lorg/apache/http/HttpResponse;
     101: astore_3
     102: ldc2_w        #17                 // long 200l
     105: aload_3
     106: invokeinterface #19,  1           // InterfaceMethod org/apache/http/HttpResponse.getStatusLine:()Lorg/apache/http/StatusLine;
     111: invokeinterface #20,  1           // InterfaceMethod org/apache/http/StatusLine.getStatusCode:()I
     116: i2l
     117: invokestatic  #21                 // Method org/junit/Assert.assertEquals:(JJ)V
     120: ldc           #23                 // String Hello World
     122: aload_3
     123: invokestatic  #24                 // Method io/undertow/testutils/HttpClientUtils.readResponse:(Lorg/apache/http/HttpResponse;)Ljava/lang/String;
     126: invokestatic  #25                 // Method org/junit/Assert.assertEquals:(Ljava/lang/Object;Ljava/lang/Object;)V
     129: aload_1
     130: aload_2
     131: invokevirtual #15                 // Method io/undertow/testutils/TestHttpClient.execute:(Lorg/apache/http/client/methods/HttpUriRequest;)Lorg/apache/http/HttpResponse;
     134: astore_3
     135: ldc2_w        #17                 // long 200l
     138: aload_3
     139: invokeinterface #19,  1           // InterfaceMethod org/apache/http/HttpResponse.getStatusLine:()Lorg/apache/http/StatusLine;
     144: invokeinterface #20,  1           // InterfaceMethod org/apache/http/StatusLine.getStatusCode:()I
     149: i2l
     150: invokestatic  #21                 // Method org/junit/Assert.assertEquals:(JJ)V
     153: ldc           #23                 // String Hello World
     155: aload_3
     156: invokestatic  #24                 // Method io/undertow/testutils/HttpClientUtils.readResponse:(Lorg/apache/http/HttpResponse;)Ljava/lang/String;
     159: invokestatic  #25                 // Method org/junit/Assert.assertEquals:(Ljava/lang/Object;Ljava/lang/Object;)V
     162: aload_1
     163: invokevirtual #26                 // Method io/undertow/testutils/TestHttpClient.getConnectionManager:()Lorg/apache/http/conn/ClientConnectionManager;
     166: invokeinterface #27,  1           // InterfaceMethod org/apache/http/conn/ClientConnectionManager.shutdown:()V
     171: goto          188
     174: astore        4
     176: aload_1
     177: invokevirtual #26                 // Method io/undertow/testutils/TestHttpClient.getConnectionManager:()Lorg/apache/http/conn/ClientConnectionManager;
     180: invokeinterface #27,  1           // InterfaceMethod org/apache/http/conn/ClientConnectionManager.shutdown:()V
     185: aload         4
     187: athrow
     188: return
    Exception table:
       from    to  target type
          19   162   174   any
         174   176   174   any
}
