Compiled from "Stream.scala"
final class de.sciss.lucre.expr.graph.Stream$NextExpanded<T extends de.sciss.lucre.Txn<T>, A> extends de.sciss.lucre.expr.graph.Stream$AbstractNextExpanded<T, A, A> {
  private final de.sciss.lucre.IExpr<T, A> default;

  public <T extends de.sciss.lucre.Txn<T>, A> de.sciss.lucre.expr.graph.Stream$NextExpanded(de.sciss.lucre.IExpr<T, de.sciss.lucre.expr.graph.Stream>, de.sciss.lucre.IExpr<T, A>, T, de.sciss.lucre.ITargets<T>, de.sciss.lucre.Adjunct$FromAny<A>);
    Code:
       0: aload_0
       1: aload_2
       2: putfield      #27                 // Field default:Lde/sciss/lucre/IExpr;
       5: aload_0
       6: aload_1
       7: aload_3
       8: aload         4
      10: aload         5
      12: invokespecial #30                 // Method de/sciss/lucre/expr/graph/Stream$AbstractNextExpanded."<init>":(Lde/sciss/lucre/IExpr;Lde/sciss/lucre/Txn;Lde/sciss/lucre/ITargets;Lde/sciss/lucre/Adjunct$FromAny;)V
      15: return

  private de.sciss.lucre.ITargets<T> targets$accessor();
    Code:
       0: aload_0
       1: invokespecial #40                 // Method de/sciss/lucre/expr/graph/Stream$AbstractNextExpanded.targets:()Lde/sciss/lucre/ITargets;
       4: areturn

  public A lower(scala.Option<A>, T);
    Code:
       0: aload_1
       1: aload_0
       2: aload_2
       3: invokedynamic #64,  0             // InvokeDynamic #0:apply:(Lde/sciss/lucre/expr/graph/Stream$NextExpanded;Lde/sciss/lucre/Txn;)Lscala/Function0;
       8: invokevirtual #70                 // Method scala/Option.getOrElse:(Lscala/Function0;)Ljava/lang/Object;
      11: areturn

  private final java.lang.Object lower$$anonfun$1(de.sciss.lucre.Txn);
    Code:
       0: aload_0
       1: getfield      #27                 // Field default:Lde/sciss/lucre/IExpr;
       4: aload_1
       5: invokeinterface #78,  2           // InterfaceMethod de/sciss/lucre/IExpr.value:(Lde/sciss/lucre/Exec;)Ljava/lang/Object;
      10: areturn

  private static java.lang.Object $deserializeLambda$(java.lang.invoke.SerializedLambda);
    Code:
       0: aload_0
       1: invokedynamic #90,  0             // InvokeDynamic #1:lambdaDeserialize:(Ljava/lang/invoke/SerializedLambda;)Ljava/lang/Object;
       6: areturn
}
