Compiled from "EndpointMetricsImpl.java"
public class org.jboss.ws.common.management.EndpointMetricsImpl implements org.jboss.wsf.spi.management.EndpointMetrics {
  private volatile boolean started;

  private final java.util.concurrent.locks.ReadWriteLock lock;

  private final java.util.concurrent.locks.Lock r;

  private final java.util.concurrent.locks.Lock w;

  private final java.util.concurrent.atomic.AtomicLong requestCount;

  private final java.util.concurrent.atomic.AtomicLong responseCount;

  private final java.util.concurrent.atomic.AtomicLong faultCount;

  private final java.util.concurrent.atomic.AtomicLong maxProcessingTime;

  private final java.util.concurrent.atomic.AtomicLong minProcessingTime;

  private final java.util.concurrent.atomic.AtomicLong totalProcessingTime;

  public org.jboss.ws.common.management.EndpointMetricsImpl();
    Code:
       0: aload_0
       1: invokespecial #1                  // Method java/lang/Object."<init>":()V
       4: aload_0
       5: iconst_0
       6: putfield      #2                  // Field started:Z
       9: aload_0
      10: new           #3                  // class java/util/concurrent/locks/ReentrantReadWriteLock
      13: dup
      14: invokespecial #4                  // Method java/util/concurrent/locks/ReentrantReadWriteLock."<init>":()V
      17: putfield      #5                  // Field lock:Ljava/util/concurrent/locks/ReadWriteLock;
      20: aload_0
      21: aload_0
      22: getfield      #5                  // Field lock:Ljava/util/concurrent/locks/ReadWriteLock;
      25: invokeinterface #6,  1            // InterfaceMethod java/util/concurrent/locks/ReadWriteLock.readLock:()Ljava/util/concurrent/locks/Lock;
      30: putfield      #7                  // Field r:Ljava/util/concurrent/locks/Lock;
      33: aload_0
      34: aload_0
      35: getfield      #5                  // Field lock:Ljava/util/concurrent/locks/ReadWriteLock;
      38: invokeinterface #8,  1            // InterfaceMethod java/util/concurrent/locks/ReadWriteLock.writeLock:()Ljava/util/concurrent/locks/Lock;
      43: putfield      #9                  // Field w:Ljava/util/concurrent/locks/Lock;
      46: aload_0
      47: new           #10                 // class java/util/concurrent/atomic/AtomicLong
      50: dup
      51: lconst_0
      52: invokespecial #11                 // Method java/util/concurrent/atomic/AtomicLong."<init>":(J)V
      55: putfield      #12                 // Field requestCount:Ljava/util/concurrent/atomic/AtomicLong;
      58: aload_0
      59: new           #10                 // class java/util/concurrent/atomic/AtomicLong
      62: dup
      63: lconst_0
      64: invokespecial #11                 // Method java/util/concurrent/atomic/AtomicLong."<init>":(J)V
      67: putfield      #13                 // Field responseCount:Ljava/util/concurrent/atomic/AtomicLong;
      70: aload_0
      71: new           #10                 // class java/util/concurrent/atomic/AtomicLong
      74: dup
      75: lconst_0
      76: invokespecial #11                 // Method java/util/concurrent/atomic/AtomicLong."<init>":(J)V
      79: putfield      #14                 // Field faultCount:Ljava/util/concurrent/atomic/AtomicLong;
      82: aload_0
      83: new           #10                 // class java/util/concurrent/atomic/AtomicLong
      86: dup
      87: lconst_0
      88: invokespecial #11                 // Method java/util/concurrent/atomic/AtomicLong."<init>":(J)V
      91: putfield      #15                 // Field maxProcessingTime:Ljava/util/concurrent/atomic/AtomicLong;
      94: aload_0
      95: new           #10                 // class java/util/concurrent/atomic/AtomicLong
      98: dup
      99: lconst_0
     100: invokespecial #11                 // Method java/util/concurrent/atomic/AtomicLong."<init>":(J)V
     103: putfield      #16                 // Field minProcessingTime:Ljava/util/concurrent/atomic/AtomicLong;
     106: aload_0
     107: new           #10                 // class java/util/concurrent/atomic/AtomicLong
     110: dup
     111: lconst_0
     112: invokespecial #11                 // Method java/util/concurrent/atomic/AtomicLong."<init>":(J)V
     115: putfield      #17                 // Field totalProcessingTime:Ljava/util/concurrent/atomic/AtomicLong;
     118: return

  public void start();
    Code:
       0: aload_0
       1: iconst_1
       2: putfield      #2                  // Field started:Z
       5: return

  public void stop();
    Code:
       0: aload_0
       1: iconst_0
       2: putfield      #2                  // Field started:Z
       5: return

  public long processRequestMessage();
    Code:
       0: aload_0
       1: getfield      #2                  // Field started:Z
       4: ifne          9
       7: lconst_0
       8: lreturn
       9: aload_0
      10: getfield      #12                 // Field requestCount:Ljava/util/concurrent/atomic/AtomicLong;
      13: invokevirtual #18                 // Method java/util/concurrent/atomic/AtomicLong.incrementAndGet:()J
      16: pop2
      17: invokestatic  #19                 // Method java/lang/System.nanoTime:()J
      20: lreturn

  public void processResponseMessage(long);
    Code:
       0: lload_1
       1: lconst_0
       2: lcmp
       3: ifle          92
       6: invokestatic  #19                 // Method java/lang/System.nanoTime:()J
       9: lload_1
      10: lsub
      11: lstore_3
      12: aload_0
      13: getfield      #7                  // Field r:Ljava/util/concurrent/locks/Lock;
      16: invokeinterface #20,  1           // InterfaceMethod java/util/concurrent/locks/Lock.lock:()V
      21: aload_0
      22: getfield      #13                 // Field responseCount:Ljava/util/concurrent/atomic/AtomicLong;
      25: invokevirtual #18                 // Method java/util/concurrent/atomic/AtomicLong.incrementAndGet:()J
      28: pop2
      29: aload_0
      30: getfield      #17                 // Field totalProcessingTime:Ljava/util/concurrent/atomic/AtomicLong;
      33: lload_3
      34: invokevirtual #21                 // Method java/util/concurrent/atomic/AtomicLong.addAndGet:(J)J
      37: pop2
      38: aload_0
      39: getfield      #7                  // Field r:Ljava/util/concurrent/locks/Lock;
      42: invokeinterface #22,  1           // InterfaceMethod java/util/concurrent/locks/Lock.unlock:()V
      47: goto          64
      50: astore        5
      52: aload_0
      53: getfield      #7                  // Field r:Ljava/util/concurrent/locks/Lock;
      56: invokeinterface #22,  1           // InterfaceMethod java/util/concurrent/locks/Lock.unlock:()V
      61: aload         5
      63: athrow
      64: aload_0
      65: getfield      #16                 // Field minProcessingTime:Ljava/util/concurrent/atomic/AtomicLong;
      68: lconst_0
      69: lload_3
      70: invokevirtual #23                 // Method java/util/concurrent/atomic/AtomicLong.compareAndSet:(JJ)Z
      73: pop
      74: aload_0
      75: aload_0
      76: getfield      #15                 // Field maxProcessingTime:Ljava/util/concurrent/atomic/AtomicLong;
      79: lload_3
      80: invokespecial #24                 // Method updateMax:(Ljava/util/concurrent/atomic/AtomicLong;J)V
      83: aload_0
      84: aload_0
      85: getfield      #16                 // Field minProcessingTime:Ljava/util/concurrent/atomic/AtomicLong;
      88: lload_3
      89: invokespecial #25                 // Method updateMin:(Ljava/util/concurrent/atomic/AtomicLong;J)V
      92: return
    Exception table:
       from    to  target type
          21    38    50   any
          50    52    50   any

  public void processFaultMessage(long);
    Code:
       0: lload_1
       1: lconst_0
       2: lcmp
       3: ifle          92
       6: invokestatic  #19                 // Method java/lang/System.nanoTime:()J
       9: lload_1
      10: lsub
      11: lstore_3
      12: aload_0
      13: getfield      #7                  // Field r:Ljava/util/concurrent/locks/Lock;
      16: invokeinterface #20,  1           // InterfaceMethod java/util/concurrent/locks/Lock.lock:()V
      21: aload_0
      22: getfield      #14                 // Field faultCount:Ljava/util/concurrent/atomic/AtomicLong;
      25: invokevirtual #18                 // Method java/util/concurrent/atomic/AtomicLong.incrementAndGet:()J
      28: pop2
      29: aload_0
      30: getfield      #17                 // Field totalProcessingTime:Ljava/util/concurrent/atomic/AtomicLong;
      33: lload_3
      34: invokevirtual #21                 // Method java/util/concurrent/atomic/AtomicLong.addAndGet:(J)J
      37: pop2
      38: aload_0
      39: getfield      #7                  // Field r:Ljava/util/concurrent/locks/Lock;
      42: invokeinterface #22,  1           // InterfaceMethod java/util/concurrent/locks/Lock.unlock:()V
      47: goto          64
      50: astore        5
      52: aload_0
      53: getfield      #7                  // Field r:Ljava/util/concurrent/locks/Lock;
      56: invokeinterface #22,  1           // InterfaceMethod java/util/concurrent/locks/Lock.unlock:()V
      61: aload         5
      63: athrow
      64: aload_0
      65: getfield      #16                 // Field minProcessingTime:Ljava/util/concurrent/atomic/AtomicLong;
      68: lconst_0
      69: lload_3
      70: invokevirtual #23                 // Method java/util/concurrent/atomic/AtomicLong.compareAndSet:(JJ)Z
      73: pop
      74: aload_0
      75: aload_0
      76: getfield      #15                 // Field maxProcessingTime:Ljava/util/concurrent/atomic/AtomicLong;
      79: lload_3
      80: invokespecial #24                 // Method updateMax:(Ljava/util/concurrent/atomic/AtomicLong;J)V
      83: aload_0
      84: aload_0
      85: getfield      #16                 // Field minProcessingTime:Ljava/util/concurrent/atomic/AtomicLong;
      88: lload_3
      89: invokespecial #25                 // Method updateMin:(Ljava/util/concurrent/atomic/AtomicLong;J)V
      92: return
    Exception table:
       from    to  target type
          21    38    50   any
          50    52    50   any

  private void updateMin(java.util.concurrent.atomic.AtomicLong, long);
    Code:
       0: aload_1
       1: invokevirtual #26                 // Method java/util/concurrent/atomic/AtomicLong.get:()J
       4: lstore        4
       6: lload_2
       7: lload         4
       9: lcmp
      10: ifge          35
      13: aload_1
      14: lload         4
      16: lload_2
      17: invokevirtual #23                 // Method java/util/concurrent/atomic/AtomicLong.compareAndSet:(JJ)Z
      20: ifeq          26
      23: goto          35
      26: aload_1
      27: invokevirtual #26                 // Method java/util/concurrent/atomic/AtomicLong.get:()J
      30: lstore        4
      32: goto          6
      35: return

  private void updateMax(java.util.concurrent.atomic.AtomicLong, long);
    Code:
       0: aload_1
       1: invokevirtual #26                 // Method java/util/concurrent/atomic/AtomicLong.get:()J
       4: lstore        4
       6: lload_2
       7: lload         4
       9: lcmp
      10: ifle          35
      13: aload_1
      14: lload         4
      16: lload_2
      17: invokevirtual #23                 // Method java/util/concurrent/atomic/AtomicLong.compareAndSet:(JJ)Z
      20: ifeq          26
      23: goto          35
      26: aload_1
      27: invokevirtual #26                 // Method java/util/concurrent/atomic/AtomicLong.get:()J
      30: lstore        4
      32: goto          6
      35: return

  public long getMinProcessingTime();
    Code:
       0: aload_0
       1: getfield      #16                 // Field minProcessingTime:Ljava/util/concurrent/atomic/AtomicLong;
       4: invokevirtual #27                 // Method java/util/concurrent/atomic/AtomicLong.longValue:()J
       7: ldc2_w        #28                 // long 1000000l
      10: ldiv
      11: lreturn

  public long getMaxProcessingTime();
    Code:
       0: aload_0
       1: getfield      #15                 // Field maxProcessingTime:Ljava/util/concurrent/atomic/AtomicLong;
       4: invokevirtual #27                 // Method java/util/concurrent/atomic/AtomicLong.longValue:()J
       7: ldc2_w        #28                 // long 1000000l
      10: ldiv
      11: lreturn

  public long getAverageProcessingTime();
    Code:
       0: aload_0
       1: getfield      #9                  // Field w:Ljava/util/concurrent/locks/Lock;
       4: invokeinterface #20,  1           // InterfaceMethod java/util/concurrent/locks/Lock.lock:()V
       9: aload_0
      10: getfield      #13                 // Field responseCount:Ljava/util/concurrent/atomic/AtomicLong;
      13: invokevirtual #26                 // Method java/util/concurrent/atomic/AtomicLong.get:()J
      16: aload_0
      17: getfield      #14                 // Field faultCount:Ljava/util/concurrent/atomic/AtomicLong;
      20: invokevirtual #26                 // Method java/util/concurrent/atomic/AtomicLong.get:()J
      23: ladd
      24: lstore_1
      25: lload_1
      26: lconst_0
      27: lcmp
      28: ifeq          47
      31: aload_0
      32: getfield      #17                 // Field totalProcessingTime:Ljava/util/concurrent/atomic/AtomicLong;
      35: invokevirtual #26                 // Method java/util/concurrent/atomic/AtomicLong.get:()J
      38: lload_1
      39: ldc2_w        #28                 // long 1000000l
      42: lmul
      43: ldiv
      44: goto          48
      47: lconst_0
      48: lstore_3
      49: aload_0
      50: getfield      #9                  // Field w:Ljava/util/concurrent/locks/Lock;
      53: invokeinterface #22,  1           // InterfaceMethod java/util/concurrent/locks/Lock.unlock:()V
      58: lload_3
      59: lreturn
      60: astore        5
      62: aload_0
      63: getfield      #9                  // Field w:Ljava/util/concurrent/locks/Lock;
      66: invokeinterface #22,  1           // InterfaceMethod java/util/concurrent/locks/Lock.unlock:()V
      71: aload         5
      73: athrow
    Exception table:
       from    to  target type
           9    49    60   any
          60    62    60   any

  public long getTotalProcessingTime();
    Code:
       0: aload_0
       1: getfield      #17                 // Field totalProcessingTime:Ljava/util/concurrent/atomic/AtomicLong;
       4: invokevirtual #26                 // Method java/util/concurrent/atomic/AtomicLong.get:()J
       7: ldc2_w        #28                 // long 1000000l
      10: ldiv
      11: lreturn

  public long getRequestCount();
    Code:
       0: aload_0
       1: getfield      #12                 // Field requestCount:Ljava/util/concurrent/atomic/AtomicLong;
       4: invokevirtual #26                 // Method java/util/concurrent/atomic/AtomicLong.get:()J
       7: lreturn

  public long getFaultCount();
    Code:
       0: aload_0
       1: getfield      #14                 // Field faultCount:Ljava/util/concurrent/atomic/AtomicLong;
       4: invokevirtual #26                 // Method java/util/concurrent/atomic/AtomicLong.get:()J
       7: lreturn

  public long getResponseCount();
    Code:
       0: aload_0
       1: getfield      #13                 // Field responseCount:Ljava/util/concurrent/atomic/AtomicLong;
       4: invokevirtual #26                 // Method java/util/concurrent/atomic/AtomicLong.get:()J
       7: lreturn

  public java.lang.String toString();
    Code:
       0: new           #30                 // class java/lang/StringBuilder
       3: dup
       4: new           #30                 // class java/lang/StringBuilder
       7: dup
       8: invokespecial #31                 // Method java/lang/StringBuilder."<init>":()V
      11: ldc           #32                 // String requestCount=
      13: invokevirtual #33                 // Method java/lang/StringBuilder.append:(Ljava/lang/String;)Ljava/lang/StringBuilder;
      16: aload_0
      17: getfield      #12                 // Field requestCount:Ljava/util/concurrent/atomic/AtomicLong;
      20: invokevirtual #34                 // Method java/lang/StringBuilder.append:(Ljava/lang/Object;)Ljava/lang/StringBuilder;
      23: invokevirtual #35                 // Method java/lang/StringBuilder.toString:()Ljava/lang/String;
      26: invokespecial #36                 // Method java/lang/StringBuilder."<init>":(Ljava/lang/String;)V
      29: astore_1
      30: aload_1
      31: new           #30                 // class java/lang/StringBuilder
      34: dup
      35: invokespecial #31                 // Method java/lang/StringBuilder."<init>":()V
      38: ldc           #37                 // String \n  responseCount=
      40: invokevirtual #33                 // Method java/lang/StringBuilder.append:(Ljava/lang/String;)Ljava/lang/StringBuilder;
      43: aload_0
      44: getfield      #13                 // Field responseCount:Ljava/util/concurrent/atomic/AtomicLong;
      47: invokevirtual #34                 // Method java/lang/StringBuilder.append:(Ljava/lang/Object;)Ljava/lang/StringBuilder;
      50: invokevirtual #35                 // Method java/lang/StringBuilder.toString:()Ljava/lang/String;
      53: invokevirtual #33                 // Method java/lang/StringBuilder.append:(Ljava/lang/String;)Ljava/lang/StringBuilder;
      56: pop
      57: aload_1
      58: new           #30                 // class java/lang/StringBuilder
      61: dup
      62: invokespecial #31                 // Method java/lang/StringBuilder."<init>":()V
      65: ldc           #38                 // String \n  faultCount=
      67: invokevirtual #33                 // Method java/lang/StringBuilder.append:(Ljava/lang/String;)Ljava/lang/StringBuilder;
      70: aload_0
      71: getfield      #14                 // Field faultCount:Ljava/util/concurrent/atomic/AtomicLong;
      74: invokevirtual #34                 // Method java/lang/StringBuilder.append:(Ljava/lang/Object;)Ljava/lang/StringBuilder;
      77: invokevirtual #35                 // Method java/lang/StringBuilder.toString:()Ljava/lang/String;
      80: invokevirtual #33                 // Method java/lang/StringBuilder.append:(Ljava/lang/String;)Ljava/lang/StringBuilder;
      83: pop
      84: aload_1
      85: new           #30                 // class java/lang/StringBuilder
      88: dup
      89: invokespecial #31                 // Method java/lang/StringBuilder."<init>":()V
      92: ldc           #39                 // String \n  maxProcessingTime=
      94: invokevirtual #33                 // Method java/lang/StringBuilder.append:(Ljava/lang/String;)Ljava/lang/StringBuilder;
      97: aload_0
      98: getfield      #15                 // Field maxProcessingTime:Ljava/util/concurrent/atomic/AtomicLong;
     101: invokevirtual #34                 // Method java/lang/StringBuilder.append:(Ljava/lang/Object;)Ljava/lang/StringBuilder;
     104: invokevirtual #35                 // Method java/lang/StringBuilder.toString:()Ljava/lang/String;
     107: invokevirtual #33                 // Method java/lang/StringBuilder.append:(Ljava/lang/String;)Ljava/lang/StringBuilder;
     110: pop
     111: aload_1
     112: new           #30                 // class java/lang/StringBuilder
     115: dup
     116: invokespecial #31                 // Method java/lang/StringBuilder."<init>":()V
     119: ldc           #40                 // String \n  minProcessingTime=
     121: invokevirtual #33                 // Method java/lang/StringBuilder.append:(Ljava/lang/String;)Ljava/lang/StringBuilder;
     124: aload_0
     125: getfield      #16                 // Field minProcessingTime:Ljava/util/concurrent/atomic/AtomicLong;
     128: invokevirtual #34                 // Method java/lang/StringBuilder.append:(Ljava/lang/Object;)Ljava/lang/StringBuilder;
     131: invokevirtual #35                 // Method java/lang/StringBuilder.toString:()Ljava/lang/String;
     134: invokevirtual #33                 // Method java/lang/StringBuilder.append:(Ljava/lang/String;)Ljava/lang/StringBuilder;
     137: pop
     138: aload_1
     139: new           #30                 // class java/lang/StringBuilder
     142: dup
     143: invokespecial #31                 // Method java/lang/StringBuilder."<init>":()V
     146: ldc           #41                 // String \n  avgProcessingTime=
     148: invokevirtual #33                 // Method java/lang/StringBuilder.append:(Ljava/lang/String;)Ljava/lang/StringBuilder;
     151: aload_0
     152: invokevirtual #42                 // Method getAverageProcessingTime:()J
     155: invokevirtual #43                 // Method java/lang/StringBuilder.append:(J)Ljava/lang/StringBuilder;
     158: invokevirtual #35                 // Method java/lang/StringBuilder.toString:()Ljava/lang/String;
     161: invokevirtual #33                 // Method java/lang/StringBuilder.append:(Ljava/lang/String;)Ljava/lang/StringBuilder;
     164: pop
     165: aload_1
     166: new           #30                 // class java/lang/StringBuilder
     169: dup
     170: invokespecial #31                 // Method java/lang/StringBuilder."<init>":()V
     173: ldc           #44                 // String \n  totalProcessingTime=
     175: invokevirtual #33                 // Method java/lang/StringBuilder.append:(Ljava/lang/String;)Ljava/lang/StringBuilder;
     178: aload_0
     179: getfield      #17                 // Field totalProcessingTime:Ljava/util/concurrent/atomic/AtomicLong;
     182: invokevirtual #34                 // Method java/lang/StringBuilder.append:(Ljava/lang/Object;)Ljava/lang/StringBuilder;
     185: invokevirtual #35                 // Method java/lang/StringBuilder.toString:()Ljava/lang/String;
     188: invokevirtual #33                 // Method java/lang/StringBuilder.append:(Ljava/lang/String;)Ljava/lang/StringBuilder;
     191: pop
     192: aload_1
     193: invokevirtual #35                 // Method java/lang/StringBuilder.toString:()Ljava/lang/String;
     196: areturn
}
