Compiled from "BasicPersistentLockStore.java"
public class com.arjuna.ats.internal.txoj.lockstore.BasicPersistentLockStore extends com.arjuna.ats.txoj.lockstore.LockStore {
  private com.arjuna.ats.arjuna.objectstore.ParticipantStore _lockStore;

  private static final java.lang.String LOCK_ROOT;

  public com.arjuna.ats.internal.txoj.lockstore.BasicPersistentLockStore(com.arjuna.ats.arjuna.common.ObjectStoreEnvironmentBean) throws com.arjuna.ats.arjuna.exceptions.ObjectStoreException;
    Code:
       0: aload_0
       1: invokespecial #1                  // Method com/arjuna/ats/txoj/lockstore/LockStore."<init>":()V
       4: getstatic     #2                  // Field com/arjuna/ats/txoj/logging/txojLogger.logger:Lorg/jboss/logging/Logger;
       7: invokevirtual #3                  // Method org/jboss/logging/Logger.isTraceEnabled:()Z
      10: ifeq          21
      13: getstatic     #2                  // Field com/arjuna/ats/txoj/logging/txojLogger.logger:Lorg/jboss/logging/Logger;
      16: ldc           #4                  // String BasicPersistentLockStore.BasicPersistentLockStore()
      18: invokevirtual #5                  // Method org/jboss/logging/Logger.trace:(Ljava/lang/Object;)V
      21: aload_0
      22: new           #6                  // class com/arjuna/ats/internal/arjuna/objectstore/ShadowingStore
      25: dup
      26: aload_1
      27: invokespecial #7                  // Method com/arjuna/ats/internal/arjuna/objectstore/ShadowingStore."<init>":(Lcom/arjuna/ats/arjuna/common/ObjectStoreEnvironmentBean;)V
      30: putfield      #8                  // Field _lockStore:Lcom/arjuna/ats/arjuna/objectstore/ParticipantStore;
      33: return

  public com.arjuna.ats.arjuna.state.InputObjectState read_state(com.arjuna.ats.arjuna.common.Uid, java.lang.String) throws com.arjuna.ats.txoj.exceptions.LockStoreException;
    Code:
       0: getstatic     #2                  // Field com/arjuna/ats/txoj/logging/txojLogger.logger:Lorg/jboss/logging/Logger;
       3: invokevirtual #3                  // Method org/jboss/logging/Logger.isTraceEnabled:()Z
       6: ifeq          48
       9: getstatic     #2                  // Field com/arjuna/ats/txoj/logging/txojLogger.logger:Lorg/jboss/logging/Logger;
      12: new           #9                  // class java/lang/StringBuilder
      15: dup
      16: invokespecial #10                 // Method java/lang/StringBuilder."<init>":()V
      19: ldc           #11                 // String BasicPersistentLockStore.read_state(
      21: invokevirtual #12                 // Method java/lang/StringBuilder.append:(Ljava/lang/String;)Ljava/lang/StringBuilder;
      24: aload_1
      25: invokevirtual #13                 // Method java/lang/StringBuilder.append:(Ljava/lang/Object;)Ljava/lang/StringBuilder;
      28: ldc           #14                 // String ,
      30: invokevirtual #12                 // Method java/lang/StringBuilder.append:(Ljava/lang/String;)Ljava/lang/StringBuilder;
      33: aload_2
      34: invokevirtual #12                 // Method java/lang/StringBuilder.append:(Ljava/lang/String;)Ljava/lang/StringBuilder;
      37: ldc           #15                 // String )
      39: invokevirtual #12                 // Method java/lang/StringBuilder.append:(Ljava/lang/String;)Ljava/lang/StringBuilder;
      42: invokevirtual #16                 // Method java/lang/StringBuilder.toString:()Ljava/lang/String;
      45: invokevirtual #5                  // Method org/jboss/logging/Logger.trace:(Ljava/lang/Object;)V
      48: aload_0
      49: getfield      #8                  // Field _lockStore:Lcom/arjuna/ats/arjuna/objectstore/ParticipantStore;
      52: aload_1
      53: new           #9                  // class java/lang/StringBuilder
      56: dup
      57: invokespecial #10                 // Method java/lang/StringBuilder."<init>":()V
      60: ldc           #18                 // String LockStore
      62: invokevirtual #12                 // Method java/lang/StringBuilder.append:(Ljava/lang/String;)Ljava/lang/StringBuilder;
      65: aload_2
      66: invokevirtual #12                 // Method java/lang/StringBuilder.append:(Ljava/lang/String;)Ljava/lang/StringBuilder;
      69: invokevirtual #16                 // Method java/lang/StringBuilder.toString:()Ljava/lang/String;
      72: invokeinterface #19,  3           // InterfaceMethod com/arjuna/ats/arjuna/objectstore/ParticipantStore.read_committed:(Lcom/arjuna/ats/arjuna/common/Uid;Ljava/lang/String;)Lcom/arjuna/ats/arjuna/state/InputObjectState;
      77: areturn
      78: astore_3
      79: new           #21                 // class com/arjuna/ats/txoj/exceptions/LockStoreException
      82: dup
      83: ldc           #22                 // String Persistent store error.
      85: aload_3
      86: invokespecial #23                 // Method com/arjuna/ats/txoj/exceptions/LockStoreException."<init>":(Ljava/lang/String;Ljava/lang/Throwable;)V
      89: athrow
    Exception table:
       from    to  target type
          48    77    78   Class com/arjuna/ats/arjuna/exceptions/ObjectStoreException

  public boolean remove_state(com.arjuna.ats.arjuna.common.Uid, java.lang.String);
    Code:
       0: getstatic     #2                  // Field com/arjuna/ats/txoj/logging/txojLogger.logger:Lorg/jboss/logging/Logger;
       3: invokevirtual #3                  // Method org/jboss/logging/Logger.isTraceEnabled:()Z
       6: ifeq          48
       9: getstatic     #2                  // Field com/arjuna/ats/txoj/logging/txojLogger.logger:Lorg/jboss/logging/Logger;
      12: new           #9                  // class java/lang/StringBuilder
      15: dup
      16: invokespecial #10                 // Method java/lang/StringBuilder."<init>":()V
      19: ldc           #24                 // String BasicPersistentLockStore.remove_state(
      21: invokevirtual #12                 // Method java/lang/StringBuilder.append:(Ljava/lang/String;)Ljava/lang/StringBuilder;
      24: aload_1
      25: invokevirtual #13                 // Method java/lang/StringBuilder.append:(Ljava/lang/Object;)Ljava/lang/StringBuilder;
      28: ldc           #14                 // String ,
      30: invokevirtual #12                 // Method java/lang/StringBuilder.append:(Ljava/lang/String;)Ljava/lang/StringBuilder;
      33: aload_2
      34: invokevirtual #12                 // Method java/lang/StringBuilder.append:(Ljava/lang/String;)Ljava/lang/StringBuilder;
      37: ldc           #15                 // String )
      39: invokevirtual #12                 // Method java/lang/StringBuilder.append:(Ljava/lang/String;)Ljava/lang/StringBuilder;
      42: invokevirtual #16                 // Method java/lang/StringBuilder.toString:()Ljava/lang/String;
      45: invokevirtual #5                  // Method org/jboss/logging/Logger.trace:(Ljava/lang/Object;)V
      48: aload_0
      49: getfield      #8                  // Field _lockStore:Lcom/arjuna/ats/arjuna/objectstore/ParticipantStore;
      52: aload_1
      53: new           #9                  // class java/lang/StringBuilder
      56: dup
      57: invokespecial #10                 // Method java/lang/StringBuilder."<init>":()V
      60: ldc           #18                 // String LockStore
      62: invokevirtual #12                 // Method java/lang/StringBuilder.append:(Ljava/lang/String;)Ljava/lang/StringBuilder;
      65: aload_2
      66: invokevirtual #12                 // Method java/lang/StringBuilder.append:(Ljava/lang/String;)Ljava/lang/StringBuilder;
      69: invokevirtual #16                 // Method java/lang/StringBuilder.toString:()Ljava/lang/String;
      72: invokeinterface #25,  3           // InterfaceMethod com/arjuna/ats/arjuna/objectstore/ParticipantStore.remove_committed:(Lcom/arjuna/ats/arjuna/common/Uid;Ljava/lang/String;)Z
      77: ireturn
      78: astore_3
      79: iconst_0
      80: ireturn
    Exception table:
       from    to  target type
          48    77    78   Class com/arjuna/ats/arjuna/exceptions/ObjectStoreException

  public boolean write_committed(com.arjuna.ats.arjuna.common.Uid, java.lang.String, com.arjuna.ats.arjuna.state.OutputObjectState);
    Code:
       0: getstatic     #2                  // Field com/arjuna/ats/txoj/logging/txojLogger.logger:Lorg/jboss/logging/Logger;
       3: invokevirtual #3                  // Method org/jboss/logging/Logger.isTraceEnabled:()Z
       6: ifeq          57
       9: getstatic     #2                  // Field com/arjuna/ats/txoj/logging/txojLogger.logger:Lorg/jboss/logging/Logger;
      12: new           #9                  // class java/lang/StringBuilder
      15: dup
      16: invokespecial #10                 // Method java/lang/StringBuilder."<init>":()V
      19: ldc           #26                 // String BasicPersistentLockStore.write_committed(
      21: invokevirtual #12                 // Method java/lang/StringBuilder.append:(Ljava/lang/String;)Ljava/lang/StringBuilder;
      24: aload_1
      25: invokevirtual #13                 // Method java/lang/StringBuilder.append:(Ljava/lang/Object;)Ljava/lang/StringBuilder;
      28: ldc           #14                 // String ,
      30: invokevirtual #12                 // Method java/lang/StringBuilder.append:(Ljava/lang/String;)Ljava/lang/StringBuilder;
      33: aload_2
      34: invokevirtual #12                 // Method java/lang/StringBuilder.append:(Ljava/lang/String;)Ljava/lang/StringBuilder;
      37: ldc           #14                 // String ,
      39: invokevirtual #12                 // Method java/lang/StringBuilder.append:(Ljava/lang/String;)Ljava/lang/StringBuilder;
      42: aload_3
      43: invokevirtual #13                 // Method java/lang/StringBuilder.append:(Ljava/lang/Object;)Ljava/lang/StringBuilder;
      46: ldc           #15                 // String )
      48: invokevirtual #12                 // Method java/lang/StringBuilder.append:(Ljava/lang/String;)Ljava/lang/StringBuilder;
      51: invokevirtual #16                 // Method java/lang/StringBuilder.toString:()Ljava/lang/String;
      54: invokevirtual #5                  // Method org/jboss/logging/Logger.trace:(Ljava/lang/Object;)V
      57: aload_0
      58: getfield      #8                  // Field _lockStore:Lcom/arjuna/ats/arjuna/objectstore/ParticipantStore;
      61: aload_1
      62: new           #9                  // class java/lang/StringBuilder
      65: dup
      66: invokespecial #10                 // Method java/lang/StringBuilder."<init>":()V
      69: ldc           #18                 // String LockStore
      71: invokevirtual #12                 // Method java/lang/StringBuilder.append:(Ljava/lang/String;)Ljava/lang/StringBuilder;
      74: aload_2
      75: invokevirtual #12                 // Method java/lang/StringBuilder.append:(Ljava/lang/String;)Ljava/lang/StringBuilder;
      78: invokevirtual #16                 // Method java/lang/StringBuilder.toString:()Ljava/lang/String;
      81: aload_3
      82: invokeinterface #27,  4           // InterfaceMethod com/arjuna/ats/arjuna/objectstore/ParticipantStore.write_committed:(Lcom/arjuna/ats/arjuna/common/Uid;Ljava/lang/String;Lcom/arjuna/ats/arjuna/state/OutputObjectState;)Z
      87: ireturn
      88: astore        4
      90: iconst_0
      91: ireturn
    Exception table:
       from    to  target type
          57    87    88   Class com/arjuna/ats/arjuna/exceptions/ObjectStoreException
}
