Compiled from "AnalyzePrototypeProperties.java"
class com.google.javascript.jscomp.AnalyzePrototypeProperties implements com.google.javascript.jscomp.CompilerPass {
  private static final com.google.javascript.jscomp.AnalyzePrototypeProperties$SymbolType PROPERTY;

  private static final com.google.javascript.jscomp.AnalyzePrototypeProperties$SymbolType VAR;

  private final com.google.javascript.jscomp.AbstractCompiler compiler;

  private final boolean canModifyExterns;

  private final boolean anchorUnusedVars;

  private final com.google.javascript.jscomp.JSModuleGraph moduleGraph;

  private final com.google.javascript.jscomp.JSModule firstModule;

  private static final java.util.Set<java.lang.String> IMPLICITLY_USED_PROPERTIES;

  private final com.google.javascript.jscomp.graph.LinkedDirectedGraph<com.google.javascript.jscomp.AnalyzePrototypeProperties$NameInfo, com.google.javascript.jscomp.JSModule> symbolGraph;

  private final com.google.javascript.jscomp.AnalyzePrototypeProperties$NameInfo globalNode;

  private final com.google.javascript.jscomp.AnalyzePrototypeProperties$NameInfo externNode;

  private final com.google.javascript.jscomp.AnalyzePrototypeProperties$NameInfo anonymousNode;

  private final java.util.Map<java.lang.String, com.google.javascript.jscomp.AnalyzePrototypeProperties$NameInfo> propertyNameInfo;

  private final java.util.Map<java.lang.String, com.google.javascript.jscomp.AnalyzePrototypeProperties$NameInfo> varNameInfo;

  com.google.javascript.jscomp.AnalyzePrototypeProperties(com.google.javascript.jscomp.AbstractCompiler, com.google.javascript.jscomp.JSModuleGraph, boolean, boolean);
    Code:
       0: aload_0
       1: invokespecial #12                 // Method java/lang/Object."<init>":()V
       4: aload_0
       5: invokestatic  #13                 // Method com/google/javascript/jscomp/graph/LinkedDirectedGraph.createWithoutAnnotations:()Lcom/google/javascript/jscomp/graph/LinkedDirectedGraph;
       8: putfield      #5                  // Field symbolGraph:Lcom/google/javascript/jscomp/graph/LinkedDirectedGraph;
      11: aload_0
      12: new           #14                 // class com/google/javascript/jscomp/AnalyzePrototypeProperties$NameInfo
      15: dup
      16: aload_0
      17: ldc           #15                 // String [global]
      19: invokespecial #16                 // Method com/google/javascript/jscomp/AnalyzePrototypeProperties$NameInfo."<init>":(Lcom/google/javascript/jscomp/AnalyzePrototypeProperties;Ljava/lang/String;)V
      22: putfield      #7                  // Field globalNode:Lcom/google/javascript/jscomp/AnalyzePrototypeProperties$NameInfo;
      25: aload_0
      26: new           #14                 // class com/google/javascript/jscomp/AnalyzePrototypeProperties$NameInfo
      29: dup
      30: aload_0
      31: ldc           #17                 // String [extern]
      33: invokespecial #16                 // Method com/google/javascript/jscomp/AnalyzePrototypeProperties$NameInfo."<init>":(Lcom/google/javascript/jscomp/AnalyzePrototypeProperties;Ljava/lang/String;)V
      36: putfield      #3                  // Field externNode:Lcom/google/javascript/jscomp/AnalyzePrototypeProperties$NameInfo;
      39: aload_0
      40: new           #14                 // class com/google/javascript/jscomp/AnalyzePrototypeProperties$NameInfo
      43: dup
      44: aload_0
      45: ldc           #18                 // String [anonymous]
      47: invokespecial #16                 // Method com/google/javascript/jscomp/AnalyzePrototypeProperties$NameInfo."<init>":(Lcom/google/javascript/jscomp/AnalyzePrototypeProperties;Ljava/lang/String;)V
      50: putfield      #8                  // Field anonymousNode:Lcom/google/javascript/jscomp/AnalyzePrototypeProperties$NameInfo;
      53: aload_0
      54: invokestatic  #19                 // Method com/google/common/collect/Maps.newLinkedHashMap:()Ljava/util/LinkedHashMap;
      57: putfield      #20                 // Field propertyNameInfo:Ljava/util/Map;
      60: aload_0
      61: invokestatic  #19                 // Method com/google/common/collect/Maps.newLinkedHashMap:()Ljava/util/LinkedHashMap;
      64: putfield      #21                 // Field varNameInfo:Ljava/util/Map;
      67: aload_0
      68: aload_1
      69: putfield      #6                  // Field compiler:Lcom/google/javascript/jscomp/AbstractCompiler;
      72: aload_0
      73: aload_2
      74: putfield      #1                  // Field moduleGraph:Lcom/google/javascript/jscomp/JSModuleGraph;
      77: aload_0
      78: iload_3
      79: putfield      #22                 // Field canModifyExterns:Z
      82: aload_0
      83: iload         4
      85: putfield      #4                  // Field anchorUnusedVars:Z
      88: aload_2
      89: ifnull        103
      92: aload_0
      93: aload_2
      94: invokevirtual #23                 // Method com/google/javascript/jscomp/JSModuleGraph.getRootModule:()Lcom/google/javascript/jscomp/JSModule;
      97: putfield      #2                  // Field firstModule:Lcom/google/javascript/jscomp/JSModule;
     100: goto          108
     103: aload_0
     104: aconst_null
     105: putfield      #2                  // Field firstModule:Lcom/google/javascript/jscomp/JSModule;
     108: aload_0
     109: getfield      #7                  // Field globalNode:Lcom/google/javascript/jscomp/AnalyzePrototypeProperties$NameInfo;
     112: aconst_null
     113: invokevirtual #24                 // Method com/google/javascript/jscomp/AnalyzePrototypeProperties$NameInfo.markReference:(Lcom/google/javascript/jscomp/JSModule;)Z
     116: pop
     117: aload_0
     118: getfield      #3                  // Field externNode:Lcom/google/javascript/jscomp/AnalyzePrototypeProperties$NameInfo;
     121: aconst_null
     122: invokevirtual #24                 // Method com/google/javascript/jscomp/AnalyzePrototypeProperties$NameInfo.markReference:(Lcom/google/javascript/jscomp/JSModule;)Z
     125: pop
     126: aload_0
     127: getfield      #5                  // Field symbolGraph:Lcom/google/javascript/jscomp/graph/LinkedDirectedGraph;
     130: aload_0
     131: getfield      #7                  // Field globalNode:Lcom/google/javascript/jscomp/AnalyzePrototypeProperties$NameInfo;
     134: invokevirtual #25                 // Method com/google/javascript/jscomp/graph/LinkedDirectedGraph.createNode:(Ljava/lang/Object;)Lcom/google/javascript/jscomp/graph/GraphNode;
     137: pop
     138: aload_0
     139: getfield      #5                  // Field symbolGraph:Lcom/google/javascript/jscomp/graph/LinkedDirectedGraph;
     142: aload_0
     143: getfield      #3                  // Field externNode:Lcom/google/javascript/jscomp/AnalyzePrototypeProperties$NameInfo;
     146: invokevirtual #25                 // Method com/google/javascript/jscomp/graph/LinkedDirectedGraph.createNode:(Ljava/lang/Object;)Lcom/google/javascript/jscomp/graph/GraphNode;
     149: pop
     150: getstatic     #26                 // Field IMPLICITLY_USED_PROPERTIES:Ljava/util/Set;
     153: invokeinterface #27,  1           // InterfaceMethod java/util/Set.iterator:()Ljava/util/Iterator;
     158: astore        5
     160: aload         5
     162: invokeinterface #28,  1           // InterfaceMethod java/util/Iterator.hasNext:()Z
     167: ifeq          268
     170: aload         5
     172: invokeinterface #29,  1           // InterfaceMethod java/util/Iterator.next:()Ljava/lang/Object;
     177: checkcast     #30                 // class java/lang/String
     180: astore        6
     182: aload_0
     183: aload         6
     185: getstatic     #11                 // Field PROPERTY:Lcom/google/javascript/jscomp/AnalyzePrototypeProperties$SymbolType;
     188: invokespecial #10                 // Method getNameInfoForName:(Ljava/lang/String;Lcom/google/javascript/jscomp/AnalyzePrototypeProperties$SymbolType;)Lcom/google/javascript/jscomp/AnalyzePrototypeProperties$NameInfo;
     191: astore        7
     193: aload_2
     194: ifnonnull     214
     197: aload_0
     198: getfield      #5                  // Field symbolGraph:Lcom/google/javascript/jscomp/graph/LinkedDirectedGraph;
     201: aload_0
     202: getfield      #3                  // Field externNode:Lcom/google/javascript/jscomp/AnalyzePrototypeProperties$NameInfo;
     205: aconst_null
     206: aload         7
     208: invokevirtual #31                 // Method com/google/javascript/jscomp/graph/LinkedDirectedGraph.connect:(Ljava/lang/Object;Ljava/lang/Object;Ljava/lang/Object;)V
     211: goto          265
     214: aload_2
     215: invokevirtual #32                 // Method com/google/javascript/jscomp/JSModuleGraph.getAllModules:()Ljava/lang/Iterable;
     218: invokeinterface #33,  1           // InterfaceMethod java/lang/Iterable.iterator:()Ljava/util/Iterator;
     223: astore        8
     225: aload         8
     227: invokeinterface #28,  1           // InterfaceMethod java/util/Iterator.hasNext:()Z
     232: ifeq          265
     235: aload         8
     237: invokeinterface #29,  1           // InterfaceMethod java/util/Iterator.next:()Ljava/lang/Object;
     242: checkcast     #34                 // class com/google/javascript/jscomp/JSModule
     245: astore        9
     247: aload_0
     248: getfield      #5                  // Field symbolGraph:Lcom/google/javascript/jscomp/graph/LinkedDirectedGraph;
     251: aload_0
     252: getfield      #3                  // Field externNode:Lcom/google/javascript/jscomp/AnalyzePrototypeProperties$NameInfo;
     255: aload         9
     257: aload         7
     259: invokevirtual #31                 // Method com/google/javascript/jscomp/graph/LinkedDirectedGraph.connect:(Ljava/lang/Object;Ljava/lang/Object;Ljava/lang/Object;)V
     262: goto          225
     265: goto          160
     268: return

  public void process(com.google.javascript.rhino.Node, com.google.javascript.rhino.Node);
    Code:
       0: aload_0
       1: getfield      #22                 // Field canModifyExterns:Z
       4: ifne          24
       7: aload_0
       8: getfield      #6                  // Field compiler:Lcom/google/javascript/jscomp/AbstractCompiler;
      11: aload_1
      12: new           #35                 // class com/google/javascript/jscomp/AnalyzePrototypeProperties$ProcessExternProperties
      15: dup
      16: aload_0
      17: aconst_null
      18: invokespecial #36                 // Method com/google/javascript/jscomp/AnalyzePrototypeProperties$ProcessExternProperties."<init>":(Lcom/google/javascript/jscomp/AnalyzePrototypeProperties;Lcom/google/javascript/jscomp/AnalyzePrototypeProperties$1;)V
      21: invokestatic  #37                 // Method com/google/javascript/jscomp/NodeTraversal.traverse:(Lcom/google/javascript/jscomp/AbstractCompiler;Lcom/google/javascript/rhino/Node;Lcom/google/javascript/jscomp/NodeTraversal$Callback;)V
      24: aload_0
      25: getfield      #6                  // Field compiler:Lcom/google/javascript/jscomp/AbstractCompiler;
      28: aload_2
      29: new           #38                 // class com/google/javascript/jscomp/AnalyzePrototypeProperties$ProcessProperties
      32: dup
      33: aload_0
      34: aconst_null
      35: invokespecial #39                 // Method com/google/javascript/jscomp/AnalyzePrototypeProperties$ProcessProperties."<init>":(Lcom/google/javascript/jscomp/AnalyzePrototypeProperties;Lcom/google/javascript/jscomp/AnalyzePrototypeProperties$1;)V
      38: invokestatic  #37                 // Method com/google/javascript/jscomp/NodeTraversal.traverse:(Lcom/google/javascript/jscomp/AbstractCompiler;Lcom/google/javascript/rhino/Node;Lcom/google/javascript/jscomp/NodeTraversal$Callback;)V
      41: new           #40                 // class com/google/javascript/jscomp/AnalyzePrototypeProperties$PropagateReferences
      44: dup
      45: aload_0
      46: aconst_null
      47: invokespecial #41                 // Method com/google/javascript/jscomp/AnalyzePrototypeProperties$PropagateReferences."<init>":(Lcom/google/javascript/jscomp/AnalyzePrototypeProperties;Lcom/google/javascript/jscomp/AnalyzePrototypeProperties$1;)V
      50: invokestatic  #42                 // Method com/google/javascript/jscomp/graph/FixedPointGraphTraversal.newTraversal:(Lcom/google/javascript/jscomp/graph/FixedPointGraphTraversal$EdgeCallback;)Lcom/google/javascript/jscomp/graph/FixedPointGraphTraversal;
      53: astore_3
      54: aload_3
      55: aload_0
      56: getfield      #5                  // Field symbolGraph:Lcom/google/javascript/jscomp/graph/LinkedDirectedGraph;
      59: aload_0
      60: getfield      #3                  // Field externNode:Lcom/google/javascript/jscomp/AnalyzePrototypeProperties$NameInfo;
      63: aload_0
      64: getfield      #7                  // Field globalNode:Lcom/google/javascript/jscomp/AnalyzePrototypeProperties$NameInfo;
      67: invokestatic  #43                 // Method com/google/common/collect/ImmutableSet.of:(Ljava/lang/Object;Ljava/lang/Object;)Lcom/google/common/collect/ImmutableSet;
      70: invokevirtual #44                 // Method com/google/javascript/jscomp/graph/FixedPointGraphTraversal.computeFixedPoint:(Lcom/google/javascript/jscomp/graph/DiGraph;Ljava/util/Set;)V
      73: return

  public java.util.Collection<com.google.javascript.jscomp.AnalyzePrototypeProperties$NameInfo> getAllNameInfo();
    Code:
       0: aload_0
       1: getfield      #20                 // Field propertyNameInfo:Ljava/util/Map;
       4: invokeinterface #45,  1           // InterfaceMethod java/util/Map.values:()Ljava/util/Collection;
       9: invokestatic  #46                 // Method com/google/common/collect/Lists.newArrayList:(Ljava/lang/Iterable;)Ljava/util/ArrayList;
      12: astore_1
      13: aload_1
      14: aload_0
      15: getfield      #21                 // Field varNameInfo:Ljava/util/Map;
      18: invokeinterface #45,  1           // InterfaceMethod java/util/Map.values:()Ljava/util/Collection;
      23: invokeinterface #47,  2           // InterfaceMethod java/util/List.addAll:(Ljava/util/Collection;)Z
      28: pop
      29: aload_1
      30: areturn

  private com.google.javascript.jscomp.AnalyzePrototypeProperties$NameInfo getNameInfoForName(java.lang.String, com.google.javascript.jscomp.AnalyzePrototypeProperties$SymbolType);
    Code:
       0: aload_2
       1: getstatic     #11                 // Field PROPERTY:Lcom/google/javascript/jscomp/AnalyzePrototypeProperties$SymbolType;
       4: if_acmpne     14
       7: aload_0
       8: getfield      #20                 // Field propertyNameInfo:Ljava/util/Map;
      11: goto          18
      14: aload_0
      15: getfield      #21                 // Field varNameInfo:Ljava/util/Map;
      18: astore_3
      19: aload_3
      20: aload_1
      21: invokeinterface #48,  2           // InterfaceMethod java/util/Map.containsKey:(Ljava/lang/Object;)Z
      26: ifeq          40
      29: aload_3
      30: aload_1
      31: invokeinterface #49,  2           // InterfaceMethod java/util/Map.get:(Ljava/lang/Object;)Ljava/lang/Object;
      36: checkcast     #14                 // class com/google/javascript/jscomp/AnalyzePrototypeProperties$NameInfo
      39: areturn
      40: new           #14                 // class com/google/javascript/jscomp/AnalyzePrototypeProperties$NameInfo
      43: dup
      44: aload_0
      45: aload_1
      46: invokespecial #16                 // Method com/google/javascript/jscomp/AnalyzePrototypeProperties$NameInfo."<init>":(Lcom/google/javascript/jscomp/AnalyzePrototypeProperties;Ljava/lang/String;)V
      49: astore        4
      51: aload_3
      52: aload_1
      53: aload         4
      55: invokeinterface #50,  3           // InterfaceMethod java/util/Map.put:(Ljava/lang/Object;Ljava/lang/Object;)Ljava/lang/Object;
      60: pop
      61: aload_0
      62: getfield      #5                  // Field symbolGraph:Lcom/google/javascript/jscomp/graph/LinkedDirectedGraph;
      65: aload         4
      67: invokevirtual #25                 // Method com/google/javascript/jscomp/graph/LinkedDirectedGraph.createNode:(Ljava/lang/Object;)Lcom/google/javascript/jscomp/graph/GraphNode;
      70: pop
      71: aload         4
      73: areturn

  static com.google.javascript.jscomp.AnalyzePrototypeProperties$SymbolType access$300();
    Code:
       0: getstatic     #11                 // Field PROPERTY:Lcom/google/javascript/jscomp/AnalyzePrototypeProperties$SymbolType;
       3: areturn

  static com.google.javascript.jscomp.AnalyzePrototypeProperties$NameInfo access$400(com.google.javascript.jscomp.AnalyzePrototypeProperties, java.lang.String, com.google.javascript.jscomp.AnalyzePrototypeProperties$SymbolType);
    Code:
       0: aload_0
       1: aload_1
       2: aload_2
       3: invokespecial #10                 // Method getNameInfoForName:(Ljava/lang/String;Lcom/google/javascript/jscomp/AnalyzePrototypeProperties$SymbolType;)Lcom/google/javascript/jscomp/AnalyzePrototypeProperties$NameInfo;
       6: areturn

  static com.google.javascript.jscomp.AnalyzePrototypeProperties$SymbolType access$500();
    Code:
       0: getstatic     #9                  // Field VAR:Lcom/google/javascript/jscomp/AnalyzePrototypeProperties$SymbolType;
       3: areturn

  static com.google.javascript.jscomp.AnalyzePrototypeProperties$NameInfo access$600(com.google.javascript.jscomp.AnalyzePrototypeProperties);
    Code:
       0: aload_0
       1: getfield      #8                  // Field anonymousNode:Lcom/google/javascript/jscomp/AnalyzePrototypeProperties$NameInfo;
       4: areturn

  static com.google.javascript.jscomp.AnalyzePrototypeProperties$NameInfo access$700(com.google.javascript.jscomp.AnalyzePrototypeProperties);
    Code:
       0: aload_0
       1: getfield      #7                  // Field globalNode:Lcom/google/javascript/jscomp/AnalyzePrototypeProperties$NameInfo;
       4: areturn

  static com.google.javascript.jscomp.AbstractCompiler access$800(com.google.javascript.jscomp.AnalyzePrototypeProperties);
    Code:
       0: aload_0
       1: getfield      #6                  // Field compiler:Lcom/google/javascript/jscomp/AbstractCompiler;
       4: areturn

  static com.google.javascript.jscomp.graph.LinkedDirectedGraph access$1000(com.google.javascript.jscomp.AnalyzePrototypeProperties);
    Code:
       0: aload_0
       1: getfield      #5                  // Field symbolGraph:Lcom/google/javascript/jscomp/graph/LinkedDirectedGraph;
       4: areturn

  static boolean access$1100(com.google.javascript.jscomp.AnalyzePrototypeProperties);
    Code:
       0: aload_0
       1: getfield      #4                  // Field anchorUnusedVars:Z
       4: ireturn

  static com.google.javascript.jscomp.AnalyzePrototypeProperties$NameInfo access$1200(com.google.javascript.jscomp.AnalyzePrototypeProperties);
    Code:
       0: aload_0
       1: getfield      #3                  // Field externNode:Lcom/google/javascript/jscomp/AnalyzePrototypeProperties$NameInfo;
       4: areturn

  static com.google.javascript.jscomp.JSModule access$1300(com.google.javascript.jscomp.AnalyzePrototypeProperties);
    Code:
       0: aload_0
       1: getfield      #2                  // Field firstModule:Lcom/google/javascript/jscomp/JSModule;
       4: areturn

  static com.google.javascript.jscomp.JSModuleGraph access$1400(com.google.javascript.jscomp.AnalyzePrototypeProperties);
    Code:
       0: aload_0
       1: getfield      #1                  // Field moduleGraph:Lcom/google/javascript/jscomp/JSModuleGraph;
       4: areturn

  static {};
    Code:
       0: getstatic     #51                 // Field com/google/javascript/jscomp/AnalyzePrototypeProperties$SymbolType.PROPERTY:Lcom/google/javascript/jscomp/AnalyzePrototypeProperties$SymbolType;
       3: putstatic     #11                 // Field PROPERTY:Lcom/google/javascript/jscomp/AnalyzePrototypeProperties$SymbolType;
       6: getstatic     #52                 // Field com/google/javascript/jscomp/AnalyzePrototypeProperties$SymbolType.VAR:Lcom/google/javascript/jscomp/AnalyzePrototypeProperties$SymbolType;
       9: putstatic     #9                  // Field VAR:Lcom/google/javascript/jscomp/AnalyzePrototypeProperties$SymbolType;
      12: ldc           #53                 // String length
      14: ldc           #54                 // String toString
      16: ldc           #55                 // String valueOf
      18: invokestatic  #56                 // Method com/google/common/collect/ImmutableSet.of:(Ljava/lang/Object;Ljava/lang/Object;Ljava/lang/Object;)Lcom/google/common/collect/ImmutableSet;
      21: putstatic     #26                 // Field IMPLICITLY_USED_PROPERTIES:Ljava/util/Set;
      24: return
}
