Compiled from "CheckSideEffects.java"
class com.google.javascript.jscomp.CheckSideEffects$StripProtection extends com.google.javascript.jscomp.NodeTraversal$AbstractPostOrderCallback implements com.google.javascript.jscomp.CompilerPass {
  private final com.google.javascript.jscomp.AbstractCompiler compiler;

  com.google.javascript.jscomp.CheckSideEffects$StripProtection(com.google.javascript.jscomp.AbstractCompiler);
    Code:
       0: aload_0
       1: invokespecial #2                  // Method com/google/javascript/jscomp/NodeTraversal$AbstractPostOrderCallback."<init>":()V
       4: aload_0
       5: aload_1
       6: putfield      #3                  // Field compiler:Lcom/google/javascript/jscomp/AbstractCompiler;
       9: return

  public void process(com.google.javascript.rhino.Node, com.google.javascript.rhino.Node);
    Code:
       0: aload_0
       1: getfield      #3                  // Field compiler:Lcom/google/javascript/jscomp/AbstractCompiler;
       4: aload_2
       5: aload_0
       6: invokestatic  #4                  // Method com/google/javascript/jscomp/NodeTraversal.traverse:(Lcom/google/javascript/jscomp/AbstractCompiler;Lcom/google/javascript/rhino/Node;Lcom/google/javascript/jscomp/NodeTraversal$Callback;)V
       9: return

  public void visit(com.google.javascript.jscomp.NodeTraversal, com.google.javascript.rhino.Node, com.google.javascript.rhino.Node);
    Code:
       0: aload_2
       1: invokevirtual #5                  // Method com/google/javascript/rhino/Node.isCall:()Z
       4: ifeq          51
       7: aload_2
       8: invokevirtual #6                  // Method com/google/javascript/rhino/Node.getFirstChild:()Lcom/google/javascript/rhino/Node;
      11: astore        4
      13: aload         4
      15: invokevirtual #7                  // Method com/google/javascript/rhino/Node.isName:()Z
      18: ifeq          51
      21: aload         4
      23: invokevirtual #8                  // Method com/google/javascript/rhino/Node.getString:()Ljava/lang/String;
      26: ldc           #9                  // String JSCOMPILER_PRESERVE
      28: invokevirtual #10                 // Method java/lang/String.equals:(Ljava/lang/Object;)Z
      31: ifeq          51
      34: aload_2
      35: invokevirtual #11                 // Method com/google/javascript/rhino/Node.getLastChild:()Lcom/google/javascript/rhino/Node;
      38: astore        5
      40: aload_2
      41: invokevirtual #12                 // Method com/google/javascript/rhino/Node.detachChildren:()V
      44: aload_3
      45: aload_2
      46: aload         5
      48: invokevirtual #13                 // Method com/google/javascript/rhino/Node.replaceChild:(Lcom/google/javascript/rhino/Node;Lcom/google/javascript/rhino/Node;)V
      51: return
}
