Compiled from "ClosureCodeRemoval.java"
class com.google.javascript.jscomp.ClosureCodeRemoval$FindAbstractMethods extends com.google.javascript.jscomp.NodeTraversal$AbstractPostOrderCallback {
  final com.google.javascript.jscomp.ClosureCodeRemoval this$0;

  private com.google.javascript.jscomp.ClosureCodeRemoval$FindAbstractMethods(com.google.javascript.jscomp.ClosureCodeRemoval);
    Code:
       0: aload_0
       1: aload_1
       2: putfield      #3                  // Field this$0:Lcom/google/javascript/jscomp/ClosureCodeRemoval;
       5: aload_0
       6: invokespecial #4                  // Method com/google/javascript/jscomp/NodeTraversal$AbstractPostOrderCallback."<init>":()V
       9: return

  public void visit(com.google.javascript.jscomp.NodeTraversal, com.google.javascript.rhino.Node, com.google.javascript.rhino.Node);
    Code:
       0: aload_2
       1: invokevirtual #5                  // Method com/google/javascript/rhino/Node.isAssign:()Z
       4: ifeq          75
       7: aload_2
       8: invokevirtual #6                  // Method com/google/javascript/rhino/Node.getFirstChild:()Lcom/google/javascript/rhino/Node;
      11: astore        4
      13: aload_2
      14: invokevirtual #7                  // Method com/google/javascript/rhino/Node.getLastChild:()Lcom/google/javascript/rhino/Node;
      17: astore        5
      19: aload         4
      21: invokevirtual #8                  // Method com/google/javascript/rhino/Node.isQualifiedName:()Z
      24: ifeq          75
      27: aload         5
      29: invokevirtual #8                  // Method com/google/javascript/rhino/Node.isQualifiedName:()Z
      32: ifeq          75
      35: aload         5
      37: ldc           #9                  // String goog.abstractMethod
      39: invokevirtual #10                 // Method com/google/javascript/rhino/Node.matchesQualifiedName:(Ljava/lang/String;)Z
      42: ifeq          75
      45: aload_0
      46: getfield      #3                  // Field this$0:Lcom/google/javascript/jscomp/ClosureCodeRemoval;
      49: invokestatic  #11                 // Method com/google/javascript/jscomp/ClosureCodeRemoval.access$100:(Lcom/google/javascript/jscomp/ClosureCodeRemoval;)Ljava/util/List;
      52: new           #12                 // class com/google/javascript/jscomp/ClosureCodeRemoval$RemovableAssignment
      55: dup
      56: aload_0
      57: getfield      #3                  // Field this$0:Lcom/google/javascript/jscomp/ClosureCodeRemoval;
      60: aload_2
      61: invokevirtual #6                  // Method com/google/javascript/rhino/Node.getFirstChild:()Lcom/google/javascript/rhino/Node;
      64: aload_2
      65: aload_1
      66: invokespecial #13                 // Method com/google/javascript/jscomp/ClosureCodeRemoval$RemovableAssignment."<init>":(Lcom/google/javascript/jscomp/ClosureCodeRemoval;Lcom/google/javascript/rhino/Node;Lcom/google/javascript/rhino/Node;Lcom/google/javascript/jscomp/NodeTraversal;)V
      69: invokeinterface #14,  2           // InterfaceMethod java/util/List.add:(Ljava/lang/Object;)Z
      74: pop
      75: return

  com.google.javascript.jscomp.ClosureCodeRemoval$FindAbstractMethods(com.google.javascript.jscomp.ClosureCodeRemoval, com.google.javascript.jscomp.ClosureCodeRemoval$1);
    Code:
       0: aload_0
       1: aload_1
       2: invokespecial #2                  // Method "<init>":(Lcom/google/javascript/jscomp/ClosureCodeRemoval;)V
       5: return
}
