Compiled from "ClosureOptimizePrimitives.java"
final class com.google.javascript.jscomp.ClosureOptimizePrimitives implements com.google.javascript.jscomp.CompilerPass {
  private final com.google.javascript.jscomp.AbstractCompiler compiler;

  com.google.javascript.jscomp.ClosureOptimizePrimitives(com.google.javascript.jscomp.AbstractCompiler);
    Code:
       0: aload_0
       1: invokespecial #1                  // Method java/lang/Object."<init>":()V
       4: aload_0
       5: aload_1
       6: putfield      #2                  // Field compiler:Lcom/google/javascript/jscomp/AbstractCompiler;
       9: return

  public void process(com.google.javascript.rhino.Node, com.google.javascript.rhino.Node);
    Code:
       0: new           #3                  // class com/google/javascript/jscomp/ClosureOptimizePrimitives$FindObjectCreateCalls
       3: dup
       4: aconst_null
       5: invokespecial #4                  // Method com/google/javascript/jscomp/ClosureOptimizePrimitives$FindObjectCreateCalls."<init>":(Lcom/google/javascript/jscomp/ClosureOptimizePrimitives$1;)V
       8: astore_3
       9: aload_0
      10: getfield      #2                  // Field compiler:Lcom/google/javascript/jscomp/AbstractCompiler;
      13: aload_2
      14: aload_3
      15: invokestatic  #5                  // Method com/google/javascript/jscomp/NodeTraversal.traverse:(Lcom/google/javascript/jscomp/AbstractCompiler;Lcom/google/javascript/rhino/Node;Lcom/google/javascript/jscomp/NodeTraversal$Callback;)V
      18: aload_0
      19: aload_3
      20: getfield      #6                  // Field com/google/javascript/jscomp/ClosureOptimizePrimitives$FindObjectCreateCalls.callNodes:Ljava/util/List;
      23: invokespecial #7                  // Method processObjectCreateCalls:(Ljava/util/List;)V
      26: return

  private void processObjectCreateCalls(java.util.List<com.google.javascript.rhino.Node>);
    Code:
       0: aload_1
       1: invokeinterface #8,  1            // InterfaceMethod java/util/List.iterator:()Ljava/util/Iterator;
       6: astore_2
       7: aload_2
       8: invokeinterface #9,  1            // InterfaceMethod java/util/Iterator.hasNext:()Z
      13: ifeq          162
      16: aload_2
      17: invokeinterface #10,  1           // InterfaceMethod java/util/Iterator.next:()Ljava/lang/Object;
      22: checkcast     #11                 // class com/google/javascript/rhino/Node
      25: astore_3
      26: aload_3
      27: invokevirtual #12                 // Method com/google/javascript/rhino/Node.getFirstChild:()Lcom/google/javascript/rhino/Node;
      30: invokevirtual #13                 // Method com/google/javascript/rhino/Node.getNext:()Lcom/google/javascript/rhino/Node;
      33: astore        4
      35: aload         4
      37: invokestatic  #14                 // Method canOptimizeObjectCreate:(Lcom/google/javascript/rhino/Node;)Z
      40: ifeq          159
      43: iconst_0
      44: anewarray     #11                 // class com/google/javascript/rhino/Node
      47: invokestatic  #15                 // Method com/google/javascript/rhino/IR.objectlit:([Lcom/google/javascript/rhino/Node;)Lcom/google/javascript/rhino/Node;
      50: aload_3
      51: invokevirtual #16                 // Method com/google/javascript/rhino/Node.srcref:(Lcom/google/javascript/rhino/Node;)Lcom/google/javascript/rhino/Node;
      54: astore        5
      56: aload         4
      58: ifnull        142
      61: aload         4
      63: astore        6
      65: aload         4
      67: invokevirtual #13                 // Method com/google/javascript/rhino/Node.getNext:()Lcom/google/javascript/rhino/Node;
      70: astore        7
      72: aload         7
      74: invokevirtual #13                 // Method com/google/javascript/rhino/Node.getNext:()Lcom/google/javascript/rhino/Node;
      77: astore        4
      79: aload_3
      80: aload         6
      82: invokevirtual #17                 // Method com/google/javascript/rhino/Node.removeChild:(Lcom/google/javascript/rhino/Node;)V
      85: aload_3
      86: aload         7
      88: invokevirtual #17                 // Method com/google/javascript/rhino/Node.removeChild:(Lcom/google/javascript/rhino/Node;)V
      91: aload         6
      93: invokevirtual #18                 // Method com/google/javascript/rhino/Node.isString:()Z
      96: ifne          114
      99: aload         6
     101: invokestatic  #19                 // Method com/google/javascript/jscomp/NodeUtil.getStringValue:(Lcom/google/javascript/rhino/Node;)Ljava/lang/String;
     104: invokestatic  #20                 // Method com/google/javascript/rhino/IR.string:(Ljava/lang/String;)Lcom/google/javascript/rhino/Node;
     107: aload         6
     109: invokevirtual #16                 // Method com/google/javascript/rhino/Node.srcref:(Lcom/google/javascript/rhino/Node;)Lcom/google/javascript/rhino/Node;
     112: astore        6
     114: aload         6
     116: sipush        154
     119: invokevirtual #22                 // Method com/google/javascript/rhino/Node.setType:(I)V
     122: aload         6
     124: invokevirtual #23                 // Method com/google/javascript/rhino/Node.setQuotedString:()V
     127: aload         5
     129: aload         6
     131: aload         7
     133: invokestatic  #24                 // Method com/google/javascript/rhino/IR.propdef:(Lcom/google/javascript/rhino/Node;Lcom/google/javascript/rhino/Node;)Lcom/google/javascript/rhino/Node;
     136: invokevirtual #25                 // Method com/google/javascript/rhino/Node.addChildToBack:(Lcom/google/javascript/rhino/Node;)V
     139: goto          56
     142: aload_3
     143: invokevirtual #26                 // Method com/google/javascript/rhino/Node.getParent:()Lcom/google/javascript/rhino/Node;
     146: aload_3
     147: aload         5
     149: invokevirtual #27                 // Method com/google/javascript/rhino/Node.replaceChild:(Lcom/google/javascript/rhino/Node;Lcom/google/javascript/rhino/Node;)V
     152: aload_0
     153: getfield      #2                  // Field compiler:Lcom/google/javascript/jscomp/AbstractCompiler;
     156: invokevirtual #28                 // Method com/google/javascript/jscomp/AbstractCompiler.reportCodeChange:()V
     159: goto          7
     162: return

  private static boolean canOptimizeObjectCreate(com.google.javascript.rhino.Node);
    Code:
       0: aload_0
       1: astore_1
       2: aload_1
       3: ifnull        41
       6: aload_1
       7: invokevirtual #18                 // Method com/google/javascript/rhino/Node.isString:()Z
      10: ifne          22
      13: aload_1
      14: invokevirtual #29                 // Method com/google/javascript/rhino/Node.isNumber:()Z
      17: ifne          22
      20: iconst_0
      21: ireturn
      22: aload_1
      23: invokevirtual #13                 // Method com/google/javascript/rhino/Node.getNext:()Lcom/google/javascript/rhino/Node;
      26: astore_1
      27: aload_1
      28: ifnonnull     33
      31: iconst_0
      32: ireturn
      33: aload_1
      34: invokevirtual #13                 // Method com/google/javascript/rhino/Node.getNext:()Lcom/google/javascript/rhino/Node;
      37: astore_1
      38: goto          2
      41: iconst_1
      42: ireturn
}
