Compiled from "ClosureCodeRemoval.java"
class com.google.javascript.jscomp.ClosureCodeRemoval$RemovableAssignment {
  final com.google.javascript.rhino.Node node;

  final com.google.javascript.rhino.Node parent;

  final java.util.List<com.google.javascript.rhino.Node> assignAncestors;

  final com.google.javascript.rhino.Node lastAncestor;

  final com.google.javascript.jscomp.ClosureCodeRemoval this$0;

  public com.google.javascript.jscomp.ClosureCodeRemoval$RemovableAssignment(com.google.javascript.jscomp.ClosureCodeRemoval, com.google.javascript.rhino.Node, com.google.javascript.rhino.Node, com.google.javascript.jscomp.NodeTraversal);
    Code:
       0: aload_0
       1: aload_1
       2: putfield      #1                  // Field this$0:Lcom/google/javascript/jscomp/ClosureCodeRemoval;
       5: aload_0
       6: invokespecial #2                  // Method java/lang/Object."<init>":()V
       9: aload_0
      10: invokestatic  #3                  // Method com/google/common/collect/Lists.newArrayList:()Ljava/util/ArrayList;
      13: putfield      #4                  // Field assignAncestors:Ljava/util/List;
      16: aload_0
      17: aload_2
      18: putfield      #5                  // Field node:Lcom/google/javascript/rhino/Node;
      21: aload_0
      22: aload_3
      23: putfield      #6                  // Field parent:Lcom/google/javascript/rhino/Node;
      26: aload_3
      27: astore        5
      29: aload         5
      31: invokevirtual #7                  // Method com/google/javascript/rhino/Node.getParent:()Lcom/google/javascript/rhino/Node;
      34: astore        5
      36: aload_0
      37: getfield      #4                  // Field assignAncestors:Ljava/util/List;
      40: aload         5
      42: invokeinterface #8,  2            // InterfaceMethod java/util/List.add:(Ljava/lang/Object;)Z
      47: pop
      48: aload         5
      50: invokevirtual #9                  // Method com/google/javascript/rhino/Node.isAssign:()Z
      53: ifeq          67
      56: aload         5
      58: invokevirtual #10                 // Method com/google/javascript/rhino/Node.getFirstChild:()Lcom/google/javascript/rhino/Node;
      61: invokevirtual #11                 // Method com/google/javascript/rhino/Node.isQualifiedName:()Z
      64: ifne          29
      67: aload_0
      68: aload         5
      70: invokevirtual #7                  // Method com/google/javascript/rhino/Node.getParent:()Lcom/google/javascript/rhino/Node;
      73: putfield      #12                 // Field lastAncestor:Lcom/google/javascript/rhino/Node;
      76: return

  public void remove();
    Code:
       0: aload_0
       1: getfield      #5                  // Field node:Lcom/google/javascript/rhino/Node;
       4: invokevirtual #13                 // Method com/google/javascript/rhino/Node.getNext:()Lcom/google/javascript/rhino/Node;
       7: astore_1
       8: aload_0
       9: getfield      #6                  // Field parent:Lcom/google/javascript/rhino/Node;
      12: astore_2
      13: aload_0
      14: getfield      #4                  // Field assignAncestors:Ljava/util/List;
      17: invokeinterface #14,  1           // InterfaceMethod java/util/List.iterator:()Ljava/util/Iterator;
      22: astore_3
      23: aload_3
      24: invokeinterface #15,  1           // InterfaceMethod java/util/Iterator.hasNext:()Z
      29: ifeq          81
      32: aload_3
      33: invokeinterface #16,  1           // InterfaceMethod java/util/Iterator.next:()Ljava/lang/Object;
      38: checkcast     #17                 // class com/google/javascript/rhino/Node
      41: astore        4
      43: aload         4
      45: invokevirtual #18                 // Method com/google/javascript/rhino/Node.isExprResult:()Z
      48: ifeq          63
      51: aload_0
      52: getfield      #12                 // Field lastAncestor:Lcom/google/javascript/rhino/Node;
      55: aload         4
      57: invokevirtual #19                 // Method com/google/javascript/rhino/Node.removeChild:(Lcom/google/javascript/rhino/Node;)V
      60: goto          75
      63: aload_1
      64: invokevirtual #20                 // Method com/google/javascript/rhino/Node.detachFromParent:()Lcom/google/javascript/rhino/Node;
      67: pop
      68: aload         4
      70: aload_2
      71: aload_1
      72: invokevirtual #21                 // Method com/google/javascript/rhino/Node.replaceChild:(Lcom/google/javascript/rhino/Node;Lcom/google/javascript/rhino/Node;)V
      75: aload         4
      77: astore_2
      78: goto          23
      81: aload_0
      82: getfield      #1                  // Field this$0:Lcom/google/javascript/jscomp/ClosureCodeRemoval;
      85: invokestatic  #22                 // Method com/google/javascript/jscomp/ClosureCodeRemoval.access$000:(Lcom/google/javascript/jscomp/ClosureCodeRemoval;)Lcom/google/javascript/jscomp/AbstractCompiler;
      88: invokevirtual #23                 // Method com/google/javascript/jscomp/AbstractCompiler.reportCodeChange:()V
      91: return
}
