Compiled from "ControlFlowGraph.java"
public class com.google.javascript.jscomp.ControlFlowGraph<N> extends com.google.javascript.jscomp.graph.LinkedDirectedGraph<N, com.google.javascript.jscomp.ControlFlowGraph$Branch> {
  private final com.google.javascript.jscomp.graph.DiGraph$DiGraphNode<N, com.google.javascript.jscomp.ControlFlowGraph$Branch> implicitReturn;

  private final com.google.javascript.jscomp.graph.DiGraph$DiGraphNode<N, com.google.javascript.jscomp.ControlFlowGraph$Branch> entry;

  com.google.javascript.jscomp.ControlFlowGraph(N, boolean, boolean);
    Code:
       0: aload_0
       1: iload_2
       2: iload_3
       3: invokespecial #1                  // Method com/google/javascript/jscomp/graph/LinkedDirectedGraph."<init>":(ZZ)V
       6: aload_0
       7: aload_0
       8: aconst_null
       9: invokevirtual #2                  // Method createDirectedGraphNode:(Ljava/lang/Object;)Lcom/google/javascript/jscomp/graph/LinkedDirectedGraph$LinkedDirectedGraphNode;
      12: putfield      #3                  // Field implicitReturn:Lcom/google/javascript/jscomp/graph/DiGraph$DiGraphNode;
      15: aload_0
      16: aload_0
      17: aload_1
      18: invokevirtual #2                  // Method createDirectedGraphNode:(Ljava/lang/Object;)Lcom/google/javascript/jscomp/graph/LinkedDirectedGraph$LinkedDirectedGraphNode;
      21: putfield      #4                  // Field entry:Lcom/google/javascript/jscomp/graph/DiGraph$DiGraphNode;
      24: return

  public com.google.javascript.jscomp.graph.DiGraph$DiGraphNode<N, com.google.javascript.jscomp.ControlFlowGraph$Branch> getImplicitReturn();
    Code:
       0: aload_0
       1: getfield      #3                  // Field implicitReturn:Lcom/google/javascript/jscomp/graph/DiGraph$DiGraphNode;
       4: areturn

  public com.google.javascript.jscomp.graph.DiGraph$DiGraphNode<N, com.google.javascript.jscomp.ControlFlowGraph$Branch> getEntry();
    Code:
       0: aload_0
       1: getfield      #4                  // Field entry:Lcom/google/javascript/jscomp/graph/DiGraph$DiGraphNode;
       4: areturn

  public boolean isImplicitReturn(com.google.javascript.jscomp.graph.DiGraph$DiGraphNode<N, com.google.javascript.jscomp.ControlFlowGraph$Branch>);
    Code:
       0: aload_1
       1: aload_0
       2: getfield      #3                  // Field implicitReturn:Lcom/google/javascript/jscomp/graph/DiGraph$DiGraphNode;
       5: if_acmpne     12
       8: iconst_1
       9: goto          13
      12: iconst_0
      13: ireturn

  public java.util.Comparator<com.google.javascript.jscomp.graph.DiGraph$DiGraphNode<N, com.google.javascript.jscomp.ControlFlowGraph$Branch>> getOptionalNodeComparator(boolean);
    Code:
       0: aconst_null
       1: areturn

  public static boolean isEnteringNewCfgNode(com.google.javascript.rhino.Node);
    Code:
       0: aload_0
       1: invokevirtual #5                  // Method com/google/javascript/rhino/Node.getParent:()Lcom/google/javascript/rhino/Node;
       4: astore_1
       5: aload_1
       6: invokevirtual #6                  // Method com/google/javascript/rhino/Node.getType:()I
       9: lookupswitch  { // 12
                    77: 116
                   105: 118
                   108: 135
                   110: 184
                   111: 184
                   113: 135
                   114: 135
                   115: 149
                   119: 184
                   120: 184
                   125: 116
                   132: 116
               default: 198
          }
     116: iconst_1
     117: ireturn
     118: aload_0
     119: aload_1
     120: invokevirtual #7                  // Method com/google/javascript/rhino/Node.getFirstChild:()Lcom/google/javascript/rhino/Node;
     123: invokevirtual #8                  // Method com/google/javascript/rhino/Node.getNext:()Lcom/google/javascript/rhino/Node;
     126: if_acmpeq     133
     129: iconst_1
     130: goto          134
     133: iconst_0
     134: ireturn
     135: aload_1
     136: invokestatic  #9                  // Method com/google/javascript/jscomp/NodeUtil.getConditionExpression:(Lcom/google/javascript/rhino/Node;)Lcom/google/javascript/rhino/Node;
     139: aload_0
     140: if_acmpeq     147
     143: iconst_1
     144: goto          148
     147: iconst_0
     148: ireturn
     149: aload_1
     150: invokestatic  #10                 // Method com/google/javascript/jscomp/NodeUtil.isForIn:(Lcom/google/javascript/rhino/Node;)Z
     153: ifeq          170
     156: aload_0
     157: aload_1
     158: invokevirtual #7                  // Method com/google/javascript/rhino/Node.getFirstChild:()Lcom/google/javascript/rhino/Node;
     161: if_acmpeq     168
     164: iconst_1
     165: goto          169
     168: iconst_0
     169: ireturn
     170: aload_1
     171: invokestatic  #9                  // Method com/google/javascript/jscomp/NodeUtil.getConditionExpression:(Lcom/google/javascript/rhino/Node;)Lcom/google/javascript/rhino/Node;
     174: aload_0
     175: if_acmpeq     182
     178: iconst_1
     179: goto          183
     182: iconst_0
     183: ireturn
     184: aload_0
     185: aload_1
     186: invokevirtual #7                  // Method com/google/javascript/rhino/Node.getFirstChild:()Lcom/google/javascript/rhino/Node;
     189: if_acmpeq     196
     192: iconst_1
     193: goto          197
     196: iconst_0
     197: ireturn
     198: iconst_0
     199: ireturn

  public java.lang.String toString();
    Code:
       0: ldc           #11                 // String CFG:\n
       2: astore_1
       3: aload_0
       4: invokevirtual #12                 // Method getGraphvizEdges:()Ljava/util/List;
       7: invokeinterface #13,  1           // InterfaceMethod java/util/List.iterator:()Ljava/util/Iterator;
      12: astore_2
      13: aload_2
      14: invokeinterface #14,  1           // InterfaceMethod java/util/Iterator.hasNext:()Z
      19: ifeq          62
      22: aload_2
      23: invokeinterface #15,  1           // InterfaceMethod java/util/Iterator.next:()Ljava/lang/Object;
      28: checkcast     #16                 // class com/google/javascript/jscomp/graph/GraphvizGraph$GraphvizEdge
      31: astore_3
      32: new           #17                 // class java/lang/StringBuilder
      35: dup
      36: invokespecial #18                 // Method java/lang/StringBuilder."<init>":()V
      39: aload_1
      40: invokevirtual #19                 // Method java/lang/StringBuilder.append:(Ljava/lang/String;)Ljava/lang/StringBuilder;
      43: aload_3
      44: invokevirtual #20                 // Method java/lang/Object.toString:()Ljava/lang/String;
      47: invokevirtual #19                 // Method java/lang/StringBuilder.append:(Ljava/lang/String;)Ljava/lang/StringBuilder;
      50: bipush        10
      52: invokevirtual #21                 // Method java/lang/StringBuilder.append:(C)Ljava/lang/StringBuilder;
      55: invokevirtual #22                 // Method java/lang/StringBuilder.toString:()Ljava/lang/String;
      58: astore_1
      59: goto          13
      62: aload_1
      63: areturn
}
