Compiled from "DefaultPassConfig.java"
class com.google.javascript.jscomp.DefaultPassConfig$110 extends com.google.javascript.jscomp.PassFactory {
  final com.google.javascript.jscomp.DefaultPassConfig this$0;

  com.google.javascript.jscomp.DefaultPassConfig$110(com.google.javascript.jscomp.DefaultPassConfig, java.lang.String, boolean);
    Code:
       0: aload_0
       1: aload_1
       2: putfield      #1                  // Field this$0:Lcom/google/javascript/jscomp/DefaultPassConfig;
       5: aload_0
       6: aload_2
       7: iload_3
       8: invokespecial #2                  // Method com/google/javascript/jscomp/PassFactory."<init>":(Ljava/lang/String;Z)V
      11: return

  protected com.google.javascript.jscomp.CompilerPass create(com.google.javascript.jscomp.AbstractCompiler);
    Code:
       0: aload_0
       1: getfield      #1                  // Field this$0:Lcom/google/javascript/jscomp/DefaultPassConfig;
       4: getfield      #3                  // Field com/google/javascript/jscomp/DefaultPassConfig.options:Lcom/google/javascript/jscomp/CompilerOptions;
       7: getfield      #4                  // Field com/google/javascript/jscomp/CompilerOptions.aggressiveRenaming:Z
      10: ifeq          29
      13: new           #5                  // class com/google/javascript/jscomp/RenameLabels
      16: dup
      17: aload_1
      18: aload_0
      19: getfield      #1                  // Field this$0:Lcom/google/javascript/jscomp/DefaultPassConfig;
      22: invokestatic  #6                  // Method com/google/javascript/jscomp/DefaultPassConfig.access$1800:(Lcom/google/javascript/jscomp/DefaultPassConfig;)Lcom/google/javascript/jscomp/NameGenerator;
      25: invokespecial #7                  // Method com/google/javascript/jscomp/RenameLabels."<init>":(Lcom/google/javascript/jscomp/AbstractCompiler;Lcom/google/javascript/jscomp/NameGenerator;)V
      28: areturn
      29: new           #5                  // class com/google/javascript/jscomp/RenameLabels
      32: dup
      33: aload_1
      34: invokespecial #8                  // Method com/google/javascript/jscomp/RenameLabels."<init>":(Lcom/google/javascript/jscomp/AbstractCompiler;)V
      37: areturn
}
