Compiled from "DefaultPassConfig.java"
class com.google.javascript.jscomp.DefaultPassConfig$80$1 implements com.google.javascript.jscomp.CompilerPass {
  final com.google.javascript.jscomp.AbstractCompiler val$compiler;

  final com.google.javascript.jscomp.DefaultPassConfig$80 this$1;

  com.google.javascript.jscomp.DefaultPassConfig$80$1(com.google.javascript.jscomp.DefaultPassConfig$80, com.google.javascript.jscomp.AbstractCompiler);
    Code:
       0: aload_0
       1: aload_1
       2: putfield      #1                  // Field this$1:Lcom/google/javascript/jscomp/DefaultPassConfig$80;
       5: aload_0
       6: aload_2
       7: putfield      #2                  // Field val$compiler:Lcom/google/javascript/jscomp/AbstractCompiler;
      10: aload_0
      11: invokespecial #3                  // Method java/lang/Object."<init>":()V
      14: return

  public void process(com.google.javascript.rhino.Node, com.google.javascript.rhino.Node);
    Code:
       0: new           #4                  // class com/google/javascript/jscomp/NameAnalyzer
       3: dup
       4: aload_0
       5: getfield      #2                  // Field val$compiler:Lcom/google/javascript/jscomp/AbstractCompiler;
       8: iconst_0
       9: invokespecial #5                  // Method com/google/javascript/jscomp/NameAnalyzer."<init>":(Lcom/google/javascript/jscomp/AbstractCompiler;Z)V
      12: astore_3
      13: aload_3
      14: aload_1
      15: aload_2
      16: invokevirtual #6                  // Method com/google/javascript/jscomp/NameAnalyzer.process:(Lcom/google/javascript/rhino/Node;Lcom/google/javascript/rhino/Node;)V
      19: aload_0
      20: getfield      #1                  // Field this$1:Lcom/google/javascript/jscomp/DefaultPassConfig$80;
      23: getfield      #7                  // Field com/google/javascript/jscomp/DefaultPassConfig$80.this$0:Lcom/google/javascript/jscomp/DefaultPassConfig;
      26: getfield      #8                  // Field com/google/javascript/jscomp/DefaultPassConfig.options:Lcom/google/javascript/jscomp/CompilerOptions;
      29: getfield      #9                  // Field com/google/javascript/jscomp/CompilerOptions.reportPath:Ljava/lang/String;
      32: astore        4
      34: aload         4
      36: ifnull        126
      39: aload_0
      40: getfield      #1                  // Field this$1:Lcom/google/javascript/jscomp/DefaultPassConfig$80;
      43: invokestatic  #10                 // Method com/google/javascript/jscomp/DefaultPassConfig$80.access$1100:(Lcom/google/javascript/jscomp/DefaultPassConfig$80;)Z
      46: ifeq          71
      49: aload_3
      50: invokevirtual #11                 // Method com/google/javascript/jscomp/NameAnalyzer.getHtmlReport:()Ljava/lang/String;
      53: new           #12                 // class java/io/File
      56: dup
      57: aload         4
      59: invokespecial #13                 // Method java/io/File."<init>":(Ljava/lang/String;)V
      62: getstatic     #14                 // Field java/nio/charset/StandardCharsets.UTF_8:Ljava/nio/charset/Charset;
      65: invokestatic  #15                 // Method com/google/common/io/Files.append:(Ljava/lang/CharSequence;Ljava/io/File;Ljava/nio/charset/Charset;)V
      68: goto          99
      71: aload_3
      72: invokevirtual #11                 // Method com/google/javascript/jscomp/NameAnalyzer.getHtmlReport:()Ljava/lang/String;
      75: new           #12                 // class java/io/File
      78: dup
      79: aload         4
      81: invokespecial #13                 // Method java/io/File."<init>":(Ljava/lang/String;)V
      84: getstatic     #14                 // Field java/nio/charset/StandardCharsets.UTF_8:Ljava/nio/charset/Charset;
      87: invokestatic  #16                 // Method com/google/common/io/Files.write:(Ljava/lang/CharSequence;Ljava/io/File;Ljava/nio/charset/Charset;)V
      90: aload_0
      91: getfield      #1                  // Field this$1:Lcom/google/javascript/jscomp/DefaultPassConfig$80;
      94: iconst_1
      95: invokestatic  #17                 // Method com/google/javascript/jscomp/DefaultPassConfig$80.access$1102:(Lcom/google/javascript/jscomp/DefaultPassConfig$80;Z)Z
      98: pop
      99: goto          126
     102: astore        5
     104: aload_0
     105: getfield      #2                  // Field val$compiler:Lcom/google/javascript/jscomp/AbstractCompiler;
     108: getstatic     #19                 // Field com/google/javascript/jscomp/DefaultPassConfig.REPORT_PATH_IO_ERROR:Lcom/google/javascript/jscomp/DiagnosticType;
     111: iconst_1
     112: anewarray     #20                 // class java/lang/String
     115: dup
     116: iconst_0
     117: aload         4
     119: aastore
     120: invokestatic  #21                 // Method com/google/javascript/jscomp/JSError.make:(Lcom/google/javascript/jscomp/DiagnosticType;[Ljava/lang/String;)Lcom/google/javascript/jscomp/JSError;
     123: invokevirtual #22                 // Method com/google/javascript/jscomp/AbstractCompiler.report:(Lcom/google/javascript/jscomp/JSError;)V
     126: aload_0
     127: getfield      #1                  // Field this$1:Lcom/google/javascript/jscomp/DefaultPassConfig$80;
     130: getfield      #7                  // Field com/google/javascript/jscomp/DefaultPassConfig$80.this$0:Lcom/google/javascript/jscomp/DefaultPassConfig;
     133: getfield      #8                  // Field com/google/javascript/jscomp/DefaultPassConfig.options:Lcom/google/javascript/jscomp/CompilerOptions;
     136: getfield      #23                 // Field com/google/javascript/jscomp/CompilerOptions.smartNameRemoval:Z
     139: ifeq          146
     142: aload_3
     143: invokevirtual #24                 // Method com/google/javascript/jscomp/NameAnalyzer.removeUnreferenced:()V
     146: return
    Exception table:
       from    to  target type
          39    99   102   Class java/io/IOException
}
