Compiled from "Es6RewriteGenerators.java"
public class com.google.javascript.jscomp.Es6RewriteGenerators extends com.google.javascript.jscomp.NodeTraversal$AbstractPostOrderCallback implements com.google.javascript.jscomp.HotSwapCompilerPass {
  private final com.google.javascript.jscomp.AbstractCompiler compiler;

  private com.google.javascript.rhino.Node enclosingBlock;

  private com.google.javascript.rhino.Node hoistRoot;

  private com.google.javascript.rhino.Node originalGeneratorBody;

  private com.google.javascript.rhino.Node currentStatement;

  private static final java.lang.String ITER_KEY;

  private static final java.lang.String GENERATOR_STATE;

  private static int generatorCaseCount;

  private static final java.lang.String GENERATOR_DO_WHILE_INITIAL;

  private static final java.lang.String GENERATOR_YIELD_ALL_NAME;

  private static final java.lang.String GENERATOR_YIELD_ALL_ENTRY;

  private static final java.lang.String GENERATOR_ARGUMENTS;

  private static final java.lang.String GENERATOR_THIS;

  private static final java.lang.String GENERATOR_NEXT_ARG;

  private static final java.lang.String GENERATOR_THROW_ARG;

  private com.google.common.base.Supplier<java.lang.String> generatorCounter;

  private static final java.lang.String GENERATOR_SWITCH_ENTERED;

  private static final java.lang.String GENERATOR_SWITCH_VAL;

  private static final java.lang.String GENERATOR_FINALLY_JUMP;

  private static final java.lang.String GENERATOR_ERROR;

  private static final java.lang.String GENERATOR_FOR_IN_ARRAY;

  private static final java.lang.String GENERATOR_FOR_IN_VAR;

  private static final java.lang.String GENERATOR_FOR_IN_ITER;

  private static final java.lang.String GENERATOR_LOOP_GUARD;

  private java.util.List<com.google.javascript.jscomp.Es6RewriteGenerators$LoopContext> currentLoopContext;

  private java.util.List<com.google.javascript.jscomp.Es6RewriteGenerators$ExceptionContext> currentExceptionContext;

  private boolean hasTranslatedTry;

  public com.google.javascript.jscomp.Es6RewriteGenerators(com.google.javascript.jscomp.AbstractCompiler);
    Code:
       0: aload_0
       1: invokespecial #5                  // Method com/google/javascript/jscomp/NodeTraversal$AbstractPostOrderCallback."<init>":()V
       4: aload_0
       5: aload_1
       6: putfield      #6                  // Field compiler:Lcom/google/javascript/jscomp/AbstractCompiler;
       9: aload_0
      10: new           #7                  // class java/util/ArrayList
      13: dup
      14: invokespecial #8                  // Method java/util/ArrayList."<init>":()V
      17: putfield      #9                  // Field currentLoopContext:Ljava/util/List;
      20: aload_0
      21: new           #7                  // class java/util/ArrayList
      24: dup
      25: invokespecial #8                  // Method java/util/ArrayList."<init>":()V
      28: putfield      #10                 // Field currentExceptionContext:Ljava/util/List;
      31: aload_0
      32: aload_1
      33: invokevirtual #11                 // Method com/google/javascript/jscomp/AbstractCompiler.getUniqueNameIdSupplier:()Lcom/google/common/base/Supplier;
      36: putfield      #2                  // Field generatorCounter:Lcom/google/common/base/Supplier;
      39: return

  public void process(com.google.javascript.rhino.Node, com.google.javascript.rhino.Node);
    Code:
       0: aload_0
       1: getfield      #6                  // Field compiler:Lcom/google/javascript/jscomp/AbstractCompiler;
       4: aload_2
       5: new           #12                 // class com/google/javascript/jscomp/Es6RewriteGenerators$DecomposeYields
       8: dup
       9: aload_0
      10: aload_0
      11: getfield      #6                  // Field compiler:Lcom/google/javascript/jscomp/AbstractCompiler;
      14: invokespecial #13                 // Method com/google/javascript/jscomp/Es6RewriteGenerators$DecomposeYields."<init>":(Lcom/google/javascript/jscomp/Es6RewriteGenerators;Lcom/google/javascript/jscomp/AbstractCompiler;)V
      17: invokestatic  #14                 // Method com/google/javascript/jscomp/NodeTraversal.traverse:(Lcom/google/javascript/jscomp/AbstractCompiler;Lcom/google/javascript/rhino/Node;Lcom/google/javascript/jscomp/NodeTraversal$Callback;)V
      20: aload_0
      21: getfield      #6                  // Field compiler:Lcom/google/javascript/jscomp/AbstractCompiler;
      24: aload_2
      25: aload_0
      26: invokestatic  #14                 // Method com/google/javascript/jscomp/NodeTraversal.traverse:(Lcom/google/javascript/jscomp/AbstractCompiler;Lcom/google/javascript/rhino/Node;Lcom/google/javascript/jscomp/NodeTraversal$Callback;)V
      29: return

  public void hotSwapScript(com.google.javascript.rhino.Node, com.google.javascript.rhino.Node);
    Code:
       0: aload_0
       1: getfield      #6                  // Field compiler:Lcom/google/javascript/jscomp/AbstractCompiler;
       4: aload_1
       5: new           #12                 // class com/google/javascript/jscomp/Es6RewriteGenerators$DecomposeYields
       8: dup
       9: aload_0
      10: aload_0
      11: getfield      #6                  // Field compiler:Lcom/google/javascript/jscomp/AbstractCompiler;
      14: invokespecial #13                 // Method com/google/javascript/jscomp/Es6RewriteGenerators$DecomposeYields."<init>":(Lcom/google/javascript/jscomp/Es6RewriteGenerators;Lcom/google/javascript/jscomp/AbstractCompiler;)V
      17: invokestatic  #14                 // Method com/google/javascript/jscomp/NodeTraversal.traverse:(Lcom/google/javascript/jscomp/AbstractCompiler;Lcom/google/javascript/rhino/Node;Lcom/google/javascript/jscomp/NodeTraversal$Callback;)V
      20: aload_0
      21: getfield      #6                  // Field compiler:Lcom/google/javascript/jscomp/AbstractCompiler;
      24: aload_1
      25: aload_0
      26: invokestatic  #14                 // Method com/google/javascript/jscomp/NodeTraversal.traverse:(Lcom/google/javascript/jscomp/AbstractCompiler;Lcom/google/javascript/rhino/Node;Lcom/google/javascript/jscomp/NodeTraversal$Callback;)V
      29: return

  public void visit(com.google.javascript.jscomp.NodeTraversal, com.google.javascript.rhino.Node, com.google.javascript.rhino.Node);
    Code:
       0: aload_2
       1: invokevirtual #15                 // Method com/google/javascript/rhino/Node.getType:()I
       4: lookupswitch  { // 4
                    38: 68
                    42: 105
                   105: 48
                   164: 140
               default: 181
          }
      48: aload_2
      49: invokevirtual #16                 // Method com/google/javascript/rhino/Node.isGeneratorFunction:()Z
      52: ifeq          181
      55: iconst_0
      56: putstatic     #17                 // Field generatorCaseCount:I
      59: aload_0
      60: aload_2
      61: aload_3
      62: invokespecial #18                 // Method visitGenerator:(Lcom/google/javascript/rhino/Node;Lcom/google/javascript/rhino/Node;)V
      65: goto          181
      68: aload_2
      69: invokestatic  #19                 // Method com/google/javascript/jscomp/NodeUtil.getEnclosingFunction:(Lcom/google/javascript/rhino/Node;)Lcom/google/javascript/rhino/Node;
      72: astore        4
      74: aload         4
      76: ifnull        181
      79: aload         4
      81: invokevirtual #16                 // Method com/google/javascript/rhino/Node.isGeneratorFunction:()Z
      84: ifeq          181
      87: aload_2
      88: ldc           #20                 // String arguments
      90: invokevirtual #21                 // Method com/google/javascript/rhino/Node.matchesQualifiedName:(Ljava/lang/String;)Z
      93: ifeq          181
      96: aload_2
      97: ldc           #23                 // String $jscomp$generator$arguments
      99: invokevirtual #24                 // Method com/google/javascript/rhino/Node.setString:(Ljava/lang/String;)V
     102: goto          181
     105: aload_2
     106: invokestatic  #19                 // Method com/google/javascript/jscomp/NodeUtil.getEnclosingFunction:(Lcom/google/javascript/rhino/Node;)Lcom/google/javascript/rhino/Node;
     109: astore        4
     111: aload         4
     113: ifnull        181
     116: aload         4
     118: invokevirtual #16                 // Method com/google/javascript/rhino/Node.isGeneratorFunction:()Z
     121: ifeq          181
     124: aload_2
     125: invokevirtual #25                 // Method com/google/javascript/rhino/Node.getParent:()Lcom/google/javascript/rhino/Node;
     128: aload_2
     129: ldc           #26                 // String $jscomp$generator$this
     131: invokestatic  #27                 // Method com/google/javascript/rhino/IR.name:(Ljava/lang/String;)Lcom/google/javascript/rhino/Node;
     134: invokevirtual #28                 // Method com/google/javascript/rhino/Node.replaceChild:(Lcom/google/javascript/rhino/Node;Lcom/google/javascript/rhino/Node;)V
     137: goto          181
     140: aload_2
     141: invokevirtual #29                 // Method com/google/javascript/rhino/Node.isYieldFor:()Z
     144: ifeq          156
     147: aload_0
     148: aload_2
     149: aload_3
     150: invokespecial #30                 // Method visitYieldFor:(Lcom/google/javascript/rhino/Node;Lcom/google/javascript/rhino/Node;)V
     153: goto          181
     156: aload_3
     157: invokevirtual #31                 // Method com/google/javascript/rhino/Node.isExprResult:()Z
     160: ifne          172
     163: aload_0
     164: aload_2
     165: aload_3
     166: invokespecial #32                 // Method visitYieldExpr:(Lcom/google/javascript/rhino/Node;Lcom/google/javascript/rhino/Node;)V
     169: goto          181
     172: aload_0
     173: aload_3
     174: aload_3
     175: invokevirtual #25                 // Method com/google/javascript/rhino/Node.getParent:()Lcom/google/javascript/rhino/Node;
     178: invokespecial #33                 // Method visitYieldThrows:(Lcom/google/javascript/rhino/Node;Lcom/google/javascript/rhino/Node;)V
     181: return

  private void visitYieldThrows(com.google.javascript.rhino.Node, com.google.javascript.rhino.Node);
    Code:
       0: ldc           #34                 // String $jscomp$generator$throw$arg
       2: invokestatic  #27                 // Method com/google/javascript/rhino/IR.name:(Ljava/lang/String;)Lcom/google/javascript/rhino/Node;
       5: ldc           #35                 // String undefined
       7: invokestatic  #27                 // Method com/google/javascript/rhino/IR.name:(Ljava/lang/String;)Lcom/google/javascript/rhino/Node;
      10: invokestatic  #36                 // Method com/google/javascript/rhino/IR.shne:(Lcom/google/javascript/rhino/Node;Lcom/google/javascript/rhino/Node;)Lcom/google/javascript/rhino/Node;
      13: ldc           #34                 // String $jscomp$generator$throw$arg
      15: invokestatic  #27                 // Method com/google/javascript/rhino/IR.name:(Ljava/lang/String;)Lcom/google/javascript/rhino/Node;
      18: invokestatic  #37                 // Method com/google/javascript/rhino/IR.throwNode:(Lcom/google/javascript/rhino/Node;)Lcom/google/javascript/rhino/Node;
      21: invokestatic  #38                 // Method com/google/javascript/rhino/IR.block:(Lcom/google/javascript/rhino/Node;)Lcom/google/javascript/rhino/Node;
      24: invokestatic  #39                 // Method com/google/javascript/rhino/IR.ifNode:(Lcom/google/javascript/rhino/Node;Lcom/google/javascript/rhino/Node;)Lcom/google/javascript/rhino/Node;
      27: astore_3
      28: aload_2
      29: aload_3
      30: aload_1
      31: invokevirtual #40                 // Method com/google/javascript/rhino/Node.addChildAfter:(Lcom/google/javascript/rhino/Node;Lcom/google/javascript/rhino/Node;)V
      34: aload_0
      35: getfield      #6                  // Field compiler:Lcom/google/javascript/jscomp/AbstractCompiler;
      38: invokevirtual #41                 // Method com/google/javascript/jscomp/AbstractCompiler.reportCodeChange:()V
      41: return

  private void visitYieldFor(com.google.javascript.rhino.Node, com.google.javascript.rhino.Node);
    Code:
       0: aload_1
       1: invokestatic  #42                 // Method com/google/javascript/jscomp/NodeUtil.getEnclosingStatement:(Lcom/google/javascript/rhino/Node;)Lcom/google/javascript/rhino/Node;
       4: astore_3
       5: ldc           #43                 // String $jscomp$generator$yield$all
       7: invokestatic  #27                 // Method com/google/javascript/rhino/IR.name:(Ljava/lang/String;)Lcom/google/javascript/rhino/Node;
      10: aload_0
      11: getfield      #6                  // Field compiler:Lcom/google/javascript/jscomp/AbstractCompiler;
      14: ldc           #45                 // String $jscomp.makeIterator
      16: invokestatic  #46                 // Method com/google/javascript/jscomp/NodeUtil.newQName:(Lcom/google/javascript/jscomp/AbstractCompiler;Ljava/lang/String;)Lcom/google/javascript/rhino/Node;
      19: iconst_1
      20: anewarray     #47                 // class com/google/javascript/rhino/Node
      23: dup
      24: iconst_0
      25: aload_1
      26: invokevirtual #48                 // Method com/google/javascript/rhino/Node.removeFirstChild:()Lcom/google/javascript/rhino/Node;
      29: aastore
      30: invokestatic  #49                 // Method com/google/javascript/rhino/IR.call:(Lcom/google/javascript/rhino/Node;[Lcom/google/javascript/rhino/Node;)Lcom/google/javascript/rhino/Node;
      33: invokestatic  #50                 // Method com/google/javascript/rhino/IR.var:(Lcom/google/javascript/rhino/Node;Lcom/google/javascript/rhino/Node;)Lcom/google/javascript/rhino/Node;
      36: astore        4
      38: ldc           #51                 // String $jscomp$generator$yield$entry
      40: invokestatic  #27                 // Method com/google/javascript/rhino/IR.name:(Ljava/lang/String;)Lcom/google/javascript/rhino/Node;
      43: invokestatic  #52                 // Method com/google/javascript/rhino/IR.var:(Lcom/google/javascript/rhino/Node;)Lcom/google/javascript/rhino/Node;
      46: astore        5
      48: aload_0
      49: getfield      #6                  // Field compiler:Lcom/google/javascript/jscomp/AbstractCompiler;
      52: iconst_1
      53: putfield      #53                 // Field com/google/javascript/jscomp/AbstractCompiler.needsEs6Runtime:Z
      56: ldc           #51                 // String $jscomp$generator$yield$entry
      58: invokestatic  #27                 // Method com/google/javascript/rhino/IR.name:(Ljava/lang/String;)Lcom/google/javascript/rhino/Node;
      61: ldc           #43                 // String $jscomp$generator$yield$all
      63: invokestatic  #27                 // Method com/google/javascript/rhino/IR.name:(Ljava/lang/String;)Lcom/google/javascript/rhino/Node;
      66: ldc           #54                 // String next
      68: invokestatic  #55                 // Method com/google/javascript/rhino/IR.string:(Ljava/lang/String;)Lcom/google/javascript/rhino/Node;
      71: invokestatic  #56                 // Method com/google/javascript/rhino/IR.getprop:(Lcom/google/javascript/rhino/Node;Lcom/google/javascript/rhino/Node;)Lcom/google/javascript/rhino/Node;
      74: iconst_1
      75: anewarray     #47                 // class com/google/javascript/rhino/Node
      78: dup
      79: iconst_0
      80: ldc           #57                 // String $jscomp$generator$next$arg
      82: invokestatic  #27                 // Method com/google/javascript/rhino/IR.name:(Ljava/lang/String;)Lcom/google/javascript/rhino/Node;
      85: aastore
      86: invokestatic  #49                 // Method com/google/javascript/rhino/IR.call:(Lcom/google/javascript/rhino/Node;[Lcom/google/javascript/rhino/Node;)Lcom/google/javascript/rhino/Node;
      89: invokestatic  #58                 // Method com/google/javascript/rhino/IR.assign:(Lcom/google/javascript/rhino/Node;Lcom/google/javascript/rhino/Node;)Lcom/google/javascript/rhino/Node;
      92: astore        6
      94: aload         6
      96: ldc           #59                 // String done
      98: invokestatic  #55                 // Method com/google/javascript/rhino/IR.string:(Ljava/lang/String;)Lcom/google/javascript/rhino/Node;
     101: invokestatic  #56                 // Method com/google/javascript/rhino/IR.getprop:(Lcom/google/javascript/rhino/Node;Lcom/google/javascript/rhino/Node;)Lcom/google/javascript/rhino/Node;
     104: invokestatic  #60                 // Method com/google/javascript/rhino/IR.not:(Lcom/google/javascript/rhino/Node;)Lcom/google/javascript/rhino/Node;
     107: astore        7
     109: ldc           #51                 // String $jscomp$generator$yield$entry
     111: invokestatic  #27                 // Method com/google/javascript/rhino/IR.name:(Ljava/lang/String;)Lcom/google/javascript/rhino/Node;
     114: ldc           #61                 // String value
     116: invokestatic  #55                 // Method com/google/javascript/rhino/IR.string:(Ljava/lang/String;)Lcom/google/javascript/rhino/Node;
     119: invokestatic  #56                 // Method com/google/javascript/rhino/IR.getprop:(Lcom/google/javascript/rhino/Node;Lcom/google/javascript/rhino/Node;)Lcom/google/javascript/rhino/Node;
     122: astore        8
     124: aload         8
     126: invokevirtual #62                 // Method com/google/javascript/rhino/Node.cloneTree:()Lcom/google/javascript/rhino/Node;
     129: invokestatic  #63                 // Method com/google/javascript/rhino/IR.yield:(Lcom/google/javascript/rhino/Node;)Lcom/google/javascript/rhino/Node;
     132: invokestatic  #64                 // Method com/google/javascript/rhino/IR.exprResult:(Lcom/google/javascript/rhino/Node;)Lcom/google/javascript/rhino/Node;
     135: astore        9
     137: aload         7
     139: aload         9
     141: invokestatic  #38                 // Method com/google/javascript/rhino/IR.block:(Lcom/google/javascript/rhino/Node;)Lcom/google/javascript/rhino/Node;
     144: invokestatic  #65                 // Method com/google/javascript/rhino/IR.whileNode:(Lcom/google/javascript/rhino/Node;Lcom/google/javascript/rhino/Node;)Lcom/google/javascript/rhino/Node;
     147: astore        10
     149: aload_3
     150: invokevirtual #25                 // Method com/google/javascript/rhino/Node.getParent:()Lcom/google/javascript/rhino/Node;
     153: aload         4
     155: aload_3
     156: invokevirtual #66                 // Method com/google/javascript/rhino/Node.addChildBefore:(Lcom/google/javascript/rhino/Node;Lcom/google/javascript/rhino/Node;)V
     159: aload_3
     160: invokevirtual #25                 // Method com/google/javascript/rhino/Node.getParent:()Lcom/google/javascript/rhino/Node;
     163: aload         5
     165: aload_3
     166: invokevirtual #66                 // Method com/google/javascript/rhino/Node.addChildBefore:(Lcom/google/javascript/rhino/Node;Lcom/google/javascript/rhino/Node;)V
     169: aload_3
     170: invokevirtual #25                 // Method com/google/javascript/rhino/Node.getParent:()Lcom/google/javascript/rhino/Node;
     173: aload         10
     175: aload_3
     176: invokevirtual #66                 // Method com/google/javascript/rhino/Node.addChildBefore:(Lcom/google/javascript/rhino/Node;Lcom/google/javascript/rhino/Node;)V
     179: aload_2
     180: invokevirtual #31                 // Method com/google/javascript/rhino/Node.isExprResult:()Z
     183: ifeq          194
     186: aload_2
     187: invokevirtual #67                 // Method com/google/javascript/rhino/Node.detachFromParent:()Lcom/google/javascript/rhino/Node;
     190: pop
     191: goto          201
     194: aload_2
     195: aload_1
     196: aload         8
     198: invokevirtual #28                 // Method com/google/javascript/rhino/Node.replaceChild:(Lcom/google/javascript/rhino/Node;Lcom/google/javascript/rhino/Node;)V
     201: aload_0
     202: aload         9
     204: aload         9
     206: invokevirtual #25                 // Method com/google/javascript/rhino/Node.getParent:()Lcom/google/javascript/rhino/Node;
     209: invokespecial #33                 // Method visitYieldThrows:(Lcom/google/javascript/rhino/Node;Lcom/google/javascript/rhino/Node;)V
     212: aload_0
     213: getfield      #6                  // Field compiler:Lcom/google/javascript/jscomp/AbstractCompiler;
     216: invokevirtual #41                 // Method com/google/javascript/jscomp/AbstractCompiler.reportCodeChange:()V
     219: return

  private void visitYieldExpr(com.google.javascript.rhino.Node, com.google.javascript.rhino.Node);
    Code:
       0: aload_1
       1: invokestatic  #42                 // Method com/google/javascript/jscomp/NodeUtil.getEnclosingStatement:(Lcom/google/javascript/rhino/Node;)Lcom/google/javascript/rhino/Node;
       4: astore_3
       5: aload_1
       6: invokevirtual #68                 // Method com/google/javascript/rhino/Node.hasChildren:()Z
       9: ifeq          22
      12: aload_1
      13: invokevirtual #48                 // Method com/google/javascript/rhino/Node.removeFirstChild:()Lcom/google/javascript/rhino/Node;
      16: invokestatic  #63                 // Method com/google/javascript/rhino/IR.yield:(Lcom/google/javascript/rhino/Node;)Lcom/google/javascript/rhino/Node;
      19: goto          25
      22: invokestatic  #69                 // Method com/google/javascript/rhino/IR.yield:()Lcom/google/javascript/rhino/Node;
      25: invokestatic  #64                 // Method com/google/javascript/rhino/IR.exprResult:(Lcom/google/javascript/rhino/Node;)Lcom/google/javascript/rhino/Node;
      28: astore        4
      30: new           #70                 // class java/lang/StringBuilder
      33: dup
      34: invokespecial #71                 // Method java/lang/StringBuilder."<init>":()V
      37: ldc           #57                 // String $jscomp$generator$next$arg
      39: invokevirtual #72                 // Method java/lang/StringBuilder.append:(Ljava/lang/String;)Ljava/lang/StringBuilder;
      42: aload_0
      43: getfield      #2                  // Field generatorCounter:Lcom/google/common/base/Supplier;
      46: invokeinterface #73,  1           // InterfaceMethod com/google/common/base/Supplier.get:()Ljava/lang/Object;
      51: checkcast     #74                 // class java/lang/String
      54: invokevirtual #72                 // Method java/lang/StringBuilder.append:(Ljava/lang/String;)Ljava/lang/StringBuilder;
      57: invokevirtual #75                 // Method java/lang/StringBuilder.toString:()Ljava/lang/String;
      60: invokestatic  #27                 // Method com/google/javascript/rhino/IR.name:(Ljava/lang/String;)Lcom/google/javascript/rhino/Node;
      63: astore        5
      65: aload         5
      67: invokevirtual #62                 // Method com/google/javascript/rhino/Node.cloneTree:()Lcom/google/javascript/rhino/Node;
      70: ldc           #57                 // String $jscomp$generator$next$arg
      72: invokestatic  #27                 // Method com/google/javascript/rhino/IR.name:(Ljava/lang/String;)Lcom/google/javascript/rhino/Node;
      75: invokestatic  #50                 // Method com/google/javascript/rhino/IR.var:(Lcom/google/javascript/rhino/Node;Lcom/google/javascript/rhino/Node;)Lcom/google/javascript/rhino/Node;
      78: astore        6
      80: aload_2
      81: aload_1
      82: aload         5
      84: invokevirtual #28                 // Method com/google/javascript/rhino/Node.replaceChild:(Lcom/google/javascript/rhino/Node;Lcom/google/javascript/rhino/Node;)V
      87: aload_3
      88: invokevirtual #25                 // Method com/google/javascript/rhino/Node.getParent:()Lcom/google/javascript/rhino/Node;
      91: aload         4
      93: aload_3
      94: invokevirtual #66                 // Method com/google/javascript/rhino/Node.addChildBefore:(Lcom/google/javascript/rhino/Node;Lcom/google/javascript/rhino/Node;)V
      97: aload_3
      98: invokevirtual #25                 // Method com/google/javascript/rhino/Node.getParent:()Lcom/google/javascript/rhino/Node;
     101: aload         6
     103: aload_3
     104: invokevirtual #66                 // Method com/google/javascript/rhino/Node.addChildBefore:(Lcom/google/javascript/rhino/Node;Lcom/google/javascript/rhino/Node;)V
     107: aload_0
     108: aload         4
     110: aload         4
     112: invokevirtual #25                 // Method com/google/javascript/rhino/Node.getParent:()Lcom/google/javascript/rhino/Node;
     115: invokespecial #33                 // Method visitYieldThrows:(Lcom/google/javascript/rhino/Node;Lcom/google/javascript/rhino/Node;)V
     118: aload_0
     119: getfield      #6                  // Field compiler:Lcom/google/javascript/jscomp/AbstractCompiler;
     122: invokevirtual #41                 // Method com/google/javascript/jscomp/AbstractCompiler.reportCodeChange:()V
     125: return

  private void visitGenerator(com.google.javascript.rhino.Node, com.google.javascript.rhino.Node);
    Code:
       0: aload_0
       1: iconst_0
       2: putfield      #76                 // Field hasTranslatedTry:Z
       5: aload_0
       6: getfield      #6                  // Field compiler:Lcom/google/javascript/jscomp/AbstractCompiler;
       9: bipush        10
      11: invokestatic  #77                 // Method com/google/common/base/Joiner.on:(C)Lcom/google/common/base/Joiner;
      14: ldc           #78                 // String function generatorBody() {
      16: new           #70                 // class java/lang/StringBuilder
      19: dup
      20: invokespecial #71                 // Method java/lang/StringBuilder."<init>":()V
      23: ldc           #79                 // String   var $jscomp$generator$state =
      25: invokevirtual #72                 // Method java/lang/StringBuilder.append:(Ljava/lang/String;)Ljava/lang/StringBuilder;
      28: getstatic     #17                 // Field generatorCaseCount:I
      31: invokevirtual #80                 // Method java/lang/StringBuilder.append:(I)Ljava/lang/StringBuilder;
      34: ldc           #81                 // String ;
      36: invokevirtual #72                 // Method java/lang/StringBuilder.append:(Ljava/lang/String;)Ljava/lang/StringBuilder;
      39: invokevirtual #75                 // Method java/lang/StringBuilder.toString:()Ljava/lang/String;
      42: bipush        14
      44: anewarray     #82                 // class java/lang/Object
      47: dup
      48: iconst_0
      49: ldc           #83                 // String   function $jscomp$generator$impl($jscomp$generator$next$arg,
      51: aastore
      52: dup
      53: iconst_1
      54: ldc           #84                 // String       $jscomp$generator$throw$arg) {
      56: aastore
      57: dup
      58: iconst_2
      59: ldc           #85                 // String     while (1) switch ($jscomp$generator$state) {
      61: aastore
      62: dup
      63: iconst_3
      64: new           #70                 // class java/lang/StringBuilder
      67: dup
      68: invokespecial #71                 // Method java/lang/StringBuilder."<init>":()V
      71: ldc           #86                 // String       case
      73: invokevirtual #72                 // Method java/lang/StringBuilder.append:(Ljava/lang/String;)Ljava/lang/StringBuilder;
      76: getstatic     #17                 // Field generatorCaseCount:I
      79: invokevirtual #80                 // Method java/lang/StringBuilder.append:(I)Ljava/lang/StringBuilder;
      82: ldc           #87                 // String :
      84: invokevirtual #72                 // Method java/lang/StringBuilder.append:(Ljava/lang/String;)Ljava/lang/StringBuilder;
      87: invokevirtual #75                 // Method java/lang/StringBuilder.toString:()Ljava/lang/String;
      90: aastore
      91: dup
      92: iconst_4
      93: ldc           #88                 // String       default:
      95: aastore
      96: dup
      97: iconst_5
      98: ldc           #89                 // String         return {value: undefined, done: true};
     100: aastore
     101: dup
     102: bipush        6
     104: ldc           #90                 // String     }
     106: aastore
     107: dup
     108: bipush        7
     110: ldc           #91                 // String   }
     112: aastore
     113: dup
     114: bipush        8
     116: ldc           #92                 // String   return {
     118: aastore
     119: dup
     120: bipush        9
     122: ldc           #93                 // String     $$iterator: function() { return this; },
     124: aastore
     125: dup
     126: bipush        10
     128: ldc           #94                 // String     next: function(arg){ return $jscomp$generator$impl(arg, undefined); },
     130: aastore
     131: dup
     132: bipush        11
     134: ldc           #95                 // String     throw: function(arg){ return $jscomp$generator$impl(undefined, arg); },
     136: aastore
     137: dup
     138: bipush        12
     140: ldc           #91                 // String   }
     142: aastore
     143: dup
     144: bipush        13
     146: ldc           #96                 // String }
     148: aastore
     149: invokevirtual #97                 // Method com/google/common/base/Joiner.join:(Ljava/lang/Object;Ljava/lang/Object;[Ljava/lang/Object;)Ljava/lang/String;
     152: invokevirtual #98                 // Method com/google/javascript/jscomp/AbstractCompiler.parseSyntheticCode:(Ljava/lang/String;)Lcom/google/javascript/rhino/Node;
     155: invokevirtual #99                 // Method com/google/javascript/rhino/Node.getFirstChild:()Lcom/google/javascript/rhino/Node;
     158: invokevirtual #100                // Method com/google/javascript/rhino/Node.getLastChild:()Lcom/google/javascript/rhino/Node;
     161: invokevirtual #67                 // Method com/google/javascript/rhino/Node.detachFromParent:()Lcom/google/javascript/rhino/Node;
     164: astore_3
     165: getstatic     #17                 // Field generatorCaseCount:I
     168: iconst_1
     169: iadd
     170: putstatic     #17                 // Field generatorCaseCount:I
     173: aload_0
     174: aload_1
     175: invokevirtual #100                // Method com/google/javascript/rhino/Node.getLastChild:()Lcom/google/javascript/rhino/Node;
     178: putfield      #101                // Field originalGeneratorBody:Lcom/google/javascript/rhino/Node;
     181: aload_1
     182: aload_0
     183: getfield      #101                // Field originalGeneratorBody:Lcom/google/javascript/rhino/Node;
     186: aload_3
     187: invokevirtual #28                 // Method com/google/javascript/rhino/Node.replaceChild:(Lcom/google/javascript/rhino/Node;Lcom/google/javascript/rhino/Node;)V
     190: aload_1
     191: iconst_0
     192: invokevirtual #102                // Method com/google/javascript/rhino/Node.setIsGeneratorFunction:(Z)V
     195: aload_1
     196: invokevirtual #103                // Method com/google/javascript/rhino/Node.getJSDocInfo:()Lcom/google/javascript/rhino/JSDocInfo;
     199: ifnonnull     215
     202: new           #104                // class com/google/javascript/rhino/JSDocInfoBuilder
     205: dup
     206: iconst_1
     207: invokespecial #105                // Method com/google/javascript/rhino/JSDocInfoBuilder."<init>":(Z)V
     210: astore        4
     212: goto          224
     215: aload_1
     216: invokevirtual #103                // Method com/google/javascript/rhino/Node.getJSDocInfo:()Lcom/google/javascript/rhino/JSDocInfo;
     219: invokestatic  #106                // Method com/google/javascript/rhino/JSDocInfoBuilder.copyFrom:(Lcom/google/javascript/rhino/JSDocInfo;)Lcom/google/javascript/rhino/JSDocInfoBuilder;
     222: astore        4
     224: aload         4
     226: ldc           #107                // String uselessCode
     228: invokestatic  #108                // Method com/google/common/collect/ImmutableSet.of:(Ljava/lang/Object;)Lcom/google/common/collect/ImmutableSet;
     231: invokevirtual #109                // Method com/google/javascript/rhino/JSDocInfoBuilder.recordSuppressions:(Ljava/util/Set;)Z
     234: pop
     235: aload         4
     237: aload_1
     238: invokevirtual #110                // Method com/google/javascript/rhino/JSDocInfoBuilder.build:(Lcom/google/javascript/rhino/Node;)Lcom/google/javascript/rhino/JSDocInfo;
     241: astore        5
     243: aload_1
     244: aload         5
     246: invokevirtual #111                // Method com/google/javascript/rhino/Node.setJSDocInfo:(Lcom/google/javascript/rhino/JSDocInfo;)Lcom/google/javascript/rhino/Node;
     249: pop
     250: aload_0
     251: getfield      #101                // Field originalGeneratorBody:Lcom/google/javascript/rhino/Node;
     254: ldc           #112                // String $jscomp$generator$state
     256: invokestatic  #27                 // Method com/google/javascript/rhino/IR.name:(Ljava/lang/String;)Lcom/google/javascript/rhino/Node;
     259: ldc2_w        #113                // double -1.0d
     262: invokestatic  #115                // Method com/google/javascript/rhino/IR.number:(D)Lcom/google/javascript/rhino/Node;
     265: invokestatic  #58                 // Method com/google/javascript/rhino/IR.assign:(Lcom/google/javascript/rhino/Node;Lcom/google/javascript/rhino/Node;)Lcom/google/javascript/rhino/Node;
     268: invokestatic  #64                 // Method com/google/javascript/rhino/IR.exprResult:(Lcom/google/javascript/rhino/Node;)Lcom/google/javascript/rhino/Node;
     271: invokevirtual #116                // Method com/google/javascript/rhino/Node.addChildToBack:(Lcom/google/javascript/rhino/Node;)V
     274: aload_0
     275: aload_0
     276: aload_3
     277: bipush        111
     279: invokespecial #118                // Method getUnique:(Lcom/google/javascript/rhino/Node;I)Lcom/google/javascript/rhino/Node;
     282: invokevirtual #100                // Method com/google/javascript/rhino/Node.getLastChild:()Lcom/google/javascript/rhino/Node;
     285: putfield      #119                // Field enclosingBlock:Lcom/google/javascript/rhino/Node;
     288: aload_0
     289: aload_0
     290: aload_3
     291: bipush        118
     293: invokespecial #118                // Method getUnique:(Lcom/google/javascript/rhino/Node;I)Lcom/google/javascript/rhino/Node;
     296: putfield      #120                // Field hoistRoot:Lcom/google/javascript/rhino/Node;
     299: aload_0
     300: getfield      #101                // Field originalGeneratorBody:Lcom/google/javascript/rhino/Node;
     303: ldc           #23                 // String $jscomp$generator$arguments
     305: invokestatic  #121                // Method com/google/javascript/jscomp/NodeUtil.isNameReferenced:(Lcom/google/javascript/rhino/Node;Ljava/lang/String;)Z
     308: ifeq          338
     311: aload_0
     312: getfield      #120                // Field hoistRoot:Lcom/google/javascript/rhino/Node;
     315: invokevirtual #25                 // Method com/google/javascript/rhino/Node.getParent:()Lcom/google/javascript/rhino/Node;
     318: ldc           #23                 // String $jscomp$generator$arguments
     320: invokestatic  #27                 // Method com/google/javascript/rhino/IR.name:(Ljava/lang/String;)Lcom/google/javascript/rhino/Node;
     323: ldc           #20                 // String arguments
     325: invokestatic  #27                 // Method com/google/javascript/rhino/IR.name:(Ljava/lang/String;)Lcom/google/javascript/rhino/Node;
     328: invokestatic  #50                 // Method com/google/javascript/rhino/IR.var:(Lcom/google/javascript/rhino/Node;Lcom/google/javascript/rhino/Node;)Lcom/google/javascript/rhino/Node;
     331: aload_0
     332: getfield      #120                // Field hoistRoot:Lcom/google/javascript/rhino/Node;
     335: invokevirtual #40                 // Method com/google/javascript/rhino/Node.addChildAfter:(Lcom/google/javascript/rhino/Node;Lcom/google/javascript/rhino/Node;)V
     338: aload_0
     339: getfield      #101                // Field originalGeneratorBody:Lcom/google/javascript/rhino/Node;
     342: ldc           #26                 // String $jscomp$generator$this
     344: invokestatic  #121                // Method com/google/javascript/jscomp/NodeUtil.isNameReferenced:(Lcom/google/javascript/rhino/Node;Ljava/lang/String;)Z
     347: ifeq          375
     350: aload_0
     351: getfield      #120                // Field hoistRoot:Lcom/google/javascript/rhino/Node;
     354: invokevirtual #25                 // Method com/google/javascript/rhino/Node.getParent:()Lcom/google/javascript/rhino/Node;
     357: ldc           #26                 // String $jscomp$generator$this
     359: invokestatic  #27                 // Method com/google/javascript/rhino/IR.name:(Ljava/lang/String;)Lcom/google/javascript/rhino/Node;
     362: invokestatic  #122                // Method com/google/javascript/rhino/IR.thisNode:()Lcom/google/javascript/rhino/Node;
     365: invokestatic  #50                 // Method com/google/javascript/rhino/IR.var:(Lcom/google/javascript/rhino/Node;Lcom/google/javascript/rhino/Node;)Lcom/google/javascript/rhino/Node;
     368: aload_0
     369: getfield      #120                // Field hoistRoot:Lcom/google/javascript/rhino/Node;
     372: invokevirtual #40                 // Method com/google/javascript/rhino/Node.addChildAfter:(Lcom/google/javascript/rhino/Node;Lcom/google/javascript/rhino/Node;)V
     375: aload_0
     376: getfield      #101                // Field originalGeneratorBody:Lcom/google/javascript/rhino/Node;
     379: invokevirtual #68                 // Method com/google/javascript/rhino/Node.hasChildren:()Z
     382: ifeq          572
     385: aload_0
     386: aload_0
     387: getfield      #101                // Field originalGeneratorBody:Lcom/google/javascript/rhino/Node;
     390: invokevirtual #48                 // Method com/google/javascript/rhino/Node.removeFirstChild:()Lcom/google/javascript/rhino/Node;
     393: putfield      #3                  // Field currentStatement:Lcom/google/javascript/rhino/Node;
     396: aload_0
     397: invokespecial #123                // Method translateStatementInOriginalBody:()Z
     400: istore        6
     402: iload         6
     404: ifeq          569
     407: aload_0
     408: getfield      #3                  // Field currentStatement:Lcom/google/javascript/rhino/Node;
     411: invokevirtual #124                // Method com/google/javascript/rhino/Node.isGeneratorMarker:()Z
     414: ifeq          430
     417: aload_0
     418: getfield      #3                  // Field currentStatement:Lcom/google/javascript/rhino/Node;
     421: invokevirtual #125                // Method com/google/javascript/rhino/Node.getDouble:()D
     424: d2i
     425: istore        7
     427: goto          443
     430: getstatic     #17                 // Field generatorCaseCount:I
     433: istore        7
     435: getstatic     #17                 // Field generatorCaseCount:I
     438: iconst_1
     439: iadd
     440: putstatic     #17                 // Field generatorCaseCount:I
     443: aload_0
     444: getfield      #119                // Field enclosingBlock:Lcom/google/javascript/rhino/Node;
     447: invokevirtual #25                 // Method com/google/javascript/rhino/Node.getParent:()Lcom/google/javascript/rhino/Node;
     450: astore        8
     452: iload         7
     454: i2d
     455: invokestatic  #115                // Method com/google/javascript/rhino/IR.number:(D)Lcom/google/javascript/rhino/Node;
     458: invokestatic  #126                // Method com/google/javascript/rhino/IR.block:()Lcom/google/javascript/rhino/Node;
     461: invokestatic  #127                // Method com/google/javascript/rhino/IR.caseNode:(Lcom/google/javascript/rhino/Node;Lcom/google/javascript/rhino/Node;)Lcom/google/javascript/rhino/Node;
     464: astore        9
     466: aload_0
     467: aload         9
     469: invokevirtual #100                // Method com/google/javascript/rhino/Node.getLastChild:()Lcom/google/javascript/rhino/Node;
     472: putfield      #119                // Field enclosingBlock:Lcom/google/javascript/rhino/Node;
     475: aload         8
     477: invokevirtual #128                // Method com/google/javascript/rhino/Node.isTry:()Z
     480: ifeq          557
     483: aload         8
     485: invokevirtual #25                 // Method com/google/javascript/rhino/Node.getParent:()Lcom/google/javascript/rhino/Node;
     488: invokevirtual #25                 // Method com/google/javascript/rhino/Node.getParent:()Lcom/google/javascript/rhino/Node;
     491: astore        8
     493: aload_0
     494: getfield      #10                 // Field currentExceptionContext:Ljava/util/List;
     497: invokeinterface #129,  1          // InterfaceMethod java/util/List.isEmpty:()Z
     502: ifne          557
     505: invokestatic  #126                // Method com/google/javascript/rhino/IR.block:()Lcom/google/javascript/rhino/Node;
     508: aload_0
     509: getfield      #10                 // Field currentExceptionContext:Ljava/util/List;
     512: iconst_0
     513: invokeinterface #130,  2          // InterfaceMethod java/util/List.get:(I)Ljava/lang/Object;
     518: checkcast     #131                // class com/google/javascript/jscomp/Es6RewriteGenerators$ExceptionContext
     521: getfield      #132                // Field com/google/javascript/jscomp/Es6RewriteGenerators$ExceptionContext.catchBlock:Lcom/google/javascript/rhino/Node;
     524: invokevirtual #62                 // Method com/google/javascript/rhino/Node.cloneTree:()Lcom/google/javascript/rhino/Node;
     527: invokestatic  #133                // Method com/google/javascript/rhino/IR.tryCatch:(Lcom/google/javascript/rhino/Node;Lcom/google/javascript/rhino/Node;)Lcom/google/javascript/rhino/Node;
     530: astore        10
     532: aload         9
     534: invokevirtual #100                // Method com/google/javascript/rhino/Node.getLastChild:()Lcom/google/javascript/rhino/Node;
     537: aload         10
     539: invokevirtual #116                // Method com/google/javascript/rhino/Node.addChildToBack:(Lcom/google/javascript/rhino/Node;)V
     542: aload_0
     543: aload         9
     545: invokevirtual #100                // Method com/google/javascript/rhino/Node.getLastChild:()Lcom/google/javascript/rhino/Node;
     548: invokevirtual #100                // Method com/google/javascript/rhino/Node.getLastChild:()Lcom/google/javascript/rhino/Node;
     551: invokevirtual #99                 // Method com/google/javascript/rhino/Node.getFirstChild:()Lcom/google/javascript/rhino/Node;
     554: putfield      #119                // Field enclosingBlock:Lcom/google/javascript/rhino/Node;
     557: aload         8
     559: invokevirtual #25                 // Method com/google/javascript/rhino/Node.getParent:()Lcom/google/javascript/rhino/Node;
     562: aload         9
     564: aload         8
     566: invokevirtual #40                 // Method com/google/javascript/rhino/Node.addChildAfter:(Lcom/google/javascript/rhino/Node;Lcom/google/javascript/rhino/Node;)V
     569: goto          375
     572: aload_2
     573: aload_2
     574: invokevirtual #134                // Method com/google/javascript/rhino/Node.useSourceInfoIfMissingFromForTree:(Lcom/google/javascript/rhino/Node;)Lcom/google/javascript/rhino/Node;
     577: pop
     578: aload_0
     579: getfield      #6                  // Field compiler:Lcom/google/javascript/jscomp/AbstractCompiler;
     582: invokevirtual #41                 // Method com/google/javascript/jscomp/AbstractCompiler.reportCodeChange:()V
     585: return

  private boolean translateStatementInOriginalBody();
    Code:
       0: aload_0
       1: getfield      #3                  // Field currentStatement:Lcom/google/javascript/rhino/Node;
       4: invokevirtual #135                // Method com/google/javascript/rhino/Node.isVar:()Z
       7: ifeq          16
      10: aload_0
      11: invokespecial #136                // Method visitVar:()V
      14: iconst_0
      15: ireturn
      16: aload_0
      17: getfield      #3                  // Field currentStatement:Lcom/google/javascript/rhino/Node;
      20: invokevirtual #124                // Method com/google/javascript/rhino/Node.isGeneratorMarker:()Z
      23: ifeq          32
      26: aload_0
      27: invokespecial #137                // Method visitGeneratorMarker:()V
      30: iconst_1
      31: ireturn
      32: aload_0
      33: getfield      #3                  // Field currentStatement:Lcom/google/javascript/rhino/Node;
      36: invokevirtual #138                // Method com/google/javascript/rhino/Node.isFunction:()Z
      39: ifeq          48
      42: aload_0
      43: invokespecial #139                // Method visitFunctionStatement:()V
      46: iconst_0
      47: ireturn
      48: aload_0
      49: getfield      #3                  // Field currentStatement:Lcom/google/javascript/rhino/Node;
      52: invokevirtual #140                // Method com/google/javascript/rhino/Node.isBlock:()Z
      55: ifeq          64
      58: aload_0
      59: invokespecial #141                // Method visitBlock:()V
      62: iconst_0
      63: ireturn
      64: aload_0
      65: aload_0
      66: getfield      #3                  // Field currentStatement:Lcom/google/javascript/rhino/Node;
      69: invokespecial #4                  // Method controlCanExit:(Lcom/google/javascript/rhino/Node;)Z
      72: ifeq          334
      75: aload_0
      76: getfield      #3                  // Field currentStatement:Lcom/google/javascript/rhino/Node;
      79: invokevirtual #15                 // Method com/google/javascript/rhino/Node.getType:()I
      82: lookupswitch  { // 12
                     4: 264
                    49: 292
                    77: 239
                   108: 223
                   110: 217
                   113: 188
                   114: 188
                   115: 188
                   116: 276
                   117: 270
                   126: 211
                   130: 245
               default: 298
          }
     188: aload_0
     189: getfield      #3                  // Field currentStatement:Lcom/google/javascript/rhino/Node;
     192: invokestatic  #142                // Method com/google/javascript/jscomp/NodeUtil.isForIn:(Lcom/google/javascript/rhino/Node;)Z
     195: ifeq          204
     198: aload_0
     199: invokespecial #143                // Method visitForIn:()V
     202: iconst_0
     203: ireturn
     204: aload_0
     205: aconst_null
     206: invokespecial #144                // Method visitLoop:(Ljava/lang/String;)V
     209: iconst_0
     210: ireturn
     211: aload_0
     212: invokespecial #145                // Method visitLabel:()V
     215: iconst_0
     216: ireturn
     217: aload_0
     218: invokespecial #146                // Method visitSwitch:()V
     221: iconst_0
     222: ireturn
     223: aload_0
     224: getfield      #3                  // Field currentStatement:Lcom/google/javascript/rhino/Node;
     227: invokevirtual #147                // Method com/google/javascript/rhino/Node.isGeneratorSafe:()Z
     230: ifne          334
     233: aload_0
     234: invokespecial #148                // Method visitIf:()V
     237: iconst_0
     238: ireturn
     239: aload_0
     240: invokespecial #149                // Method visitTry:()V
     243: iconst_0
     244: ireturn
     245: aload_0
     246: getfield      #3                  // Field currentStatement:Lcom/google/javascript/rhino/Node;
     249: invokevirtual #99                 // Method com/google/javascript/rhino/Node.getFirstChild:()Lcom/google/javascript/rhino/Node;
     252: invokevirtual #150                // Method com/google/javascript/rhino/Node.isYield:()Z
     255: ifeq          334
     258: aload_0
     259: invokespecial #151                // Method visitYieldExprResult:()V
     262: iconst_1
     263: ireturn
     264: aload_0
     265: invokespecial #152                // Method visitReturn:()V
     268: iconst_0
     269: ireturn
     270: aload_0
     271: invokespecial #153                // Method visitContinue:()V
     274: iconst_0
     275: ireturn
     276: aload_0
     277: getfield      #3                  // Field currentStatement:Lcom/google/javascript/rhino/Node;
     280: invokevirtual #147                // Method com/google/javascript/rhino/Node.isGeneratorSafe:()Z
     283: ifne          334
     286: aload_0
     287: invokespecial #154                // Method visitBreak:()V
     290: iconst_0
     291: ireturn
     292: aload_0
     293: invokespecial #155                // Method visitThrow:()V
     296: iconst_0
     297: ireturn
     298: new           #156                // class java/lang/RuntimeException
     301: dup
     302: new           #70                 // class java/lang/StringBuilder
     305: dup
     306: invokespecial #71                 // Method java/lang/StringBuilder."<init>":()V
     309: ldc           #157                // String Untranslatable control-exiting statement in generator function:
     311: invokevirtual #72                 // Method java/lang/StringBuilder.append:(Ljava/lang/String;)Ljava/lang/StringBuilder;
     314: aload_0
     315: getfield      #3                  // Field currentStatement:Lcom/google/javascript/rhino/Node;
     318: invokevirtual #15                 // Method com/google/javascript/rhino/Node.getType:()I
     321: invokestatic  #158                // Method com/google/javascript/rhino/Token.name:(I)Ljava/lang/String;
     324: invokevirtual #72                 // Method java/lang/StringBuilder.append:(Ljava/lang/String;)Ljava/lang/StringBuilder;
     327: invokevirtual #75                 // Method java/lang/StringBuilder.toString:()Ljava/lang/String;
     330: invokespecial #159                // Method java/lang/RuntimeException."<init>":(Ljava/lang/String;)V
     333: athrow
     334: aload_0
     335: getfield      #119                // Field enclosingBlock:Lcom/google/javascript/rhino/Node;
     338: aload_0
     339: getfield      #3                  // Field currentStatement:Lcom/google/javascript/rhino/Node;
     342: invokevirtual #116                // Method com/google/javascript/rhino/Node.addChildToBack:(Lcom/google/javascript/rhino/Node;)V
     345: iconst_0
     346: ireturn

  private void visitFunctionStatement();
    Code:
       0: aload_0
       1: getfield      #120                // Field hoistRoot:Lcom/google/javascript/rhino/Node;
       4: invokevirtual #25                 // Method com/google/javascript/rhino/Node.getParent:()Lcom/google/javascript/rhino/Node;
       7: aload_0
       8: getfield      #3                  // Field currentStatement:Lcom/google/javascript/rhino/Node;
      11: aload_0
      12: getfield      #120                // Field hoistRoot:Lcom/google/javascript/rhino/Node;
      15: invokevirtual #40                 // Method com/google/javascript/rhino/Node.addChildAfter:(Lcom/google/javascript/rhino/Node;Lcom/google/javascript/rhino/Node;)V
      18: return

  private void visitTry();
    Code:
       0: aload_0
       1: getfield      #3                  // Field currentStatement:Lcom/google/javascript/rhino/Node;
       4: invokevirtual #99                 // Method com/google/javascript/rhino/Node.getFirstChild:()Lcom/google/javascript/rhino/Node;
       7: astore_1
       8: aload_1
       9: invokevirtual #160                // Method com/google/javascript/rhino/Node.getNext:()Lcom/google/javascript/rhino/Node;
      12: astore        4
      14: aload         4
      16: invokevirtual #68                 // Method com/google/javascript/rhino/Node.hasChildren:()Z
      19: ifeq          43
      22: aload         4
      24: invokevirtual #99                 // Method com/google/javascript/rhino/Node.getFirstChild:()Lcom/google/javascript/rhino/Node;
      27: invokevirtual #48                 // Method com/google/javascript/rhino/Node.removeFirstChild:()Lcom/google/javascript/rhino/Node;
      30: astore_2
      31: aload         4
      33: invokevirtual #99                 // Method com/google/javascript/rhino/Node.getFirstChild:()Lcom/google/javascript/rhino/Node;
      36: invokevirtual #48                 // Method com/google/javascript/rhino/Node.removeFirstChild:()Lcom/google/javascript/rhino/Node;
      39: astore_3
      40: goto          68
      43: ldc           #161                // String $jscomp$generator$global$errortemp
      45: invokestatic  #27                 // Method com/google/javascript/rhino/IR.name:(Ljava/lang/String;)Lcom/google/javascript/rhino/Node;
      48: astore_2
      49: aload_2
      50: invokevirtual #62                 // Method com/google/javascript/rhino/Node.cloneTree:()Lcom/google/javascript/rhino/Node;
      53: invokestatic  #37                 // Method com/google/javascript/rhino/IR.throwNode:(Lcom/google/javascript/rhino/Node;)Lcom/google/javascript/rhino/Node;
      56: invokestatic  #38                 // Method com/google/javascript/rhino/IR.block:(Lcom/google/javascript/rhino/Node;)Lcom/google/javascript/rhino/Node;
      59: astore_3
      60: aload_3
      61: invokevirtual #99                 // Method com/google/javascript/rhino/Node.getFirstChild:()Lcom/google/javascript/rhino/Node;
      64: iconst_1
      65: invokevirtual #162                // Method com/google/javascript/rhino/Node.setGeneratorSafe:(Z)V
      68: aload         4
      70: invokevirtual #160                // Method com/google/javascript/rhino/Node.getNext:()Lcom/google/javascript/rhino/Node;
      73: astore        5
      75: getstatic     #17                 // Field generatorCaseCount:I
      78: dup
      79: iconst_1
      80: iadd
      81: putstatic     #17                 // Field generatorCaseCount:I
      84: istore        6
      86: iload         6
      88: i2d
      89: invokestatic  #115                // Method com/google/javascript/rhino/IR.number:(D)Lcom/google/javascript/rhino/Node;
      92: astore        7
      94: aload         7
      96: iconst_1
      97: invokevirtual #163                // Method com/google/javascript/rhino/Node.setGeneratorMarker:(Z)V
     100: new           #70                 // class java/lang/StringBuilder
     103: dup
     104: invokespecial #71                 // Method java/lang/StringBuilder."<init>":()V
     107: ldc           #164                // String $jscomp$generator$
     109: invokevirtual #72                 // Method java/lang/StringBuilder.append:(Ljava/lang/String;)Ljava/lang/StringBuilder;
     112: aload_2
     113: invokevirtual #165                // Method com/google/javascript/rhino/Node.getString:()Ljava/lang/String;
     116: invokevirtual #72                 // Method java/lang/StringBuilder.append:(Ljava/lang/String;)Ljava/lang/StringBuilder;
     119: invokevirtual #75                 // Method java/lang/StringBuilder.toString:()Ljava/lang/String;
     122: invokestatic  #27                 // Method com/google/javascript/rhino/IR.name:(Ljava/lang/String;)Lcom/google/javascript/rhino/Node;
     125: astore        8
     127: aload_0
     128: getfield      #101                // Field originalGeneratorBody:Lcom/google/javascript/rhino/Node;
     131: aload         7
     133: invokevirtual #166                // Method com/google/javascript/rhino/Node.addChildToFront:(Lcom/google/javascript/rhino/Node;)V
     136: aload_0
     137: getfield      #101                // Field originalGeneratorBody:Lcom/google/javascript/rhino/Node;
     140: aload_3
     141: aload         7
     143: invokevirtual #40                 // Method com/google/javascript/rhino/Node.addChildAfter:(Lcom/google/javascript/rhino/Node;Lcom/google/javascript/rhino/Node;)V
     146: ldc           #167                // String $jscomp$generator$global$error
     148: invokestatic  #27                 // Method com/google/javascript/rhino/IR.name:(Ljava/lang/String;)Lcom/google/javascript/rhino/Node;
     151: aload         8
     153: invokevirtual #62                 // Method com/google/javascript/rhino/Node.cloneTree:()Lcom/google/javascript/rhino/Node;
     156: invokestatic  #58                 // Method com/google/javascript/rhino/IR.assign:(Lcom/google/javascript/rhino/Node;Lcom/google/javascript/rhino/Node;)Lcom/google/javascript/rhino/Node;
     159: astore        9
     161: iconst_3
     162: anewarray     #47                 // class com/google/javascript/rhino/Node
     165: dup
     166: iconst_0
     167: aload         9
     169: invokestatic  #64                 // Method com/google/javascript/rhino/IR.exprResult:(Lcom/google/javascript/rhino/Node;)Lcom/google/javascript/rhino/Node;
     172: aastore
     173: dup
     174: iconst_1
     175: iload         6
     177: invokestatic  #168                // Method createStateUpdate:(I)Lcom/google/javascript/rhino/Node;
     180: aastore
     181: dup
     182: iconst_2
     183: invokestatic  #169                // Method createSafeBreak:()Lcom/google/javascript/rhino/Node;
     186: aastore
     187: invokestatic  #170                // Method com/google/javascript/rhino/IR.block:([Lcom/google/javascript/rhino/Node;)Lcom/google/javascript/rhino/Node;
     190: astore        10
     192: aload         8
     194: aload         10
     196: invokestatic  #171                // Method com/google/javascript/rhino/IR.catchNode:(Lcom/google/javascript/rhino/Node;Lcom/google/javascript/rhino/Node;)Lcom/google/javascript/rhino/Node;
     199: astore        11
     201: aload_0
     202: getfield      #10                 // Field currentExceptionContext:Ljava/util/List;
     205: iconst_0
     206: new           #131                // class com/google/javascript/jscomp/Es6RewriteGenerators$ExceptionContext
     209: dup
     210: aload_0
     211: iload         6
     213: aload         11
     215: invokespecial #172                // Method com/google/javascript/jscomp/Es6RewriteGenerators$ExceptionContext."<init>":(Lcom/google/javascript/jscomp/Es6RewriteGenerators;ILcom/google/javascript/rhino/Node;)V
     218: invokeinterface #173,  3          // InterfaceMethod java/util/List.add:(ILjava/lang/Object;)V
     223: aload         5
     225: ifnull        504
     228: new           #70                 // class java/lang/StringBuilder
     231: dup
     232: invokespecial #71                 // Method java/lang/StringBuilder."<init>":()V
     235: ldc           #174                // String $jscomp$generator$finally
     237: invokevirtual #72                 // Method java/lang/StringBuilder.append:(Ljava/lang/String;)Ljava/lang/StringBuilder;
     240: aload_0
     241: getfield      #2                  // Field generatorCounter:Lcom/google/common/base/Supplier;
     244: invokeinterface #73,  1           // InterfaceMethod com/google/common/base/Supplier.get:()Ljava/lang/Object;
     249: checkcast     #74                 // class java/lang/String
     252: invokevirtual #72                 // Method java/lang/StringBuilder.append:(Ljava/lang/String;)Ljava/lang/StringBuilder;
     255: invokevirtual #75                 // Method java/lang/StringBuilder.toString:()Ljava/lang/String;
     258: invokestatic  #27                 // Method com/google/javascript/rhino/IR.name:(Ljava/lang/String;)Lcom/google/javascript/rhino/Node;
     261: astore        12
     263: getstatic     #17                 // Field generatorCaseCount:I
     266: dup
     267: iconst_1
     268: iadd
     269: putstatic     #17                 // Field generatorCaseCount:I
     272: istore        13
     274: iload         13
     276: i2d
     277: invokestatic  #115                // Method com/google/javascript/rhino/IR.number:(D)Lcom/google/javascript/rhino/Node;
     280: astore        14
     282: aload         14
     284: iconst_1
     285: invokevirtual #163                // Method com/google/javascript/rhino/Node.setGeneratorMarker:(Z)V
     288: getstatic     #17                 // Field generatorCaseCount:I
     291: dup
     292: iconst_1
     293: iadd
     294: putstatic     #17                 // Field generatorCaseCount:I
     297: istore        15
     299: iload         15
     301: i2d
     302: invokestatic  #115                // Method com/google/javascript/rhino/IR.number:(D)Lcom/google/javascript/rhino/Node;
     305: astore        16
     307: aload         16
     309: iconst_1
     310: invokevirtual #163                // Method com/google/javascript/rhino/Node.setGeneratorMarker:(Z)V
     313: aload_0
     314: getfield      #6                  // Field compiler:Lcom/google/javascript/jscomp/AbstractCompiler;
     317: aload_1
     318: new           #175                // class com/google/javascript/jscomp/Es6RewriteGenerators$ControlExitsCheck
     321: dup
     322: aload_0
     323: aload         12
     325: iload         13
     327: invokespecial #176                // Method com/google/javascript/jscomp/Es6RewriteGenerators$ControlExitsCheck."<init>":(Lcom/google/javascript/jscomp/Es6RewriteGenerators;Lcom/google/javascript/rhino/Node;I)V
     330: invokestatic  #14                 // Method com/google/javascript/jscomp/NodeTraversal.traverse:(Lcom/google/javascript/jscomp/AbstractCompiler;Lcom/google/javascript/rhino/Node;Lcom/google/javascript/jscomp/NodeTraversal$Callback;)V
     333: aload_0
     334: getfield      #6                  // Field compiler:Lcom/google/javascript/jscomp/AbstractCompiler;
     337: aload_3
     338: new           #175                // class com/google/javascript/jscomp/Es6RewriteGenerators$ControlExitsCheck
     341: dup
     342: aload_0
     343: aload         12
     345: iload         13
     347: invokespecial #176                // Method com/google/javascript/jscomp/Es6RewriteGenerators$ControlExitsCheck."<init>":(Lcom/google/javascript/jscomp/Es6RewriteGenerators;Lcom/google/javascript/rhino/Node;I)V
     350: invokestatic  #14                 // Method com/google/javascript/jscomp/NodeTraversal.traverse:(Lcom/google/javascript/jscomp/AbstractCompiler;Lcom/google/javascript/rhino/Node;Lcom/google/javascript/jscomp/NodeTraversal$Callback;)V
     353: aload_0
     354: getfield      #101                // Field originalGeneratorBody:Lcom/google/javascript/rhino/Node;
     357: aload_1
     358: invokevirtual #67                 // Method com/google/javascript/rhino/Node.detachFromParent:()Lcom/google/javascript/rhino/Node;
     361: invokevirtual #166                // Method com/google/javascript/rhino/Node.addChildToFront:(Lcom/google/javascript/rhino/Node;)V
     364: aload_0
     365: getfield      #101                // Field originalGeneratorBody:Lcom/google/javascript/rhino/Node;
     368: aload         14
     370: aload_3
     371: invokevirtual #40                 // Method com/google/javascript/rhino/Node.addChildAfter:(Lcom/google/javascript/rhino/Node;Lcom/google/javascript/rhino/Node;)V
     374: aload_0
     375: getfield      #101                // Field originalGeneratorBody:Lcom/google/javascript/rhino/Node;
     378: aload         5
     380: invokevirtual #67                 // Method com/google/javascript/rhino/Node.detachFromParent:()Lcom/google/javascript/rhino/Node;
     383: aload         14
     385: invokevirtual #40                 // Method com/google/javascript/rhino/Node.addChildAfter:(Lcom/google/javascript/rhino/Node;Lcom/google/javascript/rhino/Node;)V
     388: aload_0
     389: getfield      #101                // Field originalGeneratorBody:Lcom/google/javascript/rhino/Node;
     392: aload         16
     394: aload         5
     396: invokevirtual #40                 // Method com/google/javascript/rhino/Node.addChildAfter:(Lcom/google/javascript/rhino/Node;Lcom/google/javascript/rhino/Node;)V
     399: aload_0
     400: getfield      #101                // Field originalGeneratorBody:Lcom/google/javascript/rhino/Node;
     403: aload         12
     405: invokevirtual #62                 // Method com/google/javascript/rhino/Node.cloneTree:()Lcom/google/javascript/rhino/Node;
     408: invokestatic  #52                 // Method com/google/javascript/rhino/IR.var:(Lcom/google/javascript/rhino/Node;)Lcom/google/javascript/rhino/Node;
     411: invokevirtual #166                // Method com/google/javascript/rhino/Node.addChildToFront:(Lcom/google/javascript/rhino/Node;)V
     414: aload         5
     416: ldc           #112                // String $jscomp$generator$state
     418: invokestatic  #27                 // Method com/google/javascript/rhino/IR.name:(Ljava/lang/String;)Lcom/google/javascript/rhino/Node;
     421: aload         12
     423: invokevirtual #62                 // Method com/google/javascript/rhino/Node.cloneTree:()Lcom/google/javascript/rhino/Node;
     426: invokestatic  #58                 // Method com/google/javascript/rhino/IR.assign:(Lcom/google/javascript/rhino/Node;Lcom/google/javascript/rhino/Node;)Lcom/google/javascript/rhino/Node;
     429: invokestatic  #64                 // Method com/google/javascript/rhino/IR.exprResult:(Lcom/google/javascript/rhino/Node;)Lcom/google/javascript/rhino/Node;
     432: invokevirtual #116                // Method com/google/javascript/rhino/Node.addChildToBack:(Lcom/google/javascript/rhino/Node;)V
     435: aload         5
     437: invokestatic  #169                // Method createSafeBreak:()Lcom/google/javascript/rhino/Node;
     440: invokevirtual #116                // Method com/google/javascript/rhino/Node.addChildToBack:(Lcom/google/javascript/rhino/Node;)V
     443: aload_1
     444: aload         12
     446: invokevirtual #62                 // Method com/google/javascript/rhino/Node.cloneTree:()Lcom/google/javascript/rhino/Node;
     449: iload         15
     451: i2d
     452: invokestatic  #115                // Method com/google/javascript/rhino/IR.number:(D)Lcom/google/javascript/rhino/Node;
     455: invokestatic  #58                 // Method com/google/javascript/rhino/IR.assign:(Lcom/google/javascript/rhino/Node;Lcom/google/javascript/rhino/Node;)Lcom/google/javascript/rhino/Node;
     458: invokestatic  #64                 // Method com/google/javascript/rhino/IR.exprResult:(Lcom/google/javascript/rhino/Node;)Lcom/google/javascript/rhino/Node;
     461: invokevirtual #116                // Method com/google/javascript/rhino/Node.addChildToBack:(Lcom/google/javascript/rhino/Node;)V
     464: aload_1
     465: iload         13
     467: invokestatic  #168                // Method createStateUpdate:(I)Lcom/google/javascript/rhino/Node;
     470: invokevirtual #116                // Method com/google/javascript/rhino/Node.addChildToBack:(Lcom/google/javascript/rhino/Node;)V
     473: aload_1
     474: invokestatic  #169                // Method createSafeBreak:()Lcom/google/javascript/rhino/Node;
     477: invokevirtual #116                // Method com/google/javascript/rhino/Node.addChildToBack:(Lcom/google/javascript/rhino/Node;)V
     480: aload_3
     481: aload         12
     483: invokevirtual #62                 // Method com/google/javascript/rhino/Node.cloneTree:()Lcom/google/javascript/rhino/Node;
     486: iload         15
     488: i2d
     489: invokestatic  #115                // Method com/google/javascript/rhino/IR.number:(D)Lcom/google/javascript/rhino/Node;
     492: invokestatic  #58                 // Method com/google/javascript/rhino/IR.assign:(Lcom/google/javascript/rhino/Node;Lcom/google/javascript/rhino/Node;)Lcom/google/javascript/rhino/Node;
     495: invokestatic  #64                 // Method com/google/javascript/rhino/IR.exprResult:(Lcom/google/javascript/rhino/Node;)Lcom/google/javascript/rhino/Node;
     498: invokevirtual #116                // Method com/google/javascript/rhino/Node.addChildToBack:(Lcom/google/javascript/rhino/Node;)V
     501: goto          566
     504: getstatic     #17                 // Field generatorCaseCount:I
     507: dup
     508: iconst_1
     509: iadd
     510: putstatic     #17                 // Field generatorCaseCount:I
     513: istore        12
     515: iload         12
     517: i2d
     518: invokestatic  #115                // Method com/google/javascript/rhino/IR.number:(D)Lcom/google/javascript/rhino/Node;
     521: astore        13
     523: aload         13
     525: iconst_1
     526: invokevirtual #163                // Method com/google/javascript/rhino/Node.setGeneratorMarker:(Z)V
     529: aload_0
     530: getfield      #101                // Field originalGeneratorBody:Lcom/google/javascript/rhino/Node;
     533: aload         13
     535: aload_3
     536: invokevirtual #40                 // Method com/google/javascript/rhino/Node.addChildAfter:(Lcom/google/javascript/rhino/Node;Lcom/google/javascript/rhino/Node;)V
     539: aload_1
     540: iload         12
     542: invokestatic  #168                // Method createStateUpdate:(I)Lcom/google/javascript/rhino/Node;
     545: invokevirtual #116                // Method com/google/javascript/rhino/Node.addChildToBack:(Lcom/google/javascript/rhino/Node;)V
     548: aload_1
     549: invokestatic  #169                // Method createSafeBreak:()Lcom/google/javascript/rhino/Node;
     552: invokevirtual #116                // Method com/google/javascript/rhino/Node.addChildToBack:(Lcom/google/javascript/rhino/Node;)V
     555: aload_0
     556: getfield      #101                // Field originalGeneratorBody:Lcom/google/javascript/rhino/Node;
     559: aload_1
     560: invokevirtual #67                 // Method com/google/javascript/rhino/Node.detachFromParent:()Lcom/google/javascript/rhino/Node;
     563: invokevirtual #166                // Method com/google/javascript/rhino/Node.addChildToFront:(Lcom/google/javascript/rhino/Node;)V
     566: aload_3
     567: aload_2
     568: ldc           #167                // String $jscomp$generator$global$error
     570: invokestatic  #27                 // Method com/google/javascript/rhino/IR.name:(Ljava/lang/String;)Lcom/google/javascript/rhino/Node;
     573: invokestatic  #50                 // Method com/google/javascript/rhino/IR.var:(Lcom/google/javascript/rhino/Node;Lcom/google/javascript/rhino/Node;)Lcom/google/javascript/rhino/Node;
     576: invokevirtual #166                // Method com/google/javascript/rhino/Node.addChildToFront:(Lcom/google/javascript/rhino/Node;)V
     579: aload_0
     580: getfield      #119                // Field enclosingBlock:Lcom/google/javascript/rhino/Node;
     583: invokevirtual #25                 // Method com/google/javascript/rhino/Node.getParent:()Lcom/google/javascript/rhino/Node;
     586: invokevirtual #128                // Method com/google/javascript/rhino/Node.isTry:()Z
     589: ifeq          606
     592: aload_0
     593: aload_0
     594: getfield      #119                // Field enclosingBlock:Lcom/google/javascript/rhino/Node;
     597: invokevirtual #25                 // Method com/google/javascript/rhino/Node.getParent:()Lcom/google/javascript/rhino/Node;
     600: invokevirtual #25                 // Method com/google/javascript/rhino/Node.getParent:()Lcom/google/javascript/rhino/Node;
     603: putfield      #119                // Field enclosingBlock:Lcom/google/javascript/rhino/Node;
     606: aload_0
     607: getfield      #119                // Field enclosingBlock:Lcom/google/javascript/rhino/Node;
     610: invokestatic  #126                // Method com/google/javascript/rhino/IR.block:()Lcom/google/javascript/rhino/Node;
     613: aload         11
     615: invokestatic  #133                // Method com/google/javascript/rhino/IR.tryCatch:(Lcom/google/javascript/rhino/Node;Lcom/google/javascript/rhino/Node;)Lcom/google/javascript/rhino/Node;
     618: invokevirtual #116                // Method com/google/javascript/rhino/Node.addChildToBack:(Lcom/google/javascript/rhino/Node;)V
     621: aload_0
     622: aload_0
     623: getfield      #119                // Field enclosingBlock:Lcom/google/javascript/rhino/Node;
     626: invokevirtual #100                // Method com/google/javascript/rhino/Node.getLastChild:()Lcom/google/javascript/rhino/Node;
     629: invokevirtual #99                 // Method com/google/javascript/rhino/Node.getFirstChild:()Lcom/google/javascript/rhino/Node;
     632: putfield      #119                // Field enclosingBlock:Lcom/google/javascript/rhino/Node;
     635: aload_0
     636: getfield      #76                 // Field hasTranslatedTry:Z
     639: ifne          669
     642: aload_0
     643: iconst_1
     644: putfield      #76                 // Field hasTranslatedTry:Z
     647: aload_0
     648: getfield      #120                // Field hoistRoot:Lcom/google/javascript/rhino/Node;
     651: invokevirtual #25                 // Method com/google/javascript/rhino/Node.getParent:()Lcom/google/javascript/rhino/Node;
     654: ldc           #167                // String $jscomp$generator$global$error
     656: invokestatic  #27                 // Method com/google/javascript/rhino/IR.name:(Ljava/lang/String;)Lcom/google/javascript/rhino/Node;
     659: invokestatic  #52                 // Method com/google/javascript/rhino/IR.var:(Lcom/google/javascript/rhino/Node;)Lcom/google/javascript/rhino/Node;
     662: aload_0
     663: getfield      #120                // Field hoistRoot:Lcom/google/javascript/rhino/Node;
     666: invokevirtual #40                 // Method com/google/javascript/rhino/Node.addChildAfter:(Lcom/google/javascript/rhino/Node;Lcom/google/javascript/rhino/Node;)V
     669: return

  private void visitContinue();
    Code:
       0: aload_0
       1: getfield      #9                  // Field currentLoopContext:Ljava/util/List;
       4: iconst_0
       5: invokeinterface #130,  2          // InterfaceMethod java/util/List.get:(I)Ljava/lang/Object;
      10: checkcast     #177                // class com/google/javascript/jscomp/Es6RewriteGenerators$LoopContext
      13: getfield      #178                // Field com/google/javascript/jscomp/Es6RewriteGenerators$LoopContext.continueCase:I
      16: iconst_m1
      17: if_icmpeq     24
      20: iconst_1
      21: goto          25
      24: iconst_0
      25: invokestatic  #179                // Method com/google/common/base/Preconditions.checkState:(Z)V
      28: aload_0
      29: getfield      #3                  // Field currentStatement:Lcom/google/javascript/rhino/Node;
      32: invokevirtual #68                 // Method com/google/javascript/rhino/Node.hasChildren:()Z
      35: ifeq          59
      38: aload_0
      39: aload_0
      40: getfield      #3                  // Field currentStatement:Lcom/google/javascript/rhino/Node;
      43: invokevirtual #48                 // Method com/google/javascript/rhino/Node.removeFirstChild:()Lcom/google/javascript/rhino/Node;
      46: invokevirtual #165                // Method com/google/javascript/rhino/Node.getString:()Ljava/lang/String;
      49: invokespecial #180                // Method getLoopContext:(Ljava/lang/String;)Lcom/google/javascript/jscomp/Es6RewriteGenerators$LoopContext;
      52: getfield      #178                // Field com/google/javascript/jscomp/Es6RewriteGenerators$LoopContext.continueCase:I
      55: istore_1
      56: goto          76
      59: aload_0
      60: getfield      #9                  // Field currentLoopContext:Ljava/util/List;
      63: iconst_0
      64: invokeinterface #130,  2          // InterfaceMethod java/util/List.get:(I)Ljava/lang/Object;
      69: checkcast     #177                // class com/google/javascript/jscomp/Es6RewriteGenerators$LoopContext
      72: getfield      #178                // Field com/google/javascript/jscomp/Es6RewriteGenerators$LoopContext.continueCase:I
      75: istore_1
      76: aload_0
      77: getfield      #119                // Field enclosingBlock:Lcom/google/javascript/rhino/Node;
      80: iload_1
      81: invokestatic  #168                // Method createStateUpdate:(I)Lcom/google/javascript/rhino/Node;
      84: invokevirtual #116                // Method com/google/javascript/rhino/Node.addChildToBack:(Lcom/google/javascript/rhino/Node;)V
      87: aload_0
      88: getfield      #119                // Field enclosingBlock:Lcom/google/javascript/rhino/Node;
      91: invokestatic  #169                // Method createSafeBreak:()Lcom/google/javascript/rhino/Node;
      94: invokevirtual #116                // Method com/google/javascript/rhino/Node.addChildToBack:(Lcom/google/javascript/rhino/Node;)V
      97: return

  private void visitThrow();
    Code:
       0: aload_0
       1: getfield      #119                // Field enclosingBlock:Lcom/google/javascript/rhino/Node;
       4: iconst_m1
       5: invokestatic  #168                // Method createStateUpdate:(I)Lcom/google/javascript/rhino/Node;
       8: invokevirtual #116                // Method com/google/javascript/rhino/Node.addChildToBack:(Lcom/google/javascript/rhino/Node;)V
      11: aload_0
      12: getfield      #119                // Field enclosingBlock:Lcom/google/javascript/rhino/Node;
      15: aload_0
      16: getfield      #3                  // Field currentStatement:Lcom/google/javascript/rhino/Node;
      19: invokevirtual #116                // Method com/google/javascript/rhino/Node.addChildToBack:(Lcom/google/javascript/rhino/Node;)V
      22: return

  private void visitBreak();
    Code:
       0: aload_0
       1: getfield      #3                  // Field currentStatement:Lcom/google/javascript/rhino/Node;
       4: invokevirtual #68                 // Method com/google/javascript/rhino/Node.hasChildren:()Z
       7: ifeq          64
      10: aload_0
      11: aload_0
      12: getfield      #3                  // Field currentStatement:Lcom/google/javascript/rhino/Node;
      15: invokevirtual #48                 // Method com/google/javascript/rhino/Node.removeFirstChild:()Lcom/google/javascript/rhino/Node;
      18: invokevirtual #165                // Method com/google/javascript/rhino/Node.getString:()Ljava/lang/String;
      21: invokespecial #180                // Method getLoopContext:(Ljava/lang/String;)Lcom/google/javascript/jscomp/Es6RewriteGenerators$LoopContext;
      24: astore_2
      25: aload_2
      26: ifnonnull     56
      29: aload_0
      30: getfield      #6                  // Field compiler:Lcom/google/javascript/jscomp/AbstractCompiler;
      33: aload_0
      34: getfield      #3                  // Field currentStatement:Lcom/google/javascript/rhino/Node;
      37: getstatic     #181                // Field com/google/javascript/jscomp/Es6ToEs3Converter.CANNOT_CONVERT_YET:Lcom/google/javascript/jscomp/DiagnosticType;
      40: iconst_1
      41: anewarray     #74                 // class java/lang/String
      44: dup
      45: iconst_0
      46: ldc           #182                // String Breaking to a label that is not a loop
      48: aastore
      49: invokestatic  #183                // Method com/google/javascript/jscomp/JSError.make:(Lcom/google/javascript/rhino/Node;Lcom/google/javascript/jscomp/DiagnosticType;[Ljava/lang/String;)Lcom/google/javascript/jscomp/JSError;
      52: invokevirtual #184                // Method com/google/javascript/jscomp/AbstractCompiler.report:(Lcom/google/javascript/jscomp/JSError;)V
      55: return
      56: aload_2
      57: getfield      #185                // Field com/google/javascript/jscomp/Es6RewriteGenerators$LoopContext.breakCase:I
      60: istore_1
      61: goto          81
      64: aload_0
      65: getfield      #9                  // Field currentLoopContext:Ljava/util/List;
      68: iconst_0
      69: invokeinterface #130,  2          // InterfaceMethod java/util/List.get:(I)Ljava/lang/Object;
      74: checkcast     #177                // class com/google/javascript/jscomp/Es6RewriteGenerators$LoopContext
      77: getfield      #185                // Field com/google/javascript/jscomp/Es6RewriteGenerators$LoopContext.breakCase:I
      80: istore_1
      81: aload_0
      82: getfield      #119                // Field enclosingBlock:Lcom/google/javascript/rhino/Node;
      85: iload_1
      86: invokestatic  #168                // Method createStateUpdate:(I)Lcom/google/javascript/rhino/Node;
      89: invokevirtual #116                // Method com/google/javascript/rhino/Node.addChildToBack:(Lcom/google/javascript/rhino/Node;)V
      92: aload_0
      93: getfield      #119                // Field enclosingBlock:Lcom/google/javascript/rhino/Node;
      96: invokestatic  #169                // Method createSafeBreak:()Lcom/google/javascript/rhino/Node;
      99: invokevirtual #116                // Method com/google/javascript/rhino/Node.addChildToBack:(Lcom/google/javascript/rhino/Node;)V
     102: return

  private void visitLabel();
    Code:
       0: aload_0
       1: getfield      #3                  // Field currentStatement:Lcom/google/javascript/rhino/Node;
       4: invokevirtual #48                 // Method com/google/javascript/rhino/Node.removeFirstChild:()Lcom/google/javascript/rhino/Node;
       7: astore_1
       8: aload_0
       9: getfield      #3                  // Field currentStatement:Lcom/google/javascript/rhino/Node;
      12: invokevirtual #48                 // Method com/google/javascript/rhino/Node.removeFirstChild:()Lcom/google/javascript/rhino/Node;
      15: astore_2
      16: aload_2
      17: invokestatic  #186                // Method com/google/javascript/jscomp/NodeUtil.isLoopStructure:(Lcom/google/javascript/rhino/Node;)Z
      20: ifeq          39
      23: aload_0
      24: aload_2
      25: putfield      #3                  // Field currentStatement:Lcom/google/javascript/rhino/Node;
      28: aload_0
      29: aload_1
      30: invokevirtual #165                // Method com/google/javascript/rhino/Node.getString:()Ljava/lang/String;
      33: invokespecial #144                // Method visitLoop:(Ljava/lang/String;)V
      36: goto          47
      39: aload_0
      40: getfield      #101                // Field originalGeneratorBody:Lcom/google/javascript/rhino/Node;
      43: aload_2
      44: invokevirtual #166                // Method com/google/javascript/rhino/Node.addChildToFront:(Lcom/google/javascript/rhino/Node;)V
      47: return

  private void visitGeneratorMarker();
    Code:
       0: aload_0
       1: getfield      #9                  // Field currentLoopContext:Ljava/util/List;
       4: invokeinterface #129,  1          // InterfaceMethod java/util/List.isEmpty:()Z
       9: ifne          51
      12: aload_0
      13: getfield      #9                  // Field currentLoopContext:Ljava/util/List;
      16: iconst_0
      17: invokeinterface #130,  2          // InterfaceMethod java/util/List.get:(I)Ljava/lang/Object;
      22: checkcast     #177                // class com/google/javascript/jscomp/Es6RewriteGenerators$LoopContext
      25: getfield      #185                // Field com/google/javascript/jscomp/Es6RewriteGenerators$LoopContext.breakCase:I
      28: i2d
      29: aload_0
      30: getfield      #3                  // Field currentStatement:Lcom/google/javascript/rhino/Node;
      33: invokevirtual #125                // Method com/google/javascript/rhino/Node.getDouble:()D
      36: dcmpl
      37: ifne          51
      40: aload_0
      41: getfield      #9                  // Field currentLoopContext:Ljava/util/List;
      44: iconst_0
      45: invokeinterface #187,  2          // InterfaceMethod java/util/List.remove:(I)Ljava/lang/Object;
      50: pop
      51: aload_0
      52: getfield      #10                 // Field currentExceptionContext:Ljava/util/List;
      55: invokeinterface #129,  1          // InterfaceMethod java/util/List.isEmpty:()Z
      60: ifne          102
      63: aload_0
      64: getfield      #10                 // Field currentExceptionContext:Ljava/util/List;
      67: iconst_0
      68: invokeinterface #130,  2          // InterfaceMethod java/util/List.get:(I)Ljava/lang/Object;
      73: checkcast     #131                // class com/google/javascript/jscomp/Es6RewriteGenerators$ExceptionContext
      76: getfield      #188                // Field com/google/javascript/jscomp/Es6RewriteGenerators$ExceptionContext.catchStartCase:I
      79: i2d
      80: aload_0
      81: getfield      #3                  // Field currentStatement:Lcom/google/javascript/rhino/Node;
      84: invokevirtual #125                // Method com/google/javascript/rhino/Node.getDouble:()D
      87: dcmpl
      88: ifne          102
      91: aload_0
      92: getfield      #10                 // Field currentExceptionContext:Ljava/util/List;
      95: iconst_0
      96: invokeinterface #187,  2          // InterfaceMethod java/util/List.remove:(I)Ljava/lang/Object;
     101: pop
     102: return

  private void visitIf();
    Code:
       0: aload_0
       1: getfield      #3                  // Field currentStatement:Lcom/google/javascript/rhino/Node;
       4: invokevirtual #48                 // Method com/google/javascript/rhino/Node.removeFirstChild:()Lcom/google/javascript/rhino/Node;
       7: astore_1
       8: aload_0
       9: getfield      #3                  // Field currentStatement:Lcom/google/javascript/rhino/Node;
      12: invokevirtual #48                 // Method com/google/javascript/rhino/Node.removeFirstChild:()Lcom/google/javascript/rhino/Node;
      15: astore_2
      16: aload_0
      17: getfield      #3                  // Field currentStatement:Lcom/google/javascript/rhino/Node;
      20: invokevirtual #68                 // Method com/google/javascript/rhino/Node.hasChildren:()Z
      23: istore_3
      24: getstatic     #17                 // Field generatorCaseCount:I
      27: dup
      28: iconst_1
      29: iadd
      30: putstatic     #17                 // Field generatorCaseCount:I
      33: istore        4
      35: aload_1
      36: invokestatic  #60                 // Method com/google/javascript/rhino/IR.not:(Lcom/google/javascript/rhino/Node;)Lcom/google/javascript/rhino/Node;
      39: iconst_2
      40: anewarray     #47                 // class com/google/javascript/rhino/Node
      43: dup
      44: iconst_0
      45: iload         4
      47: invokestatic  #168                // Method createStateUpdate:(I)Lcom/google/javascript/rhino/Node;
      50: aastore
      51: dup
      52: iconst_1
      53: invokestatic  #169                // Method createSafeBreak:()Lcom/google/javascript/rhino/Node;
      56: aastore
      57: invokestatic  #170                // Method com/google/javascript/rhino/IR.block:([Lcom/google/javascript/rhino/Node;)Lcom/google/javascript/rhino/Node;
      60: invokestatic  #39                 // Method com/google/javascript/rhino/IR.ifNode:(Lcom/google/javascript/rhino/Node;Lcom/google/javascript/rhino/Node;)Lcom/google/javascript/rhino/Node;
      63: astore        5
      65: aload         5
      67: iconst_1
      68: invokevirtual #162                // Method com/google/javascript/rhino/Node.setGeneratorSafe:(Z)V
      71: iload         4
      73: i2d
      74: invokestatic  #115                // Method com/google/javascript/rhino/IR.number:(D)Lcom/google/javascript/rhino/Node;
      77: astore        6
      79: aload         6
      81: iconst_1
      82: invokevirtual #163                // Method com/google/javascript/rhino/Node.setGeneratorMarker:(Z)V
      85: aload_0
      86: getfield      #101                // Field originalGeneratorBody:Lcom/google/javascript/rhino/Node;
      89: aload         5
      91: invokevirtual #166                // Method com/google/javascript/rhino/Node.addChildToFront:(Lcom/google/javascript/rhino/Node;)V
      94: aload_0
      95: getfield      #101                // Field originalGeneratorBody:Lcom/google/javascript/rhino/Node;
      98: aload_2
      99: aload         5
     101: invokevirtual #40                 // Method com/google/javascript/rhino/Node.addChildAfter:(Lcom/google/javascript/rhino/Node;Lcom/google/javascript/rhino/Node;)V
     104: aload_0
     105: getfield      #101                // Field originalGeneratorBody:Lcom/google/javascript/rhino/Node;
     108: aload         6
     110: aload_2
     111: invokevirtual #40                 // Method com/google/javascript/rhino/Node.addChildAfter:(Lcom/google/javascript/rhino/Node;Lcom/google/javascript/rhino/Node;)V
     114: iload_3
     115: ifeq          190
     118: aload_0
     119: getfield      #3                  // Field currentStatement:Lcom/google/javascript/rhino/Node;
     122: invokevirtual #48                 // Method com/google/javascript/rhino/Node.removeFirstChild:()Lcom/google/javascript/rhino/Node;
     125: astore        7
     127: getstatic     #17                 // Field generatorCaseCount:I
     130: dup
     131: iconst_1
     132: iadd
     133: putstatic     #17                 // Field generatorCaseCount:I
     136: istore        8
     138: iload         8
     140: i2d
     141: invokestatic  #115                // Method com/google/javascript/rhino/IR.number:(D)Lcom/google/javascript/rhino/Node;
     144: astore        9
     146: aload         9
     148: iconst_1
     149: invokevirtual #163                // Method com/google/javascript/rhino/Node.setGeneratorMarker:(Z)V
     152: aload_2
     153: iload         8
     155: invokestatic  #168                // Method createStateUpdate:(I)Lcom/google/javascript/rhino/Node;
     158: invokevirtual #116                // Method com/google/javascript/rhino/Node.addChildToBack:(Lcom/google/javascript/rhino/Node;)V
     161: aload_2
     162: invokestatic  #169                // Method createSafeBreak:()Lcom/google/javascript/rhino/Node;
     165: invokevirtual #116                // Method com/google/javascript/rhino/Node.addChildToBack:(Lcom/google/javascript/rhino/Node;)V
     168: aload_0
     169: getfield      #101                // Field originalGeneratorBody:Lcom/google/javascript/rhino/Node;
     172: aload         7
     174: aload         6
     176: invokevirtual #40                 // Method com/google/javascript/rhino/Node.addChildAfter:(Lcom/google/javascript/rhino/Node;Lcom/google/javascript/rhino/Node;)V
     179: aload_0
     180: getfield      #101                // Field originalGeneratorBody:Lcom/google/javascript/rhino/Node;
     183: aload         9
     185: aload         7
     187: invokevirtual #40                 // Method com/google/javascript/rhino/Node.addChildAfter:(Lcom/google/javascript/rhino/Node;Lcom/google/javascript/rhino/Node;)V
     190: return

  private void visitSwitch();
    Code:
       0: new           #70                 // class java/lang/StringBuilder
       3: dup
       4: invokespecial #71                 // Method java/lang/StringBuilder."<init>":()V
       7: ldc           #189                // String $jscomp$generator$switch$entered
       9: invokevirtual #72                 // Method java/lang/StringBuilder.append:(Ljava/lang/String;)Ljava/lang/StringBuilder;
      12: aload_0
      13: getfield      #2                  // Field generatorCounter:Lcom/google/common/base/Supplier;
      16: invokeinterface #73,  1           // InterfaceMethod com/google/common/base/Supplier.get:()Ljava/lang/Object;
      21: checkcast     #74                 // class java/lang/String
      24: invokevirtual #72                 // Method java/lang/StringBuilder.append:(Ljava/lang/String;)Ljava/lang/StringBuilder;
      27: invokevirtual #75                 // Method java/lang/StringBuilder.toString:()Ljava/lang/String;
      30: invokestatic  #27                 // Method com/google/javascript/rhino/IR.name:(Ljava/lang/String;)Lcom/google/javascript/rhino/Node;
      33: astore_1
      34: aload_1
      35: invokevirtual #62                 // Method com/google/javascript/rhino/Node.cloneTree:()Lcom/google/javascript/rhino/Node;
      38: invokestatic  #190                // Method com/google/javascript/rhino/IR.falseNode:()Lcom/google/javascript/rhino/Node;
      41: invokestatic  #50                 // Method com/google/javascript/rhino/IR.var:(Lcom/google/javascript/rhino/Node;Lcom/google/javascript/rhino/Node;)Lcom/google/javascript/rhino/Node;
      44: astore_2
      45: new           #70                 // class java/lang/StringBuilder
      48: dup
      49: invokespecial #71                 // Method java/lang/StringBuilder."<init>":()V
      52: ldc           #191                // String $jscomp$generator$switch$val
      54: invokevirtual #72                 // Method java/lang/StringBuilder.append:(Ljava/lang/String;)Ljava/lang/StringBuilder;
      57: aload_0
      58: getfield      #2                  // Field generatorCounter:Lcom/google/common/base/Supplier;
      61: invokeinterface #73,  1           // InterfaceMethod com/google/common/base/Supplier.get:()Ljava/lang/Object;
      66: checkcast     #74                 // class java/lang/String
      69: invokevirtual #72                 // Method java/lang/StringBuilder.append:(Ljava/lang/String;)Ljava/lang/StringBuilder;
      72: invokevirtual #75                 // Method java/lang/StringBuilder.toString:()Ljava/lang/String;
      75: invokestatic  #27                 // Method com/google/javascript/rhino/IR.name:(Ljava/lang/String;)Lcom/google/javascript/rhino/Node;
      78: astore_3
      79: aload_3
      80: invokevirtual #62                 // Method com/google/javascript/rhino/Node.cloneTree:()Lcom/google/javascript/rhino/Node;
      83: aload_0
      84: getfield      #3                  // Field currentStatement:Lcom/google/javascript/rhino/Node;
      87: invokevirtual #48                 // Method com/google/javascript/rhino/Node.removeFirstChild:()Lcom/google/javascript/rhino/Node;
      90: invokestatic  #50                 // Method com/google/javascript/rhino/IR.var:(Lcom/google/javascript/rhino/Node;Lcom/google/javascript/rhino/Node;)Lcom/google/javascript/rhino/Node;
      93: astore        4
      95: aload_0
      96: getfield      #101                // Field originalGeneratorBody:Lcom/google/javascript/rhino/Node;
      99: aload_2
     100: invokevirtual #166                // Method com/google/javascript/rhino/Node.addChildToFront:(Lcom/google/javascript/rhino/Node;)V
     103: aload_0
     104: getfield      #101                // Field originalGeneratorBody:Lcom/google/javascript/rhino/Node;
     107: aload         4
     109: aload_2
     110: invokevirtual #40                 // Method com/google/javascript/rhino/Node.addChildAfter:(Lcom/google/javascript/rhino/Node;Lcom/google/javascript/rhino/Node;)V
     113: aload         4
     115: astore        5
     117: aload_0
     118: getfield      #3                  // Field currentStatement:Lcom/google/javascript/rhino/Node;
     121: invokevirtual #68                 // Method com/google/javascript/rhino/Node.hasChildren:()Z
     124: ifeq          261
     127: aload_0
     128: getfield      #3                  // Field currentStatement:Lcom/google/javascript/rhino/Node;
     131: invokevirtual #48                 // Method com/google/javascript/rhino/Node.removeFirstChild:()Lcom/google/javascript/rhino/Node;
     134: astore        6
     136: aload         6
     138: invokevirtual #100                // Method com/google/javascript/rhino/Node.getLastChild:()Lcom/google/javascript/rhino/Node;
     141: aload_1
     142: invokevirtual #62                 // Method com/google/javascript/rhino/Node.cloneTree:()Lcom/google/javascript/rhino/Node;
     145: invokestatic  #192                // Method com/google/javascript/rhino/IR.trueNode:()Lcom/google/javascript/rhino/Node;
     148: invokestatic  #58                 // Method com/google/javascript/rhino/IR.assign:(Lcom/google/javascript/rhino/Node;Lcom/google/javascript/rhino/Node;)Lcom/google/javascript/rhino/Node;
     151: invokestatic  #64                 // Method com/google/javascript/rhino/IR.exprResult:(Lcom/google/javascript/rhino/Node;)Lcom/google/javascript/rhino/Node;
     154: invokevirtual #166                // Method com/google/javascript/rhino/Node.addChildToFront:(Lcom/google/javascript/rhino/Node;)V
     157: aload         6
     159: invokevirtual #193                // Method com/google/javascript/rhino/Node.isDefaultCase:()Z
     162: ifeq          214
     165: aload_0
     166: getfield      #3                  // Field currentStatement:Lcom/google/javascript/rhino/Node;
     169: invokevirtual #68                 // Method com/google/javascript/rhino/Node.hasChildren:()Z
     172: ifeq          201
     175: aload_0
     176: getfield      #6                  // Field compiler:Lcom/google/javascript/jscomp/AbstractCompiler;
     179: aload_0
     180: getfield      #3                  // Field currentStatement:Lcom/google/javascript/rhino/Node;
     183: getstatic     #181                // Field com/google/javascript/jscomp/Es6ToEs3Converter.CANNOT_CONVERT_YET:Lcom/google/javascript/jscomp/DiagnosticType;
     186: iconst_1
     187: anewarray     #74                 // class java/lang/String
     190: dup
     191: iconst_0
     192: ldc           #194                // String Default case as intermediate case
     194: aastore
     195: invokestatic  #183                // Method com/google/javascript/jscomp/JSError.make:(Lcom/google/javascript/rhino/Node;Lcom/google/javascript/jscomp/DiagnosticType;[Ljava/lang/String;)Lcom/google/javascript/jscomp/JSError;
     198: invokevirtual #184                // Method com/google/javascript/jscomp/AbstractCompiler.report:(Lcom/google/javascript/jscomp/JSError;)V
     201: aload         6
     203: invokevirtual #48                 // Method com/google/javascript/rhino/Node.removeFirstChild:()Lcom/google/javascript/rhino/Node;
     206: invokestatic  #38                 // Method com/google/javascript/rhino/IR.block:(Lcom/google/javascript/rhino/Node;)Lcom/google/javascript/rhino/Node;
     209: astore        7
     211: goto          243
     214: aload_1
     215: invokevirtual #62                 // Method com/google/javascript/rhino/Node.cloneTree:()Lcom/google/javascript/rhino/Node;
     218: aload_3
     219: invokevirtual #62                 // Method com/google/javascript/rhino/Node.cloneTree:()Lcom/google/javascript/rhino/Node;
     222: aload         6
     224: invokevirtual #48                 // Method com/google/javascript/rhino/Node.removeFirstChild:()Lcom/google/javascript/rhino/Node;
     227: invokestatic  #195                // Method com/google/javascript/rhino/IR.sheq:(Lcom/google/javascript/rhino/Node;Lcom/google/javascript/rhino/Node;)Lcom/google/javascript/rhino/Node;
     230: invokestatic  #196                // Method com/google/javascript/rhino/IR.or:(Lcom/google/javascript/rhino/Node;Lcom/google/javascript/rhino/Node;)Lcom/google/javascript/rhino/Node;
     233: aload         6
     235: invokevirtual #48                 // Method com/google/javascript/rhino/Node.removeFirstChild:()Lcom/google/javascript/rhino/Node;
     238: invokestatic  #39                 // Method com/google/javascript/rhino/IR.ifNode:(Lcom/google/javascript/rhino/Node;Lcom/google/javascript/rhino/Node;)Lcom/google/javascript/rhino/Node;
     241: astore        7
     243: aload_0
     244: getfield      #101                // Field originalGeneratorBody:Lcom/google/javascript/rhino/Node;
     247: aload         7
     249: aload         5
     251: invokevirtual #40                 // Method com/google/javascript/rhino/Node.addChildAfter:(Lcom/google/javascript/rhino/Node;Lcom/google/javascript/rhino/Node;)V
     254: aload         7
     256: astore        5
     258: goto          117
     261: getstatic     #17                 // Field generatorCaseCount:I
     264: dup
     265: iconst_1
     266: iadd
     267: putstatic     #17                 // Field generatorCaseCount:I
     270: istore        6
     272: aload_0
     273: getfield      #9                  // Field currentLoopContext:Ljava/util/List;
     276: invokeinterface #129,  1          // InterfaceMethod java/util/List.isEmpty:()Z
     281: ifeq          288
     284: iconst_m1
     285: goto          304
     288: aload_0
     289: getfield      #9                  // Field currentLoopContext:Ljava/util/List;
     292: iconst_0
     293: invokeinterface #130,  2          // InterfaceMethod java/util/List.get:(I)Ljava/lang/Object;
     298: checkcast     #177                // class com/google/javascript/jscomp/Es6RewriteGenerators$LoopContext
     301: getfield      #178                // Field com/google/javascript/jscomp/Es6RewriteGenerators$LoopContext.continueCase:I
     304: istore        7
     306: aload_0
     307: getfield      #9                  // Field currentLoopContext:Ljava/util/List;
     310: iconst_0
     311: new           #177                // class com/google/javascript/jscomp/Es6RewriteGenerators$LoopContext
     314: dup
     315: aload_0
     316: iload         6
     318: iload         7
     320: aconst_null
     321: invokespecial #197                // Method com/google/javascript/jscomp/Es6RewriteGenerators$LoopContext."<init>":(Lcom/google/javascript/jscomp/Es6RewriteGenerators;IILjava/lang/String;)V
     324: invokeinterface #173,  3          // InterfaceMethod java/util/List.add:(ILjava/lang/Object;)V
     329: iload         6
     331: i2d
     332: invokestatic  #115                // Method com/google/javascript/rhino/IR.number:(D)Lcom/google/javascript/rhino/Node;
     335: astore        8
     337: aload         8
     339: iconst_1
     340: invokevirtual #163                // Method com/google/javascript/rhino/Node.setGeneratorMarker:(Z)V
     343: aload_0
     344: getfield      #101                // Field originalGeneratorBody:Lcom/google/javascript/rhino/Node;
     347: aload         8
     349: aload         5
     351: invokevirtual #40                 // Method com/google/javascript/rhino/Node.addChildAfter:(Lcom/google/javascript/rhino/Node;Lcom/google/javascript/rhino/Node;)V
     354: return

  private void visitBlock();
    Code:
       0: aload_0
       1: getfield      #3                  // Field currentStatement:Lcom/google/javascript/rhino/Node;
       4: invokevirtual #198                // Method com/google/javascript/rhino/Node.getChildCount:()I
       7: ifne          11
      10: return
      11: aload_0
      12: getfield      #3                  // Field currentStatement:Lcom/google/javascript/rhino/Node;
      15: invokevirtual #48                 // Method com/google/javascript/rhino/Node.removeFirstChild:()Lcom/google/javascript/rhino/Node;
      18: astore_1
      19: aload_0
      20: getfield      #101                // Field originalGeneratorBody:Lcom/google/javascript/rhino/Node;
      23: aload_1
      24: invokevirtual #166                // Method com/google/javascript/rhino/Node.addChildToFront:(Lcom/google/javascript/rhino/Node;)V
      27: aload_0
      28: getfield      #3                  // Field currentStatement:Lcom/google/javascript/rhino/Node;
      31: invokevirtual #48                 // Method com/google/javascript/rhino/Node.removeFirstChild:()Lcom/google/javascript/rhino/Node;
      34: astore_2
      35: aload_2
      36: ifnull        61
      39: aload_0
      40: getfield      #101                // Field originalGeneratorBody:Lcom/google/javascript/rhino/Node;
      43: aload_2
      44: aload_1
      45: invokevirtual #40                 // Method com/google/javascript/rhino/Node.addChildAfter:(Lcom/google/javascript/rhino/Node;Lcom/google/javascript/rhino/Node;)V
      48: aload_2
      49: astore_1
      50: aload_0
      51: getfield      #3                  // Field currentStatement:Lcom/google/javascript/rhino/Node;
      54: invokevirtual #48                 // Method com/google/javascript/rhino/Node.removeFirstChild:()Lcom/google/javascript/rhino/Node;
      57: astore_2
      58: goto          35
      61: return

  private void visitForIn();
    Code:
       0: aload_0
       1: getfield      #3                  // Field currentStatement:Lcom/google/javascript/rhino/Node;
       4: invokevirtual #48                 // Method com/google/javascript/rhino/Node.removeFirstChild:()Lcom/google/javascript/rhino/Node;
       7: astore_1
       8: aload_0
       9: getfield      #3                  // Field currentStatement:Lcom/google/javascript/rhino/Node;
      12: invokevirtual #48                 // Method com/google/javascript/rhino/Node.removeFirstChild:()Lcom/google/javascript/rhino/Node;
      15: astore_2
      16: aload_0
      17: getfield      #3                  // Field currentStatement:Lcom/google/javascript/rhino/Node;
      20: invokevirtual #48                 // Method com/google/javascript/rhino/Node.removeFirstChild:()Lcom/google/javascript/rhino/Node;
      23: astore_3
      24: aload_0
      25: getfield      #2                  // Field generatorCounter:Lcom/google/common/base/Supplier;
      28: invokeinterface #73,  1           // InterfaceMethod com/google/common/base/Supplier.get:()Ljava/lang/Object;
      33: checkcast     #74                 // class java/lang/String
      36: astore        4
      38: new           #70                 // class java/lang/StringBuilder
      41: dup
      42: invokespecial #71                 // Method java/lang/StringBuilder."<init>":()V
      45: ldc           #199                // String $jscomp$generator$forin$array
      47: invokevirtual #72                 // Method java/lang/StringBuilder.append:(Ljava/lang/String;)Ljava/lang/StringBuilder;
      50: aload         4
      52: invokevirtual #72                 // Method java/lang/StringBuilder.append:(Ljava/lang/String;)Ljava/lang/StringBuilder;
      55: invokevirtual #75                 // Method java/lang/StringBuilder.toString:()Ljava/lang/String;
      58: invokestatic  #27                 // Method com/google/javascript/rhino/IR.name:(Ljava/lang/String;)Lcom/google/javascript/rhino/Node;
      61: astore        5
      63: new           #70                 // class java/lang/StringBuilder
      66: dup
      67: invokespecial #71                 // Method java/lang/StringBuilder."<init>":()V
      70: ldc           #200                // String $jscomp$generator$forin$var
      72: invokevirtual #72                 // Method java/lang/StringBuilder.append:(Ljava/lang/String;)Ljava/lang/StringBuilder;
      75: aload         4
      77: invokevirtual #72                 // Method java/lang/StringBuilder.append:(Ljava/lang/String;)Ljava/lang/StringBuilder;
      80: invokevirtual #75                 // Method java/lang/StringBuilder.toString:()Ljava/lang/String;
      83: invokestatic  #27                 // Method com/google/javascript/rhino/IR.name:(Ljava/lang/String;)Lcom/google/javascript/rhino/Node;
      86: astore        6
      88: new           #70                 // class java/lang/StringBuilder
      91: dup
      92: invokespecial #71                 // Method java/lang/StringBuilder."<init>":()V
      95: ldc           #201                // String $jscomp$generator$forin$iter
      97: invokevirtual #72                 // Method java/lang/StringBuilder.append:(Ljava/lang/String;)Ljava/lang/StringBuilder;
     100: aload         4
     102: invokevirtual #72                 // Method java/lang/StringBuilder.append:(Ljava/lang/String;)Ljava/lang/StringBuilder;
     105: invokevirtual #75                 // Method java/lang/StringBuilder.toString:()Ljava/lang/String;
     108: invokestatic  #27                 // Method com/google/javascript/rhino/IR.name:(Ljava/lang/String;)Lcom/google/javascript/rhino/Node;
     111: astore        7
     113: aload_1
     114: invokevirtual #135                // Method com/google/javascript/rhino/Node.isVar:()Z
     117: ifeq          125
     120: aload_1
     121: invokevirtual #48                 // Method com/google/javascript/rhino/Node.removeFirstChild:()Lcom/google/javascript/rhino/Node;
     124: astore_1
     125: aload_3
     126: aload_1
     127: invokevirtual #62                 // Method com/google/javascript/rhino/Node.cloneTree:()Lcom/google/javascript/rhino/Node;
     130: aload         7
     132: invokevirtual #62                 // Method com/google/javascript/rhino/Node.cloneTree:()Lcom/google/javascript/rhino/Node;
     135: invokestatic  #202                // Method com/google/javascript/rhino/IR.in:(Lcom/google/javascript/rhino/Node;Lcom/google/javascript/rhino/Node;)Lcom/google/javascript/rhino/Node;
     138: invokestatic  #60                 // Method com/google/javascript/rhino/IR.not:(Lcom/google/javascript/rhino/Node;)Lcom/google/javascript/rhino/Node;
     141: invokestatic  #203                // Method com/google/javascript/rhino/IR.continueNode:()Lcom/google/javascript/rhino/Node;
     144: invokestatic  #38                 // Method com/google/javascript/rhino/IR.block:(Lcom/google/javascript/rhino/Node;)Lcom/google/javascript/rhino/Node;
     147: invokestatic  #39                 // Method com/google/javascript/rhino/IR.ifNode:(Lcom/google/javascript/rhino/Node;Lcom/google/javascript/rhino/Node;)Lcom/google/javascript/rhino/Node;
     150: invokevirtual #166                // Method com/google/javascript/rhino/Node.addChildToFront:(Lcom/google/javascript/rhino/Node;)V
     153: aload_3
     154: aload_1
     155: invokevirtual #62                 // Method com/google/javascript/rhino/Node.cloneTree:()Lcom/google/javascript/rhino/Node;
     158: aload         5
     160: invokevirtual #62                 // Method com/google/javascript/rhino/Node.cloneTree:()Lcom/google/javascript/rhino/Node;
     163: aload         6
     165: invokevirtual #62                 // Method com/google/javascript/rhino/Node.cloneTree:()Lcom/google/javascript/rhino/Node;
     168: invokestatic  #204                // Method com/google/javascript/rhino/IR.getelem:(Lcom/google/javascript/rhino/Node;Lcom/google/javascript/rhino/Node;)Lcom/google/javascript/rhino/Node;
     171: invokestatic  #50                 // Method com/google/javascript/rhino/IR.var:(Lcom/google/javascript/rhino/Node;Lcom/google/javascript/rhino/Node;)Lcom/google/javascript/rhino/Node;
     174: invokevirtual #166                // Method com/google/javascript/rhino/Node.addChildToFront:(Lcom/google/javascript/rhino/Node;)V
     177: aload_0
     178: getfield      #120                // Field hoistRoot:Lcom/google/javascript/rhino/Node;
     181: invokevirtual #25                 // Method com/google/javascript/rhino/Node.getParent:()Lcom/google/javascript/rhino/Node;
     184: aload         5
     186: invokevirtual #62                 // Method com/google/javascript/rhino/Node.cloneTree:()Lcom/google/javascript/rhino/Node;
     189: invokestatic  #52                 // Method com/google/javascript/rhino/IR.var:(Lcom/google/javascript/rhino/Node;)Lcom/google/javascript/rhino/Node;
     192: aload_0
     193: getfield      #120                // Field hoistRoot:Lcom/google/javascript/rhino/Node;
     196: invokevirtual #40                 // Method com/google/javascript/rhino/Node.addChildAfter:(Lcom/google/javascript/rhino/Node;Lcom/google/javascript/rhino/Node;)V
     199: aload_0
     200: getfield      #120                // Field hoistRoot:Lcom/google/javascript/rhino/Node;
     203: invokevirtual #25                 // Method com/google/javascript/rhino/Node.getParent:()Lcom/google/javascript/rhino/Node;
     206: aload         6
     208: invokevirtual #62                 // Method com/google/javascript/rhino/Node.cloneTree:()Lcom/google/javascript/rhino/Node;
     211: invokestatic  #52                 // Method com/google/javascript/rhino/IR.var:(Lcom/google/javascript/rhino/Node;)Lcom/google/javascript/rhino/Node;
     214: aload_0
     215: getfield      #120                // Field hoistRoot:Lcom/google/javascript/rhino/Node;
     218: invokevirtual #40                 // Method com/google/javascript/rhino/Node.addChildAfter:(Lcom/google/javascript/rhino/Node;Lcom/google/javascript/rhino/Node;)V
     221: aload_0
     222: getfield      #120                // Field hoistRoot:Lcom/google/javascript/rhino/Node;
     225: invokevirtual #25                 // Method com/google/javascript/rhino/Node.getParent:()Lcom/google/javascript/rhino/Node;
     228: aload         7
     230: invokevirtual #62                 // Method com/google/javascript/rhino/Node.cloneTree:()Lcom/google/javascript/rhino/Node;
     233: invokestatic  #52                 // Method com/google/javascript/rhino/IR.var:(Lcom/google/javascript/rhino/Node;)Lcom/google/javascript/rhino/Node;
     236: aload_0
     237: getfield      #120                // Field hoistRoot:Lcom/google/javascript/rhino/Node;
     240: invokevirtual #40                 // Method com/google/javascript/rhino/Node.addChildAfter:(Lcom/google/javascript/rhino/Node;Lcom/google/javascript/rhino/Node;)V
     243: aload         5
     245: invokevirtual #62                 // Method com/google/javascript/rhino/Node.cloneTree:()Lcom/google/javascript/rhino/Node;
     248: iconst_0
     249: anewarray     #47                 // class com/google/javascript/rhino/Node
     252: invokestatic  #205                // Method com/google/javascript/rhino/IR.arraylit:([Lcom/google/javascript/rhino/Node;)Lcom/google/javascript/rhino/Node;
     255: invokestatic  #58                 // Method com/google/javascript/rhino/IR.assign:(Lcom/google/javascript/rhino/Node;Lcom/google/javascript/rhino/Node;)Lcom/google/javascript/rhino/Node;
     258: invokestatic  #64                 // Method com/google/javascript/rhino/IR.exprResult:(Lcom/google/javascript/rhino/Node;)Lcom/google/javascript/rhino/Node;
     261: astore        8
     263: aload         7
     265: invokevirtual #62                 // Method com/google/javascript/rhino/Node.cloneTree:()Lcom/google/javascript/rhino/Node;
     268: aload_2
     269: invokestatic  #58                 // Method com/google/javascript/rhino/IR.assign:(Lcom/google/javascript/rhino/Node;Lcom/google/javascript/rhino/Node;)Lcom/google/javascript/rhino/Node;
     272: invokestatic  #64                 // Method com/google/javascript/rhino/IR.exprResult:(Lcom/google/javascript/rhino/Node;)Lcom/google/javascript/rhino/Node;
     275: astore        9
     277: aload_1
     278: invokevirtual #62                 // Method com/google/javascript/rhino/Node.cloneTree:()Lcom/google/javascript/rhino/Node;
     281: aload         7
     283: aload         5
     285: invokevirtual #62                 // Method com/google/javascript/rhino/Node.cloneTree:()Lcom/google/javascript/rhino/Node;
     288: ldc           #206                // String push
     290: invokestatic  #55                 // Method com/google/javascript/rhino/IR.string:(Ljava/lang/String;)Lcom/google/javascript/rhino/Node;
     293: invokestatic  #56                 // Method com/google/javascript/rhino/IR.getprop:(Lcom/google/javascript/rhino/Node;Lcom/google/javascript/rhino/Node;)Lcom/google/javascript/rhino/Node;
     296: iconst_1
     297: anewarray     #47                 // class com/google/javascript/rhino/Node
     300: dup
     301: iconst_0
     302: aload_1
     303: aastore
     304: invokestatic  #49                 // Method com/google/javascript/rhino/IR.call:(Lcom/google/javascript/rhino/Node;[Lcom/google/javascript/rhino/Node;)Lcom/google/javascript/rhino/Node;
     307: invokestatic  #64                 // Method com/google/javascript/rhino/IR.exprResult:(Lcom/google/javascript/rhino/Node;)Lcom/google/javascript/rhino/Node;
     310: invokestatic  #38                 // Method com/google/javascript/rhino/IR.block:(Lcom/google/javascript/rhino/Node;)Lcom/google/javascript/rhino/Node;
     313: invokestatic  #207                // Method com/google/javascript/rhino/IR.forIn:(Lcom/google/javascript/rhino/Node;Lcom/google/javascript/rhino/Node;Lcom/google/javascript/rhino/Node;)Lcom/google/javascript/rhino/Node;
     316: astore        10
     318: aload         6
     320: invokevirtual #62                 // Method com/google/javascript/rhino/Node.cloneTree:()Lcom/google/javascript/rhino/Node;
     323: dconst_0
     324: invokestatic  #115                // Method com/google/javascript/rhino/IR.number:(D)Lcom/google/javascript/rhino/Node;
     327: invokestatic  #58                 // Method com/google/javascript/rhino/IR.assign:(Lcom/google/javascript/rhino/Node;Lcom/google/javascript/rhino/Node;)Lcom/google/javascript/rhino/Node;
     330: aload         6
     332: invokevirtual #62                 // Method com/google/javascript/rhino/Node.cloneTree:()Lcom/google/javascript/rhino/Node;
     335: aload         5
     337: ldc           #208                // String length
     339: invokestatic  #55                 // Method com/google/javascript/rhino/IR.string:(Ljava/lang/String;)Lcom/google/javascript/rhino/Node;
     342: invokestatic  #56                 // Method com/google/javascript/rhino/IR.getprop:(Lcom/google/javascript/rhino/Node;Lcom/google/javascript/rhino/Node;)Lcom/google/javascript/rhino/Node;
     345: invokestatic  #209                // Method com/google/javascript/rhino/IR.lt:(Lcom/google/javascript/rhino/Node;Lcom/google/javascript/rhino/Node;)Lcom/google/javascript/rhino/Node;
     348: aload         6
     350: iconst_1
     351: invokestatic  #210                // Method com/google/javascript/rhino/IR.inc:(Lcom/google/javascript/rhino/Node;Z)Lcom/google/javascript/rhino/Node;
     354: aload_3
     355: invokestatic  #211                // Method com/google/javascript/rhino/IR.forNode:(Lcom/google/javascript/rhino/Node;Lcom/google/javascript/rhino/Node;Lcom/google/javascript/rhino/Node;Lcom/google/javascript/rhino/Node;)Lcom/google/javascript/rhino/Node;
     358: astore        11
     360: aload_0
     361: getfield      #119                // Field enclosingBlock:Lcom/google/javascript/rhino/Node;
     364: aload         8
     366: invokevirtual #116                // Method com/google/javascript/rhino/Node.addChildToBack:(Lcom/google/javascript/rhino/Node;)V
     369: aload_0
     370: getfield      #119                // Field enclosingBlock:Lcom/google/javascript/rhino/Node;
     373: aload         9
     375: invokevirtual #116                // Method com/google/javascript/rhino/Node.addChildToBack:(Lcom/google/javascript/rhino/Node;)V
     378: aload_0
     379: getfield      #119                // Field enclosingBlock:Lcom/google/javascript/rhino/Node;
     382: aload         10
     384: invokevirtual #116                // Method com/google/javascript/rhino/Node.addChildToBack:(Lcom/google/javascript/rhino/Node;)V
     387: aload_0
     388: getfield      #101                // Field originalGeneratorBody:Lcom/google/javascript/rhino/Node;
     391: aload         11
     393: invokevirtual #166                // Method com/google/javascript/rhino/Node.addChildToFront:(Lcom/google/javascript/rhino/Node;)V
     396: return

  private void visitLoop(java.lang.String);
    Code:
       0: aload_0
       1: getfield      #3                  // Field currentStatement:Lcom/google/javascript/rhino/Node;
       4: invokevirtual #212                // Method com/google/javascript/rhino/Node.isWhile:()Z
       7: ifeq          39
      10: aload_0
      11: getfield      #3                  // Field currentStatement:Lcom/google/javascript/rhino/Node;
      14: invokevirtual #48                 // Method com/google/javascript/rhino/Node.removeFirstChild:()Lcom/google/javascript/rhino/Node;
      17: astore_3
      18: aload_0
      19: getfield      #3                  // Field currentStatement:Lcom/google/javascript/rhino/Node;
      22: invokevirtual #48                 // Method com/google/javascript/rhino/Node.removeFirstChild:()Lcom/google/javascript/rhino/Node;
      25: astore        5
      27: invokestatic  #213                // Method com/google/javascript/rhino/IR.empty:()Lcom/google/javascript/rhino/Node;
      30: astore_2
      31: invokestatic  #213                // Method com/google/javascript/rhino/IR.empty:()Lcom/google/javascript/rhino/Node;
      34: astore        4
      36: goto          142
      39: aload_0
      40: getfield      #3                  // Field currentStatement:Lcom/google/javascript/rhino/Node;
      43: invokevirtual #214                // Method com/google/javascript/rhino/Node.isFor:()Z
      46: ifeq          98
      49: aload_0
      50: getfield      #3                  // Field currentStatement:Lcom/google/javascript/rhino/Node;
      53: invokevirtual #48                 // Method com/google/javascript/rhino/Node.removeFirstChild:()Lcom/google/javascript/rhino/Node;
      56: astore_2
      57: aload_2
      58: invokevirtual #215                // Method com/google/javascript/rhino/Node.isAssign:()Z
      61: ifeq          69
      64: aload_2
      65: invokestatic  #64                 // Method com/google/javascript/rhino/IR.exprResult:(Lcom/google/javascript/rhino/Node;)Lcom/google/javascript/rhino/Node;
      68: astore_2
      69: aload_0
      70: getfield      #3                  // Field currentStatement:Lcom/google/javascript/rhino/Node;
      73: invokevirtual #48                 // Method com/google/javascript/rhino/Node.removeFirstChild:()Lcom/google/javascript/rhino/Node;
      76: astore_3
      77: aload_0
      78: getfield      #3                  // Field currentStatement:Lcom/google/javascript/rhino/Node;
      81: invokevirtual #48                 // Method com/google/javascript/rhino/Node.removeFirstChild:()Lcom/google/javascript/rhino/Node;
      84: astore        4
      86: aload_0
      87: getfield      #3                  // Field currentStatement:Lcom/google/javascript/rhino/Node;
      90: invokevirtual #48                 // Method com/google/javascript/rhino/Node.removeFirstChild:()Lcom/google/javascript/rhino/Node;
      93: astore        5
      95: goto          142
      98: aload_0
      99: getfield      #3                  // Field currentStatement:Lcom/google/javascript/rhino/Node;
     102: invokevirtual #216                // Method com/google/javascript/rhino/Node.isDo:()Z
     105: invokestatic  #179                // Method com/google/common/base/Preconditions.checkState:(Z)V
     108: invokestatic  #213                // Method com/google/javascript/rhino/IR.empty:()Lcom/google/javascript/rhino/Node;
     111: astore_2
     112: ldc           #217                // String $jscomp$generator$first$do
     114: invokestatic  #27                 // Method com/google/javascript/rhino/IR.name:(Ljava/lang/String;)Lcom/google/javascript/rhino/Node;
     117: invokestatic  #190                // Method com/google/javascript/rhino/IR.falseNode:()Lcom/google/javascript/rhino/Node;
     120: invokestatic  #58                 // Method com/google/javascript/rhino/IR.assign:(Lcom/google/javascript/rhino/Node;Lcom/google/javascript/rhino/Node;)Lcom/google/javascript/rhino/Node;
     123: astore        4
     125: aload_0
     126: getfield      #3                  // Field currentStatement:Lcom/google/javascript/rhino/Node;
     129: invokevirtual #48                 // Method com/google/javascript/rhino/Node.removeFirstChild:()Lcom/google/javascript/rhino/Node;
     132: astore        5
     134: aload_0
     135: getfield      #3                  // Field currentStatement:Lcom/google/javascript/rhino/Node;
     138: invokevirtual #48                 // Method com/google/javascript/rhino/Node.removeFirstChild:()Lcom/google/javascript/rhino/Node;
     141: astore_3
     142: aload_3
     143: invokevirtual #140                // Method com/google/javascript/rhino/Node.isBlock:()Z
     146: ifeq          164
     149: aload_3
     150: invokevirtual #48                 // Method com/google/javascript/rhino/Node.removeFirstChild:()Lcom/google/javascript/rhino/Node;
     153: astore        7
     155: aload_3
     156: invokevirtual #48                 // Method com/google/javascript/rhino/Node.removeFirstChild:()Lcom/google/javascript/rhino/Node;
     159: astore        6
     161: goto          172
     164: invokestatic  #126                // Method com/google/javascript/rhino/IR.block:()Lcom/google/javascript/rhino/Node;
     167: astore        7
     169: aload_3
     170: astore        6
     172: getstatic     #17                 // Field generatorCaseCount:I
     175: dup
     176: iconst_1
     177: iadd
     178: putstatic     #17                 // Field generatorCaseCount:I
     181: istore        8
     183: iload         8
     185: istore        9
     187: aload         4
     189: invokevirtual #218                // Method com/google/javascript/rhino/Node.isEmpty:()Z
     192: ifne          250
     195: getstatic     #17                 // Field generatorCaseCount:I
     198: dup
     199: iconst_1
     200: iadd
     201: putstatic     #17                 // Field generatorCaseCount:I
     204: istore        9
     206: iload         9
     208: i2d
     209: invokestatic  #115                // Method com/google/javascript/rhino/IR.number:(D)Lcom/google/javascript/rhino/Node;
     212: astore        10
     214: aload         10
     216: iconst_1
     217: invokevirtual #163                // Method com/google/javascript/rhino/Node.setGeneratorMarker:(Z)V
     220: aload         5
     222: aload         10
     224: invokevirtual #116                // Method com/google/javascript/rhino/Node.addChildToBack:(Lcom/google/javascript/rhino/Node;)V
     227: aload         5
     229: aload         4
     231: invokevirtual #140                // Method com/google/javascript/rhino/Node.isBlock:()Z
     234: ifeq          242
     237: aload         4
     239: goto          247
     242: aload         4
     244: invokestatic  #64                 // Method com/google/javascript/rhino/IR.exprResult:(Lcom/google/javascript/rhino/Node;)Lcom/google/javascript/rhino/Node;
     247: invokevirtual #116                // Method com/google/javascript/rhino/Node.addChildToBack:(Lcom/google/javascript/rhino/Node;)V
     250: aload_0
     251: getfield      #9                  // Field currentLoopContext:Ljava/util/List;
     254: iconst_0
     255: new           #177                // class com/google/javascript/jscomp/Es6RewriteGenerators$LoopContext
     258: dup
     259: aload_0
     260: getstatic     #17                 // Field generatorCaseCount:I
     263: iload         9
     265: aload_1
     266: invokespecial #197                // Method com/google/javascript/jscomp/Es6RewriteGenerators$LoopContext."<init>":(Lcom/google/javascript/jscomp/Es6RewriteGenerators;IILjava/lang/String;)V
     269: invokeinterface #173,  3          // InterfaceMethod java/util/List.add:(ILjava/lang/Object;)V
     274: iload         8
     276: i2d
     277: invokestatic  #115                // Method com/google/javascript/rhino/IR.number:(D)Lcom/google/javascript/rhino/Node;
     280: astore        10
     282: aload         10
     284: iconst_1
     285: invokevirtual #163                // Method com/google/javascript/rhino/Node.setGeneratorMarker:(Z)V
     288: aload         6
     290: invokevirtual #218                // Method com/google/javascript/rhino/Node.isEmpty:()Z
     293: ifeq          302
     296: invokestatic  #192                // Method com/google/javascript/rhino/IR.trueNode:()Lcom/google/javascript/rhino/Node;
     299: goto          304
     302: aload         6
     304: aload         5
     306: invokestatic  #39                 // Method com/google/javascript/rhino/IR.ifNode:(Lcom/google/javascript/rhino/Node;Lcom/google/javascript/rhino/Node;)Lcom/google/javascript/rhino/Node;
     309: astore        11
     311: iload         8
     313: invokestatic  #168                // Method createStateUpdate:(I)Lcom/google/javascript/rhino/Node;
     316: astore        12
     318: invokestatic  #169                // Method createSafeBreak:()Lcom/google/javascript/rhino/Node;
     321: astore        13
     323: aload_0
     324: getfield      #101                // Field originalGeneratorBody:Lcom/google/javascript/rhino/Node;
     327: aload         11
     329: invokevirtual #166                // Method com/google/javascript/rhino/Node.addChildToFront:(Lcom/google/javascript/rhino/Node;)V
     332: aload         7
     334: invokevirtual #218                // Method com/google/javascript/rhino/Node.isEmpty:()Z
     337: ifne          349
     340: aload_0
     341: getfield      #101                // Field originalGeneratorBody:Lcom/google/javascript/rhino/Node;
     344: aload         7
     346: invokevirtual #166                // Method com/google/javascript/rhino/Node.addChildToFront:(Lcom/google/javascript/rhino/Node;)V
     349: aload_0
     350: getfield      #101                // Field originalGeneratorBody:Lcom/google/javascript/rhino/Node;
     353: aload         10
     355: invokevirtual #166                // Method com/google/javascript/rhino/Node.addChildToFront:(Lcom/google/javascript/rhino/Node;)V
     358: aload_2
     359: invokevirtual #218                // Method com/google/javascript/rhino/Node.isEmpty:()Z
     362: ifne          373
     365: aload_0
     366: getfield      #101                // Field originalGeneratorBody:Lcom/google/javascript/rhino/Node;
     369: aload_2
     370: invokevirtual #166                // Method com/google/javascript/rhino/Node.addChildToFront:(Lcom/google/javascript/rhino/Node;)V
     373: aload         5
     375: aload         12
     377: invokevirtual #116                // Method com/google/javascript/rhino/Node.addChildToBack:(Lcom/google/javascript/rhino/Node;)V
     380: aload         5
     382: aload         13
     384: invokevirtual #116                // Method com/google/javascript/rhino/Node.addChildToBack:(Lcom/google/javascript/rhino/Node;)V
     387: return

  private void visitVar();
    Code:
       0: aload_0
       1: getfield      #3                  // Field currentStatement:Lcom/google/javascript/rhino/Node;
       4: invokevirtual #48                 // Method com/google/javascript/rhino/Node.removeFirstChild:()Lcom/google/javascript/rhino/Node;
       7: astore_1
       8: aload_1
       9: ifnull        69
      12: aload_1
      13: invokevirtual #68                 // Method com/google/javascript/rhino/Node.hasChildren:()Z
      16: ifeq          37
      19: aload_0
      20: getfield      #119                // Field enclosingBlock:Lcom/google/javascript/rhino/Node;
      23: aload_1
      24: aload_1
      25: invokevirtual #48                 // Method com/google/javascript/rhino/Node.removeFirstChild:()Lcom/google/javascript/rhino/Node;
      28: invokestatic  #58                 // Method com/google/javascript/rhino/IR.assign:(Lcom/google/javascript/rhino/Node;Lcom/google/javascript/rhino/Node;)Lcom/google/javascript/rhino/Node;
      31: invokestatic  #64                 // Method com/google/javascript/rhino/IR.exprResult:(Lcom/google/javascript/rhino/Node;)Lcom/google/javascript/rhino/Node;
      34: invokevirtual #116                // Method com/google/javascript/rhino/Node.addChildToBack:(Lcom/google/javascript/rhino/Node;)V
      37: aload_0
      38: getfield      #120                // Field hoistRoot:Lcom/google/javascript/rhino/Node;
      41: invokevirtual #25                 // Method com/google/javascript/rhino/Node.getParent:()Lcom/google/javascript/rhino/Node;
      44: aload_1
      45: invokevirtual #62                 // Method com/google/javascript/rhino/Node.cloneTree:()Lcom/google/javascript/rhino/Node;
      48: invokestatic  #52                 // Method com/google/javascript/rhino/IR.var:(Lcom/google/javascript/rhino/Node;)Lcom/google/javascript/rhino/Node;
      51: aload_0
      52: getfield      #120                // Field hoistRoot:Lcom/google/javascript/rhino/Node;
      55: invokevirtual #40                 // Method com/google/javascript/rhino/Node.addChildAfter:(Lcom/google/javascript/rhino/Node;Lcom/google/javascript/rhino/Node;)V
      58: aload_0
      59: getfield      #3                  // Field currentStatement:Lcom/google/javascript/rhino/Node;
      62: invokevirtual #48                 // Method com/google/javascript/rhino/Node.removeFirstChild:()Lcom/google/javascript/rhino/Node;
      65: astore_1
      66: goto          8
      69: return

  private void visitYieldExprResult();
    Code:
       0: aload_0
       1: getfield      #119                // Field enclosingBlock:Lcom/google/javascript/rhino/Node;
       4: invokestatic  #219                // Method createStateUpdate:()Lcom/google/javascript/rhino/Node;
       7: invokevirtual #116                // Method com/google/javascript/rhino/Node.addChildToBack:(Lcom/google/javascript/rhino/Node;)V
      10: aload_0
      11: getfield      #3                  // Field currentStatement:Lcom/google/javascript/rhino/Node;
      14: invokevirtual #99                 // Method com/google/javascript/rhino/Node.getFirstChild:()Lcom/google/javascript/rhino/Node;
      17: astore_1
      18: aload_1
      19: invokevirtual #68                 // Method com/google/javascript/rhino/Node.hasChildren:()Z
      22: ifeq          32
      25: aload_1
      26: invokevirtual #48                 // Method com/google/javascript/rhino/Node.removeFirstChild:()Lcom/google/javascript/rhino/Node;
      29: goto          37
      32: ldc           #35                 // String undefined
      34: invokestatic  #27                 // Method com/google/javascript/rhino/IR.name:(Ljava/lang/String;)Lcom/google/javascript/rhino/Node;
      37: astore_2
      38: aload_0
      39: getfield      #119                // Field enclosingBlock:Lcom/google/javascript/rhino/Node;
      42: aload_2
      43: iconst_0
      44: invokestatic  #220                // Method createIteratorResult:(Lcom/google/javascript/rhino/Node;Z)Lcom/google/javascript/rhino/Node;
      47: invokestatic  #221                // Method com/google/javascript/rhino/IR.returnNode:(Lcom/google/javascript/rhino/Node;)Lcom/google/javascript/rhino/Node;
      50: invokevirtual #116                // Method com/google/javascript/rhino/Node.addChildToBack:(Lcom/google/javascript/rhino/Node;)V
      53: return

  private void visitReturn();
    Code:
       0: aload_0
       1: getfield      #119                // Field enclosingBlock:Lcom/google/javascript/rhino/Node;
       4: iconst_m1
       5: invokestatic  #168                // Method createStateUpdate:(I)Lcom/google/javascript/rhino/Node;
       8: invokevirtual #116                // Method com/google/javascript/rhino/Node.addChildToBack:(Lcom/google/javascript/rhino/Node;)V
      11: aload_0
      12: getfield      #119                // Field enclosingBlock:Lcom/google/javascript/rhino/Node;
      15: aload_0
      16: getfield      #3                  // Field currentStatement:Lcom/google/javascript/rhino/Node;
      19: invokevirtual #68                 // Method com/google/javascript/rhino/Node.hasChildren:()Z
      22: ifeq          35
      25: aload_0
      26: getfield      #3                  // Field currentStatement:Lcom/google/javascript/rhino/Node;
      29: invokevirtual #48                 // Method com/google/javascript/rhino/Node.removeFirstChild:()Lcom/google/javascript/rhino/Node;
      32: goto          40
      35: ldc           #35                 // String undefined
      37: invokestatic  #27                 // Method com/google/javascript/rhino/IR.name:(Ljava/lang/String;)Lcom/google/javascript/rhino/Node;
      40: iconst_1
      41: invokestatic  #220                // Method createIteratorResult:(Lcom/google/javascript/rhino/Node;Z)Lcom/google/javascript/rhino/Node;
      44: invokestatic  #221                // Method com/google/javascript/rhino/IR.returnNode:(Lcom/google/javascript/rhino/Node;)Lcom/google/javascript/rhino/Node;
      47: invokevirtual #116                // Method com/google/javascript/rhino/Node.addChildToBack:(Lcom/google/javascript/rhino/Node;)V
      50: return

  private static com.google.javascript.rhino.Node createStateUpdate();
    Code:
       0: ldc           #112                // String $jscomp$generator$state
       2: invokestatic  #27                 // Method com/google/javascript/rhino/IR.name:(Ljava/lang/String;)Lcom/google/javascript/rhino/Node;
       5: getstatic     #17                 // Field generatorCaseCount:I
       8: i2d
       9: invokestatic  #115                // Method com/google/javascript/rhino/IR.number:(D)Lcom/google/javascript/rhino/Node;
      12: invokestatic  #58                 // Method com/google/javascript/rhino/IR.assign:(Lcom/google/javascript/rhino/Node;Lcom/google/javascript/rhino/Node;)Lcom/google/javascript/rhino/Node;
      15: invokestatic  #64                 // Method com/google/javascript/rhino/IR.exprResult:(Lcom/google/javascript/rhino/Node;)Lcom/google/javascript/rhino/Node;
      18: areturn

  private static com.google.javascript.rhino.Node createStateUpdate(int);
    Code:
       0: ldc           #112                // String $jscomp$generator$state
       2: invokestatic  #27                 // Method com/google/javascript/rhino/IR.name:(Ljava/lang/String;)Lcom/google/javascript/rhino/Node;
       5: iload_0
       6: i2d
       7: invokestatic  #115                // Method com/google/javascript/rhino/IR.number:(D)Lcom/google/javascript/rhino/Node;
      10: invokestatic  #58                 // Method com/google/javascript/rhino/IR.assign:(Lcom/google/javascript/rhino/Node;Lcom/google/javascript/rhino/Node;)Lcom/google/javascript/rhino/Node;
      13: invokestatic  #64                 // Method com/google/javascript/rhino/IR.exprResult:(Lcom/google/javascript/rhino/Node;)Lcom/google/javascript/rhino/Node;
      16: areturn

  private static com.google.javascript.rhino.Node createIteratorResult(com.google.javascript.rhino.Node, boolean);
    Code:
       0: iconst_2
       1: anewarray     #47                 // class com/google/javascript/rhino/Node
       4: dup
       5: iconst_0
       6: ldc           #61                 // String value
       8: invokestatic  #222                // Method com/google/javascript/rhino/IR.stringKey:(Ljava/lang/String;)Lcom/google/javascript/rhino/Node;
      11: aload_0
      12: invokestatic  #223                // Method com/google/javascript/rhino/IR.propdef:(Lcom/google/javascript/rhino/Node;Lcom/google/javascript/rhino/Node;)Lcom/google/javascript/rhino/Node;
      15: aastore
      16: dup
      17: iconst_1
      18: ldc           #59                 // String done
      20: invokestatic  #222                // Method com/google/javascript/rhino/IR.stringKey:(Ljava/lang/String;)Lcom/google/javascript/rhino/Node;
      23: iload_1
      24: ifeq          33
      27: invokestatic  #192                // Method com/google/javascript/rhino/IR.trueNode:()Lcom/google/javascript/rhino/Node;
      30: goto          36
      33: invokestatic  #190                // Method com/google/javascript/rhino/IR.falseNode:()Lcom/google/javascript/rhino/Node;
      36: invokestatic  #223                // Method com/google/javascript/rhino/IR.propdef:(Lcom/google/javascript/rhino/Node;Lcom/google/javascript/rhino/Node;)Lcom/google/javascript/rhino/Node;
      39: aastore
      40: invokestatic  #224                // Method com/google/javascript/rhino/IR.objectlit:([Lcom/google/javascript/rhino/Node;)Lcom/google/javascript/rhino/Node;
      43: areturn

  private static com.google.javascript.rhino.Node createSafeBreak();
    Code:
       0: invokestatic  #225                // Method com/google/javascript/rhino/IR.breakNode:()Lcom/google/javascript/rhino/Node;
       3: astore_0
       4: aload_0
       5: iconst_1
       6: invokevirtual #162                // Method com/google/javascript/rhino/Node.setGeneratorSafe:(Z)V
       9: aload_0
      10: areturn

  private static com.google.javascript.rhino.Node createFinallyJumpBlock(com.google.javascript.rhino.Node, int);
    Code:
       0: getstatic     #17                 // Field generatorCaseCount:I
       3: dup
       4: iconst_1
       5: iadd
       6: putstatic     #17                 // Field generatorCaseCount:I
       9: istore_2
      10: aload_0
      11: invokevirtual #62                 // Method com/google/javascript/rhino/Node.cloneTree:()Lcom/google/javascript/rhino/Node;
      14: iload_2
      15: i2d
      16: invokestatic  #115                // Method com/google/javascript/rhino/IR.number:(D)Lcom/google/javascript/rhino/Node;
      19: invokestatic  #58                 // Method com/google/javascript/rhino/IR.assign:(Lcom/google/javascript/rhino/Node;Lcom/google/javascript/rhino/Node;)Lcom/google/javascript/rhino/Node;
      22: invokestatic  #64                 // Method com/google/javascript/rhino/IR.exprResult:(Lcom/google/javascript/rhino/Node;)Lcom/google/javascript/rhino/Node;
      25: astore_3
      26: iload_1
      27: invokestatic  #168                // Method createStateUpdate:(I)Lcom/google/javascript/rhino/Node;
      30: astore        4
      32: iload_2
      33: i2d
      34: invokestatic  #115                // Method com/google/javascript/rhino/IR.number:(D)Lcom/google/javascript/rhino/Node;
      37: astore        5
      39: aload         5
      41: iconst_1
      42: invokevirtual #163                // Method com/google/javascript/rhino/Node.setGeneratorMarker:(Z)V
      45: iconst_3
      46: anewarray     #47                 // class com/google/javascript/rhino/Node
      49: dup
      50: iconst_0
      51: aload_3
      52: aastore
      53: dup
      54: iconst_1
      55: aload         4
      57: aastore
      58: dup
      59: iconst_2
      60: invokestatic  #169                // Method createSafeBreak:()Lcom/google/javascript/rhino/Node;
      63: aastore
      64: invokestatic  #170                // Method com/google/javascript/rhino/IR.block:([Lcom/google/javascript/rhino/Node;)Lcom/google/javascript/rhino/Node;
      67: astore        6
      69: aload         6
      71: aload         5
      73: invokevirtual #116                // Method com/google/javascript/rhino/Node.addChildToBack:(Lcom/google/javascript/rhino/Node;)V
      76: aload         6
      78: areturn

  private com.google.javascript.jscomp.Es6RewriteGenerators$LoopContext getLoopContext(java.lang.String);
    Code:
       0: iconst_0
       1: istore_2
       2: iload_2
       3: aload_0
       4: getfield      #9                  // Field currentLoopContext:Ljava/util/List;
       7: invokeinterface #226,  1          // InterfaceMethod java/util/List.size:()I
      12: if_icmpge     58
      15: aload_1
      16: aload_0
      17: getfield      #9                  // Field currentLoopContext:Ljava/util/List;
      20: iload_2
      21: invokeinterface #130,  2          // InterfaceMethod java/util/List.get:(I)Ljava/lang/Object;
      26: checkcast     #177                // class com/google/javascript/jscomp/Es6RewriteGenerators$LoopContext
      29: getfield      #227                // Field com/google/javascript/jscomp/Es6RewriteGenerators$LoopContext.label:Ljava/lang/String;
      32: invokevirtual #228                // Method java/lang/String.equals:(Ljava/lang/Object;)Z
      35: ifeq          52
      38: aload_0
      39: getfield      #9                  // Field currentLoopContext:Ljava/util/List;
      42: iload_2
      43: invokeinterface #130,  2          // InterfaceMethod java/util/List.get:(I)Ljava/lang/Object;
      48: checkcast     #177                // class com/google/javascript/jscomp/Es6RewriteGenerators$LoopContext
      51: areturn
      52: iinc          2, 1
      55: goto          2
      58: aconst_null
      59: areturn

  private boolean controlCanExit(com.google.javascript.rhino.Node);
    Code:
       0: new           #175                // class com/google/javascript/jscomp/Es6RewriteGenerators$ControlExitsCheck
       3: dup
       4: aload_0
       5: invokespecial #229                // Method com/google/javascript/jscomp/Es6RewriteGenerators$ControlExitsCheck."<init>":(Lcom/google/javascript/jscomp/Es6RewriteGenerators;)V
       8: astore_2
       9: aload_0
      10: getfield      #6                  // Field compiler:Lcom/google/javascript/jscomp/AbstractCompiler;
      13: aload_1
      14: aload_2
      15: invokestatic  #14                 // Method com/google/javascript/jscomp/NodeTraversal.traverse:(Lcom/google/javascript/jscomp/AbstractCompiler;Lcom/google/javascript/rhino/Node;Lcom/google/javascript/jscomp/NodeTraversal$Callback;)V
      18: aload_2
      19: invokevirtual #230                // Method com/google/javascript/jscomp/Es6RewriteGenerators$ControlExitsCheck.didExit:()Z
      22: ireturn

  private com.google.javascript.rhino.Node getUnique(com.google.javascript.rhino.Node, int);
    Code:
       0: new           #7                  // class java/util/ArrayList
       3: dup
       4: invokespecial #8                  // Method java/util/ArrayList."<init>":()V
       7: astore_3
       8: aload_0
       9: aload_1
      10: iload_2
      11: aload_3
      12: invokespecial #231                // Method insertAll:(Lcom/google/javascript/rhino/Node;ILjava/util/List;)V
      15: aload_3
      16: invokeinterface #226,  1          // InterfaceMethod java/util/List.size:()I
      21: iconst_1
      22: if_icmpne     29
      25: iconst_1
      26: goto          30
      29: iconst_0
      30: invokestatic  #179                // Method com/google/common/base/Preconditions.checkState:(Z)V
      33: aload_3
      34: iconst_0
      35: invokeinterface #130,  2          // InterfaceMethod java/util/List.get:(I)Ljava/lang/Object;
      40: checkcast     #47                 // class com/google/javascript/rhino/Node
      43: areturn

  private void insertAll(com.google.javascript.rhino.Node, int, java.util.List<com.google.javascript.rhino.Node>);
    Code:
       0: aload_1
       1: invokevirtual #15                 // Method com/google/javascript/rhino/Node.getType:()I
       4: iload_2
       5: if_icmpne     16
       8: aload_3
       9: aload_1
      10: invokeinterface #232,  2          // InterfaceMethod java/util/List.add:(Ljava/lang/Object;)Z
      15: pop
      16: aload_1
      17: invokevirtual #99                 // Method com/google/javascript/rhino/Node.getFirstChild:()Lcom/google/javascript/rhino/Node;
      20: astore        4
      22: aload         4
      24: ifnull        45
      27: aload_0
      28: aload         4
      30: iload_2
      31: aload_3
      32: invokespecial #231                // Method insertAll:(Lcom/google/javascript/rhino/Node;ILjava/util/List;)V
      35: aload         4
      37: invokevirtual #160                // Method com/google/javascript/rhino/Node.getNext:()Lcom/google/javascript/rhino/Node;
      40: astore        4
      42: goto          22
      45: return

  static boolean access$000(com.google.javascript.jscomp.Es6RewriteGenerators, com.google.javascript.rhino.Node);
    Code:
       0: aload_0
       1: aload_1
       2: invokespecial #4                  // Method controlCanExit:(Lcom/google/javascript/rhino/Node;)Z
       5: ireturn

  static com.google.javascript.rhino.Node access$100(com.google.javascript.jscomp.Es6RewriteGenerators);
    Code:
       0: aload_0
       1: getfield      #3                  // Field currentStatement:Lcom/google/javascript/rhino/Node;
       4: areturn

  static com.google.common.base.Supplier access$200(com.google.javascript.jscomp.Es6RewriteGenerators);
    Code:
       0: aload_0
       1: getfield      #2                  // Field generatorCounter:Lcom/google/common/base/Supplier;
       4: areturn

  static com.google.javascript.rhino.Node access$300(com.google.javascript.rhino.Node, int);
    Code:
       0: aload_0
       1: iload_1
       2: invokestatic  #1                  // Method createFinallyJumpBlock:(Lcom/google/javascript/rhino/Node;I)Lcom/google/javascript/rhino/Node;
       5: areturn
}
