Compiled from "Es6ToEs3ClassSideInheritance.java"
class com.google.javascript.jscomp.Es6ToEs3ClassSideInheritance$FindCopyProp extends com.google.javascript.jscomp.NodeTraversal$AbstractPreOrderCallback {
  private boolean found;

  final com.google.javascript.jscomp.Es6ToEs3ClassSideInheritance this$0;

  private com.google.javascript.jscomp.Es6ToEs3ClassSideInheritance$FindCopyProp(com.google.javascript.jscomp.Es6ToEs3ClassSideInheritance);
    Code:
       0: aload_0
       1: aload_1
       2: putfield      #3                  // Field this$0:Lcom/google/javascript/jscomp/Es6ToEs3ClassSideInheritance;
       5: aload_0
       6: invokespecial #4                  // Method com/google/javascript/jscomp/NodeTraversal$AbstractPreOrderCallback."<init>":()V
       9: aload_0
      10: iconst_0
      11: putfield      #1                  // Field found:Z
      14: return

  public boolean shouldTraverse(com.google.javascript.jscomp.NodeTraversal, com.google.javascript.rhino.Node, com.google.javascript.rhino.Node);
    Code:
       0: aload_0
       1: getfield      #1                  // Field found:Z
       4: ifne          26
       7: aload_2
       8: invokevirtual #5                  // Method com/google/javascript/rhino/Node.isCall:()Z
      11: ifeq          33
      14: aload_2
      15: invokevirtual #6                  // Method com/google/javascript/rhino/Node.getFirstChild:()Lcom/google/javascript/rhino/Node;
      18: ldc           #8                  // String $jscomp.copyProperties
      20: invokevirtual #9                  // Method com/google/javascript/rhino/Node.matchesQualifiedName:(Ljava/lang/String;)Z
      23: ifeq          33
      26: aload_0
      27: iconst_1
      28: putfield      #1                  // Field found:Z
      31: iconst_0
      32: ireturn
      33: iconst_1
      34: ireturn

  com.google.javascript.jscomp.Es6ToEs3ClassSideInheritance$FindCopyProp(com.google.javascript.jscomp.Es6ToEs3ClassSideInheritance, com.google.javascript.jscomp.Es6ToEs3ClassSideInheritance$1);
    Code:
       0: aload_0
       1: aload_1
       2: invokespecial #2                  // Method "<init>":(Lcom/google/javascript/jscomp/Es6ToEs3ClassSideInheritance;)V
       5: return

  static boolean access$100(com.google.javascript.jscomp.Es6ToEs3ClassSideInheritance$FindCopyProp);
    Code:
       0: aload_0
       1: getfield      #1                  // Field found:Z
       4: ireturn
}
