Compiled from "ExportTestFunctions.java"
class com.google.javascript.jscomp.ExportTestFunctions$ExportTestFunctionsNodes extends com.google.javascript.jscomp.NodeTraversal$AbstractShallowCallback {
  final com.google.javascript.jscomp.ExportTestFunctions this$0;

  private com.google.javascript.jscomp.ExportTestFunctions$ExportTestFunctionsNodes(com.google.javascript.jscomp.ExportTestFunctions);
    Code:
       0: aload_0
       1: aload_1
       2: putfield      #2                  // Field this$0:Lcom/google/javascript/jscomp/ExportTestFunctions;
       5: aload_0
       6: invokespecial #3                  // Method com/google/javascript/jscomp/NodeTraversal$AbstractShallowCallback."<init>":()V
       9: return

  public void visit(com.google.javascript.jscomp.NodeTraversal, com.google.javascript.rhino.Node, com.google.javascript.rhino.Node);
    Code:
       0: aload_3
       1: ifnonnull     5
       4: return
       5: aload_3
       6: invokevirtual #4                  // Method com/google/javascript/rhino/Node.isScript:()Z
       9: ifeq          93
      12: aload_2
      13: invokestatic  #5                  // Method com/google/javascript/jscomp/NodeUtil.isFunctionDeclaration:(Lcom/google/javascript/rhino/Node;)Z
      16: ifeq          47
      19: aload_2
      20: invokestatic  #6                  // Method com/google/javascript/jscomp/NodeUtil.getFunctionName:(Lcom/google/javascript/rhino/Node;)Ljava/lang/String;
      23: astore        4
      25: aload         4
      27: invokestatic  #7                  // Method com/google/javascript/jscomp/ExportTestFunctions.access$000:(Ljava/lang/String;)Z
      30: ifeq          44
      33: aload_0
      34: getfield      #2                  // Field this$0:Lcom/google/javascript/jscomp/ExportTestFunctions;
      37: aload         4
      39: aload_2
      40: aload_3
      41: invokestatic  #8                  // Method com/google/javascript/jscomp/ExportTestFunctions.access$100:(Lcom/google/javascript/jscomp/ExportTestFunctions;Ljava/lang/String;Lcom/google/javascript/rhino/Node;Lcom/google/javascript/rhino/Node;)V
      44: goto          159
      47: aload_0
      48: aload_2
      49: invokespecial #9                  // Method isVarDeclaredFunction:(Lcom/google/javascript/rhino/Node;)Z
      52: ifeq          159
      55: aload_2
      56: invokevirtual #10                 // Method com/google/javascript/rhino/Node.getFirstChild:()Lcom/google/javascript/rhino/Node;
      59: invokevirtual #10                 // Method com/google/javascript/rhino/Node.getFirstChild:()Lcom/google/javascript/rhino/Node;
      62: astore        4
      64: aload         4
      66: invokestatic  #6                  // Method com/google/javascript/jscomp/NodeUtil.getFunctionName:(Lcom/google/javascript/rhino/Node;)Ljava/lang/String;
      69: astore        5
      71: aload         5
      73: invokestatic  #7                  // Method com/google/javascript/jscomp/ExportTestFunctions.access$000:(Ljava/lang/String;)Z
      76: ifeq          90
      79: aload_0
      80: getfield      #2                  // Field this$0:Lcom/google/javascript/jscomp/ExportTestFunctions;
      83: aload         5
      85: aload_2
      86: aload_3
      87: invokestatic  #8                  // Method com/google/javascript/jscomp/ExportTestFunctions.access$100:(Lcom/google/javascript/jscomp/ExportTestFunctions;Ljava/lang/String;Lcom/google/javascript/rhino/Node;Lcom/google/javascript/rhino/Node;)V
      90: goto          159
      93: aload_3
      94: invokestatic  #11                 // Method com/google/javascript/jscomp/NodeUtil.isExprAssign:(Lcom/google/javascript/rhino/Node;)Z
      97: ifeq          159
     100: aload_2
     101: invokevirtual #12                 // Method com/google/javascript/rhino/Node.getLastChild:()Lcom/google/javascript/rhino/Node;
     104: invokevirtual #13                 // Method com/google/javascript/rhino/Node.isAssign:()Z
     107: ifne          159
     110: aload_3
     111: invokevirtual #14                 // Method com/google/javascript/rhino/Node.getParent:()Lcom/google/javascript/rhino/Node;
     114: astore        4
     116: aload         4
     118: ifnull        159
     121: aload         4
     123: invokevirtual #4                  // Method com/google/javascript/rhino/Node.isScript:()Z
     126: ifeq          159
     129: aload_2
     130: invokevirtual #10                 // Method com/google/javascript/rhino/Node.getFirstChild:()Lcom/google/javascript/rhino/Node;
     133: invokevirtual #15                 // Method com/google/javascript/rhino/Node.getQualifiedName:()Ljava/lang/String;
     136: astore        5
     138: aload         5
     140: invokestatic  #7                  // Method com/google/javascript/jscomp/ExportTestFunctions.access$000:(Ljava/lang/String;)Z
     143: ifeq          159
     146: aload_0
     147: getfield      #2                  // Field this$0:Lcom/google/javascript/jscomp/ExportTestFunctions;
     150: aload         5
     152: aload_3
     153: aload_2
     154: aload         4
     156: invokestatic  #16                 // Method com/google/javascript/jscomp/ExportTestFunctions.access$200:(Lcom/google/javascript/jscomp/ExportTestFunctions;Ljava/lang/String;Lcom/google/javascript/rhino/Node;Lcom/google/javascript/rhino/Node;Lcom/google/javascript/rhino/Node;)V
     159: return

  private boolean isVarDeclaredFunction(com.google.javascript.rhino.Node);
    Code:
       0: aload_1
       1: invokevirtual #17                 // Method com/google/javascript/rhino/Node.isVar:()Z
       4: ifne          9
       7: iconst_0
       8: ireturn
       9: aload_1
      10: invokevirtual #10                 // Method com/google/javascript/rhino/Node.getFirstChild:()Lcom/google/javascript/rhino/Node;
      13: invokevirtual #10                 // Method com/google/javascript/rhino/Node.getFirstChild:()Lcom/google/javascript/rhino/Node;
      16: astore_2
      17: aload_2
      18: ifnull        32
      21: aload_2
      22: invokevirtual #18                 // Method com/google/javascript/rhino/Node.isFunction:()Z
      25: ifeq          32
      28: iconst_1
      29: goto          33
      32: iconst_0
      33: ireturn

  com.google.javascript.jscomp.ExportTestFunctions$ExportTestFunctionsNodes(com.google.javascript.jscomp.ExportTestFunctions, com.google.javascript.jscomp.ExportTestFunctions$1);
    Code:
       0: aload_0
       1: aload_1
       2: invokespecial #1                  // Method "<init>":(Lcom/google/javascript/jscomp/ExportTestFunctions;)V
       5: return
}
