Compiled from "FlowSensitiveInlineVariables.java"
class com.google.javascript.jscomp.FlowSensitiveInlineVariables$Candidate {
  private final java.lang.String varName;

  private com.google.javascript.rhino.Node def;

  private final com.google.javascript.jscomp.MustBeReachingVariableDef$Definition defMetadata;

  private final com.google.javascript.rhino.Node use;

  private final com.google.javascript.rhino.Node useCfgNode;

  private int numUsesWithinCfgNode;

  final com.google.javascript.jscomp.FlowSensitiveInlineVariables this$0;

  com.google.javascript.jscomp.FlowSensitiveInlineVariables$Candidate(com.google.javascript.jscomp.FlowSensitiveInlineVariables, java.lang.String, com.google.javascript.jscomp.MustBeReachingVariableDef$Definition, com.google.javascript.rhino.Node, com.google.javascript.rhino.Node);
    Code:
       0: aload_0
       1: aload_1
       2: putfield      #7                  // Field this$0:Lcom/google/javascript/jscomp/FlowSensitiveInlineVariables;
       5: aload_0
       6: invokespecial #8                  // Method java/lang/Object."<init>":()V
       9: aload         4
      11: invokevirtual #9                  // Method com/google/javascript/rhino/Node.isName:()Z
      14: invokestatic  #10                 // Method com/google/common/base/Preconditions.checkArgument:(Z)V
      17: aload_0
      18: aload_2
      19: putfield      #3                  // Field varName:Ljava/lang/String;
      22: aload_0
      23: aload_3
      24: putfield      #4                  // Field defMetadata:Lcom/google/javascript/jscomp/MustBeReachingVariableDef$Definition;
      27: aload_0
      28: aload         4
      30: putfield      #11                 // Field use:Lcom/google/javascript/rhino/Node;
      33: aload_0
      34: aload         5
      36: putfield      #12                 // Field useCfgNode:Lcom/google/javascript/rhino/Node;
      39: return

  private com.google.javascript.rhino.Node getDefCfgNode();
    Code:
       0: aload_0
       1: getfield      #4                  // Field defMetadata:Lcom/google/javascript/jscomp/MustBeReachingVariableDef$Definition;
       4: getfield      #13                 // Field com/google/javascript/jscomp/MustBeReachingVariableDef$Definition.node:Lcom/google/javascript/rhino/Node;
       7: areturn

  private boolean canInline(com.google.javascript.jscomp.Scope);
    Code:
       0: aload_0
       1: invokespecial #14                 // Method getDefCfgNode:()Lcom/google/javascript/rhino/Node;
       4: invokevirtual #15                 // Method com/google/javascript/rhino/Node.isFunction:()Z
       7: ifeq          12
      10: iconst_0
      11: ireturn
      12: aload_0
      13: getfield      #4                  // Field defMetadata:Lcom/google/javascript/jscomp/MustBeReachingVariableDef$Definition;
      16: getfield      #16                 // Field com/google/javascript/jscomp/MustBeReachingVariableDef$Definition.depends:Ljava/util/Set;
      19: invokeinterface #17,  1           // InterfaceMethod java/util/Set.iterator:()Ljava/util/Iterator;
      24: astore_2
      25: aload_2
      26: invokeinterface #18,  1           // InterfaceMethod java/util/Iterator.hasNext:()Z
      31: ifeq          65
      34: aload_2
      35: invokeinterface #19,  1           // InterfaceMethod java/util/Iterator.next:()Ljava/lang/Object;
      40: checkcast     #20                 // class com/google/javascript/jscomp/Scope$Var
      43: astore_3
      44: aload_0
      45: getfield      #7                  // Field this$0:Lcom/google/javascript/jscomp/FlowSensitiveInlineVariables;
      48: invokestatic  #21                 // Method com/google/javascript/jscomp/FlowSensitiveInlineVariables.access$900:(Lcom/google/javascript/jscomp/FlowSensitiveInlineVariables;)Ljava/util/Set;
      51: aload_3
      52: invokeinterface #22,  2           // InterfaceMethod java/util/Set.contains:(Ljava/lang/Object;)Z
      57: ifeq          62
      60: iconst_0
      61: ireturn
      62: goto          25
      65: aload_0
      66: aload_0
      67: invokespecial #14                 // Method getDefCfgNode:()Lcom/google/javascript/rhino/Node;
      70: invokespecial #23                 // Method getDefinition:(Lcom/google/javascript/rhino/Node;)V
      73: aload_0
      74: aload_0
      75: getfield      #12                 // Field useCfgNode:Lcom/google/javascript/rhino/Node;
      78: invokespecial #24                 // Method getNumUseInUseCfgNode:(Lcom/google/javascript/rhino/Node;)V
      81: aload_0
      82: getfield      #2                  // Field def:Lcom/google/javascript/rhino/Node;
      85: ifnonnull     90
      88: iconst_0
      89: ireturn
      90: aload_0
      91: getfield      #2                  // Field def:Lcom/google/javascript/rhino/Node;
      94: invokevirtual #25                 // Method com/google/javascript/rhino/Node.isAssign:()Z
      97: ifeq          115
     100: aload_0
     101: getfield      #2                  // Field def:Lcom/google/javascript/rhino/Node;
     104: invokevirtual #26                 // Method com/google/javascript/rhino/Node.getParent:()Lcom/google/javascript/rhino/Node;
     107: invokestatic  #27                 // Method com/google/javascript/jscomp/NodeUtil.isExprAssign:(Lcom/google/javascript/rhino/Node;)Z
     110: ifne          115
     113: iconst_0
     114: ireturn
     115: aload_0
     116: getfield      #2                  // Field def:Lcom/google/javascript/rhino/Node;
     119: aload_0
     120: invokespecial #14                 // Method getDefCfgNode:()Lcom/google/javascript/rhino/Node;
     123: invokestatic  #28                 // Method com/google/javascript/jscomp/FlowSensitiveInlineVariables.access$1000:()Lcom/google/common/base/Predicate;
     126: invokestatic  #29                 // Method com/google/javascript/jscomp/FlowSensitiveInlineVariables.access$1100:(Lcom/google/javascript/rhino/Node;Lcom/google/javascript/rhino/Node;Lcom/google/common/base/Predicate;)Z
     129: ifeq          134
     132: iconst_0
     133: ireturn
     134: aload_0
     135: getfield      #11                 // Field use:Lcom/google/javascript/rhino/Node;
     138: aload_0
     139: getfield      #12                 // Field useCfgNode:Lcom/google/javascript/rhino/Node;
     142: invokestatic  #28                 // Method com/google/javascript/jscomp/FlowSensitiveInlineVariables.access$1000:()Lcom/google/common/base/Predicate;
     145: invokestatic  #30                 // Method com/google/javascript/jscomp/FlowSensitiveInlineVariables.access$1200:(Lcom/google/javascript/rhino/Node;Lcom/google/javascript/rhino/Node;Lcom/google/common/base/Predicate;)Z
     148: ifeq          153
     151: iconst_0
     152: ireturn
     153: aload_0
     154: getfield      #2                  // Field def:Lcom/google/javascript/rhino/Node;
     157: invokevirtual #31                 // Method com/google/javascript/rhino/Node.getLastChild:()Lcom/google/javascript/rhino/Node;
     160: aload_0
     161: getfield      #7                  // Field this$0:Lcom/google/javascript/jscomp/FlowSensitiveInlineVariables;
     164: invokestatic  #32                 // Method com/google/javascript/jscomp/FlowSensitiveInlineVariables.access$600:(Lcom/google/javascript/jscomp/FlowSensitiveInlineVariables;)Lcom/google/javascript/jscomp/AbstractCompiler;
     167: invokestatic  #33                 // Method com/google/javascript/jscomp/NodeUtil.mayHaveSideEffects:(Lcom/google/javascript/rhino/Node;Lcom/google/javascript/jscomp/AbstractCompiler;)Z
     170: ifeq          175
     173: iconst_0
     174: ireturn
     175: aload_0
     176: getfield      #1                  // Field numUsesWithinCfgNode:I
     179: iconst_1
     180: if_icmpeq     185
     183: iconst_0
     184: ireturn
     185: aload_0
     186: getfield      #11                 // Field use:Lcom/google/javascript/rhino/Node;
     189: invokestatic  #34                 // Method com/google/javascript/jscomp/NodeUtil.isWithinLoop:(Lcom/google/javascript/rhino/Node;)Z
     192: ifeq          197
     195: iconst_0
     196: ireturn
     197: aload_0
     198: getfield      #7                  // Field this$0:Lcom/google/javascript/jscomp/FlowSensitiveInlineVariables;
     201: invokestatic  #35                 // Method com/google/javascript/jscomp/FlowSensitiveInlineVariables.access$1300:(Lcom/google/javascript/jscomp/FlowSensitiveInlineVariables;)Lcom/google/javascript/jscomp/MaybeReachingVariableUse;
     204: aload_0
     205: getfield      #3                  // Field varName:Ljava/lang/String;
     208: aload_0
     209: invokespecial #14                 // Method getDefCfgNode:()Lcom/google/javascript/rhino/Node;
     212: invokevirtual #36                 // Method com/google/javascript/jscomp/MaybeReachingVariableUse.getUses:(Ljava/lang/String;Lcom/google/javascript/rhino/Node;)Ljava/util/Collection;
     215: astore_2
     216: aload_2
     217: invokeinterface #37,  1           // InterfaceMethod java/util/Collection.size:()I
     222: iconst_1
     223: if_icmpeq     228
     226: iconst_0
     227: ireturn
     228: aload_0
     229: getfield      #2                  // Field def:Lcom/google/javascript/rhino/Node;
     232: invokevirtual #31                 // Method com/google/javascript/rhino/Node.getLastChild:()Lcom/google/javascript/rhino/Node;
     235: new           #38                 // class com/google/javascript/jscomp/FlowSensitiveInlineVariables$Candidate$1
     238: dup
     239: aload_0
     240: aload_1
     241: invokespecial #39                 // Method com/google/javascript/jscomp/FlowSensitiveInlineVariables$Candidate$1."<init>":(Lcom/google/javascript/jscomp/FlowSensitiveInlineVariables$Candidate;Lcom/google/javascript/jscomp/Scope;)V
     244: new           #40                 // class com/google/javascript/jscomp/FlowSensitiveInlineVariables$Candidate$2
     247: dup
     248: aload_0
     249: invokespecial #41                 // Method com/google/javascript/jscomp/FlowSensitiveInlineVariables$Candidate$2."<init>":(Lcom/google/javascript/jscomp/FlowSensitiveInlineVariables$Candidate;)V
     252: invokestatic  #42                 // Method com/google/javascript/jscomp/NodeUtil.has:(Lcom/google/javascript/rhino/Node;Lcom/google/common/base/Predicate;Lcom/google/common/base/Predicate;)Z
     255: ifeq          260
     258: iconst_0
     259: ireturn
     260: aload_0
     261: invokespecial #14                 // Method getDefCfgNode:()Lcom/google/javascript/rhino/Node;
     264: invokevirtual #26                 // Method com/google/javascript/rhino/Node.getParent:()Lcom/google/javascript/rhino/Node;
     267: invokestatic  #43                 // Method com/google/javascript/jscomp/NodeUtil.isStatementBlock:(Lcom/google/javascript/rhino/Node;)Z
     270: ifeq          346
     273: aload_0
     274: invokespecial #14                 // Method getDefCfgNode:()Lcom/google/javascript/rhino/Node;
     277: invokevirtual #44                 // Method com/google/javascript/rhino/Node.getNext:()Lcom/google/javascript/rhino/Node;
     280: aload_0
     281: getfield      #12                 // Field useCfgNode:Lcom/google/javascript/rhino/Node;
     284: if_acmpeq     346
     287: new           #45                 // class com/google/javascript/jscomp/CheckPathsBetweenNodes
     290: dup
     291: aload_0
     292: getfield      #7                  // Field this$0:Lcom/google/javascript/jscomp/FlowSensitiveInlineVariables;
     295: invokestatic  #46                 // Method com/google/javascript/jscomp/FlowSensitiveInlineVariables.access$500:(Lcom/google/javascript/jscomp/FlowSensitiveInlineVariables;)Lcom/google/javascript/jscomp/ControlFlowGraph;
     298: aload_0
     299: getfield      #7                  // Field this$0:Lcom/google/javascript/jscomp/FlowSensitiveInlineVariables;
     302: invokestatic  #46                 // Method com/google/javascript/jscomp/FlowSensitiveInlineVariables.access$500:(Lcom/google/javascript/jscomp/FlowSensitiveInlineVariables;)Lcom/google/javascript/jscomp/ControlFlowGraph;
     305: aload_0
     306: invokespecial #14                 // Method getDefCfgNode:()Lcom/google/javascript/rhino/Node;
     309: invokevirtual #47                 // Method com/google/javascript/jscomp/ControlFlowGraph.getDirectedGraphNode:(Ljava/lang/Object;)Lcom/google/javascript/jscomp/graph/DiGraph$DiGraphNode;
     312: aload_0
     313: getfield      #7                  // Field this$0:Lcom/google/javascript/jscomp/FlowSensitiveInlineVariables;
     316: invokestatic  #46                 // Method com/google/javascript/jscomp/FlowSensitiveInlineVariables.access$500:(Lcom/google/javascript/jscomp/FlowSensitiveInlineVariables;)Lcom/google/javascript/jscomp/ControlFlowGraph;
     319: aload_0
     320: getfield      #12                 // Field useCfgNode:Lcom/google/javascript/rhino/Node;
     323: invokevirtual #47                 // Method com/google/javascript/jscomp/ControlFlowGraph.getDirectedGraphNode:(Ljava/lang/Object;)Lcom/google/javascript/jscomp/graph/DiGraph$DiGraphNode;
     326: invokestatic  #28                 // Method com/google/javascript/jscomp/FlowSensitiveInlineVariables.access$1000:()Lcom/google/common/base/Predicate;
     329: invokestatic  #48                 // Method com/google/common/base/Predicates.alwaysTrue:()Lcom/google/common/base/Predicate;
     332: iconst_0
     333: invokespecial #49                 // Method com/google/javascript/jscomp/CheckPathsBetweenNodes."<init>":(Lcom/google/javascript/jscomp/graph/DiGraph;Lcom/google/javascript/jscomp/graph/DiGraph$DiGraphNode;Lcom/google/javascript/jscomp/graph/DiGraph$DiGraphNode;Lcom/google/common/base/Predicate;Lcom/google/common/base/Predicate;Z)V
     336: astore_3
     337: aload_3
     338: invokevirtual #50                 // Method com/google/javascript/jscomp/CheckPathsBetweenNodes.somePathsSatisfyPredicate:()Z
     341: ifeq          346
     344: iconst_0
     345: ireturn
     346: iconst_1
     347: ireturn

  private void inlineVariable();
    Code:
       0: aload_0
       1: getfield      #2                  // Field def:Lcom/google/javascript/rhino/Node;
       4: invokevirtual #26                 // Method com/google/javascript/rhino/Node.getParent:()Lcom/google/javascript/rhino/Node;
       7: astore_1
       8: aload_0
       9: getfield      #11                 // Field use:Lcom/google/javascript/rhino/Node;
      12: invokevirtual #26                 // Method com/google/javascript/rhino/Node.getParent:()Lcom/google/javascript/rhino/Node;
      15: astore_2
      16: aload_0
      17: getfield      #2                  // Field def:Lcom/google/javascript/rhino/Node;
      20: invokevirtual #25                 // Method com/google/javascript/rhino/Node.isAssign:()Z
      23: ifeq          81
      26: aload_0
      27: getfield      #2                  // Field def:Lcom/google/javascript/rhino/Node;
      30: invokevirtual #31                 // Method com/google/javascript/rhino/Node.getLastChild:()Lcom/google/javascript/rhino/Node;
      33: astore_3
      34: aload_3
      35: invokevirtual #51                 // Method com/google/javascript/rhino/Node.detachFromParent:()Lcom/google/javascript/rhino/Node;
      38: pop
      39: aload_1
      40: invokevirtual #52                 // Method com/google/javascript/rhino/Node.isExprResult:()Z
      43: invokestatic  #53                 // Method com/google/common/base/Preconditions.checkState:(Z)V
      46: aload_1
      47: invokevirtual #26                 // Method com/google/javascript/rhino/Node.getParent:()Lcom/google/javascript/rhino/Node;
      50: invokevirtual #54                 // Method com/google/javascript/rhino/Node.isLabel:()Z
      53: ifeq          64
      56: aload_1
      57: invokevirtual #26                 // Method com/google/javascript/rhino/Node.getParent:()Lcom/google/javascript/rhino/Node;
      60: astore_1
      61: goto          46
      64: aload_1
      65: invokevirtual #51                 // Method com/google/javascript/rhino/Node.detachFromParent:()Lcom/google/javascript/rhino/Node;
      68: pop
      69: aload_2
      70: aload_0
      71: getfield      #11                 // Field use:Lcom/google/javascript/rhino/Node;
      74: aload_3
      75: invokevirtual #55                 // Method com/google/javascript/rhino/Node.replaceChild:(Lcom/google/javascript/rhino/Node;Lcom/google/javascript/rhino/Node;)V
      78: goto          126
      81: aload_1
      82: invokevirtual #56                 // Method com/google/javascript/rhino/Node.isVar:()Z
      85: ifeq          116
      88: aload_0
      89: getfield      #2                  // Field def:Lcom/google/javascript/rhino/Node;
      92: invokevirtual #31                 // Method com/google/javascript/rhino/Node.getLastChild:()Lcom/google/javascript/rhino/Node;
      95: astore_3
      96: aload_0
      97: getfield      #2                  // Field def:Lcom/google/javascript/rhino/Node;
     100: aload_3
     101: invokevirtual #57                 // Method com/google/javascript/rhino/Node.removeChild:(Lcom/google/javascript/rhino/Node;)V
     104: aload_2
     105: aload_0
     106: getfield      #11                 // Field use:Lcom/google/javascript/rhino/Node;
     109: aload_3
     110: invokevirtual #55                 // Method com/google/javascript/rhino/Node.replaceChild:(Lcom/google/javascript/rhino/Node;Lcom/google/javascript/rhino/Node;)V
     113: goto          126
     116: new           #58                 // class java/lang/IllegalStateException
     119: dup
     120: ldc           #59                 // String No other definitions can be inlined.
     122: invokespecial #60                 // Method java/lang/IllegalStateException."<init>":(Ljava/lang/String;)V
     125: athrow
     126: aload_0
     127: getfield      #7                  // Field this$0:Lcom/google/javascript/jscomp/FlowSensitiveInlineVariables;
     130: invokestatic  #32                 // Method com/google/javascript/jscomp/FlowSensitiveInlineVariables.access$600:(Lcom/google/javascript/jscomp/FlowSensitiveInlineVariables;)Lcom/google/javascript/jscomp/AbstractCompiler;
     133: invokevirtual #61                 // Method com/google/javascript/jscomp/AbstractCompiler.reportCodeChange:()V
     136: return

  private void getDefinition(com.google.javascript.rhino.Node);
    Code:
       0: new           #62                 // class com/google/javascript/jscomp/FlowSensitiveInlineVariables$Candidate$3
       3: dup
       4: aload_0
       5: invokespecial #63                 // Method com/google/javascript/jscomp/FlowSensitiveInlineVariables$Candidate$3."<init>":(Lcom/google/javascript/jscomp/FlowSensitiveInlineVariables$Candidate;)V
       8: astore_2
       9: aload_0
      10: getfield      #7                  // Field this$0:Lcom/google/javascript/jscomp/FlowSensitiveInlineVariables;
      13: invokestatic  #32                 // Method com/google/javascript/jscomp/FlowSensitiveInlineVariables.access$600:(Lcom/google/javascript/jscomp/FlowSensitiveInlineVariables;)Lcom/google/javascript/jscomp/AbstractCompiler;
      16: aload_1
      17: aload_2
      18: invokestatic  #64                 // Method com/google/javascript/jscomp/NodeTraversal.traverse:(Lcom/google/javascript/jscomp/AbstractCompiler;Lcom/google/javascript/rhino/Node;Lcom/google/javascript/jscomp/NodeTraversal$Callback;)V
      21: return

  private void getNumUseInUseCfgNode(com.google.javascript.rhino.Node);
    Code:
       0: aload_0
       1: iconst_0
       2: putfield      #1                  // Field numUsesWithinCfgNode:I
       5: new           #65                 // class com/google/javascript/jscomp/FlowSensitiveInlineVariables$Candidate$4
       8: dup
       9: aload_0
      10: aload_1
      11: invokespecial #66                 // Method com/google/javascript/jscomp/FlowSensitiveInlineVariables$Candidate$4."<init>":(Lcom/google/javascript/jscomp/FlowSensitiveInlineVariables$Candidate;Lcom/google/javascript/rhino/Node;)V
      14: astore_2
      15: aload_0
      16: getfield      #7                  // Field this$0:Lcom/google/javascript/jscomp/FlowSensitiveInlineVariables;
      19: invokestatic  #32                 // Method com/google/javascript/jscomp/FlowSensitiveInlineVariables.access$600:(Lcom/google/javascript/jscomp/FlowSensitiveInlineVariables;)Lcom/google/javascript/jscomp/AbstractCompiler;
      22: aload_1
      23: aload_2
      24: invokestatic  #64                 // Method com/google/javascript/jscomp/NodeTraversal.traverse:(Lcom/google/javascript/jscomp/AbstractCompiler;Lcom/google/javascript/rhino/Node;Lcom/google/javascript/jscomp/NodeTraversal$Callback;)V
      27: return

  static boolean access$100(com.google.javascript.jscomp.FlowSensitiveInlineVariables$Candidate, com.google.javascript.jscomp.Scope);
    Code:
       0: aload_0
       1: aload_1
       2: invokespecial #6                  // Method canInline:(Lcom/google/javascript/jscomp/Scope;)Z
       5: ireturn

  static void access$200(com.google.javascript.jscomp.FlowSensitiveInlineVariables$Candidate);
    Code:
       0: aload_0
       1: invokespecial #5                  // Method inlineVariable:()V
       4: return

  static com.google.javascript.jscomp.MustBeReachingVariableDef$Definition access$300(com.google.javascript.jscomp.FlowSensitiveInlineVariables$Candidate);
    Code:
       0: aload_0
       1: getfield      #4                  // Field defMetadata:Lcom/google/javascript/jscomp/MustBeReachingVariableDef$Definition;
       4: areturn

  static java.lang.String access$400(com.google.javascript.jscomp.FlowSensitiveInlineVariables$Candidate);
    Code:
       0: aload_0
       1: getfield      #3                  // Field varName:Ljava/lang/String;
       4: areturn

  static com.google.javascript.rhino.Node access$1402(com.google.javascript.jscomp.FlowSensitiveInlineVariables$Candidate, com.google.javascript.rhino.Node);
    Code:
       0: aload_0
       1: aload_1
       2: dup_x1
       3: putfield      #2                  // Field def:Lcom/google/javascript/rhino/Node;
       6: areturn

  static int access$1508(com.google.javascript.jscomp.FlowSensitiveInlineVariables$Candidate);
    Code:
       0: aload_0
       1: dup
       2: getfield      #1                  // Field numUsesWithinCfgNode:I
       5: dup_x1
       6: iconst_1
       7: iadd
       8: putfield      #1                  // Field numUsesWithinCfgNode:I
      11: ireturn
}
