Compiled from "FunctionInjector.java"
class com.google.javascript.jscomp.FunctionInjector$1 implements com.google.common.base.Supplier<java.lang.String> {
  private int nextId;

  final com.google.javascript.jscomp.FunctionInjector this$0;

  com.google.javascript.jscomp.FunctionInjector$1(com.google.javascript.jscomp.FunctionInjector);
    Code:
       0: aload_0
       1: aload_1
       2: putfield      #1                  // Field this$0:Lcom/google/javascript/jscomp/FunctionInjector;
       5: aload_0
       6: invokespecial #2                  // Method java/lang/Object."<init>":()V
       9: aload_0
      10: iconst_0
      11: putfield      #3                  // Field nextId:I
      14: return

  public java.lang.String get();
    Code:
       0: aload_0
       1: dup
       2: getfield      #3                  // Field nextId:I
       5: dup_x1
       6: iconst_1
       7: iadd
       8: putfield      #3                  // Field nextId:I
      11: invokestatic  #4                  // Method java/lang/String.valueOf:(I)Ljava/lang/String;
      14: areturn

  public java.lang.Object get();
    Code:
       0: aload_0
       1: invokevirtual #5                  // Method get:()Ljava/lang/String;
       4: areturn
}
