Compiled from "FunctionInjector.java"
final class com.google.javascript.jscomp.FunctionInjector$CallSiteType$1 extends com.google.javascript.jscomp.FunctionInjector$CallSiteType {
  com.google.javascript.jscomp.FunctionInjector$CallSiteType$1(java.lang.String, int);
    Code:
       0: aload_0
       1: aload_1
       2: iload_2
       3: aconst_null
       4: invokespecial #1                  // Method com/google/javascript/jscomp/FunctionInjector$CallSiteType."<init>":(Ljava/lang/String;ILcom/google/javascript/jscomp/FunctionInjector$1;)V
       7: return

  public void prepare(com.google.javascript.jscomp.FunctionInjector, com.google.javascript.jscomp.FunctionInjector$Reference);
    Code:
       0: new           #2                  // class java/lang/IllegalStateException
       3: dup
       4: ldc           #3                  // String unexpected
       6: invokespecial #4                  // Method java/lang/IllegalStateException."<init>":(Ljava/lang/String;)V
       9: athrow
}
