Compiled from "InlineFunctions.java"
class com.google.javascript.jscomp.InlineFunctions$Reference extends com.google.javascript.jscomp.FunctionInjector$Reference {
  boolean requiresDecomposition;

  boolean inlined;

  com.google.javascript.jscomp.InlineFunctions$Reference(com.google.javascript.rhino.Node, com.google.javascript.jscomp.Scope, com.google.javascript.jscomp.JSModule, com.google.javascript.jscomp.FunctionInjector$InliningMode);
    Code:
       0: aload_0
       1: aload_1
       2: aload_2
       3: aload_3
       4: aload         4
       6: invokespecial #1                  // Method com/google/javascript/jscomp/FunctionInjector$Reference."<init>":(Lcom/google/javascript/rhino/Node;Lcom/google/javascript/jscomp/Scope;Lcom/google/javascript/jscomp/JSModule;Lcom/google/javascript/jscomp/FunctionInjector$InliningMode;)V
       9: aload_0
      10: iconst_0
      11: putfield      #2                  // Field requiresDecomposition:Z
      14: aload_0
      15: iconst_0
      16: putfield      #3                  // Field inlined:Z
      19: return

  void setRequiresDecomposition(boolean);
    Code:
       0: aload_0
       1: iload_1
       2: putfield      #2                  // Field requiresDecomposition:Z
       5: return
}
