Compiled from "Instrumentation.java"
public final class com.google.javascript.jscomp.Instrumentation$Builder extends com.google.protobuf.GeneratedMessage$Builder<com.google.javascript.jscomp.Instrumentation$Builder> implements com.google.javascript.jscomp.InstrumentationOrBuilder {
  private int bitField0_;

  private java.lang.Object reportDefined_;

  private java.lang.Object reportCall_;

  private java.lang.Object reportExit_;

  private com.google.protobuf.LazyStringList declarationToRemove_;

  private com.google.protobuf.LazyStringList init_;

  private java.lang.Object appNameSetter_;

  public static final com.google.protobuf.Descriptors$Descriptor getDescriptor();
    Code:
       0: getstatic     #3                  // Field com/google/javascript/jscomp/InstrumentationTemplate.internal_static_jscomp_Instrumentation_descriptor:Lcom/google/protobuf/Descriptors$Descriptor;
       3: areturn

  protected com.google.protobuf.GeneratedMessage$FieldAccessorTable internalGetFieldAccessorTable();
    Code:
       0: getstatic     #4                  // Field com/google/javascript/jscomp/InstrumentationTemplate.internal_static_jscomp_Instrumentation_fieldAccessorTable:Lcom/google/protobuf/GeneratedMessage$FieldAccessorTable;
       3: ldc           #5                  // class com/google/javascript/jscomp/Instrumentation
       5: ldc           #6                  // class com/google/javascript/jscomp/Instrumentation$Builder
       7: invokevirtual #7                  // Method com/google/protobuf/GeneratedMessage$FieldAccessorTable.ensureFieldAccessorsInitialized:(Ljava/lang/Class;Ljava/lang/Class;)Lcom/google/protobuf/GeneratedMessage$FieldAccessorTable;
      10: areturn

  private com.google.javascript.jscomp.Instrumentation$Builder();
    Code:
       0: aload_0
       1: invokespecial #8                  // Method com/google/protobuf/GeneratedMessage$Builder."<init>":()V
       4: aload_0
       5: ldc           #9                  // String
       7: putfield      #10                 // Field reportDefined_:Ljava/lang/Object;
      10: aload_0
      11: ldc           #9                  // String
      13: putfield      #11                 // Field reportCall_:Ljava/lang/Object;
      16: aload_0
      17: ldc           #9                  // String
      19: putfield      #12                 // Field reportExit_:Ljava/lang/Object;
      22: aload_0
      23: getstatic     #13                 // Field com/google/protobuf/LazyStringArrayList.EMPTY:Lcom/google/protobuf/LazyStringList;
      26: putfield      #14                 // Field declarationToRemove_:Lcom/google/protobuf/LazyStringList;
      29: aload_0
      30: getstatic     #13                 // Field com/google/protobuf/LazyStringArrayList.EMPTY:Lcom/google/protobuf/LazyStringList;
      33: putfield      #15                 // Field init_:Lcom/google/protobuf/LazyStringList;
      36: aload_0
      37: ldc           #9                  // String
      39: putfield      #16                 // Field appNameSetter_:Ljava/lang/Object;
      42: aload_0
      43: invokespecial #17                 // Method maybeForceBuilderInitialization:()V
      46: return

  private com.google.javascript.jscomp.Instrumentation$Builder(com.google.protobuf.GeneratedMessage$BuilderParent);
    Code:
       0: aload_0
       1: aload_1
       2: invokespecial #18                 // Method com/google/protobuf/GeneratedMessage$Builder."<init>":(Lcom/google/protobuf/GeneratedMessage$BuilderParent;)V
       5: aload_0
       6: ldc           #9                  // String
       8: putfield      #10                 // Field reportDefined_:Ljava/lang/Object;
      11: aload_0
      12: ldc           #9                  // String
      14: putfield      #11                 // Field reportCall_:Ljava/lang/Object;
      17: aload_0
      18: ldc           #9                  // String
      20: putfield      #12                 // Field reportExit_:Ljava/lang/Object;
      23: aload_0
      24: getstatic     #13                 // Field com/google/protobuf/LazyStringArrayList.EMPTY:Lcom/google/protobuf/LazyStringList;
      27: putfield      #14                 // Field declarationToRemove_:Lcom/google/protobuf/LazyStringList;
      30: aload_0
      31: getstatic     #13                 // Field com/google/protobuf/LazyStringArrayList.EMPTY:Lcom/google/protobuf/LazyStringList;
      34: putfield      #15                 // Field init_:Lcom/google/protobuf/LazyStringList;
      37: aload_0
      38: ldc           #9                  // String
      40: putfield      #16                 // Field appNameSetter_:Ljava/lang/Object;
      43: aload_0
      44: invokespecial #17                 // Method maybeForceBuilderInitialization:()V
      47: return

  private void maybeForceBuilderInitialization();
    Code:
       0: invokestatic  #19                 // Method com/google/javascript/jscomp/Instrumentation.access$300:()Z
       3: ifeq          6
       6: return

  private static com.google.javascript.jscomp.Instrumentation$Builder create();
    Code:
       0: new           #6                  // class com/google/javascript/jscomp/Instrumentation$Builder
       3: dup
       4: invokespecial #20                 // Method "<init>":()V
       7: areturn

  public com.google.javascript.jscomp.Instrumentation$Builder clear();
    Code:
       0: aload_0
       1: invokespecial #21                 // Method com/google/protobuf/GeneratedMessage$Builder.clear:()Lcom/google/protobuf/GeneratedMessage$Builder;
       4: pop
       5: aload_0
       6: ldc           #9                  // String
       8: putfield      #10                 // Field reportDefined_:Ljava/lang/Object;
      11: aload_0
      12: aload_0
      13: getfield      #22                 // Field bitField0_:I
      16: bipush        -2
      18: iand
      19: putfield      #22                 // Field bitField0_:I
      22: aload_0
      23: ldc           #9                  // String
      25: putfield      #11                 // Field reportCall_:Ljava/lang/Object;
      28: aload_0
      29: aload_0
      30: getfield      #22                 // Field bitField0_:I
      33: bipush        -3
      35: iand
      36: putfield      #22                 // Field bitField0_:I
      39: aload_0
      40: ldc           #9                  // String
      42: putfield      #12                 // Field reportExit_:Ljava/lang/Object;
      45: aload_0
      46: aload_0
      47: getfield      #22                 // Field bitField0_:I
      50: bipush        -5
      52: iand
      53: putfield      #22                 // Field bitField0_:I
      56: aload_0
      57: getstatic     #13                 // Field com/google/protobuf/LazyStringArrayList.EMPTY:Lcom/google/protobuf/LazyStringList;
      60: putfield      #14                 // Field declarationToRemove_:Lcom/google/protobuf/LazyStringList;
      63: aload_0
      64: aload_0
      65: getfield      #22                 // Field bitField0_:I
      68: bipush        -9
      70: iand
      71: putfield      #22                 // Field bitField0_:I
      74: aload_0
      75: getstatic     #13                 // Field com/google/protobuf/LazyStringArrayList.EMPTY:Lcom/google/protobuf/LazyStringList;
      78: putfield      #15                 // Field init_:Lcom/google/protobuf/LazyStringList;
      81: aload_0
      82: aload_0
      83: getfield      #22                 // Field bitField0_:I
      86: bipush        -17
      88: iand
      89: putfield      #22                 // Field bitField0_:I
      92: aload_0
      93: ldc           #9                  // String
      95: putfield      #16                 // Field appNameSetter_:Ljava/lang/Object;
      98: aload_0
      99: aload_0
     100: getfield      #22                 // Field bitField0_:I
     103: bipush        -33
     105: iand
     106: putfield      #22                 // Field bitField0_:I
     109: aload_0
     110: areturn

  public com.google.javascript.jscomp.Instrumentation$Builder clone();
    Code:
       0: invokestatic  #2                  // Method create:()Lcom/google/javascript/jscomp/Instrumentation$Builder;
       3: aload_0
       4: invokevirtual #23                 // Method buildPartial:()Lcom/google/javascript/jscomp/Instrumentation;
       7: invokevirtual #24                 // Method mergeFrom:(Lcom/google/javascript/jscomp/Instrumentation;)Lcom/google/javascript/jscomp/Instrumentation$Builder;
      10: areturn

  public com.google.protobuf.Descriptors$Descriptor getDescriptorForType();
    Code:
       0: getstatic     #3                  // Field com/google/javascript/jscomp/InstrumentationTemplate.internal_static_jscomp_Instrumentation_descriptor:Lcom/google/protobuf/Descriptors$Descriptor;
       3: areturn

  public com.google.javascript.jscomp.Instrumentation getDefaultInstanceForType();
    Code:
       0: invokestatic  #25                 // Method com/google/javascript/jscomp/Instrumentation.getDefaultInstance:()Lcom/google/javascript/jscomp/Instrumentation;
       3: areturn

  public com.google.javascript.jscomp.Instrumentation build();
    Code:
       0: aload_0
       1: invokevirtual #23                 // Method buildPartial:()Lcom/google/javascript/jscomp/Instrumentation;
       4: astore_1
       5: aload_1
       6: invokevirtual #26                 // Method com/google/javascript/jscomp/Instrumentation.isInitialized:()Z
       9: ifne          17
      12: aload_1
      13: invokestatic  #27                 // Method newUninitializedMessageException:(Lcom/google/protobuf/Message;)Lcom/google/protobuf/UninitializedMessageException;
      16: athrow
      17: aload_1
      18: areturn

  public com.google.javascript.jscomp.Instrumentation buildPartial();
    Code:
       0: new           #5                  // class com/google/javascript/jscomp/Instrumentation
       3: dup
       4: aload_0
       5: aconst_null
       6: invokespecial #28                 // Method com/google/javascript/jscomp/Instrumentation."<init>":(Lcom/google/protobuf/GeneratedMessage$Builder;Lcom/google/javascript/jscomp/Instrumentation$1;)V
       9: astore_1
      10: aload_0
      11: getfield      #22                 // Field bitField0_:I
      14: istore_2
      15: iconst_0
      16: istore_3
      17: iload_2
      18: iconst_1
      19: iand
      20: iconst_1
      21: if_icmpne     28
      24: iload_3
      25: iconst_1
      26: ior
      27: istore_3
      28: aload_1
      29: aload_0
      30: getfield      #10                 // Field reportDefined_:Ljava/lang/Object;
      33: invokestatic  #29                 // Method com/google/javascript/jscomp/Instrumentation.access$502:(Lcom/google/javascript/jscomp/Instrumentation;Ljava/lang/Object;)Ljava/lang/Object;
      36: pop
      37: iload_2
      38: iconst_2
      39: iand
      40: iconst_2
      41: if_icmpne     48
      44: iload_3
      45: iconst_2
      46: ior
      47: istore_3
      48: aload_1
      49: aload_0
      50: getfield      #11                 // Field reportCall_:Ljava/lang/Object;
      53: invokestatic  #30                 // Method com/google/javascript/jscomp/Instrumentation.access$602:(Lcom/google/javascript/jscomp/Instrumentation;Ljava/lang/Object;)Ljava/lang/Object;
      56: pop
      57: iload_2
      58: iconst_4
      59: iand
      60: iconst_4
      61: if_icmpne     68
      64: iload_3
      65: iconst_4
      66: ior
      67: istore_3
      68: aload_1
      69: aload_0
      70: getfield      #12                 // Field reportExit_:Ljava/lang/Object;
      73: invokestatic  #31                 // Method com/google/javascript/jscomp/Instrumentation.access$702:(Lcom/google/javascript/jscomp/Instrumentation;Ljava/lang/Object;)Ljava/lang/Object;
      76: pop
      77: aload_0
      78: getfield      #22                 // Field bitField0_:I
      81: bipush        8
      83: iand
      84: bipush        8
      86: if_icmpne     115
      89: aload_0
      90: new           #32                 // class com/google/protobuf/UnmodifiableLazyStringList
      93: dup
      94: aload_0
      95: getfield      #14                 // Field declarationToRemove_:Lcom/google/protobuf/LazyStringList;
      98: invokespecial #33                 // Method com/google/protobuf/UnmodifiableLazyStringList."<init>":(Lcom/google/protobuf/LazyStringList;)V
     101: putfield      #14                 // Field declarationToRemove_:Lcom/google/protobuf/LazyStringList;
     104: aload_0
     105: aload_0
     106: getfield      #22                 // Field bitField0_:I
     109: bipush        -9
     111: iand
     112: putfield      #22                 // Field bitField0_:I
     115: aload_1
     116: aload_0
     117: getfield      #14                 // Field declarationToRemove_:Lcom/google/protobuf/LazyStringList;
     120: invokestatic  #34                 // Method com/google/javascript/jscomp/Instrumentation.access$802:(Lcom/google/javascript/jscomp/Instrumentation;Lcom/google/protobuf/LazyStringList;)Lcom/google/protobuf/LazyStringList;
     123: pop
     124: aload_0
     125: getfield      #22                 // Field bitField0_:I
     128: bipush        16
     130: iand
     131: bipush        16
     133: if_icmpne     162
     136: aload_0
     137: new           #32                 // class com/google/protobuf/UnmodifiableLazyStringList
     140: dup
     141: aload_0
     142: getfield      #15                 // Field init_:Lcom/google/protobuf/LazyStringList;
     145: invokespecial #33                 // Method com/google/protobuf/UnmodifiableLazyStringList."<init>":(Lcom/google/protobuf/LazyStringList;)V
     148: putfield      #15                 // Field init_:Lcom/google/protobuf/LazyStringList;
     151: aload_0
     152: aload_0
     153: getfield      #22                 // Field bitField0_:I
     156: bipush        -17
     158: iand
     159: putfield      #22                 // Field bitField0_:I
     162: aload_1
     163: aload_0
     164: getfield      #15                 // Field init_:Lcom/google/protobuf/LazyStringList;
     167: invokestatic  #35                 // Method com/google/javascript/jscomp/Instrumentation.access$902:(Lcom/google/javascript/jscomp/Instrumentation;Lcom/google/protobuf/LazyStringList;)Lcom/google/protobuf/LazyStringList;
     170: pop
     171: iload_2
     172: bipush        32
     174: iand
     175: bipush        32
     177: if_icmpne     185
     180: iload_3
     181: bipush        8
     183: ior
     184: istore_3
     185: aload_1
     186: aload_0
     187: getfield      #16                 // Field appNameSetter_:Ljava/lang/Object;
     190: invokestatic  #36                 // Method com/google/javascript/jscomp/Instrumentation.access$1002:(Lcom/google/javascript/jscomp/Instrumentation;Ljava/lang/Object;)Ljava/lang/Object;
     193: pop
     194: aload_1
     195: iload_3
     196: invokestatic  #37                 // Method com/google/javascript/jscomp/Instrumentation.access$1102:(Lcom/google/javascript/jscomp/Instrumentation;I)I
     199: pop
     200: aload_0
     201: invokevirtual #38                 // Method onBuilt:()V
     204: aload_1
     205: areturn

  public com.google.javascript.jscomp.Instrumentation$Builder mergeFrom(com.google.protobuf.Message);
    Code:
       0: aload_1
       1: instanceof    #5                  // class com/google/javascript/jscomp/Instrumentation
       4: ifeq          16
       7: aload_0
       8: aload_1
       9: checkcast     #5                  // class com/google/javascript/jscomp/Instrumentation
      12: invokevirtual #24                 // Method mergeFrom:(Lcom/google/javascript/jscomp/Instrumentation;)Lcom/google/javascript/jscomp/Instrumentation$Builder;
      15: areturn
      16: aload_0
      17: aload_1
      18: invokespecial #39                 // Method com/google/protobuf/GeneratedMessage$Builder.mergeFrom:(Lcom/google/protobuf/Message;)Lcom/google/protobuf/AbstractMessage$Builder;
      21: pop
      22: aload_0
      23: areturn

  public com.google.javascript.jscomp.Instrumentation$Builder mergeFrom(com.google.javascript.jscomp.Instrumentation);
    Code:
       0: aload_1
       1: invokestatic  #25                 // Method com/google/javascript/jscomp/Instrumentation.getDefaultInstance:()Lcom/google/javascript/jscomp/Instrumentation;
       4: if_acmpne     9
       7: aload_0
       8: areturn
       9: aload_1
      10: invokevirtual #40                 // Method com/google/javascript/jscomp/Instrumentation.hasReportDefined:()Z
      13: ifeq          38
      16: aload_0
      17: dup
      18: getfield      #22                 // Field bitField0_:I
      21: iconst_1
      22: ior
      23: putfield      #22                 // Field bitField0_:I
      26: aload_0
      27: aload_1
      28: invokestatic  #41                 // Method com/google/javascript/jscomp/Instrumentation.access$500:(Lcom/google/javascript/jscomp/Instrumentation;)Ljava/lang/Object;
      31: putfield      #10                 // Field reportDefined_:Ljava/lang/Object;
      34: aload_0
      35: invokevirtual #42                 // Method onChanged:()V
      38: aload_1
      39: invokevirtual #43                 // Method com/google/javascript/jscomp/Instrumentation.hasReportCall:()Z
      42: ifeq          67
      45: aload_0
      46: dup
      47: getfield      #22                 // Field bitField0_:I
      50: iconst_2
      51: ior
      52: putfield      #22                 // Field bitField0_:I
      55: aload_0
      56: aload_1
      57: invokestatic  #44                 // Method com/google/javascript/jscomp/Instrumentation.access$600:(Lcom/google/javascript/jscomp/Instrumentation;)Ljava/lang/Object;
      60: putfield      #11                 // Field reportCall_:Ljava/lang/Object;
      63: aload_0
      64: invokevirtual #42                 // Method onChanged:()V
      67: aload_1
      68: invokevirtual #45                 // Method com/google/javascript/jscomp/Instrumentation.hasReportExit:()Z
      71: ifeq          96
      74: aload_0
      75: dup
      76: getfield      #22                 // Field bitField0_:I
      79: iconst_4
      80: ior
      81: putfield      #22                 // Field bitField0_:I
      84: aload_0
      85: aload_1
      86: invokestatic  #46                 // Method com/google/javascript/jscomp/Instrumentation.access$700:(Lcom/google/javascript/jscomp/Instrumentation;)Ljava/lang/Object;
      89: putfield      #12                 // Field reportExit_:Ljava/lang/Object;
      92: aload_0
      93: invokevirtual #42                 // Method onChanged:()V
      96: aload_1
      97: invokestatic  #47                 // Method com/google/javascript/jscomp/Instrumentation.access$800:(Lcom/google/javascript/jscomp/Instrumentation;)Lcom/google/protobuf/LazyStringList;
     100: invokeinterface #48,  1           // InterfaceMethod com/google/protobuf/LazyStringList.isEmpty:()Z
     105: ifne          164
     108: aload_0
     109: getfield      #14                 // Field declarationToRemove_:Lcom/google/protobuf/LazyStringList;
     112: invokeinterface #48,  1           // InterfaceMethod com/google/protobuf/LazyStringList.isEmpty:()Z
     117: ifeq          142
     120: aload_0
     121: aload_1
     122: invokestatic  #47                 // Method com/google/javascript/jscomp/Instrumentation.access$800:(Lcom/google/javascript/jscomp/Instrumentation;)Lcom/google/protobuf/LazyStringList;
     125: putfield      #14                 // Field declarationToRemove_:Lcom/google/protobuf/LazyStringList;
     128: aload_0
     129: aload_0
     130: getfield      #22                 // Field bitField0_:I
     133: bipush        -9
     135: iand
     136: putfield      #22                 // Field bitField0_:I
     139: goto          160
     142: aload_0
     143: invokespecial #49                 // Method ensureDeclarationToRemoveIsMutable:()V
     146: aload_0
     147: getfield      #14                 // Field declarationToRemove_:Lcom/google/protobuf/LazyStringList;
     150: aload_1
     151: invokestatic  #47                 // Method com/google/javascript/jscomp/Instrumentation.access$800:(Lcom/google/javascript/jscomp/Instrumentation;)Lcom/google/protobuf/LazyStringList;
     154: invokeinterface #50,  2           // InterfaceMethod com/google/protobuf/LazyStringList.addAll:(Ljava/util/Collection;)Z
     159: pop
     160: aload_0
     161: invokevirtual #42                 // Method onChanged:()V
     164: aload_1
     165: invokestatic  #51                 // Method com/google/javascript/jscomp/Instrumentation.access$900:(Lcom/google/javascript/jscomp/Instrumentation;)Lcom/google/protobuf/LazyStringList;
     168: invokeinterface #48,  1           // InterfaceMethod com/google/protobuf/LazyStringList.isEmpty:()Z
     173: ifne          232
     176: aload_0
     177: getfield      #15                 // Field init_:Lcom/google/protobuf/LazyStringList;
     180: invokeinterface #48,  1           // InterfaceMethod com/google/protobuf/LazyStringList.isEmpty:()Z
     185: ifeq          210
     188: aload_0
     189: aload_1
     190: invokestatic  #51                 // Method com/google/javascript/jscomp/Instrumentation.access$900:(Lcom/google/javascript/jscomp/Instrumentation;)Lcom/google/protobuf/LazyStringList;
     193: putfield      #15                 // Field init_:Lcom/google/protobuf/LazyStringList;
     196: aload_0
     197: aload_0
     198: getfield      #22                 // Field bitField0_:I
     201: bipush        -17
     203: iand
     204: putfield      #22                 // Field bitField0_:I
     207: goto          228
     210: aload_0
     211: invokespecial #52                 // Method ensureInitIsMutable:()V
     214: aload_0
     215: getfield      #15                 // Field init_:Lcom/google/protobuf/LazyStringList;
     218: aload_1
     219: invokestatic  #51                 // Method com/google/javascript/jscomp/Instrumentation.access$900:(Lcom/google/javascript/jscomp/Instrumentation;)Lcom/google/protobuf/LazyStringList;
     222: invokeinterface #50,  2           // InterfaceMethod com/google/protobuf/LazyStringList.addAll:(Ljava/util/Collection;)Z
     227: pop
     228: aload_0
     229: invokevirtual #42                 // Method onChanged:()V
     232: aload_1
     233: invokevirtual #53                 // Method com/google/javascript/jscomp/Instrumentation.hasAppNameSetter:()Z
     236: ifeq          262
     239: aload_0
     240: dup
     241: getfield      #22                 // Field bitField0_:I
     244: bipush        32
     246: ior
     247: putfield      #22                 // Field bitField0_:I
     250: aload_0
     251: aload_1
     252: invokestatic  #54                 // Method com/google/javascript/jscomp/Instrumentation.access$1000:(Lcom/google/javascript/jscomp/Instrumentation;)Ljava/lang/Object;
     255: putfield      #16                 // Field appNameSetter_:Ljava/lang/Object;
     258: aload_0
     259: invokevirtual #42                 // Method onChanged:()V
     262: aload_0
     263: aload_1
     264: invokevirtual #55                 // Method com/google/javascript/jscomp/Instrumentation.getUnknownFields:()Lcom/google/protobuf/UnknownFieldSet;
     267: invokevirtual #56                 // Method mergeUnknownFields:(Lcom/google/protobuf/UnknownFieldSet;)Lcom/google/protobuf/GeneratedMessage$Builder;
     270: pop
     271: aload_0
     272: areturn

  public final boolean isInitialized();
    Code:
       0: iconst_1
       1: ireturn

  public com.google.javascript.jscomp.Instrumentation$Builder mergeFrom(com.google.protobuf.CodedInputStream, com.google.protobuf.ExtensionRegistryLite) throws java.io.IOException;
    Code:
       0: aconst_null
       1: astore_3
       2: getstatic     #57                 // Field com/google/javascript/jscomp/Instrumentation.PARSER:Lcom/google/protobuf/Parser;
       5: aload_1
       6: aload_2
       7: invokeinterface #58,  3           // InterfaceMethod com/google/protobuf/Parser.parsePartialFrom:(Lcom/google/protobuf/CodedInputStream;Lcom/google/protobuf/ExtensionRegistryLite;)Ljava/lang/Object;
      12: checkcast     #5                  // class com/google/javascript/jscomp/Instrumentation
      15: astore_3
      16: aload_3
      17: ifnull        58
      20: aload_0
      21: aload_3
      22: invokevirtual #24                 // Method mergeFrom:(Lcom/google/javascript/jscomp/Instrumentation;)Lcom/google/javascript/jscomp/Instrumentation$Builder;
      25: pop
      26: goto          58
      29: astore        4
      31: aload         4
      33: invokevirtual #60                 // Method com/google/protobuf/InvalidProtocolBufferException.getUnfinishedMessage:()Lcom/google/protobuf/MessageLite;
      36: checkcast     #5                  // class com/google/javascript/jscomp/Instrumentation
      39: astore_3
      40: aload         4
      42: athrow
      43: astore        5
      45: aload_3
      46: ifnull        55
      49: aload_0
      50: aload_3
      51: invokevirtual #24                 // Method mergeFrom:(Lcom/google/javascript/jscomp/Instrumentation;)Lcom/google/javascript/jscomp/Instrumentation$Builder;
      54: pop
      55: aload         5
      57: athrow
      58: aload_0
      59: areturn
    Exception table:
       from    to  target type
           2    16    29   Class com/google/protobuf/InvalidProtocolBufferException
           2    16    43   any
          29    45    43   any

  public boolean hasReportDefined();
    Code:
       0: aload_0
       1: getfield      #22                 // Field bitField0_:I
       4: iconst_1
       5: iand
       6: iconst_1
       7: if_icmpne     14
      10: iconst_1
      11: goto          15
      14: iconst_0
      15: ireturn

  public java.lang.String getReportDefined();
    Code:
       0: aload_0
       1: getfield      #10                 // Field reportDefined_:Ljava/lang/Object;
       4: astore_1
       5: aload_1
       6: instanceof    #61                 // class java/lang/String
       9: ifne          27
      12: aload_1
      13: checkcast     #62                 // class com/google/protobuf/ByteString
      16: invokevirtual #63                 // Method com/google/protobuf/ByteString.toStringUtf8:()Ljava/lang/String;
      19: astore_2
      20: aload_0
      21: aload_2
      22: putfield      #10                 // Field reportDefined_:Ljava/lang/Object;
      25: aload_2
      26: areturn
      27: aload_1
      28: checkcast     #61                 // class java/lang/String
      31: areturn

  public com.google.protobuf.ByteString getReportDefinedBytes();
    Code:
       0: aload_0
       1: getfield      #10                 // Field reportDefined_:Ljava/lang/Object;
       4: astore_1
       5: aload_1
       6: instanceof    #61                 // class java/lang/String
       9: ifeq          27
      12: aload_1
      13: checkcast     #61                 // class java/lang/String
      16: invokestatic  #64                 // Method com/google/protobuf/ByteString.copyFromUtf8:(Ljava/lang/String;)Lcom/google/protobuf/ByteString;
      19: astore_2
      20: aload_0
      21: aload_2
      22: putfield      #10                 // Field reportDefined_:Ljava/lang/Object;
      25: aload_2
      26: areturn
      27: aload_1
      28: checkcast     #62                 // class com/google/protobuf/ByteString
      31: areturn

  public com.google.javascript.jscomp.Instrumentation$Builder setReportDefined(java.lang.String);
    Code:
       0: aload_1
       1: ifnonnull     12
       4: new           #65                 // class java/lang/NullPointerException
       7: dup
       8: invokespecial #66                 // Method java/lang/NullPointerException."<init>":()V
      11: athrow
      12: aload_0
      13: dup
      14: getfield      #22                 // Field bitField0_:I
      17: iconst_1
      18: ior
      19: putfield      #22                 // Field bitField0_:I
      22: aload_0
      23: aload_1
      24: putfield      #10                 // Field reportDefined_:Ljava/lang/Object;
      27: aload_0
      28: invokevirtual #42                 // Method onChanged:()V
      31: aload_0
      32: areturn

  public com.google.javascript.jscomp.Instrumentation$Builder clearReportDefined();
    Code:
       0: aload_0
       1: aload_0
       2: getfield      #22                 // Field bitField0_:I
       5: bipush        -2
       7: iand
       8: putfield      #22                 // Field bitField0_:I
      11: aload_0
      12: invokestatic  #25                 // Method com/google/javascript/jscomp/Instrumentation.getDefaultInstance:()Lcom/google/javascript/jscomp/Instrumentation;
      15: invokevirtual #67                 // Method com/google/javascript/jscomp/Instrumentation.getReportDefined:()Ljava/lang/String;
      18: putfield      #10                 // Field reportDefined_:Ljava/lang/Object;
      21: aload_0
      22: invokevirtual #42                 // Method onChanged:()V
      25: aload_0
      26: areturn

  public com.google.javascript.jscomp.Instrumentation$Builder setReportDefinedBytes(com.google.protobuf.ByteString);
    Code:
       0: aload_1
       1: ifnonnull     12
       4: new           #65                 // class java/lang/NullPointerException
       7: dup
       8: invokespecial #66                 // Method java/lang/NullPointerException."<init>":()V
      11: athrow
      12: aload_0
      13: dup
      14: getfield      #22                 // Field bitField0_:I
      17: iconst_1
      18: ior
      19: putfield      #22                 // Field bitField0_:I
      22: aload_0
      23: aload_1
      24: putfield      #10                 // Field reportDefined_:Ljava/lang/Object;
      27: aload_0
      28: invokevirtual #42                 // Method onChanged:()V
      31: aload_0
      32: areturn

  public boolean hasReportCall();
    Code:
       0: aload_0
       1: getfield      #22                 // Field bitField0_:I
       4: iconst_2
       5: iand
       6: iconst_2
       7: if_icmpne     14
      10: iconst_1
      11: goto          15
      14: iconst_0
      15: ireturn

  public java.lang.String getReportCall();
    Code:
       0: aload_0
       1: getfield      #11                 // Field reportCall_:Ljava/lang/Object;
       4: astore_1
       5: aload_1
       6: instanceof    #61                 // class java/lang/String
       9: ifne          27
      12: aload_1
      13: checkcast     #62                 // class com/google/protobuf/ByteString
      16: invokevirtual #63                 // Method com/google/protobuf/ByteString.toStringUtf8:()Ljava/lang/String;
      19: astore_2
      20: aload_0
      21: aload_2
      22: putfield      #11                 // Field reportCall_:Ljava/lang/Object;
      25: aload_2
      26: areturn
      27: aload_1
      28: checkcast     #61                 // class java/lang/String
      31: areturn

  public com.google.protobuf.ByteString getReportCallBytes();
    Code:
       0: aload_0
       1: getfield      #11                 // Field reportCall_:Ljava/lang/Object;
       4: astore_1
       5: aload_1
       6: instanceof    #61                 // class java/lang/String
       9: ifeq          27
      12: aload_1
      13: checkcast     #61                 // class java/lang/String
      16: invokestatic  #64                 // Method com/google/protobuf/ByteString.copyFromUtf8:(Ljava/lang/String;)Lcom/google/protobuf/ByteString;
      19: astore_2
      20: aload_0
      21: aload_2
      22: putfield      #11                 // Field reportCall_:Ljava/lang/Object;
      25: aload_2
      26: areturn
      27: aload_1
      28: checkcast     #62                 // class com/google/protobuf/ByteString
      31: areturn

  public com.google.javascript.jscomp.Instrumentation$Builder setReportCall(java.lang.String);
    Code:
       0: aload_1
       1: ifnonnull     12
       4: new           #65                 // class java/lang/NullPointerException
       7: dup
       8: invokespecial #66                 // Method java/lang/NullPointerException."<init>":()V
      11: athrow
      12: aload_0
      13: dup
      14: getfield      #22                 // Field bitField0_:I
      17: iconst_2
      18: ior
      19: putfield      #22                 // Field bitField0_:I
      22: aload_0
      23: aload_1
      24: putfield      #11                 // Field reportCall_:Ljava/lang/Object;
      27: aload_0
      28: invokevirtual #42                 // Method onChanged:()V
      31: aload_0
      32: areturn

  public com.google.javascript.jscomp.Instrumentation$Builder clearReportCall();
    Code:
       0: aload_0
       1: aload_0
       2: getfield      #22                 // Field bitField0_:I
       5: bipush        -3
       7: iand
       8: putfield      #22                 // Field bitField0_:I
      11: aload_0
      12: invokestatic  #25                 // Method com/google/javascript/jscomp/Instrumentation.getDefaultInstance:()Lcom/google/javascript/jscomp/Instrumentation;
      15: invokevirtual #68                 // Method com/google/javascript/jscomp/Instrumentation.getReportCall:()Ljava/lang/String;
      18: putfield      #11                 // Field reportCall_:Ljava/lang/Object;
      21: aload_0
      22: invokevirtual #42                 // Method onChanged:()V
      25: aload_0
      26: areturn

  public com.google.javascript.jscomp.Instrumentation$Builder setReportCallBytes(com.google.protobuf.ByteString);
    Code:
       0: aload_1
       1: ifnonnull     12
       4: new           #65                 // class java/lang/NullPointerException
       7: dup
       8: invokespecial #66                 // Method java/lang/NullPointerException."<init>":()V
      11: athrow
      12: aload_0
      13: dup
      14: getfield      #22                 // Field bitField0_:I
      17: iconst_2
      18: ior
      19: putfield      #22                 // Field bitField0_:I
      22: aload_0
      23: aload_1
      24: putfield      #11                 // Field reportCall_:Ljava/lang/Object;
      27: aload_0
      28: invokevirtual #42                 // Method onChanged:()V
      31: aload_0
      32: areturn

  public boolean hasReportExit();
    Code:
       0: aload_0
       1: getfield      #22                 // Field bitField0_:I
       4: iconst_4
       5: iand
       6: iconst_4
       7: if_icmpne     14
      10: iconst_1
      11: goto          15
      14: iconst_0
      15: ireturn

  public java.lang.String getReportExit();
    Code:
       0: aload_0
       1: getfield      #12                 // Field reportExit_:Ljava/lang/Object;
       4: astore_1
       5: aload_1
       6: instanceof    #61                 // class java/lang/String
       9: ifne          27
      12: aload_1
      13: checkcast     #62                 // class com/google/protobuf/ByteString
      16: invokevirtual #63                 // Method com/google/protobuf/ByteString.toStringUtf8:()Ljava/lang/String;
      19: astore_2
      20: aload_0
      21: aload_2
      22: putfield      #12                 // Field reportExit_:Ljava/lang/Object;
      25: aload_2
      26: areturn
      27: aload_1
      28: checkcast     #61                 // class java/lang/String
      31: areturn

  public com.google.protobuf.ByteString getReportExitBytes();
    Code:
       0: aload_0
       1: getfield      #12                 // Field reportExit_:Ljava/lang/Object;
       4: astore_1
       5: aload_1
       6: instanceof    #61                 // class java/lang/String
       9: ifeq          27
      12: aload_1
      13: checkcast     #61                 // class java/lang/String
      16: invokestatic  #64                 // Method com/google/protobuf/ByteString.copyFromUtf8:(Ljava/lang/String;)Lcom/google/protobuf/ByteString;
      19: astore_2
      20: aload_0
      21: aload_2
      22: putfield      #12                 // Field reportExit_:Ljava/lang/Object;
      25: aload_2
      26: areturn
      27: aload_1
      28: checkcast     #62                 // class com/google/protobuf/ByteString
      31: areturn

  public com.google.javascript.jscomp.Instrumentation$Builder setReportExit(java.lang.String);
    Code:
       0: aload_1
       1: ifnonnull     12
       4: new           #65                 // class java/lang/NullPointerException
       7: dup
       8: invokespecial #66                 // Method java/lang/NullPointerException."<init>":()V
      11: athrow
      12: aload_0
      13: dup
      14: getfield      #22                 // Field bitField0_:I
      17: iconst_4
      18: ior
      19: putfield      #22                 // Field bitField0_:I
      22: aload_0
      23: aload_1
      24: putfield      #12                 // Field reportExit_:Ljava/lang/Object;
      27: aload_0
      28: invokevirtual #42                 // Method onChanged:()V
      31: aload_0
      32: areturn

  public com.google.javascript.jscomp.Instrumentation$Builder clearReportExit();
    Code:
       0: aload_0
       1: aload_0
       2: getfield      #22                 // Field bitField0_:I
       5: bipush        -5
       7: iand
       8: putfield      #22                 // Field bitField0_:I
      11: aload_0
      12: invokestatic  #25                 // Method com/google/javascript/jscomp/Instrumentation.getDefaultInstance:()Lcom/google/javascript/jscomp/Instrumentation;
      15: invokevirtual #69                 // Method com/google/javascript/jscomp/Instrumentation.getReportExit:()Ljava/lang/String;
      18: putfield      #12                 // Field reportExit_:Ljava/lang/Object;
      21: aload_0
      22: invokevirtual #42                 // Method onChanged:()V
      25: aload_0
      26: areturn

  public com.google.javascript.jscomp.Instrumentation$Builder setReportExitBytes(com.google.protobuf.ByteString);
    Code:
       0: aload_1
       1: ifnonnull     12
       4: new           #65                 // class java/lang/NullPointerException
       7: dup
       8: invokespecial #66                 // Method java/lang/NullPointerException."<init>":()V
      11: athrow
      12: aload_0
      13: dup
      14: getfield      #22                 // Field bitField0_:I
      17: iconst_4
      18: ior
      19: putfield      #22                 // Field bitField0_:I
      22: aload_0
      23: aload_1
      24: putfield      #12                 // Field reportExit_:Ljava/lang/Object;
      27: aload_0
      28: invokevirtual #42                 // Method onChanged:()V
      31: aload_0
      32: areturn

  private void ensureDeclarationToRemoveIsMutable();
    Code:
       0: aload_0
       1: getfield      #22                 // Field bitField0_:I
       4: bipush        8
       6: iand
       7: bipush        8
       9: if_icmpeq     38
      12: aload_0
      13: new           #70                 // class com/google/protobuf/LazyStringArrayList
      16: dup
      17: aload_0
      18: getfield      #14                 // Field declarationToRemove_:Lcom/google/protobuf/LazyStringList;
      21: invokespecial #71                 // Method com/google/protobuf/LazyStringArrayList."<init>":(Lcom/google/protobuf/LazyStringList;)V
      24: putfield      #14                 // Field declarationToRemove_:Lcom/google/protobuf/LazyStringList;
      27: aload_0
      28: dup
      29: getfield      #22                 // Field bitField0_:I
      32: bipush        8
      34: ior
      35: putfield      #22                 // Field bitField0_:I
      38: return

  public java.util.List<java.lang.String> getDeclarationToRemoveList();
    Code:
       0: aload_0
       1: getfield      #14                 // Field declarationToRemove_:Lcom/google/protobuf/LazyStringList;
       4: invokestatic  #72                 // Method java/util/Collections.unmodifiableList:(Ljava/util/List;)Ljava/util/List;
       7: areturn

  public int getDeclarationToRemoveCount();
    Code:
       0: aload_0
       1: getfield      #14                 // Field declarationToRemove_:Lcom/google/protobuf/LazyStringList;
       4: invokeinterface #73,  1           // InterfaceMethod com/google/protobuf/LazyStringList.size:()I
       9: ireturn

  public java.lang.String getDeclarationToRemove(int);
    Code:
       0: aload_0
       1: getfield      #14                 // Field declarationToRemove_:Lcom/google/protobuf/LazyStringList;
       4: iload_1
       5: invokeinterface #74,  2           // InterfaceMethod com/google/protobuf/LazyStringList.get:(I)Ljava/lang/Object;
      10: checkcast     #61                 // class java/lang/String
      13: areturn

  public com.google.protobuf.ByteString getDeclarationToRemoveBytes(int);
    Code:
       0: aload_0
       1: getfield      #14                 // Field declarationToRemove_:Lcom/google/protobuf/LazyStringList;
       4: iload_1
       5: invokeinterface #75,  2           // InterfaceMethod com/google/protobuf/LazyStringList.getByteString:(I)Lcom/google/protobuf/ByteString;
      10: areturn

  public com.google.javascript.jscomp.Instrumentation$Builder setDeclarationToRemove(int, java.lang.String);
    Code:
       0: aload_2
       1: ifnonnull     12
       4: new           #65                 // class java/lang/NullPointerException
       7: dup
       8: invokespecial #66                 // Method java/lang/NullPointerException."<init>":()V
      11: athrow
      12: aload_0
      13: invokespecial #49                 // Method ensureDeclarationToRemoveIsMutable:()V
      16: aload_0
      17: getfield      #14                 // Field declarationToRemove_:Lcom/google/protobuf/LazyStringList;
      20: iload_1
      21: aload_2
      22: invokeinterface #76,  3           // InterfaceMethod com/google/protobuf/LazyStringList.set:(ILjava/lang/Object;)Ljava/lang/Object;
      27: pop
      28: aload_0
      29: invokevirtual #42                 // Method onChanged:()V
      32: aload_0
      33: areturn

  public com.google.javascript.jscomp.Instrumentation$Builder addDeclarationToRemove(java.lang.String);
    Code:
       0: aload_1
       1: ifnonnull     12
       4: new           #65                 // class java/lang/NullPointerException
       7: dup
       8: invokespecial #66                 // Method java/lang/NullPointerException."<init>":()V
      11: athrow
      12: aload_0
      13: invokespecial #49                 // Method ensureDeclarationToRemoveIsMutable:()V
      16: aload_0
      17: getfield      #14                 // Field declarationToRemove_:Lcom/google/protobuf/LazyStringList;
      20: aload_1
      21: invokeinterface #77,  2           // InterfaceMethod com/google/protobuf/LazyStringList.add:(Ljava/lang/Object;)Z
      26: pop
      27: aload_0
      28: invokevirtual #42                 // Method onChanged:()V
      31: aload_0
      32: areturn

  public com.google.javascript.jscomp.Instrumentation$Builder addAllDeclarationToRemove(java.lang.Iterable<java.lang.String>);
    Code:
       0: aload_0
       1: invokespecial #49                 // Method ensureDeclarationToRemoveIsMutable:()V
       4: aload_1
       5: aload_0
       6: getfield      #14                 // Field declarationToRemove_:Lcom/google/protobuf/LazyStringList;
       9: invokestatic  #78                 // Method com/google/protobuf/GeneratedMessage$Builder.addAll:(Ljava/lang/Iterable;Ljava/util/Collection;)V
      12: aload_0
      13: invokevirtual #42                 // Method onChanged:()V
      16: aload_0
      17: areturn

  public com.google.javascript.jscomp.Instrumentation$Builder clearDeclarationToRemove();
    Code:
       0: aload_0
       1: getstatic     #13                 // Field com/google/protobuf/LazyStringArrayList.EMPTY:Lcom/google/protobuf/LazyStringList;
       4: putfield      #14                 // Field declarationToRemove_:Lcom/google/protobuf/LazyStringList;
       7: aload_0
       8: aload_0
       9: getfield      #22                 // Field bitField0_:I
      12: bipush        -9
      14: iand
      15: putfield      #22                 // Field bitField0_:I
      18: aload_0
      19: invokevirtual #42                 // Method onChanged:()V
      22: aload_0
      23: areturn

  public com.google.javascript.jscomp.Instrumentation$Builder addDeclarationToRemoveBytes(com.google.protobuf.ByteString);
    Code:
       0: aload_1
       1: ifnonnull     12
       4: new           #65                 // class java/lang/NullPointerException
       7: dup
       8: invokespecial #66                 // Method java/lang/NullPointerException."<init>":()V
      11: athrow
      12: aload_0
      13: invokespecial #49                 // Method ensureDeclarationToRemoveIsMutable:()V
      16: aload_0
      17: getfield      #14                 // Field declarationToRemove_:Lcom/google/protobuf/LazyStringList;
      20: aload_1
      21: invokeinterface #79,  2           // InterfaceMethod com/google/protobuf/LazyStringList.add:(Lcom/google/protobuf/ByteString;)V
      26: aload_0
      27: invokevirtual #42                 // Method onChanged:()V
      30: aload_0
      31: areturn

  private void ensureInitIsMutable();
    Code:
       0: aload_0
       1: getfield      #22                 // Field bitField0_:I
       4: bipush        16
       6: iand
       7: bipush        16
       9: if_icmpeq     38
      12: aload_0
      13: new           #70                 // class com/google/protobuf/LazyStringArrayList
      16: dup
      17: aload_0
      18: getfield      #15                 // Field init_:Lcom/google/protobuf/LazyStringList;
      21: invokespecial #71                 // Method com/google/protobuf/LazyStringArrayList."<init>":(Lcom/google/protobuf/LazyStringList;)V
      24: putfield      #15                 // Field init_:Lcom/google/protobuf/LazyStringList;
      27: aload_0
      28: dup
      29: getfield      #22                 // Field bitField0_:I
      32: bipush        16
      34: ior
      35: putfield      #22                 // Field bitField0_:I
      38: return

  public java.util.List<java.lang.String> getInitList();
    Code:
       0: aload_0
       1: getfield      #15                 // Field init_:Lcom/google/protobuf/LazyStringList;
       4: invokestatic  #72                 // Method java/util/Collections.unmodifiableList:(Ljava/util/List;)Ljava/util/List;
       7: areturn

  public int getInitCount();
    Code:
       0: aload_0
       1: getfield      #15                 // Field init_:Lcom/google/protobuf/LazyStringList;
       4: invokeinterface #73,  1           // InterfaceMethod com/google/protobuf/LazyStringList.size:()I
       9: ireturn

  public java.lang.String getInit(int);
    Code:
       0: aload_0
       1: getfield      #15                 // Field init_:Lcom/google/protobuf/LazyStringList;
       4: iload_1
       5: invokeinterface #74,  2           // InterfaceMethod com/google/protobuf/LazyStringList.get:(I)Ljava/lang/Object;
      10: checkcast     #61                 // class java/lang/String
      13: areturn

  public com.google.protobuf.ByteString getInitBytes(int);
    Code:
       0: aload_0
       1: getfield      #15                 // Field init_:Lcom/google/protobuf/LazyStringList;
       4: iload_1
       5: invokeinterface #75,  2           // InterfaceMethod com/google/protobuf/LazyStringList.getByteString:(I)Lcom/google/protobuf/ByteString;
      10: areturn

  public com.google.javascript.jscomp.Instrumentation$Builder setInit(int, java.lang.String);
    Code:
       0: aload_2
       1: ifnonnull     12
       4: new           #65                 // class java/lang/NullPointerException
       7: dup
       8: invokespecial #66                 // Method java/lang/NullPointerException."<init>":()V
      11: athrow
      12: aload_0
      13: invokespecial #52                 // Method ensureInitIsMutable:()V
      16: aload_0
      17: getfield      #15                 // Field init_:Lcom/google/protobuf/LazyStringList;
      20: iload_1
      21: aload_2
      22: invokeinterface #76,  3           // InterfaceMethod com/google/protobuf/LazyStringList.set:(ILjava/lang/Object;)Ljava/lang/Object;
      27: pop
      28: aload_0
      29: invokevirtual #42                 // Method onChanged:()V
      32: aload_0
      33: areturn

  public com.google.javascript.jscomp.Instrumentation$Builder addInit(java.lang.String);
    Code:
       0: aload_1
       1: ifnonnull     12
       4: new           #65                 // class java/lang/NullPointerException
       7: dup
       8: invokespecial #66                 // Method java/lang/NullPointerException."<init>":()V
      11: athrow
      12: aload_0
      13: invokespecial #52                 // Method ensureInitIsMutable:()V
      16: aload_0
      17: getfield      #15                 // Field init_:Lcom/google/protobuf/LazyStringList;
      20: aload_1
      21: invokeinterface #77,  2           // InterfaceMethod com/google/protobuf/LazyStringList.add:(Ljava/lang/Object;)Z
      26: pop
      27: aload_0
      28: invokevirtual #42                 // Method onChanged:()V
      31: aload_0
      32: areturn

  public com.google.javascript.jscomp.Instrumentation$Builder addAllInit(java.lang.Iterable<java.lang.String>);
    Code:
       0: aload_0
       1: invokespecial #52                 // Method ensureInitIsMutable:()V
       4: aload_1
       5: aload_0
       6: getfield      #15                 // Field init_:Lcom/google/protobuf/LazyStringList;
       9: invokestatic  #78                 // Method com/google/protobuf/GeneratedMessage$Builder.addAll:(Ljava/lang/Iterable;Ljava/util/Collection;)V
      12: aload_0
      13: invokevirtual #42                 // Method onChanged:()V
      16: aload_0
      17: areturn

  public com.google.javascript.jscomp.Instrumentation$Builder clearInit();
    Code:
       0: aload_0
       1: getstatic     #13                 // Field com/google/protobuf/LazyStringArrayList.EMPTY:Lcom/google/protobuf/LazyStringList;
       4: putfield      #15                 // Field init_:Lcom/google/protobuf/LazyStringList;
       7: aload_0
       8: aload_0
       9: getfield      #22                 // Field bitField0_:I
      12: bipush        -17
      14: iand
      15: putfield      #22                 // Field bitField0_:I
      18: aload_0
      19: invokevirtual #42                 // Method onChanged:()V
      22: aload_0
      23: areturn

  public com.google.javascript.jscomp.Instrumentation$Builder addInitBytes(com.google.protobuf.ByteString);
    Code:
       0: aload_1
       1: ifnonnull     12
       4: new           #65                 // class java/lang/NullPointerException
       7: dup
       8: invokespecial #66                 // Method java/lang/NullPointerException."<init>":()V
      11: athrow
      12: aload_0
      13: invokespecial #52                 // Method ensureInitIsMutable:()V
      16: aload_0
      17: getfield      #15                 // Field init_:Lcom/google/protobuf/LazyStringList;
      20: aload_1
      21: invokeinterface #79,  2           // InterfaceMethod com/google/protobuf/LazyStringList.add:(Lcom/google/protobuf/ByteString;)V
      26: aload_0
      27: invokevirtual #42                 // Method onChanged:()V
      30: aload_0
      31: areturn

  public boolean hasAppNameSetter();
    Code:
       0: aload_0
       1: getfield      #22                 // Field bitField0_:I
       4: bipush        32
       6: iand
       7: bipush        32
       9: if_icmpne     16
      12: iconst_1
      13: goto          17
      16: iconst_0
      17: ireturn

  public java.lang.String getAppNameSetter();
    Code:
       0: aload_0
       1: getfield      #16                 // Field appNameSetter_:Ljava/lang/Object;
       4: astore_1
       5: aload_1
       6: instanceof    #61                 // class java/lang/String
       9: ifne          27
      12: aload_1
      13: checkcast     #62                 // class com/google/protobuf/ByteString
      16: invokevirtual #63                 // Method com/google/protobuf/ByteString.toStringUtf8:()Ljava/lang/String;
      19: astore_2
      20: aload_0
      21: aload_2
      22: putfield      #16                 // Field appNameSetter_:Ljava/lang/Object;
      25: aload_2
      26: areturn
      27: aload_1
      28: checkcast     #61                 // class java/lang/String
      31: areturn

  public com.google.protobuf.ByteString getAppNameSetterBytes();
    Code:
       0: aload_0
       1: getfield      #16                 // Field appNameSetter_:Ljava/lang/Object;
       4: astore_1
       5: aload_1
       6: instanceof    #61                 // class java/lang/String
       9: ifeq          27
      12: aload_1
      13: checkcast     #61                 // class java/lang/String
      16: invokestatic  #64                 // Method com/google/protobuf/ByteString.copyFromUtf8:(Ljava/lang/String;)Lcom/google/protobuf/ByteString;
      19: astore_2
      20: aload_0
      21: aload_2
      22: putfield      #16                 // Field appNameSetter_:Ljava/lang/Object;
      25: aload_2
      26: areturn
      27: aload_1
      28: checkcast     #62                 // class com/google/protobuf/ByteString
      31: areturn

  public com.google.javascript.jscomp.Instrumentation$Builder setAppNameSetter(java.lang.String);
    Code:
       0: aload_1
       1: ifnonnull     12
       4: new           #65                 // class java/lang/NullPointerException
       7: dup
       8: invokespecial #66                 // Method java/lang/NullPointerException."<init>":()V
      11: athrow
      12: aload_0
      13: dup
      14: getfield      #22                 // Field bitField0_:I
      17: bipush        32
      19: ior
      20: putfield      #22                 // Field bitField0_:I
      23: aload_0
      24: aload_1
      25: putfield      #16                 // Field appNameSetter_:Ljava/lang/Object;
      28: aload_0
      29: invokevirtual #42                 // Method onChanged:()V
      32: aload_0
      33: areturn

  public com.google.javascript.jscomp.Instrumentation$Builder clearAppNameSetter();
    Code:
       0: aload_0
       1: aload_0
       2: getfield      #22                 // Field bitField0_:I
       5: bipush        -33
       7: iand
       8: putfield      #22                 // Field bitField0_:I
      11: aload_0
      12: invokestatic  #25                 // Method com/google/javascript/jscomp/Instrumentation.getDefaultInstance:()Lcom/google/javascript/jscomp/Instrumentation;
      15: invokevirtual #80                 // Method com/google/javascript/jscomp/Instrumentation.getAppNameSetter:()Ljava/lang/String;
      18: putfield      #16                 // Field appNameSetter_:Ljava/lang/Object;
      21: aload_0
      22: invokevirtual #42                 // Method onChanged:()V
      25: aload_0
      26: areturn

  public com.google.javascript.jscomp.Instrumentation$Builder setAppNameSetterBytes(com.google.protobuf.ByteString);
    Code:
       0: aload_1
       1: ifnonnull     12
       4: new           #65                 // class java/lang/NullPointerException
       7: dup
       8: invokespecial #66                 // Method java/lang/NullPointerException."<init>":()V
      11: athrow
      12: aload_0
      13: dup
      14: getfield      #22                 // Field bitField0_:I
      17: bipush        32
      19: ior
      20: putfield      #22                 // Field bitField0_:I
      23: aload_0
      24: aload_1
      25: putfield      #16                 // Field appNameSetter_:Ljava/lang/Object;
      28: aload_0
      29: invokevirtual #42                 // Method onChanged:()V
      32: aload_0
      33: areturn

  public com.google.protobuf.GeneratedMessage$Builder clear();
    Code:
       0: aload_0
       1: invokevirtual #81                 // Method clear:()Lcom/google/javascript/jscomp/Instrumentation$Builder;
       4: areturn

  public com.google.protobuf.GeneratedMessage$Builder clone();
    Code:
       0: aload_0
       1: invokevirtual #82                 // Method clone:()Lcom/google/javascript/jscomp/Instrumentation$Builder;
       4: areturn

  public com.google.protobuf.AbstractMessage$Builder mergeFrom(com.google.protobuf.CodedInputStream, com.google.protobuf.ExtensionRegistryLite) throws java.io.IOException;
    Code:
       0: aload_0
       1: aload_1
       2: aload_2
       3: invokevirtual #83                 // Method mergeFrom:(Lcom/google/protobuf/CodedInputStream;Lcom/google/protobuf/ExtensionRegistryLite;)Lcom/google/javascript/jscomp/Instrumentation$Builder;
       6: areturn

  public com.google.protobuf.AbstractMessage$Builder mergeFrom(com.google.protobuf.Message);
    Code:
       0: aload_0
       1: aload_1
       2: invokevirtual #84                 // Method mergeFrom:(Lcom/google/protobuf/Message;)Lcom/google/javascript/jscomp/Instrumentation$Builder;
       5: areturn

  public com.google.protobuf.AbstractMessage$Builder clear();
    Code:
       0: aload_0
       1: invokevirtual #81                 // Method clear:()Lcom/google/javascript/jscomp/Instrumentation$Builder;
       4: areturn

  public com.google.protobuf.AbstractMessage$Builder clone();
    Code:
       0: aload_0
       1: invokevirtual #82                 // Method clone:()Lcom/google/javascript/jscomp/Instrumentation$Builder;
       4: areturn

  public com.google.protobuf.Message$Builder mergeFrom(com.google.protobuf.CodedInputStream, com.google.protobuf.ExtensionRegistryLite) throws java.io.IOException;
    Code:
       0: aload_0
       1: aload_1
       2: aload_2
       3: invokevirtual #83                 // Method mergeFrom:(Lcom/google/protobuf/CodedInputStream;Lcom/google/protobuf/ExtensionRegistryLite;)Lcom/google/javascript/jscomp/Instrumentation$Builder;
       6: areturn

  public com.google.protobuf.Message$Builder clone();
    Code:
       0: aload_0
       1: invokevirtual #82                 // Method clone:()Lcom/google/javascript/jscomp/Instrumentation$Builder;
       4: areturn

  public com.google.protobuf.Message buildPartial();
    Code:
       0: aload_0
       1: invokevirtual #23                 // Method buildPartial:()Lcom/google/javascript/jscomp/Instrumentation;
       4: areturn

  public com.google.protobuf.Message build();
    Code:
       0: aload_0
       1: invokevirtual #85                 // Method build:()Lcom/google/javascript/jscomp/Instrumentation;
       4: areturn

  public com.google.protobuf.Message$Builder mergeFrom(com.google.protobuf.Message);
    Code:
       0: aload_0
       1: aload_1
       2: invokevirtual #84                 // Method mergeFrom:(Lcom/google/protobuf/Message;)Lcom/google/javascript/jscomp/Instrumentation$Builder;
       5: areturn

  public com.google.protobuf.Message$Builder clear();
    Code:
       0: aload_0
       1: invokevirtual #81                 // Method clear:()Lcom/google/javascript/jscomp/Instrumentation$Builder;
       4: areturn

  public com.google.protobuf.MessageLite$Builder mergeFrom(com.google.protobuf.CodedInputStream, com.google.protobuf.ExtensionRegistryLite) throws java.io.IOException;
    Code:
       0: aload_0
       1: aload_1
       2: aload_2
       3: invokevirtual #83                 // Method mergeFrom:(Lcom/google/protobuf/CodedInputStream;Lcom/google/protobuf/ExtensionRegistryLite;)Lcom/google/javascript/jscomp/Instrumentation$Builder;
       6: areturn

  public com.google.protobuf.MessageLite$Builder clone();
    Code:
       0: aload_0
       1: invokevirtual #82                 // Method clone:()Lcom/google/javascript/jscomp/Instrumentation$Builder;
       4: areturn

  public com.google.protobuf.MessageLite buildPartial();
    Code:
       0: aload_0
       1: invokevirtual #23                 // Method buildPartial:()Lcom/google/javascript/jscomp/Instrumentation;
       4: areturn

  public com.google.protobuf.MessageLite build();
    Code:
       0: aload_0
       1: invokevirtual #85                 // Method build:()Lcom/google/javascript/jscomp/Instrumentation;
       4: areturn

  public com.google.protobuf.MessageLite$Builder clear();
    Code:
       0: aload_0
       1: invokevirtual #81                 // Method clear:()Lcom/google/javascript/jscomp/Instrumentation$Builder;
       4: areturn

  public com.google.protobuf.MessageLite getDefaultInstanceForType();
    Code:
       0: aload_0
       1: invokevirtual #86                 // Method getDefaultInstanceForType:()Lcom/google/javascript/jscomp/Instrumentation;
       4: areturn

  public com.google.protobuf.Message getDefaultInstanceForType();
    Code:
       0: aload_0
       1: invokevirtual #86                 // Method getDefaultInstanceForType:()Lcom/google/javascript/jscomp/Instrumentation;
       4: areturn

  public com.google.protobuf.AbstractMessageLite$Builder mergeFrom(com.google.protobuf.CodedInputStream, com.google.protobuf.ExtensionRegistryLite) throws java.io.IOException;
    Code:
       0: aload_0
       1: aload_1
       2: aload_2
       3: invokevirtual #83                 // Method mergeFrom:(Lcom/google/protobuf/CodedInputStream;Lcom/google/protobuf/ExtensionRegistryLite;)Lcom/google/javascript/jscomp/Instrumentation$Builder;
       6: areturn

  public com.google.protobuf.AbstractMessageLite$Builder clone();
    Code:
       0: aload_0
       1: invokevirtual #82                 // Method clone:()Lcom/google/javascript/jscomp/Instrumentation$Builder;
       4: areturn

  public java.lang.Object clone() throws java.lang.CloneNotSupportedException;
    Code:
       0: aload_0
       1: invokevirtual #82                 // Method clone:()Lcom/google/javascript/jscomp/Instrumentation$Builder;
       4: areturn

  static com.google.javascript.jscomp.Instrumentation$Builder access$100();
    Code:
       0: invokestatic  #2                  // Method create:()Lcom/google/javascript/jscomp/Instrumentation$Builder;
       3: areturn

  com.google.javascript.jscomp.Instrumentation$Builder(com.google.protobuf.GeneratedMessage$BuilderParent, com.google.javascript.jscomp.Instrumentation$1);
    Code:
       0: aload_0
       1: aload_1
       2: invokespecial #1                  // Method "<init>":(Lcom/google/protobuf/GeneratedMessage$BuilderParent;)V
       5: return
}
