Compiled from "MakeDeclaredNamesUnique.java"
class com.google.javascript.jscomp.MakeDeclaredNamesUnique$WhitelistedRenamer implements com.google.javascript.jscomp.MakeDeclaredNamesUnique$Renamer {
  private com.google.javascript.jscomp.MakeDeclaredNamesUnique$Renamer delegate;

  private java.util.Set<java.lang.String> whitelist;

  com.google.javascript.jscomp.MakeDeclaredNamesUnique$WhitelistedRenamer(com.google.javascript.jscomp.MakeDeclaredNamesUnique$Renamer, java.util.Set<java.lang.String>);
    Code:
       0: aload_0
       1: invokespecial #1                  // Method java/lang/Object."<init>":()V
       4: aload_0
       5: aload_1
       6: putfield      #2                  // Field delegate:Lcom/google/javascript/jscomp/MakeDeclaredNamesUnique$Renamer;
       9: aload_0
      10: aload_2
      11: putfield      #3                  // Field whitelist:Ljava/util/Set;
      14: return

  public void addDeclaredName(java.lang.String);
    Code:
       0: aload_0
       1: getfield      #3                  // Field whitelist:Ljava/util/Set;
       4: aload_1
       5: invokeinterface #4,  2            // InterfaceMethod java/util/Set.contains:(Ljava/lang/Object;)Z
      10: ifeq          23
      13: aload_0
      14: getfield      #2                  // Field delegate:Lcom/google/javascript/jscomp/MakeDeclaredNamesUnique$Renamer;
      17: aload_1
      18: invokeinterface #5,  2            // InterfaceMethod com/google/javascript/jscomp/MakeDeclaredNamesUnique$Renamer.addDeclaredName:(Ljava/lang/String;)V
      23: return

  public java.lang.String getReplacementName(java.lang.String);
    Code:
       0: aload_0
       1: getfield      #3                  // Field whitelist:Ljava/util/Set;
       4: aload_1
       5: invokeinterface #4,  2            // InterfaceMethod java/util/Set.contains:(Ljava/lang/Object;)Z
      10: ifeq          26
      13: aload_0
      14: getfield      #2                  // Field delegate:Lcom/google/javascript/jscomp/MakeDeclaredNamesUnique$Renamer;
      17: aload_1
      18: invokeinterface #6,  2            // InterfaceMethod com/google/javascript/jscomp/MakeDeclaredNamesUnique$Renamer.getReplacementName:(Ljava/lang/String;)Ljava/lang/String;
      23: goto          27
      26: aconst_null
      27: areturn

  public boolean stripConstIfReplaced();
    Code:
       0: aload_0
       1: getfield      #2                  // Field delegate:Lcom/google/javascript/jscomp/MakeDeclaredNamesUnique$Renamer;
       4: invokeinterface #7,  1            // InterfaceMethod com/google/javascript/jscomp/MakeDeclaredNamesUnique$Renamer.stripConstIfReplaced:()Z
       9: ireturn

  public com.google.javascript.jscomp.MakeDeclaredNamesUnique$Renamer forChildScope();
    Code:
       0: new           #8                  // class com/google/javascript/jscomp/MakeDeclaredNamesUnique$WhitelistedRenamer
       3: dup
       4: aload_0
       5: getfield      #2                  // Field delegate:Lcom/google/javascript/jscomp/MakeDeclaredNamesUnique$Renamer;
       8: invokeinterface #9,  1            // InterfaceMethod com/google/javascript/jscomp/MakeDeclaredNamesUnique$Renamer.forChildScope:()Lcom/google/javascript/jscomp/MakeDeclaredNamesUnique$Renamer;
      13: aload_0
      14: getfield      #3                  // Field whitelist:Ljava/util/Set;
      17: invokespecial #10                 // Method "<init>":(Lcom/google/javascript/jscomp/MakeDeclaredNamesUnique$Renamer;Ljava/util/Set;)V
      20: areturn
}
