Compiled from "MarkNoSideEffectCalls.java"
class com.google.javascript.jscomp.MarkNoSideEffectCalls implements com.google.javascript.jscomp.CompilerPass {
  static final com.google.javascript.jscomp.DiagnosticType INVALID_NO_SIDE_EFFECT_ANNOTATION;

  private final com.google.javascript.jscomp.AbstractCompiler compiler;

  private final java.util.Set<com.google.javascript.rhino.Node> noSideEffectFunctionNames;

  com.google.javascript.jscomp.MarkNoSideEffectCalls(com.google.javascript.jscomp.AbstractCompiler);
    Code:
       0: aload_0
       1: invokespecial #4                  // Method java/lang/Object."<init>":()V
       4: aload_0
       5: aload_1
       6: putfield      #5                  // Field compiler:Lcom/google/javascript/jscomp/AbstractCompiler;
       9: aload_0
      10: invokestatic  #6                  // Method com/google/common/collect/Sets.newHashSet:()Ljava/util/HashSet;
      13: putfield      #2                  // Field noSideEffectFunctionNames:Ljava/util/Set;
      16: return

  public void process(com.google.javascript.rhino.Node, com.google.javascript.rhino.Node);
    Code:
       0: new           #7                  // class com/google/javascript/jscomp/SimpleDefinitionFinder
       3: dup
       4: aload_0
       5: getfield      #5                  // Field compiler:Lcom/google/javascript/jscomp/AbstractCompiler;
       8: invokespecial #8                  // Method com/google/javascript/jscomp/SimpleDefinitionFinder."<init>":(Lcom/google/javascript/jscomp/AbstractCompiler;)V
      11: astore_3
      12: aload_3
      13: aload_1
      14: aload_2
      15: invokevirtual #9                  // Method com/google/javascript/jscomp/SimpleDefinitionFinder.process:(Lcom/google/javascript/rhino/Node;Lcom/google/javascript/rhino/Node;)V
      18: aload_0
      19: getfield      #5                  // Field compiler:Lcom/google/javascript/jscomp/AbstractCompiler;
      22: aload_1
      23: new           #10                 // class com/google/javascript/jscomp/MarkNoSideEffectCalls$GatherNoSideEffectFunctions
      26: dup
      27: aload_0
      28: iconst_1
      29: invokespecial #11                 // Method com/google/javascript/jscomp/MarkNoSideEffectCalls$GatherNoSideEffectFunctions."<init>":(Lcom/google/javascript/jscomp/MarkNoSideEffectCalls;Z)V
      32: invokestatic  #12                 // Method com/google/javascript/jscomp/NodeTraversal.traverse:(Lcom/google/javascript/jscomp/AbstractCompiler;Lcom/google/javascript/rhino/Node;Lcom/google/javascript/jscomp/NodeTraversal$Callback;)V
      35: aload_0
      36: getfield      #5                  // Field compiler:Lcom/google/javascript/jscomp/AbstractCompiler;
      39: aload_2
      40: new           #10                 // class com/google/javascript/jscomp/MarkNoSideEffectCalls$GatherNoSideEffectFunctions
      43: dup
      44: aload_0
      45: iconst_0
      46: invokespecial #11                 // Method com/google/javascript/jscomp/MarkNoSideEffectCalls$GatherNoSideEffectFunctions."<init>":(Lcom/google/javascript/jscomp/MarkNoSideEffectCalls;Z)V
      49: invokestatic  #12                 // Method com/google/javascript/jscomp/NodeTraversal.traverse:(Lcom/google/javascript/jscomp/AbstractCompiler;Lcom/google/javascript/rhino/Node;Lcom/google/javascript/jscomp/NodeTraversal$Callback;)V
      52: aload_0
      53: getfield      #5                  // Field compiler:Lcom/google/javascript/jscomp/AbstractCompiler;
      56: aload_2
      57: new           #13                 // class com/google/javascript/jscomp/MarkNoSideEffectCalls$SetNoSideEffectCallProperty
      60: dup
      61: aload_0
      62: aload_3
      63: invokespecial #14                 // Method com/google/javascript/jscomp/MarkNoSideEffectCalls$SetNoSideEffectCallProperty."<init>":(Lcom/google/javascript/jscomp/MarkNoSideEffectCalls;Lcom/google/javascript/jscomp/SimpleDefinitionFinder;)V
      66: invokestatic  #12                 // Method com/google/javascript/jscomp/NodeTraversal.traverse:(Lcom/google/javascript/jscomp/AbstractCompiler;Lcom/google/javascript/rhino/Node;Lcom/google/javascript/jscomp/NodeTraversal$Callback;)V
      69: return

  private static boolean definitionTypeContainsFunctionType(com.google.javascript.jscomp.DefinitionsRemover$Definition);
    Code:
       0: aload_0
       1: invokevirtual #15                 // Method com/google/javascript/jscomp/DefinitionsRemover$Definition.getRValue:()Lcom/google/javascript/rhino/Node;
       4: astore_1
       5: aload_1
       6: ifnonnull     11
       9: iconst_1
      10: ireturn
      11: aload_1
      12: invokevirtual #16                 // Method com/google/javascript/rhino/Node.getType:()I
      15: lookupswitch  { // 10
                    30: 104
                    33: 104
                    35: 104
                    37: 104
                    38: 104
                    86: 104
                    98: 104
                   100: 104
                   101: 104
                   105: 104
               default: 106
          }
     104: iconst_1
     105: ireturn
     106: iconst_0
     107: ireturn

  private static boolean hasNoSideEffectsAnnotation(com.google.javascript.rhino.Node);
    Code:
       0: aload_0
       1: invokevirtual #17                 // Method com/google/javascript/rhino/Node.getJSDocInfo:()Lcom/google/javascript/rhino/JSDocInfo;
       4: astore_1
       5: aload_1
       6: ifnull        20
       9: aload_1
      10: invokevirtual #18                 // Method com/google/javascript/rhino/JSDocInfo.isNoSideEffects:()Z
      13: ifeq          20
      16: iconst_1
      17: goto          21
      20: iconst_0
      21: ireturn

  static boolean access$000(com.google.javascript.rhino.Node);
    Code:
       0: aload_0
       1: invokestatic  #3                  // Method hasNoSideEffectsAnnotation:(Lcom/google/javascript/rhino/Node;)Z
       4: ireturn

  static java.util.Set access$100(com.google.javascript.jscomp.MarkNoSideEffectCalls);
    Code:
       0: aload_0
       1: getfield      #2                  // Field noSideEffectFunctionNames:Ljava/util/Set;
       4: areturn

  static boolean access$200(com.google.javascript.jscomp.DefinitionsRemover$Definition);
    Code:
       0: aload_0
       1: invokestatic  #1                  // Method definitionTypeContainsFunctionType:(Lcom/google/javascript/jscomp/DefinitionsRemover$Definition;)Z
       4: ireturn

  static {};
    Code:
       0: ldc           #19                 // String JSC_INVALID_NO_SIDE_EFFECT_ANNOTATION
       2: ldc           #20                 // String @nosideeffects may only appear in externs files.
       4: invokestatic  #21                 // Method com/google/javascript/jscomp/DiagnosticType.error:(Ljava/lang/String;Ljava/lang/String;)Lcom/google/javascript/jscomp/DiagnosticType;
       7: putstatic     #22                 // Field INVALID_NO_SIDE_EFFECT_ANNOTATION:Lcom/google/javascript/jscomp/DiagnosticType;
      10: return
}
