Compiled from "NodeTraversal.java"
public abstract class com.google.javascript.jscomp.NodeTraversal$AbstractNodeTypePruningCallback implements com.google.javascript.jscomp.NodeTraversal$Callback {
  private final java.util.Set<java.lang.Integer> nodeTypes;

  private final boolean include;

  public com.google.javascript.jscomp.NodeTraversal$AbstractNodeTypePruningCallback(java.util.Set<java.lang.Integer>);
    Code:
       0: aload_0
       1: aload_1
       2: iconst_1
       3: invokespecial #1                  // Method "<init>":(Ljava/util/Set;Z)V
       6: return

  public com.google.javascript.jscomp.NodeTraversal$AbstractNodeTypePruningCallback(java.util.Set<java.lang.Integer>, boolean);
    Code:
       0: aload_0
       1: invokespecial #2                  // Method java/lang/Object."<init>":()V
       4: aload_0
       5: aload_1
       6: putfield      #3                  // Field nodeTypes:Ljava/util/Set;
       9: aload_0
      10: iload_2
      11: putfield      #4                  // Field include:Z
      14: return

  public boolean shouldTraverse(com.google.javascript.jscomp.NodeTraversal, com.google.javascript.rhino.Node, com.google.javascript.rhino.Node);
    Code:
       0: aload_0
       1: getfield      #4                  // Field include:Z
       4: aload_0
       5: getfield      #3                  // Field nodeTypes:Ljava/util/Set;
       8: aload_2
       9: invokevirtual #5                  // Method com/google/javascript/rhino/Node.getType:()I
      12: invokestatic  #6                  // Method java/lang/Integer.valueOf:(I)Ljava/lang/Integer;
      15: invokeinterface #7,  2            // InterfaceMethod java/util/Set.contains:(Ljava/lang/Object;)Z
      20: if_icmpne     27
      23: iconst_1
      24: goto          28
      27: iconst_0
      28: ireturn
}
