Compiled from "PerformanceTracker.java"
class com.google.javascript.jscomp.PerformanceTracker$1 implements java.util.Comparator<java.util.Map$Entry<java.lang.String, com.google.javascript.jscomp.PerformanceTracker$Stats>> {
  final com.google.javascript.jscomp.PerformanceTracker this$0;

  com.google.javascript.jscomp.PerformanceTracker$1(com.google.javascript.jscomp.PerformanceTracker);
    Code:
       0: aload_0
       1: aload_1
       2: putfield      #1                  // Field this$0:Lcom/google/javascript/jscomp/PerformanceTracker;
       5: aload_0
       6: invokespecial #2                  // Method java/lang/Object."<init>":()V
       9: return

  public int compare(java.util.Map$Entry<java.lang.String, com.google.javascript.jscomp.PerformanceTracker$Stats>, java.util.Map$Entry<java.lang.String, com.google.javascript.jscomp.PerformanceTracker$Stats>);
    Code:
       0: aload_1
       1: invokeinterface #3,  1            // InterfaceMethod java/util/Map$Entry.getValue:()Ljava/lang/Object;
       6: checkcast     #4                  // class com/google/javascript/jscomp/PerformanceTracker$Stats
       9: getfield      #5                  // Field com/google/javascript/jscomp/PerformanceTracker$Stats.runtime:J
      12: aload_2
      13: invokeinterface #3,  1            // InterfaceMethod java/util/Map$Entry.getValue:()Ljava/lang/Object;
      18: checkcast     #4                  // class com/google/javascript/jscomp/PerformanceTracker$Stats
      21: getfield      #5                  // Field com/google/javascript/jscomp/PerformanceTracker$Stats.runtime:J
      24: lsub
      25: l2i
      26: ireturn

  public int compare(java.lang.Object, java.lang.Object);
    Code:
       0: aload_0
       1: aload_1
       2: checkcast     #6                  // class java/util/Map$Entry
       5: aload_2
       6: checkcast     #6                  // class java/util/Map$Entry
       9: invokevirtual #7                  // Method compare:(Ljava/util/Map$Entry;Ljava/util/Map$Entry;)I
      12: ireturn
}
