Compiled from "ProcessDefines.java"
final class com.google.javascript.jscomp.ProcessDefines$CollectDefines implements com.google.javascript.jscomp.NodeTraversal$Callback {
  private final com.google.javascript.jscomp.AbstractCompiler compiler;

  private final java.util.Map<java.lang.String, com.google.javascript.jscomp.ProcessDefines$DefineInfo> assignableDefines;

  private final java.util.Map<java.lang.String, com.google.javascript.jscomp.ProcessDefines$DefineInfo> allDefines;

  private final java.util.Map<com.google.javascript.rhino.Node, com.google.javascript.jscomp.ProcessDefines$CollectDefines$RefInfo> allRefInfo;

  private com.google.javascript.rhino.Node lvalueToRemoveLater;

  private final java.util.Deque<java.lang.Integer> assignAllowed;

  com.google.javascript.jscomp.ProcessDefines$CollectDefines(com.google.javascript.jscomp.AbstractCompiler, java.util.List<com.google.javascript.jscomp.GlobalNamespace$Name>);
    Code:
       0: aload_0
       1: invokespecial #1                  // Method java/lang/Object."<init>":()V
       4: aload_0
       5: aconst_null
       6: putfield      #2                  // Field lvalueToRemoveLater:Lcom/google/javascript/rhino/Node;
       9: aload_0
      10: aload_1
      11: putfield      #3                  // Field compiler:Lcom/google/javascript/jscomp/AbstractCompiler;
      14: aload_0
      15: invokestatic  #4                  // Method com/google/common/collect/Maps.newHashMap:()Ljava/util/HashMap;
      18: putfield      #5                  // Field allDefines:Ljava/util/Map;
      21: aload_0
      22: invokestatic  #4                  // Method com/google/common/collect/Maps.newHashMap:()Ljava/util/HashMap;
      25: putfield      #6                  // Field assignableDefines:Ljava/util/Map;
      28: aload_0
      29: new           #7                  // class java/util/ArrayDeque
      32: dup
      33: invokespecial #8                  // Method java/util/ArrayDeque."<init>":()V
      36: putfield      #9                  // Field assignAllowed:Ljava/util/Deque;
      39: aload_0
      40: getfield      #9                  // Field assignAllowed:Ljava/util/Deque;
      43: iconst_1
      44: invokestatic  #10                 // Method java/lang/Integer.valueOf:(I)Ljava/lang/Integer;
      47: invokeinterface #11,  2           // InterfaceMethod java/util/Deque.push:(Ljava/lang/Object;)V
      52: aload_0
      53: invokestatic  #4                  // Method com/google/common/collect/Maps.newHashMap:()Ljava/util/HashMap;
      56: putfield      #12                 // Field allRefInfo:Ljava/util/Map;
      59: aload_2
      60: invokeinterface #13,  1           // InterfaceMethod java/util/List.iterator:()Ljava/util/Iterator;
      65: astore_3
      66: aload_3
      67: invokeinterface #14,  1           // InterfaceMethod java/util/Iterator.hasNext:()Z
      72: ifeq          219
      75: aload_3
      76: invokeinterface #15,  1           // InterfaceMethod java/util/Iterator.next:()Ljava/lang/Object;
      81: checkcast     #16                 // class com/google/javascript/jscomp/GlobalNamespace$Name
      84: astore        4
      86: aload         4
      88: invokevirtual #17                 // Method com/google/javascript/jscomp/GlobalNamespace$Name.getDeclaration:()Lcom/google/javascript/jscomp/GlobalNamespace$Ref;
      91: astore        5
      93: aload         5
      95: ifnull        124
      98: aload_0
      99: getfield      #12                 // Field allRefInfo:Ljava/util/Map;
     102: aload         5
     104: getfield      #18                 // Field com/google/javascript/jscomp/GlobalNamespace$Ref.node:Lcom/google/javascript/rhino/Node;
     107: new           #19                 // class com/google/javascript/jscomp/ProcessDefines$CollectDefines$RefInfo
     110: dup
     111: aload         5
     113: aload         4
     115: invokespecial #20                 // Method com/google/javascript/jscomp/ProcessDefines$CollectDefines$RefInfo."<init>":(Lcom/google/javascript/jscomp/GlobalNamespace$Ref;Lcom/google/javascript/jscomp/GlobalNamespace$Name;)V
     118: invokeinterface #21,  3           // InterfaceMethod java/util/Map.put:(Ljava/lang/Object;Ljava/lang/Object;)Ljava/lang/Object;
     123: pop
     124: aload         4
     126: invokevirtual #22                 // Method com/google/javascript/jscomp/GlobalNamespace$Name.getRefs:()Ljava/util/List;
     129: invokeinterface #13,  1           // InterfaceMethod java/util/List.iterator:()Ljava/util/Iterator;
     134: astore        6
     136: aload         6
     138: invokeinterface #14,  1           // InterfaceMethod java/util/Iterator.hasNext:()Z
     143: ifeq          216
     146: aload         6
     148: invokeinterface #15,  1           // InterfaceMethod java/util/Iterator.next:()Ljava/lang/Object;
     153: checkcast     #23                 // class com/google/javascript/jscomp/GlobalNamespace$Ref
     156: astore        7
     158: aload         7
     160: aload         5
     162: if_acmpne     168
     165: goto          136
     168: aload         7
     170: invokevirtual #24                 // Method com/google/javascript/jscomp/GlobalNamespace$Ref.getTwin:()Lcom/google/javascript/jscomp/GlobalNamespace$Ref;
     173: ifnull        187
     176: aload         7
     178: invokevirtual #24                 // Method com/google/javascript/jscomp/GlobalNamespace$Ref.getTwin:()Lcom/google/javascript/jscomp/GlobalNamespace$Ref;
     181: invokevirtual #25                 // Method com/google/javascript/jscomp/GlobalNamespace$Ref.isSet:()Z
     184: ifne          213
     187: aload_0
     188: getfield      #12                 // Field allRefInfo:Ljava/util/Map;
     191: aload         7
     193: getfield      #18                 // Field com/google/javascript/jscomp/GlobalNamespace$Ref.node:Lcom/google/javascript/rhino/Node;
     196: new           #19                 // class com/google/javascript/jscomp/ProcessDefines$CollectDefines$RefInfo
     199: dup
     200: aload         7
     202: aload         4
     204: invokespecial #20                 // Method com/google/javascript/jscomp/ProcessDefines$CollectDefines$RefInfo."<init>":(Lcom/google/javascript/jscomp/GlobalNamespace$Ref;Lcom/google/javascript/jscomp/GlobalNamespace$Name;)V
     207: invokeinterface #21,  3           // InterfaceMethod java/util/Map.put:(Ljava/lang/Object;Ljava/lang/Object;)Ljava/lang/Object;
     212: pop
     213: goto          136
     216: goto          66
     219: return

  java.util.Map<java.lang.String, com.google.javascript.jscomp.ProcessDefines$DefineInfo> getAllDefines();
    Code:
       0: aload_0
       1: getfield      #5                  // Field allDefines:Ljava/util/Map;
       4: areturn

  public boolean shouldTraverse(com.google.javascript.jscomp.NodeTraversal, com.google.javascript.rhino.Node, com.google.javascript.rhino.Node);
    Code:
       0: aload_0
       1: aload_2
       2: iconst_1
       3: invokespecial #26                 // Method updateAssignAllowedStack:(Lcom/google/javascript/rhino/Node;Z)V
       6: iconst_1
       7: ireturn

  public void visit(com.google.javascript.jscomp.NodeTraversal, com.google.javascript.rhino.Node, com.google.javascript.rhino.Node);
    Code:
       0: aload_0
       1: getfield      #12                 // Field allRefInfo:Ljava/util/Map;
       4: aload_2
       5: invokeinterface #27,  2           // InterfaceMethod java/util/Map.get:(Ljava/lang/Object;)Ljava/lang/Object;
      10: checkcast     #19                 // class com/google/javascript/jscomp/ProcessDefines$CollectDefines$RefInfo
      13: astore        4
      15: aload         4
      17: ifnull        227
      20: aload         4
      22: getfield      #28                 // Field com/google/javascript/jscomp/ProcessDefines$CollectDefines$RefInfo.ref:Lcom/google/javascript/jscomp/GlobalNamespace$Ref;
      25: astore        5
      27: aload         4
      29: getfield      #29                 // Field com/google/javascript/jscomp/ProcessDefines$CollectDefines$RefInfo.name:Lcom/google/javascript/jscomp/GlobalNamespace$Name;
      32: astore        6
      34: aload         6
      36: invokevirtual #30                 // Method com/google/javascript/jscomp/GlobalNamespace$Name.getFullName:()Ljava/lang/String;
      39: astore        7
      41: getstatic     #31                 // Field com/google/javascript/jscomp/ProcessDefines$1.$SwitchMap$com$google$javascript$jscomp$GlobalNamespace$Ref$Type:[I
      44: aload         5
      46: getfield      #32                 // Field com/google/javascript/jscomp/GlobalNamespace$Ref.type:Lcom/google/javascript/jscomp/GlobalNamespace$Ref$Type;
      49: invokevirtual #33                 // Method com/google/javascript/jscomp/GlobalNamespace$Ref$Type.ordinal:()I
      52: iaload
      53: lookupswitch  { // 2
                     1: 80
                     2: 80
               default: 181
          }
      80: aload         5
      82: invokestatic  #34                 // Method getValueParent:(Lcom/google/javascript/jscomp/GlobalNamespace$Ref;)Lcom/google/javascript/rhino/Node;
      85: astore        8
      87: aload         8
      89: invokevirtual #35                 // Method com/google/javascript/rhino/Node.getLastChild:()Lcom/google/javascript/rhino/Node;
      92: astore        9
      94: aload         8
      96: invokevirtual #36                 // Method com/google/javascript/rhino/Node.isAssign:()Z
      99: ifeq          148
     102: aload         6
     104: invokevirtual #37                 // Method com/google/javascript/jscomp/GlobalNamespace$Name.isSimpleName:()Z
     107: ifeq          148
     110: aload         6
     112: invokevirtual #17                 // Method com/google/javascript/jscomp/GlobalNamespace$Name.getDeclaration:()Lcom/google/javascript/jscomp/GlobalNamespace$Ref;
     115: aload         5
     117: if_acmpne     148
     120: aload_0
     121: getfield      #3                  // Field compiler:Lcom/google/javascript/jscomp/AbstractCompiler;
     124: aload_1
     125: aload         9
     127: getstatic     #38                 // Field com/google/javascript/jscomp/ProcessDefines.INVALID_DEFINE_INIT_ERROR:Lcom/google/javascript/jscomp/DiagnosticType;
     130: iconst_1
     131: anewarray     #39                 // class java/lang/String
     134: dup
     135: iconst_0
     136: aload         7
     138: aastore
     139: invokevirtual #40                 // Method com/google/javascript/jscomp/NodeTraversal.makeError:(Lcom/google/javascript/rhino/Node;Lcom/google/javascript/jscomp/DiagnosticType;[Ljava/lang/String;)Lcom/google/javascript/jscomp/JSError;
     142: invokevirtual #41                 // Method com/google/javascript/jscomp/AbstractCompiler.report:(Lcom/google/javascript/jscomp/JSError;)V
     145: goto          227
     148: aload_0
     149: aload_1
     150: aload         7
     152: aload         9
     154: aload         8
     156: invokespecial #42                 // Method processDefineAssignment:(Lcom/google/javascript/jscomp/NodeTraversal;Ljava/lang/String;Lcom/google/javascript/rhino/Node;Lcom/google/javascript/rhino/Node;)Z
     159: ifeq          227
     162: aload         4
     164: getfield      #29                 // Field com/google/javascript/jscomp/ProcessDefines$CollectDefines$RefInfo.name:Lcom/google/javascript/jscomp/GlobalNamespace$Name;
     167: aload         5
     169: invokevirtual #43                 // Method com/google/javascript/jscomp/GlobalNamespace$Name.removeRef:(Lcom/google/javascript/jscomp/GlobalNamespace$Ref;)V
     172: aload_0
     173: aload         8
     175: putfield      #2                  // Field lvalueToRemoveLater:Lcom/google/javascript/rhino/Node;
     178: goto          227
     181: aload_1
     182: invokevirtual #44                 // Method com/google/javascript/jscomp/NodeTraversal.inGlobalScope:()Z
     185: ifeq          227
     188: aload_0
     189: getfield      #6                  // Field assignableDefines:Ljava/util/Map;
     192: aload         7
     194: invokeinterface #27,  2           // InterfaceMethod java/util/Map.get:(Ljava/lang/Object;)Ljava/lang/Object;
     199: checkcast     #45                 // class com/google/javascript/jscomp/ProcessDefines$DefineInfo
     202: astore        10
     204: aload         10
     206: ifnull        227
     209: aload         10
     211: aload_1
     212: invokestatic  #46                 // Method setDefineInfoNotAssignable:(Lcom/google/javascript/jscomp/ProcessDefines$DefineInfo;Lcom/google/javascript/jscomp/NodeTraversal;)V
     215: aload_0
     216: getfield      #6                  // Field assignableDefines:Ljava/util/Map;
     219: aload         7
     221: invokeinterface #47,  2           // InterfaceMethod java/util/Map.remove:(Ljava/lang/Object;)Ljava/lang/Object;
     226: pop
     227: aload_1
     228: invokevirtual #44                 // Method com/google/javascript/jscomp/NodeTraversal.inGlobalScope:()Z
     231: ifne          275
     234: aload_2
     235: invokevirtual #48                 // Method com/google/javascript/rhino/Node.getJSDocInfo:()Lcom/google/javascript/rhino/JSDocInfo;
     238: ifnull        275
     241: aload_2
     242: invokevirtual #48                 // Method com/google/javascript/rhino/Node.getJSDocInfo:()Lcom/google/javascript/rhino/JSDocInfo;
     245: invokevirtual #49                 // Method com/google/javascript/rhino/JSDocInfo.isDefine:()Z
     248: ifeq          275
     251: aload_0
     252: getfield      #3                  // Field compiler:Lcom/google/javascript/jscomp/AbstractCompiler;
     255: aload_1
     256: aload_2
     257: getstatic     #50                 // Field com/google/javascript/jscomp/ProcessDefines.NON_GLOBAL_DEFINE_INIT_ERROR:Lcom/google/javascript/jscomp/DiagnosticType;
     260: iconst_1
     261: anewarray     #39                 // class java/lang/String
     264: dup
     265: iconst_0
     266: ldc           #51                 // String
     268: aastore
     269: invokevirtual #40                 // Method com/google/javascript/jscomp/NodeTraversal.makeError:(Lcom/google/javascript/rhino/Node;Lcom/google/javascript/jscomp/DiagnosticType;[Ljava/lang/String;)Lcom/google/javascript/jscomp/JSError;
     272: invokevirtual #41                 // Method com/google/javascript/jscomp/AbstractCompiler.report:(Lcom/google/javascript/jscomp/JSError;)V
     275: aload_0
     276: getfield      #2                  // Field lvalueToRemoveLater:Lcom/google/javascript/rhino/Node;
     279: aload_2
     280: if_acmpne     339
     283: aload_0
     284: aconst_null
     285: putfield      #2                  // Field lvalueToRemoveLater:Lcom/google/javascript/rhino/Node;
     288: aload_2
     289: invokevirtual #36                 // Method com/google/javascript/rhino/Node.isAssign:()Z
     292: ifeq          317
     295: aload_2
     296: invokevirtual #35                 // Method com/google/javascript/rhino/Node.getLastChild:()Lcom/google/javascript/rhino/Node;
     299: astore        5
     301: aload_2
     302: aload         5
     304: invokevirtual #52                 // Method com/google/javascript/rhino/Node.removeChild:(Lcom/google/javascript/rhino/Node;)V
     307: aload_3
     308: aload_2
     309: aload         5
     311: invokevirtual #53                 // Method com/google/javascript/rhino/Node.replaceChild:(Lcom/google/javascript/rhino/Node;Lcom/google/javascript/rhino/Node;)V
     314: goto          332
     317: aload_2
     318: invokevirtual #54                 // Method com/google/javascript/rhino/Node.isName:()Z
     321: invokestatic  #55                 // Method com/google/common/base/Preconditions.checkState:(Z)V
     324: aload_2
     325: aload_2
     326: invokevirtual #56                 // Method com/google/javascript/rhino/Node.getFirstChild:()Lcom/google/javascript/rhino/Node;
     329: invokevirtual #52                 // Method com/google/javascript/rhino/Node.removeChild:(Lcom/google/javascript/rhino/Node;)V
     332: aload_0
     333: getfield      #3                  // Field compiler:Lcom/google/javascript/jscomp/AbstractCompiler;
     336: invokevirtual #57                 // Method com/google/javascript/jscomp/AbstractCompiler.reportCodeChange:()V
     339: aload_2
     340: invokevirtual #58                 // Method com/google/javascript/rhino/Node.isCall:()Z
     343: ifeq          409
     346: aload_1
     347: invokevirtual #44                 // Method com/google/javascript/jscomp/NodeTraversal.inGlobalScope:()Z
     350: ifeq          409
     353: aload_0
     354: getfield      #6                  // Field assignableDefines:Ljava/util/Map;
     357: invokeinterface #59,  1           // InterfaceMethod java/util/Map.values:()Ljava/util/Collection;
     362: invokeinterface #60,  1           // InterfaceMethod java/util/Collection.iterator:()Ljava/util/Iterator;
     367: astore        5
     369: aload         5
     371: invokeinterface #14,  1           // InterfaceMethod java/util/Iterator.hasNext:()Z
     376: ifeq          400
     379: aload         5
     381: invokeinterface #15,  1           // InterfaceMethod java/util/Iterator.next:()Ljava/lang/Object;
     386: checkcast     #45                 // class com/google/javascript/jscomp/ProcessDefines$DefineInfo
     389: astore        6
     391: aload         6
     393: aload_1
     394: invokestatic  #46                 // Method setDefineInfoNotAssignable:(Lcom/google/javascript/jscomp/ProcessDefines$DefineInfo;Lcom/google/javascript/jscomp/NodeTraversal;)V
     397: goto          369
     400: aload_0
     401: getfield      #6                  // Field assignableDefines:Ljava/util/Map;
     404: invokeinterface #61,  1           // InterfaceMethod java/util/Map.clear:()V
     409: aload_0
     410: aload_2
     411: iconst_0
     412: invokespecial #26                 // Method updateAssignAllowedStack:(Lcom/google/javascript/rhino/Node;Z)V
     415: return

  private void updateAssignAllowedStack(com.google.javascript.rhino.Node, boolean);
    Code:
       0: aload_1
       1: invokevirtual #62                 // Method com/google/javascript/rhino/Node.getType:()I
       4: tableswitch   { // 98 to 115
                    98: 92
                    99: 122
                   100: 122
                   101: 122
                   102: 122
                   103: 122
                   104: 122
                   105: 92
                   106: 122
                   107: 122
                   108: 92
                   109: 122
                   110: 92
                   111: 92
                   112: 122
                   113: 92
                   114: 122
                   115: 92
               default: 122
          }
      92: iload_2
      93: ifeq          112
      96: aload_0
      97: getfield      #9                  // Field assignAllowed:Ljava/util/Deque;
     100: iconst_0
     101: invokestatic  #10                 // Method java/lang/Integer.valueOf:(I)Ljava/lang/Integer;
     104: invokeinterface #11,  2           // InterfaceMethod java/util/Deque.push:(Ljava/lang/Object;)V
     109: goto          122
     112: aload_0
     113: getfield      #9                  // Field assignAllowed:Ljava/util/Deque;
     116: invokeinterface #63,  1           // InterfaceMethod java/util/Deque.remove:()Ljava/lang/Object;
     121: pop
     122: return

  private boolean isAssignAllowed();
    Code:
       0: aload_0
       1: getfield      #9                  // Field assignAllowed:Ljava/util/Deque;
       4: invokeinterface #64,  1           // InterfaceMethod java/util/Deque.element:()Ljava/lang/Object;
       9: checkcast     #65                 // class java/lang/Integer
      12: invokevirtual #66                 // Method java/lang/Integer.intValue:()I
      15: iconst_1
      16: if_icmpne     23
      19: iconst_1
      20: goto          24
      23: iconst_0
      24: ireturn

  private boolean processDefineAssignment(com.google.javascript.jscomp.NodeTraversal, java.lang.String, com.google.javascript.rhino.Node, com.google.javascript.rhino.Node);
    Code:
       0: aload_3
       1: ifnull        20
       4: aload_3
       5: aload_0
       6: getfield      #5                  // Field allDefines:Ljava/util/Map;
       9: invokeinterface #67,  1           // InterfaceMethod java/util/Map.keySet:()Ljava/util/Set;
      14: invokestatic  #68                 // Method com/google/javascript/jscomp/NodeUtil.isValidDefineValue:(Lcom/google/javascript/rhino/Node;Ljava/util/Set;)Z
      17: ifne          46
      20: aload_0
      21: getfield      #3                  // Field compiler:Lcom/google/javascript/jscomp/AbstractCompiler;
      24: aload_1
      25: aload_3
      26: getstatic     #38                 // Field com/google/javascript/jscomp/ProcessDefines.INVALID_DEFINE_INIT_ERROR:Lcom/google/javascript/jscomp/DiagnosticType;
      29: iconst_1
      30: anewarray     #39                 // class java/lang/String
      33: dup
      34: iconst_0
      35: aload_2
      36: aastore
      37: invokevirtual #40                 // Method com/google/javascript/jscomp/NodeTraversal.makeError:(Lcom/google/javascript/rhino/Node;Lcom/google/javascript/jscomp/DiagnosticType;[Ljava/lang/String;)Lcom/google/javascript/jscomp/JSError;
      40: invokevirtual #41                 // Method com/google/javascript/jscomp/AbstractCompiler.report:(Lcom/google/javascript/jscomp/JSError;)V
      43: goto          184
      46: aload_0
      47: invokespecial #69                 // Method isAssignAllowed:()Z
      50: ifne          80
      53: aload_0
      54: getfield      #3                  // Field compiler:Lcom/google/javascript/jscomp/AbstractCompiler;
      57: aload_1
      58: aload         4
      60: getstatic     #50                 // Field com/google/javascript/jscomp/ProcessDefines.NON_GLOBAL_DEFINE_INIT_ERROR:Lcom/google/javascript/jscomp/DiagnosticType;
      63: iconst_1
      64: anewarray     #39                 // class java/lang/String
      67: dup
      68: iconst_0
      69: aload_2
      70: aastore
      71: invokevirtual #40                 // Method com/google/javascript/jscomp/NodeTraversal.makeError:(Lcom/google/javascript/rhino/Node;Lcom/google/javascript/jscomp/DiagnosticType;[Ljava/lang/String;)Lcom/google/javascript/jscomp/JSError;
      74: invokevirtual #41                 // Method com/google/javascript/jscomp/AbstractCompiler.report:(Lcom/google/javascript/jscomp/JSError;)V
      77: goto          184
      80: aload_0
      81: getfield      #5                  // Field allDefines:Ljava/util/Map;
      84: aload_2
      85: invokeinterface #27,  2           // InterfaceMethod java/util/Map.get:(Ljava/lang/Object;)Ljava/lang/Object;
      90: checkcast     #45                 // class com/google/javascript/jscomp/ProcessDefines$DefineInfo
      93: astore        5
      95: aload         5
      97: ifnonnull     141
     100: new           #45                 // class com/google/javascript/jscomp/ProcessDefines$DefineInfo
     103: dup
     104: aload_3
     105: aload         4
     107: invokespecial #70                 // Method com/google/javascript/jscomp/ProcessDefines$DefineInfo."<init>":(Lcom/google/javascript/rhino/Node;Lcom/google/javascript/rhino/Node;)V
     110: astore        5
     112: aload_0
     113: getfield      #5                  // Field allDefines:Ljava/util/Map;
     116: aload_2
     117: aload         5
     119: invokeinterface #21,  3           // InterfaceMethod java/util/Map.put:(Ljava/lang/Object;Ljava/lang/Object;)Ljava/lang/Object;
     124: pop
     125: aload_0
     126: getfield      #6                  // Field assignableDefines:Ljava/util/Map;
     129: aload_2
     130: aload         5
     132: invokeinterface #21,  3           // InterfaceMethod java/util/Map.put:(Ljava/lang/Object;Ljava/lang/Object;)Ljava/lang/Object;
     137: pop
     138: goto          184
     141: aload         5
     143: aload_3
     144: invokevirtual #71                 // Method com/google/javascript/jscomp/ProcessDefines$DefineInfo.recordAssignment:(Lcom/google/javascript/rhino/Node;)Z
     147: ifeq          152
     150: iconst_1
     151: ireturn
     152: aload_0
     153: getfield      #3                  // Field compiler:Lcom/google/javascript/jscomp/AbstractCompiler;
     156: aload_1
     157: aload         4
     159: getstatic     #72                 // Field com/google/javascript/jscomp/ProcessDefines.DEFINE_NOT_ASSIGNABLE_ERROR:Lcom/google/javascript/jscomp/DiagnosticType;
     162: iconst_2
     163: anewarray     #39                 // class java/lang/String
     166: dup
     167: iconst_0
     168: aload_2
     169: aastore
     170: dup
     171: iconst_1
     172: aload         5
     174: invokevirtual #73                 // Method com/google/javascript/jscomp/ProcessDefines$DefineInfo.getReasonWhyNotAssignable:()Ljava/lang/String;
     177: aastore
     178: invokevirtual #40                 // Method com/google/javascript/jscomp/NodeTraversal.makeError:(Lcom/google/javascript/rhino/Node;Lcom/google/javascript/jscomp/DiagnosticType;[Ljava/lang/String;)Lcom/google/javascript/jscomp/JSError;
     181: invokevirtual #41                 // Method com/google/javascript/jscomp/AbstractCompiler.report:(Lcom/google/javascript/jscomp/JSError;)V
     184: iconst_0
     185: ireturn

  private static com.google.javascript.rhino.Node getValueParent(com.google.javascript.jscomp.GlobalNamespace$Ref);
    Code:
       0: aload_0
       1: getfield      #18                 // Field com/google/javascript/jscomp/GlobalNamespace$Ref.node:Lcom/google/javascript/rhino/Node;
       4: invokevirtual #74                 // Method com/google/javascript/rhino/Node.getParent:()Lcom/google/javascript/rhino/Node;
       7: ifnull        30
      10: aload_0
      11: getfield      #18                 // Field com/google/javascript/jscomp/GlobalNamespace$Ref.node:Lcom/google/javascript/rhino/Node;
      14: invokevirtual #74                 // Method com/google/javascript/rhino/Node.getParent:()Lcom/google/javascript/rhino/Node;
      17: invokevirtual #75                 // Method com/google/javascript/rhino/Node.isVar:()Z
      20: ifeq          30
      23: aload_0
      24: getfield      #18                 // Field com/google/javascript/jscomp/GlobalNamespace$Ref.node:Lcom/google/javascript/rhino/Node;
      27: goto          37
      30: aload_0
      31: getfield      #18                 // Field com/google/javascript/jscomp/GlobalNamespace$Ref.node:Lcom/google/javascript/rhino/Node;
      34: invokevirtual #74                 // Method com/google/javascript/rhino/Node.getParent:()Lcom/google/javascript/rhino/Node;
      37: areturn

  private static void setDefineInfoNotAssignable(com.google.javascript.jscomp.ProcessDefines$DefineInfo, com.google.javascript.jscomp.NodeTraversal);
    Code:
       0: aload_0
       1: invokestatic  #76                 // Method com/google/javascript/jscomp/ProcessDefines.access$000:()Ljava/text/MessageFormat;
       4: iconst_2
       5: anewarray     #77                 // class java/lang/Object
       8: dup
       9: iconst_0
      10: aload_1
      11: invokevirtual #78                 // Method com/google/javascript/jscomp/NodeTraversal.getLineNumber:()I
      14: invokestatic  #10                 // Method java/lang/Integer.valueOf:(I)Ljava/lang/Integer;
      17: aastore
      18: dup
      19: iconst_1
      20: aload_1
      21: invokevirtual #79                 // Method com/google/javascript/jscomp/NodeTraversal.getSourceName:()Ljava/lang/String;
      24: aastore
      25: invokestatic  #80                 // Method com/google/javascript/jscomp/ProcessDefines.access$100:(Ljava/text/MessageFormat;[Ljava/lang/Object;)Ljava/lang/String;
      28: invokevirtual #81                 // Method com/google/javascript/jscomp/ProcessDefines$DefineInfo.setNotAssignable:(Ljava/lang/String;)V
      31: return
}
