Compiled from "ProcessClosurePrimitives.java"
class com.google.javascript.jscomp.ProcessClosurePrimitives$ProvidedName {
  private final java.lang.String namespace;

  private final com.google.javascript.rhino.Node firstNode;

  private final com.google.javascript.jscomp.JSModule firstModule;

  private com.google.javascript.rhino.Node explicitNode;

  private com.google.javascript.jscomp.JSModule explicitModule;

  private com.google.javascript.rhino.Node candidateDefinition;

  private com.google.javascript.jscomp.JSModule minimumModule;

  private com.google.javascript.rhino.Node replacementNode;

  final com.google.javascript.jscomp.ProcessClosurePrimitives this$0;

  com.google.javascript.jscomp.ProcessClosurePrimitives$ProvidedName(com.google.javascript.jscomp.ProcessClosurePrimitives, java.lang.String, com.google.javascript.rhino.Node, com.google.javascript.jscomp.JSModule, boolean);
    Code:
       0: aload_0
       1: aload_1
       2: putfield      #3                  // Field this$0:Lcom/google/javascript/jscomp/ProcessClosurePrimitives;
       5: aload_0
       6: invokespecial #4                  // Method java/lang/Object."<init>":()V
       9: aload_0
      10: aconst_null
      11: putfield      #5                  // Field explicitNode:Lcom/google/javascript/rhino/Node;
      14: aload_0
      15: aconst_null
      16: putfield      #1                  // Field explicitModule:Lcom/google/javascript/jscomp/JSModule;
      19: aload_0
      20: aconst_null
      21: putfield      #6                  // Field candidateDefinition:Lcom/google/javascript/rhino/Node;
      24: aload_0
      25: aconst_null
      26: putfield      #7                  // Field minimumModule:Lcom/google/javascript/jscomp/JSModule;
      29: aload_0
      30: aconst_null
      31: putfield      #8                  // Field replacementNode:Lcom/google/javascript/rhino/Node;
      34: aload_3
      35: ifnull        45
      38: aload_3
      39: invokevirtual #9                  // Method com/google/javascript/rhino/Node.isExprResult:()Z
      42: ifeq          49
      45: iconst_1
      46: goto          50
      49: iconst_0
      50: invokestatic  #10                 // Method com/google/common/base/Preconditions.checkArgument:(Z)V
      53: aload_0
      54: aload_2
      55: putfield      #11                 // Field namespace:Ljava/lang/String;
      58: aload_0
      59: aload_3
      60: putfield      #2                  // Field firstNode:Lcom/google/javascript/rhino/Node;
      63: aload_0
      64: aload         4
      66: putfield      #12                 // Field firstModule:Lcom/google/javascript/jscomp/JSModule;
      69: aload_0
      70: aload_3
      71: aload         4
      73: iload         5
      75: invokevirtual #13                 // Method addProvide:(Lcom/google/javascript/rhino/Node;Lcom/google/javascript/jscomp/JSModule;Z)V
      78: return

  void addProvide(com.google.javascript.rhino.Node, com.google.javascript.jscomp.JSModule, boolean);
    Code:
       0: iload_3
       1: ifeq          36
       4: aload_0
       5: getfield      #5                  // Field explicitNode:Lcom/google/javascript/rhino/Node;
       8: ifnonnull     15
      11: iconst_1
      12: goto          16
      15: iconst_0
      16: invokestatic  #14                 // Method com/google/common/base/Preconditions.checkState:(Z)V
      19: aload_1
      20: invokevirtual #9                  // Method com/google/javascript/rhino/Node.isExprResult:()Z
      23: invokestatic  #10                 // Method com/google/common/base/Preconditions.checkArgument:(Z)V
      26: aload_0
      27: aload_1
      28: putfield      #5                  // Field explicitNode:Lcom/google/javascript/rhino/Node;
      31: aload_0
      32: aload_2
      33: putfield      #1                  // Field explicitModule:Lcom/google/javascript/jscomp/JSModule;
      36: aload_0
      37: aload_2
      38: invokespecial #15                 // Method updateMinimumModule:(Lcom/google/javascript/jscomp/JSModule;)V
      41: return

  boolean isExplicitlyProvided();
    Code:
       0: aload_0
       1: getfield      #5                  // Field explicitNode:Lcom/google/javascript/rhino/Node;
       4: ifnull        11
       7: iconst_1
       8: goto          12
      11: iconst_0
      12: ireturn

  void addDefinition(com.google.javascript.rhino.Node, com.google.javascript.jscomp.JSModule);
    Code:
       0: aload_1
       1: invokevirtual #9                  // Method com/google/javascript/rhino/Node.isExprResult:()Z
       4: ifne          21
       7: aload_1
       8: invokevirtual #16                 // Method com/google/javascript/rhino/Node.isFunction:()Z
      11: ifne          21
      14: aload_1
      15: invokevirtual #17                 // Method com/google/javascript/rhino/Node.isVar:()Z
      18: ifeq          25
      21: iconst_1
      22: goto          26
      25: iconst_0
      26: invokestatic  #10                 // Method com/google/common/base/Preconditions.checkArgument:(Z)V
      29: aload_0
      30: getfield      #5                  // Field explicitNode:Lcom/google/javascript/rhino/Node;
      33: aload_1
      34: if_acmpeq     41
      37: iconst_1
      38: goto          42
      41: iconst_0
      42: invokestatic  #10                 // Method com/google/common/base/Preconditions.checkArgument:(Z)V
      45: aload_0
      46: getfield      #6                  // Field candidateDefinition:Lcom/google/javascript/rhino/Node;
      49: ifnull        59
      52: aload_1
      53: invokevirtual #9                  // Method com/google/javascript/rhino/Node.isExprResult:()Z
      56: ifne          69
      59: aload_0
      60: aload_1
      61: putfield      #6                  // Field candidateDefinition:Lcom/google/javascript/rhino/Node;
      64: aload_0
      65: aload_2
      66: invokespecial #15                 // Method updateMinimumModule:(Lcom/google/javascript/jscomp/JSModule;)V
      69: return

  private void updateMinimumModule(com.google.javascript.jscomp.JSModule);
    Code:
       0: aload_0
       1: getfield      #7                  // Field minimumModule:Lcom/google/javascript/jscomp/JSModule;
       4: ifnonnull     15
       7: aload_0
       8: aload_1
       9: putfield      #7                  // Field minimumModule:Lcom/google/javascript/jscomp/JSModule;
      12: goto          65
      15: aload_0
      16: getfield      #3                  // Field this$0:Lcom/google/javascript/jscomp/ProcessClosurePrimitives;
      19: invokestatic  #18                 // Method com/google/javascript/jscomp/ProcessClosurePrimitives.access$200:(Lcom/google/javascript/jscomp/ProcessClosurePrimitives;)Lcom/google/javascript/jscomp/JSModuleGraph;
      22: ifnull        47
      25: aload_0
      26: aload_0
      27: getfield      #3                  // Field this$0:Lcom/google/javascript/jscomp/ProcessClosurePrimitives;
      30: invokestatic  #18                 // Method com/google/javascript/jscomp/ProcessClosurePrimitives.access$200:(Lcom/google/javascript/jscomp/ProcessClosurePrimitives;)Lcom/google/javascript/jscomp/JSModuleGraph;
      33: aload_0
      34: getfield      #7                  // Field minimumModule:Lcom/google/javascript/jscomp/JSModule;
      37: aload_1
      38: invokevirtual #19                 // Method com/google/javascript/jscomp/JSModuleGraph.getDeepestCommonDependencyInclusive:(Lcom/google/javascript/jscomp/JSModule;Lcom/google/javascript/jscomp/JSModule;)Lcom/google/javascript/jscomp/JSModule;
      41: putfield      #7                  // Field minimumModule:Lcom/google/javascript/jscomp/JSModule;
      44: goto          65
      47: aload_1
      48: aload_0
      49: getfield      #7                  // Field minimumModule:Lcom/google/javascript/jscomp/JSModule;
      52: if_acmpne     59
      55: iconst_1
      56: goto          60
      59: iconst_0
      60: ldc           #20                 // String Missing module graph
      62: invokestatic  #21                 // Method com/google/common/base/Preconditions.checkState:(ZLjava/lang/Object;)V
      65: return

  void replace();
    Code:
       0: aload_0
       1: getfield      #2                  // Field firstNode:Lcom/google/javascript/rhino/Node;
       4: ifnonnull     16
       7: aload_0
       8: aload_0
       9: getfield      #6                  // Field candidateDefinition:Lcom/google/javascript/rhino/Node;
      12: putfield      #8                  // Field replacementNode:Lcom/google/javascript/rhino/Node;
      15: return
      16: aload_0
      17: getfield      #6                  // Field candidateDefinition:Lcom/google/javascript/rhino/Node;
      20: ifnull        309
      23: aload_0
      24: getfield      #5                  // Field explicitNode:Lcom/google/javascript/rhino/Node;
      27: ifnull        309
      30: aload_0
      31: getfield      #5                  // Field explicitNode:Lcom/google/javascript/rhino/Node;
      34: invokevirtual #22                 // Method com/google/javascript/rhino/Node.detachFromParent:()Lcom/google/javascript/rhino/Node;
      37: pop
      38: aload_0
      39: getfield      #3                  // Field this$0:Lcom/google/javascript/jscomp/ProcessClosurePrimitives;
      42: invokestatic  #23                 // Method com/google/javascript/jscomp/ProcessClosurePrimitives.access$300:(Lcom/google/javascript/jscomp/ProcessClosurePrimitives;)Lcom/google/javascript/jscomp/AbstractCompiler;
      45: invokevirtual #24                 // Method com/google/javascript/jscomp/AbstractCompiler.reportCodeChange:()V
      48: aload_0
      49: getfield      #6                  // Field candidateDefinition:Lcom/google/javascript/rhino/Node;
      52: invokevirtual #9                  // Method com/google/javascript/rhino/Node.isExprResult:()Z
      55: ifeq          72
      58: aload_0
      59: getfield      #6                  // Field candidateDefinition:Lcom/google/javascript/rhino/Node;
      62: invokevirtual #25                 // Method com/google/javascript/rhino/Node.getFirstChild:()Lcom/google/javascript/rhino/Node;
      65: invokevirtual #26                 // Method com/google/javascript/rhino/Node.getJSDocInfo:()Lcom/google/javascript/rhino/JSDocInfo;
      68: astore_1
      69: goto          80
      72: aload_0
      73: getfield      #6                  // Field candidateDefinition:Lcom/google/javascript/rhino/Node;
      76: invokevirtual #26                 // Method com/google/javascript/rhino/Node.getJSDocInfo:()Lcom/google/javascript/rhino/JSDocInfo;
      79: astore_1
      80: aload_1
      81: ifnull        165
      84: aload_1
      85: invokevirtual #27                 // Method com/google/javascript/rhino/JSDocInfo.getType:()Lcom/google/javascript/rhino/JSTypeExpression;
      88: astore_2
      89: aload_2
      90: ifnull        165
      93: aload_2
      94: invokevirtual #28                 // Method com/google/javascript/rhino/JSTypeExpression.getRoot:()Lcom/google/javascript/rhino/Node;
      97: astore_3
      98: aload_3
      99: invokevirtual #29                 // Method com/google/javascript/rhino/Node.getType:()I
     102: sipush        306
     105: if_icmpne     113
     108: aload_3
     109: invokevirtual #25                 // Method com/google/javascript/rhino/Node.getFirstChild:()Lcom/google/javascript/rhino/Node;
     112: astore_3
     113: aload_3
     114: invokevirtual #29                 // Method com/google/javascript/rhino/Node.getType:()I
     117: bipush        40
     119: if_icmpne     165
     122: aload_3
     123: invokevirtual #31                 // Method com/google/javascript/rhino/Node.hasChildren:()Z
     126: ifne          165
     129: aload_3
     130: invokevirtual #32                 // Method com/google/javascript/rhino/Node.getString:()Ljava/lang/String;
     133: ldc           #33                 // String Object
     135: invokevirtual #34                 // Method java/lang/String.equals:(Ljava/lang/Object;)Z
     138: ifeq          165
     141: aload_0
     142: getfield      #3                  // Field this$0:Lcom/google/javascript/jscomp/ProcessClosurePrimitives;
     145: invokestatic  #23                 // Method com/google/javascript/jscomp/ProcessClosurePrimitives.access$300:(Lcom/google/javascript/jscomp/ProcessClosurePrimitives;)Lcom/google/javascript/jscomp/AbstractCompiler;
     148: aload_0
     149: getfield      #6                  // Field candidateDefinition:Lcom/google/javascript/rhino/Node;
     152: getstatic     #35                 // Field com/google/javascript/jscomp/ProcessClosurePrimitives.WEAK_NAMESPACE_TYPE:Lcom/google/javascript/jscomp/DiagnosticType;
     155: iconst_0
     156: anewarray     #36                 // class java/lang/String
     159: invokestatic  #37                 // Method com/google/javascript/jscomp/JSError.make:(Lcom/google/javascript/rhino/Node;Lcom/google/javascript/jscomp/DiagnosticType;[Ljava/lang/String;)Lcom/google/javascript/jscomp/JSError;
     162: invokevirtual #38                 // Method com/google/javascript/jscomp/AbstractCompiler.report:(Lcom/google/javascript/jscomp/JSError;)V
     165: aload_0
     166: aload_0
     167: getfield      #6                  // Field candidateDefinition:Lcom/google/javascript/rhino/Node;
     170: putfield      #8                  // Field replacementNode:Lcom/google/javascript/rhino/Node;
     173: aload_0
     174: getfield      #6                  // Field candidateDefinition:Lcom/google/javascript/rhino/Node;
     177: invokevirtual #9                  // Method com/google/javascript/rhino/Node.isExprResult:()Z
     180: ifeq          306
     183: aload_0
     184: getfield      #6                  // Field candidateDefinition:Lcom/google/javascript/rhino/Node;
     187: invokevirtual #25                 // Method com/google/javascript/rhino/Node.getFirstChild:()Lcom/google/javascript/rhino/Node;
     190: invokevirtual #39                 // Method com/google/javascript/rhino/Node.isQualifiedName:()Z
     193: ifne          306
     196: aload_0
     197: getfield      #6                  // Field candidateDefinition:Lcom/google/javascript/rhino/Node;
     200: bipush        46
     202: iconst_1
     203: invokevirtual #41                 // Method com/google/javascript/rhino/Node.putBooleanProp:(IZ)V
     206: aload_0
     207: getfield      #6                  // Field candidateDefinition:Lcom/google/javascript/rhino/Node;
     210: invokevirtual #25                 // Method com/google/javascript/rhino/Node.getFirstChild:()Lcom/google/javascript/rhino/Node;
     213: astore_2
     214: aload_2
     215: invokevirtual #25                 // Method com/google/javascript/rhino/Node.getFirstChild:()Lcom/google/javascript/rhino/Node;
     218: astore_3
     219: aload_3
     220: invokevirtual #42                 // Method com/google/javascript/rhino/Node.isName:()Z
     223: ifeq          306
     226: aload_3
     227: invokevirtual #43                 // Method com/google/javascript/rhino/Node.getNext:()Lcom/google/javascript/rhino/Node;
     230: astore        4
     232: aload_2
     233: aload_3
     234: invokevirtual #44                 // Method com/google/javascript/rhino/Node.removeChild:(Lcom/google/javascript/rhino/Node;)V
     237: aload_2
     238: aload         4
     240: invokevirtual #44                 // Method com/google/javascript/rhino/Node.removeChild:(Lcom/google/javascript/rhino/Node;)V
     243: aload_3
     244: aload         4
     246: invokevirtual #45                 // Method com/google/javascript/rhino/Node.addChildToFront:(Lcom/google/javascript/rhino/Node;)V
     249: aload_3
     250: invokestatic  #46                 // Method com/google/javascript/rhino/IR.var:(Lcom/google/javascript/rhino/Node;)Lcom/google/javascript/rhino/Node;
     253: astore        5
     255: aload         5
     257: aload_0
     258: getfield      #6                  // Field candidateDefinition:Lcom/google/javascript/rhino/Node;
     261: invokevirtual #47                 // Method com/google/javascript/rhino/Node.copyInformationFrom:(Lcom/google/javascript/rhino/Node;)Lcom/google/javascript/rhino/Node;
     264: pop
     265: aload_0
     266: getfield      #6                  // Field candidateDefinition:Lcom/google/javascript/rhino/Node;
     269: invokevirtual #48                 // Method com/google/javascript/rhino/Node.getParent:()Lcom/google/javascript/rhino/Node;
     272: aload_0
     273: getfield      #6                  // Field candidateDefinition:Lcom/google/javascript/rhino/Node;
     276: aload         5
     278: invokevirtual #49                 // Method com/google/javascript/rhino/Node.replaceChild:(Lcom/google/javascript/rhino/Node;Lcom/google/javascript/rhino/Node;)V
     281: aload_3
     282: aload_2
     283: invokevirtual #26                 // Method com/google/javascript/rhino/Node.getJSDocInfo:()Lcom/google/javascript/rhino/JSDocInfo;
     286: invokevirtual #50                 // Method com/google/javascript/rhino/Node.setJSDocInfo:(Lcom/google/javascript/rhino/JSDocInfo;)Lcom/google/javascript/rhino/Node;
     289: pop
     290: aload_0
     291: getfield      #3                  // Field this$0:Lcom/google/javascript/jscomp/ProcessClosurePrimitives;
     294: invokestatic  #23                 // Method com/google/javascript/jscomp/ProcessClosurePrimitives.access$300:(Lcom/google/javascript/jscomp/ProcessClosurePrimitives;)Lcom/google/javascript/jscomp/AbstractCompiler;
     297: invokevirtual #24                 // Method com/google/javascript/jscomp/AbstractCompiler.reportCodeChange:()V
     300: aload_0
     301: aload         5
     303: putfield      #8                  // Field replacementNode:Lcom/google/javascript/rhino/Node;
     306: goto          469
     309: aload_0
     310: aload_0
     311: invokespecial #51                 // Method createDeclarationNode:()Lcom/google/javascript/rhino/Node;
     314: putfield      #8                  // Field replacementNode:Lcom/google/javascript/rhino/Node;
     317: aload_0
     318: getfield      #12                 // Field firstModule:Lcom/google/javascript/jscomp/JSModule;
     321: aload_0
     322: getfield      #7                  // Field minimumModule:Lcom/google/javascript/jscomp/JSModule;
     325: if_acmpne     349
     328: aload_0
     329: getfield      #2                  // Field firstNode:Lcom/google/javascript/rhino/Node;
     332: invokevirtual #48                 // Method com/google/javascript/rhino/Node.getParent:()Lcom/google/javascript/rhino/Node;
     335: aload_0
     336: getfield      #8                  // Field replacementNode:Lcom/google/javascript/rhino/Node;
     339: aload_0
     340: getfield      #2                  // Field firstNode:Lcom/google/javascript/rhino/Node;
     343: invokevirtual #52                 // Method com/google/javascript/rhino/Node.addChildBefore:(Lcom/google/javascript/rhino/Node;Lcom/google/javascript/rhino/Node;)V
     346: goto          444
     349: aload_0
     350: getfield      #11                 // Field namespace:Ljava/lang/String;
     353: bipush        46
     355: invokevirtual #53                 // Method java/lang/String.lastIndexOf:(I)I
     358: istore_1
     359: iload_1
     360: iconst_m1
     361: if_icmpne     388
     364: aload_0
     365: getfield      #3                  // Field this$0:Lcom/google/javascript/jscomp/ProcessClosurePrimitives;
     368: invokestatic  #23                 // Method com/google/javascript/jscomp/ProcessClosurePrimitives.access$300:(Lcom/google/javascript/jscomp/ProcessClosurePrimitives;)Lcom/google/javascript/jscomp/AbstractCompiler;
     371: aload_0
     372: getfield      #7                  // Field minimumModule:Lcom/google/javascript/jscomp/JSModule;
     375: invokevirtual #54                 // Method com/google/javascript/jscomp/AbstractCompiler.getNodeForCodeInsertion:(Lcom/google/javascript/jscomp/JSModule;)Lcom/google/javascript/rhino/Node;
     378: aload_0
     379: getfield      #8                  // Field replacementNode:Lcom/google/javascript/rhino/Node;
     382: invokevirtual #55                 // Method com/google/javascript/rhino/Node.addChildToBack:(Lcom/google/javascript/rhino/Node;)V
     385: goto          444
     388: aload_0
     389: getfield      #3                  // Field this$0:Lcom/google/javascript/jscomp/ProcessClosurePrimitives;
     392: invokestatic  #56                 // Method com/google/javascript/jscomp/ProcessClosurePrimitives.access$400:(Lcom/google/javascript/jscomp/ProcessClosurePrimitives;)Ljava/util/Map;
     395: aload_0
     396: getfield      #11                 // Field namespace:Ljava/lang/String;
     399: iconst_0
     400: iload_1
     401: invokevirtual #57                 // Method java/lang/String.substring:(II)Ljava/lang/String;
     404: invokeinterface #58,  2           // InterfaceMethod java/util/Map.get:(Ljava/lang/Object;)Ljava/lang/Object;
     409: checkcast     #59                 // class com/google/javascript/jscomp/ProcessClosurePrimitives$ProvidedName
     412: astore_2
     413: aload_2
     414: invokestatic  #60                 // Method com/google/common/base/Preconditions.checkNotNull:(Ljava/lang/Object;)Ljava/lang/Object;
     417: pop
     418: aload_2
     419: getfield      #8                  // Field replacementNode:Lcom/google/javascript/rhino/Node;
     422: invokestatic  #60                 // Method com/google/common/base/Preconditions.checkNotNull:(Ljava/lang/Object;)Ljava/lang/Object;
     425: pop
     426: aload_2
     427: getfield      #8                  // Field replacementNode:Lcom/google/javascript/rhino/Node;
     430: invokevirtual #48                 // Method com/google/javascript/rhino/Node.getParent:()Lcom/google/javascript/rhino/Node;
     433: aload_0
     434: getfield      #8                  // Field replacementNode:Lcom/google/javascript/rhino/Node;
     437: aload_2
     438: getfield      #8                  // Field replacementNode:Lcom/google/javascript/rhino/Node;
     441: invokevirtual #61                 // Method com/google/javascript/rhino/Node.addChildAfter:(Lcom/google/javascript/rhino/Node;Lcom/google/javascript/rhino/Node;)V
     444: aload_0
     445: getfield      #5                  // Field explicitNode:Lcom/google/javascript/rhino/Node;
     448: ifnull        459
     451: aload_0
     452: getfield      #5                  // Field explicitNode:Lcom/google/javascript/rhino/Node;
     455: invokevirtual #22                 // Method com/google/javascript/rhino/Node.detachFromParent:()Lcom/google/javascript/rhino/Node;
     458: pop
     459: aload_0
     460: getfield      #3                  // Field this$0:Lcom/google/javascript/jscomp/ProcessClosurePrimitives;
     463: invokestatic  #23                 // Method com/google/javascript/jscomp/ProcessClosurePrimitives.access$300:(Lcom/google/javascript/jscomp/ProcessClosurePrimitives;)Lcom/google/javascript/jscomp/AbstractCompiler;
     466: invokevirtual #24                 // Method com/google/javascript/jscomp/AbstractCompiler.reportCodeChange:()V
     469: return

  private com.google.javascript.rhino.Node createDeclarationNode();
    Code:
       0: aload_0
       1: getfield      #11                 // Field namespace:Ljava/lang/String;
       4: bipush        46
       6: invokevirtual #62                 // Method java/lang/String.indexOf:(I)I
       9: iconst_m1
      10: if_icmpne     18
      13: aload_0
      14: invokespecial #63                 // Method makeVarDeclNode:()Lcom/google/javascript/rhino/Node;
      17: areturn
      18: aload_0
      19: invokespecial #64                 // Method makeAssignmentExprNode:()Lcom/google/javascript/rhino/Node;
      22: areturn

  private com.google.javascript.rhino.Node makeVarDeclNode();
    Code:
       0: aload_0
       1: getfield      #11                 // Field namespace:Ljava/lang/String;
       4: invokestatic  #65                 // Method com/google/javascript/rhino/IR.name:(Ljava/lang/String;)Lcom/google/javascript/rhino/Node;
       7: astore_1
       8: aload_1
       9: aload_0
      10: invokespecial #66                 // Method createNamespaceLiteral:()Lcom/google/javascript/rhino/Node;
      13: invokevirtual #45                 // Method com/google/javascript/rhino/Node.addChildToFront:(Lcom/google/javascript/rhino/Node;)V
      16: aload_1
      17: invokestatic  #46                 // Method com/google/javascript/rhino/IR.var:(Lcom/google/javascript/rhino/Node;)Lcom/google/javascript/rhino/Node;
      20: astore_2
      21: aload_2
      22: bipush        46
      24: iconst_1
      25: invokevirtual #41                 // Method com/google/javascript/rhino/Node.putBooleanProp:(IZ)V
      28: aload_0
      29: getfield      #3                  // Field this$0:Lcom/google/javascript/jscomp/ProcessClosurePrimitives;
      32: invokestatic  #23                 // Method com/google/javascript/jscomp/ProcessClosurePrimitives.access$300:(Lcom/google/javascript/jscomp/ProcessClosurePrimitives;)Lcom/google/javascript/jscomp/AbstractCompiler;
      35: invokevirtual #67                 // Method com/google/javascript/jscomp/AbstractCompiler.getCodingConvention:()Lcom/google/javascript/jscomp/CodingConvention;
      38: aload_0
      39: getfield      #11                 // Field namespace:Ljava/lang/String;
      42: invokeinterface #68,  2           // InterfaceMethod com/google/javascript/jscomp/CodingConvention.isConstant:(Ljava/lang/String;)Z
      47: ifeq          57
      50: aload_1
      51: bipush        43
      53: iconst_1
      54: invokevirtual #41                 // Method com/google/javascript/rhino/Node.putBooleanProp:(IZ)V
      57: aload_0
      58: getfield      #6                  // Field candidateDefinition:Lcom/google/javascript/rhino/Node;
      61: ifnonnull     72
      64: aload_1
      65: invokestatic  #69                 // Method com/google/javascript/jscomp/NodeUtil.createConstantJsDoc:()Lcom/google/javascript/rhino/JSDocInfo;
      68: invokevirtual #50                 // Method com/google/javascript/rhino/Node.setJSDocInfo:(Lcom/google/javascript/rhino/JSDocInfo;)Lcom/google/javascript/rhino/Node;
      71: pop
      72: aload_2
      73: invokestatic  #70                 // Method com/google/javascript/jscomp/ProcessClosurePrimitives.access$500:(Lcom/google/javascript/rhino/Node;)Z
      76: invokestatic  #14                 // Method com/google/common/base/Preconditions.checkState:(Z)V
      79: aload_0
      80: aload_2
      81: invokespecial #71                 // Method setSourceInfo:(Lcom/google/javascript/rhino/Node;)V
      84: aload_2
      85: areturn

  private com.google.javascript.rhino.Node createNamespaceLiteral();
    Code:
       0: iconst_0
       1: anewarray     #40                 // class com/google/javascript/rhino/Node
       4: invokestatic  #72                 // Method com/google/javascript/rhino/IR.objectlit:([Lcom/google/javascript/rhino/Node;)Lcom/google/javascript/rhino/Node;
       7: astore_1
       8: aload_1
       9: aload_0
      10: getfield      #3                  // Field this$0:Lcom/google/javascript/jscomp/ProcessClosurePrimitives;
      13: invokestatic  #23                 // Method com/google/javascript/jscomp/ProcessClosurePrimitives.access$300:(Lcom/google/javascript/jscomp/ProcessClosurePrimitives;)Lcom/google/javascript/jscomp/AbstractCompiler;
      16: invokevirtual #73                 // Method com/google/javascript/jscomp/AbstractCompiler.getTypeRegistry:()Lcom/google/javascript/rhino/jstype/JSTypeRegistry;
      19: aconst_null
      20: invokevirtual #74                 // Method com/google/javascript/rhino/jstype/JSTypeRegistry.createAnonymousObjectType:(Lcom/google/javascript/rhino/JSDocInfo;)Lcom/google/javascript/rhino/jstype/ObjectType;
      23: invokevirtual #75                 // Method com/google/javascript/rhino/Node.setJSType:(Lcom/google/javascript/rhino/jstype/JSType;)V
      26: aload_1
      27: areturn

  private com.google.javascript.rhino.Node makeAssignmentExprNode();
    Code:
       0: aload_0
       1: getfield      #3                  // Field this$0:Lcom/google/javascript/jscomp/ProcessClosurePrimitives;
       4: invokestatic  #23                 // Method com/google/javascript/jscomp/ProcessClosurePrimitives.access$300:(Lcom/google/javascript/jscomp/ProcessClosurePrimitives;)Lcom/google/javascript/jscomp/AbstractCompiler;
       7: aload_0
       8: getfield      #11                 // Field namespace:Ljava/lang/String;
      11: aload_0
      12: getfield      #2                  // Field firstNode:Lcom/google/javascript/rhino/Node;
      15: aload_0
      16: getfield      #11                 // Field namespace:Ljava/lang/String;
      19: invokestatic  #76                 // Method com/google/javascript/jscomp/NodeUtil.newQName:(Lcom/google/javascript/jscomp/AbstractCompiler;Ljava/lang/String;Lcom/google/javascript/rhino/Node;Ljava/lang/String;)Lcom/google/javascript/rhino/Node;
      22: aload_0
      23: invokespecial #66                 // Method createNamespaceLiteral:()Lcom/google/javascript/rhino/Node;
      26: invokestatic  #77                 // Method com/google/javascript/rhino/IR.assign:(Lcom/google/javascript/rhino/Node;Lcom/google/javascript/rhino/Node;)Lcom/google/javascript/rhino/Node;
      29: invokestatic  #78                 // Method com/google/javascript/rhino/IR.exprResult:(Lcom/google/javascript/rhino/Node;)Lcom/google/javascript/rhino/Node;
      32: astore_1
      33: aload_1
      34: bipush        46
      36: iconst_1
      37: invokevirtual #41                 // Method com/google/javascript/rhino/Node.putBooleanProp:(IZ)V
      40: aload_0
      41: getfield      #6                  // Field candidateDefinition:Lcom/google/javascript/rhino/Node;
      44: ifnonnull     58
      47: aload_1
      48: invokevirtual #25                 // Method com/google/javascript/rhino/Node.getFirstChild:()Lcom/google/javascript/rhino/Node;
      51: invokestatic  #69                 // Method com/google/javascript/jscomp/NodeUtil.createConstantJsDoc:()Lcom/google/javascript/rhino/JSDocInfo;
      54: invokevirtual #50                 // Method com/google/javascript/rhino/Node.setJSDocInfo:(Lcom/google/javascript/rhino/JSDocInfo;)Lcom/google/javascript/rhino/Node;
      57: pop
      58: aload_1
      59: invokestatic  #70                 // Method com/google/javascript/jscomp/ProcessClosurePrimitives.access$500:(Lcom/google/javascript/rhino/Node;)Z
      62: invokestatic  #14                 // Method com/google/common/base/Preconditions.checkState:(Z)V
      65: aload_0
      66: aload_1
      67: invokespecial #71                 // Method setSourceInfo:(Lcom/google/javascript/rhino/Node;)V
      70: aload_1
      71: areturn

  private void setSourceInfo(com.google.javascript.rhino.Node);
    Code:
       0: aload_0
       1: invokespecial #79                 // Method getProvideStringNode:()Lcom/google/javascript/rhino/Node;
       4: astore_2
       5: aload_0
       6: aload_2
       7: invokespecial #80                 // Method getSourceInfoOffset:(Lcom/google/javascript/rhino/Node;)I
      10: istore_3
      11: aload_2
      12: ifnonnull     22
      15: aload_0
      16: getfield      #2                  // Field firstNode:Lcom/google/javascript/rhino/Node;
      19: goto          23
      22: aload_2
      23: astore        4
      25: aload_1
      26: aload         4
      28: invokevirtual #81                 // Method com/google/javascript/rhino/Node.copyInformationFromForTree:(Lcom/google/javascript/rhino/Node;)Lcom/google/javascript/rhino/Node;
      31: pop
      32: iload_3
      33: ifeq          47
      36: aload_1
      37: aload         4
      39: invokevirtual #82                 // Method com/google/javascript/rhino/Node.getSourcePosition:()I
      42: iload_3
      43: iadd
      44: invokevirtual #83                 // Method com/google/javascript/rhino/Node.setSourceEncodedPositionForTree:(I)V
      47: return

  private int getSourceInfoOffset(com.google.javascript.rhino.Node);
    Code:
       0: aload_1
       1: ifnonnull     6
       4: iconst_0
       5: ireturn
       6: aload_0
       7: getfield      #11                 // Field namespace:Ljava/lang/String;
      10: bipush        46
      12: invokevirtual #53                 // Method java/lang/String.lastIndexOf:(I)I
      15: istore_2
      16: iconst_2
      17: iload_2
      18: iadd
      19: ireturn

  private com.google.javascript.rhino.Node getProvideStringNode();
    Code:
       0: aload_0
       1: getfield      #2                  // Field firstNode:Lcom/google/javascript/rhino/Node;
       4: invokevirtual #25                 // Method com/google/javascript/rhino/Node.getFirstChild:()Lcom/google/javascript/rhino/Node;
       7: ifnull        33
      10: aload_0
      11: getfield      #2                  // Field firstNode:Lcom/google/javascript/rhino/Node;
      14: invokestatic  #84                 // Method com/google/javascript/jscomp/NodeUtil.isExprCall:(Lcom/google/javascript/rhino/Node;)Z
      17: ifeq          33
      20: aload_0
      21: getfield      #2                  // Field firstNode:Lcom/google/javascript/rhino/Node;
      24: invokevirtual #25                 // Method com/google/javascript/rhino/Node.getFirstChild:()Lcom/google/javascript/rhino/Node;
      27: invokevirtual #85                 // Method com/google/javascript/rhino/Node.getLastChild:()Lcom/google/javascript/rhino/Node;
      30: goto          34
      33: aconst_null
      34: areturn

  static com.google.javascript.rhino.Node access$000(com.google.javascript.jscomp.ProcessClosurePrimitives$ProvidedName);
    Code:
       0: aload_0
       1: getfield      #2                  // Field firstNode:Lcom/google/javascript/rhino/Node;
       4: areturn

  static com.google.javascript.jscomp.JSModule access$100(com.google.javascript.jscomp.ProcessClosurePrimitives$ProvidedName);
    Code:
       0: aload_0
       1: getfield      #1                  // Field explicitModule:Lcom/google/javascript/jscomp/JSModule;
       4: areturn
}
