Compiled from "RecordFunctionInformation.java"
class com.google.javascript.jscomp.RecordFunctionInformation extends com.google.javascript.jscomp.NodeTraversal$AbstractPostOrderCallback implements com.google.javascript.jscomp.CompilerPass {
  private final com.google.javascript.jscomp.Compiler compiler;

  private final com.google.javascript.jscomp.FunctionNames functionNames;

  private final com.google.javascript.jscomp.JSModuleGraph moduleGraph;

  private final com.google.javascript.jscomp.FunctionInformationMap$Builder mapBuilder;

  com.google.javascript.jscomp.RecordFunctionInformation(com.google.javascript.jscomp.Compiler, com.google.javascript.jscomp.FunctionNames);
    Code:
       0: aload_0
       1: invokespecial #1                  // Method com/google/javascript/jscomp/NodeTraversal$AbstractPostOrderCallback."<init>":()V
       4: aload_0
       5: aload_1
       6: putfield      #2                  // Field compiler:Lcom/google/javascript/jscomp/Compiler;
       9: aload_0
      10: aload_1
      11: invokevirtual #3                  // Method com/google/javascript/jscomp/Compiler.getModuleGraph:()Lcom/google/javascript/jscomp/JSModuleGraph;
      14: putfield      #4                  // Field moduleGraph:Lcom/google/javascript/jscomp/JSModuleGraph;
      17: aload_0
      18: aload_2
      19: putfield      #5                  // Field functionNames:Lcom/google/javascript/jscomp/FunctionNames;
      22: aload_0
      23: invokestatic  #6                  // Method com/google/javascript/jscomp/FunctionInformationMap.newBuilder:()Lcom/google/javascript/jscomp/FunctionInformationMap$Builder;
      26: putfield      #7                  // Field mapBuilder:Lcom/google/javascript/jscomp/FunctionInformationMap$Builder;
      29: return

  com.google.javascript.jscomp.FunctionInformationMap getMap();
    Code:
       0: aload_0
       1: getfield      #7                  // Field mapBuilder:Lcom/google/javascript/jscomp/FunctionInformationMap$Builder;
       4: invokevirtual #8                  // Method com/google/javascript/jscomp/FunctionInformationMap$Builder.build:()Lcom/google/javascript/jscomp/FunctionInformationMap;
       7: areturn

  public void process(com.google.javascript.rhino.Node, com.google.javascript.rhino.Node);
    Code:
       0: aload_0
       1: getfield      #2                  // Field compiler:Lcom/google/javascript/jscomp/Compiler;
       4: aload_2
       5: aload_0
       6: invokestatic  #9                  // Method com/google/javascript/jscomp/NodeTraversal.traverse:(Lcom/google/javascript/jscomp/AbstractCompiler;Lcom/google/javascript/rhino/Node;Lcom/google/javascript/jscomp/NodeTraversal$Callback;)V
       9: return

  public void visit(com.google.javascript.jscomp.NodeTraversal, com.google.javascript.rhino.Node, com.google.javascript.rhino.Node);
    Code:
       0: aload_2
       1: invokevirtual #10                 // Method com/google/javascript/rhino/Node.isFunction:()Z
       4: ifne          8
       7: return
       8: aload_0
       9: getfield      #5                  // Field functionNames:Lcom/google/javascript/jscomp/FunctionNames;
      12: aload_2
      13: invokevirtual #11                 // Method com/google/javascript/jscomp/FunctionNames.getFunctionId:(Lcom/google/javascript/rhino/Node;)I
      16: istore        4
      18: iload         4
      20: ifge          24
      23: return
      24: aload_0
      25: getfield      #2                  // Field compiler:Lcom/google/javascript/jscomp/Compiler;
      28: aload_2
      29: invokevirtual #12                 // Method com/google/javascript/jscomp/Compiler.toSource:(Lcom/google/javascript/rhino/Node;)Ljava/lang/String;
      32: astore        5
      34: aload_1
      35: invokevirtual #13                 // Method com/google/javascript/jscomp/NodeTraversal.getModule:()Lcom/google/javascript/jscomp/JSModule;
      38: astore        6
      40: aload_0
      41: getfield      #7                  // Field mapBuilder:Lcom/google/javascript/jscomp/FunctionInformationMap$Builder;
      44: invokestatic  #14                 // Method com/google/javascript/jscomp/FunctionInformationMap$Entry.newBuilder:()Lcom/google/javascript/jscomp/FunctionInformationMap$Entry$Builder;
      47: iload         4
      49: invokevirtual #15                 // Method com/google/javascript/jscomp/FunctionInformationMap$Entry$Builder.setId:(I)Lcom/google/javascript/jscomp/FunctionInformationMap$Entry$Builder;
      52: aload_2
      53: invokestatic  #16                 // Method com/google/javascript/jscomp/NodeUtil.getSourceName:(Lcom/google/javascript/rhino/Node;)Ljava/lang/String;
      56: invokevirtual #17                 // Method com/google/javascript/jscomp/FunctionInformationMap$Entry$Builder.setSourceName:(Ljava/lang/String;)Lcom/google/javascript/jscomp/FunctionInformationMap$Entry$Builder;
      59: aload_2
      60: invokevirtual #18                 // Method com/google/javascript/rhino/Node.getLineno:()I
      63: invokevirtual #19                 // Method com/google/javascript/jscomp/FunctionInformationMap$Entry$Builder.setLineNumber:(I)Lcom/google/javascript/jscomp/FunctionInformationMap$Entry$Builder;
      66: aload_0
      67: getfield      #4                  // Field moduleGraph:Lcom/google/javascript/jscomp/JSModuleGraph;
      70: ifnonnull     78
      73: ldc           #20                 // String
      75: goto          83
      78: aload         6
      80: invokevirtual #21                 // Method com/google/javascript/jscomp/JSModule.getName:()Ljava/lang/String;
      83: invokevirtual #22                 // Method com/google/javascript/jscomp/FunctionInformationMap$Entry$Builder.setModuleName:(Ljava/lang/String;)Lcom/google/javascript/jscomp/FunctionInformationMap$Entry$Builder;
      86: aload         5
      88: invokevirtual #23                 // Method java/lang/String.length:()I
      91: invokevirtual #24                 // Method com/google/javascript/jscomp/FunctionInformationMap$Entry$Builder.setSize:(I)Lcom/google/javascript/jscomp/FunctionInformationMap$Entry$Builder;
      94: aload_0
      95: getfield      #5                  // Field functionNames:Lcom/google/javascript/jscomp/FunctionNames;
      98: aload_2
      99: invokevirtual #25                 // Method com/google/javascript/jscomp/FunctionNames.getFunctionName:(Lcom/google/javascript/rhino/Node;)Ljava/lang/String;
     102: invokevirtual #26                 // Method com/google/javascript/jscomp/FunctionInformationMap$Entry$Builder.setName:(Ljava/lang/String;)Lcom/google/javascript/jscomp/FunctionInformationMap$Entry$Builder;
     105: aload         5
     107: invokevirtual #27                 // Method com/google/javascript/jscomp/FunctionInformationMap$Entry$Builder.setCompiledSource:(Ljava/lang/String;)Lcom/google/javascript/jscomp/FunctionInformationMap$Entry$Builder;
     110: invokevirtual #28                 // Method com/google/javascript/jscomp/FunctionInformationMap$Entry$Builder.build:()Lcom/google/javascript/jscomp/FunctionInformationMap$Entry;
     113: invokevirtual #29                 // Method com/google/javascript/jscomp/FunctionInformationMap$Builder.addEntry:(Lcom/google/javascript/jscomp/FunctionInformationMap$Entry;)Lcom/google/javascript/jscomp/FunctionInformationMap$Builder;
     116: pop
     117: return
}
