Compiled from "RenameVars.java"
class com.google.javascript.jscomp.RenameVars$Assignment {
  final java.lang.String oldName;

  final int orderOfOccurrence;

  java.lang.String newName;

  int count;

  final com.google.javascript.jscomp.RenameVars this$0;

  com.google.javascript.jscomp.RenameVars$Assignment(com.google.javascript.jscomp.RenameVars, java.lang.String);
    Code:
       0: aload_0
       1: aload_1
       2: putfield      #1                  // Field this$0:Lcom/google/javascript/jscomp/RenameVars;
       5: aload_0
       6: invokespecial #2                  // Method java/lang/Object."<init>":()V
       9: aload_0
      10: aload_2
      11: putfield      #3                  // Field oldName:Ljava/lang/String;
      14: aload_0
      15: aconst_null
      16: putfield      #4                  // Field newName:Ljava/lang/String;
      19: aload_0
      20: iconst_0
      21: putfield      #5                  // Field count:I
      24: aload_0
      25: aload_1
      26: invokestatic  #6                  // Method com/google/javascript/jscomp/RenameVars.access$008:(Lcom/google/javascript/jscomp/RenameVars;)I
      29: putfield      #7                  // Field orderOfOccurrence:I
      32: return

  void setNewName(java.lang.String);
    Code:
       0: aload_0
       1: getfield      #4                  // Field newName:Ljava/lang/String;
       4: ifnonnull     11
       7: iconst_1
       8: goto          12
      11: iconst_0
      12: invokestatic  #8                  // Method com/google/common/base/Preconditions.checkState:(Z)V
      15: aload_0
      16: aload_1
      17: putfield      #4                  // Field newName:Ljava/lang/String;
      20: return
}
