Compiled from "SymbolTable.java"
class com.google.javascript.jscomp.SymbolTable$1 extends com.google.javascript.jscomp.NodeTraversal$AbstractScopedCallback {
  final com.google.javascript.jscomp.SymbolTable this$0;

  com.google.javascript.jscomp.SymbolTable$1(com.google.javascript.jscomp.SymbolTable);
    Code:
       0: aload_0
       1: aload_1
       2: putfield      #1                  // Field this$0:Lcom/google/javascript/jscomp/SymbolTable;
       5: aload_0
       6: invokespecial #2                  // Method com/google/javascript/jscomp/NodeTraversal$AbstractScopedCallback."<init>":()V
       9: return

  public void enterScope(com.google.javascript.jscomp.NodeTraversal);
    Code:
       0: aload_0
       1: getfield      #1                  // Field this$0:Lcom/google/javascript/jscomp/SymbolTable;
       4: aload_1
       5: invokevirtual #3                  // Method com/google/javascript/jscomp/NodeTraversal.getScope:()Lcom/google/javascript/jscomp/Scope;
       8: invokestatic  #4                  // Method com/google/javascript/jscomp/SymbolTable.access$200:(Lcom/google/javascript/jscomp/SymbolTable;Lcom/google/javascript/rhino/jstype/StaticScope;)Lcom/google/javascript/jscomp/SymbolTable$SymbolScope;
      11: pop
      12: return

  public void visit(com.google.javascript.jscomp.NodeTraversal, com.google.javascript.rhino.Node, com.google.javascript.rhino.Node);
    Code:
       0: return
}
