Compiled from "VerboseMessageFormatter.java"
class com.google.javascript.jscomp.VerboseMessageFormatter extends com.google.javascript.jscomp.AbstractMessageFormatter {
  com.google.javascript.jscomp.VerboseMessageFormatter(com.google.javascript.jscomp.SourceExcerptProvider);
    Code:
       0: aload_0
       1: aload_1
       2: invokespecial #1                  // Method com/google/javascript/jscomp/AbstractMessageFormatter."<init>":(Lcom/google/javascript/jscomp/SourceExcerptProvider;)V
       5: return

  public java.lang.String formatError(com.google.javascript.jscomp.JSError);
    Code:
       0: new           #2                  // class java/lang/StringBuilder
       3: dup
       4: invokespecial #3                  // Method java/lang/StringBuilder."<init>":()V
       7: aload_0
       8: getstatic     #4                  // Field com/google/javascript/jscomp/CheckLevel.ERROR:Lcom/google/javascript/jscomp/CheckLevel;
      11: invokevirtual #5                  // Method getLevelName:(Lcom/google/javascript/jscomp/CheckLevel;)Ljava/lang/String;
      14: invokevirtual #6                  // Method java/lang/StringBuilder.append:(Ljava/lang/String;)Ljava/lang/StringBuilder;
      17: ldc           #7                  // String :
      19: invokevirtual #6                  // Method java/lang/StringBuilder.append:(Ljava/lang/String;)Ljava/lang/StringBuilder;
      22: aload_0
      23: aload_1
      24: invokespecial #8                  // Method format:(Lcom/google/javascript/jscomp/JSError;)Ljava/lang/String;
      27: invokevirtual #6                  // Method java/lang/StringBuilder.append:(Ljava/lang/String;)Ljava/lang/StringBuilder;
      30: invokevirtual #9                  // Method java/lang/StringBuilder.toString:()Ljava/lang/String;
      33: areturn

  public java.lang.String formatWarning(com.google.javascript.jscomp.JSError);
    Code:
       0: new           #2                  // class java/lang/StringBuilder
       3: dup
       4: invokespecial #3                  // Method java/lang/StringBuilder."<init>":()V
       7: aload_0
       8: getstatic     #10                 // Field com/google/javascript/jscomp/CheckLevel.WARNING:Lcom/google/javascript/jscomp/CheckLevel;
      11: invokevirtual #5                  // Method getLevelName:(Lcom/google/javascript/jscomp/CheckLevel;)Ljava/lang/String;
      14: invokevirtual #6                  // Method java/lang/StringBuilder.append:(Ljava/lang/String;)Ljava/lang/StringBuilder;
      17: ldc           #7                  // String :
      19: invokevirtual #6                  // Method java/lang/StringBuilder.append:(Ljava/lang/String;)Ljava/lang/StringBuilder;
      22: aload_0
      23: aload_1
      24: invokespecial #8                  // Method format:(Lcom/google/javascript/jscomp/JSError;)Ljava/lang/String;
      27: invokevirtual #6                  // Method java/lang/StringBuilder.append:(Ljava/lang/String;)Ljava/lang/StringBuilder;
      30: invokevirtual #9                  // Method java/lang/StringBuilder.toString:()Ljava/lang/String;
      33: areturn

  private java.lang.String format(com.google.javascript.jscomp.JSError);
    Code:
       0: aload_1
       1: getfield      #11                 // Field com/google/javascript/jscomp/JSError.description:Ljava/lang/String;
       4: astore_2
       5: aload_1
       6: getfield      #12                 // Field com/google/javascript/jscomp/JSError.sourceName:Ljava/lang/String;
       9: astore_3
      10: aload_1
      11: getfield      #13                 // Field com/google/javascript/jscomp/JSError.lineNumber:I
      14: istore        4
      16: aload_0
      17: invokevirtual #14                 // Method getSource:()Lcom/google/javascript/jscomp/SourceExcerptProvider;
      20: aload_3
      21: iload         4
      23: invokeinterface #15,  3           // InterfaceMethod com/google/javascript/jscomp/SourceExcerptProvider.getSourceRegion:(Ljava/lang/String;I)Lcom/google/javascript/jscomp/Region;
      28: astore        5
      30: aconst_null
      31: astore        6
      33: aload         5
      35: ifnull        47
      38: aload         5
      40: invokeinterface #16,  1           // InterfaceMethod com/google/javascript/jscomp/Region.getSourceExcerpt:()Ljava/lang/String;
      45: astore        6
      47: ldc           #17                 // String %s at %s line %s %s
      49: iconst_4
      50: anewarray     #18                 // class java/lang/Object
      53: dup
      54: iconst_0
      55: aload_2
      56: aastore
      57: dup
      58: iconst_1
      59: aload_3
      60: invokestatic  #19                 // Method com/google/common/base/Strings.isNullOrEmpty:(Ljava/lang/String;)Z
      63: ifeq          71
      66: ldc           #20                 // String (unknown source)
      68: goto          72
      71: aload_3
      72: aastore
      73: dup
      74: iconst_2
      75: iload         4
      77: ifge          88
      80: iload         4
      82: invokestatic  #21                 // Method java/lang/String.valueOf:(I)Ljava/lang/String;
      85: goto          90
      88: ldc           #22                 // String (unknown line)
      90: aastore
      91: dup
      92: iconst_3
      93: aload         6
      95: ifnull        121
      98: new           #2                  // class java/lang/StringBuilder
     101: dup
     102: invokespecial #3                  // Method java/lang/StringBuilder."<init>":()V
     105: ldc           #23                 // String :\n\n
     107: invokevirtual #6                  // Method java/lang/StringBuilder.append:(Ljava/lang/String;)Ljava/lang/StringBuilder;
     110: aload         6
     112: invokevirtual #6                  // Method java/lang/StringBuilder.append:(Ljava/lang/String;)Ljava/lang/StringBuilder;
     115: invokevirtual #9                  // Method java/lang/StringBuilder.toString:()Ljava/lang/String;
     118: goto          123
     121: ldc           #24                 // String .
     123: aastore
     124: invokestatic  #25                 // Method java/lang/String.format:(Ljava/lang/String;[Ljava/lang/Object;)Ljava/lang/String;
     127: areturn
}
