Compiled from "ClusterInfo.java"
public class org.elasticsearch.hadoop.util.ClusterInfo implements java.io.Serializable {
  private static final long serialVersionUID;

  private final org.elasticsearch.hadoop.util.ClusterName clusterName;

  private final org.elasticsearch.hadoop.util.EsMajorVersion majorVersion;

  public static org.elasticsearch.hadoop.util.ClusterInfo unnamedLatest();
    Code:
       0: new           #1                  // class org/elasticsearch/hadoop/util/ClusterInfo
       3: dup
       4: new           #3                  // class org/elasticsearch/hadoop/util/ClusterName
       7: dup
       8: ldc           #5                  // String !UNNAMED!
      10: aconst_null
      11: invokespecial #7                  // Method org/elasticsearch/hadoop/util/ClusterName."<init>":(Ljava/lang/String;Ljava/lang/String;)V
      14: getstatic     #11                 // Field org/elasticsearch/hadoop/util/EsMajorVersion.LATEST:Lorg/elasticsearch/hadoop/util/EsMajorVersion;
      17: invokespecial #17                 // Method "<init>":(Lorg/elasticsearch/hadoop/util/ClusterName;Lorg/elasticsearch/hadoop/util/EsMajorVersion;)V
      20: areturn

  public static org.elasticsearch.hadoop.util.ClusterInfo unnamedClusterWithVersion(org.elasticsearch.hadoop.util.EsMajorVersion);
    Code:
       0: new           #1                  // class org/elasticsearch/hadoop/util/ClusterInfo
       3: dup
       4: new           #3                  // class org/elasticsearch/hadoop/util/ClusterName
       7: dup
       8: ldc           #5                  // String !UNNAMED!
      10: aconst_null
      11: invokespecial #7                  // Method org/elasticsearch/hadoop/util/ClusterName."<init>":(Ljava/lang/String;Ljava/lang/String;)V
      14: aload_0
      15: invokespecial #17                 // Method "<init>":(Lorg/elasticsearch/hadoop/util/ClusterName;Lorg/elasticsearch/hadoop/util/EsMajorVersion;)V
      18: areturn

  public org.elasticsearch.hadoop.util.ClusterInfo(org.elasticsearch.hadoop.util.ClusterName, org.elasticsearch.hadoop.util.EsMajorVersion);
    Code:
       0: aload_0
       1: invokespecial #20                 // Method java/lang/Object."<init>":()V
       4: aload_0
       5: aload_1
       6: putfield      #25                 // Field clusterName:Lorg/elasticsearch/hadoop/util/ClusterName;
       9: aload_0
      10: aload_2
      11: putfield      #29                 // Field majorVersion:Lorg/elasticsearch/hadoop/util/EsMajorVersion;
      14: return

  public org.elasticsearch.hadoop.util.ClusterName getClusterName();
    Code:
       0: aload_0
       1: getfield      #25                 // Field clusterName:Lorg/elasticsearch/hadoop/util/ClusterName;
       4: areturn

  public org.elasticsearch.hadoop.util.EsMajorVersion getMajorVersion();
    Code:
       0: aload_0
       1: getfield      #29                 // Field majorVersion:Lorg/elasticsearch/hadoop/util/EsMajorVersion;
       4: areturn

  public boolean equals(java.lang.Object);
    Code:
       0: aload_0
       1: aload_1
       2: if_acmpne     7
       5: iconst_1
       6: ireturn
       7: aload_1
       8: ifnull        22
      11: aload_0
      12: invokevirtual #32                 // Method java/lang/Object.getClass:()Ljava/lang/Class;
      15: aload_1
      16: invokevirtual #32                 // Method java/lang/Object.getClass:()Ljava/lang/Class;
      19: if_acmpeq     24
      22: iconst_0
      23: ireturn
      24: aload_1
      25: checkcast     #1                  // class org/elasticsearch/hadoop/util/ClusterInfo
      28: astore_2
      29: aload_0
      30: getfield      #25                 // Field clusterName:Lorg/elasticsearch/hadoop/util/ClusterName;
      33: ifnull        53
      36: aload_0
      37: getfield      #25                 // Field clusterName:Lorg/elasticsearch/hadoop/util/ClusterName;
      40: aload_2
      41: getfield      #25                 // Field clusterName:Lorg/elasticsearch/hadoop/util/ClusterName;
      44: invokevirtual #36                 // Method org/elasticsearch/hadoop/util/ClusterName.equals:(Ljava/lang/Object;)Z
      47: ifne          62
      50: goto          60
      53: aload_2
      54: getfield      #25                 // Field clusterName:Lorg/elasticsearch/hadoop/util/ClusterName;
      57: ifnull        62
      60: iconst_0
      61: ireturn
      62: aload_0
      63: getfield      #29                 // Field majorVersion:Lorg/elasticsearch/hadoop/util/EsMajorVersion;
      66: ifnull        83
      69: aload_0
      70: getfield      #29                 // Field majorVersion:Lorg/elasticsearch/hadoop/util/EsMajorVersion;
      73: aload_2
      74: getfield      #29                 // Field majorVersion:Lorg/elasticsearch/hadoop/util/EsMajorVersion;
      77: invokevirtual #40                 // Method org/elasticsearch/hadoop/util/EsMajorVersion.equals:(Ljava/lang/Object;)Z
      80: goto          95
      83: aload_2
      84: getfield      #29                 // Field majorVersion:Lorg/elasticsearch/hadoop/util/EsMajorVersion;
      87: ifnonnull     94
      90: iconst_1
      91: goto          95
      94: iconst_0
      95: ireturn

  public int hashCode();
    Code:
       0: aload_0
       1: getfield      #25                 // Field clusterName:Lorg/elasticsearch/hadoop/util/ClusterName;
       4: ifnull        17
       7: aload_0
       8: getfield      #25                 // Field clusterName:Lorg/elasticsearch/hadoop/util/ClusterName;
      11: invokevirtual #41                 // Method org/elasticsearch/hadoop/util/ClusterName.hashCode:()I
      14: goto          18
      17: iconst_0
      18: istore_1
      19: bipush        31
      21: iload_1
      22: imul
      23: aload_0
      24: getfield      #29                 // Field majorVersion:Lorg/elasticsearch/hadoop/util/EsMajorVersion;
      27: ifnull        40
      30: aload_0
      31: getfield      #29                 // Field majorVersion:Lorg/elasticsearch/hadoop/util/EsMajorVersion;
      34: invokevirtual #45                 // Method org/elasticsearch/hadoop/util/EsMajorVersion.hashCode:()I
      37: goto          41
      40: iconst_0
      41: iadd
      42: istore_1
      43: iload_1
      44: ireturn

  public java.lang.String toString();
    Code:
       0: new           #46                 // class java/lang/StringBuilder
       3: dup
       4: invokespecial #48                 // Method java/lang/StringBuilder."<init>":()V
       7: ldc           #49                 // String ClusterInfo{clusterName=
       9: invokevirtual #51                 // Method java/lang/StringBuilder.append:(Ljava/lang/String;)Ljava/lang/StringBuilder;
      12: aload_0
      13: getfield      #25                 // Field clusterName:Lorg/elasticsearch/hadoop/util/ClusterName;
      16: invokevirtual #55                 // Method java/lang/StringBuilder.append:(Ljava/lang/Object;)Ljava/lang/StringBuilder;
      19: ldc           #58                 // String , majorVersion=
      21: invokevirtual #51                 // Method java/lang/StringBuilder.append:(Ljava/lang/String;)Ljava/lang/StringBuilder;
      24: aload_0
      25: getfield      #29                 // Field majorVersion:Lorg/elasticsearch/hadoop/util/EsMajorVersion;
      28: invokevirtual #55                 // Method java/lang/StringBuilder.append:(Ljava/lang/Object;)Ljava/lang/StringBuilder;
      31: bipush        125
      33: invokevirtual #60                 // Method java/lang/StringBuilder.append:(C)Ljava/lang/StringBuilder;
      36: invokevirtual #63                 // Method java/lang/StringBuilder.toString:()Ljava/lang/String;
      39: areturn
}
