Compiled from "AsyncServerFilterChainExchangeHandlerFactory.java"
public final class org.apache.hc.core5.http.nio.support.AsyncServerFilterChainExchangeHandlerFactory implements org.apache.hc.core5.http.nio.HandlerFactory<org.apache.hc.core5.http.nio.AsyncServerExchangeHandler> {
  private final org.apache.hc.core5.http.nio.support.AsyncServerFilterChainElement filterChain;

  private final org.apache.hc.core5.function.Callback<java.lang.Exception> exceptionCallback;

  public org.apache.hc.core5.http.nio.support.AsyncServerFilterChainExchangeHandlerFactory(org.apache.hc.core5.http.nio.support.AsyncServerFilterChainElement, org.apache.hc.core5.function.Callback<java.lang.Exception>);
    Code:
       0: aload_0
       1: invokespecial #3                  // Method java/lang/Object."<init>":()V
       4: aload_0
       5: aload_1
       6: ldc           #4                  // String Filter chain
       8: invokestatic  #5                  // Method org/apache/hc/core5/util/Args.notNull:(Ljava/lang/Object;Ljava/lang/String;)Ljava/lang/Object;
      11: checkcast     #6                  // class org/apache/hc/core5/http/nio/support/AsyncServerFilterChainElement
      14: putfield      #2                  // Field filterChain:Lorg/apache/hc/core5/http/nio/support/AsyncServerFilterChainElement;
      17: aload_0
      18: aload_2
      19: putfield      #1                  // Field exceptionCallback:Lorg/apache/hc/core5/function/Callback;
      22: return

  public org.apache.hc.core5.http.nio.support.AsyncServerFilterChainExchangeHandlerFactory(org.apache.hc.core5.http.nio.support.AsyncServerFilterChainElement);
    Code:
       0: aload_0
       1: aload_1
       2: aconst_null
       3: invokespecial #7                  // Method "<init>":(Lorg/apache/hc/core5/http/nio/support/AsyncServerFilterChainElement;Lorg/apache/hc/core5/function/Callback;)V
       6: return

  public org.apache.hc.core5.http.nio.AsyncServerExchangeHandler create(org.apache.hc.core5.http.HttpRequest, org.apache.hc.core5.http.protocol.HttpContext) throws org.apache.hc.core5.http.HttpException;
    Code:
       0: new           #8                  // class org/apache/hc/core5/http/nio/support/AsyncServerFilterChainExchangeHandlerFactory$1
       3: dup
       4: aload_0
       5: invokespecial #9                  // Method org/apache/hc/core5/http/nio/support/AsyncServerFilterChainExchangeHandlerFactory$1."<init>":(Lorg/apache/hc/core5/http/nio/support/AsyncServerFilterChainExchangeHandlerFactory;)V
       8: areturn

  public org.apache.hc.core5.http.nio.ResourceHolder create(org.apache.hc.core5.http.HttpRequest, org.apache.hc.core5.http.protocol.HttpContext) throws org.apache.hc.core5.http.HttpException;
    Code:
       0: aload_0
       1: aload_1
       2: aload_2
       3: invokevirtual #10                 // Method create:(Lorg/apache/hc/core5/http/HttpRequest;Lorg/apache/hc/core5/http/protocol/HttpContext;)Lorg/apache/hc/core5/http/nio/AsyncServerExchangeHandler;
       6: areturn

  static org.apache.hc.core5.http.nio.support.AsyncServerFilterChainElement access$100(org.apache.hc.core5.http.nio.support.AsyncServerFilterChainExchangeHandlerFactory);
    Code:
       0: aload_0
       1: getfield      #2                  // Field filterChain:Lorg/apache/hc/core5/http/nio/support/AsyncServerFilterChainElement;
       4: areturn

  static org.apache.hc.core5.function.Callback access$200(org.apache.hc.core5.http.nio.support.AsyncServerFilterChainExchangeHandlerFactory);
    Code:
       0: aload_0
       1: getfield      #1                  // Field exceptionCallback:Lorg/apache/hc/core5/function/Callback;
       4: areturn
}
