Compiled from "BasicClientExchangeHandler.java"
class org.apache.hc.core5.http.nio.support.BasicClientExchangeHandler$1 implements org.apache.hc.core5.concurrent.FutureCallback<T> {
  final org.apache.hc.core5.http.nio.support.BasicClientExchangeHandler this$0;

  org.apache.hc.core5.http.nio.support.BasicClientExchangeHandler$1(org.apache.hc.core5.http.nio.support.BasicClientExchangeHandler);
    Code:
       0: aload_0
       1: aload_1
       2: putfield      #1                  // Field this$0:Lorg/apache/hc/core5/http/nio/support/BasicClientExchangeHandler;
       5: aload_0
       6: invokespecial #2                  // Method java/lang/Object."<init>":()V
       9: return

  public void completed(T);
    Code:
       0: aload_0
       1: getfield      #1                  // Field this$0:Lorg/apache/hc/core5/http/nio/support/BasicClientExchangeHandler;
       4: invokestatic  #3                  // Method org/apache/hc/core5/http/nio/support/BasicClientExchangeHandler.access$000:(Lorg/apache/hc/core5/http/nio/support/BasicClientExchangeHandler;)Ljava/util/concurrent/atomic/AtomicBoolean;
       7: iconst_0
       8: iconst_1
       9: invokevirtual #4                  // Method java/util/concurrent/atomic/AtomicBoolean.compareAndSet:(ZZ)Z
      12: ifeq          58
      15: aload_0
      16: getfield      #1                  // Field this$0:Lorg/apache/hc/core5/http/nio/support/BasicClientExchangeHandler;
      19: invokestatic  #5                  // Method org/apache/hc/core5/http/nio/support/BasicClientExchangeHandler.access$100:(Lorg/apache/hc/core5/http/nio/support/BasicClientExchangeHandler;)Lorg/apache/hc/core5/concurrent/FutureCallback;
      22: ifnull        38
      25: aload_0
      26: getfield      #1                  // Field this$0:Lorg/apache/hc/core5/http/nio/support/BasicClientExchangeHandler;
      29: invokestatic  #5                  // Method org/apache/hc/core5/http/nio/support/BasicClientExchangeHandler.access$100:(Lorg/apache/hc/core5/http/nio/support/BasicClientExchangeHandler;)Lorg/apache/hc/core5/concurrent/FutureCallback;
      32: aload_1
      33: invokeinterface #6,  2            // InterfaceMethod org/apache/hc/core5/concurrent/FutureCallback.completed:(Ljava/lang/Object;)V
      38: aload_0
      39: getfield      #1                  // Field this$0:Lorg/apache/hc/core5/http/nio/support/BasicClientExchangeHandler;
      42: invokestatic  #7                  // Method org/apache/hc/core5/http/nio/support/BasicClientExchangeHandler.access$200:(Lorg/apache/hc/core5/http/nio/support/BasicClientExchangeHandler;)V
      45: goto          58
      48: astore_2
      49: aload_0
      50: getfield      #1                  // Field this$0:Lorg/apache/hc/core5/http/nio/support/BasicClientExchangeHandler;
      53: invokestatic  #7                  // Method org/apache/hc/core5/http/nio/support/BasicClientExchangeHandler.access$200:(Lorg/apache/hc/core5/http/nio/support/BasicClientExchangeHandler;)V
      56: aload_2
      57: athrow
      58: return
    Exception table:
       from    to  target type
          15    38    48   any
          48    49    48   any

  public void failed(java.lang.Exception);
    Code:
       0: aload_0
       1: getfield      #1                  // Field this$0:Lorg/apache/hc/core5/http/nio/support/BasicClientExchangeHandler;
       4: invokestatic  #3                  // Method org/apache/hc/core5/http/nio/support/BasicClientExchangeHandler.access$000:(Lorg/apache/hc/core5/http/nio/support/BasicClientExchangeHandler;)Ljava/util/concurrent/atomic/AtomicBoolean;
       7: iconst_0
       8: iconst_1
       9: invokevirtual #4                  // Method java/util/concurrent/atomic/AtomicBoolean.compareAndSet:(ZZ)Z
      12: ifeq          58
      15: aload_0
      16: getfield      #1                  // Field this$0:Lorg/apache/hc/core5/http/nio/support/BasicClientExchangeHandler;
      19: invokestatic  #5                  // Method org/apache/hc/core5/http/nio/support/BasicClientExchangeHandler.access$100:(Lorg/apache/hc/core5/http/nio/support/BasicClientExchangeHandler;)Lorg/apache/hc/core5/concurrent/FutureCallback;
      22: ifnull        38
      25: aload_0
      26: getfield      #1                  // Field this$0:Lorg/apache/hc/core5/http/nio/support/BasicClientExchangeHandler;
      29: invokestatic  #5                  // Method org/apache/hc/core5/http/nio/support/BasicClientExchangeHandler.access$100:(Lorg/apache/hc/core5/http/nio/support/BasicClientExchangeHandler;)Lorg/apache/hc/core5/concurrent/FutureCallback;
      32: aload_1
      33: invokeinterface #8,  2            // InterfaceMethod org/apache/hc/core5/concurrent/FutureCallback.failed:(Ljava/lang/Exception;)V
      38: aload_0
      39: getfield      #1                  // Field this$0:Lorg/apache/hc/core5/http/nio/support/BasicClientExchangeHandler;
      42: invokestatic  #7                  // Method org/apache/hc/core5/http/nio/support/BasicClientExchangeHandler.access$200:(Lorg/apache/hc/core5/http/nio/support/BasicClientExchangeHandler;)V
      45: goto          58
      48: astore_2
      49: aload_0
      50: getfield      #1                  // Field this$0:Lorg/apache/hc/core5/http/nio/support/BasicClientExchangeHandler;
      53: invokestatic  #7                  // Method org/apache/hc/core5/http/nio/support/BasicClientExchangeHandler.access$200:(Lorg/apache/hc/core5/http/nio/support/BasicClientExchangeHandler;)V
      56: aload_2
      57: athrow
      58: return
    Exception table:
       from    to  target type
          15    38    48   any
          48    49    48   any

  public void cancelled();
    Code:
       0: aload_0
       1: getfield      #1                  // Field this$0:Lorg/apache/hc/core5/http/nio/support/BasicClientExchangeHandler;
       4: invokestatic  #3                  // Method org/apache/hc/core5/http/nio/support/BasicClientExchangeHandler.access$000:(Lorg/apache/hc/core5/http/nio/support/BasicClientExchangeHandler;)Ljava/util/concurrent/atomic/AtomicBoolean;
       7: iconst_0
       8: iconst_1
       9: invokevirtual #4                  // Method java/util/concurrent/atomic/AtomicBoolean.compareAndSet:(ZZ)Z
      12: ifeq          57
      15: aload_0
      16: getfield      #1                  // Field this$0:Lorg/apache/hc/core5/http/nio/support/BasicClientExchangeHandler;
      19: invokestatic  #5                  // Method org/apache/hc/core5/http/nio/support/BasicClientExchangeHandler.access$100:(Lorg/apache/hc/core5/http/nio/support/BasicClientExchangeHandler;)Lorg/apache/hc/core5/concurrent/FutureCallback;
      22: ifnull        37
      25: aload_0
      26: getfield      #1                  // Field this$0:Lorg/apache/hc/core5/http/nio/support/BasicClientExchangeHandler;
      29: invokestatic  #5                  // Method org/apache/hc/core5/http/nio/support/BasicClientExchangeHandler.access$100:(Lorg/apache/hc/core5/http/nio/support/BasicClientExchangeHandler;)Lorg/apache/hc/core5/concurrent/FutureCallback;
      32: invokeinterface #9,  1            // InterfaceMethod org/apache/hc/core5/concurrent/FutureCallback.cancelled:()V
      37: aload_0
      38: getfield      #1                  // Field this$0:Lorg/apache/hc/core5/http/nio/support/BasicClientExchangeHandler;
      41: invokestatic  #7                  // Method org/apache/hc/core5/http/nio/support/BasicClientExchangeHandler.access$200:(Lorg/apache/hc/core5/http/nio/support/BasicClientExchangeHandler;)V
      44: goto          57
      47: astore_1
      48: aload_0
      49: getfield      #1                  // Field this$0:Lorg/apache/hc/core5/http/nio/support/BasicClientExchangeHandler;
      52: invokestatic  #7                  // Method org/apache/hc/core5/http/nio/support/BasicClientExchangeHandler.access$200:(Lorg/apache/hc/core5/http/nio/support/BasicClientExchangeHandler;)V
      55: aload_1
      56: athrow
      57: return
    Exception table:
       from    to  target type
          15    37    47   any
          47    48    47   any
}
