Compiled from "WizardsRegistryReader.java"
public class org.eclipse.ui.internal.registry.WizardsRegistryReader extends org.eclipse.ui.internal.registry.RegistryReader {
  private java.lang.String pluginPoint;

  private org.eclipse.ui.internal.dialogs.WizardCollectionElement wizardElements;

  private java.util.ArrayList<org.eclipse.ui.internal.dialogs.WorkbenchWizardElement> deferWizards;

  private java.util.ArrayList<org.eclipse.ui.internal.registry.Category> deferCategories;

  private java.util.Set<java.lang.String> deferPrimary;

  public static final java.lang.String FULL_EXAMPLES_WIZARD_CATEGORY;

  public static final java.lang.String UNCATEGORIZED_WIZARD_CATEGORY;

  public static final java.lang.String GENERAL_WIZARD_CATEGORY;

  private static final java.lang.String UNCATEGORIZED_WIZARD_CATEGORY_LABEL;

  private static final java.lang.String CATEGORY_SEPARATOR;

  private org.eclipse.ui.internal.dialogs.WorkbenchWizardElement[] primaryWizards;

  private static final java.util.Comparator<org.eclipse.ui.internal.registry.WizardsRegistryReader$CategoryNode> comparer;

  private boolean readAll;

  private java.lang.String plugin;

  static {};
    Code:
       0: getstatic     #323                // Field org/eclipse/ui/internal/WorkbenchMessages.NewWizardsRegistryReader_otherCategory:Ljava/lang/String;
       3: putstatic     #325                // Field UNCATEGORIZED_WIZARD_CATEGORY_LABEL:Ljava/lang/String;
       6: new           #187                // class org/eclipse/ui/internal/registry/WizardsRegistryReader$1
       9: dup
      10: invokespecial #391                // Method org/eclipse/ui/internal/registry/WizardsRegistryReader$1."<init>":()V
      13: putstatic     #330                // Field comparer:Ljava/util/Comparator;
      16: return

  public org.eclipse.ui.internal.registry.WizardsRegistryReader(java.lang.String, java.lang.String);
    Code:
       0: aload_0
       1: invokespecial #368                // Method org/eclipse/ui/internal/registry/RegistryReader."<init>":()V
       4: aload_0
       5: aconst_null
       6: putfield      #332                // Field wizardElements:Lorg/eclipse/ui/internal/dialogs/WizardCollectionElement;
       9: aload_0
      10: aconst_null
      11: putfield      #329                // Field deferWizards:Ljava/util/ArrayList;
      14: aload_0
      15: aconst_null
      16: putfield      #328                // Field deferCategories:Ljava/util/ArrayList;
      19: aload_0
      20: iconst_0
      21: anewarray     #183                // class org/eclipse/ui/internal/dialogs/WorkbenchWizardElement
      24: putfield      #333                // Field primaryWizards:[Lorg/eclipse/ui/internal/dialogs/WorkbenchWizardElement;
      27: aload_0
      28: iconst_1
      29: putfield      #324                // Field readAll:Z
      32: aload_0
      33: aload_2
      34: putfield      #327                // Field pluginPoint:Ljava/lang/String;
      37: aload_0
      38: aload_1
      39: putfield      #326                // Field plugin:Ljava/lang/String;
      42: return

  protected void addNewElementToResult(org.eclipse.ui.internal.dialogs.WorkbenchWizardElement, org.eclipse.core.runtime.IConfigurationElement);
    Code:
       0: aload_0
       1: aload_1
       2: invokevirtual #378                // Method deferWizard:(Lorg/eclipse/ui/internal/dialogs/WorkbenchWizardElement;)V
       5: return

  private org.eclipse.ui.internal.dialogs.WizardCollectionElement createCollectionElement(org.eclipse.ui.internal.dialogs.WizardCollectionElement, org.eclipse.core.runtime.IConfigurationElement);
    Code:
       0: new           #182                // class org/eclipse/ui/internal/dialogs/WizardCollectionElement
       3: dup
       4: aload_2
       5: aload_1
       6: invokespecial #358                // Method org/eclipse/ui/internal/dialogs/WizardCollectionElement."<init>":(Lorg/eclipse/core/runtime/IConfigurationElement;Lorg/eclipse/ui/internal/dialogs/WizardCollectionElement;)V
       9: astore_3
      10: aload_1
      11: aload_3
      12: invokevirtual #360                // Method org/eclipse/ui/internal/dialogs/WizardCollectionElement.add:(Lorg/eclipse/core/runtime/IAdaptable;)Lorg/eclipse/ui/model/AdaptableList;
      15: pop
      16: aload_3
      17: areturn

  protected org.eclipse.ui.internal.dialogs.WizardCollectionElement createCollectionElement(org.eclipse.ui.internal.dialogs.WizardCollectionElement, java.lang.String, java.lang.String, java.lang.String);
    Code:
       0: new           #182                // class org/eclipse/ui/internal/dialogs/WizardCollectionElement
       3: dup
       4: aload_2
       5: aload_3
       6: aload         4
       8: aload_1
       9: invokespecial #361                // Method org/eclipse/ui/internal/dialogs/WizardCollectionElement."<init>":(Ljava/lang/String;Ljava/lang/String;Ljava/lang/String;Lorg/eclipse/ui/internal/dialogs/WizardCollectionElement;)V
      12: astore        5
      14: aload_1
      15: aload         5
      17: invokevirtual #360                // Method org/eclipse/ui/internal/dialogs/WizardCollectionElement.add:(Lorg/eclipse/core/runtime/IAdaptable;)Lorg/eclipse/ui/model/AdaptableList;
      20: pop
      21: aload         5
      23: areturn

  protected void createEmptyWizardCollection();
    Code:
       0: aload_0
       1: new           #182                // class org/eclipse/ui/internal/dialogs/WizardCollectionElement
       4: dup
       5: ldc           #5                  // String root
       7: aconst_null
       8: ldc           #5                  // String root
      10: aconst_null
      11: invokespecial #361                // Method org/eclipse/ui/internal/dialogs/WizardCollectionElement."<init>":(Ljava/lang/String;Ljava/lang/String;Ljava/lang/String;Lorg/eclipse/ui/internal/dialogs/WizardCollectionElement;)V
      14: putfield      #332                // Field wizardElements:Lorg/eclipse/ui/internal/dialogs/WizardCollectionElement;
      17: return

  public void setInitialCollection(org.eclipse.ui.internal.dialogs.WizardCollectionElement);
    Code:
       0: aload_0
       1: aload_1
       2: putfield      #332                // Field wizardElements:Lorg/eclipse/ui/internal/dialogs/WizardCollectionElement;
       5: aload_0
       6: iconst_0
       7: putfield      #324                // Field readAll:Z
      10: return

  private void deferCategory(org.eclipse.core.runtime.IConfigurationElement);
    Code:
       0: aconst_null
       1: astore_2
       2: new           #184                // class org/eclipse/ui/internal/registry/Category
       5: dup
       6: aload_1
       7: invokespecial #367                // Method org/eclipse/ui/internal/registry/Category."<init>":(Lorg/eclipse/core/runtime/IConfigurationElement;)V
      10: astore_2
      11: goto          25
      14: astore_3
      15: ldc           #2                  // String Cannot create category:
      17: aload_3
      18: invokevirtual #348                // Method org/eclipse/core/runtime/CoreException.getStatus:()Lorg/eclipse/core/runtime/IStatus;
      21: invokestatic  #352                // Method org/eclipse/ui/internal/WorkbenchPlugin.log:(Ljava/lang/String;Lorg/eclipse/core/runtime/IStatus;)V
      24: return
      25: aload_0
      26: getfield      #328                // Field deferCategories:Ljava/util/ArrayList;
      29: ifnonnull     45
      32: aload_0
      33: new           #169                // class java/util/ArrayList
      36: dup
      37: bipush        20
      39: invokespecial #337                // Method java/util/ArrayList."<init>":(I)V
      42: putfield      #328                // Field deferCategories:Ljava/util/ArrayList;
      45: aload_0
      46: getfield      #328                // Field deferCategories:Ljava/util/ArrayList;
      49: aload_2
      50: invokevirtual #339                // Method java/util/ArrayList.add:(Ljava/lang/Object;)Z
      53: pop
      54: return
    Exception table:
       from    to  target type
           2    11    14   Class org/eclipse/core/runtime/CoreException

  private void deferWizard(org.eclipse.ui.internal.dialogs.WorkbenchWizardElement);
    Code:
       0: aload_0
       1: getfield      #329                // Field deferWizards:Ljava/util/ArrayList;
       4: ifnonnull     20
       7: aload_0
       8: new           #169                // class java/util/ArrayList
      11: dup
      12: bipush        50
      14: invokespecial #337                // Method java/util/ArrayList."<init>":(I)V
      17: putfield      #329                // Field deferWizards:Ljava/util/ArrayList;
      20: aload_0
      21: getfield      #329                // Field deferWizards:Ljava/util/ArrayList;
      24: aload_1
      25: invokevirtual #339                // Method java/util/ArrayList.add:(Ljava/lang/Object;)Z
      28: pop
      29: return

  private void finishCategories();
    Code:
       0: aload_0
       1: getfield      #328                // Field deferCategories:Ljava/util/ArrayList;
       4: ifnonnull     8
       7: return
       8: aload_0
       9: getfield      #328                // Field deferCategories:Ljava/util/ArrayList;
      12: invokevirtual #335                // Method java/util/ArrayList.size:()I
      15: anewarray     #188                // class org/eclipse/ui/internal/registry/WizardsRegistryReader$CategoryNode
      18: astore_1
      19: iconst_0
      20: istore_2
      21: goto          48
      24: aload_1
      25: iload_2
      26: new           #188                // class org/eclipse/ui/internal/registry/WizardsRegistryReader$CategoryNode
      29: dup
      30: aload_0
      31: getfield      #328                // Field deferCategories:Ljava/util/ArrayList;
      34: iload_2
      35: invokevirtual #338                // Method java/util/ArrayList.get:(I)Ljava/lang/Object;
      38: checkcast     #184                // class org/eclipse/ui/internal/registry/Category
      41: invokespecial #393                // Method org/eclipse/ui/internal/registry/WizardsRegistryReader$CategoryNode."<init>":(Lorg/eclipse/ui/internal/registry/Category;)V
      44: aastore
      45: iinc          2, 1
      48: iload_2
      49: aload_0
      50: getfield      #328                // Field deferCategories:Ljava/util/ArrayList;
      53: invokevirtual #335                // Method java/util/ArrayList.size:()I
      56: if_icmplt     24
      59: aload_1
      60: invokestatic  #342                // Method java/util/Arrays.asList:([Ljava/lang/Object;)Ljava/util/List;
      63: getstatic     #330                // Field comparer:Ljava/util/Comparator;
      66: invokeinterface #396,  2          // InterfaceMethod java/util/List.sort:(Ljava/util/Comparator;)V
      71: aload_1
      72: dup
      73: astore        5
      75: arraylength
      76: istore        4
      78: iconst_0
      79: istore_3
      80: goto          103
      83: aload         5
      85: iload_3
      86: aaload
      87: astore_2
      88: aload_2
      89: invokevirtual #392                // Method org/eclipse/ui/internal/registry/WizardsRegistryReader$CategoryNode.getCategory:()Lorg/eclipse/ui/internal/registry/Category;
      92: astore        6
      94: aload_0
      95: aload         6
      97: invokevirtual #379                // Method finishCategory:(Lorg/eclipse/ui/internal/registry/Category;)V
     100: iinc          3, 1
     103: iload_3
     104: iload         4
     106: if_icmplt     83
     109: aload_0
     110: aconst_null
     111: putfield      #328                // Field deferCategories:Ljava/util/ArrayList;
     114: return

  private void finishCategory(org.eclipse.ui.internal.registry.Category);
    Code:
       0: aload_1
       1: invokevirtual #366                // Method org/eclipse/ui/internal/registry/Category.getParentPath:()[Ljava/lang/String;
       4: astore_2
       5: aload_0
       6: getfield      #332                // Field wizardElements:Lorg/eclipse/ui/internal/dialogs/WizardCollectionElement;
       9: astore_3
      10: aload_2
      11: ifnull        62
      14: aload_2
      15: dup
      16: astore        7
      18: arraylength
      19: istore        6
      21: iconst_0
      22: istore        5
      24: goto          55
      27: aload         7
      29: iload         5
      31: aaload
      32: astore        4
      34: aload_0
      35: aload_3
      36: aload         4
      38: invokevirtual #388                // Method getChildWithID:(Lorg/eclipse/ui/internal/dialogs/WizardCollectionElement;Ljava/lang/String;)Lorg/eclipse/ui/internal/dialogs/WizardCollectionElement;
      41: astore        8
      43: aload         8
      45: ifnonnull     49
      48: return
      49: aload         8
      51: astore_3
      52: iinc          5, 1
      55: iload         5
      57: iload         6
      59: if_icmplt     27
      62: aload_0
      63: aload_3
      64: aload_1
      65: invokevirtual #365                // Method org/eclipse/ui/internal/registry/Category.getId:()Ljava/lang/String;
      68: invokevirtual #388                // Method getChildWithID:(Lorg/eclipse/ui/internal/dialogs/WizardCollectionElement;Ljava/lang/String;)Lorg/eclipse/ui/internal/dialogs/WizardCollectionElement;
      71: astore        4
      73: aload         4
      75: ifnull        79
      78: return
      79: aload_3
      80: ifnull        98
      83: aload_0
      84: aload_3
      85: aload_1
      86: ldc           #6                  // class org/eclipse/core/runtime/IConfigurationElement
      88: invokestatic  #347                // Method org/eclipse/core/runtime/Adapters.adapt:(Ljava/lang/Object;Ljava/lang/Class;)Ljava/lang/Object;
      91: checkcast     #6                  // class org/eclipse/core/runtime/IConfigurationElement
      94: invokevirtual #389                // Method createCollectionElement:(Lorg/eclipse/ui/internal/dialogs/WizardCollectionElement;Lorg/eclipse/core/runtime/IConfigurationElement;)Lorg/eclipse/ui/internal/dialogs/WizardCollectionElement;
      97: pop
      98: return

  private void finishPrimary();
    Code:
       0: aload_0
       1: getfield      #331                // Field deferPrimary:Ljava/util/Set;
       4: ifnull        104
       7: new           #169                // class java/util/ArrayList
      10: dup
      11: invokespecial #336                // Method java/util/ArrayList."<init>":()V
      14: astore_1
      15: aload_0
      16: getfield      #331                // Field deferPrimary:Ljava/util/Set;
      19: invokeinterface #398,  1          // InterfaceMethod java/util/Set.iterator:()Ljava/util/Iterator;
      24: astore_2
      25: goto          72
      28: aload_2
      29: invokeinterface #395,  1          // InterfaceMethod java/util/Iterator.next:()Ljava/lang/Object;
      34: checkcast     #168                // class java/lang/String
      37: astore_3
      38: aload_0
      39: getfield      #332                // Field wizardElements:Lorg/eclipse/ui/internal/dialogs/WizardCollectionElement;
      42: ifnonnull     49
      45: aconst_null
      46: goto          58
      49: aload_0
      50: getfield      #332                // Field wizardElements:Lorg/eclipse/ui/internal/dialogs/WizardCollectionElement;
      53: aload_3
      54: iconst_1
      55: invokevirtual #359                // Method org/eclipse/ui/internal/dialogs/WizardCollectionElement.findWizard:(Ljava/lang/String;Z)Lorg/eclipse/ui/internal/dialogs/WorkbenchWizardElement;
      58: astore        4
      60: aload         4
      62: ifnull        72
      65: aload_1
      66: aload         4
      68: invokevirtual #339                // Method java/util/ArrayList.add:(Ljava/lang/Object;)Z
      71: pop
      72: aload_2
      73: invokeinterface #394,  1          // InterfaceMethod java/util/Iterator.hasNext:()Z
      78: ifne          28
      81: aload_0
      82: aload_1
      83: aload_1
      84: invokevirtual #335                // Method java/util/ArrayList.size:()I
      87: anewarray     #183                // class org/eclipse/ui/internal/dialogs/WorkbenchWizardElement
      90: invokevirtual #341                // Method java/util/ArrayList.toArray:([Ljava/lang/Object;)[Ljava/lang/Object;
      93: checkcast     #165                // class "[Lorg/eclipse/ui/internal/dialogs/WorkbenchWizardElement;"
      96: putfield      #333                // Field primaryWizards:[Lorg/eclipse/ui/internal/dialogs/WorkbenchWizardElement;
      99: aload_0
     100: aconst_null
     101: putfield      #331                // Field deferPrimary:Ljava/util/Set;
     104: return

  private void finishWizard(org.eclipse.ui.internal.dialogs.WorkbenchWizardElement, org.eclipse.core.runtime.IConfigurationElement);
    Code:
       0: new           #175                // class java/util/StringTokenizer
       3: dup
       4: aload_0
       5: aload_2
       6: invokevirtual #380                // Method getCategoryStringFor:(Lorg/eclipse/core/runtime/IConfigurationElement;)Ljava/lang/String;
       9: ldc           #1                  // String /
      11: invokespecial #346                // Method java/util/StringTokenizer."<init>":(Ljava/lang/String;Ljava/lang/String;)V
      14: astore_3
      15: aload_0
      16: getfield      #332                // Field wizardElements:Lorg/eclipse/ui/internal/dialogs/WizardCollectionElement;
      19: astore        4
      21: iconst_0
      22: istore        5
      24: goto          54
      27: aload_0
      28: aload         4
      30: aload_3
      31: invokevirtual #345                // Method java/util/StringTokenizer.nextToken:()Ljava/lang/String;
      34: invokevirtual #388                // Method getChildWithID:(Lorg/eclipse/ui/internal/dialogs/WizardCollectionElement;Ljava/lang/String;)Lorg/eclipse/ui/internal/dialogs/WizardCollectionElement;
      37: astore        6
      39: aload         6
      41: ifnonnull     50
      44: iconst_1
      45: istore        5
      47: goto          61
      50: aload         6
      52: astore        4
      54: aload_3
      55: invokevirtual #344                // Method java/util/StringTokenizer.hasMoreElements:()Z
      58: ifne          27
      61: iload         5
      63: ifeq          78
      66: aload_0
      67: aload_0
      68: getfield      #332                // Field wizardElements:Lorg/eclipse/ui/internal/dialogs/WizardCollectionElement;
      71: aload_1
      72: invokevirtual #385                // Method moveElementToUncategorizedCategory:(Lorg/eclipse/ui/internal/dialogs/WizardCollectionElement;Lorg/eclipse/ui/internal/dialogs/WorkbenchWizardElement;)V
      75: goto          91
      78: aload         4
      80: aload_1
      81: invokevirtual #360                // Method org/eclipse/ui/internal/dialogs/WizardCollectionElement.add:(Lorg/eclipse/core/runtime/IAdaptable;)Lorg/eclipse/ui/model/AdaptableList;
      84: pop
      85: aload_1
      86: aload         4
      88: invokevirtual #364                // Method org/eclipse/ui/internal/dialogs/WorkbenchWizardElement.setParent:(Lorg/eclipse/ui/internal/dialogs/WizardCollectionElement;)V
      91: return

  private void finishWizards();
    Code:
       0: aload_0
       1: getfield      #329                // Field deferWizards:Ljava/util/ArrayList;
       4: ifnull        53
       7: aload_0
       8: getfield      #329                // Field deferWizards:Ljava/util/ArrayList;
      11: invokevirtual #340                // Method java/util/ArrayList.iterator:()Ljava/util/Iterator;
      14: astore_1
      15: goto          39
      18: aload_1
      19: invokeinterface #395,  1          // InterfaceMethod java/util/Iterator.next:()Ljava/lang/Object;
      24: checkcast     #183                // class org/eclipse/ui/internal/dialogs/WorkbenchWizardElement
      27: astore_2
      28: aload_2
      29: invokevirtual #362                // Method org/eclipse/ui/internal/dialogs/WorkbenchWizardElement.getConfigurationElement:()Lorg/eclipse/core/runtime/IConfigurationElement;
      32: astore_3
      33: aload_0
      34: aload_2
      35: aload_3
      36: invokevirtual #383                // Method finishWizard:(Lorg/eclipse/ui/internal/dialogs/WorkbenchWizardElement;Lorg/eclipse/core/runtime/IConfigurationElement;)V
      39: aload_1
      40: invokeinterface #394,  1          // InterfaceMethod java/util/Iterator.hasNext:()Z
      45: ifne          18
      48: aload_0
      49: aconst_null
      50: putfield      #329                // Field deferWizards:Ljava/util/ArrayList;
      53: return

  protected java.lang.String getCategoryStringFor(org.eclipse.core.runtime.IConfigurationElement);
    Code:
       0: aload_1
       1: ldc_w         #156                // String category
       4: invokeinterface #400,  2          // InterfaceMethod org/eclipse/core/runtime/IConfigurationElement.getAttribute:(Ljava/lang/String;)Ljava/lang/String;
       9: astore_2
      10: aload_2
      11: ifnonnull     17
      14: ldc           #4                  // String org.eclipse.ui.Other
      16: astore_2
      17: aload_2
      18: areturn

  protected org.eclipse.ui.internal.dialogs.WizardCollectionElement getChildWithID(org.eclipse.ui.internal.dialogs.WizardCollectionElement, java.lang.String);
    Code:
       0: aload_1
       1: aconst_null
       2: invokevirtual #357                // Method org/eclipse/ui/internal/dialogs/WizardCollectionElement.getChildren:(Ljava/lang/Object;)[Ljava/lang/Object;
       5: dup
       6: astore        6
       8: arraylength
       9: istore        5
      11: iconst_0
      12: istore        4
      14: goto          47
      17: aload         6
      19: iload         4
      21: aaload
      22: astore_3
      23: aload_3
      24: checkcast     #182                // class org/eclipse/ui/internal/dialogs/WizardCollectionElement
      27: astore        7
      29: aload         7
      31: invokevirtual #355                // Method org/eclipse/ui/internal/dialogs/WizardCollectionElement.getId:()Ljava/lang/String;
      34: aload_2
      35: invokevirtual #334                // Method java/lang/String.equals:(Ljava/lang/Object;)Z
      38: ifeq          44
      41: aload         7
      43: areturn
      44: iinc          4, 1
      47: iload         4
      49: iload         5
      51: if_icmplt     17
      54: aconst_null
      55: areturn

  protected void moveElementToUncategorizedCategory(org.eclipse.ui.internal.dialogs.WizardCollectionElement, org.eclipse.ui.internal.dialogs.WorkbenchWizardElement);
    Code:
       0: aload_0
       1: aload_1
       2: ldc           #4                  // String org.eclipse.ui.Other
       4: invokevirtual #388                // Method getChildWithID:(Lorg/eclipse/ui/internal/dialogs/WizardCollectionElement;Ljava/lang/String;)Lorg/eclipse/ui/internal/dialogs/WizardCollectionElement;
       7: astore_3
       8: aload_3
       9: ifnonnull     24
      12: aload_0
      13: aload_1
      14: ldc           #4                  // String org.eclipse.ui.Other
      16: aconst_null
      17: getstatic     #325                // Field UNCATEGORIZED_WIZARD_CATEGORY_LABEL:Ljava/lang/String;
      20: invokevirtual #390                // Method createCollectionElement:(Lorg/eclipse/ui/internal/dialogs/WizardCollectionElement;Ljava/lang/String;Ljava/lang/String;Ljava/lang/String;)Lorg/eclipse/ui/internal/dialogs/WizardCollectionElement;
      23: astore_3
      24: aload_3
      25: aload_2
      26: invokevirtual #360                // Method org/eclipse/ui/internal/dialogs/WizardCollectionElement.add:(Lorg/eclipse/core/runtime/IAdaptable;)Lorg/eclipse/ui/model/AdaptableList;
      29: pop
      30: aload_2
      31: aload_3
      32: invokevirtual #364                // Method org/eclipse/ui/internal/dialogs/WorkbenchWizardElement.setParent:(Lorg/eclipse/ui/internal/dialogs/WizardCollectionElement;)V
      35: return

  private void pruneEmptyCategories(org.eclipse.ui.internal.dialogs.WizardCollectionElement);
    Code:
       0: aload_1
       1: aconst_null
       2: invokevirtual #357                // Method org/eclipse/ui/internal/dialogs/WizardCollectionElement.getChildren:(Ljava/lang/Object;)[Ljava/lang/Object;
       5: astore_2
       6: aload_2
       7: dup
       8: astore        6
      10: arraylength
      11: istore        5
      13: iconst_0
      14: istore        4
      16: goto          71
      19: aload         6
      21: iload         4
      23: aaload
      24: astore_3
      25: aload_3
      26: checkcast     #182                // class org/eclipse/ui/internal/dialogs/WizardCollectionElement
      29: astore        7
      31: aload_0
      32: aload         7
      34: invokevirtual #377                // Method pruneEmptyCategories:(Lorg/eclipse/ui/internal/dialogs/WizardCollectionElement;)V
      37: aload         7
      39: invokevirtual #355                // Method org/eclipse/ui/internal/dialogs/WizardCollectionElement.getId:()Ljava/lang/String;
      42: ldc           #3                  // String org.eclipse.ui.Examples
      44: invokevirtual #334                // Method java/lang/String.equals:(Ljava/lang/Object;)Z
      47: istore        8
      49: aload         7
      51: invokevirtual #353                // Method org/eclipse/ui/internal/dialogs/WizardCollectionElement.isEmpty:()Z
      54: ifeq          68
      57: iload         8
      59: ifeq          68
      62: aload_1
      63: aload         7
      65: invokevirtual #356                // Method org/eclipse/ui/internal/dialogs/WizardCollectionElement.remove:(Lorg/eclipse/core/runtime/IAdaptable;)V
      68: iinc          4, 1
      71: iload         4
      73: iload         5
      75: if_icmplt     19
      78: return

  public boolean readElement(org.eclipse.core.runtime.IConfigurationElement);
    Code:
       0: aload_1
       1: invokeinterface #399,  1          // InterfaceMethod org/eclipse/core/runtime/IConfigurationElement.getName:()Ljava/lang/String;
       6: ldc_w         #156                // String category
       9: invokevirtual #334                // Method java/lang/String.equals:(Ljava/lang/Object;)Z
      12: ifeq          22
      15: aload_0
      16: aload_1
      17: invokevirtual #376                // Method deferCategory:(Lorg/eclipse/core/runtime/IConfigurationElement;)V
      20: iconst_1
      21: ireturn
      22: aload_1
      23: invokeinterface #399,  1          // InterfaceMethod org/eclipse/core/runtime/IConfigurationElement.getName:()Ljava/lang/String;
      28: ldc_w         #161                // String primaryWizard
      31: invokevirtual #334                // Method java/lang/String.equals:(Ljava/lang/Object;)Z
      34: ifeq          76
      37: aload_0
      38: getfield      #331                // Field deferPrimary:Ljava/util/Set;
      41: ifnonnull     55
      44: aload_0
      45: new           #171                // class java/util/HashSet
      48: dup
      49: invokespecial #343                // Method java/util/HashSet."<init>":()V
      52: putfield      #331                // Field deferPrimary:Ljava/util/Set;
      55: aload_0
      56: getfield      #331                // Field deferPrimary:Ljava/util/Set;
      59: aload_1
      60: ldc_w         #158                // String id
      63: invokeinterface #400,  2          // InterfaceMethod org/eclipse/core/runtime/IConfigurationElement.getAttribute:(Ljava/lang/String;)Ljava/lang/String;
      68: invokeinterface #397,  2          // InterfaceMethod java/util/Set.add:(Ljava/lang/Object;)Z
      73: pop
      74: iconst_1
      75: ireturn
      76: aload_1
      77: invokeinterface #399,  1          // InterfaceMethod org/eclipse/core/runtime/IConfigurationElement.getName:()Ljava/lang/String;
      82: ldc_w         #162                // String wizard
      85: invokevirtual #334                // Method java/lang/String.equals:(Ljava/lang/Object;)Z
      88: ifne          93
      91: iconst_0
      92: ireturn
      93: aload_0
      94: aload_1
      95: invokevirtual #384                // Method createWizardElement:(Lorg/eclipse/core/runtime/IConfigurationElement;)Lorg/eclipse/ui/internal/dialogs/WorkbenchWizardElement;
      98: astore_2
      99: aload_2
     100: ifnull        109
     103: aload_0
     104: aload_2
     105: aload_1
     106: invokevirtual #382                // Method addNewElementToResult:(Lorg/eclipse/ui/internal/dialogs/WorkbenchWizardElement;Lorg/eclipse/core/runtime/IConfigurationElement;)V
     109: iconst_1
     110: ireturn

  protected void readWizards();
    Code:
       0: aload_0
       1: getfield      #324                // Field readAll:Z
       4: ifeq          35
       7: aload_0
       8: invokevirtual #374                // Method areWizardsRead:()Z
      11: ifne          35
      14: aload_0
      15: invokevirtual #369                // Method createEmptyWizardCollection:()V
      18: invokestatic  #349                // Method org/eclipse/core/runtime/Platform.getExtensionRegistry:()Lorg/eclipse/core/runtime/IExtensionRegistry;
      21: astore_1
      22: aload_0
      23: aload_1
      24: aload_0
      25: getfield      #326                // Field plugin:Ljava/lang/String;
      28: aload_0
      29: getfield      #327                // Field pluginPoint:Ljava/lang/String;
      32: invokevirtual #387                // Method readRegistry:(Lorg/eclipse/core/runtime/IExtensionRegistry;Ljava/lang/String;Ljava/lang/String;)V
      35: aload_0
      36: invokevirtual #370                // Method finishCategories:()V
      39: aload_0
      40: invokevirtual #372                // Method finishWizards:()V
      43: aload_0
      44: invokevirtual #371                // Method finishPrimary:()V
      47: aload_0
      48: getfield      #332                // Field wizardElements:Lorg/eclipse/ui/internal/dialogs/WizardCollectionElement;
      51: ifnull        62
      54: aload_0
      55: aload_0
      56: getfield      #332                // Field wizardElements:Lorg/eclipse/ui/internal/dialogs/WizardCollectionElement;
      59: invokevirtual #377                // Method pruneEmptyCategories:(Lorg/eclipse/ui/internal/dialogs/WizardCollectionElement;)V
      62: return

  public org.eclipse.ui.internal.dialogs.WorkbenchWizardElement[] getPrimaryWizards();
    Code:
       0: aload_0
       1: invokevirtual #374                // Method areWizardsRead:()Z
       4: ifne          11
       7: aload_0
       8: invokevirtual #373                // Method readWizards:()V
      11: aload_0
      12: getfield      #333                // Field primaryWizards:[Lorg/eclipse/ui/internal/dialogs/WorkbenchWizardElement;
      15: invokestatic  #351                // Method org/eclipse/ui/activities/WorkbenchActivityHelper.restrictArray:([Ljava/lang/Object;)[Ljava/lang/Object;
      18: checkcast     #165                // class "[Lorg/eclipse/ui/internal/dialogs/WorkbenchWizardElement;"
      21: areturn

  protected boolean areWizardsRead();
    Code:
       0: aload_0
       1: getfield      #332                // Field wizardElements:Lorg/eclipse/ui/internal/dialogs/WizardCollectionElement;
       4: ifnull        16
       7: aload_0
       8: getfield      #324                // Field readAll:Z
      11: ifeq          16
      14: iconst_1
      15: ireturn
      16: iconst_0
      17: ireturn

  public org.eclipse.ui.internal.dialogs.WizardCollectionElement getWizardElements();
    Code:
       0: aload_0
       1: invokevirtual #374                // Method areWizardsRead:()Z
       4: ifne          11
       7: aload_0
       8: invokevirtual #373                // Method readWizards:()V
      11: aload_0
      12: getfield      #332                // Field wizardElements:Lorg/eclipse/ui/internal/dialogs/WizardCollectionElement;
      15: areturn

  protected java.lang.Object[] getWizardCollectionElements();
    Code:
       0: aload_0
       1: invokevirtual #374                // Method areWizardsRead:()Z
       4: ifne          11
       7: aload_0
       8: invokevirtual #373                // Method readWizards:()V
      11: aload_0
      12: getfield      #332                // Field wizardElements:Lorg/eclipse/ui/internal/dialogs/WizardCollectionElement;
      15: invokevirtual #354                // Method org/eclipse/ui/internal/dialogs/WizardCollectionElement.getChildren:()[Ljava/lang/Object;
      18: areturn

  protected org.eclipse.ui.internal.dialogs.WorkbenchWizardElement createWizardElement(org.eclipse.core.runtime.IConfigurationElement);
    Code:
       0: aload_1
       1: ldc_w         #159                // String name
       4: invokeinterface #400,  2          // InterfaceMethod org/eclipse/core/runtime/IConfigurationElement.getAttribute:(Ljava/lang/String;)Ljava/lang/String;
       9: ifnonnull     21
      12: aload_1
      13: ldc_w         #159                // String name
      16: invokestatic  #381                // Method logMissingAttribute:(Lorg/eclipse/core/runtime/IConfigurationElement;Ljava/lang/String;)V
      19: aconst_null
      20: areturn
      21: aload_1
      22: ldc_w         #157                // String class
      25: invokestatic  #386                // Method getClassValue:(Lorg/eclipse/core/runtime/IConfigurationElement;Ljava/lang/String;)Ljava/lang/String;
      28: ifnonnull     40
      31: aload_1
      32: ldc_w         #157                // String class
      35: invokestatic  #381                // Method logMissingAttribute:(Lorg/eclipse/core/runtime/IConfigurationElement;Ljava/lang/String;)V
      38: aconst_null
      39: areturn
      40: new           #183                // class org/eclipse/ui/internal/dialogs/WorkbenchWizardElement
      43: dup
      44: aload_1
      45: invokespecial #363                // Method org/eclipse/ui/internal/dialogs/WorkbenchWizardElement."<init>":(Lorg/eclipse/core/runtime/IConfigurationElement;)V
      48: areturn

  public org.eclipse.ui.internal.dialogs.WorkbenchWizardElement findWizard(java.lang.String);
    Code:
       0: aload_0
       1: invokevirtual #375                // Method getWizardCollectionElements:()[Ljava/lang/Object;
       4: dup
       5: astore        5
       7: arraylength
       8: istore        4
      10: iconst_0
      11: istore_3
      12: goto          54
      15: aload         5
      17: iload_3
      18: aaload
      19: astore_2
      20: aload_2
      21: checkcast     #182                // class org/eclipse/ui/internal/dialogs/WizardCollectionElement
      24: astore        6
      26: aload         6
      28: aload_1
      29: iconst_1
      30: invokevirtual #359                // Method org/eclipse/ui/internal/dialogs/WizardCollectionElement.findWizard:(Ljava/lang/String;Z)Lorg/eclipse/ui/internal/dialogs/WorkbenchWizardElement;
      33: astore        7
      35: aload         7
      37: ifnull        51
      40: aload         7
      42: invokestatic  #350                // Method org/eclipse/ui/activities/WorkbenchActivityHelper.restrictUseOf:(Ljava/lang/Object;)Z
      45: ifne          51
      48: aload         7
      50: areturn
      51: iinc          3, 1
      54: iload_3
      55: iload         4
      57: if_icmplt     15
      60: aconst_null
      61: areturn
}
