Compiled from "Transaction.java"
public abstract class org.apache.activemq.transaction.Transaction {
  public static final byte START_STATE;

  public static final byte IN_USE_STATE;

  public static final byte PREPARED_STATE;

  public static final byte FINISHED_STATE;

  boolean committed;

  private final java.util.ArrayList<org.apache.activemq.transaction.Synchronization> synchronizations;

  private byte state;

  protected java.util.concurrent.FutureTask<?> preCommitTask;

  protected java.util.concurrent.FutureTask<?> postCommitTask;

  public org.apache.activemq.transaction.Transaction();
    Code:
       0: aload_0
       1: invokespecial #1                  // Method java/lang/Object."<init>":()V
       4: aload_0
       5: iconst_0
       6: putfield      #2                  // Field committed:Z
       9: aload_0
      10: new           #3                  // class java/util/ArrayList
      13: dup
      14: invokespecial #4                  // Method java/util/ArrayList."<init>":()V
      17: putfield      #5                  // Field synchronizations:Ljava/util/ArrayList;
      20: aload_0
      21: iconst_0
      22: putfield      #6                  // Field state:B
      25: aload_0
      26: new           #7                  // class java/util/concurrent/FutureTask
      29: dup
      30: new           #8                  // class org/apache/activemq/transaction/Transaction$1
      33: dup
      34: aload_0
      35: invokespecial #9                  // Method org/apache/activemq/transaction/Transaction$1."<init>":(Lorg/apache/activemq/transaction/Transaction;)V
      38: invokespecial #10                 // Method java/util/concurrent/FutureTask."<init>":(Ljava/util/concurrent/Callable;)V
      41: putfield      #11                 // Field preCommitTask:Ljava/util/concurrent/FutureTask;
      44: aload_0
      45: new           #7                  // class java/util/concurrent/FutureTask
      48: dup
      49: new           #12                 // class org/apache/activemq/transaction/Transaction$2
      52: dup
      53: aload_0
      54: invokespecial #13                 // Method org/apache/activemq/transaction/Transaction$2."<init>":(Lorg/apache/activemq/transaction/Transaction;)V
      57: invokespecial #10                 // Method java/util/concurrent/FutureTask."<init>":(Ljava/util/concurrent/Callable;)V
      60: putfield      #14                 // Field postCommitTask:Ljava/util/concurrent/FutureTask;
      63: return

  public byte getState();
    Code:
       0: aload_0
       1: getfield      #6                  // Field state:B
       4: ireturn

  public void setState(byte);
    Code:
       0: aload_0
       1: iload_1
       2: putfield      #6                  // Field state:B
       5: return

  public boolean isCommitted();
    Code:
       0: aload_0
       1: getfield      #2                  // Field committed:Z
       4: ireturn

  public void setCommitted(boolean);
    Code:
       0: aload_0
       1: iload_1
       2: putfield      #2                  // Field committed:Z
       5: return

  public void addSynchronization(org.apache.activemq.transaction.Synchronization);
    Code:
       0: aload_0
       1: getfield      #5                  // Field synchronizations:Ljava/util/ArrayList;
       4: aload_1
       5: invokevirtual #15                 // Method java/util/ArrayList.add:(Ljava/lang/Object;)Z
       8: pop
       9: aload_0
      10: getfield      #6                  // Field state:B
      13: ifne          21
      16: aload_0
      17: iconst_1
      18: putfield      #6                  // Field state:B
      21: return

  public org.apache.activemq.transaction.Synchronization findMatching(org.apache.activemq.transaction.Synchronization);
    Code:
       0: aload_0
       1: getfield      #5                  // Field synchronizations:Ljava/util/ArrayList;
       4: aload_1
       5: invokevirtual #16                 // Method java/util/ArrayList.indexOf:(Ljava/lang/Object;)I
       8: istore_2
       9: iload_2
      10: iconst_m1
      11: if_icmpeq     26
      14: aload_0
      15: getfield      #5                  // Field synchronizations:Ljava/util/ArrayList;
      18: iload_2
      19: invokevirtual #17                 // Method java/util/ArrayList.get:(I)Ljava/lang/Object;
      22: checkcast     #18                 // class org/apache/activemq/transaction/Synchronization
      25: areturn
      26: aconst_null
      27: areturn

  public void removeSynchronization(org.apache.activemq.transaction.Synchronization);
    Code:
       0: aload_0
       1: getfield      #5                  // Field synchronizations:Ljava/util/ArrayList;
       4: aload_1
       5: invokevirtual #19                 // Method java/util/ArrayList.remove:(Ljava/lang/Object;)Z
       8: pop
       9: return

  public void prePrepare() throws java.lang.Exception;
    Code:
       0: aload_0
       1: getfield      #6                  // Field state:B
       4: lookupswitch  { // 2
                     0: 32
                     1: 32
               default: 35
          }
      32: goto          53
      35: new           #20                 // class javax/transaction/xa/XAException
      38: dup
      39: ldc           #21                 // String Prepare cannot be called now.
      41: invokespecial #22                 // Method javax/transaction/xa/XAException."<init>":(Ljava/lang/String;)V
      44: astore_1
      45: aload_1
      46: bipush        -6
      48: putfield      #23                 // Field javax/transaction/xa/XAException.errorCode:I
      51: aload_1
      52: athrow
      53: return

  protected void fireBeforeCommit() throws java.lang.Exception;
    Code:
       0: aload_0
       1: getfield      #5                  // Field synchronizations:Ljava/util/ArrayList;
       4: invokevirtual #24                 // Method java/util/ArrayList.iterator:()Ljava/util/Iterator;
       7: astore_1
       8: aload_1
       9: invokeinterface #25,  1           // InterfaceMethod java/util/Iterator.hasNext:()Z
      14: ifeq          34
      17: aload_1
      18: invokeinterface #26,  1           // InterfaceMethod java/util/Iterator.next:()Ljava/lang/Object;
      23: checkcast     #18                 // class org/apache/activemq/transaction/Synchronization
      26: astore_2
      27: aload_2
      28: invokevirtual #27                 // Method org/apache/activemq/transaction/Synchronization.beforeCommit:()V
      31: goto          8
      34: return

  protected void fireAfterCommit() throws java.lang.Exception;
    Code:
       0: aload_0
       1: getfield      #5                  // Field synchronizations:Ljava/util/ArrayList;
       4: invokevirtual #24                 // Method java/util/ArrayList.iterator:()Ljava/util/Iterator;
       7: astore_1
       8: aload_1
       9: invokeinterface #25,  1           // InterfaceMethod java/util/Iterator.hasNext:()Z
      14: ifeq          34
      17: aload_1
      18: invokeinterface #26,  1           // InterfaceMethod java/util/Iterator.next:()Ljava/lang/Object;
      23: checkcast     #18                 // class org/apache/activemq/transaction/Synchronization
      26: astore_2
      27: aload_2
      28: invokevirtual #28                 // Method org/apache/activemq/transaction/Synchronization.afterCommit:()V
      31: goto          8
      34: return

  public void fireAfterRollback() throws java.lang.Exception;
    Code:
       0: aload_0
       1: getfield      #5                  // Field synchronizations:Ljava/util/ArrayList;
       4: invokestatic  #29                 // Method java/util/Collections.reverse:(Ljava/util/List;)V
       7: aload_0
       8: getfield      #5                  // Field synchronizations:Ljava/util/ArrayList;
      11: invokevirtual #24                 // Method java/util/ArrayList.iterator:()Ljava/util/Iterator;
      14: astore_1
      15: aload_1
      16: invokeinterface #25,  1           // InterfaceMethod java/util/Iterator.hasNext:()Z
      21: ifeq          41
      24: aload_1
      25: invokeinterface #26,  1           // InterfaceMethod java/util/Iterator.next:()Ljava/lang/Object;
      30: checkcast     #18                 // class org/apache/activemq/transaction/Synchronization
      33: astore_2
      34: aload_2
      35: invokevirtual #30                 // Method org/apache/activemq/transaction/Synchronization.afterRollback:()V
      38: goto          15
      41: return

  public java.lang.String toString();
    Code:
       0: new           #31                 // class java/lang/StringBuilder
       3: dup
       4: invokespecial #32                 // Method java/lang/StringBuilder."<init>":()V
       7: ldc           #33                 // String Local-
       9: invokevirtual #34                 // Method java/lang/StringBuilder.append:(Ljava/lang/String;)Ljava/lang/StringBuilder;
      12: aload_0
      13: invokevirtual #35                 // Method getTransactionId:()Lorg/apache/activemq/command/TransactionId;
      16: invokevirtual #36                 // Method java/lang/StringBuilder.append:(Ljava/lang/Object;)Ljava/lang/StringBuilder;
      19: ldc           #37                 // String [synchronizations=
      21: invokevirtual #34                 // Method java/lang/StringBuilder.append:(Ljava/lang/String;)Ljava/lang/StringBuilder;
      24: aload_0
      25: getfield      #5                  // Field synchronizations:Ljava/util/ArrayList;
      28: invokevirtual #36                 // Method java/lang/StringBuilder.append:(Ljava/lang/Object;)Ljava/lang/StringBuilder;
      31: ldc           #38                 // String ]
      33: invokevirtual #34                 // Method java/lang/StringBuilder.append:(Ljava/lang/String;)Ljava/lang/StringBuilder;
      36: invokevirtual #39                 // Method java/lang/StringBuilder.toString:()Ljava/lang/String;
      39: areturn

  public abstract void commit(boolean) throws javax.transaction.xa.XAException, java.io.IOException;

  public abstract void rollback() throws javax.transaction.xa.XAException, java.io.IOException;

  public abstract int prepare() throws javax.transaction.xa.XAException, java.io.IOException;

  public abstract org.apache.activemq.command.TransactionId getTransactionId();

  public abstract org.slf4j.Logger getLog();

  public boolean isPrepared();
    Code:
       0: aload_0
       1: invokevirtual #40                 // Method getState:()B
       4: iconst_2
       5: if_icmpne     12
       8: iconst_1
       9: goto          13
      12: iconst_0
      13: ireturn

  public int size();
    Code:
       0: aload_0
       1: getfield      #5                  // Field synchronizations:Ljava/util/ArrayList;
       4: invokevirtual #41                 // Method java/util/ArrayList.size:()I
       7: ireturn

  protected void waitPostCommitDone(java.util.concurrent.FutureTask<?>) throws javax.transaction.xa.XAException, java.io.IOException;
    Code:
       0: aload_1
       1: invokevirtual #42                 // Method java/util/concurrent/FutureTask.get:()Ljava/lang/Object;
       4: pop
       5: goto          63
       8: astore_2
       9: new           #44                 // class java/io/InterruptedIOException
      12: dup
      13: aload_2
      14: invokevirtual #45                 // Method java/lang/InterruptedException.toString:()Ljava/lang/String;
      17: invokespecial #46                 // Method java/io/InterruptedIOException."<init>":(Ljava/lang/String;)V
      20: athrow
      21: astore_2
      22: aload_2
      23: invokevirtual #48                 // Method java/util/concurrent/ExecutionException.getCause:()Ljava/lang/Throwable;
      26: astore_3
      27: aload_3
      28: instanceof    #20                 // class javax/transaction/xa/XAException
      31: ifeq          39
      34: aload_3
      35: checkcast     #20                 // class javax/transaction/xa/XAException
      38: athrow
      39: aload_3
      40: instanceof    #49                 // class java/io/IOException
      43: ifeq          51
      46: aload_3
      47: checkcast     #49                 // class java/io/IOException
      50: athrow
      51: new           #20                 // class javax/transaction/xa/XAException
      54: dup
      55: aload_2
      56: invokevirtual #50                 // Method java/util/concurrent/ExecutionException.toString:()Ljava/lang/String;
      59: invokespecial #22                 // Method javax/transaction/xa/XAException."<init>":(Ljava/lang/String;)V
      62: athrow
      63: return
    Exception table:
       from    to  target type
           0     5     8   Class java/lang/InterruptedException
           0     5    21   Class java/util/concurrent/ExecutionException

  protected void doPreCommit() throws javax.transaction.xa.XAException;
    Code:
       0: aload_0
       1: invokevirtual #51                 // Method fireBeforeCommit:()V
       4: goto          44
       7: astore_1
       8: aload_0
       9: invokevirtual #53                 // Method getLog:()Lorg/slf4j/Logger;
      12: ldc           #54                 // String PRE COMMIT FAILED:
      14: aload_1
      15: invokeinterface #55,  3           // InterfaceMethod org/slf4j/Logger.warn:(Ljava/lang/String;Ljava/lang/Throwable;)V
      20: new           #20                 // class javax/transaction/xa/XAException
      23: dup
      24: ldc           #56                 // String PRE COMMIT FAILED
      26: invokespecial #22                 // Method javax/transaction/xa/XAException."<init>":(Ljava/lang/String;)V
      29: astore_2
      30: aload_2
      31: bipush        -3
      33: putfield      #23                 // Field javax/transaction/xa/XAException.errorCode:I
      36: aload_2
      37: aload_1
      38: invokevirtual #57                 // Method javax/transaction/xa/XAException.initCause:(Ljava/lang/Throwable;)Ljava/lang/Throwable;
      41: pop
      42: aload_2
      43: athrow
      44: return
    Exception table:
       from    to  target type
           0     4     7   Class java/lang/Throwable

  protected void doPostCommit() throws javax.transaction.xa.XAException;
    Code:
       0: aload_0
       1: iconst_1
       2: invokevirtual #58                 // Method setCommitted:(Z)V
       5: aload_0
       6: invokevirtual #59                 // Method fireAfterCommit:()V
       9: goto          49
      12: astore_1
      13: aload_0
      14: invokevirtual #53                 // Method getLog:()Lorg/slf4j/Logger;
      17: ldc           #60                 // String POST COMMIT FAILED:
      19: aload_1
      20: invokeinterface #55,  3           // InterfaceMethod org/slf4j/Logger.warn:(Ljava/lang/String;Ljava/lang/Throwable;)V
      25: new           #20                 // class javax/transaction/xa/XAException
      28: dup
      29: ldc           #61                 // String POST COMMIT FAILED
      31: invokespecial #22                 // Method javax/transaction/xa/XAException."<init>":(Ljava/lang/String;)V
      34: astore_2
      35: aload_2
      36: bipush        -3
      38: putfield      #23                 // Field javax/transaction/xa/XAException.errorCode:I
      41: aload_2
      42: aload_1
      43: invokevirtual #57                 // Method javax/transaction/xa/XAException.initCause:(Ljava/lang/Throwable;)Ljava/lang/Throwable;
      46: pop
      47: aload_2
      48: athrow
      49: return
    Exception table:
       from    to  target type
           0     9    12   Class java/lang/Throwable
}
