Compiled from "AbstractBuilderProcessor.java"
final class io.sundr.builder.internal.processor.AbstractBuilderProcessor$1 extends io.sundr.builder.TypedVisitor<io.sundr.codegen.model.ClassRefBuilder> {
  final io.sundr.codegen.model.TypeDef val$builderType;

  final io.sundr.codegen.model.TypeDef val$shallowInlineType;

  io.sundr.builder.internal.processor.AbstractBuilderProcessor$1(io.sundr.codegen.model.TypeDef, io.sundr.codegen.model.TypeDef);
    Code:
       0: aload_0
       1: aload_1
       2: putfield      #1                  // Field val$builderType:Lio/sundr/codegen/model/TypeDef;
       5: aload_0
       6: aload_2
       7: putfield      #2                  // Field val$shallowInlineType:Lio/sundr/codegen/model/TypeDef;
      10: aload_0
      11: invokespecial #3                  // Method io/sundr/builder/TypedVisitor."<init>":()V
      14: return

  public void visit(io.sundr.codegen.model.ClassRefBuilder);
    Code:
       0: new           #4                  // class java/util/ArrayList
       3: dup
       4: invokespecial #5                  // Method java/util/ArrayList."<init>":()V
       7: astore_2
       8: aload_1
       9: invokevirtual #6                  // Method io/sundr/codegen/model/ClassRefBuilder.getArguments:()Ljava/util/List;
      12: invokeinterface #7,  1            // InterfaceMethod java/util/List.iterator:()Ljava/util/Iterator;
      17: astore_3
      18: aload_3
      19: invokeinterface #8,  1            // InterfaceMethod java/util/Iterator.hasNext:()Z
      24: ifeq          82
      27: aload_3
      28: invokeinterface #9,  1            // InterfaceMethod java/util/Iterator.next:()Ljava/lang/Object;
      33: checkcast     #10                 // class io/sundr/codegen/model/TypeRef
      36: astore        4
      38: aload         4
      40: aload_0
      41: getfield      #1                  // Field val$builderType:Lio/sundr/codegen/model/TypeDef;
      44: invokevirtual #11                 // Method io/sundr/codegen/model/TypeDef.toInternalReference:()Lio/sundr/codegen/model/ClassRef;
      47: invokevirtual #12                 // Method java/lang/Object.equals:(Ljava/lang/Object;)Z
      50: ifeq          70
      53: aload_2
      54: aload_0
      55: getfield      #2                  // Field val$shallowInlineType:Lio/sundr/codegen/model/TypeDef;
      58: invokevirtual #11                 // Method io/sundr/codegen/model/TypeDef.toInternalReference:()Lio/sundr/codegen/model/ClassRef;
      61: invokeinterface #13,  2           // InterfaceMethod java/util/List.add:(Ljava/lang/Object;)Z
      66: pop
      67: goto          79
      70: aload_2
      71: aload         4
      73: invokeinterface #13,  2           // InterfaceMethod java/util/List.add:(Ljava/lang/Object;)Z
      78: pop
      79: goto          18
      82: aload_1
      83: aload_2
      84: invokevirtual #14                 // Method io/sundr/codegen/model/ClassRefBuilder.withArguments:(Ljava/util/List;)Lio/sundr/codegen/model/ClassRefFluent;
      87: pop
      88: return

  public void visit(java.lang.Object);
    Code:
       0: aload_0
       1: aload_1
       2: checkcast     #15                 // class io/sundr/codegen/model/ClassRefBuilder
       5: invokevirtual #16                 // Method visit:(Lio/sundr/codegen/model/ClassRefBuilder;)V
       8: return
}
