Compiled from "ChunkedStreamSourceConduit.java"
class io.undertow.conduits.ChunkedStreamSourceConduit$1 implements io.undertow.conduits.ChunkedStreamSourceConduit$BufferWrapper {
  final io.undertow.connector.ByteBufferPool val$pool;

  final org.xnio.conduits.PushBackStreamSourceConduit val$channel;

  io.undertow.conduits.ChunkedStreamSourceConduit$1(io.undertow.connector.ByteBufferPool, org.xnio.conduits.PushBackStreamSourceConduit);
    Code:
       0: aload_0
       1: aload_1
       2: putfield      #1                  // Field val$pool:Lio/undertow/connector/ByteBufferPool;
       5: aload_0
       6: aload_2
       7: putfield      #2                  // Field val$channel:Lorg/xnio/conduits/PushBackStreamSourceConduit;
      10: aload_0
      11: invokespecial #3                  // Method java/lang/Object."<init>":()V
      14: return

  public io.undertow.connector.PooledByteBuffer allocate();
    Code:
       0: aload_0
       1: getfield      #1                  // Field val$pool:Lio/undertow/connector/ByteBufferPool;
       4: invokeinterface #4,  1            // InterfaceMethod io/undertow/connector/ByteBufferPool.allocate:()Lio/undertow/connector/PooledByteBuffer;
       9: areturn

  public void pushBack(io.undertow.connector.PooledByteBuffer);
    Code:
       0: aload_0
       1: getfield      #2                  // Field val$channel:Lorg/xnio/conduits/PushBackStreamSourceConduit;
       4: new           #5                  // class io/undertow/util/PooledAdaptor
       7: dup
       8: aload_1
       9: invokespecial #6                  // Method io/undertow/util/PooledAdaptor."<init>":(Lio/undertow/connector/PooledByteBuffer;)V
      12: invokevirtual #7                  // Method org/xnio/conduits/PushBackStreamSourceConduit.pushBack:(Lorg/xnio/Pooled;)V
      15: return
}
