Compiled from "SSLContextServerParameters.java"
public class org.apache.camel.util.jsse.SSLContextServerParameters extends org.apache.camel.util.jsse.BaseSSLContextParameters {
  private static final org.slf4j.Logger LOG;

  protected java.lang.String clientAuthentication;

  public org.apache.camel.util.jsse.SSLContextServerParameters();
    Code:
       0: aload_0
       1: invokespecial #22                 // Method org/apache/camel/util/jsse/BaseSSLContextParameters."<init>":()V
       4: return

  public java.lang.String getClientAuthentication();
    Code:
       0: aload_0
       1: getfield      #28                 // Field clientAuthentication:Ljava/lang/String;
       4: areturn

  public void setClientAuthentication(java.lang.String);
    Code:
       0: aload_0
       1: aload_1
       2: putfield      #28                 // Field clientAuthentication:Ljava/lang/String;
       5: return

  protected boolean getAllowPassthrough();
    Code:
       0: iconst_1
       1: ireturn

  protected void configureSSLContext(javax.net.ssl.SSLContext) throws java.security.GeneralSecurityException;
    Code:
       0: getstatic     #39                 // Field LOG:Lorg/slf4j/Logger;
       3: ldc           #41                 // String Configuring server-side SSLContext parameters on SSLContext [{}]...
       5: aload_1
       6: invokeinterface #47,  3           // InterfaceMethod org/slf4j/Logger.trace:(Ljava/lang/String;Ljava/lang/Object;)V
      11: aload_0
      12: invokevirtual #50                 // Method getSessionTimeout:()Ljava/lang/String;
      15: ifnull        45
      18: getstatic     #39                 // Field LOG:Lorg/slf4j/Logger;
      21: ldc           #52                 // String Configuring server-side SSLContext session timeout on SSLContext [{}] to [{}].
      23: aload_1
      24: aload_0
      25: invokevirtual #50                 // Method getSessionTimeout:()Ljava/lang/String;
      28: invokeinterface #56,  4           // InterfaceMethod org/slf4j/Logger.debug:(Ljava/lang/String;Ljava/lang/Object;Ljava/lang/Object;)V
      33: aload_0
      34: aload_1
      35: invokevirtual #62                 // Method javax/net/ssl/SSLContext.getServerSessionContext:()Ljavax/net/ssl/SSLSessionContext;
      38: aload_0
      39: invokevirtual #50                 // Method getSessionTimeout:()Ljava/lang/String;
      42: invokevirtual #66                 // Method configureSessionContext:(Ljavax/net/ssl/SSLSessionContext;Ljava/lang/String;)V
      45: getstatic     #39                 // Field LOG:Lorg/slf4j/Logger;
      48: ldc           #68                 // String Configured server-side SSLContext parameters on SSLContext [{}].
      50: aload_1
      51: invokeinterface #47,  3           // InterfaceMethod org/slf4j/Logger.trace:(Ljava/lang/String;Ljava/lang/Object;)V
      56: return

  protected java.util.List<org.apache.camel.util.jsse.BaseSSLContextParameters$Configurer<javax.net.ssl.SSLEngine>> getSSLEngineConfigurers(javax.net.ssl.SSLContext);
    Code:
       0: new           #74                 // class java/util/LinkedList
       3: dup
       4: invokespecial #75                 // Method java/util/LinkedList."<init>":()V
       7: astore_2
       8: aload_0
       9: invokevirtual #77                 // Method getClientAuthentication:()Ljava/lang/String;
      12: ifnull        47
      15: aload_0
      16: aload_0
      17: invokevirtual #77                 // Method getClientAuthentication:()Ljava/lang/String;
      20: invokevirtual #81                 // Method parsePropertyValue:(Ljava/lang/String;)Ljava/lang/String;
      23: invokestatic  #87                 // Method org/apache/camel/util/jsse/ClientAuthentication.valueOf:(Ljava/lang/String;)Lorg/apache/camel/util/jsse/ClientAuthentication;
      26: astore_3
      27: new           #11                 // class org/apache/camel/util/jsse/SSLContextServerParameters$1
      30: dup
      31: aload_0
      32: aload_3
      33: invokespecial #90                 // Method org/apache/camel/util/jsse/SSLContextServerParameters$1."<init>":(Lorg/apache/camel/util/jsse/SSLContextServerParameters;Lorg/apache/camel/util/jsse/ClientAuthentication;)V
      36: astore        4
      38: aload_2
      39: aload         4
      41: invokeinterface #96,  2           // InterfaceMethod java/util/List.add:(Ljava/lang/Object;)Z
      46: pop
      47: aload_2
      48: areturn

  protected java.util.List<org.apache.camel.util.jsse.BaseSSLContextParameters$Configurer<javax.net.ssl.SSLServerSocket>> getSSLServerSocketFactorySSLServerSocketConfigurers(javax.net.ssl.SSLContext);
    Code:
       0: aload_0
       1: aload_1
       2: invokespecial #107                // Method org/apache/camel/util/jsse/BaseSSLContextParameters.getSSLServerSocketFactorySSLServerSocketConfigurers:(Ljavax/net/ssl/SSLContext;)Ljava/util/List;
       5: astore_2
       6: aload_0
       7: invokevirtual #77                 // Method getClientAuthentication:()Ljava/lang/String;
      10: ifnull        45
      13: aload_0
      14: aload_0
      15: invokevirtual #77                 // Method getClientAuthentication:()Ljava/lang/String;
      18: invokevirtual #81                 // Method parsePropertyValue:(Ljava/lang/String;)Ljava/lang/String;
      21: invokestatic  #87                 // Method org/apache/camel/util/jsse/ClientAuthentication.valueOf:(Ljava/lang/String;)Lorg/apache/camel/util/jsse/ClientAuthentication;
      24: astore_3
      25: new           #9                  // class org/apache/camel/util/jsse/SSLContextServerParameters$2
      28: dup
      29: aload_0
      30: aload_3
      31: invokespecial #108                // Method org/apache/camel/util/jsse/SSLContextServerParameters$2."<init>":(Lorg/apache/camel/util/jsse/SSLContextServerParameters;Lorg/apache/camel/util/jsse/ClientAuthentication;)V
      34: astore        4
      36: aload_2
      37: aload         4
      39: invokeinterface #96,  2           // InterfaceMethod java/util/List.add:(Ljava/lang/Object;)Z
      44: pop
      45: aload_2
      46: areturn

  protected java.util.List<org.apache.camel.util.jsse.BaseSSLContextParameters$Configurer<javax.net.ssl.SSLSocketFactory>> getSSLSocketFactoryConfigurers(javax.net.ssl.SSLContext);
    Code:
       0: invokestatic  #119                // Method java/util/Collections.emptyList:()Ljava/util/List;
       3: areturn

  public java.lang.String toString();
    Code:
       0: new           #122                // class java/lang/StringBuilder
       3: dup
       4: invokespecial #123                // Method java/lang/StringBuilder."<init>":()V
       7: astore_1
       8: aload_1
       9: ldc           #125                // String SSLContextServerParameters [clientAuthentication=
      11: invokevirtual #129                // Method java/lang/StringBuilder.append:(Ljava/lang/String;)Ljava/lang/StringBuilder;
      14: pop
      15: aload_1
      16: aload_0
      17: getfield      #28                 // Field clientAuthentication:Ljava/lang/String;
      20: invokevirtual #129                // Method java/lang/StringBuilder.append:(Ljava/lang/String;)Ljava/lang/StringBuilder;
      23: pop
      24: aload_1
      25: ldc           #131                // String , getCipherSuites()=
      27: invokevirtual #129                // Method java/lang/StringBuilder.append:(Ljava/lang/String;)Ljava/lang/StringBuilder;
      30: pop
      31: aload_1
      32: aload_0
      33: invokevirtual #135                // Method getCipherSuites:()Lorg/apache/camel/util/jsse/CipherSuitesParameters;
      36: invokevirtual #138                // Method java/lang/StringBuilder.append:(Ljava/lang/Object;)Ljava/lang/StringBuilder;
      39: pop
      40: aload_1
      41: ldc           #140                // String , getCipherSuitesFilter()=
      43: invokevirtual #129                // Method java/lang/StringBuilder.append:(Ljava/lang/String;)Ljava/lang/StringBuilder;
      46: pop
      47: aload_1
      48: aload_0
      49: invokevirtual #144                // Method getCipherSuitesFilter:()Lorg/apache/camel/util/jsse/FilterParameters;
      52: invokevirtual #138                // Method java/lang/StringBuilder.append:(Ljava/lang/Object;)Ljava/lang/StringBuilder;
      55: pop
      56: aload_1
      57: ldc           #146                // String , getSecureSocketProtocols()=
      59: invokevirtual #129                // Method java/lang/StringBuilder.append:(Ljava/lang/String;)Ljava/lang/StringBuilder;
      62: pop
      63: aload_1
      64: aload_0
      65: invokevirtual #150                // Method getSecureSocketProtocols:()Lorg/apache/camel/util/jsse/SecureSocketProtocolsParameters;
      68: invokevirtual #138                // Method java/lang/StringBuilder.append:(Ljava/lang/Object;)Ljava/lang/StringBuilder;
      71: pop
      72: aload_1
      73: ldc           #152                // String , getSecureSocketProtocolsFilter()=
      75: invokevirtual #129                // Method java/lang/StringBuilder.append:(Ljava/lang/String;)Ljava/lang/StringBuilder;
      78: pop
      79: aload_1
      80: aload_0
      81: invokevirtual #155                // Method getSecureSocketProtocolsFilter:()Lorg/apache/camel/util/jsse/FilterParameters;
      84: invokevirtual #138                // Method java/lang/StringBuilder.append:(Ljava/lang/Object;)Ljava/lang/StringBuilder;
      87: pop
      88: aload_1
      89: ldc           #157                // String , getSessionTimeout()=
      91: invokevirtual #129                // Method java/lang/StringBuilder.append:(Ljava/lang/String;)Ljava/lang/StringBuilder;
      94: pop
      95: aload_1
      96: aload_0
      97: invokevirtual #50                 // Method getSessionTimeout:()Ljava/lang/String;
     100: invokevirtual #129                // Method java/lang/StringBuilder.append:(Ljava/lang/String;)Ljava/lang/StringBuilder;
     103: pop
     104: aload_1
     105: ldc           #159                // String , getContext()=
     107: invokevirtual #129                // Method java/lang/StringBuilder.append:(Ljava/lang/String;)Ljava/lang/StringBuilder;
     110: pop
     111: aload_1
     112: aload_0
     113: invokevirtual #163                // Method getCamelContext:()Lorg/apache/camel/CamelContext;
     116: invokevirtual #138                // Method java/lang/StringBuilder.append:(Ljava/lang/Object;)Ljava/lang/StringBuilder;
     119: pop
     120: aload_1
     121: ldc           #165                // String ]
     123: invokevirtual #129                // Method java/lang/StringBuilder.append:(Ljava/lang/String;)Ljava/lang/StringBuilder;
     126: pop
     127: aload_1
     128: invokevirtual #167                // Method java/lang/StringBuilder.toString:()Ljava/lang/String;
     131: areturn

  static org.slf4j.Logger access$000();
    Code:
       0: getstatic     #39                 // Field LOG:Lorg/slf4j/Logger;
       3: areturn

  static {};
    Code:
       0: ldc           #2                  // class org/apache/camel/util/jsse/SSLContextServerParameters
       2: invokestatic  #178                // Method org/slf4j/LoggerFactory.getLogger:(Ljava/lang/Class;)Lorg/slf4j/Logger;
       5: putstatic     #39                 // Field LOG:Lorg/slf4j/Logger;
       8: return
}
