Compiled from "DeleteOp.java"
class org.jboss.as.patching.management.DeleteOp$PrepareException extends java.lang.RuntimeException {
  private final java.lang.String path;

  public org.jboss.as.patching.management.DeleteOp$PrepareException(java.io.File);
    Code:
       0: aload_0
       1: invokespecial #1                  // Method java/lang/RuntimeException."<init>":()V
       4: aload_0
       5: aload_1
       6: invokevirtual #2                  // Method java/io/File.getAbsolutePath:()Ljava/lang/String;
       9: putfield      #3                  // Field path:Ljava/lang/String;
      12: return

  public java.lang.String getPath();
    Code:
       0: aload_0
       1: getfield      #3                  // Field path:Ljava/lang/String;
       4: areturn
}
