Compiled from "LocalShowHistoryHandler.java"
public final class org.jboss.as.patching.management.LocalShowHistoryHandler extends org.jboss.as.patching.management.PatchStreamResourceOperationStepHandler {
  public static final org.jboss.as.controller.OperationStepHandler INSTANCE;

  public org.jboss.as.patching.management.LocalShowHistoryHandler();
    Code:
       0: aload_0
       1: invokespecial #1                  // Method org/jboss/as/patching/management/PatchStreamResourceOperationStepHandler."<init>":()V
       4: return

  protected void execute(org.jboss.as.controller.OperationContext, org.jboss.dmr.ModelNode, org.jboss.as.patching.installation.InstalledIdentity) throws org.jboss.as.controller.OperationFailedException;
    Code:
       0: getstatic     #2                  // Field org/jboss/as/patching/management/PatchResourceDefinition.EXCLUDE_AGEDOUT:Lorg/jboss/as/controller/AttributeDefinition;
       3: aload_1
       4: aload_2
       5: invokevirtual #3                  // Method org/jboss/as/controller/AttributeDefinition.resolveModelAttribute:(Lorg/jboss/as/controller/OperationContext;Lorg/jboss/dmr/ModelNode;)Lorg/jboss/dmr/ModelNode;
       8: invokevirtual #4                  // Method org/jboss/dmr/ModelNode.asBoolean:()Z
      11: istore        4
      13: aload_3
      14: invokevirtual #5                  // Method org/jboss/as/patching/installation/InstalledIdentity.getIdentity:()Lorg/jboss/as/patching/installation/Identity;
      17: invokeinterface #6,  1            // InterfaceMethod org/jboss/as/patching/installation/Identity.loadTargetInfo:()Lorg/jboss/as/patching/installation/PatchableTarget$TargetInfo;
      22: astore        5
      24: aload_3
      25: aload         5
      27: iload         4
      29: invokestatic  #7                  // Method org/jboss/as/patching/tool/PatchingHistory$Factory.getHistory:(Lorg/jboss/as/patching/installation/InstalledIdentity;Lorg/jboss/as/patching/installation/PatchableTarget$TargetInfo;Z)Lorg/jboss/dmr/ModelNode;
      32: astore        6
      34: aload_1
      35: invokeinterface #8,  1            // InterfaceMethod org/jboss/as/controller/OperationContext.getResult:()Lorg/jboss/dmr/ModelNode;
      40: aload         6
      42: invokevirtual #9                  // Method org/jboss/dmr/ModelNode.set:(Lorg/jboss/dmr/ModelNode;)Lorg/jboss/dmr/ModelNode;
      45: pop
      46: goto          78
      49: astore        5
      51: getstatic     #11                 // Field org/jboss/as/patching/logging/PatchLogger.ROOT_LOGGER:Lorg/jboss/as/patching/logging/PatchLogger;
      54: aload         5
      56: ldc           #12                 // String failed to get history
      58: iconst_0
      59: anewarray     #13                 // class java/lang/Object
      62: invokeinterface #14,  4           // InterfaceMethod org/jboss/as/patching/logging/PatchLogger.debugf:(Ljava/lang/Throwable;Ljava/lang/String;[Ljava/lang/Object;)V
      67: getstatic     #11                 // Field org/jboss/as/patching/logging/PatchLogger.ROOT_LOGGER:Lorg/jboss/as/patching/logging/PatchLogger;
      70: aload         5
      72: invokeinterface #15,  2           // InterfaceMethod org/jboss/as/patching/logging/PatchLogger.failedToShowHistory:(Ljava/lang/Throwable;)Lorg/jboss/as/controller/OperationFailedException;
      77: athrow
      78: return
    Exception table:
       from    to  target type
          13    46    49   Class java/lang/Throwable

  public void execute(org.jboss.as.controller.OperationContext, org.jboss.dmr.ModelNode) throws org.jboss.as.controller.OperationFailedException;
    Code:
       0: aload_0
       1: aload_1
       2: aload_2
       3: invokespecial #16                 // Method org/jboss/as/patching/management/PatchStreamResourceOperationStepHandler.execute:(Lorg/jboss/as/controller/OperationContext;Lorg/jboss/dmr/ModelNode;)V
       6: return

  static {};
    Code:
       0: new           #17                 // class org/jboss/as/patching/management/LocalShowHistoryHandler
       3: dup
       4: invokespecial #18                 // Method "<init>":()V
       7: putstatic     #19                 // Field INSTANCE:Lorg/jboss/as/controller/OperationStepHandler;
      10: return
}
