Compiled from "WDTD.java"
public class com.ctc.wstx.evt.WDTD extends org.codehaus.stax2.ri.evt.DTDEventImpl {
  final com.ctc.wstx.dtd.DTDSubset mSubset;

  java.util.List<javax.xml.stream.events.EntityDeclaration> mEntities;

  java.util.List<javax.xml.stream.events.NotationDeclaration> mNotations;

  public com.ctc.wstx.evt.WDTD(javax.xml.stream.Location, java.lang.String, java.lang.String, java.lang.String, java.lang.String, com.ctc.wstx.dtd.DTDSubset);
    Code:
       0: aload_0
       1: aload_1
       2: aload_2
       3: aload_3
       4: aload         4
       6: aload         5
       8: aload         6
      10: invokespecial #1                  // Method org/codehaus/stax2/ri/evt/DTDEventImpl."<init>":(Ljavax/xml/stream/Location;Ljava/lang/String;Ljava/lang/String;Ljava/lang/String;Ljava/lang/String;Ljava/lang/Object;)V
      13: aload_0
      14: aconst_null
      15: putfield      #2                  // Field mEntities:Ljava/util/List;
      18: aload_0
      19: aconst_null
      20: putfield      #3                  // Field mNotations:Ljava/util/List;
      23: aload_0
      24: aload         6
      26: putfield      #4                  // Field mSubset:Lcom/ctc/wstx/dtd/DTDSubset;
      29: return

  public com.ctc.wstx.evt.WDTD(javax.xml.stream.Location, java.lang.String, java.lang.String, java.lang.String, java.lang.String);
    Code:
       0: aload_0
       1: aload_1
       2: aload_2
       3: aload_3
       4: aload         4
       6: aload         5
       8: aconst_null
       9: invokespecial #5                  // Method "<init>":(Ljavax/xml/stream/Location;Ljava/lang/String;Ljava/lang/String;Ljava/lang/String;Ljava/lang/String;Lcom/ctc/wstx/dtd/DTDSubset;)V
      12: return

  public com.ctc.wstx.evt.WDTD(javax.xml.stream.Location, java.lang.String, java.lang.String);
    Code:
       0: aload_0
       1: aload_1
       2: aload_2
       3: aconst_null
       4: aconst_null
       5: aload_3
       6: aconst_null
       7: invokespecial #5                  // Method "<init>":(Ljavax/xml/stream/Location;Ljava/lang/String;Ljava/lang/String;Ljava/lang/String;Ljava/lang/String;Lcom/ctc/wstx/dtd/DTDSubset;)V
      10: return

  public com.ctc.wstx.evt.WDTD(javax.xml.stream.Location, java.lang.String);
    Code:
       0: aload_0
       1: aload_1
       2: aload_2
       3: invokespecial #6                  // Method org/codehaus/stax2/ri/evt/DTDEventImpl."<init>":(Ljavax/xml/stream/Location;Ljava/lang/String;)V
       6: aload_0
       7: aconst_null
       8: putfield      #2                  // Field mEntities:Ljava/util/List;
      11: aload_0
      12: aconst_null
      13: putfield      #3                  // Field mNotations:Ljava/util/List;
      16: aload_0
      17: aconst_null
      18: putfield      #4                  // Field mSubset:Lcom/ctc/wstx/dtd/DTDSubset;
      21: return

  public java.util.List<javax.xml.stream.events.EntityDeclaration> getEntities();
    Code:
       0: aload_0
       1: getfield      #2                  // Field mEntities:Ljava/util/List;
       4: ifnonnull     32
       7: aload_0
       8: getfield      #4                  // Field mSubset:Lcom/ctc/wstx/dtd/DTDSubset;
      11: ifnull        32
      14: aload_0
      15: new           #7                  // class java/util/ArrayList
      18: dup
      19: aload_0
      20: getfield      #4                  // Field mSubset:Lcom/ctc/wstx/dtd/DTDSubset;
      23: invokevirtual #8                  // Method com/ctc/wstx/dtd/DTDSubset.getGeneralEntityList:()Ljava/util/List;
      26: invokespecial #9                  // Method java/util/ArrayList."<init>":(Ljava/util/Collection;)V
      29: putfield      #2                  // Field mEntities:Ljava/util/List;
      32: aload_0
      33: getfield      #2                  // Field mEntities:Ljava/util/List;
      36: areturn

  public java.util.List<javax.xml.stream.events.NotationDeclaration> getNotations();
    Code:
       0: aload_0
       1: getfield      #3                  // Field mNotations:Ljava/util/List;
       4: ifnonnull     32
       7: aload_0
       8: getfield      #4                  // Field mSubset:Lcom/ctc/wstx/dtd/DTDSubset;
      11: ifnull        32
      14: aload_0
      15: new           #7                  // class java/util/ArrayList
      18: dup
      19: aload_0
      20: getfield      #4                  // Field mSubset:Lcom/ctc/wstx/dtd/DTDSubset;
      23: invokevirtual #10                 // Method com/ctc/wstx/dtd/DTDSubset.getNotationList:()Ljava/util/List;
      26: invokespecial #9                  // Method java/util/ArrayList."<init>":(Ljava/util/Collection;)V
      29: putfield      #3                  // Field mNotations:Ljava/util/List;
      32: aload_0
      33: getfield      #3                  // Field mNotations:Ljava/util/List;
      36: areturn
}
