Compiled from "Jsr310DateTimeFormatAnnotationFormatterFactory.java"
public class org.springframework.format.datetime.standard.Jsr310DateTimeFormatAnnotationFormatterFactory extends org.springframework.context.support.EmbeddedValueResolutionSupport implements org.springframework.format.AnnotationFormatterFactory<org.springframework.format.annotation.DateTimeFormat> {
  private static final java.util.Set<java.lang.Class<?>> FIELD_TYPES;

  public org.springframework.format.datetime.standard.Jsr310DateTimeFormatAnnotationFormatterFactory();
    Code:
       0: aload_0
       1: invokespecial #1                  // Method org/springframework/context/support/EmbeddedValueResolutionSupport."<init>":()V
       4: return

  public final java.util.Set<java.lang.Class<?>> getFieldTypes();
    Code:
       0: getstatic     #2                  // Field FIELD_TYPES:Ljava/util/Set;
       3: areturn

  public org.springframework.format.Printer<?> getPrinter(org.springframework.format.annotation.DateTimeFormat, java.lang.Class<?>);
    Code:
       0: aload_0
       1: aload_1
       2: aload_2
       3: invokevirtual #3                  // Method getFormatter:(Lorg/springframework/format/annotation/DateTimeFormat;Ljava/lang/Class;)Ljava/time/format/DateTimeFormatter;
       6: astore_3
       7: new           #4                  // class org/springframework/format/datetime/standard/TemporalAccessorPrinter
      10: dup
      11: aload_3
      12: invokespecial #5                  // Method org/springframework/format/datetime/standard/TemporalAccessorPrinter."<init>":(Ljava/time/format/DateTimeFormatter;)V
      15: areturn

  public org.springframework.format.Parser<?> getParser(org.springframework.format.annotation.DateTimeFormat, java.lang.Class<?>);
    Code:
       0: aload_0
       1: aload_1
       2: aload_2
       3: invokevirtual #3                  // Method getFormatter:(Lorg/springframework/format/annotation/DateTimeFormat;Ljava/lang/Class;)Ljava/time/format/DateTimeFormatter;
       6: astore_3
       7: new           #6                  // class org/springframework/format/datetime/standard/TemporalAccessorParser
      10: dup
      11: aload_2
      12: aload_3
      13: invokespecial #7                  // Method org/springframework/format/datetime/standard/TemporalAccessorParser."<init>":(Ljava/lang/Class;Ljava/time/format/DateTimeFormatter;)V
      16: areturn

  protected java.time.format.DateTimeFormatter getFormatter(org.springframework.format.annotation.DateTimeFormat, java.lang.Class<?>);
    Code:
       0: new           #8                  // class org/springframework/format/datetime/standard/DateTimeFormatterFactory
       3: dup
       4: invokespecial #9                  // Method org/springframework/format/datetime/standard/DateTimeFormatterFactory."<init>":()V
       7: astore_3
       8: aload_3
       9: aload_0
      10: aload_1
      11: invokeinterface #10,  1           // InterfaceMethod org/springframework/format/annotation/DateTimeFormat.style:()Ljava/lang/String;
      16: invokevirtual #11                 // Method resolveEmbeddedValue:(Ljava/lang/String;)Ljava/lang/String;
      19: invokevirtual #12                 // Method org/springframework/format/datetime/standard/DateTimeFormatterFactory.setStylePattern:(Ljava/lang/String;)V
      22: aload_3
      23: aload_1
      24: invokeinterface #13,  1           // InterfaceMethod org/springframework/format/annotation/DateTimeFormat.iso:()Lorg/springframework/format/annotation/DateTimeFormat$ISO;
      29: invokevirtual #14                 // Method org/springframework/format/datetime/standard/DateTimeFormatterFactory.setIso:(Lorg/springframework/format/annotation/DateTimeFormat$ISO;)V
      32: aload_3
      33: aload_0
      34: aload_1
      35: invokeinterface #15,  1           // InterfaceMethod org/springframework/format/annotation/DateTimeFormat.pattern:()Ljava/lang/String;
      40: invokevirtual #11                 // Method resolveEmbeddedValue:(Ljava/lang/String;)Ljava/lang/String;
      43: invokevirtual #16                 // Method org/springframework/format/datetime/standard/DateTimeFormatterFactory.setPattern:(Ljava/lang/String;)V
      46: aload_3
      47: invokevirtual #17                 // Method org/springframework/format/datetime/standard/DateTimeFormatterFactory.createDateTimeFormatter:()Ljava/time/format/DateTimeFormatter;
      50: areturn

  public org.springframework.format.Parser getParser(java.lang.annotation.Annotation, java.lang.Class);
    Code:
       0: aload_0
       1: aload_1
       2: checkcast     #18                 // class org/springframework/format/annotation/DateTimeFormat
       5: aload_2
       6: invokevirtual #19                 // Method getParser:(Lorg/springframework/format/annotation/DateTimeFormat;Ljava/lang/Class;)Lorg/springframework/format/Parser;
       9: areturn

  public org.springframework.format.Printer getPrinter(java.lang.annotation.Annotation, java.lang.Class);
    Code:
       0: aload_0
       1: aload_1
       2: checkcast     #18                 // class org/springframework/format/annotation/DateTimeFormat
       5: aload_2
       6: invokevirtual #20                 // Method getPrinter:(Lorg/springframework/format/annotation/DateTimeFormat;Ljava/lang/Class;)Lorg/springframework/format/Printer;
       9: areturn

  static {};
    Code:
       0: new           #21                 // class java/util/HashSet
       3: dup
       4: bipush        8
       6: invokespecial #22                 // Method java/util/HashSet."<init>":(I)V
       9: astore_0
      10: aload_0
      11: ldc           #23                 // class java/time/LocalDate
      13: invokeinterface #24,  2           // InterfaceMethod java/util/Set.add:(Ljava/lang/Object;)Z
      18: pop
      19: aload_0
      20: ldc           #25                 // class java/time/LocalTime
      22: invokeinterface #24,  2           // InterfaceMethod java/util/Set.add:(Ljava/lang/Object;)Z
      27: pop
      28: aload_0
      29: ldc           #26                 // class java/time/LocalDateTime
      31: invokeinterface #24,  2           // InterfaceMethod java/util/Set.add:(Ljava/lang/Object;)Z
      36: pop
      37: aload_0
      38: ldc           #27                 // class java/time/ZonedDateTime
      40: invokeinterface #24,  2           // InterfaceMethod java/util/Set.add:(Ljava/lang/Object;)Z
      45: pop
      46: aload_0
      47: ldc           #28                 // class java/time/OffsetDateTime
      49: invokeinterface #24,  2           // InterfaceMethod java/util/Set.add:(Ljava/lang/Object;)Z
      54: pop
      55: aload_0
      56: ldc           #29                 // class java/time/OffsetTime
      58: invokeinterface #24,  2           // InterfaceMethod java/util/Set.add:(Ljava/lang/Object;)Z
      63: pop
      64: aload_0
      65: invokestatic  #30                 // Method java/util/Collections.unmodifiableSet:(Ljava/util/Set;)Ljava/util/Set;
      68: putstatic     #2                  // Field FIELD_TYPES:Ljava/util/Set;
      71: return
}
