Compiled from "CallableInterceptorChain.java"
class org.springframework.web.context.request.async.CallableInterceptorChain {
  private static final org.apache.commons.logging.Log logger;

  private final java.util.List<org.springframework.web.context.request.async.CallableProcessingInterceptor> interceptors;

  private int preProcessIndex;

  private volatile java.util.concurrent.Future<?> taskFuture;

  public org.springframework.web.context.request.async.CallableInterceptorChain(java.util.List<org.springframework.web.context.request.async.CallableProcessingInterceptor>);
    Code:
       0: aload_0
       1: invokespecial #1                  // Method java/lang/Object."<init>":()V
       4: aload_0
       5: iconst_m1
       6: putfield      #2                  // Field preProcessIndex:I
       9: aload_0
      10: aload_1
      11: putfield      #3                  // Field interceptors:Ljava/util/List;
      14: return

  public void setTaskFuture(java.util.concurrent.Future<?>);
    Code:
       0: aload_0
       1: aload_1
       2: putfield      #4                  // Field taskFuture:Ljava/util/concurrent/Future;
       5: return

  public void applyBeforeConcurrentHandling(org.springframework.web.context.request.NativeWebRequest, java.util.concurrent.Callable<?>) throws java.lang.Exception;
    Code:
       0: aload_0
       1: getfield      #3                  // Field interceptors:Ljava/util/List;
       4: invokeinterface #5,  1            // InterfaceMethod java/util/List.iterator:()Ljava/util/Iterator;
       9: astore_3
      10: aload_3
      11: invokeinterface #6,  1            // InterfaceMethod java/util/Iterator.hasNext:()Z
      16: ifeq          42
      19: aload_3
      20: invokeinterface #7,  1            // InterfaceMethod java/util/Iterator.next:()Ljava/lang/Object;
      25: checkcast     #8                  // class org/springframework/web/context/request/async/CallableProcessingInterceptor
      28: astore        4
      30: aload         4
      32: aload_1
      33: aload_2
      34: invokeinterface #9,  3            // InterfaceMethod org/springframework/web/context/request/async/CallableProcessingInterceptor.beforeConcurrentHandling:(Lorg/springframework/web/context/request/NativeWebRequest;Ljava/util/concurrent/Callable;)V
      39: goto          10
      42: return

  public void applyPreProcess(org.springframework.web.context.request.NativeWebRequest, java.util.concurrent.Callable<?>) throws java.lang.Exception;
    Code:
       0: aload_0
       1: getfield      #3                  // Field interceptors:Ljava/util/List;
       4: invokeinterface #5,  1            // InterfaceMethod java/util/List.iterator:()Ljava/util/Iterator;
       9: astore_3
      10: aload_3
      11: invokeinterface #6,  1            // InterfaceMethod java/util/Iterator.hasNext:()Z
      16: ifeq          52
      19: aload_3
      20: invokeinterface #7,  1            // InterfaceMethod java/util/Iterator.next:()Ljava/lang/Object;
      25: checkcast     #8                  // class org/springframework/web/context/request/async/CallableProcessingInterceptor
      28: astore        4
      30: aload         4
      32: aload_1
      33: aload_2
      34: invokeinterface #10,  3           // InterfaceMethod org/springframework/web/context/request/async/CallableProcessingInterceptor.preProcess:(Lorg/springframework/web/context/request/NativeWebRequest;Ljava/util/concurrent/Callable;)V
      39: aload_0
      40: dup
      41: getfield      #2                  // Field preProcessIndex:I
      44: iconst_1
      45: iadd
      46: putfield      #2                  // Field preProcessIndex:I
      49: goto          10
      52: return

  public java.lang.Object applyPostProcess(org.springframework.web.context.request.NativeWebRequest, java.util.concurrent.Callable<?>, java.lang.Object);
    Code:
       0: aconst_null
       1: astore        4
       3: aload_0
       4: getfield      #2                  // Field preProcessIndex:I
       7: istore        5
       9: iload         5
      11: iflt          71
      14: aload_0
      15: getfield      #3                  // Field interceptors:Ljava/util/List;
      18: iload         5
      20: invokeinterface #11,  2           // InterfaceMethod java/util/List.get:(I)Ljava/lang/Object;
      25: checkcast     #8                  // class org/springframework/web/context/request/async/CallableProcessingInterceptor
      28: aload_1
      29: aload_2
      30: aload_3
      31: invokeinterface #12,  4           // InterfaceMethod org/springframework/web/context/request/async/CallableProcessingInterceptor.postProcess:(Lorg/springframework/web/context/request/NativeWebRequest;Ljava/util/concurrent/Callable;Ljava/lang/Object;)V
      36: goto          65
      39: astore        6
      41: aload         4
      43: ifnull        61
      46: getstatic     #14                 // Field logger:Lorg/apache/commons/logging/Log;
      49: ldc           #15                 // String postProcess error
      51: aload         6
      53: invokeinterface #16,  3           // InterfaceMethod org/apache/commons/logging/Log.error:(Ljava/lang/Object;Ljava/lang/Throwable;)V
      58: goto          65
      61: aload         6
      63: astore        4
      65: iinc          5, -1
      68: goto          9
      71: aload         4
      73: ifnull        81
      76: aload         4
      78: goto          82
      81: aload_3
      82: areturn
    Exception table:
       from    to  target type
          14    36    39   Class java/lang/Throwable

  public java.lang.Object triggerAfterTimeout(org.springframework.web.context.request.NativeWebRequest, java.util.concurrent.Callable<?>);
    Code:
       0: aload_0
       1: invokespecial #17                 // Method cancelTask:()V
       4: aload_0
       5: getfield      #3                  // Field interceptors:Ljava/util/List;
       8: invokeinterface #5,  1            // InterfaceMethod java/util/List.iterator:()Ljava/util/Iterator;
      13: astore_3
      14: aload_3
      15: invokeinterface #6,  1            // InterfaceMethod java/util/Iterator.hasNext:()Z
      20: ifeq          78
      23: aload_3
      24: invokeinterface #7,  1            // InterfaceMethod java/util/Iterator.next:()Ljava/lang/Object;
      29: checkcast     #8                  // class org/springframework/web/context/request/async/CallableProcessingInterceptor
      32: astore        4
      34: aload         4
      36: aload_1
      37: aload_2
      38: invokeinterface #18,  3           // InterfaceMethod org/springframework/web/context/request/async/CallableProcessingInterceptor.handleTimeout:(Lorg/springframework/web/context/request/NativeWebRequest;Ljava/util/concurrent/Callable;)Ljava/lang/Object;
      43: astore        5
      45: aload         5
      47: getstatic     #19                 // Field org/springframework/web/context/request/async/CallableProcessingInterceptor.RESPONSE_HANDLED:Ljava/lang/Object;
      50: if_acmpne     56
      53: goto          78
      56: aload         5
      58: getstatic     #20                 // Field org/springframework/web/context/request/async/CallableProcessingInterceptor.RESULT_NONE:Ljava/lang/Object;
      61: if_acmpeq     67
      64: aload         5
      66: areturn
      67: goto          75
      70: astore        5
      72: aload         5
      74: areturn
      75: goto          14
      78: getstatic     #20                 // Field org/springframework/web/context/request/async/CallableProcessingInterceptor.RESULT_NONE:Ljava/lang/Object;
      81: areturn
    Exception table:
       from    to  target type
          34    53    70   Class java/lang/Throwable
          56    66    70   Class java/lang/Throwable

  private void cancelTask();
    Code:
       0: aload_0
       1: getfield      #4                  // Field taskFuture:Ljava/util/concurrent/Future;
       4: astore_1
       5: aload_1
       6: ifnull        21
       9: aload_1
      10: iconst_1
      11: invokeinterface #21,  2           // InterfaceMethod java/util/concurrent/Future.cancel:(Z)Z
      16: pop
      17: goto          21
      20: astore_2
      21: return
    Exception table:
       from    to  target type
           9    17    20   Class java/lang/Throwable

  public void triggerAfterCompletion(org.springframework.web.context.request.NativeWebRequest, java.util.concurrent.Callable<?>);
    Code:
       0: aload_0
       1: getfield      #3                  // Field interceptors:Ljava/util/List;
       4: invokeinterface #22,  1           // InterfaceMethod java/util/List.size:()I
       9: iconst_1
      10: isub
      11: istore_3
      12: iload_3
      13: iflt          59
      16: aload_0
      17: getfield      #3                  // Field interceptors:Ljava/util/List;
      20: iload_3
      21: invokeinterface #11,  2           // InterfaceMethod java/util/List.get:(I)Ljava/lang/Object;
      26: checkcast     #8                  // class org/springframework/web/context/request/async/CallableProcessingInterceptor
      29: aload_1
      30: aload_2
      31: invokeinterface #23,  3           // InterfaceMethod org/springframework/web/context/request/async/CallableProcessingInterceptor.afterCompletion:(Lorg/springframework/web/context/request/NativeWebRequest;Ljava/util/concurrent/Callable;)V
      36: goto          53
      39: astore        4
      41: getstatic     #14                 // Field logger:Lorg/apache/commons/logging/Log;
      44: ldc           #24                 // String afterCompletion error
      46: aload         4
      48: invokeinterface #16,  3           // InterfaceMethod org/apache/commons/logging/Log.error:(Ljava/lang/Object;Ljava/lang/Throwable;)V
      53: iinc          3, -1
      56: goto          12
      59: return
    Exception table:
       from    to  target type
          16    36    39   Class java/lang/Throwable

  static {};
    Code:
       0: ldc           #25                 // class org/springframework/web/context/request/async/CallableInterceptorChain
       2: invokestatic  #26                 // Method org/apache/commons/logging/LogFactory.getLog:(Ljava/lang/Class;)Lorg/apache/commons/logging/Log;
       5: putstatic     #14                 // Field logger:Lorg/apache/commons/logging/Log;
       8: return
}
