Compiled from "MDC.java"
public class org.slf4j.MDC {
  static final java.lang.String NULL_MDCA_URL;

  static final java.lang.String NO_STATIC_MDC_BINDER_URL;

  static org.slf4j.spi.MDCAdapter mdcAdapter;

  private org.slf4j.MDC();
    Code:
       0: aload_0
       1: invokespecial #1                  // Method java/lang/Object."<init>":()V
       4: return

  private static org.slf4j.spi.MDCAdapter bwCompatibleGetMDCAdapterFromBinder() throws java.lang.NoClassDefFoundError;
    Code:
       0: invokestatic  #2                  // Method org/slf4j/impl/StaticMDCBinder.getSingleton:()Lorg/slf4j/impl/StaticMDCBinder;
       3: invokevirtual #3                  // Method org/slf4j/impl/StaticMDCBinder.getMDCA:()Lorg/slf4j/spi/MDCAdapter;
       6: areturn
       7: astore_0
       8: getstatic     #5                  // Field org/slf4j/impl/StaticMDCBinder.SINGLETON:Lorg/slf4j/impl/StaticMDCBinder;
      11: invokevirtual #3                  // Method org/slf4j/impl/StaticMDCBinder.getMDCA:()Lorg/slf4j/spi/MDCAdapter;
      14: areturn
    Exception table:
       from    to  target type
           0     6     7   Class java/lang/NoSuchMethodError

  public static void put(java.lang.String, java.lang.String) throws java.lang.IllegalArgumentException;
    Code:
       0: aload_0
       1: ifnonnull     14
       4: new           #6                  // class java/lang/IllegalArgumentException
       7: dup
       8: ldc           #7                  // String key parameter cannot be null
      10: invokespecial #8                  // Method java/lang/IllegalArgumentException."<init>":(Ljava/lang/String;)V
      13: athrow
      14: getstatic     #9                  // Field mdcAdapter:Lorg/slf4j/spi/MDCAdapter;
      17: ifnonnull     30
      20: new           #10                 // class java/lang/IllegalStateException
      23: dup
      24: ldc           #12                 // String MDCAdapter cannot be null. See also http://www.slf4j.org/codes.html#null_MDCA
      26: invokespecial #13                 // Method java/lang/IllegalStateException."<init>":(Ljava/lang/String;)V
      29: athrow
      30: getstatic     #9                  // Field mdcAdapter:Lorg/slf4j/spi/MDCAdapter;
      33: aload_0
      34: aload_1
      35: invokeinterface #14,  3           // InterfaceMethod org/slf4j/spi/MDCAdapter.put:(Ljava/lang/String;Ljava/lang/String;)V
      40: return

  public static org.slf4j.MDC$MDCCloseable putCloseable(java.lang.String, java.lang.String) throws java.lang.IllegalArgumentException;
    Code:
       0: aload_0
       1: aload_1
       2: invokestatic  #15                 // Method put:(Ljava/lang/String;Ljava/lang/String;)V
       5: new           #16                 // class org/slf4j/MDC$MDCCloseable
       8: dup
       9: aload_0
      10: aconst_null
      11: invokespecial #17                 // Method org/slf4j/MDC$MDCCloseable."<init>":(Ljava/lang/String;Lorg/slf4j/MDC$1;)V
      14: areturn

  public static java.lang.String get(java.lang.String) throws java.lang.IllegalArgumentException;
    Code:
       0: aload_0
       1: ifnonnull     14
       4: new           #6                  // class java/lang/IllegalArgumentException
       7: dup
       8: ldc           #7                  // String key parameter cannot be null
      10: invokespecial #8                  // Method java/lang/IllegalArgumentException."<init>":(Ljava/lang/String;)V
      13: athrow
      14: getstatic     #9                  // Field mdcAdapter:Lorg/slf4j/spi/MDCAdapter;
      17: ifnonnull     30
      20: new           #10                 // class java/lang/IllegalStateException
      23: dup
      24: ldc           #12                 // String MDCAdapter cannot be null. See also http://www.slf4j.org/codes.html#null_MDCA
      26: invokespecial #13                 // Method java/lang/IllegalStateException."<init>":(Ljava/lang/String;)V
      29: athrow
      30: getstatic     #9                  // Field mdcAdapter:Lorg/slf4j/spi/MDCAdapter;
      33: aload_0
      34: invokeinterface #18,  2           // InterfaceMethod org/slf4j/spi/MDCAdapter.get:(Ljava/lang/String;)Ljava/lang/String;
      39: areturn

  public static void remove(java.lang.String) throws java.lang.IllegalArgumentException;
    Code:
       0: aload_0
       1: ifnonnull     14
       4: new           #6                  // class java/lang/IllegalArgumentException
       7: dup
       8: ldc           #7                  // String key parameter cannot be null
      10: invokespecial #8                  // Method java/lang/IllegalArgumentException."<init>":(Ljava/lang/String;)V
      13: athrow
      14: getstatic     #9                  // Field mdcAdapter:Lorg/slf4j/spi/MDCAdapter;
      17: ifnonnull     30
      20: new           #10                 // class java/lang/IllegalStateException
      23: dup
      24: ldc           #12                 // String MDCAdapter cannot be null. See also http://www.slf4j.org/codes.html#null_MDCA
      26: invokespecial #13                 // Method java/lang/IllegalStateException."<init>":(Ljava/lang/String;)V
      29: athrow
      30: getstatic     #9                  // Field mdcAdapter:Lorg/slf4j/spi/MDCAdapter;
      33: aload_0
      34: invokeinterface #19,  2           // InterfaceMethod org/slf4j/spi/MDCAdapter.remove:(Ljava/lang/String;)V
      39: return

  public static void clear();
    Code:
       0: getstatic     #9                  // Field mdcAdapter:Lorg/slf4j/spi/MDCAdapter;
       3: ifnonnull     16
       6: new           #10                 // class java/lang/IllegalStateException
       9: dup
      10: ldc           #12                 // String MDCAdapter cannot be null. See also http://www.slf4j.org/codes.html#null_MDCA
      12: invokespecial #13                 // Method java/lang/IllegalStateException."<init>":(Ljava/lang/String;)V
      15: athrow
      16: getstatic     #9                  // Field mdcAdapter:Lorg/slf4j/spi/MDCAdapter;
      19: invokeinterface #20,  1           // InterfaceMethod org/slf4j/spi/MDCAdapter.clear:()V
      24: return

  public static java.util.Map<java.lang.String, java.lang.String> getCopyOfContextMap();
    Code:
       0: getstatic     #9                  // Field mdcAdapter:Lorg/slf4j/spi/MDCAdapter;
       3: ifnonnull     16
       6: new           #10                 // class java/lang/IllegalStateException
       9: dup
      10: ldc           #12                 // String MDCAdapter cannot be null. See also http://www.slf4j.org/codes.html#null_MDCA
      12: invokespecial #13                 // Method java/lang/IllegalStateException."<init>":(Ljava/lang/String;)V
      15: athrow
      16: getstatic     #9                  // Field mdcAdapter:Lorg/slf4j/spi/MDCAdapter;
      19: invokeinterface #21,  1           // InterfaceMethod org/slf4j/spi/MDCAdapter.getCopyOfContextMap:()Ljava/util/Map;
      24: areturn

  public static void setContextMap(java.util.Map<java.lang.String, java.lang.String>);
    Code:
       0: getstatic     #9                  // Field mdcAdapter:Lorg/slf4j/spi/MDCAdapter;
       3: ifnonnull     16
       6: new           #10                 // class java/lang/IllegalStateException
       9: dup
      10: ldc           #12                 // String MDCAdapter cannot be null. See also http://www.slf4j.org/codes.html#null_MDCA
      12: invokespecial #13                 // Method java/lang/IllegalStateException."<init>":(Ljava/lang/String;)V
      15: athrow
      16: getstatic     #9                  // Field mdcAdapter:Lorg/slf4j/spi/MDCAdapter;
      19: aload_0
      20: invokeinterface #22,  2           // InterfaceMethod org/slf4j/spi/MDCAdapter.setContextMap:(Ljava/util/Map;)V
      25: return

  public static org.slf4j.spi.MDCAdapter getMDCAdapter();
    Code:
       0: getstatic     #9                  // Field mdcAdapter:Lorg/slf4j/spi/MDCAdapter;
       3: areturn

  static {};
    Code:
       0: invokestatic  #23                 // Method bwCompatibleGetMDCAdapterFromBinder:()Lorg/slf4j/spi/MDCAdapter;
       3: putstatic     #9                  // Field mdcAdapter:Lorg/slf4j/spi/MDCAdapter;
       6: goto          68
       9: astore_0
      10: new           #25                 // class org/slf4j/helpers/NOPMDCAdapter
      13: dup
      14: invokespecial #26                 // Method org/slf4j/helpers/NOPMDCAdapter."<init>":()V
      17: putstatic     #9                  // Field mdcAdapter:Lorg/slf4j/spi/MDCAdapter;
      20: aload_0
      21: invokevirtual #27                 // Method java/lang/NoClassDefFoundError.getMessage:()Ljava/lang/String;
      24: astore_1
      25: aload_1
      26: ifnull        56
      29: aload_1
      30: ldc           #28                 // String StaticMDCBinder
      32: invokevirtual #29                 // Method java/lang/String.contains:(Ljava/lang/CharSequence;)Z
      35: ifeq          56
      38: ldc           #30                 // String Failed to load class \"org.slf4j.impl.StaticMDCBinder\".
      40: invokestatic  #31                 // Method org/slf4j/helpers/Util.report:(Ljava/lang/String;)V
      43: ldc           #32                 // String Defaulting to no-operation MDCAdapter implementation.
      45: invokestatic  #31                 // Method org/slf4j/helpers/Util.report:(Ljava/lang/String;)V
      48: ldc           #33                 // String See http://www.slf4j.org/codes.html#no_static_mdc_binder for further details.
      50: invokestatic  #31                 // Method org/slf4j/helpers/Util.report:(Ljava/lang/String;)V
      53: goto          58
      56: aload_0
      57: athrow
      58: goto          68
      61: astore_0
      62: ldc           #35                 // String MDC binding unsuccessful.
      64: aload_0
      65: invokestatic  #36                 // Method org/slf4j/helpers/Util.report:(Ljava/lang/String;Ljava/lang/Throwable;)V
      68: return
    Exception table:
       from    to  target type
           0     6     9   Class java/lang/NoClassDefFoundError
           0     6    61   Class java/lang/Exception
}
