Compiled from "InstantiationServiceImpl.java"
class org.jvnet.hk2.internal.InstantiationServiceImpl$1 implements org.glassfish.hk2.api.InstantiationData {
  final org.glassfish.hk2.api.Injectee val$head;

  final org.jvnet.hk2.internal.InstantiationServiceImpl this$0;

  org.jvnet.hk2.internal.InstantiationServiceImpl$1(org.jvnet.hk2.internal.InstantiationServiceImpl, org.glassfish.hk2.api.Injectee);
    Code:
       0: aload_0
       1: aload_1
       2: putfield      #1                  // Field this$0:Lorg/jvnet/hk2/internal/InstantiationServiceImpl;
       5: aload_0
       6: aload_2
       7: putfield      #2                  // Field val$head:Lorg/glassfish/hk2/api/Injectee;
      10: aload_0
      11: invokespecial #3                  // Method java/lang/Object."<init>":()V
      14: return

  public org.glassfish.hk2.api.Injectee getParentInjectee();
    Code:
       0: aload_0
       1: getfield      #2                  // Field val$head:Lorg/glassfish/hk2/api/Injectee;
       4: areturn

  public java.lang.String toString();
    Code:
       0: new           #4                  // class java/lang/StringBuilder
       3: dup
       4: invokespecial #5                  // Method java/lang/StringBuilder."<init>":()V
       7: ldc           #6                  // String InstantiationData(
       9: invokevirtual #7                  // Method java/lang/StringBuilder.append:(Ljava/lang/String;)Ljava/lang/StringBuilder;
      12: aload_0
      13: getfield      #2                  // Field val$head:Lorg/glassfish/hk2/api/Injectee;
      16: invokevirtual #8                  // Method java/lang/StringBuilder.append:(Ljava/lang/Object;)Ljava/lang/StringBuilder;
      19: ldc           #9                  // String ,
      21: invokevirtual #7                  // Method java/lang/StringBuilder.append:(Ljava/lang/String;)Ljava/lang/StringBuilder;
      24: aload_0
      25: invokestatic  #10                 // Method java/lang/System.identityHashCode:(Ljava/lang/Object;)I
      28: invokevirtual #11                 // Method java/lang/StringBuilder.append:(I)Ljava/lang/StringBuilder;
      31: ldc           #12                 // String )
      33: invokevirtual #7                  // Method java/lang/StringBuilder.append:(Ljava/lang/String;)Ljava/lang/StringBuilder;
      36: invokevirtual #13                 // Method java/lang/StringBuilder.toString:()Ljava/lang/String;
      39: areturn
}
