Compiled from "ProxyUtilities.java"
class org.jvnet.hk2.internal.ProxyUtilities$3 implements java.security.PrivilegedAction<T> {
  final org.jvnet.hk2.internal.DelegatingClassLoader val$delegatingLoader;

  final java.lang.Class[] val$interfaces;

  final javassist.util.proxy.MethodHandler val$callback;

  final org.jvnet.hk2.internal.ProxyUtilities this$0;

  org.jvnet.hk2.internal.ProxyUtilities$3(org.jvnet.hk2.internal.ProxyUtilities, org.jvnet.hk2.internal.DelegatingClassLoader, java.lang.Class[], javassist.util.proxy.MethodHandler);
    Code:
       0: aload_0
       1: aload_1
       2: putfield      #1                  // Field this$0:Lorg/jvnet/hk2/internal/ProxyUtilities;
       5: aload_0
       6: aload_2
       7: putfield      #2                  // Field val$delegatingLoader:Lorg/jvnet/hk2/internal/DelegatingClassLoader;
      10: aload_0
      11: aload_3
      12: putfield      #3                  // Field val$interfaces:[Ljava/lang/Class;
      15: aload_0
      16: aload         4
      18: putfield      #4                  // Field val$callback:Ljavassist/util/proxy/MethodHandler;
      21: aload_0
      22: invokespecial #5                  // Method java/lang/Object."<init>":()V
      25: return

  public T run();
    Code:
       0: aload_0
       1: getfield      #2                  // Field val$delegatingLoader:Lorg/jvnet/hk2/internal/DelegatingClassLoader;
       4: aload_0
       5: getfield      #3                  // Field val$interfaces:[Ljava/lang/Class;
       8: new           #6                  // class org/jvnet/hk2/internal/MethodInterceptorInvocationHandler
      11: dup
      12: aload_0
      13: getfield      #4                  // Field val$callback:Ljavassist/util/proxy/MethodHandler;
      16: invokespecial #7                  // Method org/jvnet/hk2/internal/MethodInterceptorInvocationHandler."<init>":(Ljavassist/util/proxy/MethodHandler;)V
      19: invokestatic  #8                  // Method java/lang/reflect/Proxy.newProxyInstance:(Ljava/lang/ClassLoader;[Ljava/lang/Class;Ljava/lang/reflect/InvocationHandler;)Ljava/lang/Object;
      22: areturn
}
