Compiled from "ProxyUtilities.java"
class org.jvnet.hk2.internal.ProxyUtilities$2 implements java.security.PrivilegedAction<org.jvnet.hk2.internal.DelegatingClassLoader> {
  final java.lang.ClassLoader val$loader;

  final org.jvnet.hk2.internal.ProxyUtilities this$0;

  org.jvnet.hk2.internal.ProxyUtilities$2(org.jvnet.hk2.internal.ProxyUtilities, java.lang.ClassLoader);
    Code:
       0: aload_0
       1: aload_1
       2: putfield      #1                  // Field this$0:Lorg/jvnet/hk2/internal/ProxyUtilities;
       5: aload_0
       6: aload_2
       7: putfield      #2                  // Field val$loader:Ljava/lang/ClassLoader;
      10: aload_0
      11: invokespecial #3                  // Method java/lang/Object."<init>":()V
      14: return

  public org.jvnet.hk2.internal.DelegatingClassLoader run();
    Code:
       0: new           #4                  // class org/jvnet/hk2/internal/DelegatingClassLoader
       3: dup
       4: aload_0
       5: getfield      #2                  // Field val$loader:Ljava/lang/ClassLoader;
       8: iconst_2
       9: anewarray     #5                  // class java/lang/ClassLoader
      12: dup
      13: iconst_0
      14: ldc           #6                  // class javassist/util/proxy/ProxyFactory
      16: invokevirtual #7                  // Method java/lang/Class.getClassLoader:()Ljava/lang/ClassLoader;
      19: aastore
      20: dup
      21: iconst_1
      22: ldc           #8                  // class org/glassfish/hk2/api/ProxyCtl
      24: invokevirtual #7                  // Method java/lang/Class.getClassLoader:()Ljava/lang/ClassLoader;
      27: aastore
      28: invokespecial #9                  // Method org/jvnet/hk2/internal/DelegatingClassLoader."<init>":(Ljava/lang/ClassLoader;[Ljava/lang/ClassLoader;)V
      31: areturn

  public java.lang.Object run();
    Code:
       0: aload_0
       1: invokevirtual #10                 // Method run:()Lorg/jvnet/hk2/internal/DelegatingClassLoader;
       4: areturn
}
