Compiled from "Utilities.java"
final class org.jvnet.hk2.internal.Utilities$2 implements java.security.PrivilegedAction<java.lang.Object> {
  final java.lang.reflect.Constructor val$result;

  org.jvnet.hk2.internal.Utilities$2(java.lang.reflect.Constructor);
    Code:
       0: aload_0
       1: aload_1
       2: putfield      #1                  // Field val$result:Ljava/lang/reflect/Constructor;
       5: aload_0
       6: invokespecial #2                  // Method java/lang/Object."<init>":()V
       9: return

  public java.lang.Object run();
    Code:
       0: aload_0
       1: getfield      #1                  // Field val$result:Ljava/lang/reflect/Constructor;
       4: iconst_1
       5: invokevirtual #3                  // Method java/lang/reflect/Constructor.setAccessible:(Z)V
       8: aconst_null
       9: areturn
}
