Compiled from "CompositePropertySource.java"
public class org.springframework.core.env.CompositePropertySource extends org.springframework.core.env.EnumerablePropertySource<java.lang.Object> {
  private final java.util.Set<org.springframework.core.env.PropertySource<?>> propertySources;

  public org.springframework.core.env.CompositePropertySource(java.lang.String);
    Code:
       0: aload_0
       1: aload_1
       2: invokespecial #1                  // Method org/springframework/core/env/EnumerablePropertySource."<init>":(Ljava/lang/String;)V
       5: aload_0
       6: new           #2                  // class java/util/LinkedHashSet
       9: dup
      10: invokespecial #3                  // Method java/util/LinkedHashSet."<init>":()V
      13: putfield      #4                  // Field propertySources:Ljava/util/Set;
      16: return

  public java.lang.Object getProperty(java.lang.String);
    Code:
       0: aload_0
       1: getfield      #4                  // Field propertySources:Ljava/util/Set;
       4: invokeinterface #5,  1            // InterfaceMethod java/util/Set.iterator:()Ljava/util/Iterator;
       9: astore_2
      10: aload_2
      11: invokeinterface #6,  1            // InterfaceMethod java/util/Iterator.hasNext:()Z
      16: ifeq          47
      19: aload_2
      20: invokeinterface #7,  1            // InterfaceMethod java/util/Iterator.next:()Ljava/lang/Object;
      25: checkcast     #8                  // class org/springframework/core/env/PropertySource
      28: astore_3
      29: aload_3
      30: aload_1
      31: invokevirtual #9                  // Method org/springframework/core/env/PropertySource.getProperty:(Ljava/lang/String;)Ljava/lang/Object;
      34: astore        4
      36: aload         4
      38: ifnull        44
      41: aload         4
      43: areturn
      44: goto          10
      47: aconst_null
      48: areturn

  public boolean containsProperty(java.lang.String);
    Code:
       0: aload_0
       1: getfield      #4                  // Field propertySources:Ljava/util/Set;
       4: invokeinterface #5,  1            // InterfaceMethod java/util/Set.iterator:()Ljava/util/Iterator;
       9: astore_2
      10: aload_2
      11: invokeinterface #6,  1            // InterfaceMethod java/util/Iterator.hasNext:()Z
      16: ifeq          42
      19: aload_2
      20: invokeinterface #7,  1            // InterfaceMethod java/util/Iterator.next:()Ljava/lang/Object;
      25: checkcast     #8                  // class org/springframework/core/env/PropertySource
      28: astore_3
      29: aload_3
      30: aload_1
      31: invokevirtual #10                 // Method org/springframework/core/env/PropertySource.containsProperty:(Ljava/lang/String;)Z
      34: ifeq          39
      37: iconst_1
      38: ireturn
      39: goto          10
      42: iconst_0
      43: ireturn

  public java.lang.String[] getPropertyNames();
    Code:
       0: new           #2                  // class java/util/LinkedHashSet
       3: dup
       4: invokespecial #3                  // Method java/util/LinkedHashSet."<init>":()V
       7: astore_1
       8: aload_0
       9: getfield      #4                  // Field propertySources:Ljava/util/Set;
      12: invokeinterface #5,  1            // InterfaceMethod java/util/Set.iterator:()Ljava/util/Iterator;
      17: astore_2
      18: aload_2
      19: invokeinterface #6,  1            // InterfaceMethod java/util/Iterator.hasNext:()Z
      24: ifeq          91
      27: aload_2
      28: invokeinterface #7,  1            // InterfaceMethod java/util/Iterator.next:()Ljava/lang/Object;
      33: checkcast     #8                  // class org/springframework/core/env/PropertySource
      36: astore_3
      37: aload_3
      38: instanceof    #11                 // class org/springframework/core/env/EnumerablePropertySource
      41: ifne          71
      44: new           #12                 // class java/lang/IllegalStateException
      47: dup
      48: new           #13                 // class java/lang/StringBuilder
      51: dup
      52: invokespecial #14                 // Method java/lang/StringBuilder."<init>":()V
      55: ldc           #15                 // String Failed to enumerate property names due to non-enumerable property source:
      57: invokevirtual #16                 // Method java/lang/StringBuilder.append:(Ljava/lang/String;)Ljava/lang/StringBuilder;
      60: aload_3
      61: invokevirtual #17                 // Method java/lang/StringBuilder.append:(Ljava/lang/Object;)Ljava/lang/StringBuilder;
      64: invokevirtual #18                 // Method java/lang/StringBuilder.toString:()Ljava/lang/String;
      67: invokespecial #19                 // Method java/lang/IllegalStateException."<init>":(Ljava/lang/String;)V
      70: athrow
      71: aload_1
      72: aload_3
      73: checkcast     #11                 // class org/springframework/core/env/EnumerablePropertySource
      76: invokevirtual #20                 // Method org/springframework/core/env/EnumerablePropertySource.getPropertyNames:()[Ljava/lang/String;
      79: invokestatic  #21                 // Method java/util/Arrays.asList:([Ljava/lang/Object;)Ljava/util/List;
      82: invokeinterface #22,  2           // InterfaceMethod java/util/Set.addAll:(Ljava/util/Collection;)Z
      87: pop
      88: goto          18
      91: aload_1
      92: invokestatic  #23                 // Method org/springframework/util/StringUtils.toStringArray:(Ljava/util/Collection;)[Ljava/lang/String;
      95: areturn

  public void addPropertySource(org.springframework.core.env.PropertySource<?>);
    Code:
       0: aload_0
       1: getfield      #4                  // Field propertySources:Ljava/util/Set;
       4: aload_1
       5: invokeinterface #24,  2           // InterfaceMethod java/util/Set.add:(Ljava/lang/Object;)Z
      10: pop
      11: return

  public void addFirstPropertySource(org.springframework.core.env.PropertySource<?>);
    Code:
       0: new           #25                 // class java/util/ArrayList
       3: dup
       4: aload_0
       5: getfield      #4                  // Field propertySources:Ljava/util/Set;
       8: invokespecial #26                 // Method java/util/ArrayList."<init>":(Ljava/util/Collection;)V
      11: astore_2
      12: aload_0
      13: getfield      #4                  // Field propertySources:Ljava/util/Set;
      16: invokeinterface #27,  1           // InterfaceMethod java/util/Set.clear:()V
      21: aload_0
      22: getfield      #4                  // Field propertySources:Ljava/util/Set;
      25: aload_1
      26: invokeinterface #24,  2           // InterfaceMethod java/util/Set.add:(Ljava/lang/Object;)Z
      31: pop
      32: aload_0
      33: getfield      #4                  // Field propertySources:Ljava/util/Set;
      36: aload_2
      37: invokeinterface #22,  2           // InterfaceMethod java/util/Set.addAll:(Ljava/util/Collection;)Z
      42: pop
      43: return

  public java.util.Collection<org.springframework.core.env.PropertySource<?>> getPropertySources();
    Code:
       0: aload_0
       1: getfield      #4                  // Field propertySources:Ljava/util/Set;
       4: areturn

  public java.lang.String toString();
    Code:
       0: new           #13                 // class java/lang/StringBuilder
       3: dup
       4: invokespecial #14                 // Method java/lang/StringBuilder."<init>":()V
       7: aload_0
       8: invokevirtual #28                 // Method java/lang/Object.getClass:()Ljava/lang/Class;
      11: invokevirtual #29                 // Method java/lang/Class.getSimpleName:()Ljava/lang/String;
      14: invokevirtual #16                 // Method java/lang/StringBuilder.append:(Ljava/lang/String;)Ljava/lang/StringBuilder;
      17: ldc           #30                 // String  {name=\'
      19: invokevirtual #16                 // Method java/lang/StringBuilder.append:(Ljava/lang/String;)Ljava/lang/StringBuilder;
      22: aload_0
      23: getfield      #31                 // Field name:Ljava/lang/String;
      26: invokevirtual #16                 // Method java/lang/StringBuilder.append:(Ljava/lang/String;)Ljava/lang/StringBuilder;
      29: ldc           #32                 // String \', propertySources=
      31: invokevirtual #16                 // Method java/lang/StringBuilder.append:(Ljava/lang/String;)Ljava/lang/StringBuilder;
      34: aload_0
      35: getfield      #4                  // Field propertySources:Ljava/util/Set;
      38: invokevirtual #17                 // Method java/lang/StringBuilder.append:(Ljava/lang/Object;)Ljava/lang/StringBuilder;
      41: ldc           #33                 // String }
      43: invokevirtual #16                 // Method java/lang/StringBuilder.append:(Ljava/lang/String;)Ljava/lang/StringBuilder;
      46: invokevirtual #18                 // Method java/lang/StringBuilder.toString:()Ljava/lang/String;
      49: areturn
}
