Compiled from "AsyncContextImpl.java"
class io.undertow.servlet.spec.AsyncContextImpl$1 implements java.lang.Runnable {
  final io.undertow.server.HttpServerExchange val$exchange;

  final io.undertow.servlet.spec.AsyncContextImpl this$0;

  io.undertow.servlet.spec.AsyncContextImpl$1(io.undertow.servlet.spec.AsyncContextImpl, io.undertow.server.HttpServerExchange);
    Code:
       0: aload_0
       1: aload_1
       2: putfield      #1                  // Field this$0:Lio/undertow/servlet/spec/AsyncContextImpl;
       5: aload_0
       6: aload_2
       7: putfield      #2                  // Field val$exchange:Lio/undertow/server/HttpServerExchange;
      10: aload_0
      11: invokespecial #3                  // Method java/lang/Object."<init>":()V
      14: return

  public void run();
    Code:
       0: aload_0
       1: getfield      #2                  // Field val$exchange:Lio/undertow/server/HttpServerExchange;
       4: aconst_null
       5: invokevirtual #4                  // Method io/undertow/server/HttpServerExchange.setDispatchExecutor:(Ljava/util/concurrent/Executor;)Lio/undertow/server/HttpServerExchange;
       8: pop
       9: aload_0
      10: getfield      #1                  // Field this$0:Lio/undertow/servlet/spec/AsyncContextImpl;
      13: invokevirtual #5                  // Method io/undertow/servlet/spec/AsyncContextImpl.initialRequestDone:()V
      16: return
}
