Compiled from "AsyncContextImpl.java"
final class io.undertow.servlet.spec.AsyncContextImpl$BoundAsyncListener {
  final javax.servlet.AsyncListener asyncListener;

  final javax.servlet.ServletRequest servletRequest;

  final javax.servlet.ServletResponse servletResponse;

  final io.undertow.servlet.spec.AsyncContextImpl this$0;

  private io.undertow.servlet.spec.AsyncContextImpl$BoundAsyncListener(io.undertow.servlet.spec.AsyncContextImpl, javax.servlet.AsyncListener, javax.servlet.ServletRequest, javax.servlet.ServletResponse);
    Code:
       0: aload_0
       1: aload_1
       2: putfield      #2                  // Field this$0:Lio/undertow/servlet/spec/AsyncContextImpl;
       5: aload_0
       6: invokespecial #3                  // Method java/lang/Object."<init>":()V
       9: aload_0
      10: aload_2
      11: putfield      #4                  // Field asyncListener:Ljavax/servlet/AsyncListener;
      14: aload_0
      15: aload_3
      16: putfield      #5                  // Field servletRequest:Ljavax/servlet/ServletRequest;
      19: aload_0
      20: aload         4
      22: putfield      #6                  // Field servletResponse:Ljavax/servlet/ServletResponse;
      25: return

  io.undertow.servlet.spec.AsyncContextImpl$BoundAsyncListener(io.undertow.servlet.spec.AsyncContextImpl, javax.servlet.AsyncListener, javax.servlet.ServletRequest, javax.servlet.ServletResponse, io.undertow.servlet.spec.AsyncContextImpl$1);
    Code:
       0: aload_0
       1: aload_1
       2: aload_2
       3: aload_3
       4: aload         4
       6: invokespecial #1                  // Method "<init>":(Lio/undertow/servlet/spec/AsyncContextImpl;Ljavax/servlet/AsyncListener;Ljavax/servlet/ServletRequest;Ljavax/servlet/ServletResponse;)V
       9: return
}
