Compiled from "Synchronized.java"
public class org.picocontainer.behaviors.Synchronized<T> extends org.picocontainer.behaviors.AbstractBehavior<T> {
  public org.picocontainer.behaviors.Synchronized(org.picocontainer.ComponentAdapter<T>);
    Code:
       0: aload_0
       1: aload_1
       2: invokespecial #10                 // Method org/picocontainer/behaviors/AbstractBehavior."<init>":(Lorg/picocontainer/ComponentAdapter;)V
       5: return

  public synchronized T getComponentInstance(org.picocontainer.PicoContainer, java.lang.reflect.Type) throws org.picocontainer.PicoCompositionException;
    Code:
       0: aload_0
       1: aload_1
       2: aload_2
       3: invokespecial #22                 // Method org/picocontainer/behaviors/AbstractBehavior.getComponentInstance:(Lorg/picocontainer/PicoContainer;Ljava/lang/reflect/Type;)Ljava/lang/Object;
       6: areturn

  public java.lang.String getDescriptor();
    Code:
       0: ldc           #30                 // String Synchronized
       2: areturn
}
