Compiled from "CacheCleanupListener.java"
public class org.apache.cxf.ws.security.cache.CacheCleanupListener implements org.apache.cxf.endpoint.ServerLifeCycleListener,org.apache.cxf.endpoint.ClientLifeCycleListener {
  public org.apache.cxf.ws.security.cache.CacheCleanupListener();
    Code:
       0: aload_0
       1: invokespecial #1                  // Method java/lang/Object."<init>":()V
       4: return

  public void clientCreated(org.apache.cxf.endpoint.Client);
    Code:
       0: return

  public void startServer(org.apache.cxf.endpoint.Server);
    Code:
       0: return

  public void clientDestroyed(org.apache.cxf.endpoint.Client);
    Code:
       0: aload_0
       1: aload_1
       2: invokeinterface #2,  1            // InterfaceMethod org/apache/cxf/endpoint/Client.getEndpoint:()Lorg/apache/cxf/endpoint/Endpoint;
       7: invokeinterface #3,  1            // InterfaceMethod org/apache/cxf/endpoint/Endpoint.getEndpointInfo:()Lorg/apache/cxf/service/model/EndpointInfo;
      12: invokevirtual #4                  // Method shutdownResources:(Lorg/apache/cxf/service/model/EndpointInfo;)V
      15: return

  public void stopServer(org.apache.cxf.endpoint.Server);
    Code:
       0: aload_0
       1: aload_1
       2: invokeinterface #5,  1            // InterfaceMethod org/apache/cxf/endpoint/Server.getEndpoint:()Lorg/apache/cxf/endpoint/Endpoint;
       7: invokeinterface #3,  1            // InterfaceMethod org/apache/cxf/endpoint/Endpoint.getEndpointInfo:()Lorg/apache/cxf/service/model/EndpointInfo;
      12: invokevirtual #4                  // Method shutdownResources:(Lorg/apache/cxf/service/model/EndpointInfo;)V
      15: return

  protected void shutdownResources(org.apache.cxf.service.model.EndpointInfo);
    Code:
       0: aload_1
       1: ldc           #6                  // String org.apache.cxf.ws.security.tokenstore.TokenStore
       3: invokevirtual #7                  // Method org/apache/cxf/service/model/EndpointInfo.getProperty:(Ljava/lang/String;)Ljava/lang/Object;
       6: checkcast     #8                  // class org/apache/cxf/ws/security/tokenstore/TokenStore
       9: astore_2
      10: aload_2
      11: instanceof    #9                  // class java/io/Closeable
      14: ifeq          25
      17: aload_0
      18: aload_2
      19: checkcast     #9                  // class java/io/Closeable
      22: invokespecial #10                 // Method close:(Ljava/io/Closeable;)V
      25: aload_1
      26: ldc           #11                 // String ws-security.nonce.cache.instance
      28: invokevirtual #7                  // Method org/apache/cxf/service/model/EndpointInfo.getProperty:(Ljava/lang/String;)Ljava/lang/Object;
      31: checkcast     #12                 // class org/apache/wss4j/common/cache/ReplayCache
      34: astore_3
      35: aload_3
      36: ifnull        44
      39: aload_0
      40: aload_3
      41: invokespecial #10                 // Method close:(Ljava/io/Closeable;)V
      44: aload_1
      45: ldc           #13                 // String ws-security.timestamp.cache.instance
      47: invokevirtual #7                  // Method org/apache/cxf/service/model/EndpointInfo.getProperty:(Ljava/lang/String;)Ljava/lang/Object;
      50: checkcast     #12                 // class org/apache/wss4j/common/cache/ReplayCache
      53: astore_3
      54: aload_3
      55: ifnull        63
      58: aload_0
      59: aload_3
      60: invokespecial #10                 // Method close:(Ljava/io/Closeable;)V
      63: return

  private void close(java.io.Closeable);
    Code:
       0: aload_1
       1: invokeinterface #14,  1           // InterfaceMethod java/io/Closeable.close:()V
       6: goto          10
       9: astore_2
      10: return
    Exception table:
       from    to  target type
           0     6     9   Class java/io/IOException
}
