Compiled from "BouncyCastleAlpnSslEngine.java"
final class io.netty.handler.ssl.BouncyCastleAlpnSslEngine extends io.netty.handler.ssl.JdkAlpnSslEngine {
  io.netty.handler.ssl.BouncyCastleAlpnSslEngine(javax.net.ssl.SSLEngine, io.netty.handler.ssl.JdkApplicationProtocolNegotiator, boolean);
    Code:
       0: aload_0
       1: aload_1
       2: aload_2
       3: iload_3
       4: new           #1                  // class io/netty/handler/ssl/BouncyCastleAlpnSslEngine$1
       7: dup
       8: invokespecial #2                  // Method io/netty/handler/ssl/BouncyCastleAlpnSslEngine$1."<init>":()V
      11: new           #3                  // class io/netty/handler/ssl/BouncyCastleAlpnSslEngine$2
      14: dup
      15: invokespecial #4                  // Method io/netty/handler/ssl/BouncyCastleAlpnSslEngine$2."<init>":()V
      18: invokespecial #5                  // Method io/netty/handler/ssl/JdkAlpnSslEngine."<init>":(Ljavax/net/ssl/SSLEngine;Lio/netty/handler/ssl/JdkApplicationProtocolNegotiator;ZLjava/util/function/BiConsumer;Ljava/util/function/BiConsumer;)V
      21: return

  public java.lang.String getApplicationProtocol();
    Code:
       0: aload_0
       1: invokevirtual #6                  // Method getWrappedEngine:()Ljavax/net/ssl/SSLEngine;
       4: invokestatic  #7                  // Method io/netty/handler/ssl/BouncyCastleAlpnSslUtils.getApplicationProtocol:(Ljavax/net/ssl/SSLEngine;)Ljava/lang/String;
       7: areturn

  public java.lang.String getHandshakeApplicationProtocol();
    Code:
       0: aload_0
       1: invokevirtual #6                  // Method getWrappedEngine:()Ljavax/net/ssl/SSLEngine;
       4: invokestatic  #8                  // Method io/netty/handler/ssl/BouncyCastleAlpnSslUtils.getHandshakeApplicationProtocol:(Ljavax/net/ssl/SSLEngine;)Ljava/lang/String;
       7: areturn

  public void setHandshakeApplicationProtocolSelector(java.util.function.BiFunction<javax.net.ssl.SSLEngine, java.util.List<java.lang.String>, java.lang.String>);
    Code:
       0: aload_0
       1: invokevirtual #6                  // Method getWrappedEngine:()Ljavax/net/ssl/SSLEngine;
       4: aload_1
       5: invokestatic  #9                  // Method io/netty/handler/ssl/BouncyCastleAlpnSslUtils.setHandshakeApplicationProtocolSelector:(Ljavax/net/ssl/SSLEngine;Ljava/util/function/BiFunction;)V
       8: return

  public java.util.function.BiFunction<javax.net.ssl.SSLEngine, java.util.List<java.lang.String>, java.lang.String> getHandshakeApplicationProtocolSelector();
    Code:
       0: aload_0
       1: invokevirtual #6                  // Method getWrappedEngine:()Ljavax/net/ssl/SSLEngine;
       4: invokestatic  #10                 // Method io/netty/handler/ssl/BouncyCastleAlpnSslUtils.getHandshakeApplicationProtocolSelector:(Ljavax/net/ssl/SSLEngine;)Ljava/util/function/BiFunction;
       7: areturn
}
