Compiled from "JdkBaseApplicationProtocolNegotiator.java"
class io.netty.handler.ssl.JdkBaseApplicationProtocolNegotiator$NoFailProtocolSelectionListener implements io.netty.handler.ssl.JdkApplicationProtocolNegotiator$ProtocolSelectionListener {
  private final io.netty.handler.ssl.JdkSslEngine engineWrapper;

  private final java.util.List<java.lang.String> supportedProtocols;

  io.netty.handler.ssl.JdkBaseApplicationProtocolNegotiator$NoFailProtocolSelectionListener(io.netty.handler.ssl.JdkSslEngine, java.util.List<java.lang.String>);
    Code:
       0: aload_0
       1: invokespecial #1                  // Method java/lang/Object."<init>":()V
       4: aload_0
       5: aload_1
       6: putfield      #2                  // Field engineWrapper:Lio/netty/handler/ssl/JdkSslEngine;
       9: aload_0
      10: aload_2
      11: putfield      #3                  // Field supportedProtocols:Ljava/util/List;
      14: return

  public void unsupported();
    Code:
       0: aload_0
       1: getfield      #2                  // Field engineWrapper:Lio/netty/handler/ssl/JdkSslEngine;
       4: aconst_null
       5: invokevirtual #4                  // Method io/netty/handler/ssl/JdkSslEngine.setNegotiatedApplicationProtocol:(Ljava/lang/String;)V
       8: return

  public void selected(java.lang.String) throws java.lang.Exception;
    Code:
       0: aload_0
       1: getfield      #3                  // Field supportedProtocols:Ljava/util/List;
       4: aload_1
       5: invokeinterface #5,  2            // InterfaceMethod java/util/List.contains:(Ljava/lang/Object;)Z
      10: ifeq          24
      13: aload_0
      14: getfield      #2                  // Field engineWrapper:Lio/netty/handler/ssl/JdkSslEngine;
      17: aload_1
      18: invokevirtual #4                  // Method io/netty/handler/ssl/JdkSslEngine.setNegotiatedApplicationProtocol:(Ljava/lang/String;)V
      21: goto          29
      24: aload_0
      25: aload_1
      26: invokevirtual #6                  // Method noSelectedMatchFound:(Ljava/lang/String;)V
      29: return

  protected void noSelectedMatchFound(java.lang.String) throws java.lang.Exception;
    Code:
       0: return
}
