Compiled from "EntityLookupConfiguration.java"
class org.springframework.data.rest.core.config.EntityLookupConfiguration$MappingBuilder<T, ID, R extends org.springframework.data.repository.Repository<T, ?>> implements org.springframework.data.rest.core.config.EntityLookupRegistrar$LookupRegistrar<T, ID, R>, org.springframework.data.rest.core.config.EntityLookupRegistrar$IdMappingRegistrar<T, R> {
  private final java.lang.Class<R> repositoryType;

  private org.springframework.core.convert.converter.Converter<T, ID> idMapping;

  final org.springframework.data.rest.core.config.EntityLookupConfiguration this$0;

  private org.springframework.data.rest.core.config.EntityLookupConfiguration$MappingBuilder(java.lang.Class<R>, org.springframework.core.convert.converter.Converter<T, ID>);
    Code:
       0: aload_0
       1: aload_1
       2: aload_2
       3: invokespecial #1                  // Method "<init>":(Lorg/springframework/data/rest/core/config/EntityLookupConfiguration;Ljava/lang/Class;)V
       6: aload_3
       7: ldc           #2                  // String Converter must not be null!
       9: invokestatic  #3                  // Method org/springframework/util/Assert.notNull:(Ljava/lang/Object;Ljava/lang/String;)V
      12: aload_0
      13: aload_3
      14: putfield      #4                  // Field idMapping:Lorg/springframework/core/convert/converter/Converter;
      17: return

  public org.springframework.data.rest.core.config.EntityLookupRegistrar withLookup(org.springframework.data.rest.core.config.EntityLookupRegistrar$LookupRegistrar$Lookup<R, ID>);
    Code:
       0: aload_0
       1: getfield      #5                  // Field this$0:Lorg/springframework/data/rest/core/config/EntityLookupConfiguration;
       4: invokestatic  #6                  // Method org/springframework/data/rest/core/config/EntityLookupConfiguration.access$000:(Lorg/springframework/data/rest/core/config/EntityLookupConfiguration;)Ljava/util/List;
       7: new           #7                  // class org/springframework/data/rest/core/config/EntityLookupConfiguration$LookupInformation
      10: dup
      11: aload_0
      12: getfield      #8                  // Field repositoryType:Ljava/lang/Class;
      15: aload_0
      16: getfield      #4                  // Field idMapping:Lorg/springframework/core/convert/converter/Converter;
      19: aload_1
      20: invokespecial #9                  // Method org/springframework/data/rest/core/config/EntityLookupConfiguration$LookupInformation."<init>":(Ljava/lang/Class;Lorg/springframework/core/convert/converter/Converter;Lorg/springframework/data/rest/core/config/EntityLookupRegistrar$LookupRegistrar$Lookup;)V
      23: invokeinterface #10,  2           // InterfaceMethod java/util/List.add:(Ljava/lang/Object;)Z
      28: pop
      29: aload_0
      30: getfield      #5                  // Field this$0:Lorg/springframework/data/rest/core/config/EntityLookupConfiguration;
      33: areturn

  public <ID2> org.springframework.data.rest.core.config.EntityLookupRegistrar$LookupRegistrar<T, ID2, R> withIdMapping(org.springframework.core.convert.converter.Converter<T, ID2>);
    Code:
       0: new           #11                 // class org/springframework/data/rest/core/config/EntityLookupConfiguration$MappingBuilder
       3: dup
       4: aload_0
       5: getfield      #5                  // Field this$0:Lorg/springframework/data/rest/core/config/EntityLookupConfiguration;
       8: aload_0
       9: getfield      #8                  // Field repositoryType:Ljava/lang/Class;
      12: aload_1
      13: invokespecial #12                 // Method "<init>":(Lorg/springframework/data/rest/core/config/EntityLookupConfiguration;Ljava/lang/Class;Lorg/springframework/core/convert/converter/Converter;)V
      16: areturn

  public org.springframework.data.rest.core.config.EntityLookupConfiguration$MappingBuilder(java.lang.Class<R>);
    Code:
       0: aload_0
       1: aload_1
       2: putfield      #5                  // Field this$0:Lorg/springframework/data/rest/core/config/EntityLookupConfiguration;
       5: aload_0
       6: invokespecial #13                 // Method java/lang/Object."<init>":()V
       9: aload_2
      10: ifnonnull     23
      13: new           #14                 // class java/lang/IllegalArgumentException
      16: dup
      17: ldc           #15                 // String repositoryType is marked non-null but is null
      19: invokespecial #16                 // Method java/lang/IllegalArgumentException."<init>":(Ljava/lang/String;)V
      22: athrow
      23: aload_0
      24: aload_2
      25: putfield      #8                  // Field repositoryType:Ljava/lang/Class;
      28: return
}
