Compiled from "HamletImpl.java"
public final class org.apache.hadoop.yarn.webapp.hamlet2.HamletImpl$EOpt extends java.lang.Enum<org.apache.hadoop.yarn.webapp.hamlet2.HamletImpl$EOpt> {
  public static final org.apache.hadoop.yarn.webapp.hamlet2.HamletImpl$EOpt ENDTAG;

  public static final org.apache.hadoop.yarn.webapp.hamlet2.HamletImpl$EOpt INLINE;

  public static final org.apache.hadoop.yarn.webapp.hamlet2.HamletImpl$EOpt PRE;

  private static final org.apache.hadoop.yarn.webapp.hamlet2.HamletImpl$EOpt[] $VALUES;

  public static org.apache.hadoop.yarn.webapp.hamlet2.HamletImpl$EOpt[] values();
    Code:
       0: getstatic     #1                  // Field $VALUES:[Lorg/apache/hadoop/yarn/webapp/hamlet2/HamletImpl$EOpt;
       3: invokevirtual #2                  // Method "[Lorg/apache/hadoop/yarn/webapp/hamlet2/HamletImpl$EOpt;".clone:()Ljava/lang/Object;
       6: checkcast     #3                  // class "[Lorg/apache/hadoop/yarn/webapp/hamlet2/HamletImpl$EOpt;"
       9: areturn

  public static org.apache.hadoop.yarn.webapp.hamlet2.HamletImpl$EOpt valueOf(java.lang.String);
    Code:
       0: ldc           #4                  // class org/apache/hadoop/yarn/webapp/hamlet2/HamletImpl$EOpt
       2: aload_0
       3: invokestatic  #5                  // Method java/lang/Enum.valueOf:(Ljava/lang/Class;Ljava/lang/String;)Ljava/lang/Enum;
       6: checkcast     #4                  // class org/apache/hadoop/yarn/webapp/hamlet2/HamletImpl$EOpt
       9: areturn

  private org.apache.hadoop.yarn.webapp.hamlet2.HamletImpl$EOpt();
    Code:
       0: aload_0
       1: aload_1
       2: iload_2
       3: invokespecial #6                  // Method java/lang/Enum."<init>":(Ljava/lang/String;I)V
       6: return

  static {};
    Code:
       0: new           #4                  // class org/apache/hadoop/yarn/webapp/hamlet2/HamletImpl$EOpt
       3: dup
       4: ldc           #7                  // String ENDTAG
       6: iconst_0
       7: invokespecial #8                  // Method "<init>":(Ljava/lang/String;I)V
      10: putstatic     #9                  // Field ENDTAG:Lorg/apache/hadoop/yarn/webapp/hamlet2/HamletImpl$EOpt;
      13: new           #4                  // class org/apache/hadoop/yarn/webapp/hamlet2/HamletImpl$EOpt
      16: dup
      17: ldc           #10                 // String INLINE
      19: iconst_1
      20: invokespecial #8                  // Method "<init>":(Ljava/lang/String;I)V
      23: putstatic     #11                 // Field INLINE:Lorg/apache/hadoop/yarn/webapp/hamlet2/HamletImpl$EOpt;
      26: new           #4                  // class org/apache/hadoop/yarn/webapp/hamlet2/HamletImpl$EOpt
      29: dup
      30: ldc           #12                 // String PRE
      32: iconst_2
      33: invokespecial #8                  // Method "<init>":(Ljava/lang/String;I)V
      36: putstatic     #13                 // Field PRE:Lorg/apache/hadoop/yarn/webapp/hamlet2/HamletImpl$EOpt;
      39: iconst_3
      40: anewarray     #4                  // class org/apache/hadoop/yarn/webapp/hamlet2/HamletImpl$EOpt
      43: dup
      44: iconst_0
      45: getstatic     #9                  // Field ENDTAG:Lorg/apache/hadoop/yarn/webapp/hamlet2/HamletImpl$EOpt;
      48: aastore
      49: dup
      50: iconst_1
      51: getstatic     #11                 // Field INLINE:Lorg/apache/hadoop/yarn/webapp/hamlet2/HamletImpl$EOpt;
      54: aastore
      55: dup
      56: iconst_2
      57: getstatic     #13                 // Field PRE:Lorg/apache/hadoop/yarn/webapp/hamlet2/HamletImpl$EOpt;
      60: aastore
      61: putstatic     #1                  // Field $VALUES:[Lorg/apache/hadoop/yarn/webapp/hamlet2/HamletImpl$EOpt;
      64: return
}
