Compiled from "CoreV1EventSeriesBuilder.java"
public class io.kubernetes.client.openapi.models.CoreV1EventSeriesBuilder extends io.kubernetes.client.openapi.models.CoreV1EventSeriesFluentImpl<io.kubernetes.client.openapi.models.CoreV1EventSeriesBuilder> implements io.kubernetes.client.fluent.VisitableBuilder<io.kubernetes.client.openapi.models.CoreV1EventSeries, io.kubernetes.client.openapi.models.CoreV1EventSeriesBuilder> {
  io.kubernetes.client.openapi.models.CoreV1EventSeriesFluent<?> fluent;

  java.lang.Boolean validationEnabled;

  public io.kubernetes.client.openapi.models.CoreV1EventSeriesBuilder();
    Code:
       0: aload_0
       1: iconst_1
       2: invokestatic  #1                  // Method java/lang/Boolean.valueOf:(Z)Ljava/lang/Boolean;
       5: invokespecial #2                  // Method "<init>":(Ljava/lang/Boolean;)V
       8: return

  public io.kubernetes.client.openapi.models.CoreV1EventSeriesBuilder(java.lang.Boolean);
    Code:
       0: aload_0
       1: new           #3                  // class io/kubernetes/client/openapi/models/CoreV1EventSeries
       4: dup
       5: invokespecial #4                  // Method io/kubernetes/client/openapi/models/CoreV1EventSeries."<init>":()V
       8: aload_1
       9: invokespecial #5                  // Method "<init>":(Lio/kubernetes/client/openapi/models/CoreV1EventSeries;Ljava/lang/Boolean;)V
      12: return

  public io.kubernetes.client.openapi.models.CoreV1EventSeriesBuilder(io.kubernetes.client.openapi.models.CoreV1EventSeriesFluent<?>);
    Code:
       0: aload_0
       1: aload_1
       2: iconst_1
       3: invokestatic  #1                  // Method java/lang/Boolean.valueOf:(Z)Ljava/lang/Boolean;
       6: invokespecial #6                  // Method "<init>":(Lio/kubernetes/client/openapi/models/CoreV1EventSeriesFluent;Ljava/lang/Boolean;)V
       9: return

  public io.kubernetes.client.openapi.models.CoreV1EventSeriesBuilder(io.kubernetes.client.openapi.models.CoreV1EventSeriesFluent<?>, java.lang.Boolean);
    Code:
       0: aload_0
       1: aload_1
       2: new           #3                  // class io/kubernetes/client/openapi/models/CoreV1EventSeries
       5: dup
       6: invokespecial #4                  // Method io/kubernetes/client/openapi/models/CoreV1EventSeries."<init>":()V
       9: aload_2
      10: invokespecial #7                  // Method "<init>":(Lio/kubernetes/client/openapi/models/CoreV1EventSeriesFluent;Lio/kubernetes/client/openapi/models/CoreV1EventSeries;Ljava/lang/Boolean;)V
      13: return

  public io.kubernetes.client.openapi.models.CoreV1EventSeriesBuilder(io.kubernetes.client.openapi.models.CoreV1EventSeriesFluent<?>, io.kubernetes.client.openapi.models.CoreV1EventSeries);
    Code:
       0: aload_0
       1: aload_1
       2: aload_2
       3: iconst_1
       4: invokestatic  #1                  // Method java/lang/Boolean.valueOf:(Z)Ljava/lang/Boolean;
       7: invokespecial #7                  // Method "<init>":(Lio/kubernetes/client/openapi/models/CoreV1EventSeriesFluent;Lio/kubernetes/client/openapi/models/CoreV1EventSeries;Ljava/lang/Boolean;)V
      10: return

  public io.kubernetes.client.openapi.models.CoreV1EventSeriesBuilder(io.kubernetes.client.openapi.models.CoreV1EventSeriesFluent<?>, io.kubernetes.client.openapi.models.CoreV1EventSeries, java.lang.Boolean);
    Code:
       0: aload_0
       1: invokespecial #8                  // Method io/kubernetes/client/openapi/models/CoreV1EventSeriesFluentImpl."<init>":()V
       4: aload_0
       5: aload_1
       6: putfield      #9                  // Field fluent:Lio/kubernetes/client/openapi/models/CoreV1EventSeriesFluent;
       9: aload_1
      10: aload_2
      11: invokevirtual #10                 // Method io/kubernetes/client/openapi/models/CoreV1EventSeries.getCount:()Ljava/lang/Integer;
      14: invokeinterface #11,  2           // InterfaceMethod io/kubernetes/client/openapi/models/CoreV1EventSeriesFluent.withCount:(Ljava/lang/Integer;)Lio/kubernetes/client/openapi/models/CoreV1EventSeriesFluent;
      19: pop
      20: aload_1
      21: aload_2
      22: invokevirtual #12                 // Method io/kubernetes/client/openapi/models/CoreV1EventSeries.getLastObservedTime:()Ljava/time/OffsetDateTime;
      25: invokeinterface #13,  2           // InterfaceMethod io/kubernetes/client/openapi/models/CoreV1EventSeriesFluent.withLastObservedTime:(Ljava/time/OffsetDateTime;)Lio/kubernetes/client/openapi/models/CoreV1EventSeriesFluent;
      30: pop
      31: aload_0
      32: aload_3
      33: putfield      #14                 // Field validationEnabled:Ljava/lang/Boolean;
      36: return

  public io.kubernetes.client.openapi.models.CoreV1EventSeriesBuilder(io.kubernetes.client.openapi.models.CoreV1EventSeries);
    Code:
       0: aload_0
       1: aload_1
       2: iconst_1
       3: invokestatic  #1                  // Method java/lang/Boolean.valueOf:(Z)Ljava/lang/Boolean;
       6: invokespecial #5                  // Method "<init>":(Lio/kubernetes/client/openapi/models/CoreV1EventSeries;Ljava/lang/Boolean;)V
       9: return

  public io.kubernetes.client.openapi.models.CoreV1EventSeriesBuilder(io.kubernetes.client.openapi.models.CoreV1EventSeries, java.lang.Boolean);
    Code:
       0: aload_0
       1: invokespecial #8                  // Method io/kubernetes/client/openapi/models/CoreV1EventSeriesFluentImpl."<init>":()V
       4: aload_0
       5: aload_0
       6: putfield      #9                  // Field fluent:Lio/kubernetes/client/openapi/models/CoreV1EventSeriesFluent;
       9: aload_0
      10: aload_1
      11: invokevirtual #10                 // Method io/kubernetes/client/openapi/models/CoreV1EventSeries.getCount:()Ljava/lang/Integer;
      14: invokevirtual #15                 // Method withCount:(Ljava/lang/Integer;)Lio/kubernetes/client/openapi/models/CoreV1EventSeriesFluent;
      17: pop
      18: aload_0
      19: aload_1
      20: invokevirtual #12                 // Method io/kubernetes/client/openapi/models/CoreV1EventSeries.getLastObservedTime:()Ljava/time/OffsetDateTime;
      23: invokevirtual #16                 // Method withLastObservedTime:(Ljava/time/OffsetDateTime;)Lio/kubernetes/client/openapi/models/CoreV1EventSeriesFluent;
      26: pop
      27: aload_0
      28: aload_2
      29: putfield      #14                 // Field validationEnabled:Ljava/lang/Boolean;
      32: return

  public io.kubernetes.client.openapi.models.CoreV1EventSeries build();
    Code:
       0: new           #3                  // class io/kubernetes/client/openapi/models/CoreV1EventSeries
       3: dup
       4: invokespecial #4                  // Method io/kubernetes/client/openapi/models/CoreV1EventSeries."<init>":()V
       7: astore_1
       8: aload_1
       9: aload_0
      10: getfield      #9                  // Field fluent:Lio/kubernetes/client/openapi/models/CoreV1EventSeriesFluent;
      13: invokeinterface #17,  1           // InterfaceMethod io/kubernetes/client/openapi/models/CoreV1EventSeriesFluent.getCount:()Ljava/lang/Integer;
      18: invokevirtual #18                 // Method io/kubernetes/client/openapi/models/CoreV1EventSeries.setCount:(Ljava/lang/Integer;)V
      21: aload_1
      22: aload_0
      23: getfield      #9                  // Field fluent:Lio/kubernetes/client/openapi/models/CoreV1EventSeriesFluent;
      26: invokeinterface #19,  1           // InterfaceMethod io/kubernetes/client/openapi/models/CoreV1EventSeriesFluent.getLastObservedTime:()Ljava/time/OffsetDateTime;
      31: invokevirtual #20                 // Method io/kubernetes/client/openapi/models/CoreV1EventSeries.setLastObservedTime:(Ljava/time/OffsetDateTime;)V
      34: aload_1
      35: areturn

  public boolean equals(java.lang.Object);
    Code:
       0: aload_0
       1: aload_1
       2: if_acmpne     7
       5: iconst_1
       6: ireturn
       7: aload_1
       8: ifnull        22
      11: aload_0
      12: invokevirtual #21                 // Method java/lang/Object.getClass:()Ljava/lang/Class;
      15: aload_1
      16: invokevirtual #21                 // Method java/lang/Object.getClass:()Ljava/lang/Class;
      19: if_acmpeq     24
      22: iconst_0
      23: ireturn
      24: aload_0
      25: aload_1
      26: invokespecial #22                 // Method io/kubernetes/client/openapi/models/CoreV1EventSeriesFluentImpl.equals:(Ljava/lang/Object;)Z
      29: ifne          34
      32: iconst_0
      33: ireturn
      34: aload_1
      35: checkcast     #23                 // class io/kubernetes/client/openapi/models/CoreV1EventSeriesBuilder
      38: astore_2
      39: aload_0
      40: getfield      #9                  // Field fluent:Lio/kubernetes/client/openapi/models/CoreV1EventSeriesFluent;
      43: ifnull        71
      46: aload_0
      47: getfield      #9                  // Field fluent:Lio/kubernetes/client/openapi/models/CoreV1EventSeriesFluent;
      50: aload_0
      51: if_acmpeq     71
      54: aload_0
      55: getfield      #9                  // Field fluent:Lio/kubernetes/client/openapi/models/CoreV1EventSeriesFluent;
      58: aload_2
      59: getfield      #9                  // Field fluent:Lio/kubernetes/client/openapi/models/CoreV1EventSeriesFluent;
      62: invokevirtual #24                 // Method java/lang/Object.equals:(Ljava/lang/Object;)Z
      65: ifne          88
      68: goto          86
      71: aload_2
      72: getfield      #9                  // Field fluent:Lio/kubernetes/client/openapi/models/CoreV1EventSeriesFluent;
      75: ifnull        88
      78: aload_0
      79: getfield      #9                  // Field fluent:Lio/kubernetes/client/openapi/models/CoreV1EventSeriesFluent;
      82: aload_0
      83: if_acmpeq     88
      86: iconst_0
      87: ireturn
      88: aload_0
      89: getfield      #14                 // Field validationEnabled:Ljava/lang/Boolean;
      92: ifnull        112
      95: aload_0
      96: getfield      #14                 // Field validationEnabled:Ljava/lang/Boolean;
      99: aload_2
     100: getfield      #14                 // Field validationEnabled:Ljava/lang/Boolean;
     103: invokevirtual #25                 // Method java/lang/Boolean.equals:(Ljava/lang/Object;)Z
     106: ifne          121
     109: goto          119
     112: aload_2
     113: getfield      #14                 // Field validationEnabled:Ljava/lang/Boolean;
     116: ifnull        121
     119: iconst_0
     120: ireturn
     121: iconst_1
     122: ireturn

  public int hashCode();
    Code:
       0: iconst_3
       1: anewarray     #26                 // class java/lang/Object
       4: dup
       5: iconst_0
       6: aload_0
       7: getfield      #9                  // Field fluent:Lio/kubernetes/client/openapi/models/CoreV1EventSeriesFluent;
      10: aastore
      11: dup
      12: iconst_1
      13: aload_0
      14: getfield      #14                 // Field validationEnabled:Ljava/lang/Boolean;
      17: aastore
      18: dup
      19: iconst_2
      20: aload_0
      21: invokespecial #27                 // Method io/kubernetes/client/openapi/models/CoreV1EventSeriesFluentImpl.hashCode:()I
      24: invokestatic  #28                 // Method java/lang/Integer.valueOf:(I)Ljava/lang/Integer;
      27: aastore
      28: invokestatic  #29                 // Method java/util/Objects.hash:([Ljava/lang/Object;)I
      31: ireturn

  public java.lang.Object build();
    Code:
       0: aload_0
       1: invokevirtual #30                 // Method build:()Lio/kubernetes/client/openapi/models/CoreV1EventSeries;
       4: areturn
}
