Compiled from "V1APIGroupListFluentImpl.java"
public class io.kubernetes.client.openapi.models.V1APIGroupListFluentImpl$GroupsNestedImpl<N> extends io.kubernetes.client.openapi.models.V1APIGroupFluentImpl<io.kubernetes.client.openapi.models.V1APIGroupListFluent$GroupsNested<N>> implements io.kubernetes.client.openapi.models.V1APIGroupListFluent$GroupsNested<N>, io.kubernetes.client.fluent.Nested<N> {
  private final io.kubernetes.client.openapi.models.V1APIGroupBuilder builder;

  private final int index;

  final io.kubernetes.client.openapi.models.V1APIGroupListFluentImpl this$0;

  io.kubernetes.client.openapi.models.V1APIGroupListFluentImpl$GroupsNestedImpl(io.kubernetes.client.openapi.models.V1APIGroupListFluentImpl, int, io.kubernetes.client.openapi.models.V1APIGroup);
    Code:
       0: aload_0
       1: aload_1
       2: putfield      #1                  // Field this$0:Lio/kubernetes/client/openapi/models/V1APIGroupListFluentImpl;
       5: aload_0
       6: invokespecial #2                  // Method io/kubernetes/client/openapi/models/V1APIGroupFluentImpl."<init>":()V
       9: aload_0
      10: iload_2
      11: putfield      #3                  // Field index:I
      14: aload_0
      15: new           #4                  // class io/kubernetes/client/openapi/models/V1APIGroupBuilder
      18: dup
      19: aload_0
      20: aload_3
      21: invokespecial #5                  // Method io/kubernetes/client/openapi/models/V1APIGroupBuilder."<init>":(Lio/kubernetes/client/openapi/models/V1APIGroupFluent;Lio/kubernetes/client/openapi/models/V1APIGroup;)V
      24: putfield      #6                  // Field builder:Lio/kubernetes/client/openapi/models/V1APIGroupBuilder;
      27: return

  io.kubernetes.client.openapi.models.V1APIGroupListFluentImpl$GroupsNestedImpl(io.kubernetes.client.openapi.models.V1APIGroupListFluentImpl);
    Code:
       0: aload_0
       1: aload_1
       2: putfield      #1                  // Field this$0:Lio/kubernetes/client/openapi/models/V1APIGroupListFluentImpl;
       5: aload_0
       6: invokespecial #2                  // Method io/kubernetes/client/openapi/models/V1APIGroupFluentImpl."<init>":()V
       9: aload_0
      10: iconst_m1
      11: putfield      #3                  // Field index:I
      14: aload_0
      15: new           #4                  // class io/kubernetes/client/openapi/models/V1APIGroupBuilder
      18: dup
      19: aload_0
      20: invokespecial #7                  // Method io/kubernetes/client/openapi/models/V1APIGroupBuilder."<init>":(Lio/kubernetes/client/openapi/models/V1APIGroupFluent;)V
      23: putfield      #6                  // Field builder:Lio/kubernetes/client/openapi/models/V1APIGroupBuilder;
      26: return

  public N and();
    Code:
       0: aload_0
       1: getfield      #1                  // Field this$0:Lio/kubernetes/client/openapi/models/V1APIGroupListFluentImpl;
       4: aload_0
       5: getfield      #3                  // Field index:I
       8: aload_0
       9: getfield      #6                  // Field builder:Lio/kubernetes/client/openapi/models/V1APIGroupBuilder;
      12: invokevirtual #8                  // Method io/kubernetes/client/openapi/models/V1APIGroupBuilder.build:()Lio/kubernetes/client/openapi/models/V1APIGroup;
      15: invokevirtual #9                  // Method io/kubernetes/client/openapi/models/V1APIGroupListFluentImpl.setToGroups:(ILio/kubernetes/client/openapi/models/V1APIGroup;)Lio/kubernetes/client/openapi/models/V1APIGroupListFluent;
      18: areturn

  public N endGroup();
    Code:
       0: aload_0
       1: invokevirtual #10                 // Method and:()Ljava/lang/Object;
       4: areturn
}
