Compiled from "V1beta1CertificateSigningRequestSpecBuilder.java"
public class io.kubernetes.client.openapi.models.V1beta1CertificateSigningRequestSpecBuilder extends io.kubernetes.client.openapi.models.V1beta1CertificateSigningRequestSpecFluentImpl<io.kubernetes.client.openapi.models.V1beta1CertificateSigningRequestSpecBuilder> implements io.kubernetes.client.fluent.VisitableBuilder<io.kubernetes.client.openapi.models.V1beta1CertificateSigningRequestSpec, io.kubernetes.client.openapi.models.V1beta1CertificateSigningRequestSpecBuilder> {
  io.kubernetes.client.openapi.models.V1beta1CertificateSigningRequestSpecFluent<?> fluent;

  java.lang.Boolean validationEnabled;

  public io.kubernetes.client.openapi.models.V1beta1CertificateSigningRequestSpecBuilder();
    Code:
       0: aload_0
       1: iconst_1
       2: invokestatic  #1                  // Method java/lang/Boolean.valueOf:(Z)Ljava/lang/Boolean;
       5: invokespecial #2                  // Method "<init>":(Ljava/lang/Boolean;)V
       8: return

  public io.kubernetes.client.openapi.models.V1beta1CertificateSigningRequestSpecBuilder(java.lang.Boolean);
    Code:
       0: aload_0
       1: new           #3                  // class io/kubernetes/client/openapi/models/V1beta1CertificateSigningRequestSpec
       4: dup
       5: invokespecial #4                  // Method io/kubernetes/client/openapi/models/V1beta1CertificateSigningRequestSpec."<init>":()V
       8: aload_1
       9: invokespecial #5                  // Method "<init>":(Lio/kubernetes/client/openapi/models/V1beta1CertificateSigningRequestSpec;Ljava/lang/Boolean;)V
      12: return

  public io.kubernetes.client.openapi.models.V1beta1CertificateSigningRequestSpecBuilder(io.kubernetes.client.openapi.models.V1beta1CertificateSigningRequestSpecFluent<?>);
    Code:
       0: aload_0
       1: aload_1
       2: iconst_1
       3: invokestatic  #1                  // Method java/lang/Boolean.valueOf:(Z)Ljava/lang/Boolean;
       6: invokespecial #6                  // Method "<init>":(Lio/kubernetes/client/openapi/models/V1beta1CertificateSigningRequestSpecFluent;Ljava/lang/Boolean;)V
       9: return

  public io.kubernetes.client.openapi.models.V1beta1CertificateSigningRequestSpecBuilder(io.kubernetes.client.openapi.models.V1beta1CertificateSigningRequestSpecFluent<?>, java.lang.Boolean);
    Code:
       0: aload_0
       1: aload_1
       2: new           #3                  // class io/kubernetes/client/openapi/models/V1beta1CertificateSigningRequestSpec
       5: dup
       6: invokespecial #4                  // Method io/kubernetes/client/openapi/models/V1beta1CertificateSigningRequestSpec."<init>":()V
       9: aload_2
      10: invokespecial #7                  // Method "<init>":(Lio/kubernetes/client/openapi/models/V1beta1CertificateSigningRequestSpecFluent;Lio/kubernetes/client/openapi/models/V1beta1CertificateSigningRequestSpec;Ljava/lang/Boolean;)V
      13: return

  public io.kubernetes.client.openapi.models.V1beta1CertificateSigningRequestSpecBuilder(io.kubernetes.client.openapi.models.V1beta1CertificateSigningRequestSpecFluent<?>, io.kubernetes.client.openapi.models.V1beta1CertificateSigningRequestSpec);
    Code:
       0: aload_0
       1: aload_1
       2: aload_2
       3: iconst_1
       4: invokestatic  #1                  // Method java/lang/Boolean.valueOf:(Z)Ljava/lang/Boolean;
       7: invokespecial #7                  // Method "<init>":(Lio/kubernetes/client/openapi/models/V1beta1CertificateSigningRequestSpecFluent;Lio/kubernetes/client/openapi/models/V1beta1CertificateSigningRequestSpec;Ljava/lang/Boolean;)V
      10: return

  public io.kubernetes.client.openapi.models.V1beta1CertificateSigningRequestSpecBuilder(io.kubernetes.client.openapi.models.V1beta1CertificateSigningRequestSpecFluent<?>, io.kubernetes.client.openapi.models.V1beta1CertificateSigningRequestSpec, java.lang.Boolean);
    Code:
       0: aload_0
       1: invokespecial #8                  // Method io/kubernetes/client/openapi/models/V1beta1CertificateSigningRequestSpecFluentImpl."<init>":()V
       4: aload_0
       5: aload_1
       6: putfield      #9                  // Field fluent:Lio/kubernetes/client/openapi/models/V1beta1CertificateSigningRequestSpecFluent;
       9: aload_1
      10: aload_2
      11: invokevirtual #10                 // Method io/kubernetes/client/openapi/models/V1beta1CertificateSigningRequestSpec.getExtra:()Ljava/util/Map;
      14: invokeinterface #11,  2           // InterfaceMethod io/kubernetes/client/openapi/models/V1beta1CertificateSigningRequestSpecFluent.withExtra:(Ljava/util/Map;)Lio/kubernetes/client/openapi/models/V1beta1CertificateSigningRequestSpecFluent;
      19: pop
      20: aload_1
      21: aload_2
      22: invokevirtual #12                 // Method io/kubernetes/client/openapi/models/V1beta1CertificateSigningRequestSpec.getGroups:()Ljava/util/List;
      25: invokeinterface #13,  2           // InterfaceMethod io/kubernetes/client/openapi/models/V1beta1CertificateSigningRequestSpecFluent.withGroups:(Ljava/util/List;)Lio/kubernetes/client/openapi/models/V1beta1CertificateSigningRequestSpecFluent;
      30: pop
      31: aload_1
      32: aload_2
      33: invokevirtual #14                 // Method io/kubernetes/client/openapi/models/V1beta1CertificateSigningRequestSpec.getRequest:()[B
      36: invokeinterface #15,  2           // InterfaceMethod io/kubernetes/client/openapi/models/V1beta1CertificateSigningRequestSpecFluent.withRequest:([B)Lio/kubernetes/client/openapi/models/V1beta1CertificateSigningRequestSpecFluent;
      41: pop
      42: aload_1
      43: aload_2
      44: invokevirtual #16                 // Method io/kubernetes/client/openapi/models/V1beta1CertificateSigningRequestSpec.getSignerName:()Ljava/lang/String;
      47: invokeinterface #17,  2           // InterfaceMethod io/kubernetes/client/openapi/models/V1beta1CertificateSigningRequestSpecFluent.withSignerName:(Ljava/lang/String;)Lio/kubernetes/client/openapi/models/V1beta1CertificateSigningRequestSpecFluent;
      52: pop
      53: aload_1
      54: aload_2
      55: invokevirtual #18                 // Method io/kubernetes/client/openapi/models/V1beta1CertificateSigningRequestSpec.getUid:()Ljava/lang/String;
      58: invokeinterface #19,  2           // InterfaceMethod io/kubernetes/client/openapi/models/V1beta1CertificateSigningRequestSpecFluent.withUid:(Ljava/lang/String;)Lio/kubernetes/client/openapi/models/V1beta1CertificateSigningRequestSpecFluent;
      63: pop
      64: aload_1
      65: aload_2
      66: invokevirtual #20                 // Method io/kubernetes/client/openapi/models/V1beta1CertificateSigningRequestSpec.getUsages:()Ljava/util/List;
      69: invokeinterface #21,  2           // InterfaceMethod io/kubernetes/client/openapi/models/V1beta1CertificateSigningRequestSpecFluent.withUsages:(Ljava/util/List;)Lio/kubernetes/client/openapi/models/V1beta1CertificateSigningRequestSpecFluent;
      74: pop
      75: aload_1
      76: aload_2
      77: invokevirtual #22                 // Method io/kubernetes/client/openapi/models/V1beta1CertificateSigningRequestSpec.getUsername:()Ljava/lang/String;
      80: invokeinterface #23,  2           // InterfaceMethod io/kubernetes/client/openapi/models/V1beta1CertificateSigningRequestSpecFluent.withUsername:(Ljava/lang/String;)Lio/kubernetes/client/openapi/models/V1beta1CertificateSigningRequestSpecFluent;
      85: pop
      86: aload_0
      87: aload_3
      88: putfield      #24                 // Field validationEnabled:Ljava/lang/Boolean;
      91: return

  public io.kubernetes.client.openapi.models.V1beta1CertificateSigningRequestSpecBuilder(io.kubernetes.client.openapi.models.V1beta1CertificateSigningRequestSpec);
    Code:
       0: aload_0
       1: aload_1
       2: iconst_1
       3: invokestatic  #1                  // Method java/lang/Boolean.valueOf:(Z)Ljava/lang/Boolean;
       6: invokespecial #5                  // Method "<init>":(Lio/kubernetes/client/openapi/models/V1beta1CertificateSigningRequestSpec;Ljava/lang/Boolean;)V
       9: return

  public io.kubernetes.client.openapi.models.V1beta1CertificateSigningRequestSpecBuilder(io.kubernetes.client.openapi.models.V1beta1CertificateSigningRequestSpec, java.lang.Boolean);
    Code:
       0: aload_0
       1: invokespecial #8                  // Method io/kubernetes/client/openapi/models/V1beta1CertificateSigningRequestSpecFluentImpl."<init>":()V
       4: aload_0
       5: aload_0
       6: putfield      #9                  // Field fluent:Lio/kubernetes/client/openapi/models/V1beta1CertificateSigningRequestSpecFluent;
       9: aload_0
      10: aload_1
      11: invokevirtual #10                 // Method io/kubernetes/client/openapi/models/V1beta1CertificateSigningRequestSpec.getExtra:()Ljava/util/Map;
      14: invokevirtual #25                 // Method withExtra:(Ljava/util/Map;)Lio/kubernetes/client/openapi/models/V1beta1CertificateSigningRequestSpecFluent;
      17: pop
      18: aload_0
      19: aload_1
      20: invokevirtual #12                 // Method io/kubernetes/client/openapi/models/V1beta1CertificateSigningRequestSpec.getGroups:()Ljava/util/List;
      23: invokevirtual #26                 // Method withGroups:(Ljava/util/List;)Lio/kubernetes/client/openapi/models/V1beta1CertificateSigningRequestSpecFluent;
      26: pop
      27: aload_0
      28: aload_1
      29: invokevirtual #14                 // Method io/kubernetes/client/openapi/models/V1beta1CertificateSigningRequestSpec.getRequest:()[B
      32: invokevirtual #27                 // Method withRequest:([B)Lio/kubernetes/client/openapi/models/V1beta1CertificateSigningRequestSpecFluent;
      35: pop
      36: aload_0
      37: aload_1
      38: invokevirtual #16                 // Method io/kubernetes/client/openapi/models/V1beta1CertificateSigningRequestSpec.getSignerName:()Ljava/lang/String;
      41: invokevirtual #28                 // Method withSignerName:(Ljava/lang/String;)Lio/kubernetes/client/openapi/models/V1beta1CertificateSigningRequestSpecFluent;
      44: pop
      45: aload_0
      46: aload_1
      47: invokevirtual #18                 // Method io/kubernetes/client/openapi/models/V1beta1CertificateSigningRequestSpec.getUid:()Ljava/lang/String;
      50: invokevirtual #29                 // Method withUid:(Ljava/lang/String;)Lio/kubernetes/client/openapi/models/V1beta1CertificateSigningRequestSpecFluent;
      53: pop
      54: aload_0
      55: aload_1
      56: invokevirtual #20                 // Method io/kubernetes/client/openapi/models/V1beta1CertificateSigningRequestSpec.getUsages:()Ljava/util/List;
      59: invokevirtual #30                 // Method withUsages:(Ljava/util/List;)Lio/kubernetes/client/openapi/models/V1beta1CertificateSigningRequestSpecFluent;
      62: pop
      63: aload_0
      64: aload_1
      65: invokevirtual #22                 // Method io/kubernetes/client/openapi/models/V1beta1CertificateSigningRequestSpec.getUsername:()Ljava/lang/String;
      68: invokevirtual #31                 // Method withUsername:(Ljava/lang/String;)Lio/kubernetes/client/openapi/models/V1beta1CertificateSigningRequestSpecFluent;
      71: pop
      72: aload_0
      73: aload_2
      74: putfield      #24                 // Field validationEnabled:Ljava/lang/Boolean;
      77: return

  public io.kubernetes.client.openapi.models.V1beta1CertificateSigningRequestSpec build();
    Code:
       0: new           #3                  // class io/kubernetes/client/openapi/models/V1beta1CertificateSigningRequestSpec
       3: dup
       4: invokespecial #4                  // Method io/kubernetes/client/openapi/models/V1beta1CertificateSigningRequestSpec."<init>":()V
       7: astore_1
       8: aload_1
       9: aload_0
      10: getfield      #9                  // Field fluent:Lio/kubernetes/client/openapi/models/V1beta1CertificateSigningRequestSpecFluent;
      13: invokeinterface #32,  1           // InterfaceMethod io/kubernetes/client/openapi/models/V1beta1CertificateSigningRequestSpecFluent.getExtra:()Ljava/util/Map;
      18: invokevirtual #33                 // Method io/kubernetes/client/openapi/models/V1beta1CertificateSigningRequestSpec.setExtra:(Ljava/util/Map;)V
      21: aload_1
      22: aload_0
      23: getfield      #9                  // Field fluent:Lio/kubernetes/client/openapi/models/V1beta1CertificateSigningRequestSpecFluent;
      26: invokeinterface #34,  1           // InterfaceMethod io/kubernetes/client/openapi/models/V1beta1CertificateSigningRequestSpecFluent.getGroups:()Ljava/util/List;
      31: invokevirtual #35                 // Method io/kubernetes/client/openapi/models/V1beta1CertificateSigningRequestSpec.setGroups:(Ljava/util/List;)V
      34: aload_1
      35: aload_0
      36: getfield      #9                  // Field fluent:Lio/kubernetes/client/openapi/models/V1beta1CertificateSigningRequestSpecFluent;
      39: invokeinterface #36,  1           // InterfaceMethod io/kubernetes/client/openapi/models/V1beta1CertificateSigningRequestSpecFluent.getRequest:()[B
      44: invokevirtual #37                 // Method io/kubernetes/client/openapi/models/V1beta1CertificateSigningRequestSpec.setRequest:([B)V
      47: aload_1
      48: aload_0
      49: getfield      #9                  // Field fluent:Lio/kubernetes/client/openapi/models/V1beta1CertificateSigningRequestSpecFluent;
      52: invokeinterface #38,  1           // InterfaceMethod io/kubernetes/client/openapi/models/V1beta1CertificateSigningRequestSpecFluent.getSignerName:()Ljava/lang/String;
      57: invokevirtual #39                 // Method io/kubernetes/client/openapi/models/V1beta1CertificateSigningRequestSpec.setSignerName:(Ljava/lang/String;)V
      60: aload_1
      61: aload_0
      62: getfield      #9                  // Field fluent:Lio/kubernetes/client/openapi/models/V1beta1CertificateSigningRequestSpecFluent;
      65: invokeinterface #40,  1           // InterfaceMethod io/kubernetes/client/openapi/models/V1beta1CertificateSigningRequestSpecFluent.getUid:()Ljava/lang/String;
      70: invokevirtual #41                 // Method io/kubernetes/client/openapi/models/V1beta1CertificateSigningRequestSpec.setUid:(Ljava/lang/String;)V
      73: aload_1
      74: aload_0
      75: getfield      #9                  // Field fluent:Lio/kubernetes/client/openapi/models/V1beta1CertificateSigningRequestSpecFluent;
      78: invokeinterface #42,  1           // InterfaceMethod io/kubernetes/client/openapi/models/V1beta1CertificateSigningRequestSpecFluent.getUsages:()Ljava/util/List;
      83: invokevirtual #43                 // Method io/kubernetes/client/openapi/models/V1beta1CertificateSigningRequestSpec.setUsages:(Ljava/util/List;)V
      86: aload_1
      87: aload_0
      88: getfield      #9                  // Field fluent:Lio/kubernetes/client/openapi/models/V1beta1CertificateSigningRequestSpecFluent;
      91: invokeinterface #44,  1           // InterfaceMethod io/kubernetes/client/openapi/models/V1beta1CertificateSigningRequestSpecFluent.getUsername:()Ljava/lang/String;
      96: invokevirtual #45                 // Method io/kubernetes/client/openapi/models/V1beta1CertificateSigningRequestSpec.setUsername:(Ljava/lang/String;)V
      99: aload_1
     100: areturn

  public boolean equals(java.lang.Object);
    Code:
       0: aload_0
       1: aload_1
       2: if_acmpne     7
       5: iconst_1
       6: ireturn
       7: aload_1
       8: ifnull        22
      11: aload_0
      12: invokevirtual #46                 // Method java/lang/Object.getClass:()Ljava/lang/Class;
      15: aload_1
      16: invokevirtual #46                 // Method java/lang/Object.getClass:()Ljava/lang/Class;
      19: if_acmpeq     24
      22: iconst_0
      23: ireturn
      24: aload_0
      25: aload_1
      26: invokespecial #47                 // Method io/kubernetes/client/openapi/models/V1beta1CertificateSigningRequestSpecFluentImpl.equals:(Ljava/lang/Object;)Z
      29: ifne          34
      32: iconst_0
      33: ireturn
      34: aload_1
      35: checkcast     #48                 // class io/kubernetes/client/openapi/models/V1beta1CertificateSigningRequestSpecBuilder
      38: astore_2
      39: aload_0
      40: getfield      #9                  // Field fluent:Lio/kubernetes/client/openapi/models/V1beta1CertificateSigningRequestSpecFluent;
      43: ifnull        71
      46: aload_0
      47: getfield      #9                  // Field fluent:Lio/kubernetes/client/openapi/models/V1beta1CertificateSigningRequestSpecFluent;
      50: aload_0
      51: if_acmpeq     71
      54: aload_0
      55: getfield      #9                  // Field fluent:Lio/kubernetes/client/openapi/models/V1beta1CertificateSigningRequestSpecFluent;
      58: aload_2
      59: getfield      #9                  // Field fluent:Lio/kubernetes/client/openapi/models/V1beta1CertificateSigningRequestSpecFluent;
      62: invokevirtual #49                 // Method java/lang/Object.equals:(Ljava/lang/Object;)Z
      65: ifne          88
      68: goto          86
      71: aload_2
      72: getfield      #9                  // Field fluent:Lio/kubernetes/client/openapi/models/V1beta1CertificateSigningRequestSpecFluent;
      75: ifnull        88
      78: aload_0
      79: getfield      #9                  // Field fluent:Lio/kubernetes/client/openapi/models/V1beta1CertificateSigningRequestSpecFluent;
      82: aload_0
      83: if_acmpeq     88
      86: iconst_0
      87: ireturn
      88: aload_0
      89: getfield      #24                 // Field validationEnabled:Ljava/lang/Boolean;
      92: ifnull        112
      95: aload_0
      96: getfield      #24                 // Field validationEnabled:Ljava/lang/Boolean;
      99: aload_2
     100: getfield      #24                 // Field validationEnabled:Ljava/lang/Boolean;
     103: invokevirtual #50                 // Method java/lang/Boolean.equals:(Ljava/lang/Object;)Z
     106: ifne          121
     109: goto          119
     112: aload_2
     113: getfield      #24                 // Field validationEnabled:Ljava/lang/Boolean;
     116: ifnull        121
     119: iconst_0
     120: ireturn
     121: iconst_1
     122: ireturn

  public int hashCode();
    Code:
       0: iconst_3
       1: anewarray     #51                 // class java/lang/Object
       4: dup
       5: iconst_0
       6: aload_0
       7: getfield      #9                  // Field fluent:Lio/kubernetes/client/openapi/models/V1beta1CertificateSigningRequestSpecFluent;
      10: aastore
      11: dup
      12: iconst_1
      13: aload_0
      14: getfield      #24                 // Field validationEnabled:Ljava/lang/Boolean;
      17: aastore
      18: dup
      19: iconst_2
      20: aload_0
      21: invokespecial #52                 // Method io/kubernetes/client/openapi/models/V1beta1CertificateSigningRequestSpecFluentImpl.hashCode:()I
      24: invokestatic  #53                 // Method java/lang/Integer.valueOf:(I)Ljava/lang/Integer;
      27: aastore
      28: invokestatic  #54                 // Method java/util/Objects.hash:([Ljava/lang/Object;)I
      31: ireturn

  public java.lang.Object build();
    Code:
       0: aload_0
       1: invokevirtual #55                 // Method build:()Lio/kubernetes/client/openapi/models/V1beta1CertificateSigningRequestSpec;
       4: areturn
}
