Compiled from "V1beta1CustomResourceValidationFluentImpl.java"
public class io.kubernetes.client.openapi.models.V1beta1CustomResourceValidationFluentImpl$OpenAPIV3SchemaNestedImpl<N> extends io.kubernetes.client.openapi.models.V1beta1JSONSchemaPropsFluentImpl<io.kubernetes.client.openapi.models.V1beta1CustomResourceValidationFluent$OpenAPIV3SchemaNested<N>> implements io.kubernetes.client.openapi.models.V1beta1CustomResourceValidationFluent$OpenAPIV3SchemaNested<N>, io.kubernetes.client.fluent.Nested<N> {
  private final io.kubernetes.client.openapi.models.V1beta1JSONSchemaPropsBuilder builder;

  final io.kubernetes.client.openapi.models.V1beta1CustomResourceValidationFluentImpl this$0;

  io.kubernetes.client.openapi.models.V1beta1CustomResourceValidationFluentImpl$OpenAPIV3SchemaNestedImpl(io.kubernetes.client.openapi.models.V1beta1CustomResourceValidationFluentImpl, io.kubernetes.client.openapi.models.V1beta1JSONSchemaProps);
    Code:
       0: aload_0
       1: aload_1
       2: putfield      #1                  // Field this$0:Lio/kubernetes/client/openapi/models/V1beta1CustomResourceValidationFluentImpl;
       5: aload_0
       6: invokespecial #2                  // Method io/kubernetes/client/openapi/models/V1beta1JSONSchemaPropsFluentImpl."<init>":()V
       9: aload_0
      10: new           #3                  // class io/kubernetes/client/openapi/models/V1beta1JSONSchemaPropsBuilder
      13: dup
      14: aload_0
      15: aload_2
      16: invokespecial #4                  // Method io/kubernetes/client/openapi/models/V1beta1JSONSchemaPropsBuilder."<init>":(Lio/kubernetes/client/openapi/models/V1beta1JSONSchemaPropsFluent;Lio/kubernetes/client/openapi/models/V1beta1JSONSchemaProps;)V
      19: putfield      #5                  // Field builder:Lio/kubernetes/client/openapi/models/V1beta1JSONSchemaPropsBuilder;
      22: return

  io.kubernetes.client.openapi.models.V1beta1CustomResourceValidationFluentImpl$OpenAPIV3SchemaNestedImpl(io.kubernetes.client.openapi.models.V1beta1CustomResourceValidationFluentImpl);
    Code:
       0: aload_0
       1: aload_1
       2: putfield      #1                  // Field this$0:Lio/kubernetes/client/openapi/models/V1beta1CustomResourceValidationFluentImpl;
       5: aload_0
       6: invokespecial #2                  // Method io/kubernetes/client/openapi/models/V1beta1JSONSchemaPropsFluentImpl."<init>":()V
       9: aload_0
      10: new           #3                  // class io/kubernetes/client/openapi/models/V1beta1JSONSchemaPropsBuilder
      13: dup
      14: aload_0
      15: invokespecial #6                  // Method io/kubernetes/client/openapi/models/V1beta1JSONSchemaPropsBuilder."<init>":(Lio/kubernetes/client/openapi/models/V1beta1JSONSchemaPropsFluent;)V
      18: putfield      #5                  // Field builder:Lio/kubernetes/client/openapi/models/V1beta1JSONSchemaPropsBuilder;
      21: return

  public N and();
    Code:
       0: aload_0
       1: getfield      #1                  // Field this$0:Lio/kubernetes/client/openapi/models/V1beta1CustomResourceValidationFluentImpl;
       4: aload_0
       5: getfield      #5                  // Field builder:Lio/kubernetes/client/openapi/models/V1beta1JSONSchemaPropsBuilder;
       8: invokevirtual #7                  // Method io/kubernetes/client/openapi/models/V1beta1JSONSchemaPropsBuilder.build:()Lio/kubernetes/client/openapi/models/V1beta1JSONSchemaProps;
      11: invokevirtual #8                  // Method io/kubernetes/client/openapi/models/V1beta1CustomResourceValidationFluentImpl.withOpenAPIV3Schema:(Lio/kubernetes/client/openapi/models/V1beta1JSONSchemaProps;)Lio/kubernetes/client/openapi/models/V1beta1CustomResourceValidationFluent;
      14: areturn

  public N endOpenAPIV3Schema();
    Code:
       0: aload_0
       1: invokevirtual #9                  // Method and:()Ljava/lang/Object;
       4: areturn
}
