Compiled from "V1CertificateSigningRequestFluentImpl.java"
public class io.kubernetes.client.openapi.models.V1CertificateSigningRequestFluentImpl<A extends io.kubernetes.client.openapi.models.V1CertificateSigningRequestFluent<A>> extends io.kubernetes.client.fluent.BaseFluent<A> implements io.kubernetes.client.openapi.models.V1CertificateSigningRequestFluent<A> {
  private java.lang.String apiVersion;

  private java.lang.String kind;

  private io.kubernetes.client.openapi.models.V1ObjectMetaBuilder metadata;

  private io.kubernetes.client.openapi.models.V1CertificateSigningRequestSpecBuilder spec;

  private io.kubernetes.client.openapi.models.V1CertificateSigningRequestStatusBuilder status;

  public io.kubernetes.client.openapi.models.V1CertificateSigningRequestFluentImpl();
    Code:
       0: aload_0
       1: invokespecial #1                  // Method io/kubernetes/client/fluent/BaseFluent."<init>":()V
       4: return

  public io.kubernetes.client.openapi.models.V1CertificateSigningRequestFluentImpl(io.kubernetes.client.openapi.models.V1CertificateSigningRequest);
    Code:
       0: aload_0
       1: invokespecial #1                  // Method io/kubernetes/client/fluent/BaseFluent."<init>":()V
       4: aload_0
       5: aload_1
       6: invokevirtual #2                  // Method io/kubernetes/client/openapi/models/V1CertificateSigningRequest.getApiVersion:()Ljava/lang/String;
       9: invokevirtual #3                  // Method withApiVersion:(Ljava/lang/String;)Lio/kubernetes/client/openapi/models/V1CertificateSigningRequestFluent;
      12: pop
      13: aload_0
      14: aload_1
      15: invokevirtual #4                  // Method io/kubernetes/client/openapi/models/V1CertificateSigningRequest.getKind:()Ljava/lang/String;
      18: invokevirtual #5                  // Method withKind:(Ljava/lang/String;)Lio/kubernetes/client/openapi/models/V1CertificateSigningRequestFluent;
      21: pop
      22: aload_0
      23: aload_1
      24: invokevirtual #6                  // Method io/kubernetes/client/openapi/models/V1CertificateSigningRequest.getMetadata:()Lio/kubernetes/client/openapi/models/V1ObjectMeta;
      27: invokevirtual #7                  // Method withMetadata:(Lio/kubernetes/client/openapi/models/V1ObjectMeta;)Lio/kubernetes/client/openapi/models/V1CertificateSigningRequestFluent;
      30: pop
      31: aload_0
      32: aload_1
      33: invokevirtual #8                  // Method io/kubernetes/client/openapi/models/V1CertificateSigningRequest.getSpec:()Lio/kubernetes/client/openapi/models/V1CertificateSigningRequestSpec;
      36: invokevirtual #9                  // Method withSpec:(Lio/kubernetes/client/openapi/models/V1CertificateSigningRequestSpec;)Lio/kubernetes/client/openapi/models/V1CertificateSigningRequestFluent;
      39: pop
      40: aload_0
      41: aload_1
      42: invokevirtual #10                 // Method io/kubernetes/client/openapi/models/V1CertificateSigningRequest.getStatus:()Lio/kubernetes/client/openapi/models/V1CertificateSigningRequestStatus;
      45: invokevirtual #11                 // Method withStatus:(Lio/kubernetes/client/openapi/models/V1CertificateSigningRequestStatus;)Lio/kubernetes/client/openapi/models/V1CertificateSigningRequestFluent;
      48: pop
      49: return

  public java.lang.String getApiVersion();
    Code:
       0: aload_0
       1: getfield      #12                 // Field apiVersion:Ljava/lang/String;
       4: areturn

  public A withApiVersion(java.lang.String);
    Code:
       0: aload_0
       1: aload_1
       2: putfield      #12                 // Field apiVersion:Ljava/lang/String;
       5: aload_0
       6: areturn

  public java.lang.Boolean hasApiVersion();
    Code:
       0: aload_0
       1: getfield      #12                 // Field apiVersion:Ljava/lang/String;
       4: ifnull        11
       7: iconst_1
       8: goto          12
      11: iconst_0
      12: invokestatic  #13                 // Method java/lang/Boolean.valueOf:(Z)Ljava/lang/Boolean;
      15: areturn

  public A withNewApiVersion(java.lang.String);
    Code:
       0: aload_0
       1: new           #14                 // class java/lang/String
       4: dup
       5: aload_1
       6: invokespecial #15                 // Method java/lang/String."<init>":(Ljava/lang/String;)V
       9: invokevirtual #3                  // Method withApiVersion:(Ljava/lang/String;)Lio/kubernetes/client/openapi/models/V1CertificateSigningRequestFluent;
      12: areturn

  public A withNewApiVersion(java.lang.StringBuilder);
    Code:
       0: aload_0
       1: new           #14                 // class java/lang/String
       4: dup
       5: aload_1
       6: invokespecial #16                 // Method java/lang/String."<init>":(Ljava/lang/StringBuilder;)V
       9: invokevirtual #3                  // Method withApiVersion:(Ljava/lang/String;)Lio/kubernetes/client/openapi/models/V1CertificateSigningRequestFluent;
      12: areturn

  public A withNewApiVersion(java.lang.StringBuffer);
    Code:
       0: aload_0
       1: new           #14                 // class java/lang/String
       4: dup
       5: aload_1
       6: invokespecial #17                 // Method java/lang/String."<init>":(Ljava/lang/StringBuffer;)V
       9: invokevirtual #3                  // Method withApiVersion:(Ljava/lang/String;)Lio/kubernetes/client/openapi/models/V1CertificateSigningRequestFluent;
      12: areturn

  public java.lang.String getKind();
    Code:
       0: aload_0
       1: getfield      #18                 // Field kind:Ljava/lang/String;
       4: areturn

  public A withKind(java.lang.String);
    Code:
       0: aload_0
       1: aload_1
       2: putfield      #18                 // Field kind:Ljava/lang/String;
       5: aload_0
       6: areturn

  public java.lang.Boolean hasKind();
    Code:
       0: aload_0
       1: getfield      #18                 // Field kind:Ljava/lang/String;
       4: ifnull        11
       7: iconst_1
       8: goto          12
      11: iconst_0
      12: invokestatic  #13                 // Method java/lang/Boolean.valueOf:(Z)Ljava/lang/Boolean;
      15: areturn

  public A withNewKind(java.lang.String);
    Code:
       0: aload_0
       1: new           #14                 // class java/lang/String
       4: dup
       5: aload_1
       6: invokespecial #15                 // Method java/lang/String."<init>":(Ljava/lang/String;)V
       9: invokevirtual #5                  // Method withKind:(Ljava/lang/String;)Lio/kubernetes/client/openapi/models/V1CertificateSigningRequestFluent;
      12: areturn

  public A withNewKind(java.lang.StringBuilder);
    Code:
       0: aload_0
       1: new           #14                 // class java/lang/String
       4: dup
       5: aload_1
       6: invokespecial #16                 // Method java/lang/String."<init>":(Ljava/lang/StringBuilder;)V
       9: invokevirtual #5                  // Method withKind:(Ljava/lang/String;)Lio/kubernetes/client/openapi/models/V1CertificateSigningRequestFluent;
      12: areturn

  public A withNewKind(java.lang.StringBuffer);
    Code:
       0: aload_0
       1: new           #14                 // class java/lang/String
       4: dup
       5: aload_1
       6: invokespecial #17                 // Method java/lang/String."<init>":(Ljava/lang/StringBuffer;)V
       9: invokevirtual #5                  // Method withKind:(Ljava/lang/String;)Lio/kubernetes/client/openapi/models/V1CertificateSigningRequestFluent;
      12: areturn

  public io.kubernetes.client.openapi.models.V1ObjectMeta getMetadata();
    Code:
       0: aload_0
       1: getfield      #19                 // Field metadata:Lio/kubernetes/client/openapi/models/V1ObjectMetaBuilder;
       4: ifnull        17
       7: aload_0
       8: getfield      #19                 // Field metadata:Lio/kubernetes/client/openapi/models/V1ObjectMetaBuilder;
      11: invokevirtual #20                 // Method io/kubernetes/client/openapi/models/V1ObjectMetaBuilder.build:()Lio/kubernetes/client/openapi/models/V1ObjectMeta;
      14: goto          18
      17: aconst_null
      18: areturn

  public io.kubernetes.client.openapi.models.V1ObjectMeta buildMetadata();
    Code:
       0: aload_0
       1: getfield      #19                 // Field metadata:Lio/kubernetes/client/openapi/models/V1ObjectMetaBuilder;
       4: ifnull        17
       7: aload_0
       8: getfield      #19                 // Field metadata:Lio/kubernetes/client/openapi/models/V1ObjectMetaBuilder;
      11: invokevirtual #20                 // Method io/kubernetes/client/openapi/models/V1ObjectMetaBuilder.build:()Lio/kubernetes/client/openapi/models/V1ObjectMeta;
      14: goto          18
      17: aconst_null
      18: areturn

  public A withMetadata(io.kubernetes.client.openapi.models.V1ObjectMeta);
    Code:
       0: aload_0
       1: getfield      #21                 // Field _visitables:Lio/kubernetes/client/fluent/VisitableMap;
       4: ldc           #22                 // String metadata
       6: invokevirtual #23                 // Method io/kubernetes/client/fluent/VisitableMap.get:(Ljava/lang/Object;)Ljava/util/List;
       9: aload_0
      10: getfield      #19                 // Field metadata:Lio/kubernetes/client/openapi/models/V1ObjectMetaBuilder;
      13: invokeinterface #24,  2           // InterfaceMethod java/util/List.remove:(Ljava/lang/Object;)Z
      18: pop
      19: aload_1
      20: ifnull        54
      23: aload_0
      24: new           #25                 // class io/kubernetes/client/openapi/models/V1ObjectMetaBuilder
      27: dup
      28: aload_1
      29: invokespecial #26                 // Method io/kubernetes/client/openapi/models/V1ObjectMetaBuilder."<init>":(Lio/kubernetes/client/openapi/models/V1ObjectMeta;)V
      32: putfield      #19                 // Field metadata:Lio/kubernetes/client/openapi/models/V1ObjectMetaBuilder;
      35: aload_0
      36: getfield      #21                 // Field _visitables:Lio/kubernetes/client/fluent/VisitableMap;
      39: ldc           #22                 // String metadata
      41: invokevirtual #23                 // Method io/kubernetes/client/fluent/VisitableMap.get:(Ljava/lang/Object;)Ljava/util/List;
      44: aload_0
      45: getfield      #19                 // Field metadata:Lio/kubernetes/client/openapi/models/V1ObjectMetaBuilder;
      48: invokeinterface #27,  2           // InterfaceMethod java/util/List.add:(Ljava/lang/Object;)Z
      53: pop
      54: aload_0
      55: areturn

  public java.lang.Boolean hasMetadata();
    Code:
       0: aload_0
       1: getfield      #19                 // Field metadata:Lio/kubernetes/client/openapi/models/V1ObjectMetaBuilder;
       4: ifnull        11
       7: iconst_1
       8: goto          12
      11: iconst_0
      12: invokestatic  #13                 // Method java/lang/Boolean.valueOf:(Z)Ljava/lang/Boolean;
      15: areturn

  public io.kubernetes.client.openapi.models.V1CertificateSigningRequestFluent$MetadataNested<A> withNewMetadata();
    Code:
       0: new           #28                 // class io/kubernetes/client/openapi/models/V1CertificateSigningRequestFluentImpl$MetadataNestedImpl
       3: dup
       4: aload_0
       5: invokespecial #29                 // Method io/kubernetes/client/openapi/models/V1CertificateSigningRequestFluentImpl$MetadataNestedImpl."<init>":(Lio/kubernetes/client/openapi/models/V1CertificateSigningRequestFluentImpl;)V
       8: areturn

  public io.kubernetes.client.openapi.models.V1CertificateSigningRequestFluent$MetadataNested<A> withNewMetadataLike(io.kubernetes.client.openapi.models.V1ObjectMeta);
    Code:
       0: new           #28                 // class io/kubernetes/client/openapi/models/V1CertificateSigningRequestFluentImpl$MetadataNestedImpl
       3: dup
       4: aload_0
       5: aload_1
       6: invokespecial #30                 // Method io/kubernetes/client/openapi/models/V1CertificateSigningRequestFluentImpl$MetadataNestedImpl."<init>":(Lio/kubernetes/client/openapi/models/V1CertificateSigningRequestFluentImpl;Lio/kubernetes/client/openapi/models/V1ObjectMeta;)V
       9: areturn

  public io.kubernetes.client.openapi.models.V1CertificateSigningRequestFluent$MetadataNested<A> editMetadata();
    Code:
       0: aload_0
       1: aload_0
       2: invokevirtual #31                 // Method getMetadata:()Lio/kubernetes/client/openapi/models/V1ObjectMeta;
       5: invokevirtual #32                 // Method withNewMetadataLike:(Lio/kubernetes/client/openapi/models/V1ObjectMeta;)Lio/kubernetes/client/openapi/models/V1CertificateSigningRequestFluent$MetadataNested;
       8: areturn

  public io.kubernetes.client.openapi.models.V1CertificateSigningRequestFluent$MetadataNested<A> editOrNewMetadata();
    Code:
       0: aload_0
       1: aload_0
       2: invokevirtual #31                 // Method getMetadata:()Lio/kubernetes/client/openapi/models/V1ObjectMeta;
       5: ifnull        15
       8: aload_0
       9: invokevirtual #31                 // Method getMetadata:()Lio/kubernetes/client/openapi/models/V1ObjectMeta;
      12: goto          25
      15: new           #25                 // class io/kubernetes/client/openapi/models/V1ObjectMetaBuilder
      18: dup
      19: invokespecial #33                 // Method io/kubernetes/client/openapi/models/V1ObjectMetaBuilder."<init>":()V
      22: invokevirtual #20                 // Method io/kubernetes/client/openapi/models/V1ObjectMetaBuilder.build:()Lio/kubernetes/client/openapi/models/V1ObjectMeta;
      25: invokevirtual #32                 // Method withNewMetadataLike:(Lio/kubernetes/client/openapi/models/V1ObjectMeta;)Lio/kubernetes/client/openapi/models/V1CertificateSigningRequestFluent$MetadataNested;
      28: areturn

  public io.kubernetes.client.openapi.models.V1CertificateSigningRequestFluent$MetadataNested<A> editOrNewMetadataLike(io.kubernetes.client.openapi.models.V1ObjectMeta);
    Code:
       0: aload_0
       1: aload_0
       2: invokevirtual #31                 // Method getMetadata:()Lio/kubernetes/client/openapi/models/V1ObjectMeta;
       5: ifnull        15
       8: aload_0
       9: invokevirtual #31                 // Method getMetadata:()Lio/kubernetes/client/openapi/models/V1ObjectMeta;
      12: goto          16
      15: aload_1
      16: invokevirtual #32                 // Method withNewMetadataLike:(Lio/kubernetes/client/openapi/models/V1ObjectMeta;)Lio/kubernetes/client/openapi/models/V1CertificateSigningRequestFluent$MetadataNested;
      19: areturn

  public io.kubernetes.client.openapi.models.V1CertificateSigningRequestSpec getSpec();
    Code:
       0: aload_0
       1: getfield      #34                 // Field spec:Lio/kubernetes/client/openapi/models/V1CertificateSigningRequestSpecBuilder;
       4: ifnull        17
       7: aload_0
       8: getfield      #34                 // Field spec:Lio/kubernetes/client/openapi/models/V1CertificateSigningRequestSpecBuilder;
      11: invokevirtual #35                 // Method io/kubernetes/client/openapi/models/V1CertificateSigningRequestSpecBuilder.build:()Lio/kubernetes/client/openapi/models/V1CertificateSigningRequestSpec;
      14: goto          18
      17: aconst_null
      18: areturn

  public io.kubernetes.client.openapi.models.V1CertificateSigningRequestSpec buildSpec();
    Code:
       0: aload_0
       1: getfield      #34                 // Field spec:Lio/kubernetes/client/openapi/models/V1CertificateSigningRequestSpecBuilder;
       4: ifnull        17
       7: aload_0
       8: getfield      #34                 // Field spec:Lio/kubernetes/client/openapi/models/V1CertificateSigningRequestSpecBuilder;
      11: invokevirtual #35                 // Method io/kubernetes/client/openapi/models/V1CertificateSigningRequestSpecBuilder.build:()Lio/kubernetes/client/openapi/models/V1CertificateSigningRequestSpec;
      14: goto          18
      17: aconst_null
      18: areturn

  public A withSpec(io.kubernetes.client.openapi.models.V1CertificateSigningRequestSpec);
    Code:
       0: aload_0
       1: getfield      #21                 // Field _visitables:Lio/kubernetes/client/fluent/VisitableMap;
       4: ldc           #36                 // String spec
       6: invokevirtual #23                 // Method io/kubernetes/client/fluent/VisitableMap.get:(Ljava/lang/Object;)Ljava/util/List;
       9: aload_0
      10: getfield      #34                 // Field spec:Lio/kubernetes/client/openapi/models/V1CertificateSigningRequestSpecBuilder;
      13: invokeinterface #24,  2           // InterfaceMethod java/util/List.remove:(Ljava/lang/Object;)Z
      18: pop
      19: aload_1
      20: ifnull        54
      23: aload_0
      24: new           #37                 // class io/kubernetes/client/openapi/models/V1CertificateSigningRequestSpecBuilder
      27: dup
      28: aload_1
      29: invokespecial #38                 // Method io/kubernetes/client/openapi/models/V1CertificateSigningRequestSpecBuilder."<init>":(Lio/kubernetes/client/openapi/models/V1CertificateSigningRequestSpec;)V
      32: putfield      #34                 // Field spec:Lio/kubernetes/client/openapi/models/V1CertificateSigningRequestSpecBuilder;
      35: aload_0
      36: getfield      #21                 // Field _visitables:Lio/kubernetes/client/fluent/VisitableMap;
      39: ldc           #36                 // String spec
      41: invokevirtual #23                 // Method io/kubernetes/client/fluent/VisitableMap.get:(Ljava/lang/Object;)Ljava/util/List;
      44: aload_0
      45: getfield      #34                 // Field spec:Lio/kubernetes/client/openapi/models/V1CertificateSigningRequestSpecBuilder;
      48: invokeinterface #27,  2           // InterfaceMethod java/util/List.add:(Ljava/lang/Object;)Z
      53: pop
      54: aload_0
      55: areturn

  public java.lang.Boolean hasSpec();
    Code:
       0: aload_0
       1: getfield      #34                 // Field spec:Lio/kubernetes/client/openapi/models/V1CertificateSigningRequestSpecBuilder;
       4: ifnull        11
       7: iconst_1
       8: goto          12
      11: iconst_0
      12: invokestatic  #13                 // Method java/lang/Boolean.valueOf:(Z)Ljava/lang/Boolean;
      15: areturn

  public io.kubernetes.client.openapi.models.V1CertificateSigningRequestFluent$SpecNested<A> withNewSpec();
    Code:
       0: new           #39                 // class io/kubernetes/client/openapi/models/V1CertificateSigningRequestFluentImpl$SpecNestedImpl
       3: dup
       4: aload_0
       5: invokespecial #40                 // Method io/kubernetes/client/openapi/models/V1CertificateSigningRequestFluentImpl$SpecNestedImpl."<init>":(Lio/kubernetes/client/openapi/models/V1CertificateSigningRequestFluentImpl;)V
       8: areturn

  public io.kubernetes.client.openapi.models.V1CertificateSigningRequestFluent$SpecNested<A> withNewSpecLike(io.kubernetes.client.openapi.models.V1CertificateSigningRequestSpec);
    Code:
       0: new           #39                 // class io/kubernetes/client/openapi/models/V1CertificateSigningRequestFluentImpl$SpecNestedImpl
       3: dup
       4: aload_0
       5: aload_1
       6: invokespecial #41                 // Method io/kubernetes/client/openapi/models/V1CertificateSigningRequestFluentImpl$SpecNestedImpl."<init>":(Lio/kubernetes/client/openapi/models/V1CertificateSigningRequestFluentImpl;Lio/kubernetes/client/openapi/models/V1CertificateSigningRequestSpec;)V
       9: areturn

  public io.kubernetes.client.openapi.models.V1CertificateSigningRequestFluent$SpecNested<A> editSpec();
    Code:
       0: aload_0
       1: aload_0
       2: invokevirtual #42                 // Method getSpec:()Lio/kubernetes/client/openapi/models/V1CertificateSigningRequestSpec;
       5: invokevirtual #43                 // Method withNewSpecLike:(Lio/kubernetes/client/openapi/models/V1CertificateSigningRequestSpec;)Lio/kubernetes/client/openapi/models/V1CertificateSigningRequestFluent$SpecNested;
       8: areturn

  public io.kubernetes.client.openapi.models.V1CertificateSigningRequestFluent$SpecNested<A> editOrNewSpec();
    Code:
       0: aload_0
       1: aload_0
       2: invokevirtual #42                 // Method getSpec:()Lio/kubernetes/client/openapi/models/V1CertificateSigningRequestSpec;
       5: ifnull        15
       8: aload_0
       9: invokevirtual #42                 // Method getSpec:()Lio/kubernetes/client/openapi/models/V1CertificateSigningRequestSpec;
      12: goto          25
      15: new           #37                 // class io/kubernetes/client/openapi/models/V1CertificateSigningRequestSpecBuilder
      18: dup
      19: invokespecial #44                 // Method io/kubernetes/client/openapi/models/V1CertificateSigningRequestSpecBuilder."<init>":()V
      22: invokevirtual #35                 // Method io/kubernetes/client/openapi/models/V1CertificateSigningRequestSpecBuilder.build:()Lio/kubernetes/client/openapi/models/V1CertificateSigningRequestSpec;
      25: invokevirtual #43                 // Method withNewSpecLike:(Lio/kubernetes/client/openapi/models/V1CertificateSigningRequestSpec;)Lio/kubernetes/client/openapi/models/V1CertificateSigningRequestFluent$SpecNested;
      28: areturn

  public io.kubernetes.client.openapi.models.V1CertificateSigningRequestFluent$SpecNested<A> editOrNewSpecLike(io.kubernetes.client.openapi.models.V1CertificateSigningRequestSpec);
    Code:
       0: aload_0
       1: aload_0
       2: invokevirtual #42                 // Method getSpec:()Lio/kubernetes/client/openapi/models/V1CertificateSigningRequestSpec;
       5: ifnull        15
       8: aload_0
       9: invokevirtual #42                 // Method getSpec:()Lio/kubernetes/client/openapi/models/V1CertificateSigningRequestSpec;
      12: goto          16
      15: aload_1
      16: invokevirtual #43                 // Method withNewSpecLike:(Lio/kubernetes/client/openapi/models/V1CertificateSigningRequestSpec;)Lio/kubernetes/client/openapi/models/V1CertificateSigningRequestFluent$SpecNested;
      19: areturn

  public io.kubernetes.client.openapi.models.V1CertificateSigningRequestStatus getStatus();
    Code:
       0: aload_0
       1: getfield      #45                 // Field status:Lio/kubernetes/client/openapi/models/V1CertificateSigningRequestStatusBuilder;
       4: ifnull        17
       7: aload_0
       8: getfield      #45                 // Field status:Lio/kubernetes/client/openapi/models/V1CertificateSigningRequestStatusBuilder;
      11: invokevirtual #46                 // Method io/kubernetes/client/openapi/models/V1CertificateSigningRequestStatusBuilder.build:()Lio/kubernetes/client/openapi/models/V1CertificateSigningRequestStatus;
      14: goto          18
      17: aconst_null
      18: areturn

  public io.kubernetes.client.openapi.models.V1CertificateSigningRequestStatus buildStatus();
    Code:
       0: aload_0
       1: getfield      #45                 // Field status:Lio/kubernetes/client/openapi/models/V1CertificateSigningRequestStatusBuilder;
       4: ifnull        17
       7: aload_0
       8: getfield      #45                 // Field status:Lio/kubernetes/client/openapi/models/V1CertificateSigningRequestStatusBuilder;
      11: invokevirtual #46                 // Method io/kubernetes/client/openapi/models/V1CertificateSigningRequestStatusBuilder.build:()Lio/kubernetes/client/openapi/models/V1CertificateSigningRequestStatus;
      14: goto          18
      17: aconst_null
      18: areturn

  public A withStatus(io.kubernetes.client.openapi.models.V1CertificateSigningRequestStatus);
    Code:
       0: aload_0
       1: getfield      #21                 // Field _visitables:Lio/kubernetes/client/fluent/VisitableMap;
       4: ldc           #47                 // String status
       6: invokevirtual #23                 // Method io/kubernetes/client/fluent/VisitableMap.get:(Ljava/lang/Object;)Ljava/util/List;
       9: aload_0
      10: getfield      #45                 // Field status:Lio/kubernetes/client/openapi/models/V1CertificateSigningRequestStatusBuilder;
      13: invokeinterface #24,  2           // InterfaceMethod java/util/List.remove:(Ljava/lang/Object;)Z
      18: pop
      19: aload_1
      20: ifnull        54
      23: aload_0
      24: new           #48                 // class io/kubernetes/client/openapi/models/V1CertificateSigningRequestStatusBuilder
      27: dup
      28: aload_1
      29: invokespecial #49                 // Method io/kubernetes/client/openapi/models/V1CertificateSigningRequestStatusBuilder."<init>":(Lio/kubernetes/client/openapi/models/V1CertificateSigningRequestStatus;)V
      32: putfield      #45                 // Field status:Lio/kubernetes/client/openapi/models/V1CertificateSigningRequestStatusBuilder;
      35: aload_0
      36: getfield      #21                 // Field _visitables:Lio/kubernetes/client/fluent/VisitableMap;
      39: ldc           #47                 // String status
      41: invokevirtual #23                 // Method io/kubernetes/client/fluent/VisitableMap.get:(Ljava/lang/Object;)Ljava/util/List;
      44: aload_0
      45: getfield      #45                 // Field status:Lio/kubernetes/client/openapi/models/V1CertificateSigningRequestStatusBuilder;
      48: invokeinterface #27,  2           // InterfaceMethod java/util/List.add:(Ljava/lang/Object;)Z
      53: pop
      54: aload_0
      55: areturn

  public java.lang.Boolean hasStatus();
    Code:
       0: aload_0
       1: getfield      #45                 // Field status:Lio/kubernetes/client/openapi/models/V1CertificateSigningRequestStatusBuilder;
       4: ifnull        11
       7: iconst_1
       8: goto          12
      11: iconst_0
      12: invokestatic  #13                 // Method java/lang/Boolean.valueOf:(Z)Ljava/lang/Boolean;
      15: areturn

  public io.kubernetes.client.openapi.models.V1CertificateSigningRequestFluent$StatusNested<A> withNewStatus();
    Code:
       0: new           #50                 // class io/kubernetes/client/openapi/models/V1CertificateSigningRequestFluentImpl$StatusNestedImpl
       3: dup
       4: aload_0
       5: invokespecial #51                 // Method io/kubernetes/client/openapi/models/V1CertificateSigningRequestFluentImpl$StatusNestedImpl."<init>":(Lio/kubernetes/client/openapi/models/V1CertificateSigningRequestFluentImpl;)V
       8: areturn

  public io.kubernetes.client.openapi.models.V1CertificateSigningRequestFluent$StatusNested<A> withNewStatusLike(io.kubernetes.client.openapi.models.V1CertificateSigningRequestStatus);
    Code:
       0: new           #50                 // class io/kubernetes/client/openapi/models/V1CertificateSigningRequestFluentImpl$StatusNestedImpl
       3: dup
       4: aload_0
       5: aload_1
       6: invokespecial #52                 // Method io/kubernetes/client/openapi/models/V1CertificateSigningRequestFluentImpl$StatusNestedImpl."<init>":(Lio/kubernetes/client/openapi/models/V1CertificateSigningRequestFluentImpl;Lio/kubernetes/client/openapi/models/V1CertificateSigningRequestStatus;)V
       9: areturn

  public io.kubernetes.client.openapi.models.V1CertificateSigningRequestFluent$StatusNested<A> editStatus();
    Code:
       0: aload_0
       1: aload_0
       2: invokevirtual #53                 // Method getStatus:()Lio/kubernetes/client/openapi/models/V1CertificateSigningRequestStatus;
       5: invokevirtual #54                 // Method withNewStatusLike:(Lio/kubernetes/client/openapi/models/V1CertificateSigningRequestStatus;)Lio/kubernetes/client/openapi/models/V1CertificateSigningRequestFluent$StatusNested;
       8: areturn

  public io.kubernetes.client.openapi.models.V1CertificateSigningRequestFluent$StatusNested<A> editOrNewStatus();
    Code:
       0: aload_0
       1: aload_0
       2: invokevirtual #53                 // Method getStatus:()Lio/kubernetes/client/openapi/models/V1CertificateSigningRequestStatus;
       5: ifnull        15
       8: aload_0
       9: invokevirtual #53                 // Method getStatus:()Lio/kubernetes/client/openapi/models/V1CertificateSigningRequestStatus;
      12: goto          25
      15: new           #48                 // class io/kubernetes/client/openapi/models/V1CertificateSigningRequestStatusBuilder
      18: dup
      19: invokespecial #55                 // Method io/kubernetes/client/openapi/models/V1CertificateSigningRequestStatusBuilder."<init>":()V
      22: invokevirtual #46                 // Method io/kubernetes/client/openapi/models/V1CertificateSigningRequestStatusBuilder.build:()Lio/kubernetes/client/openapi/models/V1CertificateSigningRequestStatus;
      25: invokevirtual #54                 // Method withNewStatusLike:(Lio/kubernetes/client/openapi/models/V1CertificateSigningRequestStatus;)Lio/kubernetes/client/openapi/models/V1CertificateSigningRequestFluent$StatusNested;
      28: areturn

  public io.kubernetes.client.openapi.models.V1CertificateSigningRequestFluent$StatusNested<A> editOrNewStatusLike(io.kubernetes.client.openapi.models.V1CertificateSigningRequestStatus);
    Code:
       0: aload_0
       1: aload_0
       2: invokevirtual #53                 // Method getStatus:()Lio/kubernetes/client/openapi/models/V1CertificateSigningRequestStatus;
       5: ifnull        15
       8: aload_0
       9: invokevirtual #53                 // Method getStatus:()Lio/kubernetes/client/openapi/models/V1CertificateSigningRequestStatus;
      12: goto          16
      15: aload_1
      16: invokevirtual #54                 // Method withNewStatusLike:(Lio/kubernetes/client/openapi/models/V1CertificateSigningRequestStatus;)Lio/kubernetes/client/openapi/models/V1CertificateSigningRequestFluent$StatusNested;
      19: areturn

  public boolean equals(java.lang.Object);
    Code:
       0: aload_0
       1: aload_1
       2: if_acmpne     7
       5: iconst_1
       6: ireturn
       7: aload_1
       8: ifnull        22
      11: aload_0
      12: invokevirtual #56                 // Method java/lang/Object.getClass:()Ljava/lang/Class;
      15: aload_1
      16: invokevirtual #56                 // Method java/lang/Object.getClass:()Ljava/lang/Class;
      19: if_acmpeq     24
      22: iconst_0
      23: ireturn
      24: aload_1
      25: checkcast     #57                 // class io/kubernetes/client/openapi/models/V1CertificateSigningRequestFluentImpl
      28: astore_2
      29: aload_0
      30: getfield      #12                 // Field apiVersion:Ljava/lang/String;
      33: ifnull        53
      36: aload_0
      37: getfield      #12                 // Field apiVersion:Ljava/lang/String;
      40: aload_2
      41: getfield      #12                 // Field apiVersion:Ljava/lang/String;
      44: invokevirtual #58                 // Method java/lang/String.equals:(Ljava/lang/Object;)Z
      47: ifne          62
      50: goto          60
      53: aload_2
      54: getfield      #12                 // Field apiVersion:Ljava/lang/String;
      57: ifnull        62
      60: iconst_0
      61: ireturn
      62: aload_0
      63: getfield      #18                 // Field kind:Ljava/lang/String;
      66: ifnull        86
      69: aload_0
      70: getfield      #18                 // Field kind:Ljava/lang/String;
      73: aload_2
      74: getfield      #18                 // Field kind:Ljava/lang/String;
      77: invokevirtual #58                 // Method java/lang/String.equals:(Ljava/lang/Object;)Z
      80: ifne          95
      83: goto          93
      86: aload_2
      87: getfield      #18                 // Field kind:Ljava/lang/String;
      90: ifnull        95
      93: iconst_0
      94: ireturn
      95: aload_0
      96: getfield      #19                 // Field metadata:Lio/kubernetes/client/openapi/models/V1ObjectMetaBuilder;
      99: ifnull        119
     102: aload_0
     103: getfield      #19                 // Field metadata:Lio/kubernetes/client/openapi/models/V1ObjectMetaBuilder;
     106: aload_2
     107: getfield      #19                 // Field metadata:Lio/kubernetes/client/openapi/models/V1ObjectMetaBuilder;
     110: invokevirtual #59                 // Method io/kubernetes/client/openapi/models/V1ObjectMetaBuilder.equals:(Ljava/lang/Object;)Z
     113: ifne          128
     116: goto          126
     119: aload_2
     120: getfield      #19                 // Field metadata:Lio/kubernetes/client/openapi/models/V1ObjectMetaBuilder;
     123: ifnull        128
     126: iconst_0
     127: ireturn
     128: aload_0
     129: getfield      #34                 // Field spec:Lio/kubernetes/client/openapi/models/V1CertificateSigningRequestSpecBuilder;
     132: ifnull        152
     135: aload_0
     136: getfield      #34                 // Field spec:Lio/kubernetes/client/openapi/models/V1CertificateSigningRequestSpecBuilder;
     139: aload_2
     140: getfield      #34                 // Field spec:Lio/kubernetes/client/openapi/models/V1CertificateSigningRequestSpecBuilder;
     143: invokevirtual #60                 // Method io/kubernetes/client/openapi/models/V1CertificateSigningRequestSpecBuilder.equals:(Ljava/lang/Object;)Z
     146: ifne          161
     149: goto          159
     152: aload_2
     153: getfield      #34                 // Field spec:Lio/kubernetes/client/openapi/models/V1CertificateSigningRequestSpecBuilder;
     156: ifnull        161
     159: iconst_0
     160: ireturn
     161: aload_0
     162: getfield      #45                 // Field status:Lio/kubernetes/client/openapi/models/V1CertificateSigningRequestStatusBuilder;
     165: ifnull        185
     168: aload_0
     169: getfield      #45                 // Field status:Lio/kubernetes/client/openapi/models/V1CertificateSigningRequestStatusBuilder;
     172: aload_2
     173: getfield      #45                 // Field status:Lio/kubernetes/client/openapi/models/V1CertificateSigningRequestStatusBuilder;
     176: invokevirtual #61                 // Method io/kubernetes/client/openapi/models/V1CertificateSigningRequestStatusBuilder.equals:(Ljava/lang/Object;)Z
     179: ifne          194
     182: goto          192
     185: aload_2
     186: getfield      #45                 // Field status:Lio/kubernetes/client/openapi/models/V1CertificateSigningRequestStatusBuilder;
     189: ifnull        194
     192: iconst_0
     193: ireturn
     194: iconst_1
     195: ireturn

  public int hashCode();
    Code:
       0: bipush        6
       2: anewarray     #62                 // class java/lang/Object
       5: dup
       6: iconst_0
       7: aload_0
       8: getfield      #12                 // Field apiVersion:Ljava/lang/String;
      11: aastore
      12: dup
      13: iconst_1
      14: aload_0
      15: getfield      #18                 // Field kind:Ljava/lang/String;
      18: aastore
      19: dup
      20: iconst_2
      21: aload_0
      22: getfield      #19                 // Field metadata:Lio/kubernetes/client/openapi/models/V1ObjectMetaBuilder;
      25: aastore
      26: dup
      27: iconst_3
      28: aload_0
      29: getfield      #34                 // Field spec:Lio/kubernetes/client/openapi/models/V1CertificateSigningRequestSpecBuilder;
      32: aastore
      33: dup
      34: iconst_4
      35: aload_0
      36: getfield      #45                 // Field status:Lio/kubernetes/client/openapi/models/V1CertificateSigningRequestStatusBuilder;
      39: aastore
      40: dup
      41: iconst_5
      42: aload_0
      43: invokespecial #63                 // Method java/lang/Object.hashCode:()I
      46: invokestatic  #64                 // Method java/lang/Integer.valueOf:(I)Ljava/lang/Integer;
      49: aastore
      50: invokestatic  #65                 // Method java/util/Objects.hash:([Ljava/lang/Object;)I
      53: ireturn
}
