Compiled from "V1CustomResourceDefinitionFluentImpl.java"
public class io.kubernetes.client.openapi.models.V1CustomResourceDefinitionFluentImpl$StatusNestedImpl<N> extends io.kubernetes.client.openapi.models.V1CustomResourceDefinitionStatusFluentImpl<io.kubernetes.client.openapi.models.V1CustomResourceDefinitionFluent$StatusNested<N>> implements io.kubernetes.client.openapi.models.V1CustomResourceDefinitionFluent$StatusNested<N>, io.kubernetes.client.fluent.Nested<N> {
  private final io.kubernetes.client.openapi.models.V1CustomResourceDefinitionStatusBuilder builder;

  final io.kubernetes.client.openapi.models.V1CustomResourceDefinitionFluentImpl this$0;

  io.kubernetes.client.openapi.models.V1CustomResourceDefinitionFluentImpl$StatusNestedImpl(io.kubernetes.client.openapi.models.V1CustomResourceDefinitionFluentImpl, io.kubernetes.client.openapi.models.V1CustomResourceDefinitionStatus);
    Code:
       0: aload_0
       1: aload_1
       2: putfield      #1                  // Field this$0:Lio/kubernetes/client/openapi/models/V1CustomResourceDefinitionFluentImpl;
       5: aload_0
       6: invokespecial #2                  // Method io/kubernetes/client/openapi/models/V1CustomResourceDefinitionStatusFluentImpl."<init>":()V
       9: aload_0
      10: new           #3                  // class io/kubernetes/client/openapi/models/V1CustomResourceDefinitionStatusBuilder
      13: dup
      14: aload_0
      15: aload_2
      16: invokespecial #4                  // Method io/kubernetes/client/openapi/models/V1CustomResourceDefinitionStatusBuilder."<init>":(Lio/kubernetes/client/openapi/models/V1CustomResourceDefinitionStatusFluent;Lio/kubernetes/client/openapi/models/V1CustomResourceDefinitionStatus;)V
      19: putfield      #5                  // Field builder:Lio/kubernetes/client/openapi/models/V1CustomResourceDefinitionStatusBuilder;
      22: return

  io.kubernetes.client.openapi.models.V1CustomResourceDefinitionFluentImpl$StatusNestedImpl(io.kubernetes.client.openapi.models.V1CustomResourceDefinitionFluentImpl);
    Code:
       0: aload_0
       1: aload_1
       2: putfield      #1                  // Field this$0:Lio/kubernetes/client/openapi/models/V1CustomResourceDefinitionFluentImpl;
       5: aload_0
       6: invokespecial #2                  // Method io/kubernetes/client/openapi/models/V1CustomResourceDefinitionStatusFluentImpl."<init>":()V
       9: aload_0
      10: new           #3                  // class io/kubernetes/client/openapi/models/V1CustomResourceDefinitionStatusBuilder
      13: dup
      14: aload_0
      15: invokespecial #6                  // Method io/kubernetes/client/openapi/models/V1CustomResourceDefinitionStatusBuilder."<init>":(Lio/kubernetes/client/openapi/models/V1CustomResourceDefinitionStatusFluent;)V
      18: putfield      #5                  // Field builder:Lio/kubernetes/client/openapi/models/V1CustomResourceDefinitionStatusBuilder;
      21: return

  public N and();
    Code:
       0: aload_0
       1: getfield      #1                  // Field this$0:Lio/kubernetes/client/openapi/models/V1CustomResourceDefinitionFluentImpl;
       4: aload_0
       5: getfield      #5                  // Field builder:Lio/kubernetes/client/openapi/models/V1CustomResourceDefinitionStatusBuilder;
       8: invokevirtual #7                  // Method io/kubernetes/client/openapi/models/V1CustomResourceDefinitionStatusBuilder.build:()Lio/kubernetes/client/openapi/models/V1CustomResourceDefinitionStatus;
      11: invokevirtual #8                  // Method io/kubernetes/client/openapi/models/V1CustomResourceDefinitionFluentImpl.withStatus:(Lio/kubernetes/client/openapi/models/V1CustomResourceDefinitionStatus;)Lio/kubernetes/client/openapi/models/V1CustomResourceDefinitionFluent;
      14: areturn

  public N endStatus();
    Code:
       0: aload_0
       1: invokevirtual #9                  // Method and:()Ljava/lang/Object;
       4: areturn
}
