Compiled from "V1IngressServiceBackendFluentImpl.java"
public class io.kubernetes.client.openapi.models.V1IngressServiceBackendFluentImpl<A extends io.kubernetes.client.openapi.models.V1IngressServiceBackendFluent<A>> extends io.kubernetes.client.fluent.BaseFluent<A> implements io.kubernetes.client.openapi.models.V1IngressServiceBackendFluent<A> {
  private java.lang.String name;

  private io.kubernetes.client.openapi.models.V1ServiceBackendPortBuilder port;

  public io.kubernetes.client.openapi.models.V1IngressServiceBackendFluentImpl();
    Code:
       0: aload_0
       1: invokespecial #1                  // Method io/kubernetes/client/fluent/BaseFluent."<init>":()V
       4: return

  public io.kubernetes.client.openapi.models.V1IngressServiceBackendFluentImpl(io.kubernetes.client.openapi.models.V1IngressServiceBackend);
    Code:
       0: aload_0
       1: invokespecial #1                  // Method io/kubernetes/client/fluent/BaseFluent."<init>":()V
       4: aload_0
       5: aload_1
       6: invokevirtual #2                  // Method io/kubernetes/client/openapi/models/V1IngressServiceBackend.getName:()Ljava/lang/String;
       9: invokevirtual #3                  // Method withName:(Ljava/lang/String;)Lio/kubernetes/client/openapi/models/V1IngressServiceBackendFluent;
      12: pop
      13: aload_0
      14: aload_1
      15: invokevirtual #4                  // Method io/kubernetes/client/openapi/models/V1IngressServiceBackend.getPort:()Lio/kubernetes/client/openapi/models/V1ServiceBackendPort;
      18: invokevirtual #5                  // Method withPort:(Lio/kubernetes/client/openapi/models/V1ServiceBackendPort;)Lio/kubernetes/client/openapi/models/V1IngressServiceBackendFluent;
      21: pop
      22: return

  public java.lang.String getName();
    Code:
       0: aload_0
       1: getfield      #6                  // Field name:Ljava/lang/String;
       4: areturn

  public A withName(java.lang.String);
    Code:
       0: aload_0
       1: aload_1
       2: putfield      #6                  // Field name:Ljava/lang/String;
       5: aload_0
       6: areturn

  public java.lang.Boolean hasName();
    Code:
       0: aload_0
       1: getfield      #6                  // Field name:Ljava/lang/String;
       4: ifnull        11
       7: iconst_1
       8: goto          12
      11: iconst_0
      12: invokestatic  #7                  // Method java/lang/Boolean.valueOf:(Z)Ljava/lang/Boolean;
      15: areturn

  public A withNewName(java.lang.String);
    Code:
       0: aload_0
       1: new           #8                  // class java/lang/String
       4: dup
       5: aload_1
       6: invokespecial #9                  // Method java/lang/String."<init>":(Ljava/lang/String;)V
       9: invokevirtual #3                  // Method withName:(Ljava/lang/String;)Lio/kubernetes/client/openapi/models/V1IngressServiceBackendFluent;
      12: areturn

  public A withNewName(java.lang.StringBuilder);
    Code:
       0: aload_0
       1: new           #8                  // class java/lang/String
       4: dup
       5: aload_1
       6: invokespecial #10                 // Method java/lang/String."<init>":(Ljava/lang/StringBuilder;)V
       9: invokevirtual #3                  // Method withName:(Ljava/lang/String;)Lio/kubernetes/client/openapi/models/V1IngressServiceBackendFluent;
      12: areturn

  public A withNewName(java.lang.StringBuffer);
    Code:
       0: aload_0
       1: new           #8                  // class java/lang/String
       4: dup
       5: aload_1
       6: invokespecial #11                 // Method java/lang/String."<init>":(Ljava/lang/StringBuffer;)V
       9: invokevirtual #3                  // Method withName:(Ljava/lang/String;)Lio/kubernetes/client/openapi/models/V1IngressServiceBackendFluent;
      12: areturn

  public io.kubernetes.client.openapi.models.V1ServiceBackendPort getPort();
    Code:
       0: aload_0
       1: getfield      #12                 // Field port:Lio/kubernetes/client/openapi/models/V1ServiceBackendPortBuilder;
       4: ifnull        17
       7: aload_0
       8: getfield      #12                 // Field port:Lio/kubernetes/client/openapi/models/V1ServiceBackendPortBuilder;
      11: invokevirtual #13                 // Method io/kubernetes/client/openapi/models/V1ServiceBackendPortBuilder.build:()Lio/kubernetes/client/openapi/models/V1ServiceBackendPort;
      14: goto          18
      17: aconst_null
      18: areturn

  public io.kubernetes.client.openapi.models.V1ServiceBackendPort buildPort();
    Code:
       0: aload_0
       1: getfield      #12                 // Field port:Lio/kubernetes/client/openapi/models/V1ServiceBackendPortBuilder;
       4: ifnull        17
       7: aload_0
       8: getfield      #12                 // Field port:Lio/kubernetes/client/openapi/models/V1ServiceBackendPortBuilder;
      11: invokevirtual #13                 // Method io/kubernetes/client/openapi/models/V1ServiceBackendPortBuilder.build:()Lio/kubernetes/client/openapi/models/V1ServiceBackendPort;
      14: goto          18
      17: aconst_null
      18: areturn

  public A withPort(io.kubernetes.client.openapi.models.V1ServiceBackendPort);
    Code:
       0: aload_0
       1: getfield      #14                 // Field _visitables:Lio/kubernetes/client/fluent/VisitableMap;
       4: ldc           #15                 // String port
       6: invokevirtual #16                 // Method io/kubernetes/client/fluent/VisitableMap.get:(Ljava/lang/Object;)Ljava/util/List;
       9: aload_0
      10: getfield      #12                 // Field port:Lio/kubernetes/client/openapi/models/V1ServiceBackendPortBuilder;
      13: invokeinterface #17,  2           // InterfaceMethod java/util/List.remove:(Ljava/lang/Object;)Z
      18: pop
      19: aload_1
      20: ifnull        54
      23: aload_0
      24: new           #18                 // class io/kubernetes/client/openapi/models/V1ServiceBackendPortBuilder
      27: dup
      28: aload_1
      29: invokespecial #19                 // Method io/kubernetes/client/openapi/models/V1ServiceBackendPortBuilder."<init>":(Lio/kubernetes/client/openapi/models/V1ServiceBackendPort;)V
      32: putfield      #12                 // Field port:Lio/kubernetes/client/openapi/models/V1ServiceBackendPortBuilder;
      35: aload_0
      36: getfield      #14                 // Field _visitables:Lio/kubernetes/client/fluent/VisitableMap;
      39: ldc           #15                 // String port
      41: invokevirtual #16                 // Method io/kubernetes/client/fluent/VisitableMap.get:(Ljava/lang/Object;)Ljava/util/List;
      44: aload_0
      45: getfield      #12                 // Field port:Lio/kubernetes/client/openapi/models/V1ServiceBackendPortBuilder;
      48: invokeinterface #20,  2           // InterfaceMethod java/util/List.add:(Ljava/lang/Object;)Z
      53: pop
      54: aload_0
      55: areturn

  public java.lang.Boolean hasPort();
    Code:
       0: aload_0
       1: getfield      #12                 // Field port:Lio/kubernetes/client/openapi/models/V1ServiceBackendPortBuilder;
       4: ifnull        11
       7: iconst_1
       8: goto          12
      11: iconst_0
      12: invokestatic  #7                  // Method java/lang/Boolean.valueOf:(Z)Ljava/lang/Boolean;
      15: areturn

  public io.kubernetes.client.openapi.models.V1IngressServiceBackendFluent$PortNested<A> withNewPort();
    Code:
       0: new           #21                 // class io/kubernetes/client/openapi/models/V1IngressServiceBackendFluentImpl$PortNestedImpl
       3: dup
       4: aload_0
       5: invokespecial #22                 // Method io/kubernetes/client/openapi/models/V1IngressServiceBackendFluentImpl$PortNestedImpl."<init>":(Lio/kubernetes/client/openapi/models/V1IngressServiceBackendFluentImpl;)V
       8: areturn

  public io.kubernetes.client.openapi.models.V1IngressServiceBackendFluent$PortNested<A> withNewPortLike(io.kubernetes.client.openapi.models.V1ServiceBackendPort);
    Code:
       0: new           #21                 // class io/kubernetes/client/openapi/models/V1IngressServiceBackendFluentImpl$PortNestedImpl
       3: dup
       4: aload_0
       5: aload_1
       6: invokespecial #23                 // Method io/kubernetes/client/openapi/models/V1IngressServiceBackendFluentImpl$PortNestedImpl."<init>":(Lio/kubernetes/client/openapi/models/V1IngressServiceBackendFluentImpl;Lio/kubernetes/client/openapi/models/V1ServiceBackendPort;)V
       9: areturn

  public io.kubernetes.client.openapi.models.V1IngressServiceBackendFluent$PortNested<A> editPort();
    Code:
       0: aload_0
       1: aload_0
       2: invokevirtual #24                 // Method getPort:()Lio/kubernetes/client/openapi/models/V1ServiceBackendPort;
       5: invokevirtual #25                 // Method withNewPortLike:(Lio/kubernetes/client/openapi/models/V1ServiceBackendPort;)Lio/kubernetes/client/openapi/models/V1IngressServiceBackendFluent$PortNested;
       8: areturn

  public io.kubernetes.client.openapi.models.V1IngressServiceBackendFluent$PortNested<A> editOrNewPort();
    Code:
       0: aload_0
       1: aload_0
       2: invokevirtual #24                 // Method getPort:()Lio/kubernetes/client/openapi/models/V1ServiceBackendPort;
       5: ifnull        15
       8: aload_0
       9: invokevirtual #24                 // Method getPort:()Lio/kubernetes/client/openapi/models/V1ServiceBackendPort;
      12: goto          25
      15: new           #18                 // class io/kubernetes/client/openapi/models/V1ServiceBackendPortBuilder
      18: dup
      19: invokespecial #26                 // Method io/kubernetes/client/openapi/models/V1ServiceBackendPortBuilder."<init>":()V
      22: invokevirtual #13                 // Method io/kubernetes/client/openapi/models/V1ServiceBackendPortBuilder.build:()Lio/kubernetes/client/openapi/models/V1ServiceBackendPort;
      25: invokevirtual #25                 // Method withNewPortLike:(Lio/kubernetes/client/openapi/models/V1ServiceBackendPort;)Lio/kubernetes/client/openapi/models/V1IngressServiceBackendFluent$PortNested;
      28: areturn

  public io.kubernetes.client.openapi.models.V1IngressServiceBackendFluent$PortNested<A> editOrNewPortLike(io.kubernetes.client.openapi.models.V1ServiceBackendPort);
    Code:
       0: aload_0
       1: aload_0
       2: invokevirtual #24                 // Method getPort:()Lio/kubernetes/client/openapi/models/V1ServiceBackendPort;
       5: ifnull        15
       8: aload_0
       9: invokevirtual #24                 // Method getPort:()Lio/kubernetes/client/openapi/models/V1ServiceBackendPort;
      12: goto          16
      15: aload_1
      16: invokevirtual #25                 // Method withNewPortLike:(Lio/kubernetes/client/openapi/models/V1ServiceBackendPort;)Lio/kubernetes/client/openapi/models/V1IngressServiceBackendFluent$PortNested;
      19: areturn

  public boolean equals(java.lang.Object);
    Code:
       0: aload_0
       1: aload_1
       2: if_acmpne     7
       5: iconst_1
       6: ireturn
       7: aload_1
       8: ifnull        22
      11: aload_0
      12: invokevirtual #27                 // Method java/lang/Object.getClass:()Ljava/lang/Class;
      15: aload_1
      16: invokevirtual #27                 // Method java/lang/Object.getClass:()Ljava/lang/Class;
      19: if_acmpeq     24
      22: iconst_0
      23: ireturn
      24: aload_1
      25: checkcast     #28                 // class io/kubernetes/client/openapi/models/V1IngressServiceBackendFluentImpl
      28: astore_2
      29: aload_0
      30: getfield      #6                  // Field name:Ljava/lang/String;
      33: ifnull        53
      36: aload_0
      37: getfield      #6                  // Field name:Ljava/lang/String;
      40: aload_2
      41: getfield      #6                  // Field name:Ljava/lang/String;
      44: invokevirtual #29                 // Method java/lang/String.equals:(Ljava/lang/Object;)Z
      47: ifne          62
      50: goto          60
      53: aload_2
      54: getfield      #6                  // Field name:Ljava/lang/String;
      57: ifnull        62
      60: iconst_0
      61: ireturn
      62: aload_0
      63: getfield      #12                 // Field port:Lio/kubernetes/client/openapi/models/V1ServiceBackendPortBuilder;
      66: ifnull        86
      69: aload_0
      70: getfield      #12                 // Field port:Lio/kubernetes/client/openapi/models/V1ServiceBackendPortBuilder;
      73: aload_2
      74: getfield      #12                 // Field port:Lio/kubernetes/client/openapi/models/V1ServiceBackendPortBuilder;
      77: invokevirtual #30                 // Method io/kubernetes/client/openapi/models/V1ServiceBackendPortBuilder.equals:(Ljava/lang/Object;)Z
      80: ifne          95
      83: goto          93
      86: aload_2
      87: getfield      #12                 // Field port:Lio/kubernetes/client/openapi/models/V1ServiceBackendPortBuilder;
      90: ifnull        95
      93: iconst_0
      94: ireturn
      95: iconst_1
      96: ireturn

  public int hashCode();
    Code:
       0: iconst_3
       1: anewarray     #31                 // class java/lang/Object
       4: dup
       5: iconst_0
       6: aload_0
       7: getfield      #6                  // Field name:Ljava/lang/String;
      10: aastore
      11: dup
      12: iconst_1
      13: aload_0
      14: getfield      #12                 // Field port:Lio/kubernetes/client/openapi/models/V1ServiceBackendPortBuilder;
      17: aastore
      18: dup
      19: iconst_2
      20: aload_0
      21: invokespecial #32                 // Method java/lang/Object.hashCode:()I
      24: invokestatic  #33                 // Method java/lang/Integer.valueOf:(I)Ljava/lang/Integer;
      27: aastore
      28: invokestatic  #34                 // Method java/util/Objects.hash:([Ljava/lang/Object;)I
      31: ireturn
}
