Compiled from "V1JobSpecBuilder.java"
public class io.kubernetes.client.openapi.models.V1JobSpecBuilder extends io.kubernetes.client.openapi.models.V1JobSpecFluentImpl<io.kubernetes.client.openapi.models.V1JobSpecBuilder> implements io.kubernetes.client.fluent.VisitableBuilder<io.kubernetes.client.openapi.models.V1JobSpec, io.kubernetes.client.openapi.models.V1JobSpecBuilder> {
  io.kubernetes.client.openapi.models.V1JobSpecFluent<?> fluent;

  java.lang.Boolean validationEnabled;

  public io.kubernetes.client.openapi.models.V1JobSpecBuilder();
    Code:
       0: aload_0
       1: iconst_1
       2: invokestatic  #1                  // Method java/lang/Boolean.valueOf:(Z)Ljava/lang/Boolean;
       5: invokespecial #2                  // Method "<init>":(Ljava/lang/Boolean;)V
       8: return

  public io.kubernetes.client.openapi.models.V1JobSpecBuilder(java.lang.Boolean);
    Code:
       0: aload_0
       1: new           #3                  // class io/kubernetes/client/openapi/models/V1JobSpec
       4: dup
       5: invokespecial #4                  // Method io/kubernetes/client/openapi/models/V1JobSpec."<init>":()V
       8: aload_1
       9: invokespecial #5                  // Method "<init>":(Lio/kubernetes/client/openapi/models/V1JobSpec;Ljava/lang/Boolean;)V
      12: return

  public io.kubernetes.client.openapi.models.V1JobSpecBuilder(io.kubernetes.client.openapi.models.V1JobSpecFluent<?>);
    Code:
       0: aload_0
       1: aload_1
       2: iconst_1
       3: invokestatic  #1                  // Method java/lang/Boolean.valueOf:(Z)Ljava/lang/Boolean;
       6: invokespecial #6                  // Method "<init>":(Lio/kubernetes/client/openapi/models/V1JobSpecFluent;Ljava/lang/Boolean;)V
       9: return

  public io.kubernetes.client.openapi.models.V1JobSpecBuilder(io.kubernetes.client.openapi.models.V1JobSpecFluent<?>, java.lang.Boolean);
    Code:
       0: aload_0
       1: aload_1
       2: new           #3                  // class io/kubernetes/client/openapi/models/V1JobSpec
       5: dup
       6: invokespecial #4                  // Method io/kubernetes/client/openapi/models/V1JobSpec."<init>":()V
       9: aload_2
      10: invokespecial #7                  // Method "<init>":(Lio/kubernetes/client/openapi/models/V1JobSpecFluent;Lio/kubernetes/client/openapi/models/V1JobSpec;Ljava/lang/Boolean;)V
      13: return

  public io.kubernetes.client.openapi.models.V1JobSpecBuilder(io.kubernetes.client.openapi.models.V1JobSpecFluent<?>, io.kubernetes.client.openapi.models.V1JobSpec);
    Code:
       0: aload_0
       1: aload_1
       2: aload_2
       3: iconst_1
       4: invokestatic  #1                  // Method java/lang/Boolean.valueOf:(Z)Ljava/lang/Boolean;
       7: invokespecial #7                  // Method "<init>":(Lio/kubernetes/client/openapi/models/V1JobSpecFluent;Lio/kubernetes/client/openapi/models/V1JobSpec;Ljava/lang/Boolean;)V
      10: return

  public io.kubernetes.client.openapi.models.V1JobSpecBuilder(io.kubernetes.client.openapi.models.V1JobSpecFluent<?>, io.kubernetes.client.openapi.models.V1JobSpec, java.lang.Boolean);
    Code:
       0: aload_0
       1: invokespecial #8                  // Method io/kubernetes/client/openapi/models/V1JobSpecFluentImpl."<init>":()V
       4: aload_0
       5: aload_1
       6: putfield      #9                  // Field fluent:Lio/kubernetes/client/openapi/models/V1JobSpecFluent;
       9: aload_1
      10: aload_2
      11: invokevirtual #10                 // Method io/kubernetes/client/openapi/models/V1JobSpec.getActiveDeadlineSeconds:()Ljava/lang/Long;
      14: invokeinterface #11,  2           // InterfaceMethod io/kubernetes/client/openapi/models/V1JobSpecFluent.withActiveDeadlineSeconds:(Ljava/lang/Long;)Lio/kubernetes/client/openapi/models/V1JobSpecFluent;
      19: pop
      20: aload_1
      21: aload_2
      22: invokevirtual #12                 // Method io/kubernetes/client/openapi/models/V1JobSpec.getBackoffLimit:()Ljava/lang/Integer;
      25: invokeinterface #13,  2           // InterfaceMethod io/kubernetes/client/openapi/models/V1JobSpecFluent.withBackoffLimit:(Ljava/lang/Integer;)Lio/kubernetes/client/openapi/models/V1JobSpecFluent;
      30: pop
      31: aload_1
      32: aload_2
      33: invokevirtual #14                 // Method io/kubernetes/client/openapi/models/V1JobSpec.getCompletions:()Ljava/lang/Integer;
      36: invokeinterface #15,  2           // InterfaceMethod io/kubernetes/client/openapi/models/V1JobSpecFluent.withCompletions:(Ljava/lang/Integer;)Lio/kubernetes/client/openapi/models/V1JobSpecFluent;
      41: pop
      42: aload_1
      43: aload_2
      44: invokevirtual #16                 // Method io/kubernetes/client/openapi/models/V1JobSpec.getManualSelector:()Ljava/lang/Boolean;
      47: invokeinterface #17,  2           // InterfaceMethod io/kubernetes/client/openapi/models/V1JobSpecFluent.withManualSelector:(Ljava/lang/Boolean;)Lio/kubernetes/client/openapi/models/V1JobSpecFluent;
      52: pop
      53: aload_1
      54: aload_2
      55: invokevirtual #18                 // Method io/kubernetes/client/openapi/models/V1JobSpec.getParallelism:()Ljava/lang/Integer;
      58: invokeinterface #19,  2           // InterfaceMethod io/kubernetes/client/openapi/models/V1JobSpecFluent.withParallelism:(Ljava/lang/Integer;)Lio/kubernetes/client/openapi/models/V1JobSpecFluent;
      63: pop
      64: aload_1
      65: aload_2
      66: invokevirtual #20                 // Method io/kubernetes/client/openapi/models/V1JobSpec.getSelector:()Lio/kubernetes/client/openapi/models/V1LabelSelector;
      69: invokeinterface #21,  2           // InterfaceMethod io/kubernetes/client/openapi/models/V1JobSpecFluent.withSelector:(Lio/kubernetes/client/openapi/models/V1LabelSelector;)Lio/kubernetes/client/openapi/models/V1JobSpecFluent;
      74: pop
      75: aload_1
      76: aload_2
      77: invokevirtual #22                 // Method io/kubernetes/client/openapi/models/V1JobSpec.getTemplate:()Lio/kubernetes/client/openapi/models/V1PodTemplateSpec;
      80: invokeinterface #23,  2           // InterfaceMethod io/kubernetes/client/openapi/models/V1JobSpecFluent.withTemplate:(Lio/kubernetes/client/openapi/models/V1PodTemplateSpec;)Lio/kubernetes/client/openapi/models/V1JobSpecFluent;
      85: pop
      86: aload_1
      87: aload_2
      88: invokevirtual #24                 // Method io/kubernetes/client/openapi/models/V1JobSpec.getTtlSecondsAfterFinished:()Ljava/lang/Integer;
      91: invokeinterface #25,  2           // InterfaceMethod io/kubernetes/client/openapi/models/V1JobSpecFluent.withTtlSecondsAfterFinished:(Ljava/lang/Integer;)Lio/kubernetes/client/openapi/models/V1JobSpecFluent;
      96: pop
      97: aload_0
      98: aload_3
      99: putfield      #26                 // Field validationEnabled:Ljava/lang/Boolean;
     102: return

  public io.kubernetes.client.openapi.models.V1JobSpecBuilder(io.kubernetes.client.openapi.models.V1JobSpec);
    Code:
       0: aload_0
       1: aload_1
       2: iconst_1
       3: invokestatic  #1                  // Method java/lang/Boolean.valueOf:(Z)Ljava/lang/Boolean;
       6: invokespecial #5                  // Method "<init>":(Lio/kubernetes/client/openapi/models/V1JobSpec;Ljava/lang/Boolean;)V
       9: return

  public io.kubernetes.client.openapi.models.V1JobSpecBuilder(io.kubernetes.client.openapi.models.V1JobSpec, java.lang.Boolean);
    Code:
       0: aload_0
       1: invokespecial #8                  // Method io/kubernetes/client/openapi/models/V1JobSpecFluentImpl."<init>":()V
       4: aload_0
       5: aload_0
       6: putfield      #9                  // Field fluent:Lio/kubernetes/client/openapi/models/V1JobSpecFluent;
       9: aload_0
      10: aload_1
      11: invokevirtual #10                 // Method io/kubernetes/client/openapi/models/V1JobSpec.getActiveDeadlineSeconds:()Ljava/lang/Long;
      14: invokevirtual #27                 // Method withActiveDeadlineSeconds:(Ljava/lang/Long;)Lio/kubernetes/client/openapi/models/V1JobSpecFluent;
      17: pop
      18: aload_0
      19: aload_1
      20: invokevirtual #12                 // Method io/kubernetes/client/openapi/models/V1JobSpec.getBackoffLimit:()Ljava/lang/Integer;
      23: invokevirtual #28                 // Method withBackoffLimit:(Ljava/lang/Integer;)Lio/kubernetes/client/openapi/models/V1JobSpecFluent;
      26: pop
      27: aload_0
      28: aload_1
      29: invokevirtual #14                 // Method io/kubernetes/client/openapi/models/V1JobSpec.getCompletions:()Ljava/lang/Integer;
      32: invokevirtual #29                 // Method withCompletions:(Ljava/lang/Integer;)Lio/kubernetes/client/openapi/models/V1JobSpecFluent;
      35: pop
      36: aload_0
      37: aload_1
      38: invokevirtual #16                 // Method io/kubernetes/client/openapi/models/V1JobSpec.getManualSelector:()Ljava/lang/Boolean;
      41: invokevirtual #30                 // Method withManualSelector:(Ljava/lang/Boolean;)Lio/kubernetes/client/openapi/models/V1JobSpecFluent;
      44: pop
      45: aload_0
      46: aload_1
      47: invokevirtual #18                 // Method io/kubernetes/client/openapi/models/V1JobSpec.getParallelism:()Ljava/lang/Integer;
      50: invokevirtual #31                 // Method withParallelism:(Ljava/lang/Integer;)Lio/kubernetes/client/openapi/models/V1JobSpecFluent;
      53: pop
      54: aload_0
      55: aload_1
      56: invokevirtual #20                 // Method io/kubernetes/client/openapi/models/V1JobSpec.getSelector:()Lio/kubernetes/client/openapi/models/V1LabelSelector;
      59: invokevirtual #32                 // Method withSelector:(Lio/kubernetes/client/openapi/models/V1LabelSelector;)Lio/kubernetes/client/openapi/models/V1JobSpecFluent;
      62: pop
      63: aload_0
      64: aload_1
      65: invokevirtual #22                 // Method io/kubernetes/client/openapi/models/V1JobSpec.getTemplate:()Lio/kubernetes/client/openapi/models/V1PodTemplateSpec;
      68: invokevirtual #33                 // Method withTemplate:(Lio/kubernetes/client/openapi/models/V1PodTemplateSpec;)Lio/kubernetes/client/openapi/models/V1JobSpecFluent;
      71: pop
      72: aload_0
      73: aload_1
      74: invokevirtual #24                 // Method io/kubernetes/client/openapi/models/V1JobSpec.getTtlSecondsAfterFinished:()Ljava/lang/Integer;
      77: invokevirtual #34                 // Method withTtlSecondsAfterFinished:(Ljava/lang/Integer;)Lio/kubernetes/client/openapi/models/V1JobSpecFluent;
      80: pop
      81: aload_0
      82: aload_2
      83: putfield      #26                 // Field validationEnabled:Ljava/lang/Boolean;
      86: return

  public io.kubernetes.client.openapi.models.V1JobSpec build();
    Code:
       0: new           #3                  // class io/kubernetes/client/openapi/models/V1JobSpec
       3: dup
       4: invokespecial #4                  // Method io/kubernetes/client/openapi/models/V1JobSpec."<init>":()V
       7: astore_1
       8: aload_1
       9: aload_0
      10: getfield      #9                  // Field fluent:Lio/kubernetes/client/openapi/models/V1JobSpecFluent;
      13: invokeinterface #35,  1           // InterfaceMethod io/kubernetes/client/openapi/models/V1JobSpecFluent.getActiveDeadlineSeconds:()Ljava/lang/Long;
      18: invokevirtual #36                 // Method io/kubernetes/client/openapi/models/V1JobSpec.setActiveDeadlineSeconds:(Ljava/lang/Long;)V
      21: aload_1
      22: aload_0
      23: getfield      #9                  // Field fluent:Lio/kubernetes/client/openapi/models/V1JobSpecFluent;
      26: invokeinterface #37,  1           // InterfaceMethod io/kubernetes/client/openapi/models/V1JobSpecFluent.getBackoffLimit:()Ljava/lang/Integer;
      31: invokevirtual #38                 // Method io/kubernetes/client/openapi/models/V1JobSpec.setBackoffLimit:(Ljava/lang/Integer;)V
      34: aload_1
      35: aload_0
      36: getfield      #9                  // Field fluent:Lio/kubernetes/client/openapi/models/V1JobSpecFluent;
      39: invokeinterface #39,  1           // InterfaceMethod io/kubernetes/client/openapi/models/V1JobSpecFluent.getCompletions:()Ljava/lang/Integer;
      44: invokevirtual #40                 // Method io/kubernetes/client/openapi/models/V1JobSpec.setCompletions:(Ljava/lang/Integer;)V
      47: aload_1
      48: aload_0
      49: getfield      #9                  // Field fluent:Lio/kubernetes/client/openapi/models/V1JobSpecFluent;
      52: invokeinterface #41,  1           // InterfaceMethod io/kubernetes/client/openapi/models/V1JobSpecFluent.isManualSelector:()Ljava/lang/Boolean;
      57: invokevirtual #42                 // Method io/kubernetes/client/openapi/models/V1JobSpec.setManualSelector:(Ljava/lang/Boolean;)V
      60: aload_1
      61: aload_0
      62: getfield      #9                  // Field fluent:Lio/kubernetes/client/openapi/models/V1JobSpecFluent;
      65: invokeinterface #43,  1           // InterfaceMethod io/kubernetes/client/openapi/models/V1JobSpecFluent.getParallelism:()Ljava/lang/Integer;
      70: invokevirtual #44                 // Method io/kubernetes/client/openapi/models/V1JobSpec.setParallelism:(Ljava/lang/Integer;)V
      73: aload_1
      74: aload_0
      75: getfield      #9                  // Field fluent:Lio/kubernetes/client/openapi/models/V1JobSpecFluent;
      78: invokeinterface #45,  1           // InterfaceMethod io/kubernetes/client/openapi/models/V1JobSpecFluent.getSelector:()Lio/kubernetes/client/openapi/models/V1LabelSelector;
      83: invokevirtual #46                 // Method io/kubernetes/client/openapi/models/V1JobSpec.setSelector:(Lio/kubernetes/client/openapi/models/V1LabelSelector;)V
      86: aload_1
      87: aload_0
      88: getfield      #9                  // Field fluent:Lio/kubernetes/client/openapi/models/V1JobSpecFluent;
      91: invokeinterface #47,  1           // InterfaceMethod io/kubernetes/client/openapi/models/V1JobSpecFluent.getTemplate:()Lio/kubernetes/client/openapi/models/V1PodTemplateSpec;
      96: invokevirtual #48                 // Method io/kubernetes/client/openapi/models/V1JobSpec.setTemplate:(Lio/kubernetes/client/openapi/models/V1PodTemplateSpec;)V
      99: aload_1
     100: aload_0
     101: getfield      #9                  // Field fluent:Lio/kubernetes/client/openapi/models/V1JobSpecFluent;
     104: invokeinterface #49,  1           // InterfaceMethod io/kubernetes/client/openapi/models/V1JobSpecFluent.getTtlSecondsAfterFinished:()Ljava/lang/Integer;
     109: invokevirtual #50                 // Method io/kubernetes/client/openapi/models/V1JobSpec.setTtlSecondsAfterFinished:(Ljava/lang/Integer;)V
     112: aload_1
     113: areturn

  public boolean equals(java.lang.Object);
    Code:
       0: aload_0
       1: aload_1
       2: if_acmpne     7
       5: iconst_1
       6: ireturn
       7: aload_1
       8: ifnull        22
      11: aload_0
      12: invokevirtual #51                 // Method java/lang/Object.getClass:()Ljava/lang/Class;
      15: aload_1
      16: invokevirtual #51                 // Method java/lang/Object.getClass:()Ljava/lang/Class;
      19: if_acmpeq     24
      22: iconst_0
      23: ireturn
      24: aload_0
      25: aload_1
      26: invokespecial #52                 // Method io/kubernetes/client/openapi/models/V1JobSpecFluentImpl.equals:(Ljava/lang/Object;)Z
      29: ifne          34
      32: iconst_0
      33: ireturn
      34: aload_1
      35: checkcast     #53                 // class io/kubernetes/client/openapi/models/V1JobSpecBuilder
      38: astore_2
      39: aload_0
      40: getfield      #9                  // Field fluent:Lio/kubernetes/client/openapi/models/V1JobSpecFluent;
      43: ifnull        71
      46: aload_0
      47: getfield      #9                  // Field fluent:Lio/kubernetes/client/openapi/models/V1JobSpecFluent;
      50: aload_0
      51: if_acmpeq     71
      54: aload_0
      55: getfield      #9                  // Field fluent:Lio/kubernetes/client/openapi/models/V1JobSpecFluent;
      58: aload_2
      59: getfield      #9                  // Field fluent:Lio/kubernetes/client/openapi/models/V1JobSpecFluent;
      62: invokevirtual #54                 // Method java/lang/Object.equals:(Ljava/lang/Object;)Z
      65: ifne          88
      68: goto          86
      71: aload_2
      72: getfield      #9                  // Field fluent:Lio/kubernetes/client/openapi/models/V1JobSpecFluent;
      75: ifnull        88
      78: aload_0
      79: getfield      #9                  // Field fluent:Lio/kubernetes/client/openapi/models/V1JobSpecFluent;
      82: aload_0
      83: if_acmpeq     88
      86: iconst_0
      87: ireturn
      88: aload_0
      89: getfield      #26                 // Field validationEnabled:Ljava/lang/Boolean;
      92: ifnull        112
      95: aload_0
      96: getfield      #26                 // Field validationEnabled:Ljava/lang/Boolean;
      99: aload_2
     100: getfield      #26                 // Field validationEnabled:Ljava/lang/Boolean;
     103: invokevirtual #55                 // Method java/lang/Boolean.equals:(Ljava/lang/Object;)Z
     106: ifne          121
     109: goto          119
     112: aload_2
     113: getfield      #26                 // Field validationEnabled:Ljava/lang/Boolean;
     116: ifnull        121
     119: iconst_0
     120: ireturn
     121: iconst_1
     122: ireturn

  public int hashCode();
    Code:
       0: iconst_3
       1: anewarray     #56                 // class java/lang/Object
       4: dup
       5: iconst_0
       6: aload_0
       7: getfield      #9                  // Field fluent:Lio/kubernetes/client/openapi/models/V1JobSpecFluent;
      10: aastore
      11: dup
      12: iconst_1
      13: aload_0
      14: getfield      #26                 // Field validationEnabled:Ljava/lang/Boolean;
      17: aastore
      18: dup
      19: iconst_2
      20: aload_0
      21: invokespecial #57                 // Method io/kubernetes/client/openapi/models/V1JobSpecFluentImpl.hashCode:()I
      24: invokestatic  #58                 // Method java/lang/Integer.valueOf:(I)Ljava/lang/Integer;
      27: aastore
      28: invokestatic  #59                 // Method java/util/Objects.hash:([Ljava/lang/Object;)I
      31: ireturn

  public java.lang.Object build();
    Code:
       0: aload_0
       1: invokevirtual #60                 // Method build:()Lio/kubernetes/client/openapi/models/V1JobSpec;
       4: areturn
}
