Compiled from "V1PodAffinityFluentImpl.java"
public class io.kubernetes.client.openapi.models.V1PodAffinityFluentImpl$RequiredDuringSchedulingIgnoredDuringExecutionNestedImpl<N> extends io.kubernetes.client.openapi.models.V1PodAffinityTermFluentImpl<io.kubernetes.client.openapi.models.V1PodAffinityFluent$RequiredDuringSchedulingIgnoredDuringExecutionNested<N>> implements io.kubernetes.client.openapi.models.V1PodAffinityFluent$RequiredDuringSchedulingIgnoredDuringExecutionNested<N>, io.kubernetes.client.fluent.Nested<N> {
  private final io.kubernetes.client.openapi.models.V1PodAffinityTermBuilder builder;

  private final int index;

  final io.kubernetes.client.openapi.models.V1PodAffinityFluentImpl this$0;

  io.kubernetes.client.openapi.models.V1PodAffinityFluentImpl$RequiredDuringSchedulingIgnoredDuringExecutionNestedImpl(io.kubernetes.client.openapi.models.V1PodAffinityFluentImpl, int, io.kubernetes.client.openapi.models.V1PodAffinityTerm);
    Code:
       0: aload_0
       1: aload_1
       2: putfield      #1                  // Field this$0:Lio/kubernetes/client/openapi/models/V1PodAffinityFluentImpl;
       5: aload_0
       6: invokespecial #2                  // Method io/kubernetes/client/openapi/models/V1PodAffinityTermFluentImpl."<init>":()V
       9: aload_0
      10: iload_2
      11: putfield      #3                  // Field index:I
      14: aload_0
      15: new           #4                  // class io/kubernetes/client/openapi/models/V1PodAffinityTermBuilder
      18: dup
      19: aload_0
      20: aload_3
      21: invokespecial #5                  // Method io/kubernetes/client/openapi/models/V1PodAffinityTermBuilder."<init>":(Lio/kubernetes/client/openapi/models/V1PodAffinityTermFluent;Lio/kubernetes/client/openapi/models/V1PodAffinityTerm;)V
      24: putfield      #6                  // Field builder:Lio/kubernetes/client/openapi/models/V1PodAffinityTermBuilder;
      27: return

  io.kubernetes.client.openapi.models.V1PodAffinityFluentImpl$RequiredDuringSchedulingIgnoredDuringExecutionNestedImpl(io.kubernetes.client.openapi.models.V1PodAffinityFluentImpl);
    Code:
       0: aload_0
       1: aload_1
       2: putfield      #1                  // Field this$0:Lio/kubernetes/client/openapi/models/V1PodAffinityFluentImpl;
       5: aload_0
       6: invokespecial #2                  // Method io/kubernetes/client/openapi/models/V1PodAffinityTermFluentImpl."<init>":()V
       9: aload_0
      10: iconst_m1
      11: putfield      #3                  // Field index:I
      14: aload_0
      15: new           #4                  // class io/kubernetes/client/openapi/models/V1PodAffinityTermBuilder
      18: dup
      19: aload_0
      20: invokespecial #7                  // Method io/kubernetes/client/openapi/models/V1PodAffinityTermBuilder."<init>":(Lio/kubernetes/client/openapi/models/V1PodAffinityTermFluent;)V
      23: putfield      #6                  // Field builder:Lio/kubernetes/client/openapi/models/V1PodAffinityTermBuilder;
      26: return

  public N and();
    Code:
       0: aload_0
       1: getfield      #1                  // Field this$0:Lio/kubernetes/client/openapi/models/V1PodAffinityFluentImpl;
       4: aload_0
       5: getfield      #3                  // Field index:I
       8: aload_0
       9: getfield      #6                  // Field builder:Lio/kubernetes/client/openapi/models/V1PodAffinityTermBuilder;
      12: invokevirtual #8                  // Method io/kubernetes/client/openapi/models/V1PodAffinityTermBuilder.build:()Lio/kubernetes/client/openapi/models/V1PodAffinityTerm;
      15: invokevirtual #9                  // Method io/kubernetes/client/openapi/models/V1PodAffinityFluentImpl.setToRequiredDuringSchedulingIgnoredDuringExecution:(ILio/kubernetes/client/openapi/models/V1PodAffinityTerm;)Lio/kubernetes/client/openapi/models/V1PodAffinityFluent;
      18: areturn

  public N endRequiredDuringSchedulingIgnoredDuringExecution();
    Code:
       0: aload_0
       1: invokevirtual #10                 // Method and:()Ljava/lang/Object;
       4: areturn
}
