Compiled from "V1QuobyteVolumeSource.java"
public class io.kubernetes.client.openapi.models.V1QuobyteVolumeSource {
  public static final java.lang.String SERIALIZED_NAME_GROUP;

  private java.lang.String group;

  public static final java.lang.String SERIALIZED_NAME_READ_ONLY;

  private java.lang.Boolean readOnly;

  public static final java.lang.String SERIALIZED_NAME_REGISTRY;

  private java.lang.String registry;

  public static final java.lang.String SERIALIZED_NAME_TENANT;

  private java.lang.String tenant;

  public static final java.lang.String SERIALIZED_NAME_USER;

  private java.lang.String user;

  public static final java.lang.String SERIALIZED_NAME_VOLUME;

  private java.lang.String volume;

  public io.kubernetes.client.openapi.models.V1QuobyteVolumeSource();
    Code:
       0: aload_0
       1: invokespecial #1                  // Method java/lang/Object."<init>":()V
       4: return

  public io.kubernetes.client.openapi.models.V1QuobyteVolumeSource group(java.lang.String);
    Code:
       0: aload_0
       1: aload_1
       2: putfield      #2                  // Field group:Ljava/lang/String;
       5: aload_0
       6: areturn

  public java.lang.String getGroup();
    Code:
       0: aload_0
       1: getfield      #2                  // Field group:Ljava/lang/String;
       4: areturn

  public void setGroup(java.lang.String);
    Code:
       0: aload_0
       1: aload_1
       2: putfield      #2                  // Field group:Ljava/lang/String;
       5: return

  public io.kubernetes.client.openapi.models.V1QuobyteVolumeSource readOnly(java.lang.Boolean);
    Code:
       0: aload_0
       1: aload_1
       2: putfield      #3                  // Field readOnly:Ljava/lang/Boolean;
       5: aload_0
       6: areturn

  public java.lang.Boolean getReadOnly();
    Code:
       0: aload_0
       1: getfield      #3                  // Field readOnly:Ljava/lang/Boolean;
       4: areturn

  public void setReadOnly(java.lang.Boolean);
    Code:
       0: aload_0
       1: aload_1
       2: putfield      #3                  // Field readOnly:Ljava/lang/Boolean;
       5: return

  public io.kubernetes.client.openapi.models.V1QuobyteVolumeSource registry(java.lang.String);
    Code:
       0: aload_0
       1: aload_1
       2: putfield      #4                  // Field registry:Ljava/lang/String;
       5: aload_0
       6: areturn

  public java.lang.String getRegistry();
    Code:
       0: aload_0
       1: getfield      #4                  // Field registry:Ljava/lang/String;
       4: areturn

  public void setRegistry(java.lang.String);
    Code:
       0: aload_0
       1: aload_1
       2: putfield      #4                  // Field registry:Ljava/lang/String;
       5: return

  public io.kubernetes.client.openapi.models.V1QuobyteVolumeSource tenant(java.lang.String);
    Code:
       0: aload_0
       1: aload_1
       2: putfield      #5                  // Field tenant:Ljava/lang/String;
       5: aload_0
       6: areturn

  public java.lang.String getTenant();
    Code:
       0: aload_0
       1: getfield      #5                  // Field tenant:Ljava/lang/String;
       4: areturn

  public void setTenant(java.lang.String);
    Code:
       0: aload_0
       1: aload_1
       2: putfield      #5                  // Field tenant:Ljava/lang/String;
       5: return

  public io.kubernetes.client.openapi.models.V1QuobyteVolumeSource user(java.lang.String);
    Code:
       0: aload_0
       1: aload_1
       2: putfield      #6                  // Field user:Ljava/lang/String;
       5: aload_0
       6: areturn

  public java.lang.String getUser();
    Code:
       0: aload_0
       1: getfield      #6                  // Field user:Ljava/lang/String;
       4: areturn

  public void setUser(java.lang.String);
    Code:
       0: aload_0
       1: aload_1
       2: putfield      #6                  // Field user:Ljava/lang/String;
       5: return

  public io.kubernetes.client.openapi.models.V1QuobyteVolumeSource volume(java.lang.String);
    Code:
       0: aload_0
       1: aload_1
       2: putfield      #7                  // Field volume:Ljava/lang/String;
       5: aload_0
       6: areturn

  public java.lang.String getVolume();
    Code:
       0: aload_0
       1: getfield      #7                  // Field volume:Ljava/lang/String;
       4: areturn

  public void setVolume(java.lang.String);
    Code:
       0: aload_0
       1: aload_1
       2: putfield      #7                  // Field volume:Ljava/lang/String;
       5: return

  public boolean equals(java.lang.Object);
    Code:
       0: aload_0
       1: aload_1
       2: if_acmpne     7
       5: iconst_1
       6: ireturn
       7: aload_1
       8: ifnull        22
      11: aload_0
      12: invokevirtual #8                  // Method java/lang/Object.getClass:()Ljava/lang/Class;
      15: aload_1
      16: invokevirtual #8                  // Method java/lang/Object.getClass:()Ljava/lang/Class;
      19: if_acmpeq     24
      22: iconst_0
      23: ireturn
      24: aload_1
      25: checkcast     #9                  // class io/kubernetes/client/openapi/models/V1QuobyteVolumeSource
      28: astore_2
      29: aload_0
      30: getfield      #2                  // Field group:Ljava/lang/String;
      33: aload_2
      34: getfield      #2                  // Field group:Ljava/lang/String;
      37: invokestatic  #10                 // Method java/util/Objects.equals:(Ljava/lang/Object;Ljava/lang/Object;)Z
      40: ifeq          117
      43: aload_0
      44: getfield      #3                  // Field readOnly:Ljava/lang/Boolean;
      47: aload_2
      48: getfield      #3                  // Field readOnly:Ljava/lang/Boolean;
      51: invokestatic  #10                 // Method java/util/Objects.equals:(Ljava/lang/Object;Ljava/lang/Object;)Z
      54: ifeq          117
      57: aload_0
      58: getfield      #4                  // Field registry:Ljava/lang/String;
      61: aload_2
      62: getfield      #4                  // Field registry:Ljava/lang/String;
      65: invokestatic  #10                 // Method java/util/Objects.equals:(Ljava/lang/Object;Ljava/lang/Object;)Z
      68: ifeq          117
      71: aload_0
      72: getfield      #5                  // Field tenant:Ljava/lang/String;
      75: aload_2
      76: getfield      #5                  // Field tenant:Ljava/lang/String;
      79: invokestatic  #10                 // Method java/util/Objects.equals:(Ljava/lang/Object;Ljava/lang/Object;)Z
      82: ifeq          117
      85: aload_0
      86: getfield      #6                  // Field user:Ljava/lang/String;
      89: aload_2
      90: getfield      #6                  // Field user:Ljava/lang/String;
      93: invokestatic  #10                 // Method java/util/Objects.equals:(Ljava/lang/Object;Ljava/lang/Object;)Z
      96: ifeq          117
      99: aload_0
     100: getfield      #7                  // Field volume:Ljava/lang/String;
     103: aload_2
     104: getfield      #7                  // Field volume:Ljava/lang/String;
     107: invokestatic  #10                 // Method java/util/Objects.equals:(Ljava/lang/Object;Ljava/lang/Object;)Z
     110: ifeq          117
     113: iconst_1
     114: goto          118
     117: iconst_0
     118: ireturn

  public int hashCode();
    Code:
       0: bipush        6
       2: anewarray     #11                 // class java/lang/Object
       5: dup
       6: iconst_0
       7: aload_0
       8: getfield      #2                  // Field group:Ljava/lang/String;
      11: aastore
      12: dup
      13: iconst_1
      14: aload_0
      15: getfield      #3                  // Field readOnly:Ljava/lang/Boolean;
      18: aastore
      19: dup
      20: iconst_2
      21: aload_0
      22: getfield      #4                  // Field registry:Ljava/lang/String;
      25: aastore
      26: dup
      27: iconst_3
      28: aload_0
      29: getfield      #5                  // Field tenant:Ljava/lang/String;
      32: aastore
      33: dup
      34: iconst_4
      35: aload_0
      36: getfield      #6                  // Field user:Ljava/lang/String;
      39: aastore
      40: dup
      41: iconst_5
      42: aload_0
      43: getfield      #7                  // Field volume:Ljava/lang/String;
      46: aastore
      47: invokestatic  #12                 // Method java/util/Objects.hash:([Ljava/lang/Object;)I
      50: ireturn

  public java.lang.String toString();
    Code:
       0: new           #13                 // class java/lang/StringBuilder
       3: dup
       4: invokespecial #14                 // Method java/lang/StringBuilder."<init>":()V
       7: astore_1
       8: aload_1
       9: ldc           #15                 // String class V1QuobyteVolumeSource {\n
      11: invokevirtual #16                 // Method java/lang/StringBuilder.append:(Ljava/lang/String;)Ljava/lang/StringBuilder;
      14: pop
      15: aload_1
      16: ldc           #17                 // String     group:
      18: invokevirtual #16                 // Method java/lang/StringBuilder.append:(Ljava/lang/String;)Ljava/lang/StringBuilder;
      21: aload_0
      22: aload_0
      23: getfield      #2                  // Field group:Ljava/lang/String;
      26: invokespecial #18                 // Method toIndentedString:(Ljava/lang/Object;)Ljava/lang/String;
      29: invokevirtual #16                 // Method java/lang/StringBuilder.append:(Ljava/lang/String;)Ljava/lang/StringBuilder;
      32: ldc           #19                 // String \n
      34: invokevirtual #16                 // Method java/lang/StringBuilder.append:(Ljava/lang/String;)Ljava/lang/StringBuilder;
      37: pop
      38: aload_1
      39: ldc           #20                 // String     readOnly:
      41: invokevirtual #16                 // Method java/lang/StringBuilder.append:(Ljava/lang/String;)Ljava/lang/StringBuilder;
      44: aload_0
      45: aload_0
      46: getfield      #3                  // Field readOnly:Ljava/lang/Boolean;
      49: invokespecial #18                 // Method toIndentedString:(Ljava/lang/Object;)Ljava/lang/String;
      52: invokevirtual #16                 // Method java/lang/StringBuilder.append:(Ljava/lang/String;)Ljava/lang/StringBuilder;
      55: ldc           #19                 // String \n
      57: invokevirtual #16                 // Method java/lang/StringBuilder.append:(Ljava/lang/String;)Ljava/lang/StringBuilder;
      60: pop
      61: aload_1
      62: ldc           #21                 // String     registry:
      64: invokevirtual #16                 // Method java/lang/StringBuilder.append:(Ljava/lang/String;)Ljava/lang/StringBuilder;
      67: aload_0
      68: aload_0
      69: getfield      #4                  // Field registry:Ljava/lang/String;
      72: invokespecial #18                 // Method toIndentedString:(Ljava/lang/Object;)Ljava/lang/String;
      75: invokevirtual #16                 // Method java/lang/StringBuilder.append:(Ljava/lang/String;)Ljava/lang/StringBuilder;
      78: ldc           #19                 // String \n
      80: invokevirtual #16                 // Method java/lang/StringBuilder.append:(Ljava/lang/String;)Ljava/lang/StringBuilder;
      83: pop
      84: aload_1
      85: ldc           #22                 // String     tenant:
      87: invokevirtual #16                 // Method java/lang/StringBuilder.append:(Ljava/lang/String;)Ljava/lang/StringBuilder;
      90: aload_0
      91: aload_0
      92: getfield      #5                  // Field tenant:Ljava/lang/String;
      95: invokespecial #18                 // Method toIndentedString:(Ljava/lang/Object;)Ljava/lang/String;
      98: invokevirtual #16                 // Method java/lang/StringBuilder.append:(Ljava/lang/String;)Ljava/lang/StringBuilder;
     101: ldc           #19                 // String \n
     103: invokevirtual #16                 // Method java/lang/StringBuilder.append:(Ljava/lang/String;)Ljava/lang/StringBuilder;
     106: pop
     107: aload_1
     108: ldc           #23                 // String     user:
     110: invokevirtual #16                 // Method java/lang/StringBuilder.append:(Ljava/lang/String;)Ljava/lang/StringBuilder;
     113: aload_0
     114: aload_0
     115: getfield      #6                  // Field user:Ljava/lang/String;
     118: invokespecial #18                 // Method toIndentedString:(Ljava/lang/Object;)Ljava/lang/String;
     121: invokevirtual #16                 // Method java/lang/StringBuilder.append:(Ljava/lang/String;)Ljava/lang/StringBuilder;
     124: ldc           #19                 // String \n
     126: invokevirtual #16                 // Method java/lang/StringBuilder.append:(Ljava/lang/String;)Ljava/lang/StringBuilder;
     129: pop
     130: aload_1
     131: ldc           #24                 // String     volume:
     133: invokevirtual #16                 // Method java/lang/StringBuilder.append:(Ljava/lang/String;)Ljava/lang/StringBuilder;
     136: aload_0
     137: aload_0
     138: getfield      #7                  // Field volume:Ljava/lang/String;
     141: invokespecial #18                 // Method toIndentedString:(Ljava/lang/Object;)Ljava/lang/String;
     144: invokevirtual #16                 // Method java/lang/StringBuilder.append:(Ljava/lang/String;)Ljava/lang/StringBuilder;
     147: ldc           #19                 // String \n
     149: invokevirtual #16                 // Method java/lang/StringBuilder.append:(Ljava/lang/String;)Ljava/lang/StringBuilder;
     152: pop
     153: aload_1
     154: ldc           #25                 // String }
     156: invokevirtual #16                 // Method java/lang/StringBuilder.append:(Ljava/lang/String;)Ljava/lang/StringBuilder;
     159: pop
     160: aload_1
     161: invokevirtual #26                 // Method java/lang/StringBuilder.toString:()Ljava/lang/String;
     164: areturn

  private java.lang.String toIndentedString(java.lang.Object);
    Code:
       0: aload_1
       1: ifnonnull     7
       4: ldc           #27                 // String null
       6: areturn
       7: aload_1
       8: invokevirtual #28                 // Method java/lang/Object.toString:()Ljava/lang/String;
      11: ldc           #19                 // String \n
      13: ldc           #29                 // String \n
      15: invokevirtual #30                 // Method java/lang/String.replace:(Ljava/lang/CharSequence;Ljava/lang/CharSequence;)Ljava/lang/String;
      18: areturn
}
