Compiled from "V1RoleListFluentImpl.java"
public class io.kubernetes.client.openapi.models.V1RoleListFluentImpl$ItemsNestedImpl<N> extends io.kubernetes.client.openapi.models.V1RoleFluentImpl<io.kubernetes.client.openapi.models.V1RoleListFluent$ItemsNested<N>> implements io.kubernetes.client.openapi.models.V1RoleListFluent$ItemsNested<N>, io.kubernetes.client.fluent.Nested<N> {
  private final io.kubernetes.client.openapi.models.V1RoleBuilder builder;

  private final int index;

  final io.kubernetes.client.openapi.models.V1RoleListFluentImpl this$0;

  io.kubernetes.client.openapi.models.V1RoleListFluentImpl$ItemsNestedImpl(io.kubernetes.client.openapi.models.V1RoleListFluentImpl, int, io.kubernetes.client.openapi.models.V1Role);
    Code:
       0: aload_0
       1: aload_1
       2: putfield      #1                  // Field this$0:Lio/kubernetes/client/openapi/models/V1RoleListFluentImpl;
       5: aload_0
       6: invokespecial #2                  // Method io/kubernetes/client/openapi/models/V1RoleFluentImpl."<init>":()V
       9: aload_0
      10: iload_2
      11: putfield      #3                  // Field index:I
      14: aload_0
      15: new           #4                  // class io/kubernetes/client/openapi/models/V1RoleBuilder
      18: dup
      19: aload_0
      20: aload_3
      21: invokespecial #5                  // Method io/kubernetes/client/openapi/models/V1RoleBuilder."<init>":(Lio/kubernetes/client/openapi/models/V1RoleFluent;Lio/kubernetes/client/openapi/models/V1Role;)V
      24: putfield      #6                  // Field builder:Lio/kubernetes/client/openapi/models/V1RoleBuilder;
      27: return

  io.kubernetes.client.openapi.models.V1RoleListFluentImpl$ItemsNestedImpl(io.kubernetes.client.openapi.models.V1RoleListFluentImpl);
    Code:
       0: aload_0
       1: aload_1
       2: putfield      #1                  // Field this$0:Lio/kubernetes/client/openapi/models/V1RoleListFluentImpl;
       5: aload_0
       6: invokespecial #2                  // Method io/kubernetes/client/openapi/models/V1RoleFluentImpl."<init>":()V
       9: aload_0
      10: iconst_m1
      11: putfield      #3                  // Field index:I
      14: aload_0
      15: new           #4                  // class io/kubernetes/client/openapi/models/V1RoleBuilder
      18: dup
      19: aload_0
      20: invokespecial #7                  // Method io/kubernetes/client/openapi/models/V1RoleBuilder."<init>":(Lio/kubernetes/client/openapi/models/V1RoleFluent;)V
      23: putfield      #6                  // Field builder:Lio/kubernetes/client/openapi/models/V1RoleBuilder;
      26: return

  public N and();
    Code:
       0: aload_0
       1: getfield      #1                  // Field this$0:Lio/kubernetes/client/openapi/models/V1RoleListFluentImpl;
       4: aload_0
       5: getfield      #3                  // Field index:I
       8: aload_0
       9: getfield      #6                  // Field builder:Lio/kubernetes/client/openapi/models/V1RoleBuilder;
      12: invokevirtual #8                  // Method io/kubernetes/client/openapi/models/V1RoleBuilder.build:()Lio/kubernetes/client/openapi/models/V1Role;
      15: invokevirtual #9                  // Method io/kubernetes/client/openapi/models/V1RoleListFluentImpl.setToItems:(ILio/kubernetes/client/openapi/models/V1Role;)Lio/kubernetes/client/openapi/models/V1RoleListFluent;
      18: areturn

  public N endItem();
    Code:
       0: aload_0
       1: invokevirtual #10                 // Method and:()Ljava/lang/Object;
       4: areturn
}
