Compiled from "V1RuntimeClassListFluentImpl.java"
public class io.kubernetes.client.openapi.models.V1RuntimeClassListFluentImpl$ItemsNestedImpl<N> extends io.kubernetes.client.openapi.models.V1RuntimeClassFluentImpl<io.kubernetes.client.openapi.models.V1RuntimeClassListFluent$ItemsNested<N>> implements io.kubernetes.client.openapi.models.V1RuntimeClassListFluent$ItemsNested<N>, io.kubernetes.client.fluent.Nested<N> {
  private final io.kubernetes.client.openapi.models.V1RuntimeClassBuilder builder;

  private final int index;

  final io.kubernetes.client.openapi.models.V1RuntimeClassListFluentImpl this$0;

  io.kubernetes.client.openapi.models.V1RuntimeClassListFluentImpl$ItemsNestedImpl(io.kubernetes.client.openapi.models.V1RuntimeClassListFluentImpl, int, io.kubernetes.client.openapi.models.V1RuntimeClass);
    Code:
       0: aload_0
       1: aload_1
       2: putfield      #1                  // Field this$0:Lio/kubernetes/client/openapi/models/V1RuntimeClassListFluentImpl;
       5: aload_0
       6: invokespecial #2                  // Method io/kubernetes/client/openapi/models/V1RuntimeClassFluentImpl."<init>":()V
       9: aload_0
      10: iload_2
      11: putfield      #3                  // Field index:I
      14: aload_0
      15: new           #4                  // class io/kubernetes/client/openapi/models/V1RuntimeClassBuilder
      18: dup
      19: aload_0
      20: aload_3
      21: invokespecial #5                  // Method io/kubernetes/client/openapi/models/V1RuntimeClassBuilder."<init>":(Lio/kubernetes/client/openapi/models/V1RuntimeClassFluent;Lio/kubernetes/client/openapi/models/V1RuntimeClass;)V
      24: putfield      #6                  // Field builder:Lio/kubernetes/client/openapi/models/V1RuntimeClassBuilder;
      27: return

  io.kubernetes.client.openapi.models.V1RuntimeClassListFluentImpl$ItemsNestedImpl(io.kubernetes.client.openapi.models.V1RuntimeClassListFluentImpl);
    Code:
       0: aload_0
       1: aload_1
       2: putfield      #1                  // Field this$0:Lio/kubernetes/client/openapi/models/V1RuntimeClassListFluentImpl;
       5: aload_0
       6: invokespecial #2                  // Method io/kubernetes/client/openapi/models/V1RuntimeClassFluentImpl."<init>":()V
       9: aload_0
      10: iconst_m1
      11: putfield      #3                  // Field index:I
      14: aload_0
      15: new           #4                  // class io/kubernetes/client/openapi/models/V1RuntimeClassBuilder
      18: dup
      19: aload_0
      20: invokespecial #7                  // Method io/kubernetes/client/openapi/models/V1RuntimeClassBuilder."<init>":(Lio/kubernetes/client/openapi/models/V1RuntimeClassFluent;)V
      23: putfield      #6                  // Field builder:Lio/kubernetes/client/openapi/models/V1RuntimeClassBuilder;
      26: return

  public N and();
    Code:
       0: aload_0
       1: getfield      #1                  // Field this$0:Lio/kubernetes/client/openapi/models/V1RuntimeClassListFluentImpl;
       4: aload_0
       5: getfield      #3                  // Field index:I
       8: aload_0
       9: getfield      #6                  // Field builder:Lio/kubernetes/client/openapi/models/V1RuntimeClassBuilder;
      12: invokevirtual #8                  // Method io/kubernetes/client/openapi/models/V1RuntimeClassBuilder.build:()Lio/kubernetes/client/openapi/models/V1RuntimeClass;
      15: invokevirtual #9                  // Method io/kubernetes/client/openapi/models/V1RuntimeClassListFluentImpl.setToItems:(ILio/kubernetes/client/openapi/models/V1RuntimeClass;)Lio/kubernetes/client/openapi/models/V1RuntimeClassListFluent;
      18: areturn

  public N endItem();
    Code:
       0: aload_0
       1: invokevirtual #10                 // Method and:()Ljava/lang/Object;
       4: areturn
}
