Compiled from "V2beta2HPAScalingPolicyFluentImpl.java"
public class io.kubernetes.client.openapi.models.V2beta2HPAScalingPolicyFluentImpl<A extends io.kubernetes.client.openapi.models.V2beta2HPAScalingPolicyFluent<A>> extends io.kubernetes.client.fluent.BaseFluent<A> implements io.kubernetes.client.openapi.models.V2beta2HPAScalingPolicyFluent<A> {
  private java.lang.Integer periodSeconds;

  private java.lang.String type;

  private java.lang.Integer value;

  public io.kubernetes.client.openapi.models.V2beta2HPAScalingPolicyFluentImpl();
    Code:
       0: aload_0
       1: invokespecial #1                  // Method io/kubernetes/client/fluent/BaseFluent."<init>":()V
       4: return

  public io.kubernetes.client.openapi.models.V2beta2HPAScalingPolicyFluentImpl(io.kubernetes.client.openapi.models.V2beta2HPAScalingPolicy);
    Code:
       0: aload_0
       1: invokespecial #1                  // Method io/kubernetes/client/fluent/BaseFluent."<init>":()V
       4: aload_0
       5: aload_1
       6: invokevirtual #2                  // Method io/kubernetes/client/openapi/models/V2beta2HPAScalingPolicy.getPeriodSeconds:()Ljava/lang/Integer;
       9: invokevirtual #3                  // Method withPeriodSeconds:(Ljava/lang/Integer;)Lio/kubernetes/client/openapi/models/V2beta2HPAScalingPolicyFluent;
      12: pop
      13: aload_0
      14: aload_1
      15: invokevirtual #4                  // Method io/kubernetes/client/openapi/models/V2beta2HPAScalingPolicy.getType:()Ljava/lang/String;
      18: invokevirtual #5                  // Method withType:(Ljava/lang/String;)Lio/kubernetes/client/openapi/models/V2beta2HPAScalingPolicyFluent;
      21: pop
      22: aload_0
      23: aload_1
      24: invokevirtual #6                  // Method io/kubernetes/client/openapi/models/V2beta2HPAScalingPolicy.getValue:()Ljava/lang/Integer;
      27: invokevirtual #7                  // Method withValue:(Ljava/lang/Integer;)Lio/kubernetes/client/openapi/models/V2beta2HPAScalingPolicyFluent;
      30: pop
      31: return

  public java.lang.Integer getPeriodSeconds();
    Code:
       0: aload_0
       1: getfield      #8                  // Field periodSeconds:Ljava/lang/Integer;
       4: areturn

  public A withPeriodSeconds(java.lang.Integer);
    Code:
       0: aload_0
       1: aload_1
       2: putfield      #8                  // Field periodSeconds:Ljava/lang/Integer;
       5: aload_0
       6: areturn

  public java.lang.Boolean hasPeriodSeconds();
    Code:
       0: aload_0
       1: getfield      #8                  // Field periodSeconds:Ljava/lang/Integer;
       4: ifnull        11
       7: iconst_1
       8: goto          12
      11: iconst_0
      12: invokestatic  #9                  // Method java/lang/Boolean.valueOf:(Z)Ljava/lang/Boolean;
      15: areturn

  public java.lang.String getType();
    Code:
       0: aload_0
       1: getfield      #10                 // Field type:Ljava/lang/String;
       4: areturn

  public A withType(java.lang.String);
    Code:
       0: aload_0
       1: aload_1
       2: putfield      #10                 // Field type:Ljava/lang/String;
       5: aload_0
       6: areturn

  public java.lang.Boolean hasType();
    Code:
       0: aload_0
       1: getfield      #10                 // Field type:Ljava/lang/String;
       4: ifnull        11
       7: iconst_1
       8: goto          12
      11: iconst_0
      12: invokestatic  #9                  // Method java/lang/Boolean.valueOf:(Z)Ljava/lang/Boolean;
      15: areturn

  public A withNewType(java.lang.String);
    Code:
       0: aload_0
       1: new           #11                 // class java/lang/String
       4: dup
       5: aload_1
       6: invokespecial #12                 // Method java/lang/String."<init>":(Ljava/lang/String;)V
       9: invokevirtual #5                  // Method withType:(Ljava/lang/String;)Lio/kubernetes/client/openapi/models/V2beta2HPAScalingPolicyFluent;
      12: areturn

  public A withNewType(java.lang.StringBuilder);
    Code:
       0: aload_0
       1: new           #11                 // class java/lang/String
       4: dup
       5: aload_1
       6: invokespecial #13                 // Method java/lang/String."<init>":(Ljava/lang/StringBuilder;)V
       9: invokevirtual #5                  // Method withType:(Ljava/lang/String;)Lio/kubernetes/client/openapi/models/V2beta2HPAScalingPolicyFluent;
      12: areturn

  public A withNewType(java.lang.StringBuffer);
    Code:
       0: aload_0
       1: new           #11                 // class java/lang/String
       4: dup
       5: aload_1
       6: invokespecial #14                 // Method java/lang/String."<init>":(Ljava/lang/StringBuffer;)V
       9: invokevirtual #5                  // Method withType:(Ljava/lang/String;)Lio/kubernetes/client/openapi/models/V2beta2HPAScalingPolicyFluent;
      12: areturn

  public java.lang.Integer getValue();
    Code:
       0: aload_0
       1: getfield      #15                 // Field value:Ljava/lang/Integer;
       4: areturn

  public A withValue(java.lang.Integer);
    Code:
       0: aload_0
       1: aload_1
       2: putfield      #15                 // Field value:Ljava/lang/Integer;
       5: aload_0
       6: areturn

  public java.lang.Boolean hasValue();
    Code:
       0: aload_0
       1: getfield      #15                 // Field value:Ljava/lang/Integer;
       4: ifnull        11
       7: iconst_1
       8: goto          12
      11: iconst_0
      12: invokestatic  #9                  // Method java/lang/Boolean.valueOf:(Z)Ljava/lang/Boolean;
      15: areturn

  public boolean equals(java.lang.Object);
    Code:
       0: aload_0
       1: aload_1
       2: if_acmpne     7
       5: iconst_1
       6: ireturn
       7: aload_1
       8: ifnull        22
      11: aload_0
      12: invokevirtual #16                 // Method java/lang/Object.getClass:()Ljava/lang/Class;
      15: aload_1
      16: invokevirtual #16                 // Method java/lang/Object.getClass:()Ljava/lang/Class;
      19: if_acmpeq     24
      22: iconst_0
      23: ireturn
      24: aload_1
      25: checkcast     #17                 // class io/kubernetes/client/openapi/models/V2beta2HPAScalingPolicyFluentImpl
      28: astore_2
      29: aload_0
      30: getfield      #8                  // Field periodSeconds:Ljava/lang/Integer;
      33: ifnull        53
      36: aload_0
      37: getfield      #8                  // Field periodSeconds:Ljava/lang/Integer;
      40: aload_2
      41: getfield      #8                  // Field periodSeconds:Ljava/lang/Integer;
      44: invokevirtual #18                 // Method java/lang/Integer.equals:(Ljava/lang/Object;)Z
      47: ifne          62
      50: goto          60
      53: aload_2
      54: getfield      #8                  // Field periodSeconds:Ljava/lang/Integer;
      57: ifnull        62
      60: iconst_0
      61: ireturn
      62: aload_0
      63: getfield      #10                 // Field type:Ljava/lang/String;
      66: ifnull        86
      69: aload_0
      70: getfield      #10                 // Field type:Ljava/lang/String;
      73: aload_2
      74: getfield      #10                 // Field type:Ljava/lang/String;
      77: invokevirtual #19                 // Method java/lang/String.equals:(Ljava/lang/Object;)Z
      80: ifne          95
      83: goto          93
      86: aload_2
      87: getfield      #10                 // Field type:Ljava/lang/String;
      90: ifnull        95
      93: iconst_0
      94: ireturn
      95: aload_0
      96: getfield      #15                 // Field value:Ljava/lang/Integer;
      99: ifnull        119
     102: aload_0
     103: getfield      #15                 // Field value:Ljava/lang/Integer;
     106: aload_2
     107: getfield      #15                 // Field value:Ljava/lang/Integer;
     110: invokevirtual #18                 // Method java/lang/Integer.equals:(Ljava/lang/Object;)Z
     113: ifne          128
     116: goto          126
     119: aload_2
     120: getfield      #15                 // Field value:Ljava/lang/Integer;
     123: ifnull        128
     126: iconst_0
     127: ireturn
     128: iconst_1
     129: ireturn

  public int hashCode();
    Code:
       0: iconst_4
       1: anewarray     #20                 // class java/lang/Object
       4: dup
       5: iconst_0
       6: aload_0
       7: getfield      #8                  // Field periodSeconds:Ljava/lang/Integer;
      10: aastore
      11: dup
      12: iconst_1
      13: aload_0
      14: getfield      #10                 // Field type:Ljava/lang/String;
      17: aastore
      18: dup
      19: iconst_2
      20: aload_0
      21: getfield      #15                 // Field value:Ljava/lang/Integer;
      24: aastore
      25: dup
      26: iconst_3
      27: aload_0
      28: invokespecial #21                 // Method java/lang/Object.hashCode:()I
      31: invokestatic  #22                 // Method java/lang/Integer.valueOf:(I)Ljava/lang/Integer;
      34: aastore
      35: invokestatic  #23                 // Method java/util/Objects.hash:([Ljava/lang/Object;)I
      38: ireturn
}
