Compiled from "V2beta2HorizontalPodAutoscalerBehaviorFluentImpl.java"
public class io.kubernetes.client.openapi.models.V2beta2HorizontalPodAutoscalerBehaviorFluentImpl$ScaleDownNestedImpl<N> extends io.kubernetes.client.openapi.models.V2beta2HPAScalingRulesFluentImpl<io.kubernetes.client.openapi.models.V2beta2HorizontalPodAutoscalerBehaviorFluent$ScaleDownNested<N>> implements io.kubernetes.client.openapi.models.V2beta2HorizontalPodAutoscalerBehaviorFluent$ScaleDownNested<N>, io.kubernetes.client.fluent.Nested<N> {
  private final io.kubernetes.client.openapi.models.V2beta2HPAScalingRulesBuilder builder;

  final io.kubernetes.client.openapi.models.V2beta2HorizontalPodAutoscalerBehaviorFluentImpl this$0;

  io.kubernetes.client.openapi.models.V2beta2HorizontalPodAutoscalerBehaviorFluentImpl$ScaleDownNestedImpl(io.kubernetes.client.openapi.models.V2beta2HorizontalPodAutoscalerBehaviorFluentImpl, io.kubernetes.client.openapi.models.V2beta2HPAScalingRules);
    Code:
       0: aload_0
       1: aload_1
       2: putfield      #1                  // Field this$0:Lio/kubernetes/client/openapi/models/V2beta2HorizontalPodAutoscalerBehaviorFluentImpl;
       5: aload_0
       6: invokespecial #2                  // Method io/kubernetes/client/openapi/models/V2beta2HPAScalingRulesFluentImpl."<init>":()V
       9: aload_0
      10: new           #3                  // class io/kubernetes/client/openapi/models/V2beta2HPAScalingRulesBuilder
      13: dup
      14: aload_0
      15: aload_2
      16: invokespecial #4                  // Method io/kubernetes/client/openapi/models/V2beta2HPAScalingRulesBuilder."<init>":(Lio/kubernetes/client/openapi/models/V2beta2HPAScalingRulesFluent;Lio/kubernetes/client/openapi/models/V2beta2HPAScalingRules;)V
      19: putfield      #5                  // Field builder:Lio/kubernetes/client/openapi/models/V2beta2HPAScalingRulesBuilder;
      22: return

  io.kubernetes.client.openapi.models.V2beta2HorizontalPodAutoscalerBehaviorFluentImpl$ScaleDownNestedImpl(io.kubernetes.client.openapi.models.V2beta2HorizontalPodAutoscalerBehaviorFluentImpl);
    Code:
       0: aload_0
       1: aload_1
       2: putfield      #1                  // Field this$0:Lio/kubernetes/client/openapi/models/V2beta2HorizontalPodAutoscalerBehaviorFluentImpl;
       5: aload_0
       6: invokespecial #2                  // Method io/kubernetes/client/openapi/models/V2beta2HPAScalingRulesFluentImpl."<init>":()V
       9: aload_0
      10: new           #3                  // class io/kubernetes/client/openapi/models/V2beta2HPAScalingRulesBuilder
      13: dup
      14: aload_0
      15: invokespecial #6                  // Method io/kubernetes/client/openapi/models/V2beta2HPAScalingRulesBuilder."<init>":(Lio/kubernetes/client/openapi/models/V2beta2HPAScalingRulesFluent;)V
      18: putfield      #5                  // Field builder:Lio/kubernetes/client/openapi/models/V2beta2HPAScalingRulesBuilder;
      21: return

  public N and();
    Code:
       0: aload_0
       1: getfield      #1                  // Field this$0:Lio/kubernetes/client/openapi/models/V2beta2HorizontalPodAutoscalerBehaviorFluentImpl;
       4: aload_0
       5: getfield      #5                  // Field builder:Lio/kubernetes/client/openapi/models/V2beta2HPAScalingRulesBuilder;
       8: invokevirtual #7                  // Method io/kubernetes/client/openapi/models/V2beta2HPAScalingRulesBuilder.build:()Lio/kubernetes/client/openapi/models/V2beta2HPAScalingRules;
      11: invokevirtual #8                  // Method io/kubernetes/client/openapi/models/V2beta2HorizontalPodAutoscalerBehaviorFluentImpl.withScaleDown:(Lio/kubernetes/client/openapi/models/V2beta2HPAScalingRules;)Lio/kubernetes/client/openapi/models/V2beta2HorizontalPodAutoscalerBehaviorFluent;
      14: areturn

  public N endScaleDown();
    Code:
       0: aload_0
       1: invokevirtual #9                  // Method and:()Ljava/lang/Object;
       4: areturn
}
