Compiled from "V2beta2MetricStatusFluentImpl.java"
public class io.kubernetes.client.openapi.models.V2beta2MetricStatusFluentImpl$PodsNestedImpl<N> extends io.kubernetes.client.openapi.models.V2beta2PodsMetricStatusFluentImpl<io.kubernetes.client.openapi.models.V2beta2MetricStatusFluent$PodsNested<N>> implements io.kubernetes.client.openapi.models.V2beta2MetricStatusFluent$PodsNested<N>, io.kubernetes.client.fluent.Nested<N> {
  private final io.kubernetes.client.openapi.models.V2beta2PodsMetricStatusBuilder builder;

  final io.kubernetes.client.openapi.models.V2beta2MetricStatusFluentImpl this$0;

  io.kubernetes.client.openapi.models.V2beta2MetricStatusFluentImpl$PodsNestedImpl(io.kubernetes.client.openapi.models.V2beta2MetricStatusFluentImpl, io.kubernetes.client.openapi.models.V2beta2PodsMetricStatus);
    Code:
       0: aload_0
       1: aload_1
       2: putfield      #1                  // Field this$0:Lio/kubernetes/client/openapi/models/V2beta2MetricStatusFluentImpl;
       5: aload_0
       6: invokespecial #2                  // Method io/kubernetes/client/openapi/models/V2beta2PodsMetricStatusFluentImpl."<init>":()V
       9: aload_0
      10: new           #3                  // class io/kubernetes/client/openapi/models/V2beta2PodsMetricStatusBuilder
      13: dup
      14: aload_0
      15: aload_2
      16: invokespecial #4                  // Method io/kubernetes/client/openapi/models/V2beta2PodsMetricStatusBuilder."<init>":(Lio/kubernetes/client/openapi/models/V2beta2PodsMetricStatusFluent;Lio/kubernetes/client/openapi/models/V2beta2PodsMetricStatus;)V
      19: putfield      #5                  // Field builder:Lio/kubernetes/client/openapi/models/V2beta2PodsMetricStatusBuilder;
      22: return

  io.kubernetes.client.openapi.models.V2beta2MetricStatusFluentImpl$PodsNestedImpl(io.kubernetes.client.openapi.models.V2beta2MetricStatusFluentImpl);
    Code:
       0: aload_0
       1: aload_1
       2: putfield      #1                  // Field this$0:Lio/kubernetes/client/openapi/models/V2beta2MetricStatusFluentImpl;
       5: aload_0
       6: invokespecial #2                  // Method io/kubernetes/client/openapi/models/V2beta2PodsMetricStatusFluentImpl."<init>":()V
       9: aload_0
      10: new           #3                  // class io/kubernetes/client/openapi/models/V2beta2PodsMetricStatusBuilder
      13: dup
      14: aload_0
      15: invokespecial #6                  // Method io/kubernetes/client/openapi/models/V2beta2PodsMetricStatusBuilder."<init>":(Lio/kubernetes/client/openapi/models/V2beta2PodsMetricStatusFluent;)V
      18: putfield      #5                  // Field builder:Lio/kubernetes/client/openapi/models/V2beta2PodsMetricStatusBuilder;
      21: return

  public N and();
    Code:
       0: aload_0
       1: getfield      #1                  // Field this$0:Lio/kubernetes/client/openapi/models/V2beta2MetricStatusFluentImpl;
       4: aload_0
       5: getfield      #5                  // Field builder:Lio/kubernetes/client/openapi/models/V2beta2PodsMetricStatusBuilder;
       8: invokevirtual #7                  // Method io/kubernetes/client/openapi/models/V2beta2PodsMetricStatusBuilder.build:()Lio/kubernetes/client/openapi/models/V2beta2PodsMetricStatus;
      11: invokevirtual #8                  // Method io/kubernetes/client/openapi/models/V2beta2MetricStatusFluentImpl.withPods:(Lio/kubernetes/client/openapi/models/V2beta2PodsMetricStatus;)Lio/kubernetes/client/openapi/models/V2beta2MetricStatusFluent;
      14: areturn

  public N endPods();
    Code:
       0: aload_0
       1: invokevirtual #9                  // Method and:()Ljava/lang/Object;
       4: areturn
}
