Compiled from "SSLContextBuilder.scala"
public final class com.typesafe.sslconfig.ssl.ConfigSSLContextBuilder$$anonfun$validateStoreContainsPrivateKeys$1 extends scala.runtime.AbstractFunction1<java.lang.String, scala.runtime.BoxedUnit> implements scala.Serializable {
  public static final long serialVersionUID;

  private final com.typesafe.sslconfig.ssl.ConfigSSLContextBuilder $outer;

  private final java.security.KeyStore keyStore$1;

  private final char[] password$2;

  private final scala.runtime.BooleanRef containsPrivateKeys$1;

  public final void apply(java.lang.String);
    Code:
       0: aload_0
       1: getfield      #29                 // Field keyStore$1:Ljava/security/KeyStore;
       4: aload_1
       5: aload_0
       6: getfield      #31                 // Field password$2:[C
       9: invokevirtual #37                 // Method java/security/KeyStore.getKey:(Ljava/lang/String;[C)Ljava/security/Key;
      12: astore_2
      13: aload_2
      14: astore_3
      15: aload_3
      16: instanceof    #39                 // class java/security/PrivateKey
      19: ifeq          95
      22: aload_0
      23: getfield      #41                 // Field $outer:Lcom/typesafe/sslconfig/ssl/ConfigSSLContextBuilder;
      26: invokevirtual #45                 // Method com/typesafe/sslconfig/ssl/ConfigSSLContextBuilder.logger:()Lcom/typesafe/sslconfig/util/NoDepsLogger;
      29: new           #47                 // class scala/StringContext
      32: dup
      33: getstatic     #53                 // Field scala/Predef$.MODULE$:Lscala/Predef$;
      36: iconst_2
      37: anewarray     #55                 // class java/lang/String
      40: dup
      41: iconst_0
      42: ldc           #57                 // String validateStoreContainsPrivateKeys: private key found for alias
      44: aastore
      45: dup
      46: iconst_1
      47: ldc           #59                 // String
      49: aastore
      50: checkcast     #61                 // class "[Ljava/lang/Object;"
      53: invokevirtual #65                 // Method scala/Predef$.wrapRefArray:([Ljava/lang/Object;)Lscala/collection/mutable/WrappedArray;
      56: invokespecial #69                 // Method scala/StringContext."<init>":(Lscala/collection/Seq;)V
      59: getstatic     #53                 // Field scala/Predef$.MODULE$:Lscala/Predef$;
      62: iconst_1
      63: anewarray     #71                 // class java/lang/Object
      66: dup
      67: iconst_0
      68: aload_1
      69: aastore
      70: invokevirtual #75                 // Method scala/Predef$.genericWrapArray:(Ljava/lang/Object;)Lscala/collection/mutable/WrappedArray;
      73: invokevirtual #79                 // Method scala/StringContext.s:(Lscala/collection/Seq;)Ljava/lang/String;
      76: invokevirtual #84                 // Method com/typesafe/sslconfig/util/NoDepsLogger.debug:(Ljava/lang/String;)V
      79: aload_0
      80: getfield      #86                 // Field containsPrivateKeys$1:Lscala/runtime/BooleanRef;
      83: iconst_1
      84: putfield      #92                 // Field scala/runtime/BooleanRef.elem:Z
      87: getstatic     #98                 // Field scala/runtime/BoxedUnit.UNIT:Lscala/runtime/BoxedUnit;
      90: astore        4
      92: goto          161
      95: new           #47                 // class scala/StringContext
      98: dup
      99: getstatic     #53                 // Field scala/Predef$.MODULE$:Lscala/Predef$;
     102: iconst_2
     103: anewarray     #55                 // class java/lang/String
     106: dup
     107: iconst_0
     108: ldc           #100                // String validateStoreContainsPrivateKeys: No private key found for alias
     110: aastore
     111: dup
     112: iconst_1
     113: ldc           #102                // String , it cannot be used for client authentication
     115: aastore
     116: checkcast     #61                 // class "[Ljava/lang/Object;"
     119: invokevirtual #65                 // Method scala/Predef$.wrapRefArray:([Ljava/lang/Object;)Lscala/collection/mutable/WrappedArray;
     122: invokespecial #69                 // Method scala/StringContext."<init>":(Lscala/collection/Seq;)V
     125: getstatic     #53                 // Field scala/Predef$.MODULE$:Lscala/Predef$;
     128: iconst_1
     129: anewarray     #71                 // class java/lang/Object
     132: dup
     133: iconst_0
     134: aload_1
     135: aastore
     136: invokevirtual #75                 // Method scala/Predef$.genericWrapArray:(Ljava/lang/Object;)Lscala/collection/mutable/WrappedArray;
     139: invokevirtual #79                 // Method scala/StringContext.s:(Lscala/collection/Seq;)Ljava/lang/String;
     142: astore        5
     144: aload_0
     145: getfield      #41                 // Field $outer:Lcom/typesafe/sslconfig/ssl/ConfigSSLContextBuilder;
     148: invokevirtual #45                 // Method com/typesafe/sslconfig/ssl/ConfigSSLContextBuilder.logger:()Lcom/typesafe/sslconfig/util/NoDepsLogger;
     151: aload         5
     153: invokevirtual #105                // Method com/typesafe/sslconfig/util/NoDepsLogger.warn:(Ljava/lang/String;)V
     156: getstatic     #98                 // Field scala/runtime/BoxedUnit.UNIT:Lscala/runtime/BoxedUnit;
     159: astore        4
     161: return

  public final java.lang.Object apply(java.lang.Object);
    Code:
       0: aload_0
       1: aload_1
       2: checkcast     #55                 // class java/lang/String
       5: invokevirtual #117                // Method apply:(Ljava/lang/String;)V
       8: getstatic     #98                 // Field scala/runtime/BoxedUnit.UNIT:Lscala/runtime/BoxedUnit;
      11: areturn

  public com.typesafe.sslconfig.ssl.ConfigSSLContextBuilder$$anonfun$validateStoreContainsPrivateKeys$1(com.typesafe.sslconfig.ssl.ConfigSSLContextBuilder, java.security.KeyStore, char[], scala.runtime.BooleanRef);
    Code:
       0: aload_1
       1: ifnonnull     6
       4: aconst_null
       5: athrow
       6: aload_0
       7: aload_1
       8: putfield      #41                 // Field $outer:Lcom/typesafe/sslconfig/ssl/ConfigSSLContextBuilder;
      11: aload_0
      12: aload_2
      13: putfield      #29                 // Field keyStore$1:Ljava/security/KeyStore;
      16: aload_0
      17: aload_3
      18: putfield      #31                 // Field password$2:[C
      21: aload_0
      22: aload         4
      24: putfield      #86                 // Field containsPrivateKeys$1:Lscala/runtime/BooleanRef;
      27: aload_0
      28: invokespecial #123                // Method scala/runtime/AbstractFunction1."<init>":()V
      31: return
}
