Compiled from "SSLContextBuilder.scala"
public final class com.typesafe.sslconfig.ssl.ConfigSSLContextBuilder$$anonfun$keyStoreBuilder$2 extends scala.runtime.AbstractFunction0<com.typesafe.sslconfig.ssl.KeyStoreBuilder> implements scala.Serializable {
  public static final long serialVersionUID;

  private final com.typesafe.sslconfig.ssl.ConfigSSLContextBuilder $outer;

  private final com.typesafe.sslconfig.ssl.KeyStoreConfig ksc$2;

  public final com.typesafe.sslconfig.ssl.KeyStoreBuilder apply();
    Code:
       0: aload_0
       1: getfield      #25                 // Field ksc$2:Lcom/typesafe/sslconfig/ssl/KeyStoreConfig;
       4: invokevirtual #31                 // Method com/typesafe/sslconfig/ssl/KeyStoreConfig.data:()Lscala/Option;
       7: new           #33                 // class com/typesafe/sslconfig/ssl/ConfigSSLContextBuilder$$anonfun$keyStoreBuilder$2$$anonfun$9
      10: dup
      11: aload_0
      12: invokespecial #37                 // Method com/typesafe/sslconfig/ssl/ConfigSSLContextBuilder$$anonfun$keyStoreBuilder$2$$anonfun$9."<init>":(Lcom/typesafe/sslconfig/ssl/ConfigSSLContextBuilder$$anonfun$keyStoreBuilder$2;)V
      15: invokevirtual #43                 // Method scala/Option.getOrElse:(Lscala/Function0;)Ljava/lang/Object;
      18: checkcast     #45                 // class java/lang/String
      21: astore_1
      22: aload_0
      23: getfield      #47                 // Field $outer:Lcom/typesafe/sslconfig/ssl/ConfigSSLContextBuilder;
      26: aload_1
      27: invokevirtual #51                 // Method com/typesafe/sslconfig/ssl/ConfigSSLContextBuilder.stringBuilder:(Ljava/lang/String;)Lcom/typesafe/sslconfig/ssl/KeyStoreBuilder;
      30: areturn

  public final java.lang.Object apply();
    Code:
       0: aload_0
       1: invokevirtual #57                 // Method apply:()Lcom/typesafe/sslconfig/ssl/KeyStoreBuilder;
       4: areturn

  public com.typesafe.sslconfig.ssl.ConfigSSLContextBuilder$$anonfun$keyStoreBuilder$2(com.typesafe.sslconfig.ssl.ConfigSSLContextBuilder, com.typesafe.sslconfig.ssl.KeyStoreConfig);
    Code:
       0: aload_1
       1: ifnonnull     6
       4: aconst_null
       5: athrow
       6: aload_0
       7: aload_1
       8: putfield      #47                 // Field $outer:Lcom/typesafe/sslconfig/ssl/ConfigSSLContextBuilder;
      11: aload_0
      12: aload_2
      13: putfield      #25                 // Field ksc$2:Lcom/typesafe/sslconfig/ssl/KeyStoreConfig;
      16: aload_0
      17: invokespecial #61                 // Method scala/runtime/AbstractFunction0."<init>":()V
      20: return
}
