Compiled from "Config.scala"
public final class com.typesafe.sslconfig.ssl.KeyStoreConfig$ {
  public static final com.typesafe.sslconfig.ssl.KeyStoreConfig$ MODULE$;

  public static {};
    Code:
       0: new           #2                  // class com/typesafe/sslconfig/ssl/KeyStoreConfig$
       3: invokespecial #12                 // Method "<init>":()V
       6: return

  public com.typesafe.sslconfig.ssl.KeyStoreConfig apply(scala.Option<java.lang.String>, scala.Option<java.lang.String>);
    Code:
       0: new           #16                 // class com/typesafe/sslconfig/ssl/KeyStoreConfig
       3: dup
       4: aload_1
       5: aload_2
       6: aload_0
       7: invokevirtual #20                 // Method $lessinit$greater$default$3:()Lscala/Option;
      10: aload_0
      11: invokevirtual #24                 // Method $lessinit$greater$default$4:()Ljava/lang/String;
      14: invokespecial #27                 // Method com/typesafe/sslconfig/ssl/KeyStoreConfig."<init>":(Lscala/Option;Lscala/Option;Lscala/Option;Ljava/lang/String;)V
      17: areturn

  public com.typesafe.sslconfig.ssl.KeyStoreConfig getInstance(java.util.Optional<java.lang.String>, java.util.Optional<java.lang.String>);
    Code:
       0: aload_0
       1: getstatic     #38                 // Field scala/Option$.MODULE$:Lscala/Option$;
       4: aload_1
       5: aconst_null
       6: invokevirtual #44                 // Method java/util/Optional.orElse:(Ljava/lang/Object;)Ljava/lang/Object;
       9: invokevirtual #47                 // Method scala/Option$.apply:(Ljava/lang/Object;)Lscala/Option;
      12: getstatic     #38                 // Field scala/Option$.MODULE$:Lscala/Option$;
      15: aload_2
      16: aconst_null
      17: invokevirtual #44                 // Method java/util/Optional.orElse:(Ljava/lang/Object;)Ljava/lang/Object;
      20: invokevirtual #47                 // Method scala/Option$.apply:(Ljava/lang/Object;)Lscala/Option;
      23: invokevirtual #49                 // Method apply:(Lscala/Option;Lscala/Option;)Lcom/typesafe/sslconfig/ssl/KeyStoreConfig;
      26: areturn

  public scala.Option<java.lang.String> $lessinit$greater$default$3();
    Code:
       0: getstatic     #55                 // Field scala/None$.MODULE$:Lscala/None$;
       3: areturn

  public java.lang.String $lessinit$greater$default$4();
    Code:
       0: invokestatic  #60                 // Method java/security/KeyStore.getDefaultType:()Ljava/lang/String;
       3: areturn

  private com.typesafe.sslconfig.ssl.KeyStoreConfig$();
    Code:
       0: aload_0
       1: invokespecial #61                 // Method java/lang/Object."<init>":()V
       4: aload_0
       5: putstatic     #63                 // Field MODULE$:Lcom/typesafe/sslconfig/ssl/KeyStoreConfig$;
       8: return
}
