Compiled from "Config.scala"
public class com.typesafe.sslconfig.ssl.SSLConfigParser {
  private final com.typesafe.sslconfig.util.EnrichedConfig c;

  private final java.lang.ClassLoader classLoader;

  public com.typesafe.sslconfig.ssl.SSLConfigSettings parse();
    Code:
       0: aload_0
       1: getfield      #16                 // Field c:Lcom/typesafe/sslconfig/util/EnrichedConfig;
       4: ldc           #18                 // String default
       6: getstatic     #24                 // Field com/typesafe/sslconfig/util/ConfigLoader$.MODULE$:Lcom/typesafe/sslconfig/util/ConfigLoader$;
       9: invokevirtual #28                 // Method com/typesafe/sslconfig/util/ConfigLoader$.booleanLoader:()Lcom/typesafe/sslconfig/util/ConfigLoader;
      12: invokevirtual #34                 // Method com/typesafe/sslconfig/util/EnrichedConfig.get:(Ljava/lang/String;Lcom/typesafe/sslconfig/util/ConfigLoader;)Ljava/lang/Object;
      15: invokestatic  #40                 // Method scala/runtime/BoxesRunTime.unboxToBoolean:(Ljava/lang/Object;)Z
      18: istore_1
      19: aload_0
      20: getfield      #16                 // Field c:Lcom/typesafe/sslconfig/util/EnrichedConfig;
      23: ldc           #42                 // String protocol
      25: getstatic     #24                 // Field com/typesafe/sslconfig/util/ConfigLoader$.MODULE$:Lcom/typesafe/sslconfig/util/ConfigLoader$;
      28: invokevirtual #45                 // Method com/typesafe/sslconfig/util/ConfigLoader$.stringLoader:()Lcom/typesafe/sslconfig/util/ConfigLoader;
      31: invokevirtual #34                 // Method com/typesafe/sslconfig/util/EnrichedConfig.get:(Ljava/lang/String;Lcom/typesafe/sslconfig/util/ConfigLoader;)Ljava/lang/Object;
      34: checkcast     #47                 // class java/lang/String
      37: astore_2
      38: aload_0
      39: getfield      #16                 // Field c:Lcom/typesafe/sslconfig/util/EnrichedConfig;
      42: ldc           #49                 // String checkRevocation
      44: getstatic     #24                 // Field com/typesafe/sslconfig/util/ConfigLoader$.MODULE$:Lcom/typesafe/sslconfig/util/ConfigLoader$;
      47: invokevirtual #28                 // Method com/typesafe/sslconfig/util/ConfigLoader$.booleanLoader:()Lcom/typesafe/sslconfig/util/ConfigLoader;
      50: invokevirtual #53                 // Method com/typesafe/sslconfig/util/EnrichedConfig.getOptional:(Ljava/lang/String;Lcom/typesafe/sslconfig/util/ConfigLoader;)Lscala/Option;
      53: astore_3
      54: new           #55                 // class scala/Some
      57: dup
      58: aload_0
      59: getfield      #16                 // Field c:Lcom/typesafe/sslconfig/util/EnrichedConfig;
      62: ldc           #57                 // String revocationLists
      64: getstatic     #24                 // Field com/typesafe/sslconfig/util/ConfigLoader$.MODULE$:Lcom/typesafe/sslconfig/util/ConfigLoader$;
      67: invokevirtual #60                 // Method com/typesafe/sslconfig/util/ConfigLoader$.seqStringLoader:()Lcom/typesafe/sslconfig/util/ConfigLoader;
      70: invokevirtual #64                 // Method com/typesafe/sslconfig/util/EnrichedConfig.getSeq:(Ljava/lang/String;Lcom/typesafe/sslconfig/util/ConfigLoader;)Lscala/collection/immutable/Seq;
      73: new           #66                 // class com/typesafe/sslconfig/ssl/SSLConfigParser$$anonfun$3
      76: dup
      77: aload_0
      78: invokespecial #70                 // Method com/typesafe/sslconfig/ssl/SSLConfigParser$$anonfun$3."<init>":(Lcom/typesafe/sslconfig/ssl/SSLConfigParser;)V
      81: getstatic     #75                 // Field scala/collection/immutable/Seq$.MODULE$:Lscala/collection/immutable/Seq$;
      84: invokevirtual #79                 // Method scala/collection/immutable/Seq$.canBuildFrom:()Lscala/collection/generic/CanBuildFrom;
      87: invokeinterface #85,  3           // InterfaceMethod scala/collection/immutable/Seq.map:(Lscala/Function1;Lscala/collection/generic/CanBuildFrom;)Ljava/lang/Object;
      92: invokespecial #88                 // Method scala/Some."<init>":(Ljava/lang/Object;)V
      95: new           #90                 // class com/typesafe/sslconfig/ssl/SSLConfigParser$$anonfun$4
      98: dup
      99: aload_0
     100: invokespecial #91                 // Method com/typesafe/sslconfig/ssl/SSLConfigParser$$anonfun$4."<init>":(Lcom/typesafe/sslconfig/ssl/SSLConfigParser;)V
     103: invokevirtual #95                 // Method scala/Some.filter:(Lscala/Function1;)Lscala/Option;
     106: astore        4
     108: aload_0
     109: aload_0
     110: getfield      #16                 // Field c:Lcom/typesafe/sslconfig/util/EnrichedConfig;
     113: ldc           #97                 // String debug
     115: getstatic     #24                 // Field com/typesafe/sslconfig/util/ConfigLoader$.MODULE$:Lcom/typesafe/sslconfig/util/ConfigLoader$;
     118: invokevirtual #100                // Method com/typesafe/sslconfig/util/ConfigLoader$.playConfigLoader:()Lcom/typesafe/sslconfig/util/ConfigLoader;
     121: invokevirtual #34                 // Method com/typesafe/sslconfig/util/EnrichedConfig.get:(Ljava/lang/String;Lcom/typesafe/sslconfig/util/ConfigLoader;)Ljava/lang/Object;
     124: checkcast     #30                 // class com/typesafe/sslconfig/util/EnrichedConfig
     127: invokevirtual #104                // Method parseDebug:(Lcom/typesafe/sslconfig/util/EnrichedConfig;)Lcom/typesafe/sslconfig/ssl/SSLDebugConfig;
     130: astore        5
     132: aload_0
     133: aload_0
     134: getfield      #16                 // Field c:Lcom/typesafe/sslconfig/util/EnrichedConfig;
     137: ldc           #106                // String loose
     139: getstatic     #24                 // Field com/typesafe/sslconfig/util/ConfigLoader$.MODULE$:Lcom/typesafe/sslconfig/util/ConfigLoader$;
     142: invokevirtual #100                // Method com/typesafe/sslconfig/util/ConfigLoader$.playConfigLoader:()Lcom/typesafe/sslconfig/util/ConfigLoader;
     145: invokevirtual #34                 // Method com/typesafe/sslconfig/util/EnrichedConfig.get:(Ljava/lang/String;Lcom/typesafe/sslconfig/util/ConfigLoader;)Ljava/lang/Object;
     148: checkcast     #30                 // class com/typesafe/sslconfig/util/EnrichedConfig
     151: invokevirtual #110                // Method parseLooseOptions:(Lcom/typesafe/sslconfig/util/EnrichedConfig;)Lcom/typesafe/sslconfig/ssl/SSLLooseConfig;
     154: astore        6
     156: new           #55                 // class scala/Some
     159: dup
     160: aload_0
     161: getfield      #16                 // Field c:Lcom/typesafe/sslconfig/util/EnrichedConfig;
     164: ldc           #112                // String enabledCipherSuites
     166: getstatic     #24                 // Field com/typesafe/sslconfig/util/ConfigLoader$.MODULE$:Lcom/typesafe/sslconfig/util/ConfigLoader$;
     169: invokevirtual #60                 // Method com/typesafe/sslconfig/util/ConfigLoader$.seqStringLoader:()Lcom/typesafe/sslconfig/util/ConfigLoader;
     172: invokevirtual #64                 // Method com/typesafe/sslconfig/util/EnrichedConfig.getSeq:(Ljava/lang/String;Lcom/typesafe/sslconfig/util/ConfigLoader;)Lscala/collection/immutable/Seq;
     175: invokespecial #88                 // Method scala/Some."<init>":(Ljava/lang/Object;)V
     178: new           #114                // class com/typesafe/sslconfig/ssl/SSLConfigParser$$anonfun$5
     181: dup
     182: aload_0
     183: invokespecial #115                // Method com/typesafe/sslconfig/ssl/SSLConfigParser$$anonfun$5."<init>":(Lcom/typesafe/sslconfig/ssl/SSLConfigParser;)V
     186: invokevirtual #95                 // Method scala/Some.filter:(Lscala/Function1;)Lscala/Option;
     189: astore        7
     191: new           #55                 // class scala/Some
     194: dup
     195: aload_0
     196: getfield      #16                 // Field c:Lcom/typesafe/sslconfig/util/EnrichedConfig;
     199: ldc           #117                // String enabledProtocols
     201: getstatic     #24                 // Field com/typesafe/sslconfig/util/ConfigLoader$.MODULE$:Lcom/typesafe/sslconfig/util/ConfigLoader$;
     204: invokevirtual #60                 // Method com/typesafe/sslconfig/util/ConfigLoader$.seqStringLoader:()Lcom/typesafe/sslconfig/util/ConfigLoader;
     207: invokevirtual #64                 // Method com/typesafe/sslconfig/util/EnrichedConfig.getSeq:(Ljava/lang/String;Lcom/typesafe/sslconfig/util/ConfigLoader;)Lscala/collection/immutable/Seq;
     210: invokespecial #88                 // Method scala/Some."<init>":(Ljava/lang/Object;)V
     213: new           #119                // class com/typesafe/sslconfig/ssl/SSLConfigParser$$anonfun$6
     216: dup
     217: aload_0
     218: invokespecial #120                // Method com/typesafe/sslconfig/ssl/SSLConfigParser$$anonfun$6."<init>":(Lcom/typesafe/sslconfig/ssl/SSLConfigParser;)V
     221: invokevirtual #95                 // Method scala/Some.filter:(Lscala/Function1;)Lscala/Option;
     224: astore        8
     226: aload_0
     227: getfield      #16                 // Field c:Lcom/typesafe/sslconfig/util/EnrichedConfig;
     230: ldc           #122                // String hostnameVerifierClass
     232: getstatic     #24                 // Field com/typesafe/sslconfig/util/ConfigLoader$.MODULE$:Lcom/typesafe/sslconfig/util/ConfigLoader$;
     235: invokevirtual #45                 // Method com/typesafe/sslconfig/util/ConfigLoader$.stringLoader:()Lcom/typesafe/sslconfig/util/ConfigLoader;
     238: invokevirtual #53                 // Method com/typesafe/sslconfig/util/EnrichedConfig.getOptional:(Ljava/lang/String;Lcom/typesafe/sslconfig/util/ConfigLoader;)Lscala/Option;
     241: astore        10
     243: getstatic     #127                // Field scala/None$.MODULE$:Lscala/None$;
     246: aload         10
     248: invokevirtual #130                // Method java/lang/Object.equals:(Ljava/lang/Object;)Z
     251: ifeq          261
     254: ldc           #132                // class com/typesafe/sslconfig/ssl/DefaultHostnameVerifier
     256: astore        11
     258: goto          302
     261: aload         10
     263: instanceof    #55                 // class scala/Some
     266: ifeq          508
     269: aload         10
     271: checkcast     #55                 // class scala/Some
     274: astore        12
     276: aload         12
     278: invokevirtual #136                // Method scala/Some.x:()Ljava/lang/Object;
     281: checkcast     #47                 // class java/lang/String
     284: astore        13
     286: aload_0
     287: getfield      #138                // Field classLoader:Ljava/lang/ClassLoader;
     290: aload         13
     292: invokevirtual #144                // Method java/lang/ClassLoader.loadClass:(Ljava/lang/String;)Ljava/lang/Class;
     295: ldc           #146                // class javax/net/ssl/HostnameVerifier
     297: invokevirtual #152                // Method java/lang/Class.asSubclass:(Ljava/lang/Class;)Ljava/lang/Class;
     300: astore        11
     302: aload         11
     304: astore        9
     306: aload_0
     307: getfield      #16                 // Field c:Lcom/typesafe/sslconfig/util/EnrichedConfig;
     310: ldc           #154                // String disabledSignatureAlgorithms
     312: getstatic     #24                 // Field com/typesafe/sslconfig/util/ConfigLoader$.MODULE$:Lcom/typesafe/sslconfig/util/ConfigLoader$;
     315: invokevirtual #60                 // Method com/typesafe/sslconfig/util/ConfigLoader$.seqStringLoader:()Lcom/typesafe/sslconfig/util/ConfigLoader;
     318: invokevirtual #64                 // Method com/typesafe/sslconfig/util/EnrichedConfig.getSeq:(Ljava/lang/String;Lcom/typesafe/sslconfig/util/ConfigLoader;)Lscala/collection/immutable/Seq;
     321: astore        14
     323: aload_0
     324: getfield      #16                 // Field c:Lcom/typesafe/sslconfig/util/EnrichedConfig;
     327: ldc           #156                // String disabledKeyAlgorithms
     329: getstatic     #24                 // Field com/typesafe/sslconfig/util/ConfigLoader$.MODULE$:Lcom/typesafe/sslconfig/util/ConfigLoader$;
     332: invokevirtual #60                 // Method com/typesafe/sslconfig/util/ConfigLoader$.seqStringLoader:()Lcom/typesafe/sslconfig/util/ConfigLoader;
     335: invokevirtual #64                 // Method com/typesafe/sslconfig/util/EnrichedConfig.getSeq:(Ljava/lang/String;Lcom/typesafe/sslconfig/util/ConfigLoader;)Lscala/collection/immutable/Seq;
     338: astore        15
     340: aload_0
     341: aload_0
     342: getfield      #16                 // Field c:Lcom/typesafe/sslconfig/util/EnrichedConfig;
     345: ldc           #158                // String keyManager
     347: getstatic     #24                 // Field com/typesafe/sslconfig/util/ConfigLoader$.MODULE$:Lcom/typesafe/sslconfig/util/ConfigLoader$;
     350: invokevirtual #100                // Method com/typesafe/sslconfig/util/ConfigLoader$.playConfigLoader:()Lcom/typesafe/sslconfig/util/ConfigLoader;
     353: invokevirtual #34                 // Method com/typesafe/sslconfig/util/EnrichedConfig.get:(Ljava/lang/String;Lcom/typesafe/sslconfig/util/ConfigLoader;)Ljava/lang/Object;
     356: checkcast     #30                 // class com/typesafe/sslconfig/util/EnrichedConfig
     359: invokevirtual #162                // Method parseKeyManager:(Lcom/typesafe/sslconfig/util/EnrichedConfig;)Lcom/typesafe/sslconfig/ssl/KeyManagerConfig;
     362: astore        16
     364: aload_0
     365: aload_0
     366: getfield      #16                 // Field c:Lcom/typesafe/sslconfig/util/EnrichedConfig;
     369: ldc           #164                // String trustManager
     371: getstatic     #24                 // Field com/typesafe/sslconfig/util/ConfigLoader$.MODULE$:Lcom/typesafe/sslconfig/util/ConfigLoader$;
     374: invokevirtual #100                // Method com/typesafe/sslconfig/util/ConfigLoader$.playConfigLoader:()Lcom/typesafe/sslconfig/util/ConfigLoader;
     377: invokevirtual #34                 // Method com/typesafe/sslconfig/util/EnrichedConfig.get:(Ljava/lang/String;Lcom/typesafe/sslconfig/util/ConfigLoader;)Ljava/lang/Object;
     380: checkcast     #30                 // class com/typesafe/sslconfig/util/EnrichedConfig
     383: invokevirtual #168                // Method parseTrustManager:(Lcom/typesafe/sslconfig/util/EnrichedConfig;)Lcom/typesafe/sslconfig/ssl/TrustManagerConfig;
     386: astore        17
     388: aload_0
     389: aload_0
     390: getfield      #16                 // Field c:Lcom/typesafe/sslconfig/util/EnrichedConfig;
     393: ldc           #170                // String sslParameters
     395: getstatic     #24                 // Field com/typesafe/sslconfig/util/ConfigLoader$.MODULE$:Lcom/typesafe/sslconfig/util/ConfigLoader$;
     398: invokevirtual #100                // Method com/typesafe/sslconfig/util/ConfigLoader$.playConfigLoader:()Lcom/typesafe/sslconfig/util/ConfigLoader;
     401: invokevirtual #34                 // Method com/typesafe/sslconfig/util/EnrichedConfig.get:(Ljava/lang/String;Lcom/typesafe/sslconfig/util/ConfigLoader;)Ljava/lang/Object;
     404: checkcast     #30                 // class com/typesafe/sslconfig/util/EnrichedConfig
     407: invokevirtual #174                // Method parseSSLParameters:(Lcom/typesafe/sslconfig/util/EnrichedConfig;)Lcom/typesafe/sslconfig/ssl/SSLParametersConfig;
     410: astore        18
     412: iload_1
     413: istore        19
     415: aload_2
     416: astore        20
     418: aload_3
     419: astore        21
     421: aload         4
     423: astore        22
     425: aload         7
     427: astore        23
     429: aload         8
     431: astore        24
     433: aload         16
     435: astore        25
     437: aload         9
     439: astore        26
     441: aload         14
     443: astore        27
     445: aload         15
     447: astore        28
     449: aload         18
     451: astore        29
     453: aload         17
     455: astore        30
     457: getstatic     #127                // Field scala/None$.MODULE$:Lscala/None$;
     460: astore        31
     462: aload         5
     464: astore        32
     466: aload         6
     468: astore        33
     470: new           #176                // class com/typesafe/sslconfig/ssl/SSLConfigSettings
     473: dup
     474: iload         19
     476: aload         20
     478: aload         21
     480: aload         22
     482: aload         23
     484: aload         24
     486: aload         27
     488: aload         28
     490: aload         29
     492: aload         25
     494: aload         30
     496: aload         26
     498: aload         31
     500: aload         32
     502: aload         33
     504: invokespecial #179                // Method com/typesafe/sslconfig/ssl/SSLConfigSettings."<init>":(ZLjava/lang/String;Lscala/Option;Lscala/Option;Lscala/Option;Lscala/Option;Lscala/collection/immutable/Seq;Lscala/collection/immutable/Seq;Lcom/typesafe/sslconfig/ssl/SSLParametersConfig;Lcom/typesafe/sslconfig/ssl/KeyManagerConfig;Lcom/typesafe/sslconfig/ssl/TrustManagerConfig;Ljava/lang/Class;Lscala/Option;Lcom/typesafe/sslconfig/ssl/SSLDebugConfig;Lcom/typesafe/sslconfig/ssl/SSLLooseConfig;)V
     507: areturn
     508: new           #181                // class scala/MatchError
     511: dup
     512: aload         10
     514: invokespecial #182                // Method scala/MatchError."<init>":(Ljava/lang/Object;)V
     517: athrow

  public com.typesafe.sslconfig.ssl.SSLLooseConfig parseLooseOptions(com.typesafe.sslconfig.util.EnrichedConfig);
    Code:
       0: aload_1
       1: ldc           #224                // String allowWeakProtocols
       3: getstatic     #24                 // Field com/typesafe/sslconfig/util/ConfigLoader$.MODULE$:Lcom/typesafe/sslconfig/util/ConfigLoader$;
       6: invokevirtual #28                 // Method com/typesafe/sslconfig/util/ConfigLoader$.booleanLoader:()Lcom/typesafe/sslconfig/util/ConfigLoader;
       9: invokevirtual #34                 // Method com/typesafe/sslconfig/util/EnrichedConfig.get:(Ljava/lang/String;Lcom/typesafe/sslconfig/util/ConfigLoader;)Ljava/lang/Object;
      12: invokestatic  #40                 // Method scala/runtime/BoxesRunTime.unboxToBoolean:(Ljava/lang/Object;)Z
      15: istore_2
      16: aload_1
      17: ldc           #226                // String allowWeakCiphers
      19: getstatic     #24                 // Field com/typesafe/sslconfig/util/ConfigLoader$.MODULE$:Lcom/typesafe/sslconfig/util/ConfigLoader$;
      22: invokevirtual #28                 // Method com/typesafe/sslconfig/util/ConfigLoader$.booleanLoader:()Lcom/typesafe/sslconfig/util/ConfigLoader;
      25: invokevirtual #34                 // Method com/typesafe/sslconfig/util/EnrichedConfig.get:(Ljava/lang/String;Lcom/typesafe/sslconfig/util/ConfigLoader;)Ljava/lang/Object;
      28: invokestatic  #40                 // Method scala/runtime/BoxesRunTime.unboxToBoolean:(Ljava/lang/Object;)Z
      31: istore_3
      32: aload_1
      33: ldc           #228                // String allowLegacyHelloMessages
      35: getstatic     #24                 // Field com/typesafe/sslconfig/util/ConfigLoader$.MODULE$:Lcom/typesafe/sslconfig/util/ConfigLoader$;
      38: invokevirtual #28                 // Method com/typesafe/sslconfig/util/ConfigLoader$.booleanLoader:()Lcom/typesafe/sslconfig/util/ConfigLoader;
      41: invokevirtual #53                 // Method com/typesafe/sslconfig/util/EnrichedConfig.getOptional:(Ljava/lang/String;Lcom/typesafe/sslconfig/util/ConfigLoader;)Lscala/Option;
      44: astore        4
      46: aload_1
      47: ldc           #230                // String allowUnsafeRenegotiation
      49: getstatic     #24                 // Field com/typesafe/sslconfig/util/ConfigLoader$.MODULE$:Lcom/typesafe/sslconfig/util/ConfigLoader$;
      52: invokevirtual #28                 // Method com/typesafe/sslconfig/util/ConfigLoader$.booleanLoader:()Lcom/typesafe/sslconfig/util/ConfigLoader;
      55: invokevirtual #53                 // Method com/typesafe/sslconfig/util/EnrichedConfig.getOptional:(Ljava/lang/String;Lcom/typesafe/sslconfig/util/ConfigLoader;)Lscala/Option;
      58: astore        5
      60: aload_1
      61: ldc           #232                // String disableHostnameVerification
      63: getstatic     #24                 // Field com/typesafe/sslconfig/util/ConfigLoader$.MODULE$:Lcom/typesafe/sslconfig/util/ConfigLoader$;
      66: invokevirtual #28                 // Method com/typesafe/sslconfig/util/ConfigLoader$.booleanLoader:()Lcom/typesafe/sslconfig/util/ConfigLoader;
      69: invokevirtual #34                 // Method com/typesafe/sslconfig/util/EnrichedConfig.get:(Ljava/lang/String;Lcom/typesafe/sslconfig/util/ConfigLoader;)Ljava/lang/Object;
      72: invokestatic  #40                 // Method scala/runtime/BoxesRunTime.unboxToBoolean:(Ljava/lang/Object;)Z
      75: istore        6
      77: aload_1
      78: ldc           #234                // String disableSNI
      80: getstatic     #24                 // Field com/typesafe/sslconfig/util/ConfigLoader$.MODULE$:Lcom/typesafe/sslconfig/util/ConfigLoader$;
      83: invokevirtual #28                 // Method com/typesafe/sslconfig/util/ConfigLoader$.booleanLoader:()Lcom/typesafe/sslconfig/util/ConfigLoader;
      86: invokevirtual #34                 // Method com/typesafe/sslconfig/util/EnrichedConfig.get:(Ljava/lang/String;Lcom/typesafe/sslconfig/util/ConfigLoader;)Ljava/lang/Object;
      89: invokestatic  #40                 // Method scala/runtime/BoxesRunTime.unboxToBoolean:(Ljava/lang/Object;)Z
      92: istore        7
      94: aload_1
      95: ldc           #236                // String acceptAnyCertificate
      97: getstatic     #24                 // Field com/typesafe/sslconfig/util/ConfigLoader$.MODULE$:Lcom/typesafe/sslconfig/util/ConfigLoader$;
     100: invokevirtual #28                 // Method com/typesafe/sslconfig/util/ConfigLoader$.booleanLoader:()Lcom/typesafe/sslconfig/util/ConfigLoader;
     103: invokevirtual #34                 // Method com/typesafe/sslconfig/util/EnrichedConfig.get:(Ljava/lang/String;Lcom/typesafe/sslconfig/util/ConfigLoader;)Ljava/lang/Object;
     106: invokestatic  #40                 // Method scala/runtime/BoxesRunTime.unboxToBoolean:(Ljava/lang/Object;)Z
     109: istore        8
     111: iload_3
     112: istore        9
     114: iload_2
     115: istore        10
     117: aload         4
     119: astore        11
     121: aload         5
     123: astore        12
     125: iload         6
     127: istore        13
     129: iload         7
     131: istore        14
     133: iload         8
     135: istore        15
     137: new           #222                // class com/typesafe/sslconfig/ssl/SSLLooseConfig
     140: dup
     141: iload         15
     143: aload         11
     145: aload         12
     147: iload         9
     149: iload         10
     151: iload         13
     153: iload         14
     155: invokespecial #239                // Method com/typesafe/sslconfig/ssl/SSLLooseConfig."<init>":(ZLscala/Option;Lscala/Option;ZZZZ)V
     158: areturn

  public com.typesafe.sslconfig.ssl.SSLDebugConfig parseDebug(com.typesafe.sslconfig.util.EnrichedConfig);
    Code:
       0: aload_1
       1: ldc           #250                // String certpath
       3: getstatic     #24                 // Field com/typesafe/sslconfig/util/ConfigLoader$.MODULE$:Lcom/typesafe/sslconfig/util/ConfigLoader$;
       6: invokevirtual #28                 // Method com/typesafe/sslconfig/util/ConfigLoader$.booleanLoader:()Lcom/typesafe/sslconfig/util/ConfigLoader;
       9: invokevirtual #34                 // Method com/typesafe/sslconfig/util/EnrichedConfig.get:(Ljava/lang/String;Lcom/typesafe/sslconfig/util/ConfigLoader;)Ljava/lang/Object;
      12: invokestatic  #40                 // Method scala/runtime/BoxesRunTime.unboxToBoolean:(Ljava/lang/Object;)Z
      15: istore_2
      16: aload_1
      17: ldc           #252                // String all
      19: getstatic     #24                 // Field com/typesafe/sslconfig/util/ConfigLoader$.MODULE$:Lcom/typesafe/sslconfig/util/ConfigLoader$;
      22: invokevirtual #28                 // Method com/typesafe/sslconfig/util/ConfigLoader$.booleanLoader:()Lcom/typesafe/sslconfig/util/ConfigLoader;
      25: invokevirtual #34                 // Method com/typesafe/sslconfig/util/EnrichedConfig.get:(Ljava/lang/String;Lcom/typesafe/sslconfig/util/ConfigLoader;)Ljava/lang/Object;
      28: invokestatic  #40                 // Method scala/runtime/BoxesRunTime.unboxToBoolean:(Ljava/lang/Object;)Z
      31: ifeq          118
      34: new           #220                // class com/typesafe/sslconfig/ssl/SSLDebugConfig
      37: dup
      38: iconst_1
      39: iload_2
      40: getstatic     #257                // Field com/typesafe/sslconfig/ssl/SSLDebugConfig$.MODULE$:Lcom/typesafe/sslconfig/ssl/SSLDebugConfig$;
      43: invokevirtual #261                // Method com/typesafe/sslconfig/ssl/SSLDebugConfig$.$lessinit$greater$default$3:()Z
      46: getstatic     #257                // Field com/typesafe/sslconfig/ssl/SSLDebugConfig$.MODULE$:Lcom/typesafe/sslconfig/ssl/SSLDebugConfig$;
      49: invokevirtual #265                // Method com/typesafe/sslconfig/ssl/SSLDebugConfig$.$lessinit$greater$default$4:()Lscala/Option;
      52: getstatic     #257                // Field com/typesafe/sslconfig/ssl/SSLDebugConfig$.MODULE$:Lcom/typesafe/sslconfig/ssl/SSLDebugConfig$;
      55: invokevirtual #268                // Method com/typesafe/sslconfig/ssl/SSLDebugConfig$.$lessinit$greater$default$5:()Z
      58: getstatic     #257                // Field com/typesafe/sslconfig/ssl/SSLDebugConfig$.MODULE$:Lcom/typesafe/sslconfig/ssl/SSLDebugConfig$;
      61: invokevirtual #271                // Method com/typesafe/sslconfig/ssl/SSLDebugConfig$.$lessinit$greater$default$6:()Z
      64: getstatic     #257                // Field com/typesafe/sslconfig/ssl/SSLDebugConfig$.MODULE$:Lcom/typesafe/sslconfig/ssl/SSLDebugConfig$;
      67: invokevirtual #274                // Method com/typesafe/sslconfig/ssl/SSLDebugConfig$.$lessinit$greater$default$7:()Z
      70: getstatic     #257                // Field com/typesafe/sslconfig/ssl/SSLDebugConfig$.MODULE$:Lcom/typesafe/sslconfig/ssl/SSLDebugConfig$;
      73: invokevirtual #277                // Method com/typesafe/sslconfig/ssl/SSLDebugConfig$.$lessinit$greater$default$8:()Z
      76: getstatic     #257                // Field com/typesafe/sslconfig/ssl/SSLDebugConfig$.MODULE$:Lcom/typesafe/sslconfig/ssl/SSLDebugConfig$;
      79: invokevirtual #280                // Method com/typesafe/sslconfig/ssl/SSLDebugConfig$.$lessinit$greater$default$9:()Lscala/Option;
      82: getstatic     #257                // Field com/typesafe/sslconfig/ssl/SSLDebugConfig$.MODULE$:Lcom/typesafe/sslconfig/ssl/SSLDebugConfig$;
      85: invokevirtual #283                // Method com/typesafe/sslconfig/ssl/SSLDebugConfig$.$lessinit$greater$default$10:()Z
      88: getstatic     #257                // Field com/typesafe/sslconfig/ssl/SSLDebugConfig$.MODULE$:Lcom/typesafe/sslconfig/ssl/SSLDebugConfig$;
      91: invokevirtual #286                // Method com/typesafe/sslconfig/ssl/SSLDebugConfig$.$lessinit$greater$default$11:()Z
      94: getstatic     #257                // Field com/typesafe/sslconfig/ssl/SSLDebugConfig$.MODULE$:Lcom/typesafe/sslconfig/ssl/SSLDebugConfig$;
      97: invokevirtual #289                // Method com/typesafe/sslconfig/ssl/SSLDebugConfig$.$lessinit$greater$default$12:()Z
     100: getstatic     #257                // Field com/typesafe/sslconfig/ssl/SSLDebugConfig$.MODULE$:Lcom/typesafe/sslconfig/ssl/SSLDebugConfig$;
     103: invokevirtual #292                // Method com/typesafe/sslconfig/ssl/SSLDebugConfig$.$lessinit$greater$default$13:()Z
     106: getstatic     #257                // Field com/typesafe/sslconfig/ssl/SSLDebugConfig$.MODULE$:Lcom/typesafe/sslconfig/ssl/SSLDebugConfig$;
     109: invokevirtual #295                // Method com/typesafe/sslconfig/ssl/SSLDebugConfig$.$lessinit$greater$default$14:()Z
     112: invokespecial #298                // Method com/typesafe/sslconfig/ssl/SSLDebugConfig."<init>":(ZZZLscala/Option;ZZZZLscala/Option;ZZZZZ)V
     115: goto          546
     118: aload_1
     119: ldc_w         #300                // String record
     122: getstatic     #24                 // Field com/typesafe/sslconfig/util/ConfigLoader$.MODULE$:Lcom/typesafe/sslconfig/util/ConfigLoader$;
     125: invokevirtual #28                 // Method com/typesafe/sslconfig/util/ConfigLoader$.booleanLoader:()Lcom/typesafe/sslconfig/util/ConfigLoader;
     128: invokevirtual #34                 // Method com/typesafe/sslconfig/util/EnrichedConfig.get:(Ljava/lang/String;Lcom/typesafe/sslconfig/util/ConfigLoader;)Ljava/lang/Object;
     131: invokestatic  #40                 // Method scala/runtime/BoxesRunTime.unboxToBoolean:(Ljava/lang/Object;)Z
     134: ifeq          202
     137: aload_1
     138: ldc_w         #302                // String plaintext
     141: getstatic     #24                 // Field com/typesafe/sslconfig/util/ConfigLoader$.MODULE$:Lcom/typesafe/sslconfig/util/ConfigLoader$;
     144: invokevirtual #28                 // Method com/typesafe/sslconfig/util/ConfigLoader$.booleanLoader:()Lcom/typesafe/sslconfig/util/ConfigLoader;
     147: invokevirtual #34                 // Method com/typesafe/sslconfig/util/EnrichedConfig.get:(Ljava/lang/String;Lcom/typesafe/sslconfig/util/ConfigLoader;)Ljava/lang/Object;
     150: invokestatic  #40                 // Method scala/runtime/BoxesRunTime.unboxToBoolean:(Ljava/lang/Object;)Z
     153: istore        4
     155: aload_1
     156: ldc_w         #304                // String packet
     159: getstatic     #24                 // Field com/typesafe/sslconfig/util/ConfigLoader$.MODULE$:Lcom/typesafe/sslconfig/util/ConfigLoader$;
     162: invokevirtual #28                 // Method com/typesafe/sslconfig/util/ConfigLoader$.booleanLoader:()Lcom/typesafe/sslconfig/util/ConfigLoader;
     165: invokevirtual #34                 // Method com/typesafe/sslconfig/util/EnrichedConfig.get:(Ljava/lang/String;Lcom/typesafe/sslconfig/util/ConfigLoader;)Ljava/lang/Object;
     168: invokestatic  #40                 // Method scala/runtime/BoxesRunTime.unboxToBoolean:(Ljava/lang/Object;)Z
     171: istore        5
     173: new           #55                 // class scala/Some
     176: dup
     177: iload         4
     179: istore        6
     181: iload         5
     183: istore        7
     185: new           #306                // class com/typesafe/sslconfig/ssl/SSLDebugRecordOptions
     188: dup
     189: iload         7
     191: iload         6
     193: invokespecial #309                // Method com/typesafe/sslconfig/ssl/SSLDebugRecordOptions."<init>":(ZZ)V
     196: invokespecial #88                 // Method scala/Some."<init>":(Ljava/lang/Object;)V
     199: goto          205
     202: getstatic     #127                // Field scala/None$.MODULE$:Lscala/None$;
     205: astore_3
     206: aload_1
     207: ldc_w         #311                // String handshake
     210: getstatic     #24                 // Field com/typesafe/sslconfig/util/ConfigLoader$.MODULE$:Lcom/typesafe/sslconfig/util/ConfigLoader$;
     213: invokevirtual #28                 // Method com/typesafe/sslconfig/util/ConfigLoader$.booleanLoader:()Lcom/typesafe/sslconfig/util/ConfigLoader;
     216: invokevirtual #34                 // Method com/typesafe/sslconfig/util/EnrichedConfig.get:(Ljava/lang/String;Lcom/typesafe/sslconfig/util/ConfigLoader;)Ljava/lang/Object;
     219: invokestatic  #40                 // Method scala/runtime/BoxesRunTime.unboxToBoolean:(Ljava/lang/Object;)Z
     222: ifeq          282
     225: aload_1
     226: ldc_w         #313                // String data
     229: getstatic     #24                 // Field com/typesafe/sslconfig/util/ConfigLoader$.MODULE$:Lcom/typesafe/sslconfig/util/ConfigLoader$;
     232: invokevirtual #28                 // Method com/typesafe/sslconfig/util/ConfigLoader$.booleanLoader:()Lcom/typesafe/sslconfig/util/ConfigLoader;
     235: invokevirtual #34                 // Method com/typesafe/sslconfig/util/EnrichedConfig.get:(Ljava/lang/String;Lcom/typesafe/sslconfig/util/ConfigLoader;)Ljava/lang/Object;
     238: invokestatic  #40                 // Method scala/runtime/BoxesRunTime.unboxToBoolean:(Ljava/lang/Object;)Z
     241: istore        9
     243: aload_1
     244: ldc_w         #315                // String verbose
     247: getstatic     #24                 // Field com/typesafe/sslconfig/util/ConfigLoader$.MODULE$:Lcom/typesafe/sslconfig/util/ConfigLoader$;
     250: invokevirtual #28                 // Method com/typesafe/sslconfig/util/ConfigLoader$.booleanLoader:()Lcom/typesafe/sslconfig/util/ConfigLoader;
     253: invokevirtual #34                 // Method com/typesafe/sslconfig/util/EnrichedConfig.get:(Ljava/lang/String;Lcom/typesafe/sslconfig/util/ConfigLoader;)Ljava/lang/Object;
     256: invokestatic  #40                 // Method scala/runtime/BoxesRunTime.unboxToBoolean:(Ljava/lang/Object;)Z
     259: istore        10
     261: new           #55                 // class scala/Some
     264: dup
     265: new           #317                // class com/typesafe/sslconfig/ssl/SSLDebugHandshakeOptions
     268: dup
     269: iload         9
     271: iload         10
     273: invokespecial #318                // Method com/typesafe/sslconfig/ssl/SSLDebugHandshakeOptions."<init>":(ZZ)V
     276: invokespecial #88                 // Method scala/Some."<init>":(Ljava/lang/Object;)V
     279: goto          285
     282: getstatic     #127                // Field scala/None$.MODULE$:Lscala/None$;
     285: astore        8
     287: aload_1
     288: ldc_w         #320                // String keygen
     291: getstatic     #24                 // Field com/typesafe/sslconfig/util/ConfigLoader$.MODULE$:Lcom/typesafe/sslconfig/util/ConfigLoader$;
     294: invokevirtual #28                 // Method com/typesafe/sslconfig/util/ConfigLoader$.booleanLoader:()Lcom/typesafe/sslconfig/util/ConfigLoader;
     297: invokevirtual #34                 // Method com/typesafe/sslconfig/util/EnrichedConfig.get:(Ljava/lang/String;Lcom/typesafe/sslconfig/util/ConfigLoader;)Ljava/lang/Object;
     300: invokestatic  #40                 // Method scala/runtime/BoxesRunTime.unboxToBoolean:(Ljava/lang/Object;)Z
     303: istore        11
     305: aload_1
     306: ldc_w         #322                // String session
     309: getstatic     #24                 // Field com/typesafe/sslconfig/util/ConfigLoader$.MODULE$:Lcom/typesafe/sslconfig/util/ConfigLoader$;
     312: invokevirtual #28                 // Method com/typesafe/sslconfig/util/ConfigLoader$.booleanLoader:()Lcom/typesafe/sslconfig/util/ConfigLoader;
     315: invokevirtual #34                 // Method com/typesafe/sslconfig/util/EnrichedConfig.get:(Ljava/lang/String;Lcom/typesafe/sslconfig/util/ConfigLoader;)Ljava/lang/Object;
     318: invokestatic  #40                 // Method scala/runtime/BoxesRunTime.unboxToBoolean:(Ljava/lang/Object;)Z
     321: istore        12
     323: aload_1
     324: ldc_w         #324                // String defaultctx
     327: getstatic     #24                 // Field com/typesafe/sslconfig/util/ConfigLoader$.MODULE$:Lcom/typesafe/sslconfig/util/ConfigLoader$;
     330: invokevirtual #28                 // Method com/typesafe/sslconfig/util/ConfigLoader$.booleanLoader:()Lcom/typesafe/sslconfig/util/ConfigLoader;
     333: invokevirtual #34                 // Method com/typesafe/sslconfig/util/EnrichedConfig.get:(Ljava/lang/String;Lcom/typesafe/sslconfig/util/ConfigLoader;)Ljava/lang/Object;
     336: invokestatic  #40                 // Method scala/runtime/BoxesRunTime.unboxToBoolean:(Ljava/lang/Object;)Z
     339: istore        13
     341: aload_1
     342: ldc_w         #326                // String sslctx
     345: getstatic     #24                 // Field com/typesafe/sslconfig/util/ConfigLoader$.MODULE$:Lcom/typesafe/sslconfig/util/ConfigLoader$;
     348: invokevirtual #28                 // Method com/typesafe/sslconfig/util/ConfigLoader$.booleanLoader:()Lcom/typesafe/sslconfig/util/ConfigLoader;
     351: invokevirtual #34                 // Method com/typesafe/sslconfig/util/EnrichedConfig.get:(Ljava/lang/String;Lcom/typesafe/sslconfig/util/ConfigLoader;)Ljava/lang/Object;
     354: invokestatic  #40                 // Method scala/runtime/BoxesRunTime.unboxToBoolean:(Ljava/lang/Object;)Z
     357: istore        14
     359: aload_1
     360: ldc_w         #328                // String sessioncache
     363: getstatic     #24                 // Field com/typesafe/sslconfig/util/ConfigLoader$.MODULE$:Lcom/typesafe/sslconfig/util/ConfigLoader$;
     366: invokevirtual #28                 // Method com/typesafe/sslconfig/util/ConfigLoader$.booleanLoader:()Lcom/typesafe/sslconfig/util/ConfigLoader;
     369: invokevirtual #34                 // Method com/typesafe/sslconfig/util/EnrichedConfig.get:(Ljava/lang/String;Lcom/typesafe/sslconfig/util/ConfigLoader;)Ljava/lang/Object;
     372: invokestatic  #40                 // Method scala/runtime/BoxesRunTime.unboxToBoolean:(Ljava/lang/Object;)Z
     375: istore        15
     377: aload_1
     378: ldc_w         #330                // String keymanager
     381: getstatic     #24                 // Field com/typesafe/sslconfig/util/ConfigLoader$.MODULE$:Lcom/typesafe/sslconfig/util/ConfigLoader$;
     384: invokevirtual #28                 // Method com/typesafe/sslconfig/util/ConfigLoader$.booleanLoader:()Lcom/typesafe/sslconfig/util/ConfigLoader;
     387: invokevirtual #34                 // Method com/typesafe/sslconfig/util/EnrichedConfig.get:(Ljava/lang/String;Lcom/typesafe/sslconfig/util/ConfigLoader;)Ljava/lang/Object;
     390: invokestatic  #40                 // Method scala/runtime/BoxesRunTime.unboxToBoolean:(Ljava/lang/Object;)Z
     393: istore        16
     395: aload_1
     396: ldc_w         #332                // String trustmanager
     399: getstatic     #24                 // Field com/typesafe/sslconfig/util/ConfigLoader$.MODULE$:Lcom/typesafe/sslconfig/util/ConfigLoader$;
     402: invokevirtual #28                 // Method com/typesafe/sslconfig/util/ConfigLoader$.booleanLoader:()Lcom/typesafe/sslconfig/util/ConfigLoader;
     405: invokevirtual #34                 // Method com/typesafe/sslconfig/util/EnrichedConfig.get:(Ljava/lang/String;Lcom/typesafe/sslconfig/util/ConfigLoader;)Ljava/lang/Object;
     408: invokestatic  #40                 // Method scala/runtime/BoxesRunTime.unboxToBoolean:(Ljava/lang/Object;)Z
     411: istore        17
     413: aload_1
     414: ldc_w         #334                // String pluggability
     417: getstatic     #24                 // Field com/typesafe/sslconfig/util/ConfigLoader$.MODULE$:Lcom/typesafe/sslconfig/util/ConfigLoader$;
     420: invokevirtual #28                 // Method com/typesafe/sslconfig/util/ConfigLoader$.booleanLoader:()Lcom/typesafe/sslconfig/util/ConfigLoader;
     423: invokevirtual #34                 // Method com/typesafe/sslconfig/util/EnrichedConfig.get:(Ljava/lang/String;Lcom/typesafe/sslconfig/util/ConfigLoader;)Ljava/lang/Object;
     426: invokestatic  #40                 // Method scala/runtime/BoxesRunTime.unboxToBoolean:(Ljava/lang/Object;)Z
     429: istore        18
     431: aload_1
     432: ldc_w         #336                // String ssl
     435: getstatic     #24                 // Field com/typesafe/sslconfig/util/ConfigLoader$.MODULE$:Lcom/typesafe/sslconfig/util/ConfigLoader$;
     438: invokevirtual #28                 // Method com/typesafe/sslconfig/util/ConfigLoader$.booleanLoader:()Lcom/typesafe/sslconfig/util/ConfigLoader;
     441: invokevirtual #34                 // Method com/typesafe/sslconfig/util/EnrichedConfig.get:(Ljava/lang/String;Lcom/typesafe/sslconfig/util/ConfigLoader;)Ljava/lang/Object;
     444: invokestatic  #40                 // Method scala/runtime/BoxesRunTime.unboxToBoolean:(Ljava/lang/Object;)Z
     447: istore        19
     449: iload         19
     451: istore        20
     453: aload_3
     454: astore        21
     456: aload         8
     458: astore        22
     460: iload         11
     462: istore        23
     464: iload         12
     466: istore        24
     468: iload         13
     470: istore        25
     472: iload         14
     474: istore        26
     476: iload         15
     478: istore        27
     480: iload         16
     482: istore        28
     484: iload         17
     486: istore        29
     488: iload         18
     490: istore        30
     492: iload_2
     493: istore        31
     495: getstatic     #257                // Field com/typesafe/sslconfig/ssl/SSLDebugConfig$.MODULE$:Lcom/typesafe/sslconfig/ssl/SSLDebugConfig$;
     498: invokevirtual #339                // Method com/typesafe/sslconfig/ssl/SSLDebugConfig$.$lessinit$greater$default$1:()Z
     501: istore        32
     503: getstatic     #257                // Field com/typesafe/sslconfig/ssl/SSLDebugConfig$.MODULE$:Lcom/typesafe/sslconfig/ssl/SSLDebugConfig$;
     506: invokevirtual #274                // Method com/typesafe/sslconfig/ssl/SSLDebugConfig$.$lessinit$greater$default$7:()Z
     509: istore        33
     511: new           #220                // class com/typesafe/sslconfig/ssl/SSLDebugConfig
     514: dup
     515: iload         32
     517: iload         31
     519: iload         25
     521: aload         22
     523: iload         23
     525: iload         28
     527: iload         33
     529: iload         30
     531: aload         21
     533: iload         24
     535: iload         27
     537: iload         20
     539: iload         26
     541: iload         29
     543: invokespecial #298                // Method com/typesafe/sslconfig/ssl/SSLDebugConfig."<init>":(ZZZLscala/Option;ZZZZLscala/Option;ZZZZZ)V
     546: areturn

  public com.typesafe.sslconfig.ssl.KeyStoreConfig parseKeyStoreInfo(com.typesafe.sslconfig.util.EnrichedConfig);
    Code:
       0: aload_1
       1: ldc_w         #359                // String type
       4: getstatic     #24                 // Field com/typesafe/sslconfig/util/ConfigLoader$.MODULE$:Lcom/typesafe/sslconfig/util/ConfigLoader$;
       7: invokevirtual #45                 // Method com/typesafe/sslconfig/util/ConfigLoader$.stringLoader:()Lcom/typesafe/sslconfig/util/ConfigLoader;
      10: invokevirtual #53                 // Method com/typesafe/sslconfig/util/EnrichedConfig.getOptional:(Ljava/lang/String;Lcom/typesafe/sslconfig/util/ConfigLoader;)Lscala/Option;
      13: new           #361                // class com/typesafe/sslconfig/ssl/SSLConfigParser$$anonfun$7
      16: dup
      17: aload_0
      18: invokespecial #362                // Method com/typesafe/sslconfig/ssl/SSLConfigParser$$anonfun$7."<init>":(Lcom/typesafe/sslconfig/ssl/SSLConfigParser;)V
      21: invokevirtual #366                // Method scala/Option.getOrElse:(Lscala/Function0;)Ljava/lang/Object;
      24: checkcast     #47                 // class java/lang/String
      27: astore_2
      28: aload_1
      29: ldc_w         #368                // String path
      32: getstatic     #24                 // Field com/typesafe/sslconfig/util/ConfigLoader$.MODULE$:Lcom/typesafe/sslconfig/util/ConfigLoader$;
      35: invokevirtual #45                 // Method com/typesafe/sslconfig/util/ConfigLoader$.stringLoader:()Lcom/typesafe/sslconfig/util/ConfigLoader;
      38: invokevirtual #53                 // Method com/typesafe/sslconfig/util/EnrichedConfig.getOptional:(Ljava/lang/String;Lcom/typesafe/sslconfig/util/ConfigLoader;)Lscala/Option;
      41: astore_3
      42: aload_1
      43: ldc_w         #313                // String data
      46: getstatic     #24                 // Field com/typesafe/sslconfig/util/ConfigLoader$.MODULE$:Lcom/typesafe/sslconfig/util/ConfigLoader$;
      49: invokevirtual #45                 // Method com/typesafe/sslconfig/util/ConfigLoader$.stringLoader:()Lcom/typesafe/sslconfig/util/ConfigLoader;
      52: invokevirtual #53                 // Method com/typesafe/sslconfig/util/EnrichedConfig.getOptional:(Ljava/lang/String;Lcom/typesafe/sslconfig/util/ConfigLoader;)Lscala/Option;
      55: astore        4
      57: aload_1
      58: ldc_w         #370                // String password
      61: getstatic     #24                 // Field com/typesafe/sslconfig/util/ConfigLoader$.MODULE$:Lcom/typesafe/sslconfig/util/ConfigLoader$;
      64: invokevirtual #45                 // Method com/typesafe/sslconfig/util/ConfigLoader$.stringLoader:()Lcom/typesafe/sslconfig/util/ConfigLoader;
      67: invokevirtual #53                 // Method com/typesafe/sslconfig/util/EnrichedConfig.getOptional:(Ljava/lang/String;Lcom/typesafe/sslconfig/util/ConfigLoader;)Lscala/Option;
      70: astore        5
      72: aload_3
      73: astore        6
      75: aload_2
      76: astore        7
      78: aload         4
      80: astore        8
      82: aload         5
      84: astore        9
      86: new           #372                // class com/typesafe/sslconfig/ssl/KeyStoreConfig
      89: dup
      90: aload         8
      92: aload         6
      94: aload         9
      96: aload         7
      98: invokespecial #375                // Method com/typesafe/sslconfig/ssl/KeyStoreConfig."<init>":(Lscala/Option;Lscala/Option;Lscala/Option;Ljava/lang/String;)V
     101: areturn

  public com.typesafe.sslconfig.ssl.TrustStoreConfig parseTrustStoreInfo(com.typesafe.sslconfig.util.EnrichedConfig);
    Code:
       0: aload_1
       1: ldc_w         #359                // String type
       4: getstatic     #24                 // Field com/typesafe/sslconfig/util/ConfigLoader$.MODULE$:Lcom/typesafe/sslconfig/util/ConfigLoader$;
       7: invokevirtual #45                 // Method com/typesafe/sslconfig/util/ConfigLoader$.stringLoader:()Lcom/typesafe/sslconfig/util/ConfigLoader;
      10: invokevirtual #53                 // Method com/typesafe/sslconfig/util/EnrichedConfig.getOptional:(Ljava/lang/String;Lcom/typesafe/sslconfig/util/ConfigLoader;)Lscala/Option;
      13: new           #384                // class com/typesafe/sslconfig/ssl/SSLConfigParser$$anonfun$8
      16: dup
      17: aload_0
      18: invokespecial #385                // Method com/typesafe/sslconfig/ssl/SSLConfigParser$$anonfun$8."<init>":(Lcom/typesafe/sslconfig/ssl/SSLConfigParser;)V
      21: invokevirtual #366                // Method scala/Option.getOrElse:(Lscala/Function0;)Ljava/lang/Object;
      24: checkcast     #47                 // class java/lang/String
      27: astore_2
      28: aload_1
      29: ldc_w         #368                // String path
      32: getstatic     #24                 // Field com/typesafe/sslconfig/util/ConfigLoader$.MODULE$:Lcom/typesafe/sslconfig/util/ConfigLoader$;
      35: invokevirtual #45                 // Method com/typesafe/sslconfig/util/ConfigLoader$.stringLoader:()Lcom/typesafe/sslconfig/util/ConfigLoader;
      38: invokevirtual #53                 // Method com/typesafe/sslconfig/util/EnrichedConfig.getOptional:(Ljava/lang/String;Lcom/typesafe/sslconfig/util/ConfigLoader;)Lscala/Option;
      41: astore_3
      42: aload_1
      43: ldc_w         #313                // String data
      46: getstatic     #24                 // Field com/typesafe/sslconfig/util/ConfigLoader$.MODULE$:Lcom/typesafe/sslconfig/util/ConfigLoader$;
      49: invokevirtual #45                 // Method com/typesafe/sslconfig/util/ConfigLoader$.stringLoader:()Lcom/typesafe/sslconfig/util/ConfigLoader;
      52: invokevirtual #53                 // Method com/typesafe/sslconfig/util/EnrichedConfig.getOptional:(Ljava/lang/String;Lcom/typesafe/sslconfig/util/ConfigLoader;)Lscala/Option;
      55: astore        4
      57: aload_3
      58: astore        5
      60: aload_2
      61: astore        6
      63: aload         4
      65: astore        7
      67: new           #387                // class com/typesafe/sslconfig/ssl/TrustStoreConfig
      70: dup
      71: aload         7
      73: aload         5
      75: aload         6
      77: invokespecial #390                // Method com/typesafe/sslconfig/ssl/TrustStoreConfig."<init>":(Lscala/Option;Lscala/Option;Ljava/lang/String;)V
      80: areturn

  public com.typesafe.sslconfig.ssl.KeyManagerConfig parseKeyManager(com.typesafe.sslconfig.util.EnrichedConfig);
    Code:
       0: aload_1
       1: ldc_w         #395                // String algorithm
       4: getstatic     #24                 // Field com/typesafe/sslconfig/util/ConfigLoader$.MODULE$:Lcom/typesafe/sslconfig/util/ConfigLoader$;
       7: invokevirtual #45                 // Method com/typesafe/sslconfig/util/ConfigLoader$.stringLoader:()Lcom/typesafe/sslconfig/util/ConfigLoader;
      10: invokevirtual #53                 // Method com/typesafe/sslconfig/util/EnrichedConfig.getOptional:(Ljava/lang/String;Lcom/typesafe/sslconfig/util/ConfigLoader;)Lscala/Option;
      13: astore_3
      14: getstatic     #127                // Field scala/None$.MODULE$:Lscala/None$;
      17: aload_3
      18: invokevirtual #130                // Method java/lang/Object.equals:(Ljava/lang/Object;)Z
      21: ifeq          32
      24: invokestatic  #401                // Method javax/net/ssl/KeyManagerFactory.getDefaultAlgorithm:()Ljava/lang/String;
      27: astore        4
      29: goto          59
      32: aload_3
      33: instanceof    #55                 // class scala/Some
      36: ifeq          108
      39: aload_3
      40: checkcast     #55                 // class scala/Some
      43: astore        5
      45: aload         5
      47: invokevirtual #136                // Method scala/Some.x:()Ljava/lang/Object;
      50: checkcast     #47                 // class java/lang/String
      53: astore        6
      55: aload         6
      57: astore        4
      59: aload         4
      61: astore_2
      62: aload_1
      63: ldc_w         #403                // String stores
      66: aload_1
      67: invokevirtual #406                // Method com/typesafe/sslconfig/util/EnrichedConfig.getPrototypedSeq$default$2:()Ljava/lang/String;
      70: invokevirtual #410                // Method com/typesafe/sslconfig/util/EnrichedConfig.getPrototypedSeq:(Ljava/lang/String;Ljava/lang/String;)Lscala/collection/immutable/Seq;
      73: new           #412                // class com/typesafe/sslconfig/ssl/SSLConfigParser$$anonfun$9
      76: dup
      77: aload_0
      78: invokespecial #413                // Method com/typesafe/sslconfig/ssl/SSLConfigParser$$anonfun$9."<init>":(Lcom/typesafe/sslconfig/ssl/SSLConfigParser;)V
      81: getstatic     #75                 // Field scala/collection/immutable/Seq$.MODULE$:Lscala/collection/immutable/Seq$;
      84: invokevirtual #79                 // Method scala/collection/immutable/Seq$.canBuildFrom:()Lscala/collection/generic/CanBuildFrom;
      87: invokeinterface #85,  3           // InterfaceMethod scala/collection/immutable/Seq.map:(Lscala/Function1;Lscala/collection/generic/CanBuildFrom;)Ljava/lang/Object;
      92: checkcast     #81                 // class scala/collection/immutable/Seq
      95: astore        7
      97: new           #415                // class com/typesafe/sslconfig/ssl/KeyManagerConfig
     100: dup
     101: aload_2
     102: aload         7
     104: invokespecial #418                // Method com/typesafe/sslconfig/ssl/KeyManagerConfig."<init>":(Ljava/lang/String;Lscala/collection/immutable/Seq;)V
     107: areturn
     108: new           #181                // class scala/MatchError
     111: dup
     112: aload_3
     113: invokespecial #182                // Method scala/MatchError."<init>":(Ljava/lang/Object;)V
     116: athrow

  public com.typesafe.sslconfig.ssl.TrustManagerConfig parseTrustManager(com.typesafe.sslconfig.util.EnrichedConfig);
    Code:
       0: aload_1
       1: ldc_w         #395                // String algorithm
       4: getstatic     #24                 // Field com/typesafe/sslconfig/util/ConfigLoader$.MODULE$:Lcom/typesafe/sslconfig/util/ConfigLoader$;
       7: invokevirtual #45                 // Method com/typesafe/sslconfig/util/ConfigLoader$.stringLoader:()Lcom/typesafe/sslconfig/util/ConfigLoader;
      10: invokevirtual #53                 // Method com/typesafe/sslconfig/util/EnrichedConfig.getOptional:(Ljava/lang/String;Lcom/typesafe/sslconfig/util/ConfigLoader;)Lscala/Option;
      13: astore_3
      14: getstatic     #127                // Field scala/None$.MODULE$:Lscala/None$;
      17: aload_3
      18: invokevirtual #130                // Method java/lang/Object.equals:(Ljava/lang/Object;)Z
      21: ifeq          32
      24: invokestatic  #423                // Method javax/net/ssl/TrustManagerFactory.getDefaultAlgorithm:()Ljava/lang/String;
      27: astore        4
      29: goto          59
      32: aload_3
      33: instanceof    #55                 // class scala/Some
      36: ifeq          108
      39: aload_3
      40: checkcast     #55                 // class scala/Some
      43: astore        5
      45: aload         5
      47: invokevirtual #136                // Method scala/Some.x:()Ljava/lang/Object;
      50: checkcast     #47                 // class java/lang/String
      53: astore        6
      55: aload         6
      57: astore        4
      59: aload         4
      61: astore_2
      62: aload_1
      63: ldc_w         #403                // String stores
      66: aload_1
      67: invokevirtual #406                // Method com/typesafe/sslconfig/util/EnrichedConfig.getPrototypedSeq$default$2:()Ljava/lang/String;
      70: invokevirtual #410                // Method com/typesafe/sslconfig/util/EnrichedConfig.getPrototypedSeq:(Ljava/lang/String;Ljava/lang/String;)Lscala/collection/immutable/Seq;
      73: new           #425                // class com/typesafe/sslconfig/ssl/SSLConfigParser$$anonfun$10
      76: dup
      77: aload_0
      78: invokespecial #426                // Method com/typesafe/sslconfig/ssl/SSLConfigParser$$anonfun$10."<init>":(Lcom/typesafe/sslconfig/ssl/SSLConfigParser;)V
      81: getstatic     #75                 // Field scala/collection/immutable/Seq$.MODULE$:Lscala/collection/immutable/Seq$;
      84: invokevirtual #79                 // Method scala/collection/immutable/Seq$.canBuildFrom:()Lscala/collection/generic/CanBuildFrom;
      87: invokeinterface #85,  3           // InterfaceMethod scala/collection/immutable/Seq.map:(Lscala/Function1;Lscala/collection/generic/CanBuildFrom;)Ljava/lang/Object;
      92: checkcast     #81                 // class scala/collection/immutable/Seq
      95: astore        7
      97: new           #428                // class com/typesafe/sslconfig/ssl/TrustManagerConfig
     100: dup
     101: aload_2
     102: aload         7
     104: invokespecial #429                // Method com/typesafe/sslconfig/ssl/TrustManagerConfig."<init>":(Ljava/lang/String;Lscala/collection/immutable/Seq;)V
     107: areturn
     108: new           #181                // class scala/MatchError
     111: dup
     112: aload_3
     113: invokespecial #182                // Method scala/MatchError."<init>":(Ljava/lang/Object;)V
     116: athrow

  public com.typesafe.sslconfig.ssl.SSLParametersConfig parseSSLParameters(com.typesafe.sslconfig.util.EnrichedConfig);
    Code:
       0: iconst_0
       1: istore_3
       2: aconst_null
       3: astore        4
       5: aload_1
       6: ldc_w         #432                // String clientAuth
       9: getstatic     #24                 // Field com/typesafe/sslconfig/util/ConfigLoader$.MODULE$:Lcom/typesafe/sslconfig/util/ConfigLoader$;
      12: invokevirtual #45                 // Method com/typesafe/sslconfig/util/ConfigLoader$.stringLoader:()Lcom/typesafe/sslconfig/util/ConfigLoader;
      15: invokevirtual #53                 // Method com/typesafe/sslconfig/util/EnrichedConfig.getOptional:(Ljava/lang/String;Lcom/typesafe/sslconfig/util/ConfigLoader;)Lscala/Option;
      18: astore        5
      20: aload         5
      22: instanceof    #55                 // class scala/Some
      25: ifeq          66
      28: iconst_1
      29: istore_3
      30: aload         5
      32: checkcast     #55                 // class scala/Some
      35: astore        4
      37: aload         4
      39: invokevirtual #136                // Method scala/Some.x:()Ljava/lang/Object;
      42: checkcast     #47                 // class java/lang/String
      45: astore        6
      47: ldc_w         #434                // String none
      50: aload         6
      52: invokevirtual #130                // Method java/lang/Object.equals:(Ljava/lang/Object;)Z
      55: ifeq          66
      58: getstatic     #439                // Field com/typesafe/sslconfig/ssl/ClientAuth$None$.MODULE$:Lcom/typesafe/sslconfig/ssl/ClientAuth$None$;
      61: astore        7
      63: goto          203
      66: iload_3
      67: ifeq          99
      70: aload         4
      72: invokevirtual #136                // Method scala/Some.x:()Ljava/lang/Object;
      75: checkcast     #47                 // class java/lang/String
      78: astore        8
      80: ldc_w         #441                // String want
      83: aload         8
      85: invokevirtual #130                // Method java/lang/Object.equals:(Ljava/lang/Object;)Z
      88: ifeq          99
      91: getstatic     #446                // Field com/typesafe/sslconfig/ssl/ClientAuth$Want$.MODULE$:Lcom/typesafe/sslconfig/ssl/ClientAuth$Want$;
      94: astore        7
      96: goto          203
      99: iload_3
     100: ifeq          132
     103: aload         4
     105: invokevirtual #136                // Method scala/Some.x:()Ljava/lang/Object;
     108: checkcast     #47                 // class java/lang/String
     111: astore        9
     113: ldc_w         #448                // String need
     116: aload         9
     118: invokevirtual #130                // Method java/lang/Object.equals:(Ljava/lang/Object;)Z
     121: ifeq          132
     124: getstatic     #453                // Field com/typesafe/sslconfig/ssl/ClientAuth$Need$.MODULE$:Lcom/typesafe/sslconfig/ssl/ClientAuth$Need$;
     127: astore        7
     129: goto          203
     132: getstatic     #127                // Field scala/None$.MODULE$:Lscala/None$;
     135: aload         5
     137: invokevirtual #130                // Method java/lang/Object.equals:(Ljava/lang/Object;)Z
     140: ifeq          149
     143: iconst_1
     144: istore        10
     146: goto          193
     149: aload         5
     151: instanceof    #55                 // class scala/Some
     154: ifeq          190
     157: aload         5
     159: checkcast     #55                 // class scala/Some
     162: astore        11
     164: aload         11
     166: invokevirtual #136                // Method scala/Some.x:()Ljava/lang/Object;
     169: checkcast     #47                 // class java/lang/String
     172: astore        12
     174: ldc           #18                 // String default
     176: aload         12
     178: invokevirtual #130                // Method java/lang/Object.equals:(Ljava/lang/Object;)Z
     181: ifeq          190
     184: iconst_1
     185: istore        10
     187: goto          193
     190: iconst_0
     191: istore        10
     193: iload         10
     195: ifeq          232
     198: getstatic     #458                // Field com/typesafe/sslconfig/ssl/ClientAuth$Default$.MODULE$:Lcom/typesafe/sslconfig/ssl/ClientAuth$Default$;
     201: astore        7
     203: aload         7
     205: astore_2
     206: aload_1
     207: ldc_w         #459                // String protocols
     210: getstatic     #24                 // Field com/typesafe/sslconfig/util/ConfigLoader$.MODULE$:Lcom/typesafe/sslconfig/util/ConfigLoader$;
     213: invokevirtual #60                 // Method com/typesafe/sslconfig/util/ConfigLoader$.seqStringLoader:()Lcom/typesafe/sslconfig/util/ConfigLoader;
     216: invokevirtual #64                 // Method com/typesafe/sslconfig/util/EnrichedConfig.getSeq:(Ljava/lang/String;Lcom/typesafe/sslconfig/util/ConfigLoader;)Lscala/collection/immutable/Seq;
     219: astore        13
     221: new           #461                // class com/typesafe/sslconfig/ssl/SSLParametersConfig
     224: dup
     225: aload_2
     226: aload         13
     228: invokespecial #464                // Method com/typesafe/sslconfig/ssl/SSLParametersConfig."<init>":(Lcom/typesafe/sslconfig/ssl/ClientAuth;Lscala/collection/immutable/Seq;)V
     231: areturn
     232: new           #181                // class scala/MatchError
     235: dup
     236: aload         5
     238: invokespecial #182                // Method scala/MatchError."<init>":(Ljava/lang/Object;)V
     241: athrow

  public com.typesafe.sslconfig.ssl.SSLConfigParser(com.typesafe.sslconfig.util.EnrichedConfig, java.lang.ClassLoader);
    Code:
       0: aload_0
       1: aload_1
       2: putfield      #16                 // Field c:Lcom/typesafe/sslconfig/util/EnrichedConfig;
       5: aload_0
       6: aload_2
       7: putfield      #138                // Field classLoader:Ljava/lang/ClassLoader;
      10: aload_0
      11: invokespecial #471                // Method java/lang/Object."<init>":()V
      14: return
}
