Compiled from "Config.scala"
public final class com.typesafe.sslconfig.ssl.SSLParametersConfig {
  private final com.typesafe.sslconfig.ssl.ClientAuth clientAuth;

  private final scala.collection.immutable.Seq<java.lang.String> protocols;

  public static scala.collection.immutable.Seq<java.lang.String> $lessinit$greater$default$2();
    Code:
       0: getstatic     #16                 // Field com/typesafe/sslconfig/ssl/SSLParametersConfig$.MODULE$:Lcom/typesafe/sslconfig/ssl/SSLParametersConfig$;
       3: invokevirtual #18                 // Method com/typesafe/sslconfig/ssl/SSLParametersConfig$.$lessinit$greater$default$2:()Lscala/collection/immutable/Seq;
       6: areturn

  public static com.typesafe.sslconfig.ssl.ClientAuth $lessinit$greater$default$1();
    Code:
       0: getstatic     #16                 // Field com/typesafe/sslconfig/ssl/SSLParametersConfig$.MODULE$:Lcom/typesafe/sslconfig/ssl/SSLParametersConfig$;
       3: invokevirtual #22                 // Method com/typesafe/sslconfig/ssl/SSLParametersConfig$.$lessinit$greater$default$1:()Lcom/typesafe/sslconfig/ssl/ClientAuth;
       6: areturn

  public static com.typesafe.sslconfig.ssl.SSLParametersConfig getInstance();
    Code:
       0: getstatic     #16                 // Field com/typesafe/sslconfig/ssl/SSLParametersConfig$.MODULE$:Lcom/typesafe/sslconfig/ssl/SSLParametersConfig$;
       3: invokevirtual #26                 // Method com/typesafe/sslconfig/ssl/SSLParametersConfig$.getInstance:()Lcom/typesafe/sslconfig/ssl/SSLParametersConfig;
       6: areturn

  public static com.typesafe.sslconfig.ssl.SSLParametersConfig apply();
    Code:
       0: getstatic     #16                 // Field com/typesafe/sslconfig/ssl/SSLParametersConfig$.MODULE$:Lcom/typesafe/sslconfig/ssl/SSLParametersConfig$;
       3: invokevirtual #29                 // Method com/typesafe/sslconfig/ssl/SSLParametersConfig$.apply:()Lcom/typesafe/sslconfig/ssl/SSLParametersConfig;
       6: areturn

  public com.typesafe.sslconfig.ssl.ClientAuth clientAuth();
    Code:
       0: aload_0
       1: getfield      #36                 // Field clientAuth:Lcom/typesafe/sslconfig/ssl/ClientAuth;
       4: areturn

  public scala.collection.immutable.Seq<java.lang.String> protocols();
    Code:
       0: aload_0
       1: getfield      #40                 // Field protocols:Lscala/collection/immutable/Seq;
       4: areturn

  public com.typesafe.sslconfig.ssl.SSLParametersConfig withClientAuth(com.typesafe.sslconfig.ssl.ClientAuth);
    Code:
       0: aload_0
       1: aload_1
       2: aload_0
       3: invokespecial #45                 // Method copy$default$2:()Lscala/collection/immutable/Seq;
       6: invokespecial #49                 // Method copy:(Lcom/typesafe/sslconfig/ssl/ClientAuth;Lscala/collection/immutable/Seq;)Lcom/typesafe/sslconfig/ssl/SSLParametersConfig;
       9: areturn

  public com.typesafe.sslconfig.ssl.SSLParametersConfig withProtocols(scala.collection.immutable.Seq<java.lang.String>);
    Code:
       0: aload_1
       1: astore_2
       2: aload_0
       3: invokespecial #55                 // Method copy$default$1:()Lcom/typesafe/sslconfig/ssl/ClientAuth;
       6: astore_3
       7: aload_0
       8: aload_3
       9: aload_2
      10: invokespecial #49                 // Method copy:(Lcom/typesafe/sslconfig/ssl/ClientAuth;Lscala/collection/immutable/Seq;)Lcom/typesafe/sslconfig/ssl/SSLParametersConfig;
      13: areturn

  private com.typesafe.sslconfig.ssl.SSLParametersConfig copy(com.typesafe.sslconfig.ssl.ClientAuth, scala.collection.immutable.Seq<java.lang.String>);
    Code:
       0: new           #2                  // class com/typesafe/sslconfig/ssl/SSLParametersConfig
       3: dup
       4: aload_1
       5: aload_2
       6: invokespecial #61                 // Method "<init>":(Lcom/typesafe/sslconfig/ssl/ClientAuth;Lscala/collection/immutable/Seq;)V
       9: areturn

  private com.typesafe.sslconfig.ssl.ClientAuth copy$default$1();
    Code:
       0: aload_0
       1: invokevirtual #63                 // Method clientAuth:()Lcom/typesafe/sslconfig/ssl/ClientAuth;
       4: areturn

  private scala.collection.immutable.Seq<java.lang.String> copy$default$2();
    Code:
       0: aload_0
       1: invokevirtual #65                 // Method protocols:()Lscala/collection/immutable/Seq;
       4: areturn

  public java.lang.String toString();
    Code:
       0: new           #69                 // class scala/StringContext
       3: dup
       4: getstatic     #74                 // Field scala/Predef$.MODULE$:Lscala/Predef$;
       7: iconst_3
       8: anewarray     #76                 // class java/lang/String
      11: dup
      12: iconst_0
      13: ldc           #78                 // String SSLParametersConfig(
      15: aastore
      16: dup
      17: iconst_1
      18: ldc           #80                 // String ,
      20: aastore
      21: dup
      22: iconst_2
      23: ldc           #82                 // String )
      25: aastore
      26: checkcast     #84                 // class "[Ljava/lang/Object;"
      29: invokevirtual #88                 // Method scala/Predef$.wrapRefArray:([Ljava/lang/Object;)Lscala/collection/mutable/WrappedArray;
      32: invokespecial #91                 // Method scala/StringContext."<init>":(Lscala/collection/Seq;)V
      35: getstatic     #74                 // Field scala/Predef$.MODULE$:Lscala/Predef$;
      38: iconst_2
      39: anewarray     #4                  // class java/lang/Object
      42: dup
      43: iconst_0
      44: aload_0
      45: invokevirtual #63                 // Method clientAuth:()Lcom/typesafe/sslconfig/ssl/ClientAuth;
      48: aastore
      49: dup
      50: iconst_1
      51: aload_0
      52: invokevirtual #65                 // Method protocols:()Lscala/collection/immutable/Seq;
      55: aastore
      56: invokevirtual #95                 // Method scala/Predef$.genericWrapArray:(Ljava/lang/Object;)Lscala/collection/mutable/WrappedArray;
      59: invokevirtual #99                 // Method scala/StringContext.s:(Lscala/collection/Seq;)Ljava/lang/String;
      62: areturn

  public com.typesafe.sslconfig.ssl.SSLParametersConfig(com.typesafe.sslconfig.ssl.ClientAuth, scala.collection.immutable.Seq<java.lang.String>);
    Code:
       0: aload_0
       1: aload_1
       2: putfield      #36                 // Field clientAuth:Lcom/typesafe/sslconfig/ssl/ClientAuth;
       5: aload_0
       6: aload_2
       7: putfield      #40                 // Field protocols:Lscala/collection/immutable/Seq;
      10: aload_0
      11: invokespecial #102                // Method java/lang/Object."<init>":()V
      14: return
}
