Compiled from "EndpointDescriptionWSDL.java"
public interface org.apache.axis2.jaxws.description.EndpointDescriptionWSDL {
  public static final java.lang.String SOAP11_WSDL_BINDING;

  public static final java.lang.String SOAP12_WSDL_BINDING;

  public static final java.lang.String HTTP_WSDL_BINDING;

  public static final javax.xml.namespace.QName SOAP_11_ADDRESS_ELEMENT;

  public static final javax.xml.namespace.QName SOAP_12_ADDRESS_ELEMENT;

  public abstract javax.wsdl.Definition getWSDLDefinition();

  public abstract javax.wsdl.Service getWSDLService();

  public abstract javax.wsdl.Port getWSDLPort();

  public abstract javax.wsdl.Binding getWSDLBinding();

  public abstract java.lang.String getWSDLBindingType();

  public abstract java.lang.String getWSDLSOAPAddress();

  public abstract boolean isWSDLFullySpecified();

  static {};
    Code:
       0: new           #1                  // class javax/xml/namespace/QName
       3: dup
       4: ldc           #3                  // String http://schemas.xmlsoap.org/wsdl/soap/
       6: ldc           #4                  // String address
       8: invokespecial #5                  // Method javax/xml/namespace/QName."<init>":(Ljava/lang/String;Ljava/lang/String;)V
      11: putstatic     #6                  // Field SOAP_11_ADDRESS_ELEMENT:Ljavax/xml/namespace/QName;
      14: new           #1                  // class javax/xml/namespace/QName
      17: dup
      18: ldc           #7                  // String http://schemas.xmlsoap.org/wsdl/soap12/
      20: ldc           #4                  // String address
      22: invokespecial #5                  // Method javax/xml/namespace/QName."<init>":(Ljava/lang/String;Ljava/lang/String;)V
      25: putstatic     #8                  // Field SOAP_12_ADDRESS_ELEMENT:Ljavax/xml/namespace/QName;
      28: return
}
