Compiled from "ContainerSourceSpecBuilder.java"
public class io.dekorate.deps.knative.legacysources.v1alpha1.ContainerSourceSpecBuilder extends io.dekorate.deps.knative.legacysources.v1alpha1.ContainerSourceSpecFluentImpl<io.dekorate.deps.knative.legacysources.v1alpha1.ContainerSourceSpecBuilder> implements io.dekorate.deps.kubernetes.api.builder.VisitableBuilder<io.dekorate.deps.knative.legacysources.v1alpha1.ContainerSourceSpec, io.dekorate.deps.knative.legacysources.v1alpha1.ContainerSourceSpecBuilder> {
  io.dekorate.deps.knative.legacysources.v1alpha1.ContainerSourceSpecFluent<?> fluent;

  java.lang.Boolean validationEnabled;

  public io.dekorate.deps.knative.legacysources.v1alpha1.ContainerSourceSpecBuilder();
    Code:
       0: aload_0
       1: iconst_1
       2: invokestatic  #21                 // Method java/lang/Boolean.valueOf:(Z)Ljava/lang/Boolean;
       5: invokespecial #24                 // Method "<init>":(Ljava/lang/Boolean;)V
       8: return

  public io.dekorate.deps.knative.legacysources.v1alpha1.ContainerSourceSpecBuilder(java.lang.Boolean);
    Code:
       0: aload_0
       1: new           #28                 // class io/dekorate/deps/knative/legacysources/v1alpha1/ContainerSourceSpec
       4: dup
       5: invokespecial #30                 // Method io/dekorate/deps/knative/legacysources/v1alpha1/ContainerSourceSpec."<init>":()V
       8: aload_1
       9: invokespecial #33                 // Method "<init>":(Lio/dekorate/deps/knative/legacysources/v1alpha1/ContainerSourceSpec;Ljava/lang/Boolean;)V
      12: return

  public io.dekorate.deps.knative.legacysources.v1alpha1.ContainerSourceSpecBuilder(io.dekorate.deps.knative.legacysources.v1alpha1.ContainerSourceSpecFluent<?>);
    Code:
       0: aload_0
       1: aload_1
       2: iconst_1
       3: invokestatic  #21                 // Method java/lang/Boolean.valueOf:(Z)Ljava/lang/Boolean;
       6: invokespecial #38                 // Method "<init>":(Lio/dekorate/deps/knative/legacysources/v1alpha1/ContainerSourceSpecFluent;Ljava/lang/Boolean;)V
       9: return

  public io.dekorate.deps.knative.legacysources.v1alpha1.ContainerSourceSpecBuilder(io.dekorate.deps.knative.legacysources.v1alpha1.ContainerSourceSpecFluent<?>, java.lang.Boolean);
    Code:
       0: aload_0
       1: aload_1
       2: new           #28                 // class io/dekorate/deps/knative/legacysources/v1alpha1/ContainerSourceSpec
       5: dup
       6: invokespecial #30                 // Method io/dekorate/deps/knative/legacysources/v1alpha1/ContainerSourceSpec."<init>":()V
       9: aload_2
      10: invokespecial #42                 // Method "<init>":(Lio/dekorate/deps/knative/legacysources/v1alpha1/ContainerSourceSpecFluent;Lio/dekorate/deps/knative/legacysources/v1alpha1/ContainerSourceSpec;Ljava/lang/Boolean;)V
      13: return

  public io.dekorate.deps.knative.legacysources.v1alpha1.ContainerSourceSpecBuilder(io.dekorate.deps.knative.legacysources.v1alpha1.ContainerSourceSpecFluent<?>, io.dekorate.deps.knative.legacysources.v1alpha1.ContainerSourceSpec);
    Code:
       0: aload_0
       1: aload_1
       2: aload_2
       3: iconst_1
       4: invokestatic  #21                 // Method java/lang/Boolean.valueOf:(Z)Ljava/lang/Boolean;
       7: invokespecial #42                 // Method "<init>":(Lio/dekorate/deps/knative/legacysources/v1alpha1/ContainerSourceSpecFluent;Lio/dekorate/deps/knative/legacysources/v1alpha1/ContainerSourceSpec;Ljava/lang/Boolean;)V
      10: return

  public io.dekorate.deps.knative.legacysources.v1alpha1.ContainerSourceSpecBuilder(io.dekorate.deps.knative.legacysources.v1alpha1.ContainerSourceSpecFluent<?>, io.dekorate.deps.knative.legacysources.v1alpha1.ContainerSourceSpec, java.lang.Boolean);
    Code:
       0: aload_0
       1: invokespecial #48                 // Method io/dekorate/deps/knative/legacysources/v1alpha1/ContainerSourceSpecFluentImpl."<init>":()V
       4: aload_0
       5: aload_1
       6: putfield      #50                 // Field fluent:Lio/dekorate/deps/knative/legacysources/v1alpha1/ContainerSourceSpecFluent;
       9: aload_1
      10: aload_2
      11: invokevirtual #54                 // Method io/dekorate/deps/knative/legacysources/v1alpha1/ContainerSourceSpec.getArgs:()Ljava/util/List;
      14: invokeinterface #60,  2           // InterfaceMethod io/dekorate/deps/knative/legacysources/v1alpha1/ContainerSourceSpecFluent.withArgs:(Ljava/util/List;)Lio/dekorate/deps/knative/legacysources/v1alpha1/ContainerSourceSpecFluent;
      19: pop
      20: aload_1
      21: aload_2
      22: invokevirtual #63                 // Method io/dekorate/deps/knative/legacysources/v1alpha1/ContainerSourceSpec.getEnv:()Ljava/util/List;
      25: invokeinterface #66,  2           // InterfaceMethod io/dekorate/deps/knative/legacysources/v1alpha1/ContainerSourceSpecFluent.withEnv:(Ljava/util/List;)Lio/dekorate/deps/knative/legacysources/v1alpha1/ContainerSourceSpecFluent;
      30: pop
      31: aload_1
      32: aload_2
      33: invokevirtual #70                 // Method io/dekorate/deps/knative/legacysources/v1alpha1/ContainerSourceSpec.getImage:()Ljava/lang/String;
      36: invokeinterface #74,  2           // InterfaceMethod io/dekorate/deps/knative/legacysources/v1alpha1/ContainerSourceSpecFluent.withImage:(Ljava/lang/String;)Lio/dekorate/deps/knative/legacysources/v1alpha1/ContainerSourceSpecFluent;
      41: pop
      42: aload_1
      43: aload_2
      44: invokevirtual #77                 // Method io/dekorate/deps/knative/legacysources/v1alpha1/ContainerSourceSpec.getServiceAccountName:()Ljava/lang/String;
      47: invokeinterface #80,  2           // InterfaceMethod io/dekorate/deps/knative/legacysources/v1alpha1/ContainerSourceSpecFluent.withServiceAccountName:(Ljava/lang/String;)Lio/dekorate/deps/knative/legacysources/v1alpha1/ContainerSourceSpecFluent;
      52: pop
      53: aload_1
      54: aload_2
      55: invokevirtual #84                 // Method io/dekorate/deps/knative/legacysources/v1alpha1/ContainerSourceSpec.getSink:()Lio/dekorate/deps/knative/duck/v1beta1/Destination;
      58: invokeinterface #88,  2           // InterfaceMethod io/dekorate/deps/knative/legacysources/v1alpha1/ContainerSourceSpecFluent.withSink:(Lio/dekorate/deps/knative/duck/v1beta1/Destination;)Lio/dekorate/deps/knative/legacysources/v1alpha1/ContainerSourceSpecFluent;
      63: pop
      64: aload_1
      65: aload_2
      66: invokevirtual #92                 // Method io/dekorate/deps/knative/legacysources/v1alpha1/ContainerSourceSpec.getTemplate:()Lio/dekorate/deps/kubernetes/api/model/PodTemplateSpec;
      69: invokeinterface #96,  2           // InterfaceMethod io/dekorate/deps/knative/legacysources/v1alpha1/ContainerSourceSpecFluent.withTemplate:(Lio/dekorate/deps/kubernetes/api/model/PodTemplateSpec;)Lio/dekorate/deps/knative/legacysources/v1alpha1/ContainerSourceSpecFluent;
      74: pop
      75: aload_0
      76: aload_3
      77: putfield      #98                 // Field validationEnabled:Ljava/lang/Boolean;
      80: return

  public io.dekorate.deps.knative.legacysources.v1alpha1.ContainerSourceSpecBuilder(io.dekorate.deps.knative.legacysources.v1alpha1.ContainerSourceSpec);
    Code:
       0: aload_0
       1: aload_1
       2: iconst_1
       3: invokestatic  #21                 // Method java/lang/Boolean.valueOf:(Z)Ljava/lang/Boolean;
       6: invokespecial #33                 // Method "<init>":(Lio/dekorate/deps/knative/legacysources/v1alpha1/ContainerSourceSpec;Ljava/lang/Boolean;)V
       9: return

  public io.dekorate.deps.knative.legacysources.v1alpha1.ContainerSourceSpecBuilder(io.dekorate.deps.knative.legacysources.v1alpha1.ContainerSourceSpec, java.lang.Boolean);
    Code:
       0: aload_0
       1: invokespecial #48                 // Method io/dekorate/deps/knative/legacysources/v1alpha1/ContainerSourceSpecFluentImpl."<init>":()V
       4: aload_0
       5: aload_0
       6: putfield      #50                 // Field fluent:Lio/dekorate/deps/knative/legacysources/v1alpha1/ContainerSourceSpecFluent;
       9: aload_0
      10: aload_1
      11: invokevirtual #54                 // Method io/dekorate/deps/knative/legacysources/v1alpha1/ContainerSourceSpec.getArgs:()Ljava/util/List;
      14: invokevirtual #100                // Method withArgs:(Ljava/util/List;)Lio/dekorate/deps/knative/legacysources/v1alpha1/ContainerSourceSpecFluent;
      17: pop
      18: aload_0
      19: aload_1
      20: invokevirtual #63                 // Method io/dekorate/deps/knative/legacysources/v1alpha1/ContainerSourceSpec.getEnv:()Ljava/util/List;
      23: invokevirtual #101                // Method withEnv:(Ljava/util/List;)Lio/dekorate/deps/knative/legacysources/v1alpha1/ContainerSourceSpecFluent;
      26: pop
      27: aload_0
      28: aload_1
      29: invokevirtual #70                 // Method io/dekorate/deps/knative/legacysources/v1alpha1/ContainerSourceSpec.getImage:()Ljava/lang/String;
      32: invokevirtual #102                // Method withImage:(Ljava/lang/String;)Lio/dekorate/deps/knative/legacysources/v1alpha1/ContainerSourceSpecFluent;
      35: pop
      36: aload_0
      37: aload_1
      38: invokevirtual #77                 // Method io/dekorate/deps/knative/legacysources/v1alpha1/ContainerSourceSpec.getServiceAccountName:()Ljava/lang/String;
      41: invokevirtual #103                // Method withServiceAccountName:(Ljava/lang/String;)Lio/dekorate/deps/knative/legacysources/v1alpha1/ContainerSourceSpecFluent;
      44: pop
      45: aload_0
      46: aload_1
      47: invokevirtual #84                 // Method io/dekorate/deps/knative/legacysources/v1alpha1/ContainerSourceSpec.getSink:()Lio/dekorate/deps/knative/duck/v1beta1/Destination;
      50: invokevirtual #104                // Method withSink:(Lio/dekorate/deps/knative/duck/v1beta1/Destination;)Lio/dekorate/deps/knative/legacysources/v1alpha1/ContainerSourceSpecFluent;
      53: pop
      54: aload_0
      55: aload_1
      56: invokevirtual #92                 // Method io/dekorate/deps/knative/legacysources/v1alpha1/ContainerSourceSpec.getTemplate:()Lio/dekorate/deps/kubernetes/api/model/PodTemplateSpec;
      59: invokevirtual #105                // Method withTemplate:(Lio/dekorate/deps/kubernetes/api/model/PodTemplateSpec;)Lio/dekorate/deps/knative/legacysources/v1alpha1/ContainerSourceSpecFluent;
      62: pop
      63: aload_0
      64: aload_2
      65: putfield      #98                 // Field validationEnabled:Ljava/lang/Boolean;
      68: return

  public io.dekorate.deps.knative.legacysources.v1alpha1.ContainerSourceSpec build();
    Code:
       0: new           #28                 // class io/dekorate/deps/knative/legacysources/v1alpha1/ContainerSourceSpec
       3: dup
       4: aload_0
       5: getfield      #50                 // Field fluent:Lio/dekorate/deps/knative/legacysources/v1alpha1/ContainerSourceSpecFluent;
       8: invokeinterface #108,  1          // InterfaceMethod io/dekorate/deps/knative/legacysources/v1alpha1/ContainerSourceSpecFluent.getArgs:()Ljava/util/List;
      13: aload_0
      14: getfield      #50                 // Field fluent:Lio/dekorate/deps/knative/legacysources/v1alpha1/ContainerSourceSpecFluent;
      17: invokeinterface #109,  1          // InterfaceMethod io/dekorate/deps/knative/legacysources/v1alpha1/ContainerSourceSpecFluent.getEnv:()Ljava/util/List;
      22: aload_0
      23: getfield      #50                 // Field fluent:Lio/dekorate/deps/knative/legacysources/v1alpha1/ContainerSourceSpecFluent;
      26: invokeinterface #110,  1          // InterfaceMethod io/dekorate/deps/knative/legacysources/v1alpha1/ContainerSourceSpecFluent.getImage:()Ljava/lang/String;
      31: aload_0
      32: getfield      #50                 // Field fluent:Lio/dekorate/deps/knative/legacysources/v1alpha1/ContainerSourceSpecFluent;
      35: invokeinterface #111,  1          // InterfaceMethod io/dekorate/deps/knative/legacysources/v1alpha1/ContainerSourceSpecFluent.getServiceAccountName:()Ljava/lang/String;
      40: aload_0
      41: getfield      #50                 // Field fluent:Lio/dekorate/deps/knative/legacysources/v1alpha1/ContainerSourceSpecFluent;
      44: invokeinterface #112,  1          // InterfaceMethod io/dekorate/deps/knative/legacysources/v1alpha1/ContainerSourceSpecFluent.getSink:()Lio/dekorate/deps/knative/duck/v1beta1/Destination;
      49: aload_0
      50: getfield      #50                 // Field fluent:Lio/dekorate/deps/knative/legacysources/v1alpha1/ContainerSourceSpecFluent;
      53: invokeinterface #113,  1          // InterfaceMethod io/dekorate/deps/knative/legacysources/v1alpha1/ContainerSourceSpecFluent.getTemplate:()Lio/dekorate/deps/kubernetes/api/model/PodTemplateSpec;
      58: invokespecial #116                // Method io/dekorate/deps/knative/legacysources/v1alpha1/ContainerSourceSpec."<init>":(Ljava/util/List;Ljava/util/List;Ljava/lang/String;Ljava/lang/String;Lio/dekorate/deps/knative/duck/v1beta1/Destination;Lio/dekorate/deps/kubernetes/api/model/PodTemplateSpec;)V
      61: astore_1
      62: aload_1
      63: areturn

  public boolean equals(java.lang.Object);
    Code:
       0: aload_0
       1: aload_1
       2: if_acmpne     7
       5: iconst_1
       6: ireturn
       7: aload_1
       8: ifnull        22
      11: aload_0
      12: invokevirtual #125                // Method java/lang/Object.getClass:()Ljava/lang/Class;
      15: aload_1
      16: invokevirtual #125                // Method java/lang/Object.getClass:()Ljava/lang/Class;
      19: if_acmpeq     24
      22: iconst_0
      23: ireturn
      24: aload_0
      25: aload_1
      26: invokespecial #127                // Method io/dekorate/deps/knative/legacysources/v1alpha1/ContainerSourceSpecFluentImpl.equals:(Ljava/lang/Object;)Z
      29: ifne          34
      32: iconst_0
      33: ireturn
      34: aload_1
      35: checkcast     #2                  // class io/dekorate/deps/knative/legacysources/v1alpha1/ContainerSourceSpecBuilder
      38: astore_2
      39: aload_0
      40: getfield      #50                 // Field fluent:Lio/dekorate/deps/knative/legacysources/v1alpha1/ContainerSourceSpecFluent;
      43: ifnull        71
      46: aload_0
      47: getfield      #50                 // Field fluent:Lio/dekorate/deps/knative/legacysources/v1alpha1/ContainerSourceSpecFluent;
      50: aload_0
      51: if_acmpeq     71
      54: aload_0
      55: getfield      #50                 // Field fluent:Lio/dekorate/deps/knative/legacysources/v1alpha1/ContainerSourceSpecFluent;
      58: aload_2
      59: getfield      #50                 // Field fluent:Lio/dekorate/deps/knative/legacysources/v1alpha1/ContainerSourceSpecFluent;
      62: invokevirtual #128                // Method java/lang/Object.equals:(Ljava/lang/Object;)Z
      65: ifne          88
      68: goto          86
      71: aload_2
      72: getfield      #50                 // Field fluent:Lio/dekorate/deps/knative/legacysources/v1alpha1/ContainerSourceSpecFluent;
      75: ifnull        88
      78: aload_0
      79: getfield      #50                 // Field fluent:Lio/dekorate/deps/knative/legacysources/v1alpha1/ContainerSourceSpecFluent;
      82: aload_0
      83: if_acmpeq     88
      86: iconst_0
      87: ireturn
      88: aload_0
      89: getfield      #98                 // Field validationEnabled:Ljava/lang/Boolean;
      92: ifnull        112
      95: aload_0
      96: getfield      #98                 // Field validationEnabled:Ljava/lang/Boolean;
      99: aload_2
     100: getfield      #98                 // Field validationEnabled:Ljava/lang/Boolean;
     103: invokevirtual #129                // Method java/lang/Boolean.equals:(Ljava/lang/Object;)Z
     106: ifne          121
     109: goto          119
     112: aload_2
     113: getfield      #98                 // Field validationEnabled:Ljava/lang/Boolean;
     116: ifnull        121
     119: iconst_0
     120: ireturn
     121: iconst_1
     122: ireturn

  public java.lang.Object build();
    Code:
       0: aload_0
       1: invokevirtual #135                // Method build:()Lio/dekorate/deps/knative/legacysources/v1alpha1/ContainerSourceSpec;
       4: areturn
}
