Compiled from "DeprecatedBuilder.java"
public class io.dekorate.deps.knative.legacysources.v1alpha1.DeprecatedBuilder extends io.dekorate.deps.knative.legacysources.v1alpha1.DeprecatedFluentImpl<io.dekorate.deps.knative.legacysources.v1alpha1.DeprecatedBuilder> implements io.dekorate.deps.kubernetes.api.builder.VisitableBuilder<io.dekorate.deps.knative.legacysources.v1alpha1.Deprecated, io.dekorate.deps.knative.legacysources.v1alpha1.DeprecatedBuilder> {
  io.dekorate.deps.knative.legacysources.v1alpha1.DeprecatedFluent<?> fluent;

  java.lang.Boolean validationEnabled;

  public io.dekorate.deps.knative.legacysources.v1alpha1.DeprecatedBuilder();
    Code:
       0: aload_0
       1: iconst_1
       2: invokestatic  #21                 // Method java/lang/Boolean.valueOf:(Z)Ljava/lang/Boolean;
       5: invokespecial #24                 // Method "<init>":(Ljava/lang/Boolean;)V
       8: return

  public io.dekorate.deps.knative.legacysources.v1alpha1.DeprecatedBuilder(java.lang.Boolean);
    Code:
       0: aload_0
       1: new           #28                 // class io/dekorate/deps/knative/legacysources/v1alpha1/Deprecated
       4: dup
       5: invokespecial #30                 // Method io/dekorate/deps/knative/legacysources/v1alpha1/Deprecated."<init>":()V
       8: aload_1
       9: invokespecial #33                 // Method "<init>":(Lio/dekorate/deps/knative/legacysources/v1alpha1/Deprecated;Ljava/lang/Boolean;)V
      12: return

  public io.dekorate.deps.knative.legacysources.v1alpha1.DeprecatedBuilder(io.dekorate.deps.knative.legacysources.v1alpha1.DeprecatedFluent<?>);
    Code:
       0: aload_0
       1: aload_1
       2: iconst_1
       3: invokestatic  #21                 // Method java/lang/Boolean.valueOf:(Z)Ljava/lang/Boolean;
       6: invokespecial #38                 // Method "<init>":(Lio/dekorate/deps/knative/legacysources/v1alpha1/DeprecatedFluent;Ljava/lang/Boolean;)V
       9: return

  public io.dekorate.deps.knative.legacysources.v1alpha1.DeprecatedBuilder(io.dekorate.deps.knative.legacysources.v1alpha1.DeprecatedFluent<?>, java.lang.Boolean);
    Code:
       0: aload_0
       1: aload_1
       2: new           #28                 // class io/dekorate/deps/knative/legacysources/v1alpha1/Deprecated
       5: dup
       6: invokespecial #30                 // Method io/dekorate/deps/knative/legacysources/v1alpha1/Deprecated."<init>":()V
       9: aload_2
      10: invokespecial #42                 // Method "<init>":(Lio/dekorate/deps/knative/legacysources/v1alpha1/DeprecatedFluent;Lio/dekorate/deps/knative/legacysources/v1alpha1/Deprecated;Ljava/lang/Boolean;)V
      13: return

  public io.dekorate.deps.knative.legacysources.v1alpha1.DeprecatedBuilder(io.dekorate.deps.knative.legacysources.v1alpha1.DeprecatedFluent<?>, io.dekorate.deps.knative.legacysources.v1alpha1.Deprecated);
    Code:
       0: aload_0
       1: aload_1
       2: aload_2
       3: iconst_1
       4: invokestatic  #21                 // Method java/lang/Boolean.valueOf:(Z)Ljava/lang/Boolean;
       7: invokespecial #42                 // Method "<init>":(Lio/dekorate/deps/knative/legacysources/v1alpha1/DeprecatedFluent;Lio/dekorate/deps/knative/legacysources/v1alpha1/Deprecated;Ljava/lang/Boolean;)V
      10: return

  public io.dekorate.deps.knative.legacysources.v1alpha1.DeprecatedBuilder(io.dekorate.deps.knative.legacysources.v1alpha1.DeprecatedFluent<?>, io.dekorate.deps.knative.legacysources.v1alpha1.Deprecated, java.lang.Boolean);
    Code:
       0: aload_0
       1: invokespecial #48                 // Method io/dekorate/deps/knative/legacysources/v1alpha1/DeprecatedFluentImpl."<init>":()V
       4: aload_0
       5: aload_1
       6: putfield      #50                 // Field fluent:Lio/dekorate/deps/knative/legacysources/v1alpha1/DeprecatedFluent;
       9: aload_0
      10: aload_3
      11: putfield      #52                 // Field validationEnabled:Ljava/lang/Boolean;
      14: return

  public io.dekorate.deps.knative.legacysources.v1alpha1.DeprecatedBuilder(io.dekorate.deps.knative.legacysources.v1alpha1.Deprecated);
    Code:
       0: aload_0
       1: aload_1
       2: iconst_1
       3: invokestatic  #21                 // Method java/lang/Boolean.valueOf:(Z)Ljava/lang/Boolean;
       6: invokespecial #33                 // Method "<init>":(Lio/dekorate/deps/knative/legacysources/v1alpha1/Deprecated;Ljava/lang/Boolean;)V
       9: return

  public io.dekorate.deps.knative.legacysources.v1alpha1.DeprecatedBuilder(io.dekorate.deps.knative.legacysources.v1alpha1.Deprecated, java.lang.Boolean);
    Code:
       0: aload_0
       1: invokespecial #48                 // Method io/dekorate/deps/knative/legacysources/v1alpha1/DeprecatedFluentImpl."<init>":()V
       4: aload_0
       5: aload_0
       6: putfield      #50                 // Field fluent:Lio/dekorate/deps/knative/legacysources/v1alpha1/DeprecatedFluent;
       9: aload_0
      10: aload_2
      11: putfield      #52                 // Field validationEnabled:Ljava/lang/Boolean;
      14: return

  public io.dekorate.deps.knative.legacysources.v1alpha1.Deprecated build();
    Code:
       0: new           #28                 // class io/dekorate/deps/knative/legacysources/v1alpha1/Deprecated
       3: dup
       4: invokespecial #30                 // Method io/dekorate/deps/knative/legacysources/v1alpha1/Deprecated."<init>":()V
       7: astore_1
       8: aload_1
       9: areturn

  public boolean equals(java.lang.Object);
    Code:
       0: aload_0
       1: aload_1
       2: if_acmpne     7
       5: iconst_1
       6: ireturn
       7: aload_1
       8: ifnull        22
      11: aload_0
      12: invokevirtual #64                 // Method java/lang/Object.getClass:()Ljava/lang/Class;
      15: aload_1
      16: invokevirtual #64                 // Method java/lang/Object.getClass:()Ljava/lang/Class;
      19: if_acmpeq     24
      22: iconst_0
      23: ireturn
      24: aload_0
      25: aload_1
      26: invokespecial #66                 // Method io/dekorate/deps/knative/legacysources/v1alpha1/DeprecatedFluentImpl.equals:(Ljava/lang/Object;)Z
      29: ifne          34
      32: iconst_0
      33: ireturn
      34: aload_1
      35: checkcast     #2                  // class io/dekorate/deps/knative/legacysources/v1alpha1/DeprecatedBuilder
      38: astore_2
      39: aload_0
      40: getfield      #50                 // Field fluent:Lio/dekorate/deps/knative/legacysources/v1alpha1/DeprecatedFluent;
      43: ifnull        71
      46: aload_0
      47: getfield      #50                 // Field fluent:Lio/dekorate/deps/knative/legacysources/v1alpha1/DeprecatedFluent;
      50: aload_0
      51: if_acmpeq     71
      54: aload_0
      55: getfield      #50                 // Field fluent:Lio/dekorate/deps/knative/legacysources/v1alpha1/DeprecatedFluent;
      58: aload_2
      59: getfield      #50                 // Field fluent:Lio/dekorate/deps/knative/legacysources/v1alpha1/DeprecatedFluent;
      62: invokevirtual #67                 // Method java/lang/Object.equals:(Ljava/lang/Object;)Z
      65: ifne          88
      68: goto          86
      71: aload_2
      72: getfield      #50                 // Field fluent:Lio/dekorate/deps/knative/legacysources/v1alpha1/DeprecatedFluent;
      75: ifnull        88
      78: aload_0
      79: getfield      #50                 // Field fluent:Lio/dekorate/deps/knative/legacysources/v1alpha1/DeprecatedFluent;
      82: aload_0
      83: if_acmpeq     88
      86: iconst_0
      87: ireturn
      88: aload_0
      89: getfield      #52                 // Field validationEnabled:Ljava/lang/Boolean;
      92: ifnull        112
      95: aload_0
      96: getfield      #52                 // Field validationEnabled:Ljava/lang/Boolean;
      99: aload_2
     100: getfield      #52                 // Field validationEnabled:Ljava/lang/Boolean;
     103: invokevirtual #68                 // Method java/lang/Boolean.equals:(Ljava/lang/Object;)Z
     106: ifne          121
     109: goto          119
     112: aload_2
     113: getfield      #52                 // Field validationEnabled:Ljava/lang/Boolean;
     116: ifnull        121
     119: iconst_0
     120: ireturn
     121: iconst_1
     122: ireturn

  public java.lang.Object build();
    Code:
       0: aload_0
       1: invokevirtual #74                 // Method build:()Lio/dekorate/deps/knative/legacysources/v1alpha1/Deprecated;
       4: areturn
}
