Compiled from "LinkedListMultimap.java"
class com.google.common.collect.LinkedListMultimap$AsMapEntries$1$1 extends com.google.common.collect.AbstractMapEntry<K, java.util.Collection<V>> {
  final java.lang.Object val$key;

  final com.google.common.collect.LinkedListMultimap$AsMapEntries$1 this$2;

  com.google.common.collect.LinkedListMultimap$AsMapEntries$1$1(com.google.common.collect.LinkedListMultimap$AsMapEntries$1, java.lang.Object);
    Code:
       0: aload_0
       1: aload_1
       2: putfield      #1                  // Field this$2:Lcom/google/common/collect/LinkedListMultimap$AsMapEntries$1;
       5: aload_0
       6: aload_2
       7: putfield      #2                  // Field val$key:Ljava/lang/Object;
      10: aload_0
      11: invokespecial #3                  // Method com/google/common/collect/AbstractMapEntry."<init>":()V
      14: return

  public K getKey();
    Code:
       0: aload_0
       1: getfield      #2                  // Field val$key:Ljava/lang/Object;
       4: areturn

  public java.util.Collection<V> getValue();
    Code:
       0: aload_0
       1: getfield      #1                  // Field this$2:Lcom/google/common/collect/LinkedListMultimap$AsMapEntries$1;
       4: getfield      #4                  // Field com/google/common/collect/LinkedListMultimap$AsMapEntries$1.this$1:Lcom/google/common/collect/LinkedListMultimap$AsMapEntries;
       7: getfield      #5                  // Field com/google/common/collect/LinkedListMultimap$AsMapEntries.this$0:Lcom/google/common/collect/LinkedListMultimap;
      10: aload_0
      11: getfield      #2                  // Field val$key:Ljava/lang/Object;
      14: invokevirtual #6                  // Method com/google/common/collect/LinkedListMultimap.get:(Ljava/lang/Object;)Ljava/util/List;
      17: areturn

  public java.lang.Object getValue();
    Code:
       0: aload_0
       1: invokevirtual #7                  // Method getValue:()Ljava/util/Collection;
       4: areturn
}
