Compiled from "Lists.java"
class com.google.common.collect.Lists$TransformingSequentialList$1 implements java.util.ListIterator<T> {
  final java.util.ListIterator val$delegate;

  final com.google.common.collect.Lists$TransformingSequentialList this$0;

  com.google.common.collect.Lists$TransformingSequentialList$1(com.google.common.collect.Lists$TransformingSequentialList, java.util.ListIterator);
    Code:
       0: aload_0
       1: aload_1
       2: putfield      #1                  // Field this$0:Lcom/google/common/collect/Lists$TransformingSequentialList;
       5: aload_0
       6: aload_2
       7: putfield      #2                  // Field val$delegate:Ljava/util/ListIterator;
      10: aload_0
      11: invokespecial #3                  // Method java/lang/Object."<init>":()V
      14: return

  public void add(T);
    Code:
       0: new           #4                  // class java/lang/UnsupportedOperationException
       3: dup
       4: invokespecial #5                  // Method java/lang/UnsupportedOperationException."<init>":()V
       7: athrow

  public boolean hasNext();
    Code:
       0: aload_0
       1: getfield      #2                  // Field val$delegate:Ljava/util/ListIterator;
       4: invokeinterface #6,  1            // InterfaceMethod java/util/ListIterator.hasNext:()Z
       9: ireturn

  public boolean hasPrevious();
    Code:
       0: aload_0
       1: getfield      #2                  // Field val$delegate:Ljava/util/ListIterator;
       4: invokeinterface #7,  1            // InterfaceMethod java/util/ListIterator.hasPrevious:()Z
       9: ireturn

  public T next();
    Code:
       0: aload_0
       1: getfield      #1                  // Field this$0:Lcom/google/common/collect/Lists$TransformingSequentialList;
       4: getfield      #8                  // Field com/google/common/collect/Lists$TransformingSequentialList.function:Lcom/google/common/base/Function;
       7: aload_0
       8: getfield      #2                  // Field val$delegate:Ljava/util/ListIterator;
      11: invokeinterface #9,  1            // InterfaceMethod java/util/ListIterator.next:()Ljava/lang/Object;
      16: invokeinterface #10,  2           // InterfaceMethod com/google/common/base/Function.apply:(Ljava/lang/Object;)Ljava/lang/Object;
      21: areturn

  public int nextIndex();
    Code:
       0: aload_0
       1: getfield      #2                  // Field val$delegate:Ljava/util/ListIterator;
       4: invokeinterface #11,  1           // InterfaceMethod java/util/ListIterator.nextIndex:()I
       9: ireturn

  public T previous();
    Code:
       0: aload_0
       1: getfield      #1                  // Field this$0:Lcom/google/common/collect/Lists$TransformingSequentialList;
       4: getfield      #8                  // Field com/google/common/collect/Lists$TransformingSequentialList.function:Lcom/google/common/base/Function;
       7: aload_0
       8: getfield      #2                  // Field val$delegate:Ljava/util/ListIterator;
      11: invokeinterface #12,  1           // InterfaceMethod java/util/ListIterator.previous:()Ljava/lang/Object;
      16: invokeinterface #10,  2           // InterfaceMethod com/google/common/base/Function.apply:(Ljava/lang/Object;)Ljava/lang/Object;
      21: areturn

  public int previousIndex();
    Code:
       0: aload_0
       1: getfield      #2                  // Field val$delegate:Ljava/util/ListIterator;
       4: invokeinterface #13,  1           // InterfaceMethod java/util/ListIterator.previousIndex:()I
       9: ireturn

  public void remove();
    Code:
       0: aload_0
       1: getfield      #2                  // Field val$delegate:Ljava/util/ListIterator;
       4: invokeinterface #14,  1           // InterfaceMethod java/util/ListIterator.remove:()V
       9: return

  public void set(T);
    Code:
       0: new           #4                  // class java/lang/UnsupportedOperationException
       3: dup
       4: ldc           #15                 // String not supported
       6: invokespecial #16                 // Method java/lang/UnsupportedOperationException."<init>":(Ljava/lang/String;)V
       9: athrow
}
