Compiled from "SortedLists.java"
final class com.google.common.collect.SortedLists$KeyAbsentBehavior$3 extends com.google.common.collect.SortedLists$KeyAbsentBehavior {
  com.google.common.collect.SortedLists$KeyAbsentBehavior$3(java.lang.String, int);
    Code:
       0: aload_0
       1: aload_1
       2: iload_2
       3: aconst_null
       4: invokespecial #1                  // Method com/google/common/collect/SortedLists$KeyAbsentBehavior."<init>":(Ljava/lang/String;ILcom/google/common/collect/SortedLists$1;)V
       7: return

  public <E> int resultIndex(int);
    Code:
       0: iload_1
       1: iconst_m1
       2: ixor
       3: ireturn
}
