Compiled from "SolrParams.java"
public abstract class org.apache.solr.common.params.SolrParams implements java.io.Serializable,org.apache.solr.common.MapSerializable {
  public org.apache.solr.common.params.SolrParams();
    Code:
       0: aload_0
       1: invokespecial #1                  // Method java/lang/Object."<init>":()V
       4: return

  public abstract java.lang.String get(java.lang.String);

  public abstract java.lang.String[] getParams(java.lang.String);

  public abstract java.util.Iterator<java.lang.String> getParameterNamesIterator();

  public java.lang.String get(java.lang.String, java.lang.String);
    Code:
       0: aload_0
       1: aload_1
       2: invokevirtual #2                  // Method get:(Ljava/lang/String;)Ljava/lang/String;
       5: astore_3
       6: aload_3
       7: ifnonnull     14
      10: aload_2
      11: goto          15
      14: aload_3
      15: areturn

  public org.apache.solr.common.params.RequiredSolrParams required();
    Code:
       0: new           #3                  // class org/apache/solr/common/params/RequiredSolrParams
       3: dup
       4: aload_0
       5: invokespecial #4                  // Method org/apache/solr/common/params/RequiredSolrParams."<init>":(Lorg/apache/solr/common/params/SolrParams;)V
       8: areturn

  protected java.lang.String fpname(java.lang.String, java.lang.String);
    Code:
       0: new           #5                  // class java/lang/StringBuilder
       3: dup
       4: invokespecial #6                  // Method java/lang/StringBuilder."<init>":()V
       7: ldc           #7                  // String f.
       9: invokevirtual #8                  // Method java/lang/StringBuilder.append:(Ljava/lang/String;)Ljava/lang/StringBuilder;
      12: aload_1
      13: invokevirtual #8                  // Method java/lang/StringBuilder.append:(Ljava/lang/String;)Ljava/lang/StringBuilder;
      16: bipush        46
      18: invokevirtual #9                  // Method java/lang/StringBuilder.append:(C)Ljava/lang/StringBuilder;
      21: aload_2
      22: invokevirtual #8                  // Method java/lang/StringBuilder.append:(Ljava/lang/String;)Ljava/lang/StringBuilder;
      25: invokevirtual #10                 // Method java/lang/StringBuilder.toString:()Ljava/lang/String;
      28: areturn

  public java.lang.String getFieldParam(java.lang.String, java.lang.String);
    Code:
       0: aload_0
       1: aload_0
       2: aload_1
       3: aload_2
       4: invokevirtual #11                 // Method fpname:(Ljava/lang/String;Ljava/lang/String;)Ljava/lang/String;
       7: invokevirtual #2                  // Method get:(Ljava/lang/String;)Ljava/lang/String;
      10: astore_3
      11: aload_3
      12: ifnull        19
      15: aload_3
      16: goto          24
      19: aload_0
      20: aload_2
      21: invokevirtual #2                  // Method get:(Ljava/lang/String;)Ljava/lang/String;
      24: areturn

  public java.lang.String getFieldParam(java.lang.String, java.lang.String, java.lang.String);
    Code:
       0: aload_0
       1: aload_0
       2: aload_1
       3: aload_2
       4: invokevirtual #11                 // Method fpname:(Ljava/lang/String;Ljava/lang/String;)Ljava/lang/String;
       7: invokevirtual #2                  // Method get:(Ljava/lang/String;)Ljava/lang/String;
      10: astore        4
      12: aload         4
      14: ifnull        22
      17: aload         4
      19: goto          28
      22: aload_0
      23: aload_2
      24: aload_3
      25: invokevirtual #12                 // Method get:(Ljava/lang/String;Ljava/lang/String;)Ljava/lang/String;
      28: areturn

  public java.lang.String[] getFieldParams(java.lang.String, java.lang.String);
    Code:
       0: aload_0
       1: aload_0
       2: aload_1
       3: aload_2
       4: invokevirtual #11                 // Method fpname:(Ljava/lang/String;Ljava/lang/String;)Ljava/lang/String;
       7: invokevirtual #13                 // Method getParams:(Ljava/lang/String;)[Ljava/lang/String;
      10: astore_3
      11: aload_3
      12: ifnull        19
      15: aload_3
      16: goto          24
      19: aload_0
      20: aload_2
      21: invokevirtual #13                 // Method getParams:(Ljava/lang/String;)[Ljava/lang/String;
      24: areturn

  public java.lang.Boolean getBool(java.lang.String);
    Code:
       0: aload_0
       1: aload_1
       2: invokevirtual #2                  // Method get:(Ljava/lang/String;)Ljava/lang/String;
       5: astore_2
       6: aload_2
       7: ifnonnull     14
      10: aconst_null
      11: goto          21
      14: aload_2
      15: invokestatic  #14                 // Method org/apache/solr/common/util/StrUtils.parseBool:(Ljava/lang/String;)Z
      18: invokestatic  #15                 // Method java/lang/Boolean.valueOf:(Z)Ljava/lang/Boolean;
      21: areturn

  public boolean getPrimitiveBool(java.lang.String);
    Code:
       0: aload_0
       1: aload_1
       2: iconst_0
       3: invokevirtual #16                 // Method getBool:(Ljava/lang/String;Z)Z
       6: ireturn

  public boolean getBool(java.lang.String, boolean);
    Code:
       0: aload_0
       1: aload_1
       2: invokevirtual #2                  // Method get:(Ljava/lang/String;)Ljava/lang/String;
       5: astore_3
       6: aload_3
       7: ifnonnull     14
      10: iload_2
      11: goto          18
      14: aload_3
      15: invokestatic  #14                 // Method org/apache/solr/common/util/StrUtils.parseBool:(Ljava/lang/String;)Z
      18: ireturn

  public java.lang.Boolean getFieldBool(java.lang.String, java.lang.String);
    Code:
       0: aload_0
       1: aload_1
       2: aload_2
       3: invokevirtual #17                 // Method getFieldParam:(Ljava/lang/String;Ljava/lang/String;)Ljava/lang/String;
       6: astore_3
       7: aload_3
       8: ifnonnull     15
      11: aconst_null
      12: goto          22
      15: aload_3
      16: invokestatic  #14                 // Method org/apache/solr/common/util/StrUtils.parseBool:(Ljava/lang/String;)Z
      19: invokestatic  #15                 // Method java/lang/Boolean.valueOf:(Z)Ljava/lang/Boolean;
      22: areturn

  public boolean getPrimitiveFieldBool(java.lang.String, java.lang.String);
    Code:
       0: aload_0
       1: aload_1
       2: aload_2
       3: iconst_0
       4: invokevirtual #18                 // Method getFieldBool:(Ljava/lang/String;Ljava/lang/String;Z)Z
       7: ireturn

  public boolean getFieldBool(java.lang.String, java.lang.String, boolean);
    Code:
       0: aload_0
       1: aload_1
       2: aload_2
       3: invokevirtual #17                 // Method getFieldParam:(Ljava/lang/String;Ljava/lang/String;)Ljava/lang/String;
       6: astore        4
       8: aload         4
      10: ifnonnull     17
      13: iload_3
      14: goto          22
      17: aload         4
      19: invokestatic  #14                 // Method org/apache/solr/common/util/StrUtils.parseBool:(Ljava/lang/String;)Z
      22: ireturn

  public java.lang.Integer getInt(java.lang.String);
    Code:
       0: aload_0
       1: aload_1
       2: invokevirtual #2                  // Method get:(Ljava/lang/String;)Ljava/lang/String;
       5: astore_2
       6: aload_2
       7: ifnonnull     14
      10: aconst_null
      11: goto          18
      14: aload_2
      15: invokestatic  #19                 // Method java/lang/Integer.valueOf:(Ljava/lang/String;)Ljava/lang/Integer;
      18: areturn
      19: astore_3
      20: new           #21                 // class org/apache/solr/common/SolrException
      23: dup
      24: getstatic     #22                 // Field org/apache/solr/common/SolrException$ErrorCode.BAD_REQUEST:Lorg/apache/solr/common/SolrException$ErrorCode;
      27: aload_3
      28: invokevirtual #23                 // Method java/lang/Exception.getMessage:()Ljava/lang/String;
      31: aload_3
      32: invokespecial #24                 // Method org/apache/solr/common/SolrException."<init>":(Lorg/apache/solr/common/SolrException$ErrorCode;Ljava/lang/String;Ljava/lang/Throwable;)V
      35: athrow
    Exception table:
       from    to  target type
           6    18    19   Class java/lang/Exception

  public int getPrimitiveInt(java.lang.String);
    Code:
       0: aload_0
       1: aload_1
       2: iconst_0
       3: invokevirtual #25                 // Method getInt:(Ljava/lang/String;I)I
       6: ireturn

  public int getInt(java.lang.String, int);
    Code:
       0: aload_0
       1: aload_1
       2: invokevirtual #2                  // Method get:(Ljava/lang/String;)Ljava/lang/String;
       5: astore_3
       6: aload_3
       7: ifnonnull     14
      10: iload_2
      11: goto          18
      14: aload_3
      15: invokestatic  #26                 // Method java/lang/Integer.parseInt:(Ljava/lang/String;)I
      18: ireturn
      19: astore        4
      21: new           #21                 // class org/apache/solr/common/SolrException
      24: dup
      25: getstatic     #22                 // Field org/apache/solr/common/SolrException$ErrorCode.BAD_REQUEST:Lorg/apache/solr/common/SolrException$ErrorCode;
      28: aload         4
      30: invokevirtual #23                 // Method java/lang/Exception.getMessage:()Ljava/lang/String;
      33: aload         4
      35: invokespecial #24                 // Method org/apache/solr/common/SolrException."<init>":(Lorg/apache/solr/common/SolrException$ErrorCode;Ljava/lang/String;Ljava/lang/Throwable;)V
      38: athrow
    Exception table:
       from    to  target type
           6    18    19   Class java/lang/Exception

  public java.lang.Long getLong(java.lang.String);
    Code:
       0: aload_0
       1: aload_1
       2: invokevirtual #2                  // Method get:(Ljava/lang/String;)Ljava/lang/String;
       5: astore_2
       6: aload_2
       7: ifnonnull     14
      10: aconst_null
      11: goto          18
      14: aload_2
      15: invokestatic  #27                 // Method java/lang/Long.valueOf:(Ljava/lang/String;)Ljava/lang/Long;
      18: areturn
      19: astore_3
      20: new           #21                 // class org/apache/solr/common/SolrException
      23: dup
      24: getstatic     #22                 // Field org/apache/solr/common/SolrException$ErrorCode.BAD_REQUEST:Lorg/apache/solr/common/SolrException$ErrorCode;
      27: aload_3
      28: invokevirtual #23                 // Method java/lang/Exception.getMessage:()Ljava/lang/String;
      31: aload_3
      32: invokespecial #24                 // Method org/apache/solr/common/SolrException."<init>":(Lorg/apache/solr/common/SolrException$ErrorCode;Ljava/lang/String;Ljava/lang/Throwable;)V
      35: athrow
    Exception table:
       from    to  target type
           6    18    19   Class java/lang/Exception

  public long getLong(java.lang.String, long);
    Code:
       0: aload_0
       1: aload_1
       2: invokevirtual #2                  // Method get:(Ljava/lang/String;)Ljava/lang/String;
       5: astore        4
       7: aload         4
       9: ifnonnull     16
      12: lload_2
      13: goto          21
      16: aload         4
      18: invokestatic  #28                 // Method java/lang/Long.parseLong:(Ljava/lang/String;)J
      21: lreturn
      22: astore        5
      24: new           #21                 // class org/apache/solr/common/SolrException
      27: dup
      28: getstatic     #22                 // Field org/apache/solr/common/SolrException$ErrorCode.BAD_REQUEST:Lorg/apache/solr/common/SolrException$ErrorCode;
      31: aload         5
      33: invokevirtual #23                 // Method java/lang/Exception.getMessage:()Ljava/lang/String;
      36: aload         5
      38: invokespecial #24                 // Method org/apache/solr/common/SolrException."<init>":(Lorg/apache/solr/common/SolrException$ErrorCode;Ljava/lang/String;Ljava/lang/Throwable;)V
      41: athrow
    Exception table:
       from    to  target type
           7    21    22   Class java/lang/Exception

  public java.lang.Integer getFieldInt(java.lang.String, java.lang.String);
    Code:
       0: aload_0
       1: aload_1
       2: aload_2
       3: invokevirtual #17                 // Method getFieldParam:(Ljava/lang/String;Ljava/lang/String;)Ljava/lang/String;
       6: astore_3
       7: aload_3
       8: ifnonnull     15
      11: aconst_null
      12: goto          19
      15: aload_3
      16: invokestatic  #19                 // Method java/lang/Integer.valueOf:(Ljava/lang/String;)Ljava/lang/Integer;
      19: areturn
      20: astore        4
      22: new           #21                 // class org/apache/solr/common/SolrException
      25: dup
      26: getstatic     #22                 // Field org/apache/solr/common/SolrException$ErrorCode.BAD_REQUEST:Lorg/apache/solr/common/SolrException$ErrorCode;
      29: aload         4
      31: invokevirtual #23                 // Method java/lang/Exception.getMessage:()Ljava/lang/String;
      34: aload         4
      36: invokespecial #24                 // Method org/apache/solr/common/SolrException."<init>":(Lorg/apache/solr/common/SolrException$ErrorCode;Ljava/lang/String;Ljava/lang/Throwable;)V
      39: athrow
    Exception table:
       from    to  target type
           7    19    20   Class java/lang/Exception

  public int getFieldInt(java.lang.String, java.lang.String, int);
    Code:
       0: aload_0
       1: aload_1
       2: aload_2
       3: invokevirtual #17                 // Method getFieldParam:(Ljava/lang/String;Ljava/lang/String;)Ljava/lang/String;
       6: astore        4
       8: aload         4
      10: ifnonnull     17
      13: iload_3
      14: goto          22
      17: aload         4
      19: invokestatic  #26                 // Method java/lang/Integer.parseInt:(Ljava/lang/String;)I
      22: ireturn
      23: astore        5
      25: new           #21                 // class org/apache/solr/common/SolrException
      28: dup
      29: getstatic     #22                 // Field org/apache/solr/common/SolrException$ErrorCode.BAD_REQUEST:Lorg/apache/solr/common/SolrException$ErrorCode;
      32: aload         5
      34: invokevirtual #23                 // Method java/lang/Exception.getMessage:()Ljava/lang/String;
      37: aload         5
      39: invokespecial #24                 // Method org/apache/solr/common/SolrException."<init>":(Lorg/apache/solr/common/SolrException$ErrorCode;Ljava/lang/String;Ljava/lang/Throwable;)V
      42: athrow
    Exception table:
       from    to  target type
           8    22    23   Class java/lang/Exception

  public java.lang.Float getFloat(java.lang.String);
    Code:
       0: aload_0
       1: aload_1
       2: invokevirtual #2                  // Method get:(Ljava/lang/String;)Ljava/lang/String;
       5: astore_2
       6: aload_2
       7: ifnonnull     14
      10: aconst_null
      11: goto          18
      14: aload_2
      15: invokestatic  #29                 // Method java/lang/Float.valueOf:(Ljava/lang/String;)Ljava/lang/Float;
      18: areturn
      19: astore_3
      20: new           #21                 // class org/apache/solr/common/SolrException
      23: dup
      24: getstatic     #22                 // Field org/apache/solr/common/SolrException$ErrorCode.BAD_REQUEST:Lorg/apache/solr/common/SolrException$ErrorCode;
      27: aload_3
      28: invokevirtual #23                 // Method java/lang/Exception.getMessage:()Ljava/lang/String;
      31: aload_3
      32: invokespecial #24                 // Method org/apache/solr/common/SolrException."<init>":(Lorg/apache/solr/common/SolrException$ErrorCode;Ljava/lang/String;Ljava/lang/Throwable;)V
      35: athrow
    Exception table:
       from    to  target type
           6    18    19   Class java/lang/Exception

  public float getFloat(java.lang.String, float);
    Code:
       0: aload_0
       1: aload_1
       2: invokevirtual #2                  // Method get:(Ljava/lang/String;)Ljava/lang/String;
       5: astore_3
       6: aload_3
       7: ifnonnull     14
      10: fload_2
      11: goto          18
      14: aload_3
      15: invokestatic  #30                 // Method java/lang/Float.parseFloat:(Ljava/lang/String;)F
      18: freturn
      19: astore        4
      21: new           #21                 // class org/apache/solr/common/SolrException
      24: dup
      25: getstatic     #22                 // Field org/apache/solr/common/SolrException$ErrorCode.BAD_REQUEST:Lorg/apache/solr/common/SolrException$ErrorCode;
      28: aload         4
      30: invokevirtual #23                 // Method java/lang/Exception.getMessage:()Ljava/lang/String;
      33: aload         4
      35: invokespecial #24                 // Method org/apache/solr/common/SolrException."<init>":(Lorg/apache/solr/common/SolrException$ErrorCode;Ljava/lang/String;Ljava/lang/Throwable;)V
      38: athrow
    Exception table:
       from    to  target type
           6    18    19   Class java/lang/Exception

  public java.lang.Double getDouble(java.lang.String);
    Code:
       0: aload_0
       1: aload_1
       2: invokevirtual #2                  // Method get:(Ljava/lang/String;)Ljava/lang/String;
       5: astore_2
       6: aload_2
       7: ifnonnull     14
      10: aconst_null
      11: goto          18
      14: aload_2
      15: invokestatic  #31                 // Method java/lang/Double.valueOf:(Ljava/lang/String;)Ljava/lang/Double;
      18: areturn
      19: astore_3
      20: new           #21                 // class org/apache/solr/common/SolrException
      23: dup
      24: getstatic     #22                 // Field org/apache/solr/common/SolrException$ErrorCode.BAD_REQUEST:Lorg/apache/solr/common/SolrException$ErrorCode;
      27: aload_3
      28: invokevirtual #23                 // Method java/lang/Exception.getMessage:()Ljava/lang/String;
      31: aload_3
      32: invokespecial #24                 // Method org/apache/solr/common/SolrException."<init>":(Lorg/apache/solr/common/SolrException$ErrorCode;Ljava/lang/String;Ljava/lang/Throwable;)V
      35: athrow
    Exception table:
       from    to  target type
           6    18    19   Class java/lang/Exception

  public double getDouble(java.lang.String, double);
    Code:
       0: aload_0
       1: aload_1
       2: invokevirtual #2                  // Method get:(Ljava/lang/String;)Ljava/lang/String;
       5: astore        4
       7: aload         4
       9: ifnonnull     16
      12: dload_2
      13: goto          21
      16: aload         4
      18: invokestatic  #32                 // Method java/lang/Double.parseDouble:(Ljava/lang/String;)D
      21: dreturn
      22: astore        5
      24: new           #21                 // class org/apache/solr/common/SolrException
      27: dup
      28: getstatic     #22                 // Field org/apache/solr/common/SolrException$ErrorCode.BAD_REQUEST:Lorg/apache/solr/common/SolrException$ErrorCode;
      31: aload         5
      33: invokevirtual #23                 // Method java/lang/Exception.getMessage:()Ljava/lang/String;
      36: aload         5
      38: invokespecial #24                 // Method org/apache/solr/common/SolrException."<init>":(Lorg/apache/solr/common/SolrException$ErrorCode;Ljava/lang/String;Ljava/lang/Throwable;)V
      41: athrow
    Exception table:
       from    to  target type
           7    21    22   Class java/lang/Exception

  public java.lang.Float getFieldFloat(java.lang.String, java.lang.String);
    Code:
       0: aload_0
       1: aload_1
       2: aload_2
       3: invokevirtual #17                 // Method getFieldParam:(Ljava/lang/String;Ljava/lang/String;)Ljava/lang/String;
       6: astore_3
       7: aload_3
       8: ifnonnull     15
      11: aconst_null
      12: goto          19
      15: aload_3
      16: invokestatic  #29                 // Method java/lang/Float.valueOf:(Ljava/lang/String;)Ljava/lang/Float;
      19: areturn
      20: astore        4
      22: new           #21                 // class org/apache/solr/common/SolrException
      25: dup
      26: getstatic     #22                 // Field org/apache/solr/common/SolrException$ErrorCode.BAD_REQUEST:Lorg/apache/solr/common/SolrException$ErrorCode;
      29: aload         4
      31: invokevirtual #23                 // Method java/lang/Exception.getMessage:()Ljava/lang/String;
      34: aload         4
      36: invokespecial #24                 // Method org/apache/solr/common/SolrException."<init>":(Lorg/apache/solr/common/SolrException$ErrorCode;Ljava/lang/String;Ljava/lang/Throwable;)V
      39: athrow
    Exception table:
       from    to  target type
           7    19    20   Class java/lang/Exception

  public float getPrimitiveFieldFloat(java.lang.String, java.lang.String);
    Code:
       0: aload_0
       1: aload_1
       2: aload_2
       3: fconst_0
       4: invokevirtual #33                 // Method getFieldFloat:(Ljava/lang/String;Ljava/lang/String;F)F
       7: freturn

  public float getFieldFloat(java.lang.String, java.lang.String, float);
    Code:
       0: aload_0
       1: aload_1
       2: aload_2
       3: invokevirtual #17                 // Method getFieldParam:(Ljava/lang/String;Ljava/lang/String;)Ljava/lang/String;
       6: astore        4
       8: aload         4
      10: ifnonnull     17
      13: fload_3
      14: goto          22
      17: aload         4
      19: invokestatic  #30                 // Method java/lang/Float.parseFloat:(Ljava/lang/String;)F
      22: freturn
      23: astore        5
      25: new           #21                 // class org/apache/solr/common/SolrException
      28: dup
      29: getstatic     #22                 // Field org/apache/solr/common/SolrException$ErrorCode.BAD_REQUEST:Lorg/apache/solr/common/SolrException$ErrorCode;
      32: aload         5
      34: invokevirtual #23                 // Method java/lang/Exception.getMessage:()Ljava/lang/String;
      37: aload         5
      39: invokespecial #24                 // Method org/apache/solr/common/SolrException."<init>":(Lorg/apache/solr/common/SolrException$ErrorCode;Ljava/lang/String;Ljava/lang/Throwable;)V
      42: athrow
    Exception table:
       from    to  target type
           8    22    23   Class java/lang/Exception

  public java.lang.Double getFieldDouble(java.lang.String, java.lang.String);
    Code:
       0: aload_0
       1: aload_1
       2: aload_2
       3: invokevirtual #17                 // Method getFieldParam:(Ljava/lang/String;Ljava/lang/String;)Ljava/lang/String;
       6: astore_3
       7: aload_3
       8: ifnonnull     15
      11: aconst_null
      12: goto          19
      15: aload_3
      16: invokestatic  #31                 // Method java/lang/Double.valueOf:(Ljava/lang/String;)Ljava/lang/Double;
      19: areturn
      20: astore        4
      22: new           #21                 // class org/apache/solr/common/SolrException
      25: dup
      26: getstatic     #22                 // Field org/apache/solr/common/SolrException$ErrorCode.BAD_REQUEST:Lorg/apache/solr/common/SolrException$ErrorCode;
      29: aload         4
      31: invokevirtual #23                 // Method java/lang/Exception.getMessage:()Ljava/lang/String;
      34: aload         4
      36: invokespecial #24                 // Method org/apache/solr/common/SolrException."<init>":(Lorg/apache/solr/common/SolrException$ErrorCode;Ljava/lang/String;Ljava/lang/Throwable;)V
      39: athrow
    Exception table:
       from    to  target type
           7    19    20   Class java/lang/Exception

  public double getFieldDouble(java.lang.String, java.lang.String, double);
    Code:
       0: aload_0
       1: aload_1
       2: aload_2
       3: invokevirtual #17                 // Method getFieldParam:(Ljava/lang/String;Ljava/lang/String;)Ljava/lang/String;
       6: astore        5
       8: aload         5
      10: ifnonnull     17
      13: dload_3
      14: goto          22
      17: aload         5
      19: invokestatic  #32                 // Method java/lang/Double.parseDouble:(Ljava/lang/String;)D
      22: dreturn
      23: astore        6
      25: new           #21                 // class org/apache/solr/common/SolrException
      28: dup
      29: getstatic     #22                 // Field org/apache/solr/common/SolrException$ErrorCode.BAD_REQUEST:Lorg/apache/solr/common/SolrException$ErrorCode;
      32: aload         6
      34: invokevirtual #23                 // Method java/lang/Exception.getMessage:()Ljava/lang/String;
      37: aload         6
      39: invokespecial #24                 // Method org/apache/solr/common/SolrException."<init>":(Lorg/apache/solr/common/SolrException$ErrorCode;Ljava/lang/String;Ljava/lang/Throwable;)V
      42: athrow
    Exception table:
       from    to  target type
           8    22    23   Class java/lang/Exception

  public static org.apache.solr.common.params.SolrParams wrapDefaults(org.apache.solr.common.params.SolrParams, org.apache.solr.common.params.SolrParams);
    Code:
       0: aload_0
       1: ifnonnull     6
       4: aload_1
       5: areturn
       6: aload_1
       7: ifnonnull     12
      10: aload_0
      11: areturn
      12: new           #34                 // class org/apache/solr/common/params/DefaultSolrParams
      15: dup
      16: aload_0
      17: aload_1
      18: invokespecial #35                 // Method org/apache/solr/common/params/DefaultSolrParams."<init>":(Lorg/apache/solr/common/params/SolrParams;Lorg/apache/solr/common/params/SolrParams;)V
      21: areturn

  public static org.apache.solr.common.params.SolrParams wrapAppended(org.apache.solr.common.params.SolrParams, org.apache.solr.common.params.SolrParams);
    Code:
       0: aload_0
       1: ifnonnull     6
       4: aload_1
       5: areturn
       6: aload_1
       7: ifnonnull     12
      10: aload_0
      11: areturn
      12: aload_0
      13: aload_1
      14: invokestatic  #36                 // Method org/apache/solr/common/params/AppendedSolrParams.wrapAppended:(Lorg/apache/solr/common/params/SolrParams;Lorg/apache/solr/common/params/SolrParams;)Lorg/apache/solr/common/params/AppendedSolrParams;
      17: areturn

  public static java.util.Map<java.lang.String, java.lang.String> toMap(org.apache.solr.common.util.NamedList);
    Code:
       0: new           #37                 // class java/util/HashMap
       3: dup
       4: invokespecial #38                 // Method java/util/HashMap."<init>":()V
       7: astore_1
       8: iconst_0
       9: istore_2
      10: iload_2
      11: aload_0
      12: invokevirtual #39                 // Method org/apache/solr/common/util/NamedList.size:()I
      15: if_icmpge     42
      18: aload_1
      19: aload_0
      20: iload_2
      21: invokevirtual #40                 // Method org/apache/solr/common/util/NamedList.getName:(I)Ljava/lang/String;
      24: aload_0
      25: iload_2
      26: invokevirtual #41                 // Method org/apache/solr/common/util/NamedList.getVal:(I)Ljava/lang/Object;
      29: invokevirtual #42                 // Method java/lang/Object.toString:()Ljava/lang/String;
      32: invokevirtual #43                 // Method java/util/HashMap.put:(Ljava/lang/Object;Ljava/lang/Object;)Ljava/lang/Object;
      35: pop
      36: iinc          2, 1
      39: goto          10
      42: aload_1
      43: areturn

  public static java.util.Map<java.lang.String, java.lang.String[]> toMultiMap(org.apache.solr.common.util.NamedList);
    Code:
       0: new           #37                 // class java/util/HashMap
       3: dup
       4: invokespecial #38                 // Method java/util/HashMap."<init>":()V
       7: astore_1
       8: iconst_0
       9: istore_2
      10: iload_2
      11: aload_0
      12: invokevirtual #39                 // Method org/apache/solr/common/util/NamedList.size:()I
      15: if_icmpge     162
      18: aload_0
      19: iload_2
      20: invokevirtual #40                 // Method org/apache/solr/common/util/NamedList.getName:(I)Ljava/lang/String;
      23: astore_3
      24: aload_0
      25: iload_2
      26: invokevirtual #41                 // Method org/apache/solr/common/util/NamedList.getVal:(I)Ljava/lang/Object;
      29: astore        4
      31: aload         4
      33: instanceof    #44                 // class "[Ljava/lang/String;"
      36: ifeq          55
      39: aload_3
      40: aload         4
      42: checkcast     #44                 // class "[Ljava/lang/String;"
      45: checkcast     #44                 // class "[Ljava/lang/String;"
      48: aload_1
      49: invokestatic  #45                 // Method org/apache/solr/common/params/MultiMapSolrParams.addParam:(Ljava/lang/String;[Ljava/lang/String;Ljava/util/Map;)V
      52: goto          156
      55: aload         4
      57: instanceof    #46                 // class java/util/List
      60: ifeq          146
      63: aload         4
      65: checkcast     #46                 // class java/util/List
      68: astore        5
      70: aload         5
      72: invokeinterface #47,  1           // InterfaceMethod java/util/List.size:()I
      77: anewarray     #48                 // class java/lang/String
      80: astore        6
      82: iconst_0
      83: istore        7
      85: iload         7
      87: aload         5
      89: invokeinterface #47,  1           // InterfaceMethod java/util/List.size:()I
      94: if_icmpge     136
      97: aload         6
      99: iload         7
     101: aload         5
     103: iload         7
     105: invokeinterface #49,  2           // InterfaceMethod java/util/List.get:(I)Ljava/lang/Object;
     110: ifnonnull     117
     113: aconst_null
     114: goto          129
     117: aload         5
     119: iload         7
     121: invokeinterface #49,  2           // InterfaceMethod java/util/List.get:(I)Ljava/lang/Object;
     126: invokestatic  #50                 // Method java/lang/String.valueOf:(Ljava/lang/Object;)Ljava/lang/String;
     129: aastore
     130: iinc          7, 1
     133: goto          85
     136: aload_3
     137: aload         6
     139: aload_1
     140: invokestatic  #45                 // Method org/apache/solr/common/params/MultiMapSolrParams.addParam:(Ljava/lang/String;[Ljava/lang/String;Ljava/util/Map;)V
     143: goto          156
     146: aload_3
     147: aload         4
     149: invokevirtual #42                 // Method java/lang/Object.toString:()Ljava/lang/String;
     152: aload_1
     153: invokestatic  #51                 // Method org/apache/solr/common/params/MultiMapSolrParams.addParam:(Ljava/lang/String;Ljava/lang/String;Ljava/util/Map;)V
     156: iinc          2, 1
     159: goto          10
     162: aload_1
     163: areturn

  public static org.apache.solr.common.params.SolrParams toSolrParams(org.apache.solr.common.util.NamedList);
    Code:
       0: new           #52                 // class org/apache/solr/common/params/MultiMapSolrParams
       3: dup
       4: aload_0
       5: invokestatic  #53                 // Method toMultiMap:(Lorg/apache/solr/common/util/NamedList;)Ljava/util/Map;
       8: invokespecial #54                 // Method org/apache/solr/common/params/MultiMapSolrParams."<init>":(Ljava/util/Map;)V
      11: areturn

  public org.apache.solr.common.params.SolrParams toFilteredSolrParams(java.util.List<java.lang.String>);
    Code:
       0: new           #55                 // class org/apache/solr/common/util/NamedList
       3: dup
       4: invokespecial #56                 // Method org/apache/solr/common/util/NamedList."<init>":()V
       7: astore_2
       8: aload_0
       9: invokevirtual #57                 // Method getParameterNamesIterator:()Ljava/util/Iterator;
      12: astore_3
      13: aload_3
      14: invokeinterface #58,  1           // InterfaceMethod java/util/Iterator.hasNext:()Z
      19: ifeq          95
      22: aload_3
      23: invokeinterface #59,  1           // InterfaceMethod java/util/Iterator.next:()Ljava/lang/Object;
      28: checkcast     #48                 // class java/lang/String
      31: astore        4
      33: aload_1
      34: aload         4
      36: invokeinterface #60,  2           // InterfaceMethod java/util/List.contains:(Ljava/lang/Object;)Z
      41: ifeq          92
      44: aload_0
      45: aload         4
      47: invokevirtual #13                 // Method getParams:(Ljava/lang/String;)[Ljava/lang/String;
      50: astore        5
      52: aload         5
      54: astore        6
      56: aload         6
      58: arraylength
      59: istore        7
      61: iconst_0
      62: istore        8
      64: iload         8
      66: iload         7
      68: if_icmpge     92
      71: aload         6
      73: iload         8
      75: aaload
      76: astore        9
      78: aload_2
      79: aload         4
      81: aload         9
      83: invokevirtual #61                 // Method org/apache/solr/common/util/NamedList.add:(Ljava/lang/String;Ljava/lang/Object;)V
      86: iinc          8, 1
      89: goto          64
      92: goto          13
      95: aload_2
      96: invokestatic  #62                 // Method toSolrParams:(Lorg/apache/solr/common/util/NamedList;)Lorg/apache/solr/common/params/SolrParams;
      99: areturn

  public org.apache.solr.common.util.NamedList<java.lang.Object> toNamedList();
    Code:
       0: new           #63                 // class org/apache/solr/common/util/SimpleOrderedMap
       3: dup
       4: invokespecial #64                 // Method org/apache/solr/common/util/SimpleOrderedMap."<init>":()V
       7: astore_1
       8: aload_0
       9: invokevirtual #57                 // Method getParameterNamesIterator:()Ljava/util/Iterator;
      12: astore_2
      13: aload_2
      14: invokeinterface #58,  1           // InterfaceMethod java/util/Iterator.hasNext:()Z
      19: ifeq          68
      22: aload_2
      23: invokeinterface #59,  1           // InterfaceMethod java/util/Iterator.next:()Ljava/lang/Object;
      28: checkcast     #48                 // class java/lang/String
      31: astore_3
      32: aload_0
      33: aload_3
      34: invokevirtual #13                 // Method getParams:(Ljava/lang/String;)[Ljava/lang/String;
      37: astore        4
      39: aload         4
      41: arraylength
      42: iconst_1
      43: if_icmpne     58
      46: aload_1
      47: aload_3
      48: aload         4
      50: iconst_0
      51: aaload
      52: invokevirtual #65                 // Method org/apache/solr/common/util/SimpleOrderedMap.add:(Ljava/lang/String;Ljava/lang/Object;)V
      55: goto          65
      58: aload_1
      59: aload_3
      60: aload         4
      62: invokevirtual #65                 // Method org/apache/solr/common/util/SimpleOrderedMap.add:(Ljava/lang/String;Ljava/lang/Object;)V
      65: goto          13
      68: aload_1
      69: areturn

  public java.util.Map<java.lang.String, java.lang.Object> getAll(java.util.Map<java.lang.String, java.lang.Object>, java.util.Collection<java.lang.String>);
    Code:
       0: aload_1
       1: ifnonnull     12
       4: new           #66                 // class java/util/LinkedHashMap
       7: dup
       8: invokespecial #67                 // Method java/util/LinkedHashMap."<init>":()V
      11: astore_1
      12: aload_2
      13: invokeinterface #68,  1           // InterfaceMethod java/util/Collection.iterator:()Ljava/util/Iterator;
      18: astore_3
      19: aload_3
      20: invokeinterface #58,  1           // InterfaceMethod java/util/Iterator.hasNext:()Z
      25: ifeq          95
      28: aload_3
      29: invokeinterface #59,  1           // InterfaceMethod java/util/Iterator.next:()Ljava/lang/Object;
      34: checkcast     #48                 // class java/lang/String
      37: astore        4
      39: aload_0
      40: aload         4
      42: invokevirtual #13                 // Method getParams:(Ljava/lang/String;)[Ljava/lang/String;
      45: astore        5
      47: aload         5
      49: ifnull        92
      52: aload         5
      54: arraylength
      55: ifle          92
      58: aload         5
      60: arraylength
      61: iconst_1
      62: if_icmpne     81
      65: aload_1
      66: aload         4
      68: aload         5
      70: iconst_0
      71: aaload
      72: invokeinterface #69,  3           // InterfaceMethod java/util/Map.put:(Ljava/lang/Object;Ljava/lang/Object;)Ljava/lang/Object;
      77: pop
      78: goto          92
      81: aload_1
      82: aload         4
      84: aload         5
      86: invokeinterface #69,  3           // InterfaceMethod java/util/Map.put:(Ljava/lang/Object;Ljava/lang/Object;)Ljava/lang/Object;
      91: pop
      92: goto          19
      95: aload_1
      96: areturn

  public java.util.Map<java.lang.String, java.lang.Object> getAll(java.util.Map<java.lang.String, java.lang.Object>, java.lang.String...);
    Code:
       0: aload_0
       1: aload_1
       2: aload_2
       3: ifnonnull     12
       6: invokestatic  #70                 // Method java/util/Collections.emptyList:()Ljava/util/List;
       9: goto          16
      12: aload_2
      13: invokestatic  #71                 // Method java/util/Arrays.asList:([Ljava/lang/Object;)Ljava/util/List;
      16: invokevirtual #72                 // Method getAll:(Ljava/util/Map;Ljava/util/Collection;)Ljava/util/Map;
      19: areturn

  public java.lang.String toQueryString();
    Code:
       0: getstatic     #73                 // Field java/nio/charset/StandardCharsets.UTF_8:Ljava/nio/charset/Charset;
       3: invokevirtual #74                 // Method java/nio/charset/Charset.name:()Ljava/lang/String;
       6: astore_1
       7: new           #5                  // class java/lang/StringBuilder
      10: dup
      11: sipush        128
      14: invokespecial #75                 // Method java/lang/StringBuilder."<init>":(I)V
      17: astore_2
      18: iconst_1
      19: istore_3
      20: aload_0
      21: invokevirtual #57                 // Method getParameterNamesIterator:()Ljava/util/Iterator;
      24: astore        4
      26: aload         4
      28: invokeinterface #58,  1           // InterfaceMethod java/util/Iterator.hasNext:()Z
      33: ifeq          132
      36: aload         4
      38: invokeinterface #59,  1           // InterfaceMethod java/util/Iterator.next:()Ljava/lang/Object;
      43: checkcast     #48                 // class java/lang/String
      46: astore        5
      48: aload         5
      50: aload_1
      51: invokestatic  #76                 // Method java/net/URLEncoder.encode:(Ljava/lang/String;Ljava/lang/String;)Ljava/lang/String;
      54: astore        6
      56: aload_0
      57: aload         5
      59: invokevirtual #13                 // Method getParams:(Ljava/lang/String;)[Ljava/lang/String;
      62: astore        7
      64: aload         7
      66: arraylength
      67: istore        8
      69: iconst_0
      70: istore        9
      72: iload         9
      74: iload         8
      76: if_icmpge     129
      79: aload         7
      81: iload         9
      83: aaload
      84: astore        10
      86: aload_2
      87: iload_3
      88: ifeq          96
      91: bipush        63
      93: goto          98
      96: bipush        38
      98: invokevirtual #9                  // Method java/lang/StringBuilder.append:(C)Ljava/lang/StringBuilder;
     101: aload         6
     103: invokevirtual #8                  // Method java/lang/StringBuilder.append:(Ljava/lang/String;)Ljava/lang/StringBuilder;
     106: bipush        61
     108: invokevirtual #9                  // Method java/lang/StringBuilder.append:(C)Ljava/lang/StringBuilder;
     111: aload         10
     113: aload_1
     114: invokestatic  #76                 // Method java/net/URLEncoder.encode:(Ljava/lang/String;Ljava/lang/String;)Ljava/lang/String;
     117: invokevirtual #8                  // Method java/lang/StringBuilder.append:(Ljava/lang/String;)Ljava/lang/StringBuilder;
     120: pop
     121: iconst_0
     122: istore_3
     123: iinc          9, 1
     126: goto          72
     129: goto          26
     132: aload_2
     133: invokevirtual #10                 // Method java/lang/StringBuilder.toString:()Ljava/lang/String;
     136: areturn
     137: astore_1
     138: new           #78                 // class java/lang/AssertionError
     141: dup
     142: aload_1
     143: invokespecial #79                 // Method java/lang/AssertionError."<init>":(Ljava/lang/Object;)V
     146: athrow
    Exception table:
       from    to  target type
           0   136   137   Class java/io/UnsupportedEncodingException

  public java.lang.String toString();
    Code:
       0: new           #5                  // class java/lang/StringBuilder
       3: dup
       4: sipush        128
       7: invokespecial #75                 // Method java/lang/StringBuilder."<init>":(I)V
      10: astore_1
      11: iconst_1
      12: istore_2
      13: aload_0
      14: invokevirtual #57                 // Method getParameterNamesIterator:()Ljava/util/Iterator;
      17: astore_3
      18: aload_3
      19: invokeinterface #58,  1           // InterfaceMethod java/util/Iterator.hasNext:()Z
      24: ifeq          109
      27: aload_3
      28: invokeinterface #59,  1           // InterfaceMethod java/util/Iterator.next:()Ljava/lang/Object;
      33: checkcast     #48                 // class java/lang/String
      36: astore        4
      38: aload_0
      39: aload         4
      41: invokevirtual #13                 // Method getParams:(Ljava/lang/String;)[Ljava/lang/String;
      44: astore        5
      46: aload         5
      48: arraylength
      49: istore        6
      51: iconst_0
      52: istore        7
      54: iload         7
      56: iload         6
      58: if_icmpge     106
      61: aload         5
      63: iload         7
      65: aaload
      66: astore        8
      68: iload_2
      69: ifne          79
      72: aload_1
      73: bipush        38
      75: invokevirtual #9                  // Method java/lang/StringBuilder.append:(C)Ljava/lang/StringBuilder;
      78: pop
      79: iconst_0
      80: istore_2
      81: aload_1
      82: aload         4
      84: invokestatic  #80                 // Method org/apache/solr/common/util/StrUtils.partialURLEncodeVal:(Ljava/lang/Appendable;Ljava/lang/String;)V
      87: aload_1
      88: bipush        61
      90: invokevirtual #9                  // Method java/lang/StringBuilder.append:(C)Ljava/lang/StringBuilder;
      93: pop
      94: aload_1
      95: aload         8
      97: invokestatic  #80                 // Method org/apache/solr/common/util/StrUtils.partialURLEncodeVal:(Ljava/lang/Appendable;Ljava/lang/String;)V
     100: iinc          7, 1
     103: goto          54
     106: goto          18
     109: aload_1
     110: invokevirtual #10                 // Method java/lang/StringBuilder.toString:()Ljava/lang/String;
     113: areturn
     114: astore_2
     115: new           #78                 // class java/lang/AssertionError
     118: dup
     119: aload_2
     120: invokespecial #79                 // Method java/lang/AssertionError."<init>":(Ljava/lang/Object;)V
     123: athrow
    Exception table:
       from    to  target type
          11   113   114   Class java/io/IOException

  public java.util.Map toMap(java.util.Map<java.lang.String, java.lang.Object>);
    Code:
       0: aload_0
       1: invokevirtual #82                 // Method toNamedList:()Lorg/apache/solr/common/util/NamedList;
       4: aload_1
       5: invokedynamic #83,  0             // InvokeDynamic #0:accept:(Ljava/util/Map;)Ljava/util/function/BiConsumer;
      10: invokevirtual #84                 // Method org/apache/solr/common/util/NamedList.forEach:(Ljava/util/function/BiConsumer;)V
      13: aload_1
      14: areturn

  private static void lambda$toMap$0(java.util.Map, java.lang.String, java.lang.Object);
    Code:
       0: aload_2
       1: ifnull        13
       4: ldc           #85                 // String
       6: aload_2
       7: invokevirtual #86                 // Method java/lang/String.equals:(Ljava/lang/Object;)Z
      10: ifeq          14
      13: return
      14: aload_0
      15: aload_1
      16: aload_2
      17: invokeinterface #69,  3           // InterfaceMethod java/util/Map.put:(Ljava/lang/Object;Ljava/lang/Object;)Ljava/lang/Object;
      22: pop
      23: return
}
