Compiled from "DeleteObjectRequest.java"
final class software.amazon.awssdk.services.s3.model.DeleteObjectRequest$BuilderImpl extends software.amazon.awssdk.services.s3.model.S3Request$BuilderImpl implements software.amazon.awssdk.services.s3.model.DeleteObjectRequest$Builder {
  private java.lang.String bucket;

  private java.lang.String key;

  private java.lang.String mfa;

  private java.lang.String versionId;

  private java.lang.String requestPayer;

  private java.lang.Boolean bypassGovernanceRetention;

  private java.lang.String expectedBucketOwner;

  private software.amazon.awssdk.services.s3.model.DeleteObjectRequest$BuilderImpl();
    Code:
       0: aload_0
       1: invokespecial #10                 // Method software/amazon/awssdk/services/s3/model/S3Request$BuilderImpl."<init>":()V
       4: return

  private software.amazon.awssdk.services.s3.model.DeleteObjectRequest$BuilderImpl(software.amazon.awssdk.services.s3.model.DeleteObjectRequest);
    Code:
       0: aload_0
       1: aload_1
       2: invokespecial #11                 // Method software/amazon/awssdk/services/s3/model/S3Request$BuilderImpl."<init>":(Lsoftware/amazon/awssdk/services/s3/model/S3Request;)V
       5: aload_0
       6: aload_1
       7: invokestatic  #12                 // Method software/amazon/awssdk/services/s3/model/DeleteObjectRequest.access$900:(Lsoftware/amazon/awssdk/services/s3/model/DeleteObjectRequest;)Ljava/lang/String;
      10: invokevirtual #13                 // Method bucket:(Ljava/lang/String;)Lsoftware/amazon/awssdk/services/s3/model/DeleteObjectRequest$Builder;
      13: pop
      14: aload_0
      15: aload_1
      16: invokestatic  #14                 // Method software/amazon/awssdk/services/s3/model/DeleteObjectRequest.access$1000:(Lsoftware/amazon/awssdk/services/s3/model/DeleteObjectRequest;)Ljava/lang/String;
      19: invokevirtual #15                 // Method key:(Ljava/lang/String;)Lsoftware/amazon/awssdk/services/s3/model/DeleteObjectRequest$Builder;
      22: pop
      23: aload_0
      24: aload_1
      25: invokestatic  #16                 // Method software/amazon/awssdk/services/s3/model/DeleteObjectRequest.access$1100:(Lsoftware/amazon/awssdk/services/s3/model/DeleteObjectRequest;)Ljava/lang/String;
      28: invokevirtual #17                 // Method mfa:(Ljava/lang/String;)Lsoftware/amazon/awssdk/services/s3/model/DeleteObjectRequest$Builder;
      31: pop
      32: aload_0
      33: aload_1
      34: invokestatic  #18                 // Method software/amazon/awssdk/services/s3/model/DeleteObjectRequest.access$1200:(Lsoftware/amazon/awssdk/services/s3/model/DeleteObjectRequest;)Ljava/lang/String;
      37: invokevirtual #19                 // Method versionId:(Ljava/lang/String;)Lsoftware/amazon/awssdk/services/s3/model/DeleteObjectRequest$Builder;
      40: pop
      41: aload_0
      42: aload_1
      43: invokestatic  #20                 // Method software/amazon/awssdk/services/s3/model/DeleteObjectRequest.access$1300:(Lsoftware/amazon/awssdk/services/s3/model/DeleteObjectRequest;)Ljava/lang/String;
      46: invokevirtual #21                 // Method requestPayer:(Ljava/lang/String;)Lsoftware/amazon/awssdk/services/s3/model/DeleteObjectRequest$Builder;
      49: pop
      50: aload_0
      51: aload_1
      52: invokestatic  #22                 // Method software/amazon/awssdk/services/s3/model/DeleteObjectRequest.access$1400:(Lsoftware/amazon/awssdk/services/s3/model/DeleteObjectRequest;)Ljava/lang/Boolean;
      55: invokevirtual #23                 // Method bypassGovernanceRetention:(Ljava/lang/Boolean;)Lsoftware/amazon/awssdk/services/s3/model/DeleteObjectRequest$Builder;
      58: pop
      59: aload_0
      60: aload_1
      61: invokestatic  #24                 // Method software/amazon/awssdk/services/s3/model/DeleteObjectRequest.access$1500:(Lsoftware/amazon/awssdk/services/s3/model/DeleteObjectRequest;)Ljava/lang/String;
      64: invokevirtual #25                 // Method expectedBucketOwner:(Ljava/lang/String;)Lsoftware/amazon/awssdk/services/s3/model/DeleteObjectRequest$Builder;
      67: pop
      68: return

  public final java.lang.String getBucket();
    Code:
       0: aload_0
       1: getfield      #9                  // Field bucket:Ljava/lang/String;
       4: areturn

  public final void setBucket(java.lang.String);
    Code:
       0: aload_0
       1: aload_1
       2: putfield      #9                  // Field bucket:Ljava/lang/String;
       5: return

  public final software.amazon.awssdk.services.s3.model.DeleteObjectRequest$Builder bucket(java.lang.String);
    Code:
       0: aload_0
       1: aload_1
       2: putfield      #9                  // Field bucket:Ljava/lang/String;
       5: aload_0
       6: areturn

  public final java.lang.String getKey();
    Code:
       0: aload_0
       1: getfield      #8                  // Field key:Ljava/lang/String;
       4: areturn

  public final void setKey(java.lang.String);
    Code:
       0: aload_0
       1: aload_1
       2: putfield      #8                  // Field key:Ljava/lang/String;
       5: return

  public final software.amazon.awssdk.services.s3.model.DeleteObjectRequest$Builder key(java.lang.String);
    Code:
       0: aload_0
       1: aload_1
       2: putfield      #8                  // Field key:Ljava/lang/String;
       5: aload_0
       6: areturn

  public final java.lang.String getMfa();
    Code:
       0: aload_0
       1: getfield      #7                  // Field mfa:Ljava/lang/String;
       4: areturn

  public final void setMfa(java.lang.String);
    Code:
       0: aload_0
       1: aload_1
       2: putfield      #7                  // Field mfa:Ljava/lang/String;
       5: return

  public final software.amazon.awssdk.services.s3.model.DeleteObjectRequest$Builder mfa(java.lang.String);
    Code:
       0: aload_0
       1: aload_1
       2: putfield      #7                  // Field mfa:Ljava/lang/String;
       5: aload_0
       6: areturn

  public final java.lang.String getVersionId();
    Code:
       0: aload_0
       1: getfield      #6                  // Field versionId:Ljava/lang/String;
       4: areturn

  public final void setVersionId(java.lang.String);
    Code:
       0: aload_0
       1: aload_1
       2: putfield      #6                  // Field versionId:Ljava/lang/String;
       5: return

  public final software.amazon.awssdk.services.s3.model.DeleteObjectRequest$Builder versionId(java.lang.String);
    Code:
       0: aload_0
       1: aload_1
       2: putfield      #6                  // Field versionId:Ljava/lang/String;
       5: aload_0
       6: areturn

  public final java.lang.String getRequestPayer();
    Code:
       0: aload_0
       1: getfield      #5                  // Field requestPayer:Ljava/lang/String;
       4: areturn

  public final void setRequestPayer(java.lang.String);
    Code:
       0: aload_0
       1: aload_1
       2: putfield      #5                  // Field requestPayer:Ljava/lang/String;
       5: return

  public final software.amazon.awssdk.services.s3.model.DeleteObjectRequest$Builder requestPayer(java.lang.String);
    Code:
       0: aload_0
       1: aload_1
       2: putfield      #5                  // Field requestPayer:Ljava/lang/String;
       5: aload_0
       6: areturn

  public final software.amazon.awssdk.services.s3.model.DeleteObjectRequest$Builder requestPayer(software.amazon.awssdk.services.s3.model.RequestPayer);
    Code:
       0: aload_0
       1: aload_1
       2: ifnonnull     9
       5: aconst_null
       6: goto          13
       9: aload_1
      10: invokevirtual #26                 // Method software/amazon/awssdk/services/s3/model/RequestPayer.toString:()Ljava/lang/String;
      13: invokevirtual #21                 // Method requestPayer:(Ljava/lang/String;)Lsoftware/amazon/awssdk/services/s3/model/DeleteObjectRequest$Builder;
      16: pop
      17: aload_0
      18: areturn

  public final java.lang.Boolean getBypassGovernanceRetention();
    Code:
       0: aload_0
       1: getfield      #4                  // Field bypassGovernanceRetention:Ljava/lang/Boolean;
       4: areturn

  public final void setBypassGovernanceRetention(java.lang.Boolean);
    Code:
       0: aload_0
       1: aload_1
       2: putfield      #4                  // Field bypassGovernanceRetention:Ljava/lang/Boolean;
       5: return

  public final software.amazon.awssdk.services.s3.model.DeleteObjectRequest$Builder bypassGovernanceRetention(java.lang.Boolean);
    Code:
       0: aload_0
       1: aload_1
       2: putfield      #4                  // Field bypassGovernanceRetention:Ljava/lang/Boolean;
       5: aload_0
       6: areturn

  public final java.lang.String getExpectedBucketOwner();
    Code:
       0: aload_0
       1: getfield      #3                  // Field expectedBucketOwner:Ljava/lang/String;
       4: areturn

  public final void setExpectedBucketOwner(java.lang.String);
    Code:
       0: aload_0
       1: aload_1
       2: putfield      #3                  // Field expectedBucketOwner:Ljava/lang/String;
       5: return

  public final software.amazon.awssdk.services.s3.model.DeleteObjectRequest$Builder expectedBucketOwner(java.lang.String);
    Code:
       0: aload_0
       1: aload_1
       2: putfield      #3                  // Field expectedBucketOwner:Ljava/lang/String;
       5: aload_0
       6: areturn

  public software.amazon.awssdk.services.s3.model.DeleteObjectRequest$Builder overrideConfiguration(software.amazon.awssdk.awscore.AwsRequestOverrideConfiguration);
    Code:
       0: aload_0
       1: aload_1
       2: invokespecial #27                 // Method software/amazon/awssdk/services/s3/model/S3Request$BuilderImpl.overrideConfiguration:(Lsoftware/amazon/awssdk/awscore/AwsRequestOverrideConfiguration;)Lsoftware/amazon/awssdk/awscore/AwsRequest$Builder;
       5: pop
       6: aload_0
       7: areturn

  public software.amazon.awssdk.services.s3.model.DeleteObjectRequest$Builder overrideConfiguration(java.util.function.Consumer<software.amazon.awssdk.awscore.AwsRequestOverrideConfiguration$Builder>);
    Code:
       0: aload_0
       1: aload_1
       2: invokespecial #28                 // Method software/amazon/awssdk/services/s3/model/S3Request$BuilderImpl.overrideConfiguration:(Ljava/util/function/Consumer;)Lsoftware/amazon/awssdk/awscore/AwsRequest$Builder;
       5: pop
       6: aload_0
       7: areturn

  public software.amazon.awssdk.services.s3.model.DeleteObjectRequest build();
    Code:
       0: new           #29                 // class software/amazon/awssdk/services/s3/model/DeleteObjectRequest
       3: dup
       4: aload_0
       5: aconst_null
       6: invokespecial #30                 // Method software/amazon/awssdk/services/s3/model/DeleteObjectRequest."<init>":(Lsoftware/amazon/awssdk/services/s3/model/DeleteObjectRequest$BuilderImpl;Lsoftware/amazon/awssdk/services/s3/model/DeleteObjectRequest$1;)V
       9: areturn

  public java.util.List<software.amazon.awssdk.core.SdkField<?>> sdkFields();
    Code:
       0: invokestatic  #31                 // Method software/amazon/awssdk/services/s3/model/DeleteObjectRequest.access$1700:()Ljava/util/List;
       3: areturn

  public software.amazon.awssdk.services.s3.model.S3Request build();
    Code:
       0: aload_0
       1: invokevirtual #32                 // Method build:()Lsoftware/amazon/awssdk/services/s3/model/DeleteObjectRequest;
       4: areturn

  public software.amazon.awssdk.awscore.AwsRequest build();
    Code:
       0: aload_0
       1: invokevirtual #32                 // Method build:()Lsoftware/amazon/awssdk/services/s3/model/DeleteObjectRequest;
       4: areturn

  public software.amazon.awssdk.awscore.AwsRequest$Builder overrideConfiguration(java.util.function.Consumer);
    Code:
       0: aload_0
       1: aload_1
       2: invokevirtual #33                 // Method overrideConfiguration:(Ljava/util/function/Consumer;)Lsoftware/amazon/awssdk/services/s3/model/DeleteObjectRequest$Builder;
       5: areturn

  public software.amazon.awssdk.awscore.AwsRequest$Builder overrideConfiguration(software.amazon.awssdk.awscore.AwsRequestOverrideConfiguration);
    Code:
       0: aload_0
       1: aload_1
       2: invokevirtual #34                 // Method overrideConfiguration:(Lsoftware/amazon/awssdk/awscore/AwsRequestOverrideConfiguration;)Lsoftware/amazon/awssdk/services/s3/model/DeleteObjectRequest$Builder;
       5: areturn

  public software.amazon.awssdk.core.SdkRequest build();
    Code:
       0: aload_0
       1: invokevirtual #32                 // Method build:()Lsoftware/amazon/awssdk/services/s3/model/DeleteObjectRequest;
       4: areturn

  public java.lang.Object build();
    Code:
       0: aload_0
       1: invokevirtual #32                 // Method build:()Lsoftware/amazon/awssdk/services/s3/model/DeleteObjectRequest;
       4: areturn

  static java.lang.String access$000(software.amazon.awssdk.services.s3.model.DeleteObjectRequest$BuilderImpl);
    Code:
       0: aload_0
       1: getfield      #9                  // Field bucket:Ljava/lang/String;
       4: areturn

  static java.lang.String access$100(software.amazon.awssdk.services.s3.model.DeleteObjectRequest$BuilderImpl);
    Code:
       0: aload_0
       1: getfield      #8                  // Field key:Ljava/lang/String;
       4: areturn

  static java.lang.String access$200(software.amazon.awssdk.services.s3.model.DeleteObjectRequest$BuilderImpl);
    Code:
       0: aload_0
       1: getfield      #7                  // Field mfa:Ljava/lang/String;
       4: areturn

  static java.lang.String access$300(software.amazon.awssdk.services.s3.model.DeleteObjectRequest$BuilderImpl);
    Code:
       0: aload_0
       1: getfield      #6                  // Field versionId:Ljava/lang/String;
       4: areturn

  static java.lang.String access$400(software.amazon.awssdk.services.s3.model.DeleteObjectRequest$BuilderImpl);
    Code:
       0: aload_0
       1: getfield      #5                  // Field requestPayer:Ljava/lang/String;
       4: areturn

  static java.lang.Boolean access$500(software.amazon.awssdk.services.s3.model.DeleteObjectRequest$BuilderImpl);
    Code:
       0: aload_0
       1: getfield      #4                  // Field bypassGovernanceRetention:Ljava/lang/Boolean;
       4: areturn

  static java.lang.String access$600(software.amazon.awssdk.services.s3.model.DeleteObjectRequest$BuilderImpl);
    Code:
       0: aload_0
       1: getfield      #3                  // Field expectedBucketOwner:Ljava/lang/String;
       4: areturn

  software.amazon.awssdk.services.s3.model.DeleteObjectRequest$BuilderImpl(software.amazon.awssdk.services.s3.model.DeleteObjectRequest, software.amazon.awssdk.services.s3.model.DeleteObjectRequest$1);
    Code:
       0: aload_0
       1: aload_1
       2: invokespecial #2                  // Method "<init>":(Lsoftware/amazon/awssdk/services/s3/model/DeleteObjectRequest;)V
       5: return

  software.amazon.awssdk.services.s3.model.DeleteObjectRequest$BuilderImpl(software.amazon.awssdk.services.s3.model.DeleteObjectRequest$1);
    Code:
       0: aload_0
       1: invokespecial #1                  // Method "<init>":()V
       4: return
}
