Compiled from "GetBucketIntelligentTieringConfigurationResponse.java"
public interface software.amazon.awssdk.services.s3.model.GetBucketIntelligentTieringConfigurationResponse$Builder extends software.amazon.awssdk.services.s3.model.S3Response$Builder, software.amazon.awssdk.core.SdkPojo, software.amazon.awssdk.utils.builder.CopyableBuilder<software.amazon.awssdk.services.s3.model.GetBucketIntelligentTieringConfigurationResponse$Builder, software.amazon.awssdk.services.s3.model.GetBucketIntelligentTieringConfigurationResponse> {
  public abstract software.amazon.awssdk.services.s3.model.GetBucketIntelligentTieringConfigurationResponse$Builder intelligentTieringConfiguration(software.amazon.awssdk.services.s3.model.IntelligentTieringConfiguration);

  public default software.amazon.awssdk.services.s3.model.GetBucketIntelligentTieringConfigurationResponse$Builder intelligentTieringConfiguration(java.util.function.Consumer<software.amazon.awssdk.services.s3.model.IntelligentTieringConfiguration$Builder>);
    Code:
       0: aload_0
       1: invokestatic  #1                  // Method software/amazon/awssdk/services/s3/model/IntelligentTieringConfiguration.builder:()Lsoftware/amazon/awssdk/services/s3/model/IntelligentTieringConfiguration$Builder;
       4: aload_1
       5: invokeinterface #2,  2            // InterfaceMethod software/amazon/awssdk/services/s3/model/IntelligentTieringConfiguration$Builder.applyMutation:(Ljava/util/function/Consumer;)Lsoftware/amazon/awssdk/utils/builder/SdkBuilder;
      10: checkcast     #3                  // class software/amazon/awssdk/services/s3/model/IntelligentTieringConfiguration$Builder
      13: invokeinterface #4,  1            // InterfaceMethod software/amazon/awssdk/services/s3/model/IntelligentTieringConfiguration$Builder.build:()Ljava/lang/Object;
      18: checkcast     #5                  // class software/amazon/awssdk/services/s3/model/IntelligentTieringConfiguration
      21: invokeinterface #6,  2            // InterfaceMethod intelligentTieringConfiguration:(Lsoftware/amazon/awssdk/services/s3/model/IntelligentTieringConfiguration;)Lsoftware/amazon/awssdk/services/s3/model/GetBucketIntelligentTieringConfigurationResponse$Builder;
      26: areturn
}
