Compiled from "IntelligentTieringConfiguration.java"
public interface software.amazon.awssdk.services.s3.model.IntelligentTieringConfiguration$Builder extends software.amazon.awssdk.core.SdkPojo, software.amazon.awssdk.utils.builder.CopyableBuilder<software.amazon.awssdk.services.s3.model.IntelligentTieringConfiguration$Builder, software.amazon.awssdk.services.s3.model.IntelligentTieringConfiguration> {
  public abstract software.amazon.awssdk.services.s3.model.IntelligentTieringConfiguration$Builder id(java.lang.String);

  public abstract software.amazon.awssdk.services.s3.model.IntelligentTieringConfiguration$Builder filter(software.amazon.awssdk.services.s3.model.IntelligentTieringFilter);

  public default software.amazon.awssdk.services.s3.model.IntelligentTieringConfiguration$Builder filter(java.util.function.Consumer<software.amazon.awssdk.services.s3.model.IntelligentTieringFilter$Builder>);
    Code:
       0: aload_0
       1: invokestatic  #1                  // Method software/amazon/awssdk/services/s3/model/IntelligentTieringFilter.builder:()Lsoftware/amazon/awssdk/services/s3/model/IntelligentTieringFilter$Builder;
       4: aload_1
       5: invokeinterface #2,  2            // InterfaceMethod software/amazon/awssdk/services/s3/model/IntelligentTieringFilter$Builder.applyMutation:(Ljava/util/function/Consumer;)Lsoftware/amazon/awssdk/utils/builder/SdkBuilder;
      10: checkcast     #3                  // class software/amazon/awssdk/services/s3/model/IntelligentTieringFilter$Builder
      13: invokeinterface #4,  1            // InterfaceMethod software/amazon/awssdk/services/s3/model/IntelligentTieringFilter$Builder.build:()Ljava/lang/Object;
      18: checkcast     #5                  // class software/amazon/awssdk/services/s3/model/IntelligentTieringFilter
      21: invokeinterface #6,  2            // InterfaceMethod filter:(Lsoftware/amazon/awssdk/services/s3/model/IntelligentTieringFilter;)Lsoftware/amazon/awssdk/services/s3/model/IntelligentTieringConfiguration$Builder;
      26: areturn

  public abstract software.amazon.awssdk.services.s3.model.IntelligentTieringConfiguration$Builder status(java.lang.String);

  public abstract software.amazon.awssdk.services.s3.model.IntelligentTieringConfiguration$Builder status(software.amazon.awssdk.services.s3.model.IntelligentTieringStatus);

  public abstract software.amazon.awssdk.services.s3.model.IntelligentTieringConfiguration$Builder tierings(java.util.Collection<software.amazon.awssdk.services.s3.model.Tiering>);

  public abstract software.amazon.awssdk.services.s3.model.IntelligentTieringConfiguration$Builder tierings(software.amazon.awssdk.services.s3.model.Tiering...);

  public abstract software.amazon.awssdk.services.s3.model.IntelligentTieringConfiguration$Builder tierings(java.util.function.Consumer<software.amazon.awssdk.services.s3.model.Tiering$Builder>...);
}
