Compiled from "InvalidObjectStateException.java"
final class software.amazon.awssdk.services.s3.model.InvalidObjectStateException$BuilderImpl extends software.amazon.awssdk.services.s3.model.S3Exception$BuilderImpl implements software.amazon.awssdk.services.s3.model.InvalidObjectStateException$Builder {
  private java.lang.String storageClass;

  private java.lang.String accessTier;

  private software.amazon.awssdk.services.s3.model.InvalidObjectStateException$BuilderImpl();
    Code:
       0: aload_0
       1: invokespecial #5                  // Method software/amazon/awssdk/services/s3/model/S3Exception$BuilderImpl."<init>":()V
       4: return

  private software.amazon.awssdk.services.s3.model.InvalidObjectStateException$BuilderImpl(software.amazon.awssdk.services.s3.model.InvalidObjectStateException);
    Code:
       0: aload_0
       1: aload_1
       2: invokespecial #6                  // Method software/amazon/awssdk/services/s3/model/S3Exception$BuilderImpl."<init>":(Lsoftware/amazon/awssdk/services/s3/model/S3Exception;)V
       5: aload_0
       6: aload_1
       7: invokestatic  #7                  // Method software/amazon/awssdk/services/s3/model/InvalidObjectStateException.access$400:(Lsoftware/amazon/awssdk/services/s3/model/InvalidObjectStateException;)Ljava/lang/String;
      10: invokevirtual #8                  // Method storageClass:(Ljava/lang/String;)Lsoftware/amazon/awssdk/services/s3/model/InvalidObjectStateException$Builder;
      13: pop
      14: aload_0
      15: aload_1
      16: invokestatic  #9                  // Method software/amazon/awssdk/services/s3/model/InvalidObjectStateException.access$500:(Lsoftware/amazon/awssdk/services/s3/model/InvalidObjectStateException;)Ljava/lang/String;
      19: invokevirtual #10                 // Method accessTier:(Ljava/lang/String;)Lsoftware/amazon/awssdk/services/s3/model/InvalidObjectStateException$Builder;
      22: pop
      23: return

  public final java.lang.String getStorageClass();
    Code:
       0: aload_0
       1: getfield      #4                  // Field storageClass:Ljava/lang/String;
       4: areturn

  public final void setStorageClass(java.lang.String);
    Code:
       0: aload_0
       1: aload_1
       2: putfield      #4                  // Field storageClass:Ljava/lang/String;
       5: return

  public final software.amazon.awssdk.services.s3.model.InvalidObjectStateException$Builder storageClass(java.lang.String);
    Code:
       0: aload_0
       1: aload_1
       2: putfield      #4                  // Field storageClass:Ljava/lang/String;
       5: aload_0
       6: areturn

  public final software.amazon.awssdk.services.s3.model.InvalidObjectStateException$Builder storageClass(software.amazon.awssdk.services.s3.model.StorageClass);
    Code:
       0: aload_0
       1: aload_1
       2: ifnonnull     9
       5: aconst_null
       6: goto          13
       9: aload_1
      10: invokevirtual #11                 // Method software/amazon/awssdk/services/s3/model/StorageClass.toString:()Ljava/lang/String;
      13: invokevirtual #8                  // Method storageClass:(Ljava/lang/String;)Lsoftware/amazon/awssdk/services/s3/model/InvalidObjectStateException$Builder;
      16: pop
      17: aload_0
      18: areturn

  public final java.lang.String getAccessTier();
    Code:
       0: aload_0
       1: getfield      #3                  // Field accessTier:Ljava/lang/String;
       4: areturn

  public final void setAccessTier(java.lang.String);
    Code:
       0: aload_0
       1: aload_1
       2: putfield      #3                  // Field accessTier:Ljava/lang/String;
       5: return

  public final software.amazon.awssdk.services.s3.model.InvalidObjectStateException$Builder accessTier(java.lang.String);
    Code:
       0: aload_0
       1: aload_1
       2: putfield      #3                  // Field accessTier:Ljava/lang/String;
       5: aload_0
       6: areturn

  public final software.amazon.awssdk.services.s3.model.InvalidObjectStateException$Builder accessTier(software.amazon.awssdk.services.s3.model.IntelligentTieringAccessTier);
    Code:
       0: aload_0
       1: aload_1
       2: ifnonnull     9
       5: aconst_null
       6: goto          13
       9: aload_1
      10: invokevirtual #12                 // Method software/amazon/awssdk/services/s3/model/IntelligentTieringAccessTier.toString:()Ljava/lang/String;
      13: invokevirtual #10                 // Method accessTier:(Ljava/lang/String;)Lsoftware/amazon/awssdk/services/s3/model/InvalidObjectStateException$Builder;
      16: pop
      17: aload_0
      18: areturn

  public software.amazon.awssdk.services.s3.model.InvalidObjectStateException$BuilderImpl awsErrorDetails(software.amazon.awssdk.awscore.exception.AwsErrorDetails);
    Code:
       0: aload_0
       1: aload_1
       2: putfield      #13                 // Field awsErrorDetails:Lsoftware/amazon/awssdk/awscore/exception/AwsErrorDetails;
       5: aload_0
       6: areturn

  public software.amazon.awssdk.services.s3.model.InvalidObjectStateException$BuilderImpl message(java.lang.String);
    Code:
       0: aload_0
       1: aload_1
       2: putfield      #14                 // Field message:Ljava/lang/String;
       5: aload_0
       6: areturn

  public software.amazon.awssdk.services.s3.model.InvalidObjectStateException$BuilderImpl requestId(java.lang.String);
    Code:
       0: aload_0
       1: aload_1
       2: putfield      #15                 // Field requestId:Ljava/lang/String;
       5: aload_0
       6: areturn

  public software.amazon.awssdk.services.s3.model.InvalidObjectStateException$BuilderImpl statusCode(int);
    Code:
       0: aload_0
       1: iload_1
       2: putfield      #16                 // Field statusCode:I
       5: aload_0
       6: areturn

  public software.amazon.awssdk.services.s3.model.InvalidObjectStateException$BuilderImpl cause(java.lang.Throwable);
    Code:
       0: aload_0
       1: aload_1
       2: putfield      #17                 // Field cause:Ljava/lang/Throwable;
       5: aload_0
       6: areturn

  public software.amazon.awssdk.services.s3.model.InvalidObjectStateException$BuilderImpl writableStackTrace(java.lang.Boolean);
    Code:
       0: aload_0
       1: aload_1
       2: putfield      #18                 // Field writableStackTrace:Ljava/lang/Boolean;
       5: aload_0
       6: areturn

  public software.amazon.awssdk.services.s3.model.InvalidObjectStateException build();
    Code:
       0: new           #19                 // class software/amazon/awssdk/services/s3/model/InvalidObjectStateException
       3: dup
       4: aload_0
       5: aconst_null
       6: invokespecial #20                 // Method software/amazon/awssdk/services/s3/model/InvalidObjectStateException."<init>":(Lsoftware/amazon/awssdk/services/s3/model/InvalidObjectStateException$BuilderImpl;Lsoftware/amazon/awssdk/services/s3/model/InvalidObjectStateException$1;)V
       9: areturn

  public java.util.List<software.amazon.awssdk.core.SdkField<?>> sdkFields();
    Code:
       0: invokestatic  #21                 // Method software/amazon/awssdk/services/s3/model/InvalidObjectStateException.access$700:()Ljava/util/List;
       3: areturn

  public software.amazon.awssdk.services.s3.model.S3Exception build();
    Code:
       0: aload_0
       1: invokevirtual #22                 // Method build:()Lsoftware/amazon/awssdk/services/s3/model/InvalidObjectStateException;
       4: areturn

  public software.amazon.awssdk.services.s3.model.S3Exception$BuilderImpl writableStackTrace(java.lang.Boolean);
    Code:
       0: aload_0
       1: aload_1
       2: invokevirtual #23                 // Method writableStackTrace:(Ljava/lang/Boolean;)Lsoftware/amazon/awssdk/services/s3/model/InvalidObjectStateException$BuilderImpl;
       5: areturn

  public software.amazon.awssdk.services.s3.model.S3Exception$BuilderImpl cause(java.lang.Throwable);
    Code:
       0: aload_0
       1: aload_1
       2: invokevirtual #24                 // Method cause:(Ljava/lang/Throwable;)Lsoftware/amazon/awssdk/services/s3/model/InvalidObjectStateException$BuilderImpl;
       5: areturn

  public software.amazon.awssdk.services.s3.model.S3Exception$BuilderImpl statusCode(int);
    Code:
       0: aload_0
       1: iload_1
       2: invokevirtual #25                 // Method statusCode:(I)Lsoftware/amazon/awssdk/services/s3/model/InvalidObjectStateException$BuilderImpl;
       5: areturn

  public software.amazon.awssdk.services.s3.model.S3Exception$BuilderImpl requestId(java.lang.String);
    Code:
       0: aload_0
       1: aload_1
       2: invokevirtual #26                 // Method requestId:(Ljava/lang/String;)Lsoftware/amazon/awssdk/services/s3/model/InvalidObjectStateException$BuilderImpl;
       5: areturn

  public software.amazon.awssdk.services.s3.model.S3Exception$BuilderImpl message(java.lang.String);
    Code:
       0: aload_0
       1: aload_1
       2: invokevirtual #27                 // Method message:(Ljava/lang/String;)Lsoftware/amazon/awssdk/services/s3/model/InvalidObjectStateException$BuilderImpl;
       5: areturn

  public software.amazon.awssdk.services.s3.model.S3Exception$BuilderImpl awsErrorDetails(software.amazon.awssdk.awscore.exception.AwsErrorDetails);
    Code:
       0: aload_0
       1: aload_1
       2: invokevirtual #28                 // Method awsErrorDetails:(Lsoftware/amazon/awssdk/awscore/exception/AwsErrorDetails;)Lsoftware/amazon/awssdk/services/s3/model/InvalidObjectStateException$BuilderImpl;
       5: areturn

  public software.amazon.awssdk.services.s3.model.S3Exception$Builder writableStackTrace(java.lang.Boolean);
    Code:
       0: aload_0
       1: aload_1
       2: invokevirtual #23                 // Method writableStackTrace:(Ljava/lang/Boolean;)Lsoftware/amazon/awssdk/services/s3/model/InvalidObjectStateException$BuilderImpl;
       5: areturn

  public software.amazon.awssdk.services.s3.model.S3Exception$Builder cause(java.lang.Throwable);
    Code:
       0: aload_0
       1: aload_1
       2: invokevirtual #24                 // Method cause:(Ljava/lang/Throwable;)Lsoftware/amazon/awssdk/services/s3/model/InvalidObjectStateException$BuilderImpl;
       5: areturn

  public software.amazon.awssdk.services.s3.model.S3Exception$Builder statusCode(int);
    Code:
       0: aload_0
       1: iload_1
       2: invokevirtual #25                 // Method statusCode:(I)Lsoftware/amazon/awssdk/services/s3/model/InvalidObjectStateException$BuilderImpl;
       5: areturn

  public software.amazon.awssdk.services.s3.model.S3Exception$Builder requestId(java.lang.String);
    Code:
       0: aload_0
       1: aload_1
       2: invokevirtual #26                 // Method requestId:(Ljava/lang/String;)Lsoftware/amazon/awssdk/services/s3/model/InvalidObjectStateException$BuilderImpl;
       5: areturn

  public software.amazon.awssdk.services.s3.model.S3Exception$Builder message(java.lang.String);
    Code:
       0: aload_0
       1: aload_1
       2: invokevirtual #27                 // Method message:(Ljava/lang/String;)Lsoftware/amazon/awssdk/services/s3/model/InvalidObjectStateException$BuilderImpl;
       5: areturn

  public software.amazon.awssdk.services.s3.model.S3Exception$Builder awsErrorDetails(software.amazon.awssdk.awscore.exception.AwsErrorDetails);
    Code:
       0: aload_0
       1: aload_1
       2: invokevirtual #28                 // Method awsErrorDetails:(Lsoftware/amazon/awssdk/awscore/exception/AwsErrorDetails;)Lsoftware/amazon/awssdk/services/s3/model/InvalidObjectStateException$BuilderImpl;
       5: areturn

  public software.amazon.awssdk.awscore.exception.AwsServiceException build();
    Code:
       0: aload_0
       1: invokevirtual #22                 // Method build:()Lsoftware/amazon/awssdk/services/s3/model/InvalidObjectStateException;
       4: areturn

  public software.amazon.awssdk.awscore.exception.AwsServiceException$Builder statusCode(int);
    Code:
       0: aload_0
       1: iload_1
       2: invokevirtual #25                 // Method statusCode:(I)Lsoftware/amazon/awssdk/services/s3/model/InvalidObjectStateException$BuilderImpl;
       5: areturn

  public software.amazon.awssdk.awscore.exception.AwsServiceException$Builder requestId(java.lang.String);
    Code:
       0: aload_0
       1: aload_1
       2: invokevirtual #26                 // Method requestId:(Ljava/lang/String;)Lsoftware/amazon/awssdk/services/s3/model/InvalidObjectStateException$BuilderImpl;
       5: areturn

  public software.amazon.awssdk.awscore.exception.AwsServiceException$Builder cause(java.lang.Throwable);
    Code:
       0: aload_0
       1: aload_1
       2: invokevirtual #24                 // Method cause:(Ljava/lang/Throwable;)Lsoftware/amazon/awssdk/services/s3/model/InvalidObjectStateException$BuilderImpl;
       5: areturn

  public software.amazon.awssdk.awscore.exception.AwsServiceException$Builder message(java.lang.String);
    Code:
       0: aload_0
       1: aload_1
       2: invokevirtual #27                 // Method message:(Ljava/lang/String;)Lsoftware/amazon/awssdk/services/s3/model/InvalidObjectStateException$BuilderImpl;
       5: areturn

  public software.amazon.awssdk.awscore.exception.AwsServiceException$Builder awsErrorDetails(software.amazon.awssdk.awscore.exception.AwsErrorDetails);
    Code:
       0: aload_0
       1: aload_1
       2: invokevirtual #28                 // Method awsErrorDetails:(Lsoftware/amazon/awssdk/awscore/exception/AwsErrorDetails;)Lsoftware/amazon/awssdk/services/s3/model/InvalidObjectStateException$BuilderImpl;
       5: areturn

  public software.amazon.awssdk.core.exception.SdkServiceException build();
    Code:
       0: aload_0
       1: invokevirtual #22                 // Method build:()Lsoftware/amazon/awssdk/services/s3/model/InvalidObjectStateException;
       4: areturn

  public software.amazon.awssdk.core.exception.SdkServiceException$Builder statusCode(int);
    Code:
       0: aload_0
       1: iload_1
       2: invokevirtual #25                 // Method statusCode:(I)Lsoftware/amazon/awssdk/services/s3/model/InvalidObjectStateException$BuilderImpl;
       5: areturn

  public software.amazon.awssdk.core.exception.SdkServiceException$Builder requestId(java.lang.String);
    Code:
       0: aload_0
       1: aload_1
       2: invokevirtual #26                 // Method requestId:(Ljava/lang/String;)Lsoftware/amazon/awssdk/services/s3/model/InvalidObjectStateException$BuilderImpl;
       5: areturn

  public software.amazon.awssdk.core.exception.SdkServiceException$Builder writableStackTrace(java.lang.Boolean);
    Code:
       0: aload_0
       1: aload_1
       2: invokevirtual #23                 // Method writableStackTrace:(Ljava/lang/Boolean;)Lsoftware/amazon/awssdk/services/s3/model/InvalidObjectStateException$BuilderImpl;
       5: areturn

  public software.amazon.awssdk.core.exception.SdkServiceException$Builder cause(java.lang.Throwable);
    Code:
       0: aload_0
       1: aload_1
       2: invokevirtual #24                 // Method cause:(Ljava/lang/Throwable;)Lsoftware/amazon/awssdk/services/s3/model/InvalidObjectStateException$BuilderImpl;
       5: areturn

  public software.amazon.awssdk.core.exception.SdkServiceException$Builder message(java.lang.String);
    Code:
       0: aload_0
       1: aload_1
       2: invokevirtual #27                 // Method message:(Ljava/lang/String;)Lsoftware/amazon/awssdk/services/s3/model/InvalidObjectStateException$BuilderImpl;
       5: areturn

  public software.amazon.awssdk.core.exception.SdkException build();
    Code:
       0: aload_0
       1: invokevirtual #22                 // Method build:()Lsoftware/amazon/awssdk/services/s3/model/InvalidObjectStateException;
       4: areturn

  public software.amazon.awssdk.core.exception.SdkException$Builder writableStackTrace(java.lang.Boolean);
    Code:
       0: aload_0
       1: aload_1
       2: invokevirtual #23                 // Method writableStackTrace:(Ljava/lang/Boolean;)Lsoftware/amazon/awssdk/services/s3/model/InvalidObjectStateException$BuilderImpl;
       5: areturn

  public software.amazon.awssdk.core.exception.SdkException$Builder message(java.lang.String);
    Code:
       0: aload_0
       1: aload_1
       2: invokevirtual #27                 // Method message:(Ljava/lang/String;)Lsoftware/amazon/awssdk/services/s3/model/InvalidObjectStateException$BuilderImpl;
       5: areturn

  public software.amazon.awssdk.core.exception.SdkException$Builder cause(java.lang.Throwable);
    Code:
       0: aload_0
       1: aload_1
       2: invokevirtual #24                 // Method cause:(Ljava/lang/Throwable;)Lsoftware/amazon/awssdk/services/s3/model/InvalidObjectStateException$BuilderImpl;
       5: areturn

  public java.lang.Object build();
    Code:
       0: aload_0
       1: invokevirtual #22                 // Method build:()Lsoftware/amazon/awssdk/services/s3/model/InvalidObjectStateException;
       4: areturn

  public software.amazon.awssdk.awscore.exception.AwsServiceException$Builder writableStackTrace(java.lang.Boolean);
    Code:
       0: aload_0
       1: aload_1
       2: invokevirtual #23                 // Method writableStackTrace:(Ljava/lang/Boolean;)Lsoftware/amazon/awssdk/services/s3/model/InvalidObjectStateException$BuilderImpl;
       5: areturn

  public software.amazon.awssdk.services.s3.model.InvalidObjectStateException$Builder writableStackTrace(java.lang.Boolean);
    Code:
       0: aload_0
       1: aload_1
       2: invokevirtual #23                 // Method writableStackTrace:(Ljava/lang/Boolean;)Lsoftware/amazon/awssdk/services/s3/model/InvalidObjectStateException$BuilderImpl;
       5: areturn

  public software.amazon.awssdk.services.s3.model.InvalidObjectStateException$Builder cause(java.lang.Throwable);
    Code:
       0: aload_0
       1: aload_1
       2: invokevirtual #24                 // Method cause:(Ljava/lang/Throwable;)Lsoftware/amazon/awssdk/services/s3/model/InvalidObjectStateException$BuilderImpl;
       5: areturn

  public software.amazon.awssdk.services.s3.model.InvalidObjectStateException$Builder statusCode(int);
    Code:
       0: aload_0
       1: iload_1
       2: invokevirtual #25                 // Method statusCode:(I)Lsoftware/amazon/awssdk/services/s3/model/InvalidObjectStateException$BuilderImpl;
       5: areturn

  public software.amazon.awssdk.services.s3.model.InvalidObjectStateException$Builder requestId(java.lang.String);
    Code:
       0: aload_0
       1: aload_1
       2: invokevirtual #26                 // Method requestId:(Ljava/lang/String;)Lsoftware/amazon/awssdk/services/s3/model/InvalidObjectStateException$BuilderImpl;
       5: areturn

  public software.amazon.awssdk.services.s3.model.InvalidObjectStateException$Builder message(java.lang.String);
    Code:
       0: aload_0
       1: aload_1
       2: invokevirtual #27                 // Method message:(Ljava/lang/String;)Lsoftware/amazon/awssdk/services/s3/model/InvalidObjectStateException$BuilderImpl;
       5: areturn

  public software.amazon.awssdk.services.s3.model.InvalidObjectStateException$Builder awsErrorDetails(software.amazon.awssdk.awscore.exception.AwsErrorDetails);
    Code:
       0: aload_0
       1: aload_1
       2: invokevirtual #28                 // Method awsErrorDetails:(Lsoftware/amazon/awssdk/awscore/exception/AwsErrorDetails;)Lsoftware/amazon/awssdk/services/s3/model/InvalidObjectStateException$BuilderImpl;
       5: areturn

  static java.lang.String access$000(software.amazon.awssdk.services.s3.model.InvalidObjectStateException$BuilderImpl);
    Code:
       0: aload_0
       1: getfield      #4                  // Field storageClass:Ljava/lang/String;
       4: areturn

  static java.lang.String access$100(software.amazon.awssdk.services.s3.model.InvalidObjectStateException$BuilderImpl);
    Code:
       0: aload_0
       1: getfield      #3                  // Field accessTier:Ljava/lang/String;
       4: areturn

  software.amazon.awssdk.services.s3.model.InvalidObjectStateException$BuilderImpl(software.amazon.awssdk.services.s3.model.InvalidObjectStateException, software.amazon.awssdk.services.s3.model.InvalidObjectStateException$1);
    Code:
       0: aload_0
       1: aload_1
       2: invokespecial #2                  // Method "<init>":(Lsoftware/amazon/awssdk/services/s3/model/InvalidObjectStateException;)V
       5: return

  software.amazon.awssdk.services.s3.model.InvalidObjectStateException$BuilderImpl(software.amazon.awssdk.services.s3.model.InvalidObjectStateException$1);
    Code:
       0: aload_0
       1: invokespecial #1                  // Method "<init>":()V
       4: return
}
