Compiled from "LambdaFunctionConfiguration.java"
public interface software.amazon.awssdk.services.s3.model.LambdaFunctionConfiguration$Builder extends software.amazon.awssdk.core.SdkPojo, software.amazon.awssdk.utils.builder.CopyableBuilder<software.amazon.awssdk.services.s3.model.LambdaFunctionConfiguration$Builder, software.amazon.awssdk.services.s3.model.LambdaFunctionConfiguration> {
  public abstract software.amazon.awssdk.services.s3.model.LambdaFunctionConfiguration$Builder id(java.lang.String);

  public abstract software.amazon.awssdk.services.s3.model.LambdaFunctionConfiguration$Builder lambdaFunctionArn(java.lang.String);

  public abstract software.amazon.awssdk.services.s3.model.LambdaFunctionConfiguration$Builder eventsWithStrings(java.util.Collection<java.lang.String>);

  public abstract software.amazon.awssdk.services.s3.model.LambdaFunctionConfiguration$Builder eventsWithStrings(java.lang.String...);

  public abstract software.amazon.awssdk.services.s3.model.LambdaFunctionConfiguration$Builder events(java.util.Collection<software.amazon.awssdk.services.s3.model.Event>);

  public abstract software.amazon.awssdk.services.s3.model.LambdaFunctionConfiguration$Builder events(software.amazon.awssdk.services.s3.model.Event...);

  public abstract software.amazon.awssdk.services.s3.model.LambdaFunctionConfiguration$Builder filter(software.amazon.awssdk.services.s3.model.NotificationConfigurationFilter);

  public default software.amazon.awssdk.services.s3.model.LambdaFunctionConfiguration$Builder filter(java.util.function.Consumer<software.amazon.awssdk.services.s3.model.NotificationConfigurationFilter$Builder>);
    Code:
       0: aload_0
       1: invokestatic  #1                  // Method software/amazon/awssdk/services/s3/model/NotificationConfigurationFilter.builder:()Lsoftware/amazon/awssdk/services/s3/model/NotificationConfigurationFilter$Builder;
       4: aload_1
       5: invokeinterface #2,  2            // InterfaceMethod software/amazon/awssdk/services/s3/model/NotificationConfigurationFilter$Builder.applyMutation:(Ljava/util/function/Consumer;)Lsoftware/amazon/awssdk/utils/builder/SdkBuilder;
      10: checkcast     #3                  // class software/amazon/awssdk/services/s3/model/NotificationConfigurationFilter$Builder
      13: invokeinterface #4,  1            // InterfaceMethod software/amazon/awssdk/services/s3/model/NotificationConfigurationFilter$Builder.build:()Ljava/lang/Object;
      18: checkcast     #5                  // class software/amazon/awssdk/services/s3/model/NotificationConfigurationFilter
      21: invokeinterface #6,  2            // InterfaceMethod filter:(Lsoftware/amazon/awssdk/services/s3/model/NotificationConfigurationFilter;)Lsoftware/amazon/awssdk/services/s3/model/LambdaFunctionConfiguration$Builder;
      26: areturn
}
