Compiled from "Metrics.java"
final class software.amazon.awssdk.services.s3.model.Metrics$BuilderImpl implements software.amazon.awssdk.services.s3.model.Metrics$Builder {
  private java.lang.String status;

  private software.amazon.awssdk.services.s3.model.ReplicationTimeValue eventThreshold;

  private software.amazon.awssdk.services.s3.model.Metrics$BuilderImpl();
    Code:
       0: aload_0
       1: invokespecial #5                  // Method java/lang/Object."<init>":()V
       4: return

  private software.amazon.awssdk.services.s3.model.Metrics$BuilderImpl(software.amazon.awssdk.services.s3.model.Metrics);
    Code:
       0: aload_0
       1: invokespecial #5                  // Method java/lang/Object."<init>":()V
       4: aload_0
       5: aload_1
       6: invokestatic  #6                  // Method software/amazon/awssdk/services/s3/model/Metrics.access$400:(Lsoftware/amazon/awssdk/services/s3/model/Metrics;)Ljava/lang/String;
       9: invokevirtual #7                  // Method status:(Ljava/lang/String;)Lsoftware/amazon/awssdk/services/s3/model/Metrics$Builder;
      12: pop
      13: aload_0
      14: aload_1
      15: invokestatic  #8                  // Method software/amazon/awssdk/services/s3/model/Metrics.access$500:(Lsoftware/amazon/awssdk/services/s3/model/Metrics;)Lsoftware/amazon/awssdk/services/s3/model/ReplicationTimeValue;
      18: invokevirtual #9                  // Method eventThreshold:(Lsoftware/amazon/awssdk/services/s3/model/ReplicationTimeValue;)Lsoftware/amazon/awssdk/services/s3/model/Metrics$Builder;
      21: pop
      22: return

  public final java.lang.String getStatus();
    Code:
       0: aload_0
       1: getfield      #4                  // Field status:Ljava/lang/String;
       4: areturn

  public final void setStatus(java.lang.String);
    Code:
       0: aload_0
       1: aload_1
       2: putfield      #4                  // Field status:Ljava/lang/String;
       5: return

  public final software.amazon.awssdk.services.s3.model.Metrics$Builder status(java.lang.String);
    Code:
       0: aload_0
       1: aload_1
       2: putfield      #4                  // Field status:Ljava/lang/String;
       5: aload_0
       6: areturn

  public final software.amazon.awssdk.services.s3.model.Metrics$Builder status(software.amazon.awssdk.services.s3.model.MetricsStatus);
    Code:
       0: aload_0
       1: aload_1
       2: ifnonnull     9
       5: aconst_null
       6: goto          13
       9: aload_1
      10: invokevirtual #10                 // Method software/amazon/awssdk/services/s3/model/MetricsStatus.toString:()Ljava/lang/String;
      13: invokevirtual #7                  // Method status:(Ljava/lang/String;)Lsoftware/amazon/awssdk/services/s3/model/Metrics$Builder;
      16: pop
      17: aload_0
      18: areturn

  public final software.amazon.awssdk.services.s3.model.ReplicationTimeValue$Builder getEventThreshold();
    Code:
       0: aload_0
       1: getfield      #3                  // Field eventThreshold:Lsoftware/amazon/awssdk/services/s3/model/ReplicationTimeValue;
       4: ifnull        17
       7: aload_0
       8: getfield      #3                  // Field eventThreshold:Lsoftware/amazon/awssdk/services/s3/model/ReplicationTimeValue;
      11: invokevirtual #11                 // Method software/amazon/awssdk/services/s3/model/ReplicationTimeValue.toBuilder:()Lsoftware/amazon/awssdk/services/s3/model/ReplicationTimeValue$Builder;
      14: goto          18
      17: aconst_null
      18: areturn

  public final void setEventThreshold(software.amazon.awssdk.services.s3.model.ReplicationTimeValue$BuilderImpl);
    Code:
       0: aload_0
       1: aload_1
       2: ifnull        12
       5: aload_1
       6: invokevirtual #12                 // Method software/amazon/awssdk/services/s3/model/ReplicationTimeValue$BuilderImpl.build:()Lsoftware/amazon/awssdk/services/s3/model/ReplicationTimeValue;
       9: goto          13
      12: aconst_null
      13: putfield      #3                  // Field eventThreshold:Lsoftware/amazon/awssdk/services/s3/model/ReplicationTimeValue;
      16: return

  public final software.amazon.awssdk.services.s3.model.Metrics$Builder eventThreshold(software.amazon.awssdk.services.s3.model.ReplicationTimeValue);
    Code:
       0: aload_0
       1: aload_1
       2: putfield      #3                  // Field eventThreshold:Lsoftware/amazon/awssdk/services/s3/model/ReplicationTimeValue;
       5: aload_0
       6: areturn

  public software.amazon.awssdk.services.s3.model.Metrics build();
    Code:
       0: new           #13                 // class software/amazon/awssdk/services/s3/model/Metrics
       3: dup
       4: aload_0
       5: aconst_null
       6: invokespecial #14                 // Method software/amazon/awssdk/services/s3/model/Metrics."<init>":(Lsoftware/amazon/awssdk/services/s3/model/Metrics$BuilderImpl;Lsoftware/amazon/awssdk/services/s3/model/Metrics$1;)V
       9: areturn

  public java.util.List<software.amazon.awssdk.core.SdkField<?>> sdkFields();
    Code:
       0: invokestatic  #15                 // Method software/amazon/awssdk/services/s3/model/Metrics.access$700:()Ljava/util/List;
       3: areturn

  public java.lang.Object build();
    Code:
       0: aload_0
       1: invokevirtual #16                 // Method build:()Lsoftware/amazon/awssdk/services/s3/model/Metrics;
       4: areturn

  static java.lang.String access$000(software.amazon.awssdk.services.s3.model.Metrics$BuilderImpl);
    Code:
       0: aload_0
       1: getfield      #4                  // Field status:Ljava/lang/String;
       4: areturn

  static software.amazon.awssdk.services.s3.model.ReplicationTimeValue access$100(software.amazon.awssdk.services.s3.model.Metrics$BuilderImpl);
    Code:
       0: aload_0
       1: getfield      #3                  // Field eventThreshold:Lsoftware/amazon/awssdk/services/s3/model/ReplicationTimeValue;
       4: areturn

  software.amazon.awssdk.services.s3.model.Metrics$BuilderImpl(software.amazon.awssdk.services.s3.model.Metrics, software.amazon.awssdk.services.s3.model.Metrics$1);
    Code:
       0: aload_0
       1: aload_1
       2: invokespecial #2                  // Method "<init>":(Lsoftware/amazon/awssdk/services/s3/model/Metrics;)V
       5: return

  software.amazon.awssdk.services.s3.model.Metrics$BuilderImpl(software.amazon.awssdk.services.s3.model.Metrics$1);
    Code:
       0: aload_0
       1: invokespecial #1                  // Method "<init>":()V
       4: return
}
