Compiled from "ObjectLockConfiguration.java"
final class software.amazon.awssdk.services.s3.model.ObjectLockConfiguration$BuilderImpl implements software.amazon.awssdk.services.s3.model.ObjectLockConfiguration$Builder {
  private java.lang.String objectLockEnabled;

  private software.amazon.awssdk.services.s3.model.ObjectLockRule rule;

  private software.amazon.awssdk.services.s3.model.ObjectLockConfiguration$BuilderImpl();
    Code:
       0: aload_0
       1: invokespecial #5                  // Method java/lang/Object."<init>":()V
       4: return

  private software.amazon.awssdk.services.s3.model.ObjectLockConfiguration$BuilderImpl(software.amazon.awssdk.services.s3.model.ObjectLockConfiguration);
    Code:
       0: aload_0
       1: invokespecial #5                  // Method java/lang/Object."<init>":()V
       4: aload_0
       5: aload_1
       6: invokestatic  #6                  // Method software/amazon/awssdk/services/s3/model/ObjectLockConfiguration.access$400:(Lsoftware/amazon/awssdk/services/s3/model/ObjectLockConfiguration;)Ljava/lang/String;
       9: invokevirtual #7                  // Method objectLockEnabled:(Ljava/lang/String;)Lsoftware/amazon/awssdk/services/s3/model/ObjectLockConfiguration$Builder;
      12: pop
      13: aload_0
      14: aload_1
      15: invokestatic  #8                  // Method software/amazon/awssdk/services/s3/model/ObjectLockConfiguration.access$500:(Lsoftware/amazon/awssdk/services/s3/model/ObjectLockConfiguration;)Lsoftware/amazon/awssdk/services/s3/model/ObjectLockRule;
      18: invokevirtual #9                  // Method rule:(Lsoftware/amazon/awssdk/services/s3/model/ObjectLockRule;)Lsoftware/amazon/awssdk/services/s3/model/ObjectLockConfiguration$Builder;
      21: pop
      22: return

  public final java.lang.String getObjectLockEnabled();
    Code:
       0: aload_0
       1: getfield      #4                  // Field objectLockEnabled:Ljava/lang/String;
       4: areturn

  public final void setObjectLockEnabled(java.lang.String);
    Code:
       0: aload_0
       1: aload_1
       2: putfield      #4                  // Field objectLockEnabled:Ljava/lang/String;
       5: return

  public final software.amazon.awssdk.services.s3.model.ObjectLockConfiguration$Builder objectLockEnabled(java.lang.String);
    Code:
       0: aload_0
       1: aload_1
       2: putfield      #4                  // Field objectLockEnabled:Ljava/lang/String;
       5: aload_0
       6: areturn

  public final software.amazon.awssdk.services.s3.model.ObjectLockConfiguration$Builder objectLockEnabled(software.amazon.awssdk.services.s3.model.ObjectLockEnabled);
    Code:
       0: aload_0
       1: aload_1
       2: ifnonnull     9
       5: aconst_null
       6: goto          13
       9: aload_1
      10: invokevirtual #10                 // Method software/amazon/awssdk/services/s3/model/ObjectLockEnabled.toString:()Ljava/lang/String;
      13: invokevirtual #7                  // Method objectLockEnabled:(Ljava/lang/String;)Lsoftware/amazon/awssdk/services/s3/model/ObjectLockConfiguration$Builder;
      16: pop
      17: aload_0
      18: areturn

  public final software.amazon.awssdk.services.s3.model.ObjectLockRule$Builder getRule();
    Code:
       0: aload_0
       1: getfield      #3                  // Field rule:Lsoftware/amazon/awssdk/services/s3/model/ObjectLockRule;
       4: ifnull        17
       7: aload_0
       8: getfield      #3                  // Field rule:Lsoftware/amazon/awssdk/services/s3/model/ObjectLockRule;
      11: invokevirtual #11                 // Method software/amazon/awssdk/services/s3/model/ObjectLockRule.toBuilder:()Lsoftware/amazon/awssdk/services/s3/model/ObjectLockRule$Builder;
      14: goto          18
      17: aconst_null
      18: areturn

  public final void setRule(software.amazon.awssdk.services.s3.model.ObjectLockRule$BuilderImpl);
    Code:
       0: aload_0
       1: aload_1
       2: ifnull        12
       5: aload_1
       6: invokevirtual #12                 // Method software/amazon/awssdk/services/s3/model/ObjectLockRule$BuilderImpl.build:()Lsoftware/amazon/awssdk/services/s3/model/ObjectLockRule;
       9: goto          13
      12: aconst_null
      13: putfield      #3                  // Field rule:Lsoftware/amazon/awssdk/services/s3/model/ObjectLockRule;
      16: return

  public final software.amazon.awssdk.services.s3.model.ObjectLockConfiguration$Builder rule(software.amazon.awssdk.services.s3.model.ObjectLockRule);
    Code:
       0: aload_0
       1: aload_1
       2: putfield      #3                  // Field rule:Lsoftware/amazon/awssdk/services/s3/model/ObjectLockRule;
       5: aload_0
       6: areturn

  public software.amazon.awssdk.services.s3.model.ObjectLockConfiguration build();
    Code:
       0: new           #13                 // class software/amazon/awssdk/services/s3/model/ObjectLockConfiguration
       3: dup
       4: aload_0
       5: aconst_null
       6: invokespecial #14                 // Method software/amazon/awssdk/services/s3/model/ObjectLockConfiguration."<init>":(Lsoftware/amazon/awssdk/services/s3/model/ObjectLockConfiguration$BuilderImpl;Lsoftware/amazon/awssdk/services/s3/model/ObjectLockConfiguration$1;)V
       9: areturn

  public java.util.List<software.amazon.awssdk.core.SdkField<?>> sdkFields();
    Code:
       0: invokestatic  #15                 // Method software/amazon/awssdk/services/s3/model/ObjectLockConfiguration.access$700:()Ljava/util/List;
       3: areturn

  public java.lang.Object build();
    Code:
       0: aload_0
       1: invokevirtual #16                 // Method build:()Lsoftware/amazon/awssdk/services/s3/model/ObjectLockConfiguration;
       4: areturn

  static java.lang.String access$000(software.amazon.awssdk.services.s3.model.ObjectLockConfiguration$BuilderImpl);
    Code:
       0: aload_0
       1: getfield      #4                  // Field objectLockEnabled:Ljava/lang/String;
       4: areturn

  static software.amazon.awssdk.services.s3.model.ObjectLockRule access$100(software.amazon.awssdk.services.s3.model.ObjectLockConfiguration$BuilderImpl);
    Code:
       0: aload_0
       1: getfield      #3                  // Field rule:Lsoftware/amazon/awssdk/services/s3/model/ObjectLockRule;
       4: areturn

  software.amazon.awssdk.services.s3.model.ObjectLockConfiguration$BuilderImpl(software.amazon.awssdk.services.s3.model.ObjectLockConfiguration, software.amazon.awssdk.services.s3.model.ObjectLockConfiguration$1);
    Code:
       0: aload_0
       1: aload_1
       2: invokespecial #2                  // Method "<init>":(Lsoftware/amazon/awssdk/services/s3/model/ObjectLockConfiguration;)V
       5: return

  software.amazon.awssdk.services.s3.model.ObjectLockConfiguration$BuilderImpl(software.amazon.awssdk.services.s3.model.ObjectLockConfiguration$1);
    Code:
       0: aload_0
       1: invokespecial #1                  // Method "<init>":()V
       4: return
}
