Compiled from "PutBucketNotificationConfigurationRequest.java"
final class software.amazon.awssdk.services.s3.model.PutBucketNotificationConfigurationRequest$BuilderImpl extends software.amazon.awssdk.services.s3.model.S3Request$BuilderImpl implements software.amazon.awssdk.services.s3.model.PutBucketNotificationConfigurationRequest$Builder {
  private java.lang.String bucket;

  private software.amazon.awssdk.services.s3.model.NotificationConfiguration notificationConfiguration;

  private java.lang.String expectedBucketOwner;

  private java.lang.Boolean skipDestinationValidation;

  private software.amazon.awssdk.services.s3.model.PutBucketNotificationConfigurationRequest$BuilderImpl();
    Code:
       0: aload_0
       1: invokespecial #7                  // Method software/amazon/awssdk/services/s3/model/S3Request$BuilderImpl."<init>":()V
       4: return

  private software.amazon.awssdk.services.s3.model.PutBucketNotificationConfigurationRequest$BuilderImpl(software.amazon.awssdk.services.s3.model.PutBucketNotificationConfigurationRequest);
    Code:
       0: aload_0
       1: aload_1
       2: invokespecial #8                  // Method software/amazon/awssdk/services/s3/model/S3Request$BuilderImpl."<init>":(Lsoftware/amazon/awssdk/services/s3/model/S3Request;)V
       5: aload_0
       6: aload_1
       7: invokestatic  #9                  // Method software/amazon/awssdk/services/s3/model/PutBucketNotificationConfigurationRequest.access$600:(Lsoftware/amazon/awssdk/services/s3/model/PutBucketNotificationConfigurationRequest;)Ljava/lang/String;
      10: invokevirtual #10                 // Method bucket:(Ljava/lang/String;)Lsoftware/amazon/awssdk/services/s3/model/PutBucketNotificationConfigurationRequest$Builder;
      13: pop
      14: aload_0
      15: aload_1
      16: invokestatic  #11                 // Method software/amazon/awssdk/services/s3/model/PutBucketNotificationConfigurationRequest.access$700:(Lsoftware/amazon/awssdk/services/s3/model/PutBucketNotificationConfigurationRequest;)Lsoftware/amazon/awssdk/services/s3/model/NotificationConfiguration;
      19: invokevirtual #12                 // Method notificationConfiguration:(Lsoftware/amazon/awssdk/services/s3/model/NotificationConfiguration;)Lsoftware/amazon/awssdk/services/s3/model/PutBucketNotificationConfigurationRequest$Builder;
      22: pop
      23: aload_0
      24: aload_1
      25: invokestatic  #13                 // Method software/amazon/awssdk/services/s3/model/PutBucketNotificationConfigurationRequest.access$800:(Lsoftware/amazon/awssdk/services/s3/model/PutBucketNotificationConfigurationRequest;)Ljava/lang/String;
      28: invokevirtual #14                 // Method expectedBucketOwner:(Ljava/lang/String;)Lsoftware/amazon/awssdk/services/s3/model/PutBucketNotificationConfigurationRequest$Builder;
      31: pop
      32: aload_0
      33: aload_1
      34: invokestatic  #15                 // Method software/amazon/awssdk/services/s3/model/PutBucketNotificationConfigurationRequest.access$900:(Lsoftware/amazon/awssdk/services/s3/model/PutBucketNotificationConfigurationRequest;)Ljava/lang/Boolean;
      37: invokevirtual #16                 // Method skipDestinationValidation:(Ljava/lang/Boolean;)Lsoftware/amazon/awssdk/services/s3/model/PutBucketNotificationConfigurationRequest$Builder;
      40: pop
      41: return

  public final java.lang.String getBucket();
    Code:
       0: aload_0
       1: getfield      #6                  // Field bucket:Ljava/lang/String;
       4: areturn

  public final void setBucket(java.lang.String);
    Code:
       0: aload_0
       1: aload_1
       2: putfield      #6                  // Field bucket:Ljava/lang/String;
       5: return

  public final software.amazon.awssdk.services.s3.model.PutBucketNotificationConfigurationRequest$Builder bucket(java.lang.String);
    Code:
       0: aload_0
       1: aload_1
       2: putfield      #6                  // Field bucket:Ljava/lang/String;
       5: aload_0
       6: areturn

  public final software.amazon.awssdk.services.s3.model.NotificationConfiguration$Builder getNotificationConfiguration();
    Code:
       0: aload_0
       1: getfield      #5                  // Field notificationConfiguration:Lsoftware/amazon/awssdk/services/s3/model/NotificationConfiguration;
       4: ifnull        17
       7: aload_0
       8: getfield      #5                  // Field notificationConfiguration:Lsoftware/amazon/awssdk/services/s3/model/NotificationConfiguration;
      11: invokevirtual #17                 // Method software/amazon/awssdk/services/s3/model/NotificationConfiguration.toBuilder:()Lsoftware/amazon/awssdk/services/s3/model/NotificationConfiguration$Builder;
      14: goto          18
      17: aconst_null
      18: areturn

  public final void setNotificationConfiguration(software.amazon.awssdk.services.s3.model.NotificationConfiguration$BuilderImpl);
    Code:
       0: aload_0
       1: aload_1
       2: ifnull        12
       5: aload_1
       6: invokevirtual #18                 // Method software/amazon/awssdk/services/s3/model/NotificationConfiguration$BuilderImpl.build:()Lsoftware/amazon/awssdk/services/s3/model/NotificationConfiguration;
       9: goto          13
      12: aconst_null
      13: putfield      #5                  // Field notificationConfiguration:Lsoftware/amazon/awssdk/services/s3/model/NotificationConfiguration;
      16: return

  public final software.amazon.awssdk.services.s3.model.PutBucketNotificationConfigurationRequest$Builder notificationConfiguration(software.amazon.awssdk.services.s3.model.NotificationConfiguration);
    Code:
       0: aload_0
       1: aload_1
       2: putfield      #5                  // Field notificationConfiguration:Lsoftware/amazon/awssdk/services/s3/model/NotificationConfiguration;
       5: aload_0
       6: areturn

  public final java.lang.String getExpectedBucketOwner();
    Code:
       0: aload_0
       1: getfield      #4                  // Field expectedBucketOwner:Ljava/lang/String;
       4: areturn

  public final void setExpectedBucketOwner(java.lang.String);
    Code:
       0: aload_0
       1: aload_1
       2: putfield      #4                  // Field expectedBucketOwner:Ljava/lang/String;
       5: return

  public final software.amazon.awssdk.services.s3.model.PutBucketNotificationConfigurationRequest$Builder expectedBucketOwner(java.lang.String);
    Code:
       0: aload_0
       1: aload_1
       2: putfield      #4                  // Field expectedBucketOwner:Ljava/lang/String;
       5: aload_0
       6: areturn

  public final java.lang.Boolean getSkipDestinationValidation();
    Code:
       0: aload_0
       1: getfield      #3                  // Field skipDestinationValidation:Ljava/lang/Boolean;
       4: areturn

  public final void setSkipDestinationValidation(java.lang.Boolean);
    Code:
       0: aload_0
       1: aload_1
       2: putfield      #3                  // Field skipDestinationValidation:Ljava/lang/Boolean;
       5: return

  public final software.amazon.awssdk.services.s3.model.PutBucketNotificationConfigurationRequest$Builder skipDestinationValidation(java.lang.Boolean);
    Code:
       0: aload_0
       1: aload_1
       2: putfield      #3                  // Field skipDestinationValidation:Ljava/lang/Boolean;
       5: aload_0
       6: areturn

  public software.amazon.awssdk.services.s3.model.PutBucketNotificationConfigurationRequest$Builder overrideConfiguration(software.amazon.awssdk.awscore.AwsRequestOverrideConfiguration);
    Code:
       0: aload_0
       1: aload_1
       2: invokespecial #19                 // Method software/amazon/awssdk/services/s3/model/S3Request$BuilderImpl.overrideConfiguration:(Lsoftware/amazon/awssdk/awscore/AwsRequestOverrideConfiguration;)Lsoftware/amazon/awssdk/awscore/AwsRequest$Builder;
       5: pop
       6: aload_0
       7: areturn

  public software.amazon.awssdk.services.s3.model.PutBucketNotificationConfigurationRequest$Builder overrideConfiguration(java.util.function.Consumer<software.amazon.awssdk.awscore.AwsRequestOverrideConfiguration$Builder>);
    Code:
       0: aload_0
       1: aload_1
       2: invokespecial #20                 // Method software/amazon/awssdk/services/s3/model/S3Request$BuilderImpl.overrideConfiguration:(Ljava/util/function/Consumer;)Lsoftware/amazon/awssdk/awscore/AwsRequest$Builder;
       5: pop
       6: aload_0
       7: areturn

  public software.amazon.awssdk.services.s3.model.PutBucketNotificationConfigurationRequest build();
    Code:
       0: new           #21                 // class software/amazon/awssdk/services/s3/model/PutBucketNotificationConfigurationRequest
       3: dup
       4: aload_0
       5: aconst_null
       6: invokespecial #22                 // Method software/amazon/awssdk/services/s3/model/PutBucketNotificationConfigurationRequest."<init>":(Lsoftware/amazon/awssdk/services/s3/model/PutBucketNotificationConfigurationRequest$BuilderImpl;Lsoftware/amazon/awssdk/services/s3/model/PutBucketNotificationConfigurationRequest$1;)V
       9: areturn

  public java.util.List<software.amazon.awssdk.core.SdkField<?>> sdkFields();
    Code:
       0: invokestatic  #23                 // Method software/amazon/awssdk/services/s3/model/PutBucketNotificationConfigurationRequest.access$1100:()Ljava/util/List;
       3: areturn

  public software.amazon.awssdk.services.s3.model.S3Request build();
    Code:
       0: aload_0
       1: invokevirtual #24                 // Method build:()Lsoftware/amazon/awssdk/services/s3/model/PutBucketNotificationConfigurationRequest;
       4: areturn

  public software.amazon.awssdk.awscore.AwsRequest build();
    Code:
       0: aload_0
       1: invokevirtual #24                 // Method build:()Lsoftware/amazon/awssdk/services/s3/model/PutBucketNotificationConfigurationRequest;
       4: areturn

  public software.amazon.awssdk.awscore.AwsRequest$Builder overrideConfiguration(java.util.function.Consumer);
    Code:
       0: aload_0
       1: aload_1
       2: invokevirtual #25                 // Method overrideConfiguration:(Ljava/util/function/Consumer;)Lsoftware/amazon/awssdk/services/s3/model/PutBucketNotificationConfigurationRequest$Builder;
       5: areturn

  public software.amazon.awssdk.awscore.AwsRequest$Builder overrideConfiguration(software.amazon.awssdk.awscore.AwsRequestOverrideConfiguration);
    Code:
       0: aload_0
       1: aload_1
       2: invokevirtual #26                 // Method overrideConfiguration:(Lsoftware/amazon/awssdk/awscore/AwsRequestOverrideConfiguration;)Lsoftware/amazon/awssdk/services/s3/model/PutBucketNotificationConfigurationRequest$Builder;
       5: areturn

  public software.amazon.awssdk.core.SdkRequest build();
    Code:
       0: aload_0
       1: invokevirtual #24                 // Method build:()Lsoftware/amazon/awssdk/services/s3/model/PutBucketNotificationConfigurationRequest;
       4: areturn

  public java.lang.Object build();
    Code:
       0: aload_0
       1: invokevirtual #24                 // Method build:()Lsoftware/amazon/awssdk/services/s3/model/PutBucketNotificationConfigurationRequest;
       4: areturn

  static java.lang.String access$000(software.amazon.awssdk.services.s3.model.PutBucketNotificationConfigurationRequest$BuilderImpl);
    Code:
       0: aload_0
       1: getfield      #6                  // Field bucket:Ljava/lang/String;
       4: areturn

  static software.amazon.awssdk.services.s3.model.NotificationConfiguration access$100(software.amazon.awssdk.services.s3.model.PutBucketNotificationConfigurationRequest$BuilderImpl);
    Code:
       0: aload_0
       1: getfield      #5                  // Field notificationConfiguration:Lsoftware/amazon/awssdk/services/s3/model/NotificationConfiguration;
       4: areturn

  static java.lang.String access$200(software.amazon.awssdk.services.s3.model.PutBucketNotificationConfigurationRequest$BuilderImpl);
    Code:
       0: aload_0
       1: getfield      #4                  // Field expectedBucketOwner:Ljava/lang/String;
       4: areturn

  static java.lang.Boolean access$300(software.amazon.awssdk.services.s3.model.PutBucketNotificationConfigurationRequest$BuilderImpl);
    Code:
       0: aload_0
       1: getfield      #3                  // Field skipDestinationValidation:Ljava/lang/Boolean;
       4: areturn

  software.amazon.awssdk.services.s3.model.PutBucketNotificationConfigurationRequest$BuilderImpl(software.amazon.awssdk.services.s3.model.PutBucketNotificationConfigurationRequest, software.amazon.awssdk.services.s3.model.PutBucketNotificationConfigurationRequest$1);
    Code:
       0: aload_0
       1: aload_1
       2: invokespecial #2                  // Method "<init>":(Lsoftware/amazon/awssdk/services/s3/model/PutBucketNotificationConfigurationRequest;)V
       5: return

  software.amazon.awssdk.services.s3.model.PutBucketNotificationConfigurationRequest$BuilderImpl(software.amazon.awssdk.services.s3.model.PutBucketNotificationConfigurationRequest$1);
    Code:
       0: aload_0
       1: invokespecial #1                  // Method "<init>":()V
       4: return
}
