Compiled from "PutBucketAclRequest.java"
public interface software.amazon.awssdk.services.s3.model.PutBucketAclRequest$Builder extends software.amazon.awssdk.services.s3.model.S3Request$Builder, software.amazon.awssdk.core.SdkPojo, software.amazon.awssdk.utils.builder.CopyableBuilder<software.amazon.awssdk.services.s3.model.PutBucketAclRequest$Builder, software.amazon.awssdk.services.s3.model.PutBucketAclRequest> {
  public abstract software.amazon.awssdk.services.s3.model.PutBucketAclRequest$Builder acl(java.lang.String);

  public abstract software.amazon.awssdk.services.s3.model.PutBucketAclRequest$Builder acl(software.amazon.awssdk.services.s3.model.BucketCannedACL);

  public abstract software.amazon.awssdk.services.s3.model.PutBucketAclRequest$Builder accessControlPolicy(software.amazon.awssdk.services.s3.model.AccessControlPolicy);

  public default software.amazon.awssdk.services.s3.model.PutBucketAclRequest$Builder accessControlPolicy(java.util.function.Consumer<software.amazon.awssdk.services.s3.model.AccessControlPolicy$Builder>);
    Code:
       0: aload_0
       1: invokestatic  #1                  // Method software/amazon/awssdk/services/s3/model/AccessControlPolicy.builder:()Lsoftware/amazon/awssdk/services/s3/model/AccessControlPolicy$Builder;
       4: aload_1
       5: invokeinterface #2,  2            // InterfaceMethod software/amazon/awssdk/services/s3/model/AccessControlPolicy$Builder.applyMutation:(Ljava/util/function/Consumer;)Lsoftware/amazon/awssdk/utils/builder/SdkBuilder;
      10: checkcast     #3                  // class software/amazon/awssdk/services/s3/model/AccessControlPolicy$Builder
      13: invokeinterface #4,  1            // InterfaceMethod software/amazon/awssdk/services/s3/model/AccessControlPolicy$Builder.build:()Ljava/lang/Object;
      18: checkcast     #5                  // class software/amazon/awssdk/services/s3/model/AccessControlPolicy
      21: invokeinterface #6,  2            // InterfaceMethod accessControlPolicy:(Lsoftware/amazon/awssdk/services/s3/model/AccessControlPolicy;)Lsoftware/amazon/awssdk/services/s3/model/PutBucketAclRequest$Builder;
      26: areturn

  public abstract software.amazon.awssdk.services.s3.model.PutBucketAclRequest$Builder bucket(java.lang.String);

  public abstract software.amazon.awssdk.services.s3.model.PutBucketAclRequest$Builder contentMD5(java.lang.String);

  public abstract software.amazon.awssdk.services.s3.model.PutBucketAclRequest$Builder checksumAlgorithm(java.lang.String);

  public abstract software.amazon.awssdk.services.s3.model.PutBucketAclRequest$Builder checksumAlgorithm(software.amazon.awssdk.services.s3.model.ChecksumAlgorithm);

  public abstract software.amazon.awssdk.services.s3.model.PutBucketAclRequest$Builder grantFullControl(java.lang.String);

  public abstract software.amazon.awssdk.services.s3.model.PutBucketAclRequest$Builder grantRead(java.lang.String);

  public abstract software.amazon.awssdk.services.s3.model.PutBucketAclRequest$Builder grantReadACP(java.lang.String);

  public abstract software.amazon.awssdk.services.s3.model.PutBucketAclRequest$Builder grantWrite(java.lang.String);

  public abstract software.amazon.awssdk.services.s3.model.PutBucketAclRequest$Builder grantWriteACP(java.lang.String);

  public abstract software.amazon.awssdk.services.s3.model.PutBucketAclRequest$Builder expectedBucketOwner(java.lang.String);

  public abstract software.amazon.awssdk.services.s3.model.PutBucketAclRequest$Builder overrideConfiguration(software.amazon.awssdk.awscore.AwsRequestOverrideConfiguration);

  public abstract software.amazon.awssdk.services.s3.model.PutBucketAclRequest$Builder overrideConfiguration(java.util.function.Consumer<software.amazon.awssdk.awscore.AwsRequestOverrideConfiguration$Builder>);

  public default software.amazon.awssdk.awscore.AwsRequest$Builder overrideConfiguration(java.util.function.Consumer);
    Code:
       0: aload_0
       1: aload_1
       2: invokeinterface #7,  2            // InterfaceMethod overrideConfiguration:(Ljava/util/function/Consumer;)Lsoftware/amazon/awssdk/services/s3/model/PutBucketAclRequest$Builder;
       7: areturn

  public default software.amazon.awssdk.awscore.AwsRequest$Builder overrideConfiguration(software.amazon.awssdk.awscore.AwsRequestOverrideConfiguration);
    Code:
       0: aload_0
       1: aload_1
       2: invokeinterface #8,  2            // InterfaceMethod overrideConfiguration:(Lsoftware/amazon/awssdk/awscore/AwsRequestOverrideConfiguration;)Lsoftware/amazon/awssdk/services/s3/model/PutBucketAclRequest$Builder;
       7: areturn
}
