Compiled from "PutBucketAnalyticsConfigurationRequest.java"
final class software.amazon.awssdk.services.s3.model.PutBucketAnalyticsConfigurationRequest$BuilderImpl extends software.amazon.awssdk.services.s3.model.S3Request$BuilderImpl implements software.amazon.awssdk.services.s3.model.PutBucketAnalyticsConfigurationRequest$Builder {
  private java.lang.String bucket;

  private java.lang.String id;

  private software.amazon.awssdk.services.s3.model.AnalyticsConfiguration analyticsConfiguration;

  private java.lang.String expectedBucketOwner;

  private software.amazon.awssdk.services.s3.model.PutBucketAnalyticsConfigurationRequest$BuilderImpl();
    Code:
       0: aload_0
       1: invokespecial #7                  // Method software/amazon/awssdk/services/s3/model/S3Request$BuilderImpl."<init>":()V
       4: return

  private software.amazon.awssdk.services.s3.model.PutBucketAnalyticsConfigurationRequest$BuilderImpl(software.amazon.awssdk.services.s3.model.PutBucketAnalyticsConfigurationRequest);
    Code:
       0: aload_0
       1: aload_1
       2: invokespecial #8                  // Method software/amazon/awssdk/services/s3/model/S3Request$BuilderImpl."<init>":(Lsoftware/amazon/awssdk/services/s3/model/S3Request;)V
       5: aload_0
       6: aload_1
       7: invokestatic  #9                  // Method software/amazon/awssdk/services/s3/model/PutBucketAnalyticsConfigurationRequest.access$600:(Lsoftware/amazon/awssdk/services/s3/model/PutBucketAnalyticsConfigurationRequest;)Ljava/lang/String;
      10: invokevirtual #10                 // Method bucket:(Ljava/lang/String;)Lsoftware/amazon/awssdk/services/s3/model/PutBucketAnalyticsConfigurationRequest$Builder;
      13: pop
      14: aload_0
      15: aload_1
      16: invokestatic  #11                 // Method software/amazon/awssdk/services/s3/model/PutBucketAnalyticsConfigurationRequest.access$700:(Lsoftware/amazon/awssdk/services/s3/model/PutBucketAnalyticsConfigurationRequest;)Ljava/lang/String;
      19: invokevirtual #12                 // Method id:(Ljava/lang/String;)Lsoftware/amazon/awssdk/services/s3/model/PutBucketAnalyticsConfigurationRequest$Builder;
      22: pop
      23: aload_0
      24: aload_1
      25: invokestatic  #13                 // Method software/amazon/awssdk/services/s3/model/PutBucketAnalyticsConfigurationRequest.access$800:(Lsoftware/amazon/awssdk/services/s3/model/PutBucketAnalyticsConfigurationRequest;)Lsoftware/amazon/awssdk/services/s3/model/AnalyticsConfiguration;
      28: invokevirtual #14                 // Method analyticsConfiguration:(Lsoftware/amazon/awssdk/services/s3/model/AnalyticsConfiguration;)Lsoftware/amazon/awssdk/services/s3/model/PutBucketAnalyticsConfigurationRequest$Builder;
      31: pop
      32: aload_0
      33: aload_1
      34: invokestatic  #15                 // Method software/amazon/awssdk/services/s3/model/PutBucketAnalyticsConfigurationRequest.access$900:(Lsoftware/amazon/awssdk/services/s3/model/PutBucketAnalyticsConfigurationRequest;)Ljava/lang/String;
      37: invokevirtual #16                 // Method expectedBucketOwner:(Ljava/lang/String;)Lsoftware/amazon/awssdk/services/s3/model/PutBucketAnalyticsConfigurationRequest$Builder;
      40: pop
      41: return

  public final java.lang.String getBucket();
    Code:
       0: aload_0
       1: getfield      #6                  // Field bucket:Ljava/lang/String;
       4: areturn

  public final void setBucket(java.lang.String);
    Code:
       0: aload_0
       1: aload_1
       2: putfield      #6                  // Field bucket:Ljava/lang/String;
       5: return

  public final software.amazon.awssdk.services.s3.model.PutBucketAnalyticsConfigurationRequest$Builder bucket(java.lang.String);
    Code:
       0: aload_0
       1: aload_1
       2: putfield      #6                  // Field bucket:Ljava/lang/String;
       5: aload_0
       6: areturn

  public final java.lang.String getId();
    Code:
       0: aload_0
       1: getfield      #5                  // Field id:Ljava/lang/String;
       4: areturn

  public final void setId(java.lang.String);
    Code:
       0: aload_0
       1: aload_1
       2: putfield      #5                  // Field id:Ljava/lang/String;
       5: return

  public final software.amazon.awssdk.services.s3.model.PutBucketAnalyticsConfigurationRequest$Builder id(java.lang.String);
    Code:
       0: aload_0
       1: aload_1
       2: putfield      #5                  // Field id:Ljava/lang/String;
       5: aload_0
       6: areturn

  public final software.amazon.awssdk.services.s3.model.AnalyticsConfiguration$Builder getAnalyticsConfiguration();
    Code:
       0: aload_0
       1: getfield      #4                  // Field analyticsConfiguration:Lsoftware/amazon/awssdk/services/s3/model/AnalyticsConfiguration;
       4: ifnull        17
       7: aload_0
       8: getfield      #4                  // Field analyticsConfiguration:Lsoftware/amazon/awssdk/services/s3/model/AnalyticsConfiguration;
      11: invokevirtual #17                 // Method software/amazon/awssdk/services/s3/model/AnalyticsConfiguration.toBuilder:()Lsoftware/amazon/awssdk/services/s3/model/AnalyticsConfiguration$Builder;
      14: goto          18
      17: aconst_null
      18: areturn

  public final void setAnalyticsConfiguration(software.amazon.awssdk.services.s3.model.AnalyticsConfiguration$BuilderImpl);
    Code:
       0: aload_0
       1: aload_1
       2: ifnull        12
       5: aload_1
       6: invokevirtual #18                 // Method software/amazon/awssdk/services/s3/model/AnalyticsConfiguration$BuilderImpl.build:()Lsoftware/amazon/awssdk/services/s3/model/AnalyticsConfiguration;
       9: goto          13
      12: aconst_null
      13: putfield      #4                  // Field analyticsConfiguration:Lsoftware/amazon/awssdk/services/s3/model/AnalyticsConfiguration;
      16: return

  public final software.amazon.awssdk.services.s3.model.PutBucketAnalyticsConfigurationRequest$Builder analyticsConfiguration(software.amazon.awssdk.services.s3.model.AnalyticsConfiguration);
    Code:
       0: aload_0
       1: aload_1
       2: putfield      #4                  // Field analyticsConfiguration:Lsoftware/amazon/awssdk/services/s3/model/AnalyticsConfiguration;
       5: aload_0
       6: areturn

  public final java.lang.String getExpectedBucketOwner();
    Code:
       0: aload_0
       1: getfield      #3                  // Field expectedBucketOwner:Ljava/lang/String;
       4: areturn

  public final void setExpectedBucketOwner(java.lang.String);
    Code:
       0: aload_0
       1: aload_1
       2: putfield      #3                  // Field expectedBucketOwner:Ljava/lang/String;
       5: return

  public final software.amazon.awssdk.services.s3.model.PutBucketAnalyticsConfigurationRequest$Builder expectedBucketOwner(java.lang.String);
    Code:
       0: aload_0
       1: aload_1
       2: putfield      #3                  // Field expectedBucketOwner:Ljava/lang/String;
       5: aload_0
       6: areturn

  public software.amazon.awssdk.services.s3.model.PutBucketAnalyticsConfigurationRequest$Builder overrideConfiguration(software.amazon.awssdk.awscore.AwsRequestOverrideConfiguration);
    Code:
       0: aload_0
       1: aload_1
       2: invokespecial #19                 // Method software/amazon/awssdk/services/s3/model/S3Request$BuilderImpl.overrideConfiguration:(Lsoftware/amazon/awssdk/awscore/AwsRequestOverrideConfiguration;)Lsoftware/amazon/awssdk/awscore/AwsRequest$Builder;
       5: pop
       6: aload_0
       7: areturn

  public software.amazon.awssdk.services.s3.model.PutBucketAnalyticsConfigurationRequest$Builder overrideConfiguration(java.util.function.Consumer<software.amazon.awssdk.awscore.AwsRequestOverrideConfiguration$Builder>);
    Code:
       0: aload_0
       1: aload_1
       2: invokespecial #20                 // Method software/amazon/awssdk/services/s3/model/S3Request$BuilderImpl.overrideConfiguration:(Ljava/util/function/Consumer;)Lsoftware/amazon/awssdk/awscore/AwsRequest$Builder;
       5: pop
       6: aload_0
       7: areturn

  public software.amazon.awssdk.services.s3.model.PutBucketAnalyticsConfigurationRequest build();
    Code:
       0: new           #21                 // class software/amazon/awssdk/services/s3/model/PutBucketAnalyticsConfigurationRequest
       3: dup
       4: aload_0
       5: aconst_null
       6: invokespecial #22                 // Method software/amazon/awssdk/services/s3/model/PutBucketAnalyticsConfigurationRequest."<init>":(Lsoftware/amazon/awssdk/services/s3/model/PutBucketAnalyticsConfigurationRequest$BuilderImpl;Lsoftware/amazon/awssdk/services/s3/model/PutBucketAnalyticsConfigurationRequest$1;)V
       9: areturn

  public java.util.List<software.amazon.awssdk.core.SdkField<?>> sdkFields();
    Code:
       0: invokestatic  #23                 // Method software/amazon/awssdk/services/s3/model/PutBucketAnalyticsConfigurationRequest.access$1100:()Ljava/util/List;
       3: areturn

  public software.amazon.awssdk.services.s3.model.S3Request build();
    Code:
       0: aload_0
       1: invokevirtual #24                 // Method build:()Lsoftware/amazon/awssdk/services/s3/model/PutBucketAnalyticsConfigurationRequest;
       4: areturn

  public software.amazon.awssdk.awscore.AwsRequest build();
    Code:
       0: aload_0
       1: invokevirtual #24                 // Method build:()Lsoftware/amazon/awssdk/services/s3/model/PutBucketAnalyticsConfigurationRequest;
       4: areturn

  public software.amazon.awssdk.awscore.AwsRequest$Builder overrideConfiguration(java.util.function.Consumer);
    Code:
       0: aload_0
       1: aload_1
       2: invokevirtual #25                 // Method overrideConfiguration:(Ljava/util/function/Consumer;)Lsoftware/amazon/awssdk/services/s3/model/PutBucketAnalyticsConfigurationRequest$Builder;
       5: areturn

  public software.amazon.awssdk.awscore.AwsRequest$Builder overrideConfiguration(software.amazon.awssdk.awscore.AwsRequestOverrideConfiguration);
    Code:
       0: aload_0
       1: aload_1
       2: invokevirtual #26                 // Method overrideConfiguration:(Lsoftware/amazon/awssdk/awscore/AwsRequestOverrideConfiguration;)Lsoftware/amazon/awssdk/services/s3/model/PutBucketAnalyticsConfigurationRequest$Builder;
       5: areturn

  public software.amazon.awssdk.core.SdkRequest build();
    Code:
       0: aload_0
       1: invokevirtual #24                 // Method build:()Lsoftware/amazon/awssdk/services/s3/model/PutBucketAnalyticsConfigurationRequest;
       4: areturn

  public java.lang.Object build();
    Code:
       0: aload_0
       1: invokevirtual #24                 // Method build:()Lsoftware/amazon/awssdk/services/s3/model/PutBucketAnalyticsConfigurationRequest;
       4: areturn

  static java.lang.String access$000(software.amazon.awssdk.services.s3.model.PutBucketAnalyticsConfigurationRequest$BuilderImpl);
    Code:
       0: aload_0
       1: getfield      #6                  // Field bucket:Ljava/lang/String;
       4: areturn

  static java.lang.String access$100(software.amazon.awssdk.services.s3.model.PutBucketAnalyticsConfigurationRequest$BuilderImpl);
    Code:
       0: aload_0
       1: getfield      #5                  // Field id:Ljava/lang/String;
       4: areturn

  static software.amazon.awssdk.services.s3.model.AnalyticsConfiguration access$200(software.amazon.awssdk.services.s3.model.PutBucketAnalyticsConfigurationRequest$BuilderImpl);
    Code:
       0: aload_0
       1: getfield      #4                  // Field analyticsConfiguration:Lsoftware/amazon/awssdk/services/s3/model/AnalyticsConfiguration;
       4: areturn

  static java.lang.String access$300(software.amazon.awssdk.services.s3.model.PutBucketAnalyticsConfigurationRequest$BuilderImpl);
    Code:
       0: aload_0
       1: getfield      #3                  // Field expectedBucketOwner:Ljava/lang/String;
       4: areturn

  software.amazon.awssdk.services.s3.model.PutBucketAnalyticsConfigurationRequest$BuilderImpl(software.amazon.awssdk.services.s3.model.PutBucketAnalyticsConfigurationRequest, software.amazon.awssdk.services.s3.model.PutBucketAnalyticsConfigurationRequest$1);
    Code:
       0: aload_0
       1: aload_1
       2: invokespecial #2                  // Method "<init>":(Lsoftware/amazon/awssdk/services/s3/model/PutBucketAnalyticsConfigurationRequest;)V
       5: return

  software.amazon.awssdk.services.s3.model.PutBucketAnalyticsConfigurationRequest$BuilderImpl(software.amazon.awssdk.services.s3.model.PutBucketAnalyticsConfigurationRequest$1);
    Code:
       0: aload_0
       1: invokespecial #1                  // Method "<init>":()V
       4: return
}
