Compiled from "PutBucketPolicyRequest.java"
public interface software.amazon.awssdk.services.s3.model.PutBucketPolicyRequest$Builder extends software.amazon.awssdk.services.s3.model.S3Request$Builder, software.amazon.awssdk.core.SdkPojo, software.amazon.awssdk.utils.builder.CopyableBuilder<software.amazon.awssdk.services.s3.model.PutBucketPolicyRequest$Builder, software.amazon.awssdk.services.s3.model.PutBucketPolicyRequest> {
  public abstract software.amazon.awssdk.services.s3.model.PutBucketPolicyRequest$Builder bucket(java.lang.String);

  public abstract software.amazon.awssdk.services.s3.model.PutBucketPolicyRequest$Builder contentMD5(java.lang.String);

  public abstract software.amazon.awssdk.services.s3.model.PutBucketPolicyRequest$Builder checksumAlgorithm(java.lang.String);

  public abstract software.amazon.awssdk.services.s3.model.PutBucketPolicyRequest$Builder checksumAlgorithm(software.amazon.awssdk.services.s3.model.ChecksumAlgorithm);

  public abstract software.amazon.awssdk.services.s3.model.PutBucketPolicyRequest$Builder confirmRemoveSelfBucketAccess(java.lang.Boolean);

  public abstract software.amazon.awssdk.services.s3.model.PutBucketPolicyRequest$Builder policy(java.lang.String);

  public abstract software.amazon.awssdk.services.s3.model.PutBucketPolicyRequest$Builder expectedBucketOwner(java.lang.String);

  public abstract software.amazon.awssdk.services.s3.model.PutBucketPolicyRequest$Builder overrideConfiguration(software.amazon.awssdk.awscore.AwsRequestOverrideConfiguration);

  public abstract software.amazon.awssdk.services.s3.model.PutBucketPolicyRequest$Builder overrideConfiguration(java.util.function.Consumer<software.amazon.awssdk.awscore.AwsRequestOverrideConfiguration$Builder>);

  public default software.amazon.awssdk.awscore.AwsRequest$Builder overrideConfiguration(java.util.function.Consumer);
    Code:
       0: aload_0
       1: aload_1
       2: invokeinterface #1,  2            // InterfaceMethod overrideConfiguration:(Ljava/util/function/Consumer;)Lsoftware/amazon/awssdk/services/s3/model/PutBucketPolicyRequest$Builder;
       7: areturn

  public default software.amazon.awssdk.awscore.AwsRequest$Builder overrideConfiguration(software.amazon.awssdk.awscore.AwsRequestOverrideConfiguration);
    Code:
       0: aload_0
       1: aload_1
       2: invokeinterface #2,  2            // InterfaceMethod overrideConfiguration:(Lsoftware/amazon/awssdk/awscore/AwsRequestOverrideConfiguration;)Lsoftware/amazon/awssdk/services/s3/model/PutBucketPolicyRequest$Builder;
       7: areturn
}
