Compiled from "PutObjectRetentionRequest.java"
public interface software.amazon.awssdk.services.s3.model.PutObjectRetentionRequest$Builder extends software.amazon.awssdk.services.s3.model.S3Request$Builder, software.amazon.awssdk.core.SdkPojo, software.amazon.awssdk.utils.builder.CopyableBuilder<software.amazon.awssdk.services.s3.model.PutObjectRetentionRequest$Builder, software.amazon.awssdk.services.s3.model.PutObjectRetentionRequest> {
  public abstract software.amazon.awssdk.services.s3.model.PutObjectRetentionRequest$Builder bucket(java.lang.String);

  public abstract software.amazon.awssdk.services.s3.model.PutObjectRetentionRequest$Builder key(java.lang.String);

  public abstract software.amazon.awssdk.services.s3.model.PutObjectRetentionRequest$Builder retention(software.amazon.awssdk.services.s3.model.ObjectLockRetention);

  public default software.amazon.awssdk.services.s3.model.PutObjectRetentionRequest$Builder retention(java.util.function.Consumer<software.amazon.awssdk.services.s3.model.ObjectLockRetention$Builder>);
    Code:
       0: aload_0
       1: invokestatic  #1                  // Method software/amazon/awssdk/services/s3/model/ObjectLockRetention.builder:()Lsoftware/amazon/awssdk/services/s3/model/ObjectLockRetention$Builder;
       4: aload_1
       5: invokeinterface #2,  2            // InterfaceMethod software/amazon/awssdk/services/s3/model/ObjectLockRetention$Builder.applyMutation:(Ljava/util/function/Consumer;)Lsoftware/amazon/awssdk/utils/builder/SdkBuilder;
      10: checkcast     #3                  // class software/amazon/awssdk/services/s3/model/ObjectLockRetention$Builder
      13: invokeinterface #4,  1            // InterfaceMethod software/amazon/awssdk/services/s3/model/ObjectLockRetention$Builder.build:()Ljava/lang/Object;
      18: checkcast     #5                  // class software/amazon/awssdk/services/s3/model/ObjectLockRetention
      21: invokeinterface #6,  2            // InterfaceMethod retention:(Lsoftware/amazon/awssdk/services/s3/model/ObjectLockRetention;)Lsoftware/amazon/awssdk/services/s3/model/PutObjectRetentionRequest$Builder;
      26: areturn

  public abstract software.amazon.awssdk.services.s3.model.PutObjectRetentionRequest$Builder requestPayer(java.lang.String);

  public abstract software.amazon.awssdk.services.s3.model.PutObjectRetentionRequest$Builder requestPayer(software.amazon.awssdk.services.s3.model.RequestPayer);

  public abstract software.amazon.awssdk.services.s3.model.PutObjectRetentionRequest$Builder versionId(java.lang.String);

  public abstract software.amazon.awssdk.services.s3.model.PutObjectRetentionRequest$Builder bypassGovernanceRetention(java.lang.Boolean);

  public abstract software.amazon.awssdk.services.s3.model.PutObjectRetentionRequest$Builder contentMD5(java.lang.String);

  public abstract software.amazon.awssdk.services.s3.model.PutObjectRetentionRequest$Builder checksumAlgorithm(java.lang.String);

  public abstract software.amazon.awssdk.services.s3.model.PutObjectRetentionRequest$Builder checksumAlgorithm(software.amazon.awssdk.services.s3.model.ChecksumAlgorithm);

  public abstract software.amazon.awssdk.services.s3.model.PutObjectRetentionRequest$Builder expectedBucketOwner(java.lang.String);

  public abstract software.amazon.awssdk.services.s3.model.PutObjectRetentionRequest$Builder overrideConfiguration(software.amazon.awssdk.awscore.AwsRequestOverrideConfiguration);

  public abstract software.amazon.awssdk.services.s3.model.PutObjectRetentionRequest$Builder overrideConfiguration(java.util.function.Consumer<software.amazon.awssdk.awscore.AwsRequestOverrideConfiguration$Builder>);

  public default software.amazon.awssdk.awscore.AwsRequest$Builder overrideConfiguration(java.util.function.Consumer);
    Code:
       0: aload_0
       1: aload_1
       2: invokeinterface #7,  2            // InterfaceMethod overrideConfiguration:(Ljava/util/function/Consumer;)Lsoftware/amazon/awssdk/services/s3/model/PutObjectRetentionRequest$Builder;
       7: areturn

  public default software.amazon.awssdk.awscore.AwsRequest$Builder overrideConfiguration(software.amazon.awssdk.awscore.AwsRequestOverrideConfiguration);
    Code:
       0: aload_0
       1: aload_1
       2: invokeinterface #8,  2            // InterfaceMethod overrideConfiguration:(Lsoftware/amazon/awssdk/awscore/AwsRequestOverrideConfiguration;)Lsoftware/amazon/awssdk/services/s3/model/PutObjectRetentionRequest$Builder;
       7: areturn
}
