Compiled from "PutObjectAclRequest.java"
final class software.amazon.awssdk.services.s3.model.PutObjectAclRequest$BuilderImpl extends software.amazon.awssdk.services.s3.model.S3Request$BuilderImpl implements software.amazon.awssdk.services.s3.model.PutObjectAclRequest$Builder {
  private java.lang.String acl;

  private software.amazon.awssdk.services.s3.model.AccessControlPolicy accessControlPolicy;

  private java.lang.String bucket;

  private java.lang.String contentMD5;

  private java.lang.String checksumAlgorithm;

  private java.lang.String grantFullControl;

  private java.lang.String grantRead;

  private java.lang.String grantReadACP;

  private java.lang.String grantWrite;

  private java.lang.String grantWriteACP;

  private java.lang.String key;

  private java.lang.String requestPayer;

  private java.lang.String versionId;

  private java.lang.String expectedBucketOwner;

  private software.amazon.awssdk.services.s3.model.PutObjectAclRequest$BuilderImpl();
    Code:
       0: aload_0
       1: invokespecial #17                 // Method software/amazon/awssdk/services/s3/model/S3Request$BuilderImpl."<init>":()V
       4: return

  private software.amazon.awssdk.services.s3.model.PutObjectAclRequest$BuilderImpl(software.amazon.awssdk.services.s3.model.PutObjectAclRequest);
    Code:
       0: aload_0
       1: aload_1
       2: invokespecial #18                 // Method software/amazon/awssdk/services/s3/model/S3Request$BuilderImpl."<init>":(Lsoftware/amazon/awssdk/services/s3/model/S3Request;)V
       5: aload_0
       6: aload_1
       7: invokestatic  #19                 // Method software/amazon/awssdk/services/s3/model/PutObjectAclRequest.access$1600:(Lsoftware/amazon/awssdk/services/s3/model/PutObjectAclRequest;)Ljava/lang/String;
      10: invokevirtual #20                 // Method acl:(Ljava/lang/String;)Lsoftware/amazon/awssdk/services/s3/model/PutObjectAclRequest$Builder;
      13: pop
      14: aload_0
      15: aload_1
      16: invokestatic  #21                 // Method software/amazon/awssdk/services/s3/model/PutObjectAclRequest.access$1700:(Lsoftware/amazon/awssdk/services/s3/model/PutObjectAclRequest;)Lsoftware/amazon/awssdk/services/s3/model/AccessControlPolicy;
      19: invokevirtual #22                 // Method accessControlPolicy:(Lsoftware/amazon/awssdk/services/s3/model/AccessControlPolicy;)Lsoftware/amazon/awssdk/services/s3/model/PutObjectAclRequest$Builder;
      22: pop
      23: aload_0
      24: aload_1
      25: invokestatic  #23                 // Method software/amazon/awssdk/services/s3/model/PutObjectAclRequest.access$1800:(Lsoftware/amazon/awssdk/services/s3/model/PutObjectAclRequest;)Ljava/lang/String;
      28: invokevirtual #24                 // Method bucket:(Ljava/lang/String;)Lsoftware/amazon/awssdk/services/s3/model/PutObjectAclRequest$Builder;
      31: pop
      32: aload_0
      33: aload_1
      34: invokestatic  #25                 // Method software/amazon/awssdk/services/s3/model/PutObjectAclRequest.access$1900:(Lsoftware/amazon/awssdk/services/s3/model/PutObjectAclRequest;)Ljava/lang/String;
      37: invokevirtual #26                 // Method contentMD5:(Ljava/lang/String;)Lsoftware/amazon/awssdk/services/s3/model/PutObjectAclRequest$Builder;
      40: pop
      41: aload_0
      42: aload_1
      43: invokestatic  #27                 // Method software/amazon/awssdk/services/s3/model/PutObjectAclRequest.access$2000:(Lsoftware/amazon/awssdk/services/s3/model/PutObjectAclRequest;)Ljava/lang/String;
      46: invokevirtual #28                 // Method checksumAlgorithm:(Ljava/lang/String;)Lsoftware/amazon/awssdk/services/s3/model/PutObjectAclRequest$Builder;
      49: pop
      50: aload_0
      51: aload_1
      52: invokestatic  #29                 // Method software/amazon/awssdk/services/s3/model/PutObjectAclRequest.access$2100:(Lsoftware/amazon/awssdk/services/s3/model/PutObjectAclRequest;)Ljava/lang/String;
      55: invokevirtual #30                 // Method grantFullControl:(Ljava/lang/String;)Lsoftware/amazon/awssdk/services/s3/model/PutObjectAclRequest$Builder;
      58: pop
      59: aload_0
      60: aload_1
      61: invokestatic  #31                 // Method software/amazon/awssdk/services/s3/model/PutObjectAclRequest.access$2200:(Lsoftware/amazon/awssdk/services/s3/model/PutObjectAclRequest;)Ljava/lang/String;
      64: invokevirtual #32                 // Method grantRead:(Ljava/lang/String;)Lsoftware/amazon/awssdk/services/s3/model/PutObjectAclRequest$Builder;
      67: pop
      68: aload_0
      69: aload_1
      70: invokestatic  #33                 // Method software/amazon/awssdk/services/s3/model/PutObjectAclRequest.access$2300:(Lsoftware/amazon/awssdk/services/s3/model/PutObjectAclRequest;)Ljava/lang/String;
      73: invokevirtual #34                 // Method grantReadACP:(Ljava/lang/String;)Lsoftware/amazon/awssdk/services/s3/model/PutObjectAclRequest$Builder;
      76: pop
      77: aload_0
      78: aload_1
      79: invokestatic  #35                 // Method software/amazon/awssdk/services/s3/model/PutObjectAclRequest.access$2400:(Lsoftware/amazon/awssdk/services/s3/model/PutObjectAclRequest;)Ljava/lang/String;
      82: invokevirtual #36                 // Method grantWrite:(Ljava/lang/String;)Lsoftware/amazon/awssdk/services/s3/model/PutObjectAclRequest$Builder;
      85: pop
      86: aload_0
      87: aload_1
      88: invokestatic  #37                 // Method software/amazon/awssdk/services/s3/model/PutObjectAclRequest.access$2500:(Lsoftware/amazon/awssdk/services/s3/model/PutObjectAclRequest;)Ljava/lang/String;
      91: invokevirtual #38                 // Method grantWriteACP:(Ljava/lang/String;)Lsoftware/amazon/awssdk/services/s3/model/PutObjectAclRequest$Builder;
      94: pop
      95: aload_0
      96: aload_1
      97: invokestatic  #39                 // Method software/amazon/awssdk/services/s3/model/PutObjectAclRequest.access$2600:(Lsoftware/amazon/awssdk/services/s3/model/PutObjectAclRequest;)Ljava/lang/String;
     100: invokevirtual #40                 // Method key:(Ljava/lang/String;)Lsoftware/amazon/awssdk/services/s3/model/PutObjectAclRequest$Builder;
     103: pop
     104: aload_0
     105: aload_1
     106: invokestatic  #41                 // Method software/amazon/awssdk/services/s3/model/PutObjectAclRequest.access$2700:(Lsoftware/amazon/awssdk/services/s3/model/PutObjectAclRequest;)Ljava/lang/String;
     109: invokevirtual #42                 // Method requestPayer:(Ljava/lang/String;)Lsoftware/amazon/awssdk/services/s3/model/PutObjectAclRequest$Builder;
     112: pop
     113: aload_0
     114: aload_1
     115: invokestatic  #43                 // Method software/amazon/awssdk/services/s3/model/PutObjectAclRequest.access$2800:(Lsoftware/amazon/awssdk/services/s3/model/PutObjectAclRequest;)Ljava/lang/String;
     118: invokevirtual #44                 // Method versionId:(Ljava/lang/String;)Lsoftware/amazon/awssdk/services/s3/model/PutObjectAclRequest$Builder;
     121: pop
     122: aload_0
     123: aload_1
     124: invokestatic  #45                 // Method software/amazon/awssdk/services/s3/model/PutObjectAclRequest.access$2900:(Lsoftware/amazon/awssdk/services/s3/model/PutObjectAclRequest;)Ljava/lang/String;
     127: invokevirtual #46                 // Method expectedBucketOwner:(Ljava/lang/String;)Lsoftware/amazon/awssdk/services/s3/model/PutObjectAclRequest$Builder;
     130: pop
     131: return

  public final java.lang.String getAcl();
    Code:
       0: aload_0
       1: getfield      #16                 // Field acl:Ljava/lang/String;
       4: areturn

  public final void setAcl(java.lang.String);
    Code:
       0: aload_0
       1: aload_1
       2: putfield      #16                 // Field acl:Ljava/lang/String;
       5: return

  public final software.amazon.awssdk.services.s3.model.PutObjectAclRequest$Builder acl(java.lang.String);
    Code:
       0: aload_0
       1: aload_1
       2: putfield      #16                 // Field acl:Ljava/lang/String;
       5: aload_0
       6: areturn

  public final software.amazon.awssdk.services.s3.model.PutObjectAclRequest$Builder acl(software.amazon.awssdk.services.s3.model.ObjectCannedACL);
    Code:
       0: aload_0
       1: aload_1
       2: ifnonnull     9
       5: aconst_null
       6: goto          13
       9: aload_1
      10: invokevirtual #47                 // Method software/amazon/awssdk/services/s3/model/ObjectCannedACL.toString:()Ljava/lang/String;
      13: invokevirtual #20                 // Method acl:(Ljava/lang/String;)Lsoftware/amazon/awssdk/services/s3/model/PutObjectAclRequest$Builder;
      16: pop
      17: aload_0
      18: areturn

  public final software.amazon.awssdk.services.s3.model.AccessControlPolicy$Builder getAccessControlPolicy();
    Code:
       0: aload_0
       1: getfield      #15                 // Field accessControlPolicy:Lsoftware/amazon/awssdk/services/s3/model/AccessControlPolicy;
       4: ifnull        17
       7: aload_0
       8: getfield      #15                 // Field accessControlPolicy:Lsoftware/amazon/awssdk/services/s3/model/AccessControlPolicy;
      11: invokevirtual #48                 // Method software/amazon/awssdk/services/s3/model/AccessControlPolicy.toBuilder:()Lsoftware/amazon/awssdk/services/s3/model/AccessControlPolicy$Builder;
      14: goto          18
      17: aconst_null
      18: areturn

  public final void setAccessControlPolicy(software.amazon.awssdk.services.s3.model.AccessControlPolicy$BuilderImpl);
    Code:
       0: aload_0
       1: aload_1
       2: ifnull        12
       5: aload_1
       6: invokevirtual #49                 // Method software/amazon/awssdk/services/s3/model/AccessControlPolicy$BuilderImpl.build:()Lsoftware/amazon/awssdk/services/s3/model/AccessControlPolicy;
       9: goto          13
      12: aconst_null
      13: putfield      #15                 // Field accessControlPolicy:Lsoftware/amazon/awssdk/services/s3/model/AccessControlPolicy;
      16: return

  public final software.amazon.awssdk.services.s3.model.PutObjectAclRequest$Builder accessControlPolicy(software.amazon.awssdk.services.s3.model.AccessControlPolicy);
    Code:
       0: aload_0
       1: aload_1
       2: putfield      #15                 // Field accessControlPolicy:Lsoftware/amazon/awssdk/services/s3/model/AccessControlPolicy;
       5: aload_0
       6: areturn

  public final java.lang.String getBucket();
    Code:
       0: aload_0
       1: getfield      #14                 // Field bucket:Ljava/lang/String;
       4: areturn

  public final void setBucket(java.lang.String);
    Code:
       0: aload_0
       1: aload_1
       2: putfield      #14                 // Field bucket:Ljava/lang/String;
       5: return

  public final software.amazon.awssdk.services.s3.model.PutObjectAclRequest$Builder bucket(java.lang.String);
    Code:
       0: aload_0
       1: aload_1
       2: putfield      #14                 // Field bucket:Ljava/lang/String;
       5: aload_0
       6: areturn

  public final java.lang.String getContentMD5();
    Code:
       0: aload_0
       1: getfield      #13                 // Field contentMD5:Ljava/lang/String;
       4: areturn

  public final void setContentMD5(java.lang.String);
    Code:
       0: aload_0
       1: aload_1
       2: putfield      #13                 // Field contentMD5:Ljava/lang/String;
       5: return

  public final software.amazon.awssdk.services.s3.model.PutObjectAclRequest$Builder contentMD5(java.lang.String);
    Code:
       0: aload_0
       1: aload_1
       2: putfield      #13                 // Field contentMD5:Ljava/lang/String;
       5: aload_0
       6: areturn

  public final java.lang.String getChecksumAlgorithm();
    Code:
       0: aload_0
       1: getfield      #12                 // Field checksumAlgorithm:Ljava/lang/String;
       4: areturn

  public final void setChecksumAlgorithm(java.lang.String);
    Code:
       0: aload_0
       1: aload_1
       2: putfield      #12                 // Field checksumAlgorithm:Ljava/lang/String;
       5: return

  public final software.amazon.awssdk.services.s3.model.PutObjectAclRequest$Builder checksumAlgorithm(java.lang.String);
    Code:
       0: aload_0
       1: aload_1
       2: putfield      #12                 // Field checksumAlgorithm:Ljava/lang/String;
       5: aload_0
       6: areturn

  public final software.amazon.awssdk.services.s3.model.PutObjectAclRequest$Builder checksumAlgorithm(software.amazon.awssdk.services.s3.model.ChecksumAlgorithm);
    Code:
       0: aload_0
       1: aload_1
       2: ifnonnull     9
       5: aconst_null
       6: goto          13
       9: aload_1
      10: invokevirtual #50                 // Method software/amazon/awssdk/services/s3/model/ChecksumAlgorithm.toString:()Ljava/lang/String;
      13: invokevirtual #28                 // Method checksumAlgorithm:(Ljava/lang/String;)Lsoftware/amazon/awssdk/services/s3/model/PutObjectAclRequest$Builder;
      16: pop
      17: aload_0
      18: areturn

  public final java.lang.String getGrantFullControl();
    Code:
       0: aload_0
       1: getfield      #11                 // Field grantFullControl:Ljava/lang/String;
       4: areturn

  public final void setGrantFullControl(java.lang.String);
    Code:
       0: aload_0
       1: aload_1
       2: putfield      #11                 // Field grantFullControl:Ljava/lang/String;
       5: return

  public final software.amazon.awssdk.services.s3.model.PutObjectAclRequest$Builder grantFullControl(java.lang.String);
    Code:
       0: aload_0
       1: aload_1
       2: putfield      #11                 // Field grantFullControl:Ljava/lang/String;
       5: aload_0
       6: areturn

  public final java.lang.String getGrantRead();
    Code:
       0: aload_0
       1: getfield      #10                 // Field grantRead:Ljava/lang/String;
       4: areturn

  public final void setGrantRead(java.lang.String);
    Code:
       0: aload_0
       1: aload_1
       2: putfield      #10                 // Field grantRead:Ljava/lang/String;
       5: return

  public final software.amazon.awssdk.services.s3.model.PutObjectAclRequest$Builder grantRead(java.lang.String);
    Code:
       0: aload_0
       1: aload_1
       2: putfield      #10                 // Field grantRead:Ljava/lang/String;
       5: aload_0
       6: areturn

  public final java.lang.String getGrantReadACP();
    Code:
       0: aload_0
       1: getfield      #9                  // Field grantReadACP:Ljava/lang/String;
       4: areturn

  public final void setGrantReadACP(java.lang.String);
    Code:
       0: aload_0
       1: aload_1
       2: putfield      #9                  // Field grantReadACP:Ljava/lang/String;
       5: return

  public final software.amazon.awssdk.services.s3.model.PutObjectAclRequest$Builder grantReadACP(java.lang.String);
    Code:
       0: aload_0
       1: aload_1
       2: putfield      #9                  // Field grantReadACP:Ljava/lang/String;
       5: aload_0
       6: areturn

  public final java.lang.String getGrantWrite();
    Code:
       0: aload_0
       1: getfield      #8                  // Field grantWrite:Ljava/lang/String;
       4: areturn

  public final void setGrantWrite(java.lang.String);
    Code:
       0: aload_0
       1: aload_1
       2: putfield      #8                  // Field grantWrite:Ljava/lang/String;
       5: return

  public final software.amazon.awssdk.services.s3.model.PutObjectAclRequest$Builder grantWrite(java.lang.String);
    Code:
       0: aload_0
       1: aload_1
       2: putfield      #8                  // Field grantWrite:Ljava/lang/String;
       5: aload_0
       6: areturn

  public final java.lang.String getGrantWriteACP();
    Code:
       0: aload_0
       1: getfield      #7                  // Field grantWriteACP:Ljava/lang/String;
       4: areturn

  public final void setGrantWriteACP(java.lang.String);
    Code:
       0: aload_0
       1: aload_1
       2: putfield      #7                  // Field grantWriteACP:Ljava/lang/String;
       5: return

  public final software.amazon.awssdk.services.s3.model.PutObjectAclRequest$Builder grantWriteACP(java.lang.String);
    Code:
       0: aload_0
       1: aload_1
       2: putfield      #7                  // Field grantWriteACP:Ljava/lang/String;
       5: aload_0
       6: areturn

  public final java.lang.String getKey();
    Code:
       0: aload_0
       1: getfield      #6                  // Field key:Ljava/lang/String;
       4: areturn

  public final void setKey(java.lang.String);
    Code:
       0: aload_0
       1: aload_1
       2: putfield      #6                  // Field key:Ljava/lang/String;
       5: return

  public final software.amazon.awssdk.services.s3.model.PutObjectAclRequest$Builder key(java.lang.String);
    Code:
       0: aload_0
       1: aload_1
       2: putfield      #6                  // Field key:Ljava/lang/String;
       5: aload_0
       6: areturn

  public final java.lang.String getRequestPayer();
    Code:
       0: aload_0
       1: getfield      #5                  // Field requestPayer:Ljava/lang/String;
       4: areturn

  public final void setRequestPayer(java.lang.String);
    Code:
       0: aload_0
       1: aload_1
       2: putfield      #5                  // Field requestPayer:Ljava/lang/String;
       5: return

  public final software.amazon.awssdk.services.s3.model.PutObjectAclRequest$Builder requestPayer(java.lang.String);
    Code:
       0: aload_0
       1: aload_1
       2: putfield      #5                  // Field requestPayer:Ljava/lang/String;
       5: aload_0
       6: areturn

  public final software.amazon.awssdk.services.s3.model.PutObjectAclRequest$Builder requestPayer(software.amazon.awssdk.services.s3.model.RequestPayer);
    Code:
       0: aload_0
       1: aload_1
       2: ifnonnull     9
       5: aconst_null
       6: goto          13
       9: aload_1
      10: invokevirtual #51                 // Method software/amazon/awssdk/services/s3/model/RequestPayer.toString:()Ljava/lang/String;
      13: invokevirtual #42                 // Method requestPayer:(Ljava/lang/String;)Lsoftware/amazon/awssdk/services/s3/model/PutObjectAclRequest$Builder;
      16: pop
      17: aload_0
      18: areturn

  public final java.lang.String getVersionId();
    Code:
       0: aload_0
       1: getfield      #4                  // Field versionId:Ljava/lang/String;
       4: areturn

  public final void setVersionId(java.lang.String);
    Code:
       0: aload_0
       1: aload_1
       2: putfield      #4                  // Field versionId:Ljava/lang/String;
       5: return

  public final software.amazon.awssdk.services.s3.model.PutObjectAclRequest$Builder versionId(java.lang.String);
    Code:
       0: aload_0
       1: aload_1
       2: putfield      #4                  // Field versionId:Ljava/lang/String;
       5: aload_0
       6: areturn

  public final java.lang.String getExpectedBucketOwner();
    Code:
       0: aload_0
       1: getfield      #3                  // Field expectedBucketOwner:Ljava/lang/String;
       4: areturn

  public final void setExpectedBucketOwner(java.lang.String);
    Code:
       0: aload_0
       1: aload_1
       2: putfield      #3                  // Field expectedBucketOwner:Ljava/lang/String;
       5: return

  public final software.amazon.awssdk.services.s3.model.PutObjectAclRequest$Builder expectedBucketOwner(java.lang.String);
    Code:
       0: aload_0
       1: aload_1
       2: putfield      #3                  // Field expectedBucketOwner:Ljava/lang/String;
       5: aload_0
       6: areturn

  public software.amazon.awssdk.services.s3.model.PutObjectAclRequest$Builder overrideConfiguration(software.amazon.awssdk.awscore.AwsRequestOverrideConfiguration);
    Code:
       0: aload_0
       1: aload_1
       2: invokespecial #52                 // Method software/amazon/awssdk/services/s3/model/S3Request$BuilderImpl.overrideConfiguration:(Lsoftware/amazon/awssdk/awscore/AwsRequestOverrideConfiguration;)Lsoftware/amazon/awssdk/awscore/AwsRequest$Builder;
       5: pop
       6: aload_0
       7: areturn

  public software.amazon.awssdk.services.s3.model.PutObjectAclRequest$Builder overrideConfiguration(java.util.function.Consumer<software.amazon.awssdk.awscore.AwsRequestOverrideConfiguration$Builder>);
    Code:
       0: aload_0
       1: aload_1
       2: invokespecial #53                 // Method software/amazon/awssdk/services/s3/model/S3Request$BuilderImpl.overrideConfiguration:(Ljava/util/function/Consumer;)Lsoftware/amazon/awssdk/awscore/AwsRequest$Builder;
       5: pop
       6: aload_0
       7: areturn

  public software.amazon.awssdk.services.s3.model.PutObjectAclRequest build();
    Code:
       0: new           #54                 // class software/amazon/awssdk/services/s3/model/PutObjectAclRequest
       3: dup
       4: aload_0
       5: aconst_null
       6: invokespecial #55                 // Method software/amazon/awssdk/services/s3/model/PutObjectAclRequest."<init>":(Lsoftware/amazon/awssdk/services/s3/model/PutObjectAclRequest$BuilderImpl;Lsoftware/amazon/awssdk/services/s3/model/PutObjectAclRequest$1;)V
       9: areturn

  public java.util.List<software.amazon.awssdk.core.SdkField<?>> sdkFields();
    Code:
       0: invokestatic  #56                 // Method software/amazon/awssdk/services/s3/model/PutObjectAclRequest.access$3100:()Ljava/util/List;
       3: areturn

  public software.amazon.awssdk.services.s3.model.S3Request build();
    Code:
       0: aload_0
       1: invokevirtual #57                 // Method build:()Lsoftware/amazon/awssdk/services/s3/model/PutObjectAclRequest;
       4: areturn

  public software.amazon.awssdk.awscore.AwsRequest build();
    Code:
       0: aload_0
       1: invokevirtual #57                 // Method build:()Lsoftware/amazon/awssdk/services/s3/model/PutObjectAclRequest;
       4: areturn

  public software.amazon.awssdk.awscore.AwsRequest$Builder overrideConfiguration(java.util.function.Consumer);
    Code:
       0: aload_0
       1: aload_1
       2: invokevirtual #58                 // Method overrideConfiguration:(Ljava/util/function/Consumer;)Lsoftware/amazon/awssdk/services/s3/model/PutObjectAclRequest$Builder;
       5: areturn

  public software.amazon.awssdk.awscore.AwsRequest$Builder overrideConfiguration(software.amazon.awssdk.awscore.AwsRequestOverrideConfiguration);
    Code:
       0: aload_0
       1: aload_1
       2: invokevirtual #59                 // Method overrideConfiguration:(Lsoftware/amazon/awssdk/awscore/AwsRequestOverrideConfiguration;)Lsoftware/amazon/awssdk/services/s3/model/PutObjectAclRequest$Builder;
       5: areturn

  public software.amazon.awssdk.core.SdkRequest build();
    Code:
       0: aload_0
       1: invokevirtual #57                 // Method build:()Lsoftware/amazon/awssdk/services/s3/model/PutObjectAclRequest;
       4: areturn

  public java.lang.Object build();
    Code:
       0: aload_0
       1: invokevirtual #57                 // Method build:()Lsoftware/amazon/awssdk/services/s3/model/PutObjectAclRequest;
       4: areturn

  static java.lang.String access$000(software.amazon.awssdk.services.s3.model.PutObjectAclRequest$BuilderImpl);
    Code:
       0: aload_0
       1: getfield      #16                 // Field acl:Ljava/lang/String;
       4: areturn

  static software.amazon.awssdk.services.s3.model.AccessControlPolicy access$100(software.amazon.awssdk.services.s3.model.PutObjectAclRequest$BuilderImpl);
    Code:
       0: aload_0
       1: getfield      #15                 // Field accessControlPolicy:Lsoftware/amazon/awssdk/services/s3/model/AccessControlPolicy;
       4: areturn

  static java.lang.String access$200(software.amazon.awssdk.services.s3.model.PutObjectAclRequest$BuilderImpl);
    Code:
       0: aload_0
       1: getfield      #14                 // Field bucket:Ljava/lang/String;
       4: areturn

  static java.lang.String access$300(software.amazon.awssdk.services.s3.model.PutObjectAclRequest$BuilderImpl);
    Code:
       0: aload_0
       1: getfield      #13                 // Field contentMD5:Ljava/lang/String;
       4: areturn

  static java.lang.String access$400(software.amazon.awssdk.services.s3.model.PutObjectAclRequest$BuilderImpl);
    Code:
       0: aload_0
       1: getfield      #12                 // Field checksumAlgorithm:Ljava/lang/String;
       4: areturn

  static java.lang.String access$500(software.amazon.awssdk.services.s3.model.PutObjectAclRequest$BuilderImpl);
    Code:
       0: aload_0
       1: getfield      #11                 // Field grantFullControl:Ljava/lang/String;
       4: areturn

  static java.lang.String access$600(software.amazon.awssdk.services.s3.model.PutObjectAclRequest$BuilderImpl);
    Code:
       0: aload_0
       1: getfield      #10                 // Field grantRead:Ljava/lang/String;
       4: areturn

  static java.lang.String access$700(software.amazon.awssdk.services.s3.model.PutObjectAclRequest$BuilderImpl);
    Code:
       0: aload_0
       1: getfield      #9                  // Field grantReadACP:Ljava/lang/String;
       4: areturn

  static java.lang.String access$800(software.amazon.awssdk.services.s3.model.PutObjectAclRequest$BuilderImpl);
    Code:
       0: aload_0
       1: getfield      #8                  // Field grantWrite:Ljava/lang/String;
       4: areturn

  static java.lang.String access$900(software.amazon.awssdk.services.s3.model.PutObjectAclRequest$BuilderImpl);
    Code:
       0: aload_0
       1: getfield      #7                  // Field grantWriteACP:Ljava/lang/String;
       4: areturn

  static java.lang.String access$1000(software.amazon.awssdk.services.s3.model.PutObjectAclRequest$BuilderImpl);
    Code:
       0: aload_0
       1: getfield      #6                  // Field key:Ljava/lang/String;
       4: areturn

  static java.lang.String access$1100(software.amazon.awssdk.services.s3.model.PutObjectAclRequest$BuilderImpl);
    Code:
       0: aload_0
       1: getfield      #5                  // Field requestPayer:Ljava/lang/String;
       4: areturn

  static java.lang.String access$1200(software.amazon.awssdk.services.s3.model.PutObjectAclRequest$BuilderImpl);
    Code:
       0: aload_0
       1: getfield      #4                  // Field versionId:Ljava/lang/String;
       4: areturn

  static java.lang.String access$1300(software.amazon.awssdk.services.s3.model.PutObjectAclRequest$BuilderImpl);
    Code:
       0: aload_0
       1: getfield      #3                  // Field expectedBucketOwner:Ljava/lang/String;
       4: areturn

  software.amazon.awssdk.services.s3.model.PutObjectAclRequest$BuilderImpl(software.amazon.awssdk.services.s3.model.PutObjectAclRequest, software.amazon.awssdk.services.s3.model.PutObjectAclRequest$1);
    Code:
       0: aload_0
       1: aload_1
       2: invokespecial #2                  // Method "<init>":(Lsoftware/amazon/awssdk/services/s3/model/PutObjectAclRequest;)V
       5: return

  software.amazon.awssdk.services.s3.model.PutObjectAclRequest$BuilderImpl(software.amazon.awssdk.services.s3.model.PutObjectAclRequest$1);
    Code:
       0: aload_0
       1: invokespecial #1                  // Method "<init>":()V
       4: return
}
