Compiled from "S3Location.java"
final class software.amazon.awssdk.services.s3.model.S3Location$BuilderImpl implements software.amazon.awssdk.services.s3.model.S3Location$Builder {
  private java.lang.String bucketName;

  private java.lang.String prefix;

  private software.amazon.awssdk.services.s3.model.Encryption encryption;

  private java.lang.String cannedACL;

  private java.util.List<software.amazon.awssdk.services.s3.model.Grant> accessControlList;

  private software.amazon.awssdk.services.s3.model.Tagging tagging;

  private java.util.List<software.amazon.awssdk.services.s3.model.MetadataEntry> userMetadata;

  private java.lang.String storageClass;

  private software.amazon.awssdk.services.s3.model.S3Location$BuilderImpl();
    Code:
       0: aload_0
       1: invokespecial #11                 // Method java/lang/Object."<init>":()V
       4: aload_0
       5: invokestatic  #12                 // Method software/amazon/awssdk/core/util/DefaultSdkAutoConstructList.getInstance:()Lsoftware/amazon/awssdk/core/util/DefaultSdkAutoConstructList;
       8: putfield      #6                  // Field accessControlList:Ljava/util/List;
      11: aload_0
      12: invokestatic  #12                 // Method software/amazon/awssdk/core/util/DefaultSdkAutoConstructList.getInstance:()Lsoftware/amazon/awssdk/core/util/DefaultSdkAutoConstructList;
      15: putfield      #4                  // Field userMetadata:Ljava/util/List;
      18: return

  private software.amazon.awssdk.services.s3.model.S3Location$BuilderImpl(software.amazon.awssdk.services.s3.model.S3Location);
    Code:
       0: aload_0
       1: invokespecial #11                 // Method java/lang/Object."<init>":()V
       4: aload_0
       5: invokestatic  #12                 // Method software/amazon/awssdk/core/util/DefaultSdkAutoConstructList.getInstance:()Lsoftware/amazon/awssdk/core/util/DefaultSdkAutoConstructList;
       8: putfield      #6                  // Field accessControlList:Ljava/util/List;
      11: aload_0
      12: invokestatic  #12                 // Method software/amazon/awssdk/core/util/DefaultSdkAutoConstructList.getInstance:()Lsoftware/amazon/awssdk/core/util/DefaultSdkAutoConstructList;
      15: putfield      #4                  // Field userMetadata:Ljava/util/List;
      18: aload_0
      19: aload_1
      20: invokestatic  #13                 // Method software/amazon/awssdk/services/s3/model/S3Location.access$1000:(Lsoftware/amazon/awssdk/services/s3/model/S3Location;)Ljava/lang/String;
      23: invokevirtual #14                 // Method bucketName:(Ljava/lang/String;)Lsoftware/amazon/awssdk/services/s3/model/S3Location$Builder;
      26: pop
      27: aload_0
      28: aload_1
      29: invokestatic  #15                 // Method software/amazon/awssdk/services/s3/model/S3Location.access$1100:(Lsoftware/amazon/awssdk/services/s3/model/S3Location;)Ljava/lang/String;
      32: invokevirtual #16                 // Method prefix:(Ljava/lang/String;)Lsoftware/amazon/awssdk/services/s3/model/S3Location$Builder;
      35: pop
      36: aload_0
      37: aload_1
      38: invokestatic  #17                 // Method software/amazon/awssdk/services/s3/model/S3Location.access$1200:(Lsoftware/amazon/awssdk/services/s3/model/S3Location;)Lsoftware/amazon/awssdk/services/s3/model/Encryption;
      41: invokevirtual #18                 // Method encryption:(Lsoftware/amazon/awssdk/services/s3/model/Encryption;)Lsoftware/amazon/awssdk/services/s3/model/S3Location$Builder;
      44: pop
      45: aload_0
      46: aload_1
      47: invokestatic  #19                 // Method software/amazon/awssdk/services/s3/model/S3Location.access$1300:(Lsoftware/amazon/awssdk/services/s3/model/S3Location;)Ljava/lang/String;
      50: invokevirtual #20                 // Method cannedACL:(Ljava/lang/String;)Lsoftware/amazon/awssdk/services/s3/model/S3Location$Builder;
      53: pop
      54: aload_0
      55: aload_1
      56: invokestatic  #21                 // Method software/amazon/awssdk/services/s3/model/S3Location.access$1400:(Lsoftware/amazon/awssdk/services/s3/model/S3Location;)Ljava/util/List;
      59: invokevirtual #22                 // Method accessControlList:(Ljava/util/Collection;)Lsoftware/amazon/awssdk/services/s3/model/S3Location$Builder;
      62: pop
      63: aload_0
      64: aload_1
      65: invokestatic  #23                 // Method software/amazon/awssdk/services/s3/model/S3Location.access$1500:(Lsoftware/amazon/awssdk/services/s3/model/S3Location;)Lsoftware/amazon/awssdk/services/s3/model/Tagging;
      68: invokevirtual #24                 // Method tagging:(Lsoftware/amazon/awssdk/services/s3/model/Tagging;)Lsoftware/amazon/awssdk/services/s3/model/S3Location$Builder;
      71: pop
      72: aload_0
      73: aload_1
      74: invokestatic  #25                 // Method software/amazon/awssdk/services/s3/model/S3Location.access$1600:(Lsoftware/amazon/awssdk/services/s3/model/S3Location;)Ljava/util/List;
      77: invokevirtual #26                 // Method userMetadata:(Ljava/util/Collection;)Lsoftware/amazon/awssdk/services/s3/model/S3Location$Builder;
      80: pop
      81: aload_0
      82: aload_1
      83: invokestatic  #27                 // Method software/amazon/awssdk/services/s3/model/S3Location.access$1700:(Lsoftware/amazon/awssdk/services/s3/model/S3Location;)Ljava/lang/String;
      86: invokevirtual #28                 // Method storageClass:(Ljava/lang/String;)Lsoftware/amazon/awssdk/services/s3/model/S3Location$Builder;
      89: pop
      90: return

  public final java.lang.String getBucketName();
    Code:
       0: aload_0
       1: getfield      #10                 // Field bucketName:Ljava/lang/String;
       4: areturn

  public final void setBucketName(java.lang.String);
    Code:
       0: aload_0
       1: aload_1
       2: putfield      #10                 // Field bucketName:Ljava/lang/String;
       5: return

  public final software.amazon.awssdk.services.s3.model.S3Location$Builder bucketName(java.lang.String);
    Code:
       0: aload_0
       1: aload_1
       2: putfield      #10                 // Field bucketName:Ljava/lang/String;
       5: aload_0
       6: areturn

  public final java.lang.String getPrefix();
    Code:
       0: aload_0
       1: getfield      #9                  // Field prefix:Ljava/lang/String;
       4: areturn

  public final void setPrefix(java.lang.String);
    Code:
       0: aload_0
       1: aload_1
       2: putfield      #9                  // Field prefix:Ljava/lang/String;
       5: return

  public final software.amazon.awssdk.services.s3.model.S3Location$Builder prefix(java.lang.String);
    Code:
       0: aload_0
       1: aload_1
       2: putfield      #9                  // Field prefix:Ljava/lang/String;
       5: aload_0
       6: areturn

  public final software.amazon.awssdk.services.s3.model.Encryption$Builder getEncryption();
    Code:
       0: aload_0
       1: getfield      #8                  // Field encryption:Lsoftware/amazon/awssdk/services/s3/model/Encryption;
       4: ifnull        17
       7: aload_0
       8: getfield      #8                  // Field encryption:Lsoftware/amazon/awssdk/services/s3/model/Encryption;
      11: invokevirtual #29                 // Method software/amazon/awssdk/services/s3/model/Encryption.toBuilder:()Lsoftware/amazon/awssdk/services/s3/model/Encryption$Builder;
      14: goto          18
      17: aconst_null
      18: areturn

  public final void setEncryption(software.amazon.awssdk.services.s3.model.Encryption$BuilderImpl);
    Code:
       0: aload_0
       1: aload_1
       2: ifnull        12
       5: aload_1
       6: invokevirtual #30                 // Method software/amazon/awssdk/services/s3/model/Encryption$BuilderImpl.build:()Lsoftware/amazon/awssdk/services/s3/model/Encryption;
       9: goto          13
      12: aconst_null
      13: putfield      #8                  // Field encryption:Lsoftware/amazon/awssdk/services/s3/model/Encryption;
      16: return

  public final software.amazon.awssdk.services.s3.model.S3Location$Builder encryption(software.amazon.awssdk.services.s3.model.Encryption);
    Code:
       0: aload_0
       1: aload_1
       2: putfield      #8                  // Field encryption:Lsoftware/amazon/awssdk/services/s3/model/Encryption;
       5: aload_0
       6: areturn

  public final java.lang.String getCannedACL();
    Code:
       0: aload_0
       1: getfield      #7                  // Field cannedACL:Ljava/lang/String;
       4: areturn

  public final void setCannedACL(java.lang.String);
    Code:
       0: aload_0
       1: aload_1
       2: putfield      #7                  // Field cannedACL:Ljava/lang/String;
       5: return

  public final software.amazon.awssdk.services.s3.model.S3Location$Builder cannedACL(java.lang.String);
    Code:
       0: aload_0
       1: aload_1
       2: putfield      #7                  // Field cannedACL:Ljava/lang/String;
       5: aload_0
       6: areturn

  public final software.amazon.awssdk.services.s3.model.S3Location$Builder cannedACL(software.amazon.awssdk.services.s3.model.ObjectCannedACL);
    Code:
       0: aload_0
       1: aload_1
       2: ifnonnull     9
       5: aconst_null
       6: goto          13
       9: aload_1
      10: invokevirtual #31                 // Method software/amazon/awssdk/services/s3/model/ObjectCannedACL.toString:()Ljava/lang/String;
      13: invokevirtual #20                 // Method cannedACL:(Ljava/lang/String;)Lsoftware/amazon/awssdk/services/s3/model/S3Location$Builder;
      16: pop
      17: aload_0
      18: areturn

  public final java.util.List<software.amazon.awssdk.services.s3.model.Grant$Builder> getAccessControlList();
    Code:
       0: aload_0
       1: getfield      #6                  // Field accessControlList:Ljava/util/List;
       4: invokestatic  #32                 // Method software/amazon/awssdk/services/s3/model/GrantsCopier.copyToBuilder:(Ljava/util/Collection;)Ljava/util/List;
       7: astore_1
       8: aload_1
       9: instanceof    #33                 // class software/amazon/awssdk/core/util/SdkAutoConstructList
      12: ifeq          17
      15: aconst_null
      16: areturn
      17: aload_1
      18: areturn

  public final void setAccessControlList(java.util.Collection<software.amazon.awssdk.services.s3.model.Grant$BuilderImpl>);
    Code:
       0: aload_0
       1: aload_1
       2: invokestatic  #34                 // Method software/amazon/awssdk/services/s3/model/GrantsCopier.copyFromBuilder:(Ljava/util/Collection;)Ljava/util/List;
       5: putfield      #6                  // Field accessControlList:Ljava/util/List;
       8: return

  public final software.amazon.awssdk.services.s3.model.S3Location$Builder accessControlList(java.util.Collection<software.amazon.awssdk.services.s3.model.Grant>);
    Code:
       0: aload_0
       1: aload_1
       2: invokestatic  #35                 // Method software/amazon/awssdk/services/s3/model/GrantsCopier.copy:(Ljava/util/Collection;)Ljava/util/List;
       5: putfield      #6                  // Field accessControlList:Ljava/util/List;
       8: aload_0
       9: areturn

  public final software.amazon.awssdk.services.s3.model.S3Location$Builder accessControlList(software.amazon.awssdk.services.s3.model.Grant...);
    Code:
       0: aload_0
       1: aload_1
       2: invokestatic  #36                 // Method java/util/Arrays.asList:([Ljava/lang/Object;)Ljava/util/List;
       5: invokevirtual #22                 // Method accessControlList:(Ljava/util/Collection;)Lsoftware/amazon/awssdk/services/s3/model/S3Location$Builder;
       8: pop
       9: aload_0
      10: areturn

  public final software.amazon.awssdk.services.s3.model.S3Location$Builder accessControlList(java.util.function.Consumer<software.amazon.awssdk.services.s3.model.Grant$Builder>...);
    Code:
       0: aload_0
       1: aload_1
       2: invokestatic  #37                 // InterfaceMethod java/util/stream/Stream.of:([Ljava/lang/Object;)Ljava/util/stream/Stream;
       5: invokedynamic #38,  0             // InvokeDynamic #0:apply:()Ljava/util/function/Function;
      10: invokeinterface #39,  2           // InterfaceMethod java/util/stream/Stream.map:(Ljava/util/function/Function;)Ljava/util/stream/Stream;
      15: invokestatic  #40                 // Method java/util/stream/Collectors.toList:()Ljava/util/stream/Collector;
      18: invokeinterface #41,  2           // InterfaceMethod java/util/stream/Stream.collect:(Ljava/util/stream/Collector;)Ljava/lang/Object;
      23: checkcast     #42                 // class java/util/Collection
      26: invokevirtual #22                 // Method accessControlList:(Ljava/util/Collection;)Lsoftware/amazon/awssdk/services/s3/model/S3Location$Builder;
      29: pop
      30: aload_0
      31: areturn

  public final software.amazon.awssdk.services.s3.model.Tagging$Builder getTagging();
    Code:
       0: aload_0
       1: getfield      #5                  // Field tagging:Lsoftware/amazon/awssdk/services/s3/model/Tagging;
       4: ifnull        17
       7: aload_0
       8: getfield      #5                  // Field tagging:Lsoftware/amazon/awssdk/services/s3/model/Tagging;
      11: invokevirtual #43                 // Method software/amazon/awssdk/services/s3/model/Tagging.toBuilder:()Lsoftware/amazon/awssdk/services/s3/model/Tagging$Builder;
      14: goto          18
      17: aconst_null
      18: areturn

  public final void setTagging(software.amazon.awssdk.services.s3.model.Tagging$BuilderImpl);
    Code:
       0: aload_0
       1: aload_1
       2: ifnull        12
       5: aload_1
       6: invokevirtual #44                 // Method software/amazon/awssdk/services/s3/model/Tagging$BuilderImpl.build:()Lsoftware/amazon/awssdk/services/s3/model/Tagging;
       9: goto          13
      12: aconst_null
      13: putfield      #5                  // Field tagging:Lsoftware/amazon/awssdk/services/s3/model/Tagging;
      16: return

  public final software.amazon.awssdk.services.s3.model.S3Location$Builder tagging(software.amazon.awssdk.services.s3.model.Tagging);
    Code:
       0: aload_0
       1: aload_1
       2: putfield      #5                  // Field tagging:Lsoftware/amazon/awssdk/services/s3/model/Tagging;
       5: aload_0
       6: areturn

  public final java.util.List<software.amazon.awssdk.services.s3.model.MetadataEntry$Builder> getUserMetadata();
    Code:
       0: aload_0
       1: getfield      #4                  // Field userMetadata:Ljava/util/List;
       4: invokestatic  #45                 // Method software/amazon/awssdk/services/s3/model/UserMetadataCopier.copyToBuilder:(Ljava/util/Collection;)Ljava/util/List;
       7: astore_1
       8: aload_1
       9: instanceof    #33                 // class software/amazon/awssdk/core/util/SdkAutoConstructList
      12: ifeq          17
      15: aconst_null
      16: areturn
      17: aload_1
      18: areturn

  public final void setUserMetadata(java.util.Collection<software.amazon.awssdk.services.s3.model.MetadataEntry$BuilderImpl>);
    Code:
       0: aload_0
       1: aload_1
       2: invokestatic  #46                 // Method software/amazon/awssdk/services/s3/model/UserMetadataCopier.copyFromBuilder:(Ljava/util/Collection;)Ljava/util/List;
       5: putfield      #4                  // Field userMetadata:Ljava/util/List;
       8: return

  public final software.amazon.awssdk.services.s3.model.S3Location$Builder userMetadata(java.util.Collection<software.amazon.awssdk.services.s3.model.MetadataEntry>);
    Code:
       0: aload_0
       1: aload_1
       2: invokestatic  #47                 // Method software/amazon/awssdk/services/s3/model/UserMetadataCopier.copy:(Ljava/util/Collection;)Ljava/util/List;
       5: putfield      #4                  // Field userMetadata:Ljava/util/List;
       8: aload_0
       9: areturn

  public final software.amazon.awssdk.services.s3.model.S3Location$Builder userMetadata(software.amazon.awssdk.services.s3.model.MetadataEntry...);
    Code:
       0: aload_0
       1: aload_1
       2: invokestatic  #36                 // Method java/util/Arrays.asList:([Ljava/lang/Object;)Ljava/util/List;
       5: invokevirtual #26                 // Method userMetadata:(Ljava/util/Collection;)Lsoftware/amazon/awssdk/services/s3/model/S3Location$Builder;
       8: pop
       9: aload_0
      10: areturn

  public final software.amazon.awssdk.services.s3.model.S3Location$Builder userMetadata(java.util.function.Consumer<software.amazon.awssdk.services.s3.model.MetadataEntry$Builder>...);
    Code:
       0: aload_0
       1: aload_1
       2: invokestatic  #37                 // InterfaceMethod java/util/stream/Stream.of:([Ljava/lang/Object;)Ljava/util/stream/Stream;
       5: invokedynamic #48,  0             // InvokeDynamic #1:apply:()Ljava/util/function/Function;
      10: invokeinterface #39,  2           // InterfaceMethod java/util/stream/Stream.map:(Ljava/util/function/Function;)Ljava/util/stream/Stream;
      15: invokestatic  #40                 // Method java/util/stream/Collectors.toList:()Ljava/util/stream/Collector;
      18: invokeinterface #41,  2           // InterfaceMethod java/util/stream/Stream.collect:(Ljava/util/stream/Collector;)Ljava/lang/Object;
      23: checkcast     #42                 // class java/util/Collection
      26: invokevirtual #26                 // Method userMetadata:(Ljava/util/Collection;)Lsoftware/amazon/awssdk/services/s3/model/S3Location$Builder;
      29: pop
      30: aload_0
      31: areturn

  public final java.lang.String getStorageClass();
    Code:
       0: aload_0
       1: getfield      #3                  // Field storageClass:Ljava/lang/String;
       4: areturn

  public final void setStorageClass(java.lang.String);
    Code:
       0: aload_0
       1: aload_1
       2: putfield      #3                  // Field storageClass:Ljava/lang/String;
       5: return

  public final software.amazon.awssdk.services.s3.model.S3Location$Builder storageClass(java.lang.String);
    Code:
       0: aload_0
       1: aload_1
       2: putfield      #3                  // Field storageClass:Ljava/lang/String;
       5: aload_0
       6: areturn

  public final software.amazon.awssdk.services.s3.model.S3Location$Builder storageClass(software.amazon.awssdk.services.s3.model.StorageClass);
    Code:
       0: aload_0
       1: aload_1
       2: ifnonnull     9
       5: aconst_null
       6: goto          13
       9: aload_1
      10: invokevirtual #49                 // Method software/amazon/awssdk/services/s3/model/StorageClass.toString:()Ljava/lang/String;
      13: invokevirtual #28                 // Method storageClass:(Ljava/lang/String;)Lsoftware/amazon/awssdk/services/s3/model/S3Location$Builder;
      16: pop
      17: aload_0
      18: areturn

  public software.amazon.awssdk.services.s3.model.S3Location build();
    Code:
       0: new           #50                 // class software/amazon/awssdk/services/s3/model/S3Location
       3: dup
       4: aload_0
       5: aconst_null
       6: invokespecial #51                 // Method software/amazon/awssdk/services/s3/model/S3Location."<init>":(Lsoftware/amazon/awssdk/services/s3/model/S3Location$BuilderImpl;Lsoftware/amazon/awssdk/services/s3/model/S3Location$1;)V
       9: areturn

  public java.util.List<software.amazon.awssdk.core.SdkField<?>> sdkFields();
    Code:
       0: invokestatic  #52                 // Method software/amazon/awssdk/services/s3/model/S3Location.access$1900:()Ljava/util/List;
       3: areturn

  public java.lang.Object build();
    Code:
       0: aload_0
       1: invokevirtual #53                 // Method build:()Lsoftware/amazon/awssdk/services/s3/model/S3Location;
       4: areturn

  private static software.amazon.awssdk.services.s3.model.MetadataEntry lambda$userMetadata$1(java.util.function.Consumer);
    Code:
       0: invokestatic  #54                 // Method software/amazon/awssdk/services/s3/model/MetadataEntry.builder:()Lsoftware/amazon/awssdk/services/s3/model/MetadataEntry$Builder;
       3: aload_0
       4: invokeinterface #55,  2           // InterfaceMethod software/amazon/awssdk/services/s3/model/MetadataEntry$Builder.applyMutation:(Ljava/util/function/Consumer;)Lsoftware/amazon/awssdk/utils/builder/SdkBuilder;
       9: checkcast     #56                 // class software/amazon/awssdk/services/s3/model/MetadataEntry$Builder
      12: invokeinterface #57,  1           // InterfaceMethod software/amazon/awssdk/services/s3/model/MetadataEntry$Builder.build:()Ljava/lang/Object;
      17: checkcast     #58                 // class software/amazon/awssdk/services/s3/model/MetadataEntry
      20: areturn

  private static software.amazon.awssdk.services.s3.model.Grant lambda$accessControlList$0(java.util.function.Consumer);
    Code:
       0: invokestatic  #59                 // Method software/amazon/awssdk/services/s3/model/Grant.builder:()Lsoftware/amazon/awssdk/services/s3/model/Grant$Builder;
       3: aload_0
       4: invokeinterface #60,  2           // InterfaceMethod software/amazon/awssdk/services/s3/model/Grant$Builder.applyMutation:(Ljava/util/function/Consumer;)Lsoftware/amazon/awssdk/utils/builder/SdkBuilder;
       9: checkcast     #61                 // class software/amazon/awssdk/services/s3/model/Grant$Builder
      12: invokeinterface #62,  1           // InterfaceMethod software/amazon/awssdk/services/s3/model/Grant$Builder.build:()Ljava/lang/Object;
      17: checkcast     #63                 // class software/amazon/awssdk/services/s3/model/Grant
      20: areturn

  static java.lang.String access$000(software.amazon.awssdk.services.s3.model.S3Location$BuilderImpl);
    Code:
       0: aload_0
       1: getfield      #10                 // Field bucketName:Ljava/lang/String;
       4: areturn

  static java.lang.String access$100(software.amazon.awssdk.services.s3.model.S3Location$BuilderImpl);
    Code:
       0: aload_0
       1: getfield      #9                  // Field prefix:Ljava/lang/String;
       4: areturn

  static software.amazon.awssdk.services.s3.model.Encryption access$200(software.amazon.awssdk.services.s3.model.S3Location$BuilderImpl);
    Code:
       0: aload_0
       1: getfield      #8                  // Field encryption:Lsoftware/amazon/awssdk/services/s3/model/Encryption;
       4: areturn

  static java.lang.String access$300(software.amazon.awssdk.services.s3.model.S3Location$BuilderImpl);
    Code:
       0: aload_0
       1: getfield      #7                  // Field cannedACL:Ljava/lang/String;
       4: areturn

  static java.util.List access$400(software.amazon.awssdk.services.s3.model.S3Location$BuilderImpl);
    Code:
       0: aload_0
       1: getfield      #6                  // Field accessControlList:Ljava/util/List;
       4: areturn

  static software.amazon.awssdk.services.s3.model.Tagging access$500(software.amazon.awssdk.services.s3.model.S3Location$BuilderImpl);
    Code:
       0: aload_0
       1: getfield      #5                  // Field tagging:Lsoftware/amazon/awssdk/services/s3/model/Tagging;
       4: areturn

  static java.util.List access$600(software.amazon.awssdk.services.s3.model.S3Location$BuilderImpl);
    Code:
       0: aload_0
       1: getfield      #4                  // Field userMetadata:Ljava/util/List;
       4: areturn

  static java.lang.String access$700(software.amazon.awssdk.services.s3.model.S3Location$BuilderImpl);
    Code:
       0: aload_0
       1: getfield      #3                  // Field storageClass:Ljava/lang/String;
       4: areturn

  software.amazon.awssdk.services.s3.model.S3Location$BuilderImpl(software.amazon.awssdk.services.s3.model.S3Location, software.amazon.awssdk.services.s3.model.S3Location$1);
    Code:
       0: aload_0
       1: aload_1
       2: invokespecial #2                  // Method "<init>":(Lsoftware/amazon/awssdk/services/s3/model/S3Location;)V
       5: return

  software.amazon.awssdk.services.s3.model.S3Location$BuilderImpl(software.amazon.awssdk.services.s3.model.S3Location$1);
    Code:
       0: aload_0
       1: invokespecial #1                  // Method "<init>":()V
       4: return
}
