Compiled from "StatsEvent.java"
public class software.amazon.awssdk.services.s3.model.StatsEvent$BuilderImpl implements software.amazon.awssdk.services.s3.model.StatsEvent$Builder {
  private software.amazon.awssdk.services.s3.model.Stats details;

  protected software.amazon.awssdk.services.s3.model.StatsEvent$BuilderImpl();
    Code:
       0: aload_0
       1: invokespecial #2                  // Method java/lang/Object."<init>":()V
       4: return

  protected software.amazon.awssdk.services.s3.model.StatsEvent$BuilderImpl(software.amazon.awssdk.services.s3.model.StatsEvent);
    Code:
       0: aload_0
       1: invokespecial #2                  // Method java/lang/Object."<init>":()V
       4: aload_0
       5: aload_1
       6: invokestatic  #3                  // Method software/amazon/awssdk/services/s3/model/StatsEvent.access$100:(Lsoftware/amazon/awssdk/services/s3/model/StatsEvent;)Lsoftware/amazon/awssdk/services/s3/model/Stats;
       9: invokevirtual #4                  // Method details:(Lsoftware/amazon/awssdk/services/s3/model/Stats;)Lsoftware/amazon/awssdk/services/s3/model/StatsEvent$Builder;
      12: pop
      13: return

  public final software.amazon.awssdk.services.s3.model.Stats$Builder getDetails();
    Code:
       0: aload_0
       1: getfield      #1                  // Field details:Lsoftware/amazon/awssdk/services/s3/model/Stats;
       4: ifnull        17
       7: aload_0
       8: getfield      #1                  // Field details:Lsoftware/amazon/awssdk/services/s3/model/Stats;
      11: invokevirtual #5                  // Method software/amazon/awssdk/services/s3/model/Stats.toBuilder:()Lsoftware/amazon/awssdk/services/s3/model/Stats$Builder;
      14: goto          18
      17: aconst_null
      18: areturn

  public final void setDetails(software.amazon.awssdk.services.s3.model.Stats$BuilderImpl);
    Code:
       0: aload_0
       1: aload_1
       2: ifnull        12
       5: aload_1
       6: invokevirtual #6                  // Method software/amazon/awssdk/services/s3/model/Stats$BuilderImpl.build:()Lsoftware/amazon/awssdk/services/s3/model/Stats;
       9: goto          13
      12: aconst_null
      13: putfield      #1                  // Field details:Lsoftware/amazon/awssdk/services/s3/model/Stats;
      16: return

  public final software.amazon.awssdk.services.s3.model.StatsEvent$Builder details(software.amazon.awssdk.services.s3.model.Stats);
    Code:
       0: aload_0
       1: aload_1
       2: putfield      #1                  // Field details:Lsoftware/amazon/awssdk/services/s3/model/Stats;
       5: aload_0
       6: areturn

  public software.amazon.awssdk.services.s3.model.StatsEvent build();
    Code:
       0: new           #7                  // class software/amazon/awssdk/services/s3/model/StatsEvent
       3: dup
       4: aload_0
       5: invokespecial #8                  // Method software/amazon/awssdk/services/s3/model/StatsEvent."<init>":(Lsoftware/amazon/awssdk/services/s3/model/StatsEvent$BuilderImpl;)V
       8: areturn

  public java.util.List<software.amazon.awssdk.core.SdkField<?>> sdkFields();
    Code:
       0: invokestatic  #9                  // Method software/amazon/awssdk/services/s3/model/StatsEvent.access$200:()Ljava/util/List;
       3: areturn

  public java.lang.Object build();
    Code:
       0: aload_0
       1: invokevirtual #10                 // Method build:()Lsoftware/amazon/awssdk/services/s3/model/StatsEvent;
       4: areturn

  static software.amazon.awssdk.services.s3.model.Stats access$000(software.amazon.awssdk.services.s3.model.StatsEvent$BuilderImpl);
    Code:
       0: aload_0
       1: getfield      #1                  // Field details:Lsoftware/amazon/awssdk/services/s3/model/Stats;
       4: areturn
}
