Compiled from "StorageClassAnalysis.java"
public interface software.amazon.awssdk.services.s3.model.StorageClassAnalysis$Builder extends software.amazon.awssdk.core.SdkPojo, software.amazon.awssdk.utils.builder.CopyableBuilder<software.amazon.awssdk.services.s3.model.StorageClassAnalysis$Builder, software.amazon.awssdk.services.s3.model.StorageClassAnalysis> {
  public abstract software.amazon.awssdk.services.s3.model.StorageClassAnalysis$Builder dataExport(software.amazon.awssdk.services.s3.model.StorageClassAnalysisDataExport);

  public default software.amazon.awssdk.services.s3.model.StorageClassAnalysis$Builder dataExport(java.util.function.Consumer<software.amazon.awssdk.services.s3.model.StorageClassAnalysisDataExport$Builder>);
    Code:
       0: aload_0
       1: invokestatic  #1                  // Method software/amazon/awssdk/services/s3/model/StorageClassAnalysisDataExport.builder:()Lsoftware/amazon/awssdk/services/s3/model/StorageClassAnalysisDataExport$Builder;
       4: aload_1
       5: invokeinterface #2,  2            // InterfaceMethod software/amazon/awssdk/services/s3/model/StorageClassAnalysisDataExport$Builder.applyMutation:(Ljava/util/function/Consumer;)Lsoftware/amazon/awssdk/utils/builder/SdkBuilder;
      10: checkcast     #3                  // class software/amazon/awssdk/services/s3/model/StorageClassAnalysisDataExport$Builder
      13: invokeinterface #4,  1            // InterfaceMethod software/amazon/awssdk/services/s3/model/StorageClassAnalysisDataExport$Builder.build:()Ljava/lang/Object;
      18: checkcast     #5                  // class software/amazon/awssdk/services/s3/model/StorageClassAnalysisDataExport
      21: invokeinterface #6,  2            // InterfaceMethod dataExport:(Lsoftware/amazon/awssdk/services/s3/model/StorageClassAnalysisDataExport;)Lsoftware/amazon/awssdk/services/s3/model/StorageClassAnalysis$Builder;
      26: areturn
}
