Compiled from "LayerJsonMarshaller.java"
public class com.amazonaws.services.opsworks.model.transform.LayerJsonMarshaller {
  private static com.amazonaws.services.opsworks.model.transform.LayerJsonMarshaller instance;

  public com.amazonaws.services.opsworks.model.transform.LayerJsonMarshaller();
    Code:
       0: aload_0
       1: invokespecial #1                  // Method java/lang/Object."<init>":()V
       4: return

  public void marshall(com.amazonaws.services.opsworks.model.Layer, com.amazonaws.protocol.json.StructuredJsonGenerator);
    Code:
       0: aload_1
       1: ifnonnull     14
       4: new           #2                  // class com/amazonaws/AmazonClientException
       7: dup
       8: ldc           #3                  // String Invalid argument passed to marshall(...)
      10: invokespecial #4                  // Method com/amazonaws/AmazonClientException."<init>":(Ljava/lang/String;)V
      13: athrow
      14: aload_2
      15: invokeinterface #5,  1            // InterfaceMethod com/amazonaws/protocol/json/StructuredJsonGenerator.writeStartObject:()Lcom/amazonaws/protocol/json/StructuredJsonGenerator;
      20: pop
      21: aload_1
      22: invokevirtual #6                  // Method com/amazonaws/services/opsworks/model/Layer.getStackId:()Ljava/lang/String;
      25: ifnull        46
      28: aload_2
      29: ldc           #7                  // String StackId
      31: invokeinterface #8,  2            // InterfaceMethod com/amazonaws/protocol/json/StructuredJsonGenerator.writeFieldName:(Ljava/lang/String;)Lcom/amazonaws/protocol/json/StructuredJsonGenerator;
      36: aload_1
      37: invokevirtual #6                  // Method com/amazonaws/services/opsworks/model/Layer.getStackId:()Ljava/lang/String;
      40: invokeinterface #9,  2            // InterfaceMethod com/amazonaws/protocol/json/StructuredJsonGenerator.writeValue:(Ljava/lang/String;)Lcom/amazonaws/protocol/json/StructuredJsonGenerator;
      45: pop
      46: aload_1
      47: invokevirtual #10                 // Method com/amazonaws/services/opsworks/model/Layer.getLayerId:()Ljava/lang/String;
      50: ifnull        71
      53: aload_2
      54: ldc           #11                 // String LayerId
      56: invokeinterface #8,  2            // InterfaceMethod com/amazonaws/protocol/json/StructuredJsonGenerator.writeFieldName:(Ljava/lang/String;)Lcom/amazonaws/protocol/json/StructuredJsonGenerator;
      61: aload_1
      62: invokevirtual #10                 // Method com/amazonaws/services/opsworks/model/Layer.getLayerId:()Ljava/lang/String;
      65: invokeinterface #9,  2            // InterfaceMethod com/amazonaws/protocol/json/StructuredJsonGenerator.writeValue:(Ljava/lang/String;)Lcom/amazonaws/protocol/json/StructuredJsonGenerator;
      70: pop
      71: aload_1
      72: invokevirtual #12                 // Method com/amazonaws/services/opsworks/model/Layer.getType:()Ljava/lang/String;
      75: ifnull        96
      78: aload_2
      79: ldc           #13                 // String Type
      81: invokeinterface #8,  2            // InterfaceMethod com/amazonaws/protocol/json/StructuredJsonGenerator.writeFieldName:(Ljava/lang/String;)Lcom/amazonaws/protocol/json/StructuredJsonGenerator;
      86: aload_1
      87: invokevirtual #12                 // Method com/amazonaws/services/opsworks/model/Layer.getType:()Ljava/lang/String;
      90: invokeinterface #9,  2            // InterfaceMethod com/amazonaws/protocol/json/StructuredJsonGenerator.writeValue:(Ljava/lang/String;)Lcom/amazonaws/protocol/json/StructuredJsonGenerator;
      95: pop
      96: aload_1
      97: invokevirtual #14                 // Method com/amazonaws/services/opsworks/model/Layer.getName:()Ljava/lang/String;
     100: ifnull        121
     103: aload_2
     104: ldc           #15                 // String Name
     106: invokeinterface #8,  2            // InterfaceMethod com/amazonaws/protocol/json/StructuredJsonGenerator.writeFieldName:(Ljava/lang/String;)Lcom/amazonaws/protocol/json/StructuredJsonGenerator;
     111: aload_1
     112: invokevirtual #14                 // Method com/amazonaws/services/opsworks/model/Layer.getName:()Ljava/lang/String;
     115: invokeinterface #9,  2            // InterfaceMethod com/amazonaws/protocol/json/StructuredJsonGenerator.writeValue:(Ljava/lang/String;)Lcom/amazonaws/protocol/json/StructuredJsonGenerator;
     120: pop
     121: aload_1
     122: invokevirtual #16                 // Method com/amazonaws/services/opsworks/model/Layer.getShortname:()Ljava/lang/String;
     125: ifnull        146
     128: aload_2
     129: ldc           #17                 // String Shortname
     131: invokeinterface #8,  2            // InterfaceMethod com/amazonaws/protocol/json/StructuredJsonGenerator.writeFieldName:(Ljava/lang/String;)Lcom/amazonaws/protocol/json/StructuredJsonGenerator;
     136: aload_1
     137: invokevirtual #16                 // Method com/amazonaws/services/opsworks/model/Layer.getShortname:()Ljava/lang/String;
     140: invokeinterface #9,  2            // InterfaceMethod com/amazonaws/protocol/json/StructuredJsonGenerator.writeValue:(Ljava/lang/String;)Lcom/amazonaws/protocol/json/StructuredJsonGenerator;
     145: pop
     146: aload_1
     147: invokevirtual #18                 // Method com/amazonaws/services/opsworks/model/Layer.getAttributes:()Ljava/util/Map;
     150: checkcast     #19                 // class com/amazonaws/internal/SdkInternalMap
     153: astore_3
     154: aload_3
     155: invokevirtual #20                 // Method com/amazonaws/internal/SdkInternalMap.isEmpty:()Z
     158: ifeq          168
     161: aload_3
     162: invokevirtual #21                 // Method com/amazonaws/internal/SdkInternalMap.isAutoConstruct:()Z
     165: ifne          271
     168: aload_2
     169: ldc           #22                 // String Attributes
     171: invokeinterface #8,  2            // InterfaceMethod com/amazonaws/protocol/json/StructuredJsonGenerator.writeFieldName:(Ljava/lang/String;)Lcom/amazonaws/protocol/json/StructuredJsonGenerator;
     176: pop
     177: aload_2
     178: invokeinterface #5,  1            // InterfaceMethod com/amazonaws/protocol/json/StructuredJsonGenerator.writeStartObject:()Lcom/amazonaws/protocol/json/StructuredJsonGenerator;
     183: pop
     184: aload_3
     185: invokevirtual #23                 // Method com/amazonaws/internal/SdkInternalMap.entrySet:()Ljava/util/Set;
     188: invokeinterface #24,  1           // InterfaceMethod java/util/Set.iterator:()Ljava/util/Iterator;
     193: astore        4
     195: aload         4
     197: invokeinterface #25,  1           // InterfaceMethod java/util/Iterator.hasNext:()Z
     202: ifeq          264
     205: aload         4
     207: invokeinterface #26,  1           // InterfaceMethod java/util/Iterator.next:()Ljava/lang/Object;
     212: checkcast     #27                 // class java/util/Map$Entry
     215: astore        5
     217: aload         5
     219: invokeinterface #28,  1           // InterfaceMethod java/util/Map$Entry.getValue:()Ljava/lang/Object;
     224: ifnull        261
     227: aload_2
     228: aload         5
     230: invokeinterface #29,  1           // InterfaceMethod java/util/Map$Entry.getKey:()Ljava/lang/Object;
     235: checkcast     #30                 // class java/lang/String
     238: invokeinterface #8,  2            // InterfaceMethod com/amazonaws/protocol/json/StructuredJsonGenerator.writeFieldName:(Ljava/lang/String;)Lcom/amazonaws/protocol/json/StructuredJsonGenerator;
     243: pop
     244: aload_2
     245: aload         5
     247: invokeinterface #28,  1           // InterfaceMethod java/util/Map$Entry.getValue:()Ljava/lang/Object;
     252: checkcast     #30                 // class java/lang/String
     255: invokeinterface #9,  2            // InterfaceMethod com/amazonaws/protocol/json/StructuredJsonGenerator.writeValue:(Ljava/lang/String;)Lcom/amazonaws/protocol/json/StructuredJsonGenerator;
     260: pop
     261: goto          195
     264: aload_2
     265: invokeinterface #31,  1           // InterfaceMethod com/amazonaws/protocol/json/StructuredJsonGenerator.writeEndObject:()Lcom/amazonaws/protocol/json/StructuredJsonGenerator;
     270: pop
     271: aload_1
     272: invokevirtual #32                 // Method com/amazonaws/services/opsworks/model/Layer.getCustomInstanceProfileArn:()Ljava/lang/String;
     275: ifnull        296
     278: aload_2
     279: ldc           #33                 // String CustomInstanceProfileArn
     281: invokeinterface #8,  2            // InterfaceMethod com/amazonaws/protocol/json/StructuredJsonGenerator.writeFieldName:(Ljava/lang/String;)Lcom/amazonaws/protocol/json/StructuredJsonGenerator;
     286: aload_1
     287: invokevirtual #32                 // Method com/amazonaws/services/opsworks/model/Layer.getCustomInstanceProfileArn:()Ljava/lang/String;
     290: invokeinterface #9,  2            // InterfaceMethod com/amazonaws/protocol/json/StructuredJsonGenerator.writeValue:(Ljava/lang/String;)Lcom/amazonaws/protocol/json/StructuredJsonGenerator;
     295: pop
     296: aload_1
     297: invokevirtual #34                 // Method com/amazonaws/services/opsworks/model/Layer.getCustomJson:()Ljava/lang/String;
     300: ifnull        321
     303: aload_2
     304: ldc           #35                 // String CustomJson
     306: invokeinterface #8,  2            // InterfaceMethod com/amazonaws/protocol/json/StructuredJsonGenerator.writeFieldName:(Ljava/lang/String;)Lcom/amazonaws/protocol/json/StructuredJsonGenerator;
     311: aload_1
     312: invokevirtual #34                 // Method com/amazonaws/services/opsworks/model/Layer.getCustomJson:()Ljava/lang/String;
     315: invokeinterface #9,  2            // InterfaceMethod com/amazonaws/protocol/json/StructuredJsonGenerator.writeValue:(Ljava/lang/String;)Lcom/amazonaws/protocol/json/StructuredJsonGenerator;
     320: pop
     321: aload_1
     322: invokevirtual #36                 // Method com/amazonaws/services/opsworks/model/Layer.getCustomSecurityGroupIds:()Ljava/util/List;
     325: checkcast     #37                 // class com/amazonaws/internal/SdkInternalList
     328: astore        4
     330: aload         4
     332: invokevirtual #38                 // Method com/amazonaws/internal/SdkInternalList.isEmpty:()Z
     335: ifeq          346
     338: aload         4
     340: invokevirtual #39                 // Method com/amazonaws/internal/SdkInternalList.isAutoConstruct:()Z
     343: ifne          415
     346: aload_2
     347: ldc           #40                 // String CustomSecurityGroupIds
     349: invokeinterface #8,  2            // InterfaceMethod com/amazonaws/protocol/json/StructuredJsonGenerator.writeFieldName:(Ljava/lang/String;)Lcom/amazonaws/protocol/json/StructuredJsonGenerator;
     354: pop
     355: aload_2
     356: invokeinterface #41,  1           // InterfaceMethod com/amazonaws/protocol/json/StructuredJsonGenerator.writeStartArray:()Lcom/amazonaws/protocol/json/StructuredJsonGenerator;
     361: pop
     362: aload         4
     364: invokevirtual #42                 // Method com/amazonaws/internal/SdkInternalList.iterator:()Ljava/util/Iterator;
     367: astore        5
     369: aload         5
     371: invokeinterface #25,  1           // InterfaceMethod java/util/Iterator.hasNext:()Z
     376: ifeq          408
     379: aload         5
     381: invokeinterface #26,  1           // InterfaceMethod java/util/Iterator.next:()Ljava/lang/Object;
     386: checkcast     #30                 // class java/lang/String
     389: astore        6
     391: aload         6
     393: ifnull        405
     396: aload_2
     397: aload         6
     399: invokeinterface #9,  2            // InterfaceMethod com/amazonaws/protocol/json/StructuredJsonGenerator.writeValue:(Ljava/lang/String;)Lcom/amazonaws/protocol/json/StructuredJsonGenerator;
     404: pop
     405: goto          369
     408: aload_2
     409: invokeinterface #43,  1           // InterfaceMethod com/amazonaws/protocol/json/StructuredJsonGenerator.writeEndArray:()Lcom/amazonaws/protocol/json/StructuredJsonGenerator;
     414: pop
     415: aload_1
     416: invokevirtual #44                 // Method com/amazonaws/services/opsworks/model/Layer.getDefaultSecurityGroupNames:()Ljava/util/List;
     419: checkcast     #37                 // class com/amazonaws/internal/SdkInternalList
     422: astore        5
     424: aload         5
     426: invokevirtual #38                 // Method com/amazonaws/internal/SdkInternalList.isEmpty:()Z
     429: ifeq          440
     432: aload         5
     434: invokevirtual #39                 // Method com/amazonaws/internal/SdkInternalList.isAutoConstruct:()Z
     437: ifne          509
     440: aload_2
     441: ldc           #45                 // String DefaultSecurityGroupNames
     443: invokeinterface #8,  2            // InterfaceMethod com/amazonaws/protocol/json/StructuredJsonGenerator.writeFieldName:(Ljava/lang/String;)Lcom/amazonaws/protocol/json/StructuredJsonGenerator;
     448: pop
     449: aload_2
     450: invokeinterface #41,  1           // InterfaceMethod com/amazonaws/protocol/json/StructuredJsonGenerator.writeStartArray:()Lcom/amazonaws/protocol/json/StructuredJsonGenerator;
     455: pop
     456: aload         5
     458: invokevirtual #42                 // Method com/amazonaws/internal/SdkInternalList.iterator:()Ljava/util/Iterator;
     461: astore        6
     463: aload         6
     465: invokeinterface #25,  1           // InterfaceMethod java/util/Iterator.hasNext:()Z
     470: ifeq          502
     473: aload         6
     475: invokeinterface #26,  1           // InterfaceMethod java/util/Iterator.next:()Ljava/lang/Object;
     480: checkcast     #30                 // class java/lang/String
     483: astore        7
     485: aload         7
     487: ifnull        499
     490: aload_2
     491: aload         7
     493: invokeinterface #9,  2            // InterfaceMethod com/amazonaws/protocol/json/StructuredJsonGenerator.writeValue:(Ljava/lang/String;)Lcom/amazonaws/protocol/json/StructuredJsonGenerator;
     498: pop
     499: goto          463
     502: aload_2
     503: invokeinterface #43,  1           // InterfaceMethod com/amazonaws/protocol/json/StructuredJsonGenerator.writeEndArray:()Lcom/amazonaws/protocol/json/StructuredJsonGenerator;
     508: pop
     509: aload_1
     510: invokevirtual #46                 // Method com/amazonaws/services/opsworks/model/Layer.getPackages:()Ljava/util/List;
     513: checkcast     #37                 // class com/amazonaws/internal/SdkInternalList
     516: astore        6
     518: aload         6
     520: invokevirtual #38                 // Method com/amazonaws/internal/SdkInternalList.isEmpty:()Z
     523: ifeq          534
     526: aload         6
     528: invokevirtual #39                 // Method com/amazonaws/internal/SdkInternalList.isAutoConstruct:()Z
     531: ifne          603
     534: aload_2
     535: ldc           #47                 // String Packages
     537: invokeinterface #8,  2            // InterfaceMethod com/amazonaws/protocol/json/StructuredJsonGenerator.writeFieldName:(Ljava/lang/String;)Lcom/amazonaws/protocol/json/StructuredJsonGenerator;
     542: pop
     543: aload_2
     544: invokeinterface #41,  1           // InterfaceMethod com/amazonaws/protocol/json/StructuredJsonGenerator.writeStartArray:()Lcom/amazonaws/protocol/json/StructuredJsonGenerator;
     549: pop
     550: aload         6
     552: invokevirtual #42                 // Method com/amazonaws/internal/SdkInternalList.iterator:()Ljava/util/Iterator;
     555: astore        7
     557: aload         7
     559: invokeinterface #25,  1           // InterfaceMethod java/util/Iterator.hasNext:()Z
     564: ifeq          596
     567: aload         7
     569: invokeinterface #26,  1           // InterfaceMethod java/util/Iterator.next:()Ljava/lang/Object;
     574: checkcast     #30                 // class java/lang/String
     577: astore        8
     579: aload         8
     581: ifnull        593
     584: aload_2
     585: aload         8
     587: invokeinterface #9,  2            // InterfaceMethod com/amazonaws/protocol/json/StructuredJsonGenerator.writeValue:(Ljava/lang/String;)Lcom/amazonaws/protocol/json/StructuredJsonGenerator;
     592: pop
     593: goto          557
     596: aload_2
     597: invokeinterface #43,  1           // InterfaceMethod com/amazonaws/protocol/json/StructuredJsonGenerator.writeEndArray:()Lcom/amazonaws/protocol/json/StructuredJsonGenerator;
     602: pop
     603: aload_1
     604: invokevirtual #48                 // Method com/amazonaws/services/opsworks/model/Layer.getVolumeConfigurations:()Ljava/util/List;
     607: checkcast     #37                 // class com/amazonaws/internal/SdkInternalList
     610: astore        7
     612: aload         7
     614: invokevirtual #38                 // Method com/amazonaws/internal/SdkInternalList.isEmpty:()Z
     617: ifeq          628
     620: aload         7
     622: invokevirtual #39                 // Method com/amazonaws/internal/SdkInternalList.isAutoConstruct:()Z
     625: ifne          697
     628: aload_2
     629: ldc           #49                 // String VolumeConfigurations
     631: invokeinterface #8,  2            // InterfaceMethod com/amazonaws/protocol/json/StructuredJsonGenerator.writeFieldName:(Ljava/lang/String;)Lcom/amazonaws/protocol/json/StructuredJsonGenerator;
     636: pop
     637: aload_2
     638: invokeinterface #41,  1           // InterfaceMethod com/amazonaws/protocol/json/StructuredJsonGenerator.writeStartArray:()Lcom/amazonaws/protocol/json/StructuredJsonGenerator;
     643: pop
     644: aload         7
     646: invokevirtual #42                 // Method com/amazonaws/internal/SdkInternalList.iterator:()Ljava/util/Iterator;
     649: astore        8
     651: aload         8
     653: invokeinterface #25,  1           // InterfaceMethod java/util/Iterator.hasNext:()Z
     658: ifeq          690
     661: aload         8
     663: invokeinterface #26,  1           // InterfaceMethod java/util/Iterator.next:()Ljava/lang/Object;
     668: checkcast     #50                 // class com/amazonaws/services/opsworks/model/VolumeConfiguration
     671: astore        9
     673: aload         9
     675: ifnull        687
     678: invokestatic  #51                 // Method com/amazonaws/services/opsworks/model/transform/VolumeConfigurationJsonMarshaller.getInstance:()Lcom/amazonaws/services/opsworks/model/transform/VolumeConfigurationJsonMarshaller;
     681: aload         9
     683: aload_2
     684: invokevirtual #52                 // Method com/amazonaws/services/opsworks/model/transform/VolumeConfigurationJsonMarshaller.marshall:(Lcom/amazonaws/services/opsworks/model/VolumeConfiguration;Lcom/amazonaws/protocol/json/StructuredJsonGenerator;)V
     687: goto          651
     690: aload_2
     691: invokeinterface #43,  1           // InterfaceMethod com/amazonaws/protocol/json/StructuredJsonGenerator.writeEndArray:()Lcom/amazonaws/protocol/json/StructuredJsonGenerator;
     696: pop
     697: aload_1
     698: invokevirtual #53                 // Method com/amazonaws/services/opsworks/model/Layer.getEnableAutoHealing:()Ljava/lang/Boolean;
     701: ifnull        725
     704: aload_2
     705: ldc           #54                 // String EnableAutoHealing
     707: invokeinterface #8,  2            // InterfaceMethod com/amazonaws/protocol/json/StructuredJsonGenerator.writeFieldName:(Ljava/lang/String;)Lcom/amazonaws/protocol/json/StructuredJsonGenerator;
     712: aload_1
     713: invokevirtual #53                 // Method com/amazonaws/services/opsworks/model/Layer.getEnableAutoHealing:()Ljava/lang/Boolean;
     716: invokevirtual #55                 // Method java/lang/Boolean.booleanValue:()Z
     719: invokeinterface #56,  2           // InterfaceMethod com/amazonaws/protocol/json/StructuredJsonGenerator.writeValue:(Z)Lcom/amazonaws/protocol/json/StructuredJsonGenerator;
     724: pop
     725: aload_1
     726: invokevirtual #57                 // Method com/amazonaws/services/opsworks/model/Layer.getAutoAssignElasticIps:()Ljava/lang/Boolean;
     729: ifnull        753
     732: aload_2
     733: ldc           #58                 // String AutoAssignElasticIps
     735: invokeinterface #8,  2            // InterfaceMethod com/amazonaws/protocol/json/StructuredJsonGenerator.writeFieldName:(Ljava/lang/String;)Lcom/amazonaws/protocol/json/StructuredJsonGenerator;
     740: aload_1
     741: invokevirtual #57                 // Method com/amazonaws/services/opsworks/model/Layer.getAutoAssignElasticIps:()Ljava/lang/Boolean;
     744: invokevirtual #55                 // Method java/lang/Boolean.booleanValue:()Z
     747: invokeinterface #56,  2           // InterfaceMethod com/amazonaws/protocol/json/StructuredJsonGenerator.writeValue:(Z)Lcom/amazonaws/protocol/json/StructuredJsonGenerator;
     752: pop
     753: aload_1
     754: invokevirtual #59                 // Method com/amazonaws/services/opsworks/model/Layer.getAutoAssignPublicIps:()Ljava/lang/Boolean;
     757: ifnull        781
     760: aload_2
     761: ldc           #60                 // String AutoAssignPublicIps
     763: invokeinterface #8,  2            // InterfaceMethod com/amazonaws/protocol/json/StructuredJsonGenerator.writeFieldName:(Ljava/lang/String;)Lcom/amazonaws/protocol/json/StructuredJsonGenerator;
     768: aload_1
     769: invokevirtual #59                 // Method com/amazonaws/services/opsworks/model/Layer.getAutoAssignPublicIps:()Ljava/lang/Boolean;
     772: invokevirtual #55                 // Method java/lang/Boolean.booleanValue:()Z
     775: invokeinterface #56,  2           // InterfaceMethod com/amazonaws/protocol/json/StructuredJsonGenerator.writeValue:(Z)Lcom/amazonaws/protocol/json/StructuredJsonGenerator;
     780: pop
     781: aload_1
     782: invokevirtual #61                 // Method com/amazonaws/services/opsworks/model/Layer.getDefaultRecipes:()Lcom/amazonaws/services/opsworks/model/Recipes;
     785: ifnull        808
     788: aload_2
     789: ldc           #62                 // String DefaultRecipes
     791: invokeinterface #8,  2            // InterfaceMethod com/amazonaws/protocol/json/StructuredJsonGenerator.writeFieldName:(Ljava/lang/String;)Lcom/amazonaws/protocol/json/StructuredJsonGenerator;
     796: pop
     797: invokestatic  #63                 // Method com/amazonaws/services/opsworks/model/transform/RecipesJsonMarshaller.getInstance:()Lcom/amazonaws/services/opsworks/model/transform/RecipesJsonMarshaller;
     800: aload_1
     801: invokevirtual #61                 // Method com/amazonaws/services/opsworks/model/Layer.getDefaultRecipes:()Lcom/amazonaws/services/opsworks/model/Recipes;
     804: aload_2
     805: invokevirtual #64                 // Method com/amazonaws/services/opsworks/model/transform/RecipesJsonMarshaller.marshall:(Lcom/amazonaws/services/opsworks/model/Recipes;Lcom/amazonaws/protocol/json/StructuredJsonGenerator;)V
     808: aload_1
     809: invokevirtual #65                 // Method com/amazonaws/services/opsworks/model/Layer.getCustomRecipes:()Lcom/amazonaws/services/opsworks/model/Recipes;
     812: ifnull        835
     815: aload_2
     816: ldc           #66                 // String CustomRecipes
     818: invokeinterface #8,  2            // InterfaceMethod com/amazonaws/protocol/json/StructuredJsonGenerator.writeFieldName:(Ljava/lang/String;)Lcom/amazonaws/protocol/json/StructuredJsonGenerator;
     823: pop
     824: invokestatic  #63                 // Method com/amazonaws/services/opsworks/model/transform/RecipesJsonMarshaller.getInstance:()Lcom/amazonaws/services/opsworks/model/transform/RecipesJsonMarshaller;
     827: aload_1
     828: invokevirtual #65                 // Method com/amazonaws/services/opsworks/model/Layer.getCustomRecipes:()Lcom/amazonaws/services/opsworks/model/Recipes;
     831: aload_2
     832: invokevirtual #64                 // Method com/amazonaws/services/opsworks/model/transform/RecipesJsonMarshaller.marshall:(Lcom/amazonaws/services/opsworks/model/Recipes;Lcom/amazonaws/protocol/json/StructuredJsonGenerator;)V
     835: aload_1
     836: invokevirtual #67                 // Method com/amazonaws/services/opsworks/model/Layer.getCreatedAt:()Ljava/lang/String;
     839: ifnull        860
     842: aload_2
     843: ldc           #68                 // String CreatedAt
     845: invokeinterface #8,  2            // InterfaceMethod com/amazonaws/protocol/json/StructuredJsonGenerator.writeFieldName:(Ljava/lang/String;)Lcom/amazonaws/protocol/json/StructuredJsonGenerator;
     850: aload_1
     851: invokevirtual #67                 // Method com/amazonaws/services/opsworks/model/Layer.getCreatedAt:()Ljava/lang/String;
     854: invokeinterface #9,  2            // InterfaceMethod com/amazonaws/protocol/json/StructuredJsonGenerator.writeValue:(Ljava/lang/String;)Lcom/amazonaws/protocol/json/StructuredJsonGenerator;
     859: pop
     860: aload_1
     861: invokevirtual #69                 // Method com/amazonaws/services/opsworks/model/Layer.getInstallUpdatesOnBoot:()Ljava/lang/Boolean;
     864: ifnull        888
     867: aload_2
     868: ldc           #70                 // String InstallUpdatesOnBoot
     870: invokeinterface #8,  2            // InterfaceMethod com/amazonaws/protocol/json/StructuredJsonGenerator.writeFieldName:(Ljava/lang/String;)Lcom/amazonaws/protocol/json/StructuredJsonGenerator;
     875: aload_1
     876: invokevirtual #69                 // Method com/amazonaws/services/opsworks/model/Layer.getInstallUpdatesOnBoot:()Ljava/lang/Boolean;
     879: invokevirtual #55                 // Method java/lang/Boolean.booleanValue:()Z
     882: invokeinterface #56,  2           // InterfaceMethod com/amazonaws/protocol/json/StructuredJsonGenerator.writeValue:(Z)Lcom/amazonaws/protocol/json/StructuredJsonGenerator;
     887: pop
     888: aload_1
     889: invokevirtual #71                 // Method com/amazonaws/services/opsworks/model/Layer.getUseEbsOptimizedInstances:()Ljava/lang/Boolean;
     892: ifnull        916
     895: aload_2
     896: ldc           #72                 // String UseEbsOptimizedInstances
     898: invokeinterface #8,  2            // InterfaceMethod com/amazonaws/protocol/json/StructuredJsonGenerator.writeFieldName:(Ljava/lang/String;)Lcom/amazonaws/protocol/json/StructuredJsonGenerator;
     903: aload_1
     904: invokevirtual #71                 // Method com/amazonaws/services/opsworks/model/Layer.getUseEbsOptimizedInstances:()Ljava/lang/Boolean;
     907: invokevirtual #55                 // Method java/lang/Boolean.booleanValue:()Z
     910: invokeinterface #56,  2           // InterfaceMethod com/amazonaws/protocol/json/StructuredJsonGenerator.writeValue:(Z)Lcom/amazonaws/protocol/json/StructuredJsonGenerator;
     915: pop
     916: aload_1
     917: invokevirtual #73                 // Method com/amazonaws/services/opsworks/model/Layer.getLifecycleEventConfiguration:()Lcom/amazonaws/services/opsworks/model/LifecycleEventConfiguration;
     920: ifnull        943
     923: aload_2
     924: ldc           #74                 // String LifecycleEventConfiguration
     926: invokeinterface #8,  2            // InterfaceMethod com/amazonaws/protocol/json/StructuredJsonGenerator.writeFieldName:(Ljava/lang/String;)Lcom/amazonaws/protocol/json/StructuredJsonGenerator;
     931: pop
     932: invokestatic  #75                 // Method com/amazonaws/services/opsworks/model/transform/LifecycleEventConfigurationJsonMarshaller.getInstance:()Lcom/amazonaws/services/opsworks/model/transform/LifecycleEventConfigurationJsonMarshaller;
     935: aload_1
     936: invokevirtual #73                 // Method com/amazonaws/services/opsworks/model/Layer.getLifecycleEventConfiguration:()Lcom/amazonaws/services/opsworks/model/LifecycleEventConfiguration;
     939: aload_2
     940: invokevirtual #76                 // Method com/amazonaws/services/opsworks/model/transform/LifecycleEventConfigurationJsonMarshaller.marshall:(Lcom/amazonaws/services/opsworks/model/LifecycleEventConfiguration;Lcom/amazonaws/protocol/json/StructuredJsonGenerator;)V
     943: aload_2
     944: invokeinterface #31,  1           // InterfaceMethod com/amazonaws/protocol/json/StructuredJsonGenerator.writeEndObject:()Lcom/amazonaws/protocol/json/StructuredJsonGenerator;
     949: pop
     950: goto          985
     953: astore_3
     954: new           #2                  // class com/amazonaws/AmazonClientException
     957: dup
     958: new           #78                 // class java/lang/StringBuilder
     961: dup
     962: invokespecial #79                 // Method java/lang/StringBuilder."<init>":()V
     965: ldc           #80                 // String Unable to marshall request to JSON:
     967: invokevirtual #81                 // Method java/lang/StringBuilder.append:(Ljava/lang/String;)Ljava/lang/StringBuilder;
     970: aload_3
     971: invokevirtual #82                 // Method java/lang/Throwable.getMessage:()Ljava/lang/String;
     974: invokevirtual #81                 // Method java/lang/StringBuilder.append:(Ljava/lang/String;)Ljava/lang/StringBuilder;
     977: invokevirtual #83                 // Method java/lang/StringBuilder.toString:()Ljava/lang/String;
     980: aload_3
     981: invokespecial #84                 // Method com/amazonaws/AmazonClientException."<init>":(Ljava/lang/String;Ljava/lang/Throwable;)V
     984: athrow
     985: return
    Exception table:
       from    to  target type
          14   950   953   Class java/lang/Throwable

  public static com.amazonaws.services.opsworks.model.transform.LayerJsonMarshaller getInstance();
    Code:
       0: getstatic     #85                 // Field instance:Lcom/amazonaws/services/opsworks/model/transform/LayerJsonMarshaller;
       3: ifnonnull     16
       6: new           #86                 // class com/amazonaws/services/opsworks/model/transform/LayerJsonMarshaller
       9: dup
      10: invokespecial #87                 // Method "<init>":()V
      13: putstatic     #85                 // Field instance:Lcom/amazonaws/services/opsworks/model/transform/LayerJsonMarshaller;
      16: getstatic     #85                 // Field instance:Lcom/amazonaws/services/opsworks/model/transform/LayerJsonMarshaller;
      19: areturn
}
