Compiled from "DistinguishedName.java"
public class org.springframework.ldap.core.DistinguishedName implements javax.naming.Name {
  public static final java.lang.String SPACED_DN_FORMAT_PROPERTY;

  public static final java.lang.String KEY_CASE_FOLD_PROPERTY;

  public static final java.lang.String KEY_CASE_FOLD_LOWER;

  public static final java.lang.String KEY_CASE_FOLD_UPPER;

  public static final java.lang.String KEY_CASE_FOLD_NONE;

  private static final java.lang.String MANGLED_DOUBLE_QUOTES;

  private static final java.lang.String PROPER_DOUBLE_QUOTES;

  private static final org.slf4j.Logger LOG;

  private static final boolean COMPACT;

  private static final boolean NON_COMPACT;

  private static final long serialVersionUID;

  public static final org.springframework.ldap.core.DistinguishedName EMPTY_PATH;

  private static final int DEFAULT_BUFFER_SIZE;

  private java.util.List names;

  public org.springframework.ldap.core.DistinguishedName();
    Code:
       0: aload_0
       1: invokespecial #1                  // Method java/lang/Object."<init>":()V
       4: aload_0
       5: new           #2                  // class java/util/LinkedList
       8: dup
       9: invokespecial #3                  // Method java/util/LinkedList."<init>":()V
      12: putfield      #4                  // Field names:Ljava/util/List;
      15: return

  public org.springframework.ldap.core.DistinguishedName(java.lang.String);
    Code:
       0: aload_0
       1: invokespecial #1                  // Method java/lang/Object."<init>":()V
       4: aload_1
       5: invokestatic  #5                  // Method org/springframework/util/StringUtils.hasText:(Ljava/lang/String;)Z
       8: ifne          25
      11: aload_0
      12: new           #2                  // class java/util/LinkedList
      15: dup
      16: invokespecial #3                  // Method java/util/LinkedList."<init>":()V
      19: putfield      #4                  // Field names:Ljava/util/List;
      22: goto          30
      25: aload_0
      26: aload_1
      27: invokevirtual #6                  // Method parse:(Ljava/lang/String;)V
      30: return

  public org.springframework.ldap.core.DistinguishedName(java.util.List);
    Code:
       0: aload_0
       1: invokespecial #1                  // Method java/lang/Object."<init>":()V
       4: aload_0
       5: aload_1
       6: putfield      #4                  // Field names:Ljava/util/List;
       9: return

  public org.springframework.ldap.core.DistinguishedName(javax.naming.Name);
    Code:
       0: aload_0
       1: invokespecial #1                  // Method java/lang/Object."<init>":()V
       4: aload_1
       5: ldc           #7                  // String name cannot be null
       7: invokestatic  #8                  // Method org/springframework/util/Assert.notNull:(Ljava/lang/Object;Ljava/lang/String;)V
      10: aload_1
      11: instanceof    #9                  // class javax/naming/CompositeName
      14: ifeq          29
      17: aload_0
      18: aload_1
      19: checkcast     #9                  // class javax/naming/CompositeName
      22: invokestatic  #10                 // Method org/springframework/ldap/support/LdapUtils.convertCompositeNameToString:(Ljavax/naming/CompositeName;)Ljava/lang/String;
      25: invokevirtual #6                  // Method parse:(Ljava/lang/String;)V
      28: return
      29: aload_0
      30: new           #2                  // class java/util/LinkedList
      33: dup
      34: invokespecial #3                  // Method java/util/LinkedList."<init>":()V
      37: putfield      #4                  // Field names:Ljava/util/List;
      40: iconst_0
      41: istore_2
      42: iload_2
      43: aload_1
      44: invokeinterface #11,  1           // InterfaceMethod javax/naming/Name.size:()I
      49: if_icmpge     82
      52: aload_0
      53: getfield      #4                  // Field names:Ljava/util/List;
      56: new           #12                 // class org/springframework/ldap/core/LdapRdn
      59: dup
      60: aload_1
      61: iload_2
      62: invokeinterface #13,  2           // InterfaceMethod javax/naming/Name.get:(I)Ljava/lang/String;
      67: invokespecial #14                 // Method org/springframework/ldap/core/LdapRdn."<init>":(Ljava/lang/String;)V
      70: invokeinterface #15,  2           // InterfaceMethod java/util/List.add:(Ljava/lang/Object;)Z
      75: pop
      76: iinc          2, 1
      79: goto          42
      82: return

  protected final void parse(java.lang.String);
    Code:
       0: aload_0
       1: aload_1
       2: invokespecial #16                 // Method unmangleCompositeName:(Ljava/lang/String;)Ljava/lang/String;
       5: invokestatic  #17                 // Method org/springframework/ldap/core/DefaultDnParserFactory.createDnParser:(Ljava/lang/String;)Lorg/springframework/ldap/core/DnParser;
       8: astore_2
       9: aload_2
      10: invokeinterface #18,  1           // InterfaceMethod org/springframework/ldap/core/DnParser.dn:()Lorg/springframework/ldap/core/DistinguishedName;
      15: astore_3
      16: goto          47
      19: astore        4
      21: new           #20                 // class org/springframework/ldap/BadLdapGrammarException
      24: dup
      25: ldc           #21                 // String Failed to parse DN
      27: aload         4
      29: invokespecial #22                 // Method org/springframework/ldap/BadLdapGrammarException."<init>":(Ljava/lang/String;Ljava/lang/Throwable;)V
      32: athrow
      33: astore        4
      35: new           #20                 // class org/springframework/ldap/BadLdapGrammarException
      38: dup
      39: ldc           #21                 // String Failed to parse DN
      41: aload         4
      43: invokespecial #22                 // Method org/springframework/ldap/BadLdapGrammarException."<init>":(Ljava/lang/String;Ljava/lang/Throwable;)V
      46: athrow
      47: aload_0
      48: aload_3
      49: getfield      #4                  // Field names:Ljava/util/List;
      52: putfield      #4                  // Field names:Ljava/util/List;
      55: return
    Exception table:
       from    to  target type
           9    16    19   Class org/springframework/ldap/core/ParseException
           9    16    33   Class org/springframework/ldap/core/TokenMgrError

  private java.lang.String unmangleCompositeName(java.lang.String);
    Code:
       0: aload_1
       1: ldc           #24                 // String \"
       3: invokevirtual #25                 // Method java/lang/String.startsWith:(Ljava/lang/String;)Z
       6: ifeq          33
       9: aload_1
      10: ldc           #24                 // String \"
      12: invokevirtual #26                 // Method java/lang/String.endsWith:(Ljava/lang/String;)Z
      15: ifeq          33
      18: aload_1
      19: iconst_1
      20: aload_1
      21: invokevirtual #27                 // Method java/lang/String.length:()I
      24: iconst_1
      25: isub
      26: invokevirtual #28                 // Method java/lang/String.substring:(II)Ljava/lang/String;
      29: astore_2
      30: goto          35
      33: aload_1
      34: astore_2
      35: aload_2
      36: ldc           #30                 // String \\\\\"
      38: ldc           #31                 // String \\\"
      40: invokestatic  #32                 // Method org/springframework/util/StringUtils.replace:(Ljava/lang/String;Ljava/lang/String;Ljava/lang/String;)Ljava/lang/String;
      43: astore_2
      44: aload_2
      45: areturn

  public org.springframework.ldap.core.LdapRdn getLdapRdn(int);
    Code:
       0: aload_0
       1: getfield      #4                  // Field names:Ljava/util/List;
       4: iload_1
       5: invokeinterface #33,  2           // InterfaceMethod java/util/List.get:(I)Ljava/lang/Object;
      10: checkcast     #12                 // class org/springframework/ldap/core/LdapRdn
      13: areturn

  public org.springframework.ldap.core.LdapRdn getLdapRdn(java.lang.String);
    Code:
       0: aload_0
       1: getfield      #4                  // Field names:Ljava/util/List;
       4: invokeinterface #34,  1           // InterfaceMethod java/util/List.iterator:()Ljava/util/Iterator;
       9: astore_2
      10: aload_2
      11: invokeinterface #35,  1           // InterfaceMethod java/util/Iterator.hasNext:()Z
      16: ifeq          45
      19: aload_2
      20: invokeinterface #36,  1           // InterfaceMethod java/util/Iterator.next:()Ljava/lang/Object;
      25: checkcast     #12                 // class org/springframework/ldap/core/LdapRdn
      28: astore_3
      29: aload_3
      30: invokevirtual #37                 // Method org/springframework/ldap/core/LdapRdn.getKey:()Ljava/lang/String;
      33: aload_1
      34: invokestatic  #38                 // Method org/springframework/util/ObjectUtils.nullSafeEquals:(Ljava/lang/Object;Ljava/lang/Object;)Z
      37: ifeq          42
      40: aload_3
      41: areturn
      42: goto          10
      45: new           #39                 // class java/lang/IllegalArgumentException
      48: dup
      49: new           #40                 // class java/lang/StringBuilder
      52: dup
      53: invokespecial #41                 // Method java/lang/StringBuilder."<init>":()V
      56: ldc           #42                 // String No Rdn with the requested key: \'
      58: invokevirtual #43                 // Method java/lang/StringBuilder.append:(Ljava/lang/String;)Ljava/lang/StringBuilder;
      61: aload_1
      62: invokevirtual #43                 // Method java/lang/StringBuilder.append:(Ljava/lang/String;)Ljava/lang/StringBuilder;
      65: ldc           #44                 // String \'
      67: invokevirtual #43                 // Method java/lang/StringBuilder.append:(Ljava/lang/String;)Ljava/lang/StringBuilder;
      70: invokevirtual #45                 // Method java/lang/StringBuilder.toString:()Ljava/lang/String;
      73: invokespecial #46                 // Method java/lang/IllegalArgumentException."<init>":(Ljava/lang/String;)V
      76: athrow

  public java.lang.String getValue(java.lang.String);
    Code:
       0: aload_0
       1: aload_1
       2: invokevirtual #47                 // Method getLdapRdn:(Ljava/lang/String;)Lorg/springframework/ldap/core/LdapRdn;
       5: invokevirtual #48                 // Method org/springframework/ldap/core/LdapRdn.getValue:()Ljava/lang/String;
       8: areturn

  public java.util.List getNames();
    Code:
       0: aload_0
       1: getfield      #4                  // Field names:Ljava/util/List;
       4: areturn

  public java.lang.String toString();
    Code:
       0: ldc           #49                 // String org.springframework.ldap.core.spacedDnFormat
       2: invokestatic  #50                 // Method java/lang/System.getProperty:(Ljava/lang/String;)Ljava/lang/String;
       5: astore_1
       6: aload_1
       7: invokestatic  #5                  // Method org/springframework/util/StringUtils.hasText:(Ljava/lang/String;)Z
      10: ifne          19
      13: aload_0
      14: iconst_1
      15: invokespecial #51                 // Method format:(Z)Ljava/lang/String;
      18: areturn
      19: aload_0
      20: iconst_0
      21: invokespecial #51                 // Method format:(Z)Ljava/lang/String;
      24: areturn

  public java.lang.String toCompactString();
    Code:
       0: aload_0
       1: iconst_1
       2: invokespecial #51                 // Method format:(Z)Ljava/lang/String;
       5: areturn

  public java.lang.String encode();
    Code:
       0: aload_0
       1: iconst_0
       2: invokespecial #51                 // Method format:(Z)Ljava/lang/String;
       5: areturn

  private java.lang.String format(boolean);
    Code:
       0: aload_0
       1: getfield      #4                  // Field names:Ljava/util/List;
       4: invokeinterface #52,  1           // InterfaceMethod java/util/List.size:()I
       9: ifne          15
      12: ldc           #53                 // String
      14: areturn
      15: new           #54                 // class java/lang/StringBuffer
      18: dup
      19: sipush        256
      22: invokespecial #55                 // Method java/lang/StringBuffer."<init>":(I)V
      25: astore_2
      26: aload_0
      27: getfield      #4                  // Field names:Ljava/util/List;
      30: aload_0
      31: getfield      #4                  // Field names:Ljava/util/List;
      34: invokeinterface #52,  1           // InterfaceMethod java/util/List.size:()I
      39: invokeinterface #56,  2           // InterfaceMethod java/util/List.listIterator:(I)Ljava/util/ListIterator;
      44: astore_3
      45: aload_3
      46: invokeinterface #57,  1           // InterfaceMethod java/util/ListIterator.hasPrevious:()Z
      51: ifeq          108
      54: aload_3
      55: invokeinterface #58,  1           // InterfaceMethod java/util/ListIterator.previous:()Ljava/lang/Object;
      60: checkcast     #12                 // class org/springframework/ldap/core/LdapRdn
      63: astore        4
      65: aload_2
      66: aload         4
      68: invokevirtual #59                 // Method org/springframework/ldap/core/LdapRdn.getLdapEncoded:()Ljava/lang/String;
      71: invokevirtual #60                 // Method java/lang/StringBuffer.append:(Ljava/lang/String;)Ljava/lang/StringBuffer;
      74: pop
      75: aload_3
      76: invokeinterface #57,  1           // InterfaceMethod java/util/ListIterator.hasPrevious:()Z
      81: ifeq          105
      84: iload_1
      85: ifeq          98
      88: aload_2
      89: ldc           #61                 // String ,
      91: invokevirtual #60                 // Method java/lang/StringBuffer.append:(Ljava/lang/String;)Ljava/lang/StringBuffer;
      94: pop
      95: goto          105
      98: aload_2
      99: ldc           #62                 // String ,
     101: invokevirtual #60                 // Method java/lang/StringBuffer.append:(Ljava/lang/String;)Ljava/lang/StringBuffer;
     104: pop
     105: goto          45
     108: aload_2
     109: invokevirtual #63                 // Method java/lang/StringBuffer.toString:()Ljava/lang/String;
     112: areturn

  public java.lang.String toUrl();
    Code:
       0: new           #54                 // class java/lang/StringBuffer
       3: dup
       4: sipush        256
       7: invokespecial #55                 // Method java/lang/StringBuffer."<init>":(I)V
      10: astore_1
      11: aload_0
      12: getfield      #4                  // Field names:Ljava/util/List;
      15: invokeinterface #52,  1           // InterfaceMethod java/util/List.size:()I
      20: iconst_1
      21: isub
      22: istore_2
      23: iload_2
      24: iflt          67
      27: aload_0
      28: getfield      #4                  // Field names:Ljava/util/List;
      31: iload_2
      32: invokeinterface #33,  2           // InterfaceMethod java/util/List.get:(I)Ljava/lang/Object;
      37: checkcast     #12                 // class org/springframework/ldap/core/LdapRdn
      40: astore_3
      41: aload_1
      42: aload_3
      43: invokevirtual #64                 // Method org/springframework/ldap/core/LdapRdn.encodeUrl:()Ljava/lang/String;
      46: invokevirtual #60                 // Method java/lang/StringBuffer.append:(Ljava/lang/String;)Ljava/lang/StringBuffer;
      49: pop
      50: iload_2
      51: ifle          61
      54: aload_1
      55: ldc           #61                 // String ,
      57: invokevirtual #60                 // Method java/lang/StringBuffer.append:(Ljava/lang/String;)Ljava/lang/StringBuffer;
      60: pop
      61: iinc          2, -1
      64: goto          23
      67: aload_1
      68: invokevirtual #63                 // Method java/lang/StringBuffer.toString:()Ljava/lang/String;
      71: areturn

  public boolean contains(org.springframework.ldap.core.DistinguishedName);
    Code:
       0: aload_1
       1: invokevirtual #65                 // Method getNames:()Ljava/util/List;
       4: astore_2
       5: aload_0
       6: invokevirtual #65                 // Method getNames:()Ljava/util/List;
       9: invokeinterface #52,  1           // InterfaceMethod java/util/List.size:()I
      14: aload_2
      15: invokeinterface #52,  1           // InterfaceMethod java/util/List.size:()I
      20: if_icmpge     25
      23: iconst_0
      24: ireturn
      25: aload_2
      26: invokeinterface #52,  1           // InterfaceMethod java/util/List.size:()I
      31: ifne          36
      34: iconst_0
      35: ireturn
      36: aload_0
      37: invokevirtual #65                 // Method getNames:()Ljava/util/List;
      40: invokeinterface #34,  1           // InterfaceMethod java/util/List.iterator:()Ljava/util/Iterator;
      45: astore_3
      46: aload_2
      47: invokeinterface #34,  1           // InterfaceMethod java/util/List.iterator:()Ljava/util/Iterator;
      52: astore        4
      54: aload_3
      55: invokeinterface #36,  1           // InterfaceMethod java/util/Iterator.next:()Ljava/lang/Object;
      60: checkcast     #12                 // class org/springframework/ldap/core/LdapRdn
      63: astore        5
      65: aload         4
      67: invokeinterface #36,  1           // InterfaceMethod java/util/Iterator.next:()Ljava/lang/Object;
      72: checkcast     #12                 // class org/springframework/ldap/core/LdapRdn
      75: astore        6
      77: aload         5
      79: aload         6
      81: invokevirtual #66                 // Method org/springframework/ldap/core/LdapRdn.equals:(Ljava/lang/Object;)Z
      84: ifne          110
      87: aload_3
      88: invokeinterface #35,  1           // InterfaceMethod java/util/Iterator.hasNext:()Z
      93: ifeq          110
      96: aload_3
      97: invokeinterface #36,  1           // InterfaceMethod java/util/Iterator.next:()Ljava/lang/Object;
     102: checkcast     #12                 // class org/springframework/ldap/core/LdapRdn
     105: astore        5
     107: goto          77
     110: aload         4
     112: invokeinterface #35,  1           // InterfaceMethod java/util/Iterator.hasNext:()Z
     117: ifne          132
     120: aload         5
     122: aload         6
     124: invokevirtual #66                 // Method org/springframework/ldap/core/LdapRdn.equals:(Ljava/lang/Object;)Z
     127: ifeq          132
     130: iconst_1
     131: ireturn
     132: aload_3
     133: invokeinterface #35,  1           // InterfaceMethod java/util/Iterator.hasNext:()Z
     138: ifne          143
     141: iconst_0
     142: ireturn
     143: aload         5
     145: aload         6
     147: invokevirtual #66                 // Method org/springframework/ldap/core/LdapRdn.equals:(Ljava/lang/Object;)Z
     150: ifeq          198
     153: aload_3
     154: invokeinterface #35,  1           // InterfaceMethod java/util/Iterator.hasNext:()Z
     159: ifeq          198
     162: aload         4
     164: invokeinterface #35,  1           // InterfaceMethod java/util/Iterator.hasNext:()Z
     169: ifeq          198
     172: aload_3
     173: invokeinterface #36,  1           // InterfaceMethod java/util/Iterator.next:()Ljava/lang/Object;
     178: checkcast     #12                 // class org/springframework/ldap/core/LdapRdn
     181: astore        5
     183: aload         4
     185: invokeinterface #36,  1           // InterfaceMethod java/util/Iterator.next:()Ljava/lang/Object;
     190: checkcast     #12                 // class org/springframework/ldap/core/LdapRdn
     193: astore        6
     195: goto          143
     198: aload         4
     200: invokeinterface #35,  1           // InterfaceMethod java/util/Iterator.hasNext:()Z
     205: ifne          222
     208: aload         5
     210: aload         6
     212: invokevirtual #66                 // Method org/springframework/ldap/core/LdapRdn.equals:(Ljava/lang/Object;)Z
     215: ifeq          222
     218: iconst_1
     219: goto          223
     222: iconst_0
     223: ireturn

  public org.springframework.ldap.core.DistinguishedName append(org.springframework.ldap.core.DistinguishedName);
    Code:
       0: aload_0
       1: invokevirtual #65                 // Method getNames:()Ljava/util/List;
       4: aload_1
       5: invokevirtual #65                 // Method getNames:()Ljava/util/List;
       8: invokeinterface #67,  2           // InterfaceMethod java/util/List.addAll:(Ljava/util/Collection;)Z
      13: pop
      14: aload_0
      15: areturn

  public org.springframework.ldap.core.DistinguishedName append(java.lang.String, java.lang.String);
    Code:
       0: aload_0
       1: aload_1
       2: aload_2
       3: invokevirtual #68                 // Method add:(Ljava/lang/String;Ljava/lang/String;)V
       6: aload_0
       7: areturn

  public void prepend(org.springframework.ldap.core.DistinguishedName);
    Code:
       0: aload_1
       1: invokevirtual #65                 // Method getNames:()Ljava/util/List;
       4: aload_1
       5: invokevirtual #65                 // Method getNames:()Ljava/util/List;
       8: invokeinterface #52,  1           // InterfaceMethod java/util/List.size:()I
      13: invokeinterface #56,  2           // InterfaceMethod java/util/List.listIterator:(I)Ljava/util/ListIterator;
      18: astore_2
      19: aload_2
      20: invokeinterface #57,  1           // InterfaceMethod java/util/ListIterator.hasPrevious:()Z
      25: ifeq          47
      28: aload_0
      29: getfield      #4                  // Field names:Ljava/util/List;
      32: iconst_0
      33: aload_2
      34: invokeinterface #58,  1           // InterfaceMethod java/util/ListIterator.previous:()Ljava/lang/Object;
      39: invokeinterface #69,  3           // InterfaceMethod java/util/List.add:(ILjava/lang/Object;)V
      44: goto          19
      47: return

  public org.springframework.ldap.core.LdapRdn removeFirst();
    Code:
       0: aload_0
       1: getfield      #4                  // Field names:Ljava/util/List;
       4: iconst_0
       5: invokeinterface #70,  2           // InterfaceMethod java/util/List.remove:(I)Ljava/lang/Object;
      10: checkcast     #12                 // class org/springframework/ldap/core/LdapRdn
      13: areturn

  public void removeFirst(javax.naming.Name);
    Code:
       0: aload_1
       1: ifnull        35
       4: aload_0
       5: aload_1
       6: invokevirtual #71                 // Method startsWith:(Ljavax/naming/Name;)Z
       9: ifeq          35
      12: iconst_0
      13: istore_2
      14: iload_2
      15: aload_1
      16: invokeinterface #11,  1           // InterfaceMethod javax/naming/Name.size:()I
      21: if_icmpge     35
      24: aload_0
      25: invokevirtual #72                 // Method removeFirst:()Lorg/springframework/ldap/core/LdapRdn;
      28: pop
      29: iinc          2, 1
      32: goto          14
      35: return

  public java.lang.Object clone();
    Code:
       0: aload_0
       1: invokespecial #73                 // Method java/lang/Object.clone:()Ljava/lang/Object;
       4: checkcast     #29                 // class org/springframework/ldap/core/DistinguishedName
       7: astore_1
       8: aload_1
       9: new           #2                  // class java/util/LinkedList
      12: dup
      13: aload_0
      14: getfield      #4                  // Field names:Ljava/util/List;
      17: invokespecial #74                 // Method java/util/LinkedList."<init>":(Ljava/util/Collection;)V
      20: putfield      #4                  // Field names:Ljava/util/List;
      23: aload_1
      24: areturn
      25: astore_1
      26: getstatic     #76                 // Field LOG:Lorg/slf4j/Logger;
      29: ldc           #77                 // String CloneNotSupported thrown from superclass - this should not happen
      31: invokeinterface #78,  2           // InterfaceMethod org/slf4j/Logger.error:(Ljava/lang/String;)V
      36: new           #79                 // class org/springframework/ldap/UncategorizedLdapException
      39: dup
      40: ldc           #80                 // String Fatal error in clone
      42: aload_1
      43: invokespecial #81                 // Method org/springframework/ldap/UncategorizedLdapException."<init>":(Ljava/lang/String;Ljava/lang/Throwable;)V
      46: athrow
    Exception table:
       from    to  target type
           0    24    25   Class java/lang/CloneNotSupportedException

  public boolean equals(java.lang.Object);
    Code:
       0: aload_1
       1: ifnull        15
       4: aload_1
       5: invokevirtual #82                 // Method java/lang/Object.getClass:()Ljava/lang/Class;
       8: aload_0
       9: invokevirtual #82                 // Method java/lang/Object.getClass:()Ljava/lang/Class;
      12: if_acmpeq     17
      15: iconst_0
      16: ireturn
      17: aload_1
      18: checkcast     #29                 // class org/springframework/ldap/core/DistinguishedName
      21: astore_2
      22: aload_0
      23: invokevirtual #65                 // Method getNames:()Ljava/util/List;
      26: aload_2
      27: invokevirtual #65                 // Method getNames:()Ljava/util/List;
      30: invokeinterface #83,  2           // InterfaceMethod java/util/List.equals:(Ljava/lang/Object;)Z
      35: ireturn

  public int hashCode();
    Code:
       0: aload_0
       1: invokevirtual #82                 // Method java/lang/Object.getClass:()Ljava/lang/Class;
       4: invokevirtual #84                 // Method java/lang/Object.hashCode:()I
       7: aload_0
       8: invokevirtual #65                 // Method getNames:()Ljava/util/List;
      11: invokeinterface #85,  1           // InterfaceMethod java/util/List.hashCode:()I
      16: ixor
      17: ireturn

  public int compareTo(java.lang.Object);
    Code:
       0: aload_1
       1: checkcast     #29                 // class org/springframework/ldap/core/DistinguishedName
       4: astore_2
       5: new           #86                 // class org/springframework/ldap/support/ListComparator
       8: dup
       9: invokespecial #87                 // Method org/springframework/ldap/support/ListComparator."<init>":()V
      12: astore_3
      13: aload_3
      14: aload_0
      15: getfield      #4                  // Field names:Ljava/util/List;
      18: aload_2
      19: getfield      #4                  // Field names:Ljava/util/List;
      22: invokevirtual #88                 // Method org/springframework/ldap/support/ListComparator.compare:(Ljava/lang/Object;Ljava/lang/Object;)I
      25: ireturn

  public int size();
    Code:
       0: aload_0
       1: getfield      #4                  // Field names:Ljava/util/List;
       4: invokeinterface #52,  1           // InterfaceMethod java/util/List.size:()I
       9: ireturn

  public boolean isEmpty();
    Code:
       0: aload_0
       1: getfield      #4                  // Field names:Ljava/util/List;
       4: invokeinterface #52,  1           // InterfaceMethod java/util/List.size:()I
       9: ifne          16
      12: iconst_1
      13: goto          17
      16: iconst_0
      17: ireturn

  public java.util.Enumeration getAll();
    Code:
       0: new           #2                  // class java/util/LinkedList
       3: dup
       4: invokespecial #3                  // Method java/util/LinkedList."<init>":()V
       7: astore_1
       8: aload_0
       9: getfield      #4                  // Field names:Ljava/util/List;
      12: invokeinterface #34,  1           // InterfaceMethod java/util/List.iterator:()Ljava/util/Iterator;
      17: astore_2
      18: aload_2
      19: invokeinterface #35,  1           // InterfaceMethod java/util/Iterator.hasNext:()Z
      24: ifeq          49
      27: aload_2
      28: invokeinterface #36,  1           // InterfaceMethod java/util/Iterator.next:()Ljava/lang/Object;
      33: checkcast     #12                 // class org/springframework/ldap/core/LdapRdn
      36: astore_3
      37: aload_1
      38: aload_3
      39: invokevirtual #59                 // Method org/springframework/ldap/core/LdapRdn.getLdapEncoded:()Ljava/lang/String;
      42: invokevirtual #89                 // Method java/util/LinkedList.add:(Ljava/lang/Object;)Z
      45: pop
      46: goto          18
      49: aload_1
      50: invokestatic  #90                 // Method java/util/Collections.enumeration:(Ljava/util/Collection;)Ljava/util/Enumeration;
      53: areturn

  public java.lang.String get(int);
    Code:
       0: aload_0
       1: getfield      #4                  // Field names:Ljava/util/List;
       4: iload_1
       5: invokeinterface #33,  2           // InterfaceMethod java/util/List.get:(I)Ljava/lang/Object;
      10: checkcast     #12                 // class org/springframework/ldap/core/LdapRdn
      13: astore_2
      14: aload_2
      15: invokevirtual #59                 // Method org/springframework/ldap/core/LdapRdn.getLdapEncoded:()Ljava/lang/String;
      18: areturn

  public javax.naming.Name getPrefix(int);
    Code:
       0: new           #2                  // class java/util/LinkedList
       3: dup
       4: invokespecial #3                  // Method java/util/LinkedList."<init>":()V
       7: astore_2
       8: iconst_0
       9: istore_3
      10: iload_3
      11: iload_1
      12: if_icmpge     36
      15: aload_2
      16: aload_0
      17: getfield      #4                  // Field names:Ljava/util/List;
      20: iload_3
      21: invokeinterface #33,  2           // InterfaceMethod java/util/List.get:(I)Ljava/lang/Object;
      26: invokevirtual #89                 // Method java/util/LinkedList.add:(Ljava/lang/Object;)Z
      29: pop
      30: iinc          3, 1
      33: goto          10
      36: new           #29                 // class org/springframework/ldap/core/DistinguishedName
      39: dup
      40: aload_2
      41: invokespecial #91                 // Method "<init>":(Ljava/util/List;)V
      44: areturn

  public javax.naming.Name getSuffix(int);
    Code:
       0: iload_1
       1: aload_0
       2: getfield      #4                  // Field names:Ljava/util/List;
       5: invokeinterface #52,  1           // InterfaceMethod java/util/List.size:()I
      10: if_icmple     21
      13: new           #92                 // class java/lang/ArrayIndexOutOfBoundsException
      16: dup
      17: invokespecial #93                 // Method java/lang/ArrayIndexOutOfBoundsException."<init>":()V
      20: athrow
      21: new           #2                  // class java/util/LinkedList
      24: dup
      25: invokespecial #3                  // Method java/util/LinkedList."<init>":()V
      28: astore_2
      29: iload_1
      30: istore_3
      31: iload_3
      32: aload_0
      33: getfield      #4                  // Field names:Ljava/util/List;
      36: invokeinterface #52,  1           // InterfaceMethod java/util/List.size:()I
      41: if_icmpge     65
      44: aload_2
      45: aload_0
      46: getfield      #4                  // Field names:Ljava/util/List;
      49: iload_3
      50: invokeinterface #33,  2           // InterfaceMethod java/util/List.get:(I)Ljava/lang/Object;
      55: invokevirtual #89                 // Method java/util/LinkedList.add:(Ljava/lang/Object;)Z
      58: pop
      59: iinc          3, 1
      62: goto          31
      65: new           #29                 // class org/springframework/ldap/core/DistinguishedName
      68: dup
      69: aload_2
      70: invokespecial #91                 // Method "<init>":(Ljava/util/List;)V
      73: areturn

  public boolean startsWith(javax.naming.Name);
    Code:
       0: aload_1
       1: invokeinterface #11,  1           // InterfaceMethod javax/naming/Name.size:()I
       6: ifne          11
       9: iconst_0
      10: ireturn
      11: aconst_null
      12: astore_2
      13: aload_1
      14: instanceof    #29                 // class org/springframework/ldap/core/DistinguishedName
      17: ifeq          28
      20: aload_1
      21: checkcast     #29                 // class org/springframework/ldap/core/DistinguishedName
      24: astore_2
      25: goto          30
      28: iconst_0
      29: ireturn
      30: aload_2
      31: invokevirtual #94                 // Method size:()I
      34: aload_0
      35: invokevirtual #94                 // Method size:()I
      38: if_icmple     43
      41: iconst_0
      42: ireturn
      43: aload_0
      44: getfield      #4                  // Field names:Ljava/util/List;
      47: invokeinterface #34,  1           // InterfaceMethod java/util/List.iterator:()Ljava/util/Iterator;
      52: astore_3
      53: aload_2
      54: invokevirtual #65                 // Method getNames:()Ljava/util/List;
      57: invokeinterface #34,  1           // InterfaceMethod java/util/List.iterator:()Ljava/util/Iterator;
      62: astore        4
      64: aload         4
      66: invokeinterface #35,  1           // InterfaceMethod java/util/Iterator.hasNext:()Z
      71: ifeq          106
      74: aload_3
      75: invokeinterface #36,  1           // InterfaceMethod java/util/Iterator.next:()Ljava/lang/Object;
      80: astore        5
      82: aload         4
      84: invokeinterface #36,  1           // InterfaceMethod java/util/Iterator.next:()Ljava/lang/Object;
      89: astore        6
      91: aload         5
      93: aload         6
      95: invokevirtual #95                 // Method java/lang/Object.equals:(Ljava/lang/Object;)Z
      98: ifne          103
     101: iconst_0
     102: ireturn
     103: goto          64
     106: iconst_1
     107: ireturn

  public boolean endsWith(javax.naming.Name);
    Code:
       0: aconst_null
       1: astore_2
       2: aload_1
       3: instanceof    #29                 // class org/springframework/ldap/core/DistinguishedName
       6: ifeq          17
       9: aload_1
      10: checkcast     #29                 // class org/springframework/ldap/core/DistinguishedName
      13: astore_2
      14: goto          19
      17: iconst_0
      18: ireturn
      19: aload_2
      20: invokevirtual #65                 // Method getNames:()Ljava/util/List;
      23: astore_3
      24: aload_0
      25: invokevirtual #65                 // Method getNames:()Ljava/util/List;
      28: invokeinterface #52,  1           // InterfaceMethod java/util/List.size:()I
      33: aload_3
      34: invokeinterface #52,  1           // InterfaceMethod java/util/List.size:()I
      39: if_icmpge     44
      42: iconst_0
      43: ireturn
      44: aload_3
      45: invokeinterface #52,  1           // InterfaceMethod java/util/List.size:()I
      50: ifne          55
      53: iconst_0
      54: ireturn
      55: aload_0
      56: invokevirtual #65                 // Method getNames:()Ljava/util/List;
      59: aload_0
      60: invokevirtual #65                 // Method getNames:()Ljava/util/List;
      63: invokeinterface #52,  1           // InterfaceMethod java/util/List.size:()I
      68: invokeinterface #56,  2           // InterfaceMethod java/util/List.listIterator:(I)Ljava/util/ListIterator;
      73: astore        4
      75: aload_3
      76: aload_3
      77: invokeinterface #52,  1           // InterfaceMethod java/util/List.size:()I
      82: invokeinterface #56,  2           // InterfaceMethod java/util/List.listIterator:(I)Ljava/util/ListIterator;
      87: astore        5
      89: aload         5
      91: invokeinterface #57,  1           // InterfaceMethod java/util/ListIterator.hasPrevious:()Z
      96: ifeq          138
      99: aload         4
     101: invokeinterface #58,  1           // InterfaceMethod java/util/ListIterator.previous:()Ljava/lang/Object;
     106: checkcast     #12                 // class org/springframework/ldap/core/LdapRdn
     109: astore        6
     111: aload         5
     113: invokeinterface #58,  1           // InterfaceMethod java/util/ListIterator.previous:()Ljava/lang/Object;
     118: checkcast     #12                 // class org/springframework/ldap/core/LdapRdn
     121: astore        7
     123: aload         6
     125: aload         7
     127: invokevirtual #66                 // Method org/springframework/ldap/core/LdapRdn.equals:(Ljava/lang/Object;)Z
     130: ifne          135
     133: iconst_0
     134: ireturn
     135: goto          89
     138: iconst_1
     139: ireturn

  public javax.naming.Name addAll(javax.naming.Name) throws javax.naming.InvalidNameException;
    Code:
       0: aload_0
       1: aload_0
       2: getfield      #4                  // Field names:Ljava/util/List;
       5: invokeinterface #52,  1           // InterfaceMethod java/util/List.size:()I
      10: aload_1
      11: invokevirtual #96                 // Method addAll:(ILjavax/naming/Name;)Ljavax/naming/Name;
      14: areturn

  public javax.naming.Name addAll(int, javax.naming.Name) throws javax.naming.InvalidNameException;
    Code:
       0: aconst_null
       1: astore_3
       2: aload_2
       3: checkcast     #29                 // class org/springframework/ldap/core/DistinguishedName
       6: astore_3
       7: goto          22
      10: astore        4
      12: new           #98                 // class javax/naming/InvalidNameException
      15: dup
      16: ldc           #99                 // String Invalid name type
      18: invokespecial #100                // Method javax/naming/InvalidNameException."<init>":(Ljava/lang/String;)V
      21: athrow
      22: aload_0
      23: getfield      #4                  // Field names:Ljava/util/List;
      26: iload_1
      27: aload_3
      28: invokevirtual #65                 // Method getNames:()Ljava/util/List;
      31: invokeinterface #101,  3          // InterfaceMethod java/util/List.addAll:(ILjava/util/Collection;)Z
      36: pop
      37: aload_0
      38: areturn
    Exception table:
       from    to  target type
           2     7    10   Class java/lang/ClassCastException

  public javax.naming.Name add(java.lang.String) throws javax.naming.InvalidNameException;
    Code:
       0: aload_0
       1: aload_0
       2: getfield      #4                  // Field names:Ljava/util/List;
       5: invokeinterface #52,  1           // InterfaceMethod java/util/List.size:()I
      10: aload_1
      11: invokevirtual #102                // Method add:(ILjava/lang/String;)Ljavax/naming/Name;
      14: areturn

  public javax.naming.Name add(int, java.lang.String) throws javax.naming.InvalidNameException;
    Code:
       0: aload_0
       1: getfield      #4                  // Field names:Ljava/util/List;
       4: iload_1
       5: new           #12                 // class org/springframework/ldap/core/LdapRdn
       8: dup
       9: aload_2
      10: invokespecial #14                 // Method org/springframework/ldap/core/LdapRdn."<init>":(Ljava/lang/String;)V
      13: invokeinterface #69,  3           // InterfaceMethod java/util/List.add:(ILjava/lang/Object;)V
      18: goto          54
      21: astore_3
      22: new           #98                 // class javax/naming/InvalidNameException
      25: dup
      26: new           #40                 // class java/lang/StringBuilder
      29: dup
      30: invokespecial #41                 // Method java/lang/StringBuilder."<init>":()V
      33: ldc           #103                // String Failed to parse rdn \'
      35: invokevirtual #43                 // Method java/lang/StringBuilder.append:(Ljava/lang/String;)Ljava/lang/StringBuilder;
      38: aload_2
      39: invokevirtual #43                 // Method java/lang/StringBuilder.append:(Ljava/lang/String;)Ljava/lang/StringBuilder;
      42: ldc           #44                 // String \'
      44: invokevirtual #43                 // Method java/lang/StringBuilder.append:(Ljava/lang/String;)Ljava/lang/StringBuilder;
      47: invokevirtual #45                 // Method java/lang/StringBuilder.toString:()Ljava/lang/String;
      50: invokespecial #100                // Method javax/naming/InvalidNameException."<init>":(Ljava/lang/String;)V
      53: athrow
      54: aload_0
      55: areturn
    Exception table:
       from    to  target type
           0    18    21   Class org/springframework/ldap/BadLdapGrammarException

  public java.lang.Object remove(int) throws javax.naming.InvalidNameException;
    Code:
       0: aload_0
       1: getfield      #4                  // Field names:Ljava/util/List;
       4: iload_1
       5: invokeinterface #70,  2           // InterfaceMethod java/util/List.remove:(I)Ljava/lang/Object;
      10: checkcast     #12                 // class org/springframework/ldap/core/LdapRdn
      13: astore_2
      14: aload_2
      15: invokevirtual #59                 // Method org/springframework/ldap/core/LdapRdn.getLdapEncoded:()Ljava/lang/String;
      18: areturn

  public org.springframework.ldap.core.LdapRdn removeLast();
    Code:
       0: aload_0
       1: getfield      #4                  // Field names:Ljava/util/List;
       4: aload_0
       5: getfield      #4                  // Field names:Ljava/util/List;
       8: invokeinterface #52,  1           // InterfaceMethod java/util/List.size:()I
      13: iconst_1
      14: isub
      15: invokeinterface #70,  2           // InterfaceMethod java/util/List.remove:(I)Ljava/lang/Object;
      20: checkcast     #12                 // class org/springframework/ldap/core/LdapRdn
      23: areturn

  public void add(java.lang.String, java.lang.String);
    Code:
       0: aload_0
       1: getfield      #4                  // Field names:Ljava/util/List;
       4: new           #12                 // class org/springframework/ldap/core/LdapRdn
       7: dup
       8: aload_1
       9: aload_2
      10: invokespecial #104                // Method org/springframework/ldap/core/LdapRdn."<init>":(Ljava/lang/String;Ljava/lang/String;)V
      13: invokeinterface #15,  2           // InterfaceMethod java/util/List.add:(Ljava/lang/Object;)Z
      18: pop
      19: return

  public void add(org.springframework.ldap.core.LdapRdn);
    Code:
       0: aload_0
       1: getfield      #4                  // Field names:Ljava/util/List;
       4: aload_1
       5: invokeinterface #15,  2           // InterfaceMethod java/util/List.add:(Ljava/lang/Object;)Z
      10: pop
      11: return

  public void add(int, org.springframework.ldap.core.LdapRdn);
    Code:
       0: aload_0
       1: getfield      #4                  // Field names:Ljava/util/List;
       4: iload_1
       5: aload_2
       6: invokeinterface #69,  3           // InterfaceMethod java/util/List.add:(ILjava/lang/Object;)V
      11: return

  public org.springframework.ldap.core.DistinguishedName immutableDistinguishedName();
    Code:
       0: new           #105                // class java/util/ArrayList
       3: dup
       4: aload_0
       5: getfield      #4                  // Field names:Ljava/util/List;
       8: invokeinterface #52,  1           // InterfaceMethod java/util/List.size:()I
      13: invokespecial #106                // Method java/util/ArrayList."<init>":(I)V
      16: astore_1
      17: aload_0
      18: getfield      #4                  // Field names:Ljava/util/List;
      21: invokeinterface #34,  1           // InterfaceMethod java/util/List.iterator:()Ljava/util/Iterator;
      26: astore_2
      27: aload_2
      28: invokeinterface #35,  1           // InterfaceMethod java/util/Iterator.hasNext:()Z
      33: ifeq          60
      36: aload_2
      37: invokeinterface #36,  1           // InterfaceMethod java/util/Iterator.next:()Ljava/lang/Object;
      42: checkcast     #12                 // class org/springframework/ldap/core/LdapRdn
      45: astore_3
      46: aload_1
      47: aload_3
      48: invokevirtual #107                // Method org/springframework/ldap/core/LdapRdn.immutableLdapRdn:()Lorg/springframework/ldap/core/LdapRdn;
      51: invokeinterface #15,  2           // InterfaceMethod java/util/List.add:(Ljava/lang/Object;)Z
      56: pop
      57: goto          27
      60: new           #29                 // class org/springframework/ldap/core/DistinguishedName
      63: dup
      64: aload_1
      65: invokestatic  #108                // Method java/util/Collections.unmodifiableList:(Ljava/util/List;)Ljava/util/List;
      68: invokespecial #91                 // Method "<init>":(Ljava/util/List;)V
      71: areturn

  public static final org.springframework.ldap.core.DistinguishedName immutableDistinguishedName(java.lang.String);
    Code:
       0: new           #29                 // class org/springframework/ldap/core/DistinguishedName
       3: dup
       4: aload_0
       5: invokespecial #109                // Method "<init>":(Ljava/lang/String;)V
       8: invokevirtual #110                // Method immutableDistinguishedName:()Lorg/springframework/ldap/core/DistinguishedName;
      11: areturn

  static {};
    Code:
       0: ldc           #29                 // class org/springframework/ldap/core/DistinguishedName
       2: invokestatic  #111                // Method org/slf4j/LoggerFactory.getLogger:(Ljava/lang/Class;)Lorg/slf4j/Logger;
       5: putstatic     #76                 // Field LOG:Lorg/slf4j/Logger;
       8: new           #29                 // class org/springframework/ldap/core/DistinguishedName
      11: dup
      12: getstatic     #112                // Field java/util/Collections.EMPTY_LIST:Ljava/util/List;
      15: invokespecial #91                 // Method "<init>":(Ljava/util/List;)V
      18: putstatic     #113                // Field EMPTY_PATH:Lorg/springframework/ldap/core/DistinguishedName;
      21: return
}
