Compiled from "NotificationReceiverHandler.java"
public class io.undertow.security.handlers.NotificationReceiverHandler implements io.undertow.server.HttpHandler {
  private final io.undertow.server.HttpHandler next;

  private final io.undertow.security.api.NotificationReceiver[] receivers;

  public io.undertow.security.handlers.NotificationReceiverHandler(io.undertow.server.HttpHandler, java.util.Collection<io.undertow.security.api.NotificationReceiver>);
    Code:
       0: aload_0
       1: invokespecial #1                  // Method java/lang/Object."<init>":()V
       4: aload_0
       5: aload_1
       6: putfield      #2                  // Field next:Lio/undertow/server/HttpHandler;
       9: aload_0
      10: aload_2
      11: aload_2
      12: invokeinterface #3,  1            // InterfaceMethod java/util/Collection.size:()I
      17: anewarray     #4                  // class io/undertow/security/api/NotificationReceiver
      20: invokeinterface #5,  2            // InterfaceMethod java/util/Collection.toArray:([Ljava/lang/Object;)[Ljava/lang/Object;
      25: checkcast     #6                  // class "[Lio/undertow/security/api/NotificationReceiver;"
      28: putfield      #7                  // Field receivers:[Lio/undertow/security/api/NotificationReceiver;
      31: return

  public void handleRequest(io.undertow.server.HttpServerExchange) throws java.lang.Exception;
    Code:
       0: aload_1
       1: invokevirtual #8                  // Method io/undertow/server/HttpServerExchange.getSecurityContext:()Lio/undertow/security/api/SecurityContext;
       4: astore_2
       5: iconst_0
       6: istore_3
       7: iload_3
       8: aload_0
       9: getfield      #7                  // Field receivers:[Lio/undertow/security/api/NotificationReceiver;
      12: arraylength
      13: if_icmpge     34
      16: aload_2
      17: aload_0
      18: getfield      #7                  // Field receivers:[Lio/undertow/security/api/NotificationReceiver;
      21: iload_3
      22: aaload
      23: invokeinterface #9,  2            // InterfaceMethod io/undertow/security/api/SecurityContext.registerNotificationReceiver:(Lio/undertow/security/api/NotificationReceiver;)V
      28: iinc          3, 1
      31: goto          7
      34: aload_0
      35: getfield      #2                  // Field next:Lio/undertow/server/HttpHandler;
      38: aload_1
      39: invokeinterface #10,  2           // InterfaceMethod io/undertow/server/HttpHandler.handleRequest:(Lio/undertow/server/HttpServerExchange;)V
      44: return
}
