Compiled from "EventFiringWebDriver.java"
class org.openqa.selenium.support.events.EventFiringWebDriver$EventFiringTimeouts implements org.openqa.selenium.WebDriver$Timeouts {
  private final org.openqa.selenium.WebDriver$Timeouts timeouts;

  final org.openqa.selenium.support.events.EventFiringWebDriver this$0;

  org.openqa.selenium.support.events.EventFiringWebDriver$EventFiringTimeouts(org.openqa.selenium.support.events.EventFiringWebDriver, org.openqa.selenium.WebDriver$Timeouts);
    Code:
       0: aload_0
       1: aload_1
       2: putfield      #1                  // Field this$0:Lorg/openqa/selenium/support/events/EventFiringWebDriver;
       5: aload_0
       6: invokespecial #2                  // Method java/lang/Object."<init>":()V
       9: aload_0
      10: aload_2
      11: putfield      #3                  // Field timeouts:Lorg/openqa/selenium/WebDriver$Timeouts;
      14: return

  public org.openqa.selenium.WebDriver$Timeouts implicitlyWait(long, java.util.concurrent.TimeUnit);
    Code:
       0: aload_0
       1: getfield      #3                  // Field timeouts:Lorg/openqa/selenium/WebDriver$Timeouts;
       4: lload_1
       5: aload_3
       6: invokeinterface #4,  4            // InterfaceMethod org/openqa/selenium/WebDriver$Timeouts.implicitlyWait:(JLjava/util/concurrent/TimeUnit;)Lorg/openqa/selenium/WebDriver$Timeouts;
      11: pop
      12: aload_0
      13: areturn

  public org.openqa.selenium.WebDriver$Timeouts setScriptTimeout(long, java.util.concurrent.TimeUnit);
    Code:
       0: aload_0
       1: getfield      #3                  // Field timeouts:Lorg/openqa/selenium/WebDriver$Timeouts;
       4: lload_1
       5: aload_3
       6: invokeinterface #5,  4            // InterfaceMethod org/openqa/selenium/WebDriver$Timeouts.setScriptTimeout:(JLjava/util/concurrent/TimeUnit;)Lorg/openqa/selenium/WebDriver$Timeouts;
      11: pop
      12: aload_0
      13: areturn

  public org.openqa.selenium.WebDriver$Timeouts pageLoadTimeout(long, java.util.concurrent.TimeUnit);
    Code:
       0: aload_0
       1: getfield      #3                  // Field timeouts:Lorg/openqa/selenium/WebDriver$Timeouts;
       4: lload_1
       5: aload_3
       6: invokeinterface #6,  4            // InterfaceMethod org/openqa/selenium/WebDriver$Timeouts.pageLoadTimeout:(JLjava/util/concurrent/TimeUnit;)Lorg/openqa/selenium/WebDriver$Timeouts;
      11: pop
      12: aload_0
      13: areturn
}
