Compiled from "BufferedHttpEntity.java"
public class org.apache.http.entity.BufferedHttpEntity extends org.apache.http.entity.HttpEntityWrapper {
  private final byte[] buffer;

  public org.apache.http.entity.BufferedHttpEntity(org.apache.http.HttpEntity) throws java.io.IOException;
    Code:
       0: aload_0
       1: aload_1
       2: invokespecial #1                  // Method org/apache/http/entity/HttpEntityWrapper."<init>":(Lorg/apache/http/HttpEntity;)V
       5: aload_1
       6: invokeinterface #2,  1            // InterfaceMethod org/apache/http/HttpEntity.isRepeatable:()Z
      11: ifeq          25
      14: aload_1
      15: invokeinterface #3,  1            // InterfaceMethod org/apache/http/HttpEntity.getContentLength:()J
      20: lconst_0
      21: lcmp
      22: ifge          36
      25: aload_0
      26: aload_1
      27: invokestatic  #4                  // Method org/apache/http/util/EntityUtils.toByteArray:(Lorg/apache/http/HttpEntity;)[B
      30: putfield      #5                  // Field buffer:[B
      33: goto          41
      36: aload_0
      37: aconst_null
      38: putfield      #5                  // Field buffer:[B
      41: return

  public long getContentLength();
    Code:
       0: aload_0
       1: getfield      #5                  // Field buffer:[B
       4: ifnull        14
       7: aload_0
       8: getfield      #5                  // Field buffer:[B
      11: arraylength
      12: i2l
      13: lreturn
      14: aload_0
      15: getfield      #6                  // Field wrappedEntity:Lorg/apache/http/HttpEntity;
      18: invokeinterface #3,  1            // InterfaceMethod org/apache/http/HttpEntity.getContentLength:()J
      23: lreturn

  public java.io.InputStream getContent() throws java.io.IOException;
    Code:
       0: aload_0
       1: getfield      #5                  // Field buffer:[B
       4: ifnull        19
       7: new           #7                  // class java/io/ByteArrayInputStream
      10: dup
      11: aload_0
      12: getfield      #5                  // Field buffer:[B
      15: invokespecial #8                  // Method java/io/ByteArrayInputStream."<init>":([B)V
      18: areturn
      19: aload_0
      20: getfield      #6                  // Field wrappedEntity:Lorg/apache/http/HttpEntity;
      23: invokeinterface #9,  1            // InterfaceMethod org/apache/http/HttpEntity.getContent:()Ljava/io/InputStream;
      28: areturn

  public boolean isChunked();
    Code:
       0: aload_0
       1: getfield      #5                  // Field buffer:[B
       4: ifnonnull     23
       7: aload_0
       8: getfield      #6                  // Field wrappedEntity:Lorg/apache/http/HttpEntity;
      11: invokeinterface #10,  1           // InterfaceMethod org/apache/http/HttpEntity.isChunked:()Z
      16: ifeq          23
      19: iconst_1
      20: goto          24
      23: iconst_0
      24: ireturn

  public boolean isRepeatable();
    Code:
       0: iconst_1
       1: ireturn

  public void writeTo(java.io.OutputStream) throws java.io.IOException;
    Code:
       0: aload_1
       1: ifnonnull     14
       4: new           #11                 // class java/lang/IllegalArgumentException
       7: dup
       8: ldc           #12                 // String Output stream may not be null
      10: invokespecial #13                 // Method java/lang/IllegalArgumentException."<init>":(Ljava/lang/String;)V
      13: athrow
      14: aload_0
      15: getfield      #5                  // Field buffer:[B
      18: ifnull        32
      21: aload_1
      22: aload_0
      23: getfield      #5                  // Field buffer:[B
      26: invokevirtual #14                 // Method java/io/OutputStream.write:([B)V
      29: goto          42
      32: aload_0
      33: getfield      #6                  // Field wrappedEntity:Lorg/apache/http/HttpEntity;
      36: aload_1
      37: invokeinterface #15,  2           // InterfaceMethod org/apache/http/HttpEntity.writeTo:(Ljava/io/OutputStream;)V
      42: return

  public boolean isStreaming();
    Code:
       0: aload_0
       1: getfield      #5                  // Field buffer:[B
       4: ifnonnull     23
       7: aload_0
       8: getfield      #6                  // Field wrappedEntity:Lorg/apache/http/HttpEntity;
      11: invokeinterface #16,  1           // InterfaceMethod org/apache/http/HttpEntity.isStreaming:()Z
      16: ifeq          23
      19: iconst_1
      20: goto          24
      23: iconst_0
      24: ireturn
}
