Compiled from "HeaderProcessor.java"
public final class org.elasticsearch.hadoop.rest.HeaderProcessor {
  private static final org.apache.commons.logging.Log LOG;

  private final java.util.List<org.elasticsearch.hadoop.thirdparty.apache.commons.httpclient.Header> headers;

  public org.elasticsearch.hadoop.rest.HeaderProcessor(org.elasticsearch.hadoop.cfg.Settings);
    Code:
       0: aload_0
       1: invokespecial #3                  // Method java/lang/Object."<init>":()V
       4: new           #9                  // class java/util/HashMap
       7: dup
       8: invokespecial #11                 // Method java/util/HashMap."<init>":()V
      11: astore_2
      12: aload_1
      13: invokevirtual #12                 // Method org/elasticsearch/hadoop/cfg/Settings.asProperties:()Ljava/util/Properties;
      16: invokevirtual #18                 // Method java/util/Properties.entrySet:()Ljava/util/Set;
      19: invokeinterface #24,  1           // InterfaceMethod java/util/Set.iterator:()Ljava/util/Iterator;
      24: astore_3
      25: aload_3
      26: invokeinterface #30,  1           // InterfaceMethod java/util/Iterator.hasNext:()Z
      31: ifeq          117
      34: aload_3
      35: invokeinterface #36,  1           // InterfaceMethod java/util/Iterator.next:()Ljava/lang/Object;
      40: checkcast     #40                 // class java/util/Map$Entry
      43: astore        4
      45: aload         4
      47: invokeinterface #42,  1           // InterfaceMethod java/util/Map$Entry.getKey:()Ljava/lang/Object;
      52: invokevirtual #45                 // Method java/lang/Object.toString:()Ljava/lang/String;
      55: astore        5
      57: aload         5
      59: ldc           #49                 // String es.net.http.header.
      61: invokevirtual #51                 // Method java/lang/String.startsWith:(Ljava/lang/String;)Z
      64: ifeq          114
      67: aload         5
      69: ldc           #49                 // String es.net.http.header.
      71: invokevirtual #57                 // Method java/lang/String.length:()I
      74: invokevirtual #61                 // Method java/lang/String.substring:(I)Ljava/lang/String;
      77: astore        6
      79: aload_0
      80: aload         6
      82: aload         4
      84: invokespecial #65                 // Method validateName:(Ljava/lang/String;Ljava/util/Map$Entry;)V
      87: aload_0
      88: aload         6
      90: aload_2
      91: invokespecial #71                 // Method ensureNotReserved:(Ljava/lang/String;Ljava/util/Map;)V
      94: aload_2
      95: aload         6
      97: aload_0
      98: aload         4
     100: invokeinterface #75,  1           // InterfaceMethod java/util/Map$Entry.getValue:()Ljava/lang/Object;
     105: invokespecial #78                 // Method extractHeaderValue:(Ljava/lang/Object;)Ljava/lang/String;
     108: invokeinterface #82,  3           // InterfaceMethod java/util/Map.put:(Ljava/lang/Object;Ljava/lang/Object;)Ljava/lang/Object;
     113: pop
     114: goto          25
     117: aload_0
     118: new           #88                 // class java/util/ArrayList
     121: dup
     122: aload_2
     123: invokeinterface #90,  1           // InterfaceMethod java/util/Map.keySet:()Ljava/util/Set;
     128: invokeinterface #93,  1           // InterfaceMethod java/util/Set.size:()I
     133: invokespecial #96                 // Method java/util/ArrayList."<init>":(I)V
     136: putfield      #99                 // Field headers:Ljava/util/List;
     139: aload_2
     140: invokeinterface #103,  1          // InterfaceMethod java/util/Map.entrySet:()Ljava/util/Set;
     145: invokeinterface #24,  1           // InterfaceMethod java/util/Set.iterator:()Ljava/util/Iterator;
     150: astore_3
     151: aload_3
     152: invokeinterface #30,  1           // InterfaceMethod java/util/Iterator.hasNext:()Z
     157: ifeq          211
     160: aload_3
     161: invokeinterface #36,  1           // InterfaceMethod java/util/Iterator.next:()Ljava/lang/Object;
     166: checkcast     #40                 // class java/util/Map$Entry
     169: astore        4
     171: aload_0
     172: getfield      #99                 // Field headers:Ljava/util/List;
     175: new           #104                // class org/elasticsearch/hadoop/thirdparty/apache/commons/httpclient/Header
     178: dup
     179: aload         4
     181: invokeinterface #42,  1           // InterfaceMethod java/util/Map$Entry.getKey:()Ljava/lang/Object;
     186: checkcast     #52                 // class java/lang/String
     189: aload         4
     191: invokeinterface #75,  1           // InterfaceMethod java/util/Map$Entry.getValue:()Ljava/lang/Object;
     196: checkcast     #52                 // class java/lang/String
     199: invokespecial #106                // Method org/elasticsearch/hadoop/thirdparty/apache/commons/httpclient/Header."<init>":(Ljava/lang/String;Ljava/lang/String;)V
     202: invokeinterface #109,  2          // InterfaceMethod java/util/List.add:(Ljava/lang/Object;)Z
     207: pop
     208: goto          151
     211: invokestatic  #115                // Method org/elasticsearch/hadoop/rest/HeaderProcessor$ReservedHeaders.values:()[Lorg/elasticsearch/hadoop/rest/HeaderProcessor$ReservedHeaders;
     214: astore_3
     215: aload_3
     216: arraylength
     217: istore        4
     219: iconst_0
     220: istore        5
     222: iload         5
     224: iload         4
     226: if_icmpge     268
     229: aload_3
     230: iload         5
     232: aaload
     233: astore        6
     235: aload_0
     236: getfield      #99                 // Field headers:Ljava/util/List;
     239: new           #104                // class org/elasticsearch/hadoop/thirdparty/apache/commons/httpclient/Header
     242: dup
     243: aload         6
     245: invokevirtual #121                // Method org/elasticsearch/hadoop/rest/HeaderProcessor$ReservedHeaders.getName:()Ljava/lang/String;
     248: aload         6
     250: invokevirtual #124                // Method org/elasticsearch/hadoop/rest/HeaderProcessor$ReservedHeaders.getDefaultValue:()Ljava/lang/String;
     253: invokespecial #106                // Method org/elasticsearch/hadoop/thirdparty/apache/commons/httpclient/Header."<init>":(Ljava/lang/String;Ljava/lang/String;)V
     256: invokeinterface #109,  2          // InterfaceMethod java/util/List.add:(Ljava/lang/Object;)Z
     261: pop
     262: iinc          5, 1
     265: goto          222
     268: return

  private void validateName(java.lang.String, java.util.Map$Entry<java.lang.Object, java.lang.Object>);
    Code:
       0: aload_1
       1: invokestatic  #127                // Method org/elasticsearch/hadoop/util/StringUtils.hasText:(Ljava/lang/CharSequence;)Z
       4: ifne          42
       7: new           #133                // class org/elasticsearch/hadoop/EsHadoopIllegalArgumentException
      10: dup
      11: ldc           #135                // String Found configuration entry denoting a header prefix, but no header was given after the prefix. Please add a header name for the configuration entry : [%s] = [%s]
      13: iconst_2
      14: anewarray     #4                  // class java/lang/Object
      17: dup
      18: iconst_0
      19: aload_2
      20: invokeinterface #42,  1           // InterfaceMethod java/util/Map$Entry.getKey:()Ljava/lang/Object;
      25: aastore
      26: dup
      27: iconst_1
      28: aload_2
      29: invokeinterface #75,  1           // InterfaceMethod java/util/Map$Entry.getValue:()Ljava/lang/Object;
      34: aastore
      35: invokestatic  #137                // Method java/lang/String.format:(Ljava/lang/String;[Ljava/lang/Object;)Ljava/lang/String;
      38: invokespecial #141                // Method org/elasticsearch/hadoop/EsHadoopIllegalArgumentException."<init>":(Ljava/lang/String;)V
      41: athrow
      42: return

  private void ensureNotReserved(java.lang.String, java.util.Map<java.lang.String, java.lang.String>);
    Code:
       0: aload_2
       1: aload_1
       2: invokeinterface #144,  2          // InterfaceMethod java/util/Map.containsKey:(Ljava/lang/Object;)Z
       7: ifeq          41
      10: new           #133                // class org/elasticsearch/hadoop/EsHadoopIllegalArgumentException
      13: dup
      14: ldc           #147                // String Could not set header [%s]: Header value [%s] is already present from a previous setting. Please submit multiple header values as a comma (,) separated list on the propertyvalue.
      16: iconst_2
      17: anewarray     #4                  // class java/lang/Object
      20: dup
      21: iconst_0
      22: aload_1
      23: aastore
      24: dup
      25: iconst_1
      26: aload_2
      27: aload_1
      28: invokeinterface #149,  2          // InterfaceMethod java/util/Map.get:(Ljava/lang/Object;)Ljava/lang/Object;
      33: aastore
      34: invokestatic  #137                // Method java/lang/String.format:(Ljava/lang/String;[Ljava/lang/Object;)Ljava/lang/String;
      37: invokespecial #141                // Method org/elasticsearch/hadoop/EsHadoopIllegalArgumentException."<init>":(Ljava/lang/String;)V
      40: athrow
      41: invokestatic  #153                // Method org/elasticsearch/hadoop/rest/HeaderProcessor$ReservedHeaders.byName:()Ljava/util/Map;
      44: aload_1
      45: invokeinterface #144,  2          // InterfaceMethod java/util/Map.containsKey:(Ljava/lang/Object;)Z
      50: ifeq          92
      53: new           #133                // class org/elasticsearch/hadoop/EsHadoopIllegalArgumentException
      56: dup
      57: ldc           #157                // String Could not set header [%s]: This header is a reserved header. Reason: %s.
      59: iconst_2
      60: anewarray     #4                  // class java/lang/Object
      63: dup
      64: iconst_0
      65: aload_1
      66: aastore
      67: dup
      68: iconst_1
      69: invokestatic  #153                // Method org/elasticsearch/hadoop/rest/HeaderProcessor$ReservedHeaders.byName:()Ljava/util/Map;
      72: aload_1
      73: invokeinterface #149,  2          // InterfaceMethod java/util/Map.get:(Ljava/lang/Object;)Ljava/lang/Object;
      78: checkcast     #116                // class org/elasticsearch/hadoop/rest/HeaderProcessor$ReservedHeaders
      81: invokevirtual #159                // Method org/elasticsearch/hadoop/rest/HeaderProcessor$ReservedHeaders.getReasonReserved:()Ljava/lang/String;
      84: aastore
      85: invokestatic  #137                // Method java/lang/String.format:(Ljava/lang/String;[Ljava/lang/Object;)Ljava/lang/String;
      88: invokespecial #141                // Method org/elasticsearch/hadoop/EsHadoopIllegalArgumentException."<init>":(Ljava/lang/String;)V
      91: athrow
      92: return

  private java.lang.String extractHeaderValue(java.lang.Object);
    Code:
       0: aload_1
       1: instanceof    #162                // class "[Ljava/lang/Object;"
       4: ifeq          79
       7: new           #164                // class java/lang/StringBuilder
      10: dup
      11: invokespecial #166                // Method java/lang/StringBuilder."<init>":()V
      14: astore_3
      15: aload_1
      16: checkcast     #162                // class "[Ljava/lang/Object;"
      19: astore        4
      21: aload         4
      23: arraylength
      24: istore        5
      26: iconst_0
      27: istore        6
      29: iload         6
      31: iload         5
      33: if_icmpge     64
      36: aload         4
      38: iload         6
      40: aaload
      41: astore        7
      43: aload_3
      44: aload         7
      46: invokevirtual #45                 // Method java/lang/Object.toString:()Ljava/lang/String;
      49: invokevirtual #167                // Method java/lang/StringBuilder.append:(Ljava/lang/String;)Ljava/lang/StringBuilder;
      52: bipush        44
      54: invokevirtual #171                // Method java/lang/StringBuilder.append:(C)Ljava/lang/StringBuilder;
      57: pop
      58: iinc          6, 1
      61: goto          29
      64: aload_3
      65: iconst_0
      66: aload_3
      67: invokevirtual #174                // Method java/lang/StringBuilder.length:()I
      70: iconst_1
      71: isub
      72: invokevirtual #175                // Method java/lang/StringBuilder.substring:(II)Ljava/lang/String;
      75: astore_2
      76: goto          84
      79: aload_1
      80: invokevirtual #45                 // Method java/lang/Object.toString:()Ljava/lang/String;
      83: astore_2
      84: aload_2
      85: areturn

  public org.elasticsearch.hadoop.thirdparty.apache.commons.httpclient.HttpMethod applyTo(org.elasticsearch.hadoop.thirdparty.apache.commons.httpclient.HttpMethod);
    Code:
       0: aload_0
       1: getfield      #99                 // Field headers:Ljava/util/List;
       4: invokeinterface #178,  1          // InterfaceMethod java/util/List.iterator:()Ljava/util/Iterator;
       9: astore_2
      10: aload_2
      11: invokeinterface #30,  1           // InterfaceMethod java/util/Iterator.hasNext:()Z
      16: ifeq          39
      19: aload_2
      20: invokeinterface #36,  1           // InterfaceMethod java/util/Iterator.next:()Ljava/lang/Object;
      25: checkcast     #104                // class org/elasticsearch/hadoop/thirdparty/apache/commons/httpclient/Header
      28: astore_3
      29: aload_1
      30: aload_3
      31: invokeinterface #179,  2          // InterfaceMethod org/elasticsearch/hadoop/thirdparty/apache/commons/httpclient/HttpMethod.setRequestHeader:(Lorg/elasticsearch/hadoop/thirdparty/apache/commons/httpclient/Header;)V
      36: goto          10
      39: getstatic     #185                // Field LOG:Lorg/apache/commons/logging/Log;
      42: invokeinterface #189,  1          // InterfaceMethod org/apache/commons/logging/Log.isDebugEnabled:()Z
      47: ifeq          85
      50: getstatic     #185                // Field LOG:Lorg/apache/commons/logging/Log;
      53: new           #164                // class java/lang/StringBuilder
      56: dup
      57: invokespecial #166                // Method java/lang/StringBuilder."<init>":()V
      60: ldc           #194                // String Added HTTP Headers to method:
      62: invokevirtual #167                // Method java/lang/StringBuilder.append:(Ljava/lang/String;)Ljava/lang/StringBuilder;
      65: aload_1
      66: invokeinterface #196,  1          // InterfaceMethod org/elasticsearch/hadoop/thirdparty/apache/commons/httpclient/HttpMethod.getRequestHeaders:()[Lorg/elasticsearch/hadoop/thirdparty/apache/commons/httpclient/Header;
      71: invokestatic  #200                // Method java/util/Arrays.toString:([Ljava/lang/Object;)Ljava/lang/String;
      74: invokevirtual #167                // Method java/lang/StringBuilder.append:(Ljava/lang/String;)Ljava/lang/StringBuilder;
      77: invokevirtual #205                // Method java/lang/StringBuilder.toString:()Ljava/lang/String;
      80: invokeinterface #206,  2          // InterfaceMethod org/apache/commons/logging/Log.debug:(Ljava/lang/Object;)V
      85: aload_1
      86: areturn

  static {};
    Code:
       0: ldc           #66                 // class org/elasticsearch/hadoop/rest/HeaderProcessor
       2: invokestatic  #210                // Method org/apache/commons/logging/LogFactory.getLog:(Ljava/lang/Class;)Lorg/apache/commons/logging/Log;
       5: putstatic     #185                // Field LOG:Lorg/apache/commons/logging/Log;
       8: return
}
