Compiled from "RestClient.java"
public final class org.elasticsearch.hadoop.rest.RestClient$Health extends java.lang.Enum<org.elasticsearch.hadoop.rest.RestClient$Health> {
  public static final org.elasticsearch.hadoop.rest.RestClient$Health RED;

  public static final org.elasticsearch.hadoop.rest.RestClient$Health YELLOW;

  public static final org.elasticsearch.hadoop.rest.RestClient$Health GREEN;

  private static final org.elasticsearch.hadoop.rest.RestClient$Health[] $VALUES;

  public static org.elasticsearch.hadoop.rest.RestClient$Health[] values();
    Code:
       0: getstatic     #13                 // Field $VALUES:[Lorg/elasticsearch/hadoop/rest/RestClient$Health;
       3: invokevirtual #17                 // Method "[Lorg/elasticsearch/hadoop/rest/RestClient$Health;".clone:()Ljava/lang/Object;
       6: checkcast     #18                 // class "[Lorg/elasticsearch/hadoop/rest/RestClient$Health;"
       9: areturn

  public static org.elasticsearch.hadoop.rest.RestClient$Health valueOf(java.lang.String);
    Code:
       0: ldc           #1                  // class org/elasticsearch/hadoop/rest/RestClient$Health
       2: aload_0
       3: invokestatic  #22                 // Method java/lang/Enum.valueOf:(Ljava/lang/Class;Ljava/lang/String;)Ljava/lang/Enum;
       6: checkcast     #1                  // class org/elasticsearch/hadoop/rest/RestClient$Health
       9: areturn

  private org.elasticsearch.hadoop.rest.RestClient$Health();
    Code:
       0: aload_0
       1: aload_1
       2: iload_2
       3: invokespecial #28                 // Method java/lang/Enum."<init>":(Ljava/lang/String;I)V
       6: return

  private static org.elasticsearch.hadoop.rest.RestClient$Health[] $values();
    Code:
       0: iconst_3
       1: anewarray     #1                  // class org/elasticsearch/hadoop/rest/RestClient$Health
       4: dup
       5: iconst_0
       6: getstatic     #3                  // Field RED:Lorg/elasticsearch/hadoop/rest/RestClient$Health;
       9: aastore
      10: dup
      11: iconst_1
      12: getstatic     #7                  // Field YELLOW:Lorg/elasticsearch/hadoop/rest/RestClient$Health;
      15: aastore
      16: dup
      17: iconst_2
      18: getstatic     #10                 // Field GREEN:Lorg/elasticsearch/hadoop/rest/RestClient$Health;
      21: aastore
      22: areturn

  static {};
    Code:
       0: new           #1                  // class org/elasticsearch/hadoop/rest/RestClient$Health
       3: dup
       4: ldc           #32                 // String RED
       6: iconst_0
       7: invokespecial #33                 // Method "<init>":(Ljava/lang/String;I)V
      10: putstatic     #3                  // Field RED:Lorg/elasticsearch/hadoop/rest/RestClient$Health;
      13: new           #1                  // class org/elasticsearch/hadoop/rest/RestClient$Health
      16: dup
      17: ldc           #34                 // String YELLOW
      19: iconst_1
      20: invokespecial #33                 // Method "<init>":(Ljava/lang/String;I)V
      23: putstatic     #7                  // Field YELLOW:Lorg/elasticsearch/hadoop/rest/RestClient$Health;
      26: new           #1                  // class org/elasticsearch/hadoop/rest/RestClient$Health
      29: dup
      30: ldc           #35                 // String GREEN
      32: iconst_2
      33: invokespecial #33                 // Method "<init>":(Ljava/lang/String;I)V
      36: putstatic     #10                 // Field GREEN:Lorg/elasticsearch/hadoop/rest/RestClient$Health;
      39: invokestatic  #36                 // Method $values:()[Lorg/elasticsearch/hadoop/rest/RestClient$Health;
      42: putstatic     #13                 // Field $VALUES:[Lorg/elasticsearch/hadoop/rest/RestClient$Health;
      45: return
}
