Compiled from "SearchRequestBuilder.java"
public class org.elasticsearch.hadoop.rest.SearchRequestBuilder {
  private final org.elasticsearch.hadoop.util.EsMajorVersion version;

  private final boolean includeVersion;

  private org.elasticsearch.hadoop.util.unit.TimeValue scroll;

  private long size;

  private long limit;

  private java.lang.String indices;

  private java.lang.String types;

  private java.lang.String shard;

  private java.lang.String fields;

  private org.elasticsearch.hadoop.rest.query.QueryBuilder query;

  private final java.util.List<org.elasticsearch.hadoop.rest.query.QueryBuilder> filters;

  private java.lang.String routing;

  private org.elasticsearch.hadoop.rest.SearchRequestBuilder$Slice slice;

  private boolean local;

  private java.lang.String preference;

  private boolean excludeSource;

  private boolean readMetadata;

  public org.elasticsearch.hadoop.rest.SearchRequestBuilder(org.elasticsearch.hadoop.util.EsMajorVersion, boolean);
    Code:
       0: aload_0
       1: invokespecial #1                  // Method java/lang/Object."<init>":()V
       4: aload_0
       5: ldc2_w        #7                  // long 10l
       8: invokestatic  #9                  // Method org/elasticsearch/hadoop/util/unit/TimeValue.timeValueMinutes:(J)Lorg/elasticsearch/hadoop/util/unit/TimeValue;
      11: putfield      #15                 // Field scroll:Lorg/elasticsearch/hadoop/util/unit/TimeValue;
      14: aload_0
      15: ldc2_w        #21                 // long 50l
      18: putfield      #23                 // Field size:J
      21: aload_0
      22: ldc2_w        #27                 // long -1l
      25: putfield      #29                 // Field limit:J
      28: aload_0
      29: new           #32                 // class java/util/ArrayList
      32: dup
      33: invokespecial #34                 // Method java/util/ArrayList."<init>":()V
      36: putfield      #35                 // Field filters:Ljava/util/List;
      39: aload_0
      40: iconst_0
      41: putfield      #39                 // Field local:Z
      44: aload_0
      45: ldc           #43                 // String
      47: putfield      #45                 // Field preference:Ljava/lang/String;
      50: aload_0
      51: iconst_0
      52: putfield      #49                 // Field excludeSource:Z
      55: aload_0
      56: iconst_0
      57: putfield      #52                 // Field readMetadata:Z
      60: aload_0
      61: aload_1
      62: putfield      #55                 // Field version:Lorg/elasticsearch/hadoop/util/EsMajorVersion;
      65: aload_0
      66: iload_2
      67: putfield      #59                 // Field includeVersion:Z
      70: return

  public boolean isReadMetadata();
    Code:
       0: aload_0
       1: getfield      #52                 // Field readMetadata:Z
       4: ireturn

  public java.lang.String routing();
    Code:
       0: aload_0
       1: getfield      #62                 // Field routing:Ljava/lang/String;
       4: areturn

  public java.util.List<org.elasticsearch.hadoop.rest.query.QueryBuilder> filters();
    Code:
       0: aload_0
       1: getfield      #35                 // Field filters:Ljava/util/List;
       4: areturn

  public org.elasticsearch.hadoop.rest.SearchRequestBuilder resource(org.elasticsearch.hadoop.rest.Resource);
    Code:
       0: aload_0
       1: aload_1
       2: invokevirtual #65                 // Method org/elasticsearch/hadoop/rest/Resource.index:()Ljava/lang/String;
       5: putfield      #71                 // Field indices:Ljava/lang/String;
       8: aload_1
       9: invokevirtual #74                 // Method org/elasticsearch/hadoop/rest/Resource.isTyped:()Z
      12: ifeq          26
      15: aload_0
      16: aload_1
      17: invokevirtual #78                 // Method org/elasticsearch/hadoop/rest/Resource.type:()Ljava/lang/String;
      20: putfield      #81                 // Field types:Ljava/lang/String;
      23: goto          31
      26: aload_0
      27: aconst_null
      28: putfield      #81                 // Field types:Ljava/lang/String;
      31: aload_0
      32: areturn

  public org.elasticsearch.hadoop.rest.SearchRequestBuilder indices(java.lang.String);
    Code:
       0: aload_0
       1: aload_1
       2: putfield      #71                 // Field indices:Ljava/lang/String;
       5: aload_0
       6: areturn

  public org.elasticsearch.hadoop.rest.SearchRequestBuilder query(org.elasticsearch.hadoop.rest.query.QueryBuilder);
    Code:
       0: aload_0
       1: aload_1
       2: putfield      #84                 // Field query:Lorg/elasticsearch/hadoop/rest/query/QueryBuilder;
       5: aload_0
       6: areturn

  public org.elasticsearch.hadoop.rest.query.QueryBuilder query();
    Code:
       0: aload_0
       1: getfield      #84                 // Field query:Lorg/elasticsearch/hadoop/rest/query/QueryBuilder;
       4: areturn

  public org.elasticsearch.hadoop.rest.SearchRequestBuilder size(long);
    Code:
       0: aload_0
       1: lload_1
       2: putfield      #23                 // Field size:J
       5: aload_0
       6: areturn

  public org.elasticsearch.hadoop.rest.SearchRequestBuilder limit(long);
    Code:
       0: aload_0
       1: lload_1
       2: putfield      #29                 // Field limit:J
       5: aload_0
       6: areturn

  public org.elasticsearch.hadoop.rest.SearchRequestBuilder scroll(long);
    Code:
       0: lload_1
       1: lconst_0
       2: lcmp
       3: ifle          10
       6: iconst_1
       7: goto          11
      10: iconst_0
      11: invokestatic  #88                 // Method java/lang/Boolean.valueOf:(Z)Ljava/lang/Boolean;
      14: ldc           #94                 // String Invalid scroll
      16: invokestatic  #96                 // Method org/elasticsearch/hadoop/util/Assert.isTrue:(Ljava/lang/Boolean;Ljava/lang/String;)V
      19: aload_0
      20: lload_1
      21: invokestatic  #102                // Method org/elasticsearch/hadoop/util/unit/TimeValue.timeValueMillis:(J)Lorg/elasticsearch/hadoop/util/unit/TimeValue;
      24: putfield      #15                 // Field scroll:Lorg/elasticsearch/hadoop/util/unit/TimeValue;
      27: aload_0
      28: areturn

  public org.elasticsearch.hadoop.rest.SearchRequestBuilder shard(java.lang.String);
    Code:
       0: aload_1
       1: ldc           #105                // String Invalid shard
       3: invokestatic  #107                // Method org/elasticsearch/hadoop/util/Assert.hasText:(Ljava/lang/CharSequence;Ljava/lang/String;)V
       6: aload_0
       7: aload_1
       8: putfield      #111                // Field shard:Ljava/lang/String;
      11: aload_0
      12: areturn

  public org.elasticsearch.hadoop.rest.SearchRequestBuilder fields(java.lang.String);
    Code:
       0: aload_0
       1: getfield      #49                 // Field excludeSource:Z
       4: invokestatic  #88                 // Method java/lang/Boolean.valueOf:(Z)Ljava/lang/Boolean;
       7: ldc           #114                // String Fields can\'t be requested because _source section is excluded
       9: invokestatic  #116                // Method org/elasticsearch/hadoop/util/Assert.isFalse:(Ljava/lang/Boolean;Ljava/lang/String;)V
      12: aload_0
      13: aload_1
      14: putfield      #119                // Field fields:Ljava/lang/String;
      17: aload_0
      18: areturn

  public org.elasticsearch.hadoop.rest.SearchRequestBuilder filter(org.elasticsearch.hadoop.rest.query.QueryBuilder);
    Code:
       0: aload_0
       1: getfield      #35                 // Field filters:Ljava/util/List;
       4: aload_1
       5: invokeinterface #122,  2          // InterfaceMethod java/util/List.add:(Ljava/lang/Object;)Z
      10: pop
      11: aload_0
      12: areturn

  public org.elasticsearch.hadoop.rest.SearchRequestBuilder filters(java.util.Collection<org.elasticsearch.hadoop.rest.query.QueryBuilder>);
    Code:
       0: aload_0
       1: getfield      #35                 // Field filters:Ljava/util/List;
       4: aload_1
       5: invokeinterface #128,  2          // InterfaceMethod java/util/List.addAll:(Ljava/util/Collection;)Z
      10: pop
      11: aload_0
      12: areturn

  public org.elasticsearch.hadoop.rest.SearchRequestBuilder readMetadata(boolean);
    Code:
       0: aload_0
       1: iload_1
       2: putfield      #52                 // Field readMetadata:Z
       5: aload_0
       6: areturn

  public org.elasticsearch.hadoop.rest.SearchRequestBuilder routing(java.lang.String);
    Code:
       0: aload_0
       1: aload_1
       2: putfield      #62                 // Field routing:Ljava/lang/String;
       5: aload_0
       6: areturn

  public org.elasticsearch.hadoop.rest.SearchRequestBuilder slice(int, int);
    Code:
       0: aload_0
       1: new           #132                // class org/elasticsearch/hadoop/rest/SearchRequestBuilder$Slice
       4: dup
       5: iload_1
       6: iload_2
       7: invokespecial #134                // Method org/elasticsearch/hadoop/rest/SearchRequestBuilder$Slice."<init>":(II)V
      10: putfield      #137                // Field slice:Lorg/elasticsearch/hadoop/rest/SearchRequestBuilder$Slice;
      13: aload_0
      14: areturn

  public org.elasticsearch.hadoop.rest.SearchRequestBuilder local(boolean);
    Code:
       0: aload_0
       1: iload_1
       2: putfield      #39                 // Field local:Z
       5: aload_0
       6: areturn

  public org.elasticsearch.hadoop.rest.SearchRequestBuilder preference(java.lang.String);
    Code:
       0: aload_0
       1: aload_1
       2: putfield      #45                 // Field preference:Ljava/lang/String;
       5: aload_0
       6: areturn

  public org.elasticsearch.hadoop.rest.SearchRequestBuilder excludeSource(boolean);
    Code:
       0: iload_1
       1: ifeq          27
       4: aload_0
       5: getfield      #119                // Field fields:Ljava/lang/String;
       8: ldc           #141                // String _source section can\'t be excluded if fields [%s] are requested
      10: iconst_1
      11: anewarray     #2                  // class java/lang/Object
      14: dup
      15: iconst_0
      16: aload_0
      17: getfield      #119                // Field fields:Ljava/lang/String;
      20: aastore
      21: invokestatic  #143                // Method java/lang/String.format:(Ljava/lang/String;[Ljava/lang/Object;)Ljava/lang/String;
      24: invokestatic  #149                // Method org/elasticsearch/hadoop/util/Assert.hasNoText:(Ljava/lang/CharSequence;Ljava/lang/String;)V
      27: aload_0
      28: iload_1
      29: putfield      #49                 // Field excludeSource:Z
      32: aload_0
      33: areturn

  private java.lang.String assemble();
    Code:
       0: aload_0
       1: getfield      #29                 // Field limit:J
       4: lconst_0
       5: lcmp
       6: ifle          29
       9: aload_0
      10: getfield      #23                 // Field size:J
      13: aload_0
      14: getfield      #29                 // Field limit:J
      17: lcmp
      18: ifle          29
      21: aload_0
      22: aload_0
      23: getfield      #29                 // Field limit:J
      26: putfield      #23                 // Field size:J
      29: new           #152                // class java/util/LinkedHashMap
      32: dup
      33: invokespecial #154                // Method java/util/LinkedHashMap."<init>":()V
      36: astore_1
      37: new           #155                // class java/lang/StringBuilder
      40: dup
      41: invokespecial #157                // Method java/lang/StringBuilder."<init>":()V
      44: astore_2
      45: aload_2
      46: aload_0
      47: getfield      #71                 // Field indices:Ljava/lang/String;
      50: invokevirtual #158                // Method java/lang/StringBuilder.append:(Ljava/lang/String;)Ljava/lang/StringBuilder;
      53: pop
      54: aload_0
      55: getfield      #81                 // Field types:Ljava/lang/String;
      58: invokestatic  #162                // Method org/elasticsearch/hadoop/util/StringUtils.hasLength:(Ljava/lang/CharSequence;)Z
      61: ifeq          80
      64: aload_2
      65: ldc           #168                // String /
      67: invokevirtual #158                // Method java/lang/StringBuilder.append:(Ljava/lang/String;)Ljava/lang/StringBuilder;
      70: pop
      71: aload_2
      72: aload_0
      73: getfield      #81                 // Field types:Ljava/lang/String;
      76: invokevirtual #158                // Method java/lang/StringBuilder.append:(Ljava/lang/String;)Ljava/lang/StringBuilder;
      79: pop
      80: aload_2
      81: ldc           #170                // String /_search?
      83: invokevirtual #158                // Method java/lang/StringBuilder.append:(Ljava/lang/String;)Ljava/lang/StringBuilder;
      86: pop
      87: aload_0
      88: getfield      #55                 // Field version:Lorg/elasticsearch/hadoop/util/EsMajorVersion;
      91: getstatic     #172                // Field org/elasticsearch/hadoop/util/EsMajorVersion.V_5_X:Lorg/elasticsearch/hadoop/util/EsMajorVersion;
      94: invokevirtual #177                // Method org/elasticsearch/hadoop/util/EsMajorVersion.onOrAfter:(Lorg/elasticsearch/hadoop/util/EsMajorVersion;)Z
      97: ifeq          114
     100: aload_1
     101: ldc           #181                // String sort
     103: ldc           #183                // String _doc
     105: invokeinterface #185,  3          // InterfaceMethod java/util/Map.put:(Ljava/lang/Object;Ljava/lang/Object;)Ljava/lang/Object;
     110: pop
     111: goto          125
     114: aload_1
     115: ldc           #191                // String search_type
     117: ldc           #193                // String scan
     119: invokeinterface #185,  3          // InterfaceMethod java/util/Map.put:(Ljava/lang/Object;Ljava/lang/Object;)Ljava/lang/Object;
     124: pop
     125: aload_1
     126: ldc           #195                // String scroll
     128: aload_0
     129: getfield      #15                 // Field scroll:Lorg/elasticsearch/hadoop/util/unit/TimeValue;
     132: invokevirtual #196                // Method org/elasticsearch/hadoop/util/unit/TimeValue.toString:()Ljava/lang/String;
     135: invokestatic  #199                // Method java/lang/String.valueOf:(Ljava/lang/Object;)Ljava/lang/String;
     138: invokeinterface #185,  3          // InterfaceMethod java/util/Map.put:(Ljava/lang/Object;Ljava/lang/Object;)Ljava/lang/Object;
     143: pop
     144: aload_1
     145: ldc           #202                // String size
     147: aload_0
     148: getfield      #23                 // Field size:J
     151: invokestatic  #203                // Method java/lang/String.valueOf:(J)Ljava/lang/String;
     154: invokeinterface #185,  3          // InterfaceMethod java/util/Map.put:(Ljava/lang/Object;Ljava/lang/Object;)Ljava/lang/Object;
     159: pop
     160: aload_0
     161: getfield      #59                 // Field includeVersion:Z
     164: ifeq          178
     167: aload_1
     168: ldc           #206                // String version
     170: ldc           #207                // String true
     172: invokeinterface #185,  3          // InterfaceMethod java/util/Map.put:(Ljava/lang/Object;Ljava/lang/Object;)Ljava/lang/Object;
     177: pop
     178: new           #155                // class java/lang/StringBuilder
     181: dup
     182: invokespecial #157                // Method java/lang/StringBuilder."<init>":()V
     185: astore_3
     186: aload_0
     187: getfield      #111                // Field shard:Ljava/lang/String;
     190: invokestatic  #209                // Method org/elasticsearch/hadoop/util/StringUtils.hasText:(Ljava/lang/CharSequence;)Z
     193: ifeq          212
     196: aload_3
     197: ldc           #211                // String _shards:
     199: invokevirtual #158                // Method java/lang/StringBuilder.append:(Ljava/lang/String;)Ljava/lang/StringBuilder;
     202: pop
     203: aload_3
     204: aload_0
     205: getfield      #111                // Field shard:Ljava/lang/String;
     208: invokevirtual #158                // Method java/lang/StringBuilder.append:(Ljava/lang/String;)Ljava/lang/StringBuilder;
     211: pop
     212: aload_0
     213: getfield      #39                 // Field local:Z
     216: ifne          229
     219: aload_0
     220: getfield      #45                 // Field preference:Ljava/lang/String;
     223: invokestatic  #209                // Method org/elasticsearch/hadoop/util/StringUtils.hasText:(Ljava/lang/CharSequence;)Z
     226: ifeq          295
     229: aload_3
     230: invokevirtual #213                // Method java/lang/StringBuilder.length:()I
     233: ifle          266
     236: aload_0
     237: getfield      #55                 // Field version:Lorg/elasticsearch/hadoop/util/EsMajorVersion;
     240: getstatic     #172                // Field org/elasticsearch/hadoop/util/EsMajorVersion.V_5_X:Lorg/elasticsearch/hadoop/util/EsMajorVersion;
     243: invokevirtual #177                // Method org/elasticsearch/hadoop/util/EsMajorVersion.onOrAfter:(Lorg/elasticsearch/hadoop/util/EsMajorVersion;)Z
     246: ifeq          259
     249: aload_3
     250: ldc           #217                // String |
     252: invokevirtual #158                // Method java/lang/StringBuilder.append:(Ljava/lang/String;)Ljava/lang/StringBuilder;
     255: pop
     256: goto          266
     259: aload_3
     260: ldc           #219                // String ;
     262: invokevirtual #158                // Method java/lang/StringBuilder.append:(Ljava/lang/String;)Ljava/lang/StringBuilder;
     265: pop
     266: aload_0
     267: getfield      #45                 // Field preference:Ljava/lang/String;
     270: invokestatic  #209                // Method org/elasticsearch/hadoop/util/StringUtils.hasText:(Ljava/lang/CharSequence;)Z
     273: ifeq          288
     276: aload_3
     277: aload_0
     278: getfield      #45                 // Field preference:Ljava/lang/String;
     281: invokevirtual #158                // Method java/lang/StringBuilder.append:(Ljava/lang/String;)Ljava/lang/StringBuilder;
     284: pop
     285: goto          295
     288: aload_3
     289: ldc           #221                // String _local
     291: invokevirtual #158                // Method java/lang/StringBuilder.append:(Ljava/lang/String;)Ljava/lang/StringBuilder;
     294: pop
     295: aload_3
     296: invokevirtual #213                // Method java/lang/StringBuilder.length:()I
     299: ifle          318
     302: aload_1
     303: ldc           #223                // String preference
     305: aload_3
     306: invokevirtual #224                // Method java/lang/StringBuilder.toString:()Ljava/lang/String;
     309: invokestatic  #225                // Method org/elasticsearch/hadoop/util/encoding/HttpEncodingTools.encode:(Ljava/lang/String;)Ljava/lang/String;
     312: invokeinterface #185,  3          // InterfaceMethod java/util/Map.put:(Ljava/lang/Object;Ljava/lang/Object;)Ljava/lang/Object;
     317: pop
     318: aload_0
     319: getfield      #62                 // Field routing:Ljava/lang/String;
     322: ifnull        341
     325: aload_1
     326: ldc           #231                // String routing
     328: aload_0
     329: getfield      #62                 // Field routing:Ljava/lang/String;
     332: invokestatic  #225                // Method org/elasticsearch/hadoop/util/encoding/HttpEncodingTools.encode:(Ljava/lang/String;)Ljava/lang/String;
     335: invokeinterface #185,  3          // InterfaceMethod java/util/Map.put:(Ljava/lang/Object;Ljava/lang/Object;)Ljava/lang/Object;
     340: pop
     341: aload_0
     342: getfield      #55                 // Field version:Lorg/elasticsearch/hadoop/util/EsMajorVersion;
     345: getstatic     #232                // Field org/elasticsearch/hadoop/util/EsMajorVersion.V_6_X:Lorg/elasticsearch/hadoop/util/EsMajorVersion;
     348: invokevirtual #177                // Method org/elasticsearch/hadoop/util/EsMajorVersion.onOrAfter:(Lorg/elasticsearch/hadoop/util/EsMajorVersion;)Z
     351: ifeq          365
     354: aload_1
     355: ldc           #235                // String track_total_hits
     357: ldc           #207                // String true
     359: invokeinterface #185,  3          // InterfaceMethod java/util/Map.put:(Ljava/lang/Object;Ljava/lang/Object;)Ljava/lang/Object;
     364: pop
     365: aload_0
     366: getfield      #52                 // Field readMetadata:Z
     369: ifeq          383
     372: aload_1
     373: ldc           #237                // String track_scores
     375: ldc           #207                // String true
     377: invokeinterface #185,  3          // InterfaceMethod java/util/Map.put:(Ljava/lang/Object;Ljava/lang/Object;)Ljava/lang/Object;
     382: pop
     383: aload_1
     384: invokeinterface #239,  1          // InterfaceMethod java/util/Map.entrySet:()Ljava/util/Set;
     389: invokeinterface #243,  1          // InterfaceMethod java/util/Set.iterator:()Ljava/util/Iterator;
     394: astore        4
     396: aload         4
     398: invokeinterface #249,  1          // InterfaceMethod java/util/Iterator.hasNext:()Z
     403: ifeq          493
     406: aload         4
     408: invokeinterface #254,  1          // InterfaceMethod java/util/Iterator.next:()Ljava/lang/Object;
     413: checkcast     #258                // class java/util/Map$Entry
     416: astore        5
     418: aload_2
     419: aload         5
     421: invokeinterface #260,  1          // InterfaceMethod java/util/Map$Entry.getKey:()Ljava/lang/Object;
     426: checkcast     #144                // class java/lang/String
     429: invokevirtual #158                // Method java/lang/StringBuilder.append:(Ljava/lang/String;)Ljava/lang/StringBuilder;
     432: pop
     433: aload         5
     435: invokeinterface #263,  1          // InterfaceMethod java/util/Map$Entry.getValue:()Ljava/lang/Object;
     440: checkcast     #266                // class java/lang/CharSequence
     443: invokestatic  #209                // Method org/elasticsearch/hadoop/util/StringUtils.hasText:(Ljava/lang/CharSequence;)Z
     446: ifeq          472
     449: aload_2
     450: ldc_w         #268                // String =
     453: invokevirtual #158                // Method java/lang/StringBuilder.append:(Ljava/lang/String;)Ljava/lang/StringBuilder;
     456: pop
     457: aload_2
     458: aload         5
     460: invokeinterface #263,  1          // InterfaceMethod java/util/Map$Entry.getValue:()Ljava/lang/Object;
     465: checkcast     #144                // class java/lang/String
     468: invokevirtual #158                // Method java/lang/StringBuilder.append:(Ljava/lang/String;)Ljava/lang/StringBuilder;
     471: pop
     472: aload         4
     474: invokeinterface #249,  1          // InterfaceMethod java/util/Iterator.hasNext:()Z
     479: ifeq          490
     482: aload_2
     483: ldc_w         #270                // String &
     486: invokevirtual #158                // Method java/lang/StringBuilder.append:(Ljava/lang/String;)Ljava/lang/StringBuilder;
     489: pop
     490: goto          396
     493: aload_2
     494: invokevirtual #224                // Method java/lang/StringBuilder.toString:()Ljava/lang/String;
     497: areturn

  private org.elasticsearch.hadoop.util.BytesArray assembleBody();
    Code:
       0: aload_0
       1: getfield      #84                 // Field query:Lorg/elasticsearch/hadoop/rest/query/QueryBuilder;
       4: astore_1
       5: aload_1
       6: ifnonnull     13
       9: getstatic     #272                // Field org/elasticsearch/hadoop/rest/query/MatchAllQueryBuilder.MATCH_ALL:Lorg/elasticsearch/hadoop/rest/query/MatchAllQueryBuilder;
      12: astore_1
      13: aload_0
      14: getfield      #35                 // Field filters:Ljava/util/List;
      17: invokeinterface #278,  1          // InterfaceMethod java/util/List.isEmpty:()Z
      22: ifne          79
      25: aload_0
      26: getfield      #55                 // Field version:Lorg/elasticsearch/hadoop/util/EsMajorVersion;
      29: getstatic     #281                // Field org/elasticsearch/hadoop/util/EsMajorVersion.V_2_X:Lorg/elasticsearch/hadoop/util/EsMajorVersion;
      32: invokevirtual #177                // Method org/elasticsearch/hadoop/util/EsMajorVersion.onOrAfter:(Lorg/elasticsearch/hadoop/util/EsMajorVersion;)Z
      35: ifeq          60
      38: new           #284                // class org/elasticsearch/hadoop/rest/query/BoolQueryBuilder
      41: dup
      42: invokespecial #286                // Method org/elasticsearch/hadoop/rest/query/BoolQueryBuilder."<init>":()V
      45: aload_1
      46: invokevirtual #287                // Method org/elasticsearch/hadoop/rest/query/BoolQueryBuilder.must:(Lorg/elasticsearch/hadoop/rest/query/QueryBuilder;)Lorg/elasticsearch/hadoop/rest/query/BoolQueryBuilder;
      49: aload_0
      50: getfield      #35                 // Field filters:Ljava/util/List;
      53: invokevirtual #291                // Method org/elasticsearch/hadoop/rest/query/BoolQueryBuilder.filters:(Ljava/util/Collection;)Lorg/elasticsearch/hadoop/rest/query/BoolQueryBuilder;
      56: astore_1
      57: goto          79
      60: new           #294                // class org/elasticsearch/hadoop/rest/query/FilteredQueryBuilder
      63: dup
      64: invokespecial #296                // Method org/elasticsearch/hadoop/rest/query/FilteredQueryBuilder."<init>":()V
      67: aload_1
      68: invokevirtual #297                // Method org/elasticsearch/hadoop/rest/query/FilteredQueryBuilder.query:(Lorg/elasticsearch/hadoop/rest/query/QueryBuilder;)Lorg/elasticsearch/hadoop/rest/query/FilteredQueryBuilder;
      71: aload_0
      72: getfield      #35                 // Field filters:Ljava/util/List;
      75: invokevirtual #300                // Method org/elasticsearch/hadoop/rest/query/FilteredQueryBuilder.filters:(Ljava/util/Collection;)Lorg/elasticsearch/hadoop/rest/query/FilteredQueryBuilder;
      78: astore_1
      79: new           #303                // class org/elasticsearch/hadoop/util/FastByteArrayOutputStream
      82: dup
      83: sipush        256
      86: invokespecial #305                // Method org/elasticsearch/hadoop/util/FastByteArrayOutputStream."<init>":(I)V
      89: astore_2
      90: new           #308                // class org/elasticsearch/hadoop/serialization/json/JacksonJsonGenerator
      93: dup
      94: aload_2
      95: invokespecial #310                // Method org/elasticsearch/hadoop/serialization/json/JacksonJsonGenerator."<init>":(Ljava/io/OutputStream;)V
      98: astore_3
      99: aload_3
     100: invokevirtual #313                // Method org/elasticsearch/hadoop/serialization/json/JacksonJsonGenerator.writeBeginObject:()Lorg/elasticsearch/hadoop/serialization/Generator;
     103: pop
     104: aload_0
     105: getfield      #137                // Field slice:Lorg/elasticsearch/hadoop/rest/SearchRequestBuilder$Slice;
     108: ifnull        180
     111: aload_0
     112: getfield      #137                // Field slice:Lorg/elasticsearch/hadoop/rest/SearchRequestBuilder$Slice;
     115: getfield      #317                // Field org/elasticsearch/hadoop/rest/SearchRequestBuilder$Slice.max:I
     118: iconst_1
     119: if_icmple     180
     122: aload_3
     123: ldc_w         #321                // String slice
     126: invokevirtual #322                // Method org/elasticsearch/hadoop/serialization/json/JacksonJsonGenerator.writeFieldName:(Ljava/lang/String;)Lorg/elasticsearch/hadoop/serialization/Generator;
     129: pop
     130: aload_3
     131: invokevirtual #313                // Method org/elasticsearch/hadoop/serialization/json/JacksonJsonGenerator.writeBeginObject:()Lorg/elasticsearch/hadoop/serialization/Generator;
     134: pop
     135: aload_3
     136: ldc_w         #326                // String id
     139: invokevirtual #322                // Method org/elasticsearch/hadoop/serialization/json/JacksonJsonGenerator.writeFieldName:(Ljava/lang/String;)Lorg/elasticsearch/hadoop/serialization/Generator;
     142: pop
     143: aload_3
     144: aload_0
     145: getfield      #137                // Field slice:Lorg/elasticsearch/hadoop/rest/SearchRequestBuilder$Slice;
     148: getfield      #328                // Field org/elasticsearch/hadoop/rest/SearchRequestBuilder$Slice.id:I
     151: invokevirtual #330                // Method org/elasticsearch/hadoop/serialization/json/JacksonJsonGenerator.writeNumber:(I)Lorg/elasticsearch/hadoop/serialization/Generator;
     154: pop
     155: aload_3
     156: ldc_w         #334                // String max
     159: invokevirtual #322                // Method org/elasticsearch/hadoop/serialization/json/JacksonJsonGenerator.writeFieldName:(Ljava/lang/String;)Lorg/elasticsearch/hadoop/serialization/Generator;
     162: pop
     163: aload_3
     164: aload_0
     165: getfield      #137                // Field slice:Lorg/elasticsearch/hadoop/rest/SearchRequestBuilder$Slice;
     168: getfield      #317                // Field org/elasticsearch/hadoop/rest/SearchRequestBuilder$Slice.max:I
     171: invokevirtual #330                // Method org/elasticsearch/hadoop/serialization/json/JacksonJsonGenerator.writeNumber:(I)Lorg/elasticsearch/hadoop/serialization/Generator;
     174: pop
     175: aload_3
     176: invokevirtual #335                // Method org/elasticsearch/hadoop/serialization/json/JacksonJsonGenerator.writeEndObject:()Lorg/elasticsearch/hadoop/serialization/Generator;
     179: pop
     180: aload_3
     181: ldc_w         #338                // String query
     184: invokevirtual #322                // Method org/elasticsearch/hadoop/serialization/json/JacksonJsonGenerator.writeFieldName:(Ljava/lang/String;)Lorg/elasticsearch/hadoop/serialization/Generator;
     187: pop
     188: aload_3
     189: invokevirtual #313                // Method org/elasticsearch/hadoop/serialization/json/JacksonJsonGenerator.writeBeginObject:()Lorg/elasticsearch/hadoop/serialization/Generator;
     192: pop
     193: aload_1
     194: aload_3
     195: invokevirtual #339                // Method org/elasticsearch/hadoop/rest/query/QueryBuilder.toJson:(Lorg/elasticsearch/hadoop/serialization/Generator;)V
     198: aload_3
     199: invokevirtual #335                // Method org/elasticsearch/hadoop/serialization/json/JacksonJsonGenerator.writeEndObject:()Lorg/elasticsearch/hadoop/serialization/Generator;
     202: pop
     203: aload_0
     204: getfield      #119                // Field fields:Ljava/lang/String;
     207: invokestatic  #209                // Method org/elasticsearch/hadoop/util/StringUtils.hasText:(Ljava/lang/CharSequence;)Z
     210: ifeq          287
     213: aload_3
     214: ldc_w         #345                // String _source
     217: invokevirtual #322                // Method org/elasticsearch/hadoop/serialization/json/JacksonJsonGenerator.writeFieldName:(Ljava/lang/String;)Lorg/elasticsearch/hadoop/serialization/Generator;
     220: pop
     221: aload_3
     222: invokevirtual #347                // Method org/elasticsearch/hadoop/serialization/json/JacksonJsonGenerator.writeBeginArray:()Lorg/elasticsearch/hadoop/serialization/Generator;
     225: pop
     226: aload_0
     227: getfield      #119                // Field fields:Ljava/lang/String;
     230: ldc_w         #350                // String ,
     233: invokestatic  #352                // Method org/elasticsearch/hadoop/util/StringUtils.tokenize:(Ljava/lang/String;Ljava/lang/String;)Ljava/util/List;
     236: astore        4
     238: aload         4
     240: invokeinterface #356,  1          // InterfaceMethod java/util/List.iterator:()Ljava/util/Iterator;
     245: astore        5
     247: aload         5
     249: invokeinterface #249,  1          // InterfaceMethod java/util/Iterator.hasNext:()Z
     254: ifeq          279
     257: aload         5
     259: invokeinterface #254,  1          // InterfaceMethod java/util/Iterator.next:()Ljava/lang/Object;
     264: checkcast     #144                // class java/lang/String
     267: astore        6
     269: aload_3
     270: aload         6
     272: invokevirtual #357                // Method org/elasticsearch/hadoop/serialization/json/JacksonJsonGenerator.writeString:(Ljava/lang/String;)Lorg/elasticsearch/hadoop/serialization/Generator;
     275: pop
     276: goto          247
     279: aload_3
     280: invokevirtual #360                // Method org/elasticsearch/hadoop/serialization/json/JacksonJsonGenerator.writeEndArray:()Lorg/elasticsearch/hadoop/serialization/Generator;
     283: pop
     284: goto          308
     287: aload_0
     288: getfield      #49                 // Field excludeSource:Z
     291: ifeq          308
     294: aload_3
     295: ldc_w         #345                // String _source
     298: invokevirtual #322                // Method org/elasticsearch/hadoop/serialization/json/JacksonJsonGenerator.writeFieldName:(Ljava/lang/String;)Lorg/elasticsearch/hadoop/serialization/Generator;
     301: pop
     302: aload_3
     303: iconst_0
     304: invokevirtual #363                // Method org/elasticsearch/hadoop/serialization/json/JacksonJsonGenerator.writeBoolean:(Z)Lorg/elasticsearch/hadoop/serialization/Generator;
     307: pop
     308: aload_3
     309: invokevirtual #335                // Method org/elasticsearch/hadoop/serialization/json/JacksonJsonGenerator.writeEndObject:()Lorg/elasticsearch/hadoop/serialization/Generator;
     312: pop
     313: aload_3
     314: invokevirtual #367                // Method org/elasticsearch/hadoop/serialization/json/JacksonJsonGenerator.close:()V
     317: goto          329
     320: astore        7
     322: aload_3
     323: invokevirtual #367                // Method org/elasticsearch/hadoop/serialization/json/JacksonJsonGenerator.close:()V
     326: aload         7
     328: athrow
     329: aload_2
     330: invokevirtual #370                // Method org/elasticsearch/hadoop/util/FastByteArrayOutputStream.bytes:()Lorg/elasticsearch/hadoop/util/BytesArray;
     333: areturn
    Exception table:
       from    to  target type
          99   313   320   any
         320   322   320   any

  public org.elasticsearch.hadoop.rest.ScrollQuery build(org.elasticsearch.hadoop.rest.RestRepository, org.elasticsearch.hadoop.serialization.ScrollReader);
    Code:
       0: aload_0
       1: invokespecial #374                // Method assemble:()Ljava/lang/String;
       4: astore_3
       5: aload_0
       6: invokespecial #377                // Method assembleBody:()Lorg/elasticsearch/hadoop/util/BytesArray;
       9: astore        4
      11: aload_1
      12: aload_3
      13: aload         4
      15: aload_0
      16: getfield      #29                 // Field limit:J
      19: aload_2
      20: invokevirtual #380                // Method org/elasticsearch/hadoop/rest/RestRepository.scanLimit:(Ljava/lang/String;Lorg/elasticsearch/hadoop/util/BytesArray;JLorg/elasticsearch/hadoop/serialization/ScrollReader;)Lorg/elasticsearch/hadoop/rest/ScrollQuery;
      23: areturn

  public java.lang.String toString();
    Code:
       0: new           #155                // class java/lang/StringBuilder
       3: dup
       4: invokespecial #157                // Method java/lang/StringBuilder."<init>":()V
       7: ldc_w         #386                // String QueryBuilder [
      10: invokevirtual #158                // Method java/lang/StringBuilder.append:(Ljava/lang/String;)Ljava/lang/StringBuilder;
      13: aload_0
      14: invokespecial #374                // Method assemble:()Ljava/lang/String;
      17: invokevirtual #158                // Method java/lang/StringBuilder.append:(Ljava/lang/String;)Ljava/lang/StringBuilder;
      20: ldc_w         #388                // String ][
      23: invokevirtual #158                // Method java/lang/StringBuilder.append:(Ljava/lang/String;)Ljava/lang/StringBuilder;
      26: aload_0
      27: invokespecial #377                // Method assembleBody:()Lorg/elasticsearch/hadoop/util/BytesArray;
      30: invokevirtual #390                // Method java/lang/StringBuilder.append:(Ljava/lang/Object;)Ljava/lang/StringBuilder;
      33: ldc_w         #393                // String ]
      36: invokevirtual #158                // Method java/lang/StringBuilder.append:(Ljava/lang/String;)Ljava/lang/StringBuilder;
      39: invokevirtual #224                // Method java/lang/StringBuilder.toString:()Ljava/lang/String;
      42: areturn
}
