public class org.bouncycastle.crypto.signers.SM2Signer implements org.bouncycastle.crypto.Signer,org.bouncycastle.math.ec.ECConstants {
  private final org.bouncycastle.crypto.signers.DSAKCalculator kCalculator;

  private final org.bouncycastle.crypto.Digest digest;

  private final org.bouncycastle.crypto.signers.DSAEncoding encoding;

  private org.bouncycastle.crypto.params.ECDomainParameters ecParams;

  private org.bouncycastle.math.ec.ECPoint pubPoint;

  private org.bouncycastle.crypto.params.ECKeyParameters ecKey;

  private byte[] z;

  public org.bouncycastle.crypto.signers.SM2Signer();
    Code:
       0: aload_0
       1: getstatic     #243                // Field org/bouncycastle/crypto/signers/StandardDSAEncoding.INSTANCE:Lorg/bouncycastle/crypto/signers/StandardDSAEncoding;
       4: new           #113                // class org/bouncycastle/crypto/digests/SM3Digest
       7: dup
       8: invokespecial #259                // Method org/bouncycastle/crypto/digests/SM3Digest."<init>":()V
      11: invokespecial #278                // Method "<init>":(Lorg/bouncycastle/crypto/signers/DSAEncoding;Lorg/bouncycastle/crypto/Digest;)V
      14: return

  public org.bouncycastle.crypto.signers.SM2Signer(org.bouncycastle.crypto.Digest);
    Code:
       0: aload_0
       1: getstatic     #243                // Field org/bouncycastle/crypto/signers/StandardDSAEncoding.INSTANCE:Lorg/bouncycastle/crypto/signers/StandardDSAEncoding;
       4: aload_1
       5: invokespecial #278                // Method "<init>":(Lorg/bouncycastle/crypto/signers/DSAEncoding;Lorg/bouncycastle/crypto/Digest;)V
       8: return

  public org.bouncycastle.crypto.signers.SM2Signer(org.bouncycastle.crypto.signers.DSAEncoding);
    Code:
       0: aload_0
       1: invokespecial #246                // Method java/lang/Object."<init>":()V
       4: aload_0
       5: new           #122                // class org/bouncycastle/crypto/signers/RandomDSAKCalculator
       8: dup
       9: invokespecial #270                // Method org/bouncycastle/crypto/signers/RandomDSAKCalculator."<init>":()V
      12: putfield      #241                // Field kCalculator:Lorg/bouncycastle/crypto/signers/DSAKCalculator;
      15: aload_0
      16: aload_1
      17: putfield      #240                // Field encoding:Lorg/bouncycastle/crypto/signers/DSAEncoding;
      20: aload_0
      21: new           #113                // class org/bouncycastle/crypto/digests/SM3Digest
      24: dup
      25: invokespecial #259                // Method org/bouncycastle/crypto/digests/SM3Digest."<init>":()V
      28: putfield      #237                // Field digest:Lorg/bouncycastle/crypto/Digest;
      31: return

  public org.bouncycastle.crypto.signers.SM2Signer(org.bouncycastle.crypto.signers.DSAEncoding, org.bouncycastle.crypto.Digest);
    Code:
       0: aload_0
       1: invokespecial #246                // Method java/lang/Object."<init>":()V
       4: aload_0
       5: new           #122                // class org/bouncycastle/crypto/signers/RandomDSAKCalculator
       8: dup
       9: invokespecial #270                // Method org/bouncycastle/crypto/signers/RandomDSAKCalculator."<init>":()V
      12: putfield      #241                // Field kCalculator:Lorg/bouncycastle/crypto/signers/DSAKCalculator;
      15: aload_0
      16: aload_1
      17: putfield      #240                // Field encoding:Lorg/bouncycastle/crypto/signers/DSAEncoding;
      20: aload_0
      21: aload_2
      22: putfield      #237                // Field digest:Lorg/bouncycastle/crypto/Digest;
      25: return

  public void init(boolean, org.bouncycastle.crypto.CipherParameters);
    Code:
       0: aload_2
       1: instanceof    #118                // class org/bouncycastle/crypto/params/ParametersWithID
       4: ifeq          43
       7: aload_2
       8: checkcast     #118                // class org/bouncycastle/crypto/params/ParametersWithID
      11: invokevirtual #267                // Method org/bouncycastle/crypto/params/ParametersWithID.getParameters:()Lorg/bouncycastle/crypto/CipherParameters;
      14: astore_3
      15: aload_2
      16: checkcast     #118                // class org/bouncycastle/crypto/params/ParametersWithID
      19: invokevirtual #266                // Method org/bouncycastle/crypto/params/ParametersWithID.getID:()[B
      22: astore        4
      24: aload         4
      26: arraylength
      27: sipush        8192
      30: if_icmplt     52
      33: new           #105                // class java/lang/IllegalArgumentException
      36: dup
      37: ldc           #2                  // String SM2 user ID must be less than 2^16 bits long
      39: invokespecial #245                // Method java/lang/IllegalArgumentException."<init>":(Ljava/lang/String;)V
      42: athrow
      43: aload_2
      44: astore_3
      45: ldc           #1                  // String 31323334353637383132333435363738
      47: invokestatic  #291                // Method org/bouncycastle/util/encoders/Hex.decodeStrict:(Ljava/lang/String;)[B
      50: astore        4
      52: iload_1
      53: ifeq          190
      56: aload_3
      57: instanceof    #119                // class org/bouncycastle/crypto/params/ParametersWithRandom
      60: ifeq          116
      63: aload_3
      64: checkcast     #119                // class org/bouncycastle/crypto/params/ParametersWithRandom
      67: astore        5
      69: aload_0
      70: aload         5
      72: invokevirtual #269                // Method org/bouncycastle/crypto/params/ParametersWithRandom.getParameters:()Lorg/bouncycastle/crypto/CipherParameters;
      75: checkcast     #115                // class org/bouncycastle/crypto/params/ECKeyParameters
      78: putfield      #239                // Field ecKey:Lorg/bouncycastle/crypto/params/ECKeyParameters;
      81: aload_0
      82: aload_0
      83: getfield      #239                // Field ecKey:Lorg/bouncycastle/crypto/params/ECKeyParameters;
      86: invokevirtual #263                // Method org/bouncycastle/crypto/params/ECKeyParameters.getParameters:()Lorg/bouncycastle/crypto/params/ECDomainParameters;
      89: putfield      #238                // Field ecParams:Lorg/bouncycastle/crypto/params/ECDomainParameters;
      92: aload_0
      93: getfield      #241                // Field kCalculator:Lorg/bouncycastle/crypto/signers/DSAKCalculator;
      96: aload_0
      97: getfield      #238                // Field ecParams:Lorg/bouncycastle/crypto/params/ECDomainParameters;
     100: invokevirtual #260                // Method org/bouncycastle/crypto/params/ECDomainParameters.getN:()Ljava/math/BigInteger;
     103: aload         5
     105: invokevirtual #268                // Method org/bouncycastle/crypto/params/ParametersWithRandom.getRandom:()Ljava/security/SecureRandom;
     108: invokeinterface #300,  3          // InterfaceMethod org/bouncycastle/crypto/signers/DSAKCalculator.init:(Ljava/math/BigInteger;Ljava/security/SecureRandom;)V
     113: goto          154
     116: aload_0
     117: aload_3
     118: checkcast     #115                // class org/bouncycastle/crypto/params/ECKeyParameters
     121: putfield      #239                // Field ecKey:Lorg/bouncycastle/crypto/params/ECKeyParameters;
     124: aload_0
     125: aload_0
     126: getfield      #239                // Field ecKey:Lorg/bouncycastle/crypto/params/ECKeyParameters;
     129: invokevirtual #263                // Method org/bouncycastle/crypto/params/ECKeyParameters.getParameters:()Lorg/bouncycastle/crypto/params/ECDomainParameters;
     132: putfield      #238                // Field ecParams:Lorg/bouncycastle/crypto/params/ECDomainParameters;
     135: aload_0
     136: getfield      #241                // Field kCalculator:Lorg/bouncycastle/crypto/signers/DSAKCalculator;
     139: aload_0
     140: getfield      #238                // Field ecParams:Lorg/bouncycastle/crypto/params/ECDomainParameters;
     143: invokevirtual #260                // Method org/bouncycastle/crypto/params/ECDomainParameters.getN:()Ljava/math/BigInteger;
     146: invokestatic  #258                // Method org/bouncycastle/crypto/CryptoServicesRegistrar.getSecureRandom:()Ljava/security/SecureRandom;
     149: invokeinterface #300,  3          // InterfaceMethod org/bouncycastle/crypto/signers/DSAKCalculator.init:(Ljava/math/BigInteger;Ljava/security/SecureRandom;)V
     154: aload_0
     155: aload_0
     156: invokevirtual #275                // Method createBasePointMultiplier:()Lorg/bouncycastle/math/ec/ECMultiplier;
     159: aload_0
     160: getfield      #238                // Field ecParams:Lorg/bouncycastle/crypto/params/ECDomainParameters;
     163: invokevirtual #262                // Method org/bouncycastle/crypto/params/ECDomainParameters.getG:()Lorg/bouncycastle/math/ec/ECPoint;
     166: aload_0
     167: getfield      #239                // Field ecKey:Lorg/bouncycastle/crypto/params/ECKeyParameters;
     170: checkcast     #116                // class org/bouncycastle/crypto/params/ECPrivateKeyParameters
     173: invokevirtual #264                // Method org/bouncycastle/crypto/params/ECPrivateKeyParameters.getD:()Ljava/math/BigInteger;
     176: invokeinterface #301,  3          // InterfaceMethod org/bouncycastle/math/ec/ECMultiplier.multiply:(Lorg/bouncycastle/math/ec/ECPoint;Ljava/math/BigInteger;)Lorg/bouncycastle/math/ec/ECPoint;
     181: invokevirtual #288                // Method org/bouncycastle/math/ec/ECPoint.normalize:()Lorg/bouncycastle/math/ec/ECPoint;
     184: putfield      #242                // Field pubPoint:Lorg/bouncycastle/math/ec/ECPoint;
     187: goto          223
     190: aload_0
     191: aload_3
     192: checkcast     #115                // class org/bouncycastle/crypto/params/ECKeyParameters
     195: putfield      #239                // Field ecKey:Lorg/bouncycastle/crypto/params/ECKeyParameters;
     198: aload_0
     199: aload_0
     200: getfield      #239                // Field ecKey:Lorg/bouncycastle/crypto/params/ECKeyParameters;
     203: invokevirtual #263                // Method org/bouncycastle/crypto/params/ECKeyParameters.getParameters:()Lorg/bouncycastle/crypto/params/ECDomainParameters;
     206: putfield      #238                // Field ecParams:Lorg/bouncycastle/crypto/params/ECDomainParameters;
     209: aload_0
     210: aload_0
     211: getfield      #239                // Field ecKey:Lorg/bouncycastle/crypto/params/ECKeyParameters;
     214: checkcast     #117                // class org/bouncycastle/crypto/params/ECPublicKeyParameters
     217: invokevirtual #265                // Method org/bouncycastle/crypto/params/ECPublicKeyParameters.getQ:()Lorg/bouncycastle/math/ec/ECPoint;
     220: putfield      #242                // Field pubPoint:Lorg/bouncycastle/math/ec/ECPoint;
     223: aload_0
     224: aload_0
     225: aload         4
     227: invokespecial #273                // Method getZ:([B)[B
     230: putfield      #234                // Field z:[B
     233: aload_0
     234: getfield      #237                // Field digest:Lorg/bouncycastle/crypto/Digest;
     237: aload_0
     238: getfield      #234                // Field z:[B
     241: iconst_0
     242: aload_0
     243: getfield      #234                // Field z:[B
     246: arraylength
     247: invokeinterface #296,  4          // InterfaceMethod org/bouncycastle/crypto/Digest.update:([BII)V
     252: return

  public void update(byte);
    Code:
       0: aload_0
       1: getfield      #237                // Field digest:Lorg/bouncycastle/crypto/Digest;
       4: iload_1
       5: invokeinterface #294,  2          // InterfaceMethod org/bouncycastle/crypto/Digest.update:(B)V
      10: return

  public void update(byte[], int, int);
    Code:
       0: aload_0
       1: getfield      #237                // Field digest:Lorg/bouncycastle/crypto/Digest;
       4: aload_1
       5: iload_2
       6: iload_3
       7: invokeinterface #296,  4          // InterfaceMethod org/bouncycastle/crypto/Digest.update:([BII)V
      12: return

  public boolean verifySignature(byte[]);
    Code:
       0: aload_0
       1: getfield      #240                // Field encoding:Lorg/bouncycastle/crypto/signers/DSAEncoding;
       4: aload_0
       5: getfield      #238                // Field ecParams:Lorg/bouncycastle/crypto/params/ECDomainParameters;
       8: invokevirtual #260                // Method org/bouncycastle/crypto/params/ECDomainParameters.getN:()Ljava/math/BigInteger;
      11: aload_1
      12: invokeinterface #297,  3          // InterfaceMethod org/bouncycastle/crypto/signers/DSAEncoding.decode:(Ljava/math/BigInteger;[B)[Ljava/math/BigInteger;
      17: astore_2
      18: aload_0
      19: aload_2
      20: iconst_0
      21: aaload
      22: aload_2
      23: iconst_1
      24: aaload
      25: invokespecial #276                // Method verifySignature:(Ljava/math/BigInteger;Ljava/math/BigInteger;)Z
      28: ireturn
      29: astore_2
      30: iconst_0
      31: ireturn
    Exception table:
       from    to  target type
           0    28    29   Class java/lang/Exception

  public void reset();
    Code:
       0: aload_0
       1: getfield      #237                // Field digest:Lorg/bouncycastle/crypto/Digest;
       4: invokeinterface #293,  1          // InterfaceMethod org/bouncycastle/crypto/Digest.reset:()V
       9: aload_0
      10: getfield      #234                // Field z:[B
      13: ifnull        35
      16: aload_0
      17: getfield      #237                // Field digest:Lorg/bouncycastle/crypto/Digest;
      20: aload_0
      21: getfield      #234                // Field z:[B
      24: iconst_0
      25: aload_0
      26: getfield      #234                // Field z:[B
      29: arraylength
      30: invokeinterface #296,  4          // InterfaceMethod org/bouncycastle/crypto/Digest.update:([BII)V
      35: return

  public byte[] generateSignature() throws org.bouncycastle.crypto.CryptoException;
    Code:
       0: aload_0
       1: invokespecial #272                // Method digestDoFinal:()[B
       4: astore_1
       5: aload_0
       6: getfield      #238                // Field ecParams:Lorg/bouncycastle/crypto/params/ECDomainParameters;
       9: invokevirtual #260                // Method org/bouncycastle/crypto/params/ECDomainParameters.getN:()Ljava/math/BigInteger;
      12: astore_2
      13: aload_0
      14: aload_2
      15: aload_1
      16: invokevirtual #277                // Method calculateE:(Ljava/math/BigInteger;[B)Ljava/math/BigInteger;
      19: astore_3
      20: aload_0
      21: getfield      #239                // Field ecKey:Lorg/bouncycastle/crypto/params/ECKeyParameters;
      24: checkcast     #116                // class org/bouncycastle/crypto/params/ECPrivateKeyParameters
      27: invokevirtual #264                // Method org/bouncycastle/crypto/params/ECPrivateKeyParameters.getD:()Ljava/math/BigInteger;
      30: astore        4
      32: aload_0
      33: invokevirtual #275                // Method createBasePointMultiplier:()Lorg/bouncycastle/math/ec/ECMultiplier;
      36: astore        7
      38: aload_0
      39: getfield      #241                // Field kCalculator:Lorg/bouncycastle/crypto/signers/DSAKCalculator;
      42: invokeinterface #299,  1          // InterfaceMethod org/bouncycastle/crypto/signers/DSAKCalculator.nextK:()Ljava/math/BigInteger;
      47: astore        8
      49: aload         7
      51: aload_0
      52: getfield      #238                // Field ecParams:Lorg/bouncycastle/crypto/params/ECDomainParameters;
      55: invokevirtual #262                // Method org/bouncycastle/crypto/params/ECDomainParameters.getG:()Lorg/bouncycastle/math/ec/ECPoint;
      58: aload         8
      60: invokeinterface #301,  3          // InterfaceMethod org/bouncycastle/math/ec/ECMultiplier.multiply:(Lorg/bouncycastle/math/ec/ECPoint;Ljava/math/BigInteger;)Lorg/bouncycastle/math/ec/ECPoint;
      65: invokevirtual #288                // Method org/bouncycastle/math/ec/ECPoint.normalize:()Lorg/bouncycastle/math/ec/ECPoint;
      68: astore        9
      70: aload_3
      71: aload         9
      73: invokevirtual #286                // Method org/bouncycastle/math/ec/ECPoint.getAffineXCoord:()Lorg/bouncycastle/math/ec/ECFieldElement;
      76: invokevirtual #284                // Method org/bouncycastle/math/ec/ECFieldElement.toBigInteger:()Ljava/math/BigInteger;
      79: invokevirtual #253                // Method java/math/BigInteger.add:(Ljava/math/BigInteger;)Ljava/math/BigInteger;
      82: aload_2
      83: invokevirtual #254                // Method java/math/BigInteger.mod:(Ljava/math/BigInteger;)Ljava/math/BigInteger;
      86: astore        5
      88: aload         5
      90: getstatic     #236                // Field ZERO:Ljava/math/BigInteger;
      93: invokevirtual #251                // Method java/math/BigInteger.equals:(Ljava/lang/Object;)Z
      96: ifne          38
      99: aload         5
     101: aload         8
     103: invokevirtual #253                // Method java/math/BigInteger.add:(Ljava/math/BigInteger;)Ljava/math/BigInteger;
     106: aload_2
     107: invokevirtual #251                // Method java/math/BigInteger.equals:(Ljava/lang/Object;)Z
     110: ifne          38
     113: aload_2
     114: aload         4
     116: getstatic     #235                // Field ONE:Ljava/math/BigInteger;
     119: invokevirtual #253                // Method java/math/BigInteger.add:(Ljava/math/BigInteger;)Ljava/math/BigInteger;
     122: invokestatic  #290                // Method org/bouncycastle/util/BigIntegers.modOddInverse:(Ljava/math/BigInteger;Ljava/math/BigInteger;)Ljava/math/BigInteger;
     125: astore        9
     127: aload         8
     129: aload         5
     131: aload         4
     133: invokevirtual #255                // Method java/math/BigInteger.multiply:(Ljava/math/BigInteger;)Ljava/math/BigInteger;
     136: invokevirtual #256                // Method java/math/BigInteger.subtract:(Ljava/math/BigInteger;)Ljava/math/BigInteger;
     139: aload_2
     140: invokevirtual #254                // Method java/math/BigInteger.mod:(Ljava/math/BigInteger;)Ljava/math/BigInteger;
     143: astore        6
     145: aload         9
     147: aload         6
     149: invokevirtual #255                // Method java/math/BigInteger.multiply:(Ljava/math/BigInteger;)Ljava/math/BigInteger;
     152: aload_2
     153: invokevirtual #254                // Method java/math/BigInteger.mod:(Ljava/math/BigInteger;)Ljava/math/BigInteger;
     156: astore        6
     158: aload         6
     160: getstatic     #236                // Field ZERO:Ljava/math/BigInteger;
     163: invokevirtual #251                // Method java/math/BigInteger.equals:(Ljava/lang/Object;)Z
     166: ifne          38
     169: aload_0
     170: getfield      #240                // Field encoding:Lorg/bouncycastle/crypto/signers/DSAEncoding;
     173: aload_0
     174: getfield      #238                // Field ecParams:Lorg/bouncycastle/crypto/params/ECDomainParameters;
     177: invokevirtual #260                // Method org/bouncycastle/crypto/params/ECDomainParameters.getN:()Ljava/math/BigInteger;
     180: aload         5
     182: aload         6
     184: invokeinterface #298,  4          // InterfaceMethod org/bouncycastle/crypto/signers/DSAEncoding.encode:(Ljava/math/BigInteger;Ljava/math/BigInteger;Ljava/math/BigInteger;)[B
     189: areturn
     190: astore        8
     192: new           #109                // class org/bouncycastle/crypto/CryptoException
     195: dup
     196: new           #107                // class java/lang/StringBuilder
     199: dup
     200: invokespecial #247                // Method java/lang/StringBuilder."<init>":()V
     203: ldc           #3                  // String unable to encode signature:
     205: invokevirtual #249                // Method java/lang/StringBuilder.append:(Ljava/lang/String;)Ljava/lang/StringBuilder;
     208: aload         8
     210: invokevirtual #244                // Method java/lang/Exception.getMessage:()Ljava/lang/String;
     213: invokevirtual #249                // Method java/lang/StringBuilder.append:(Ljava/lang/String;)Ljava/lang/StringBuilder;
     216: invokevirtual #248                // Method java/lang/StringBuilder.toString:()Ljava/lang/String;
     219: aload         8
     221: invokespecial #257                // Method org/bouncycastle/crypto/CryptoException."<init>":(Ljava/lang/String;Ljava/lang/Throwable;)V
     224: athrow
    Exception table:
       from    to  target type
         169   189   190   Class java/lang/Exception

  private boolean verifySignature(java.math.BigInteger, java.math.BigInteger);
    Code:
       0: aload_0
       1: getfield      #238                // Field ecParams:Lorg/bouncycastle/crypto/params/ECDomainParameters;
       4: invokevirtual #260                // Method org/bouncycastle/crypto/params/ECDomainParameters.getN:()Ljava/math/BigInteger;
       7: astore_3
       8: aload_1
       9: getstatic     #235                // Field ONE:Ljava/math/BigInteger;
      12: invokevirtual #252                // Method java/math/BigInteger.compareTo:(Ljava/math/BigInteger;)I
      15: iflt          26
      18: aload_1
      19: aload_3
      20: invokevirtual #252                // Method java/math/BigInteger.compareTo:(Ljava/math/BigInteger;)I
      23: iflt          28
      26: iconst_0
      27: ireturn
      28: aload_2
      29: getstatic     #235                // Field ONE:Ljava/math/BigInteger;
      32: invokevirtual #252                // Method java/math/BigInteger.compareTo:(Ljava/math/BigInteger;)I
      35: iflt          46
      38: aload_2
      39: aload_3
      40: invokevirtual #252                // Method java/math/BigInteger.compareTo:(Ljava/math/BigInteger;)I
      43: iflt          48
      46: iconst_0
      47: ireturn
      48: aload_0
      49: invokespecial #272                // Method digestDoFinal:()[B
      52: astore        4
      54: aload_0
      55: aload_3
      56: aload         4
      58: invokevirtual #277                // Method calculateE:(Ljava/math/BigInteger;[B)Ljava/math/BigInteger;
      61: astore        5
      63: aload_1
      64: aload_2
      65: invokevirtual #253                // Method java/math/BigInteger.add:(Ljava/math/BigInteger;)Ljava/math/BigInteger;
      68: aload_3
      69: invokevirtual #254                // Method java/math/BigInteger.mod:(Ljava/math/BigInteger;)Ljava/math/BigInteger;
      72: astore        6
      74: aload         6
      76: getstatic     #236                // Field ZERO:Ljava/math/BigInteger;
      79: invokevirtual #251                // Method java/math/BigInteger.equals:(Ljava/lang/Object;)Z
      82: ifeq          87
      85: iconst_0
      86: ireturn
      87: aload_0
      88: getfield      #239                // Field ecKey:Lorg/bouncycastle/crypto/params/ECKeyParameters;
      91: checkcast     #117                // class org/bouncycastle/crypto/params/ECPublicKeyParameters
      94: invokevirtual #265                // Method org/bouncycastle/crypto/params/ECPublicKeyParameters.getQ:()Lorg/bouncycastle/math/ec/ECPoint;
      97: astore        7
      99: aload_0
     100: getfield      #238                // Field ecParams:Lorg/bouncycastle/crypto/params/ECDomainParameters;
     103: invokevirtual #262                // Method org/bouncycastle/crypto/params/ECDomainParameters.getG:()Lorg/bouncycastle/math/ec/ECPoint;
     106: aload_2
     107: aload         7
     109: aload         6
     111: invokestatic  #280                // Method org/bouncycastle/math/ec/ECAlgorithms.sumOfTwoMultiplies:(Lorg/bouncycastle/math/ec/ECPoint;Ljava/math/BigInteger;Lorg/bouncycastle/math/ec/ECPoint;Ljava/math/BigInteger;)Lorg/bouncycastle/math/ec/ECPoint;
     114: invokevirtual #288                // Method org/bouncycastle/math/ec/ECPoint.normalize:()Lorg/bouncycastle/math/ec/ECPoint;
     117: astore        8
     119: aload         8
     121: invokevirtual #285                // Method org/bouncycastle/math/ec/ECPoint.isInfinity:()Z
     124: ifeq          129
     127: iconst_0
     128: ireturn
     129: aload         5
     131: aload         8
     133: invokevirtual #286                // Method org/bouncycastle/math/ec/ECPoint.getAffineXCoord:()Lorg/bouncycastle/math/ec/ECFieldElement;
     136: invokevirtual #284                // Method org/bouncycastle/math/ec/ECFieldElement.toBigInteger:()Ljava/math/BigInteger;
     139: invokevirtual #253                // Method java/math/BigInteger.add:(Ljava/math/BigInteger;)Ljava/math/BigInteger;
     142: aload_3
     143: invokevirtual #254                // Method java/math/BigInteger.mod:(Ljava/math/BigInteger;)Ljava/math/BigInteger;
     146: astore        9
     148: aload         9
     150: aload_1
     151: invokevirtual #251                // Method java/math/BigInteger.equals:(Ljava/lang/Object;)Z
     154: ireturn

  private byte[] digestDoFinal();
    Code:
       0: aload_0
       1: getfield      #237                // Field digest:Lorg/bouncycastle/crypto/Digest;
       4: invokeinterface #292,  1          // InterfaceMethod org/bouncycastle/crypto/Digest.getDigestSize:()I
       9: newarray       byte
      11: astore_1
      12: aload_0
      13: getfield      #237                // Field digest:Lorg/bouncycastle/crypto/Digest;
      16: aload_1
      17: iconst_0
      18: invokeinterface #295,  3          // InterfaceMethod org/bouncycastle/crypto/Digest.doFinal:([BI)I
      23: pop
      24: aload_0
      25: invokevirtual #271                // Method reset:()V
      28: aload_1
      29: areturn

  private byte[] getZ(byte[]);
    Code:
       0: aload_0
       1: getfield      #237                // Field digest:Lorg/bouncycastle/crypto/Digest;
       4: invokeinterface #293,  1          // InterfaceMethod org/bouncycastle/crypto/Digest.reset:()V
       9: aload_0
      10: aload_0
      11: getfield      #237                // Field digest:Lorg/bouncycastle/crypto/Digest;
      14: aload_1
      15: invokespecial #274                // Method addUserID:(Lorg/bouncycastle/crypto/Digest;[B)V
      18: aload_0
      19: aload_0
      20: getfield      #237                // Field digest:Lorg/bouncycastle/crypto/Digest;
      23: aload_0
      24: getfield      #238                // Field ecParams:Lorg/bouncycastle/crypto/params/ECDomainParameters;
      27: invokevirtual #261                // Method org/bouncycastle/crypto/params/ECDomainParameters.getCurve:()Lorg/bouncycastle/math/ec/ECCurve;
      30: invokevirtual #281                // Method org/bouncycastle/math/ec/ECCurve.getA:()Lorg/bouncycastle/math/ec/ECFieldElement;
      33: invokespecial #279                // Method addFieldElement:(Lorg/bouncycastle/crypto/Digest;Lorg/bouncycastle/math/ec/ECFieldElement;)V
      36: aload_0
      37: aload_0
      38: getfield      #237                // Field digest:Lorg/bouncycastle/crypto/Digest;
      41: aload_0
      42: getfield      #238                // Field ecParams:Lorg/bouncycastle/crypto/params/ECDomainParameters;
      45: invokevirtual #261                // Method org/bouncycastle/crypto/params/ECDomainParameters.getCurve:()Lorg/bouncycastle/math/ec/ECCurve;
      48: invokevirtual #282                // Method org/bouncycastle/math/ec/ECCurve.getB:()Lorg/bouncycastle/math/ec/ECFieldElement;
      51: invokespecial #279                // Method addFieldElement:(Lorg/bouncycastle/crypto/Digest;Lorg/bouncycastle/math/ec/ECFieldElement;)V
      54: aload_0
      55: aload_0
      56: getfield      #237                // Field digest:Lorg/bouncycastle/crypto/Digest;
      59: aload_0
      60: getfield      #238                // Field ecParams:Lorg/bouncycastle/crypto/params/ECDomainParameters;
      63: invokevirtual #262                // Method org/bouncycastle/crypto/params/ECDomainParameters.getG:()Lorg/bouncycastle/math/ec/ECPoint;
      66: invokevirtual #286                // Method org/bouncycastle/math/ec/ECPoint.getAffineXCoord:()Lorg/bouncycastle/math/ec/ECFieldElement;
      69: invokespecial #279                // Method addFieldElement:(Lorg/bouncycastle/crypto/Digest;Lorg/bouncycastle/math/ec/ECFieldElement;)V
      72: aload_0
      73: aload_0
      74: getfield      #237                // Field digest:Lorg/bouncycastle/crypto/Digest;
      77: aload_0
      78: getfield      #238                // Field ecParams:Lorg/bouncycastle/crypto/params/ECDomainParameters;
      81: invokevirtual #262                // Method org/bouncycastle/crypto/params/ECDomainParameters.getG:()Lorg/bouncycastle/math/ec/ECPoint;
      84: invokevirtual #287                // Method org/bouncycastle/math/ec/ECPoint.getAffineYCoord:()Lorg/bouncycastle/math/ec/ECFieldElement;
      87: invokespecial #279                // Method addFieldElement:(Lorg/bouncycastle/crypto/Digest;Lorg/bouncycastle/math/ec/ECFieldElement;)V
      90: aload_0
      91: aload_0
      92: getfield      #237                // Field digest:Lorg/bouncycastle/crypto/Digest;
      95: aload_0
      96: getfield      #242                // Field pubPoint:Lorg/bouncycastle/math/ec/ECPoint;
      99: invokevirtual #286                // Method org/bouncycastle/math/ec/ECPoint.getAffineXCoord:()Lorg/bouncycastle/math/ec/ECFieldElement;
     102: invokespecial #279                // Method addFieldElement:(Lorg/bouncycastle/crypto/Digest;Lorg/bouncycastle/math/ec/ECFieldElement;)V
     105: aload_0
     106: aload_0
     107: getfield      #237                // Field digest:Lorg/bouncycastle/crypto/Digest;
     110: aload_0
     111: getfield      #242                // Field pubPoint:Lorg/bouncycastle/math/ec/ECPoint;
     114: invokevirtual #287                // Method org/bouncycastle/math/ec/ECPoint.getAffineYCoord:()Lorg/bouncycastle/math/ec/ECFieldElement;
     117: invokespecial #279                // Method addFieldElement:(Lorg/bouncycastle/crypto/Digest;Lorg/bouncycastle/math/ec/ECFieldElement;)V
     120: aload_0
     121: getfield      #237                // Field digest:Lorg/bouncycastle/crypto/Digest;
     124: invokeinterface #292,  1          // InterfaceMethod org/bouncycastle/crypto/Digest.getDigestSize:()I
     129: newarray       byte
     131: astore_2
     132: aload_0
     133: getfield      #237                // Field digest:Lorg/bouncycastle/crypto/Digest;
     136: aload_2
     137: iconst_0
     138: invokeinterface #295,  3          // InterfaceMethod org/bouncycastle/crypto/Digest.doFinal:([BI)I
     143: pop
     144: aload_2
     145: areturn

  private void addUserID(org.bouncycastle.crypto.Digest, byte[]);
    Code:
       0: aload_2
       1: arraylength
       2: bipush        8
       4: imul
       5: istore_3
       6: aload_1
       7: iload_3
       8: bipush        8
      10: ishr
      11: sipush        255
      14: iand
      15: i2b
      16: invokeinterface #294,  2          // InterfaceMethod org/bouncycastle/crypto/Digest.update:(B)V
      21: aload_1
      22: iload_3
      23: sipush        255
      26: iand
      27: i2b
      28: invokeinterface #294,  2          // InterfaceMethod org/bouncycastle/crypto/Digest.update:(B)V
      33: aload_1
      34: aload_2
      35: iconst_0
      36: aload_2
      37: arraylength
      38: invokeinterface #296,  4          // InterfaceMethod org/bouncycastle/crypto/Digest.update:([BII)V
      43: return

  private void addFieldElement(org.bouncycastle.crypto.Digest, org.bouncycastle.math.ec.ECFieldElement);
    Code:
       0: aload_2
       1: invokevirtual #283                // Method org/bouncycastle/math/ec/ECFieldElement.getEncoded:()[B
       4: astore_3
       5: aload_1
       6: aload_3
       7: iconst_0
       8: aload_3
       9: arraylength
      10: invokeinterface #296,  4          // InterfaceMethod org/bouncycastle/crypto/Digest.update:([BII)V
      15: return

  protected org.bouncycastle.math.ec.ECMultiplier createBasePointMultiplier();
    Code:
       0: new           #131                // class org/bouncycastle/math/ec/FixedPointCombMultiplier
       3: dup
       4: invokespecial #289                // Method org/bouncycastle/math/ec/FixedPointCombMultiplier."<init>":()V
       7: areturn

  protected java.math.BigInteger calculateE(java.math.BigInteger, byte[]);
    Code:
       0: new           #108                // class java/math/BigInteger
       3: dup
       4: iconst_1
       5: aload_2
       6: invokespecial #250                // Method java/math/BigInteger."<init>":(I[B)V
       9: areturn
}
