Compiled from "ClosureUtils.java"
public class org.apache.commons.collections4.ClosureUtils {
  private org.apache.commons.collections4.ClosureUtils();
    Code:
       0: aload_0
       1: invokespecial #1                  // Method java/lang/Object."<init>":()V
       4: return

  public static <E> org.apache.commons.collections4.Closure<E> exceptionClosure();
    Code:
       0: invokestatic  #2                  // Method org/apache/commons/collections4/functors/ExceptionClosure.exceptionClosure:()Lorg/apache/commons/collections4/Closure;
       3: areturn

  public static <E> org.apache.commons.collections4.Closure<E> nopClosure();
    Code:
       0: invokestatic  #3                  // Method org/apache/commons/collections4/functors/NOPClosure.nopClosure:()Lorg/apache/commons/collections4/Closure;
       3: areturn

  public static <E> org.apache.commons.collections4.Closure<E> asClosure(org.apache.commons.collections4.Transformer<? super E, ?>);
    Code:
       0: aload_0
       1: invokestatic  #4                  // Method org/apache/commons/collections4/functors/TransformerClosure.transformerClosure:(Lorg/apache/commons/collections4/Transformer;)Lorg/apache/commons/collections4/Closure;
       4: areturn

  public static <E> org.apache.commons.collections4.Closure<E> forClosure(int, org.apache.commons.collections4.Closure<? super E>);
    Code:
       0: iload_0
       1: aload_1
       2: invokestatic  #5                  // Method org/apache/commons/collections4/functors/ForClosure.forClosure:(ILorg/apache/commons/collections4/Closure;)Lorg/apache/commons/collections4/Closure;
       5: areturn

  public static <E> org.apache.commons.collections4.Closure<E> whileClosure(org.apache.commons.collections4.Predicate<? super E>, org.apache.commons.collections4.Closure<? super E>);
    Code:
       0: aload_0
       1: aload_1
       2: iconst_0
       3: invokestatic  #6                  // Method org/apache/commons/collections4/functors/WhileClosure.whileClosure:(Lorg/apache/commons/collections4/Predicate;Lorg/apache/commons/collections4/Closure;Z)Lorg/apache/commons/collections4/Closure;
       6: areturn

  public static <E> org.apache.commons.collections4.Closure<E> doWhileClosure(org.apache.commons.collections4.Closure<? super E>, org.apache.commons.collections4.Predicate<? super E>);
    Code:
       0: aload_1
       1: aload_0
       2: iconst_1
       3: invokestatic  #6                  // Method org/apache/commons/collections4/functors/WhileClosure.whileClosure:(Lorg/apache/commons/collections4/Predicate;Lorg/apache/commons/collections4/Closure;Z)Lorg/apache/commons/collections4/Closure;
       6: areturn

  public static <E> org.apache.commons.collections4.Closure<E> invokerClosure(java.lang.String);
    Code:
       0: aload_0
       1: invokestatic  #7                  // Method org/apache/commons/collections4/functors/InvokerTransformer.invokerTransformer:(Ljava/lang/String;)Lorg/apache/commons/collections4/Transformer;
       4: invokestatic  #8                  // Method asClosure:(Lorg/apache/commons/collections4/Transformer;)Lorg/apache/commons/collections4/Closure;
       7: areturn

  public static <E> org.apache.commons.collections4.Closure<E> invokerClosure(java.lang.String, java.lang.Class<?>[], java.lang.Object[]);
    Code:
       0: aload_0
       1: aload_1
       2: aload_2
       3: invokestatic  #9                  // Method org/apache/commons/collections4/functors/InvokerTransformer.invokerTransformer:(Ljava/lang/String;[Ljava/lang/Class;[Ljava/lang/Object;)Lorg/apache/commons/collections4/Transformer;
       6: invokestatic  #8                  // Method asClosure:(Lorg/apache/commons/collections4/Transformer;)Lorg/apache/commons/collections4/Closure;
       9: areturn

  public static <E> org.apache.commons.collections4.Closure<E> chainedClosure(org.apache.commons.collections4.Closure<? super E>...);
    Code:
       0: aload_0
       1: invokestatic  #10                 // Method org/apache/commons/collections4/functors/ChainedClosure.chainedClosure:([Lorg/apache/commons/collections4/Closure;)Lorg/apache/commons/collections4/Closure;
       4: areturn

  public static <E> org.apache.commons.collections4.Closure<E> chainedClosure(java.util.Collection<? extends org.apache.commons.collections4.Closure<? super E>>);
    Code:
       0: aload_0
       1: invokestatic  #11                 // Method org/apache/commons/collections4/functors/ChainedClosure.chainedClosure:(Ljava/util/Collection;)Lorg/apache/commons/collections4/Closure;
       4: areturn

  public static <E> org.apache.commons.collections4.Closure<E> ifClosure(org.apache.commons.collections4.Predicate<? super E>, org.apache.commons.collections4.Closure<? super E>);
    Code:
       0: aload_0
       1: aload_1
       2: invokestatic  #12                 // Method org/apache/commons/collections4/functors/IfClosure.ifClosure:(Lorg/apache/commons/collections4/Predicate;Lorg/apache/commons/collections4/Closure;)Lorg/apache/commons/collections4/Closure;
       5: areturn

  public static <E> org.apache.commons.collections4.Closure<E> ifClosure(org.apache.commons.collections4.Predicate<? super E>, org.apache.commons.collections4.Closure<? super E>, org.apache.commons.collections4.Closure<? super E>);
    Code:
       0: aload_0
       1: aload_1
       2: aload_2
       3: invokestatic  #13                 // Method org/apache/commons/collections4/functors/IfClosure.ifClosure:(Lorg/apache/commons/collections4/Predicate;Lorg/apache/commons/collections4/Closure;Lorg/apache/commons/collections4/Closure;)Lorg/apache/commons/collections4/Closure;
       6: areturn

  public static <E> org.apache.commons.collections4.Closure<E> switchClosure(org.apache.commons.collections4.Predicate<? super E>[], org.apache.commons.collections4.Closure<? super E>[]);
    Code:
       0: aload_0
       1: aload_1
       2: aconst_null
       3: invokestatic  #14                 // Method org/apache/commons/collections4/functors/SwitchClosure.switchClosure:([Lorg/apache/commons/collections4/Predicate;[Lorg/apache/commons/collections4/Closure;Lorg/apache/commons/collections4/Closure;)Lorg/apache/commons/collections4/Closure;
       6: areturn

  public static <E> org.apache.commons.collections4.Closure<E> switchClosure(org.apache.commons.collections4.Predicate<? super E>[], org.apache.commons.collections4.Closure<? super E>[], org.apache.commons.collections4.Closure<? super E>);
    Code:
       0: aload_0
       1: aload_1
       2: aload_2
       3: invokestatic  #14                 // Method org/apache/commons/collections4/functors/SwitchClosure.switchClosure:([Lorg/apache/commons/collections4/Predicate;[Lorg/apache/commons/collections4/Closure;Lorg/apache/commons/collections4/Closure;)Lorg/apache/commons/collections4/Closure;
       6: areturn

  public static <E> org.apache.commons.collections4.Closure<E> switchClosure(java.util.Map<org.apache.commons.collections4.Predicate<E>, org.apache.commons.collections4.Closure<E>>);
    Code:
       0: aload_0
       1: invokestatic  #15                 // Method org/apache/commons/collections4/functors/SwitchClosure.switchClosure:(Ljava/util/Map;)Lorg/apache/commons/collections4/Closure;
       4: areturn

  public static <E> org.apache.commons.collections4.Closure<E> switchMapClosure(java.util.Map<? extends E, org.apache.commons.collections4.Closure<E>>);
    Code:
       0: aload_0
       1: ifnonnull     14
       4: new           #16                 // class java/lang/NullPointerException
       7: dup
       8: ldc           #17                 // String The object and closure map must not be null
      10: invokespecial #18                 // Method java/lang/NullPointerException."<init>":(Ljava/lang/String;)V
      13: athrow
      14: aload_0
      15: aconst_null
      16: invokeinterface #19,  2           // InterfaceMethod java/util/Map.remove:(Ljava/lang/Object;)Ljava/lang/Object;
      21: checkcast     #20                 // class org/apache/commons/collections4/Closure
      24: astore_1
      25: aload_0
      26: invokeinterface #21,  1           // InterfaceMethod java/util/Map.size:()I
      31: istore_2
      32: iload_2
      33: anewarray     #20                 // class org/apache/commons/collections4/Closure
      36: astore_3
      37: iload_2
      38: anewarray     #22                 // class org/apache/commons/collections4/Predicate
      41: astore        4
      43: iconst_0
      44: istore        5
      46: aload_0
      47: invokeinterface #23,  1           // InterfaceMethod java/util/Map.entrySet:()Ljava/util/Set;
      52: invokeinterface #24,  1           // InterfaceMethod java/util/Set.iterator:()Ljava/util/Iterator;
      57: astore        6
      59: aload         6
      61: invokeinterface #25,  1           // InterfaceMethod java/util/Iterator.hasNext:()Z
      66: ifeq          116
      69: aload         6
      71: invokeinterface #26,  1           // InterfaceMethod java/util/Iterator.next:()Ljava/lang/Object;
      76: checkcast     #27                 // class java/util/Map$Entry
      79: astore        7
      81: aload         4
      83: iload         5
      85: aload         7
      87: invokeinterface #28,  1           // InterfaceMethod java/util/Map$Entry.getKey:()Ljava/lang/Object;
      92: invokestatic  #29                 // Method org/apache/commons/collections4/functors/EqualPredicate.equalPredicate:(Ljava/lang/Object;)Lorg/apache/commons/collections4/Predicate;
      95: aastore
      96: aload_3
      97: iload         5
      99: aload         7
     101: invokeinterface #30,  1           // InterfaceMethod java/util/Map$Entry.getValue:()Ljava/lang/Object;
     106: checkcast     #20                 // class org/apache/commons/collections4/Closure
     109: aastore
     110: iinc          5, 1
     113: goto          59
     116: aload         4
     118: aload_3
     119: aload_1
     120: invokestatic  #31                 // Method switchClosure:([Lorg/apache/commons/collections4/Predicate;[Lorg/apache/commons/collections4/Closure;Lorg/apache/commons/collections4/Closure;)Lorg/apache/commons/collections4/Closure;
     123: areturn
}
