Compiled from "DelegatedDurationField.java"
public class org.joda.time.field.DelegatedDurationField extends org.joda.time.DurationField implements java.io.Serializable {
  private static final long serialVersionUID;

  private final org.joda.time.DurationField iField;

  private final org.joda.time.DurationFieldType iType;

  protected org.joda.time.field.DelegatedDurationField(org.joda.time.DurationField);
    Code:
       0: aload_0
       1: aload_1
       2: aconst_null
       3: invokespecial #1                  // Method "<init>":(Lorg/joda/time/DurationField;Lorg/joda/time/DurationFieldType;)V
       6: return

  protected org.joda.time.field.DelegatedDurationField(org.joda.time.DurationField, org.joda.time.DurationFieldType);
    Code:
       0: aload_0
       1: invokespecial #2                  // Method org/joda/time/DurationField."<init>":()V
       4: aload_1
       5: ifnonnull     18
       8: new           #3                  // class java/lang/IllegalArgumentException
      11: dup
      12: ldc           #4                  // String The field must not be null
      14: invokespecial #5                  // Method java/lang/IllegalArgumentException."<init>":(Ljava/lang/String;)V
      17: athrow
      18: aload_0
      19: aload_1
      20: putfield      #6                  // Field iField:Lorg/joda/time/DurationField;
      23: aload_0
      24: aload_2
      25: ifnonnull     35
      28: aload_1
      29: invokevirtual #7                  // Method org/joda/time/DurationField.getType:()Lorg/joda/time/DurationFieldType;
      32: goto          36
      35: aload_2
      36: putfield      #8                  // Field iType:Lorg/joda/time/DurationFieldType;
      39: return

  public final org.joda.time.DurationField getWrappedField();
    Code:
       0: aload_0
       1: getfield      #6                  // Field iField:Lorg/joda/time/DurationField;
       4: areturn

  public org.joda.time.DurationFieldType getType();
    Code:
       0: aload_0
       1: getfield      #8                  // Field iType:Lorg/joda/time/DurationFieldType;
       4: areturn

  public java.lang.String getName();
    Code:
       0: aload_0
       1: getfield      #8                  // Field iType:Lorg/joda/time/DurationFieldType;
       4: invokevirtual #9                  // Method org/joda/time/DurationFieldType.getName:()Ljava/lang/String;
       7: areturn

  public boolean isSupported();
    Code:
       0: aload_0
       1: getfield      #6                  // Field iField:Lorg/joda/time/DurationField;
       4: invokevirtual #10                 // Method org/joda/time/DurationField.isSupported:()Z
       7: ireturn

  public boolean isPrecise();
    Code:
       0: aload_0
       1: getfield      #6                  // Field iField:Lorg/joda/time/DurationField;
       4: invokevirtual #11                 // Method org/joda/time/DurationField.isPrecise:()Z
       7: ireturn

  public int getValue(long);
    Code:
       0: aload_0
       1: getfield      #6                  // Field iField:Lorg/joda/time/DurationField;
       4: lload_1
       5: invokevirtual #12                 // Method org/joda/time/DurationField.getValue:(J)I
       8: ireturn

  public long getValueAsLong(long);
    Code:
       0: aload_0
       1: getfield      #6                  // Field iField:Lorg/joda/time/DurationField;
       4: lload_1
       5: invokevirtual #13                 // Method org/joda/time/DurationField.getValueAsLong:(J)J
       8: lreturn

  public int getValue(long, long);
    Code:
       0: aload_0
       1: getfield      #6                  // Field iField:Lorg/joda/time/DurationField;
       4: lload_1
       5: lload_3
       6: invokevirtual #14                 // Method org/joda/time/DurationField.getValue:(JJ)I
       9: ireturn

  public long getValueAsLong(long, long);
    Code:
       0: aload_0
       1: getfield      #6                  // Field iField:Lorg/joda/time/DurationField;
       4: lload_1
       5: lload_3
       6: invokevirtual #15                 // Method org/joda/time/DurationField.getValueAsLong:(JJ)J
       9: lreturn

  public long getMillis(int);
    Code:
       0: aload_0
       1: getfield      #6                  // Field iField:Lorg/joda/time/DurationField;
       4: iload_1
       5: invokevirtual #16                 // Method org/joda/time/DurationField.getMillis:(I)J
       8: lreturn

  public long getMillis(long);
    Code:
       0: aload_0
       1: getfield      #6                  // Field iField:Lorg/joda/time/DurationField;
       4: lload_1
       5: invokevirtual #17                 // Method org/joda/time/DurationField.getMillis:(J)J
       8: lreturn

  public long getMillis(int, long);
    Code:
       0: aload_0
       1: getfield      #6                  // Field iField:Lorg/joda/time/DurationField;
       4: iload_1
       5: lload_2
       6: invokevirtual #18                 // Method org/joda/time/DurationField.getMillis:(IJ)J
       9: lreturn

  public long getMillis(long, long);
    Code:
       0: aload_0
       1: getfield      #6                  // Field iField:Lorg/joda/time/DurationField;
       4: lload_1
       5: lload_3
       6: invokevirtual #19                 // Method org/joda/time/DurationField.getMillis:(JJ)J
       9: lreturn

  public long add(long, int);
    Code:
       0: aload_0
       1: getfield      #6                  // Field iField:Lorg/joda/time/DurationField;
       4: lload_1
       5: iload_3
       6: invokevirtual #20                 // Method org/joda/time/DurationField.add:(JI)J
       9: lreturn

  public long add(long, long);
    Code:
       0: aload_0
       1: getfield      #6                  // Field iField:Lorg/joda/time/DurationField;
       4: lload_1
       5: lload_3
       6: invokevirtual #21                 // Method org/joda/time/DurationField.add:(JJ)J
       9: lreturn

  public int getDifference(long, long);
    Code:
       0: aload_0
       1: getfield      #6                  // Field iField:Lorg/joda/time/DurationField;
       4: lload_1
       5: lload_3
       6: invokevirtual #22                 // Method org/joda/time/DurationField.getDifference:(JJ)I
       9: ireturn

  public long getDifferenceAsLong(long, long);
    Code:
       0: aload_0
       1: getfield      #6                  // Field iField:Lorg/joda/time/DurationField;
       4: lload_1
       5: lload_3
       6: invokevirtual #23                 // Method org/joda/time/DurationField.getDifferenceAsLong:(JJ)J
       9: lreturn

  public long getUnitMillis();
    Code:
       0: aload_0
       1: getfield      #6                  // Field iField:Lorg/joda/time/DurationField;
       4: invokevirtual #24                 // Method org/joda/time/DurationField.getUnitMillis:()J
       7: lreturn

  public int compareTo(org.joda.time.DurationField);
    Code:
       0: aload_0
       1: getfield      #6                  // Field iField:Lorg/joda/time/DurationField;
       4: aload_1
       5: invokevirtual #25                 // Method org/joda/time/DurationField.compareTo:(Ljava/lang/Object;)I
       8: ireturn

  public boolean equals(java.lang.Object);
    Code:
       0: aload_1
       1: instanceof    #26                 // class org/joda/time/field/DelegatedDurationField
       4: ifeq          22
       7: aload_0
       8: getfield      #6                  // Field iField:Lorg/joda/time/DurationField;
      11: aload_1
      12: checkcast     #26                 // class org/joda/time/field/DelegatedDurationField
      15: getfield      #6                  // Field iField:Lorg/joda/time/DurationField;
      18: invokevirtual #27                 // Method java/lang/Object.equals:(Ljava/lang/Object;)Z
      21: ireturn
      22: iconst_0
      23: ireturn

  public int hashCode();
    Code:
       0: aload_0
       1: getfield      #6                  // Field iField:Lorg/joda/time/DurationField;
       4: invokevirtual #28                 // Method java/lang/Object.hashCode:()I
       7: aload_0
       8: getfield      #8                  // Field iType:Lorg/joda/time/DurationFieldType;
      11: invokevirtual #28                 // Method java/lang/Object.hashCode:()I
      14: ixor
      15: ireturn

  public java.lang.String toString();
    Code:
       0: aload_0
       1: getfield      #8                  // Field iType:Lorg/joda/time/DurationFieldType;
       4: ifnonnull     17
       7: aload_0
       8: getfield      #6                  // Field iField:Lorg/joda/time/DurationField;
      11: invokevirtual #29                 // Method org/joda/time/DurationField.toString:()Ljava/lang/String;
      14: goto          44
      17: new           #30                 // class java/lang/StringBuilder
      20: dup
      21: invokespecial #31                 // Method java/lang/StringBuilder."<init>":()V
      24: ldc           #32                 // String DurationField[
      26: invokevirtual #33                 // Method java/lang/StringBuilder.append:(Ljava/lang/String;)Ljava/lang/StringBuilder;
      29: aload_0
      30: getfield      #8                  // Field iType:Lorg/joda/time/DurationFieldType;
      33: invokevirtual #34                 // Method java/lang/StringBuilder.append:(Ljava/lang/Object;)Ljava/lang/StringBuilder;
      36: bipush        93
      38: invokevirtual #35                 // Method java/lang/StringBuilder.append:(C)Ljava/lang/StringBuilder;
      41: invokevirtual #36                 // Method java/lang/StringBuilder.toString:()Ljava/lang/String;
      44: areturn

  public int compareTo(java.lang.Object);
    Code:
       0: aload_0
       1: aload_1
       2: checkcast     #37                 // class org/joda/time/DurationField
       5: invokevirtual #38                 // Method compareTo:(Lorg/joda/time/DurationField;)I
       8: ireturn
}
