Compiled from "ApplicationConfiguration.java"
public class org.atmosphere.config.ApplicationConfiguration {
  private java.lang.String paramName;

  private java.lang.String paramValue;

  public org.atmosphere.config.ApplicationConfiguration(java.lang.String, java.lang.String);
    Code:
       0: aload_0
       1: invokespecial #1                  // Method java/lang/Object."<init>":()V
       4: aload_0
       5: aload_1
       6: putfield      #2                  // Field paramName:Ljava/lang/String;
       9: aload_0
      10: aload_2
      11: putfield      #3                  // Field paramValue:Ljava/lang/String;
      14: return

  public java.lang.String getParamName();
    Code:
       0: aload_0
       1: getfield      #2                  // Field paramName:Ljava/lang/String;
       4: areturn

  public void setParamName(java.lang.String);
    Code:
       0: aload_0
       1: aload_1
       2: putfield      #2                  // Field paramName:Ljava/lang/String;
       5: return

  public java.lang.String getParamValue();
    Code:
       0: aload_0
       1: getfield      #3                  // Field paramValue:Ljava/lang/String;
       4: areturn

  public void setParamValue(java.lang.String);
    Code:
       0: aload_0
       1: aload_1
       2: putfield      #3                  // Field paramValue:Ljava/lang/String;
       5: return
}
