Compiled from "StringEncoderComparator.java"
public class io.dekorate.deps.commons.codec.StringEncoderComparator implements java.util.Comparator {
  private final io.dekorate.deps.commons.codec.StringEncoder stringEncoder;

  public io.dekorate.deps.commons.codec.StringEncoderComparator();
    Code:
       0: aload_0
       1: invokespecial #14                 // Method java/lang/Object."<init>":()V
       4: aload_0
       5: aconst_null
       6: putfield      #16                 // Field stringEncoder:Lio/dekorate/deps/commons/codec/StringEncoder;
       9: return

  public io.dekorate.deps.commons.codec.StringEncoderComparator(io.dekorate.deps.commons.codec.StringEncoder);
    Code:
       0: aload_0
       1: invokespecial #14                 // Method java/lang/Object."<init>":()V
       4: aload_0
       5: aload_1
       6: putfield      #16                 // Field stringEncoder:Lio/dekorate/deps/commons/codec/StringEncoder;
       9: return

  public int compare(java.lang.Object, java.lang.Object);
    Code:
       0: iconst_0
       1: istore_3
       2: aload_0
       3: getfield      #16                 // Field stringEncoder:Lio/dekorate/deps/commons/codec/StringEncoder;
       6: aload_1
       7: invokeinterface #29,  2           // InterfaceMethod io/dekorate/deps/commons/codec/StringEncoder.encode:(Ljava/lang/Object;)Ljava/lang/Object;
      12: checkcast     #31                 // class java/lang/Comparable
      15: astore        4
      17: aload_0
      18: getfield      #16                 // Field stringEncoder:Lio/dekorate/deps/commons/codec/StringEncoder;
      21: aload_2
      22: invokeinterface #29,  2           // InterfaceMethod io/dekorate/deps/commons/codec/StringEncoder.encode:(Ljava/lang/Object;)Ljava/lang/Object;
      27: checkcast     #31                 // class java/lang/Comparable
      30: astore        5
      32: aload         4
      34: aload         5
      36: invokeinterface #35,  2           // InterfaceMethod java/lang/Comparable.compareTo:(Ljava/lang/Object;)I
      41: istore_3
      42: goto          49
      45: astore        4
      47: iconst_0
      48: istore_3
      49: iload_3
      50: ireturn
    Exception table:
       from    to  target type
           2    42    45   Class io/dekorate/deps/commons/codec/EncoderException
}
