Compiled from "ChangeToPerspectiveMenu.java"
public class org.eclipse.ui.internal.ChangeToPerspectiveMenu extends org.eclipse.ui.actions.PerspectiveMenu {
  public org.eclipse.ui.internal.ChangeToPerspectiveMenu(org.eclipse.ui.IWorkbenchWindow, java.lang.String);
    Code:
       0: aload_0
       1: aload_1
       2: aload_2
       3: invokespecial #146                // Method org/eclipse/ui/actions/PerspectiveMenu."<init>":(Lorg/eclipse/ui/IWorkbenchWindow;Ljava/lang/String;)V
       6: aload_1
       7: instanceof    #92                 // class org/eclipse/ui/internal/WorkbenchWindow
      10: ifeq          21
      13: aload_1
      14: checkcast     #92                 // class org/eclipse/ui/internal/WorkbenchWindow
      17: iconst_2
      18: invokevirtual #149                // Method org/eclipse/ui/internal/WorkbenchWindow.addSubmenu:(I)V
      21: aload_0
      22: iconst_1
      23: invokevirtual #147                // Method showActive:(Z)V
      26: return

  protected void run(org.eclipse.ui.IPerspectiveDescriptor);
    Code:
       0: invokestatic  #150                // Method org/eclipse/ui/internal/util/PrefUtil.getInternalPreferenceStore:()Lorg/eclipse/jface/preference/IPreferenceStore;
       3: astore_2
       4: aload_2
       5: ldc           #2                  // String OPEN_PERSPECTIVE_MODE
       7: invokeinterface #154,  2          // InterfaceMethod org/eclipse/jface/preference/IPreferenceStore.getInt:(Ljava/lang/String;)I
      12: istore_3
      13: aload_0
      14: invokevirtual #148                // Method getWindow:()Lorg/eclipse/ui/IWorkbenchWindow;
      17: invokeinterface #157,  1          // InterfaceMethod org/eclipse/ui/IWorkbenchWindow.getActivePage:()Lorg/eclipse/ui/IWorkbenchPage;
      22: astore        4
      24: aconst_null
      25: astore        5
      27: aload         4
      29: ifnull        41
      32: aload         4
      34: invokeinterface #156,  1          // InterfaceMethod org/eclipse/ui/IWorkbenchPage.getPerspective:()Lorg/eclipse/ui/IPerspectiveDescriptor;
      39: astore        5
      41: aload_0
      42: invokevirtual #148                // Method getWindow:()Lorg/eclipse/ui/IWorkbenchWindow;
      45: ldc           #8                  // class org/eclipse/ui/handlers/IHandlerService
      47: invokeinterface #158,  2          // InterfaceMethod org/eclipse/ui/IWorkbenchWindow.getService:(Ljava/lang/Class;)Ljava/lang/Object;
      52: checkcast     #8                  // class org/eclipse/ui/handlers/IHandlerService
      55: astore        6
      57: aload_0
      58: invokevirtual #148                // Method getWindow:()Lorg/eclipse/ui/IWorkbenchWindow;
      61: ldc           #7                  // class org/eclipse/ui/commands/ICommandService
      63: invokeinterface #158,  2          // InterfaceMethod org/eclipse/ui/IWorkbenchWindow.getService:(Ljava/lang/Class;)Ljava/lang/Object;
      68: checkcast     #7                  // class org/eclipse/ui/commands/ICommandService
      71: astore        7
      73: aload         7
      75: ldc           #3                  // String org.eclipse.ui.perspectives.showPerspective
      77: invokeinterface #159,  2          // InterfaceMethod org/eclipse/ui/commands/ICommandService.getCommand:(Ljava/lang/String;)Lorg/eclipse/core/commands/Command;
      82: astore        8
      84: new           #75                 // class java/util/HashMap
      87: dup
      88: invokespecial #143                // Method java/util/HashMap."<init>":()V
      91: astore        9
      93: aload         9
      95: ldc           #5                  // String org.eclipse.ui.perspectives.showPerspective.perspectiveId
      97: aload_1
      98: invokeinterface #155,  1          // InterfaceMethod org/eclipse/ui/IPerspectiveDescriptor.getId:()Ljava/lang/String;
     103: invokeinterface #153,  3          // InterfaceMethod java/util/Map.put:(Ljava/lang/Object;Ljava/lang/Object;)Ljava/lang/Object;
     108: pop
     109: iconst_2
     110: iload_3
     111: if_icmpne     131
     114: aload         5
     116: ifnull        131
     119: aload         9
     121: ldc           #4                  // String org.eclipse.ui.perspectives.showPerspective.newWindow
     123: ldc           #6                  // String true
     125: invokeinterface #153,  3          // InterfaceMethod java/util/Map.put:(Ljava/lang/Object;Ljava/lang/Object;)Ljava/lang/Object;
     130: pop
     131: aload         8
     133: aload         9
     135: invokestatic  #144                // Method org/eclipse/core/commands/ParameterizedCommand.generateCommand:(Lorg/eclipse/core/commands/Command;Ljava/util/Map;)Lorg/eclipse/core/commands/ParameterizedCommand;
     138: astore        10
     140: aload         6
     142: aload         10
     144: aconst_null
     145: invokeinterface #160,  3          // InterfaceMethod org/eclipse/ui/handlers/IHandlerService.executeCommand:(Lorg/eclipse/core/commands/ParameterizedCommand;Lorg/eclipse/swt/widgets/Event;)Ljava/lang/Object;
     150: pop
     151: goto          177
     154: astore        11
     156: invokestatic  #152                // Method org/eclipse/ui/statushandlers/StatusManager.getManager:()Lorg/eclipse/ui/statushandlers/StatusManager;
     159: new           #84                 // class org/eclipse/core/runtime/Status
     162: dup
     163: iconst_2
     164: getstatic     #142                // Field org/eclipse/ui/internal/WorkbenchPlugin.PI_WORKBENCH:Ljava/lang/String;
     167: ldc           #1                  // String Failed to execute org.eclipse.ui.perspectives.showPerspective
     169: aload         11
     171: invokespecial #145                // Method org/eclipse/core/runtime/Status."<init>":(ILjava/lang/String;Ljava/lang/String;Ljava/lang/Throwable;)V
     174: invokevirtual #151                // Method org/eclipse/ui/statushandlers/StatusManager.handle:(Lorg/eclipse/core/runtime/IStatus;)V
     177: return
    Exception table:
       from    to  target type
         140   151   154   Class org/eclipse/core/commands/ExecutionException
         140   151   154   Class org/eclipse/core/commands/common/NotDefinedException
         140   151   154   Class org/eclipse/core/commands/NotEnabledException
         140   151   154   Class org/eclipse/core/commands/NotHandledException
}
