Compiled from "EditorActionBuilder.java"
class org.eclipse.ui.internal.EditorActionBuilder$EditorContribution extends org.eclipse.ui.internal.PluginActionBuilder$BasicContribution {
  private org.eclipse.ui.internal.EditorActionBuilder$EditorContribution();
    Code:
       0: aload_0
       1: invokespecial #58                 // Method org/eclipse/ui/internal/PluginActionBuilder$BasicContribution."<init>":()V
       4: return

  public void dispose();
    Code:
       0: aload_0
       1: invokevirtual #56                 // Method disposeActions:()V
       4: aload_0
       5: invokespecial #59                 // Method org/eclipse/ui/internal/PluginActionBuilder$BasicContribution.dispose:()V
       8: return

  public void editorChanged(org.eclipse.ui.IEditorPart);
    Code:
       0: aload_0
       1: getfield      #53                 // Field actions:Ljava/util/ArrayList;
       4: ifnull        52
       7: aload_0
       8: getfield      #53                 // Field actions:Ljava/util/ArrayList;
      11: invokevirtual #54                 // Method java/util/ArrayList.iterator:()Ljava/util/Iterator;
      14: astore_3
      15: goto          43
      18: aload_3
      19: invokeinterface #61,  1           // InterfaceMethod java/util/Iterator.next:()Ljava/lang/Object;
      24: checkcast     #29                 // class org/eclipse/ui/internal/ActionDescriptor
      27: astore_2
      28: aload_2
      29: invokevirtual #55                 // Method org/eclipse/ui/internal/ActionDescriptor.getAction:()Lorg/eclipse/ui/internal/PluginAction;
      32: checkcast     #32                 // class org/eclipse/ui/internal/EditorPluginAction
      35: astore        4
      37: aload         4
      39: aload_1
      40: invokevirtual #57                 // Method org/eclipse/ui/internal/EditorPluginAction.editorChanged:(Lorg/eclipse/ui/IEditorPart;)V
      43: aload_3
      44: invokeinterface #60,  1           // InterfaceMethod java/util/Iterator.hasNext:()Z
      49: ifne          18
      52: return
}
