Compiled from "ExtensionEventHandler.java"
class org.eclipse.ui.internal.ExtensionEventHandler implements org.eclipse.core.runtime.IRegistryChangeListener {
  private org.eclipse.ui.internal.Workbench workbench;

  private java.util.List<?> changeList;

  public org.eclipse.ui.internal.ExtensionEventHandler(org.eclipse.ui.internal.Workbench);
    Code:
       0: aload_0
       1: invokespecial #329                // Method java/lang/Object."<init>":()V
       4: aload_0
       5: new           #159                // class java/util/ArrayList
       8: dup
       9: bipush        10
      11: invokespecial #339                // Method java/util/ArrayList."<init>":(I)V
      14: putfield      #323                // Field changeList:Ljava/util/List;
      17: aload_0
      18: aload_1
      19: putfield      #324                // Field workbench:Lorg/eclipse/ui/internal/Workbench;
      22: return

  public void registryChanged(org.eclipse.core.runtime.IRegistryChangeEvent);
    Code:
       0: aload_1
       1: getstatic     #328                // Field org/eclipse/ui/internal/WorkbenchPlugin.PI_WORKBENCH:Ljava/lang/String;
       4: invokeinterface #383,  2          // InterfaceMethod org/eclipse/core/runtime/IRegistryChangeEvent.getExtensionDeltas:(Ljava/lang/String;)[Lorg/eclipse/core/runtime/IExtensionDelta;
       9: astore_2
      10: invokestatic  #347                // Method org/eclipse/ui/PlatformUI.getWorkbench:()Lorg/eclipse/ui/IWorkbench;
      13: invokeinterface #384,  1          // InterfaceMethod org/eclipse/ui/IWorkbench.getWorkbenchWindows:()[Lorg/eclipse/ui/IWorkbenchWindow;
      18: astore        5
      20: aload         5
      22: arraylength
      23: ifne          36
      26: aload_0
      27: getfield      #323                // Field changeList:Ljava/util/List;
      30: invokeinterface #375,  1          // InterfaceMethod java/util/List.clear:()V
      35: return
      36: aload         5
      38: iconst_0
      39: aaload
      40: invokeinterface #386,  1          // InterfaceMethod org/eclipse/ui/IWorkbenchWindow.getShell:()Lorg/eclipse/swt/widgets/Shell;
      45: invokevirtual #346                // Method org/eclipse/swt/widgets/Shell.getDisplay:()Lorg/eclipse/swt/widgets/Display;
      48: astore        6
      50: aload         6
      52: ifnonnull     65
      55: aload_0
      56: getfield      #323                // Field changeList:Ljava/util/List;
      59: invokeinterface #375,  1          // InterfaceMethod java/util/List.clear:()V
      64: return
      65: new           #159                // class java/util/ArrayList
      68: dup
      69: iconst_5
      70: invokespecial #339                // Method java/util/ArrayList."<init>":(I)V
      73: astore        7
      75: new           #159                // class java/util/ArrayList
      78: dup
      79: iconst_5
      80: invokespecial #339                // Method java/util/ArrayList."<init>":(I)V
      83: astore        8
      85: aconst_null
      86: astore        9
      88: iconst_0
      89: istore        10
      91: iconst_0
      92: istore        11
      94: aload_2
      95: dup
      96: astore        15
      98: arraylength
      99: istore        14
     101: iconst_0
     102: istore        13
     104: goto          315
     107: aload         15
     109: iload         13
     111: aaload
     112: astore        12
     114: aload         12
     116: invokeinterface #381,  1          // InterfaceMethod org/eclipse/core/runtime/IExtensionDelta.getExtensionPoint:()Lorg/eclipse/core/runtime/IExtensionPoint;
     121: invokeinterface #382,  1          // InterfaceMethod org/eclipse/core/runtime/IExtensionPoint.getSimpleIdentifier:()Ljava/lang/String;
     126: astore        9
     128: aload         12
     130: invokeinterface #379,  1          // InterfaceMethod org/eclipse/core/runtime/IExtensionDelta.getKind:()I
     135: iconst_1
     136: if_icmpne     208
     139: aload         9
     141: ldc           #2                  // String actionSets
     143: invokevirtual #331                // Method java/lang/String.equals:(Ljava/lang/Object;)Z
     146: ifeq          160
     149: aload         7
     151: iconst_0
     152: aload         12
     154: invokevirtual #340                // Method java/util/ArrayList.add:(ILjava/lang/Object;)V
     157: goto          312
     160: aload         9
     162: ldc           #5                  // String perspectives
     164: invokevirtual #331                // Method java/lang/String.equals:(Ljava/lang/Object;)Z
     167: ifne          312
     170: aload         9
     172: ldc           #7                  // String views
     174: invokevirtual #331                // Method java/lang/String.equals:(Ljava/lang/Object;)Z
     177: ifne          312
     180: aload         9
     182: ldc           #2                  // String actionSets
     184: invokevirtual #331                // Method java/lang/String.equals:(Ljava/lang/Object;)Z
     187: ifne          312
     190: aload         7
     192: aload         7
     194: invokevirtual #338                // Method java/util/ArrayList.size:()I
     197: iload         10
     199: isub
     200: aload         12
     202: invokevirtual #340                // Method java/util/ArrayList.add:(ILjava/lang/Object;)V
     205: goto          312
     208: aload         12
     210: invokeinterface #379,  1          // InterfaceMethod org/eclipse/core/runtime/IExtensionDelta.getKind:()I
     215: iconst_2
     216: if_icmpne     312
     219: aload         9
     221: dup
     222: astore        16
     224: invokevirtual #330                // Method java/lang/String.hashCode:()I
     227: lookupswitch  { // 2
           -2143154761: 252
           -1227565551: 265
               default: 304
          }
     252: aload         16
     254: ldc           #5                  // String perspectives
     256: invokevirtual #331                // Method java/lang/String.equals:(Ljava/lang/Object;)Z
     259: ifne          292
     262: goto          304
     265: aload         16
     267: ldc           #1                  // String actionSetPartAssociations
     269: invokevirtual #331                // Method java/lang/String.equals:(Ljava/lang/Object;)Z
     272: ifne          278
     275: goto          304
     278: aload         8
     280: iconst_0
     281: aload         12
     283: invokevirtual #340                // Method java/util/ArrayList.add:(ILjava/lang/Object;)V
     286: iinc          11, 1
     289: goto          312
     292: aload         8
     294: iload         11
     296: aload         12
     298: invokevirtual #340                // Method java/util/ArrayList.add:(ILjava/lang/Object;)V
     301: goto          312
     304: aload         8
     306: aload         12
     308: invokevirtual #341                // Method java/util/ArrayList.add:(Ljava/lang/Object;)Z
     311: pop
     312: iinc          13, 1
     315: iload         13
     317: iload         14
     319: if_icmplt     107
     322: aload         7
     324: invokevirtual #342                // Method java/util/ArrayList.iterator:()Ljava/util/Iterator;
     327: astore        12
     329: aconst_null
     330: astore        13
     332: goto          373
     335: aload         12
     337: invokeinterface #374,  1          // InterfaceMethod java/util/Iterator.next:()Ljava/lang/Object;
     342: checkcast     #164                // class org/eclipse/core/runtime/IExtensionDelta
     345: astore        13
     347: aload         13
     349: invokeinterface #381,  1          // InterfaceMethod org/eclipse/core/runtime/IExtensionDelta.getExtensionPoint:()Lorg/eclipse/core/runtime/IExtensionPoint;
     354: astore        4
     356: aload         13
     358: invokeinterface #380,  1          // InterfaceMethod org/eclipse/core/runtime/IExtensionDelta.getExtension:()Lorg/eclipse/core/runtime/IExtension;
     363: astore_3
     364: aload_0
     365: aload         6
     367: aload         4
     369: aload_3
     370: invokevirtual #354                // Method asyncAppear:(Lorg/eclipse/swt/widgets/Display;Lorg/eclipse/core/runtime/IExtensionPoint;Lorg/eclipse/core/runtime/IExtension;)V
     373: aload         12
     375: invokeinterface #373,  1          // InterfaceMethod java/util/Iterator.hasNext:()Z
     380: ifne          335
     383: aload_0
     384: aload         6
     386: invokevirtual #351                // Method resetCurrentPerspective:(Lorg/eclipse/swt/widgets/Display;)V
     389: goto          406
     392: astore        17
     394: aload_0
     395: getfield      #323                // Field changeList:Ljava/util/List;
     398: invokeinterface #375,  1          // InterfaceMethod java/util/List.clear:()V
     403: aload         17
     405: athrow
     406: aload_0
     407: getfield      #323                // Field changeList:Ljava/util/List;
     410: invokeinterface #375,  1          // InterfaceMethod java/util/List.clear:()V
     415: return
    Exception table:
       from    to  target type
           0    26   392   any
          36    55   392   any
          65   392   392   any

  private void asyncAppear(org.eclipse.swt.widgets.Display, org.eclipse.core.runtime.IExtensionPoint, org.eclipse.core.runtime.IExtension);
    Code:
       0: aload_0
       1: aload_2
       2: aload_3
       3: invokedynamic #394,  0            // InvokeDynamic #1:run:(Lorg/eclipse/ui/internal/ExtensionEventHandler;Lorg/eclipse/core/runtime/IExtensionPoint;Lorg/eclipse/core/runtime/IExtension;)Ljava/lang/Runnable;
       8: astore        4
      10: aload_1
      11: aload         4
      13: invokevirtual #345                // Method org/eclipse/swt/widgets/Display.syncExec:(Ljava/lang/Runnable;)V
      16: return

  private void appear(org.eclipse.core.runtime.IExtensionPoint, org.eclipse.core.runtime.IExtension);
    Code:
       0: aload_1
       1: invokeinterface #382,  1          // InterfaceMethod org/eclipse/core/runtime/IExtensionPoint.getSimpleIdentifier:()Ljava/lang/String;
       6: astore_3
       7: aload_3
       8: ldc           #3                  // String fontDefinitions
      10: invokevirtual #332                // Method java/lang/String.equalsIgnoreCase:(Ljava/lang/String;)Z
      13: ifeq          22
      16: aload_0
      17: aload_2
      18: invokevirtual #349                // Method loadFontDefinitions:(Lorg/eclipse/core/runtime/IExtension;)V
      21: return
      22: aload_3
      23: ldc           #6                  // String themes
      25: invokevirtual #332                // Method java/lang/String.equalsIgnoreCase:(Ljava/lang/String;)Z
      28: ifeq          37
      31: aload_0
      32: aload_2
      33: invokevirtual #350                // Method loadThemes:(Lorg/eclipse/core/runtime/IExtension;)V
      36: return
      37: return

  private void loadFontDefinitions(org.eclipse.core.runtime.IExtension);
    Code:
       0: new           #183                // class org/eclipse/ui/internal/themes/ThemeRegistryReader
       3: dup
       4: invokespecial #364                // Method org/eclipse/ui/internal/themes/ThemeRegistryReader."<init>":()V
       7: astore_2
       8: aload_2
       9: invokestatic  #359                // Method org/eclipse/ui/internal/WorkbenchPlugin.getDefault:()Lorg/eclipse/ui/internal/WorkbenchPlugin;
      12: invokevirtual #360                // Method org/eclipse/ui/internal/WorkbenchPlugin.getThemeRegistry:()Lorg/eclipse/ui/internal/themes/IThemeRegistry;
      15: checkcast     #182                // class org/eclipse/ui/internal/themes/ThemeRegistry
      18: invokevirtual #369                // Method org/eclipse/ui/internal/themes/ThemeRegistryReader.setRegistry:(Lorg/eclipse/ui/internal/themes/ThemeRegistry;)V
      21: aload_1
      22: invokeinterface #378,  1          // InterfaceMethod org/eclipse/core/runtime/IExtension.getConfigurationElements:()[Lorg/eclipse/core/runtime/IConfigurationElement;
      27: dup
      28: astore        6
      30: arraylength
      31: istore        5
      33: iconst_0
      34: istore        4
      36: goto          54
      39: aload         6
      41: iload         4
      43: aaload
      44: astore_3
      45: aload_2
      46: aload_3
      47: invokevirtual #368                // Method org/eclipse/ui/internal/themes/ThemeRegistryReader.readElement:(Lorg/eclipse/core/runtime/IConfigurationElement;)Z
      50: pop
      51: iinc          4, 1
      54: iload         4
      56: iload         5
      58: if_icmplt     39
      61: aload_2
      62: invokevirtual #366                // Method org/eclipse/ui/internal/themes/ThemeRegistryReader.getFontDefinitions:()Ljava/util/Collection;
      65: astore_3
      66: aload_3
      67: aload_3
      68: invokeinterface #371,  1          // InterfaceMethod java/util/Collection.size:()I
      73: anewarray     #180                // class org/eclipse/ui/internal/themes/FontDefinition
      76: invokeinterface #372,  2          // InterfaceMethod java/util/Collection.toArray:([Ljava/lang/Object;)[Ljava/lang/Object;
      81: checkcast     #152                // class "[Lorg/eclipse/ui/internal/themes/FontDefinition;"
      84: astore        4
      86: aload_0
      87: getfield      #324                // Field workbench:Lorg/eclipse/ui/internal/Workbench;
      90: invokevirtual #358                // Method org/eclipse/ui/internal/Workbench.getThemeManager:()Lorg/eclipse/ui/themes/IThemeManager;
      93: ldc           #4                  // String org.eclipse.ui.defaultTheme
      95: invokeinterface #388,  2          // InterfaceMethod org/eclipse/ui/themes/IThemeManager.getTheme:(Ljava/lang/String;)Lorg/eclipse/ui/themes/ITheme;
     100: aload         4
     102: invokestatic  #370                // Method org/eclipse/ui/internal/util/PrefUtil.getInternalPreferenceStore:()Lorg/eclipse/jface/preference/IPreferenceStore;
     105: invokestatic  #362                // Method org/eclipse/ui/internal/themes/ThemeElementHelper.populateRegistry:(Lorg/eclipse/ui/themes/ITheme;[Lorg/eclipse/ui/internal/themes/FontDefinition;Lorg/eclipse/jface/preference/IPreferenceStore;)V
     108: return

  private void loadThemes(org.eclipse.core.runtime.IExtension);
    Code:
       0: new           #183                // class org/eclipse/ui/internal/themes/ThemeRegistryReader
       3: dup
       4: invokespecial #364                // Method org/eclipse/ui/internal/themes/ThemeRegistryReader."<init>":()V
       7: astore_2
       8: invokestatic  #359                // Method org/eclipse/ui/internal/WorkbenchPlugin.getDefault:()Lorg/eclipse/ui/internal/WorkbenchPlugin;
      11: invokevirtual #360                // Method org/eclipse/ui/internal/WorkbenchPlugin.getThemeRegistry:()Lorg/eclipse/ui/internal/themes/IThemeRegistry;
      14: checkcast     #182                // class org/eclipse/ui/internal/themes/ThemeRegistry
      17: astore_3
      18: aload_2
      19: aload_3
      20: invokevirtual #369                // Method org/eclipse/ui/internal/themes/ThemeRegistryReader.setRegistry:(Lorg/eclipse/ui/internal/themes/ThemeRegistry;)V
      23: aload_1
      24: invokeinterface #378,  1          // InterfaceMethod org/eclipse/core/runtime/IExtension.getConfigurationElements:()[Lorg/eclipse/core/runtime/IConfigurationElement;
      29: dup
      30: astore        7
      32: arraylength
      33: istore        6
      35: iconst_0
      36: istore        5
      38: goto          58
      41: aload         7
      43: iload         5
      45: aaload
      46: astore        4
      48: aload_2
      49: aload         4
      51: invokevirtual #368                // Method org/eclipse/ui/internal/themes/ThemeRegistryReader.readElement:(Lorg/eclipse/core/runtime/IConfigurationElement;)Z
      54: pop
      55: iinc          5, 1
      58: iload         5
      60: iload         6
      62: if_icmplt     41
      65: aload_2
      66: invokevirtual #365                // Method org/eclipse/ui/internal/themes/ThemeRegistryReader.getColorDefinitions:()Ljava/util/Collection;
      69: astore        4
      71: aload         4
      73: aload         4
      75: invokeinterface #371,  1          // InterfaceMethod java/util/Collection.size:()I
      80: anewarray     #179                // class org/eclipse/ui/internal/themes/ColorDefinition
      83: invokeinterface #372,  2          // InterfaceMethod java/util/Collection.toArray:([Ljava/lang/Object;)[Ljava/lang/Object;
      88: checkcast     #151                // class "[Lorg/eclipse/ui/internal/themes/ColorDefinition;"
      91: astore        5
      93: aload_0
      94: getfield      #324                // Field workbench:Lorg/eclipse/ui/internal/Workbench;
      97: invokevirtual #358                // Method org/eclipse/ui/internal/Workbench.getThemeManager:()Lorg/eclipse/ui/themes/IThemeManager;
     100: ldc           #4                  // String org.eclipse.ui.defaultTheme
     102: invokeinterface #388,  2          // InterfaceMethod org/eclipse/ui/themes/IThemeManager.getTheme:(Ljava/lang/String;)Lorg/eclipse/ui/themes/ITheme;
     107: astore        6
     109: aload         6
     111: aload         5
     113: invokestatic  #370                // Method org/eclipse/ui/internal/util/PrefUtil.getInternalPreferenceStore:()Lorg/eclipse/jface/preference/IPreferenceStore;
     116: invokestatic  #361                // Method org/eclipse/ui/internal/themes/ThemeElementHelper.populateRegistry:(Lorg/eclipse/ui/themes/ITheme;[Lorg/eclipse/ui/internal/themes/ColorDefinition;Lorg/eclipse/jface/preference/IPreferenceStore;)V
     119: aload_2
     120: invokevirtual #366                // Method org/eclipse/ui/internal/themes/ThemeRegistryReader.getFontDefinitions:()Ljava/util/Collection;
     123: astore        7
     125: aload         7
     127: aload         7
     129: invokeinterface #371,  1          // InterfaceMethod java/util/Collection.size:()I
     134: anewarray     #180                // class org/eclipse/ui/internal/themes/FontDefinition
     137: invokeinterface #372,  2          // InterfaceMethod java/util/Collection.toArray:([Ljava/lang/Object;)[Ljava/lang/Object;
     142: checkcast     #152                // class "[Lorg/eclipse/ui/internal/themes/FontDefinition;"
     145: astore        8
     147: aload         6
     149: aload         8
     151: invokestatic  #370                // Method org/eclipse/ui/internal/util/PrefUtil.getInternalPreferenceStore:()Lorg/eclipse/jface/preference/IPreferenceStore;
     154: invokestatic  #362                // Method org/eclipse/ui/internal/themes/ThemeElementHelper.populateRegistry:(Lorg/eclipse/ui/themes/ITheme;[Lorg/eclipse/ui/internal/themes/FontDefinition;Lorg/eclipse/jface/preference/IPreferenceStore;)V
     157: aload_2
     158: invokevirtual #367                // Method org/eclipse/ui/internal/themes/ThemeRegistryReader.getData:()Ljava/util/Map;
     161: astore        9
     163: aload_3
     164: aload         9
     166: invokevirtual #363                // Method org/eclipse/ui/internal/themes/ThemeRegistry.addData:(Ljava/util/Map;)V
     169: return

  private void resetCurrentPerspective(org.eclipse.swt.widgets.Display);
    Code:
       0: aload_0
       1: getfield      #323                // Field changeList:Ljava/util/List;
       4: invokeinterface #376,  1          // InterfaceMethod java/util/List.isEmpty:()Z
       9: ifeq          13
      12: return
      13: new           #155                // class java/lang/StringBuilder
      16: dup
      17: getstatic     #325                // Field org/eclipse/ui/internal/ExtensionEventHandlerMessages.ExtensionEventHandler_following_changes:Ljava/lang/String;
      20: invokespecial #334                // Method java/lang/StringBuilder."<init>":(Ljava/lang/String;)V
      23: astore_2
      24: aload_0
      25: getfield      #323                // Field changeList:Ljava/util/List;
      28: invokeinterface #377,  1          // InterfaceMethod java/util/List.iterator:()Ljava/util/Iterator;
      33: astore        4
      35: goto          52
      38: aload         4
      40: invokeinterface #374,  1          // InterfaceMethod java/util/Iterator.next:()Ljava/lang/Object;
      45: astore_3
      46: aload_2
      47: aload_3
      48: invokevirtual #335                // Method java/lang/StringBuilder.append:(Ljava/lang/Object;)Ljava/lang/StringBuilder;
      51: pop
      52: aload         4
      54: invokeinterface #373,  1          // InterfaceMethod java/util/Iterator.hasNext:()Z
      59: ifne          38
      62: aload_2
      63: getstatic     #326                // Field org/eclipse/ui/internal/ExtensionEventHandlerMessages.ExtensionEventHandler_need_to_reset:Ljava/lang/String;
      66: invokevirtual #336                // Method java/lang/StringBuilder.append:(Ljava/lang/String;)Ljava/lang/StringBuilder;
      69: pop
      70: aload_1
      71: aload_0
      72: aload_2
      73: invokedynamic #393,  0            // InvokeDynamic #0:run:(Lorg/eclipse/ui/internal/ExtensionEventHandler;Ljava/lang/StringBuilder;)Ljava/lang/Runnable;
      78: invokevirtual #344                // Method org/eclipse/swt/widgets/Display.asyncExec:(Ljava/lang/Runnable;)V
      81: return

  private void lambda$0(org.eclipse.core.runtime.IExtensionPoint, org.eclipse.core.runtime.IExtension);
    Code:
       0: aload_0
       1: aload_1
       2: aload_2
       3: invokevirtual #352                // Method appear:(Lorg/eclipse/core/runtime/IExtensionPoint;Lorg/eclipse/core/runtime/IExtension;)V
       6: return

  private void lambda$1(java.lang.StringBuilder);
    Code:
       0: aconst_null
       1: astore_2
       2: aload_0
       3: getfield      #324                // Field workbench:Lorg/eclipse/ui/internal/Workbench;
       6: invokevirtual #356                // Method org/eclipse/ui/internal/Workbench.getActiveWorkbenchWindow:()Lorg/eclipse/ui/IWorkbenchWindow;
       9: astore_3
      10: aload_3
      11: ifnonnull     35
      14: aload_0
      15: getfield      #324                // Field workbench:Lorg/eclipse/ui/internal/Workbench;
      18: invokevirtual #355                // Method org/eclipse/ui/internal/Workbench.getWorkbenchWindowCount:()I
      21: ifne          25
      24: return
      25: aload_0
      26: getfield      #324                // Field workbench:Lorg/eclipse/ui/internal/Workbench;
      29: invokevirtual #357                // Method org/eclipse/ui/internal/Workbench.getWorkbenchWindows:()[Lorg/eclipse/ui/IWorkbenchWindow;
      32: iconst_0
      33: aaload
      34: astore_3
      35: aload_3
      36: invokeinterface #386,  1          // InterfaceMethod org/eclipse/ui/IWorkbenchWindow.getShell:()Lorg/eclipse/swt/widgets/Shell;
      41: astore_2
      42: aload_2
      43: getstatic     #327                // Field org/eclipse/ui/internal/ExtensionEventHandlerMessages.ExtensionEventHandler_reset_perspective:Ljava/lang/String;
      46: aload_1
      47: invokevirtual #333                // Method java/lang/StringBuilder.toString:()Ljava/lang/String;
      50: invokestatic  #343                // Method org/eclipse/jface/dialogs/MessageDialog.openQuestion:(Lorg/eclipse/swt/widgets/Shell;Ljava/lang/String;Ljava/lang/String;)Z
      53: ifeq          77
      56: aload_3
      57: invokeinterface #387,  1          // InterfaceMethod org/eclipse/ui/IWorkbenchWindow.getActivePage:()Lorg/eclipse/ui/IWorkbenchPage;
      62: astore        4
      64: aload         4
      66: ifnonnull     70
      69: return
      70: aload         4
      72: invokeinterface #385,  1          // InterfaceMethod org/eclipse/ui/IWorkbenchPage.resetPerspective:()V
      77: return
}
