Compiled from "JFaceUtil.java"
class org.eclipse.ui.internal.JFaceUtil$2 implements org.eclipse.core.runtime.preferences.IEclipsePreferences$INodeChangeListener {
  private final java.lang.String val$workbenchName;

  org.eclipse.ui.internal.JFaceUtil$2(java.lang.String);
    Code:
       0: aload_0
       1: aload_1
       2: putfield      #53                 // Field val$workbenchName:Ljava/lang/String;
       5: aload_0
       6: invokespecial #54                 // Method java/lang/Object."<init>":()V
       9: return

  public void added(org.eclipse.core.runtime.preferences.IEclipsePreferences$NodeChangeEvent);
    Code:
       0: aload_1
       1: invokevirtual #56                 // Method org/eclipse/core/runtime/preferences/IEclipsePreferences$NodeChangeEvent.getChild:()Lorg/osgi/service/prefs/Preferences;
       4: invokeinterface #59,  1           // InterfaceMethod org/osgi/service/prefs/Preferences.name:()Ljava/lang/String;
       9: aload_0
      10: getfield      #53                 // Field val$workbenchName:Ljava/lang/String;
      13: invokevirtual #55                 // Method java/lang/String.equals:(Ljava/lang/Object;)Z
      16: ifne          20
      19: return
      20: aload_1
      21: invokevirtual #56                 // Method org/eclipse/core/runtime/preferences/IEclipsePreferences$NodeChangeEvent.getChild:()Lorg/osgi/service/prefs/Preferences;
      24: checkcast     #27                 // class org/eclipse/core/runtime/preferences/IEclipsePreferences
      27: invokestatic  #57                 // Method org/eclipse/ui/internal/PlatformUIPreferenceListener.getSingleton:()Lorg/eclipse/core/runtime/preferences/IEclipsePreferences$IPreferenceChangeListener;
      30: invokeinterface #58,  2           // InterfaceMethod org/eclipse/core/runtime/preferences/IEclipsePreferences.addPreferenceChangeListener:(Lorg/eclipse/core/runtime/preferences/IEclipsePreferences$IPreferenceChangeListener;)V
      35: return

  public void removed(org.eclipse.core.runtime.preferences.IEclipsePreferences$NodeChangeEvent);
    Code:
       0: return
}
