Compiled from "PopupMenuExtender.java"
public class org.eclipse.ui.internal.PopupMenuExtender implements org.eclipse.jface.action.IMenuListener2,org.eclipse.core.runtime.IRegistryChangeListener {
  private static final int STATIC_ACTION_READ;

  private static final int INCLUDE_EDITOR_INPUT;

  private final org.eclipse.jface.action.MenuManager menu;

  private org.eclipse.jface.action.SubMenuManager menuWrapper;

  private final org.eclipse.jface.viewers.ISelectionProvider selProvider;

  private final org.eclipse.ui.IWorkbenchPart part;

  private java.util.Map<java.lang.String, org.eclipse.ui.internal.ViewerActionBuilder> staticActionBuilders;

  private int bitSet;

  private java.util.ArrayList<org.eclipse.ui.internal.PluginActionContributionItem> actionContributionCache;

  private boolean cleanupNeeded;

  private org.eclipse.e4.ui.model.application.ui.basic.MPart modelPart;

  private org.eclipse.e4.core.contexts.IEclipseContext context;

  private org.eclipse.e4.ui.model.application.ui.menu.MPopupMenu menuModel;

  public org.eclipse.ui.internal.PopupMenuExtender(java.lang.String, org.eclipse.jface.action.MenuManager, org.eclipse.jface.viewers.ISelectionProvider, org.eclipse.ui.IWorkbenchPart, org.eclipse.e4.core.contexts.IEclipseContext);
    Code:
       0: aload_0
       1: aload_1
       2: aload_2
       3: aload_3
       4: aload         4
       6: aload         5
       8: iconst_1
       9: invokespecial #642                // Method "<init>":(Ljava/lang/String;Lorg/eclipse/jface/action/MenuManager;Lorg/eclipse/jface/viewers/ISelectionProvider;Lorg/eclipse/ui/IWorkbenchPart;Lorg/eclipse/e4/core/contexts/IEclipseContext;Z)V
      12: return

  public org.eclipse.ui.internal.PopupMenuExtender(java.lang.String, org.eclipse.jface.action.MenuManager, org.eclipse.jface.viewers.ISelectionProvider, org.eclipse.ui.IWorkbenchPart, org.eclipse.e4.core.contexts.IEclipseContext, boolean);
    Code:
       0: aload_0
       1: invokespecial #573                // Method java/lang/Object."<init>":()V
       4: aload_0
       5: aconst_null
       6: putfield      #562                // Field staticActionBuilders:Ljava/util/Map;
       9: aload_0
      10: iconst_0
      11: putfield      #559                // Field bitSet:I
      14: aload_0
      15: new           #263                // class java/util/ArrayList
      18: dup
      19: invokespecial #586                // Method java/util/ArrayList."<init>":()V
      22: putfield      #561                // Field actionContributionCache:Ljava/util/ArrayList;
      25: aload_0
      26: iconst_0
      27: putfield      #560                // Field cleanupNeeded:Z
      30: aload_0
      31: aload_2
      32: putfield      #566                // Field menu:Lorg/eclipse/jface/action/MenuManager;
      35: aload_0
      36: aload_3
      37: putfield      #568                // Field selProvider:Lorg/eclipse/jface/viewers/ISelectionProvider;
      40: aload_0
      41: aload         4
      43: putfield      #569                // Field part:Lorg/eclipse/ui/IWorkbenchPart;
      46: aload_0
      47: aload         5
      49: putfield      #563                // Field context:Lorg/eclipse/e4/core/contexts/IEclipseContext;
      52: aload_0
      53: aload         4
      55: invokeinterface #690,  1          // InterfaceMethod org/eclipse/ui/IWorkbenchPart.getSite:()Lorg/eclipse/ui/IWorkbenchPartSite;
      60: ldc           #4                  // class org/eclipse/e4/ui/model/application/ui/basic/MPart
      62: invokeinterface #693,  2          // InterfaceMethod org/eclipse/ui/IWorkbenchPartSite.getService:(Ljava/lang/Class;)Ljava/lang/Object;
      67: checkcast     #4                  // class org/eclipse/e4/ui/model/application/ui/basic/MPart
      70: putfield      #564                // Field modelPart:Lorg/eclipse/e4/ui/model/application/ui/basic/MPart;
      73: iload         6
      75: ifeq          88
      78: aload_0
      79: dup
      80: getfield      #559                // Field bitSet:I
      83: iconst_2
      84: ior
      85: putfield      #559                // Field bitSet:I
      88: aload_2
      89: aload_0
      90: invokevirtual #611                // Method org/eclipse/jface/action/MenuManager.addMenuListener:(Lorg/eclipse/jface/action/IMenuListener;)V
      93: aload_2
      94: invokevirtual #610                // Method org/eclipse/jface/action/MenuManager.getRemoveAllWhenShown:()Z
      97: ifne          120
     100: aload_0
     101: new           #296                // class org/eclipse/jface/action/SubMenuManager
     104: dup
     105: aload_2
     106: invokespecial #617                // Method org/eclipse/jface/action/SubMenuManager."<init>":(Lorg/eclipse/jface/action/IMenuManager;)V
     109: putfield      #567                // Field menuWrapper:Lorg/eclipse/jface/action/SubMenuManager;
     112: aload_0
     113: getfield      #567                // Field menuWrapper:Lorg/eclipse/jface/action/SubMenuManager;
     116: iconst_1
     117: invokevirtual #616                // Method org/eclipse/jface/action/SubMenuManager.setVisible:(Z)V
     120: aload_0
     121: aload_1
     122: invokevirtual #632                // Method createModelFor:(Ljava/lang/String;)V
     125: aload_0
     126: aload_1
     127: invokevirtual #631                // Method addMenuId:(Ljava/lang/String;)V
     130: invokestatic  #594                // Method org/eclipse/core/runtime/Platform.getExtensionRegistry:()Lorg/eclipse/core/runtime/IExtensionRegistry;
     133: aload_0
     134: invokeinterface #669,  2          // InterfaceMethod org/eclipse/core/runtime/IExtensionRegistry.addRegistryChangeListener:(Lorg/eclipse/core/runtime/IRegistryChangeListener;)V
     139: return

  private void createModelFor(java.lang.String);
    Code:
       0: aload_1
       1: ifnonnull     37
       4: new           #259                // class java/lang/StringBuilder
       7: dup
       8: aload_0
       9: invokevirtual #574                // Method java/lang/Object.getClass:()Ljava/lang/Class;
      12: invokevirtual #572                // Method java/lang/Class.getName:()Ljava/lang/String;
      15: invokestatic  #577                // Method java/lang/String.valueOf:(Ljava/lang/Object;)Ljava/lang/String;
      18: invokespecial #579                // Method java/lang/StringBuilder."<init>":(Ljava/lang/String;)V
      21: bipush        46
      23: invokevirtual #580                // Method java/lang/StringBuilder.append:(C)Ljava/lang/StringBuilder;
      26: aload_0
      27: invokestatic  #583                // Method java/lang/System.identityHashCode:(Ljava/lang/Object;)I
      30: invokevirtual #581                // Method java/lang/StringBuilder.append:(I)Ljava/lang/StringBuilder;
      33: invokevirtual #578                // Method java/lang/StringBuilder.toString:()Ljava/lang/String;
      36: astore_1
      37: aload_0
      38: aconst_null
      39: putfield      #565                // Field menuModel:Lorg/eclipse/e4/ui/model/application/ui/menu/MPopupMenu;
      42: aload_0
      43: getfield      #564                // Field modelPart:Lorg/eclipse/e4/ui/model/application/ui/basic/MPart;
      46: invokeinterface #673,  1          // InterfaceMethod org/eclipse/e4/ui/model/application/ui/basic/MPart.getMenus:()Ljava/util/List;
      51: invokeinterface #656,  1          // InterfaceMethod java/util/List.iterator:()Ljava/util/Iterator;
      56: astore_3
      57: goto          117
      60: aload_3
      61: invokeinterface #652,  1          // InterfaceMethod java/util/Iterator.next:()Ljava/lang/Object;
      66: checkcast     #286                // class org/eclipse/e4/ui/model/application/ui/menu/MMenu
      69: astore_2
      70: aload_1
      71: aload_2
      72: invokeinterface #675,  1          // InterfaceMethod org/eclipse/e4/ui/model/application/ui/menu/MMenu.getElementId:()Ljava/lang/String;
      77: invokevirtual #576                // Method java/lang/String.equals:(Ljava/lang/Object;)Z
      80: ifeq          117
      83: aload_2
      84: instanceof    #288                // class org/eclipse/e4/ui/model/application/ui/menu/MPopupMenu
      87: ifeq          117
      90: aload_2
      91: invokeinterface #677,  1          // InterfaceMethod org/eclipse/e4/ui/model/application/ui/menu/MMenu.getTags:()Ljava/util/List;
      96: ldc           #3                  // String popup
      98: invokeinterface #654,  2          // InterfaceMethod java/util/List.contains:(Ljava/lang/Object;)Z
     103: ifeq          117
     106: aload_0
     107: aload_2
     108: checkcast     #288                // class org/eclipse/e4/ui/model/application/ui/menu/MPopupMenu
     111: putfield      #565                // Field menuModel:Lorg/eclipse/e4/ui/model/application/ui/menu/MPopupMenu;
     114: goto          126
     117: aload_3
     118: invokeinterface #651,  1          // InterfaceMethod java/util/Iterator.hasNext:()Z
     123: ifne          60
     126: aload_0
     127: getfield      #565                // Field menuModel:Lorg/eclipse/e4/ui/model/application/ui/menu/MPopupMenu;
     130: ifnonnull     212
     133: aload_0
     134: getstatic     #558                // Field org/eclipse/e4/ui/model/application/ui/menu/impl/MenuFactoryImpl.eINSTANCE:Lorg/eclipse/e4/ui/model/application/ui/menu/impl/MenuFactoryImpl;
     137: invokevirtual #600                // Method org/eclipse/e4/ui/model/application/ui/menu/impl/MenuFactoryImpl.createPopupMenu:()Lorg/eclipse/e4/ui/model/application/ui/menu/MPopupMenu;
     140: putfield      #565                // Field menuModel:Lorg/eclipse/e4/ui/model/application/ui/menu/MPopupMenu;
     143: aload_0
     144: getfield      #565                // Field menuModel:Lorg/eclipse/e4/ui/model/application/ui/menu/MPopupMenu;
     147: invokeinterface #682,  1          // InterfaceMethod org/eclipse/e4/ui/model/application/ui/menu/MPopupMenu.getPersistedState:()Ljava/util/Map;
     152: ldc           #2                  // String persistState
     154: getstatic     #557                // Field java/lang/Boolean.FALSE:Ljava/lang/Boolean;
     157: invokevirtual #571                // Method java/lang/Boolean.toString:()Ljava/lang/String;
     160: invokeinterface #660,  3          // InterfaceMethod java/util/Map.put:(Ljava/lang/Object;Ljava/lang/Object;)Ljava/lang/Object;
     165: pop
     166: aload_0
     167: getfield      #565                // Field menuModel:Lorg/eclipse/e4/ui/model/application/ui/menu/MPopupMenu;
     170: aload_1
     171: invokeinterface #680,  2          // InterfaceMethod org/eclipse/e4/ui/model/application/ui/menu/MPopupMenu.setElementId:(Ljava/lang/String;)V
     176: aload_0
     177: getfield      #565                // Field menuModel:Lorg/eclipse/e4/ui/model/application/ui/menu/MPopupMenu;
     180: invokeinterface #681,  1          // InterfaceMethod org/eclipse/e4/ui/model/application/ui/menu/MPopupMenu.getTags:()Ljava/util/List;
     185: ldc           #1                  // String menuContribution:popup
     187: invokeinterface #653,  2          // InterfaceMethod java/util/List.add:(Ljava/lang/Object;)Z
     192: pop
     193: aload_0
     194: getfield      #564                // Field modelPart:Lorg/eclipse/e4/ui/model/application/ui/basic/MPart;
     197: invokeinterface #673,  1          // InterfaceMethod org/eclipse/e4/ui/model/application/ui/basic/MPart.getMenus:()Ljava/util/List;
     202: aload_0
     203: getfield      #565                // Field menuModel:Lorg/eclipse/e4/ui/model/application/ui/menu/MPopupMenu;
     206: invokeinterface #653,  2          // InterfaceMethod java/util/List.add:(Ljava/lang/Object;)Z
     211: pop
     212: aload_0
     213: getfield      #564                // Field modelPart:Lorg/eclipse/e4/ui/model/application/ui/basic/MPart;
     216: invokeinterface #674,  1          // InterfaceMethod org/eclipse/e4/ui/model/application/ui/basic/MPart.getContext:()Lorg/eclipse/e4/core/contexts/IEclipseContext;
     221: ldc           #5                  // class org/eclipse/e4/ui/workbench/swt/factories/IRendererFactory
     223: invokeinterface #672,  2          // InterfaceMethod org/eclipse/e4/core/contexts/IEclipseContext.get:(Ljava/lang/Class;)Ljava/lang/Object;
     228: checkcast     #5                  // class org/eclipse/e4/ui/workbench/swt/factories/IRendererFactory
     231: astore_2
     232: aload_2
     233: aload_0
     234: getfield      #565                // Field menuModel:Lorg/eclipse/e4/ui/model/application/ui/menu/MPopupMenu;
     237: aconst_null
     238: invokeinterface #683,  3          // InterfaceMethod org/eclipse/e4/ui/workbench/swt/factories/IRendererFactory.getRenderer:(Lorg/eclipse/e4/ui/model/application/ui/MUIElement;Ljava/lang/Object;)Lorg/eclipse/e4/ui/internal/workbench/swt/AbstractPartRenderer;
     243: astore_3
     244: aload_3
     245: instanceof    #290                // class org/eclipse/e4/ui/workbench/renderers/swt/MenuManagerRenderer
     248: ifeq          266
     251: aload_3
     252: checkcast     #290                // class org/eclipse/e4/ui/workbench/renderers/swt/MenuManagerRenderer
     255: aload_0
     256: getfield      #565                // Field menuModel:Lorg/eclipse/e4/ui/model/application/ui/menu/MPopupMenu;
     259: aload_0
     260: getfield      #566                // Field menu:Lorg/eclipse/jface/action/MenuManager;
     263: invokevirtual #609                // Method org/eclipse/e4/ui/workbench/renderers/swt/MenuManagerRenderer.linkModelToManager:(Lorg/eclipse/e4/ui/model/application/ui/menu/MMenu;Lorg/eclipse/jface/action/MenuManager;)V
     266: aload_0
     267: invokevirtual #630                // Method registerE4Support:()V
     270: aload_0
     271: invokevirtual #627                // Method cleanUpContributionCache:()V
     274: return

  private void registerE4Support();
    Code:
       0: aload_0
       1: getfield      #565                // Field menuModel:Lorg/eclipse/e4/ui/model/application/ui/menu/MPopupMenu;
       4: invokeinterface #678,  1          // InterfaceMethod org/eclipse/e4/ui/model/application/ui/menu/MPopupMenu.getWidget:()Ljava/lang/Object;
       9: ifnonnull     44
      12: aload_0
      13: getfield      #566                // Field menu:Lorg/eclipse/jface/action/MenuManager;
      16: invokevirtual #613                // Method org/eclipse/jface/action/MenuManager.getMenu:()Lorg/eclipse/swt/widgets/Menu;
      19: ifnull        44
      22: aload_0
      23: getfield      #566                // Field menu:Lorg/eclipse/jface/action/MenuManager;
      26: invokevirtual #613                // Method org/eclipse/jface/action/MenuManager.getMenu:()Lorg/eclipse/swt/widgets/Menu;
      29: invokevirtual #622                // Method org/eclipse/swt/widgets/Menu.getParent:()Lorg/eclipse/swt/widgets/Decorations;
      32: aload_0
      33: getfield      #565                // Field menuModel:Lorg/eclipse/e4/ui/model/application/ui/menu/MPopupMenu;
      36: aload_0
      37: getfield      #563                // Field context:Lorg/eclipse/e4/core/contexts/IEclipseContext;
      40: invokestatic  #599                // Method org/eclipse/e4/ui/internal/workbench/swt/MenuService.registerMenu:(Lorg/eclipse/swt/widgets/Control;Lorg/eclipse/e4/ui/model/application/ui/menu/MPopupMenu;Lorg/eclipse/e4/core/contexts/IEclipseContext;)Lorg/eclipse/swt/widgets/Menu;
      43: pop
      44: return

  public java.util.Set<java.lang.String> getMenuIds();
    Code:
       0: aload_0
       1: getfield      #562                // Field staticActionBuilders:Ljava/util/Map;
       4: ifnonnull     11
       7: invokestatic  #591                // Method java/util/Collections.emptySet:()Ljava/util/Set;
      10: areturn
      11: aload_0
      12: getfield      #562                // Field staticActionBuilders:Ljava/util/Map;
      15: invokeinterface #658,  1          // InterfaceMethod java/util/Map.keySet:()Ljava/util/Set;
      20: areturn

  public final void addMenuId(java.lang.String);
    Code:
       0: aload_0
       1: dup
       2: getfield      #559                // Field bitSet:I
       5: bipush        -2
       7: iand
       8: putfield      #559                // Field bitSet:I
      11: aload_0
      12: getfield      #565                // Field menuModel:Lorg/eclipse/e4/ui/model/application/ui/menu/MPopupMenu;
      15: ifnull        64
      18: aload_0
      19: getfield      #565                // Field menuModel:Lorg/eclipse/e4/ui/model/application/ui/menu/MPopupMenu;
      22: invokeinterface #681,  1          // InterfaceMethod org/eclipse/e4/ui/model/application/ui/menu/MPopupMenu.getTags:()Ljava/util/List;
      27: astore_2
      28: new           #259                // class java/lang/StringBuilder
      31: dup
      32: ldc_w         #248                // String popup:
      35: invokespecial #579                // Method java/lang/StringBuilder."<init>":(Ljava/lang/String;)V
      38: aload_1
      39: invokevirtual #582                // Method java/lang/StringBuilder.append:(Ljava/lang/String;)Ljava/lang/StringBuilder;
      42: invokevirtual #578                // Method java/lang/StringBuilder.toString:()Ljava/lang/String;
      45: astore_3
      46: aload_2
      47: aload_3
      48: invokeinterface #654,  2          // InterfaceMethod java/util/List.contains:(Ljava/lang/Object;)Z
      53: ifne          64
      56: aload_2
      57: aload_3
      58: invokeinterface #653,  2          // InterfaceMethod java/util/List.add:(Ljava/lang/Object;)Z
      63: pop
      64: aload_0
      65: aload_1
      66: invokevirtual #633                // Method readStaticActionsFor:(Ljava/lang/String;)V
      69: return

  public final boolean matches(org.eclipse.jface.action.MenuManager, org.eclipse.jface.viewers.ISelectionProvider, org.eclipse.ui.IWorkbenchPart);
    Code:
       0: aload_0
       1: getfield      #566                // Field menu:Lorg/eclipse/jface/action/MenuManager;
       4: aload_1
       5: if_acmpne     26
       8: aload_0
       9: getfield      #568                // Field selProvider:Lorg/eclipse/jface/viewers/ISelectionProvider;
      12: aload_2
      13: if_acmpne     26
      16: aload_0
      17: getfield      #569                // Field part:Lorg/eclipse/ui/IWorkbenchPart;
      20: aload_3
      21: if_acmpne     26
      24: iconst_1
      25: ireturn
      26: iconst_0
      27: ireturn

  private void addEditorActions(org.eclipse.jface.action.IMenuManager, java.util.Set<org.eclipse.ui.internal.IObjectActionContributor>);
    Code:
       0: new           #311                // class org/eclipse/ui/internal/PopupMenuExtender$1
       3: dup
       4: aload_0
       5: invokespecial #643                // Method org/eclipse/ui/internal/PopupMenuExtender$1."<init>":(Lorg/eclipse/ui/internal/PopupMenuExtender;)V
       8: astore_3
       9: invokestatic  #623                // Method org/eclipse/ui/internal/ObjectActionContributorManager.getManager:()Lorg/eclipse/ui/internal/ObjectActionContributorManager;
      12: aload_0
      13: getfield      #569                // Field part:Lorg/eclipse/ui/IWorkbenchPart;
      16: aload_1
      17: aload_3
      18: aload_2
      19: invokevirtual #624                // Method org/eclipse/ui/internal/ObjectActionContributorManager.contributeObjectActions:(Lorg/eclipse/ui/IWorkbenchPart;Lorg/eclipse/jface/action/IMenuManager;Lorg/eclipse/jface/viewers/ISelectionProvider;Ljava/util/Set;)Z
      22: ifeq          38
      25: aload_1
      26: new           #295                // class org/eclipse/jface/action/Separator
      29: dup
      30: invokespecial #614                // Method org/eclipse/jface/action/Separator."<init>":()V
      33: invokeinterface #685,  2          // InterfaceMethod org/eclipse/jface/action/IMenuManager.add:(Lorg/eclipse/jface/action/IContributionItem;)V
      38: return

  private void addObjectActions(org.eclipse.jface.action.IMenuManager, java.util.Set<org.eclipse.ui.internal.IObjectActionContributor>);
    Code:
       0: aload_0
       1: getfield      #568                // Field selProvider:Lorg/eclipse/jface/viewers/ISelectionProvider;
       4: ifnull        39
       7: invokestatic  #623                // Method org/eclipse/ui/internal/ObjectActionContributorManager.getManager:()Lorg/eclipse/ui/internal/ObjectActionContributorManager;
      10: aload_0
      11: getfield      #569                // Field part:Lorg/eclipse/ui/IWorkbenchPart;
      14: aload_1
      15: aload_0
      16: getfield      #568                // Field selProvider:Lorg/eclipse/jface/viewers/ISelectionProvider;
      19: aload_2
      20: invokevirtual #624                // Method org/eclipse/ui/internal/ObjectActionContributorManager.contributeObjectActions:(Lorg/eclipse/ui/IWorkbenchPart;Lorg/eclipse/jface/action/IMenuManager;Lorg/eclipse/jface/viewers/ISelectionProvider;Ljava/util/Set;)Z
      23: ifeq          39
      26: aload_1
      27: new           #295                // class org/eclipse/jface/action/Separator
      30: dup
      31: invokespecial #614                // Method org/eclipse/jface/action/Separator."<init>":()V
      34: invokeinterface #685,  2          // InterfaceMethod org/eclipse/jface/action/IMenuManager.add:(Lorg/eclipse/jface/action/IContributionItem;)V
      39: return

  private final void clearStaticActions();
    Code:
       0: aload_0
       1: dup
       2: getfield      #559                // Field bitSet:I
       5: bipush        -2
       7: iand
       8: putfield      #559                // Field bitSet:I
      11: aload_0
      12: getfield      #562                // Field staticActionBuilders:Ljava/util/Map;
      15: ifnull        59
      18: aload_0
      19: getfield      #562                // Field staticActionBuilders:Ljava/util/Map;
      22: invokeinterface #657,  1          // InterfaceMethod java/util/Map.values:()Ljava/util/Collection;
      27: invokeinterface #650,  1          // InterfaceMethod java/util/Collection.iterator:()Ljava/util/Iterator;
      32: astore_1
      33: goto          50
      36: aload_1
      37: invokeinterface #652,  1          // InterfaceMethod java/util/Iterator.next:()Ljava/lang/Object;
      42: checkcast     #312                // class org/eclipse/ui/internal/ViewerActionBuilder
      45: astore_2
      46: aload_2
      47: invokevirtual #645                // Method org/eclipse/ui/internal/ViewerActionBuilder.dispose:()V
      50: aload_1
      51: invokeinterface #651,  1          // InterfaceMethod java/util/Iterator.hasNext:()Z
      56: ifne          36
      59: return

  private void addStaticActions(org.eclipse.jface.action.IMenuManager);
    Code:
       0: aload_0
       1: getfield      #562                // Field staticActionBuilders:Ljava/util/Map;
       4: ifnull        51
       7: aload_0
       8: getfield      #562                // Field staticActionBuilders:Ljava/util/Map;
      11: invokeinterface #657,  1          // InterfaceMethod java/util/Map.values:()Ljava/util/Collection;
      16: invokeinterface #650,  1          // InterfaceMethod java/util/Collection.iterator:()Ljava/util/Iterator;
      21: astore_2
      22: goto          42
      25: aload_2
      26: invokeinterface #652,  1          // InterfaceMethod java/util/Iterator.next:()Ljava/lang/Object;
      31: checkcast     #312                // class org/eclipse/ui/internal/ViewerActionBuilder
      34: astore_3
      35: aload_3
      36: aload_1
      37: aconst_null
      38: iconst_1
      39: invokevirtual #646                // Method org/eclipse/ui/internal/ViewerActionBuilder.contribute:(Lorg/eclipse/jface/action/IMenuManager;Lorg/eclipse/jface/action/IToolBarManager;Z)V
      42: aload_2
      43: invokeinterface #651,  1          // InterfaceMethod java/util/Iterator.hasNext:()Z
      48: ifne          25
      51: return

  public void menuAboutToShow(org.eclipse.jface.action.IMenuManager);
    Code:
       0: aload_0
       1: invokevirtual #630                // Method registerE4Support:()V
       4: aload_0
       5: getfield      #569                // Field part:Lorg/eclipse/ui/IWorkbenchPart;
       8: invokeinterface #690,  1          // InterfaceMethod org/eclipse/ui/IWorkbenchPart.getSite:()Lorg/eclipse/ui/IWorkbenchPartSite;
      13: astore_2
      14: aload_2
      15: ifnull        138
      18: aload_2
      19: invokeinterface #692,  1          // InterfaceMethod org/eclipse/ui/IWorkbenchPartSite.getWorkbenchWindow:()Lorg/eclipse/ui/IWorkbenchWindow;
      24: invokeinterface #694,  1          // InterfaceMethod org/eclipse/ui/IWorkbenchWindow.getWorkbench:()Lorg/eclipse/ui/IWorkbench;
      29: astore_3
      30: aload_3
      31: instanceof    #313                // class org/eclipse/ui/internal/Workbench
      34: ifeq          138
      37: aload_3
      38: checkcast     #313                // class org/eclipse/ui/internal/Workbench
      41: astore        4
      43: aload_0
      44: aload         4
      46: invokevirtual #638                // Method runCleanUp:(Lorg/eclipse/ui/internal/Workbench;)V
      49: aconst_null
      50: astore        5
      52: aload_0
      53: getfield      #559                // Field bitSet:I
      56: iconst_2
      57: iand
      58: ifeq          103
      61: aload_0
      62: getfield      #569                // Field part:Lorg/eclipse/ui/IWorkbenchPart;
      65: instanceof    #302                // class org/eclipse/ui/IEditorPart
      68: ifeq          103
      71: aload_0
      72: getfield      #569                // Field part:Lorg/eclipse/ui/IWorkbenchPart;
      75: checkcast     #302                // class org/eclipse/ui/IEditorPart
      78: astore        6
      80: new           #299                // class org/eclipse/jface/viewers/StructuredSelection
      83: dup
      84: iconst_1
      85: anewarray     #257                // class java/lang/Object
      88: dup
      89: iconst_0
      90: aload         6
      92: invokeinterface #687,  1          // InterfaceMethod org/eclipse/ui/IEditorPart.getEditorInput:()Lorg/eclipse/ui/IEditorInput;
      97: aastore
      98: invokespecial #618                // Method org/eclipse/jface/viewers/StructuredSelection."<init>":([Ljava/lang/Object;)V
     101: astore        5
     103: aload_0
     104: getfield      #568                // Field selProvider:Lorg/eclipse/jface/viewers/ISelectionProvider;
     107: ifnonnull     114
     110: aconst_null
     111: goto          123
     114: aload_0
     115: getfield      #568                // Field selProvider:Lorg/eclipse/jface/viewers/ISelectionProvider;
     118: invokeinterface #686,  1          // InterfaceMethod org/eclipse/jface/viewers/ISelectionProvider.getSelection:()Lorg/eclipse/jface/viewers/ISelection;
     123: astore        6
     125: aload         4
     127: aload_0
     128: invokevirtual #634                // Method getMenuIds:()Ljava/util/Set;
     131: aload         6
     133: aload         5
     135: invokevirtual #648                // Method org/eclipse/ui/internal/Workbench.addShowingMenus:(Ljava/util/Set;Lorg/eclipse/jface/viewers/ISelection;Lorg/eclipse/jface/viewers/ISelection;)V
     138: aload_0
     139: invokevirtual #626                // Method addMenuContributions:()V
     142: aload_0
     143: invokevirtual #629                // Method readStaticActions:()V
     146: aload_0
     147: getfield      #567                // Field menuWrapper:Lorg/eclipse/jface/action/SubMenuManager;
     150: ifnull        165
     153: aload_0
     154: getfield      #567                // Field menuWrapper:Lorg/eclipse/jface/action/SubMenuManager;
     157: astore_1
     158: aload_0
     159: getfield      #567                // Field menuWrapper:Lorg/eclipse/jface/action/SubMenuManager;
     162: invokevirtual #615                // Method org/eclipse/jface/action/SubMenuManager.removeAll:()V
     165: new           #267                // class java/util/HashSet
     168: dup
     169: invokespecial #593                // Method java/util/HashSet."<init>":()V
     172: astore_3
     173: aload_0
     174: getfield      #559                // Field bitSet:I
     177: iconst_2
     178: iand
     179: ifeq          188
     182: aload_0
     183: aload_1
     184: aload_3
     185: invokevirtual #639                // Method addEditorActions:(Lorg/eclipse/jface/action/IMenuManager;Ljava/util/Set;)V
     188: aload_0
     189: aload_1
     190: aload_3
     191: invokevirtual #640                // Method addObjectActions:(Lorg/eclipse/jface/action/IMenuManager;Ljava/util/Set;)V
     194: aload_0
     195: aload_1
     196: invokevirtual #635                // Method addStaticActions:(Lorg/eclipse/jface/action/IMenuManager;)V
     199: return

  private void addMenuContributions();
    Code:
       0: aload_0
       1: getfield      #564                // Field modelPart:Lorg/eclipse/e4/ui/model/application/ui/basic/MPart;
       4: invokeinterface #674,  1          // InterfaceMethod org/eclipse/e4/ui/model/application/ui/basic/MPart.getContext:()Lorg/eclipse/e4/core/contexts/IEclipseContext;
       9: ldc           #5                  // class org/eclipse/e4/ui/workbench/swt/factories/IRendererFactory
      11: invokeinterface #672,  2          // InterfaceMethod org/eclipse/e4/core/contexts/IEclipseContext.get:(Ljava/lang/Class;)Ljava/lang/Object;
      16: checkcast     #5                  // class org/eclipse/e4/ui/workbench/swt/factories/IRendererFactory
      19: astore_1
      20: aload_1
      21: aload_0
      22: getfield      #565                // Field menuModel:Lorg/eclipse/e4/ui/model/application/ui/menu/MPopupMenu;
      25: aconst_null
      26: invokeinterface #683,  3          // InterfaceMethod org/eclipse/e4/ui/workbench/swt/factories/IRendererFactory.getRenderer:(Lorg/eclipse/e4/ui/model/application/ui/MUIElement;Ljava/lang/Object;)Lorg/eclipse/e4/ui/internal/workbench/swt/AbstractPartRenderer;
      31: astore_2
      32: aload_2
      33: instanceof    #290                // class org/eclipse/e4/ui/workbench/renderers/swt/MenuManagerRenderer
      36: ifeq          86
      39: aload_2
      40: checkcast     #290                // class org/eclipse/e4/ui/workbench/renderers/swt/MenuManagerRenderer
      43: astore_3
      44: aload_3
      45: aload_0
      46: getfield      #566                // Field menu:Lorg/eclipse/jface/action/MenuManager;
      49: aload_0
      50: getfield      #565                // Field menuModel:Lorg/eclipse/e4/ui/model/application/ui/menu/MPopupMenu;
      53: invokevirtual #604                // Method org/eclipse/e4/ui/workbench/renderers/swt/MenuManagerRenderer.reconcileManagerToModel:(Lorg/eclipse/jface/action/MenuManager;Lorg/eclipse/e4/ui/model/application/ui/menu/MMenu;)V
      56: aload_3
      57: aload_0
      58: getfield      #565                // Field menuModel:Lorg/eclipse/e4/ui/model/application/ui/menu/MPopupMenu;
      61: aload_0
      62: getfield      #565                // Field menuModel:Lorg/eclipse/e4/ui/model/application/ui/menu/MPopupMenu;
      65: invokeinterface #679,  1          // InterfaceMethod org/eclipse/e4/ui/model/application/ui/menu/MPopupMenu.getElementId:()Ljava/lang/String;
      70: iconst_0
      71: iconst_1
      72: invokevirtual #603                // Method org/eclipse/e4/ui/workbench/renderers/swt/MenuManagerRenderer.processContributions:(Lorg/eclipse/e4/ui/model/application/ui/menu/MMenu;Ljava/lang/String;ZZ)V
      75: aload_3
      76: aload_0
      77: getfield      #565                // Field menuModel:Lorg/eclipse/e4/ui/model/application/ui/menu/MPopupMenu;
      80: checkcast     #285                // class org/eclipse/e4/ui/model/application/ui/MElementContainer
      83: invokevirtual #601                // Method org/eclipse/e4/ui/workbench/renderers/swt/MenuManagerRenderer.processContents:(Lorg/eclipse/e4/ui/model/application/ui/MElementContainer;)V
      86: return

  public final void menuAboutToHide(org.eclipse.jface.action.IMenuManager);
    Code:
       0: aload_0
       1: aload_1
       2: invokevirtual #636                // Method gatherContributions:(Lorg/eclipse/jface/action/IMenuManager;)V
       5: aload_0
       6: iconst_1
       7: putfield      #560                // Field cleanupNeeded:Z
      10: aload_0
      11: getfield      #569                // Field part:Lorg/eclipse/ui/IWorkbenchPart;
      14: invokeinterface #690,  1          // InterfaceMethod org/eclipse/ui/IWorkbenchPart.getSite:()Lorg/eclipse/ui/IWorkbenchPartSite;
      19: astore_2
      20: aload_2
      21: ifnull        59
      24: aload_2
      25: invokeinterface #692,  1          // InterfaceMethod org/eclipse/ui/IWorkbenchPartSite.getWorkbenchWindow:()Lorg/eclipse/ui/IWorkbenchWindow;
      30: invokeinterface #694,  1          // InterfaceMethod org/eclipse/ui/IWorkbenchWindow.getWorkbench:()Lorg/eclipse/ui/IWorkbench;
      35: astore_3
      36: aload_3
      37: instanceof    #313                // class org/eclipse/ui/internal/Workbench
      40: ifeq          59
      43: aload_3
      44: invokeinterface #688,  1          // InterfaceMethod org/eclipse/ui/IWorkbench.getDisplay:()Lorg/eclipse/swt/widgets/Display;
      49: aload_0
      50: aload_3
      51: invokedynamic #700,  0            // InvokeDynamic #1:run:(Lorg/eclipse/ui/internal/PopupMenuExtender;Lorg/eclipse/ui/IWorkbench;)Ljava/lang/Runnable;
      56: invokevirtual #619                // Method org/eclipse/swt/widgets/Display.asyncExec:(Ljava/lang/Runnable;)V
      59: return

  private void runCleanUp(org.eclipse.ui.internal.Workbench);
    Code:
       0: aload_0
       1: getfield      #560                // Field cleanupNeeded:Z
       4: ifne          8
       7: return
       8: aload_0
       9: iconst_0
      10: putfield      #560                // Field cleanupNeeded:Z
      13: aload_1
      14: aload_0
      15: invokevirtual #634                // Method getMenuIds:()Ljava/util/Set;
      18: aconst_null
      19: aconst_null
      20: invokevirtual #649                // Method org/eclipse/ui/internal/Workbench.removeShowingMenus:(Ljava/util/Set;Lorg/eclipse/jface/viewers/ISelection;Lorg/eclipse/jface/viewers/ISelection;)V
      23: aload_0
      24: invokevirtual #627                // Method cleanUpContributionCache:()V
      27: return

  private void gatherContributions(org.eclipse.jface.action.IMenuManager);
    Code:
       0: aload_1
       1: invokeinterface #684,  1          // InterfaceMethod org/eclipse/jface/action/IMenuManager.getItems:()[Lorg/eclipse/jface/action/IContributionItem;
       6: astore_2
       7: aload_2
       8: dup
       9: astore        6
      11: arraylength
      12: istore        5
      14: iconst_0
      15: istore        4
      17: goto          66
      20: aload         6
      22: iload         4
      24: aaload
      25: astore_3
      26: aload_3
      27: instanceof    #309                // class org/eclipse/ui/internal/PluginActionContributionItem
      30: ifeq          48
      33: aload_0
      34: getfield      #561                // Field actionContributionCache:Ljava/util/ArrayList;
      37: aload_3
      38: checkcast     #309                // class org/eclipse/ui/internal/PluginActionContributionItem
      41: invokevirtual #589                // Method java/util/ArrayList.add:(Ljava/lang/Object;)Z
      44: pop
      45: goto          63
      48: aload_3
      49: instanceof    #293                // class org/eclipse/jface/action/IMenuManager
      52: ifeq          63
      55: aload_0
      56: aload_3
      57: checkcast     #293                // class org/eclipse/jface/action/IMenuManager
      60: invokevirtual #636                // Method gatherContributions:(Lorg/eclipse/jface/action/IMenuManager;)V
      63: iinc          4, 1
      66: iload         4
      68: iload         5
      70: if_icmplt     20
      73: return

  private void cleanUpContributionCache();
    Code:
       0: aload_0
       1: getfield      #561                // Field actionContributionCache:Ljava/util/ArrayList;
       4: invokevirtual #588                // Method java/util/ArrayList.isEmpty:()Z
       7: ifne          68
      10: aload_0
      11: getfield      #561                // Field actionContributionCache:Ljava/util/ArrayList;
      14: aload_0
      15: getfield      #561                // Field actionContributionCache:Ljava/util/ArrayList;
      18: invokevirtual #585                // Method java/util/ArrayList.size:()I
      21: anewarray     #309                // class org/eclipse/ui/internal/PluginActionContributionItem
      24: invokevirtual #590                // Method java/util/ArrayList.toArray:([Ljava/lang/Object;)[Ljava/lang/Object;
      27: checkcast     #254                // class "[Lorg/eclipse/ui/internal/PluginActionContributionItem;"
      30: astore_1
      31: aload_0
      32: getfield      #561                // Field actionContributionCache:Ljava/util/ArrayList;
      35: invokevirtual #587                // Method java/util/ArrayList.clear:()V
      38: aload_1
      39: dup
      40: astore        5
      42: arraylength
      43: istore        4
      45: iconst_0
      46: istore_3
      47: goto          62
      50: aload         5
      52: iload_3
      53: aaload
      54: astore_2
      55: aload_2
      56: invokevirtual #625                // Method org/eclipse/ui/internal/PluginActionContributionItem.dispose:()V
      59: iinc          3, 1
      62: iload_3
      63: iload         4
      65: if_icmplt     50
      68: aload_0
      69: getfield      #564                // Field modelPart:Lorg/eclipse/e4/ui/model/application/ui/basic/MPart;
      72: ifnull        82
      75: aload_0
      76: getfield      #565                // Field menuModel:Lorg/eclipse/e4/ui/model/application/ui/menu/MPopupMenu;
      79: ifnonnull     83
      82: return
      83: aload_0
      84: getfield      #564                // Field modelPart:Lorg/eclipse/e4/ui/model/application/ui/basic/MPart;
      87: invokeinterface #674,  1          // InterfaceMethod org/eclipse/e4/ui/model/application/ui/basic/MPart.getContext:()Lorg/eclipse/e4/core/contexts/IEclipseContext;
      92: astore_1
      93: aload_1
      94: ifnull        147
      97: aload_1
      98: ldc           #5                  // class org/eclipse/e4/ui/workbench/swt/factories/IRendererFactory
     100: invokeinterface #672,  2          // InterfaceMethod org/eclipse/e4/core/contexts/IEclipseContext.get:(Ljava/lang/Class;)Ljava/lang/Object;
     105: checkcast     #5                  // class org/eclipse/e4/ui/workbench/swt/factories/IRendererFactory
     108: astore_2
     109: aload_2
     110: ifnull        147
     113: aload_2
     114: aload_0
     115: getfield      #565                // Field menuModel:Lorg/eclipse/e4/ui/model/application/ui/menu/MPopupMenu;
     118: aconst_null
     119: invokeinterface #683,  3          // InterfaceMethod org/eclipse/e4/ui/workbench/swt/factories/IRendererFactory.getRenderer:(Lorg/eclipse/e4/ui/model/application/ui/MUIElement;Ljava/lang/Object;)Lorg/eclipse/e4/ui/internal/workbench/swt/AbstractPartRenderer;
     124: astore_3
     125: aload_3
     126: instanceof    #290                // class org/eclipse/e4/ui/workbench/renderers/swt/MenuManagerRenderer
     129: ifeq          147
     132: aload_3
     133: checkcast     #290                // class org/eclipse/e4/ui/workbench/renderers/swt/MenuManagerRenderer
     136: astore        4
     138: aload         4
     140: aload_0
     141: getfield      #565                // Field menuModel:Lorg/eclipse/e4/ui/model/application/ui/menu/MPopupMenu;
     144: invokevirtual #602                // Method org/eclipse/e4/ui/workbench/renderers/swt/MenuManagerRenderer.cleanUp:(Lorg/eclipse/e4/ui/model/application/ui/menu/MMenu;)V
     147: return

  private final void readStaticActions();
    Code:
       0: aload_0
       1: getfield      #562                // Field staticActionBuilders:Ljava/util/Map;
       4: ifnull        49
       7: aload_0
       8: getfield      #562                // Field staticActionBuilders:Ljava/util/Map;
      11: invokeinterface #658,  1          // InterfaceMethod java/util/Map.keySet:()Ljava/util/Set;
      16: invokeinterface #661,  1          // InterfaceMethod java/util/Set.iterator:()Ljava/util/Iterator;
      21: astore_1
      22: goto          40
      25: aload_1
      26: invokeinterface #652,  1          // InterfaceMethod java/util/Iterator.next:()Ljava/lang/Object;
      31: checkcast     #258                // class java/lang/String
      34: astore_2
      35: aload_0
      36: aload_2
      37: invokevirtual #633                // Method readStaticActionsFor:(Ljava/lang/String;)V
      40: aload_1
      41: invokeinterface #651,  1          // InterfaceMethod java/util/Iterator.hasNext:()Z
      46: ifne          25
      49: return

  private void readStaticActionsFor(java.lang.String);
    Code:
       0: aload_0
       1: getfield      #559                // Field bitSet:I
       4: iconst_1
       5: iand
       6: ifeq          10
       9: return
      10: aload_0
      11: dup
      12: getfield      #559                // Field bitSet:I
      15: iconst_1
      16: ior
      17: putfield      #559                // Field bitSet:I
      20: aload_1
      21: ifnull        32
      24: aload_1
      25: invokevirtual #575                // Method java/lang/String.length:()I
      28: iconst_1
      29: if_icmpge     33
      32: return
      33: aload_0
      34: getfield      #562                // Field staticActionBuilders:Ljava/util/Map;
      37: ifnonnull     51
      40: aload_0
      41: new           #266                // class java/util/HashMap
      44: dup
      45: invokespecial #592                // Method java/util/HashMap."<init>":()V
      48: putfield      #562                // Field staticActionBuilders:Ljava/util/Map;
      51: aload_0
      52: getfield      #562                // Field staticActionBuilders:Ljava/util/Map;
      55: aload_1
      56: invokeinterface #659,  2          // InterfaceMethod java/util/Map.get:(Ljava/lang/Object;)Ljava/lang/Object;
      61: checkcast     #312                // class org/eclipse/ui/internal/ViewerActionBuilder
      64: astore_2
      65: aload_2
      66: ifnonnull     89
      69: new           #312                // class org/eclipse/ui/internal/ViewerActionBuilder
      72: dup
      73: invokespecial #644                // Method org/eclipse/ui/internal/ViewerActionBuilder."<init>":()V
      76: astore_2
      77: aload_0
      78: getfield      #562                // Field staticActionBuilders:Ljava/util/Map;
      81: aload_1
      82: aload_2
      83: invokeinterface #660,  3          // InterfaceMethod java/util/Map.put:(Ljava/lang/Object;Ljava/lang/Object;)Ljava/lang/Object;
      88: pop
      89: aload_2
      90: aload_1
      91: aload_0
      92: getfield      #568                // Field selProvider:Lorg/eclipse/jface/viewers/ISelectionProvider;
      95: aload_0
      96: getfield      #569                // Field part:Lorg/eclipse/ui/IWorkbenchPart;
      99: invokevirtual #647                // Method org/eclipse/ui/internal/ViewerActionBuilder.readViewerContributions:(Ljava/lang/String;Lorg/eclipse/jface/viewers/ISelectionProvider;Lorg/eclipse/ui/IWorkbenchPart;)Z
     102: pop
     103: return

  public void dispose();
    Code:
       0: aload_0
       1: invokevirtual #628                // Method clearStaticActions:()V
       4: invokestatic  #594                // Method org/eclipse/core/runtime/Platform.getExtensionRegistry:()Lorg/eclipse/core/runtime/IExtensionRegistry;
       7: aload_0
       8: invokeinterface #670,  2          // InterfaceMethod org/eclipse/core/runtime/IExtensionRegistry.removeRegistryChangeListener:(Lorg/eclipse/core/runtime/IRegistryChangeListener;)V
      13: aload_0
      14: getfield      #566                // Field menu:Lorg/eclipse/jface/action/MenuManager;
      17: aload_0
      18: invokevirtual #612                // Method org/eclipse/jface/action/MenuManager.removeMenuListener:(Lorg/eclipse/jface/action/IMenuListener;)V
      21: aload_0
      22: getfield      #565                // Field menuModel:Lorg/eclipse/e4/ui/model/application/ui/menu/MPopupMenu;
      25: ifnull        112
      28: aload_0
      29: getfield      #564                // Field modelPart:Lorg/eclipse/e4/ui/model/application/ui/basic/MPart;
      32: invokeinterface #674,  1          // InterfaceMethod org/eclipse/e4/ui/model/application/ui/basic/MPart.getContext:()Lorg/eclipse/e4/core/contexts/IEclipseContext;
      37: ldc           #5                  // class org/eclipse/e4/ui/workbench/swt/factories/IRendererFactory
      39: invokeinterface #672,  2          // InterfaceMethod org/eclipse/e4/core/contexts/IEclipseContext.get:(Ljava/lang/Class;)Ljava/lang/Object;
      44: checkcast     #5                  // class org/eclipse/e4/ui/workbench/swt/factories/IRendererFactory
      47: astore_1
      48: aload_1
      49: aload_0
      50: getfield      #565                // Field menuModel:Lorg/eclipse/e4/ui/model/application/ui/menu/MPopupMenu;
      53: aconst_null
      54: invokeinterface #683,  3          // InterfaceMethod org/eclipse/e4/ui/workbench/swt/factories/IRendererFactory.getRenderer:(Lorg/eclipse/e4/ui/model/application/ui/MUIElement;Ljava/lang/Object;)Lorg/eclipse/e4/ui/internal/workbench/swt/AbstractPartRenderer;
      59: astore_2
      60: aload_2
      61: instanceof    #290                // class org/eclipse/e4/ui/workbench/renderers/swt/MenuManagerRenderer
      64: ifeq          93
      67: aload_2
      68: checkcast     #290                // class org/eclipse/e4/ui/workbench/renderers/swt/MenuManagerRenderer
      71: astore_3
      72: aload_0
      73: aload_3
      74: aload_0
      75: getfield      #565                // Field menuModel:Lorg/eclipse/e4/ui/model/application/ui/menu/MPopupMenu;
      78: invokevirtual #641                // Method unlink:(Lorg/eclipse/e4/ui/workbench/renderers/swt/MenuManagerRenderer;Lorg/eclipse/e4/ui/model/application/ui/menu/MMenu;)V
      81: aload_3
      82: aload_0
      83: getfield      #565                // Field menuModel:Lorg/eclipse/e4/ui/model/application/ui/menu/MPopupMenu;
      86: aload_0
      87: getfield      #566                // Field menu:Lorg/eclipse/jface/action/MenuManager;
      90: invokevirtual #608                // Method org/eclipse/e4/ui/workbench/renderers/swt/MenuManagerRenderer.clearModelToManager:(Lorg/eclipse/e4/ui/model/application/ui/menu/MMenu;Lorg/eclipse/jface/action/MenuManager;)V
      93: aload_0
      94: getfield      #564                // Field modelPart:Lorg/eclipse/e4/ui/model/application/ui/basic/MPart;
      97: invokeinterface #673,  1          // InterfaceMethod org/eclipse/e4/ui/model/application/ui/basic/MPart.getMenus:()Ljava/util/List;
     102: aload_0
     103: getfield      #565                // Field menuModel:Lorg/eclipse/e4/ui/model/application/ui/menu/MPopupMenu;
     106: invokeinterface #655,  2          // InterfaceMethod java/util/List.remove:(Ljava/lang/Object;)Z
     111: pop
     112: return

  private void unlink(org.eclipse.e4.ui.workbench.renderers.swt.MenuManagerRenderer, org.eclipse.e4.ui.model.application.ui.menu.MMenu);
    Code:
       0: aload_2
       1: invokeinterface #676,  1          // InterfaceMethod org/eclipse/e4/ui/model/application/ui/menu/MMenu.getChildren:()Ljava/util/List;
       6: invokeinterface #656,  1          // InterfaceMethod java/util/List.iterator:()Ljava/util/Iterator;
      11: astore        4
      13: goto          136
      16: aload         4
      18: invokeinterface #652,  1          // InterfaceMethod java/util/Iterator.next:()Ljava/lang/Object;
      23: checkcast     #287                // class org/eclipse/e4/ui/model/application/ui/menu/MMenuElement
      26: astore_3
      27: aload_3
      28: invokestatic  #595                // Method org/eclipse/e4/ui/internal/workbench/OpaqueElementUtil.isOpaqueMenuItem:(Lorg/eclipse/e4/ui/model/application/ui/MUIElement;)Z
      31: ifne          41
      34: aload_3
      35: invokestatic  #596                // Method org/eclipse/e4/ui/internal/workbench/OpaqueElementUtil.isOpaqueMenuSeparator:(Lorg/eclipse/e4/ui/model/application/ui/MUIElement;)Z
      38: ifeq          73
      41: aload_3
      42: invokestatic  #598                // Method org/eclipse/e4/ui/internal/workbench/OpaqueElementUtil.getOpaqueItem:(Lorg/eclipse/e4/ui/model/application/ui/MUIElement;)Ljava/lang/Object;
      45: astore        5
      47: aload         5
      49: instanceof    #291                // class org/eclipse/jface/action/IContributionItem
      52: ifeq          136
      55: aload_1
      56: aload_3
      57: aload         5
      59: checkcast     #291                // class org/eclipse/jface/action/IContributionItem
      62: invokevirtual #606                // Method org/eclipse/e4/ui/workbench/renderers/swt/MenuManagerRenderer.clearModelToContribution:(Lorg/eclipse/e4/ui/model/application/ui/menu/MMenuElement;Lorg/eclipse/jface/action/IContributionItem;)V
      65: aload_3
      66: invokestatic  #597                // Method org/eclipse/e4/ui/internal/workbench/OpaqueElementUtil.clearOpaqueItem:(Lorg/eclipse/e4/ui/model/application/ui/MUIElement;)Ljava/lang/Object;
      69: pop
      70: goto          136
      73: aload_3
      74: instanceof    #286                // class org/eclipse/e4/ui/model/application/ui/menu/MMenu
      77: ifeq          117
      80: aload_3
      81: checkcast     #286                // class org/eclipse/e4/ui/model/application/ui/menu/MMenu
      84: astore        5
      86: aload_0
      87: aload_1
      88: aload         5
      90: invokevirtual #641                // Method unlink:(Lorg/eclipse/e4/ui/workbench/renderers/swt/MenuManagerRenderer;Lorg/eclipse/e4/ui/model/application/ui/menu/MMenu;)V
      93: aload_1
      94: aload         5
      96: invokevirtual #607                // Method org/eclipse/e4/ui/workbench/renderers/swt/MenuManagerRenderer.getManager:(Lorg/eclipse/e4/ui/model/application/ui/menu/MMenu;)Lorg/eclipse/jface/action/MenuManager;
      99: astore        6
     101: aload         6
     103: ifnull        136
     106: aload_1
     107: aload         5
     109: aload         6
     111: invokevirtual #608                // Method org/eclipse/e4/ui/workbench/renderers/swt/MenuManagerRenderer.clearModelToManager:(Lorg/eclipse/e4/ui/model/application/ui/menu/MMenu;Lorg/eclipse/jface/action/MenuManager;)V
     114: goto          136
     117: aload_1
     118: aload_3
     119: invokevirtual #605                // Method org/eclipse/e4/ui/workbench/renderers/swt/MenuManagerRenderer.getContribution:(Lorg/eclipse/e4/ui/model/application/ui/menu/MMenuElement;)Lorg/eclipse/jface/action/IContributionItem;
     122: astore        5
     124: aload         5
     126: ifnull        136
     129: aload_1
     130: aload_3
     131: aload         5
     133: invokevirtual #606                // Method org/eclipse/e4/ui/workbench/renderers/swt/MenuManagerRenderer.clearModelToContribution:(Lorg/eclipse/e4/ui/model/application/ui/menu/MMenuElement;Lorg/eclipse/jface/action/IContributionItem;)V
     136: aload         4
     138: invokeinterface #651,  1          // InterfaceMethod java/util/Iterator.hasNext:()Z
     143: ifne          16
     146: return

  public void registryChanged(org.eclipse.core.runtime.IRegistryChangeEvent);
    Code:
       0: invokestatic  #621                // Method org/eclipse/swt/widgets/Display.getDefault:()Lorg/eclipse/swt/widgets/Display;
       3: astore_2
       4: aload_0
       5: getfield      #569                // Field part:Lorg/eclipse/ui/IWorkbenchPart;
       8: ifnull        41
      11: aload_0
      12: getfield      #569                // Field part:Lorg/eclipse/ui/IWorkbenchPart;
      15: invokeinterface #690,  1          // InterfaceMethod org/eclipse/ui/IWorkbenchPart.getSite:()Lorg/eclipse/ui/IWorkbenchPartSite;
      20: invokeinterface #691,  1          // InterfaceMethod org/eclipse/ui/IWorkbenchPartSite.getPage:()Lorg/eclipse/ui/IWorkbenchPage;
      25: invokeinterface #689,  1          // InterfaceMethod org/eclipse/ui/IWorkbenchPage.getWorkbenchWindow:()Lorg/eclipse/ui/IWorkbenchWindow;
      30: invokeinterface #694,  1          // InterfaceMethod org/eclipse/ui/IWorkbenchWindow.getWorkbench:()Lorg/eclipse/ui/IWorkbench;
      35: invokeinterface #688,  1          // InterfaceMethod org/eclipse/ui/IWorkbench.getDisplay:()Lorg/eclipse/swt/widgets/Display;
      40: astore_2
      41: aload_1
      42: invokeinterface #671,  1          // InterfaceMethod org/eclipse/core/runtime/IRegistryChangeEvent.getExtensionDeltas:()[Lorg/eclipse/core/runtime/IExtensionDelta;
      47: astore_3
      48: aload_3
      49: dup
      50: astore        7
      52: arraylength
      53: istore        6
      55: iconst_0
      56: istore        5
      58: goto          202
      61: aload         7
      63: iload         5
      65: aaload
      66: astore        4
      68: aload         4
      70: invokeinterface #666,  1          // InterfaceMethod org/eclipse/core/runtime/IExtensionDelta.getExtensionPoint:()Lorg/eclipse/core/runtime/IExtensionPoint;
      75: astore        8
      77: aload         8
      79: invokeinterface #668,  1          // InterfaceMethod org/eclipse/core/runtime/IExtensionPoint.getContributor:()Lorg/eclipse/core/runtime/IContributor;
      84: invokeinterface #663,  1          // InterfaceMethod org/eclipse/core/runtime/IContributor.getName:()Ljava/lang/String;
      89: getstatic     #570                // Field org/eclipse/ui/internal/WorkbenchPlugin.PI_WORKBENCH:Ljava/lang/String;
      92: invokevirtual #576                // Method java/lang/String.equals:(Ljava/lang/Object;)Z
      95: ifeq          199
      98: aload         8
     100: invokeinterface #667,  1          // InterfaceMethod org/eclipse/core/runtime/IExtensionPoint.getSimpleIdentifier:()Ljava/lang/String;
     105: ldc_w         #249                // String popupMenus
     108: invokevirtual #576                // Method java/lang/String.equals:(Ljava/lang/Object;)Z
     111: ifeq          199
     114: iconst_0
     115: istore        9
     117: aload         4
     119: invokeinterface #665,  1          // InterfaceMethod org/eclipse/core/runtime/IExtensionDelta.getExtension:()Lorg/eclipse/core/runtime/IExtension;
     124: invokeinterface #664,  1          // InterfaceMethod org/eclipse/core/runtime/IExtension.getConfigurationElements:()[Lorg/eclipse/core/runtime/IConfigurationElement;
     129: astore        10
     131: aload         10
     133: dup
     134: astore        14
     136: arraylength
     137: istore        13
     139: iconst_0
     140: istore        12
     142: goto          177
     145: aload         14
     147: iload         12
     149: aaload
     150: astore        11
     152: aload         11
     154: invokeinterface #662,  1          // InterfaceMethod org/eclipse/core/runtime/IConfigurationElement.getName:()Ljava/lang/String;
     159: ldc_w         #250                // String viewerContribution
     162: invokevirtual #576                // Method java/lang/String.equals:(Ljava/lang/Object;)Z
     165: ifeq          174
     168: iconst_1
     169: istore        9
     171: goto          184
     174: iinc          12, 1
     177: iload         12
     179: iload         13
     181: if_icmplt     145
     184: iload         9
     186: ifeq          199
     189: aload_2
     190: aload_0
     191: invokedynamic #699,  0            // InvokeDynamic #0:run:(Lorg/eclipse/ui/internal/PopupMenuExtender;)Ljava/lang/Runnable;
     196: invokevirtual #620                // Method org/eclipse/swt/widgets/Display.syncExec:(Ljava/lang/Runnable;)V
     199: iinc          5, 1
     202: iload         5
     204: iload         6
     206: if_icmplt     61
     209: return

  public org.eclipse.jface.action.MenuManager getManager();
    Code:
       0: aload_0
       1: getfield      #566                // Field menu:Lorg/eclipse/jface/action/MenuManager;
       4: areturn

  private void lambda$0(org.eclipse.ui.IWorkbench);
    Code:
       0: aload_1
       1: checkcast     #313                // class org/eclipse/ui/internal/Workbench
       4: astore_2
       5: aload_0
       6: aload_2
       7: invokevirtual #638                // Method runCleanUp:(Lorg/eclipse/ui/internal/Workbench;)V
      10: return
}
