Compiled from "ViewPluginAction.java"
public final class org.eclipse.ui.internal.ViewPluginAction extends org.eclipse.ui.internal.PartPluginAction {
  private org.eclipse.ui.IViewPart viewPart;

  public org.eclipse.ui.internal.ViewPluginAction(org.eclipse.core.runtime.IConfigurationElement, org.eclipse.ui.IViewPart, java.lang.String, int);
    Code:
       0: aload_0
       1: aload_1
       2: aload_3
       3: iload         4
       5: invokespecial #56                 // Method org/eclipse/ui/internal/PartPluginAction."<init>":(Lorg/eclipse/core/runtime/IConfigurationElement;Ljava/lang/String;I)V
       8: aload_0
       9: aload_2
      10: putfield      #51                 // Field viewPart:Lorg/eclipse/ui/IViewPart;
      13: aload_0
      14: aload_2
      15: invokevirtual #58                 // Method registerSelectionListener:(Lorg/eclipse/ui/IWorkbenchPart;)V
      18: return

  protected org.eclipse.ui.IActionDelegate validateDelegate(java.lang.Object) throws org.eclipse.ui.WorkbenchException;
    Code:
       0: aload_1
       1: instanceof    #25                 // class org/eclipse/ui/IViewActionDelegate
       4: ifeq          12
       7: aload_1
       8: checkcast     #25                 // class org/eclipse/ui/IViewActionDelegate
      11: areturn
      12: new           #26                 // class org/eclipse/ui/WorkbenchException
      15: dup
      16: ldc           #1                  // String Action must implement IViewActionDelegate
      18: invokespecial #52                 // Method org/eclipse/ui/WorkbenchException."<init>":(Ljava/lang/String;)V
      21: athrow

  protected void initDelegate();
    Code:
       0: aload_0
       1: invokespecial #54                 // Method org/eclipse/ui/internal/PartPluginAction.initDelegate:()V
       4: aload_0
       5: invokevirtual #57                 // Method getDelegate:()Lorg/eclipse/ui/IActionDelegate;
       8: checkcast     #25                 // class org/eclipse/ui/IViewActionDelegate
      11: aload_0
      12: getfield      #51                 // Field viewPart:Lorg/eclipse/ui/IViewPart;
      15: invokeinterface #60,  2           // InterfaceMethod org/eclipse/ui/IViewActionDelegate.init:(Lorg/eclipse/ui/IViewPart;)V
      20: return

  public boolean isOkToCreateDelegate();
    Code:
       0: aload_0
       1: invokespecial #55                 // Method org/eclipse/ui/internal/PartPluginAction.isOkToCreateDelegate:()Z
       4: ifeq          16
       7: aload_0
       8: getfield      #51                 // Field viewPart:Lorg/eclipse/ui/IViewPart;
      11: ifnull        16
      14: iconst_1
      15: ireturn
      16: iconst_0
      17: ireturn

  public void dispose();
    Code:
       0: aload_0
       1: aload_0
       2: getfield      #51                 // Field viewPart:Lorg/eclipse/ui/IViewPart;
       5: invokevirtual #59                 // Method unregisterSelectionListener:(Lorg/eclipse/ui/IWorkbenchPart;)V
       8: aload_0
       9: invokespecial #53                 // Method org/eclipse/ui/internal/PartPluginAction.dispose:()V
      12: return
}
