Compiled from "Workbench.java"
class org.eclipse.ui.internal.Workbench$35 extends org.eclipse.ui.internal.StartupThreading$StartupRunnable {
  final org.eclipse.ui.internal.Workbench this$0;

  private final org.eclipse.ui.internal.services.SourceProviderService val$sourceProviderService;

  org.eclipse.ui.internal.Workbench$35(org.eclipse.ui.internal.Workbench, org.eclipse.ui.internal.services.SourceProviderService);
    Code:
       0: aload_0
       1: aload_1
       2: putfield      #55                 // Field this$0:Lorg/eclipse/ui/internal/Workbench;
       5: aload_0
       6: aload_2
       7: putfield      #56                 // Field val$sourceProviderService:Lorg/eclipse/ui/internal/services/SourceProviderService;
      10: aload_0
      11: invokespecial #57                 // Method org/eclipse/ui/internal/StartupThreading$StartupRunnable."<init>":()V
      14: return

  public void runWithException();
    Code:
       0: aload_0
       1: getfield      #56                 // Field val$sourceProviderService:Lorg/eclipse/ui/internal/services/SourceProviderService;
       4: ldc           #1                  // String activeFocusControlId
       6: invokevirtual #59                 // Method org/eclipse/ui/internal/services/SourceProviderService.getSourceProvider:(Ljava/lang/String;)Lorg/eclipse/ui/ISourceProvider;
       9: checkcast     #32                 // class org/eclipse/ui/internal/menus/FocusControlSourceProvider
      12: astore_1
      13: aload_0
      14: getfield      #55                 // Field this$0:Lorg/eclipse/ui/internal/Workbench;
      17: getfield      #54                 // Field org/eclipse/ui/internal/Workbench.serviceLocator:Lorg/eclipse/ui/internal/services/ServiceLocator;
      20: ldc           #3                  // class org/eclipse/ui/swt/IFocusService
      22: aload_1
      23: invokevirtual #58                 // Method org/eclipse/ui/internal/services/ServiceLocator.registerService:(Ljava/lang/Class;Ljava/lang/Object;)V
      26: aload_0
      27: getfield      #55                 // Field this$0:Lorg/eclipse/ui/internal/Workbench;
      30: aload_0
      31: getfield      #56                 // Field val$sourceProviderService:Lorg/eclipse/ui/internal/services/SourceProviderService;
      34: ldc           #2                  // String activeMenu
      36: invokevirtual #59                 // Method org/eclipse/ui/internal/services/SourceProviderService.getSourceProvider:(Ljava/lang/String;)Lorg/eclipse/ui/ISourceProvider;
      39: checkcast     #33                 // class org/eclipse/ui/internal/services/MenuSourceProvider
      42: putfield      #53                 // Field org/eclipse/ui/internal/Workbench.menuSourceProvider:Lorg/eclipse/ui/internal/services/MenuSourceProvider;
      45: return
}
