Compiled from "Workbench.java"
class org.eclipse.ui.internal.Workbench$39 extends org.eclipse.ui.internal.StartupThreading$StartupRunnable {
  final org.eclipse.ui.internal.Workbench this$0;

  private final org.eclipse.ui.WorkbenchException val$e;

  org.eclipse.ui.internal.Workbench$39(org.eclipse.ui.internal.Workbench, org.eclipse.ui.WorkbenchException);
    Code:
       0: aload_0
       1: aload_1
       2: putfield      #46                 // Field this$0:Lorg/eclipse/ui/internal/Workbench;
       5: aload_0
       6: aload_2
       7: putfield      #45                 // Field val$e:Lorg/eclipse/ui/WorkbenchException;
      10: aload_0
      11: invokespecial #51                 // Method org/eclipse/ui/internal/StartupThreading$StartupRunnable."<init>":()V
      14: return

  public void runWithException() throws java.lang.Throwable;
    Code:
       0: aconst_null
       1: getstatic     #47                 // Field org/eclipse/ui/internal/WorkbenchMessages.Problems_Opening_Page:Ljava/lang/String;
       4: aload_0
       5: getfield      #45                 // Field val$e:Lorg/eclipse/ui/WorkbenchException;
       8: invokevirtual #49                 // Method org/eclipse/ui/WorkbenchException.getMessage:()Ljava/lang/String;
      11: aload_0
      12: getfield      #45                 // Field val$e:Lorg/eclipse/ui/WorkbenchException;
      15: invokevirtual #50                 // Method org/eclipse/ui/WorkbenchException.getStatus:()Lorg/eclipse/core/runtime/IStatus;
      18: invokestatic  #48                 // Method org/eclipse/jface/dialogs/ErrorDialog.openError:(Lorg/eclipse/swt/widgets/Shell;Ljava/lang/String;Ljava/lang/String;Lorg/eclipse/core/runtime/IStatus;)I
      21: pop
      22: return
}
