Compiled from "WorkingSet.java"
class org.eclipse.ui.internal.WorkingSet$2 extends org.eclipse.jface.util.SafeRunnable {
  final org.eclipse.ui.internal.WorkingSet this$0;

  private final org.eclipse.ui.IPersistableElement val$persistable;

  private final org.eclipse.ui.IMemento val$itemMemento;

  org.eclipse.ui.internal.WorkingSet$2(org.eclipse.ui.internal.WorkingSet, java.lang.String, org.eclipse.ui.IPersistableElement, org.eclipse.ui.IMemento);
    Code:
       0: aload_0
       1: aload_1
       2: putfield      #36                 // Field this$0:Lorg/eclipse/ui/internal/WorkingSet;
       5: aload_0
       6: aload_3
       7: putfield      #35                 // Field val$persistable:Lorg/eclipse/ui/IPersistableElement;
      10: aload_0
      11: aload         4
      13: putfield      #34                 // Field val$itemMemento:Lorg/eclipse/ui/IMemento;
      16: aload_0
      17: aload_2
      18: invokespecial #37                 // Method org/eclipse/jface/util/SafeRunnable."<init>":(Ljava/lang/String;)V
      21: return

  public void run() throws java.lang.Exception;
    Code:
       0: aload_0
       1: getfield      #35                 // Field val$persistable:Lorg/eclipse/ui/IPersistableElement;
       4: aload_0
       5: getfield      #34                 // Field val$itemMemento:Lorg/eclipse/ui/IMemento;
       8: invokeinterface #38,  2           // InterfaceMethod org/eclipse/ui/IPersistableElement.saveState:(Lorg/eclipse/ui/IMemento;)V
      13: return
}
