Compiled from "ZKFailoverController.java"
class org.apache.hadoop.ha.ZKFailoverController$ActiveAttemptRecord {
  private final boolean succeeded;

  private final java.lang.String status;

  private final long nanoTime;

  public org.apache.hadoop.ha.ZKFailoverController$ActiveAttemptRecord(boolean, java.lang.String);
    Code:
       0: aload_0
       1: invokespecial #4                  // Method java/lang/Object."<init>":()V
       4: aload_0
       5: iload_1
       6: putfield      #2                  // Field succeeded:Z
       9: aload_0
      10: aload_2
      11: putfield      #1                  // Field status:Ljava/lang/String;
      14: aload_0
      15: invokestatic  #5                  // Method java/lang/System.nanoTime:()J
      18: putfield      #3                  // Field nanoTime:J
      21: return

  static long access$200(org.apache.hadoop.ha.ZKFailoverController$ActiveAttemptRecord);
    Code:
       0: aload_0
       1: getfield      #3                  // Field nanoTime:J
       4: lreturn

  static boolean access$500(org.apache.hadoop.ha.ZKFailoverController$ActiveAttemptRecord);
    Code:
       0: aload_0
       1: getfield      #2                  // Field succeeded:Z
       4: ireturn

  static java.lang.String access$600(org.apache.hadoop.ha.ZKFailoverController$ActiveAttemptRecord);
    Code:
       0: aload_0
       1: getfield      #1                  // Field status:Ljava/lang/String;
       4: areturn
}
