Compiled from "ProjectingMethodInterceptor.java"
class org.springframework.data.projection.ProjectingMethodInterceptor implements org.aopalliance.intercept.MethodInterceptor {
  private final org.springframework.data.projection.ProjectionFactory factory;

  private final org.aopalliance.intercept.MethodInterceptor delegate;

  private final org.springframework.core.convert.ConversionService conversionService;

  public java.lang.Object invoke(org.aopalliance.intercept.MethodInvocation) throws java.lang.Throwable;
    Code:
       0: aload_0
       1: getfield      #1                  // Field delegate:Lorg/aopalliance/intercept/MethodInterceptor;
       4: aload_1
       5: invokeinterface #2,  2            // InterfaceMethod org/aopalliance/intercept/MethodInterceptor.invoke:(Lorg/aopalliance/intercept/MethodInvocation;)Ljava/lang/Object;
      10: astore_2
      11: aload_2
      12: ifnonnull     17
      15: aconst_null
      16: areturn
      17: aload_1
      18: invokeinterface #3,  1            // InterfaceMethod org/aopalliance/intercept/MethodInvocation.getMethod:()Ljava/lang/reflect/Method;
      23: invokestatic  #4                  // Method org/springframework/data/util/ClassTypeInformation.fromReturnTypeOf:(Ljava/lang/reflect/Method;)Lorg/springframework/data/util/TypeInformation;
      26: astore_3
      27: aload_3
      28: invokeinterface #5,  1            // InterfaceMethod org/springframework/data/util/TypeInformation.getType:()Ljava/lang/Class;
      33: astore        4
      35: aload_3
      36: invokeinterface #6,  1            // InterfaceMethod org/springframework/data/util/TypeInformation.isCollectionLike:()Z
      41: ifeq          62
      44: aload         4
      46: invokestatic  #7                  // Method org/springframework/util/ClassUtils.isPrimitiveArray:(Ljava/lang/Class;)Z
      49: ifne          62
      52: aload_0
      53: aload_2
      54: invokestatic  #8                  // Method asCollection:(Ljava/lang/Object;)Ljava/util/Collection;
      57: aload_3
      58: invokespecial #9                  // Method projectCollectionElements:(Ljava/util/Collection;Lorg/springframework/data/util/TypeInformation;)Ljava/lang/Object;
      61: areturn
      62: aload_3
      63: invokeinterface #10,  1           // InterfaceMethod org/springframework/data/util/TypeInformation.isMap:()Z
      68: ifeq          81
      71: aload_0
      72: aload_2
      73: checkcast     #11                 // class java/util/Map
      76: aload_3
      77: invokespecial #12                 // Method projectMapValues:(Ljava/util/Map;Lorg/springframework/data/util/TypeInformation;)Ljava/util/Map;
      80: areturn
      81: aload_0
      82: aload_2
      83: aload         4
      85: invokespecial #13                 // Method conversionRequiredAndPossible:(Ljava/lang/Object;Ljava/lang/Class;)Z
      88: ifeq          104
      91: aload_0
      92: getfield      #14                 // Field conversionService:Lorg/springframework/core/convert/ConversionService;
      95: aload_2
      96: aload         4
      98: invokeinterface #15,  3           // InterfaceMethod org/springframework/core/convert/ConversionService.convert:(Ljava/lang/Object;Ljava/lang/Class;)Ljava/lang/Object;
     103: areturn
     104: aload_0
     105: aload_2
     106: aload         4
     108: invokespecial #16                 // Method getProjection:(Ljava/lang/Object;Ljava/lang/Class;)Ljava/lang/Object;
     111: areturn

  private java.lang.Object projectCollectionElements(java.util.Collection<?>, org.springframework.data.util.TypeInformation<?>);
    Code:
       0: aload_2
       1: invokeinterface #5,  1            // InterfaceMethod org/springframework/data/util/TypeInformation.getType:()Ljava/lang/Class;
       6: astore_3
       7: aload_2
       8: invokeinterface #17,  1           // InterfaceMethod org/springframework/data/util/TypeInformation.getComponentType:()Lorg/springframework/data/util/TypeInformation;
      13: astore        4
      15: aload_3
      16: invokevirtual #18                 // Method java/lang/Class.isArray:()Z
      19: ifeq          27
      22: ldc           #19                 // class java/util/List
      24: goto          28
      27: aload_3
      28: aload         4
      30: ifnull        43
      33: aload         4
      35: invokeinterface #5,  1            // InterfaceMethod org/springframework/data/util/TypeInformation.getType:()Ljava/lang/Class;
      40: goto          44
      43: aconst_null
      44: aload_1
      45: invokeinterface #20,  1           // InterfaceMethod java/util/Collection.size:()I
      50: invokestatic  #21                 // Method org/springframework/core/CollectionFactory.createCollection:(Ljava/lang/Class;Ljava/lang/Class;I)Ljava/util/Collection;
      53: astore        5
      55: aload_1
      56: invokeinterface #22,  1           // InterfaceMethod java/util/Collection.iterator:()Ljava/util/Iterator;
      61: astore        6
      63: aload         6
      65: invokeinterface #23,  1           // InterfaceMethod java/util/Iterator.hasNext:()Z
      70: ifeq          110
      73: aload         6
      75: invokeinterface #24,  1           // InterfaceMethod java/util/Iterator.next:()Ljava/lang/Object;
      80: astore        7
      82: aload         5
      84: aload_0
      85: aload         7
      87: aload_2
      88: invokeinterface #25,  1           // InterfaceMethod org/springframework/data/util/TypeInformation.getRequiredComponentType:()Lorg/springframework/data/util/TypeInformation;
      93: invokeinterface #5,  1            // InterfaceMethod org/springframework/data/util/TypeInformation.getType:()Ljava/lang/Class;
      98: invokespecial #16                 // Method getProjection:(Ljava/lang/Object;Ljava/lang/Class;)Ljava/lang/Object;
     101: invokeinterface #26,  2           // InterfaceMethod java/util/Collection.add:(Ljava/lang/Object;)Z
     106: pop
     107: goto          63
     110: aload_3
     111: invokevirtual #18                 // Method java/lang/Class.isArray:()Z
     114: ifeq          152
     117: aload         5
     119: aload_2
     120: invokeinterface #25,  1           // InterfaceMethod org/springframework/data/util/TypeInformation.getRequiredComponentType:()Lorg/springframework/data/util/TypeInformation;
     125: invokeinterface #5,  1            // InterfaceMethod org/springframework/data/util/TypeInformation.getType:()Ljava/lang/Class;
     130: aload         5
     132: invokeinterface #20,  1           // InterfaceMethod java/util/Collection.size:()I
     137: invokestatic  #27                 // Method java/lang/reflect/Array.newInstance:(Ljava/lang/Class;I)Ljava/lang/Object;
     140: checkcast     #28                 // class "[Ljava/lang/Object;"
     143: checkcast     #28                 // class "[Ljava/lang/Object;"
     146: invokeinterface #29,  2           // InterfaceMethod java/util/Collection.toArray:([Ljava/lang/Object;)[Ljava/lang/Object;
     151: areturn
     152: aload         5
     154: areturn

  private java.util.Map<java.lang.Object, java.lang.Object> projectMapValues(java.util.Map<?, ?>, org.springframework.data.util.TypeInformation<?>);
    Code:
       0: aload_2
       1: invokeinterface #5,  1            // InterfaceMethod org/springframework/data/util/TypeInformation.getType:()Ljava/lang/Class;
       6: aload_1
       7: invokeinterface #30,  1           // InterfaceMethod java/util/Map.size:()I
      12: invokestatic  #31                 // Method org/springframework/core/CollectionFactory.createMap:(Ljava/lang/Class;I)Ljava/util/Map;
      15: astore_3
      16: aload_1
      17: invokeinterface #32,  1           // InterfaceMethod java/util/Map.entrySet:()Ljava/util/Set;
      22: invokeinterface #33,  1           // InterfaceMethod java/util/Set.iterator:()Ljava/util/Iterator;
      27: astore        4
      29: aload         4
      31: invokeinterface #23,  1           // InterfaceMethod java/util/Iterator.hasNext:()Z
      36: ifeq          90
      39: aload         4
      41: invokeinterface #24,  1           // InterfaceMethod java/util/Iterator.next:()Ljava/lang/Object;
      46: checkcast     #34                 // class java/util/Map$Entry
      49: astore        5
      51: aload_3
      52: aload         5
      54: invokeinterface #35,  1           // InterfaceMethod java/util/Map$Entry.getKey:()Ljava/lang/Object;
      59: aload_0
      60: aload         5
      62: invokeinterface #36,  1           // InterfaceMethod java/util/Map$Entry.getValue:()Ljava/lang/Object;
      67: aload_2
      68: invokeinterface #37,  1           // InterfaceMethod org/springframework/data/util/TypeInformation.getRequiredMapValueType:()Lorg/springframework/data/util/TypeInformation;
      73: invokeinterface #5,  1            // InterfaceMethod org/springframework/data/util/TypeInformation.getType:()Ljava/lang/Class;
      78: invokespecial #16                 // Method getProjection:(Ljava/lang/Object;Ljava/lang/Class;)Ljava/lang/Object;
      81: invokeinterface #38,  3           // InterfaceMethod java/util/Map.put:(Ljava/lang/Object;Ljava/lang/Object;)Ljava/lang/Object;
      86: pop
      87: goto          29
      90: aload_3
      91: areturn

  private java.lang.Object getProjection(java.lang.Object, java.lang.Class<?>);
    Code:
       0: aload_1
       1: ifnull        15
       4: aload_2
       5: aload_1
       6: invokevirtual #39                 // Method java/lang/Object.getClass:()Ljava/lang/Class;
       9: invokestatic  #40                 // Method org/springframework/util/ClassUtils.isAssignable:(Ljava/lang/Class;Ljava/lang/Class;)Z
      12: ifeq          19
      15: aload_1
      16: goto          30
      19: aload_0
      20: getfield      #41                 // Field factory:Lorg/springframework/data/projection/ProjectionFactory;
      23: aload_2
      24: aload_1
      25: invokeinterface #42,  3           // InterfaceMethod org/springframework/data/projection/ProjectionFactory.createProjection:(Ljava/lang/Class;Ljava/lang/Object;)Ljava/lang/Object;
      30: areturn

  private boolean conversionRequiredAndPossible(java.lang.Object, java.lang.Class<?>);
    Code:
       0: aload_1
       1: ifnull        12
       4: aload_2
       5: aload_1
       6: invokevirtual #43                 // Method java/lang/Class.isInstance:(Ljava/lang/Object;)Z
       9: ifeq          14
      12: iconst_0
      13: ireturn
      14: aload_0
      15: getfield      #14                 // Field conversionService:Lorg/springframework/core/convert/ConversionService;
      18: aload_1
      19: invokevirtual #39                 // Method java/lang/Object.getClass:()Ljava/lang/Class;
      22: aload_2
      23: invokeinterface #44,  3           // InterfaceMethod org/springframework/core/convert/ConversionService.canConvert:(Ljava/lang/Class;Ljava/lang/Class;)Z
      28: ireturn

  private static java.util.Collection<?> asCollection(java.lang.Object);
    Code:
       0: aload_0
       1: ldc           #45                 // String Source object must not be null!
       3: invokestatic  #46                 // Method org/springframework/util/Assert.notNull:(Ljava/lang/Object;Ljava/lang/String;)V
       6: aload_0
       7: instanceof    #47                 // class java/util/Collection
      10: ifeq          18
      13: aload_0
      14: checkcast     #47                 // class java/util/Collection
      17: areturn
      18: aload_0
      19: invokevirtual #39                 // Method java/lang/Object.getClass:()Ljava/lang/Class;
      22: invokevirtual #18                 // Method java/lang/Class.isArray:()Z
      25: ifeq          36
      28: aload_0
      29: invokestatic  #48                 // Method org/springframework/util/ObjectUtils.toObjectArray:(Ljava/lang/Object;)[Ljava/lang/Object;
      32: invokestatic  #49                 // Method java/util/Arrays.asList:([Ljava/lang/Object;)Ljava/util/List;
      35: areturn
      36: aload_0
      37: invokestatic  #50                 // Method java/util/Collections.singleton:(Ljava/lang/Object;)Ljava/util/Set;
      40: areturn

  public org.springframework.data.projection.ProjectingMethodInterceptor(org.springframework.data.projection.ProjectionFactory, org.aopalliance.intercept.MethodInterceptor, org.springframework.core.convert.ConversionService);
    Code:
       0: aload_0
       1: invokespecial #51                 // Method java/lang/Object."<init>":()V
       4: aload_1
       5: ifnonnull     18
       8: new           #52                 // class java/lang/IllegalArgumentException
      11: dup
      12: ldc           #53                 // String factory is marked non-null but is null
      14: invokespecial #54                 // Method java/lang/IllegalArgumentException."<init>":(Ljava/lang/String;)V
      17: athrow
      18: aload_2
      19: ifnonnull     32
      22: new           #52                 // class java/lang/IllegalArgumentException
      25: dup
      26: ldc           #55                 // String delegate is marked non-null but is null
      28: invokespecial #54                 // Method java/lang/IllegalArgumentException."<init>":(Ljava/lang/String;)V
      31: athrow
      32: aload_3
      33: ifnonnull     46
      36: new           #52                 // class java/lang/IllegalArgumentException
      39: dup
      40: ldc           #56                 // String conversionService is marked non-null but is null
      42: invokespecial #54                 // Method java/lang/IllegalArgumentException."<init>":(Ljava/lang/String;)V
      45: athrow
      46: aload_0
      47: aload_1
      48: putfield      #41                 // Field factory:Lorg/springframework/data/projection/ProjectionFactory;
      51: aload_0
      52: aload_2
      53: putfield      #1                  // Field delegate:Lorg/aopalliance/intercept/MethodInterceptor;
      56: aload_0
      57: aload_3
      58: putfield      #14                 // Field conversionService:Lorg/springframework/core/convert/ConversionService;
      61: return
}
