Compiled from "ApiClient.java"
class io.lakefs.clients.api.ApiClient$2 implements okhttp3.Interceptor {
  final io.lakefs.clients.api.ApiClient this$0;

  io.lakefs.clients.api.ApiClient$2(io.lakefs.clients.api.ApiClient);
    Code:
       0: aload_0
       1: aload_1
       2: putfield      #1                  // Field this$0:Lio/lakefs/clients/api/ApiClient;
       5: aload_0
       6: invokespecial #2                  // Method java/lang/Object."<init>":()V
       9: return

  public okhttp3.Response intercept(okhttp3.Interceptor$Chain) throws java.io.IOException;
    Code:
       0: aload_1
       1: invokeinterface #3,  1            // InterfaceMethod okhttp3/Interceptor$Chain.request:()Lokhttp3/Request;
       6: astore_2
       7: aload_1
       8: aload_2
       9: invokeinterface #4,  2            // InterfaceMethod okhttp3/Interceptor$Chain.proceed:(Lokhttp3/Request;)Lokhttp3/Response;
      14: astore_3
      15: aload_2
      16: invokevirtual #5                  // Method okhttp3/Request.tag:()Ljava/lang/Object;
      19: instanceof    #6                  // class io/lakefs/clients/api/ApiCallback
      22: ifeq          58
      25: aload_2
      26: invokevirtual #5                  // Method okhttp3/Request.tag:()Ljava/lang/Object;
      29: checkcast     #6                  // class io/lakefs/clients/api/ApiCallback
      32: astore        4
      34: aload_3
      35: invokevirtual #7                  // Method okhttp3/Response.newBuilder:()Lokhttp3/Response$Builder;
      38: new           #8                  // class io/lakefs/clients/api/ProgressResponseBody
      41: dup
      42: aload_3
      43: invokevirtual #9                  // Method okhttp3/Response.body:()Lokhttp3/ResponseBody;
      46: aload         4
      48: invokespecial #10                 // Method io/lakefs/clients/api/ProgressResponseBody."<init>":(Lokhttp3/ResponseBody;Lio/lakefs/clients/api/ApiCallback;)V
      51: invokevirtual #11                 // Method okhttp3/Response$Builder.body:(Lokhttp3/ResponseBody;)Lokhttp3/Response$Builder;
      54: invokevirtual #12                 // Method okhttp3/Response$Builder.build:()Lokhttp3/Response;
      57: areturn
      58: aload_3
      59: areturn
}
