Compiled from "StagingApi.java"
public class io.lakefs.clients.api.StagingApi {
  private io.lakefs.clients.api.ApiClient localVarApiClient;

  public io.lakefs.clients.api.StagingApi();
    Code:
       0: aload_0
       1: invokestatic  #1                  // Method io/lakefs/clients/api/Configuration.getDefaultApiClient:()Lio/lakefs/clients/api/ApiClient;
       4: invokespecial #2                  // Method "<init>":(Lio/lakefs/clients/api/ApiClient;)V
       7: return

  public io.lakefs.clients.api.StagingApi(io.lakefs.clients.api.ApiClient);
    Code:
       0: aload_0
       1: invokespecial #3                  // Method java/lang/Object."<init>":()V
       4: aload_0
       5: aload_1
       6: putfield      #4                  // Field localVarApiClient:Lio/lakefs/clients/api/ApiClient;
       9: return

  public io.lakefs.clients.api.ApiClient getApiClient();
    Code:
       0: aload_0
       1: getfield      #4                  // Field localVarApiClient:Lio/lakefs/clients/api/ApiClient;
       4: areturn

  public void setApiClient(io.lakefs.clients.api.ApiClient);
    Code:
       0: aload_0
       1: aload_1
       2: putfield      #4                  // Field localVarApiClient:Lio/lakefs/clients/api/ApiClient;
       5: return

  public okhttp3.Call getPhysicalAddressCall(java.lang.String, java.lang.String, java.lang.String, io.lakefs.clients.api.ApiCallback) throws io.lakefs.clients.api.ApiException;
    Code:
       0: aconst_null
       1: astore        5
       3: ldc           #5                  // String /repositories/{repository}/branches/{branch}/staging/backing
       5: ldc           #6                  // String \\{repository\\}
       7: aload_0
       8: getfield      #4                  // Field localVarApiClient:Lio/lakefs/clients/api/ApiClient;
      11: aload_1
      12: invokevirtual #7                  // Method java/lang/String.toString:()Ljava/lang/String;
      15: invokevirtual #8                  // Method io/lakefs/clients/api/ApiClient.escapeString:(Ljava/lang/String;)Ljava/lang/String;
      18: invokevirtual #9                  // Method java/lang/String.replaceAll:(Ljava/lang/String;Ljava/lang/String;)Ljava/lang/String;
      21: ldc           #10                 // String \\{branch\\}
      23: aload_0
      24: getfield      #4                  // Field localVarApiClient:Lio/lakefs/clients/api/ApiClient;
      27: aload_2
      28: invokevirtual #7                  // Method java/lang/String.toString:()Ljava/lang/String;
      31: invokevirtual #8                  // Method io/lakefs/clients/api/ApiClient.escapeString:(Ljava/lang/String;)Ljava/lang/String;
      34: invokevirtual #9                  // Method java/lang/String.replaceAll:(Ljava/lang/String;Ljava/lang/String;)Ljava/lang/String;
      37: astore        6
      39: new           #11                 // class java/util/ArrayList
      42: dup
      43: invokespecial #12                 // Method java/util/ArrayList."<init>":()V
      46: astore        7
      48: new           #11                 // class java/util/ArrayList
      51: dup
      52: invokespecial #12                 // Method java/util/ArrayList."<init>":()V
      55: astore        8
      57: new           #13                 // class java/util/HashMap
      60: dup
      61: invokespecial #14                 // Method java/util/HashMap."<init>":()V
      64: astore        9
      66: new           #13                 // class java/util/HashMap
      69: dup
      70: invokespecial #14                 // Method java/util/HashMap."<init>":()V
      73: astore        10
      75: new           #13                 // class java/util/HashMap
      78: dup
      79: invokespecial #14                 // Method java/util/HashMap."<init>":()V
      82: astore        11
      84: aload_3
      85: ifnull        106
      88: aload         7
      90: aload_0
      91: getfield      #4                  // Field localVarApiClient:Lio/lakefs/clients/api/ApiClient;
      94: ldc           #15                 // String path
      96: aload_3
      97: invokevirtual #16                 // Method io/lakefs/clients/api/ApiClient.parameterToPair:(Ljava/lang/String;Ljava/lang/Object;)Ljava/util/List;
     100: invokeinterface #17,  2           // InterfaceMethod java/util/List.addAll:(Ljava/util/Collection;)Z
     105: pop
     106: iconst_1
     107: anewarray     #18                 // class java/lang/String
     110: dup
     111: iconst_0
     112: ldc           #19                 // String application/json
     114: aastore
     115: astore        12
     117: aload_0
     118: getfield      #4                  // Field localVarApiClient:Lio/lakefs/clients/api/ApiClient;
     121: aload         12
     123: invokevirtual #20                 // Method io/lakefs/clients/api/ApiClient.selectHeaderAccept:([Ljava/lang/String;)Ljava/lang/String;
     126: astore        13
     128: aload         13
     130: ifnull        145
     133: aload         9
     135: ldc           #21                 // String Accept
     137: aload         13
     139: invokeinterface #22,  3           // InterfaceMethod java/util/Map.put:(Ljava/lang/Object;Ljava/lang/Object;)Ljava/lang/Object;
     144: pop
     145: iconst_0
     146: anewarray     #18                 // class java/lang/String
     149: astore        14
     151: aload_0
     152: getfield      #4                  // Field localVarApiClient:Lio/lakefs/clients/api/ApiClient;
     155: aload         14
     157: invokevirtual #23                 // Method io/lakefs/clients/api/ApiClient.selectHeaderContentType:([Ljava/lang/String;)Ljava/lang/String;
     160: astore        15
     162: aload         9
     164: ldc           #24                 // String Content-Type
     166: aload         15
     168: invokeinterface #22,  3           // InterfaceMethod java/util/Map.put:(Ljava/lang/Object;Ljava/lang/Object;)Ljava/lang/Object;
     173: pop
     174: iconst_4
     175: anewarray     #18                 // class java/lang/String
     178: dup
     179: iconst_0
     180: ldc           #25                 // String basic_auth
     182: aastore
     183: dup
     184: iconst_1
     185: ldc           #26                 // String cookie_auth
     187: aastore
     188: dup
     189: iconst_2
     190: ldc           #27                 // String jwt_token
     192: aastore
     193: dup
     194: iconst_3
     195: ldc           #28                 // String oidc_auth
     197: aastore
     198: astore        16
     200: aload_0
     201: getfield      #4                  // Field localVarApiClient:Lio/lakefs/clients/api/ApiClient;
     204: aload         6
     206: ldc           #29                 // String GET
     208: aload         7
     210: aload         8
     212: aload         5
     214: aload         9
     216: aload         10
     218: aload         11
     220: aload         16
     222: aload         4
     224: invokevirtual #30                 // Method io/lakefs/clients/api/ApiClient.buildCall:(Ljava/lang/String;Ljava/lang/String;Ljava/util/List;Ljava/util/List;Ljava/lang/Object;Ljava/util/Map;Ljava/util/Map;Ljava/util/Map;[Ljava/lang/String;Lio/lakefs/clients/api/ApiCallback;)Lokhttp3/Call;
     227: areturn

  private okhttp3.Call getPhysicalAddressValidateBeforeCall(java.lang.String, java.lang.String, java.lang.String, io.lakefs.clients.api.ApiCallback) throws io.lakefs.clients.api.ApiException;
    Code:
       0: aload_1
       1: ifnonnull     14
       4: new           #31                 // class io/lakefs/clients/api/ApiException
       7: dup
       8: ldc           #32                 // String Missing the required parameter \'repository\' when calling getPhysicalAddress(Async)
      10: invokespecial #33                 // Method io/lakefs/clients/api/ApiException."<init>":(Ljava/lang/String;)V
      13: athrow
      14: aload_2
      15: ifnonnull     28
      18: new           #31                 // class io/lakefs/clients/api/ApiException
      21: dup
      22: ldc           #34                 // String Missing the required parameter \'branch\' when calling getPhysicalAddress(Async)
      24: invokespecial #33                 // Method io/lakefs/clients/api/ApiException."<init>":(Ljava/lang/String;)V
      27: athrow
      28: aload_3
      29: ifnonnull     42
      32: new           #31                 // class io/lakefs/clients/api/ApiException
      35: dup
      36: ldc           #35                 // String Missing the required parameter \'path\' when calling getPhysicalAddress(Async)
      38: invokespecial #33                 // Method io/lakefs/clients/api/ApiException."<init>":(Ljava/lang/String;)V
      41: athrow
      42: aload_0
      43: aload_1
      44: aload_2
      45: aload_3
      46: aload         4
      48: invokevirtual #36                 // Method getPhysicalAddressCall:(Ljava/lang/String;Ljava/lang/String;Ljava/lang/String;Lio/lakefs/clients/api/ApiCallback;)Lokhttp3/Call;
      51: astore        5
      53: aload         5
      55: areturn

  public io.lakefs.clients.api.model.StagingLocation getPhysicalAddress(java.lang.String, java.lang.String, java.lang.String) throws io.lakefs.clients.api.ApiException;
    Code:
       0: aload_0
       1: aload_1
       2: aload_2
       3: aload_3
       4: invokevirtual #37                 // Method getPhysicalAddressWithHttpInfo:(Ljava/lang/String;Ljava/lang/String;Ljava/lang/String;)Lio/lakefs/clients/api/ApiResponse;
       7: astore        4
       9: aload         4
      11: invokevirtual #38                 // Method io/lakefs/clients/api/ApiResponse.getData:()Ljava/lang/Object;
      14: checkcast     #39                 // class io/lakefs/clients/api/model/StagingLocation
      17: areturn

  public io.lakefs.clients.api.ApiResponse<io.lakefs.clients.api.model.StagingLocation> getPhysicalAddressWithHttpInfo(java.lang.String, java.lang.String, java.lang.String) throws io.lakefs.clients.api.ApiException;
    Code:
       0: aload_0
       1: aload_1
       2: aload_2
       3: aload_3
       4: aconst_null
       5: invokespecial #40                 // Method getPhysicalAddressValidateBeforeCall:(Ljava/lang/String;Ljava/lang/String;Ljava/lang/String;Lio/lakefs/clients/api/ApiCallback;)Lokhttp3/Call;
       8: astore        4
      10: new           #41                 // class io/lakefs/clients/api/StagingApi$1
      13: dup
      14: aload_0
      15: invokespecial #42                 // Method io/lakefs/clients/api/StagingApi$1."<init>":(Lio/lakefs/clients/api/StagingApi;)V
      18: invokevirtual #43                 // Method io/lakefs/clients/api/StagingApi$1.getType:()Ljava/lang/reflect/Type;
      21: astore        5
      23: aload_0
      24: getfield      #4                  // Field localVarApiClient:Lio/lakefs/clients/api/ApiClient;
      27: aload         4
      29: aload         5
      31: invokevirtual #44                 // Method io/lakefs/clients/api/ApiClient.execute:(Lokhttp3/Call;Ljava/lang/reflect/Type;)Lio/lakefs/clients/api/ApiResponse;
      34: areturn

  public okhttp3.Call getPhysicalAddressAsync(java.lang.String, java.lang.String, java.lang.String, io.lakefs.clients.api.ApiCallback<io.lakefs.clients.api.model.StagingLocation>) throws io.lakefs.clients.api.ApiException;
    Code:
       0: aload_0
       1: aload_1
       2: aload_2
       3: aload_3
       4: aload         4
       6: invokespecial #40                 // Method getPhysicalAddressValidateBeforeCall:(Ljava/lang/String;Ljava/lang/String;Ljava/lang/String;Lio/lakefs/clients/api/ApiCallback;)Lokhttp3/Call;
       9: astore        5
      11: new           #45                 // class io/lakefs/clients/api/StagingApi$2
      14: dup
      15: aload_0
      16: invokespecial #46                 // Method io/lakefs/clients/api/StagingApi$2."<init>":(Lio/lakefs/clients/api/StagingApi;)V
      19: invokevirtual #47                 // Method io/lakefs/clients/api/StagingApi$2.getType:()Ljava/lang/reflect/Type;
      22: astore        6
      24: aload_0
      25: getfield      #4                  // Field localVarApiClient:Lio/lakefs/clients/api/ApiClient;
      28: aload         5
      30: aload         6
      32: aload         4
      34: invokevirtual #48                 // Method io/lakefs/clients/api/ApiClient.executeAsync:(Lokhttp3/Call;Ljava/lang/reflect/Type;Lio/lakefs/clients/api/ApiCallback;)V
      37: aload         5
      39: areturn

  public okhttp3.Call linkPhysicalAddressCall(java.lang.String, java.lang.String, java.lang.String, io.lakefs.clients.api.model.StagingMetadata, io.lakefs.clients.api.ApiCallback) throws io.lakefs.clients.api.ApiException;
    Code:
       0: aload         4
       2: astore        6
       4: ldc           #5                  // String /repositories/{repository}/branches/{branch}/staging/backing
       6: ldc           #6                  // String \\{repository\\}
       8: aload_0
       9: getfield      #4                  // Field localVarApiClient:Lio/lakefs/clients/api/ApiClient;
      12: aload_1
      13: invokevirtual #7                  // Method java/lang/String.toString:()Ljava/lang/String;
      16: invokevirtual #8                  // Method io/lakefs/clients/api/ApiClient.escapeString:(Ljava/lang/String;)Ljava/lang/String;
      19: invokevirtual #9                  // Method java/lang/String.replaceAll:(Ljava/lang/String;Ljava/lang/String;)Ljava/lang/String;
      22: ldc           #10                 // String \\{branch\\}
      24: aload_0
      25: getfield      #4                  // Field localVarApiClient:Lio/lakefs/clients/api/ApiClient;
      28: aload_2
      29: invokevirtual #7                  // Method java/lang/String.toString:()Ljava/lang/String;
      32: invokevirtual #8                  // Method io/lakefs/clients/api/ApiClient.escapeString:(Ljava/lang/String;)Ljava/lang/String;
      35: invokevirtual #9                  // Method java/lang/String.replaceAll:(Ljava/lang/String;Ljava/lang/String;)Ljava/lang/String;
      38: astore        7
      40: new           #11                 // class java/util/ArrayList
      43: dup
      44: invokespecial #12                 // Method java/util/ArrayList."<init>":()V
      47: astore        8
      49: new           #11                 // class java/util/ArrayList
      52: dup
      53: invokespecial #12                 // Method java/util/ArrayList."<init>":()V
      56: astore        9
      58: new           #13                 // class java/util/HashMap
      61: dup
      62: invokespecial #14                 // Method java/util/HashMap."<init>":()V
      65: astore        10
      67: new           #13                 // class java/util/HashMap
      70: dup
      71: invokespecial #14                 // Method java/util/HashMap."<init>":()V
      74: astore        11
      76: new           #13                 // class java/util/HashMap
      79: dup
      80: invokespecial #14                 // Method java/util/HashMap."<init>":()V
      83: astore        12
      85: aload_3
      86: ifnull        107
      89: aload         8
      91: aload_0
      92: getfield      #4                  // Field localVarApiClient:Lio/lakefs/clients/api/ApiClient;
      95: ldc           #15                 // String path
      97: aload_3
      98: invokevirtual #16                 // Method io/lakefs/clients/api/ApiClient.parameterToPair:(Ljava/lang/String;Ljava/lang/Object;)Ljava/util/List;
     101: invokeinterface #17,  2           // InterfaceMethod java/util/List.addAll:(Ljava/util/Collection;)Z
     106: pop
     107: iconst_1
     108: anewarray     #18                 // class java/lang/String
     111: dup
     112: iconst_0
     113: ldc           #19                 // String application/json
     115: aastore
     116: astore        13
     118: aload_0
     119: getfield      #4                  // Field localVarApiClient:Lio/lakefs/clients/api/ApiClient;
     122: aload         13
     124: invokevirtual #20                 // Method io/lakefs/clients/api/ApiClient.selectHeaderAccept:([Ljava/lang/String;)Ljava/lang/String;
     127: astore        14
     129: aload         14
     131: ifnull        146
     134: aload         10
     136: ldc           #21                 // String Accept
     138: aload         14
     140: invokeinterface #22,  3           // InterfaceMethod java/util/Map.put:(Ljava/lang/Object;Ljava/lang/Object;)Ljava/lang/Object;
     145: pop
     146: iconst_1
     147: anewarray     #18                 // class java/lang/String
     150: dup
     151: iconst_0
     152: ldc           #19                 // String application/json
     154: aastore
     155: astore        15
     157: aload_0
     158: getfield      #4                  // Field localVarApiClient:Lio/lakefs/clients/api/ApiClient;
     161: aload         15
     163: invokevirtual #23                 // Method io/lakefs/clients/api/ApiClient.selectHeaderContentType:([Ljava/lang/String;)Ljava/lang/String;
     166: astore        16
     168: aload         10
     170: ldc           #24                 // String Content-Type
     172: aload         16
     174: invokeinterface #22,  3           // InterfaceMethod java/util/Map.put:(Ljava/lang/Object;Ljava/lang/Object;)Ljava/lang/Object;
     179: pop
     180: iconst_4
     181: anewarray     #18                 // class java/lang/String
     184: dup
     185: iconst_0
     186: ldc           #25                 // String basic_auth
     188: aastore
     189: dup
     190: iconst_1
     191: ldc           #26                 // String cookie_auth
     193: aastore
     194: dup
     195: iconst_2
     196: ldc           #27                 // String jwt_token
     198: aastore
     199: dup
     200: iconst_3
     201: ldc           #28                 // String oidc_auth
     203: aastore
     204: astore        17
     206: aload_0
     207: getfield      #4                  // Field localVarApiClient:Lio/lakefs/clients/api/ApiClient;
     210: aload         7
     212: ldc           #49                 // String PUT
     214: aload         8
     216: aload         9
     218: aload         6
     220: aload         10
     222: aload         11
     224: aload         12
     226: aload         17
     228: aload         5
     230: invokevirtual #30                 // Method io/lakefs/clients/api/ApiClient.buildCall:(Ljava/lang/String;Ljava/lang/String;Ljava/util/List;Ljava/util/List;Ljava/lang/Object;Ljava/util/Map;Ljava/util/Map;Ljava/util/Map;[Ljava/lang/String;Lio/lakefs/clients/api/ApiCallback;)Lokhttp3/Call;
     233: areturn

  private okhttp3.Call linkPhysicalAddressValidateBeforeCall(java.lang.String, java.lang.String, java.lang.String, io.lakefs.clients.api.model.StagingMetadata, io.lakefs.clients.api.ApiCallback) throws io.lakefs.clients.api.ApiException;
    Code:
       0: aload_1
       1: ifnonnull     14
       4: new           #31                 // class io/lakefs/clients/api/ApiException
       7: dup
       8: ldc           #50                 // String Missing the required parameter \'repository\' when calling linkPhysicalAddress(Async)
      10: invokespecial #33                 // Method io/lakefs/clients/api/ApiException."<init>":(Ljava/lang/String;)V
      13: athrow
      14: aload_2
      15: ifnonnull     28
      18: new           #31                 // class io/lakefs/clients/api/ApiException
      21: dup
      22: ldc           #51                 // String Missing the required parameter \'branch\' when calling linkPhysicalAddress(Async)
      24: invokespecial #33                 // Method io/lakefs/clients/api/ApiException."<init>":(Ljava/lang/String;)V
      27: athrow
      28: aload_3
      29: ifnonnull     42
      32: new           #31                 // class io/lakefs/clients/api/ApiException
      35: dup
      36: ldc           #52                 // String Missing the required parameter \'path\' when calling linkPhysicalAddress(Async)
      38: invokespecial #33                 // Method io/lakefs/clients/api/ApiException."<init>":(Ljava/lang/String;)V
      41: athrow
      42: aload         4
      44: ifnonnull     57
      47: new           #31                 // class io/lakefs/clients/api/ApiException
      50: dup
      51: ldc           #53                 // String Missing the required parameter \'stagingMetadata\' when calling linkPhysicalAddress(Async)
      53: invokespecial #33                 // Method io/lakefs/clients/api/ApiException."<init>":(Ljava/lang/String;)V
      56: athrow
      57: aload_0
      58: aload_1
      59: aload_2
      60: aload_3
      61: aload         4
      63: aload         5
      65: invokevirtual #54                 // Method linkPhysicalAddressCall:(Ljava/lang/String;Ljava/lang/String;Ljava/lang/String;Lio/lakefs/clients/api/model/StagingMetadata;Lio/lakefs/clients/api/ApiCallback;)Lokhttp3/Call;
      68: astore        6
      70: aload         6
      72: areturn

  public io.lakefs.clients.api.model.ObjectStats linkPhysicalAddress(java.lang.String, java.lang.String, java.lang.String, io.lakefs.clients.api.model.StagingMetadata) throws io.lakefs.clients.api.ApiException;
    Code:
       0: aload_0
       1: aload_1
       2: aload_2
       3: aload_3
       4: aload         4
       6: invokevirtual #55                 // Method linkPhysicalAddressWithHttpInfo:(Ljava/lang/String;Ljava/lang/String;Ljava/lang/String;Lio/lakefs/clients/api/model/StagingMetadata;)Lio/lakefs/clients/api/ApiResponse;
       9: astore        5
      11: aload         5
      13: invokevirtual #38                 // Method io/lakefs/clients/api/ApiResponse.getData:()Ljava/lang/Object;
      16: checkcast     #56                 // class io/lakefs/clients/api/model/ObjectStats
      19: areturn

  public io.lakefs.clients.api.ApiResponse<io.lakefs.clients.api.model.ObjectStats> linkPhysicalAddressWithHttpInfo(java.lang.String, java.lang.String, java.lang.String, io.lakefs.clients.api.model.StagingMetadata) throws io.lakefs.clients.api.ApiException;
    Code:
       0: aload_0
       1: aload_1
       2: aload_2
       3: aload_3
       4: aload         4
       6: aconst_null
       7: invokespecial #57                 // Method linkPhysicalAddressValidateBeforeCall:(Ljava/lang/String;Ljava/lang/String;Ljava/lang/String;Lio/lakefs/clients/api/model/StagingMetadata;Lio/lakefs/clients/api/ApiCallback;)Lokhttp3/Call;
      10: astore        5
      12: new           #58                 // class io/lakefs/clients/api/StagingApi$3
      15: dup
      16: aload_0
      17: invokespecial #59                 // Method io/lakefs/clients/api/StagingApi$3."<init>":(Lio/lakefs/clients/api/StagingApi;)V
      20: invokevirtual #60                 // Method io/lakefs/clients/api/StagingApi$3.getType:()Ljava/lang/reflect/Type;
      23: astore        6
      25: aload_0
      26: getfield      #4                  // Field localVarApiClient:Lio/lakefs/clients/api/ApiClient;
      29: aload         5
      31: aload         6
      33: invokevirtual #44                 // Method io/lakefs/clients/api/ApiClient.execute:(Lokhttp3/Call;Ljava/lang/reflect/Type;)Lio/lakefs/clients/api/ApiResponse;
      36: areturn

  public okhttp3.Call linkPhysicalAddressAsync(java.lang.String, java.lang.String, java.lang.String, io.lakefs.clients.api.model.StagingMetadata, io.lakefs.clients.api.ApiCallback<io.lakefs.clients.api.model.ObjectStats>) throws io.lakefs.clients.api.ApiException;
    Code:
       0: aload_0
       1: aload_1
       2: aload_2
       3: aload_3
       4: aload         4
       6: aload         5
       8: invokespecial #57                 // Method linkPhysicalAddressValidateBeforeCall:(Ljava/lang/String;Ljava/lang/String;Ljava/lang/String;Lio/lakefs/clients/api/model/StagingMetadata;Lio/lakefs/clients/api/ApiCallback;)Lokhttp3/Call;
      11: astore        6
      13: new           #61                 // class io/lakefs/clients/api/StagingApi$4
      16: dup
      17: aload_0
      18: invokespecial #62                 // Method io/lakefs/clients/api/StagingApi$4."<init>":(Lio/lakefs/clients/api/StagingApi;)V
      21: invokevirtual #63                 // Method io/lakefs/clients/api/StagingApi$4.getType:()Ljava/lang/reflect/Type;
      24: astore        7
      26: aload_0
      27: getfield      #4                  // Field localVarApiClient:Lio/lakefs/clients/api/ApiClient;
      30: aload         6
      32: aload         7
      34: aload         5
      36: invokevirtual #48                 // Method io/lakefs/clients/api/ApiClient.executeAsync:(Lokhttp3/Call;Ljava/lang/reflect/Type;Lio/lakefs/clients/api/ApiCallback;)V
      39: aload         6
      41: areturn
}
