Compiled from "PseudoTransactionManager.java"
public class org.springframework.integration.transaction.PseudoTransactionManager extends org.springframework.transaction.support.AbstractPlatformTransactionManager {
  private static final long serialVersionUID;

  public org.springframework.integration.transaction.PseudoTransactionManager();
    Code:
       0: aload_0
       1: invokespecial #1                  // Method org/springframework/transaction/support/AbstractPlatformTransactionManager."<init>":()V
       4: return

  protected java.lang.Object doGetTransaction() throws org.springframework.transaction.TransactionException;
    Code:
       0: new           #2                  // class java/lang/Object
       3: dup
       4: invokespecial #3                  // Method java/lang/Object."<init>":()V
       7: areturn

  protected void doBegin(java.lang.Object, org.springframework.transaction.TransactionDefinition) throws org.springframework.transaction.TransactionException;
    Code:
       0: return

  protected void doCommit(org.springframework.transaction.support.DefaultTransactionStatus) throws org.springframework.transaction.TransactionException;
    Code:
       0: return

  protected void doRollback(org.springframework.transaction.support.DefaultTransactionStatus) throws org.springframework.transaction.TransactionException;
    Code:
       0: return
}
