Compiled from "ZipSerializableViewImpl.java"
public class org.jboss.shrinkwrap.impl.base.serialization.ZipSerializableViewImpl implements org.jboss.shrinkwrap.api.serialization.ZipSerializableView {
  private static final long serialVersionUID;

  private static final java.util.logging.Logger log;

  private final java.lang.String name;

  private transient java.lang.String id;

  private transient org.jboss.shrinkwrap.api.Archive<?> archive;

  public org.jboss.shrinkwrap.impl.base.serialization.ZipSerializableViewImpl(org.jboss.shrinkwrap.api.Archive<?>);
    Code:
       0: aload_0
       1: invokespecial #1                  // Method java/lang/Object."<init>":()V
       4: aload_1
       5: ldc           #2                  // String Archive must be specified
       7: invokestatic  #3                  // Method org/jboss/shrinkwrap/impl/base/Validate.notNull:(Ljava/lang/Object;Ljava/lang/String;)V
      10: aload_1
      11: invokeinterface #4,  1            // InterfaceMethod org/jboss/shrinkwrap/api/Archive.getName:()Ljava/lang/String;
      16: astore_2
      17: aload_2
      18: ldc           #5                  // String Name of archive must be specified
      20: invokestatic  #6                  // Method org/jboss/shrinkwrap/impl/base/Validate.notNullOrEmpty:(Ljava/lang/String;Ljava/lang/String;)V
      23: aload_0
      24: aload_1
      25: putfield      #7                  // Field archive:Lorg/jboss/shrinkwrap/api/Archive;
      28: aload_0
      29: aload_2
      30: putfield      #8                  // Field name:Ljava/lang/String;
      33: aload_0
      34: aload_1
      35: invokeinterface #9,  1            // InterfaceMethod org/jboss/shrinkwrap/api/Archive.getId:()Ljava/lang/String;
      40: putfield      #10                 // Field id:Ljava/lang/String;
      43: return

  public <TYPE extends org.jboss.shrinkwrap.api.Assignable> TYPE as(java.lang.Class<TYPE>);
    Code:
       0: aload_0
       1: getfield      #7                  // Field archive:Lorg/jboss/shrinkwrap/api/Archive;
       4: aload_1
       5: invokeinterface #11,  2           // InterfaceMethod org/jboss/shrinkwrap/api/Archive.as:(Ljava/lang/Class;)Lorg/jboss/shrinkwrap/api/Assignable;
      10: areturn

  private void writeObject(java.io.ObjectOutputStream) throws java.io.IOException;
    Code:
       0: aload_1
       1: invokevirtual #12                 // Method java/io/ObjectOutputStream.defaultWriteObject:()V
       4: aload_0
       5: getfield      #7                  // Field archive:Lorg/jboss/shrinkwrap/api/Archive;
       8: ldc           #13                 // class org/jboss/shrinkwrap/api/exporter/ZipExporter
      10: invokeinterface #11,  2           // InterfaceMethod org/jboss/shrinkwrap/api/Archive.as:(Ljava/lang/Class;)Lorg/jboss/shrinkwrap/api/Assignable;
      15: checkcast     #13                 // class org/jboss/shrinkwrap/api/exporter/ZipExporter
      18: invokeinterface #14,  1           // InterfaceMethod org/jboss/shrinkwrap/api/exporter/ZipExporter.exportAsInputStream:()Ljava/io/InputStream;
      23: astore_2
      24: aload_2
      25: aload_1
      26: invokestatic  #15                 // Method org/jboss/shrinkwrap/impl/base/io/IOUtil.copy:(Ljava/io/InputStream;Ljava/io/OutputStream;)V
      29: aload_1
      30: aload_0
      31: getfield      #10                 // Field id:Ljava/lang/String;
      34: invokevirtual #16                 // Method java/io/ObjectOutputStream.writeObject:(Ljava/lang/Object;)V
      37: aload_2
      38: invokevirtual #17                 // Method java/io/InputStream.close:()V
      41: goto          51
      44: astore_3
      45: aload_2
      46: invokevirtual #17                 // Method java/io/InputStream.close:()V
      49: aload_3
      50: athrow
      51: getstatic     #18                 // Field log:Ljava/util/logging/Logger;
      54: getstatic     #19                 // Field java/util/logging/Level.FINER:Ljava/util/logging/Level;
      57: invokevirtual #20                 // Method java/util/logging/Logger.isLoggable:(Ljava/util/logging/Level;)Z
      60: ifeq          96
      63: getstatic     #18                 // Field log:Ljava/util/logging/Logger;
      66: new           #21                 // class java/lang/StringBuilder
      69: dup
      70: invokespecial #22                 // Method java/lang/StringBuilder."<init>":()V
      73: ldc           #23                 // String Wrote archive:
      75: invokevirtual #24                 // Method java/lang/StringBuilder.append:(Ljava/lang/String;)Ljava/lang/StringBuilder;
      78: aload_0
      79: getfield      #7                  // Field archive:Lorg/jboss/shrinkwrap/api/Archive;
      82: invokeinterface #25,  1           // InterfaceMethod org/jboss/shrinkwrap/api/Archive.toString:()Ljava/lang/String;
      87: invokevirtual #24                 // Method java/lang/StringBuilder.append:(Ljava/lang/String;)Ljava/lang/StringBuilder;
      90: invokevirtual #26                 // Method java/lang/StringBuilder.toString:()Ljava/lang/String;
      93: invokevirtual #27                 // Method java/util/logging/Logger.finer:(Ljava/lang/String;)V
      96: return
    Exception table:
       from    to  target type
          24    37    44   any

  private void readObject(java.io.ObjectInputStream) throws java.io.IOException, java.lang.ClassNotFoundException;
    Code:
       0: aload_1
       1: invokevirtual #28                 // Method java/io/ObjectInputStream.defaultReadObject:()V
       4: aload_0
       5: getfield      #8                  // Field name:Ljava/lang/String;
       8: astore_2
       9: ldc           #29                 // class org/jboss/shrinkwrap/api/importer/ZipImporter
      11: aload_2
      12: invokestatic  #30                 // Method org/jboss/shrinkwrap/api/ShrinkWrap.create:(Ljava/lang/Class;Ljava/lang/String;)Lorg/jboss/shrinkwrap/api/Assignable;
      15: checkcast     #29                 // class org/jboss/shrinkwrap/api/importer/ZipImporter
      18: astore_3
      19: aload_3
      20: aload_1
      21: invokeinterface #31,  2           // InterfaceMethod org/jboss/shrinkwrap/api/importer/ZipImporter.importFrom:(Ljava/io/InputStream;)Lorg/jboss/shrinkwrap/api/importer/StreamImporter;
      26: pop
      27: aload_0
      28: aload_3
      29: ldc           #32                 // class org/jboss/shrinkwrap/api/spec/JavaArchive
      31: invokeinterface #33,  2           // InterfaceMethod org/jboss/shrinkwrap/api/importer/ZipImporter.as:(Ljava/lang/Class;)Lorg/jboss/shrinkwrap/api/Assignable;
      36: checkcast     #34                 // class org/jboss/shrinkwrap/api/Archive
      39: putfield      #7                  // Field archive:Lorg/jboss/shrinkwrap/api/Archive;
      42: getstatic     #18                 // Field log:Ljava/util/logging/Logger;
      45: getstatic     #19                 // Field java/util/logging/Level.FINER:Ljava/util/logging/Level;
      48: invokevirtual #20                 // Method java/util/logging/Logger.isLoggable:(Ljava/util/logging/Level;)Z
      51: ifeq          82
      54: getstatic     #18                 // Field log:Ljava/util/logging/Logger;
      57: new           #21                 // class java/lang/StringBuilder
      60: dup
      61: invokespecial #22                 // Method java/lang/StringBuilder."<init>":()V
      64: ldc           #35                 // String Read in archive:
      66: invokevirtual #24                 // Method java/lang/StringBuilder.append:(Ljava/lang/String;)Ljava/lang/StringBuilder;
      69: aload_3
      70: invokevirtual #36                 // Method java/lang/Object.toString:()Ljava/lang/String;
      73: invokevirtual #24                 // Method java/lang/StringBuilder.append:(Ljava/lang/String;)Ljava/lang/StringBuilder;
      76: invokevirtual #26                 // Method java/lang/StringBuilder.toString:()Ljava/lang/String;
      79: invokevirtual #27                 // Method java/util/logging/Logger.finer:(Ljava/lang/String;)V
      82: aload_1
      83: invokevirtual #37                 // Method java/io/ObjectInputStream.read:()I
      86: iconst_m1
      87: if_icmpeq     93
      90: goto          82
      93: aload_1
      94: invokevirtual #38                 // Method java/io/ObjectInputStream.readObject:()Ljava/lang/Object;
      97: checkcast     #39                 // class java/lang/String
     100: astore        4
     102: aload_0
     103: getfield      #7                  // Field archive:Lorg/jboss/shrinkwrap/api/Archive;
     106: ldc           #40                 // class org/jboss/shrinkwrap/spi/Identifiable
     108: invokeinterface #11,  2           // InterfaceMethod org/jboss/shrinkwrap/api/Archive.as:(Ljava/lang/Class;)Lorg/jboss/shrinkwrap/api/Assignable;
     113: checkcast     #40                 // class org/jboss/shrinkwrap/spi/Identifiable
     116: aload         4
     118: invokeinterface #41,  2           // InterfaceMethod org/jboss/shrinkwrap/spi/Identifiable.setId:(Ljava/lang/String;)V
     123: goto          168
     126: astore        4
     128: getstatic     #18                 // Field log:Ljava/util/logging/Logger;
     131: getstatic     #19                 // Field java/util/logging/Level.FINER:Ljava/util/logging/Level;
     134: invokevirtual #20                 // Method java/util/logging/Logger.isLoggable:(Ljava/util/logging/Level;)Z
     137: ifeq          168
     140: getstatic     #18                 // Field log:Ljava/util/logging/Logger;
     143: new           #21                 // class java/lang/StringBuilder
     146: dup
     147: invokespecial #22                 // Method java/lang/StringBuilder."<init>":()V
     150: ldc           #43                 // String Detected an older version of the archive sent over the wire; no ID was sent.  Ignoring and using the default ID for this archive:
     152: invokevirtual #24                 // Method java/lang/StringBuilder.append:(Ljava/lang/String;)Ljava/lang/StringBuilder;
     155: aload_3
     156: invokevirtual #36                 // Method java/lang/Object.toString:()Ljava/lang/String;
     159: invokevirtual #24                 // Method java/lang/StringBuilder.append:(Ljava/lang/String;)Ljava/lang/StringBuilder;
     162: invokevirtual #26                 // Method java/lang/StringBuilder.toString:()Ljava/lang/String;
     165: invokevirtual #27                 // Method java/util/logging/Logger.finer:(Ljava/lang/String;)V
     168: return
    Exception table:
       from    to  target type
          93   123   126   Class java/io/OptionalDataException

  static {};
    Code:
       0: ldc           #44                 // class org/jboss/shrinkwrap/impl/base/serialization/ZipSerializableViewImpl
       2: invokevirtual #45                 // Method java/lang/Class.getName:()Ljava/lang/String;
       5: invokestatic  #46                 // Method java/util/logging/Logger.getLogger:(Ljava/lang/String;)Ljava/util/logging/Logger;
       8: putstatic     #18                 // Field log:Ljava/util/logging/Logger;
      11: return
}
