Compiled from "Redirect.java"
public class org.apache.jasper.tagplugins.jstl.core.Redirect implements org.apache.jasper.compiler.tagplugin.TagPlugin {
  public org.apache.jasper.tagplugins.jstl.core.Redirect();
    Code:
       0: aload_0
       1: invokespecial #1                  // Method java/lang/Object."<init>":()V
       4: return

  public void doTag(org.apache.jasper.compiler.tagplugin.TagPluginContext);
    Code:
       0: aload_1
       1: ldc           #2                  // String context
       3: invokeinterface #3,  2            // InterfaceMethod org/apache/jasper/compiler/tagplugin/TagPluginContext.isAttributeSpecified:(Ljava/lang/String;)Z
       8: istore_2
       9: aload_1
      10: invokeinterface #4,  1            // InterfaceMethod org/apache/jasper/compiler/tagplugin/TagPluginContext.getTemporaryVariableName:()Ljava/lang/String;
      15: astore_3
      16: aload_1
      17: invokeinterface #4,  1            // InterfaceMethod org/apache/jasper/compiler/tagplugin/TagPluginContext.getTemporaryVariableName:()Ljava/lang/String;
      22: astore        4
      24: aload_1
      25: invokeinterface #4,  1            // InterfaceMethod org/apache/jasper/compiler/tagplugin/TagPluginContext.getTemporaryVariableName:()Ljava/lang/String;
      30: astore        5
      32: aload_1
      33: invokeinterface #4,  1            // InterfaceMethod org/apache/jasper/compiler/tagplugin/TagPluginContext.getTemporaryVariableName:()Ljava/lang/String;
      38: astore        6
      40: aload_1
      41: invokeinterface #4,  1            // InterfaceMethod org/apache/jasper/compiler/tagplugin/TagPluginContext.getTemporaryVariableName:()Ljava/lang/String;
      46: astore        7
      48: aload_1
      49: new           #5                  // class java/lang/StringBuilder
      52: dup
      53: invokespecial #6                  // Method java/lang/StringBuilder."<init>":()V
      56: ldc           #7                  // String String
      58: invokevirtual #8                  // Method java/lang/StringBuilder.append:(Ljava/lang/String;)Ljava/lang/StringBuilder;
      61: aload         4
      63: invokevirtual #8                  // Method java/lang/StringBuilder.append:(Ljava/lang/String;)Ljava/lang/StringBuilder;
      66: ldc           #9                  // String  = null;
      68: invokevirtual #8                  // Method java/lang/StringBuilder.append:(Ljava/lang/String;)Ljava/lang/StringBuilder;
      71: invokevirtual #10                 // Method java/lang/StringBuilder.toString:()Ljava/lang/String;
      74: invokeinterface #11,  2           // InterfaceMethod org/apache/jasper/compiler/tagplugin/TagPluginContext.generateJavaSource:(Ljava/lang/String;)V
      79: iload_2
      80: ifeq          125
      83: aload_1
      84: new           #5                  // class java/lang/StringBuilder
      87: dup
      88: invokespecial #6                  // Method java/lang/StringBuilder."<init>":()V
      91: aload         4
      93: invokevirtual #8                  // Method java/lang/StringBuilder.append:(Ljava/lang/String;)Ljava/lang/StringBuilder;
      96: ldc           #12                 // String  =
      98: invokevirtual #8                  // Method java/lang/StringBuilder.append:(Ljava/lang/String;)Ljava/lang/StringBuilder;
     101: invokevirtual #10                 // Method java/lang/StringBuilder.toString:()Ljava/lang/String;
     104: invokeinterface #11,  2           // InterfaceMethod org/apache/jasper/compiler/tagplugin/TagPluginContext.generateJavaSource:(Ljava/lang/String;)V
     109: aload_1
     110: ldc           #2                  // String context
     112: invokeinterface #13,  2           // InterfaceMethod org/apache/jasper/compiler/tagplugin/TagPluginContext.generateAttribute:(Ljava/lang/String;)V
     117: aload_1
     118: ldc           #14                 // String ;
     120: invokeinterface #11,  2           // InterfaceMethod org/apache/jasper/compiler/tagplugin/TagPluginContext.generateJavaSource:(Ljava/lang/String;)V
     125: aload_1
     126: new           #5                  // class java/lang/StringBuilder
     129: dup
     130: invokespecial #6                  // Method java/lang/StringBuilder."<init>":()V
     133: ldc           #7                  // String String
     135: invokevirtual #8                  // Method java/lang/StringBuilder.append:(Ljava/lang/String;)Ljava/lang/StringBuilder;
     138: aload_3
     139: invokevirtual #8                  // Method java/lang/StringBuilder.append:(Ljava/lang/String;)Ljava/lang/StringBuilder;
     142: ldc           #12                 // String  =
     144: invokevirtual #8                  // Method java/lang/StringBuilder.append:(Ljava/lang/String;)Ljava/lang/StringBuilder;
     147: invokevirtual #10                 // Method java/lang/StringBuilder.toString:()Ljava/lang/String;
     150: invokeinterface #11,  2           // InterfaceMethod org/apache/jasper/compiler/tagplugin/TagPluginContext.generateJavaSource:(Ljava/lang/String;)V
     155: aload_1
     156: ldc           #15                 // String url
     158: invokeinterface #13,  2           // InterfaceMethod org/apache/jasper/compiler/tagplugin/TagPluginContext.generateAttribute:(Ljava/lang/String;)V
     163: aload_1
     164: ldc           #14                 // String ;
     166: invokeinterface #11,  2           // InterfaceMethod org/apache/jasper/compiler/tagplugin/TagPluginContext.generateJavaSource:(Ljava/lang/String;)V
     171: aload_1
     172: new           #5                  // class java/lang/StringBuilder
     175: dup
     176: invokespecial #6                  // Method java/lang/StringBuilder."<init>":()V
     179: ldc           #7                  // String String
     181: invokevirtual #8                  // Method java/lang/StringBuilder.append:(Ljava/lang/String;)Ljava/lang/StringBuilder;
     184: aload         5
     186: invokevirtual #8                  // Method java/lang/StringBuilder.append:(Ljava/lang/String;)Ljava/lang/StringBuilder;
     189: ldc           #12                 // String  =
     191: invokevirtual #8                  // Method java/lang/StringBuilder.append:(Ljava/lang/String;)Ljava/lang/StringBuilder;
     194: ldc           #16                 // String org.apache.jasper.tagplugins.jstl.Util.resolveUrl(
     196: invokevirtual #8                  // Method java/lang/StringBuilder.append:(Ljava/lang/String;)Ljava/lang/StringBuilder;
     199: aload_3
     200: invokevirtual #8                  // Method java/lang/StringBuilder.append:(Ljava/lang/String;)Ljava/lang/StringBuilder;
     203: ldc           #17                 // String ,
     205: invokevirtual #8                  // Method java/lang/StringBuilder.append:(Ljava/lang/String;)Ljava/lang/StringBuilder;
     208: aload         4
     210: invokevirtual #8                  // Method java/lang/StringBuilder.append:(Ljava/lang/String;)Ljava/lang/StringBuilder;
     213: ldc           #18                 // String , pageContext);
     215: invokevirtual #8                  // Method java/lang/StringBuilder.append:(Ljava/lang/String;)Ljava/lang/StringBuilder;
     218: invokevirtual #10                 // Method java/lang/StringBuilder.toString:()Ljava/lang/String;
     221: invokeinterface #11,  2           // InterfaceMethod org/apache/jasper/compiler/tagplugin/TagPluginContext.generateJavaSource:(Ljava/lang/String;)V
     226: aload_1
     227: new           #5                  // class java/lang/StringBuilder
     230: dup
     231: invokespecial #6                  // Method java/lang/StringBuilder."<init>":()V
     234: ldc           #19                 // String pageContext.setAttribute(\"url_without_param\",
     236: invokevirtual #8                  // Method java/lang/StringBuilder.append:(Ljava/lang/String;)Ljava/lang/StringBuilder;
     239: aload         5
     241: invokevirtual #8                  // Method java/lang/StringBuilder.append:(Ljava/lang/String;)Ljava/lang/StringBuilder;
     244: ldc           #20                 // String );
     246: invokevirtual #8                  // Method java/lang/StringBuilder.append:(Ljava/lang/String;)Ljava/lang/StringBuilder;
     249: invokevirtual #10                 // Method java/lang/StringBuilder.toString:()Ljava/lang/String;
     252: invokeinterface #11,  2           // InterfaceMethod org/apache/jasper/compiler/tagplugin/TagPluginContext.generateJavaSource:(Ljava/lang/String;)V
     257: aload_1
     258: invokeinterface #21,  1           // InterfaceMethod org/apache/jasper/compiler/tagplugin/TagPluginContext.generateBody:()V
     263: aload_1
     264: new           #5                  // class java/lang/StringBuilder
     267: dup
     268: invokespecial #6                  // Method java/lang/StringBuilder."<init>":()V
     271: ldc           #7                  // String String
     273: invokevirtual #8                  // Method java/lang/StringBuilder.append:(Ljava/lang/String;)Ljava/lang/StringBuilder;
     276: aload         6
     278: invokevirtual #8                  // Method java/lang/StringBuilder.append:(Ljava/lang/String;)Ljava/lang/StringBuilder;
     281: ldc           #12                 // String  =
     283: invokevirtual #8                  // Method java/lang/StringBuilder.append:(Ljava/lang/String;)Ljava/lang/StringBuilder;
     286: ldc           #22                 // String (String)pageContext.getAttribute(\"url_without_param\");
     288: invokevirtual #8                  // Method java/lang/StringBuilder.append:(Ljava/lang/String;)Ljava/lang/StringBuilder;
     291: invokevirtual #10                 // Method java/lang/StringBuilder.toString:()Ljava/lang/String;
     294: invokeinterface #11,  2           // InterfaceMethod org/apache/jasper/compiler/tagplugin/TagPluginContext.generateJavaSource:(Ljava/lang/String;)V
     299: aload_1
     300: ldc           #23                 // String pageContext.removeAttribute(\"url_without_param\");
     302: invokeinterface #11,  2           // InterfaceMethod org/apache/jasper/compiler/tagplugin/TagPluginContext.generateJavaSource:(Ljava/lang/String;)V
     307: aload_1
     308: new           #5                  // class java/lang/StringBuilder
     311: dup
     312: invokespecial #6                  // Method java/lang/StringBuilder."<init>":()V
     315: ldc           #24                 // String HttpServletResponse
     317: invokevirtual #8                  // Method java/lang/StringBuilder.append:(Ljava/lang/String;)Ljava/lang/StringBuilder;
     320: aload         7
     322: invokevirtual #8                  // Method java/lang/StringBuilder.append:(Ljava/lang/String;)Ljava/lang/StringBuilder;
     325: ldc           #12                 // String  =
     327: invokevirtual #8                  // Method java/lang/StringBuilder.append:(Ljava/lang/String;)Ljava/lang/StringBuilder;
     330: ldc           #25                 // String ((HttpServletResponse) pageContext.getResponse());
     332: invokevirtual #8                  // Method java/lang/StringBuilder.append:(Ljava/lang/String;)Ljava/lang/StringBuilder;
     335: invokevirtual #10                 // Method java/lang/StringBuilder.toString:()Ljava/lang/String;
     338: invokeinterface #11,  2           // InterfaceMethod org/apache/jasper/compiler/tagplugin/TagPluginContext.generateJavaSource:(Ljava/lang/String;)V
     343: aload_1
     344: new           #5                  // class java/lang/StringBuilder
     347: dup
     348: invokespecial #6                  // Method java/lang/StringBuilder."<init>":()V
     351: ldc           #26                 // String if(!org.apache.jasper.tagplugins.jstl.Util.isAbsoluteUrl(
     353: invokevirtual #8                  // Method java/lang/StringBuilder.append:(Ljava/lang/String;)Ljava/lang/StringBuilder;
     356: aload         6
     358: invokevirtual #8                  // Method java/lang/StringBuilder.append:(Ljava/lang/String;)Ljava/lang/StringBuilder;
     361: ldc           #27                 // String )){
     363: invokevirtual #8                  // Method java/lang/StringBuilder.append:(Ljava/lang/String;)Ljava/lang/StringBuilder;
     366: invokevirtual #10                 // Method java/lang/StringBuilder.toString:()Ljava/lang/String;
     369: invokeinterface #11,  2           // InterfaceMethod org/apache/jasper/compiler/tagplugin/TagPluginContext.generateJavaSource:(Ljava/lang/String;)V
     374: aload_1
     375: new           #5                  // class java/lang/StringBuilder
     378: dup
     379: invokespecial #6                  // Method java/lang/StringBuilder."<init>":()V
     382: ldc           #28                 // String
     384: invokevirtual #8                  // Method java/lang/StringBuilder.append:(Ljava/lang/String;)Ljava/lang/StringBuilder;
     387: aload         6
     389: invokevirtual #8                  // Method java/lang/StringBuilder.append:(Ljava/lang/String;)Ljava/lang/StringBuilder;
     392: ldc           #12                 // String  =
     394: invokevirtual #8                  // Method java/lang/StringBuilder.append:(Ljava/lang/String;)Ljava/lang/StringBuilder;
     397: aload         7
     399: invokevirtual #8                  // Method java/lang/StringBuilder.append:(Ljava/lang/String;)Ljava/lang/StringBuilder;
     402: ldc           #29                 // String .encodeRedirectURL(
     404: invokevirtual #8                  // Method java/lang/StringBuilder.append:(Ljava/lang/String;)Ljava/lang/StringBuilder;
     407: aload         6
     409: invokevirtual #8                  // Method java/lang/StringBuilder.append:(Ljava/lang/String;)Ljava/lang/StringBuilder;
     412: ldc           #20                 // String );
     414: invokevirtual #8                  // Method java/lang/StringBuilder.append:(Ljava/lang/String;)Ljava/lang/StringBuilder;
     417: invokevirtual #10                 // Method java/lang/StringBuilder.toString:()Ljava/lang/String;
     420: invokeinterface #11,  2           // InterfaceMethod org/apache/jasper/compiler/tagplugin/TagPluginContext.generateJavaSource:(Ljava/lang/String;)V
     425: aload_1
     426: ldc           #30                 // String }
     428: invokeinterface #11,  2           // InterfaceMethod org/apache/jasper/compiler/tagplugin/TagPluginContext.generateJavaSource:(Ljava/lang/String;)V
     433: aload_1
     434: ldc           #31                 // String try{
     436: invokeinterface #11,  2           // InterfaceMethod org/apache/jasper/compiler/tagplugin/TagPluginContext.generateJavaSource:(Ljava/lang/String;)V
     441: aload_1
     442: new           #5                  // class java/lang/StringBuilder
     445: dup
     446: invokespecial #6                  // Method java/lang/StringBuilder."<init>":()V
     449: ldc           #28                 // String
     451: invokevirtual #8                  // Method java/lang/StringBuilder.append:(Ljava/lang/String;)Ljava/lang/StringBuilder;
     454: aload         7
     456: invokevirtual #8                  // Method java/lang/StringBuilder.append:(Ljava/lang/String;)Ljava/lang/StringBuilder;
     459: ldc           #32                 // String .sendRedirect(
     461: invokevirtual #8                  // Method java/lang/StringBuilder.append:(Ljava/lang/String;)Ljava/lang/StringBuilder;
     464: aload         6
     466: invokevirtual #8                  // Method java/lang/StringBuilder.append:(Ljava/lang/String;)Ljava/lang/StringBuilder;
     469: ldc           #20                 // String );
     471: invokevirtual #8                  // Method java/lang/StringBuilder.append:(Ljava/lang/String;)Ljava/lang/StringBuilder;
     474: invokevirtual #10                 // Method java/lang/StringBuilder.toString:()Ljava/lang/String;
     477: invokeinterface #11,  2           // InterfaceMethod org/apache/jasper/compiler/tagplugin/TagPluginContext.generateJavaSource:(Ljava/lang/String;)V
     482: aload_1
     483: ldc           #33                 // String }catch(java.io.IOException ex){
     485: invokeinterface #11,  2           // InterfaceMethod org/apache/jasper/compiler/tagplugin/TagPluginContext.generateJavaSource:(Ljava/lang/String;)V
     490: aload_1
     491: ldc           #34                 // String     throw new JspTagException(ex.toString(), ex);
     493: invokeinterface #11,  2           // InterfaceMethod org/apache/jasper/compiler/tagplugin/TagPluginContext.generateJavaSource:(Ljava/lang/String;)V
     498: aload_1
     499: ldc           #30                 // String }
     501: invokeinterface #11,  2           // InterfaceMethod org/apache/jasper/compiler/tagplugin/TagPluginContext.generateJavaSource:(Ljava/lang/String;)V
     506: return
}
