Compiled from "SecurityModuleExtension.java"
public abstract class org.webswing.server.services.security.extension.api.SecurityModuleExtension<T extends org.webswing.server.services.security.extension.api.SecurityModuleExtensionConfig> {
  private T config;

  public org.webswing.server.services.security.extension.api.SecurityModuleExtension(T);
    Code:
       0: aload_0
       1: invokespecial #1                  // Method java/lang/Object."<init>":()V
       4: aload_0
       5: aload_1
       6: putfield      #2                  // Field config:Lorg/webswing/server/services/security/extension/api/SecurityModuleExtensionConfig;
       9: return

  public T getConfig();
    Code:
       0: aload_0
       1: getfield      #2                  // Field config:Lorg/webswing/server/services/security/extension/api/SecurityModuleExtensionConfig;
       4: areturn

  public org.webswing.server.services.security.api.AbstractWebswingUser doSufficientPreValidation(org.webswing.server.services.security.modules.AbstractExtendableSecurityModule<?>, javax.servlet.http.HttpServletRequest, javax.servlet.http.HttpServletResponse) throws org.webswing.server.services.security.api.LoginResponseClosedException, org.webswing.server.services.security.api.WebswingAuthenticationException;
    Code:
       0: aconst_null
       1: areturn

  public void doRequiredPreValidation(org.webswing.server.services.security.modules.AbstractExtendableSecurityModule<?>, javax.servlet.http.HttpServletRequest, javax.servlet.http.HttpServletResponse) throws org.webswing.server.services.security.api.LoginResponseClosedException, org.webswing.server.services.security.api.WebswingAuthenticationException;
    Code:
       0: return

  public void doRequiredPostValidation(org.webswing.server.services.security.modules.AbstractExtendableSecurityModule<?>, org.webswing.server.services.security.api.AbstractWebswingUser, javax.servlet.http.HttpServletRequest, javax.servlet.http.HttpServletResponse) throws org.webswing.server.services.security.api.LoginResponseClosedException, org.webswing.server.services.security.api.WebswingAuthenticationException;
    Code:
       0: return

  public org.webswing.server.services.security.api.AbstractWebswingUser decorateUser(org.webswing.server.services.security.api.AbstractWebswingUser, javax.servlet.http.HttpServletRequest, javax.servlet.http.HttpServletResponse);
    Code:
       0: aload_1
       1: areturn

  public boolean serveAuthenticated(org.webswing.server.services.security.api.AbstractWebswingUser, java.lang.String, javax.servlet.http.HttpServletRequest, javax.servlet.http.HttpServletResponse);
    Code:
       0: iconst_0
       1: ireturn

  public void logSuccess(javax.servlet.http.HttpServletRequest, java.lang.String);
    Code:
       0: aload_0
       1: invokevirtual #3                  // Method getConfig:()Lorg/webswing/server/services/security/extension/api/SecurityModuleExtensionConfig;
       4: invokeinterface #4,  1            // InterfaceMethod org/webswing/server/services/security/extension/api/SecurityModuleExtensionConfig.getContext:()Lorg/webswing/server/services/security/api/SecurityContext;
       9: invokeinterface #5,  1            // InterfaceMethod org/webswing/server/services/security/api/SecurityContext.getSecuredPath:()Ljava/lang/String;
      14: astore_3
      15: aload_3
      16: invokestatic  #6                  // Method org/apache/commons/lang/StringUtils.isEmpty:(Ljava/lang/String;)Z
      19: ifeq          27
      22: ldc           #7                  // String /
      24: goto          28
      27: aload_3
      28: astore_3
      29: aload_0
      30: invokevirtual #8                  // Method java/lang/Object.getClass:()Ljava/lang/Class;
      33: invokevirtual #9                  // Method java/lang/Class.getName:()Ljava/lang/String;
      36: astore        4
      38: ldc           #10                 // String SUCCESS
      40: aload_1
      41: aload_3
      42: aload         4
      44: aload_2
      45: ldc           #11                 // String
      47: invokestatic  #12                 // Method org/webswing/server/services/security/modules/AbstractSecurityModule.auditLog:(Ljava/lang/String;Ljavax/servlet/http/HttpServletRequest;Ljava/lang/String;Ljava/lang/String;Ljava/lang/String;Ljava/lang/String;)V
      50: return

  public void logFailure(javax.servlet.http.HttpServletRequest, java.lang.String, java.lang.String);
    Code:
       0: aload_0
       1: invokevirtual #3                  // Method getConfig:()Lorg/webswing/server/services/security/extension/api/SecurityModuleExtensionConfig;
       4: invokeinterface #4,  1            // InterfaceMethod org/webswing/server/services/security/extension/api/SecurityModuleExtensionConfig.getContext:()Lorg/webswing/server/services/security/api/SecurityContext;
       9: invokeinterface #5,  1            // InterfaceMethod org/webswing/server/services/security/api/SecurityContext.getSecuredPath:()Ljava/lang/String;
      14: astore        4
      16: aload         4
      18: invokestatic  #6                  // Method org/apache/commons/lang/StringUtils.isEmpty:(Ljava/lang/String;)Z
      21: ifeq          29
      24: ldc           #7                  // String /
      26: goto          31
      29: aload         4
      31: astore        4
      33: aload_0
      34: invokevirtual #8                  // Method java/lang/Object.getClass:()Ljava/lang/Class;
      37: invokevirtual #9                  // Method java/lang/Class.getName:()Ljava/lang/String;
      40: astore        5
      42: ldc           #13                 // String FAILED
      44: aload_1
      45: aload         4
      47: aload         5
      49: aload_2
      50: aload_3
      51: invokestatic  #12                 // Method org/webswing/server/services/security/modules/AbstractSecurityModule.auditLog:(Ljava/lang/String;Ljavax/servlet/http/HttpServletRequest;Ljava/lang/String;Ljava/lang/String;Ljava/lang/String;Ljava/lang/String;)V
      54: return
}
