Compiled from "DataDrivenStepInterceptor.java"
public class net.thucydides.core.steps.DataDrivenStepInterceptor implements net.sf.cglib.proxy.MethodInterceptor {
  private java.util.List<?> instantiatedSteps;

  public net.thucydides.core.steps.DataDrivenStepInterceptor(java.util.List<?>);
    Code:
       0: aload_0
       1: invokespecial #1                  // Method java/lang/Object."<init>":()V
       4: aload_0
       5: aload_1
       6: putfield      #2                  // Field instantiatedSteps:Ljava/util/List;
       9: return

  public java.lang.Object intercept(java.lang.Object, java.lang.reflect.Method, java.lang.Object[], net.sf.cglib.proxy.MethodProxy) throws java.lang.Throwable;
    Code:
       0: invokestatic  #3                  // Method net/thucydides/core/steps/DataDrivenStep.startDataDrivenStep:()V
       3: aconst_null
       4: astore        5
       6: aload_0
       7: getfield      #2                  // Field instantiatedSteps:Ljava/util/List;
      10: invokeinterface #4,  1            // InterfaceMethod java/util/List.iterator:()Ljava/util/Iterator;
      15: astore        6
      17: aload         6
      19: invokeinterface #5,  1            // InterfaceMethod java/util/Iterator.hasNext:()Z
      24: ifeq          57
      27: aload         6
      29: invokeinterface #6,  1            // InterfaceMethod java/util/Iterator.next:()Ljava/lang/Object;
      34: astore        7
      36: aload_0
      37: aload         7
      39: aload         4
      41: aload_2
      42: aload_3
      43: invokespecial #7                  // Method runMethodAndIgnoreExceptions:(Ljava/lang/Object;Lnet/sf/cglib/proxy/MethodProxy;Ljava/lang/reflect/Method;[Ljava/lang/Object;)Ljava/lang/Object;
      46: astore        5
      48: invokestatic  #8                  // Method net/thucydides/core/steps/StepEventBus.getEventBus:()Lnet/thucydides/core/steps/StepEventBus;
      51: invokevirtual #9                  // Method net/thucydides/core/steps/StepEventBus.clearStepFailures:()V
      54: goto          17
      57: invokestatic  #10                 // Method net/thucydides/core/steps/DataDrivenStep.endDataDrivenStep:()V
      60: aload         5
      62: areturn

  private java.lang.Object runMethodAndIgnoreExceptions(java.lang.Object, net.sf.cglib.proxy.MethodProxy, java.lang.reflect.Method, java.lang.Object[]) throws java.lang.Throwable;
    Code:
       0: aload_0
       1: aload_3
       2: invokespecial #11                 // Method isFinalizer:(Ljava/lang/reflect/Method;)Z
       5: ifeq          10
       8: aload_0
       9: areturn
      10: aload_2
      11: aload_1
      12: aload         4
      14: invokevirtual #12                 // Method net/sf/cglib/proxy/MethodProxy.invoke:(Ljava/lang/Object;[Ljava/lang/Object;)Ljava/lang/Object;
      17: areturn

  private boolean isFinalizer(java.lang.reflect.Method);
    Code:
       0: aload_1
       1: invokevirtual #13                 // Method java/lang/reflect/Method.getName:()Ljava/lang/String;
       4: ldc           #14                 // String finalize
       6: invokevirtual #15                 // Method java/lang/String.equals:(Ljava/lang/Object;)Z
       9: ireturn
}
