Compiled from "StepsAnnotatedField.java"
public class net.thucydides.core.steps.StepsAnnotatedField {
  private java.lang.reflect.Field field;

  private static final java.lang.String NO_ANNOTATED_FIELD_ERROR;

  public java.lang.String getFieldName();
    Code:
       0: aload_0
       1: getfield      #1                  // Field field:Ljava/lang/reflect/Field;
       4: invokevirtual #2                  // Method java/lang/reflect/Field.getName:()Ljava/lang/String;
       7: areturn

  public static java.util.List<net.thucydides.core.steps.StepsAnnotatedField> findMandatoryAnnotatedFields(java.lang.Class<?>);
    Code:
       0: aload_0
       1: invokestatic  #3                  // Method findOptionalAnnotatedFields:(Ljava/lang/Class;)Ljava/util/List;
       4: astore_1
       5: aload_1
       6: invokeinterface #4,  1            // InterfaceMethod java/util/List.isEmpty:()Z
      11: ifeq          24
      14: new           #5                  // class net/thucydides/core/annotations/InvalidStepsFieldException
      17: dup
      18: ldc           #7                  // String No field annotated with @Steps was found in the test case.
      20: invokespecial #8                  // Method net/thucydides/core/annotations/InvalidStepsFieldException."<init>":(Ljava/lang/String;)V
      23: athrow
      24: aload_1
      25: areturn

  public static java.util.List<net.thucydides.core.steps.StepsAnnotatedField> findOptionalAnnotatedFields(java.lang.Class<?>);
    Code:
       0: new           #9                  // class java/util/ArrayList
       3: dup
       4: invokespecial #10                 // Method java/util/ArrayList."<init>":()V
       7: astore_1
       8: aload_0
       9: invokestatic  #11                 // Method net/thucydides/core/annotations/Fields.of:(Ljava/lang/Class;)Lnet/thucydides/core/annotations/Fields;
      12: invokevirtual #12                 // Method net/thucydides/core/annotations/Fields.allFields:()Ljava/util/Set;
      15: invokeinterface #13,  1           // InterfaceMethod java/util/Set.iterator:()Ljava/util/Iterator;
      20: astore_2
      21: aload_2
      22: invokeinterface #14,  1           // InterfaceMethod java/util/Iterator.hasNext:()Z
      27: ifeq          65
      30: aload_2
      31: invokeinterface #15,  1           // InterfaceMethod java/util/Iterator.next:()Ljava/lang/Object;
      36: checkcast     #16                 // class java/lang/reflect/Field
      39: astore_3
      40: aload_3
      41: invokestatic  #17                 // Method fieldIsAnnotated:(Ljava/lang/reflect/Field;)Z
      44: ifeq          62
      47: aload_1
      48: new           #6                  // class net/thucydides/core/steps/StepsAnnotatedField
      51: dup
      52: aload_3
      53: invokespecial #18                 // Method "<init>":(Ljava/lang/reflect/Field;)V
      56: invokeinterface #19,  2           // InterfaceMethod java/util/List.add:(Ljava/lang/Object;)Z
      61: pop
      62: goto          21
      65: aload_1
      66: areturn

  private static boolean fieldIsAnnotated(java.lang.reflect.Field);
    Code:
       0: aload_0
       1: invokestatic  #20                 // Method fieldIsAnnotatedCorrectly:(Ljava/lang/reflect/Field;)Z
       4: ireturn

  private static boolean fieldIsAnnotatedCorrectly(java.lang.reflect.Field);
    Code:
       0: aload_0
       1: ldc           #21                 // class net/thucydides/core/annotations/Steps
       3: invokevirtual #22                 // Method java/lang/reflect/Field.getAnnotation:(Ljava/lang/Class;)Ljava/lang/annotation/Annotation;
       6: ifnonnull     18
       9: aload_0
      10: ldc           #23                 // class net/thucydides/core/annotations/Shared
      12: invokevirtual #22                 // Method java/lang/reflect/Field.getAnnotation:(Ljava/lang/Class;)Ljava/lang/annotation/Annotation;
      15: ifnull        22
      18: iconst_1
      19: goto          23
      22: iconst_0
      23: ireturn

  protected net.thucydides.core.steps.StepsAnnotatedField(java.lang.reflect.Field);
    Code:
       0: aload_0
       1: invokespecial #24                 // Method java/lang/Object."<init>":()V
       4: aload_0
       5: aload_1
       6: putfield      #1                  // Field field:Ljava/lang/reflect/Field;
       9: return

  protected net.thucydides.core.reflection.FieldSetter set(java.lang.Object);
    Code:
       0: new           #25                 // class net/thucydides/core/reflection/FieldSetter
       3: dup
       4: aload_0
       5: getfield      #1                  // Field field:Ljava/lang/reflect/Field;
       8: aload_1
       9: invokespecial #26                 // Method net/thucydides/core/reflection/FieldSetter."<init>":(Ljava/lang/reflect/Field;Ljava/lang/Object;)V
      12: areturn

  public void setValue(java.lang.Object, java.lang.Object);
    Code:
       0: aload_0
       1: aload_1
       2: invokevirtual #27                 // Method set:(Ljava/lang/Object;)Lnet/thucydides/core/reflection/FieldSetter;
       5: aload_2
       6: invokevirtual #28                 // Method net/thucydides/core/reflection/FieldSetter.to:(Ljava/lang/Object;)V
       9: goto          41
      12: astore_3
      13: new           #5                  // class net/thucydides/core/annotations/InvalidStepsFieldException
      16: dup
      17: new           #30                 // class java/lang/StringBuilder
      20: dup
      21: invokespecial #31                 // Method java/lang/StringBuilder."<init>":()V
      24: ldc           #32                 // String Could not access or set field:
      26: invokevirtual #33                 // Method java/lang/StringBuilder.append:(Ljava/lang/String;)Ljava/lang/StringBuilder;
      29: aload_1
      30: invokevirtual #34                 // Method java/lang/StringBuilder.append:(Ljava/lang/Object;)Ljava/lang/StringBuilder;
      33: invokevirtual #35                 // Method java/lang/StringBuilder.toString:()Ljava/lang/String;
      36: aload_3
      37: invokespecial #36                 // Method net/thucydides/core/annotations/InvalidStepsFieldException."<init>":(Ljava/lang/String;Ljava/lang/IllegalAccessException;)V
      40: athrow
      41: return
    Exception table:
       from    to  target type
           0     9    12   Class java/lang/IllegalAccessException

  public boolean isInstantiated(java.lang.Object);
    Code:
       0: aload_0
       1: getfield      #1                  // Field field:Ljava/lang/reflect/Field;
       4: iconst_1
       5: invokevirtual #37                 // Method java/lang/reflect/Field.setAccessible:(Z)V
       8: aload_0
       9: getfield      #1                  // Field field:Ljava/lang/reflect/Field;
      12: aload_1
      13: invokevirtual #38                 // Method java/lang/reflect/Field.get:(Ljava/lang/Object;)Ljava/lang/Object;
      16: astore_2
      17: aload_2
      18: ifnull        25
      21: iconst_1
      22: goto          26
      25: iconst_0
      26: ireturn
      27: astore_2
      28: new           #5                  // class net/thucydides/core/annotations/InvalidStepsFieldException
      31: dup
      32: new           #30                 // class java/lang/StringBuilder
      35: dup
      36: invokespecial #31                 // Method java/lang/StringBuilder."<init>":()V
      39: ldc           #39                 // String Could not access or set @Steps field:
      41: invokevirtual #33                 // Method java/lang/StringBuilder.append:(Ljava/lang/String;)Ljava/lang/StringBuilder;
      44: aload_0
      45: getfield      #1                  // Field field:Ljava/lang/reflect/Field;
      48: invokevirtual #34                 // Method java/lang/StringBuilder.append:(Ljava/lang/Object;)Ljava/lang/StringBuilder;
      51: invokevirtual #35                 // Method java/lang/StringBuilder.toString:()Ljava/lang/String;
      54: aload_2
      55: invokespecial #36                 // Method net/thucydides/core/annotations/InvalidStepsFieldException."<init>":(Ljava/lang/String;Ljava/lang/IllegalAccessException;)V
      58: athrow
    Exception table:
       from    to  target type
           0    26    27   Class java/lang/IllegalAccessException

  public java.lang.Class<?> getFieldClass();
    Code:
       0: aload_0
       1: getfield      #1                  // Field field:Ljava/lang/reflect/Field;
       4: invokevirtual #40                 // Method java/lang/reflect/Field.getType:()Ljava/lang/Class;
       7: areturn

  public boolean isSharedInstance();
    Code:
       0: aload_0
       1: getfield      #1                  // Field field:Ljava/lang/reflect/Field;
       4: ldc           #23                 // class net/thucydides/core/annotations/Shared
       6: invokevirtual #22                 // Method java/lang/reflect/Field.getAnnotation:(Ljava/lang/Class;)Ljava/lang/annotation/Annotation;
       9: ifnonnull     32
      12: aload_0
      13: getfield      #1                  // Field field:Ljava/lang/reflect/Field;
      16: ldc           #21                 // class net/thucydides/core/annotations/Steps
      18: invokevirtual #22                 // Method java/lang/reflect/Field.getAnnotation:(Ljava/lang/Class;)Ljava/lang/annotation/Annotation;
      21: checkcast     #21                 // class net/thucydides/core/annotations/Steps
      24: invokeinterface #41,  1           // InterfaceMethod net/thucydides/core/annotations/Steps.shared:()Z
      29: ifeq          36
      32: iconst_1
      33: goto          37
      36: iconst_0
      37: ireturn

  public boolean isUniqueInstance();
    Code:
       0: aload_0
       1: getfield      #1                  // Field field:Ljava/lang/reflect/Field;
       4: ldc           #21                 // class net/thucydides/core/annotations/Steps
       6: invokevirtual #22                 // Method java/lang/reflect/Field.getAnnotation:(Ljava/lang/Class;)Ljava/lang/annotation/Annotation;
       9: ifnull        36
      12: aload_0
      13: getfield      #1                  // Field field:Ljava/lang/reflect/Field;
      16: ldc           #21                 // class net/thucydides/core/annotations/Steps
      18: invokevirtual #22                 // Method java/lang/reflect/Field.getAnnotation:(Ljava/lang/Class;)Ljava/lang/annotation/Annotation;
      21: checkcast     #21                 // class net/thucydides/core/annotations/Steps
      24: invokeinterface #42,  1           // InterfaceMethod net/thucydides/core/annotations/Steps.uniqueInstance:()Z
      29: ifeq          36
      32: iconst_1
      33: goto          37
      36: iconst_0
      37: ireturn

  public java.util.Optional<java.lang.String> actor();
    Code:
       0: aload_0
       1: invokespecial #43                 // Method getActorAttribute:()Ljava/lang/String;
       4: astore_1
       5: aload_1
       6: invokestatic  #44                 // Method org/apache/commons/lang3/StringUtils.isEmpty:(Ljava/lang/CharSequence;)Z
       9: ifeq          16
      12: invokestatic  #45                 // Method java/util/Optional.empty:()Ljava/util/Optional;
      15: areturn
      16: aload_1
      17: invokestatic  #46                 // Method java/util/Optional.of:(Ljava/lang/Object;)Ljava/util/Optional;
      20: areturn

  private java.lang.String getActorAttribute();
    Code:
       0: aload_0
       1: getfield      #1                  // Field field:Ljava/lang/reflect/Field;
       4: ldc           #21                 // class net/thucydides/core/annotations/Steps
       6: invokevirtual #22                 // Method java/lang/reflect/Field.getAnnotation:(Ljava/lang/Class;)Ljava/lang/annotation/Annotation;
       9: ifnull        30
      12: aload_0
      13: getfield      #1                  // Field field:Ljava/lang/reflect/Field;
      16: ldc           #21                 // class net/thucydides/core/annotations/Steps
      18: invokevirtual #22                 // Method java/lang/reflect/Field.getAnnotation:(Ljava/lang/Class;)Ljava/lang/annotation/Annotation;
      21: checkcast     #21                 // class net/thucydides/core/annotations/Steps
      24: invokeinterface #47,  1           // InterfaceMethod net/thucydides/core/annotations/Steps.actor:()Ljava/lang/String;
      29: areturn
      30: aload_0
      31: getfield      #1                  // Field field:Ljava/lang/reflect/Field;
      34: ldc           #23                 // class net/thucydides/core/annotations/Shared
      36: invokevirtual #22                 // Method java/lang/reflect/Field.getAnnotation:(Ljava/lang/Class;)Ljava/lang/annotation/Annotation;
      39: ifnull        60
      42: aload_0
      43: getfield      #1                  // Field field:Ljava/lang/reflect/Field;
      46: ldc           #23                 // class net/thucydides/core/annotations/Shared
      48: invokevirtual #22                 // Method java/lang/reflect/Field.getAnnotation:(Ljava/lang/Class;)Ljava/lang/annotation/Annotation;
      51: checkcast     #23                 // class net/thucydides/core/annotations/Shared
      54: invokeinterface #48,  1           // InterfaceMethod net/thucydides/core/annotations/Shared.actor:()Ljava/lang/String;
      59: areturn
      60: aconst_null
      61: areturn

  public void assignActorNameIn(java.lang.Object);
    Code:
       0: aload_0
       1: invokevirtual #49                 // Method actor:()Ljava/util/Optional;
       4: aload_0
       5: aload_0
       6: invokevirtual #50                 // Method getFieldName:()Ljava/lang/String;
       9: invokespecial #51                 // Method humanReadable:(Ljava/lang/String;)Ljava/lang/String;
      12: invokevirtual #52                 // Method java/util/Optional.orElse:(Ljava/lang/Object;)Ljava/lang/Object;
      15: checkcast     #53                 // class java/lang/String
      18: astore_2
      19: aload_2
      20: invokestatic  #54                 // Method org/apache/commons/lang3/StringUtils.isNotBlank:(Ljava/lang/CharSequence;)Z
      23: ifeq          42
      26: aload_0
      27: aload_1
      28: invokespecial #55                 // Method actorFieldIn:(Ljava/lang/Object;)Ljava/util/Optional;
      31: aload_0
      32: aload_1
      33: aload_2
      34: invokedynamic #56,  0             // InvokeDynamic #0:accept:(Lnet/thucydides/core/steps/StepsAnnotatedField;Ljava/lang/Object;Ljava/lang/String;)Ljava/util/function/Consumer;
      39: invokevirtual #57                 // Method java/util/Optional.ifPresent:(Ljava/util/function/Consumer;)V
      42: return

  private java.lang.String humanReadable(java.lang.String);
    Code:
       0: new           #58                 // class net/thucydides/core/util/Inflector
       3: dup
       4: invokespecial #59                 // Method net/thucydides/core/util/Inflector."<init>":()V
       7: aload_1
       8: invokevirtual #60                 // Method net/thucydides/core/util/Inflector.of:(Ljava/lang/String;)Lnet/thucydides/core/util/Inflection;
      11: invokevirtual #61                 // Method net/thucydides/core/util/Inflection.asATitle:()Lnet/thucydides/core/util/Inflection;
      14: invokevirtual #62                 // Method net/thucydides/core/util/Inflection.toString:()Ljava/lang/String;
      17: areturn

  private void assignValueToField(java.lang.reflect.Field, java.lang.Object, java.lang.String);
    Code:
       0: aload_1
       1: iconst_1
       2: invokevirtual #37                 // Method java/lang/reflect/Field.setAccessible:(Z)V
       5: aload_1
       6: aload_2
       7: aload_3
       8: invokevirtual #63                 // Method java/lang/reflect/Field.set:(Ljava/lang/Object;Ljava/lang/Object;)V
      11: goto          45
      14: astore        4
      16: new           #5                  // class net/thucydides/core/annotations/InvalidStepsFieldException
      19: dup
      20: new           #30                 // class java/lang/StringBuilder
      23: dup
      24: invokespecial #31                 // Method java/lang/StringBuilder."<init>":()V
      27: ldc           #64                 // String Could not access or set name field:
      29: invokevirtual #33                 // Method java/lang/StringBuilder.append:(Ljava/lang/String;)Ljava/lang/StringBuilder;
      32: aload_1
      33: invokevirtual #34                 // Method java/lang/StringBuilder.append:(Ljava/lang/Object;)Ljava/lang/StringBuilder;
      36: invokevirtual #35                 // Method java/lang/StringBuilder.toString:()Ljava/lang/String;
      39: aload         4
      41: invokespecial #36                 // Method net/thucydides/core/annotations/InvalidStepsFieldException."<init>":(Ljava/lang/String;Ljava/lang/IllegalAccessException;)V
      44: athrow
      45: return
    Exception table:
       from    to  target type
           5    11    14   Class java/lang/IllegalAccessException

  private java.util.Optional<java.lang.reflect.Field> actorFieldIn(java.lang.Object);
    Code:
       0: aload_1
       1: invokevirtual #65                 // Method java/lang/Object.getClass:()Ljava/lang/Class;
       4: invokestatic  #11                 // Method net/thucydides/core/annotations/Fields.of:(Ljava/lang/Class;)Lnet/thucydides/core/annotations/Fields;
       7: invokevirtual #12                 // Method net/thucydides/core/annotations/Fields.allFields:()Ljava/util/Set;
      10: invokeinterface #66,  1           // InterfaceMethod java/util/Set.stream:()Ljava/util/stream/Stream;
      15: invokedynamic #67,  0             // InvokeDynamic #1:test:()Ljava/util/function/Predicate;
      20: invokeinterface #68,  2           // InterfaceMethod java/util/stream/Stream.filter:(Ljava/util/function/Predicate;)Ljava/util/stream/Stream;
      25: invokeinterface #69,  1           // InterfaceMethod java/util/stream/Stream.findFirst:()Ljava/util/Optional;
      30: areturn

  private static boolean lambda$actorFieldIn$1(java.lang.reflect.Field);
    Code:
       0: aload_0
       1: invokevirtual #2                  // Method java/lang/reflect/Field.getName:()Ljava/lang/String;
       4: ldc           #70                 // String actor
       6: invokevirtual #71                 // Method java/lang/String.equals:(Ljava/lang/Object;)Z
       9: ifeq          28
      12: aload_0
      13: invokevirtual #40                 // Method java/lang/reflect/Field.getType:()Ljava/lang/Class;
      16: ldc           #53                 // class java/lang/String
      18: invokevirtual #72                 // Method java/lang/Object.equals:(Ljava/lang/Object;)Z
      21: ifeq          28
      24: iconst_1
      25: goto          29
      28: iconst_0
      29: ireturn

  private void lambda$assignActorNameIn$0(java.lang.Object, java.lang.String, java.lang.reflect.Field);
    Code:
       0: aload_0
       1: aload_3
       2: aload_1
       3: aload_2
       4: invokespecial #73                 // Method assignValueToField:(Ljava/lang/reflect/Field;Ljava/lang/Object;Ljava/lang/String;)V
       7: return
}
