Compiled from "ByteSink.java"
final class com.google.common.io.ByteSink$AsCharSink extends com.google.common.io.CharSink {
  private final java.nio.charset.Charset charset;

  final com.google.common.io.ByteSink this$0;

  private com.google.common.io.ByteSink$AsCharSink(com.google.common.io.ByteSink, java.nio.charset.Charset);
    Code:
       0: aload_0
       1: aload_1
       2: putfield      #2                  // Field this$0:Lcom/google/common/io/ByteSink;
       5: aload_0
       6: invokespecial #3                  // Method com/google/common/io/CharSink."<init>":()V
       9: aload_0
      10: aload_2
      11: invokestatic  #4                  // Method com/google/common/base/Preconditions.checkNotNull:(Ljava/lang/Object;)Ljava/lang/Object;
      14: checkcast     #5                  // class java/nio/charset/Charset
      17: putfield      #6                  // Field charset:Ljava/nio/charset/Charset;
      20: return

  public java.io.Writer openStream() throws java.io.IOException;
    Code:
       0: new           #7                  // class java/io/OutputStreamWriter
       3: dup
       4: aload_0
       5: getfield      #2                  // Field this$0:Lcom/google/common/io/ByteSink;
       8: invokevirtual #8                  // Method com/google/common/io/ByteSink.openStream:()Ljava/io/OutputStream;
      11: aload_0
      12: getfield      #6                  // Field charset:Ljava/nio/charset/Charset;
      15: invokespecial #9                  // Method java/io/OutputStreamWriter."<init>":(Ljava/io/OutputStream;Ljava/nio/charset/Charset;)V
      18: areturn

  public java.lang.String toString();
    Code:
       0: aload_0
       1: getfield      #2                  // Field this$0:Lcom/google/common/io/ByteSink;
       4: invokevirtual #10                 // Method java/lang/Object.toString:()Ljava/lang/String;
       7: invokestatic  #11                 // Method java/lang/String.valueOf:(Ljava/lang/Object;)Ljava/lang/String;
      10: invokestatic  #11                 // Method java/lang/String.valueOf:(Ljava/lang/Object;)Ljava/lang/String;
      13: astore_1
      14: aload_0
      15: getfield      #6                  // Field charset:Ljava/nio/charset/Charset;
      18: invokestatic  #11                 // Method java/lang/String.valueOf:(Ljava/lang/Object;)Ljava/lang/String;
      21: invokestatic  #11                 // Method java/lang/String.valueOf:(Ljava/lang/Object;)Ljava/lang/String;
      24: astore_2
      25: new           #12                 // class java/lang/StringBuilder
      28: dup
      29: bipush        13
      31: aload_1
      32: invokevirtual #13                 // Method java/lang/String.length:()I
      35: iadd
      36: aload_2
      37: invokevirtual #13                 // Method java/lang/String.length:()I
      40: iadd
      41: invokespecial #14                 // Method java/lang/StringBuilder."<init>":(I)V
      44: aload_1
      45: invokevirtual #15                 // Method java/lang/StringBuilder.append:(Ljava/lang/String;)Ljava/lang/StringBuilder;
      48: ldc           #16                 // String .asCharSink(
      50: invokevirtual #15                 // Method java/lang/StringBuilder.append:(Ljava/lang/String;)Ljava/lang/StringBuilder;
      53: aload_2
      54: invokevirtual #15                 // Method java/lang/StringBuilder.append:(Ljava/lang/String;)Ljava/lang/StringBuilder;
      57: ldc           #17                 // String )
      59: invokevirtual #15                 // Method java/lang/StringBuilder.append:(Ljava/lang/String;)Ljava/lang/StringBuilder;
      62: invokevirtual #18                 // Method java/lang/StringBuilder.toString:()Ljava/lang/String;
      65: areturn

  com.google.common.io.ByteSink$AsCharSink(com.google.common.io.ByteSink, java.nio.charset.Charset, com.google.common.io.ByteSink$1);
    Code:
       0: aload_0
       1: aload_1
       2: aload_2
       3: invokespecial #1                  // Method "<init>":(Lcom/google/common/io/ByteSink;Ljava/nio/charset/Charset;)V
       6: return
}
