Compiled from "FileBackedOutputStream.java"
class com.google.common.io.FileBackedOutputStream$MemoryOutput extends java.io.ByteArrayOutputStream {
  private com.google.common.io.FileBackedOutputStream$MemoryOutput();
    Code:
       0: aload_0
       1: invokespecial #2                  // Method java/io/ByteArrayOutputStream."<init>":()V
       4: return

  byte[] getBuffer();
    Code:
       0: aload_0
       1: getfield      #3                  // Field buf:[B
       4: areturn

  int getCount();
    Code:
       0: aload_0
       1: getfield      #4                  // Field count:I
       4: ireturn

  com.google.common.io.FileBackedOutputStream$MemoryOutput(com.google.common.io.FileBackedOutputStream$1);
    Code:
       0: aload_0
       1: invokespecial #1                  // Method "<init>":()V
       4: return
}
