Compiled from "DelegatedProtocol.java"
class org.elasticsearch.hadoop.rest.commonshttp.DelegatedProtocol extends org.elasticsearch.hadoop.thirdparty.apache.commons.httpclient.protocol.Protocol {
  private final org.elasticsearch.hadoop.thirdparty.apache.commons.httpclient.protocol.Protocol original;

  org.elasticsearch.hadoop.rest.commonshttp.DelegatedProtocol(org.elasticsearch.hadoop.thirdparty.apache.commons.httpclient.protocol.ProtocolSocketFactory, org.elasticsearch.hadoop.thirdparty.apache.commons.httpclient.protocol.Protocol, java.lang.String, int);
    Code:
       0: aload_0
       1: aload_3
       2: aload_1
       3: iload         4
       5: invokespecial #1                  // Method org/elasticsearch/hadoop/thirdparty/apache/commons/httpclient/protocol/Protocol."<init>":(Ljava/lang/String;Lorg/elasticsearch/hadoop/thirdparty/apache/commons/httpclient/protocol/ProtocolSocketFactory;I)V
       8: aload_0
       9: aload_2
      10: putfield      #7                  // Field original:Lorg/elasticsearch/hadoop/thirdparty/apache/commons/httpclient/protocol/Protocol;
      13: return

  public boolean equals(java.lang.Object);
    Code:
       0: aload_1
       1: instanceof    #8                  // class org/elasticsearch/hadoop/rest/commonshttp/DelegatedProtocol
       4: ifeq          11
       7: iconst_1
       8: goto          19
      11: aload_0
      12: getfield      #7                  // Field original:Lorg/elasticsearch/hadoop/thirdparty/apache/commons/httpclient/protocol/Protocol;
      15: aload_1
      16: invokevirtual #13                 // Method org/elasticsearch/hadoop/thirdparty/apache/commons/httpclient/protocol/Protocol.equals:(Ljava/lang/Object;)Z
      19: ireturn

  public int hashCode();
    Code:
       0: aload_0
       1: getfield      #7                  // Field original:Lorg/elasticsearch/hadoop/thirdparty/apache/commons/httpclient/protocol/Protocol;
       4: invokevirtual #17                 // Method org/elasticsearch/hadoop/thirdparty/apache/commons/httpclient/protocol/Protocol.hashCode:()I
       7: ireturn

  org.elasticsearch.hadoop.thirdparty.apache.commons.httpclient.protocol.Protocol getOriginal();
    Code:
       0: aload_0
       1: getfield      #7                  // Field original:Lorg/elasticsearch/hadoop/thirdparty/apache/commons/httpclient/protocol/Protocol;
       4: areturn
}
