Compiled from "SocksSocketFactory.java"
class org.elasticsearch.hadoop.rest.commonshttp.SocksSocketFactory extends org.elasticsearch.hadoop.thirdparty.apache.commons.httpclient.protocol.DefaultProtocolSocketFactory {
  private final java.lang.String socksHost;

  private final int socksPort;

  org.elasticsearch.hadoop.rest.commonshttp.SocksSocketFactory(java.lang.String, int);
    Code:
       0: aload_0
       1: aload_1
       2: iload_2
       3: aconst_null
       4: aconst_null
       5: invokespecial #1                  // Method "<init>":(Ljava/lang/String;ILjava/lang/String;Ljava/lang/String;)V
       8: return

  org.elasticsearch.hadoop.rest.commonshttp.SocksSocketFactory(java.lang.String, int, java.lang.String, java.lang.String);
    Code:
       0: aload_0
       1: invokespecial #7                  // Method org/elasticsearch/hadoop/thirdparty/apache/commons/httpclient/protocol/DefaultProtocolSocketFactory."<init>":()V
       4: aload_0
       5: aload_1
       6: putfield      #12                 // Field socksHost:Ljava/lang/String;
       9: aload_0
      10: iload_2
      11: putfield      #16                 // Field socksPort:I
      14: aload_3
      15: invokestatic  #20                 // Method org/elasticsearch/hadoop/util/StringUtils.hasText:(Ljava/lang/CharSequence;)Z
      18: ifeq          49
      21: new           #26                 // class java/net/PasswordAuthentication
      24: dup
      25: aload_3
      26: aload         4
      28: invokevirtual #28                 // Method java/lang/String.toCharArray:()[C
      31: invokespecial #34                 // Method java/net/PasswordAuthentication."<init>":(Ljava/lang/String;[C)V
      34: astore        5
      36: new           #37                 // class org/elasticsearch/hadoop/rest/commonshttp/SocksSocketFactory$1
      39: dup
      40: aload_0
      41: aload         5
      43: invokespecial #39                 // Method org/elasticsearch/hadoop/rest/commonshttp/SocksSocketFactory$1."<init>":(Lorg/elasticsearch/hadoop/rest/commonshttp/SocksSocketFactory;Ljava/net/PasswordAuthentication;)V
      46: invokestatic  #42                 // Method java/net/Authenticator.setDefault:(Ljava/net/Authenticator;)V
      49: return

  public java.net.Socket createSocket(java.lang.String, int, java.net.InetAddress, int, org.elasticsearch.hadoop.thirdparty.apache.commons.httpclient.params.HttpConnectionParams) throws java.io.IOException, java.net.UnknownHostException, org.elasticsearch.hadoop.thirdparty.apache.commons.httpclient.ConnectTimeoutException;
    Code:
       0: new           #48                 // class java/net/InetSocketAddress
       3: dup
       4: aload_0
       5: getfield      #12                 // Field socksHost:Ljava/lang/String;
       8: aload_0
       9: getfield      #16                 // Field socksPort:I
      12: invokespecial #50                 // Method java/net/InetSocketAddress."<init>":(Ljava/lang/String;I)V
      15: astore        6
      17: new           #53                 // class java/net/Proxy
      20: dup
      21: getstatic     #55                 // Field java/net/Proxy$Type.SOCKS:Ljava/net/Proxy$Type;
      24: aload         6
      26: invokespecial #61                 // Method java/net/Proxy."<init>":(Ljava/net/Proxy$Type;Ljava/net/SocketAddress;)V
      29: astore        7
      31: aload         5
      33: invokevirtual #64                 // Method org/elasticsearch/hadoop/thirdparty/apache/commons/httpclient/params/HttpConnectionParams.getConnectionTimeout:()I
      36: istore        8
      38: new           #70                 // class java/net/Socket
      41: dup
      42: aload         7
      44: invokespecial #72                 // Method java/net/Socket."<init>":(Ljava/net/Proxy;)V
      47: astore        9
      49: aload         9
      51: iload         8
      53: invokevirtual #75                 // Method java/net/Socket.setSoTimeout:(I)V
      56: new           #48                 // class java/net/InetSocketAddress
      59: dup
      60: aload_3
      61: iload         4
      63: invokespecial #79                 // Method java/net/InetSocketAddress."<init>":(Ljava/net/InetAddress;I)V
      66: astore        10
      68: new           #48                 // class java/net/InetSocketAddress
      71: dup
      72: aload_1
      73: iload_2
      74: invokespecial #50                 // Method java/net/InetSocketAddress."<init>":(Ljava/lang/String;I)V
      77: astore        11
      79: aload         9
      81: aload         10
      83: invokevirtual #82                 // Method java/net/Socket.bind:(Ljava/net/SocketAddress;)V
      86: aload         9
      88: aload         11
      90: iload         8
      92: invokevirtual #86                 // Method java/net/Socket.connect:(Ljava/net/SocketAddress;I)V
      95: aload         9
      97: areturn

  public int hashCode();
    Code:
       0: ldc           #2                  // class org/elasticsearch/hadoop/rest/commonshttp/SocksSocketFactory
       2: invokevirtual #90                 // Method java/lang/Object.hashCode:()I
       5: ireturn
}
