Compiled from "JdoTransactionManager.java"
public class org.springframework.orm.jdo.JdoTransactionManager extends org.springframework.transaction.support.AbstractPlatformTransactionManager implements org.springframework.transaction.support.ResourceTransactionManager,org.springframework.beans.factory.InitializingBean {
  private javax.jdo.PersistenceManagerFactory persistenceManagerFactory;

  private javax.sql.DataSource dataSource;

  private boolean autodetectDataSource;

  private org.springframework.orm.jdo.JdoDialect jdoDialect;

  public org.springframework.orm.jdo.JdoTransactionManager();
    Code:
       0: aload_0
       1: invokespecial #1                  // Method org/springframework/transaction/support/AbstractPlatformTransactionManager."<init>":()V
       4: aload_0
       5: iconst_1
       6: putfield      #2                  // Field autodetectDataSource:Z
       9: return

  public org.springframework.orm.jdo.JdoTransactionManager(javax.jdo.PersistenceManagerFactory);
    Code:
       0: aload_0
       1: invokespecial #1                  // Method org/springframework/transaction/support/AbstractPlatformTransactionManager."<init>":()V
       4: aload_0
       5: iconst_1
       6: putfield      #2                  // Field autodetectDataSource:Z
       9: aload_0
      10: aload_1
      11: putfield      #3                  // Field persistenceManagerFactory:Ljavax/jdo/PersistenceManagerFactory;
      14: aload_0
      15: invokevirtual #4                  // Method afterPropertiesSet:()V
      18: return

  public void setPersistenceManagerFactory(javax.jdo.PersistenceManagerFactory);
    Code:
       0: aload_0
       1: aload_1
       2: putfield      #3                  // Field persistenceManagerFactory:Ljavax/jdo/PersistenceManagerFactory;
       5: return

  public javax.jdo.PersistenceManagerFactory getPersistenceManagerFactory();
    Code:
       0: aload_0
       1: getfield      #3                  // Field persistenceManagerFactory:Ljavax/jdo/PersistenceManagerFactory;
       4: areturn

  public void setDataSource(javax.sql.DataSource);
    Code:
       0: aload_1
       1: instanceof    #5                  // class org/springframework/jdbc/datasource/TransactionAwareDataSourceProxy
       4: ifeq          21
       7: aload_0
       8: aload_1
       9: checkcast     #5                  // class org/springframework/jdbc/datasource/TransactionAwareDataSourceProxy
      12: invokevirtual #6                  // Method org/springframework/jdbc/datasource/TransactionAwareDataSourceProxy.getTargetDataSource:()Ljavax/sql/DataSource;
      15: putfield      #7                  // Field dataSource:Ljavax/sql/DataSource;
      18: goto          26
      21: aload_0
      22: aload_1
      23: putfield      #7                  // Field dataSource:Ljavax/sql/DataSource;
      26: return

  public javax.sql.DataSource getDataSource();
    Code:
       0: aload_0
       1: getfield      #7                  // Field dataSource:Ljavax/sql/DataSource;
       4: areturn

  public void setAutodetectDataSource(boolean);
    Code:
       0: aload_0
       1: iload_1
       2: putfield      #2                  // Field autodetectDataSource:Z
       5: return

  public void setJdoDialect(org.springframework.orm.jdo.JdoDialect);
    Code:
       0: aload_0
       1: aload_1
       2: putfield      #8                  // Field jdoDialect:Lorg/springframework/orm/jdo/JdoDialect;
       5: return

  public org.springframework.orm.jdo.JdoDialect getJdoDialect();
    Code:
       0: aload_0
       1: getfield      #8                  // Field jdoDialect:Lorg/springframework/orm/jdo/JdoDialect;
       4: ifnonnull     18
       7: aload_0
       8: new           #9                  // class org/springframework/orm/jdo/DefaultJdoDialect
      11: dup
      12: invokespecial #10                 // Method org/springframework/orm/jdo/DefaultJdoDialect."<init>":()V
      15: putfield      #8                  // Field jdoDialect:Lorg/springframework/orm/jdo/JdoDialect;
      18: aload_0
      19: getfield      #8                  // Field jdoDialect:Lorg/springframework/orm/jdo/JdoDialect;
      22: areturn

  public void afterPropertiesSet();
    Code:
       0: aload_0
       1: invokevirtual #11                 // Method getPersistenceManagerFactory:()Ljavax/jdo/PersistenceManagerFactory;
       4: ifnonnull     17
       7: new           #12                 // class java/lang/IllegalArgumentException
      10: dup
      11: ldc           #13                 // String Property \'persistenceManagerFactory\' is required
      13: invokespecial #14                 // Method java/lang/IllegalArgumentException."<init>":(Ljava/lang/String;)V
      16: athrow
      17: aload_0
      18: getfield      #8                  // Field jdoDialect:Lorg/springframework/orm/jdo/JdoDialect;
      21: ifnonnull     44
      24: aload_0
      25: new           #9                  // class org/springframework/orm/jdo/DefaultJdoDialect
      28: dup
      29: aload_0
      30: invokevirtual #11                 // Method getPersistenceManagerFactory:()Ljavax/jdo/PersistenceManagerFactory;
      33: invokeinterface #15,  1           // InterfaceMethod javax/jdo/PersistenceManagerFactory.getConnectionFactory:()Ljava/lang/Object;
      38: invokespecial #16                 // Method org/springframework/orm/jdo/DefaultJdoDialect."<init>":(Ljava/lang/Object;)V
      41: putfield      #8                  // Field jdoDialect:Lorg/springframework/orm/jdo/JdoDialect;
      44: aload_0
      45: getfield      #2                  // Field autodetectDataSource:Z
      48: ifeq          131
      51: aload_0
      52: invokevirtual #17                 // Method getDataSource:()Ljavax/sql/DataSource;
      55: ifnonnull     131
      58: aload_0
      59: invokevirtual #11                 // Method getPersistenceManagerFactory:()Ljavax/jdo/PersistenceManagerFactory;
      62: invokeinterface #15,  1           // InterfaceMethod javax/jdo/PersistenceManagerFactory.getConnectionFactory:()Ljava/lang/Object;
      67: astore_1
      68: aload_1
      69: instanceof    #18                 // class javax/sql/DataSource
      72: ifeq          131
      75: aload_0
      76: aload_1
      77: checkcast     #18                 // class javax/sql/DataSource
      80: putfield      #7                  // Field dataSource:Ljavax/sql/DataSource;
      83: aload_0
      84: getfield      #19                 // Field logger:Lorg/apache/commons/logging/Log;
      87: invokeinterface #20,  1           // InterfaceMethod org/apache/commons/logging/Log.isInfoEnabled:()Z
      92: ifeq          131
      95: aload_0
      96: getfield      #19                 // Field logger:Lorg/apache/commons/logging/Log;
      99: new           #21                 // class java/lang/StringBuilder
     102: dup
     103: invokespecial #22                 // Method java/lang/StringBuilder."<init>":()V
     106: ldc           #23                 // String Using DataSource [
     108: invokevirtual #24                 // Method java/lang/StringBuilder.append:(Ljava/lang/String;)Ljava/lang/StringBuilder;
     111: aload_0
     112: getfield      #7                  // Field dataSource:Ljavax/sql/DataSource;
     115: invokevirtual #25                 // Method java/lang/StringBuilder.append:(Ljava/lang/Object;)Ljava/lang/StringBuilder;
     118: ldc           #26                 // String ] of JDO PersistenceManagerFactory for JdoTransactionManager
     120: invokevirtual #24                 // Method java/lang/StringBuilder.append:(Ljava/lang/String;)Ljava/lang/StringBuilder;
     123: invokevirtual #27                 // Method java/lang/StringBuilder.toString:()Ljava/lang/String;
     126: invokeinterface #28,  2           // InterfaceMethod org/apache/commons/logging/Log.info:(Ljava/lang/Object;)V
     131: return

  public java.lang.Object getResourceFactory();
    Code:
       0: aload_0
       1: invokevirtual #11                 // Method getPersistenceManagerFactory:()Ljavax/jdo/PersistenceManagerFactory;
       4: areturn

  protected java.lang.Object doGetTransaction();
    Code:
       0: new           #29                 // class org/springframework/orm/jdo/JdoTransactionManager$JdoTransactionObject
       3: dup
       4: aload_0
       5: aconst_null
       6: invokespecial #30                 // Method org/springframework/orm/jdo/JdoTransactionManager$JdoTransactionObject."<init>":(Lorg/springframework/orm/jdo/JdoTransactionManager;Lorg/springframework/orm/jdo/JdoTransactionManager$1;)V
       9: astore_1
      10: aload_1
      11: aload_0
      12: invokevirtual #31                 // Method isNestedTransactionAllowed:()Z
      15: invokevirtual #32                 // Method org/springframework/orm/jdo/JdoTransactionManager$JdoTransactionObject.setSavepointAllowed:(Z)V
      18: aload_0
      19: invokevirtual #11                 // Method getPersistenceManagerFactory:()Ljavax/jdo/PersistenceManagerFactory;
      22: invokestatic  #33                 // Method org/springframework/transaction/support/TransactionSynchronizationManager.getResource:(Ljava/lang/Object;)Ljava/lang/Object;
      25: checkcast     #34                 // class org/springframework/orm/jdo/PersistenceManagerHolder
      28: astore_2
      29: aload_2
      30: ifnull        87
      33: aload_0
      34: getfield      #19                 // Field logger:Lorg/apache/commons/logging/Log;
      37: invokeinterface #35,  1           // InterfaceMethod org/apache/commons/logging/Log.isDebugEnabled:()Z
      42: ifeq          81
      45: aload_0
      46: getfield      #19                 // Field logger:Lorg/apache/commons/logging/Log;
      49: new           #21                 // class java/lang/StringBuilder
      52: dup
      53: invokespecial #22                 // Method java/lang/StringBuilder."<init>":()V
      56: ldc           #36                 // String Found thread-bound PersistenceManager [
      58: invokevirtual #24                 // Method java/lang/StringBuilder.append:(Ljava/lang/String;)Ljava/lang/StringBuilder;
      61: aload_2
      62: invokevirtual #37                 // Method org/springframework/orm/jdo/PersistenceManagerHolder.getPersistenceManager:()Ljavax/jdo/PersistenceManager;
      65: invokevirtual #25                 // Method java/lang/StringBuilder.append:(Ljava/lang/Object;)Ljava/lang/StringBuilder;
      68: ldc           #38                 // String ] for JDO transaction
      70: invokevirtual #24                 // Method java/lang/StringBuilder.append:(Ljava/lang/String;)Ljava/lang/StringBuilder;
      73: invokevirtual #27                 // Method java/lang/StringBuilder.toString:()Ljava/lang/String;
      76: invokeinterface #39,  2           // InterfaceMethod org/apache/commons/logging/Log.debug:(Ljava/lang/Object;)V
      81: aload_1
      82: aload_2
      83: iconst_0
      84: invokevirtual #40                 // Method org/springframework/orm/jdo/JdoTransactionManager$JdoTransactionObject.setPersistenceManagerHolder:(Lorg/springframework/orm/jdo/PersistenceManagerHolder;Z)V
      87: aload_0
      88: invokevirtual #17                 // Method getDataSource:()Ljavax/sql/DataSource;
      91: ifnull        110
      94: aload_0
      95: invokevirtual #17                 // Method getDataSource:()Ljavax/sql/DataSource;
      98: invokestatic  #33                 // Method org/springframework/transaction/support/TransactionSynchronizationManager.getResource:(Ljava/lang/Object;)Ljava/lang/Object;
     101: checkcast     #41                 // class org/springframework/jdbc/datasource/ConnectionHolder
     104: astore_3
     105: aload_1
     106: aload_3
     107: invokevirtual #42                 // Method org/springframework/orm/jdo/JdoTransactionManager$JdoTransactionObject.setConnectionHolder:(Lorg/springframework/jdbc/datasource/ConnectionHolder;)V
     110: aload_1
     111: areturn

  protected boolean isExistingTransaction(java.lang.Object);
    Code:
       0: aload_1
       1: checkcast     #29                 // class org/springframework/orm/jdo/JdoTransactionManager$JdoTransactionObject
       4: invokevirtual #43                 // Method org/springframework/orm/jdo/JdoTransactionManager$JdoTransactionObject.hasTransaction:()Z
       7: ireturn

  protected void doBegin(java.lang.Object, org.springframework.transaction.TransactionDefinition);
    Code:
       0: aload_1
       1: checkcast     #29                 // class org/springframework/orm/jdo/JdoTransactionManager$JdoTransactionObject
       4: astore_3
       5: aload_3
       6: invokevirtual #44                 // Method org/springframework/orm/jdo/JdoTransactionManager$JdoTransactionObject.hasConnectionHolder:()Z
       9: ifeq          32
      12: aload_3
      13: invokevirtual #45                 // Method org/springframework/orm/jdo/JdoTransactionManager$JdoTransactionObject.getConnectionHolder:()Lorg/springframework/jdbc/datasource/ConnectionHolder;
      16: invokevirtual #46                 // Method org/springframework/jdbc/datasource/ConnectionHolder.isSynchronizedWithTransaction:()Z
      19: ifne          32
      22: new           #47                 // class org/springframework/transaction/IllegalTransactionStateException
      25: dup
      26: ldc           #48                 // String Pre-bound JDBC Connection found! JdoTransactionManager does not support running within DataSourceTransactionManager if told to manage the DataSource itself. It is recommended to use a single JdoTransactionManager for all transactions on a single DataSource, no matter whether JDO or JDBC access.
      28: invokespecial #49                 // Method org/springframework/transaction/IllegalTransactionStateException."<init>":(Ljava/lang/String;)V
      31: athrow
      32: aload_3
      33: invokevirtual #50                 // Method org/springframework/orm/jdo/JdoTransactionManager$JdoTransactionObject.getPersistenceManagerHolder:()Lorg/springframework/orm/jdo/PersistenceManagerHolder;
      36: ifnull        49
      39: aload_3
      40: invokevirtual #50                 // Method org/springframework/orm/jdo/JdoTransactionManager$JdoTransactionObject.getPersistenceManagerHolder:()Lorg/springframework/orm/jdo/PersistenceManagerHolder;
      43: invokevirtual #51                 // Method org/springframework/orm/jdo/PersistenceManagerHolder.isSynchronizedWithTransaction:()Z
      46: ifeq          120
      49: aload_0
      50: invokevirtual #11                 // Method getPersistenceManagerFactory:()Ljavax/jdo/PersistenceManagerFactory;
      53: invokeinterface #52,  1           // InterfaceMethod javax/jdo/PersistenceManagerFactory.getPersistenceManager:()Ljavax/jdo/PersistenceManager;
      58: astore        5
      60: aload_0
      61: getfield      #19                 // Field logger:Lorg/apache/commons/logging/Log;
      64: invokeinterface #35,  1           // InterfaceMethod org/apache/commons/logging/Log.isDebugEnabled:()Z
      69: ifeq          106
      72: aload_0
      73: getfield      #19                 // Field logger:Lorg/apache/commons/logging/Log;
      76: new           #21                 // class java/lang/StringBuilder
      79: dup
      80: invokespecial #22                 // Method java/lang/StringBuilder."<init>":()V
      83: ldc           #53                 // String Opened new PersistenceManager [
      85: invokevirtual #24                 // Method java/lang/StringBuilder.append:(Ljava/lang/String;)Ljava/lang/StringBuilder;
      88: aload         5
      90: invokevirtual #25                 // Method java/lang/StringBuilder.append:(Ljava/lang/Object;)Ljava/lang/StringBuilder;
      93: ldc           #38                 // String ] for JDO transaction
      95: invokevirtual #24                 // Method java/lang/StringBuilder.append:(Ljava/lang/String;)Ljava/lang/StringBuilder;
      98: invokevirtual #27                 // Method java/lang/StringBuilder.toString:()Ljava/lang/String;
     101: invokeinterface #39,  2           // InterfaceMethod org/apache/commons/logging/Log.debug:(Ljava/lang/Object;)V
     106: aload_3
     107: new           #34                 // class org/springframework/orm/jdo/PersistenceManagerHolder
     110: dup
     111: aload         5
     113: invokespecial #54                 // Method org/springframework/orm/jdo/PersistenceManagerHolder."<init>":(Ljavax/jdo/PersistenceManager;)V
     116: iconst_1
     117: invokevirtual #40                 // Method org/springframework/orm/jdo/JdoTransactionManager$JdoTransactionObject.setPersistenceManagerHolder:(Lorg/springframework/orm/jdo/PersistenceManagerHolder;Z)V
     120: aload_3
     121: invokevirtual #50                 // Method org/springframework/orm/jdo/JdoTransactionManager$JdoTransactionObject.getPersistenceManagerHolder:()Lorg/springframework/orm/jdo/PersistenceManagerHolder;
     124: invokevirtual #37                 // Method org/springframework/orm/jdo/PersistenceManagerHolder.getPersistenceManager:()Ljavax/jdo/PersistenceManager;
     127: astore        4
     129: aload_0
     130: aload_2
     131: invokevirtual #55                 // Method determineTimeout:(Lorg/springframework/transaction/TransactionDefinition;)I
     134: istore        5
     136: aload_0
     137: invokevirtual #56                 // Method getJdoDialect:()Lorg/springframework/orm/jdo/JdoDialect;
     140: aload         4
     142: invokeinterface #57,  1           // InterfaceMethod javax/jdo/PersistenceManager.currentTransaction:()Ljavax/jdo/Transaction;
     147: new           #58                 // class org/springframework/orm/jdo/JdoTransactionManager$1
     150: dup
     151: aload_0
     152: aload_2
     153: iload         5
     155: invokespecial #59                 // Method org/springframework/orm/jdo/JdoTransactionManager$1."<init>":(Lorg/springframework/orm/jdo/JdoTransactionManager;Lorg/springframework/transaction/TransactionDefinition;I)V
     158: invokeinterface #60,  3           // InterfaceMethod org/springframework/orm/jdo/JdoDialect.beginTransaction:(Ljavax/jdo/Transaction;Lorg/springframework/transaction/TransactionDefinition;)Ljava/lang/Object;
     163: astore        6
     165: aload_3
     166: aload         6
     168: invokevirtual #61                 // Method org/springframework/orm/jdo/JdoTransactionManager$JdoTransactionObject.setTransactionData:(Ljava/lang/Object;)V
     171: iload         5
     173: iconst_m1
     174: if_icmpeq     186
     177: aload_3
     178: invokevirtual #50                 // Method org/springframework/orm/jdo/JdoTransactionManager$JdoTransactionObject.getPersistenceManagerHolder:()Lorg/springframework/orm/jdo/PersistenceManagerHolder;
     181: iload         5
     183: invokevirtual #63                 // Method org/springframework/orm/jdo/PersistenceManagerHolder.setTimeoutInSeconds:(I)V
     186: aload_0
     187: invokevirtual #17                 // Method getDataSource:()Ljavax/sql/DataSource;
     190: ifnull        366
     193: aload_0
     194: invokevirtual #56                 // Method getJdoDialect:()Lorg/springframework/orm/jdo/JdoDialect;
     197: aload         4
     199: aload_2
     200: invokeinterface #64,  1           // InterfaceMethod org/springframework/transaction/TransactionDefinition.isReadOnly:()Z
     205: invokeinterface #65,  3           // InterfaceMethod org/springframework/orm/jdo/JdoDialect.getJdbcConnection:(Ljavax/jdo/PersistenceManager;Z)Lorg/springframework/jdbc/datasource/ConnectionHandle;
     210: astore        7
     212: aload         7
     214: ifnull        308
     217: new           #41                 // class org/springframework/jdbc/datasource/ConnectionHolder
     220: dup
     221: aload         7
     223: invokespecial #66                 // Method org/springframework/jdbc/datasource/ConnectionHolder."<init>":(Lorg/springframework/jdbc/datasource/ConnectionHandle;)V
     226: astore        8
     228: iload         5
     230: iconst_m1
     231: if_icmpeq     241
     234: aload         8
     236: iload         5
     238: invokevirtual #67                 // Method org/springframework/jdbc/datasource/ConnectionHolder.setTimeoutInSeconds:(I)V
     241: aload_0
     242: getfield      #19                 // Field logger:Lorg/apache/commons/logging/Log;
     245: invokeinterface #35,  1           // InterfaceMethod org/apache/commons/logging/Log.isDebugEnabled:()Z
     250: ifeq          290
     253: aload_0
     254: getfield      #19                 // Field logger:Lorg/apache/commons/logging/Log;
     257: new           #21                 // class java/lang/StringBuilder
     260: dup
     261: invokespecial #22                 // Method java/lang/StringBuilder."<init>":()V
     264: ldc           #68                 // String Exposing JDO transaction as JDBC transaction [
     266: invokevirtual #24                 // Method java/lang/StringBuilder.append:(Ljava/lang/String;)Ljava/lang/StringBuilder;
     269: aload         8
     271: invokevirtual #69                 // Method org/springframework/jdbc/datasource/ConnectionHolder.getConnectionHandle:()Lorg/springframework/jdbc/datasource/ConnectionHandle;
     274: invokevirtual #25                 // Method java/lang/StringBuilder.append:(Ljava/lang/Object;)Ljava/lang/StringBuilder;
     277: ldc           #70                 // String ]
     279: invokevirtual #24                 // Method java/lang/StringBuilder.append:(Ljava/lang/String;)Ljava/lang/StringBuilder;
     282: invokevirtual #27                 // Method java/lang/StringBuilder.toString:()Ljava/lang/String;
     285: invokeinterface #39,  2           // InterfaceMethod org/apache/commons/logging/Log.debug:(Ljava/lang/Object;)V
     290: aload_0
     291: invokevirtual #17                 // Method getDataSource:()Ljavax/sql/DataSource;
     294: aload         8
     296: invokestatic  #71                 // Method org/springframework/transaction/support/TransactionSynchronizationManager.bindResource:(Ljava/lang/Object;Ljava/lang/Object;)V
     299: aload_3
     300: aload         8
     302: invokevirtual #42                 // Method org/springframework/orm/jdo/JdoTransactionManager$JdoTransactionObject.setConnectionHolder:(Lorg/springframework/jdbc/datasource/ConnectionHolder;)V
     305: goto          366
     308: aload_0
     309: getfield      #19                 // Field logger:Lorg/apache/commons/logging/Log;
     312: invokeinterface #35,  1           // InterfaceMethod org/apache/commons/logging/Log.isDebugEnabled:()Z
     317: ifeq          366
     320: aload_0
     321: getfield      #19                 // Field logger:Lorg/apache/commons/logging/Log;
     324: new           #21                 // class java/lang/StringBuilder
     327: dup
     328: invokespecial #22                 // Method java/lang/StringBuilder."<init>":()V
     331: ldc           #72                 // String Not exposing JDO transaction [
     333: invokevirtual #24                 // Method java/lang/StringBuilder.append:(Ljava/lang/String;)Ljava/lang/StringBuilder;
     336: aload         4
     338: invokevirtual #25                 // Method java/lang/StringBuilder.append:(Ljava/lang/Object;)Ljava/lang/StringBuilder;
     341: ldc           #73                 // String ] as JDBC transaction because JdoDialect [
     343: invokevirtual #24                 // Method java/lang/StringBuilder.append:(Ljava/lang/String;)Ljava/lang/StringBuilder;
     346: aload_0
     347: invokevirtual #56                 // Method getJdoDialect:()Lorg/springframework/orm/jdo/JdoDialect;
     350: invokevirtual #25                 // Method java/lang/StringBuilder.append:(Ljava/lang/Object;)Ljava/lang/StringBuilder;
     353: ldc           #74                 // String ] does not support JDBC Connection retrieval
     355: invokevirtual #24                 // Method java/lang/StringBuilder.append:(Ljava/lang/String;)Ljava/lang/StringBuilder;
     358: invokevirtual #27                 // Method java/lang/StringBuilder.toString:()Ljava/lang/String;
     361: invokeinterface #39,  2           // InterfaceMethod org/apache/commons/logging/Log.debug:(Ljava/lang/Object;)V
     366: aload_3
     367: invokevirtual #75                 // Method org/springframework/orm/jdo/JdoTransactionManager$JdoTransactionObject.isNewPersistenceManagerHolder:()Z
     370: ifeq          384
     373: aload_0
     374: invokevirtual #11                 // Method getPersistenceManagerFactory:()Ljavax/jdo/PersistenceManagerFactory;
     377: aload_3
     378: invokevirtual #50                 // Method org/springframework/orm/jdo/JdoTransactionManager$JdoTransactionObject.getPersistenceManagerHolder:()Lorg/springframework/orm/jdo/PersistenceManagerHolder;
     381: invokestatic  #71                 // Method org/springframework/transaction/support/TransactionSynchronizationManager.bindResource:(Ljava/lang/Object;Ljava/lang/Object;)V
     384: aload_3
     385: invokevirtual #50                 // Method org/springframework/orm/jdo/JdoTransactionManager$JdoTransactionObject.getPersistenceManagerHolder:()Lorg/springframework/orm/jdo/PersistenceManagerHolder;
     388: iconst_1
     389: invokevirtual #76                 // Method org/springframework/orm/jdo/PersistenceManagerHolder.setSynchronizedWithTransaction:(Z)V
     392: goto          424
     395: astore        5
     397: aload_0
     398: aload_3
     399: invokevirtual #78                 // Method closePersistenceManagerAfterFailedBegin:(Lorg/springframework/orm/jdo/JdoTransactionManager$JdoTransactionObject;)V
     402: aload         5
     404: athrow
     405: astore        5
     407: aload_0
     408: aload_3
     409: invokevirtual #78                 // Method closePersistenceManagerAfterFailedBegin:(Lorg/springframework/orm/jdo/JdoTransactionManager$JdoTransactionObject;)V
     412: new           #80                 // class org/springframework/transaction/CannotCreateTransactionException
     415: dup
     416: ldc           #81                 // String Could not open JDO PersistenceManager for transaction
     418: aload         5
     420: invokespecial #82                 // Method org/springframework/transaction/CannotCreateTransactionException."<init>":(Ljava/lang/String;Ljava/lang/Throwable;)V
     423: athrow
     424: return
    Exception table:
       from    to  target type
          32   392   395   Class org/springframework/transaction/TransactionException
          32   392   405   Class java/lang/Throwable

  protected void closePersistenceManagerAfterFailedBegin(org.springframework.orm.jdo.JdoTransactionManager$JdoTransactionObject);
    Code:
       0: aload_1
       1: invokevirtual #75                 // Method org/springframework/orm/jdo/JdoTransactionManager$JdoTransactionObject.isNewPersistenceManagerHolder:()Z
       4: ifeq          94
       7: aload_1
       8: invokevirtual #50                 // Method org/springframework/orm/jdo/JdoTransactionManager$JdoTransactionObject.getPersistenceManagerHolder:()Lorg/springframework/orm/jdo/PersistenceManagerHolder;
      11: invokevirtual #37                 // Method org/springframework/orm/jdo/PersistenceManagerHolder.getPersistenceManager:()Ljavax/jdo/PersistenceManager;
      14: astore_2
      15: aload_2
      16: invokeinterface #57,  1           // InterfaceMethod javax/jdo/PersistenceManager.currentTransaction:()Ljavax/jdo/Transaction;
      21: invokeinterface #83,  1           // InterfaceMethod javax/jdo/Transaction.isActive:()Z
      26: ifeq          40
      29: aload_2
      30: invokeinterface #57,  1           // InterfaceMethod javax/jdo/PersistenceManager.currentTransaction:()Ljavax/jdo/Transaction;
      35: invokeinterface #84,  1           // InterfaceMethod javax/jdo/Transaction.rollback:()V
      40: aload_2
      41: aload_0
      42: invokevirtual #11                 // Method getPersistenceManagerFactory:()Ljavax/jdo/PersistenceManagerFactory;
      45: invokestatic  #85                 // Method org/springframework/orm/jdo/PersistenceManagerFactoryUtils.releasePersistenceManager:(Ljavax/jdo/PersistenceManager;Ljavax/jdo/PersistenceManagerFactory;)V
      48: goto          88
      51: astore_3
      52: aload_0
      53: getfield      #19                 // Field logger:Lorg/apache/commons/logging/Log;
      56: ldc           #86                 // String Could not rollback PersistenceManager after failed transaction begin
      58: aload_3
      59: invokeinterface #87,  3           // InterfaceMethod org/apache/commons/logging/Log.debug:(Ljava/lang/Object;Ljava/lang/Throwable;)V
      64: aload_2
      65: aload_0
      66: invokevirtual #11                 // Method getPersistenceManagerFactory:()Ljavax/jdo/PersistenceManagerFactory;
      69: invokestatic  #85                 // Method org/springframework/orm/jdo/PersistenceManagerFactoryUtils.releasePersistenceManager:(Ljavax/jdo/PersistenceManager;Ljavax/jdo/PersistenceManagerFactory;)V
      72: goto          88
      75: astore        4
      77: aload_2
      78: aload_0
      79: invokevirtual #11                 // Method getPersistenceManagerFactory:()Ljavax/jdo/PersistenceManagerFactory;
      82: invokestatic  #85                 // Method org/springframework/orm/jdo/PersistenceManagerFactoryUtils.releasePersistenceManager:(Ljavax/jdo/PersistenceManager;Ljavax/jdo/PersistenceManagerFactory;)V
      85: aload         4
      87: athrow
      88: aload_1
      89: aconst_null
      90: iconst_0
      91: invokevirtual #40                 // Method org/springframework/orm/jdo/JdoTransactionManager$JdoTransactionObject.setPersistenceManagerHolder:(Lorg/springframework/orm/jdo/PersistenceManagerHolder;Z)V
      94: return
    Exception table:
       from    to  target type
          15    40    51   Class java/lang/Throwable
          15    40    75   any
          51    64    75   any
          75    77    75   any

  protected java.lang.Object doSuspend(java.lang.Object);
    Code:
       0: aload_1
       1: checkcast     #29                 // class org/springframework/orm/jdo/JdoTransactionManager$JdoTransactionObject
       4: astore_2
       5: aload_2
       6: aconst_null
       7: iconst_0
       8: invokevirtual #40                 // Method org/springframework/orm/jdo/JdoTransactionManager$JdoTransactionObject.setPersistenceManagerHolder:(Lorg/springframework/orm/jdo/PersistenceManagerHolder;Z)V
      11: aload_0
      12: invokevirtual #11                 // Method getPersistenceManagerFactory:()Ljavax/jdo/PersistenceManagerFactory;
      15: invokestatic  #88                 // Method org/springframework/transaction/support/TransactionSynchronizationManager.unbindResource:(Ljava/lang/Object;)Ljava/lang/Object;
      18: checkcast     #34                 // class org/springframework/orm/jdo/PersistenceManagerHolder
      21: astore_3
      22: aload_2
      23: aconst_null
      24: invokevirtual #42                 // Method org/springframework/orm/jdo/JdoTransactionManager$JdoTransactionObject.setConnectionHolder:(Lorg/springframework/jdbc/datasource/ConnectionHolder;)V
      27: aconst_null
      28: astore        4
      30: aload_0
      31: invokevirtual #17                 // Method getDataSource:()Ljavax/sql/DataSource;
      34: ifnull        59
      37: aload_0
      38: invokevirtual #17                 // Method getDataSource:()Ljavax/sql/DataSource;
      41: invokestatic  #89                 // Method org/springframework/transaction/support/TransactionSynchronizationManager.hasResource:(Ljava/lang/Object;)Z
      44: ifeq          59
      47: aload_0
      48: invokevirtual #17                 // Method getDataSource:()Ljavax/sql/DataSource;
      51: invokestatic  #88                 // Method org/springframework/transaction/support/TransactionSynchronizationManager.unbindResource:(Ljava/lang/Object;)Ljava/lang/Object;
      54: checkcast     #41                 // class org/springframework/jdbc/datasource/ConnectionHolder
      57: astore        4
      59: new           #90                 // class org/springframework/orm/jdo/JdoTransactionManager$SuspendedResourcesHolder
      62: dup
      63: aload_3
      64: aload         4
      66: aconst_null
      67: invokespecial #91                 // Method org/springframework/orm/jdo/JdoTransactionManager$SuspendedResourcesHolder."<init>":(Lorg/springframework/orm/jdo/PersistenceManagerHolder;Lorg/springframework/jdbc/datasource/ConnectionHolder;Lorg/springframework/orm/jdo/JdoTransactionManager$1;)V
      70: areturn

  protected void doResume(java.lang.Object, java.lang.Object);
    Code:
       0: aload_2
       1: checkcast     #90                 // class org/springframework/orm/jdo/JdoTransactionManager$SuspendedResourcesHolder
       4: astore_3
       5: aload_0
       6: invokevirtual #11                 // Method getPersistenceManagerFactory:()Ljavax/jdo/PersistenceManagerFactory;
       9: aload_3
      10: invokestatic  #92                 // Method org/springframework/orm/jdo/JdoTransactionManager$SuspendedResourcesHolder.access$200:(Lorg/springframework/orm/jdo/JdoTransactionManager$SuspendedResourcesHolder;)Lorg/springframework/orm/jdo/PersistenceManagerHolder;
      13: invokestatic  #71                 // Method org/springframework/transaction/support/TransactionSynchronizationManager.bindResource:(Ljava/lang/Object;Ljava/lang/Object;)V
      16: aload_0
      17: invokevirtual #17                 // Method getDataSource:()Ljavax/sql/DataSource;
      20: ifnull        41
      23: aload_3
      24: invokestatic  #93                 // Method org/springframework/orm/jdo/JdoTransactionManager$SuspendedResourcesHolder.access$300:(Lorg/springframework/orm/jdo/JdoTransactionManager$SuspendedResourcesHolder;)Lorg/springframework/jdbc/datasource/ConnectionHolder;
      27: ifnull        41
      30: aload_0
      31: invokevirtual #17                 // Method getDataSource:()Ljavax/sql/DataSource;
      34: aload_3
      35: invokestatic  #93                 // Method org/springframework/orm/jdo/JdoTransactionManager$SuspendedResourcesHolder.access$300:(Lorg/springframework/orm/jdo/JdoTransactionManager$SuspendedResourcesHolder;)Lorg/springframework/jdbc/datasource/ConnectionHolder;
      38: invokestatic  #71                 // Method org/springframework/transaction/support/TransactionSynchronizationManager.bindResource:(Ljava/lang/Object;Ljava/lang/Object;)V
      41: return

  protected boolean shouldCommitOnGlobalRollbackOnly();
    Code:
       0: iconst_1
       1: ireturn

  protected void doCommit(org.springframework.transaction.support.DefaultTransactionStatus);
    Code:
       0: aload_1
       1: invokevirtual #94                 // Method org/springframework/transaction/support/DefaultTransactionStatus.getTransaction:()Ljava/lang/Object;
       4: checkcast     #29                 // class org/springframework/orm/jdo/JdoTransactionManager$JdoTransactionObject
       7: astore_2
       8: aload_1
       9: invokevirtual #95                 // Method org/springframework/transaction/support/DefaultTransactionStatus.isDebug:()Z
      12: ifeq          54
      15: aload_0
      16: getfield      #19                 // Field logger:Lorg/apache/commons/logging/Log;
      19: new           #21                 // class java/lang/StringBuilder
      22: dup
      23: invokespecial #22                 // Method java/lang/StringBuilder."<init>":()V
      26: ldc           #96                 // String Committing JDO transaction on PersistenceManager [
      28: invokevirtual #24                 // Method java/lang/StringBuilder.append:(Ljava/lang/String;)Ljava/lang/StringBuilder;
      31: aload_2
      32: invokevirtual #50                 // Method org/springframework/orm/jdo/JdoTransactionManager$JdoTransactionObject.getPersistenceManagerHolder:()Lorg/springframework/orm/jdo/PersistenceManagerHolder;
      35: invokevirtual #37                 // Method org/springframework/orm/jdo/PersistenceManagerHolder.getPersistenceManager:()Ljavax/jdo/PersistenceManager;
      38: invokevirtual #25                 // Method java/lang/StringBuilder.append:(Ljava/lang/Object;)Ljava/lang/StringBuilder;
      41: ldc           #70                 // String ]
      43: invokevirtual #24                 // Method java/lang/StringBuilder.append:(Ljava/lang/String;)Ljava/lang/StringBuilder;
      46: invokevirtual #27                 // Method java/lang/StringBuilder.toString:()Ljava/lang/String;
      49: invokeinterface #39,  2           // InterfaceMethod org/apache/commons/logging/Log.debug:(Ljava/lang/Object;)V
      54: aload_2
      55: invokevirtual #50                 // Method org/springframework/orm/jdo/JdoTransactionManager$JdoTransactionObject.getPersistenceManagerHolder:()Lorg/springframework/orm/jdo/PersistenceManagerHolder;
      58: invokevirtual #37                 // Method org/springframework/orm/jdo/PersistenceManagerHolder.getPersistenceManager:()Ljavax/jdo/PersistenceManager;
      61: invokeinterface #57,  1           // InterfaceMethod javax/jdo/PersistenceManager.currentTransaction:()Ljavax/jdo/Transaction;
      66: astore_3
      67: aload_3
      68: invokeinterface #97,  1           // InterfaceMethod javax/jdo/Transaction.commit:()V
      73: goto          83
      76: astore_3
      77: aload_0
      78: aload_3
      79: invokevirtual #99                 // Method convertJdoAccessException:(Ljavax/jdo/JDOException;)Lorg/springframework/dao/DataAccessException;
      82: athrow
      83: return
    Exception table:
       from    to  target type
          54    73    76   Class javax/jdo/JDOException

  protected void doRollback(org.springframework.transaction.support.DefaultTransactionStatus);
    Code:
       0: aload_1
       1: invokevirtual #94                 // Method org/springframework/transaction/support/DefaultTransactionStatus.getTransaction:()Ljava/lang/Object;
       4: checkcast     #29                 // class org/springframework/orm/jdo/JdoTransactionManager$JdoTransactionObject
       7: astore_2
       8: aload_1
       9: invokevirtual #95                 // Method org/springframework/transaction/support/DefaultTransactionStatus.isDebug:()Z
      12: ifeq          54
      15: aload_0
      16: getfield      #19                 // Field logger:Lorg/apache/commons/logging/Log;
      19: new           #21                 // class java/lang/StringBuilder
      22: dup
      23: invokespecial #22                 // Method java/lang/StringBuilder."<init>":()V
      26: ldc           #100                // String Rolling back JDO transaction on PersistenceManager [
      28: invokevirtual #24                 // Method java/lang/StringBuilder.append:(Ljava/lang/String;)Ljava/lang/StringBuilder;
      31: aload_2
      32: invokevirtual #50                 // Method org/springframework/orm/jdo/JdoTransactionManager$JdoTransactionObject.getPersistenceManagerHolder:()Lorg/springframework/orm/jdo/PersistenceManagerHolder;
      35: invokevirtual #37                 // Method org/springframework/orm/jdo/PersistenceManagerHolder.getPersistenceManager:()Ljavax/jdo/PersistenceManager;
      38: invokevirtual #25                 // Method java/lang/StringBuilder.append:(Ljava/lang/Object;)Ljava/lang/StringBuilder;
      41: ldc           #70                 // String ]
      43: invokevirtual #24                 // Method java/lang/StringBuilder.append:(Ljava/lang/String;)Ljava/lang/StringBuilder;
      46: invokevirtual #27                 // Method java/lang/StringBuilder.toString:()Ljava/lang/String;
      49: invokeinterface #39,  2           // InterfaceMethod org/apache/commons/logging/Log.debug:(Ljava/lang/Object;)V
      54: aload_2
      55: invokevirtual #50                 // Method org/springframework/orm/jdo/JdoTransactionManager$JdoTransactionObject.getPersistenceManagerHolder:()Lorg/springframework/orm/jdo/PersistenceManagerHolder;
      58: invokevirtual #37                 // Method org/springframework/orm/jdo/PersistenceManagerHolder.getPersistenceManager:()Ljavax/jdo/PersistenceManager;
      61: invokeinterface #57,  1           // InterfaceMethod javax/jdo/PersistenceManager.currentTransaction:()Ljavax/jdo/Transaction;
      66: astore_3
      67: aload_3
      68: invokeinterface #83,  1           // InterfaceMethod javax/jdo/Transaction.isActive:()Z
      73: ifeq          82
      76: aload_3
      77: invokeinterface #84,  1           // InterfaceMethod javax/jdo/Transaction.rollback:()V
      82: goto          97
      85: astore_3
      86: new           #101                // class org/springframework/transaction/TransactionSystemException
      89: dup
      90: ldc           #102                // String Could not roll back JDO transaction
      92: aload_3
      93: invokespecial #103                // Method org/springframework/transaction/TransactionSystemException."<init>":(Ljava/lang/String;Ljava/lang/Throwable;)V
      96: athrow
      97: return
    Exception table:
       from    to  target type
          54    82    85   Class javax/jdo/JDOException

  protected void doSetRollbackOnly(org.springframework.transaction.support.DefaultTransactionStatus);
    Code:
       0: aload_1
       1: invokevirtual #94                 // Method org/springframework/transaction/support/DefaultTransactionStatus.getTransaction:()Ljava/lang/Object;
       4: checkcast     #29                 // class org/springframework/orm/jdo/JdoTransactionManager$JdoTransactionObject
       7: astore_2
       8: aload_1
       9: invokevirtual #95                 // Method org/springframework/transaction/support/DefaultTransactionStatus.isDebug:()Z
      12: ifeq          54
      15: aload_0
      16: getfield      #19                 // Field logger:Lorg/apache/commons/logging/Log;
      19: new           #21                 // class java/lang/StringBuilder
      22: dup
      23: invokespecial #22                 // Method java/lang/StringBuilder."<init>":()V
      26: ldc           #104                // String Setting JDO transaction on PersistenceManager [
      28: invokevirtual #24                 // Method java/lang/StringBuilder.append:(Ljava/lang/String;)Ljava/lang/StringBuilder;
      31: aload_2
      32: invokevirtual #50                 // Method org/springframework/orm/jdo/JdoTransactionManager$JdoTransactionObject.getPersistenceManagerHolder:()Lorg/springframework/orm/jdo/PersistenceManagerHolder;
      35: invokevirtual #37                 // Method org/springframework/orm/jdo/PersistenceManagerHolder.getPersistenceManager:()Ljavax/jdo/PersistenceManager;
      38: invokevirtual #25                 // Method java/lang/StringBuilder.append:(Ljava/lang/Object;)Ljava/lang/StringBuilder;
      41: ldc           #105                // String ] rollback-only
      43: invokevirtual #24                 // Method java/lang/StringBuilder.append:(Ljava/lang/String;)Ljava/lang/StringBuilder;
      46: invokevirtual #27                 // Method java/lang/StringBuilder.toString:()Ljava/lang/String;
      49: invokeinterface #39,  2           // InterfaceMethod org/apache/commons/logging/Log.debug:(Ljava/lang/Object;)V
      54: aload_2
      55: invokevirtual #106                // Method org/springframework/orm/jdo/JdoTransactionManager$JdoTransactionObject.setRollbackOnly:()V
      58: return

  protected void doCleanupAfterCompletion(java.lang.Object);
    Code:
       0: aload_1
       1: checkcast     #29                 // class org/springframework/orm/jdo/JdoTransactionManager$JdoTransactionObject
       4: astore_2
       5: aload_2
       6: invokevirtual #75                 // Method org/springframework/orm/jdo/JdoTransactionManager$JdoTransactionObject.isNewPersistenceManagerHolder:()Z
       9: ifeq          20
      12: aload_0
      13: invokevirtual #11                 // Method getPersistenceManagerFactory:()Ljavax/jdo/PersistenceManagerFactory;
      16: invokestatic  #88                 // Method org/springframework/transaction/support/TransactionSynchronizationManager.unbindResource:(Ljava/lang/Object;)Ljava/lang/Object;
      19: pop
      20: aload_2
      21: invokevirtual #50                 // Method org/springframework/orm/jdo/JdoTransactionManager$JdoTransactionObject.getPersistenceManagerHolder:()Lorg/springframework/orm/jdo/PersistenceManagerHolder;
      24: invokevirtual #107                // Method org/springframework/orm/jdo/PersistenceManagerHolder.clear:()V
      27: aload_2
      28: invokevirtual #44                 // Method org/springframework/orm/jdo/JdoTransactionManager$JdoTransactionObject.hasConnectionHolder:()Z
      31: ifeq          81
      34: aload_0
      35: invokevirtual #17                 // Method getDataSource:()Ljavax/sql/DataSource;
      38: invokestatic  #88                 // Method org/springframework/transaction/support/TransactionSynchronizationManager.unbindResource:(Ljava/lang/Object;)Ljava/lang/Object;
      41: pop
      42: aload_0
      43: invokevirtual #56                 // Method getJdoDialect:()Lorg/springframework/orm/jdo/JdoDialect;
      46: aload_2
      47: invokevirtual #45                 // Method org/springframework/orm/jdo/JdoTransactionManager$JdoTransactionObject.getConnectionHolder:()Lorg/springframework/jdbc/datasource/ConnectionHolder;
      50: invokevirtual #69                 // Method org/springframework/jdbc/datasource/ConnectionHolder.getConnectionHandle:()Lorg/springframework/jdbc/datasource/ConnectionHandle;
      53: aload_2
      54: invokevirtual #50                 // Method org/springframework/orm/jdo/JdoTransactionManager$JdoTransactionObject.getPersistenceManagerHolder:()Lorg/springframework/orm/jdo/PersistenceManagerHolder;
      57: invokevirtual #37                 // Method org/springframework/orm/jdo/PersistenceManagerHolder.getPersistenceManager:()Ljavax/jdo/PersistenceManager;
      60: invokeinterface #108,  3          // InterfaceMethod org/springframework/orm/jdo/JdoDialect.releaseJdbcConnection:(Lorg/springframework/jdbc/datasource/ConnectionHandle;Ljavax/jdo/PersistenceManager;)V
      65: goto          81
      68: astore_3
      69: aload_0
      70: getfield      #19                 // Field logger:Lorg/apache/commons/logging/Log;
      73: ldc           #109                // String Could not release JDBC connection after transaction
      75: aload_3
      76: invokeinterface #87,  3           // InterfaceMethod org/apache/commons/logging/Log.debug:(Ljava/lang/Object;Ljava/lang/Throwable;)V
      81: aload_0
      82: invokevirtual #56                 // Method getJdoDialect:()Lorg/springframework/orm/jdo/JdoDialect;
      85: aload_2
      86: invokevirtual #110                // Method org/springframework/orm/jdo/JdoTransactionManager$JdoTransactionObject.getTransactionData:()Ljava/lang/Object;
      89: invokeinterface #111,  2          // InterfaceMethod org/springframework/orm/jdo/JdoDialect.cleanupTransaction:(Ljava/lang/Object;)V
      94: aload_2
      95: invokevirtual #75                 // Method org/springframework/orm/jdo/JdoTransactionManager$JdoTransactionObject.isNewPersistenceManagerHolder:()Z
      98: ifeq          165
     101: aload_2
     102: invokevirtual #50                 // Method org/springframework/orm/jdo/JdoTransactionManager$JdoTransactionObject.getPersistenceManagerHolder:()Lorg/springframework/orm/jdo/PersistenceManagerHolder;
     105: invokevirtual #37                 // Method org/springframework/orm/jdo/PersistenceManagerHolder.getPersistenceManager:()Ljavax/jdo/PersistenceManager;
     108: astore_3
     109: aload_0
     110: getfield      #19                 // Field logger:Lorg/apache/commons/logging/Log;
     113: invokeinterface #35,  1           // InterfaceMethod org/apache/commons/logging/Log.isDebugEnabled:()Z
     118: ifeq          154
     121: aload_0
     122: getfield      #19                 // Field logger:Lorg/apache/commons/logging/Log;
     125: new           #21                 // class java/lang/StringBuilder
     128: dup
     129: invokespecial #22                 // Method java/lang/StringBuilder."<init>":()V
     132: ldc           #112                // String Closing JDO PersistenceManager [
     134: invokevirtual #24                 // Method java/lang/StringBuilder.append:(Ljava/lang/String;)Ljava/lang/StringBuilder;
     137: aload_3
     138: invokevirtual #25                 // Method java/lang/StringBuilder.append:(Ljava/lang/Object;)Ljava/lang/StringBuilder;
     141: ldc           #113                // String ] after transaction
     143: invokevirtual #24                 // Method java/lang/StringBuilder.append:(Ljava/lang/String;)Ljava/lang/StringBuilder;
     146: invokevirtual #27                 // Method java/lang/StringBuilder.toString:()Ljava/lang/String;
     149: invokeinterface #39,  2           // InterfaceMethod org/apache/commons/logging/Log.debug:(Ljava/lang/Object;)V
     154: aload_3
     155: aload_0
     156: invokevirtual #11                 // Method getPersistenceManagerFactory:()Ljavax/jdo/PersistenceManagerFactory;
     159: invokestatic  #85                 // Method org/springframework/orm/jdo/PersistenceManagerFactoryUtils.releasePersistenceManager:(Ljavax/jdo/PersistenceManager;Ljavax/jdo/PersistenceManagerFactory;)V
     162: goto          176
     165: aload_0
     166: getfield      #19                 // Field logger:Lorg/apache/commons/logging/Log;
     169: ldc           #114                // String Not closing pre-bound JDO PersistenceManager after transaction
     171: invokeinterface #39,  2           // InterfaceMethod org/apache/commons/logging/Log.debug:(Ljava/lang/Object;)V
     176: return
    Exception table:
       from    to  target type
          42    65    68   Class java/lang/Throwable

  protected org.springframework.dao.DataAccessException convertJdoAccessException(javax.jdo.JDOException);
    Code:
       0: aload_0
       1: invokevirtual #56                 // Method getJdoDialect:()Lorg/springframework/orm/jdo/JdoDialect;
       4: aload_1
       5: invokeinterface #115,  2          // InterfaceMethod org/springframework/orm/jdo/JdoDialect.translateException:(Ljavax/jdo/JDOException;)Lorg/springframework/dao/DataAccessException;
      10: areturn
}
