Compiled from "PageAdapter.java"
public class org.springframework.data.domain.jaxb.PageAdapter extends javax.xml.bind.annotation.adapters.XmlAdapter<org.springframework.data.domain.jaxb.SpringDataJaxb$PageDto, org.springframework.data.domain.Page<java.lang.Object>> {
  public org.springframework.data.domain.jaxb.PageAdapter();
    Code:
       0: aload_0
       1: invokespecial #1                  // Method javax/xml/bind/annotation/adapters/XmlAdapter."<init>":()V
       4: return

  public org.springframework.data.domain.jaxb.SpringDataJaxb$PageDto marshal(org.springframework.data.domain.Page<java.lang.Object>);
    Code:
       0: aload_1
       1: ifnonnull     6
       4: aconst_null
       5: areturn
       6: new           #2                  // class org/springframework/data/domain/jaxb/SpringDataJaxb$PageDto
       9: dup
      10: invokespecial #3                  // Method org/springframework/data/domain/jaxb/SpringDataJaxb$PageDto."<init>":()V
      13: astore_2
      14: aload_2
      15: aload_1
      16: invokeinterface #4,  1            // InterfaceMethod org/springframework/data/domain/Page.getContent:()Ljava/util/List;
      21: putfield      #5                  // Field org/springframework/data/domain/jaxb/SpringDataJaxb$PageDto.content:Ljava/util/List;
      24: aload_2
      25: aload_0
      26: aload_1
      27: invokevirtual #6                  // Method getLinks:(Lorg/springframework/data/domain/Page;)Ljava/util/List;
      30: invokevirtual #7                  // Method org/springframework/data/domain/jaxb/SpringDataJaxb$PageDto.add:(Ljava/lang/Iterable;)V
      33: aload_2
      34: areturn

  public org.springframework.data.domain.Page<java.lang.Object> unmarshal(org.springframework.data.domain.jaxb.SpringDataJaxb$PageDto);
    Code:
       0: aconst_null
       1: areturn

  protected java.util.List<org.springframework.hateoas.Link> getLinks(org.springframework.data.domain.Page<?>);
    Code:
       0: invokestatic  #8                  // Method java/util/Collections.emptyList:()Ljava/util/List;
       3: areturn

  public java.lang.Object marshal(java.lang.Object) throws java.lang.Exception;
    Code:
       0: aload_0
       1: aload_1
       2: checkcast     #9                  // class org/springframework/data/domain/Page
       5: invokevirtual #10                 // Method marshal:(Lorg/springframework/data/domain/Page;)Lorg/springframework/data/domain/jaxb/SpringDataJaxb$PageDto;
       8: areturn

  public java.lang.Object unmarshal(java.lang.Object) throws java.lang.Exception;
    Code:
       0: aload_0
       1: aload_1
       2: checkcast     #2                  // class org/springframework/data/domain/jaxb/SpringDataJaxb$PageDto
       5: invokevirtual #11                 // Method unmarshal:(Lorg/springframework/data/domain/jaxb/SpringDataJaxb$PageDto;)Lorg/springframework/data/domain/Page;
       8: areturn
}
