Compiled from "FilterCollectionWriter.java"
public class org.apache.commons.io.output.FilterCollectionWriter extends java.io.Writer {
  protected final java.util.Collection<java.io.Writer> EMPTY_WRITERS;

  protected final java.util.Collection<java.io.Writer> writers;

  protected org.apache.commons.io.output.FilterCollectionWriter(java.util.Collection<java.io.Writer>);
    Code:
       0: aload_0
       1: invokespecial #1                  // Method java/io/Writer."<init>":()V
       4: aload_0
       5: invokestatic  #2                  // Method java/util/Collections.emptyList:()Ljava/util/List;
       8: putfield      #3                  // Field EMPTY_WRITERS:Ljava/util/Collection;
      11: aload_0
      12: aload_1
      13: ifnonnull     23
      16: aload_0
      17: getfield      #3                  // Field EMPTY_WRITERS:Ljava/util/Collection;
      20: goto          24
      23: aload_1
      24: putfield      #4                  // Field writers:Ljava/util/Collection;
      27: return

  protected org.apache.commons.io.output.FilterCollectionWriter(java.io.Writer...);
    Code:
       0: aload_0
       1: invokespecial #1                  // Method java/io/Writer."<init>":()V
       4: aload_0
       5: invokestatic  #2                  // Method java/util/Collections.emptyList:()Ljava/util/List;
       8: putfield      #3                  // Field EMPTY_WRITERS:Ljava/util/Collection;
      11: aload_0
      12: aload_1
      13: ifnonnull     23
      16: aload_0
      17: getfield      #3                  // Field EMPTY_WRITERS:Ljava/util/Collection;
      20: goto          27
      23: aload_1
      24: invokestatic  #5                  // Method java/util/Arrays.asList:([Ljava/lang/Object;)Ljava/util/List;
      27: putfield      #4                  // Field writers:Ljava/util/Collection;
      30: return

  public java.io.Writer append(char) throws java.io.IOException;
    Code:
       0: new           #6                  // class java/util/ArrayList
       3: dup
       4: invokespecial #7                  // Method java/util/ArrayList."<init>":()V
       7: astore_2
       8: iconst_0
       9: istore_3
      10: aload_0
      11: getfield      #4                  // Field writers:Ljava/util/Collection;
      14: invokeinterface #8,  1            // InterfaceMethod java/util/Collection.iterator:()Ljava/util/Iterator;
      19: astore        4
      21: aload         4
      23: invokeinterface #9,  1            // InterfaceMethod java/util/Iterator.hasNext:()Z
      28: ifeq          83
      31: aload         4
      33: invokeinterface #10,  1           // InterfaceMethod java/util/Iterator.next:()Ljava/lang/Object;
      38: checkcast     #11                 // class java/io/Writer
      41: astore        5
      43: aload         5
      45: ifnull        77
      48: aload         5
      50: iload_1
      51: invokevirtual #12                 // Method java/io/Writer.append:(C)Ljava/io/Writer;
      54: pop
      55: goto          77
      58: astore        6
      60: aload_2
      61: new           #14                 // class org/apache/commons/io/IOIndexedException
      64: dup
      65: iload_3
      66: aload         6
      68: invokespecial #15                 // Method org/apache/commons/io/IOIndexedException."<init>":(ILjava/lang/Throwable;)V
      71: invokeinterface #16,  2           // InterfaceMethod java/util/List.add:(Ljava/lang/Object;)Z
      76: pop
      77: iinc          3, 1
      80: goto          21
      83: aload_2
      84: invokeinterface #17,  1           // InterfaceMethod java/util/List.isEmpty:()Z
      89: ifne          101
      92: new           #18                 // class org/apache/commons/io/IOExceptionList
      95: dup
      96: aload_2
      97: invokespecial #19                 // Method org/apache/commons/io/IOExceptionList."<init>":(Ljava/util/List;)V
     100: athrow
     101: aload_0
     102: areturn
    Exception table:
       from    to  target type
          48    55    58   Class java/io/IOException

  public java.io.Writer append(java.lang.CharSequence) throws java.io.IOException;
    Code:
       0: new           #6                  // class java/util/ArrayList
       3: dup
       4: invokespecial #7                  // Method java/util/ArrayList."<init>":()V
       7: astore_2
       8: iconst_0
       9: istore_3
      10: aload_0
      11: getfield      #4                  // Field writers:Ljava/util/Collection;
      14: invokeinterface #8,  1            // InterfaceMethod java/util/Collection.iterator:()Ljava/util/Iterator;
      19: astore        4
      21: aload         4
      23: invokeinterface #9,  1            // InterfaceMethod java/util/Iterator.hasNext:()Z
      28: ifeq          83
      31: aload         4
      33: invokeinterface #10,  1           // InterfaceMethod java/util/Iterator.next:()Ljava/lang/Object;
      38: checkcast     #11                 // class java/io/Writer
      41: astore        5
      43: aload         5
      45: ifnull        77
      48: aload         5
      50: aload_1
      51: invokevirtual #20                 // Method java/io/Writer.append:(Ljava/lang/CharSequence;)Ljava/io/Writer;
      54: pop
      55: goto          77
      58: astore        6
      60: aload_2
      61: new           #14                 // class org/apache/commons/io/IOIndexedException
      64: dup
      65: iload_3
      66: aload         6
      68: invokespecial #15                 // Method org/apache/commons/io/IOIndexedException."<init>":(ILjava/lang/Throwable;)V
      71: invokeinterface #16,  2           // InterfaceMethod java/util/List.add:(Ljava/lang/Object;)Z
      76: pop
      77: iinc          3, 1
      80: goto          21
      83: aload_2
      84: invokeinterface #17,  1           // InterfaceMethod java/util/List.isEmpty:()Z
      89: ifne          101
      92: new           #18                 // class org/apache/commons/io/IOExceptionList
      95: dup
      96: aload_2
      97: invokespecial #19                 // Method org/apache/commons/io/IOExceptionList."<init>":(Ljava/util/List;)V
     100: athrow
     101: aload_0
     102: areturn
    Exception table:
       from    to  target type
          48    55    58   Class java/io/IOException

  public java.io.Writer append(java.lang.CharSequence, int, int) throws java.io.IOException;
    Code:
       0: new           #6                  // class java/util/ArrayList
       3: dup
       4: invokespecial #7                  // Method java/util/ArrayList."<init>":()V
       7: astore        4
       9: iconst_0
      10: istore        5
      12: aload_0
      13: getfield      #4                  // Field writers:Ljava/util/Collection;
      16: invokeinterface #8,  1            // InterfaceMethod java/util/Collection.iterator:()Ljava/util/Iterator;
      21: astore        6
      23: aload         6
      25: invokeinterface #9,  1            // InterfaceMethod java/util/Iterator.hasNext:()Z
      30: ifeq          89
      33: aload         6
      35: invokeinterface #10,  1           // InterfaceMethod java/util/Iterator.next:()Ljava/lang/Object;
      40: checkcast     #11                 // class java/io/Writer
      43: astore        7
      45: aload         7
      47: ifnull        83
      50: aload         7
      52: aload_1
      53: iload_2
      54: iload_3
      55: invokevirtual #21                 // Method java/io/Writer.append:(Ljava/lang/CharSequence;II)Ljava/io/Writer;
      58: pop
      59: goto          83
      62: astore        8
      64: aload         4
      66: new           #14                 // class org/apache/commons/io/IOIndexedException
      69: dup
      70: iload         5
      72: aload         8
      74: invokespecial #15                 // Method org/apache/commons/io/IOIndexedException."<init>":(ILjava/lang/Throwable;)V
      77: invokeinterface #16,  2           // InterfaceMethod java/util/List.add:(Ljava/lang/Object;)Z
      82: pop
      83: iinc          5, 1
      86: goto          23
      89: aload         4
      91: invokeinterface #17,  1           // InterfaceMethod java/util/List.isEmpty:()Z
      96: ifne          109
      99: new           #18                 // class org/apache/commons/io/IOExceptionList
     102: dup
     103: aload         4
     105: invokespecial #19                 // Method org/apache/commons/io/IOExceptionList."<init>":(Ljava/util/List;)V
     108: athrow
     109: aload_0
     110: areturn
    Exception table:
       from    to  target type
          50    59    62   Class java/io/IOException

  public void close() throws java.io.IOException;
    Code:
       0: new           #6                  // class java/util/ArrayList
       3: dup
       4: invokespecial #7                  // Method java/util/ArrayList."<init>":()V
       7: astore_1
       8: iconst_0
       9: istore_2
      10: aload_0
      11: getfield      #4                  // Field writers:Ljava/util/Collection;
      14: invokeinterface #8,  1            // InterfaceMethod java/util/Collection.iterator:()Ljava/util/Iterator;
      19: astore_3
      20: aload_3
      21: invokeinterface #9,  1            // InterfaceMethod java/util/Iterator.hasNext:()Z
      26: ifeq          78
      29: aload_3
      30: invokeinterface #10,  1           // InterfaceMethod java/util/Iterator.next:()Ljava/lang/Object;
      35: checkcast     #11                 // class java/io/Writer
      38: astore        4
      40: aload         4
      42: ifnull        72
      45: aload         4
      47: invokevirtual #22                 // Method java/io/Writer.close:()V
      50: goto          72
      53: astore        5
      55: aload_1
      56: new           #14                 // class org/apache/commons/io/IOIndexedException
      59: dup
      60: iload_2
      61: aload         5
      63: invokespecial #15                 // Method org/apache/commons/io/IOIndexedException."<init>":(ILjava/lang/Throwable;)V
      66: invokeinterface #16,  2           // InterfaceMethod java/util/List.add:(Ljava/lang/Object;)Z
      71: pop
      72: iinc          2, 1
      75: goto          20
      78: aload_1
      79: invokeinterface #17,  1           // InterfaceMethod java/util/List.isEmpty:()Z
      84: ifne          96
      87: new           #18                 // class org/apache/commons/io/IOExceptionList
      90: dup
      91: aload_1
      92: invokespecial #19                 // Method org/apache/commons/io/IOExceptionList."<init>":(Ljava/util/List;)V
      95: athrow
      96: return
    Exception table:
       from    to  target type
          45    50    53   Class java/io/IOException

  public void flush() throws java.io.IOException;
    Code:
       0: new           #6                  // class java/util/ArrayList
       3: dup
       4: invokespecial #7                  // Method java/util/ArrayList."<init>":()V
       7: astore_1
       8: iconst_0
       9: istore_2
      10: aload_0
      11: getfield      #4                  // Field writers:Ljava/util/Collection;
      14: invokeinterface #8,  1            // InterfaceMethod java/util/Collection.iterator:()Ljava/util/Iterator;
      19: astore_3
      20: aload_3
      21: invokeinterface #9,  1            // InterfaceMethod java/util/Iterator.hasNext:()Z
      26: ifeq          78
      29: aload_3
      30: invokeinterface #10,  1           // InterfaceMethod java/util/Iterator.next:()Ljava/lang/Object;
      35: checkcast     #11                 // class java/io/Writer
      38: astore        4
      40: aload         4
      42: ifnull        72
      45: aload         4
      47: invokevirtual #23                 // Method java/io/Writer.flush:()V
      50: goto          72
      53: astore        5
      55: aload_1
      56: new           #14                 // class org/apache/commons/io/IOIndexedException
      59: dup
      60: iload_2
      61: aload         5
      63: invokespecial #15                 // Method org/apache/commons/io/IOIndexedException."<init>":(ILjava/lang/Throwable;)V
      66: invokeinterface #16,  2           // InterfaceMethod java/util/List.add:(Ljava/lang/Object;)Z
      71: pop
      72: iinc          2, 1
      75: goto          20
      78: aload_1
      79: invokeinterface #17,  1           // InterfaceMethod java/util/List.isEmpty:()Z
      84: ifne          96
      87: new           #18                 // class org/apache/commons/io/IOExceptionList
      90: dup
      91: aload_1
      92: invokespecial #19                 // Method org/apache/commons/io/IOExceptionList."<init>":(Ljava/util/List;)V
      95: athrow
      96: return
    Exception table:
       from    to  target type
          45    50    53   Class java/io/IOException

  public void write(char[], int, int) throws java.io.IOException;
    Code:
       0: new           #6                  // class java/util/ArrayList
       3: dup
       4: invokespecial #7                  // Method java/util/ArrayList."<init>":()V
       7: astore        4
       9: iconst_0
      10: istore        5
      12: aload_0
      13: getfield      #4                  // Field writers:Ljava/util/Collection;
      16: invokeinterface #8,  1            // InterfaceMethod java/util/Collection.iterator:()Ljava/util/Iterator;
      21: astore        6
      23: aload         6
      25: invokeinterface #9,  1            // InterfaceMethod java/util/Iterator.hasNext:()Z
      30: ifeq          88
      33: aload         6
      35: invokeinterface #10,  1           // InterfaceMethod java/util/Iterator.next:()Ljava/lang/Object;
      40: checkcast     #11                 // class java/io/Writer
      43: astore        7
      45: aload         7
      47: ifnull        82
      50: aload         7
      52: aload_1
      53: iload_2
      54: iload_3
      55: invokevirtual #24                 // Method java/io/Writer.write:([CII)V
      58: goto          82
      61: astore        8
      63: aload         4
      65: new           #14                 // class org/apache/commons/io/IOIndexedException
      68: dup
      69: iload         5
      71: aload         8
      73: invokespecial #15                 // Method org/apache/commons/io/IOIndexedException."<init>":(ILjava/lang/Throwable;)V
      76: invokeinterface #16,  2           // InterfaceMethod java/util/List.add:(Ljava/lang/Object;)Z
      81: pop
      82: iinc          5, 1
      85: goto          23
      88: aload         4
      90: invokeinterface #17,  1           // InterfaceMethod java/util/List.isEmpty:()Z
      95: ifne          108
      98: new           #18                 // class org/apache/commons/io/IOExceptionList
     101: dup
     102: aload         4
     104: invokespecial #19                 // Method org/apache/commons/io/IOExceptionList."<init>":(Ljava/util/List;)V
     107: athrow
     108: return
    Exception table:
       from    to  target type
          50    58    61   Class java/io/IOException

  public void write(char[]) throws java.io.IOException;
    Code:
       0: new           #6                  // class java/util/ArrayList
       3: dup
       4: invokespecial #7                  // Method java/util/ArrayList."<init>":()V
       7: astore_2
       8: iconst_0
       9: istore_3
      10: aload_0
      11: getfield      #4                  // Field writers:Ljava/util/Collection;
      14: invokeinterface #8,  1            // InterfaceMethod java/util/Collection.iterator:()Ljava/util/Iterator;
      19: astore        4
      21: aload         4
      23: invokeinterface #9,  1            // InterfaceMethod java/util/Iterator.hasNext:()Z
      28: ifeq          82
      31: aload         4
      33: invokeinterface #10,  1           // InterfaceMethod java/util/Iterator.next:()Ljava/lang/Object;
      38: checkcast     #11                 // class java/io/Writer
      41: astore        5
      43: aload         5
      45: ifnull        76
      48: aload         5
      50: aload_1
      51: invokevirtual #25                 // Method java/io/Writer.write:([C)V
      54: goto          76
      57: astore        6
      59: aload_2
      60: new           #14                 // class org/apache/commons/io/IOIndexedException
      63: dup
      64: iload_3
      65: aload         6
      67: invokespecial #15                 // Method org/apache/commons/io/IOIndexedException."<init>":(ILjava/lang/Throwable;)V
      70: invokeinterface #16,  2           // InterfaceMethod java/util/List.add:(Ljava/lang/Object;)Z
      75: pop
      76: iinc          3, 1
      79: goto          21
      82: aload_2
      83: invokeinterface #17,  1           // InterfaceMethod java/util/List.isEmpty:()Z
      88: ifne          100
      91: new           #18                 // class org/apache/commons/io/IOExceptionList
      94: dup
      95: aload_2
      96: invokespecial #19                 // Method org/apache/commons/io/IOExceptionList."<init>":(Ljava/util/List;)V
      99: athrow
     100: return
    Exception table:
       from    to  target type
          48    54    57   Class java/io/IOException

  public void write(int) throws java.io.IOException;
    Code:
       0: new           #6                  // class java/util/ArrayList
       3: dup
       4: invokespecial #7                  // Method java/util/ArrayList."<init>":()V
       7: astore_2
       8: iconst_0
       9: istore_3
      10: aload_0
      11: getfield      #4                  // Field writers:Ljava/util/Collection;
      14: invokeinterface #8,  1            // InterfaceMethod java/util/Collection.iterator:()Ljava/util/Iterator;
      19: astore        4
      21: aload         4
      23: invokeinterface #9,  1            // InterfaceMethod java/util/Iterator.hasNext:()Z
      28: ifeq          82
      31: aload         4
      33: invokeinterface #10,  1           // InterfaceMethod java/util/Iterator.next:()Ljava/lang/Object;
      38: checkcast     #11                 // class java/io/Writer
      41: astore        5
      43: aload         5
      45: ifnull        76
      48: aload         5
      50: iload_1
      51: invokevirtual #26                 // Method java/io/Writer.write:(I)V
      54: goto          76
      57: astore        6
      59: aload_2
      60: new           #14                 // class org/apache/commons/io/IOIndexedException
      63: dup
      64: iload_3
      65: aload         6
      67: invokespecial #15                 // Method org/apache/commons/io/IOIndexedException."<init>":(ILjava/lang/Throwable;)V
      70: invokeinterface #16,  2           // InterfaceMethod java/util/List.add:(Ljava/lang/Object;)Z
      75: pop
      76: iinc          3, 1
      79: goto          21
      82: aload_2
      83: invokeinterface #17,  1           // InterfaceMethod java/util/List.isEmpty:()Z
      88: ifne          100
      91: new           #18                 // class org/apache/commons/io/IOExceptionList
      94: dup
      95: aload_2
      96: invokespecial #19                 // Method org/apache/commons/io/IOExceptionList."<init>":(Ljava/util/List;)V
      99: athrow
     100: return
    Exception table:
       from    to  target type
          48    54    57   Class java/io/IOException

  public void write(java.lang.String) throws java.io.IOException;
    Code:
       0: new           #6                  // class java/util/ArrayList
       3: dup
       4: invokespecial #7                  // Method java/util/ArrayList."<init>":()V
       7: astore_2
       8: iconst_0
       9: istore_3
      10: aload_0
      11: getfield      #4                  // Field writers:Ljava/util/Collection;
      14: invokeinterface #8,  1            // InterfaceMethod java/util/Collection.iterator:()Ljava/util/Iterator;
      19: astore        4
      21: aload         4
      23: invokeinterface #9,  1            // InterfaceMethod java/util/Iterator.hasNext:()Z
      28: ifeq          82
      31: aload         4
      33: invokeinterface #10,  1           // InterfaceMethod java/util/Iterator.next:()Ljava/lang/Object;
      38: checkcast     #11                 // class java/io/Writer
      41: astore        5
      43: aload         5
      45: ifnull        76
      48: aload         5
      50: aload_1
      51: invokevirtual #27                 // Method java/io/Writer.write:(Ljava/lang/String;)V
      54: goto          76
      57: astore        6
      59: aload_2
      60: new           #14                 // class org/apache/commons/io/IOIndexedException
      63: dup
      64: iload_3
      65: aload         6
      67: invokespecial #15                 // Method org/apache/commons/io/IOIndexedException."<init>":(ILjava/lang/Throwable;)V
      70: invokeinterface #16,  2           // InterfaceMethod java/util/List.add:(Ljava/lang/Object;)Z
      75: pop
      76: iinc          3, 1
      79: goto          21
      82: aload_2
      83: invokeinterface #17,  1           // InterfaceMethod java/util/List.isEmpty:()Z
      88: ifne          100
      91: new           #18                 // class org/apache/commons/io/IOExceptionList
      94: dup
      95: aload_2
      96: invokespecial #19                 // Method org/apache/commons/io/IOExceptionList."<init>":(Ljava/util/List;)V
      99: athrow
     100: return
    Exception table:
       from    to  target type
          48    54    57   Class java/io/IOException

  public void write(java.lang.String, int, int) throws java.io.IOException;
    Code:
       0: new           #6                  // class java/util/ArrayList
       3: dup
       4: invokespecial #7                  // Method java/util/ArrayList."<init>":()V
       7: astore        4
       9: iconst_0
      10: istore        5
      12: aload_0
      13: getfield      #4                  // Field writers:Ljava/util/Collection;
      16: invokeinterface #8,  1            // InterfaceMethod java/util/Collection.iterator:()Ljava/util/Iterator;
      21: astore        6
      23: aload         6
      25: invokeinterface #9,  1            // InterfaceMethod java/util/Iterator.hasNext:()Z
      30: ifeq          88
      33: aload         6
      35: invokeinterface #10,  1           // InterfaceMethod java/util/Iterator.next:()Ljava/lang/Object;
      40: checkcast     #11                 // class java/io/Writer
      43: astore        7
      45: aload         7
      47: ifnull        82
      50: aload         7
      52: aload_1
      53: iload_2
      54: iload_3
      55: invokevirtual #28                 // Method java/io/Writer.write:(Ljava/lang/String;II)V
      58: goto          82
      61: astore        8
      63: aload         4
      65: new           #14                 // class org/apache/commons/io/IOIndexedException
      68: dup
      69: iload         5
      71: aload         8
      73: invokespecial #15                 // Method org/apache/commons/io/IOIndexedException."<init>":(ILjava/lang/Throwable;)V
      76: invokeinterface #16,  2           // InterfaceMethod java/util/List.add:(Ljava/lang/Object;)Z
      81: pop
      82: iinc          5, 1
      85: goto          23
      88: aload         4
      90: invokeinterface #17,  1           // InterfaceMethod java/util/List.isEmpty:()Z
      95: ifne          108
      98: new           #18                 // class org/apache/commons/io/IOExceptionList
     101: dup
     102: aload         4
     104: invokespecial #19                 // Method org/apache/commons/io/IOExceptionList."<init>":(Ljava/util/List;)V
     107: athrow
     108: return
    Exception table:
       from    to  target type
          50    58    61   Class java/io/IOException

  public java.lang.Appendable append(char) throws java.io.IOException;
    Code:
       0: aload_0
       1: iload_1
       2: invokevirtual #29                 // Method append:(C)Ljava/io/Writer;
       5: areturn

  public java.lang.Appendable append(java.lang.CharSequence, int, int) throws java.io.IOException;
    Code:
       0: aload_0
       1: aload_1
       2: iload_2
       3: iload_3
       4: invokevirtual #30                 // Method append:(Ljava/lang/CharSequence;II)Ljava/io/Writer;
       7: areturn

  public java.lang.Appendable append(java.lang.CharSequence) throws java.io.IOException;
    Code:
       0: aload_0
       1: aload_1
       2: invokevirtual #31                 // Method append:(Ljava/lang/CharSequence;)Ljava/io/Writer;
       5: areturn
}
