public class org.bouncycastle.asn1.crmf.POPOPrivKey extends org.bouncycastle.asn1.ASN1Object implements org.bouncycastle.asn1.ASN1Choice {
  public static final int thisMessage;

  public static final int subsequentMessage;

  public static final int dhMAC;

  public static final int agreeMAC;

  public static final int encryptedKey;

  private int tagNo;

  private org.bouncycastle.asn1.ASN1Encodable obj;

  private org.bouncycastle.asn1.crmf.POPOPrivKey(org.bouncycastle.asn1.ASN1TaggedObject);
    Code:
       0: aload_0
       1: invokespecial #86                 // Method org/bouncycastle/asn1/ASN1Object."<init>":()V
       4: aload_0
       5: aload_1
       6: invokevirtual #87                 // Method org/bouncycastle/asn1/ASN1TaggedObject.getTagNo:()I
       9: putfield      #81                 // Field tagNo:I
      12: aload_0
      13: getfield      #81                 // Field tagNo:I
      16: tableswitch   { // 0 to 4
                     0: 52
                     1: 64
                     2: 82
                     3: 94
                     4: 106
               default: 118
          }
      52: aload_0
      53: aload_1
      54: iconst_0
      55: invokestatic  #90                 // Method org/bouncycastle/asn1/DERBitString.getInstance:(Lorg/bouncycastle/asn1/ASN1TaggedObject;Z)Lorg/bouncycastle/asn1/DERBitString;
      58: putfield      #82                 // Field obj:Lorg/bouncycastle/asn1/ASN1Encodable;
      61: goto          128
      64: aload_0
      65: aload_1
      66: iconst_0
      67: invokestatic  #85                 // Method org/bouncycastle/asn1/ASN1Integer.getInstance:(Lorg/bouncycastle/asn1/ASN1TaggedObject;Z)Lorg/bouncycastle/asn1/ASN1Integer;
      70: invokevirtual #84                 // Method org/bouncycastle/asn1/ASN1Integer.intValueExact:()I
      73: invokestatic  #96                 // Method org/bouncycastle/asn1/crmf/SubsequentMessage.valueOf:(I)Lorg/bouncycastle/asn1/crmf/SubsequentMessage;
      76: putfield      #82                 // Field obj:Lorg/bouncycastle/asn1/ASN1Encodable;
      79: goto          128
      82: aload_0
      83: aload_1
      84: iconst_0
      85: invokestatic  #90                 // Method org/bouncycastle/asn1/DERBitString.getInstance:(Lorg/bouncycastle/asn1/ASN1TaggedObject;Z)Lorg/bouncycastle/asn1/DERBitString;
      88: putfield      #82                 // Field obj:Lorg/bouncycastle/asn1/ASN1Encodable;
      91: goto          128
      94: aload_0
      95: aload_1
      96: iconst_0
      97: invokestatic  #93                 // Method org/bouncycastle/asn1/crmf/PKMACValue.getInstance:(Lorg/bouncycastle/asn1/ASN1TaggedObject;Z)Lorg/bouncycastle/asn1/crmf/PKMACValue;
     100: putfield      #82                 // Field obj:Lorg/bouncycastle/asn1/ASN1Encodable;
     103: goto          128
     106: aload_0
     107: aload_1
     108: iconst_0
     109: invokestatic  #92                 // Method org/bouncycastle/asn1/cms/EnvelopedData.getInstance:(Lorg/bouncycastle/asn1/ASN1TaggedObject;Z)Lorg/bouncycastle/asn1/cms/EnvelopedData;
     112: putfield      #82                 // Field obj:Lorg/bouncycastle/asn1/ASN1Encodable;
     115: goto          128
     118: new           #37                 // class java/lang/IllegalArgumentException
     121: dup
     122: ldc           #1                  // String unknown tag in POPOPrivKey
     124: invokespecial #83                 // Method java/lang/IllegalArgumentException."<init>":(Ljava/lang/String;)V
     127: athrow
     128: return

  public static org.bouncycastle.asn1.crmf.POPOPrivKey getInstance(java.lang.Object);
    Code:
       0: aload_0
       1: instanceof    #46                 // class org/bouncycastle/asn1/crmf/POPOPrivKey
       4: ifeq          12
       7: aload_0
       8: checkcast     #46                 // class org/bouncycastle/asn1/crmf/POPOPrivKey
      11: areturn
      12: aload_0
      13: ifnull        28
      16: new           #46                 // class org/bouncycastle/asn1/crmf/POPOPrivKey
      19: dup
      20: aload_0
      21: invokestatic  #88                 // Method org/bouncycastle/asn1/ASN1TaggedObject.getInstance:(Ljava/lang/Object;)Lorg/bouncycastle/asn1/ASN1TaggedObject;
      24: invokespecial #94                 // Method "<init>":(Lorg/bouncycastle/asn1/ASN1TaggedObject;)V
      27: areturn
      28: aconst_null
      29: areturn

  public static org.bouncycastle.asn1.crmf.POPOPrivKey getInstance(org.bouncycastle.asn1.ASN1TaggedObject, boolean);
    Code:
       0: aload_0
       1: iload_1
       2: invokestatic  #89                 // Method org/bouncycastle/asn1/ASN1TaggedObject.getInstance:(Lorg/bouncycastle/asn1/ASN1TaggedObject;Z)Lorg/bouncycastle/asn1/ASN1TaggedObject;
       5: invokestatic  #95                 // Method getInstance:(Ljava/lang/Object;)Lorg/bouncycastle/asn1/crmf/POPOPrivKey;
       8: areturn

  public org.bouncycastle.asn1.crmf.POPOPrivKey(org.bouncycastle.asn1.crmf.PKMACValue);
    Code:
       0: aload_0
       1: invokespecial #86                 // Method org/bouncycastle/asn1/ASN1Object."<init>":()V
       4: aload_0
       5: iconst_3
       6: putfield      #81                 // Field tagNo:I
       9: aload_0
      10: aload_1
      11: putfield      #82                 // Field obj:Lorg/bouncycastle/asn1/ASN1Encodable;
      14: return

  public org.bouncycastle.asn1.crmf.POPOPrivKey(org.bouncycastle.asn1.crmf.SubsequentMessage);
    Code:
       0: aload_0
       1: invokespecial #86                 // Method org/bouncycastle/asn1/ASN1Object."<init>":()V
       4: aload_0
       5: iconst_1
       6: putfield      #81                 // Field tagNo:I
       9: aload_0
      10: aload_1
      11: putfield      #82                 // Field obj:Lorg/bouncycastle/asn1/ASN1Encodable;
      14: return

  public int getType();
    Code:
       0: aload_0
       1: getfield      #81                 // Field tagNo:I
       4: ireturn

  public org.bouncycastle.asn1.ASN1Encodable getValue();
    Code:
       0: aload_0
       1: getfield      #82                 // Field obj:Lorg/bouncycastle/asn1/ASN1Encodable;
       4: areturn

  public org.bouncycastle.asn1.ASN1Primitive toASN1Primitive();
    Code:
       0: new           #43                 // class org/bouncycastle/asn1/DERTaggedObject
       3: dup
       4: iconst_0
       5: aload_0
       6: getfield      #81                 // Field tagNo:I
       9: aload_0
      10: getfield      #82                 // Field obj:Lorg/bouncycastle/asn1/ASN1Encodable;
      13: invokespecial #91                 // Method org/bouncycastle/asn1/DERTaggedObject."<init>":(ZILorg/bouncycastle/asn1/ASN1Encodable;)V
      16: areturn
}
