Compiled from "ConsumerIndex.java"
public class io.openmessaging.joyqueue.consumer.ConsumerIndex {
  private long index;

  private long leftIndex;

  private long rightIndex;

  public io.openmessaging.joyqueue.consumer.ConsumerIndex(long, long, long);
    Code:
       0: aload_0
       1: invokespecial #1                  // Method java/lang/Object."<init>":()V
       4: aload_0
       5: lload_1
       6: putfield      #2                  // Field index:J
       9: aload_0
      10: lload_3
      11: putfield      #3                  // Field leftIndex:J
      14: aload_0
      15: lload         5
      17: putfield      #4                  // Field rightIndex:J
      20: return

  public long getIndex();
    Code:
       0: aload_0
       1: getfield      #2                  // Field index:J
       4: lreturn

  public void setIndex(long);
    Code:
       0: aload_0
       1: lload_1
       2: putfield      #2                  // Field index:J
       5: return

  public long getLeftIndex();
    Code:
       0: aload_0
       1: getfield      #3                  // Field leftIndex:J
       4: lreturn

  public void setLeftIndex(long);
    Code:
       0: aload_0
       1: lload_1
       2: putfield      #3                  // Field leftIndex:J
       5: return

  public long getRightIndex();
    Code:
       0: aload_0
       1: getfield      #4                  // Field rightIndex:J
       4: lreturn

  public void setRightIndex(long);
    Code:
       0: aload_0
       1: lload_1
       2: putfield      #4                  // Field rightIndex:J
       5: return
}
