Compiled from "LiteralNode.java"
public class org.hibernate.hql.internal.ast.tree.LiteralNode extends org.hibernate.hql.internal.ast.tree.AbstractSelectExpression implements org.hibernate.hql.internal.antlr.HqlSqlTokenTypes,org.hibernate.hql.internal.ast.tree.ExpectedTypeAwareNode {
  private org.hibernate.type.Type expectedType;

  public org.hibernate.hql.internal.ast.tree.LiteralNode();
    Code:
       0: aload_0
       1: invokespecial #1                  // Method org/hibernate/hql/internal/ast/tree/AbstractSelectExpression."<init>":()V
       4: return

  public void setScalarColumnText(int) throws antlr.SemanticException;
    Code:
       0: aload_0
       1: iload_1
       2: invokestatic  #2                  // Method org/hibernate/hql/internal/ast/util/ColumnHelper.generateSingleScalarColumn:(Lorg/hibernate/hql/internal/ast/tree/HqlSqlWalkerNode;I)V
       5: return

  public org.hibernate.type.Type getDataType();
    Code:
       0: aload_0
       1: invokevirtual #3                  // Method getExpectedType:()Lorg/hibernate/type/Type;
       4: ifnull        12
       7: aload_0
       8: invokevirtual #3                  // Method getExpectedType:()Lorg/hibernate/type/Type;
      11: areturn
      12: aload_0
      13: invokevirtual #4                  // Method getType:()I
      16: lookupswitch  { // 9
                    20: 128
                    49: 128
                    98: 112
                    99: 104
                   100: 108
                   101: 116
                   102: 120
                   126: 124
                   129: 100
               default: 132
          }
     100: getstatic     #5                  // Field org/hibernate/type/StandardBasicTypes.INTEGER:Lorg/hibernate/type/IntegerType;
     103: areturn
     104: getstatic     #6                  // Field org/hibernate/type/StandardBasicTypes.FLOAT:Lorg/hibernate/type/FloatType;
     107: areturn
     108: getstatic     #7                  // Field org/hibernate/type/StandardBasicTypes.LONG:Lorg/hibernate/type/LongType;
     111: areturn
     112: getstatic     #8                  // Field org/hibernate/type/StandardBasicTypes.DOUBLE:Lorg/hibernate/type/DoubleType;
     115: areturn
     116: getstatic     #9                  // Field org/hibernate/type/StandardBasicTypes.BIG_INTEGER:Lorg/hibernate/type/BigIntegerType;
     119: areturn
     120: getstatic     #10                 // Field org/hibernate/type/StandardBasicTypes.BIG_DECIMAL:Lorg/hibernate/type/BigDecimalType;
     123: areturn
     124: getstatic     #11                 // Field org/hibernate/type/StandardBasicTypes.STRING:Lorg/hibernate/type/StringType;
     127: areturn
     128: getstatic     #12                 // Field org/hibernate/type/StandardBasicTypes.BOOLEAN:Lorg/hibernate/type/BooleanType;
     131: areturn
     132: aconst_null
     133: areturn

  public java.lang.Object getLiteralValue();
    Code:
       0: aload_0
       1: invokevirtual #13                 // Method getText:()Ljava/lang/String;
       4: astore_1
       5: aload_0
       6: invokevirtual #4                  // Method getType:()I
       9: bipush        126
      11: if_icmpne     26
      14: aload_1
      15: iconst_1
      16: aload_1
      17: invokevirtual #15                 // Method java/lang/String.length:()I
      20: iconst_1
      21: isub
      22: invokevirtual #16                 // Method java/lang/String.substring:(II)Ljava/lang/String;
      25: astore_1
      26: aload_0
      27: invokevirtual #17                 // Method getDataType:()Lorg/hibernate/type/Type;
      30: astore_2
      31: aload_2
      32: ifnonnull     37
      35: aload_1
      36: areturn
      37: aload_2
      38: checkcast     #18                 // class org/hibernate/type/SingleColumnType
      41: aload_1
      42: invokeinterface #19,  2           // InterfaceMethod org/hibernate/type/SingleColumnType.fromStringValue:(Ljava/lang/String;)Ljava/lang/Object;
      47: areturn

  public void setExpectedType(org.hibernate.type.Type);
    Code:
       0: aload_0
       1: getfield      #20                 // Field expectedType:Lorg/hibernate/type/Type;
       4: ifnull        8
       7: return
       8: ldc           #21                 // class org/hibernate/type/descriptor/converter/AttributeConverterTypeAdapter
      10: aload_1
      11: invokevirtual #22                 // Method java/lang/Class.isInstance:(Ljava/lang/Object;)Z
      14: ifeq          40
      17: aload_1
      18: checkcast     #21                 // class org/hibernate/type/descriptor/converter/AttributeConverterTypeAdapter
      21: astore_2
      22: aload_0
      23: aload_0
      24: aload_2
      25: aload_0
      26: invokevirtual #23                 // Method getLiteralValue:()Ljava/lang/Object;
      29: invokevirtual #24                 // Method determineConvertedValue:(Lorg/hibernate/type/descriptor/converter/AttributeConverterTypeAdapter;Ljava/lang/Object;)Ljava/lang/String;
      32: invokevirtual #25                 // Method setText:(Ljava/lang/String;)V
      35: aload_0
      36: aload_1
      37: putfield      #20                 // Field expectedType:Lorg/hibernate/type/Type;
      40: return

  protected java.lang.String determineConvertedValue(org.hibernate.type.descriptor.converter.AttributeConverterTypeAdapter, java.lang.Object);
    Code:
       0: aload_0
       1: invokevirtual #17                 // Method getDataType:()Lorg/hibernate/type/Type;
       4: invokeinterface #26,  1           // InterfaceMethod org/hibernate/type/Type.getReturnedClass:()Ljava/lang/Class;
       9: aload_1
      10: invokevirtual #27                 // Method org/hibernate/type/descriptor/converter/AttributeConverterTypeAdapter.getModelType:()Ljava/lang/Class;
      13: invokevirtual #28                 // Method java/lang/Object.equals:(Ljava/lang/Object;)Z
      16: ifeq          82
      19: aload_1
      20: invokevirtual #29                 // Method org/hibernate/type/descriptor/converter/AttributeConverterTypeAdapter.getAttributeConverter:()Ljavax/persistence/AttributeConverter;
      23: astore_3
      24: aload_3
      25: aload_0
      26: invokevirtual #23                 // Method getLiteralValue:()Ljava/lang/Object;
      29: invokeinterface #30,  2           // InterfaceMethod javax/persistence/AttributeConverter.convertToDatabaseColumn:(Ljava/lang/Object;)Ljava/lang/Object;
      34: astore        4
      36: aload_0
      37: aload_1
      38: invokevirtual #31                 // Method org/hibernate/type/descriptor/converter/AttributeConverterTypeAdapter.sqlType:()I
      41: invokespecial #32                 // Method isCharacterData:(I)Z
      44: ifeq          76
      47: new           #33                 // class java/lang/StringBuilder
      50: dup
      51: invokespecial #34                 // Method java/lang/StringBuilder."<init>":()V
      54: ldc           #35                 // String \'
      56: invokevirtual #36                 // Method java/lang/StringBuilder.append:(Ljava/lang/String;)Ljava/lang/StringBuilder;
      59: aload         4
      61: invokevirtual #37                 // Method java/lang/Object.toString:()Ljava/lang/String;
      64: invokevirtual #36                 // Method java/lang/StringBuilder.append:(Ljava/lang/String;)Ljava/lang/StringBuilder;
      67: ldc           #35                 // String \'
      69: invokevirtual #36                 // Method java/lang/StringBuilder.append:(Ljava/lang/String;)Ljava/lang/StringBuilder;
      72: invokevirtual #38                 // Method java/lang/StringBuilder.toString:()Ljava/lang/String;
      75: areturn
      76: aload         4
      78: invokevirtual #37                 // Method java/lang/Object.toString:()Ljava/lang/String;
      81: areturn
      82: new           #39                 // class org/hibernate/QueryException
      85: dup
      86: getstatic     #40                 // Field java/util/Locale.ROOT:Ljava/util/Locale;
      89: ldc           #41                 // String AttributeConverter domain-model attribute type [%s] did not match query literal type [%s]
      91: iconst_2
      92: anewarray     #42                 // class java/lang/Object
      95: dup
      96: iconst_0
      97: aload_1
      98: invokevirtual #27                 // Method org/hibernate/type/descriptor/converter/AttributeConverterTypeAdapter.getModelType:()Ljava/lang/Class;
     101: invokevirtual #43                 // Method java/lang/Class.getName:()Ljava/lang/String;
     104: aastore
     105: dup
     106: iconst_1
     107: aload_0
     108: invokevirtual #17                 // Method getDataType:()Lorg/hibernate/type/Type;
     111: invokeinterface #26,  1           // InterfaceMethod org/hibernate/type/Type.getReturnedClass:()Ljava/lang/Class;
     116: invokevirtual #43                 // Method java/lang/Class.getName:()Ljava/lang/String;
     119: aastore
     120: invokestatic  #44                 // Method java/lang/String.format:(Ljava/util/Locale;Ljava/lang/String;[Ljava/lang/Object;)Ljava/lang/String;
     123: invokespecial #45                 // Method org/hibernate/QueryException."<init>":(Ljava/lang/String;)V
     126: athrow

  private boolean isCharacterData(int);
    Code:
       0: bipush        12
       2: iload_1
       3: if_icmpeq     23
       6: iconst_1
       7: iload_1
       8: if_icmpeq     23
      11: bipush        -9
      13: iload_1
      14: if_icmpeq     23
      17: bipush        -15
      19: iload_1
      20: if_icmpne     27
      23: iconst_1
      24: goto          28
      27: iconst_0
      28: ireturn

  public org.hibernate.type.Type getExpectedType();
    Code:
       0: aload_0
       1: getfield      #20                 // Field expectedType:Lorg/hibernate/type/Type;
       4: areturn
}
