public class org.bouncycastle.tsp.TimeStampResponseGenerator {
  int status;

  org.bouncycastle.asn1.ASN1EncodableVector statusStrings;

  int failInfo;

  private org.bouncycastle.tsp.TimeStampTokenGenerator tokenGenerator;

  private java.util.Set acceptedAlgorithms;

  private java.util.Set acceptedPolicies;

  private java.util.Set acceptedExtensions;

  public org.bouncycastle.tsp.TimeStampResponseGenerator(org.bouncycastle.tsp.TimeStampTokenGenerator, java.util.Set);
    Code:
       0: aload_0
       1: aload_1
       2: aload_2
       3: aconst_null
       4: aconst_null
       5: invokespecial #212                // Method "<init>":(Lorg/bouncycastle/tsp/TimeStampTokenGenerator;Ljava/util/Set;Ljava/util/Set;Ljava/util/Set;)V
       8: return

  public org.bouncycastle.tsp.TimeStampResponseGenerator(org.bouncycastle.tsp.TimeStampTokenGenerator, java.util.Set, java.util.Set);
    Code:
       0: aload_0
       1: aload_1
       2: aload_2
       3: aload_3
       4: aconst_null
       5: invokespecial #212                // Method "<init>":(Lorg/bouncycastle/tsp/TimeStampTokenGenerator;Ljava/util/Set;Ljava/util/Set;Ljava/util/Set;)V
       8: return

  public org.bouncycastle.tsp.TimeStampResponseGenerator(org.bouncycastle.tsp.TimeStampTokenGenerator, java.util.Set, java.util.Set, java.util.Set);
    Code:
       0: aload_0
       1: invokespecial #183                // Method java/lang/Object."<init>":()V
       4: aload_0
       5: aload_1
       6: putfield      #181                // Field tokenGenerator:Lorg/bouncycastle/tsp/TimeStampTokenGenerator;
       9: aload_0
      10: aload_0
      11: aload_2
      12: invokespecial #209                // Method convert:(Ljava/util/Set;)Ljava/util/Set;
      15: putfield      #177                // Field acceptedAlgorithms:Ljava/util/Set;
      18: aload_0
      19: aload_0
      20: aload_3
      21: invokespecial #209                // Method convert:(Ljava/util/Set;)Ljava/util/Set;
      24: putfield      #179                // Field acceptedPolicies:Ljava/util/Set;
      27: aload_0
      28: aload_0
      29: aload         4
      31: invokespecial #209                // Method convert:(Ljava/util/Set;)Ljava/util/Set;
      34: putfield      #178                // Field acceptedExtensions:Ljava/util/Set;
      37: aload_0
      38: new           #79                 // class org/bouncycastle/asn1/ASN1EncodableVector
      41: dup
      42: invokespecial #186                // Method org/bouncycastle/asn1/ASN1EncodableVector."<init>":()V
      45: putfield      #180                // Field statusStrings:Lorg/bouncycastle/asn1/ASN1EncodableVector;
      48: return

  private void addStatusString(java.lang.String);
    Code:
       0: aload_0
       1: getfield      #180                // Field statusStrings:Lorg/bouncycastle/asn1/ASN1EncodableVector;
       4: new           #83                 // class org/bouncycastle/asn1/DERUTF8String
       7: dup
       8: aload_1
       9: invokespecial #191                // Method org/bouncycastle/asn1/DERUTF8String."<init>":(Ljava/lang/String;)V
      12: invokevirtual #187                // Method org/bouncycastle/asn1/ASN1EncodableVector.add:(Lorg/bouncycastle/asn1/ASN1Encodable;)V
      15: return

  private void setFailInfoField(int);
    Code:
       0: aload_0
       1: aload_0
       2: getfield      #175                // Field failInfo:I
       5: iload_1
       6: ior
       7: putfield      #175                // Field failInfo:I
      10: return

  private org.bouncycastle.asn1.cmp.PKIStatusInfo getPKIStatusInfo();
    Code:
       0: new           #79                 // class org/bouncycastle/asn1/ASN1EncodableVector
       3: dup
       4: invokespecial #186                // Method org/bouncycastle/asn1/ASN1EncodableVector."<init>":()V
       7: astore_1
       8: aload_1
       9: new           #80                 // class org/bouncycastle/asn1/ASN1Integer
      12: dup
      13: aload_0
      14: getfield      #176                // Field status:I
      17: i2l
      18: invokespecial #188                // Method org/bouncycastle/asn1/ASN1Integer."<init>":(J)V
      21: invokevirtual #187                // Method org/bouncycastle/asn1/ASN1EncodableVector.add:(Lorg/bouncycastle/asn1/ASN1Encodable;)V
      24: aload_0
      25: getfield      #180                // Field statusStrings:Lorg/bouncycastle/asn1/ASN1EncodableVector;
      28: invokevirtual #185                // Method org/bouncycastle/asn1/ASN1EncodableVector.size:()I
      31: ifle          52
      34: aload_1
      35: new           #82                 // class org/bouncycastle/asn1/DERSequence
      38: dup
      39: aload_0
      40: getfield      #180                // Field statusStrings:Lorg/bouncycastle/asn1/ASN1EncodableVector;
      43: invokespecial #190                // Method org/bouncycastle/asn1/DERSequence."<init>":(Lorg/bouncycastle/asn1/ASN1EncodableVector;)V
      46: invokestatic  #193                // Method org/bouncycastle/asn1/cmp/PKIFreeText.getInstance:(Ljava/lang/Object;)Lorg/bouncycastle/asn1/cmp/PKIFreeText;
      49: invokevirtual #187                // Method org/bouncycastle/asn1/ASN1EncodableVector.add:(Lorg/bouncycastle/asn1/ASN1Encodable;)V
      52: aload_0
      53: getfield      #175                // Field failInfo:I
      56: ifeq          77
      59: new           #95                 // class org/bouncycastle/tsp/TimeStampResponseGenerator$FailInfo
      62: dup
      63: aload_0
      64: aload_0
      65: getfield      #175                // Field failInfo:I
      68: invokespecial #215                // Method org/bouncycastle/tsp/TimeStampResponseGenerator$FailInfo."<init>":(Lorg/bouncycastle/tsp/TimeStampResponseGenerator;I)V
      71: astore_2
      72: aload_1
      73: aload_2
      74: invokevirtual #187                // Method org/bouncycastle/asn1/ASN1EncodableVector.add:(Lorg/bouncycastle/asn1/ASN1Encodable;)V
      77: new           #82                 // class org/bouncycastle/asn1/DERSequence
      80: dup
      81: aload_1
      82: invokespecial #190                // Method org/bouncycastle/asn1/DERSequence."<init>":(Lorg/bouncycastle/asn1/ASN1EncodableVector;)V
      85: invokestatic  #195                // Method org/bouncycastle/asn1/cmp/PKIStatusInfo.getInstance:(Ljava/lang/Object;)Lorg/bouncycastle/asn1/cmp/PKIStatusInfo;
      88: areturn

  public org.bouncycastle.tsp.TimeStampResponse generate(org.bouncycastle.tsp.TimeStampRequest, java.math.BigInteger, java.util.Date) throws org.bouncycastle.tsp.TSPException;
    Code:
       0: aload_0
       1: aload_1
       2: aload_2
       3: aload_3
       4: ldc           #2                  // String Operation Okay
       6: invokevirtual #213                // Method generateGrantedResponse:(Lorg/bouncycastle/tsp/TimeStampRequest;Ljava/math/BigInteger;Ljava/util/Date;Ljava/lang/String;)Lorg/bouncycastle/tsp/TimeStampResponse;
       9: areturn
      10: astore        4
      12: aload_0
      13: aload         4
      15: invokevirtual #210                // Method generateRejectedResponse:(Ljava/lang/Exception;)Lorg/bouncycastle/tsp/TimeStampResponse;
      18: areturn
    Exception table:
       from    to  target type
           0     9    10   Class java/lang/Exception

  public org.bouncycastle.tsp.TimeStampResponse generateGrantedResponse(org.bouncycastle.tsp.TimeStampRequest, java.math.BigInteger, java.util.Date) throws org.bouncycastle.tsp.TSPException;
    Code:
       0: aload_0
       1: aload_1
       2: aload_2
       3: aload_3
       4: aconst_null
       5: invokevirtual #213                // Method generateGrantedResponse:(Lorg/bouncycastle/tsp/TimeStampRequest;Ljava/math/BigInteger;Ljava/util/Date;Ljava/lang/String;)Lorg/bouncycastle/tsp/TimeStampResponse;
       8: areturn

  public org.bouncycastle.tsp.TimeStampResponse generateGrantedResponse(org.bouncycastle.tsp.TimeStampRequest, java.math.BigInteger, java.util.Date, java.lang.String) throws org.bouncycastle.tsp.TSPException;
    Code:
       0: aload_0
       1: aload_1
       2: aload_2
       3: aload_3
       4: aload         4
       6: aconst_null
       7: invokevirtual #214                // Method generateGrantedResponse:(Lorg/bouncycastle/tsp/TimeStampRequest;Ljava/math/BigInteger;Ljava/util/Date;Ljava/lang/String;Lorg/bouncycastle/asn1/x509/Extensions;)Lorg/bouncycastle/tsp/TimeStampResponse;
      10: areturn

  public org.bouncycastle.tsp.TimeStampResponse generateGrantedResponse(org.bouncycastle.tsp.TimeStampRequest, java.math.BigInteger, java.util.Date, java.lang.String, org.bouncycastle.asn1.x509.Extensions) throws org.bouncycastle.tsp.TSPException;
    Code:
       0: aload_3
       1: ifnonnull     17
       4: new           #91                 // class org/bouncycastle/tsp/TSPValidationException
       7: dup
       8: ldc           #3                  // String The time source is not available.
      10: sipush        512
      13: invokespecial #202                // Method org/bouncycastle/tsp/TSPValidationException."<init>":(Ljava/lang/String;I)V
      16: athrow
      17: aload_1
      18: aload_0
      19: getfield      #177                // Field acceptedAlgorithms:Ljava/util/Set;
      22: aload_0
      23: getfield      #179                // Field acceptedPolicies:Ljava/util/Set;
      26: aload_0
      27: getfield      #178                // Field acceptedExtensions:Ljava/util/Set;
      30: invokevirtual #203                // Method org/bouncycastle/tsp/TimeStampRequest.validate:(Ljava/util/Set;Ljava/util/Set;Ljava/util/Set;)V
      33: aload_0
      34: iconst_0
      35: putfield      #176                // Field status:I
      38: aload_0
      39: new           #79                 // class org/bouncycastle/asn1/ASN1EncodableVector
      42: dup
      43: invokespecial #186                // Method org/bouncycastle/asn1/ASN1EncodableVector."<init>":()V
      46: putfield      #180                // Field statusStrings:Lorg/bouncycastle/asn1/ASN1EncodableVector;
      49: aload         4
      51: ifnull        60
      54: aload_0
      55: aload         4
      57: invokespecial #207                // Method addStatusString:(Ljava/lang/String;)V
      60: aload_0
      61: invokespecial #208                // Method getPKIStatusInfo:()Lorg/bouncycastle/asn1/cmp/PKIStatusInfo;
      64: astore        6
      66: aload_0
      67: getfield      #181                // Field tokenGenerator:Lorg/bouncycastle/tsp/TimeStampTokenGenerator;
      70: aload_1
      71: aload_2
      72: aload_3
      73: aload         5
      75: invokevirtual #217                // Method org/bouncycastle/tsp/TimeStampTokenGenerator.generate:(Lorg/bouncycastle/tsp/TimeStampRequest;Ljava/math/BigInteger;Ljava/util/Date;Lorg/bouncycastle/asn1/x509/Extensions;)Lorg/bouncycastle/tsp/TimeStampToken;
      78: invokevirtual #216                // Method org/bouncycastle/tsp/TimeStampToken.toCMSSignedData:()Lorg/bouncycastle/cms/CMSSignedData;
      81: invokevirtual #198                // Method org/bouncycastle/cms/CMSSignedData.toASN1Structure:()Lorg/bouncycastle/asn1/cms/ContentInfo;
      84: astore        7
      86: goto          108
      89: astore        8
      91: aload         8
      93: athrow
      94: astore        8
      96: new           #90                 // class org/bouncycastle/tsp/TSPException
      99: dup
     100: ldc           #4                  // String Timestamp token received cannot be converted to ContentInfo
     102: aload         8
     104: invokespecial #200                // Method org/bouncycastle/tsp/TSPException."<init>":(Ljava/lang/String;Ljava/lang/Throwable;)V
     107: athrow
     108: new           #93                 // class org/bouncycastle/tsp/TimeStampResponse
     111: dup
     112: new           #84                 // class org/bouncycastle/asn1/DLSequence
     115: dup
     116: iconst_2
     117: anewarray     #78                 // class org/bouncycastle/asn1/ASN1Encodable
     120: dup
     121: iconst_0
     122: aload         6
     124: invokevirtual #194                // Method org/bouncycastle/asn1/cmp/PKIStatusInfo.toASN1Primitive:()Lorg/bouncycastle/asn1/ASN1Primitive;
     127: aastore
     128: dup
     129: iconst_1
     130: aload         7
     132: invokevirtual #196                // Method org/bouncycastle/asn1/cms/ContentInfo.toASN1Primitive:()Lorg/bouncycastle/asn1/ASN1Primitive;
     135: aastore
     136: invokespecial #192                // Method org/bouncycastle/asn1/DLSequence."<init>":([Lorg/bouncycastle/asn1/ASN1Encodable;)V
     139: invokespecial #204                // Method org/bouncycastle/tsp/TimeStampResponse."<init>":(Lorg/bouncycastle/asn1/DLSequence;)V
     142: areturn
     143: astore        8
     145: new           #90                 // class org/bouncycastle/tsp/TSPException
     148: dup
     149: ldc           #5                  // String created badly formatted response!
     151: invokespecial #199                // Method org/bouncycastle/tsp/TSPException."<init>":(Ljava/lang/String;)V
     154: athrow
    Exception table:
       from    to  target type
          66    86    89   Class org/bouncycastle/tsp/TSPException
          66    86    94   Class java/lang/Exception
         108   142   143   Class java/io/IOException

  public org.bouncycastle.tsp.TimeStampResponse generateRejectedResponse(java.lang.Exception) throws org.bouncycastle.tsp.TSPException;
    Code:
       0: aload_1
       1: instanceof    #91                 // class org/bouncycastle/tsp/TSPValidationException
       4: ifeq          24
       7: aload_0
       8: iconst_2
       9: aload_1
      10: checkcast     #91                 // class org/bouncycastle/tsp/TSPValidationException
      13: invokevirtual #201                // Method org/bouncycastle/tsp/TSPValidationException.getFailureCode:()I
      16: aload_1
      17: invokevirtual #182                // Method java/lang/Exception.getMessage:()Ljava/lang/String;
      20: invokevirtual #211                // Method generateFailResponse:(IILjava/lang/String;)Lorg/bouncycastle/tsp/TimeStampResponse;
      23: areturn
      24: aload_0
      25: iconst_2
      26: ldc           #1                  // int 1073741824
      28: aload_1
      29: invokevirtual #182                // Method java/lang/Exception.getMessage:()Ljava/lang/String;
      32: invokevirtual #211                // Method generateFailResponse:(IILjava/lang/String;)Lorg/bouncycastle/tsp/TimeStampResponse;
      35: areturn

  public org.bouncycastle.tsp.TimeStampResponse generateFailResponse(int, int, java.lang.String) throws org.bouncycastle.tsp.TSPException;
    Code:
       0: aload_0
       1: iload_1
       2: putfield      #176                // Field status:I
       5: aload_0
       6: new           #79                 // class org/bouncycastle/asn1/ASN1EncodableVector
       9: dup
      10: invokespecial #186                // Method org/bouncycastle/asn1/ASN1EncodableVector."<init>":()V
      13: putfield      #180                // Field statusStrings:Lorg/bouncycastle/asn1/ASN1EncodableVector;
      16: aload_0
      17: iload_2
      18: invokespecial #206                // Method setFailInfoField:(I)V
      21: aload_3
      22: ifnull        30
      25: aload_0
      26: aload_3
      27: invokespecial #207                // Method addStatusString:(Ljava/lang/String;)V
      30: aload_0
      31: invokespecial #208                // Method getPKIStatusInfo:()Lorg/bouncycastle/asn1/cmp/PKIStatusInfo;
      34: astore        4
      36: new           #88                 // class org/bouncycastle/asn1/tsp/TimeStampResp
      39: dup
      40: aload         4
      42: aconst_null
      43: invokespecial #197                // Method org/bouncycastle/asn1/tsp/TimeStampResp."<init>":(Lorg/bouncycastle/asn1/cmp/PKIStatusInfo;Lorg/bouncycastle/asn1/cms/ContentInfo;)V
      46: astore        5
      48: new           #93                 // class org/bouncycastle/tsp/TimeStampResponse
      51: dup
      52: aload         5
      54: invokespecial #205                // Method org/bouncycastle/tsp/TimeStampResponse."<init>":(Lorg/bouncycastle/asn1/tsp/TimeStampResp;)V
      57: areturn
      58: astore        6
      60: new           #90                 // class org/bouncycastle/tsp/TSPException
      63: dup
      64: ldc           #5                  // String created badly formatted response!
      66: invokespecial #199                // Method org/bouncycastle/tsp/TSPException."<init>":(Ljava/lang/String;)V
      69: athrow
    Exception table:
       from    to  target type
          48    57    58   Class java/io/IOException

  private java.util.Set convert(java.util.Set);
    Code:
       0: aload_1
       1: ifnonnull     6
       4: aload_1
       5: areturn
       6: new           #75                 // class java/util/HashSet
       9: dup
      10: aload_1
      11: invokeinterface #220,  1          // InterfaceMethod java/util/Set.size:()I
      16: invokespecial #184                // Method java/util/HashSet."<init>":(I)V
      19: astore_2
      20: aload_1
      21: invokeinterface #222,  1          // InterfaceMethod java/util/Set.iterator:()Ljava/util/Iterator;
      26: astore_3
      27: aload_3
      28: invokeinterface #218,  1          // InterfaceMethod java/util/Iterator.hasNext:()Z
      33: ifeq          86
      36: aload_3
      37: invokeinterface #219,  1          // InterfaceMethod java/util/Iterator.next:()Ljava/lang/Object;
      42: astore        4
      44: aload         4
      46: instanceof    #74                 // class java/lang/String
      49: ifeq          74
      52: aload_2
      53: new           #81                 // class org/bouncycastle/asn1/ASN1ObjectIdentifier
      56: dup
      57: aload         4
      59: checkcast     #74                 // class java/lang/String
      62: invokespecial #189                // Method org/bouncycastle/asn1/ASN1ObjectIdentifier."<init>":(Ljava/lang/String;)V
      65: invokeinterface #221,  2          // InterfaceMethod java/util/Set.add:(Ljava/lang/Object;)Z
      70: pop
      71: goto          83
      74: aload_2
      75: aload         4
      77: invokeinterface #221,  2          // InterfaceMethod java/util/Set.add:(Ljava/lang/Object;)Z
      82: pop
      83: goto          27
      86: aload_2
      87: areturn
}
