Compiled from "OmsPitfiller.java"
public class org.hortonmachine.hmachine.modules.demmanipulation.pitfiller.OmsPitfiller extends org.hortonmachine.gears.libs.modules.HMModel {
  public org.geotools.coverage.grid.GridCoverage2D inElev;

  public org.geotools.coverage.grid.GridCoverage2D outPit;

  public static final java.lang.String OMSPITFILLER_DESCRIPTION;

  public static final java.lang.String OMSPITFILLER_DOCUMENTATION;

  public static final java.lang.String OMSPITFILLER_KEYWORDS;

  public static final java.lang.String OMSPITFILLER_LABEL;

  public static final java.lang.String OMSPITFILLER_NAME;

  public static final int OMSPITFILLER_STATUS;

  public static final java.lang.String OMSPITFILLER_LICENSE;

  public static final java.lang.String OMSPITFILLER_AUTHORNAMES;

  public static final java.lang.String OMSPITFILLER_AUTHORCONTACTS;

  public static final java.lang.String OMSPITFILLER_inElev_DESCRIPTION;

  public static final java.lang.String OMSPITFILLER_outPit_DESCRIPTION;

  private org.hortonmachine.hmachine.i18n.HortonMessageHandler msg;

  public static final double PITNOVALUE;

  private javax.media.jai.iterator.WritableRandomIter pitIter;

  private javax.media.jai.iterator.RandomIter elevationIter;

  private int nCols;

  private int nRows;

  private double xRes;

  private double yRes;

  private int firstCol;

  private int firstRow;

  private int lastCol;

  private int lastRow;

  private int currentPitsCount;

  private int[] currentPitRows;

  private int[] currentPitCols;

  private int pitsStackSize;

  private int pstack;

  private int nf;

  private int pooln;

  private int[] ipool;

  private int[] jpool;

  private int[] dn;

  private int[][] dir;

  private int[][] apool;

  private int[][] DIR_WITHFLOW_EXITING_INVERTED;

  private double et;

  private double emin;

  public org.hortonmachine.hmachine.modules.demmanipulation.pitfiller.OmsPitfiller();
    Code:
       0: aload_0
       1: invokespecial #2                  // Method org/hortonmachine/gears/libs/modules/HMModel."<init>":()V
       4: aload_0
       5: aconst_null
       6: putfield      #3                  // Field outPit:Lorg/geotools/coverage/grid/GridCoverage2D;
       9: aload_0
      10: invokestatic  #4                  // Method org/hortonmachine/hmachine/i18n/HortonMessageHandler.getInstance:()Lorg/hortonmachine/hmachine/i18n/HortonMessageHandler;
      13: putfield      #5                  // Field msg:Lorg/hortonmachine/hmachine/i18n/HortonMessageHandler;
      16: aload_0
      17: aconst_null
      18: putfield      #6                  // Field elevationIter:Ljavax/media/jai/iterator/RandomIter;
      21: aload_0
      22: getstatic     #7                  // Field org/hortonmachine/gears/libs/modules/ModelsSupporter.DIR_WITHFLOW_EXITING_INVERTED:[[I
      25: putfield      #8                  // Field DIR_WITHFLOW_EXITING_INVERTED:[[I
      28: return

  public void process() throws java.lang.Exception;
    Code:
       0: aload_0
       1: iconst_2
       2: newarray       boolean
       4: dup
       5: iconst_0
       6: aload_0
       7: getfield      #3                  // Field outPit:Lorg/geotools/coverage/grid/GridCoverage2D;
      10: ifnonnull     17
      13: iconst_1
      14: goto          18
      17: iconst_0
      18: bastore
      19: dup
      20: iconst_1
      21: aload_0
      22: getfield      #9                  // Field doReset:Z
      25: bastore
      26: invokevirtual #10                 // Method concatOr:([Z)Z
      29: ifne          33
      32: return
      33: aload_0
      34: iconst_1
      35: anewarray     #11                 // class java/lang/Object
      38: dup
      39: iconst_0
      40: aload_0
      41: getfield      #12                 // Field inElev:Lorg/geotools/coverage/grid/GridCoverage2D;
      44: aastore
      45: invokevirtual #13                 // Method checkNull:([Ljava/lang/Object;)V
      48: aload_0
      49: getfield      #12                 // Field inElev:Lorg/geotools/coverage/grid/GridCoverage2D;
      52: invokestatic  #14                 // Method org/hortonmachine/gears/utils/coverage/CoverageUtilities.getRegionParamsFromGridCoverage:(Lorg/geotools/coverage/grid/GridCoverage2D;)Lorg/hortonmachine/gears/utils/RegionMap;
      55: astore_1
      56: aload_0
      57: aload_1
      58: ldc           #16                 // String COLS
      60: invokevirtual #17                 // Method java/util/HashMap.get:(Ljava/lang/Object;)Ljava/lang/Object;
      63: checkcast     #18                 // class java/lang/Double
      66: invokevirtual #19                 // Method java/lang/Double.intValue:()I
      69: putfield      #20                 // Field nCols:I
      72: aload_0
      73: aload_1
      74: ldc           #21                 // String ROWS
      76: invokevirtual #17                 // Method java/util/HashMap.get:(Ljava/lang/Object;)Ljava/lang/Object;
      79: checkcast     #18                 // class java/lang/Double
      82: invokevirtual #19                 // Method java/lang/Double.intValue:()I
      85: putfield      #22                 // Field nRows:I
      88: aload_0
      89: aload_1
      90: ldc           #23                 // String XRES
      92: invokevirtual #17                 // Method java/util/HashMap.get:(Ljava/lang/Object;)Ljava/lang/Object;
      95: checkcast     #18                 // class java/lang/Double
      98: invokevirtual #24                 // Method java/lang/Double.doubleValue:()D
     101: putfield      #25                 // Field xRes:D
     104: aload_0
     105: aload_1
     106: ldc           #26                 // String YRES
     108: invokevirtual #17                 // Method java/util/HashMap.get:(Ljava/lang/Object;)Ljava/lang/Object;
     111: checkcast     #18                 // class java/lang/Double
     114: invokevirtual #24                 // Method java/lang/Double.doubleValue:()D
     117: putfield      #27                 // Field yRes:D
     120: aload_0
     121: aload_0
     122: getfield      #12                 // Field inElev:Lorg/geotools/coverage/grid/GridCoverage2D;
     125: invokestatic  #28                 // Method org/hortonmachine/gears/utils/coverage/CoverageUtilities.getRandomIterator:(Lorg/geotools/coverage/grid/GridCoverage2D;)Ljavax/media/jai/iterator/RandomIter;
     128: putfield      #6                  // Field elevationIter:Ljavax/media/jai/iterator/RandomIter;
     131: aload_0
     132: getfield      #20                 // Field nCols:I
     135: aload_0
     136: getfield      #22                 // Field nRows:I
     139: aconst_null
     140: aconst_null
     141: aconst_null
     142: invokestatic  #29                 // Method org/hortonmachine/gears/utils/coverage/CoverageUtilities.createWritableRaster:(IILjava/lang/Class;Ljava/awt/image/SampleModel;Ljava/lang/Object;)Ljava/awt/image/WritableRaster;
     145: astore_2
     146: aload_0
     147: aload_2
     148: invokestatic  #30                 // Method org/hortonmachine/gears/utils/coverage/CoverageUtilities.getWritableRandomIterator:(Ljava/awt/image/WritableRaster;)Ljavax/media/jai/iterator/WritableRandomIter;
     151: putfield      #31                 // Field pitIter:Ljavax/media/jai/iterator/WritableRandomIter;
     154: iconst_0
     155: istore_3
     156: iload_3
     157: aload_0
     158: getfield      #22                 // Field nRows:I
     161: if_icmpge     258
     164: aload_0
     165: getfield      #32                 // Field pm:Lorg/hortonmachine/gears/libs/monitor/IHMProgressMonitor;
     168: invokeinterface #33,  1           // InterfaceMethod org/hortonmachine/gears/libs/monitor/IHMProgressMonitor.isCanceled:()Z
     173: ifeq          177
     176: return
     177: iconst_0
     178: istore        4
     180: iload         4
     182: aload_0
     183: getfield      #20                 // Field nCols:I
     186: if_icmpge     252
     189: aload_0
     190: getfield      #6                  // Field elevationIter:Ljavax/media/jai/iterator/RandomIter;
     193: iload         4
     195: iload_3
     196: iconst_0
     197: invokeinterface #34,  4           // InterfaceMethod javax/media/jai/iterator/RandomIter.getSampleDouble:(III)D
     202: dstore        5
     204: dload         5
     206: invokestatic  #35                 // Method org/hortonmachine/gears/libs/modules/HMConstants.isNovalue:(D)Z
     209: ifne          230
     212: aload_0
     213: getfield      #31                 // Field pitIter:Ljavax/media/jai/iterator/WritableRandomIter;
     216: iload         4
     218: iload_3
     219: iconst_0
     220: dload         5
     222: invokeinterface #36,  6           // InterfaceMethod javax/media/jai/iterator/WritableRandomIter.setSample:(IIID)V
     227: goto          246
     230: aload_0
     231: getfield      #31                 // Field pitIter:Ljavax/media/jai/iterator/WritableRandomIter;
     234: iload         4
     236: iload_3
     237: iconst_0
     238: ldc2_w        #38                 // double -1.0d
     241: invokeinterface #36,  6           // InterfaceMethod javax/media/jai/iterator/WritableRandomIter.setSample:(IIID)V
     246: iinc          4, 1
     249: goto          180
     252: iinc          3, 1
     255: goto          156
     258: aload_0
     259: invokespecial #40                 // Method flood:()V
     262: aload_0
     263: getfield      #32                 // Field pm:Lorg/hortonmachine/gears/libs/monitor/IHMProgressMonitor;
     266: invokeinterface #33,  1           // InterfaceMethod org/hortonmachine/gears/libs/monitor/IHMProgressMonitor.isCanceled:()Z
     271: ifeq          275
     274: return
     275: iconst_0
     276: istore_3
     277: iload_3
     278: aload_0
     279: getfield      #22                 // Field nRows:I
     282: if_icmpge     383
     285: aload_0
     286: getfield      #32                 // Field pm:Lorg/hortonmachine/gears/libs/monitor/IHMProgressMonitor;
     289: invokeinterface #33,  1           // InterfaceMethod org/hortonmachine/gears/libs/monitor/IHMProgressMonitor.isCanceled:()Z
     294: ifeq          298
     297: return
     298: iconst_0
     299: istore        4
     301: iload         4
     303: aload_0
     304: getfield      #20                 // Field nCols:I
     307: if_icmpge     377
     310: aload_0
     311: getfield      #41                 // Field dir:[[I
     314: iload         4
     316: aaload
     317: iload_3
     318: iaload
     319: ifne          323
     322: return
     323: aload_0
     324: getfield      #31                 // Field pitIter:Ljavax/media/jai/iterator/WritableRandomIter;
     327: iload         4
     329: iload_3
     330: iconst_0
     331: invokeinterface #42,  4           // InterfaceMethod javax/media/jai/iterator/WritableRandomIter.getSampleDouble:(III)D
     336: dstore        5
     338: dload         5
     340: ldc2_w        #38                 // double -1.0d
     343: dcmpl
     344: ifeq          355
     347: dload         5
     349: invokestatic  #35                 // Method org/hortonmachine/gears/libs/modules/HMConstants.isNovalue:(D)Z
     352: ifeq          371
     355: aload_0
     356: getfield      #31                 // Field pitIter:Ljavax/media/jai/iterator/WritableRandomIter;
     359: iload         4
     361: iload_3
     362: iconst_0
     363: ldc2_w        #43                 // double -9999.0d
     366: invokeinterface #36,  6           // InterfaceMethod javax/media/jai/iterator/WritableRandomIter.setSample:(IIID)V
     371: iinc          4, 1
     374: goto          301
     377: iinc          3, 1
     380: goto          277
     383: aload_0
     384: getfield      #31                 // Field pitIter:Ljavax/media/jai/iterator/WritableRandomIter;
     387: invokeinterface #45,  1           // InterfaceMethod javax/media/jai/iterator/WritableRandomIter.done:()V
     392: aload_0
     393: ldc           #46                 // String pitfiller
     395: aload_2
     396: aload_1
     397: aload_0
     398: getfield      #12                 // Field inElev:Lorg/geotools/coverage/grid/GridCoverage2D;
     401: invokevirtual #47                 // Method org/geotools/coverage/grid/GridCoverage2D.getCoordinateReferenceSystem:()Lorg/opengis/referencing/crs/CoordinateReferenceSystem;
     404: invokestatic  #48                 // Method org/hortonmachine/gears/utils/coverage/CoverageUtilities.buildCoverage:(Ljava/lang/String;Ljava/awt/image/WritableRaster;Ljava/util/HashMap;Lorg/opengis/referencing/crs/CoordinateReferenceSystem;)Lorg/geotools/coverage/grid/GridCoverage2D;
     407: putfield      #3                  // Field outPit:Lorg/geotools/coverage/grid/GridCoverage2D;
     410: return

  private void flood() throws java.lang.Exception;
    Code:
       0: aload_0
       1: aload_0
       2: getfield      #20                 // Field nCols:I
       5: aload_0
       6: getfield      #22                 // Field nRows:I
       9: imul
      10: i2d
      11: ldc2_w        #49                 // double 0.1d
      14: dmul
      15: d2i
      16: putfield      #51                 // Field pitsStackSize:I
      19: aload_0
      20: aload_0
      21: getfield      #51                 // Field pitsStackSize:I
      24: putfield      #52                 // Field pstack:I
      27: aload_0
      28: aload_0
      29: getfield      #51                 // Field pitsStackSize:I
      32: newarray       int
      34: putfield      #53                 // Field dn:[I
      37: aload_0
      38: aload_0
      39: getfield      #51                 // Field pitsStackSize:I
      42: newarray       int
      44: putfield      #54                 // Field currentPitRows:[I
      47: aload_0
      48: aload_0
      49: getfield      #51                 // Field pitsStackSize:I
      52: newarray       int
      54: putfield      #55                 // Field currentPitCols:[I
      57: aload_0
      58: aload_0
      59: getfield      #52                 // Field pstack:I
      62: newarray       int
      64: putfield      #56                 // Field ipool:[I
      67: aload_0
      68: aload_0
      69: getfield      #52                 // Field pstack:I
      72: newarray       int
      74: putfield      #57                 // Field jpool:[I
      77: aload_0
      78: iconst_0
      79: putfield      #58                 // Field firstCol:I
      82: aload_0
      83: iconst_0
      84: putfield      #59                 // Field firstRow:I
      87: aload_0
      88: aload_0
      89: getfield      #20                 // Field nCols:I
      92: putfield      #60                 // Field lastCol:I
      95: aload_0
      96: aload_0
      97: getfield      #22                 // Field nRows:I
     100: putfield      #61                 // Field lastRow:I
     103: aload_0
     104: invokespecial #62                 // Method setdf:()V
     107: return

  private void setdf() throws java.lang.Exception;
    Code:
       0: fconst_1
       1: fstore_1
       2: aload_0
       3: aload_0
       4: getfield      #25                 // Field xRes:D
       7: aload_0
       8: getfield      #27                 // Field yRes:D
      11: invokespecial #63                 // Method calculateDirectionFactor:(DD)[D
      14: astore_2
      15: aload_0
      16: aload_0
      17: getfield      #20                 // Field nCols:I
      20: aload_0
      21: getfield      #22                 // Field nRows:I
      24: multianewarray #64,  2            // class "[[I"
      28: putfield      #41                 // Field dir:[[I
      31: aload_0
      32: aload_0
      33: getfield      #20                 // Field nCols:I
      36: aload_0
      37: getfield      #22                 // Field nRows:I
      40: multianewarray #64,  2            // class "[[I"
      44: putfield      #65                 // Field apool:[[I
      47: aload_0
      48: getfield      #32                 // Field pm:Lorg/hortonmachine/gears/libs/monitor/IHMProgressMonitor;
      51: aload_0
      52: getfield      #5                  // Field msg:Lorg/hortonmachine/hmachine/i18n/HortonMessageHandler;
      55: ldc           #66                 // String pitfiller.initpointers
      57: invokevirtual #67                 // Method org/hortonmachine/hmachine/i18n/HortonMessageHandler.message:(Ljava/lang/String;)Ljava/lang/String;
      60: invokeinterface #68,  2           // InterfaceMethod org/hortonmachine/gears/libs/monitor/IHMProgressMonitor.message:(Ljava/lang/String;)V
      65: aload_0
      66: getfield      #59                 // Field firstRow:I
      69: istore_3
      70: iload_3
      71: aload_0
      72: getfield      #61                 // Field lastRow:I
      75: if_icmpge     198
      78: aload_0
      79: getfield      #32                 // Field pm:Lorg/hortonmachine/gears/libs/monitor/IHMProgressMonitor;
      82: invokeinterface #33,  1           // InterfaceMethod org/hortonmachine/gears/libs/monitor/IHMProgressMonitor.isCanceled:()Z
      87: ifeq          91
      90: return
      91: aload_0
      92: getfield      #58                 // Field firstCol:I
      95: istore        4
      97: iload         4
      99: aload_0
     100: getfield      #60                 // Field lastCol:I
     103: if_icmpge     192
     106: iload_3
     107: aload_0
     108: getfield      #59                 // Field firstRow:I
     111: if_icmpeq     163
     114: iload_3
     115: aload_0
     116: getfield      #61                 // Field lastRow:I
     119: iconst_1
     120: isub
     121: if_icmpeq     163
     124: iload         4
     126: aload_0
     127: getfield      #58                 // Field firstCol:I
     130: if_icmpeq     163
     133: iload         4
     135: aload_0
     136: getfield      #60                 // Field lastCol:I
     139: iconst_1
     140: isub
     141: if_icmpeq     163
     144: aload_0
     145: getfield      #31                 // Field pitIter:Ljavax/media/jai/iterator/WritableRandomIter;
     148: iload         4
     150: iload_3
     151: iconst_0
     152: invokeinterface #42,  4           // InterfaceMethod javax/media/jai/iterator/WritableRandomIter.getSampleDouble:(III)D
     157: invokestatic  #35                 // Method org/hortonmachine/gears/libs/modules/HMConstants.isNovalue:(D)Z
     160: ifeq          176
     163: aload_0
     164: getfield      #41                 // Field dir:[[I
     167: iload         4
     169: aaload
     170: iload_3
     171: iconst_m1
     172: iastore
     173: goto          186
     176: aload_0
     177: getfield      #41                 // Field dir:[[I
     180: iload         4
     182: aaload
     183: iload_3
     184: iconst_0
     185: iastore
     186: iinc          4, 1
     189: goto          97
     192: iinc          3, 1
     195: goto          70
     198: aload_0
     199: getfield      #32                 // Field pm:Lorg/hortonmachine/gears/libs/monitor/IHMProgressMonitor;
     202: aload_0
     203: getfield      #5                  // Field msg:Lorg/hortonmachine/hmachine/i18n/HortonMessageHandler;
     206: ldc           #69                 // String pitfiller.setpos
     208: invokevirtual #67                 // Method org/hortonmachine/hmachine/i18n/HortonMessageHandler.message:(Ljava/lang/String;)Ljava/lang/String;
     211: invokeinterface #68,  2           // InterfaceMethod org/hortonmachine/gears/libs/monitor/IHMProgressMonitor.message:(Ljava/lang/String;)V
     216: aload_0
     217: iconst_0
     218: putfield      #70                 // Field currentPitsCount:I
     221: aload_0
     222: getfield      #59                 // Field firstRow:I
     225: iconst_1
     226: iadd
     227: istore_3
     228: iload_3
     229: aload_0
     230: getfield      #61                 // Field lastRow:I
     233: iconst_1
     234: isub
     235: if_icmpge     338
     238: aload_0
     239: getfield      #32                 // Field pm:Lorg/hortonmachine/gears/libs/monitor/IHMProgressMonitor;
     242: invokeinterface #33,  1           // InterfaceMethod org/hortonmachine/gears/libs/monitor/IHMProgressMonitor.isCanceled:()Z
     247: ifeq          251
     250: return
     251: aload_0
     252: getfield      #58                 // Field firstCol:I
     255: iconst_1
     256: iadd
     257: istore        4
     259: iload         4
     261: aload_0
     262: getfield      #60                 // Field lastCol:I
     265: iconst_1
     266: isub
     267: if_icmpge     332
     270: aload_0
     271: getfield      #31                 // Field pitIter:Ljavax/media/jai/iterator/WritableRandomIter;
     274: iload         4
     276: iload_3
     277: iconst_0
     278: invokeinterface #42,  4           // InterfaceMethod javax/media/jai/iterator/WritableRandomIter.getSampleDouble:(III)D
     283: dstore        5
     285: dload         5
     287: invokestatic  #35                 // Method org/hortonmachine/gears/libs/modules/HMConstants.isNovalue:(D)Z
     290: ifne          307
     293: aload_0
     294: dload         5
     296: iload_3
     297: iload         4
     299: aload_0
     300: getfield      #41                 // Field dir:[[I
     303: aload_2
     304: invokespecial #71                 // Method setDirection:(DII[[I[D)V
     307: aload_0
     308: getfield      #41                 // Field dir:[[I
     311: iload         4
     313: aaload
     314: iload_3
     315: iaload
     316: ifne          326
     319: aload_0
     320: iload_3
     321: iload         4
     323: invokespecial #72                 // Method addPitToStack:(II)V
     326: iinc          4, 1
     329: goto          259
     332: iinc          3, 1
     335: goto          228
     338: aload_0
     339: aload_0
     340: getfield      #70                 // Field currentPitsCount:I
     343: invokespecial #73                 // Method resolveFlats:(I)I
     346: istore_3
     347: iload_3
     348: iconst_m1
     349: if_icmpne     353
     352: return
     353: aload_0
     354: getfield      #70                 // Field currentPitsCount:I
     357: istore        4
     359: aload_0
     360: getfield      #32                 // Field pm:Lorg/hortonmachine/gears/libs/monitor/IHMProgressMonitor;
     363: new           #74                 // class java/lang/StringBuilder
     366: dup
     367: invokespecial #75                 // Method java/lang/StringBuilder."<init>":()V
     370: aload_0
     371: getfield      #5                  // Field msg:Lorg/hortonmachine/hmachine/i18n/HortonMessageHandler;
     374: ldc           #76                 // String pitfiller.numpit
     376: invokevirtual #67                 // Method org/hortonmachine/hmachine/i18n/HortonMessageHandler.message:(Ljava/lang/String;)Ljava/lang/String;
     379: invokevirtual #77                 // Method java/lang/StringBuilder.append:(Ljava/lang/String;)Ljava/lang/StringBuilder;
     382: iload         4
     384: invokevirtual #78                 // Method java/lang/StringBuilder.append:(I)Ljava/lang/StringBuilder;
     387: invokevirtual #79                 // Method java/lang/StringBuilder.toString:()Ljava/lang/String;
     390: invokeinterface #68,  2           // InterfaceMethod org/hortonmachine/gears/libs/monitor/IHMProgressMonitor.message:(Ljava/lang/String;)V
     395: iload         4
     397: istore        5
     399: iload         5
     401: iconst_1
     402: imul
     403: i2f
     404: fload_1
     405: ldc           #80                 // float 100.0f
     407: fdiv
     408: fsub
     409: f2i
     410: istore        6
     412: aload_0
     413: getfield      #32                 // Field pm:Lorg/hortonmachine/gears/libs/monitor/IHMProgressMonitor;
     416: aload_0
     417: getfield      #5                  // Field msg:Lorg/hortonmachine/hmachine/i18n/HortonMessageHandler;
     420: ldc           #81                 // String pitfiller.main
     422: invokevirtual #67                 // Method org/hortonmachine/hmachine/i18n/HortonMessageHandler.message:(Ljava/lang/String;)Ljava/lang/String;
     425: invokeinterface #68,  2           // InterfaceMethod org/hortonmachine/gears/libs/monitor/IHMProgressMonitor.message:(Ljava/lang/String;)V
     430: aload_0
     431: getfield      #32                 // Field pm:Lorg/hortonmachine/gears/libs/monitor/IHMProgressMonitor;
     434: aload_0
     435: getfield      #5                  // Field msg:Lorg/hortonmachine/hmachine/i18n/HortonMessageHandler;
     438: ldc           #82                 // String pitfiller.perc
     440: invokevirtual #67                 // Method org/hortonmachine/hmachine/i18n/HortonMessageHandler.message:(Ljava/lang/String;)Ljava/lang/String;
     443: invokeinterface #68,  2           // InterfaceMethod org/hortonmachine/gears/libs/monitor/IHMProgressMonitor.message:(Ljava/lang/String;)V
     448: aload_0
     449: getfield      #32                 // Field pm:Lorg/hortonmachine/gears/libs/monitor/IHMProgressMonitor;
     452: ldc           #83                 // String 0%
     454: invokeinterface #68,  2           // InterfaceMethod org/hortonmachine/gears/libs/monitor/IHMProgressMonitor.message:(Ljava/lang/String;)V
     459: aload_0
     460: getfield      #70                 // Field currentPitsCount:I
     463: ifle          1162
     466: aload_0
     467: getfield      #32                 // Field pm:Lorg/hortonmachine/gears/libs/monitor/IHMProgressMonitor;
     470: invokeinterface #33,  1           // InterfaceMethod org/hortonmachine/gears/libs/monitor/IHMProgressMonitor.isCanceled:()Z
     475: ifeq          479
     478: return
     479: aload_0
     480: getfield      #54                 // Field currentPitRows:[I
     483: iload_3
     484: iaload
     485: istore        7
     487: aload_0
     488: getfield      #55                 // Field currentPitCols:[I
     491: iload_3
     492: iaload
     493: istore        8
     495: aload_0
     496: iconst_1
     497: putfield      #84                 // Field pooln:I
     500: aload_0
     501: iconst_0
     502: putfield      #85                 // Field nf:I
     505: aload_0
     506: iload         7
     508: iload         8
     510: iconst_0
     511: invokespecial #86                 // Method pool:(III)I
     514: istore        9
     516: iconst_1
     517: istore        10
     519: iload         10
     521: iload         9
     523: if_icmpgt     703
     526: aload_0
     527: getfield      #32                 // Field pm:Lorg/hortonmachine/gears/libs/monitor/IHMProgressMonitor;
     530: invokeinterface #33,  1           // InterfaceMethod org/hortonmachine/gears/libs/monitor/IHMProgressMonitor.isCanceled:()Z
     535: ifeq          539
     538: return
     539: aload_0
     540: getfield      #56                 // Field ipool:[I
     543: iload         10
     545: iaload
     546: istore        7
     548: aload_0
     549: getfield      #57                 // Field jpool:[I
     552: iload         10
     554: iaload
     555: istore        8
     557: iconst_1
     558: istore        11
     560: iload         11
     562: bipush        8
     564: if_icmpgt     697
     567: iload         8
     569: aload_0
     570: getfield      #8                  // Field DIR_WITHFLOW_EXITING_INVERTED:[[I
     573: iload         11
     575: aaload
     576: iconst_0
     577: iaload
     578: iadd
     579: istore        12
     581: iload         7
     583: aload_0
     584: getfield      #8                  // Field DIR_WITHFLOW_EXITING_INVERTED:[[I
     587: iload         11
     589: aaload
     590: iconst_1
     591: iaload
     592: iadd
     593: istore        13
     595: aload_0
     596: getfield      #65                 // Field apool:[[I
     599: iload         12
     601: aaload
     602: iload         13
     604: iaload
     605: aload_0
     606: getfield      #84                 // Field pooln:I
     609: if_icmpeq     691
     612: aload_0
     613: aload_0
     614: aload_0
     615: getfield      #31                 // Field pitIter:Ljavax/media/jai/iterator/WritableRandomIter;
     618: iload         8
     620: iload         7
     622: iconst_0
     623: invokeinterface #42,  4           // InterfaceMethod javax/media/jai/iterator/WritableRandomIter.getSampleDouble:(III)D
     628: aload_0
     629: getfield      #31                 // Field pitIter:Ljavax/media/jai/iterator/WritableRandomIter;
     632: iload         12
     634: iload         13
     636: iconst_0
     637: invokeinterface #42,  4           // InterfaceMethod javax/media/jai/iterator/WritableRandomIter.getSampleDouble:(III)D
     642: invokespecial #87                 // Method max2:(DD)D
     645: putfield      #88                 // Field et:D
     648: aload_0
     649: getfield      #85                 // Field nf:I
     652: ifne          671
     655: aload_0
     656: aload_0
     657: getfield      #88                 // Field et:D
     660: putfield      #89                 // Field emin:D
     663: aload_0
     664: iconst_1
     665: putfield      #85                 // Field nf:I
     668: goto          691
     671: aload_0
     672: getfield      #89                 // Field emin:D
     675: aload_0
     676: getfield      #88                 // Field et:D
     679: dcmpl
     680: ifle          691
     683: aload_0
     684: aload_0
     685: getfield      #88                 // Field et:D
     688: putfield      #89                 // Field emin:D
     691: iinc          11, 1
     694: goto          560
     697: iinc          10, 1
     700: goto          519
     703: iconst_1
     704: istore        10
     706: iload         10
     708: iload         9
     710: if_icmpgt     941
     713: aload_0
     714: getfield      #32                 // Field pm:Lorg/hortonmachine/gears/libs/monitor/IHMProgressMonitor;
     717: invokeinterface #33,  1           // InterfaceMethod org/hortonmachine/gears/libs/monitor/IHMProgressMonitor.isCanceled:()Z
     722: ifeq          726
     725: return
     726: aload_0
     727: getfield      #56                 // Field ipool:[I
     730: iload         10
     732: iaload
     733: istore        7
     735: aload_0
     736: getfield      #57                 // Field jpool:[I
     739: iload         10
     741: iaload
     742: istore        8
     744: aload_0
     745: getfield      #31                 // Field pitIter:Ljavax/media/jai/iterator/WritableRandomIter;
     748: iload         8
     750: iload         7
     752: iconst_0
     753: invokeinterface #42,  4           // InterfaceMethod javax/media/jai/iterator/WritableRandomIter.getSampleDouble:(III)D
     758: aload_0
     759: getfield      #89                 // Field emin:D
     762: dcmpg
     763: ifgt          924
     766: aload_0
     767: getfield      #41                 // Field dir:[[I
     770: iload         8
     772: aaload
     773: iload         7
     775: iaload
     776: ifle          798
     779: aload_0
     780: getfield      #41                 // Field dir:[[I
     783: iload         8
     785: aaload
     786: iload         7
     788: iconst_0
     789: iastore
     790: aload_0
     791: iload         7
     793: iload         8
     795: invokespecial #72                 // Method addPitToStack:(II)V
     798: iconst_1
     799: istore        11
     801: iload         11
     803: bipush        8
     805: if_icmpgt     906
     808: iload         8
     810: aload_0
     811: getfield      #8                  // Field DIR_WITHFLOW_EXITING_INVERTED:[[I
     814: iload         11
     816: aaload
     817: iconst_0
     818: iaload
     819: iadd
     820: istore        12
     822: iload         7
     824: aload_0
     825: getfield      #8                  // Field DIR_WITHFLOW_EXITING_INVERTED:[[I
     828: iload         11
     830: aaload
     831: iconst_1
     832: iaload
     833: iadd
     834: istore        13
     836: aload_0
     837: getfield      #31                 // Field pitIter:Ljavax/media/jai/iterator/WritableRandomIter;
     840: iload         12
     842: iload         13
     844: iconst_0
     845: invokeinterface #42,  4           // InterfaceMethod javax/media/jai/iterator/WritableRandomIter.getSampleDouble:(III)D
     850: aload_0
     851: getfield      #31                 // Field pitIter:Ljavax/media/jai/iterator/WritableRandomIter;
     854: iload         8
     856: iload         7
     858: iconst_0
     859: invokeinterface #42,  4           // InterfaceMethod javax/media/jai/iterator/WritableRandomIter.getSampleDouble:(III)D
     864: dcmpl
     865: ifle          900
     868: aload_0
     869: getfield      #41                 // Field dir:[[I
     872: iload         12
     874: aaload
     875: iload         13
     877: iaload
     878: ifle          900
     881: aload_0
     882: getfield      #41                 // Field dir:[[I
     885: iload         12
     887: aaload
     888: iload         13
     890: iconst_0
     891: iastore
     892: aload_0
     893: iload         13
     895: iload         12
     897: invokespecial #72                 // Method addPitToStack:(II)V
     900: iinc          11, 1
     903: goto          801
     906: aload_0
     907: getfield      #31                 // Field pitIter:Ljavax/media/jai/iterator/WritableRandomIter;
     910: iload         8
     912: iload         7
     914: iconst_0
     915: aload_0
     916: getfield      #89                 // Field emin:D
     919: invokeinterface #36,  6           // InterfaceMethod javax/media/jai/iterator/WritableRandomIter.setSample:(IIID)V
     924: aload_0
     925: getfield      #65                 // Field apool:[[I
     928: iload         8
     930: aaload
     931: iload         7
     933: iconst_0
     934: iastore
     935: iinc          10, 1
     938: goto          706
     941: iconst_0
     942: istore        10
     944: iconst_1
     945: istore        11
     947: iload         11
     949: aload_0
     950: getfield      #70                 // Field currentPitsCount:I
     953: if_icmpgt     1076
     956: aload_0
     957: getfield      #32                 // Field pm:Lorg/hortonmachine/gears/libs/monitor/IHMProgressMonitor;
     960: invokeinterface #33,  1           // InterfaceMethod org/hortonmachine/gears/libs/monitor/IHMProgressMonitor.isCanceled:()Z
     965: ifeq          969
     968: return
     969: aload_0
     970: aload_0
     971: getfield      #31                 // Field pitIter:Ljavax/media/jai/iterator/WritableRandomIter;
     974: aload_0
     975: getfield      #55                 // Field currentPitCols:[I
     978: iload         11
     980: iaload
     981: aload_0
     982: getfield      #54                 // Field currentPitRows:[I
     985: iload         11
     987: iaload
     988: iconst_0
     989: invokeinterface #42,  4           // InterfaceMethod javax/media/jai/iterator/WritableRandomIter.getSampleDouble:(III)D
     994: aload_0
     995: getfield      #54                 // Field currentPitRows:[I
     998: iload         11
    1000: iaload
    1001: aload_0
    1002: getfield      #55                 // Field currentPitCols:[I
    1005: iload         11
    1007: iaload
    1008: aload_0
    1009: getfield      #41                 // Field dir:[[I
    1012: aload_2
    1013: invokespecial #71                 // Method setDirection:(DII[[I[D)V
    1016: aload_0
    1017: getfield      #41                 // Field dir:[[I
    1020: aload_0
    1021: getfield      #55                 // Field currentPitCols:[I
    1024: iload         11
    1026: iaload
    1027: aaload
    1028: aload_0
    1029: getfield      #54                 // Field currentPitRows:[I
    1032: iload         11
    1034: iaload
    1035: iaload
    1036: ifne          1070
    1039: iinc          10, 1
    1042: aload_0
    1043: getfield      #54                 // Field currentPitRows:[I
    1046: iload         10
    1048: aload_0
    1049: getfield      #54                 // Field currentPitRows:[I
    1052: iload         11
    1054: iaload
    1055: iastore
    1056: aload_0
    1057: getfield      #55                 // Field currentPitCols:[I
    1060: iload         10
    1062: aload_0
    1063: getfield      #55                 // Field currentPitCols:[I
    1066: iload         11
    1068: iaload
    1069: iastore
    1070: iinc          11, 1
    1073: goto          947
    1076: aload_0
    1077: getfield      #70                 // Field currentPitsCount:I
    1080: istore        4
    1082: aload_0
    1083: iload         10
    1085: invokespecial #73                 // Method resolveFlats:(I)I
    1088: istore_3
    1089: iload_3
    1090: iconst_m1
    1091: if_icmpne     1095
    1094: return
    1095: aload_0
    1096: getfield      #70                 // Field currentPitsCount:I
    1099: iload         6
    1101: if_icmpge     1159
    1104: fload_1
    1105: ldc           #90                 // float 10.0f
    1107: frem
    1108: fconst_0
    1109: fcmpl
    1110: ifne          1142
    1113: aload_0
    1114: getfield      #32                 // Field pm:Lorg/hortonmachine/gears/libs/monitor/IHMProgressMonitor;
    1117: new           #74                 // class java/lang/StringBuilder
    1120: dup
    1121: invokespecial #75                 // Method java/lang/StringBuilder."<init>":()V
    1124: fload_1
    1125: f2i
    1126: invokevirtual #78                 // Method java/lang/StringBuilder.append:(I)Ljava/lang/StringBuilder;
    1129: ldc           #91                 // String %
    1131: invokevirtual #77                 // Method java/lang/StringBuilder.append:(Ljava/lang/String;)Ljava/lang/StringBuilder;
    1134: invokevirtual #79                 // Method java/lang/StringBuilder.toString:()Ljava/lang/String;
    1137: invokeinterface #68,  2           // InterfaceMethod org/hortonmachine/gears/libs/monitor/IHMProgressMonitor.message:(Ljava/lang/String;)V
    1142: fload_1
    1143: fconst_1
    1144: fadd
    1145: fstore_1
    1146: iload         5
    1148: i2f
    1149: fconst_1
    1150: fload_1
    1151: ldc           #80                 // float 100.0f
    1153: fdiv
    1154: fsub
    1155: fmul
    1156: f2i
    1157: istore        6
    1159: goto          459
    1162: aload_0
    1163: getfield      #32                 // Field pm:Lorg/hortonmachine/gears/libs/monitor/IHMProgressMonitor;
    1166: ldc           #92                 // String OmsPitfiller finished...
    1168: invokeinterface #68,  2           // InterfaceMethod org/hortonmachine/gears/libs/monitor/IHMProgressMonitor.message:(Ljava/lang/String;)V
    1173: return

  private void addPitToStack(int, int);
    Code:
       0: aload_0
       1: aload_0
       2: getfield      #70                 // Field currentPitsCount:I
       5: iconst_1
       6: iadd
       7: putfield      #70                 // Field currentPitsCount:I
      10: aload_0
      11: getfield      #70                 // Field currentPitsCount:I
      14: aload_0
      15: getfield      #51                 // Field pitsStackSize:I
      18: if_icmplt     96
      21: aload_0
      22: aload_0
      23: getfield      #51                 // Field pitsStackSize:I
      26: i2d
      27: aload_0
      28: getfield      #20                 // Field nCols:I
      31: aload_0
      32: getfield      #22                 // Field nRows:I
      35: imul
      36: i2d
      37: ldc2_w        #49                 // double 0.1d
      40: dmul
      41: dadd
      42: d2i
      43: iconst_2
      44: iadd
      45: putfield      #51                 // Field pitsStackSize:I
      48: aload_0
      49: aload_0
      50: aload_0
      51: getfield      #54                 // Field currentPitRows:[I
      54: aload_0
      55: getfield      #51                 // Field pitsStackSize:I
      58: invokespecial #93                 // Method realloc:([II)[I
      61: putfield      #54                 // Field currentPitRows:[I
      64: aload_0
      65: aload_0
      66: aload_0
      67: getfield      #55                 // Field currentPitCols:[I
      70: aload_0
      71: getfield      #51                 // Field pitsStackSize:I
      74: invokespecial #93                 // Method realloc:([II)[I
      77: putfield      #55                 // Field currentPitCols:[I
      80: aload_0
      81: aload_0
      82: aload_0
      83: getfield      #53                 // Field dn:[I
      86: aload_0
      87: getfield      #51                 // Field pitsStackSize:I
      90: invokespecial #93                 // Method realloc:([II)[I
      93: putfield      #53                 // Field dn:[I
      96: aload_0
      97: getfield      #54                 // Field currentPitRows:[I
     100: aload_0
     101: getfield      #70                 // Field currentPitsCount:I
     104: iload_1
     105: iastore
     106: aload_0
     107: getfield      #55                 // Field currentPitCols:[I
     110: aload_0
     111: getfield      #70                 // Field currentPitsCount:I
     114: iload_2
     115: iastore
     116: return

  private int[] realloc(int[], int);
    Code:
       0: iload_2
       1: newarray       int
       3: astore_3
       4: aload_1
       5: iconst_0
       6: aload_3
       7: iconst_0
       8: aload_1
       9: arraylength
      10: invokestatic  #94                 // Method java/lang/System.arraycopy:(Ljava/lang/Object;ILjava/lang/Object;II)V
      13: aload_3
      14: areturn

  private int resolveFlats(int);
    Code:
       0: aload_0
       1: iload_1
       2: putfield      #70                 // Field currentPitsCount:I
       5: aload_0
       6: getfield      #32                 // Field pm:Lorg/hortonmachine/gears/libs/monitor/IHMProgressMonitor;
       9: invokeinterface #33,  1           // InterfaceMethod org/hortonmachine/gears/libs/monitor/IHMProgressMonitor.isCanceled:()Z
      14: ifeq          19
      17: iconst_m1
      18: ireturn
      19: aload_0
      20: getfield      #70                 // Field currentPitsCount:I
      23: istore_1
      24: aload_0
      25: iconst_0
      26: putfield      #70                 // Field currentPitsCount:I
      29: iconst_1
      30: istore_3
      31: iload_3
      32: iload_1
      33: if_icmpgt     49
      36: aload_0
      37: getfield      #53                 // Field dn:[I
      40: iload_3
      41: iconst_0
      42: iastore
      43: iinc          3, 1
      46: goto          31
      49: iconst_1
      50: istore_3
      51: iload_3
      52: bipush        8
      54: if_icmpgt     213
      57: iconst_1
      58: istore        4
      60: iload         4
      62: iload_1
      63: if_icmpgt     207
      66: aload_0
      67: getfield      #31                 // Field pitIter:Ljavax/media/jai/iterator/WritableRandomIter;
      70: aload_0
      71: getfield      #55                 // Field currentPitCols:[I
      74: iload         4
      76: iaload
      77: aload_0
      78: getfield      #54                 // Field currentPitRows:[I
      81: iload         4
      83: iaload
      84: iconst_0
      85: invokeinterface #42,  4           // InterfaceMethod javax/media/jai/iterator/WritableRandomIter.getSampleDouble:(III)D
      90: aload_0
      91: getfield      #31                 // Field pitIter:Ljavax/media/jai/iterator/WritableRandomIter;
      94: aload_0
      95: getfield      #55                 // Field currentPitCols:[I
      98: iload         4
     100: iaload
     101: aload_0
     102: getfield      #8                  // Field DIR_WITHFLOW_EXITING_INVERTED:[[I
     105: iload_3
     106: aaload
     107: iconst_0
     108: iaload
     109: iadd
     110: aload_0
     111: getfield      #54                 // Field currentPitRows:[I
     114: iload         4
     116: iaload
     117: aload_0
     118: getfield      #8                  // Field DIR_WITHFLOW_EXITING_INVERTED:[[I
     121: iload_3
     122: aaload
     123: iconst_1
     124: iaload
     125: iadd
     126: iconst_0
     127: invokeinterface #42,  4           // InterfaceMethod javax/media/jai/iterator/WritableRandomIter.getSampleDouble:(III)D
     132: dsub
     133: dstore        5
     135: dload         5
     137: dconst_0
     138: dcmpl
     139: iflt          201
     142: aload_0
     143: getfield      #41                 // Field dir:[[I
     146: aload_0
     147: getfield      #55                 // Field currentPitCols:[I
     150: iload         4
     152: iaload
     153: aload_0
     154: getfield      #8                  // Field DIR_WITHFLOW_EXITING_INVERTED:[[I
     157: iload_3
     158: aaload
     159: iconst_0
     160: iaload
     161: iadd
     162: aaload
     163: aload_0
     164: getfield      #54                 // Field currentPitRows:[I
     167: iload         4
     169: iaload
     170: aload_0
     171: getfield      #8                  // Field DIR_WITHFLOW_EXITING_INVERTED:[[I
     174: iload_3
     175: aaload
     176: iconst_1
     177: iaload
     178: iadd
     179: iaload
     180: ifeq          201
     183: aload_0
     184: getfield      #53                 // Field dn:[I
     187: iload         4
     189: iaload
     190: ifne          201
     193: aload_0
     194: getfield      #53                 // Field dn:[I
     197: iload         4
     199: iload_3
     200: iastore
     201: iinc          4, 1
     204: goto          60
     207: iinc          3, 1
     210: goto          51
     213: iconst_1
     214: istore_2
     215: iconst_1
     216: istore_3
     217: iload_3
     218: iload_1
     219: if_icmpgt     363
     222: aload_0
     223: getfield      #53                 // Field dn:[I
     226: iload_3
     227: iaload
     228: ifle          258
     231: aload_0
     232: getfield      #41                 // Field dir:[[I
     235: aload_0
     236: getfield      #55                 // Field currentPitCols:[I
     239: iload_3
     240: iaload
     241: aaload
     242: aload_0
     243: getfield      #54                 // Field currentPitRows:[I
     246: iload_3
     247: iaload
     248: aload_0
     249: getfield      #53                 // Field dn:[I
     252: iload_3
     253: iaload
     254: iastore
     255: goto          357
     258: aload_0
     259: dup
     260: getfield      #70                 // Field currentPitsCount:I
     263: iconst_1
     264: iadd
     265: putfield      #70                 // Field currentPitsCount:I
     268: aload_0
     269: getfield      #54                 // Field currentPitRows:[I
     272: aload_0
     273: getfield      #70                 // Field currentPitsCount:I
     276: aload_0
     277: getfield      #54                 // Field currentPitRows:[I
     280: iload_3
     281: iaload
     282: iastore
     283: aload_0
     284: getfield      #55                 // Field currentPitCols:[I
     287: aload_0
     288: getfield      #70                 // Field currentPitsCount:I
     291: aload_0
     292: getfield      #55                 // Field currentPitCols:[I
     295: iload_3
     296: iaload
     297: iastore
     298: aload_0
     299: getfield      #31                 // Field pitIter:Ljavax/media/jai/iterator/WritableRandomIter;
     302: aload_0
     303: getfield      #55                 // Field currentPitCols:[I
     306: aload_0
     307: getfield      #70                 // Field currentPitsCount:I
     310: iaload
     311: aload_0
     312: getfield      #54                 // Field currentPitRows:[I
     315: aload_0
     316: getfield      #70                 // Field currentPitsCount:I
     319: iaload
     320: iconst_0
     321: invokeinterface #42,  4           // InterfaceMethod javax/media/jai/iterator/WritableRandomIter.getSampleDouble:(III)D
     326: aload_0
     327: getfield      #31                 // Field pitIter:Ljavax/media/jai/iterator/WritableRandomIter;
     330: aload_0
     331: getfield      #55                 // Field currentPitCols:[I
     334: iload_2
     335: iaload
     336: aload_0
     337: getfield      #54                 // Field currentPitRows:[I
     340: iload_2
     341: iaload
     342: iconst_0
     343: invokeinterface #42,  4           // InterfaceMethod javax/media/jai/iterator/WritableRandomIter.getSampleDouble:(III)D
     348: dcmpg
     349: ifge          357
     352: aload_0
     353: getfield      #70                 // Field currentPitsCount:I
     356: istore_2
     357: iinc          3, 1
     360: goto          217
     363: aload_0
     364: getfield      #70                 // Field currentPitsCount:I
     367: iload_1
     368: if_icmplt     5
     371: iload_2
     372: ireturn

  private int pool(int, int, int);
    Code:
       0: iload_3
       1: istore        6
       3: aload_0
       4: getfield      #65                 // Field apool:[[I
       7: iload_2
       8: aaload
       9: iload_1
      10: iaload
      11: ifgt          303
      14: aload_0
      15: getfield      #41                 // Field dir:[[I
      18: iload_2
      19: aaload
      20: iload_1
      21: iaload
      22: iconst_m1
      23: if_icmpeq     303
      26: aload_0
      27: getfield      #65                 // Field apool:[[I
      30: iload_2
      31: aaload
      32: iload_1
      33: aload_0
      34: getfield      #84                 // Field pooln:I
      37: iastore
      38: iload         6
      40: iconst_1
      41: iadd
      42: istore        6
      44: iload         6
      46: aload_0
      47: getfield      #52                 // Field pstack:I
      50: if_icmplt     142
      53: aload_0
      54: getfield      #52                 // Field pstack:I
      57: aload_0
      58: getfield      #20                 // Field nCols:I
      61: aload_0
      62: getfield      #22                 // Field nRows:I
      65: imul
      66: if_icmpge     142
      69: aload_0
      70: aload_0
      71: getfield      #52                 // Field pstack:I
      74: i2d
      75: aload_0
      76: getfield      #20                 // Field nCols:I
      79: aload_0
      80: getfield      #22                 // Field nRows:I
      83: imul
      84: i2d
      85: ldc2_w        #49                 // double 0.1d
      88: dmul
      89: dadd
      90: d2i
      91: putfield      #52                 // Field pstack:I
      94: aload_0
      95: getfield      #52                 // Field pstack:I
      98: aload_0
      99: getfield      #20                 // Field nCols:I
     102: aload_0
     103: getfield      #22                 // Field nRows:I
     106: imul
     107: if_icmple     110
     110: aload_0
     111: aload_0
     112: aload_0
     113: getfield      #56                 // Field ipool:[I
     116: aload_0
     117: getfield      #52                 // Field pstack:I
     120: invokespecial #93                 // Method realloc:([II)[I
     123: putfield      #56                 // Field ipool:[I
     126: aload_0
     127: aload_0
     128: aload_0
     129: getfield      #57                 // Field jpool:[I
     132: aload_0
     133: getfield      #52                 // Field pstack:I
     136: invokespecial #93                 // Method realloc:([II)[I
     139: putfield      #57                 // Field jpool:[I
     142: aload_0
     143: getfield      #56                 // Field ipool:[I
     146: iload         6
     148: iload_1
     149: iastore
     150: aload_0
     151: getfield      #57                 // Field jpool:[I
     154: iload         6
     156: iload_2
     157: iastore
     158: iconst_1
     159: istore        7
     161: iload         7
     163: bipush        8
     165: if_icmpgt     303
     168: iload_1
     169: aload_0
     170: getfield      #8                  // Field DIR_WITHFLOW_EXITING_INVERTED:[[I
     173: iload         7
     175: aaload
     176: iconst_1
     177: iaload
     178: iadd
     179: istore        4
     181: iload_2
     182: aload_0
     183: getfield      #8                  // Field DIR_WITHFLOW_EXITING_INVERTED:[[I
     186: iload         7
     188: aaload
     189: iconst_0
     190: iaload
     191: iadd
     192: istore        5
     194: aload_0
     195: getfield      #41                 // Field dir:[[I
     198: iload         5
     200: aaload
     201: iload         4
     203: iaload
     204: ifle          242
     207: aload_0
     208: getfield      #41                 // Field dir:[[I
     211: iload         5
     213: aaload
     214: iload         4
     216: iaload
     217: iload         7
     219: isub
     220: iconst_4
     221: if_icmpeq     285
     224: aload_0
     225: getfield      #41                 // Field dir:[[I
     228: iload         5
     230: aaload
     231: iload         4
     233: iaload
     234: iload         7
     236: isub
     237: bipush        -4
     239: if_icmpeq     285
     242: aload_0
     243: getfield      #41                 // Field dir:[[I
     246: iload         5
     248: aaload
     249: iload         4
     251: iaload
     252: ifne          297
     255: aload_0
     256: getfield      #31                 // Field pitIter:Ljavax/media/jai/iterator/WritableRandomIter;
     259: iload         5
     261: iload         4
     263: iconst_0
     264: invokeinterface #42,  4           // InterfaceMethod javax/media/jai/iterator/WritableRandomIter.getSampleDouble:(III)D
     269: aload_0
     270: getfield      #31                 // Field pitIter:Ljavax/media/jai/iterator/WritableRandomIter;
     273: iload_2
     274: iload_1
     275: iconst_0
     276: invokeinterface #42,  4           // InterfaceMethod javax/media/jai/iterator/WritableRandomIter.getSampleDouble:(III)D
     281: dcmpl
     282: iflt          297
     285: aload_0
     286: iload         4
     288: iload         5
     290: iload         6
     292: invokespecial #86                 // Method pool:(III)I
     295: istore        6
     297: iinc          7, 1
     300: goto          161
     303: iload         6
     305: ireturn

  private double max2(double, double);
    Code:
       0: dload_1
       1: dstore        5
       3: dload_3
       4: dload         5
       6: dcmpl
       7: ifle          13
      10: dload_3
      11: dstore        5
      13: dload         5
      15: dreturn

  private void setDirection(double, int, int, int[][], double[]);
    Code:
       0: aload         5
       2: iload         4
       4: aaload
       5: iload_3
       6: iconst_0
       7: iastore
       8: dconst_0
       9: dstore        7
      11: iconst_1
      12: istore        9
      14: iload         9
      16: bipush        8
      18: if_icmpgt     133
      21: iload         4
      23: aload_0
      24: getfield      #8                  // Field DIR_WITHFLOW_EXITING_INVERTED:[[I
      27: iload         9
      29: aaload
      30: iconst_0
      31: iaload
      32: iadd
      33: istore        10
      35: iload_3
      36: aload_0
      37: getfield      #8                  // Field DIR_WITHFLOW_EXITING_INVERTED:[[I
      40: iload         9
      42: aaload
      43: iconst_1
      44: iaload
      45: iadd
      46: istore        11
      48: aload_0
      49: getfield      #31                 // Field pitIter:Ljavax/media/jai/iterator/WritableRandomIter;
      52: iload         10
      54: iload         11
      56: iconst_0
      57: invokeinterface #42,  4           // InterfaceMethod javax/media/jai/iterator/WritableRandomIter.getSampleDouble:(III)D
      62: dstore        12
      64: dload         12
      66: invokestatic  #35                 // Method org/hortonmachine/gears/libs/modules/HMConstants.isNovalue:(D)Z
      69: ifeq          83
      72: aload         5
      74: iload         4
      76: aaload
      77: iload_3
      78: iconst_m1
      79: iastore
      80: goto          133
      83: aload         5
      85: iload         4
      87: aaload
      88: iload_3
      89: iaload
      90: iconst_m1
      91: if_icmpeq     127
      94: aload         6
      96: iload         9
      98: daload
      99: dload_1
     100: dload         12
     102: dsub
     103: dmul
     104: dstore        14
     106: dload         14
     108: dload         7
     110: dcmpl
     111: ifle          127
     114: dload         14
     116: dstore        7
     118: aload         5
     120: iload         4
     122: aaload
     123: iload_3
     124: iload         9
     126: iastore
     127: iinc          9, 1
     130: goto          14
     133: return

  private double[] calculateDirectionFactor(double, double);
    Code:
       0: bipush        9
       2: newarray       double
       4: astore        5
       6: iconst_1
       7: istore        6
       9: iload         6
      11: bipush        8
      13: if_icmpgt     82
      16: aload         5
      18: iload         6
      20: dconst_1
      21: aload_0
      22: getfield      #8                  // Field DIR_WITHFLOW_EXITING_INVERTED:[[I
      25: iload         6
      27: aaload
      28: iconst_0
      29: iaload
      30: i2d
      31: dload_3
      32: dmul
      33: aload_0
      34: getfield      #8                  // Field DIR_WITHFLOW_EXITING_INVERTED:[[I
      37: iload         6
      39: aaload
      40: iconst_0
      41: iaload
      42: i2d
      43: dmul
      44: dload_3
      45: dmul
      46: aload_0
      47: getfield      #8                  // Field DIR_WITHFLOW_EXITING_INVERTED:[[I
      50: iload         6
      52: aaload
      53: iconst_1
      54: iaload
      55: aload_0
      56: getfield      #8                  // Field DIR_WITHFLOW_EXITING_INVERTED:[[I
      59: iload         6
      61: aaload
      62: iconst_1
      63: iaload
      64: imul
      65: i2d
      66: dload_1
      67: dmul
      68: dload_1
      69: dmul
      70: dadd
      71: invokestatic  #95                 // Method java/lang/Math.sqrt:(D)D
      74: ddiv
      75: dastore
      76: iinc          6, 1
      79: goto          9
      82: aload         5
      84: areturn
}
