class org.bouncycastle.cms.CMSTypedStream$FullReaderStream extends java.io.FilterInputStream {
  org.bouncycastle.cms.CMSTypedStream$FullReaderStream(java.io.InputStream);
    Code:
       0: aload_0
       1: aload_1
       2: invokespecial #23                 // Method java/io/FilterInputStream."<init>":(Ljava/io/InputStream;)V
       5: return

  public int read(byte[], int, int) throws java.io.IOException;
    Code:
       0: iload_3
       1: ifne          6
       4: iconst_0
       5: ireturn
       6: aload_0
       7: getfield      #22                 // Field java/io/FilterInputStream.in:Ljava/io/InputStream;
      10: aload_1
      11: iload_2
      12: iload_3
      13: invokestatic  #24                 // Method org/bouncycastle/util/io/Streams.readFully:(Ljava/io/InputStream;[BII)I
      16: istore        4
      18: iload         4
      20: ifle          28
      23: iload         4
      25: goto          29
      28: iconst_m1
      29: ireturn
}
