Compiled from "PatchingHistoryUnitTestCase.java"
public class org.jboss.as.patching.validation.PatchingHistoryUnitTestCase extends org.jboss.as.patching.tests.AbstractPatchingTest {
  static final java.lang.String[] FILE_ONE;

  static final java.lang.String[] FILE_TWO;

  static final java.lang.String[] FILE_EXISTING;

  private static final java.lang.String CP_1_ID;

  private static final java.lang.String ONE_OFF_1_ID;

  private static final java.lang.String ONE_OFF_2_ID;

  public org.jboss.as.patching.validation.PatchingHistoryUnitTestCase();
    Code:
       0: aload_0
       1: invokespecial #1                  // Method org/jboss/as/patching/tests/AbstractPatchingTest."<init>":()V
       4: return

  public void testTreeHandleAll() throws java.lang.Exception;
    Code:
       0: aload_0
       1: invokevirtual #2                  // Method installOneOffCpOneOff:()Lorg/jboss/as/patching/tests/PatchingTestBuilder;
       4: pop
       5: new           #3                  // class java/util/ArrayList
       8: dup
       9: invokespecial #4                  // Method java/util/ArrayList."<init>":()V
      12: astore_1
      13: new           #3                  // class java/util/ArrayList
      16: dup
      17: invokespecial #4                  // Method java/util/ArrayList."<init>":()V
      20: astore_2
      21: new           #3                  // class java/util/ArrayList
      24: dup
      25: invokespecial #4                  // Method java/util/ArrayList."<init>":()V
      28: astore_3
      29: aload_0
      30: invokevirtual #5                  // Method updateInstallationManager:()Lorg/jboss/as/patching/installation/InstallationManager;
      33: invokestatic  #6                  // Method org/jboss/as/patching/validation/PatchHistoryIterator$Builder.create:(Lorg/jboss/as/patching/installation/InstalledIdentity;)Lorg/jboss/as/patching/validation/PatchHistoryIterator$Builder;
      36: astore        4
      38: aload         4
      40: getstatic     #7                  // Field org/jboss/as/patching/validation/PatchingArtifacts.HISTORY_DIR:Lorg/jboss/as/patching/validation/PatchingHistoryDirArtifact;
      43: new           #8                  // class org/jboss/as/patching/validation/PatchingHistoryUnitTestCase$1
      46: dup
      47: aload_0
      48: aload_1
      49: invokespecial #9                  // Method org/jboss/as/patching/validation/PatchingHistoryUnitTestCase$1."<init>":(Lorg/jboss/as/patching/validation/PatchingHistoryUnitTestCase;Ljava/util/List;)V
      52: invokevirtual #10                 // Method org/jboss/as/patching/validation/PatchHistoryIterator$Builder.addStateHandler:(Lorg/jboss/as/patching/validation/PatchingArtifact;Lorg/jboss/as/patching/validation/PatchingArtifactStateHandler;)V
      55: aload         4
      57: getstatic     #11                 // Field org/jboss/as/patching/validation/PatchingArtifacts.MODULE_OVERLAY:Lorg/jboss/as/patching/validation/PatchingOverlayDirArtifact;
      60: new           #12                 // class org/jboss/as/patching/validation/PatchingHistoryUnitTestCase$2
      63: dup
      64: aload_0
      65: aload_2
      66: invokespecial #13                 // Method org/jboss/as/patching/validation/PatchingHistoryUnitTestCase$2."<init>":(Lorg/jboss/as/patching/validation/PatchingHistoryUnitTestCase;Ljava/util/List;)V
      69: invokevirtual #10                 // Method org/jboss/as/patching/validation/PatchHistoryIterator$Builder.addStateHandler:(Lorg/jboss/as/patching/validation/PatchingArtifact;Lorg/jboss/as/patching/validation/PatchingArtifactStateHandler;)V
      72: aload         4
      74: getstatic     #14                 // Field org/jboss/as/patching/validation/PatchingArtifacts.BUNDLE_OVERLAY:Lorg/jboss/as/patching/validation/PatchingOverlayDirArtifact;
      77: new           #15                 // class org/jboss/as/patching/validation/PatchingHistoryUnitTestCase$3
      80: dup
      81: aload_0
      82: aload_3
      83: invokespecial #16                 // Method org/jboss/as/patching/validation/PatchingHistoryUnitTestCase$3."<init>":(Lorg/jboss/as/patching/validation/PatchingHistoryUnitTestCase;Ljava/util/List;)V
      86: invokevirtual #10                 // Method org/jboss/as/patching/validation/PatchHistoryIterator$Builder.addStateHandler:(Lorg/jboss/as/patching/validation/PatchingArtifact;Lorg/jboss/as/patching/validation/PatchingArtifactStateHandler;)V
      89: aload         4
      91: invokevirtual #17                 // Method org/jboss/as/patching/validation/PatchHistoryIterator$Builder.iterator:()Lorg/jboss/as/patching/validation/PatchHistoryIterator;
      94: astore        5
      96: aload         5
      98: invokeinterface #18,  1           // InterfaceMethod org/jboss/as/patching/validation/PatchHistoryIterator.hasNext:()Z
     103: ifeq          117
     106: aload         5
     108: invokeinterface #19,  1           // InterfaceMethod org/jboss/as/patching/validation/PatchHistoryIterator.next:()Ljava/lang/String;
     113: pop
     114: goto          96
     117: iconst_3
     118: anewarray     #20                 // class java/lang/String
     121: dup
     122: iconst_0
     123: ldc           #21                 // String oneOff2
     125: aastore
     126: dup
     127: iconst_1
     128: ldc           #22                 // String cp1
     130: aastore
     131: dup
     132: iconst_2
     133: ldc           #23                 // String oneOff1
     135: aastore
     136: invokestatic  #24                 // Method java/util/Arrays.asList:([Ljava/lang/Object;)Ljava/util/List;
     139: aload_1
     140: invokestatic  #25                 // Method org/junit/Assert.assertEquals:(Ljava/lang/Object;Ljava/lang/Object;)V
     143: iconst_3
     144: anewarray     #20                 // class java/lang/String
     147: dup
     148: iconst_0
     149: ldc           #26                 // String base-oneOff2
     151: aastore
     152: dup
     153: iconst_1
     154: ldc           #27                 // String base-cp1
     156: aastore
     157: dup
     158: iconst_2
     159: ldc           #28                 // String base-oneOff1
     161: aastore
     162: invokestatic  #24                 // Method java/util/Arrays.asList:([Ljava/lang/Object;)Ljava/util/List;
     165: aload_2
     166: invokestatic  #25                 // Method org/junit/Assert.assertEquals:(Ljava/lang/Object;Ljava/lang/Object;)V
     169: aload_3
     170: invokeinterface #29,  1           // InterfaceMethod java/util/List.isEmpty:()Z
     175: invokestatic  #30                 // Method org/junit/Assert.assertTrue:(Z)V
     178: return

  public void testTreeIterator() throws java.lang.Exception;
    Code:
       0: aload_0
       1: invokevirtual #2                  // Method installOneOffCpOneOff:()Lorg/jboss/as/patching/tests/PatchingTestBuilder;
       4: pop
       5: new           #3                  // class java/util/ArrayList
       8: dup
       9: invokespecial #4                  // Method java/util/ArrayList."<init>":()V
      12: astore_1
      13: new           #3                  // class java/util/ArrayList
      16: dup
      17: invokespecial #4                  // Method java/util/ArrayList."<init>":()V
      20: astore_2
      21: new           #3                  // class java/util/ArrayList
      24: dup
      25: invokespecial #4                  // Method java/util/ArrayList."<init>":()V
      28: astore_3
      29: aload_0
      30: invokevirtual #5                  // Method updateInstallationManager:()Lorg/jboss/as/patching/installation/InstallationManager;
      33: invokestatic  #6                  // Method org/jboss/as/patching/validation/PatchHistoryIterator$Builder.create:(Lorg/jboss/as/patching/installation/InstalledIdentity;)Lorg/jboss/as/patching/validation/PatchHistoryIterator$Builder;
      36: astore        4
      38: aload         4
      40: getstatic     #7                  // Field org/jboss/as/patching/validation/PatchingArtifacts.HISTORY_DIR:Lorg/jboss/as/patching/validation/PatchingHistoryDirArtifact;
      43: new           #31                 // class org/jboss/as/patching/validation/PatchingHistoryUnitTestCase$4
      46: dup
      47: aload_0
      48: aload_1
      49: invokespecial #32                 // Method org/jboss/as/patching/validation/PatchingHistoryUnitTestCase$4."<init>":(Lorg/jboss/as/patching/validation/PatchingHistoryUnitTestCase;Ljava/util/List;)V
      52: invokevirtual #10                 // Method org/jboss/as/patching/validation/PatchHistoryIterator$Builder.addStateHandler:(Lorg/jboss/as/patching/validation/PatchingArtifact;Lorg/jboss/as/patching/validation/PatchingArtifactStateHandler;)V
      55: aload         4
      57: getstatic     #11                 // Field org/jboss/as/patching/validation/PatchingArtifacts.MODULE_OVERLAY:Lorg/jboss/as/patching/validation/PatchingOverlayDirArtifact;
      60: new           #33                 // class org/jboss/as/patching/validation/PatchingHistoryUnitTestCase$5
      63: dup
      64: aload_0
      65: aload_2
      66: invokespecial #34                 // Method org/jboss/as/patching/validation/PatchingHistoryUnitTestCase$5."<init>":(Lorg/jboss/as/patching/validation/PatchingHistoryUnitTestCase;Ljava/util/List;)V
      69: invokevirtual #10                 // Method org/jboss/as/patching/validation/PatchHistoryIterator$Builder.addStateHandler:(Lorg/jboss/as/patching/validation/PatchingArtifact;Lorg/jboss/as/patching/validation/PatchingArtifactStateHandler;)V
      72: aload         4
      74: getstatic     #14                 // Field org/jboss/as/patching/validation/PatchingArtifacts.BUNDLE_OVERLAY:Lorg/jboss/as/patching/validation/PatchingOverlayDirArtifact;
      77: new           #35                 // class org/jboss/as/patching/validation/PatchingHistoryUnitTestCase$6
      80: dup
      81: aload_0
      82: aload_3
      83: invokespecial #36                 // Method org/jboss/as/patching/validation/PatchingHistoryUnitTestCase$6."<init>":(Lorg/jboss/as/patching/validation/PatchingHistoryUnitTestCase;Ljava/util/List;)V
      86: invokevirtual #10                 // Method org/jboss/as/patching/validation/PatchHistoryIterator$Builder.addStateHandler:(Lorg/jboss/as/patching/validation/PatchingArtifact;Lorg/jboss/as/patching/validation/PatchingArtifactStateHandler;)V
      89: aload         4
      91: invokevirtual #17                 // Method org/jboss/as/patching/validation/PatchHistoryIterator$Builder.iterator:()Lorg/jboss/as/patching/validation/PatchHistoryIterator;
      94: astore        5
      96: aload         5
      98: invokeinterface #18,  1           // InterfaceMethod org/jboss/as/patching/validation/PatchHistoryIterator.hasNext:()Z
     103: invokestatic  #30                 // Method org/junit/Assert.assertTrue:(Z)V
     106: aload_1
     107: invokeinterface #29,  1           // InterfaceMethod java/util/List.isEmpty:()Z
     112: invokestatic  #30                 // Method org/junit/Assert.assertTrue:(Z)V
     115: aload_2
     116: invokeinterface #29,  1           // InterfaceMethod java/util/List.isEmpty:()Z
     121: invokestatic  #30                 // Method org/junit/Assert.assertTrue:(Z)V
     124: aload_3
     125: invokeinterface #29,  1           // InterfaceMethod java/util/List.isEmpty:()Z
     130: invokestatic  #30                 // Method org/junit/Assert.assertTrue:(Z)V
     133: aload         5
     135: invokeinterface #18,  1           // InterfaceMethod org/jboss/as/patching/validation/PatchHistoryIterator.hasNext:()Z
     140: invokestatic  #30                 // Method org/junit/Assert.assertTrue:(Z)V
     143: aload         5
     145: invokeinterface #19,  1           // InterfaceMethod org/jboss/as/patching/validation/PatchHistoryIterator.next:()Ljava/lang/String;
     150: pop
     151: lconst_1
     152: aload_1
     153: invokeinterface #37,  1           // InterfaceMethod java/util/List.size:()I
     158: i2l
     159: invokestatic  #38                 // Method org/junit/Assert.assertEquals:(JJ)V
     162: aload_1
     163: ldc           #21                 // String oneOff2
     165: invokeinterface #39,  2           // InterfaceMethod java/util/List.contains:(Ljava/lang/Object;)Z
     170: invokestatic  #30                 // Method org/junit/Assert.assertTrue:(Z)V
     173: aload_2
     174: ldc           #26                 // String base-oneOff2
     176: invokeinterface #39,  2           // InterfaceMethod java/util/List.contains:(Ljava/lang/Object;)Z
     181: invokestatic  #30                 // Method org/junit/Assert.assertTrue:(Z)V
     184: aload_3
     185: invokeinterface #29,  1           // InterfaceMethod java/util/List.isEmpty:()Z
     190: invokestatic  #30                 // Method org/junit/Assert.assertTrue:(Z)V
     193: aload         5
     195: invokeinterface #18,  1           // InterfaceMethod org/jboss/as/patching/validation/PatchHistoryIterator.hasNext:()Z
     200: invokestatic  #30                 // Method org/junit/Assert.assertTrue:(Z)V
     203: aload         5
     205: invokeinterface #19,  1           // InterfaceMethod org/jboss/as/patching/validation/PatchHistoryIterator.next:()Ljava/lang/String;
     210: pop
     211: ldc2_w        #40                 // long 2l
     214: aload_1
     215: invokeinterface #37,  1           // InterfaceMethod java/util/List.size:()I
     220: i2l
     221: invokestatic  #38                 // Method org/junit/Assert.assertEquals:(JJ)V
     224: aload_1
     225: ldc           #22                 // String cp1
     227: invokeinterface #39,  2           // InterfaceMethod java/util/List.contains:(Ljava/lang/Object;)Z
     232: invokestatic  #30                 // Method org/junit/Assert.assertTrue:(Z)V
     235: ldc2_w        #40                 // long 2l
     238: aload_2
     239: invokeinterface #37,  1           // InterfaceMethod java/util/List.size:()I
     244: i2l
     245: invokestatic  #38                 // Method org/junit/Assert.assertEquals:(JJ)V
     248: aload_2
     249: ldc           #27                 // String base-cp1
     251: invokeinterface #39,  2           // InterfaceMethod java/util/List.contains:(Ljava/lang/Object;)Z
     256: invokestatic  #30                 // Method org/junit/Assert.assertTrue:(Z)V
     259: aload_3
     260: invokeinterface #29,  1           // InterfaceMethod java/util/List.isEmpty:()Z
     265: invokestatic  #30                 // Method org/junit/Assert.assertTrue:(Z)V
     268: aload         5
     270: invokeinterface #18,  1           // InterfaceMethod org/jboss/as/patching/validation/PatchHistoryIterator.hasNext:()Z
     275: invokestatic  #30                 // Method org/junit/Assert.assertTrue:(Z)V
     278: aload         5
     280: invokeinterface #19,  1           // InterfaceMethod org/jboss/as/patching/validation/PatchHistoryIterator.next:()Ljava/lang/String;
     285: pop
     286: ldc2_w        #42                 // long 3l
     289: aload_1
     290: invokeinterface #37,  1           // InterfaceMethod java/util/List.size:()I
     295: i2l
     296: invokestatic  #38                 // Method org/junit/Assert.assertEquals:(JJ)V
     299: aload_1
     300: ldc           #23                 // String oneOff1
     302: invokeinterface #39,  2           // InterfaceMethod java/util/List.contains:(Ljava/lang/Object;)Z
     307: invokestatic  #30                 // Method org/junit/Assert.assertTrue:(Z)V
     310: aload_2
     311: ldc           #28                 // String base-oneOff1
     313: invokeinterface #39,  2           // InterfaceMethod java/util/List.contains:(Ljava/lang/Object;)Z
     318: invokestatic  #30                 // Method org/junit/Assert.assertTrue:(Z)V
     321: aload_3
     322: invokeinterface #29,  1           // InterfaceMethod java/util/List.isEmpty:()Z
     327: invokestatic  #30                 // Method org/junit/Assert.assertTrue:(Z)V
     330: aload         5
     332: invokeinterface #18,  1           // InterfaceMethod org/jboss/as/patching/validation/PatchHistoryIterator.hasNext:()Z
     337: invokestatic  #44                 // Method org/junit/Assert.assertFalse:(Z)V
     340: return

  public void testSimpleValidRollbackOneOff() throws java.lang.Exception;
    Code:
       0: aload_0
       1: invokevirtual #45                 // Method installOneOff:()Lorg/jboss/as/patching/tests/PatchingTestBuilder;
       4: pop
       5: ldc           #23                 // String oneOff1
       7: aload_0
       8: invokevirtual #5                  // Method updateInstallationManager:()Lorg/jboss/as/patching/installation/InstallationManager;
      11: invokestatic  #46                 // Method org/jboss/as/patching/validation/PatchHistoryValidations.validateRollbackState:(Ljava/lang/String;Lorg/jboss/as/patching/installation/InstalledIdentity;)V
      14: return

  public void testSimpleMissingHistory() throws java.lang.Exception;
    Code:
       0: aload_0
       1: invokevirtual #45                 // Method installOneOff:()Lorg/jboss/as/patching/tests/PatchingTestBuilder;
       4: astore_1
       5: aload_1
       6: ldc           #23                 // String oneOff1
       8: invokestatic  #47                 // Method getHistory:(Lorg/jboss/as/patching/tests/PatchingTestBuilder;Ljava/lang/String;)Ljava/io/File;
      11: astore_2
      12: aload_2
      13: invokestatic  #48                 // Method org/jboss/as/patching/IoUtils.recursiveDelete:(Ljava/io/File;)Z
      16: pop
      17: aload_0
      18: ldc           #23                 // String oneOff1
      20: invokevirtual #49                 // Method cannotRollbackPatch:(Ljava/lang/String;)V
      23: return

  public void testSimpleMissingMiscFiles() throws java.lang.Exception;
    Code:
       0: aload_0
       1: invokevirtual #45                 // Method installOneOff:()Lorg/jboss/as/patching/tests/PatchingTestBuilder;
       4: astore_1
       5: aload_1
       6: ldc           #23                 // String oneOff1
       8: invokestatic  #47                 // Method getHistory:(Lorg/jboss/as/patching/tests/PatchingTestBuilder;Ljava/lang/String;)Ljava/io/File;
      11: astore_2
      12: new           #50                 // class java/io/File
      15: dup
      16: aload_2
      17: ldc           #51                 // String misc
      19: invokespecial #52                 // Method java/io/File."<init>":(Ljava/io/File;Ljava/lang/String;)V
      22: astore_3
      23: aload_3
      24: invokestatic  #48                 // Method org/jboss/as/patching/IoUtils.recursiveDelete:(Ljava/io/File;)Z
      27: pop
      28: aload_0
      29: ldc           #23                 // String oneOff1
      31: invokevirtual #49                 // Method cannotRollbackPatch:(Ljava/lang/String;)V
      34: return

  public void testSimpleMissingRollbackXml() throws java.lang.Exception;
    Code:
       0: aload_0
       1: invokevirtual #45                 // Method installOneOff:()Lorg/jboss/as/patching/tests/PatchingTestBuilder;
       4: astore_1
       5: aload_1
       6: ldc           #23                 // String oneOff1
       8: invokestatic  #47                 // Method getHistory:(Lorg/jboss/as/patching/tests/PatchingTestBuilder;Ljava/lang/String;)Ljava/io/File;
      11: astore_2
      12: new           #50                 // class java/io/File
      15: dup
      16: aload_2
      17: ldc           #53                 // String rollback.xml
      19: invokespecial #52                 // Method java/io/File."<init>":(Ljava/io/File;Ljava/lang/String;)V
      22: astore_3
      23: aload_3
      24: invokevirtual #54                 // Method java/io/File.delete:()Z
      27: pop
      28: aload_0
      29: ldc           #23                 // String oneOff1
      31: invokevirtual #49                 // Method cannotRollbackPatch:(Ljava/lang/String;)V
      34: return

  public void testMissingHistoryOneOff() throws java.lang.Exception;
    Code:
       0: aload_0
       1: invokevirtual #2                  // Method installOneOffCpOneOff:()Lorg/jboss/as/patching/tests/PatchingTestBuilder;
       4: astore_1
       5: ldc           #23                 // String oneOff1
       7: aload_0
       8: invokevirtual #5                  // Method updateInstallationManager:()Lorg/jboss/as/patching/installation/InstallationManager;
      11: invokestatic  #46                 // Method org/jboss/as/patching/validation/PatchHistoryValidations.validateRollbackState:(Ljava/lang/String;Lorg/jboss/as/patching/installation/InstalledIdentity;)V
      14: aload_1
      15: ldc           #23                 // String oneOff1
      17: invokestatic  #47                 // Method getHistory:(Lorg/jboss/as/patching/tests/PatchingTestBuilder;Ljava/lang/String;)Ljava/io/File;
      20: astore_2
      21: aload_2
      22: invokestatic  #48                 // Method org/jboss/as/patching/IoUtils.recursiveDelete:(Ljava/io/File;)Z
      25: pop
      26: aload_0
      27: ldc           #23                 // String oneOff1
      29: invokevirtual #49                 // Method cannotRollbackPatch:(Ljava/lang/String;)V
      32: ldc           #22                 // String cp1
      34: aload_0
      35: invokevirtual #5                  // Method updateInstallationManager:()Lorg/jboss/as/patching/installation/InstallationManager;
      38: invokestatic  #46                 // Method org/jboss/as/patching/validation/PatchHistoryValidations.validateRollbackState:(Ljava/lang/String;Lorg/jboss/as/patching/installation/InstalledIdentity;)V
      41: aload_1
      42: ldc           #22                 // String cp1
      44: invokestatic  #47                 // Method getHistory:(Lorg/jboss/as/patching/tests/PatchingTestBuilder;Ljava/lang/String;)Ljava/io/File;
      47: astore_3
      48: aload_3
      49: invokestatic  #48                 // Method org/jboss/as/patching/IoUtils.recursiveDelete:(Ljava/io/File;)Z
      52: pop
      53: aload_0
      54: ldc           #22                 // String cp1
      56: invokevirtual #49                 // Method cannotRollbackPatch:(Ljava/lang/String;)V
      59: ldc           #21                 // String oneOff2
      61: aload_0
      62: invokevirtual #5                  // Method updateInstallationManager:()Lorg/jboss/as/patching/installation/InstallationManager;
      65: invokestatic  #46                 // Method org/jboss/as/patching/validation/PatchHistoryValidations.validateRollbackState:(Ljava/lang/String;Lorg/jboss/as/patching/installation/InstalledIdentity;)V
      68: return

  public void testMissingOverlay() throws java.lang.Exception;
    Code:
       0: aload_0
       1: invokevirtual #2                  // Method installOneOffCpOneOff:()Lorg/jboss/as/patching/tests/PatchingTestBuilder;
       4: astore_1
       5: ldc           #23                 // String oneOff1
       7: aload_0
       8: invokevirtual #5                  // Method updateInstallationManager:()Lorg/jboss/as/patching/installation/InstallationManager;
      11: invokestatic  #46                 // Method org/jboss/as/patching/validation/PatchHistoryValidations.validateRollbackState:(Ljava/lang/String;Lorg/jboss/as/patching/installation/InstalledIdentity;)V
      14: aload_1
      15: ldc           #55                 // String base
      17: ldc           #28                 // String base-oneOff1
      19: invokestatic  #56                 // Method getOverlays:(Lorg/jboss/as/patching/tests/PatchingTestBuilder;Ljava/lang/String;Ljava/lang/String;)Ljava/io/File;
      22: astore_2
      23: aload_2
      24: invokestatic  #48                 // Method org/jboss/as/patching/IoUtils.recursiveDelete:(Ljava/io/File;)Z
      27: pop
      28: aload_0
      29: ldc           #23                 // String oneOff1
      31: invokevirtual #49                 // Method cannotRollbackPatch:(Ljava/lang/String;)V
      34: aload_0
      35: ldc           #22                 // String cp1
      37: invokevirtual #49                 // Method cannotRollbackPatch:(Ljava/lang/String;)V
      40: return

  protected void cannotRollbackPatch(java.lang.String) throws java.lang.Exception;
    Code:
       0: aload_1
       1: aload_0
       2: invokevirtual #5                  // Method updateInstallationManager:()Lorg/jboss/as/patching/installation/InstallationManager;
       5: invokestatic  #46                 // Method org/jboss/as/patching/validation/PatchHistoryValidations.validateRollbackState:(Ljava/lang/String;Lorg/jboss/as/patching/installation/InstalledIdentity;)V
       8: new           #57                 // class java/lang/StringBuilder
      11: dup
      12: invokespecial #58                 // Method java/lang/StringBuilder."<init>":()V
      15: ldc           #59                 // String should not be able to rollback
      17: invokevirtual #60                 // Method java/lang/StringBuilder.append:(Ljava/lang/String;)Ljava/lang/StringBuilder;
      20: aload_1
      21: invokevirtual #60                 // Method java/lang/StringBuilder.append:(Ljava/lang/String;)Ljava/lang/StringBuilder;
      24: invokevirtual #61                 // Method java/lang/StringBuilder.toString:()Ljava/lang/String;
      27: invokestatic  #62                 // Method org/junit/Assert.fail:(Ljava/lang/String;)V
      30: goto          40
      33: astore_2
      34: goto          40
      37: astore_2
      38: aload_2
      39: athrow
      40: return
    Exception table:
       from    to  target type
           0    30    33   Class org/jboss/as/patching/PatchingException
           0    30    37   Class java/lang/Exception

  protected org.jboss.as.patching.tests.PatchingTestBuilder installOneOffCpOneOff() throws java.io.IOException, org.jboss.as.patching.PatchingException;
    Code:
       0: aload_0
       1: invokevirtual #65                 // Method createDefaultBuilder:()Lorg/jboss/as/patching/tests/PatchingTestBuilder;
       4: astore_1
       5: bipush        20
       7: newarray       byte
       9: astore_2
      10: bipush        20
      12: newarray       byte
      14: astore_3
      15: aload_1
      16: getstatic     #66                 // Field FILE_EXISTING:[Ljava/lang/String;
      19: invokevirtual #67                 // Method org/jboss/as/patching/tests/PatchingTestBuilder.getFile:([Ljava/lang/String;)Ljava/io/File;
      22: astore        4
      24: aload         4
      26: iconst_0
      27: anewarray     #20                 // class java/lang/String
      30: invokestatic  #68                 // Method org/jboss/as/patching/runner/TestUtils.touch:(Ljava/io/File;[Ljava/lang/String;)Ljava/io/File;
      33: pop
      34: aload         4
      36: invokestatic  #69                 // Method org/jboss/as/patching/runner/TestUtils.randomString:()Ljava/lang/String;
      39: invokestatic  #70                 // Method org/jboss/as/patching/runner/TestUtils.dump:(Ljava/io/File;Ljava/lang/String;)V
      42: aload         4
      44: invokestatic  #71                 // Method org/jboss/as/patching/HashUtils.hashFile:(Ljava/io/File;)[B
      47: astore        5
      49: aload         5
      51: aload         5
      53: arraylength
      54: invokestatic  #72                 // Method java/util/Arrays.copyOf:([BI)[B
      57: astore        6
      59: aload_1
      60: invokevirtual #73                 // Method org/jboss/as/patching/tests/PatchingTestBuilder.createStepBuilder:()Lorg/jboss/as/patching/tests/PatchingTestStepBuilder;
      63: astore        7
      65: aload         7
      67: ldc           #23                 // String oneOff1
      69: invokevirtual #74                 // Method org/jboss/as/patching/tests/PatchingTestStepBuilder.setPatchId:(Ljava/lang/String;)Lorg/jboss/as/patching/tests/PatchingTestStepBuilder;
      72: ldc           #75                 // String 6.2.0.GA
      74: invokevirtual #76                 // Method org/jboss/as/patching/tests/PatchingTestStepBuilder.oneOffPatchIdentity:(Ljava/lang/String;)Lorg/jboss/as/patching/tests/PatchingTestStepBuilder;
      77: ldc           #28                 // String base-oneOff1
      79: ldc           #55                 // String base
      81: iconst_0
      82: invokevirtual #77                 // Method org/jboss/as/patching/tests/PatchingTestStepBuilder.oneOffPatchElement:(Ljava/lang/String;Ljava/lang/String;Z)Lorg/jboss/as/patching/tests/PatchElementTestStepBuilder;
      85: ldc           #78                 // String org.jboss.test
      87: aload_3
      88: invokevirtual #79                 // Method org/jboss/as/patching/tests/PatchElementTestStepBuilder.addModuleWithRandomContent:(Ljava/lang/String;[B)Ljava/lang/Object;
      91: checkcast     #80                 // class org/jboss/as/patching/tests/PatchElementTestStepBuilder
      94: invokevirtual #81                 // Method org/jboss/as/patching/tests/PatchElementTestStepBuilder.getParent:()Lorg/jboss/as/patching/tests/PatchingTestStepBuilder;
      97: aload_2
      98: getstatic     #82                 // Field FILE_ONE:[Ljava/lang/String;
     101: invokevirtual #83                 // Method org/jboss/as/patching/tests/PatchingTestStepBuilder.addFileWithRandomContent:([B[Ljava/lang/String;)Ljava/lang/Object;
     104: checkcast     #84                 // class org/jboss/as/patching/tests/PatchingTestStepBuilder
     107: aload         5
     109: aload         5
     111: arraylength
     112: invokestatic  #72                 // Method java/util/Arrays.copyOf:([BI)[B
     115: aload         5
     117: getstatic     #66                 // Field FILE_EXISTING:[Ljava/lang/String;
     120: invokevirtual #85                 // Method org/jboss/as/patching/tests/PatchingTestStepBuilder.updateFileWithRandomContent:([B[B[Ljava/lang/String;)Ljava/lang/Object;
     123: pop
     124: aload_0
     125: aload         7
     127: invokevirtual #86                 // Method apply:(Lorg/jboss/as/patching/tests/PatchingTestStepBuilder;)Lorg/jboss/as/patching/tool/PatchingResult;
     130: pop
     131: aload_1
     132: invokevirtual #73                 // Method org/jboss/as/patching/tests/PatchingTestBuilder.createStepBuilder:()Lorg/jboss/as/patching/tests/PatchingTestStepBuilder;
     135: astore        8
     137: aload         8
     139: ldc           #22                 // String cp1
     141: invokevirtual #74                 // Method org/jboss/as/patching/tests/PatchingTestStepBuilder.setPatchId:(Ljava/lang/String;)Lorg/jboss/as/patching/tests/PatchingTestStepBuilder;
     144: ldc           #75                 // String 6.2.0.GA
     146: ldc           #75                 // String 6.2.0.GA
     148: invokevirtual #87                 // Method org/jboss/as/patching/tests/PatchingTestStepBuilder.upgradeIdentity:(Ljava/lang/String;Ljava/lang/String;)Lorg/jboss/as/patching/tests/PatchingTestStepBuilder;
     151: ldc           #27                 // String base-cp1
     153: ldc           #55                 // String base
     155: iconst_0
     156: invokevirtual #88                 // Method org/jboss/as/patching/tests/PatchingTestStepBuilder.upgradeElement:(Ljava/lang/String;Ljava/lang/String;Z)Lorg/jboss/as/patching/tests/PatchElementTestStepBuilder;
     159: ldc           #78                 // String org.jboss.test
     161: aload_3
     162: aload_3
     163: arraylength
     164: invokestatic  #72                 // Method java/util/Arrays.copyOf:([BI)[B
     167: aload_3
     168: invokevirtual #89                 // Method org/jboss/as/patching/tests/PatchElementTestStepBuilder.updateModuleWithRandomContent:(Ljava/lang/String;[B[B)Ljava/lang/Object;
     171: checkcast     #80                 // class org/jboss/as/patching/tests/PatchElementTestStepBuilder
     174: invokevirtual #81                 // Method org/jboss/as/patching/tests/PatchElementTestStepBuilder.getParent:()Lorg/jboss/as/patching/tests/PatchingTestStepBuilder;
     177: aload_2
     178: aload_2
     179: arraylength
     180: invokestatic  #72                 // Method java/util/Arrays.copyOf:([BI)[B
     183: aload_2
     184: getstatic     #82                 // Field FILE_ONE:[Ljava/lang/String;
     187: invokevirtual #85                 // Method org/jboss/as/patching/tests/PatchingTestStepBuilder.updateFileWithRandomContent:([B[B[Ljava/lang/String;)Ljava/lang/Object;
     190: checkcast     #84                 // class org/jboss/as/patching/tests/PatchingTestStepBuilder
     193: aload         6
     195: aload         5
     197: getstatic     #66                 // Field FILE_EXISTING:[Ljava/lang/String;
     200: invokevirtual #85                 // Method org/jboss/as/patching/tests/PatchingTestStepBuilder.updateFileWithRandomContent:([B[B[Ljava/lang/String;)Ljava/lang/Object;
     203: pop
     204: aload_0
     205: aload         8
     207: invokevirtual #86                 // Method apply:(Lorg/jboss/as/patching/tests/PatchingTestStepBuilder;)Lorg/jboss/as/patching/tool/PatchingResult;
     210: pop
     211: aload_1
     212: invokevirtual #73                 // Method org/jboss/as/patching/tests/PatchingTestBuilder.createStepBuilder:()Lorg/jboss/as/patching/tests/PatchingTestStepBuilder;
     215: astore        9
     217: aload         9
     219: ldc           #21                 // String oneOff2
     221: invokevirtual #74                 // Method org/jboss/as/patching/tests/PatchingTestStepBuilder.setPatchId:(Ljava/lang/String;)Lorg/jboss/as/patching/tests/PatchingTestStepBuilder;
     224: ldc           #75                 // String 6.2.0.GA
     226: invokevirtual #76                 // Method org/jboss/as/patching/tests/PatchingTestStepBuilder.oneOffPatchIdentity:(Ljava/lang/String;)Lorg/jboss/as/patching/tests/PatchingTestStepBuilder;
     229: ldc           #26                 // String base-oneOff2
     231: ldc           #55                 // String base
     233: iconst_0
     234: invokevirtual #77                 // Method org/jboss/as/patching/tests/PatchingTestStepBuilder.oneOffPatchElement:(Ljava/lang/String;Ljava/lang/String;Z)Lorg/jboss/as/patching/tests/PatchElementTestStepBuilder;
     237: ldc           #78                 // String org.jboss.test
     239: aload_3
     240: aconst_null
     241: invokevirtual #89                 // Method org/jboss/as/patching/tests/PatchElementTestStepBuilder.updateModuleWithRandomContent:(Ljava/lang/String;[B[B)Ljava/lang/Object;
     244: checkcast     #80                 // class org/jboss/as/patching/tests/PatchElementTestStepBuilder
     247: invokevirtual #81                 // Method org/jboss/as/patching/tests/PatchElementTestStepBuilder.getParent:()Lorg/jboss/as/patching/tests/PatchingTestStepBuilder;
     250: aload_2
     251: aconst_null
     252: getstatic     #82                 // Field FILE_ONE:[Ljava/lang/String;
     255: invokevirtual #85                 // Method org/jboss/as/patching/tests/PatchingTestStepBuilder.updateFileWithRandomContent:([B[B[Ljava/lang/String;)Ljava/lang/Object;
     258: checkcast     #84                 // class org/jboss/as/patching/tests/PatchingTestStepBuilder
     261: aload         5
     263: aload         5
     265: arraylength
     266: invokestatic  #72                 // Method java/util/Arrays.copyOf:([BI)[B
     269: aload         5
     271: getstatic     #66                 // Field FILE_EXISTING:[Ljava/lang/String;
     274: invokevirtual #85                 // Method org/jboss/as/patching/tests/PatchingTestStepBuilder.updateFileWithRandomContent:([B[B[Ljava/lang/String;)Ljava/lang/Object;
     277: pop
     278: aload_0
     279: aload         9
     281: invokevirtual #86                 // Method apply:(Lorg/jboss/as/patching/tests/PatchingTestStepBuilder;)Lorg/jboss/as/patching/tool/PatchingResult;
     284: pop
     285: aload_1
     286: areturn

  protected org.jboss.as.patching.tests.PatchingTestBuilder installOneOff() throws java.lang.Exception;
    Code:
       0: aload_0
       1: invokevirtual #65                 // Method createDefaultBuilder:()Lorg/jboss/as/patching/tests/PatchingTestBuilder;
       4: astore_1
       5: bipush        20
       7: newarray       byte
       9: astore_2
      10: bipush        20
      12: newarray       byte
      14: astore_3
      15: aload_1
      16: getstatic     #66                 // Field FILE_EXISTING:[Ljava/lang/String;
      19: invokevirtual #67                 // Method org/jboss/as/patching/tests/PatchingTestBuilder.getFile:([Ljava/lang/String;)Ljava/io/File;
      22: astore        4
      24: aload         4
      26: iconst_0
      27: anewarray     #20                 // class java/lang/String
      30: invokestatic  #68                 // Method org/jboss/as/patching/runner/TestUtils.touch:(Ljava/io/File;[Ljava/lang/String;)Ljava/io/File;
      33: pop
      34: aload         4
      36: invokestatic  #69                 // Method org/jboss/as/patching/runner/TestUtils.randomString:()Ljava/lang/String;
      39: invokestatic  #70                 // Method org/jboss/as/patching/runner/TestUtils.dump:(Ljava/io/File;Ljava/lang/String;)V
      42: aload         4
      44: invokestatic  #71                 // Method org/jboss/as/patching/HashUtils.hashFile:(Ljava/io/File;)[B
      47: astore        5
      49: aload         5
      51: aload         5
      53: arraylength
      54: invokestatic  #72                 // Method java/util/Arrays.copyOf:([BI)[B
      57: astore        6
      59: aload_1
      60: invokevirtual #73                 // Method org/jboss/as/patching/tests/PatchingTestBuilder.createStepBuilder:()Lorg/jboss/as/patching/tests/PatchingTestStepBuilder;
      63: astore        7
      65: aload         7
      67: ldc           #23                 // String oneOff1
      69: invokevirtual #74                 // Method org/jboss/as/patching/tests/PatchingTestStepBuilder.setPatchId:(Ljava/lang/String;)Lorg/jboss/as/patching/tests/PatchingTestStepBuilder;
      72: ldc           #75                 // String 6.2.0.GA
      74: invokevirtual #76                 // Method org/jboss/as/patching/tests/PatchingTestStepBuilder.oneOffPatchIdentity:(Ljava/lang/String;)Lorg/jboss/as/patching/tests/PatchingTestStepBuilder;
      77: ldc           #28                 // String base-oneOff1
      79: ldc           #55                 // String base
      81: iconst_0
      82: invokevirtual #77                 // Method org/jboss/as/patching/tests/PatchingTestStepBuilder.oneOffPatchElement:(Ljava/lang/String;Ljava/lang/String;Z)Lorg/jboss/as/patching/tests/PatchElementTestStepBuilder;
      85: ldc           #78                 // String org.jboss.test
      87: aload_3
      88: invokevirtual #79                 // Method org/jboss/as/patching/tests/PatchElementTestStepBuilder.addModuleWithRandomContent:(Ljava/lang/String;[B)Ljava/lang/Object;
      91: checkcast     #80                 // class org/jboss/as/patching/tests/PatchElementTestStepBuilder
      94: invokevirtual #81                 // Method org/jboss/as/patching/tests/PatchElementTestStepBuilder.getParent:()Lorg/jboss/as/patching/tests/PatchingTestStepBuilder;
      97: aload_2
      98: getstatic     #82                 // Field FILE_ONE:[Ljava/lang/String;
     101: invokevirtual #83                 // Method org/jboss/as/patching/tests/PatchingTestStepBuilder.addFileWithRandomContent:([B[Ljava/lang/String;)Ljava/lang/Object;
     104: checkcast     #84                 // class org/jboss/as/patching/tests/PatchingTestStepBuilder
     107: aload         5
     109: aload         5
     111: arraylength
     112: invokestatic  #72                 // Method java/util/Arrays.copyOf:([BI)[B
     115: aload         5
     117: getstatic     #66                 // Field FILE_EXISTING:[Ljava/lang/String;
     120: invokevirtual #85                 // Method org/jboss/as/patching/tests/PatchingTestStepBuilder.updateFileWithRandomContent:([B[B[Ljava/lang/String;)Ljava/lang/Object;
     123: pop
     124: aload_0
     125: aload         7
     127: invokevirtual #86                 // Method apply:(Lorg/jboss/as/patching/tests/PatchingTestStepBuilder;)Lorg/jboss/as/patching/tool/PatchingResult;
     130: pop
     131: aload_1
     132: areturn

  static java.io.File getHistory(org.jboss.as.patching.tests.PatchingTestBuilder, java.lang.String);
    Code:
       0: aload_0
       1: iconst_3
       2: anewarray     #20                 // class java/lang/String
       5: dup
       6: iconst_0
       7: ldc           #90                 // String .installation
       9: aastore
      10: dup
      11: iconst_1
      12: ldc           #91                 // String patches
      14: aastore
      15: dup
      16: iconst_2
      17: aload_1
      18: aastore
      19: invokevirtual #67                 // Method org/jboss/as/patching/tests/PatchingTestBuilder.getFile:([Ljava/lang/String;)Ljava/io/File;
      22: areturn

  static java.io.File getOverlays(org.jboss.as.patching.tests.PatchingTestBuilder, java.lang.String, java.lang.String);
    Code:
       0: aload_0
       1: bipush        6
       3: anewarray     #20                 // class java/lang/String
       6: dup
       7: iconst_0
       8: ldc           #92                 // String modules
      10: aastore
      11: dup
      12: iconst_1
      13: ldc           #93                 // String system
      15: aastore
      16: dup
      17: iconst_2
      18: ldc           #94                 // String layers
      20: aastore
      21: dup
      22: iconst_3
      23: aload_1
      24: aastore
      25: dup
      26: iconst_4
      27: ldc           #95                 // String .overlays
      29: aastore
      30: dup
      31: iconst_5
      32: aload_2
      33: aastore
      34: invokevirtual #67                 // Method org/jboss/as/patching/tests/PatchingTestBuilder.getFile:([Ljava/lang/String;)Ljava/io/File;
      37: areturn

  static {};
    Code:
       0: iconst_2
       1: anewarray     #20                 // class java/lang/String
       4: dup
       5: iconst_0
       6: ldc           #96                 // String bin
       8: aastore
       9: dup
      10: iconst_1
      11: ldc           #97                 // String standalone.sh
      13: aastore
      14: putstatic     #82                 // Field FILE_ONE:[Ljava/lang/String;
      17: iconst_2
      18: anewarray     #20                 // class java/lang/String
      21: dup
      22: iconst_0
      23: ldc           #96                 // String bin
      25: aastore
      26: dup
      27: iconst_1
      28: ldc           #98                 // String standalone.conf
      30: aastore
      31: putstatic     #99                 // Field FILE_TWO:[Ljava/lang/String;
      34: iconst_2
      35: anewarray     #20                 // class java/lang/String
      38: dup
      39: iconst_0
      40: ldc           #96                 // String bin
      42: aastore
      43: dup
      44: iconst_1
      45: ldc           #100                // String test
      47: aastore
      48: putstatic     #66                 // Field FILE_EXISTING:[Ljava/lang/String;
      51: return
}
