Compiled from "LengthTrackingAppendableImpl.java"
public class com.vladsch.flexmark.util.html.LengthTrackingAppendableImpl implements com.vladsch.flexmark.util.html.LengthTrackingAppendable {
  private final java.lang.Appendable myAppendable;

  private int myLength;

  public com.vladsch.flexmark.util.html.LengthTrackingAppendableImpl(java.lang.Appendable);
    Code:
       0: aload_0
       1: invokespecial #1                  // Method java/lang/Object."<init>":()V
       4: aload_0
       5: aload_1
       6: putfield      #2                  // Field myAppendable:Ljava/lang/Appendable;
       9: aload_0
      10: iconst_0
      11: putfield      #3                  // Field myLength:I
      14: return

  public int getLength();
    Code:
       0: aload_0
       1: getfield      #3                  // Field myLength:I
       4: ireturn

  public com.vladsch.flexmark.util.html.LengthTrackingAppendable append(java.lang.CharSequence) throws java.io.IOException;
    Code:
       0: aload_0
       1: getfield      #2                  // Field myAppendable:Ljava/lang/Appendable;
       4: aload_1
       5: invokeinterface #4,  2            // InterfaceMethod java/lang/Appendable.append:(Ljava/lang/CharSequence;)Ljava/lang/Appendable;
      10: pop
      11: aload_0
      12: dup
      13: getfield      #3                  // Field myLength:I
      16: aload_1
      17: invokeinterface #5,  1            // InterfaceMethod java/lang/CharSequence.length:()I
      22: iadd
      23: putfield      #3                  // Field myLength:I
      26: aload_0
      27: areturn

  public com.vladsch.flexmark.util.html.LengthTrackingAppendable append(java.lang.CharSequence, int, int) throws java.io.IOException;
    Code:
       0: aload_0
       1: getfield      #2                  // Field myAppendable:Ljava/lang/Appendable;
       4: aload_1
       5: iload_2
       6: iload_3
       7: invokeinterface #6,  4            // InterfaceMethod java/lang/Appendable.append:(Ljava/lang/CharSequence;II)Ljava/lang/Appendable;
      12: pop
      13: aload_0
      14: dup
      15: getfield      #3                  // Field myLength:I
      18: iload_3
      19: iload_2
      20: isub
      21: iadd
      22: putfield      #3                  // Field myLength:I
      25: aload_0
      26: areturn

  public com.vladsch.flexmark.util.html.LengthTrackingAppendable append(char) throws java.io.IOException;
    Code:
       0: aload_0
       1: getfield      #2                  // Field myAppendable:Ljava/lang/Appendable;
       4: iload_1
       5: invokeinterface #7,  2            // InterfaceMethod java/lang/Appendable.append:(C)Ljava/lang/Appendable;
      10: pop
      11: aload_0
      12: dup
      13: getfield      #3                  // Field myLength:I
      16: iconst_1
      17: iadd
      18: putfield      #3                  // Field myLength:I
      21: aload_0
      22: areturn

  public java.lang.Appendable getAppendable();
    Code:
       0: aload_0
       1: getfield      #2                  // Field myAppendable:Ljava/lang/Appendable;
       4: areturn

  public static com.vladsch.flexmark.util.html.LengthTrackingAppendable of(java.lang.Appendable);
    Code:
       0: new           #8                  // class com/vladsch/flexmark/util/html/LengthTrackingAppendableImpl
       3: dup
       4: aload_0
       5: invokespecial #9                  // Method "<init>":(Ljava/lang/Appendable;)V
       8: areturn

  public java.lang.String toString();
    Code:
       0: aload_0
       1: getfield      #2                  // Field myAppendable:Ljava/lang/Appendable;
       4: invokevirtual #10                 // Method java/lang/Object.toString:()Ljava/lang/String;
       7: areturn

  public java.lang.Appendable append(char) throws java.io.IOException;
    Code:
       0: aload_0
       1: iload_1
       2: invokevirtual #11                 // Method append:(C)Lcom/vladsch/flexmark/util/html/LengthTrackingAppendable;
       5: areturn

  public java.lang.Appendable append(java.lang.CharSequence, int, int) throws java.io.IOException;
    Code:
       0: aload_0
       1: aload_1
       2: iload_2
       3: iload_3
       4: invokevirtual #12                 // Method append:(Ljava/lang/CharSequence;II)Lcom/vladsch/flexmark/util/html/LengthTrackingAppendable;
       7: areturn

  public java.lang.Appendable append(java.lang.CharSequence) throws java.io.IOException;
    Code:
       0: aload_0
       1: aload_1
       2: invokevirtual #13                 // Method append:(Ljava/lang/CharSequence;)Lcom/vladsch/flexmark/util/html/LengthTrackingAppendable;
       5: areturn
}
