Compiled from "AeronErrorLog.java"
public class akka.remote.artery.AeronErrorLog {
  private final java.io.File cncFile;

  final java.nio.MappedByteBuffer cncByteBuffer;

  final org.agrona.DirectBuffer cncMetaDataBuffer;

  final int cncVersion;

  final org.agrona.concurrent.AtomicBuffer buffer;

  final java.text.SimpleDateFormat dateFormat;

  public akka.remote.artery.AeronErrorLog(java.io.File);
    Code:
       0: aload_0
       1: invokespecial #1                  // Method java/lang/Object."<init>":()V
       4: aload_0
       5: aload_1
       6: putfield      #2                  // Field cncFile:Ljava/io/File;
       9: aload_0
      10: aload_1
      11: ldc           #3                  // String cnc
      13: invokestatic  #4                  // Method org/agrona/IoUtil.mapExistingFile:(Ljava/io/File;Ljava/lang/String;)Ljava/nio/MappedByteBuffer;
      16: putfield      #5                  // Field cncByteBuffer:Ljava/nio/MappedByteBuffer;
      19: aload_0
      20: aload_0
      21: getfield      #5                  // Field cncByteBuffer:Ljava/nio/MappedByteBuffer;
      24: invokestatic  #6                  // Method io/aeron/CncFileDescriptor.createMetaDataBuffer:(Ljava/nio/ByteBuffer;)Lorg/agrona/concurrent/UnsafeBuffer;
      27: putfield      #7                  // Field cncMetaDataBuffer:Lorg/agrona/DirectBuffer;
      30: aload_0
      31: aload_0
      32: getfield      #7                  // Field cncMetaDataBuffer:Lorg/agrona/DirectBuffer;
      35: iconst_0
      36: invokestatic  #8                  // Method io/aeron/CncFileDescriptor.cncVersionOffset:(I)I
      39: invokeinterface #9,  2            // InterfaceMethod org/agrona/DirectBuffer.getInt:(I)I
      44: putfield      #10                 // Field cncVersion:I
      47: aload_0
      48: aload_0
      49: getfield      #5                  // Field cncByteBuffer:Ljava/nio/MappedByteBuffer;
      52: aload_0
      53: getfield      #7                  // Field cncMetaDataBuffer:Lorg/agrona/DirectBuffer;
      56: invokestatic  #11                 // Method io/aeron/CncFileDescriptor.createErrorLogBuffer:(Ljava/nio/ByteBuffer;Lorg/agrona/DirectBuffer;)Lorg/agrona/concurrent/UnsafeBuffer;
      59: putfield      #12                 // Field buffer:Lorg/agrona/concurrent/AtomicBuffer;
      62: aload_0
      63: new           #13                 // class java/text/SimpleDateFormat
      66: dup
      67: ldc           #14                 // String yyyy-MM-dd HH:mm:ss.SSSZ
      69: invokespecial #15                 // Method java/text/SimpleDateFormat."<init>":(Ljava/lang/String;)V
      72: putfield      #16                 // Field dateFormat:Ljava/text/SimpleDateFormat;
      75: iconst_5
      76: aload_0
      77: getfield      #10                 // Field cncVersion:I
      80: if_icmpeq     120
      83: aload_0
      84: getfield      #5                  // Field cncByteBuffer:Ljava/nio/MappedByteBuffer;
      87: invokestatic  #18                 // Method org/agrona/IoUtil.unmap:(Ljava/nio/MappedByteBuffer;)V
      90: new           #19                 // class java/lang/IllegalStateException
      93: dup
      94: new           #20                 // class java/lang/StringBuilder
      97: dup
      98: invokespecial #21                 // Method java/lang/StringBuilder."<init>":()V
     101: ldc           #22                 // String CNC version not supported: file version=
     103: invokevirtual #23                 // Method java/lang/StringBuilder.append:(Ljava/lang/String;)Ljava/lang/StringBuilder;
     106: aload_0
     107: getfield      #10                 // Field cncVersion:I
     110: invokevirtual #24                 // Method java/lang/StringBuilder.append:(I)Ljava/lang/StringBuilder;
     113: invokevirtual #25                 // Method java/lang/StringBuilder.toString:()Ljava/lang/String;
     116: invokespecial #26                 // Method java/lang/IllegalStateException."<init>":(Ljava/lang/String;)V
     119: athrow
     120: return

  public long logErrors(akka.event.LoggingAdapter, long);
    Code:
       0: new           #27                 // class java/util/concurrent/atomic/AtomicLong
       3: dup
       4: lload_2
       5: invokespecial #28                 // Method java/util/concurrent/atomic/AtomicLong."<init>":(J)V
       8: astore        4
      10: aload_0
      11: getfield      #12                 // Field buffer:Lorg/agrona/concurrent/AtomicBuffer;
      14: aload_0
      15: aload_1
      16: aload         4
      18: invokedynamic #29,  0             // InvokeDynamic #0:accept:(Lakka/remote/artery/AeronErrorLog;Lakka/event/LoggingAdapter;Ljava/util/concurrent/atomic/AtomicLong;)Lorg/agrona/concurrent/errors/ErrorConsumer;
      23: lload_2
      24: invokestatic  #30                 // Method org/agrona/concurrent/errors/ErrorLogReader.read:(Lorg/agrona/concurrent/AtomicBuffer;Lorg/agrona/concurrent/errors/ErrorConsumer;J)I
      27: pop
      28: aload         4
      30: invokevirtual #31                 // Method java/util/concurrent/atomic/AtomicLong.get:()J
      33: lreturn

  public void close();
    Code:
       0: aload_0
       1: getfield      #5                  // Field cncByteBuffer:Ljava/nio/MappedByteBuffer;
       4: invokestatic  #18                 // Method org/agrona/IoUtil.unmap:(Ljava/nio/MappedByteBuffer;)V
       7: return

  private void lambda$logErrors$0(akka.event.LoggingAdapter, java.util.concurrent.atomic.AtomicLong, int, long, long, java.lang.String);
    Code:
       0: aload_1
       1: ldc           #32                 // String Aeron error: %d observations from %s to %s for:%n %s
       3: iconst_4
       4: anewarray     #33                 // class java/lang/Object
       7: dup
       8: iconst_0
       9: iload_3
      10: invokestatic  #34                 // Method java/lang/Integer.valueOf:(I)Ljava/lang/Integer;
      13: aastore
      14: dup
      15: iconst_1
      16: aload_0
      17: getfield      #16                 // Field dateFormat:Ljava/text/SimpleDateFormat;
      20: new           #35                 // class java/util/Date
      23: dup
      24: lload         4
      26: invokespecial #36                 // Method java/util/Date."<init>":(J)V
      29: invokevirtual #37                 // Method java/text/SimpleDateFormat.format:(Ljava/util/Date;)Ljava/lang/String;
      32: aastore
      33: dup
      34: iconst_2
      35: aload_0
      36: getfield      #16                 // Field dateFormat:Ljava/text/SimpleDateFormat;
      39: new           #35                 // class java/util/Date
      42: dup
      43: lload         6
      45: invokespecial #36                 // Method java/util/Date."<init>":(J)V
      48: invokevirtual #37                 // Method java/text/SimpleDateFormat.format:(Ljava/util/Date;)Ljava/lang/String;
      51: aastore
      52: dup
      53: iconst_3
      54: aload         8
      56: aastore
      57: invokestatic  #38                 // Method java/lang/String.format:(Ljava/lang/String;[Ljava/lang/Object;)Ljava/lang/String;
      60: invokeinterface #39,  2           // InterfaceMethod akka/event/LoggingAdapter.error:(Ljava/lang/String;)V
      65: aload_2
      66: aload_2
      67: invokevirtual #31                 // Method java/util/concurrent/atomic/AtomicLong.get:()J
      70: lload         6
      72: invokestatic  #40                 // Method java/lang/Math.max:(JJ)J
      75: invokevirtual #41                 // Method java/util/concurrent/atomic/AtomicLong.set:(J)V
      78: return
}
