Compiled from "ArterySettings.scala"
public final class akka.remote.artery.ArterySettings$Advanced$$anonfun$18 extends scala.runtime.AbstractFunction1<java.lang.String, java.lang.Object> implements scala.Serializable {
  public static final long serialVersionUID;

  private final akka.remote.artery.ArterySettings$Advanced$ $outer;

  public final boolean apply(java.lang.String);
    Code:
       0: aload_0
       1: getfield      #20                 // Field $outer:Lakka/remote/artery/ArterySettings$Advanced$;
       4: invokevirtual #24                 // Method akka/remote/artery/ArterySettings$Advanced$.EmbeddedMediaDriver:()Z
       7: ifne          30
      10: new           #26                 // class scala/collection/immutable/StringOps
      13: dup
      14: getstatic     #32                 // Field scala/Predef$.MODULE$:Lscala/Predef$;
      17: aload_1
      18: invokevirtual #36                 // Method scala/Predef$.augmentString:(Ljava/lang/String;)Ljava/lang/String;
      21: invokespecial #40                 // Method scala/collection/immutable/StringOps."<init>":(Ljava/lang/String;)V
      24: invokevirtual #43                 // Method scala/collection/immutable/StringOps.nonEmpty:()Z
      27: ifeq          34
      30: iconst_1
      31: goto          35
      34: iconst_0
      35: ireturn

  public final java.lang.Object apply(java.lang.Object);
    Code:
       0: aload_0
       1: aload_1
       2: checkcast     #50                 // class java/lang/String
       5: invokevirtual #52                 // Method apply:(Ljava/lang/String;)Z
       8: invokestatic  #58                 // Method scala/runtime/BoxesRunTime.boxToBoolean:(Z)Ljava/lang/Boolean;
      11: areturn

  public akka.remote.artery.ArterySettings$Advanced$$anonfun$18(akka.remote.artery.ArterySettings$Advanced$);
    Code:
       0: aload_1
       1: ifnonnull     6
       4: aconst_null
       5: athrow
       6: aload_0
       7: aload_1
       8: putfield      #20                 // Field $outer:Lakka/remote/artery/ArterySettings$Advanced$;
      11: aload_0
      12: invokespecial #64                 // Method scala/runtime/AbstractFunction1."<init>":()V
      15: return
}
