Compiled from "Association.scala"
public final class akka.remote.artery.Association$$anonfun$completeHandshake$2 extends scala.runtime.AbstractFunction1<akka.Done, akka.Done$> implements scala.Serializable {
  public static final long serialVersionUID;

  private final akka.remote.artery.Association $outer;

  private final akka.remote.UniqueAddress peer$1;

  private final akka.remote.artery.AssociationState current$1;

  public final akka.Done$ apply(akka.Done);
    Code:
       0: aload_0
       1: getfield      #27                 // Field current$1:Lakka/remote/artery/AssociationState;
       4: invokevirtual #33                 // Method akka/remote/artery/AssociationState.uniqueRemoteAddressPromise:()Lscala/concurrent/Promise;
       7: aload_0
       8: getfield      #35                 // Field peer$1:Lakka/remote/UniqueAddress;
      11: invokeinterface #41,  2           // InterfaceMethod scala/concurrent/Promise.trySuccess:(Ljava/lang/Object;)Z
      16: pop
      17: aload_0
      18: getfield      #27                 // Field current$1:Lakka/remote/artery/AssociationState;
      21: invokevirtual #45                 // Method akka/remote/artery/AssociationState.uniqueRemoteAddressValue:()Lscala/Option;
      24: astore_2
      25: aload_2
      26: instanceof    #47                 // class scala/Some
      29: ifeq          83
      32: aload_2
      33: checkcast     #47                 // class scala/Some
      36: astore_3
      37: aload_3
      38: invokevirtual #51                 // Method scala/Some.x:()Ljava/lang/Object;
      41: checkcast     #53                 // class akka/remote/UniqueAddress
      44: astore        4
      46: aload_0
      47: getfield      #35                 // Field peer$1:Lakka/remote/UniqueAddress;
      50: aload         4
      52: astore        5
      54: dup
      55: ifnonnull     67
      58: pop
      59: aload         5
      61: ifnull        75
      64: goto          83
      67: aload         5
      69: invokevirtual #58                 // Method java/lang/Object.equals:(Ljava/lang/Object;)Z
      72: ifeq          83
      75: getstatic     #64                 // Field scala/runtime/BoxedUnit.UNIT:Lscala/runtime/BoxedUnit;
      78: astore        6
      80: goto          263
      83: aload_0
      84: getfield      #27                 // Field current$1:Lakka/remote/artery/AssociationState;
      87: getstatic     #70                 // Field scala/concurrent/Promise$.MODULE$:Lscala/concurrent/Promise$;
      90: aload_0
      91: getfield      #35                 // Field peer$1:Lakka/remote/UniqueAddress;
      94: invokevirtual #74                 // Method scala/concurrent/Promise$.successful:(Ljava/lang/Object;)Lscala/concurrent/Promise;
      97: invokevirtual #78                 // Method akka/remote/artery/AssociationState.newIncarnation:(Lscala/concurrent/Promise;)Lakka/remote/artery/AssociationState;
     100: astore        7
     102: aload_0
     103: getfield      #80                 // Field $outer:Lakka/remote/artery/Association;
     106: aload_0
     107: getfield      #27                 // Field current$1:Lakka/remote/artery/AssociationState;
     110: aload         7
     112: invokevirtual #84                 // Method akka/remote/artery/Association.akka$remote$artery$Association$$swapState:(Lakka/remote/artery/AssociationState;Lakka/remote/artery/AssociationState;)Z
     115: ifeq          258
     118: aload_0
     119: getfield      #27                 // Field current$1:Lakka/remote/artery/AssociationState;
     122: invokevirtual #45                 // Method akka/remote/artery/AssociationState.uniqueRemoteAddressValue:()Lscala/Option;
     125: astore        8
     127: aload         8
     129: instanceof    #47                 // class scala/Some
     132: ifeq          226
     135: aload         8
     137: checkcast     #47                 // class scala/Some
     140: astore        9
     142: aload         9
     144: invokevirtual #51                 // Method scala/Some.x:()Ljava/lang/Object;
     147: checkcast     #53                 // class akka/remote/UniqueAddress
     150: astore        10
     152: aload_0
     153: getfield      #80                 // Field $outer:Lakka/remote/artery/Association;
     156: invokevirtual #88                 // Method akka/remote/artery/Association.akka$remote$artery$Association$$cancelIdleTimer:()V
     159: aload_0
     160: getfield      #80                 // Field $outer:Lakka/remote/artery/Association;
     163: invokevirtual #92                 // Method akka/remote/artery/Association.akka$remote$artery$Association$$log:()Lakka/event/LoggingAdapter;
     166: ldc           #94                 // String Incarnation {} of association to [{}] with new UID [{}] (old UID [{}])
     168: aload         7
     170: invokevirtual #98                 // Method akka/remote/artery/AssociationState.incarnation:()I
     173: invokestatic  #104                // Method scala/runtime/BoxesRunTime.boxToInteger:(I)Ljava/lang/Integer;
     176: aload_0
     177: getfield      #35                 // Field peer$1:Lakka/remote/UniqueAddress;
     180: invokevirtual #108                // Method akka/remote/UniqueAddress.address:()Lakka/actor/Address;
     183: aload_0
     184: getfield      #35                 // Field peer$1:Lakka/remote/UniqueAddress;
     187: invokevirtual #112                // Method akka/remote/UniqueAddress.uid:()J
     190: invokestatic  #116                // Method scala/runtime/BoxesRunTime.boxToLong:(J)Ljava/lang/Long;
     193: aload         10
     195: invokevirtual #112                // Method akka/remote/UniqueAddress.uid:()J
     198: invokestatic  #116                // Method scala/runtime/BoxesRunTime.boxToLong:(J)Ljava/lang/Long;
     201: invokeinterface #122,  6          // InterfaceMethod akka/event/LoggingAdapter.debug:(Ljava/lang/String;Ljava/lang/Object;Ljava/lang/Object;Ljava/lang/Object;Ljava/lang/Object;)V
     206: aload_0
     207: getfield      #80                 // Field $outer:Lakka/remote/artery/Association;
     210: aload         10
     212: invokevirtual #112                // Method akka/remote/UniqueAddress.uid:()J
     215: invokevirtual #126                // Method akka/remote/artery/Association.akka$remote$artery$Association$$clearInboundCompression:(J)V
     218: getstatic     #64                 // Field scala/runtime/BoxedUnit.UNIT:Lscala/runtime/BoxedUnit;
     221: astore        11
     223: goto          242
     226: getstatic     #131                // Field scala/None$.MODULE$:Lscala/None$;
     229: aload         8
     231: invokevirtual #58                 // Method java/lang/Object.equals:(Ljava/lang/Object;)Z
     234: ifeq          248
     237: getstatic     #64                 // Field scala/runtime/BoxedUnit.UNIT:Lscala/runtime/BoxedUnit;
     240: astore        11
     242: getstatic     #64                 // Field scala/runtime/BoxedUnit.UNIT:Lscala/runtime/BoxedUnit;
     245: goto          261
     248: new           #133                // class scala/MatchError
     251: dup
     252: aload         8
     254: invokespecial #137                // Method scala/MatchError."<init>":(Ljava/lang/Object;)V
     257: athrow
     258: getstatic     #64                 // Field scala/runtime/BoxedUnit.UNIT:Lscala/runtime/BoxedUnit;
     261: astore        6
     263: getstatic     #142                // Field akka/Done$.MODULE$:Lakka/Done$;
     266: areturn

  public final java.lang.Object apply(java.lang.Object);
    Code:
       0: aload_0
       1: aload_1
       2: checkcast     #150                // class akka/Done
       5: invokevirtual #155                // Method apply:(Lakka/Done;)Lakka/Done$;
       8: areturn

  public akka.remote.artery.Association$$anonfun$completeHandshake$2(akka.remote.artery.Association, akka.remote.UniqueAddress, akka.remote.artery.AssociationState);
    Code:
       0: aload_1
       1: ifnonnull     6
       4: aconst_null
       5: athrow
       6: aload_0
       7: aload_1
       8: putfield      #80                 // Field $outer:Lakka/remote/artery/Association;
      11: aload_0
      12: aload_2
      13: putfield      #35                 // Field peer$1:Lakka/remote/UniqueAddress;
      16: aload_0
      17: aload_3
      18: putfield      #27                 // Field current$1:Lakka/remote/artery/AssociationState;
      21: aload_0
      22: invokespecial #160                // Method scala/runtime/AbstractFunction1."<init>":()V
      25: return
}
