Compiled from "ImmutableLongMap.scala"
public final class akka.remote.artery.ImmutableLongMap$ {
  public static final akka.remote.artery.ImmutableLongMap$ MODULE$;

  private final int MaxScanLength;

  public static {};
    Code:
       0: new           #2                  // class akka/remote/artery/ImmutableLongMap$
       3: invokespecial #12                 // Method "<init>":()V
       6: return

  public <A> akka.remote.artery.ImmutableLongMap<A> empty(scala.reflect.ClassTag<A>);
    Code:
       0: new           #18                 // class akka/remote/artery/ImmutableLongMap
       3: dup
       4: getstatic     #23                 // Field scala/Array$.MODULE$:Lscala/Array$;
       7: invokevirtual #27                 // Method scala/Array$.emptyLongArray:()[J
      10: getstatic     #23                 // Field scala/Array$.MODULE$:Lscala/Array$;
      13: aload_1
      14: invokevirtual #30                 // Method scala/Array$.empty:(Lscala/reflect/ClassTag;)Ljava/lang/Object;
      17: aload_1
      18: invokespecial #33                 // Method akka/remote/artery/ImmutableLongMap."<init>":([JLjava/lang/Object;Lscala/reflect/ClassTag;)V
      21: areturn

  private int MaxScanLength();
    Code:
       0: aload_0
       1: getfield      #39                 // Field MaxScanLength:I
       4: ireturn

  private akka.remote.artery.ImmutableLongMap$();
    Code:
       0: aload_0
       1: invokespecial #40                 // Method java/lang/Object."<init>":()V
       4: aload_0
       5: putstatic     #42                 // Field MODULE$:Lakka/remote/artery/ImmutableLongMap$;
       8: aload_0
       9: bipush        10
      11: putfield      #39                 // Field MaxScanLength:I
      14: return
}
