Compiled from "ImmutableLongMap.scala"
public class akka.remote.artery.ImmutableLongMap<A> {
  private final long[] keys;

  private final java.lang.Object values;

  private final scala.reflect.ClassTag<A> t;

  private final int size;

  public static <A> akka.remote.artery.ImmutableLongMap<A> empty(scala.reflect.ClassTag<A>);
    Code:
       0: getstatic     #17                 // Field akka/remote/artery/ImmutableLongMap$.MODULE$:Lakka/remote/artery/ImmutableLongMap$;
       3: aload_0
       4: invokevirtual #19                 // Method akka/remote/artery/ImmutableLongMap$.empty:(Lscala/reflect/ClassTag;)Lakka/remote/artery/ImmutableLongMap;
       7: areturn

  private long[] keys();
    Code:
       0: aload_0
       1: getfield      #31                 // Field keys:[J
       4: areturn

  private java.lang.Object values();
    Code:
       0: aload_0
       1: getfield      #36                 // Field values:Ljava/lang/Object;
       4: areturn

  public int size();
    Code:
       0: aload_0
       1: getfield      #39                 // Field size:I
       4: ireturn

  public A get(long);
    Code:
       0: aload_0
       1: invokespecial #43                 // Method keys:()[J
       4: lload_1
       5: invokestatic  #49                 // Method java/util/Arrays.binarySearch:([JJ)I
       8: istore_3
       9: iload_3
      10: iconst_0
      11: if_icmplt     34
      14: getstatic     #54                 // Field akka/util/OptionVal$.MODULE$:Lakka/util/OptionVal$;
      17: getstatic     #59                 // Field scala/runtime/ScalaRunTime$.MODULE$:Lscala/runtime/ScalaRunTime$;
      20: aload_0
      21: invokespecial #61                 // Method values:()Ljava/lang/Object;
      24: iload_3
      25: invokevirtual #65                 // Method scala/runtime/ScalaRunTime$.array_apply:(Ljava/lang/Object;I)Ljava/lang/Object;
      28: invokevirtual #69                 // Method akka/util/OptionVal$.apply:(Ljava/lang/Object;)Ljava/lang/Object;
      31: goto          42
      34: getstatic     #54                 // Field akka/util/OptionVal$.MODULE$:Lakka/util/OptionVal$;
      37: invokevirtual #73                 // Method akka/util/OptionVal$.None:()Lscala/runtime/Null$;
      40: pop
      41: aconst_null
      42: areturn

  public boolean contains(long);
    Code:
       0: aload_0
       1: invokespecial #43                 // Method keys:()[J
       4: lload_1
       5: invokestatic  #49                 // Method java/util/Arrays.binarySearch:([JJ)I
       8: iconst_0
       9: if_icmplt     16
      12: iconst_1
      13: goto          17
      16: iconst_0
      17: ireturn

  public akka.remote.artery.ImmutableLongMap<A> updated(long, A);
    Code:
       0: aload_0
       1: invokevirtual #82                 // Method size:()I
       4: iconst_0
       5: if_icmpne     53
       8: new           #2                  // class akka/remote/artery/ImmutableLongMap
      11: dup
      12: iconst_1
      13: newarray       long
      15: dup
      16: iconst_0
      17: lload_1
      18: lastore
      19: getstatic     #87                 // Field scala/Array$.MODULE$:Lscala/Array$;
      22: getstatic     #92                 // Field scala/Predef$.MODULE$:Lscala/Predef$;
      25: iconst_1
      26: anewarray     #5                  // class java/lang/Object
      29: dup
      30: iconst_0
      31: aload_3
      32: aastore
      33: invokevirtual #96                 // Method scala/Predef$.genericWrapArray:(Ljava/lang/Object;)Lscala/collection/mutable/WrappedArray;
      36: aload_0
      37: getfield      #98                 // Field t:Lscala/reflect/ClassTag;
      40: invokevirtual #101                // Method scala/Array$.apply:(Lscala/collection/Seq;Lscala/reflect/ClassTag;)Ljava/lang/Object;
      43: aload_0
      44: getfield      #98                 // Field t:Lscala/reflect/ClassTag;
      47: invokespecial #105                // Method "<init>":([JLjava/lang/Object;Lscala/reflect/ClassTag;)V
      50: goto          300
      53: aload_0
      54: invokespecial #43                 // Method keys:()[J
      57: lload_1
      58: invokestatic  #49                 // Method java/util/Arrays.binarySearch:([JJ)I
      61: istore        4
      63: iload         4
      65: iconst_0
      66: if_icmplt     143
      69: getstatic     #87                 // Field scala/Array$.MODULE$:Lscala/Array$;
      72: getstatic     #59                 // Field scala/runtime/ScalaRunTime$.MODULE$:Lscala/runtime/ScalaRunTime$;
      75: aload_0
      76: invokespecial #61                 // Method values:()Ljava/lang/Object;
      79: invokevirtual #109                // Method scala/runtime/ScalaRunTime$.array_length:(Ljava/lang/Object;)I
      82: aload_0
      83: getfield      #98                 // Field t:Lscala/reflect/ClassTag;
      86: invokevirtual #113                // Method scala/Array$.ofDim:(ILscala/reflect/ClassTag;)Ljava/lang/Object;
      89: astore        5
      91: aload_0
      92: invokespecial #61                 // Method values:()Ljava/lang/Object;
      95: iconst_0
      96: aload         5
      98: iconst_0
      99: getstatic     #59                 // Field scala/runtime/ScalaRunTime$.MODULE$:Lscala/runtime/ScalaRunTime$;
     102: aload_0
     103: invokespecial #61                 // Method values:()Ljava/lang/Object;
     106: invokevirtual #109                // Method scala/runtime/ScalaRunTime$.array_length:(Ljava/lang/Object;)I
     109: invokestatic  #119                // Method java/lang/System.arraycopy:(Ljava/lang/Object;ILjava/lang/Object;II)V
     112: getstatic     #59                 // Field scala/runtime/ScalaRunTime$.MODULE$:Lscala/runtime/ScalaRunTime$;
     115: aload         5
     117: iload         4
     119: aload_3
     120: invokevirtual #123                // Method scala/runtime/ScalaRunTime$.array_update:(Ljava/lang/Object;ILjava/lang/Object;)V
     123: new           #2                  // class akka/remote/artery/ImmutableLongMap
     126: dup
     127: aload_0
     128: invokespecial #43                 // Method keys:()[J
     131: aload         5
     133: aload_0
     134: getfield      #98                 // Field t:Lscala/reflect/ClassTag;
     137: invokespecial #105                // Method "<init>":([JLjava/lang/Object;Lscala/reflect/ClassTag;)V
     140: goto          300
     143: iload         4
     145: iconst_1
     146: iadd
     147: ineg
     148: istore        6
     150: getstatic     #87                 // Field scala/Array$.MODULE$:Lscala/Array$;
     153: aload_0
     154: invokevirtual #82                 // Method size:()I
     157: iconst_1
     158: iadd
     159: getstatic     #128                // Field scala/reflect/ClassTag$.MODULE$:Lscala/reflect/ClassTag$;
     162: invokevirtual #132                // Method scala/reflect/ClassTag$.Long:()Lscala/reflect/ClassTag;
     165: invokevirtual #113                // Method scala/Array$.ofDim:(ILscala/reflect/ClassTag;)Ljava/lang/Object;
     168: checkcast     #133                // class "[J"
     171: astore        7
     173: aload_0
     174: invokespecial #43                 // Method keys:()[J
     177: iconst_0
     178: aload         7
     180: iconst_0
     181: iload         6
     183: invokestatic  #119                // Method java/lang/System.arraycopy:(Ljava/lang/Object;ILjava/lang/Object;II)V
     186: aload         7
     188: iload         6
     190: lload_1
     191: lastore
     192: aload_0
     193: invokespecial #43                 // Method keys:()[J
     196: iload         6
     198: aload         7
     200: iload         6
     202: iconst_1
     203: iadd
     204: aload_0
     205: invokespecial #43                 // Method keys:()[J
     208: arraylength
     209: iload         6
     211: isub
     212: invokestatic  #119                // Method java/lang/System.arraycopy:(Ljava/lang/Object;ILjava/lang/Object;II)V
     215: getstatic     #87                 // Field scala/Array$.MODULE$:Lscala/Array$;
     218: aload_0
     219: invokevirtual #82                 // Method size:()I
     222: iconst_1
     223: iadd
     224: aload_0
     225: getfield      #98                 // Field t:Lscala/reflect/ClassTag;
     228: invokevirtual #113                // Method scala/Array$.ofDim:(ILscala/reflect/ClassTag;)Ljava/lang/Object;
     231: astore        8
     233: aload_0
     234: invokespecial #61                 // Method values:()Ljava/lang/Object;
     237: iconst_0
     238: aload         8
     240: iconst_0
     241: iload         6
     243: invokestatic  #119                // Method java/lang/System.arraycopy:(Ljava/lang/Object;ILjava/lang/Object;II)V
     246: getstatic     #59                 // Field scala/runtime/ScalaRunTime$.MODULE$:Lscala/runtime/ScalaRunTime$;
     249: aload         8
     251: iload         6
     253: aload_3
     254: invokevirtual #123                // Method scala/runtime/ScalaRunTime$.array_update:(Ljava/lang/Object;ILjava/lang/Object;)V
     257: aload_0
     258: invokespecial #61                 // Method values:()Ljava/lang/Object;
     261: iload         6
     263: aload         8
     265: iload         6
     267: iconst_1
     268: iadd
     269: getstatic     #59                 // Field scala/runtime/ScalaRunTime$.MODULE$:Lscala/runtime/ScalaRunTime$;
     272: aload_0
     273: invokespecial #61                 // Method values:()Ljava/lang/Object;
     276: invokevirtual #109                // Method scala/runtime/ScalaRunTime$.array_length:(Ljava/lang/Object;)I
     279: iload         6
     281: isub
     282: invokestatic  #119                // Method java/lang/System.arraycopy:(Ljava/lang/Object;ILjava/lang/Object;II)V
     285: new           #2                  // class akka/remote/artery/ImmutableLongMap
     288: dup
     289: aload         7
     291: aload         8
     293: aload_0
     294: getfield      #98                 // Field t:Lscala/reflect/ClassTag;
     297: invokespecial #105                // Method "<init>":([JLjava/lang/Object;Lscala/reflect/ClassTag;)V
     300: areturn

  public akka.remote.artery.ImmutableLongMap<A> remove(long);
    Code:
       0: aload_0
       1: invokespecial #43                 // Method keys:()[J
       4: lload_1
       5: invokestatic  #49                 // Method java/util/Arrays.binarySearch:([JJ)I
       8: istore_3
       9: iload_3
      10: iconst_0
      11: if_icmplt     167
      14: aload_0
      15: invokevirtual #82                 // Method size:()I
      18: iconst_1
      19: if_icmpne     35
      22: getstatic     #17                 // Field akka/remote/artery/ImmutableLongMap$.MODULE$:Lakka/remote/artery/ImmutableLongMap$;
      25: aload_0
      26: getfield      #98                 // Field t:Lscala/reflect/ClassTag;
      29: invokevirtual #19                 // Method akka/remote/artery/ImmutableLongMap$.empty:(Lscala/reflect/ClassTag;)Lakka/remote/artery/ImmutableLongMap;
      32: goto          168
      35: getstatic     #87                 // Field scala/Array$.MODULE$:Lscala/Array$;
      38: aload_0
      39: invokevirtual #82                 // Method size:()I
      42: iconst_1
      43: isub
      44: getstatic     #128                // Field scala/reflect/ClassTag$.MODULE$:Lscala/reflect/ClassTag$;
      47: invokevirtual #132                // Method scala/reflect/ClassTag$.Long:()Lscala/reflect/ClassTag;
      50: invokevirtual #113                // Method scala/Array$.ofDim:(ILscala/reflect/ClassTag;)Ljava/lang/Object;
      53: checkcast     #133                // class "[J"
      56: astore        4
      58: aload_0
      59: invokespecial #43                 // Method keys:()[J
      62: iconst_0
      63: aload         4
      65: iconst_0
      66: iload_3
      67: invokestatic  #119                // Method java/lang/System.arraycopy:(Ljava/lang/Object;ILjava/lang/Object;II)V
      70: aload_0
      71: invokespecial #43                 // Method keys:()[J
      74: iload_3
      75: iconst_1
      76: iadd
      77: aload         4
      79: iload_3
      80: aload_0
      81: invokespecial #43                 // Method keys:()[J
      84: arraylength
      85: iload_3
      86: isub
      87: iconst_1
      88: isub
      89: invokestatic  #119                // Method java/lang/System.arraycopy:(Ljava/lang/Object;ILjava/lang/Object;II)V
      92: getstatic     #87                 // Field scala/Array$.MODULE$:Lscala/Array$;
      95: aload_0
      96: invokevirtual #82                 // Method size:()I
      99: iconst_1
     100: isub
     101: aload_0
     102: getfield      #98                 // Field t:Lscala/reflect/ClassTag;
     105: invokevirtual #113                // Method scala/Array$.ofDim:(ILscala/reflect/ClassTag;)Ljava/lang/Object;
     108: astore        5
     110: aload_0
     111: invokespecial #61                 // Method values:()Ljava/lang/Object;
     114: iconst_0
     115: aload         5
     117: iconst_0
     118: iload_3
     119: invokestatic  #119                // Method java/lang/System.arraycopy:(Ljava/lang/Object;ILjava/lang/Object;II)V
     122: aload_0
     123: invokespecial #61                 // Method values:()Ljava/lang/Object;
     126: iload_3
     127: iconst_1
     128: iadd
     129: aload         5
     131: iload_3
     132: getstatic     #59                 // Field scala/runtime/ScalaRunTime$.MODULE$:Lscala/runtime/ScalaRunTime$;
     135: aload_0
     136: invokespecial #61                 // Method values:()Ljava/lang/Object;
     139: invokevirtual #109                // Method scala/runtime/ScalaRunTime$.array_length:(Ljava/lang/Object;)I
     142: iload_3
     143: isub
     144: iconst_1
     145: isub
     146: invokestatic  #119                // Method java/lang/System.arraycopy:(Ljava/lang/Object;ILjava/lang/Object;II)V
     149: new           #2                  // class akka/remote/artery/ImmutableLongMap
     152: dup
     153: aload         4
     155: aload         5
     157: aload_0
     158: getfield      #98                 // Field t:Lscala/reflect/ClassTag;
     161: invokespecial #105                // Method "<init>":([JLjava/lang/Object;Lscala/reflect/ClassTag;)V
     164: goto          168
     167: aload_0
     168: areturn

  public scala.collection.Iterator<java.lang.Object> keysIterator();
    Code:
       0: getstatic     #92                 // Field scala/Predef$.MODULE$:Lscala/Predef$;
       3: aload_0
       4: invokespecial #43                 // Method keys:()[J
       7: invokevirtual #145                // Method scala/Predef$.longArrayOps:([J)Lscala/collection/mutable/ArrayOps;
      10: invokeinterface #150,  1          // InterfaceMethod scala/collection/mutable/ArrayOps.iterator:()Lscala/collection/Iterator;
      15: areturn

  public java.lang.String toString();
    Code:
       0: aload_0
       1: invokevirtual #154                // Method keysIterator:()Lscala/collection/Iterator;
       4: new           #156                // class akka/remote/artery/ImmutableLongMap$$anonfun$toString$1
       7: dup
       8: aload_0
       9: invokespecial #159                // Method akka/remote/artery/ImmutableLongMap$$anonfun$toString$1."<init>":(Lakka/remote/artery/ImmutableLongMap;)V
      12: invokeinterface #165,  2          // InterfaceMethod scala/collection/Iterator.map:(Lscala/Function1;)Lscala/collection/Iterator;
      17: ldc           #167                // String ImmutableLongMap(
      19: ldc           #169                // String ,
      21: ldc           #171                // String )
      23: invokeinterface #175,  4          // InterfaceMethod scala/collection/Iterator.mkString:(Ljava/lang/String;Ljava/lang/String;Ljava/lang/String;)Ljava/lang/String;
      28: areturn

  public int hashCode();
    Code:
       0: getstatic     #181                // Field akka/util/HashCode$.MODULE$:Lakka/util/HashCode$;
       3: invokevirtual #184                // Method akka/util/HashCode$.SEED:()I
       6: istore_1
       7: getstatic     #181                // Field akka/util/HashCode$.MODULE$:Lakka/util/HashCode$;
      10: iload_1
      11: aload_0
      12: invokespecial #43                 // Method keys:()[J
      15: invokevirtual #188                // Method akka/util/HashCode$.hash:(ILjava/lang/Object;)I
      18: istore_1
      19: getstatic     #181                // Field akka/util/HashCode$.MODULE$:Lakka/util/HashCode$;
      22: iload_1
      23: aload_0
      24: invokespecial #61                 // Method values:()Ljava/lang/Object;
      27: invokevirtual #188                // Method akka/util/HashCode$.hash:(ILjava/lang/Object;)I
      30: istore_1
      31: iload_1
      32: ireturn

  public boolean equals(java.lang.Object);
    Code:
       0: aload_1
       1: astore_2
       2: aload_2
       3: instanceof    #2                  // class akka/remote/artery/ImmutableLongMap
       6: ifeq          69
       9: aload_2
      10: checkcast     #2                  // class akka/remote/artery/ImmutableLongMap
      13: astore_3
      14: aload_3
      15: aload_0
      16: if_acmpne     23
      19: iconst_1
      20: goto          64
      23: aload_0
      24: invokevirtual #82                 // Method size:()I
      27: aload_3
      28: invokevirtual #82                 // Method size:()I
      31: if_icmpeq     38
      34: iconst_0
      35: goto          64
      38: aload_0
      39: invokevirtual #82                 // Method size:()I
      42: iconst_0
      43: if_icmpne     58
      46: aload_3
      47: invokevirtual #82                 // Method size:()I
      50: iconst_0
      51: if_icmpne     58
      54: iconst_1
      55: goto          64
      58: aload_0
      59: iconst_0
      60: aload_3
      61: invokespecial #195                // Method check$1:(ILakka/remote/artery/ImmutableLongMap;)Z
      64: istore        4
      66: goto          72
      69: iconst_0
      70: istore        4
      72: iload         4
      74: ireturn

  private final boolean check$1(int, akka.remote.artery.ImmutableLongMap);
    Code:
       0: iload_1
       1: aload_0
       2: invokevirtual #82                 // Method size:()I
       5: if_icmpne     12
       8: iconst_1
       9: goto          64
      12: aload_0
      13: invokespecial #43                 // Method keys:()[J
      16: iload_1
      17: laload
      18: aload_2
      19: invokespecial #43                 // Method keys:()[J
      22: iload_1
      23: laload
      24: lcmp
      25: ifne          63
      28: getstatic     #59                 // Field scala/runtime/ScalaRunTime$.MODULE$:Lscala/runtime/ScalaRunTime$;
      31: aload_0
      32: invokespecial #61                 // Method values:()Ljava/lang/Object;
      35: iload_1
      36: invokevirtual #65                 // Method scala/runtime/ScalaRunTime$.array_apply:(Ljava/lang/Object;I)Ljava/lang/Object;
      39: getstatic     #59                 // Field scala/runtime/ScalaRunTime$.MODULE$:Lscala/runtime/ScalaRunTime$;
      42: aload_2
      43: invokespecial #61                 // Method values:()Ljava/lang/Object;
      46: iload_1
      47: invokevirtual #65                 // Method scala/runtime/ScalaRunTime$.array_apply:(Ljava/lang/Object;I)Ljava/lang/Object;
      50: invokestatic  #201                // Method scala/runtime/BoxesRunTime.equals:(Ljava/lang/Object;Ljava/lang/Object;)Z
      53: ifeq          63
      56: iload_1
      57: iconst_1
      58: iadd
      59: istore_1
      60: goto          0
      63: iconst_0
      64: ireturn

  public akka.remote.artery.ImmutableLongMap(long[], java.lang.Object, scala.reflect.ClassTag<A>);
    Code:
       0: aload_0
       1: aload_1
       2: putfield      #31                 // Field keys:[J
       5: aload_0
       6: aload_2
       7: putfield      #36                 // Field values:Ljava/lang/Object;
      10: aload_0
      11: aload_3
      12: putfield      #98                 // Field t:Lscala/reflect/ClassTag;
      15: aload_0
      16: invokespecial #205                // Method java/lang/Object."<init>":()V
      19: aload_0
      20: aload_1
      21: arraylength
      22: putfield      #39                 // Field size:I
      25: return
}
