Compiled from "MetadataEnvelopeSerializer.scala"
public final class akka.remote.artery.MetadataMapParsing$ {
  public static final akka.remote.artery.MetadataMapParsing$ MODULE$;

  public static {};
    Code:
       0: new           #2                  // class akka/remote/artery/MetadataMapParsing$
       3: invokespecial #12                 // Method "<init>":()V
       6: return

  public akka.remote.artery.MetadataMap parse(akka.remote.artery.InboundEnvelope);
    Code:
       0: aload_1
       1: invokeinterface #20,  1           // InterfaceMethod akka/remote/artery/InboundEnvelope.envelopeBuffer:()Lakka/remote/artery/EnvelopeBuffer;
       6: invokevirtual #26                 // Method akka/remote/artery/EnvelopeBuffer.byteBuffer:()Ljava/nio/ByteBuffer;
       9: astore_2
      10: aload_2
      11: getstatic     #31                 // Field akka/remote/artery/EnvelopeBuffer$.MODULE$:Lakka/remote/artery/EnvelopeBuffer$;
      14: invokevirtual #35                 // Method akka/remote/artery/EnvelopeBuffer$.MetadataContainerAndLiteralSectionOffset:()I
      17: invokevirtual #41                 // Method java/nio/ByteBuffer.position:(I)Ljava/nio/Buffer;
      20: pop
      21: aload_0
      22: aload_2
      23: invokevirtual #45                 // Method parseRaw:(Ljava/nio/ByteBuffer;)Lakka/remote/artery/MetadataMap;
      26: areturn

  public akka.remote.artery.MetadataMap parseRaw(java.nio.ByteBuffer);
    Code:
       0: aload_1
       1: getstatic     #56                 // Field java/nio/ByteOrder.LITTLE_ENDIAN:Ljava/nio/ByteOrder;
       4: invokevirtual #60                 // Method java/nio/ByteBuffer.order:(Ljava/nio/ByteOrder;)Ljava/nio/ByteBuffer;
       7: pop
       8: aload_1
       9: invokevirtual #63                 // Method java/nio/ByteBuffer.getInt:()I
      12: istore_2
      13: iload_2
      14: aload_1
      15: invokevirtual #65                 // Method java/nio/ByteBuffer.position:()I
      18: iadd
      19: istore_3
      20: getstatic     #70                 // Field akka/remote/artery/MetadataMap$.MODULE$:Lakka/remote/artery/MetadataMap$;
      23: invokevirtual #74                 // Method akka/remote/artery/MetadataMap$.apply:()Lakka/remote/artery/MetadataMap;
      26: astore        4
      28: aload_1
      29: invokevirtual #65                 // Method java/nio/ByteBuffer.position:()I
      32: iload_3
      33: if_icmpge     110
      36: aload_1
      37: invokevirtual #63                 // Method java/nio/ByteBuffer.getInt:()I
      40: istore        5
      42: getstatic     #79                 // Field akka/remote/artery/MetadataEnvelopeSerializer$.MODULE$:Lakka/remote/artery/MetadataEnvelopeSerializer$;
      45: iload         5
      47: invokevirtual #83                 // Method akka/remote/artery/MetadataEnvelopeSerializer$.unmaskEntryKey:(I)B
      50: istore        6
      52: getstatic     #79                 // Field akka/remote/artery/MetadataEnvelopeSerializer$.MODULE$:Lakka/remote/artery/MetadataEnvelopeSerializer$;
      55: iload         5
      57: invokevirtual #87                 // Method akka/remote/artery/MetadataEnvelopeSerializer$.unmaskEntryLength:(I)I
      60: istore        7
      62: getstatic     #92                 // Field scala/Array$.MODULE$:Lscala/Array$;
      65: iload         7
      67: getstatic     #97                 // Field scala/reflect/ClassTag$.MODULE$:Lscala/reflect/ClassTag$;
      70: invokevirtual #101                // Method scala/reflect/ClassTag$.Byte:()Lscala/reflect/ClassTag;
      73: invokevirtual #105                // Method scala/Array$.ofDim:(ILscala/reflect/ClassTag;)Ljava/lang/Object;
      76: checkcast     #107                // class "[B"
      79: astore        8
      81: aload_1
      82: aload         8
      84: invokevirtual #111                // Method java/nio/ByteBuffer.get:([B)Ljava/nio/ByteBuffer;
      87: pop
      88: getstatic     #116                // Field akka/util/ByteString$ByteString1C$.MODULE$:Lakka/util/ByteString$ByteString1C$;
      91: aload         8
      93: invokevirtual #119                // Method akka/util/ByteString$ByteString1C$.apply:([B)Lakka/util/ByteString$ByteString1C;
      96: astore        9
      98: aload         4
     100: iload         6
     102: aload         9
     104: invokevirtual #125                // Method akka/remote/artery/MetadataMap.set:(ILjava/lang/Object;)V
     107: goto          28
     110: aload         4
     112: areturn

  public void applyAllRemoteMessageReceived(scala.collection.immutable.Vector<akka.remote.artery.RemoteInstrument>, akka.remote.artery.InboundEnvelope);
    Code:
       0: aload_2
       1: invokeinterface #20,  1           // InterfaceMethod akka/remote/artery/InboundEnvelope.envelopeBuffer:()Lakka/remote/artery/EnvelopeBuffer;
       6: invokevirtual #26                 // Method akka/remote/artery/EnvelopeBuffer.byteBuffer:()Ljava/nio/ByteBuffer;
       9: astore_3
      10: aload_3
      11: getstatic     #31                 // Field akka/remote/artery/EnvelopeBuffer$.MODULE$:Lakka/remote/artery/EnvelopeBuffer$;
      14: invokevirtual #35                 // Method akka/remote/artery/EnvelopeBuffer$.MetadataContainerAndLiteralSectionOffset:()I
      17: invokevirtual #41                 // Method java/nio/ByteBuffer.position:(I)Ljava/nio/Buffer;
      20: pop
      21: aload_0
      22: aload_1
      23: aload_2
      24: aload_3
      25: invokevirtual #143                // Method applyAllRemoteMessageReceivedRaw:(Lscala/collection/immutable/Vector;Lakka/remote/artery/InboundEnvelope;Ljava/nio/ByteBuffer;)V
      28: return

  public void applyAllRemoteMessageReceivedRaw(scala.collection.immutable.Vector<akka.remote.artery.RemoteInstrument>, akka.remote.artery.InboundEnvelope, java.nio.ByteBuffer);
    Code:
       0: aload_3
       1: getstatic     #56                 // Field java/nio/ByteOrder.LITTLE_ENDIAN:Ljava/nio/ByteOrder;
       4: invokevirtual #60                 // Method java/nio/ByteBuffer.order:(Ljava/nio/ByteOrder;)Ljava/nio/ByteBuffer;
       7: pop
       8: aload_3
       9: invokevirtual #63                 // Method java/nio/ByteBuffer.getInt:()I
      12: istore        4
      14: iload         4
      16: aload_3
      17: invokevirtual #65                 // Method java/nio/ByteBuffer.position:()I
      20: iadd
      21: istore        5
      23: aload_3
      24: invokevirtual #65                 // Method java/nio/ByteBuffer.position:()I
      27: iload         5
      29: if_icmpge     256
      32: aload_3
      33: invokevirtual #63                 // Method java/nio/ByteBuffer.getInt:()I
      36: istore        6
      38: getstatic     #79                 // Field akka/remote/artery/MetadataEnvelopeSerializer$.MODULE$:Lakka/remote/artery/MetadataEnvelopeSerializer$;
      41: iload         6
      43: invokevirtual #83                 // Method akka/remote/artery/MetadataEnvelopeSerializer$.unmaskEntryKey:(I)B
      46: istore        7
      48: getstatic     #79                 // Field akka/remote/artery/MetadataEnvelopeSerializer$.MODULE$:Lakka/remote/artery/MetadataEnvelopeSerializer$;
      51: iload         6
      53: invokevirtual #87                 // Method akka/remote/artery/MetadataEnvelopeSerializer$.unmaskEntryLength:(I)I
      56: istore        8
      58: getstatic     #92                 // Field scala/Array$.MODULE$:Lscala/Array$;
      61: iload         8
      63: getstatic     #97                 // Field scala/reflect/ClassTag$.MODULE$:Lscala/reflect/ClassTag$;
      66: invokevirtual #101                // Method scala/reflect/ClassTag$.Byte:()Lscala/reflect/ClassTag;
      69: invokevirtual #105                // Method scala/Array$.ofDim:(ILscala/reflect/ClassTag;)Ljava/lang/Object;
      72: checkcast     #107                // class "[B"
      75: astore        9
      77: aload_3
      78: aload         9
      80: invokevirtual #111                // Method java/nio/ByteBuffer.get:([B)Ljava/nio/ByteBuffer;
      83: pop
      84: getstatic     #150                // Field akka/util/ByteString$.MODULE$:Lakka/util/ByteString$;
      87: aload         9
      89: invokevirtual #153                // Method akka/util/ByteString$.apply:([B)Lakka/util/ByteString;
      92: astore        10
      94: aload_1
      95: new           #155                // class akka/remote/artery/MetadataMapParsing$$anonfun$2
      98: dup
      99: iload         7
     101: invokespecial #158                // Method akka/remote/artery/MetadataMapParsing$$anonfun$2."<init>":(B)V
     104: invokevirtual #164                // Method scala/collection/immutable/Vector.find:(Lscala/Function1;)Lscala/Option;
     107: astore        11
     109: aload         11
     111: instanceof    #166                // class scala/Some
     114: ifeq          197
     117: aload         11
     119: checkcast     #166                // class scala/Some
     122: astore        12
     124: aload         12
     126: invokevirtual #170                // Method scala/Some.x:()Ljava/lang/Object;
     129: checkcast     #172                // class akka/remote/artery/RemoteInstrument
     132: astore        13
     134: aload         13
     136: getstatic     #177                // Field akka/util/OptionVal$.MODULE$:Lakka/util/OptionVal$;
     139: aload_2
     140: invokeinterface #181,  1          // InterfaceMethod akka/remote/artery/InboundEnvelope.recipient:()Lakka/actor/InternalActorRef;
     145: getstatic     #186                // Field scala/Predef$.MODULE$:Lscala/Predef$;
     148: invokevirtual #190                // Method scala/Predef$.$conforms:()Lscala/Predef$$less$colon$less;
     151: invokevirtual #194                // Method akka/util/OptionVal$.orNull$extension:(Ljava/lang/Object;Lscala/Predef$$less$colon$less;)Ljava/lang/Object;
     154: checkcast     #196                // class akka/actor/ActorRef
     157: aload_2
     158: invokeinterface #199,  1          // InterfaceMethod akka/remote/artery/InboundEnvelope.message:()Ljava/lang/Object;
     163: getstatic     #177                // Field akka/util/OptionVal$.MODULE$:Lakka/util/OptionVal$;
     166: aload_2
     167: invokeinterface #203,  1          // InterfaceMethod akka/remote/artery/InboundEnvelope.sender:()Lakka/actor/ActorRef;
     172: getstatic     #186                // Field scala/Predef$.MODULE$:Lscala/Predef$;
     175: invokevirtual #190                // Method scala/Predef$.$conforms:()Lscala/Predef$$less$colon$less;
     178: invokevirtual #194                // Method akka/util/OptionVal$.orNull$extension:(Ljava/lang/Object;Lscala/Predef$$less$colon$less;)Ljava/lang/Object;
     181: checkcast     #196                // class akka/actor/ActorRef
     184: aload         10
     186: invokevirtual #207                // Method akka/remote/artery/RemoteInstrument.remoteMessageReceived:(Lakka/actor/ActorRef;Ljava/lang/Object;Lakka/actor/ActorRef;Lakka/util/ByteString;)V
     189: getstatic     #213                // Field scala/runtime/BoxedUnit.UNIT:Lscala/runtime/BoxedUnit;
     192: astore        14
     194: goto          23
     197: new           #215                // class java/lang/Exception
     200: dup
     201: new           #217                // class scala/StringContext
     204: dup
     205: getstatic     #186                // Field scala/Predef$.MODULE$:Lscala/Predef$;
     208: iconst_2
     209: anewarray     #219                // class java/lang/String
     212: dup
     213: iconst_0
     214: ldc           #221                // String No RemoteInstrument for id
     216: aastore
     217: dup
     218: iconst_1
     219: ldc           #223                // String  available!
     221: aastore
     222: checkcast     #225                // class "[Ljava/lang/Object;"
     225: invokevirtual #229                // Method scala/Predef$.wrapRefArray:([Ljava/lang/Object;)Lscala/collection/mutable/WrappedArray;
     228: invokespecial #232                // Method scala/StringContext."<init>":(Lscala/collection/Seq;)V
     231: getstatic     #186                // Field scala/Predef$.MODULE$:Lscala/Predef$;
     234: iconst_1
     235: anewarray     #4                  // class java/lang/Object
     238: dup
     239: iconst_0
     240: iload         7
     242: invokestatic  #238                // Method scala/runtime/BoxesRunTime.boxToByte:(B)Ljava/lang/Byte;
     245: aastore
     246: invokevirtual #242                // Method scala/Predef$.genericWrapArray:(Ljava/lang/Object;)Lscala/collection/mutable/WrappedArray;
     249: invokevirtual #246                // Method scala/StringContext.s:(Lscala/collection/Seq;)Ljava/lang/String;
     252: invokespecial #249                // Method java/lang/Exception."<init>":(Ljava/lang/String;)V
     255: athrow
     256: return

  private akka.remote.artery.MetadataMapParsing$();
    Code:
       0: aload_0
       1: invokespecial #261                // Method java/lang/Object."<init>":()V
       4: aload_0
       5: putstatic     #263                // Field MODULE$:Lakka/remote/artery/MetadataMapParsing$;
       8: return
}
