Compiled from "TraitHelpersTuple.java"
class org.codehaus.groovy.transform.trait.TraitHelpersTuple {
  private final org.codehaus.groovy.ast.ClassNode helper;

  private final org.codehaus.groovy.ast.ClassNode fieldHelper;

  public org.codehaus.groovy.transform.trait.TraitHelpersTuple(org.codehaus.groovy.ast.ClassNode, org.codehaus.groovy.ast.ClassNode);
    Code:
       0: aload_0
       1: invokespecial #13                 // Method java/lang/Object."<init>":()V
       4: aload_0
       5: aload_1
       6: putfield      #15                 // Field helper:Lorg/codehaus/groovy/ast/ClassNode;
       9: aload_0
      10: aload_2
      11: putfield      #17                 // Field fieldHelper:Lorg/codehaus/groovy/ast/ClassNode;
      14: return

  public org.codehaus.groovy.ast.ClassNode getHelper();
    Code:
       0: aload_0
       1: getfield      #15                 // Field helper:Lorg/codehaus/groovy/ast/ClassNode;
       4: areturn

  public org.codehaus.groovy.ast.ClassNode getFieldHelper();
    Code:
       0: aload_0
       1: getfield      #17                 // Field fieldHelper:Lorg/codehaus/groovy/ast/ClassNode;
       4: areturn
}
