Compiled from "UsernamePasswordAuthenticationInfo.java"
public class org.sonatype.nexus.client.rest.UsernamePasswordAuthenticationInfo implements org.sonatype.nexus.client.rest.AuthenticationInfo {
  private final java.lang.String username;

  private final java.lang.String password;

  public org.sonatype.nexus.client.rest.UsernamePasswordAuthenticationInfo(java.lang.String, java.lang.String);
    Code:
       0: aload_0
       1: invokespecial #1                  // Method java/lang/Object."<init>":()V
       4: aload_0
       5: aload_1
       6: ldc           #2                  // String username
       8: invokestatic  #3                  // Method org/sonatype/nexus/client/internal/util/Check.notBlank:(Ljava/lang/String;Ljava/lang/String;)Ljava/lang/String;
      11: putfield      #4                  // Field username:Ljava/lang/String;
      14: aload_0
      15: aload_2
      16: ldc           #5                  // String password
      18: invokestatic  #3                  // Method org/sonatype/nexus/client/internal/util/Check.notBlank:(Ljava/lang/String;Ljava/lang/String;)Ljava/lang/String;
      21: putfield      #6                  // Field password:Ljava/lang/String;
      24: return

  public java.lang.String getUsername();
    Code:
       0: aload_0
       1: getfield      #4                  // Field username:Ljava/lang/String;
       4: areturn

  public java.lang.String getPassword();
    Code:
       0: aload_0
       1: getfield      #6                  // Field password:Ljava/lang/String;
       4: areturn

  public java.lang.String toString();
    Code:
       0: new           #7                  // class java/lang/StringBuilder
       3: dup
       4: invokespecial #8                  // Method java/lang/StringBuilder."<init>":()V
       7: aload_0
       8: invokevirtual #9                  // Method java/lang/Object.getClass:()Ljava/lang/Class;
      11: invokevirtual #10                 // Method java/lang/Class.getSimpleName:()Ljava/lang/String;
      14: invokevirtual #11                 // Method java/lang/StringBuilder.append:(Ljava/lang/String;)Ljava/lang/StringBuilder;
      17: ldc           #12                 // String [username=
      19: invokevirtual #11                 // Method java/lang/StringBuilder.append:(Ljava/lang/String;)Ljava/lang/StringBuilder;
      22: aload_0
      23: getfield      #4                  // Field username:Ljava/lang/String;
      26: invokevirtual #11                 // Method java/lang/StringBuilder.append:(Ljava/lang/String;)Ljava/lang/StringBuilder;
      29: ldc           #13                 // String , password=****]
      31: invokevirtual #11                 // Method java/lang/StringBuilder.append:(Ljava/lang/String;)Ljava/lang/StringBuilder;
      34: invokevirtual #14                 // Method java/lang/StringBuilder.toString:()Ljava/lang/String;
      37: areturn
}
