Compiled from "ExtendedThreadInformation.java"
class org.apache.logging.log4j.core.message.ExtendedThreadInformation implements org.apache.logging.log4j.message.ThreadInformation {
  private final java.lang.management.ThreadInfo threadInfo;

  org.apache.logging.log4j.core.message.ExtendedThreadInformation(java.lang.management.ThreadInfo);
    Code:
       0: aload_0
       1: invokespecial #2                  // Method java/lang/Object."<init>":()V
       4: aload_0
       5: aload_1
       6: putfield      #3                  // Field threadInfo:Ljava/lang/management/ThreadInfo;
       9: return

  public void printThreadInfo(java.lang.StringBuilder);
    Code:
       0: aload_1
       1: aload_0
       2: getfield      #3                  // Field threadInfo:Ljava/lang/management/ThreadInfo;
       5: invokevirtual #4                  // Method java/lang/management/ThreadInfo.getThreadName:()Ljava/lang/String;
       8: invokestatic  #5                  // Method org/apache/logging/log4j/util/StringBuilders.appendDqValue:(Ljava/lang/StringBuilder;Ljava/lang/Object;)Ljava/lang/StringBuilder;
      11: pop
      12: aload_1
      13: ldc           #6                  // String  Id=
      15: invokevirtual #7                  // Method java/lang/StringBuilder.append:(Ljava/lang/String;)Ljava/lang/StringBuilder;
      18: aload_0
      19: getfield      #3                  // Field threadInfo:Ljava/lang/management/ThreadInfo;
      22: invokevirtual #8                  // Method java/lang/management/ThreadInfo.getThreadId:()J
      25: invokevirtual #9                  // Method java/lang/StringBuilder.append:(J)Ljava/lang/StringBuilder;
      28: bipush        32
      30: invokevirtual #10                 // Method java/lang/StringBuilder.append:(C)Ljava/lang/StringBuilder;
      33: pop
      34: aload_0
      35: aload_1
      36: aload_0
      37: getfield      #3                  // Field threadInfo:Ljava/lang/management/ThreadInfo;
      40: invokespecial #11                 // Method formatState:(Ljava/lang/StringBuilder;Ljava/lang/management/ThreadInfo;)V
      43: aload_0
      44: getfield      #3                  // Field threadInfo:Ljava/lang/management/ThreadInfo;
      47: invokevirtual #12                 // Method java/lang/management/ThreadInfo.isSuspended:()Z
      50: ifeq          60
      53: aload_1
      54: ldc           #13                 // String  (suspended)
      56: invokevirtual #7                  // Method java/lang/StringBuilder.append:(Ljava/lang/String;)Ljava/lang/StringBuilder;
      59: pop
      60: aload_0
      61: getfield      #3                  // Field threadInfo:Ljava/lang/management/ThreadInfo;
      64: invokevirtual #14                 // Method java/lang/management/ThreadInfo.isInNative:()Z
      67: ifeq          77
      70: aload_1
      71: ldc           #15                 // String  (in native)
      73: invokevirtual #7                  // Method java/lang/StringBuilder.append:(Ljava/lang/String;)Ljava/lang/StringBuilder;
      76: pop
      77: aload_1
      78: bipush        10
      80: invokevirtual #10                 // Method java/lang/StringBuilder.append:(C)Ljava/lang/StringBuilder;
      83: pop
      84: return

  public void printStack(java.lang.StringBuilder, java.lang.StackTraceElement[]);
    Code:
       0: iconst_0
       1: istore_3
       2: aload_2
       3: astore        4
       5: aload         4
       7: arraylength
       8: istore        5
      10: iconst_0
      11: istore        6
      13: iload         6
      15: iload         5
      17: if_icmpge     271
      20: aload         4
      22: iload         6
      24: aaload
      25: astore        7
      27: aload_1
      28: ldc           #16                 // String \tat
      30: invokevirtual #7                  // Method java/lang/StringBuilder.append:(Ljava/lang/String;)Ljava/lang/StringBuilder;
      33: aload         7
      35: invokevirtual #17                 // Method java/lang/StackTraceElement.toString:()Ljava/lang/String;
      38: invokevirtual #7                  // Method java/lang/StringBuilder.append:(Ljava/lang/String;)Ljava/lang/StringBuilder;
      41: pop
      42: aload_1
      43: bipush        10
      45: invokevirtual #10                 // Method java/lang/StringBuilder.append:(C)Ljava/lang/StringBuilder;
      48: pop
      49: iload_3
      50: ifne          195
      53: aload_0
      54: getfield      #3                  // Field threadInfo:Ljava/lang/management/ThreadInfo;
      57: invokevirtual #18                 // Method java/lang/management/ThreadInfo.getLockInfo:()Ljava/lang/management/LockInfo;
      60: ifnull        195
      63: aload_0
      64: getfield      #3                  // Field threadInfo:Ljava/lang/management/ThreadInfo;
      67: invokevirtual #19                 // Method java/lang/management/ThreadInfo.getThreadState:()Ljava/lang/Thread$State;
      70: astore        8
      72: getstatic     #20                 // Field org/apache/logging/log4j/core/message/ExtendedThreadInformation$1.$SwitchMap$java$lang$Thread$State:[I
      75: aload         8
      77: invokevirtual #21                 // Method java/lang/Thread$State.ordinal:()I
      80: iaload
      81: tableswitch   { // 1 to 3
                     1: 108
                     2: 137
                     3: 166
               default: 195
          }
     108: aload_1
     109: ldc           #22                 // String \t-  blocked on
     111: invokevirtual #7                  // Method java/lang/StringBuilder.append:(Ljava/lang/String;)Ljava/lang/StringBuilder;
     114: pop
     115: aload_0
     116: aload_1
     117: aload_0
     118: getfield      #3                  // Field threadInfo:Ljava/lang/management/ThreadInfo;
     121: invokevirtual #18                 // Method java/lang/management/ThreadInfo.getLockInfo:()Ljava/lang/management/LockInfo;
     124: invokespecial #23                 // Method formatLock:(Ljava/lang/StringBuilder;Ljava/lang/management/LockInfo;)V
     127: aload_1
     128: bipush        10
     130: invokevirtual #10                 // Method java/lang/StringBuilder.append:(C)Ljava/lang/StringBuilder;
     133: pop
     134: goto          195
     137: aload_1
     138: ldc           #24                 // String \t-  waiting on
     140: invokevirtual #7                  // Method java/lang/StringBuilder.append:(Ljava/lang/String;)Ljava/lang/StringBuilder;
     143: pop
     144: aload_0
     145: aload_1
     146: aload_0
     147: getfield      #3                  // Field threadInfo:Ljava/lang/management/ThreadInfo;
     150: invokevirtual #18                 // Method java/lang/management/ThreadInfo.getLockInfo:()Ljava/lang/management/LockInfo;
     153: invokespecial #23                 // Method formatLock:(Ljava/lang/StringBuilder;Ljava/lang/management/LockInfo;)V
     156: aload_1
     157: bipush        10
     159: invokevirtual #10                 // Method java/lang/StringBuilder.append:(C)Ljava/lang/StringBuilder;
     162: pop
     163: goto          195
     166: aload_1
     167: ldc           #24                 // String \t-  waiting on
     169: invokevirtual #7                  // Method java/lang/StringBuilder.append:(Ljava/lang/String;)Ljava/lang/StringBuilder;
     172: pop
     173: aload_0
     174: aload_1
     175: aload_0
     176: getfield      #3                  // Field threadInfo:Ljava/lang/management/ThreadInfo;
     179: invokevirtual #18                 // Method java/lang/management/ThreadInfo.getLockInfo:()Ljava/lang/management/LockInfo;
     182: invokespecial #23                 // Method formatLock:(Ljava/lang/StringBuilder;Ljava/lang/management/LockInfo;)V
     185: aload_1
     186: bipush        10
     188: invokevirtual #10                 // Method java/lang/StringBuilder.append:(C)Ljava/lang/StringBuilder;
     191: pop
     192: goto          195
     195: aload_0
     196: getfield      #3                  // Field threadInfo:Ljava/lang/management/ThreadInfo;
     199: invokevirtual #25                 // Method java/lang/management/ThreadInfo.getLockedMonitors:()[Ljava/lang/management/MonitorInfo;
     202: astore        8
     204: aload         8
     206: arraylength
     207: istore        9
     209: iconst_0
     210: istore        10
     212: iload         10
     214: iload         9
     216: if_icmpge     262
     219: aload         8
     221: iload         10
     223: aaload
     224: astore        11
     226: aload         11
     228: invokevirtual #26                 // Method java/lang/management/MonitorInfo.getLockedStackDepth:()I
     231: iload_3
     232: if_icmpne     256
     235: aload_1
     236: ldc           #27                 // String \t-  locked
     238: invokevirtual #7                  // Method java/lang/StringBuilder.append:(Ljava/lang/String;)Ljava/lang/StringBuilder;
     241: pop
     242: aload_0
     243: aload_1
     244: aload         11
     246: invokespecial #23                 // Method formatLock:(Ljava/lang/StringBuilder;Ljava/lang/management/LockInfo;)V
     249: aload_1
     250: bipush        10
     252: invokevirtual #10                 // Method java/lang/StringBuilder.append:(C)Ljava/lang/StringBuilder;
     255: pop
     256: iinc          10, 1
     259: goto          212
     262: iinc          3, 1
     265: iinc          6, 1
     268: goto          13
     271: aload_0
     272: getfield      #3                  // Field threadInfo:Ljava/lang/management/ThreadInfo;
     275: invokevirtual #28                 // Method java/lang/management/ThreadInfo.getLockedSynchronizers:()[Ljava/lang/management/LockInfo;
     278: astore        4
     280: aload         4
     282: arraylength
     283: ifle          357
     286: aload_1
     287: ldc           #29                 // String \n\tNumber of locked synchronizers =
     289: invokevirtual #7                  // Method java/lang/StringBuilder.append:(Ljava/lang/String;)Ljava/lang/StringBuilder;
     292: aload         4
     294: arraylength
     295: invokevirtual #30                 // Method java/lang/StringBuilder.append:(I)Ljava/lang/StringBuilder;
     298: bipush        10
     300: invokevirtual #10                 // Method java/lang/StringBuilder.append:(C)Ljava/lang/StringBuilder;
     303: pop
     304: aload         4
     306: astore        5
     308: aload         5
     310: arraylength
     311: istore        6
     313: iconst_0
     314: istore        7
     316: iload         7
     318: iload         6
     320: if_icmpge     357
     323: aload         5
     325: iload         7
     327: aaload
     328: astore        8
     330: aload_1
     331: ldc           #31                 // String \t-
     333: invokevirtual #7                  // Method java/lang/StringBuilder.append:(Ljava/lang/String;)Ljava/lang/StringBuilder;
     336: pop
     337: aload_0
     338: aload_1
     339: aload         8
     341: invokespecial #23                 // Method formatLock:(Ljava/lang/StringBuilder;Ljava/lang/management/LockInfo;)V
     344: aload_1
     345: bipush        10
     347: invokevirtual #10                 // Method java/lang/StringBuilder.append:(C)Ljava/lang/StringBuilder;
     350: pop
     351: iinc          7, 1
     354: goto          316
     357: return

  private void formatLock(java.lang.StringBuilder, java.lang.management.LockInfo);
    Code:
       0: aload_1
       1: bipush        60
       3: invokevirtual #10                 // Method java/lang/StringBuilder.append:(C)Ljava/lang/StringBuilder;
       6: aload_2
       7: invokevirtual #32                 // Method java/lang/management/LockInfo.getIdentityHashCode:()I
      10: invokevirtual #30                 // Method java/lang/StringBuilder.append:(I)Ljava/lang/StringBuilder;
      13: ldc           #33                 // String > (a
      15: invokevirtual #7                  // Method java/lang/StringBuilder.append:(Ljava/lang/String;)Ljava/lang/StringBuilder;
      18: pop
      19: aload_1
      20: aload_2
      21: invokevirtual #34                 // Method java/lang/management/LockInfo.getClassName:()Ljava/lang/String;
      24: invokevirtual #7                  // Method java/lang/StringBuilder.append:(Ljava/lang/String;)Ljava/lang/StringBuilder;
      27: bipush        41
      29: invokevirtual #10                 // Method java/lang/StringBuilder.append:(C)Ljava/lang/StringBuilder;
      32: pop
      33: return

  private void formatState(java.lang.StringBuilder, java.lang.management.ThreadInfo);
    Code:
       0: aload_2
       1: invokevirtual #19                 // Method java/lang/management/ThreadInfo.getThreadState:()Ljava/lang/Thread$State;
       4: astore_3
       5: aload_1
       6: aload_3
       7: invokevirtual #35                 // Method java/lang/StringBuilder.append:(Ljava/lang/Object;)Ljava/lang/StringBuilder;
      10: pop
      11: getstatic     #20                 // Field org/apache/logging/log4j/core/message/ExtendedThreadInformation$1.$SwitchMap$java$lang$Thread$State:[I
      14: aload_3
      15: invokevirtual #21                 // Method java/lang/Thread$State.ordinal:()I
      18: iaload
      19: tableswitch   { // 1 to 3
                     1: 44
                     2: 80
                     3: 268
               default: 486
          }
      44: aload_1
      45: ldc           #36                 // String  (on object monitor owned by \"
      47: invokevirtual #7                  // Method java/lang/StringBuilder.append:(Ljava/lang/String;)Ljava/lang/StringBuilder;
      50: pop
      51: aload_1
      52: aload_2
      53: invokevirtual #37                 // Method java/lang/management/ThreadInfo.getLockOwnerName:()Ljava/lang/String;
      56: invokevirtual #7                  // Method java/lang/StringBuilder.append:(Ljava/lang/String;)Ljava/lang/StringBuilder;
      59: ldc           #38                 // String \" Id=
      61: invokevirtual #7                  // Method java/lang/StringBuilder.append:(Ljava/lang/String;)Ljava/lang/StringBuilder;
      64: aload_2
      65: invokevirtual #39                 // Method java/lang/management/ThreadInfo.getLockOwnerId:()J
      68: invokevirtual #9                  // Method java/lang/StringBuilder.append:(J)Ljava/lang/StringBuilder;
      71: bipush        41
      73: invokevirtual #10                 // Method java/lang/StringBuilder.append:(C)Ljava/lang/StringBuilder;
      76: pop
      77: goto          486
      80: aload_2
      81: invokevirtual #40                 // Method java/lang/management/ThreadInfo.getStackTrace:()[Ljava/lang/StackTraceElement;
      84: iconst_0
      85: aaload
      86: astore        4
      88: aload         4
      90: invokevirtual #41                 // Method java/lang/StackTraceElement.getClassName:()Ljava/lang/String;
      93: astore        5
      95: aload         4
      97: invokevirtual #42                 // Method java/lang/StackTraceElement.getMethodName:()Ljava/lang/String;
     100: astore        6
     102: aload         5
     104: ldc           #43                 // String java.lang.Object
     106: invokevirtual #44                 // Method java/lang/String.equals:(Ljava/lang/Object;)Z
     109: ifeq          174
     112: aload         6
     114: ldc           #45                 // String wait
     116: invokevirtual #44                 // Method java/lang/String.equals:(Ljava/lang/Object;)Z
     119: ifeq          174
     122: aload_1
     123: ldc           #46                 // String  (on object monitor
     125: invokevirtual #7                  // Method java/lang/StringBuilder.append:(Ljava/lang/String;)Ljava/lang/StringBuilder;
     128: pop
     129: aload_2
     130: invokevirtual #37                 // Method java/lang/management/ThreadInfo.getLockOwnerName:()Ljava/lang/String;
     133: ifnull        164
     136: aload_1
     137: ldc           #47                 // String  owned by \"
     139: invokevirtual #7                  // Method java/lang/StringBuilder.append:(Ljava/lang/String;)Ljava/lang/StringBuilder;
     142: pop
     143: aload_1
     144: aload_2
     145: invokevirtual #37                 // Method java/lang/management/ThreadInfo.getLockOwnerName:()Ljava/lang/String;
     148: invokevirtual #7                  // Method java/lang/StringBuilder.append:(Ljava/lang/String;)Ljava/lang/StringBuilder;
     151: ldc           #38                 // String \" Id=
     153: invokevirtual #7                  // Method java/lang/StringBuilder.append:(Ljava/lang/String;)Ljava/lang/StringBuilder;
     156: aload_2
     157: invokevirtual #39                 // Method java/lang/management/ThreadInfo.getLockOwnerId:()J
     160: invokevirtual #9                  // Method java/lang/StringBuilder.append:(J)Ljava/lang/StringBuilder;
     163: pop
     164: aload_1
     165: bipush        41
     167: invokevirtual #10                 // Method java/lang/StringBuilder.append:(C)Ljava/lang/StringBuilder;
     170: pop
     171: goto          486
     174: aload         5
     176: ldc           #48                 // String java.lang.Thread
     178: invokevirtual #44                 // Method java/lang/String.equals:(Ljava/lang/Object;)Z
     181: ifeq          216
     184: aload         6
     186: ldc           #49                 // String join
     188: invokevirtual #44                 // Method java/lang/String.equals:(Ljava/lang/Object;)Z
     191: ifeq          216
     194: aload_1
     195: ldc           #50                 // String  (on completion of thread
     197: invokevirtual #7                  // Method java/lang/StringBuilder.append:(Ljava/lang/String;)Ljava/lang/StringBuilder;
     200: aload_2
     201: invokevirtual #39                 // Method java/lang/management/ThreadInfo.getLockOwnerId:()J
     204: invokevirtual #9                  // Method java/lang/StringBuilder.append:(J)Ljava/lang/StringBuilder;
     207: bipush        41
     209: invokevirtual #10                 // Method java/lang/StringBuilder.append:(C)Ljava/lang/StringBuilder;
     212: pop
     213: goto          486
     216: aload_1
     217: ldc           #51                 // String  (parking for lock
     219: invokevirtual #7                  // Method java/lang/StringBuilder.append:(Ljava/lang/String;)Ljava/lang/StringBuilder;
     222: pop
     223: aload_2
     224: invokevirtual #37                 // Method java/lang/management/ThreadInfo.getLockOwnerName:()Ljava/lang/String;
     227: ifnull        258
     230: aload_1
     231: ldc           #47                 // String  owned by \"
     233: invokevirtual #7                  // Method java/lang/StringBuilder.append:(Ljava/lang/String;)Ljava/lang/StringBuilder;
     236: pop
     237: aload_1
     238: aload_2
     239: invokevirtual #37                 // Method java/lang/management/ThreadInfo.getLockOwnerName:()Ljava/lang/String;
     242: invokevirtual #7                  // Method java/lang/StringBuilder.append:(Ljava/lang/String;)Ljava/lang/StringBuilder;
     245: ldc           #38                 // String \" Id=
     247: invokevirtual #7                  // Method java/lang/StringBuilder.append:(Ljava/lang/String;)Ljava/lang/StringBuilder;
     250: aload_2
     251: invokevirtual #39                 // Method java/lang/management/ThreadInfo.getLockOwnerId:()J
     254: invokevirtual #9                  // Method java/lang/StringBuilder.append:(J)Ljava/lang/StringBuilder;
     257: pop
     258: aload_1
     259: bipush        41
     261: invokevirtual #10                 // Method java/lang/StringBuilder.append:(C)Ljava/lang/StringBuilder;
     264: pop
     265: goto          486
     268: aload_2
     269: invokevirtual #40                 // Method java/lang/management/ThreadInfo.getStackTrace:()[Ljava/lang/StackTraceElement;
     272: iconst_0
     273: aaload
     274: astore        4
     276: aload         4
     278: invokevirtual #41                 // Method java/lang/StackTraceElement.getClassName:()Ljava/lang/String;
     281: astore        5
     283: aload         4
     285: invokevirtual #42                 // Method java/lang/StackTraceElement.getMethodName:()Ljava/lang/String;
     288: astore        6
     290: aload         5
     292: ldc           #43                 // String java.lang.Object
     294: invokevirtual #44                 // Method java/lang/String.equals:(Ljava/lang/Object;)Z
     297: ifeq          362
     300: aload         6
     302: ldc           #45                 // String wait
     304: invokevirtual #44                 // Method java/lang/String.equals:(Ljava/lang/Object;)Z
     307: ifeq          362
     310: aload_1
     311: ldc           #46                 // String  (on object monitor
     313: invokevirtual #7                  // Method java/lang/StringBuilder.append:(Ljava/lang/String;)Ljava/lang/StringBuilder;
     316: pop
     317: aload_2
     318: invokevirtual #37                 // Method java/lang/management/ThreadInfo.getLockOwnerName:()Ljava/lang/String;
     321: ifnull        352
     324: aload_1
     325: ldc           #47                 // String  owned by \"
     327: invokevirtual #7                  // Method java/lang/StringBuilder.append:(Ljava/lang/String;)Ljava/lang/StringBuilder;
     330: pop
     331: aload_1
     332: aload_2
     333: invokevirtual #37                 // Method java/lang/management/ThreadInfo.getLockOwnerName:()Ljava/lang/String;
     336: invokevirtual #7                  // Method java/lang/StringBuilder.append:(Ljava/lang/String;)Ljava/lang/StringBuilder;
     339: ldc           #38                 // String \" Id=
     341: invokevirtual #7                  // Method java/lang/StringBuilder.append:(Ljava/lang/String;)Ljava/lang/StringBuilder;
     344: aload_2
     345: invokevirtual #39                 // Method java/lang/management/ThreadInfo.getLockOwnerId:()J
     348: invokevirtual #9                  // Method java/lang/StringBuilder.append:(J)Ljava/lang/StringBuilder;
     351: pop
     352: aload_1
     353: bipush        41
     355: invokevirtual #10                 // Method java/lang/StringBuilder.append:(C)Ljava/lang/StringBuilder;
     358: pop
     359: goto          486
     362: aload         5
     364: ldc           #48                 // String java.lang.Thread
     366: invokevirtual #44                 // Method java/lang/String.equals:(Ljava/lang/Object;)Z
     369: ifeq          392
     372: aload         6
     374: ldc           #52                 // String sleep
     376: invokevirtual #44                 // Method java/lang/String.equals:(Ljava/lang/Object;)Z
     379: ifeq          392
     382: aload_1
     383: ldc           #53                 // String  (sleeping)
     385: invokevirtual #7                  // Method java/lang/StringBuilder.append:(Ljava/lang/String;)Ljava/lang/StringBuilder;
     388: pop
     389: goto          486
     392: aload         5
     394: ldc           #48                 // String java.lang.Thread
     396: invokevirtual #44                 // Method java/lang/String.equals:(Ljava/lang/Object;)Z
     399: ifeq          434
     402: aload         6
     404: ldc           #49                 // String join
     406: invokevirtual #44                 // Method java/lang/String.equals:(Ljava/lang/Object;)Z
     409: ifeq          434
     412: aload_1
     413: ldc           #50                 // String  (on completion of thread
     415: invokevirtual #7                  // Method java/lang/StringBuilder.append:(Ljava/lang/String;)Ljava/lang/StringBuilder;
     418: aload_2
     419: invokevirtual #39                 // Method java/lang/management/ThreadInfo.getLockOwnerId:()J
     422: invokevirtual #9                  // Method java/lang/StringBuilder.append:(J)Ljava/lang/StringBuilder;
     425: bipush        41
     427: invokevirtual #10                 // Method java/lang/StringBuilder.append:(C)Ljava/lang/StringBuilder;
     430: pop
     431: goto          486
     434: aload_1
     435: ldc           #51                 // String  (parking for lock
     437: invokevirtual #7                  // Method java/lang/StringBuilder.append:(Ljava/lang/String;)Ljava/lang/StringBuilder;
     440: pop
     441: aload_2
     442: invokevirtual #37                 // Method java/lang/management/ThreadInfo.getLockOwnerName:()Ljava/lang/String;
     445: ifnull        476
     448: aload_1
     449: ldc           #47                 // String  owned by \"
     451: invokevirtual #7                  // Method java/lang/StringBuilder.append:(Ljava/lang/String;)Ljava/lang/StringBuilder;
     454: pop
     455: aload_1
     456: aload_2
     457: invokevirtual #37                 // Method java/lang/management/ThreadInfo.getLockOwnerName:()Ljava/lang/String;
     460: invokevirtual #7                  // Method java/lang/StringBuilder.append:(Ljava/lang/String;)Ljava/lang/StringBuilder;
     463: ldc           #38                 // String \" Id=
     465: invokevirtual #7                  // Method java/lang/StringBuilder.append:(Ljava/lang/String;)Ljava/lang/StringBuilder;
     468: aload_2
     469: invokevirtual #39                 // Method java/lang/management/ThreadInfo.getLockOwnerId:()J
     472: invokevirtual #9                  // Method java/lang/StringBuilder.append:(J)Ljava/lang/StringBuilder;
     475: pop
     476: aload_1
     477: bipush        41
     479: invokevirtual #10                 // Method java/lang/StringBuilder.append:(C)Ljava/lang/StringBuilder;
     482: pop
     483: goto          486
     486: return
}
