Compiled from "Principal.java"
public final class io.grpc.xds.shaded.io.envoyproxy.envoy.config.rbac.v2.Principal$IdentifierCase extends java.lang.Enum<io.grpc.xds.shaded.io.envoyproxy.envoy.config.rbac.v2.Principal$IdentifierCase> implements com.google.protobuf.Internal$EnumLite, com.google.protobuf.AbstractMessageLite$InternalOneOfEnum {
  public static final io.grpc.xds.shaded.io.envoyproxy.envoy.config.rbac.v2.Principal$IdentifierCase AND_IDS;

  public static final io.grpc.xds.shaded.io.envoyproxy.envoy.config.rbac.v2.Principal$IdentifierCase OR_IDS;

  public static final io.grpc.xds.shaded.io.envoyproxy.envoy.config.rbac.v2.Principal$IdentifierCase ANY;

  public static final io.grpc.xds.shaded.io.envoyproxy.envoy.config.rbac.v2.Principal$IdentifierCase AUTHENTICATED;

  public static final io.grpc.xds.shaded.io.envoyproxy.envoy.config.rbac.v2.Principal$IdentifierCase SOURCE_IP;

  public static final io.grpc.xds.shaded.io.envoyproxy.envoy.config.rbac.v2.Principal$IdentifierCase DIRECT_REMOTE_IP;

  public static final io.grpc.xds.shaded.io.envoyproxy.envoy.config.rbac.v2.Principal$IdentifierCase REMOTE_IP;

  public static final io.grpc.xds.shaded.io.envoyproxy.envoy.config.rbac.v2.Principal$IdentifierCase HEADER;

  public static final io.grpc.xds.shaded.io.envoyproxy.envoy.config.rbac.v2.Principal$IdentifierCase URL_PATH;

  public static final io.grpc.xds.shaded.io.envoyproxy.envoy.config.rbac.v2.Principal$IdentifierCase METADATA;

  public static final io.grpc.xds.shaded.io.envoyproxy.envoy.config.rbac.v2.Principal$IdentifierCase NOT_ID;

  public static final io.grpc.xds.shaded.io.envoyproxy.envoy.config.rbac.v2.Principal$IdentifierCase IDENTIFIER_NOT_SET;

  private final int value;

  private static final io.grpc.xds.shaded.io.envoyproxy.envoy.config.rbac.v2.Principal$IdentifierCase[] $VALUES;

  public static io.grpc.xds.shaded.io.envoyproxy.envoy.config.rbac.v2.Principal$IdentifierCase[] values();
    Code:
       0: getstatic     #41                 // Field $VALUES:[Lio/grpc/xds/shaded/io/envoyproxy/envoy/config/rbac/v2/Principal$IdentifierCase;
       3: invokevirtual #46                 // Method "[Lio/grpc/xds/shaded/io/envoyproxy/envoy/config/rbac/v2/Principal$IdentifierCase;".clone:()Ljava/lang/Object;
       6: checkcast     #42                 // class "[Lio/grpc/xds/shaded/io/envoyproxy/envoy/config/rbac/v2/Principal$IdentifierCase;"
       9: areturn

  public static io.grpc.xds.shaded.io.envoyproxy.envoy.config.rbac.v2.Principal$IdentifierCase valueOf(java.lang.String);
    Code:
       0: ldc           #2                  // class io/grpc/xds/shaded/io/envoyproxy/envoy/config/rbac/v2/Principal$IdentifierCase
       2: aload_0
       3: invokestatic  #51                 // Method java/lang/Enum.valueOf:(Ljava/lang/Class;Ljava/lang/String;)Ljava/lang/Enum;
       6: checkcast     #2                  // class io/grpc/xds/shaded/io/envoyproxy/envoy/config/rbac/v2/Principal$IdentifierCase
       9: areturn

  private io.grpc.xds.shaded.io.envoyproxy.envoy.config.rbac.v2.Principal$IdentifierCase(int);
    Code:
       0: aload_0
       1: aload_1
       2: iload_2
       3: invokespecial #59                 // Method java/lang/Enum."<init>":(Ljava/lang/String;I)V
       6: aload_0
       7: iload_3
       8: putfield      #61                 // Field value:I
      11: return

  public static io.grpc.xds.shaded.io.envoyproxy.envoy.config.rbac.v2.Principal$IdentifierCase valueOf(int);
    Code:
       0: iload_0
       1: invokestatic  #66                 // Method forNumber:(I)Lio/grpc/xds/shaded/io/envoyproxy/envoy/config/rbac/v2/Principal$IdentifierCase;
       4: areturn

  public static io.grpc.xds.shaded.io.envoyproxy.envoy.config.rbac.v2.Principal$IdentifierCase forNumber(int);
    Code:
       0: iload_0
       1: tableswitch   { // 0 to 11
                     0: 108
                     1: 64
                     2: 68
                     3: 72
                     4: 76
                     5: 80
                     6: 92
                     7: 100
                     8: 104
                     9: 96
                    10: 84
                    11: 88
               default: 112
          }
      64: getstatic     #68                 // Field AND_IDS:Lio/grpc/xds/shaded/io/envoyproxy/envoy/config/rbac/v2/Principal$IdentifierCase;
      67: areturn
      68: getstatic     #70                 // Field OR_IDS:Lio/grpc/xds/shaded/io/envoyproxy/envoy/config/rbac/v2/Principal$IdentifierCase;
      71: areturn
      72: getstatic     #72                 // Field ANY:Lio/grpc/xds/shaded/io/envoyproxy/envoy/config/rbac/v2/Principal$IdentifierCase;
      75: areturn
      76: getstatic     #74                 // Field AUTHENTICATED:Lio/grpc/xds/shaded/io/envoyproxy/envoy/config/rbac/v2/Principal$IdentifierCase;
      79: areturn
      80: getstatic     #76                 // Field SOURCE_IP:Lio/grpc/xds/shaded/io/envoyproxy/envoy/config/rbac/v2/Principal$IdentifierCase;
      83: areturn
      84: getstatic     #78                 // Field DIRECT_REMOTE_IP:Lio/grpc/xds/shaded/io/envoyproxy/envoy/config/rbac/v2/Principal$IdentifierCase;
      87: areturn
      88: getstatic     #80                 // Field REMOTE_IP:Lio/grpc/xds/shaded/io/envoyproxy/envoy/config/rbac/v2/Principal$IdentifierCase;
      91: areturn
      92: getstatic     #82                 // Field HEADER:Lio/grpc/xds/shaded/io/envoyproxy/envoy/config/rbac/v2/Principal$IdentifierCase;
      95: areturn
      96: getstatic     #84                 // Field URL_PATH:Lio/grpc/xds/shaded/io/envoyproxy/envoy/config/rbac/v2/Principal$IdentifierCase;
      99: areturn
     100: getstatic     #86                 // Field METADATA:Lio/grpc/xds/shaded/io/envoyproxy/envoy/config/rbac/v2/Principal$IdentifierCase;
     103: areturn
     104: getstatic     #88                 // Field NOT_ID:Lio/grpc/xds/shaded/io/envoyproxy/envoy/config/rbac/v2/Principal$IdentifierCase;
     107: areturn
     108: getstatic     #90                 // Field IDENTIFIER_NOT_SET:Lio/grpc/xds/shaded/io/envoyproxy/envoy/config/rbac/v2/Principal$IdentifierCase;
     111: areturn
     112: aconst_null
     113: areturn

  public int getNumber();
    Code:
       0: aload_0
       1: getfield      #61                 // Field value:I
       4: ireturn

  static {};
    Code:
       0: new           #2                  // class io/grpc/xds/shaded/io/envoyproxy/envoy/config/rbac/v2/Principal$IdentifierCase
       3: dup
       4: ldc           #95                 // String AND_IDS
       6: iconst_0
       7: iconst_1
       8: invokespecial #97                 // Method "<init>":(Ljava/lang/String;II)V
      11: putstatic     #68                 // Field AND_IDS:Lio/grpc/xds/shaded/io/envoyproxy/envoy/config/rbac/v2/Principal$IdentifierCase;
      14: new           #2                  // class io/grpc/xds/shaded/io/envoyproxy/envoy/config/rbac/v2/Principal$IdentifierCase
      17: dup
      18: ldc           #98                 // String OR_IDS
      20: iconst_1
      21: iconst_2
      22: invokespecial #97                 // Method "<init>":(Ljava/lang/String;II)V
      25: putstatic     #70                 // Field OR_IDS:Lio/grpc/xds/shaded/io/envoyproxy/envoy/config/rbac/v2/Principal$IdentifierCase;
      28: new           #2                  // class io/grpc/xds/shaded/io/envoyproxy/envoy/config/rbac/v2/Principal$IdentifierCase
      31: dup
      32: ldc           #99                 // String ANY
      34: iconst_2
      35: iconst_3
      36: invokespecial #97                 // Method "<init>":(Ljava/lang/String;II)V
      39: putstatic     #72                 // Field ANY:Lio/grpc/xds/shaded/io/envoyproxy/envoy/config/rbac/v2/Principal$IdentifierCase;
      42: new           #2                  // class io/grpc/xds/shaded/io/envoyproxy/envoy/config/rbac/v2/Principal$IdentifierCase
      45: dup
      46: ldc           #100                // String AUTHENTICATED
      48: iconst_3
      49: iconst_4
      50: invokespecial #97                 // Method "<init>":(Ljava/lang/String;II)V
      53: putstatic     #74                 // Field AUTHENTICATED:Lio/grpc/xds/shaded/io/envoyproxy/envoy/config/rbac/v2/Principal$IdentifierCase;
      56: new           #2                  // class io/grpc/xds/shaded/io/envoyproxy/envoy/config/rbac/v2/Principal$IdentifierCase
      59: dup
      60: ldc           #101                // String SOURCE_IP
      62: iconst_4
      63: iconst_5
      64: invokespecial #97                 // Method "<init>":(Ljava/lang/String;II)V
      67: putstatic     #76                 // Field SOURCE_IP:Lio/grpc/xds/shaded/io/envoyproxy/envoy/config/rbac/v2/Principal$IdentifierCase;
      70: new           #2                  // class io/grpc/xds/shaded/io/envoyproxy/envoy/config/rbac/v2/Principal$IdentifierCase
      73: dup
      74: ldc           #102                // String DIRECT_REMOTE_IP
      76: iconst_5
      77: bipush        10
      79: invokespecial #97                 // Method "<init>":(Ljava/lang/String;II)V
      82: putstatic     #78                 // Field DIRECT_REMOTE_IP:Lio/grpc/xds/shaded/io/envoyproxy/envoy/config/rbac/v2/Principal$IdentifierCase;
      85: new           #2                  // class io/grpc/xds/shaded/io/envoyproxy/envoy/config/rbac/v2/Principal$IdentifierCase
      88: dup
      89: ldc           #103                // String REMOTE_IP
      91: bipush        6
      93: bipush        11
      95: invokespecial #97                 // Method "<init>":(Ljava/lang/String;II)V
      98: putstatic     #80                 // Field REMOTE_IP:Lio/grpc/xds/shaded/io/envoyproxy/envoy/config/rbac/v2/Principal$IdentifierCase;
     101: new           #2                  // class io/grpc/xds/shaded/io/envoyproxy/envoy/config/rbac/v2/Principal$IdentifierCase
     104: dup
     105: ldc           #104                // String HEADER
     107: bipush        7
     109: bipush        6
     111: invokespecial #97                 // Method "<init>":(Ljava/lang/String;II)V
     114: putstatic     #82                 // Field HEADER:Lio/grpc/xds/shaded/io/envoyproxy/envoy/config/rbac/v2/Principal$IdentifierCase;
     117: new           #2                  // class io/grpc/xds/shaded/io/envoyproxy/envoy/config/rbac/v2/Principal$IdentifierCase
     120: dup
     121: ldc           #105                // String URL_PATH
     123: bipush        8
     125: bipush        9
     127: invokespecial #97                 // Method "<init>":(Ljava/lang/String;II)V
     130: putstatic     #84                 // Field URL_PATH:Lio/grpc/xds/shaded/io/envoyproxy/envoy/config/rbac/v2/Principal$IdentifierCase;
     133: new           #2                  // class io/grpc/xds/shaded/io/envoyproxy/envoy/config/rbac/v2/Principal$IdentifierCase
     136: dup
     137: ldc           #106                // String METADATA
     139: bipush        9
     141: bipush        7
     143: invokespecial #97                 // Method "<init>":(Ljava/lang/String;II)V
     146: putstatic     #86                 // Field METADATA:Lio/grpc/xds/shaded/io/envoyproxy/envoy/config/rbac/v2/Principal$IdentifierCase;
     149: new           #2                  // class io/grpc/xds/shaded/io/envoyproxy/envoy/config/rbac/v2/Principal$IdentifierCase
     152: dup
     153: ldc           #107                // String NOT_ID
     155: bipush        10
     157: bipush        8
     159: invokespecial #97                 // Method "<init>":(Ljava/lang/String;II)V
     162: putstatic     #88                 // Field NOT_ID:Lio/grpc/xds/shaded/io/envoyproxy/envoy/config/rbac/v2/Principal$IdentifierCase;
     165: new           #2                  // class io/grpc/xds/shaded/io/envoyproxy/envoy/config/rbac/v2/Principal$IdentifierCase
     168: dup
     169: ldc           #108                // String IDENTIFIER_NOT_SET
     171: bipush        11
     173: iconst_0
     174: invokespecial #97                 // Method "<init>":(Ljava/lang/String;II)V
     177: putstatic     #90                 // Field IDENTIFIER_NOT_SET:Lio/grpc/xds/shaded/io/envoyproxy/envoy/config/rbac/v2/Principal$IdentifierCase;
     180: bipush        12
     182: anewarray     #2                  // class io/grpc/xds/shaded/io/envoyproxy/envoy/config/rbac/v2/Principal$IdentifierCase
     185: dup
     186: iconst_0
     187: getstatic     #68                 // Field AND_IDS:Lio/grpc/xds/shaded/io/envoyproxy/envoy/config/rbac/v2/Principal$IdentifierCase;
     190: aastore
     191: dup
     192: iconst_1
     193: getstatic     #70                 // Field OR_IDS:Lio/grpc/xds/shaded/io/envoyproxy/envoy/config/rbac/v2/Principal$IdentifierCase;
     196: aastore
     197: dup
     198: iconst_2
     199: getstatic     #72                 // Field ANY:Lio/grpc/xds/shaded/io/envoyproxy/envoy/config/rbac/v2/Principal$IdentifierCase;
     202: aastore
     203: dup
     204: iconst_3
     205: getstatic     #74                 // Field AUTHENTICATED:Lio/grpc/xds/shaded/io/envoyproxy/envoy/config/rbac/v2/Principal$IdentifierCase;
     208: aastore
     209: dup
     210: iconst_4
     211: getstatic     #76                 // Field SOURCE_IP:Lio/grpc/xds/shaded/io/envoyproxy/envoy/config/rbac/v2/Principal$IdentifierCase;
     214: aastore
     215: dup
     216: iconst_5
     217: getstatic     #78                 // Field DIRECT_REMOTE_IP:Lio/grpc/xds/shaded/io/envoyproxy/envoy/config/rbac/v2/Principal$IdentifierCase;
     220: aastore
     221: dup
     222: bipush        6
     224: getstatic     #80                 // Field REMOTE_IP:Lio/grpc/xds/shaded/io/envoyproxy/envoy/config/rbac/v2/Principal$IdentifierCase;
     227: aastore
     228: dup
     229: bipush        7
     231: getstatic     #82                 // Field HEADER:Lio/grpc/xds/shaded/io/envoyproxy/envoy/config/rbac/v2/Principal$IdentifierCase;
     234: aastore
     235: dup
     236: bipush        8
     238: getstatic     #84                 // Field URL_PATH:Lio/grpc/xds/shaded/io/envoyproxy/envoy/config/rbac/v2/Principal$IdentifierCase;
     241: aastore
     242: dup
     243: bipush        9
     245: getstatic     #86                 // Field METADATA:Lio/grpc/xds/shaded/io/envoyproxy/envoy/config/rbac/v2/Principal$IdentifierCase;
     248: aastore
     249: dup
     250: bipush        10
     252: getstatic     #88                 // Field NOT_ID:Lio/grpc/xds/shaded/io/envoyproxy/envoy/config/rbac/v2/Principal$IdentifierCase;
     255: aastore
     256: dup
     257: bipush        11
     259: getstatic     #90                 // Field IDENTIFIER_NOT_SET:Lio/grpc/xds/shaded/io/envoyproxy/envoy/config/rbac/v2/Principal$IdentifierCase;
     262: aastore
     263: putstatic     #41                 // Field $VALUES:[Lio/grpc/xds/shaded/io/envoyproxy/envoy/config/rbac/v2/Principal$IdentifierCase;
     266: return
}
