Compiled from "MessageListenerContainer.java"
public class org.apache.cxf.transport.jms.util.MessageListenerContainer extends org.apache.cxf.transport.jms.util.AbstractMessageListenerContainer {
  private javax.jms.MessageConsumer consumer;

  private javax.jms.Session session;

  public org.apache.cxf.transport.jms.util.MessageListenerContainer(javax.jms.Connection, javax.jms.Destination, javax.jms.MessageListener);
    Code:
       0: aload_0
       1: invokespecial #1                  // Method org/apache/cxf/transport/jms/util/AbstractMessageListenerContainer."<init>":()V
       4: aload_0
       5: aload_1
       6: putfield      #2                  // Field connection:Ljavax/jms/Connection;
       9: aload_0
      10: aload_2
      11: putfield      #3                  // Field destination:Ljavax/jms/Destination;
      14: aload_0
      15: aload_3
      16: putfield      #4                  // Field listenerHandler:Ljavax/jms/MessageListener;
      19: return

  public void start();
    Code:
       0: aload_0
       1: aload_0
       2: getfield      #2                  // Field connection:Ljavax/jms/Connection;
       5: aload_0
       6: getfield      #5                  // Field transacted:Z
       9: aload_0
      10: getfield      #6                  // Field acknowledgeMode:I
      13: invokeinterface #7,  3            // InterfaceMethod javax/jms/Connection.createSession:(ZI)Ljavax/jms/Session;
      18: putfield      #8                  // Field session:Ljavax/jms/Session;
      21: aload_0
      22: getfield      #9                  // Field durableSubscriptionName:Ljava/lang/String;
      25: ifnull        73
      28: aload_0
      29: getfield      #3                  // Field destination:Ljavax/jms/Destination;
      32: instanceof    #10                 // class javax/jms/Topic
      35: ifeq          73
      38: aload_0
      39: aload_0
      40: getfield      #8                  // Field session:Ljavax/jms/Session;
      43: aload_0
      44: getfield      #3                  // Field destination:Ljavax/jms/Destination;
      47: checkcast     #10                 // class javax/jms/Topic
      50: aload_0
      51: getfield      #9                  // Field durableSubscriptionName:Ljava/lang/String;
      54: aload_0
      55: getfield      #11                 // Field messageSelector:Ljava/lang/String;
      58: aload_0
      59: getfield      #12                 // Field pubSubNoLocal:Z
      62: invokeinterface #13,  5           // InterfaceMethod javax/jms/Session.createDurableSubscriber:(Ljavax/jms/Topic;Ljava/lang/String;Ljava/lang/String;Z)Ljavax/jms/TopicSubscriber;
      67: putfield      #14                 // Field consumer:Ljavax/jms/MessageConsumer;
      70: goto          94
      73: aload_0
      74: aload_0
      75: getfield      #8                  // Field session:Ljavax/jms/Session;
      78: aload_0
      79: getfield      #3                  // Field destination:Ljavax/jms/Destination;
      82: aload_0
      83: getfield      #11                 // Field messageSelector:Ljava/lang/String;
      86: invokeinterface #15,  3           // InterfaceMethod javax/jms/Session.createConsumer:(Ljavax/jms/Destination;Ljava/lang/String;)Ljavax/jms/MessageConsumer;
      91: putfield      #14                 // Field consumer:Ljavax/jms/MessageConsumer;
      94: new           #16                 // class org/apache/cxf/transport/jms/util/MessageListenerContainer$LocalTransactionalMessageListener
      97: dup
      98: aload_0
      99: getfield      #8                  // Field session:Ljavax/jms/Session;
     102: aload_0
     103: getfield      #4                  // Field listenerHandler:Ljavax/jms/MessageListener;
     106: invokespecial #17                 // Method org/apache/cxf/transport/jms/util/MessageListenerContainer$LocalTransactionalMessageListener."<init>":(Ljavax/jms/Session;Ljavax/jms/MessageListener;)V
     109: astore_1
     110: aload_0
     111: getfield      #14                 // Field consumer:Ljavax/jms/MessageConsumer;
     114: aload_1
     115: invokeinterface #18,  2           // InterfaceMethod javax/jms/MessageConsumer.setMessageListener:(Ljavax/jms/MessageListener;)V
     120: aload_0
     121: iconst_1
     122: putfield      #19                 // Field running:Z
     125: goto          134
     128: astore_1
     129: aload_1
     130: invokestatic  #21                 // Method org/apache/cxf/transport/jms/util/JMSUtil.convertJmsException:(Ljavax/jms/JMSException;)Ljava/lang/RuntimeException;
     133: athrow
     134: return
    Exception table:
       from    to  target type
           0   125   128   Class javax/jms/JMSException

  public void stop();
    Code:
       0: aload_0
       1: iconst_0
       2: putfield      #19                 // Field running:Z
       5: aload_0
       6: getfield      #14                 // Field consumer:Ljavax/jms/MessageConsumer;
       9: invokestatic  #22                 // Method org/apache/cxf/transport/jms/util/ResourceCloser.close:(Ljava/lang/Object;)V
      12: aload_0
      13: getfield      #8                  // Field session:Ljavax/jms/Session;
      16: invokestatic  #22                 // Method org/apache/cxf/transport/jms/util/ResourceCloser.close:(Ljava/lang/Object;)V
      19: aload_0
      20: aconst_null
      21: putfield      #14                 // Field consumer:Ljavax/jms/MessageConsumer;
      24: aload_0
      25: aconst_null
      26: putfield      #8                  // Field session:Ljavax/jms/Session;
      29: return

  public void shutdown();
    Code:
       0: aload_0
       1: invokevirtual #23                 // Method stop:()V
       4: aload_0
       5: getfield      #2                  // Field connection:Ljavax/jms/Connection;
       8: invokestatic  #22                 // Method org/apache/cxf/transport/jms/util/ResourceCloser.close:(Ljava/lang/Object;)V
      11: return
}
