Compiled from "NumberDeserializers.java"
public final class com.fasterxml.jackson.databind.deser.std.NumberDeserializers$LongDeserializer extends com.fasterxml.jackson.databind.deser.std.NumberDeserializers$PrimitiveOrWrapperDeserializer<java.lang.Long> {
  private static final long serialVersionUID;

  static final com.fasterxml.jackson.databind.deser.std.NumberDeserializers$LongDeserializer primitiveInstance;

  static final com.fasterxml.jackson.databind.deser.std.NumberDeserializers$LongDeserializer wrapperInstance;

  public com.fasterxml.jackson.databind.deser.std.NumberDeserializers$LongDeserializer(java.lang.Class<java.lang.Long>, java.lang.Long);
    Code:
       0: aload_0
       1: aload_1
       2: getstatic     #1                  // Field com/fasterxml/jackson/databind/type/LogicalType.Integer:Lcom/fasterxml/jackson/databind/type/LogicalType;
       5: aload_2
       6: lconst_0
       7: invokestatic  #2                  // Method java/lang/Long.valueOf:(J)Ljava/lang/Long;
      10: invokespecial #3                  // Method com/fasterxml/jackson/databind/deser/std/NumberDeserializers$PrimitiveOrWrapperDeserializer."<init>":(Ljava/lang/Class;Lcom/fasterxml/jackson/databind/type/LogicalType;Ljava/lang/Object;Ljava/lang/Object;)V
      13: return

  public boolean isCachable();
    Code:
       0: iconst_1
       1: ireturn

  public java.lang.Long deserialize(com.fasterxml.jackson.core.JsonParser, com.fasterxml.jackson.databind.DeserializationContext) throws java.io.IOException;
    Code:
       0: aload_1
       1: invokevirtual #4                  // Method com/fasterxml/jackson/core/JsonParser.isExpectedNumberIntToken:()Z
       4: ifeq          15
       7: aload_1
       8: invokevirtual #5                  // Method com/fasterxml/jackson/core/JsonParser.getLongValue:()J
      11: invokestatic  #2                  // Method java/lang/Long.valueOf:(J)Ljava/lang/Long;
      14: areturn
      15: aload_0
      16: getfield      #6                  // Field _primitive:Z
      19: ifeq          32
      22: aload_0
      23: aload_1
      24: aload_2
      25: invokevirtual #7                  // Method _parseLongPrimitive:(Lcom/fasterxml/jackson/core/JsonParser;Lcom/fasterxml/jackson/databind/DeserializationContext;)J
      28: invokestatic  #2                  // Method java/lang/Long.valueOf:(J)Ljava/lang/Long;
      31: areturn
      32: aload_0
      33: aload_1
      34: aload_2
      35: ldc           #8                  // class java/lang/Long
      37: invokevirtual #9                  // Method _parseLong:(Lcom/fasterxml/jackson/core/JsonParser;Lcom/fasterxml/jackson/databind/DeserializationContext;Ljava/lang/Class;)Ljava/lang/Long;
      40: areturn

  public java.lang.Object getEmptyValue(com.fasterxml.jackson.databind.DeserializationContext) throws com.fasterxml.jackson.databind.JsonMappingException;
    Code:
       0: aload_0
       1: aload_1
       2: invokespecial #10                 // Method com/fasterxml/jackson/databind/deser/std/NumberDeserializers$PrimitiveOrWrapperDeserializer.getEmptyValue:(Lcom/fasterxml/jackson/databind/DeserializationContext;)Ljava/lang/Object;
       5: areturn

  public com.fasterxml.jackson.databind.util.AccessPattern getNullAccessPattern();
    Code:
       0: aload_0
       1: invokespecial #11                 // Method com/fasterxml/jackson/databind/deser/std/NumberDeserializers$PrimitiveOrWrapperDeserializer.getNullAccessPattern:()Lcom/fasterxml/jackson/databind/util/AccessPattern;
       4: areturn

  public java.lang.Object deserialize(com.fasterxml.jackson.core.JsonParser, com.fasterxml.jackson.databind.DeserializationContext) throws java.io.IOException, com.fasterxml.jackson.core.JacksonException;
    Code:
       0: aload_0
       1: aload_1
       2: aload_2
       3: invokevirtual #12                 // Method deserialize:(Lcom/fasterxml/jackson/core/JsonParser;Lcom/fasterxml/jackson/databind/DeserializationContext;)Ljava/lang/Long;
       6: areturn

  static {};
    Code:
       0: new           #13                 // class com/fasterxml/jackson/databind/deser/std/NumberDeserializers$LongDeserializer
       3: dup
       4: getstatic     #14                 // Field java/lang/Long.TYPE:Ljava/lang/Class;
       7: lconst_0
       8: invokestatic  #2                  // Method java/lang/Long.valueOf:(J)Ljava/lang/Long;
      11: invokespecial #15                 // Method "<init>":(Ljava/lang/Class;Ljava/lang/Long;)V
      14: putstatic     #16                 // Field primitiveInstance:Lcom/fasterxml/jackson/databind/deser/std/NumberDeserializers$LongDeserializer;
      17: new           #13                 // class com/fasterxml/jackson/databind/deser/std/NumberDeserializers$LongDeserializer
      20: dup
      21: ldc           #8                  // class java/lang/Long
      23: aconst_null
      24: invokespecial #15                 // Method "<init>":(Ljava/lang/Class;Ljava/lang/Long;)V
      27: putstatic     #17                 // Field wrapperInstance:Lcom/fasterxml/jackson/databind/deser/std/NumberDeserializers$LongDeserializer;
      30: return
}
