Compiled from "NumberDeserializers.java"
public class com.fasterxml.jackson.databind.deser.std.NumberDeserializers$BigDecimalDeserializer extends com.fasterxml.jackson.databind.deser.std.StdScalarDeserializer<java.math.BigDecimal> {
  public static final com.fasterxml.jackson.databind.deser.std.NumberDeserializers$BigDecimalDeserializer instance;

  public com.fasterxml.jackson.databind.deser.std.NumberDeserializers$BigDecimalDeserializer();
    Code:
       0: aload_0
       1: ldc           #1                  // class java/math/BigDecimal
       3: invokespecial #2                  // Method com/fasterxml/jackson/databind/deser/std/StdScalarDeserializer."<init>":(Ljava/lang/Class;)V
       6: return

  public java.lang.Object getEmptyValue(com.fasterxml.jackson.databind.DeserializationContext);
    Code:
       0: getstatic     #3                  // Field java/math/BigDecimal.ZERO:Ljava/math/BigDecimal;
       3: areturn

  public final com.fasterxml.jackson.databind.type.LogicalType logicalType();
    Code:
       0: getstatic     #4                  // Field com/fasterxml/jackson/databind/type/LogicalType.Float:Lcom/fasterxml/jackson/databind/type/LogicalType;
       3: areturn

  public java.math.BigDecimal deserialize(com.fasterxml.jackson.core.JsonParser, com.fasterxml.jackson.databind.DeserializationContext) throws java.io.IOException;
    Code:
       0: aload_1
       1: invokevirtual #5                  // Method com/fasterxml/jackson/core/JsonParser.currentTokenId:()I
       4: tableswitch   { // 1 to 8
                     1: 111
                     2: 135
                     3: 125
                     4: 135
                     5: 135
                     6: 103
                     7: 52
                     8: 98
               default: 135
          }
      52: aload_0
      53: aload_1
      54: aload_2
      55: aload_0
      56: getfield      #6                  // Field _valueClass:Ljava/lang/Class;
      59: invokevirtual #7                  // Method _checkIntToFloatCoercion:(Lcom/fasterxml/jackson/core/JsonParser;Lcom/fasterxml/jackson/databind/DeserializationContext;Ljava/lang/Class;)Lcom/fasterxml/jackson/databind/cfg/CoercionAction;
      62: astore        4
      64: aload         4
      66: getstatic     #8                  // Field com/fasterxml/jackson/databind/cfg/CoercionAction.AsNull:Lcom/fasterxml/jackson/databind/cfg/CoercionAction;
      69: if_acmpne     81
      72: aload_0
      73: aload_2
      74: invokevirtual #9                  // Method getNullValue:(Lcom/fasterxml/jackson/databind/DeserializationContext;)Ljava/lang/Object;
      77: checkcast     #1                  // class java/math/BigDecimal
      80: areturn
      81: aload         4
      83: getstatic     #10                 // Field com/fasterxml/jackson/databind/cfg/CoercionAction.AsEmpty:Lcom/fasterxml/jackson/databind/cfg/CoercionAction;
      86: if_acmpne     98
      89: aload_0
      90: aload_2
      91: invokevirtual #11                 // Method getEmptyValue:(Lcom/fasterxml/jackson/databind/DeserializationContext;)Ljava/lang/Object;
      94: checkcast     #1                  // class java/math/BigDecimal
      97: areturn
      98: aload_1
      99: invokevirtual #12                 // Method com/fasterxml/jackson/core/JsonParser.getDecimalValue:()Ljava/math/BigDecimal;
     102: areturn
     103: aload_1
     104: invokevirtual #13                 // Method com/fasterxml/jackson/core/JsonParser.getText:()Ljava/lang/String;
     107: astore_3
     108: goto          149
     111: aload_2
     112: aload_1
     113: aload_0
     114: aload_0
     115: getfield      #6                  // Field _valueClass:Ljava/lang/Class;
     118: invokevirtual #14                 // Method com/fasterxml/jackson/databind/DeserializationContext.extractScalarFromObject:(Lcom/fasterxml/jackson/core/JsonParser;Lcom/fasterxml/jackson/databind/JsonDeserializer;Ljava/lang/Class;)Ljava/lang/String;
     121: astore_3
     122: goto          149
     125: aload_0
     126: aload_1
     127: aload_2
     128: invokevirtual #15                 // Method _deserializeFromArray:(Lcom/fasterxml/jackson/core/JsonParser;Lcom/fasterxml/jackson/databind/DeserializationContext;)Ljava/lang/Object;
     131: checkcast     #1                  // class java/math/BigDecimal
     134: areturn
     135: aload_2
     136: aload_0
     137: aload_2
     138: invokevirtual #16                 // Method getValueType:(Lcom/fasterxml/jackson/databind/DeserializationContext;)Lcom/fasterxml/jackson/databind/JavaType;
     141: aload_1
     142: invokevirtual #17                 // Method com/fasterxml/jackson/databind/DeserializationContext.handleUnexpectedToken:(Lcom/fasterxml/jackson/databind/JavaType;Lcom/fasterxml/jackson/core/JsonParser;)Ljava/lang/Object;
     145: checkcast     #1                  // class java/math/BigDecimal
     148: areturn
     149: aload_0
     150: aload_2
     151: aload_3
     152: invokevirtual #18                 // Method _checkFromStringCoercion:(Lcom/fasterxml/jackson/databind/DeserializationContext;Ljava/lang/String;)Lcom/fasterxml/jackson/databind/cfg/CoercionAction;
     155: astore        4
     157: aload         4
     159: getstatic     #8                  // Field com/fasterxml/jackson/databind/cfg/CoercionAction.AsNull:Lcom/fasterxml/jackson/databind/cfg/CoercionAction;
     162: if_acmpne     174
     165: aload_0
     166: aload_2
     167: invokevirtual #9                  // Method getNullValue:(Lcom/fasterxml/jackson/databind/DeserializationContext;)Ljava/lang/Object;
     170: checkcast     #1                  // class java/math/BigDecimal
     173: areturn
     174: aload         4
     176: getstatic     #10                 // Field com/fasterxml/jackson/databind/cfg/CoercionAction.AsEmpty:Lcom/fasterxml/jackson/databind/cfg/CoercionAction;
     179: if_acmpne     191
     182: aload_0
     183: aload_2
     184: invokevirtual #11                 // Method getEmptyValue:(Lcom/fasterxml/jackson/databind/DeserializationContext;)Ljava/lang/Object;
     187: checkcast     #1                  // class java/math/BigDecimal
     190: areturn
     191: aload_3
     192: invokevirtual #19                 // Method java/lang/String.trim:()Ljava/lang/String;
     195: astore_3
     196: aload_0
     197: aload_3
     198: invokevirtual #20                 // Method _hasTextualNull:(Ljava/lang/String;)Z
     201: ifeq          213
     204: aload_0
     205: aload_2
     206: invokevirtual #9                  // Method getNullValue:(Lcom/fasterxml/jackson/databind/DeserializationContext;)Ljava/lang/Object;
     209: checkcast     #1                  // class java/math/BigDecimal
     212: areturn
     213: aload_3
     214: invokestatic  #21                 // Method com/fasterxml/jackson/core/io/NumberInput.parseBigDecimal:(Ljava/lang/String;)Ljava/math/BigDecimal;
     217: areturn
     218: astore        5
     220: aload_2
     221: aload_0
     222: getfield      #6                  // Field _valueClass:Ljava/lang/Class;
     225: aload_3
     226: ldc           #23                 // String not a valid representation
     228: iconst_0
     229: anewarray     #24                 // class java/lang/Object
     232: invokevirtual #25                 // Method com/fasterxml/jackson/databind/DeserializationContext.handleWeirdStringValue:(Ljava/lang/Class;Ljava/lang/String;Ljava/lang/String;[Ljava/lang/Object;)Ljava/lang/Object;
     235: checkcast     #1                  // class java/math/BigDecimal
     238: areturn
    Exception table:
       from    to  target type
         213   217   218   Class java/lang/IllegalArgumentException

  public java.lang.Object deserialize(com.fasterxml.jackson.core.JsonParser, com.fasterxml.jackson.databind.DeserializationContext) throws java.io.IOException, com.fasterxml.jackson.core.JacksonException;
    Code:
       0: aload_0
       1: aload_1
       2: aload_2
       3: invokevirtual #26                 // Method deserialize:(Lcom/fasterxml/jackson/core/JsonParser;Lcom/fasterxml/jackson/databind/DeserializationContext;)Ljava/math/BigDecimal;
       6: areturn

  static {};
    Code:
       0: new           #27                 // class com/fasterxml/jackson/databind/deser/std/NumberDeserializers$BigDecimalDeserializer
       3: dup
       4: invokespecial #28                 // Method "<init>":()V
       7: putstatic     #29                 // Field instance:Lcom/fasterxml/jackson/databind/deser/std/NumberDeserializers$BigDecimalDeserializer;
      10: return
}
