Compiled from "StdDeserializer.java"
public abstract class com.fasterxml.jackson.databind.deser.std.StdDeserializer<T> extends com.fasterxml.jackson.databind.JsonDeserializer<T> implements java.io.Serializable, com.fasterxml.jackson.databind.deser.ValueInstantiator$Gettable {
  private static final long serialVersionUID;

  protected static final int F_MASK_INT_COERCIONS;

  protected static final int F_MASK_ACCEPT_ARRAYS;

  protected final java.lang.Class<?> _valueClass;

  protected final com.fasterxml.jackson.databind.JavaType _valueType;

  protected com.fasterxml.jackson.databind.deser.std.StdDeserializer(java.lang.Class<?>);
    Code:
       0: aload_0
       1: invokespecial #1                  // Method com/fasterxml/jackson/databind/JsonDeserializer."<init>":()V
       4: aload_0
       5: aload_1
       6: putfield      #2                  // Field _valueClass:Ljava/lang/Class;
       9: aload_0
      10: aconst_null
      11: putfield      #3                  // Field _valueType:Lcom/fasterxml/jackson/databind/JavaType;
      14: return

  protected com.fasterxml.jackson.databind.deser.std.StdDeserializer(com.fasterxml.jackson.databind.JavaType);
    Code:
       0: aload_0
       1: invokespecial #1                  // Method com/fasterxml/jackson/databind/JsonDeserializer."<init>":()V
       4: aload_0
       5: aload_1
       6: ifnonnull     14
       9: ldc           #4                  // class java/lang/Object
      11: goto          18
      14: aload_1
      15: invokevirtual #5                  // Method com/fasterxml/jackson/databind/JavaType.getRawClass:()Ljava/lang/Class;
      18: putfield      #2                  // Field _valueClass:Ljava/lang/Class;
      21: aload_0
      22: aload_1
      23: putfield      #3                  // Field _valueType:Lcom/fasterxml/jackson/databind/JavaType;
      26: return

  protected com.fasterxml.jackson.databind.deser.std.StdDeserializer(com.fasterxml.jackson.databind.deser.std.StdDeserializer<?>);
    Code:
       0: aload_0
       1: invokespecial #1                  // Method com/fasterxml/jackson/databind/JsonDeserializer."<init>":()V
       4: aload_0
       5: aload_1
       6: getfield      #2                  // Field _valueClass:Ljava/lang/Class;
       9: putfield      #2                  // Field _valueClass:Ljava/lang/Class;
      12: aload_0
      13: aload_1
      14: getfield      #3                  // Field _valueType:Lcom/fasterxml/jackson/databind/JavaType;
      17: putfield      #3                  // Field _valueType:Lcom/fasterxml/jackson/databind/JavaType;
      20: return

  public java.lang.Class<?> handledType();
    Code:
       0: aload_0
       1: getfield      #2                  // Field _valueClass:Ljava/lang/Class;
       4: areturn

  public final java.lang.Class<?> getValueClass();
    Code:
       0: aload_0
       1: getfield      #2                  // Field _valueClass:Ljava/lang/Class;
       4: areturn

  public com.fasterxml.jackson.databind.JavaType getValueType();
    Code:
       0: aload_0
       1: getfield      #3                  // Field _valueType:Lcom/fasterxml/jackson/databind/JavaType;
       4: areturn

  public com.fasterxml.jackson.databind.JavaType getValueType(com.fasterxml.jackson.databind.DeserializationContext);
    Code:
       0: aload_0
       1: getfield      #3                  // Field _valueType:Lcom/fasterxml/jackson/databind/JavaType;
       4: ifnull        12
       7: aload_0
       8: getfield      #3                  // Field _valueType:Lcom/fasterxml/jackson/databind/JavaType;
      11: areturn
      12: aload_1
      13: aload_0
      14: getfield      #2                  // Field _valueClass:Ljava/lang/Class;
      17: invokevirtual #6                  // Method com/fasterxml/jackson/databind/DeserializationContext.constructType:(Ljava/lang/Class;)Lcom/fasterxml/jackson/databind/JavaType;
      20: areturn

  public com.fasterxml.jackson.databind.deser.ValueInstantiator getValueInstantiator();
    Code:
       0: aconst_null
       1: areturn

  protected boolean isDefaultDeserializer(com.fasterxml.jackson.databind.JsonDeserializer<?>);
    Code:
       0: aload_1
       1: invokestatic  #7                  // Method com/fasterxml/jackson/databind/util/ClassUtil.isJacksonStdImpl:(Ljava/lang/Object;)Z
       4: ireturn

  protected boolean isDefaultKeyDeserializer(com.fasterxml.jackson.databind.KeyDeserializer);
    Code:
       0: aload_1
       1: invokestatic  #7                  // Method com/fasterxml/jackson/databind/util/ClassUtil.isJacksonStdImpl:(Ljava/lang/Object;)Z
       4: ireturn

  public java.lang.Object deserializeWithType(com.fasterxml.jackson.core.JsonParser, com.fasterxml.jackson.databind.DeserializationContext, com.fasterxml.jackson.databind.jsontype.TypeDeserializer) throws java.io.IOException;
    Code:
       0: aload_3
       1: aload_1
       2: aload_2
       3: invokevirtual #8                  // Method com/fasterxml/jackson/databind/jsontype/TypeDeserializer.deserializeTypedFromAny:(Lcom/fasterxml/jackson/core/JsonParser;Lcom/fasterxml/jackson/databind/DeserializationContext;)Ljava/lang/Object;
       6: areturn

  protected T _deserializeFromArray(com.fasterxml.jackson.core.JsonParser, com.fasterxml.jackson.databind.DeserializationContext) throws java.io.IOException;
    Code:
       0: aload_0
       1: aload_2
       2: invokevirtual #9                  // Method _findCoercionFromEmptyArray:(Lcom/fasterxml/jackson/databind/DeserializationContext;)Lcom/fasterxml/jackson/databind/cfg/CoercionAction;
       5: astore_3
       6: aload_2
       7: getstatic     #10                 // Field com/fasterxml/jackson/databind/DeserializationFeature.UNWRAP_SINGLE_VALUE_ARRAYS:Lcom/fasterxml/jackson/databind/DeserializationFeature;
      10: invokevirtual #11                 // Method com/fasterxml/jackson/databind/DeserializationContext.isEnabled:(Lcom/fasterxml/jackson/databind/DeserializationFeature;)Z
      13: istore        4
      15: iload         4
      17: ifne          27
      20: aload_3
      21: getstatic     #12                 // Field com/fasterxml/jackson/databind/cfg/CoercionAction.Fail:Lcom/fasterxml/jackson/databind/cfg/CoercionAction;
      24: if_acmpeq     123
      27: aload_1
      28: invokevirtual #13                 // Method com/fasterxml/jackson/core/JsonParser.nextToken:()Lcom/fasterxml/jackson/core/JsonToken;
      31: astore        5
      33: aload         5
      35: getstatic     #14                 // Field com/fasterxml/jackson/core/JsonToken.END_ARRAY:Lcom/fasterxml/jackson/core/JsonToken;
      38: if_acmpne     91
      41: getstatic     #15                 // Field com/fasterxml/jackson/databind/deser/std/StdDeserializer$1.$SwitchMap$com$fasterxml$jackson$databind$cfg$CoercionAction:[I
      44: aload_3
      45: invokevirtual #16                 // Method com/fasterxml/jackson/databind/cfg/CoercionAction.ordinal:()I
      48: iaload
      49: tableswitch   { // 1 to 3
                     1: 76
                     2: 82
                     3: 82
               default: 88
          }
      76: aload_0
      77: aload_2
      78: invokevirtual #17                 // Method getEmptyValue:(Lcom/fasterxml/jackson/databind/DeserializationContext;)Ljava/lang/Object;
      81: areturn
      82: aload_0
      83: aload_2
      84: invokevirtual #18                 // Method getNullValue:(Lcom/fasterxml/jackson/databind/DeserializationContext;)Ljava/lang/Object;
      87: areturn
      88: goto          123
      91: iload         4
      93: ifeq          123
      96: aload_0
      97: aload_1
      98: aload_2
      99: invokevirtual #19                 // Method _deserializeWrappedValue:(Lcom/fasterxml/jackson/core/JsonParser;Lcom/fasterxml/jackson/databind/DeserializationContext;)Ljava/lang/Object;
     102: astore        6
     104: aload_1
     105: invokevirtual #13                 // Method com/fasterxml/jackson/core/JsonParser.nextToken:()Lcom/fasterxml/jackson/core/JsonToken;
     108: getstatic     #14                 // Field com/fasterxml/jackson/core/JsonToken.END_ARRAY:Lcom/fasterxml/jackson/core/JsonToken;
     111: if_acmpeq     120
     114: aload_0
     115: aload_1
     116: aload_2
     117: invokevirtual #20                 // Method handleMissingEndArrayForSingle:(Lcom/fasterxml/jackson/core/JsonParser;Lcom/fasterxml/jackson/databind/DeserializationContext;)V
     120: aload         6
     122: areturn
     123: aload_2
     124: aload_0
     125: aload_2
     126: invokevirtual #21                 // Method getValueType:(Lcom/fasterxml/jackson/databind/DeserializationContext;)Lcom/fasterxml/jackson/databind/JavaType;
     129: getstatic     #22                 // Field com/fasterxml/jackson/core/JsonToken.START_ARRAY:Lcom/fasterxml/jackson/core/JsonToken;
     132: aload_1
     133: aconst_null
     134: iconst_0
     135: anewarray     #4                  // class java/lang/Object
     138: invokevirtual #23                 // Method com/fasterxml/jackson/databind/DeserializationContext.handleUnexpectedToken:(Lcom/fasterxml/jackson/databind/JavaType;Lcom/fasterxml/jackson/core/JsonToken;Lcom/fasterxml/jackson/core/JsonParser;Ljava/lang/String;[Ljava/lang/Object;)Ljava/lang/Object;
     141: areturn

  protected T _deserializeFromEmpty(com.fasterxml.jackson.core.JsonParser, com.fasterxml.jackson.databind.DeserializationContext) throws java.io.IOException;
    Code:
       0: aload_1
       1: getstatic     #22                 // Field com/fasterxml/jackson/core/JsonToken.START_ARRAY:Lcom/fasterxml/jackson/core/JsonToken;
       4: invokevirtual #24                 // Method com/fasterxml/jackson/core/JsonParser.hasToken:(Lcom/fasterxml/jackson/core/JsonToken;)Z
       7: ifeq          45
      10: aload_2
      11: getstatic     #25                 // Field com/fasterxml/jackson/databind/DeserializationFeature.ACCEPT_EMPTY_ARRAY_AS_NULL_OBJECT:Lcom/fasterxml/jackson/databind/DeserializationFeature;
      14: invokevirtual #11                 // Method com/fasterxml/jackson/databind/DeserializationContext.isEnabled:(Lcom/fasterxml/jackson/databind/DeserializationFeature;)Z
      17: ifeq          45
      20: aload_1
      21: invokevirtual #13                 // Method com/fasterxml/jackson/core/JsonParser.nextToken:()Lcom/fasterxml/jackson/core/JsonToken;
      24: astore_3
      25: aload_3
      26: getstatic     #14                 // Field com/fasterxml/jackson/core/JsonToken.END_ARRAY:Lcom/fasterxml/jackson/core/JsonToken;
      29: if_acmpne     34
      32: aconst_null
      33: areturn
      34: aload_2
      35: aload_0
      36: aload_2
      37: invokevirtual #21                 // Method getValueType:(Lcom/fasterxml/jackson/databind/DeserializationContext;)Lcom/fasterxml/jackson/databind/JavaType;
      40: aload_1
      41: invokevirtual #26                 // Method com/fasterxml/jackson/databind/DeserializationContext.handleUnexpectedToken:(Lcom/fasterxml/jackson/databind/JavaType;Lcom/fasterxml/jackson/core/JsonParser;)Ljava/lang/Object;
      44: areturn
      45: aload_2
      46: aload_0
      47: aload_2
      48: invokevirtual #21                 // Method getValueType:(Lcom/fasterxml/jackson/databind/DeserializationContext;)Lcom/fasterxml/jackson/databind/JavaType;
      51: aload_1
      52: invokevirtual #26                 // Method com/fasterxml/jackson/databind/DeserializationContext.handleUnexpectedToken:(Lcom/fasterxml/jackson/databind/JavaType;Lcom/fasterxml/jackson/core/JsonParser;)Ljava/lang/Object;
      55: areturn

  protected T _deserializeFromString(com.fasterxml.jackson.core.JsonParser, com.fasterxml.jackson.databind.DeserializationContext) throws java.io.IOException;
    Code:
       0: aload_0
       1: invokevirtual #27                 // Method getValueInstantiator:()Lcom/fasterxml/jackson/databind/deser/ValueInstantiator;
       4: astore_3
       5: aload_0
       6: invokevirtual #28                 // Method handledType:()Ljava/lang/Class;
       9: astore        4
      11: aload_1
      12: invokevirtual #29                 // Method com/fasterxml/jackson/core/JsonParser.getValueAsString:()Ljava/lang/String;
      15: astore        5
      17: aload_3
      18: ifnull        36
      21: aload_3
      22: invokevirtual #30                 // Method com/fasterxml/jackson/databind/deser/ValueInstantiator.canCreateFromString:()Z
      25: ifeq          36
      28: aload_3
      29: aload_2
      30: aload         5
      32: invokevirtual #31                 // Method com/fasterxml/jackson/databind/deser/ValueInstantiator.createFromString:(Lcom/fasterxml/jackson/databind/DeserializationContext;Ljava/lang/String;)Ljava/lang/Object;
      35: areturn
      36: aload         5
      38: invokevirtual #32                 // Method java/lang/String.isEmpty:()Z
      41: ifeq          72
      44: aload_2
      45: aload_0
      46: invokevirtual #33                 // Method logicalType:()Lcom/fasterxml/jackson/databind/type/LogicalType;
      49: aload         4
      51: getstatic     #34                 // Field com/fasterxml/jackson/databind/cfg/CoercionInputShape.EmptyString:Lcom/fasterxml/jackson/databind/cfg/CoercionInputShape;
      54: invokevirtual #35                 // Method com/fasterxml/jackson/databind/DeserializationContext.findCoercionAction:(Lcom/fasterxml/jackson/databind/type/LogicalType;Ljava/lang/Class;Lcom/fasterxml/jackson/databind/cfg/CoercionInputShape;)Lcom/fasterxml/jackson/databind/cfg/CoercionAction;
      57: astore        6
      59: aload_0
      60: aload_1
      61: aload_2
      62: aload         6
      64: aload         4
      66: ldc           #36                 // String empty String (\"\")
      68: invokevirtual #37                 // Method _deserializeFromEmptyString:(Lcom/fasterxml/jackson/core/JsonParser;Lcom/fasterxml/jackson/databind/DeserializationContext;Lcom/fasterxml/jackson/databind/cfg/CoercionAction;Ljava/lang/Class;Ljava/lang/String;)Ljava/lang/Object;
      71: areturn
      72: aload         5
      74: invokestatic  #38                 // Method _isBlank:(Ljava/lang/String;)Z
      77: ifeq          108
      80: aload_2
      81: aload_0
      82: invokevirtual #33                 // Method logicalType:()Lcom/fasterxml/jackson/databind/type/LogicalType;
      85: aload         4
      87: getstatic     #12                 // Field com/fasterxml/jackson/databind/cfg/CoercionAction.Fail:Lcom/fasterxml/jackson/databind/cfg/CoercionAction;
      90: invokevirtual #39                 // Method com/fasterxml/jackson/databind/DeserializationContext.findCoercionFromBlankString:(Lcom/fasterxml/jackson/databind/type/LogicalType;Ljava/lang/Class;Lcom/fasterxml/jackson/databind/cfg/CoercionAction;)Lcom/fasterxml/jackson/databind/cfg/CoercionAction;
      93: astore        6
      95: aload_0
      96: aload_1
      97: aload_2
      98: aload         6
     100: aload         4
     102: ldc           #40                 // String blank String (all whitespace)
     104: invokevirtual #37                 // Method _deserializeFromEmptyString:(Lcom/fasterxml/jackson/core/JsonParser;Lcom/fasterxml/jackson/databind/DeserializationContext;Lcom/fasterxml/jackson/databind/cfg/CoercionAction;Ljava/lang/Class;Ljava/lang/String;)Ljava/lang/Object;
     107: areturn
     108: aload_3
     109: ifnull        261
     112: aload         5
     114: invokevirtual #41                 // Method java/lang/String.trim:()Ljava/lang/String;
     117: astore        5
     119: aload_3
     120: invokevirtual #42                 // Method com/fasterxml/jackson/databind/deser/ValueInstantiator.canCreateFromInt:()Z
     123: ifeq          157
     126: aload_2
     127: getstatic     #43                 // Field com/fasterxml/jackson/databind/type/LogicalType.Integer:Lcom/fasterxml/jackson/databind/type/LogicalType;
     130: ldc           #44                 // class java/lang/Integer
     132: getstatic     #45                 // Field com/fasterxml/jackson/databind/cfg/CoercionInputShape.String:Lcom/fasterxml/jackson/databind/cfg/CoercionInputShape;
     135: invokevirtual #35                 // Method com/fasterxml/jackson/databind/DeserializationContext.findCoercionAction:(Lcom/fasterxml/jackson/databind/type/LogicalType;Ljava/lang/Class;Lcom/fasterxml/jackson/databind/cfg/CoercionInputShape;)Lcom/fasterxml/jackson/databind/cfg/CoercionAction;
     138: getstatic     #46                 // Field com/fasterxml/jackson/databind/cfg/CoercionAction.TryConvert:Lcom/fasterxml/jackson/databind/cfg/CoercionAction;
     141: if_acmpne     157
     144: aload_3
     145: aload_2
     146: aload_0
     147: aload_2
     148: aload         5
     150: invokevirtual #47                 // Method _parseIntPrimitive:(Lcom/fasterxml/jackson/databind/DeserializationContext;Ljava/lang/String;)I
     153: invokevirtual #48                 // Method com/fasterxml/jackson/databind/deser/ValueInstantiator.createFromInt:(Lcom/fasterxml/jackson/databind/DeserializationContext;I)Ljava/lang/Object;
     156: areturn
     157: aload_3
     158: invokevirtual #49                 // Method com/fasterxml/jackson/databind/deser/ValueInstantiator.canCreateFromLong:()Z
     161: ifeq          195
     164: aload_2
     165: getstatic     #43                 // Field com/fasterxml/jackson/databind/type/LogicalType.Integer:Lcom/fasterxml/jackson/databind/type/LogicalType;
     168: ldc           #50                 // class java/lang/Long
     170: getstatic     #45                 // Field com/fasterxml/jackson/databind/cfg/CoercionInputShape.String:Lcom/fasterxml/jackson/databind/cfg/CoercionInputShape;
     173: invokevirtual #35                 // Method com/fasterxml/jackson/databind/DeserializationContext.findCoercionAction:(Lcom/fasterxml/jackson/databind/type/LogicalType;Ljava/lang/Class;Lcom/fasterxml/jackson/databind/cfg/CoercionInputShape;)Lcom/fasterxml/jackson/databind/cfg/CoercionAction;
     176: getstatic     #46                 // Field com/fasterxml/jackson/databind/cfg/CoercionAction.TryConvert:Lcom/fasterxml/jackson/databind/cfg/CoercionAction;
     179: if_acmpne     195
     182: aload_3
     183: aload_2
     184: aload_0
     185: aload_2
     186: aload         5
     188: invokevirtual #51                 // Method _parseLongPrimitive:(Lcom/fasterxml/jackson/databind/DeserializationContext;Ljava/lang/String;)J
     191: invokevirtual #52                 // Method com/fasterxml/jackson/databind/deser/ValueInstantiator.createFromLong:(Lcom/fasterxml/jackson/databind/DeserializationContext;J)Ljava/lang/Object;
     194: areturn
     195: aload_3
     196: invokevirtual #53                 // Method com/fasterxml/jackson/databind/deser/ValueInstantiator.canCreateFromBoolean:()Z
     199: ifeq          261
     202: aload_2
     203: getstatic     #54                 // Field com/fasterxml/jackson/databind/type/LogicalType.Boolean:Lcom/fasterxml/jackson/databind/type/LogicalType;
     206: ldc           #55                 // class java/lang/Boolean
     208: getstatic     #45                 // Field com/fasterxml/jackson/databind/cfg/CoercionInputShape.String:Lcom/fasterxml/jackson/databind/cfg/CoercionInputShape;
     211: invokevirtual #35                 // Method com/fasterxml/jackson/databind/DeserializationContext.findCoercionAction:(Lcom/fasterxml/jackson/databind/type/LogicalType;Ljava/lang/Class;Lcom/fasterxml/jackson/databind/cfg/CoercionInputShape;)Lcom/fasterxml/jackson/databind/cfg/CoercionAction;
     214: getstatic     #46                 // Field com/fasterxml/jackson/databind/cfg/CoercionAction.TryConvert:Lcom/fasterxml/jackson/databind/cfg/CoercionAction;
     217: if_acmpne     261
     220: aload         5
     222: invokevirtual #41                 // Method java/lang/String.trim:()Ljava/lang/String;
     225: astore        6
     227: ldc           #56                 // String true
     229: aload         6
     231: invokevirtual #57                 // Method java/lang/String.equals:(Ljava/lang/Object;)Z
     234: ifeq          244
     237: aload_3
     238: aload_2
     239: iconst_1
     240: invokevirtual #58                 // Method com/fasterxml/jackson/databind/deser/ValueInstantiator.createFromBoolean:(Lcom/fasterxml/jackson/databind/DeserializationContext;Z)Ljava/lang/Object;
     243: areturn
     244: ldc           #59                 // String false
     246: aload         6
     248: invokevirtual #57                 // Method java/lang/String.equals:(Ljava/lang/Object;)Z
     251: ifeq          261
     254: aload_3
     255: aload_2
     256: iconst_0
     257: invokevirtual #58                 // Method com/fasterxml/jackson/databind/deser/ValueInstantiator.createFromBoolean:(Lcom/fasterxml/jackson/databind/DeserializationContext;Z)Ljava/lang/Object;
     260: areturn
     261: aload_2
     262: aload         4
     264: aload_3
     265: aload_2
     266: invokevirtual #60                 // Method com/fasterxml/jackson/databind/DeserializationContext.getParser:()Lcom/fasterxml/jackson/core/JsonParser;
     269: ldc           #61                 // String no String-argument constructor/factory method to deserialize from String value (\'%s\')
     271: iconst_1
     272: anewarray     #4                  // class java/lang/Object
     275: dup
     276: iconst_0
     277: aload         5
     279: aastore
     280: invokevirtual #62                 // Method com/fasterxml/jackson/databind/DeserializationContext.handleMissingInstantiator:(Ljava/lang/Class;Lcom/fasterxml/jackson/databind/deser/ValueInstantiator;Lcom/fasterxml/jackson/core/JsonParser;Ljava/lang/String;[Ljava/lang/Object;)Ljava/lang/Object;
     283: areturn

  protected java.lang.Object _deserializeFromEmptyString(com.fasterxml.jackson.core.JsonParser, com.fasterxml.jackson.databind.DeserializationContext, com.fasterxml.jackson.databind.cfg.CoercionAction, java.lang.Class<?>, java.lang.String) throws java.io.IOException;
    Code:
       0: getstatic     #15                 // Field com/fasterxml/jackson/databind/deser/std/StdDeserializer$1.$SwitchMap$com$fasterxml$jackson$databind$cfg$CoercionAction:[I
       3: aload_3
       4: invokevirtual #16                 // Method com/fasterxml/jackson/databind/cfg/CoercionAction.ordinal:()I
       7: iaload
       8: tableswitch   { // 1 to 4
                     1: 40
                     2: 59
                     3: 59
                     4: 46
               default: 59
          }
      40: aload_0
      41: aload_2
      42: invokevirtual #17                 // Method getEmptyValue:(Lcom/fasterxml/jackson/databind/DeserializationContext;)Ljava/lang/Object;
      45: areturn
      46: aload_0
      47: aload_2
      48: aload_3
      49: aload         4
      51: ldc           #63                 // String
      53: ldc           #36                 // String empty String (\"\")
      55: invokevirtual #64                 // Method _checkCoercionFail:(Lcom/fasterxml/jackson/databind/DeserializationContext;Lcom/fasterxml/jackson/databind/cfg/CoercionAction;Ljava/lang/Class;Ljava/lang/Object;Ljava/lang/String;)Lcom/fasterxml/jackson/databind/cfg/CoercionAction;
      58: pop
      59: aconst_null
      60: areturn

  protected T _deserializeWrappedValue(com.fasterxml.jackson.core.JsonParser, com.fasterxml.jackson.databind.DeserializationContext) throws java.io.IOException;
    Code:
       0: aload_1
       1: getstatic     #22                 // Field com/fasterxml/jackson/core/JsonToken.START_ARRAY:Lcom/fasterxml/jackson/core/JsonToken;
       4: invokevirtual #24                 // Method com/fasterxml/jackson/core/JsonParser.hasToken:(Lcom/fasterxml/jackson/core/JsonToken;)Z
       7: ifeq          19
      10: aload_0
      11: aload_1
      12: aload_2
      13: invokevirtual #65                 // Method handleNestedArrayForSingle:(Lcom/fasterxml/jackson/core/JsonParser;Lcom/fasterxml/jackson/databind/DeserializationContext;)Ljava/lang/Object;
      16: astore_3
      17: aload_3
      18: areturn
      19: aload_0
      20: aload_1
      21: aload_2
      22: invokevirtual #66                 // Method deserialize:(Lcom/fasterxml/jackson/core/JsonParser;Lcom/fasterxml/jackson/databind/DeserializationContext;)Ljava/lang/Object;
      25: areturn

  protected final boolean _parseBooleanPrimitive(com.fasterxml.jackson.databind.DeserializationContext, com.fasterxml.jackson.core.JsonParser, java.lang.Class<?>) throws java.io.IOException;
    Code:
       0: aload_0
       1: aload_2
       2: aload_1
       3: invokevirtual #67                 // Method _parseBooleanPrimitive:(Lcom/fasterxml/jackson/core/JsonParser;Lcom/fasterxml/jackson/databind/DeserializationContext;)Z
       6: ireturn

  protected final boolean _parseBooleanPrimitive(com.fasterxml.jackson.core.JsonParser, com.fasterxml.jackson.databind.DeserializationContext) throws java.io.IOException;
    Code:
       0: aload_1
       1: invokevirtual #68                 // Method com/fasterxml/jackson/core/JsonParser.currentTokenId:()I
       4: tableswitch   { // 1 to 11
                     1: 99
                     2: 162
                     3: 112
                     4: 162
                     5: 162
                     6: 64
                     7: 72
                     8: 162
                     9: 88
                    10: 90
                    11: 92
               default: 162
          }
      64: aload_1
      65: invokevirtual #69                 // Method com/fasterxml/jackson/core/JsonParser.getText:()Ljava/lang/String;
      68: astore_3
      69: goto          177
      72: getstatic     #70                 // Field java/lang/Boolean.TRUE:Ljava/lang/Boolean;
      75: aload_0
      76: aload_1
      77: aload_2
      78: getstatic     #71                 // Field java/lang/Boolean.TYPE:Ljava/lang/Class;
      81: invokevirtual #72                 // Method _coerceBooleanFromInt:(Lcom/fasterxml/jackson/core/JsonParser;Lcom/fasterxml/jackson/databind/DeserializationContext;Ljava/lang/Class;)Ljava/lang/Boolean;
      84: invokevirtual #73                 // Method java/lang/Boolean.equals:(Ljava/lang/Object;)Z
      87: ireturn
      88: iconst_1
      89: ireturn
      90: iconst_0
      91: ireturn
      92: aload_0
      93: aload_2
      94: invokevirtual #74                 // Method _verifyNullForPrimitive:(Lcom/fasterxml/jackson/databind/DeserializationContext;)V
      97: iconst_0
      98: ireturn
      99: aload_2
     100: aload_1
     101: aload_0
     102: getstatic     #71                 // Field java/lang/Boolean.TYPE:Ljava/lang/Class;
     105: invokevirtual #75                 // Method com/fasterxml/jackson/databind/DeserializationContext.extractScalarFromObject:(Lcom/fasterxml/jackson/core/JsonParser;Lcom/fasterxml/jackson/databind/JsonDeserializer;Ljava/lang/Class;)Ljava/lang/String;
     108: astore_3
     109: goto          177
     112: aload_2
     113: getstatic     #10                 // Field com/fasterxml/jackson/databind/DeserializationFeature.UNWRAP_SINGLE_VALUE_ARRAYS:Lcom/fasterxml/jackson/databind/DeserializationFeature;
     116: invokevirtual #11                 // Method com/fasterxml/jackson/databind/DeserializationContext.isEnabled:(Lcom/fasterxml/jackson/databind/DeserializationFeature;)Z
     119: ifeq          162
     122: aload_1
     123: invokevirtual #13                 // Method com/fasterxml/jackson/core/JsonParser.nextToken:()Lcom/fasterxml/jackson/core/JsonToken;
     126: getstatic     #22                 // Field com/fasterxml/jackson/core/JsonToken.START_ARRAY:Lcom/fasterxml/jackson/core/JsonToken;
     129: if_acmpne     145
     132: aload_0
     133: aload_1
     134: aload_2
     135: invokevirtual #65                 // Method handleNestedArrayForSingle:(Lcom/fasterxml/jackson/core/JsonParser;Lcom/fasterxml/jackson/databind/DeserializationContext;)Ljava/lang/Object;
     138: checkcast     #55                 // class java/lang/Boolean
     141: invokevirtual #76                 // Method java/lang/Boolean.booleanValue:()Z
     144: ireturn
     145: aload_0
     146: aload_1
     147: aload_2
     148: invokevirtual #67                 // Method _parseBooleanPrimitive:(Lcom/fasterxml/jackson/core/JsonParser;Lcom/fasterxml/jackson/databind/DeserializationContext;)Z
     151: istore        4
     153: aload_0
     154: aload_1
     155: aload_2
     156: invokevirtual #77                 // Method _verifyEndArrayForSingle:(Lcom/fasterxml/jackson/core/JsonParser;Lcom/fasterxml/jackson/databind/DeserializationContext;)V
     159: iload         4
     161: ireturn
     162: aload_2
     163: getstatic     #71                 // Field java/lang/Boolean.TYPE:Ljava/lang/Class;
     166: aload_1
     167: invokevirtual #78                 // Method com/fasterxml/jackson/databind/DeserializationContext.handleUnexpectedToken:(Ljava/lang/Class;Lcom/fasterxml/jackson/core/JsonParser;)Ljava/lang/Object;
     170: checkcast     #55                 // class java/lang/Boolean
     173: invokevirtual #76                 // Method java/lang/Boolean.booleanValue:()Z
     176: ireturn
     177: aload_0
     178: aload_2
     179: aload_3
     180: getstatic     #54                 // Field com/fasterxml/jackson/databind/type/LogicalType.Boolean:Lcom/fasterxml/jackson/databind/type/LogicalType;
     183: getstatic     #71                 // Field java/lang/Boolean.TYPE:Ljava/lang/Class;
     186: invokevirtual #79                 // Method _checkFromStringCoercion:(Lcom/fasterxml/jackson/databind/DeserializationContext;Ljava/lang/String;Lcom/fasterxml/jackson/databind/type/LogicalType;Ljava/lang/Class;)Lcom/fasterxml/jackson/databind/cfg/CoercionAction;
     189: astore        4
     191: aload         4
     193: getstatic     #80                 // Field com/fasterxml/jackson/databind/cfg/CoercionAction.AsNull:Lcom/fasterxml/jackson/databind/cfg/CoercionAction;
     196: if_acmpne     206
     199: aload_0
     200: aload_2
     201: invokevirtual #74                 // Method _verifyNullForPrimitive:(Lcom/fasterxml/jackson/databind/DeserializationContext;)V
     204: iconst_0
     205: ireturn
     206: aload         4
     208: getstatic     #81                 // Field com/fasterxml/jackson/databind/cfg/CoercionAction.AsEmpty:Lcom/fasterxml/jackson/databind/cfg/CoercionAction;
     211: if_acmpne     216
     214: iconst_0
     215: ireturn
     216: aload_3
     217: invokevirtual #41                 // Method java/lang/String.trim:()Ljava/lang/String;
     220: astore_3
     221: aload_3
     222: invokevirtual #82                 // Method java/lang/String.length:()I
     225: istore        5
     227: iload         5
     229: iconst_4
     230: if_icmpne     243
     233: aload_0
     234: aload_3
     235: invokevirtual #83                 // Method _isTrue:(Ljava/lang/String;)Z
     238: ifeq          259
     241: iconst_1
     242: ireturn
     243: iload         5
     245: iconst_5
     246: if_icmpne     259
     249: aload_0
     250: aload_3
     251: invokevirtual #84                 // Method _isFalse:(Ljava/lang/String;)Z
     254: ifeq          259
     257: iconst_0
     258: ireturn
     259: aload_0
     260: aload_3
     261: invokevirtual #85                 // Method _hasTextualNull:(Ljava/lang/String;)Z
     264: ifeq          275
     267: aload_0
     268: aload_2
     269: aload_3
     270: invokevirtual #86                 // Method _verifyNullForPrimitiveCoercion:(Lcom/fasterxml/jackson/databind/DeserializationContext;Ljava/lang/String;)V
     273: iconst_0
     274: ireturn
     275: aload_2
     276: getstatic     #71                 // Field java/lang/Boolean.TYPE:Ljava/lang/Class;
     279: aload_3
     280: ldc           #87                 // String only \"true\"/\"True\"/\"TRUE\" or \"false\"/\"False\"/\"FALSE\" recognized
     282: iconst_0
     283: anewarray     #4                  // class java/lang/Object
     286: invokevirtual #88                 // Method com/fasterxml/jackson/databind/DeserializationContext.handleWeirdStringValue:(Ljava/lang/Class;Ljava/lang/String;Ljava/lang/String;[Ljava/lang/Object;)Ljava/lang/Object;
     289: checkcast     #55                 // class java/lang/Boolean
     292: astore        6
     294: getstatic     #70                 // Field java/lang/Boolean.TRUE:Ljava/lang/Boolean;
     297: aload         6
     299: invokevirtual #73                 // Method java/lang/Boolean.equals:(Ljava/lang/Object;)Z
     302: ireturn

  protected boolean _isTrue(java.lang.String);
    Code:
       0: aload_1
       1: iconst_0
       2: invokevirtual #89                 // Method java/lang/String.charAt:(I)C
       5: istore_2
       6: iload_2
       7: bipush        116
       9: if_icmpne     19
      12: ldc           #56                 // String true
      14: aload_1
      15: invokevirtual #57                 // Method java/lang/String.equals:(Ljava/lang/Object;)Z
      18: ireturn
      19: iload_2
      20: bipush        84
      22: if_icmpne     49
      25: ldc           #90                 // String TRUE
      27: aload_1
      28: invokevirtual #57                 // Method java/lang/String.equals:(Ljava/lang/Object;)Z
      31: ifne          43
      34: ldc           #91                 // String True
      36: aload_1
      37: invokevirtual #57                 // Method java/lang/String.equals:(Ljava/lang/Object;)Z
      40: ifeq          47
      43: iconst_1
      44: goto          48
      47: iconst_0
      48: ireturn
      49: iconst_0
      50: ireturn

  protected boolean _isFalse(java.lang.String);
    Code:
       0: aload_1
       1: iconst_0
       2: invokevirtual #89                 // Method java/lang/String.charAt:(I)C
       5: istore_2
       6: iload_2
       7: bipush        102
       9: if_icmpne     19
      12: ldc           #59                 // String false
      14: aload_1
      15: invokevirtual #57                 // Method java/lang/String.equals:(Ljava/lang/Object;)Z
      18: ireturn
      19: iload_2
      20: bipush        70
      22: if_icmpne     49
      25: ldc           #92                 // String FALSE
      27: aload_1
      28: invokevirtual #57                 // Method java/lang/String.equals:(Ljava/lang/Object;)Z
      31: ifne          43
      34: ldc           #93                 // String False
      36: aload_1
      37: invokevirtual #57                 // Method java/lang/String.equals:(Ljava/lang/Object;)Z
      40: ifeq          47
      43: iconst_1
      44: goto          48
      47: iconst_0
      48: ireturn
      49: iconst_0
      50: ireturn

  protected final java.lang.Boolean _parseBoolean(com.fasterxml.jackson.core.JsonParser, com.fasterxml.jackson.databind.DeserializationContext, java.lang.Class<?>) throws java.io.IOException;
    Code:
       0: aload_1
       1: invokevirtual #68                 // Method com/fasterxml/jackson/core/JsonParser.currentTokenId:()I
       4: tableswitch   { // 1 to 11
                     1: 93
                     2: 115
                     3: 105
                     4: 115
                     5: 115
                     6: 64
                     7: 73
                     8: 115
                     9: 81
                    10: 86
                    11: 91
               default: 115
          }
      64: aload_1
      65: invokevirtual #69                 // Method com/fasterxml/jackson/core/JsonParser.getText:()Ljava/lang/String;
      68: astore        4
      70: goto          125
      73: aload_0
      74: aload_1
      75: aload_2
      76: aload_3
      77: invokevirtual #72                 // Method _coerceBooleanFromInt:(Lcom/fasterxml/jackson/core/JsonParser;Lcom/fasterxml/jackson/databind/DeserializationContext;Ljava/lang/Class;)Ljava/lang/Boolean;
      80: areturn
      81: iconst_1
      82: invokestatic  #94                 // Method java/lang/Boolean.valueOf:(Z)Ljava/lang/Boolean;
      85: areturn
      86: iconst_0
      87: invokestatic  #94                 // Method java/lang/Boolean.valueOf:(Z)Ljava/lang/Boolean;
      90: areturn
      91: aconst_null
      92: areturn
      93: aload_2
      94: aload_1
      95: aload_0
      96: aload_3
      97: invokevirtual #75                 // Method com/fasterxml/jackson/databind/DeserializationContext.extractScalarFromObject:(Lcom/fasterxml/jackson/core/JsonParser;Lcom/fasterxml/jackson/databind/JsonDeserializer;Ljava/lang/Class;)Ljava/lang/String;
     100: astore        4
     102: goto          125
     105: aload_0
     106: aload_1
     107: aload_2
     108: invokevirtual #95                 // Method _deserializeFromArray:(Lcom/fasterxml/jackson/core/JsonParser;Lcom/fasterxml/jackson/databind/DeserializationContext;)Ljava/lang/Object;
     111: checkcast     #55                 // class java/lang/Boolean
     114: areturn
     115: aload_2
     116: aload_3
     117: aload_1
     118: invokevirtual #78                 // Method com/fasterxml/jackson/databind/DeserializationContext.handleUnexpectedToken:(Ljava/lang/Class;Lcom/fasterxml/jackson/core/JsonParser;)Ljava/lang/Object;
     121: checkcast     #55                 // class java/lang/Boolean
     124: areturn
     125: aload_0
     126: aload_2
     127: aload         4
     129: getstatic     #54                 // Field com/fasterxml/jackson/databind/type/LogicalType.Boolean:Lcom/fasterxml/jackson/databind/type/LogicalType;
     132: aload_3
     133: invokevirtual #79                 // Method _checkFromStringCoercion:(Lcom/fasterxml/jackson/databind/DeserializationContext;Ljava/lang/String;Lcom/fasterxml/jackson/databind/type/LogicalType;Ljava/lang/Class;)Lcom/fasterxml/jackson/databind/cfg/CoercionAction;
     136: astore        5
     138: aload         5
     140: getstatic     #80                 // Field com/fasterxml/jackson/databind/cfg/CoercionAction.AsNull:Lcom/fasterxml/jackson/databind/cfg/CoercionAction;
     143: if_acmpne     148
     146: aconst_null
     147: areturn
     148: aload         5
     150: getstatic     #81                 // Field com/fasterxml/jackson/databind/cfg/CoercionAction.AsEmpty:Lcom/fasterxml/jackson/databind/cfg/CoercionAction;
     153: if_acmpne     161
     156: iconst_0
     157: invokestatic  #94                 // Method java/lang/Boolean.valueOf:(Z)Ljava/lang/Boolean;
     160: areturn
     161: aload         4
     163: invokevirtual #41                 // Method java/lang/String.trim:()Ljava/lang/String;
     166: astore        4
     168: aload         4
     170: invokevirtual #82                 // Method java/lang/String.length:()I
     173: istore        6
     175: iload         6
     177: iconst_4
     178: if_icmpne     195
     181: aload_0
     182: aload         4
     184: invokevirtual #83                 // Method _isTrue:(Ljava/lang/String;)Z
     187: ifeq          215
     190: iconst_1
     191: invokestatic  #94                 // Method java/lang/Boolean.valueOf:(Z)Ljava/lang/Boolean;
     194: areturn
     195: iload         6
     197: iconst_5
     198: if_icmpne     215
     201: aload_0
     202: aload         4
     204: invokevirtual #84                 // Method _isFalse:(Ljava/lang/String;)Z
     207: ifeq          215
     210: iconst_0
     211: invokestatic  #94                 // Method java/lang/Boolean.valueOf:(Z)Ljava/lang/Boolean;
     214: areturn
     215: aload_0
     216: aload_2
     217: aload         4
     219: invokevirtual #96                 // Method _checkTextualNull:(Lcom/fasterxml/jackson/databind/DeserializationContext;Ljava/lang/String;)Z
     222: ifeq          227
     225: aconst_null
     226: areturn
     227: aload_2
     228: aload_3
     229: aload         4
     231: ldc           #97                 // String only \"true\" or \"false\" recognized
     233: iconst_0
     234: anewarray     #4                  // class java/lang/Object
     237: invokevirtual #88                 // Method com/fasterxml/jackson/databind/DeserializationContext.handleWeirdStringValue:(Ljava/lang/Class;Ljava/lang/String;Ljava/lang/String;[Ljava/lang/Object;)Ljava/lang/Object;
     240: checkcast     #55                 // class java/lang/Boolean
     243: areturn

  protected final byte _parseBytePrimitive(com.fasterxml.jackson.core.JsonParser, com.fasterxml.jackson.databind.DeserializationContext) throws java.io.IOException;
    Code:
       0: aload_1
       1: invokevirtual #68                 // Method com/fasterxml/jackson/core/JsonParser.currentTokenId:()I
       4: tableswitch   { // 1 to 11
                     1: 120
                     2: 183
                     3: 133
                     4: 183
                     5: 183
                     6: 64
                     7: 108
                     8: 72
                     9: 183
                    10: 183
                    11: 113
               default: 183
          }
      64: aload_1
      65: invokevirtual #69                 // Method com/fasterxml/jackson/core/JsonParser.getText:()Ljava/lang/String;
      68: astore_3
      69: goto          202
      72: aload_0
      73: aload_1
      74: aload_2
      75: getstatic     #98                 // Field java/lang/Byte.TYPE:Ljava/lang/Class;
      78: invokevirtual #99                 // Method _checkFloatToIntCoercion:(Lcom/fasterxml/jackson/core/JsonParser;Lcom/fasterxml/jackson/databind/DeserializationContext;Ljava/lang/Class;)Lcom/fasterxml/jackson/databind/cfg/CoercionAction;
      81: astore        4
      83: aload         4
      85: getstatic     #80                 // Field com/fasterxml/jackson/databind/cfg/CoercionAction.AsNull:Lcom/fasterxml/jackson/databind/cfg/CoercionAction;
      88: if_acmpne     93
      91: iconst_0
      92: ireturn
      93: aload         4
      95: getstatic     #81                 // Field com/fasterxml/jackson/databind/cfg/CoercionAction.AsEmpty:Lcom/fasterxml/jackson/databind/cfg/CoercionAction;
      98: if_acmpne     103
     101: iconst_0
     102: ireturn
     103: aload_1
     104: invokevirtual #100                // Method com/fasterxml/jackson/core/JsonParser.getByteValue:()B
     107: ireturn
     108: aload_1
     109: invokevirtual #100                // Method com/fasterxml/jackson/core/JsonParser.getByteValue:()B
     112: ireturn
     113: aload_0
     114: aload_2
     115: invokevirtual #74                 // Method _verifyNullForPrimitive:(Lcom/fasterxml/jackson/databind/DeserializationContext;)V
     118: iconst_0
     119: ireturn
     120: aload_2
     121: aload_1
     122: aload_0
     123: getstatic     #98                 // Field java/lang/Byte.TYPE:Ljava/lang/Class;
     126: invokevirtual #75                 // Method com/fasterxml/jackson/databind/DeserializationContext.extractScalarFromObject:(Lcom/fasterxml/jackson/core/JsonParser;Lcom/fasterxml/jackson/databind/JsonDeserializer;Ljava/lang/Class;)Ljava/lang/String;
     129: astore_3
     130: goto          202
     133: aload_2
     134: getstatic     #10                 // Field com/fasterxml/jackson/databind/DeserializationFeature.UNWRAP_SINGLE_VALUE_ARRAYS:Lcom/fasterxml/jackson/databind/DeserializationFeature;
     137: invokevirtual #11                 // Method com/fasterxml/jackson/databind/DeserializationContext.isEnabled:(Lcom/fasterxml/jackson/databind/DeserializationFeature;)Z
     140: ifeq          183
     143: aload_1
     144: invokevirtual #13                 // Method com/fasterxml/jackson/core/JsonParser.nextToken:()Lcom/fasterxml/jackson/core/JsonToken;
     147: getstatic     #22                 // Field com/fasterxml/jackson/core/JsonToken.START_ARRAY:Lcom/fasterxml/jackson/core/JsonToken;
     150: if_acmpne     166
     153: aload_0
     154: aload_1
     155: aload_2
     156: invokevirtual #65                 // Method handleNestedArrayForSingle:(Lcom/fasterxml/jackson/core/JsonParser;Lcom/fasterxml/jackson/databind/DeserializationContext;)Ljava/lang/Object;
     159: checkcast     #101                // class java/lang/Byte
     162: invokevirtual #102                // Method java/lang/Byte.byteValue:()B
     165: ireturn
     166: aload_0
     167: aload_1
     168: aload_2
     169: invokevirtual #103                // Method _parseBytePrimitive:(Lcom/fasterxml/jackson/core/JsonParser;Lcom/fasterxml/jackson/databind/DeserializationContext;)B
     172: istore        5
     174: aload_0
     175: aload_1
     176: aload_2
     177: invokevirtual #77                 // Method _verifyEndArrayForSingle:(Lcom/fasterxml/jackson/core/JsonParser;Lcom/fasterxml/jackson/databind/DeserializationContext;)V
     180: iload         5
     182: ireturn
     183: aload_2
     184: aload_2
     185: getstatic     #98                 // Field java/lang/Byte.TYPE:Ljava/lang/Class;
     188: invokevirtual #6                  // Method com/fasterxml/jackson/databind/DeserializationContext.constructType:(Ljava/lang/Class;)Lcom/fasterxml/jackson/databind/JavaType;
     191: aload_1
     192: invokevirtual #26                 // Method com/fasterxml/jackson/databind/DeserializationContext.handleUnexpectedToken:(Lcom/fasterxml/jackson/databind/JavaType;Lcom/fasterxml/jackson/core/JsonParser;)Ljava/lang/Object;
     195: checkcast     #101                // class java/lang/Byte
     198: invokevirtual #102                // Method java/lang/Byte.byteValue:()B
     201: ireturn
     202: aload_0
     203: aload_2
     204: aload_3
     205: getstatic     #43                 // Field com/fasterxml/jackson/databind/type/LogicalType.Integer:Lcom/fasterxml/jackson/databind/type/LogicalType;
     208: getstatic     #98                 // Field java/lang/Byte.TYPE:Ljava/lang/Class;
     211: invokevirtual #79                 // Method _checkFromStringCoercion:(Lcom/fasterxml/jackson/databind/DeserializationContext;Ljava/lang/String;Lcom/fasterxml/jackson/databind/type/LogicalType;Ljava/lang/Class;)Lcom/fasterxml/jackson/databind/cfg/CoercionAction;
     214: astore        4
     216: aload         4
     218: getstatic     #80                 // Field com/fasterxml/jackson/databind/cfg/CoercionAction.AsNull:Lcom/fasterxml/jackson/databind/cfg/CoercionAction;
     221: if_acmpne     231
     224: aload_0
     225: aload_2
     226: invokevirtual #74                 // Method _verifyNullForPrimitive:(Lcom/fasterxml/jackson/databind/DeserializationContext;)V
     229: iconst_0
     230: ireturn
     231: aload         4
     233: getstatic     #81                 // Field com/fasterxml/jackson/databind/cfg/CoercionAction.AsEmpty:Lcom/fasterxml/jackson/databind/cfg/CoercionAction;
     236: if_acmpne     241
     239: iconst_0
     240: ireturn
     241: aload_3
     242: invokevirtual #41                 // Method java/lang/String.trim:()Ljava/lang/String;
     245: astore_3
     246: aload_0
     247: aload_3
     248: invokevirtual #85                 // Method _hasTextualNull:(Ljava/lang/String;)Z
     251: ifeq          262
     254: aload_0
     255: aload_2
     256: aload_3
     257: invokevirtual #86                 // Method _verifyNullForPrimitiveCoercion:(Lcom/fasterxml/jackson/databind/DeserializationContext;Ljava/lang/String;)V
     260: iconst_0
     261: ireturn
     262: aload_3
     263: invokestatic  #104                // Method com/fasterxml/jackson/core/io/NumberInput.parseInt:(Ljava/lang/String;)I
     266: istore        5
     268: goto          295
     271: astore        6
     273: aload_2
     274: aload_0
     275: getfield      #2                  // Field _valueClass:Ljava/lang/Class;
     278: aload_3
     279: ldc           #106                // String not a valid `byte` value
     281: iconst_0
     282: anewarray     #4                  // class java/lang/Object
     285: invokevirtual #88                 // Method com/fasterxml/jackson/databind/DeserializationContext.handleWeirdStringValue:(Ljava/lang/Class;Ljava/lang/String;Ljava/lang/String;[Ljava/lang/Object;)Ljava/lang/Object;
     288: checkcast     #101                // class java/lang/Byte
     291: invokevirtual #102                // Method java/lang/Byte.byteValue:()B
     294: ireturn
     295: aload_0
     296: iload         5
     298: invokevirtual #107                // Method _byteOverflow:(I)Z
     301: ifeq          326
     304: aload_2
     305: aload_0
     306: getfield      #2                  // Field _valueClass:Ljava/lang/Class;
     309: aload_3
     310: ldc           #108                // String overflow, value cannot be represented as 8-bit value
     312: iconst_0
     313: anewarray     #4                  // class java/lang/Object
     316: invokevirtual #88                 // Method com/fasterxml/jackson/databind/DeserializationContext.handleWeirdStringValue:(Ljava/lang/Class;Ljava/lang/String;Ljava/lang/String;[Ljava/lang/Object;)Ljava/lang/Object;
     319: checkcast     #101                // class java/lang/Byte
     322: invokevirtual #102                // Method java/lang/Byte.byteValue:()B
     325: ireturn
     326: iload         5
     328: i2b
     329: ireturn
    Exception table:
       from    to  target type
         262   268   271   Class java/lang/IllegalArgumentException

  protected final short _parseShortPrimitive(com.fasterxml.jackson.core.JsonParser, com.fasterxml.jackson.databind.DeserializationContext) throws java.io.IOException;
    Code:
       0: aload_1
       1: invokevirtual #68                 // Method com/fasterxml/jackson/core/JsonParser.currentTokenId:()I
       4: tableswitch   { // 1 to 11
                     1: 120
                     2: 183
                     3: 133
                     4: 183
                     5: 183
                     6: 64
                     7: 108
                     8: 72
                     9: 183
                    10: 183
                    11: 113
               default: 183
          }
      64: aload_1
      65: invokevirtual #69                 // Method com/fasterxml/jackson/core/JsonParser.getText:()Ljava/lang/String;
      68: astore_3
      69: goto          202
      72: aload_0
      73: aload_1
      74: aload_2
      75: getstatic     #109                // Field java/lang/Short.TYPE:Ljava/lang/Class;
      78: invokevirtual #99                 // Method _checkFloatToIntCoercion:(Lcom/fasterxml/jackson/core/JsonParser;Lcom/fasterxml/jackson/databind/DeserializationContext;Ljava/lang/Class;)Lcom/fasterxml/jackson/databind/cfg/CoercionAction;
      81: astore        4
      83: aload         4
      85: getstatic     #80                 // Field com/fasterxml/jackson/databind/cfg/CoercionAction.AsNull:Lcom/fasterxml/jackson/databind/cfg/CoercionAction;
      88: if_acmpne     93
      91: iconst_0
      92: ireturn
      93: aload         4
      95: getstatic     #81                 // Field com/fasterxml/jackson/databind/cfg/CoercionAction.AsEmpty:Lcom/fasterxml/jackson/databind/cfg/CoercionAction;
      98: if_acmpne     103
     101: iconst_0
     102: ireturn
     103: aload_1
     104: invokevirtual #110                // Method com/fasterxml/jackson/core/JsonParser.getShortValue:()S
     107: ireturn
     108: aload_1
     109: invokevirtual #110                // Method com/fasterxml/jackson/core/JsonParser.getShortValue:()S
     112: ireturn
     113: aload_0
     114: aload_2
     115: invokevirtual #74                 // Method _verifyNullForPrimitive:(Lcom/fasterxml/jackson/databind/DeserializationContext;)V
     118: iconst_0
     119: ireturn
     120: aload_2
     121: aload_1
     122: aload_0
     123: getstatic     #109                // Field java/lang/Short.TYPE:Ljava/lang/Class;
     126: invokevirtual #75                 // Method com/fasterxml/jackson/databind/DeserializationContext.extractScalarFromObject:(Lcom/fasterxml/jackson/core/JsonParser;Lcom/fasterxml/jackson/databind/JsonDeserializer;Ljava/lang/Class;)Ljava/lang/String;
     129: astore_3
     130: goto          202
     133: aload_2
     134: getstatic     #10                 // Field com/fasterxml/jackson/databind/DeserializationFeature.UNWRAP_SINGLE_VALUE_ARRAYS:Lcom/fasterxml/jackson/databind/DeserializationFeature;
     137: invokevirtual #11                 // Method com/fasterxml/jackson/databind/DeserializationContext.isEnabled:(Lcom/fasterxml/jackson/databind/DeserializationFeature;)Z
     140: ifeq          183
     143: aload_1
     144: invokevirtual #13                 // Method com/fasterxml/jackson/core/JsonParser.nextToken:()Lcom/fasterxml/jackson/core/JsonToken;
     147: getstatic     #22                 // Field com/fasterxml/jackson/core/JsonToken.START_ARRAY:Lcom/fasterxml/jackson/core/JsonToken;
     150: if_acmpne     166
     153: aload_0
     154: aload_1
     155: aload_2
     156: invokevirtual #65                 // Method handleNestedArrayForSingle:(Lcom/fasterxml/jackson/core/JsonParser;Lcom/fasterxml/jackson/databind/DeserializationContext;)Ljava/lang/Object;
     159: checkcast     #111                // class java/lang/Short
     162: invokevirtual #112                // Method java/lang/Short.shortValue:()S
     165: ireturn
     166: aload_0
     167: aload_1
     168: aload_2
     169: invokevirtual #113                // Method _parseShortPrimitive:(Lcom/fasterxml/jackson/core/JsonParser;Lcom/fasterxml/jackson/databind/DeserializationContext;)S
     172: istore        5
     174: aload_0
     175: aload_1
     176: aload_2
     177: invokevirtual #77                 // Method _verifyEndArrayForSingle:(Lcom/fasterxml/jackson/core/JsonParser;Lcom/fasterxml/jackson/databind/DeserializationContext;)V
     180: iload         5
     182: ireturn
     183: aload_2
     184: aload_2
     185: getstatic     #109                // Field java/lang/Short.TYPE:Ljava/lang/Class;
     188: invokevirtual #6                  // Method com/fasterxml/jackson/databind/DeserializationContext.constructType:(Ljava/lang/Class;)Lcom/fasterxml/jackson/databind/JavaType;
     191: aload_1
     192: invokevirtual #26                 // Method com/fasterxml/jackson/databind/DeserializationContext.handleUnexpectedToken:(Lcom/fasterxml/jackson/databind/JavaType;Lcom/fasterxml/jackson/core/JsonParser;)Ljava/lang/Object;
     195: checkcast     #111                // class java/lang/Short
     198: invokevirtual #112                // Method java/lang/Short.shortValue:()S
     201: ireturn
     202: aload_0
     203: aload_2
     204: aload_3
     205: getstatic     #43                 // Field com/fasterxml/jackson/databind/type/LogicalType.Integer:Lcom/fasterxml/jackson/databind/type/LogicalType;
     208: getstatic     #109                // Field java/lang/Short.TYPE:Ljava/lang/Class;
     211: invokevirtual #79                 // Method _checkFromStringCoercion:(Lcom/fasterxml/jackson/databind/DeserializationContext;Ljava/lang/String;Lcom/fasterxml/jackson/databind/type/LogicalType;Ljava/lang/Class;)Lcom/fasterxml/jackson/databind/cfg/CoercionAction;
     214: astore        4
     216: aload         4
     218: getstatic     #80                 // Field com/fasterxml/jackson/databind/cfg/CoercionAction.AsNull:Lcom/fasterxml/jackson/databind/cfg/CoercionAction;
     221: if_acmpne     231
     224: aload_0
     225: aload_2
     226: invokevirtual #74                 // Method _verifyNullForPrimitive:(Lcom/fasterxml/jackson/databind/DeserializationContext;)V
     229: iconst_0
     230: ireturn
     231: aload         4
     233: getstatic     #81                 // Field com/fasterxml/jackson/databind/cfg/CoercionAction.AsEmpty:Lcom/fasterxml/jackson/databind/cfg/CoercionAction;
     236: if_acmpne     241
     239: iconst_0
     240: ireturn
     241: aload_3
     242: invokevirtual #41                 // Method java/lang/String.trim:()Ljava/lang/String;
     245: astore_3
     246: aload_0
     247: aload_3
     248: invokevirtual #85                 // Method _hasTextualNull:(Ljava/lang/String;)Z
     251: ifeq          262
     254: aload_0
     255: aload_2
     256: aload_3
     257: invokevirtual #86                 // Method _verifyNullForPrimitiveCoercion:(Lcom/fasterxml/jackson/databind/DeserializationContext;Ljava/lang/String;)V
     260: iconst_0
     261: ireturn
     262: aload_3
     263: invokestatic  #104                // Method com/fasterxml/jackson/core/io/NumberInput.parseInt:(Ljava/lang/String;)I
     266: istore        5
     268: goto          294
     271: astore        6
     273: aload_2
     274: getstatic     #109                // Field java/lang/Short.TYPE:Ljava/lang/Class;
     277: aload_3
     278: ldc           #114                // String not a valid `short` value
     280: iconst_0
     281: anewarray     #4                  // class java/lang/Object
     284: invokevirtual #88                 // Method com/fasterxml/jackson/databind/DeserializationContext.handleWeirdStringValue:(Ljava/lang/Class;Ljava/lang/String;Ljava/lang/String;[Ljava/lang/Object;)Ljava/lang/Object;
     287: checkcast     #111                // class java/lang/Short
     290: invokevirtual #112                // Method java/lang/Short.shortValue:()S
     293: ireturn
     294: aload_0
     295: iload         5
     297: invokevirtual #115                // Method _shortOverflow:(I)Z
     300: ifeq          324
     303: aload_2
     304: getstatic     #109                // Field java/lang/Short.TYPE:Ljava/lang/Class;
     307: aload_3
     308: ldc           #116                // String overflow, value cannot be represented as 16-bit value
     310: iconst_0
     311: anewarray     #4                  // class java/lang/Object
     314: invokevirtual #88                 // Method com/fasterxml/jackson/databind/DeserializationContext.handleWeirdStringValue:(Ljava/lang/Class;Ljava/lang/String;Ljava/lang/String;[Ljava/lang/Object;)Ljava/lang/Object;
     317: checkcast     #111                // class java/lang/Short
     320: invokevirtual #112                // Method java/lang/Short.shortValue:()S
     323: ireturn
     324: iload         5
     326: i2s
     327: ireturn
    Exception table:
       from    to  target type
         262   268   271   Class java/lang/IllegalArgumentException

  protected final int _parseIntPrimitive(com.fasterxml.jackson.core.JsonParser, com.fasterxml.jackson.databind.DeserializationContext) throws java.io.IOException;
    Code:
       0: aload_1
       1: invokevirtual #68                 // Method com/fasterxml/jackson/core/JsonParser.currentTokenId:()I
       4: tableswitch   { // 1 to 11
                     1: 120
                     2: 183
                     3: 133
                     4: 183
                     5: 183
                     6: 64
                     7: 108
                     8: 72
                     9: 183
                    10: 183
                    11: 113
               default: 183
          }
      64: aload_1
      65: invokevirtual #69                 // Method com/fasterxml/jackson/core/JsonParser.getText:()Ljava/lang/String;
      68: astore_3
      69: goto          198
      72: aload_0
      73: aload_1
      74: aload_2
      75: getstatic     #117                // Field java/lang/Integer.TYPE:Ljava/lang/Class;
      78: invokevirtual #99                 // Method _checkFloatToIntCoercion:(Lcom/fasterxml/jackson/core/JsonParser;Lcom/fasterxml/jackson/databind/DeserializationContext;Ljava/lang/Class;)Lcom/fasterxml/jackson/databind/cfg/CoercionAction;
      81: astore        4
      83: aload         4
      85: getstatic     #80                 // Field com/fasterxml/jackson/databind/cfg/CoercionAction.AsNull:Lcom/fasterxml/jackson/databind/cfg/CoercionAction;
      88: if_acmpne     93
      91: iconst_0
      92: ireturn
      93: aload         4
      95: getstatic     #81                 // Field com/fasterxml/jackson/databind/cfg/CoercionAction.AsEmpty:Lcom/fasterxml/jackson/databind/cfg/CoercionAction;
      98: if_acmpne     103
     101: iconst_0
     102: ireturn
     103: aload_1
     104: invokevirtual #118                // Method com/fasterxml/jackson/core/JsonParser.getValueAsInt:()I
     107: ireturn
     108: aload_1
     109: invokevirtual #119                // Method com/fasterxml/jackson/core/JsonParser.getIntValue:()I
     112: ireturn
     113: aload_0
     114: aload_2
     115: invokevirtual #74                 // Method _verifyNullForPrimitive:(Lcom/fasterxml/jackson/databind/DeserializationContext;)V
     118: iconst_0
     119: ireturn
     120: aload_2
     121: aload_1
     122: aload_0
     123: getstatic     #117                // Field java/lang/Integer.TYPE:Ljava/lang/Class;
     126: invokevirtual #75                 // Method com/fasterxml/jackson/databind/DeserializationContext.extractScalarFromObject:(Lcom/fasterxml/jackson/core/JsonParser;Lcom/fasterxml/jackson/databind/JsonDeserializer;Ljava/lang/Class;)Ljava/lang/String;
     129: astore_3
     130: goto          198
     133: aload_2
     134: getstatic     #10                 // Field com/fasterxml/jackson/databind/DeserializationFeature.UNWRAP_SINGLE_VALUE_ARRAYS:Lcom/fasterxml/jackson/databind/DeserializationFeature;
     137: invokevirtual #11                 // Method com/fasterxml/jackson/databind/DeserializationContext.isEnabled:(Lcom/fasterxml/jackson/databind/DeserializationFeature;)Z
     140: ifeq          183
     143: aload_1
     144: invokevirtual #13                 // Method com/fasterxml/jackson/core/JsonParser.nextToken:()Lcom/fasterxml/jackson/core/JsonToken;
     147: getstatic     #22                 // Field com/fasterxml/jackson/core/JsonToken.START_ARRAY:Lcom/fasterxml/jackson/core/JsonToken;
     150: if_acmpne     166
     153: aload_0
     154: aload_1
     155: aload_2
     156: invokevirtual #65                 // Method handleNestedArrayForSingle:(Lcom/fasterxml/jackson/core/JsonParser;Lcom/fasterxml/jackson/databind/DeserializationContext;)Ljava/lang/Object;
     159: checkcast     #44                 // class java/lang/Integer
     162: invokevirtual #120                // Method java/lang/Integer.intValue:()I
     165: ireturn
     166: aload_0
     167: aload_1
     168: aload_2
     169: invokevirtual #121                // Method _parseIntPrimitive:(Lcom/fasterxml/jackson/core/JsonParser;Lcom/fasterxml/jackson/databind/DeserializationContext;)I
     172: istore        5
     174: aload_0
     175: aload_1
     176: aload_2
     177: invokevirtual #77                 // Method _verifyEndArrayForSingle:(Lcom/fasterxml/jackson/core/JsonParser;Lcom/fasterxml/jackson/databind/DeserializationContext;)V
     180: iload         5
     182: ireturn
     183: aload_2
     184: getstatic     #117                // Field java/lang/Integer.TYPE:Ljava/lang/Class;
     187: aload_1
     188: invokevirtual #78                 // Method com/fasterxml/jackson/databind/DeserializationContext.handleUnexpectedToken:(Ljava/lang/Class;Lcom/fasterxml/jackson/core/JsonParser;)Ljava/lang/Object;
     191: checkcast     #122                // class java/lang/Number
     194: invokevirtual #123                // Method java/lang/Number.intValue:()I
     197: ireturn
     198: aload_0
     199: aload_2
     200: aload_3
     201: getstatic     #43                 // Field com/fasterxml/jackson/databind/type/LogicalType.Integer:Lcom/fasterxml/jackson/databind/type/LogicalType;
     204: getstatic     #117                // Field java/lang/Integer.TYPE:Ljava/lang/Class;
     207: invokevirtual #79                 // Method _checkFromStringCoercion:(Lcom/fasterxml/jackson/databind/DeserializationContext;Ljava/lang/String;Lcom/fasterxml/jackson/databind/type/LogicalType;Ljava/lang/Class;)Lcom/fasterxml/jackson/databind/cfg/CoercionAction;
     210: astore        4
     212: aload         4
     214: getstatic     #80                 // Field com/fasterxml/jackson/databind/cfg/CoercionAction.AsNull:Lcom/fasterxml/jackson/databind/cfg/CoercionAction;
     217: if_acmpne     227
     220: aload_0
     221: aload_2
     222: invokevirtual #74                 // Method _verifyNullForPrimitive:(Lcom/fasterxml/jackson/databind/DeserializationContext;)V
     225: iconst_0
     226: ireturn
     227: aload         4
     229: getstatic     #81                 // Field com/fasterxml/jackson/databind/cfg/CoercionAction.AsEmpty:Lcom/fasterxml/jackson/databind/cfg/CoercionAction;
     232: if_acmpne     237
     235: iconst_0
     236: ireturn
     237: aload_3
     238: invokevirtual #41                 // Method java/lang/String.trim:()Ljava/lang/String;
     241: astore_3
     242: aload_0
     243: aload_3
     244: invokevirtual #85                 // Method _hasTextualNull:(Ljava/lang/String;)Z
     247: ifeq          258
     250: aload_0
     251: aload_2
     252: aload_3
     253: invokevirtual #86                 // Method _verifyNullForPrimitiveCoercion:(Lcom/fasterxml/jackson/databind/DeserializationContext;Ljava/lang/String;)V
     256: iconst_0
     257: ireturn
     258: aload_0
     259: aload_2
     260: aload_3
     261: invokevirtual #47                 // Method _parseIntPrimitive:(Lcom/fasterxml/jackson/databind/DeserializationContext;Ljava/lang/String;)I
     264: ireturn

  protected final int _parseIntPrimitive(com.fasterxml.jackson.databind.DeserializationContext, java.lang.String) throws java.io.IOException;
    Code:
       0: aload_2
       1: invokevirtual #82                 // Method java/lang/String.length:()I
       4: bipush        9
       6: if_icmple     74
       9: aload_2
      10: invokestatic  #124                // Method com/fasterxml/jackson/core/io/NumberInput.parseLong:(Ljava/lang/String;)J
      13: lstore_3
      14: aload_0
      15: lload_3
      16: invokevirtual #125                // Method _intOverflow:(J)Z
      19: ifeq          71
      22: aload_1
      23: getstatic     #117                // Field java/lang/Integer.TYPE:Ljava/lang/Class;
      26: aload_2
      27: ldc           #126                // String Overflow: numeric value (%s) out of range of int (%d -%d)
      29: iconst_3
      30: anewarray     #4                  // class java/lang/Object
      33: dup
      34: iconst_0
      35: aload_2
      36: aastore
      37: dup
      38: iconst_1
      39: ldc           #127                // int -2147483648
      41: invokestatic  #128                // Method java/lang/Integer.valueOf:(I)Ljava/lang/Integer;
      44: aastore
      45: dup
      46: iconst_2
      47: ldc           #129                // int 2147483647
      49: invokestatic  #128                // Method java/lang/Integer.valueOf:(I)Ljava/lang/Integer;
      52: aastore
      53: invokevirtual #88                 // Method com/fasterxml/jackson/databind/DeserializationContext.handleWeirdStringValue:(Ljava/lang/Class;Ljava/lang/String;Ljava/lang/String;[Ljava/lang/Object;)Ljava/lang/Object;
      56: checkcast     #122                // class java/lang/Number
      59: astore        5
      61: aload_0
      62: aload         5
      64: invokevirtual #130                // Method _nonNullNumber:(Ljava/lang/Number;)Ljava/lang/Number;
      67: invokevirtual #123                // Method java/lang/Number.intValue:()I
      70: ireturn
      71: lload_3
      72: l2i
      73: ireturn
      74: aload_2
      75: invokestatic  #104                // Method com/fasterxml/jackson/core/io/NumberInput.parseInt:(Ljava/lang/String;)I
      78: ireturn
      79: astore_3
      80: aload_1
      81: getstatic     #117                // Field java/lang/Integer.TYPE:Ljava/lang/Class;
      84: aload_2
      85: ldc           #131                // String not a valid `int` value
      87: iconst_0
      88: anewarray     #4                  // class java/lang/Object
      91: invokevirtual #88                 // Method com/fasterxml/jackson/databind/DeserializationContext.handleWeirdStringValue:(Ljava/lang/Class;Ljava/lang/String;Ljava/lang/String;[Ljava/lang/Object;)Ljava/lang/Object;
      94: checkcast     #122                // class java/lang/Number
      97: astore        4
      99: aload_0
     100: aload         4
     102: invokevirtual #130                // Method _nonNullNumber:(Ljava/lang/Number;)Ljava/lang/Number;
     105: invokevirtual #123                // Method java/lang/Number.intValue:()I
     108: ireturn
    Exception table:
       from    to  target type
           0    70    79   Class java/lang/IllegalArgumentException
          71    73    79   Class java/lang/IllegalArgumentException
          74    78    79   Class java/lang/IllegalArgumentException

  protected final java.lang.Integer _parseInteger(com.fasterxml.jackson.core.JsonParser, com.fasterxml.jackson.databind.DeserializationContext, java.lang.Class<?>) throws java.io.IOException;
    Code:
       0: aload_1
       1: invokevirtual #68                 // Method com/fasterxml/jackson/core/JsonParser.currentTokenId:()I
       4: tableswitch   { // 1 to 11
                     1: 141
                     2: 163
                     3: 153
                     4: 163
                     5: 163
                     6: 64
                     7: 124
                     8: 73
                     9: 163
                    10: 163
                    11: 132
               default: 163
          }
      64: aload_1
      65: invokevirtual #69                 // Method com/fasterxml/jackson/core/JsonParser.getText:()Ljava/lang/String;
      68: astore        4
      70: goto          177
      73: aload_0
      74: aload_1
      75: aload_2
      76: aload_3
      77: invokevirtual #99                 // Method _checkFloatToIntCoercion:(Lcom/fasterxml/jackson/core/JsonParser;Lcom/fasterxml/jackson/databind/DeserializationContext;Ljava/lang/Class;)Lcom/fasterxml/jackson/databind/cfg/CoercionAction;
      80: astore        5
      82: aload         5
      84: getstatic     #80                 // Field com/fasterxml/jackson/databind/cfg/CoercionAction.AsNull:Lcom/fasterxml/jackson/databind/cfg/CoercionAction;
      87: if_acmpne     99
      90: aload_0
      91: aload_2
      92: invokevirtual #18                 // Method getNullValue:(Lcom/fasterxml/jackson/databind/DeserializationContext;)Ljava/lang/Object;
      95: checkcast     #44                 // class java/lang/Integer
      98: areturn
      99: aload         5
     101: getstatic     #81                 // Field com/fasterxml/jackson/databind/cfg/CoercionAction.AsEmpty:Lcom/fasterxml/jackson/databind/cfg/CoercionAction;
     104: if_acmpne     116
     107: aload_0
     108: aload_2
     109: invokevirtual #17                 // Method getEmptyValue:(Lcom/fasterxml/jackson/databind/DeserializationContext;)Ljava/lang/Object;
     112: checkcast     #44                 // class java/lang/Integer
     115: areturn
     116: aload_1
     117: invokevirtual #118                // Method com/fasterxml/jackson/core/JsonParser.getValueAsInt:()I
     120: invokestatic  #128                // Method java/lang/Integer.valueOf:(I)Ljava/lang/Integer;
     123: areturn
     124: aload_1
     125: invokevirtual #119                // Method com/fasterxml/jackson/core/JsonParser.getIntValue:()I
     128: invokestatic  #128                // Method java/lang/Integer.valueOf:(I)Ljava/lang/Integer;
     131: areturn
     132: aload_0
     133: aload_2
     134: invokevirtual #18                 // Method getNullValue:(Lcom/fasterxml/jackson/databind/DeserializationContext;)Ljava/lang/Object;
     137: checkcast     #44                 // class java/lang/Integer
     140: areturn
     141: aload_2
     142: aload_1
     143: aload_0
     144: aload_3
     145: invokevirtual #75                 // Method com/fasterxml/jackson/databind/DeserializationContext.extractScalarFromObject:(Lcom/fasterxml/jackson/core/JsonParser;Lcom/fasterxml/jackson/databind/JsonDeserializer;Ljava/lang/Class;)Ljava/lang/String;
     148: astore        4
     150: goto          177
     153: aload_0
     154: aload_1
     155: aload_2
     156: invokevirtual #95                 // Method _deserializeFromArray:(Lcom/fasterxml/jackson/core/JsonParser;Lcom/fasterxml/jackson/databind/DeserializationContext;)Ljava/lang/Object;
     159: checkcast     #44                 // class java/lang/Integer
     162: areturn
     163: aload_2
     164: aload_0
     165: aload_2
     166: invokevirtual #21                 // Method getValueType:(Lcom/fasterxml/jackson/databind/DeserializationContext;)Lcom/fasterxml/jackson/databind/JavaType;
     169: aload_1
     170: invokevirtual #26                 // Method com/fasterxml/jackson/databind/DeserializationContext.handleUnexpectedToken:(Lcom/fasterxml/jackson/databind/JavaType;Lcom/fasterxml/jackson/core/JsonParser;)Ljava/lang/Object;
     173: checkcast     #44                 // class java/lang/Integer
     176: areturn
     177: aload_0
     178: aload_2
     179: aload         4
     181: invokevirtual #132                // Method _checkFromStringCoercion:(Lcom/fasterxml/jackson/databind/DeserializationContext;Ljava/lang/String;)Lcom/fasterxml/jackson/databind/cfg/CoercionAction;
     184: astore        5
     186: aload         5
     188: getstatic     #80                 // Field com/fasterxml/jackson/databind/cfg/CoercionAction.AsNull:Lcom/fasterxml/jackson/databind/cfg/CoercionAction;
     191: if_acmpne     203
     194: aload_0
     195: aload_2
     196: invokevirtual #18                 // Method getNullValue:(Lcom/fasterxml/jackson/databind/DeserializationContext;)Ljava/lang/Object;
     199: checkcast     #44                 // class java/lang/Integer
     202: areturn
     203: aload         5
     205: getstatic     #81                 // Field com/fasterxml/jackson/databind/cfg/CoercionAction.AsEmpty:Lcom/fasterxml/jackson/databind/cfg/CoercionAction;
     208: if_acmpne     220
     211: aload_0
     212: aload_2
     213: invokevirtual #17                 // Method getEmptyValue:(Lcom/fasterxml/jackson/databind/DeserializationContext;)Ljava/lang/Object;
     216: checkcast     #44                 // class java/lang/Integer
     219: areturn
     220: aload         4
     222: invokevirtual #41                 // Method java/lang/String.trim:()Ljava/lang/String;
     225: astore        4
     227: aload_0
     228: aload_2
     229: aload         4
     231: invokevirtual #96                 // Method _checkTextualNull:(Lcom/fasterxml/jackson/databind/DeserializationContext;Ljava/lang/String;)Z
     234: ifeq          246
     237: aload_0
     238: aload_2
     239: invokevirtual #18                 // Method getNullValue:(Lcom/fasterxml/jackson/databind/DeserializationContext;)Ljava/lang/Object;
     242: checkcast     #44                 // class java/lang/Integer
     245: areturn
     246: aload_0
     247: aload_2
     248: aload         4
     250: invokevirtual #133                // Method _parseInteger:(Lcom/fasterxml/jackson/databind/DeserializationContext;Ljava/lang/String;)Ljava/lang/Integer;
     253: areturn

  protected final java.lang.Integer _parseInteger(com.fasterxml.jackson.databind.DeserializationContext, java.lang.String) throws java.io.IOException;
    Code:
       0: aload_2
       1: invokevirtual #82                 // Method java/lang/String.length:()I
       4: bipush        9
       6: if_icmple     65
       9: aload_2
      10: invokestatic  #124                // Method com/fasterxml/jackson/core/io/NumberInput.parseLong:(Ljava/lang/String;)J
      13: lstore_3
      14: aload_0
      15: lload_3
      16: invokevirtual #125                // Method _intOverflow:(J)Z
      19: ifeq          59
      22: aload_1
      23: ldc           #44                 // class java/lang/Integer
      25: aload_2
      26: ldc           #134                // String Overflow: numeric value (%s) out of range of `java.lang.Integer` (%d -%d)
      28: iconst_3
      29: anewarray     #4                  // class java/lang/Object
      32: dup
      33: iconst_0
      34: aload_2
      35: aastore
      36: dup
      37: iconst_1
      38: ldc           #127                // int -2147483648
      40: invokestatic  #128                // Method java/lang/Integer.valueOf:(I)Ljava/lang/Integer;
      43: aastore
      44: dup
      45: iconst_2
      46: ldc           #129                // int 2147483647
      48: invokestatic  #128                // Method java/lang/Integer.valueOf:(I)Ljava/lang/Integer;
      51: aastore
      52: invokevirtual #88                 // Method com/fasterxml/jackson/databind/DeserializationContext.handleWeirdStringValue:(Ljava/lang/Class;Ljava/lang/String;Ljava/lang/String;[Ljava/lang/Object;)Ljava/lang/Object;
      55: checkcast     #44                 // class java/lang/Integer
      58: areturn
      59: lload_3
      60: l2i
      61: invokestatic  #128                // Method java/lang/Integer.valueOf:(I)Ljava/lang/Integer;
      64: areturn
      65: aload_2
      66: invokestatic  #104                // Method com/fasterxml/jackson/core/io/NumberInput.parseInt:(Ljava/lang/String;)I
      69: invokestatic  #128                // Method java/lang/Integer.valueOf:(I)Ljava/lang/Integer;
      72: areturn
      73: astore_3
      74: aload_1
      75: ldc           #44                 // class java/lang/Integer
      77: aload_2
      78: ldc           #135                // String not a valid `java.lang.Integer` value
      80: iconst_0
      81: anewarray     #4                  // class java/lang/Object
      84: invokevirtual #88                 // Method com/fasterxml/jackson/databind/DeserializationContext.handleWeirdStringValue:(Ljava/lang/Class;Ljava/lang/String;Ljava/lang/String;[Ljava/lang/Object;)Ljava/lang/Object;
      87: checkcast     #44                 // class java/lang/Integer
      90: areturn
    Exception table:
       from    to  target type
           0    58    73   Class java/lang/IllegalArgumentException
          59    64    73   Class java/lang/IllegalArgumentException
          65    72    73   Class java/lang/IllegalArgumentException

  protected final long _parseLongPrimitive(com.fasterxml.jackson.core.JsonParser, com.fasterxml.jackson.databind.DeserializationContext) throws java.io.IOException;
    Code:
       0: aload_1
       1: invokevirtual #68                 // Method com/fasterxml/jackson/core/JsonParser.currentTokenId:()I
       4: tableswitch   { // 1 to 11
                     1: 120
                     2: 183
                     3: 133
                     4: 183
                     5: 183
                     6: 64
                     7: 108
                     8: 72
                     9: 183
                    10: 183
                    11: 113
               default: 183
          }
      64: aload_1
      65: invokevirtual #69                 // Method com/fasterxml/jackson/core/JsonParser.getText:()Ljava/lang/String;
      68: astore_3
      69: goto          198
      72: aload_0
      73: aload_1
      74: aload_2
      75: getstatic     #136                // Field java/lang/Long.TYPE:Ljava/lang/Class;
      78: invokevirtual #99                 // Method _checkFloatToIntCoercion:(Lcom/fasterxml/jackson/core/JsonParser;Lcom/fasterxml/jackson/databind/DeserializationContext;Ljava/lang/Class;)Lcom/fasterxml/jackson/databind/cfg/CoercionAction;
      81: astore        4
      83: aload         4
      85: getstatic     #80                 // Field com/fasterxml/jackson/databind/cfg/CoercionAction.AsNull:Lcom/fasterxml/jackson/databind/cfg/CoercionAction;
      88: if_acmpne     93
      91: lconst_0
      92: lreturn
      93: aload         4
      95: getstatic     #81                 // Field com/fasterxml/jackson/databind/cfg/CoercionAction.AsEmpty:Lcom/fasterxml/jackson/databind/cfg/CoercionAction;
      98: if_acmpne     103
     101: lconst_0
     102: lreturn
     103: aload_1
     104: invokevirtual #137                // Method com/fasterxml/jackson/core/JsonParser.getValueAsLong:()J
     107: lreturn
     108: aload_1
     109: invokevirtual #138                // Method com/fasterxml/jackson/core/JsonParser.getLongValue:()J
     112: lreturn
     113: aload_0
     114: aload_2
     115: invokevirtual #74                 // Method _verifyNullForPrimitive:(Lcom/fasterxml/jackson/databind/DeserializationContext;)V
     118: lconst_0
     119: lreturn
     120: aload_2
     121: aload_1
     122: aload_0
     123: getstatic     #136                // Field java/lang/Long.TYPE:Ljava/lang/Class;
     126: invokevirtual #75                 // Method com/fasterxml/jackson/databind/DeserializationContext.extractScalarFromObject:(Lcom/fasterxml/jackson/core/JsonParser;Lcom/fasterxml/jackson/databind/JsonDeserializer;Ljava/lang/Class;)Ljava/lang/String;
     129: astore_3
     130: goto          198
     133: aload_2
     134: getstatic     #10                 // Field com/fasterxml/jackson/databind/DeserializationFeature.UNWRAP_SINGLE_VALUE_ARRAYS:Lcom/fasterxml/jackson/databind/DeserializationFeature;
     137: invokevirtual #11                 // Method com/fasterxml/jackson/databind/DeserializationContext.isEnabled:(Lcom/fasterxml/jackson/databind/DeserializationFeature;)Z
     140: ifeq          183
     143: aload_1
     144: invokevirtual #13                 // Method com/fasterxml/jackson/core/JsonParser.nextToken:()Lcom/fasterxml/jackson/core/JsonToken;
     147: getstatic     #22                 // Field com/fasterxml/jackson/core/JsonToken.START_ARRAY:Lcom/fasterxml/jackson/core/JsonToken;
     150: if_acmpne     166
     153: aload_0
     154: aload_1
     155: aload_2
     156: invokevirtual #65                 // Method handleNestedArrayForSingle:(Lcom/fasterxml/jackson/core/JsonParser;Lcom/fasterxml/jackson/databind/DeserializationContext;)Ljava/lang/Object;
     159: checkcast     #50                 // class java/lang/Long
     162: invokevirtual #139                // Method java/lang/Long.longValue:()J
     165: lreturn
     166: aload_0
     167: aload_1
     168: aload_2
     169: invokevirtual #140                // Method _parseLongPrimitive:(Lcom/fasterxml/jackson/core/JsonParser;Lcom/fasterxml/jackson/databind/DeserializationContext;)J
     172: lstore        5
     174: aload_0
     175: aload_1
     176: aload_2
     177: invokevirtual #77                 // Method _verifyEndArrayForSingle:(Lcom/fasterxml/jackson/core/JsonParser;Lcom/fasterxml/jackson/databind/DeserializationContext;)V
     180: lload         5
     182: lreturn
     183: aload_2
     184: getstatic     #136                // Field java/lang/Long.TYPE:Ljava/lang/Class;
     187: aload_1
     188: invokevirtual #78                 // Method com/fasterxml/jackson/databind/DeserializationContext.handleUnexpectedToken:(Ljava/lang/Class;Lcom/fasterxml/jackson/core/JsonParser;)Ljava/lang/Object;
     191: checkcast     #122                // class java/lang/Number
     194: invokevirtual #141                // Method java/lang/Number.longValue:()J
     197: lreturn
     198: aload_0
     199: aload_2
     200: aload_3
     201: getstatic     #43                 // Field com/fasterxml/jackson/databind/type/LogicalType.Integer:Lcom/fasterxml/jackson/databind/type/LogicalType;
     204: getstatic     #136                // Field java/lang/Long.TYPE:Ljava/lang/Class;
     207: invokevirtual #79                 // Method _checkFromStringCoercion:(Lcom/fasterxml/jackson/databind/DeserializationContext;Ljava/lang/String;Lcom/fasterxml/jackson/databind/type/LogicalType;Ljava/lang/Class;)Lcom/fasterxml/jackson/databind/cfg/CoercionAction;
     210: astore        4
     212: aload         4
     214: getstatic     #80                 // Field com/fasterxml/jackson/databind/cfg/CoercionAction.AsNull:Lcom/fasterxml/jackson/databind/cfg/CoercionAction;
     217: if_acmpne     227
     220: aload_0
     221: aload_2
     222: invokevirtual #74                 // Method _verifyNullForPrimitive:(Lcom/fasterxml/jackson/databind/DeserializationContext;)V
     225: lconst_0
     226: lreturn
     227: aload         4
     229: getstatic     #81                 // Field com/fasterxml/jackson/databind/cfg/CoercionAction.AsEmpty:Lcom/fasterxml/jackson/databind/cfg/CoercionAction;
     232: if_acmpne     237
     235: lconst_0
     236: lreturn
     237: aload_3
     238: invokevirtual #41                 // Method java/lang/String.trim:()Ljava/lang/String;
     241: astore_3
     242: aload_0
     243: aload_3
     244: invokevirtual #85                 // Method _hasTextualNull:(Ljava/lang/String;)Z
     247: ifeq          258
     250: aload_0
     251: aload_2
     252: aload_3
     253: invokevirtual #86                 // Method _verifyNullForPrimitiveCoercion:(Lcom/fasterxml/jackson/databind/DeserializationContext;Ljava/lang/String;)V
     256: lconst_0
     257: lreturn
     258: aload_0
     259: aload_2
     260: aload_3
     261: invokevirtual #51                 // Method _parseLongPrimitive:(Lcom/fasterxml/jackson/databind/DeserializationContext;Ljava/lang/String;)J
     264: lreturn

  protected final long _parseLongPrimitive(com.fasterxml.jackson.databind.DeserializationContext, java.lang.String) throws java.io.IOException;
    Code:
       0: aload_2
       1: invokestatic  #124                // Method com/fasterxml/jackson/core/io/NumberInput.parseLong:(Ljava/lang/String;)J
       4: lreturn
       5: astore_3
       6: aload_1
       7: getstatic     #136                // Field java/lang/Long.TYPE:Ljava/lang/Class;
      10: aload_2
      11: ldc           #142                // String not a valid `long` value
      13: iconst_0
      14: anewarray     #4                  // class java/lang/Object
      17: invokevirtual #88                 // Method com/fasterxml/jackson/databind/DeserializationContext.handleWeirdStringValue:(Ljava/lang/Class;Ljava/lang/String;Ljava/lang/String;[Ljava/lang/Object;)Ljava/lang/Object;
      20: checkcast     #122                // class java/lang/Number
      23: astore_3
      24: aload_0
      25: aload_3
      26: invokevirtual #130                // Method _nonNullNumber:(Ljava/lang/Number;)Ljava/lang/Number;
      29: invokevirtual #141                // Method java/lang/Number.longValue:()J
      32: lreturn
    Exception table:
       from    to  target type
           0     4     5   Class java/lang/IllegalArgumentException

  protected final java.lang.Long _parseLong(com.fasterxml.jackson.core.JsonParser, com.fasterxml.jackson.databind.DeserializationContext, java.lang.Class<?>) throws java.io.IOException;
    Code:
       0: aload_1
       1: invokevirtual #68                 // Method com/fasterxml/jackson/core/JsonParser.currentTokenId:()I
       4: tableswitch   { // 1 to 11
                     1: 141
                     2: 163
                     3: 153
                     4: 163
                     5: 163
                     6: 64
                     7: 133
                     8: 73
                     9: 163
                    10: 163
                    11: 124
               default: 163
          }
      64: aload_1
      65: invokevirtual #69                 // Method com/fasterxml/jackson/core/JsonParser.getText:()Ljava/lang/String;
      68: astore        4
      70: goto          177
      73: aload_0
      74: aload_1
      75: aload_2
      76: aload_3
      77: invokevirtual #99                 // Method _checkFloatToIntCoercion:(Lcom/fasterxml/jackson/core/JsonParser;Lcom/fasterxml/jackson/databind/DeserializationContext;Ljava/lang/Class;)Lcom/fasterxml/jackson/databind/cfg/CoercionAction;
      80: astore        5
      82: aload         5
      84: getstatic     #80                 // Field com/fasterxml/jackson/databind/cfg/CoercionAction.AsNull:Lcom/fasterxml/jackson/databind/cfg/CoercionAction;
      87: if_acmpne     99
      90: aload_0
      91: aload_2
      92: invokevirtual #18                 // Method getNullValue:(Lcom/fasterxml/jackson/databind/DeserializationContext;)Ljava/lang/Object;
      95: checkcast     #50                 // class java/lang/Long
      98: areturn
      99: aload         5
     101: getstatic     #81                 // Field com/fasterxml/jackson/databind/cfg/CoercionAction.AsEmpty:Lcom/fasterxml/jackson/databind/cfg/CoercionAction;
     104: if_acmpne     116
     107: aload_0
     108: aload_2
     109: invokevirtual #17                 // Method getEmptyValue:(Lcom/fasterxml/jackson/databind/DeserializationContext;)Ljava/lang/Object;
     112: checkcast     #50                 // class java/lang/Long
     115: areturn
     116: aload_1
     117: invokevirtual #137                // Method com/fasterxml/jackson/core/JsonParser.getValueAsLong:()J
     120: invokestatic  #143                // Method java/lang/Long.valueOf:(J)Ljava/lang/Long;
     123: areturn
     124: aload_0
     125: aload_2
     126: invokevirtual #18                 // Method getNullValue:(Lcom/fasterxml/jackson/databind/DeserializationContext;)Ljava/lang/Object;
     129: checkcast     #50                 // class java/lang/Long
     132: areturn
     133: aload_1
     134: invokevirtual #138                // Method com/fasterxml/jackson/core/JsonParser.getLongValue:()J
     137: invokestatic  #143                // Method java/lang/Long.valueOf:(J)Ljava/lang/Long;
     140: areturn
     141: aload_2
     142: aload_1
     143: aload_0
     144: aload_3
     145: invokevirtual #75                 // Method com/fasterxml/jackson/databind/DeserializationContext.extractScalarFromObject:(Lcom/fasterxml/jackson/core/JsonParser;Lcom/fasterxml/jackson/databind/JsonDeserializer;Ljava/lang/Class;)Ljava/lang/String;
     148: astore        4
     150: goto          177
     153: aload_0
     154: aload_1
     155: aload_2
     156: invokevirtual #95                 // Method _deserializeFromArray:(Lcom/fasterxml/jackson/core/JsonParser;Lcom/fasterxml/jackson/databind/DeserializationContext;)Ljava/lang/Object;
     159: checkcast     #50                 // class java/lang/Long
     162: areturn
     163: aload_2
     164: aload_0
     165: aload_2
     166: invokevirtual #21                 // Method getValueType:(Lcom/fasterxml/jackson/databind/DeserializationContext;)Lcom/fasterxml/jackson/databind/JavaType;
     169: aload_1
     170: invokevirtual #26                 // Method com/fasterxml/jackson/databind/DeserializationContext.handleUnexpectedToken:(Lcom/fasterxml/jackson/databind/JavaType;Lcom/fasterxml/jackson/core/JsonParser;)Ljava/lang/Object;
     173: checkcast     #50                 // class java/lang/Long
     176: areturn
     177: aload_0
     178: aload_2
     179: aload         4
     181: invokevirtual #132                // Method _checkFromStringCoercion:(Lcom/fasterxml/jackson/databind/DeserializationContext;Ljava/lang/String;)Lcom/fasterxml/jackson/databind/cfg/CoercionAction;
     184: astore        5
     186: aload         5
     188: getstatic     #80                 // Field com/fasterxml/jackson/databind/cfg/CoercionAction.AsNull:Lcom/fasterxml/jackson/databind/cfg/CoercionAction;
     191: if_acmpne     203
     194: aload_0
     195: aload_2
     196: invokevirtual #18                 // Method getNullValue:(Lcom/fasterxml/jackson/databind/DeserializationContext;)Ljava/lang/Object;
     199: checkcast     #50                 // class java/lang/Long
     202: areturn
     203: aload         5
     205: getstatic     #81                 // Field com/fasterxml/jackson/databind/cfg/CoercionAction.AsEmpty:Lcom/fasterxml/jackson/databind/cfg/CoercionAction;
     208: if_acmpne     220
     211: aload_0
     212: aload_2
     213: invokevirtual #17                 // Method getEmptyValue:(Lcom/fasterxml/jackson/databind/DeserializationContext;)Ljava/lang/Object;
     216: checkcast     #50                 // class java/lang/Long
     219: areturn
     220: aload         4
     222: invokevirtual #41                 // Method java/lang/String.trim:()Ljava/lang/String;
     225: astore        4
     227: aload_0
     228: aload_2
     229: aload         4
     231: invokevirtual #96                 // Method _checkTextualNull:(Lcom/fasterxml/jackson/databind/DeserializationContext;Ljava/lang/String;)Z
     234: ifeq          246
     237: aload_0
     238: aload_2
     239: invokevirtual #18                 // Method getNullValue:(Lcom/fasterxml/jackson/databind/DeserializationContext;)Ljava/lang/Object;
     242: checkcast     #50                 // class java/lang/Long
     245: areturn
     246: aload_0
     247: aload_2
     248: aload         4
     250: invokevirtual #144                // Method _parseLong:(Lcom/fasterxml/jackson/databind/DeserializationContext;Ljava/lang/String;)Ljava/lang/Long;
     253: areturn

  protected final java.lang.Long _parseLong(com.fasterxml.jackson.databind.DeserializationContext, java.lang.String) throws java.io.IOException;
    Code:
       0: aload_2
       1: invokestatic  #124                // Method com/fasterxml/jackson/core/io/NumberInput.parseLong:(Ljava/lang/String;)J
       4: invokestatic  #143                // Method java/lang/Long.valueOf:(J)Ljava/lang/Long;
       7: areturn
       8: astore_3
       9: aload_1
      10: ldc           #50                 // class java/lang/Long
      12: aload_2
      13: ldc           #145                // String not a valid `java.lang.Long` value
      15: iconst_0
      16: anewarray     #4                  // class java/lang/Object
      19: invokevirtual #88                 // Method com/fasterxml/jackson/databind/DeserializationContext.handleWeirdStringValue:(Ljava/lang/Class;Ljava/lang/String;Ljava/lang/String;[Ljava/lang/Object;)Ljava/lang/Object;
      22: checkcast     #50                 // class java/lang/Long
      25: areturn
    Exception table:
       from    to  target type
           0     7     8   Class java/lang/IllegalArgumentException

  protected final float _parseFloatPrimitive(com.fasterxml.jackson.core.JsonParser, com.fasterxml.jackson.databind.DeserializationContext) throws java.io.IOException;
    Code:
       0: aload_1
       1: invokevirtual #68                 // Method com/fasterxml/jackson/core/JsonParser.currentTokenId:()I
       4: tableswitch   { // 1 to 11
                     1: 115
                     2: 178
                     3: 128
                     4: 178
                     5: 178
                     6: 64
                     7: 72
                     8: 103
                     9: 178
                    10: 178
                    11: 108
               default: 178
          }
      64: aload_1
      65: invokevirtual #69                 // Method com/fasterxml/jackson/core/JsonParser.getText:()Ljava/lang/String;
      68: astore_3
      69: goto          193
      72: aload_0
      73: aload_1
      74: aload_2
      75: getstatic     #146                // Field java/lang/Float.TYPE:Ljava/lang/Class;
      78: invokevirtual #147                // Method _checkIntToFloatCoercion:(Lcom/fasterxml/jackson/core/JsonParser;Lcom/fasterxml/jackson/databind/DeserializationContext;Ljava/lang/Class;)Lcom/fasterxml/jackson/databind/cfg/CoercionAction;
      81: astore        4
      83: aload         4
      85: getstatic     #80                 // Field com/fasterxml/jackson/databind/cfg/CoercionAction.AsNull:Lcom/fasterxml/jackson/databind/cfg/CoercionAction;
      88: if_acmpne     93
      91: fconst_0
      92: freturn
      93: aload         4
      95: getstatic     #81                 // Field com/fasterxml/jackson/databind/cfg/CoercionAction.AsEmpty:Lcom/fasterxml/jackson/databind/cfg/CoercionAction;
      98: if_acmpne     103
     101: fconst_0
     102: freturn
     103: aload_1
     104: invokevirtual #148                // Method com/fasterxml/jackson/core/JsonParser.getFloatValue:()F
     107: freturn
     108: aload_0
     109: aload_2
     110: invokevirtual #74                 // Method _verifyNullForPrimitive:(Lcom/fasterxml/jackson/databind/DeserializationContext;)V
     113: fconst_0
     114: freturn
     115: aload_2
     116: aload_1
     117: aload_0
     118: getstatic     #146                // Field java/lang/Float.TYPE:Ljava/lang/Class;
     121: invokevirtual #75                 // Method com/fasterxml/jackson/databind/DeserializationContext.extractScalarFromObject:(Lcom/fasterxml/jackson/core/JsonParser;Lcom/fasterxml/jackson/databind/JsonDeserializer;Ljava/lang/Class;)Ljava/lang/String;
     124: astore_3
     125: goto          193
     128: aload_2
     129: getstatic     #10                 // Field com/fasterxml/jackson/databind/DeserializationFeature.UNWRAP_SINGLE_VALUE_ARRAYS:Lcom/fasterxml/jackson/databind/DeserializationFeature;
     132: invokevirtual #11                 // Method com/fasterxml/jackson/databind/DeserializationContext.isEnabled:(Lcom/fasterxml/jackson/databind/DeserializationFeature;)Z
     135: ifeq          178
     138: aload_1
     139: invokevirtual #13                 // Method com/fasterxml/jackson/core/JsonParser.nextToken:()Lcom/fasterxml/jackson/core/JsonToken;
     142: getstatic     #22                 // Field com/fasterxml/jackson/core/JsonToken.START_ARRAY:Lcom/fasterxml/jackson/core/JsonToken;
     145: if_acmpne     161
     148: aload_0
     149: aload_1
     150: aload_2
     151: invokevirtual #65                 // Method handleNestedArrayForSingle:(Lcom/fasterxml/jackson/core/JsonParser;Lcom/fasterxml/jackson/databind/DeserializationContext;)Ljava/lang/Object;
     154: checkcast     #149                // class java/lang/Float
     157: invokevirtual #150                // Method java/lang/Float.floatValue:()F
     160: freturn
     161: aload_0
     162: aload_1
     163: aload_2
     164: invokevirtual #151                // Method _parseFloatPrimitive:(Lcom/fasterxml/jackson/core/JsonParser;Lcom/fasterxml/jackson/databind/DeserializationContext;)F
     167: fstore        5
     169: aload_0
     170: aload_1
     171: aload_2
     172: invokevirtual #77                 // Method _verifyEndArrayForSingle:(Lcom/fasterxml/jackson/core/JsonParser;Lcom/fasterxml/jackson/databind/DeserializationContext;)V
     175: fload         5
     177: freturn
     178: aload_2
     179: getstatic     #146                // Field java/lang/Float.TYPE:Ljava/lang/Class;
     182: aload_1
     183: invokevirtual #78                 // Method com/fasterxml/jackson/databind/DeserializationContext.handleUnexpectedToken:(Ljava/lang/Class;Lcom/fasterxml/jackson/core/JsonParser;)Ljava/lang/Object;
     186: checkcast     #122                // class java/lang/Number
     189: invokevirtual #152                // Method java/lang/Number.floatValue:()F
     192: freturn
     193: aload_0
     194: aload_3
     195: invokevirtual #153                // Method _checkFloatSpecialValue:(Ljava/lang/String;)Ljava/lang/Float;
     198: astore        4
     200: aload         4
     202: ifnull        211
     205: aload         4
     207: invokevirtual #150                // Method java/lang/Float.floatValue:()F
     210: freturn
     211: aload_0
     212: aload_2
     213: aload_3
     214: getstatic     #43                 // Field com/fasterxml/jackson/databind/type/LogicalType.Integer:Lcom/fasterxml/jackson/databind/type/LogicalType;
     217: getstatic     #146                // Field java/lang/Float.TYPE:Ljava/lang/Class;
     220: invokevirtual #79                 // Method _checkFromStringCoercion:(Lcom/fasterxml/jackson/databind/DeserializationContext;Ljava/lang/String;Lcom/fasterxml/jackson/databind/type/LogicalType;Ljava/lang/Class;)Lcom/fasterxml/jackson/databind/cfg/CoercionAction;
     223: astore        4
     225: aload         4
     227: getstatic     #80                 // Field com/fasterxml/jackson/databind/cfg/CoercionAction.AsNull:Lcom/fasterxml/jackson/databind/cfg/CoercionAction;
     230: if_acmpne     240
     233: aload_0
     234: aload_2
     235: invokevirtual #74                 // Method _verifyNullForPrimitive:(Lcom/fasterxml/jackson/databind/DeserializationContext;)V
     238: fconst_0
     239: freturn
     240: aload         4
     242: getstatic     #81                 // Field com/fasterxml/jackson/databind/cfg/CoercionAction.AsEmpty:Lcom/fasterxml/jackson/databind/cfg/CoercionAction;
     245: if_acmpne     250
     248: fconst_0
     249: freturn
     250: aload_3
     251: invokevirtual #41                 // Method java/lang/String.trim:()Ljava/lang/String;
     254: astore_3
     255: aload_0
     256: aload_3
     257: invokevirtual #85                 // Method _hasTextualNull:(Ljava/lang/String;)Z
     260: ifeq          271
     263: aload_0
     264: aload_2
     265: aload_3
     266: invokevirtual #86                 // Method _verifyNullForPrimitiveCoercion:(Lcom/fasterxml/jackson/databind/DeserializationContext;Ljava/lang/String;)V
     269: fconst_0
     270: freturn
     271: aload_0
     272: aload_1
     273: aload_2
     274: aload_3
     275: invokevirtual #154                // Method _parseFloatPrimitive:(Lcom/fasterxml/jackson/core/JsonParser;Lcom/fasterxml/jackson/databind/DeserializationContext;Ljava/lang/String;)F
     278: freturn

  protected final float _parseFloatPrimitive(com.fasterxml.jackson.databind.DeserializationContext, java.lang.String) throws java.io.IOException;
    Code:
       0: aload_2
       1: invokestatic  #155                // Method com/fasterxml/jackson/core/io/NumberInput.parseFloat:(Ljava/lang/String;)F
       4: freturn
       5: astore_3
       6: aload_1
       7: getstatic     #146                // Field java/lang/Float.TYPE:Ljava/lang/Class;
      10: aload_2
      11: ldc           #156                // String not a valid `float` value
      13: iconst_0
      14: anewarray     #4                  // class java/lang/Object
      17: invokevirtual #88                 // Method com/fasterxml/jackson/databind/DeserializationContext.handleWeirdStringValue:(Ljava/lang/Class;Ljava/lang/String;Ljava/lang/String;[Ljava/lang/Object;)Ljava/lang/Object;
      20: checkcast     #122                // class java/lang/Number
      23: astore_3
      24: aload_0
      25: aload_3
      26: invokevirtual #130                // Method _nonNullNumber:(Ljava/lang/Number;)Ljava/lang/Number;
      29: invokevirtual #152                // Method java/lang/Number.floatValue:()F
      32: freturn
    Exception table:
       from    to  target type
           0     4     5   Class java/lang/IllegalArgumentException

  protected final float _parseFloatPrimitive(com.fasterxml.jackson.core.JsonParser, com.fasterxml.jackson.databind.DeserializationContext, java.lang.String) throws java.io.IOException;
    Code:
       0: aload_3
       1: aload_1
       2: getstatic     #157                // Field com/fasterxml/jackson/core/StreamReadFeature.USE_FAST_DOUBLE_PARSER:Lcom/fasterxml/jackson/core/StreamReadFeature;
       5: invokevirtual #158                // Method com/fasterxml/jackson/core/JsonParser.isEnabled:(Lcom/fasterxml/jackson/core/StreamReadFeature;)Z
       8: invokestatic  #159                // Method com/fasterxml/jackson/core/io/NumberInput.parseFloat:(Ljava/lang/String;Z)F
      11: freturn
      12: astore        4
      14: aload_2
      15: getstatic     #146                // Field java/lang/Float.TYPE:Ljava/lang/Class;
      18: aload_3
      19: ldc           #156                // String not a valid `float` value
      21: iconst_0
      22: anewarray     #4                  // class java/lang/Object
      25: invokevirtual #88                 // Method com/fasterxml/jackson/databind/DeserializationContext.handleWeirdStringValue:(Ljava/lang/Class;Ljava/lang/String;Ljava/lang/String;[Ljava/lang/Object;)Ljava/lang/Object;
      28: checkcast     #122                // class java/lang/Number
      31: astore        4
      33: aload_0
      34: aload         4
      36: invokevirtual #130                // Method _nonNullNumber:(Ljava/lang/Number;)Ljava/lang/Number;
      39: invokevirtual #152                // Method java/lang/Number.floatValue:()F
      42: freturn
    Exception table:
       from    to  target type
           0    11    12   Class java/lang/IllegalArgumentException

  protected java.lang.Float _checkFloatSpecialValue(java.lang.String);
    Code:
       0: aload_1
       1: invokevirtual #32                 // Method java/lang/String.isEmpty:()Z
       4: ifne          90
       7: aload_1
       8: iconst_0
       9: invokevirtual #89                 // Method java/lang/String.charAt:(I)C
      12: lookupswitch  { // 3
                    45: 76
                    73: 48
                    78: 62
               default: 90
          }
      48: aload_0
      49: aload_1
      50: invokevirtual #160                // Method _isPosInf:(Ljava/lang/String;)Z
      53: ifeq          90
      56: ldc           #161                // float Infinityf
      58: invokestatic  #162                // Method java/lang/Float.valueOf:(F)Ljava/lang/Float;
      61: areturn
      62: aload_0
      63: aload_1
      64: invokevirtual #163                // Method _isNaN:(Ljava/lang/String;)Z
      67: ifeq          90
      70: ldc           #164                // float NaNf
      72: invokestatic  #162                // Method java/lang/Float.valueOf:(F)Ljava/lang/Float;
      75: areturn
      76: aload_0
      77: aload_1
      78: invokevirtual #165                // Method _isNegInf:(Ljava/lang/String;)Z
      81: ifeq          90
      84: ldc           #166                // float -Infinityf
      86: invokestatic  #162                // Method java/lang/Float.valueOf:(F)Ljava/lang/Float;
      89: areturn
      90: aconst_null
      91: areturn

  protected final double _parseDoublePrimitive(com.fasterxml.jackson.core.JsonParser, com.fasterxml.jackson.databind.DeserializationContext) throws java.io.IOException;
    Code:
       0: aload_1
       1: invokevirtual #68                 // Method com/fasterxml/jackson/core/JsonParser.currentTokenId:()I
       4: tableswitch   { // 1 to 11
                     1: 115
                     2: 178
                     3: 128
                     4: 178
                     5: 178
                     6: 64
                     7: 72
                     8: 103
                     9: 178
                    10: 178
                    11: 108
               default: 178
          }
      64: aload_1
      65: invokevirtual #69                 // Method com/fasterxml/jackson/core/JsonParser.getText:()Ljava/lang/String;
      68: astore_3
      69: goto          193
      72: aload_0
      73: aload_1
      74: aload_2
      75: getstatic     #167                // Field java/lang/Double.TYPE:Ljava/lang/Class;
      78: invokevirtual #147                // Method _checkIntToFloatCoercion:(Lcom/fasterxml/jackson/core/JsonParser;Lcom/fasterxml/jackson/databind/DeserializationContext;Ljava/lang/Class;)Lcom/fasterxml/jackson/databind/cfg/CoercionAction;
      81: astore        4
      83: aload         4
      85: getstatic     #80                 // Field com/fasterxml/jackson/databind/cfg/CoercionAction.AsNull:Lcom/fasterxml/jackson/databind/cfg/CoercionAction;
      88: if_acmpne     93
      91: dconst_0
      92: dreturn
      93: aload         4
      95: getstatic     #81                 // Field com/fasterxml/jackson/databind/cfg/CoercionAction.AsEmpty:Lcom/fasterxml/jackson/databind/cfg/CoercionAction;
      98: if_acmpne     103
     101: dconst_0
     102: dreturn
     103: aload_1
     104: invokevirtual #168                // Method com/fasterxml/jackson/core/JsonParser.getDoubleValue:()D
     107: dreturn
     108: aload_0
     109: aload_2
     110: invokevirtual #74                 // Method _verifyNullForPrimitive:(Lcom/fasterxml/jackson/databind/DeserializationContext;)V
     113: dconst_0
     114: dreturn
     115: aload_2
     116: aload_1
     117: aload_0
     118: getstatic     #167                // Field java/lang/Double.TYPE:Ljava/lang/Class;
     121: invokevirtual #75                 // Method com/fasterxml/jackson/databind/DeserializationContext.extractScalarFromObject:(Lcom/fasterxml/jackson/core/JsonParser;Lcom/fasterxml/jackson/databind/JsonDeserializer;Ljava/lang/Class;)Ljava/lang/String;
     124: astore_3
     125: goto          193
     128: aload_2
     129: getstatic     #10                 // Field com/fasterxml/jackson/databind/DeserializationFeature.UNWRAP_SINGLE_VALUE_ARRAYS:Lcom/fasterxml/jackson/databind/DeserializationFeature;
     132: invokevirtual #11                 // Method com/fasterxml/jackson/databind/DeserializationContext.isEnabled:(Lcom/fasterxml/jackson/databind/DeserializationFeature;)Z
     135: ifeq          178
     138: aload_1
     139: invokevirtual #13                 // Method com/fasterxml/jackson/core/JsonParser.nextToken:()Lcom/fasterxml/jackson/core/JsonToken;
     142: getstatic     #22                 // Field com/fasterxml/jackson/core/JsonToken.START_ARRAY:Lcom/fasterxml/jackson/core/JsonToken;
     145: if_acmpne     161
     148: aload_0
     149: aload_1
     150: aload_2
     151: invokevirtual #65                 // Method handleNestedArrayForSingle:(Lcom/fasterxml/jackson/core/JsonParser;Lcom/fasterxml/jackson/databind/DeserializationContext;)Ljava/lang/Object;
     154: checkcast     #169                // class java/lang/Double
     157: invokevirtual #170                // Method java/lang/Double.doubleValue:()D
     160: dreturn
     161: aload_0
     162: aload_1
     163: aload_2
     164: invokevirtual #171                // Method _parseDoublePrimitive:(Lcom/fasterxml/jackson/core/JsonParser;Lcom/fasterxml/jackson/databind/DeserializationContext;)D
     167: dstore        5
     169: aload_0
     170: aload_1
     171: aload_2
     172: invokevirtual #77                 // Method _verifyEndArrayForSingle:(Lcom/fasterxml/jackson/core/JsonParser;Lcom/fasterxml/jackson/databind/DeserializationContext;)V
     175: dload         5
     177: dreturn
     178: aload_2
     179: getstatic     #167                // Field java/lang/Double.TYPE:Ljava/lang/Class;
     182: aload_1
     183: invokevirtual #78                 // Method com/fasterxml/jackson/databind/DeserializationContext.handleUnexpectedToken:(Ljava/lang/Class;Lcom/fasterxml/jackson/core/JsonParser;)Ljava/lang/Object;
     186: checkcast     #122                // class java/lang/Number
     189: invokevirtual #172                // Method java/lang/Number.doubleValue:()D
     192: dreturn
     193: aload_0
     194: aload_3
     195: invokevirtual #173                // Method _checkDoubleSpecialValue:(Ljava/lang/String;)Ljava/lang/Double;
     198: astore        4
     200: aload         4
     202: ifnull        211
     205: aload         4
     207: invokevirtual #170                // Method java/lang/Double.doubleValue:()D
     210: dreturn
     211: aload_0
     212: aload_2
     213: aload_3
     214: getstatic     #43                 // Field com/fasterxml/jackson/databind/type/LogicalType.Integer:Lcom/fasterxml/jackson/databind/type/LogicalType;
     217: getstatic     #167                // Field java/lang/Double.TYPE:Ljava/lang/Class;
     220: invokevirtual #79                 // Method _checkFromStringCoercion:(Lcom/fasterxml/jackson/databind/DeserializationContext;Ljava/lang/String;Lcom/fasterxml/jackson/databind/type/LogicalType;Ljava/lang/Class;)Lcom/fasterxml/jackson/databind/cfg/CoercionAction;
     223: astore        4
     225: aload         4
     227: getstatic     #80                 // Field com/fasterxml/jackson/databind/cfg/CoercionAction.AsNull:Lcom/fasterxml/jackson/databind/cfg/CoercionAction;
     230: if_acmpne     240
     233: aload_0
     234: aload_2
     235: invokevirtual #74                 // Method _verifyNullForPrimitive:(Lcom/fasterxml/jackson/databind/DeserializationContext;)V
     238: dconst_0
     239: dreturn
     240: aload         4
     242: getstatic     #81                 // Field com/fasterxml/jackson/databind/cfg/CoercionAction.AsEmpty:Lcom/fasterxml/jackson/databind/cfg/CoercionAction;
     245: if_acmpne     250
     248: dconst_0
     249: dreturn
     250: aload_3
     251: invokevirtual #41                 // Method java/lang/String.trim:()Ljava/lang/String;
     254: astore_3
     255: aload_0
     256: aload_3
     257: invokevirtual #85                 // Method _hasTextualNull:(Ljava/lang/String;)Z
     260: ifeq          271
     263: aload_0
     264: aload_2
     265: aload_3
     266: invokevirtual #86                 // Method _verifyNullForPrimitiveCoercion:(Lcom/fasterxml/jackson/databind/DeserializationContext;Ljava/lang/String;)V
     269: dconst_0
     270: dreturn
     271: aload_0
     272: aload_1
     273: aload_2
     274: aload_3
     275: invokevirtual #174                // Method _parseDoublePrimitive:(Lcom/fasterxml/jackson/core/JsonParser;Lcom/fasterxml/jackson/databind/DeserializationContext;Ljava/lang/String;)D
     278: dreturn

  protected final double _parseDoublePrimitive(com.fasterxml.jackson.databind.DeserializationContext, java.lang.String) throws java.io.IOException;
    Code:
       0: aload_2
       1: invokestatic  #175                // Method _parseDouble:(Ljava/lang/String;)D
       4: dreturn
       5: astore_3
       6: aload_1
       7: getstatic     #167                // Field java/lang/Double.TYPE:Ljava/lang/Class;
      10: aload_2
      11: ldc           #176                // String not a valid `double` value (as String to convert)
      13: iconst_0
      14: anewarray     #4                  // class java/lang/Object
      17: invokevirtual #88                 // Method com/fasterxml/jackson/databind/DeserializationContext.handleWeirdStringValue:(Ljava/lang/Class;Ljava/lang/String;Ljava/lang/String;[Ljava/lang/Object;)Ljava/lang/Object;
      20: checkcast     #122                // class java/lang/Number
      23: astore_3
      24: aload_0
      25: aload_3
      26: invokevirtual #130                // Method _nonNullNumber:(Ljava/lang/Number;)Ljava/lang/Number;
      29: invokevirtual #172                // Method java/lang/Number.doubleValue:()D
      32: dreturn
    Exception table:
       from    to  target type
           0     4     5   Class java/lang/IllegalArgumentException

  protected final double _parseDoublePrimitive(com.fasterxml.jackson.core.JsonParser, com.fasterxml.jackson.databind.DeserializationContext, java.lang.String) throws java.io.IOException;
    Code:
       0: aload_3
       1: aload_1
       2: getstatic     #157                // Field com/fasterxml/jackson/core/StreamReadFeature.USE_FAST_DOUBLE_PARSER:Lcom/fasterxml/jackson/core/StreamReadFeature;
       5: invokevirtual #158                // Method com/fasterxml/jackson/core/JsonParser.isEnabled:(Lcom/fasterxml/jackson/core/StreamReadFeature;)Z
       8: invokestatic  #177                // Method _parseDouble:(Ljava/lang/String;Z)D
      11: dreturn
      12: astore        4
      14: aload_2
      15: getstatic     #167                // Field java/lang/Double.TYPE:Ljava/lang/Class;
      18: aload_3
      19: ldc           #176                // String not a valid `double` value (as String to convert)
      21: iconst_0
      22: anewarray     #4                  // class java/lang/Object
      25: invokevirtual #88                 // Method com/fasterxml/jackson/databind/DeserializationContext.handleWeirdStringValue:(Ljava/lang/Class;Ljava/lang/String;Ljava/lang/String;[Ljava/lang/Object;)Ljava/lang/Object;
      28: checkcast     #122                // class java/lang/Number
      31: astore        4
      33: aload_0
      34: aload         4
      36: invokevirtual #130                // Method _nonNullNumber:(Ljava/lang/Number;)Ljava/lang/Number;
      39: invokevirtual #172                // Method java/lang/Number.doubleValue:()D
      42: dreturn
    Exception table:
       from    to  target type
           0    11    12   Class java/lang/IllegalArgumentException

  protected static final double _parseDouble(java.lang.String) throws java.lang.NumberFormatException;
    Code:
       0: aload_0
       1: iconst_0
       2: invokestatic  #177                // Method _parseDouble:(Ljava/lang/String;Z)D
       5: dreturn

  protected static final double _parseDouble(java.lang.String, boolean) throws java.lang.NumberFormatException;
    Code:
       0: aload_0
       1: iload_1
       2: invokestatic  #178                // Method com/fasterxml/jackson/core/io/NumberInput.parseDouble:(Ljava/lang/String;Z)D
       5: dreturn

  protected java.lang.Double _checkDoubleSpecialValue(java.lang.String);
    Code:
       0: aload_1
       1: invokevirtual #32                 // Method java/lang/String.isEmpty:()Z
       4: ifne          93
       7: aload_1
       8: iconst_0
       9: invokevirtual #89                 // Method java/lang/String.charAt:(I)C
      12: lookupswitch  { // 3
                    45: 78
                    73: 48
                    78: 63
               default: 93
          }
      48: aload_0
      49: aload_1
      50: invokevirtual #160                // Method _isPosInf:(Ljava/lang/String;)Z
      53: ifeq          93
      56: ldc2_w        #179                // double Infinityd
      59: invokestatic  #181                // Method java/lang/Double.valueOf:(D)Ljava/lang/Double;
      62: areturn
      63: aload_0
      64: aload_1
      65: invokevirtual #163                // Method _isNaN:(Ljava/lang/String;)Z
      68: ifeq          93
      71: ldc2_w        #182                // double NaNd
      74: invokestatic  #181                // Method java/lang/Double.valueOf:(D)Ljava/lang/Double;
      77: areturn
      78: aload_0
      79: aload_1
      80: invokevirtual #165                // Method _isNegInf:(Ljava/lang/String;)Z
      83: ifeq          93
      86: ldc2_w        #184                // double -Infinityd
      89: invokestatic  #181                // Method java/lang/Double.valueOf:(D)Ljava/lang/Double;
      92: areturn
      93: aconst_null
      94: areturn

  protected java.util.Date _parseDate(com.fasterxml.jackson.core.JsonParser, com.fasterxml.jackson.databind.DeserializationContext) throws java.io.IOException;
    Code:
       0: aload_1
       1: invokevirtual #68                 // Method com/fasterxml/jackson/core/JsonParser.currentTokenId:()I
       4: tableswitch   { // 1 to 11
                     1: 132
                     2: 153
                     3: 146
                     4: 153
                     5: 153
                     6: 64
                     7: 72
                     8: 153
                     9: 153
                    10: 153
                    11: 123
               default: 153
          }
      64: aload_1
      65: invokevirtual #69                 // Method com/fasterxml/jackson/core/JsonParser.getText:()Ljava/lang/String;
      68: astore_3
      69: goto          166
      72: aload_1
      73: invokevirtual #138                // Method com/fasterxml/jackson/core/JsonParser.getLongValue:()J
      76: lstore        4
      78: goto          113
      81: astore        6
      83: aload_2
      84: aload_0
      85: getfield      #2                  // Field _valueClass:Ljava/lang/Class;
      88: aload_1
      89: invokevirtual #187                // Method com/fasterxml/jackson/core/JsonParser.getNumberValue:()Ljava/lang/Number;
      92: ldc           #188                // String not a valid 64-bit `long` for creating `java.util.Date`
      94: iconst_0
      95: anewarray     #4                  // class java/lang/Object
      98: invokevirtual #189                // Method com/fasterxml/jackson/databind/DeserializationContext.handleWeirdNumberValue:(Ljava/lang/Class;Ljava/lang/Number;Ljava/lang/String;[Ljava/lang/Object;)Ljava/lang/Object;
     101: checkcast     #122                // class java/lang/Number
     104: astore        7
     106: aload         7
     108: invokevirtual #141                // Method java/lang/Number.longValue:()J
     111: lstore        4
     113: new           #190                // class java/util/Date
     116: dup
     117: lload         4
     119: invokespecial #191                // Method java/util/Date."<init>":(J)V
     122: areturn
     123: aload_0
     124: aload_2
     125: invokevirtual #18                 // Method getNullValue:(Lcom/fasterxml/jackson/databind/DeserializationContext;)Ljava/lang/Object;
     128: checkcast     #190                // class java/util/Date
     131: areturn
     132: aload_2
     133: aload_1
     134: aload_0
     135: aload_0
     136: getfield      #2                  // Field _valueClass:Ljava/lang/Class;
     139: invokevirtual #75                 // Method com/fasterxml/jackson/databind/DeserializationContext.extractScalarFromObject:(Lcom/fasterxml/jackson/core/JsonParser;Lcom/fasterxml/jackson/databind/JsonDeserializer;Ljava/lang/Class;)Ljava/lang/String;
     142: astore_3
     143: goto          166
     146: aload_0
     147: aload_1
     148: aload_2
     149: invokevirtual #192                // Method _parseDateFromArray:(Lcom/fasterxml/jackson/core/JsonParser;Lcom/fasterxml/jackson/databind/DeserializationContext;)Ljava/util/Date;
     152: areturn
     153: aload_2
     154: aload_0
     155: getfield      #2                  // Field _valueClass:Ljava/lang/Class;
     158: aload_1
     159: invokevirtual #78                 // Method com/fasterxml/jackson/databind/DeserializationContext.handleUnexpectedToken:(Ljava/lang/Class;Lcom/fasterxml/jackson/core/JsonParser;)Ljava/lang/Object;
     162: checkcast     #190                // class java/util/Date
     165: areturn
     166: aload_0
     167: aload_3
     168: invokevirtual #41                 // Method java/lang/String.trim:()Ljava/lang/String;
     171: aload_2
     172: invokevirtual #193                // Method _parseDate:(Ljava/lang/String;Lcom/fasterxml/jackson/databind/DeserializationContext;)Ljava/util/Date;
     175: areturn
    Exception table:
       from    to  target type
          72    78    81   Class com/fasterxml/jackson/core/exc/StreamReadException

  protected java.util.Date _parseDateFromArray(com.fasterxml.jackson.core.JsonParser, com.fasterxml.jackson.databind.DeserializationContext) throws java.io.IOException;
    Code:
       0: aload_0
       1: aload_2
       2: invokevirtual #9                  // Method _findCoercionFromEmptyArray:(Lcom/fasterxml/jackson/databind/DeserializationContext;)Lcom/fasterxml/jackson/databind/cfg/CoercionAction;
       5: astore_3
       6: aload_2
       7: getstatic     #10                 // Field com/fasterxml/jackson/databind/DeserializationFeature.UNWRAP_SINGLE_VALUE_ARRAYS:Lcom/fasterxml/jackson/databind/DeserializationFeature;
      10: invokevirtual #11                 // Method com/fasterxml/jackson/databind/DeserializationContext.isEnabled:(Lcom/fasterxml/jackson/databind/DeserializationFeature;)Z
      13: istore        4
      15: iload         4
      17: ifne          27
      20: aload_3
      21: getstatic     #12                 // Field com/fasterxml/jackson/databind/cfg/CoercionAction.Fail:Lcom/fasterxml/jackson/databind/cfg/CoercionAction;
      24: if_acmpeq     137
      27: aload_1
      28: invokevirtual #13                 // Method com/fasterxml/jackson/core/JsonParser.nextToken:()Lcom/fasterxml/jackson/core/JsonToken;
      31: astore        5
      33: aload         5
      35: getstatic     #14                 // Field com/fasterxml/jackson/core/JsonToken.END_ARRAY:Lcom/fasterxml/jackson/core/JsonToken;
      38: if_acmpne     97
      41: getstatic     #15                 // Field com/fasterxml/jackson/databind/deser/std/StdDeserializer$1.$SwitchMap$com$fasterxml$jackson$databind$cfg$CoercionAction:[I
      44: aload_3
      45: invokevirtual #16                 // Method com/fasterxml/jackson/databind/cfg/CoercionAction.ordinal:()I
      48: iaload
      49: tableswitch   { // 1 to 3
                     1: 76
                     2: 85
                     3: 85
               default: 94
          }
      76: aload_0
      77: aload_2
      78: invokevirtual #17                 // Method getEmptyValue:(Lcom/fasterxml/jackson/databind/DeserializationContext;)Ljava/lang/Object;
      81: checkcast     #190                // class java/util/Date
      84: areturn
      85: aload_0
      86: aload_2
      87: invokevirtual #18                 // Method getNullValue:(Lcom/fasterxml/jackson/databind/DeserializationContext;)Ljava/lang/Object;
      90: checkcast     #190                // class java/util/Date
      93: areturn
      94: goto          137
      97: iload         4
      99: ifeq          137
     102: aload         5
     104: getstatic     #22                 // Field com/fasterxml/jackson/core/JsonToken.START_ARRAY:Lcom/fasterxml/jackson/core/JsonToken;
     107: if_acmpne     120
     110: aload_0
     111: aload_1
     112: aload_2
     113: invokevirtual #65                 // Method handleNestedArrayForSingle:(Lcom/fasterxml/jackson/core/JsonParser;Lcom/fasterxml/jackson/databind/DeserializationContext;)Ljava/lang/Object;
     116: checkcast     #190                // class java/util/Date
     119: areturn
     120: aload_0
     121: aload_1
     122: aload_2
     123: invokevirtual #194                // Method _parseDate:(Lcom/fasterxml/jackson/core/JsonParser;Lcom/fasterxml/jackson/databind/DeserializationContext;)Ljava/util/Date;
     126: astore        6
     128: aload_0
     129: aload_1
     130: aload_2
     131: invokevirtual #77                 // Method _verifyEndArrayForSingle:(Lcom/fasterxml/jackson/core/JsonParser;Lcom/fasterxml/jackson/databind/DeserializationContext;)V
     134: aload         6
     136: areturn
     137: aload_2
     138: aload_0
     139: getfield      #2                  // Field _valueClass:Ljava/lang/Class;
     142: getstatic     #22                 // Field com/fasterxml/jackson/core/JsonToken.START_ARRAY:Lcom/fasterxml/jackson/core/JsonToken;
     145: aload_1
     146: aconst_null
     147: iconst_0
     148: anewarray     #4                  // class java/lang/Object
     151: invokevirtual #195                // Method com/fasterxml/jackson/databind/DeserializationContext.handleUnexpectedToken:(Ljava/lang/Class;Lcom/fasterxml/jackson/core/JsonToken;Lcom/fasterxml/jackson/core/JsonParser;Ljava/lang/String;[Ljava/lang/Object;)Ljava/lang/Object;
     154: checkcast     #190                // class java/util/Date
     157: areturn

  protected java.util.Date _parseDate(java.lang.String, com.fasterxml.jackson.databind.DeserializationContext) throws java.io.IOException;
    Code:
       0: aload_1
       1: invokevirtual #32                 // Method java/lang/String.isEmpty:()Z
       4: ifeq          59
       7: aload_0
       8: aload_2
       9: aload_1
      10: invokevirtual #132                // Method _checkFromStringCoercion:(Lcom/fasterxml/jackson/databind/DeserializationContext;Ljava/lang/String;)Lcom/fasterxml/jackson/databind/cfg/CoercionAction;
      13: astore_3
      14: getstatic     #15                 // Field com/fasterxml/jackson/databind/deser/std/StdDeserializer$1.$SwitchMap$com$fasterxml$jackson$databind$cfg$CoercionAction:[I
      17: aload_3
      18: invokevirtual #16                 // Method com/fasterxml/jackson/databind/cfg/CoercionAction.ordinal:()I
      21: iaload
      22: tableswitch   { // 1 to 3
                     1: 48
                     2: 57
                     3: 57
               default: 57
          }
      48: new           #190                // class java/util/Date
      51: dup
      52: lconst_0
      53: invokespecial #191                // Method java/util/Date."<init>":(J)V
      56: areturn
      57: aconst_null
      58: areturn
      59: aload_0
      60: aload_1
      61: invokevirtual #85                 // Method _hasTextualNull:(Ljava/lang/String;)Z
      64: ifeq          69
      67: aconst_null
      68: areturn
      69: aload_2
      70: aload_1
      71: invokevirtual #196                // Method com/fasterxml/jackson/databind/DeserializationContext.parseDate:(Ljava/lang/String;)Ljava/util/Date;
      74: areturn
      75: astore_3
      76: aload_2
      77: aload_0
      78: getfield      #2                  // Field _valueClass:Ljava/lang/Class;
      81: aload_1
      82: ldc           #197                // String not a valid representation (error: %s)
      84: iconst_1
      85: anewarray     #4                  // class java/lang/Object
      88: dup
      89: iconst_0
      90: aload_3
      91: invokestatic  #198                // Method com/fasterxml/jackson/databind/util/ClassUtil.exceptionMessage:(Ljava/lang/Throwable;)Ljava/lang/String;
      94: aastore
      95: invokevirtual #88                 // Method com/fasterxml/jackson/databind/DeserializationContext.handleWeirdStringValue:(Ljava/lang/Class;Ljava/lang/String;Ljava/lang/String;[Ljava/lang/Object;)Ljava/lang/Object;
      98: checkcast     #190                // class java/util/Date
     101: areturn
    Exception table:
       from    to  target type
           0    56    75   Class java/lang/IllegalArgumentException
          57    58    75   Class java/lang/IllegalArgumentException
          59    68    75   Class java/lang/IllegalArgumentException
          69    74    75   Class java/lang/IllegalArgumentException

  protected final java.lang.String _parseString(com.fasterxml.jackson.core.JsonParser, com.fasterxml.jackson.databind.DeserializationContext) throws java.io.IOException;
    Code:
       0: aload_0
       1: aload_1
       2: aload_2
       3: invokestatic  #199                // Method com/fasterxml/jackson/databind/deser/impl/NullsConstantProvider.nuller:()Lcom/fasterxml/jackson/databind/deser/impl/NullsConstantProvider;
       6: invokevirtual #200                // Method _parseString:(Lcom/fasterxml/jackson/core/JsonParser;Lcom/fasterxml/jackson/databind/DeserializationContext;Lcom/fasterxml/jackson/databind/deser/NullValueProvider;)Ljava/lang/String;
       9: areturn

  protected final java.lang.String _parseString(com.fasterxml.jackson.core.JsonParser, com.fasterxml.jackson.databind.DeserializationContext, com.fasterxml.jackson.databind.deser.NullValueProvider) throws java.io.IOException;
    Code:
       0: getstatic     #46                 // Field com/fasterxml/jackson/databind/cfg/CoercionAction.TryConvert:Lcom/fasterxml/jackson/databind/cfg/CoercionAction;
       3: astore        4
       5: aload_1
       6: invokevirtual #68                 // Method com/fasterxml/jackson/core/JsonParser.currentTokenId:()I
       9: tableswitch   { // 1 to 12
                     1: 121
                     2: 174
                     3: 174
                     4: 174
                     5: 174
                     6: 72
                     7: 132
                     8: 147
                     9: 162
                    10: 162
                    11: 174
                    12: 77
               default: 174
          }
      72: aload_1
      73: invokevirtual #69                 // Method com/fasterxml/jackson/core/JsonParser.getText:()Ljava/lang/String;
      76: areturn
      77: aload_1
      78: invokevirtual #201                // Method com/fasterxml/jackson/core/JsonParser.getEmbeddedObject:()Ljava/lang/Object;
      81: astore        5
      83: aload         5
      85: instanceof    #202                // class "[B"
      88: ifeq          108
      91: aload_2
      92: invokevirtual #203                // Method com/fasterxml/jackson/databind/DeserializationContext.getBase64Variant:()Lcom/fasterxml/jackson/core/Base64Variant;
      95: aload         5
      97: checkcast     #202                // class "[B"
     100: checkcast     #202                // class "[B"
     103: iconst_0
     104: invokevirtual #204                // Method com/fasterxml/jackson/core/Base64Variant.encode:([BZ)Ljava/lang/String;
     107: areturn
     108: aload         5
     110: ifnonnull     115
     113: aconst_null
     114: areturn
     115: aload         5
     117: invokevirtual #205                // Method java/lang/Object.toString:()Ljava/lang/String;
     120: areturn
     121: aload_2
     122: aload_1
     123: aload_0
     124: aload_0
     125: getfield      #2                  // Field _valueClass:Ljava/lang/Class;
     128: invokevirtual #75                 // Method com/fasterxml/jackson/databind/DeserializationContext.extractScalarFromObject:(Lcom/fasterxml/jackson/core/JsonParser;Lcom/fasterxml/jackson/databind/JsonDeserializer;Ljava/lang/Class;)Ljava/lang/String;
     131: areturn
     132: aload_0
     133: aload_1
     134: aload_2
     135: aload_0
     136: getfield      #2                  // Field _valueClass:Ljava/lang/Class;
     139: invokevirtual #206                // Method _checkIntToStringCoercion:(Lcom/fasterxml/jackson/core/JsonParser;Lcom/fasterxml/jackson/databind/DeserializationContext;Ljava/lang/Class;)Lcom/fasterxml/jackson/databind/cfg/CoercionAction;
     142: astore        4
     144: goto          174
     147: aload_0
     148: aload_1
     149: aload_2
     150: aload_0
     151: getfield      #2                  // Field _valueClass:Ljava/lang/Class;
     154: invokevirtual #207                // Method _checkFloatToStringCoercion:(Lcom/fasterxml/jackson/core/JsonParser;Lcom/fasterxml/jackson/databind/DeserializationContext;Ljava/lang/Class;)Lcom/fasterxml/jackson/databind/cfg/CoercionAction;
     157: astore        4
     159: goto          174
     162: aload_0
     163: aload_1
     164: aload_2
     165: aload_0
     166: getfield      #2                  // Field _valueClass:Ljava/lang/Class;
     169: invokevirtual #208                // Method _checkBooleanToStringCoercion:(Lcom/fasterxml/jackson/core/JsonParser;Lcom/fasterxml/jackson/databind/DeserializationContext;Ljava/lang/Class;)Lcom/fasterxml/jackson/databind/cfg/CoercionAction;
     172: astore        4
     174: aload         4
     176: getstatic     #80                 // Field com/fasterxml/jackson/databind/cfg/CoercionAction.AsNull:Lcom/fasterxml/jackson/databind/cfg/CoercionAction;
     179: if_acmpne     193
     182: aload_3
     183: aload_2
     184: invokeinterface #209,  2          // InterfaceMethod com/fasterxml/jackson/databind/deser/NullValueProvider.getNullValue:(Lcom/fasterxml/jackson/databind/DeserializationContext;)Ljava/lang/Object;
     189: checkcast     #210                // class java/lang/String
     192: areturn
     193: aload         4
     195: getstatic     #81                 // Field com/fasterxml/jackson/databind/cfg/CoercionAction.AsEmpty:Lcom/fasterxml/jackson/databind/cfg/CoercionAction;
     198: if_acmpne     204
     201: ldc           #63                 // String
     203: areturn
     204: aload_1
     205: invokevirtual #211                // Method com/fasterxml/jackson/core/JsonParser.currentToken:()Lcom/fasterxml/jackson/core/JsonToken;
     208: invokevirtual #212                // Method com/fasterxml/jackson/core/JsonToken.isScalarValue:()Z
     211: ifeq          228
     214: aload_1
     215: invokevirtual #29                 // Method com/fasterxml/jackson/core/JsonParser.getValueAsString:()Ljava/lang/String;
     218: astore        5
     220: aload         5
     222: ifnull        228
     225: aload         5
     227: areturn
     228: aload_2
     229: aload_0
     230: aload_2
     231: invokevirtual #21                 // Method getValueType:(Lcom/fasterxml/jackson/databind/DeserializationContext;)Lcom/fasterxml/jackson/databind/JavaType;
     234: aload_1
     235: invokevirtual #26                 // Method com/fasterxml/jackson/databind/DeserializationContext.handleUnexpectedToken:(Lcom/fasterxml/jackson/databind/JavaType;Lcom/fasterxml/jackson/core/JsonParser;)Ljava/lang/Object;
     238: checkcast     #210                // class java/lang/String
     241: areturn

  protected boolean _hasTextualNull(java.lang.String);
    Code:
       0: ldc           #213                // String null
       2: aload_1
       3: invokevirtual #57                 // Method java/lang/String.equals:(Ljava/lang/Object;)Z
       6: ireturn

  protected final boolean _isNegInf(java.lang.String);
    Code:
       0: ldc           #214                // String -Infinity
       2: aload_1
       3: invokevirtual #57                 // Method java/lang/String.equals:(Ljava/lang/Object;)Z
       6: ifne          18
       9: ldc           #215                // String -INF
      11: aload_1
      12: invokevirtual #57                 // Method java/lang/String.equals:(Ljava/lang/Object;)Z
      15: ifeq          22
      18: iconst_1
      19: goto          23
      22: iconst_0
      23: ireturn

  protected final boolean _isPosInf(java.lang.String);
    Code:
       0: ldc           #216                // String Infinity
       2: aload_1
       3: invokevirtual #57                 // Method java/lang/String.equals:(Ljava/lang/Object;)Z
       6: ifne          18
       9: ldc           #217                // String INF
      11: aload_1
      12: invokevirtual #57                 // Method java/lang/String.equals:(Ljava/lang/Object;)Z
      15: ifeq          22
      18: iconst_1
      19: goto          23
      22: iconst_0
      23: ireturn

  protected final boolean _isNaN(java.lang.String);
    Code:
       0: ldc           #218                // String NaN
       2: aload_1
       3: invokevirtual #57                 // Method java/lang/String.equals:(Ljava/lang/Object;)Z
       6: ireturn

  protected static final boolean _isBlank(java.lang.String);
    Code:
       0: aload_0
       1: invokevirtual #82                 // Method java/lang/String.length:()I
       4: istore_1
       5: iconst_0
       6: istore_2
       7: iload_2
       8: iload_1
       9: if_icmpge     30
      12: aload_0
      13: iload_2
      14: invokevirtual #89                 // Method java/lang/String.charAt:(I)C
      17: bipush        32
      19: if_icmple     24
      22: iconst_0
      23: ireturn
      24: iinc          2, 1
      27: goto          7
      30: iconst_1
      31: ireturn

  protected com.fasterxml.jackson.databind.cfg.CoercionAction _checkFromStringCoercion(com.fasterxml.jackson.databind.DeserializationContext, java.lang.String) throws java.io.IOException;
    Code:
       0: aload_0
       1: aload_1
       2: aload_2
       3: aload_0
       4: invokevirtual #33                 // Method logicalType:()Lcom/fasterxml/jackson/databind/type/LogicalType;
       7: aload_0
       8: invokevirtual #28                 // Method handledType:()Ljava/lang/Class;
      11: invokevirtual #79                 // Method _checkFromStringCoercion:(Lcom/fasterxml/jackson/databind/DeserializationContext;Ljava/lang/String;Lcom/fasterxml/jackson/databind/type/LogicalType;Ljava/lang/Class;)Lcom/fasterxml/jackson/databind/cfg/CoercionAction;
      14: areturn

  protected com.fasterxml.jackson.databind.cfg.CoercionAction _checkFromStringCoercion(com.fasterxml.jackson.databind.DeserializationContext, java.lang.String, com.fasterxml.jackson.databind.type.LogicalType, java.lang.Class<?>) throws java.io.IOException;
    Code:
       0: aload_2
       1: invokevirtual #32                 // Method java/lang/String.isEmpty:()Z
       4: ifeq          32
       7: aload_1
       8: aload_3
       9: aload         4
      11: getstatic     #34                 // Field com/fasterxml/jackson/databind/cfg/CoercionInputShape.EmptyString:Lcom/fasterxml/jackson/databind/cfg/CoercionInputShape;
      14: invokevirtual #35                 // Method com/fasterxml/jackson/databind/DeserializationContext.findCoercionAction:(Lcom/fasterxml/jackson/databind/type/LogicalType;Ljava/lang/Class;Lcom/fasterxml/jackson/databind/cfg/CoercionInputShape;)Lcom/fasterxml/jackson/databind/cfg/CoercionAction;
      17: astore        5
      19: aload_0
      20: aload_1
      21: aload         5
      23: aload         4
      25: aload_2
      26: ldc           #36                 // String empty String (\"\")
      28: invokevirtual #64                 // Method _checkCoercionFail:(Lcom/fasterxml/jackson/databind/DeserializationContext;Lcom/fasterxml/jackson/databind/cfg/CoercionAction;Ljava/lang/Class;Ljava/lang/Object;Ljava/lang/String;)Lcom/fasterxml/jackson/databind/cfg/CoercionAction;
      31: areturn
      32: aload_2
      33: invokestatic  #38                 // Method _isBlank:(Ljava/lang/String;)Z
      36: ifeq          64
      39: aload_1
      40: aload_3
      41: aload         4
      43: getstatic     #12                 // Field com/fasterxml/jackson/databind/cfg/CoercionAction.Fail:Lcom/fasterxml/jackson/databind/cfg/CoercionAction;
      46: invokevirtual #39                 // Method com/fasterxml/jackson/databind/DeserializationContext.findCoercionFromBlankString:(Lcom/fasterxml/jackson/databind/type/LogicalType;Ljava/lang/Class;Lcom/fasterxml/jackson/databind/cfg/CoercionAction;)Lcom/fasterxml/jackson/databind/cfg/CoercionAction;
      49: astore        5
      51: aload_0
      52: aload_1
      53: aload         5
      55: aload         4
      57: aload_2
      58: ldc           #40                 // String blank String (all whitespace)
      60: invokevirtual #64                 // Method _checkCoercionFail:(Lcom/fasterxml/jackson/databind/DeserializationContext;Lcom/fasterxml/jackson/databind/cfg/CoercionAction;Ljava/lang/Class;Ljava/lang/Object;Ljava/lang/String;)Lcom/fasterxml/jackson/databind/cfg/CoercionAction;
      63: areturn
      64: aload_1
      65: getstatic     #219                // Field com/fasterxml/jackson/core/StreamReadCapability.UNTYPED_SCALARS:Lcom/fasterxml/jackson/core/StreamReadCapability;
      68: invokevirtual #220                // Method com/fasterxml/jackson/databind/DeserializationContext.isEnabled:(Lcom/fasterxml/jackson/core/StreamReadCapability;)Z
      71: ifeq          78
      74: getstatic     #46                 // Field com/fasterxml/jackson/databind/cfg/CoercionAction.TryConvert:Lcom/fasterxml/jackson/databind/cfg/CoercionAction;
      77: areturn
      78: aload_1
      79: aload_3
      80: aload         4
      82: getstatic     #45                 // Field com/fasterxml/jackson/databind/cfg/CoercionInputShape.String:Lcom/fasterxml/jackson/databind/cfg/CoercionInputShape;
      85: invokevirtual #35                 // Method com/fasterxml/jackson/databind/DeserializationContext.findCoercionAction:(Lcom/fasterxml/jackson/databind/type/LogicalType;Ljava/lang/Class;Lcom/fasterxml/jackson/databind/cfg/CoercionInputShape;)Lcom/fasterxml/jackson/databind/cfg/CoercionAction;
      88: astore        5
      90: aload         5
      92: getstatic     #12                 // Field com/fasterxml/jackson/databind/cfg/CoercionAction.Fail:Lcom/fasterxml/jackson/databind/cfg/CoercionAction;
      95: if_acmpne     121
      98: aload_1
      99: aload_0
     100: ldc           #221                // String Cannot coerce String value (\"%s\") to %s (but might if coercion using `CoercionConfig` was enabled)
     102: iconst_2
     103: anewarray     #4                  // class java/lang/Object
     106: dup
     107: iconst_0
     108: aload_2
     109: aastore
     110: dup
     111: iconst_1
     112: aload_0
     113: invokevirtual #222                // Method _coercedTypeDesc:()Ljava/lang/String;
     116: aastore
     117: invokevirtual #223                // Method com/fasterxml/jackson/databind/DeserializationContext.reportInputMismatch:(Lcom/fasterxml/jackson/databind/JsonDeserializer;Ljava/lang/String;[Ljava/lang/Object;)Ljava/lang/Object;
     120: pop
     121: aload         5
     123: areturn

  protected com.fasterxml.jackson.databind.cfg.CoercionAction _checkFloatToIntCoercion(com.fasterxml.jackson.core.JsonParser, com.fasterxml.jackson.databind.DeserializationContext, java.lang.Class<?>) throws java.io.IOException;
    Code:
       0: aload_2
       1: getstatic     #43                 // Field com/fasterxml/jackson/databind/type/LogicalType.Integer:Lcom/fasterxml/jackson/databind/type/LogicalType;
       4: aload_3
       5: getstatic     #224                // Field com/fasterxml/jackson/databind/cfg/CoercionInputShape.Float:Lcom/fasterxml/jackson/databind/cfg/CoercionInputShape;
       8: invokevirtual #35                 // Method com/fasterxml/jackson/databind/DeserializationContext.findCoercionAction:(Lcom/fasterxml/jackson/databind/type/LogicalType;Ljava/lang/Class;Lcom/fasterxml/jackson/databind/cfg/CoercionInputShape;)Lcom/fasterxml/jackson/databind/cfg/CoercionAction;
      11: astore        4
      13: aload         4
      15: getstatic     #12                 // Field com/fasterxml/jackson/databind/cfg/CoercionAction.Fail:Lcom/fasterxml/jackson/databind/cfg/CoercionAction;
      18: if_acmpne     61
      21: aload_0
      22: aload_2
      23: aload         4
      25: aload_3
      26: aload_1
      27: invokevirtual #187                // Method com/fasterxml/jackson/core/JsonParser.getNumberValue:()Ljava/lang/Number;
      30: new           #225                // class java/lang/StringBuilder
      33: dup
      34: invokespecial #226                // Method java/lang/StringBuilder."<init>":()V
      37: ldc           #227                // String Floating-point value (
      39: invokevirtual #228                // Method java/lang/StringBuilder.append:(Ljava/lang/String;)Ljava/lang/StringBuilder;
      42: aload_1
      43: invokevirtual #69                 // Method com/fasterxml/jackson/core/JsonParser.getText:()Ljava/lang/String;
      46: invokevirtual #228                // Method java/lang/StringBuilder.append:(Ljava/lang/String;)Ljava/lang/StringBuilder;
      49: ldc           #229                // String )
      51: invokevirtual #228                // Method java/lang/StringBuilder.append:(Ljava/lang/String;)Ljava/lang/StringBuilder;
      54: invokevirtual #230                // Method java/lang/StringBuilder.toString:()Ljava/lang/String;
      57: invokevirtual #64                 // Method _checkCoercionFail:(Lcom/fasterxml/jackson/databind/DeserializationContext;Lcom/fasterxml/jackson/databind/cfg/CoercionAction;Ljava/lang/Class;Ljava/lang/Object;Ljava/lang/String;)Lcom/fasterxml/jackson/databind/cfg/CoercionAction;
      60: areturn
      61: aload         4
      63: areturn

  protected com.fasterxml.jackson.databind.cfg.CoercionAction _checkIntToStringCoercion(com.fasterxml.jackson.core.JsonParser, com.fasterxml.jackson.databind.DeserializationContext, java.lang.Class<?>) throws java.io.IOException;
    Code:
       0: aload_0
       1: aload_1
       2: aload_2
       3: aload_3
       4: aload_1
       5: invokevirtual #187                // Method com/fasterxml/jackson/core/JsonParser.getNumberValue:()Ljava/lang/Number;
       8: getstatic     #231                // Field com/fasterxml/jackson/databind/cfg/CoercionInputShape.Integer:Lcom/fasterxml/jackson/databind/cfg/CoercionInputShape;
      11: invokevirtual #232                // Method _checkToStringCoercion:(Lcom/fasterxml/jackson/core/JsonParser;Lcom/fasterxml/jackson/databind/DeserializationContext;Ljava/lang/Class;Ljava/lang/Object;Lcom/fasterxml/jackson/databind/cfg/CoercionInputShape;)Lcom/fasterxml/jackson/databind/cfg/CoercionAction;
      14: areturn

  protected com.fasterxml.jackson.databind.cfg.CoercionAction _checkFloatToStringCoercion(com.fasterxml.jackson.core.JsonParser, com.fasterxml.jackson.databind.DeserializationContext, java.lang.Class<?>) throws java.io.IOException;
    Code:
       0: aload_0
       1: aload_1
       2: aload_2
       3: aload_3
       4: aload_1
       5: invokevirtual #187                // Method com/fasterxml/jackson/core/JsonParser.getNumberValue:()Ljava/lang/Number;
       8: getstatic     #224                // Field com/fasterxml/jackson/databind/cfg/CoercionInputShape.Float:Lcom/fasterxml/jackson/databind/cfg/CoercionInputShape;
      11: invokevirtual #232                // Method _checkToStringCoercion:(Lcom/fasterxml/jackson/core/JsonParser;Lcom/fasterxml/jackson/databind/DeserializationContext;Ljava/lang/Class;Ljava/lang/Object;Lcom/fasterxml/jackson/databind/cfg/CoercionInputShape;)Lcom/fasterxml/jackson/databind/cfg/CoercionAction;
      14: areturn

  protected com.fasterxml.jackson.databind.cfg.CoercionAction _checkBooleanToStringCoercion(com.fasterxml.jackson.core.JsonParser, com.fasterxml.jackson.databind.DeserializationContext, java.lang.Class<?>) throws java.io.IOException;
    Code:
       0: aload_0
       1: aload_1
       2: aload_2
       3: aload_3
       4: aload_1
       5: invokevirtual #233                // Method com/fasterxml/jackson/core/JsonParser.getBooleanValue:()Z
       8: invokestatic  #94                 // Method java/lang/Boolean.valueOf:(Z)Ljava/lang/Boolean;
      11: getstatic     #234                // Field com/fasterxml/jackson/databind/cfg/CoercionInputShape.Boolean:Lcom/fasterxml/jackson/databind/cfg/CoercionInputShape;
      14: invokevirtual #232                // Method _checkToStringCoercion:(Lcom/fasterxml/jackson/core/JsonParser;Lcom/fasterxml/jackson/databind/DeserializationContext;Ljava/lang/Class;Ljava/lang/Object;Lcom/fasterxml/jackson/databind/cfg/CoercionInputShape;)Lcom/fasterxml/jackson/databind/cfg/CoercionAction;
      17: areturn

  protected com.fasterxml.jackson.databind.cfg.CoercionAction _checkToStringCoercion(com.fasterxml.jackson.core.JsonParser, com.fasterxml.jackson.databind.DeserializationContext, java.lang.Class<?>, java.lang.Object, com.fasterxml.jackson.databind.cfg.CoercionInputShape) throws java.io.IOException;
    Code:
       0: aload_2
       1: getstatic     #235                // Field com/fasterxml/jackson/databind/type/LogicalType.Textual:Lcom/fasterxml/jackson/databind/type/LogicalType;
       4: aload_3
       5: aload         5
       7: invokevirtual #35                 // Method com/fasterxml/jackson/databind/DeserializationContext.findCoercionAction:(Lcom/fasterxml/jackson/databind/type/LogicalType;Ljava/lang/Class;Lcom/fasterxml/jackson/databind/cfg/CoercionInputShape;)Lcom/fasterxml/jackson/databind/cfg/CoercionAction;
      10: astore        6
      12: aload         6
      14: getstatic     #12                 // Field com/fasterxml/jackson/databind/cfg/CoercionAction.Fail:Lcom/fasterxml/jackson/databind/cfg/CoercionAction;
      17: if_acmpne     66
      20: aload_0
      21: aload_2
      22: aload         6
      24: aload_3
      25: aload         4
      27: new           #225                // class java/lang/StringBuilder
      30: dup
      31: invokespecial #226                // Method java/lang/StringBuilder."<init>":()V
      34: aload         5
      36: invokevirtual #236                // Method com/fasterxml/jackson/databind/cfg/CoercionInputShape.name:()Ljava/lang/String;
      39: invokevirtual #228                // Method java/lang/StringBuilder.append:(Ljava/lang/String;)Ljava/lang/StringBuilder;
      42: ldc           #237                // String  value (
      44: invokevirtual #228                // Method java/lang/StringBuilder.append:(Ljava/lang/String;)Ljava/lang/StringBuilder;
      47: aload_1
      48: invokevirtual #69                 // Method com/fasterxml/jackson/core/JsonParser.getText:()Ljava/lang/String;
      51: invokevirtual #228                // Method java/lang/StringBuilder.append:(Ljava/lang/String;)Ljava/lang/StringBuilder;
      54: ldc           #229                // String )
      56: invokevirtual #228                // Method java/lang/StringBuilder.append:(Ljava/lang/String;)Ljava/lang/StringBuilder;
      59: invokevirtual #230                // Method java/lang/StringBuilder.toString:()Ljava/lang/String;
      62: invokevirtual #64                 // Method _checkCoercionFail:(Lcom/fasterxml/jackson/databind/DeserializationContext;Lcom/fasterxml/jackson/databind/cfg/CoercionAction;Ljava/lang/Class;Ljava/lang/Object;Ljava/lang/String;)Lcom/fasterxml/jackson/databind/cfg/CoercionAction;
      65: areturn
      66: aload         6
      68: areturn

  protected com.fasterxml.jackson.databind.cfg.CoercionAction _checkIntToFloatCoercion(com.fasterxml.jackson.core.JsonParser, com.fasterxml.jackson.databind.DeserializationContext, java.lang.Class<?>) throws java.io.IOException;
    Code:
       0: aload_2
       1: getstatic     #238                // Field com/fasterxml/jackson/databind/type/LogicalType.Float:Lcom/fasterxml/jackson/databind/type/LogicalType;
       4: aload_3
       5: getstatic     #231                // Field com/fasterxml/jackson/databind/cfg/CoercionInputShape.Integer:Lcom/fasterxml/jackson/databind/cfg/CoercionInputShape;
       8: invokevirtual #35                 // Method com/fasterxml/jackson/databind/DeserializationContext.findCoercionAction:(Lcom/fasterxml/jackson/databind/type/LogicalType;Ljava/lang/Class;Lcom/fasterxml/jackson/databind/cfg/CoercionInputShape;)Lcom/fasterxml/jackson/databind/cfg/CoercionAction;
      11: astore        4
      13: aload         4
      15: getstatic     #12                 // Field com/fasterxml/jackson/databind/cfg/CoercionAction.Fail:Lcom/fasterxml/jackson/databind/cfg/CoercionAction;
      18: if_acmpne     61
      21: aload_0
      22: aload_2
      23: aload         4
      25: aload_3
      26: aload_1
      27: invokevirtual #187                // Method com/fasterxml/jackson/core/JsonParser.getNumberValue:()Ljava/lang/Number;
      30: new           #225                // class java/lang/StringBuilder
      33: dup
      34: invokespecial #226                // Method java/lang/StringBuilder."<init>":()V
      37: ldc           #239                // String Integer value (
      39: invokevirtual #228                // Method java/lang/StringBuilder.append:(Ljava/lang/String;)Ljava/lang/StringBuilder;
      42: aload_1
      43: invokevirtual #69                 // Method com/fasterxml/jackson/core/JsonParser.getText:()Ljava/lang/String;
      46: invokevirtual #228                // Method java/lang/StringBuilder.append:(Ljava/lang/String;)Ljava/lang/StringBuilder;
      49: ldc           #229                // String )
      51: invokevirtual #228                // Method java/lang/StringBuilder.append:(Ljava/lang/String;)Ljava/lang/StringBuilder;
      54: invokevirtual #230                // Method java/lang/StringBuilder.toString:()Ljava/lang/String;
      57: invokevirtual #64                 // Method _checkCoercionFail:(Lcom/fasterxml/jackson/databind/DeserializationContext;Lcom/fasterxml/jackson/databind/cfg/CoercionAction;Ljava/lang/Class;Ljava/lang/Object;Ljava/lang/String;)Lcom/fasterxml/jackson/databind/cfg/CoercionAction;
      60: areturn
      61: aload         4
      63: areturn

  protected java.lang.Boolean _coerceBooleanFromInt(com.fasterxml.jackson.core.JsonParser, com.fasterxml.jackson.databind.DeserializationContext, java.lang.Class<?>) throws java.io.IOException;
    Code:
       0: aload_2
       1: getstatic     #54                 // Field com/fasterxml/jackson/databind/type/LogicalType.Boolean:Lcom/fasterxml/jackson/databind/type/LogicalType;
       4: aload_3
       5: getstatic     #231                // Field com/fasterxml/jackson/databind/cfg/CoercionInputShape.Integer:Lcom/fasterxml/jackson/databind/cfg/CoercionInputShape;
       8: invokevirtual #35                 // Method com/fasterxml/jackson/databind/DeserializationContext.findCoercionAction:(Lcom/fasterxml/jackson/databind/type/LogicalType;Ljava/lang/Class;Lcom/fasterxml/jackson/databind/cfg/CoercionInputShape;)Lcom/fasterxml/jackson/databind/cfg/CoercionAction;
      11: astore        4
      13: getstatic     #15                 // Field com/fasterxml/jackson/databind/deser/std/StdDeserializer$1.$SwitchMap$com$fasterxml$jackson$databind$cfg$CoercionAction:[I
      16: aload         4
      18: invokevirtual #16                 // Method com/fasterxml/jackson/databind/cfg/CoercionAction.ordinal:()I
      21: iaload
      22: tableswitch   { // 1 to 4
                     1: 98
                     2: 96
                     3: 102
                     4: 52
               default: 102
          }
      52: aload_0
      53: aload_2
      54: aload         4
      56: aload_3
      57: aload_1
      58: invokevirtual #187                // Method com/fasterxml/jackson/core/JsonParser.getNumberValue:()Ljava/lang/Number;
      61: new           #225                // class java/lang/StringBuilder
      64: dup
      65: invokespecial #226                // Method java/lang/StringBuilder."<init>":()V
      68: ldc           #239                // String Integer value (
      70: invokevirtual #228                // Method java/lang/StringBuilder.append:(Ljava/lang/String;)Ljava/lang/StringBuilder;
      73: aload_1
      74: invokevirtual #69                 // Method com/fasterxml/jackson/core/JsonParser.getText:()Ljava/lang/String;
      77: invokevirtual #228                // Method java/lang/StringBuilder.append:(Ljava/lang/String;)Ljava/lang/StringBuilder;
      80: ldc           #229                // String )
      82: invokevirtual #228                // Method java/lang/StringBuilder.append:(Ljava/lang/String;)Ljava/lang/StringBuilder;
      85: invokevirtual #230                // Method java/lang/StringBuilder.toString:()Ljava/lang/String;
      88: invokevirtual #64                 // Method _checkCoercionFail:(Lcom/fasterxml/jackson/databind/DeserializationContext;Lcom/fasterxml/jackson/databind/cfg/CoercionAction;Ljava/lang/Class;Ljava/lang/Object;Ljava/lang/String;)Lcom/fasterxml/jackson/databind/cfg/CoercionAction;
      91: pop
      92: getstatic     #240                // Field java/lang/Boolean.FALSE:Ljava/lang/Boolean;
      95: areturn
      96: aconst_null
      97: areturn
      98: getstatic     #240                // Field java/lang/Boolean.FALSE:Ljava/lang/Boolean;
     101: areturn
     102: aload_1
     103: invokevirtual #241                // Method com/fasterxml/jackson/core/JsonParser.getNumberType:()Lcom/fasterxml/jackson/core/JsonParser$NumberType;
     106: getstatic     #242                // Field com/fasterxml/jackson/core/JsonParser$NumberType.INT:Lcom/fasterxml/jackson/core/JsonParser$NumberType;
     109: if_acmpne     128
     112: aload_1
     113: invokevirtual #119                // Method com/fasterxml/jackson/core/JsonParser.getIntValue:()I
     116: ifeq          123
     119: iconst_1
     120: goto          124
     123: iconst_0
     124: invokestatic  #94                 // Method java/lang/Boolean.valueOf:(Z)Ljava/lang/Boolean;
     127: areturn
     128: ldc           #243                // String 0
     130: aload_1
     131: invokevirtual #69                 // Method com/fasterxml/jackson/core/JsonParser.getText:()Ljava/lang/String;
     134: invokevirtual #57                 // Method java/lang/String.equals:(Ljava/lang/Object;)Z
     137: ifne          144
     140: iconst_1
     141: goto          145
     144: iconst_0
     145: invokestatic  #94                 // Method java/lang/Boolean.valueOf:(Z)Ljava/lang/Boolean;
     148: areturn

  protected com.fasterxml.jackson.databind.cfg.CoercionAction _checkCoercionFail(com.fasterxml.jackson.databind.DeserializationContext, com.fasterxml.jackson.databind.cfg.CoercionAction, java.lang.Class<?>, java.lang.Object, java.lang.String) throws java.io.IOException;
    Code:
       0: aload_2
       1: getstatic     #12                 // Field com/fasterxml/jackson/databind/cfg/CoercionAction.Fail:Lcom/fasterxml/jackson/databind/cfg/CoercionAction;
       4: if_acmpne     34
       7: aload_1
       8: aload_0
       9: aload_3
      10: aload         4
      12: ldc           #244                // String Cannot coerce %s to %s (but could if coercion was enabled using `CoercionConfig`)
      14: iconst_2
      15: anewarray     #4                  // class java/lang/Object
      18: dup
      19: iconst_0
      20: aload         5
      22: aastore
      23: dup
      24: iconst_1
      25: aload_0
      26: invokevirtual #222                // Method _coercedTypeDesc:()Ljava/lang/String;
      29: aastore
      30: invokevirtual #245                // Method com/fasterxml/jackson/databind/DeserializationContext.reportBadCoercion:(Lcom/fasterxml/jackson/databind/JsonDeserializer;Ljava/lang/Class;Ljava/lang/Object;Ljava/lang/String;[Ljava/lang/Object;)Ljava/lang/Object;
      33: pop
      34: aload_2
      35: areturn

  protected boolean _checkTextualNull(com.fasterxml.jackson.databind.DeserializationContext, java.lang.String) throws com.fasterxml.jackson.databind.JsonMappingException;
    Code:
       0: aload_0
       1: aload_2
       2: invokevirtual #85                 // Method _hasTextualNull:(Ljava/lang/String;)Z
       5: ifeq          31
       8: aload_1
       9: getstatic     #246                // Field com/fasterxml/jackson/databind/MapperFeature.ALLOW_COERCION_OF_SCALARS:Lcom/fasterxml/jackson/databind/MapperFeature;
      12: invokevirtual #247                // Method com/fasterxml/jackson/databind/DeserializationContext.isEnabled:(Lcom/fasterxml/jackson/databind/MapperFeature;)Z
      15: ifne          29
      18: aload_0
      19: aload_1
      20: iconst_1
      21: getstatic     #246                // Field com/fasterxml/jackson/databind/MapperFeature.ALLOW_COERCION_OF_SCALARS:Lcom/fasterxml/jackson/databind/MapperFeature;
      24: ldc           #248                // String String \"null\"
      26: invokevirtual #249                // Method _reportFailedNullCoerce:(Lcom/fasterxml/jackson/databind/DeserializationContext;ZLjava/lang/Enum;Ljava/lang/String;)V
      29: iconst_1
      30: ireturn
      31: iconst_0
      32: ireturn

  protected java.lang.Object _coerceIntegral(com.fasterxml.jackson.core.JsonParser, com.fasterxml.jackson.databind.DeserializationContext) throws java.io.IOException;
    Code:
       0: aload_2
       1: getstatic     #250                // Field com/fasterxml/jackson/databind/DeserializationFeature.USE_BIG_INTEGER_FOR_INTS:Lcom/fasterxml/jackson/databind/DeserializationFeature;
       4: invokevirtual #11                 // Method com/fasterxml/jackson/databind/DeserializationContext.isEnabled:(Lcom/fasterxml/jackson/databind/DeserializationFeature;)Z
       7: ifeq          15
      10: aload_1
      11: invokevirtual #251                // Method com/fasterxml/jackson/core/JsonParser.getBigIntegerValue:()Ljava/math/BigInteger;
      14: areturn
      15: aload_2
      16: getstatic     #252                // Field com/fasterxml/jackson/databind/DeserializationFeature.USE_LONG_FOR_INTS:Lcom/fasterxml/jackson/databind/DeserializationFeature;
      19: invokevirtual #11                 // Method com/fasterxml/jackson/databind/DeserializationContext.isEnabled:(Lcom/fasterxml/jackson/databind/DeserializationFeature;)Z
      22: ifeq          33
      25: aload_1
      26: invokevirtual #138                // Method com/fasterxml/jackson/core/JsonParser.getLongValue:()J
      29: invokestatic  #143                // Method java/lang/Long.valueOf:(J)Ljava/lang/Long;
      32: areturn
      33: aload_1
      34: invokevirtual #187                // Method com/fasterxml/jackson/core/JsonParser.getNumberValue:()Ljava/lang/Number;
      37: areturn

  protected final void _verifyNullForPrimitive(com.fasterxml.jackson.databind.DeserializationContext) throws com.fasterxml.jackson.databind.JsonMappingException;
    Code:
       0: aload_1
       1: getstatic     #253                // Field com/fasterxml/jackson/databind/DeserializationFeature.FAIL_ON_NULL_FOR_PRIMITIVES:Lcom/fasterxml/jackson/databind/DeserializationFeature;
       4: invokevirtual #11                 // Method com/fasterxml/jackson/databind/DeserializationContext.isEnabled:(Lcom/fasterxml/jackson/databind/DeserializationFeature;)Z
       7: ifeq          29
      10: aload_1
      11: aload_0
      12: ldc           #254                // String Cannot coerce `null` to %s (disable `DeserializationFeature.FAIL_ON_NULL_FOR_PRIMITIVES` to allow)
      14: iconst_1
      15: anewarray     #4                  // class java/lang/Object
      18: dup
      19: iconst_0
      20: aload_0
      21: invokevirtual #222                // Method _coercedTypeDesc:()Ljava/lang/String;
      24: aastore
      25: invokevirtual #223                // Method com/fasterxml/jackson/databind/DeserializationContext.reportInputMismatch:(Lcom/fasterxml/jackson/databind/JsonDeserializer;Ljava/lang/String;[Ljava/lang/Object;)Ljava/lang/Object;
      28: pop
      29: return

  protected final void _verifyNullForPrimitiveCoercion(com.fasterxml.jackson.databind.DeserializationContext, java.lang.String) throws com.fasterxml.jackson.databind.JsonMappingException;
    Code:
       0: aload_1
       1: getstatic     #246                // Field com/fasterxml/jackson/databind/MapperFeature.ALLOW_COERCION_OF_SCALARS:Lcom/fasterxml/jackson/databind/MapperFeature;
       4: invokevirtual #247                // Method com/fasterxml/jackson/databind/DeserializationContext.isEnabled:(Lcom/fasterxml/jackson/databind/MapperFeature;)Z
       7: ifne          20
      10: getstatic     #246                // Field com/fasterxml/jackson/databind/MapperFeature.ALLOW_COERCION_OF_SCALARS:Lcom/fasterxml/jackson/databind/MapperFeature;
      13: astore_3
      14: iconst_1
      15: istore        4
      17: goto          41
      20: aload_1
      21: getstatic     #253                // Field com/fasterxml/jackson/databind/DeserializationFeature.FAIL_ON_NULL_FOR_PRIMITIVES:Lcom/fasterxml/jackson/databind/DeserializationFeature;
      24: invokevirtual #11                 // Method com/fasterxml/jackson/databind/DeserializationContext.isEnabled:(Lcom/fasterxml/jackson/databind/DeserializationFeature;)Z
      27: ifeq          40
      30: getstatic     #253                // Field com/fasterxml/jackson/databind/DeserializationFeature.FAIL_ON_NULL_FOR_PRIMITIVES:Lcom/fasterxml/jackson/databind/DeserializationFeature;
      33: astore_3
      34: iconst_0
      35: istore        4
      37: goto          41
      40: return
      41: aload_2
      42: invokevirtual #32                 // Method java/lang/String.isEmpty:()Z
      45: ifeq          53
      48: ldc           #36                 // String empty String (\"\")
      50: goto          66
      53: ldc           #255                // String String \"%s\"
      55: iconst_1
      56: anewarray     #4                  // class java/lang/Object
      59: dup
      60: iconst_0
      61: aload_2
      62: aastore
      63: invokestatic  #256                // Method java/lang/String.format:(Ljava/lang/String;[Ljava/lang/Object;)Ljava/lang/String;
      66: astore        5
      68: aload_0
      69: aload_1
      70: iload         4
      72: aload_3
      73: aload         5
      75: invokevirtual #249                // Method _reportFailedNullCoerce:(Lcom/fasterxml/jackson/databind/DeserializationContext;ZLjava/lang/Enum;Ljava/lang/String;)V
      78: return

  protected void _reportFailedNullCoerce(com.fasterxml.jackson.databind.DeserializationContext, boolean, java.lang.Enum<?>, java.lang.String) throws com.fasterxml.jackson.databind.JsonMappingException;
    Code:
       0: iload_2
       1: ifeq          10
       4: ldc_w         #257                // String enable
       7: goto          13
      10: ldc_w         #258                // String disable
      13: astore        5
      15: aload_1
      16: aload_0
      17: ldc_w         #259                // String Cannot coerce %s to Null value as %s (%s `%s.%s` to allow)
      20: iconst_5
      21: anewarray     #4                  // class java/lang/Object
      24: dup
      25: iconst_0
      26: aload         4
      28: aastore
      29: dup
      30: iconst_1
      31: aload_0
      32: invokevirtual #222                // Method _coercedTypeDesc:()Ljava/lang/String;
      35: aastore
      36: dup
      37: iconst_2
      38: aload         5
      40: aastore
      41: dup
      42: iconst_3
      43: aload_3
      44: invokevirtual #260                // Method java/lang/Enum.getDeclaringClass:()Ljava/lang/Class;
      47: invokevirtual #261                // Method java/lang/Class.getSimpleName:()Ljava/lang/String;
      50: aastore
      51: dup
      52: iconst_4
      53: aload_3
      54: invokevirtual #262                // Method java/lang/Enum.name:()Ljava/lang/String;
      57: aastore
      58: invokevirtual #223                // Method com/fasterxml/jackson/databind/DeserializationContext.reportInputMismatch:(Lcom/fasterxml/jackson/databind/JsonDeserializer;Ljava/lang/String;[Ljava/lang/Object;)Ljava/lang/Object;
      61: pop
      62: return

  protected java.lang.String _coercedTypeDesc();
    Code:
       0: aload_0
       1: invokevirtual #263                // Method getValueType:()Lcom/fasterxml/jackson/databind/JavaType;
       4: astore_3
       5: aload_3
       6: ifnull        44
       9: aload_3
      10: invokevirtual #264                // Method com/fasterxml/jackson/databind/JavaType.isPrimitive:()Z
      13: ifne          44
      16: aload_3
      17: invokevirtual #265                // Method com/fasterxml/jackson/databind/JavaType.isContainerType:()Z
      20: ifne          30
      23: aload_3
      24: invokevirtual #266                // Method com/fasterxml/jackson/databind/JavaType.isReferenceType:()Z
      27: ifeq          34
      30: iconst_1
      31: goto          35
      34: iconst_0
      35: istore_1
      36: aload_3
      37: invokestatic  #267                // Method com/fasterxml/jackson/databind/util/ClassUtil.getTypeDescription:(Lcom/fasterxml/jackson/databind/JavaType;)Ljava/lang/String;
      40: astore_2
      41: goto          92
      44: aload_0
      45: invokevirtual #28                 // Method handledType:()Ljava/lang/Class;
      48: astore        4
      50: aload         4
      52: invokevirtual #268                // Method java/lang/Class.isArray:()Z
      55: ifne          80
      58: ldc_w         #269                // class java/util/Collection
      61: aload         4
      63: invokevirtual #270                // Method java/lang/Class.isAssignableFrom:(Ljava/lang/Class;)Z
      66: ifne          80
      69: ldc_w         #271                // class java/util/Map
      72: aload         4
      74: invokevirtual #270                // Method java/lang/Class.isAssignableFrom:(Ljava/lang/Class;)Z
      77: ifeq          84
      80: iconst_1
      81: goto          85
      84: iconst_0
      85: istore_1
      86: aload         4
      88: invokestatic  #272                // Method com/fasterxml/jackson/databind/util/ClassUtil.getClassDescription:(Ljava/lang/Object;)Ljava/lang/String;
      91: astore_2
      92: iload_1
      93: ifeq          117
      96: new           #225                // class java/lang/StringBuilder
      99: dup
     100: invokespecial #226                // Method java/lang/StringBuilder."<init>":()V
     103: ldc_w         #273                // String element of
     106: invokevirtual #228                // Method java/lang/StringBuilder.append:(Ljava/lang/String;)Ljava/lang/StringBuilder;
     109: aload_2
     110: invokevirtual #228                // Method java/lang/StringBuilder.append:(Ljava/lang/String;)Ljava/lang/StringBuilder;
     113: invokevirtual #230                // Method java/lang/StringBuilder.toString:()Ljava/lang/String;
     116: areturn
     117: new           #225                // class java/lang/StringBuilder
     120: dup
     121: invokespecial #226                // Method java/lang/StringBuilder."<init>":()V
     124: aload_2
     125: invokevirtual #228                // Method java/lang/StringBuilder.append:(Ljava/lang/String;)Ljava/lang/StringBuilder;
     128: ldc_w         #274                // String  value
     131: invokevirtual #228                // Method java/lang/StringBuilder.append:(Ljava/lang/String;)Ljava/lang/StringBuilder;
     134: invokevirtual #230                // Method java/lang/StringBuilder.toString:()Ljava/lang/String;
     137: areturn

  protected boolean _parseBooleanFromInt(com.fasterxml.jackson.core.JsonParser, com.fasterxml.jackson.databind.DeserializationContext) throws java.io.IOException;
    Code:
       0: aload_0
       1: aload_2
       2: aload_1
       3: invokevirtual #275                // Method _verifyNumberForScalarCoercion:(Lcom/fasterxml/jackson/databind/DeserializationContext;Lcom/fasterxml/jackson/core/JsonParser;)V
       6: ldc           #243                // String 0
       8: aload_1
       9: invokevirtual #69                 // Method com/fasterxml/jackson/core/JsonParser.getText:()Ljava/lang/String;
      12: invokevirtual #57                 // Method java/lang/String.equals:(Ljava/lang/Object;)Z
      15: ifne          22
      18: iconst_1
      19: goto          23
      22: iconst_0
      23: ireturn

  protected void _verifyStringForScalarCoercion(com.fasterxml.jackson.databind.DeserializationContext, java.lang.String) throws com.fasterxml.jackson.databind.JsonMappingException;
    Code:
       0: getstatic     #246                // Field com/fasterxml/jackson/databind/MapperFeature.ALLOW_COERCION_OF_SCALARS:Lcom/fasterxml/jackson/databind/MapperFeature;
       3: astore_3
       4: aload_1
       5: aload_3
       6: invokevirtual #247                // Method com/fasterxml/jackson/databind/DeserializationContext.isEnabled:(Lcom/fasterxml/jackson/databind/MapperFeature;)Z
       9: ifne          53
      12: aload_1
      13: aload_0
      14: ldc_w         #276                // String Cannot coerce String \"%s\" to %s (enable `%s.%s` to allow)
      17: iconst_4
      18: anewarray     #4                  // class java/lang/Object
      21: dup
      22: iconst_0
      23: aload_2
      24: aastore
      25: dup
      26: iconst_1
      27: aload_0
      28: invokevirtual #222                // Method _coercedTypeDesc:()Ljava/lang/String;
      31: aastore
      32: dup
      33: iconst_2
      34: aload_3
      35: invokevirtual #277                // Method com/fasterxml/jackson/databind/MapperFeature.getDeclaringClass:()Ljava/lang/Class;
      38: invokevirtual #261                // Method java/lang/Class.getSimpleName:()Ljava/lang/String;
      41: aastore
      42: dup
      43: iconst_3
      44: aload_3
      45: invokevirtual #278                // Method com/fasterxml/jackson/databind/MapperFeature.name:()Ljava/lang/String;
      48: aastore
      49: invokevirtual #223                // Method com/fasterxml/jackson/databind/DeserializationContext.reportInputMismatch:(Lcom/fasterxml/jackson/databind/JsonDeserializer;Ljava/lang/String;[Ljava/lang/Object;)Ljava/lang/Object;
      52: pop
      53: return

  protected java.lang.Object _coerceEmptyString(com.fasterxml.jackson.databind.DeserializationContext, boolean) throws com.fasterxml.jackson.databind.JsonMappingException;
    Code:
       0: aload_1
       1: getstatic     #246                // Field com/fasterxml/jackson/databind/MapperFeature.ALLOW_COERCION_OF_SCALARS:Lcom/fasterxml/jackson/databind/MapperFeature;
       4: invokevirtual #247                // Method com/fasterxml/jackson/databind/DeserializationContext.isEnabled:(Lcom/fasterxml/jackson/databind/MapperFeature;)Z
       7: ifne          20
      10: getstatic     #246                // Field com/fasterxml/jackson/databind/MapperFeature.ALLOW_COERCION_OF_SCALARS:Lcom/fasterxml/jackson/databind/MapperFeature;
      13: astore_3
      14: iconst_1
      15: istore        4
      17: goto          50
      20: iload_2
      21: ifeq          44
      24: aload_1
      25: getstatic     #253                // Field com/fasterxml/jackson/databind/DeserializationFeature.FAIL_ON_NULL_FOR_PRIMITIVES:Lcom/fasterxml/jackson/databind/DeserializationFeature;
      28: invokevirtual #11                 // Method com/fasterxml/jackson/databind/DeserializationContext.isEnabled:(Lcom/fasterxml/jackson/databind/DeserializationFeature;)Z
      31: ifeq          44
      34: getstatic     #253                // Field com/fasterxml/jackson/databind/DeserializationFeature.FAIL_ON_NULL_FOR_PRIMITIVES:Lcom/fasterxml/jackson/databind/DeserializationFeature;
      37: astore_3
      38: iconst_0
      39: istore        4
      41: goto          50
      44: aload_0
      45: aload_1
      46: invokevirtual #18                 // Method getNullValue:(Lcom/fasterxml/jackson/databind/DeserializationContext;)Ljava/lang/Object;
      49: areturn
      50: aload_0
      51: aload_1
      52: iload         4
      54: aload_3
      55: ldc           #36                 // String empty String (\"\")
      57: invokevirtual #249                // Method _reportFailedNullCoerce:(Lcom/fasterxml/jackson/databind/DeserializationContext;ZLjava/lang/Enum;Ljava/lang/String;)V
      60: aconst_null
      61: areturn

  protected void _failDoubleToIntCoercion(com.fasterxml.jackson.core.JsonParser, com.fasterxml.jackson.databind.DeserializationContext, java.lang.String) throws java.io.IOException;
    Code:
       0: aload_2
       1: aload_0
       2: invokevirtual #28                 // Method handledType:()Ljava/lang/Class;
       5: ldc_w         #279                // String Cannot coerce a floating-point value (\'%s\') into %s (enable `DeserializationFeature.ACCEPT_FLOAT_AS_INT` to allow)
       8: iconst_2
       9: anewarray     #4                  // class java/lang/Object
      12: dup
      13: iconst_0
      14: aload_1
      15: invokevirtual #29                 // Method com/fasterxml/jackson/core/JsonParser.getValueAsString:()Ljava/lang/String;
      18: aastore
      19: dup
      20: iconst_1
      21: aload_3
      22: aastore
      23: invokevirtual #280                // Method com/fasterxml/jackson/databind/DeserializationContext.reportInputMismatch:(Ljava/lang/Class;Ljava/lang/String;[Ljava/lang/Object;)Ljava/lang/Object;
      26: pop
      27: return

  protected final void _verifyNullForScalarCoercion(com.fasterxml.jackson.databind.DeserializationContext, java.lang.String) throws com.fasterxml.jackson.databind.JsonMappingException;
    Code:
       0: aload_1
       1: getstatic     #246                // Field com/fasterxml/jackson/databind/MapperFeature.ALLOW_COERCION_OF_SCALARS:Lcom/fasterxml/jackson/databind/MapperFeature;
       4: invokevirtual #247                // Method com/fasterxml/jackson/databind/DeserializationContext.isEnabled:(Lcom/fasterxml/jackson/databind/MapperFeature;)Z
       7: ifne          46
      10: aload_2
      11: invokevirtual #32                 // Method java/lang/String.isEmpty:()Z
      14: ifeq          22
      17: ldc           #36                 // String empty String (\"\")
      19: goto          35
      22: ldc           #255                // String String \"%s\"
      24: iconst_1
      25: anewarray     #4                  // class java/lang/Object
      28: dup
      29: iconst_0
      30: aload_2
      31: aastore
      32: invokestatic  #256                // Method java/lang/String.format:(Ljava/lang/String;[Ljava/lang/Object;)Ljava/lang/String;
      35: astore_3
      36: aload_0
      37: aload_1
      38: iconst_1
      39: getstatic     #246                // Field com/fasterxml/jackson/databind/MapperFeature.ALLOW_COERCION_OF_SCALARS:Lcom/fasterxml/jackson/databind/MapperFeature;
      42: aload_3
      43: invokevirtual #249                // Method _reportFailedNullCoerce:(Lcom/fasterxml/jackson/databind/DeserializationContext;ZLjava/lang/Enum;Ljava/lang/String;)V
      46: return

  protected void _verifyNumberForScalarCoercion(com.fasterxml.jackson.databind.DeserializationContext, com.fasterxml.jackson.core.JsonParser) throws java.io.IOException;
    Code:
       0: getstatic     #246                // Field com/fasterxml/jackson/databind/MapperFeature.ALLOW_COERCION_OF_SCALARS:Lcom/fasterxml/jackson/databind/MapperFeature;
       3: astore_3
       4: aload_1
       5: aload_3
       6: invokevirtual #247                // Method com/fasterxml/jackson/databind/DeserializationContext.isEnabled:(Lcom/fasterxml/jackson/databind/MapperFeature;)Z
       9: ifne          60
      12: aload_2
      13: invokevirtual #69                 // Method com/fasterxml/jackson/core/JsonParser.getText:()Ljava/lang/String;
      16: astore        4
      18: aload_1
      19: aload_0
      20: ldc_w         #281                // String Cannot coerce Number (%s) to %s (enable `%s.%s` to allow)
      23: iconst_4
      24: anewarray     #4                  // class java/lang/Object
      27: dup
      28: iconst_0
      29: aload         4
      31: aastore
      32: dup
      33: iconst_1
      34: aload_0
      35: invokevirtual #222                // Method _coercedTypeDesc:()Ljava/lang/String;
      38: aastore
      39: dup
      40: iconst_2
      41: aload_3
      42: invokevirtual #277                // Method com/fasterxml/jackson/databind/MapperFeature.getDeclaringClass:()Ljava/lang/Class;
      45: invokevirtual #261                // Method java/lang/Class.getSimpleName:()Ljava/lang/String;
      48: aastore
      49: dup
      50: iconst_3
      51: aload_3
      52: invokevirtual #278                // Method com/fasterxml/jackson/databind/MapperFeature.name:()Ljava/lang/String;
      55: aastore
      56: invokevirtual #223                // Method com/fasterxml/jackson/databind/DeserializationContext.reportInputMismatch:(Lcom/fasterxml/jackson/databind/JsonDeserializer;Ljava/lang/String;[Ljava/lang/Object;)Ljava/lang/Object;
      59: pop
      60: return

  protected java.lang.Object _coerceNullToken(com.fasterxml.jackson.databind.DeserializationContext, boolean) throws com.fasterxml.jackson.databind.JsonMappingException;
    Code:
       0: iload_2
       1: ifeq          9
       4: aload_0
       5: aload_1
       6: invokevirtual #74                 // Method _verifyNullForPrimitive:(Lcom/fasterxml/jackson/databind/DeserializationContext;)V
       9: aload_0
      10: aload_1
      11: invokevirtual #18                 // Method getNullValue:(Lcom/fasterxml/jackson/databind/DeserializationContext;)Ljava/lang/Object;
      14: areturn

  protected java.lang.Object _coerceTextualNull(com.fasterxml.jackson.databind.DeserializationContext, boolean) throws com.fasterxml.jackson.databind.JsonMappingException;
    Code:
       0: aload_1
       1: getstatic     #246                // Field com/fasterxml/jackson/databind/MapperFeature.ALLOW_COERCION_OF_SCALARS:Lcom/fasterxml/jackson/databind/MapperFeature;
       4: invokevirtual #247                // Method com/fasterxml/jackson/databind/DeserializationContext.isEnabled:(Lcom/fasterxml/jackson/databind/MapperFeature;)Z
       7: ifne          21
      10: aload_0
      11: aload_1
      12: iconst_1
      13: getstatic     #246                // Field com/fasterxml/jackson/databind/MapperFeature.ALLOW_COERCION_OF_SCALARS:Lcom/fasterxml/jackson/databind/MapperFeature;
      16: ldc           #248                // String String \"null\"
      18: invokevirtual #249                // Method _reportFailedNullCoerce:(Lcom/fasterxml/jackson/databind/DeserializationContext;ZLjava/lang/Enum;Ljava/lang/String;)V
      21: aload_0
      22: aload_1
      23: invokevirtual #18                 // Method getNullValue:(Lcom/fasterxml/jackson/databind/DeserializationContext;)Ljava/lang/Object;
      26: areturn

  protected boolean _isEmptyOrTextualNull(java.lang.String);
    Code:
       0: aload_1
       1: invokevirtual #32                 // Method java/lang/String.isEmpty:()Z
       4: ifne          16
       7: ldc           #213                // String null
       9: aload_1
      10: invokevirtual #57                 // Method java/lang/String.equals:(Ljava/lang/Object;)Z
      13: ifeq          20
      16: iconst_1
      17: goto          21
      20: iconst_0
      21: ireturn

  protected com.fasterxml.jackson.databind.JsonDeserializer<java.lang.Object> findDeserializer(com.fasterxml.jackson.databind.DeserializationContext, com.fasterxml.jackson.databind.JavaType, com.fasterxml.jackson.databind.BeanProperty) throws com.fasterxml.jackson.databind.JsonMappingException;
    Code:
       0: aload_1
       1: aload_2
       2: aload_3
       3: invokevirtual #282                // Method com/fasterxml/jackson/databind/DeserializationContext.findContextualValueDeserializer:(Lcom/fasterxml/jackson/databind/JavaType;Lcom/fasterxml/jackson/databind/BeanProperty;)Lcom/fasterxml/jackson/databind/JsonDeserializer;
       6: areturn

  protected final boolean _isIntNumber(java.lang.String);
    Code:
       0: aload_1
       1: invokevirtual #82                 // Method java/lang/String.length:()I
       4: istore_2
       5: iload_2
       6: ifle          81
       9: aload_1
      10: iconst_0
      11: invokevirtual #89                 // Method java/lang/String.charAt:(I)C
      14: istore_3
      15: iload_3
      16: bipush        45
      18: if_icmpeq     27
      21: iload_3
      22: bipush        43
      24: if_icmpne     40
      27: iload_2
      28: iconst_1
      29: if_icmpne     34
      32: iconst_0
      33: ireturn
      34: iconst_1
      35: istore        4
      37: goto          43
      40: iconst_0
      41: istore        4
      43: iload         4
      45: iload_2
      46: if_icmpge     79
      49: aload_1
      50: iload         4
      52: invokevirtual #89                 // Method java/lang/String.charAt:(I)C
      55: istore        5
      57: iload         5
      59: bipush        57
      61: if_icmpgt     71
      64: iload         5
      66: bipush        48
      68: if_icmpge     73
      71: iconst_0
      72: ireturn
      73: iinc          4, 1
      76: goto          43
      79: iconst_1
      80: ireturn
      81: iconst_0
      82: ireturn

  protected com.fasterxml.jackson.databind.JsonDeserializer<?> findConvertingContentDeserializer(com.fasterxml.jackson.databind.DeserializationContext, com.fasterxml.jackson.databind.BeanProperty, com.fasterxml.jackson.databind.JsonDeserializer<?>) throws com.fasterxml.jackson.databind.JsonMappingException;
    Code:
       0: aload_1
       1: invokevirtual #283                // Method com/fasterxml/jackson/databind/DeserializationContext.getAnnotationIntrospector:()Lcom/fasterxml/jackson/databind/AnnotationIntrospector;
       4: astore        4
       6: aload         4
       8: aload_2
       9: invokestatic  #284                // Method _neitherNull:(Ljava/lang/Object;Ljava/lang/Object;)Z
      12: ifeq          94
      15: aload_2
      16: invokeinterface #285,  1          // InterfaceMethod com/fasterxml/jackson/databind/BeanProperty.getMember:()Lcom/fasterxml/jackson/databind/introspect/AnnotatedMember;
      21: astore        5
      23: aload         5
      25: ifnull        94
      28: aload         4
      30: aload         5
      32: invokevirtual #286                // Method com/fasterxml/jackson/databind/AnnotationIntrospector.findDeserializationContentConverter:(Lcom/fasterxml/jackson/databind/introspect/AnnotatedMember;)Ljava/lang/Object;
      35: astore        6
      37: aload         6
      39: ifnull        94
      42: aload_1
      43: aload_2
      44: invokeinterface #285,  1          // InterfaceMethod com/fasterxml/jackson/databind/BeanProperty.getMember:()Lcom/fasterxml/jackson/databind/introspect/AnnotatedMember;
      49: aload         6
      51: invokevirtual #287                // Method com/fasterxml/jackson/databind/DeserializationContext.converterInstance:(Lcom/fasterxml/jackson/databind/introspect/Annotated;Ljava/lang/Object;)Lcom/fasterxml/jackson/databind/util/Converter;
      54: astore        7
      56: aload         7
      58: aload_1
      59: invokevirtual #288                // Method com/fasterxml/jackson/databind/DeserializationContext.getTypeFactory:()Lcom/fasterxml/jackson/databind/type/TypeFactory;
      62: invokeinterface #289,  2          // InterfaceMethod com/fasterxml/jackson/databind/util/Converter.getInputType:(Lcom/fasterxml/jackson/databind/type/TypeFactory;)Lcom/fasterxml/jackson/databind/JavaType;
      67: astore        8
      69: aload_3
      70: ifnonnull     81
      73: aload_1
      74: aload         8
      76: aload_2
      77: invokevirtual #282                // Method com/fasterxml/jackson/databind/DeserializationContext.findContextualValueDeserializer:(Lcom/fasterxml/jackson/databind/JavaType;Lcom/fasterxml/jackson/databind/BeanProperty;)Lcom/fasterxml/jackson/databind/JsonDeserializer;
      80: astore_3
      81: new           #290                // class com/fasterxml/jackson/databind/deser/std/StdDelegatingDeserializer
      84: dup
      85: aload         7
      87: aload         8
      89: aload_3
      90: invokespecial #291                // Method com/fasterxml/jackson/databind/deser/std/StdDelegatingDeserializer."<init>":(Lcom/fasterxml/jackson/databind/util/Converter;Lcom/fasterxml/jackson/databind/JavaType;Lcom/fasterxml/jackson/databind/JsonDeserializer;)V
      93: areturn
      94: aload_3
      95: areturn

  protected com.fasterxml.jackson.annotation.JsonFormat$Value findFormatOverrides(com.fasterxml.jackson.databind.DeserializationContext, com.fasterxml.jackson.databind.BeanProperty, java.lang.Class<?>);
    Code:
       0: aload_2
       1: ifnull        16
       4: aload_2
       5: aload_1
       6: invokevirtual #292                // Method com/fasterxml/jackson/databind/DeserializationContext.getConfig:()Lcom/fasterxml/jackson/databind/DeserializationConfig;
       9: aload_3
      10: invokeinterface #293,  3          // InterfaceMethod com/fasterxml/jackson/databind/BeanProperty.findPropertyFormat:(Lcom/fasterxml/jackson/databind/cfg/MapperConfig;Ljava/lang/Class;)Lcom/fasterxml/jackson/annotation/JsonFormat$Value;
      15: areturn
      16: aload_1
      17: aload_3
      18: invokevirtual #294                // Method com/fasterxml/jackson/databind/DeserializationContext.getDefaultPropertyFormat:(Ljava/lang/Class;)Lcom/fasterxml/jackson/annotation/JsonFormat$Value;
      21: areturn

  protected java.lang.Boolean findFormatFeature(com.fasterxml.jackson.databind.DeserializationContext, com.fasterxml.jackson.databind.BeanProperty, java.lang.Class<?>, com.fasterxml.jackson.annotation.JsonFormat$Feature);
    Code:
       0: aload_0
       1: aload_1
       2: aload_2
       3: aload_3
       4: invokevirtual #295                // Method findFormatOverrides:(Lcom/fasterxml/jackson/databind/DeserializationContext;Lcom/fasterxml/jackson/databind/BeanProperty;Ljava/lang/Class;)Lcom/fasterxml/jackson/annotation/JsonFormat$Value;
       7: astore        5
       9: aload         5
      11: ifnull        22
      14: aload         5
      16: aload         4
      18: invokevirtual #296                // Method com/fasterxml/jackson/annotation/JsonFormat$Value.getFeature:(Lcom/fasterxml/jackson/annotation/JsonFormat$Feature;)Ljava/lang/Boolean;
      21: areturn
      22: aconst_null
      23: areturn

  protected final com.fasterxml.jackson.databind.deser.NullValueProvider findValueNullProvider(com.fasterxml.jackson.databind.DeserializationContext, com.fasterxml.jackson.databind.deser.SettableBeanProperty, com.fasterxml.jackson.databind.PropertyMetadata) throws com.fasterxml.jackson.databind.JsonMappingException;
    Code:
       0: aload_2
       1: ifnull        19
       4: aload_0
       5: aload_1
       6: aload_2
       7: aload_3
       8: invokevirtual #297                // Method com/fasterxml/jackson/databind/PropertyMetadata.getValueNulls:()Lcom/fasterxml/jackson/annotation/Nulls;
      11: aload_2
      12: invokevirtual #298                // Method com/fasterxml/jackson/databind/deser/SettableBeanProperty.getValueDeserializer:()Lcom/fasterxml/jackson/databind/JsonDeserializer;
      15: invokevirtual #299                // Method _findNullProvider:(Lcom/fasterxml/jackson/databind/DeserializationContext;Lcom/fasterxml/jackson/databind/BeanProperty;Lcom/fasterxml/jackson/annotation/Nulls;Lcom/fasterxml/jackson/databind/JsonDeserializer;)Lcom/fasterxml/jackson/databind/deser/NullValueProvider;
      18: areturn
      19: aconst_null
      20: areturn

  protected com.fasterxml.jackson.databind.deser.NullValueProvider findContentNullProvider(com.fasterxml.jackson.databind.DeserializationContext, com.fasterxml.jackson.databind.BeanProperty, com.fasterxml.jackson.databind.JsonDeserializer<?>) throws com.fasterxml.jackson.databind.JsonMappingException;
    Code:
       0: aload_0
       1: aload_1
       2: aload_2
       3: invokevirtual #300                // Method findContentNullStyle:(Lcom/fasterxml/jackson/databind/DeserializationContext;Lcom/fasterxml/jackson/databind/BeanProperty;)Lcom/fasterxml/jackson/annotation/Nulls;
       6: astore        4
       8: aload         4
      10: getstatic     #301                // Field com/fasterxml/jackson/annotation/Nulls.SKIP:Lcom/fasterxml/jackson/annotation/Nulls;
      13: if_acmpne     20
      16: invokestatic  #302                // Method com/fasterxml/jackson/databind/deser/impl/NullsConstantProvider.skipper:()Lcom/fasterxml/jackson/databind/deser/impl/NullsConstantProvider;
      19: areturn
      20: aload         4
      22: getstatic     #303                // Field com/fasterxml/jackson/annotation/Nulls.FAIL:Lcom/fasterxml/jackson/annotation/Nulls;
      25: if_acmpne     77
      28: aload_2
      29: ifnonnull     63
      32: aload_1
      33: aload_3
      34: invokevirtual #304                // Method com/fasterxml/jackson/databind/JsonDeserializer.handledType:()Ljava/lang/Class;
      37: invokevirtual #6                  // Method com/fasterxml/jackson/databind/DeserializationContext.constructType:(Ljava/lang/Class;)Lcom/fasterxml/jackson/databind/JavaType;
      40: astore        5
      42: aload         5
      44: invokevirtual #265                // Method com/fasterxml/jackson/databind/JavaType.isContainerType:()Z
      47: ifeq          57
      50: aload         5
      52: invokevirtual #305                // Method com/fasterxml/jackson/databind/JavaType.getContentType:()Lcom/fasterxml/jackson/databind/JavaType;
      55: astore        5
      57: aload         5
      59: invokestatic  #306                // Method com/fasterxml/jackson/databind/deser/impl/NullsFailProvider.constructForRootValue:(Lcom/fasterxml/jackson/databind/JavaType;)Lcom/fasterxml/jackson/databind/deser/impl/NullsFailProvider;
      62: areturn
      63: aload_2
      64: aload_2
      65: invokeinterface #307,  1          // InterfaceMethod com/fasterxml/jackson/databind/BeanProperty.getType:()Lcom/fasterxml/jackson/databind/JavaType;
      70: invokevirtual #305                // Method com/fasterxml/jackson/databind/JavaType.getContentType:()Lcom/fasterxml/jackson/databind/JavaType;
      73: invokestatic  #308                // Method com/fasterxml/jackson/databind/deser/impl/NullsFailProvider.constructForProperty:(Lcom/fasterxml/jackson/databind/BeanProperty;Lcom/fasterxml/jackson/databind/JavaType;)Lcom/fasterxml/jackson/databind/deser/impl/NullsFailProvider;
      76: areturn
      77: aload_0
      78: aload_1
      79: aload_2
      80: aload         4
      82: aload_3
      83: invokevirtual #299                // Method _findNullProvider:(Lcom/fasterxml/jackson/databind/DeserializationContext;Lcom/fasterxml/jackson/databind/BeanProperty;Lcom/fasterxml/jackson/annotation/Nulls;Lcom/fasterxml/jackson/databind/JsonDeserializer;)Lcom/fasterxml/jackson/databind/deser/NullValueProvider;
      86: astore        5
      88: aload         5
      90: ifnull        96
      93: aload         5
      95: areturn
      96: aload_3
      97: areturn

  protected com.fasterxml.jackson.annotation.Nulls findContentNullStyle(com.fasterxml.jackson.databind.DeserializationContext, com.fasterxml.jackson.databind.BeanProperty) throws com.fasterxml.jackson.databind.JsonMappingException;
    Code:
       0: aload_2
       1: ifnull        14
       4: aload_2
       5: invokeinterface #309,  1          // InterfaceMethod com/fasterxml/jackson/databind/BeanProperty.getMetadata:()Lcom/fasterxml/jackson/databind/PropertyMetadata;
      10: invokevirtual #310                // Method com/fasterxml/jackson/databind/PropertyMetadata.getContentNulls:()Lcom/fasterxml/jackson/annotation/Nulls;
      13: areturn
      14: aload_1
      15: invokevirtual #292                // Method com/fasterxml/jackson/databind/DeserializationContext.getConfig:()Lcom/fasterxml/jackson/databind/DeserializationConfig;
      18: invokevirtual #311                // Method com/fasterxml/jackson/databind/DeserializationConfig.getDefaultSetterInfo:()Lcom/fasterxml/jackson/annotation/JsonSetter$Value;
      21: invokevirtual #312                // Method com/fasterxml/jackson/annotation/JsonSetter$Value.getContentNulls:()Lcom/fasterxml/jackson/annotation/Nulls;
      24: areturn

  protected final com.fasterxml.jackson.databind.deser.NullValueProvider _findNullProvider(com.fasterxml.jackson.databind.DeserializationContext, com.fasterxml.jackson.databind.BeanProperty, com.fasterxml.jackson.annotation.Nulls, com.fasterxml.jackson.databind.JsonDeserializer<?>) throws com.fasterxml.jackson.databind.JsonMappingException;
    Code:
       0: aload_3
       1: getstatic     #303                // Field com/fasterxml/jackson/annotation/Nulls.FAIL:Lcom/fasterxml/jackson/annotation/Nulls;
       4: if_acmpne     43
       7: aload_2
       8: ifnonnull     38
      11: aload         4
      13: ifnonnull     21
      16: ldc           #4                  // class java/lang/Object
      18: goto          26
      21: aload         4
      23: invokevirtual #304                // Method com/fasterxml/jackson/databind/JsonDeserializer.handledType:()Ljava/lang/Class;
      26: astore        5
      28: aload_1
      29: aload         5
      31: invokevirtual #6                  // Method com/fasterxml/jackson/databind/DeserializationContext.constructType:(Ljava/lang/Class;)Lcom/fasterxml/jackson/databind/JavaType;
      34: invokestatic  #306                // Method com/fasterxml/jackson/databind/deser/impl/NullsFailProvider.constructForRootValue:(Lcom/fasterxml/jackson/databind/JavaType;)Lcom/fasterxml/jackson/databind/deser/impl/NullsFailProvider;
      37: areturn
      38: aload_2
      39: invokestatic  #313                // Method com/fasterxml/jackson/databind/deser/impl/NullsFailProvider.constructForProperty:(Lcom/fasterxml/jackson/databind/BeanProperty;)Lcom/fasterxml/jackson/databind/deser/impl/NullsFailProvider;
      42: areturn
      43: aload_3
      44: getstatic     #314                // Field com/fasterxml/jackson/annotation/Nulls.AS_EMPTY:Lcom/fasterxml/jackson/annotation/Nulls;
      47: if_acmpne     179
      50: aload         4
      52: ifnonnull     57
      55: aconst_null
      56: areturn
      57: aload         4
      59: instanceof    #315                // class com/fasterxml/jackson/databind/deser/BeanDeserializerBase
      62: ifeq          132
      65: aload         4
      67: checkcast     #315                // class com/fasterxml/jackson/databind/deser/BeanDeserializerBase
      70: astore        5
      72: aload         5
      74: invokevirtual #316                // Method com/fasterxml/jackson/databind/deser/BeanDeserializerBase.getValueInstantiator:()Lcom/fasterxml/jackson/databind/deser/ValueInstantiator;
      77: astore        6
      79: aload         6
      81: invokevirtual #317                // Method com/fasterxml/jackson/databind/deser/ValueInstantiator.canCreateUsingDefault:()Z
      84: ifne          132
      87: aload_2
      88: ifnonnull     99
      91: aload         5
      93: invokevirtual #318                // Method com/fasterxml/jackson/databind/deser/BeanDeserializerBase.getValueType:()Lcom/fasterxml/jackson/databind/JavaType;
      96: goto          105
      99: aload_2
     100: invokeinterface #307,  1          // InterfaceMethod com/fasterxml/jackson/databind/BeanProperty.getType:()Lcom/fasterxml/jackson/databind/JavaType;
     105: astore        7
     107: aload_1
     108: aload         7
     110: ldc_w         #319                // String Cannot create empty instance of %s, no default Creator
     113: iconst_1
     114: anewarray     #4                  // class java/lang/Object
     117: dup
     118: iconst_0
     119: aload         7
     121: aastore
     122: invokestatic  #256                // Method java/lang/String.format:(Ljava/lang/String;[Ljava/lang/Object;)Ljava/lang/String;
     125: invokevirtual #320                // Method com/fasterxml/jackson/databind/DeserializationContext.reportBadDefinition:(Lcom/fasterxml/jackson/databind/JavaType;Ljava/lang/String;)Ljava/lang/Object;
     128: checkcast     #321                // class com/fasterxml/jackson/databind/deser/NullValueProvider
     131: areturn
     132: aload         4
     134: invokevirtual #322                // Method com/fasterxml/jackson/databind/JsonDeserializer.getEmptyAccessPattern:()Lcom/fasterxml/jackson/databind/util/AccessPattern;
     137: astore        5
     139: aload         5
     141: getstatic     #323                // Field com/fasterxml/jackson/databind/util/AccessPattern.ALWAYS_NULL:Lcom/fasterxml/jackson/databind/util/AccessPattern;
     144: if_acmpne     151
     147: invokestatic  #199                // Method com/fasterxml/jackson/databind/deser/impl/NullsConstantProvider.nuller:()Lcom/fasterxml/jackson/databind/deser/impl/NullsConstantProvider;
     150: areturn
     151: aload         5
     153: getstatic     #324                // Field com/fasterxml/jackson/databind/util/AccessPattern.CONSTANT:Lcom/fasterxml/jackson/databind/util/AccessPattern;
     156: if_acmpne     169
     159: aload         4
     161: aload_1
     162: invokevirtual #325                // Method com/fasterxml/jackson/databind/JsonDeserializer.getEmptyValue:(Lcom/fasterxml/jackson/databind/DeserializationContext;)Ljava/lang/Object;
     165: invokestatic  #326                // Method com/fasterxml/jackson/databind/deser/impl/NullsConstantProvider.forValue:(Ljava/lang/Object;)Lcom/fasterxml/jackson/databind/deser/impl/NullsConstantProvider;
     168: areturn
     169: new           #327                // class com/fasterxml/jackson/databind/deser/impl/NullsAsEmptyProvider
     172: dup
     173: aload         4
     175: invokespecial #328                // Method com/fasterxml/jackson/databind/deser/impl/NullsAsEmptyProvider."<init>":(Lcom/fasterxml/jackson/databind/JsonDeserializer;)V
     178: areturn
     179: aload_3
     180: getstatic     #301                // Field com/fasterxml/jackson/annotation/Nulls.SKIP:Lcom/fasterxml/jackson/annotation/Nulls;
     183: if_acmpne     190
     186: invokestatic  #302                // Method com/fasterxml/jackson/databind/deser/impl/NullsConstantProvider.skipper:()Lcom/fasterxml/jackson/databind/deser/impl/NullsConstantProvider;
     189: areturn
     190: aconst_null
     191: areturn

  protected com.fasterxml.jackson.databind.cfg.CoercionAction _findCoercionFromEmptyString(com.fasterxml.jackson.databind.DeserializationContext);
    Code:
       0: aload_1
       1: aload_0
       2: invokevirtual #33                 // Method logicalType:()Lcom/fasterxml/jackson/databind/type/LogicalType;
       5: aload_0
       6: invokevirtual #28                 // Method handledType:()Ljava/lang/Class;
       9: getstatic     #34                 // Field com/fasterxml/jackson/databind/cfg/CoercionInputShape.EmptyString:Lcom/fasterxml/jackson/databind/cfg/CoercionInputShape;
      12: invokevirtual #35                 // Method com/fasterxml/jackson/databind/DeserializationContext.findCoercionAction:(Lcom/fasterxml/jackson/databind/type/LogicalType;Ljava/lang/Class;Lcom/fasterxml/jackson/databind/cfg/CoercionInputShape;)Lcom/fasterxml/jackson/databind/cfg/CoercionAction;
      15: areturn

  protected com.fasterxml.jackson.databind.cfg.CoercionAction _findCoercionFromEmptyArray(com.fasterxml.jackson.databind.DeserializationContext);
    Code:
       0: aload_1
       1: aload_0
       2: invokevirtual #33                 // Method logicalType:()Lcom/fasterxml/jackson/databind/type/LogicalType;
       5: aload_0
       6: invokevirtual #28                 // Method handledType:()Ljava/lang/Class;
       9: getstatic     #329                // Field com/fasterxml/jackson/databind/cfg/CoercionInputShape.EmptyArray:Lcom/fasterxml/jackson/databind/cfg/CoercionInputShape;
      12: invokevirtual #35                 // Method com/fasterxml/jackson/databind/DeserializationContext.findCoercionAction:(Lcom/fasterxml/jackson/databind/type/LogicalType;Ljava/lang/Class;Lcom/fasterxml/jackson/databind/cfg/CoercionInputShape;)Lcom/fasterxml/jackson/databind/cfg/CoercionAction;
      15: areturn

  protected com.fasterxml.jackson.databind.cfg.CoercionAction _findCoercionFromBlankString(com.fasterxml.jackson.databind.DeserializationContext);
    Code:
       0: aload_1
       1: aload_0
       2: invokevirtual #33                 // Method logicalType:()Lcom/fasterxml/jackson/databind/type/LogicalType;
       5: aload_0
       6: invokevirtual #28                 // Method handledType:()Ljava/lang/Class;
       9: getstatic     #12                 // Field com/fasterxml/jackson/databind/cfg/CoercionAction.Fail:Lcom/fasterxml/jackson/databind/cfg/CoercionAction;
      12: invokevirtual #39                 // Method com/fasterxml/jackson/databind/DeserializationContext.findCoercionFromBlankString:(Lcom/fasterxml/jackson/databind/type/LogicalType;Ljava/lang/Class;Lcom/fasterxml/jackson/databind/cfg/CoercionAction;)Lcom/fasterxml/jackson/databind/cfg/CoercionAction;
      15: areturn

  protected void handleUnknownProperty(com.fasterxml.jackson.core.JsonParser, com.fasterxml.jackson.databind.DeserializationContext, java.lang.Object, java.lang.String) throws java.io.IOException;
    Code:
       0: aload_3
       1: ifnonnull     9
       4: aload_0
       5: invokevirtual #28                 // Method handledType:()Ljava/lang/Class;
       8: astore_3
       9: aload_2
      10: aload_1
      11: aload_0
      12: aload_3
      13: aload         4
      15: invokevirtual #330                // Method com/fasterxml/jackson/databind/DeserializationContext.handleUnknownProperty:(Lcom/fasterxml/jackson/core/JsonParser;Lcom/fasterxml/jackson/databind/JsonDeserializer;Ljava/lang/Object;Ljava/lang/String;)Z
      18: ifeq          22
      21: return
      22: aload_1
      23: invokevirtual #331                // Method com/fasterxml/jackson/core/JsonParser.skipChildren:()Lcom/fasterxml/jackson/core/JsonParser;
      26: pop
      27: return

  protected void handleMissingEndArrayForSingle(com.fasterxml.jackson.core.JsonParser, com.fasterxml.jackson.databind.DeserializationContext) throws java.io.IOException;
    Code:
       0: aload_2
       1: aload_0
       2: getstatic     #14                 // Field com/fasterxml/jackson/core/JsonToken.END_ARRAY:Lcom/fasterxml/jackson/core/JsonToken;
       5: ldc_w         #332                // String Attempted to unwrap \'%s\' value from an array (with `DeserializationFeature.UNWRAP_SINGLE_VALUE_ARRAYS`) but it contains more than one value
       8: iconst_1
       9: anewarray     #4                  // class java/lang/Object
      12: dup
      13: iconst_0
      14: aload_0
      15: invokevirtual #28                 // Method handledType:()Ljava/lang/Class;
      18: invokevirtual #333                // Method java/lang/Class.getName:()Ljava/lang/String;
      21: aastore
      22: invokevirtual #334                // Method com/fasterxml/jackson/databind/DeserializationContext.reportWrongTokenException:(Lcom/fasterxml/jackson/databind/JsonDeserializer;Lcom/fasterxml/jackson/core/JsonToken;Ljava/lang/String;[Ljava/lang/Object;)V
      25: return

  protected java.lang.Object handleNestedArrayForSingle(com.fasterxml.jackson.core.JsonParser, com.fasterxml.jackson.databind.DeserializationContext) throws java.io.IOException;
    Code:
       0: ldc_w         #335                // String Cannot deserialize instance of %s out of %s token: nested Arrays not allowed with %s
       3: iconst_3
       4: anewarray     #4                  // class java/lang/Object
       7: dup
       8: iconst_0
       9: aload_0
      10: getfield      #2                  // Field _valueClass:Ljava/lang/Class;
      13: invokestatic  #336                // Method com/fasterxml/jackson/databind/util/ClassUtil.nameOf:(Ljava/lang/Class;)Ljava/lang/String;
      16: aastore
      17: dup
      18: iconst_1
      19: getstatic     #22                 // Field com/fasterxml/jackson/core/JsonToken.START_ARRAY:Lcom/fasterxml/jackson/core/JsonToken;
      22: aastore
      23: dup
      24: iconst_2
      25: ldc_w         #337                // String DeserializationFeature.UNWRAP_SINGLE_VALUE_ARRAYS
      28: aastore
      29: invokestatic  #256                // Method java/lang/String.format:(Ljava/lang/String;[Ljava/lang/Object;)Ljava/lang/String;
      32: astore_3
      33: aload_2
      34: aload_0
      35: aload_2
      36: invokevirtual #21                 // Method getValueType:(Lcom/fasterxml/jackson/databind/DeserializationContext;)Lcom/fasterxml/jackson/databind/JavaType;
      39: aload_1
      40: invokevirtual #211                // Method com/fasterxml/jackson/core/JsonParser.currentToken:()Lcom/fasterxml/jackson/core/JsonToken;
      43: aload_1
      44: aload_3
      45: iconst_0
      46: anewarray     #4                  // class java/lang/Object
      49: invokevirtual #23                 // Method com/fasterxml/jackson/databind/DeserializationContext.handleUnexpectedToken:(Lcom/fasterxml/jackson/databind/JavaType;Lcom/fasterxml/jackson/core/JsonToken;Lcom/fasterxml/jackson/core/JsonParser;Ljava/lang/String;[Ljava/lang/Object;)Ljava/lang/Object;
      52: areturn

  protected void _verifyEndArrayForSingle(com.fasterxml.jackson.core.JsonParser, com.fasterxml.jackson.databind.DeserializationContext) throws java.io.IOException;
    Code:
       0: aload_1
       1: invokevirtual #13                 // Method com/fasterxml/jackson/core/JsonParser.nextToken:()Lcom/fasterxml/jackson/core/JsonToken;
       4: astore_3
       5: aload_3
       6: getstatic     #14                 // Field com/fasterxml/jackson/core/JsonToken.END_ARRAY:Lcom/fasterxml/jackson/core/JsonToken;
       9: if_acmpeq     18
      12: aload_0
      13: aload_1
      14: aload_2
      15: invokevirtual #20                 // Method handleMissingEndArrayForSingle:(Lcom/fasterxml/jackson/core/JsonParser;Lcom/fasterxml/jackson/databind/DeserializationContext;)V
      18: return

  protected static final boolean _neitherNull(java.lang.Object, java.lang.Object);
    Code:
       0: aload_0
       1: ifnull        12
       4: aload_1
       5: ifnull        12
       8: iconst_1
       9: goto          13
      12: iconst_0
      13: ireturn

  protected final boolean _byteOverflow(int);
    Code:
       0: iload_1
       1: bipush        -128
       3: if_icmplt     13
       6: iload_1
       7: sipush        255
      10: if_icmple     17
      13: iconst_1
      14: goto          18
      17: iconst_0
      18: ireturn

  protected final boolean _shortOverflow(int);
    Code:
       0: iload_1
       1: sipush        -32768
       4: if_icmplt     14
       7: iload_1
       8: sipush        32767
      11: if_icmple     18
      14: iconst_1
      15: goto          19
      18: iconst_0
      19: ireturn

  protected final boolean _intOverflow(long);
    Code:
       0: lload_1
       1: ldc2_w        #338                // long -2147483648l
       4: lcmp
       5: iflt          16
       8: lload_1
       9: ldc2_w        #340                // long 2147483647l
      12: lcmp
      13: ifle          20
      16: iconst_1
      17: goto          21
      20: iconst_0
      21: ireturn

  protected java.lang.Number _nonNullNumber(java.lang.Number);
    Code:
       0: aload_1
       1: ifnonnull     9
       4: iconst_0
       5: invokestatic  #128                // Method java/lang/Integer.valueOf:(I)Ljava/lang/Integer;
       8: astore_1
       9: aload_1
      10: areturn

  static {};
    Code:
       0: getstatic     #250                // Field com/fasterxml/jackson/databind/DeserializationFeature.USE_BIG_INTEGER_FOR_INTS:Lcom/fasterxml/jackson/databind/DeserializationFeature;
       3: invokevirtual #342                // Method com/fasterxml/jackson/databind/DeserializationFeature.getMask:()I
       6: getstatic     #252                // Field com/fasterxml/jackson/databind/DeserializationFeature.USE_LONG_FOR_INTS:Lcom/fasterxml/jackson/databind/DeserializationFeature;
       9: invokevirtual #342                // Method com/fasterxml/jackson/databind/DeserializationFeature.getMask:()I
      12: ior
      13: putstatic     #343                // Field F_MASK_INT_COERCIONS:I
      16: getstatic     #10                 // Field com/fasterxml/jackson/databind/DeserializationFeature.UNWRAP_SINGLE_VALUE_ARRAYS:Lcom/fasterxml/jackson/databind/DeserializationFeature;
      19: invokevirtual #342                // Method com/fasterxml/jackson/databind/DeserializationFeature.getMask:()I
      22: getstatic     #25                 // Field com/fasterxml/jackson/databind/DeserializationFeature.ACCEPT_EMPTY_ARRAY_AS_NULL_OBJECT:Lcom/fasterxml/jackson/databind/DeserializationFeature;
      25: invokevirtual #342                // Method com/fasterxml/jackson/databind/DeserializationFeature.getMask:()I
      28: ior
      29: putstatic     #344                // Field F_MASK_ACCEPT_ARRAYS:I
      32: return
}
