Compiled from "EarlyExitException.java"
public class org.antlr.runtime.EarlyExitException extends org.antlr.runtime.RecognitionException {
  public int decisionNumber;

  public org.antlr.runtime.EarlyExitException();
    Code:
       0: aload_0
       1: invokespecial #1                  // Method org/antlr/runtime/RecognitionException."<init>":()V
       4: return

  public org.antlr.runtime.EarlyExitException(int, org.antlr.runtime.IntStream);
    Code:
       0: aload_0
       1: aload_2
       2: invokespecial #2                  // Method org/antlr/runtime/RecognitionException."<init>":(Lorg/antlr/runtime/IntStream;)V
       5: aload_0
       6: iload_1
       7: putfield      #3                  // Field decisionNumber:I
      10: return
}
