Compiled from "CounterRepository.java"
public class org.apache.cxf.management.counters.CounterRepository {
  private static final java.util.logging.Logger LOG;

  private java.util.Map<javax.management.ObjectName, org.apache.cxf.management.counters.Counter> counters;

  private org.apache.cxf.Bus bus;

  private java.util.concurrent.locks.Lock counterCreationLock;

  public org.apache.cxf.management.counters.CounterRepository();
    Code:
       0: aload_0
       1: invokespecial #1                  // Method java/lang/Object."<init>":()V
       4: aload_0
       5: new           #2                  // class java/util/concurrent/locks/ReentrantLock
       8: dup
       9: invokespecial #3                  // Method java/util/concurrent/locks/ReentrantLock."<init>":()V
      12: putfield      #4                  // Field counterCreationLock:Ljava/util/concurrent/locks/Lock;
      15: aload_0
      16: new           #5                  // class java/util/concurrent/ConcurrentHashMap
      19: dup
      20: invokespecial #6                  // Method java/util/concurrent/ConcurrentHashMap."<init>":()V
      23: putfield      #7                  // Field counters:Ljava/util/Map;
      26: return

  public void setBus(org.apache.cxf.Bus);
    Code:
       0: aload_0
       1: aload_1
       2: putfield      #8                  // Field bus:Lorg/apache/cxf/Bus;
       5: aload_0
       6: getfield      #8                  // Field bus:Lorg/apache/cxf/Bus;
       9: ifnull        16
      12: aload_0
      13: invokevirtual #9                  // Method registerInterceptorsToBus:()V
      16: return

  public org.apache.cxf.Bus getBus();
    Code:
       0: aload_0
       1: getfield      #8                  // Field bus:Lorg/apache/cxf/Bus;
       4: areturn

  public java.util.Map<javax.management.ObjectName, org.apache.cxf.management.counters.Counter> getCounters();
    Code:
       0: aload_0
       1: getfield      #7                  // Field counters:Ljava/util/Map;
       4: areturn

  void registerInterceptorsToBus();
    Code:
       0: new           #10                 // class org/apache/cxf/management/interceptor/ResponseTimeMessageInInterceptor
       3: dup
       4: invokespecial #11                 // Method org/apache/cxf/management/interceptor/ResponseTimeMessageInInterceptor."<init>":()V
       7: astore_1
       8: new           #12                 // class org/apache/cxf/management/interceptor/ResponseTimeMessageInvokerInterceptor
      11: dup
      12: invokespecial #13                 // Method org/apache/cxf/management/interceptor/ResponseTimeMessageInvokerInterceptor."<init>":()V
      15: astore_2
      16: new           #14                 // class org/apache/cxf/management/interceptor/ResponseTimeMessageOutInterceptor
      19: dup
      20: invokespecial #15                 // Method org/apache/cxf/management/interceptor/ResponseTimeMessageOutInterceptor."<init>":()V
      23: astore_3
      24: aload_0
      25: getfield      #8                  // Field bus:Lorg/apache/cxf/Bus;
      28: invokeinterface #16,  1           // InterfaceMethod org/apache/cxf/Bus.getInInterceptors:()Ljava/util/List;
      33: aload_1
      34: invokeinterface #17,  2           // InterfaceMethod java/util/List.add:(Ljava/lang/Object;)Z
      39: pop
      40: aload_0
      41: getfield      #8                  // Field bus:Lorg/apache/cxf/Bus;
      44: invokeinterface #16,  1           // InterfaceMethod org/apache/cxf/Bus.getInInterceptors:()Ljava/util/List;
      49: aload_2
      50: invokeinterface #17,  2           // InterfaceMethod java/util/List.add:(Ljava/lang/Object;)Z
      55: pop
      56: aload_0
      57: getfield      #8                  // Field bus:Lorg/apache/cxf/Bus;
      60: invokeinterface #18,  1           // InterfaceMethod org/apache/cxf/Bus.getOutInterceptors:()Ljava/util/List;
      65: aload_3
      66: invokeinterface #17,  2           // InterfaceMethod java/util/List.add:(Ljava/lang/Object;)Z
      71: pop
      72: aload_0
      73: getfield      #8                  // Field bus:Lorg/apache/cxf/Bus;
      76: invokeinterface #19,  1           // InterfaceMethod org/apache/cxf/Bus.getOutFaultInterceptors:()Ljava/util/List;
      81: aload_3
      82: invokeinterface #17,  2           // InterfaceMethod java/util/List.add:(Ljava/lang/Object;)Z
      87: pop
      88: aload_0
      89: getfield      #8                  // Field bus:Lorg/apache/cxf/Bus;
      92: aload_0
      93: ldc_w         #20                 // class org/apache/cxf/management/counters/CounterRepository
      96: invokeinterface #21,  3           // InterfaceMethod org/apache/cxf/Bus.setExtension:(Ljava/lang/Object;Ljava/lang/Class;)V
     101: return

  public void increaseCounter(javax.management.ObjectName, org.apache.cxf.management.counters.MessageHandlingTimeRecorder);
    Code:
       0: aload_0
       1: aload_1
       2: invokevirtual #22                 // Method getCounter:(Ljavax/management/ObjectName;)Lorg/apache/cxf/management/counters/Counter;
       5: astore_3
       6: aconst_null
       7: aload_3
       8: if_acmpne     74
      11: aload_0
      12: getfield      #4                  // Field counterCreationLock:Ljava/util/concurrent/locks/Lock;
      15: invokeinterface #23,  1           // InterfaceMethod java/util/concurrent/locks/Lock.lock:()V
      20: aload_0
      21: aload_1
      22: invokevirtual #22                 // Method getCounter:(Ljavax/management/ObjectName;)Lorg/apache/cxf/management/counters/Counter;
      25: astore_3
      26: aload_3
      27: ifnonnull     48
      30: aload_0
      31: aload_1
      32: invokevirtual #24                 // Method createCounter:(Ljavax/management/ObjectName;)Lorg/apache/cxf/management/counters/Counter;
      35: astore_3
      36: aload_0
      37: getfield      #7                  // Field counters:Ljava/util/Map;
      40: aload_1
      41: aload_3
      42: invokeinterface #25,  3           // InterfaceMethod java/util/Map.put:(Ljava/lang/Object;Ljava/lang/Object;)Ljava/lang/Object;
      47: pop
      48: aload_0
      49: getfield      #4                  // Field counterCreationLock:Ljava/util/concurrent/locks/Lock;
      52: invokeinterface #26,  1           // InterfaceMethod java/util/concurrent/locks/Lock.unlock:()V
      57: goto          74
      60: astore        4
      62: aload_0
      63: getfield      #4                  // Field counterCreationLock:Ljava/util/concurrent/locks/Lock;
      66: invokeinterface #26,  1           // InterfaceMethod java/util/concurrent/locks/Lock.unlock:()V
      71: aload         4
      73: athrow
      74: aload_3
      75: aload_2
      76: invokeinterface #27,  2           // InterfaceMethod org/apache/cxf/management/counters/Counter.increase:(Lorg/apache/cxf/management/counters/MessageHandlingTimeRecorder;)V
      81: getstatic     #28                 // Field LOG:Ljava/util/logging/Logger;
      84: getstatic     #29                 // Field java/util/logging/Level.FINE:Ljava/util/logging/Level;
      87: invokevirtual #30                 // Method java/util/logging/Logger.isLoggable:(Ljava/util/logging/Level;)Z
      90: ifeq          127
      93: getstatic     #28                 // Field LOG:Ljava/util/logging/Logger;
      96: new           #31                 // class java/lang/StringBuilder
      99: dup
     100: invokespecial #32                 // Method java/lang/StringBuilder."<init>":()V
     103: ldc           #33                 // String Increase counter
     105: invokevirtual #34                 // Method java/lang/StringBuilder.append:(Ljava/lang/String;)Ljava/lang/StringBuilder;
     108: aload_1
     109: invokevirtual #35                 // Method java/lang/StringBuilder.append:(Ljava/lang/Object;)Ljava/lang/StringBuilder;
     112: ldc           #36                 // String  with
     114: invokevirtual #34                 // Method java/lang/StringBuilder.append:(Ljava/lang/String;)Ljava/lang/StringBuilder;
     117: aload_2
     118: invokevirtual #35                 // Method java/lang/StringBuilder.append:(Ljava/lang/Object;)Ljava/lang/StringBuilder;
     121: invokevirtual #37                 // Method java/lang/StringBuilder.toString:()Ljava/lang/String;
     124: invokevirtual #38                 // Method java/util/logging/Logger.fine:(Ljava/lang/String;)V
     127: return
    Exception table:
       from    to  target type
          20    48    60   any
          60    62    60   any

  public org.apache.cxf.management.counters.Counter getCounter(javax.management.ObjectName);
    Code:
       0: aload_0
       1: getfield      #7                  // Field counters:Ljava/util/Map;
       4: aload_1
       5: invokeinterface #39,  2           // InterfaceMethod java/util/Map.get:(Ljava/lang/Object;)Ljava/lang/Object;
      10: checkcast     #40                 // class org/apache/cxf/management/counters/Counter
      13: areturn

  public org.apache.cxf.management.counters.Counter createCounter(javax.management.ObjectName);
    Code:
       0: aconst_null
       1: astore_2
       2: new           #41                 // class org/apache/cxf/management/counters/ResponseTimeCounter
       5: dup
       6: aload_1
       7: invokespecial #42                 // Method org/apache/cxf/management/counters/ResponseTimeCounter."<init>":(Ljavax/management/ObjectName;)V
      10: astore_2
      11: aload_0
      12: getfield      #8                  // Field bus:Lorg/apache/cxf/Bus;
      15: ldc_w         #43                 // class org/apache/cxf/management/InstrumentationManager
      18: invokeinterface #44,  2           // InterfaceMethod org/apache/cxf/Bus.getExtension:(Ljava/lang/Class;)Ljava/lang/Object;
      23: checkcast     #43                 // class org/apache/cxf/management/InstrumentationManager
      26: astore_3
      27: aconst_null
      28: aload_3
      29: if_acmpeq     69
      32: aload_3
      33: aload_2
      34: invokeinterface #45,  2           // InterfaceMethod org/apache/cxf/management/InstrumentationManager.register:(Lorg/apache/cxf/management/ManagedComponent;)Ljavax/management/ObjectName;
      39: pop
      40: goto          69
      43: astore        4
      45: getstatic     #28                 // Field LOG:Ljava/util/logging/Logger;
      48: getstatic     #47                 // Field java/util/logging/Level.WARNING:Ljava/util/logging/Level;
      51: ldc           #48                 // String INSTRUMENTATION_REGISTER_FAULT_MSG
      53: iconst_2
      54: anewarray     #49                 // class java/lang/Object
      57: dup
      58: iconst_0
      59: aload_1
      60: aastore
      61: dup
      62: iconst_1
      63: aload         4
      65: aastore
      66: invokevirtual #50                 // Method java/util/logging/Logger.log:(Ljava/util/logging/Level;Ljava/lang/String;[Ljava/lang/Object;)V
      69: aload_2
      70: areturn
    Exception table:
       from    to  target type
          32    40    43   Class javax/management/JMException

  static {};
    Code:
       0: ldc_w         #20                 // class org/apache/cxf/management/counters/CounterRepository
       3: invokestatic  #51                 // Method org/apache/cxf/common/logging/LogUtils.getL7dLogger:(Ljava/lang/Class;)Ljava/util/logging/Logger;
       6: putstatic     #28                 // Field LOG:Ljava/util/logging/Logger;
       9: return
}
