Compiled from "BaseZeroCopyRequestProducer.java"
abstract class org.apache.http.nio.client.methods.BaseZeroCopyRequestProducer implements org.apache.http.nio.protocol.HttpAsyncRequestProducer {
  private final java.net.URI requestURI;

  private final java.io.File file;

  private final java.io.RandomAccessFile accessfile;

  private final org.apache.http.entity.ContentType contentType;

  private java.nio.channels.FileChannel fileChannel;

  private long idx;

  protected org.apache.http.nio.client.methods.BaseZeroCopyRequestProducer(java.net.URI, java.io.File, org.apache.http.entity.ContentType) throws java.io.FileNotFoundException;
    Code:
       0: aload_0
       1: invokespecial #1                  // Method java/lang/Object."<init>":()V
       4: aload_0
       5: ldc2_w        #2                  // long -1l
       8: putfield      #4                  // Field idx:J
      11: aload_1
      12: ldc           #5                  // String Request URI
      14: invokestatic  #6                  // Method org/apache/http/util/Args.notNull:(Ljava/lang/Object;Ljava/lang/String;)Ljava/lang/Object;
      17: pop
      18: aload_2
      19: ldc           #7                  // String Source file
      21: invokestatic  #6                  // Method org/apache/http/util/Args.notNull:(Ljava/lang/Object;Ljava/lang/String;)Ljava/lang/Object;
      24: pop
      25: aload_0
      26: aload_1
      27: putfield      #8                  // Field requestURI:Ljava/net/URI;
      30: aload_0
      31: aload_2
      32: putfield      #9                  // Field file:Ljava/io/File;
      35: aload_0
      36: new           #10                 // class java/io/RandomAccessFile
      39: dup
      40: aload_2
      41: ldc           #11                 // String r
      43: invokespecial #12                 // Method java/io/RandomAccessFile."<init>":(Ljava/io/File;Ljava/lang/String;)V
      46: putfield      #13                 // Field accessfile:Ljava/io/RandomAccessFile;
      49: aload_0
      50: aload_3
      51: putfield      #14                 // Field contentType:Lorg/apache/http/entity/ContentType;
      54: return

  private void closeChannel() throws java.io.IOException;
    Code:
       0: aload_0
       1: getfield      #15                 // Field fileChannel:Ljava/nio/channels/FileChannel;
       4: ifnull        19
       7: aload_0
       8: getfield      #15                 // Field fileChannel:Ljava/nio/channels/FileChannel;
      11: invokevirtual #16                 // Method java/nio/channels/FileChannel.close:()V
      14: aload_0
      15: aconst_null
      16: putfield      #15                 // Field fileChannel:Ljava/nio/channels/FileChannel;
      19: return

  protected abstract org.apache.http.HttpEntityEnclosingRequest createRequest(java.net.URI, org.apache.http.HttpEntity);

  public org.apache.http.HttpRequest generateRequest() throws java.io.IOException, org.apache.http.HttpException;
    Code:
       0: new           #17                 // class org/apache/http/entity/BasicHttpEntity
       3: dup
       4: invokespecial #18                 // Method org/apache/http/entity/BasicHttpEntity."<init>":()V
       7: astore_1
       8: aload_1
       9: iconst_0
      10: invokevirtual #19                 // Method org/apache/http/entity/BasicHttpEntity.setChunked:(Z)V
      13: aload_1
      14: aload_0
      15: getfield      #9                  // Field file:Ljava/io/File;
      18: invokevirtual #20                 // Method java/io/File.length:()J
      21: invokevirtual #21                 // Method org/apache/http/entity/BasicHttpEntity.setContentLength:(J)V
      24: aload_0
      25: getfield      #14                 // Field contentType:Lorg/apache/http/entity/ContentType;
      28: ifnull        42
      31: aload_1
      32: aload_0
      33: getfield      #14                 // Field contentType:Lorg/apache/http/entity/ContentType;
      36: invokevirtual #22                 // Method org/apache/http/entity/ContentType.toString:()Ljava/lang/String;
      39: invokevirtual #23                 // Method org/apache/http/entity/BasicHttpEntity.setContentType:(Ljava/lang/String;)V
      42: aload_0
      43: aload_0
      44: getfield      #8                  // Field requestURI:Ljava/net/URI;
      47: aload_1
      48: invokevirtual #24                 // Method createRequest:(Ljava/net/URI;Lorg/apache/http/HttpEntity;)Lorg/apache/http/HttpEntityEnclosingRequest;
      51: areturn

  public synchronized org.apache.http.HttpHost getTarget();
    Code:
       0: aload_0
       1: getfield      #8                  // Field requestURI:Ljava/net/URI;
       4: invokestatic  #25                 // Method org/apache/http/client/utils/URIUtils.extractHost:(Ljava/net/URI;)Lorg/apache/http/HttpHost;
       7: areturn

  public synchronized void produceContent(org.apache.http.nio.ContentEncoder, org.apache.http.nio.IOControl) throws java.io.IOException;
    Code:
       0: aload_0
       1: getfield      #15                 // Field fileChannel:Ljava/nio/channels/FileChannel;
       4: ifnonnull     23
       7: aload_0
       8: aload_0
       9: getfield      #13                 // Field accessfile:Ljava/io/RandomAccessFile;
      12: invokevirtual #26                 // Method java/io/RandomAccessFile.getChannel:()Ljava/nio/channels/FileChannel;
      15: putfield      #15                 // Field fileChannel:Ljava/nio/channels/FileChannel;
      18: aload_0
      19: lconst_0
      20: putfield      #4                  // Field idx:J
      23: aload_1
      24: instanceof    #27                 // class org/apache/http/nio/FileContentEncoder
      27: ifeq          54
      30: aload_1
      31: checkcast     #27                 // class org/apache/http/nio/FileContentEncoder
      34: aload_0
      35: getfield      #15                 // Field fileChannel:Ljava/nio/channels/FileChannel;
      38: aload_0
      39: getfield      #4                  // Field idx:J
      42: ldc2_w        #28                 // long 2147483647l
      45: invokeinterface #30,  6           // InterfaceMethod org/apache/http/nio/FileContentEncoder.transfer:(Ljava/nio/channels/FileChannel;JJ)J
      50: lstore_3
      51: goto          77
      54: aload_0
      55: getfield      #15                 // Field fileChannel:Ljava/nio/channels/FileChannel;
      58: aload_0
      59: getfield      #4                  // Field idx:J
      62: ldc2_w        #28                 // long 2147483647l
      65: new           #31                 // class org/apache/http/nio/ContentEncoderChannel
      68: dup
      69: aload_1
      70: invokespecial #32                 // Method org/apache/http/nio/ContentEncoderChannel."<init>":(Lorg/apache/http/nio/ContentEncoder;)V
      73: invokevirtual #33                 // Method java/nio/channels/FileChannel.transferTo:(JJLjava/nio/channels/WritableByteChannel;)J
      76: lstore_3
      77: lload_3
      78: lconst_0
      79: lcmp
      80: ifle          93
      83: aload_0
      84: dup
      85: getfield      #4                  // Field idx:J
      88: lload_3
      89: ladd
      90: putfield      #4                  // Field idx:J
      93: aload_0
      94: getfield      #4                  // Field idx:J
      97: aload_0
      98: getfield      #15                 // Field fileChannel:Ljava/nio/channels/FileChannel;
     101: invokevirtual #34                 // Method java/nio/channels/FileChannel.size:()J
     104: lcmp
     105: iflt          118
     108: aload_1
     109: invokeinterface #35,  1           // InterfaceMethod org/apache/http/nio/ContentEncoder.complete:()V
     114: aload_0
     115: invokespecial #36                 // Method closeChannel:()V
     118: return

  public void requestCompleted(org.apache.http.protocol.HttpContext);
    Code:
       0: return

  public void failed(java.lang.Exception);
    Code:
       0: return

  public boolean isRepeatable();
    Code:
       0: iconst_1
       1: ireturn

  public synchronized void resetRequest() throws java.io.IOException;
    Code:
       0: aload_0
       1: invokespecial #36                 // Method closeChannel:()V
       4: return

  public synchronized void close() throws java.io.IOException;
    Code:
       0: aload_0
       1: getfield      #13                 // Field accessfile:Ljava/io/RandomAccessFile;
       4: invokevirtual #37                 // Method java/io/RandomAccessFile.close:()V
       7: goto          11
      10: astore_1
      11: return
    Exception table:
       from    to  target type
           0     7    10   Class java/io/IOException
}
