Compiled from "BeanType.java"
public class org.apache.cxf.aegis.type.basic.BeanType extends org.apache.cxf.aegis.type.AegisType {
  private org.apache.cxf.aegis.type.basic.BeanTypeInfo info;

  private boolean isInterface;

  private boolean isException;

  public org.apache.cxf.aegis.type.basic.BeanType();
    Code:
       0: aload_0
       1: invokespecial #1                  // Method org/apache/cxf/aegis/type/AegisType."<init>":()V
       4: return

  public org.apache.cxf.aegis.type.basic.BeanType(org.apache.cxf.aegis.type.basic.BeanTypeInfo);
    Code:
       0: aload_0
       1: invokespecial #1                  // Method org/apache/cxf/aegis/type/AegisType."<init>":()V
       4: aload_0
       5: aload_1
       6: putfield      #2                  // Field info:Lorg/apache/cxf/aegis/type/basic/BeanTypeInfo;
       9: aload_0
      10: aload_1
      11: invokevirtual #3                  // Method org/apache/cxf/aegis/type/basic/BeanTypeInfo.getTypeClass:()Ljava/lang/Class;
      14: putfield      #4                  // Field typeClass:Ljava/lang/reflect/Type;
      17: aload_0
      18: invokespecial #5                  // Method initTypeClass:()V
      21: return

  private void initTypeClass();
    Code:
       0: aload_0
       1: getfield      #4                  // Field typeClass:Ljava/lang/reflect/Type;
       4: checkcast     #6                  // class java/lang/Class
       7: astore_1
       8: aload_0
       9: aload_1
      10: invokevirtual #7                  // Method java/lang/Class.isInterface:()Z
      13: putfield      #8                  // Field isInterface:Z
      16: aload_0
      17: ldc_w         #9                  // class java/lang/Exception
      20: aload_1
      21: invokevirtual #10                 // Method java/lang/Class.isAssignableFrom:(Ljava/lang/Class;)Z
      24: putfield      #11                 // Field isException:Z
      27: return

  public java.lang.Object readObject(org.apache.cxf.aegis.xml.MessageReader, org.apache.cxf.aegis.Context) throws org.apache.cxf.aegis.DatabindingException;
    Code:
       0: aload_0
       1: invokevirtual #12                 // Method getTypeInfo:()Lorg/apache/cxf/aegis/type/basic/BeanTypeInfo;
       4: astore_3
       5: aload_0
       6: invokevirtual #13                 // Method getTypeClass:()Ljava/lang/Class;
       9: astore        4
      11: aload_0
      12: getfield      #8                  // Field isInterface:Z
      15: ifeq          150
      18: aload_2
      19: invokevirtual #14                 // Method org/apache/cxf/aegis/Context.getGlobalContext:()Lorg/apache/cxf/aegis/AegisContext;
      22: invokevirtual #15                 // Method org/apache/cxf/aegis/AegisContext.getBeanImplementationMap:()Ljava/util/Map;
      25: aload         4
      27: invokeinterface #16,  2           // InterfaceMethod java/util/Map.get:(Ljava/lang/Object;)Ljava/lang/Object;
      32: checkcast     #17                 // class java/lang/String
      35: astore        7
      37: aload         7
      39: ifnonnull     79
      42: new           #18                 // class org/apache/cxf/aegis/type/basic/InterfaceInvocationHandler
      45: dup
      46: invokespecial #19                 // Method org/apache/cxf/aegis/type/basic/InterfaceInvocationHandler."<init>":()V
      49: astore        8
      51: aload         4
      53: invokevirtual #20                 // Method java/lang/Class.getClassLoader:()Ljava/lang/ClassLoader;
      56: iconst_1
      57: anewarray     #6                  // class java/lang/Class
      60: dup
      61: iconst_0
      62: aload         4
      64: aastore
      65: aload         8
      67: invokestatic  #21                 // Method java/lang/reflect/Proxy.newProxyInstance:(Ljava/lang/ClassLoader;[Ljava/lang/Class;Ljava/lang/reflect/InvocationHandler;)Ljava/lang/Object;
      70: astore        5
      72: aload         8
      74: astore        6
      76: goto          147
      79: aload         7
      81: aload_0
      82: invokevirtual #22                 // Method java/lang/Object.getClass:()Ljava/lang/Class;
      85: invokestatic  #23                 // Method org/apache/cxf/common/classloader/ClassLoaderUtils.loadClass:(Ljava/lang/String;Ljava/lang/Class;)Ljava/lang/Class;
      88: astore        4
      90: aload         4
      92: invokevirtual #24                 // Method java/lang/Class.newInstance:()Ljava/lang/Object;
      95: astore        5
      97: aload         5
      99: astore        6
     101: goto          147
     104: astore        8
     106: new           #26                 // class org/apache/cxf/aegis/DatabindingException
     109: dup
     110: new           #27                 // class java/lang/StringBuilder
     113: dup
     114: invokespecial #28                 // Method java/lang/StringBuilder."<init>":()V
     117: ldc           #29                 // String Could not find implementation class
     119: invokevirtual #30                 // Method java/lang/StringBuilder.append:(Ljava/lang/String;)Ljava/lang/StringBuilder;
     122: aload         7
     124: invokevirtual #30                 // Method java/lang/StringBuilder.append:(Ljava/lang/String;)Ljava/lang/StringBuilder;
     127: ldc           #31                 // String  for class
     129: invokevirtual #30                 // Method java/lang/StringBuilder.append:(Ljava/lang/String;)Ljava/lang/StringBuilder;
     132: aload         4
     134: invokevirtual #32                 // Method java/lang/Class.getName:()Ljava/lang/String;
     137: invokevirtual #30                 // Method java/lang/StringBuilder.append:(Ljava/lang/String;)Ljava/lang/StringBuilder;
     140: invokevirtual #33                 // Method java/lang/StringBuilder.toString:()Ljava/lang/String;
     143: invokespecial #34                 // Method org/apache/cxf/aegis/DatabindingException."<init>":(Ljava/lang/String;)V
     146: athrow
     147: goto          182
     150: aload_0
     151: getfield      #11                 // Field isException:Z
     154: ifeq          171
     157: aload_0
     158: aload_2
     159: invokevirtual #35                 // Method createFromFault:(Lorg/apache/cxf/aegis/Context;)Ljava/lang/Object;
     162: astore        5
     164: aload         5
     166: astore        6
     168: goto          182
     171: aload         4
     173: invokevirtual #24                 // Method java/lang/Class.newInstance:()Ljava/lang/Object;
     176: astore        5
     178: aload         5
     180: astore        6
     182: aload_1
     183: invokeinterface #36,  1           // InterfaceMethod org/apache/cxf/aegis/xml/MessageReader.hasMoreAttributeReaders:()Z
     188: ifeq          247
     191: aload_1
     192: invokeinterface #37,  1           // InterfaceMethod org/apache/cxf/aegis/xml/MessageReader.getNextAttributeReader:()Lorg/apache/cxf/aegis/xml/MessageReader;
     197: astore        7
     199: aload         7
     201: invokeinterface #38,  1           // InterfaceMethod org/apache/cxf/aegis/xml/MessageReader.getName:()Ljavax/xml/namespace/QName;
     206: astore        8
     208: aload_3
     209: aload         8
     211: invokevirtual #39                 // Method org/apache/cxf/aegis/type/basic/BeanTypeInfo.getType:(Ljavax/xml/namespace/QName;)Lorg/apache/cxf/aegis/type/AegisType;
     214: astore        9
     216: aload         9
     218: ifnull        244
     221: aload         9
     223: aload         7
     225: aload_2
     226: invokevirtual #40                 // Method org/apache/cxf/aegis/type/AegisType.readObject:(Lorg/apache/cxf/aegis/xml/MessageReader;Lorg/apache/cxf/aegis/Context;)Ljava/lang/Object;
     229: astore        10
     231: aload_0
     232: aload         8
     234: aload         6
     236: aload         10
     238: aload         4
     240: aload_3
     241: invokevirtual #41                 // Method writeProperty:(Ljavax/xml/namespace/QName;Ljava/lang/Object;Ljava/lang/Object;Ljava/lang/Class;Lorg/apache/cxf/aegis/type/basic/BeanTypeInfo;)V
     244: goto          182
     247: aload_1
     248: invokeinterface #42,  1           // InterfaceMethod org/apache/cxf/aegis/xml/MessageReader.hasMoreElementReaders:()Z
     253: ifeq          465
     256: aload_1
     257: invokeinterface #43,  1           // InterfaceMethod org/apache/cxf/aegis/xml/MessageReader.getNextElementReader:()Lorg/apache/cxf/aegis/xml/MessageReader;
     262: astore        7
     264: aload         7
     266: invokeinterface #38,  1           // InterfaceMethod org/apache/cxf/aegis/xml/MessageReader.getName:()Ljavax/xml/namespace/QName;
     271: astore        8
     273: aload_0
     274: aload         8
     276: invokevirtual #44                 // Method getBeanTypeInfoWithProperty:(Ljavax/xml/namespace/QName;)Lorg/apache/cxf/aegis/type/basic/BeanTypeInfo;
     279: astore        9
     281: aload_0
     282: aload         8
     284: aload         9
     286: aload         7
     288: aload_2
     289: invokevirtual #45                 // Method getElementType:(Ljavax/xml/namespace/QName;Lorg/apache/cxf/aegis/type/basic/BeanTypeInfo;Lorg/apache/cxf/aegis/xml/MessageReader;Lorg/apache/cxf/aegis/Context;)Lorg/apache/cxf/aegis/type/AegisType;
     292: astore        10
     294: aload         10
     296: ifnull        455
     299: aload         7
     301: invokeinterface #46,  1           // InterfaceMethod org/apache/cxf/aegis/xml/MessageReader.isXsiNil:()Z
     306: ifne          397
     309: aload         10
     311: invokevirtual #47                 // Method org/apache/cxf/aegis/type/AegisType.isFlatArray:()Z
     314: ifeq          370
     317: aload         10
     319: checkcast     #48                 // class org/apache/cxf/aegis/type/basic/ArrayType
     322: astore        12
     324: aload_3
     325: aload         8
     327: invokevirtual #49                 // Method org/apache/cxf/aegis/type/basic/BeanTypeInfo.getPropertyDescriptorFromMappedName:(Ljavax/xml/namespace/QName;)Ljava/beans/PropertyDescriptor;
     330: astore        13
     332: ldc_w         #50                 // class java/util/List
     335: aload         13
     337: invokevirtual #51                 // Method java/beans/PropertyDescriptor.getPropertyType:()Ljava/lang/Class;
     340: invokevirtual #10                 // Method java/lang/Class.isAssignableFrom:(Ljava/lang/Class;)Z
     343: istore        14
     345: aload         12
     347: aload         7
     349: aload         8
     351: aload_2
     352: iload         14
     354: ifne          361
     357: iconst_1
     358: goto          362
     361: iconst_0
     362: invokevirtual #52                 // Method org/apache/cxf/aegis/type/basic/ArrayType.readObject:(Lorg/apache/cxf/aegis/xml/MessageReader;Ljavax/xml/namespace/QName;Lorg/apache/cxf/aegis/Context;Z)Ljava/lang/Object;
     365: astore        11
     367: goto          380
     370: aload         10
     372: aload         7
     374: aload_2
     375: invokevirtual #40                 // Method org/apache/cxf/aegis/type/AegisType.readObject:(Lorg/apache/cxf/aegis/xml/MessageReader;Lorg/apache/cxf/aegis/Context;)Ljava/lang/Object;
     378: astore        11
     380: aload_0
     381: aload         8
     383: aload         6
     385: aload         11
     387: aload         4
     389: aload         9
     391: invokevirtual #41                 // Method writeProperty:(Ljavax/xml/namespace/QName;Ljava/lang/Object;Ljava/lang/Object;Ljava/lang/Class;Lorg/apache/cxf/aegis/type/basic/BeanTypeInfo;)V
     394: goto          462
     397: aload_0
     398: invokevirtual #53                 // Method alwaysAllowNillables:()Z
     401: ifne          445
     404: aload         9
     406: aload         8
     408: invokevirtual #54                 // Method org/apache/cxf/aegis/type/basic/BeanTypeInfo.isNillable:(Ljavax/xml/namespace/QName;)Z
     411: ifne          445
     414: new           #26                 // class org/apache/cxf/aegis/DatabindingException
     417: dup
     418: new           #27                 // class java/lang/StringBuilder
     421: dup
     422: invokespecial #28                 // Method java/lang/StringBuilder."<init>":()V
     425: aload         8
     427: invokevirtual #55                 // Method javax/xml/namespace/QName.getLocalPart:()Ljava/lang/String;
     430: invokevirtual #30                 // Method java/lang/StringBuilder.append:(Ljava/lang/String;)Ljava/lang/StringBuilder;
     433: ldc           #56                 // String  is nil, but not nillable.
     435: invokevirtual #30                 // Method java/lang/StringBuilder.append:(Ljava/lang/String;)Ljava/lang/StringBuilder;
     438: invokevirtual #33                 // Method java/lang/StringBuilder.toString:()Ljava/lang/String;
     441: invokespecial #34                 // Method org/apache/cxf/aegis/DatabindingException."<init>":(Ljava/lang/String;)V
     444: athrow
     445: aload         7
     447: invokeinterface #57,  1           // InterfaceMethod org/apache/cxf/aegis/xml/MessageReader.readToEnd:()V
     452: goto          462
     455: aload         7
     457: invokeinterface #57,  1           // InterfaceMethod org/apache/cxf/aegis/xml/MessageReader.readToEnd:()V
     462: goto          247
     465: aload         5
     467: areturn
     468: astore        4
     470: new           #26                 // class org/apache/cxf/aegis/DatabindingException
     473: dup
     474: new           #27                 // class java/lang/StringBuilder
     477: dup
     478: invokespecial #28                 // Method java/lang/StringBuilder."<init>":()V
     481: ldc           #59                 // String Illegal access.
     483: invokevirtual #30                 // Method java/lang/StringBuilder.append:(Ljava/lang/String;)Ljava/lang/StringBuilder;
     486: aload         4
     488: invokevirtual #60                 // Method java/lang/IllegalAccessException.getMessage:()Ljava/lang/String;
     491: invokevirtual #30                 // Method java/lang/StringBuilder.append:(Ljava/lang/String;)Ljava/lang/StringBuilder;
     494: invokevirtual #33                 // Method java/lang/StringBuilder.toString:()Ljava/lang/String;
     497: aload         4
     499: invokespecial #61                 // Method org/apache/cxf/aegis/DatabindingException."<init>":(Ljava/lang/String;Ljava/lang/Throwable;)V
     502: athrow
     503: astore        4
     505: new           #26                 // class org/apache/cxf/aegis/DatabindingException
     508: dup
     509: new           #27                 // class java/lang/StringBuilder
     512: dup
     513: invokespecial #28                 // Method java/lang/StringBuilder."<init>":()V
     516: ldc           #63                 // String Couldn\'t instantiate class.
     518: invokevirtual #30                 // Method java/lang/StringBuilder.append:(Ljava/lang/String;)Ljava/lang/StringBuilder;
     521: aload         4
     523: invokevirtual #64                 // Method java/lang/InstantiationException.getMessage:()Ljava/lang/String;
     526: invokevirtual #30                 // Method java/lang/StringBuilder.append:(Ljava/lang/String;)Ljava/lang/StringBuilder;
     529: invokevirtual #33                 // Method java/lang/StringBuilder.toString:()Ljava/lang/String;
     532: aload         4
     534: invokespecial #61                 // Method org/apache/cxf/aegis/DatabindingException."<init>":(Ljava/lang/String;Ljava/lang/Throwable;)V
     537: athrow
     538: astore        4
     540: new           #26                 // class org/apache/cxf/aegis/DatabindingException
     543: dup
     544: new           #27                 // class java/lang/StringBuilder
     547: dup
     548: invokespecial #28                 // Method java/lang/StringBuilder."<init>":()V
     551: ldc           #59                 // String Illegal access.
     553: invokevirtual #30                 // Method java/lang/StringBuilder.append:(Ljava/lang/String;)Ljava/lang/StringBuilder;
     556: aload         4
     558: invokevirtual #66                 // Method java/lang/SecurityException.getMessage:()Ljava/lang/String;
     561: invokevirtual #30                 // Method java/lang/StringBuilder.append:(Ljava/lang/String;)Ljava/lang/StringBuilder;
     564: invokevirtual #33                 // Method java/lang/StringBuilder.toString:()Ljava/lang/String;
     567: aload         4
     569: invokespecial #61                 // Method org/apache/cxf/aegis/DatabindingException."<init>":(Ljava/lang/String;Ljava/lang/Throwable;)V
     572: athrow
     573: astore        4
     575: new           #26                 // class org/apache/cxf/aegis/DatabindingException
     578: dup
     579: new           #27                 // class java/lang/StringBuilder
     582: dup
     583: invokespecial #28                 // Method java/lang/StringBuilder."<init>":()V
     586: ldc           #68                 // String Illegal argument.
     588: invokevirtual #30                 // Method java/lang/StringBuilder.append:(Ljava/lang/String;)Ljava/lang/StringBuilder;
     591: aload         4
     593: invokevirtual #69                 // Method java/lang/IllegalArgumentException.getMessage:()Ljava/lang/String;
     596: invokevirtual #30                 // Method java/lang/StringBuilder.append:(Ljava/lang/String;)Ljava/lang/StringBuilder;
     599: invokevirtual #33                 // Method java/lang/StringBuilder.toString:()Ljava/lang/String;
     602: aload         4
     604: invokespecial #61                 // Method org/apache/cxf/aegis/DatabindingException."<init>":(Ljava/lang/String;Ljava/lang/Throwable;)V
     607: athrow
     608: astore        4
     610: new           #26                 // class org/apache/cxf/aegis/DatabindingException
     613: dup
     614: new           #27                 // class java/lang/StringBuilder
     617: dup
     618: invokespecial #28                 // Method java/lang/StringBuilder."<init>":()V
     621: ldc           #71                 // String Could not create class:
     623: invokevirtual #30                 // Method java/lang/StringBuilder.append:(Ljava/lang/String;)Ljava/lang/StringBuilder;
     626: aload         4
     628: invokevirtual #72                 // Method java/lang/reflect/InvocationTargetException.getMessage:()Ljava/lang/String;
     631: invokevirtual #30                 // Method java/lang/StringBuilder.append:(Ljava/lang/String;)Ljava/lang/StringBuilder;
     634: invokevirtual #33                 // Method java/lang/StringBuilder.toString:()Ljava/lang/String;
     637: aload         4
     639: invokespecial #61                 // Method org/apache/cxf/aegis/DatabindingException."<init>":(Ljava/lang/String;Ljava/lang/Throwable;)V
     642: athrow
    Exception table:
       from    to  target type
          79   101   104   Class java/lang/ClassNotFoundException
           5   467   468   Class java/lang/IllegalAccessException
           5   467   503   Class java/lang/InstantiationException
           5   467   538   Class java/lang/SecurityException
           5   467   573   Class java/lang/IllegalArgumentException
           5   467   608   Class java/lang/reflect/InvocationTargetException

  protected boolean alwaysAllowNillables();
    Code:
       0: iconst_0
       1: ireturn

  protected org.apache.cxf.aegis.type.AegisType getElementType(javax.xml.namespace.QName, org.apache.cxf.aegis.type.basic.BeanTypeInfo, org.apache.cxf.aegis.xml.MessageReader, org.apache.cxf.aegis.Context);
    Code:
       0: aload_2
       1: aload_1
       2: invokevirtual #39                 // Method org/apache/cxf/aegis/type/basic/BeanTypeInfo.getType:(Ljavax/xml/namespace/QName;)Lorg/apache/cxf/aegis/type/AegisType;
       5: astore        5
       7: aload_3
       8: invokeinterface #73,  1           // InterfaceMethod org/apache/cxf/aegis/xml/MessageReader.getXMLStreamReader:()Ljavax/xml/stream/XMLStreamReader;
      13: aload         4
      15: invokevirtual #14                 // Method org/apache/cxf/aegis/Context.getGlobalContext:()Lorg/apache/cxf/aegis/AegisContext;
      18: aload         5
      20: invokestatic  #74                 // Method org/apache/cxf/aegis/type/TypeUtil.getReadType:(Ljavax/xml/stream/XMLStreamReader;Lorg/apache/cxf/aegis/AegisContext;Lorg/apache/cxf/aegis/type/AegisType;)Lorg/apache/cxf/aegis/type/AegisType;
      23: astore        5
      25: aload         5
      27: areturn

  protected java.lang.Object createFromFault(org.apache.cxf.aegis.Context) throws java.lang.SecurityException, java.lang.InstantiationException, java.lang.IllegalAccessException, java.lang.IllegalArgumentException, java.lang.reflect.InvocationTargetException;
    Code:
       0: aload_0
       1: invokevirtual #13                 // Method getTypeClass:()Ljava/lang/Class;
       4: astore_2
       5: aload_1
       6: invokevirtual #75                 // Method org/apache/cxf/aegis/Context.getFault:()Lorg/apache/cxf/interceptor/Fault;
       9: astore        5
      11: aload_2
      12: iconst_2
      13: anewarray     #6                  // class java/lang/Class
      16: dup
      17: iconst_0
      18: ldc_w         #17                 // class java/lang/String
      21: aastore
      22: dup
      23: iconst_1
      24: ldc_w         #76                 // class java/lang/Throwable
      27: aastore
      28: invokevirtual #77                 // Method java/lang/Class.getConstructor:([Ljava/lang/Class;)Ljava/lang/reflect/Constructor;
      31: astore_3
      32: aload_3
      33: iconst_2
      34: anewarray     #78                 // class java/lang/Object
      37: dup
      38: iconst_0
      39: aload         5
      41: invokevirtual #79                 // Method org/apache/cxf/interceptor/Fault.getMessage:()Ljava/lang/String;
      44: aastore
      45: dup
      46: iconst_1
      47: aload         5
      49: aastore
      50: invokevirtual #80                 // Method java/lang/reflect/Constructor.newInstance:([Ljava/lang/Object;)Ljava/lang/Object;
      53: astore        4
      55: goto          152
      58: astore        6
      60: aload_2
      61: iconst_2
      62: anewarray     #6                  // class java/lang/Class
      65: dup
      66: iconst_0
      67: ldc_w         #17                 // class java/lang/String
      70: aastore
      71: dup
      72: iconst_1
      73: ldc_w         #9                  // class java/lang/Exception
      76: aastore
      77: invokevirtual #77                 // Method java/lang/Class.getConstructor:([Ljava/lang/Class;)Ljava/lang/reflect/Constructor;
      80: astore_3
      81: aload_3
      82: iconst_2
      83: anewarray     #78                 // class java/lang/Object
      86: dup
      87: iconst_0
      88: aload         5
      90: invokevirtual #79                 // Method org/apache/cxf/interceptor/Fault.getMessage:()Ljava/lang/String;
      93: aastore
      94: dup
      95: iconst_1
      96: aload         5
      98: aastore
      99: invokevirtual #80                 // Method java/lang/reflect/Constructor.newInstance:([Ljava/lang/Object;)Ljava/lang/Object;
     102: astore        4
     104: goto          152
     107: astore        7
     109: aload_2
     110: iconst_1
     111: anewarray     #6                  // class java/lang/Class
     114: dup
     115: iconst_0
     116: ldc_w         #17                 // class java/lang/String
     119: aastore
     120: invokevirtual #77                 // Method java/lang/Class.getConstructor:([Ljava/lang/Class;)Ljava/lang/reflect/Constructor;
     123: astore_3
     124: aload_3
     125: iconst_1
     126: anewarray     #78                 // class java/lang/Object
     129: dup
     130: iconst_0
     131: aload         5
     133: invokevirtual #79                 // Method org/apache/cxf/interceptor/Fault.getMessage:()Ljava/lang/String;
     136: aastore
     137: invokevirtual #80                 // Method java/lang/reflect/Constructor.newInstance:([Ljava/lang/Object;)Ljava/lang/Object;
     140: astore        4
     142: goto          152
     145: astore        8
     147: aload_2
     148: invokevirtual #24                 // Method java/lang/Class.newInstance:()Ljava/lang/Object;
     151: areturn
     152: aload         4
     154: areturn
    Exception table:
       from    to  target type
          11    55    58   Class java/lang/NoSuchMethodException
          60   104   107   Class java/lang/NoSuchMethodException
         109   142   145   Class java/lang/NoSuchMethodException

  protected void writeProperty(javax.xml.namespace.QName, java.lang.Object, java.lang.Object, java.lang.Class<?>, org.apache.cxf.aegis.type.basic.BeanTypeInfo) throws org.apache.cxf.aegis.DatabindingException;
    Code:
       0: aload_2
       1: instanceof    #18                 // class org/apache/cxf/aegis/type/basic/InterfaceInvocationHandler
       4: ifeq          24
       7: aload_2
       8: checkcast     #18                 // class org/apache/cxf/aegis/type/basic/InterfaceInvocationHandler
      11: astore        6
      13: aload         6
      15: aload_1
      16: invokevirtual #55                 // Method javax/xml/namespace/QName.getLocalPart:()Ljava/lang/String;
      19: aload_3
      20: invokevirtual #82                 // Method org/apache/cxf/aegis/type/basic/InterfaceInvocationHandler.writeProperty:(Ljava/lang/Object;Ljava/lang/Object;)V
      23: return
      24: aload         5
      26: aload_1
      27: invokevirtual #49                 // Method org/apache/cxf/aegis/type/basic/BeanTypeInfo.getPropertyDescriptorFromMappedName:(Ljavax/xml/namespace/QName;)Ljava/beans/PropertyDescriptor;
      30: astore        6
      32: aload         6
      34: invokevirtual #83                 // Method java/beans/PropertyDescriptor.getWriteMethod:()Ljava/lang/reflect/Method;
      37: astore        7
      39: aload         7
      41: ifnonnull     165
      44: aload_0
      45: invokevirtual #13                 // Method getTypeClass:()Ljava/lang/Class;
      48: invokevirtual #7                  // Method java/lang/Class.isInterface:()Z
      51: ifeq          64
      54: aload_0
      55: aload         4
      57: aload         6
      59: invokespecial #84                 // Method getWriteMethodFromImplClass:(Ljava/lang/Class;Ljava/beans/PropertyDescriptor;)Ljava/lang/reflect/Method;
      62: astore        7
      64: aload         7
      66: ifnonnull     121
      69: aload_3
      70: instanceof    #50                 // class java/util/List
      73: ifeq          121
      76: aload         6
      78: invokevirtual #85                 // Method java/beans/PropertyDescriptor.getReadMethod:()Ljava/lang/reflect/Method;
      81: astore        7
      83: aload         7
      85: aload_2
      86: iconst_0
      87: anewarray     #78                 // class java/lang/Object
      90: invokevirtual #86                 // Method java/lang/reflect/Method.invoke:(Ljava/lang/Object;[Ljava/lang/Object;)Ljava/lang/Object;
      93: checkcast     #50                 // class java/util/List
      96: invokestatic  #87                 // Method org/apache/cxf/helpers/CastUtils.cast:(Ljava/util/List;)Ljava/util/List;
      99: astore        8
     101: aload_3
     102: checkcast     #50                 // class java/util/List
     105: invokestatic  #87                 // Method org/apache/cxf/helpers/CastUtils.cast:(Ljava/util/List;)Ljava/util/List;
     108: astore        9
     110: aload         8
     112: aload         9
     114: invokeinterface #88,  2           // InterfaceMethod java/util/List.addAll:(Ljava/util/Collection;)Z
     119: pop
     120: return
     121: aload         7
     123: ifnonnull     165
     126: new           #26                 // class org/apache/cxf/aegis/DatabindingException
     129: dup
     130: new           #27                 // class java/lang/StringBuilder
     133: dup
     134: invokespecial #28                 // Method java/lang/StringBuilder."<init>":()V
     137: ldc           #89                 // String No write method for property
     139: invokevirtual #30                 // Method java/lang/StringBuilder.append:(Ljava/lang/String;)Ljava/lang/StringBuilder;
     142: aload_1
     143: invokevirtual #90                 // Method java/lang/StringBuilder.append:(Ljava/lang/Object;)Ljava/lang/StringBuilder;
     146: ldc           #91                 // String  in
     148: invokevirtual #30                 // Method java/lang/StringBuilder.append:(Ljava/lang/String;)Ljava/lang/StringBuilder;
     151: aload_2
     152: invokevirtual #22                 // Method java/lang/Object.getClass:()Ljava/lang/Class;
     155: invokevirtual #90                 // Method java/lang/StringBuilder.append:(Ljava/lang/Object;)Ljava/lang/StringBuilder;
     158: invokevirtual #33                 // Method java/lang/StringBuilder.toString:()Ljava/lang/String;
     161: invokespecial #34                 // Method org/apache/cxf/aegis/DatabindingException."<init>":(Ljava/lang/String;)V
     164: athrow
     165: aload         6
     167: invokevirtual #51                 // Method java/beans/PropertyDescriptor.getPropertyType:()Ljava/lang/Class;
     170: astore        8
     172: aload_3
     173: ifnonnull     184
     176: aload         8
     178: invokevirtual #92                 // Method java/lang/Class.isPrimitive:()Z
     181: ifeq          188
     184: aload_3
     185: ifnull        203
     188: aload         7
     190: aload_2
     191: iconst_1
     192: anewarray     #78                 // class java/lang/Object
     195: dup
     196: iconst_0
     197: aload_3
     198: aastore
     199: invokevirtual #86                 // Method java/lang/reflect/Method.invoke:(Ljava/lang/Object;[Ljava/lang/Object;)Ljava/lang/Object;
     202: pop
     203: goto          273
     206: astore        6
     208: aload         6
     210: instanceof    #26                 // class org/apache/cxf/aegis/DatabindingException
     213: ifeq          222
     216: aload         6
     218: checkcast     #26                 // class org/apache/cxf/aegis/DatabindingException
     221: athrow
     222: new           #26                 // class org/apache/cxf/aegis/DatabindingException
     225: dup
     226: new           #27                 // class java/lang/StringBuilder
     229: dup
     230: invokespecial #28                 // Method java/lang/StringBuilder."<init>":()V
     233: ldc           #93                 // String Couldn\'t set property
     235: invokevirtual #30                 // Method java/lang/StringBuilder.append:(Ljava/lang/String;)Ljava/lang/StringBuilder;
     238: aload_1
     239: invokevirtual #90                 // Method java/lang/StringBuilder.append:(Ljava/lang/Object;)Ljava/lang/StringBuilder;
     242: ldc           #94                 // String  on
     244: invokevirtual #30                 // Method java/lang/StringBuilder.append:(Ljava/lang/String;)Ljava/lang/StringBuilder;
     247: aload_2
     248: invokevirtual #90                 // Method java/lang/StringBuilder.append:(Ljava/lang/Object;)Ljava/lang/StringBuilder;
     251: ldc           #95                 // String .
     253: invokevirtual #30                 // Method java/lang/StringBuilder.append:(Ljava/lang/String;)Ljava/lang/StringBuilder;
     256: aload         6
     258: invokevirtual #96                 // Method java/lang/Exception.getMessage:()Ljava/lang/String;
     261: invokevirtual #30                 // Method java/lang/StringBuilder.append:(Ljava/lang/String;)Ljava/lang/StringBuilder;
     264: invokevirtual #33                 // Method java/lang/StringBuilder.toString:()Ljava/lang/String;
     267: aload         6
     269: invokespecial #61                 // Method org/apache/cxf/aegis/DatabindingException."<init>":(Ljava/lang/String;Ljava/lang/Throwable;)V
     272: athrow
     273: return
    Exception table:
       from    to  target type
          24   120   206   Class java/lang/Exception
         121   203   206   Class java/lang/Exception

  private java.lang.reflect.Method getWriteMethodFromImplClass(java.lang.Class<?>, java.beans.PropertyDescriptor) throws java.lang.Exception;
    Code:
       0: aload_2
       1: invokevirtual #97                 // Method java/beans/PropertyDescriptor.getName:()Ljava/lang/String;
       4: astore_3
       5: new           #27                 // class java/lang/StringBuilder
       8: dup
       9: invokespecial #28                 // Method java/lang/StringBuilder."<init>":()V
      12: ldc           #98                 // String set
      14: invokevirtual #30                 // Method java/lang/StringBuilder.append:(Ljava/lang/String;)Ljava/lang/StringBuilder;
      17: aload_3
      18: iconst_0
      19: iconst_1
      20: invokevirtual #99                 // Method java/lang/String.substring:(II)Ljava/lang/String;
      23: invokevirtual #100                // Method java/lang/String.toUpperCase:()Ljava/lang/String;
      26: invokevirtual #30                 // Method java/lang/StringBuilder.append:(Ljava/lang/String;)Ljava/lang/StringBuilder;
      29: aload_3
      30: iconst_1
      31: invokevirtual #101                // Method java/lang/String.substring:(I)Ljava/lang/String;
      34: invokevirtual #30                 // Method java/lang/StringBuilder.append:(Ljava/lang/String;)Ljava/lang/StringBuilder;
      37: invokevirtual #33                 // Method java/lang/StringBuilder.toString:()Ljava/lang/String;
      40: astore_3
      41: aload_1
      42: aload_3
      43: iconst_1
      44: anewarray     #6                  // class java/lang/Class
      47: dup
      48: iconst_0
      49: aload_2
      50: invokevirtual #51                 // Method java/beans/PropertyDescriptor.getPropertyType:()Ljava/lang/Class;
      53: aastore
      54: invokevirtual #102                // Method java/lang/Class.getMethod:(Ljava/lang/String;[Ljava/lang/Class;)Ljava/lang/reflect/Method;
      57: areturn

  void writeObjectFromObjectType(java.lang.Object, org.apache.cxf.aegis.xml.MessageWriter, org.apache.cxf.aegis.Context, boolean);
    Code:
       0: aload_0
       1: aload_1
       2: aload_2
       3: aload_3
       4: iload         4
       6: invokespecial #103                // Method writeObjectInternal:(Ljava/lang/Object;Lorg/apache/cxf/aegis/xml/MessageWriter;Lorg/apache/cxf/aegis/Context;Z)V
       9: return

  public void writeObject(java.lang.Object, org.apache.cxf.aegis.xml.MessageWriter, org.apache.cxf.aegis.Context) throws org.apache.cxf.aegis.DatabindingException;
    Code:
       0: aload_0
       1: aload_1
       2: aload_2
       3: aload_3
       4: iconst_0
       5: invokespecial #103                // Method writeObjectInternal:(Ljava/lang/Object;Lorg/apache/cxf/aegis/xml/MessageWriter;Lorg/apache/cxf/aegis/Context;Z)V
       8: return

  private void writeObjectInternal(java.lang.Object, org.apache.cxf.aegis.xml.MessageWriter, org.apache.cxf.aegis.Context, boolean) throws org.apache.cxf.aegis.DatabindingException;
    Code:
       0: aload_1
       1: ifnonnull     5
       4: return
       5: aload_0
       6: invokevirtual #12                 // Method getTypeInfo:()Lorg/apache/cxf/aegis/type/basic/BeanTypeInfo;
       9: astore        5
      11: iload         4
      13: ifne          44
      16: aload_1
      17: invokevirtual #22                 // Method java/lang/Object.getClass:()Ljava/lang/Class;
      20: aload_0
      21: invokevirtual #13                 // Method getTypeClass:()Ljava/lang/Class;
      24: if_acmpne     44
      27: aload_3
      28: invokevirtual #104                // Method org/apache/cxf/aegis/Context.isWriteXsiTypes:()Z
      31: ifeq          44
      34: aload_2
      35: aload_0
      36: invokevirtual #105                // Method getSchemaType:()Ljavax/xml/namespace/QName;
      39: invokeinterface #106,  2          // InterfaceMethod org/apache/cxf/aegis/xml/MessageWriter.writeXsiType:(Ljavax/xml/namespace/QName;)V
      44: aload         5
      46: invokevirtual #107                // Method org/apache/cxf/aegis/type/basic/BeanTypeInfo.getAttributes:()Ljava/util/List;
      49: invokeinterface #108,  1          // InterfaceMethod java/util/List.iterator:()Ljava/util/Iterator;
      54: astore        6
      56: aload         6
      58: invokeinterface #109,  1          // InterfaceMethod java/util/Iterator.hasNext:()Z
      63: ifeq          192
      66: aload         6
      68: invokeinterface #110,  1          // InterfaceMethod java/util/Iterator.next:()Ljava/lang/Object;
      73: checkcast     #111                // class javax/xml/namespace/QName
      76: astore        7
      78: aload_0
      79: aload         5
      81: aload         7
      83: invokespecial #112                // Method isInheritedProperty:(Lorg/apache/cxf/aegis/type/basic/BeanTypeInfo;Ljavax/xml/namespace/QName;)Z
      86: ifeq          92
      89: goto          56
      92: aload_0
      93: aload_1
      94: aload         7
      96: invokevirtual #113                // Method readProperty:(Ljava/lang/Object;Ljavax/xml/namespace/QName;)Ljava/lang/Object;
      99: astore        8
     101: aload         8
     103: ifnull        189
     106: aload_0
     107: aload         5
     109: aload         7
     111: invokespecial #114                // Method getType:(Lorg/apache/cxf/aegis/type/basic/BeanTypeInfo;Ljavax/xml/namespace/QName;)Lorg/apache/cxf/aegis/type/AegisType;
     114: astore        9
     116: aload         9
     118: ifnonnull     162
     121: new           #26                 // class org/apache/cxf/aegis/DatabindingException
     124: dup
     125: new           #27                 // class java/lang/StringBuilder
     128: dup
     129: invokespecial #28                 // Method java/lang/StringBuilder."<init>":()V
     132: ldc           #115                // String Couldn\'t find type for
     134: invokevirtual #30                 // Method java/lang/StringBuilder.append:(Ljava/lang/String;)Ljava/lang/StringBuilder;
     137: aload         8
     139: invokevirtual #22                 // Method java/lang/Object.getClass:()Ljava/lang/Class;
     142: invokevirtual #90                 // Method java/lang/StringBuilder.append:(Ljava/lang/Object;)Ljava/lang/StringBuilder;
     145: ldc           #116                // String  for property
     147: invokevirtual #30                 // Method java/lang/StringBuilder.append:(Ljava/lang/String;)Ljava/lang/StringBuilder;
     150: aload         7
     152: invokevirtual #90                 // Method java/lang/StringBuilder.append:(Ljava/lang/Object;)Ljava/lang/StringBuilder;
     155: invokevirtual #33                 // Method java/lang/StringBuilder.toString:()Ljava/lang/String;
     158: invokespecial #34                 // Method org/apache/cxf/aegis/DatabindingException."<init>":(Ljava/lang/String;)V
     161: athrow
     162: aload_2
     163: aload         7
     165: invokeinterface #117,  2          // InterfaceMethod org/apache/cxf/aegis/xml/MessageWriter.getAttributeWriter:(Ljavax/xml/namespace/QName;)Lorg/apache/cxf/aegis/xml/MessageWriter;
     170: astore        10
     172: aload         9
     174: aload         8
     176: aload         10
     178: aload_3
     179: invokevirtual #118                // Method org/apache/cxf/aegis/type/AegisType.writeObject:(Ljava/lang/Object;Lorg/apache/cxf/aegis/xml/MessageWriter;Lorg/apache/cxf/aegis/Context;)V
     182: aload         10
     184: invokeinterface #119,  1          // InterfaceMethod org/apache/cxf/aegis/xml/MessageWriter.close:()V
     189: goto          56
     192: aload         5
     194: invokevirtual #120                // Method org/apache/cxf/aegis/type/basic/BeanTypeInfo.isExtension:()Z
     197: ifeq          219
     200: aload_0
     201: invokevirtual #121                // Method getSuperType:()Lorg/apache/cxf/aegis/type/AegisType;
     204: astore        6
     206: aload         6
     208: ifnull        219
     211: aload         6
     213: aload_1
     214: aload_2
     215: aload_3
     216: invokevirtual #118                // Method org/apache/cxf/aegis/type/AegisType.writeObject:(Ljava/lang/Object;Lorg/apache/cxf/aegis/xml/MessageWriter;Lorg/apache/cxf/aegis/Context;)V
     219: aload         5
     221: invokevirtual #122                // Method org/apache/cxf/aegis/type/basic/BeanTypeInfo.getElements:()Ljava/util/List;
     224: invokeinterface #108,  1          // InterfaceMethod java/util/List.iterator:()Ljava/util/Iterator;
     229: astore        6
     231: aload         6
     233: invokeinterface #109,  1          // InterfaceMethod java/util/Iterator.hasNext:()Z
     238: ifeq          403
     241: aload         6
     243: invokeinterface #110,  1          // InterfaceMethod java/util/Iterator.next:()Ljava/lang/Object;
     248: checkcast     #111                // class javax/xml/namespace/QName
     251: astore        7
     253: aload_0
     254: aload         5
     256: aload         7
     258: invokespecial #112                // Method isInheritedProperty:(Lorg/apache/cxf/aegis/type/basic/BeanTypeInfo;Ljavax/xml/namespace/QName;)Z
     261: ifeq          267
     264: goto          231
     267: aload_0
     268: aload_1
     269: aload         7
     271: invokevirtual #113                // Method readProperty:(Ljava/lang/Object;Ljavax/xml/namespace/QName;)Ljava/lang/Object;
     274: astore        8
     276: aload_0
     277: aload         5
     279: aload         7
     281: invokespecial #114                // Method getType:(Lorg/apache/cxf/aegis/type/basic/BeanTypeInfo;Ljavax/xml/namespace/QName;)Lorg/apache/cxf/aegis/type/AegisType;
     284: astore        9
     286: aload_3
     287: invokevirtual #14                 // Method org/apache/cxf/aegis/Context.getGlobalContext:()Lorg/apache/cxf/aegis/AegisContext;
     290: aload         8
     292: aload         9
     294: invokestatic  #123                // Method org/apache/cxf/aegis/type/TypeUtil.getWriteType:(Lorg/apache/cxf/aegis/AegisContext;Ljava/lang/Object;Lorg/apache/cxf/aegis/type/AegisType;)Lorg/apache/cxf/aegis/type/AegisType;
     297: astore        10
     299: aload         8
     301: ifnull        365
     304: aload         10
     306: ifnonnull     350
     309: new           #26                 // class org/apache/cxf/aegis/DatabindingException
     312: dup
     313: new           #27                 // class java/lang/StringBuilder
     316: dup
     317: invokespecial #28                 // Method java/lang/StringBuilder."<init>":()V
     320: ldc           #115                // String Couldn\'t find type for
     322: invokevirtual #30                 // Method java/lang/StringBuilder.append:(Ljava/lang/String;)Ljava/lang/StringBuilder;
     325: aload         8
     327: invokevirtual #22                 // Method java/lang/Object.getClass:()Ljava/lang/Class;
     330: invokevirtual #90                 // Method java/lang/StringBuilder.append:(Ljava/lang/Object;)Ljava/lang/StringBuilder;
     333: ldc           #116                // String  for property
     335: invokevirtual #30                 // Method java/lang/StringBuilder.append:(Ljava/lang/String;)Ljava/lang/StringBuilder;
     338: aload         7
     340: invokevirtual #90                 // Method java/lang/StringBuilder.append:(Ljava/lang/Object;)Ljava/lang/StringBuilder;
     343: invokevirtual #33                 // Method java/lang/StringBuilder.toString:()Ljava/lang/String;
     346: invokespecial #34                 // Method org/apache/cxf/aegis/DatabindingException."<init>":(Ljava/lang/String;)V
     349: athrow
     350: aload_0
     351: aload         7
     353: aload         8
     355: aload         10
     357: aload_2
     358: aload_3
     359: invokevirtual #124                // Method writeElement:(Ljavax/xml/namespace/QName;Ljava/lang/Object;Lorg/apache/cxf/aegis/type/AegisType;Lorg/apache/cxf/aegis/xml/MessageWriter;Lorg/apache/cxf/aegis/Context;)V
     362: goto          400
     365: aload         5
     367: aload         7
     369: invokevirtual #54                 // Method org/apache/cxf/aegis/type/basic/BeanTypeInfo.isNillable:(Ljavax/xml/namespace/QName;)Z
     372: ifeq          400
     375: aload_0
     376: aload_2
     377: aload         7
     379: aload         10
     381: invokespecial #125                // Method getWriter:(Lorg/apache/cxf/aegis/xml/MessageWriter;Ljavax/xml/namespace/QName;Lorg/apache/cxf/aegis/type/AegisType;)Lorg/apache/cxf/aegis/xml/MessageWriter;
     384: astore        11
     386: aload         11
     388: invokeinterface #126,  1          // InterfaceMethod org/apache/cxf/aegis/xml/MessageWriter.writeXsiNil:()V
     393: aload         11
     395: invokeinterface #119,  1          // InterfaceMethod org/apache/cxf/aegis/xml/MessageWriter.close:()V
     400: goto          231
     403: return

  private boolean isInheritedProperty(org.apache.cxf.aegis.type.basic.BeanTypeInfo, javax.xml.namespace.QName);
    Code:
       0: aload_1
       1: invokevirtual #120                // Method org/apache/cxf/aegis/type/basic/BeanTypeInfo.isExtension:()Z
       4: ifeq          29
       7: aload_1
       8: aload_2
       9: invokevirtual #49                 // Method org/apache/cxf/aegis/type/basic/BeanTypeInfo.getPropertyDescriptorFromMappedName:(Ljavax/xml/namespace/QName;)Ljava/beans/PropertyDescriptor;
      12: invokevirtual #85                 // Method java/beans/PropertyDescriptor.getReadMethod:()Ljava/lang/reflect/Method;
      15: invokevirtual #127                // Method java/lang/reflect/Method.getDeclaringClass:()Ljava/lang/Class;
      18: aload_1
      19: invokevirtual #3                  // Method org/apache/cxf/aegis/type/basic/BeanTypeInfo.getTypeClass:()Ljava/lang/Class;
      22: if_acmpeq     29
      25: iconst_1
      26: goto          30
      29: iconst_0
      30: ireturn

  protected void writeElement(javax.xml.namespace.QName, java.lang.Object, org.apache.cxf.aegis.type.AegisType, org.apache.cxf.aegis.xml.MessageWriter, org.apache.cxf.aegis.Context);
    Code:
       0: aload_3
       1: invokevirtual #47                 // Method org/apache/cxf/aegis/type/AegisType.isFlatArray:()Z
       4: ifne          39
       7: aconst_null
       8: astore        6
      10: aload_0
      11: aload         4
      13: aload_1
      14: aload_3
      15: invokespecial #125                // Method getWriter:(Lorg/apache/cxf/aegis/xml/MessageWriter;Ljavax/xml/namespace/QName;Lorg/apache/cxf/aegis/type/AegisType;)Lorg/apache/cxf/aegis/xml/MessageWriter;
      18: astore        6
      20: aload_3
      21: aload_2
      22: aload         6
      24: aload         5
      26: invokevirtual #118                // Method org/apache/cxf/aegis/type/AegisType.writeObject:(Ljava/lang/Object;Lorg/apache/cxf/aegis/xml/MessageWriter;Lorg/apache/cxf/aegis/Context;)V
      29: aload         6
      31: invokeinterface #119,  1          // InterfaceMethod org/apache/cxf/aegis/xml/MessageWriter.close:()V
      36: goto          56
      39: aload_3
      40: checkcast     #48                 // class org/apache/cxf/aegis/type/basic/ArrayType
      43: astore        6
      45: aload         6
      47: aload_2
      48: aload         4
      50: aload         5
      52: aload_1
      53: invokevirtual #128                // Method org/apache/cxf/aegis/type/basic/ArrayType.writeObject:(Ljava/lang/Object;Lorg/apache/cxf/aegis/xml/MessageWriter;Lorg/apache/cxf/aegis/Context;Ljavax/xml/namespace/QName;)V
      56: return

  private org.apache.cxf.aegis.xml.MessageWriter getWriter(org.apache.cxf.aegis.xml.MessageWriter, javax.xml.namespace.QName, org.apache.cxf.aegis.type.AegisType);
    Code:
       0: aload_1
       1: aload_2
       2: invokeinterface #129,  2          // InterfaceMethod org/apache/cxf/aegis/xml/MessageWriter.getElementWriter:(Ljavax/xml/namespace/QName;)Lorg/apache/cxf/aegis/xml/MessageWriter;
       7: astore        4
       9: aload         4
      11: areturn

  protected java.lang.Object readProperty(java.lang.Object, javax.xml.namespace.QName);
    Code:
       0: aload_0
       1: invokevirtual #12                 // Method getTypeInfo:()Lorg/apache/cxf/aegis/type/basic/BeanTypeInfo;
       4: aload_2
       5: invokevirtual #49                 // Method org/apache/cxf/aegis/type/basic/BeanTypeInfo.getPropertyDescriptorFromMappedName:(Ljavax/xml/namespace/QName;)Ljava/beans/PropertyDescriptor;
       8: astore_3
       9: aload_3
      10: invokevirtual #85                 // Method java/beans/PropertyDescriptor.getReadMethod:()Ljava/lang/reflect/Method;
      13: astore        4
      15: aload         4
      17: ifnonnull     62
      20: new           #26                 // class org/apache/cxf/aegis/DatabindingException
      23: dup
      24: new           #27                 // class java/lang/StringBuilder
      27: dup
      28: invokespecial #28                 // Method java/lang/StringBuilder."<init>":()V
      31: ldc           #130                // String No read method for property
      33: invokevirtual #30                 // Method java/lang/StringBuilder.append:(Ljava/lang/String;)Ljava/lang/StringBuilder;
      36: aload_2
      37: invokevirtual #90                 // Method java/lang/StringBuilder.append:(Ljava/lang/Object;)Ljava/lang/StringBuilder;
      40: ldc           #131                // String  in class
      42: invokevirtual #30                 // Method java/lang/StringBuilder.append:(Ljava/lang/String;)Ljava/lang/StringBuilder;
      45: aload_1
      46: invokevirtual #22                 // Method java/lang/Object.getClass:()Ljava/lang/Class;
      49: invokevirtual #32                 // Method java/lang/Class.getName:()Ljava/lang/String;
      52: invokevirtual #30                 // Method java/lang/StringBuilder.append:(Ljava/lang/String;)Ljava/lang/StringBuilder;
      55: invokevirtual #33                 // Method java/lang/StringBuilder.toString:()Ljava/lang/String;
      58: invokespecial #34                 // Method org/apache/cxf/aegis/DatabindingException."<init>":(Ljava/lang/String;)V
      61: athrow
      62: aload         4
      64: aload_1
      65: iconst_0
      66: anewarray     #78                 // class java/lang/Object
      69: invokevirtual #86                 // Method java/lang/reflect/Method.invoke:(Ljava/lang/Object;[Ljava/lang/Object;)Ljava/lang/Object;
      72: areturn
      73: astore_3
      74: new           #26                 // class org/apache/cxf/aegis/DatabindingException
      77: dup
      78: new           #27                 // class java/lang/StringBuilder
      81: dup
      82: invokespecial #28                 // Method java/lang/StringBuilder."<init>":()V
      85: ldc           #132                // String Couldn\'t get property
      87: invokevirtual #30                 // Method java/lang/StringBuilder.append:(Ljava/lang/String;)Ljava/lang/StringBuilder;
      90: aload_2
      91: invokevirtual #90                 // Method java/lang/StringBuilder.append:(Ljava/lang/Object;)Ljava/lang/StringBuilder;
      94: ldc           #133                // String  from bean
      96: invokevirtual #30                 // Method java/lang/StringBuilder.append:(Ljava/lang/String;)Ljava/lang/StringBuilder;
      99: aload_1
     100: invokevirtual #90                 // Method java/lang/StringBuilder.append:(Ljava/lang/Object;)Ljava/lang/StringBuilder;
     103: invokevirtual #33                 // Method java/lang/StringBuilder.toString:()Ljava/lang/String;
     106: aload_3
     107: invokespecial #61                 // Method org/apache/cxf/aegis/DatabindingException."<init>":(Ljava/lang/String;Ljava/lang/Throwable;)V
     110: athrow
    Exception table:
       from    to  target type
           0    72    73   Class java/lang/Exception

  private org.apache.cxf.aegis.type.AegisType getType(org.apache.cxf.aegis.type.basic.BeanTypeInfo, javax.xml.namespace.QName);
    Code:
       0: aload_1
       1: aload_2
       2: invokevirtual #39                 // Method org/apache/cxf/aegis/type/basic/BeanTypeInfo.getType:(Ljavax/xml/namespace/QName;)Lorg/apache/cxf/aegis/type/AegisType;
       5: astore_3
       6: aload_3
       7: ifnonnull     52
      10: new           #134                // class java/lang/NullPointerException
      13: dup
      14: new           #27                 // class java/lang/StringBuilder
      17: dup
      18: invokespecial #28                 // Method java/lang/StringBuilder."<init>":()V
      21: ldc           #135                // String Couldn\'t find type for
      23: invokevirtual #30                 // Method java/lang/StringBuilder.append:(Ljava/lang/String;)Ljava/lang/StringBuilder;
      26: aload_2
      27: invokevirtual #90                 // Method java/lang/StringBuilder.append:(Ljava/lang/Object;)Ljava/lang/StringBuilder;
      30: ldc           #131                // String  in class
      32: invokevirtual #30                 // Method java/lang/StringBuilder.append:(Ljava/lang/String;)Ljava/lang/StringBuilder;
      35: aload_0
      36: invokevirtual #13                 // Method getTypeClass:()Ljava/lang/Class;
      39: invokevirtual #32                 // Method java/lang/Class.getName:()Ljava/lang/String;
      42: invokevirtual #30                 // Method java/lang/StringBuilder.append:(Ljava/lang/String;)Ljava/lang/StringBuilder;
      45: invokevirtual #33                 // Method java/lang/StringBuilder.toString:()Ljava/lang/String;
      48: invokespecial #136                // Method java/lang/NullPointerException."<init>":(Ljava/lang/String;)V
      51: athrow
      52: aload_3
      53: areturn

  private void writeTypeReference(javax.xml.namespace.QName, org.apache.ws.commons.schema.XmlSchemaElement, org.apache.cxf.aegis.type.AegisType, org.apache.ws.commons.schema.XmlSchema);
    Code:
       0: aload_3
       1: invokevirtual #137                // Method org/apache/cxf/aegis/type/AegisType.isAbstract:()Z
       4: ifeq          74
       7: aload_2
       8: aload_1
       9: invokevirtual #55                 // Method javax/xml/namespace/QName.getLocalPart:()Ljava/lang/String;
      12: invokevirtual #138                // Method org/apache/ws/commons/schema/XmlSchemaElement.setName:(Ljava/lang/String;)V
      15: aload_2
      16: aload_3
      17: invokevirtual #139                // Method org/apache/cxf/aegis/type/AegisType.getSchemaType:()Ljavax/xml/namespace/QName;
      20: invokevirtual #140                // Method org/apache/ws/commons/schema/XmlSchemaElement.setSchemaTypeName:(Ljavax/xml/namespace/QName;)V
      23: aload         4
      25: aload_3
      26: invokevirtual #139                // Method org/apache/cxf/aegis/type/AegisType.getSchemaType:()Ljavax/xml/namespace/QName;
      29: invokevirtual #141                // Method javax/xml/namespace/QName.getNamespaceURI:()Ljava/lang/String;
      32: invokestatic  #142                // Method org/apache/cxf/common/xmlschema/XmlSchemaUtils.addImportIfNeeded:(Lorg/apache/ws/commons/schema/XmlSchema;Ljava/lang/String;)V
      35: aload_0
      36: invokevirtual #12                 // Method getTypeInfo:()Lorg/apache/cxf/aegis/type/basic/BeanTypeInfo;
      39: aload_1
      40: invokevirtual #143                // Method org/apache/cxf/aegis/type/basic/BeanTypeInfo.getMinOccurs:(Ljavax/xml/namespace/QName;)I
      43: i2l
      44: lstore        5
      46: lload         5
      48: lconst_0
      49: lcmp
      50: ifne          59
      53: aload_2
      54: lload         5
      56: invokevirtual #144                // Method org/apache/ws/commons/schema/XmlSchemaElement.setMinOccurs:(J)V
      59: aload_2
      60: aload_0
      61: invokevirtual #12                 // Method getTypeInfo:()Lorg/apache/cxf/aegis/type/basic/BeanTypeInfo;
      64: aload_1
      65: invokevirtual #54                 // Method org/apache/cxf/aegis/type/basic/BeanTypeInfo.isNillable:(Ljavax/xml/namespace/QName;)Z
      68: invokevirtual #145                // Method org/apache/ws/commons/schema/XmlSchemaElement.setNillable:(Z)V
      71: goto          85
      74: aload_2
      75: invokevirtual #146                // Method org/apache/ws/commons/schema/XmlSchemaElement.getRef:()Lorg/apache/ws/commons/schema/utils/XmlSchemaRef;
      78: aload_3
      79: invokevirtual #139                // Method org/apache/cxf/aegis/type/AegisType.getSchemaType:()Ljavax/xml/namespace/QName;
      82: invokevirtual #147                // Method org/apache/ws/commons/schema/utils/XmlSchemaRef.setTargetQName:(Ljavax/xml/namespace/QName;)V
      85: return

  public void setTypeClass(java.lang.reflect.Type);
    Code:
       0: aload_0
       1: aload_1
       2: invokespecial #148                // Method org/apache/cxf/aegis/type/AegisType.setTypeClass:(Ljava/lang/reflect/Type;)V
       5: aload_0
       6: invokespecial #5                  // Method initTypeClass:()V
       9: return

  public boolean isComplex();
    Code:
       0: iconst_1
       1: ireturn

  public java.util.Set<org.apache.cxf.aegis.type.AegisType> getDependencies();
    Code:
       0: new           #149                // class java/util/HashSet
       3: dup
       4: invokespecial #150                // Method java/util/HashSet."<init>":()V
       7: astore_1
       8: aload_0
       9: invokevirtual #12                 // Method getTypeInfo:()Lorg/apache/cxf/aegis/type/basic/BeanTypeInfo;
      12: astore_2
      13: aload_2
      14: invokevirtual #107                // Method org/apache/cxf/aegis/type/basic/BeanTypeInfo.getAttributes:()Ljava/util/List;
      17: invokeinterface #108,  1          // InterfaceMethod java/util/List.iterator:()Ljava/util/Iterator;
      22: astore_3
      23: aload_3
      24: invokeinterface #109,  1          // InterfaceMethod java/util/Iterator.hasNext:()Z
      29: ifeq          72
      32: aload_3
      33: invokeinterface #110,  1          // InterfaceMethod java/util/Iterator.next:()Ljava/lang/Object;
      38: checkcast     #111                // class javax/xml/namespace/QName
      41: astore        4
      43: aload_0
      44: aload_2
      45: aload         4
      47: invokespecial #112                // Method isInheritedProperty:(Lorg/apache/cxf/aegis/type/basic/BeanTypeInfo;Ljavax/xml/namespace/QName;)Z
      50: ifeq          56
      53: goto          23
      56: aload_1
      57: aload_2
      58: aload         4
      60: invokevirtual #39                 // Method org/apache/cxf/aegis/type/basic/BeanTypeInfo.getType:(Ljavax/xml/namespace/QName;)Lorg/apache/cxf/aegis/type/AegisType;
      63: invokeinterface #151,  2          // InterfaceMethod java/util/Set.add:(Ljava/lang/Object;)Z
      68: pop
      69: goto          23
      72: aload_2
      73: invokevirtual #122                // Method org/apache/cxf/aegis/type/basic/BeanTypeInfo.getElements:()Ljava/util/List;
      76: invokeinterface #108,  1          // InterfaceMethod java/util/List.iterator:()Ljava/util/Iterator;
      81: astore_3
      82: aload_3
      83: invokeinterface #109,  1          // InterfaceMethod java/util/Iterator.hasNext:()Z
      88: ifeq          131
      91: aload_3
      92: invokeinterface #110,  1          // InterfaceMethod java/util/Iterator.next:()Ljava/lang/Object;
      97: checkcast     #111                // class javax/xml/namespace/QName
     100: astore        4
     102: aload_0
     103: aload_2
     104: aload         4
     106: invokespecial #112                // Method isInheritedProperty:(Lorg/apache/cxf/aegis/type/basic/BeanTypeInfo;Ljavax/xml/namespace/QName;)Z
     109: ifeq          115
     112: goto          82
     115: aload_1
     116: aload_2
     117: aload         4
     119: invokevirtual #39                 // Method org/apache/cxf/aegis/type/basic/BeanTypeInfo.getType:(Ljavax/xml/namespace/QName;)Lorg/apache/cxf/aegis/type/AegisType;
     122: invokeinterface #151,  2          // InterfaceMethod java/util/Set.add:(Ljava/lang/Object;)Z
     127: pop
     128: goto          82
     131: aload_0
     132: invokevirtual #121                // Method getSuperType:()Lorg/apache/cxf/aegis/type/AegisType;
     135: astore_3
     136: aload_3
     137: ifnull        148
     140: aload_1
     141: aload_3
     142: invokeinterface #151,  2          // InterfaceMethod java/util/Set.add:(Ljava/lang/Object;)Z
     147: pop
     148: aload_1
     149: areturn

  protected org.apache.cxf.aegis.type.basic.BeanTypeInfo getBeanTypeInfoWithProperty(javax.xml.namespace.QName);
    Code:
       0: aload_0
       1: astore_2
       2: aconst_null
       3: astore_3
       4: aload_3
       5: ifnonnull     44
       8: aload_2
       9: invokevirtual #12                 // Method getTypeInfo:()Lorg/apache/cxf/aegis/type/basic/BeanTypeInfo;
      12: aload_1
      13: invokevirtual #39                 // Method org/apache/cxf/aegis/type/basic/BeanTypeInfo.getType:(Ljavax/xml/namespace/QName;)Lorg/apache/cxf/aegis/type/AegisType;
      16: astore_3
      17: aload_3
      18: ifnonnull     4
      21: aload_2
      22: invokevirtual #121                // Method getSuperType:()Lorg/apache/cxf/aegis/type/AegisType;
      25: astore        4
      27: aload         4
      29: instanceof    #152                // class org/apache/cxf/aegis/type/basic/BeanType
      32: ifeq          44
      35: aload         4
      37: checkcast     #152                // class org/apache/cxf/aegis/type/basic/BeanType
      40: astore_2
      41: goto          4
      44: aload_2
      45: invokevirtual #12                 // Method getTypeInfo:()Lorg/apache/cxf/aegis/type/basic/BeanTypeInfo;
      48: areturn

  public org.apache.cxf.aegis.type.AegisType getSuperType();
    Code:
       0: aload_0
       1: invokevirtual #12                 // Method getTypeInfo:()Lorg/apache/cxf/aegis/type/basic/BeanTypeInfo;
       4: astore_1
       5: aload_1
       6: invokevirtual #3                  // Method org/apache/cxf/aegis/type/basic/BeanTypeInfo.getTypeClass:()Ljava/lang/Class;
       9: astore_2
      10: aload_2
      11: invokevirtual #7                  // Method java/lang/Class.isInterface:()Z
      14: ifeq          36
      17: aload_2
      18: invokevirtual #153                // Method java/lang/Class.getInterfaces:()[Ljava/lang/Class;
      21: arraylength
      22: iconst_1
      23: if_icmpne     36
      26: aload_2
      27: invokevirtual #153                // Method java/lang/Class.getInterfaces:()[Ljava/lang/Class;
      30: iconst_0
      31: aaload
      32: astore_2
      33: goto          41
      36: aload_2
      37: invokevirtual #154                // Method java/lang/Class.getSuperclass:()Ljava/lang/Class;
      40: astore_2
      41: aload_2
      42: ifnull        158
      45: aload_2
      46: ldc_w         #78                 // class java/lang/Object
      49: if_acmpeq     158
      52: aload_2
      53: ldc_w         #9                  // class java/lang/Exception
      56: if_acmpeq     158
      59: aload_2
      60: ldc_w         #155                // class java/lang/RuntimeException
      63: if_acmpeq     158
      66: aload_2
      67: ldc_w         #156                // class java/lang/Enum
      70: if_acmpeq     158
      73: aload_2
      74: ldc_w         #157                // class java/io/Serializable
      77: if_acmpeq     158
      80: aload_2
      81: ldc_w         #158                // class java/lang/Cloneable
      84: if_acmpeq     158
      87: aload_1
      88: invokevirtual #159                // Method org/apache/cxf/aegis/type/basic/BeanTypeInfo.getTypeMapping:()Lorg/apache/cxf/aegis/type/TypeMapping;
      91: astore_3
      92: aload_3
      93: aload_2
      94: invokeinterface #160,  2          // InterfaceMethod org/apache/cxf/aegis/type/TypeMapping.getType:(Ljava/lang/reflect/Type;)Lorg/apache/cxf/aegis/type/AegisType;
      99: astore        4
     101: aload         4
     103: ifnonnull     147
     106: aload_0
     107: invokevirtual #161                // Method getTypeMapping:()Lorg/apache/cxf/aegis/type/TypeMapping;
     110: invokeinterface #162,  1          // InterfaceMethod org/apache/cxf/aegis/type/TypeMapping.getTypeCreator:()Lorg/apache/cxf/aegis/type/TypeCreator;
     115: aload_2
     116: invokeinterface #163,  2          // InterfaceMethod org/apache/cxf/aegis/type/TypeCreator.createType:(Ljava/lang/reflect/Type;)Lorg/apache/cxf/aegis/type/AegisType;
     121: astore        4
     123: aload         4
     125: ifnull        155
     128: aload_3
     129: aload         4
     131: invokeinterface #164,  2          // InterfaceMethod org/apache/cxf/aegis/type/TypeMapping.register:(Lorg/apache/cxf/aegis/type/AegisType;)V
     136: aload_0
     137: getfield      #2                  // Field info:Lorg/apache/cxf/aegis/type/basic/BeanTypeInfo;
     140: iconst_1
     141: invokevirtual #165                // Method org/apache/cxf/aegis/type/basic/BeanTypeInfo.setExtension:(Z)V
     144: goto          155
     147: aload_0
     148: getfield      #2                  // Field info:Lorg/apache/cxf/aegis/type/basic/BeanTypeInfo;
     151: iconst_1
     152: invokevirtual #165                // Method org/apache/cxf/aegis/type/basic/BeanTypeInfo.setExtension:(Z)V
     155: aload         4
     157: areturn
     158: aconst_null
     159: areturn

  public org.apache.cxf.aegis.type.basic.BeanTypeInfo getTypeInfo();
    Code:
       0: aload_0
       1: getfield      #2                  // Field info:Lorg/apache/cxf/aegis/type/basic/BeanTypeInfo;
       4: ifnonnull     15
       7: aload_0
       8: aload_0
       9: invokevirtual #166                // Method createTypeInfo:()Lorg/apache/cxf/aegis/type/basic/BeanTypeInfo;
      12: putfield      #2                  // Field info:Lorg/apache/cxf/aegis/type/basic/BeanTypeInfo;
      15: aload_0
      16: getfield      #2                  // Field info:Lorg/apache/cxf/aegis/type/basic/BeanTypeInfo;
      19: invokevirtual #167                // Method org/apache/cxf/aegis/type/basic/BeanTypeInfo.initialize:()V
      22: aload_0
      23: getfield      #2                  // Field info:Lorg/apache/cxf/aegis/type/basic/BeanTypeInfo;
      26: areturn

  public org.apache.cxf.aegis.type.basic.BeanTypeInfo createTypeInfo();
    Code:
       0: new           #168                // class org/apache/cxf/aegis/type/basic/BeanTypeInfo
       3: dup
       4: aload_0
       5: invokevirtual #13                 // Method getTypeClass:()Ljava/lang/Class;
       8: aload_0
       9: invokevirtual #105                // Method getSchemaType:()Ljavax/xml/namespace/QName;
      12: invokevirtual #141                // Method javax/xml/namespace/QName.getNamespaceURI:()Ljava/lang/String;
      15: invokespecial #169                // Method org/apache/cxf/aegis/type/basic/BeanTypeInfo."<init>":(Ljava/lang/Class;Ljava/lang/String;)V
      18: astore_1
      19: aload_1
      20: aload_0
      21: invokevirtual #161                // Method getTypeMapping:()Lorg/apache/cxf/aegis/type/TypeMapping;
      24: invokevirtual #170                // Method org/apache/cxf/aegis/type/basic/BeanTypeInfo.setTypeMapping:(Lorg/apache/cxf/aegis/type/TypeMapping;)V
      27: aload_1
      28: areturn

  public java.lang.String toString();
    Code:
       0: new           #27                 // class java/lang/StringBuilder
       3: dup
       4: invokespecial #28                 // Method java/lang/StringBuilder."<init>":()V
       7: astore_1
       8: aload_1
       9: aload_0
      10: invokevirtual #22                 // Method java/lang/Object.getClass:()Ljava/lang/Class;
      13: invokevirtual #32                 // Method java/lang/Class.getName:()Ljava/lang/String;
      16: invokevirtual #30                 // Method java/lang/StringBuilder.append:(Ljava/lang/String;)Ljava/lang/StringBuilder;
      19: pop
      20: aload_1
      21: ldc           #171                // String : [class=
      23: invokevirtual #30                 // Method java/lang/StringBuilder.append:(Ljava/lang/String;)Ljava/lang/StringBuilder;
      26: pop
      27: aload_0
      28: invokevirtual #13                 // Method getTypeClass:()Ljava/lang/Class;
      31: astore_2
      32: aload_1
      33: aload_2
      34: ifnonnull     42
      37: ldc           #172                // String <null>
      39: goto          46
      42: aload_2
      43: invokevirtual #32                 // Method java/lang/Class.getName:()Ljava/lang/String;
      46: invokevirtual #30                 // Method java/lang/StringBuilder.append:(Ljava/lang/String;)Ljava/lang/StringBuilder;
      49: pop
      50: aload_1
      51: ldc           #173                // String ,\nQName=
      53: invokevirtual #30                 // Method java/lang/StringBuilder.append:(Ljava/lang/String;)Ljava/lang/StringBuilder;
      56: pop
      57: aload_0
      58: invokevirtual #105                // Method getSchemaType:()Ljavax/xml/namespace/QName;
      61: astore_3
      62: aload_1
      63: aload_3
      64: ifnonnull     72
      67: ldc           #172                // String <null>
      69: goto          76
      72: aload_3
      73: invokevirtual #174                // Method javax/xml/namespace/QName.toString:()Ljava/lang/String;
      76: invokevirtual #30                 // Method java/lang/StringBuilder.append:(Ljava/lang/String;)Ljava/lang/StringBuilder;
      79: pop
      80: aload_1
      81: ldc           #175                // String ,\ninfo=
      83: invokevirtual #30                 // Method java/lang/StringBuilder.append:(Ljava/lang/String;)Ljava/lang/StringBuilder;
      86: pop
      87: aload_1
      88: aload_0
      89: invokevirtual #12                 // Method getTypeInfo:()Lorg/apache/cxf/aegis/type/basic/BeanTypeInfo;
      92: invokevirtual #176                // Method java/lang/Object.toString:()Ljava/lang/String;
      95: invokevirtual #30                 // Method java/lang/StringBuilder.append:(Ljava/lang/String;)Ljava/lang/StringBuilder;
      98: pop
      99: aload_1
     100: ldc           #177                // String ]
     102: invokevirtual #30                 // Method java/lang/StringBuilder.append:(Ljava/lang/String;)Ljava/lang/StringBuilder;
     105: pop
     106: aload_1
     107: invokevirtual #33                 // Method java/lang/StringBuilder.toString:()Ljava/lang/String;
     110: areturn

  private void addXmimeToSchema(org.apache.ws.commons.schema.XmlSchema);
    Code:
       0: aload_1
       1: ldc           #178                // String http://www.w3.org/2005/05/xmlmime
       3: invokestatic  #142                // Method org/apache/cxf/common/xmlschema/XmlSchemaUtils.addImportIfNeeded:(Lorg/apache/ws/commons/schema/XmlSchema;Ljava/lang/String;)V
       6: return

  public long getMinOccurs();
    Code:
       0: aload_0
       1: invokevirtual #12                 // Method getTypeInfo:()Lorg/apache/cxf/aegis/type/basic/BeanTypeInfo;
       4: invokevirtual #179                // Method org/apache/cxf/aegis/type/basic/BeanTypeInfo.getMinOccurs:()J
       7: lreturn

  public boolean hasMinOccurs();
    Code:
       0: iconst_1
       1: ireturn

  public void setTypeMapping(org.apache.cxf.aegis.type.TypeMapping);
    Code:
       0: aload_0
       1: aload_1
       2: invokespecial #180                // Method org/apache/cxf/aegis/type/AegisType.setTypeMapping:(Lorg/apache/cxf/aegis/type/TypeMapping;)V
       5: aload_0
       6: getfield      #2                  // Field info:Lorg/apache/cxf/aegis/type/basic/BeanTypeInfo;
       9: ifnull        20
      12: aload_0
      13: getfield      #2                  // Field info:Lorg/apache/cxf/aegis/type/basic/BeanTypeInfo;
      16: aload_1
      17: invokevirtual #170                // Method org/apache/cxf/aegis/type/basic/BeanTypeInfo.setTypeMapping:(Lorg/apache/cxf/aegis/type/TypeMapping;)V
      20: return

  public void writeSchema(org.apache.ws.commons.schema.XmlSchema);
    Code:
       0: aload_0
       1: invokevirtual #12                 // Method getTypeInfo:()Lorg/apache/cxf/aegis/type/basic/BeanTypeInfo;
       4: astore_2
       5: new           #181                // class org/apache/ws/commons/schema/XmlSchemaComplexType
       8: dup
       9: aload_1
      10: iconst_1
      11: invokespecial #182                // Method org/apache/ws/commons/schema/XmlSchemaComplexType."<init>":(Lorg/apache/ws/commons/schema/XmlSchema;Z)V
      14: astore_3
      15: aload_3
      16: aload_0
      17: invokevirtual #105                // Method getSchemaType:()Ljavax/xml/namespace/QName;
      20: invokevirtual #55                 // Method javax/xml/namespace/QName.getLocalPart:()Ljava/lang/String;
      23: invokevirtual #183                // Method org/apache/ws/commons/schema/XmlSchemaComplexType.setName:(Ljava/lang/String;)V
      26: aload_0
      27: invokevirtual #121                // Method getSuperType:()Lorg/apache/cxf/aegis/type/AegisType;
      30: astore        4
      32: aload_2
      33: invokevirtual #3                  // Method org/apache/cxf/aegis/type/basic/BeanTypeInfo.getTypeClass:()Ljava/lang/Class;
      36: invokevirtual #184                // Method java/lang/Class.getModifiers:()I
      39: sipush        1024
      42: iand
      43: ifeq          61
      46: aload_2
      47: invokevirtual #3                  // Method org/apache/cxf/aegis/type/basic/BeanTypeInfo.getTypeClass:()Ljava/lang/Class;
      50: invokevirtual #7                  // Method java/lang/Class.isInterface:()Z
      53: ifne          61
      56: aload_3
      57: iconst_1
      58: invokevirtual #185                // Method org/apache/ws/commons/schema/XmlSchemaComplexType.setAbstract:(Z)V
      61: new           #186                // class org/apache/ws/commons/schema/XmlSchemaSequence
      64: dup
      65: invokespecial #187                // Method org/apache/ws/commons/schema/XmlSchemaSequence."<init>":()V
      68: astore        5
      70: aload_2
      71: invokevirtual #120                // Method org/apache/cxf/aegis/type/basic/BeanTypeInfo.isExtension:()Z
      74: istore        6
      76: iload         6
      78: ifeq          137
      81: aload         4
      83: ifnull        137
      86: new           #188                // class org/apache/ws/commons/schema/XmlSchemaComplexContent
      89: dup
      90: invokespecial #189                // Method org/apache/ws/commons/schema/XmlSchemaComplexContent."<init>":()V
      93: astore        7
      95: aload_3
      96: aload         7
      98: invokevirtual #190                // Method org/apache/ws/commons/schema/XmlSchemaComplexType.setContentModel:(Lorg/apache/ws/commons/schema/XmlSchemaContentModel;)V
     101: new           #191                // class org/apache/ws/commons/schema/XmlSchemaComplexContentExtension
     104: dup
     105: invokespecial #192                // Method org/apache/ws/commons/schema/XmlSchemaComplexContentExtension."<init>":()V
     108: astore        8
     110: aload         7
     112: aload         8
     114: invokevirtual #193                // Method org/apache/ws/commons/schema/XmlSchemaComplexContent.setContent:(Lorg/apache/ws/commons/schema/XmlSchemaContent;)V
     117: aload         8
     119: aload         4
     121: invokevirtual #139                // Method org/apache/cxf/aegis/type/AegisType.getSchemaType:()Ljavax/xml/namespace/QName;
     124: invokevirtual #194                // Method org/apache/ws/commons/schema/XmlSchemaComplexContentExtension.setBaseTypeName:(Ljavax/xml/namespace/QName;)V
     127: aload         8
     129: aload         5
     131: invokevirtual #195                // Method org/apache/ws/commons/schema/XmlSchemaComplexContentExtension.setParticle:(Lorg/apache/ws/commons/schema/XmlSchemaParticle;)V
     134: goto          143
     137: aload_3
     138: aload         5
     140: invokevirtual #196                // Method org/apache/ws/commons/schema/XmlSchemaComplexType.setParticle:(Lorg/apache/ws/commons/schema/XmlSchemaParticle;)V
     143: iconst_0
     144: istore        7
     146: iconst_0
     147: istore        8
     149: aload_2
     150: invokevirtual #122                // Method org/apache/cxf/aegis/type/basic/BeanTypeInfo.getElements:()Ljava/util/List;
     153: invokeinterface #108,  1          // InterfaceMethod java/util/List.iterator:()Ljava/util/Iterator;
     158: astore        9
     160: aload         9
     162: invokeinterface #109,  1          // InterfaceMethod java/util/Iterator.hasNext:()Z
     167: ifeq          349
     170: aload         9
     172: invokeinterface #110,  1          // InterfaceMethod java/util/Iterator.next:()Ljava/lang/Object;
     177: checkcast     #111                // class javax/xml/namespace/QName
     180: astore        10
     182: aload_0
     183: aload_2
     184: aload         10
     186: invokespecial #112                // Method isInheritedProperty:(Lorg/apache/cxf/aegis/type/basic/BeanTypeInfo;Ljavax/xml/namespace/QName;)Z
     189: ifeq          195
     192: goto          160
     195: new           #197                // class org/apache/ws/commons/schema/XmlSchemaElement
     198: dup
     199: aload_1
     200: iconst_0
     201: invokespecial #198                // Method org/apache/ws/commons/schema/XmlSchemaElement."<init>":(Lorg/apache/ws/commons/schema/XmlSchema;Z)V
     204: astore        11
     206: aload         11
     208: aload         10
     210: invokevirtual #55                 // Method javax/xml/namespace/QName.getLocalPart:()Ljava/lang/String;
     213: invokevirtual #138                // Method org/apache/ws/commons/schema/XmlSchemaElement.setName:(Ljava/lang/String;)V
     216: aload         5
     218: invokevirtual #199                // Method org/apache/ws/commons/schema/XmlSchemaSequence.getItems:()Ljava/util/List;
     221: aload         11
     223: invokeinterface #200,  2          // InterfaceMethod java/util/List.add:(Ljava/lang/Object;)Z
     228: pop
     229: aload_0
     230: aload_2
     231: aload         10
     233: invokespecial #114                // Method getType:(Lorg/apache/cxf/aegis/type/basic/BeanTypeInfo;Ljavax/xml/namespace/QName;)Lorg/apache/cxf/aegis/type/AegisType;
     236: astore        12
     238: aload         12
     240: invokevirtual #47                 // Method org/apache/cxf/aegis/type/AegisType.isFlatArray:()Z
     243: ifeq          293
     246: aload         11
     248: aload         12
     250: invokevirtual #201                // Method org/apache/cxf/aegis/type/AegisType.getMinOccurs:()J
     253: invokevirtual #144                // Method org/apache/ws/commons/schema/XmlSchemaElement.setMinOccurs:(J)V
     256: aload         11
     258: aload         12
     260: invokevirtual #202                // Method org/apache/cxf/aegis/type/AegisType.getMaxOccurs:()J
     263: invokevirtual #203                // Method org/apache/ws/commons/schema/XmlSchemaElement.setMaxOccurs:(J)V
     266: aload         12
     268: checkcast     #48                 // class org/apache/cxf/aegis/type/basic/ArrayType
     271: astore        13
     273: aload         13
     275: invokevirtual #204                // Method org/apache/cxf/aegis/type/basic/ArrayType.getComponentType:()Lorg/apache/cxf/aegis/type/AegisType;
     278: astore        12
     280: aload         11
     282: aload         12
     284: invokevirtual #205                // Method org/apache/cxf/aegis/type/AegisType.isNillable:()Z
     287: invokevirtual #145                // Method org/apache/ws/commons/schema/XmlSchemaElement.setNillable:(Z)V
     290: goto          315
     293: ldc           #206                // String http://cxf.apache.org/arrays
     295: aload         12
     297: invokevirtual #139                // Method org/apache/cxf/aegis/type/AegisType.getSchemaType:()Ljavax/xml/namespace/QName;
     300: invokevirtual #141                // Method javax/xml/namespace/QName.getNamespaceURI:()Ljava/lang/String;
     303: invokevirtual #207                // Method java/lang/String.equals:(Ljava/lang/Object;)Z
     306: ifeq          315
     309: aload_1
     310: ldc           #206                // String http://cxf.apache.org/arrays
     312: invokestatic  #142                // Method org/apache/cxf/common/xmlschema/XmlSchemaUtils.addImportIfNeeded:(Lorg/apache/ws/commons/schema/XmlSchema;Ljava/lang/String;)V
     315: aload_0
     316: aload         10
     318: aload         11
     320: aload         12
     322: aload_1
     323: invokespecial #208                // Method writeTypeReference:(Ljavax/xml/namespace/QName;Lorg/apache/ws/commons/schema/XmlSchemaElement;Lorg/apache/cxf/aegis/type/AegisType;Lorg/apache/ws/commons/schema/XmlSchema;)V
     326: iload         7
     328: aload         12
     330: invokevirtual #209                // Method org/apache/cxf/aegis/type/AegisType.usesXmime:()Z
     333: ior
     334: istore        7
     336: iload         8
     338: aload         12
     340: invokevirtual #210                // Method org/apache/cxf/aegis/type/AegisType.usesUtilityTypes:()Z
     343: ior
     344: istore        8
     346: goto          160
     349: iload         7
     351: ifeq          359
     354: aload_0
     355: aload_1
     356: invokespecial #211                // Method addXmimeToSchema:(Lorg/apache/ws/commons/schema/XmlSchema;)V
     359: iload         8
     361: ifeq          368
     364: aload_1
     365: invokestatic  #212                // Method org/apache/cxf/aegis/AegisContext.addUtilityTypesToSchema:(Lorg/apache/ws/commons/schema/XmlSchema;)V
     368: aload_2
     369: invokevirtual #213                // Method org/apache/cxf/aegis/type/basic/BeanTypeInfo.isExtensibleElements:()Z
     372: ifeq          411
     375: new           #214                // class org/apache/ws/commons/schema/XmlSchemaAny
     378: dup
     379: invokespecial #215                // Method org/apache/ws/commons/schema/XmlSchemaAny."<init>":()V
     382: astore        9
     384: aload         9
     386: lconst_0
     387: invokevirtual #216                // Method org/apache/ws/commons/schema/XmlSchemaAny.setMinOccurs:(J)V
     390: aload         9
     392: ldc2_w        #217                // long 9223372036854775807l
     395: invokevirtual #219                // Method org/apache/ws/commons/schema/XmlSchemaAny.setMaxOccurs:(J)V
     398: aload         5
     400: invokevirtual #199                // Method org/apache/ws/commons/schema/XmlSchemaSequence.getItems:()Ljava/util/List;
     403: aload         9
     405: invokeinterface #200,  2          // InterfaceMethod java/util/List.add:(Ljava/lang/Object;)Z
     410: pop
     411: aload_2
     412: invokevirtual #107                // Method org/apache/cxf/aegis/type/basic/BeanTypeInfo.getAttributes:()Ljava/util/List;
     415: invokeinterface #108,  1          // InterfaceMethod java/util/List.iterator:()Ljava/util/Iterator;
     420: astore        9
     422: aload         9
     424: invokeinterface #109,  1          // InterfaceMethod java/util/Iterator.hasNext:()Z
     429: ifeq          537
     432: aload         9
     434: invokeinterface #110,  1          // InterfaceMethod java/util/Iterator.next:()Ljava/lang/Object;
     439: checkcast     #111                // class javax/xml/namespace/QName
     442: astore        10
     444: aload_0
     445: aload_2
     446: aload         10
     448: invokespecial #112                // Method isInheritedProperty:(Lorg/apache/cxf/aegis/type/basic/BeanTypeInfo;Ljavax/xml/namespace/QName;)Z
     451: ifeq          457
     454: goto          422
     457: new           #220                // class org/apache/ws/commons/schema/XmlSchemaAttribute
     460: dup
     461: aload_1
     462: iconst_0
     463: invokespecial #221                // Method org/apache/ws/commons/schema/XmlSchemaAttribute."<init>":(Lorg/apache/ws/commons/schema/XmlSchema;Z)V
     466: astore        11
     468: aload_3
     469: invokevirtual #222                // Method org/apache/ws/commons/schema/XmlSchemaComplexType.getAttributes:()Ljava/util/List;
     472: aload         11
     474: invokeinterface #200,  2          // InterfaceMethod java/util/List.add:(Ljava/lang/Object;)Z
     479: pop
     480: aload         11
     482: aload         10
     484: invokevirtual #55                 // Method javax/xml/namespace/QName.getLocalPart:()Ljava/lang/String;
     487: invokevirtual #223                // Method org/apache/ws/commons/schema/XmlSchemaAttribute.setName:(Ljava/lang/String;)V
     490: aload_0
     491: aload_2
     492: aload         10
     494: invokespecial #114                // Method getType:(Lorg/apache/cxf/aegis/type/basic/BeanTypeInfo;Ljavax/xml/namespace/QName;)Lorg/apache/cxf/aegis/type/AegisType;
     497: astore        12
     499: aload         11
     501: aload         12
     503: invokevirtual #139                // Method org/apache/cxf/aegis/type/AegisType.getSchemaType:()Ljavax/xml/namespace/QName;
     506: invokevirtual #224                // Method org/apache/ws/commons/schema/XmlSchemaAttribute.setSchemaTypeName:(Ljavax/xml/namespace/QName;)V
     509: aload         10
     511: invokevirtual #141                // Method javax/xml/namespace/QName.getNamespaceURI:()Ljava/lang/String;
     514: astore        13
     516: aload         13
     518: aload_1
     519: invokevirtual #225                // Method org/apache/ws/commons/schema/XmlSchema.getTargetNamespace:()Ljava/lang/String;
     522: invokevirtual #207                // Method java/lang/String.equals:(Ljava/lang/Object;)Z
     525: ifne          534
     528: aload_1
     529: aload         13
     531: invokestatic  #142                // Method org/apache/cxf/common/xmlschema/XmlSchemaUtils.addImportIfNeeded:(Lorg/apache/ws/commons/schema/XmlSchema;Ljava/lang/String;)V
     534: goto          422
     537: aload_2
     538: invokevirtual #226                // Method org/apache/cxf/aegis/type/basic/BeanTypeInfo.isExtensibleAttributes:()Z
     541: ifeq          555
     544: aload_3
     545: new           #227                // class org/apache/ws/commons/schema/XmlSchemaAnyAttribute
     548: dup
     549: invokespecial #228                // Method org/apache/ws/commons/schema/XmlSchemaAnyAttribute."<init>":()V
     552: invokevirtual #229                // Method org/apache/ws/commons/schema/XmlSchemaComplexType.setAnyAttribute:(Lorg/apache/ws/commons/schema/XmlSchemaAnyAttribute;)V
     555: return
}
