Compiled from "CharacterType.java"
public class org.apache.cxf.aegis.type.basic.CharacterType extends org.apache.cxf.aegis.type.AegisType {
  public org.apache.cxf.aegis.type.basic.CharacterType();
    Code:
       0: aload_0
       1: invokespecial #1                  // Method org/apache/cxf/aegis/type/AegisType."<init>":()V
       4: return

  public java.lang.Object readObject(org.apache.cxf.aegis.xml.MessageReader, org.apache.cxf.aegis.Context);
    Code:
       0: aload_1
       1: invokeinterface #2,  1            // InterfaceMethod org/apache/cxf/aegis/xml/MessageReader.getValueAsCharacter:()C
       6: invokestatic  #3                  // Method java/lang/Character.valueOf:(C)Ljava/lang/Character;
       9: areturn

  public void writeObject(java.lang.Object, org.apache.cxf.aegis.xml.MessageWriter, org.apache.cxf.aegis.Context);
    Code:
       0: aload_2
       1: aload_1
       2: checkcast     #4                  // class java/lang/Character
       5: invokeinterface #5,  2            // InterfaceMethod org/apache/cxf/aegis/xml/MessageWriter.writeValueAsCharacter:(Ljava/lang/Character;)V
      10: return
}
