Compiled from "URIType.java"
public class org.apache.cxf.aegis.type.basic.URIType extends org.apache.cxf.aegis.type.AegisType {
  public org.apache.cxf.aegis.type.basic.URIType();
    Code:
       0: aload_0
       1: invokespecial #1                  // Method org/apache/cxf/aegis/type/AegisType."<init>":()V
       4: return

  public java.lang.Object readObject(org.apache.cxf.aegis.xml.MessageReader, org.apache.cxf.aegis.Context);
    Code:
       0: aload_1
       1: invokeinterface #2,  1            // InterfaceMethod org/apache/cxf/aegis/xml/MessageReader.getValue:()Ljava/lang/String;
       6: astore_3
       7: aconst_null
       8: aload_3
       9: if_acmpne     16
      12: aconst_null
      13: goto          23
      16: aload_3
      17: invokevirtual #3                  // Method java/lang/String.trim:()Ljava/lang/String;
      20: invokestatic  #4                  // Method java/net/URI.create:(Ljava/lang/String;)Ljava/net/URI;
      23: areturn

  public void writeObject(java.lang.Object, org.apache.cxf.aegis.xml.MessageWriter, org.apache.cxf.aegis.Context);
    Code:
       0: aload_2
       1: aload_1
       2: checkcast     #5                  // class java/net/URI
       5: invokevirtual #6                  // Method java/net/URI.toASCIIString:()Ljava/lang/String;
       8: invokeinterface #7,  2            // InterfaceMethod org/apache/cxf/aegis/xml/MessageWriter.writeValue:(Ljava/lang/Object;)V
      13: return
}
