Compiled from "GlobalMatrixAuthorizationStrategy.java"
public class hudson.security.GlobalMatrixAuthorizationStrategy extends hudson.security.AuthorizationStrategy {
  private transient hudson.security.ACL acl;

  private final java.util.Map<hudson.security.Permission, java.util.Set<java.lang.String>> grantedPermissions;

  private final java.util.Set<java.lang.String> sids;

  public static final hudson.model.Descriptor<hudson.security.AuthorizationStrategy> DESCRIPTOR;

  public hudson.security.GlobalMatrixAuthorizationStrategy();
    Code:
       0: aload_0
       1: invokespecial #4                  // Method hudson/security/AuthorizationStrategy."<init>":()V
       4: aload_0
       5: new           #5                  // class hudson/security/GlobalMatrixAuthorizationStrategy$AclImpl
       8: dup
       9: aload_0
      10: aconst_null
      11: invokespecial #6                  // Method hudson/security/GlobalMatrixAuthorizationStrategy$AclImpl."<init>":(Lhudson/security/GlobalMatrixAuthorizationStrategy;Lhudson/security/GlobalMatrixAuthorizationStrategy$1;)V
      14: putfield      #7                  // Field acl:Lhudson/security/ACL;
      17: aload_0
      18: new           #8                  // class java/util/HashMap
      21: dup
      22: invokespecial #9                  // Method java/util/HashMap."<init>":()V
      25: putfield      #3                  // Field grantedPermissions:Ljava/util/Map;
      28: aload_0
      29: new           #10                 // class java/util/HashSet
      32: dup
      33: invokespecial #11                 // Method java/util/HashSet."<init>":()V
      36: putfield      #12                 // Field sids:Ljava/util/Set;
      39: return

  private void add(hudson.security.Permission, java.lang.String);
    Code:
       0: aload_0
       1: getfield      #3                  // Field grantedPermissions:Ljava/util/Map;
       4: aload_1
       5: invokeinterface #13,  2           // InterfaceMethod java/util/Map.get:(Ljava/lang/Object;)Ljava/lang/Object;
      10: checkcast     #14                 // class java/util/Set
      13: astore_3
      14: aload_3
      15: ifnonnull     38
      18: aload_0
      19: getfield      #3                  // Field grantedPermissions:Ljava/util/Map;
      22: aload_1
      23: new           #10                 // class java/util/HashSet
      26: dup
      27: invokespecial #11                 // Method java/util/HashSet."<init>":()V
      30: dup
      31: astore_3
      32: invokeinterface #15,  3           // InterfaceMethod java/util/Map.put:(Ljava/lang/Object;Ljava/lang/Object;)Ljava/lang/Object;
      37: pop
      38: aload_3
      39: aload_2
      40: invokeinterface #16,  2           // InterfaceMethod java/util/Set.add:(Ljava/lang/Object;)Z
      45: pop
      46: aload_0
      47: getfield      #12                 // Field sids:Ljava/util/Set;
      50: aload_2
      51: invokeinterface #16,  2           // InterfaceMethod java/util/Set.add:(Ljava/lang/Object;)Z
      56: pop
      57: return

  private void add(java.lang.String);
    Code:
       0: aload_1
       1: bipush        58
       3: invokevirtual #17                 // Method java/lang/String.indexOf:(I)I
       6: istore_2
       7: aload_0
       8: aload_1
       9: iconst_0
      10: iload_2
      11: invokevirtual #18                 // Method java/lang/String.substring:(II)Ljava/lang/String;
      14: invokestatic  #19                 // Method hudson/security/Permission.fromId:(Ljava/lang/String;)Lhudson/security/Permission;
      17: aload_1
      18: iload_2
      19: iconst_1
      20: iadd
      21: invokevirtual #20                 // Method java/lang/String.substring:(I)Ljava/lang/String;
      24: invokespecial #1                  // Method add:(Lhudson/security/Permission;Ljava/lang/String;)V
      27: return

  public hudson.security.ACL getRootACL();
    Code:
       0: aload_0
       1: getfield      #7                  // Field acl:Lhudson/security/ACL;
       4: areturn

  public java.util.Set<java.lang.String> getGroups();
    Code:
       0: aload_0
       1: getfield      #12                 // Field sids:Ljava/util/Set;
       4: areturn

  private java.lang.Object readResolve();
    Code:
       0: aload_0
       1: new           #5                  // class hudson/security/GlobalMatrixAuthorizationStrategy$AclImpl
       4: dup
       5: aload_0
       6: aconst_null
       7: invokespecial #6                  // Method hudson/security/GlobalMatrixAuthorizationStrategy$AclImpl."<init>":(Lhudson/security/GlobalMatrixAuthorizationStrategy;Lhudson/security/GlobalMatrixAuthorizationStrategy$1;)V
      10: putfield      #7                  // Field acl:Lhudson/security/ACL;
      13: aload_0
      14: areturn

  public boolean hasPermission(java.lang.String, hudson.security.Permission);
    Code:
       0: aload_0
       1: getfield      #3                  // Field grantedPermissions:Ljava/util/Map;
       4: aload_2
       5: invokeinterface #13,  2           // InterfaceMethod java/util/Map.get:(Ljava/lang/Object;)Ljava/lang/Object;
      10: checkcast     #14                 // class java/util/Set
      13: astore_3
      14: aload_3
      15: ifnull        32
      18: aload_3
      19: aload_1
      20: invokeinterface #21,  2           // InterfaceMethod java/util/Set.contains:(Ljava/lang/Object;)Z
      25: ifeq          32
      28: iconst_1
      29: goto          33
      32: iconst_0
      33: ireturn

  public java.util.List<java.lang.String> getAllSIDs();
    Code:
       0: new           #10                 // class java/util/HashSet
       3: dup
       4: invokespecial #11                 // Method java/util/HashSet."<init>":()V
       7: astore_1
       8: aload_0
       9: getfield      #3                  // Field grantedPermissions:Ljava/util/Map;
      12: invokeinterface #22,  1           // InterfaceMethod java/util/Map.values:()Ljava/util/Collection;
      17: invokeinterface #23,  1           // InterfaceMethod java/util/Collection.iterator:()Ljava/util/Iterator;
      22: astore_2
      23: aload_2
      24: invokeinterface #24,  1           // InterfaceMethod java/util/Iterator.hasNext:()Z
      29: ifeq          53
      32: aload_2
      33: invokeinterface #25,  1           // InterfaceMethod java/util/Iterator.next:()Ljava/lang/Object;
      38: checkcast     #14                 // class java/util/Set
      41: astore_3
      42: aload_1
      43: aload_3
      44: invokeinterface #26,  2           // InterfaceMethod java/util/Set.addAll:(Ljava/util/Collection;)Z
      49: pop
      50: goto          23
      53: aload_1
      54: ldc           #27                 // String anonymous
      56: invokeinterface #28,  2           // InterfaceMethod java/util/Set.remove:(Ljava/lang/Object;)Z
      61: pop
      62: aload_1
      63: aload_1
      64: invokeinterface #29,  1           // InterfaceMethod java/util/Set.size:()I
      69: anewarray     #30                 // class java/lang/String
      72: invokeinterface #31,  2           // InterfaceMethod java/util/Set.toArray:([Ljava/lang/Object;)[Ljava/lang/Object;
      77: checkcast     #32                 // class "[Ljava/lang/String;"
      80: astore_2
      81: aload_2
      82: invokestatic  #33                 // Method java/util/Arrays.sort:([Ljava/lang/Object;)V
      85: aload_2
      86: invokestatic  #34                 // Method java/util/Arrays.asList:([Ljava/lang/Object;)Ljava/util/List;
      89: areturn

  public hudson.model.Descriptor<hudson.security.AuthorizationStrategy> getDescriptor();
    Code:
       0: getstatic     #35                 // Field DESCRIPTOR:Lhudson/model/Descriptor;
       3: areturn

  public java.util.Collection getGroups();
    Code:
       0: aload_0
       1: invokevirtual #36                 // Method getGroups:()Ljava/util/Set;
       4: areturn

  static java.util.Map access$100(hudson.security.GlobalMatrixAuthorizationStrategy);
    Code:
       0: aload_0
       1: getfield      #3                  // Field grantedPermissions:Ljava/util/Map;
       4: areturn

  static void access$200(hudson.security.GlobalMatrixAuthorizationStrategy, java.lang.String);
    Code:
       0: aload_0
       1: aload_1
       2: invokespecial #2                  // Method add:(Ljava/lang/String;)V
       5: return

  static void access$300(hudson.security.GlobalMatrixAuthorizationStrategy, hudson.security.Permission, java.lang.String);
    Code:
       0: aload_0
       1: aload_1
       2: aload_2
       3: invokespecial #1                  // Method add:(Lhudson/security/Permission;Ljava/lang/String;)V
       6: return

  static {};
    Code:
       0: new           #37                 // class hudson/security/GlobalMatrixAuthorizationStrategy$DescriptorImpl
       3: dup
       4: invokespecial #38                 // Method hudson/security/GlobalMatrixAuthorizationStrategy$DescriptorImpl."<init>":()V
       7: putstatic     #35                 // Field DESCRIPTOR:Lhudson/model/Descriptor;
      10: getstatic     #39                 // Field LIST:Lhudson/util/DescriptorList;
      13: getstatic     #35                 // Field DESCRIPTOR:Lhudson/model/Descriptor;
      16: invokevirtual #40                 // Method hudson/util/DescriptorList.add:(Ljava/lang/Object;)Z
      19: pop
      20: return
}
