Compiled from "LDAPSecurityRealm.java"
public final class hudson.security.LDAPSecurityRealm$MailAdressResolverImpl extends hudson.tasks.MailAddressResolver {
  public hudson.security.LDAPSecurityRealm$MailAdressResolverImpl();
    Code:
       0: aload_0
       1: invokespecial #1                  // Method hudson/tasks/MailAddressResolver."<init>":()V
       4: return

  public java.lang.String findMailAddressFor(hudson.model.User);
    Code:
       0: invokestatic  #2                  // Method hudson/model/Hudson.getInstance:()Lhudson/model/Hudson;
       3: astore_2
       4: aload_2
       5: invokevirtual #3                  // Method hudson/model/Hudson.getSecurityRealm:()Lhudson/security/SecurityRealm;
       8: instanceof    #4                  // class hudson/security/LDAPSecurityRealm
      11: ifne          16
      14: aconst_null
      15: areturn
      16: getstatic     #5                  // Field hudson/security/HudsonFilter.USER_DETAILS_SERVICE_PROXY:Lhudson/security/UserDetailsServiceProxy;
      19: aload_1
      20: invokevirtual #6                  // Method hudson/model/User.getId:()Ljava/lang/String;
      23: invokevirtual #7                  // Method hudson/security/UserDetailsServiceProxy.loadUserByUsername:(Ljava/lang/String;)Lorg/acegisecurity/userdetails/UserDetails;
      26: checkcast     #8                  // class org/acegisecurity/userdetails/ldap/LdapUserDetails
      29: astore_3
      30: aload_3
      31: invokeinterface #9,  1            // InterfaceMethod org/acegisecurity/userdetails/ldap/LdapUserDetails.getAttributes:()Ljavax/naming/directory/Attributes;
      36: ldc           #10                 // String mail
      38: invokeinterface #11,  2           // InterfaceMethod javax/naming/directory/Attributes.get:(Ljava/lang/String;)Ljavax/naming/directory/Attribute;
      43: astore        4
      45: aload         4
      47: ifnonnull     52
      50: aconst_null
      51: areturn
      52: aload         4
      54: invokeinterface #12,  1           // InterfaceMethod javax/naming/directory/Attribute.get:()Ljava/lang/Object;
      59: checkcast     #13                 // class java/lang/String
      62: areturn
      63: astore_3
      64: invokestatic  #15                 // Method hudson/security/LDAPSecurityRealm.access$000:()Ljava/util/logging/Logger;
      67: getstatic     #16                 // Field java/util/logging/Level.FINE:Ljava/util/logging/Level;
      70: ldc           #17                 // String Failed to look up LDAP for e-mail address
      72: aload_3
      73: invokevirtual #18                 // Method java/util/logging/Logger.log:(Ljava/util/logging/Level;Ljava/lang/String;Ljava/lang/Throwable;)V
      76: aconst_null
      77: areturn
      78: astore_3
      79: invokestatic  #15                 // Method hudson/security/LDAPSecurityRealm.access$000:()Ljava/util/logging/Logger;
      82: getstatic     #16                 // Field java/util/logging/Level.FINE:Ljava/util/logging/Level;
      85: ldc           #17                 // String Failed to look up LDAP for e-mail address
      87: aload_3
      88: invokevirtual #18                 // Method java/util/logging/Logger.log:(Ljava/util/logging/Level;Ljava/lang/String;Ljava/lang/Throwable;)V
      91: aconst_null
      92: areturn
      93: astore_3
      94: invokestatic  #15                 // Method hudson/security/LDAPSecurityRealm.access$000:()Ljava/util/logging/Logger;
      97: getstatic     #16                 // Field java/util/logging/Level.FINE:Ljava/util/logging/Level;
     100: ldc           #17                 // String Failed to look up LDAP for e-mail address
     102: aload_3
     103: invokevirtual #18                 // Method java/util/logging/Logger.log:(Ljava/util/logging/Level;Ljava/lang/String;Ljava/lang/Throwable;)V
     106: aconst_null
     107: areturn
    Exception table:
       from    to  target type
          16    51    63   Class org/acegisecurity/userdetails/UsernameNotFoundException
          52    62    63   Class org/acegisecurity/userdetails/UsernameNotFoundException
          16    51    78   Class org/springframework/dao/DataAccessException
          52    62    78   Class org/springframework/dao/DataAccessException
          16    51    93   Class javax/naming/NamingException
          52    62    93   Class javax/naming/NamingException
}
