Compiled from "SparseACL.java"
public final class hudson.security.SparseACL$Entry {
  public final org.acegisecurity.acls.sid.Sid sid;

  public final hudson.security.Permission permission;

  public final boolean allowed;

  public hudson.security.SparseACL$Entry(org.acegisecurity.acls.sid.Sid, hudson.security.Permission, boolean);
    Code:
       0: aload_0
       1: invokespecial #1                  // Method java/lang/Object."<init>":()V
       4: aload_0
       5: aload_1
       6: putfield      #2                  // Field sid:Lorg/acegisecurity/acls/sid/Sid;
       9: aload_0
      10: aload_2
      11: putfield      #3                  // Field permission:Lhudson/security/Permission;
      14: aload_0
      15: iload_3
      16: putfield      #4                  // Field allowed:Z
      19: return
}
