Compiled from "WebSocketMessagingAutoConfiguration.java"
class org.springframework.boot.autoconfigure.websocket.WebSocketMessagingAutoConfiguration$WebSocketMessageConverterConfiguration extends org.springframework.web.socket.config.annotation.AbstractWebSocketMessageBrokerConfigurer {
  private final com.fasterxml.jackson.databind.ObjectMapper objectMapper;

  org.springframework.boot.autoconfigure.websocket.WebSocketMessagingAutoConfiguration$WebSocketMessageConverterConfiguration(com.fasterxml.jackson.databind.ObjectMapper);
    Code:
       0: aload_0
       1: invokespecial #1                  // Method org/springframework/web/socket/config/annotation/AbstractWebSocketMessageBrokerConfigurer."<init>":()V
       4: aload_0
       5: aload_1
       6: putfield      #2                  // Field objectMapper:Lcom/fasterxml/jackson/databind/ObjectMapper;
       9: return

  public void registerStompEndpoints(org.springframework.web.socket.config.annotation.StompEndpointRegistry);
    Code:
       0: return

  public boolean configureMessageConverters(java.util.List<org.springframework.messaging.converter.MessageConverter>);
    Code:
       0: new           #3                  // class org/springframework/messaging/converter/MappingJackson2MessageConverter
       3: dup
       4: invokespecial #4                  // Method org/springframework/messaging/converter/MappingJackson2MessageConverter."<init>":()V
       7: astore_2
       8: aload_2
       9: aload_0
      10: getfield      #2                  // Field objectMapper:Lcom/fasterxml/jackson/databind/ObjectMapper;
      13: invokevirtual #5                  // Method org/springframework/messaging/converter/MappingJackson2MessageConverter.setObjectMapper:(Lcom/fasterxml/jackson/databind/ObjectMapper;)V
      16: new           #6                  // class org/springframework/messaging/converter/DefaultContentTypeResolver
      19: dup
      20: invokespecial #7                  // Method org/springframework/messaging/converter/DefaultContentTypeResolver."<init>":()V
      23: astore_3
      24: aload_3
      25: getstatic     #8                  // Field org/springframework/util/MimeTypeUtils.APPLICATION_JSON:Lorg/springframework/util/MimeType;
      28: invokevirtual #9                  // Method org/springframework/messaging/converter/DefaultContentTypeResolver.setDefaultMimeType:(Lorg/springframework/util/MimeType;)V
      31: aload_2
      32: aload_3
      33: invokevirtual #10                 // Method org/springframework/messaging/converter/MappingJackson2MessageConverter.setContentTypeResolver:(Lorg/springframework/messaging/converter/ContentTypeResolver;)V
      36: aload_1
      37: new           #11                 // class org/springframework/messaging/converter/StringMessageConverter
      40: dup
      41: invokespecial #12                 // Method org/springframework/messaging/converter/StringMessageConverter."<init>":()V
      44: invokeinterface #13,  2           // InterfaceMethod java/util/List.add:(Ljava/lang/Object;)Z
      49: pop
      50: aload_1
      51: new           #14                 // class org/springframework/messaging/converter/ByteArrayMessageConverter
      54: dup
      55: invokespecial #15                 // Method org/springframework/messaging/converter/ByteArrayMessageConverter."<init>":()V
      58: invokeinterface #13,  2           // InterfaceMethod java/util/List.add:(Ljava/lang/Object;)Z
      63: pop
      64: aload_1
      65: aload_2
      66: invokeinterface #13,  2           // InterfaceMethod java/util/List.add:(Ljava/lang/Object;)Z
      71: pop
      72: iconst_0
      73: ireturn
}
