Compiled from "WebSocketContainerCustomizer.java"
public abstract class org.springframework.boot.autoconfigure.websocket.WebSocketContainerCustomizer<T extends org.springframework.boot.context.embedded.EmbeddedServletContainerFactory> implements org.springframework.boot.context.embedded.EmbeddedServletContainerCustomizer, org.springframework.core.Ordered {
  public org.springframework.boot.autoconfigure.websocket.WebSocketContainerCustomizer();
    Code:
       0: aload_0
       1: invokespecial #1                  // Method java/lang/Object."<init>":()V
       4: return

  public int getOrder();
    Code:
       0: iconst_0
       1: ireturn

  public void customize(org.springframework.boot.context.embedded.ConfigurableEmbeddedServletContainer);
    Code:
       0: aload_0
       1: invokevirtual #2                  // Method getContainerType:()Ljava/lang/Class;
       4: aload_1
       5: invokevirtual #3                  // Method java/lang/Object.getClass:()Ljava/lang/Class;
       8: invokevirtual #4                  // Method java/lang/Class.isAssignableFrom:(Ljava/lang/Class;)Z
      11: ifeq          22
      14: aload_0
      15: aload_1
      16: checkcast     #5                  // class org/springframework/boot/context/embedded/EmbeddedServletContainerFactory
      19: invokevirtual #6                  // Method doCustomize:(Lorg/springframework/boot/context/embedded/EmbeddedServletContainerFactory;)V
      22: return

  protected java.lang.Class<?> getContainerType();
    Code:
       0: ldc           #7                  // class org/springframework/boot/autoconfigure/websocket/WebSocketContainerCustomizer
       2: aload_0
       3: invokevirtual #3                  // Method java/lang/Object.getClass:()Ljava/lang/Class;
       6: invokestatic  #8                  // Method org/springframework/core/ResolvableType.forClass:(Ljava/lang/Class;Ljava/lang/Class;)Lorg/springframework/core/ResolvableType;
       9: iconst_0
      10: newarray       int
      12: invokevirtual #9                  // Method org/springframework/core/ResolvableType.resolveGeneric:([I)Ljava/lang/Class;
      15: areturn

  protected abstract void doCustomize(T);
}
