Compiled from "ITConfig.java"
public class net.nemerosa.ontrack.it.ITConfig {
  private final org.slf4j.Logger logger;

  public net.nemerosa.ontrack.it.ITConfig();
    Code:
       0: aload_0
       1: invokespecial #1                  // Method java/lang/Object."<init>":()V
       4: aload_0
       5: ldc           #2                  // class net/nemerosa/ontrack/it/ITConfig
       7: invokestatic  #3                  // Method org/slf4j/LoggerFactory.getLogger:(Ljava/lang/Class;)Lorg/slf4j/Logger;
      10: putfield      #4                  // Field logger:Lorg/slf4j/Logger;
      13: return

  public javax.sql.DataSource dataSource() throws java.io.IOException;
    Code:
       0: ldc           #5                  // String it.jdbc.url
       2: ldc           #6                  // String jdbc:postgresql://postgresql/ontrack
       4: invokestatic  #7                  // Method java/lang/System.getProperty:(Ljava/lang/String;Ljava/lang/String;)Ljava/lang/String;
       7: astore_1
       8: ldc           #8                  // String it.jdbc.user
      10: ldc           #9                  // String ontrack
      12: invokestatic  #7                  // Method java/lang/System.getProperty:(Ljava/lang/String;Ljava/lang/String;)Ljava/lang/String;
      15: astore_2
      16: ldc           #10                 // String it.jdbc.password
      18: ldc           #9                  // String ontrack
      20: invokestatic  #7                  // Method java/lang/System.getProperty:(Ljava/lang/String;Ljava/lang/String;)Ljava/lang/String;
      23: astore_3
      24: aload_0
      25: getfield      #4                  // Field logger:Lorg/slf4j/Logger;
      28: ldc           #11                 // String Using database at {}
      30: aload_1
      31: invokeinterface #12,  3           // InterfaceMethod org/slf4j/Logger.info:(Ljava/lang/String;Ljava/lang/Object;)V
      36: new           #13                 // class org/apache/tomcat/jdbc/pool/DataSource
      39: dup
      40: invokespecial #14                 // Method org/apache/tomcat/jdbc/pool/DataSource."<init>":()V
      43: astore        4
      45: aload         4
      47: ldc           #15                 // String org.postgresql.Driver
      49: invokevirtual #16                 // Method org/apache/tomcat/jdbc/pool/DataSource.setDriverClassName:(Ljava/lang/String;)V
      52: aload         4
      54: aload_1
      55: invokevirtual #17                 // Method org/apache/tomcat/jdbc/pool/DataSource.setUrl:(Ljava/lang/String;)V
      58: aload         4
      60: aload_2
      61: invokevirtual #18                 // Method org/apache/tomcat/jdbc/pool/DataSource.setUsername:(Ljava/lang/String;)V
      64: aload         4
      66: aload_3
      67: invokevirtual #19                 // Method org/apache/tomcat/jdbc/pool/DataSource.setPassword:(Ljava/lang/String;)V
      70: aload         4
      72: iconst_0
      73: invokestatic  #20                 // Method java/lang/Boolean.valueOf:(Z)Ljava/lang/Boolean;
      76: invokevirtual #21                 // Method org/apache/tomcat/jdbc/pool/DataSource.setDefaultAutoCommit:(Ljava/lang/Boolean;)V
      79: aload         4
      81: bipush        10
      83: invokevirtual #22                 // Method org/apache/tomcat/jdbc/pool/DataSource.setInitialSize:(I)V
      86: aload         4
      88: bipush        10
      90: invokevirtual #23                 // Method org/apache/tomcat/jdbc/pool/DataSource.setMaxIdle:(I)V
      93: aload         4
      95: bipush        20
      97: invokevirtual #24                 // Method org/apache/tomcat/jdbc/pool/DataSource.setMaxActive:(I)V
     100: aload         4
     102: areturn

  public org.springframework.transaction.PlatformTransactionManager transactionManager() throws java.io.IOException;
    Code:
       0: new           #25                 // class org/springframework/jdbc/datasource/DataSourceTransactionManager
       3: dup
       4: aload_0
       5: invokevirtual #26                 // Method dataSource:()Ljavax/sql/DataSource;
       8: invokespecial #27                 // Method org/springframework/jdbc/datasource/DataSourceTransactionManager."<init>":(Ljavax/sql/DataSource;)V
      11: areturn

  public org.springframework.core.convert.converter.ConverterRegistry converterRegistry();
    Code:
       0: new           #28                 // class org/springframework/core/convert/support/DefaultConversionService
       3: dup
       4: invokespecial #29                 // Method org/springframework/core/convert/support/DefaultConversionService."<init>":()V
       7: areturn
}
