Compiled from "streams.kt"
public final class io.vertx.kotlin.core.streams.StreamsKt {
  public static final <S extends io.vertx.core.streams.WriteStream<io.vertx.core.buffer.Buffer>> S write(S, boolean, kotlin.jvm.functions.Function1<? super io.vertx.kotlin.core.json.Json, ? extends java.lang.Object>);
    Code:
       0: ldc           #9                  // int 0
       2: istore_3
       3: aload_0
       4: ldc           #11                 // String $this$write
       6: invokestatic  #17                 // Method kotlin/jvm/internal/Intrinsics.checkParameterIsNotNull:(Ljava/lang/Object;Ljava/lang/String;)V
       9: aload_2
      10: ldc           #19                 // String block
      12: invokestatic  #17                 // Method kotlin/jvm/internal/Intrinsics.checkParameterIsNotNull:(Ljava/lang/Object;Ljava/lang/String;)V
      15: aload_0
      16: invokestatic  #25                 // InterfaceMethod io/vertx/core/buffer/Buffer.buffer:()Lio/vertx/core/buffer/Buffer;
      19: dup
      20: ldc           #27                 // String Buffer.buffer()
      22: invokestatic  #30                 // Method kotlin/jvm/internal/Intrinsics.checkExpressionValueIsNotNull:(Ljava/lang/Object;Ljava/lang/String;)V
      25: astore        4
      27: astore        11
      29: iconst_0
      30: istore        5
      32: aload_2
      33: getstatic     #36                 // Field io/vertx/kotlin/core/json/Json.INSTANCE:Lio/vertx/kotlin/core/json/Json;
      36: invokeinterface #42,  2           // InterfaceMethod kotlin/jvm/functions/Function1.invoke:(Ljava/lang/Object;)Ljava/lang/Object;
      41: astore        6
      43: iconst_0
      44: istore        7
      46: iconst_0
      47: istore        8
      49: aload         6
      51: astore        9
      53: iconst_0
      54: istore        10
      56: iload_1
      57: ifeq          68
      60: aload         9
      62: invokestatic  #48                 // Method io/vertx/core/json/Json.encodePrettily:(Ljava/lang/Object;)Ljava/lang/String;
      65: goto          73
      68: aload         9
      70: invokestatic  #51                 // Method io/vertx/core/json/Json.encode:(Ljava/lang/Object;)Ljava/lang/String;
      73: nop
      74: astore        6
      76: iconst_0
      77: istore        7
      79: iconst_0
      80: istore        8
      82: aload         6
      84: astore        9
      86: iconst_0
      87: istore        10
      89: aload         4
      91: aload         9
      93: invokeinterface #55,  2           // InterfaceMethod io/vertx/core/buffer/Buffer.appendString:(Ljava/lang/String;)Lio/vertx/core/buffer/Buffer;
      98: dup
      99: ldc           #57                 // String appendString(encoded)
     101: invokestatic  #30                 // Method kotlin/jvm/internal/Intrinsics.checkExpressionValueIsNotNull:(Ljava/lang/Object;Ljava/lang/String;)V
     104: dup
     105: ldc           #59                 // String block(Json).let { json -…> appendString(encoded) }
     107: invokestatic  #30                 // Method kotlin/jvm/internal/Intrinsics.checkExpressionValueIsNotNull:(Ljava/lang/Object;Ljava/lang/String;)V
     110: astore        12
     112: aload         11
     114: aload         12
     116: invokeinterface #64,  2           // InterfaceMethod io/vertx/core/streams/WriteStream.write:(Ljava/lang/Object;)Lio/vertx/core/Future;
     121: pop
     122: aload_0
     123: areturn

  public static io.vertx.core.streams.WriteStream write$default(io.vertx.core.streams.WriteStream, boolean, kotlin.jvm.functions.Function1, int, java.lang.Object);
    Code:
       0: iload_3
       1: iconst_1
       2: iand
       3: ifeq          8
       6: iconst_0
       7: istore_1
       8: iconst_0
       9: istore_3
      10: aload_0
      11: ldc           #11                 // String $this$write
      13: invokestatic  #17                 // Method kotlin/jvm/internal/Intrinsics.checkParameterIsNotNull:(Ljava/lang/Object;Ljava/lang/String;)V
      16: aload_2
      17: ldc           #19                 // String block
      19: invokestatic  #17                 // Method kotlin/jvm/internal/Intrinsics.checkParameterIsNotNull:(Ljava/lang/Object;Ljava/lang/String;)V
      22: aload_0
      23: invokestatic  #25                 // InterfaceMethod io/vertx/core/buffer/Buffer.buffer:()Lio/vertx/core/buffer/Buffer;
      26: dup
      27: ldc           #27                 // String Buffer.buffer()
      29: invokestatic  #30                 // Method kotlin/jvm/internal/Intrinsics.checkExpressionValueIsNotNull:(Ljava/lang/Object;Ljava/lang/String;)V
      32: astore        4
      34: astore        11
      36: iconst_0
      37: istore        5
      39: aload_2
      40: getstatic     #36                 // Field io/vertx/kotlin/core/json/Json.INSTANCE:Lio/vertx/kotlin/core/json/Json;
      43: invokeinterface #42,  2           // InterfaceMethod kotlin/jvm/functions/Function1.invoke:(Ljava/lang/Object;)Ljava/lang/Object;
      48: astore        6
      50: iconst_0
      51: istore        7
      53: iconst_0
      54: istore        8
      56: aload         6
      58: astore        9
      60: iconst_0
      61: istore        10
      63: iload_1
      64: ifeq          75
      67: aload         9
      69: invokestatic  #48                 // Method io/vertx/core/json/Json.encodePrettily:(Ljava/lang/Object;)Ljava/lang/String;
      72: goto          80
      75: aload         9
      77: invokestatic  #51                 // Method io/vertx/core/json/Json.encode:(Ljava/lang/Object;)Ljava/lang/String;
      80: nop
      81: astore        6
      83: iconst_0
      84: istore        7
      86: iconst_0
      87: istore        8
      89: aload         6
      91: astore        9
      93: iconst_0
      94: istore        10
      96: aload         4
      98: aload         9
     100: invokeinterface #55,  2           // InterfaceMethod io/vertx/core/buffer/Buffer.appendString:(Ljava/lang/String;)Lio/vertx/core/buffer/Buffer;
     105: dup
     106: ldc           #57                 // String appendString(encoded)
     108: invokestatic  #30                 // Method kotlin/jvm/internal/Intrinsics.checkExpressionValueIsNotNull:(Ljava/lang/Object;Ljava/lang/String;)V
     111: dup
     112: ldc           #59                 // String block(Json).let { json -…> appendString(encoded) }
     114: invokestatic  #30                 // Method kotlin/jvm/internal/Intrinsics.checkExpressionValueIsNotNull:(Ljava/lang/Object;Ljava/lang/String;)V
     117: astore        12
     119: aload         11
     121: aload         12
     123: invokeinterface #64,  2           // InterfaceMethod io/vertx/core/streams/WriteStream.write:(Ljava/lang/Object;)Lio/vertx/core/Future;
     128: pop
     129: aload_0
     130: areturn

  public static final <S extends io.vertx.core.streams.WriteStream<io.vertx.core.buffer.Buffer>> S end(S, boolean, kotlin.jvm.functions.Function1<? super io.vertx.kotlin.core.json.Json, ? extends java.lang.Object>);
    Code:
       0: ldc           #9                  // int 0
       2: istore_3
       3: aload_0
       4: ldc           #86                 // String $this$end
       6: invokestatic  #17                 // Method kotlin/jvm/internal/Intrinsics.checkParameterIsNotNull:(Ljava/lang/Object;Ljava/lang/String;)V
       9: aload_2
      10: ldc           #19                 // String block
      12: invokestatic  #17                 // Method kotlin/jvm/internal/Intrinsics.checkParameterIsNotNull:(Ljava/lang/Object;Ljava/lang/String;)V
      15: aload_0
      16: invokestatic  #25                 // InterfaceMethod io/vertx/core/buffer/Buffer.buffer:()Lio/vertx/core/buffer/Buffer;
      19: dup
      20: ldc           #27                 // String Buffer.buffer()
      22: invokestatic  #30                 // Method kotlin/jvm/internal/Intrinsics.checkExpressionValueIsNotNull:(Ljava/lang/Object;Ljava/lang/String;)V
      25: astore        4
      27: astore        11
      29: iconst_0
      30: istore        5
      32: aload_2
      33: getstatic     #36                 // Field io/vertx/kotlin/core/json/Json.INSTANCE:Lio/vertx/kotlin/core/json/Json;
      36: invokeinterface #42,  2           // InterfaceMethod kotlin/jvm/functions/Function1.invoke:(Ljava/lang/Object;)Ljava/lang/Object;
      41: astore        6
      43: iconst_0
      44: istore        7
      46: iconst_0
      47: istore        8
      49: aload         6
      51: astore        9
      53: iconst_0
      54: istore        10
      56: iload_1
      57: ifeq          68
      60: aload         9
      62: invokestatic  #48                 // Method io/vertx/core/json/Json.encodePrettily:(Ljava/lang/Object;)Ljava/lang/String;
      65: goto          73
      68: aload         9
      70: invokestatic  #51                 // Method io/vertx/core/json/Json.encode:(Ljava/lang/Object;)Ljava/lang/String;
      73: nop
      74: astore        6
      76: iconst_0
      77: istore        7
      79: iconst_0
      80: istore        8
      82: aload         6
      84: astore        9
      86: iconst_0
      87: istore        10
      89: aload         4
      91: aload         9
      93: invokeinterface #55,  2           // InterfaceMethod io/vertx/core/buffer/Buffer.appendString:(Ljava/lang/String;)Lio/vertx/core/buffer/Buffer;
      98: dup
      99: ldc           #57                 // String appendString(encoded)
     101: invokestatic  #30                 // Method kotlin/jvm/internal/Intrinsics.checkExpressionValueIsNotNull:(Ljava/lang/Object;Ljava/lang/String;)V
     104: dup
     105: ldc           #59                 // String block(Json).let { json -…> appendString(encoded) }
     107: invokestatic  #30                 // Method kotlin/jvm/internal/Intrinsics.checkExpressionValueIsNotNull:(Ljava/lang/Object;Ljava/lang/String;)V
     110: astore        12
     112: aload         11
     114: aload         12
     116: invokeinterface #88,  2           // InterfaceMethod io/vertx/core/streams/WriteStream.end:(Ljava/lang/Object;)Lio/vertx/core/Future;
     121: pop
     122: aload_0
     123: areturn

  public static io.vertx.core.streams.WriteStream end$default(io.vertx.core.streams.WriteStream, boolean, kotlin.jvm.functions.Function1, int, java.lang.Object);
    Code:
       0: iload_3
       1: iconst_1
       2: iand
       3: ifeq          8
       6: iconst_0
       7: istore_1
       8: iconst_0
       9: istore_3
      10: aload_0
      11: ldc           #86                 // String $this$end
      13: invokestatic  #17                 // Method kotlin/jvm/internal/Intrinsics.checkParameterIsNotNull:(Ljava/lang/Object;Ljava/lang/String;)V
      16: aload_2
      17: ldc           #19                 // String block
      19: invokestatic  #17                 // Method kotlin/jvm/internal/Intrinsics.checkParameterIsNotNull:(Ljava/lang/Object;Ljava/lang/String;)V
      22: aload_0
      23: invokestatic  #25                 // InterfaceMethod io/vertx/core/buffer/Buffer.buffer:()Lio/vertx/core/buffer/Buffer;
      26: dup
      27: ldc           #27                 // String Buffer.buffer()
      29: invokestatic  #30                 // Method kotlin/jvm/internal/Intrinsics.checkExpressionValueIsNotNull:(Ljava/lang/Object;Ljava/lang/String;)V
      32: astore        4
      34: astore        11
      36: iconst_0
      37: istore        5
      39: aload_2
      40: getstatic     #36                 // Field io/vertx/kotlin/core/json/Json.INSTANCE:Lio/vertx/kotlin/core/json/Json;
      43: invokeinterface #42,  2           // InterfaceMethod kotlin/jvm/functions/Function1.invoke:(Ljava/lang/Object;)Ljava/lang/Object;
      48: astore        6
      50: iconst_0
      51: istore        7
      53: iconst_0
      54: istore        8
      56: aload         6
      58: astore        9
      60: iconst_0
      61: istore        10
      63: iload_1
      64: ifeq          75
      67: aload         9
      69: invokestatic  #48                 // Method io/vertx/core/json/Json.encodePrettily:(Ljava/lang/Object;)Ljava/lang/String;
      72: goto          80
      75: aload         9
      77: invokestatic  #51                 // Method io/vertx/core/json/Json.encode:(Ljava/lang/Object;)Ljava/lang/String;
      80: nop
      81: astore        6
      83: iconst_0
      84: istore        7
      86: iconst_0
      87: istore        8
      89: aload         6
      91: astore        9
      93: iconst_0
      94: istore        10
      96: aload         4
      98: aload         9
     100: invokeinterface #55,  2           // InterfaceMethod io/vertx/core/buffer/Buffer.appendString:(Ljava/lang/String;)Lio/vertx/core/buffer/Buffer;
     105: dup
     106: ldc           #57                 // String appendString(encoded)
     108: invokestatic  #30                 // Method kotlin/jvm/internal/Intrinsics.checkExpressionValueIsNotNull:(Ljava/lang/Object;Ljava/lang/String;)V
     111: dup
     112: ldc           #59                 // String block(Json).let { json -…> appendString(encoded) }
     114: invokestatic  #30                 // Method kotlin/jvm/internal/Intrinsics.checkExpressionValueIsNotNull:(Ljava/lang/Object;Ljava/lang/String;)V
     117: astore        12
     119: aload         11
     121: aload         12
     123: invokeinterface #88,  2           // InterfaceMethod io/vertx/core/streams/WriteStream.end:(Ljava/lang/Object;)Lio/vertx/core/Future;
     128: pop
     129: aload_0
     130: areturn
}
