Compiled from "UnixCrypt.java"
public class org.eclipse.jetty.util.security.UnixCrypt {
  private static final byte[] IP;

  private static final byte[] ExpandTr;

  private static final byte[] PC1;

  private static final byte[] Rotates;

  private static final byte[] PC2;

  private static final byte[][] S;

  private static final byte[] P32Tr;

  private static final byte[] CIFP;

  private static final byte[] ITOA64;

  private static final byte[] A64TOI;

  private static final long[][] PC1ROT;

  private static final long[][][] PC2ROT;

  private static final long[][] IE3264;

  private static final long[][] SPE;

  private static final long[][] CF6464;

  private org.eclipse.jetty.util.security.UnixCrypt();
    Code:
       0: aload_0
       1: invokespecial #1                  // Method java/lang/Object."<init>":()V
       4: return

  private static int to_six_bit(int);
    Code:
       0: iload_0
       1: bipush        26
       3: ishl
       4: ldc           #2                  // int -67108864
       6: iand
       7: iload_0
       8: bipush        12
      10: ishl
      11: ldc           #3                  // int 16515072
      13: iand
      14: ior
      15: iload_0
      16: iconst_2
      17: ishr
      18: ldc           #4                  // int 64512
      20: iand
      21: ior
      22: iload_0
      23: bipush        16
      25: ishr
      26: sipush        252
      29: iand
      30: ior
      31: ireturn

  private static long to_six_bit(long);
    Code:
       0: lload_0
       1: bipush        26
       3: lshl
       4: ldc2_w        #5                  // long -288230371923853312l
       7: land
       8: lload_0
       9: bipush        12
      11: lshl
      12: ldc2_w        #7                  // long 70931694147600384l
      15: land
      16: lor
      17: lload_0
      18: iconst_2
      19: lshr
      20: ldc2_w        #9                  // long 277076930264064l
      23: land
      24: lor
      25: lload_0
      26: bipush        16
      28: lshr
      29: ldc2_w        #11                 // long 1082331758844l
      32: land
      33: lor
      34: lreturn

  private static long perm6464(long, long[][]);
    Code:
       0: lconst_0
       1: lstore_3
       2: bipush        8
       4: istore        5
       6: iinc          5, -1
       9: iload         5
      11: iflt          69
      14: ldc2_w        #13                 // long 255l
      17: lload_0
      18: land
      19: l2i
      20: istore        6
      22: lload_0
      23: bipush        8
      25: lshr
      26: lstore_0
      27: aload_2
      28: iload         5
      30: iconst_1
      31: ishl
      32: aaload
      33: iload         6
      35: bipush        15
      37: iand
      38: laload
      39: lstore        7
      41: lload_3
      42: lload         7
      44: lor
      45: lstore_3
      46: aload_2
      47: iload         5
      49: iconst_1
      50: ishl
      51: iconst_1
      52: iadd
      53: aaload
      54: iload         6
      56: iconst_4
      57: ishr
      58: laload
      59: lstore        7
      61: lload_3
      62: lload         7
      64: lor
      65: lstore_3
      66: goto          6
      69: lload_3
      70: lreturn

  private static long perm3264(int, long[][]);
    Code:
       0: lconst_0
       1: lstore_2
       2: iconst_4
       3: istore        4
       5: iinc          4, -1
       8: iload         4
      10: iflt          67
      13: sipush        255
      16: iload_0
      17: iand
      18: istore        5
      20: iload_0
      21: bipush        8
      23: ishr
      24: istore_0
      25: aload_1
      26: iload         4
      28: iconst_1
      29: ishl
      30: aaload
      31: iload         5
      33: bipush        15
      35: iand
      36: laload
      37: lstore        6
      39: lload_2
      40: lload         6
      42: lor
      43: lstore_2
      44: aload_1
      45: iload         4
      47: iconst_1
      48: ishl
      49: iconst_1
      50: iadd
      51: aaload
      52: iload         5
      54: iconst_4
      55: ishr
      56: laload
      57: lstore        6
      59: lload_2
      60: lload         6
      62: lor
      63: lstore_2
      64: goto          5
      67: lload_2
      68: lreturn

  private static long[] des_setkey(long);
    Code:
       0: lload_0
       1: getstatic     #15                 // Field PC1ROT:[[J
       4: invokestatic  #16                 // Method perm6464:(J[[J)J
       7: lstore_2
       8: bipush        16
      10: newarray       long
      12: astore        4
      14: aload         4
      16: iconst_0
      17: lload_2
      18: ldc2_w        #17                 // long -217020518463700993l
      21: land
      22: lastore
      23: iconst_1
      24: istore        5
      26: iload         5
      28: bipush        16
      30: if_icmpge     72
      33: aload         4
      35: iload         5
      37: lload_2
      38: lastore
      39: lload_2
      40: getstatic     #19                 // Field PC2ROT:[[[J
      43: getstatic     #20                 // Field Rotates:[B
      46: iload         5
      48: baload
      49: iconst_1
      50: isub
      51: aaload
      52: invokestatic  #16                 // Method perm6464:(J[[J)J
      55: lstore_2
      56: aload         4
      58: iload         5
      60: lload_2
      61: ldc2_w        #17                 // long -217020518463700993l
      64: land
      65: lastore
      66: iinc          5, 1
      69: goto          26
      72: aload         4
      74: areturn

  private static long des_cipher(long, int, int, long[]);
    Code:
       0: iload_2
       1: invokestatic  #21                 // Method to_six_bit:(I)I
       4: istore_2
       5: lload_0
       6: lstore        5
       8: lload         5
      10: lstore        7
      12: lload         5
      14: ldc2_w        #22                 // long 6148914691236517205l
      17: land
      18: lstore        5
      20: lload         7
      22: ldc2_w        #24                 // long -6148914694099828736l
      25: land
      26: lload         7
      28: iconst_1
      29: lshr
      30: ldc2_w        #26                 // long 1431655765l
      33: land
      34: lor
      35: lstore        7
      37: lload         5
      39: iconst_1
      40: lshl
      41: lload         5
      43: bipush        32
      45: lshl
      46: lor
      47: ldc2_w        #28                 // long -4294967296l
      50: land
      51: lload         7
      53: lload         7
      55: bipush        32
      57: lshr
      58: lor
      59: ldc2_w        #30                 // long 4294967295l
      62: land
      63: lor
      64: lstore        5
      66: lload         5
      68: bipush        32
      70: lshr
      71: l2i
      72: getstatic     #32                 // Field IE3264:[[J
      75: invokestatic  #33                 // Method perm3264:(I[[J)J
      78: lstore        5
      80: lload         5
      82: ldc2_w        #34                 // long -1l
      85: land
      86: l2i
      87: getstatic     #32                 // Field IE3264:[[J
      90: invokestatic  #33                 // Method perm3264:(I[[J)J
      93: lstore        7
      95: iinc          3, -1
      98: iload_3
      99: iflt          518
     102: iconst_0
     103: istore        9
     105: iload         9
     107: bipush        8
     109: if_icmpge     494
     112: aload         4
     114: iload         9
     116: iconst_1
     117: ishl
     118: laload
     119: lstore        10
     121: lload         7
     123: bipush        32
     125: lshr
     126: lload         7
     128: lxor
     129: iload_2
     130: i2l
     131: land
     132: ldc2_w        #30                 // long 4294967295l
     135: land
     136: lstore        14
     138: lload         14
     140: lload         14
     142: bipush        32
     144: lshl
     145: lor
     146: lstore        14
     148: lload         14
     150: lload         7
     152: lxor
     153: lload         10
     155: lxor
     156: lstore        12
     158: lload         5
     160: getstatic     #36                 // Field SPE:[[J
     163: iconst_0
     164: aaload
     165: lload         12
     167: bipush        58
     169: lshr
     170: ldc2_w        #37                 // long 63l
     173: land
     174: l2i
     175: laload
     176: getstatic     #36                 // Field SPE:[[J
     179: iconst_1
     180: aaload
     181: lload         12
     183: bipush        50
     185: lshr
     186: ldc2_w        #37                 // long 63l
     189: land
     190: l2i
     191: laload
     192: lxor
     193: getstatic     #36                 // Field SPE:[[J
     196: iconst_2
     197: aaload
     198: lload         12
     200: bipush        42
     202: lshr
     203: ldc2_w        #37                 // long 63l
     206: land
     207: l2i
     208: laload
     209: lxor
     210: getstatic     #36                 // Field SPE:[[J
     213: iconst_3
     214: aaload
     215: lload         12
     217: bipush        34
     219: lshr
     220: ldc2_w        #37                 // long 63l
     223: land
     224: l2i
     225: laload
     226: lxor
     227: getstatic     #36                 // Field SPE:[[J
     230: iconst_4
     231: aaload
     232: lload         12
     234: bipush        26
     236: lshr
     237: ldc2_w        #37                 // long 63l
     240: land
     241: l2i
     242: laload
     243: lxor
     244: getstatic     #36                 // Field SPE:[[J
     247: iconst_5
     248: aaload
     249: lload         12
     251: bipush        18
     253: lshr
     254: ldc2_w        #37                 // long 63l
     257: land
     258: l2i
     259: laload
     260: lxor
     261: getstatic     #36                 // Field SPE:[[J
     264: bipush        6
     266: aaload
     267: lload         12
     269: bipush        10
     271: lshr
     272: ldc2_w        #37                 // long 63l
     275: land
     276: l2i
     277: laload
     278: lxor
     279: getstatic     #36                 // Field SPE:[[J
     282: bipush        7
     284: aaload
     285: lload         12
     287: iconst_2
     288: lshr
     289: ldc2_w        #37                 // long 63l
     292: land
     293: l2i
     294: laload
     295: lxor
     296: lxor
     297: lstore        5
     299: aload         4
     301: iload         9
     303: iconst_1
     304: ishl
     305: iconst_1
     306: iadd
     307: laload
     308: lstore        10
     310: lload         5
     312: bipush        32
     314: lshr
     315: lload         5
     317: lxor
     318: iload_2
     319: i2l
     320: land
     321: ldc2_w        #30                 // long 4294967295l
     324: land
     325: lstore        14
     327: lload         14
     329: lload         14
     331: bipush        32
     333: lshl
     334: lor
     335: lstore        14
     337: lload         14
     339: lload         5
     341: lxor
     342: lload         10
     344: lxor
     345: lstore        12
     347: lload         7
     349: getstatic     #36                 // Field SPE:[[J
     352: iconst_0
     353: aaload
     354: lload         12
     356: bipush        58
     358: lshr
     359: ldc2_w        #37                 // long 63l
     362: land
     363: l2i
     364: laload
     365: getstatic     #36                 // Field SPE:[[J
     368: iconst_1
     369: aaload
     370: lload         12
     372: bipush        50
     374: lshr
     375: ldc2_w        #37                 // long 63l
     378: land
     379: l2i
     380: laload
     381: lxor
     382: getstatic     #36                 // Field SPE:[[J
     385: iconst_2
     386: aaload
     387: lload         12
     389: bipush        42
     391: lshr
     392: ldc2_w        #37                 // long 63l
     395: land
     396: l2i
     397: laload
     398: lxor
     399: getstatic     #36                 // Field SPE:[[J
     402: iconst_3
     403: aaload
     404: lload         12
     406: bipush        34
     408: lshr
     409: ldc2_w        #37                 // long 63l
     412: land
     413: l2i
     414: laload
     415: lxor
     416: getstatic     #36                 // Field SPE:[[J
     419: iconst_4
     420: aaload
     421: lload         12
     423: bipush        26
     425: lshr
     426: ldc2_w        #37                 // long 63l
     429: land
     430: l2i
     431: laload
     432: lxor
     433: getstatic     #36                 // Field SPE:[[J
     436: iconst_5
     437: aaload
     438: lload         12
     440: bipush        18
     442: lshr
     443: ldc2_w        #37                 // long 63l
     446: land
     447: l2i
     448: laload
     449: lxor
     450: getstatic     #36                 // Field SPE:[[J
     453: bipush        6
     455: aaload
     456: lload         12
     458: bipush        10
     460: lshr
     461: ldc2_w        #37                 // long 63l
     464: land
     465: l2i
     466: laload
     467: lxor
     468: getstatic     #36                 // Field SPE:[[J
     471: bipush        7
     473: aaload
     474: lload         12
     476: iconst_2
     477: lshr
     478: ldc2_w        #37                 // long 63l
     481: land
     482: l2i
     483: laload
     484: lxor
     485: lxor
     486: lstore        7
     488: iinc          9, 1
     491: goto          105
     494: lload         5
     496: lload         7
     498: lxor
     499: lstore        5
     501: lload         7
     503: lload         5
     505: lxor
     506: lstore        7
     508: lload         5
     510: lload         7
     512: lxor
     513: lstore        5
     515: goto          95
     518: lload         5
     520: bipush        35
     522: lshr
     523: ldc2_w        #39                 // long 252645135l
     526: land
     527: lload         5
     529: ldc2_w        #34                 // long -1l
     532: land
     533: iconst_1
     534: lshl
     535: ldc2_w        #41                 // long 4042322160l
     538: land
     539: lor
     540: bipush        32
     542: lshl
     543: lload         7
     545: bipush        35
     547: lshr
     548: ldc2_w        #39                 // long 252645135l
     551: land
     552: lload         7
     554: ldc2_w        #34                 // long -1l
     557: land
     558: iconst_1
     559: lshl
     560: ldc2_w        #41                 // long 4042322160l
     563: land
     564: lor
     565: lor
     566: lstore        5
     568: lload         5
     570: getstatic     #43                 // Field CF6464:[[J
     573: invokestatic  #16                 // Method perm6464:(J[[J)J
     576: lstore        5
     578: lload         5
     580: lreturn

  private static void init_perm(long[][], byte[], int);
    Code:
       0: iconst_0
       1: istore_3
       2: iload_3
       3: iload_2
       4: bipush        8
       6: imul
       7: if_icmpge     98
      10: aload_1
      11: iload_3
      12: baload
      13: iconst_1
      14: isub
      15: istore        4
      17: iload         4
      19: ifge          25
      22: goto          92
      25: iload         4
      27: iconst_2
      28: ishr
      29: istore        5
      31: iconst_1
      32: iload         4
      34: iconst_3
      35: iand
      36: ishl
      37: istore        4
      39: iconst_0
      40: istore        6
      42: iload         6
      44: bipush        16
      46: if_icmpge     92
      49: iload_3
      50: bipush        7
      52: iand
      53: bipush        7
      55: iload_3
      56: iconst_3
      57: ishr
      58: isub
      59: iconst_3
      60: ishl
      61: iadd
      62: istore        7
      64: iload         6
      66: iload         4
      68: iand
      69: ifeq          86
      72: aload_0
      73: iload         5
      75: aaload
      76: iload         6
      78: dup2
      79: laload
      80: lconst_1
      81: iload         7
      83: lshl
      84: lor
      85: lastore
      86: iinc          6, 1
      89: goto          42
      92: iinc          3, 1
      95: goto          2
      98: return

  public static java.lang.String crypt(java.lang.String, java.lang.String);
    Code:
       0: lconst_0
       1: lstore_2
       2: bipush        13
       4: newarray       byte
       6: astore        4
       8: lconst_0
       9: lstore        5
      11: aload_0
      12: ifnull        19
      15: aload_1
      16: ifnonnull     22
      19: ldc           #44                 // String *
      21: areturn
      22: aload_0
      23: invokevirtual #45                 // Method java/lang/String.length:()I
      26: istore        7
      28: iconst_0
      29: istore        8
      31: iload         8
      33: bipush        8
      35: if_icmpge     72
      38: lload         5
      40: bipush        8
      42: lshl
      43: iload         8
      45: iload         7
      47: if_icmpge     61
      50: iconst_2
      51: aload_0
      52: iload         8
      54: invokevirtual #46                 // Method java/lang/String.charAt:(I)C
      57: imul
      58: goto          62
      61: iconst_0
      62: i2l
      63: lor
      64: lstore        5
      66: iinc          8, 1
      69: goto          31
      72: lload         5
      74: invokestatic  #47                 // Method des_setkey:(J)[J
      77: astore        8
      79: iconst_0
      80: istore        9
      82: iconst_2
      83: istore        10
      85: iinc          10, -1
      88: iload         10
      90: iflt          144
      93: iload         10
      95: aload_1
      96: invokevirtual #45                 // Method java/lang/String.length:()I
      99: if_icmpge     111
     102: aload_1
     103: iload         10
     105: invokevirtual #46                 // Method java/lang/String.charAt:(I)C
     108: goto          113
     111: bipush        46
     113: istore        11
     115: aload         4
     117: iload         10
     119: iload         11
     121: i2b
     122: bastore
     123: iload         9
     125: bipush        6
     127: ishl
     128: sipush        255
     131: getstatic     #48                 // Field A64TOI:[B
     134: iload         11
     136: baload
     137: iand
     138: ior
     139: istore        9
     141: goto          85
     144: lload_2
     145: iload         9
     147: bipush        25
     149: aload         8
     151: invokestatic  #49                 // Method des_cipher:(JII[J)J
     154: lstore        10
     156: aload         4
     158: bipush        12
     160: getstatic     #50                 // Field ITOA64:[B
     163: lload         10
     165: l2i
     166: iconst_2
     167: ishl
     168: bipush        63
     170: iand
     171: baload
     172: bastore
     173: lload         10
     175: iconst_4
     176: lshr
     177: lstore        10
     179: bipush        12
     181: istore        12
     183: iinc          12, -1
     186: iload         12
     188: iconst_2
     189: if_icmplt     217
     192: aload         4
     194: iload         12
     196: getstatic     #50                 // Field ITOA64:[B
     199: lload         10
     201: l2i
     202: bipush        63
     204: iand
     205: baload
     206: bastore
     207: lload         10
     209: bipush        6
     211: lshr
     212: lstore        10
     214: goto          183
     217: new           #51                 // class java/lang/String
     220: dup
     221: aload         4
     223: iconst_0
     224: bipush        13
     226: getstatic     #52                 // Field java/nio/charset/StandardCharsets.US_ASCII:Ljava/nio/charset/Charset;
     229: invokespecial #53                 // Method java/lang/String."<init>":([BIILjava/nio/charset/Charset;)V
     232: areturn

  public static void main(java.lang.String[]);
    Code:
       0: aload_0
       1: arraylength
       2: iconst_2
       3: if_icmpeq     18
       6: getstatic     #54                 // Field java/lang/System.err:Ljava/io/PrintStream;
       9: ldc           #55                 // String Usage - java org.eclipse.util.UnixCrypt <key> <salt>
      11: invokevirtual #56                 // Method java/io/PrintStream.println:(Ljava/lang/String;)V
      14: iconst_1
      15: invokestatic  #57                 // Method java/lang/System.exit:(I)V
      18: getstatic     #54                 // Field java/lang/System.err:Ljava/io/PrintStream;
      21: new           #58                 // class java/lang/StringBuilder
      24: dup
      25: invokespecial #59                 // Method java/lang/StringBuilder."<init>":()V
      28: ldc           #60                 // String Crypt=
      30: invokevirtual #61                 // Method java/lang/StringBuilder.append:(Ljava/lang/String;)Ljava/lang/StringBuilder;
      33: aload_0
      34: iconst_0
      35: aaload
      36: aload_0
      37: iconst_1
      38: aaload
      39: invokestatic  #62                 // Method crypt:(Ljava/lang/String;Ljava/lang/String;)Ljava/lang/String;
      42: invokevirtual #61                 // Method java/lang/StringBuilder.append:(Ljava/lang/String;)Ljava/lang/StringBuilder;
      45: invokevirtual #63                 // Method java/lang/StringBuilder.toString:()Ljava/lang/String;
      48: invokevirtual #56                 // Method java/io/PrintStream.println:(Ljava/lang/String;)V
      51: return

  static {};
    Code:
       0: bipush        64
       2: newarray       byte
       4: dup
       5: iconst_0
       6: bipush        58
       8: bastore
       9: dup
      10: iconst_1
      11: bipush        50
      13: bastore
      14: dup
      15: iconst_2
      16: bipush        42
      18: bastore
      19: dup
      20: iconst_3
      21: bipush        34
      23: bastore
      24: dup
      25: iconst_4
      26: bipush        26
      28: bastore
      29: dup
      30: iconst_5
      31: bipush        18
      33: bastore
      34: dup
      35: bipush        6
      37: bipush        10
      39: bastore
      40: dup
      41: bipush        7
      43: iconst_2
      44: bastore
      45: dup
      46: bipush        8
      48: bipush        60
      50: bastore
      51: dup
      52: bipush        9
      54: bipush        52
      56: bastore
      57: dup
      58: bipush        10
      60: bipush        44
      62: bastore
      63: dup
      64: bipush        11
      66: bipush        36
      68: bastore
      69: dup
      70: bipush        12
      72: bipush        28
      74: bastore
      75: dup
      76: bipush        13
      78: bipush        20
      80: bastore
      81: dup
      82: bipush        14
      84: bipush        12
      86: bastore
      87: dup
      88: bipush        15
      90: iconst_4
      91: bastore
      92: dup
      93: bipush        16
      95: bipush        62
      97: bastore
      98: dup
      99: bipush        17
     101: bipush        54
     103: bastore
     104: dup
     105: bipush        18
     107: bipush        46
     109: bastore
     110: dup
     111: bipush        19
     113: bipush        38
     115: bastore
     116: dup
     117: bipush        20
     119: bipush        30
     121: bastore
     122: dup
     123: bipush        21
     125: bipush        22
     127: bastore
     128: dup
     129: bipush        22
     131: bipush        14
     133: bastore
     134: dup
     135: bipush        23
     137: bipush        6
     139: bastore
     140: dup
     141: bipush        24
     143: bipush        64
     145: bastore
     146: dup
     147: bipush        25
     149: bipush        56
     151: bastore
     152: dup
     153: bipush        26
     155: bipush        48
     157: bastore
     158: dup
     159: bipush        27
     161: bipush        40
     163: bastore
     164: dup
     165: bipush        28
     167: bipush        32
     169: bastore
     170: dup
     171: bipush        29
     173: bipush        24
     175: bastore
     176: dup
     177: bipush        30
     179: bipush        16
     181: bastore
     182: dup
     183: bipush        31
     185: bipush        8
     187: bastore
     188: dup
     189: bipush        32
     191: bipush        57
     193: bastore
     194: dup
     195: bipush        33
     197: bipush        49
     199: bastore
     200: dup
     201: bipush        34
     203: bipush        41
     205: bastore
     206: dup
     207: bipush        35
     209: bipush        33
     211: bastore
     212: dup
     213: bipush        36
     215: bipush        25
     217: bastore
     218: dup
     219: bipush        37
     221: bipush        17
     223: bastore
     224: dup
     225: bipush        38
     227: bipush        9
     229: bastore
     230: dup
     231: bipush        39
     233: iconst_1
     234: bastore
     235: dup
     236: bipush        40
     238: bipush        59
     240: bastore
     241: dup
     242: bipush        41
     244: bipush        51
     246: bastore
     247: dup
     248: bipush        42
     250: bipush        43
     252: bastore
     253: dup
     254: bipush        43
     256: bipush        35
     258: bastore
     259: dup
     260: bipush        44
     262: bipush        27
     264: bastore
     265: dup
     266: bipush        45
     268: bipush        19
     270: bastore
     271: dup
     272: bipush        46
     274: bipush        11
     276: bastore
     277: dup
     278: bipush        47
     280: iconst_3
     281: bastore
     282: dup
     283: bipush        48
     285: bipush        61
     287: bastore
     288: dup
     289: bipush        49
     291: bipush        53
     293: bastore
     294: dup
     295: bipush        50
     297: bipush        45
     299: bastore
     300: dup
     301: bipush        51
     303: bipush        37
     305: bastore
     306: dup
     307: bipush        52
     309: bipush        29
     311: bastore
     312: dup
     313: bipush        53
     315: bipush        21
     317: bastore
     318: dup
     319: bipush        54
     321: bipush        13
     323: bastore
     324: dup
     325: bipush        55
     327: iconst_5
     328: bastore
     329: dup
     330: bipush        56
     332: bipush        63
     334: bastore
     335: dup
     336: bipush        57
     338: bipush        55
     340: bastore
     341: dup
     342: bipush        58
     344: bipush        47
     346: bastore
     347: dup
     348: bipush        59
     350: bipush        39
     352: bastore
     353: dup
     354: bipush        60
     356: bipush        31
     358: bastore
     359: dup
     360: bipush        61
     362: bipush        23
     364: bastore
     365: dup
     366: bipush        62
     368: bipush        15
     370: bastore
     371: dup
     372: bipush        63
     374: bipush        7
     376: bastore
     377: putstatic     #64                 // Field IP:[B
     380: bipush        48
     382: newarray       byte
     384: dup
     385: iconst_0
     386: bipush        32
     388: bastore
     389: dup
     390: iconst_1
     391: iconst_1
     392: bastore
     393: dup
     394: iconst_2
     395: iconst_2
     396: bastore
     397: dup
     398: iconst_3
     399: iconst_3
     400: bastore
     401: dup
     402: iconst_4
     403: iconst_4
     404: bastore
     405: dup
     406: iconst_5
     407: iconst_5
     408: bastore
     409: dup
     410: bipush        6
     412: iconst_4
     413: bastore
     414: dup
     415: bipush        7
     417: iconst_5
     418: bastore
     419: dup
     420: bipush        8
     422: bipush        6
     424: bastore
     425: dup
     426: bipush        9
     428: bipush        7
     430: bastore
     431: dup
     432: bipush        10
     434: bipush        8
     436: bastore
     437: dup
     438: bipush        11
     440: bipush        9
     442: bastore
     443: dup
     444: bipush        12
     446: bipush        8
     448: bastore
     449: dup
     450: bipush        13
     452: bipush        9
     454: bastore
     455: dup
     456: bipush        14
     458: bipush        10
     460: bastore
     461: dup
     462: bipush        15
     464: bipush        11
     466: bastore
     467: dup
     468: bipush        16
     470: bipush        12
     472: bastore
     473: dup
     474: bipush        17
     476: bipush        13
     478: bastore
     479: dup
     480: bipush        18
     482: bipush        12
     484: bastore
     485: dup
     486: bipush        19
     488: bipush        13
     490: bastore
     491: dup
     492: bipush        20
     494: bipush        14
     496: bastore
     497: dup
     498: bipush        21
     500: bipush        15
     502: bastore
     503: dup
     504: bipush        22
     506: bipush        16
     508: bastore
     509: dup
     510: bipush        23
     512: bipush        17
     514: bastore
     515: dup
     516: bipush        24
     518: bipush        16
     520: bastore
     521: dup
     522: bipush        25
     524: bipush        17
     526: bastore
     527: dup
     528: bipush        26
     530: bipush        18
     532: bastore
     533: dup
     534: bipush        27
     536: bipush        19
     538: bastore
     539: dup
     540: bipush        28
     542: bipush        20
     544: bastore
     545: dup
     546: bipush        29
     548: bipush        21
     550: bastore
     551: dup
     552: bipush        30
     554: bipush        20
     556: bastore
     557: dup
     558: bipush        31
     560: bipush        21
     562: bastore
     563: dup
     564: bipush        32
     566: bipush        22
     568: bastore
     569: dup
     570: bipush        33
     572: bipush        23
     574: bastore
     575: dup
     576: bipush        34
     578: bipush        24
     580: bastore
     581: dup
     582: bipush        35
     584: bipush        25
     586: bastore
     587: dup
     588: bipush        36
     590: bipush        24
     592: bastore
     593: dup
     594: bipush        37
     596: bipush        25
     598: bastore
     599: dup
     600: bipush        38
     602: bipush        26
     604: bastore
     605: dup
     606: bipush        39
     608: bipush        27
     610: bastore
     611: dup
     612: bipush        40
     614: bipush        28
     616: bastore
     617: dup
     618: bipush        41
     620: bipush        29
     622: bastore
     623: dup
     624: bipush        42
     626: bipush        28
     628: bastore
     629: dup
     630: bipush        43
     632: bipush        29
     634: bastore
     635: dup
     636: bipush        44
     638: bipush        30
     640: bastore
     641: dup
     642: bipush        45
     644: bipush        31
     646: bastore
     647: dup
     648: bipush        46
     650: bipush        32
     652: bastore
     653: dup
     654: bipush        47
     656: iconst_1
     657: bastore
     658: putstatic     #65                 // Field ExpandTr:[B
     661: bipush        56
     663: newarray       byte
     665: dup
     666: iconst_0
     667: bipush        57
     669: bastore
     670: dup
     671: iconst_1
     672: bipush        49
     674: bastore
     675: dup
     676: iconst_2
     677: bipush        41
     679: bastore
     680: dup
     681: iconst_3
     682: bipush        33
     684: bastore
     685: dup
     686: iconst_4
     687: bipush        25
     689: bastore
     690: dup
     691: iconst_5
     692: bipush        17
     694: bastore
     695: dup
     696: bipush        6
     698: bipush        9
     700: bastore
     701: dup
     702: bipush        7
     704: iconst_1
     705: bastore
     706: dup
     707: bipush        8
     709: bipush        58
     711: bastore
     712: dup
     713: bipush        9
     715: bipush        50
     717: bastore
     718: dup
     719: bipush        10
     721: bipush        42
     723: bastore
     724: dup
     725: bipush        11
     727: bipush        34
     729: bastore
     730: dup
     731: bipush        12
     733: bipush        26
     735: bastore
     736: dup
     737: bipush        13
     739: bipush        18
     741: bastore
     742: dup
     743: bipush        14
     745: bipush        10
     747: bastore
     748: dup
     749: bipush        15
     751: iconst_2
     752: bastore
     753: dup
     754: bipush        16
     756: bipush        59
     758: bastore
     759: dup
     760: bipush        17
     762: bipush        51
     764: bastore
     765: dup
     766: bipush        18
     768: bipush        43
     770: bastore
     771: dup
     772: bipush        19
     774: bipush        35
     776: bastore
     777: dup
     778: bipush        20
     780: bipush        27
     782: bastore
     783: dup
     784: bipush        21
     786: bipush        19
     788: bastore
     789: dup
     790: bipush        22
     792: bipush        11
     794: bastore
     795: dup
     796: bipush        23
     798: iconst_3
     799: bastore
     800: dup
     801: bipush        24
     803: bipush        60
     805: bastore
     806: dup
     807: bipush        25
     809: bipush        52
     811: bastore
     812: dup
     813: bipush        26
     815: bipush        44
     817: bastore
     818: dup
     819: bipush        27
     821: bipush        36
     823: bastore
     824: dup
     825: bipush        28
     827: bipush        63
     829: bastore
     830: dup
     831: bipush        29
     833: bipush        55
     835: bastore
     836: dup
     837: bipush        30
     839: bipush        47
     841: bastore
     842: dup
     843: bipush        31
     845: bipush        39
     847: bastore
     848: dup
     849: bipush        32
     851: bipush        31
     853: bastore
     854: dup
     855: bipush        33
     857: bipush        23
     859: bastore
     860: dup
     861: bipush        34
     863: bipush        15
     865: bastore
     866: dup
     867: bipush        35
     869: bipush        7
     871: bastore
     872: dup
     873: bipush        36
     875: bipush        62
     877: bastore
     878: dup
     879: bipush        37
     881: bipush        54
     883: bastore
     884: dup
     885: bipush        38
     887: bipush        46
     889: bastore
     890: dup
     891: bipush        39
     893: bipush        38
     895: bastore
     896: dup
     897: bipush        40
     899: bipush        30
     901: bastore
     902: dup
     903: bipush        41
     905: bipush        22
     907: bastore
     908: dup
     909: bipush        42
     911: bipush        14
     913: bastore
     914: dup
     915: bipush        43
     917: bipush        6
     919: bastore
     920: dup
     921: bipush        44
     923: bipush        61
     925: bastore
     926: dup
     927: bipush        45
     929: bipush        53
     931: bastore
     932: dup
     933: bipush        46
     935: bipush        45
     937: bastore
     938: dup
     939: bipush        47
     941: bipush        37
     943: bastore
     944: dup
     945: bipush        48
     947: bipush        29
     949: bastore
     950: dup
     951: bipush        49
     953: bipush        21
     955: bastore
     956: dup
     957: bipush        50
     959: bipush        13
     961: bastore
     962: dup
     963: bipush        51
     965: iconst_5
     966: bastore
     967: dup
     968: bipush        52
     970: bipush        28
     972: bastore
     973: dup
     974: bipush        53
     976: bipush        20
     978: bastore
     979: dup
     980: bipush        54
     982: bipush        12
     984: bastore
     985: dup
     986: bipush        55
     988: iconst_4
     989: bastore
     990: putstatic     #66                 // Field PC1:[B
     993: bipush        16
     995: newarray       byte
     997: dup
     998: iconst_0
     999: iconst_1
    1000: bastore
    1001: dup
    1002: iconst_1
    1003: iconst_1
    1004: bastore
    1005: dup
    1006: iconst_2
    1007: iconst_2
    1008: bastore
    1009: dup
    1010: iconst_3
    1011: iconst_2
    1012: bastore
    1013: dup
    1014: iconst_4
    1015: iconst_2
    1016: bastore
    1017: dup
    1018: iconst_5
    1019: iconst_2
    1020: bastore
    1021: dup
    1022: bipush        6
    1024: iconst_2
    1025: bastore
    1026: dup
    1027: bipush        7
    1029: iconst_2
    1030: bastore
    1031: dup
    1032: bipush        8
    1034: iconst_1
    1035: bastore
    1036: dup
    1037: bipush        9
    1039: iconst_2
    1040: bastore
    1041: dup
    1042: bipush        10
    1044: iconst_2
    1045: bastore
    1046: dup
    1047: bipush        11
    1049: iconst_2
    1050: bastore
    1051: dup
    1052: bipush        12
    1054: iconst_2
    1055: bastore
    1056: dup
    1057: bipush        13
    1059: iconst_2
    1060: bastore
    1061: dup
    1062: bipush        14
    1064: iconst_2
    1065: bastore
    1066: dup
    1067: bipush        15
    1069: iconst_1
    1070: bastore
    1071: putstatic     #20                 // Field Rotates:[B
    1074: bipush        64
    1076: newarray       byte
    1078: dup
    1079: iconst_0
    1080: bipush        9
    1082: bastore
    1083: dup
    1084: iconst_1
    1085: bipush        18
    1087: bastore
    1088: dup
    1089: iconst_2
    1090: bipush        14
    1092: bastore
    1093: dup
    1094: iconst_3
    1095: bipush        17
    1097: bastore
    1098: dup
    1099: iconst_4
    1100: bipush        11
    1102: bastore
    1103: dup
    1104: iconst_5
    1105: bipush        24
    1107: bastore
    1108: dup
    1109: bipush        6
    1111: iconst_1
    1112: bastore
    1113: dup
    1114: bipush        7
    1116: iconst_5
    1117: bastore
    1118: dup
    1119: bipush        8
    1121: bipush        22
    1123: bastore
    1124: dup
    1125: bipush        9
    1127: bipush        25
    1129: bastore
    1130: dup
    1131: bipush        10
    1133: iconst_3
    1134: bastore
    1135: dup
    1136: bipush        11
    1138: bipush        28
    1140: bastore
    1141: dup
    1142: bipush        12
    1144: bipush        15
    1146: bastore
    1147: dup
    1148: bipush        13
    1150: bipush        6
    1152: bastore
    1153: dup
    1154: bipush        14
    1156: bipush        21
    1158: bastore
    1159: dup
    1160: bipush        15
    1162: bipush        10
    1164: bastore
    1165: dup
    1166: bipush        16
    1168: bipush        35
    1170: bastore
    1171: dup
    1172: bipush        17
    1174: bipush        38
    1176: bastore
    1177: dup
    1178: bipush        18
    1180: bipush        23
    1182: bastore
    1183: dup
    1184: bipush        19
    1186: bipush        19
    1188: bastore
    1189: dup
    1190: bipush        20
    1192: bipush        12
    1194: bastore
    1195: dup
    1196: bipush        21
    1198: iconst_4
    1199: bastore
    1200: dup
    1201: bipush        22
    1203: bipush        26
    1205: bastore
    1206: dup
    1207: bipush        23
    1209: bipush        8
    1211: bastore
    1212: dup
    1213: bipush        24
    1215: bipush        43
    1217: bastore
    1218: dup
    1219: bipush        25
    1221: bipush        54
    1223: bastore
    1224: dup
    1225: bipush        26
    1227: bipush        16
    1229: bastore
    1230: dup
    1231: bipush        27
    1233: bipush        7
    1235: bastore
    1236: dup
    1237: bipush        28
    1239: bipush        27
    1241: bastore
    1242: dup
    1243: bipush        29
    1245: bipush        20
    1247: bastore
    1248: dup
    1249: bipush        30
    1251: bipush        13
    1253: bastore
    1254: dup
    1255: bipush        31
    1257: iconst_2
    1258: bastore
    1259: dup
    1260: bipush        32
    1262: iconst_0
    1263: bastore
    1264: dup
    1265: bipush        33
    1267: iconst_0
    1268: bastore
    1269: dup
    1270: bipush        34
    1272: bipush        41
    1274: bastore
    1275: dup
    1276: bipush        35
    1278: bipush        52
    1280: bastore
    1281: dup
    1282: bipush        36
    1284: bipush        31
    1286: bastore
    1287: dup
    1288: bipush        37
    1290: bipush        37
    1292: bastore
    1293: dup
    1294: bipush        38
    1296: bipush        47
    1298: bastore
    1299: dup
    1300: bipush        39
    1302: bipush        55
    1304: bastore
    1305: dup
    1306: bipush        40
    1308: iconst_0
    1309: bastore
    1310: dup
    1311: bipush        41
    1313: iconst_0
    1314: bastore
    1315: dup
    1316: bipush        42
    1318: bipush        30
    1320: bastore
    1321: dup
    1322: bipush        43
    1324: bipush        40
    1326: bastore
    1327: dup
    1328: bipush        44
    1330: bipush        51
    1332: bastore
    1333: dup
    1334: bipush        45
    1336: bipush        45
    1338: bastore
    1339: dup
    1340: bipush        46
    1342: bipush        33
    1344: bastore
    1345: dup
    1346: bipush        47
    1348: bipush        48
    1350: bastore
    1351: dup
    1352: bipush        48
    1354: iconst_0
    1355: bastore
    1356: dup
    1357: bipush        49
    1359: iconst_0
    1360: bastore
    1361: dup
    1362: bipush        50
    1364: bipush        44
    1366: bastore
    1367: dup
    1368: bipush        51
    1370: bipush        49
    1372: bastore
    1373: dup
    1374: bipush        52
    1376: bipush        39
    1378: bastore
    1379: dup
    1380: bipush        53
    1382: bipush        56
    1384: bastore
    1385: dup
    1386: bipush        54
    1388: bipush        34
    1390: bastore
    1391: dup
    1392: bipush        55
    1394: bipush        53
    1396: bastore
    1397: dup
    1398: bipush        56
    1400: iconst_0
    1401: bastore
    1402: dup
    1403: bipush        57
    1405: iconst_0
    1406: bastore
    1407: dup
    1408: bipush        58
    1410: bipush        46
    1412: bastore
    1413: dup
    1414: bipush        59
    1416: bipush        42
    1418: bastore
    1419: dup
    1420: bipush        60
    1422: bipush        50
    1424: bastore
    1425: dup
    1426: bipush        61
    1428: bipush        36
    1430: bastore
    1431: dup
    1432: bipush        62
    1434: bipush        29
    1436: bastore
    1437: dup
    1438: bipush        63
    1440: bipush        32
    1442: bastore
    1443: putstatic     #67                 // Field PC2:[B
    1446: bipush        8
    1448: anewarray     #68                 // class "[B"
    1451: dup
    1452: iconst_0
    1453: bipush        64
    1455: newarray       byte
    1457: dup
    1458: iconst_0
    1459: bipush        14
    1461: bastore
    1462: dup
    1463: iconst_1
    1464: iconst_4
    1465: bastore
    1466: dup
    1467: iconst_2
    1468: bipush        13
    1470: bastore
    1471: dup
    1472: iconst_3
    1473: iconst_1
    1474: bastore
    1475: dup
    1476: iconst_4
    1477: iconst_2
    1478: bastore
    1479: dup
    1480: iconst_5
    1481: bipush        15
    1483: bastore
    1484: dup
    1485: bipush        6
    1487: bipush        11
    1489: bastore
    1490: dup
    1491: bipush        7
    1493: bipush        8
    1495: bastore
    1496: dup
    1497: bipush        8
    1499: iconst_3
    1500: bastore
    1501: dup
    1502: bipush        9
    1504: bipush        10
    1506: bastore
    1507: dup
    1508: bipush        10
    1510: bipush        6
    1512: bastore
    1513: dup
    1514: bipush        11
    1516: bipush        12
    1518: bastore
    1519: dup
    1520: bipush        12
    1522: iconst_5
    1523: bastore
    1524: dup
    1525: bipush        13
    1527: bipush        9
    1529: bastore
    1530: dup
    1531: bipush        14
    1533: iconst_0
    1534: bastore
    1535: dup
    1536: bipush        15
    1538: bipush        7
    1540: bastore
    1541: dup
    1542: bipush        16
    1544: iconst_0
    1545: bastore
    1546: dup
    1547: bipush        17
    1549: bipush        15
    1551: bastore
    1552: dup
    1553: bipush        18
    1555: bipush        7
    1557: bastore
    1558: dup
    1559: bipush        19
    1561: iconst_4
    1562: bastore
    1563: dup
    1564: bipush        20
    1566: bipush        14
    1568: bastore
    1569: dup
    1570: bipush        21
    1572: iconst_2
    1573: bastore
    1574: dup
    1575: bipush        22
    1577: bipush        13
    1579: bastore
    1580: dup
    1581: bipush        23
    1583: iconst_1
    1584: bastore
    1585: dup
    1586: bipush        24
    1588: bipush        10
    1590: bastore
    1591: dup
    1592: bipush        25
    1594: bipush        6
    1596: bastore
    1597: dup
    1598: bipush        26
    1600: bipush        12
    1602: bastore
    1603: dup
    1604: bipush        27
    1606: bipush        11
    1608: bastore
    1609: dup
    1610: bipush        28
    1612: bipush        9
    1614: bastore
    1615: dup
    1616: bipush        29
    1618: iconst_5
    1619: bastore
    1620: dup
    1621: bipush        30
    1623: iconst_3
    1624: bastore
    1625: dup
    1626: bipush        31
    1628: bipush        8
    1630: bastore
    1631: dup
    1632: bipush        32
    1634: iconst_4
    1635: bastore
    1636: dup
    1637: bipush        33
    1639: iconst_1
    1640: bastore
    1641: dup
    1642: bipush        34
    1644: bipush        14
    1646: bastore
    1647: dup
    1648: bipush        35
    1650: bipush        8
    1652: bastore
    1653: dup
    1654: bipush        36
    1656: bipush        13
    1658: bastore
    1659: dup
    1660: bipush        37
    1662: bipush        6
    1664: bastore
    1665: dup
    1666: bipush        38
    1668: iconst_2
    1669: bastore
    1670: dup
    1671: bipush        39
    1673: bipush        11
    1675: bastore
    1676: dup
    1677: bipush        40
    1679: bipush        15
    1681: bastore
    1682: dup
    1683: bipush        41
    1685: bipush        12
    1687: bastore
    1688: dup
    1689: bipush        42
    1691: bipush        9
    1693: bastore
    1694: dup
    1695: bipush        43
    1697: bipush        7
    1699: bastore
    1700: dup
    1701: bipush        44
    1703: iconst_3
    1704: bastore
    1705: dup
    1706: bipush        45
    1708: bipush        10
    1710: bastore
    1711: dup
    1712: bipush        46
    1714: iconst_5
    1715: bastore
    1716: dup
    1717: bipush        47
    1719: iconst_0
    1720: bastore
    1721: dup
    1722: bipush        48
    1724: bipush        15
    1726: bastore
    1727: dup
    1728: bipush        49
    1730: bipush        12
    1732: bastore
    1733: dup
    1734: bipush        50
    1736: bipush        8
    1738: bastore
    1739: dup
    1740: bipush        51
    1742: iconst_2
    1743: bastore
    1744: dup
    1745: bipush        52
    1747: iconst_4
    1748: bastore
    1749: dup
    1750: bipush        53
    1752: bipush        9
    1754: bastore
    1755: dup
    1756: bipush        54
    1758: iconst_1
    1759: bastore
    1760: dup
    1761: bipush        55
    1763: bipush        7
    1765: bastore
    1766: dup
    1767: bipush        56
    1769: iconst_5
    1770: bastore
    1771: dup
    1772: bipush        57
    1774: bipush        11
    1776: bastore
    1777: dup
    1778: bipush        58
    1780: iconst_3
    1781: bastore
    1782: dup
    1783: bipush        59
    1785: bipush        14
    1787: bastore
    1788: dup
    1789: bipush        60
    1791: bipush        10
    1793: bastore
    1794: dup
    1795: bipush        61
    1797: iconst_0
    1798: bastore
    1799: dup
    1800: bipush        62
    1802: bipush        6
    1804: bastore
    1805: dup
    1806: bipush        63
    1808: bipush        13
    1810: bastore
    1811: aastore
    1812: dup
    1813: iconst_1
    1814: bipush        64
    1816: newarray       byte
    1818: dup
    1819: iconst_0
    1820: bipush        15
    1822: bastore
    1823: dup
    1824: iconst_1
    1825: iconst_1
    1826: bastore
    1827: dup
    1828: iconst_2
    1829: bipush        8
    1831: bastore
    1832: dup
    1833: iconst_3
    1834: bipush        14
    1836: bastore
    1837: dup
    1838: iconst_4
    1839: bipush        6
    1841: bastore
    1842: dup
    1843: iconst_5
    1844: bipush        11
    1846: bastore
    1847: dup
    1848: bipush        6
    1850: iconst_3
    1851: bastore
    1852: dup
    1853: bipush        7
    1855: iconst_4
    1856: bastore
    1857: dup
    1858: bipush        8
    1860: bipush        9
    1862: bastore
    1863: dup
    1864: bipush        9
    1866: bipush        7
    1868: bastore
    1869: dup
    1870: bipush        10
    1872: iconst_2
    1873: bastore
    1874: dup
    1875: bipush        11
    1877: bipush        13
    1879: bastore
    1880: dup
    1881: bipush        12
    1883: bipush        12
    1885: bastore
    1886: dup
    1887: bipush        13
    1889: iconst_0
    1890: bastore
    1891: dup
    1892: bipush        14
    1894: iconst_5
    1895: bastore
    1896: dup
    1897: bipush        15
    1899: bipush        10
    1901: bastore
    1902: dup
    1903: bipush        16
    1905: iconst_3
    1906: bastore
    1907: dup
    1908: bipush        17
    1910: bipush        13
    1912: bastore
    1913: dup
    1914: bipush        18
    1916: iconst_4
    1917: bastore
    1918: dup
    1919: bipush        19
    1921: bipush        7
    1923: bastore
    1924: dup
    1925: bipush        20
    1927: bipush        15
    1929: bastore
    1930: dup
    1931: bipush        21
    1933: iconst_2
    1934: bastore
    1935: dup
    1936: bipush        22
    1938: bipush        8
    1940: bastore
    1941: dup
    1942: bipush        23
    1944: bipush        14
    1946: bastore
    1947: dup
    1948: bipush        24
    1950: bipush        12
    1952: bastore
    1953: dup
    1954: bipush        25
    1956: iconst_0
    1957: bastore
    1958: dup
    1959: bipush        26
    1961: iconst_1
    1962: bastore
    1963: dup
    1964: bipush        27
    1966: bipush        10
    1968: bastore
    1969: dup
    1970: bipush        28
    1972: bipush        6
    1974: bastore
    1975: dup
    1976: bipush        29
    1978: bipush        9
    1980: bastore
    1981: dup
    1982: bipush        30
    1984: bipush        11
    1986: bastore
    1987: dup
    1988: bipush        31
    1990: iconst_5
    1991: bastore
    1992: dup
    1993: bipush        32
    1995: iconst_0
    1996: bastore
    1997: dup
    1998: bipush        33
    2000: bipush        14
    2002: bastore
    2003: dup
    2004: bipush        34
    2006: bipush        7
    2008: bastore
    2009: dup
    2010: bipush        35
    2012: bipush        11
    2014: bastore
    2015: dup
    2016: bipush        36
    2018: bipush        10
    2020: bastore
    2021: dup
    2022: bipush        37
    2024: iconst_4
    2025: bastore
    2026: dup
    2027: bipush        38
    2029: bipush        13
    2031: bastore
    2032: dup
    2033: bipush        39
    2035: iconst_1
    2036: bastore
    2037: dup
    2038: bipush        40
    2040: iconst_5
    2041: bastore
    2042: dup
    2043: bipush        41
    2045: bipush        8
    2047: bastore
    2048: dup
    2049: bipush        42
    2051: bipush        12
    2053: bastore
    2054: dup
    2055: bipush        43
    2057: bipush        6
    2059: bastore
    2060: dup
    2061: bipush        44
    2063: bipush        9
    2065: bastore
    2066: dup
    2067: bipush        45
    2069: iconst_3
    2070: bastore
    2071: dup
    2072: bipush        46
    2074: iconst_2
    2075: bastore
    2076: dup
    2077: bipush        47
    2079: bipush        15
    2081: bastore
    2082: dup
    2083: bipush        48
    2085: bipush        13
    2087: bastore
    2088: dup
    2089: bipush        49
    2091: bipush        8
    2093: bastore
    2094: dup
    2095: bipush        50
    2097: bipush        10
    2099: bastore
    2100: dup
    2101: bipush        51
    2103: iconst_1
    2104: bastore
    2105: dup
    2106: bipush        52
    2108: iconst_3
    2109: bastore
    2110: dup
    2111: bipush        53
    2113: bipush        15
    2115: bastore
    2116: dup
    2117: bipush        54
    2119: iconst_4
    2120: bastore
    2121: dup
    2122: bipush        55
    2124: iconst_2
    2125: bastore
    2126: dup
    2127: bipush        56
    2129: bipush        11
    2131: bastore
    2132: dup
    2133: bipush        57
    2135: bipush        6
    2137: bastore
    2138: dup
    2139: bipush        58
    2141: bipush        7
    2143: bastore
    2144: dup
    2145: bipush        59
    2147: bipush        12
    2149: bastore
    2150: dup
    2151: bipush        60
    2153: iconst_0
    2154: bastore
    2155: dup
    2156: bipush        61
    2158: iconst_5
    2159: bastore
    2160: dup
    2161: bipush        62
    2163: bipush        14
    2165: bastore
    2166: dup
    2167: bipush        63
    2169: bipush        9
    2171: bastore
    2172: aastore
    2173: dup
    2174: iconst_2
    2175: bipush        64
    2177: newarray       byte
    2179: dup
    2180: iconst_0
    2181: bipush        10
    2183: bastore
    2184: dup
    2185: iconst_1
    2186: iconst_0
    2187: bastore
    2188: dup
    2189: iconst_2
    2190: bipush        9
    2192: bastore
    2193: dup
    2194: iconst_3
    2195: bipush        14
    2197: bastore
    2198: dup
    2199: iconst_4
    2200: bipush        6
    2202: bastore
    2203: dup
    2204: iconst_5
    2205: iconst_3
    2206: bastore
    2207: dup
    2208: bipush        6
    2210: bipush        15
    2212: bastore
    2213: dup
    2214: bipush        7
    2216: iconst_5
    2217: bastore
    2218: dup
    2219: bipush        8
    2221: iconst_1
    2222: bastore
    2223: dup
    2224: bipush        9
    2226: bipush        13
    2228: bastore
    2229: dup
    2230: bipush        10
    2232: bipush        12
    2234: bastore
    2235: dup
    2236: bipush        11
    2238: bipush        7
    2240: bastore
    2241: dup
    2242: bipush        12
    2244: bipush        11
    2246: bastore
    2247: dup
    2248: bipush        13
    2250: iconst_4
    2251: bastore
    2252: dup
    2253: bipush        14
    2255: iconst_2
    2256: bastore
    2257: dup
    2258: bipush        15
    2260: bipush        8
    2262: bastore
    2263: dup
    2264: bipush        16
    2266: bipush        13
    2268: bastore
    2269: dup
    2270: bipush        17
    2272: bipush        7
    2274: bastore
    2275: dup
    2276: bipush        18
    2278: iconst_0
    2279: bastore
    2280: dup
    2281: bipush        19
    2283: bipush        9
    2285: bastore
    2286: dup
    2287: bipush        20
    2289: iconst_3
    2290: bastore
    2291: dup
    2292: bipush        21
    2294: iconst_4
    2295: bastore
    2296: dup
    2297: bipush        22
    2299: bipush        6
    2301: bastore
    2302: dup
    2303: bipush        23
    2305: bipush        10
    2307: bastore
    2308: dup
    2309: bipush        24
    2311: iconst_2
    2312: bastore
    2313: dup
    2314: bipush        25
    2316: bipush        8
    2318: bastore
    2319: dup
    2320: bipush        26
    2322: iconst_5
    2323: bastore
    2324: dup
    2325: bipush        27
    2327: bipush        14
    2329: bastore
    2330: dup
    2331: bipush        28
    2333: bipush        12
    2335: bastore
    2336: dup
    2337: bipush        29
    2339: bipush        11
    2341: bastore
    2342: dup
    2343: bipush        30
    2345: bipush        15
    2347: bastore
    2348: dup
    2349: bipush        31
    2351: iconst_1
    2352: bastore
    2353: dup
    2354: bipush        32
    2356: bipush        13
    2358: bastore
    2359: dup
    2360: bipush        33
    2362: bipush        6
    2364: bastore
    2365: dup
    2366: bipush        34
    2368: iconst_4
    2369: bastore
    2370: dup
    2371: bipush        35
    2373: bipush        9
    2375: bastore
    2376: dup
    2377: bipush        36
    2379: bipush        8
    2381: bastore
    2382: dup
    2383: bipush        37
    2385: bipush        15
    2387: bastore
    2388: dup
    2389: bipush        38
    2391: iconst_3
    2392: bastore
    2393: dup
    2394: bipush        39
    2396: iconst_0
    2397: bastore
    2398: dup
    2399: bipush        40
    2401: bipush        11
    2403: bastore
    2404: dup
    2405: bipush        41
    2407: iconst_1
    2408: bastore
    2409: dup
    2410: bipush        42
    2412: iconst_2
    2413: bastore
    2414: dup
    2415: bipush        43
    2417: bipush        12
    2419: bastore
    2420: dup
    2421: bipush        44
    2423: iconst_5
    2424: bastore
    2425: dup
    2426: bipush        45
    2428: bipush        10
    2430: bastore
    2431: dup
    2432: bipush        46
    2434: bipush        14
    2436: bastore
    2437: dup
    2438: bipush        47
    2440: bipush        7
    2442: bastore
    2443: dup
    2444: bipush        48
    2446: iconst_1
    2447: bastore
    2448: dup
    2449: bipush        49
    2451: bipush        10
    2453: bastore
    2454: dup
    2455: bipush        50
    2457: bipush        13
    2459: bastore
    2460: dup
    2461: bipush        51
    2463: iconst_0
    2464: bastore
    2465: dup
    2466: bipush        52
    2468: bipush        6
    2470: bastore
    2471: dup
    2472: bipush        53
    2474: bipush        9
    2476: bastore
    2477: dup
    2478: bipush        54
    2480: bipush        8
    2482: bastore
    2483: dup
    2484: bipush        55
    2486: bipush        7
    2488: bastore
    2489: dup
    2490: bipush        56
    2492: iconst_4
    2493: bastore
    2494: dup
    2495: bipush        57
    2497: bipush        15
    2499: bastore
    2500: dup
    2501: bipush        58
    2503: bipush        14
    2505: bastore
    2506: dup
    2507: bipush        59
    2509: iconst_3
    2510: bastore
    2511: dup
    2512: bipush        60
    2514: bipush        11
    2516: bastore
    2517: dup
    2518: bipush        61
    2520: iconst_5
    2521: bastore
    2522: dup
    2523: bipush        62
    2525: iconst_2
    2526: bastore
    2527: dup
    2528: bipush        63
    2530: bipush        12
    2532: bastore
    2533: aastore
    2534: dup
    2535: iconst_3
    2536: bipush        64
    2538: newarray       byte
    2540: dup
    2541: iconst_0
    2542: bipush        7
    2544: bastore
    2545: dup
    2546: iconst_1
    2547: bipush        13
    2549: bastore
    2550: dup
    2551: iconst_2
    2552: bipush        14
    2554: bastore
    2555: dup
    2556: iconst_3
    2557: iconst_3
    2558: bastore
    2559: dup
    2560: iconst_4
    2561: iconst_0
    2562: bastore
    2563: dup
    2564: iconst_5
    2565: bipush        6
    2567: bastore
    2568: dup
    2569: bipush        6
    2571: bipush        9
    2573: bastore
    2574: dup
    2575: bipush        7
    2577: bipush        10
    2579: bastore
    2580: dup
    2581: bipush        8
    2583: iconst_1
    2584: bastore
    2585: dup
    2586: bipush        9
    2588: iconst_2
    2589: bastore
    2590: dup
    2591: bipush        10
    2593: bipush        8
    2595: bastore
    2596: dup
    2597: bipush        11
    2599: iconst_5
    2600: bastore
    2601: dup
    2602: bipush        12
    2604: bipush        11
    2606: bastore
    2607: dup
    2608: bipush        13
    2610: bipush        12
    2612: bastore
    2613: dup
    2614: bipush        14
    2616: iconst_4
    2617: bastore
    2618: dup
    2619: bipush        15
    2621: bipush        15
    2623: bastore
    2624: dup
    2625: bipush        16
    2627: bipush        13
    2629: bastore
    2630: dup
    2631: bipush        17
    2633: bipush        8
    2635: bastore
    2636: dup
    2637: bipush        18
    2639: bipush        11
    2641: bastore
    2642: dup
    2643: bipush        19
    2645: iconst_5
    2646: bastore
    2647: dup
    2648: bipush        20
    2650: bipush        6
    2652: bastore
    2653: dup
    2654: bipush        21
    2656: bipush        15
    2658: bastore
    2659: dup
    2660: bipush        22
    2662: iconst_0
    2663: bastore
    2664: dup
    2665: bipush        23
    2667: iconst_3
    2668: bastore
    2669: dup
    2670: bipush        24
    2672: iconst_4
    2673: bastore
    2674: dup
    2675: bipush        25
    2677: bipush        7
    2679: bastore
    2680: dup
    2681: bipush        26
    2683: iconst_2
    2684: bastore
    2685: dup
    2686: bipush        27
    2688: bipush        12
    2690: bastore
    2691: dup
    2692: bipush        28
    2694: iconst_1
    2695: bastore
    2696: dup
    2697: bipush        29
    2699: bipush        10
    2701: bastore
    2702: dup
    2703: bipush        30
    2705: bipush        14
    2707: bastore
    2708: dup
    2709: bipush        31
    2711: bipush        9
    2713: bastore
    2714: dup
    2715: bipush        32
    2717: bipush        10
    2719: bastore
    2720: dup
    2721: bipush        33
    2723: bipush        6
    2725: bastore
    2726: dup
    2727: bipush        34
    2729: bipush        9
    2731: bastore
    2732: dup
    2733: bipush        35
    2735: iconst_0
    2736: bastore
    2737: dup
    2738: bipush        36
    2740: bipush        12
    2742: bastore
    2743: dup
    2744: bipush        37
    2746: bipush        11
    2748: bastore
    2749: dup
    2750: bipush        38
    2752: bipush        7
    2754: bastore
    2755: dup
    2756: bipush        39
    2758: bipush        13
    2760: bastore
    2761: dup
    2762: bipush        40
    2764: bipush        15
    2766: bastore
    2767: dup
    2768: bipush        41
    2770: iconst_1
    2771: bastore
    2772: dup
    2773: bipush        42
    2775: iconst_3
    2776: bastore
    2777: dup
    2778: bipush        43
    2780: bipush        14
    2782: bastore
    2783: dup
    2784: bipush        44
    2786: iconst_5
    2787: bastore
    2788: dup
    2789: bipush        45
    2791: iconst_2
    2792: bastore
    2793: dup
    2794: bipush        46
    2796: bipush        8
    2798: bastore
    2799: dup
    2800: bipush        47
    2802: iconst_4
    2803: bastore
    2804: dup
    2805: bipush        48
    2807: iconst_3
    2808: bastore
    2809: dup
    2810: bipush        49
    2812: bipush        15
    2814: bastore
    2815: dup
    2816: bipush        50
    2818: iconst_0
    2819: bastore
    2820: dup
    2821: bipush        51
    2823: bipush        6
    2825: bastore
    2826: dup
    2827: bipush        52
    2829: bipush        10
    2831: bastore
    2832: dup
    2833: bipush        53
    2835: iconst_1
    2836: bastore
    2837: dup
    2838: bipush        54
    2840: bipush        13
    2842: bastore
    2843: dup
    2844: bipush        55
    2846: bipush        8
    2848: bastore
    2849: dup
    2850: bipush        56
    2852: bipush        9
    2854: bastore
    2855: dup
    2856: bipush        57
    2858: iconst_4
    2859: bastore
    2860: dup
    2861: bipush        58
    2863: iconst_5
    2864: bastore
    2865: dup
    2866: bipush        59
    2868: bipush        11
    2870: bastore
    2871: dup
    2872: bipush        60
    2874: bipush        12
    2876: bastore
    2877: dup
    2878: bipush        61
    2880: bipush        7
    2882: bastore
    2883: dup
    2884: bipush        62
    2886: iconst_2
    2887: bastore
    2888: dup
    2889: bipush        63
    2891: bipush        14
    2893: bastore
    2894: aastore
    2895: dup
    2896: iconst_4
    2897: bipush        64
    2899: newarray       byte
    2901: dup
    2902: iconst_0
    2903: iconst_2
    2904: bastore
    2905: dup
    2906: iconst_1
    2907: bipush        12
    2909: bastore
    2910: dup
    2911: iconst_2
    2912: iconst_4
    2913: bastore
    2914: dup
    2915: iconst_3
    2916: iconst_1
    2917: bastore
    2918: dup
    2919: iconst_4
    2920: bipush        7
    2922: bastore
    2923: dup
    2924: iconst_5
    2925: bipush        10
    2927: bastore
    2928: dup
    2929: bipush        6
    2931: bipush        11
    2933: bastore
    2934: dup
    2935: bipush        7
    2937: bipush        6
    2939: bastore
    2940: dup
    2941: bipush        8
    2943: bipush        8
    2945: bastore
    2946: dup
    2947: bipush        9
    2949: iconst_5
    2950: bastore
    2951: dup
    2952: bipush        10
    2954: iconst_3
    2955: bastore
    2956: dup
    2957: bipush        11
    2959: bipush        15
    2961: bastore
    2962: dup
    2963: bipush        12
    2965: bipush        13
    2967: bastore
    2968: dup
    2969: bipush        13
    2971: iconst_0
    2972: bastore
    2973: dup
    2974: bipush        14
    2976: bipush        14
    2978: bastore
    2979: dup
    2980: bipush        15
    2982: bipush        9
    2984: bastore
    2985: dup
    2986: bipush        16
    2988: bipush        14
    2990: bastore
    2991: dup
    2992: bipush        17
    2994: bipush        11
    2996: bastore
    2997: dup
    2998: bipush        18
    3000: iconst_2
    3001: bastore
    3002: dup
    3003: bipush        19
    3005: bipush        12
    3007: bastore
    3008: dup
    3009: bipush        20
    3011: iconst_4
    3012: bastore
    3013: dup
    3014: bipush        21
    3016: bipush        7
    3018: bastore
    3019: dup
    3020: bipush        22
    3022: bipush        13
    3024: bastore
    3025: dup
    3026: bipush        23
    3028: iconst_1
    3029: bastore
    3030: dup
    3031: bipush        24
    3033: iconst_5
    3034: bastore
    3035: dup
    3036: bipush        25
    3038: iconst_0
    3039: bastore
    3040: dup
    3041: bipush        26
    3043: bipush        15
    3045: bastore
    3046: dup
    3047: bipush        27
    3049: bipush        10
    3051: bastore
    3052: dup
    3053: bipush        28
    3055: iconst_3
    3056: bastore
    3057: dup
    3058: bipush        29
    3060: bipush        9
    3062: bastore
    3063: dup
    3064: bipush        30
    3066: bipush        8
    3068: bastore
    3069: dup
    3070: bipush        31
    3072: bipush        6
    3074: bastore
    3075: dup
    3076: bipush        32
    3078: iconst_4
    3079: bastore
    3080: dup
    3081: bipush        33
    3083: iconst_2
    3084: bastore
    3085: dup
    3086: bipush        34
    3088: iconst_1
    3089: bastore
    3090: dup
    3091: bipush        35
    3093: bipush        11
    3095: bastore
    3096: dup
    3097: bipush        36
    3099: bipush        10
    3101: bastore
    3102: dup
    3103: bipush        37
    3105: bipush        13
    3107: bastore
    3108: dup
    3109: bipush        38
    3111: bipush        7
    3113: bastore
    3114: dup
    3115: bipush        39
    3117: bipush        8
    3119: bastore
    3120: dup
    3121: bipush        40
    3123: bipush        15
    3125: bastore
    3126: dup
    3127: bipush        41
    3129: bipush        9
    3131: bastore
    3132: dup
    3133: bipush        42
    3135: bipush        12
    3137: bastore
    3138: dup
    3139: bipush        43
    3141: iconst_5
    3142: bastore
    3143: dup
    3144: bipush        44
    3146: bipush        6
    3148: bastore
    3149: dup
    3150: bipush        45
    3152: iconst_3
    3153: bastore
    3154: dup
    3155: bipush        46
    3157: iconst_0
    3158: bastore
    3159: dup
    3160: bipush        47
    3162: bipush        14
    3164: bastore
    3165: dup
    3166: bipush        48
    3168: bipush        11
    3170: bastore
    3171: dup
    3172: bipush        49
    3174: bipush        8
    3176: bastore
    3177: dup
    3178: bipush        50
    3180: bipush        12
    3182: bastore
    3183: dup
    3184: bipush        51
    3186: bipush        7
    3188: bastore
    3189: dup
    3190: bipush        52
    3192: iconst_1
    3193: bastore
    3194: dup
    3195: bipush        53
    3197: bipush        14
    3199: bastore
    3200: dup
    3201: bipush        54
    3203: iconst_2
    3204: bastore
    3205: dup
    3206: bipush        55
    3208: bipush        13
    3210: bastore
    3211: dup
    3212: bipush        56
    3214: bipush        6
    3216: bastore
    3217: dup
    3218: bipush        57
    3220: bipush        15
    3222: bastore
    3223: dup
    3224: bipush        58
    3226: iconst_0
    3227: bastore
    3228: dup
    3229: bipush        59
    3231: bipush        9
    3233: bastore
    3234: dup
    3235: bipush        60
    3237: bipush        10
    3239: bastore
    3240: dup
    3241: bipush        61
    3243: iconst_4
    3244: bastore
    3245: dup
    3246: bipush        62
    3248: iconst_5
    3249: bastore
    3250: dup
    3251: bipush        63
    3253: iconst_3
    3254: bastore
    3255: aastore
    3256: dup
    3257: iconst_5
    3258: bipush        64
    3260: newarray       byte
    3262: dup
    3263: iconst_0
    3264: bipush        12
    3266: bastore
    3267: dup
    3268: iconst_1
    3269: iconst_1
    3270: bastore
    3271: dup
    3272: iconst_2
    3273: bipush        10
    3275: bastore
    3276: dup
    3277: iconst_3
    3278: bipush        15
    3280: bastore
    3281: dup
    3282: iconst_4
    3283: bipush        9
    3285: bastore
    3286: dup
    3287: iconst_5
    3288: iconst_2
    3289: bastore
    3290: dup
    3291: bipush        6
    3293: bipush        6
    3295: bastore
    3296: dup
    3297: bipush        7
    3299: bipush        8
    3301: bastore
    3302: dup
    3303: bipush        8
    3305: iconst_0
    3306: bastore
    3307: dup
    3308: bipush        9
    3310: bipush        13
    3312: bastore
    3313: dup
    3314: bipush        10
    3316: iconst_3
    3317: bastore
    3318: dup
    3319: bipush        11
    3321: iconst_4
    3322: bastore
    3323: dup
    3324: bipush        12
    3326: bipush        14
    3328: bastore
    3329: dup
    3330: bipush        13
    3332: bipush        7
    3334: bastore
    3335: dup
    3336: bipush        14
    3338: iconst_5
    3339: bastore
    3340: dup
    3341: bipush        15
    3343: bipush        11
    3345: bastore
    3346: dup
    3347: bipush        16
    3349: bipush        10
    3351: bastore
    3352: dup
    3353: bipush        17
    3355: bipush        15
    3357: bastore
    3358: dup
    3359: bipush        18
    3361: iconst_4
    3362: bastore
    3363: dup
    3364: bipush        19
    3366: iconst_2
    3367: bastore
    3368: dup
    3369: bipush        20
    3371: bipush        7
    3373: bastore
    3374: dup
    3375: bipush        21
    3377: bipush        12
    3379: bastore
    3380: dup
    3381: bipush        22
    3383: bipush        9
    3385: bastore
    3386: dup
    3387: bipush        23
    3389: iconst_5
    3390: bastore
    3391: dup
    3392: bipush        24
    3394: bipush        6
    3396: bastore
    3397: dup
    3398: bipush        25
    3400: iconst_1
    3401: bastore
    3402: dup
    3403: bipush        26
    3405: bipush        13
    3407: bastore
    3408: dup
    3409: bipush        27
    3411: bipush        14
    3413: bastore
    3414: dup
    3415: bipush        28
    3417: iconst_0
    3418: bastore
    3419: dup
    3420: bipush        29
    3422: bipush        11
    3424: bastore
    3425: dup
    3426: bipush        30
    3428: iconst_3
    3429: bastore
    3430: dup
    3431: bipush        31
    3433: bipush        8
    3435: bastore
    3436: dup
    3437: bipush        32
    3439: bipush        9
    3441: bastore
    3442: dup
    3443: bipush        33
    3445: bipush        14
    3447: bastore
    3448: dup
    3449: bipush        34
    3451: bipush        15
    3453: bastore
    3454: dup
    3455: bipush        35
    3457: iconst_5
    3458: bastore
    3459: dup
    3460: bipush        36
    3462: iconst_2
    3463: bastore
    3464: dup
    3465: bipush        37
    3467: bipush        8
    3469: bastore
    3470: dup
    3471: bipush        38
    3473: bipush        12
    3475: bastore
    3476: dup
    3477: bipush        39
    3479: iconst_3
    3480: bastore
    3481: dup
    3482: bipush        40
    3484: bipush        7
    3486: bastore
    3487: dup
    3488: bipush        41
    3490: iconst_0
    3491: bastore
    3492: dup
    3493: bipush        42
    3495: iconst_4
    3496: bastore
    3497: dup
    3498: bipush        43
    3500: bipush        10
    3502: bastore
    3503: dup
    3504: bipush        44
    3506: iconst_1
    3507: bastore
    3508: dup
    3509: bipush        45
    3511: bipush        13
    3513: bastore
    3514: dup
    3515: bipush        46
    3517: bipush        11
    3519: bastore
    3520: dup
    3521: bipush        47
    3523: bipush        6
    3525: bastore
    3526: dup
    3527: bipush        48
    3529: iconst_4
    3530: bastore
    3531: dup
    3532: bipush        49
    3534: iconst_3
    3535: bastore
    3536: dup
    3537: bipush        50
    3539: iconst_2
    3540: bastore
    3541: dup
    3542: bipush        51
    3544: bipush        12
    3546: bastore
    3547: dup
    3548: bipush        52
    3550: bipush        9
    3552: bastore
    3553: dup
    3554: bipush        53
    3556: iconst_5
    3557: bastore
    3558: dup
    3559: bipush        54
    3561: bipush        15
    3563: bastore
    3564: dup
    3565: bipush        55
    3567: bipush        10
    3569: bastore
    3570: dup
    3571: bipush        56
    3573: bipush        11
    3575: bastore
    3576: dup
    3577: bipush        57
    3579: bipush        14
    3581: bastore
    3582: dup
    3583: bipush        58
    3585: iconst_1
    3586: bastore
    3587: dup
    3588: bipush        59
    3590: bipush        7
    3592: bastore
    3593: dup
    3594: bipush        60
    3596: bipush        6
    3598: bastore
    3599: dup
    3600: bipush        61
    3602: iconst_0
    3603: bastore
    3604: dup
    3605: bipush        62
    3607: bipush        8
    3609: bastore
    3610: dup
    3611: bipush        63
    3613: bipush        13
    3615: bastore
    3616: aastore
    3617: dup
    3618: bipush        6
    3620: bipush        64
    3622: newarray       byte
    3624: dup
    3625: iconst_0
    3626: iconst_4
    3627: bastore
    3628: dup
    3629: iconst_1
    3630: bipush        11
    3632: bastore
    3633: dup
    3634: iconst_2
    3635: iconst_2
    3636: bastore
    3637: dup
    3638: iconst_3
    3639: bipush        14
    3641: bastore
    3642: dup
    3643: iconst_4
    3644: bipush        15
    3646: bastore
    3647: dup
    3648: iconst_5
    3649: iconst_0
    3650: bastore
    3651: dup
    3652: bipush        6
    3654: bipush        8
    3656: bastore
    3657: dup
    3658: bipush        7
    3660: bipush        13
    3662: bastore
    3663: dup
    3664: bipush        8
    3666: iconst_3
    3667: bastore
    3668: dup
    3669: bipush        9
    3671: bipush        12
    3673: bastore
    3674: dup
    3675: bipush        10
    3677: bipush        9
    3679: bastore
    3680: dup
    3681: bipush        11
    3683: bipush        7
    3685: bastore
    3686: dup
    3687: bipush        12
    3689: iconst_5
    3690: bastore
    3691: dup
    3692: bipush        13
    3694: bipush        10
    3696: bastore
    3697: dup
    3698: bipush        14
    3700: bipush        6
    3702: bastore
    3703: dup
    3704: bipush        15
    3706: iconst_1
    3707: bastore
    3708: dup
    3709: bipush        16
    3711: bipush        13
    3713: bastore
    3714: dup
    3715: bipush        17
    3717: iconst_0
    3718: bastore
    3719: dup
    3720: bipush        18
    3722: bipush        11
    3724: bastore
    3725: dup
    3726: bipush        19
    3728: bipush        7
    3730: bastore
    3731: dup
    3732: bipush        20
    3734: iconst_4
    3735: bastore
    3736: dup
    3737: bipush        21
    3739: bipush        9
    3741: bastore
    3742: dup
    3743: bipush        22
    3745: iconst_1
    3746: bastore
    3747: dup
    3748: bipush        23
    3750: bipush        10
    3752: bastore
    3753: dup
    3754: bipush        24
    3756: bipush        14
    3758: bastore
    3759: dup
    3760: bipush        25
    3762: iconst_3
    3763: bastore
    3764: dup
    3765: bipush        26
    3767: iconst_5
    3768: bastore
    3769: dup
    3770: bipush        27
    3772: bipush        12
    3774: bastore
    3775: dup
    3776: bipush        28
    3778: iconst_2
    3779: bastore
    3780: dup
    3781: bipush        29
    3783: bipush        15
    3785: bastore
    3786: dup
    3787: bipush        30
    3789: bipush        8
    3791: bastore
    3792: dup
    3793: bipush        31
    3795: bipush        6
    3797: bastore
    3798: dup
    3799: bipush        32
    3801: iconst_1
    3802: bastore
    3803: dup
    3804: bipush        33
    3806: iconst_4
    3807: bastore
    3808: dup
    3809: bipush        34
    3811: bipush        11
    3813: bastore
    3814: dup
    3815: bipush        35
    3817: bipush        13
    3819: bastore
    3820: dup
    3821: bipush        36
    3823: bipush        12
    3825: bastore
    3826: dup
    3827: bipush        37
    3829: iconst_3
    3830: bastore
    3831: dup
    3832: bipush        38
    3834: bipush        7
    3836: bastore
    3837: dup
    3838: bipush        39
    3840: bipush        14
    3842: bastore
    3843: dup
    3844: bipush        40
    3846: bipush        10
    3848: bastore
    3849: dup
    3850: bipush        41
    3852: bipush        15
    3854: bastore
    3855: dup
    3856: bipush        42
    3858: bipush        6
    3860: bastore
    3861: dup
    3862: bipush        43
    3864: bipush        8
    3866: bastore
    3867: dup
    3868: bipush        44
    3870: iconst_0
    3871: bastore
    3872: dup
    3873: bipush        45
    3875: iconst_5
    3876: bastore
    3877: dup
    3878: bipush        46
    3880: bipush        9
    3882: bastore
    3883: dup
    3884: bipush        47
    3886: iconst_2
    3887: bastore
    3888: dup
    3889: bipush        48
    3891: bipush        6
    3893: bastore
    3894: dup
    3895: bipush        49
    3897: bipush        11
    3899: bastore
    3900: dup
    3901: bipush        50
    3903: bipush        13
    3905: bastore
    3906: dup
    3907: bipush        51
    3909: bipush        8
    3911: bastore
    3912: dup
    3913: bipush        52
    3915: iconst_1
    3916: bastore
    3917: dup
    3918: bipush        53
    3920: iconst_4
    3921: bastore
    3922: dup
    3923: bipush        54
    3925: bipush        10
    3927: bastore
    3928: dup
    3929: bipush        55
    3931: bipush        7
    3933: bastore
    3934: dup
    3935: bipush        56
    3937: bipush        9
    3939: bastore
    3940: dup
    3941: bipush        57
    3943: iconst_5
    3944: bastore
    3945: dup
    3946: bipush        58
    3948: iconst_0
    3949: bastore
    3950: dup
    3951: bipush        59
    3953: bipush        15
    3955: bastore
    3956: dup
    3957: bipush        60
    3959: bipush        14
    3961: bastore
    3962: dup
    3963: bipush        61
    3965: iconst_2
    3966: bastore
    3967: dup
    3968: bipush        62
    3970: iconst_3
    3971: bastore
    3972: dup
    3973: bipush        63
    3975: bipush        12
    3977: bastore
    3978: aastore
    3979: dup
    3980: bipush        7
    3982: bipush        64
    3984: newarray       byte
    3986: dup
    3987: iconst_0
    3988: bipush        13
    3990: bastore
    3991: dup
    3992: iconst_1
    3993: iconst_2
    3994: bastore
    3995: dup
    3996: iconst_2
    3997: bipush        8
    3999: bastore
    4000: dup
    4001: iconst_3
    4002: iconst_4
    4003: bastore
    4004: dup
    4005: iconst_4
    4006: bipush        6
    4008: bastore
    4009: dup
    4010: iconst_5
    4011: bipush        15
    4013: bastore
    4014: dup
    4015: bipush        6
    4017: bipush        11
    4019: bastore
    4020: dup
    4021: bipush        7
    4023: iconst_1
    4024: bastore
    4025: dup
    4026: bipush        8
    4028: bipush        10
    4030: bastore
    4031: dup
    4032: bipush        9
    4034: bipush        9
    4036: bastore
    4037: dup
    4038: bipush        10
    4040: iconst_3
    4041: bastore
    4042: dup
    4043: bipush        11
    4045: bipush        14
    4047: bastore
    4048: dup
    4049: bipush        12
    4051: iconst_5
    4052: bastore
    4053: dup
    4054: bipush        13
    4056: iconst_0
    4057: bastore
    4058: dup
    4059: bipush        14
    4061: bipush        12
    4063: bastore
    4064: dup
    4065: bipush        15
    4067: bipush        7
    4069: bastore
    4070: dup
    4071: bipush        16
    4073: iconst_1
    4074: bastore
    4075: dup
    4076: bipush        17
    4078: bipush        15
    4080: bastore
    4081: dup
    4082: bipush        18
    4084: bipush        13
    4086: bastore
    4087: dup
    4088: bipush        19
    4090: bipush        8
    4092: bastore
    4093: dup
    4094: bipush        20
    4096: bipush        10
    4098: bastore
    4099: dup
    4100: bipush        21
    4102: iconst_3
    4103: bastore
    4104: dup
    4105: bipush        22
    4107: bipush        7
    4109: bastore
    4110: dup
    4111: bipush        23
    4113: iconst_4
    4114: bastore
    4115: dup
    4116: bipush        24
    4118: bipush        12
    4120: bastore
    4121: dup
    4122: bipush        25
    4124: iconst_5
    4125: bastore
    4126: dup
    4127: bipush        26
    4129: bipush        6
    4131: bastore
    4132: dup
    4133: bipush        27
    4135: bipush        11
    4137: bastore
    4138: dup
    4139: bipush        28
    4141: iconst_0
    4142: bastore
    4143: dup
    4144: bipush        29
    4146: bipush        14
    4148: bastore
    4149: dup
    4150: bipush        30
    4152: bipush        9
    4154: bastore
    4155: dup
    4156: bipush        31
    4158: iconst_2
    4159: bastore
    4160: dup
    4161: bipush        32
    4163: bipush        7
    4165: bastore
    4166: dup
    4167: bipush        33
    4169: bipush        11
    4171: bastore
    4172: dup
    4173: bipush        34
    4175: iconst_4
    4176: bastore
    4177: dup
    4178: bipush        35
    4180: iconst_1
    4181: bastore
    4182: dup
    4183: bipush        36
    4185: bipush        9
    4187: bastore
    4188: dup
    4189: bipush        37
    4191: bipush        12
    4193: bastore
    4194: dup
    4195: bipush        38
    4197: bipush        14
    4199: bastore
    4200: dup
    4201: bipush        39
    4203: iconst_2
    4204: bastore
    4205: dup
    4206: bipush        40
    4208: iconst_0
    4209: bastore
    4210: dup
    4211: bipush        41
    4213: bipush        6
    4215: bastore
    4216: dup
    4217: bipush        42
    4219: bipush        10
    4221: bastore
    4222: dup
    4223: bipush        43
    4225: bipush        13
    4227: bastore
    4228: dup
    4229: bipush        44
    4231: bipush        15
    4233: bastore
    4234: dup
    4235: bipush        45
    4237: iconst_3
    4238: bastore
    4239: dup
    4240: bipush        46
    4242: iconst_5
    4243: bastore
    4244: dup
    4245: bipush        47
    4247: bipush        8
    4249: bastore
    4250: dup
    4251: bipush        48
    4253: iconst_2
    4254: bastore
    4255: dup
    4256: bipush        49
    4258: iconst_1
    4259: bastore
    4260: dup
    4261: bipush        50
    4263: bipush        14
    4265: bastore
    4266: dup
    4267: bipush        51
    4269: bipush        7
    4271: bastore
    4272: dup
    4273: bipush        52
    4275: iconst_4
    4276: bastore
    4277: dup
    4278: bipush        53
    4280: bipush        10
    4282: bastore
    4283: dup
    4284: bipush        54
    4286: bipush        8
    4288: bastore
    4289: dup
    4290: bipush        55
    4292: bipush        13
    4294: bastore
    4295: dup
    4296: bipush        56
    4298: bipush        15
    4300: bastore
    4301: dup
    4302: bipush        57
    4304: bipush        12
    4306: bastore
    4307: dup
    4308: bipush        58
    4310: bipush        9
    4312: bastore
    4313: dup
    4314: bipush        59
    4316: iconst_0
    4317: bastore
    4318: dup
    4319: bipush        60
    4321: iconst_3
    4322: bastore
    4323: dup
    4324: bipush        61
    4326: iconst_5
    4327: bastore
    4328: dup
    4329: bipush        62
    4331: bipush        6
    4333: bastore
    4334: dup
    4335: bipush        63
    4337: bipush        11
    4339: bastore
    4340: aastore
    4341: putstatic     #69                 // Field S:[[B
    4344: bipush        32
    4346: newarray       byte
    4348: dup
    4349: iconst_0
    4350: bipush        16
    4352: bastore
    4353: dup
    4354: iconst_1
    4355: bipush        7
    4357: bastore
    4358: dup
    4359: iconst_2
    4360: bipush        20
    4362: bastore
    4363: dup
    4364: iconst_3
    4365: bipush        21
    4367: bastore
    4368: dup
    4369: iconst_4
    4370: bipush        29
    4372: bastore
    4373: dup
    4374: iconst_5
    4375: bipush        12
    4377: bastore
    4378: dup
    4379: bipush        6
    4381: bipush        28
    4383: bastore
    4384: dup
    4385: bipush        7
    4387: bipush        17
    4389: bastore
    4390: dup
    4391: bipush        8
    4393: iconst_1
    4394: bastore
    4395: dup
    4396: bipush        9
    4398: bipush        15
    4400: bastore
    4401: dup
    4402: bipush        10
    4404: bipush        23
    4406: bastore
    4407: dup
    4408: bipush        11
    4410: bipush        26
    4412: bastore
    4413: dup
    4414: bipush        12
    4416: iconst_5
    4417: bastore
    4418: dup
    4419: bipush        13
    4421: bipush        18
    4423: bastore
    4424: dup
    4425: bipush        14
    4427: bipush        31
    4429: bastore
    4430: dup
    4431: bipush        15
    4433: bipush        10
    4435: bastore
    4436: dup
    4437: bipush        16
    4439: iconst_2
    4440: bastore
    4441: dup
    4442: bipush        17
    4444: bipush        8
    4446: bastore
    4447: dup
    4448: bipush        18
    4450: bipush        24
    4452: bastore
    4453: dup
    4454: bipush        19
    4456: bipush        14
    4458: bastore
    4459: dup
    4460: bipush        20
    4462: bipush        32
    4464: bastore
    4465: dup
    4466: bipush        21
    4468: bipush        27
    4470: bastore
    4471: dup
    4472: bipush        22
    4474: iconst_3
    4475: bastore
    4476: dup
    4477: bipush        23
    4479: bipush        9
    4481: bastore
    4482: dup
    4483: bipush        24
    4485: bipush        19
    4487: bastore
    4488: dup
    4489: bipush        25
    4491: bipush        13
    4493: bastore
    4494: dup
    4495: bipush        26
    4497: bipush        30
    4499: bastore
    4500: dup
    4501: bipush        27
    4503: bipush        6
    4505: bastore
    4506: dup
    4507: bipush        28
    4509: bipush        22
    4511: bastore
    4512: dup
    4513: bipush        29
    4515: bipush        11
    4517: bastore
    4518: dup
    4519: bipush        30
    4521: iconst_4
    4522: bastore
    4523: dup
    4524: bipush        31
    4526: bipush        25
    4528: bastore
    4529: putstatic     #70                 // Field P32Tr:[B
    4532: bipush        64
    4534: newarray       byte
    4536: dup
    4537: iconst_0
    4538: iconst_1
    4539: bastore
    4540: dup
    4541: iconst_1
    4542: iconst_2
    4543: bastore
    4544: dup
    4545: iconst_2
    4546: iconst_3
    4547: bastore
    4548: dup
    4549: iconst_3
    4550: iconst_4
    4551: bastore
    4552: dup
    4553: iconst_4
    4554: bipush        17
    4556: bastore
    4557: dup
    4558: iconst_5
    4559: bipush        18
    4561: bastore
    4562: dup
    4563: bipush        6
    4565: bipush        19
    4567: bastore
    4568: dup
    4569: bipush        7
    4571: bipush        20
    4573: bastore
    4574: dup
    4575: bipush        8
    4577: iconst_5
    4578: bastore
    4579: dup
    4580: bipush        9
    4582: bipush        6
    4584: bastore
    4585: dup
    4586: bipush        10
    4588: bipush        7
    4590: bastore
    4591: dup
    4592: bipush        11
    4594: bipush        8
    4596: bastore
    4597: dup
    4598: bipush        12
    4600: bipush        21
    4602: bastore
    4603: dup
    4604: bipush        13
    4606: bipush        22
    4608: bastore
    4609: dup
    4610: bipush        14
    4612: bipush        23
    4614: bastore
    4615: dup
    4616: bipush        15
    4618: bipush        24
    4620: bastore
    4621: dup
    4622: bipush        16
    4624: bipush        9
    4626: bastore
    4627: dup
    4628: bipush        17
    4630: bipush        10
    4632: bastore
    4633: dup
    4634: bipush        18
    4636: bipush        11
    4638: bastore
    4639: dup
    4640: bipush        19
    4642: bipush        12
    4644: bastore
    4645: dup
    4646: bipush        20
    4648: bipush        25
    4650: bastore
    4651: dup
    4652: bipush        21
    4654: bipush        26
    4656: bastore
    4657: dup
    4658: bipush        22
    4660: bipush        27
    4662: bastore
    4663: dup
    4664: bipush        23
    4666: bipush        28
    4668: bastore
    4669: dup
    4670: bipush        24
    4672: bipush        13
    4674: bastore
    4675: dup
    4676: bipush        25
    4678: bipush        14
    4680: bastore
    4681: dup
    4682: bipush        26
    4684: bipush        15
    4686: bastore
    4687: dup
    4688: bipush        27
    4690: bipush        16
    4692: bastore
    4693: dup
    4694: bipush        28
    4696: bipush        29
    4698: bastore
    4699: dup
    4700: bipush        29
    4702: bipush        30
    4704: bastore
    4705: dup
    4706: bipush        30
    4708: bipush        31
    4710: bastore
    4711: dup
    4712: bipush        31
    4714: bipush        32
    4716: bastore
    4717: dup
    4718: bipush        32
    4720: bipush        33
    4722: bastore
    4723: dup
    4724: bipush        33
    4726: bipush        34
    4728: bastore
    4729: dup
    4730: bipush        34
    4732: bipush        35
    4734: bastore
    4735: dup
    4736: bipush        35
    4738: bipush        36
    4740: bastore
    4741: dup
    4742: bipush        36
    4744: bipush        49
    4746: bastore
    4747: dup
    4748: bipush        37
    4750: bipush        50
    4752: bastore
    4753: dup
    4754: bipush        38
    4756: bipush        51
    4758: bastore
    4759: dup
    4760: bipush        39
    4762: bipush        52
    4764: bastore
    4765: dup
    4766: bipush        40
    4768: bipush        37
    4770: bastore
    4771: dup
    4772: bipush        41
    4774: bipush        38
    4776: bastore
    4777: dup
    4778: bipush        42
    4780: bipush        39
    4782: bastore
    4783: dup
    4784: bipush        43
    4786: bipush        40
    4788: bastore
    4789: dup
    4790: bipush        44
    4792: bipush        53
    4794: bastore
    4795: dup
    4796: bipush        45
    4798: bipush        54
    4800: bastore
    4801: dup
    4802: bipush        46
    4804: bipush        55
    4806: bastore
    4807: dup
    4808: bipush        47
    4810: bipush        56
    4812: bastore
    4813: dup
    4814: bipush        48
    4816: bipush        41
    4818: bastore
    4819: dup
    4820: bipush        49
    4822: bipush        42
    4824: bastore
    4825: dup
    4826: bipush        50
    4828: bipush        43
    4830: bastore
    4831: dup
    4832: bipush        51
    4834: bipush        44
    4836: bastore
    4837: dup
    4838: bipush        52
    4840: bipush        57
    4842: bastore
    4843: dup
    4844: bipush        53
    4846: bipush        58
    4848: bastore
    4849: dup
    4850: bipush        54
    4852: bipush        59
    4854: bastore
    4855: dup
    4856: bipush        55
    4858: bipush        60
    4860: bastore
    4861: dup
    4862: bipush        56
    4864: bipush        45
    4866: bastore
    4867: dup
    4868: bipush        57
    4870: bipush        46
    4872: bastore
    4873: dup
    4874: bipush        58
    4876: bipush        47
    4878: bastore
    4879: dup
    4880: bipush        59
    4882: bipush        48
    4884: bastore
    4885: dup
    4886: bipush        60
    4888: bipush        61
    4890: bastore
    4891: dup
    4892: bipush        61
    4894: bipush        62
    4896: bastore
    4897: dup
    4898: bipush        62
    4900: bipush        63
    4902: bastore
    4903: dup
    4904: bipush        63
    4906: bipush        64
    4908: bastore
    4909: putstatic     #71                 // Field CIFP:[B
    4912: bipush        64
    4914: newarray       byte
    4916: dup
    4917: iconst_0
    4918: bipush        46
    4920: bastore
    4921: dup
    4922: iconst_1
    4923: bipush        47
    4925: bastore
    4926: dup
    4927: iconst_2
    4928: bipush        48
    4930: bastore
    4931: dup
    4932: iconst_3
    4933: bipush        49
    4935: bastore
    4936: dup
    4937: iconst_4
    4938: bipush        50
    4940: bastore
    4941: dup
    4942: iconst_5
    4943: bipush        51
    4945: bastore
    4946: dup
    4947: bipush        6
    4949: bipush        52
    4951: bastore
    4952: dup
    4953: bipush        7
    4955: bipush        53
    4957: bastore
    4958: dup
    4959: bipush        8
    4961: bipush        54
    4963: bastore
    4964: dup
    4965: bipush        9
    4967: bipush        55
    4969: bastore
    4970: dup
    4971: bipush        10
    4973: bipush        56
    4975: bastore
    4976: dup
    4977: bipush        11
    4979: bipush        57
    4981: bastore
    4982: dup
    4983: bipush        12
    4985: bipush        65
    4987: bastore
    4988: dup
    4989: bipush        13
    4991: bipush        66
    4993: bastore
    4994: dup
    4995: bipush        14
    4997: bipush        67
    4999: bastore
    5000: dup
    5001: bipush        15
    5003: bipush        68
    5005: bastore
    5006: dup
    5007: bipush        16
    5009: bipush        69
    5011: bastore
    5012: dup
    5013: bipush        17
    5015: bipush        70
    5017: bastore
    5018: dup
    5019: bipush        18
    5021: bipush        71
    5023: bastore
    5024: dup
    5025: bipush        19
    5027: bipush        72
    5029: bastore
    5030: dup
    5031: bipush        20
    5033: bipush        73
    5035: bastore
    5036: dup
    5037: bipush        21
    5039: bipush        74
    5041: bastore
    5042: dup
    5043: bipush        22
    5045: bipush        75
    5047: bastore
    5048: dup
    5049: bipush        23
    5051: bipush        76
    5053: bastore
    5054: dup
    5055: bipush        24
    5057: bipush        77
    5059: bastore
    5060: dup
    5061: bipush        25
    5063: bipush        78
    5065: bastore
    5066: dup
    5067: bipush        26
    5069: bipush        79
    5071: bastore
    5072: dup
    5073: bipush        27
    5075: bipush        80
    5077: bastore
    5078: dup
    5079: bipush        28
    5081: bipush        81
    5083: bastore
    5084: dup
    5085: bipush        29
    5087: bipush        82
    5089: bastore
    5090: dup
    5091: bipush        30
    5093: bipush        83
    5095: bastore
    5096: dup
    5097: bipush        31
    5099: bipush        84
    5101: bastore
    5102: dup
    5103: bipush        32
    5105: bipush        85
    5107: bastore
    5108: dup
    5109: bipush        33
    5111: bipush        86
    5113: bastore
    5114: dup
    5115: bipush        34
    5117: bipush        87
    5119: bastore
    5120: dup
    5121: bipush        35
    5123: bipush        88
    5125: bastore
    5126: dup
    5127: bipush        36
    5129: bipush        89
    5131: bastore
    5132: dup
    5133: bipush        37
    5135: bipush        90
    5137: bastore
    5138: dup
    5139: bipush        38
    5141: bipush        97
    5143: bastore
    5144: dup
    5145: bipush        39
    5147: bipush        98
    5149: bastore
    5150: dup
    5151: bipush        40
    5153: bipush        99
    5155: bastore
    5156: dup
    5157: bipush        41
    5159: bipush        100
    5161: bastore
    5162: dup
    5163: bipush        42
    5165: bipush        101
    5167: bastore
    5168: dup
    5169: bipush        43
    5171: bipush        102
    5173: bastore
    5174: dup
    5175: bipush        44
    5177: bipush        103
    5179: bastore
    5180: dup
    5181: bipush        45
    5183: bipush        104
    5185: bastore
    5186: dup
    5187: bipush        46
    5189: bipush        105
    5191: bastore
    5192: dup
    5193: bipush        47
    5195: bipush        106
    5197: bastore
    5198: dup
    5199: bipush        48
    5201: bipush        107
    5203: bastore
    5204: dup
    5205: bipush        49
    5207: bipush        108
    5209: bastore
    5210: dup
    5211: bipush        50
    5213: bipush        109
    5215: bastore
    5216: dup
    5217: bipush        51
    5219: bipush        110
    5221: bastore
    5222: dup
    5223: bipush        52
    5225: bipush        111
    5227: bastore
    5228: dup
    5229: bipush        53
    5231: bipush        112
    5233: bastore
    5234: dup
    5235: bipush        54
    5237: bipush        113
    5239: bastore
    5240: dup
    5241: bipush        55
    5243: bipush        114
    5245: bastore
    5246: dup
    5247: bipush        56
    5249: bipush        115
    5251: bastore
    5252: dup
    5253: bipush        57
    5255: bipush        116
    5257: bastore
    5258: dup
    5259: bipush        58
    5261: bipush        117
    5263: bastore
    5264: dup
    5265: bipush        59
    5267: bipush        118
    5269: bastore
    5270: dup
    5271: bipush        60
    5273: bipush        119
    5275: bastore
    5276: dup
    5277: bipush        61
    5279: bipush        120
    5281: bastore
    5282: dup
    5283: bipush        62
    5285: bipush        121
    5287: bastore
    5288: dup
    5289: bipush        63
    5291: bipush        122
    5293: bastore
    5294: putstatic     #50                 // Field ITOA64:[B
    5297: sipush        128
    5300: newarray       byte
    5302: putstatic     #48                 // Field A64TOI:[B
    5305: bipush        16
    5307: bipush        16
    5309: multianewarray #72,  2            // class "[[J"
    5313: putstatic     #15                 // Field PC1ROT:[[J
    5316: iconst_2
    5317: bipush        16
    5319: bipush        16
    5321: multianewarray #73,  3            // class "[[[J"
    5325: putstatic     #19                 // Field PC2ROT:[[[J
    5328: bipush        8
    5330: bipush        16
    5332: multianewarray #72,  2            // class "[[J"
    5336: putstatic     #32                 // Field IE3264:[[J
    5339: bipush        8
    5341: bipush        64
    5343: multianewarray #72,  2            // class "[[J"
    5347: putstatic     #36                 // Field SPE:[[J
    5350: bipush        16
    5352: bipush        16
    5354: multianewarray #72,  2            // class "[[J"
    5358: putstatic     #43                 // Field CF6464:[[J
    5361: bipush        64
    5363: newarray       byte
    5365: astore_0
    5366: bipush        64
    5368: newarray       byte
    5370: astore_1
    5371: iconst_0
    5372: istore_2
    5373: iload_2
    5374: bipush        64
    5376: if_icmpge     5396
    5379: getstatic     #48                 // Field A64TOI:[B
    5382: getstatic     #50                 // Field ITOA64:[B
    5385: iload_2
    5386: baload
    5387: iload_2
    5388: i2b
    5389: bastore
    5390: iinc          2, 1
    5393: goto          5373
    5396: iconst_0
    5397: istore_2
    5398: iload_2
    5399: bipush        64
    5401: if_icmpge     5414
    5404: aload_0
    5405: iload_2
    5406: iconst_0
    5407: bastore
    5408: iinc          2, 1
    5411: goto          5398
    5414: iconst_0
    5415: istore_2
    5416: iload_2
    5417: bipush        64
    5419: if_icmpge     5497
    5422: getstatic     #67                 // Field PC2:[B
    5425: iload_2
    5426: baload
    5427: dup
    5428: istore_3
    5429: ifne          5435
    5432: goto          5491
    5435: iload_3
    5436: getstatic     #20                 // Field Rotates:[B
    5439: iconst_0
    5440: baload
    5441: iconst_1
    5442: isub
    5443: iadd
    5444: istore_3
    5445: iload_3
    5446: bipush        28
    5448: irem
    5449: getstatic     #20                 // Field Rotates:[B
    5452: iconst_0
    5453: baload
    5454: if_icmpge     5460
    5457: iinc          3, -28
    5460: getstatic     #66                 // Field PC1:[B
    5463: iload_3
    5464: baload
    5465: istore_3
    5466: iload_3
    5467: ifle          5486
    5470: iinc          3, -1
    5473: iload_3
    5474: bipush        7
    5476: ior
    5477: iload_3
    5478: bipush        7
    5480: iand
    5481: isub
    5482: istore_3
    5483: iinc          3, 1
    5486: aload_0
    5487: iload_2
    5488: iload_3
    5489: i2b
    5490: bastore
    5491: iinc          2, 1
    5494: goto          5416
    5497: getstatic     #15                 // Field PC1ROT:[[J
    5500: aload_0
    5501: bipush        8
    5503: invokestatic  #74                 // Method init_perm:([[J[BI)V
    5506: iconst_0
    5507: istore_2
    5508: iload_2
    5509: iconst_2
    5510: if_icmpge     5648
    5513: iconst_0
    5514: istore        4
    5516: iload         4
    5518: bipush        64
    5520: if_icmpge     5539
    5523: aload_0
    5524: iload         4
    5526: aload_1
    5527: iload         4
    5529: iconst_0
    5530: dup_x2
    5531: bastore
    5532: bastore
    5533: iinc          4, 1
    5536: goto          5516
    5539: iconst_0
    5540: istore        4
    5542: iload         4
    5544: bipush        64
    5546: if_icmpge     5579
    5549: getstatic     #67                 // Field PC2:[B
    5552: iload         4
    5554: baload
    5555: dup
    5556: istore_3
    5557: ifne          5563
    5560: goto          5573
    5563: aload_1
    5564: iload_3
    5565: iconst_1
    5566: isub
    5567: iload         4
    5569: iconst_1
    5570: iadd
    5571: i2b
    5572: bastore
    5573: iinc          4, 1
    5576: goto          5542
    5579: iconst_0
    5580: istore        4
    5582: iload         4
    5584: bipush        64
    5586: if_icmpge     5631
    5589: getstatic     #67                 // Field PC2:[B
    5592: iload         4
    5594: baload
    5595: dup
    5596: istore_3
    5597: ifne          5603
    5600: goto          5625
    5603: iload_3
    5604: iload_2
    5605: iadd
    5606: istore_3
    5607: iload_3
    5608: bipush        28
    5610: irem
    5611: iload_2
    5612: if_icmpgt     5618
    5615: iinc          3, -28
    5618: aload_0
    5619: iload         4
    5621: aload_1
    5622: iload_3
    5623: baload
    5624: bastore
    5625: iinc          4, 1
    5628: goto          5582
    5631: getstatic     #19                 // Field PC2ROT:[[[J
    5634: iload_2
    5635: aaload
    5636: aload_0
    5637: bipush        8
    5639: invokestatic  #74                 // Method init_perm:([[J[BI)V
    5642: iinc          2, 1
    5645: goto          5508
    5648: iconst_0
    5649: istore_2
    5650: iload_2
    5651: bipush        8
    5653: if_icmpge     5761
    5656: iconst_0
    5657: istore_3
    5658: iload_3
    5659: bipush        8
    5661: if_icmpge     5755
    5664: iload_3
    5665: iconst_2
    5666: if_icmpge     5673
    5669: iconst_0
    5670: goto          5691
    5673: getstatic     #64                 // Field IP:[B
    5676: getstatic     #65                 // Field ExpandTr:[B
    5679: iload_2
    5680: bipush        6
    5682: imul
    5683: iload_3
    5684: iadd
    5685: iconst_2
    5686: isub
    5687: baload
    5688: iconst_1
    5689: isub
    5690: baload
    5691: istore        4
    5693: iload         4
    5695: bipush        32
    5697: if_icmple     5706
    5700: iinc          4, -32
    5703: goto          5714
    5706: iload         4
    5708: ifle          5714
    5711: iinc          4, -1
    5714: iload         4
    5716: ifle          5738
    5719: iinc          4, -1
    5722: iload         4
    5724: bipush        7
    5726: ior
    5727: iload         4
    5729: bipush        7
    5731: iand
    5732: isub
    5733: istore        4
    5735: iinc          4, 1
    5738: aload_0
    5739: iload_2
    5740: bipush        8
    5742: imul
    5743: iload_3
    5744: iadd
    5745: iload         4
    5747: i2b
    5748: bastore
    5749: iinc          3, 1
    5752: goto          5658
    5755: iinc          2, 1
    5758: goto          5650
    5761: getstatic     #32                 // Field IE3264:[[J
    5764: aload_0
    5765: bipush        8
    5767: invokestatic  #74                 // Method init_perm:([[J[BI)V
    5770: iconst_0
    5771: istore_2
    5772: iload_2
    5773: bipush        64
    5775: if_icmpge     5825
    5778: getstatic     #64                 // Field IP:[B
    5781: getstatic     #71                 // Field CIFP:[B
    5784: iload_2
    5785: baload
    5786: iconst_1
    5787: isub
    5788: baload
    5789: istore_3
    5790: iload_3
    5791: ifle          5810
    5794: iinc          3, -1
    5797: iload_3
    5798: bipush        7
    5800: ior
    5801: iload_3
    5802: bipush        7
    5804: iand
    5805: isub
    5806: istore_3
    5807: iinc          3, 1
    5810: aload_0
    5811: iload_3
    5812: iconst_1
    5813: isub
    5814: iload_2
    5815: iconst_1
    5816: iadd
    5817: i2b
    5818: bastore
    5819: iinc          2, 1
    5822: goto          5772
    5825: getstatic     #43                 // Field CF6464:[[J
    5828: aload_0
    5829: bipush        8
    5831: invokestatic  #74                 // Method init_perm:([[J[BI)V
    5834: iconst_0
    5835: istore_2
    5836: iload_2
    5837: bipush        48
    5839: if_icmpge     5862
    5842: aload_0
    5843: iload_2
    5844: getstatic     #70                 // Field P32Tr:[B
    5847: getstatic     #65                 // Field ExpandTr:[B
    5850: iload_2
    5851: baload
    5852: iconst_1
    5853: isub
    5854: baload
    5855: bastore
    5856: iinc          2, 1
    5859: goto          5836
    5862: iconst_0
    5863: istore_2
    5864: iload_2
    5865: bipush        8
    5867: if_icmpge     6100
    5870: iconst_0
    5871: istore_3
    5872: iload_3
    5873: bipush        64
    5875: if_icmpge     6094
    5878: iload_3
    5879: iconst_0
    5880: ishr
    5881: iconst_1
    5882: iand
    5883: iconst_5
    5884: ishl
    5885: iload_3
    5886: iconst_1
    5887: ishr
    5888: iconst_1
    5889: iand
    5890: iconst_3
    5891: ishl
    5892: ior
    5893: iload_3
    5894: iconst_2
    5895: ishr
    5896: iconst_1
    5897: iand
    5898: iconst_2
    5899: ishl
    5900: ior
    5901: iload_3
    5902: iconst_3
    5903: ishr
    5904: iconst_1
    5905: iand
    5906: iconst_1
    5907: ishl
    5908: ior
    5909: iload_3
    5910: iconst_4
    5911: ishr
    5912: iconst_1
    5913: iand
    5914: iconst_0
    5915: ishl
    5916: ior
    5917: iload_3
    5918: iconst_5
    5919: ishr
    5920: iconst_1
    5921: iand
    5922: iconst_4
    5923: ishl
    5924: ior
    5925: istore        4
    5927: getstatic     #69                 // Field S:[[B
    5930: iload_2
    5931: aaload
    5932: iload         4
    5934: baload
    5935: istore        4
    5937: iload         4
    5939: iconst_3
    5940: ishr
    5941: iconst_1
    5942: iand
    5943: iconst_0
    5944: ishl
    5945: iload         4
    5947: iconst_2
    5948: ishr
    5949: iconst_1
    5950: iand
    5951: iconst_1
    5952: ishl
    5953: ior
    5954: iload         4
    5956: iconst_1
    5957: ishr
    5958: iconst_1
    5959: iand
    5960: iconst_2
    5961: ishl
    5962: ior
    5963: iload         4
    5965: iconst_0
    5966: ishr
    5967: iconst_1
    5968: iand
    5969: iconst_3
    5970: ishl
    5971: ior
    5972: istore        4
    5974: iconst_0
    5975: istore        5
    5977: iload         5
    5979: bipush        32
    5981: if_icmpge     5995
    5984: aload_1
    5985: iload         5
    5987: iconst_0
    5988: bastore
    5989: iinc          5, 1
    5992: goto          5977
    5995: iconst_0
    5996: istore        5
    5998: iload         5
    6000: iconst_4
    6001: if_icmpge     6026
    6004: aload_1
    6005: iconst_4
    6006: iload_2
    6007: imul
    6008: iload         5
    6010: iadd
    6011: iload         4
    6013: iload         5
    6015: ishr
    6016: iconst_1
    6017: iand
    6018: i2b
    6019: bastore
    6020: iinc          5, 1
    6023: goto          5998
    6026: lconst_0
    6027: lstore        5
    6029: bipush        24
    6031: istore        7
    6033: iinc          7, -1
    6036: iload         7
    6038: iflt          6076
    6041: lload         5
    6043: iconst_1
    6044: lshl
    6045: aload_1
    6046: aload_0
    6047: iload         7
    6049: baload
    6050: iconst_1
    6051: isub
    6052: baload
    6053: i2l
    6054: bipush        32
    6056: lshl
    6057: lor
    6058: aload_1
    6059: aload_0
    6060: iload         7
    6062: bipush        24
    6064: iadd
    6065: baload
    6066: iconst_1
    6067: isub
    6068: baload
    6069: i2l
    6070: lor
    6071: lstore        5
    6073: goto          6033
    6076: getstatic     #36                 // Field SPE:[[J
    6079: iload_2
    6080: aaload
    6081: iload_3
    6082: lload         5
    6084: invokestatic  #75                 // Method to_six_bit:(J)J
    6087: lastore
    6088: iinc          3, 1
    6091: goto          5872
    6094: iinc          2, 1
    6097: goto          5864
    6100: return
}
