Compiled from "Relationship.java"
public class org.apache.cxf.sts.token.realm.Relationship {
  public static final java.lang.String FED_TYPE_IDENTITY;

  public static final java.lang.String FED_TYPE_CLAIMS;

  private java.lang.String sourceRealm;

  private java.lang.String targetRealm;

  private org.apache.cxf.sts.IdentityMapper identityMapper;

  private org.apache.cxf.sts.claims.ClaimsMapper claimsMapper;

  private java.lang.String type;

  public org.apache.cxf.sts.token.realm.Relationship();
    Code:
       0: aload_0
       1: invokespecial #1                  // Method java/lang/Object."<init>":()V
       4: return

  public void setSourceRealm(java.lang.String);
    Code:
       0: aload_0
       1: aload_1
       2: putfield      #2                  // Field sourceRealm:Ljava/lang/String;
       5: return

  public java.lang.String getSourceRealm();
    Code:
       0: aload_0
       1: getfield      #2                  // Field sourceRealm:Ljava/lang/String;
       4: areturn

  public void setTargetRealm(java.lang.String);
    Code:
       0: aload_0
       1: aload_1
       2: putfield      #3                  // Field targetRealm:Ljava/lang/String;
       5: return

  public java.lang.String getTargetRealm();
    Code:
       0: aload_0
       1: getfield      #3                  // Field targetRealm:Ljava/lang/String;
       4: areturn

  public void setIdentityMapper(org.apache.cxf.sts.IdentityMapper);
    Code:
       0: aload_0
       1: aload_1
       2: putfield      #4                  // Field identityMapper:Lorg/apache/cxf/sts/IdentityMapper;
       5: return

  public org.apache.cxf.sts.IdentityMapper getIdentityMapper();
    Code:
       0: aload_0
       1: getfield      #4                  // Field identityMapper:Lorg/apache/cxf/sts/IdentityMapper;
       4: areturn

  public void setClaimsMapper(org.apache.cxf.sts.claims.ClaimsMapper);
    Code:
       0: aload_0
       1: aload_1
       2: putfield      #5                  // Field claimsMapper:Lorg/apache/cxf/sts/claims/ClaimsMapper;
       5: return

  public org.apache.cxf.sts.claims.ClaimsMapper getClaimsMapper();
    Code:
       0: aload_0
       1: getfield      #5                  // Field claimsMapper:Lorg/apache/cxf/sts/claims/ClaimsMapper;
       4: areturn

  public void setType(java.lang.String);
    Code:
       0: aload_0
       1: aload_1
       2: putfield      #6                  // Field type:Ljava/lang/String;
       5: return

  public java.lang.String getType();
    Code:
       0: aload_0
       1: getfield      #6                  // Field type:Ljava/lang/String;
       4: areturn
}
