Compiled from "RelationshipResolver.java"
public class org.apache.cxf.sts.token.realm.RelationshipResolver {
  private java.util.Map<java.lang.String, org.apache.cxf.sts.token.realm.Relationship> relationshipMap;

  public org.apache.cxf.sts.token.realm.RelationshipResolver(java.util.List<org.apache.cxf.sts.token.realm.Relationship>);
    Code:
       0: aload_0
       1: invokespecial #1                  // Method java/lang/Object."<init>":()V
       4: aload_0
       5: new           #2                  // class java/util/HashMap
       8: dup
       9: invokespecial #3                  // Method java/util/HashMap."<init>":()V
      12: putfield      #4                  // Field relationshipMap:Ljava/util/Map;
      15: aload_1
      16: invokeinterface #5,  1            // InterfaceMethod java/util/List.iterator:()Ljava/util/Iterator;
      21: astore_2
      22: aload_2
      23: invokeinterface #6,  1            // InterfaceMethod java/util/Iterator.hasNext:()Z
      28: ifeq          71
      31: aload_2
      32: invokeinterface #7,  1            // InterfaceMethod java/util/Iterator.next:()Ljava/lang/Object;
      37: checkcast     #8                  // class org/apache/cxf/sts/token/realm/Relationship
      40: astore_3
      41: aload_0
      42: aload_3
      43: invokevirtual #9                  // Method org/apache/cxf/sts/token/realm/Relationship.getSourceRealm:()Ljava/lang/String;
      46: aload_3
      47: invokevirtual #10                 // Method org/apache/cxf/sts/token/realm/Relationship.getTargetRealm:()Ljava/lang/String;
      50: invokespecial #11                 // Method generateKey:(Ljava/lang/String;Ljava/lang/String;)Ljava/lang/String;
      53: astore        4
      55: aload_0
      56: getfield      #4                  // Field relationshipMap:Ljava/util/Map;
      59: aload         4
      61: aload_3
      62: invokeinterface #12,  3           // InterfaceMethod java/util/Map.put:(Ljava/lang/Object;Ljava/lang/Object;)Ljava/lang/Object;
      67: pop
      68: goto          22
      71: return

  public org.apache.cxf.sts.token.realm.Relationship resolveRelationship(java.lang.String, java.lang.String);
    Code:
       0: aload_0
       1: aload_1
       2: aload_2
       3: invokespecial #11                 // Method generateKey:(Ljava/lang/String;Ljava/lang/String;)Ljava/lang/String;
       6: astore_3
       7: aload_0
       8: getfield      #4                  // Field relationshipMap:Ljava/util/Map;
      11: aload_3
      12: invokeinterface #13,  2           // InterfaceMethod java/util/Map.get:(Ljava/lang/Object;)Ljava/lang/Object;
      17: checkcast     #8                  // class org/apache/cxf/sts/token/realm/Relationship
      20: areturn

  private java.lang.String generateKey(java.lang.String, java.lang.String);
    Code:
       0: new           #14                 // class java/lang/StringBuilder
       3: dup
       4: invokespecial #15                 // Method java/lang/StringBuilder."<init>":()V
       7: aload_1
       8: invokevirtual #16                 // Method java/lang/StringBuilder.append:(Ljava/lang/String;)Ljava/lang/StringBuilder;
      11: ldc           #17                 // String >
      13: invokevirtual #16                 // Method java/lang/StringBuilder.append:(Ljava/lang/String;)Ljava/lang/StringBuilder;
      16: aload_2
      17: invokevirtual #16                 // Method java/lang/StringBuilder.append:(Ljava/lang/String;)Ljava/lang/StringBuilder;
      20: invokevirtual #18                 // Method java/lang/StringBuilder.toString:()Ljava/lang/String;
      23: areturn
}
