Compiled from "DoubleOrderedMap.java"
class org.apache.commons.collections.DoubleOrderedMap$5$1 extends org.apache.commons.collections.DoubleOrderedMap$DoubleOrderedMapIterator {
  private final org.apache.commons.collections.DoubleOrderedMap$5 this$1;

  org.apache.commons.collections.DoubleOrderedMap$5$1(org.apache.commons.collections.DoubleOrderedMap$5, int);
    Code:
       0: aload_0
       1: aload_1
       2: invokestatic  #1                  // Method org/apache/commons/collections/DoubleOrderedMap$5.access$2000:(Lorg/apache/commons/collections/DoubleOrderedMap$5;)Lorg/apache/commons/collections/DoubleOrderedMap;
       5: iload_2
       6: invokespecial #2                  // Method org/apache/commons/collections/DoubleOrderedMap$DoubleOrderedMapIterator."<init>":(Lorg/apache/commons/collections/DoubleOrderedMap;I)V
       9: aload_0
      10: aload_1
      11: putfield      #3                  // Field this$1:Lorg/apache/commons/collections/DoubleOrderedMap$5;
      14: return

  protected java.lang.Object doGetNext();
    Code:
       0: aload_0
       1: getfield      #4                  // Field lastReturnedNode:Lorg/apache/commons/collections/DoubleOrderedMap$Node;
       4: iconst_1
       5: invokestatic  #5                  // Method org/apache/commons/collections/DoubleOrderedMap$Node.access$200:(Lorg/apache/commons/collections/DoubleOrderedMap$Node;I)Ljava/lang/Comparable;
       8: areturn
}
