Compiled from "JsonArgument.java"
public class org.smallmind.web.jersey.proxy.JsonArgument {
  private java.lang.String name;

  private javax.xml.bind.annotation.adapters.XmlAdapter xmlAdapter;

  public org.smallmind.web.jersey.proxy.JsonArgument(java.lang.String, javax.xml.bind.annotation.adapters.XmlAdapter);
    Code:
       0: aload_0
       1: invokespecial #13                 // Method java/lang/Object."<init>":()V
       4: aload_0
       5: aload_1
       6: putfield      #16                 // Field name:Ljava/lang/String;
       9: aload_0
      10: aload_2
      11: putfield      #18                 // Field xmlAdapter:Ljavax/xml/bind/annotation/adapters/XmlAdapter;
      14: return

  public java.lang.String getName();
    Code:
       0: aload_0
       1: getfield      #16                 // Field name:Ljava/lang/String;
       4: areturn

  public javax.xml.bind.annotation.adapters.XmlAdapter getXmlAdapter();
    Code:
       0: aload_0
       1: getfield      #18                 // Field xmlAdapter:Ljavax/xml/bind/annotation/adapters/XmlAdapter;
       4: areturn
}
