Compiled from "Authentication.java"
public class org.apache.maven.artifact.repository.Authentication {
  private java.lang.String privateKey;

  private java.lang.String passphrase;

  private java.lang.String username;

  private java.lang.String password;

  public org.apache.maven.artifact.repository.Authentication(java.lang.String, java.lang.String);
    Code:
       0: aload_0
       1: invokespecial #1                  // Method java/lang/Object."<init>":()V
       4: aload_0
       5: aload_1
       6: putfield      #2                  // Field username:Ljava/lang/String;
       9: aload_0
      10: aload_2
      11: putfield      #3                  // Field password:Ljava/lang/String;
      14: return

  public java.lang.String getPassword();
    Code:
       0: aload_0
       1: getfield      #3                  // Field password:Ljava/lang/String;
       4: areturn

  public void setPassword(java.lang.String);
    Code:
       0: aload_0
       1: aload_1
       2: putfield      #3                  // Field password:Ljava/lang/String;
       5: return

  public java.lang.String getUsername();
    Code:
       0: aload_0
       1: getfield      #2                  // Field username:Ljava/lang/String;
       4: areturn

  public void setUsername(java.lang.String);
    Code:
       0: aload_0
       1: aload_1
       2: putfield      #2                  // Field username:Ljava/lang/String;
       5: return

  public java.lang.String getPassphrase();
    Code:
       0: aload_0
       1: getfield      #4                  // Field passphrase:Ljava/lang/String;
       4: areturn

  public void setPassphrase(java.lang.String);
    Code:
       0: aload_0
       1: aload_1
       2: putfield      #4                  // Field passphrase:Ljava/lang/String;
       5: return

  public java.lang.String getPrivateKey();
    Code:
       0: aload_0
       1: getfield      #5                  // Field privateKey:Ljava/lang/String;
       4: areturn

  public void setPrivateKey(java.lang.String);
    Code:
       0: aload_0
       1: aload_1
       2: putfield      #5                  // Field privateKey:Ljava/lang/String;
       5: return
}
