Compiled from "TilesConfigurer.java"
class org.springframework.web.servlet.view.tiles3.TilesConfigurer$SpringTilesInitializer extends org.apache.tiles.startup.DefaultTilesInitializer {
  final org.springframework.web.servlet.view.tiles3.TilesConfigurer this$0;

  private org.springframework.web.servlet.view.tiles3.TilesConfigurer$SpringTilesInitializer(org.springframework.web.servlet.view.tiles3.TilesConfigurer);
    Code:
       0: aload_0
       1: aload_1
       2: putfield      #2                  // Field this$0:Lorg/springframework/web/servlet/view/tiles3/TilesConfigurer;
       5: aload_0
       6: invokespecial #3                  // Method org/apache/tiles/startup/DefaultTilesInitializer."<init>":()V
       9: return

  protected org.apache.tiles.factory.AbstractTilesContainerFactory createContainerFactory(org.apache.tiles.request.ApplicationContext);
    Code:
       0: new           #4                  // class org/springframework/web/servlet/view/tiles3/TilesConfigurer$SpringTilesContainerFactory
       3: dup
       4: aload_0
       5: getfield      #2                  // Field this$0:Lorg/springframework/web/servlet/view/tiles3/TilesConfigurer;
       8: aconst_null
       9: invokespecial #5                  // Method org/springframework/web/servlet/view/tiles3/TilesConfigurer$SpringTilesContainerFactory."<init>":(Lorg/springframework/web/servlet/view/tiles3/TilesConfigurer;Lorg/springframework/web/servlet/view/tiles3/TilesConfigurer$1;)V
      12: areturn

  org.springframework.web.servlet.view.tiles3.TilesConfigurer$SpringTilesInitializer(org.springframework.web.servlet.view.tiles3.TilesConfigurer, org.springframework.web.servlet.view.tiles3.TilesConfigurer$1);
    Code:
       0: aload_0
       1: aload_1
       2: invokespecial #1                  // Method "<init>":(Lorg/springframework/web/servlet/view/tiles3/TilesConfigurer;)V
       5: return
}
