Compiled from "SizeUnits.java"
final class javafx.css.SizeUnits$6 extends javafx.css.SizeUnits {
  javafx.css.SizeUnits$6(java.lang.String, int, boolean);
    Code:
       0: aload_0
       1: aload_1
       2: iload_2
       3: iload_3
       4: aconst_null
       5: invokespecial #1                  // Method javafx/css/SizeUnits."<init>":(Ljava/lang/String;IZLjavafx/css/SizeUnits$1;)V
       8: return

  public java.lang.String toString();
    Code:
       0: ldc           #2                  // String ex
       2: areturn

  public double points(double, double, javafx.scene.text.Font);
    Code:
       0: dload_1
       1: ldc2_w        #3                  // double 2.0d
       4: ddiv
       5: aload         5
       7: invokestatic  #5                  // Method javafx/css/SizeUnits.access$100:(Ljavafx/scene/text/Font;)D
      10: dmul
      11: invokestatic  #6                  // Method javafx/css/SizeUnits.access$200:(D)D
      14: dreturn

  public double pixels(double, double, javafx.scene.text.Font);
    Code:
       0: dload_1
       1: ldc2_w        #3                  // double 2.0d
       4: ddiv
       5: aload         5
       7: invokestatic  #7                  // Method javafx/css/SizeUnits.access$300:(Ljavafx/scene/text/Font;)D
      10: dmul
      11: invokestatic  #6                  // Method javafx/css/SizeUnits.access$200:(D)D
      14: dreturn
}
