Compiled from "StyleOrigin.java"
public final class javafx.css.StyleOrigin extends java.lang.Enum<javafx.css.StyleOrigin> {
  public static final javafx.css.StyleOrigin USER_AGENT;

  public static final javafx.css.StyleOrigin USER;

  public static final javafx.css.StyleOrigin AUTHOR;

  public static final javafx.css.StyleOrigin INLINE;

  private static final javafx.css.StyleOrigin[] $VALUES;

  public static javafx.css.StyleOrigin[] values();
    Code:
       0: getstatic     #1                  // Field $VALUES:[Ljavafx/css/StyleOrigin;
       3: invokevirtual #2                  // Method "[Ljavafx/css/StyleOrigin;".clone:()Ljava/lang/Object;
       6: checkcast     #3                  // class "[Ljavafx/css/StyleOrigin;"
       9: areturn

  public static javafx.css.StyleOrigin valueOf(java.lang.String);
    Code:
       0: ldc           #4                  // class javafx/css/StyleOrigin
       2: aload_0
       3: invokestatic  #5                  // Method java/lang/Enum.valueOf:(Ljava/lang/Class;Ljava/lang/String;)Ljava/lang/Enum;
       6: checkcast     #4                  // class javafx/css/StyleOrigin
       9: areturn

  private javafx.css.StyleOrigin();
    Code:
       0: aload_0
       1: aload_1
       2: iload_2
       3: invokespecial #6                  // Method java/lang/Enum."<init>":(Ljava/lang/String;I)V
       6: return

  static {};
    Code:
       0: new           #4                  // class javafx/css/StyleOrigin
       3: dup
       4: ldc           #7                  // String USER_AGENT
       6: iconst_0
       7: invokespecial #8                  // Method "<init>":(Ljava/lang/String;I)V
      10: putstatic     #9                  // Field USER_AGENT:Ljavafx/css/StyleOrigin;
      13: new           #4                  // class javafx/css/StyleOrigin
      16: dup
      17: ldc           #10                 // String USER
      19: iconst_1
      20: invokespecial #8                  // Method "<init>":(Ljava/lang/String;I)V
      23: putstatic     #11                 // Field USER:Ljavafx/css/StyleOrigin;
      26: new           #4                  // class javafx/css/StyleOrigin
      29: dup
      30: ldc           #12                 // String AUTHOR
      32: iconst_2
      33: invokespecial #8                  // Method "<init>":(Ljava/lang/String;I)V
      36: putstatic     #13                 // Field AUTHOR:Ljavafx/css/StyleOrigin;
      39: new           #4                  // class javafx/css/StyleOrigin
      42: dup
      43: ldc           #14                 // String INLINE
      45: iconst_3
      46: invokespecial #8                  // Method "<init>":(Ljava/lang/String;I)V
      49: putstatic     #15                 // Field INLINE:Ljavafx/css/StyleOrigin;
      52: iconst_4
      53: anewarray     #4                  // class javafx/css/StyleOrigin
      56: dup
      57: iconst_0
      58: getstatic     #9                  // Field USER_AGENT:Ljavafx/css/StyleOrigin;
      61: aastore
      62: dup
      63: iconst_1
      64: getstatic     #11                 // Field USER:Ljavafx/css/StyleOrigin;
      67: aastore
      68: dup
      69: iconst_2
      70: getstatic     #13                 // Field AUTHOR:Ljavafx/css/StyleOrigin;
      73: aastore
      74: dup
      75: iconst_3
      76: getstatic     #15                 // Field INLINE:Ljavafx/css/StyleOrigin;
      79: aastore
      80: putstatic     #1                  // Field $VALUES:[Ljavafx/css/StyleOrigin;
      83: return
}
