Compiled from "StyleablePropertyFactory.java"
class javafx.css.StyleablePropertyFactory$SimpleCssMetaData<S extends javafx.css.Styleable, V> extends javafx.css.CssMetaData<S, V> {
  private final java.util.function.Function<S, javafx.css.StyleableProperty<V>> function;

  javafx.css.StyleablePropertyFactory$SimpleCssMetaData(java.lang.String, java.util.function.Function<S, javafx.css.StyleableProperty<V>>, javafx.css.StyleConverter<?, V>, V, boolean);
    Code:
       0: aload_0
       1: aload_1
       2: aload_3
       3: aload         4
       5: iload         5
       7: invokespecial #1                  // Method javafx/css/CssMetaData."<init>":(Ljava/lang/String;Ljavafx/css/StyleConverter;Ljava/lang/Object;Z)V
      10: aload_0
      11: aload_2
      12: putfield      #2                  // Field function:Ljava/util/function/Function;
      15: return

  public final boolean isSettable(S);
    Code:
       0: aload_0
       1: aload_1
       2: invokevirtual #3                  // Method getStyleableProperty:(Ljavafx/css/Styleable;)Ljavafx/css/StyleableProperty;
       5: astore_2
       6: aload_2
       7: instanceof    #4                  // class javafx/beans/property/Property
      10: ifeq          31
      13: aload_2
      14: checkcast     #4                  // class javafx/beans/property/Property
      17: invokeinterface #5,  1            // InterfaceMethod javafx/beans/property/Property.isBound:()Z
      22: ifne          29
      25: iconst_1
      26: goto          30
      29: iconst_0
      30: ireturn
      31: aload_2
      32: ifnull        39
      35: iconst_1
      36: goto          40
      39: iconst_0
      40: ireturn

  public final javafx.css.StyleableProperty<V> getStyleableProperty(S);
    Code:
       0: aload_1
       1: ifnull        20
       4: aload_0
       5: getfield      #2                  // Field function:Ljava/util/function/Function;
       8: aload_1
       9: invokeinterface #6,  2            // InterfaceMethod java/util/function/Function.apply:(Ljava/lang/Object;)Ljava/lang/Object;
      14: checkcast     #7                  // class javafx/css/StyleableProperty
      17: astore_2
      18: aload_2
      19: areturn
      20: aconst_null
      21: areturn
}
