Compiled from "BoundedByteString.java"
class com.google.protobuf.BoundedByteString$BoundedByteIterator implements com.google.protobuf.ByteString$ByteIterator {
  private int position;

  private final int limit;

  final com.google.protobuf.BoundedByteString this$0;

  private com.google.protobuf.BoundedByteString$BoundedByteIterator(com.google.protobuf.BoundedByteString);
    Code:
       0: aload_0
       1: aload_1
       2: putfield      #2                  // Field this$0:Lcom/google/protobuf/BoundedByteString;
       5: aload_0
       6: invokespecial #3                  // Method java/lang/Object."<init>":()V
       9: aload_0
      10: aload_1
      11: invokevirtual #4                  // Method com/google/protobuf/BoundedByteString.getOffsetIntoBytes:()I
      14: putfield      #5                  // Field position:I
      17: aload_0
      18: aload_0
      19: getfield      #5                  // Field position:I
      22: aload_1
      23: invokevirtual #6                  // Method com/google/protobuf/BoundedByteString.size:()I
      26: iadd
      27: putfield      #7                  // Field limit:I
      30: return

  public boolean hasNext();
    Code:
       0: aload_0
       1: getfield      #5                  // Field position:I
       4: aload_0
       5: getfield      #7                  // Field limit:I
       8: if_icmpge     15
      11: iconst_1
      12: goto          16
      15: iconst_0
      16: ireturn

  public java.lang.Byte next();
    Code:
       0: aload_0
       1: invokevirtual #8                  // Method nextByte:()B
       4: invokestatic  #9                  // Method java/lang/Byte.valueOf:(B)Ljava/lang/Byte;
       7: areturn

  public byte nextByte();
    Code:
       0: aload_0
       1: getfield      #5                  // Field position:I
       4: aload_0
       5: getfield      #7                  // Field limit:I
       8: if_icmplt     19
      11: new           #10                 // class java/util/NoSuchElementException
      14: dup
      15: invokespecial #11                 // Method java/util/NoSuchElementException."<init>":()V
      18: athrow
      19: aload_0
      20: getfield      #2                  // Field this$0:Lcom/google/protobuf/BoundedByteString;
      23: getfield      #12                 // Field com/google/protobuf/BoundedByteString.bytes:[B
      26: aload_0
      27: dup
      28: getfield      #5                  // Field position:I
      31: dup_x1
      32: iconst_1
      33: iadd
      34: putfield      #5                  // Field position:I
      37: baload
      38: ireturn

  public void remove();
    Code:
       0: new           #13                 // class java/lang/UnsupportedOperationException
       3: dup
       4: invokespecial #14                 // Method java/lang/UnsupportedOperationException."<init>":()V
       7: athrow

  public java.lang.Object next();
    Code:
       0: aload_0
       1: invokevirtual #15                 // Method next:()Ljava/lang/Byte;
       4: areturn

  com.google.protobuf.BoundedByteString$BoundedByteIterator(com.google.protobuf.BoundedByteString, com.google.protobuf.BoundedByteString$1);
    Code:
       0: aload_0
       1: aload_1
       2: invokespecial #1                  // Method "<init>":(Lcom/google/protobuf/BoundedByteString;)V
       5: return
}
