Compiled from "ServiceException.java"
public class com.google.protobuf.ServiceException extends java.lang.Exception {
  private static final long serialVersionUID;

  public com.google.protobuf.ServiceException(java.lang.String);
    Code:
       0: aload_0
       1: aload_1
       2: invokespecial #1                  // Method java/lang/Exception."<init>":(Ljava/lang/String;)V
       5: return

  public com.google.protobuf.ServiceException(java.lang.Throwable);
    Code:
       0: aload_0
       1: aload_1
       2: invokespecial #2                  // Method java/lang/Exception."<init>":(Ljava/lang/Throwable;)V
       5: return

  public com.google.protobuf.ServiceException(java.lang.String, java.lang.Throwable);
    Code:
       0: aload_0
       1: aload_1
       2: aload_2
       3: invokespecial #3                  // Method java/lang/Exception."<init>":(Ljava/lang/String;Ljava/lang/Throwable;)V
       6: return
}
