Compiled from "CtBehavior.java"
public abstract class javassist.CtBehavior extends javassist.CtMember {
  protected javassist.bytecode.MethodInfo methodInfo;

  protected javassist.CtBehavior(javassist.CtClass, javassist.bytecode.MethodInfo);
    Code:
       0: aload_0
       1: aload_1
       2: invokespecial #1                  // Method javassist/CtMember."<init>":(Ljavassist/CtClass;)V
       5: aload_0
       6: aload_2
       7: putfield      #2                  // Field methodInfo:Ljavassist/bytecode/MethodInfo;
      10: return

  void copy(javassist.CtBehavior, boolean, javassist.ClassMap) throws javassist.CannotCompileException;
    Code:
       0: aload_0
       1: getfield      #3                  // Field declaringClass:Ljavassist/CtClass;
       4: astore        4
       6: aload_1
       7: getfield      #2                  // Field methodInfo:Ljavassist/bytecode/MethodInfo;
      10: astore        5
      12: aload_1
      13: invokevirtual #4                  // Method getDeclaringClass:()Ljavassist/CtClass;
      16: astore        6
      18: aload         4
      20: invokevirtual #5                  // Method javassist/CtClass.getClassFile2:()Ljavassist/bytecode/ClassFile;
      23: invokevirtual #6                  // Method javassist/bytecode/ClassFile.getConstPool:()Ljavassist/bytecode/ConstPool;
      26: astore        7
      28: new           #7                  // class javassist/ClassMap
      31: dup
      32: aload_3
      33: invokespecial #8                  // Method javassist/ClassMap."<init>":(Ljavassist/ClassMap;)V
      36: astore_3
      37: aload_3
      38: aload         6
      40: invokevirtual #9                  // Method javassist/CtClass.getName:()Ljava/lang/String;
      43: aload         4
      45: invokevirtual #9                  // Method javassist/CtClass.getName:()Ljava/lang/String;
      48: invokevirtual #10                 // Method javassist/ClassMap.put:(Ljava/lang/String;Ljava/lang/String;)Ljava/lang/String;
      51: pop
      52: iconst_0
      53: istore        8
      55: aload         6
      57: invokevirtual #11                 // Method javassist/CtClass.getSuperclass:()Ljavassist/CtClass;
      60: astore        9
      62: aload         4
      64: invokevirtual #11                 // Method javassist/CtClass.getSuperclass:()Ljavassist/CtClass;
      67: astore        10
      69: aconst_null
      70: astore        11
      72: aload         9
      74: ifnull        130
      77: aload         10
      79: ifnull        130
      82: aload         9
      84: invokevirtual #9                  // Method javassist/CtClass.getName:()Ljava/lang/String;
      87: astore        12
      89: aload         10
      91: invokevirtual #9                  // Method javassist/CtClass.getName:()Ljava/lang/String;
      94: astore        11
      96: aload         12
      98: aload         11
     100: invokevirtual #12                 // Method java/lang/String.equals:(Ljava/lang/Object;)Z
     103: ifne          130
     106: aload         12
     108: ldc           #14                 // String java.lang.Object
     110: invokevirtual #12                 // Method java/lang/String.equals:(Ljava/lang/Object;)Z
     113: ifeq          122
     116: iconst_1
     117: istore        8
     119: goto          130
     122: aload_3
     123: aload         12
     125: aload         11
     127: invokevirtual #15                 // Method javassist/ClassMap.putIfNone:(Ljava/lang/String;Ljava/lang/String;)V
     130: aload_0
     131: new           #16                 // class javassist/bytecode/MethodInfo
     134: dup
     135: aload         7
     137: aload         5
     139: invokevirtual #17                 // Method javassist/bytecode/MethodInfo.getName:()Ljava/lang/String;
     142: aload         5
     144: aload_3
     145: invokespecial #18                 // Method javassist/bytecode/MethodInfo."<init>":(Ljavassist/bytecode/ConstPool;Ljava/lang/String;Ljavassist/bytecode/MethodInfo;Ljava/util/Map;)V
     148: putfield      #2                  // Field methodInfo:Ljavassist/bytecode/MethodInfo;
     151: iload_2
     152: ifeq          169
     155: iload         8
     157: ifeq          169
     160: aload_0
     161: getfield      #2                  // Field methodInfo:Ljavassist/bytecode/MethodInfo;
     164: aload         11
     166: invokevirtual #19                 // Method javassist/bytecode/MethodInfo.setSuperclass:(Ljava/lang/String;)V
     169: goto          196
     172: astore        8
     174: new           #21                 // class javassist/CannotCompileException
     177: dup
     178: aload         8
     180: invokespecial #22                 // Method javassist/CannotCompileException."<init>":(Ljavassist/NotFoundException;)V
     183: athrow
     184: astore        8
     186: new           #21                 // class javassist/CannotCompileException
     189: dup
     190: aload         8
     192: invokespecial #24                 // Method javassist/CannotCompileException."<init>":(Ljava/lang/Throwable;)V
     195: athrow
     196: return
    Exception table:
       from    to  target type
          52   169   172   Class javassist/NotFoundException
          52   169   184   Class javassist/bytecode/BadBytecode

  protected void extendToString(java.lang.StringBuffer);
    Code:
       0: aload_1
       1: bipush        32
       3: invokevirtual #25                 // Method java/lang/StringBuffer.append:(C)Ljava/lang/StringBuffer;
       6: pop
       7: aload_1
       8: aload_0
       9: invokevirtual #26                 // Method getName:()Ljava/lang/String;
      12: invokevirtual #27                 // Method java/lang/StringBuffer.append:(Ljava/lang/String;)Ljava/lang/StringBuffer;
      15: pop
      16: aload_1
      17: bipush        32
      19: invokevirtual #25                 // Method java/lang/StringBuffer.append:(C)Ljava/lang/StringBuffer;
      22: pop
      23: aload_1
      24: aload_0
      25: getfield      #2                  // Field methodInfo:Ljavassist/bytecode/MethodInfo;
      28: invokevirtual #28                 // Method javassist/bytecode/MethodInfo.getDescriptor:()Ljava/lang/String;
      31: invokevirtual #27                 // Method java/lang/StringBuffer.append:(Ljava/lang/String;)Ljava/lang/StringBuffer;
      34: pop
      35: return

  public abstract java.lang.String getLongName();

  public javassist.bytecode.MethodInfo getMethodInfo();
    Code:
       0: aload_0
       1: getfield      #3                  // Field declaringClass:Ljavassist/CtClass;
       4: invokevirtual #29                 // Method javassist/CtClass.checkModify:()V
       7: aload_0
       8: getfield      #2                  // Field methodInfo:Ljavassist/bytecode/MethodInfo;
      11: areturn

  public javassist.bytecode.MethodInfo getMethodInfo2();
    Code:
       0: aload_0
       1: getfield      #2                  // Field methodInfo:Ljavassist/bytecode/MethodInfo;
       4: areturn

  public int getModifiers();
    Code:
       0: aload_0
       1: getfield      #2                  // Field methodInfo:Ljavassist/bytecode/MethodInfo;
       4: invokevirtual #30                 // Method javassist/bytecode/MethodInfo.getAccessFlags:()I
       7: invokestatic  #31                 // Method javassist/bytecode/AccessFlag.toModifier:(I)I
      10: ireturn

  public void setModifiers(int);
    Code:
       0: aload_0
       1: getfield      #3                  // Field declaringClass:Ljavassist/CtClass;
       4: invokevirtual #29                 // Method javassist/CtClass.checkModify:()V
       7: aload_0
       8: getfield      #2                  // Field methodInfo:Ljavassist/bytecode/MethodInfo;
      11: iload_1
      12: invokestatic  #32                 // Method javassist/bytecode/AccessFlag.of:(I)I
      15: invokevirtual #33                 // Method javassist/bytecode/MethodInfo.setAccessFlags:(I)V
      18: return

  public boolean hasAnnotation(java.lang.String);
    Code:
       0: aload_0
       1: invokevirtual #34                 // Method getMethodInfo2:()Ljavassist/bytecode/MethodInfo;
       4: astore_2
       5: aload_2
       6: ldc           #36                 // String RuntimeInvisibleAnnotations
       8: invokevirtual #37                 // Method javassist/bytecode/MethodInfo.getAttribute:(Ljava/lang/String;)Ljavassist/bytecode/AttributeInfo;
      11: checkcast     #35                 // class javassist/bytecode/AnnotationsAttribute
      14: astore_3
      15: aload_2
      16: ldc           #38                 // String RuntimeVisibleAnnotations
      18: invokevirtual #37                 // Method javassist/bytecode/MethodInfo.getAttribute:(Ljava/lang/String;)Ljavassist/bytecode/AttributeInfo;
      21: checkcast     #35                 // class javassist/bytecode/AnnotationsAttribute
      24: astore        4
      26: aload_1
      27: aload_0
      28: invokevirtual #4                  // Method getDeclaringClass:()Ljavassist/CtClass;
      31: invokevirtual #39                 // Method javassist/CtClass.getClassPool:()Ljavassist/ClassPool;
      34: aload_3
      35: aload         4
      37: invokestatic  #40                 // Method javassist/CtClassType.hasAnnotationType:(Ljava/lang/String;Ljavassist/ClassPool;Ljavassist/bytecode/AnnotationsAttribute;Ljavassist/bytecode/AnnotationsAttribute;)Z
      40: ireturn

  public java.lang.Object getAnnotation(java.lang.Class<?>) throws java.lang.ClassNotFoundException;
    Code:
       0: aload_0
       1: invokevirtual #34                 // Method getMethodInfo2:()Ljavassist/bytecode/MethodInfo;
       4: astore_2
       5: aload_2
       6: ldc           #36                 // String RuntimeInvisibleAnnotations
       8: invokevirtual #37                 // Method javassist/bytecode/MethodInfo.getAttribute:(Ljava/lang/String;)Ljavassist/bytecode/AttributeInfo;
      11: checkcast     #35                 // class javassist/bytecode/AnnotationsAttribute
      14: astore_3
      15: aload_2
      16: ldc           #38                 // String RuntimeVisibleAnnotations
      18: invokevirtual #37                 // Method javassist/bytecode/MethodInfo.getAttribute:(Ljava/lang/String;)Ljavassist/bytecode/AttributeInfo;
      21: checkcast     #35                 // class javassist/bytecode/AnnotationsAttribute
      24: astore        4
      26: aload_1
      27: aload_0
      28: invokevirtual #4                  // Method getDeclaringClass:()Ljavassist/CtClass;
      31: invokevirtual #39                 // Method javassist/CtClass.getClassPool:()Ljavassist/ClassPool;
      34: aload_3
      35: aload         4
      37: invokestatic  #41                 // Method javassist/CtClassType.getAnnotationType:(Ljava/lang/Class;Ljavassist/ClassPool;Ljavassist/bytecode/AnnotationsAttribute;Ljavassist/bytecode/AnnotationsAttribute;)Ljava/lang/Object;
      40: areturn

  public java.lang.Object[] getAnnotations() throws java.lang.ClassNotFoundException;
    Code:
       0: aload_0
       1: iconst_0
       2: invokespecial #42                 // Method getAnnotations:(Z)[Ljava/lang/Object;
       5: areturn

  public java.lang.Object[] getAvailableAnnotations();
    Code:
       0: aload_0
       1: iconst_1
       2: invokespecial #42                 // Method getAnnotations:(Z)[Ljava/lang/Object;
       5: areturn
       6: astore_1
       7: new           #44                 // class java/lang/RuntimeException
      10: dup
      11: ldc           #45                 // String Unexpected exception
      13: aload_1
      14: invokespecial #46                 // Method java/lang/RuntimeException."<init>":(Ljava/lang/String;Ljava/lang/Throwable;)V
      17: athrow
    Exception table:
       from    to  target type
           0     5     6   Class java/lang/ClassNotFoundException

  private java.lang.Object[] getAnnotations(boolean) throws java.lang.ClassNotFoundException;
    Code:
       0: aload_0
       1: invokevirtual #34                 // Method getMethodInfo2:()Ljavassist/bytecode/MethodInfo;
       4: astore_2
       5: aload_2
       6: ldc           #36                 // String RuntimeInvisibleAnnotations
       8: invokevirtual #37                 // Method javassist/bytecode/MethodInfo.getAttribute:(Ljava/lang/String;)Ljavassist/bytecode/AttributeInfo;
      11: checkcast     #35                 // class javassist/bytecode/AnnotationsAttribute
      14: astore_3
      15: aload_2
      16: ldc           #38                 // String RuntimeVisibleAnnotations
      18: invokevirtual #37                 // Method javassist/bytecode/MethodInfo.getAttribute:(Ljava/lang/String;)Ljavassist/bytecode/AttributeInfo;
      21: checkcast     #35                 // class javassist/bytecode/AnnotationsAttribute
      24: astore        4
      26: iload_1
      27: aload_0
      28: invokevirtual #4                  // Method getDeclaringClass:()Ljavassist/CtClass;
      31: invokevirtual #39                 // Method javassist/CtClass.getClassPool:()Ljavassist/ClassPool;
      34: aload_3
      35: aload         4
      37: invokestatic  #47                 // Method javassist/CtClassType.toAnnotationType:(ZLjavassist/ClassPool;Ljavassist/bytecode/AnnotationsAttribute;Ljavassist/bytecode/AnnotationsAttribute;)[Ljava/lang/Object;
      40: areturn

  public java.lang.Object[][] getParameterAnnotations() throws java.lang.ClassNotFoundException;
    Code:
       0: aload_0
       1: iconst_0
       2: invokevirtual #48                 // Method getParameterAnnotations:(Z)[[Ljava/lang/Object;
       5: areturn

  public java.lang.Object[][] getAvailableParameterAnnotations();
    Code:
       0: aload_0
       1: iconst_1
       2: invokevirtual #48                 // Method getParameterAnnotations:(Z)[[Ljava/lang/Object;
       5: areturn
       6: astore_1
       7: new           #44                 // class java/lang/RuntimeException
      10: dup
      11: ldc           #45                 // String Unexpected exception
      13: aload_1
      14: invokespecial #46                 // Method java/lang/RuntimeException."<init>":(Ljava/lang/String;Ljava/lang/Throwable;)V
      17: athrow
    Exception table:
       from    to  target type
           0     5     6   Class java/lang/ClassNotFoundException

  java.lang.Object[][] getParameterAnnotations(boolean) throws java.lang.ClassNotFoundException;
    Code:
       0: aload_0
       1: invokevirtual #34                 // Method getMethodInfo2:()Ljavassist/bytecode/MethodInfo;
       4: astore_2
       5: aload_2
       6: ldc           #50                 // String RuntimeInvisibleParameterAnnotations
       8: invokevirtual #37                 // Method javassist/bytecode/MethodInfo.getAttribute:(Ljava/lang/String;)Ljavassist/bytecode/AttributeInfo;
      11: checkcast     #49                 // class javassist/bytecode/ParameterAnnotationsAttribute
      14: astore_3
      15: aload_2
      16: ldc           #51                 // String RuntimeVisibleParameterAnnotations
      18: invokevirtual #37                 // Method javassist/bytecode/MethodInfo.getAttribute:(Ljava/lang/String;)Ljavassist/bytecode/AttributeInfo;
      21: checkcast     #49                 // class javassist/bytecode/ParameterAnnotationsAttribute
      24: astore        4
      26: iload_1
      27: aload_0
      28: invokevirtual #4                  // Method getDeclaringClass:()Ljavassist/CtClass;
      31: invokevirtual #39                 // Method javassist/CtClass.getClassPool:()Ljavassist/ClassPool;
      34: aload_3
      35: aload         4
      37: aload_2
      38: invokestatic  #52                 // Method javassist/CtClassType.toAnnotationType:(ZLjavassist/ClassPool;Ljavassist/bytecode/ParameterAnnotationsAttribute;Ljavassist/bytecode/ParameterAnnotationsAttribute;Ljavassist/bytecode/MethodInfo;)[[Ljava/lang/Object;
      41: areturn

  public javassist.CtClass[] getParameterTypes() throws javassist.NotFoundException;
    Code:
       0: aload_0
       1: getfield      #2                  // Field methodInfo:Ljavassist/bytecode/MethodInfo;
       4: invokevirtual #28                 // Method javassist/bytecode/MethodInfo.getDescriptor:()Ljava/lang/String;
       7: aload_0
       8: getfield      #3                  // Field declaringClass:Ljavassist/CtClass;
      11: invokevirtual #39                 // Method javassist/CtClass.getClassPool:()Ljavassist/ClassPool;
      14: invokestatic  #53                 // Method javassist/bytecode/Descriptor.getParameterTypes:(Ljava/lang/String;Ljavassist/ClassPool;)[Ljavassist/CtClass;
      17: areturn

  javassist.CtClass getReturnType0() throws javassist.NotFoundException;
    Code:
       0: aload_0
       1: getfield      #2                  // Field methodInfo:Ljavassist/bytecode/MethodInfo;
       4: invokevirtual #28                 // Method javassist/bytecode/MethodInfo.getDescriptor:()Ljava/lang/String;
       7: aload_0
       8: getfield      #3                  // Field declaringClass:Ljavassist/CtClass;
      11: invokevirtual #39                 // Method javassist/CtClass.getClassPool:()Ljavassist/ClassPool;
      14: invokestatic  #54                 // Method javassist/bytecode/Descriptor.getReturnType:(Ljava/lang/String;Ljavassist/ClassPool;)Ljavassist/CtClass;
      17: areturn

  public java.lang.String getSignature();
    Code:
       0: aload_0
       1: getfield      #2                  // Field methodInfo:Ljavassist/bytecode/MethodInfo;
       4: invokevirtual #28                 // Method javassist/bytecode/MethodInfo.getDescriptor:()Ljava/lang/String;
       7: areturn

  public java.lang.String getGenericSignature();
    Code:
       0: aload_0
       1: getfield      #2                  // Field methodInfo:Ljavassist/bytecode/MethodInfo;
       4: ldc           #56                 // String Signature
       6: invokevirtual #37                 // Method javassist/bytecode/MethodInfo.getAttribute:(Ljava/lang/String;)Ljavassist/bytecode/AttributeInfo;
       9: checkcast     #55                 // class javassist/bytecode/SignatureAttribute
      12: astore_1
      13: aload_1
      14: ifnonnull     21
      17: aconst_null
      18: goto          25
      21: aload_1
      22: invokevirtual #57                 // Method javassist/bytecode/SignatureAttribute.getSignature:()Ljava/lang/String;
      25: areturn

  public void setGenericSignature(java.lang.String);
    Code:
       0: aload_0
       1: getfield      #3                  // Field declaringClass:Ljavassist/CtClass;
       4: invokevirtual #29                 // Method javassist/CtClass.checkModify:()V
       7: aload_0
       8: getfield      #2                  // Field methodInfo:Ljavassist/bytecode/MethodInfo;
      11: new           #55                 // class javassist/bytecode/SignatureAttribute
      14: dup
      15: aload_0
      16: getfield      #2                  // Field methodInfo:Ljavassist/bytecode/MethodInfo;
      19: invokevirtual #58                 // Method javassist/bytecode/MethodInfo.getConstPool:()Ljavassist/bytecode/ConstPool;
      22: aload_1
      23: invokespecial #59                 // Method javassist/bytecode/SignatureAttribute."<init>":(Ljavassist/bytecode/ConstPool;Ljava/lang/String;)V
      26: invokevirtual #60                 // Method javassist/bytecode/MethodInfo.addAttribute:(Ljavassist/bytecode/AttributeInfo;)V
      29: return

  public javassist.CtClass[] getExceptionTypes() throws javassist.NotFoundException;
    Code:
       0: aload_0
       1: getfield      #2                  // Field methodInfo:Ljavassist/bytecode/MethodInfo;
       4: invokevirtual #61                 // Method javassist/bytecode/MethodInfo.getExceptionsAttribute:()Ljavassist/bytecode/ExceptionsAttribute;
       7: astore_2
       8: aload_2
       9: ifnonnull     17
      12: aconst_null
      13: astore_1
      14: goto          22
      17: aload_2
      18: invokevirtual #62                 // Method javassist/bytecode/ExceptionsAttribute.getExceptions:()[Ljava/lang/String;
      21: astore_1
      22: aload_0
      23: getfield      #3                  // Field declaringClass:Ljavassist/CtClass;
      26: invokevirtual #39                 // Method javassist/CtClass.getClassPool:()Ljavassist/ClassPool;
      29: aload_1
      30: invokevirtual #63                 // Method javassist/ClassPool.get:([Ljava/lang/String;)[Ljavassist/CtClass;
      33: areturn

  public void setExceptionTypes(javassist.CtClass[]) throws javassist.NotFoundException;
    Code:
       0: aload_0
       1: getfield      #3                  // Field declaringClass:Ljavassist/CtClass;
       4: invokevirtual #29                 // Method javassist/CtClass.checkModify:()V
       7: aload_1
       8: ifnull        16
      11: aload_1
      12: arraylength
      13: ifne          24
      16: aload_0
      17: getfield      #2                  // Field methodInfo:Ljavassist/bytecode/MethodInfo;
      20: invokevirtual #64                 // Method javassist/bytecode/MethodInfo.removeExceptionsAttribute:()V
      23: return
      24: aload_1
      25: arraylength
      26: anewarray     #65                 // class java/lang/String
      29: astore_2
      30: iconst_0
      31: istore_3
      32: iload_3
      33: aload_1
      34: arraylength
      35: if_icmpge     53
      38: aload_2
      39: iload_3
      40: aload_1
      41: iload_3
      42: aaload
      43: invokevirtual #9                  // Method javassist/CtClass.getName:()Ljava/lang/String;
      46: aastore
      47: iinc          3, 1
      50: goto          32
      53: aload_0
      54: getfield      #2                  // Field methodInfo:Ljavassist/bytecode/MethodInfo;
      57: invokevirtual #61                 // Method javassist/bytecode/MethodInfo.getExceptionsAttribute:()Ljavassist/bytecode/ExceptionsAttribute;
      60: astore_3
      61: aload_3
      62: ifnonnull     88
      65: new           #66                 // class javassist/bytecode/ExceptionsAttribute
      68: dup
      69: aload_0
      70: getfield      #2                  // Field methodInfo:Ljavassist/bytecode/MethodInfo;
      73: invokevirtual #58                 // Method javassist/bytecode/MethodInfo.getConstPool:()Ljavassist/bytecode/ConstPool;
      76: invokespecial #67                 // Method javassist/bytecode/ExceptionsAttribute."<init>":(Ljavassist/bytecode/ConstPool;)V
      79: astore_3
      80: aload_0
      81: getfield      #2                  // Field methodInfo:Ljavassist/bytecode/MethodInfo;
      84: aload_3
      85: invokevirtual #68                 // Method javassist/bytecode/MethodInfo.setExceptionsAttribute:(Ljavassist/bytecode/ExceptionsAttribute;)V
      88: aload_3
      89: aload_2
      90: invokevirtual #69                 // Method javassist/bytecode/ExceptionsAttribute.setExceptions:([Ljava/lang/String;)V
      93: return

  public abstract boolean isEmpty();

  public void setBody(java.lang.String) throws javassist.CannotCompileException;
    Code:
       0: aload_0
       1: aload_1
       2: aconst_null
       3: aconst_null
       4: invokevirtual #70                 // Method setBody:(Ljava/lang/String;Ljava/lang/String;Ljava/lang/String;)V
       7: return

  public void setBody(java.lang.String, java.lang.String, java.lang.String) throws javassist.CannotCompileException;
    Code:
       0: aload_0
       1: getfield      #3                  // Field declaringClass:Ljavassist/CtClass;
       4: astore        4
       6: aload         4
       8: invokevirtual #29                 // Method javassist/CtClass.checkModify:()V
      11: new           #71                 // class javassist/compiler/Javac
      14: dup
      15: aload         4
      17: invokespecial #72                 // Method javassist/compiler/Javac."<init>":(Ljavassist/CtClass;)V
      20: astore        5
      22: aload_3
      23: ifnull        33
      26: aload         5
      28: aload_2
      29: aload_3
      30: invokevirtual #73                 // Method javassist/compiler/Javac.recordProceed:(Ljava/lang/String;Ljava/lang/String;)V
      33: aload         5
      35: aload_0
      36: aload_1
      37: invokevirtual #74                 // Method javassist/compiler/Javac.compileBody:(Ljavassist/CtBehavior;Ljava/lang/String;)Ljavassist/bytecode/Bytecode;
      40: astore        6
      42: aload_0
      43: getfield      #2                  // Field methodInfo:Ljavassist/bytecode/MethodInfo;
      46: aload         6
      48: invokevirtual #75                 // Method javassist/bytecode/Bytecode.toCodeAttribute:()Ljavassist/bytecode/CodeAttribute;
      51: invokevirtual #76                 // Method javassist/bytecode/MethodInfo.setCodeAttribute:(Ljavassist/bytecode/CodeAttribute;)V
      54: aload_0
      55: getfield      #2                  // Field methodInfo:Ljavassist/bytecode/MethodInfo;
      58: aload_0
      59: getfield      #2                  // Field methodInfo:Ljavassist/bytecode/MethodInfo;
      62: invokevirtual #30                 // Method javassist/bytecode/MethodInfo.getAccessFlags:()I
      65: sipush        -1025
      68: iand
      69: invokevirtual #33                 // Method javassist/bytecode/MethodInfo.setAccessFlags:(I)V
      72: aload_0
      73: getfield      #2                  // Field methodInfo:Ljavassist/bytecode/MethodInfo;
      76: aload         4
      78: invokevirtual #39                 // Method javassist/CtClass.getClassPool:()Ljavassist/ClassPool;
      81: aload         4
      83: invokevirtual #5                  // Method javassist/CtClass.getClassFile2:()Ljavassist/bytecode/ClassFile;
      86: invokevirtual #78                 // Method javassist/bytecode/MethodInfo.rebuildStackMapIf6:(Ljavassist/ClassPool;Ljavassist/bytecode/ClassFile;)V
      89: aload_0
      90: getfield      #3                  // Field declaringClass:Ljavassist/CtClass;
      93: invokevirtual #79                 // Method javassist/CtClass.rebuildClassFile:()V
      96: goto          123
      99: astore        5
     101: new           #21                 // class javassist/CannotCompileException
     104: dup
     105: aload         5
     107: invokespecial #81                 // Method javassist/CannotCompileException."<init>":(Ljavassist/compiler/CompileError;)V
     110: athrow
     111: astore        5
     113: new           #21                 // class javassist/CannotCompileException
     116: dup
     117: aload         5
     119: invokespecial #24                 // Method javassist/CannotCompileException."<init>":(Ljava/lang/Throwable;)V
     122: athrow
     123: return
    Exception table:
       from    to  target type
          11    96    99   Class javassist/compiler/CompileError
          11    96   111   Class javassist/bytecode/BadBytecode

  static void setBody0(javassist.CtClass, javassist.bytecode.MethodInfo, javassist.CtClass, javassist.bytecode.MethodInfo, javassist.ClassMap) throws javassist.CannotCompileException;
    Code:
       0: aload_2
       1: invokevirtual #29                 // Method javassist/CtClass.checkModify:()V
       4: new           #7                  // class javassist/ClassMap
       7: dup
       8: aload         4
      10: invokespecial #8                  // Method javassist/ClassMap."<init>":(Ljavassist/ClassMap;)V
      13: astore        4
      15: aload         4
      17: aload_0
      18: invokevirtual #9                  // Method javassist/CtClass.getName:()Ljava/lang/String;
      21: aload_2
      22: invokevirtual #9                  // Method javassist/CtClass.getName:()Ljava/lang/String;
      25: invokevirtual #10                 // Method javassist/ClassMap.put:(Ljava/lang/String;Ljava/lang/String;)Ljava/lang/String;
      28: pop
      29: aload_1
      30: invokevirtual #82                 // Method javassist/bytecode/MethodInfo.getCodeAttribute:()Ljavassist/bytecode/CodeAttribute;
      33: astore        5
      35: aload         5
      37: ifnull        66
      40: aload_3
      41: invokevirtual #58                 // Method javassist/bytecode/MethodInfo.getConstPool:()Ljavassist/bytecode/ConstPool;
      44: astore        6
      46: aload         5
      48: aload         6
      50: aload         4
      52: invokevirtual #83                 // Method javassist/bytecode/CodeAttribute.copy:(Ljavassist/bytecode/ConstPool;Ljava/util/Map;)Ljavassist/bytecode/AttributeInfo;
      55: checkcast     #84                 // class javassist/bytecode/CodeAttribute
      58: astore        7
      60: aload_3
      61: aload         7
      63: invokevirtual #76                 // Method javassist/bytecode/MethodInfo.setCodeAttribute:(Ljavassist/bytecode/CodeAttribute;)V
      66: goto          81
      69: astore        5
      71: new           #21                 // class javassist/CannotCompileException
      74: dup
      75: aload         5
      77: invokespecial #24                 // Method javassist/CannotCompileException."<init>":(Ljava/lang/Throwable;)V
      80: athrow
      81: aload_3
      82: aload_3
      83: invokevirtual #30                 // Method javassist/bytecode/MethodInfo.getAccessFlags:()I
      86: sipush        -1025
      89: iand
      90: invokevirtual #33                 // Method javassist/bytecode/MethodInfo.setAccessFlags:(I)V
      93: aload_2
      94: invokevirtual #79                 // Method javassist/CtClass.rebuildClassFile:()V
      97: return
    Exception table:
       from    to  target type
          29    66    69   Class javassist/bytecode/CodeAttribute$RuntimeCopyException

  public byte[] getAttribute(java.lang.String);
    Code:
       0: aload_0
       1: getfield      #2                  // Field methodInfo:Ljavassist/bytecode/MethodInfo;
       4: aload_1
       5: invokevirtual #37                 // Method javassist/bytecode/MethodInfo.getAttribute:(Ljava/lang/String;)Ljavassist/bytecode/AttributeInfo;
       8: astore_2
       9: aload_2
      10: ifnonnull     15
      13: aconst_null
      14: areturn
      15: aload_2
      16: invokevirtual #86                 // Method javassist/bytecode/AttributeInfo.get:()[B
      19: areturn

  public void setAttribute(java.lang.String, byte[]);
    Code:
       0: aload_0
       1: getfield      #3                  // Field declaringClass:Ljavassist/CtClass;
       4: invokevirtual #29                 // Method javassist/CtClass.checkModify:()V
       7: aload_0
       8: getfield      #2                  // Field methodInfo:Ljavassist/bytecode/MethodInfo;
      11: new           #87                 // class javassist/bytecode/AttributeInfo
      14: dup
      15: aload_0
      16: getfield      #2                  // Field methodInfo:Ljavassist/bytecode/MethodInfo;
      19: invokevirtual #58                 // Method javassist/bytecode/MethodInfo.getConstPool:()Ljavassist/bytecode/ConstPool;
      22: aload_1
      23: aload_2
      24: invokespecial #88                 // Method javassist/bytecode/AttributeInfo."<init>":(Ljavassist/bytecode/ConstPool;Ljava/lang/String;[B)V
      27: invokevirtual #60                 // Method javassist/bytecode/MethodInfo.addAttribute:(Ljavassist/bytecode/AttributeInfo;)V
      30: return

  public void useCflow(java.lang.String) throws javassist.CannotCompileException;
    Code:
       0: aload_0
       1: getfield      #3                  // Field declaringClass:Ljavassist/CtClass;
       4: astore_2
       5: aload_2
       6: invokevirtual #29                 // Method javassist/CtClass.checkModify:()V
       9: aload_2
      10: invokevirtual #39                 // Method javassist/CtClass.getClassPool:()Ljavassist/ClassPool;
      13: astore_3
      14: iconst_0
      15: istore        5
      17: new           #89                 // class java/lang/StringBuilder
      20: dup
      21: invokespecial #90                 // Method java/lang/StringBuilder."<init>":()V
      24: ldc           #91                 // String _cflow$
      26: invokevirtual #92                 // Method java/lang/StringBuilder.append:(Ljava/lang/String;)Ljava/lang/StringBuilder;
      29: iload         5
      31: iinc          5, 1
      34: invokevirtual #93                 // Method java/lang/StringBuilder.append:(I)Ljava/lang/StringBuilder;
      37: invokevirtual #94                 // Method java/lang/StringBuilder.toString:()Ljava/lang/String;
      40: astore        4
      42: aload_2
      43: aload         4
      45: invokevirtual #95                 // Method javassist/CtClass.getDeclaredField:(Ljava/lang/String;)Ljavassist/CtField;
      48: pop
      49: goto          17
      52: astore        6
      54: goto          57
      57: aload_3
      58: aload_1
      59: aload_0
      60: getfield      #3                  // Field declaringClass:Ljavassist/CtClass;
      63: invokevirtual #9                  // Method javassist/CtClass.getName:()Ljava/lang/String;
      66: aload         4
      68: invokevirtual #96                 // Method javassist/ClassPool.recordCflow:(Ljava/lang/String;Ljava/lang/String;Ljava/lang/String;)V
      71: aload_3
      72: ldc           #97                 // String javassist.runtime.Cflow
      74: invokevirtual #98                 // Method javassist/ClassPool.get:(Ljava/lang/String;)Ljavassist/CtClass;
      77: astore        6
      79: new           #99                 // class javassist/CtField
      82: dup
      83: aload         6
      85: aload         4
      87: aload_2
      88: invokespecial #100                // Method javassist/CtField."<init>":(Ljavassist/CtClass;Ljava/lang/String;Ljavassist/CtClass;)V
      91: astore        7
      93: aload         7
      95: bipush        9
      97: invokevirtual #102                // Method javassist/CtField.setModifiers:(I)V
     100: aload_2
     101: aload         7
     103: aload         6
     105: invokestatic  #103                // Method javassist/CtField$Initializer.byNew:(Ljavassist/CtClass;)Ljavassist/CtField$Initializer;
     108: invokevirtual #104                // Method javassist/CtClass.addField:(Ljavassist/CtField;Ljavassist/CtField$Initializer;)V
     111: aload_0
     112: new           #89                 // class java/lang/StringBuilder
     115: dup
     116: invokespecial #90                 // Method java/lang/StringBuilder."<init>":()V
     119: aload         4
     121: invokevirtual #92                 // Method java/lang/StringBuilder.append:(Ljava/lang/String;)Ljava/lang/StringBuilder;
     124: ldc           #105                // String .enter();
     126: invokevirtual #92                 // Method java/lang/StringBuilder.append:(Ljava/lang/String;)Ljava/lang/StringBuilder;
     129: invokevirtual #94                 // Method java/lang/StringBuilder.toString:()Ljava/lang/String;
     132: iconst_0
     133: invokespecial #106                // Method insertBefore:(Ljava/lang/String;Z)V
     136: new           #89                 // class java/lang/StringBuilder
     139: dup
     140: invokespecial #90                 // Method java/lang/StringBuilder."<init>":()V
     143: aload         4
     145: invokevirtual #92                 // Method java/lang/StringBuilder.append:(Ljava/lang/String;)Ljava/lang/StringBuilder;
     148: ldc           #107                // String .exit();
     150: invokevirtual #92                 // Method java/lang/StringBuilder.append:(Ljava/lang/String;)Ljava/lang/StringBuilder;
     153: invokevirtual #94                 // Method java/lang/StringBuilder.toString:()Ljava/lang/String;
     156: astore        8
     158: aload_0
     159: aload         8
     161: iconst_1
     162: invokevirtual #108                // Method insertAfter:(Ljava/lang/String;Z)V
     165: goto          180
     168: astore        6
     170: new           #21                 // class javassist/CannotCompileException
     173: dup
     174: aload         6
     176: invokespecial #22                 // Method javassist/CannotCompileException."<init>":(Ljavassist/NotFoundException;)V
     179: athrow
     180: return
    Exception table:
       from    to  target type
          42    49    52   Class javassist/NotFoundException
          71   165   168   Class javassist/NotFoundException

  public void addLocalVariable(java.lang.String, javassist.CtClass) throws javassist.CannotCompileException;
    Code:
       0: aload_0
       1: getfield      #3                  // Field declaringClass:Ljavassist/CtClass;
       4: invokevirtual #29                 // Method javassist/CtClass.checkModify:()V
       7: aload_0
       8: getfield      #2                  // Field methodInfo:Ljavassist/bytecode/MethodInfo;
      11: invokevirtual #58                 // Method javassist/bytecode/MethodInfo.getConstPool:()Ljavassist/bytecode/ConstPool;
      14: astore_3
      15: aload_0
      16: getfield      #2                  // Field methodInfo:Ljavassist/bytecode/MethodInfo;
      19: invokevirtual #82                 // Method javassist/bytecode/MethodInfo.getCodeAttribute:()Ljavassist/bytecode/CodeAttribute;
      22: astore        4
      24: aload         4
      26: ifnonnull     39
      29: new           #21                 // class javassist/CannotCompileException
      32: dup
      33: ldc           #109                // String no method body
      35: invokespecial #110                // Method javassist/CannotCompileException."<init>":(Ljava/lang/String;)V
      38: athrow
      39: aload         4
      41: ldc           #112                // String LocalVariableTable
      43: invokevirtual #113                // Method javassist/bytecode/CodeAttribute.getAttribute:(Ljava/lang/String;)Ljavassist/bytecode/AttributeInfo;
      46: checkcast     #111                // class javassist/bytecode/LocalVariableAttribute
      49: astore        5
      51: aload         5
      53: ifnonnull     79
      56: new           #111                // class javassist/bytecode/LocalVariableAttribute
      59: dup
      60: aload_3
      61: invokespecial #114                // Method javassist/bytecode/LocalVariableAttribute."<init>":(Ljavassist/bytecode/ConstPool;)V
      64: astore        5
      66: aload         4
      68: invokevirtual #115                // Method javassist/bytecode/CodeAttribute.getAttributes:()Ljava/util/List;
      71: aload         5
      73: invokeinterface #116,  2          // InterfaceMethod java/util/List.add:(Ljava/lang/Object;)Z
      78: pop
      79: aload         4
      81: invokevirtual #117                // Method javassist/bytecode/CodeAttribute.getMaxLocals:()I
      84: istore        6
      86: aload_2
      87: invokestatic  #118                // Method javassist/bytecode/Descriptor.of:(Ljavassist/CtClass;)Ljava/lang/String;
      90: astore        7
      92: aload         5
      94: iconst_0
      95: aload         4
      97: invokevirtual #119                // Method javassist/bytecode/CodeAttribute.getCodeLength:()I
     100: aload_3
     101: aload_1
     102: invokevirtual #120                // Method javassist/bytecode/ConstPool.addUtf8Info:(Ljava/lang/String;)I
     105: aload_3
     106: aload         7
     108: invokevirtual #120                // Method javassist/bytecode/ConstPool.addUtf8Info:(Ljava/lang/String;)I
     111: iload         6
     113: invokevirtual #121                // Method javassist/bytecode/LocalVariableAttribute.addEntry:(IIIII)V
     116: aload         4
     118: iload         6
     120: aload         7
     122: invokestatic  #122                // Method javassist/bytecode/Descriptor.dataSize:(Ljava/lang/String;)I
     125: iadd
     126: invokevirtual #123                // Method javassist/bytecode/CodeAttribute.setMaxLocals:(I)V
     129: return

  public void insertParameter(javassist.CtClass) throws javassist.CannotCompileException;
    Code:
       0: aload_0
       1: getfield      #3                  // Field declaringClass:Ljavassist/CtClass;
       4: invokevirtual #29                 // Method javassist/CtClass.checkModify:()V
       7: aload_0
       8: getfield      #2                  // Field methodInfo:Ljavassist/bytecode/MethodInfo;
      11: invokevirtual #28                 // Method javassist/bytecode/MethodInfo.getDescriptor:()Ljava/lang/String;
      14: astore_2
      15: aload_1
      16: aload_2
      17: invokestatic  #124                // Method javassist/bytecode/Descriptor.insertParameter:(Ljavassist/CtClass;Ljava/lang/String;)Ljava/lang/String;
      20: astore_3
      21: aload_0
      22: aload_0
      23: invokevirtual #125                // Method getModifiers:()I
      26: invokestatic  #126                // Method javassist/Modifier.isStatic:(I)Z
      29: ifeq          36
      32: iconst_0
      33: goto          37
      36: iconst_1
      37: aload_1
      38: aload_2
      39: invokespecial #127                // Method addParameter2:(ILjavassist/CtClass;Ljava/lang/String;)V
      42: goto          57
      45: astore        4
      47: new           #21                 // class javassist/CannotCompileException
      50: dup
      51: aload         4
      53: invokespecial #24                 // Method javassist/CannotCompileException."<init>":(Ljava/lang/Throwable;)V
      56: athrow
      57: aload_0
      58: getfield      #2                  // Field methodInfo:Ljavassist/bytecode/MethodInfo;
      61: aload_3
      62: invokevirtual #128                // Method javassist/bytecode/MethodInfo.setDescriptor:(Ljava/lang/String;)V
      65: return
    Exception table:
       from    to  target type
          21    42    45   Class javassist/bytecode/BadBytecode

  public void addParameter(javassist.CtClass) throws javassist.CannotCompileException;
    Code:
       0: aload_0
       1: getfield      #3                  // Field declaringClass:Ljavassist/CtClass;
       4: invokevirtual #29                 // Method javassist/CtClass.checkModify:()V
       7: aload_0
       8: getfield      #2                  // Field methodInfo:Ljavassist/bytecode/MethodInfo;
      11: invokevirtual #28                 // Method javassist/bytecode/MethodInfo.getDescriptor:()Ljava/lang/String;
      14: astore_2
      15: aload_1
      16: aload_2
      17: invokestatic  #129                // Method javassist/bytecode/Descriptor.appendParameter:(Ljavassist/CtClass;Ljava/lang/String;)Ljava/lang/String;
      20: astore_3
      21: aload_0
      22: invokevirtual #125                // Method getModifiers:()I
      25: invokestatic  #126                // Method javassist/Modifier.isStatic:(I)Z
      28: ifeq          35
      31: iconst_0
      32: goto          36
      35: iconst_1
      36: istore        4
      38: aload_0
      39: iload         4
      41: aload_2
      42: invokestatic  #130                // Method javassist/bytecode/Descriptor.paramSize:(Ljava/lang/String;)I
      45: iadd
      46: aload_1
      47: aload_2
      48: invokespecial #127                // Method addParameter2:(ILjavassist/CtClass;Ljava/lang/String;)V
      51: goto          66
      54: astore        5
      56: new           #21                 // class javassist/CannotCompileException
      59: dup
      60: aload         5
      62: invokespecial #24                 // Method javassist/CannotCompileException."<init>":(Ljava/lang/Throwable;)V
      65: athrow
      66: aload_0
      67: getfield      #2                  // Field methodInfo:Ljavassist/bytecode/MethodInfo;
      70: aload_3
      71: invokevirtual #128                // Method javassist/bytecode/MethodInfo.setDescriptor:(Ljava/lang/String;)V
      74: return
    Exception table:
       from    to  target type
          38    51    54   Class javassist/bytecode/BadBytecode

  private void addParameter2(int, javassist.CtClass, java.lang.String) throws javassist.bytecode.BadBytecode;
    Code:
       0: aload_0
       1: getfield      #2                  // Field methodInfo:Ljavassist/bytecode/MethodInfo;
       4: invokevirtual #82                 // Method javassist/bytecode/MethodInfo.getCodeAttribute:()Ljavassist/bytecode/CodeAttribute;
       7: astore        4
       9: aload         4
      11: ifnull        185
      14: iconst_1
      15: istore        5
      17: bipush        76
      19: istore        6
      21: iconst_0
      22: istore        7
      24: aload_2
      25: invokevirtual #131                // Method javassist/CtClass.isPrimitive:()Z
      28: ifeq          54
      31: aload_2
      32: checkcast     #132                // class javassist/CtPrimitiveType
      35: astore        8
      37: aload         8
      39: invokevirtual #133                // Method javassist/CtPrimitiveType.getDataSize:()I
      42: istore        5
      44: aload         8
      46: invokevirtual #134                // Method javassist/CtPrimitiveType.getDescriptor:()C
      49: istore        6
      51: goto          67
      54: aload_0
      55: getfield      #2                  // Field methodInfo:Ljavassist/bytecode/MethodInfo;
      58: invokevirtual #58                 // Method javassist/bytecode/MethodInfo.getConstPool:()Ljavassist/bytecode/ConstPool;
      61: aload_2
      62: invokevirtual #135                // Method javassist/bytecode/ConstPool.addClassInfo:(Ljavassist/CtClass;)I
      65: istore        7
      67: aload         4
      69: iload_1
      70: iload         5
      72: invokevirtual #136                // Method javassist/bytecode/CodeAttribute.insertLocalVar:(II)V
      75: aload         4
      77: ldc           #112                // String LocalVariableTable
      79: invokevirtual #113                // Method javassist/bytecode/CodeAttribute.getAttribute:(Ljava/lang/String;)Ljavassist/bytecode/AttributeInfo;
      82: checkcast     #111                // class javassist/bytecode/LocalVariableAttribute
      85: astore        8
      87: aload         8
      89: ifnull        100
      92: aload         8
      94: iload_1
      95: iload         5
      97: invokevirtual #137                // Method javassist/bytecode/LocalVariableAttribute.shiftIndex:(II)V
     100: aload         4
     102: ldc           #139                // String LocalVariableTypeTable
     104: invokevirtual #113                // Method javassist/bytecode/CodeAttribute.getAttribute:(Ljava/lang/String;)Ljavassist/bytecode/AttributeInfo;
     107: checkcast     #138                // class javassist/bytecode/LocalVariableTypeAttribute
     110: astore        9
     112: aload         9
     114: ifnull        125
     117: aload         9
     119: iload_1
     120: iload         5
     122: invokevirtual #140                // Method javassist/bytecode/LocalVariableTypeAttribute.shiftIndex:(II)V
     125: aload         4
     127: ldc           #142                // String StackMapTable
     129: invokevirtual #113                // Method javassist/bytecode/CodeAttribute.getAttribute:(Ljava/lang/String;)Ljavassist/bytecode/AttributeInfo;
     132: checkcast     #141                // class javassist/bytecode/StackMapTable
     135: astore        10
     137: aload         10
     139: ifnull        155
     142: aload         10
     144: iload_1
     145: iload         6
     147: invokestatic  #143                // Method javassist/bytecode/StackMapTable.typeTagOf:(C)I
     150: iload         7
     152: invokevirtual #144                // Method javassist/bytecode/StackMapTable.insertLocal:(III)V
     155: aload         4
     157: ldc           #146                // String StackMap
     159: invokevirtual #113                // Method javassist/bytecode/CodeAttribute.getAttribute:(Ljava/lang/String;)Ljavassist/bytecode/AttributeInfo;
     162: checkcast     #145                // class javassist/bytecode/StackMap
     165: astore        11
     167: aload         11
     169: ifnull        185
     172: aload         11
     174: iload_1
     175: iload         6
     177: invokestatic  #143                // Method javassist/bytecode/StackMapTable.typeTagOf:(C)I
     180: iload         7
     182: invokevirtual #147                // Method javassist/bytecode/StackMap.insertLocal:(III)V
     185: return

  public void instrument(javassist.CodeConverter) throws javassist.CannotCompileException;
    Code:
       0: aload_0
       1: getfield      #3                  // Field declaringClass:Ljavassist/CtClass;
       4: invokevirtual #29                 // Method javassist/CtClass.checkModify:()V
       7: aload_0
       8: getfield      #2                  // Field methodInfo:Ljavassist/bytecode/MethodInfo;
      11: invokevirtual #58                 // Method javassist/bytecode/MethodInfo.getConstPool:()Ljavassist/bytecode/ConstPool;
      14: astore_2
      15: aload_1
      16: aload_0
      17: invokevirtual #4                  // Method getDeclaringClass:()Ljavassist/CtClass;
      20: aload_0
      21: getfield      #2                  // Field methodInfo:Ljavassist/bytecode/MethodInfo;
      24: aload_2
      25: invokevirtual #148                // Method javassist/CodeConverter.doit:(Ljavassist/CtClass;Ljavassist/bytecode/MethodInfo;Ljavassist/bytecode/ConstPool;)V
      28: return

  public void instrument(javassist.expr.ExprEditor) throws javassist.CannotCompileException;
    Code:
       0: aload_0
       1: getfield      #3                  // Field declaringClass:Ljavassist/CtClass;
       4: invokevirtual #149                // Method javassist/CtClass.isFrozen:()Z
       7: ifeq          17
      10: aload_0
      11: getfield      #3                  // Field declaringClass:Ljavassist/CtClass;
      14: invokevirtual #29                 // Method javassist/CtClass.checkModify:()V
      17: aload_1
      18: aload_0
      19: getfield      #3                  // Field declaringClass:Ljavassist/CtClass;
      22: aload_0
      23: getfield      #2                  // Field methodInfo:Ljavassist/bytecode/MethodInfo;
      26: invokevirtual #150                // Method javassist/expr/ExprEditor.doit:(Ljavassist/CtClass;Ljavassist/bytecode/MethodInfo;)Z
      29: ifeq          39
      32: aload_0
      33: getfield      #3                  // Field declaringClass:Ljavassist/CtClass;
      36: invokevirtual #29                 // Method javassist/CtClass.checkModify:()V
      39: return

  public void insertBefore(java.lang.String) throws javassist.CannotCompileException;
    Code:
       0: aload_0
       1: aload_1
       2: iconst_1
       3: invokespecial #106                // Method insertBefore:(Ljava/lang/String;Z)V
       6: return

  private void insertBefore(java.lang.String, boolean) throws javassist.CannotCompileException;
    Code:
       0: aload_0
       1: getfield      #3                  // Field declaringClass:Ljavassist/CtClass;
       4: astore_3
       5: aload_3
       6: invokevirtual #29                 // Method javassist/CtClass.checkModify:()V
       9: aload_0
      10: getfield      #2                  // Field methodInfo:Ljavassist/bytecode/MethodInfo;
      13: invokevirtual #82                 // Method javassist/bytecode/MethodInfo.getCodeAttribute:()Ljavassist/bytecode/CodeAttribute;
      16: astore        4
      18: aload         4
      20: ifnonnull     33
      23: new           #21                 // class javassist/CannotCompileException
      26: dup
      27: ldc           #109                // String no method body
      29: invokespecial #110                // Method javassist/CannotCompileException."<init>":(Ljava/lang/String;)V
      32: athrow
      33: aload         4
      35: invokevirtual #151                // Method javassist/bytecode/CodeAttribute.iterator:()Ljavassist/bytecode/CodeIterator;
      38: astore        5
      40: new           #71                 // class javassist/compiler/Javac
      43: dup
      44: aload_3
      45: invokespecial #72                 // Method javassist/compiler/Javac."<init>":(Ljavassist/CtClass;)V
      48: astore        6
      50: aload         6
      52: aload_0
      53: invokevirtual #152                // Method getParameterTypes:()[Ljavassist/CtClass;
      56: aload_0
      57: invokevirtual #125                // Method getModifiers:()I
      60: invokestatic  #126                // Method javassist/Modifier.isStatic:(I)Z
      63: invokevirtual #153                // Method javassist/compiler/Javac.recordParams:([Ljavassist/CtClass;Z)I
      66: istore        7
      68: aload         6
      70: aload         4
      72: iload         7
      74: invokevirtual #154                // Method javassist/compiler/Javac.recordParamNames:(Ljavassist/bytecode/CodeAttribute;I)Z
      77: pop
      78: aload         6
      80: aload         4
      82: iconst_0
      83: invokevirtual #155                // Method javassist/compiler/Javac.recordLocalVariables:(Ljavassist/bytecode/CodeAttribute;I)Z
      86: pop
      87: aload         6
      89: aload_0
      90: invokevirtual #156                // Method getReturnType0:()Ljavassist/CtClass;
      93: iconst_0
      94: invokevirtual #157                // Method javassist/compiler/Javac.recordReturnType:(Ljavassist/CtClass;Z)I
      97: pop
      98: aload         6
     100: aload_1
     101: invokevirtual #158                // Method javassist/compiler/Javac.compileStmnt:(Ljava/lang/String;)V
     104: aload         6
     106: invokevirtual #159                // Method javassist/compiler/Javac.getBytecode:()Ljavassist/bytecode/Bytecode;
     109: astore        8
     111: aload         8
     113: invokevirtual #160                // Method javassist/bytecode/Bytecode.getMaxStack:()I
     116: istore        9
     118: aload         8
     120: invokevirtual #161                // Method javassist/bytecode/Bytecode.getMaxLocals:()I
     123: istore        10
     125: iload         9
     127: aload         4
     129: invokevirtual #162                // Method javassist/bytecode/CodeAttribute.getMaxStack:()I
     132: if_icmple     142
     135: aload         4
     137: iload         9
     139: invokevirtual #163                // Method javassist/bytecode/CodeAttribute.setMaxStack:(I)V
     142: iload         10
     144: aload         4
     146: invokevirtual #117                // Method javassist/bytecode/CodeAttribute.getMaxLocals:()I
     149: if_icmple     159
     152: aload         4
     154: iload         10
     156: invokevirtual #123                // Method javassist/bytecode/CodeAttribute.setMaxLocals:(I)V
     159: aload         5
     161: aload         8
     163: invokevirtual #164                // Method javassist/bytecode/Bytecode.get:()[B
     166: invokevirtual #165                // Method javassist/bytecode/CodeIterator.insertEx:([B)I
     169: istore        11
     171: aload         5
     173: aload         8
     175: invokevirtual #166                // Method javassist/bytecode/Bytecode.getExceptionTable:()Ljavassist/bytecode/ExceptionTable;
     178: iload         11
     180: invokevirtual #167                // Method javassist/bytecode/CodeIterator.insert:(Ljavassist/bytecode/ExceptionTable;I)V
     183: iload_2
     184: ifeq          202
     187: aload_0
     188: getfield      #2                  // Field methodInfo:Ljavassist/bytecode/MethodInfo;
     191: aload_3
     192: invokevirtual #39                 // Method javassist/CtClass.getClassPool:()Ljavassist/ClassPool;
     195: aload_3
     196: invokevirtual #5                  // Method javassist/CtClass.getClassFile2:()Ljavassist/bytecode/ClassFile;
     199: invokevirtual #78                 // Method javassist/bytecode/MethodInfo.rebuildStackMapIf6:(Ljavassist/ClassPool;Ljavassist/bytecode/ClassFile;)V
     202: goto          241
     205: astore        7
     207: new           #21                 // class javassist/CannotCompileException
     210: dup
     211: aload         7
     213: invokespecial #22                 // Method javassist/CannotCompileException."<init>":(Ljavassist/NotFoundException;)V
     216: athrow
     217: astore        7
     219: new           #21                 // class javassist/CannotCompileException
     222: dup
     223: aload         7
     225: invokespecial #81                 // Method javassist/CannotCompileException."<init>":(Ljavassist/compiler/CompileError;)V
     228: athrow
     229: astore        7
     231: new           #21                 // class javassist/CannotCompileException
     234: dup
     235: aload         7
     237: invokespecial #24                 // Method javassist/CannotCompileException."<init>":(Ljava/lang/Throwable;)V
     240: athrow
     241: return
    Exception table:
       from    to  target type
          50   202   205   Class javassist/NotFoundException
          50   202   217   Class javassist/compiler/CompileError
          50   202   229   Class javassist/bytecode/BadBytecode

  public void insertAfter(java.lang.String) throws javassist.CannotCompileException;
    Code:
       0: aload_0
       1: aload_1
       2: iconst_0
       3: iconst_0
       4: invokevirtual #168                // Method insertAfter:(Ljava/lang/String;ZZ)V
       7: return

  public void insertAfter(java.lang.String, boolean) throws javassist.CannotCompileException;
    Code:
       0: aload_0
       1: aload_1
       2: iload_2
       3: iconst_0
       4: invokevirtual #168                // Method insertAfter:(Ljava/lang/String;ZZ)V
       7: return

  public void insertAfter(java.lang.String, boolean, boolean) throws javassist.CannotCompileException;
    Code:
       0: aload_0
       1: getfield      #3                  // Field declaringClass:Ljavassist/CtClass;
       4: astore        4
       6: aload         4
       8: invokevirtual #29                 // Method javassist/CtClass.checkModify:()V
      11: aload_0
      12: getfield      #2                  // Field methodInfo:Ljavassist/bytecode/MethodInfo;
      15: invokevirtual #58                 // Method javassist/bytecode/MethodInfo.getConstPool:()Ljavassist/bytecode/ConstPool;
      18: astore        5
      20: aload_0
      21: getfield      #2                  // Field methodInfo:Ljavassist/bytecode/MethodInfo;
      24: invokevirtual #82                 // Method javassist/bytecode/MethodInfo.getCodeAttribute:()Ljavassist/bytecode/CodeAttribute;
      27: astore        6
      29: aload         6
      31: ifnonnull     44
      34: new           #21                 // class javassist/CannotCompileException
      37: dup
      38: ldc           #109                // String no method body
      40: invokespecial #110                // Method javassist/CannotCompileException."<init>":(Ljava/lang/String;)V
      43: athrow
      44: aload         6
      46: invokevirtual #151                // Method javassist/bytecode/CodeAttribute.iterator:()Ljavassist/bytecode/CodeIterator;
      49: astore        7
      51: aload         6
      53: invokevirtual #117                // Method javassist/bytecode/CodeAttribute.getMaxLocals:()I
      56: istore        8
      58: new           #169                // class javassist/bytecode/Bytecode
      61: dup
      62: aload         5
      64: iconst_0
      65: iload         8
      67: iconst_1
      68: iadd
      69: invokespecial #170                // Method javassist/bytecode/Bytecode."<init>":(Ljavassist/bytecode/ConstPool;II)V
      72: astore        9
      74: aload         9
      76: aload         6
      78: invokevirtual #162                // Method javassist/bytecode/CodeAttribute.getMaxStack:()I
      81: iconst_1
      82: iadd
      83: invokevirtual #171                // Method javassist/bytecode/Bytecode.setStackDepth:(I)V
      86: new           #71                 // class javassist/compiler/Javac
      89: dup
      90: aload         9
      92: aload         4
      94: invokespecial #172                // Method javassist/compiler/Javac."<init>":(Ljavassist/bytecode/Bytecode;Ljavassist/CtClass;)V
      97: astore        10
      99: aload         10
     101: aload_0
     102: invokevirtual #152                // Method getParameterTypes:()[Ljavassist/CtClass;
     105: aload_0
     106: invokevirtual #125                // Method getModifiers:()I
     109: invokestatic  #126                // Method javassist/Modifier.isStatic:(I)Z
     112: invokevirtual #153                // Method javassist/compiler/Javac.recordParams:([Ljavassist/CtClass;Z)I
     115: istore        11
     117: aload         10
     119: aload         6
     121: iload         11
     123: invokevirtual #154                // Method javassist/compiler/Javac.recordParamNames:(Ljavassist/bytecode/CodeAttribute;I)Z
     126: pop
     127: aload_0
     128: invokevirtual #156                // Method getReturnType0:()Ljavassist/CtClass;
     131: astore        12
     133: aload         10
     135: aload         12
     137: iconst_1
     138: invokevirtual #157                // Method javassist/compiler/Javac.recordReturnType:(Ljavassist/CtClass;Z)I
     141: istore        13
     143: aload         10
     145: aload         6
     147: iconst_0
     148: invokevirtual #155                // Method javassist/compiler/Javac.recordLocalVariables:(Ljavassist/bytecode/CodeAttribute;I)Z
     151: pop
     152: aload_0
     153: iload_2
     154: aload         9
     156: aload         12
     158: iload         13
     160: aload         10
     162: aload_1
     163: invokespecial #173                // Method insertAfterHandler:(ZLjavassist/bytecode/Bytecode;Ljavassist/CtClass;ILjavassist/compiler/Javac;Ljava/lang/String;)I
     166: istore        14
     168: aload         7
     170: invokevirtual #174                // Method javassist/bytecode/CodeIterator.getCodeLength:()I
     173: istore        15
     175: iload_2
     176: ifeq          198
     179: aload         6
     181: invokevirtual #175                // Method javassist/bytecode/CodeAttribute.getExceptionTable:()Ljavassist/bytecode/ExceptionTable;
     184: aload_0
     185: aload         6
     187: invokevirtual #176                // Method getStartPosOfBody:(Ljavassist/bytecode/CodeAttribute;)I
     190: iload         15
     192: iload         15
     194: iconst_0
     195: invokevirtual #177                // Method javassist/bytecode/ExceptionTable.add:(IIII)V
     198: iconst_0
     199: istore        16
     201: iconst_0
     202: istore        17
     204: iconst_1
     205: istore        18
     207: aload         7
     209: invokevirtual #178                // Method javassist/bytecode/CodeIterator.hasNext:()Z
     212: ifeq          578
     215: aload         7
     217: invokevirtual #179                // Method javassist/bytecode/CodeIterator.next:()I
     220: istore        19
     222: iload         19
     224: iload         15
     226: if_icmplt     232
     229: goto          578
     232: aload         7
     234: iload         19
     236: invokevirtual #180                // Method javassist/bytecode/CodeIterator.byteAt:(I)I
     239: istore        20
     241: iload         20
     243: sipush        176
     246: if_icmpeq     289
     249: iload         20
     251: sipush        172
     254: if_icmpeq     289
     257: iload         20
     259: sipush        174
     262: if_icmpeq     289
     265: iload         20
     267: sipush        173
     270: if_icmpeq     289
     273: iload         20
     275: sipush        175
     278: if_icmpeq     289
     281: iload         20
     283: sipush        177
     286: if_icmpne     575
     289: iload_3
     290: ifeq          482
     293: aload         7
     295: iload         15
     297: invokevirtual #182                // Method javassist/bytecode/CodeIterator.setMark2:(I)V
     300: iload         18
     302: ifeq          323
     305: iconst_0
     306: istore        18
     308: aload         9
     310: astore        21
     312: aload         10
     314: astore        22
     316: iload         13
     318: istore        23
     320: goto          411
     323: new           #169                // class javassist/bytecode/Bytecode
     326: dup
     327: aload         5
     329: iconst_0
     330: iload         8
     332: iconst_1
     333: iadd
     334: invokespecial #170                // Method javassist/bytecode/Bytecode."<init>":(Ljavassist/bytecode/ConstPool;II)V
     337: astore        21
     339: aload         21
     341: aload         6
     343: invokevirtual #162                // Method javassist/bytecode/CodeAttribute.getMaxStack:()I
     346: iconst_1
     347: iadd
     348: invokevirtual #171                // Method javassist/bytecode/Bytecode.setStackDepth:(I)V
     351: new           #71                 // class javassist/compiler/Javac
     354: dup
     355: aload         21
     357: aload         4
     359: invokespecial #172                // Method javassist/compiler/Javac."<init>":(Ljavassist/bytecode/Bytecode;Ljavassist/CtClass;)V
     362: astore        22
     364: aload         22
     366: aload_0
     367: invokevirtual #152                // Method getParameterTypes:()[Ljavassist/CtClass;
     370: aload_0
     371: invokevirtual #125                // Method getModifiers:()I
     374: invokestatic  #126                // Method javassist/Modifier.isStatic:(I)Z
     377: invokevirtual #153                // Method javassist/compiler/Javac.recordParams:([Ljavassist/CtClass;Z)I
     380: istore        24
     382: aload         22
     384: aload         6
     386: iload         24
     388: invokevirtual #154                // Method javassist/compiler/Javac.recordParamNames:(Ljavassist/bytecode/CodeAttribute;I)Z
     391: pop
     392: aload         22
     394: aload         12
     396: iconst_1
     397: invokevirtual #157                // Method javassist/compiler/Javac.recordReturnType:(Ljavassist/CtClass;Z)I
     400: istore        23
     402: aload         22
     404: aload         6
     406: iconst_0
     407: invokevirtual #155                // Method javassist/compiler/Javac.recordLocalVariables:(Ljavassist/bytecode/CodeAttribute;I)Z
     410: pop
     411: aload_0
     412: aload         21
     414: aload         22
     416: aload_1
     417: aload         5
     419: aload         12
     421: iload         23
     423: invokespecial #183                // Method insertAfterAdvice:(Ljavassist/bytecode/Bytecode;Ljavassist/compiler/Javac;Ljava/lang/String;Ljavassist/bytecode/ConstPool;Ljavassist/CtClass;I)I
     426: istore        24
     428: aload         7
     430: aload         21
     432: invokevirtual #164                // Method javassist/bytecode/Bytecode.get:()[B
     435: invokevirtual #184                // Method javassist/bytecode/CodeIterator.append:([B)I
     438: istore        25
     440: aload         7
     442: aload         21
     444: invokevirtual #166                // Method javassist/bytecode/Bytecode.getExceptionTable:()Ljavassist/bytecode/ExceptionTable;
     447: iload         25
     449: invokevirtual #185                // Method javassist/bytecode/CodeIterator.append:(Ljavassist/bytecode/ExceptionTable;I)V
     452: aload         7
     454: invokevirtual #174                // Method javassist/bytecode/CodeIterator.getCodeLength:()I
     457: iload         24
     459: isub
     460: istore        26
     462: aload_0
     463: aload         7
     465: iload         26
     467: iload         19
     469: invokespecial #186                // Method insertGoto:(Ljavassist/bytecode/CodeIterator;II)V
     472: aload         7
     474: invokevirtual #187                // Method javassist/bytecode/CodeIterator.getMark2:()I
     477: istore        15
     479: goto          575
     482: iload         18
     484: ifeq          548
     487: aload_0
     488: aload         9
     490: aload         10
     492: aload_1
     493: aload         5
     495: aload         12
     497: iload         13
     499: invokespecial #183                // Method insertAfterAdvice:(Ljavassist/bytecode/Bytecode;Ljavassist/compiler/Javac;Ljava/lang/String;Ljavassist/bytecode/ConstPool;Ljavassist/CtClass;I)I
     502: istore        16
     504: aload         7
     506: aload         9
     508: invokevirtual #164                // Method javassist/bytecode/Bytecode.get:()[B
     511: invokevirtual #184                // Method javassist/bytecode/CodeIterator.append:([B)I
     514: istore        15
     516: aload         7
     518: aload         9
     520: invokevirtual #166                // Method javassist/bytecode/Bytecode.getExceptionTable:()Ljavassist/bytecode/ExceptionTable;
     523: iload         15
     525: invokevirtual #185                // Method javassist/bytecode/CodeIterator.append:(Ljavassist/bytecode/ExceptionTable;I)V
     528: aload         7
     530: invokevirtual #174                // Method javassist/bytecode/CodeIterator.getCodeLength:()I
     533: iload         16
     535: isub
     536: istore        17
     538: iload         17
     540: iload         15
     542: isub
     543: istore        14
     545: iconst_0
     546: istore        18
     548: aload_0
     549: aload         7
     551: iload         17
     553: iload         19
     555: invokespecial #186                // Method insertGoto:(Ljavassist/bytecode/CodeIterator;II)V
     558: aload         7
     560: invokevirtual #174                // Method javassist/bytecode/CodeIterator.getCodeLength:()I
     563: iload         16
     565: isub
     566: istore        17
     568: iload         17
     570: iload         14
     572: isub
     573: istore        15
     575: goto          207
     578: iload         18
     580: ifeq          607
     583: aload         7
     585: aload         9
     587: invokevirtual #164                // Method javassist/bytecode/Bytecode.get:()[B
     590: invokevirtual #184                // Method javassist/bytecode/CodeIterator.append:([B)I
     593: istore        15
     595: aload         7
     597: aload         9
     599: invokevirtual #166                // Method javassist/bytecode/Bytecode.getExceptionTable:()Ljavassist/bytecode/ExceptionTable;
     602: iload         15
     604: invokevirtual #185                // Method javassist/bytecode/CodeIterator.append:(Ljavassist/bytecode/ExceptionTable;I)V
     607: aload         6
     609: aload         9
     611: invokevirtual #160                // Method javassist/bytecode/Bytecode.getMaxStack:()I
     614: invokevirtual #163                // Method javassist/bytecode/CodeAttribute.setMaxStack:(I)V
     617: aload         6
     619: aload         9
     621: invokevirtual #161                // Method javassist/bytecode/Bytecode.getMaxLocals:()I
     624: invokevirtual #123                // Method javassist/bytecode/CodeAttribute.setMaxLocals:(I)V
     627: aload_0
     628: getfield      #2                  // Field methodInfo:Ljavassist/bytecode/MethodInfo;
     631: aload         4
     633: invokevirtual #39                 // Method javassist/CtClass.getClassPool:()Ljavassist/ClassPool;
     636: aload         4
     638: invokevirtual #5                  // Method javassist/CtClass.getClassFile2:()Ljavassist/bytecode/ClassFile;
     641: invokevirtual #78                 // Method javassist/bytecode/MethodInfo.rebuildStackMapIf6:(Ljavassist/ClassPool;Ljavassist/bytecode/ClassFile;)V
     644: goto          683
     647: astore        11
     649: new           #21                 // class javassist/CannotCompileException
     652: dup
     653: aload         11
     655: invokespecial #22                 // Method javassist/CannotCompileException."<init>":(Ljavassist/NotFoundException;)V
     658: athrow
     659: astore        11
     661: new           #21                 // class javassist/CannotCompileException
     664: dup
     665: aload         11
     667: invokespecial #81                 // Method javassist/CannotCompileException."<init>":(Ljavassist/compiler/CompileError;)V
     670: athrow
     671: astore        11
     673: new           #21                 // class javassist/CannotCompileException
     676: dup
     677: aload         11
     679: invokespecial #24                 // Method javassist/CannotCompileException."<init>":(Ljava/lang/Throwable;)V
     682: athrow
     683: return
    Exception table:
       from    to  target type
          99   644   647   Class javassist/NotFoundException
          99   644   659   Class javassist/compiler/CompileError
          99   644   671   Class javassist/bytecode/BadBytecode

  private int insertAfterAdvice(javassist.bytecode.Bytecode, javassist.compiler.Javac, java.lang.String, javassist.bytecode.ConstPool, javassist.CtClass, int) throws javassist.compiler.CompileError;
    Code:
       0: aload_1
       1: invokevirtual #188                // Method javassist/bytecode/Bytecode.currentPc:()I
       4: istore        7
       6: aload         5
       8: getstatic     #189                // Field javassist/CtClass.voidType:Ljavassist/CtClass;
      11: if_acmpne     53
      14: aload_1
      15: iconst_1
      16: invokevirtual #190                // Method javassist/bytecode/Bytecode.addOpcode:(I)V
      19: aload_1
      20: iload         6
      22: invokevirtual #191                // Method javassist/bytecode/Bytecode.addAstore:(I)V
      25: aload_2
      26: aload_3
      27: invokevirtual #158                // Method javassist/compiler/Javac.compileStmnt:(Ljava/lang/String;)V
      30: aload_1
      31: sipush        177
      34: invokevirtual #190                // Method javassist/bytecode/Bytecode.addOpcode:(I)V
      37: aload_1
      38: invokevirtual #161                // Method javassist/bytecode/Bytecode.getMaxLocals:()I
      41: iconst_1
      42: if_icmpge     106
      45: aload_1
      46: iconst_1
      47: invokevirtual #192                // Method javassist/bytecode/Bytecode.setMaxLocals:(I)V
      50: goto          106
      53: aload_1
      54: iload         6
      56: aload         5
      58: invokevirtual #193                // Method javassist/bytecode/Bytecode.addStore:(ILjavassist/CtClass;)I
      61: pop
      62: aload_2
      63: aload_3
      64: invokevirtual #158                // Method javassist/compiler/Javac.compileStmnt:(Ljava/lang/String;)V
      67: aload_1
      68: iload         6
      70: aload         5
      72: invokevirtual #194                // Method javassist/bytecode/Bytecode.addLoad:(ILjavassist/CtClass;)I
      75: pop
      76: aload         5
      78: invokevirtual #131                // Method javassist/CtClass.isPrimitive:()Z
      81: ifeq          99
      84: aload_1
      85: aload         5
      87: checkcast     #132                // class javassist/CtPrimitiveType
      90: invokevirtual #195                // Method javassist/CtPrimitiveType.getReturnOp:()I
      93: invokevirtual #190                // Method javassist/bytecode/Bytecode.addOpcode:(I)V
      96: goto          106
      99: aload_1
     100: sipush        176
     103: invokevirtual #190                // Method javassist/bytecode/Bytecode.addOpcode:(I)V
     106: aload_1
     107: invokevirtual #188                // Method javassist/bytecode/Bytecode.currentPc:()I
     110: iload         7
     112: isub
     113: ireturn

  private void insertGoto(javassist.bytecode.CodeIterator, int, int) throws javassist.bytecode.BadBytecode;
    Code:
       0: aload_1
       1: iload_2
       2: invokevirtual #196                // Method javassist/bytecode/CodeIterator.setMark:(I)V
       5: aload_1
       6: iconst_0
       7: iload_3
       8: invokevirtual #197                // Method javassist/bytecode/CodeIterator.writeByte:(II)V
      11: iload_2
      12: iconst_2
      13: iadd
      14: iload_3
      15: isub
      16: sipush        32767
      19: if_icmple     26
      22: iconst_1
      23: goto          27
      26: iconst_0
      27: istore        4
      29: iload         4
      31: ifeq          38
      34: iconst_4
      35: goto          39
      38: iconst_2
      39: istore        5
      41: aload_1
      42: iload_3
      43: iload         5
      45: iconst_0
      46: invokevirtual #199                // Method javassist/bytecode/CodeIterator.insertGapAt:(IIZ)Ljavassist/bytecode/CodeIterator$Gap;
      49: astore        6
      51: aload         6
      53: getfield      #200                // Field javassist/bytecode/CodeIterator$Gap.position:I
      56: aload         6
      58: getfield      #201                // Field javassist/bytecode/CodeIterator$Gap.length:I
      61: iadd
      62: iload         5
      64: isub
      65: istore_3
      66: aload_1
      67: invokevirtual #202                // Method javassist/bytecode/CodeIterator.getMark:()I
      70: iload_3
      71: isub
      72: istore        7
      74: iload         4
      76: ifeq          99
      79: aload_1
      80: sipush        200
      83: iload_3
      84: invokevirtual #197                // Method javassist/bytecode/CodeIterator.writeByte:(II)V
      87: aload_1
      88: iload         7
      90: iload_3
      91: iconst_1
      92: iadd
      93: invokevirtual #203                // Method javassist/bytecode/CodeIterator.write32bit:(II)V
      96: goto          190
      99: iload         7
     101: sipush        32767
     104: if_icmpgt     127
     107: aload_1
     108: sipush        167
     111: iload_3
     112: invokevirtual #197                // Method javassist/bytecode/CodeIterator.writeByte:(II)V
     115: aload_1
     116: iload         7
     118: iload_3
     119: iconst_1
     120: iadd
     121: invokevirtual #204                // Method javassist/bytecode/CodeIterator.write16bit:(II)V
     124: goto          190
     127: aload         6
     129: getfield      #201                // Field javassist/bytecode/CodeIterator$Gap.length:I
     132: iconst_4
     133: if_icmpge     169
     136: aload_1
     137: aload         6
     139: getfield      #200                // Field javassist/bytecode/CodeIterator$Gap.position:I
     142: iconst_2
     143: iconst_0
     144: invokevirtual #199                // Method javassist/bytecode/CodeIterator.insertGapAt:(IIZ)Ljavassist/bytecode/CodeIterator$Gap;
     147: astore        8
     149: aload         8
     151: getfield      #200                // Field javassist/bytecode/CodeIterator$Gap.position:I
     154: aload         8
     156: getfield      #201                // Field javassist/bytecode/CodeIterator$Gap.length:I
     159: iadd
     160: aload         6
     162: getfield      #201                // Field javassist/bytecode/CodeIterator$Gap.length:I
     165: iadd
     166: iconst_4
     167: isub
     168: istore_3
     169: aload_1
     170: sipush        200
     173: iload_3
     174: invokevirtual #197                // Method javassist/bytecode/CodeIterator.writeByte:(II)V
     177: aload_1
     178: aload_1
     179: invokevirtual #202                // Method javassist/bytecode/CodeIterator.getMark:()I
     182: iload_3
     183: isub
     184: iload_3
     185: iconst_1
     186: iadd
     187: invokevirtual #203                // Method javassist/bytecode/CodeIterator.write32bit:(II)V
     190: return

  private int insertAfterHandler(boolean, javassist.bytecode.Bytecode, javassist.CtClass, int, javassist.compiler.Javac, java.lang.String) throws javassist.compiler.CompileError;
    Code:
       0: iload_1
       1: ifne          6
       4: iconst_0
       5: ireturn
       6: aload_2
       7: invokevirtual #161                // Method javassist/bytecode/Bytecode.getMaxLocals:()I
      10: istore        7
      12: aload_2
      13: iconst_1
      14: invokevirtual #205                // Method javassist/bytecode/Bytecode.incMaxLocals:(I)V
      17: aload_2
      18: invokevirtual #188                // Method javassist/bytecode/Bytecode.currentPc:()I
      21: istore        8
      23: aload_2
      24: iload         7
      26: invokevirtual #191                // Method javassist/bytecode/Bytecode.addAstore:(I)V
      29: aload_3
      30: invokevirtual #131                // Method javassist/CtClass.isPrimitive:()Z
      33: ifeq          143
      36: aload_3
      37: checkcast     #132                // class javassist/CtPrimitiveType
      40: invokevirtual #134                // Method javassist/CtPrimitiveType.getDescriptor:()C
      43: istore        9
      45: iload         9
      47: bipush        68
      49: if_icmpne     66
      52: aload_2
      53: dconst_0
      54: invokevirtual #206                // Method javassist/bytecode/Bytecode.addDconst:(D)V
      57: aload_2
      58: iload         4
      60: invokevirtual #207                // Method javassist/bytecode/Bytecode.addDstore:(I)V
      63: goto          140
      66: iload         9
      68: bipush        70
      70: if_icmpne     87
      73: aload_2
      74: fconst_0
      75: invokevirtual #208                // Method javassist/bytecode/Bytecode.addFconst:(F)V
      78: aload_2
      79: iload         4
      81: invokevirtual #209                // Method javassist/bytecode/Bytecode.addFstore:(I)V
      84: goto          140
      87: iload         9
      89: bipush        74
      91: if_icmpne     108
      94: aload_2
      95: lconst_0
      96: invokevirtual #210                // Method javassist/bytecode/Bytecode.addLconst:(J)V
      99: aload_2
     100: iload         4
     102: invokevirtual #211                // Method javassist/bytecode/Bytecode.addLstore:(I)V
     105: goto          140
     108: iload         9
     110: bipush        86
     112: if_icmpne     129
     115: aload_2
     116: iconst_1
     117: invokevirtual #190                // Method javassist/bytecode/Bytecode.addOpcode:(I)V
     120: aload_2
     121: iload         4
     123: invokevirtual #191                // Method javassist/bytecode/Bytecode.addAstore:(I)V
     126: goto          140
     129: aload_2
     130: iconst_0
     131: invokevirtual #212                // Method javassist/bytecode/Bytecode.addIconst:(I)V
     134: aload_2
     135: iload         4
     137: invokevirtual #213                // Method javassist/bytecode/Bytecode.addIstore:(I)V
     140: goto          154
     143: aload_2
     144: iconst_1
     145: invokevirtual #190                // Method javassist/bytecode/Bytecode.addOpcode:(I)V
     148: aload_2
     149: iload         4
     151: invokevirtual #191                // Method javassist/bytecode/Bytecode.addAstore:(I)V
     154: aload         5
     156: aload         6
     158: invokevirtual #158                // Method javassist/compiler/Javac.compileStmnt:(Ljava/lang/String;)V
     161: aload_2
     162: iload         7
     164: invokevirtual #214                // Method javassist/bytecode/Bytecode.addAload:(I)V
     167: aload_2
     168: sipush        191
     171: invokevirtual #190                // Method javassist/bytecode/Bytecode.addOpcode:(I)V
     174: aload_2
     175: invokevirtual #188                // Method javassist/bytecode/Bytecode.currentPc:()I
     178: iload         8
     180: isub
     181: ireturn

  public void addCatch(java.lang.String, javassist.CtClass) throws javassist.CannotCompileException;
    Code:
       0: aload_0
       1: aload_1
       2: aload_2
       3: ldc           #215                // String $e
       5: invokevirtual #216                // Method addCatch:(Ljava/lang/String;Ljavassist/CtClass;Ljava/lang/String;)V
       8: return

  public void addCatch(java.lang.String, javassist.CtClass, java.lang.String) throws javassist.CannotCompileException;
    Code:
       0: aload_0
       1: getfield      #3                  // Field declaringClass:Ljavassist/CtClass;
       4: astore        4
       6: aload         4
       8: invokevirtual #29                 // Method javassist/CtClass.checkModify:()V
      11: aload_0
      12: getfield      #2                  // Field methodInfo:Ljavassist/bytecode/MethodInfo;
      15: invokevirtual #58                 // Method javassist/bytecode/MethodInfo.getConstPool:()Ljavassist/bytecode/ConstPool;
      18: astore        5
      20: aload_0
      21: getfield      #2                  // Field methodInfo:Ljavassist/bytecode/MethodInfo;
      24: invokevirtual #82                 // Method javassist/bytecode/MethodInfo.getCodeAttribute:()Ljavassist/bytecode/CodeAttribute;
      27: astore        6
      29: aload         6
      31: invokevirtual #151                // Method javassist/bytecode/CodeAttribute.iterator:()Ljavassist/bytecode/CodeIterator;
      34: astore        7
      36: new           #169                // class javassist/bytecode/Bytecode
      39: dup
      40: aload         5
      42: aload         6
      44: invokevirtual #162                // Method javassist/bytecode/CodeAttribute.getMaxStack:()I
      47: aload         6
      49: invokevirtual #117                // Method javassist/bytecode/CodeAttribute.getMaxLocals:()I
      52: invokespecial #170                // Method javassist/bytecode/Bytecode."<init>":(Ljavassist/bytecode/ConstPool;II)V
      55: astore        8
      57: aload         8
      59: iconst_1
      60: invokevirtual #171                // Method javassist/bytecode/Bytecode.setStackDepth:(I)V
      63: new           #71                 // class javassist/compiler/Javac
      66: dup
      67: aload         8
      69: aload         4
      71: invokespecial #172                // Method javassist/compiler/Javac."<init>":(Ljavassist/bytecode/Bytecode;Ljavassist/CtClass;)V
      74: astore        9
      76: aload         9
      78: aload_0
      79: invokevirtual #152                // Method getParameterTypes:()[Ljavassist/CtClass;
      82: aload_0
      83: invokevirtual #125                // Method getModifiers:()I
      86: invokestatic  #126                // Method javassist/Modifier.isStatic:(I)Z
      89: invokevirtual #153                // Method javassist/compiler/Javac.recordParams:([Ljavassist/CtClass;Z)I
      92: pop
      93: aload         9
      95: aload_2
      96: aload_3
      97: invokevirtual #217                // Method javassist/compiler/Javac.recordVariable:(Ljavassist/CtClass;Ljava/lang/String;)I
     100: istore        10
     102: aload         8
     104: iload         10
     106: invokevirtual #191                // Method javassist/bytecode/Bytecode.addAstore:(I)V
     109: aload         9
     111: aload_1
     112: invokevirtual #158                // Method javassist/compiler/Javac.compileStmnt:(Ljava/lang/String;)V
     115: aload         8
     117: invokevirtual #160                // Method javassist/bytecode/Bytecode.getMaxStack:()I
     120: istore        11
     122: aload         8
     124: invokevirtual #161                // Method javassist/bytecode/Bytecode.getMaxLocals:()I
     127: istore        12
     129: iload         11
     131: aload         6
     133: invokevirtual #162                // Method javassist/bytecode/CodeAttribute.getMaxStack:()I
     136: if_icmple     146
     139: aload         6
     141: iload         11
     143: invokevirtual #163                // Method javassist/bytecode/CodeAttribute.setMaxStack:(I)V
     146: iload         12
     148: aload         6
     150: invokevirtual #117                // Method javassist/bytecode/CodeAttribute.getMaxLocals:()I
     153: if_icmple     163
     156: aload         6
     158: iload         12
     160: invokevirtual #123                // Method javassist/bytecode/CodeAttribute.setMaxLocals:(I)V
     163: aload         7
     165: invokevirtual #174                // Method javassist/bytecode/CodeIterator.getCodeLength:()I
     168: istore        13
     170: aload         7
     172: aload         8
     174: invokevirtual #164                // Method javassist/bytecode/Bytecode.get:()[B
     177: invokevirtual #184                // Method javassist/bytecode/CodeIterator.append:([B)I
     180: istore        14
     182: aload         6
     184: invokevirtual #175                // Method javassist/bytecode/CodeAttribute.getExceptionTable:()Ljavassist/bytecode/ExceptionTable;
     187: aload_0
     188: aload         6
     190: invokevirtual #176                // Method getStartPosOfBody:(Ljavassist/bytecode/CodeAttribute;)I
     193: iload         13
     195: iload         13
     197: aload         5
     199: aload_2
     200: invokevirtual #135                // Method javassist/bytecode/ConstPool.addClassInfo:(Ljavassist/CtClass;)I
     203: invokevirtual #177                // Method javassist/bytecode/ExceptionTable.add:(IIII)V
     206: aload         7
     208: aload         8
     210: invokevirtual #166                // Method javassist/bytecode/Bytecode.getExceptionTable:()Ljavassist/bytecode/ExceptionTable;
     213: iload         14
     215: invokevirtual #185                // Method javassist/bytecode/CodeIterator.append:(Ljavassist/bytecode/ExceptionTable;I)V
     218: aload_0
     219: getfield      #2                  // Field methodInfo:Ljavassist/bytecode/MethodInfo;
     222: aload         4
     224: invokevirtual #39                 // Method javassist/CtClass.getClassPool:()Ljavassist/ClassPool;
     227: aload         4
     229: invokevirtual #5                  // Method javassist/CtClass.getClassFile2:()Ljavassist/bytecode/ClassFile;
     232: invokevirtual #78                 // Method javassist/bytecode/MethodInfo.rebuildStackMapIf6:(Ljavassist/ClassPool;Ljavassist/bytecode/ClassFile;)V
     235: goto          274
     238: astore        10
     240: new           #21                 // class javassist/CannotCompileException
     243: dup
     244: aload         10
     246: invokespecial #22                 // Method javassist/CannotCompileException."<init>":(Ljavassist/NotFoundException;)V
     249: athrow
     250: astore        10
     252: new           #21                 // class javassist/CannotCompileException
     255: dup
     256: aload         10
     258: invokespecial #81                 // Method javassist/CannotCompileException."<init>":(Ljavassist/compiler/CompileError;)V
     261: athrow
     262: astore        10
     264: new           #21                 // class javassist/CannotCompileException
     267: dup
     268: aload         10
     270: invokespecial #24                 // Method javassist/CannotCompileException."<init>":(Ljava/lang/Throwable;)V
     273: athrow
     274: return
    Exception table:
       from    to  target type
          76   235   238   Class javassist/NotFoundException
          76   235   250   Class javassist/compiler/CompileError
          76   235   262   Class javassist/bytecode/BadBytecode

  int getStartPosOfBody(javassist.bytecode.CodeAttribute) throws javassist.CannotCompileException;
    Code:
       0: iconst_0
       1: ireturn

  public int insertAt(int, java.lang.String) throws javassist.CannotCompileException;
    Code:
       0: aload_0
       1: iload_1
       2: iconst_1
       3: aload_2
       4: invokevirtual #218                // Method insertAt:(IZLjava/lang/String;)I
       7: ireturn

  public int insertAt(int, boolean, java.lang.String) throws javassist.CannotCompileException;
    Code:
       0: aload_0
       1: getfield      #2                  // Field methodInfo:Ljavassist/bytecode/MethodInfo;
       4: invokevirtual #82                 // Method javassist/bytecode/MethodInfo.getCodeAttribute:()Ljavassist/bytecode/CodeAttribute;
       7: astore        4
       9: aload         4
      11: ifnonnull     24
      14: new           #21                 // class javassist/CannotCompileException
      17: dup
      18: ldc           #109                // String no method body
      20: invokespecial #110                // Method javassist/CannotCompileException."<init>":(Ljava/lang/String;)V
      23: athrow
      24: aload         4
      26: ldc           #220                // String LineNumberTable
      28: invokevirtual #113                // Method javassist/bytecode/CodeAttribute.getAttribute:(Ljava/lang/String;)Ljavassist/bytecode/AttributeInfo;
      31: checkcast     #219                // class javassist/bytecode/LineNumberAttribute
      34: astore        5
      36: aload         5
      38: ifnonnull     51
      41: new           #21                 // class javassist/CannotCompileException
      44: dup
      45: ldc           #221                // String no line number info
      47: invokespecial #110                // Method javassist/CannotCompileException."<init>":(Ljava/lang/String;)V
      50: athrow
      51: aload         5
      53: iload_1
      54: invokevirtual #222                // Method javassist/bytecode/LineNumberAttribute.toNearPc:(I)Ljavassist/bytecode/LineNumberAttribute$Pc;
      57: astore        6
      59: aload         6
      61: getfield      #223                // Field javassist/bytecode/LineNumberAttribute$Pc.line:I
      64: istore_1
      65: aload         6
      67: getfield      #224                // Field javassist/bytecode/LineNumberAttribute$Pc.index:I
      70: istore        7
      72: iload_2
      73: ifne          78
      76: iload_1
      77: ireturn
      78: aload_0
      79: getfield      #3                  // Field declaringClass:Ljavassist/CtClass;
      82: astore        8
      84: aload         8
      86: invokevirtual #29                 // Method javassist/CtClass.checkModify:()V
      89: aload         4
      91: invokevirtual #151                // Method javassist/bytecode/CodeAttribute.iterator:()Ljavassist/bytecode/CodeIterator;
      94: astore        9
      96: new           #71                 // class javassist/compiler/Javac
      99: dup
     100: aload         8
     102: invokespecial #72                 // Method javassist/compiler/Javac."<init>":(Ljavassist/CtClass;)V
     105: astore        10
     107: aload         10
     109: aload         4
     111: iload         7
     113: invokevirtual #155                // Method javassist/compiler/Javac.recordLocalVariables:(Ljavassist/bytecode/CodeAttribute;I)Z
     116: pop
     117: aload         10
     119: aload_0
     120: invokevirtual #152                // Method getParameterTypes:()[Ljavassist/CtClass;
     123: aload_0
     124: invokevirtual #125                // Method getModifiers:()I
     127: invokestatic  #126                // Method javassist/Modifier.isStatic:(I)Z
     130: invokevirtual #153                // Method javassist/compiler/Javac.recordParams:([Ljavassist/CtClass;Z)I
     133: pop
     134: aload         10
     136: aload         4
     138: invokevirtual #117                // Method javassist/bytecode/CodeAttribute.getMaxLocals:()I
     141: invokevirtual #225                // Method javassist/compiler/Javac.setMaxLocals:(I)V
     144: aload         10
     146: aload_3
     147: invokevirtual #158                // Method javassist/compiler/Javac.compileStmnt:(Ljava/lang/String;)V
     150: aload         10
     152: invokevirtual #159                // Method javassist/compiler/Javac.getBytecode:()Ljavassist/bytecode/Bytecode;
     155: astore        11
     157: aload         11
     159: invokevirtual #161                // Method javassist/bytecode/Bytecode.getMaxLocals:()I
     162: istore        12
     164: aload         11
     166: invokevirtual #160                // Method javassist/bytecode/Bytecode.getMaxStack:()I
     169: istore        13
     171: aload         4
     173: iload         12
     175: invokevirtual #123                // Method javassist/bytecode/CodeAttribute.setMaxLocals:(I)V
     178: iload         13
     180: aload         4
     182: invokevirtual #162                // Method javassist/bytecode/CodeAttribute.getMaxStack:()I
     185: if_icmple     195
     188: aload         4
     190: iload         13
     192: invokevirtual #163                // Method javassist/bytecode/CodeAttribute.setMaxStack:(I)V
     195: aload         9
     197: iload         7
     199: aload         11
     201: invokevirtual #164                // Method javassist/bytecode/Bytecode.get:()[B
     204: invokevirtual #226                // Method javassist/bytecode/CodeIterator.insertAt:(I[B)I
     207: istore        7
     209: aload         9
     211: aload         11
     213: invokevirtual #166                // Method javassist/bytecode/Bytecode.getExceptionTable:()Ljavassist/bytecode/ExceptionTable;
     216: iload         7
     218: invokevirtual #167                // Method javassist/bytecode/CodeIterator.insert:(Ljavassist/bytecode/ExceptionTable;I)V
     221: aload_0
     222: getfield      #2                  // Field methodInfo:Ljavassist/bytecode/MethodInfo;
     225: aload         8
     227: invokevirtual #39                 // Method javassist/CtClass.getClassPool:()Ljavassist/ClassPool;
     230: aload         8
     232: invokevirtual #5                  // Method javassist/CtClass.getClassFile2:()Ljavassist/bytecode/ClassFile;
     235: invokevirtual #78                 // Method javassist/bytecode/MethodInfo.rebuildStackMapIf6:(Ljavassist/ClassPool;Ljavassist/bytecode/ClassFile;)V
     238: iload_1
     239: ireturn
     240: astore        11
     242: new           #21                 // class javassist/CannotCompileException
     245: dup
     246: aload         11
     248: invokespecial #22                 // Method javassist/CannotCompileException."<init>":(Ljavassist/NotFoundException;)V
     251: athrow
     252: astore        11
     254: new           #21                 // class javassist/CannotCompileException
     257: dup
     258: aload         11
     260: invokespecial #81                 // Method javassist/CannotCompileException."<init>":(Ljavassist/compiler/CompileError;)V
     263: athrow
     264: astore        11
     266: new           #21                 // class javassist/CannotCompileException
     269: dup
     270: aload         11
     272: invokespecial #24                 // Method javassist/CannotCompileException."<init>":(Ljava/lang/Throwable;)V
     275: athrow
    Exception table:
       from    to  target type
         107   239   240   Class javassist/NotFoundException
         107   239   252   Class javassist/compiler/CompileError
         107   239   264   Class javassist/bytecode/BadBytecode
}
