Compiled from "ClassPoolTail.java"
final class javassist.JarDirClassPath implements javassist.ClassPath {
  javassist.JarClassPath[] jars;

  javassist.JarDirClassPath(java.lang.String) throws javassist.NotFoundException;
    Code:
       0: aload_0
       1: invokespecial #1                  // Method java/lang/Object."<init>":()V
       4: new           #2                  // class java/io/File
       7: dup
       8: aload_1
       9: invokespecial #3                  // Method java/io/File."<init>":(Ljava/lang/String;)V
      12: new           #4                  // class javassist/JarDirClassPath$1
      15: dup
      16: aload_0
      17: invokespecial #5                  // Method javassist/JarDirClassPath$1."<init>":(Ljavassist/JarDirClassPath;)V
      20: invokevirtual #6                  // Method java/io/File.listFiles:(Ljava/io/FilenameFilter;)[Ljava/io/File;
      23: astore_2
      24: aload_2
      25: ifnull        70
      28: aload_0
      29: aload_2
      30: arraylength
      31: anewarray     #7                  // class javassist/JarClassPath
      34: putfield      #8                  // Field jars:[Ljavassist/JarClassPath;
      37: iconst_0
      38: istore_3
      39: iload_3
      40: aload_2
      41: arraylength
      42: if_icmpge     70
      45: aload_0
      46: getfield      #8                  // Field jars:[Ljavassist/JarClassPath;
      49: iload_3
      50: new           #7                  // class javassist/JarClassPath
      53: dup
      54: aload_2
      55: iload_3
      56: aaload
      57: invokevirtual #9                  // Method java/io/File.getPath:()Ljava/lang/String;
      60: invokespecial #10                 // Method javassist/JarClassPath."<init>":(Ljava/lang/String;)V
      63: aastore
      64: iinc          3, 1
      67: goto          39
      70: return

  public java.io.InputStream openClassfile(java.lang.String) throws javassist.NotFoundException;
    Code:
       0: aload_0
       1: getfield      #8                  // Field jars:[Ljavassist/JarClassPath;
       4: ifnull        41
       7: iconst_0
       8: istore_2
       9: iload_2
      10: aload_0
      11: getfield      #8                  // Field jars:[Ljavassist/JarClassPath;
      14: arraylength
      15: if_icmpge     41
      18: aload_0
      19: getfield      #8                  // Field jars:[Ljavassist/JarClassPath;
      22: iload_2
      23: aaload
      24: aload_1
      25: invokevirtual #11                 // Method javassist/JarClassPath.openClassfile:(Ljava/lang/String;)Ljava/io/InputStream;
      28: astore_3
      29: aload_3
      30: ifnull        35
      33: aload_3
      34: areturn
      35: iinc          2, 1
      38: goto          9
      41: aconst_null
      42: areturn

  public java.net.URL find(java.lang.String);
    Code:
       0: aload_0
       1: getfield      #8                  // Field jars:[Ljavassist/JarClassPath;
       4: ifnull        41
       7: iconst_0
       8: istore_2
       9: iload_2
      10: aload_0
      11: getfield      #8                  // Field jars:[Ljavassist/JarClassPath;
      14: arraylength
      15: if_icmpge     41
      18: aload_0
      19: getfield      #8                  // Field jars:[Ljavassist/JarClassPath;
      22: iload_2
      23: aaload
      24: aload_1
      25: invokevirtual #12                 // Method javassist/JarClassPath.find:(Ljava/lang/String;)Ljava/net/URL;
      28: astore_3
      29: aload_3
      30: ifnull        35
      33: aload_3
      34: areturn
      35: iinc          2, 1
      38: goto          9
      41: aconst_null
      42: areturn
}
