Compiled from "SimpleResultSet.java"
public class org.h2.tools.SimpleResultSet$SimpleArray implements java.sql.Array {
  private final java.lang.Object[] value;

  org.h2.tools.SimpleResultSet$SimpleArray(java.lang.Object[]);
    Code:
       0: aload_0
       1: invokespecial #1                  // Method java/lang/Object."<init>":()V
       4: aload_0
       5: aload_1
       6: putfield      #2                  // Field value:[Ljava/lang/Object;
       9: return

  public java.lang.Object getArray();
    Code:
       0: aload_0
       1: getfield      #2                  // Field value:[Ljava/lang/Object;
       4: areturn

  public java.lang.Object getArray(java.util.Map<java.lang.String, java.lang.Class<?>>) throws java.sql.SQLException;
    Code:
       0: invokestatic  #3                  // Method org/h2/tools/SimpleResultSet.getUnsupportedException:()Ljava/sql/SQLException;
       3: athrow

  public java.lang.Object getArray(long, int) throws java.sql.SQLException;
    Code:
       0: invokestatic  #3                  // Method org/h2/tools/SimpleResultSet.getUnsupportedException:()Ljava/sql/SQLException;
       3: athrow

  public java.lang.Object getArray(long, int, java.util.Map<java.lang.String, java.lang.Class<?>>) throws java.sql.SQLException;
    Code:
       0: invokestatic  #3                  // Method org/h2/tools/SimpleResultSet.getUnsupportedException:()Ljava/sql/SQLException;
       3: athrow

  public int getBaseType();
    Code:
       0: iconst_0
       1: ireturn

  public java.lang.String getBaseTypeName();
    Code:
       0: ldc           #4                  // String NULL
       2: areturn

  public java.sql.ResultSet getResultSet() throws java.sql.SQLException;
    Code:
       0: invokestatic  #3                  // Method org/h2/tools/SimpleResultSet.getUnsupportedException:()Ljava/sql/SQLException;
       3: athrow

  public java.sql.ResultSet getResultSet(java.util.Map<java.lang.String, java.lang.Class<?>>) throws java.sql.SQLException;
    Code:
       0: invokestatic  #3                  // Method org/h2/tools/SimpleResultSet.getUnsupportedException:()Ljava/sql/SQLException;
       3: athrow

  public java.sql.ResultSet getResultSet(long, int) throws java.sql.SQLException;
    Code:
       0: invokestatic  #3                  // Method org/h2/tools/SimpleResultSet.getUnsupportedException:()Ljava/sql/SQLException;
       3: athrow

  public java.sql.ResultSet getResultSet(long, int, java.util.Map<java.lang.String, java.lang.Class<?>>) throws java.sql.SQLException;
    Code:
       0: invokestatic  #3                  // Method org/h2/tools/SimpleResultSet.getUnsupportedException:()Ljava/sql/SQLException;
       3: athrow

  public void free();
    Code:
       0: return
}
