Compiled from "GroupPrincipal.scala"
public class blended.security.boot.GroupPrincipal implements java.security.Principal {
  private final java.lang.String group;

  public boolean implies(javax.security.auth.Subject);
    Code:
       0: aload_0
       1: aload_1
       2: invokespecial #17                 // InterfaceMethod java/security/Principal.implies:(Ljavax/security/auth/Subject;)Z
       5: ireturn

  public java.lang.String getName();
    Code:
       0: aload_0
       1: getfield      #24                 // Field group:Ljava/lang/String;
       4: areturn

  public int hashCode();
    Code:
       0: aload_0
       1: getfield      #24                 // Field group:Ljava/lang/String;
       4: invokevirtual #30                 // Method java/lang/String.hashCode:()I
       7: ireturn

  public boolean equals(java.lang.Object);
    Code:
       0: aload_1
       1: astore_3
       2: aload_3
       3: instanceof    #2                  // class blended/security/boot/GroupPrincipal
       6: ifeq          31
       9: aload_3
      10: checkcast     #2                  // class blended/security/boot/GroupPrincipal
      13: astore        4
      15: aload_0
      16: getfield      #24                 // Field group:Ljava/lang/String;
      19: aload         4
      21: invokevirtual #35                 // Method getName:()Ljava/lang/String;
      24: invokevirtual #37                 // Method java/lang/String.equals:(Ljava/lang/Object;)Z
      27: istore_2
      28: goto          39
      31: goto          34
      34: iconst_0
      35: istore_2
      36: goto          39
      39: iload_2
      40: ireturn

  public java.lang.String toString();
    Code:
       0: new           #41                 // class java/lang/StringBuilder
       3: dup
       4: ldc           #42                 // int 16
       6: invokespecial #46                 // Method java/lang/StringBuilder."<init>":(I)V
       9: ldc           #48                 // String GroupPrincipal(
      11: invokevirtual #52                 // Method java/lang/StringBuilder.append:(Ljava/lang/String;)Ljava/lang/StringBuilder;
      14: aload_0
      15: getfield      #24                 // Field group:Ljava/lang/String;
      18: invokevirtual #52                 // Method java/lang/StringBuilder.append:(Ljava/lang/String;)Ljava/lang/StringBuilder;
      21: ldc           #54                 // String )
      23: invokevirtual #52                 // Method java/lang/StringBuilder.append:(Ljava/lang/String;)Ljava/lang/StringBuilder;
      26: invokevirtual #56                 // Method java/lang/StringBuilder.toString:()Ljava/lang/String;
      29: areturn

  public blended.security.boot.GroupPrincipal(java.lang.String);
    Code:
       0: aload_0
       1: aload_1
       2: putfield      #24                 // Field group:Ljava/lang/String;
       5: aload_0
       6: invokespecial #60                 // Method java/lang/Object."<init>":()V
       9: return
}
