Compiled from "GroupExtract.scala"
public final class edu.psu.sagnik.research.inkscapesvgprocessing.impl.GroupExtract$ {
  public static final edu.psu.sagnik.research.inkscapesvgprocessing.impl.GroupExtract$ MODULE$;

  public static {};
    Code:
       0: new           #2                  // class edu/psu/sagnik/research/inkscapesvgprocessing/impl/GroupExtract$
       3: invokespecial #12                 // Method "<init>":()V
       6: return

  public scala.collection.Seq<edu.psu.sagnik.research.inkscapesvgprocessing.model.SVGGroup> apply(java.lang.String);
    Code:
       0: aload_0
       1: getstatic     #19                 // Field edu/psu/sagnik/research/inkscapesvgprocessing/reader/XMLReader$.MODULE$:Ledu/psu/sagnik/research/inkscapesvgprocessing/reader/XMLReader$;
       4: aload_1
       5: invokevirtual #22                 // Method edu/psu/sagnik/research/inkscapesvgprocessing/reader/XMLReader$.apply:(Ljava/lang/String;)Lscala/xml/Elem;
       8: invokevirtual #26                 // Method getGroups:(Lscala/xml/Elem;)Lscala/collection/Seq;
      11: areturn

  public scala.collection.Seq<edu.psu.sagnik.research.inkscapesvgprocessing.model.SVGGroup> getGroups(scala.xml.Elem);
    Code:
       0: aload_1
       1: ldc           #31                 // String g
       3: invokevirtual #37                 // Method scala/xml/Elem.$bslash$bslash:(Ljava/lang/String;)Lscala/xml/NodeSeq;
       6: new           #39                 // class edu/psu/sagnik/research/inkscapesvgprocessing/impl/GroupExtract$$anonfun$getGroups$1
       9: dup
      10: invokespecial #40                 // Method edu/psu/sagnik/research/inkscapesvgprocessing/impl/GroupExtract$$anonfun$getGroups$1."<init>":()V
      13: getstatic     #45                 // Field scala/collection/immutable/Seq$.MODULE$:Lscala/collection/immutable/Seq$;
      16: invokevirtual #49                 // Method scala/collection/immutable/Seq$.canBuildFrom:()Lscala/collection/generic/CanBuildFrom;
      19: invokevirtual #55                 // Method scala/xml/NodeSeq.map:(Lscala/Function1;Lscala/collection/generic/CanBuildFrom;)Ljava/lang/Object;
      22: checkcast     #57                 // class scala/collection/Seq
      25: areturn

  public void main(java.lang.String[]);
    Code:
       0: ldc           #63                 // String src/test/resources/pg_0006.svg
       2: astore_2
       3: aload_0
       4: aload_2
       5: invokevirtual #65                 // Method apply:(Ljava/lang/String;)Lscala/collection/Seq;
       8: astore_3
       9: aload_3
      10: new           #67                 // class edu/psu/sagnik/research/inkscapesvgprocessing/impl/GroupExtract$$anonfun$main$1
      13: dup
      14: invokespecial #68                 // Method edu/psu/sagnik/research/inkscapesvgprocessing/impl/GroupExtract$$anonfun$main$1."<init>":()V
      17: invokeinterface #72,  2           // InterfaceMethod scala/collection/Seq.foreach:(Lscala/Function1;)V
      22: return

  private edu.psu.sagnik.research.inkscapesvgprocessing.impl.GroupExtract$();
    Code:
       0: aload_0
       1: invokespecial #78                 // Method java/lang/Object."<init>":()V
       4: aload_0
       5: putstatic     #80                 // Field MODULE$:Ledu/psu/sagnik/research/inkscapesvgprocessing/impl/GroupExtract$;
       8: return
}
