Compiled from "SVGRasterExtract.scala"
public final class edu.psu.sagnik.research.inkscapesvgprocessing.impl.SVGRasterExtract$$anonfun$getRasters$1 extends scala.runtime.AbstractFunction1<edu.psu.sagnik.research.inkscapesvgprocessing.rasterparser.model.SVGRasterIm, edu.psu.sagnik.research.inkscapesvgprocessing.rasterparser.model.SVGRaster> implements scala.Serializable {
  public static final long serialVersionUID;

  public final edu.psu.sagnik.research.inkscapesvgprocessing.rasterparser.model.SVGRaster apply(edu.psu.sagnik.research.inkscapesvgprocessing.rasterparser.model.SVGRasterIm);
    Code:
       0: getstatic     #25                 // Field edu/psu/sagnik/research/inkscapesvgprocessing/impl/SVGRasterBB$.MODULE$:Ledu/psu/sagnik/research/inkscapesvgprocessing/impl/SVGRasterBB$;
       3: aload_1
       4: invokevirtual #27                 // Method edu/psu/sagnik/research/inkscapesvgprocessing/impl/SVGRasterBB$.apply:(Ledu/psu/sagnik/research/inkscapesvgprocessing/rasterparser/model/SVGRasterIm;)Ledu/psu/sagnik/research/inkscapesvgprocessing/rasterparser/model/SVGRaster;
       7: areturn

  public final java.lang.Object apply(java.lang.Object);
    Code:
       0: aload_0
       1: aload_1
       2: checkcast     #34                 // class edu/psu/sagnik/research/inkscapesvgprocessing/rasterparser/model/SVGRasterIm
       5: invokevirtual #35                 // Method apply:(Ledu/psu/sagnik/research/inkscapesvgprocessing/rasterparser/model/SVGRasterIm;)Ledu/psu/sagnik/research/inkscapesvgprocessing/rasterparser/model/SVGRaster;
       8: areturn

  public edu.psu.sagnik.research.inkscapesvgprocessing.impl.SVGRasterExtract$$anonfun$getRasters$1();
    Code:
       0: aload_0
       1: invokespecial #41                 // Method scala/runtime/AbstractFunction1."<init>":()V
       4: return
}
