Compiled from "CreateSubscriptionRequest.scala"
public final class zio.aws.shield.model.CreateSubscriptionRequest$Wrapper implements zio.aws.shield.model.CreateSubscriptionRequest$ReadOnly {
  public zio.aws.shield.model.CreateSubscriptionRequest asEditable();
    Code:
       0: aload_0
       1: invokestatic  #17                 // InterfaceMethod zio/aws/shield/model/CreateSubscriptionRequest$ReadOnly.asEditable$:(Lzio/aws/shield/model/CreateSubscriptionRequest$ReadOnly;)Lzio/aws/shield/model/CreateSubscriptionRequest;
       4: areturn

  public zio.aws.shield.model.CreateSubscriptionRequest$Wrapper(software.amazon.awssdk.services.shield.model.CreateSubscriptionRequest);
    Code:
       0: aload_0
       1: invokespecial #25                 // Method java/lang/Object."<init>":()V
       4: aload_0
       5: invokestatic  #29                 // InterfaceMethod zio/aws/shield/model/CreateSubscriptionRequest$ReadOnly.$init$:(Lzio/aws/shield/model/CreateSubscriptionRequest$ReadOnly;)V
       8: return
}
