Compiled from "DeleteProtectionResponse.scala"
public final class zio.aws.shield.model.DeleteProtectionResponse$Wrapper implements zio.aws.shield.model.DeleteProtectionResponse$ReadOnly {
  public zio.aws.shield.model.DeleteProtectionResponse asEditable();
    Code:
       0: aload_0
       1: invokestatic  #17                 // InterfaceMethod zio/aws/shield/model/DeleteProtectionResponse$ReadOnly.asEditable$:(Lzio/aws/shield/model/DeleteProtectionResponse$ReadOnly;)Lzio/aws/shield/model/DeleteProtectionResponse;
       4: areturn

  public zio.aws.shield.model.DeleteProtectionResponse$Wrapper(software.amazon.awssdk.services.shield.model.DeleteProtectionResponse);
    Code:
       0: aload_0
       1: invokespecial #25                 // Method java/lang/Object."<init>":()V
       4: aload_0
       5: invokestatic  #29                 // InterfaceMethod zio/aws/shield/model/DeleteProtectionResponse$ReadOnly.$init$:(Lzio/aws/shield/model/DeleteProtectionResponse$ReadOnly;)V
       8: return
}
