Compiled from "StompBrokerRelayMessageHandler.java"
class org.springframework.messaging.simp.stomp.StompBrokerRelayMessageHandler$SystemStompConnectionHandler extends org.springframework.messaging.simp.stomp.StompBrokerRelayMessageHandler$StompConnectionHandler {
  final org.springframework.messaging.simp.stomp.StompBrokerRelayMessageHandler this$0;

  public org.springframework.messaging.simp.stomp.StompBrokerRelayMessageHandler$SystemStompConnectionHandler(org.springframework.messaging.simp.stomp.StompBrokerRelayMessageHandler, org.springframework.messaging.simp.stomp.StompHeaderAccessor);
    Code:
       0: aload_0
       1: aload_1
       2: putfield      #2                  // Field this$0:Lorg/springframework/messaging/simp/stomp/StompBrokerRelayMessageHandler;
       5: aload_0
       6: aload_1
       7: ldc           #3                  // String _system_
       9: aload_2
      10: iconst_0
      11: aconst_null
      12: invokespecial #4                  // Method org/springframework/messaging/simp/stomp/StompBrokerRelayMessageHandler$StompConnectionHandler."<init>":(Lorg/springframework/messaging/simp/stomp/StompBrokerRelayMessageHandler;Ljava/lang/String;Lorg/springframework/messaging/simp/stomp/StompHeaderAccessor;ZLorg/springframework/messaging/simp/stomp/StompBrokerRelayMessageHandler$1;)V
      15: return

  protected void afterStompConnected(org.springframework.messaging.simp.stomp.StompHeaderAccessor);
    Code:
       0: aload_0
       1: getfield      #2                  // Field this$0:Lorg/springframework/messaging/simp/stomp/StompBrokerRelayMessageHandler;
       4: invokestatic  #5                  // Method org/springframework/messaging/simp/stomp/StompBrokerRelayMessageHandler.access$4200:(Lorg/springframework/messaging/simp/stomp/StompBrokerRelayMessageHandler;)Lorg/apache/commons/logging/Log;
       7: invokeinterface #6,  1            // InterfaceMethod org/apache/commons/logging/Log.isInfoEnabled:()Z
      12: ifeq          29
      15: aload_0
      16: getfield      #2                  // Field this$0:Lorg/springframework/messaging/simp/stomp/StompBrokerRelayMessageHandler;
      19: invokestatic  #7                  // Method org/springframework/messaging/simp/stomp/StompBrokerRelayMessageHandler.access$4300:(Lorg/springframework/messaging/simp/stomp/StompBrokerRelayMessageHandler;)Lorg/apache/commons/logging/Log;
      22: ldc           #8                  // String \"System\" session connected.
      24: invokeinterface #9,  2            // InterfaceMethod org/apache/commons/logging/Log.info:(Ljava/lang/Object;)V
      29: aload_0
      30: aload_1
      31: invokespecial #10                 // Method org/springframework/messaging/simp/stomp/StompBrokerRelayMessageHandler$StompConnectionHandler.afterStompConnected:(Lorg/springframework/messaging/simp/stomp/StompHeaderAccessor;)V
      34: aload_0
      35: getfield      #2                  // Field this$0:Lorg/springframework/messaging/simp/stomp/StompBrokerRelayMessageHandler;
      38: invokestatic  #11                 // Method org/springframework/messaging/simp/stomp/StompBrokerRelayMessageHandler.access$4400:(Lorg/springframework/messaging/simp/stomp/StompBrokerRelayMessageHandler;)V
      41: aload_0
      42: invokespecial #12                 // Method sendSystemSubscriptions:()V
      45: return

  private void sendSystemSubscriptions();
    Code:
       0: iconst_0
       1: istore_1
       2: aload_0
       3: getfield      #2                  // Field this$0:Lorg/springframework/messaging/simp/stomp/StompBrokerRelayMessageHandler;
       6: invokevirtual #13                 // Method org/springframework/messaging/simp/stomp/StompBrokerRelayMessageHandler.getSystemSubscriptions:()Ljava/util/Map;
       9: invokeinterface #14,  1           // InterfaceMethod java/util/Map.keySet:()Ljava/util/Set;
      14: invokeinterface #15,  1           // InterfaceMethod java/util/Set.iterator:()Ljava/util/Iterator;
      19: astore_2
      20: aload_2
      21: invokeinterface #16,  1           // InterfaceMethod java/util/Iterator.hasNext:()Z
      26: ifeq          168
      29: aload_2
      30: invokeinterface #17,  1           // InterfaceMethod java/util/Iterator.next:()Ljava/lang/Object;
      35: checkcast     #18                 // class java/lang/String
      38: astore_3
      39: getstatic     #19                 // Field org/springframework/messaging/simp/stomp/StompCommand.SUBSCRIBE:Lorg/springframework/messaging/simp/stomp/StompCommand;
      42: invokestatic  #20                 // Method org/springframework/messaging/simp/stomp/StompHeaderAccessor.create:(Lorg/springframework/messaging/simp/stomp/StompCommand;)Lorg/springframework/messaging/simp/stomp/StompHeaderAccessor;
      45: astore        4
      47: aload         4
      49: iload_1
      50: iinc          1, 1
      53: invokestatic  #21                 // Method java/lang/String.valueOf:(I)Ljava/lang/String;
      56: invokevirtual #22                 // Method org/springframework/messaging/simp/stomp/StompHeaderAccessor.setSubscriptionId:(Ljava/lang/String;)V
      59: aload         4
      61: aload_3
      62: invokevirtual #23                 // Method org/springframework/messaging/simp/stomp/StompHeaderAccessor.setDestination:(Ljava/lang/String;)V
      65: aload_0
      66: getfield      #2                  // Field this$0:Lorg/springframework/messaging/simp/stomp/StompBrokerRelayMessageHandler;
      69: invokestatic  #24                 // Method org/springframework/messaging/simp/stomp/StompBrokerRelayMessageHandler.access$4500:(Lorg/springframework/messaging/simp/stomp/StompBrokerRelayMessageHandler;)Lorg/apache/commons/logging/Log;
      72: invokeinterface #25,  1           // InterfaceMethod org/apache/commons/logging/Log.isDebugEnabled:()Z
      77: ifeq          116
      80: aload_0
      81: getfield      #2                  // Field this$0:Lorg/springframework/messaging/simp/stomp/StompBrokerRelayMessageHandler;
      84: invokestatic  #26                 // Method org/springframework/messaging/simp/stomp/StompBrokerRelayMessageHandler.access$4600:(Lorg/springframework/messaging/simp/stomp/StompBrokerRelayMessageHandler;)Lorg/apache/commons/logging/Log;
      87: new           #27                 // class java/lang/StringBuilder
      90: dup
      91: invokespecial #28                 // Method java/lang/StringBuilder."<init>":()V
      94: ldc           #29                 // String Subscribing to
      96: invokevirtual #30                 // Method java/lang/StringBuilder.append:(Ljava/lang/String;)Ljava/lang/StringBuilder;
      99: aload_3
     100: invokevirtual #30                 // Method java/lang/StringBuilder.append:(Ljava/lang/String;)Ljava/lang/StringBuilder;
     103: ldc           #31                 // String  on \"system\" connection.
     105: invokevirtual #30                 // Method java/lang/StringBuilder.append:(Ljava/lang/String;)Ljava/lang/StringBuilder;
     108: invokevirtual #32                 // Method java/lang/StringBuilder.toString:()Ljava/lang/String;
     111: invokeinterface #33,  2           // InterfaceMethod org/apache/commons/logging/Log.debug:(Ljava/lang/Object;)V
     116: aload_0
     117: invokevirtual #34                 // Method getTcpConnection:()Lorg/springframework/messaging/tcp/TcpConnection;
     120: astore        5
     122: aload         5
     124: ifnull        165
     127: aload         4
     129: invokevirtual #35                 // Method org/springframework/messaging/simp/stomp/StompHeaderAccessor.getMessageHeaders:()Lorg/springframework/messaging/MessageHeaders;
     132: astore        6
     134: aload         5
     136: invokestatic  #36                 // Method org/springframework/messaging/simp/stomp/StompBrokerRelayMessageHandler.access$600:()[B
     139: aload         6
     141: invokestatic  #37                 // Method org/springframework/messaging/support/MessageBuilder.createMessage:(Ljava/lang/Object;Lorg/springframework/messaging/MessageHeaders;)Lorg/springframework/messaging/Message;
     144: invokeinterface #38,  2           // InterfaceMethod org/springframework/messaging/tcp/TcpConnection.send:(Lorg/springframework/messaging/Message;)Lorg/springframework/util/concurrent/ListenableFuture;
     149: invokedynamic #39,  0             // InvokeDynamic #0:onSuccess:()Lorg/springframework/util/concurrent/SuccessCallback;
     154: aload_0
     155: invokedynamic #40,  0             // InvokeDynamic #1:onFailure:(Lorg/springframework/messaging/simp/stomp/StompBrokerRelayMessageHandler$SystemStompConnectionHandler;)Lorg/springframework/util/concurrent/FailureCallback;
     160: invokeinterface #41,  3           // InterfaceMethod org/springframework/util/concurrent/ListenableFuture.addCallback:(Lorg/springframework/util/concurrent/SuccessCallback;Lorg/springframework/util/concurrent/FailureCallback;)V
     165: goto          20
     168: return

  protected void handleInboundMessage(org.springframework.messaging.Message<?>);
    Code:
       0: aload_1
       1: ldc           #42                 // class org/springframework/messaging/simp/stomp/StompHeaderAccessor
       3: invokestatic  #43                 // Method org/springframework/messaging/support/MessageHeaderAccessor.getAccessor:(Lorg/springframework/messaging/Message;Ljava/lang/Class;)Lorg/springframework/messaging/support/MessageHeaderAccessor;
       6: checkcast     #42                 // class org/springframework/messaging/simp/stomp/StompHeaderAccessor
       9: astore_2
      10: aload_2
      11: ifnull        226
      14: getstatic     #44                 // Field org/springframework/messaging/simp/stomp/StompCommand.MESSAGE:Lorg/springframework/messaging/simp/stomp/StompCommand;
      17: aload_2
      18: invokevirtual #45                 // Method org/springframework/messaging/simp/stomp/StompHeaderAccessor.getCommand:()Lorg/springframework/messaging/simp/stomp/StompCommand;
      21: invokevirtual #46                 // Method org/springframework/messaging/simp/stomp/StompCommand.equals:(Ljava/lang/Object;)Z
      24: ifeq          226
      27: aload_2
      28: invokevirtual #47                 // Method org/springframework/messaging/simp/stomp/StompHeaderAccessor.getDestination:()Ljava/lang/String;
      31: astore_3
      32: aload_3
      33: ifnonnull     92
      36: aload_0
      37: getfield      #2                  // Field this$0:Lorg/springframework/messaging/simp/stomp/StompBrokerRelayMessageHandler;
      40: invokestatic  #48                 // Method org/springframework/messaging/simp/stomp/StompBrokerRelayMessageHandler.access$4700:(Lorg/springframework/messaging/simp/stomp/StompBrokerRelayMessageHandler;)Lorg/apache/commons/logging/Log;
      43: invokeinterface #25,  1           // InterfaceMethod org/apache/commons/logging/Log.isDebugEnabled:()Z
      48: ifeq          91
      51: aload_0
      52: getfield      #2                  // Field this$0:Lorg/springframework/messaging/simp/stomp/StompBrokerRelayMessageHandler;
      55: invokestatic  #49                 // Method org/springframework/messaging/simp/stomp/StompBrokerRelayMessageHandler.access$4800:(Lorg/springframework/messaging/simp/stomp/StompBrokerRelayMessageHandler;)Lorg/apache/commons/logging/Log;
      58: new           #27                 // class java/lang/StringBuilder
      61: dup
      62: invokespecial #28                 // Method java/lang/StringBuilder."<init>":()V
      65: ldc           #50                 // String Got message on \"system\" connection, with no destination:
      67: invokevirtual #30                 // Method java/lang/StringBuilder.append:(Ljava/lang/String;)Ljava/lang/StringBuilder;
      70: aload_2
      71: aload_1
      72: invokeinterface #51,  1           // InterfaceMethod org/springframework/messaging/Message.getPayload:()Ljava/lang/Object;
      77: invokevirtual #52                 // Method org/springframework/messaging/simp/stomp/StompHeaderAccessor.getDetailedLogMessage:(Ljava/lang/Object;)Ljava/lang/String;
      80: invokevirtual #30                 // Method java/lang/StringBuilder.append:(Ljava/lang/String;)Ljava/lang/StringBuilder;
      83: invokevirtual #32                 // Method java/lang/StringBuilder.toString:()Ljava/lang/String;
      86: invokeinterface #33,  2           // InterfaceMethod org/apache/commons/logging/Log.debug:(Ljava/lang/Object;)V
      91: return
      92: aload_0
      93: getfield      #2                  // Field this$0:Lorg/springframework/messaging/simp/stomp/StompBrokerRelayMessageHandler;
      96: invokevirtual #13                 // Method org/springframework/messaging/simp/stomp/StompBrokerRelayMessageHandler.getSystemSubscriptions:()Ljava/util/Map;
      99: aload_3
     100: invokeinterface #53,  2           // InterfaceMethod java/util/Map.containsKey:(Ljava/lang/Object;)Z
     105: ifne          164
     108: aload_0
     109: getfield      #2                  // Field this$0:Lorg/springframework/messaging/simp/stomp/StompBrokerRelayMessageHandler;
     112: invokestatic  #54                 // Method org/springframework/messaging/simp/stomp/StompBrokerRelayMessageHandler.access$4900:(Lorg/springframework/messaging/simp/stomp/StompBrokerRelayMessageHandler;)Lorg/apache/commons/logging/Log;
     115: invokeinterface #25,  1           // InterfaceMethod org/apache/commons/logging/Log.isDebugEnabled:()Z
     120: ifeq          163
     123: aload_0
     124: getfield      #2                  // Field this$0:Lorg/springframework/messaging/simp/stomp/StompBrokerRelayMessageHandler;
     127: invokestatic  #55                 // Method org/springframework/messaging/simp/stomp/StompBrokerRelayMessageHandler.access$5000:(Lorg/springframework/messaging/simp/stomp/StompBrokerRelayMessageHandler;)Lorg/apache/commons/logging/Log;
     130: new           #27                 // class java/lang/StringBuilder
     133: dup
     134: invokespecial #28                 // Method java/lang/StringBuilder."<init>":()V
     137: ldc           #56                 // String Got message on \"system\" connection with no handler:
     139: invokevirtual #30                 // Method java/lang/StringBuilder.append:(Ljava/lang/String;)Ljava/lang/StringBuilder;
     142: aload_2
     143: aload_1
     144: invokeinterface #51,  1           // InterfaceMethod org/springframework/messaging/Message.getPayload:()Ljava/lang/Object;
     149: invokevirtual #52                 // Method org/springframework/messaging/simp/stomp/StompHeaderAccessor.getDetailedLogMessage:(Ljava/lang/Object;)Ljava/lang/String;
     152: invokevirtual #30                 // Method java/lang/StringBuilder.append:(Ljava/lang/String;)Ljava/lang/StringBuilder;
     155: invokevirtual #32                 // Method java/lang/StringBuilder.toString:()Ljava/lang/String;
     158: invokeinterface #33,  2           // InterfaceMethod org/apache/commons/logging/Log.debug:(Ljava/lang/Object;)V
     163: return
     164: aload_0
     165: getfield      #2                  // Field this$0:Lorg/springframework/messaging/simp/stomp/StompBrokerRelayMessageHandler;
     168: invokevirtual #13                 // Method org/springframework/messaging/simp/stomp/StompBrokerRelayMessageHandler.getSystemSubscriptions:()Ljava/util/Map;
     171: aload_3
     172: invokeinterface #57,  2           // InterfaceMethod java/util/Map.get:(Ljava/lang/Object;)Ljava/lang/Object;
     177: checkcast     #58                 // class org/springframework/messaging/MessageHandler
     180: astore        4
     182: aload         4
     184: aload_1
     185: invokeinterface #59,  2           // InterfaceMethod org/springframework/messaging/MessageHandler.handleMessage:(Lorg/springframework/messaging/Message;)V
     190: goto          226
     193: astore        4
     195: aload_0
     196: getfield      #2                  // Field this$0:Lorg/springframework/messaging/simp/stomp/StompBrokerRelayMessageHandler;
     199: invokestatic  #61                 // Method org/springframework/messaging/simp/stomp/StompBrokerRelayMessageHandler.access$5100:(Lorg/springframework/messaging/simp/stomp/StompBrokerRelayMessageHandler;)Lorg/apache/commons/logging/Log;
     202: invokeinterface #25,  1           // InterfaceMethod org/apache/commons/logging/Log.isDebugEnabled:()Z
     207: ifeq          226
     210: aload_0
     211: getfield      #2                  // Field this$0:Lorg/springframework/messaging/simp/stomp/StompBrokerRelayMessageHandler;
     214: invokestatic  #62                 // Method org/springframework/messaging/simp/stomp/StompBrokerRelayMessageHandler.access$5200:(Lorg/springframework/messaging/simp/stomp/StompBrokerRelayMessageHandler;)Lorg/apache/commons/logging/Log;
     217: ldc           #63                 // String Error while handling message on \"system\" connection.
     219: aload         4
     221: invokeinterface #64,  3           // InterfaceMethod org/apache/commons/logging/Log.debug:(Ljava/lang/Object;Ljava/lang/Throwable;)V
     226: return
    Exception table:
       from    to  target type
         164   190   193   Class java/lang/Throwable

  protected void handleTcpConnectionFailure(java.lang.String, java.lang.Throwable);
    Code:
       0: aload_0
       1: aload_1
       2: aload_2
       3: invokespecial #65                 // Method org/springframework/messaging/simp/stomp/StompBrokerRelayMessageHandler$StompConnectionHandler.handleTcpConnectionFailure:(Ljava/lang/String;Ljava/lang/Throwable;)V
       6: aload_0
       7: getfield      #2                  // Field this$0:Lorg/springframework/messaging/simp/stomp/StompBrokerRelayMessageHandler;
      10: invokestatic  #66                 // Method org/springframework/messaging/simp/stomp/StompBrokerRelayMessageHandler.access$5300:(Lorg/springframework/messaging/simp/stomp/StompBrokerRelayMessageHandler;)V
      13: return

  public void afterConnectionClosed();
    Code:
       0: aload_0
       1: invokespecial #67                 // Method org/springframework/messaging/simp/stomp/StompBrokerRelayMessageHandler$StompConnectionHandler.afterConnectionClosed:()V
       4: aload_0
       5: getfield      #2                  // Field this$0:Lorg/springframework/messaging/simp/stomp/StompBrokerRelayMessageHandler;
       8: invokestatic  #68                 // Method org/springframework/messaging/simp/stomp/StompBrokerRelayMessageHandler.access$5400:(Lorg/springframework/messaging/simp/stomp/StompBrokerRelayMessageHandler;)V
      11: return

  public org.springframework.util.concurrent.ListenableFuture<java.lang.Void> forward(org.springframework.messaging.Message<?>, org.springframework.messaging.simp.stomp.StompHeaderAccessor);
    Code:
       0: aload_0
       1: aload_1
       2: aload_2
       3: invokespecial #69                 // Method org/springframework/messaging/simp/stomp/StompBrokerRelayMessageHandler$StompConnectionHandler.forward:(Lorg/springframework/messaging/Message;Lorg/springframework/messaging/simp/stomp/StompHeaderAccessor;)Lorg/springframework/util/concurrent/ListenableFuture;
       6: astore_3
       7: aload_1
       8: invokeinterface #70,  1           // InterfaceMethod org/springframework/messaging/Message.getHeaders:()Lorg/springframework/messaging/MessageHeaders;
      13: ldc           #72                 // String simpIgnoreError
      15: invokevirtual #73                 // Method org/springframework/messaging/MessageHeaders.get:(Ljava/lang/Object;)Ljava/lang/Object;
      18: ifnonnull     28
      21: aload_3
      22: invokeinterface #74,  1           // InterfaceMethod org/springframework/util/concurrent/ListenableFuture.get:()Ljava/lang/Object;
      27: pop
      28: aload_3
      29: areturn
      30: astore_3
      31: new           #75                 // class org/springframework/messaging/MessageDeliveryException
      34: dup
      35: aload_1
      36: aload_3
      37: invokespecial #76                 // Method org/springframework/messaging/MessageDeliveryException."<init>":(Lorg/springframework/messaging/Message;Ljava/lang/Throwable;)V
      40: athrow
    Exception table:
       from    to  target type
           0    29    30   Class java/lang/Throwable

  private void lambda$sendSystemSubscriptions$1(java.lang.Throwable);
    Code:
       0: ldc           #77                 // String Failed to subscribe in \"system\" session.
       2: astore_2
       3: aload_0
       4: aload_2
       5: aload_1
       6: invokevirtual #78                 // Method handleTcpConnectionFailure:(Ljava/lang/String;Ljava/lang/Throwable;)V
       9: return

  private static void lambda$sendSystemSubscriptions$0(java.lang.Void);
    Code:
       0: return
}
