Compiled from "NewEntitiesPreferencesPanel.java"
public class org.protege.editor.owl.ui.preferences.NewEntitiesPreferencesPanel extends org.protege.editor.owl.ui.preferences.OWLPreferencesPanel implements java.awt.event.ActionListener {
  private static final long serialVersionUID;

  private static final java.lang.String SEP_COLON;

  private static final java.lang.String SEP_HASH;

  private static final java.lang.String SEP_SLASH;

  private final org.slf4j.Logger logger;

  private javax.swing.JRadioButton autoIDIriFragment;

  private javax.swing.JRadioButton colonButton;

  private javax.swing.JRadioButton hashButton;

  private javax.swing.JRadioButton nameAsIriFragment;

  private javax.swing.JRadioButton slashButton;

  private javax.swing.JRadioButton iriBaseActiveOntology;

  private javax.swing.JRadioButton iriBaseSpecifiedIri;

  private javax.swing.JTextField iriDefaultBaseField;

  private org.semanticweb.owlapi.model.IRI labelAnnotation;

  private javax.swing.JButton annotationSelectButton;

  private javax.swing.JComboBox annotationLangSelector;

  private javax.swing.JLabel langLabel;

  private javax.swing.JLabel iriLabel;

  private javax.swing.JRadioButton customLabelButton;

  private javax.swing.JRadioButton sameAsRendererLabelButton;

  private javax.swing.JTextField annotationIriLabel;

  private javax.swing.JCheckBox saveIterativeIds;

  private javax.swing.JLabel digitCountLabel;

  private javax.swing.JLabel endLabel;

  private javax.swing.JLabel prefixLabel;

  private javax.swing.JLabel startLabel;

  private javax.swing.JLabel suffixLabel;

  private javax.swing.JPanel autoGeneratedIDPanel;

  private javax.swing.JRadioButton iterativeButton;

  private javax.swing.JRadioButton uniqueIdButton;

  private javax.swing.JSpinner autoIDEnd;

  private javax.swing.JSpinner autoIDStart;

  private javax.swing.JSpinner autoIDDigitCount;

  private javax.swing.JTextField autoIDPrefix;

  private javax.swing.JTextField autoIDSuffix;

  public org.protege.editor.owl.ui.preferences.NewEntitiesPreferencesPanel();
    Code:
       0: aload_0
       1: invokespecial #1                  // Method org/protege/editor/owl/ui/preferences/OWLPreferencesPanel."<init>":()V
       4: aload_0
       5: ldc           #2                  // class org/protege/editor/owl/ui/preferences/NewEntitiesPreferencesPanel
       7: invokestatic  #3                  // Method org/slf4j/LoggerFactory.getLogger:(Ljava/lang/Class;)Lorg/slf4j/Logger;
      10: putfield      #4                  // Field logger:Lorg/slf4j/Logger;
      13: aload_0
      14: aconst_null
      15: putfield      #5                  // Field labelAnnotation:Lorg/semanticweb/owlapi/model/IRI;
      18: return

  public void initialise() throws java.lang.Exception;
    Code:
       0: aload_0
       1: new           #6                  // class javax/swing/BoxLayout
       4: dup
       5: aload_0
       6: iconst_1
       7: invokespecial #7                  // Method javax/swing/BoxLayout."<init>":(Ljava/awt/Container;I)V
      10: invokevirtual #8                  // Method setLayout:(Ljava/awt/LayoutManager;)V
      13: aload_0
      14: aload_0
      15: invokespecial #9                  // Method createEntityIriPanel:()Ljavax/swing/JPanel;
      18: invokevirtual #10                 // Method add:(Ljava/awt/Component;)Ljava/awt/Component;
      21: pop
      22: aload_0
      23: bipush        7
      25: invokestatic  #11                 // Method javax/swing/Box.createVerticalStrut:(I)Ljava/awt/Component;
      28: invokevirtual #10                 // Method add:(Ljava/awt/Component;)Ljava/awt/Component;
      31: pop
      32: aload_0
      33: aload_0
      34: invokespecial #12                 // Method createEntityLabelPanel:()Ljavax/swing/JPanel;
      37: invokevirtual #10                 // Method add:(Ljava/awt/Component;)Ljava/awt/Component;
      40: pop
      41: aload_0
      42: bipush        7
      44: invokestatic  #11                 // Method javax/swing/Box.createVerticalStrut:(I)Ljava/awt/Component;
      47: invokevirtual #10                 // Method add:(Ljava/awt/Component;)Ljava/awt/Component;
      50: pop
      51: aload_0
      52: aload_0
      53: invokespecial #13                 // Method createAutoGeneratedIDPanel:()Ljavax/swing/JPanel;
      56: invokevirtual #10                 // Method add:(Ljava/awt/Component;)Ljava/awt/Component;
      59: pop
      60: return

  private javax.swing.JPanel createEntityIriPanel();
    Code:
       0: new           #14                 // class javax/swing/JPanel
       3: dup
       4: invokespecial #15                 // Method javax/swing/JPanel."<init>":()V
       7: astore_1
       8: aload_1
       9: new           #16                 // class javax/swing/border/TitledBorder
      12: dup
      13: ldc           #17                 // String Entity IRI
      15: invokespecial #18                 // Method javax/swing/border/TitledBorder."<init>":(Ljava/lang/String;)V
      18: invokevirtual #19                 // Method javax/swing/JPanel.setBorder:(Ljavax/swing/border/Border;)V
      21: aload_1
      22: new           #20                 // class java/awt/GridBagLayout
      25: dup
      26: invokespecial #21                 // Method java/awt/GridBagLayout."<init>":()V
      29: invokevirtual #22                 // Method javax/swing/JPanel.setLayout:(Ljava/awt/LayoutManager;)V
      32: new           #23                 // class java/awt/GridBagConstraints
      35: dup
      36: invokespecial #24                 // Method java/awt/GridBagConstraints."<init>":()V
      39: astore_2
      40: aload_2
      41: iconst_0
      42: putfield      #25                 // Field java/awt/GridBagConstraints.gridx:I
      45: aload_2
      46: iconst_0
      47: putfield      #26                 // Field java/awt/GridBagConstraints.gridy:I
      50: aload_2
      51: iconst_1
      52: putfield      #27                 // Field java/awt/GridBagConstraints.gridwidth:I
      55: aload_2
      56: iconst_1
      57: putfield      #28                 // Field java/awt/GridBagConstraints.gridheight:I
      60: aload_2
      61: iconst_0
      62: putfield      #29                 // Field java/awt/GridBagConstraints.fill:I
      65: aload_2
      66: new           #30                 // class java/awt/Insets
      69: dup
      70: bipush        12
      72: bipush        12
      74: iconst_0
      75: bipush        12
      77: invokespecial #31                 // Method java/awt/Insets."<init>":(IIII)V
      80: putfield      #32                 // Field java/awt/GridBagConstraints.insets:Ljava/awt/Insets;
      83: aload_2
      84: bipush        23
      86: putfield      #33                 // Field java/awt/GridBagConstraints.anchor:I
      89: aload_1
      90: new           #34                 // class javax/swing/JLabel
      93: dup
      94: ldc           #35                 // String Start with:
      96: invokespecial #36                 // Method javax/swing/JLabel."<init>":(Ljava/lang/String;)V
      99: aload_2
     100: invokevirtual #37                 // Method javax/swing/JPanel.add:(Ljava/awt/Component;Ljava/lang/Object;)V
     103: aload_2
     104: iconst_1
     105: putfield      #25                 // Field java/awt/GridBagConstraints.gridx:I
     108: aload_2
     109: iconst_0
     110: putfield      #26                 // Field java/awt/GridBagConstraints.gridy:I
     113: aload_2
     114: iconst_2
     115: putfield      #27                 // Field java/awt/GridBagConstraints.gridwidth:I
     118: aload_2
     119: new           #30                 // class java/awt/Insets
     122: dup
     123: bipush        12
     125: iconst_0
     126: iconst_0
     127: iconst_0
     128: invokespecial #31                 // Method java/awt/Insets."<init>":(IIII)V
     131: putfield      #32                 // Field java/awt/GridBagConstraints.insets:Ljava/awt/Insets;
     134: aload_0
     135: new           #38                 // class javax/swing/JRadioButton
     138: dup
     139: ldc           #39                 // String Active ontology IRI
     141: invokespecial #40                 // Method javax/swing/JRadioButton."<init>":(Ljava/lang/String;)V
     144: putfield      #41                 // Field iriBaseActiveOntology:Ljavax/swing/JRadioButton;
     147: aload_0
     148: getfield      #41                 // Field iriBaseActiveOntology:Ljavax/swing/JRadioButton;
     151: invokestatic  #42                 // Method org/protege/editor/owl/model/entity/EntityCreationPreferences.useDefaultBaseIRI:()Z
     154: ifne          161
     157: iconst_1
     158: goto          162
     161: iconst_0
     162: invokevirtual #43                 // Method javax/swing/JRadioButton.setSelected:(Z)V
     165: aload_1
     166: aload_0
     167: getfield      #41                 // Field iriBaseActiveOntology:Ljavax/swing/JRadioButton;
     170: aload_2
     171: invokevirtual #37                 // Method javax/swing/JPanel.add:(Ljava/awt/Component;Ljava/lang/Object;)V
     174: aload_2
     175: iconst_1
     176: putfield      #25                 // Field java/awt/GridBagConstraints.gridx:I
     179: aload_2
     180: iconst_1
     181: putfield      #26                 // Field java/awt/GridBagConstraints.gridy:I
     184: aload_2
     185: iconst_1
     186: putfield      #27                 // Field java/awt/GridBagConstraints.gridwidth:I
     189: aload_2
     190: new           #30                 // class java/awt/Insets
     193: dup
     194: iconst_0
     195: iconst_0
     196: iconst_0
     197: iconst_5
     198: invokespecial #31                 // Method java/awt/Insets."<init>":(IIII)V
     201: putfield      #32                 // Field java/awt/GridBagConstraints.insets:Ljava/awt/Insets;
     204: aload_0
     205: new           #38                 // class javax/swing/JRadioButton
     208: dup
     209: ldc           #44                 // String Specified IRI:
     211: invokespecial #40                 // Method javax/swing/JRadioButton."<init>":(Ljava/lang/String;)V
     214: putfield      #45                 // Field iriBaseSpecifiedIri:Ljavax/swing/JRadioButton;
     217: aload_0
     218: getfield      #45                 // Field iriBaseSpecifiedIri:Ljavax/swing/JRadioButton;
     221: invokestatic  #42                 // Method org/protege/editor/owl/model/entity/EntityCreationPreferences.useDefaultBaseIRI:()Z
     224: invokevirtual #43                 // Method javax/swing/JRadioButton.setSelected:(Z)V
     227: aload_1
     228: aload_0
     229: getfield      #45                 // Field iriBaseSpecifiedIri:Ljavax/swing/JRadioButton;
     232: aload_2
     233: invokevirtual #37                 // Method javax/swing/JPanel.add:(Ljava/awt/Component;Ljava/lang/Object;)V
     236: aload_2
     237: iconst_2
     238: putfield      #25                 // Field java/awt/GridBagConstraints.gridx:I
     241: aload_2
     242: iconst_2
     243: putfield      #29                 // Field java/awt/GridBagConstraints.fill:I
     246: aload_2
     247: dconst_1
     248: putfield      #46                 // Field java/awt/GridBagConstraints.weightx:D
     251: aload_2
     252: new           #30                 // class java/awt/Insets
     255: dup
     256: iconst_0
     257: iconst_0
     258: iconst_0
     259: bipush        12
     261: invokespecial #31                 // Method java/awt/Insets."<init>":(IIII)V
     264: putfield      #32                 // Field java/awt/GridBagConstraints.insets:Ljava/awt/Insets;
     267: aload_0
     268: new           #47                 // class javax/swing/JTextField
     271: dup
     272: invokespecial #48                 // Method javax/swing/JTextField."<init>":()V
     275: putfield      #49                 // Field iriDefaultBaseField:Ljavax/swing/JTextField;
     278: aload_0
     279: getfield      #49                 // Field iriDefaultBaseField:Ljavax/swing/JTextField;
     282: invokestatic  #50                 // Method org/protege/editor/owl/model/entity/EntityCreationPreferences.getDefaultBaseIRI:()Lorg/semanticweb/owlapi/model/IRI;
     285: invokevirtual #51                 // Method org/semanticweb/owlapi/model/IRI.toString:()Ljava/lang/String;
     288: invokevirtual #52                 // Method javax/swing/JTextField.setText:(Ljava/lang/String;)V
     291: aload_1
     292: aload_0
     293: getfield      #49                 // Field iriDefaultBaseField:Ljavax/swing/JTextField;
     296: aload_2
     297: invokevirtual #37                 // Method javax/swing/JPanel.add:(Ljava/awt/Component;Ljava/lang/Object;)V
     300: new           #53                 // class javax/swing/ButtonGroup
     303: dup
     304: invokespecial #54                 // Method javax/swing/ButtonGroup."<init>":()V
     307: astore_3
     308: aload_3
     309: aload_0
     310: getfield      #41                 // Field iriBaseActiveOntology:Ljavax/swing/JRadioButton;
     313: invokevirtual #55                 // Method javax/swing/ButtonGroup.add:(Ljavax/swing/AbstractButton;)V
     316: aload_3
     317: aload_0
     318: getfield      #45                 // Field iriBaseSpecifiedIri:Ljavax/swing/JRadioButton;
     321: invokevirtual #55                 // Method javax/swing/ButtonGroup.add:(Ljavax/swing/AbstractButton;)V
     324: aload_2
     325: iconst_0
     326: putfield      #25                 // Field java/awt/GridBagConstraints.gridx:I
     329: aload_2
     330: iconst_2
     331: putfield      #26                 // Field java/awt/GridBagConstraints.gridy:I
     334: aload_2
     335: iconst_0
     336: putfield      #29                 // Field java/awt/GridBagConstraints.fill:I
     339: aload_2
     340: new           #30                 // class java/awt/Insets
     343: dup
     344: bipush        11
     346: bipush        12
     348: iconst_0
     349: bipush        12
     351: invokespecial #31                 // Method java/awt/Insets."<init>":(IIII)V
     354: putfield      #32                 // Field java/awt/GridBagConstraints.insets:Ljava/awt/Insets;
     357: aload_2
     358: dconst_0
     359: putfield      #46                 // Field java/awt/GridBagConstraints.weightx:D
     362: aload_1
     363: new           #34                 // class javax/swing/JLabel
     366: dup
     367: ldc           #56                 // String Followed by:
     369: invokespecial #36                 // Method javax/swing/JLabel."<init>":(Ljava/lang/String;)V
     372: aload_2
     373: invokevirtual #37                 // Method javax/swing/JPanel.add:(Ljava/awt/Component;Ljava/lang/Object;)V
     376: aload_2
     377: iconst_1
     378: putfield      #25                 // Field java/awt/GridBagConstraints.gridx:I
     381: aload_2
     382: new           #30                 // class java/awt/Insets
     385: dup
     386: bipush        11
     388: iconst_0
     389: iconst_0
     390: iconst_0
     391: invokespecial #31                 // Method java/awt/Insets."<init>":(IIII)V
     394: putfield      #32                 // Field java/awt/GridBagConstraints.insets:Ljava/awt/Insets;
     397: aload_0
     398: new           #38                 // class javax/swing/JRadioButton
     401: dup
     402: ldc           #57                 // String #
     404: invokespecial #40                 // Method javax/swing/JRadioButton."<init>":(Ljava/lang/String;)V
     407: putfield      #58                 // Field hashButton:Ljavax/swing/JRadioButton;
     410: aload_0
     411: getfield      #58                 // Field hashButton:Ljavax/swing/JRadioButton;
     414: invokestatic  #59                 // Method org/protege/editor/owl/model/entity/EntityCreationPreferences.getDefaultSeparator:()Ljava/lang/String;
     417: ldc           #57                 // String #
     419: invokevirtual #60                 // Method java/lang/String.equals:(Ljava/lang/Object;)Z
     422: invokevirtual #43                 // Method javax/swing/JRadioButton.setSelected:(Z)V
     425: aload_1
     426: aload_0
     427: getfield      #58                 // Field hashButton:Ljavax/swing/JRadioButton;
     430: aload_2
     431: invokevirtual #37                 // Method javax/swing/JPanel.add:(Ljava/awt/Component;Ljava/lang/Object;)V
     434: aload_2
     435: iconst_3
     436: putfield      #26                 // Field java/awt/GridBagConstraints.gridy:I
     439: aload_2
     440: new           #30                 // class java/awt/Insets
     443: dup
     444: iconst_0
     445: iconst_0
     446: iconst_0
     447: iconst_0
     448: invokespecial #31                 // Method java/awt/Insets."<init>":(IIII)V
     451: putfield      #32                 // Field java/awt/GridBagConstraints.insets:Ljava/awt/Insets;
     454: aload_0
     455: new           #38                 // class javax/swing/JRadioButton
     458: dup
     459: ldc           #61                 // String /
     461: invokespecial #40                 // Method javax/swing/JRadioButton."<init>":(Ljava/lang/String;)V
     464: putfield      #62                 // Field slashButton:Ljavax/swing/JRadioButton;
     467: aload_0
     468: getfield      #62                 // Field slashButton:Ljavax/swing/JRadioButton;
     471: invokestatic  #59                 // Method org/protege/editor/owl/model/entity/EntityCreationPreferences.getDefaultSeparator:()Ljava/lang/String;
     474: ldc           #61                 // String /
     476: invokevirtual #60                 // Method java/lang/String.equals:(Ljava/lang/Object;)Z
     479: invokevirtual #43                 // Method javax/swing/JRadioButton.setSelected:(Z)V
     482: aload_1
     483: aload_0
     484: getfield      #62                 // Field slashButton:Ljavax/swing/JRadioButton;
     487: aload_2
     488: invokevirtual #37                 // Method javax/swing/JPanel.add:(Ljava/awt/Component;Ljava/lang/Object;)V
     491: aload_2
     492: iconst_4
     493: putfield      #26                 // Field java/awt/GridBagConstraints.gridy:I
     496: aload_2
     497: new           #30                 // class java/awt/Insets
     500: dup
     501: iconst_0
     502: iconst_0
     503: iconst_0
     504: iconst_0
     505: invokespecial #31                 // Method java/awt/Insets."<init>":(IIII)V
     508: putfield      #32                 // Field java/awt/GridBagConstraints.insets:Ljava/awt/Insets;
     511: aload_0
     512: new           #38                 // class javax/swing/JRadioButton
     515: dup
     516: ldc           #63                 // String :
     518: invokespecial #40                 // Method javax/swing/JRadioButton."<init>":(Ljava/lang/String;)V
     521: putfield      #64                 // Field colonButton:Ljavax/swing/JRadioButton;
     524: aload_0
     525: getfield      #64                 // Field colonButton:Ljavax/swing/JRadioButton;
     528: invokestatic  #59                 // Method org/protege/editor/owl/model/entity/EntityCreationPreferences.getDefaultSeparator:()Ljava/lang/String;
     531: ldc           #63                 // String :
     533: invokevirtual #60                 // Method java/lang/String.equals:(Ljava/lang/Object;)Z
     536: invokevirtual #43                 // Method javax/swing/JRadioButton.setSelected:(Z)V
     539: aload_1
     540: aload_0
     541: getfield      #64                 // Field colonButton:Ljavax/swing/JRadioButton;
     544: aload_2
     545: invokevirtual #37                 // Method javax/swing/JPanel.add:(Ljava/awt/Component;Ljava/lang/Object;)V
     548: new           #53                 // class javax/swing/ButtonGroup
     551: dup
     552: invokespecial #54                 // Method javax/swing/ButtonGroup."<init>":()V
     555: astore        4
     557: aload         4
     559: aload_0
     560: getfield      #58                 // Field hashButton:Ljavax/swing/JRadioButton;
     563: invokevirtual #55                 // Method javax/swing/ButtonGroup.add:(Ljavax/swing/AbstractButton;)V
     566: aload         4
     568: aload_0
     569: getfield      #62                 // Field slashButton:Ljavax/swing/JRadioButton;
     572: invokevirtual #55                 // Method javax/swing/ButtonGroup.add:(Ljavax/swing/AbstractButton;)V
     575: aload         4
     577: aload_0
     578: getfield      #64                 // Field colonButton:Ljavax/swing/JRadioButton;
     581: invokevirtual #55                 // Method javax/swing/ButtonGroup.add:(Ljavax/swing/AbstractButton;)V
     584: aload_2
     585: iconst_0
     586: putfield      #25                 // Field java/awt/GridBagConstraints.gridx:I
     589: aload_2
     590: iconst_5
     591: putfield      #26                 // Field java/awt/GridBagConstraints.gridy:I
     594: aload_2
     595: new           #30                 // class java/awt/Insets
     598: dup
     599: bipush        11
     601: bipush        12
     603: iconst_0
     604: bipush        12
     606: invokespecial #31                 // Method java/awt/Insets."<init>":(IIII)V
     609: putfield      #32                 // Field java/awt/GridBagConstraints.insets:Ljava/awt/Insets;
     612: aload_1
     613: new           #34                 // class javax/swing/JLabel
     616: dup
     617: ldc           #65                 // String End with:
     619: invokespecial #36                 // Method javax/swing/JLabel."<init>":(Ljava/lang/String;)V
     622: aload_2
     623: invokevirtual #37                 // Method javax/swing/JPanel.add:(Ljava/awt/Component;Ljava/lang/Object;)V
     626: aload_2
     627: iconst_1
     628: putfield      #25                 // Field java/awt/GridBagConstraints.gridx:I
     631: aload_2
     632: new           #30                 // class java/awt/Insets
     635: dup
     636: bipush        11
     638: iconst_0
     639: iconst_0
     640: iconst_0
     641: invokespecial #31                 // Method java/awt/Insets."<init>":(IIII)V
     644: putfield      #32                 // Field java/awt/GridBagConstraints.insets:Ljava/awt/Insets;
     647: aload_2
     648: iconst_2
     649: putfield      #27                 // Field java/awt/GridBagConstraints.gridwidth:I
     652: aload_0
     653: new           #38                 // class javax/swing/JRadioButton
     656: dup
     657: ldc           #66                 // String User supplied name
     659: invokespecial #40                 // Method javax/swing/JRadioButton."<init>":(Ljava/lang/String;)V
     662: putfield      #67                 // Field nameAsIriFragment:Ljavax/swing/JRadioButton;
     665: aload_0
     666: getfield      #67                 // Field nameAsIriFragment:Ljavax/swing/JRadioButton;
     669: invokestatic  #68                 // Method org/protege/editor/owl/model/entity/EntityCreationPreferences.isFragmentAutoGenerated:()Z
     672: ifne          679
     675: iconst_1
     676: goto          680
     679: iconst_0
     680: invokevirtual #43                 // Method javax/swing/JRadioButton.setSelected:(Z)V
     683: aload_0
     684: getfield      #67                 // Field nameAsIriFragment:Ljavax/swing/JRadioButton;
     687: aload_0
     688: invokedynamic #69,  0             // InvokeDynamic #0:actionPerformed:(Lorg/protege/editor/owl/ui/preferences/NewEntitiesPreferencesPanel;)Ljava/awt/event/ActionListener;
     693: invokevirtual #70                 // Method javax/swing/JRadioButton.addActionListener:(Ljava/awt/event/ActionListener;)V
     696: aload_1
     697: aload_0
     698: getfield      #67                 // Field nameAsIriFragment:Ljavax/swing/JRadioButton;
     701: aload_2
     702: invokevirtual #37                 // Method javax/swing/JPanel.add:(Ljava/awt/Component;Ljava/lang/Object;)V
     705: aload_2
     706: bipush        6
     708: putfield      #26                 // Field java/awt/GridBagConstraints.gridy:I
     711: aload_2
     712: new           #30                 // class java/awt/Insets
     715: dup
     716: iconst_0
     717: iconst_0
     718: bipush        12
     720: iconst_0
     721: invokespecial #31                 // Method java/awt/Insets."<init>":(IIII)V
     724: putfield      #32                 // Field java/awt/GridBagConstraints.insets:Ljava/awt/Insets;
     727: aload_2
     728: dconst_1
     729: putfield      #71                 // Field java/awt/GridBagConstraints.weighty:D
     732: aload_0
     733: new           #38                 // class javax/swing/JRadioButton
     736: dup
     737: ldc           #72                 // String Auto-generated ID
     739: invokespecial #40                 // Method javax/swing/JRadioButton."<init>":(Ljava/lang/String;)V
     742: putfield      #73                 // Field autoIDIriFragment:Ljavax/swing/JRadioButton;
     745: aload_0
     746: getfield      #73                 // Field autoIDIriFragment:Ljavax/swing/JRadioButton;
     749: invokestatic  #68                 // Method org/protege/editor/owl/model/entity/EntityCreationPreferences.isFragmentAutoGenerated:()Z
     752: invokevirtual #43                 // Method javax/swing/JRadioButton.setSelected:(Z)V
     755: aload_0
     756: getfield      #73                 // Field autoIDIriFragment:Ljavax/swing/JRadioButton;
     759: aload_0
     760: invokedynamic #74,  0             // InvokeDynamic #1:actionPerformed:(Lorg/protege/editor/owl/ui/preferences/NewEntitiesPreferencesPanel;)Ljava/awt/event/ActionListener;
     765: invokevirtual #70                 // Method javax/swing/JRadioButton.addActionListener:(Ljava/awt/event/ActionListener;)V
     768: aload_1
     769: aload_0
     770: getfield      #73                 // Field autoIDIriFragment:Ljavax/swing/JRadioButton;
     773: aload_2
     774: invokevirtual #37                 // Method javax/swing/JPanel.add:(Ljava/awt/Component;Ljava/lang/Object;)V
     777: new           #53                 // class javax/swing/ButtonGroup
     780: dup
     781: invokespecial #54                 // Method javax/swing/ButtonGroup."<init>":()V
     784: astore        5
     786: aload         5
     788: aload_0
     789: getfield      #67                 // Field nameAsIriFragment:Ljavax/swing/JRadioButton;
     792: invokevirtual #55                 // Method javax/swing/ButtonGroup.add:(Ljavax/swing/AbstractButton;)V
     795: aload         5
     797: aload_0
     798: getfield      #73                 // Field autoIDIriFragment:Ljavax/swing/JRadioButton;
     801: invokevirtual #55                 // Method javax/swing/ButtonGroup.add:(Ljavax/swing/AbstractButton;)V
     804: aload_1
     805: areturn

  private javax.swing.JPanel createEntityLabelPanel();
    Code:
       0: invokestatic  #75                 // Method org/protege/editor/owl/model/entity/EntityCreationPreferences.getLabelDescriptorClass:()Ljava/lang/Class;
       3: astore_1
       4: new           #14                 // class javax/swing/JPanel
       7: dup
       8: invokespecial #15                 // Method javax/swing/JPanel."<init>":()V
      11: astore_2
      12: aload_2
      13: new           #16                 // class javax/swing/border/TitledBorder
      16: dup
      17: ldc           #76                 // String Entity Label (for use with Auto-generated ID)
      19: invokespecial #18                 // Method javax/swing/border/TitledBorder."<init>":(Ljava/lang/String;)V
      22: invokevirtual #19                 // Method javax/swing/JPanel.setBorder:(Ljavax/swing/border/Border;)V
      25: aload_2
      26: new           #20                 // class java/awt/GridBagLayout
      29: dup
      30: invokespecial #21                 // Method java/awt/GridBagLayout."<init>":()V
      33: invokevirtual #22                 // Method javax/swing/JPanel.setLayout:(Ljava/awt/LayoutManager;)V
      36: new           #23                 // class java/awt/GridBagConstraints
      39: dup
      40: invokespecial #24                 // Method java/awt/GridBagConstraints."<init>":()V
      43: astore_3
      44: aload_3
      45: iconst_0
      46: putfield      #25                 // Field java/awt/GridBagConstraints.gridx:I
      49: aload_3
      50: iconst_0
      51: putfield      #26                 // Field java/awt/GridBagConstraints.gridy:I
      54: aload_3
      55: iconst_2
      56: putfield      #27                 // Field java/awt/GridBagConstraints.gridwidth:I
      59: aload_3
      60: iconst_1
      61: putfield      #28                 // Field java/awt/GridBagConstraints.gridheight:I
      64: aload_3
      65: iconst_0
      66: putfield      #29                 // Field java/awt/GridBagConstraints.fill:I
      69: aload_3
      70: bipush        23
      72: putfield      #33                 // Field java/awt/GridBagConstraints.anchor:I
      75: aload_3
      76: new           #30                 // class java/awt/Insets
      79: dup
      80: iconst_0
      81: bipush        12
      83: iconst_0
      84: iconst_0
      85: invokespecial #31                 // Method java/awt/Insets."<init>":(IIII)V
      88: putfield      #32                 // Field java/awt/GridBagConstraints.insets:Ljava/awt/Insets;
      91: aload_0
      92: new           #38                 // class javax/swing/JRadioButton
      95: dup
      96: ldc           #77                 // String Same as label renderer
      98: invokespecial #40                 // Method javax/swing/JRadioButton."<init>":(Ljava/lang/String;)V
     101: putfield      #78                 // Field sameAsRendererLabelButton:Ljavax/swing/JRadioButton;
     104: aload_0
     105: getfield      #78                 // Field sameAsRendererLabelButton:Ljavax/swing/JRadioButton;
     108: aload_1
     109: ldc           #79                 // class org/protege/editor/owl/model/entity/MatchRendererLabelDescriptor
     111: invokevirtual #80                 // Method java/lang/Object.equals:(Ljava/lang/Object;)Z
     114: invokevirtual #43                 // Method javax/swing/JRadioButton.setSelected:(Z)V
     117: aload_2
     118: aload_0
     119: getfield      #78                 // Field sameAsRendererLabelButton:Ljavax/swing/JRadioButton;
     122: aload_3
     123: invokevirtual #37                 // Method javax/swing/JPanel.add:(Ljava/awt/Component;Ljava/lang/Object;)V
     126: aload_3
     127: iconst_1
     128: putfield      #26                 // Field java/awt/GridBagConstraints.gridy:I
     131: aload_0
     132: new           #38                 // class javax/swing/JRadioButton
     135: dup
     136: ldc           #81                 // String Custom label
     138: invokespecial #40                 // Method javax/swing/JRadioButton."<init>":(Ljava/lang/String;)V
     141: putfield      #82                 // Field customLabelButton:Ljavax/swing/JRadioButton;
     144: aload_0
     145: getfield      #82                 // Field customLabelButton:Ljavax/swing/JRadioButton;
     148: aload_1
     149: ldc           #83                 // class org/protege/editor/owl/model/entity/CustomLabelDescriptor
     151: invokevirtual #80                 // Method java/lang/Object.equals:(Ljava/lang/Object;)Z
     154: invokevirtual #43                 // Method javax/swing/JRadioButton.setSelected:(Z)V
     157: aload_2
     158: aload_0
     159: getfield      #82                 // Field customLabelButton:Ljavax/swing/JRadioButton;
     162: aload_3
     163: invokevirtual #37                 // Method javax/swing/JPanel.add:(Ljava/awt/Component;Ljava/lang/Object;)V
     166: new           #53                 // class javax/swing/ButtonGroup
     169: dup
     170: invokespecial #54                 // Method javax/swing/ButtonGroup."<init>":()V
     173: astore        4
     175: aload         4
     177: aload_0
     178: getfield      #78                 // Field sameAsRendererLabelButton:Ljavax/swing/JRadioButton;
     181: invokevirtual #55                 // Method javax/swing/ButtonGroup.add:(Ljavax/swing/AbstractButton;)V
     184: aload         4
     186: aload_0
     187: getfield      #82                 // Field customLabelButton:Ljavax/swing/JRadioButton;
     190: invokevirtual #55                 // Method javax/swing/ButtonGroup.add:(Ljavax/swing/AbstractButton;)V
     193: aload_3
     194: iconst_2
     195: putfield      #26                 // Field java/awt/GridBagConstraints.gridy:I
     198: aload_3
     199: iconst_1
     200: putfield      #27                 // Field java/awt/GridBagConstraints.gridwidth:I
     203: aload_3
     204: new           #30                 // class java/awt/Insets
     207: dup
     208: iconst_5
     209: bipush        30
     211: iconst_0
     212: iconst_5
     213: invokespecial #31                 // Method java/awt/Insets."<init>":(IIII)V
     216: putfield      #32                 // Field java/awt/GridBagConstraints.insets:Ljava/awt/Insets;
     219: aload_0
     220: new           #34                 // class javax/swing/JLabel
     223: dup
     224: ldc           #84                 // String IRI
     226: invokespecial #36                 // Method javax/swing/JLabel."<init>":(Ljava/lang/String;)V
     229: putfield      #85                 // Field iriLabel:Ljavax/swing/JLabel;
     232: aload_2
     233: aload_0
     234: getfield      #85                 // Field iriLabel:Ljavax/swing/JLabel;
     237: aload_3
     238: invokevirtual #37                 // Method javax/swing/JPanel.add:(Ljava/awt/Component;Ljava/lang/Object;)V
     241: aload_3
     242: iconst_1
     243: putfield      #25                 // Field java/awt/GridBagConstraints.gridx:I
     246: aload_3
     247: iconst_2
     248: putfield      #29                 // Field java/awt/GridBagConstraints.fill:I
     251: aload_3
     252: new           #30                 // class java/awt/Insets
     255: dup
     256: iconst_5
     257: iconst_0
     258: iconst_0
     259: iconst_0
     260: invokespecial #31                 // Method java/awt/Insets."<init>":(IIII)V
     263: putfield      #32                 // Field java/awt/GridBagConstraints.insets:Ljava/awt/Insets;
     266: aload_3
     267: dconst_1
     268: putfield      #46                 // Field java/awt/GridBagConstraints.weightx:D
     271: aload_0
     272: new           #47                 // class javax/swing/JTextField
     275: dup
     276: invokespecial #48                 // Method javax/swing/JTextField."<init>":()V
     279: putfield      #86                 // Field annotationIriLabel:Ljavax/swing/JTextField;
     282: aload_0
     283: invokestatic  #87                 // Method org/protege/editor/owl/model/entity/EntityCreationPreferences.getNameLabelIRI:()Lorg/semanticweb/owlapi/model/IRI;
     286: putfield      #5                  // Field labelAnnotation:Lorg/semanticweb/owlapi/model/IRI;
     289: aload_0
     290: getfield      #5                  // Field labelAnnotation:Lorg/semanticweb/owlapi/model/IRI;
     293: ifnonnull     306
     296: aload_0
     297: getstatic     #88                 // Field org/semanticweb/owlapi/vocab/OWLRDFVocabulary.RDFS_LABEL:Lorg/semanticweb/owlapi/vocab/OWLRDFVocabulary;
     300: invokevirtual #89                 // Method org/semanticweb/owlapi/vocab/OWLRDFVocabulary.getIRI:()Lorg/semanticweb/owlapi/model/IRI;
     303: putfield      #5                  // Field labelAnnotation:Lorg/semanticweb/owlapi/model/IRI;
     306: aload_0
     307: getfield      #86                 // Field annotationIriLabel:Ljavax/swing/JTextField;
     310: aload_0
     311: getfield      #5                  // Field labelAnnotation:Lorg/semanticweb/owlapi/model/IRI;
     314: invokevirtual #51                 // Method org/semanticweb/owlapi/model/IRI.toString:()Ljava/lang/String;
     317: invokevirtual #52                 // Method javax/swing/JTextField.setText:(Ljava/lang/String;)V
     320: aload_0
     321: getfield      #86                 // Field annotationIriLabel:Ljavax/swing/JTextField;
     324: iconst_0
     325: invokevirtual #90                 // Method javax/swing/JTextField.setEditable:(Z)V
     328: aload_2
     329: aload_0
     330: getfield      #86                 // Field annotationIriLabel:Ljavax/swing/JTextField;
     333: aload_3
     334: invokevirtual #37                 // Method javax/swing/JPanel.add:(Ljava/awt/Component;Ljava/lang/Object;)V
     337: aload_3
     338: iconst_2
     339: putfield      #25                 // Field java/awt/GridBagConstraints.gridx:I
     342: aload_3
     343: iconst_0
     344: putfield      #29                 // Field java/awt/GridBagConstraints.fill:I
     347: aload_3
     348: new           #30                 // class java/awt/Insets
     351: dup
     352: iconst_5
     353: iconst_5
     354: iconst_0
     355: bipush        12
     357: invokespecial #31                 // Method java/awt/Insets."<init>":(IIII)V
     360: putfield      #32                 // Field java/awt/GridBagConstraints.insets:Ljava/awt/Insets;
     363: aload_3
     364: dconst_0
     365: putfield      #46                 // Field java/awt/GridBagConstraints.weightx:D
     368: aload_0
     369: new           #91                 // class javax/swing/JButton
     372: dup
     373: new           #92                 // class org/protege/editor/owl/ui/preferences/NewEntitiesPreferencesPanel$1
     376: dup
     377: aload_0
     378: ldc           #93                 // String ...
     380: invokespecial #94                 // Method org/protege/editor/owl/ui/preferences/NewEntitiesPreferencesPanel$1."<init>":(Lorg/protege/editor/owl/ui/preferences/NewEntitiesPreferencesPanel;Ljava/lang/String;)V
     383: invokespecial #95                 // Method javax/swing/JButton."<init>":(Ljavax/swing/Action;)V
     386: putfield      #96                 // Field annotationSelectButton:Ljavax/swing/JButton;
     389: aload_2
     390: aload_0
     391: getfield      #96                 // Field annotationSelectButton:Ljavax/swing/JButton;
     394: aload_3
     395: invokevirtual #37                 // Method javax/swing/JPanel.add:(Ljava/awt/Component;Ljava/lang/Object;)V
     398: aload_3
     399: iconst_0
     400: putfield      #25                 // Field java/awt/GridBagConstraints.gridx:I
     403: aload_3
     404: iconst_3
     405: putfield      #26                 // Field java/awt/GridBagConstraints.gridy:I
     408: aload_3
     409: new           #30                 // class java/awt/Insets
     412: dup
     413: iconst_5
     414: bipush        30
     416: bipush        12
     418: iconst_5
     419: invokespecial #31                 // Method java/awt/Insets."<init>":(IIII)V
     422: putfield      #32                 // Field java/awt/GridBagConstraints.insets:Ljava/awt/Insets;
     425: aload_0
     426: new           #34                 // class javax/swing/JLabel
     429: dup
     430: ldc           #97                 // String Lang
     432: invokespecial #36                 // Method javax/swing/JLabel."<init>":(Ljava/lang/String;)V
     435: putfield      #98                 // Field langLabel:Ljavax/swing/JLabel;
     438: aload_2
     439: aload_0
     440: getfield      #98                 // Field langLabel:Ljavax/swing/JLabel;
     443: aload_3
     444: invokevirtual #37                 // Method javax/swing/JPanel.add:(Ljava/awt/Component;Ljava/lang/Object;)V
     447: aload_3
     448: iconst_1
     449: putfield      #25                 // Field java/awt/GridBagConstraints.gridx:I
     452: aload_3
     453: new           #30                 // class java/awt/Insets
     456: dup
     457: iconst_5
     458: iconst_0
     459: bipush        12
     461: iconst_0
     462: invokespecial #31                 // Method java/awt/Insets."<init>":(IIII)V
     465: putfield      #32                 // Field java/awt/GridBagConstraints.insets:Ljava/awt/Insets;
     468: aload_3
     469: dconst_1
     470: putfield      #71                 // Field java/awt/GridBagConstraints.weighty:D
     473: aload_0
     474: new           #99                 // class org/protege/editor/owl/ui/UIHelper
     477: dup
     478: aload_0
     479: invokevirtual #100                // Method getOWLEditorKit:()Lorg/protege/editor/owl/OWLEditorKit;
     482: invokespecial #101                // Method org/protege/editor/owl/ui/UIHelper."<init>":(Lorg/protege/editor/owl/OWLEditorKit;)V
     485: invokevirtual #102                // Method org/protege/editor/owl/ui/UIHelper.getLanguageSelector:()Ljavax/swing/JComboBox;
     488: putfield      #103                // Field annotationLangSelector:Ljavax/swing/JComboBox;
     491: aload_0
     492: getfield      #103                // Field annotationLangSelector:Ljavax/swing/JComboBox;
     495: invokestatic  #104                // Method org/protege/editor/owl/model/entity/EntityCreationPreferences.getNameLabelLang:()Ljava/lang/String;
     498: invokevirtual #105                // Method javax/swing/JComboBox.setSelectedItem:(Ljava/lang/Object;)V
     501: aload_2
     502: aload_0
     503: getfield      #103                // Field annotationLangSelector:Ljavax/swing/JComboBox;
     506: aload_3
     507: invokevirtual #37                 // Method javax/swing/JPanel.add:(Ljava/awt/Component;Ljava/lang/Object;)V
     510: aload_2
     511: areturn

  private javax.swing.JPanel createAutoGeneratedIDPanel();
    Code:
       0: aload_0
       1: new           #14                 // class javax/swing/JPanel
       4: dup
       5: invokespecial #15                 // Method javax/swing/JPanel."<init>":()V
       8: putfield      #106                // Field autoGeneratedIDPanel:Ljavax/swing/JPanel;
      11: aload_0
      12: getfield      #106                // Field autoGeneratedIDPanel:Ljavax/swing/JPanel;
      15: new           #107                // class java/awt/FlowLayout
      18: dup
      19: iconst_3
      20: invokespecial #108                // Method java/awt/FlowLayout."<init>":(I)V
      23: invokevirtual #22                 // Method javax/swing/JPanel.setLayout:(Ljava/awt/LayoutManager;)V
      26: aload_0
      27: getfield      #106                // Field autoGeneratedIDPanel:Ljavax/swing/JPanel;
      30: new           #16                 // class javax/swing/border/TitledBorder
      33: dup
      34: ldc           #72                 // String Auto-generated ID
      36: invokespecial #18                 // Method javax/swing/border/TitledBorder."<init>":(Ljava/lang/String;)V
      39: invokevirtual #19                 // Method javax/swing/JPanel.setBorder:(Ljavax/swing/border/Border;)V
      42: new           #14                 // class javax/swing/JPanel
      45: dup
      46: new           #109                // class java/awt/BorderLayout
      49: dup
      50: bipush        32
      52: iconst_0
      53: invokespecial #110                // Method java/awt/BorderLayout."<init>":(II)V
      56: invokespecial #111                // Method javax/swing/JPanel."<init>":(Ljava/awt/LayoutManager;)V
      59: astore_1
      60: aload_1
      61: bipush        7
      63: bipush        7
      65: iconst_0
      66: iconst_0
      67: invokestatic  #112                // Method javax/swing/BorderFactory.createEmptyBorder:(IIII)Ljavax/swing/border/Border;
      70: invokevirtual #19                 // Method javax/swing/JPanel.setBorder:(Ljavax/swing/border/Border;)V
      73: new           #14                 // class javax/swing/JPanel
      76: dup
      77: invokespecial #15                 // Method javax/swing/JPanel."<init>":()V
      80: astore_2
      81: aload_2
      82: new           #6                  // class javax/swing/BoxLayout
      85: dup
      86: aload_2
      87: iconst_3
      88: invokespecial #7                  // Method javax/swing/BoxLayout."<init>":(Ljava/awt/Container;I)V
      91: invokevirtual #22                 // Method javax/swing/JPanel.setLayout:(Ljava/awt/LayoutManager;)V
      94: aload_0
      95: new           #38                 // class javax/swing/JRadioButton
      98: dup
      99: ldc           #113                // String Numeric (iterative)
     101: invokespecial #40                 // Method javax/swing/JRadioButton."<init>":(Ljava/lang/String;)V
     104: putfield      #114                // Field iterativeButton:Ljavax/swing/JRadioButton;
     107: aload_0
     108: new           #38                 // class javax/swing/JRadioButton
     111: dup
     112: ldc           #115                // String Globally unique
     114: invokespecial #40                 // Method javax/swing/JRadioButton."<init>":(Ljava/lang/String;)V
     117: putfield      #116                // Field uniqueIdButton:Ljavax/swing/JRadioButton;
     120: invokestatic  #117                // Method org/protege/editor/owl/model/entity/EntityCreationPreferences.getAutoIDGeneratorClass:()Ljava/lang/Class;
     123: astore_3
     124: aload_0
     125: getfield      #114                // Field iterativeButton:Ljavax/swing/JRadioButton;
     128: aload_3
     129: ldc           #118                // class org/protege/editor/owl/model/entity/IterativeAutoIDGenerator
     131: invokevirtual #80                 // Method java/lang/Object.equals:(Ljava/lang/Object;)Z
     134: invokevirtual #43                 // Method javax/swing/JRadioButton.setSelected:(Z)V
     137: aload_0
     138: getfield      #116                // Field uniqueIdButton:Ljavax/swing/JRadioButton;
     141: aload_3
     142: ldc           #119                // class org/protege/editor/owl/model/entity/UniqueIdGenerator
     144: invokevirtual #80                 // Method java/lang/Object.equals:(Ljava/lang/Object;)Z
     147: invokevirtual #43                 // Method javax/swing/JRadioButton.setSelected:(Z)V
     150: new           #53                 // class javax/swing/ButtonGroup
     153: dup
     154: invokespecial #54                 // Method javax/swing/ButtonGroup."<init>":()V
     157: astore        4
     159: aload         4
     161: aload_0
     162: getfield      #114                // Field iterativeButton:Ljavax/swing/JRadioButton;
     165: invokevirtual #55                 // Method javax/swing/ButtonGroup.add:(Ljavax/swing/AbstractButton;)V
     168: aload         4
     170: aload_0
     171: getfield      #116                // Field uniqueIdButton:Ljavax/swing/JRadioButton;
     174: invokevirtual #55                 // Method javax/swing/ButtonGroup.add:(Ljavax/swing/AbstractButton;)V
     177: aload_0
     178: getfield      #114                // Field iterativeButton:Ljavax/swing/JRadioButton;
     181: aload_0
     182: invokevirtual #70                 // Method javax/swing/JRadioButton.addActionListener:(Ljava/awt/event/ActionListener;)V
     185: aload_0
     186: getfield      #116                // Field uniqueIdButton:Ljavax/swing/JRadioButton;
     189: aload_0
     190: invokevirtual #70                 // Method javax/swing/JRadioButton.addActionListener:(Ljava/awt/event/ActionListener;)V
     193: aload_2
     194: aload_0
     195: getfield      #114                // Field iterativeButton:Ljavax/swing/JRadioButton;
     198: invokevirtual #120                // Method javax/swing/JPanel.add:(Ljava/awt/Component;)Ljava/awt/Component;
     201: pop
     202: aload_2
     203: aload_0
     204: getfield      #116                // Field uniqueIdButton:Ljavax/swing/JRadioButton;
     207: invokevirtual #120                // Method javax/swing/JPanel.add:(Ljava/awt/Component;)Ljava/awt/Component;
     210: pop
     211: aload_2
     212: invokestatic  #121                // Method javax/swing/Box.createVerticalGlue:()Ljava/awt/Component;
     215: invokevirtual #120                // Method javax/swing/JPanel.add:(Ljava/awt/Component;)Ljava/awt/Component;
     218: pop
     219: new           #14                 // class javax/swing/JPanel
     222: dup
     223: invokespecial #15                 // Method javax/swing/JPanel."<init>":()V
     226: astore        5
     228: aload         5
     230: new           #20                 // class java/awt/GridBagLayout
     233: dup
     234: invokespecial #21                 // Method java/awt/GridBagLayout."<init>":()V
     237: invokevirtual #22                 // Method javax/swing/JPanel.setLayout:(Ljava/awt/LayoutManager;)V
     240: new           #23                 // class java/awt/GridBagConstraints
     243: dup
     244: invokespecial #24                 // Method java/awt/GridBagConstraints."<init>":()V
     247: astore        6
     249: aload         6
     251: iconst_0
     252: putfield      #25                 // Field java/awt/GridBagConstraints.gridx:I
     255: aload         6
     257: iconst_0
     258: putfield      #26                 // Field java/awt/GridBagConstraints.gridy:I
     261: aload         6
     263: new           #30                 // class java/awt/Insets
     266: dup
     267: iconst_0
     268: iconst_0
     269: iconst_5
     270: iconst_0
     271: invokespecial #31                 // Method java/awt/Insets."<init>":(IIII)V
     274: putfield      #32                 // Field java/awt/GridBagConstraints.insets:Ljava/awt/Insets;
     277: aload         6
     279: bipush        22
     281: putfield      #33                 // Field java/awt/GridBagConstraints.anchor:I
     284: aload_0
     285: new           #34                 // class javax/swing/JLabel
     288: dup
     289: ldc           #122                // String Prefix:
     291: invokespecial #36                 // Method javax/swing/JLabel."<init>":(Ljava/lang/String;)V
     294: putfield      #123                // Field prefixLabel:Ljavax/swing/JLabel;
     297: aload         5
     299: aload_0
     300: getfield      #123                // Field prefixLabel:Ljavax/swing/JLabel;
     303: aload         6
     305: invokevirtual #37                 // Method javax/swing/JPanel.add:(Ljava/awt/Component;Ljava/lang/Object;)V
     308: aload         6
     310: iconst_1
     311: putfield      #25                 // Field java/awt/GridBagConstraints.gridx:I
     314: aload         6
     316: iconst_0
     317: putfield      #26                 // Field java/awt/GridBagConstraints.gridy:I
     320: aload         6
     322: bipush        23
     324: putfield      #33                 // Field java/awt/GridBagConstraints.anchor:I
     327: aload_0
     328: new           #47                 // class javax/swing/JTextField
     331: dup
     332: invokespecial #48                 // Method javax/swing/JTextField."<init>":()V
     335: putfield      #124                // Field autoIDPrefix:Ljavax/swing/JTextField;
     338: aload_0
     339: getfield      #124                // Field autoIDPrefix:Ljavax/swing/JTextField;
     342: invokestatic  #125                // Method org/protege/editor/owl/model/entity/EntityCreationPreferences.getPrefix:()Ljava/lang/String;
     345: invokevirtual #52                 // Method javax/swing/JTextField.setText:(Ljava/lang/String;)V
     348: aload_0
     349: getfield      #124                // Field autoIDPrefix:Ljavax/swing/JTextField;
     352: bipush        30
     354: invokevirtual #126                // Method javax/swing/JTextField.setColumns:(I)V
     357: aload         5
     359: aload_0
     360: getfield      #124                // Field autoIDPrefix:Ljavax/swing/JTextField;
     363: aload         6
     365: invokevirtual #37                 // Method javax/swing/JPanel.add:(Ljava/awt/Component;Ljava/lang/Object;)V
     368: aload         6
     370: iconst_0
     371: putfield      #25                 // Field java/awt/GridBagConstraints.gridx:I
     374: aload         6
     376: iconst_1
     377: putfield      #26                 // Field java/awt/GridBagConstraints.gridy:I
     380: aload         6
     382: bipush        22
     384: putfield      #33                 // Field java/awt/GridBagConstraints.anchor:I
     387: aload_0
     388: new           #34                 // class javax/swing/JLabel
     391: dup
     392: ldc           #127                // String Suffix:
     394: invokespecial #36                 // Method javax/swing/JLabel."<init>":(Ljava/lang/String;)V
     397: putfield      #128                // Field suffixLabel:Ljavax/swing/JLabel;
     400: aload         5
     402: aload_0
     403: getfield      #128                // Field suffixLabel:Ljavax/swing/JLabel;
     406: aload         6
     408: invokevirtual #37                 // Method javax/swing/JPanel.add:(Ljava/awt/Component;Ljava/lang/Object;)V
     411: aload         6
     413: iconst_1
     414: putfield      #25                 // Field java/awt/GridBagConstraints.gridx:I
     417: aload         6
     419: iconst_1
     420: putfield      #26                 // Field java/awt/GridBagConstraints.gridy:I
     423: aload         6
     425: bipush        23
     427: putfield      #33                 // Field java/awt/GridBagConstraints.anchor:I
     430: aload_0
     431: new           #47                 // class javax/swing/JTextField
     434: dup
     435: invokespecial #48                 // Method javax/swing/JTextField."<init>":()V
     438: putfield      #129                // Field autoIDSuffix:Ljavax/swing/JTextField;
     441: aload_0
     442: getfield      #129                // Field autoIDSuffix:Ljavax/swing/JTextField;
     445: invokestatic  #130                // Method org/protege/editor/owl/model/entity/EntityCreationPreferences.getSuffix:()Ljava/lang/String;
     448: invokevirtual #52                 // Method javax/swing/JTextField.setText:(Ljava/lang/String;)V
     451: aload_0
     452: getfield      #129                // Field autoIDSuffix:Ljavax/swing/JTextField;
     455: bipush        30
     457: invokevirtual #126                // Method javax/swing/JTextField.setColumns:(I)V
     460: aload         5
     462: aload_0
     463: getfield      #129                // Field autoIDSuffix:Ljavax/swing/JTextField;
     466: aload         6
     468: invokevirtual #37                 // Method javax/swing/JPanel.add:(Ljava/awt/Component;Ljava/lang/Object;)V
     471: aload         6
     473: iconst_0
     474: putfield      #25                 // Field java/awt/GridBagConstraints.gridx:I
     477: aload         6
     479: iconst_2
     480: putfield      #26                 // Field java/awt/GridBagConstraints.gridy:I
     483: aload         6
     485: bipush        22
     487: putfield      #33                 // Field java/awt/GridBagConstraints.anchor:I
     490: aload_0
     491: new           #34                 // class javax/swing/JLabel
     494: dup
     495: ldc           #131                // String Digit count:
     497: invokespecial #36                 // Method javax/swing/JLabel."<init>":(Ljava/lang/String;)V
     500: putfield      #132                // Field digitCountLabel:Ljavax/swing/JLabel;
     503: aload         5
     505: aload_0
     506: getfield      #132                // Field digitCountLabel:Ljavax/swing/JLabel;
     509: aload         6
     511: invokevirtual #37                 // Method javax/swing/JPanel.add:(Ljava/awt/Component;Ljava/lang/Object;)V
     514: aload         6
     516: iconst_1
     517: putfield      #25                 // Field java/awt/GridBagConstraints.gridx:I
     520: aload         6
     522: iconst_2
     523: putfield      #26                 // Field java/awt/GridBagConstraints.gridy:I
     526: aload         6
     528: bipush        23
     530: putfield      #33                 // Field java/awt/GridBagConstraints.anchor:I
     533: aload         6
     535: ldc2_w        #133                // double 0.5d
     538: putfield      #46                 // Field java/awt/GridBagConstraints.weightx:D
     541: aload_0
     542: new           #135                // class javax/swing/JSpinner
     545: dup
     546: new           #136                // class javax/swing/SpinnerNumberModel
     549: dup
     550: bipush        6
     552: iconst_0
     553: sipush        255
     556: iconst_1
     557: invokespecial #137                // Method javax/swing/SpinnerNumberModel."<init>":(IIII)V
     560: invokespecial #138                // Method javax/swing/JSpinner."<init>":(Ljavax/swing/SpinnerModel;)V
     563: putfield      #139                // Field autoIDDigitCount:Ljavax/swing/JSpinner;
     566: aload_0
     567: getfield      #139                // Field autoIDDigitCount:Ljavax/swing/JSpinner;
     570: invokestatic  #140                // Method org/protege/editor/owl/model/entity/EntityCreationPreferences.getAutoIDDigitCount:()I
     573: invokestatic  #141                // Method java/lang/Integer.valueOf:(I)Ljava/lang/Integer;
     576: invokevirtual #142                // Method javax/swing/JSpinner.setValue:(Ljava/lang/Object;)V
     579: aload_0
     580: getfield      #139                // Field autoIDDigitCount:Ljavax/swing/JSpinner;
     583: new           #143                // class java/awt/Dimension
     586: dup
     587: bipush        100
     589: bipush        20
     591: invokespecial #144                // Method java/awt/Dimension."<init>":(II)V
     594: invokevirtual #145                // Method javax/swing/JSpinner.setPreferredSize:(Ljava/awt/Dimension;)V
     597: aload         5
     599: aload_0
     600: getfield      #139                // Field autoIDDigitCount:Ljavax/swing/JSpinner;
     603: aload         6
     605: invokevirtual #37                 // Method javax/swing/JPanel.add:(Ljava/awt/Component;Ljava/lang/Object;)V
     608: aload         6
     610: iconst_0
     611: putfield      #25                 // Field java/awt/GridBagConstraints.gridx:I
     614: aload         6
     616: iconst_3
     617: putfield      #26                 // Field java/awt/GridBagConstraints.gridy:I
     620: aload         6
     622: dconst_0
     623: putfield      #46                 // Field java/awt/GridBagConstraints.weightx:D
     626: aload         6
     628: bipush        22
     630: putfield      #33                 // Field java/awt/GridBagConstraints.anchor:I
     633: aload_0
     634: new           #34                 // class javax/swing/JLabel
     637: dup
     638: ldc           #146                // String Start:
     640: invokespecial #36                 // Method javax/swing/JLabel."<init>":(Ljava/lang/String;)V
     643: putfield      #147                // Field startLabel:Ljavax/swing/JLabel;
     646: aload_0
     647: getfield      #147                // Field startLabel:Ljavax/swing/JLabel;
     650: aload_0
     651: getfield      #114                // Field iterativeButton:Ljavax/swing/JRadioButton;
     654: invokevirtual #148                // Method javax/swing/JRadioButton.isSelected:()Z
     657: invokevirtual #149                // Method javax/swing/JLabel.setEnabled:(Z)V
     660: aload         5
     662: aload_0
     663: getfield      #147                // Field startLabel:Ljavax/swing/JLabel;
     666: aload         6
     668: invokevirtual #37                 // Method javax/swing/JPanel.add:(Ljava/awt/Component;Ljava/lang/Object;)V
     671: aload         6
     673: iconst_1
     674: putfield      #25                 // Field java/awt/GridBagConstraints.gridx:I
     677: aload         6
     679: iconst_3
     680: putfield      #26                 // Field java/awt/GridBagConstraints.gridy:I
     683: aload         6
     685: bipush        23
     687: putfield      #33                 // Field java/awt/GridBagConstraints.anchor:I
     690: aload_0
     691: new           #135                // class javax/swing/JSpinner
     694: dup
     695: new           #136                // class javax/swing/SpinnerNumberModel
     698: dup
     699: iconst_0
     700: iconst_0
     701: ldc           #151                // int 2147483647
     703: iconst_1
     704: invokespecial #137                // Method javax/swing/SpinnerNumberModel."<init>":(IIII)V
     707: invokespecial #138                // Method javax/swing/JSpinner."<init>":(Ljavax/swing/SpinnerModel;)V
     710: putfield      #152                // Field autoIDStart:Ljavax/swing/JSpinner;
     713: aload_0
     714: getfield      #152                // Field autoIDStart:Ljavax/swing/JSpinner;
     717: new           #143                // class java/awt/Dimension
     720: dup
     721: bipush        100
     723: bipush        20
     725: invokespecial #144                // Method java/awt/Dimension."<init>":(II)V
     728: invokevirtual #145                // Method javax/swing/JSpinner.setPreferredSize:(Ljava/awt/Dimension;)V
     731: aload_0
     732: getfield      #152                // Field autoIDStart:Ljavax/swing/JSpinner;
     735: invokestatic  #153                // Method org/protege/editor/owl/model/entity/EntityCreationPreferences.getAutoIDStart:()I
     738: invokestatic  #141                // Method java/lang/Integer.valueOf:(I)Ljava/lang/Integer;
     741: invokevirtual #142                // Method javax/swing/JSpinner.setValue:(Ljava/lang/Object;)V
     744: aload_0
     745: getfield      #152                // Field autoIDStart:Ljavax/swing/JSpinner;
     748: aload_0
     749: getfield      #114                // Field iterativeButton:Ljavax/swing/JRadioButton;
     752: invokevirtual #148                // Method javax/swing/JRadioButton.isSelected:()Z
     755: invokevirtual #154                // Method javax/swing/JSpinner.setEnabled:(Z)V
     758: aload_0
     759: getfield      #152                // Field autoIDStart:Ljavax/swing/JSpinner;
     762: aload_0
     763: invokedynamic #155,  0            // InvokeDynamic #2:stateChanged:(Lorg/protege/editor/owl/ui/preferences/NewEntitiesPreferencesPanel;)Ljavax/swing/event/ChangeListener;
     768: invokevirtual #156                // Method javax/swing/JSpinner.addChangeListener:(Ljavax/swing/event/ChangeListener;)V
     771: aload         5
     773: aload_0
     774: getfield      #152                // Field autoIDStart:Ljavax/swing/JSpinner;
     777: aload         6
     779: invokevirtual #37                 // Method javax/swing/JPanel.add:(Ljava/awt/Component;Ljava/lang/Object;)V
     782: aload         6
     784: iconst_0
     785: putfield      #25                 // Field java/awt/GridBagConstraints.gridx:I
     788: aload         6
     790: iconst_4
     791: putfield      #26                 // Field java/awt/GridBagConstraints.gridy:I
     794: aload         6
     796: bipush        22
     798: putfield      #33                 // Field java/awt/GridBagConstraints.anchor:I
     801: aload_0
     802: new           #34                 // class javax/swing/JLabel
     805: dup
     806: ldc           #157                // String End:
     808: invokespecial #36                 // Method javax/swing/JLabel."<init>":(Ljava/lang/String;)V
     811: putfield      #158                // Field endLabel:Ljavax/swing/JLabel;
     814: aload_0
     815: getfield      #158                // Field endLabel:Ljavax/swing/JLabel;
     818: aload_0
     819: getfield      #114                // Field iterativeButton:Ljavax/swing/JRadioButton;
     822: invokevirtual #148                // Method javax/swing/JRadioButton.isSelected:()Z
     825: invokevirtual #149                // Method javax/swing/JLabel.setEnabled:(Z)V
     828: aload         5
     830: aload_0
     831: getfield      #158                // Field endLabel:Ljavax/swing/JLabel;
     834: aload         6
     836: invokevirtual #37                 // Method javax/swing/JPanel.add:(Ljava/awt/Component;Ljava/lang/Object;)V
     839: aload         6
     841: iconst_1
     842: putfield      #25                 // Field java/awt/GridBagConstraints.gridx:I
     845: aload         6
     847: iconst_4
     848: putfield      #26                 // Field java/awt/GridBagConstraints.gridy:I
     851: aload         6
     853: bipush        23
     855: putfield      #33                 // Field java/awt/GridBagConstraints.anchor:I
     858: aload_0
     859: new           #135                // class javax/swing/JSpinner
     862: dup
     863: new           #136                // class javax/swing/SpinnerNumberModel
     866: dup
     867: iconst_m1
     868: iconst_m1
     869: ldc           #151                // int 2147483647
     871: iconst_1
     872: invokespecial #137                // Method javax/swing/SpinnerNumberModel."<init>":(IIII)V
     875: invokespecial #138                // Method javax/swing/JSpinner."<init>":(Ljavax/swing/SpinnerModel;)V
     878: putfield      #159                // Field autoIDEnd:Ljavax/swing/JSpinner;
     881: aload_0
     882: getfield      #159                // Field autoIDEnd:Ljavax/swing/JSpinner;
     885: new           #143                // class java/awt/Dimension
     888: dup
     889: bipush        100
     891: bipush        20
     893: invokespecial #144                // Method java/awt/Dimension."<init>":(II)V
     896: invokevirtual #145                // Method javax/swing/JSpinner.setPreferredSize:(Ljava/awt/Dimension;)V
     899: aload_0
     900: getfield      #159                // Field autoIDEnd:Ljavax/swing/JSpinner;
     903: invokestatic  #160                // Method org/protege/editor/owl/model/entity/EntityCreationPreferences.getAutoIDEnd:()I
     906: invokestatic  #141                // Method java/lang/Integer.valueOf:(I)Ljava/lang/Integer;
     909: invokevirtual #142                // Method javax/swing/JSpinner.setValue:(Ljava/lang/Object;)V
     912: aload_0
     913: getfield      #159                // Field autoIDEnd:Ljavax/swing/JSpinner;
     916: aload_0
     917: getfield      #114                // Field iterativeButton:Ljavax/swing/JRadioButton;
     920: invokevirtual #148                // Method javax/swing/JRadioButton.isSelected:()Z
     923: invokevirtual #154                // Method javax/swing/JSpinner.setEnabled:(Z)V
     926: aload_0
     927: getfield      #159                // Field autoIDEnd:Ljavax/swing/JSpinner;
     930: aload_0
     931: invokedynamic #161,  0            // InvokeDynamic #3:stateChanged:(Lorg/protege/editor/owl/ui/preferences/NewEntitiesPreferencesPanel;)Ljavax/swing/event/ChangeListener;
     936: invokevirtual #156                // Method javax/swing/JSpinner.addChangeListener:(Ljavax/swing/event/ChangeListener;)V
     939: aload         5
     941: aload_0
     942: getfield      #159                // Field autoIDEnd:Ljavax/swing/JSpinner;
     945: aload         6
     947: invokevirtual #37                 // Method javax/swing/JPanel.add:(Ljava/awt/Component;Ljava/lang/Object;)V
     950: aload         6
     952: iconst_1
     953: putfield      #25                 // Field java/awt/GridBagConstraints.gridx:I
     956: aload         6
     958: iconst_5
     959: putfield      #26                 // Field java/awt/GridBagConstraints.gridy:I
     962: aload         6
     964: iconst_2
     965: putfield      #27                 // Field java/awt/GridBagConstraints.gridwidth:I
     968: aload         6
     970: iconst_2
     971: putfield      #29                 // Field java/awt/GridBagConstraints.fill:I
     974: aload         6
     976: dconst_1
     977: putfield      #71                 // Field java/awt/GridBagConstraints.weighty:D
     980: aload_0
     981: new           #162                // class javax/swing/JCheckBox
     984: dup
     985: ldc           #163                // String Remember last ID between Protg sessions
     987: invokespecial #164                // Method javax/swing/JCheckBox."<init>":(Ljava/lang/String;)V
     990: putfield      #165                // Field saveIterativeIds:Ljavax/swing/JCheckBox;
     993: aload_0
     994: getfield      #165                // Field saveIterativeIds:Ljavax/swing/JCheckBox;
     997: invokestatic  #166                // Method org/protege/editor/owl/model/entity/EntityCreationPreferences.getSaveAutoIDStart:()Z
    1000: invokevirtual #167                // Method javax/swing/JCheckBox.setSelected:(Z)V
    1003: aload_0
    1004: getfield      #165                // Field saveIterativeIds:Ljavax/swing/JCheckBox;
    1007: aload_0
    1008: getfield      #114                // Field iterativeButton:Ljavax/swing/JRadioButton;
    1011: invokevirtual #148                // Method javax/swing/JRadioButton.isSelected:()Z
    1014: invokevirtual #168                // Method javax/swing/JCheckBox.setEnabled:(Z)V
    1017: aload         5
    1019: aload_0
    1020: getfield      #165                // Field saveIterativeIds:Ljavax/swing/JCheckBox;
    1023: aload         6
    1025: invokevirtual #37                 // Method javax/swing/JPanel.add:(Ljava/awt/Component;Ljava/lang/Object;)V
    1028: aload         6
    1030: iconst_2
    1031: putfield      #25                 // Field java/awt/GridBagConstraints.gridx:I
    1034: aload         6
    1036: iconst_0
    1037: putfield      #26                 // Field java/awt/GridBagConstraints.gridy:I
    1040: aload         6
    1042: iconst_2
    1043: putfield      #29                 // Field java/awt/GridBagConstraints.fill:I
    1046: aload         6
    1048: dconst_1
    1049: putfield      #46                 // Field java/awt/GridBagConstraints.weightx:D
    1052: aload         6
    1054: dconst_0
    1055: putfield      #71                 // Field java/awt/GridBagConstraints.weighty:D
    1058: aload         5
    1060: new           #34                 // class javax/swing/JLabel
    1063: dup
    1064: ldc           #169                // String
    1066: invokespecial #36                 // Method javax/swing/JLabel."<init>":(Ljava/lang/String;)V
    1069: invokevirtual #120                // Method javax/swing/JPanel.add:(Ljava/awt/Component;)Ljava/awt/Component;
    1072: pop
    1073: aload_0
    1074: aload_0
    1075: getfield      #73                 // Field autoIDIriFragment:Ljavax/swing/JRadioButton;
    1078: invokevirtual #148                // Method javax/swing/JRadioButton.isSelected:()Z
    1081: invokespecial #170                // Method enableAutoGeneratedIDPanel:(Z)V
    1084: aload_0
    1085: aload_0
    1086: getfield      #73                 // Field autoIDIriFragment:Ljavax/swing/JRadioButton;
    1089: invokevirtual #148                // Method javax/swing/JRadioButton.isSelected:()Z
    1092: invokespecial #171                // Method enableLabelCreationPanel:(Z)V
    1095: aload_1
    1096: aload_2
    1097: ldc           #172                // String Before
    1099: invokevirtual #37                 // Method javax/swing/JPanel.add:(Ljava/awt/Component;Ljava/lang/Object;)V
    1102: aload_1
    1103: aload         5
    1105: ldc           #173                // String Center
    1107: invokevirtual #37                 // Method javax/swing/JPanel.add:(Ljava/awt/Component;Ljava/lang/Object;)V
    1110: aload_0
    1111: getfield      #106                // Field autoGeneratedIDPanel:Ljavax/swing/JPanel;
    1114: aload_1
    1115: invokevirtual #120                // Method javax/swing/JPanel.add:(Ljava/awt/Component;)Ljava/awt/Component;
    1118: pop
    1119: aload_0
    1120: getfield      #106                // Field autoGeneratedIDPanel:Ljavax/swing/JPanel;
    1123: areturn

  private void enableAutoGeneratedIDPanel(boolean);
    Code:
       0: aload_0
       1: getfield      #139                // Field autoIDDigitCount:Ljavax/swing/JSpinner;
       4: iload_1
       5: invokevirtual #154                // Method javax/swing/JSpinner.setEnabled:(Z)V
       8: aload_0
       9: getfield      #159                // Field autoIDEnd:Ljavax/swing/JSpinner;
      12: iload_1
      13: invokevirtual #154                // Method javax/swing/JSpinner.setEnabled:(Z)V
      16: aload_0
      17: getfield      #124                // Field autoIDPrefix:Ljavax/swing/JTextField;
      20: iload_1
      21: invokevirtual #174                // Method javax/swing/JTextField.setEnabled:(Z)V
      24: aload_0
      25: getfield      #152                // Field autoIDStart:Ljavax/swing/JSpinner;
      28: iload_1
      29: invokevirtual #154                // Method javax/swing/JSpinner.setEnabled:(Z)V
      32: aload_0
      33: getfield      #129                // Field autoIDSuffix:Ljavax/swing/JTextField;
      36: iload_1
      37: invokevirtual #174                // Method javax/swing/JTextField.setEnabled:(Z)V
      40: aload_0
      41: getfield      #106                // Field autoGeneratedIDPanel:Ljavax/swing/JPanel;
      44: iload_1
      45: invokevirtual #175                // Method javax/swing/JPanel.setEnabled:(Z)V
      48: aload_0
      49: getfield      #132                // Field digitCountLabel:Ljavax/swing/JLabel;
      52: iload_1
      53: invokevirtual #149                // Method javax/swing/JLabel.setEnabled:(Z)V
      56: aload_0
      57: getfield      #158                // Field endLabel:Ljavax/swing/JLabel;
      60: iload_1
      61: invokevirtual #149                // Method javax/swing/JLabel.setEnabled:(Z)V
      64: aload_0
      65: getfield      #114                // Field iterativeButton:Ljavax/swing/JRadioButton;
      68: iload_1
      69: invokevirtual #176                // Method javax/swing/JRadioButton.setEnabled:(Z)V
      72: aload_0
      73: getfield      #123                // Field prefixLabel:Ljavax/swing/JLabel;
      76: iload_1
      77: invokevirtual #149                // Method javax/swing/JLabel.setEnabled:(Z)V
      80: aload_0
      81: getfield      #165                // Field saveIterativeIds:Ljavax/swing/JCheckBox;
      84: iload_1
      85: invokevirtual #168                // Method javax/swing/JCheckBox.setEnabled:(Z)V
      88: aload_0
      89: getfield      #147                // Field startLabel:Ljavax/swing/JLabel;
      92: iload_1
      93: invokevirtual #149                // Method javax/swing/JLabel.setEnabled:(Z)V
      96: aload_0
      97: getfield      #128                // Field suffixLabel:Ljavax/swing/JLabel;
     100: iload_1
     101: invokevirtual #149                // Method javax/swing/JLabel.setEnabled:(Z)V
     104: aload_0
     105: getfield      #116                // Field uniqueIdButton:Ljavax/swing/JRadioButton;
     108: iload_1
     109: invokevirtual #176                // Method javax/swing/JRadioButton.setEnabled:(Z)V
     112: aload_0
     113: aload_0
     114: getfield      #114                // Field iterativeButton:Ljavax/swing/JRadioButton;
     117: invokevirtual #148                // Method javax/swing/JRadioButton.isSelected:()Z
     120: ifeq          137
     123: aload_0
     124: getfield      #114                // Field iterativeButton:Ljavax/swing/JRadioButton;
     127: invokevirtual #177                // Method javax/swing/JRadioButton.isEnabled:()Z
     130: ifeq          137
     133: iconst_1
     134: goto          138
     137: iconst_0
     138: invokespecial #178                // Method enableNumericIterativeOptions:(Z)V
     141: return

  private void enableLabelCreationPanel(boolean);
    Code:
       0: aload_0
       1: getfield      #96                 // Field annotationSelectButton:Ljavax/swing/JButton;
       4: iload_1
       5: invokevirtual #179                // Method javax/swing/JButton.setEnabled:(Z)V
       8: aload_0
       9: getfield      #103                // Field annotationLangSelector:Ljavax/swing/JComboBox;
      12: iload_1
      13: invokevirtual #180                // Method javax/swing/JComboBox.setEnabled:(Z)V
      16: aload_0
      17: getfield      #82                 // Field customLabelButton:Ljavax/swing/JRadioButton;
      20: iload_1
      21: invokevirtual #176                // Method javax/swing/JRadioButton.setEnabled:(Z)V
      24: aload_0
      25: getfield      #78                 // Field sameAsRendererLabelButton:Ljavax/swing/JRadioButton;
      28: iload_1
      29: invokevirtual #176                // Method javax/swing/JRadioButton.setEnabled:(Z)V
      32: aload_0
      33: getfield      #86                 // Field annotationIriLabel:Ljavax/swing/JTextField;
      36: iload_1
      37: invokevirtual #174                // Method javax/swing/JTextField.setEnabled:(Z)V
      40: return

  private void enableNumericIterativeOptions(boolean);
    Code:
       0: aload_0
       1: getfield      #147                // Field startLabel:Ljavax/swing/JLabel;
       4: iload_1
       5: invokevirtual #149                // Method javax/swing/JLabel.setEnabled:(Z)V
       8: aload_0
       9: getfield      #152                // Field autoIDStart:Ljavax/swing/JSpinner;
      12: iload_1
      13: invokevirtual #154                // Method javax/swing/JSpinner.setEnabled:(Z)V
      16: aload_0
      17: getfield      #158                // Field endLabel:Ljavax/swing/JLabel;
      20: iload_1
      21: invokevirtual #149                // Method javax/swing/JLabel.setEnabled:(Z)V
      24: aload_0
      25: getfield      #159                // Field autoIDEnd:Ljavax/swing/JSpinner;
      28: iload_1
      29: invokevirtual #154                // Method javax/swing/JSpinner.setEnabled:(Z)V
      32: aload_0
      33: getfield      #165                // Field saveIterativeIds:Ljavax/swing/JCheckBox;
      36: iload_1
      37: invokevirtual #168                // Method javax/swing/JCheckBox.setEnabled:(Z)V
      40: return

  public void actionPerformed(java.awt.event.ActionEvent);
    Code:
       0: aload_1
       1: invokevirtual #181                // Method java/awt/event/ActionEvent.getSource:()Ljava/lang/Object;
       4: astore_2
       5: aload_2
       6: aload_0
       7: getfield      #114                // Field iterativeButton:Ljavax/swing/JRadioButton;
      10: if_acmpne     21
      13: aload_0
      14: iconst_1
      15: invokespecial #178                // Method enableNumericIterativeOptions:(Z)V
      18: goto          34
      21: aload_2
      22: aload_0
      23: getfield      #116                // Field uniqueIdButton:Ljavax/swing/JRadioButton;
      26: if_acmpne     34
      29: aload_0
      30: iconst_0
      31: invokespecial #178                // Method enableNumericIterativeOptions:(Z)V
      34: return

  public void applyChanges();
    Code:
       0: aload_0
       1: getfield      #45                 // Field iriBaseSpecifiedIri:Ljavax/swing/JRadioButton;
       4: invokevirtual #148                // Method javax/swing/JRadioButton.isSelected:()Z
       7: invokestatic  #182                // Method org/protege/editor/owl/model/entity/EntityCreationPreferences.setUseDefaultBaseIRI:(Z)V
      10: new           #183                // class java/net/URI
      13: dup
      14: aload_0
      15: getfield      #49                 // Field iriDefaultBaseField:Ljavax/swing/JTextField;
      18: invokevirtual #184                // Method javax/swing/JTextField.getText:()Ljava/lang/String;
      21: invokespecial #185                // Method java/net/URI."<init>":(Ljava/lang/String;)V
      24: invokestatic  #186                // Method org/semanticweb/owlapi/model/IRI.create:(Ljava/net/URI;)Lorg/semanticweb/owlapi/model/IRI;
      27: astore_1
      28: aload_1
      29: invokestatic  #187                // Method org/protege/editor/owl/model/entity/EntityCreationPreferences.setDefaultBaseIRI:(Lorg/semanticweb/owlapi/model/IRI;)V
      32: goto          55
      35: astore_1
      36: aload_0
      37: getfield      #4                  // Field logger:Lorg/slf4j/Logger;
      40: ldc           #189                // String Ignoring invalid base IRI ({})
      42: aload_0
      43: getfield      #49                 // Field iriDefaultBaseField:Ljavax/swing/JTextField;
      46: invokevirtual #184                // Method javax/swing/JTextField.getText:()Ljava/lang/String;
      49: aload_1
      50: invokeinterface #190,  4          // InterfaceMethod org/slf4j/Logger.error:(Ljava/lang/String;Ljava/lang/Object;Ljava/lang/Object;)V
      55: aload_0
      56: getfield      #58                 // Field hashButton:Ljavax/swing/JRadioButton;
      59: invokevirtual #148                // Method javax/swing/JRadioButton.isSelected:()Z
      62: ifeq          73
      65: ldc           #57                 // String #
      67: invokestatic  #191                // Method org/protege/editor/owl/model/entity/EntityCreationPreferences.setDefaultSeparator:(Ljava/lang/String;)V
      70: goto          106
      73: aload_0
      74: getfield      #62                 // Field slashButton:Ljavax/swing/JRadioButton;
      77: invokevirtual #148                // Method javax/swing/JRadioButton.isSelected:()Z
      80: ifeq          91
      83: ldc           #61                 // String /
      85: invokestatic  #191                // Method org/protege/editor/owl/model/entity/EntityCreationPreferences.setDefaultSeparator:(Ljava/lang/String;)V
      88: goto          106
      91: aload_0
      92: getfield      #64                 // Field colonButton:Ljavax/swing/JRadioButton;
      95: invokevirtual #148                // Method javax/swing/JRadioButton.isSelected:()Z
      98: ifeq          106
     101: ldc           #63                 // String :
     103: invokestatic  #191                // Method org/protege/editor/owl/model/entity/EntityCreationPreferences.setDefaultSeparator:(Ljava/lang/String;)V
     106: aload_0
     107: getfield      #73                 // Field autoIDIriFragment:Ljavax/swing/JRadioButton;
     110: invokevirtual #148                // Method javax/swing/JRadioButton.isSelected:()Z
     113: invokestatic  #192                // Method org/protege/editor/owl/model/entity/EntityCreationPreferences.setFragmentAutoGenerated:(Z)V
     116: aload_0
     117: getfield      #73                 // Field autoIDIriFragment:Ljavax/swing/JRadioButton;
     120: invokevirtual #148                // Method javax/swing/JRadioButton.isSelected:()Z
     123: invokestatic  #193                // Method org/protege/editor/owl/model/entity/EntityCreationPreferences.setGenerateNameLabel:(Z)V
     126: iconst_0
     127: invokestatic  #194                // Method org/protege/editor/owl/model/entity/EntityCreationPreferences.setGenerateIDLabel:(Z)V
     130: aload_0
     131: getfield      #78                 // Field sameAsRendererLabelButton:Ljavax/swing/JRadioButton;
     134: invokevirtual #148                // Method javax/swing/JRadioButton.isSelected:()Z
     137: ifeq          145
     140: ldc           #79                 // class org/protege/editor/owl/model/entity/MatchRendererLabelDescriptor
     142: invokestatic  #195                // Method org/protege/editor/owl/model/entity/EntityCreationPreferences.setLabelDescriptorClass:(Ljava/lang/Class;)V
     145: aload_0
     146: getfield      #82                 // Field customLabelButton:Ljavax/swing/JRadioButton;
     149: invokevirtual #148                // Method javax/swing/JRadioButton.isSelected:()Z
     152: ifeq          160
     155: ldc           #83                 // class org/protege/editor/owl/model/entity/CustomLabelDescriptor
     157: invokestatic  #195                // Method org/protege/editor/owl/model/entity/EntityCreationPreferences.setLabelDescriptorClass:(Ljava/lang/Class;)V
     160: aload_0
     161: getfield      #86                 // Field annotationIriLabel:Ljavax/swing/JTextField;
     164: invokevirtual #184                // Method javax/swing/JTextField.getText:()Ljava/lang/String;
     167: invokestatic  #196                // Method org/semanticweb/owlapi/model/IRI.create:(Ljava/lang/String;)Lorg/semanticweb/owlapi/model/IRI;
     170: invokestatic  #197                // Method org/protege/editor/owl/model/entity/EntityCreationPreferences.setNameLabelIRI:(Lorg/semanticweb/owlapi/model/IRI;)V
     173: aload_0
     174: getfield      #103                // Field annotationLangSelector:Ljavax/swing/JComboBox;
     177: invokevirtual #198                // Method javax/swing/JComboBox.getSelectedItem:()Ljava/lang/Object;
     180: astore_1
     181: aload_1
     182: ifnull        204
     185: aload_1
     186: ldc           #169                // String
     188: invokevirtual #80                 // Method java/lang/Object.equals:(Ljava/lang/Object;)Z
     191: ifne          204
     194: aload_1
     195: checkcast     #199                // class java/lang/String
     198: invokestatic  #200                // Method org/protege/editor/owl/model/entity/EntityCreationPreferences.setNameLabelLang:(Ljava/lang/String;)V
     201: goto          208
     204: aconst_null
     205: invokestatic  #200                // Method org/protege/editor/owl/model/entity/EntityCreationPreferences.setNameLabelLang:(Ljava/lang/String;)V
     208: aload_0
     209: getfield      #114                // Field iterativeButton:Ljavax/swing/JRadioButton;
     212: invokevirtual #148                // Method javax/swing/JRadioButton.isSelected:()Z
     215: ifeq          223
     218: ldc           #118                // class org/protege/editor/owl/model/entity/IterativeAutoIDGenerator
     220: invokestatic  #201                // Method org/protege/editor/owl/model/entity/EntityCreationPreferences.setAutoIDGeneratorClass:(Ljava/lang/Class;)V
     223: aload_0
     224: getfield      #116                // Field uniqueIdButton:Ljavax/swing/JRadioButton;
     227: invokevirtual #148                // Method javax/swing/JRadioButton.isSelected:()Z
     230: ifeq          238
     233: ldc           #119                // class org/protege/editor/owl/model/entity/UniqueIdGenerator
     235: invokestatic  #201                // Method org/protege/editor/owl/model/entity/EntityCreationPreferences.setAutoIDGeneratorClass:(Ljava/lang/Class;)V
     238: aload_0
     239: getfield      #152                // Field autoIDStart:Ljavax/swing/JSpinner;
     242: invokevirtual #202                // Method javax/swing/JSpinner.getValue:()Ljava/lang/Object;
     245: checkcast     #150                // class java/lang/Integer
     248: invokevirtual #203                // Method java/lang/Integer.intValue:()I
     251: invokestatic  #204                // Method org/protege/editor/owl/model/entity/EntityCreationPreferences.setAutoIDStart:(I)V
     254: aload_0
     255: getfield      #159                // Field autoIDEnd:Ljavax/swing/JSpinner;
     258: invokevirtual #202                // Method javax/swing/JSpinner.getValue:()Ljava/lang/Object;
     261: checkcast     #150                // class java/lang/Integer
     264: invokevirtual #203                // Method java/lang/Integer.intValue:()I
     267: invokestatic  #205                // Method org/protege/editor/owl/model/entity/EntityCreationPreferences.setAutoIDEnd:(I)V
     270: aload_0
     271: getfield      #139                // Field autoIDDigitCount:Ljavax/swing/JSpinner;
     274: invokevirtual #202                // Method javax/swing/JSpinner.getValue:()Ljava/lang/Object;
     277: checkcast     #150                // class java/lang/Integer
     280: invokevirtual #203                // Method java/lang/Integer.intValue:()I
     283: invokestatic  #206                // Method org/protege/editor/owl/model/entity/EntityCreationPreferences.setAutoIDDigitCount:(I)V
     286: aload_0
     287: getfield      #124                // Field autoIDPrefix:Ljavax/swing/JTextField;
     290: invokevirtual #184                // Method javax/swing/JTextField.getText:()Ljava/lang/String;
     293: invokestatic  #207                // Method org/protege/editor/owl/model/entity/EntityCreationPreferences.setPrefix:(Ljava/lang/String;)V
     296: aload_0
     297: getfield      #129                // Field autoIDSuffix:Ljavax/swing/JTextField;
     300: invokevirtual #184                // Method javax/swing/JTextField.getText:()Ljava/lang/String;
     303: invokestatic  #208                // Method org/protege/editor/owl/model/entity/EntityCreationPreferences.setSuffix:(Ljava/lang/String;)V
     306: aload_0
     307: getfield      #165                // Field saveIterativeIds:Ljavax/swing/JCheckBox;
     310: invokevirtual #209                // Method javax/swing/JCheckBox.isSelected:()Z
     313: invokestatic  #210                // Method org/protege/editor/owl/model/entity/EntityCreationPreferences.setSaveAutoIDStart:(Z)V
     316: return
    Exception table:
       from    to  target type
          10    32    35   Class java/net/URISyntaxException

  private void handleActionEndWithID();
    Code:
       0: aload_0
       1: getfield      #73                 // Field autoIDIriFragment:Ljavax/swing/JRadioButton;
       4: invokevirtual #148                // Method javax/swing/JRadioButton.isSelected:()Z
       7: istore_1
       8: aload_0
       9: iload_1
      10: invokespecial #170                // Method enableAutoGeneratedIDPanel:(Z)V
      13: aload_0
      14: iload_1
      15: invokespecial #171                // Method enableLabelCreationPanel:(Z)V
      18: return

  private void handleActionEndWithName();
    Code:
       0: aload_0
       1: getfield      #67                 // Field nameAsIriFragment:Ljavax/swing/JRadioButton;
       4: invokevirtual #148                // Method javax/swing/JRadioButton.isSelected:()Z
       7: istore_1
       8: iload_1
       9: ifeq          22
      12: aload_0
      13: iconst_0
      14: invokespecial #170                // Method enableAutoGeneratedIDPanel:(Z)V
      17: aload_0
      18: iconst_0
      19: invokespecial #171                // Method enableLabelCreationPanel:(Z)V
      22: return

  protected void handleSelectAnnotation();
    Code:
       0: new           #99                 // class org/protege/editor/owl/ui/UIHelper
       3: dup
       4: aload_0
       5: invokevirtual #100                // Method getOWLEditorKit:()Lorg/protege/editor/owl/OWLEditorKit;
       8: invokespecial #101                // Method org/protege/editor/owl/ui/UIHelper."<init>":(Lorg/protege/editor/owl/OWLEditorKit;)V
      11: invokevirtual #211                // Method org/protege/editor/owl/ui/UIHelper.pickAnnotationProperty:()Lorg/semanticweb/owlapi/model/OWLAnnotationProperty;
      14: astore_1
      15: aload_1
      16: ifnull        43
      19: aload_0
      20: aload_1
      21: invokeinterface #212,  1          // InterfaceMethod org/semanticweb/owlapi/model/OWLAnnotationProperty.getIRI:()Lorg/semanticweb/owlapi/model/IRI;
      26: putfield      #5                  // Field labelAnnotation:Lorg/semanticweb/owlapi/model/IRI;
      29: aload_0
      30: getfield      #86                 // Field annotationIriLabel:Ljavax/swing/JTextField;
      33: aload_0
      34: getfield      #5                  // Field labelAnnotation:Lorg/semanticweb/owlapi/model/IRI;
      37: invokevirtual #51                 // Method org/semanticweb/owlapi/model/IRI.toString:()Ljava/lang/String;
      40: invokevirtual #52                 // Method javax/swing/JTextField.setText:(Ljava/lang/String;)V
      43: return

  public org.semanticweb.owlapi.model.IRI getFirstRendererLabel();
    Code:
       0: invokestatic  #213                // Method org/protege/editor/owl/ui/renderer/OWLRendererPreferences.getInstance:()Lorg/protege/editor/owl/ui/renderer/OWLRendererPreferences;
       3: invokevirtual #214                // Method org/protege/editor/owl/ui/renderer/OWLRendererPreferences.getAnnotationIRIs:()Ljava/util/List;
       6: astore_1
       7: aload_1
       8: invokeinterface #215,  1          // InterfaceMethod java/util/List.isEmpty:()Z
      13: ifne          27
      16: aload_1
      17: iconst_0
      18: invokeinterface #216,  2          // InterfaceMethod java/util/List.get:(I)Ljava/lang/Object;
      23: checkcast     #217                // class org/semanticweb/owlapi/model/IRI
      26: areturn
      27: getstatic     #88                 // Field org/semanticweb/owlapi/vocab/OWLRDFVocabulary.RDFS_LABEL:Lorg/semanticweb/owlapi/vocab/OWLRDFVocabulary;
      30: invokevirtual #89                 // Method org/semanticweb/owlapi/vocab/OWLRDFVocabulary.getIRI:()Lorg/semanticweb/owlapi/model/IRI;
      33: areturn

  public void dispose() throws java.lang.Exception;
    Code:
       0: return

  private void lambda$createAutoGeneratedIDPanel$3(javax.swing.event.ChangeEvent);
    Code:
       0: aload_0
       1: getfield      #159                // Field autoIDEnd:Ljavax/swing/JSpinner;
       4: invokevirtual #202                // Method javax/swing/JSpinner.getValue:()Ljava/lang/Object;
       7: checkcast     #150                // class java/lang/Integer
      10: invokevirtual #203                // Method java/lang/Integer.intValue:()I
      13: iconst_m1
      14: if_icmpeq     60
      17: aload_0
      18: getfield      #159                // Field autoIDEnd:Ljavax/swing/JSpinner;
      21: invokevirtual #202                // Method javax/swing/JSpinner.getValue:()Ljava/lang/Object;
      24: checkcast     #150                // class java/lang/Integer
      27: invokevirtual #203                // Method java/lang/Integer.intValue:()I
      30: aload_0
      31: getfield      #152                // Field autoIDStart:Ljavax/swing/JSpinner;
      34: invokevirtual #202                // Method javax/swing/JSpinner.getValue:()Ljava/lang/Object;
      37: checkcast     #150                // class java/lang/Integer
      40: invokevirtual #203                // Method java/lang/Integer.intValue:()I
      43: if_icmpgt     60
      46: aload_0
      47: getfield      #152                // Field autoIDStart:Ljavax/swing/JSpinner;
      50: aload_0
      51: getfield      #159                // Field autoIDEnd:Ljavax/swing/JSpinner;
      54: invokevirtual #202                // Method javax/swing/JSpinner.getValue:()Ljava/lang/Object;
      57: invokevirtual #142                // Method javax/swing/JSpinner.setValue:(Ljava/lang/Object;)V
      60: return

  private void lambda$createAutoGeneratedIDPanel$2(javax.swing.event.ChangeEvent);
    Code:
       0: aload_0
       1: getfield      #159                // Field autoIDEnd:Ljavax/swing/JSpinner;
       4: invokevirtual #202                // Method javax/swing/JSpinner.getValue:()Ljava/lang/Object;
       7: checkcast     #150                // class java/lang/Integer
      10: invokevirtual #203                // Method java/lang/Integer.intValue:()I
      13: iconst_m1
      14: if_icmpeq     60
      17: aload_0
      18: getfield      #159                // Field autoIDEnd:Ljavax/swing/JSpinner;
      21: invokevirtual #202                // Method javax/swing/JSpinner.getValue:()Ljava/lang/Object;
      24: checkcast     #150                // class java/lang/Integer
      27: invokevirtual #203                // Method java/lang/Integer.intValue:()I
      30: aload_0
      31: getfield      #152                // Field autoIDStart:Ljavax/swing/JSpinner;
      34: invokevirtual #202                // Method javax/swing/JSpinner.getValue:()Ljava/lang/Object;
      37: checkcast     #150                // class java/lang/Integer
      40: invokevirtual #203                // Method java/lang/Integer.intValue:()I
      43: if_icmpgt     60
      46: aload_0
      47: getfield      #159                // Field autoIDEnd:Ljavax/swing/JSpinner;
      50: aload_0
      51: getfield      #152                // Field autoIDStart:Ljavax/swing/JSpinner;
      54: invokevirtual #202                // Method javax/swing/JSpinner.getValue:()Ljava/lang/Object;
      57: invokevirtual #142                // Method javax/swing/JSpinner.setValue:(Ljava/lang/Object;)V
      60: return

  private void lambda$createEntityIriPanel$1(java.awt.event.ActionEvent);
    Code:
       0: aload_0
       1: invokespecial #218                // Method handleActionEndWithID:()V
       4: return

  private void lambda$createEntityIriPanel$0(java.awt.event.ActionEvent);
    Code:
       0: aload_0
       1: invokespecial #219                // Method handleActionEndWithName:()V
       4: return
}
