Compiled from "DefaultErrorHandlingPolicies.java"
public class org.eclipse.jdt.internal.compiler.DefaultErrorHandlingPolicies {
  public org.eclipse.jdt.internal.compiler.DefaultErrorHandlingPolicies();
    Code:
       0: aload_0
       1: invokespecial #8                  // Method java/lang/Object."<init>":()V
       4: return

  public static org.eclipse.jdt.internal.compiler.IErrorHandlingPolicy exitAfterAllProblems();
    Code:
       0: new           #16                 // class org/eclipse/jdt/internal/compiler/DefaultErrorHandlingPolicies$1
       3: dup
       4: invokespecial #18                 // Method org/eclipse/jdt/internal/compiler/DefaultErrorHandlingPolicies$1."<init>":()V
       7: areturn

  public static org.eclipse.jdt.internal.compiler.IErrorHandlingPolicy exitOnFirstError();
    Code:
       0: new           #20                 // class org/eclipse/jdt/internal/compiler/DefaultErrorHandlingPolicies$2
       3: dup
       4: invokespecial #22                 // Method org/eclipse/jdt/internal/compiler/DefaultErrorHandlingPolicies$2."<init>":()V
       7: areturn

  public static org.eclipse.jdt.internal.compiler.IErrorHandlingPolicy proceedOnFirstError();
    Code:
       0: new           #24                 // class org/eclipse/jdt/internal/compiler/DefaultErrorHandlingPolicies$3
       3: dup
       4: invokespecial #26                 // Method org/eclipse/jdt/internal/compiler/DefaultErrorHandlingPolicies$3."<init>":()V
       7: areturn

  public static org.eclipse.jdt.internal.compiler.IErrorHandlingPolicy proceedWithAllProblems();
    Code:
       0: new           #28                 // class org/eclipse/jdt/internal/compiler/DefaultErrorHandlingPolicies$4
       3: dup
       4: invokespecial #30                 // Method org/eclipse/jdt/internal/compiler/DefaultErrorHandlingPolicies$4."<init>":()V
       7: areturn

  public static org.eclipse.jdt.internal.compiler.IErrorHandlingPolicy ignoreAllProblems();
    Code:
       0: new           #32                 // class org/eclipse/jdt/internal/compiler/DefaultErrorHandlingPolicies$5
       3: dup
       4: invokespecial #34                 // Method org/eclipse/jdt/internal/compiler/DefaultErrorHandlingPolicies$5."<init>":()V
       7: areturn
}
