Compiled from "ContextFactory.java"
public abstract class net.oneandone.inline.internal.ContextFactory {
  private final java.util.List<net.oneandone.inline.internal.Argument> arguments;

  public net.oneandone.inline.internal.ContextFactory(java.util.List<net.oneandone.inline.internal.Argument>);
    Code:
       0: aload_0
       1: invokespecial #1                  // Method java/lang/Object."<init>":()V
       4: aload_0
       5: aload_1
       6: putfield      #2                  // Field arguments:Ljava/util/List;
       9: return

  public java.util.List<net.oneandone.inline.internal.Argument> arguments();
    Code:
       0: aload_0
       1: getfield      #2                  // Field arguments:Ljava/util/List;
       4: areturn

  public abstract java.lang.Object newInstance(java.util.Map<net.oneandone.inline.internal.Context, java.lang.Object>) throws java.lang.Throwable;
}
