Compiled from "Handle.java"
public class net.oneandone.inline.internal.Handle$InstanceHandle extends net.oneandone.inline.internal.Handle {
  private final java.lang.Object instance;

  public net.oneandone.inline.internal.Handle$InstanceHandle(java.lang.Object);
    Code:
       0: aload_0
       1: invokespecial #1                  // Method net/oneandone/inline/internal/Handle."<init>":()V
       4: aload_0
       5: aload_1
       6: putfield      #2                  // Field instance:Ljava/lang/Object;
       9: return

  public java.lang.Class<?> clazz();
    Code:
       0: aload_0
       1: getfield      #2                  // Field instance:Ljava/lang/Object;
       4: invokevirtual #3                  // Method java/lang/Object.getClass:()Ljava/lang/Class;
       7: areturn

  public net.oneandone.inline.internal.ContextFactory compile(net.oneandone.inline.internal.Context, net.oneandone.inline.internal.Repository, java.util.List<net.oneandone.inline.internal.Source>);
    Code:
       0: aload_3
       1: invokeinterface #4,  1            // InterfaceMethod java/util/List.isEmpty:()Z
       6: ifne          42
       9: new           #5                  // class net/oneandone/inline/internal/InvalidCliException
      12: dup
      13: new           #6                  // class java/lang/StringBuilder
      16: dup
      17: invokespecial #7                  // Method java/lang/StringBuilder."<init>":()V
      20: ldc           #8                  // String cannot apply constructor argument to an instance of class
      22: invokevirtual #9                  // Method java/lang/StringBuilder.append:(Ljava/lang/String;)Ljava/lang/StringBuilder;
      25: aload_0
      26: getfield      #2                  // Field instance:Ljava/lang/Object;
      29: invokevirtual #3                  // Method java/lang/Object.getClass:()Ljava/lang/Class;
      32: invokevirtual #10                 // Method java/lang/StringBuilder.append:(Ljava/lang/Object;)Ljava/lang/StringBuilder;
      35: invokevirtual #11                 // Method java/lang/StringBuilder.toString:()Ljava/lang/String;
      38: invokespecial #12                 // Method net/oneandone/inline/internal/InvalidCliException."<init>":(Ljava/lang/String;)V
      41: athrow
      42: new           #13                 // class net/oneandone/inline/internal/Handle$IdentityContextFactory
      45: dup
      46: aload_0
      47: getfield      #2                  // Field instance:Ljava/lang/Object;
      50: invokespecial #14                 // Method net/oneandone/inline/internal/Handle$IdentityContextFactory."<init>":(Ljava/lang/Object;)V
      53: areturn
}
