public class org.bouncycastle.i18n.filter.UntrustedInput {
  protected java.lang.Object input;

  public org.bouncycastle.i18n.filter.UntrustedInput(java.lang.Object);
    Code:
       0: aload_0
       1: invokespecial #19                 // Method java/lang/Object."<init>":()V
       4: aload_0
       5: aload_1
       6: putfield      #18                 // Field input:Ljava/lang/Object;
       9: return

  public java.lang.Object getInput();
    Code:
       0: aload_0
       1: getfield      #18                 // Field input:Ljava/lang/Object;
       4: areturn

  public java.lang.String getString();
    Code:
       0: aload_0
       1: getfield      #18                 // Field input:Ljava/lang/Object;
       4: invokevirtual #20                 // Method java/lang/Object.toString:()Ljava/lang/String;
       7: areturn

  public java.lang.String toString();
    Code:
       0: aload_0
       1: getfield      #18                 // Field input:Ljava/lang/Object;
       4: invokevirtual #20                 // Method java/lang/Object.toString:()Ljava/lang/String;
       7: areturn
}
