Compiled from "DefaultPermissionFactory.java"
class org.jboss.as.controller.access.rbac.DefaultPermissionFactory$NoPermissionsCollection$1 implements java.util.Enumeration<java.security.Permission> {
  final org.jboss.as.controller.access.rbac.DefaultPermissionFactory$NoPermissionsCollection this$0;

  org.jboss.as.controller.access.rbac.DefaultPermissionFactory$NoPermissionsCollection$1(org.jboss.as.controller.access.rbac.DefaultPermissionFactory$NoPermissionsCollection);
    Code:
       0: aload_0
       1: aload_1
       2: putfield      #1                  // Field this$0:Lorg/jboss/as/controller/access/rbac/DefaultPermissionFactory$NoPermissionsCollection;
       5: aload_0
       6: invokespecial #2                  // Method java/lang/Object."<init>":()V
       9: return

  public boolean hasMoreElements();
    Code:
       0: iconst_0
       1: ireturn

  public java.security.Permission nextElement();
    Code:
       0: new           #3                  // class java/util/NoSuchElementException
       3: dup
       4: invokespecial #4                  // Method java/util/NoSuchElementException."<init>":()V
       7: athrow

  public java.lang.Object nextElement();
    Code:
       0: aload_0
       1: invokevirtual #5                  // Method nextElement:()Ljava/security/Permission;
       4: areturn
}
