Compiled from "GlobalEnablementBuilder.java"
public class org.jboss.weld.bootstrap.enablement.GlobalEnablementBuilder extends org.jboss.weld.bootstrap.api.helpers.AbstractBootstrapService {
  private final java.util.List<org.jboss.weld.bootstrap.enablement.GlobalEnablementBuilder$Item> alternatives;

  private final java.util.List<org.jboss.weld.bootstrap.enablement.GlobalEnablementBuilder$Item> interceptors;

  private final java.util.List<org.jboss.weld.bootstrap.enablement.GlobalEnablementBuilder$Item> decorators;

  private volatile java.util.Map<java.lang.Class<?>, java.lang.Integer> cachedAlternativeMap;

  private volatile boolean sorted;

  public org.jboss.weld.bootstrap.enablement.GlobalEnablementBuilder();
    Code:
       0: aload_0
       1: invokespecial #4                  // Method org/jboss/weld/bootstrap/api/helpers/AbstractBootstrapService."<init>":()V
       4: aload_0
       5: new           #5                  // class java/util/ArrayList
       8: dup
       9: invokespecial #6                  // Method java/util/ArrayList."<init>":()V
      12: invokestatic  #7                  // Method java/util/Collections.synchronizedList:(Ljava/util/List;)Ljava/util/List;
      15: putfield      #3                  // Field alternatives:Ljava/util/List;
      18: aload_0
      19: new           #5                  // class java/util/ArrayList
      22: dup
      23: invokespecial #6                  // Method java/util/ArrayList."<init>":()V
      26: invokestatic  #7                  // Method java/util/Collections.synchronizedList:(Ljava/util/List;)Ljava/util/List;
      29: putfield      #2                  // Field interceptors:Ljava/util/List;
      32: aload_0
      33: new           #5                  // class java/util/ArrayList
      36: dup
      37: invokespecial #6                  // Method java/util/ArrayList."<init>":()V
      40: invokestatic  #7                  // Method java/util/Collections.synchronizedList:(Ljava/util/List;)Ljava/util/List;
      43: putfield      #1                  // Field decorators:Ljava/util/List;
      46: return

  private void addItem(java.util.List<org.jboss.weld.bootstrap.enablement.GlobalEnablementBuilder$Item>, java.lang.Class<?>, int);
    Code:
       0: aload_1
       1: new           #8                  // class org/jboss/weld/bootstrap/enablement/GlobalEnablementBuilder$Item
       4: dup
       5: aload_2
       6: iload_3
       7: invokestatic  #9                  // Method java/lang/Integer.valueOf:(I)Ljava/lang/Integer;
      10: aconst_null
      11: invokespecial #10                 // Method org/jboss/weld/bootstrap/enablement/GlobalEnablementBuilder$Item."<init>":(Ljava/lang/Class;Ljava/lang/Integer;Lorg/jboss/weld/bootstrap/enablement/GlobalEnablementBuilder$1;)V
      14: invokeinterface #11,  2           // InterfaceMethod java/util/List.add:(Ljava/lang/Object;)Z
      19: pop
      20: return

  public void addAlternative(java.lang.Class<?>, int);
    Code:
       0: aload_0
       1: aload_0
       2: getfield      #3                  // Field alternatives:Ljava/util/List;
       5: aload_1
       6: iload_2
       7: invokespecial #12                 // Method addItem:(Ljava/util/List;Ljava/lang/Class;I)V
      10: return

  public void addInterceptor(java.lang.Class<?>, int);
    Code:
       0: aload_0
       1: aload_0
       2: getfield      #2                  // Field interceptors:Ljava/util/List;
       5: aload_1
       6: iload_2
       7: invokespecial #12                 // Method addItem:(Ljava/util/List;Ljava/lang/Class;I)V
      10: return

  public void addDecorator(java.lang.Class<?>, int);
    Code:
       0: aload_0
       1: aload_0
       2: getfield      #1                  // Field decorators:Ljava/util/List;
       5: aload_1
       6: iload_2
       7: invokespecial #12                 // Method addItem:(Ljava/util/List;Ljava/lang/Class;I)V
      10: return

  public java.util.List<java.lang.Class<?>> getAlternativeList();
    Code:
       0: aload_0
       1: invokespecial #13                 // Method initialize:()V
       4: new           #14                 // class org/jboss/weld/bootstrap/enablement/GlobalEnablementBuilder$1
       7: dup
       8: aload_0
       9: invokespecial #15                 // Method org/jboss/weld/bootstrap/enablement/GlobalEnablementBuilder$1."<init>":(Lorg/jboss/weld/bootstrap/enablement/GlobalEnablementBuilder;)V
      12: areturn

  public java.util.List<java.lang.Class<?>> getInterceptorList();
    Code:
       0: aload_0
       1: invokespecial #13                 // Method initialize:()V
       4: new           #16                 // class org/jboss/weld/bootstrap/enablement/GlobalEnablementBuilder$2
       7: dup
       8: aload_0
       9: invokespecial #17                 // Method org/jboss/weld/bootstrap/enablement/GlobalEnablementBuilder$2."<init>":(Lorg/jboss/weld/bootstrap/enablement/GlobalEnablementBuilder;)V
      12: areturn

  public java.util.List<java.lang.Class<?>> getDecoratorList();
    Code:
       0: aload_0
       1: invokespecial #13                 // Method initialize:()V
       4: new           #18                 // class org/jboss/weld/bootstrap/enablement/GlobalEnablementBuilder$3
       7: dup
       8: aload_0
       9: invokespecial #19                 // Method org/jboss/weld/bootstrap/enablement/GlobalEnablementBuilder$3."<init>":(Lorg/jboss/weld/bootstrap/enablement/GlobalEnablementBuilder;)V
      12: areturn

  private java.util.Map<java.lang.Class<?>, java.lang.Integer> getGlobalAlternativeMap();
    Code:
       0: aload_0
       1: getfield      #20                 // Field cachedAlternativeMap:Ljava/util/Map;
       4: ifnonnull     75
       7: new           #21                 // class java/util/HashMap
      10: dup
      11: invokespecial #22                 // Method java/util/HashMap."<init>":()V
      14: astore_1
      15: aload_0
      16: getfield      #3                  // Field alternatives:Ljava/util/List;
      19: invokeinterface #23,  1           // InterfaceMethod java/util/List.listIterator:()Ljava/util/ListIterator;
      24: astore_2
      25: aload_2
      26: invokeinterface #24,  1           // InterfaceMethod java/util/ListIterator.hasNext:()Z
      31: ifeq          67
      34: aload_2
      35: invokeinterface #25,  1           // InterfaceMethod java/util/ListIterator.next:()Ljava/lang/Object;
      40: checkcast     #8                  // class org/jboss/weld/bootstrap/enablement/GlobalEnablementBuilder$Item
      43: astore_3
      44: aload_1
      45: aload_3
      46: invokestatic  #26                 // Method org/jboss/weld/bootstrap/enablement/GlobalEnablementBuilder$Item.access$000:(Lorg/jboss/weld/bootstrap/enablement/GlobalEnablementBuilder$Item;)Ljava/lang/Class;
      49: aload_2
      50: invokeinterface #27,  1           // InterfaceMethod java/util/ListIterator.previousIndex:()I
      55: invokestatic  #9                  // Method java/lang/Integer.valueOf:(I)Ljava/lang/Integer;
      58: invokeinterface #28,  3           // InterfaceMethod java/util/Map.put:(Ljava/lang/Object;Ljava/lang/Object;)Ljava/lang/Object;
      63: pop
      64: goto          25
      67: aload_0
      68: aload_1
      69: invokestatic  #29                 // Method com/google/common/collect/ImmutableMap.copyOf:(Ljava/util/Map;)Lcom/google/common/collect/ImmutableMap;
      72: putfield      #20                 // Field cachedAlternativeMap:Ljava/util/Map;
      75: aload_0
      76: getfield      #20                 // Field cachedAlternativeMap:Ljava/util/Map;
      79: areturn

  private void initialize();
    Code:
       0: aload_0
       1: getfield      #30                 // Field sorted:Z
       4: ifne          33
       7: aload_0
       8: getfield      #3                  // Field alternatives:Ljava/util/List;
      11: invokestatic  #31                 // Method java/util/Collections.sort:(Ljava/util/List;)V
      14: aload_0
      15: getfield      #2                  // Field interceptors:Ljava/util/List;
      18: invokestatic  #31                 // Method java/util/Collections.sort:(Ljava/util/List;)V
      21: aload_0
      22: getfield      #1                  // Field decorators:Ljava/util/List;
      25: invokestatic  #31                 // Method java/util/Collections.sort:(Ljava/util/List;)V
      28: aload_0
      29: iconst_1
      30: putfield      #30                 // Field sorted:Z
      33: return

  public org.jboss.weld.bootstrap.enablement.ModuleEnablement createModuleEnablement(org.jboss.weld.bootstrap.BeanDeployment);
    Code:
       0: new           #32                 // class org/jboss/weld/bootstrap/enablement/GlobalEnablementBuilder$ClassLoader
       3: dup
       4: aload_1
       5: invokevirtual #33                 // Method org/jboss/weld/bootstrap/BeanDeployment.getBeanManager:()Lorg/jboss/weld/manager/BeanManagerImpl;
       8: invokevirtual #34                 // Method org/jboss/weld/manager/BeanManagerImpl.getServices:()Lorg/jboss/weld/bootstrap/api/ServiceRegistry;
      11: ldc           #35                 // class org/jboss/weld/resources/spi/ResourceLoader
      13: invokeinterface #36,  2           // InterfaceMethod org/jboss/weld/bootstrap/api/ServiceRegistry.get:(Ljava/lang/Class;)Lorg/jboss/weld/bootstrap/api/Service;
      18: checkcast     #35                 // class org/jboss/weld/resources/spi/ResourceLoader
      21: invokespecial #37                 // Method org/jboss/weld/bootstrap/enablement/GlobalEnablementBuilder$ClassLoader."<init>":(Lorg/jboss/weld/resources/spi/ResourceLoader;)V
      24: astore_2
      25: aload_1
      26: invokevirtual #38                 // Method org/jboss/weld/bootstrap/BeanDeployment.getBeanDeploymentArchive:()Lorg/jboss/weld/bootstrap/spi/BeanDeploymentArchive;
      29: invokeinterface #39,  1           // InterfaceMethod org/jboss/weld/bootstrap/spi/BeanDeploymentArchive.getBeansXml:()Lorg/jboss/weld/bootstrap/spi/BeansXml;
      34: astore_3
      35: aconst_null
      36: astore        4
      38: aconst_null
      39: astore        5
      41: aload_0
      42: invokevirtual #40                 // Method getInterceptorList:()Ljava/util/List;
      45: astore        6
      47: aload_0
      48: invokevirtual #41                 // Method getDecoratorList:()Ljava/util/List;
      51: astore        7
      53: invokestatic  #42                 // Method com/google/common/collect/ImmutableList.builder:()Lcom/google/common/collect/ImmutableList$Builder;
      56: astore        8
      58: aload         8
      60: aload         6
      62: invokevirtual #43                 // Method com/google/common/collect/ImmutableList$Builder.addAll:(Ljava/lang/Iterable;)Lcom/google/common/collect/ImmutableList$Builder;
      65: pop
      66: invokestatic  #42                 // Method com/google/common/collect/ImmutableList.builder:()Lcom/google/common/collect/ImmutableList$Builder;
      69: astore        9
      71: aload         9
      73: aload         7
      75: invokevirtual #43                 // Method com/google/common/collect/ImmutableList$Builder.addAll:(Ljava/lang/Iterable;)Lcom/google/common/collect/ImmutableList$Builder;
      78: pop
      79: aload_3
      80: ifnull        234
      83: aload_0
      84: aload_3
      85: invokeinterface #44,  1           // InterfaceMethod org/jboss/weld/bootstrap/spi/BeansXml.getEnabledInterceptors:()Ljava/util/List;
      90: getstatic     #45                 // Field org/jboss/weld/logging/ValidatorLogger.INTERCEPTOR_SPECIFIED_TWICE:Lorg/jboss/weld/logging/MessageCallback;
      93: invokespecial #46                 // Method checkForDuplicates:(Ljava/util/List;Lorg/jboss/weld/logging/MessageCallback;)V
      96: aload_0
      97: aload_3
      98: invokeinterface #47,  1           // InterfaceMethod org/jboss/weld/bootstrap/spi/BeansXml.getEnabledDecorators:()Ljava/util/List;
     103: getstatic     #48                 // Field org/jboss/weld/logging/ValidatorLogger.DECORATOR_SPECIFIED_TWICE:Lorg/jboss/weld/logging/MessageCallback;
     106: invokespecial #46                 // Method checkForDuplicates:(Ljava/util/List;Lorg/jboss/weld/logging/MessageCallback;)V
     109: aload_0
     110: aload_3
     111: invokeinterface #49,  1           // InterfaceMethod org/jboss/weld/bootstrap/spi/BeansXml.getEnabledAlternativeClasses:()Ljava/util/List;
     116: getstatic     #50                 // Field org/jboss/weld/logging/ValidatorLogger.ALTERNATIVE_CLASS_SPECIFIED_MULTIPLE_TIMES:Lorg/jboss/weld/logging/MessageCallback;
     119: invokespecial #46                 // Method checkForDuplicates:(Ljava/util/List;Lorg/jboss/weld/logging/MessageCallback;)V
     122: aload_0
     123: aload_3
     124: invokeinterface #51,  1           // InterfaceMethod org/jboss/weld/bootstrap/spi/BeansXml.getEnabledAlternativeStereotypes:()Ljava/util/List;
     129: getstatic     #52                 // Field org/jboss/weld/logging/ValidatorLogger.ALTERNATIVE_STEREOTYPE_SPECIFIED_MULTIPLE_TIMES:Lorg/jboss/weld/logging/MessageCallback;
     132: invokespecial #46                 // Method checkForDuplicates:(Ljava/util/List;Lorg/jboss/weld/logging/MessageCallback;)V
     135: aload_3
     136: invokeinterface #44,  1           // InterfaceMethod org/jboss/weld/bootstrap/spi/BeansXml.getEnabledInterceptors:()Ljava/util/List;
     141: aload_2
     142: invokestatic  #53                 // Method com/google/common/collect/Lists.transform:(Ljava/util/List;Lcom/google/common/base/Function;)Ljava/util/List;
     145: astore        10
     147: aload         8
     149: aload_0
     150: aload         10
     152: aload         6
     154: getstatic     #54                 // Field org/jboss/weld/logging/ValidatorLogger.INTERCEPTOR_ENABLED_FOR_APP_AND_ARCHIVE:Lorg/jboss/weld/logging/LogMessageCallback;
     157: aload_1
     158: invokespecial #55                 // Method filter:(Ljava/util/List;Ljava/util/List;Lorg/jboss/weld/logging/LogMessageCallback;Lorg/jboss/weld/bootstrap/BeanDeployment;)Ljava/util/List;
     161: invokevirtual #43                 // Method com/google/common/collect/ImmutableList$Builder.addAll:(Ljava/lang/Iterable;)Lcom/google/common/collect/ImmutableList$Builder;
     164: pop
     165: aload_3
     166: invokeinterface #47,  1           // InterfaceMethod org/jboss/weld/bootstrap/spi/BeansXml.getEnabledDecorators:()Ljava/util/List;
     171: aload_2
     172: invokestatic  #53                 // Method com/google/common/collect/Lists.transform:(Ljava/util/List;Lcom/google/common/base/Function;)Ljava/util/List;
     175: astore        11
     177: aload         9
     179: aload_0
     180: aload         11
     182: aload         7
     184: getstatic     #56                 // Field org/jboss/weld/logging/ValidatorLogger.DECORATOR_ENABLED_FOR_APP_AND_ARCHIVE:Lorg/jboss/weld/logging/LogMessageCallback;
     187: aload_1
     188: invokespecial #55                 // Method filter:(Ljava/util/List;Ljava/util/List;Lorg/jboss/weld/logging/LogMessageCallback;Lorg/jboss/weld/bootstrap/BeanDeployment;)Ljava/util/List;
     191: invokevirtual #43                 // Method com/google/common/collect/ImmutableList$Builder.addAll:(Ljava/lang/Iterable;)Lcom/google/common/collect/ImmutableList$Builder;
     194: pop
     195: aload_3
     196: invokeinterface #49,  1           // InterfaceMethod org/jboss/weld/bootstrap/spi/BeansXml.getEnabledAlternativeClasses:()Ljava/util/List;
     201: aload_2
     202: invokestatic  #53                 // Method com/google/common/collect/Lists.transform:(Ljava/util/List;Lcom/google/common/base/Function;)Ljava/util/List;
     205: invokestatic  #57                 // Method com/google/common/collect/ImmutableSet.copyOf:(Ljava/util/Collection;)Lcom/google/common/collect/ImmutableSet;
     208: astore        4
     210: aload_3
     211: invokeinterface #51,  1           // InterfaceMethod org/jboss/weld/bootstrap/spi/BeansXml.getEnabledAlternativeStereotypes:()Ljava/util/List;
     216: aload_2
     217: invokestatic  #53                 // Method com/google/common/collect/Lists.transform:(Ljava/util/List;Lcom/google/common/base/Function;)Ljava/util/List;
     220: invokestatic  #57                 // Method com/google/common/collect/ImmutableSet.copyOf:(Ljava/util/Collection;)Lcom/google/common/collect/ImmutableSet;
     223: invokestatic  #58                 // Method org/jboss/weld/util/reflection/Reflections.cast:(Ljava/lang/Object;)Ljava/lang/Object;
     226: checkcast     #59                 // class java/util/Set
     229: astore        5
     231: goto          244
     234: invokestatic  #60                 // Method java/util/Collections.emptySet:()Ljava/util/Set;
     237: astore        4
     239: invokestatic  #60                 // Method java/util/Collections.emptySet:()Ljava/util/Set;
     242: astore        5
     244: aload_0
     245: invokespecial #61                 // Method getGlobalAlternativeMap:()Ljava/util/Map;
     248: astore        10
     250: new           #62                 // class org/jboss/weld/bootstrap/enablement/ModuleEnablement
     253: dup
     254: aload         8
     256: invokevirtual #63                 // Method com/google/common/collect/ImmutableList$Builder.build:()Lcom/google/common/collect/ImmutableList;
     259: aload         9
     261: invokevirtual #63                 // Method com/google/common/collect/ImmutableList$Builder.build:()Lcom/google/common/collect/ImmutableList;
     264: aload         10
     266: aload         4
     268: aload         5
     270: invokespecial #64                 // Method org/jboss/weld/bootstrap/enablement/ModuleEnablement."<init>":(Ljava/util/List;Ljava/util/List;Ljava/util/Map;Ljava/util/Set;Ljava/util/Set;)V
     273: areturn

  public void cleanupAfterBoot();
    Code:
       0: aload_0
       1: getfield      #3                  // Field alternatives:Ljava/util/List;
       4: invokeinterface #65,  1           // InterfaceMethod java/util/List.clear:()V
       9: aload_0
      10: getfield      #2                  // Field interceptors:Ljava/util/List;
      13: invokeinterface #65,  1           // InterfaceMethod java/util/List.clear:()V
      18: aload_0
      19: getfield      #1                  // Field decorators:Ljava/util/List;
      22: invokeinterface #65,  1           // InterfaceMethod java/util/List.clear:()V
      27: return

  public java.lang.String toString();
    Code:
       0: new           #66                 // class java/lang/StringBuilder
       3: dup
       4: invokespecial #67                 // Method java/lang/StringBuilder."<init>":()V
       7: ldc           #68                 // String GlobalEnablementBuilder [alternatives=
       9: invokevirtual #69                 // Method java/lang/StringBuilder.append:(Ljava/lang/String;)Ljava/lang/StringBuilder;
      12: aload_0
      13: getfield      #3                  // Field alternatives:Ljava/util/List;
      16: invokevirtual #70                 // Method java/lang/StringBuilder.append:(Ljava/lang/Object;)Ljava/lang/StringBuilder;
      19: ldc           #71                 // String , interceptors=
      21: invokevirtual #69                 // Method java/lang/StringBuilder.append:(Ljava/lang/String;)Ljava/lang/StringBuilder;
      24: aload_0
      25: getfield      #2                  // Field interceptors:Ljava/util/List;
      28: invokevirtual #70                 // Method java/lang/StringBuilder.append:(Ljava/lang/Object;)Ljava/lang/StringBuilder;
      31: ldc           #72                 // String , decorators=
      33: invokevirtual #69                 // Method java/lang/StringBuilder.append:(Ljava/lang/String;)Ljava/lang/StringBuilder;
      36: aload_0
      37: getfield      #1                  // Field decorators:Ljava/util/List;
      40: invokevirtual #70                 // Method java/lang/StringBuilder.append:(Ljava/lang/Object;)Ljava/lang/StringBuilder;
      43: ldc           #73                 // String ]
      45: invokevirtual #69                 // Method java/lang/StringBuilder.append:(Ljava/lang/String;)Ljava/lang/StringBuilder;
      48: invokevirtual #74                 // Method java/lang/StringBuilder.toString:()Ljava/lang/String;
      51: areturn

  private <T> void checkForDuplicates(java.util.List<org.jboss.weld.bootstrap.spi.Metadata<T>>, org.jboss.weld.logging.MessageCallback<org.jboss.weld.exceptions.DeploymentException>);
    Code:
       0: new           #21                 // class java/util/HashMap
       3: dup
       4: invokespecial #22                 // Method java/util/HashMap."<init>":()V
       7: astore_3
       8: aload_1
       9: invokeinterface #75,  1           // InterfaceMethod java/util/List.iterator:()Ljava/util/Iterator;
      14: astore        4
      16: aload         4
      18: invokeinterface #76,  1           // InterfaceMethod java/util/Iterator.hasNext:()Z
      23: ifeq          100
      26: aload         4
      28: invokeinterface #77,  1           // InterfaceMethod java/util/Iterator.next:()Ljava/lang/Object;
      33: checkcast     #78                 // class org/jboss/weld/bootstrap/spi/Metadata
      36: astore        5
      38: aload_3
      39: aload         5
      41: invokeinterface #79,  1           // InterfaceMethod org/jboss/weld/bootstrap/spi/Metadata.getValue:()Ljava/lang/Object;
      46: aload         5
      48: invokeinterface #28,  3           // InterfaceMethod java/util/Map.put:(Ljava/lang/Object;Ljava/lang/Object;)Ljava/lang/Object;
      53: checkcast     #78                 // class org/jboss/weld/bootstrap/spi/Metadata
      56: astore        6
      58: aload         6
      60: ifnull        97
      63: aload_2
      64: iconst_3
      65: anewarray     #80                 // class java/lang/Object
      68: dup
      69: iconst_0
      70: aload         5
      72: invokeinterface #79,  1           // InterfaceMethod org/jboss/weld/bootstrap/spi/Metadata.getValue:()Ljava/lang/Object;
      77: aastore
      78: dup
      79: iconst_1
      80: aload         5
      82: aastore
      83: dup
      84: iconst_2
      85: aload         6
      87: aastore
      88: invokeinterface #81,  2           // InterfaceMethod org/jboss/weld/logging/MessageCallback.construct:([Ljava/lang/Object;)Ljava/lang/Object;
      93: checkcast     #82                 // class org/jboss/weld/exceptions/DeploymentException
      96: athrow
      97: goto          16
     100: return

  private <T> java.util.List<java.lang.Class<?>> filter(java.util.List<java.lang.Class<?>>, java.util.List<java.lang.Class<?>>, org.jboss.weld.logging.LogMessageCallback, org.jboss.weld.bootstrap.BeanDeployment);
    Code:
       0: aload_1
       1: invokeinterface #75,  1           // InterfaceMethod java/util/List.iterator:()Ljava/util/Iterator;
       6: astore        5
       8: aload         5
      10: invokeinterface #76,  1           // InterfaceMethod java/util/Iterator.hasNext:()Z
      15: ifeq          79
      18: aload         5
      20: invokeinterface #77,  1           // InterfaceMethod java/util/Iterator.next:()Ljava/lang/Object;
      25: checkcast     #83                 // class java/lang/Class
      28: astore        6
      30: aload_2
      31: aload         6
      33: invokeinterface #84,  2           // InterfaceMethod java/util/List.contains:(Ljava/lang/Object;)Z
      38: ifeq          76
      41: aload_3
      42: iconst_2
      43: anewarray     #80                 // class java/lang/Object
      46: dup
      47: iconst_0
      48: aload         6
      50: aastore
      51: dup
      52: iconst_1
      53: aload         4
      55: invokevirtual #38                 // Method org/jboss/weld/bootstrap/BeanDeployment.getBeanDeploymentArchive:()Lorg/jboss/weld/bootstrap/spi/BeanDeploymentArchive;
      58: invokeinterface #85,  1           // InterfaceMethod org/jboss/weld/bootstrap/spi/BeanDeploymentArchive.getId:()Ljava/lang/String;
      63: aastore
      64: invokeinterface #86,  2           // InterfaceMethod org/jboss/weld/logging/LogMessageCallback.log:([Ljava/lang/Object;)V
      69: aload         5
      71: invokeinterface #87,  1           // InterfaceMethod java/util/Iterator.remove:()V
      76: goto          8
      79: aload_1
      80: areturn

  static java.util.List access$500(org.jboss.weld.bootstrap.enablement.GlobalEnablementBuilder);
    Code:
       0: aload_0
       1: getfield      #3                  // Field alternatives:Ljava/util/List;
       4: areturn

  static java.util.List access$600(org.jboss.weld.bootstrap.enablement.GlobalEnablementBuilder);
    Code:
       0: aload_0
       1: getfield      #2                  // Field interceptors:Ljava/util/List;
       4: areturn

  static java.util.List access$700(org.jboss.weld.bootstrap.enablement.GlobalEnablementBuilder);
    Code:
       0: aload_0
       1: getfield      #1                  // Field decorators:Ljava/util/List;
       4: areturn
}
