Compiled from "ReasonerStatus.java"
final class org.protege.editor.owl.model.inference.ReasonerStatus$2 extends org.protege.editor.owl.model.inference.ReasonerStatus {
  org.protege.editor.owl.model.inference.ReasonerStatus$2(java.lang.String, int, java.lang.String, java.lang.String, java.lang.String);
    Code:
       0: aload_0
       1: aload_1
       2: iload_2
       3: aload_3
       4: aload         4
       6: aload         5
       8: aconst_null
       9: invokespecial #1                  // Method org/protege/editor/owl/model/inference/ReasonerStatus."<init>":(Ljava/lang/String;ILjava/lang/String;Ljava/lang/String;Ljava/lang/String;Lorg/protege/editor/owl/model/inference/ReasonerStatus$1;)V
      12: return

  public boolean isEnableInitialization();
    Code:
       0: iconst_1
       1: ireturn

  public boolean isEnableSynchronization();
    Code:
       0: iconst_0
       1: ireturn

  public boolean isEnableStop();
    Code:
       0: iconst_0
       1: ireturn
}
