Compiled from "Tuple.java"
public class org.assertj.core.groups.Tuple {
  private final java.util.List<java.lang.Object> datas;

  public org.assertj.core.groups.Tuple(java.lang.Object...);
    Code:
       0: aload_0
       1: invokespecial #13                 // Method java/lang/Object."<init>":()V
       4: aload_0
       5: invokestatic  #19                 // Method org/assertj/core/util/Lists.newArrayList:()Ljava/util/ArrayList;
       8: putfield      #21                 // Field datas:Ljava/util/List;
      11: aload_0
      12: getfield      #21                 // Field datas:Ljava/util/List;
      15: aload_1
      16: invokestatic  #27                 // Method java/util/Collections.addAll:(Ljava/util/Collection;[Ljava/lang/Object;)Z
      19: pop
      20: return

  public java.lang.Object[] toArray();
    Code:
       0: aload_0
       1: getfield      #21                 // Field datas:Ljava/util/List;
       4: invokeinterface #37,  1           // InterfaceMethod java/util/List.toArray:()[Ljava/lang/Object;
       9: areturn

  public java.util.List<java.lang.Object> toList();
    Code:
       0: aload_0
       1: getfield      #21                 // Field datas:Ljava/util/List;
       4: areturn

  public int hashCode();
    Code:
       0: bipush        31
       2: istore_1
       3: iconst_1
       4: istore_2
       5: bipush        31
       7: iload_2
       8: imul
       9: aload_0
      10: getfield      #21                 // Field datas:Ljava/util/List;
      13: invokeinterface #43,  1           // InterfaceMethod java/util/List.hashCode:()I
      18: iadd
      19: istore_2
      20: iload_2
      21: ireturn

  public boolean equals(java.lang.Object);
    Code:
       0: aload_0
       1: aload_1
       2: if_acmpne     7
       5: iconst_1
       6: ireturn
       7: aload_1
       8: ifnonnull     13
      11: iconst_0
      12: ireturn
      13: aload_1
      14: instanceof    #2                  // class org/assertj/core/groups/Tuple
      17: ifne          22
      20: iconst_0
      21: ireturn
      22: aload_1
      23: checkcast     #2                  // class org/assertj/core/groups/Tuple
      26: astore_2
      27: aload_0
      28: getfield      #21                 // Field datas:Ljava/util/List;
      31: invokeinterface #37,  1           // InterfaceMethod java/util/List.toArray:()[Ljava/lang/Object;
      36: aload_2
      37: getfield      #21                 // Field datas:Ljava/util/List;
      40: invokeinterface #37,  1           // InterfaceMethod java/util/List.toArray:()[Ljava/lang/Object;
      45: invokestatic  #54                 // Method org/assertj/core/util/Objects.areEqual:(Ljava/lang/Object;Ljava/lang/Object;)Z
      48: ireturn

  public java.lang.String toString();
    Code:
       0: getstatic     #65                 // Field org/assertj/core/configuration/ConfigurationProvider.CONFIGURATION_PROVIDER:Lorg/assertj/core/configuration/ConfigurationProvider;
       3: invokevirtual #69                 // Method org/assertj/core/configuration/ConfigurationProvider.representation:()Lorg/assertj/core/presentation/Representation;
       6: aload_0
       7: invokeinterface #75,  2           // InterfaceMethod org/assertj/core/presentation/Representation.toStringOf:(Ljava/lang/Object;)Ljava/lang/String;
      12: areturn

  public static org.assertj.core.groups.Tuple tuple(java.lang.Object...);
    Code:
       0: new           #2                  // class org/assertj/core/groups/Tuple
       3: dup
       4: aload_0
       5: invokespecial #79                 // Method "<init>":([Ljava/lang/Object;)V
       8: areturn
}
