Compiled from "AssertionRule.java"
final class software.amazon.awssdk.services.route53recoverycontrolconfig.model.AssertionRule$BuilderImpl implements software.amazon.awssdk.services.route53recoverycontrolconfig.model.AssertionRule$Builder {
  private java.util.List<java.lang.String> assertedControls;

  private java.lang.String controlPanelArn;

  private java.lang.String name;

  private software.amazon.awssdk.services.route53recoverycontrolconfig.model.RuleConfig ruleConfig;

  private java.lang.String safetyRuleArn;

  private java.lang.String status;

  private java.lang.Integer waitPeriodMs;

  private software.amazon.awssdk.services.route53recoverycontrolconfig.model.AssertionRule$BuilderImpl();
    Code:
       0: aload_0
       1: invokespecial #10                 // Method java/lang/Object."<init>":()V
       4: aload_0
       5: invokestatic  #11                 // Method software/amazon/awssdk/core/util/DefaultSdkAutoConstructList.getInstance:()Lsoftware/amazon/awssdk/core/util/DefaultSdkAutoConstructList;
       8: putfield      #9                  // Field assertedControls:Ljava/util/List;
      11: return

  private software.amazon.awssdk.services.route53recoverycontrolconfig.model.AssertionRule$BuilderImpl(software.amazon.awssdk.services.route53recoverycontrolconfig.model.AssertionRule);
    Code:
       0: aload_0
       1: invokespecial #10                 // Method java/lang/Object."<init>":()V
       4: aload_0
       5: invokestatic  #11                 // Method software/amazon/awssdk/core/util/DefaultSdkAutoConstructList.getInstance:()Lsoftware/amazon/awssdk/core/util/DefaultSdkAutoConstructList;
       8: putfield      #9                  // Field assertedControls:Ljava/util/List;
      11: aload_0
      12: aload_1
      13: invokestatic  #12                 // Method software/amazon/awssdk/services/route53recoverycontrolconfig/model/AssertionRule.access$900:(Lsoftware/amazon/awssdk/services/route53recoverycontrolconfig/model/AssertionRule;)Ljava/util/List;
      16: invokevirtual #13                 // Method assertedControls:(Ljava/util/Collection;)Lsoftware/amazon/awssdk/services/route53recoverycontrolconfig/model/AssertionRule$Builder;
      19: pop
      20: aload_0
      21: aload_1
      22: invokestatic  #14                 // Method software/amazon/awssdk/services/route53recoverycontrolconfig/model/AssertionRule.access$1000:(Lsoftware/amazon/awssdk/services/route53recoverycontrolconfig/model/AssertionRule;)Ljava/lang/String;
      25: invokevirtual #15                 // Method controlPanelArn:(Ljava/lang/String;)Lsoftware/amazon/awssdk/services/route53recoverycontrolconfig/model/AssertionRule$Builder;
      28: pop
      29: aload_0
      30: aload_1
      31: invokestatic  #16                 // Method software/amazon/awssdk/services/route53recoverycontrolconfig/model/AssertionRule.access$1100:(Lsoftware/amazon/awssdk/services/route53recoverycontrolconfig/model/AssertionRule;)Ljava/lang/String;
      34: invokevirtual #17                 // Method name:(Ljava/lang/String;)Lsoftware/amazon/awssdk/services/route53recoverycontrolconfig/model/AssertionRule$Builder;
      37: pop
      38: aload_0
      39: aload_1
      40: invokestatic  #18                 // Method software/amazon/awssdk/services/route53recoverycontrolconfig/model/AssertionRule.access$1200:(Lsoftware/amazon/awssdk/services/route53recoverycontrolconfig/model/AssertionRule;)Lsoftware/amazon/awssdk/services/route53recoverycontrolconfig/model/RuleConfig;
      43: invokevirtual #19                 // Method ruleConfig:(Lsoftware/amazon/awssdk/services/route53recoverycontrolconfig/model/RuleConfig;)Lsoftware/amazon/awssdk/services/route53recoverycontrolconfig/model/AssertionRule$Builder;
      46: pop
      47: aload_0
      48: aload_1
      49: invokestatic  #20                 // Method software/amazon/awssdk/services/route53recoverycontrolconfig/model/AssertionRule.access$1300:(Lsoftware/amazon/awssdk/services/route53recoverycontrolconfig/model/AssertionRule;)Ljava/lang/String;
      52: invokevirtual #21                 // Method safetyRuleArn:(Ljava/lang/String;)Lsoftware/amazon/awssdk/services/route53recoverycontrolconfig/model/AssertionRule$Builder;
      55: pop
      56: aload_0
      57: aload_1
      58: invokestatic  #22                 // Method software/amazon/awssdk/services/route53recoverycontrolconfig/model/AssertionRule.access$1400:(Lsoftware/amazon/awssdk/services/route53recoverycontrolconfig/model/AssertionRule;)Ljava/lang/String;
      61: invokevirtual #23                 // Method status:(Ljava/lang/String;)Lsoftware/amazon/awssdk/services/route53recoverycontrolconfig/model/AssertionRule$Builder;
      64: pop
      65: aload_0
      66: aload_1
      67: invokestatic  #24                 // Method software/amazon/awssdk/services/route53recoverycontrolconfig/model/AssertionRule.access$1500:(Lsoftware/amazon/awssdk/services/route53recoverycontrolconfig/model/AssertionRule;)Ljava/lang/Integer;
      70: invokevirtual #25                 // Method waitPeriodMs:(Ljava/lang/Integer;)Lsoftware/amazon/awssdk/services/route53recoverycontrolconfig/model/AssertionRule$Builder;
      73: pop
      74: return

  public final java.util.Collection<java.lang.String> getAssertedControls();
    Code:
       0: aload_0
       1: getfield      #9                  // Field assertedControls:Ljava/util/List;
       4: instanceof    #26                 // class software/amazon/awssdk/core/util/SdkAutoConstructList
       7: ifeq          12
      10: aconst_null
      11: areturn
      12: aload_0
      13: getfield      #9                  // Field assertedControls:Ljava/util/List;
      16: areturn

  public final void setAssertedControls(java.util.Collection<java.lang.String>);
    Code:
       0: aload_0
       1: aload_1
       2: invokestatic  #27                 // Method software/amazon/awssdk/services/route53recoverycontrolconfig/model/___listOf__stringCopier.copy:(Ljava/util/Collection;)Ljava/util/List;
       5: putfield      #9                  // Field assertedControls:Ljava/util/List;
       8: return

  public final software.amazon.awssdk.services.route53recoverycontrolconfig.model.AssertionRule$Builder assertedControls(java.util.Collection<java.lang.String>);
    Code:
       0: aload_0
       1: aload_1
       2: invokestatic  #27                 // Method software/amazon/awssdk/services/route53recoverycontrolconfig/model/___listOf__stringCopier.copy:(Ljava/util/Collection;)Ljava/util/List;
       5: putfield      #9                  // Field assertedControls:Ljava/util/List;
       8: aload_0
       9: areturn

  public final software.amazon.awssdk.services.route53recoverycontrolconfig.model.AssertionRule$Builder assertedControls(java.lang.String...);
    Code:
       0: aload_0
       1: aload_1
       2: invokestatic  #28                 // Method java/util/Arrays.asList:([Ljava/lang/Object;)Ljava/util/List;
       5: invokevirtual #13                 // Method assertedControls:(Ljava/util/Collection;)Lsoftware/amazon/awssdk/services/route53recoverycontrolconfig/model/AssertionRule$Builder;
       8: pop
       9: aload_0
      10: areturn

  public final java.lang.String getControlPanelArn();
    Code:
       0: aload_0
       1: getfield      #8                  // Field controlPanelArn:Ljava/lang/String;
       4: areturn

  public final void setControlPanelArn(java.lang.String);
    Code:
       0: aload_0
       1: aload_1
       2: putfield      #8                  // Field controlPanelArn:Ljava/lang/String;
       5: return

  public final software.amazon.awssdk.services.route53recoverycontrolconfig.model.AssertionRule$Builder controlPanelArn(java.lang.String);
    Code:
       0: aload_0
       1: aload_1
       2: putfield      #8                  // Field controlPanelArn:Ljava/lang/String;
       5: aload_0
       6: areturn

  public final java.lang.String getName();
    Code:
       0: aload_0
       1: getfield      #7                  // Field name:Ljava/lang/String;
       4: areturn

  public final void setName(java.lang.String);
    Code:
       0: aload_0
       1: aload_1
       2: putfield      #7                  // Field name:Ljava/lang/String;
       5: return

  public final software.amazon.awssdk.services.route53recoverycontrolconfig.model.AssertionRule$Builder name(java.lang.String);
    Code:
       0: aload_0
       1: aload_1
       2: putfield      #7                  // Field name:Ljava/lang/String;
       5: aload_0
       6: areturn

  public final software.amazon.awssdk.services.route53recoverycontrolconfig.model.RuleConfig$Builder getRuleConfig();
    Code:
       0: aload_0
       1: getfield      #6                  // Field ruleConfig:Lsoftware/amazon/awssdk/services/route53recoverycontrolconfig/model/RuleConfig;
       4: ifnull        17
       7: aload_0
       8: getfield      #6                  // Field ruleConfig:Lsoftware/amazon/awssdk/services/route53recoverycontrolconfig/model/RuleConfig;
      11: invokevirtual #29                 // Method software/amazon/awssdk/services/route53recoverycontrolconfig/model/RuleConfig.toBuilder:()Lsoftware/amazon/awssdk/services/route53recoverycontrolconfig/model/RuleConfig$Builder;
      14: goto          18
      17: aconst_null
      18: areturn

  public final void setRuleConfig(software.amazon.awssdk.services.route53recoverycontrolconfig.model.RuleConfig$BuilderImpl);
    Code:
       0: aload_0
       1: aload_1
       2: ifnull        12
       5: aload_1
       6: invokevirtual #30                 // Method software/amazon/awssdk/services/route53recoverycontrolconfig/model/RuleConfig$BuilderImpl.build:()Lsoftware/amazon/awssdk/services/route53recoverycontrolconfig/model/RuleConfig;
       9: goto          13
      12: aconst_null
      13: putfield      #6                  // Field ruleConfig:Lsoftware/amazon/awssdk/services/route53recoverycontrolconfig/model/RuleConfig;
      16: return

  public final software.amazon.awssdk.services.route53recoverycontrolconfig.model.AssertionRule$Builder ruleConfig(software.amazon.awssdk.services.route53recoverycontrolconfig.model.RuleConfig);
    Code:
       0: aload_0
       1: aload_1
       2: putfield      #6                  // Field ruleConfig:Lsoftware/amazon/awssdk/services/route53recoverycontrolconfig/model/RuleConfig;
       5: aload_0
       6: areturn

  public final java.lang.String getSafetyRuleArn();
    Code:
       0: aload_0
       1: getfield      #5                  // Field safetyRuleArn:Ljava/lang/String;
       4: areturn

  public final void setSafetyRuleArn(java.lang.String);
    Code:
       0: aload_0
       1: aload_1
       2: putfield      #5                  // Field safetyRuleArn:Ljava/lang/String;
       5: return

  public final software.amazon.awssdk.services.route53recoverycontrolconfig.model.AssertionRule$Builder safetyRuleArn(java.lang.String);
    Code:
       0: aload_0
       1: aload_1
       2: putfield      #5                  // Field safetyRuleArn:Ljava/lang/String;
       5: aload_0
       6: areturn

  public final java.lang.String getStatus();
    Code:
       0: aload_0
       1: getfield      #4                  // Field status:Ljava/lang/String;
       4: areturn

  public final void setStatus(java.lang.String);
    Code:
       0: aload_0
       1: aload_1
       2: putfield      #4                  // Field status:Ljava/lang/String;
       5: return

  public final software.amazon.awssdk.services.route53recoverycontrolconfig.model.AssertionRule$Builder status(java.lang.String);
    Code:
       0: aload_0
       1: aload_1
       2: putfield      #4                  // Field status:Ljava/lang/String;
       5: aload_0
       6: areturn

  public final software.amazon.awssdk.services.route53recoverycontrolconfig.model.AssertionRule$Builder status(software.amazon.awssdk.services.route53recoverycontrolconfig.model.Status);
    Code:
       0: aload_0
       1: aload_1
       2: ifnonnull     9
       5: aconst_null
       6: goto          13
       9: aload_1
      10: invokevirtual #31                 // Method software/amazon/awssdk/services/route53recoverycontrolconfig/model/Status.toString:()Ljava/lang/String;
      13: invokevirtual #23                 // Method status:(Ljava/lang/String;)Lsoftware/amazon/awssdk/services/route53recoverycontrolconfig/model/AssertionRule$Builder;
      16: pop
      17: aload_0
      18: areturn

  public final java.lang.Integer getWaitPeriodMs();
    Code:
       0: aload_0
       1: getfield      #3                  // Field waitPeriodMs:Ljava/lang/Integer;
       4: areturn

  public final void setWaitPeriodMs(java.lang.Integer);
    Code:
       0: aload_0
       1: aload_1
       2: putfield      #3                  // Field waitPeriodMs:Ljava/lang/Integer;
       5: return

  public final software.amazon.awssdk.services.route53recoverycontrolconfig.model.AssertionRule$Builder waitPeriodMs(java.lang.Integer);
    Code:
       0: aload_0
       1: aload_1
       2: putfield      #3                  // Field waitPeriodMs:Ljava/lang/Integer;
       5: aload_0
       6: areturn

  public software.amazon.awssdk.services.route53recoverycontrolconfig.model.AssertionRule build();
    Code:
       0: new           #32                 // class software/amazon/awssdk/services/route53recoverycontrolconfig/model/AssertionRule
       3: dup
       4: aload_0
       5: aconst_null
       6: invokespecial #33                 // Method software/amazon/awssdk/services/route53recoverycontrolconfig/model/AssertionRule."<init>":(Lsoftware/amazon/awssdk/services/route53recoverycontrolconfig/model/AssertionRule$BuilderImpl;Lsoftware/amazon/awssdk/services/route53recoverycontrolconfig/model/AssertionRule$1;)V
       9: areturn

  public java.util.List<software.amazon.awssdk.core.SdkField<?>> sdkFields();
    Code:
       0: invokestatic  #34                 // Method software/amazon/awssdk/services/route53recoverycontrolconfig/model/AssertionRule.access$1700:()Ljava/util/List;
       3: areturn

  public java.lang.Object build();
    Code:
       0: aload_0
       1: invokevirtual #35                 // Method build:()Lsoftware/amazon/awssdk/services/route53recoverycontrolconfig/model/AssertionRule;
       4: areturn

  static java.util.List access$000(software.amazon.awssdk.services.route53recoverycontrolconfig.model.AssertionRule$BuilderImpl);
    Code:
       0: aload_0
       1: getfield      #9                  // Field assertedControls:Ljava/util/List;
       4: areturn

  static java.lang.String access$100(software.amazon.awssdk.services.route53recoverycontrolconfig.model.AssertionRule$BuilderImpl);
    Code:
       0: aload_0
       1: getfield      #8                  // Field controlPanelArn:Ljava/lang/String;
       4: areturn

  static java.lang.String access$200(software.amazon.awssdk.services.route53recoverycontrolconfig.model.AssertionRule$BuilderImpl);
    Code:
       0: aload_0
       1: getfield      #7                  // Field name:Ljava/lang/String;
       4: areturn

  static software.amazon.awssdk.services.route53recoverycontrolconfig.model.RuleConfig access$300(software.amazon.awssdk.services.route53recoverycontrolconfig.model.AssertionRule$BuilderImpl);
    Code:
       0: aload_0
       1: getfield      #6                  // Field ruleConfig:Lsoftware/amazon/awssdk/services/route53recoverycontrolconfig/model/RuleConfig;
       4: areturn

  static java.lang.String access$400(software.amazon.awssdk.services.route53recoverycontrolconfig.model.AssertionRule$BuilderImpl);
    Code:
       0: aload_0
       1: getfield      #5                  // Field safetyRuleArn:Ljava/lang/String;
       4: areturn

  static java.lang.String access$500(software.amazon.awssdk.services.route53recoverycontrolconfig.model.AssertionRule$BuilderImpl);
    Code:
       0: aload_0
       1: getfield      #4                  // Field status:Ljava/lang/String;
       4: areturn

  static java.lang.Integer access$600(software.amazon.awssdk.services.route53recoverycontrolconfig.model.AssertionRule$BuilderImpl);
    Code:
       0: aload_0
       1: getfield      #3                  // Field waitPeriodMs:Ljava/lang/Integer;
       4: areturn

  software.amazon.awssdk.services.route53recoverycontrolconfig.model.AssertionRule$BuilderImpl(software.amazon.awssdk.services.route53recoverycontrolconfig.model.AssertionRule, software.amazon.awssdk.services.route53recoverycontrolconfig.model.AssertionRule$1);
    Code:
       0: aload_0
       1: aload_1
       2: invokespecial #2                  // Method "<init>":(Lsoftware/amazon/awssdk/services/route53recoverycontrolconfig/model/AssertionRule;)V
       5: return

  software.amazon.awssdk.services.route53recoverycontrolconfig.model.AssertionRule$BuilderImpl(software.amazon.awssdk.services.route53recoverycontrolconfig.model.AssertionRule$1);
    Code:
       0: aload_0
       1: invokespecial #1                  // Method "<init>":()V
       4: return
}
