Compiled from "ControlPanel.java"
final class software.amazon.awssdk.services.route53recoverycontrolconfig.model.ControlPanel$BuilderImpl implements software.amazon.awssdk.services.route53recoverycontrolconfig.model.ControlPanel$Builder {
  private java.lang.String clusterArn;

  private java.lang.String controlPanelArn;

  private java.lang.Boolean defaultControlPanel;

  private java.lang.String name;

  private java.lang.Integer routingControlCount;

  private java.lang.String status;

  private software.amazon.awssdk.services.route53recoverycontrolconfig.model.ControlPanel$BuilderImpl();
    Code:
       0: aload_0
       1: invokespecial #9                  // Method java/lang/Object."<init>":()V
       4: return

  private software.amazon.awssdk.services.route53recoverycontrolconfig.model.ControlPanel$BuilderImpl(software.amazon.awssdk.services.route53recoverycontrolconfig.model.ControlPanel);
    Code:
       0: aload_0
       1: invokespecial #9                  // Method java/lang/Object."<init>":()V
       4: aload_0
       5: aload_1
       6: invokestatic  #10                 // Method software/amazon/awssdk/services/route53recoverycontrolconfig/model/ControlPanel.access$800:(Lsoftware/amazon/awssdk/services/route53recoverycontrolconfig/model/ControlPanel;)Ljava/lang/String;
       9: invokevirtual #11                 // Method clusterArn:(Ljava/lang/String;)Lsoftware/amazon/awssdk/services/route53recoverycontrolconfig/model/ControlPanel$Builder;
      12: pop
      13: aload_0
      14: aload_1
      15: invokestatic  #12                 // Method software/amazon/awssdk/services/route53recoverycontrolconfig/model/ControlPanel.access$900:(Lsoftware/amazon/awssdk/services/route53recoverycontrolconfig/model/ControlPanel;)Ljava/lang/String;
      18: invokevirtual #13                 // Method controlPanelArn:(Ljava/lang/String;)Lsoftware/amazon/awssdk/services/route53recoverycontrolconfig/model/ControlPanel$Builder;
      21: pop
      22: aload_0
      23: aload_1
      24: invokestatic  #14                 // Method software/amazon/awssdk/services/route53recoverycontrolconfig/model/ControlPanel.access$1000:(Lsoftware/amazon/awssdk/services/route53recoverycontrolconfig/model/ControlPanel;)Ljava/lang/Boolean;
      27: invokevirtual #15                 // Method defaultControlPanel:(Ljava/lang/Boolean;)Lsoftware/amazon/awssdk/services/route53recoverycontrolconfig/model/ControlPanel$Builder;
      30: pop
      31: aload_0
      32: aload_1
      33: invokestatic  #16                 // Method software/amazon/awssdk/services/route53recoverycontrolconfig/model/ControlPanel.access$1100:(Lsoftware/amazon/awssdk/services/route53recoverycontrolconfig/model/ControlPanel;)Ljava/lang/String;
      36: invokevirtual #17                 // Method name:(Ljava/lang/String;)Lsoftware/amazon/awssdk/services/route53recoverycontrolconfig/model/ControlPanel$Builder;
      39: pop
      40: aload_0
      41: aload_1
      42: invokestatic  #18                 // Method software/amazon/awssdk/services/route53recoverycontrolconfig/model/ControlPanel.access$1200:(Lsoftware/amazon/awssdk/services/route53recoverycontrolconfig/model/ControlPanel;)Ljava/lang/Integer;
      45: invokevirtual #19                 // Method routingControlCount:(Ljava/lang/Integer;)Lsoftware/amazon/awssdk/services/route53recoverycontrolconfig/model/ControlPanel$Builder;
      48: pop
      49: aload_0
      50: aload_1
      51: invokestatic  #20                 // Method software/amazon/awssdk/services/route53recoverycontrolconfig/model/ControlPanel.access$1300:(Lsoftware/amazon/awssdk/services/route53recoverycontrolconfig/model/ControlPanel;)Ljava/lang/String;
      54: invokevirtual #21                 // Method status:(Ljava/lang/String;)Lsoftware/amazon/awssdk/services/route53recoverycontrolconfig/model/ControlPanel$Builder;
      57: pop
      58: return

  public final java.lang.String getClusterArn();
    Code:
       0: aload_0
       1: getfield      #8                  // Field clusterArn:Ljava/lang/String;
       4: areturn

  public final void setClusterArn(java.lang.String);
    Code:
       0: aload_0
       1: aload_1
       2: putfield      #8                  // Field clusterArn:Ljava/lang/String;
       5: return

  public final software.amazon.awssdk.services.route53recoverycontrolconfig.model.ControlPanel$Builder clusterArn(java.lang.String);
    Code:
       0: aload_0
       1: aload_1
       2: putfield      #8                  // Field clusterArn:Ljava/lang/String;
       5: aload_0
       6: areturn

  public final java.lang.String getControlPanelArn();
    Code:
       0: aload_0
       1: getfield      #7                  // Field controlPanelArn:Ljava/lang/String;
       4: areturn

  public final void setControlPanelArn(java.lang.String);
    Code:
       0: aload_0
       1: aload_1
       2: putfield      #7                  // Field controlPanelArn:Ljava/lang/String;
       5: return

  public final software.amazon.awssdk.services.route53recoverycontrolconfig.model.ControlPanel$Builder controlPanelArn(java.lang.String);
    Code:
       0: aload_0
       1: aload_1
       2: putfield      #7                  // Field controlPanelArn:Ljava/lang/String;
       5: aload_0
       6: areturn

  public final java.lang.Boolean getDefaultControlPanel();
    Code:
       0: aload_0
       1: getfield      #6                  // Field defaultControlPanel:Ljava/lang/Boolean;
       4: areturn

  public final void setDefaultControlPanel(java.lang.Boolean);
    Code:
       0: aload_0
       1: aload_1
       2: putfield      #6                  // Field defaultControlPanel:Ljava/lang/Boolean;
       5: return

  public final software.amazon.awssdk.services.route53recoverycontrolconfig.model.ControlPanel$Builder defaultControlPanel(java.lang.Boolean);
    Code:
       0: aload_0
       1: aload_1
       2: putfield      #6                  // Field defaultControlPanel:Ljava/lang/Boolean;
       5: aload_0
       6: areturn

  public final java.lang.String getName();
    Code:
       0: aload_0
       1: getfield      #5                  // Field name:Ljava/lang/String;
       4: areturn

  public final void setName(java.lang.String);
    Code:
       0: aload_0
       1: aload_1
       2: putfield      #5                  // Field name:Ljava/lang/String;
       5: return

  public final software.amazon.awssdk.services.route53recoverycontrolconfig.model.ControlPanel$Builder name(java.lang.String);
    Code:
       0: aload_0
       1: aload_1
       2: putfield      #5                  // Field name:Ljava/lang/String;
       5: aload_0
       6: areturn

  public final java.lang.Integer getRoutingControlCount();
    Code:
       0: aload_0
       1: getfield      #4                  // Field routingControlCount:Ljava/lang/Integer;
       4: areturn

  public final void setRoutingControlCount(java.lang.Integer);
    Code:
       0: aload_0
       1: aload_1
       2: putfield      #4                  // Field routingControlCount:Ljava/lang/Integer;
       5: return

  public final software.amazon.awssdk.services.route53recoverycontrolconfig.model.ControlPanel$Builder routingControlCount(java.lang.Integer);
    Code:
       0: aload_0
       1: aload_1
       2: putfield      #4                  // Field routingControlCount:Ljava/lang/Integer;
       5: aload_0
       6: areturn

  public final java.lang.String getStatus();
    Code:
       0: aload_0
       1: getfield      #3                  // Field status:Ljava/lang/String;
       4: areturn

  public final void setStatus(java.lang.String);
    Code:
       0: aload_0
       1: aload_1
       2: putfield      #3                  // Field status:Ljava/lang/String;
       5: return

  public final software.amazon.awssdk.services.route53recoverycontrolconfig.model.ControlPanel$Builder status(java.lang.String);
    Code:
       0: aload_0
       1: aload_1
       2: putfield      #3                  // Field status:Ljava/lang/String;
       5: aload_0
       6: areturn

  public final software.amazon.awssdk.services.route53recoverycontrolconfig.model.ControlPanel$Builder status(software.amazon.awssdk.services.route53recoverycontrolconfig.model.Status);
    Code:
       0: aload_0
       1: aload_1
       2: ifnonnull     9
       5: aconst_null
       6: goto          13
       9: aload_1
      10: invokevirtual #22                 // Method software/amazon/awssdk/services/route53recoverycontrolconfig/model/Status.toString:()Ljava/lang/String;
      13: invokevirtual #21                 // Method status:(Ljava/lang/String;)Lsoftware/amazon/awssdk/services/route53recoverycontrolconfig/model/ControlPanel$Builder;
      16: pop
      17: aload_0
      18: areturn

  public software.amazon.awssdk.services.route53recoverycontrolconfig.model.ControlPanel build();
    Code:
       0: new           #23                 // class software/amazon/awssdk/services/route53recoverycontrolconfig/model/ControlPanel
       3: dup
       4: aload_0
       5: aconst_null
       6: invokespecial #24                 // Method software/amazon/awssdk/services/route53recoverycontrolconfig/model/ControlPanel."<init>":(Lsoftware/amazon/awssdk/services/route53recoverycontrolconfig/model/ControlPanel$BuilderImpl;Lsoftware/amazon/awssdk/services/route53recoverycontrolconfig/model/ControlPanel$1;)V
       9: areturn

  public java.util.List<software.amazon.awssdk.core.SdkField<?>> sdkFields();
    Code:
       0: invokestatic  #25                 // Method software/amazon/awssdk/services/route53recoverycontrolconfig/model/ControlPanel.access$1500:()Ljava/util/List;
       3: areturn

  public java.lang.Object build();
    Code:
       0: aload_0
       1: invokevirtual #26                 // Method build:()Lsoftware/amazon/awssdk/services/route53recoverycontrolconfig/model/ControlPanel;
       4: areturn

  static java.lang.String access$000(software.amazon.awssdk.services.route53recoverycontrolconfig.model.ControlPanel$BuilderImpl);
    Code:
       0: aload_0
       1: getfield      #8                  // Field clusterArn:Ljava/lang/String;
       4: areturn

  static java.lang.String access$100(software.amazon.awssdk.services.route53recoverycontrolconfig.model.ControlPanel$BuilderImpl);
    Code:
       0: aload_0
       1: getfield      #7                  // Field controlPanelArn:Ljava/lang/String;
       4: areturn

  static java.lang.Boolean access$200(software.amazon.awssdk.services.route53recoverycontrolconfig.model.ControlPanel$BuilderImpl);
    Code:
       0: aload_0
       1: getfield      #6                  // Field defaultControlPanel:Ljava/lang/Boolean;
       4: areturn

  static java.lang.String access$300(software.amazon.awssdk.services.route53recoverycontrolconfig.model.ControlPanel$BuilderImpl);
    Code:
       0: aload_0
       1: getfield      #5                  // Field name:Ljava/lang/String;
       4: areturn

  static java.lang.Integer access$400(software.amazon.awssdk.services.route53recoverycontrolconfig.model.ControlPanel$BuilderImpl);
    Code:
       0: aload_0
       1: getfield      #4                  // Field routingControlCount:Ljava/lang/Integer;
       4: areturn

  static java.lang.String access$500(software.amazon.awssdk.services.route53recoverycontrolconfig.model.ControlPanel$BuilderImpl);
    Code:
       0: aload_0
       1: getfield      #3                  // Field status:Ljava/lang/String;
       4: areturn

  software.amazon.awssdk.services.route53recoverycontrolconfig.model.ControlPanel$BuilderImpl(software.amazon.awssdk.services.route53recoverycontrolconfig.model.ControlPanel, software.amazon.awssdk.services.route53recoverycontrolconfig.model.ControlPanel$1);
    Code:
       0: aload_0
       1: aload_1
       2: invokespecial #2                  // Method "<init>":(Lsoftware/amazon/awssdk/services/route53recoverycontrolconfig/model/ControlPanel;)V
       5: return

  software.amazon.awssdk.services.route53recoverycontrolconfig.model.ControlPanel$BuilderImpl(software.amazon.awssdk.services.route53recoverycontrolconfig.model.ControlPanel$1);
    Code:
       0: aload_0
       1: invokespecial #1                  // Method "<init>":()V
       4: return
}
