Compiled from "CreateClusterResponse.java"
public interface software.amazon.awssdk.services.route53recoverycontrolconfig.model.CreateClusterResponse$Builder extends software.amazon.awssdk.services.route53recoverycontrolconfig.model.Route53RecoveryControlConfigResponse$Builder, software.amazon.awssdk.core.SdkPojo, software.amazon.awssdk.utils.builder.CopyableBuilder<software.amazon.awssdk.services.route53recoverycontrolconfig.model.CreateClusterResponse$Builder, software.amazon.awssdk.services.route53recoverycontrolconfig.model.CreateClusterResponse> {
  public abstract software.amazon.awssdk.services.route53recoverycontrolconfig.model.CreateClusterResponse$Builder cluster(software.amazon.awssdk.services.route53recoverycontrolconfig.model.Cluster);

  public default software.amazon.awssdk.services.route53recoverycontrolconfig.model.CreateClusterResponse$Builder cluster(java.util.function.Consumer<software.amazon.awssdk.services.route53recoverycontrolconfig.model.Cluster$Builder>);
    Code:
       0: aload_0
       1: invokestatic  #1                  // Method software/amazon/awssdk/services/route53recoverycontrolconfig/model/Cluster.builder:()Lsoftware/amazon/awssdk/services/route53recoverycontrolconfig/model/Cluster$Builder;
       4: aload_1
       5: invokeinterface #2,  2            // InterfaceMethod software/amazon/awssdk/services/route53recoverycontrolconfig/model/Cluster$Builder.applyMutation:(Ljava/util/function/Consumer;)Lsoftware/amazon/awssdk/utils/builder/SdkBuilder;
      10: checkcast     #3                  // class software/amazon/awssdk/services/route53recoverycontrolconfig/model/Cluster$Builder
      13: invokeinterface #4,  1            // InterfaceMethod software/amazon/awssdk/services/route53recoverycontrolconfig/model/Cluster$Builder.build:()Ljava/lang/Object;
      18: checkcast     #5                  // class software/amazon/awssdk/services/route53recoverycontrolconfig/model/Cluster
      21: invokeinterface #6,  2            // InterfaceMethod cluster:(Lsoftware/amazon/awssdk/services/route53recoverycontrolconfig/model/Cluster;)Lsoftware/amazon/awssdk/services/route53recoverycontrolconfig/model/CreateClusterResponse$Builder;
      26: areturn
}
