Compiled from "ArrayCopy.java"
public final class org.jdom2.internal.ArrayCopy {
  private org.jdom2.internal.ArrayCopy();
    Code:
       0: aload_0
       1: invokespecial #1                  // Method java/lang/Object."<init>":()V
       4: return

  public static final <E> E[] copyOf(E[], int);
    Code:
       0: aload_0
       1: invokevirtual #2                  // Method java/lang/Object.getClass:()Ljava/lang/Class;
       4: invokevirtual #3                  // Method java/lang/Class.getComponentType:()Ljava/lang/Class;
       7: iload_1
       8: invokestatic  #4                  // Method java/lang/reflect/Array.newInstance:(Ljava/lang/Class;I)Ljava/lang/Object;
      11: checkcast     #5                  // class "[Ljava/lang/Object;"
      14: checkcast     #5                  // class "[Ljava/lang/Object;"
      17: astore_2
      18: aload_0
      19: iconst_0
      20: aload_2
      21: iconst_0
      22: iload_1
      23: aload_0
      24: arraylength
      25: if_icmpge     32
      28: iload_1
      29: goto          34
      32: aload_0
      33: arraylength
      34: invokestatic  #6                  // Method java/lang/System.arraycopy:(Ljava/lang/Object;ILjava/lang/Object;II)V
      37: aload_2
      38: areturn

  public static final <E> E[] copyOfRange(E[], int, int);
    Code:
       0: iload_2
       1: iload_1
       2: isub
       3: istore_3
       4: iload_3
       5: ifge          49
       8: new           #7                  // class java/lang/IllegalArgumentException
      11: dup
      12: new           #8                  // class java/lang/StringBuilder
      15: dup
      16: invokespecial #9                  // Method java/lang/StringBuilder."<init>":()V
      19: ldc           #10                 // String From(
      21: invokevirtual #11                 // Method java/lang/StringBuilder.append:(Ljava/lang/String;)Ljava/lang/StringBuilder;
      24: iload_1
      25: invokevirtual #12                 // Method java/lang/StringBuilder.append:(I)Ljava/lang/StringBuilder;
      28: ldc           #13                 // String ) > To (
      30: invokevirtual #11                 // Method java/lang/StringBuilder.append:(Ljava/lang/String;)Ljava/lang/StringBuilder;
      33: iload_2
      34: invokevirtual #12                 // Method java/lang/StringBuilder.append:(I)Ljava/lang/StringBuilder;
      37: ldc           #14                 // String )
      39: invokevirtual #11                 // Method java/lang/StringBuilder.append:(Ljava/lang/String;)Ljava/lang/StringBuilder;
      42: invokevirtual #15                 // Method java/lang/StringBuilder.toString:()Ljava/lang/String;
      45: invokespecial #16                 // Method java/lang/IllegalArgumentException."<init>":(Ljava/lang/String;)V
      48: athrow
      49: aload_0
      50: invokevirtual #2                  // Method java/lang/Object.getClass:()Ljava/lang/Class;
      53: invokevirtual #3                  // Method java/lang/Class.getComponentType:()Ljava/lang/Class;
      56: iload_3
      57: invokestatic  #4                  // Method java/lang/reflect/Array.newInstance:(Ljava/lang/Class;I)Ljava/lang/Object;
      60: checkcast     #5                  // class "[Ljava/lang/Object;"
      63: checkcast     #5                  // class "[Ljava/lang/Object;"
      66: astore        4
      68: iload_1
      69: iload_3
      70: iadd
      71: aload_0
      72: arraylength
      73: if_icmple     83
      76: aload_0
      77: arraylength
      78: iload_1
      79: isub
      80: goto          84
      83: iload_3
      84: istore        5
      86: aload_0
      87: iload_1
      88: aload         4
      90: iconst_0
      91: iload         5
      93: invokestatic  #6                  // Method java/lang/System.arraycopy:(Ljava/lang/Object;ILjava/lang/Object;II)V
      96: aload         4
      98: areturn

  public static final char[] copyOf(char[], int);
    Code:
       0: iload_1
       1: newarray       char
       3: astore_2
       4: aload_0
       5: iconst_0
       6: aload_2
       7: iconst_0
       8: iload_1
       9: aload_0
      10: arraylength
      11: if_icmpge     18
      14: iload_1
      15: goto          20
      18: aload_0
      19: arraylength
      20: invokestatic  #6                  // Method java/lang/System.arraycopy:(Ljava/lang/Object;ILjava/lang/Object;II)V
      23: aload_2
      24: areturn

  public static final int[] copyOf(int[], int);
    Code:
       0: iload_1
       1: newarray       int
       3: astore_2
       4: aload_0
       5: iconst_0
       6: aload_2
       7: iconst_0
       8: iload_1
       9: aload_0
      10: arraylength
      11: if_icmpge     18
      14: iload_1
      15: goto          20
      18: aload_0
      19: arraylength
      20: invokestatic  #6                  // Method java/lang/System.arraycopy:(Ljava/lang/Object;ILjava/lang/Object;II)V
      23: aload_2
      24: areturn

  public static final boolean[] copyOf(boolean[], int);
    Code:
       0: iload_1
       1: newarray       boolean
       3: astore_2
       4: aload_0
       5: iconst_0
       6: aload_2
       7: iconst_0
       8: iload_1
       9: aload_0
      10: arraylength
      11: if_icmpge     18
      14: iload_1
      15: goto          20
      18: aload_0
      19: arraylength
      20: invokestatic  #6                  // Method java/lang/System.arraycopy:(Ljava/lang/Object;ILjava/lang/Object;II)V
      23: aload_2
      24: areturn
}
