Compiled from "MetricData.java"
class io.mantisrx.server.worker.jobmaster.MetricData {
  private final java.lang.String jobId;

  private final int stage;

  private final int workerIndex;

  private final int workerNumber;

  private final java.lang.String metricGroupName;

  private final io.mantisrx.server.worker.jobmaster.GaugeData gauges;

  io.mantisrx.server.worker.jobmaster.MetricData(java.lang.String, int, int, int, java.lang.String, java.util.List<io.mantisrx.common.metrics.measurement.GaugeMeasurement>);
    Code:
       0: aload_0
       1: aload_1
       2: iload_2
       3: iload_3
       4: iload         4
       6: aload         5
       8: new           #1                  // class io/mantisrx/server/worker/jobmaster/GaugeData
      11: dup
      12: invokestatic  #2                  // Method java/lang/System.currentTimeMillis:()J
      15: aload         6
      17: invokespecial #3                  // Method io/mantisrx/server/worker/jobmaster/GaugeData."<init>":(JLjava/util/List;)V
      20: invokespecial #4                  // Method "<init>":(Ljava/lang/String;IIILjava/lang/String;Lio/mantisrx/server/worker/jobmaster/GaugeData;)V
      23: return

  io.mantisrx.server.worker.jobmaster.MetricData(java.lang.String, int, int, int, java.lang.String, io.mantisrx.server.worker.jobmaster.GaugeData);
    Code:
       0: aload_0
       1: invokespecial #5                  // Method java/lang/Object."<init>":()V
       4: aload_0
       5: aload_1
       6: putfield      #6                  // Field jobId:Ljava/lang/String;
       9: aload_0
      10: iload_2
      11: putfield      #7                  // Field stage:I
      14: aload_0
      15: iload_3
      16: putfield      #8                  // Field workerIndex:I
      19: aload_0
      20: iload         4
      22: putfield      #9                  // Field workerNumber:I
      25: aload_0
      26: aload         5
      28: putfield      #10                 // Field metricGroupName:Ljava/lang/String;
      31: aload_0
      32: aload         6
      34: putfield      #11                 // Field gauges:Lio/mantisrx/server/worker/jobmaster/GaugeData;
      37: return

  java.lang.String getJobId();
    Code:
       0: aload_0
       1: getfield      #6                  // Field jobId:Ljava/lang/String;
       4: areturn

  int getStage();
    Code:
       0: aload_0
       1: getfield      #7                  // Field stage:I
       4: ireturn

  int getWorkerIndex();
    Code:
       0: aload_0
       1: getfield      #8                  // Field workerIndex:I
       4: ireturn

  int getWorkerNumber();
    Code:
       0: aload_0
       1: getfield      #9                  // Field workerNumber:I
       4: ireturn

  public java.lang.String getMetricGroupName();
    Code:
       0: aload_0
       1: getfield      #10                 // Field metricGroupName:Ljava/lang/String;
       4: areturn

  public io.mantisrx.server.worker.jobmaster.GaugeData getGaugeData();
    Code:
       0: aload_0
       1: getfield      #11                 // Field gauges:Lio/mantisrx/server/worker/jobmaster/GaugeData;
       4: areturn

  public java.lang.String toString();
    Code:
       0: new           #12                 // class java/lang/StringBuilder
       3: dup
       4: invokespecial #13                 // Method java/lang/StringBuilder."<init>":()V
       7: ldc           #14                 // String MetricData{jobId=\'
       9: invokevirtual #15                 // Method java/lang/StringBuilder.append:(Ljava/lang/String;)Ljava/lang/StringBuilder;
      12: aload_0
      13: getfield      #6                  // Field jobId:Ljava/lang/String;
      16: invokevirtual #15                 // Method java/lang/StringBuilder.append:(Ljava/lang/String;)Ljava/lang/StringBuilder;
      19: bipush        39
      21: invokevirtual #16                 // Method java/lang/StringBuilder.append:(C)Ljava/lang/StringBuilder;
      24: ldc           #17                 // String , stage=
      26: invokevirtual #15                 // Method java/lang/StringBuilder.append:(Ljava/lang/String;)Ljava/lang/StringBuilder;
      29: aload_0
      30: getfield      #7                  // Field stage:I
      33: invokevirtual #18                 // Method java/lang/StringBuilder.append:(I)Ljava/lang/StringBuilder;
      36: ldc           #19                 // String , workerIndex=
      38: invokevirtual #15                 // Method java/lang/StringBuilder.append:(Ljava/lang/String;)Ljava/lang/StringBuilder;
      41: aload_0
      42: getfield      #8                  // Field workerIndex:I
      45: invokevirtual #18                 // Method java/lang/StringBuilder.append:(I)Ljava/lang/StringBuilder;
      48: ldc           #20                 // String , workerNumber=
      50: invokevirtual #15                 // Method java/lang/StringBuilder.append:(Ljava/lang/String;)Ljava/lang/StringBuilder;
      53: aload_0
      54: getfield      #9                  // Field workerNumber:I
      57: invokevirtual #18                 // Method java/lang/StringBuilder.append:(I)Ljava/lang/StringBuilder;
      60: ldc           #21                 // String , metricGroupName=\'
      62: invokevirtual #15                 // Method java/lang/StringBuilder.append:(Ljava/lang/String;)Ljava/lang/StringBuilder;
      65: aload_0
      66: getfield      #10                 // Field metricGroupName:Ljava/lang/String;
      69: invokevirtual #15                 // Method java/lang/StringBuilder.append:(Ljava/lang/String;)Ljava/lang/StringBuilder;
      72: bipush        39
      74: invokevirtual #16                 // Method java/lang/StringBuilder.append:(C)Ljava/lang/StringBuilder;
      77: ldc           #22                 // String , gauges=
      79: invokevirtual #15                 // Method java/lang/StringBuilder.append:(Ljava/lang/String;)Ljava/lang/StringBuilder;
      82: aload_0
      83: getfield      #11                 // Field gauges:Lio/mantisrx/server/worker/jobmaster/GaugeData;
      86: invokevirtual #23                 // Method java/lang/StringBuilder.append:(Ljava/lang/Object;)Ljava/lang/StringBuilder;
      89: bipush        125
      91: invokevirtual #16                 // Method java/lang/StringBuilder.append:(C)Ljava/lang/StringBuilder;
      94: invokevirtual #24                 // Method java/lang/StringBuilder.toString:()Ljava/lang/String;
      97: areturn
}
