Compiled from "DefineGrammarSymbols.java"
public class antlr.DefineGrammarSymbols implements antlr.ANTLRGrammarParseBehavior {
  protected java.util.Hashtable grammars;

  protected java.util.Hashtable tokenManagers;

  protected antlr.Grammar grammar;

  protected antlr.Tool tool;

  antlr.LLkAnalyzer analyzer;

  java.lang.String[] args;

  static final java.lang.String DEFAULT_TOKENMANAGER_NAME;

  protected java.util.Hashtable headerActions;

  antlr.Token thePreambleAction;

  java.lang.String language;

  protected int numLexers;

  protected int numParsers;

  protected int numTreeParsers;

  public antlr.DefineGrammarSymbols(antlr.Tool, java.lang.String[], antlr.LLkAnalyzer);
    Code:
       0: aload_0
       1: invokespecial #1                  // Method java/lang/Object."<init>":()V
       4: aload_0
       5: new           #2                  // class java/util/Hashtable
       8: dup
       9: invokespecial #3                  // Method java/util/Hashtable."<init>":()V
      12: putfield      #4                  // Field grammars:Ljava/util/Hashtable;
      15: aload_0
      16: new           #2                  // class java/util/Hashtable
      19: dup
      20: invokespecial #3                  // Method java/util/Hashtable."<init>":()V
      23: putfield      #5                  // Field tokenManagers:Ljava/util/Hashtable;
      26: aload_0
      27: new           #2                  // class java/util/Hashtable
      30: dup
      31: invokespecial #3                  // Method java/util/Hashtable."<init>":()V
      34: putfield      #6                  // Field headerActions:Ljava/util/Hashtable;
      37: aload_0
      38: new           #7                  // class antlr/CommonToken
      41: dup
      42: iconst_0
      43: ldc           #8                  // String
      45: invokespecial #9                  // Method antlr/CommonToken."<init>":(ILjava/lang/String;)V
      48: putfield      #10                 // Field thePreambleAction:Lantlr/Token;
      51: aload_0
      52: ldc           #11                 // String Java
      54: putfield      #12                 // Field language:Ljava/lang/String;
      57: aload_0
      58: iconst_0
      59: putfield      #13                 // Field numLexers:I
      62: aload_0
      63: iconst_0
      64: putfield      #14                 // Field numParsers:I
      67: aload_0
      68: iconst_0
      69: putfield      #15                 // Field numTreeParsers:I
      72: aload_0
      73: aload_1
      74: putfield      #16                 // Field tool:Lantlr/Tool;
      77: aload_0
      78: aload_2
      79: putfield      #17                 // Field args:[Ljava/lang/String;
      82: aload_0
      83: aload_3
      84: putfield      #18                 // Field analyzer:Lantlr/LLkAnalyzer;
      87: return

  public void _refStringLiteral(antlr.Token, antlr.Token, int, boolean);
    Code:
       0: aload_0
       1: getfield      #19                 // Field grammar:Lantlr/Grammar;
       4: instanceof    #20                 // class antlr/LexerGrammar
       7: ifne          80
      10: aload_1
      11: invokevirtual #21                 // Method antlr/Token.getText:()Ljava/lang/String;
      14: astore        5
      16: aload_0
      17: getfield      #19                 // Field grammar:Lantlr/Grammar;
      20: getfield      #22                 // Field antlr/Grammar.tokenManager:Lantlr/TokenManager;
      23: aload         5
      25: invokeinterface #23,  2           // InterfaceMethod antlr/TokenManager.getTokenSymbol:(Ljava/lang/String;)Lantlr/TokenSymbol;
      30: ifnull        34
      33: return
      34: new           #24                 // class antlr/StringLiteralSymbol
      37: dup
      38: aload         5
      40: invokespecial #25                 // Method antlr/StringLiteralSymbol."<init>":(Ljava/lang/String;)V
      43: astore        6
      45: aload_0
      46: getfield      #19                 // Field grammar:Lantlr/Grammar;
      49: getfield      #22                 // Field antlr/Grammar.tokenManager:Lantlr/TokenManager;
      52: invokeinterface #26,  1           // InterfaceMethod antlr/TokenManager.nextTokenType:()I
      57: istore        7
      59: aload         6
      61: iload         7
      63: invokevirtual #27                 // Method antlr/StringLiteralSymbol.setTokenType:(I)V
      66: aload_0
      67: getfield      #19                 // Field grammar:Lantlr/Grammar;
      70: getfield      #22                 // Field antlr/Grammar.tokenManager:Lantlr/TokenManager;
      73: aload         6
      75: invokeinterface #28,  2           // InterfaceMethod antlr/TokenManager.define:(Lantlr/TokenSymbol;)V
      80: return

  public void _refToken(antlr.Token, antlr.Token, antlr.Token, antlr.Token, boolean, int, boolean);
    Code:
       0: aload_2
       1: invokevirtual #21                 // Method antlr/Token.getText:()Ljava/lang/String;
       4: astore        8
       6: aload_0
       7: getfield      #19                 // Field grammar:Lantlr/Grammar;
      10: getfield      #22                 // Field antlr/Grammar.tokenManager:Lantlr/TokenManager;
      13: aload         8
      15: invokeinterface #29,  2           // InterfaceMethod antlr/TokenManager.tokenDefined:(Ljava/lang/String;)Z
      20: ifne          69
      23: aload_0
      24: getfield      #19                 // Field grammar:Lantlr/Grammar;
      27: getfield      #22                 // Field antlr/Grammar.tokenManager:Lantlr/TokenManager;
      30: invokeinterface #26,  1           // InterfaceMethod antlr/TokenManager.nextTokenType:()I
      35: istore        9
      37: new           #30                 // class antlr/TokenSymbol
      40: dup
      41: aload         8
      43: invokespecial #31                 // Method antlr/TokenSymbol."<init>":(Ljava/lang/String;)V
      46: astore        10
      48: aload         10
      50: iload         9
      52: invokevirtual #32                 // Method antlr/TokenSymbol.setTokenType:(I)V
      55: aload_0
      56: getfield      #19                 // Field grammar:Lantlr/Grammar;
      59: getfield      #22                 // Field antlr/Grammar.tokenManager:Lantlr/TokenManager;
      62: aload         10
      64: invokeinterface #28,  2           // InterfaceMethod antlr/TokenManager.define:(Lantlr/TokenSymbol;)V
      69: return

  public void abortGrammar();
    Code:
       0: aload_0
       1: getfield      #19                 // Field grammar:Lantlr/Grammar;
       4: ifnull        32
       7: aload_0
       8: getfield      #19                 // Field grammar:Lantlr/Grammar;
      11: invokevirtual #33                 // Method antlr/Grammar.getClassName:()Ljava/lang/String;
      14: ifnull        32
      17: aload_0
      18: getfield      #4                  // Field grammars:Ljava/util/Hashtable;
      21: aload_0
      22: getfield      #19                 // Field grammar:Lantlr/Grammar;
      25: invokevirtual #33                 // Method antlr/Grammar.getClassName:()Ljava/lang/String;
      28: invokevirtual #34                 // Method java/util/Hashtable.remove:(Ljava/lang/Object;)Ljava/lang/Object;
      31: pop
      32: aload_0
      33: aconst_null
      34: putfield      #19                 // Field grammar:Lantlr/Grammar;
      37: return

  public void beginAlt(boolean);
    Code:
       0: return

  public void beginChildList();
    Code:
       0: return

  public void beginExceptionGroup();
    Code:
       0: return

  public void beginExceptionSpec(antlr.Token);
    Code:
       0: return

  public void beginSubRule(antlr.Token, antlr.Token, boolean);
    Code:
       0: return

  public void beginTree(antlr.Token) throws antlr.SemanticException;
    Code:
       0: return

  public void defineRuleName(antlr.Token, java.lang.String, boolean, java.lang.String) throws antlr.SemanticException;
    Code:
       0: aload_1
       1: invokevirtual #21                 // Method antlr/Token.getText:()Ljava/lang/String;
       4: astore        5
       6: aload_1
       7: getfield      #35                 // Field antlr/Token.type:I
      10: bipush        24
      12: if_icmpne     89
      15: aload         5
      17: invokestatic  #36                 // Method antlr/CodeGenerator.encodeLexerRuleName:(Ljava/lang/String;)Ljava/lang/String;
      20: astore        5
      22: aload_0
      23: getfield      #19                 // Field grammar:Lantlr/Grammar;
      26: getfield      #22                 // Field antlr/Grammar.tokenManager:Lantlr/TokenManager;
      29: aload_1
      30: invokevirtual #21                 // Method antlr/Token.getText:()Ljava/lang/String;
      33: invokeinterface #29,  2           // InterfaceMethod antlr/TokenManager.tokenDefined:(Ljava/lang/String;)Z
      38: ifne          89
      41: aload_0
      42: getfield      #19                 // Field grammar:Lantlr/Grammar;
      45: getfield      #22                 // Field antlr/Grammar.tokenManager:Lantlr/TokenManager;
      48: invokeinterface #26,  1           // InterfaceMethod antlr/TokenManager.nextTokenType:()I
      53: istore        6
      55: new           #30                 // class antlr/TokenSymbol
      58: dup
      59: aload_1
      60: invokevirtual #21                 // Method antlr/Token.getText:()Ljava/lang/String;
      63: invokespecial #31                 // Method antlr/TokenSymbol."<init>":(Ljava/lang/String;)V
      66: astore        7
      68: aload         7
      70: iload         6
      72: invokevirtual #32                 // Method antlr/TokenSymbol.setTokenType:(I)V
      75: aload_0
      76: getfield      #19                 // Field grammar:Lantlr/Grammar;
      79: getfield      #22                 // Field antlr/Grammar.tokenManager:Lantlr/TokenManager;
      82: aload         7
      84: invokeinterface #28,  2           // InterfaceMethod antlr/TokenManager.define:(Lantlr/TokenSymbol;)V
      89: aload_0
      90: getfield      #19                 // Field grammar:Lantlr/Grammar;
      93: aload         5
      95: invokevirtual #37                 // Method antlr/Grammar.isDefined:(Ljava/lang/String;)Z
      98: ifeq          168
     101: aload_0
     102: getfield      #19                 // Field grammar:Lantlr/Grammar;
     105: aload         5
     107: invokevirtual #38                 // Method antlr/Grammar.getSymbol:(Ljava/lang/String;)Lantlr/GrammarSymbol;
     110: checkcast     #39                 // class antlr/RuleSymbol
     113: astore        6
     115: aload         6
     117: invokevirtual #40                 // Method antlr/RuleSymbol.isDefined:()Z
     120: ifeq          188
     123: aload_0
     124: getfield      #16                 // Field tool:Lantlr/Tool;
     127: new           #41                 // class java/lang/StringBuffer
     130: dup
     131: invokespecial #42                 // Method java/lang/StringBuffer."<init>":()V
     134: ldc           #43                 // String redefinition of rule
     136: invokevirtual #44                 // Method java/lang/StringBuffer.append:(Ljava/lang/String;)Ljava/lang/StringBuffer;
     139: aload         5
     141: invokevirtual #44                 // Method java/lang/StringBuffer.append:(Ljava/lang/String;)Ljava/lang/StringBuffer;
     144: invokevirtual #45                 // Method java/lang/StringBuffer.toString:()Ljava/lang/String;
     147: aload_0
     148: getfield      #19                 // Field grammar:Lantlr/Grammar;
     151: invokevirtual #46                 // Method antlr/Grammar.getFilename:()Ljava/lang/String;
     154: aload_1
     155: invokevirtual #47                 // Method antlr/Token.getLine:()I
     158: aload_1
     159: invokevirtual #48                 // Method antlr/Token.getColumn:()I
     162: invokevirtual #49                 // Method antlr/Tool.error:(Ljava/lang/String;Ljava/lang/String;II)V
     165: goto          188
     168: new           #39                 // class antlr/RuleSymbol
     171: dup
     172: aload         5
     174: invokespecial #50                 // Method antlr/RuleSymbol."<init>":(Ljava/lang/String;)V
     177: astore        6
     179: aload_0
     180: getfield      #19                 // Field grammar:Lantlr/Grammar;
     183: aload         6
     185: invokevirtual #51                 // Method antlr/Grammar.define:(Lantlr/RuleSymbol;)V
     188: aload         6
     190: invokevirtual #52                 // Method antlr/RuleSymbol.setDefined:()V
     193: aload         6
     195: aload_2
     196: putfield      #53                 // Field antlr/RuleSymbol.access:Ljava/lang/String;
     199: aload         6
     201: aload         4
     203: putfield      #54                 // Field antlr/RuleSymbol.comment:Ljava/lang/String;
     206: return

  public void defineToken(antlr.Token, antlr.Token);
    Code:
       0: aconst_null
       1: astore_3
       2: aconst_null
       3: astore        4
       5: aload_1
       6: ifnull        14
       9: aload_1
      10: invokevirtual #21                 // Method antlr/Token.getText:()Ljava/lang/String;
      13: astore_3
      14: aload_2
      15: ifnull        24
      18: aload_2
      19: invokevirtual #21                 // Method antlr/Token.getText:()Ljava/lang/String;
      22: astore        4
      24: aload         4
      26: ifnull        342
      29: aload_0
      30: getfield      #19                 // Field grammar:Lantlr/Grammar;
      33: getfield      #22                 // Field antlr/Grammar.tokenManager:Lantlr/TokenManager;
      36: aload         4
      38: invokeinterface #23,  2           // InterfaceMethod antlr/TokenManager.getTokenSymbol:(Ljava/lang/String;)Lantlr/TokenSymbol;
      43: checkcast     #24                 // class antlr/StringLiteralSymbol
      46: astore        5
      48: aload         5
      50: ifnull        133
      53: aload_3
      54: ifnull        65
      57: aload         5
      59: invokevirtual #55                 // Method antlr/StringLiteralSymbol.getLabel:()Ljava/lang/String;
      62: ifnull        108
      65: aload_0
      66: getfield      #16                 // Field tool:Lantlr/Tool;
      69: new           #41                 // class java/lang/StringBuffer
      72: dup
      73: invokespecial #42                 // Method java/lang/StringBuffer."<init>":()V
      76: ldc           #56                 // String Redefinition of literal in tokens {...}:
      78: invokevirtual #44                 // Method java/lang/StringBuffer.append:(Ljava/lang/String;)Ljava/lang/StringBuffer;
      81: aload         4
      83: invokevirtual #44                 // Method java/lang/StringBuffer.append:(Ljava/lang/String;)Ljava/lang/StringBuffer;
      86: invokevirtual #45                 // Method java/lang/StringBuffer.toString:()Ljava/lang/String;
      89: aload_0
      90: getfield      #19                 // Field grammar:Lantlr/Grammar;
      93: invokevirtual #46                 // Method antlr/Grammar.getFilename:()Ljava/lang/String;
      96: aload_2
      97: invokevirtual #47                 // Method antlr/Token.getLine:()I
     100: aload_2
     101: invokevirtual #48                 // Method antlr/Token.getColumn:()I
     104: invokevirtual #57                 // Method antlr/Tool.warning:(Ljava/lang/String;Ljava/lang/String;II)V
     107: return
     108: aload_3
     109: ifnull        133
     112: aload         5
     114: aload_3
     115: invokevirtual #58                 // Method antlr/StringLiteralSymbol.setLabel:(Ljava/lang/String;)V
     118: aload_0
     119: getfield      #19                 // Field grammar:Lantlr/Grammar;
     122: getfield      #22                 // Field antlr/Grammar.tokenManager:Lantlr/TokenManager;
     125: aload_3
     126: aload         5
     128: invokeinterface #59,  3           // InterfaceMethod antlr/TokenManager.mapToTokenSymbol:(Ljava/lang/String;Lantlr/TokenSymbol;)V
     133: aload_3
     134: ifnull        268
     137: aload_0
     138: getfield      #19                 // Field grammar:Lantlr/Grammar;
     141: getfield      #22                 // Field antlr/Grammar.tokenManager:Lantlr/TokenManager;
     144: aload_3
     145: invokeinterface #23,  2           // InterfaceMethod antlr/TokenManager.getTokenSymbol:(Ljava/lang/String;)Lantlr/TokenSymbol;
     150: astore        6
     152: aload         6
     154: ifnull        268
     157: aload         6
     159: instanceof    #24                 // class antlr/StringLiteralSymbol
     162: ifeq          207
     165: aload_0
     166: getfield      #16                 // Field tool:Lantlr/Tool;
     169: new           #41                 // class java/lang/StringBuffer
     172: dup
     173: invokespecial #42                 // Method java/lang/StringBuffer."<init>":()V
     176: ldc           #60                 // String Redefinition of token in tokens {...}:
     178: invokevirtual #44                 // Method java/lang/StringBuffer.append:(Ljava/lang/String;)Ljava/lang/StringBuffer;
     181: aload_3
     182: invokevirtual #44                 // Method java/lang/StringBuffer.append:(Ljava/lang/String;)Ljava/lang/StringBuffer;
     185: invokevirtual #45                 // Method java/lang/StringBuffer.toString:()Ljava/lang/String;
     188: aload_0
     189: getfield      #19                 // Field grammar:Lantlr/Grammar;
     192: invokevirtual #46                 // Method antlr/Grammar.getFilename:()Ljava/lang/String;
     195: aload_2
     196: invokevirtual #47                 // Method antlr/Token.getLine:()I
     199: aload_2
     200: invokevirtual #48                 // Method antlr/Token.getColumn:()I
     203: invokevirtual #57                 // Method antlr/Tool.warning:(Ljava/lang/String;Ljava/lang/String;II)V
     206: return
     207: aload         6
     209: invokevirtual #61                 // Method antlr/TokenSymbol.getTokenType:()I
     212: istore        7
     214: new           #24                 // class antlr/StringLiteralSymbol
     217: dup
     218: aload         4
     220: invokespecial #25                 // Method antlr/StringLiteralSymbol."<init>":(Ljava/lang/String;)V
     223: astore        5
     225: aload         5
     227: iload         7
     229: invokevirtual #27                 // Method antlr/StringLiteralSymbol.setTokenType:(I)V
     232: aload         5
     234: aload_3
     235: invokevirtual #58                 // Method antlr/StringLiteralSymbol.setLabel:(Ljava/lang/String;)V
     238: aload_0
     239: getfield      #19                 // Field grammar:Lantlr/Grammar;
     242: getfield      #22                 // Field antlr/Grammar.tokenManager:Lantlr/TokenManager;
     245: aload         5
     247: invokeinterface #28,  2           // InterfaceMethod antlr/TokenManager.define:(Lantlr/TokenSymbol;)V
     252: aload_0
     253: getfield      #19                 // Field grammar:Lantlr/Grammar;
     256: getfield      #22                 // Field antlr/Grammar.tokenManager:Lantlr/TokenManager;
     259: aload_3
     260: aload         5
     262: invokeinterface #59,  3           // InterfaceMethod antlr/TokenManager.mapToTokenSymbol:(Ljava/lang/String;Lantlr/TokenSymbol;)V
     267: return
     268: new           #24                 // class antlr/StringLiteralSymbol
     271: dup
     272: aload         4
     274: invokespecial #25                 // Method antlr/StringLiteralSymbol."<init>":(Ljava/lang/String;)V
     277: astore        5
     279: aload_0
     280: getfield      #19                 // Field grammar:Lantlr/Grammar;
     283: getfield      #22                 // Field antlr/Grammar.tokenManager:Lantlr/TokenManager;
     286: invokeinterface #26,  1           // InterfaceMethod antlr/TokenManager.nextTokenType:()I
     291: istore        6
     293: aload         5
     295: iload         6
     297: invokevirtual #27                 // Method antlr/StringLiteralSymbol.setTokenType:(I)V
     300: aload         5
     302: aload_3
     303: invokevirtual #58                 // Method antlr/StringLiteralSymbol.setLabel:(Ljava/lang/String;)V
     306: aload_0
     307: getfield      #19                 // Field grammar:Lantlr/Grammar;
     310: getfield      #22                 // Field antlr/Grammar.tokenManager:Lantlr/TokenManager;
     313: aload         5
     315: invokeinterface #28,  2           // InterfaceMethod antlr/TokenManager.define:(Lantlr/TokenSymbol;)V
     320: aload_3
     321: ifnull        445
     324: aload_0
     325: getfield      #19                 // Field grammar:Lantlr/Grammar;
     328: getfield      #22                 // Field antlr/Grammar.tokenManager:Lantlr/TokenManager;
     331: aload_3
     332: aload         5
     334: invokeinterface #59,  3           // InterfaceMethod antlr/TokenManager.mapToTokenSymbol:(Ljava/lang/String;Lantlr/TokenSymbol;)V
     339: goto          445
     342: aload_0
     343: getfield      #19                 // Field grammar:Lantlr/Grammar;
     346: getfield      #22                 // Field antlr/Grammar.tokenManager:Lantlr/TokenManager;
     349: aload_3
     350: invokeinterface #29,  2           // InterfaceMethod antlr/TokenManager.tokenDefined:(Ljava/lang/String;)Z
     355: ifeq          400
     358: aload_0
     359: getfield      #16                 // Field tool:Lantlr/Tool;
     362: new           #41                 // class java/lang/StringBuffer
     365: dup
     366: invokespecial #42                 // Method java/lang/StringBuffer."<init>":()V
     369: ldc           #60                 // String Redefinition of token in tokens {...}:
     371: invokevirtual #44                 // Method java/lang/StringBuffer.append:(Ljava/lang/String;)Ljava/lang/StringBuffer;
     374: aload_3
     375: invokevirtual #44                 // Method java/lang/StringBuffer.append:(Ljava/lang/String;)Ljava/lang/StringBuffer;
     378: invokevirtual #45                 // Method java/lang/StringBuffer.toString:()Ljava/lang/String;
     381: aload_0
     382: getfield      #19                 // Field grammar:Lantlr/Grammar;
     385: invokevirtual #46                 // Method antlr/Grammar.getFilename:()Ljava/lang/String;
     388: aload_1
     389: invokevirtual #47                 // Method antlr/Token.getLine:()I
     392: aload_1
     393: invokevirtual #48                 // Method antlr/Token.getColumn:()I
     396: invokevirtual #57                 // Method antlr/Tool.warning:(Ljava/lang/String;Ljava/lang/String;II)V
     399: return
     400: aload_0
     401: getfield      #19                 // Field grammar:Lantlr/Grammar;
     404: getfield      #22                 // Field antlr/Grammar.tokenManager:Lantlr/TokenManager;
     407: invokeinterface #26,  1           // InterfaceMethod antlr/TokenManager.nextTokenType:()I
     412: istore        5
     414: new           #30                 // class antlr/TokenSymbol
     417: dup
     418: aload_3
     419: invokespecial #31                 // Method antlr/TokenSymbol."<init>":(Ljava/lang/String;)V
     422: astore        6
     424: aload         6
     426: iload         5
     428: invokevirtual #32                 // Method antlr/TokenSymbol.setTokenType:(I)V
     431: aload_0
     432: getfield      #19                 // Field grammar:Lantlr/Grammar;
     435: getfield      #22                 // Field antlr/Grammar.tokenManager:Lantlr/TokenManager;
     438: aload         6
     440: invokeinterface #28,  2           // InterfaceMethod antlr/TokenManager.define:(Lantlr/TokenSymbol;)V
     445: return

  public void endAlt();
    Code:
       0: return

  public void endChildList();
    Code:
       0: return

  public void endExceptionGroup();
    Code:
       0: return

  public void endExceptionSpec();
    Code:
       0: return

  public void endGrammar();
    Code:
       0: return

  public void endOptions();
    Code:
       0: aload_0
       1: getfield      #19                 // Field grammar:Lantlr/Grammar;
       4: getfield      #62                 // Field antlr/Grammar.exportVocab:Ljava/lang/String;
       7: ifnonnull     132
      10: aload_0
      11: getfield      #19                 // Field grammar:Lantlr/Grammar;
      14: getfield      #63                 // Field antlr/Grammar.importVocab:Ljava/lang/String;
      17: ifnonnull     132
      20: aload_0
      21: getfield      #19                 // Field grammar:Lantlr/Grammar;
      24: aload_0
      25: getfield      #19                 // Field grammar:Lantlr/Grammar;
      28: invokevirtual #33                 // Method antlr/Grammar.getClassName:()Ljava/lang/String;
      31: putfield      #62                 // Field antlr/Grammar.exportVocab:Ljava/lang/String;
      34: aload_0
      35: getfield      #5                  // Field tokenManagers:Ljava/util/Hashtable;
      38: ldc           #64                 // String *default
      40: invokevirtual #65                 // Method java/util/Hashtable.containsKey:(Ljava/lang/Object;)Z
      43: ifeq          77
      46: aload_0
      47: getfield      #19                 // Field grammar:Lantlr/Grammar;
      50: ldc           #64                 // String *default
      52: putfield      #62                 // Field antlr/Grammar.exportVocab:Ljava/lang/String;
      55: aload_0
      56: getfield      #5                  // Field tokenManagers:Ljava/util/Hashtable;
      59: ldc           #64                 // String *default
      61: invokevirtual #66                 // Method java/util/Hashtable.get:(Ljava/lang/Object;)Ljava/lang/Object;
      64: checkcast     #67                 // class antlr/TokenManager
      67: astore_1
      68: aload_0
      69: getfield      #19                 // Field grammar:Lantlr/Grammar;
      72: aload_1
      73: invokevirtual #68                 // Method antlr/Grammar.setTokenManager:(Lantlr/TokenManager;)V
      76: return
      77: new           #69                 // class antlr/SimpleTokenManager
      80: dup
      81: aload_0
      82: getfield      #19                 // Field grammar:Lantlr/Grammar;
      85: getfield      #62                 // Field antlr/Grammar.exportVocab:Ljava/lang/String;
      88: aload_0
      89: getfield      #16                 // Field tool:Lantlr/Tool;
      92: invokespecial #70                 // Method antlr/SimpleTokenManager."<init>":(Ljava/lang/String;Lantlr/Tool;)V
      95: astore_1
      96: aload_0
      97: getfield      #19                 // Field grammar:Lantlr/Grammar;
     100: aload_1
     101: invokevirtual #68                 // Method antlr/Grammar.setTokenManager:(Lantlr/TokenManager;)V
     104: aload_0
     105: getfield      #5                  // Field tokenManagers:Ljava/util/Hashtable;
     108: aload_0
     109: getfield      #19                 // Field grammar:Lantlr/Grammar;
     112: getfield      #62                 // Field antlr/Grammar.exportVocab:Ljava/lang/String;
     115: aload_1
     116: invokevirtual #71                 // Method java/util/Hashtable.put:(Ljava/lang/Object;Ljava/lang/Object;)Ljava/lang/Object;
     119: pop
     120: aload_0
     121: getfield      #5                  // Field tokenManagers:Ljava/util/Hashtable;
     124: ldc           #64                 // String *default
     126: aload_1
     127: invokevirtual #71                 // Method java/util/Hashtable.put:(Ljava/lang/Object;Ljava/lang/Object;)Ljava/lang/Object;
     130: pop
     131: return
     132: aload_0
     133: getfield      #19                 // Field grammar:Lantlr/Grammar;
     136: getfield      #62                 // Field antlr/Grammar.exportVocab:Ljava/lang/String;
     139: ifnonnull     434
     142: aload_0
     143: getfield      #19                 // Field grammar:Lantlr/Grammar;
     146: getfield      #63                 // Field antlr/Grammar.importVocab:Ljava/lang/String;
     149: ifnull        434
     152: aload_0
     153: getfield      #19                 // Field grammar:Lantlr/Grammar;
     156: aload_0
     157: getfield      #19                 // Field grammar:Lantlr/Grammar;
     160: invokevirtual #33                 // Method antlr/Grammar.getClassName:()Ljava/lang/String;
     163: putfield      #62                 // Field antlr/Grammar.exportVocab:Ljava/lang/String;
     166: aload_0
     167: getfield      #19                 // Field grammar:Lantlr/Grammar;
     170: getfield      #63                 // Field antlr/Grammar.importVocab:Ljava/lang/String;
     173: aload_0
     174: getfield      #19                 // Field grammar:Lantlr/Grammar;
     177: getfield      #62                 // Field antlr/Grammar.exportVocab:Ljava/lang/String;
     180: invokevirtual #72                 // Method java/lang/String.equals:(Ljava/lang/Object;)Z
     183: ifeq          236
     186: aload_0
     187: getfield      #16                 // Field tool:Lantlr/Tool;
     190: new           #41                 // class java/lang/StringBuffer
     193: dup
     194: invokespecial #42                 // Method java/lang/StringBuffer."<init>":()V
     197: ldc           #73                 // String Grammar
     199: invokevirtual #44                 // Method java/lang/StringBuffer.append:(Ljava/lang/String;)Ljava/lang/StringBuffer;
     202: aload_0
     203: getfield      #19                 // Field grammar:Lantlr/Grammar;
     206: invokevirtual #33                 // Method antlr/Grammar.getClassName:()Ljava/lang/String;
     209: invokevirtual #44                 // Method java/lang/StringBuffer.append:(Ljava/lang/String;)Ljava/lang/StringBuffer;
     212: ldc           #74                 // String  cannot have importVocab same as default output vocab (grammar name); ignored.
     214: invokevirtual #44                 // Method java/lang/StringBuffer.append:(Ljava/lang/String;)Ljava/lang/StringBuffer;
     217: invokevirtual #45                 // Method java/lang/StringBuffer.toString:()Ljava/lang/String;
     220: invokevirtual #75                 // Method antlr/Tool.warning:(Ljava/lang/String;)V
     223: aload_0
     224: getfield      #19                 // Field grammar:Lantlr/Grammar;
     227: aconst_null
     228: putfield      #63                 // Field antlr/Grammar.importVocab:Ljava/lang/String;
     231: aload_0
     232: invokevirtual #76                 // Method endOptions:()V
     235: return
     236: aload_0
     237: getfield      #5                  // Field tokenManagers:Ljava/util/Hashtable;
     240: aload_0
     241: getfield      #19                 // Field grammar:Lantlr/Grammar;
     244: getfield      #63                 // Field antlr/Grammar.importVocab:Ljava/lang/String;
     247: invokevirtual #65                 // Method java/util/Hashtable.containsKey:(Ljava/lang/Object;)Z
     250: ifeq          326
     253: aload_0
     254: getfield      #5                  // Field tokenManagers:Ljava/util/Hashtable;
     257: aload_0
     258: getfield      #19                 // Field grammar:Lantlr/Grammar;
     261: getfield      #63                 // Field antlr/Grammar.importVocab:Ljava/lang/String;
     264: invokevirtual #66                 // Method java/util/Hashtable.get:(Ljava/lang/Object;)Ljava/lang/Object;
     267: checkcast     #67                 // class antlr/TokenManager
     270: astore_1
     271: aload_1
     272: invokeinterface #77,  1           // InterfaceMethod antlr/TokenManager.clone:()Ljava/lang/Object;
     277: checkcast     #67                 // class antlr/TokenManager
     280: astore_2
     281: aload_2
     282: aload_0
     283: getfield      #19                 // Field grammar:Lantlr/Grammar;
     286: getfield      #62                 // Field antlr/Grammar.exportVocab:Ljava/lang/String;
     289: invokeinterface #78,  2           // InterfaceMethod antlr/TokenManager.setName:(Ljava/lang/String;)V
     294: aload_2
     295: iconst_0
     296: invokeinterface #79,  2           // InterfaceMethod antlr/TokenManager.setReadOnly:(Z)V
     301: aload_0
     302: getfield      #19                 // Field grammar:Lantlr/Grammar;
     305: aload_2
     306: invokevirtual #68                 // Method antlr/Grammar.setTokenManager:(Lantlr/TokenManager;)V
     309: aload_0
     310: getfield      #5                  // Field tokenManagers:Ljava/util/Hashtable;
     313: aload_0
     314: getfield      #19                 // Field grammar:Lantlr/Grammar;
     317: getfield      #62                 // Field antlr/Grammar.exportVocab:Ljava/lang/String;
     320: aload_2
     321: invokevirtual #71                 // Method java/util/Hashtable.put:(Ljava/lang/Object;Ljava/lang/Object;)Ljava/lang/Object;
     324: pop
     325: return
     326: new           #80                 // class antlr/ImportVocabTokenManager
     329: dup
     330: aload_0
     331: getfield      #19                 // Field grammar:Lantlr/Grammar;
     334: new           #41                 // class java/lang/StringBuffer
     337: dup
     338: invokespecial #42                 // Method java/lang/StringBuffer."<init>":()V
     341: aload_0
     342: getfield      #19                 // Field grammar:Lantlr/Grammar;
     345: getfield      #63                 // Field antlr/Grammar.importVocab:Ljava/lang/String;
     348: invokevirtual #44                 // Method java/lang/StringBuffer.append:(Ljava/lang/String;)Ljava/lang/StringBuffer;
     351: getstatic     #81                 // Field antlr/CodeGenerator.TokenTypesFileSuffix:Ljava/lang/String;
     354: invokevirtual #44                 // Method java/lang/StringBuffer.append:(Ljava/lang/String;)Ljava/lang/StringBuffer;
     357: getstatic     #82                 // Field antlr/CodeGenerator.TokenTypesFileExt:Ljava/lang/String;
     360: invokevirtual #44                 // Method java/lang/StringBuffer.append:(Ljava/lang/String;)Ljava/lang/StringBuffer;
     363: invokevirtual #45                 // Method java/lang/StringBuffer.toString:()Ljava/lang/String;
     366: aload_0
     367: getfield      #19                 // Field grammar:Lantlr/Grammar;
     370: getfield      #62                 // Field antlr/Grammar.exportVocab:Ljava/lang/String;
     373: aload_0
     374: getfield      #16                 // Field tool:Lantlr/Tool;
     377: invokespecial #83                 // Method antlr/ImportVocabTokenManager."<init>":(Lantlr/Grammar;Ljava/lang/String;Ljava/lang/String;Lantlr/Tool;)V
     380: astore_1
     381: aload_1
     382: iconst_0
     383: invokevirtual #84                 // Method antlr/ImportVocabTokenManager.setReadOnly:(Z)V
     386: aload_0
     387: getfield      #5                  // Field tokenManagers:Ljava/util/Hashtable;
     390: aload_0
     391: getfield      #19                 // Field grammar:Lantlr/Grammar;
     394: getfield      #62                 // Field antlr/Grammar.exportVocab:Ljava/lang/String;
     397: aload_1
     398: invokevirtual #71                 // Method java/util/Hashtable.put:(Ljava/lang/Object;Ljava/lang/Object;)Ljava/lang/Object;
     401: pop
     402: aload_0
     403: getfield      #19                 // Field grammar:Lantlr/Grammar;
     406: aload_1
     407: invokevirtual #68                 // Method antlr/Grammar.setTokenManager:(Lantlr/TokenManager;)V
     410: aload_0
     411: getfield      #5                  // Field tokenManagers:Ljava/util/Hashtable;
     414: ldc           #64                 // String *default
     416: invokevirtual #65                 // Method java/util/Hashtable.containsKey:(Ljava/lang/Object;)Z
     419: ifne          433
     422: aload_0
     423: getfield      #5                  // Field tokenManagers:Ljava/util/Hashtable;
     426: ldc           #64                 // String *default
     428: aload_1
     429: invokevirtual #71                 // Method java/util/Hashtable.put:(Ljava/lang/Object;Ljava/lang/Object;)Ljava/lang/Object;
     432: pop
     433: return
     434: aload_0
     435: getfield      #19                 // Field grammar:Lantlr/Grammar;
     438: getfield      #62                 // Field antlr/Grammar.exportVocab:Ljava/lang/String;
     441: ifnull        565
     444: aload_0
     445: getfield      #19                 // Field grammar:Lantlr/Grammar;
     448: getfield      #63                 // Field antlr/Grammar.importVocab:Ljava/lang/String;
     451: ifnonnull     565
     454: aload_0
     455: getfield      #5                  // Field tokenManagers:Ljava/util/Hashtable;
     458: aload_0
     459: getfield      #19                 // Field grammar:Lantlr/Grammar;
     462: getfield      #62                 // Field antlr/Grammar.exportVocab:Ljava/lang/String;
     465: invokevirtual #65                 // Method java/util/Hashtable.containsKey:(Ljava/lang/Object;)Z
     468: ifeq          498
     471: aload_0
     472: getfield      #5                  // Field tokenManagers:Ljava/util/Hashtable;
     475: aload_0
     476: getfield      #19                 // Field grammar:Lantlr/Grammar;
     479: getfield      #62                 // Field antlr/Grammar.exportVocab:Ljava/lang/String;
     482: invokevirtual #66                 // Method java/util/Hashtable.get:(Ljava/lang/Object;)Ljava/lang/Object;
     485: checkcast     #67                 // class antlr/TokenManager
     488: astore_1
     489: aload_0
     490: getfield      #19                 // Field grammar:Lantlr/Grammar;
     493: aload_1
     494: invokevirtual #68                 // Method antlr/Grammar.setTokenManager:(Lantlr/TokenManager;)V
     497: return
     498: new           #69                 // class antlr/SimpleTokenManager
     501: dup
     502: aload_0
     503: getfield      #19                 // Field grammar:Lantlr/Grammar;
     506: getfield      #62                 // Field antlr/Grammar.exportVocab:Ljava/lang/String;
     509: aload_0
     510: getfield      #16                 // Field tool:Lantlr/Tool;
     513: invokespecial #70                 // Method antlr/SimpleTokenManager."<init>":(Ljava/lang/String;Lantlr/Tool;)V
     516: astore_1
     517: aload_0
     518: getfield      #19                 // Field grammar:Lantlr/Grammar;
     521: aload_1
     522: invokevirtual #68                 // Method antlr/Grammar.setTokenManager:(Lantlr/TokenManager;)V
     525: aload_0
     526: getfield      #5                  // Field tokenManagers:Ljava/util/Hashtable;
     529: aload_0
     530: getfield      #19                 // Field grammar:Lantlr/Grammar;
     533: getfield      #62                 // Field antlr/Grammar.exportVocab:Ljava/lang/String;
     536: aload_1
     537: invokevirtual #71                 // Method java/util/Hashtable.put:(Ljava/lang/Object;Ljava/lang/Object;)Ljava/lang/Object;
     540: pop
     541: aload_0
     542: getfield      #5                  // Field tokenManagers:Ljava/util/Hashtable;
     545: ldc           #64                 // String *default
     547: invokevirtual #65                 // Method java/util/Hashtable.containsKey:(Ljava/lang/Object;)Z
     550: ifne          564
     553: aload_0
     554: getfield      #5                  // Field tokenManagers:Ljava/util/Hashtable;
     557: ldc           #64                 // String *default
     559: aload_1
     560: invokevirtual #71                 // Method java/util/Hashtable.put:(Ljava/lang/Object;Ljava/lang/Object;)Ljava/lang/Object;
     563: pop
     564: return
     565: aload_0
     566: getfield      #19                 // Field grammar:Lantlr/Grammar;
     569: getfield      #62                 // Field antlr/Grammar.exportVocab:Ljava/lang/String;
     572: ifnull        840
     575: aload_0
     576: getfield      #19                 // Field grammar:Lantlr/Grammar;
     579: getfield      #63                 // Field antlr/Grammar.importVocab:Ljava/lang/String;
     582: ifnull        840
     585: aload_0
     586: getfield      #19                 // Field grammar:Lantlr/Grammar;
     589: getfield      #63                 // Field antlr/Grammar.importVocab:Ljava/lang/String;
     592: aload_0
     593: getfield      #19                 // Field grammar:Lantlr/Grammar;
     596: getfield      #62                 // Field antlr/Grammar.exportVocab:Ljava/lang/String;
     599: invokevirtual #72                 // Method java/lang/String.equals:(Ljava/lang/Object;)Z
     602: ifeq          642
     605: aload_0
     606: getfield      #16                 // Field tool:Lantlr/Tool;
     609: new           #41                 // class java/lang/StringBuffer
     612: dup
     613: invokespecial #42                 // Method java/lang/StringBuffer."<init>":()V
     616: ldc           #85                 // String exportVocab of
     618: invokevirtual #44                 // Method java/lang/StringBuffer.append:(Ljava/lang/String;)Ljava/lang/StringBuffer;
     621: aload_0
     622: getfield      #19                 // Field grammar:Lantlr/Grammar;
     625: getfield      #62                 // Field antlr/Grammar.exportVocab:Ljava/lang/String;
     628: invokevirtual #44                 // Method java/lang/StringBuffer.append:(Ljava/lang/String;)Ljava/lang/StringBuffer;
     631: ldc           #86                 // String  same as importVocab; probably not what you want
     633: invokevirtual #44                 // Method java/lang/StringBuffer.append:(Ljava/lang/String;)Ljava/lang/StringBuffer;
     636: invokevirtual #45                 // Method java/lang/StringBuffer.toString:()Ljava/lang/String;
     639: invokevirtual #87                 // Method antlr/Tool.error:(Ljava/lang/String;)V
     642: aload_0
     643: getfield      #5                  // Field tokenManagers:Ljava/util/Hashtable;
     646: aload_0
     647: getfield      #19                 // Field grammar:Lantlr/Grammar;
     650: getfield      #63                 // Field antlr/Grammar.importVocab:Ljava/lang/String;
     653: invokevirtual #65                 // Method java/util/Hashtable.containsKey:(Ljava/lang/Object;)Z
     656: ifeq          732
     659: aload_0
     660: getfield      #5                  // Field tokenManagers:Ljava/util/Hashtable;
     663: aload_0
     664: getfield      #19                 // Field grammar:Lantlr/Grammar;
     667: getfield      #63                 // Field antlr/Grammar.importVocab:Ljava/lang/String;
     670: invokevirtual #66                 // Method java/util/Hashtable.get:(Ljava/lang/Object;)Ljava/lang/Object;
     673: checkcast     #67                 // class antlr/TokenManager
     676: astore_1
     677: aload_1
     678: invokeinterface #77,  1           // InterfaceMethod antlr/TokenManager.clone:()Ljava/lang/Object;
     683: checkcast     #67                 // class antlr/TokenManager
     686: astore_2
     687: aload_2
     688: aload_0
     689: getfield      #19                 // Field grammar:Lantlr/Grammar;
     692: getfield      #62                 // Field antlr/Grammar.exportVocab:Ljava/lang/String;
     695: invokeinterface #78,  2           // InterfaceMethod antlr/TokenManager.setName:(Ljava/lang/String;)V
     700: aload_2
     701: iconst_0
     702: invokeinterface #79,  2           // InterfaceMethod antlr/TokenManager.setReadOnly:(Z)V
     707: aload_0
     708: getfield      #19                 // Field grammar:Lantlr/Grammar;
     711: aload_2
     712: invokevirtual #68                 // Method antlr/Grammar.setTokenManager:(Lantlr/TokenManager;)V
     715: aload_0
     716: getfield      #5                  // Field tokenManagers:Ljava/util/Hashtable;
     719: aload_0
     720: getfield      #19                 // Field grammar:Lantlr/Grammar;
     723: getfield      #62                 // Field antlr/Grammar.exportVocab:Ljava/lang/String;
     726: aload_2
     727: invokevirtual #71                 // Method java/util/Hashtable.put:(Ljava/lang/Object;Ljava/lang/Object;)Ljava/lang/Object;
     730: pop
     731: return
     732: new           #80                 // class antlr/ImportVocabTokenManager
     735: dup
     736: aload_0
     737: getfield      #19                 // Field grammar:Lantlr/Grammar;
     740: new           #41                 // class java/lang/StringBuffer
     743: dup
     744: invokespecial #42                 // Method java/lang/StringBuffer."<init>":()V
     747: aload_0
     748: getfield      #19                 // Field grammar:Lantlr/Grammar;
     751: getfield      #63                 // Field antlr/Grammar.importVocab:Ljava/lang/String;
     754: invokevirtual #44                 // Method java/lang/StringBuffer.append:(Ljava/lang/String;)Ljava/lang/StringBuffer;
     757: getstatic     #81                 // Field antlr/CodeGenerator.TokenTypesFileSuffix:Ljava/lang/String;
     760: invokevirtual #44                 // Method java/lang/StringBuffer.append:(Ljava/lang/String;)Ljava/lang/StringBuffer;
     763: getstatic     #82                 // Field antlr/CodeGenerator.TokenTypesFileExt:Ljava/lang/String;
     766: invokevirtual #44                 // Method java/lang/StringBuffer.append:(Ljava/lang/String;)Ljava/lang/StringBuffer;
     769: invokevirtual #45                 // Method java/lang/StringBuffer.toString:()Ljava/lang/String;
     772: aload_0
     773: getfield      #19                 // Field grammar:Lantlr/Grammar;
     776: getfield      #62                 // Field antlr/Grammar.exportVocab:Ljava/lang/String;
     779: aload_0
     780: getfield      #16                 // Field tool:Lantlr/Tool;
     783: invokespecial #83                 // Method antlr/ImportVocabTokenManager."<init>":(Lantlr/Grammar;Ljava/lang/String;Ljava/lang/String;Lantlr/Tool;)V
     786: astore_1
     787: aload_1
     788: iconst_0
     789: invokevirtual #84                 // Method antlr/ImportVocabTokenManager.setReadOnly:(Z)V
     792: aload_0
     793: getfield      #5                  // Field tokenManagers:Ljava/util/Hashtable;
     796: aload_0
     797: getfield      #19                 // Field grammar:Lantlr/Grammar;
     800: getfield      #62                 // Field antlr/Grammar.exportVocab:Ljava/lang/String;
     803: aload_1
     804: invokevirtual #71                 // Method java/util/Hashtable.put:(Ljava/lang/Object;Ljava/lang/Object;)Ljava/lang/Object;
     807: pop
     808: aload_0
     809: getfield      #19                 // Field grammar:Lantlr/Grammar;
     812: aload_1
     813: invokevirtual #68                 // Method antlr/Grammar.setTokenManager:(Lantlr/TokenManager;)V
     816: aload_0
     817: getfield      #5                  // Field tokenManagers:Ljava/util/Hashtable;
     820: ldc           #64                 // String *default
     822: invokevirtual #65                 // Method java/util/Hashtable.containsKey:(Ljava/lang/Object;)Z
     825: ifne          839
     828: aload_0
     829: getfield      #5                  // Field tokenManagers:Ljava/util/Hashtable;
     832: ldc           #64                 // String *default
     834: aload_1
     835: invokevirtual #71                 // Method java/util/Hashtable.put:(Ljava/lang/Object;Ljava/lang/Object;)Ljava/lang/Object;
     838: pop
     839: return
     840: return

  public void endRule(java.lang.String);
    Code:
       0: return

  public void endSubRule();
    Code:
       0: return

  public void endTree();
    Code:
       0: return

  public void hasError();
    Code:
       0: return

  public void noASTSubRule();
    Code:
       0: return

  public void oneOrMoreSubRule();
    Code:
       0: return

  public void optionalSubRule();
    Code:
       0: return

  public void setUserExceptions(java.lang.String);
    Code:
       0: return

  public void refAction(antlr.Token);
    Code:
       0: return

  public void refArgAction(antlr.Token);
    Code:
       0: return

  public void refCharLiteral(antlr.Token, antlr.Token, boolean, int, boolean);
    Code:
       0: return

  public void refCharRange(antlr.Token, antlr.Token, antlr.Token, int, boolean);
    Code:
       0: return

  public void refElementOption(antlr.Token, antlr.Token);
    Code:
       0: return

  public void refTokensSpecElementOption(antlr.Token, antlr.Token, antlr.Token);
    Code:
       0: return

  public void refExceptionHandler(antlr.Token, antlr.Token);
    Code:
       0: return

  public void refHeaderAction(antlr.Token, antlr.Token);
    Code:
       0: aload_1
       1: ifnonnull     10
       4: ldc           #8                  // String
       6: astore_3
       7: goto          22
      10: aload_1
      11: invokevirtual #21                 // Method antlr/Token.getText:()Ljava/lang/String;
      14: ldc           #88                 // String \"
      16: ldc           #88                 // String \"
      18: invokestatic  #89                 // Method antlr/StringUtils.stripFrontBack:(Ljava/lang/String;Ljava/lang/String;Ljava/lang/String;)Ljava/lang/String;
      21: astore_3
      22: aload_0
      23: getfield      #6                  // Field headerActions:Ljava/util/Hashtable;
      26: aload_3
      27: invokevirtual #65                 // Method java/util/Hashtable.containsKey:(Ljava/lang/Object;)Z
      30: ifeq          112
      33: aload_3
      34: ldc           #8                  // String
      36: invokevirtual #72                 // Method java/lang/String.equals:(Ljava/lang/Object;)Z
      39: ifeq          74
      42: aload_0
      43: getfield      #16                 // Field tool:Lantlr/Tool;
      46: new           #41                 // class java/lang/StringBuffer
      49: dup
      50: invokespecial #42                 // Method java/lang/StringBuffer."<init>":()V
      53: aload_2
      54: invokevirtual #47                 // Method antlr/Token.getLine:()I
      57: invokevirtual #90                 // Method java/lang/StringBuffer.append:(I)Ljava/lang/StringBuffer;
      60: ldc           #91                 // String : header action already defined
      62: invokevirtual #44                 // Method java/lang/StringBuffer.append:(Ljava/lang/String;)Ljava/lang/StringBuffer;
      65: invokevirtual #45                 // Method java/lang/StringBuffer.toString:()Ljava/lang/String;
      68: invokevirtual #87                 // Method antlr/Tool.error:(Ljava/lang/String;)V
      71: goto          112
      74: aload_0
      75: getfield      #16                 // Field tool:Lantlr/Tool;
      78: new           #41                 // class java/lang/StringBuffer
      81: dup
      82: invokespecial #42                 // Method java/lang/StringBuffer."<init>":()V
      85: aload_2
      86: invokevirtual #47                 // Method antlr/Token.getLine:()I
      89: invokevirtual #90                 // Method java/lang/StringBuffer.append:(I)Ljava/lang/StringBuffer;
      92: ldc           #92                 // String : header action \'
      94: invokevirtual #44                 // Method java/lang/StringBuffer.append:(Ljava/lang/String;)Ljava/lang/StringBuffer;
      97: aload_3
      98: invokevirtual #44                 // Method java/lang/StringBuffer.append:(Ljava/lang/String;)Ljava/lang/StringBuffer;
     101: ldc           #93                 // String \' already defined
     103: invokevirtual #44                 // Method java/lang/StringBuffer.append:(Ljava/lang/String;)Ljava/lang/StringBuffer;
     106: invokevirtual #45                 // Method java/lang/StringBuffer.toString:()Ljava/lang/String;
     109: invokevirtual #87                 // Method antlr/Tool.error:(Ljava/lang/String;)V
     112: aload_0
     113: getfield      #6                  // Field headerActions:Ljava/util/Hashtable;
     116: aload_3
     117: aload_2
     118: invokevirtual #71                 // Method java/util/Hashtable.put:(Ljava/lang/Object;Ljava/lang/Object;)Ljava/lang/Object;
     121: pop
     122: return

  public java.lang.String getHeaderAction(java.lang.String);
    Code:
       0: aload_0
       1: getfield      #6                  // Field headerActions:Ljava/util/Hashtable;
       4: aload_1
       5: invokevirtual #66                 // Method java/util/Hashtable.get:(Ljava/lang/Object;)Ljava/lang/Object;
       8: checkcast     #94                 // class antlr/Token
      11: astore_2
      12: aload_2
      13: ifnonnull     19
      16: ldc           #8                  // String
      18: areturn
      19: aload_2
      20: invokevirtual #21                 // Method antlr/Token.getText:()Ljava/lang/String;
      23: areturn

  public int getHeaderActionLine(java.lang.String);
    Code:
       0: aload_0
       1: getfield      #6                  // Field headerActions:Ljava/util/Hashtable;
       4: aload_1
       5: invokevirtual #66                 // Method java/util/Hashtable.get:(Ljava/lang/Object;)Ljava/lang/Object;
       8: checkcast     #94                 // class antlr/Token
      11: astore_2
      12: aload_2
      13: ifnonnull     18
      16: iconst_0
      17: ireturn
      18: aload_2
      19: invokevirtual #47                 // Method antlr/Token.getLine:()I
      22: ireturn

  public void refInitAction(antlr.Token);
    Code:
       0: return

  public void refMemberAction(antlr.Token);
    Code:
       0: return

  public void refPreambleAction(antlr.Token);
    Code:
       0: aload_0
       1: aload_1
       2: putfield      #10                 // Field thePreambleAction:Lantlr/Token;
       5: return

  public void refReturnAction(antlr.Token);
    Code:
       0: return

  public void refRule(antlr.Token, antlr.Token, antlr.Token, antlr.Token, int);
    Code:
       0: aload_2
       1: invokevirtual #21                 // Method antlr/Token.getText:()Ljava/lang/String;
       4: astore        6
       6: aload_2
       7: getfield      #35                 // Field antlr/Token.type:I
      10: bipush        24
      12: if_icmpne     22
      15: aload         6
      17: invokestatic  #36                 // Method antlr/CodeGenerator.encodeLexerRuleName:(Ljava/lang/String;)Ljava/lang/String;
      20: astore        6
      22: aload_0
      23: getfield      #19                 // Field grammar:Lantlr/Grammar;
      26: aload         6
      28: invokevirtual #37                 // Method antlr/Grammar.isDefined:(Ljava/lang/String;)Z
      31: ifne          50
      34: aload_0
      35: getfield      #19                 // Field grammar:Lantlr/Grammar;
      38: new           #39                 // class antlr/RuleSymbol
      41: dup
      42: aload         6
      44: invokespecial #50                 // Method antlr/RuleSymbol."<init>":(Ljava/lang/String;)V
      47: invokevirtual #51                 // Method antlr/Grammar.define:(Lantlr/RuleSymbol;)V
      50: return

  public void refSemPred(antlr.Token);
    Code:
       0: return

  public void refStringLiteral(antlr.Token, antlr.Token, int, boolean);
    Code:
       0: aload_0
       1: aload_1
       2: aload_2
       3: iload_3
       4: iload         4
       6: invokevirtual #95                 // Method _refStringLiteral:(Lantlr/Token;Lantlr/Token;IZ)V
       9: return

  public void refToken(antlr.Token, antlr.Token, antlr.Token, antlr.Token, boolean, int, boolean);
    Code:
       0: aload_0
       1: aload_1
       2: aload_2
       3: aload_3
       4: aload         4
       6: iload         5
       8: iload         6
      10: iload         7
      12: invokevirtual #96                 // Method _refToken:(Lantlr/Token;Lantlr/Token;Lantlr/Token;Lantlr/Token;ZIZ)V
      15: return

  public void refTokenRange(antlr.Token, antlr.Token, antlr.Token, int, boolean);
    Code:
       0: aload_1
       1: invokevirtual #21                 // Method antlr/Token.getText:()Ljava/lang/String;
       4: iconst_0
       5: invokevirtual #97                 // Method java/lang/String.charAt:(I)C
       8: bipush        34
      10: if_icmpne     25
      13: aload_0
      14: aload_1
      15: aconst_null
      16: iconst_1
      17: iload         5
      19: invokevirtual #98                 // Method refStringLiteral:(Lantlr/Token;Lantlr/Token;IZ)V
      22: goto          37
      25: aload_0
      26: aconst_null
      27: aload_1
      28: aconst_null
      29: aconst_null
      30: iconst_0
      31: iconst_1
      32: iload         5
      34: invokevirtual #96                 // Method _refToken:(Lantlr/Token;Lantlr/Token;Lantlr/Token;Lantlr/Token;ZIZ)V
      37: aload_2
      38: invokevirtual #21                 // Method antlr/Token.getText:()Ljava/lang/String;
      41: iconst_0
      42: invokevirtual #97                 // Method java/lang/String.charAt:(I)C
      45: bipush        34
      47: if_icmpne     62
      50: aload_0
      51: aload_2
      52: aconst_null
      53: iconst_1
      54: iload         5
      56: invokevirtual #95                 // Method _refStringLiteral:(Lantlr/Token;Lantlr/Token;IZ)V
      59: goto          74
      62: aload_0
      63: aconst_null
      64: aload_2
      65: aconst_null
      66: aconst_null
      67: iconst_0
      68: iconst_1
      69: iload         5
      71: invokevirtual #96                 // Method _refToken:(Lantlr/Token;Lantlr/Token;Lantlr/Token;Lantlr/Token;ZIZ)V
      74: return

  public void refTreeSpecifier(antlr.Token);
    Code:
       0: return

  public void refWildcard(antlr.Token, antlr.Token, int);
    Code:
       0: return

  public void reset();
    Code:
       0: aload_0
       1: aconst_null
       2: putfield      #19                 // Field grammar:Lantlr/Grammar;
       5: return

  public void setArgOfRuleRef(antlr.Token);
    Code:
       0: return

  public void setCharVocabulary(antlr.collections.impl.BitSet);
    Code:
       0: aload_0
       1: getfield      #19                 // Field grammar:Lantlr/Grammar;
       4: checkcast     #20                 // class antlr/LexerGrammar
       7: aload_1
       8: invokevirtual #99                 // Method antlr/LexerGrammar.setCharVocabulary:(Lantlr/collections/impl/BitSet;)V
      11: return

  public void setFileOption(antlr.Token, antlr.Token, java.lang.String);
    Code:
       0: aload_1
       1: invokevirtual #21                 // Method antlr/Token.getText:()Ljava/lang/String;
       4: ldc           #100                // String language
       6: invokevirtual #72                 // Method java/lang/String.equals:(Ljava/lang/Object;)Z
       9: ifeq          92
      12: aload_2
      13: invokevirtual #101                // Method antlr/Token.getType:()I
      16: bipush        6
      18: if_icmpne     42
      21: aload_0
      22: aload_2
      23: invokevirtual #21                 // Method antlr/Token.getText:()Ljava/lang/String;
      26: bipush        34
      28: invokestatic  #102                // Method antlr/StringUtils.stripFront:(Ljava/lang/String;C)Ljava/lang/String;
      31: bipush        34
      33: invokestatic  #103                // Method antlr/StringUtils.stripBack:(Ljava/lang/String;C)Ljava/lang/String;
      36: putfield      #12                 // Field language:Ljava/lang/String;
      39: goto          765
      42: aload_2
      43: invokevirtual #101                // Method antlr/Token.getType:()I
      46: bipush        24
      48: if_icmpeq     60
      51: aload_2
      52: invokevirtual #101                // Method antlr/Token.getType:()I
      55: bipush        41
      57: if_icmpne     71
      60: aload_0
      61: aload_2
      62: invokevirtual #21                 // Method antlr/Token.getText:()Ljava/lang/String;
      65: putfield      #12                 // Field language:Ljava/lang/String;
      68: goto          765
      71: aload_0
      72: getfield      #16                 // Field tool:Lantlr/Tool;
      75: ldc           #104                // String language option must be string or identifier
      77: aload_3
      78: aload_2
      79: invokevirtual #47                 // Method antlr/Token.getLine:()I
      82: aload_2
      83: invokevirtual #48                 // Method antlr/Token.getColumn:()I
      86: invokevirtual #49                 // Method antlr/Tool.error:(Ljava/lang/String;Ljava/lang/String;II)V
      89: goto          765
      92: aload_1
      93: invokevirtual #21                 // Method antlr/Token.getText:()Ljava/lang/String;
      96: ldc           #105                // String mangleLiteralPrefix
      98: invokevirtual #72                 // Method java/lang/String.equals:(Ljava/lang/Object;)Z
     101: ifeq          155
     104: aload_2
     105: invokevirtual #101                // Method antlr/Token.getType:()I
     108: bipush        6
     110: if_icmpne     134
     113: aload_0
     114: getfield      #16                 // Field tool:Lantlr/Tool;
     117: aload_2
     118: invokevirtual #21                 // Method antlr/Token.getText:()Ljava/lang/String;
     121: ldc           #88                 // String \"
     123: ldc           #88                 // String \"
     125: invokestatic  #89                 // Method antlr/StringUtils.stripFrontBack:(Ljava/lang/String;Ljava/lang/String;Ljava/lang/String;)Ljava/lang/String;
     128: putfield      #106                // Field antlr/Tool.literalsPrefix:Ljava/lang/String;
     131: goto          765
     134: aload_0
     135: getfield      #16                 // Field tool:Lantlr/Tool;
     138: ldc           #107                // String mangleLiteralPrefix option must be string
     140: aload_3
     141: aload_2
     142: invokevirtual #47                 // Method antlr/Token.getLine:()I
     145: aload_2
     146: invokevirtual #48                 // Method antlr/Token.getColumn:()I
     149: invokevirtual #49                 // Method antlr/Tool.error:(Ljava/lang/String;Ljava/lang/String;II)V
     152: goto          765
     155: aload_1
     156: invokevirtual #21                 // Method antlr/Token.getText:()Ljava/lang/String;
     159: ldc           #108                // String upperCaseMangledLiterals
     161: invokevirtual #72                 // Method java/lang/String.equals:(Ljava/lang/Object;)Z
     164: ifeq          237
     167: aload_2
     168: invokevirtual #21                 // Method antlr/Token.getText:()Ljava/lang/String;
     171: ldc           #109                // String true
     173: invokevirtual #72                 // Method java/lang/String.equals:(Ljava/lang/Object;)Z
     176: ifeq          190
     179: aload_0
     180: getfield      #16                 // Field tool:Lantlr/Tool;
     183: iconst_1
     184: putfield      #110                // Field antlr/Tool.upperCaseMangledLiterals:Z
     187: goto          765
     190: aload_2
     191: invokevirtual #21                 // Method antlr/Token.getText:()Ljava/lang/String;
     194: ldc           #111                // String false
     196: invokevirtual #72                 // Method java/lang/String.equals:(Ljava/lang/Object;)Z
     199: ifeq          213
     202: aload_0
     203: getfield      #16                 // Field tool:Lantlr/Tool;
     206: iconst_0
     207: putfield      #110                // Field antlr/Tool.upperCaseMangledLiterals:Z
     210: goto          765
     213: aload_0
     214: getfield      #19                 // Field grammar:Lantlr/Grammar;
     217: getfield      #112                // Field antlr/Grammar.antlrTool:Lantlr/Tool;
     220: ldc           #113                // String Value for upperCaseMangledLiterals must be true or false
     222: aload_3
     223: aload_1
     224: invokevirtual #47                 // Method antlr/Token.getLine:()I
     227: aload_1
     228: invokevirtual #48                 // Method antlr/Token.getColumn:()I
     231: invokevirtual #49                 // Method antlr/Tool.error:(Ljava/lang/String;Ljava/lang/String;II)V
     234: goto          765
     237: aload_1
     238: invokevirtual #21                 // Method antlr/Token.getText:()Ljava/lang/String;
     241: ldc           #114                // String namespaceStd
     243: invokevirtual #72                 // Method java/lang/String.equals:(Ljava/lang/Object;)Z
     246: ifne          273
     249: aload_1
     250: invokevirtual #21                 // Method antlr/Token.getText:()Ljava/lang/String;
     253: ldc           #115                // String namespaceAntlr
     255: invokevirtual #72                 // Method java/lang/String.equals:(Ljava/lang/Object;)Z
     258: ifne          273
     261: aload_1
     262: invokevirtual #21                 // Method antlr/Token.getText:()Ljava/lang/String;
     265: ldc           #116                // String genHashLines
     267: invokevirtual #72                 // Method java/lang/String.equals:(Ljava/lang/Object;)Z
     270: ifeq          574
     273: aload_0
     274: getfield      #12                 // Field language:Ljava/lang/String;
     277: ldc           #117                // String Cpp
     279: invokevirtual #72                 // Method java/lang/String.equals:(Ljava/lang/Object;)Z
     282: ifne          326
     285: aload_0
     286: getfield      #16                 // Field tool:Lantlr/Tool;
     289: new           #41                 // class java/lang/StringBuffer
     292: dup
     293: invokespecial #42                 // Method java/lang/StringBuffer."<init>":()V
     296: aload_1
     297: invokevirtual #21                 // Method antlr/Token.getText:()Ljava/lang/String;
     300: invokevirtual #44                 // Method java/lang/StringBuffer.append:(Ljava/lang/String;)Ljava/lang/StringBuffer;
     303: ldc           #118                // String  option only valid for C++
     305: invokevirtual #44                 // Method java/lang/StringBuffer.append:(Ljava/lang/String;)Ljava/lang/StringBuffer;
     308: invokevirtual #45                 // Method java/lang/StringBuffer.toString:()Ljava/lang/String;
     311: aload_3
     312: aload_1
     313: invokevirtual #47                 // Method antlr/Token.getLine:()I
     316: aload_1
     317: invokevirtual #48                 // Method antlr/Token.getColumn:()I
     320: invokevirtual #49                 // Method antlr/Tool.error:(Ljava/lang/String;Ljava/lang/String;II)V
     323: goto          765
     326: aload_1
     327: invokevirtual #21                 // Method antlr/Token.getText:()Ljava/lang/String;
     330: ldc           #119                // String noConstructors
     332: invokevirtual #72                 // Method java/lang/String.equals:(Ljava/lang/Object;)Z
     335: ifeq          399
     338: aload_2
     339: invokevirtual #21                 // Method antlr/Token.getText:()Ljava/lang/String;
     342: ldc           #109                // String true
     344: invokevirtual #72                 // Method java/lang/String.equals:(Ljava/lang/Object;)Z
     347: ifne          380
     350: aload_2
     351: invokevirtual #21                 // Method antlr/Token.getText:()Ljava/lang/String;
     354: ldc           #111                // String false
     356: invokevirtual #72                 // Method java/lang/String.equals:(Ljava/lang/Object;)Z
     359: ifne          380
     362: aload_0
     363: getfield      #16                 // Field tool:Lantlr/Tool;
     366: ldc           #120                // String noConstructors option must be true or false
     368: aload_3
     369: aload_2
     370: invokevirtual #47                 // Method antlr/Token.getLine:()I
     373: aload_2
     374: invokevirtual #48                 // Method antlr/Token.getColumn:()I
     377: invokevirtual #49                 // Method antlr/Tool.error:(Ljava/lang/String;Ljava/lang/String;II)V
     380: aload_0
     381: getfield      #16                 // Field tool:Lantlr/Tool;
     384: aload_2
     385: invokevirtual #21                 // Method antlr/Token.getText:()Ljava/lang/String;
     388: ldc           #109                // String true
     390: invokevirtual #72                 // Method java/lang/String.equals:(Ljava/lang/Object;)Z
     393: putfield      #121                // Field antlr/Tool.noConstructors:Z
     396: goto          765
     399: aload_1
     400: invokevirtual #21                 // Method antlr/Token.getText:()Ljava/lang/String;
     403: ldc           #116                // String genHashLines
     405: invokevirtual #72                 // Method java/lang/String.equals:(Ljava/lang/Object;)Z
     408: ifeq          472
     411: aload_2
     412: invokevirtual #21                 // Method antlr/Token.getText:()Ljava/lang/String;
     415: ldc           #109                // String true
     417: invokevirtual #72                 // Method java/lang/String.equals:(Ljava/lang/Object;)Z
     420: ifne          453
     423: aload_2
     424: invokevirtual #21                 // Method antlr/Token.getText:()Ljava/lang/String;
     427: ldc           #111                // String false
     429: invokevirtual #72                 // Method java/lang/String.equals:(Ljava/lang/Object;)Z
     432: ifne          453
     435: aload_0
     436: getfield      #16                 // Field tool:Lantlr/Tool;
     439: ldc           #122                // String genHashLines option must be true or false
     441: aload_3
     442: aload_2
     443: invokevirtual #47                 // Method antlr/Token.getLine:()I
     446: aload_2
     447: invokevirtual #48                 // Method antlr/Token.getColumn:()I
     450: invokevirtual #49                 // Method antlr/Tool.error:(Ljava/lang/String;Ljava/lang/String;II)V
     453: aload_0
     454: getfield      #16                 // Field tool:Lantlr/Tool;
     457: aload_2
     458: invokevirtual #21                 // Method antlr/Token.getText:()Ljava/lang/String;
     461: ldc           #109                // String true
     463: invokevirtual #72                 // Method java/lang/String.equals:(Ljava/lang/Object;)Z
     466: putfield      #123                // Field antlr/Tool.genHashLines:Z
     469: goto          765
     472: aload_2
     473: invokevirtual #101                // Method antlr/Token.getType:()I
     476: bipush        6
     478: if_icmpeq     522
     481: aload_0
     482: getfield      #16                 // Field tool:Lantlr/Tool;
     485: new           #41                 // class java/lang/StringBuffer
     488: dup
     489: invokespecial #42                 // Method java/lang/StringBuffer."<init>":()V
     492: aload_1
     493: invokevirtual #21                 // Method antlr/Token.getText:()Ljava/lang/String;
     496: invokevirtual #44                 // Method java/lang/StringBuffer.append:(Ljava/lang/String;)Ljava/lang/StringBuffer;
     499: ldc           #124                // String  option must be a string
     501: invokevirtual #44                 // Method java/lang/StringBuffer.append:(Ljava/lang/String;)Ljava/lang/StringBuffer;
     504: invokevirtual #45                 // Method java/lang/StringBuffer.toString:()Ljava/lang/String;
     507: aload_3
     508: aload_2
     509: invokevirtual #47                 // Method antlr/Token.getLine:()I
     512: aload_2
     513: invokevirtual #48                 // Method antlr/Token.getColumn:()I
     516: invokevirtual #49                 // Method antlr/Tool.error:(Ljava/lang/String;Ljava/lang/String;II)V
     519: goto          765
     522: aload_1
     523: invokevirtual #21                 // Method antlr/Token.getText:()Ljava/lang/String;
     526: ldc           #114                // String namespaceStd
     528: invokevirtual #72                 // Method java/lang/String.equals:(Ljava/lang/Object;)Z
     531: ifeq          548
     534: aload_0
     535: getfield      #16                 // Field tool:Lantlr/Tool;
     538: aload_2
     539: invokevirtual #21                 // Method antlr/Token.getText:()Ljava/lang/String;
     542: putfield      #125                // Field antlr/Tool.namespaceStd:Ljava/lang/String;
     545: goto          765
     548: aload_1
     549: invokevirtual #21                 // Method antlr/Token.getText:()Ljava/lang/String;
     552: ldc           #115                // String namespaceAntlr
     554: invokevirtual #72                 // Method java/lang/String.equals:(Ljava/lang/Object;)Z
     557: ifeq          765
     560: aload_0
     561: getfield      #16                 // Field tool:Lantlr/Tool;
     564: aload_2
     565: invokevirtual #21                 // Method antlr/Token.getText:()Ljava/lang/String;
     568: putfield      #126                // Field antlr/Tool.namespaceAntlr:Ljava/lang/String;
     571: goto          765
     574: aload_1
     575: invokevirtual #21                 // Method antlr/Token.getText:()Ljava/lang/String;
     578: ldc           #127                // String namespace
     580: invokevirtual #72                 // Method java/lang/String.equals:(Ljava/lang/Object;)Z
     583: ifeq          727
     586: aload_0
     587: getfield      #12                 // Field language:Ljava/lang/String;
     590: ldc           #117                // String Cpp
     592: invokevirtual #72                 // Method java/lang/String.equals:(Ljava/lang/Object;)Z
     595: ifne          651
     598: aload_0
     599: getfield      #12                 // Field language:Ljava/lang/String;
     602: ldc           #128                // String CSharp
     604: invokevirtual #72                 // Method java/lang/String.equals:(Ljava/lang/Object;)Z
     607: ifne          651
     610: aload_0
     611: getfield      #16                 // Field tool:Lantlr/Tool;
     614: new           #41                 // class java/lang/StringBuffer
     617: dup
     618: invokespecial #42                 // Method java/lang/StringBuffer."<init>":()V
     621: aload_1
     622: invokevirtual #21                 // Method antlr/Token.getText:()Ljava/lang/String;
     625: invokevirtual #44                 // Method java/lang/StringBuffer.append:(Ljava/lang/String;)Ljava/lang/StringBuffer;
     628: ldc           #129                // String  option only valid for C++ and C# (a.k.a CSharp)
     630: invokevirtual #44                 // Method java/lang/StringBuffer.append:(Ljava/lang/String;)Ljava/lang/StringBuffer;
     633: invokevirtual #45                 // Method java/lang/StringBuffer.toString:()Ljava/lang/String;
     636: aload_3
     637: aload_1
     638: invokevirtual #47                 // Method antlr/Token.getLine:()I
     641: aload_1
     642: invokevirtual #48                 // Method antlr/Token.getColumn:()I
     645: invokevirtual #49                 // Method antlr/Tool.error:(Ljava/lang/String;Ljava/lang/String;II)V
     648: goto          765
     651: aload_2
     652: invokevirtual #101                // Method antlr/Token.getType:()I
     655: bipush        6
     657: if_icmpeq     701
     660: aload_0
     661: getfield      #16                 // Field tool:Lantlr/Tool;
     664: new           #41                 // class java/lang/StringBuffer
     667: dup
     668: invokespecial #42                 // Method java/lang/StringBuffer."<init>":()V
     671: aload_1
     672: invokevirtual #21                 // Method antlr/Token.getText:()Ljava/lang/String;
     675: invokevirtual #44                 // Method java/lang/StringBuffer.append:(Ljava/lang/String;)Ljava/lang/StringBuffer;
     678: ldc           #124                // String  option must be a string
     680: invokevirtual #44                 // Method java/lang/StringBuffer.append:(Ljava/lang/String;)Ljava/lang/StringBuffer;
     683: invokevirtual #45                 // Method java/lang/StringBuffer.toString:()Ljava/lang/String;
     686: aload_3
     687: aload_2
     688: invokevirtual #47                 // Method antlr/Token.getLine:()I
     691: aload_2
     692: invokevirtual #48                 // Method antlr/Token.getColumn:()I
     695: invokevirtual #49                 // Method antlr/Tool.error:(Ljava/lang/String;Ljava/lang/String;II)V
     698: goto          765
     701: aload_1
     702: invokevirtual #21                 // Method antlr/Token.getText:()Ljava/lang/String;
     705: ldc           #127                // String namespace
     707: invokevirtual #72                 // Method java/lang/String.equals:(Ljava/lang/Object;)Z
     710: ifeq          765
     713: aload_0
     714: getfield      #16                 // Field tool:Lantlr/Tool;
     717: aload_2
     718: invokevirtual #21                 // Method antlr/Token.getText:()Ljava/lang/String;
     721: invokevirtual #130                // Method antlr/Tool.setNameSpace:(Ljava/lang/String;)V
     724: goto          765
     727: aload_0
     728: getfield      #16                 // Field tool:Lantlr/Tool;
     731: new           #41                 // class java/lang/StringBuffer
     734: dup
     735: invokespecial #42                 // Method java/lang/StringBuffer."<init>":()V
     738: ldc           #131                // String Invalid file-level option:
     740: invokevirtual #44                 // Method java/lang/StringBuffer.append:(Ljava/lang/String;)Ljava/lang/StringBuffer;
     743: aload_1
     744: invokevirtual #21                 // Method antlr/Token.getText:()Ljava/lang/String;
     747: invokevirtual #44                 // Method java/lang/StringBuffer.append:(Ljava/lang/String;)Ljava/lang/StringBuffer;
     750: invokevirtual #45                 // Method java/lang/StringBuffer.toString:()Ljava/lang/String;
     753: aload_3
     754: aload_1
     755: invokevirtual #47                 // Method antlr/Token.getLine:()I
     758: aload_2
     759: invokevirtual #48                 // Method antlr/Token.getColumn:()I
     762: invokevirtual #49                 // Method antlr/Tool.error:(Ljava/lang/String;Ljava/lang/String;II)V
     765: return

  public void setGrammarOption(antlr.Token, antlr.Token);
    Code:
       0: aload_1
       1: invokevirtual #21                 // Method antlr/Token.getText:()Ljava/lang/String;
       4: ldc           #132                // String tokdef
       6: invokevirtual #72                 // Method java/lang/String.equals:(Ljava/lang/Object;)Z
       9: ifne          24
      12: aload_1
      13: invokevirtual #21                 // Method antlr/Token.getText:()Ljava/lang/String;
      16: ldc           #133                // String tokenVocabulary
      18: invokevirtual #72                 // Method java/lang/String.equals:(Ljava/lang/Object;)Z
      21: ifeq          51
      24: aload_0
      25: getfield      #16                 // Field tool:Lantlr/Tool;
      28: ldc           #134                // String tokdef/tokenVocabulary options are invalid >= ANTLR 2.6.0.\n  Use importVocab/exportVocab instead.  Please see the documentation.\n  The previous options were so heinous that Terence changed the whole\n  vocabulary mechanism; it was better to change the names rather than\n  subtly change the functionality of the known options.  Sorry!
      30: aload_0
      31: getfield      #19                 // Field grammar:Lantlr/Grammar;
      34: invokevirtual #46                 // Method antlr/Grammar.getFilename:()Ljava/lang/String;
      37: aload_2
      38: invokevirtual #47                 // Method antlr/Token.getLine:()I
      41: aload_2
      42: invokevirtual #48                 // Method antlr/Token.getColumn:()I
      45: invokevirtual #49                 // Method antlr/Tool.error:(Ljava/lang/String;Ljava/lang/String;II)V
      48: goto          332
      51: aload_1
      52: invokevirtual #21                 // Method antlr/Token.getText:()Ljava/lang/String;
      55: ldc           #135                // String literal
      57: invokevirtual #72                 // Method java/lang/String.equals:(Ljava/lang/Object;)Z
      60: ifeq          100
      63: aload_0
      64: getfield      #19                 // Field grammar:Lantlr/Grammar;
      67: instanceof    #20                 // class antlr/LexerGrammar
      70: ifeq          100
      73: aload_0
      74: getfield      #16                 // Field tool:Lantlr/Tool;
      77: ldc           #136                // String the literal option is invalid >= ANTLR 2.6.0.\n  Use the \"tokens {...}\" mechanism instead.
      79: aload_0
      80: getfield      #19                 // Field grammar:Lantlr/Grammar;
      83: invokevirtual #46                 // Method antlr/Grammar.getFilename:()Ljava/lang/String;
      86: aload_2
      87: invokevirtual #47                 // Method antlr/Token.getLine:()I
      90: aload_2
      91: invokevirtual #48                 // Method antlr/Token.getColumn:()I
      94: invokevirtual #49                 // Method antlr/Tool.error:(Ljava/lang/String;Ljava/lang/String;II)V
      97: goto          332
     100: aload_1
     101: invokevirtual #21                 // Method antlr/Token.getText:()Ljava/lang/String;
     104: ldc           #137                // String exportVocab
     106: invokevirtual #72                 // Method java/lang/String.equals:(Ljava/lang/Object;)Z
     109: ifeq          171
     112: aload_2
     113: invokevirtual #101                // Method antlr/Token.getType:()I
     116: bipush        41
     118: if_icmpeq     130
     121: aload_2
     122: invokevirtual #101                // Method antlr/Token.getType:()I
     125: bipush        24
     127: if_icmpne     144
     130: aload_0
     131: getfield      #19                 // Field grammar:Lantlr/Grammar;
     134: aload_2
     135: invokevirtual #21                 // Method antlr/Token.getText:()Ljava/lang/String;
     138: putfield      #62                 // Field antlr/Grammar.exportVocab:Ljava/lang/String;
     141: goto          332
     144: aload_0
     145: getfield      #16                 // Field tool:Lantlr/Tool;
     148: ldc           #138                // String exportVocab must be an identifier
     150: aload_0
     151: getfield      #19                 // Field grammar:Lantlr/Grammar;
     154: invokevirtual #46                 // Method antlr/Grammar.getFilename:()Ljava/lang/String;
     157: aload_2
     158: invokevirtual #47                 // Method antlr/Token.getLine:()I
     161: aload_2
     162: invokevirtual #48                 // Method antlr/Token.getColumn:()I
     165: invokevirtual #49                 // Method antlr/Tool.error:(Ljava/lang/String;Ljava/lang/String;II)V
     168: goto          332
     171: aload_1
     172: invokevirtual #21                 // Method antlr/Token.getText:()Ljava/lang/String;
     175: ldc           #139                // String importVocab
     177: invokevirtual #72                 // Method java/lang/String.equals:(Ljava/lang/Object;)Z
     180: ifeq          242
     183: aload_2
     184: invokevirtual #101                // Method antlr/Token.getType:()I
     187: bipush        41
     189: if_icmpeq     201
     192: aload_2
     193: invokevirtual #101                // Method antlr/Token.getType:()I
     196: bipush        24
     198: if_icmpne     215
     201: aload_0
     202: getfield      #19                 // Field grammar:Lantlr/Grammar;
     205: aload_2
     206: invokevirtual #21                 // Method antlr/Token.getText:()Ljava/lang/String;
     209: putfield      #63                 // Field antlr/Grammar.importVocab:Ljava/lang/String;
     212: goto          332
     215: aload_0
     216: getfield      #16                 // Field tool:Lantlr/Tool;
     219: ldc           #140                // String importVocab must be an identifier
     221: aload_0
     222: getfield      #19                 // Field grammar:Lantlr/Grammar;
     225: invokevirtual #46                 // Method antlr/Grammar.getFilename:()Ljava/lang/String;
     228: aload_2
     229: invokevirtual #47                 // Method antlr/Token.getLine:()I
     232: aload_2
     233: invokevirtual #48                 // Method antlr/Token.getColumn:()I
     236: invokevirtual #49                 // Method antlr/Tool.error:(Ljava/lang/String;Ljava/lang/String;II)V
     239: goto          332
     242: aload_1
     243: invokevirtual #21                 // Method antlr/Token.getText:()Ljava/lang/String;
     246: ldc           #141                // String k
     248: invokevirtual #72                 // Method java/lang/String.equals:(Ljava/lang/Object;)Z
     251: ifeq          319
     254: aload_0
     255: getfield      #19                 // Field grammar:Lantlr/Grammar;
     258: instanceof    #142                // class antlr/TreeWalkerGrammar
     261: ifeq          303
     264: aload_2
     265: invokevirtual #21                 // Method antlr/Token.getText:()Ljava/lang/String;
     268: ldc           #143                // String 1
     270: invokevirtual #72                 // Method java/lang/String.equals:(Ljava/lang/Object;)Z
     273: ifne          303
     276: aload_0
     277: getfield      #16                 // Field tool:Lantlr/Tool;
     280: ldc           #144                // String Treewalkers only support k=1
     282: aload_0
     283: getfield      #19                 // Field grammar:Lantlr/Grammar;
     286: invokevirtual #46                 // Method antlr/Grammar.getFilename:()Ljava/lang/String;
     289: aload_2
     290: invokevirtual #47                 // Method antlr/Token.getLine:()I
     293: aload_2
     294: invokevirtual #48                 // Method antlr/Token.getColumn:()I
     297: invokevirtual #49                 // Method antlr/Tool.error:(Ljava/lang/String;Ljava/lang/String;II)V
     300: goto          332
     303: aload_0
     304: getfield      #19                 // Field grammar:Lantlr/Grammar;
     307: aload_1
     308: invokevirtual #21                 // Method antlr/Token.getText:()Ljava/lang/String;
     311: aload_2
     312: invokevirtual #145                // Method antlr/Grammar.setOption:(Ljava/lang/String;Lantlr/Token;)Z
     315: pop
     316: goto          332
     319: aload_0
     320: getfield      #19                 // Field grammar:Lantlr/Grammar;
     323: aload_1
     324: invokevirtual #21                 // Method antlr/Token.getText:()Ljava/lang/String;
     327: aload_2
     328: invokevirtual #145                // Method antlr/Grammar.setOption:(Ljava/lang/String;Lantlr/Token;)Z
     331: pop
     332: return

  public void setRuleOption(antlr.Token, antlr.Token);
    Code:
       0: return

  public void setSubruleOption(antlr.Token, antlr.Token);
    Code:
       0: return

  public void startLexer(java.lang.String, antlr.Token, java.lang.String, java.lang.String);
    Code:
       0: aload_0
       1: getfield      #13                 // Field numLexers:I
       4: ifle          36
       7: aload_0
       8: getfield      #16                 // Field tool:Lantlr/Tool;
      11: new           #41                 // class java/lang/StringBuffer
      14: dup
      15: invokespecial #42                 // Method java/lang/StringBuffer."<init>":()V
      18: ldc           #146                // String You may only have one lexer per grammar file: class
      20: invokevirtual #44                 // Method java/lang/StringBuffer.append:(Ljava/lang/String;)Ljava/lang/StringBuffer;
      23: aload_2
      24: invokevirtual #21                 // Method antlr/Token.getText:()Ljava/lang/String;
      27: invokevirtual #44                 // Method java/lang/StringBuffer.append:(Ljava/lang/String;)Ljava/lang/StringBuffer;
      30: invokevirtual #45                 // Method java/lang/StringBuffer.toString:()Ljava/lang/String;
      33: invokevirtual #147                // Method antlr/Tool.panic:(Ljava/lang/String;)V
      36: aload_0
      37: dup
      38: getfield      #13                 // Field numLexers:I
      41: iconst_1
      42: iadd
      43: putfield      #13                 // Field numLexers:I
      46: aload_0
      47: invokevirtual #148                // Method reset:()V
      50: aload_0
      51: getfield      #4                  // Field grammars:Ljava/util/Hashtable;
      54: aload_2
      55: invokevirtual #66                 // Method java/util/Hashtable.get:(Ljava/lang/Object;)Ljava/lang/Object;
      58: checkcast     #149                // class antlr/Grammar
      61: astore        5
      63: aload         5
      65: ifnull        150
      68: aload         5
      70: instanceof    #20                 // class antlr/LexerGrammar
      73: ifne          113
      76: aload_0
      77: getfield      #16                 // Field tool:Lantlr/Tool;
      80: new           #41                 // class java/lang/StringBuffer
      83: dup
      84: invokespecial #42                 // Method java/lang/StringBuffer."<init>":()V
      87: ldc           #150                // String \'
      89: invokevirtual #44                 // Method java/lang/StringBuffer.append:(Ljava/lang/String;)Ljava/lang/StringBuffer;
      92: aload_2
      93: invokevirtual #21                 // Method antlr/Token.getText:()Ljava/lang/String;
      96: invokevirtual #44                 // Method java/lang/StringBuffer.append:(Ljava/lang/String;)Ljava/lang/StringBuffer;
      99: ldc           #151                // String \' is already defined as a non-lexer
     101: invokevirtual #44                 // Method java/lang/StringBuffer.append:(Ljava/lang/String;)Ljava/lang/StringBuffer;
     104: invokevirtual #45                 // Method java/lang/StringBuffer.toString:()Ljava/lang/String;
     107: invokevirtual #147                // Method antlr/Tool.panic:(Ljava/lang/String;)V
     110: goto          234
     113: aload_0
     114: getfield      #16                 // Field tool:Lantlr/Tool;
     117: new           #41                 // class java/lang/StringBuffer
     120: dup
     121: invokespecial #42                 // Method java/lang/StringBuffer."<init>":()V
     124: ldc           #152                // String Lexer \'
     126: invokevirtual #44                 // Method java/lang/StringBuffer.append:(Ljava/lang/String;)Ljava/lang/StringBuffer;
     129: aload_2
     130: invokevirtual #21                 // Method antlr/Token.getText:()Ljava/lang/String;
     133: invokevirtual #44                 // Method java/lang/StringBuffer.append:(Ljava/lang/String;)Ljava/lang/StringBuffer;
     136: ldc           #153                // String \' is already defined
     138: invokevirtual #44                 // Method java/lang/StringBuffer.append:(Ljava/lang/String;)Ljava/lang/StringBuffer;
     141: invokevirtual #45                 // Method java/lang/StringBuffer.toString:()Ljava/lang/String;
     144: invokevirtual #147                // Method antlr/Tool.panic:(Ljava/lang/String;)V
     147: goto          234
     150: new           #20                 // class antlr/LexerGrammar
     153: dup
     154: aload_2
     155: invokevirtual #21                 // Method antlr/Token.getText:()Ljava/lang/String;
     158: aload_0
     159: getfield      #16                 // Field tool:Lantlr/Tool;
     162: aload_3
     163: invokespecial #154                // Method antlr/LexerGrammar."<init>":(Ljava/lang/String;Lantlr/Tool;Ljava/lang/String;)V
     166: astore        6
     168: aload         6
     170: aload         4
     172: putfield      #155                // Field antlr/LexerGrammar.comment:Ljava/lang/String;
     175: aload         6
     177: aload_0
     178: getfield      #17                 // Field args:[Ljava/lang/String;
     181: invokevirtual #156                // Method antlr/LexerGrammar.processArguments:([Ljava/lang/String;)V
     184: aload         6
     186: aload_1
     187: invokevirtual #157                // Method antlr/LexerGrammar.setFilename:(Ljava/lang/String;)V
     190: aload_0
     191: getfield      #4                  // Field grammars:Ljava/util/Hashtable;
     194: aload         6
     196: invokevirtual #158                // Method antlr/LexerGrammar.getClassName:()Ljava/lang/String;
     199: aload         6
     201: invokevirtual #71                 // Method java/util/Hashtable.put:(Ljava/lang/Object;Ljava/lang/Object;)Ljava/lang/Object;
     204: pop
     205: aload         6
     207: aload_0
     208: getfield      #10                 // Field thePreambleAction:Lantlr/Token;
     211: putfield      #159                // Field antlr/LexerGrammar.preambleAction:Lantlr/Token;
     214: aload_0
     215: new           #7                  // class antlr/CommonToken
     218: dup
     219: iconst_0
     220: ldc           #8                  // String
     222: invokespecial #9                  // Method antlr/CommonToken."<init>":(ILjava/lang/String;)V
     225: putfield      #10                 // Field thePreambleAction:Lantlr/Token;
     228: aload_0
     229: aload         6
     231: putfield      #19                 // Field grammar:Lantlr/Grammar;
     234: return

  public void startParser(java.lang.String, antlr.Token, java.lang.String, java.lang.String);
    Code:
       0: aload_0
       1: getfield      #14                 // Field numParsers:I
       4: ifle          36
       7: aload_0
       8: getfield      #16                 // Field tool:Lantlr/Tool;
      11: new           #41                 // class java/lang/StringBuffer
      14: dup
      15: invokespecial #42                 // Method java/lang/StringBuffer."<init>":()V
      18: ldc           #160                // String You may only have one parser per grammar file: class
      20: invokevirtual #44                 // Method java/lang/StringBuffer.append:(Ljava/lang/String;)Ljava/lang/StringBuffer;
      23: aload_2
      24: invokevirtual #21                 // Method antlr/Token.getText:()Ljava/lang/String;
      27: invokevirtual #44                 // Method java/lang/StringBuffer.append:(Ljava/lang/String;)Ljava/lang/StringBuffer;
      30: invokevirtual #45                 // Method java/lang/StringBuffer.toString:()Ljava/lang/String;
      33: invokevirtual #147                // Method antlr/Tool.panic:(Ljava/lang/String;)V
      36: aload_0
      37: dup
      38: getfield      #14                 // Field numParsers:I
      41: iconst_1
      42: iadd
      43: putfield      #14                 // Field numParsers:I
      46: aload_0
      47: invokevirtual #148                // Method reset:()V
      50: aload_0
      51: getfield      #4                  // Field grammars:Ljava/util/Hashtable;
      54: aload_2
      55: invokevirtual #66                 // Method java/util/Hashtable.get:(Ljava/lang/Object;)Ljava/lang/Object;
      58: checkcast     #149                // class antlr/Grammar
      61: astore        5
      63: aload         5
      65: ifnull        150
      68: aload         5
      70: instanceof    #161                // class antlr/ParserGrammar
      73: ifne          113
      76: aload_0
      77: getfield      #16                 // Field tool:Lantlr/Tool;
      80: new           #41                 // class java/lang/StringBuffer
      83: dup
      84: invokespecial #42                 // Method java/lang/StringBuffer."<init>":()V
      87: ldc           #150                // String \'
      89: invokevirtual #44                 // Method java/lang/StringBuffer.append:(Ljava/lang/String;)Ljava/lang/StringBuffer;
      92: aload_2
      93: invokevirtual #21                 // Method antlr/Token.getText:()Ljava/lang/String;
      96: invokevirtual #44                 // Method java/lang/StringBuffer.append:(Ljava/lang/String;)Ljava/lang/StringBuffer;
      99: ldc           #162                // String \' is already defined as a non-parser
     101: invokevirtual #44                 // Method java/lang/StringBuffer.append:(Ljava/lang/String;)Ljava/lang/StringBuffer;
     104: invokevirtual #45                 // Method java/lang/StringBuffer.toString:()Ljava/lang/String;
     107: invokevirtual #147                // Method antlr/Tool.panic:(Ljava/lang/String;)V
     110: goto          242
     113: aload_0
     114: getfield      #16                 // Field tool:Lantlr/Tool;
     117: new           #41                 // class java/lang/StringBuffer
     120: dup
     121: invokespecial #42                 // Method java/lang/StringBuffer."<init>":()V
     124: ldc           #163                // String Parser \'
     126: invokevirtual #44                 // Method java/lang/StringBuffer.append:(Ljava/lang/String;)Ljava/lang/StringBuffer;
     129: aload_2
     130: invokevirtual #21                 // Method antlr/Token.getText:()Ljava/lang/String;
     133: invokevirtual #44                 // Method java/lang/StringBuffer.append:(Ljava/lang/String;)Ljava/lang/StringBuffer;
     136: ldc           #153                // String \' is already defined
     138: invokevirtual #44                 // Method java/lang/StringBuffer.append:(Ljava/lang/String;)Ljava/lang/StringBuffer;
     141: invokevirtual #45                 // Method java/lang/StringBuffer.toString:()Ljava/lang/String;
     144: invokevirtual #147                // Method antlr/Tool.panic:(Ljava/lang/String;)V
     147: goto          242
     150: aload_0
     151: new           #161                // class antlr/ParserGrammar
     154: dup
     155: aload_2
     156: invokevirtual #21                 // Method antlr/Token.getText:()Ljava/lang/String;
     159: aload_0
     160: getfield      #16                 // Field tool:Lantlr/Tool;
     163: aload_3
     164: invokespecial #164                // Method antlr/ParserGrammar."<init>":(Ljava/lang/String;Lantlr/Tool;Ljava/lang/String;)V
     167: putfield      #19                 // Field grammar:Lantlr/Grammar;
     170: aload_0
     171: getfield      #19                 // Field grammar:Lantlr/Grammar;
     174: aload         4
     176: putfield      #165                // Field antlr/Grammar.comment:Ljava/lang/String;
     179: aload_0
     180: getfield      #19                 // Field grammar:Lantlr/Grammar;
     183: aload_0
     184: getfield      #17                 // Field args:[Ljava/lang/String;
     187: invokevirtual #166                // Method antlr/Grammar.processArguments:([Ljava/lang/String;)V
     190: aload_0
     191: getfield      #19                 // Field grammar:Lantlr/Grammar;
     194: aload_1
     195: invokevirtual #167                // Method antlr/Grammar.setFilename:(Ljava/lang/String;)V
     198: aload_0
     199: getfield      #4                  // Field grammars:Ljava/util/Hashtable;
     202: aload_0
     203: getfield      #19                 // Field grammar:Lantlr/Grammar;
     206: invokevirtual #33                 // Method antlr/Grammar.getClassName:()Ljava/lang/String;
     209: aload_0
     210: getfield      #19                 // Field grammar:Lantlr/Grammar;
     213: invokevirtual #71                 // Method java/util/Hashtable.put:(Ljava/lang/Object;Ljava/lang/Object;)Ljava/lang/Object;
     216: pop
     217: aload_0
     218: getfield      #19                 // Field grammar:Lantlr/Grammar;
     221: aload_0
     222: getfield      #10                 // Field thePreambleAction:Lantlr/Token;
     225: putfield      #168                // Field antlr/Grammar.preambleAction:Lantlr/Token;
     228: aload_0
     229: new           #7                  // class antlr/CommonToken
     232: dup
     233: iconst_0
     234: ldc           #8                  // String
     236: invokespecial #9                  // Method antlr/CommonToken."<init>":(ILjava/lang/String;)V
     239: putfield      #10                 // Field thePreambleAction:Lantlr/Token;
     242: return

  public void startTreeWalker(java.lang.String, antlr.Token, java.lang.String, java.lang.String);
    Code:
       0: aload_0
       1: getfield      #15                 // Field numTreeParsers:I
       4: ifle          36
       7: aload_0
       8: getfield      #16                 // Field tool:Lantlr/Tool;
      11: new           #41                 // class java/lang/StringBuffer
      14: dup
      15: invokespecial #42                 // Method java/lang/StringBuffer."<init>":()V
      18: ldc           #169                // String You may only have one tree parser per grammar file: class
      20: invokevirtual #44                 // Method java/lang/StringBuffer.append:(Ljava/lang/String;)Ljava/lang/StringBuffer;
      23: aload_2
      24: invokevirtual #21                 // Method antlr/Token.getText:()Ljava/lang/String;
      27: invokevirtual #44                 // Method java/lang/StringBuffer.append:(Ljava/lang/String;)Ljava/lang/StringBuffer;
      30: invokevirtual #45                 // Method java/lang/StringBuffer.toString:()Ljava/lang/String;
      33: invokevirtual #147                // Method antlr/Tool.panic:(Ljava/lang/String;)V
      36: aload_0
      37: dup
      38: getfield      #15                 // Field numTreeParsers:I
      41: iconst_1
      42: iadd
      43: putfield      #15                 // Field numTreeParsers:I
      46: aload_0
      47: invokevirtual #148                // Method reset:()V
      50: aload_0
      51: getfield      #4                  // Field grammars:Ljava/util/Hashtable;
      54: aload_2
      55: invokevirtual #66                 // Method java/util/Hashtable.get:(Ljava/lang/Object;)Ljava/lang/Object;
      58: checkcast     #149                // class antlr/Grammar
      61: astore        5
      63: aload         5
      65: ifnull        150
      68: aload         5
      70: instanceof    #142                // class antlr/TreeWalkerGrammar
      73: ifne          113
      76: aload_0
      77: getfield      #16                 // Field tool:Lantlr/Tool;
      80: new           #41                 // class java/lang/StringBuffer
      83: dup
      84: invokespecial #42                 // Method java/lang/StringBuffer."<init>":()V
      87: ldc           #150                // String \'
      89: invokevirtual #44                 // Method java/lang/StringBuffer.append:(Ljava/lang/String;)Ljava/lang/StringBuffer;
      92: aload_2
      93: invokevirtual #21                 // Method antlr/Token.getText:()Ljava/lang/String;
      96: invokevirtual #44                 // Method java/lang/StringBuffer.append:(Ljava/lang/String;)Ljava/lang/StringBuffer;
      99: ldc           #170                // String \' is already defined as a non-tree-walker
     101: invokevirtual #44                 // Method java/lang/StringBuffer.append:(Ljava/lang/String;)Ljava/lang/StringBuffer;
     104: invokevirtual #45                 // Method java/lang/StringBuffer.toString:()Ljava/lang/String;
     107: invokevirtual #147                // Method antlr/Tool.panic:(Ljava/lang/String;)V
     110: goto          242
     113: aload_0
     114: getfield      #16                 // Field tool:Lantlr/Tool;
     117: new           #41                 // class java/lang/StringBuffer
     120: dup
     121: invokespecial #42                 // Method java/lang/StringBuffer."<init>":()V
     124: ldc           #171                // String Tree-walker \'
     126: invokevirtual #44                 // Method java/lang/StringBuffer.append:(Ljava/lang/String;)Ljava/lang/StringBuffer;
     129: aload_2
     130: invokevirtual #21                 // Method antlr/Token.getText:()Ljava/lang/String;
     133: invokevirtual #44                 // Method java/lang/StringBuffer.append:(Ljava/lang/String;)Ljava/lang/StringBuffer;
     136: ldc           #153                // String \' is already defined
     138: invokevirtual #44                 // Method java/lang/StringBuffer.append:(Ljava/lang/String;)Ljava/lang/StringBuffer;
     141: invokevirtual #45                 // Method java/lang/StringBuffer.toString:()Ljava/lang/String;
     144: invokevirtual #147                // Method antlr/Tool.panic:(Ljava/lang/String;)V
     147: goto          242
     150: aload_0
     151: new           #142                // class antlr/TreeWalkerGrammar
     154: dup
     155: aload_2
     156: invokevirtual #21                 // Method antlr/Token.getText:()Ljava/lang/String;
     159: aload_0
     160: getfield      #16                 // Field tool:Lantlr/Tool;
     163: aload_3
     164: invokespecial #172                // Method antlr/TreeWalkerGrammar."<init>":(Ljava/lang/String;Lantlr/Tool;Ljava/lang/String;)V
     167: putfield      #19                 // Field grammar:Lantlr/Grammar;
     170: aload_0
     171: getfield      #19                 // Field grammar:Lantlr/Grammar;
     174: aload         4
     176: putfield      #165                // Field antlr/Grammar.comment:Ljava/lang/String;
     179: aload_0
     180: getfield      #19                 // Field grammar:Lantlr/Grammar;
     183: aload_0
     184: getfield      #17                 // Field args:[Ljava/lang/String;
     187: invokevirtual #166                // Method antlr/Grammar.processArguments:([Ljava/lang/String;)V
     190: aload_0
     191: getfield      #19                 // Field grammar:Lantlr/Grammar;
     194: aload_1
     195: invokevirtual #167                // Method antlr/Grammar.setFilename:(Ljava/lang/String;)V
     198: aload_0
     199: getfield      #4                  // Field grammars:Ljava/util/Hashtable;
     202: aload_0
     203: getfield      #19                 // Field grammar:Lantlr/Grammar;
     206: invokevirtual #33                 // Method antlr/Grammar.getClassName:()Ljava/lang/String;
     209: aload_0
     210: getfield      #19                 // Field grammar:Lantlr/Grammar;
     213: invokevirtual #71                 // Method java/util/Hashtable.put:(Ljava/lang/Object;Ljava/lang/Object;)Ljava/lang/Object;
     216: pop
     217: aload_0
     218: getfield      #19                 // Field grammar:Lantlr/Grammar;
     221: aload_0
     222: getfield      #10                 // Field thePreambleAction:Lantlr/Token;
     225: putfield      #168                // Field antlr/Grammar.preambleAction:Lantlr/Token;
     228: aload_0
     229: new           #7                  // class antlr/CommonToken
     232: dup
     233: iconst_0
     234: ldc           #8                  // String
     236: invokespecial #9                  // Method antlr/CommonToken."<init>":(ILjava/lang/String;)V
     239: putfield      #10                 // Field thePreambleAction:Lantlr/Token;
     242: return

  public void synPred();
    Code:
       0: return

  public void zeroOrMoreSubRule();
    Code:
       0: return
}
