Compiled from "AbstractPropertyConfiguration.java"
class org.jboss.logmanager.config.AbstractPropertyConfiguration$ModuleFinder {
  private org.jboss.logmanager.config.AbstractPropertyConfiguration$ModuleFinder();
    Code:
       0: aload_0
       1: invokespecial #1                  // Method java/lang/Object."<init>":()V
       4: return

  static java.lang.ClassLoader getClassLoader(java.lang.String) throws java.lang.Exception;
    Code:
       0: ldc_w         #2                  // class org/jboss/logmanager/config/AbstractPropertyConfiguration$ModuleFinder
       3: invokestatic  #3                  // Method org/jboss/modules/ModuleLoader.forClass:(Ljava/lang/Class;)Lorg/jboss/modules/ModuleLoader;
       6: astore_1
       7: aload_1
       8: ifnonnull     15
      11: invokestatic  #4                  // Method org/jboss/modules/Module.getBootModuleLoader:()Lorg/jboss/modules/ModuleLoader;
      14: astore_1
      15: aload_1
      16: aload_0
      17: invokestatic  #5                  // Method org/jboss/modules/ModuleIdentifier.create:(Ljava/lang/String;)Lorg/jboss/modules/ModuleIdentifier;
      20: invokevirtual #6                  // Method org/jboss/modules/ModuleLoader.loadModule:(Lorg/jboss/modules/ModuleIdentifier;)Lorg/jboss/modules/Module;
      23: invokevirtual #7                  // Method org/jboss/modules/Module.getClassLoader:()Lorg/jboss/modules/ModuleClassLoader;
      26: areturn
}
