Compiled from "HandlerConfigurationImpl.java"
class org.jboss.logmanager.config.HandlerConfigurationImpl$6 implements org.jboss.logmanager.config.ConfigAction<java.lang.Void> {
  final java.lang.String[] val$stringsArray;

  final org.jboss.logmanager.config.LogContextConfigurationImpl val$configuration;

  final java.lang.String[] val$oldHandlerNames;

  final org.jboss.logmanager.config.HandlerConfigurationImpl this$0;

  org.jboss.logmanager.config.HandlerConfigurationImpl$6(org.jboss.logmanager.config.HandlerConfigurationImpl, java.lang.String[], org.jboss.logmanager.config.LogContextConfigurationImpl, java.lang.String[]);
    Code:
       0: aload_0
       1: aload_1
       2: putfield      #1                  // Field this$0:Lorg/jboss/logmanager/config/HandlerConfigurationImpl;
       5: aload_0
       6: aload_2
       7: putfield      #2                  // Field val$stringsArray:[Ljava/lang/String;
      10: aload_0
      11: aload_3
      12: putfield      #3                  // Field val$configuration:Lorg/jboss/logmanager/config/LogContextConfigurationImpl;
      15: aload_0
      16: aload         4
      18: putfield      #4                  // Field val$oldHandlerNames:[Ljava/lang/String;
      21: aload_0
      22: invokespecial #5                  // Method java/lang/Object."<init>":()V
      25: return

  public java.lang.Void validate() throws java.lang.IllegalArgumentException;
    Code:
       0: aload_0
       1: getfield      #2                  // Field val$stringsArray:[Ljava/lang/String;
       4: astore_1
       5: aload_1
       6: arraylength
       7: istore_2
       8: iconst_0
       9: istore_3
      10: iload_3
      11: iload_2
      12: if_icmpge     60
      15: aload_1
      16: iload_3
      17: aaload
      18: astore        4
      20: aload_0
      21: getfield      #3                  // Field val$configuration:Lorg/jboss/logmanager/config/LogContextConfigurationImpl;
      24: aload         4
      26: invokevirtual #6                  // Method org/jboss/logmanager/config/LogContextConfigurationImpl.getHandlerConfiguration:(Ljava/lang/String;)Lorg/jboss/logmanager/config/HandlerConfiguration;
      29: ifnonnull     54
      32: new           #7                  // class java/lang/IllegalArgumentException
      35: dup
      36: ldc           #8                  // String Handler \"%s\" is not found
      38: iconst_1
      39: anewarray     #9                  // class java/lang/Object
      42: dup
      43: iconst_0
      44: aload         4
      46: aastore
      47: invokestatic  #10                 // Method java/lang/String.format:(Ljava/lang/String;[Ljava/lang/Object;)Ljava/lang/String;
      50: invokespecial #11                 // Method java/lang/IllegalArgumentException."<init>":(Ljava/lang/String;)V
      53: athrow
      54: iinc          3, 1
      57: goto          10
      60: aconst_null
      61: areturn

  public void applyPreCreate(java.lang.Void);
    Code:
       0: aload_0
       1: getfield      #1                  // Field this$0:Lorg/jboss/logmanager/config/HandlerConfigurationImpl;
       4: invokevirtual #12                 // Method org/jboss/logmanager/config/HandlerConfigurationImpl.addPostConfigurationActions:()V
       7: return

  public void applyPostCreate(java.lang.Void);
    Code:
       0: aload_0
       1: getfield      #3                  // Field val$configuration:Lorg/jboss/logmanager/config/LogContextConfigurationImpl;
       4: invokevirtual #13                 // Method org/jboss/logmanager/config/LogContextConfigurationImpl.getHandlerRefs:()Ljava/util/Map;
       7: astore_2
       8: aload_2
       9: aload_0
      10: getfield      #1                  // Field this$0:Lorg/jboss/logmanager/config/HandlerConfigurationImpl;
      13: invokevirtual #14                 // Method org/jboss/logmanager/config/HandlerConfigurationImpl.getName:()Ljava/lang/String;
      16: invokeinterface #15,  2           // InterfaceMethod java/util/Map.get:(Ljava/lang/Object;)Ljava/lang/Object;
      21: checkcast     #16                 // class org/jboss/logmanager/ExtHandler
      24: astore_3
      25: aload_0
      26: getfield      #2                  // Field val$stringsArray:[Ljava/lang/String;
      29: arraylength
      30: istore        4
      32: iload         4
      34: anewarray     #17                 // class java/util/logging/Handler
      37: astore        5
      39: iconst_0
      40: istore        6
      42: iload         6
      44: iload         4
      46: if_icmpge     76
      49: aload         5
      51: iload         6
      53: aload_2
      54: aload_0
      55: getfield      #2                  // Field val$stringsArray:[Ljava/lang/String;
      58: iload         6
      60: aaload
      61: invokeinterface #15,  2           // InterfaceMethod java/util/Map.get:(Ljava/lang/Object;)Ljava/lang/Object;
      66: checkcast     #17                 // class java/util/logging/Handler
      69: aastore
      70: iinc          6, 1
      73: goto          42
      76: aload_3
      77: aload         5
      79: invokevirtual #18                 // Method org/jboss/logmanager/ExtHandler.setHandlers:([Ljava/util/logging/Handler;)[Ljava/util/logging/Handler;
      82: pop
      83: return

  public void rollback();
    Code:
       0: aload_0
       1: getfield      #1                  // Field this$0:Lorg/jboss/logmanager/config/HandlerConfigurationImpl;
       4: invokestatic  #19                 // Method org/jboss/logmanager/config/HandlerConfigurationImpl.access$500:(Lorg/jboss/logmanager/config/HandlerConfigurationImpl;)Ljava/util/List;
       7: invokeinterface #20,  1           // InterfaceMethod java/util/List.clear:()V
      12: aload_0
      13: getfield      #1                  // Field this$0:Lorg/jboss/logmanager/config/HandlerConfigurationImpl;
      16: invokestatic  #19                 // Method org/jboss/logmanager/config/HandlerConfigurationImpl.access$500:(Lorg/jboss/logmanager/config/HandlerConfigurationImpl;)Ljava/util/List;
      19: aload_0
      20: getfield      #4                  // Field val$oldHandlerNames:[Ljava/lang/String;
      23: invokestatic  #21                 // Method java/util/Arrays.asList:([Ljava/lang/Object;)Ljava/util/List;
      26: invokeinterface #22,  2           // InterfaceMethod java/util/List.addAll:(Ljava/util/Collection;)Z
      31: pop
      32: return

  public void applyPostCreate(java.lang.Object);
    Code:
       0: aload_0
       1: aload_1
       2: checkcast     #23                 // class java/lang/Void
       5: invokevirtual #24                 // Method applyPostCreate:(Ljava/lang/Void;)V
       8: return

  public void applyPreCreate(java.lang.Object);
    Code:
       0: aload_0
       1: aload_1
       2: checkcast     #23                 // class java/lang/Void
       5: invokevirtual #25                 // Method applyPreCreate:(Ljava/lang/Void;)V
       8: return

  public java.lang.Object validate() throws java.lang.IllegalArgumentException;
    Code:
       0: aload_0
       1: invokevirtual #26                 // Method validate:()Ljava/lang/Void;
       4: areturn
}
