Compiled from "ValueExpressionImpl.java"
class org.jboss.logmanager.config.ValueExpressionImpl<T> implements org.jboss.logmanager.config.ValueExpression<T> {
  private final java.lang.String expression;

  private final T resolvedValue;

  org.jboss.logmanager.config.ValueExpressionImpl(java.lang.String, T);
    Code:
       0: aload_0
       1: invokespecial #1                  // Method java/lang/Object."<init>":()V
       4: aload_0
       5: aload_1
       6: putfield      #2                  // Field expression:Ljava/lang/String;
       9: aload_0
      10: aload_2
      11: putfield      #3                  // Field resolvedValue:Ljava/lang/Object;
      14: return

  public T getResolvedValue();
    Code:
       0: aload_0
       1: getfield      #3                  // Field resolvedValue:Ljava/lang/Object;
       4: areturn

  public boolean isExpression();
    Code:
       0: aload_0
       1: getfield      #2                  // Field expression:Ljava/lang/String;
       4: ifnull        11
       7: iconst_1
       8: goto          12
      11: iconst_0
      12: ireturn

  public java.lang.String getValue();
    Code:
       0: aload_0
       1: getfield      #2                  // Field expression:Ljava/lang/String;
       4: ifnonnull     28
       7: aload_0
       8: getfield      #3                  // Field resolvedValue:Ljava/lang/Object;
      11: ifnonnull     18
      14: aconst_null
      15: goto          32
      18: aload_0
      19: getfield      #3                  // Field resolvedValue:Ljava/lang/Object;
      22: invokestatic  #4                  // Method java/lang/String.valueOf:(Ljava/lang/Object;)Ljava/lang/String;
      25: goto          32
      28: aload_0
      29: getfield      #2                  // Field expression:Ljava/lang/String;
      32: areturn

  public java.lang.String toString();
    Code:
       0: aload_0
       1: invokevirtual #5                  // Method getValue:()Ljava/lang/String;
       4: areturn
}
