Compiled from "PactBrokerClient.kt"
public final class au.com.dius.pact.core.pactbroker.Latest$UseLatestTag extends au.com.dius.pact.core.pactbroker.Latest {
  private final java.lang.String latestTag;

  public final java.lang.String getLatestTag();
    Code:
       0: aload_0
       1: getfield      #11                 // Field latestTag:Ljava/lang/String;
       4: areturn

  public au.com.dius.pact.core.pactbroker.Latest$UseLatestTag(java.lang.String);
    Code:
       0: aload_1
       1: ldc           #16                 // String latestTag
       3: invokestatic  #22                 // Method kotlin/jvm/internal/Intrinsics.checkNotNullParameter:(Ljava/lang/Object;Ljava/lang/String;)V
       6: aload_0
       7: aconst_null
       8: invokespecial #25                 // Method au/com/dius/pact/core/pactbroker/Latest."<init>":(Lkotlin/jvm/internal/DefaultConstructorMarker;)V
      11: aload_0
      12: aload_1
      13: putfield      #11                 // Field latestTag:Ljava/lang/String;
      16: return

  public final java.lang.String component1();
    Code:
       0: aload_0
       1: getfield      #11                 // Field latestTag:Ljava/lang/String;
       4: areturn

  public final au.com.dius.pact.core.pactbroker.Latest$UseLatestTag copy(java.lang.String);
    Code:
       0: aload_1
       1: ldc           #16                 // String latestTag
       3: invokestatic  #22                 // Method kotlin/jvm/internal/Intrinsics.checkNotNullParameter:(Ljava/lang/Object;Ljava/lang/String;)V
       6: new           #2                  // class au/com/dius/pact/core/pactbroker/Latest$UseLatestTag
       9: dup
      10: aload_1
      11: invokespecial #30                 // Method "<init>":(Ljava/lang/String;)V
      14: areturn

  public static au.com.dius.pact.core.pactbroker.Latest$UseLatestTag copy$default(au.com.dius.pact.core.pactbroker.Latest$UseLatestTag, java.lang.String, int, java.lang.Object);
    Code:
       0: iload_2
       1: iconst_1
       2: iand
       3: ifeq          11
       6: aload_0
       7: getfield      #11                 // Field latestTag:Ljava/lang/String;
      10: astore_1
      11: aload_0
      12: aload_1
      13: invokevirtual #34                 // Method copy:(Ljava/lang/String;)Lau/com/dius/pact/core/pactbroker/Latest$UseLatestTag;
      16: areturn

  public java.lang.String toString();
    Code:
       0: new           #37                 // class java/lang/StringBuilder
       3: dup
       4: invokespecial #40                 // Method java/lang/StringBuilder."<init>":()V
       7: ldc           #42                 // String UseLatestTag(latestTag=
       9: invokevirtual #46                 // Method java/lang/StringBuilder.append:(Ljava/lang/String;)Ljava/lang/StringBuilder;
      12: aload_0
      13: getfield      #11                 // Field latestTag:Ljava/lang/String;
      16: invokevirtual #46                 // Method java/lang/StringBuilder.append:(Ljava/lang/String;)Ljava/lang/StringBuilder;
      19: ldc           #48                 // String )
      21: invokevirtual #46                 // Method java/lang/StringBuilder.append:(Ljava/lang/String;)Ljava/lang/StringBuilder;
      24: invokevirtual #50                 // Method java/lang/StringBuilder.toString:()Ljava/lang/String;
      27: areturn

  public int hashCode();
    Code:
       0: aload_0
       1: getfield      #11                 // Field latestTag:Ljava/lang/String;
       4: dup
       5: ifnull        14
       8: invokevirtual #56                 // Method java/lang/Object.hashCode:()I
      11: goto          16
      14: pop
      15: iconst_0
      16: ireturn

  public boolean equals(java.lang.Object);
    Code:
       0: aload_0
       1: aload_1
       2: if_acmpeq     31
       5: aload_1
       6: instanceof    #2                  // class au/com/dius/pact/core/pactbroker/Latest$UseLatestTag
       9: ifeq          33
      12: aload_1
      13: checkcast     #2                  // class au/com/dius/pact/core/pactbroker/Latest$UseLatestTag
      16: astore_2
      17: aload_0
      18: getfield      #11                 // Field latestTag:Ljava/lang/String;
      21: aload_2
      22: getfield      #11                 // Field latestTag:Ljava/lang/String;
      25: invokestatic  #65                 // Method kotlin/jvm/internal/Intrinsics.areEqual:(Ljava/lang/Object;Ljava/lang/Object;)Z
      28: ifeq          33
      31: iconst_1
      32: ireturn
      33: iconst_0
      34: ireturn
}
