Compiled from "PactBrokerClient.kt"
final class au.com.dius.pact.core.pactbroker.PactBrokerClient$fetchConsumersWithSelectors$1 extends kotlin.jvm.internal.Lambda implements kotlin.jvm.functions.Function0<java.lang.Object> {
  final au.com.dius.pact.core.pactbroker.PactBrokerClient this$0;

  final java.util.List $selectors;

  final java.lang.String $providerName;

  public final java.lang.Object invoke();
    Code:
       0: aload_0
       1: getfield      #14                 // Field $selectors:Ljava/util/List;
       4: checkcast     #16                 // class java/lang/Iterable
       7: astore_2
       8: iconst_0
       9: istore_3
      10: aload_2
      11: astore        4
      13: new           #18                 // class java/util/ArrayList
      16: dup
      17: invokespecial #22                 // Method java/util/ArrayList."<init>":()V
      20: checkcast     #24                 // class java/util/Collection
      23: astore        5
      25: iconst_0
      26: istore        6
      28: aload         4
      30: invokeinterface #28,  1           // InterfaceMethod java/lang/Iterable.iterator:()Ljava/util/Iterator;
      35: astore        7
      37: aload         7
      39: invokeinterface #34,  1           // InterfaceMethod java/util/Iterator.hasNext:()Z
      44: ifeq          90
      47: aload         7
      49: invokeinterface #37,  1           // InterfaceMethod java/util/Iterator.next:()Ljava/lang/Object;
      54: astore        8
      56: aload         8
      58: checkcast     #39                 // class au/com/dius/pact/core/pactbroker/ConsumerVersionSelector
      61: astore        9
      63: iconst_0
      64: istore        10
      66: aload         9
      68: invokevirtual #43                 // Method au/com/dius/pact/core/pactbroker/ConsumerVersionSelector.getTag:()Ljava/lang/String;
      71: invokestatic  #49                 // Method au/com/dius/pact/core/support/KotlinLanguageSupportKt.isNotEmpty:(Ljava/lang/String;)Z
      74: ifeq          37
      77: aload         5
      79: aload         8
      81: invokeinterface #53,  2           // InterfaceMethod java/util/Collection.add:(Ljava/lang/Object;)Z
      86: pop
      87: goto          37
      90: aload         5
      92: checkcast     #55                 // class java/util/List
      95: nop
      96: checkcast     #16                 // class java/lang/Iterable
      99: astore_2
     100: nop
     101: iconst_0
     102: istore_3
     103: aload_2
     104: astore        4
     106: new           #18                 // class java/util/ArrayList
     109: dup
     110: aload_2
     111: bipush        10
     113: invokestatic  #61                 // Method kotlin/collections/CollectionsKt.collectionSizeOrDefault:(Ljava/lang/Iterable;I)I
     116: invokespecial #64                 // Method java/util/ArrayList."<init>":(I)V
     119: checkcast     #24                 // class java/util/Collection
     122: astore        5
     124: iconst_0
     125: istore        6
     127: aload         4
     129: invokeinterface #28,  1           // InterfaceMethod java/lang/Iterable.iterator:()Ljava/util/Iterator;
     134: astore        7
     136: aload         7
     138: invokeinterface #34,  1           // InterfaceMethod java/util/Iterator.hasNext:()Z
     143: ifeq          197
     146: aload         7
     148: invokeinterface #37,  1           // InterfaceMethod java/util/Iterator.next:()Ljava/lang/Object;
     153: astore        8
     155: aload         5
     157: aload         8
     159: checkcast     #39                 // class au/com/dius/pact/core/pactbroker/ConsumerVersionSelector
     162: astore        9
     164: astore        14
     166: iconst_0
     167: istore        10
     169: aload         9
     171: invokevirtual #43                 // Method au/com/dius/pact/core/pactbroker/ConsumerVersionSelector.getTag:()Ljava/lang/String;
     174: aload         9
     176: invokevirtual #67                 // Method au/com/dius/pact/core/pactbroker/ConsumerVersionSelector.getFallbackTag:()Ljava/lang/String;
     179: invokestatic  #73                 // Method kotlin/TuplesKt.to:(Ljava/lang/Object;Ljava/lang/Object;)Lkotlin/Pair;
     182: astore        15
     184: aload         14
     186: aload         15
     188: invokeinterface #53,  2           // InterfaceMethod java/util/Collection.add:(Ljava/lang/Object;)Z
     193: pop
     194: goto          136
     197: aload         5
     199: checkcast     #55                 // class java/util/List
     202: nop
     203: astore_1
     204: aload_1
     205: invokeinterface #76,  1           // InterfaceMethod java/util/List.isEmpty:()Z
     210: ifeq          227
     213: aload_0
     214: getfield      #80                 // Field this$0:Lau/com/dius/pact/core/pactbroker/PactBrokerClient;
     217: aload_0
     218: getfield      #84                 // Field $providerName:Ljava/lang/String;
     221: invokevirtual #90                 // Method au/com/dius/pact/core/pactbroker/PactBrokerClient.fetchConsumers:(Ljava/lang/String;)Ljava/util/List;
     224: goto          384
     227: aload_1
     228: checkcast     #16                 // class java/lang/Iterable
     231: astore_2
     232: iconst_0
     233: istore_3
     234: aload_2
     235: astore        4
     237: new           #18                 // class java/util/ArrayList
     240: dup
     241: invokespecial #22                 // Method java/util/ArrayList."<init>":()V
     244: checkcast     #24                 // class java/util/Collection
     247: astore        5
     249: iconst_0
     250: istore        6
     252: aload         4
     254: invokeinterface #28,  1           // InterfaceMethod java/lang/Iterable.iterator:()Ljava/util/Iterator;
     259: astore        7
     261: aload         7
     263: invokeinterface #34,  1           // InterfaceMethod java/util/Iterator.hasNext:()Z
     268: ifeq          378
     271: aload         7
     273: invokeinterface #37,  1           // InterfaceMethod java/util/Iterator.next:()Ljava/lang/Object;
     278: astore        8
     280: aload         8
     282: checkcast     #92                 // class kotlin/Pair
     285: astore        9
     287: iconst_0
     288: istore        10
     290: aload         9
     292: invokevirtual #95                 // Method kotlin/Pair.component1:()Ljava/lang/Object;
     295: checkcast     #97                 // class java/lang/String
     298: astore        11
     300: aload         9
     302: invokevirtual #100                // Method kotlin/Pair.component2:()Ljava/lang/Object;
     305: checkcast     #97                 // class java/lang/String
     308: astore        12
     310: aload_0
     311: getfield      #80                 // Field this$0:Lau/com/dius/pact/core/pactbroker/PactBrokerClient;
     314: aload_0
     315: getfield      #84                 // Field $providerName:Ljava/lang/String;
     318: aload         11
     320: dup
     321: invokestatic  #106                // Method kotlin/jvm/internal/Intrinsics.checkNotNull:(Ljava/lang/Object;)V
     324: invokevirtual #110                // Method au/com/dius/pact/core/pactbroker/PactBrokerClient.fetchConsumersWithTag:(Ljava/lang/String;Ljava/lang/String;)Ljava/util/List;
     327: astore        13
     329: aload         13
     331: invokeinterface #76,  1           // InterfaceMethod java/util/List.isEmpty:()Z
     336: ifeq          360
     339: aload         12
     341: ifnull        360
     344: aload_0
     345: getfield      #80                 // Field this$0:Lau/com/dius/pact/core/pactbroker/PactBrokerClient;
     348: aload_0
     349: getfield      #84                 // Field $providerName:Ljava/lang/String;
     352: aload         12
     354: invokevirtual #110                // Method au/com/dius/pact/core/pactbroker/PactBrokerClient.fetchConsumersWithTag:(Ljava/lang/String;Ljava/lang/String;)Ljava/util/List;
     357: goto          362
     360: aload         13
     362: checkcast     #16                 // class java/lang/Iterable
     365: astore        9
     367: aload         5
     369: aload         9
     371: invokestatic  #114                // Method kotlin/collections/CollectionsKt.addAll:(Ljava/util/Collection;Ljava/lang/Iterable;)Z
     374: pop
     375: goto          261
     378: aload         5
     380: checkcast     #55                 // class java/util/List
     383: nop
     384: areturn

  au.com.dius.pact.core.pactbroker.PactBrokerClient$fetchConsumersWithSelectors$1(au.com.dius.pact.core.pactbroker.PactBrokerClient, java.util.List, java.lang.String);
    Code:
       0: aload_0
       1: aload_1
       2: putfield      #80                 // Field this$0:Lau/com/dius/pact/core/pactbroker/PactBrokerClient;
       5: aload_0
       6: aload_2
       7: putfield      #14                 // Field $selectors:Ljava/util/List;
      10: aload_0
      11: aload_3
      12: putfield      #84                 // Field $providerName:Ljava/lang/String;
      15: aload_0
      16: iconst_0
      17: invokespecial #151                // Method kotlin/jvm/internal/Lambda."<init>":(I)V
      20: return
}
