Compiled from "TestLambdaFunctionClient.java"
class com.amazonaws.services.simpleworkflow.flow.test.TestLambdaFunctionClient$1 extends com.amazonaws.services.simpleworkflow.flow.core.Task {
  final com.amazonaws.services.simpleworkflow.flow.test.TestLambdaFunctionClient this$0;

  private final com.amazonaws.services.simpleworkflow.flow.core.Settable val$result;

  private final java.lang.String val$name;

  private final com.amazonaws.services.simpleworkflow.flow.core.Promise val$input;

  private final long val$timeoutSeconds;

  com.amazonaws.services.simpleworkflow.flow.test.TestLambdaFunctionClient$1(com.amazonaws.services.simpleworkflow.flow.test.TestLambdaFunctionClient, com.amazonaws.services.simpleworkflow.flow.core.Promise..., com.amazonaws.services.simpleworkflow.flow.core.Settable, java.lang.String, com.amazonaws.services.simpleworkflow.flow.core.Promise, long);
    Code:
       0: aload_0
       1: aload_1
       2: putfield      #18                 // Field this$0:Lcom/amazonaws/services/simpleworkflow/flow/test/TestLambdaFunctionClient;
       5: aload_0
       6: aload_3
       7: putfield      #20                 // Field val$result:Lcom/amazonaws/services/simpleworkflow/flow/core/Settable;
      10: aload_0
      11: aload         4
      13: putfield      #22                 // Field val$name:Ljava/lang/String;
      16: aload_0
      17: aload         5
      19: putfield      #24                 // Field val$input:Lcom/amazonaws/services/simpleworkflow/flow/core/Promise;
      22: aload_0
      23: lload         6
      25: putfield      #26                 // Field val$timeoutSeconds:J
      28: aload_0
      29: aload_2
      30: invokespecial #28                 // Method com/amazonaws/services/simpleworkflow/flow/core/Task."<init>":([Lcom/amazonaws/services/simpleworkflow/flow/core/Promise;)V
      33: return

  protected void doExecute() throws java.lang.Throwable;
    Code:
       0: aload_0
       1: getfield      #20                 // Field val$result:Lcom/amazonaws/services/simpleworkflow/flow/core/Settable;
       4: aload_0
       5: getfield      #18                 // Field this$0:Lcom/amazonaws/services/simpleworkflow/flow/test/TestLambdaFunctionClient;
       8: aload_0
       9: getfield      #22                 // Field val$name:Ljava/lang/String;
      12: aload_0
      13: getfield      #24                 // Field val$input:Lcom/amazonaws/services/simpleworkflow/flow/core/Promise;
      16: invokevirtual #43                 // Method com/amazonaws/services/simpleworkflow/flow/core/Promise.get:()Ljava/lang/Object;
      19: checkcast     #49                 // class java/lang/String
      22: aload_0
      23: getfield      #26                 // Field val$timeoutSeconds:J
      26: invokevirtual #51                 // Method com/amazonaws/services/simpleworkflow/flow/test/TestLambdaFunctionClient.scheduleLambdaFunction:(Ljava/lang/String;Ljava/lang/String;J)Lcom/amazonaws/services/simpleworkflow/flow/core/Promise;
      29: invokevirtual #57                 // Method com/amazonaws/services/simpleworkflow/flow/core/Settable.chain:(Lcom/amazonaws/services/simpleworkflow/flow/core/Promise;)V
      32: return
}
