Compiled from "Roller.java"
public class org.apache.log4j.varia.Roller {
  static org.apache.log4j.Logger cat;

  static java.lang.String host;

  static int port;

  static java.lang.Class class$org$apache$log4j$varia$Roller;

  org.apache.log4j.varia.Roller();
    Code:
       0: aload_0
       1: invokespecial #6                  // Method java/lang/Object."<init>":()V
       4: return

  public static void main(java.lang.String[]);
    Code:
       0: invokestatic  #7                  // Method org/apache/log4j/BasicConfigurator.configure:()V
       3: aload_0
       4: arraylength
       5: iconst_2
       6: if_icmpne     21
       9: aload_0
      10: iconst_0
      11: aaload
      12: aload_0
      13: iconst_1
      14: aaload
      15: invokestatic  #8                  // Method init:(Ljava/lang/String;Ljava/lang/String;)V
      18: goto          26
      21: ldc           #9                  // String Wrong number of arguments.
      23: invokestatic  #10                 // Method usage:(Ljava/lang/String;)V
      26: invokestatic  #11                 // Method roll:()V
      29: return

  static void usage(java.lang.String);
    Code:
       0: getstatic     #12                 // Field java/lang/System.err:Ljava/io/PrintStream;
       3: aload_0
       4: invokevirtual #13                 // Method java/io/PrintStream.println:(Ljava/lang/String;)V
       7: getstatic     #12                 // Field java/lang/System.err:Ljava/io/PrintStream;
      10: new           #14                 // class java/lang/StringBuffer
      13: dup
      14: invokespecial #15                 // Method java/lang/StringBuffer."<init>":()V
      17: ldc           #16                 // String Usage: java
      19: invokevirtual #17                 // Method java/lang/StringBuffer.append:(Ljava/lang/String;)Ljava/lang/StringBuffer;
      22: getstatic     #18                 // Field class$org$apache$log4j$varia$Roller:Ljava/lang/Class;
      25: ifnonnull     40
      28: ldc           #19                 // String org.apache.log4j.varia.Roller
      30: invokestatic  #20                 // Method class$:(Ljava/lang/String;)Ljava/lang/Class;
      33: dup
      34: putstatic     #18                 // Field class$org$apache$log4j$varia$Roller:Ljava/lang/Class;
      37: goto          43
      40: getstatic     #18                 // Field class$org$apache$log4j$varia$Roller:Ljava/lang/Class;
      43: invokevirtual #21                 // Method java/lang/Class.getName:()Ljava/lang/String;
      46: invokevirtual #17                 // Method java/lang/StringBuffer.append:(Ljava/lang/String;)Ljava/lang/StringBuffer;
      49: ldc           #22                 // String host_name port_number
      51: invokevirtual #17                 // Method java/lang/StringBuffer.append:(Ljava/lang/String;)Ljava/lang/StringBuffer;
      54: invokevirtual #23                 // Method java/lang/StringBuffer.toString:()Ljava/lang/String;
      57: invokevirtual #13                 // Method java/io/PrintStream.println:(Ljava/lang/String;)V
      60: iconst_1
      61: invokestatic  #24                 // Method java/lang/System.exit:(I)V
      64: return

  static void init(java.lang.String, java.lang.String);
    Code:
       0: aload_0
       1: putstatic     #25                 // Field host:Ljava/lang/String;
       4: aload_1
       5: invokestatic  #26                 // Method java/lang/Integer.parseInt:(Ljava/lang/String;)I
       8: putstatic     #27                 // Field port:I
      11: goto          42
      14: astore_2
      15: new           #14                 // class java/lang/StringBuffer
      18: dup
      19: invokespecial #15                 // Method java/lang/StringBuffer."<init>":()V
      22: ldc           #29                 // String Second argument
      24: invokevirtual #17                 // Method java/lang/StringBuffer.append:(Ljava/lang/String;)Ljava/lang/StringBuffer;
      27: aload_1
      28: invokevirtual #17                 // Method java/lang/StringBuffer.append:(Ljava/lang/String;)Ljava/lang/StringBuffer;
      31: ldc           #30                 // String  is not a valid integer.
      33: invokevirtual #17                 // Method java/lang/StringBuffer.append:(Ljava/lang/String;)Ljava/lang/StringBuffer;
      36: invokevirtual #23                 // Method java/lang/StringBuffer.toString:()Ljava/lang/String;
      39: invokestatic  #10                 // Method usage:(Ljava/lang/String;)V
      42: return
    Exception table:
       from    to  target type
           4    11    14   Class java/lang/NumberFormatException

  static void roll();
    Code:
       0: new           #31                 // class java/net/Socket
       3: dup
       4: getstatic     #25                 // Field host:Ljava/lang/String;
       7: getstatic     #27                 // Field port:I
      10: invokespecial #32                 // Method java/net/Socket."<init>":(Ljava/lang/String;I)V
      13: astore_0
      14: new           #33                 // class java/io/DataOutputStream
      17: dup
      18: aload_0
      19: invokevirtual #34                 // Method java/net/Socket.getOutputStream:()Ljava/io/OutputStream;
      22: invokespecial #35                 // Method java/io/DataOutputStream."<init>":(Ljava/io/OutputStream;)V
      25: astore_1
      26: new           #36                 // class java/io/DataInputStream
      29: dup
      30: aload_0
      31: invokevirtual #37                 // Method java/net/Socket.getInputStream:()Ljava/io/InputStream;
      34: invokespecial #38                 // Method java/io/DataInputStream."<init>":(Ljava/io/InputStream;)V
      37: astore_2
      38: aload_1
      39: ldc           #39                 // String RollOver
      41: invokevirtual #40                 // Method java/io/DataOutputStream.writeUTF:(Ljava/lang/String;)V
      44: aload_2
      45: invokevirtual #41                 // Method java/io/DataInputStream.readUTF:()Ljava/lang/String;
      48: astore_3
      49: ldc           #42                 // String OK
      51: aload_3
      52: invokevirtual #43                 // Method java/lang/String.equals:(Ljava/lang/Object;)Z
      55: ifeq          69
      58: getstatic     #44                 // Field cat:Lorg/apache/log4j/Logger;
      61: ldc           #45                 // String Roll over signal acknowledged by remote appender.
      63: invokevirtual #46                 // Method org/apache/log4j/Logger.info:(Ljava/lang/Object;)V
      66: goto          103
      69: getstatic     #44                 // Field cat:Lorg/apache/log4j/Logger;
      72: new           #14                 // class java/lang/StringBuffer
      75: dup
      76: invokespecial #15                 // Method java/lang/StringBuffer."<init>":()V
      79: ldc           #47                 // String Unexpected return code
      81: invokevirtual #17                 // Method java/lang/StringBuffer.append:(Ljava/lang/String;)Ljava/lang/StringBuffer;
      84: aload_3
      85: invokevirtual #17                 // Method java/lang/StringBuffer.append:(Ljava/lang/String;)Ljava/lang/StringBuffer;
      88: ldc           #48                 // String  from remote entity.
      90: invokevirtual #17                 // Method java/lang/StringBuffer.append:(Ljava/lang/String;)Ljava/lang/StringBuffer;
      93: invokevirtual #23                 // Method java/lang/StringBuffer.toString:()Ljava/lang/String;
      96: invokevirtual #49                 // Method org/apache/log4j/Logger.warn:(Ljava/lang/Object;)V
      99: iconst_2
     100: invokestatic  #24                 // Method java/lang/System.exit:(I)V
     103: goto          155
     106: astore_0
     107: getstatic     #44                 // Field cat:Lorg/apache/log4j/Logger;
     110: new           #14                 // class java/lang/StringBuffer
     113: dup
     114: invokespecial #15                 // Method java/lang/StringBuffer."<init>":()V
     117: ldc           #51                 // String Could not send roll signal on host
     119: invokevirtual #17                 // Method java/lang/StringBuffer.append:(Ljava/lang/String;)Ljava/lang/StringBuffer;
     122: getstatic     #25                 // Field host:Ljava/lang/String;
     125: invokevirtual #17                 // Method java/lang/StringBuffer.append:(Ljava/lang/String;)Ljava/lang/StringBuffer;
     128: ldc           #52                 // String  port
     130: invokevirtual #17                 // Method java/lang/StringBuffer.append:(Ljava/lang/String;)Ljava/lang/StringBuffer;
     133: getstatic     #27                 // Field port:I
     136: invokevirtual #53                 // Method java/lang/StringBuffer.append:(I)Ljava/lang/StringBuffer;
     139: ldc           #54                 // String  .
     141: invokevirtual #17                 // Method java/lang/StringBuffer.append:(Ljava/lang/String;)Ljava/lang/StringBuffer;
     144: invokevirtual #23                 // Method java/lang/StringBuffer.toString:()Ljava/lang/String;
     147: aload_0
     148: invokevirtual #55                 // Method org/apache/log4j/Logger.error:(Ljava/lang/Object;Ljava/lang/Throwable;)V
     151: iconst_2
     152: invokestatic  #24                 // Method java/lang/System.exit:(I)V
     155: iconst_0
     156: invokestatic  #24                 // Method java/lang/System.exit:(I)V
     159: return
    Exception table:
       from    to  target type
           0   103   106   Class java/io/IOException

  static java.lang.Class class$(java.lang.String);
    Code:
       0: aload_0
       1: invokestatic  #1                  // Method java/lang/Class.forName:(Ljava/lang/String;)Ljava/lang/Class;
       4: areturn
       5: astore_1
       6: new           #3                  // class java/lang/NoClassDefFoundError
       9: dup
      10: invokespecial #4                  // Method java/lang/NoClassDefFoundError."<init>":()V
      13: aload_1
      14: invokevirtual #5                  // Method java/lang/NoClassDefFoundError.initCause:(Ljava/lang/Throwable;)Ljava/lang/Throwable;
      17: athrow
    Exception table:
       from    to  target type
           0     4     5   Class java/lang/ClassNotFoundException

  static {};
    Code:
       0: getstatic     #18                 // Field class$org$apache$log4j$varia$Roller:Ljava/lang/Class;
       3: ifnonnull     18
       6: ldc           #19                 // String org.apache.log4j.varia.Roller
       8: invokestatic  #20                 // Method class$:(Ljava/lang/String;)Ljava/lang/Class;
      11: dup
      12: putstatic     #18                 // Field class$org$apache$log4j$varia$Roller:Ljava/lang/Class;
      15: goto          21
      18: getstatic     #18                 // Field class$org$apache$log4j$varia$Roller:Ljava/lang/Class;
      21: invokestatic  #56                 // Method org/apache/log4j/Logger.getLogger:(Ljava/lang/Class;)Lorg/apache/log4j/Logger;
      24: putstatic     #44                 // Field cat:Lorg/apache/log4j/Logger;
      27: return
}
