Compiled from "AdvancedLdapLoginModule.java"
public class org.jboss.security.negotiation.spnego.AdvancedLdapLoginModule extends org.jboss.security.negotiation.AdvancedLdapLoginModule {
  private static boolean warned;

  public org.jboss.security.negotiation.spnego.AdvancedLdapLoginModule();
    Code:
       0: aload_0
       1: invokespecial #1                  // Method org/jboss/security/negotiation/AdvancedLdapLoginModule."<init>":()V
       4: return

  public void initialize(javax.security.auth.Subject, javax.security.auth.callback.CallbackHandler, java.util.Map, java.util.Map);
    Code:
       0: aload_0
       1: aload_1
       2: aload_2
       3: aload_3
       4: aload         4
       6: invokespecial #2                  // Method org/jboss/security/negotiation/AdvancedLdapLoginModule.initialize:(Ljavax/security/auth/Subject;Ljavax/security/auth/callback/CallbackHandler;Ljava/util/Map;Ljava/util/Map;)V
       9: getstatic     #3                  // Field warned:Z
      12: ifne          77
      15: iconst_1
      16: putstatic     #3                  // Field warned:Z
      19: aload_0
      20: invokevirtual #4                  // Method java/lang/Object.getClass:()Ljava/lang/Class;
      23: invokevirtual #5                  // Method java/lang/Class.getName:()Ljava/lang/String;
      26: astore        5
      28: ldc           #6                  // class org/jboss/security/negotiation/AdvancedLdapLoginModule
      30: invokevirtual #5                  // Method java/lang/Class.getName:()Ljava/lang/String;
      33: astore        6
      35: aload_0
      36: getfield      #7                  // Field log:Lorg/jboss/logging/Logger;
      39: new           #8                  // class java/lang/StringBuilder
      42: dup
      43: invokespecial #9                  // Method java/lang/StringBuilder."<init>":()V
      46: ldc           #10                 // String \'
      48: invokevirtual #11                 // Method java/lang/StringBuilder.append:(Ljava/lang/String;)Ljava/lang/StringBuilder;
      51: aload         5
      53: invokevirtual #11                 // Method java/lang/StringBuilder.append:(Ljava/lang/String;)Ljava/lang/StringBuilder;
      56: ldc           #12                 // String \' is deprecated, use \'
      58: invokevirtual #11                 // Method java/lang/StringBuilder.append:(Ljava/lang/String;)Ljava/lang/StringBuilder;
      61: aload         6
      63: invokevirtual #11                 // Method java/lang/StringBuilder.append:(Ljava/lang/String;)Ljava/lang/StringBuilder;
      66: ldc           #13                 // String \' instead.
      68: invokevirtual #11                 // Method java/lang/StringBuilder.append:(Ljava/lang/String;)Ljava/lang/StringBuilder;
      71: invokevirtual #14                 // Method java/lang/StringBuilder.toString:()Ljava/lang/String;
      74: invokevirtual #15                 // Method org/jboss/logging/Logger.warn:(Ljava/lang/Object;)V
      77: return

  static {};
    Code:
       0: iconst_0
       1: putstatic     #3                  // Field warned:Z
       4: return
}
