Compiled from "InvalidateApiKeyRequest.java"
public final class org.elasticsearch.client.security.InvalidateApiKeyRequest implements org.elasticsearch.client.Validatable,org.elasticsearch.common.xcontent.ToXContentObject {
  private final java.lang.String realmName;

  private final java.lang.String userName;

  private final java.lang.String id;

  private final java.lang.String name;

  org.elasticsearch.client.security.InvalidateApiKeyRequest(java.lang.String, java.lang.String, java.lang.String, java.lang.String);
    Code:
       0: aload_0
       1: invokespecial #1                  // Method java/lang/Object."<init>":()V
       4: aload_1
       5: invokestatic  #2                  // Method org/elasticsearch/common/Strings.hasText:(Ljava/lang/String;)Z
       8: ifne          39
      11: aload_2
      12: invokestatic  #2                  // Method org/elasticsearch/common/Strings.hasText:(Ljava/lang/String;)Z
      15: ifne          39
      18: aload_3
      19: invokestatic  #2                  // Method org/elasticsearch/common/Strings.hasText:(Ljava/lang/String;)Z
      22: ifne          39
      25: aload         4
      27: invokestatic  #2                  // Method org/elasticsearch/common/Strings.hasText:(Ljava/lang/String;)Z
      30: ifne          39
      33: aload_0
      34: ldc           #3                  // String One of [api key id, api key name, username, realm name] must be specified
      36: invokespecial #4                  // Method throwValidationError:(Ljava/lang/String;)V
      39: aload_3
      40: invokestatic  #2                  // Method org/elasticsearch/common/Strings.hasText:(Ljava/lang/String;)Z
      43: ifne          54
      46: aload         4
      48: invokestatic  #2                  // Method org/elasticsearch/common/Strings.hasText:(Ljava/lang/String;)Z
      51: ifeq          74
      54: aload_1
      55: invokestatic  #2                  // Method org/elasticsearch/common/Strings.hasText:(Ljava/lang/String;)Z
      58: ifne          68
      61: aload_2
      62: invokestatic  #2                  // Method org/elasticsearch/common/Strings.hasText:(Ljava/lang/String;)Z
      65: ifeq          74
      68: aload_0
      69: ldc           #5                  // String username or realm name must not be specified when the api key id or api key name is specified
      71: invokespecial #4                  // Method throwValidationError:(Ljava/lang/String;)V
      74: aload_3
      75: invokestatic  #2                  // Method org/elasticsearch/common/Strings.hasText:(Ljava/lang/String;)Z
      78: ifeq          95
      81: aload         4
      83: invokestatic  #2                  // Method org/elasticsearch/common/Strings.hasText:(Ljava/lang/String;)Z
      86: ifeq          95
      89: aload_0
      90: ldc           #6                  // String only one of [api key id, api key name] can be specified
      92: invokespecial #4                  // Method throwValidationError:(Ljava/lang/String;)V
      95: aload_0
      96: aload_1
      97: putfield      #7                  // Field realmName:Ljava/lang/String;
     100: aload_0
     101: aload_2
     102: putfield      #8                  // Field userName:Ljava/lang/String;
     105: aload_0
     106: aload_3
     107: putfield      #9                  // Field id:Ljava/lang/String;
     110: aload_0
     111: aload         4
     113: putfield      #10                 // Field name:Ljava/lang/String;
     116: return

  private void throwValidationError(java.lang.String);
    Code:
       0: new           #11                 // class java/lang/IllegalArgumentException
       3: dup
       4: aload_1
       5: invokespecial #12                 // Method java/lang/IllegalArgumentException."<init>":(Ljava/lang/String;)V
       8: athrow

  public java.lang.String getRealmName();
    Code:
       0: aload_0
       1: getfield      #7                  // Field realmName:Ljava/lang/String;
       4: areturn

  public java.lang.String getUserName();
    Code:
       0: aload_0
       1: getfield      #8                  // Field userName:Ljava/lang/String;
       4: areturn

  public java.lang.String getId();
    Code:
       0: aload_0
       1: getfield      #9                  // Field id:Ljava/lang/String;
       4: areturn

  public java.lang.String getName();
    Code:
       0: aload_0
       1: getfield      #10                 // Field name:Ljava/lang/String;
       4: areturn

  public static org.elasticsearch.client.security.InvalidateApiKeyRequest usingRealmName(java.lang.String);
    Code:
       0: new           #13                 // class org/elasticsearch/client/security/InvalidateApiKeyRequest
       3: dup
       4: aload_0
       5: aconst_null
       6: aconst_null
       7: aconst_null
       8: invokespecial #14                 // Method "<init>":(Ljava/lang/String;Ljava/lang/String;Ljava/lang/String;Ljava/lang/String;)V
      11: areturn

  public static org.elasticsearch.client.security.InvalidateApiKeyRequest usingUserName(java.lang.String);
    Code:
       0: new           #13                 // class org/elasticsearch/client/security/InvalidateApiKeyRequest
       3: dup
       4: aconst_null
       5: aload_0
       6: aconst_null
       7: aconst_null
       8: invokespecial #14                 // Method "<init>":(Ljava/lang/String;Ljava/lang/String;Ljava/lang/String;Ljava/lang/String;)V
      11: areturn

  public static org.elasticsearch.client.security.InvalidateApiKeyRequest usingRealmAndUserName(java.lang.String, java.lang.String);
    Code:
       0: new           #13                 // class org/elasticsearch/client/security/InvalidateApiKeyRequest
       3: dup
       4: aload_0
       5: aload_1
       6: aconst_null
       7: aconst_null
       8: invokespecial #14                 // Method "<init>":(Ljava/lang/String;Ljava/lang/String;Ljava/lang/String;Ljava/lang/String;)V
      11: areturn

  public static org.elasticsearch.client.security.InvalidateApiKeyRequest usingApiKeyId(java.lang.String);
    Code:
       0: new           #13                 // class org/elasticsearch/client/security/InvalidateApiKeyRequest
       3: dup
       4: aconst_null
       5: aconst_null
       6: aload_0
       7: aconst_null
       8: invokespecial #14                 // Method "<init>":(Ljava/lang/String;Ljava/lang/String;Ljava/lang/String;Ljava/lang/String;)V
      11: areturn

  public static org.elasticsearch.client.security.InvalidateApiKeyRequest usingApiKeyName(java.lang.String);
    Code:
       0: new           #13                 // class org/elasticsearch/client/security/InvalidateApiKeyRequest
       3: dup
       4: aconst_null
       5: aconst_null
       6: aconst_null
       7: aload_0
       8: invokespecial #14                 // Method "<init>":(Ljava/lang/String;Ljava/lang/String;Ljava/lang/String;Ljava/lang/String;)V
      11: areturn

  public org.elasticsearch.common.xcontent.XContentBuilder toXContent(org.elasticsearch.common.xcontent.XContentBuilder, org.elasticsearch.common.xcontent.ToXContent$Params) throws java.io.IOException;
    Code:
       0: aload_1
       1: invokevirtual #15                 // Method org/elasticsearch/common/xcontent/XContentBuilder.startObject:()Lorg/elasticsearch/common/xcontent/XContentBuilder;
       4: pop
       5: aload_0
       6: getfield      #7                  // Field realmName:Ljava/lang/String;
       9: ifnull        23
      12: aload_1
      13: ldc           #16                 // String realm_name
      15: aload_0
      16: getfield      #7                  // Field realmName:Ljava/lang/String;
      19: invokevirtual #17                 // Method org/elasticsearch/common/xcontent/XContentBuilder.field:(Ljava/lang/String;Ljava/lang/String;)Lorg/elasticsearch/common/xcontent/XContentBuilder;
      22: pop
      23: aload_0
      24: getfield      #8                  // Field userName:Ljava/lang/String;
      27: ifnull        41
      30: aload_1
      31: ldc           #18                 // String username
      33: aload_0
      34: getfield      #8                  // Field userName:Ljava/lang/String;
      37: invokevirtual #17                 // Method org/elasticsearch/common/xcontent/XContentBuilder.field:(Ljava/lang/String;Ljava/lang/String;)Lorg/elasticsearch/common/xcontent/XContentBuilder;
      40: pop
      41: aload_0
      42: getfield      #9                  // Field id:Ljava/lang/String;
      45: ifnull        59
      48: aload_1
      49: ldc           #19                 // String id
      51: aload_0
      52: getfield      #9                  // Field id:Ljava/lang/String;
      55: invokevirtual #17                 // Method org/elasticsearch/common/xcontent/XContentBuilder.field:(Ljava/lang/String;Ljava/lang/String;)Lorg/elasticsearch/common/xcontent/XContentBuilder;
      58: pop
      59: aload_0
      60: getfield      #10                 // Field name:Ljava/lang/String;
      63: ifnull        77
      66: aload_1
      67: ldc           #20                 // String name
      69: aload_0
      70: getfield      #10                 // Field name:Ljava/lang/String;
      73: invokevirtual #17                 // Method org/elasticsearch/common/xcontent/XContentBuilder.field:(Ljava/lang/String;Ljava/lang/String;)Lorg/elasticsearch/common/xcontent/XContentBuilder;
      76: pop
      77: aload_1
      78: invokevirtual #21                 // Method org/elasticsearch/common/xcontent/XContentBuilder.endObject:()Lorg/elasticsearch/common/xcontent/XContentBuilder;
      81: areturn
}
