Compiled from "TryFlowContext.java"
public abstract class org.eclipse.jdt.internal.compiler.flow.TryFlowContext extends org.eclipse.jdt.internal.compiler.flow.FlowContext {
  public org.eclipse.jdt.internal.compiler.flow.FlowContext outerTryContext;

  public org.eclipse.jdt.internal.compiler.flow.TryFlowContext(org.eclipse.jdt.internal.compiler.flow.FlowContext, org.eclipse.jdt.internal.compiler.ast.ASTNode);
    Code:
       0: aload_0
       1: aload_1
       2: aload_2
       3: invokespecial #10                 // Method org/eclipse/jdt/internal/compiler/flow/FlowContext."<init>":(Lorg/eclipse/jdt/internal/compiler/flow/FlowContext;Lorg/eclipse/jdt/internal/compiler/ast/ASTNode;)V
       6: return

  public void markFinallyNullStatus(org.eclipse.jdt.internal.compiler.lookup.LocalVariableBinding, int);
    Code:
       0: aload_0
       1: getfield      #21                 // Field outerTryContext:Lorg/eclipse/jdt/internal/compiler/flow/FlowContext;
       4: ifnull        16
       7: aload_0
       8: getfield      #21                 // Field outerTryContext:Lorg/eclipse/jdt/internal/compiler/flow/FlowContext;
      11: aload_1
      12: iload_2
      13: invokevirtual #23                 // Method org/eclipse/jdt/internal/compiler/flow/FlowContext.markFinallyNullStatus:(Lorg/eclipse/jdt/internal/compiler/lookup/LocalVariableBinding;I)V
      16: aload_0
      17: aload_1
      18: iload_2
      19: invokespecial #23                 // Method org/eclipse/jdt/internal/compiler/flow/FlowContext.markFinallyNullStatus:(Lorg/eclipse/jdt/internal/compiler/lookup/LocalVariableBinding;I)V
      22: return

  public void mergeFinallyNullInfo(org.eclipse.jdt.internal.compiler.flow.FlowInfo);
    Code:
       0: aload_0
       1: getfield      #21                 // Field outerTryContext:Lorg/eclipse/jdt/internal/compiler/flow/FlowContext;
       4: ifnull        15
       7: aload_0
       8: getfield      #21                 // Field outerTryContext:Lorg/eclipse/jdt/internal/compiler/flow/FlowContext;
      11: aload_1
      12: invokevirtual #32                 // Method org/eclipse/jdt/internal/compiler/flow/FlowContext.mergeFinallyNullInfo:(Lorg/eclipse/jdt/internal/compiler/flow/FlowInfo;)V
      15: aload_0
      16: aload_1
      17: invokespecial #32                 // Method org/eclipse/jdt/internal/compiler/flow/FlowContext.mergeFinallyNullInfo:(Lorg/eclipse/jdt/internal/compiler/flow/FlowInfo;)V
      20: return
}
