Compiled from "HexDumpBytes.java"
class net.openhft.chronicle.bytes.HexDumpBytes$TextBytesReader extends java.io.Reader {
  private final java.io.Reader reader;

  private final net.openhft.chronicle.bytes.Bytes base;

  public net.openhft.chronicle.bytes.HexDumpBytes$TextBytesReader(java.io.Reader, net.openhft.chronicle.bytes.Bytes);
    Code:
       0: aload_0
       1: invokespecial #1                  // Method java/io/Reader."<init>":()V
       4: aload_0
       5: aload_1
       6: putfield      #2                  // Field reader:Ljava/io/Reader;
       9: aload_0
      10: aload_2
      11: putfield      #3                  // Field base:Lnet/openhft/chronicle/bytes/Bytes;
      14: return

  public int read(char[], int, int) throws java.io.IOException;
    Code:
       0: aload_0
       1: getfield      #2                  // Field reader:Ljava/io/Reader;
       4: aload_1
       5: iload_2
       6: iload_3
       7: invokevirtual #4                  // Method java/io/Reader.read:([CII)I
      10: istore        4
      12: aload_0
      13: getfield      #3                  // Field base:Lnet/openhft/chronicle/bytes/Bytes;
      16: new           #5                  // class java/lang/String
      19: dup
      20: aload_1
      21: iload_2
      22: iload_3
      23: invokespecial #6                  // Method java/lang/String."<init>":([CII)V
      26: invokeinterface #7,  2            // InterfaceMethod net/openhft/chronicle/bytes/Bytes.append:(Ljava/lang/CharSequence;)Lnet/openhft/chronicle/bytes/ByteStringAppender;
      31: pop
      32: iload         4
      34: ireturn

  public void close() throws java.io.IOException;
    Code:
       0: aload_0
       1: getfield      #2                  // Field reader:Ljava/io/Reader;
       4: invokevirtual #8                  // Method java/io/Reader.close:()V
       7: return
}
