Compiled from "StopCharTesters.java"
public abstract class net.openhft.chronicle.bytes.StopCharTesters extends java.lang.Enum<net.openhft.chronicle.bytes.StopCharTesters> implements net.openhft.chronicle.bytes.StopCharTester {
  public static final net.openhft.chronicle.bytes.StopCharTesters COMMA_STOP;

  public static final net.openhft.chronicle.bytes.StopCharTesters CURLY_STOP;

  public static final net.openhft.chronicle.bytes.StopCharTesters COMMA_SPACE_STOP;

  public static final net.openhft.chronicle.bytes.StopCharTesters CONTROL_STOP;

  public static final net.openhft.chronicle.bytes.StopCharTesters SPACE_STOP;

  public static final net.openhft.chronicle.bytes.StopCharTesters QUOTES;

  public static final net.openhft.chronicle.bytes.StopCharTesters SINGLE_QUOTES;

  public static final net.openhft.chronicle.bytes.StopCharTesters EQUALS;

  public static final net.openhft.chronicle.bytes.StopCharTesters NUMBER_END;

  public static final net.openhft.chronicle.bytes.StopCharTesters NON_ALPHA_DIGIT;

  public static final net.openhft.chronicle.bytes.StopCharTesters ALL;

  private static final net.openhft.chronicle.bytes.StopCharTesters[] $VALUES;

  public static net.openhft.chronicle.bytes.StopCharTesters[] values();
    Code:
       0: getstatic     #2                  // Field $VALUES:[Lnet/openhft/chronicle/bytes/StopCharTesters;
       3: invokevirtual #3                  // Method "[Lnet/openhft/chronicle/bytes/StopCharTesters;".clone:()Ljava/lang/Object;
       6: checkcast     #4                  // class "[Lnet/openhft/chronicle/bytes/StopCharTesters;"
       9: areturn

  public static net.openhft.chronicle.bytes.StopCharTesters valueOf(java.lang.String);
    Code:
       0: ldc           #5                  // class net/openhft/chronicle/bytes/StopCharTesters
       2: aload_0
       3: invokestatic  #6                  // Method java/lang/Enum.valueOf:(Ljava/lang/Class;Ljava/lang/String;)Ljava/lang/Enum;
       6: checkcast     #5                  // class net/openhft/chronicle/bytes/StopCharTesters
       9: areturn

  private net.openhft.chronicle.bytes.StopCharTesters();
    Code:
       0: aload_0
       1: aload_1
       2: iload_2
       3: invokespecial #7                  // Method java/lang/Enum."<init>":(Ljava/lang/String;I)V
       6: return

  net.openhft.chronicle.bytes.StopCharTesters(java.lang.String, int, net.openhft.chronicle.bytes.StopCharTesters$1);
    Code:
       0: aload_0
       1: aload_1
       2: iload_2
       3: invokespecial #1                  // Method "<init>":(Ljava/lang/String;I)V
       6: return

  static {};
    Code:
       0: new           #8                  // class net/openhft/chronicle/bytes/StopCharTesters$1
       3: dup
       4: ldc           #9                  // String COMMA_STOP
       6: iconst_0
       7: invokespecial #10                 // Method net/openhft/chronicle/bytes/StopCharTesters$1."<init>":(Ljava/lang/String;I)V
      10: putstatic     #11                 // Field COMMA_STOP:Lnet/openhft/chronicle/bytes/StopCharTesters;
      13: new           #12                 // class net/openhft/chronicle/bytes/StopCharTesters$2
      16: dup
      17: ldc           #13                 // String CURLY_STOP
      19: iconst_1
      20: invokespecial #14                 // Method net/openhft/chronicle/bytes/StopCharTesters$2."<init>":(Ljava/lang/String;I)V
      23: putstatic     #15                 // Field CURLY_STOP:Lnet/openhft/chronicle/bytes/StopCharTesters;
      26: new           #16                 // class net/openhft/chronicle/bytes/StopCharTesters$3
      29: dup
      30: ldc           #17                 // String COMMA_SPACE_STOP
      32: iconst_2
      33: invokespecial #18                 // Method net/openhft/chronicle/bytes/StopCharTesters$3."<init>":(Ljava/lang/String;I)V
      36: putstatic     #19                 // Field COMMA_SPACE_STOP:Lnet/openhft/chronicle/bytes/StopCharTesters;
      39: new           #20                 // class net/openhft/chronicle/bytes/StopCharTesters$4
      42: dup
      43: ldc           #21                 // String CONTROL_STOP
      45: iconst_3
      46: invokespecial #22                 // Method net/openhft/chronicle/bytes/StopCharTesters$4."<init>":(Ljava/lang/String;I)V
      49: putstatic     #23                 // Field CONTROL_STOP:Lnet/openhft/chronicle/bytes/StopCharTesters;
      52: new           #24                 // class net/openhft/chronicle/bytes/StopCharTesters$5
      55: dup
      56: ldc           #25                 // String SPACE_STOP
      58: iconst_4
      59: invokespecial #26                 // Method net/openhft/chronicle/bytes/StopCharTesters$5."<init>":(Ljava/lang/String;I)V
      62: putstatic     #27                 // Field SPACE_STOP:Lnet/openhft/chronicle/bytes/StopCharTesters;
      65: new           #28                 // class net/openhft/chronicle/bytes/StopCharTesters$6
      68: dup
      69: ldc           #29                 // String QUOTES
      71: iconst_5
      72: invokespecial #30                 // Method net/openhft/chronicle/bytes/StopCharTesters$6."<init>":(Ljava/lang/String;I)V
      75: putstatic     #31                 // Field QUOTES:Lnet/openhft/chronicle/bytes/StopCharTesters;
      78: new           #32                 // class net/openhft/chronicle/bytes/StopCharTesters$7
      81: dup
      82: ldc           #33                 // String SINGLE_QUOTES
      84: bipush        6
      86: invokespecial #34                 // Method net/openhft/chronicle/bytes/StopCharTesters$7."<init>":(Ljava/lang/String;I)V
      89: putstatic     #35                 // Field SINGLE_QUOTES:Lnet/openhft/chronicle/bytes/StopCharTesters;
      92: new           #36                 // class net/openhft/chronicle/bytes/StopCharTesters$8
      95: dup
      96: ldc           #37                 // String EQUALS
      98: bipush        7
     100: invokespecial #38                 // Method net/openhft/chronicle/bytes/StopCharTesters$8."<init>":(Ljava/lang/String;I)V
     103: putstatic     #39                 // Field EQUALS:Lnet/openhft/chronicle/bytes/StopCharTesters;
     106: new           #40                 // class net/openhft/chronicle/bytes/StopCharTesters$9
     109: dup
     110: ldc           #41                 // String NUMBER_END
     112: bipush        8
     114: invokespecial #42                 // Method net/openhft/chronicle/bytes/StopCharTesters$9."<init>":(Ljava/lang/String;I)V
     117: putstatic     #43                 // Field NUMBER_END:Lnet/openhft/chronicle/bytes/StopCharTesters;
     120: new           #44                 // class net/openhft/chronicle/bytes/StopCharTesters$10
     123: dup
     124: ldc           #45                 // String NON_ALPHA_DIGIT
     126: bipush        9
     128: invokespecial #46                 // Method net/openhft/chronicle/bytes/StopCharTesters$10."<init>":(Ljava/lang/String;I)V
     131: putstatic     #47                 // Field NON_ALPHA_DIGIT:Lnet/openhft/chronicle/bytes/StopCharTesters;
     134: new           #48                 // class net/openhft/chronicle/bytes/StopCharTesters$11
     137: dup
     138: ldc           #49                 // String ALL
     140: bipush        10
     142: invokespecial #50                 // Method net/openhft/chronicle/bytes/StopCharTesters$11."<init>":(Ljava/lang/String;I)V
     145: putstatic     #51                 // Field ALL:Lnet/openhft/chronicle/bytes/StopCharTesters;
     148: bipush        11
     150: anewarray     #5                  // class net/openhft/chronicle/bytes/StopCharTesters
     153: dup
     154: iconst_0
     155: getstatic     #11                 // Field COMMA_STOP:Lnet/openhft/chronicle/bytes/StopCharTesters;
     158: aastore
     159: dup
     160: iconst_1
     161: getstatic     #15                 // Field CURLY_STOP:Lnet/openhft/chronicle/bytes/StopCharTesters;
     164: aastore
     165: dup
     166: iconst_2
     167: getstatic     #19                 // Field COMMA_SPACE_STOP:Lnet/openhft/chronicle/bytes/StopCharTesters;
     170: aastore
     171: dup
     172: iconst_3
     173: getstatic     #23                 // Field CONTROL_STOP:Lnet/openhft/chronicle/bytes/StopCharTesters;
     176: aastore
     177: dup
     178: iconst_4
     179: getstatic     #27                 // Field SPACE_STOP:Lnet/openhft/chronicle/bytes/StopCharTesters;
     182: aastore
     183: dup
     184: iconst_5
     185: getstatic     #31                 // Field QUOTES:Lnet/openhft/chronicle/bytes/StopCharTesters;
     188: aastore
     189: dup
     190: bipush        6
     192: getstatic     #35                 // Field SINGLE_QUOTES:Lnet/openhft/chronicle/bytes/StopCharTesters;
     195: aastore
     196: dup
     197: bipush        7
     199: getstatic     #39                 // Field EQUALS:Lnet/openhft/chronicle/bytes/StopCharTesters;
     202: aastore
     203: dup
     204: bipush        8
     206: getstatic     #43                 // Field NUMBER_END:Lnet/openhft/chronicle/bytes/StopCharTesters;
     209: aastore
     210: dup
     211: bipush        9
     213: getstatic     #47                 // Field NON_ALPHA_DIGIT:Lnet/openhft/chronicle/bytes/StopCharTesters;
     216: aastore
     217: dup
     218: bipush        10
     220: getstatic     #51                 // Field ALL:Lnet/openhft/chronicle/bytes/StopCharTesters;
     223: aastore
     224: putstatic     #2                  // Field $VALUES:[Lnet/openhft/chronicle/bytes/StopCharTesters;
     227: return
}
