Compiled from "LocalDateDeserializer.java"
public class io.dekorate.deps.jackson.datatype.jsr310.deser.LocalDateDeserializer extends io.dekorate.deps.jackson.datatype.jsr310.deser.JSR310DateTimeDeserializerBase<java.time.LocalDate> {
  private static final long serialVersionUID;

  private static final java.time.format.DateTimeFormatter DEFAULT_FORMATTER;

  public static final io.dekorate.deps.jackson.datatype.jsr310.deser.LocalDateDeserializer INSTANCE;

  protected io.dekorate.deps.jackson.datatype.jsr310.deser.LocalDateDeserializer();
    Code:
       0: aload_0
       1: getstatic     #18                 // Field DEFAULT_FORMATTER:Ljava/time/format/DateTimeFormatter;
       4: invokespecial #21                 // Method "<init>":(Ljava/time/format/DateTimeFormatter;)V
       7: return

  public io.dekorate.deps.jackson.datatype.jsr310.deser.LocalDateDeserializer(java.time.format.DateTimeFormatter);
    Code:
       0: aload_0
       1: ldc           #24                 // class java/time/LocalDate
       3: aload_1
       4: invokespecial #27                 // Method io/dekorate/deps/jackson/datatype/jsr310/deser/JSR310DateTimeDeserializerBase."<init>":(Ljava/lang/Class;Ljava/time/format/DateTimeFormatter;)V
       7: return

  public io.dekorate.deps.jackson.datatype.jsr310.deser.LocalDateDeserializer(io.dekorate.deps.jackson.datatype.jsr310.deser.LocalDateDeserializer, java.time.format.DateTimeFormatter);
    Code:
       0: aload_0
       1: aload_1
       2: aload_2
       3: invokespecial #32                 // Method io/dekorate/deps/jackson/datatype/jsr310/deser/JSR310DateTimeDeserializerBase."<init>":(Lio/dekorate/deps/jackson/datatype/jsr310/deser/JSR310DateTimeDeserializerBase;Ljava/time/format/DateTimeFormatter;)V
       6: return

  protected io.dekorate.deps.jackson.datatype.jsr310.deser.LocalDateDeserializer(io.dekorate.deps.jackson.datatype.jsr310.deser.LocalDateDeserializer, java.lang.Boolean);
    Code:
       0: aload_0
       1: aload_1
       2: aload_2
       3: invokespecial #37                 // Method io/dekorate/deps/jackson/datatype/jsr310/deser/JSR310DateTimeDeserializerBase."<init>":(Lio/dekorate/deps/jackson/datatype/jsr310/deser/JSR310DateTimeDeserializerBase;Ljava/lang/Boolean;)V
       6: return

  protected io.dekorate.deps.jackson.datatype.jsr310.deser.LocalDateDeserializer withDateFormat(java.time.format.DateTimeFormatter);
    Code:
       0: new           #2                  // class io/dekorate/deps/jackson/datatype/jsr310/deser/LocalDateDeserializer
       3: dup
       4: aload_0
       5: aload_1
       6: invokespecial #43                 // Method "<init>":(Lio/dekorate/deps/jackson/datatype/jsr310/deser/LocalDateDeserializer;Ljava/time/format/DateTimeFormatter;)V
       9: areturn

  protected io.dekorate.deps.jackson.datatype.jsr310.deser.LocalDateDeserializer withLeniency(java.lang.Boolean);
    Code:
       0: new           #2                  // class io/dekorate/deps/jackson/datatype/jsr310/deser/LocalDateDeserializer
       3: dup
       4: aload_0
       5: aload_1
       6: invokespecial #47                 // Method "<init>":(Lio/dekorate/deps/jackson/datatype/jsr310/deser/LocalDateDeserializer;Ljava/lang/Boolean;)V
       9: areturn

  public java.time.LocalDate deserialize(io.dekorate.deps.jackson.core.JsonParser, io.dekorate.deps.jackson.databind.DeserializationContext) throws java.io.IOException;
    Code:
       0: aload_1
       1: getstatic     #59                 // Field io/dekorate/deps/jackson/core/JsonToken.VALUE_STRING:Lio/dekorate/deps/jackson/core/JsonToken;
       4: invokevirtual #65                 // Method io/dekorate/deps/jackson/core/JsonParser.hasToken:(Lio/dekorate/deps/jackson/core/JsonToken;)Z
       7: ifeq          133
      10: aload_1
      11: invokevirtual #69                 // Method io/dekorate/deps/jackson/core/JsonParser.getText:()Ljava/lang/String;
      14: invokevirtual #74                 // Method java/lang/String.trim:()Ljava/lang/String;
      17: astore_3
      18: aload_3
      19: invokevirtual #78                 // Method java/lang/String.length:()I
      22: ifne          47
      25: aload_0
      26: invokevirtual #82                 // Method isLenient:()Z
      29: ifne          45
      32: aload_0
      33: aload_1
      34: aload_2
      35: getstatic     #59                 // Field io/dekorate/deps/jackson/core/JsonToken.VALUE_STRING:Lio/dekorate/deps/jackson/core/JsonToken;
      38: invokevirtual #86                 // Method _failForNotLenient:(Lio/dekorate/deps/jackson/core/JsonParser;Lio/dekorate/deps/jackson/databind/DeserializationContext;Lio/dekorate/deps/jackson/core/JsonToken;)Ljava/lang/Object;
      41: checkcast     #24                 // class java/time/LocalDate
      44: areturn
      45: aconst_null
      46: areturn
      47: aload_0
      48: getfield      #89                 // Field _formatter:Ljava/time/format/DateTimeFormatter;
      51: astore        4
      53: aload         4
      55: getstatic     #18                 // Field DEFAULT_FORMATTER:Ljava/time/format/DateTimeFormatter;
      58: if_acmpne     112
      61: aload_3
      62: invokevirtual #78                 // Method java/lang/String.length:()I
      65: bipush        10
      67: if_icmple     112
      70: aload_3
      71: bipush        10
      73: invokevirtual #93                 // Method java/lang/String.charAt:(I)C
      76: bipush        84
      78: if_icmpne     112
      81: aload_3
      82: ldc           #95                 // String Z
      84: invokevirtual #99                 // Method java/lang/String.endsWith:(Ljava/lang/String;)Z
      87: ifeq          104
      90: aload_3
      91: invokestatic  #105                // Method java/time/Instant.parse:(Ljava/lang/CharSequence;)Ljava/time/Instant;
      94: getstatic     #111                // Field java/time/ZoneOffset.UTC:Ljava/time/ZoneOffset;
      97: invokestatic  #117                // Method java/time/LocalDateTime.ofInstant:(Ljava/time/Instant;Ljava/time/ZoneId;)Ljava/time/LocalDateTime;
     100: invokevirtual #121                // Method java/time/LocalDateTime.toLocalDate:()Ljava/time/LocalDate;
     103: areturn
     104: aload_3
     105: getstatic     #126                // Field java/time/format/DateTimeFormatter.ISO_LOCAL_DATE_TIME:Ljava/time/format/DateTimeFormatter;
     108: invokestatic  #129                // Method java/time/LocalDate.parse:(Ljava/lang/CharSequence;Ljava/time/format/DateTimeFormatter;)Ljava/time/LocalDate;
     111: areturn
     112: aload_3
     113: aload         4
     115: invokestatic  #129                // Method java/time/LocalDate.parse:(Ljava/lang/CharSequence;Ljava/time/format/DateTimeFormatter;)Ljava/time/LocalDate;
     118: areturn
     119: astore        5
     121: aload_0
     122: aload_2
     123: aload         5
     125: aload_3
     126: invokevirtual #133                // Method _handleDateTimeException:(Lio/dekorate/deps/jackson/databind/DeserializationContext;Ljava/time/DateTimeException;Ljava/lang/String;)Ljava/lang/Object;
     129: checkcast     #24                 // class java/time/LocalDate
     132: areturn
     133: aload_1
     134: invokevirtual #136                // Method io/dekorate/deps/jackson/core/JsonParser.isExpectedStartArrayToken:()Z
     137: ifeq          286
     140: aload_1
     141: invokevirtual #140                // Method io/dekorate/deps/jackson/core/JsonParser.nextToken:()Lio/dekorate/deps/jackson/core/JsonToken;
     144: astore_3
     145: aload_3
     146: getstatic     #143                // Field io/dekorate/deps/jackson/core/JsonToken.END_ARRAY:Lio/dekorate/deps/jackson/core/JsonToken;
     149: if_acmpne     154
     152: aconst_null
     153: areturn
     154: aload_2
     155: getstatic     #149                // Field io/dekorate/deps/jackson/databind/DeserializationFeature.UNWRAP_SINGLE_VALUE_ARRAYS:Lio/dekorate/deps/jackson/databind/DeserializationFeature;
     158: invokevirtual #155                // Method io/dekorate/deps/jackson/databind/DeserializationContext.isEnabled:(Lio/dekorate/deps/jackson/databind/DeserializationFeature;)Z
     161: ifeq          205
     164: aload_3
     165: getstatic     #59                 // Field io/dekorate/deps/jackson/core/JsonToken.VALUE_STRING:Lio/dekorate/deps/jackson/core/JsonToken;
     168: if_acmpeq     178
     171: aload_3
     172: getstatic     #158                // Field io/dekorate/deps/jackson/core/JsonToken.VALUE_EMBEDDED_OBJECT:Lio/dekorate/deps/jackson/core/JsonToken;
     175: if_acmpne     205
     178: aload_0
     179: aload_1
     180: aload_2
     181: invokevirtual #160                // Method deserialize:(Lio/dekorate/deps/jackson/core/JsonParser;Lio/dekorate/deps/jackson/databind/DeserializationContext;)Ljava/time/LocalDate;
     184: astore        4
     186: aload_1
     187: invokevirtual #140                // Method io/dekorate/deps/jackson/core/JsonParser.nextToken:()Lio/dekorate/deps/jackson/core/JsonToken;
     190: getstatic     #143                // Field io/dekorate/deps/jackson/core/JsonToken.END_ARRAY:Lio/dekorate/deps/jackson/core/JsonToken;
     193: if_acmpeq     202
     196: aload_0
     197: aload_1
     198: aload_2
     199: invokevirtual #164                // Method handleMissingEndArrayForSingle:(Lio/dekorate/deps/jackson/core/JsonParser;Lio/dekorate/deps/jackson/databind/DeserializationContext;)V
     202: aload         4
     204: areturn
     205: aload_3
     206: getstatic     #167                // Field io/dekorate/deps/jackson/core/JsonToken.VALUE_NUMBER_INT:Lio/dekorate/deps/jackson/core/JsonToken;
     209: if_acmpne     267
     212: aload_1
     213: invokevirtual #170                // Method io/dekorate/deps/jackson/core/JsonParser.getIntValue:()I
     216: istore        4
     218: aload_1
     219: iconst_m1
     220: invokevirtual #174                // Method io/dekorate/deps/jackson/core/JsonParser.nextIntValue:(I)I
     223: istore        5
     225: aload_1
     226: iconst_m1
     227: invokevirtual #174                // Method io/dekorate/deps/jackson/core/JsonParser.nextIntValue:(I)I
     230: istore        6
     232: aload_1
     233: invokevirtual #140                // Method io/dekorate/deps/jackson/core/JsonParser.nextToken:()Lio/dekorate/deps/jackson/core/JsonToken;
     236: getstatic     #143                // Field io/dekorate/deps/jackson/core/JsonToken.END_ARRAY:Lio/dekorate/deps/jackson/core/JsonToken;
     239: if_acmpeq     257
     242: aload_2
     243: aload_1
     244: aload_0
     245: invokevirtual #178                // Method handledType:()Ljava/lang/Class;
     248: getstatic     #143                // Field io/dekorate/deps/jackson/core/JsonToken.END_ARRAY:Lio/dekorate/deps/jackson/core/JsonToken;
     251: ldc           #180                // String Expected array to end
     253: invokevirtual #184                // Method io/dekorate/deps/jackson/databind/DeserializationContext.wrongTokenException:(Lio/dekorate/deps/jackson/core/JsonParser;Ljava/lang/Class;Lio/dekorate/deps/jackson/core/JsonToken;Ljava/lang/String;)Lio/dekorate/deps/jackson/databind/JsonMappingException;
     256: athrow
     257: iload         4
     259: iload         5
     261: iload         6
     263: invokestatic  #188                // Method java/time/LocalDate.of:(III)Ljava/time/LocalDate;
     266: areturn
     267: aload_2
     268: aload_0
     269: invokevirtual #178                // Method handledType:()Ljava/lang/Class;
     272: ldc           #190                // String Unexpected token (%s) within Array, expected VALUE_NUMBER_INT
     274: iconst_1
     275: anewarray     #192                // class java/lang/Object
     278: dup
     279: iconst_0
     280: aload_3
     281: aastore
     282: invokevirtual #196                // Method io/dekorate/deps/jackson/databind/DeserializationContext.reportInputMismatch:(Ljava/lang/Class;Ljava/lang/String;[Ljava/lang/Object;)Ljava/lang/Object;
     285: pop
     286: aload_1
     287: getstatic     #158                // Field io/dekorate/deps/jackson/core/JsonToken.VALUE_EMBEDDED_OBJECT:Lio/dekorate/deps/jackson/core/JsonToken;
     290: invokevirtual #65                 // Method io/dekorate/deps/jackson/core/JsonParser.hasToken:(Lio/dekorate/deps/jackson/core/JsonToken;)Z
     293: ifeq          304
     296: aload_1
     297: invokevirtual #200                // Method io/dekorate/deps/jackson/core/JsonParser.getEmbeddedObject:()Ljava/lang/Object;
     300: checkcast     #24                 // class java/time/LocalDate
     303: areturn
     304: aload_1
     305: getstatic     #167                // Field io/dekorate/deps/jackson/core/JsonToken.VALUE_NUMBER_INT:Lio/dekorate/deps/jackson/core/JsonToken;
     308: invokevirtual #65                 // Method io/dekorate/deps/jackson/core/JsonParser.hasToken:(Lio/dekorate/deps/jackson/core/JsonToken;)Z
     311: ifeq          342
     314: aload_0
     315: invokevirtual #82                 // Method isLenient:()Z
     318: ifne          334
     321: aload_0
     322: aload_1
     323: aload_2
     324: getstatic     #59                 // Field io/dekorate/deps/jackson/core/JsonToken.VALUE_STRING:Lio/dekorate/deps/jackson/core/JsonToken;
     327: invokevirtual #86                 // Method _failForNotLenient:(Lio/dekorate/deps/jackson/core/JsonParser;Lio/dekorate/deps/jackson/databind/DeserializationContext;Lio/dekorate/deps/jackson/core/JsonToken;)Ljava/lang/Object;
     330: checkcast     #24                 // class java/time/LocalDate
     333: areturn
     334: aload_1
     335: invokevirtual #204                // Method io/dekorate/deps/jackson/core/JsonParser.getLongValue:()J
     338: invokestatic  #208                // Method java/time/LocalDate.ofEpochDay:(J)Ljava/time/LocalDate;
     341: areturn
     342: aload_0
     343: aload_2
     344: aload_1
     345: ldc           #210                // String Expected array or string.
     347: iconst_0
     348: anewarray     #192                // class java/lang/Object
     351: invokevirtual #214                // Method _handleUnexpectedToken:(Lio/dekorate/deps/jackson/databind/DeserializationContext;Lio/dekorate/deps/jackson/core/JsonParser;Ljava/lang/String;[Ljava/lang/Object;)Ljava/lang/Object;
     354: checkcast     #24                 // class java/time/LocalDate
     357: areturn
    Exception table:
       from    to  target type
          53   103   119   Class java/time/DateTimeException
         104   111   119   Class java/time/DateTimeException
         112   118   119   Class java/time/DateTimeException

  protected io.dekorate.deps.jackson.datatype.jsr310.deser.JSR310DateTimeDeserializerBase withLeniency(java.lang.Boolean);
    Code:
       0: aload_0
       1: aload_1
       2: invokevirtual #233                // Method withLeniency:(Ljava/lang/Boolean;)Lio/dekorate/deps/jackson/datatype/jsr310/deser/LocalDateDeserializer;
       5: areturn

  protected io.dekorate.deps.jackson.datatype.jsr310.deser.JSR310DateTimeDeserializerBase withDateFormat(java.time.format.DateTimeFormatter);
    Code:
       0: aload_0
       1: aload_1
       2: invokevirtual #236                // Method withDateFormat:(Ljava/time/format/DateTimeFormatter;)Lio/dekorate/deps/jackson/datatype/jsr310/deser/LocalDateDeserializer;
       5: areturn

  public java.lang.Object deserialize(io.dekorate.deps.jackson.core.JsonParser, io.dekorate.deps.jackson.databind.DeserializationContext) throws java.io.IOException, io.dekorate.deps.jackson.core.JsonProcessingException;
    Code:
       0: aload_0
       1: aload_1
       2: aload_2
       3: invokevirtual #160                // Method deserialize:(Lio/dekorate/deps/jackson/core/JsonParser;Lio/dekorate/deps/jackson/databind/DeserializationContext;)Ljava/time/LocalDate;
       6: areturn

  static {};
    Code:
       0: getstatic     #243                // Field java/time/format/DateTimeFormatter.ISO_LOCAL_DATE:Ljava/time/format/DateTimeFormatter;
       3: putstatic     #18                 // Field DEFAULT_FORMATTER:Ljava/time/format/DateTimeFormatter;
       6: new           #2                  // class io/dekorate/deps/jackson/datatype/jsr310/deser/LocalDateDeserializer
       9: dup
      10: invokespecial #245                // Method "<init>":()V
      13: putstatic     #247                // Field INSTANCE:Lio/dekorate/deps/jackson/datatype/jsr310/deser/LocalDateDeserializer;
      16: return
}
