Compiled from "InjectionTargetFactoryImpl.java"
public class org.jboss.weld.manager.InjectionTargetFactoryImpl<T> implements org.jboss.weld.manager.api.WeldInjectionTargetFactory<T> {
  private final org.jboss.weld.manager.BeanManagerImpl manager;

  private final org.jboss.weld.annotated.enhanced.EnhancedAnnotatedType<T> type;

  private final org.jboss.weld.injection.producer.InjectionTargetService injectionTargetService;

  private final org.jboss.weld.injection.spi.InjectionServices injectionServices;

  protected org.jboss.weld.manager.InjectionTargetFactoryImpl(javax.enterprise.inject.spi.AnnotatedType<T>, org.jboss.weld.manager.BeanManagerImpl);
    Code:
       0: aload_0
       1: invokespecial #1                  // Method java/lang/Object."<init>":()V
       4: aload_0
       5: aload_2
       6: putfield      #2                  // Field manager:Lorg/jboss/weld/manager/BeanManagerImpl;
       9: aload_0
      10: aload_2
      11: invokevirtual #3                  // Method org/jboss/weld/manager/BeanManagerImpl.getServices:()Lorg/jboss/weld/bootstrap/api/ServiceRegistry;
      14: ldc           #4                  // class org/jboss/weld/resources/ClassTransformer
      16: invokeinterface #5,  2            // InterfaceMethod org/jboss/weld/bootstrap/api/ServiceRegistry.get:(Ljava/lang/Class;)Lorg/jboss/weld/bootstrap/api/Service;
      21: checkcast     #4                  // class org/jboss/weld/resources/ClassTransformer
      24: aload_1
      25: aload_2
      26: invokevirtual #6                  // Method org/jboss/weld/manager/BeanManagerImpl.getId:()Ljava/lang/String;
      29: invokevirtual #7                  // Method org/jboss/weld/resources/ClassTransformer.getEnhancedAnnotatedType:(Ljavax/enterprise/inject/spi/AnnotatedType;Ljava/lang/String;)Lorg/jboss/weld/annotated/enhanced/EnhancedAnnotatedType;
      32: putfield      #8                  // Field type:Lorg/jboss/weld/annotated/enhanced/EnhancedAnnotatedType;
      35: aload_0
      36: aload_2
      37: invokevirtual #3                  // Method org/jboss/weld/manager/BeanManagerImpl.getServices:()Lorg/jboss/weld/bootstrap/api/ServiceRegistry;
      40: ldc           #9                  // class org/jboss/weld/injection/producer/InjectionTargetService
      42: invokeinterface #5,  2            // InterfaceMethod org/jboss/weld/bootstrap/api/ServiceRegistry.get:(Ljava/lang/Class;)Lorg/jboss/weld/bootstrap/api/Service;
      47: checkcast     #9                  // class org/jboss/weld/injection/producer/InjectionTargetService
      50: putfield      #10                 // Field injectionTargetService:Lorg/jboss/weld/injection/producer/InjectionTargetService;
      53: aload_0
      54: aload_2
      55: invokevirtual #3                  // Method org/jboss/weld/manager/BeanManagerImpl.getServices:()Lorg/jboss/weld/bootstrap/api/ServiceRegistry;
      58: ldc           #11                 // class org/jboss/weld/injection/spi/InjectionServices
      60: invokeinterface #5,  2            // InterfaceMethod org/jboss/weld/bootstrap/api/ServiceRegistry.get:(Ljava/lang/Class;)Lorg/jboss/weld/bootstrap/api/Service;
      65: checkcast     #11                 // class org/jboss/weld/injection/spi/InjectionServices
      68: putfield      #12                 // Field injectionServices:Lorg/jboss/weld/injection/spi/InjectionServices;
      71: return

  public org.jboss.weld.manager.api.WeldInjectionTarget<T> createInjectionTarget(javax.enterprise.inject.spi.Bean<T>);
    Code:
       0: aload_0
       1: aload_1
       2: iconst_0
       3: invokespecial #13                 // Method createInjectionTarget:(Ljavax/enterprise/inject/spi/Bean;Z)Lorg/jboss/weld/manager/api/WeldInjectionTarget;
       6: areturn

  public org.jboss.weld.manager.api.WeldInjectionTarget<T> createInterceptorInjectionTarget();
    Code:
       0: aload_0
       1: aconst_null
       2: iconst_1
       3: invokespecial #13                 // Method createInjectionTarget:(Ljavax/enterprise/inject/spi/Bean;Z)Lorg/jboss/weld/manager/api/WeldInjectionTarget;
       6: areturn

  private org.jboss.weld.manager.api.WeldInjectionTarget<T> createInjectionTarget(javax.enterprise.inject.spi.Bean<T>, boolean);
    Code:
       0: aload_0
       1: aload_0
       2: aload_0
       3: getfield      #8                  // Field type:Lorg/jboss/weld/annotated/enhanced/EnhancedAnnotatedType;
       6: aload_1
       7: iload_2
       8: invokevirtual #14                 // Method createInjectionTarget:(Lorg/jboss/weld/annotated/enhanced/EnhancedAnnotatedType;Ljavax/enterprise/inject/spi/Bean;Z)Lorg/jboss/weld/injection/producer/BasicInjectionTarget;
      11: invokespecial #15                 // Method validate:(Ljavax/enterprise/inject/spi/InjectionTarget;)Ljavax/enterprise/inject/spi/InjectionTarget;
      14: checkcast     #16                 // class org/jboss/weld/manager/api/WeldInjectionTarget
      17: areturn
      18: astore_3
      19: new           #18                 // class org/jboss/weld/exceptions/IllegalArgumentException
      22: dup
      23: aload_3
      24: invokespecial #19                 // Method org/jboss/weld/exceptions/IllegalArgumentException."<init>":(Ljava/lang/Throwable;)V
      27: athrow
    Exception table:
       from    to  target type
           0    17    18   Class java/lang/Throwable

  public org.jboss.weld.injection.producer.BasicInjectionTarget<T> createInjectionTarget(org.jboss.weld.annotated.enhanced.EnhancedAnnotatedType<T>, javax.enterprise.inject.spi.Bean<T>, boolean);
    Code:
       0: aload_0
       1: aload_1
       2: aload_2
       3: iload_3
       4: invokespecial #20                 // Method chooseInjectionTarget:(Lorg/jboss/weld/annotated/enhanced/EnhancedAnnotatedType;Ljavax/enterprise/inject/spi/Bean;Z)Lorg/jboss/weld/injection/producer/BasicInjectionTarget;
       7: astore        4
       9: aload_0
      10: aload         4
      12: invokespecial #21                 // Method initialize:(Lorg/jboss/weld/injection/producer/BasicInjectionTarget;)Lorg/jboss/weld/injection/producer/BasicInjectionTarget;
      15: pop
      16: aload_0
      17: aload         4
      19: invokespecial #22                 // Method postProcess:(Ljavax/enterprise/inject/spi/InjectionTarget;)V
      22: aload         4
      24: areturn

  private org.jboss.weld.injection.producer.BasicInjectionTarget<T> chooseInjectionTarget(org.jboss.weld.annotated.enhanced.EnhancedAnnotatedType<T>, javax.enterprise.inject.spi.Bean<T>, boolean);
    Code:
       0: aload_2
       1: instanceof    #23                 // class javax/enterprise/inject/spi/Decorator
       4: ifne          18
       7: aload_1
       8: ldc           #24                 // class javax/decorator/Decorator
      10: invokeinterface #25,  2           // InterfaceMethod org/jboss/weld/annotated/enhanced/EnhancedAnnotatedType.isAnnotationPresent:(Ljava/lang/Class;)Z
      15: ifeq          32
      18: new           #26                 // class org/jboss/weld/injection/producer/DecoratorInjectionTarget
      21: dup
      22: aload_1
      23: aload_2
      24: aload_0
      25: getfield      #2                  // Field manager:Lorg/jboss/weld/manager/BeanManagerImpl;
      28: invokespecial #27                 // Method org/jboss/weld/injection/producer/DecoratorInjectionTarget."<init>":(Lorg/jboss/weld/annotated/enhanced/EnhancedAnnotatedType;Ljavax/enterprise/inject/spi/Bean;Lorg/jboss/weld/manager/BeanManagerImpl;)V
      31: areturn
      32: aload_1
      33: aload_2
      34: aload_0
      35: getfield      #2                  // Field manager:Lorg/jboss/weld/manager/BeanManagerImpl;
      38: invokestatic  #28                 // Method org/jboss/weld/util/InjectionTargets.createNonProducibleInjectionTarget:(Lorg/jboss/weld/annotated/enhanced/EnhancedAnnotatedType;Ljavax/enterprise/inject/spi/Bean;Lorg/jboss/weld/manager/BeanManagerImpl;)Lorg/jboss/weld/injection/producer/NonProducibleInjectionTarget;
      41: astore        4
      43: aload         4
      45: ifnull        51
      48: aload         4
      50: areturn
      51: aload_2
      52: instanceof    #29                 // class org/jboss/weld/bean/SessionBean
      55: ifeq          71
      58: aload_1
      59: aload_2
      60: checkcast     #29                 // class org/jboss/weld/bean/SessionBean
      63: aload_0
      64: getfield      #2                  // Field manager:Lorg/jboss/weld/manager/BeanManagerImpl;
      67: invokestatic  #30                 // Method org/jboss/weld/injection/producer/ejb/SessionBeanInjectionTarget.of:(Lorg/jboss/weld/annotated/enhanced/EnhancedAnnotatedType;Lorg/jboss/weld/bean/SessionBean;Lorg/jboss/weld/manager/BeanManagerImpl;)Lorg/jboss/weld/injection/producer/ejb/SessionBeanInjectionTarget;
      70: areturn
      71: aload_2
      72: instanceof    #31                 // class javax/enterprise/inject/spi/Interceptor
      75: ifne          89
      78: aload_1
      79: ldc           #32                 // class javax/interceptor/Interceptor
      81: invokeinterface #25,  2           // InterfaceMethod org/jboss/weld/annotated/enhanced/EnhancedAnnotatedType.isAnnotationPresent:(Ljava/lang/Class;)Z
      86: ifeq          99
      89: aload_1
      90: aload_2
      91: aload_0
      92: getfield      #2                  // Field manager:Lorg/jboss/weld/manager/BeanManagerImpl;
      95: invokestatic  #33                 // Method org/jboss/weld/injection/producer/BeanInjectionTarget.forCdiInterceptor:(Lorg/jboss/weld/annotated/enhanced/EnhancedAnnotatedType;Ljavax/enterprise/inject/spi/Bean;Lorg/jboss/weld/manager/BeanManagerImpl;)Lorg/jboss/weld/injection/producer/BeanInjectionTarget;
      98: areturn
      99: iload_3
     100: ifeq          112
     103: aload_1
     104: aload_0
     105: getfield      #2                  // Field manager:Lorg/jboss/weld/manager/BeanManagerImpl;
     108: invokestatic  #34                 // Method org/jboss/weld/injection/producer/BasicInjectionTarget.createNonCdiInterceptor:(Lorg/jboss/weld/annotated/enhanced/EnhancedAnnotatedType;Lorg/jboss/weld/manager/BeanManagerImpl;)Lorg/jboss/weld/injection/producer/BasicInjectionTarget;
     111: areturn
     112: aload_1
     113: aload_2
     114: aload_0
     115: getfield      #2                  // Field manager:Lorg/jboss/weld/manager/BeanManagerImpl;
     118: invokestatic  #35                 // Method org/jboss/weld/injection/producer/BeanInjectionTarget.createDefault:(Lorg/jboss/weld/annotated/enhanced/EnhancedAnnotatedType;Ljavax/enterprise/inject/spi/Bean;Lorg/jboss/weld/manager/BeanManagerImpl;)Lorg/jboss/weld/injection/producer/BeanInjectionTarget;
     121: areturn

  protected javax.enterprise.inject.spi.InjectionTarget<T> createMessageDrivenInjectionTarget(org.jboss.weld.ejb.InternalEjbDescriptor<T>);
    Code:
       0: aload_1
       1: aload_0
       2: getfield      #2                  // Field manager:Lorg/jboss/weld/manager/BeanManagerImpl;
       5: aload_0
       6: getfield      #8                  // Field type:Lorg/jboss/weld/annotated/enhanced/EnhancedAnnotatedType;
       9: invokestatic  #36                 // Method org/jboss/weld/util/Beans.getEjbImplementationClass:(Lorg/jboss/weld/ejb/InternalEjbDescriptor;Lorg/jboss/weld/manager/BeanManagerImpl;Lorg/jboss/weld/annotated/enhanced/EnhancedAnnotatedType;)Lorg/jboss/weld/annotated/enhanced/EnhancedAnnotatedType;
      12: astore_2
      13: aconst_null
      14: astore_3
      15: aload_0
      16: getfield      #8                  // Field type:Lorg/jboss/weld/annotated/enhanced/EnhancedAnnotatedType;
      19: aload_2
      20: invokevirtual #37                 // Method java/lang/Object.equals:(Ljava/lang/Object;)Z
      23: ifeq          46
      26: new           #38                 // class org/jboss/weld/injection/producer/DefaultInstantiator
      29: dup
      30: aload_0
      31: getfield      #8                  // Field type:Lorg/jboss/weld/annotated/enhanced/EnhancedAnnotatedType;
      34: aconst_null
      35: aload_0
      36: getfield      #2                  // Field manager:Lorg/jboss/weld/manager/BeanManagerImpl;
      39: invokespecial #39                 // Method org/jboss/weld/injection/producer/DefaultInstantiator."<init>":(Lorg/jboss/weld/annotated/enhanced/EnhancedAnnotatedType;Ljavax/enterprise/inject/spi/Bean;Lorg/jboss/weld/manager/BeanManagerImpl;)V
      42: astore_3
      43: goto          60
      46: aload_0
      47: getfield      #8                  // Field type:Lorg/jboss/weld/annotated/enhanced/EnhancedAnnotatedType;
      50: aload_2
      51: aconst_null
      52: aload_0
      53: getfield      #2                  // Field manager:Lorg/jboss/weld/manager/BeanManagerImpl;
      56: invokestatic  #40                 // Method org/jboss/weld/injection/producer/SubclassedComponentInstantiator.forSubclassedEjb:(Lorg/jboss/weld/annotated/enhanced/EnhancedAnnotatedType;Lorg/jboss/weld/annotated/enhanced/EnhancedAnnotatedType;Ljavax/enterprise/inject/spi/Bean;Lorg/jboss/weld/manager/BeanManagerImpl;)Lorg/jboss/weld/injection/producer/SubclassedComponentInstantiator;
      59: astore_3
      60: aload_0
      61: aload_0
      62: getfield      #8                  // Field type:Lorg/jboss/weld/annotated/enhanced/EnhancedAnnotatedType;
      65: aconst_null
      66: aload_0
      67: getfield      #2                  // Field manager:Lorg/jboss/weld/manager/BeanManagerImpl;
      70: aload_3
      71: invokestatic  #41                 // Method org/jboss/weld/injection/producer/BasicInjectionTarget.createDefault:(Lorg/jboss/weld/annotated/enhanced/EnhancedAnnotatedType;Ljavax/enterprise/inject/spi/Bean;Lorg/jboss/weld/manager/BeanManagerImpl;Lorg/jboss/weld/injection/producer/Instantiator;)Lorg/jboss/weld/injection/producer/BasicInjectionTarget;
      74: invokespecial #42                 // Method prepareInjectionTarget:(Lorg/jboss/weld/injection/producer/BasicInjectionTarget;)Lorg/jboss/weld/injection/producer/BasicInjectionTarget;
      77: areturn

  private org.jboss.weld.injection.producer.BasicInjectionTarget<T> initialize(org.jboss.weld.injection.producer.BasicInjectionTarget<T>);
    Code:
       0: aload_0
       1: getfield      #10                 // Field injectionTargetService:Lorg/jboss/weld/injection/producer/InjectionTargetService;
       4: aload_0
       5: getfield      #8                  // Field type:Lorg/jboss/weld/annotated/enhanced/EnhancedAnnotatedType;
       8: aload_1
       9: invokevirtual #43                 // Method org/jboss/weld/injection/producer/InjectionTargetService.addInjectionTargetToBeInitialized:(Lorg/jboss/weld/annotated/enhanced/EnhancedAnnotatedType;Lorg/jboss/weld/injection/producer/BasicInjectionTarget;)V
      12: aload_1
      13: areturn

  private <I extends javax.enterprise.inject.spi.InjectionTarget<T>> I validate(I);
    Code:
       0: aload_0
       1: getfield      #10                 // Field injectionTargetService:Lorg/jboss/weld/injection/producer/InjectionTargetService;
       4: aload_1
       5: invokevirtual #44                 // Method org/jboss/weld/injection/producer/InjectionTargetService.validateProducer:(Ljavax/enterprise/inject/spi/Producer;)V
       8: aload_1
       9: areturn

  private void postProcess(javax.enterprise.inject.spi.InjectionTarget<T>);
    Code:
       0: aload_0
       1: getfield      #12                 // Field injectionServices:Lorg/jboss/weld/injection/spi/InjectionServices;
       4: ifnull        26
       7: aload_0
       8: getfield      #12                 // Field injectionServices:Lorg/jboss/weld/injection/spi/InjectionServices;
      11: aload_1
      12: aload_0
      13: getfield      #8                  // Field type:Lorg/jboss/weld/annotated/enhanced/EnhancedAnnotatedType;
      16: invokeinterface #45,  1           // InterfaceMethod org/jboss/weld/annotated/enhanced/EnhancedAnnotatedType.slim:()Lorg/jboss/weld/annotated/slim/SlimAnnotatedType;
      21: invokeinterface #46,  3           // InterfaceMethod org/jboss/weld/injection/spi/InjectionServices.registerInjectionTarget:(Ljavax/enterprise/inject/spi/InjectionTarget;Ljavax/enterprise/inject/spi/AnnotatedType;)V
      26: return

  private org.jboss.weld.injection.producer.BasicInjectionTarget<T> prepareInjectionTarget(org.jboss.weld.injection.producer.BasicInjectionTarget<T>);
    Code:
       0: aload_0
       1: aload_0
       2: aload_0
       3: aload_1
       4: invokespecial #15                 // Method validate:(Ljavax/enterprise/inject/spi/InjectionTarget;)Ljavax/enterprise/inject/spi/InjectionTarget;
       7: checkcast     #47                 // class org/jboss/weld/injection/producer/BasicInjectionTarget
      10: invokespecial #21                 // Method initialize:(Lorg/jboss/weld/injection/producer/BasicInjectionTarget;)Lorg/jboss/weld/injection/producer/BasicInjectionTarget;
      13: invokespecial #22                 // Method postProcess:(Ljavax/enterprise/inject/spi/InjectionTarget;)V
      16: aload_1
      17: areturn
      18: astore_2
      19: new           #18                 // class org/jboss/weld/exceptions/IllegalArgumentException
      22: dup
      23: aload_2
      24: invokespecial #19                 // Method org/jboss/weld/exceptions/IllegalArgumentException."<init>":(Ljava/lang/Throwable;)V
      27: athrow
    Exception table:
       from    to  target type
           0    17    18   Class java/lang/Throwable

  public org.jboss.weld.manager.api.WeldInjectionTarget<T> createNonProducibleInjectionTarget();
    Code:
       0: aload_0
       1: aload_0
       2: getfield      #8                  // Field type:Lorg/jboss/weld/annotated/enhanced/EnhancedAnnotatedType;
       5: aconst_null
       6: aload_0
       7: getfield      #2                  // Field manager:Lorg/jboss/weld/manager/BeanManagerImpl;
      10: invokestatic  #48                 // Method org/jboss/weld/injection/producer/NonProducibleInjectionTarget.create:(Lorg/jboss/weld/annotated/enhanced/EnhancedAnnotatedType;Ljavax/enterprise/inject/spi/Bean;Lorg/jboss/weld/manager/BeanManagerImpl;)Lorg/jboss/weld/injection/producer/NonProducibleInjectionTarget;
      13: invokespecial #42                 // Method prepareInjectionTarget:(Lorg/jboss/weld/injection/producer/BasicInjectionTarget;)Lorg/jboss/weld/injection/producer/BasicInjectionTarget;
      16: areturn

  public javax.enterprise.inject.spi.InjectionTarget createInjectionTarget(javax.enterprise.inject.spi.Bean);
    Code:
       0: aload_0
       1: aload_1
       2: invokevirtual #49                 // Method createInjectionTarget:(Ljavax/enterprise/inject/spi/Bean;)Lorg/jboss/weld/manager/api/WeldInjectionTarget;
       5: areturn
}
