Compiled from "MessageOutputBindings.java"
public class org.graylog2.bindings.MessageOutputBindings extends org.graylog2.plugin.inject.Graylog2Module {
  private static final org.slf4j.Logger LOG;

  private final org.graylog2.Configuration configuration;

  private final org.graylog2.shared.plugins.ChainingClassLoader chainingClassLoader;

  public org.graylog2.bindings.MessageOutputBindings(org.graylog2.Configuration, org.graylog2.shared.plugins.ChainingClassLoader);
    Code:
       0: aload_0
       1: invokespecial #1                  // Method org/graylog2/plugin/inject/Graylog2Module."<init>":()V
       4: aload_0
       5: aload_1
       6: putfield      #2                  // Field configuration:Lorg/graylog2/Configuration;
       9: aload_0
      10: aload_2
      11: putfield      #3                  // Field chainingClassLoader:Lorg/graylog2/shared/plugins/ChainingClassLoader;
      14: return

  protected void configure();
    Code:
       0: aload_0
       1: ldc           #4                  // class org/graylog2/outputs/BlockingBatchedESOutput
       3: invokespecial #5                  // Method getDefaultMessageOutputClass:(Ljava/lang/Class;)Ljava/lang/Class;
       6: astore_1
       7: getstatic     #6                  // Field LOG:Lorg/slf4j/Logger;
      10: ldc           #7                  // String Using default message output class: {}
      12: aload_1
      13: invokevirtual #8                  // Method java/lang/Class.getCanonicalName:()Ljava/lang/String;
      16: invokeinterface #9,  3            // InterfaceMethod org/slf4j/Logger.debug:(Ljava/lang/String;Ljava/lang/Object;)V
      21: aload_0
      22: ldc           #10                 // class org/graylog2/plugin/outputs/MessageOutput
      24: invokevirtual #11                 // Method bind:(Ljava/lang/Class;)Lcom/google/inject/binder/AnnotatedBindingBuilder;
      27: ldc           #12                 // class org/graylog2/outputs/DefaultMessageOutput
      29: invokeinterface #13,  2           // InterfaceMethod com/google/inject/binder/AnnotatedBindingBuilder.annotatedWith:(Ljava/lang/Class;)Lcom/google/inject/binder/LinkedBindingBuilder;
      34: aload_1
      35: invokeinterface #14,  2           // InterfaceMethod com/google/inject/binder/LinkedBindingBuilder.to:(Ljava/lang/Class;)Lcom/google/inject/binder/ScopedBindingBuilder;
      40: getstatic     #15                 // Field com/google/inject/Scopes.SINGLETON:Lcom/google/inject/Scope;
      43: invokeinterface #16,  2           // InterfaceMethod com/google/inject/binder/ScopedBindingBuilder.in:(Lcom/google/inject/Scope;)V
      48: aload_0
      49: invokevirtual #17                 // Method outputsMapBinder:()Lcom/google/inject/multibindings/MapBinder;
      52: astore_2
      53: aload_0
      54: aload_2
      55: ldc           #18                 // class org/graylog2/outputs/GelfOutput
      57: ldc           #19                 // class org/graylog2/outputs/GelfOutput$Factory
      59: invokevirtual #20                 // Method installOutput:(Lcom/google/inject/multibindings/MapBinder;Ljava/lang/Class;Ljava/lang/Class;)V
      62: aload_0
      63: aload_2
      64: ldc           #21                 // class org/graylog2/outputs/LoggingOutput
      66: ldc           #22                 // class org/graylog2/outputs/LoggingOutput$Factory
      68: invokevirtual #20                 // Method installOutput:(Lcom/google/inject/multibindings/MapBinder;Ljava/lang/Class;Ljava/lang/Class;)V
      71: return

  private java.lang.Class<? extends org.graylog2.plugin.outputs.MessageOutput> getDefaultMessageOutputClass(java.lang.Class<? extends org.graylog2.plugin.outputs.MessageOutput>);
    Code:
       0: aload_0
       1: getfield      #2                  // Field configuration:Lorg/graylog2/Configuration;
       4: invokevirtual #23                 // Method org/graylog2/Configuration.getDefaultMessageOutputClass:()Ljava/lang/String;
       7: invokestatic  #24                 // Method com/google/common/base/Strings.isNullOrEmpty:(Ljava/lang/String;)Z
      10: ifeq          15
      13: aload_1
      14: areturn
      15: aload_0
      16: getfield      #3                  // Field chainingClassLoader:Lorg/graylog2/shared/plugins/ChainingClassLoader;
      19: aload_0
      20: getfield      #2                  // Field configuration:Lorg/graylog2/Configuration;
      23: invokevirtual #23                 // Method org/graylog2/Configuration.getDefaultMessageOutputClass:()Ljava/lang/String;
      26: invokevirtual #25                 // Method org/graylog2/shared/plugins/ChainingClassLoader.loadClass:(Ljava/lang/String;)Ljava/lang/Class;
      29: astore_2
      30: ldc           #10                 // class org/graylog2/plugin/outputs/MessageOutput
      32: aload_2
      33: invokevirtual #26                 // Method java/lang/Class.isAssignableFrom:(Ljava/lang/Class;)Z
      36: ifeq          55
      39: getstatic     #6                  // Field LOG:Lorg/slf4j/Logger;
      42: ldc           #27                 // String Using {} as default message output
      44: aload_2
      45: invokevirtual #8                  // Method java/lang/Class.getCanonicalName:()Ljava/lang/String;
      48: invokeinterface #28,  3           // InterfaceMethod org/slf4j/Logger.info:(Ljava/lang/String;Ljava/lang/Object;)V
      53: aload_2
      54: areturn
      55: getstatic     #6                  // Field LOG:Lorg/slf4j/Logger;
      58: ldc           #29                 // String Class \"{}\" is not a subclass of \"{}\". Using \"{}\" as default message output
      60: iconst_3
      61: anewarray     #30                 // class java/lang/Object
      64: dup
      65: iconst_0
      66: aload_0
      67: getfield      #2                  // Field configuration:Lorg/graylog2/Configuration;
      70: invokevirtual #23                 // Method org/graylog2/Configuration.getDefaultMessageOutputClass:()Ljava/lang/String;
      73: aastore
      74: dup
      75: iconst_1
      76: ldc           #10                 // class org/graylog2/plugin/outputs/MessageOutput
      78: invokevirtual #8                  // Method java/lang/Class.getCanonicalName:()Ljava/lang/String;
      81: aastore
      82: dup
      83: iconst_2
      84: aload_1
      85: invokevirtual #8                  // Method java/lang/Class.getCanonicalName:()Ljava/lang/String;
      88: aastore
      89: invokeinterface #31,  3           // InterfaceMethod org/slf4j/Logger.warn:(Ljava/lang/String;[Ljava/lang/Object;)V
      94: aload_1
      95: areturn
      96: astore_2
      97: getstatic     #6                  // Field LOG:Lorg/slf4j/Logger;
     100: ldc           #33                 // String Unable to find default message output class \"{}\", using \"{}\"
     102: aload_0
     103: getfield      #2                  // Field configuration:Lorg/graylog2/Configuration;
     106: invokevirtual #23                 // Method org/graylog2/Configuration.getDefaultMessageOutputClass:()Ljava/lang/String;
     109: aload_1
     110: invokevirtual #8                  // Method java/lang/Class.getCanonicalName:()Ljava/lang/String;
     113: invokeinterface #34,  4           // InterfaceMethod org/slf4j/Logger.warn:(Ljava/lang/String;Ljava/lang/Object;Ljava/lang/Object;)V
     118: aload_1
     119: areturn
    Exception table:
       from    to  target type
          15    54    96   Class java/lang/ClassNotFoundException
          55    95    96   Class java/lang/ClassNotFoundException

  static {};
    Code:
       0: ldc           #35                 // class org/graylog2/bindings/MessageOutputBindings
       2: invokestatic  #36                 // Method org/slf4j/LoggerFactory.getLogger:(Ljava/lang/Class;)Lorg/slf4j/Logger;
       5: putstatic     #6                  // Field LOG:Lorg/slf4j/Logger;
       8: return
}
