Compiled from "ServerBindings.java"
public class org.graylog2.bindings.ServerBindings extends org.graylog2.plugin.inject.Graylog2Module {
  private final org.graylog2.Configuration configuration;

  public org.graylog2.bindings.ServerBindings(org.graylog2.Configuration);
    Code:
       0: aload_0
       1: invokespecial #1                  // Method org/graylog2/plugin/inject/Graylog2Module."<init>":()V
       4: aload_0
       5: aload_1
       6: putfield      #2                  // Field configuration:Lorg/graylog2/Configuration;
       9: return

  protected void configure();
    Code:
       0: aload_0
       1: invokespecial #3                  // Method bindInterfaces:()V
       4: aload_0
       5: invokespecial #4                  // Method bindSingletons:()V
       8: aload_0
       9: invokespecial #5                  // Method bindProviders:()V
      12: aload_0
      13: invokespecial #6                  // Method bindFactoryModules:()V
      16: aload_0
      17: invokespecial #7                  // Method bindDynamicFeatures:()V
      20: aload_0
      21: invokespecial #8                  // Method bindExceptionMappers:()V
      24: aload_0
      25: invokespecial #9                  // Method bindAdditionalJerseyComponents:()V
      28: aload_0
      29: invokespecial #10                 // Method bindEventBusListeners:()V
      32: aload_0
      33: new           #11                 // class org/graylog2/security/realm/AuthenticatingRealmModule
      36: dup
      37: invokespecial #12                 // Method org/graylog2/security/realm/AuthenticatingRealmModule."<init>":()V
      40: invokevirtual #13                 // Method install:(Lcom/google/inject/Module;)V
      43: aload_0
      44: invokespecial #14                 // Method bindSearchResponseDecorators:()V
      47: aload_0
      48: new           #15                 // class org/graylog2/grok/GrokModule
      51: dup
      52: invokespecial #16                 // Method org/graylog2/grok/GrokModule."<init>":()V
      55: invokevirtual #13                 // Method install:(Lcom/google/inject/Module;)V
      58: aload_0
      59: new           #17                 // class org/graylog2/lookup/LookupModule
      62: dup
      63: invokespecial #18                 // Method org/graylog2/lookup/LookupModule."<init>":()V
      66: invokevirtual #13                 // Method install:(Lcom/google/inject/Module;)V
      69: aload_0
      70: new           #19                 // class org/graylog2/indexer/fieldtypes/FieldTypesModule
      73: dup
      74: invokespecial #20                 // Method org/graylog2/indexer/fieldtypes/FieldTypesModule."<init>":()V
      77: invokevirtual #13                 // Method install:(Lcom/google/inject/Module;)V
      80: return

  private void bindProviders();
    Code:
       0: aload_0
       1: ldc           #21                 // class org/graylog2/events/ClusterEventBus
       3: invokevirtual #22                 // Method bind:(Ljava/lang/Class;)Lcom/google/inject/binder/AnnotatedBindingBuilder;
       6: ldc           #23                 // class org/graylog2/bindings/providers/ClusterEventBusProvider
       8: invokeinterface #24,  2           // InterfaceMethod com/google/inject/binder/AnnotatedBindingBuilder.toProvider:(Ljava/lang/Class;)Lcom/google/inject/binder/ScopedBindingBuilder;
      13: invokeinterface #25,  1           // InterfaceMethod com/google/inject/binder/ScopedBindingBuilder.asEagerSingleton:()V
      18: return

  private void bindFactoryModules();
    Code:
       0: aload_0
       1: new           #26                 // class com/google/inject/assistedinject/FactoryModuleBuilder
       4: dup
       5: invokespecial #27                 // Method com/google/inject/assistedinject/FactoryModuleBuilder."<init>":()V
       8: ldc           #28                 // class org/graylog2/indexer/ranges/RebuildIndexRangesJob$Factory
      10: invokevirtual #29                 // Method com/google/inject/assistedinject/FactoryModuleBuilder.build:(Ljava/lang/Class;)Lcom/google/inject/Module;
      13: invokevirtual #13                 // Method install:(Lcom/google/inject/Module;)V
      16: aload_0
      17: new           #26                 // class com/google/inject/assistedinject/FactoryModuleBuilder
      20: dup
      21: invokespecial #27                 // Method com/google/inject/assistedinject/FactoryModuleBuilder."<init>":()V
      24: ldc           #30                 // class org/graylog2/indexer/indices/jobs/OptimizeIndexJob$Factory
      26: invokevirtual #29                 // Method com/google/inject/assistedinject/FactoryModuleBuilder.build:(Ljava/lang/Class;)Lcom/google/inject/Module;
      29: invokevirtual #13                 // Method install:(Lcom/google/inject/Module;)V
      32: aload_0
      33: new           #26                 // class com/google/inject/assistedinject/FactoryModuleBuilder
      36: dup
      37: invokespecial #27                 // Method com/google/inject/assistedinject/FactoryModuleBuilder."<init>":()V
      40: ldc           #31                 // class org/graylog2/indexer/SetIndexReadOnlyJob$Factory
      42: invokevirtual #29                 // Method com/google/inject/assistedinject/FactoryModuleBuilder.build:(Ljava/lang/Class;)Lcom/google/inject/Module;
      45: invokevirtual #13                 // Method install:(Lcom/google/inject/Module;)V
      48: aload_0
      49: new           #26                 // class com/google/inject/assistedinject/FactoryModuleBuilder
      52: dup
      53: invokespecial #27                 // Method com/google/inject/assistedinject/FactoryModuleBuilder."<init>":()V
      56: ldc           #32                 // class org/graylog2/indexer/indices/jobs/IndexSetCleanupJob$Factory
      58: invokevirtual #29                 // Method com/google/inject/assistedinject/FactoryModuleBuilder.build:(Ljava/lang/Class;)Lcom/google/inject/Module;
      61: invokevirtual #13                 // Method install:(Lcom/google/inject/Module;)V
      64: aload_0
      65: new           #26                 // class com/google/inject/assistedinject/FactoryModuleBuilder
      68: dup
      69: invokespecial #27                 // Method com/google/inject/assistedinject/FactoryModuleBuilder."<init>":()V
      72: ldc           #33                 // class org/graylog2/indexer/ranges/CreateNewSingleIndexRangeJob$Factory
      74: invokevirtual #29                 // Method com/google/inject/assistedinject/FactoryModuleBuilder.build:(Ljava/lang/Class;)Lcom/google/inject/Module;
      77: invokevirtual #13                 // Method install:(Lcom/google/inject/Module;)V
      80: aload_0
      81: new           #26                 // class com/google/inject/assistedinject/FactoryModuleBuilder
      84: dup
      85: invokespecial #27                 // Method com/google/inject/assistedinject/FactoryModuleBuilder."<init>":()V
      88: ldc           #34                 // class org/graylog2/indexer/healing/FixDeflectorByDeleteJob$Factory
      90: invokevirtual #29                 // Method com/google/inject/assistedinject/FactoryModuleBuilder.build:(Ljava/lang/Class;)Lcom/google/inject/Module;
      93: invokevirtual #13                 // Method install:(Lcom/google/inject/Module;)V
      96: aload_0
      97: new           #26                 // class com/google/inject/assistedinject/FactoryModuleBuilder
     100: dup
     101: invokespecial #27                 // Method com/google/inject/assistedinject/FactoryModuleBuilder."<init>":()V
     104: ldc           #35                 // class org/graylog2/indexer/healing/FixDeflectorByMoveJob$Factory
     106: invokevirtual #29                 // Method com/google/inject/assistedinject/FactoryModuleBuilder.build:(Ljava/lang/Class;)Lcom/google/inject/Module;
     109: invokevirtual #13                 // Method install:(Lcom/google/inject/Module;)V
     112: aload_0
     113: new           #26                 // class com/google/inject/assistedinject/FactoryModuleBuilder
     116: dup
     117: invokespecial #27                 // Method com/google/inject/assistedinject/FactoryModuleBuilder."<init>":()V
     120: ldc           #36                 // class org/graylog2/indexer/indices/jobs/SetIndexReadOnlyAndCalculateRangeJob$Factory
     122: invokevirtual #29                 // Method com/google/inject/assistedinject/FactoryModuleBuilder.build:(Ljava/lang/Class;)Lcom/google/inject/Module;
     125: invokevirtual #13                 // Method install:(Lcom/google/inject/Module;)V
     128: aload_0
     129: new           #26                 // class com/google/inject/assistedinject/FactoryModuleBuilder
     132: dup
     133: invokespecial #27                 // Method com/google/inject/assistedinject/FactoryModuleBuilder."<init>":()V
     136: ldc           #37                 // class org/graylog2/security/ldap/LdapSettingsImpl$Factory
     138: invokevirtual #29                 // Method com/google/inject/assistedinject/FactoryModuleBuilder.build:(Ljava/lang/Class;)Lcom/google/inject/Module;
     141: invokevirtual #13                 // Method install:(Lcom/google/inject/Module;)V
     144: aload_0
     145: new           #26                 // class com/google/inject/assistedinject/FactoryModuleBuilder
     148: dup
     149: invokespecial #27                 // Method com/google/inject/assistedinject/FactoryModuleBuilder."<init>":()V
     152: ldc           #38                 // class org/graylog2/dashboards/widgets/WidgetCacheTime$Factory
     154: invokevirtual #29                 // Method com/google/inject/assistedinject/FactoryModuleBuilder.build:(Ljava/lang/Class;)Lcom/google/inject/Module;
     157: invokevirtual #13                 // Method install:(Lcom/google/inject/Module;)V
     160: aload_0
     161: new           #26                 // class com/google/inject/assistedinject/FactoryModuleBuilder
     164: dup
     165: invokespecial #27                 // Method com/google/inject/assistedinject/FactoryModuleBuilder."<init>":()V
     168: ldc           #39                 // class org/graylog2/users/UserImpl$Factory
     170: invokevirtual #29                 // Method com/google/inject/assistedinject/FactoryModuleBuilder.build:(Ljava/lang/Class;)Lcom/google/inject/Module;
     173: invokevirtual #13                 // Method install:(Lcom/google/inject/Module;)V
     176: aload_0
     177: new           #26                 // class com/google/inject/assistedinject/FactoryModuleBuilder
     180: dup
     181: invokespecial #27                 // Method com/google/inject/assistedinject/FactoryModuleBuilder."<init>":()V
     184: ldc           #40                 // class org/graylog2/alerts/EmailRecipients$Factory
     186: invokevirtual #29                 // Method com/google/inject/assistedinject/FactoryModuleBuilder.build:(Ljava/lang/Class;)Lcom/google/inject/Module;
     189: invokevirtual #13                 // Method install:(Lcom/google/inject/Module;)V
     192: aload_0
     193: new           #26                 // class com/google/inject/assistedinject/FactoryModuleBuilder
     196: dup
     197: invokespecial #27                 // Method com/google/inject/assistedinject/FactoryModuleBuilder."<init>":()V
     200: ldc           #41                 // class org/graylog2/shared/buffers/processors/ProcessBufferProcessor$Factory
     202: invokevirtual #29                 // Method com/google/inject/assistedinject/FactoryModuleBuilder.build:(Ljava/lang/Class;)Lcom/google/inject/Module;
     205: invokevirtual #13                 // Method install:(Lcom/google/inject/Module;)V
     208: aload_0
     209: ldc           #42                 // class org/graylog2/plugin/streams/Stream
     211: invokevirtual #22                 // Method bind:(Ljava/lang/Class;)Lcom/google/inject/binder/AnnotatedBindingBuilder;
     214: ldc           #43                 // class org/graylog2/plugin/streams/DefaultStream
     216: invokeinterface #44,  2           // InterfaceMethod com/google/inject/binder/AnnotatedBindingBuilder.annotatedWith:(Ljava/lang/Class;)Lcom/google/inject/binder/LinkedBindingBuilder;
     221: ldc           #45                 // class org/graylog2/bindings/providers/DefaultStreamProvider
     223: invokeinterface #46,  2           // InterfaceMethod com/google/inject/binder/LinkedBindingBuilder.toProvider:(Ljava/lang/Class;)Lcom/google/inject/binder/ScopedBindingBuilder;
     228: pop
     229: aload_0
     230: ldc           #47                 // class org/graylog2/streams/DefaultStreamChangeHandler
     232: invokevirtual #22                 // Method bind:(Ljava/lang/Class;)Lcom/google/inject/binder/AnnotatedBindingBuilder;
     235: invokeinterface #48,  1           // InterfaceMethod com/google/inject/binder/AnnotatedBindingBuilder.asEagerSingleton:()V
     240: return

  private void bindSingletons();
    Code:
       0: aload_0
       1: ldc           #49                 // class org/graylog2/database/MongoConnection
       3: invokevirtual #22                 // Method bind:(Ljava/lang/Class;)Lcom/google/inject/binder/AnnotatedBindingBuilder;
       6: ldc           #50                 // class org/graylog2/bindings/providers/MongoConnectionProvider
       8: invokeinterface #24,  2           // InterfaceMethod com/google/inject/binder/AnnotatedBindingBuilder.toProvider:(Ljava/lang/Class;)Lcom/google/inject/binder/ScopedBindingBuilder;
      13: pop
      14: aload_0
      15: getfield      #2                  // Field configuration:Lorg/graylog2/Configuration;
      18: invokevirtual #51                 // Method org/graylog2/Configuration.isMessageJournalEnabled:()Z
      21: ifeq          49
      24: aload_0
      25: new           #52                 // class org/graylog2/shared/journal/KafkaJournalModule
      28: dup
      29: invokespecial #53                 // Method org/graylog2/shared/journal/KafkaJournalModule."<init>":()V
      32: invokevirtual #13                 // Method install:(Lcom/google/inject/Module;)V
      35: aload_0
      36: new           #54                 // class org/graylog2/shared/journal/JournalReaderModule
      39: dup
      40: invokespecial #55                 // Method org/graylog2/shared/journal/JournalReaderModule."<init>":()V
      43: invokevirtual #13                 // Method install:(Lcom/google/inject/Module;)V
      46: goto          60
      49: aload_0
      50: new           #56                 // class org/graylog2/shared/journal/NoopJournalModule
      53: dup
      54: invokespecial #57                 // Method org/graylog2/shared/journal/NoopJournalModule."<init>":()V
      57: invokevirtual #13                 // Method install:(Lcom/google/inject/Module;)V
      60: aload_0
      61: ldc           #58                 // class org/graylog2/system/jobs/SystemJobManager
      63: invokevirtual #22                 // Method bind:(Ljava/lang/Class;)Lcom/google/inject/binder/AnnotatedBindingBuilder;
      66: ldc           #59                 // class org/graylog2/bindings/providers/SystemJobManagerProvider
      68: invokeinterface #24,  2           // InterfaceMethod com/google/inject/binder/AnnotatedBindingBuilder.toProvider:(Ljava/lang/Class;)Lcom/google/inject/binder/ScopedBindingBuilder;
      73: pop
      74: aload_0
      75: ldc           #60                 // class org/graylog2/security/ldap/LdapConnector
      77: invokevirtual #22                 // Method bind:(Ljava/lang/Class;)Lcom/google/inject/binder/AnnotatedBindingBuilder;
      80: getstatic     #61                 // Field com/google/inject/Scopes.SINGLETON:Lcom/google/inject/Scope;
      83: invokeinterface #62,  2           // InterfaceMethod com/google/inject/binder/AnnotatedBindingBuilder.in:(Lcom/google/inject/Scope;)V
      88: aload_0
      89: ldc           #63                 // class org/graylog2/security/realm/LdapUserAuthenticator
      91: invokevirtual #22                 // Method bind:(Ljava/lang/Class;)Lcom/google/inject/binder/AnnotatedBindingBuilder;
      94: getstatic     #61                 // Field com/google/inject/Scopes.SINGLETON:Lcom/google/inject/Scope;
      97: invokeinterface #62,  2           // InterfaceMethod com/google/inject/binder/AnnotatedBindingBuilder.in:(Lcom/google/inject/Scope;)V
     102: aload_0
     103: ldc           #64                 // class org/apache/shiro/mgt/DefaultSecurityManager
     105: invokevirtual #22                 // Method bind:(Ljava/lang/Class;)Lcom/google/inject/binder/AnnotatedBindingBuilder;
     108: ldc           #65                 // class org/graylog2/bindings/providers/DefaultSecurityManagerProvider
     110: invokeinterface #24,  2           // InterfaceMethod com/google/inject/binder/AnnotatedBindingBuilder.toProvider:(Ljava/lang/Class;)Lcom/google/inject/binder/ScopedBindingBuilder;
     115: invokeinterface #25,  1           // InterfaceMethod com/google/inject/binder/ScopedBindingBuilder.asEagerSingleton:()V
     120: aload_0
     121: ldc           #66                 // class org/graylog2/system/jobs/SystemJobFactory
     123: invokevirtual #22                 // Method bind:(Ljava/lang/Class;)Lcom/google/inject/binder/AnnotatedBindingBuilder;
     126: ldc           #67                 // class org/graylog2/bindings/providers/SystemJobFactoryProvider
     128: invokeinterface #24,  2           // InterfaceMethod com/google/inject/binder/AnnotatedBindingBuilder.toProvider:(Ljava/lang/Class;)Lcom/google/inject/binder/ScopedBindingBuilder;
     133: pop
     134: aload_0
     135: ldc           #68                 // class org/graylog2/system/shutdown/GracefulShutdown
     137: invokevirtual #22                 // Method bind:(Ljava/lang/Class;)Lcom/google/inject/binder/AnnotatedBindingBuilder;
     140: getstatic     #61                 // Field com/google/inject/Scopes.SINGLETON:Lcom/google/inject/Scope;
     143: invokeinterface #62,  2           // InterfaceMethod com/google/inject/binder/AnnotatedBindingBuilder.in:(Lcom/google/inject/Scope;)V
     148: aload_0
     149: ldc           #69                 // class org/graylog2/system/stats/ClusterStatsModule
     151: invokevirtual #22                 // Method bind:(Ljava/lang/Class;)Lcom/google/inject/binder/AnnotatedBindingBuilder;
     154: invokeinterface #48,  1           // InterfaceMethod com/google/inject/binder/AnnotatedBindingBuilder.asEagerSingleton:()V
     159: aload_0
     160: ldc           #70                 // class org/graylog2/plugin/cluster/ClusterConfigService
     162: invokevirtual #22                 // Method bind:(Ljava/lang/Class;)Lcom/google/inject/binder/AnnotatedBindingBuilder;
     165: ldc           #71                 // class org/graylog2/cluster/ClusterConfigServiceImpl
     167: invokeinterface #72,  2           // InterfaceMethod com/google/inject/binder/AnnotatedBindingBuilder.to:(Ljava/lang/Class;)Lcom/google/inject/binder/ScopedBindingBuilder;
     172: invokeinterface #25,  1           // InterfaceMethod com/google/inject/binder/ScopedBindingBuilder.asEagerSingleton:()V
     177: aload_0
     178: ldc           #73                 // class org/graylog2/grok/GrokPatternRegistry
     180: invokevirtual #22                 // Method bind:(Ljava/lang/Class;)Lcom/google/inject/binder/AnnotatedBindingBuilder;
     183: getstatic     #61                 // Field com/google/inject/Scopes.SINGLETON:Lcom/google/inject/Scope;
     186: invokeinterface #62,  2           // InterfaceMethod com/google/inject/binder/AnnotatedBindingBuilder.in:(Lcom/google/inject/Scope;)V
     191: aload_0
     192: ldc           #74                 // class com/floreysoft/jmte/Engine
     194: invokevirtual #22                 // Method bind:(Ljava/lang/Class;)Lcom/google/inject/binder/AnnotatedBindingBuilder;
     197: invokestatic  #75                 // Method com/floreysoft/jmte/Engine.createEngine:()Lcom/floreysoft/jmte/Engine;
     200: invokeinterface #76,  2           // InterfaceMethod com/google/inject/binder/AnnotatedBindingBuilder.toInstance:(Ljava/lang/Object;)V
     205: aload_0
     206: ldc           #77                 // class org/glassfish/grizzly/http/server/ErrorPageGenerator
     208: invokevirtual #22                 // Method bind:(Ljava/lang/Class;)Lcom/google/inject/binder/AnnotatedBindingBuilder;
     211: ldc           #78                 // class org/graylog2/rest/GraylogErrorPageGenerator
     213: invokeinterface #72,  2           // InterfaceMethod com/google/inject/binder/AnnotatedBindingBuilder.to:(Ljava/lang/Class;)Lcom/google/inject/binder/ScopedBindingBuilder;
     218: invokeinterface #25,  1           // InterfaceMethod com/google/inject/binder/ScopedBindingBuilder.asEagerSingleton:()V
     223: aload_0
     224: ldc           #79                 // String org.graylog2.rest.resources
     226: invokevirtual #80                 // Method registerRestControllerPackage:(Ljava/lang/String;)V
     229: aload_0
     230: ldc           #81                 // String org.graylog2.shared.rest.resources
     232: invokevirtual #80                 // Method registerRestControllerPackage:(Ljava/lang/String;)V
     235: return

  private void bindInterfaces();
    Code:
       0: aload_0
       1: ldc           #82                 // class org/graylog2/alerts/AlertSender
       3: invokevirtual #22                 // Method bind:(Ljava/lang/Class;)Lcom/google/inject/binder/AnnotatedBindingBuilder;
       6: ldc           #83                 // class org/graylog2/alerts/FormattedEmailAlertSender
       8: invokeinterface #72,  2           // InterfaceMethod com/google/inject/binder/AnnotatedBindingBuilder.to:(Ljava/lang/Class;)Lcom/google/inject/binder/ScopedBindingBuilder;
      13: pop
      14: aload_0
      15: ldc           #84                 // class org/graylog2/streams/StreamRouter
      17: invokevirtual #22                 // Method bind:(Ljava/lang/Class;)Lcom/google/inject/binder/AnnotatedBindingBuilder;
      20: pop
      21: aload_0
      22: new           #26                 // class com/google/inject/assistedinject/FactoryModuleBuilder
      25: dup
      26: invokespecial #27                 // Method com/google/inject/assistedinject/FactoryModuleBuilder."<init>":()V
      29: ldc           #85                 // class org/graylog2/streams/StreamRouterEngine
      31: ldc           #85                 // class org/graylog2/streams/StreamRouterEngine
      33: invokevirtual #86                 // Method com/google/inject/assistedinject/FactoryModuleBuilder.implement:(Ljava/lang/Class;Ljava/lang/Class;)Lcom/google/inject/assistedinject/FactoryModuleBuilder;
      36: ldc           #87                 // class org/graylog2/streams/StreamRouterEngine$Factory
      38: invokevirtual #29                 // Method com/google/inject/assistedinject/FactoryModuleBuilder.build:(Ljava/lang/Class;)Lcom/google/inject/Module;
      41: invokevirtual #13                 // Method install:(Lcom/google/inject/Module;)V
      44: aload_0
      45: ldc           #88                 // class org/graylog2/shared/system/activities/ActivityWriter
      47: invokevirtual #22                 // Method bind:(Ljava/lang/Class;)Lcom/google/inject/binder/AnnotatedBindingBuilder;
      50: ldc           #89                 // class org/graylog2/system/activities/SystemMessageActivityWriter
      52: invokeinterface #72,  2           // InterfaceMethod com/google/inject/binder/AnnotatedBindingBuilder.to:(Ljava/lang/Class;)Lcom/google/inject/binder/ScopedBindingBuilder;
      57: pop
      58: aload_0
      59: ldc           #90                 // class org/graylog2/shared/inputs/PersistedInputs
      61: invokevirtual #22                 // Method bind:(Ljava/lang/Class;)Lcom/google/inject/binder/AnnotatedBindingBuilder;
      64: ldc           #91                 // class org/graylog2/inputs/PersistedInputsImpl
      66: invokeinterface #72,  2           // InterfaceMethod com/google/inject/binder/AnnotatedBindingBuilder.to:(Ljava/lang/Class;)Lcom/google/inject/binder/ScopedBindingBuilder;
      71: pop
      72: aload_0
      73: ldc           #92                 // class org/graylog2/users/RoleService
      75: invokevirtual #22                 // Method bind:(Ljava/lang/Class;)Lcom/google/inject/binder/AnnotatedBindingBuilder;
      78: ldc           #93                 // class org/graylog2/users/RoleServiceImpl
      80: invokeinterface #72,  2           // InterfaceMethod com/google/inject/binder/AnnotatedBindingBuilder.to:(Ljava/lang/Class;)Lcom/google/inject/binder/ScopedBindingBuilder;
      85: getstatic     #61                 // Field com/google/inject/Scopes.SINGLETON:Lcom/google/inject/Scope;
      88: invokeinterface #94,  2           // InterfaceMethod com/google/inject/binder/ScopedBindingBuilder.in:(Lcom/google/inject/Scope;)V
      93: return

  private void bindDynamicFeatures();
    Code:
       0: aload_0
       1: invokevirtual #95                 // Method jerseyDynamicFeatureBinder:()Lcom/google/inject/multibindings/Multibinder;
       4: astore_1
       5: aload_1
       6: invokevirtual #96                 // Method com/google/inject/multibindings/Multibinder.addBinding:()Lcom/google/inject/binder/LinkedBindingBuilder;
       9: ldc           #97                 // class org/graylog2/shared/metrics/jersey2/MetricsDynamicBinding
      11: invokeinterface #98,  2           // InterfaceMethod com/google/inject/binder/LinkedBindingBuilder.toInstance:(Ljava/lang/Object;)V
      16: aload_1
      17: invokevirtual #96                 // Method com/google/inject/multibindings/Multibinder.addBinding:()Lcom/google/inject/binder/LinkedBindingBuilder;
      20: ldc           #99                 // class org/graylog2/shared/security/RestrictToMasterFeature
      22: invokeinterface #98,  2           // InterfaceMethod com/google/inject/binder/LinkedBindingBuilder.toInstance:(Ljava/lang/Object;)V
      27: return

  private void bindExceptionMappers();
    Code:
       0: aload_0
       1: invokevirtual #100                // Method jerseyExceptionMapperBinder:()Lcom/google/inject/multibindings/Multibinder;
       4: astore_1
       5: aload_1
       6: invokevirtual #96                 // Method com/google/inject/multibindings/Multibinder.addBinding:()Lcom/google/inject/binder/LinkedBindingBuilder;
       9: ldc           #101                // class org/graylog2/rest/NotFoundExceptionMapper
      11: invokeinterface #98,  2           // InterfaceMethod com/google/inject/binder/LinkedBindingBuilder.toInstance:(Ljava/lang/Object;)V
      16: aload_1
      17: invokevirtual #96                 // Method com/google/inject/multibindings/Multibinder.addBinding:()Lcom/google/inject/binder/LinkedBindingBuilder;
      20: ldc           #102                // class org/graylog2/rest/ValidationExceptionMapper
      22: invokeinterface #98,  2           // InterfaceMethod com/google/inject/binder/LinkedBindingBuilder.toInstance:(Ljava/lang/Object;)V
      27: aload_1
      28: invokevirtual #96                 // Method com/google/inject/multibindings/Multibinder.addBinding:()Lcom/google/inject/binder/LinkedBindingBuilder;
      31: ldc           #103                // class org/graylog2/rest/ElasticsearchExceptionMapper
      33: invokeinterface #98,  2           // InterfaceMethod com/google/inject/binder/LinkedBindingBuilder.toInstance:(Ljava/lang/Object;)V
      38: aload_1
      39: invokevirtual #96                 // Method com/google/inject/multibindings/Multibinder.addBinding:()Lcom/google/inject/binder/LinkedBindingBuilder;
      42: ldc           #104                // class org/graylog2/rest/QueryParsingExceptionMapper
      44: invokeinterface #98,  2           // InterfaceMethod com/google/inject/binder/LinkedBindingBuilder.toInstance:(Ljava/lang/Object;)V
      49: return

  private void bindAdditionalJerseyComponents();
    Code:
       0: aload_0
       1: invokevirtual #105                // Method jerseyAdditionalComponentsBinder:()Lcom/google/inject/multibindings/Multibinder;
       4: invokevirtual #96                 // Method com/google/inject/multibindings/Multibinder.addBinding:()Lcom/google/inject/binder/LinkedBindingBuilder;
       7: ldc           #106                // class org/graylog2/rest/ScrollChunkWriter
       9: invokeinterface #98,  2           // InterfaceMethod com/google/inject/binder/LinkedBindingBuilder.toInstance:(Ljava/lang/Object;)V
      14: aload_0
      15: invokevirtual #105                // Method jerseyAdditionalComponentsBinder:()Lcom/google/inject/multibindings/Multibinder;
      18: invokevirtual #96                 // Method com/google/inject/multibindings/Multibinder.addBinding:()Lcom/google/inject/binder/LinkedBindingBuilder;
      21: ldc           #107                // class org/graylog2/rest/GenericErrorCsvWriter
      23: invokeinterface #98,  2           // InterfaceMethod com/google/inject/binder/LinkedBindingBuilder.toInstance:(Ljava/lang/Object;)V
      28: return

  private void bindEventBusListeners();
    Code:
       0: aload_0
       1: ldc           #108                // class org/graylog2/inputs/InputStateListener
       3: invokevirtual #22                 // Method bind:(Ljava/lang/Class;)Lcom/google/inject/binder/AnnotatedBindingBuilder;
       6: invokeinterface #48,  1           // InterfaceMethod com/google/inject/binder/AnnotatedBindingBuilder.asEagerSingleton:()V
      11: aload_0
      12: ldc           #109                // class org/graylog2/inputs/InputEventListener
      14: invokevirtual #22                 // Method bind:(Ljava/lang/Class;)Lcom/google/inject/binder/AnnotatedBindingBuilder;
      17: invokeinterface #48,  1           // InterfaceMethod com/google/inject/binder/AnnotatedBindingBuilder.asEagerSingleton:()V
      22: aload_0
      23: ldc           #110                // class org/graylog2/system/debug/LocalDebugEventListener
      25: invokevirtual #22                 // Method bind:(Ljava/lang/Class;)Lcom/google/inject/binder/AnnotatedBindingBuilder;
      28: invokeinterface #48,  1           // InterfaceMethod com/google/inject/binder/AnnotatedBindingBuilder.asEagerSingleton:()V
      33: aload_0
      34: ldc           #111                // class org/graylog2/system/debug/ClusterDebugEventListener
      36: invokevirtual #22                 // Method bind:(Ljava/lang/Class;)Lcom/google/inject/binder/AnnotatedBindingBuilder;
      39: invokeinterface #48,  1           // InterfaceMethod com/google/inject/binder/AnnotatedBindingBuilder.asEagerSingleton:()V
      44: aload_0
      45: ldc           #112                // class org/graylog2/users/StartPageCleanupListener
      47: invokevirtual #22                 // Method bind:(Ljava/lang/Class;)Lcom/google/inject/binder/AnnotatedBindingBuilder;
      50: invokeinterface #48,  1           // InterfaceMethod com/google/inject/binder/AnnotatedBindingBuilder.asEagerSingleton:()V
      55: aload_0
      56: ldc           #113                // class org/graylog2/dashboards/widgets/WidgetEventsListener
      58: invokevirtual #22                 // Method bind:(Ljava/lang/Class;)Lcom/google/inject/binder/AnnotatedBindingBuilder;
      61: invokeinterface #48,  1           // InterfaceMethod com/google/inject/binder/AnnotatedBindingBuilder.asEagerSingleton:()V
      66: aload_0
      67: ldc           #114                // class org/graylog2/users/UserPermissionsCleanupListener
      69: invokevirtual #22                 // Method bind:(Ljava/lang/Class;)Lcom/google/inject/binder/AnnotatedBindingBuilder;
      72: invokeinterface #48,  1           // InterfaceMethod com/google/inject/binder/AnnotatedBindingBuilder.asEagerSingleton:()V
      77: return

  private void bindSearchResponseDecorators();
    Code:
       0: aload_0
       1: invokevirtual #115                // Method searchResponseDecoratorBinder:()Lcom/google/inject/multibindings/MapBinder;
       4: pop
       5: return
}
