Compiled from "AssignorConfiguration.java"
public class org.apache.kafka.streams.processor.internals.assignment.AssignorConfiguration$AssignmentConfigs {
  public final long acceptableRecoveryLag;

  public final int maxWarmupReplicas;

  public final int numStandbyReplicas;

  public final long probingRebalanceIntervalMs;

  private org.apache.kafka.streams.processor.internals.assignment.AssignorConfiguration$AssignmentConfigs(org.apache.kafka.streams.StreamsConfig);
    Code:
       0: aload_0
       1: invokespecial #2                  // Method java/lang/Object."<init>":()V
       4: aload_0
       5: aload_1
       6: ldc           #4                  // String acceptable.recovery.lag
       8: invokevirtual #5                  // Method org/apache/kafka/streams/StreamsConfig.getLong:(Ljava/lang/String;)Ljava/lang/Long;
      11: invokevirtual #6                  // Method java/lang/Long.longValue:()J
      14: putfield      #7                  // Field acceptableRecoveryLag:J
      17: aload_0
      18: aload_1
      19: ldc           #8                  // String max.warmup.replicas
      21: invokevirtual #9                  // Method org/apache/kafka/streams/StreamsConfig.getInt:(Ljava/lang/String;)Ljava/lang/Integer;
      24: invokevirtual #10                 // Method java/lang/Integer.intValue:()I
      27: putfield      #11                 // Field maxWarmupReplicas:I
      30: aload_0
      31: aload_1
      32: ldc           #12                 // String num.standby.replicas
      34: invokevirtual #9                  // Method org/apache/kafka/streams/StreamsConfig.getInt:(Ljava/lang/String;)Ljava/lang/Integer;
      37: invokevirtual #10                 // Method java/lang/Integer.intValue:()I
      40: putfield      #13                 // Field numStandbyReplicas:I
      43: aload_0
      44: aload_1
      45: ldc           #14                 // String probing.rebalance.interval.ms
      47: invokevirtual #5                  // Method org/apache/kafka/streams/StreamsConfig.getLong:(Ljava/lang/String;)Ljava/lang/Long;
      50: invokevirtual #6                  // Method java/lang/Long.longValue:()J
      53: putfield      #15                 // Field probingRebalanceIntervalMs:J
      56: return

  org.apache.kafka.streams.processor.internals.assignment.AssignorConfiguration$AssignmentConfigs(java.lang.Long, java.lang.Integer, java.lang.Integer, java.lang.Long);
    Code:
       0: aload_0
       1: invokespecial #2                  // Method java/lang/Object."<init>":()V
       4: aload_0
       5: ldc           #4                  // String acceptable.recovery.lag
       7: aload_1
       8: invokestatic  #16                 // Method validated:(Ljava/lang/String;Ljava/lang/Object;)Ljava/lang/Object;
      11: checkcast     #17                 // class java/lang/Long
      14: invokevirtual #6                  // Method java/lang/Long.longValue:()J
      17: putfield      #7                  // Field acceptableRecoveryLag:J
      20: aload_0
      21: ldc           #8                  // String max.warmup.replicas
      23: aload_2
      24: invokestatic  #16                 // Method validated:(Ljava/lang/String;Ljava/lang/Object;)Ljava/lang/Object;
      27: checkcast     #18                 // class java/lang/Integer
      30: invokevirtual #10                 // Method java/lang/Integer.intValue:()I
      33: putfield      #11                 // Field maxWarmupReplicas:I
      36: aload_0
      37: ldc           #12                 // String num.standby.replicas
      39: aload_3
      40: invokestatic  #16                 // Method validated:(Ljava/lang/String;Ljava/lang/Object;)Ljava/lang/Object;
      43: checkcast     #18                 // class java/lang/Integer
      46: invokevirtual #10                 // Method java/lang/Integer.intValue:()I
      49: putfield      #13                 // Field numStandbyReplicas:I
      52: aload_0
      53: ldc           #14                 // String probing.rebalance.interval.ms
      55: aload         4
      57: invokestatic  #16                 // Method validated:(Ljava/lang/String;Ljava/lang/Object;)Ljava/lang/Object;
      60: checkcast     #17                 // class java/lang/Long
      63: invokevirtual #6                  // Method java/lang/Long.longValue:()J
      66: putfield      #15                 // Field probingRebalanceIntervalMs:J
      69: return

  private static <T> T validated(java.lang.String, T);
    Code:
       0: invokestatic  #19                 // Method org/apache/kafka/streams/StreamsConfig.configDef:()Lorg/apache/kafka/common/config/ConfigDef;
       3: invokevirtual #20                 // Method org/apache/kafka/common/config/ConfigDef.configKeys:()Ljava/util/Map;
       6: aload_0
       7: invokeinterface #21,  2           // InterfaceMethod java/util/Map.get:(Ljava/lang/Object;)Ljava/lang/Object;
      12: checkcast     #22                 // class org/apache/kafka/common/config/ConfigDef$ConfigKey
      15: getfield      #23                 // Field org/apache/kafka/common/config/ConfigDef$ConfigKey.validator:Lorg/apache/kafka/common/config/ConfigDef$Validator;
      18: astore_2
      19: aload_2
      20: ifnull        31
      23: aload_2
      24: aload_0
      25: aload_1
      26: invokeinterface #24,  3           // InterfaceMethod org/apache/kafka/common/config/ConfigDef$Validator.ensureValid:(Ljava/lang/String;Ljava/lang/Object;)V
      31: aload_1
      32: areturn

  public java.lang.String toString();
    Code:
       0: new           #25                 // class java/lang/StringBuilder
       3: dup
       4: invokespecial #26                 // Method java/lang/StringBuilder."<init>":()V
       7: ldc           #27                 // String AssignmentConfigs{\n  acceptableRecoveryLag=
       9: invokevirtual #28                 // Method java/lang/StringBuilder.append:(Ljava/lang/String;)Ljava/lang/StringBuilder;
      12: aload_0
      13: getfield      #7                  // Field acceptableRecoveryLag:J
      16: invokevirtual #29                 // Method java/lang/StringBuilder.append:(J)Ljava/lang/StringBuilder;
      19: ldc           #30                 // String \n  maxWarmupReplicas=
      21: invokevirtual #28                 // Method java/lang/StringBuilder.append:(Ljava/lang/String;)Ljava/lang/StringBuilder;
      24: aload_0
      25: getfield      #11                 // Field maxWarmupReplicas:I
      28: invokevirtual #31                 // Method java/lang/StringBuilder.append:(I)Ljava/lang/StringBuilder;
      31: ldc           #32                 // String \n  numStandbyReplicas=
      33: invokevirtual #28                 // Method java/lang/StringBuilder.append:(Ljava/lang/String;)Ljava/lang/StringBuilder;
      36: aload_0
      37: getfield      #13                 // Field numStandbyReplicas:I
      40: invokevirtual #31                 // Method java/lang/StringBuilder.append:(I)Ljava/lang/StringBuilder;
      43: ldc           #33                 // String \n  probingRebalanceIntervalMs=
      45: invokevirtual #28                 // Method java/lang/StringBuilder.append:(Ljava/lang/String;)Ljava/lang/StringBuilder;
      48: aload_0
      49: getfield      #15                 // Field probingRebalanceIntervalMs:J
      52: invokevirtual #29                 // Method java/lang/StringBuilder.append:(J)Ljava/lang/StringBuilder;
      55: ldc           #34                 // String \n}
      57: invokevirtual #28                 // Method java/lang/StringBuilder.append:(Ljava/lang/String;)Ljava/lang/StringBuilder;
      60: invokevirtual #35                 // Method java/lang/StringBuilder.toString:()Ljava/lang/String;
      63: areturn

  org.apache.kafka.streams.processor.internals.assignment.AssignorConfiguration$AssignmentConfigs(org.apache.kafka.streams.StreamsConfig, org.apache.kafka.streams.processor.internals.assignment.AssignorConfiguration$1);
    Code:
       0: aload_0
       1: aload_1
       2: invokespecial #1                  // Method "<init>":(Lorg/apache/kafka/streams/StreamsConfig;)V
       5: return
}
