Compiled from "Requirement.java"
public class org.apache.maven.plugin.descriptor.Requirement implements java.lang.Cloneable {
  private final java.lang.String role;

  private final java.lang.String roleHint;

  public org.apache.maven.plugin.descriptor.Requirement(java.lang.String);
    Code:
       0: aload_0
       1: invokespecial #1                  // Method java/lang/Object."<init>":()V
       4: aload_0
       5: aload_1
       6: putfield      #2                  // Field role:Ljava/lang/String;
       9: aload_0
      10: aconst_null
      11: putfield      #3                  // Field roleHint:Ljava/lang/String;
      14: return

  public org.apache.maven.plugin.descriptor.Requirement(java.lang.String, java.lang.String);
    Code:
       0: aload_0
       1: invokespecial #1                  // Method java/lang/Object."<init>":()V
       4: aload_0
       5: aload_1
       6: putfield      #2                  // Field role:Ljava/lang/String;
       9: aload_0
      10: aload_2
      11: putfield      #3                  // Field roleHint:Ljava/lang/String;
      14: return

  public java.lang.String getRole();
    Code:
       0: aload_0
       1: getfield      #2                  // Field role:Ljava/lang/String;
       4: areturn

  public java.lang.String getRoleHint();
    Code:
       0: aload_0
       1: getfield      #3                  // Field roleHint:Ljava/lang/String;
       4: areturn

  public org.apache.maven.plugin.descriptor.Requirement clone();
    Code:
       0: aload_0
       1: invokespecial #4                  // Method java/lang/Object.clone:()Ljava/lang/Object;
       4: checkcast     #5                  // class org/apache/maven/plugin/descriptor/Requirement
       7: areturn
       8: astore_1
       9: new           #7                  // class java/lang/UnsupportedOperationException
      12: dup
      13: aload_1
      14: invokespecial #8                  // Method java/lang/UnsupportedOperationException."<init>":(Ljava/lang/Throwable;)V
      17: athrow
    Exception table:
       from    to  target type
           0     7     8   Class java/lang/CloneNotSupportedException

  public java.lang.Object clone() throws java.lang.CloneNotSupportedException;
    Code:
       0: aload_0
       1: invokevirtual #9                  // Method clone:()Lorg/apache/maven/plugin/descriptor/Requirement;
       4: areturn
}
