Compiled from "ScannerBase.java"
class net.jangaroo.jooc.ScannerBase$ScanError extends java.lang.RuntimeException {
  private net.jangaroo.jooc.JooSymbol sym;

  public net.jangaroo.jooc.ScannerBase$ScanError(java.lang.String, net.jangaroo.jooc.JooSymbol);
    Code:
       0: aload_0
       1: aload_1
       2: invokespecial #1                  // Method java/lang/RuntimeException."<init>":(Ljava/lang/String;)V
       5: aload_0
       6: aload_2
       7: putfield      #2                  // Field sym:Lnet/jangaroo/jooc/JooSymbol;
      10: return

  public net.jangaroo.jooc.JooSymbol getSym();
    Code:
       0: aload_0
       1: getfield      #2                  // Field sym:Lnet/jangaroo/jooc/JooSymbol;
       4: areturn

  public void setSym(net.jangaroo.jooc.JooSymbol);
    Code:
       0: aload_0
       1: aload_1
       2: putfield      #2                  // Field sym:Lnet/jangaroo/jooc/JooSymbol;
       5: return
}
