Compiled from "ComplexFormat.java"
public class org.apache.commons.math3.complex.ComplexFormat {
  private static final java.lang.String DEFAULT_IMAGINARY_CHARACTER;

  private final java.lang.String imaginaryCharacter;

  private final java.text.NumberFormat imaginaryFormat;

  private final java.text.NumberFormat realFormat;

  public org.apache.commons.math3.complex.ComplexFormat();
    Code:
       0: aload_0
       1: invokespecial #1                  // Method java/lang/Object."<init>":()V
       4: aload_0
       5: ldc           #2                  // String i
       7: putfield      #3                  // Field imaginaryCharacter:Ljava/lang/String;
      10: aload_0
      11: invokestatic  #4                  // Method org/apache/commons/math3/util/CompositeFormat.getDefaultNumberFormat:()Ljava/text/NumberFormat;
      14: putfield      #5                  // Field imaginaryFormat:Ljava/text/NumberFormat;
      17: aload_0
      18: aload_0
      19: getfield      #5                  // Field imaginaryFormat:Ljava/text/NumberFormat;
      22: putfield      #6                  // Field realFormat:Ljava/text/NumberFormat;
      25: return

  public org.apache.commons.math3.complex.ComplexFormat(java.text.NumberFormat) throws org.apache.commons.math3.exception.NullArgumentException;
    Code:
       0: aload_0
       1: invokespecial #1                  // Method java/lang/Object."<init>":()V
       4: aload_1
       5: ifnonnull     23
       8: new           #7                  // class org/apache/commons/math3/exception/NullArgumentException
      11: dup
      12: getstatic     #8                  // Field org/apache/commons/math3/exception/util/LocalizedFormats.IMAGINARY_FORMAT:Lorg/apache/commons/math3/exception/util/LocalizedFormats;
      15: iconst_0
      16: anewarray     #9                  // class java/lang/Object
      19: invokespecial #10                 // Method org/apache/commons/math3/exception/NullArgumentException."<init>":(Lorg/apache/commons/math3/exception/util/Localizable;[Ljava/lang/Object;)V
      22: athrow
      23: aload_0
      24: ldc           #2                  // String i
      26: putfield      #3                  // Field imaginaryCharacter:Ljava/lang/String;
      29: aload_0
      30: aload_1
      31: putfield      #5                  // Field imaginaryFormat:Ljava/text/NumberFormat;
      34: aload_0
      35: aload_1
      36: putfield      #6                  // Field realFormat:Ljava/text/NumberFormat;
      39: return

  public org.apache.commons.math3.complex.ComplexFormat(java.text.NumberFormat, java.text.NumberFormat) throws org.apache.commons.math3.exception.NullArgumentException;
    Code:
       0: aload_0
       1: invokespecial #1                  // Method java/lang/Object."<init>":()V
       4: aload_2
       5: ifnonnull     23
       8: new           #7                  // class org/apache/commons/math3/exception/NullArgumentException
      11: dup
      12: getstatic     #8                  // Field org/apache/commons/math3/exception/util/LocalizedFormats.IMAGINARY_FORMAT:Lorg/apache/commons/math3/exception/util/LocalizedFormats;
      15: iconst_0
      16: anewarray     #9                  // class java/lang/Object
      19: invokespecial #10                 // Method org/apache/commons/math3/exception/NullArgumentException."<init>":(Lorg/apache/commons/math3/exception/util/Localizable;[Ljava/lang/Object;)V
      22: athrow
      23: aload_1
      24: ifnonnull     42
      27: new           #7                  // class org/apache/commons/math3/exception/NullArgumentException
      30: dup
      31: getstatic     #11                 // Field org/apache/commons/math3/exception/util/LocalizedFormats.REAL_FORMAT:Lorg/apache/commons/math3/exception/util/LocalizedFormats;
      34: iconst_0
      35: anewarray     #9                  // class java/lang/Object
      38: invokespecial #10                 // Method org/apache/commons/math3/exception/NullArgumentException."<init>":(Lorg/apache/commons/math3/exception/util/Localizable;[Ljava/lang/Object;)V
      41: athrow
      42: aload_0
      43: ldc           #2                  // String i
      45: putfield      #3                  // Field imaginaryCharacter:Ljava/lang/String;
      48: aload_0
      49: aload_2
      50: putfield      #5                  // Field imaginaryFormat:Ljava/text/NumberFormat;
      53: aload_0
      54: aload_1
      55: putfield      #6                  // Field realFormat:Ljava/text/NumberFormat;
      58: return

  public org.apache.commons.math3.complex.ComplexFormat(java.lang.String) throws org.apache.commons.math3.exception.NullArgumentException, org.apache.commons.math3.exception.NoDataException;
    Code:
       0: aload_0
       1: aload_1
       2: invokestatic  #4                  // Method org/apache/commons/math3/util/CompositeFormat.getDefaultNumberFormat:()Ljava/text/NumberFormat;
       5: invokespecial #12                 // Method "<init>":(Ljava/lang/String;Ljava/text/NumberFormat;)V
       8: return

  public org.apache.commons.math3.complex.ComplexFormat(java.lang.String, java.text.NumberFormat) throws org.apache.commons.math3.exception.NullArgumentException, org.apache.commons.math3.exception.NoDataException;
    Code:
       0: aload_0
       1: aload_1
       2: aload_2
       3: aload_2
       4: invokespecial #13                 // Method "<init>":(Ljava/lang/String;Ljava/text/NumberFormat;Ljava/text/NumberFormat;)V
       7: return

  public org.apache.commons.math3.complex.ComplexFormat(java.lang.String, java.text.NumberFormat, java.text.NumberFormat) throws org.apache.commons.math3.exception.NullArgumentException, org.apache.commons.math3.exception.NoDataException;
    Code:
       0: aload_0
       1: invokespecial #1                  // Method java/lang/Object."<init>":()V
       4: aload_1
       5: ifnonnull     16
       8: new           #7                  // class org/apache/commons/math3/exception/NullArgumentException
      11: dup
      12: invokespecial #14                 // Method org/apache/commons/math3/exception/NullArgumentException."<init>":()V
      15: athrow
      16: aload_1
      17: invokevirtual #15                 // Method java/lang/String.length:()I
      20: ifne          31
      23: new           #16                 // class org/apache/commons/math3/exception/NoDataException
      26: dup
      27: invokespecial #17                 // Method org/apache/commons/math3/exception/NoDataException."<init>":()V
      30: athrow
      31: aload_3
      32: ifnonnull     50
      35: new           #7                  // class org/apache/commons/math3/exception/NullArgumentException
      38: dup
      39: getstatic     #8                  // Field org/apache/commons/math3/exception/util/LocalizedFormats.IMAGINARY_FORMAT:Lorg/apache/commons/math3/exception/util/LocalizedFormats;
      42: iconst_0
      43: anewarray     #9                  // class java/lang/Object
      46: invokespecial #10                 // Method org/apache/commons/math3/exception/NullArgumentException."<init>":(Lorg/apache/commons/math3/exception/util/Localizable;[Ljava/lang/Object;)V
      49: athrow
      50: aload_2
      51: ifnonnull     69
      54: new           #7                  // class org/apache/commons/math3/exception/NullArgumentException
      57: dup
      58: getstatic     #11                 // Field org/apache/commons/math3/exception/util/LocalizedFormats.REAL_FORMAT:Lorg/apache/commons/math3/exception/util/LocalizedFormats;
      61: iconst_0
      62: anewarray     #9                  // class java/lang/Object
      65: invokespecial #10                 // Method org/apache/commons/math3/exception/NullArgumentException."<init>":(Lorg/apache/commons/math3/exception/util/Localizable;[Ljava/lang/Object;)V
      68: athrow
      69: aload_0
      70: aload_1
      71: putfield      #3                  // Field imaginaryCharacter:Ljava/lang/String;
      74: aload_0
      75: aload_3
      76: putfield      #5                  // Field imaginaryFormat:Ljava/text/NumberFormat;
      79: aload_0
      80: aload_2
      81: putfield      #6                  // Field realFormat:Ljava/text/NumberFormat;
      84: return

  public static java.util.Locale[] getAvailableLocales();
    Code:
       0: invokestatic  #18                 // Method java/text/NumberFormat.getAvailableLocales:()[Ljava/util/Locale;
       3: areturn

  public java.lang.String format(org.apache.commons.math3.complex.Complex);
    Code:
       0: aload_0
       1: aload_1
       2: new           #19                 // class java/lang/StringBuffer
       5: dup
       6: invokespecial #20                 // Method java/lang/StringBuffer."<init>":()V
       9: new           #21                 // class java/text/FieldPosition
      12: dup
      13: iconst_0
      14: invokespecial #22                 // Method java/text/FieldPosition."<init>":(I)V
      17: invokevirtual #23                 // Method format:(Lorg/apache/commons/math3/complex/Complex;Ljava/lang/StringBuffer;Ljava/text/FieldPosition;)Ljava/lang/StringBuffer;
      20: invokevirtual #24                 // Method java/lang/StringBuffer.toString:()Ljava/lang/String;
      23: areturn

  public java.lang.String format(java.lang.Double);
    Code:
       0: aload_0
       1: new           #25                 // class org/apache/commons/math3/complex/Complex
       4: dup
       5: aload_1
       6: invokevirtual #26                 // Method java/lang/Double.doubleValue:()D
       9: dconst_0
      10: invokespecial #27                 // Method org/apache/commons/math3/complex/Complex."<init>":(DD)V
      13: new           #19                 // class java/lang/StringBuffer
      16: dup
      17: invokespecial #20                 // Method java/lang/StringBuffer."<init>":()V
      20: new           #21                 // class java/text/FieldPosition
      23: dup
      24: iconst_0
      25: invokespecial #22                 // Method java/text/FieldPosition."<init>":(I)V
      28: invokevirtual #23                 // Method format:(Lorg/apache/commons/math3/complex/Complex;Ljava/lang/StringBuffer;Ljava/text/FieldPosition;)Ljava/lang/StringBuffer;
      31: invokevirtual #24                 // Method java/lang/StringBuffer.toString:()Ljava/lang/String;
      34: areturn

  public java.lang.StringBuffer format(org.apache.commons.math3.complex.Complex, java.lang.StringBuffer, java.text.FieldPosition);
    Code:
       0: aload_3
       1: iconst_0
       2: invokevirtual #28                 // Method java/text/FieldPosition.setBeginIndex:(I)V
       5: aload_3
       6: iconst_0
       7: invokevirtual #29                 // Method java/text/FieldPosition.setEndIndex:(I)V
      10: aload_1
      11: invokevirtual #30                 // Method org/apache/commons/math3/complex/Complex.getReal:()D
      14: dstore        4
      16: dload         4
      18: aload_0
      19: invokevirtual #31                 // Method getRealFormat:()Ljava/text/NumberFormat;
      22: aload_2
      23: aload_3
      24: invokestatic  #32                 // Method org/apache/commons/math3/util/CompositeFormat.formatDouble:(DLjava/text/NumberFormat;Ljava/lang/StringBuffer;Ljava/text/FieldPosition;)Ljava/lang/StringBuffer;
      27: pop
      28: aload_1
      29: invokevirtual #33                 // Method org/apache/commons/math3/complex/Complex.getImaginary:()D
      32: dstore        6
      34: dload         6
      36: dconst_0
      37: dcmpg
      38: ifge          84
      41: aload_2
      42: ldc           #34                 // String  -
      44: invokevirtual #35                 // Method java/lang/StringBuffer.append:(Ljava/lang/String;)Ljava/lang/StringBuffer;
      47: pop
      48: aload_0
      49: dload         6
      51: dneg
      52: new           #19                 // class java/lang/StringBuffer
      55: dup
      56: invokespecial #20                 // Method java/lang/StringBuffer."<init>":()V
      59: aload_3
      60: invokespecial #36                 // Method formatImaginary:(DLjava/lang/StringBuffer;Ljava/text/FieldPosition;)Ljava/lang/StringBuffer;
      63: astore        8
      65: aload_2
      66: aload         8
      68: invokevirtual #37                 // Method java/lang/StringBuffer.append:(Ljava/lang/StringBuffer;)Ljava/lang/StringBuffer;
      71: pop
      72: aload_2
      73: aload_0
      74: invokevirtual #38                 // Method getImaginaryCharacter:()Ljava/lang/String;
      77: invokevirtual #35                 // Method java/lang/StringBuffer.append:(Ljava/lang/String;)Ljava/lang/StringBuffer;
      80: pop
      81: goto          138
      84: dload         6
      86: dconst_0
      87: dcmpl
      88: ifgt          99
      91: dload         6
      93: invokestatic  #39                 // Method java/lang/Double.isNaN:(D)Z
      96: ifeq          138
      99: aload_2
     100: ldc           #40                 // String  +
     102: invokevirtual #35                 // Method java/lang/StringBuffer.append:(Ljava/lang/String;)Ljava/lang/StringBuffer;
     105: pop
     106: aload_0
     107: dload         6
     109: new           #19                 // class java/lang/StringBuffer
     112: dup
     113: invokespecial #20                 // Method java/lang/StringBuffer."<init>":()V
     116: aload_3
     117: invokespecial #36                 // Method formatImaginary:(DLjava/lang/StringBuffer;Ljava/text/FieldPosition;)Ljava/lang/StringBuffer;
     120: astore        8
     122: aload_2
     123: aload         8
     125: invokevirtual #37                 // Method java/lang/StringBuffer.append:(Ljava/lang/StringBuffer;)Ljava/lang/StringBuffer;
     128: pop
     129: aload_2
     130: aload_0
     131: invokevirtual #38                 // Method getImaginaryCharacter:()Ljava/lang/String;
     134: invokevirtual #35                 // Method java/lang/StringBuffer.append:(Ljava/lang/String;)Ljava/lang/StringBuffer;
     137: pop
     138: aload_2
     139: areturn

  private java.lang.StringBuffer formatImaginary(double, java.lang.StringBuffer, java.text.FieldPosition);
    Code:
       0: aload         4
       2: iconst_0
       3: invokevirtual #28                 // Method java/text/FieldPosition.setBeginIndex:(I)V
       6: aload         4
       8: iconst_0
       9: invokevirtual #29                 // Method java/text/FieldPosition.setEndIndex:(I)V
      12: dload_1
      13: aload_0
      14: invokevirtual #41                 // Method getImaginaryFormat:()Ljava/text/NumberFormat;
      17: aload_3
      18: aload         4
      20: invokestatic  #32                 // Method org/apache/commons/math3/util/CompositeFormat.formatDouble:(DLjava/text/NumberFormat;Ljava/lang/StringBuffer;Ljava/text/FieldPosition;)Ljava/lang/StringBuffer;
      23: pop
      24: aload_3
      25: invokevirtual #24                 // Method java/lang/StringBuffer.toString:()Ljava/lang/String;
      28: ldc           #42                 // String 1
      30: invokevirtual #43                 // Method java/lang/String.equals:(Ljava/lang/Object;)Z
      33: ifeq          41
      36: aload_3
      37: iconst_0
      38: invokevirtual #44                 // Method java/lang/StringBuffer.setLength:(I)V
      41: aload_3
      42: areturn

  public java.lang.StringBuffer format(java.lang.Object, java.lang.StringBuffer, java.text.FieldPosition) throws org.apache.commons.math3.exception.MathIllegalArgumentException;
    Code:
       0: aconst_null
       1: astore        4
       3: aload_1
       4: instanceof    #25                 // class org/apache/commons/math3/complex/Complex
       7: ifeq          25
      10: aload_0
      11: aload_1
      12: checkcast     #25                 // class org/apache/commons/math3/complex/Complex
      15: aload_2
      16: aload_3
      17: invokevirtual #23                 // Method format:(Lorg/apache/commons/math3/complex/Complex;Ljava/lang/StringBuffer;Ljava/text/FieldPosition;)Ljava/lang/StringBuffer;
      20: astore        4
      22: goto          83
      25: aload_1
      26: instanceof    #45                 // class java/lang/Number
      29: ifeq          58
      32: aload_0
      33: new           #25                 // class org/apache/commons/math3/complex/Complex
      36: dup
      37: aload_1
      38: checkcast     #45                 // class java/lang/Number
      41: invokevirtual #46                 // Method java/lang/Number.doubleValue:()D
      44: dconst_0
      45: invokespecial #27                 // Method org/apache/commons/math3/complex/Complex."<init>":(DD)V
      48: aload_2
      49: aload_3
      50: invokevirtual #23                 // Method format:(Lorg/apache/commons/math3/complex/Complex;Ljava/lang/StringBuffer;Ljava/text/FieldPosition;)Ljava/lang/StringBuffer;
      53: astore        4
      55: goto          83
      58: new           #47                 // class org/apache/commons/math3/exception/MathIllegalArgumentException
      61: dup
      62: getstatic     #48                 // Field org/apache/commons/math3/exception/util/LocalizedFormats.CANNOT_FORMAT_INSTANCE_AS_COMPLEX:Lorg/apache/commons/math3/exception/util/LocalizedFormats;
      65: iconst_1
      66: anewarray     #9                  // class java/lang/Object
      69: dup
      70: iconst_0
      71: aload_1
      72: invokevirtual #49                 // Method java/lang/Object.getClass:()Ljava/lang/Class;
      75: invokevirtual #50                 // Method java/lang/Class.getName:()Ljava/lang/String;
      78: aastore
      79: invokespecial #51                 // Method org/apache/commons/math3/exception/MathIllegalArgumentException."<init>":(Lorg/apache/commons/math3/exception/util/Localizable;[Ljava/lang/Object;)V
      82: athrow
      83: aload         4
      85: areturn

  public java.lang.String getImaginaryCharacter();
    Code:
       0: aload_0
       1: getfield      #3                  // Field imaginaryCharacter:Ljava/lang/String;
       4: areturn

  public java.text.NumberFormat getImaginaryFormat();
    Code:
       0: aload_0
       1: getfield      #5                  // Field imaginaryFormat:Ljava/text/NumberFormat;
       4: areturn

  public static org.apache.commons.math3.complex.ComplexFormat getInstance();
    Code:
       0: invokestatic  #52                 // Method java/util/Locale.getDefault:()Ljava/util/Locale;
       3: invokestatic  #53                 // Method getInstance:(Ljava/util/Locale;)Lorg/apache/commons/math3/complex/ComplexFormat;
       6: areturn

  public static org.apache.commons.math3.complex.ComplexFormat getInstance(java.util.Locale);
    Code:
       0: aload_0
       1: invokestatic  #54                 // Method org/apache/commons/math3/util/CompositeFormat.getDefaultNumberFormat:(Ljava/util/Locale;)Ljava/text/NumberFormat;
       4: astore_1
       5: new           #55                 // class org/apache/commons/math3/complex/ComplexFormat
       8: dup
       9: aload_1
      10: invokespecial #56                 // Method "<init>":(Ljava/text/NumberFormat;)V
      13: areturn

  public static org.apache.commons.math3.complex.ComplexFormat getInstance(java.lang.String, java.util.Locale) throws org.apache.commons.math3.exception.NullArgumentException, org.apache.commons.math3.exception.NoDataException;
    Code:
       0: aload_1
       1: invokestatic  #54                 // Method org/apache/commons/math3/util/CompositeFormat.getDefaultNumberFormat:(Ljava/util/Locale;)Ljava/text/NumberFormat;
       4: astore_2
       5: new           #55                 // class org/apache/commons/math3/complex/ComplexFormat
       8: dup
       9: aload_0
      10: aload_2
      11: invokespecial #12                 // Method "<init>":(Ljava/lang/String;Ljava/text/NumberFormat;)V
      14: areturn

  public java.text.NumberFormat getRealFormat();
    Code:
       0: aload_0
       1: getfield      #6                  // Field realFormat:Ljava/text/NumberFormat;
       4: areturn

  public org.apache.commons.math3.complex.Complex parse(java.lang.String) throws org.apache.commons.math3.exception.MathParseException;
    Code:
       0: new           #57                 // class java/text/ParsePosition
       3: dup
       4: iconst_0
       5: invokespecial #58                 // Method java/text/ParsePosition."<init>":(I)V
       8: astore_2
       9: aload_0
      10: aload_1
      11: aload_2
      12: invokevirtual #59                 // Method parse:(Ljava/lang/String;Ljava/text/ParsePosition;)Lorg/apache/commons/math3/complex/Complex;
      15: astore_3
      16: aload_2
      17: invokevirtual #60                 // Method java/text/ParsePosition.getIndex:()I
      20: ifne          39
      23: new           #61                 // class org/apache/commons/math3/exception/MathParseException
      26: dup
      27: aload_1
      28: aload_2
      29: invokevirtual #62                 // Method java/text/ParsePosition.getErrorIndex:()I
      32: ldc_w         #25                 // class org/apache/commons/math3/complex/Complex
      35: invokespecial #63                 // Method org/apache/commons/math3/exception/MathParseException."<init>":(Ljava/lang/String;ILjava/lang/Class;)V
      38: athrow
      39: aload_3
      40: areturn

  public org.apache.commons.math3.complex.Complex parse(java.lang.String, java.text.ParsePosition);
    Code:
       0: aload_2
       1: invokevirtual #60                 // Method java/text/ParsePosition.getIndex:()I
       4: istore_3
       5: aload_1
       6: aload_2
       7: invokestatic  #64                 // Method org/apache/commons/math3/util/CompositeFormat.parseAndIgnoreWhitespace:(Ljava/lang/String;Ljava/text/ParsePosition;)V
      10: aload_1
      11: aload_0
      12: invokevirtual #31                 // Method getRealFormat:()Ljava/text/NumberFormat;
      15: aload_2
      16: invokestatic  #65                 // Method org/apache/commons/math3/util/CompositeFormat.parseNumber:(Ljava/lang/String;Ljava/text/NumberFormat;Ljava/text/ParsePosition;)Ljava/lang/Number;
      19: astore        4
      21: aload         4
      23: ifnonnull     33
      26: aload_2
      27: iload_3
      28: invokevirtual #66                 // Method java/text/ParsePosition.setIndex:(I)V
      31: aconst_null
      32: areturn
      33: aload_2
      34: invokevirtual #60                 // Method java/text/ParsePosition.getIndex:()I
      37: istore        5
      39: aload_1
      40: aload_2
      41: invokestatic  #67                 // Method org/apache/commons/math3/util/CompositeFormat.parseNextCharacter:(Ljava/lang/String;Ljava/text/ParsePosition;)C
      44: istore        6
      46: iconst_0
      47: istore        7
      49: iload         6
      51: lookupswitch  { // 3
                     0: 84
                    43: 104
                    45: 98
               default: 110
          }
      84: new           #25                 // class org/apache/commons/math3/complex/Complex
      87: dup
      88: aload         4
      90: invokevirtual #46                 // Method java/lang/Number.doubleValue:()D
      93: dconst_0
      94: invokespecial #27                 // Method org/apache/commons/math3/complex/Complex."<init>":(DD)V
      97: areturn
      98: iconst_m1
      99: istore        7
     101: goto          123
     104: iconst_1
     105: istore        7
     107: goto          123
     110: aload_2
     111: iload_3
     112: invokevirtual #66                 // Method java/text/ParsePosition.setIndex:(I)V
     115: aload_2
     116: iload         5
     118: invokevirtual #68                 // Method java/text/ParsePosition.setErrorIndex:(I)V
     121: aconst_null
     122: areturn
     123: aload_1
     124: aload_2
     125: invokestatic  #64                 // Method org/apache/commons/math3/util/CompositeFormat.parseAndIgnoreWhitespace:(Ljava/lang/String;Ljava/text/ParsePosition;)V
     128: aload_1
     129: aload_0
     130: invokevirtual #31                 // Method getRealFormat:()Ljava/text/NumberFormat;
     133: aload_2
     134: invokestatic  #65                 // Method org/apache/commons/math3/util/CompositeFormat.parseNumber:(Ljava/lang/String;Ljava/text/NumberFormat;Ljava/text/ParsePosition;)Ljava/lang/Number;
     137: astore        8
     139: aload         8
     141: ifnonnull     151
     144: aload_2
     145: iload_3
     146: invokevirtual #66                 // Method java/text/ParsePosition.setIndex:(I)V
     149: aconst_null
     150: areturn
     151: aload_1
     152: aload_0
     153: invokevirtual #38                 // Method getImaginaryCharacter:()Ljava/lang/String;
     156: aload_2
     157: invokestatic  #69                 // Method org/apache/commons/math3/util/CompositeFormat.parseFixedstring:(Ljava/lang/String;Ljava/lang/String;Ljava/text/ParsePosition;)Z
     160: ifne          165
     163: aconst_null
     164: areturn
     165: new           #25                 // class org/apache/commons/math3/complex/Complex
     168: dup
     169: aload         4
     171: invokevirtual #46                 // Method java/lang/Number.doubleValue:()D
     174: aload         8
     176: invokevirtual #46                 // Method java/lang/Number.doubleValue:()D
     179: iload         7
     181: i2d
     182: dmul
     183: invokespecial #27                 // Method org/apache/commons/math3/complex/Complex."<init>":(DD)V
     186: areturn
}
