Compiled from "Version.java"
public class org.hibernate.ogm.cfg.impl.Version {
  public org.hibernate.ogm.cfg.impl.Version();
    Code:
       0: aload_0
       1: invokespecial #10                 // Method java/lang/Object."<init>":()V
       4: return

  public static java.lang.String getVersionString();
    Code:
       0: ldc           #18                 // String 4.0.0.Beta2
       2: areturn

  public static void touch();
    Code:
       0: return

  static {};
    Code:
       0: invokestatic  #26                 // Method org/hibernate/ogm/util/impl/LoggerFactory.make:()Lorg/hibernate/ogm/util/impl/Log;
       3: invokestatic  #29                 // Method org/hibernate/ogm/cfg/impl/Version.getVersionString:()Ljava/lang/String;
       6: invokeinterface #35,  2           // InterfaceMethod org/hibernate/ogm/util/impl/Log.version:(Ljava/lang/String;)V
      11: return
}
