Compiled from "ArrayQueue.java"
public final class org.jboss.threads.ArrayQueue<E> extends java.util.AbstractQueue<E> implements java.util.Queue<E> {
  private final E[] elements;

  private int head;

  private int tail;

  private int modCnt;

  public org.jboss.threads.ArrayQueue(int);
    Code:
       0: aload_0
       1: invokespecial #4                  // Method java/util/AbstractQueue."<init>":()V
       4: aload_0
       5: iload_1
       6: anewarray     #5                  // class java/lang/Object
       9: checkcast     #6                  // class "[Ljava/lang/Object;"
      12: putfield      #2                  // Field elements:[Ljava/lang/Object;
      15: return

  public java.util.Iterator<E> iterator();
    Code:
       0: new           #7                  // class org/jboss/threads/ArrayQueue$1
       3: dup
       4: aload_0
       5: invokespecial #8                  // Method org/jboss/threads/ArrayQueue$1."<init>":(Lorg/jboss/threads/ArrayQueue;)V
       8: areturn

  public boolean isEmpty();
    Code:
       0: aload_0
       1: getfield      #2                  // Field elements:[Ljava/lang/Object;
       4: aload_0
       5: getfield      #1                  // Field tail:I
       8: aaload
       9: ifnonnull     16
      12: iconst_1
      13: goto          17
      16: iconst_0
      17: ireturn

  public int size();
    Code:
       0: aload_0
       1: getfield      #9                  // Field head:I
       4: istore_1
       5: aload_0
       6: getfield      #1                  // Field tail:I
       9: istore_2
      10: aload_0
      11: getfield      #2                  // Field elements:[Ljava/lang/Object;
      14: astore_3
      15: aload_3
      16: iload_2
      17: aaload
      18: ifnonnull     23
      21: iconst_0
      22: ireturn
      23: iload_1
      24: iload_2
      25: if_icmple     32
      28: iload_1
      29: iload_2
      30: isub
      31: ireturn
      32: iload_1
      33: aload_3
      34: arraylength
      35: iadd
      36: iload_2
      37: isub
      38: ireturn

  public boolean offer(E);
    Code:
       0: aload_1
       1: ifnonnull     14
       4: new           #10                 // class java/lang/NullPointerException
       7: dup
       8: ldc           #11                 // String e is null
      10: invokespecial #12                 // Method java/lang/NullPointerException."<init>":(Ljava/lang/String;)V
      13: athrow
      14: aload_0
      15: getfield      #9                  // Field head:I
      18: istore_2
      19: aload_0
      20: getfield      #2                  // Field elements:[Ljava/lang/Object;
      23: astore_3
      24: aload_3
      25: arraylength
      26: istore        4
      28: aload_3
      29: iload_2
      30: aaload
      31: ifnull        36
      34: iconst_0
      35: ireturn
      36: aload_3
      37: iload_2
      38: aload_1
      39: aastore
      40: aload_0
      41: iload_2
      42: iconst_1
      43: iadd
      44: iload         4
      46: irem
      47: putfield      #9                  // Field head:I
      50: aload_0
      51: dup
      52: getfield      #3                  // Field modCnt:I
      55: iconst_1
      56: iadd
      57: putfield      #3                  // Field modCnt:I
      60: iconst_1
      61: ireturn

  public E poll();
    Code:
       0: aload_0
       1: getfield      #1                  // Field tail:I
       4: istore_1
       5: aload_0
       6: getfield      #2                  // Field elements:[Ljava/lang/Object;
       9: astore_2
      10: aload_2
      11: iload_1
      12: aaload
      13: astore_3
      14: aload_3
      15: ifnull        42
      18: aload_0
      19: dup
      20: getfield      #3                  // Field modCnt:I
      23: iconst_1
      24: iadd
      25: putfield      #3                  // Field modCnt:I
      28: aload_2
      29: iload_1
      30: aconst_null
      31: aastore
      32: aload_0
      33: iload_1
      34: iconst_1
      35: iadd
      36: aload_2
      37: arraylength
      38: irem
      39: putfield      #1                  // Field tail:I
      42: aload_3
      43: areturn

  public E peek();
    Code:
       0: aload_0
       1: getfield      #1                  // Field tail:I
       4: istore_1
       5: iload_1
       6: iconst_m1
       7: if_icmpne     14
      10: aconst_null
      11: goto          20
      14: aload_0
      15: getfield      #2                  // Field elements:[Ljava/lang/Object;
      18: iload_1
      19: aaload
      20: areturn

  public void clear();
    Code:
       0: aload_0
       1: getfield      #2                  // Field elements:[Ljava/lang/Object;
       4: aconst_null
       5: invokestatic  #13                 // Method java/util/Arrays.fill:([Ljava/lang/Object;Ljava/lang/Object;)V
       8: aload_0
       9: dup
      10: getfield      #3                  // Field modCnt:I
      13: iconst_1
      14: iadd
      15: putfield      #3                  // Field modCnt:I
      18: aload_0
      19: aload_0
      20: iconst_0
      21: dup_x1
      22: putfield      #9                  // Field head:I
      25: putfield      #1                  // Field tail:I
      28: return

  static int access$000(org.jboss.threads.ArrayQueue);
    Code:
       0: aload_0
       1: getfield      #3                  // Field modCnt:I
       4: ireturn

  static java.lang.Object[] access$100(org.jboss.threads.ArrayQueue);
    Code:
       0: aload_0
       1: getfield      #2                  // Field elements:[Ljava/lang/Object;
       4: areturn

  static int access$200(org.jboss.threads.ArrayQueue);
    Code:
       0: aload_0
       1: getfield      #1                  // Field tail:I
       4: ireturn
}
