Compiled from "DelegatingDirectExecutor.java"
class org.jboss.threads.DelegatingDirectExecutor extends org.jboss.threads.DelegatingExecutor implements org.jboss.threads.DirectExecutor {
  org.jboss.threads.DelegatingDirectExecutor(org.jboss.threads.DirectExecutor);
    Code:
       0: aload_0
       1: aload_1
       2: invokespecial #1                  // Method org/jboss/threads/DelegatingExecutor."<init>":(Ljava/util/concurrent/Executor;)V
       5: return

  protected org.jboss.threads.DirectExecutor getDelegate();
    Code:
       0: aload_0
       1: invokespecial #2                  // Method org/jboss/threads/DelegatingExecutor.getDelegate:()Ljava/util/concurrent/Executor;
       4: checkcast     #3                  // class org/jboss/threads/DirectExecutor
       7: areturn

  protected java.util.concurrent.Executor getDelegate();
    Code:
       0: aload_0
       1: invokevirtual #4                  // Method getDelegate:()Lorg/jboss/threads/DirectExecutor;
       4: areturn
}
