Compiled from "DelegatingDirectBlockingExecutor.java"
class org.jboss.threads.DelegatingDirectBlockingExecutor implements org.jboss.threads.BlockingExecutor,org.jboss.threads.DirectExecutor {
  private final org.jboss.threads.DirectExecutor delegate;

  org.jboss.threads.DelegatingDirectBlockingExecutor(org.jboss.threads.DirectExecutor);
    Code:
       0: aload_0
       1: invokespecial #1                  // Method java/lang/Object."<init>":()V
       4: aload_0
       5: aload_1
       6: putfield      #2                  // Field delegate:Lorg/jboss/threads/DirectExecutor;
       9: return

  public void execute(java.lang.Runnable);
    Code:
       0: aload_0
       1: getfield      #2                  // Field delegate:Lorg/jboss/threads/DirectExecutor;
       4: aload_1
       5: invokeinterface #3,  2            // InterfaceMethod org/jboss/threads/DirectExecutor.execute:(Ljava/lang/Runnable;)V
      10: return

  public void executeNonBlocking(java.lang.Runnable) throws java.util.concurrent.RejectedExecutionException;
    Code:
       0: aload_0
       1: getfield      #2                  // Field delegate:Lorg/jboss/threads/DirectExecutor;
       4: aload_1
       5: invokeinterface #3,  2            // InterfaceMethod org/jboss/threads/DirectExecutor.execute:(Ljava/lang/Runnable;)V
      10: return

  public void executeBlocking(java.lang.Runnable, long, java.util.concurrent.TimeUnit) throws java.util.concurrent.RejectedExecutionException, java.lang.InterruptedException;
    Code:
       0: aload_0
       1: getfield      #2                  // Field delegate:Lorg/jboss/threads/DirectExecutor;
       4: aload_1
       5: invokeinterface #3,  2            // InterfaceMethod org/jboss/threads/DirectExecutor.execute:(Ljava/lang/Runnable;)V
      10: goto          32
      13: astore        5
      15: invokestatic  #5                  // Method java/lang/Thread.interrupted:()Z
      18: ifeq          29
      21: new           #6                  // class java/lang/InterruptedException
      24: dup
      25: invokespecial #7                  // Method java/lang/InterruptedException."<init>":()V
      28: athrow
      29: aload         5
      31: athrow
      32: return
    Exception table:
       from    to  target type
           0    10    13   Class org/jboss/threads/ExecutionInterruptedException

  public void executeBlocking(java.lang.Runnable) throws java.util.concurrent.RejectedExecutionException, java.lang.InterruptedException;
    Code:
       0: aload_0
       1: getfield      #2                  // Field delegate:Lorg/jboss/threads/DirectExecutor;
       4: aload_1
       5: invokeinterface #3,  2            // InterfaceMethod org/jboss/threads/DirectExecutor.execute:(Ljava/lang/Runnable;)V
      10: goto          30
      13: astore_2
      14: invokestatic  #5                  // Method java/lang/Thread.interrupted:()Z
      17: ifeq          28
      20: new           #6                  // class java/lang/InterruptedException
      23: dup
      24: invokespecial #7                  // Method java/lang/InterruptedException."<init>":()V
      27: athrow
      28: aload_2
      29: athrow
      30: return
    Exception table:
       from    to  target type
           0    10    13   Class org/jboss/threads/ExecutionInterruptedException
}
