Compiled from "DependencyTaskBuilder.java"
public final class org.jboss.threads.DependencyTaskBuilder {
  private final java.util.Collection<org.jboss.threads.Dependency> dependencies;

  private final java.util.concurrent.Executor executor;

  private final java.lang.Runnable task;

  org.jboss.threads.DependencyTaskBuilder(java.util.concurrent.Executor, java.lang.Runnable);
    Code:
       0: aload_0
       1: invokespecial #1                  // Method java/lang/Object."<init>":()V
       4: aload_0
       5: new           #2                  // class java/util/LinkedHashSet
       8: dup
       9: invokespecial #3                  // Method java/util/LinkedHashSet."<init>":()V
      12: putfield      #4                  // Field dependencies:Ljava/util/Collection;
      15: aload_0
      16: aload_1
      17: putfield      #5                  // Field executor:Ljava/util/concurrent/Executor;
      20: aload_0
      21: aload_2
      22: putfield      #6                  // Field task:Ljava/lang/Runnable;
      25: return

  public org.jboss.threads.DependencyTaskBuilder add(org.jboss.threads.Dependency);
    Code:
       0: aload_1
       1: ifnonnull     14
       4: new           #7                  // class java/lang/NullPointerException
       7: dup
       8: ldc           #8                  // String dependency is null
      10: invokespecial #9                  // Method java/lang/NullPointerException."<init>":(Ljava/lang/String;)V
      13: athrow
      14: aload_0
      15: getfield      #4                  // Field dependencies:Ljava/util/Collection;
      18: aload_1
      19: invokeinterface #10,  2           // InterfaceMethod java/util/Collection.add:(Ljava/lang/Object;)Z
      24: pop
      25: aload_0
      26: areturn

  public org.jboss.threads.DependencyTaskBuilder add(java.util.Collection<org.jboss.threads.Dependency>);
    Code:
       0: aload_0
       1: getfield      #4                  // Field dependencies:Ljava/util/Collection;
       4: aload_1
       5: invokeinterface #11,  2           // InterfaceMethod java/util/Collection.addAll:(Ljava/util/Collection;)Z
      10: pop
      11: aload_0
      12: areturn

  public org.jboss.threads.DependencyTaskBuilder add(org.jboss.threads.Dependency...);
    Code:
       0: aload_0
       1: getfield      #4                  // Field dependencies:Ljava/util/Collection;
       4: aload_1
       5: invokestatic  #12                 // Method java/util/Arrays.asList:([Ljava/lang/Object;)Ljava/util/List;
       8: invokeinterface #11,  2           // InterfaceMethod java/util/Collection.addAll:(Ljava/util/Collection;)Z
      13: pop
      14: aload_0
      15: areturn

  public org.jboss.threads.Dependency create();
    Code:
       0: aload_0
       1: getfield      #4                  // Field dependencies:Ljava/util/Collection;
       4: astore_1
       5: new           #13                 // class org/jboss/threads/Dependency
       8: dup
       9: aload_0
      10: getfield      #5                  // Field executor:Ljava/util/concurrent/Executor;
      13: aload_0
      14: getfield      #6                  // Field task:Ljava/lang/Runnable;
      17: aload_1
      18: invokeinterface #14,  1           // InterfaceMethod java/util/Collection.size:()I
      23: iconst_1
      24: iadd
      25: invokespecial #15                 // Method org/jboss/threads/Dependency."<init>":(Ljava/util/concurrent/Executor;Ljava/lang/Runnable;I)V
      28: astore_2
      29: aload_1
      30: invokeinterface #16,  1           // InterfaceMethod java/util/Collection.iterator:()Ljava/util/Iterator;
      35: astore_3
      36: aload_3
      37: invokeinterface #17,  1           // InterfaceMethod java/util/Iterator.hasNext:()Z
      42: ifeq          65
      45: aload_3
      46: invokeinterface #18,  1           // InterfaceMethod java/util/Iterator.next:()Ljava/lang/Object;
      51: checkcast     #13                 // class org/jboss/threads/Dependency
      54: astore        4
      56: aload         4
      58: aload_2
      59: invokevirtual #19                 // Method org/jboss/threads/Dependency.addDependent:(Lorg/jboss/threads/Dependency;)V
      62: goto          36
      65: aload_2
      66: invokevirtual #20                 // Method org/jboss/threads/Dependency.dependencyFinished:()V
      69: aload_2
      70: areturn
}
