Compiled from "QueueExecutor.java"
class org.jboss.threads.QueueExecutor$Worker implements java.lang.Runnable {
  private volatile java.lang.Runnable first;

  final org.jboss.threads.QueueExecutor this$0;

  public org.jboss.threads.QueueExecutor$Worker(org.jboss.threads.QueueExecutor, java.lang.Runnable);
    Code:
       0: aload_0
       1: aload_1
       2: putfield      #1                  // Field this$0:Lorg/jboss/threads/QueueExecutor;
       5: aload_0
       6: invokespecial #2                  // Method java/lang/Object."<init>":()V
       9: aload_0
      10: aload_2
      11: putfield      #3                  // Field first:Ljava/lang/Runnable;
      14: return

  public void run();
    Code:
       0: aload_0
       1: getfield      #1                  // Field this$0:Lorg/jboss/threads/QueueExecutor;
       4: invokestatic  #4                  // Method org/jboss/threads/QueueExecutor.access$000:(Lorg/jboss/threads/QueueExecutor;)Ljava/util/concurrent/locks/Lock;
       7: astore_1
       8: aload_0
       9: getfield      #3                  // Field first:Ljava/lang/Runnable;
      12: astore_2
      13: aload_0
      14: aconst_null
      15: putfield      #3                  // Field first:Ljava/lang/Runnable;
      18: aload_0
      19: getfield      #1                  // Field this$0:Lorg/jboss/threads/QueueExecutor;
      22: aload_2
      23: invokestatic  #5                  // Method org/jboss/threads/QueueExecutor.access$100:(Lorg/jboss/threads/QueueExecutor;Ljava/lang/Runnable;)V
      26: aconst_null
      27: astore_2
      28: aload_1
      29: invokeinterface #6,  1            // InterfaceMethod java/util/concurrent/locks/Lock.lock:()V
      34: aload_0
      35: getfield      #1                  // Field this$0:Lorg/jboss/threads/QueueExecutor;
      38: invokestatic  #7                  // Method org/jboss/threads/QueueExecutor.access$200:(Lorg/jboss/threads/QueueExecutor;)Z
      41: ifeq          161
      44: aload_0
      45: getfield      #1                  // Field this$0:Lorg/jboss/threads/QueueExecutor;
      48: invokestatic  #8                  // Method org/jboss/threads/QueueExecutor.access$300:(Lorg/jboss/threads/QueueExecutor;)Ljava/lang/Runnable;
      51: dup
      52: astore_2
      53: ifnonnull     152
      56: aload_1
      57: invokeinterface #9,  1            // InterfaceMethod java/util/concurrent/locks/Lock.unlock:()V
      62: iconst_0
      63: istore_3
      64: aload_1
      65: invokeinterface #6,  1            // InterfaceMethod java/util/concurrent/locks/Lock.lock:()V
      70: aload_0
      71: getfield      #1                  // Field this$0:Lorg/jboss/threads/QueueExecutor;
      74: invokestatic  #10                 // Method org/jboss/threads/QueueExecutor.access$500:(Lorg/jboss/threads/QueueExecutor;)Ljava/util/Set;
      77: invokestatic  #11                 // Method java/lang/Thread.currentThread:()Ljava/lang/Thread;
      80: invokeinterface #12,  2           // InterfaceMethod java/util/Set.remove:(Ljava/lang/Object;)Z
      85: pop
      86: aload_0
      87: getfield      #1                  // Field this$0:Lorg/jboss/threads/QueueExecutor;
      90: invokestatic  #7                  // Method org/jboss/threads/QueueExecutor.access$200:(Lorg/jboss/threads/QueueExecutor;)Z
      93: ifeq          115
      96: aload_0
      97: getfield      #1                  // Field this$0:Lorg/jboss/threads/QueueExecutor;
     100: invokestatic  #10                 // Method org/jboss/threads/QueueExecutor.access$500:(Lorg/jboss/threads/QueueExecutor;)Ljava/util/Set;
     103: invokeinterface #13,  1           // InterfaceMethod java/util/Set.isEmpty:()Z
     108: ifeq          115
     111: iconst_1
     112: goto          116
     115: iconst_0
     116: istore_3
     117: aload_1
     118: invokeinterface #9,  1            // InterfaceMethod java/util/concurrent/locks/Lock.unlock:()V
     123: goto          137
     126: astore        4
     128: aload_1
     129: invokeinterface #9,  1            // InterfaceMethod java/util/concurrent/locks/Lock.unlock:()V
     134: aload         4
     136: athrow
     137: iload_3
     138: ifeq          151
     141: aload_0
     142: getfield      #1                  // Field this$0:Lorg/jboss/threads/QueueExecutor;
     145: invokestatic  #14                 // Method org/jboss/threads/QueueExecutor.access$600:(Lorg/jboss/threads/QueueExecutor;)Lorg/jboss/threads/SimpleShutdownListenable;
     148: invokevirtual #15                 // Method org/jboss/threads/SimpleShutdownListenable.shutdown:()V
     151: return
     152: invokestatic  #11                 // Method java/lang/Thread.currentThread:()Ljava/lang/Thread;
     155: invokevirtual #16                 // Method java/lang/Thread.interrupt:()V
     158: goto          269
     161: aload_0
     162: getfield      #1                  // Field this$0:Lorg/jboss/threads/QueueExecutor;
     165: invokestatic  #17                 // Method org/jboss/threads/QueueExecutor.access$400:(Lorg/jboss/threads/QueueExecutor;)Ljava/lang/Runnable;
     168: dup
     169: astore_2
     170: ifnonnull     269
     173: aload_1
     174: invokeinterface #9,  1            // InterfaceMethod java/util/concurrent/locks/Lock.unlock:()V
     179: iconst_0
     180: istore_3
     181: aload_1
     182: invokeinterface #6,  1            // InterfaceMethod java/util/concurrent/locks/Lock.lock:()V
     187: aload_0
     188: getfield      #1                  // Field this$0:Lorg/jboss/threads/QueueExecutor;
     191: invokestatic  #10                 // Method org/jboss/threads/QueueExecutor.access$500:(Lorg/jboss/threads/QueueExecutor;)Ljava/util/Set;
     194: invokestatic  #11                 // Method java/lang/Thread.currentThread:()Ljava/lang/Thread;
     197: invokeinterface #12,  2           // InterfaceMethod java/util/Set.remove:(Ljava/lang/Object;)Z
     202: pop
     203: aload_0
     204: getfield      #1                  // Field this$0:Lorg/jboss/threads/QueueExecutor;
     207: invokestatic  #7                  // Method org/jboss/threads/QueueExecutor.access$200:(Lorg/jboss/threads/QueueExecutor;)Z
     210: ifeq          232
     213: aload_0
     214: getfield      #1                  // Field this$0:Lorg/jboss/threads/QueueExecutor;
     217: invokestatic  #10                 // Method org/jboss/threads/QueueExecutor.access$500:(Lorg/jboss/threads/QueueExecutor;)Ljava/util/Set;
     220: invokeinterface #13,  1           // InterfaceMethod java/util/Set.isEmpty:()Z
     225: ifeq          232
     228: iconst_1
     229: goto          233
     232: iconst_0
     233: istore_3
     234: aload_1
     235: invokeinterface #9,  1            // InterfaceMethod java/util/concurrent/locks/Lock.unlock:()V
     240: goto          254
     243: astore        5
     245: aload_1
     246: invokeinterface #9,  1            // InterfaceMethod java/util/concurrent/locks/Lock.unlock:()V
     251: aload         5
     253: athrow
     254: iload_3
     255: ifeq          268
     258: aload_0
     259: getfield      #1                  // Field this$0:Lorg/jboss/threads/QueueExecutor;
     262: invokestatic  #14                 // Method org/jboss/threads/QueueExecutor.access$600:(Lorg/jboss/threads/QueueExecutor;)Lorg/jboss/threads/SimpleShutdownListenable;
     265: invokevirtual #15                 // Method org/jboss/threads/SimpleShutdownListenable.shutdown:()V
     268: return
     269: aload_1
     270: invokeinterface #9,  1            // InterfaceMethod java/util/concurrent/locks/Lock.unlock:()V
     275: goto          289
     278: astore        6
     280: aload_1
     281: invokeinterface #9,  1            // InterfaceMethod java/util/concurrent/locks/Lock.unlock:()V
     286: aload         6
     288: athrow
     289: aload_0
     290: getfield      #1                  // Field this$0:Lorg/jboss/threads/QueueExecutor;
     293: aload_2
     294: invokestatic  #5                  // Method org/jboss/threads/QueueExecutor.access$100:(Lorg/jboss/threads/QueueExecutor;Ljava/lang/Runnable;)V
     297: invokestatic  #18                 // Method java/lang/Thread.interrupted:()Z
     300: pop
     301: goto          26
     304: astore        7
     306: iconst_0
     307: istore        8
     309: aload_1
     310: invokeinterface #6,  1            // InterfaceMethod java/util/concurrent/locks/Lock.lock:()V
     315: aload_0
     316: getfield      #1                  // Field this$0:Lorg/jboss/threads/QueueExecutor;
     319: invokestatic  #10                 // Method org/jboss/threads/QueueExecutor.access$500:(Lorg/jboss/threads/QueueExecutor;)Ljava/util/Set;
     322: invokestatic  #11                 // Method java/lang/Thread.currentThread:()Ljava/lang/Thread;
     325: invokeinterface #12,  2           // InterfaceMethod java/util/Set.remove:(Ljava/lang/Object;)Z
     330: pop
     331: aload_0
     332: getfield      #1                  // Field this$0:Lorg/jboss/threads/QueueExecutor;
     335: invokestatic  #7                  // Method org/jboss/threads/QueueExecutor.access$200:(Lorg/jboss/threads/QueueExecutor;)Z
     338: ifeq          360
     341: aload_0
     342: getfield      #1                  // Field this$0:Lorg/jboss/threads/QueueExecutor;
     345: invokestatic  #10                 // Method org/jboss/threads/QueueExecutor.access$500:(Lorg/jboss/threads/QueueExecutor;)Ljava/util/Set;
     348: invokeinterface #13,  1           // InterfaceMethod java/util/Set.isEmpty:()Z
     353: ifeq          360
     356: iconst_1
     357: goto          361
     360: iconst_0
     361: istore        8
     363: aload_1
     364: invokeinterface #9,  1            // InterfaceMethod java/util/concurrent/locks/Lock.unlock:()V
     369: goto          383
     372: astore        9
     374: aload_1
     375: invokeinterface #9,  1            // InterfaceMethod java/util/concurrent/locks/Lock.unlock:()V
     380: aload         9
     382: athrow
     383: iload         8
     385: ifeq          398
     388: aload_0
     389: getfield      #1                  // Field this$0:Lorg/jboss/threads/QueueExecutor;
     392: invokestatic  #14                 // Method org/jboss/threads/QueueExecutor.access$600:(Lorg/jboss/threads/QueueExecutor;)Lorg/jboss/threads/SimpleShutdownListenable;
     395: invokevirtual #15                 // Method org/jboss/threads/SimpleShutdownListenable.shutdown:()V
     398: aload         7
     400: athrow
    Exception table:
       from    to  target type
          70   117   126   any
         126   128   126   any
         187   234   243   any
         243   245   243   any
          34    56   278   any
         152   173   278   any
         278   280   278   any
           8    62   304   any
         152   179   304   any
         315   363   372   any
         372   374   372   any
         269   306   304   any
}
