Compiled from "AbsIRIImpl.java"
class org.apache.jena.iri.impl.AbsIRIImpl$PathRelativize {
  private final int flag;

  private final int allFlags;

  private final java.lang.String replacement;

  org.apache.jena.iri.impl.AbsIRIImpl$PathRelativize(int, int, java.lang.String);
    Code:
       0: aload_0
       1: invokespecial #2                  // Method java/lang/Object."<init>":()V
       4: aload_0
       5: iload_1
       6: putfield      #3                  // Field flag:I
       9: aload_0
      10: aload_3
      11: putfield      #4                  // Field replacement:Ljava/lang/String;
      14: aload_0
      15: iload_2
      16: putfield      #5                  // Field allFlags:I
      19: return

  boolean check(java.lang.String, java.lang.String[], int, java.lang.String);
    Code:
       0: aload_2
       1: iconst_0
       2: aconst_null
       3: aastore
       4: aload_1
       5: ifnonnull     10
       8: iconst_0
       9: ireturn
      10: iload_3
      11: aload_0
      12: getfield      #5                  // Field allFlags:I
      15: iand
      16: ifne          21
      19: iconst_0
      20: ireturn
      21: aload_1
      22: bipush        47
      24: invokevirtual #6                  // Method java/lang/String.lastIndexOf:(I)I
      27: istore        5
      29: iload         5
      31: iconst_m1
      32: if_icmpne     37
      35: iconst_0
      36: ireturn
      37: iload         5
      39: ifne          59
      42: iload_3
      43: iconst_4
      44: iand
      45: ifeq          59
      48: aload_0
      49: getfield      #3                  // Field flag:I
      52: bipush        8
      54: if_icmpeq     59
      57: iconst_0
      58: ireturn
      59: aload_1
      60: iconst_0
      61: iload         5
      63: iconst_1
      64: iadd
      65: invokevirtual #7                  // Method java/lang/String.substring:(II)Ljava/lang/String;
      68: astore_1
      69: aload_2
      70: iconst_0
      71: aload_1
      72: iconst_0
      73: iload         5
      75: invokevirtual #7                  // Method java/lang/String.substring:(II)Ljava/lang/String;
      78: aastore
      79: iload_3
      80: aload_0
      81: getfield      #3                  // Field flag:I
      84: iand
      85: ifne          90
      88: iconst_0
      89: ireturn
      90: aload         4
      92: aload_1
      93: invokevirtual #8                  // Method java/lang/String.startsWith:(Ljava/lang/String;)Z
      96: ifne          101
      99: iconst_0
     100: ireturn
     101: aload         4
     103: invokevirtual #9                  // Method java/lang/String.length:()I
     106: iload         5
     108: iconst_1
     109: iadd
     110: if_icmpne     122
     113: aload_2
     114: iconst_0
     115: aload_0
     116: getfield      #4                  // Field replacement:Ljava/lang/String;
     119: aastore
     120: iconst_1
     121: ireturn
     122: aload_2
     123: iconst_0
     124: aload_0
     125: aload         4
     127: iload         5
     129: iconst_1
     130: iadd
     131: invokevirtual #10                 // Method java/lang/String.substring:(I)Ljava/lang/String;
     134: invokevirtual #11                 // Method descendentMatch:(Ljava/lang/String;)Ljava/lang/String;
     137: aastore
     138: iconst_1
     139: ireturn

  java.lang.String descendentMatch(java.lang.String);
    Code:
       0: new           #12                 // class java/lang/StringBuilder
       3: dup
       4: invokespecial #13                 // Method java/lang/StringBuilder."<init>":()V
       7: aload_0
       8: getfield      #4                  // Field replacement:Ljava/lang/String;
      11: invokevirtual #14                 // Method java/lang/StringBuilder.append:(Ljava/lang/String;)Ljava/lang/StringBuilder;
      14: ldc           #15                 // String /
      16: invokevirtual #14                 // Method java/lang/StringBuilder.append:(Ljava/lang/String;)Ljava/lang/StringBuilder;
      19: aload_1
      20: invokevirtual #14                 // Method java/lang/StringBuilder.append:(Ljava/lang/String;)Ljava/lang/StringBuilder;
      23: invokevirtual #16                 // Method java/lang/StringBuilder.toString:()Ljava/lang/String;
      26: areturn
}
