Compiled from "ViolationImpl.java"
public class org.apache.jena.iri.impl.ViolationImpl extends org.apache.jena.iri.Violation {
  static java.lang.String[] componentNames;

  private final int code;

  private final int slot;

  private final org.apache.jena.iri.impl.AbsIRIImpl iri;

  static java.lang.String componentName(int);
    Code:
       0: getstatic     #1                  // Field componentNames:[Ljava/lang/String;
       3: ifnonnull     16
       6: ldc           #2                  // class org/apache/jena/iri/IRIComponents
       8: bipush        40
      10: invokestatic  #3                  // Method org/apache/jena/iri/impl/PatternCompiler.constantsFromClass:(Ljava/lang/Class;I)[Ljava/lang/String;
      13: putstatic     #1                  // Field componentNames:[Ljava/lang/String;
      16: getstatic     #1                  // Field componentNames:[Ljava/lang/String;
      19: iload_0
      20: aaload
      21: areturn

  public org.apache.jena.iri.impl.ViolationImpl(org.apache.jena.iri.IRI, int, int);
    Code:
       0: aload_0
       1: invokespecial #4                  // Method org/apache/jena/iri/Violation."<init>":()V
       4: aload_0
       5: aload_1
       6: checkcast     #5                  // class org/apache/jena/iri/impl/AbsIRIImpl
       9: putfield      #6                  // Field iri:Lorg/apache/jena/iri/impl/AbsIRIImpl;
      12: aload_0
      13: iload_3
      14: putfield      #7                  // Field code:I
      17: aload_0
      18: iload_2
      19: putfield      #8                  // Field slot:I
      22: return

  public int getViolationCode();
    Code:
       0: aload_0
       1: getfield      #7                  // Field code:I
       4: ireturn

  public org.apache.jena.iri.IRI getIRI();
    Code:
       0: aload_0
       1: getfield      #6                  // Field iri:Lorg/apache/jena/iri/impl/AbsIRIImpl;
       4: areturn

  public int getComponent();
    Code:
       0: aload_0
       1: getfield      #8                  // Field slot:I
       4: ireturn

  public java.lang.String component();
    Code:
       0: aload_0
       1: getfield      #8                  // Field slot:I
       4: invokestatic  #9                  // Method componentName:(I)Ljava/lang/String;
       7: areturn

  public java.lang.String codeName();
    Code:
       0: aload_0
       1: getfield      #7                  // Field code:I
       4: invokestatic  #10                 // Method org/apache/jena/iri/impl/PatternCompiler.errorCodeName:(I)Ljava/lang/String;
       7: areturn

  public boolean isError();
    Code:
       0: aload_0
       1: getfield      #6                  // Field iri:Lorg/apache/jena/iri/impl/AbsIRIImpl;
       4: invokevirtual #11                 // Method org/apache/jena/iri/impl/AbsIRIImpl.getSchemeSpec:()Lorg/apache/jena/iri/impl/SchemeSpecificPart;
       7: iconst_0
       8: invokevirtual #12                 // Method org/apache/jena/iri/impl/SchemeSpecificPart.getMask:(Z)J
      11: lconst_1
      12: aload_0
      13: getfield      #7                  // Field code:I
      16: lshl
      17: land
      18: lconst_0
      19: lcmp
      20: ifeq          27
      23: iconst_1
      24: goto          28
      27: iconst_0
      28: ireturn

  public java.lang.String getShortMessage();
    Code:
       0: new           #13                 // class java/lang/StringBuilder
       3: dup
       4: invokespecial #14                 // Method java/lang/StringBuilder."<init>":()V
       7: ldc           #15                 // String <
       9: invokevirtual #16                 // Method java/lang/StringBuilder.append:(Ljava/lang/String;)Ljava/lang/StringBuilder;
      12: aload_0
      13: invokevirtual #17                 // Method getIRI:()Lorg/apache/jena/iri/IRI;
      16: invokevirtual #18                 // Method java/lang/StringBuilder.append:(Ljava/lang/Object;)Ljava/lang/StringBuilder;
      19: ldc           #19                 // String > Code:
      21: invokevirtual #16                 // Method java/lang/StringBuilder.append:(Ljava/lang/String;)Ljava/lang/StringBuilder;
      24: aload_0
      25: getfield      #7                  // Field code:I
      28: invokevirtual #20                 // Method java/lang/StringBuilder.append:(I)Ljava/lang/StringBuilder;
      31: ldc           #21                 // String /
      33: invokevirtual #16                 // Method java/lang/StringBuilder.append:(Ljava/lang/String;)Ljava/lang/StringBuilder;
      36: aload_0
      37: invokevirtual #22                 // Method codeName:()Ljava/lang/String;
      40: invokevirtual #16                 // Method java/lang/StringBuilder.append:(Ljava/lang/String;)Ljava/lang/StringBuilder;
      43: ldc           #23                 // String  in
      45: invokevirtual #16                 // Method java/lang/StringBuilder.append:(Ljava/lang/String;)Ljava/lang/StringBuilder;
      48: aload_0
      49: invokevirtual #24                 // Method component:()Ljava/lang/String;
      52: invokevirtual #16                 // Method java/lang/StringBuilder.append:(Ljava/lang/String;)Ljava/lang/StringBuilder;
      55: ldc           #25                 // String :
      57: invokevirtual #16                 // Method java/lang/StringBuilder.append:(Ljava/lang/String;)Ljava/lang/StringBuilder;
      60: aload_0
      61: invokespecial #26                 // Method description:()Ljava/lang/String;
      64: invokevirtual #16                 // Method java/lang/StringBuilder.append:(Ljava/lang/String;)Ljava/lang/StringBuilder;
      67: invokevirtual #27                 // Method java/lang/StringBuilder.toString:()Ljava/lang/String;
      70: areturn

  private java.lang.String description();
    Code:
       0: getstatic     #28                 // Field org/apache/jena/iri/impl/ViolationCodeInfo.all:[Lorg/apache/jena/iri/impl/ViolationCodeInfo;
       3: aload_0
       4: getfield      #7                  // Field code:I
       7: aaload
       8: astore_1
       9: aload_1
      10: ifnonnull     16
      13: ldc           #29                 // String internal error: description of error not found
      15: areturn
      16: aload_1
      17: aload_0
      18: getfield      #8                  // Field slot:I
      21: aload_0
      22: getfield      #6                  // Field iri:Lorg/apache/jena/iri/impl/AbsIRIImpl;
      25: invokevirtual #30                 // Method org/apache/jena/iri/impl/ViolationCodeInfo.description:(ILorg/apache/jena/iri/impl/AbsIRIImpl;)Ljava/lang/String;
      28: areturn

  public java.lang.String getLongMessage();
    Code:
       0: new           #13                 // class java/lang/StringBuilder
       3: dup
       4: invokespecial #14                 // Method java/lang/StringBuilder."<init>":()V
       7: ldc           #15                 // String <
       9: invokevirtual #16                 // Method java/lang/StringBuilder.append:(Ljava/lang/String;)Ljava/lang/StringBuilder;
      12: aload_0
      13: invokevirtual #17                 // Method getIRI:()Lorg/apache/jena/iri/IRI;
      16: invokevirtual #18                 // Method java/lang/StringBuilder.append:(Ljava/lang/Object;)Ljava/lang/StringBuilder;
      19: ldc           #19                 // String > Code:
      21: invokevirtual #16                 // Method java/lang/StringBuilder.append:(Ljava/lang/String;)Ljava/lang/StringBuilder;
      24: aload_0
      25: getfield      #7                  // Field code:I
      28: invokevirtual #20                 // Method java/lang/StringBuilder.append:(I)Ljava/lang/StringBuilder;
      31: ldc           #21                 // String /
      33: invokevirtual #16                 // Method java/lang/StringBuilder.append:(Ljava/lang/String;)Ljava/lang/StringBuilder;
      36: aload_0
      37: invokevirtual #22                 // Method codeName:()Ljava/lang/String;
      40: invokevirtual #16                 // Method java/lang/StringBuilder.append:(Ljava/lang/String;)Ljava/lang/StringBuilder;
      43: ldc           #23                 // String  in
      45: invokevirtual #16                 // Method java/lang/StringBuilder.append:(Ljava/lang/String;)Ljava/lang/StringBuilder;
      48: aload_0
      49: invokevirtual #24                 // Method component:()Ljava/lang/String;
      52: invokevirtual #16                 // Method java/lang/StringBuilder.append:(Ljava/lang/String;)Ljava/lang/StringBuilder;
      55: ldc           #25                 // String :
      57: invokevirtual #16                 // Method java/lang/StringBuilder.append:(Ljava/lang/String;)Ljava/lang/StringBuilder;
      60: aload_0
      61: invokespecial #26                 // Method description:()Ljava/lang/String;
      64: invokevirtual #16                 // Method java/lang/StringBuilder.append:(Ljava/lang/String;)Ljava/lang/StringBuilder;
      67: ldc           #31                 // String  see:
      69: invokevirtual #16                 // Method java/lang/StringBuilder.append:(Ljava/lang/String;)Ljava/lang/StringBuilder;
      72: aload_0
      73: invokespecial #32                 // Method specs:()Ljava/lang/String;
      76: invokevirtual #16                 // Method java/lang/StringBuilder.append:(Ljava/lang/String;)Ljava/lang/StringBuilder;
      79: invokevirtual #27                 // Method java/lang/StringBuilder.toString:()Ljava/lang/String;
      82: areturn

  private java.lang.String specs();
    Code:
       0: getstatic     #28                 // Field org/apache/jena/iri/impl/ViolationCodeInfo.all:[Lorg/apache/jena/iri/impl/ViolationCodeInfo;
       3: aload_0
       4: getfield      #7                  // Field code:I
       7: aaload
       8: astore_1
       9: aload_1
      10: ifnonnull     16
      13: ldc           #33                 // String (null)
      15: areturn
      16: aload_1
      17: aload_0
      18: getfield      #8                  // Field slot:I
      21: aload_0
      22: getfield      #6                  // Field iri:Lorg/apache/jena/iri/impl/AbsIRIImpl;
      25: invokevirtual #34                 // Method org/apache/jena/iri/impl/AbsIRIImpl.getFactory:()Lorg/apache/jena/iri/impl/IRIFactoryImpl;
      28: aload_0
      29: getfield      #6                  // Field iri:Lorg/apache/jena/iri/impl/AbsIRIImpl;
      32: invokevirtual #35                 // Method org/apache/jena/iri/impl/AbsIRIImpl.getScheme:()Ljava/lang/String;
      35: invokevirtual #36                 // Method org/apache/jena/iri/impl/ViolationCodeInfo.specs:(ILorg/apache/jena/iri/impl/IRIFactoryImpl;Ljava/lang/String;)Ljava/lang/String;
      38: areturn

  public java.lang.String getSpecificationURL();
    Code:
       0: new           #37                 // class java/lang/UnsupportedOperationException
       3: dup
       4: ldc           #38                 // String Not yet implemented.
       6: invokespecial #39                 // Method java/lang/UnsupportedOperationException."<init>":(Ljava/lang/String;)V
       9: athrow
}
