Compiled from "UserBean.java"
public class org.camunda.bpm.engine.spring.test.transaction.modification.UserBean {
  public org.camunda.bpm.engine.ProcessEngine processEngine;

  org.camunda.bpm.engine.RuntimeService runtimeService;

  org.camunda.bpm.engine.RepositoryService repositoryService;

  public org.camunda.bpm.engine.spring.test.transaction.modification.UserBean();
    Code:
       0: aload_0
       1: invokespecial #1                  // Method java/lang/Object."<init>":()V
       4: return

  public void completeUserTaskAndModifyInstanceInOneTransaction(org.camunda.bpm.engine.runtime.ProcessInstance);
    Code:
       0: aload_0
       1: getfield      #2                  // Field runtimeService:Lorg/camunda/bpm/engine/RuntimeService;
       4: aload_1
       5: invokeinterface #3,  1            // InterfaceMethod org/camunda/bpm/engine/runtime/ProcessInstance.getId:()Ljava/lang/String;
      10: invokeinterface #4,  2            // InterfaceMethod org/camunda/bpm/engine/RuntimeService.createProcessInstanceModification:(Ljava/lang/String;)Lorg/camunda/bpm/engine/runtime/ProcessInstanceModificationBuilder;
      15: ldc           #5                  // String TimerEvent
      17: invokeinterface #6,  2            // InterfaceMethod org/camunda/bpm/engine/runtime/ProcessInstanceModificationBuilder.cancelAllForActivity:(Ljava/lang/String;)Lorg/camunda/bpm/engine/runtime/ProcessInstanceModificationBuilder;
      22: ldc           #5                  // String TimerEvent
      24: invokeinterface #7,  2            // InterfaceMethod org/camunda/bpm/engine/runtime/ProcessInstanceModificationBuilder.startBeforeActivity:(Ljava/lang/String;)Lorg/camunda/bpm/engine/runtime/InstantiationBuilder;
      29: checkcast     #8                  // class org/camunda/bpm/engine/runtime/ProcessInstanceModificationInstantiationBuilder
      32: invokeinterface #9,  1            // InterfaceMethod org/camunda/bpm/engine/runtime/ProcessInstanceModificationInstantiationBuilder.execute:()V
      37: return
}
