Compiled from "SamlAssertionWrapper.java"
public class org.apache.wss4j.common.saml.SamlAssertionWrapper {
  private static final org.slf4j.Logger LOG;

  private org.opensaml.saml.common.SAMLObject samlObject;

  private org.opensaml.saml.common.SAMLVersion samlVersion;

  private org.w3c.dom.Element assertionElement;

  private org.apache.wss4j.common.saml.SAMLKeyInfo subjectKeyInfo;

  private org.apache.wss4j.common.saml.SAMLKeyInfo signatureKeyInfo;

  private final java.lang.String defaultCanonicalizationAlgorithm;

  private final java.lang.String defaultRSASignatureAlgorithm;

  private final java.lang.String defaultDSASignatureAlgorithm;

  private final java.lang.String defaultSignatureDigestAlgorithm;

  private final boolean fromDOM;

  public org.apache.wss4j.common.saml.SamlAssertionWrapper(org.w3c.dom.Element) throws org.apache.wss4j.common.ext.WSSecurityException;
    Code:
       0: aload_0
       1: invokespecial #1                  // Method java/lang/Object."<init>":()V
       4: aload_0
       5: aconst_null
       6: putfield      #2                  // Field samlObject:Lorg/opensaml/saml/common/SAMLObject;
       9: aload_0
      10: ldc           #3                  // String http://www.w3.org/2001/10/xml-exc-c14n#
      12: putfield      #4                  // Field defaultCanonicalizationAlgorithm:Ljava/lang/String;
      15: aload_0
      16: ldc           #5                  // String http://www.w3.org/2000/09/xmldsig#rsa-sha1
      18: putfield      #6                  // Field defaultRSASignatureAlgorithm:Ljava/lang/String;
      21: aload_0
      22: ldc           #7                  // String http://www.w3.org/2000/09/xmldsig#dsa-sha1
      24: putfield      #8                  // Field defaultDSASignatureAlgorithm:Ljava/lang/String;
      27: aload_0
      28: ldc           #9                  // String http://www.w3.org/2000/09/xmldsig#sha1
      30: putfield      #10                 // Field defaultSignatureDigestAlgorithm:Ljava/lang/String;
      33: invokestatic  #11                 // Method org/apache/wss4j/common/saml/OpenSAMLUtil.initSamlEngine:()V
      36: aload_0
      37: aload_1
      38: invokespecial #12                 // Method parseElement:(Lorg/w3c/dom/Element;)V
      41: aload_0
      42: iconst_1
      43: putfield      #13                 // Field fromDOM:Z
      46: return

  public org.apache.wss4j.common.saml.SamlAssertionWrapper(org.opensaml.saml.common.SAMLObject) throws org.apache.wss4j.common.ext.WSSecurityException;
    Code:
       0: aload_0
       1: invokespecial #1                  // Method java/lang/Object."<init>":()V
       4: aload_0
       5: aconst_null
       6: putfield      #2                  // Field samlObject:Lorg/opensaml/saml/common/SAMLObject;
       9: aload_0
      10: ldc           #3                  // String http://www.w3.org/2001/10/xml-exc-c14n#
      12: putfield      #4                  // Field defaultCanonicalizationAlgorithm:Ljava/lang/String;
      15: aload_0
      16: ldc           #5                  // String http://www.w3.org/2000/09/xmldsig#rsa-sha1
      18: putfield      #6                  // Field defaultRSASignatureAlgorithm:Ljava/lang/String;
      21: aload_0
      22: ldc           #7                  // String http://www.w3.org/2000/09/xmldsig#dsa-sha1
      24: putfield      #8                  // Field defaultDSASignatureAlgorithm:Ljava/lang/String;
      27: aload_0
      28: ldc           #9                  // String http://www.w3.org/2000/09/xmldsig#sha1
      30: putfield      #10                 // Field defaultSignatureDigestAlgorithm:Ljava/lang/String;
      33: invokestatic  #11                 // Method org/apache/wss4j/common/saml/OpenSAMLUtil.initSamlEngine:()V
      36: aload_0
      37: aload_1
      38: putfield      #2                  // Field samlObject:Lorg/opensaml/saml/common/SAMLObject;
      41: aload_1
      42: instanceof    #14                 // class org/opensaml/saml/saml1/core/Assertion
      45: ifeq          58
      48: aload_0
      49: getstatic     #15                 // Field org/opensaml/saml/common/SAMLVersion.VERSION_11:Lorg/opensaml/saml/common/SAMLVersion;
      52: putfield      #16                 // Field samlVersion:Lorg/opensaml/saml/common/SAMLVersion;
      55: goto          138
      58: aload_1
      59: instanceof    #17                 // class org/opensaml/saml/saml2/core/Assertion
      62: ifeq          75
      65: aload_0
      66: getstatic     #18                 // Field org/opensaml/saml/common/SAMLVersion.VERSION_20:Lorg/opensaml/saml/common/SAMLVersion;
      69: putfield      #16                 // Field samlVersion:Lorg/opensaml/saml/common/SAMLVersion;
      72: goto          138
      75: getstatic     #19                 // Field LOG:Lorg/slf4j/Logger;
      78: new           #20                 // class java/lang/StringBuilder
      81: dup
      82: invokespecial #21                 // Method java/lang/StringBuilder."<init>":()V
      85: ldc           #22                 // String SamlAssertionWrapper: found unexpected type
      87: invokevirtual #23                 // Method java/lang/StringBuilder.append:(Ljava/lang/String;)Ljava/lang/StringBuilder;
      90: aload_1
      91: ifnull        104
      94: aload_1
      95: invokevirtual #24                 // Method java/lang/Object.getClass:()Ljava/lang/Class;
      98: invokevirtual #25                 // Method java/lang/Class.getName:()Ljava/lang/String;
     101: goto          105
     104: aconst_null
     105: invokevirtual #23                 // Method java/lang/StringBuilder.append:(Ljava/lang/String;)Ljava/lang/StringBuilder;
     108: invokevirtual #26                 // Method java/lang/StringBuilder.toString:()Ljava/lang/String;
     111: invokeinterface #27,  2           // InterfaceMethod org/slf4j/Logger.error:(Ljava/lang/String;)V
     116: new           #28                 // class org/apache/wss4j/common/ext/WSSecurityException
     119: dup
     120: getstatic     #29                 // Field org/apache/wss4j/common/ext/WSSecurityException$ErrorCode.FAILURE:Lorg/apache/wss4j/common/ext/WSSecurityException$ErrorCode;
     123: ldc           #30                 // String empty
     125: iconst_1
     126: anewarray     #31                 // class java/lang/Object
     129: dup
     130: iconst_0
     131: ldc           #32                 // String A SAML 2.0 or 1.1 Assertion can only be used with SamlAssertionWrapper
     133: aastore
     134: invokespecial #33                 // Method org/apache/wss4j/common/ext/WSSecurityException."<init>":(Lorg/apache/wss4j/common/ext/WSSecurityException$ErrorCode;Ljava/lang/String;[Ljava/lang/Object;)V
     137: athrow
     138: aload_0
     139: iconst_0
     140: putfield      #13                 // Field fromDOM:Z
     143: return

  public org.apache.wss4j.common.saml.SamlAssertionWrapper(org.apache.wss4j.common.saml.SAMLCallback) throws org.apache.wss4j.common.ext.WSSecurityException;
    Code:
       0: aload_0
       1: invokespecial #1                  // Method java/lang/Object."<init>":()V
       4: aload_0
       5: aconst_null
       6: putfield      #2                  // Field samlObject:Lorg/opensaml/saml/common/SAMLObject;
       9: aload_0
      10: ldc           #3                  // String http://www.w3.org/2001/10/xml-exc-c14n#
      12: putfield      #4                  // Field defaultCanonicalizationAlgorithm:Ljava/lang/String;
      15: aload_0
      16: ldc           #5                  // String http://www.w3.org/2000/09/xmldsig#rsa-sha1
      18: putfield      #6                  // Field defaultRSASignatureAlgorithm:Ljava/lang/String;
      21: aload_0
      22: ldc           #7                  // String http://www.w3.org/2000/09/xmldsig#dsa-sha1
      24: putfield      #8                  // Field defaultDSASignatureAlgorithm:Ljava/lang/String;
      27: aload_0
      28: ldc           #9                  // String http://www.w3.org/2000/09/xmldsig#sha1
      30: putfield      #10                 // Field defaultSignatureDigestAlgorithm:Ljava/lang/String;
      33: invokestatic  #11                 // Method org/apache/wss4j/common/saml/OpenSAMLUtil.initSamlEngine:()V
      36: aload_1
      37: invokevirtual #34                 // Method org/apache/wss4j/common/saml/SAMLCallback.getAssertionElement:()Lorg/w3c/dom/Element;
      40: ifnull        59
      43: aload_0
      44: aload_1
      45: invokevirtual #34                 // Method org/apache/wss4j/common/saml/SAMLCallback.getAssertionElement:()Lorg/w3c/dom/Element;
      48: invokespecial #12                 // Method parseElement:(Lorg/w3c/dom/Element;)V
      51: aload_0
      52: iconst_1
      53: putfield      #13                 // Field fromDOM:Z
      56: goto          69
      59: aload_0
      60: aload_1
      61: invokespecial #35                 // Method parseCallback:(Lorg/apache/wss4j/common/saml/SAMLCallback;)V
      64: aload_0
      65: iconst_0
      66: putfield      #13                 // Field fromDOM:Z
      69: return

  public org.opensaml.saml.saml1.core.Assertion getSaml1();
    Code:
       0: aload_0
       1: getfield      #16                 // Field samlVersion:Lorg/opensaml/saml/common/SAMLVersion;
       4: getstatic     #15                 // Field org/opensaml/saml/common/SAMLVersion.VERSION_11:Lorg/opensaml/saml/common/SAMLVersion;
       7: if_acmpne     18
      10: aload_0
      11: getfield      #2                  // Field samlObject:Lorg/opensaml/saml/common/SAMLObject;
      14: checkcast     #14                 // class org/opensaml/saml/saml1/core/Assertion
      17: areturn
      18: aconst_null
      19: areturn

  public org.opensaml.saml.saml2.core.Assertion getSaml2();
    Code:
       0: aload_0
       1: getfield      #16                 // Field samlVersion:Lorg/opensaml/saml/common/SAMLVersion;
       4: getstatic     #18                 // Field org/opensaml/saml/common/SAMLVersion.VERSION_20:Lorg/opensaml/saml/common/SAMLVersion;
       7: if_acmpne     18
      10: aload_0
      11: getfield      #2                  // Field samlObject:Lorg/opensaml/saml/common/SAMLObject;
      14: checkcast     #17                 // class org/opensaml/saml/saml2/core/Assertion
      17: areturn
      18: aconst_null
      19: areturn

  public boolean isCreated();
    Code:
       0: aload_0
       1: getfield      #2                  // Field samlObject:Lorg/opensaml/saml/common/SAMLObject;
       4: ifnull        11
       7: iconst_1
       8: goto          12
      11: iconst_0
      12: ireturn

  public org.w3c.dom.Element toDOM(org.w3c.dom.Document) throws org.apache.wss4j.common.ext.WSSecurityException;
    Code:
       0: aload_0
       1: getfield      #13                 // Field fromDOM:Z
       4: ifeq          46
       7: aload_0
       8: getfield      #36                 // Field assertionElement:Lorg/w3c/dom/Element;
      11: ifnull        46
      14: aload_0
      15: aload_0
      16: getfield      #36                 // Field assertionElement:Lorg/w3c/dom/Element;
      19: invokespecial #12                 // Method parseElement:(Lorg/w3c/dom/Element;)V
      22: aload_1
      23: ifnull        41
      26: aload_1
      27: aload_0
      28: getfield      #36                 // Field assertionElement:Lorg/w3c/dom/Element;
      31: iconst_1
      32: invokeinterface #37,  3           // InterfaceMethod org/w3c/dom/Document.importNode:(Lorg/w3c/dom/Node;Z)Lorg/w3c/dom/Node;
      37: checkcast     #38                 // class org/w3c/dom/Element
      40: areturn
      41: aload_0
      42: getfield      #36                 // Field assertionElement:Lorg/w3c/dom/Element;
      45: areturn
      46: aload_0
      47: aload_0
      48: getfield      #2                  // Field samlObject:Lorg/opensaml/saml/common/SAMLObject;
      51: aload_1
      52: invokestatic  #39                 // Method org/apache/wss4j/common/saml/OpenSAMLUtil.toDom:(Lorg/opensaml/core/xml/XMLObject;Lorg/w3c/dom/Document;)Lorg/w3c/dom/Element;
      55: putfield      #36                 // Field assertionElement:Lorg/w3c/dom/Element;
      58: aload_0
      59: getfield      #36                 // Field assertionElement:Lorg/w3c/dom/Element;
      62: areturn

  public java.lang.String assertionToString() throws org.apache.wss4j.common.ext.WSSecurityException;
    Code:
       0: aload_0
       1: getfield      #36                 // Field assertionElement:Lorg/w3c/dom/Element;
       4: ifnonnull     18
       7: aload_0
       8: aconst_null
       9: invokevirtual #40                 // Method toDOM:(Lorg/w3c/dom/Document;)Lorg/w3c/dom/Element;
      12: astore_1
      13: aload_1
      14: invokestatic  #41                 // Method org/apache/wss4j/common/util/DOM2Writer.nodeToString:(Lorg/w3c/dom/Node;)Ljava/lang/String;
      17: areturn
      18: aload_0
      19: getfield      #36                 // Field assertionElement:Lorg/w3c/dom/Element;
      22: invokestatic  #41                 // Method org/apache/wss4j/common/util/DOM2Writer.nodeToString:(Lorg/w3c/dom/Node;)Ljava/lang/String;
      25: areturn

  public java.lang.String getId();
    Code:
       0: aconst_null
       1: astore_1
       2: aload_0
       3: getfield      #16                 // Field samlVersion:Lorg/opensaml/saml/common/SAMLVersion;
       6: getstatic     #18                 // Field org/opensaml/saml/common/SAMLVersion.VERSION_20:Lorg/opensaml/saml/common/SAMLVersion;
       9: if_acmpne     68
      12: aload_0
      13: getfield      #2                  // Field samlObject:Lorg/opensaml/saml/common/SAMLObject;
      16: checkcast     #17                 // class org/opensaml/saml/saml2/core/Assertion
      19: invokeinterface #42,  1           // InterfaceMethod org/opensaml/saml/saml2/core/Assertion.getID:()Ljava/lang/String;
      24: astore_1
      25: aload_1
      26: ifnull        36
      29: aload_1
      30: invokevirtual #43                 // Method java/lang/String.length:()I
      33: ifne          144
      36: getstatic     #19                 // Field LOG:Lorg/slf4j/Logger;
      39: ldc           #44                 // String SamlAssertionWrapper: ID was null, seeting a new ID value
      41: invokeinterface #27,  2           // InterfaceMethod org/slf4j/Logger.error:(Ljava/lang/String;)V
      46: ldc           #45                 // String _
      48: invokestatic  #46                 // Method org/apache/xml/security/stax/impl/util/IDGenerator.generateID:(Ljava/lang/String;)Ljava/lang/String;
      51: astore_1
      52: aload_0
      53: getfield      #2                  // Field samlObject:Lorg/opensaml/saml/common/SAMLObject;
      56: checkcast     #17                 // class org/opensaml/saml/saml2/core/Assertion
      59: aload_1
      60: invokeinterface #47,  2           // InterfaceMethod org/opensaml/saml/saml2/core/Assertion.setID:(Ljava/lang/String;)V
      65: goto          144
      68: aload_0
      69: getfield      #16                 // Field samlVersion:Lorg/opensaml/saml/common/SAMLVersion;
      72: getstatic     #15                 // Field org/opensaml/saml/common/SAMLVersion.VERSION_11:Lorg/opensaml/saml/common/SAMLVersion;
      75: if_acmpne     134
      78: aload_0
      79: getfield      #2                  // Field samlObject:Lorg/opensaml/saml/common/SAMLObject;
      82: checkcast     #14                 // class org/opensaml/saml/saml1/core/Assertion
      85: invokeinterface #48,  1           // InterfaceMethod org/opensaml/saml/saml1/core/Assertion.getID:()Ljava/lang/String;
      90: astore_1
      91: aload_1
      92: ifnull        102
      95: aload_1
      96: invokevirtual #43                 // Method java/lang/String.length:()I
      99: ifne          144
     102: getstatic     #19                 // Field LOG:Lorg/slf4j/Logger;
     105: ldc           #44                 // String SamlAssertionWrapper: ID was null, seeting a new ID value
     107: invokeinterface #27,  2           // InterfaceMethod org/slf4j/Logger.error:(Ljava/lang/String;)V
     112: ldc           #45                 // String _
     114: invokestatic  #46                 // Method org/apache/xml/security/stax/impl/util/IDGenerator.generateID:(Ljava/lang/String;)Ljava/lang/String;
     117: astore_1
     118: aload_0
     119: getfield      #2                  // Field samlObject:Lorg/opensaml/saml/common/SAMLObject;
     122: checkcast     #14                 // class org/opensaml/saml/saml1/core/Assertion
     125: aload_1
     126: invokeinterface #49,  2           // InterfaceMethod org/opensaml/saml/saml1/core/Assertion.setID:(Ljava/lang/String;)V
     131: goto          144
     134: getstatic     #19                 // Field LOG:Lorg/slf4j/Logger;
     137: ldc           #50                 // String SamlAssertionWrapper: unable to return ID - no saml assertion object
     139: invokeinterface #27,  2           // InterfaceMethod org/slf4j/Logger.error:(Ljava/lang/String;)V
     144: aload_1
     145: areturn

  public java.lang.String getIssuerString();
    Code:
       0: aload_0
       1: getfield      #16                 // Field samlVersion:Lorg/opensaml/saml/common/SAMLVersion;
       4: getstatic     #18                 // Field org/opensaml/saml/common/SAMLVersion.VERSION_20:Lorg/opensaml/saml/common/SAMLVersion;
       7: if_acmpne     43
      10: aload_0
      11: getfield      #2                  // Field samlObject:Lorg/opensaml/saml/common/SAMLObject;
      14: checkcast     #17                 // class org/opensaml/saml/saml2/core/Assertion
      17: invokeinterface #51,  1           // InterfaceMethod org/opensaml/saml/saml2/core/Assertion.getIssuer:()Lorg/opensaml/saml/saml2/core/Issuer;
      22: ifnull        43
      25: aload_0
      26: getfield      #2                  // Field samlObject:Lorg/opensaml/saml/common/SAMLObject;
      29: checkcast     #17                 // class org/opensaml/saml/saml2/core/Assertion
      32: invokeinterface #51,  1           // InterfaceMethod org/opensaml/saml/saml2/core/Assertion.getIssuer:()Lorg/opensaml/saml/saml2/core/Issuer;
      37: invokeinterface #52,  1           // InterfaceMethod org/opensaml/saml/saml2/core/Issuer.getValue:()Ljava/lang/String;
      42: areturn
      43: aload_0
      44: getfield      #16                 // Field samlVersion:Lorg/opensaml/saml/common/SAMLVersion;
      47: getstatic     #15                 // Field org/opensaml/saml/common/SAMLVersion.VERSION_11:Lorg/opensaml/saml/common/SAMLVersion;
      50: if_acmpne     81
      53: aload_0
      54: getfield      #2                  // Field samlObject:Lorg/opensaml/saml/common/SAMLObject;
      57: checkcast     #14                 // class org/opensaml/saml/saml1/core/Assertion
      60: invokeinterface #53,  1           // InterfaceMethod org/opensaml/saml/saml1/core/Assertion.getIssuer:()Ljava/lang/String;
      65: ifnull        81
      68: aload_0
      69: getfield      #2                  // Field samlObject:Lorg/opensaml/saml/common/SAMLObject;
      72: checkcast     #14                 // class org/opensaml/saml/saml1/core/Assertion
      75: invokeinterface #53,  1           // InterfaceMethod org/opensaml/saml/saml1/core/Assertion.getIssuer:()Ljava/lang/String;
      80: areturn
      81: getstatic     #19                 // Field LOG:Lorg/slf4j/Logger;
      84: ldc           #54                 // String SamlAssertionWrapper: unable to return Issuer string - no saml assertion object or issuer is null
      86: invokeinterface #27,  2           // InterfaceMethod org/slf4j/Logger.error:(Ljava/lang/String;)V
      91: aconst_null
      92: areturn

  public java.lang.String getSubjectName();
    Code:
       0: aload_0
       1: getfield      #16                 // Field samlVersion:Lorg/opensaml/saml/common/SAMLVersion;
       4: getstatic     #18                 // Field org/opensaml/saml/common/SAMLVersion.VERSION_20:Lorg/opensaml/saml/common/SAMLVersion;
       7: if_acmpne     51
      10: aload_0
      11: getfield      #2                  // Field samlObject:Lorg/opensaml/saml/common/SAMLObject;
      14: checkcast     #17                 // class org/opensaml/saml/saml2/core/Assertion
      17: invokeinterface #55,  1           // InterfaceMethod org/opensaml/saml/saml2/core/Assertion.getSubject:()Lorg/opensaml/saml/saml2/core/Subject;
      22: astore_1
      23: aload_1
      24: ifnull        48
      27: aload_1
      28: invokeinterface #56,  1           // InterfaceMethod org/opensaml/saml/saml2/core/Subject.getNameID:()Lorg/opensaml/saml/saml2/core/NameID;
      33: ifnull        48
      36: aload_1
      37: invokeinterface #56,  1           // InterfaceMethod org/opensaml/saml/saml2/core/Subject.getNameID:()Lorg/opensaml/saml/saml2/core/NameID;
      42: invokeinterface #57,  1           // InterfaceMethod org/opensaml/saml/saml2/core/NameID.getValue:()Ljava/lang/String;
      47: areturn
      48: goto          197
      51: aload_0
      52: getfield      #16                 // Field samlVersion:Lorg/opensaml/saml/common/SAMLVersion;
      55: getstatic     #15                 // Field org/opensaml/saml/common/SAMLVersion.VERSION_11:Lorg/opensaml/saml/common/SAMLVersion;
      58: if_acmpne     197
      61: aconst_null
      62: astore_1
      63: aload_0
      64: getfield      #2                  // Field samlObject:Lorg/opensaml/saml/common/SAMLObject;
      67: checkcast     #14                 // class org/opensaml/saml/saml1/core/Assertion
      70: invokeinterface #58,  1           // InterfaceMethod org/opensaml/saml/saml1/core/Assertion.getStatements:()Ljava/util/List;
      75: invokeinterface #59,  1           // InterfaceMethod java/util/List.iterator:()Ljava/util/Iterator;
      80: astore_2
      81: aload_2
      82: invokeinterface #60,  1           // InterfaceMethod java/util/Iterator.hasNext:()Z
      87: ifeq          172
      90: aload_2
      91: invokeinterface #61,  1           // InterfaceMethod java/util/Iterator.next:()Ljava/lang/Object;
      96: checkcast     #62                 // class org/opensaml/saml/saml1/core/Statement
      99: astore_3
     100: aload_3
     101: instanceof    #63                 // class org/opensaml/saml/saml1/core/AttributeStatement
     104: ifeq          124
     107: aload_3
     108: checkcast     #63                 // class org/opensaml/saml/saml1/core/AttributeStatement
     111: astore        4
     113: aload         4
     115: invokeinterface #64,  1           // InterfaceMethod org/opensaml/saml/saml1/core/AttributeStatement.getSubject:()Lorg/opensaml/saml/saml1/core/Subject;
     120: astore_1
     121: goto          162
     124: aload_3
     125: instanceof    #65                 // class org/opensaml/saml/saml1/core/AuthenticationStatement
     128: ifeq          148
     131: aload_3
     132: checkcast     #65                 // class org/opensaml/saml/saml1/core/AuthenticationStatement
     135: astore        4
     137: aload         4
     139: invokeinterface #66,  1           // InterfaceMethod org/opensaml/saml/saml1/core/AuthenticationStatement.getSubject:()Lorg/opensaml/saml/saml1/core/Subject;
     144: astore_1
     145: goto          162
     148: aload_3
     149: checkcast     #67                 // class org/opensaml/saml/saml1/core/AuthorizationDecisionStatement
     152: astore        4
     154: aload         4
     156: invokeinterface #68,  1           // InterfaceMethod org/opensaml/saml/saml1/core/AuthorizationDecisionStatement.getSubject:()Lorg/opensaml/saml/saml1/core/Subject;
     161: astore_1
     162: aload_1
     163: ifnull        169
     166: goto          172
     169: goto          81
     172: aload_1
     173: ifnull        197
     176: aload_1
     177: invokeinterface #69,  1           // InterfaceMethod org/opensaml/saml/saml1/core/Subject.getNameIdentifier:()Lorg/opensaml/saml/saml1/core/NameIdentifier;
     182: ifnull        197
     185: aload_1
     186: invokeinterface #69,  1           // InterfaceMethod org/opensaml/saml/saml1/core/Subject.getNameIdentifier:()Lorg/opensaml/saml/saml1/core/NameIdentifier;
     191: invokeinterface #70,  1           // InterfaceMethod org/opensaml/saml/saml1/core/NameIdentifier.getValue:()Ljava/lang/String;
     196: areturn
     197: getstatic     #19                 // Field LOG:Lorg/slf4j/Logger;
     200: ldc           #71                 // String SamlAssertionWrapper: unable to return SubjectName - no saml assertion object or subject is null
     202: invokeinterface #27,  2           // InterfaceMethod org/slf4j/Logger.error:(Ljava/lang/String;)V
     207: aconst_null
     208: areturn

  public java.util.List<java.lang.String> getConfirmationMethods();
    Code:
       0: new           #72                 // class java/util/ArrayList
       3: dup
       4: invokespecial #73                 // Method java/util/ArrayList."<init>":()V
       7: astore_1
       8: aload_0
       9: getfield      #16                 // Field samlVersion:Lorg/opensaml/saml/common/SAMLVersion;
      12: getstatic     #18                 // Field org/opensaml/saml/common/SAMLVersion.VERSION_20:Lorg/opensaml/saml/common/SAMLVersion;
      15: if_acmpne     88
      18: aload_0
      19: getfield      #2                  // Field samlObject:Lorg/opensaml/saml/common/SAMLObject;
      22: checkcast     #17                 // class org/opensaml/saml/saml2/core/Assertion
      25: invokeinterface #55,  1           // InterfaceMethod org/opensaml/saml/saml2/core/Assertion.getSubject:()Lorg/opensaml/saml/saml2/core/Subject;
      30: astore_2
      31: aload_2
      32: invokeinterface #74,  1           // InterfaceMethod org/opensaml/saml/saml2/core/Subject.getSubjectConfirmations:()Ljava/util/List;
      37: astore_3
      38: aload_3
      39: invokeinterface #59,  1           // InterfaceMethod java/util/List.iterator:()Ljava/util/Iterator;
      44: astore        4
      46: aload         4
      48: invokeinterface #60,  1           // InterfaceMethod java/util/Iterator.hasNext:()Z
      53: ifeq          85
      56: aload         4
      58: invokeinterface #61,  1           // InterfaceMethod java/util/Iterator.next:()Ljava/lang/Object;
      63: checkcast     #75                 // class org/opensaml/saml/saml2/core/SubjectConfirmation
      66: astore        5
      68: aload_1
      69: aload         5
      71: invokeinterface #76,  1           // InterfaceMethod org/opensaml/saml/saml2/core/SubjectConfirmation.getMethod:()Ljava/lang/String;
      76: invokeinterface #77,  2           // InterfaceMethod java/util/List.add:(Ljava/lang/Object;)Z
      81: pop
      82: goto          46
      85: goto          322
      88: aload_0
      89: getfield      #16                 // Field samlVersion:Lorg/opensaml/saml/common/SAMLVersion;
      92: getstatic     #15                 // Field org/opensaml/saml/common/SAMLVersion.VERSION_11:Lorg/opensaml/saml/common/SAMLVersion;
      95: if_acmpne     322
      98: new           #72                 // class java/util/ArrayList
     101: dup
     102: invokespecial #73                 // Method java/util/ArrayList."<init>":()V
     105: astore_2
     106: aload_0
     107: getfield      #2                  // Field samlObject:Lorg/opensaml/saml/common/SAMLObject;
     110: checkcast     #14                 // class org/opensaml/saml/saml1/core/Assertion
     113: astore_3
     114: aload_2
     115: aload_3
     116: invokeinterface #78,  1           // InterfaceMethod org/opensaml/saml/saml1/core/Assertion.getSubjectStatements:()Ljava/util/List;
     121: invokeinterface #79,  2           // InterfaceMethod java/util/List.addAll:(Ljava/util/Collection;)Z
     126: pop
     127: aload_2
     128: aload_3
     129: invokeinterface #80,  1           // InterfaceMethod org/opensaml/saml/saml1/core/Assertion.getAuthenticationStatements:()Ljava/util/List;
     134: invokeinterface #79,  2           // InterfaceMethod java/util/List.addAll:(Ljava/util/Collection;)Z
     139: pop
     140: aload_2
     141: aload_3
     142: invokeinterface #81,  1           // InterfaceMethod org/opensaml/saml/saml1/core/Assertion.getAttributeStatements:()Ljava/util/List;
     147: invokeinterface #79,  2           // InterfaceMethod java/util/List.addAll:(Ljava/util/Collection;)Z
     152: pop
     153: aload_2
     154: aload_3
     155: invokeinterface #82,  1           // InterfaceMethod org/opensaml/saml/saml1/core/Assertion.getAuthorizationDecisionStatements:()Ljava/util/List;
     160: invokeinterface #79,  2           // InterfaceMethod java/util/List.addAll:(Ljava/util/Collection;)Z
     165: pop
     166: aload_2
     167: invokeinterface #59,  1           // InterfaceMethod java/util/List.iterator:()Ljava/util/Iterator;
     172: astore        4
     174: aload         4
     176: invokeinterface #60,  1           // InterfaceMethod java/util/Iterator.hasNext:()Z
     181: ifeq          322
     184: aload         4
     186: invokeinterface #61,  1           // InterfaceMethod java/util/Iterator.next:()Ljava/lang/Object;
     191: checkcast     #83                 // class org/opensaml/saml/saml1/core/SubjectStatement
     194: astore        5
     196: aload         5
     198: invokeinterface #84,  1           // InterfaceMethod org/opensaml/saml/saml1/core/SubjectStatement.getSubject:()Lorg/opensaml/saml/saml1/core/Subject;
     203: astore        6
     205: aload         6
     207: ifnull        319
     210: aload         6
     212: invokeinterface #85,  1           // InterfaceMethod org/opensaml/saml/saml1/core/Subject.getSubjectConfirmation:()Lorg/opensaml/saml/saml1/core/SubjectConfirmation;
     217: astore        7
     219: aload         7
     221: ifnull        319
     224: aload         7
     226: invokeinterface #86,  1           // InterfaceMethod org/opensaml/saml/saml1/core/SubjectConfirmation.getSubjectConfirmationData:()Lorg/opensaml/core/xml/XMLObject;
     231: astore        8
     233: aload         8
     235: instanceof    #87                 // class org/opensaml/saml/saml1/core/ConfirmationMethod
     238: ifeq          262
     241: aload         8
     243: checkcast     #87                 // class org/opensaml/saml/saml1/core/ConfirmationMethod
     246: astore        9
     248: aload_1
     249: aload         9
     251: invokeinterface #88,  1           // InterfaceMethod org/opensaml/saml/saml1/core/ConfirmationMethod.getConfirmationMethod:()Ljava/lang/String;
     256: invokeinterface #77,  2           // InterfaceMethod java/util/List.add:(Ljava/lang/Object;)Z
     261: pop
     262: aload         7
     264: invokeinterface #89,  1           // InterfaceMethod org/opensaml/saml/saml1/core/SubjectConfirmation.getConfirmationMethods:()Ljava/util/List;
     269: astore        9
     271: aload         9
     273: invokeinterface #59,  1           // InterfaceMethod java/util/List.iterator:()Ljava/util/Iterator;
     278: astore        10
     280: aload         10
     282: invokeinterface #60,  1           // InterfaceMethod java/util/Iterator.hasNext:()Z
     287: ifeq          319
     290: aload         10
     292: invokeinterface #61,  1           // InterfaceMethod java/util/Iterator.next:()Ljava/lang/Object;
     297: checkcast     #87                 // class org/opensaml/saml/saml1/core/ConfirmationMethod
     300: astore        11
     302: aload_1
     303: aload         11
     305: invokeinterface #88,  1           // InterfaceMethod org/opensaml/saml/saml1/core/ConfirmationMethod.getConfirmationMethod:()Ljava/lang/String;
     310: invokeinterface #77,  2           // InterfaceMethod java/util/List.add:(Ljava/lang/Object;)Z
     315: pop
     316: goto          280
     319: goto          174
     322: aload_1
     323: areturn

  public boolean isSigned();
    Code:
       0: aload_0
       1: getfield      #2                  // Field samlObject:Lorg/opensaml/saml/common/SAMLObject;
       4: instanceof    #90                 // class org/opensaml/saml/common/SignableSAMLObject
       7: ifeq          42
      10: aload_0
      11: getfield      #2                  // Field samlObject:Lorg/opensaml/saml/common/SAMLObject;
      14: checkcast     #90                 // class org/opensaml/saml/common/SignableSAMLObject
      17: invokeinterface #91,  1           // InterfaceMethod org/opensaml/saml/common/SignableSAMLObject.isSigned:()Z
      22: ifne          40
      25: aload_0
      26: getfield      #2                  // Field samlObject:Lorg/opensaml/saml/common/SAMLObject;
      29: checkcast     #90                 // class org/opensaml/saml/common/SignableSAMLObject
      32: invokeinterface #92,  1           // InterfaceMethod org/opensaml/saml/common/SignableSAMLObject.getSignature:()Lorg/opensaml/xmlsec/signature/Signature;
      37: ifnull        42
      40: iconst_1
      41: ireturn
      42: iconst_0
      43: ireturn

  public void setSignature(org.opensaml.xmlsec.signature.Signature);
    Code:
       0: aload_0
       1: aload_1
       2: ldc           #9                  // String http://www.w3.org/2000/09/xmldsig#sha1
       4: invokevirtual #93                 // Method setSignature:(Lorg/opensaml/xmlsec/signature/Signature;Ljava/lang/String;)V
       7: return

  public void setSignature(org.opensaml.xmlsec.signature.Signature, java.lang.String);
    Code:
       0: aload_0
       1: getfield      #2                  // Field samlObject:Lorg/opensaml/saml/common/SAMLObject;
       4: instanceof    #90                 // class org/opensaml/saml/common/SignableSAMLObject
       7: ifeq          77
      10: aload_0
      11: getfield      #2                  // Field samlObject:Lorg/opensaml/saml/common/SAMLObject;
      14: checkcast     #90                 // class org/opensaml/saml/common/SignableSAMLObject
      17: astore_3
      18: aload_3
      19: aload_1
      20: invokeinterface #94,  2           // InterfaceMethod org/opensaml/saml/common/SignableSAMLObject.setSignature:(Lorg/opensaml/xmlsec/signature/Signature;)V
      25: aload_2
      26: astore        4
      28: aload         4
      30: ifnonnull     37
      33: ldc           #9                  // String http://www.w3.org/2000/09/xmldsig#sha1
      35: astore        4
      37: aload_1
      38: invokeinterface #95,  1           // InterfaceMethod org/opensaml/xmlsec/signature/Signature.getContentReferences:()Ljava/util/List;
      43: iconst_0
      44: invokeinterface #96,  2           // InterfaceMethod java/util/List.get:(I)Ljava/lang/Object;
      49: checkcast     #97                 // class org/opensaml/saml/common/SAMLObjectContentReference
      52: astore        5
      54: aload         5
      56: aload         4
      58: invokevirtual #98                 // Method org/opensaml/saml/common/SAMLObjectContentReference.setDigestAlgorithm:(Ljava/lang/String;)V
      61: aload_3
      62: invokeinterface #99,  1           // InterfaceMethod org/opensaml/saml/common/SignableSAMLObject.releaseDOM:()V
      67: aload_3
      68: iconst_1
      69: invokeinterface #100,  2          // InterfaceMethod org/opensaml/saml/common/SignableSAMLObject.releaseChildrenDOM:(Z)V
      74: goto          113
      77: getstatic     #19                 // Field LOG:Lorg/slf4j/Logger;
      80: new           #20                 // class java/lang/StringBuilder
      83: dup
      84: invokespecial #21                 // Method java/lang/StringBuilder."<init>":()V
      87: ldc           #101                // String Attempt to sign an unsignable object
      89: invokevirtual #23                 // Method java/lang/StringBuilder.append:(Ljava/lang/String;)Ljava/lang/StringBuilder;
      92: aload_0
      93: getfield      #2                  // Field samlObject:Lorg/opensaml/saml/common/SAMLObject;
      96: invokevirtual #24                 // Method java/lang/Object.getClass:()Ljava/lang/Class;
      99: invokevirtual #25                 // Method java/lang/Class.getName:()Ljava/lang/String;
     102: invokevirtual #23                 // Method java/lang/StringBuilder.append:(Ljava/lang/String;)Ljava/lang/StringBuilder;
     105: invokevirtual #26                 // Method java/lang/StringBuilder.toString:()Ljava/lang/String;
     108: invokeinterface #27,  2           // InterfaceMethod org/slf4j/Logger.error:(Ljava/lang/String;)V
     113: return

  public void signAssertion(java.lang.String, java.lang.String, org.apache.wss4j.common.crypto.Crypto, boolean) throws org.apache.wss4j.common.ext.WSSecurityException;
    Code:
       0: aload_0
       1: aload_1
       2: aload_2
       3: aload_3
       4: iload         4
       6: ldc           #3                  // String http://www.w3.org/2001/10/xml-exc-c14n#
       8: ldc           #5                  // String http://www.w3.org/2000/09/xmldsig#rsa-sha1
      10: ldc           #9                  // String http://www.w3.org/2000/09/xmldsig#sha1
      12: invokevirtual #102                // Method signAssertion:(Ljava/lang/String;Ljava/lang/String;Lorg/apache/wss4j/common/crypto/Crypto;ZLjava/lang/String;Ljava/lang/String;Ljava/lang/String;)V
      15: return

  public void signAssertion(java.lang.String, java.lang.String, org.apache.wss4j.common.crypto.Crypto, boolean, java.lang.String, java.lang.String) throws org.apache.wss4j.common.ext.WSSecurityException;
    Code:
       0: aload_0
       1: aload_1
       2: aload_2
       3: aload_3
       4: iload         4
       6: aload         5
       8: aload         6
      10: ldc           #9                  // String http://www.w3.org/2000/09/xmldsig#sha1
      12: invokevirtual #102                // Method signAssertion:(Ljava/lang/String;Ljava/lang/String;Lorg/apache/wss4j/common/crypto/Crypto;ZLjava/lang/String;Ljava/lang/String;Ljava/lang/String;)V
      15: return

  public void signAssertion(java.lang.String, java.lang.String, org.apache.wss4j.common.crypto.Crypto, boolean, java.lang.String, java.lang.String, java.lang.String) throws org.apache.wss4j.common.ext.WSSecurityException;
    Code:
       0: invokestatic  #103                // Method org/apache/wss4j/common/saml/OpenSAMLUtil.buildSignature:()Lorg/opensaml/xmlsec/signature/Signature;
       3: astore        8
       5: aload         5
       7: astore        9
       9: aload         9
      11: ifnonnull     18
      14: ldc           #3                  // String http://www.w3.org/2001/10/xml-exc-c14n#
      16: astore        9
      18: aload         8
      20: aload         9
      22: invokeinterface #104,  2          // InterfaceMethod org/opensaml/xmlsec/signature/Signature.setCanonicalizationAlgorithm:(Ljava/lang/String;)V
      27: getstatic     #19                 // Field LOG:Lorg/slf4j/Logger;
      30: invokeinterface #105,  1          // InterfaceMethod org/slf4j/Logger.isDebugEnabled:()Z
      35: ifeq          66
      38: getstatic     #19                 // Field LOG:Lorg/slf4j/Logger;
      41: new           #20                 // class java/lang/StringBuilder
      44: dup
      45: invokespecial #21                 // Method java/lang/StringBuilder."<init>":()V
      48: ldc           #106                // String Using Canonicalization algorithm
      50: invokevirtual #23                 // Method java/lang/StringBuilder.append:(Ljava/lang/String;)Ljava/lang/StringBuilder;
      53: aload         9
      55: invokevirtual #23                 // Method java/lang/StringBuilder.append:(Ljava/lang/String;)Ljava/lang/StringBuilder;
      58: invokevirtual #26                 // Method java/lang/StringBuilder.toString:()Ljava/lang/String;
      61: invokeinterface #107,  2          // InterfaceMethod org/slf4j/Logger.debug:(Ljava/lang/String;)V
      66: new           #108                // class org/apache/wss4j/common/crypto/CryptoType
      69: dup
      70: getstatic     #109                // Field org/apache/wss4j/common/crypto/CryptoType$TYPE.ALIAS:Lorg/apache/wss4j/common/crypto/CryptoType$TYPE;
      73: invokespecial #110                // Method org/apache/wss4j/common/crypto/CryptoType."<init>":(Lorg/apache/wss4j/common/crypto/CryptoType$TYPE;)V
      76: astore        10
      78: aload         10
      80: aload_1
      81: invokevirtual #111                // Method org/apache/wss4j/common/crypto/CryptoType.setAlias:(Ljava/lang/String;)V
      84: aload_3
      85: aload         10
      87: invokeinterface #112,  2          // InterfaceMethod org/apache/wss4j/common/crypto/Crypto.getX509Certificates:(Lorg/apache/wss4j/common/crypto/CryptoType;)[Ljava/security/cert/X509Certificate;
      92: astore        11
      94: aload         11
      96: ifnull        105
      99: aload         11
     101: arraylength
     102: ifne          144
     105: new           #28                 // class org/apache/wss4j/common/ext/WSSecurityException
     108: dup
     109: getstatic     #29                 // Field org/apache/wss4j/common/ext/WSSecurityException$ErrorCode.FAILURE:Lorg/apache/wss4j/common/ext/WSSecurityException$ErrorCode;
     112: ldc           #30                 // String empty
     114: iconst_1
     115: anewarray     #31                 // class java/lang/Object
     118: dup
     119: iconst_0
     120: new           #20                 // class java/lang/StringBuilder
     123: dup
     124: invokespecial #21                 // Method java/lang/StringBuilder."<init>":()V
     127: ldc           #113                // String No issuer certs were found to sign the SAML Assertion using issuer name:
     129: invokevirtual #23                 // Method java/lang/StringBuilder.append:(Ljava/lang/String;)Ljava/lang/StringBuilder;
     132: aload_1
     133: invokevirtual #23                 // Method java/lang/StringBuilder.append:(Ljava/lang/String;)Ljava/lang/StringBuilder;
     136: invokevirtual #26                 // Method java/lang/StringBuilder.toString:()Ljava/lang/String;
     139: aastore
     140: invokespecial #33                 // Method org/apache/wss4j/common/ext/WSSecurityException."<init>":(Lorg/apache/wss4j/common/ext/WSSecurityException$ErrorCode;Ljava/lang/String;[Ljava/lang/Object;)V
     143: athrow
     144: aload         6
     146: astore        12
     148: aload         12
     150: ifnonnull     157
     153: ldc           #5                  // String http://www.w3.org/2000/09/xmldsig#rsa-sha1
     155: astore        12
     157: aload         11
     159: iconst_0
     160: aaload
     161: invokevirtual #114                // Method java/security/cert/X509Certificate.getPublicKey:()Ljava/security/PublicKey;
     164: invokeinterface #115,  1          // InterfaceMethod java/security/PublicKey.getAlgorithm:()Ljava/lang/String;
     169: astore        13
     171: getstatic     #19                 // Field LOG:Lorg/slf4j/Logger;
     174: invokeinterface #105,  1          // InterfaceMethod org/slf4j/Logger.isDebugEnabled:()Z
     179: ifeq          210
     182: getstatic     #19                 // Field LOG:Lorg/slf4j/Logger;
     185: new           #20                 // class java/lang/StringBuilder
     188: dup
     189: invokespecial #21                 // Method java/lang/StringBuilder."<init>":()V
     192: ldc           #116                // String automatic sig algo detection:
     194: invokevirtual #23                 // Method java/lang/StringBuilder.append:(Ljava/lang/String;)Ljava/lang/StringBuilder;
     197: aload         13
     199: invokevirtual #23                 // Method java/lang/StringBuilder.append:(Ljava/lang/String;)Ljava/lang/StringBuilder;
     202: invokevirtual #26                 // Method java/lang/StringBuilder.toString:()Ljava/lang/String;
     205: invokeinterface #107,  2          // InterfaceMethod org/slf4j/Logger.debug:(Ljava/lang/String;)V
     210: aload         13
     212: ldc           #117                // String DSA
     214: invokevirtual #118                // Method java/lang/String.equalsIgnoreCase:(Ljava/lang/String;)Z
     217: ifeq          224
     220: ldc           #7                  // String http://www.w3.org/2000/09/xmldsig#dsa-sha1
     222: astore        12
     224: getstatic     #19                 // Field LOG:Lorg/slf4j/Logger;
     227: invokeinterface #105,  1          // InterfaceMethod org/slf4j/Logger.isDebugEnabled:()Z
     232: ifeq          263
     235: getstatic     #19                 // Field LOG:Lorg/slf4j/Logger;
     238: new           #20                 // class java/lang/StringBuilder
     241: dup
     242: invokespecial #21                 // Method java/lang/StringBuilder."<init>":()V
     245: ldc           #119                // String Using Signature algorithm
     247: invokevirtual #23                 // Method java/lang/StringBuilder.append:(Ljava/lang/String;)Ljava/lang/StringBuilder;
     250: aload         12
     252: invokevirtual #23                 // Method java/lang/StringBuilder.append:(Ljava/lang/String;)Ljava/lang/StringBuilder;
     255: invokevirtual #26                 // Method java/lang/StringBuilder.toString:()Ljava/lang/String;
     258: invokeinterface #107,  2          // InterfaceMethod org/slf4j/Logger.debug:(Ljava/lang/String;)V
     263: aconst_null
     264: astore        14
     266: aload_3
     267: aload_1
     268: aload_2
     269: invokeinterface #120,  3          // InterfaceMethod org/apache/wss4j/common/crypto/Crypto.getPrivateKey:(Ljava/lang/String;Ljava/lang/String;)Ljava/security/PrivateKey;
     274: astore        14
     276: goto          294
     279: astore        15
     281: new           #28                 // class org/apache/wss4j/common/ext/WSSecurityException
     284: dup
     285: getstatic     #29                 // Field org/apache/wss4j/common/ext/WSSecurityException$ErrorCode.FAILURE:Lorg/apache/wss4j/common/ext/WSSecurityException$ErrorCode;
     288: aload         15
     290: invokespecial #122                // Method org/apache/wss4j/common/ext/WSSecurityException."<init>":(Lorg/apache/wss4j/common/ext/WSSecurityException$ErrorCode;Ljava/lang/Exception;)V
     293: athrow
     294: aload         14
     296: ifnonnull     338
     299: new           #28                 // class org/apache/wss4j/common/ext/WSSecurityException
     302: dup
     303: getstatic     #29                 // Field org/apache/wss4j/common/ext/WSSecurityException$ErrorCode.FAILURE:Lorg/apache/wss4j/common/ext/WSSecurityException$ErrorCode;
     306: ldc           #30                 // String empty
     308: iconst_1
     309: anewarray     #31                 // class java/lang/Object
     312: dup
     313: iconst_0
     314: new           #20                 // class java/lang/StringBuilder
     317: dup
     318: invokespecial #21                 // Method java/lang/StringBuilder."<init>":()V
     321: ldc           #123                // String No private key was found using issuer name:
     323: invokevirtual #23                 // Method java/lang/StringBuilder.append:(Ljava/lang/String;)Ljava/lang/StringBuilder;
     326: aload_1
     327: invokevirtual #23                 // Method java/lang/StringBuilder.append:(Ljava/lang/String;)Ljava/lang/StringBuilder;
     330: invokevirtual #26                 // Method java/lang/StringBuilder.toString:()Ljava/lang/String;
     333: aastore
     334: invokespecial #33                 // Method org/apache/wss4j/common/ext/WSSecurityException."<init>":(Lorg/apache/wss4j/common/ext/WSSecurityException$ErrorCode;Ljava/lang/String;[Ljava/lang/Object;)V
     337: athrow
     338: aload         8
     340: aload         12
     342: invokeinterface #124,  2          // InterfaceMethod org/opensaml/xmlsec/signature/Signature.setSignatureAlgorithm:(Ljava/lang/String;)V
     347: new           #125                // class org/opensaml/security/x509/BasicX509Credential
     350: dup
     351: aload         11
     353: iconst_0
     354: aaload
     355: aload         14
     357: invokespecial #126                // Method org/opensaml/security/x509/BasicX509Credential."<init>":(Ljava/security/cert/X509Certificate;Ljava/security/PrivateKey;)V
     360: astore        15
     362: aload         8
     364: aload         15
     366: invokeinterface #127,  2          // InterfaceMethod org/opensaml/xmlsec/signature/Signature.setSigningCredential:(Lorg/opensaml/security/credential/Credential;)V
     371: new           #128                // class org/opensaml/xmlsec/keyinfo/impl/X509KeyInfoGeneratorFactory
     374: dup
     375: invokespecial #129                // Method org/opensaml/xmlsec/keyinfo/impl/X509KeyInfoGeneratorFactory."<init>":()V
     378: astore        16
     380: iload         4
     382: ifeq          394
     385: aload         16
     387: iconst_1
     388: invokevirtual #130                // Method org/opensaml/xmlsec/keyinfo/impl/X509KeyInfoGeneratorFactory.setEmitPublicKeyValue:(Z)V
     391: goto          400
     394: aload         16
     396: iconst_1
     397: invokevirtual #131                // Method org/opensaml/xmlsec/keyinfo/impl/X509KeyInfoGeneratorFactory.setEmitEntityCertificate:(Z)V
     400: aload         16
     402: invokevirtual #132                // Method org/opensaml/xmlsec/keyinfo/impl/X509KeyInfoGeneratorFactory.newInstance:()Lorg/opensaml/xmlsec/keyinfo/KeyInfoGenerator;
     405: aload         15
     407: invokeinterface #133,  2          // InterfaceMethod org/opensaml/xmlsec/keyinfo/KeyInfoGenerator.generate:(Lorg/opensaml/security/credential/Credential;)Lorg/opensaml/xmlsec/signature/KeyInfo;
     412: astore        17
     414: aload         8
     416: aload         17
     418: invokeinterface #134,  2          // InterfaceMethod org/opensaml/xmlsec/signature/Signature.setKeyInfo:(Lorg/opensaml/xmlsec/signature/KeyInfo;)V
     423: goto          452
     426: astore        17
     428: new           #28                 // class org/apache/wss4j/common/ext/WSSecurityException
     431: dup
     432: getstatic     #29                 // Field org/apache/wss4j/common/ext/WSSecurityException$ErrorCode.FAILURE:Lorg/apache/wss4j/common/ext/WSSecurityException$ErrorCode;
     435: aload         17
     437: ldc           #30                 // String empty
     439: iconst_1
     440: anewarray     #31                 // class java/lang/Object
     443: dup
     444: iconst_0
     445: ldc           #136                // String Error generating KeyInfo from signing credential
     447: aastore
     448: invokespecial #137                // Method org/apache/wss4j/common/ext/WSSecurityException."<init>":(Lorg/apache/wss4j/common/ext/WSSecurityException$ErrorCode;Ljava/lang/Exception;Ljava/lang/String;[Ljava/lang/Object;)V
     451: athrow
     452: aload_0
     453: aload         8
     455: aload         7
     457: invokevirtual #93                 // Method setSignature:(Lorg/opensaml/xmlsec/signature/Signature;Ljava/lang/String;)V
     460: return
    Exception table:
       from    to  target type
         266   276   279   Class java/lang/Exception
         400   423   426   Class org/opensaml/security/SecurityException

  public void verifySignature(org.apache.wss4j.common.saml.SAMLKeyInfoProcessor, org.apache.wss4j.common.crypto.Crypto) throws org.apache.wss4j.common.ext.WSSecurityException;
    Code:
       0: aload_0
       1: invokevirtual #138                // Method getSignature:()Lorg/opensaml/xmlsec/signature/Signature;
       4: astore_3
       5: aload_3
       6: ifnull        67
       9: aload_3
      10: invokeinterface #139,  1          // InterfaceMethod org/opensaml/xmlsec/signature/Signature.getKeyInfo:()Lorg/opensaml/xmlsec/signature/KeyInfo;
      15: astore        4
      17: aload         4
      19: ifnonnull     44
      22: new           #28                 // class org/apache/wss4j/common/ext/WSSecurityException
      25: dup
      26: getstatic     #29                 // Field org/apache/wss4j/common/ext/WSSecurityException$ErrorCode.FAILURE:Lorg/apache/wss4j/common/ext/WSSecurityException$ErrorCode;
      29: ldc           #140                // String invalidSAMLsecurity
      31: iconst_1
      32: anewarray     #31                 // class java/lang/Object
      35: dup
      36: iconst_0
      37: ldc           #141                // String cannot get certificate or key
      39: aastore
      40: invokespecial #33                 // Method org/apache/wss4j/common/ext/WSSecurityException."<init>":(Lorg/apache/wss4j/common/ext/WSSecurityException$ErrorCode;Ljava/lang/String;[Ljava/lang/Object;)V
      43: athrow
      44: aload         4
      46: invokeinterface #142,  1          // InterfaceMethod org/opensaml/xmlsec/signature/KeyInfo.getDOM:()Lorg/w3c/dom/Element;
      51: aload_1
      52: aload_2
      53: invokestatic  #143                // Method org/apache/wss4j/common/saml/SAMLUtil.getCredentialFromKeyInfo:(Lorg/w3c/dom/Element;Lorg/apache/wss4j/common/saml/SAMLKeyInfoProcessor;Lorg/apache/wss4j/common/crypto/Crypto;)Lorg/apache/wss4j/common/saml/SAMLKeyInfo;
      56: astore        5
      58: aload_0
      59: aload         5
      61: invokevirtual #144                // Method verifySignature:(Lorg/apache/wss4j/common/saml/SAMLKeyInfo;)V
      64: goto          77
      67: getstatic     #19                 // Field LOG:Lorg/slf4j/Logger;
      70: ldc           #145                // String SamlAssertionWrapper: no signature to validate
      72: invokeinterface #107,  2          // InterfaceMethod org/slf4j/Logger.debug:(Ljava/lang/String;)V
      77: return

  public void verifySignature(org.apache.wss4j.common.saml.SAMLKeyInfo) throws org.apache.wss4j.common.ext.WSSecurityException;
    Code:
       0: aload_0
       1: invokevirtual #138                // Method getSignature:()Lorg/opensaml/xmlsec/signature/Signature;
       4: astore_2
       5: aload_2
       6: ifnull        188
       9: aload_1
      10: ifnonnull     35
      13: new           #28                 // class org/apache/wss4j/common/ext/WSSecurityException
      16: dup
      17: getstatic     #29                 // Field org/apache/wss4j/common/ext/WSSecurityException$ErrorCode.FAILURE:Lorg/apache/wss4j/common/ext/WSSecurityException$ErrorCode;
      20: ldc           #140                // String invalidSAMLsecurity
      22: iconst_1
      23: anewarray     #31                 // class java/lang/Object
      26: dup
      27: iconst_0
      28: ldc           #141                // String cannot get certificate or key
      30: aastore
      31: invokespecial #33                 // Method org/apache/wss4j/common/ext/WSSecurityException."<init>":(Lorg/apache/wss4j/common/ext/WSSecurityException$ErrorCode;Ljava/lang/String;[Ljava/lang/Object;)V
      34: athrow
      35: aconst_null
      36: astore_3
      37: aload_1
      38: invokevirtual #146                // Method org/apache/wss4j/common/saml/SAMLKeyInfo.getCerts:()[Ljava/security/cert/X509Certificate;
      41: ifnull        61
      44: new           #125                // class org/opensaml/security/x509/BasicX509Credential
      47: dup
      48: aload_1
      49: invokevirtual #146                // Method org/apache/wss4j/common/saml/SAMLKeyInfo.getCerts:()[Ljava/security/cert/X509Certificate;
      52: iconst_0
      53: aaload
      54: invokespecial #147                // Method org/opensaml/security/x509/BasicX509Credential."<init>":(Ljava/security/cert/X509Certificate;)V
      57: astore_3
      58: goto          105
      61: aload_1
      62: invokevirtual #148                // Method org/apache/wss4j/common/saml/SAMLKeyInfo.getPublicKey:()Ljava/security/PublicKey;
      65: ifnull        83
      68: new           #149                // class org/opensaml/security/credential/BasicCredential
      71: dup
      72: aload_1
      73: invokevirtual #148                // Method org/apache/wss4j/common/saml/SAMLKeyInfo.getPublicKey:()Ljava/security/PublicKey;
      76: invokespecial #150                // Method org/opensaml/security/credential/BasicCredential."<init>":(Ljava/security/PublicKey;)V
      79: astore_3
      80: goto          105
      83: new           #28                 // class org/apache/wss4j/common/ext/WSSecurityException
      86: dup
      87: getstatic     #29                 // Field org/apache/wss4j/common/ext/WSSecurityException$ErrorCode.FAILURE:Lorg/apache/wss4j/common/ext/WSSecurityException$ErrorCode;
      90: ldc           #140                // String invalidSAMLsecurity
      92: iconst_1
      93: anewarray     #31                 // class java/lang/Object
      96: dup
      97: iconst_0
      98: ldc           #141                // String cannot get certificate or key
     100: aastore
     101: invokespecial #33                 // Method org/apache/wss4j/common/ext/WSSecurityException."<init>":(Lorg/apache/wss4j/common/ext/WSSecurityException$ErrorCode;Ljava/lang/String;[Ljava/lang/Object;)V
     104: athrow
     105: invokestatic  #151                // Method java/lang/Thread.currentThread:()Ljava/lang/Thread;
     108: invokevirtual #152                // Method java/lang/Thread.getContextClassLoader:()Ljava/lang/ClassLoader;
     111: astore        4
     113: invokestatic  #151                // Method java/lang/Thread.currentThread:()Ljava/lang/Thread;
     116: ldc_w         #153                // class org/opensaml/xmlsec/signature/support/SignerProvider
     119: invokevirtual #154                // Method java/lang/Class.getClassLoader:()Ljava/lang/ClassLoader;
     122: invokevirtual #155                // Method java/lang/Thread.setContextClassLoader:(Ljava/lang/ClassLoader;)V
     125: aload_2
     126: aload_3
     127: invokestatic  #156                // Method org/opensaml/xmlsec/signature/support/SignatureValidator.validate:(Lorg/opensaml/xmlsec/signature/Signature;Lorg/opensaml/security/credential/Credential;)V
     130: invokestatic  #151                // Method java/lang/Thread.currentThread:()Ljava/lang/Thread;
     133: aload         4
     135: invokevirtual #155                // Method java/lang/Thread.setContextClassLoader:(Ljava/lang/ClassLoader;)V
     138: goto          180
     141: astore        5
     143: new           #28                 // class org/apache/wss4j/common/ext/WSSecurityException
     146: dup
     147: getstatic     #29                 // Field org/apache/wss4j/common/ext/WSSecurityException$ErrorCode.FAILURE:Lorg/apache/wss4j/common/ext/WSSecurityException$ErrorCode;
     150: aload         5
     152: ldc           #30                 // String empty
     154: iconst_1
     155: anewarray     #31                 // class java/lang/Object
     158: dup
     159: iconst_0
     160: ldc           #158                // String SAML signature validation failed
     162: aastore
     163: invokespecial #137                // Method org/apache/wss4j/common/ext/WSSecurityException."<init>":(Lorg/apache/wss4j/common/ext/WSSecurityException$ErrorCode;Ljava/lang/Exception;Ljava/lang/String;[Ljava/lang/Object;)V
     166: athrow
     167: astore        6
     169: invokestatic  #151                // Method java/lang/Thread.currentThread:()Ljava/lang/Thread;
     172: aload         4
     174: invokevirtual #155                // Method java/lang/Thread.setContextClassLoader:(Ljava/lang/ClassLoader;)V
     177: aload         6
     179: athrow
     180: aload_0
     181: aload_1
     182: putfield      #159                // Field signatureKeyInfo:Lorg/apache/wss4j/common/saml/SAMLKeyInfo;
     185: goto          198
     188: getstatic     #19                 // Field LOG:Lorg/slf4j/Logger;
     191: ldc           #145                // String SamlAssertionWrapper: no signature to validate
     193: invokeinterface #107,  2          // InterfaceMethod org/slf4j/Logger.debug:(Ljava/lang/String;)V
     198: return
    Exception table:
       from    to  target type
         113   130   141   Class org/opensaml/xmlsec/signature/support/SignatureException
         113   130   167   any
         141   169   167   any

  public void validateSignatureAgainstProfile() throws org.apache.wss4j.common.ext.WSSecurityException;
    Code:
       0: aload_0
       1: invokevirtual #138                // Method getSignature:()Lorg/opensaml/xmlsec/signature/Signature;
       4: astore_1
       5: aload_1
       6: ifnull        49
       9: new           #160                // class org/opensaml/saml/security/impl/SAMLSignatureProfileValidator
      12: dup
      13: invokespecial #161                // Method org/opensaml/saml/security/impl/SAMLSignatureProfileValidator."<init>":()V
      16: astore_2
      17: aload_2
      18: aload_1
      19: invokevirtual #162                // Method org/opensaml/saml/security/impl/SAMLSignatureProfileValidator.validate:(Lorg/opensaml/xmlsec/signature/Signature;)V
      22: goto          49
      25: astore_3
      26: new           #28                 // class org/apache/wss4j/common/ext/WSSecurityException
      29: dup
      30: getstatic     #29                 // Field org/apache/wss4j/common/ext/WSSecurityException$ErrorCode.FAILURE:Lorg/apache/wss4j/common/ext/WSSecurityException$ErrorCode;
      33: aload_3
      34: ldc           #30                 // String empty
      36: iconst_1
      37: anewarray     #31                 // class java/lang/Object
      40: dup
      41: iconst_0
      42: ldc           #158                // String SAML signature validation failed
      44: aastore
      45: invokespecial #137                // Method org/apache/wss4j/common/ext/WSSecurityException."<init>":(Lorg/apache/wss4j/common/ext/WSSecurityException$ErrorCode;Ljava/lang/Exception;Ljava/lang/String;[Ljava/lang/Object;)V
      48: athrow
      49: return
    Exception table:
       from    to  target type
          17    22    25   Class org/opensaml/xmlsec/signature/support/SignatureException

  public void parseSubject(org.apache.wss4j.common.saml.SAMLKeyInfoProcessor, org.apache.wss4j.common.crypto.Crypto, javax.security.auth.callback.CallbackHandler) throws org.apache.wss4j.common.ext.WSSecurityException;
    Code:
       0: aload_0
       1: getfield      #16                 // Field samlVersion:Lorg/opensaml/saml/common/SAMLVersion;
       4: getstatic     #15                 // Field org/opensaml/saml/common/SAMLVersion.VERSION_11:Lorg/opensaml/saml/common/SAMLVersion;
       7: if_acmpne     30
      10: aload_0
      11: aload_0
      12: getfield      #2                  // Field samlObject:Lorg/opensaml/saml/common/SAMLObject;
      15: checkcast     #14                 // class org/opensaml/saml/saml1/core/Assertion
      18: aload_1
      19: aload_2
      20: aload_3
      21: invokestatic  #163                // Method org/apache/wss4j/common/saml/SAMLUtil.getCredentialFromSubject:(Lorg/opensaml/saml/saml1/core/Assertion;Lorg/apache/wss4j/common/saml/SAMLKeyInfoProcessor;Lorg/apache/wss4j/common/crypto/Crypto;Ljavax/security/auth/callback/CallbackHandler;)Lorg/apache/wss4j/common/saml/SAMLKeyInfo;
      24: putfield      #164                // Field subjectKeyInfo:Lorg/apache/wss4j/common/saml/SAMLKeyInfo;
      27: goto          57
      30: aload_0
      31: getfield      #16                 // Field samlVersion:Lorg/opensaml/saml/common/SAMLVersion;
      34: getstatic     #18                 // Field org/opensaml/saml/common/SAMLVersion.VERSION_20:Lorg/opensaml/saml/common/SAMLVersion;
      37: if_acmpne     57
      40: aload_0
      41: aload_0
      42: getfield      #2                  // Field samlObject:Lorg/opensaml/saml/common/SAMLObject;
      45: checkcast     #17                 // class org/opensaml/saml/saml2/core/Assertion
      48: aload_1
      49: aload_2
      50: aload_3
      51: invokestatic  #165                // Method org/apache/wss4j/common/saml/SAMLUtil.getCredentialFromSubject:(Lorg/opensaml/saml/saml2/core/Assertion;Lorg/apache/wss4j/common/saml/SAMLKeyInfoProcessor;Lorg/apache/wss4j/common/crypto/Crypto;Ljavax/security/auth/callback/CallbackHandler;)Lorg/apache/wss4j/common/saml/SAMLKeyInfo;
      54: putfield      #164                // Field subjectKeyInfo:Lorg/apache/wss4j/common/saml/SAMLKeyInfo;
      57: return

  public org.opensaml.saml.common.SAMLVersion getSamlVersion();
    Code:
       0: aload_0
       1: getfield      #16                 // Field samlVersion:Lorg/opensaml/saml/common/SAMLVersion;
       4: ifnonnull     78
       7: getstatic     #19                 // Field LOG:Lorg/slf4j/Logger;
      10: invokeinterface #105,  1          // InterfaceMethod org/slf4j/Logger.isDebugEnabled:()Z
      15: ifeq          28
      18: getstatic     #19                 // Field LOG:Lorg/slf4j/Logger;
      21: ldc           #166                // String The SAML version was null in getSamlVersion(). Recomputing SAML version...
      23: invokeinterface #107,  2          // InterfaceMethod org/slf4j/Logger.debug:(Ljava/lang/String;)V
      28: aload_0
      29: getfield      #2                  // Field samlObject:Lorg/opensaml/saml/common/SAMLObject;
      32: instanceof    #14                 // class org/opensaml/saml/saml1/core/Assertion
      35: ifeq          48
      38: aload_0
      39: getstatic     #15                 // Field org/opensaml/saml/common/SAMLVersion.VERSION_11:Lorg/opensaml/saml/common/SAMLVersion;
      42: putfield      #16                 // Field samlVersion:Lorg/opensaml/saml/common/SAMLVersion;
      45: goto          78
      48: aload_0
      49: getfield      #2                  // Field samlObject:Lorg/opensaml/saml/common/SAMLObject;
      52: instanceof    #17                 // class org/opensaml/saml/saml2/core/Assertion
      55: ifeq          68
      58: aload_0
      59: getstatic     #18                 // Field org/opensaml/saml/common/SAMLVersion.VERSION_20:Lorg/opensaml/saml/common/SAMLVersion;
      62: putfield      #16                 // Field samlVersion:Lorg/opensaml/saml/common/SAMLVersion;
      65: goto          78
      68: new           #167                // class java/lang/IllegalStateException
      71: dup
      72: ldc           #168                // String Could not determine the SAML version number. Check your configuration and try again.
      74: invokespecial #169                // Method java/lang/IllegalStateException."<init>":(Ljava/lang/String;)V
      77: athrow
      78: aload_0
      79: getfield      #16                 // Field samlVersion:Lorg/opensaml/saml/common/SAMLVersion;
      82: areturn

  public org.w3c.dom.Element getElement();
    Code:
       0: aload_0
       1: getfield      #36                 // Field assertionElement:Lorg/w3c/dom/Element;
       4: areturn

  public org.apache.wss4j.common.saml.SAMLKeyInfo getSignatureKeyInfo();
    Code:
       0: aload_0
       1: getfield      #159                // Field signatureKeyInfo:Lorg/apache/wss4j/common/saml/SAMLKeyInfo;
       4: areturn

  public org.apache.wss4j.common.saml.SAMLKeyInfo getSubjectKeyInfo();
    Code:
       0: aload_0
       1: getfield      #164                // Field subjectKeyInfo:Lorg/apache/wss4j/common/saml/SAMLKeyInfo;
       4: areturn

  public byte[] getSignatureValue() throws org.apache.wss4j.common.ext.WSSecurityException;
    Code:
       0: aconst_null
       1: astore_1
       2: aload_0
       3: getfield      #2                  // Field samlObject:Lorg/opensaml/saml/common/SAMLObject;
       6: instanceof    #90                 // class org/opensaml/saml/common/SignableSAMLObject
       9: ifeq          25
      12: aload_0
      13: getfield      #2                  // Field samlObject:Lorg/opensaml/saml/common/SAMLObject;
      16: checkcast     #90                 // class org/opensaml/saml/common/SignableSAMLObject
      19: invokeinterface #92,  1           // InterfaceMethod org/opensaml/saml/common/SignableSAMLObject.getSignature:()Lorg/opensaml/xmlsec/signature/Signature;
      24: astore_1
      25: aload_1
      26: ifnull        35
      29: aload_0
      30: aload_1
      31: invokespecial #170                // Method getSignatureValue:(Lorg/opensaml/xmlsec/signature/Signature;)[B
      34: areturn
      35: aconst_null
      36: areturn

  private byte[] getSignatureValue(org.opensaml.xmlsec.signature.Signature) throws org.apache.wss4j.common.ext.WSSecurityException;
    Code:
       0: aload_1
       1: invokeinterface #171,  1          // InterfaceMethod org/opensaml/xmlsec/signature/Signature.getDOM:()Lorg/w3c/dom/Element;
       6: astore_2
       7: aload_2
       8: ifnull        64
      11: aload_2
      12: invokeinterface #172,  1          // InterfaceMethod org/w3c/dom/Element.getFirstChild:()Lorg/w3c/dom/Node;
      17: invokestatic  #173                // Method org/apache/xml/security/utils/XMLUtils.getNextElement:(Lorg/w3c/dom/Node;)Lorg/w3c/dom/Element;
      20: astore_3
      21: aload_3
      22: ifnull        64
      25: aload_3
      26: invokeinterface #174,  1          // InterfaceMethod org/w3c/dom/Element.getNextSibling:()Lorg/w3c/dom/Node;
      31: invokestatic  #173                // Method org/apache/xml/security/utils/XMLUtils.getNextElement:(Lorg/w3c/dom/Node;)Lorg/w3c/dom/Element;
      34: astore        4
      36: aload         4
      38: ifnull        64
      41: aload         4
      43: invokestatic  #175                // Method org/apache/xml/security/utils/Base64.decode:(Lorg/w3c/dom/Element;)[B
      46: areturn
      47: astore        5
      49: new           #28                 // class org/apache/wss4j/common/ext/WSSecurityException
      52: dup
      53: getstatic     #29                 // Field org/apache/wss4j/common/ext/WSSecurityException$ErrorCode.FAILURE:Lorg/apache/wss4j/common/ext/WSSecurityException$ErrorCode;
      56: aload         5
      58: ldc           #140                // String invalidSAMLsecurity
      60: invokespecial #177                // Method org/apache/wss4j/common/ext/WSSecurityException."<init>":(Lorg/apache/wss4j/common/ext/WSSecurityException$ErrorCode;Ljava/lang/Exception;Ljava/lang/String;)V
      63: athrow
      64: aconst_null
      65: areturn
    Exception table:
       from    to  target type
          41    46    47   Class org/apache/xml/security/exceptions/Base64DecodingException

  public org.opensaml.xmlsec.signature.Signature getSignature() throws org.apache.wss4j.common.ext.WSSecurityException;
    Code:
       0: aload_0
       1: getfield      #2                  // Field samlObject:Lorg/opensaml/saml/common/SAMLObject;
       4: instanceof    #90                 // class org/opensaml/saml/common/SignableSAMLObject
       7: ifeq          23
      10: aload_0
      11: getfield      #2                  // Field samlObject:Lorg/opensaml/saml/common/SAMLObject;
      14: checkcast     #90                 // class org/opensaml/saml/common/SignableSAMLObject
      17: invokeinterface #92,  1           // InterfaceMethod org/opensaml/saml/common/SignableSAMLObject.getSignature:()Lorg/opensaml/xmlsec/signature/Signature;
      22: areturn
      23: aconst_null
      24: areturn

  public org.opensaml.saml.common.SAMLObject getSamlObject();
    Code:
       0: aload_0
       1: getfield      #2                  // Field samlObject:Lorg/opensaml/saml/common/SAMLObject;
       4: areturn

  public void checkConditions(int) throws org.apache.wss4j.common.ext.WSSecurityException;
    Code:
       0: aconst_null
       1: astore_2
       2: aconst_null
       3: astore_3
       4: aload_0
       5: invokevirtual #178                // Method getSamlVersion:()Lorg/opensaml/saml/common/SAMLVersion;
       8: getstatic     #18                 // Field org/opensaml/saml/common/SAMLVersion.VERSION_20:Lorg/opensaml/saml/common/SAMLVersion;
      11: invokevirtual #179                // Method java/lang/Object.equals:(Ljava/lang/Object;)Z
      14: ifeq          62
      17: aload_0
      18: invokevirtual #180                // Method getSaml2:()Lorg/opensaml/saml/saml2/core/Assertion;
      21: invokeinterface #181,  1          // InterfaceMethod org/opensaml/saml/saml2/core/Assertion.getConditions:()Lorg/opensaml/saml/saml2/core/Conditions;
      26: ifnull        62
      29: aload_0
      30: invokevirtual #180                // Method getSaml2:()Lorg/opensaml/saml/saml2/core/Assertion;
      33: invokeinterface #181,  1          // InterfaceMethod org/opensaml/saml/saml2/core/Assertion.getConditions:()Lorg/opensaml/saml/saml2/core/Conditions;
      38: invokeinterface #182,  1          // InterfaceMethod org/opensaml/saml/saml2/core/Conditions.getNotBefore:()Lorg/joda/time/DateTime;
      43: astore_2
      44: aload_0
      45: invokevirtual #180                // Method getSaml2:()Lorg/opensaml/saml/saml2/core/Assertion;
      48: invokeinterface #181,  1          // InterfaceMethod org/opensaml/saml/saml2/core/Assertion.getConditions:()Lorg/opensaml/saml/saml2/core/Conditions;
      53: invokeinterface #183,  1          // InterfaceMethod org/opensaml/saml/saml2/core/Conditions.getNotOnOrAfter:()Lorg/joda/time/DateTime;
      58: astore_3
      59: goto          117
      62: aload_0
      63: invokevirtual #178                // Method getSamlVersion:()Lorg/opensaml/saml/common/SAMLVersion;
      66: getstatic     #15                 // Field org/opensaml/saml/common/SAMLVersion.VERSION_11:Lorg/opensaml/saml/common/SAMLVersion;
      69: invokevirtual #179                // Method java/lang/Object.equals:(Ljava/lang/Object;)Z
      72: ifeq          117
      75: aload_0
      76: invokevirtual #184                // Method getSaml1:()Lorg/opensaml/saml/saml1/core/Assertion;
      79: invokeinterface #185,  1          // InterfaceMethod org/opensaml/saml/saml1/core/Assertion.getConditions:()Lorg/opensaml/saml/saml1/core/Conditions;
      84: ifnull        117
      87: aload_0
      88: invokevirtual #184                // Method getSaml1:()Lorg/opensaml/saml/saml1/core/Assertion;
      91: invokeinterface #185,  1          // InterfaceMethod org/opensaml/saml/saml1/core/Assertion.getConditions:()Lorg/opensaml/saml/saml1/core/Conditions;
      96: invokeinterface #186,  1          // InterfaceMethod org/opensaml/saml/saml1/core/Conditions.getNotBefore:()Lorg/joda/time/DateTime;
     101: astore_2
     102: aload_0
     103: invokevirtual #184                // Method getSaml1:()Lorg/opensaml/saml/saml1/core/Assertion;
     106: invokeinterface #185,  1          // InterfaceMethod org/opensaml/saml/saml1/core/Assertion.getConditions:()Lorg/opensaml/saml/saml1/core/Conditions;
     111: invokeinterface #187,  1          // InterfaceMethod org/opensaml/saml/saml1/core/Conditions.getNotOnOrAfter:()Lorg/joda/time/DateTime;
     116: astore_3
     117: aload_2
     118: ifnull        170
     121: new           #188                // class org/joda/time/DateTime
     124: dup
     125: invokespecial #189                // Method org/joda/time/DateTime."<init>":()V
     128: astore        4
     130: aload         4
     132: iload_1
     133: invokevirtual #190                // Method org/joda/time/DateTime.plusSeconds:(I)Lorg/joda/time/DateTime;
     136: astore        4
     138: aload_2
     139: aload         4
     141: invokevirtual #191                // Method org/joda/time/DateTime.isAfter:(Lorg/joda/time/ReadableInstant;)Z
     144: ifeq          170
     147: getstatic     #19                 // Field LOG:Lorg/slf4j/Logger;
     150: ldc           #192                // String SAML Token condition (Not Before) not met
     152: invokeinterface #107,  2          // InterfaceMethod org/slf4j/Logger.debug:(Ljava/lang/String;)V
     157: new           #28                 // class org/apache/wss4j/common/ext/WSSecurityException
     160: dup
     161: getstatic     #29                 // Field org/apache/wss4j/common/ext/WSSecurityException$ErrorCode.FAILURE:Lorg/apache/wss4j/common/ext/WSSecurityException$ErrorCode;
     164: ldc           #140                // String invalidSAMLsecurity
     166: invokespecial #193                // Method org/apache/wss4j/common/ext/WSSecurityException."<init>":(Lorg/apache/wss4j/common/ext/WSSecurityException$ErrorCode;Ljava/lang/String;)V
     169: athrow
     170: aload_3
     171: ifnull        204
     174: aload_3
     175: invokevirtual #194                // Method org/joda/time/DateTime.isBeforeNow:()Z
     178: ifeq          204
     181: getstatic     #19                 // Field LOG:Lorg/slf4j/Logger;
     184: ldc           #195                // String SAML Token condition (Not On Or After) not met
     186: invokeinterface #107,  2          // InterfaceMethod org/slf4j/Logger.debug:(Ljava/lang/String;)V
     191: new           #28                 // class org/apache/wss4j/common/ext/WSSecurityException
     194: dup
     195: getstatic     #29                 // Field org/apache/wss4j/common/ext/WSSecurityException$ErrorCode.FAILURE:Lorg/apache/wss4j/common/ext/WSSecurityException$ErrorCode;
     198: ldc           #140                // String invalidSAMLsecurity
     200: invokespecial #193                // Method org/apache/wss4j/common/ext/WSSecurityException."<init>":(Lorg/apache/wss4j/common/ext/WSSecurityException$ErrorCode;Ljava/lang/String;)V
     203: athrow
     204: return

  public void checkIssueInstant(int, int) throws org.apache.wss4j.common.ext.WSSecurityException;
    Code:
       0: aconst_null
       1: astore_3
       2: aconst_null
       3: astore        4
       5: aload_0
       6: invokevirtual #178                // Method getSamlVersion:()Lorg/opensaml/saml/common/SAMLVersion;
       9: getstatic     #18                 // Field org/opensaml/saml/common/SAMLVersion.VERSION_20:Lorg/opensaml/saml/common/SAMLVersion;
      12: invokevirtual #179                // Method java/lang/Object.equals:(Ljava/lang/Object;)Z
      15: ifeq          59
      18: aload_0
      19: invokevirtual #180                // Method getSaml2:()Lorg/opensaml/saml/saml2/core/Assertion;
      22: invokeinterface #181,  1          // InterfaceMethod org/opensaml/saml/saml2/core/Assertion.getConditions:()Lorg/opensaml/saml/saml2/core/Conditions;
      27: ifnull        59
      30: aload_0
      31: invokevirtual #180                // Method getSaml2:()Lorg/opensaml/saml/saml2/core/Assertion;
      34: invokeinterface #181,  1          // InterfaceMethod org/opensaml/saml/saml2/core/Assertion.getConditions:()Lorg/opensaml/saml/saml2/core/Conditions;
      39: invokeinterface #183,  1          // InterfaceMethod org/opensaml/saml/saml2/core/Conditions.getNotOnOrAfter:()Lorg/joda/time/DateTime;
      44: astore        4
      46: aload_0
      47: invokevirtual #180                // Method getSaml2:()Lorg/opensaml/saml/saml2/core/Assertion;
      50: invokeinterface #196,  1          // InterfaceMethod org/opensaml/saml/saml2/core/Assertion.getIssueInstant:()Lorg/joda/time/DateTime;
      55: astore_3
      56: goto          110
      59: aload_0
      60: invokevirtual #178                // Method getSamlVersion:()Lorg/opensaml/saml/common/SAMLVersion;
      63: getstatic     #15                 // Field org/opensaml/saml/common/SAMLVersion.VERSION_11:Lorg/opensaml/saml/common/SAMLVersion;
      66: invokevirtual #179                // Method java/lang/Object.equals:(Ljava/lang/Object;)Z
      69: ifeq          110
      72: aload_0
      73: invokevirtual #184                // Method getSaml1:()Lorg/opensaml/saml/saml1/core/Assertion;
      76: invokeinterface #185,  1          // InterfaceMethod org/opensaml/saml/saml1/core/Assertion.getConditions:()Lorg/opensaml/saml/saml1/core/Conditions;
      81: ifnull        110
      84: aload_0
      85: invokevirtual #184                // Method getSaml1:()Lorg/opensaml/saml/saml1/core/Assertion;
      88: invokeinterface #185,  1          // InterfaceMethod org/opensaml/saml/saml1/core/Assertion.getConditions:()Lorg/opensaml/saml/saml1/core/Conditions;
      93: invokeinterface #187,  1          // InterfaceMethod org/opensaml/saml/saml1/core/Conditions.getNotOnOrAfter:()Lorg/joda/time/DateTime;
      98: astore        4
     100: aload_0
     101: invokevirtual #184                // Method getSaml1:()Lorg/opensaml/saml/saml1/core/Assertion;
     104: invokeinterface #197,  1          // InterfaceMethod org/opensaml/saml/saml1/core/Assertion.getIssueInstant:()Lorg/joda/time/DateTime;
     109: astore_3
     110: aload_3
     111: ifnull        216
     114: new           #188                // class org/joda/time/DateTime
     117: dup
     118: invokespecial #189                // Method org/joda/time/DateTime."<init>":()V
     121: astore        5
     123: aload         5
     125: iload_1
     126: invokevirtual #190                // Method org/joda/time/DateTime.plusSeconds:(I)Lorg/joda/time/DateTime;
     129: astore        5
     131: aload_3
     132: aload         5
     134: invokevirtual #191                // Method org/joda/time/DateTime.isAfter:(Lorg/joda/time/ReadableInstant;)Z
     137: ifeq          163
     140: getstatic     #19                 // Field LOG:Lorg/slf4j/Logger;
     143: ldc           #198                // String SAML Token IssueInstant not met
     145: invokeinterface #107,  2          // InterfaceMethod org/slf4j/Logger.debug:(Ljava/lang/String;)V
     150: new           #28                 // class org/apache/wss4j/common/ext/WSSecurityException
     153: dup
     154: getstatic     #29                 // Field org/apache/wss4j/common/ext/WSSecurityException$ErrorCode.FAILURE:Lorg/apache/wss4j/common/ext/WSSecurityException$ErrorCode;
     157: ldc           #140                // String invalidSAMLsecurity
     159: invokespecial #193                // Method org/apache/wss4j/common/ext/WSSecurityException."<init>":(Lorg/apache/wss4j/common/ext/WSSecurityException$ErrorCode;Ljava/lang/String;)V
     162: athrow
     163: aload         4
     165: ifnonnull     216
     168: new           #188                // class org/joda/time/DateTime
     171: dup
     172: invokespecial #189                // Method org/joda/time/DateTime."<init>":()V
     175: astore        5
     177: aload         5
     179: iload_2
     180: invokevirtual #199                // Method org/joda/time/DateTime.minusSeconds:(I)Lorg/joda/time/DateTime;
     183: pop
     184: aload_3
     185: aload         5
     187: invokevirtual #200                // Method org/joda/time/DateTime.isBefore:(Lorg/joda/time/ReadableInstant;)Z
     190: ifeq          216
     193: getstatic     #19                 // Field LOG:Lorg/slf4j/Logger;
     196: ldc           #201                // String SAML Token IssueInstant not met. The assertion was created too long ago.
     198: invokeinterface #107,  2          // InterfaceMethod org/slf4j/Logger.debug:(Ljava/lang/String;)V
     203: new           #28                 // class org/apache/wss4j/common/ext/WSSecurityException
     206: dup
     207: getstatic     #29                 // Field org/apache/wss4j/common/ext/WSSecurityException$ErrorCode.FAILURE:Lorg/apache/wss4j/common/ext/WSSecurityException$ErrorCode;
     210: ldc           #140                // String invalidSAMLsecurity
     212: invokespecial #193                // Method org/apache/wss4j/common/ext/WSSecurityException."<init>":(Lorg/apache/wss4j/common/ext/WSSecurityException$ErrorCode;Ljava/lang/String;)V
     215: athrow
     216: return

  public void checkAudienceRestrictions(java.util.List<java.lang.String>) throws org.apache.wss4j.common.ext.WSSecurityException;
    Code:
       0: aload_1
       1: ifnull        13
       4: aload_1
       5: invokeinterface #202,  1          // InterfaceMethod java/util/List.isEmpty:()Z
      10: ifeq          14
      13: return
      14: aload_0
      15: invokevirtual #178                // Method getSamlVersion:()Lorg/opensaml/saml/common/SAMLVersion;
      18: getstatic     #18                 // Field org/opensaml/saml/common/SAMLVersion.VERSION_20:Lorg/opensaml/saml/common/SAMLVersion;
      21: invokevirtual #179                // Method java/lang/Object.equals:(Ljava/lang/Object;)Z
      24: ifeq          214
      27: aload_0
      28: invokevirtual #180                // Method getSaml2:()Lorg/opensaml/saml/saml2/core/Assertion;
      31: invokeinterface #181,  1          // InterfaceMethod org/opensaml/saml/saml2/core/Assertion.getConditions:()Lorg/opensaml/saml/saml2/core/Conditions;
      36: ifnull        214
      39: aload_0
      40: invokevirtual #180                // Method getSaml2:()Lorg/opensaml/saml/saml2/core/Assertion;
      43: invokeinterface #181,  1          // InterfaceMethod org/opensaml/saml/saml2/core/Assertion.getConditions:()Lorg/opensaml/saml/saml2/core/Conditions;
      48: astore_2
      49: aload_2
      50: ifnull        211
      53: aload_2
      54: invokeinterface #203,  1          // InterfaceMethod org/opensaml/saml/saml2/core/Conditions.getAudienceRestrictions:()Ljava/util/List;
      59: ifnull        211
      62: aload_2
      63: invokeinterface #203,  1          // InterfaceMethod org/opensaml/saml/saml2/core/Conditions.getAudienceRestrictions:()Ljava/util/List;
      68: invokeinterface #202,  1          // InterfaceMethod java/util/List.isEmpty:()Z
      73: ifne          211
      76: iconst_0
      77: istore_3
      78: aload_2
      79: invokeinterface #203,  1          // InterfaceMethod org/opensaml/saml/saml2/core/Conditions.getAudienceRestrictions:()Ljava/util/List;
      84: invokeinterface #59,  1           // InterfaceMethod java/util/List.iterator:()Ljava/util/Iterator;
      89: astore        4
      91: aload         4
      93: invokeinterface #60,  1           // InterfaceMethod java/util/Iterator.hasNext:()Z
      98: ifeq          194
     101: aload         4
     103: invokeinterface #61,  1           // InterfaceMethod java/util/Iterator.next:()Ljava/lang/Object;
     108: checkcast     #204                // class org/opensaml/saml/saml2/core/AudienceRestriction
     111: astore        5
     113: aload         5
     115: invokeinterface #205,  1          // InterfaceMethod org/opensaml/saml/saml2/core/AudienceRestriction.getAudiences:()Ljava/util/List;
     120: ifnull        191
     123: aload         5
     125: invokeinterface #205,  1          // InterfaceMethod org/opensaml/saml/saml2/core/AudienceRestriction.getAudiences:()Ljava/util/List;
     130: astore        6
     132: aload         6
     134: invokeinterface #59,  1           // InterfaceMethod java/util/List.iterator:()Ljava/util/Iterator;
     139: astore        7
     141: aload         7
     143: invokeinterface #60,  1           // InterfaceMethod java/util/Iterator.hasNext:()Z
     148: ifeq          191
     151: aload         7
     153: invokeinterface #61,  1           // InterfaceMethod java/util/Iterator.next:()Ljava/lang/Object;
     158: checkcast     #206                // class org/opensaml/saml/saml2/core/Audience
     161: astore        8
     163: aload         8
     165: invokeinterface #207,  1          // InterfaceMethod org/opensaml/saml/saml2/core/Audience.getAudienceURI:()Ljava/lang/String;
     170: astore        9
     172: aload_1
     173: aload         9
     175: invokeinterface #208,  2          // InterfaceMethod java/util/List.contains:(Ljava/lang/Object;)Z
     180: ifeq          188
     183: iconst_1
     184: istore_3
     185: goto          191
     188: goto          141
     191: goto          91
     194: iload_3
     195: ifne          211
     198: new           #28                 // class org/apache/wss4j/common/ext/WSSecurityException
     201: dup
     202: getstatic     #29                 // Field org/apache/wss4j/common/ext/WSSecurityException$ErrorCode.FAILURE:Lorg/apache/wss4j/common/ext/WSSecurityException$ErrorCode;
     205: ldc           #140                // String invalidSAMLsecurity
     207: invokespecial #193                // Method org/apache/wss4j/common/ext/WSSecurityException."<init>":(Lorg/apache/wss4j/common/ext/WSSecurityException$ErrorCode;Ljava/lang/String;)V
     210: athrow
     211: goto          411
     214: aload_0
     215: invokevirtual #178                // Method getSamlVersion:()Lorg/opensaml/saml/common/SAMLVersion;
     218: getstatic     #15                 // Field org/opensaml/saml/common/SAMLVersion.VERSION_11:Lorg/opensaml/saml/common/SAMLVersion;
     221: invokevirtual #179                // Method java/lang/Object.equals:(Ljava/lang/Object;)Z
     224: ifeq          411
     227: aload_0
     228: invokevirtual #184                // Method getSaml1:()Lorg/opensaml/saml/saml1/core/Assertion;
     231: invokeinterface #185,  1          // InterfaceMethod org/opensaml/saml/saml1/core/Assertion.getConditions:()Lorg/opensaml/saml/saml1/core/Conditions;
     236: ifnull        411
     239: aload_0
     240: invokevirtual #184                // Method getSaml1:()Lorg/opensaml/saml/saml1/core/Assertion;
     243: invokeinterface #185,  1          // InterfaceMethod org/opensaml/saml/saml1/core/Assertion.getConditions:()Lorg/opensaml/saml/saml1/core/Conditions;
     248: astore_2
     249: aload_2
     250: ifnull        411
     253: aload_2
     254: invokeinterface #209,  1          // InterfaceMethod org/opensaml/saml/saml1/core/Conditions.getAudienceRestrictionConditions:()Ljava/util/List;
     259: ifnull        411
     262: aload_2
     263: invokeinterface #209,  1          // InterfaceMethod org/opensaml/saml/saml1/core/Conditions.getAudienceRestrictionConditions:()Ljava/util/List;
     268: invokeinterface #202,  1          // InterfaceMethod java/util/List.isEmpty:()Z
     273: ifne          411
     276: iconst_0
     277: istore_3
     278: aload_2
     279: invokeinterface #209,  1          // InterfaceMethod org/opensaml/saml/saml1/core/Conditions.getAudienceRestrictionConditions:()Ljava/util/List;
     284: invokeinterface #59,  1           // InterfaceMethod java/util/List.iterator:()Ljava/util/Iterator;
     289: astore        4
     291: aload         4
     293: invokeinterface #60,  1           // InterfaceMethod java/util/Iterator.hasNext:()Z
     298: ifeq          394
     301: aload         4
     303: invokeinterface #61,  1           // InterfaceMethod java/util/Iterator.next:()Ljava/lang/Object;
     308: checkcast     #210                // class org/opensaml/saml/saml1/core/AudienceRestrictionCondition
     311: astore        5
     313: aload         5
     315: invokeinterface #211,  1          // InterfaceMethod org/opensaml/saml/saml1/core/AudienceRestrictionCondition.getAudiences:()Ljava/util/List;
     320: ifnull        391
     323: aload         5
     325: invokeinterface #211,  1          // InterfaceMethod org/opensaml/saml/saml1/core/AudienceRestrictionCondition.getAudiences:()Ljava/util/List;
     330: astore        6
     332: aload         6
     334: invokeinterface #59,  1           // InterfaceMethod java/util/List.iterator:()Ljava/util/Iterator;
     339: astore        7
     341: aload         7
     343: invokeinterface #60,  1           // InterfaceMethod java/util/Iterator.hasNext:()Z
     348: ifeq          391
     351: aload         7
     353: invokeinterface #61,  1           // InterfaceMethod java/util/Iterator.next:()Ljava/lang/Object;
     358: checkcast     #212                // class org/opensaml/saml/saml1/core/Audience
     361: astore        8
     363: aload         8
     365: invokeinterface #213,  1          // InterfaceMethod org/opensaml/saml/saml1/core/Audience.getUri:()Ljava/lang/String;
     370: astore        9
     372: aload_1
     373: aload         9
     375: invokeinterface #208,  2          // InterfaceMethod java/util/List.contains:(Ljava/lang/Object;)Z
     380: ifeq          388
     383: iconst_1
     384: istore_3
     385: goto          391
     388: goto          341
     391: goto          291
     394: iload_3
     395: ifne          411
     398: new           #28                 // class org/apache/wss4j/common/ext/WSSecurityException
     401: dup
     402: getstatic     #29                 // Field org/apache/wss4j/common/ext/WSSecurityException$ErrorCode.FAILURE:Lorg/apache/wss4j/common/ext/WSSecurityException$ErrorCode;
     405: ldc           #140                // String invalidSAMLsecurity
     407: invokespecial #193                // Method org/apache/wss4j/common/ext/WSSecurityException."<init>":(Lorg/apache/wss4j/common/ext/WSSecurityException$ErrorCode;Ljava/lang/String;)V
     410: athrow
     411: return

  public void checkAuthnStatements(int) throws org.apache.wss4j.common.ext.WSSecurityException;
    Code:
       0: aload_0
       1: invokevirtual #178                // Method getSamlVersion:()Lorg/opensaml/saml/common/SAMLVersion;
       4: getstatic     #18                 // Field org/opensaml/saml/common/SAMLVersion.VERSION_20:Lorg/opensaml/saml/common/SAMLVersion;
       7: invokevirtual #179                // Method java/lang/Object.equals:(Ljava/lang/Object;)Z
      10: ifeq          139
      13: aload_0
      14: invokevirtual #180                // Method getSaml2:()Lorg/opensaml/saml/saml2/core/Assertion;
      17: invokeinterface #214,  1          // InterfaceMethod org/opensaml/saml/saml2/core/Assertion.getAuthnStatements:()Ljava/util/List;
      22: ifnull        139
      25: aload_0
      26: invokevirtual #180                // Method getSaml2:()Lorg/opensaml/saml/saml2/core/Assertion;
      29: invokeinterface #214,  1          // InterfaceMethod org/opensaml/saml/saml2/core/Assertion.getAuthnStatements:()Ljava/util/List;
      34: astore_2
      35: aload_2
      36: invokeinterface #59,  1           // InterfaceMethod java/util/List.iterator:()Ljava/util/Iterator;
      41: astore_3
      42: aload_3
      43: invokeinterface #60,  1           // InterfaceMethod java/util/Iterator.hasNext:()Z
      48: ifeq          136
      51: aload_3
      52: invokeinterface #61,  1           // InterfaceMethod java/util/Iterator.next:()Ljava/lang/Object;
      57: checkcast     #215                // class org/opensaml/saml/saml2/core/AuthnStatement
      60: astore        4
      62: aload         4
      64: invokeinterface #216,  1          // InterfaceMethod org/opensaml/saml/saml2/core/AuthnStatement.getAuthnInstant:()Lorg/joda/time/DateTime;
      69: astore        5
      71: aload         4
      73: invokeinterface #217,  1          // InterfaceMethod org/opensaml/saml/saml2/core/AuthnStatement.getSessionNotOnOrAfter:()Lorg/joda/time/DateTime;
      78: astore        6
      80: aconst_null
      81: astore        7
      83: aload         4
      85: invokeinterface #218,  1          // InterfaceMethod org/opensaml/saml/saml2/core/AuthnStatement.getSubjectLocality:()Lorg/opensaml/saml/saml2/core/SubjectLocality;
      90: ifnull        122
      93: aload         4
      95: invokeinterface #218,  1          // InterfaceMethod org/opensaml/saml/saml2/core/AuthnStatement.getSubjectLocality:()Lorg/opensaml/saml/saml2/core/SubjectLocality;
     100: invokeinterface #219,  1          // InterfaceMethod org/opensaml/saml/saml2/core/SubjectLocality.getAddress:()Ljava/lang/String;
     105: ifnull        122
     108: aload         4
     110: invokeinterface #218,  1          // InterfaceMethod org/opensaml/saml/saml2/core/AuthnStatement.getSubjectLocality:()Lorg/opensaml/saml/saml2/core/SubjectLocality;
     115: invokeinterface #219,  1          // InterfaceMethod org/opensaml/saml/saml2/core/SubjectLocality.getAddress:()Ljava/lang/String;
     120: astore        7
     122: aload_0
     123: aload         5
     125: aload         6
     127: aload         7
     129: iload_1
     130: invokespecial #220                // Method validateAuthnStatement:(Lorg/joda/time/DateTime;Lorg/joda/time/DateTime;Ljava/lang/String;I)V
     133: goto          42
     136: goto          265
     139: aload_0
     140: invokevirtual #178                // Method getSamlVersion:()Lorg/opensaml/saml/common/SAMLVersion;
     143: getstatic     #15                 // Field org/opensaml/saml/common/SAMLVersion.VERSION_11:Lorg/opensaml/saml/common/SAMLVersion;
     146: invokevirtual #179                // Method java/lang/Object.equals:(Ljava/lang/Object;)Z
     149: ifeq          265
     152: aload_0
     153: invokevirtual #184                // Method getSaml1:()Lorg/opensaml/saml/saml1/core/Assertion;
     156: invokeinterface #80,  1           // InterfaceMethod org/opensaml/saml/saml1/core/Assertion.getAuthenticationStatements:()Ljava/util/List;
     161: ifnull        265
     164: aload_0
     165: invokevirtual #184                // Method getSaml1:()Lorg/opensaml/saml/saml1/core/Assertion;
     168: invokeinterface #80,  1           // InterfaceMethod org/opensaml/saml/saml1/core/Assertion.getAuthenticationStatements:()Ljava/util/List;
     173: astore_2
     174: aload_2
     175: invokeinterface #59,  1           // InterfaceMethod java/util/List.iterator:()Ljava/util/Iterator;
     180: astore_3
     181: aload_3
     182: invokeinterface #60,  1           // InterfaceMethod java/util/Iterator.hasNext:()Z
     187: ifeq          265
     190: aload_3
     191: invokeinterface #61,  1           // InterfaceMethod java/util/Iterator.next:()Ljava/lang/Object;
     196: checkcast     #65                 // class org/opensaml/saml/saml1/core/AuthenticationStatement
     199: astore        4
     201: aload         4
     203: invokeinterface #221,  1          // InterfaceMethod org/opensaml/saml/saml1/core/AuthenticationStatement.getAuthenticationInstant:()Lorg/joda/time/DateTime;
     208: astore        5
     210: aconst_null
     211: astore        6
     213: aload         4
     215: invokeinterface #222,  1          // InterfaceMethod org/opensaml/saml/saml1/core/AuthenticationStatement.getSubjectLocality:()Lorg/opensaml/saml/saml1/core/SubjectLocality;
     220: ifnull        252
     223: aload         4
     225: invokeinterface #222,  1          // InterfaceMethod org/opensaml/saml/saml1/core/AuthenticationStatement.getSubjectLocality:()Lorg/opensaml/saml/saml1/core/SubjectLocality;
     230: invokeinterface #223,  1          // InterfaceMethod org/opensaml/saml/saml1/core/SubjectLocality.getIPAddress:()Ljava/lang/String;
     235: ifnull        252
     238: aload         4
     240: invokeinterface #222,  1          // InterfaceMethod org/opensaml/saml/saml1/core/AuthenticationStatement.getSubjectLocality:()Lorg/opensaml/saml/saml1/core/SubjectLocality;
     245: invokeinterface #223,  1          // InterfaceMethod org/opensaml/saml/saml1/core/SubjectLocality.getIPAddress:()Ljava/lang/String;
     250: astore        6
     252: aload_0
     253: aload         5
     255: aconst_null
     256: aload         6
     258: iload_1
     259: invokespecial #220                // Method validateAuthnStatement:(Lorg/joda/time/DateTime;Lorg/joda/time/DateTime;Ljava/lang/String;I)V
     262: goto          181
     265: return

  private void validateAuthnStatement(org.joda.time.DateTime, org.joda.time.DateTime, java.lang.String, int) throws org.apache.wss4j.common.ext.WSSecurityException;
    Code:
       0: new           #188                // class org/joda/time/DateTime
       3: dup
       4: invokespecial #189                // Method org/joda/time/DateTime."<init>":()V
       7: astore        5
       9: aload         5
      11: iload         4
      13: invokevirtual #190                // Method org/joda/time/DateTime.plusSeconds:(I)Lorg/joda/time/DateTime;
      16: astore        5
      18: aload_1
      19: aload         5
      21: invokevirtual #191                // Method org/joda/time/DateTime.isAfter:(Lorg/joda/time/ReadableInstant;)Z
      24: ifeq          50
      27: getstatic     #19                 // Field LOG:Lorg/slf4j/Logger;
      30: ldc           #224                // String SAML Token AuthnInstant not met
      32: invokeinterface #107,  2          // InterfaceMethod org/slf4j/Logger.debug:(Ljava/lang/String;)V
      37: new           #28                 // class org/apache/wss4j/common/ext/WSSecurityException
      40: dup
      41: getstatic     #29                 // Field org/apache/wss4j/common/ext/WSSecurityException$ErrorCode.FAILURE:Lorg/apache/wss4j/common/ext/WSSecurityException$ErrorCode;
      44: ldc           #140                // String invalidSAMLsecurity
      46: invokespecial #193                // Method org/apache/wss4j/common/ext/WSSecurityException."<init>":(Lorg/apache/wss4j/common/ext/WSSecurityException$ErrorCode;Ljava/lang/String;)V
      49: athrow
      50: aload_2
      51: ifnull        84
      54: aload_2
      55: invokevirtual #194                // Method org/joda/time/DateTime.isBeforeNow:()Z
      58: ifeq          84
      61: getstatic     #19                 // Field LOG:Lorg/slf4j/Logger;
      64: ldc           #225                // String SAML Token SessionNotOnOrAfter not met
      66: invokeinterface #107,  2          // InterfaceMethod org/slf4j/Logger.debug:(Ljava/lang/String;)V
      71: new           #28                 // class org/apache/wss4j/common/ext/WSSecurityException
      74: dup
      75: getstatic     #29                 // Field org/apache/wss4j/common/ext/WSSecurityException$ErrorCode.FAILURE:Lorg/apache/wss4j/common/ext/WSSecurityException$ErrorCode;
      78: ldc           #140                // String invalidSAMLsecurity
      80: invokespecial #193                // Method org/apache/wss4j/common/ext/WSSecurityException."<init>":(Lorg/apache/wss4j/common/ext/WSSecurityException$ErrorCode;Ljava/lang/String;)V
      83: athrow
      84: aload_3
      85: ifnull        142
      88: aload_3
      89: invokestatic  #226                // Method org/apache/wss4j/common/util/InetAddressUtils.isIPv4Address:(Ljava/lang/String;)Z
      92: ifne          142
      95: aload_3
      96: invokestatic  #227                // Method org/apache/wss4j/common/util/InetAddressUtils.isIPv6Address:(Ljava/lang/String;)Z
      99: ifne          142
     102: getstatic     #19                 // Field LOG:Lorg/slf4j/Logger;
     105: new           #20                 // class java/lang/StringBuilder
     108: dup
     109: invokespecial #21                 // Method java/lang/StringBuilder."<init>":()V
     112: ldc           #228                // String SAML Token SubjectLocality address is not valid:
     114: invokevirtual #23                 // Method java/lang/StringBuilder.append:(Ljava/lang/String;)Ljava/lang/StringBuilder;
     117: aload_3
     118: invokevirtual #23                 // Method java/lang/StringBuilder.append:(Ljava/lang/String;)Ljava/lang/StringBuilder;
     121: invokevirtual #26                 // Method java/lang/StringBuilder.toString:()Ljava/lang/String;
     124: invokeinterface #107,  2          // InterfaceMethod org/slf4j/Logger.debug:(Ljava/lang/String;)V
     129: new           #28                 // class org/apache/wss4j/common/ext/WSSecurityException
     132: dup
     133: getstatic     #29                 // Field org/apache/wss4j/common/ext/WSSecurityException$ErrorCode.FAILURE:Lorg/apache/wss4j/common/ext/WSSecurityException$ErrorCode;
     136: ldc           #140                // String invalidSAMLsecurity
     138: invokespecial #193                // Method org/apache/wss4j/common/ext/WSSecurityException."<init>":(Lorg/apache/wss4j/common/ext/WSSecurityException$ErrorCode;Ljava/lang/String;)V
     141: athrow
     142: return

  private void parseElement(org.w3c.dom.Element) throws org.apache.wss4j.common.ext.WSSecurityException;
    Code:
       0: aload_1
       1: invokestatic  #229                // Method org/apache/wss4j/common/saml/OpenSAMLUtil.fromDom:(Lorg/w3c/dom/Element;)Lorg/opensaml/core/xml/XMLObject;
       4: astore_2
       5: aload_2
       6: instanceof    #14                 // class org/opensaml/saml/saml1/core/Assertion
       9: ifeq          30
      12: aload_0
      13: aload_2
      14: checkcast     #230                // class org/opensaml/saml/common/SAMLObject
      17: putfield      #2                  // Field samlObject:Lorg/opensaml/saml/common/SAMLObject;
      20: aload_0
      21: getstatic     #15                 // Field org/opensaml/saml/common/SAMLVersion.VERSION_11:Lorg/opensaml/saml/common/SAMLVersion;
      24: putfield      #16                 // Field samlVersion:Lorg/opensaml/saml/common/SAMLVersion;
      27: goto          96
      30: aload_2
      31: instanceof    #17                 // class org/opensaml/saml/saml2/core/Assertion
      34: ifeq          55
      37: aload_0
      38: aload_2
      39: checkcast     #230                // class org/opensaml/saml/common/SAMLObject
      42: putfield      #2                  // Field samlObject:Lorg/opensaml/saml/common/SAMLObject;
      45: aload_0
      46: getstatic     #18                 // Field org/opensaml/saml/common/SAMLVersion.VERSION_20:Lorg/opensaml/saml/common/SAMLVersion;
      49: putfield      #16                 // Field samlVersion:Lorg/opensaml/saml/common/SAMLVersion;
      52: goto          96
      55: getstatic     #19                 // Field LOG:Lorg/slf4j/Logger;
      58: new           #20                 // class java/lang/StringBuilder
      61: dup
      62: invokespecial #21                 // Method java/lang/StringBuilder."<init>":()V
      65: ldc           #22                 // String SamlAssertionWrapper: found unexpected type
      67: invokevirtual #23                 // Method java/lang/StringBuilder.append:(Ljava/lang/String;)Ljava/lang/StringBuilder;
      70: aload_2
      71: ifnull        84
      74: aload_2
      75: invokevirtual #24                 // Method java/lang/Object.getClass:()Ljava/lang/Class;
      78: invokevirtual #25                 // Method java/lang/Class.getName:()Ljava/lang/String;
      81: goto          85
      84: aload_2
      85: invokevirtual #231                // Method java/lang/StringBuilder.append:(Ljava/lang/Object;)Ljava/lang/StringBuilder;
      88: invokevirtual #26                 // Method java/lang/StringBuilder.toString:()Ljava/lang/String;
      91: invokeinterface #27,  2           // InterfaceMethod org/slf4j/Logger.error:(Ljava/lang/String;)V
      96: aload_0
      97: aload_1
      98: putfield      #36                 // Field assertionElement:Lorg/w3c/dom/Element;
     101: return

  private void parseCallback(org.apache.wss4j.common.saml.SAMLCallback) throws org.apache.wss4j.common.ext.WSSecurityException;
    Code:
       0: aload_0
       1: aload_1
       2: invokevirtual #232                // Method org/apache/wss4j/common/saml/SAMLCallback.getSamlVersion:()Lorg/opensaml/saml/common/SAMLVersion;
       5: putfield      #16                 // Field samlVersion:Lorg/opensaml/saml/common/SAMLVersion;
       8: aload_0
       9: getfield      #16                 // Field samlVersion:Lorg/opensaml/saml/common/SAMLVersion;
      12: ifnonnull     22
      15: aload_0
      16: getstatic     #18                 // Field org/opensaml/saml/common/SAMLVersion.VERSION_20:Lorg/opensaml/saml/common/SAMLVersion;
      19: putfield      #16                 // Field samlVersion:Lorg/opensaml/saml/common/SAMLVersion;
      22: aload_1
      23: invokevirtual #233                // Method org/apache/wss4j/common/saml/SAMLCallback.getIssuer:()Ljava/lang/String;
      26: astore_2
      27: aload_0
      28: getfield      #16                 // Field samlVersion:Lorg/opensaml/saml/common/SAMLVersion;
      31: getstatic     #15                 // Field org/opensaml/saml/common/SAMLVersion.VERSION_11:Lorg/opensaml/saml/common/SAMLVersion;
      34: invokevirtual #179                // Method java/lang/Object.equals:(Ljava/lang/Object;)Z
      37: ifeq          192
      40: aload_2
      41: invokestatic  #234                // Method org/apache/wss4j/common/saml/builder/SAML1ComponentBuilder.createSamlv1Assertion:(Ljava/lang/String;)Lorg/opensaml/saml/saml1/core/Assertion;
      44: astore_3
      45: aload_1
      46: invokevirtual #235                // Method org/apache/wss4j/common/saml/SAMLCallback.getAuthenticationStatementData:()Ljava/util/List;
      49: invokestatic  #236                // Method org/apache/wss4j/common/saml/builder/SAML1ComponentBuilder.createSamlv1AuthenticationStatement:(Ljava/util/List;)Ljava/util/List;
      52: astore        4
      54: aload_3
      55: invokeinterface #80,  1           // InterfaceMethod org/opensaml/saml/saml1/core/Assertion.getAuthenticationStatements:()Ljava/util/List;
      60: aload         4
      62: invokeinterface #79,  2           // InterfaceMethod java/util/List.addAll:(Ljava/util/Collection;)Z
      67: pop
      68: aload_1
      69: invokevirtual #237                // Method org/apache/wss4j/common/saml/SAMLCallback.getAttributeStatementData:()Ljava/util/List;
      72: invokestatic  #238                // Method org/apache/wss4j/common/saml/builder/SAML1ComponentBuilder.createSamlv1AttributeStatement:(Ljava/util/List;)Ljava/util/List;
      75: astore        5
      77: aload_3
      78: invokeinterface #81,  1           // InterfaceMethod org/opensaml/saml/saml1/core/Assertion.getAttributeStatements:()Ljava/util/List;
      83: aload         5
      85: invokeinterface #79,  2           // InterfaceMethod java/util/List.addAll:(Ljava/util/Collection;)Z
      90: pop
      91: aload_1
      92: invokevirtual #239                // Method org/apache/wss4j/common/saml/SAMLCallback.getAuthDecisionStatementData:()Ljava/util/List;
      95: invokestatic  #240                // Method org/apache/wss4j/common/saml/builder/SAML1ComponentBuilder.createSamlv1AuthorizationDecisionStatement:(Ljava/util/List;)Ljava/util/List;
      98: astore        6
     100: aload_3
     101: invokeinterface #82,  1           // InterfaceMethod org/opensaml/saml/saml1/core/Assertion.getAuthorizationDecisionStatements:()Ljava/util/List;
     106: aload         6
     108: invokeinterface #79,  2           // InterfaceMethod java/util/List.addAll:(Ljava/util/Collection;)Z
     113: pop
     114: aload_1
     115: invokevirtual #241                // Method org/apache/wss4j/common/saml/SAMLCallback.getConditions:()Lorg/apache/wss4j/common/saml/bean/ConditionsBean;
     118: invokestatic  #242                // Method org/apache/wss4j/common/saml/builder/SAML1ComponentBuilder.createSamlv1Conditions:(Lorg/apache/wss4j/common/saml/bean/ConditionsBean;)Lorg/opensaml/saml/saml1/core/Conditions;
     121: astore        7
     123: aload_3
     124: aload         7
     126: invokeinterface #243,  2          // InterfaceMethod org/opensaml/saml/saml1/core/Assertion.setConditions:(Lorg/opensaml/saml/saml1/core/Conditions;)V
     131: aload_1
     132: invokevirtual #244                // Method org/apache/wss4j/common/saml/SAMLCallback.getAdvice:()Lorg/apache/wss4j/common/saml/bean/AdviceBean;
     135: ifnull        155
     138: aload_1
     139: invokevirtual #244                // Method org/apache/wss4j/common/saml/SAMLCallback.getAdvice:()Lorg/apache/wss4j/common/saml/bean/AdviceBean;
     142: invokestatic  #245                // Method org/apache/wss4j/common/saml/builder/SAML1ComponentBuilder.createAdvice:(Lorg/apache/wss4j/common/saml/bean/AdviceBean;)Lorg/opensaml/saml/saml1/core/Advice;
     145: astore        8
     147: aload_3
     148: aload         8
     150: invokeinterface #246,  2          // InterfaceMethod org/opensaml/saml/saml1/core/Assertion.setAdvice:(Lorg/opensaml/saml/saml1/core/Advice;)V
     155: goto          184
     158: astore        4
     160: new           #28                 // class org/apache/wss4j/common/ext/WSSecurityException
     163: dup
     164: getstatic     #29                 // Field org/apache/wss4j/common/ext/WSSecurityException$ErrorCode.FAILURE:Lorg/apache/wss4j/common/ext/WSSecurityException$ErrorCode;
     167: aload         4
     169: ldc           #30                 // String empty
     171: iconst_1
     172: anewarray     #31                 // class java/lang/Object
     175: dup
     176: iconst_0
     177: ldc           #136                // String Error generating KeyInfo from signing credential
     179: aastore
     180: invokespecial #137                // Method org/apache/wss4j/common/ext/WSSecurityException."<init>":(Lorg/apache/wss4j/common/ext/WSSecurityException$ErrorCode;Ljava/lang/Exception;Ljava/lang/String;[Ljava/lang/Object;)V
     183: athrow
     184: aload_0
     185: aload_3
     186: putfield      #2                  // Field samlObject:Lorg/opensaml/saml/common/SAMLObject;
     189: goto          384
     192: aload_0
     193: getfield      #16                 // Field samlVersion:Lorg/opensaml/saml/common/SAMLVersion;
     196: getstatic     #18                 // Field org/opensaml/saml/common/SAMLVersion.VERSION_20:Lorg/opensaml/saml/common/SAMLVersion;
     199: invokevirtual #179                // Method java/lang/Object.equals:(Ljava/lang/Object;)Z
     202: ifeq          384
     205: invokestatic  #247                // Method org/apache/wss4j/common/saml/builder/SAML2ComponentBuilder.createAssertion:()Lorg/opensaml/saml/saml2/core/Assertion;
     208: astore_3
     209: aload_2
     210: invokestatic  #248                // Method org/apache/wss4j/common/saml/builder/SAML2ComponentBuilder.createIssuer:(Ljava/lang/String;)Lorg/opensaml/saml/saml2/core/Issuer;
     213: astore        4
     215: aload_1
     216: invokevirtual #235                // Method org/apache/wss4j/common/saml/SAMLCallback.getAuthenticationStatementData:()Ljava/util/List;
     219: invokestatic  #249                // Method org/apache/wss4j/common/saml/builder/SAML2ComponentBuilder.createAuthnStatement:(Ljava/util/List;)Ljava/util/List;
     222: astore        5
     224: aload_3
     225: invokeinterface #214,  1          // InterfaceMethod org/opensaml/saml/saml2/core/Assertion.getAuthnStatements:()Ljava/util/List;
     230: aload         5
     232: invokeinterface #79,  2           // InterfaceMethod java/util/List.addAll:(Ljava/util/Collection;)Z
     237: pop
     238: aload_1
     239: invokevirtual #237                // Method org/apache/wss4j/common/saml/SAMLCallback.getAttributeStatementData:()Ljava/util/List;
     242: invokestatic  #250                // Method org/apache/wss4j/common/saml/builder/SAML2ComponentBuilder.createAttributeStatement:(Ljava/util/List;)Ljava/util/List;
     245: astore        6
     247: aload_3
     248: invokeinterface #251,  1          // InterfaceMethod org/opensaml/saml/saml2/core/Assertion.getAttributeStatements:()Ljava/util/List;
     253: aload         6
     255: invokeinterface #79,  2           // InterfaceMethod java/util/List.addAll:(Ljava/util/Collection;)Z
     260: pop
     261: aload_1
     262: invokevirtual #239                // Method org/apache/wss4j/common/saml/SAMLCallback.getAuthDecisionStatementData:()Ljava/util/List;
     265: invokestatic  #252                // Method org/apache/wss4j/common/saml/builder/SAML2ComponentBuilder.createAuthorizationDecisionStatement:(Ljava/util/List;)Ljava/util/List;
     268: astore        7
     270: aload_3
     271: invokeinterface #253,  1          // InterfaceMethod org/opensaml/saml/saml2/core/Assertion.getAuthzDecisionStatements:()Ljava/util/List;
     276: aload         7
     278: invokeinterface #79,  2           // InterfaceMethod java/util/List.addAll:(Ljava/util/Collection;)Z
     283: pop
     284: aload_3
     285: aload         4
     287: invokeinterface #254,  2          // InterfaceMethod org/opensaml/saml/saml2/core/Assertion.setIssuer:(Lorg/opensaml/saml/saml2/core/Issuer;)V
     292: aload_1
     293: invokevirtual #255                // Method org/apache/wss4j/common/saml/SAMLCallback.getSubject:()Lorg/apache/wss4j/common/saml/bean/SubjectBean;
     296: invokestatic  #256                // Method org/apache/wss4j/common/saml/builder/SAML2ComponentBuilder.createSaml2Subject:(Lorg/apache/wss4j/common/saml/bean/SubjectBean;)Lorg/opensaml/saml/saml2/core/Subject;
     299: astore        8
     301: aload_3
     302: aload         8
     304: invokeinterface #257,  2          // InterfaceMethod org/opensaml/saml/saml2/core/Assertion.setSubject:(Lorg/opensaml/saml/saml2/core/Subject;)V
     309: goto          338
     312: astore        8
     314: new           #28                 // class org/apache/wss4j/common/ext/WSSecurityException
     317: dup
     318: getstatic     #29                 // Field org/apache/wss4j/common/ext/WSSecurityException$ErrorCode.FAILURE:Lorg/apache/wss4j/common/ext/WSSecurityException$ErrorCode;
     321: aload         8
     323: ldc           #30                 // String empty
     325: iconst_1
     326: anewarray     #31                 // class java/lang/Object
     329: dup
     330: iconst_0
     331: ldc           #136                // String Error generating KeyInfo from signing credential
     333: aastore
     334: invokespecial #137                // Method org/apache/wss4j/common/ext/WSSecurityException."<init>":(Lorg/apache/wss4j/common/ext/WSSecurityException$ErrorCode;Ljava/lang/Exception;Ljava/lang/String;[Ljava/lang/Object;)V
     337: athrow
     338: aload_1
     339: invokevirtual #241                // Method org/apache/wss4j/common/saml/SAMLCallback.getConditions:()Lorg/apache/wss4j/common/saml/bean/ConditionsBean;
     342: invokestatic  #258                // Method org/apache/wss4j/common/saml/builder/SAML2ComponentBuilder.createConditions:(Lorg/apache/wss4j/common/saml/bean/ConditionsBean;)Lorg/opensaml/saml/saml2/core/Conditions;
     345: astore        8
     347: aload_3
     348: aload         8
     350: invokeinterface #259,  2          // InterfaceMethod org/opensaml/saml/saml2/core/Assertion.setConditions:(Lorg/opensaml/saml/saml2/core/Conditions;)V
     355: aload_1
     356: invokevirtual #244                // Method org/apache/wss4j/common/saml/SAMLCallback.getAdvice:()Lorg/apache/wss4j/common/saml/bean/AdviceBean;
     359: ifnull        379
     362: aload_1
     363: invokevirtual #244                // Method org/apache/wss4j/common/saml/SAMLCallback.getAdvice:()Lorg/apache/wss4j/common/saml/bean/AdviceBean;
     366: invokestatic  #260                // Method org/apache/wss4j/common/saml/builder/SAML2ComponentBuilder.createAdvice:(Lorg/apache/wss4j/common/saml/bean/AdviceBean;)Lorg/opensaml/saml/saml2/core/Advice;
     369: astore        9
     371: aload_3
     372: aload         9
     374: invokeinterface #261,  2          // InterfaceMethod org/opensaml/saml/saml2/core/Assertion.setAdvice:(Lorg/opensaml/saml/saml2/core/Advice;)V
     379: aload_0
     380: aload_3
     381: putfield      #2                  // Field samlObject:Lorg/opensaml/saml/common/SAMLObject;
     384: return
    Exception table:
       from    to  target type
          45   155   158   Class org/opensaml/security/SecurityException
         292   309   312   Class org/opensaml/security/SecurityException

  static {};
    Code:
       0: ldc_w         #262                // class org/apache/wss4j/common/saml/SamlAssertionWrapper
       3: invokestatic  #263                // Method org/slf4j/LoggerFactory.getLogger:(Ljava/lang/Class;)Lorg/slf4j/Logger;
       6: putstatic     #19                 // Field LOG:Lorg/slf4j/Logger;
       9: return
}
