Compiled from "ConfigExtensions.kt"
public final class nz.co.trademe.konfigure.extensions.ConfigExtensionsKt {
  public static final java.lang.String getQualifiedGroup(nz.co.trademe.konfigure.api.ConfigRegistry);
    Code:
       0: aload_0
       1: ldc           #10                 // String <this>
       3: invokestatic  #16                 // Method kotlin/jvm/internal/Intrinsics.checkNotNullParameter:(Ljava/lang/Object;Ljava/lang/String;)V
       6: aload_0
       7: invokeinterface #22,  1           // InterfaceMethod nz/co/trademe/konfigure/api/ConfigRegistry.getParent:()Lnz/co/trademe/konfigure/api/ConfigRegistry;
      12: astore_1
      13: nop
      14: aload_1
      15: ifnonnull     22
      18: aconst_null
      19: goto          85
      22: aload_1
      23: invokestatic  #24                 // Method getQualifiedGroup:(Lnz/co/trademe/konfigure/api/ConfigRegistry;)Ljava/lang/String;
      26: ifnonnull     38
      29: aload_0
      30: invokeinterface #28,  1           // InterfaceMethod nz/co/trademe/konfigure/api/ConfigRegistry.getGroup:()Ljava/lang/String;
      35: goto          85
      38: aload_0
      39: invokeinterface #28,  1           // InterfaceMethod nz/co/trademe/konfigure/api/ConfigRegistry.getGroup:()Ljava/lang/String;
      44: ifnonnull     54
      47: aload_1
      48: invokestatic  #24                 // Method getQualifiedGroup:(Lnz/co/trademe/konfigure/api/ConfigRegistry;)Ljava/lang/String;
      51: goto          85
      54: new           #30                 // class java/lang/StringBuilder
      57: dup
      58: invokespecial #34                 // Method java/lang/StringBuilder."<init>":()V
      61: aload_1
      62: invokestatic  #24                 // Method getQualifiedGroup:(Lnz/co/trademe/konfigure/api/ConfigRegistry;)Ljava/lang/String;
      65: invokevirtual #38                 // Method java/lang/StringBuilder.append:(Ljava/lang/String;)Ljava/lang/StringBuilder;
      68: ldc           #40                 // String  -
      70: invokevirtual #38                 // Method java/lang/StringBuilder.append:(Ljava/lang/String;)Ljava/lang/StringBuilder;
      73: aload_0
      74: invokeinterface #28,  1           // InterfaceMethod nz/co/trademe/konfigure/api/ConfigRegistry.getGroup:()Ljava/lang/String;
      79: invokevirtual #38                 // Method java/lang/StringBuilder.append:(Ljava/lang/String;)Ljava/lang/StringBuilder;
      82: invokevirtual #43                 // Method java/lang/StringBuilder.toString:()Ljava/lang/String;
      85: areturn

  public static final <T> nz.co.trademe.konfigure.api.ConfigRegistrar<T> config(nz.co.trademe.konfigure.api.ConfigRegistry, java.lang.String, T, nz.co.trademe.konfigure.model.ConfigMetadata, kotlin.jvm.functions.Function1<? super kotlin.reflect.KProperty<?>, ? extends nz.co.trademe.konfigure.model.ConfigMetadata>);
    Code:
       0: aload_0
       1: ldc           #10                 // String <this>
       3: invokestatic  #16                 // Method kotlin/jvm/internal/Intrinsics.checkNotNullParameter:(Ljava/lang/Object;Ljava/lang/String;)V
       6: iconst_0
       7: istore        5
       9: new           #53                 // class nz/co/trademe/konfigure/api/ConfigRegistrar
      12: dup
      13: aload_1
      14: aload_2
      15: aload         4
      17: iconst_4
      18: ldc           #55                 // String T
      20: invokestatic  #59                 // Method kotlin/jvm/internal/Intrinsics.reifiedOperationMarker:(ILjava/lang/String;)V
      23: ldc           #4                  // class java/lang/Object
      25: invokestatic  #65                 // Method kotlin/jvm/internal/Reflection.getOrCreateKotlinClass:(Ljava/lang/Class;)Lkotlin/reflect/KClass;
      28: invokespecial #68                 // Method nz/co/trademe/konfigure/api/ConfigRegistrar."<init>":(Ljava/lang/String;Ljava/lang/Object;Lkotlin/jvm/functions/Function1;Lkotlin/reflect/KClass;)V
      31: areturn

  public static nz.co.trademe.konfigure.api.ConfigRegistrar config$default(nz.co.trademe.konfigure.api.ConfigRegistry, java.lang.String, java.lang.Object, nz.co.trademe.konfigure.model.ConfigMetadata, kotlin.jvm.functions.Function1, int, java.lang.Object);
    Code:
       0: iload         5
       2: iconst_1
       3: iand
       4: ifeq          9
       7: aconst_null
       8: astore_1
       9: iload         5
      11: iconst_2
      12: iand
      13: ifeq          18
      16: aconst_null
      17: astore_2
      18: iload         5
      20: iconst_4
      21: iand
      22: ifeq          27
      25: aconst_null
      26: astore_3
      27: iload         5
      29: bipush        8
      31: iand
      32: ifeq          57
      35: aload_3
      36: ifnull        53
      39: new           #83                 // class nz/co/trademe/konfigure/extensions/ConfigExtensionsKt$config$1
      42: dup
      43: aload_3
      44: invokespecial #86                 // Method nz/co/trademe/konfigure/extensions/ConfigExtensionsKt$config$1."<init>":(Lnz/co/trademe/konfigure/model/ConfigMetadata;)V
      47: checkcast     #88                 // class kotlin/jvm/functions/Function1
      50: goto          55
      53: nop
      54: aconst_null
      55: astore        4
      57: aload_0
      58: ldc           #10                 // String <this>
      60: invokestatic  #16                 // Method kotlin/jvm/internal/Intrinsics.checkNotNullParameter:(Ljava/lang/Object;Ljava/lang/String;)V
      63: iconst_0
      64: istore        5
      66: new           #53                 // class nz/co/trademe/konfigure/api/ConfigRegistrar
      69: dup
      70: aload_1
      71: aload_2
      72: aload         4
      74: iconst_4
      75: ldc           #55                 // String T
      77: invokestatic  #59                 // Method kotlin/jvm/internal/Intrinsics.reifiedOperationMarker:(ILjava/lang/String;)V
      80: ldc           #4                  // class java/lang/Object
      82: invokestatic  #65                 // Method kotlin/jvm/internal/Reflection.getOrCreateKotlinClass:(Ljava/lang/Class;)Lkotlin/reflect/KClass;
      85: invokespecial #68                 // Method nz/co/trademe/konfigure/api/ConfigRegistrar."<init>":(Ljava/lang/String;Ljava/lang/Object;Lkotlin/jvm/functions/Function1;Lkotlin/reflect/KClass;)V
      88: areturn
}
