Compiled from "BaseTerminalOperation.java"
public abstract class org.infinispan.stream.impl.termop.BaseTerminalOperation {
  protected final java.lang.Iterable<org.infinispan.stream.impl.intops.IntermediateOperation> intermediateOperations;

  protected transient java.util.function.Supplier<? extends java.util.stream.BaseStream<?, ?>> supplier;

  protected org.infinispan.stream.impl.termop.BaseTerminalOperation(java.lang.Iterable<org.infinispan.stream.impl.intops.IntermediateOperation>, java.util.function.Supplier<? extends java.util.stream.BaseStream<?, ?>>);
    Code:
       0: aload_0
       1: invokespecial #1                  // Method java/lang/Object."<init>":()V
       4: aload_0
       5: aload_1
       6: putfield      #2                  // Field intermediateOperations:Ljava/lang/Iterable;
       9: aload_0
      10: aload_2
      11: putfield      #3                  // Field supplier:Ljava/util/function/Supplier;
      14: return

  public java.lang.Iterable<org.infinispan.stream.impl.intops.IntermediateOperation> getIntermediateOperations();
    Code:
       0: aload_0
       1: getfield      #2                  // Field intermediateOperations:Ljava/lang/Iterable;
       4: areturn

  public void setSupplier(java.util.function.Supplier<? extends java.util.stream.Stream<?>>);
    Code:
       0: aload_0
       1: aload_1
       2: putfield      #3                  // Field supplier:Ljava/util/function/Supplier;
       5: return

  public void handleInjection(org.infinispan.factories.ComponentRegistry);
    Code:
       0: aload_0
       1: getfield      #2                  // Field intermediateOperations:Ljava/lang/Iterable;
       4: aload_1
       5: invokedynamic #4,  0              // InvokeDynamic #0:accept:(Lorg/infinispan/factories/ComponentRegistry;)Ljava/util/function/Consumer;
      10: invokeinterface #5,  2            // InterfaceMethod java/lang/Iterable.forEach:(Ljava/util/function/Consumer;)V
      15: return

  private static void lambda$handleInjection$70(org.infinispan.factories.ComponentRegistry, org.infinispan.stream.impl.intops.IntermediateOperation);
    Code:
       0: aload_1
       1: aload_0
       2: invokeinterface #6,  2            // InterfaceMethod org/infinispan/stream/impl/intops/IntermediateOperation.handleInjection:(Lorg/infinispan/factories/ComponentRegistry;)V
       7: return
}
