Compiled from "CompileStrategy.java"
class juzu.test.CompileStrategy$1 {
  static final int[] $SwitchMap$juzu$impl$fs$Change;

  static {};
    Code:
       0: invokestatic  #1                  // Method juzu/impl/fs/Change.values:()[Ljuzu/impl/fs/Change;
       3: arraylength
       4: newarray       int
       6: putstatic     #2                  // Field $SwitchMap$juzu$impl$fs$Change:[I
       9: getstatic     #2                  // Field $SwitchMap$juzu$impl$fs$Change:[I
      12: getstatic     #3                  // Field juzu/impl/fs/Change.REMOVE:Ljuzu/impl/fs/Change;
      15: invokevirtual #4                  // Method juzu/impl/fs/Change.ordinal:()I
      18: iconst_1
      19: iastore
      20: goto          24
      23: astore_0
      24: getstatic     #2                  // Field $SwitchMap$juzu$impl$fs$Change:[I
      27: getstatic     #6                  // Field juzu/impl/fs/Change.ADD:Ljuzu/impl/fs/Change;
      30: invokevirtual #4                  // Method juzu/impl/fs/Change.ordinal:()I
      33: iconst_2
      34: iastore
      35: goto          39
      38: astore_0
      39: getstatic     #2                  // Field $SwitchMap$juzu$impl$fs$Change:[I
      42: getstatic     #7                  // Field juzu/impl/fs/Change.UPDATE:Ljuzu/impl/fs/Change;
      45: invokevirtual #4                  // Method juzu/impl/fs/Change.ordinal:()I
      48: iconst_3
      49: iastore
      50: goto          54
      53: astore_0
      54: return
    Exception table:
       from    to  target type
           9    20    23   Class java/lang/NoSuchFieldError
          24    35    38   Class java/lang/NoSuchFieldError
          39    50    53   Class java/lang/NoSuchFieldError
}
