Compiled from "JavaCompilerProvider.java"
final class juzu.test.JavaCompilerProvider$1 extends juzu.test.JavaCompilerProvider {
  juzu.test.JavaCompilerProvider$1(java.lang.String, int);
    Code:
       0: aload_0
       1: aload_1
       2: iload_2
       3: aconst_null
       4: invokespecial #1                  // Method juzu/test/JavaCompilerProvider."<init>":(Ljava/lang/String;ILjuzu/test/JavaCompilerProvider$1;)V
       7: return

  public javax.tools.JavaCompiler get();
    Code:
       0: invokestatic  #2                  // Method javax/tools/ToolProvider.getSystemJavaCompiler:()Ljavax/tools/JavaCompiler;
       3: areturn

  public java.lang.Object get();
    Code:
       0: aload_0
       1: invokevirtual #3                  // Method get:()Ljavax/tools/JavaCompiler;
       4: areturn
}
