Compiled from "AnyEquivalence.java"
public final class org.infinispan.commons.equivalence.AnyEquivalence<T> implements org.infinispan.commons.equivalence.Equivalence<T> {
  private static org.infinispan.commons.equivalence.AnyEquivalence<java.lang.Object> OBJECT;

  public static org.infinispan.commons.equivalence.AnyEquivalence<java.lang.String> STRING;

  public static org.infinispan.commons.equivalence.AnyEquivalence<java.lang.Byte> BYTE;

  public static org.infinispan.commons.equivalence.AnyEquivalence<java.lang.Short> SHORT;

  public static org.infinispan.commons.equivalence.AnyEquivalence<java.lang.Integer> INT;

  public static org.infinispan.commons.equivalence.AnyEquivalence<java.lang.Long> LONG;

  public static org.infinispan.commons.equivalence.AnyEquivalence<java.lang.Double> DOUBLE;

  public static org.infinispan.commons.equivalence.AnyEquivalence<java.lang.Float> FLOAT;

  public static org.infinispan.commons.equivalence.AnyEquivalence<java.lang.Boolean> BOOLEAN;

  private org.infinispan.commons.equivalence.AnyEquivalence();
    Code:
       0: aload_0
       1: invokespecial #1                  // Method java/lang/Object."<init>":()V
       4: return

  public int hashCode(java.lang.Object);
    Code:
       0: aload_1
       1: ifnonnull     8
       4: iconst_0
       5: goto          12
       8: aload_1
       9: invokevirtual #2                  // Method java/lang/Object.hashCode:()I
      12: ireturn

  public boolean equals(T, java.lang.Object);
    Code:
       0: aload_1
       1: ifnull        16
       4: aload_1
       5: aload_2
       6: invokevirtual #3                  // Method java/lang/Object.equals:(Ljava/lang/Object;)Z
       9: ifeq          16
      12: iconst_1
      13: goto          17
      16: iconst_0
      17: ireturn

  public java.lang.String toString(java.lang.Object);
    Code:
       0: aload_1
       1: invokestatic  #4                  // Method java/lang/String.valueOf:(Ljava/lang/Object;)Ljava/lang/String;
       4: areturn

  public boolean isComparable(java.lang.Object);
    Code:
       0: aload_1
       1: instanceof    #5                  // class java/lang/Comparable
       4: ireturn

  public int compare(T, T);
    Code:
       0: aload_1
       1: checkcast     #5                  // class java/lang/Comparable
       4: aload_2
       5: invokeinterface #6,  2            // InterfaceMethod java/lang/Comparable.compareTo:(Ljava/lang/Object;)I
      10: ireturn

  public static <T> org.infinispan.commons.equivalence.AnyEquivalence<T> getInstance();
    Code:
       0: getstatic     #7                  // Field OBJECT:Lorg/infinispan/commons/equivalence/AnyEquivalence;
       3: areturn

  public static <T> org.infinispan.commons.equivalence.AnyEquivalence<T> getInstance(java.lang.Class<T>);
    Code:
       0: getstatic     #7                  // Field OBJECT:Lorg/infinispan/commons/equivalence/AnyEquivalence;
       3: areturn

  static {};
    Code:
       0: new           #8                  // class org/infinispan/commons/equivalence/AnyEquivalence
       3: dup
       4: invokespecial #9                  // Method "<init>":()V
       7: putstatic     #7                  // Field OBJECT:Lorg/infinispan/commons/equivalence/AnyEquivalence;
      10: ldc           #10                 // class java/lang/String
      12: invokestatic  #11                 // Method getInstance:(Ljava/lang/Class;)Lorg/infinispan/commons/equivalence/AnyEquivalence;
      15: putstatic     #12                 // Field STRING:Lorg/infinispan/commons/equivalence/AnyEquivalence;
      18: ldc           #13                 // class java/lang/Byte
      20: invokestatic  #11                 // Method getInstance:(Ljava/lang/Class;)Lorg/infinispan/commons/equivalence/AnyEquivalence;
      23: putstatic     #14                 // Field BYTE:Lorg/infinispan/commons/equivalence/AnyEquivalence;
      26: ldc           #15                 // class java/lang/Short
      28: invokestatic  #11                 // Method getInstance:(Ljava/lang/Class;)Lorg/infinispan/commons/equivalence/AnyEquivalence;
      31: putstatic     #16                 // Field SHORT:Lorg/infinispan/commons/equivalence/AnyEquivalence;
      34: ldc           #17                 // class java/lang/Integer
      36: invokestatic  #11                 // Method getInstance:(Ljava/lang/Class;)Lorg/infinispan/commons/equivalence/AnyEquivalence;
      39: putstatic     #18                 // Field INT:Lorg/infinispan/commons/equivalence/AnyEquivalence;
      42: ldc           #19                 // class java/lang/Long
      44: invokestatic  #11                 // Method getInstance:(Ljava/lang/Class;)Lorg/infinispan/commons/equivalence/AnyEquivalence;
      47: putstatic     #20                 // Field LONG:Lorg/infinispan/commons/equivalence/AnyEquivalence;
      50: ldc           #21                 // class java/lang/Double
      52: invokestatic  #11                 // Method getInstance:(Ljava/lang/Class;)Lorg/infinispan/commons/equivalence/AnyEquivalence;
      55: putstatic     #22                 // Field DOUBLE:Lorg/infinispan/commons/equivalence/AnyEquivalence;
      58: ldc           #23                 // class java/lang/Float
      60: invokestatic  #11                 // Method getInstance:(Ljava/lang/Class;)Lorg/infinispan/commons/equivalence/AnyEquivalence;
      63: putstatic     #24                 // Field FLOAT:Lorg/infinispan/commons/equivalence/AnyEquivalence;
      66: ldc           #25                 // class java/lang/Boolean
      68: invokestatic  #11                 // Method getInstance:(Ljava/lang/Class;)Lorg/infinispan/commons/equivalence/AnyEquivalence;
      71: putstatic     #26                 // Field BOOLEAN:Lorg/infinispan/commons/equivalence/AnyEquivalence;
      74: return
}
