Compiled from "ClassLoadingUtils.java"
public class org.jboss.as.ee.utils.ClassLoadingUtils {
  public static java.lang.Class<?> loadClass(java.lang.String, org.jboss.as.server.deployment.DeploymentUnit) throws java.lang.ClassNotFoundException;
    Code:
       0: aload_0
       1: aload_1
       2: getstatic     #1                  // Field org/jboss/as/server/deployment/Attachments.MODULE:Lorg/jboss/as/server/deployment/AttachmentKey;
       5: invokeinterface #2,  2            // InterfaceMethod org/jboss/as/server/deployment/DeploymentUnit.getAttachment:(Lorg/jboss/as/server/deployment/AttachmentKey;)Ljava/lang/Object;
      10: checkcast     #3                  // class org/jboss/modules/Module
      13: invokestatic  #4                  // Method loadClass:(Ljava/lang/String;Lorg/jboss/modules/Module;)Ljava/lang/Class;
      16: areturn

  public static java.lang.Class<?> loadClass(java.lang.String, org.jboss.modules.Module) throws java.lang.ClassNotFoundException;
    Code:
       0: invokestatic  #5                  // Method org/wildfly/security/manager/WildFlySecurityManager.getCurrentContextClassLoaderPrivileged:()Ljava/lang/ClassLoader;
       3: astore_2
       4: aload_1
       5: invokevirtual #6                  // Method org/jboss/modules/Module.getClassLoader:()Lorg/jboss/modules/ModuleClassLoader;
       8: invokestatic  #7                  // Method org/wildfly/security/manager/WildFlySecurityManager.setCurrentContextClassLoaderPrivileged:(Ljava/lang/ClassLoader;)Ljava/lang/ClassLoader;
      11: pop
      12: aload_0
      13: iconst_0
      14: aload_1
      15: invokevirtual #6                  // Method org/jboss/modules/Module.getClassLoader:()Lorg/jboss/modules/ModuleClassLoader;
      18: invokestatic  #8                  // Method java/lang/Class.forName:(Ljava/lang/String;ZLjava/lang/ClassLoader;)Ljava/lang/Class;
      21: astore_3
      22: aload_2
      23: invokestatic  #7                  // Method org/wildfly/security/manager/WildFlySecurityManager.setCurrentContextClassLoaderPrivileged:(Ljava/lang/ClassLoader;)Ljava/lang/ClassLoader;
      26: pop
      27: aload_3
      28: areturn
      29: astore        4
      31: aload_2
      32: invokestatic  #7                  // Method org/wildfly/security/manager/WildFlySecurityManager.setCurrentContextClassLoaderPrivileged:(Ljava/lang/ClassLoader;)Ljava/lang/ClassLoader;
      35: pop
      36: aload         4
      38: athrow
    Exception table:
       from    to  target type
           4    22    29   any
          29    31    29   any

  private org.jboss.as.ee.utils.ClassLoadingUtils();
    Code:
       0: aload_0
       1: invokespecial #9                  // Method java/lang/Object."<init>":()V
       4: return
}
