Compiled from "KClassImpl.kt"
final class kotlin.reflect.jvm.internal.KClassImpl$Data$objectInstance$2 extends kotlin.jvm.internal.Lambda implements kotlin.jvm.functions.Function0<T> {
  final kotlin.reflect.jvm.internal.KClassImpl<T>.Data this$0;

  final kotlin.reflect.jvm.internal.KClassImpl<T> this$1;

  kotlin.reflect.jvm.internal.KClassImpl$Data$objectInstance$2(kotlin.reflect.jvm.internal.KClassImpl<T>.Data, kotlin.reflect.jvm.internal.KClassImpl<T>);
    Code:
       0: aload_0
       1: aload_1
       2: putfield      #21                 // Field this$0:Lkotlin/reflect/jvm/internal/KClassImpl$Data;
       5: aload_0
       6: aload_2
       7: putfield      #22                 // Field this$1:Lkotlin/reflect/jvm/internal/KClassImpl;
      10: aload_0
      11: iconst_0
      12: invokespecial #29                 // Method kotlin/jvm/internal/Lambda."<init>":(I)V
      15: return

  public final T invoke();
    Code:
       0: aload_0
       1: getfield      #21                 // Field this$0:Lkotlin/reflect/jvm/internal/KClassImpl$Data;
       4: invokevirtual #31                 // Method kotlin/reflect/jvm/internal/KClassImpl$Data.getDescriptor:()Lkotlin/reflect/jvm/internal/impl/descriptors/ClassDescriptor;
       7: astore_1
       8: aload_1
       9: invokeinterface #34,  1           // InterfaceMethod kotlin/reflect/jvm/internal/impl/descriptors/ClassDescriptor.getKind:()Lkotlin/reflect/jvm/internal/impl/descriptors/ClassKind;
      14: getstatic     #24                 // Field kotlin/reflect/jvm/internal/impl/descriptors/ClassKind.OBJECT:Lkotlin/reflect/jvm/internal/impl/descriptors/ClassKind;
      17: if_acmpeq     22
      20: aconst_null
      21: areturn
      22: aload_1
      23: invokeinterface #36,  1           // InterfaceMethod kotlin/reflect/jvm/internal/impl/descriptors/ClassDescriptor.isCompanionObject:()Z
      28: ifeq          66
      31: getstatic     #23                 // Field kotlin/reflect/jvm/internal/impl/builtins/CompanionObjectMapping.INSTANCE:Lkotlin/reflect/jvm/internal/impl/builtins/CompanionObjectMapping;
      34: aload_1
      35: invokestatic  #32                 // Method kotlin/reflect/jvm/internal/impl/builtins/CompanionObjectMappingUtilsKt.isMappedIntrinsicCompanionObject:(Lkotlin/reflect/jvm/internal/impl/builtins/CompanionObjectMapping;Lkotlin/reflect/jvm/internal/impl/descriptors/ClassDescriptor;)Z
      38: ifne          66
      41: aload_0
      42: getfield      #22                 // Field this$1:Lkotlin/reflect/jvm/internal/KClassImpl;
      45: invokevirtual #30                 // Method kotlin/reflect/jvm/internal/KClassImpl.getJClass:()Ljava/lang/Class;
      48: invokevirtual #26                 // Method java/lang/Class.getEnclosingClass:()Ljava/lang/Class;
      51: aload_1
      52: invokeinterface #35,  1           // InterfaceMethod kotlin/reflect/jvm/internal/impl/descriptors/ClassDescriptor.getName:()Lkotlin/reflect/jvm/internal/impl/name/Name;
      57: invokevirtual #33                 // Method kotlin/reflect/jvm/internal/impl/name/Name.asString:()Ljava/lang/String;
      60: invokevirtual #25                 // Method java/lang/Class.getDeclaredField:(Ljava/lang/String;)Ljava/lang/reflect/Field;
      63: goto          78
      66: aload_0
      67: getfield      #22                 // Field this$1:Lkotlin/reflect/jvm/internal/KClassImpl;
      70: invokevirtual #30                 // Method kotlin/reflect/jvm/internal/KClassImpl.getJClass:()Ljava/lang/Class;
      73: ldc           #6                  // String INSTANCE
      75: invokevirtual #25                 // Method java/lang/Class.getDeclaredField:(Ljava/lang/String;)Ljava/lang/reflect/Field;
      78: astore_2
      79: aload_2
      80: aconst_null
      81: invokevirtual #27                 // Method java/lang/reflect/Field.get:(Ljava/lang/Object;)Ljava/lang/Object;
      84: dup
      85: ldc           #7                  // String null cannot be cast to non-null type T of kotlin.reflect.jvm.internal.KClassImpl
      87: invokestatic  #28                 // Method kotlin/jvm/internal/Intrinsics.checkNotNull:(Ljava/lang/Object;Ljava/lang/String;)V
      90: areturn
}
