Compiled from "KDeclarationContainerImpl.kt"
final class kotlin.reflect.jvm.internal.KDeclarationContainerImpl$findPropertyDescriptor$allMembers$1 extends kotlin.jvm.internal.Lambda implements kotlin.jvm.functions.Function1<kotlin.reflect.jvm.internal.impl.descriptors.PropertyDescriptor, java.lang.CharSequence> {
  public static final kotlin.reflect.jvm.internal.KDeclarationContainerImpl$findPropertyDescriptor$allMembers$1 INSTANCE;

  kotlin.reflect.jvm.internal.KDeclarationContainerImpl$findPropertyDescriptor$allMembers$1();
    Code:
       0: aload_0
       1: iconst_1
       2: invokespecial #27                 // Method kotlin/jvm/internal/Lambda."<init>":(I)V
       5: return

  public final java.lang.CharSequence invoke(kotlin.reflect.jvm.internal.impl.descriptors.PropertyDescriptor);
    Code:
       0: aload_1
       1: ldc           #7                  // String descriptor
       3: invokestatic  #26                 // Method kotlin/jvm/internal/Intrinsics.checkNotNullParameter:(Ljava/lang/Object;Ljava/lang/String;)V
       6: new           #9                  // class java/lang/StringBuilder
       9: dup
      10: invokespecial #23                 // Method java/lang/StringBuilder."<init>":()V
      13: getstatic     #22                 // Field kotlin/reflect/jvm/internal/impl/renderer/DescriptorRenderer.DEBUG_TEXT:Lkotlin/reflect/jvm/internal/impl/renderer/DescriptorRenderer;
      16: aload_1
      17: checkcast     #17                 // class kotlin/reflect/jvm/internal/impl/descriptors/DeclarationDescriptor
      20: invokevirtual #32                 // Method kotlin/reflect/jvm/internal/impl/renderer/DescriptorRenderer.render:(Lkotlin/reflect/jvm/internal/impl/descriptors/DeclarationDescriptor;)Ljava/lang/String;
      23: invokevirtual #24                 // Method java/lang/StringBuilder.append:(Ljava/lang/String;)Ljava/lang/StringBuilder;
      26: ldc           #6                  // String  |
      28: invokevirtual #24                 // Method java/lang/StringBuilder.append:(Ljava/lang/String;)Ljava/lang/StringBuilder;
      31: getstatic     #21                 // Field kotlin/reflect/jvm/internal/RuntimeTypeMapper.INSTANCE:Lkotlin/reflect/jvm/internal/RuntimeTypeMapper;
      34: aload_1
      35: invokevirtual #31                 // Method kotlin/reflect/jvm/internal/RuntimeTypeMapper.mapPropertySignature:(Lkotlin/reflect/jvm/internal/impl/descriptors/PropertyDescriptor;)Lkotlin/reflect/jvm/internal/JvmPropertySignature;
      38: invokevirtual #28                 // Method kotlin/reflect/jvm/internal/JvmPropertySignature.asString:()Ljava/lang/String;
      41: invokevirtual #24                 // Method java/lang/StringBuilder.append:(Ljava/lang/String;)Ljava/lang/StringBuilder;
      44: invokevirtual #25                 // Method java/lang/StringBuilder.toString:()Ljava/lang/String;
      47: checkcast     #8                  // class java/lang/CharSequence
      50: areturn

  public java.lang.Object invoke(java.lang.Object);
    Code:
       0: aload_0
       1: aload_1
       2: checkcast     #18                 // class kotlin/reflect/jvm/internal/impl/descriptors/PropertyDescriptor
       5: invokevirtual #30                 // Method invoke:(Lkotlin/reflect/jvm/internal/impl/descriptors/PropertyDescriptor;)Ljava/lang/CharSequence;
       8: areturn

  static {};
    Code:
       0: new           #15                 // class kotlin/reflect/jvm/internal/KDeclarationContainerImpl$findPropertyDescriptor$allMembers$1
       3: dup
       4: invokespecial #29                 // Method "<init>":()V
       7: putstatic     #20                 // Field INSTANCE:Lkotlin/reflect/jvm/internal/KDeclarationContainerImpl$findPropertyDescriptor$allMembers$1;
      10: return
}
