Compiled from "KProperty1Impl.kt"
final class kotlin.reflect.jvm.internal.KMutableProperty1Impl$_setter$1 extends kotlin.jvm.internal.Lambda implements kotlin.jvm.functions.Function0<kotlin.reflect.jvm.internal.KMutableProperty1Impl$Setter<T, V>> {
  final kotlin.reflect.jvm.internal.KMutableProperty1Impl<T, V> this$0;

  kotlin.reflect.jvm.internal.KMutableProperty1Impl$_setter$1(kotlin.reflect.jvm.internal.KMutableProperty1Impl<T, V>);
    Code:
       0: aload_0
       1: aload_1
       2: putfield      #11                 // Field this$0:Lkotlin/reflect/jvm/internal/KMutableProperty1Impl;
       5: aload_0
       6: iconst_0
       7: invokespecial #12                 // Method kotlin/jvm/internal/Lambda."<init>":(I)V
      10: return

  public final kotlin.reflect.jvm.internal.KMutableProperty1Impl$Setter<T, V> invoke();
    Code:
       0: new           #9                  // class kotlin/reflect/jvm/internal/KMutableProperty1Impl$Setter
       3: dup
       4: aload_0
       5: getfield      #11                 // Field this$0:Lkotlin/reflect/jvm/internal/KMutableProperty1Impl;
       8: invokespecial #13                 // Method kotlin/reflect/jvm/internal/KMutableProperty1Impl$Setter."<init>":(Lkotlin/reflect/jvm/internal/KMutableProperty1Impl;)V
      11: areturn

  public java.lang.Object invoke();
    Code:
       0: aload_0
       1: invokevirtual #14                 // Method invoke:()Lkotlin/reflect/jvm/internal/KMutableProperty1Impl$Setter;
       4: areturn
}
