Compiled from "StringLocaleConverter.java"
public class org.apache.commons.beanutils.locale.converters.StringLocaleConverter extends org.apache.commons.beanutils.locale.BaseLocaleConverter {
  private org.apache.commons.logging.Log log;

  static java.lang.Class class$org$apache$commons$beanutils$locale$converters$StringLocaleConverter;

  public org.apache.commons.beanutils.locale.converters.StringLocaleConverter();
    Code:
       0: aload_0
       1: iconst_0
       2: invokespecial #6                  // Method "<init>":(Z)V
       5: return

  public org.apache.commons.beanutils.locale.converters.StringLocaleConverter(boolean);
    Code:
       0: aload_0
       1: invokestatic  #7                  // Method java/util/Locale.getDefault:()Ljava/util/Locale;
       4: iload_1
       5: invokespecial #8                  // Method "<init>":(Ljava/util/Locale;Z)V
       8: return

  public org.apache.commons.beanutils.locale.converters.StringLocaleConverter(java.util.Locale);
    Code:
       0: aload_0
       1: aload_1
       2: iconst_0
       3: invokespecial #8                  // Method "<init>":(Ljava/util/Locale;Z)V
       6: return

  public org.apache.commons.beanutils.locale.converters.StringLocaleConverter(java.util.Locale, boolean);
    Code:
       0: aload_0
       1: aload_1
       2: aconst_null
       3: checkcast     #9                  // class java/lang/String
       6: iload_2
       7: invokespecial #10                 // Method "<init>":(Ljava/util/Locale;Ljava/lang/String;Z)V
      10: return

  public org.apache.commons.beanutils.locale.converters.StringLocaleConverter(java.util.Locale, java.lang.String);
    Code:
       0: aload_0
       1: aload_1
       2: aload_2
       3: iconst_0
       4: invokespecial #10                 // Method "<init>":(Ljava/util/Locale;Ljava/lang/String;Z)V
       7: return

  public org.apache.commons.beanutils.locale.converters.StringLocaleConverter(java.util.Locale, java.lang.String, boolean);
    Code:
       0: aload_0
       1: aload_1
       2: aload_2
       3: iload_3
       4: invokespecial #11                 // Method org/apache/commons/beanutils/locale/BaseLocaleConverter."<init>":(Ljava/util/Locale;Ljava/lang/String;Z)V
       7: aload_0
       8: getstatic     #12                 // Field class$org$apache$commons$beanutils$locale$converters$StringLocaleConverter:Ljava/lang/Class;
      11: ifnonnull     26
      14: ldc           #13                 // String org.apache.commons.beanutils.locale.converters.StringLocaleConverter
      16: invokestatic  #14                 // Method class$:(Ljava/lang/String;)Ljava/lang/Class;
      19: dup
      20: putstatic     #12                 // Field class$org$apache$commons$beanutils$locale$converters$StringLocaleConverter:Ljava/lang/Class;
      23: goto          29
      26: getstatic     #12                 // Field class$org$apache$commons$beanutils$locale$converters$StringLocaleConverter:Ljava/lang/Class;
      29: invokestatic  #15                 // Method org/apache/commons/logging/LogFactory.getLog:(Ljava/lang/Class;)Lorg/apache/commons/logging/Log;
      32: putfield      #16                 // Field log:Lorg/apache/commons/logging/Log;
      35: return

  public org.apache.commons.beanutils.locale.converters.StringLocaleConverter(java.lang.Object);
    Code:
       0: aload_0
       1: aload_1
       2: iconst_0
       3: invokespecial #17                 // Method "<init>":(Ljava/lang/Object;Z)V
       6: return

  public org.apache.commons.beanutils.locale.converters.StringLocaleConverter(java.lang.Object, boolean);
    Code:
       0: aload_0
       1: aload_1
       2: invokestatic  #7                  // Method java/util/Locale.getDefault:()Ljava/util/Locale;
       5: iload_2
       6: invokespecial #18                 // Method "<init>":(Ljava/lang/Object;Ljava/util/Locale;Z)V
       9: return

  public org.apache.commons.beanutils.locale.converters.StringLocaleConverter(java.lang.Object, java.util.Locale);
    Code:
       0: aload_0
       1: aload_1
       2: aload_2
       3: iconst_0
       4: invokespecial #18                 // Method "<init>":(Ljava/lang/Object;Ljava/util/Locale;Z)V
       7: return

  public org.apache.commons.beanutils.locale.converters.StringLocaleConverter(java.lang.Object, java.util.Locale, boolean);
    Code:
       0: aload_0
       1: aload_1
       2: aload_2
       3: aconst_null
       4: iload_3
       5: invokespecial #19                 // Method "<init>":(Ljava/lang/Object;Ljava/util/Locale;Ljava/lang/String;Z)V
       8: return

  public org.apache.commons.beanutils.locale.converters.StringLocaleConverter(java.lang.Object, java.util.Locale, java.lang.String);
    Code:
       0: aload_0
       1: aload_1
       2: aload_2
       3: aload_3
       4: iconst_0
       5: invokespecial #19                 // Method "<init>":(Ljava/lang/Object;Ljava/util/Locale;Ljava/lang/String;Z)V
       8: return

  public org.apache.commons.beanutils.locale.converters.StringLocaleConverter(java.lang.Object, java.util.Locale, java.lang.String, boolean);
    Code:
       0: aload_0
       1: aload_1
       2: aload_2
       3: aload_3
       4: iload         4
       6: invokespecial #20                 // Method org/apache/commons/beanutils/locale/BaseLocaleConverter."<init>":(Ljava/lang/Object;Ljava/util/Locale;Ljava/lang/String;Z)V
       9: aload_0
      10: getstatic     #12                 // Field class$org$apache$commons$beanutils$locale$converters$StringLocaleConverter:Ljava/lang/Class;
      13: ifnonnull     28
      16: ldc           #13                 // String org.apache.commons.beanutils.locale.converters.StringLocaleConverter
      18: invokestatic  #14                 // Method class$:(Ljava/lang/String;)Ljava/lang/Class;
      21: dup
      22: putstatic     #12                 // Field class$org$apache$commons$beanutils$locale$converters$StringLocaleConverter:Ljava/lang/Class;
      25: goto          31
      28: getstatic     #12                 // Field class$org$apache$commons$beanutils$locale$converters$StringLocaleConverter:Ljava/lang/Class;
      31: invokestatic  #15                 // Method org/apache/commons/logging/LogFactory.getLog:(Ljava/lang/Class;)Lorg/apache/commons/logging/Log;
      34: putfield      #16                 // Field log:Lorg/apache/commons/logging/Log;
      37: return

  protected java.lang.Object parse(java.lang.Object, java.lang.String) throws java.text.ParseException;
    Code:
       0: aconst_null
       1: astore_3
       2: aload_1
       3: instanceof    #21                 // class java/lang/Integer
       6: ifne          37
       9: aload_1
      10: instanceof    #22                 // class java/lang/Long
      13: ifne          37
      16: aload_1
      17: instanceof    #23                 // class java/math/BigInteger
      20: ifne          37
      23: aload_1
      24: instanceof    #24                 // class java/lang/Byte
      27: ifne          37
      30: aload_1
      31: instanceof    #25                 // class java/lang/Short
      34: ifeq          60
      37: aload_0
      38: aload_0
      39: getfield      #26                 // Field locale:Ljava/util/Locale;
      42: aload_2
      43: invokespecial #27                 // Method getDecimalFormat:(Ljava/util/Locale;Ljava/lang/String;)Ljava/text/DecimalFormat;
      46: aload_1
      47: checkcast     #28                 // class java/lang/Number
      50: invokevirtual #29                 // Method java/lang/Number.longValue:()J
      53: invokevirtual #30                 // Method java/text/DecimalFormat.format:(J)Ljava/lang/String;
      56: astore_3
      57: goto          140
      60: aload_1
      61: instanceof    #31                 // class java/lang/Double
      64: ifne          81
      67: aload_1
      68: instanceof    #32                 // class java/math/BigDecimal
      71: ifne          81
      74: aload_1
      75: instanceof    #33                 // class java/lang/Float
      78: ifeq          104
      81: aload_0
      82: aload_0
      83: getfield      #26                 // Field locale:Ljava/util/Locale;
      86: aload_2
      87: invokespecial #27                 // Method getDecimalFormat:(Ljava/util/Locale;Ljava/lang/String;)Ljava/text/DecimalFormat;
      90: aload_1
      91: checkcast     #28                 // class java/lang/Number
      94: invokevirtual #34                 // Method java/lang/Number.doubleValue:()D
      97: invokevirtual #35                 // Method java/text/DecimalFormat.format:(D)Ljava/lang/String;
     100: astore_3
     101: goto          140
     104: aload_1
     105: instanceof    #36                 // class java/util/Date
     108: ifeq          135
     111: new           #37                 // class java/text/SimpleDateFormat
     114: dup
     115: aload_2
     116: aload_0
     117: getfield      #26                 // Field locale:Ljava/util/Locale;
     120: invokespecial #38                 // Method java/text/SimpleDateFormat."<init>":(Ljava/lang/String;Ljava/util/Locale;)V
     123: astore        4
     125: aload         4
     127: aload_1
     128: invokevirtual #39                 // Method java/text/SimpleDateFormat.format:(Ljava/lang/Object;)Ljava/lang/String;
     131: astore_3
     132: goto          140
     135: aload_1
     136: invokevirtual #40                 // Method java/lang/Object.toString:()Ljava/lang/String;
     139: astore_3
     140: aload_3
     141: areturn

  private java.text.DecimalFormat getDecimalFormat(java.util.Locale, java.lang.String);
    Code:
       0: aload_1
       1: invokestatic  #41                 // Method java/text/NumberFormat.getInstance:(Ljava/util/Locale;)Ljava/text/NumberFormat;
       4: checkcast     #42                 // class java/text/DecimalFormat
       7: astore_3
       8: aload_2
       9: ifnull        35
      12: aload_0
      13: getfield      #43                 // Field locPattern:Z
      16: ifeq          27
      19: aload_3
      20: aload_2
      21: invokevirtual #44                 // Method java/text/DecimalFormat.applyLocalizedPattern:(Ljava/lang/String;)V
      24: goto          46
      27: aload_3
      28: aload_2
      29: invokevirtual #45                 // Method java/text/DecimalFormat.applyPattern:(Ljava/lang/String;)V
      32: goto          46
      35: aload_0
      36: getfield      #16                 // Field log:Lorg/apache/commons/logging/Log;
      39: ldc           #46                 // String No pattern provided, using default.
      41: invokeinterface #47,  2           // InterfaceMethod org/apache/commons/logging/Log.debug:(Ljava/lang/Object;)V
      46: aload_3
      47: areturn

  static java.lang.Class class$(java.lang.String);
    Code:
       0: aload_0
       1: invokestatic  #1                  // Method java/lang/Class.forName:(Ljava/lang/String;)Ljava/lang/Class;
       4: areturn
       5: astore_1
       6: new           #3                  // class java/lang/NoClassDefFoundError
       9: dup
      10: aload_1
      11: invokevirtual #4                  // Method java/lang/ClassNotFoundException.getMessage:()Ljava/lang/String;
      14: invokespecial #5                  // Method java/lang/NoClassDefFoundError."<init>":(Ljava/lang/String;)V
      17: athrow
    Exception table:
       from    to  target type
           0     4     5   Class java/lang/ClassNotFoundException
}
