Compiled from "ConcurrentLinkedHashMap.java"
final class org.apache.camel.com.googlecode.concurrentlinkedhashmap.ConcurrentLinkedHashMap$ValueIterator implements java.util.Iterator<V> {
  final java.util.Iterator<org.apache.camel.com.googlecode.concurrentlinkedhashmap.ConcurrentLinkedHashMap$Node<K, V>> iterator;

  org.apache.camel.com.googlecode.concurrentlinkedhashmap.ConcurrentLinkedHashMap$Node<K, V> current;

  final org.apache.camel.com.googlecode.concurrentlinkedhashmap.ConcurrentLinkedHashMap this$0;

  org.apache.camel.com.googlecode.concurrentlinkedhashmap.ConcurrentLinkedHashMap$ValueIterator(org.apache.camel.com.googlecode.concurrentlinkedhashmap.ConcurrentLinkedHashMap);
    Code:
       0: aload_0
       1: aload_1
       2: putfield      #26                 // Field this$0:Lorg/apache/camel/com/googlecode/concurrentlinkedhashmap/ConcurrentLinkedHashMap;
       5: aload_0
       6: invokespecial #29                 // Method java/lang/Object."<init>":()V
       9: aload_0
      10: aload_0
      11: getfield      #26                 // Field this$0:Lorg/apache/camel/com/googlecode/concurrentlinkedhashmap/ConcurrentLinkedHashMap;
      14: getfield      #33                 // Field org/apache/camel/com/googlecode/concurrentlinkedhashmap/ConcurrentLinkedHashMap.data:Ljava/util/concurrent/ConcurrentMap;
      17: invokeinterface #39,  1           // InterfaceMethod java/util/concurrent/ConcurrentMap.values:()Ljava/util/Collection;
      22: invokeinterface #44,  1           // InterfaceMethod java/util/Collection.iterator:()Ljava/util/Iterator;
      27: putfield      #46                 // Field iterator:Ljava/util/Iterator;
      30: return

  public boolean hasNext();
    Code:
       0: aload_0
       1: getfield      #46                 // Field iterator:Ljava/util/Iterator;
       4: invokeinterface #53,  1           // InterfaceMethod java/util/Iterator.hasNext:()Z
       9: ireturn

  public V next();
    Code:
       0: aload_0
       1: aload_0
       2: getfield      #46                 // Field iterator:Ljava/util/Iterator;
       5: invokeinterface #57,  1           // InterfaceMethod java/util/Iterator.next:()Ljava/lang/Object;
      10: checkcast     #10                 // class org/apache/camel/com/googlecode/concurrentlinkedhashmap/ConcurrentLinkedHashMap$Node
      13: putfield      #59                 // Field current:Lorg/apache/camel/com/googlecode/concurrentlinkedhashmap/ConcurrentLinkedHashMap$Node;
      16: aload_0
      17: getfield      #59                 // Field current:Lorg/apache/camel/com/googlecode/concurrentlinkedhashmap/ConcurrentLinkedHashMap$Node;
      20: invokevirtual #62                 // Method org/apache/camel/com/googlecode/concurrentlinkedhashmap/ConcurrentLinkedHashMap$Node.getValue:()Ljava/lang/Object;
      23: areturn

  public void remove();
    Code:
       0: aload_0
       1: getfield      #59                 // Field current:Lorg/apache/camel/com/googlecode/concurrentlinkedhashmap/ConcurrentLinkedHashMap$Node;
       4: ifnull        11
       7: iconst_1
       8: goto          12
      11: iconst_0
      12: invokestatic  #67                 // Method org/apache/camel/com/googlecode/concurrentlinkedhashmap/ConcurrentLinkedHashMap.checkState:(Z)V
      15: aload_0
      16: getfield      #26                 // Field this$0:Lorg/apache/camel/com/googlecode/concurrentlinkedhashmap/ConcurrentLinkedHashMap;
      19: aload_0
      20: getfield      #59                 // Field current:Lorg/apache/camel/com/googlecode/concurrentlinkedhashmap/ConcurrentLinkedHashMap$Node;
      23: getfield      #71                 // Field org/apache/camel/com/googlecode/concurrentlinkedhashmap/ConcurrentLinkedHashMap$Node.key:Ljava/lang/Object;
      26: invokevirtual #74                 // Method org/apache/camel/com/googlecode/concurrentlinkedhashmap/ConcurrentLinkedHashMap.remove:(Ljava/lang/Object;)Ljava/lang/Object;
      29: pop
      30: aload_0
      31: aconst_null
      32: putfield      #59                 // Field current:Lorg/apache/camel/com/googlecode/concurrentlinkedhashmap/ConcurrentLinkedHashMap$Node;
      35: return
}
