Compiled from "ScalaRunTime.scala"
public final class scala.runtime.ScalaRunTime$$anonfun$arrayToString$1$1 extends scala.runtime.AbstractFunction1<java.lang.Object, java.lang.String> implements scala.Serializable {
  public static final long serialVersionUID;

  public final java.lang.String apply(int);
    Code:
       0: ldc           #21                 // String ()
       2: areturn

  public final java.lang.Object apply(java.lang.Object);
    Code:
       0: aload_0
       1: aload_1
       2: invokestatic  #32                 // Method scala/runtime/BoxesRunTime.unboxToInt:(Ljava/lang/Object;)I
       5: invokevirtual #34                 // Method apply:(I)Ljava/lang/String;
       8: areturn

  public scala.runtime.ScalaRunTime$$anonfun$arrayToString$1$1();
    Code:
       0: aload_0
       1: invokespecial #40                 // Method scala/runtime/AbstractFunction1."<init>":()V
       4: return
}
