Compiled from "FileListRequestWrapper.java"
public class org.hpccsystems.ws.client.wrappers.gen.filespray.FileListRequestWrapper {
  protected java.lang.String local_netaddr;

  protected java.lang.String local_path;

  protected java.lang.String local_mask;

  protected java.lang.String local_oS;

  protected boolean local_directoryOnly;

  public org.hpccsystems.ws.client.wrappers.gen.filespray.FileListRequestWrapper();
    Code:
       0: aload_0
       1: invokespecial #1                  // Method java/lang/Object."<init>":()V
       4: return

  public org.hpccsystems.ws.client.wrappers.gen.filespray.FileListRequestWrapper(org.hpccsystems.ws.client.gen.axis2.filespray.v1_20.FileListRequest);
    Code:
       0: aload_0
       1: invokespecial #1                  // Method java/lang/Object."<init>":()V
       4: aload_0
       5: aload_1
       6: invokespecial #2                  // Method copy:(Lorg/hpccsystems/ws/client/gen/axis2/filespray/v1_20/FileListRequest;)V
       9: return

  public org.hpccsystems.ws.client.wrappers.gen.filespray.FileListRequestWrapper(java.lang.String, java.lang.String, java.lang.String, java.lang.String, boolean);
    Code:
       0: aload_0
       1: invokespecial #1                  // Method java/lang/Object."<init>":()V
       4: aload_0
       5: aload_1
       6: putfield      #3                  // Field local_netaddr:Ljava/lang/String;
       9: aload_0
      10: aload_2
      11: putfield      #4                  // Field local_path:Ljava/lang/String;
      14: aload_0
      15: aload_3
      16: putfield      #5                  // Field local_mask:Ljava/lang/String;
      19: aload_0
      20: aload         4
      22: putfield      #6                  // Field local_oS:Ljava/lang/String;
      25: aload_0
      26: iload         5
      28: putfield      #7                  // Field local_directoryOnly:Z
      31: return

  private void copy(org.hpccsystems.ws.client.gen.axis2.filespray.v1_20.FileListRequest);
    Code:
       0: aload_1
       1: ifnonnull     5
       4: return
       5: aload_0
       6: aload_1
       7: invokevirtual #8                  // Method org/hpccsystems/ws/client/gen/axis2/filespray/v1_20/FileListRequest.getNetaddr:()Ljava/lang/String;
      10: putfield      #3                  // Field local_netaddr:Ljava/lang/String;
      13: aload_0
      14: aload_1
      15: invokevirtual #9                  // Method org/hpccsystems/ws/client/gen/axis2/filespray/v1_20/FileListRequest.getPath:()Ljava/lang/String;
      18: putfield      #4                  // Field local_path:Ljava/lang/String;
      21: aload_0
      22: aload_1
      23: invokevirtual #10                 // Method org/hpccsystems/ws/client/gen/axis2/filespray/v1_20/FileListRequest.getMask:()Ljava/lang/String;
      26: putfield      #5                  // Field local_mask:Ljava/lang/String;
      29: aload_0
      30: aload_1
      31: invokevirtual #11                 // Method org/hpccsystems/ws/client/gen/axis2/filespray/v1_20/FileListRequest.getOS:()Ljava/lang/String;
      34: putfield      #6                  // Field local_oS:Ljava/lang/String;
      37: aload_0
      38: aload_1
      39: invokevirtual #12                 // Method org/hpccsystems/ws/client/gen/axis2/filespray/v1_20/FileListRequest.getDirectoryOnly:()Z
      42: putfield      #7                  // Field local_directoryOnly:Z
      45: return

  public java.lang.String toString();
    Code:
       0: new           #13                 // class java/lang/StringBuilder
       3: dup
       4: invokespecial #14                 // Method java/lang/StringBuilder."<init>":()V
       7: ldc           #15                 // String FileListRequestWrapper [netaddr =
       9: invokevirtual #16                 // Method java/lang/StringBuilder.append:(Ljava/lang/String;)Ljava/lang/StringBuilder;
      12: aload_0
      13: getfield      #3                  // Field local_netaddr:Ljava/lang/String;
      16: invokevirtual #16                 // Method java/lang/StringBuilder.append:(Ljava/lang/String;)Ljava/lang/StringBuilder;
      19: ldc           #17                 // String , path =
      21: invokevirtual #16                 // Method java/lang/StringBuilder.append:(Ljava/lang/String;)Ljava/lang/StringBuilder;
      24: aload_0
      25: getfield      #4                  // Field local_path:Ljava/lang/String;
      28: invokevirtual #16                 // Method java/lang/StringBuilder.append:(Ljava/lang/String;)Ljava/lang/StringBuilder;
      31: ldc           #18                 // String , mask =
      33: invokevirtual #16                 // Method java/lang/StringBuilder.append:(Ljava/lang/String;)Ljava/lang/StringBuilder;
      36: aload_0
      37: getfield      #5                  // Field local_mask:Ljava/lang/String;
      40: invokevirtual #16                 // Method java/lang/StringBuilder.append:(Ljava/lang/String;)Ljava/lang/StringBuilder;
      43: ldc           #19                 // String , oS =
      45: invokevirtual #16                 // Method java/lang/StringBuilder.append:(Ljava/lang/String;)Ljava/lang/StringBuilder;
      48: aload_0
      49: getfield      #6                  // Field local_oS:Ljava/lang/String;
      52: invokevirtual #16                 // Method java/lang/StringBuilder.append:(Ljava/lang/String;)Ljava/lang/StringBuilder;
      55: ldc           #20                 // String , directoryOnly =
      57: invokevirtual #16                 // Method java/lang/StringBuilder.append:(Ljava/lang/String;)Ljava/lang/StringBuilder;
      60: aload_0
      61: getfield      #7                  // Field local_directoryOnly:Z
      64: invokevirtual #21                 // Method java/lang/StringBuilder.append:(Z)Ljava/lang/StringBuilder;
      67: ldc           #22                 // String ]
      69: invokevirtual #16                 // Method java/lang/StringBuilder.append:(Ljava/lang/String;)Ljava/lang/StringBuilder;
      72: invokevirtual #23                 // Method java/lang/StringBuilder.toString:()Ljava/lang/String;
      75: areturn

  public org.hpccsystems.ws.client.gen.axis2.filespray.v1_20.FileListRequest getRaw();
    Code:
       0: new           #24                 // class org/hpccsystems/ws/client/gen/axis2/filespray/v1_20/FileListRequest
       3: dup
       4: invokespecial #25                 // Method org/hpccsystems/ws/client/gen/axis2/filespray/v1_20/FileListRequest."<init>":()V
       7: astore_1
       8: aload_1
       9: aload_0
      10: getfield      #3                  // Field local_netaddr:Ljava/lang/String;
      13: invokevirtual #26                 // Method org/hpccsystems/ws/client/gen/axis2/filespray/v1_20/FileListRequest.setNetaddr:(Ljava/lang/String;)V
      16: aload_1
      17: aload_0
      18: getfield      #4                  // Field local_path:Ljava/lang/String;
      21: invokevirtual #27                 // Method org/hpccsystems/ws/client/gen/axis2/filespray/v1_20/FileListRequest.setPath:(Ljava/lang/String;)V
      24: aload_1
      25: aload_0
      26: getfield      #5                  // Field local_mask:Ljava/lang/String;
      29: invokevirtual #28                 // Method org/hpccsystems/ws/client/gen/axis2/filespray/v1_20/FileListRequest.setMask:(Ljava/lang/String;)V
      32: aload_1
      33: aload_0
      34: getfield      #6                  // Field local_oS:Ljava/lang/String;
      37: invokevirtual #29                 // Method org/hpccsystems/ws/client/gen/axis2/filespray/v1_20/FileListRequest.setOS:(Ljava/lang/String;)V
      40: aload_1
      41: aload_0
      42: getfield      #7                  // Field local_directoryOnly:Z
      45: invokevirtual #30                 // Method org/hpccsystems/ws/client/gen/axis2/filespray/v1_20/FileListRequest.setDirectoryOnly:(Z)V
      48: aload_1
      49: areturn

  public void setNetaddr(java.lang.String);
    Code:
       0: aload_0
       1: aload_1
       2: putfield      #3                  // Field local_netaddr:Ljava/lang/String;
       5: return

  public java.lang.String getNetaddr();
    Code:
       0: aload_0
       1: getfield      #3                  // Field local_netaddr:Ljava/lang/String;
       4: areturn

  public void setPath(java.lang.String);
    Code:
       0: aload_0
       1: aload_1
       2: putfield      #4                  // Field local_path:Ljava/lang/String;
       5: return

  public java.lang.String getPath();
    Code:
       0: aload_0
       1: getfield      #4                  // Field local_path:Ljava/lang/String;
       4: areturn

  public void setMask(java.lang.String);
    Code:
       0: aload_0
       1: aload_1
       2: putfield      #5                  // Field local_mask:Ljava/lang/String;
       5: return

  public java.lang.String getMask();
    Code:
       0: aload_0
       1: getfield      #5                  // Field local_mask:Ljava/lang/String;
       4: areturn

  public void setOS(java.lang.String);
    Code:
       0: aload_0
       1: aload_1
       2: putfield      #6                  // Field local_oS:Ljava/lang/String;
       5: return

  public java.lang.String getOS();
    Code:
       0: aload_0
       1: getfield      #6                  // Field local_oS:Ljava/lang/String;
       4: areturn

  public void setDirectoryOnly(boolean);
    Code:
       0: aload_0
       1: iload_1
       2: putfield      #7                  // Field local_directoryOnly:Z
       5: return

  public boolean getDirectoryOnly();
    Code:
       0: aload_0
       1: getfield      #7                  // Field local_directoryOnly:Z
       4: ireturn
}
