Compiled from "SingleBody.java"
public abstract class org.apache.james.mime4j.message.SingleBody implements org.apache.james.mime4j.message.Body {
  private org.apache.james.mime4j.message.Entity parent;

  protected org.apache.james.mime4j.message.SingleBody();
    Code:
       0: aload_0
       1: invokespecial #1                  // Method java/lang/Object."<init>":()V
       4: aload_0
       5: aconst_null
       6: putfield      #2                  // Field parent:Lorg/apache/james/mime4j/message/Entity;
       9: return

  public org.apache.james.mime4j.message.Entity getParent();
    Code:
       0: aload_0
       1: getfield      #2                  // Field parent:Lorg/apache/james/mime4j/message/Entity;
       4: areturn

  public void setParent(org.apache.james.mime4j.message.Entity);
    Code:
       0: aload_0
       1: aload_1
       2: putfield      #2                  // Field parent:Lorg/apache/james/mime4j/message/Entity;
       5: return

  public abstract void writeTo(java.io.OutputStream) throws java.io.IOException;

  public org.apache.james.mime4j.message.SingleBody copy();
    Code:
       0: new           #3                  // class java/lang/UnsupportedOperationException
       3: dup
       4: invokespecial #4                  // Method java/lang/UnsupportedOperationException."<init>":()V
       7: athrow

  public void dispose();
    Code:
       0: return
}
