Compiled from "JMSBridgeAdd.java"
class org.wildfly.extension.messaging.activemq.jms.bridge.JMSBridgeAdd$1 implements org.jboss.as.controller.OperationStepHandler {
  final org.jboss.dmr.ModelNode val$model;

  final org.wildfly.extension.messaging.activemq.jms.bridge.JMSBridgeAdd this$0;

  org.wildfly.extension.messaging.activemq.jms.bridge.JMSBridgeAdd$1(org.wildfly.extension.messaging.activemq.jms.bridge.JMSBridgeAdd, org.jboss.dmr.ModelNode);
    Code:
       0: aload_0
       1: aload_1
       2: putfield      #2                  // Field this$0:Lorg/wildfly/extension/messaging/activemq/jms/bridge/JMSBridgeAdd;
       5: aload_0
       6: aload_2
       7: putfield      #3                  // Field val$model:Lorg/jboss/dmr/ModelNode;
      10: aload_0
      11: invokespecial #4                  // Method java/lang/Object."<init>":()V
      14: return

  public void execute(org.jboss.as.controller.OperationContext, org.jboss.dmr.ModelNode) throws org.jboss.as.controller.OperationFailedException;
    Code:
       0: aload_2
       1: ldc           #5                  // String address
       3: invokevirtual #6                  // Method org/jboss/dmr/ModelNode.get:(Ljava/lang/String;)Lorg/jboss/dmr/ModelNode;
       6: invokestatic  #7                  // Method org/jboss/as/controller/PathAddress.pathAddress:(Lorg/jboss/dmr/ModelNode;)Lorg/jboss/as/controller/PathAddress;
       9: astore_3
      10: aload_0
      11: getfield      #2                  // Field this$0:Lorg/wildfly/extension/messaging/activemq/jms/bridge/JMSBridgeAdd;
      14: getstatic     #8                  // Field org/wildfly/extension/messaging/activemq/jms/bridge/JMSBridgeDefinition.MODULE:Lorg/jboss/as/controller/SimpleAttributeDefinition;
      17: aload_1
      18: aload_0
      19: getfield      #3                  // Field val$model:Lorg/jboss/dmr/ModelNode;
      22: invokestatic  #9                  // Method org/wildfly/extension/messaging/activemq/jms/bridge/JMSBridgeAdd.access$000:(Lorg/wildfly/extension/messaging/activemq/jms/bridge/JMSBridgeAdd;Lorg/jboss/as/controller/SimpleAttributeDefinition;Lorg/jboss/as/controller/OperationContext;Lorg/jboss/dmr/ModelNode;)Ljava/lang/String;
      25: astore        4
      27: aload_0
      28: getfield      #2                  // Field this$0:Lorg/wildfly/extension/messaging/activemq/jms/bridge/JMSBridgeAdd;
      31: aload_1
      32: aload_0
      33: getfield      #3                  // Field val$model:Lorg/jboss/dmr/ModelNode;
      36: invokestatic  #10                 // Method org/wildfly/extension/messaging/activemq/jms/bridge/JMSBridgeAdd.access$100:(Lorg/wildfly/extension/messaging/activemq/jms/bridge/JMSBridgeAdd;Lorg/jboss/as/controller/OperationContext;Lorg/jboss/dmr/ModelNode;)Lorg/apache/activemq/artemis/jms/bridge/JMSBridge;
      39: astore        5
      41: aload_3
      42: invokevirtual #11                 // Method org/jboss/as/controller/PathAddress.getLastElement:()Lorg/jboss/as/controller/PathElement;
      45: invokevirtual #12                 // Method org/jboss/as/controller/PathElement.getValue:()Ljava/lang/String;
      48: astore        6
      50: new           #13                 // class org/wildfly/extension/messaging/activemq/jms/bridge/JMSBridgeService
      53: dup
      54: aload         4
      56: aload         6
      58: aload         5
      60: invokespecial #14                 // Method org/wildfly/extension/messaging/activemq/jms/bridge/JMSBridgeService."<init>":(Ljava/lang/String;Ljava/lang/String;Lorg/apache/activemq/artemis/jms/bridge/JMSBridge;)V
      63: astore        7
      65: aload         6
      67: invokestatic  #15                 // Method org/wildfly/extension/messaging/activemq/MessagingServices.getJMSBridgeServiceName:(Ljava/lang/String;)Lorg/jboss/msc/service/ServiceName;
      70: astore        8
      72: aload_1
      73: invokeinterface #16,  1           // InterfaceMethod org/jboss/as/controller/OperationContext.getServiceTarget:()Lorg/jboss/msc/service/ServiceTarget;
      78: aload         8
      80: aload         7
      82: invokeinterface #17,  3           // InterfaceMethod org/jboss/msc/service/ServiceTarget.addService:(Lorg/jboss/msc/service/ServiceName;Lorg/jboss/msc/service/Service;)Lorg/jboss/msc/service/ServiceBuilder;
      87: getstatic     #18                 // Field org/jboss/as/txn/service/TxnServices.JBOSS_TXN_TRANSACTION_MANAGER:Lorg/jboss/msc/service/ServiceName;
      90: invokeinterface #19,  2           // InterfaceMethod org/jboss/msc/service/ServiceBuilder.addDependency:(Lorg/jboss/msc/service/ServiceName;)Lorg/jboss/msc/service/ServiceBuilder;
      95: getstatic     #20                 // Field org/jboss/msc/service/ServiceController$Mode.ACTIVE:Lorg/jboss/msc/service/ServiceController$Mode;
      98: invokeinterface #21,  2           // InterfaceMethod org/jboss/msc/service/ServiceBuilder.setInitialMode:(Lorg/jboss/msc/service/ServiceController$Mode;)Lorg/jboss/msc/service/ServiceBuilder;
     103: astore        9
     105: aload         9
     107: aload         7
     109: invokevirtual #22                 // Method org/wildfly/extension/messaging/activemq/jms/bridge/JMSBridgeService.getExecutorInjector:()Lorg/jboss/msc/value/InjectedValue;
     112: iconst_0
     113: invokestatic  #23                 // Method org/jboss/as/server/Services.addServerExecutorDependency:(Lorg/jboss/msc/service/ServiceBuilder;Lorg/jboss/msc/inject/Injector;Z)Lorg/jboss/msc/service/ServiceBuilder;
     116: pop
     117: aload_0
     118: getfield      #2                  // Field this$0:Lorg/wildfly/extension/messaging/activemq/jms/bridge/JMSBridgeAdd;
     121: aload_0
     122: getfield      #3                  // Field val$model:Lorg/jboss/dmr/ModelNode;
     125: getstatic     #24                 // Field org/wildfly/extension/messaging/activemq/jms/bridge/JMSBridgeDefinition.SOURCE_CONTEXT:Lorg/jboss/as/controller/PropertiesAttributeDefinition;
     128: invokestatic  #25                 // Method org/wildfly/extension/messaging/activemq/jms/bridge/JMSBridgeAdd.access$200:(Lorg/wildfly/extension/messaging/activemq/jms/bridge/JMSBridgeAdd;Lorg/jboss/dmr/ModelNode;Lorg/jboss/as/controller/AttributeDefinition;)Z
     131: ifeq          168
     134: aload_0
     135: getfield      #2                  // Field this$0:Lorg/wildfly/extension/messaging/activemq/jms/bridge/JMSBridgeAdd;
     138: aload         9
     140: aload_0
     141: getfield      #3                  // Field val$model:Lorg/jboss/dmr/ModelNode;
     144: aload_1
     145: getstatic     #26                 // Field org/wildfly/extension/messaging/activemq/jms/bridge/JMSBridgeDefinition.SOURCE_CONNECTION_FACTORY:Lorg/jboss/as/controller/SimpleAttributeDefinition;
     148: invokestatic  #27                 // Method org/wildfly/extension/messaging/activemq/jms/bridge/JMSBridgeAdd.access$300:(Lorg/wildfly/extension/messaging/activemq/jms/bridge/JMSBridgeAdd;Lorg/jboss/msc/service/ServiceBuilder;Lorg/jboss/dmr/ModelNode;Lorg/jboss/as/controller/OperationContext;Lorg/jboss/as/controller/AttributeDefinition;)V
     151: aload_0
     152: getfield      #2                  // Field this$0:Lorg/wildfly/extension/messaging/activemq/jms/bridge/JMSBridgeAdd;
     155: aload         9
     157: aload_0
     158: getfield      #3                  // Field val$model:Lorg/jboss/dmr/ModelNode;
     161: aload_1
     162: getstatic     #28                 // Field org/wildfly/extension/messaging/activemq/jms/bridge/JMSBridgeDefinition.SOURCE_DESTINATION:Lorg/jboss/as/controller/SimpleAttributeDefinition;
     165: invokestatic  #27                 // Method org/wildfly/extension/messaging/activemq/jms/bridge/JMSBridgeAdd.access$300:(Lorg/wildfly/extension/messaging/activemq/jms/bridge/JMSBridgeAdd;Lorg/jboss/msc/service/ServiceBuilder;Lorg/jboss/dmr/ModelNode;Lorg/jboss/as/controller/OperationContext;Lorg/jboss/as/controller/AttributeDefinition;)V
     168: aload_0
     169: getfield      #2                  // Field this$0:Lorg/wildfly/extension/messaging/activemq/jms/bridge/JMSBridgeAdd;
     172: aload_0
     173: getfield      #3                  // Field val$model:Lorg/jboss/dmr/ModelNode;
     176: getstatic     #29                 // Field org/wildfly/extension/messaging/activemq/jms/bridge/JMSBridgeDefinition.TARGET_CONTEXT:Lorg/jboss/as/controller/PropertiesAttributeDefinition;
     179: invokestatic  #25                 // Method org/wildfly/extension/messaging/activemq/jms/bridge/JMSBridgeAdd.access$200:(Lorg/wildfly/extension/messaging/activemq/jms/bridge/JMSBridgeAdd;Lorg/jboss/dmr/ModelNode;Lorg/jboss/as/controller/AttributeDefinition;)Z
     182: ifeq          219
     185: aload_0
     186: getfield      #2                  // Field this$0:Lorg/wildfly/extension/messaging/activemq/jms/bridge/JMSBridgeAdd;
     189: aload         9
     191: aload_0
     192: getfield      #3                  // Field val$model:Lorg/jboss/dmr/ModelNode;
     195: aload_1
     196: getstatic     #30                 // Field org/wildfly/extension/messaging/activemq/jms/bridge/JMSBridgeDefinition.TARGET_CONNECTION_FACTORY:Lorg/jboss/as/controller/SimpleAttributeDefinition;
     199: invokestatic  #27                 // Method org/wildfly/extension/messaging/activemq/jms/bridge/JMSBridgeAdd.access$300:(Lorg/wildfly/extension/messaging/activemq/jms/bridge/JMSBridgeAdd;Lorg/jboss/msc/service/ServiceBuilder;Lorg/jboss/dmr/ModelNode;Lorg/jboss/as/controller/OperationContext;Lorg/jboss/as/controller/AttributeDefinition;)V
     202: aload_0
     203: getfield      #2                  // Field this$0:Lorg/wildfly/extension/messaging/activemq/jms/bridge/JMSBridgeAdd;
     206: aload         9
     208: aload_0
     209: getfield      #3                  // Field val$model:Lorg/jboss/dmr/ModelNode;
     212: aload_1
     213: getstatic     #31                 // Field org/wildfly/extension/messaging/activemq/jms/bridge/JMSBridgeDefinition.TARGET_DESTINATION:Lorg/jboss/as/controller/SimpleAttributeDefinition;
     216: invokestatic  #27                 // Method org/wildfly/extension/messaging/activemq/jms/bridge/JMSBridgeAdd.access$300:(Lorg/wildfly/extension/messaging/activemq/jms/bridge/JMSBridgeAdd;Lorg/jboss/msc/service/ServiceBuilder;Lorg/jboss/dmr/ModelNode;Lorg/jboss/as/controller/OperationContext;Lorg/jboss/as/controller/AttributeDefinition;)V
     219: aload         9
     221: invokeinterface #32,  1           // InterfaceMethod org/jboss/msc/service/ServiceBuilder.install:()Lorg/jboss/msc/service/ServiceController;
     226: pop
     227: aload_1
     228: getstatic     #33                 // Field org/jboss/as/controller/OperationContext$RollbackHandler.NOOP_ROLLBACK_HANDLER:Lorg/jboss/as/controller/OperationContext$RollbackHandler;
     231: invokeinterface #34,  2           // InterfaceMethod org/jboss/as/controller/OperationContext.completeStep:(Lorg/jboss/as/controller/OperationContext$RollbackHandler;)V
     236: return
}
