Compiled from "AbstractRestrictionCreatorPanel.java"
public abstract class org.protege.editor.owl.ui.editor.AbstractRestrictionCreatorPanel$CardinalityRestrictionCreator<P extends org.semanticweb.owlapi.model.OWLProperty, F extends org.semanticweb.owlapi.model.OWLObject> extends org.protege.editor.owl.ui.editor.AbstractRestrictionCreatorPanel<P, F>.RestrictionCreator<P, F> {
  final org.protege.editor.owl.ui.editor.AbstractRestrictionCreatorPanel this$0;

  protected org.protege.editor.owl.ui.editor.AbstractRestrictionCreatorPanel$CardinalityRestrictionCreator(org.protege.editor.owl.ui.editor.AbstractRestrictionCreatorPanel, java.lang.String);
    Code:
       0: aload_0
       1: aload_1
       2: putfield      #1                  // Field this$0:Lorg/protege/editor/owl/ui/editor/AbstractRestrictionCreatorPanel;
       5: aload_0
       6: aload_1
       7: aload_2
       8: invokespecial #2                  // Method org/protege/editor/owl/ui/editor/AbstractRestrictionCreatorPanel$RestrictionCreator."<init>":(Lorg/protege/editor/owl/ui/editor/AbstractRestrictionCreatorPanel;Ljava/lang/String;)V
      11: return

  public void createRestrictions(java.util.Set<P>, java.util.Set<F>, java.util.Set<org.semanticweb.owlapi.model.OWLClassExpression>);
    Code:
       0: aload_1
       1: invokeinterface #3,  1            // InterfaceMethod java/util/Set.iterator:()Ljava/util/Iterator;
       6: astore        4
       8: aload         4
      10: invokeinterface #4,  1            // InterfaceMethod java/util/Iterator.hasNext:()Z
      15: ifeq          97
      18: aload         4
      20: invokeinterface #5,  1            // InterfaceMethod java/util/Iterator.next:()Ljava/lang/Object;
      25: checkcast     #6                  // class org/semanticweb/owlapi/model/OWLProperty
      28: astore        5
      30: aload_2
      31: invokeinterface #3,  1            // InterfaceMethod java/util/Set.iterator:()Ljava/util/Iterator;
      36: astore        6
      38: aload         6
      40: invokeinterface #4,  1            // InterfaceMethod java/util/Iterator.hasNext:()Z
      45: ifeq          94
      48: aload         6
      50: invokeinterface #5,  1            // InterfaceMethod java/util/Iterator.next:()Ljava/lang/Object;
      55: checkcast     #7                  // class org/semanticweb/owlapi/model/OWLObject
      58: astore        7
      60: aload_3
      61: aload_0
      62: aload         5
      64: aload         7
      66: aload_0
      67: getfield      #1                  // Field this$0:Lorg/protege/editor/owl/ui/editor/AbstractRestrictionCreatorPanel;
      70: invokestatic  #8                  // Method org/protege/editor/owl/ui/editor/AbstractRestrictionCreatorPanel.access$000:(Lorg/protege/editor/owl/ui/editor/AbstractRestrictionCreatorPanel;)Ljavax/swing/JSpinner;
      73: invokevirtual #9                  // Method javax/swing/JSpinner.getValue:()Ljava/lang/Object;
      76: checkcast     #10                 // class java/lang/Integer
      79: invokevirtual #11                 // Method java/lang/Integer.intValue:()I
      82: invokevirtual #12                 // Method createRestriction:(Lorg/semanticweb/owlapi/model/OWLProperty;Lorg/semanticweb/owlapi/model/OWLObject;I)Lorg/semanticweb/owlapi/model/OWLClassExpression;
      85: invokeinterface #13,  2           // InterfaceMethod java/util/Set.add:(Ljava/lang/Object;)Z
      90: pop
      91: goto          38
      94: goto          8
      97: return

  public abstract org.semanticweb.owlapi.model.OWLClassExpression createRestriction(P, F, int);
}
