Compiled from "AESGCMKW.java"
public class com.nimbusds.jose.crypto.impl.AESGCMKW {
  public static com.nimbusds.jose.crypto.impl.AuthenticatedCipherText encryptCEK(javax.crypto.SecretKey, com.nimbusds.jose.util.Container<byte[]>, javax.crypto.SecretKey, java.security.Provider) throws com.nimbusds.jose.JOSEException;
    Code:
       0: aload_2
       1: aload_1
       2: aload_0
       3: invokeinterface #17,  1           // InterfaceMethod javax/crypto/SecretKey.getEncoded:()[B
       8: iconst_0
       9: newarray       byte
      11: aload_3
      12: invokestatic  #23                 // Method com/nimbusds/jose/crypto/impl/AESGCM.encrypt:(Ljavax/crypto/SecretKey;Lcom/nimbusds/jose/util/Container;[B[BLjava/security/Provider;)Lcom/nimbusds/jose/crypto/impl/AuthenticatedCipherText;
      15: areturn

  public static javax.crypto.SecretKey decryptCEK(javax.crypto.SecretKey, byte[], com.nimbusds.jose.crypto.impl.AuthenticatedCipherText, int, java.security.Provider) throws com.nimbusds.jose.JOSEException;
    Code:
       0: aload_0
       1: aload_1
       2: aload_2
       3: invokevirtual #38                 // Method com/nimbusds/jose/crypto/impl/AuthenticatedCipherText.getCipherText:()[B
       6: iconst_0
       7: newarray       byte
       9: aload_2
      10: invokevirtual #41                 // Method com/nimbusds/jose/crypto/impl/AuthenticatedCipherText.getAuthenticationTag:()[B
      13: aload         4
      15: invokestatic  #45                 // Method com/nimbusds/jose/crypto/impl/AESGCM.decrypt:(Ljavax/crypto/SecretKey;[B[B[B[BLjava/security/Provider;)[B
      18: astore        5
      20: aload         5
      22: invokestatic  #51                 // Method com/nimbusds/jose/util/ByteUtils.safeBitLength:([B)I
      25: iload_3
      26: if_icmpeq     69
      29: new           #53                 // class com/nimbusds/jose/KeyLengthException
      32: dup
      33: new           #55                 // class java/lang/StringBuilder
      36: dup
      37: invokespecial #59                 // Method java/lang/StringBuilder."<init>":()V
      40: ldc           #61                 // String CEK key length mismatch:
      42: invokevirtual #65                 // Method java/lang/StringBuilder.append:(Ljava/lang/String;)Ljava/lang/StringBuilder;
      45: aload         5
      47: invokestatic  #51                 // Method com/nimbusds/jose/util/ByteUtils.safeBitLength:([B)I
      50: invokevirtual #68                 // Method java/lang/StringBuilder.append:(I)Ljava/lang/StringBuilder;
      53: ldc           #70                 // String  !=
      55: invokevirtual #65                 // Method java/lang/StringBuilder.append:(Ljava/lang/String;)Ljava/lang/StringBuilder;
      58: iload_3
      59: invokevirtual #68                 // Method java/lang/StringBuilder.append:(I)Ljava/lang/StringBuilder;
      62: invokevirtual #74                 // Method java/lang/StringBuilder.toString:()Ljava/lang/String;
      65: invokespecial #77                 // Method com/nimbusds/jose/KeyLengthException."<init>":(Ljava/lang/String;)V
      68: athrow
      69: new           #81                 // class javax/crypto/spec/SecretKeySpec
      72: dup
      73: aload         5
      75: ldc           #83                 // String AES
      77: invokespecial #86                 // Method javax/crypto/spec/SecretKeySpec."<init>":([BLjava/lang/String;)V
      80: areturn

  private com.nimbusds.jose.crypto.impl.AESGCMKW();
    Code:
       0: aload_0
       1: invokespecial #92                 // Method java/lang/Object."<init>":()V
       4: return
}
