Compiled from "BaseJWEProvider.java"
abstract class com.nimbusds.jose.crypto.impl.BaseJWEProvider implements com.nimbusds.jose.JWEProvider {
  private final java.util.Set<com.nimbusds.jose.JWEAlgorithm> algs;

  private final java.util.Set<com.nimbusds.jose.EncryptionMethod> encs;

  private final com.nimbusds.jose.jca.JWEJCAContext jcaContext;

  public com.nimbusds.jose.crypto.impl.BaseJWEProvider(java.util.Set<com.nimbusds.jose.JWEAlgorithm>, java.util.Set<com.nimbusds.jose.EncryptionMethod>);
    Code:
       0: aload_0
       1: invokespecial #20                 // Method java/lang/Object."<init>":()V
       4: aload_0
       5: new           #22                 // class com/nimbusds/jose/jca/JWEJCAContext
       8: dup
       9: invokespecial #23                 // Method com/nimbusds/jose/jca/JWEJCAContext."<init>":()V
      12: putfield      #25                 // Field jcaContext:Lcom/nimbusds/jose/jca/JWEJCAContext;
      15: aload_1
      16: ifnonnull     29
      19: new           #27                 // class java/lang/IllegalArgumentException
      22: dup
      23: ldc           #29                 // String The supported JWE algorithm set must not be null
      25: invokespecial #32                 // Method java/lang/IllegalArgumentException."<init>":(Ljava/lang/String;)V
      28: athrow
      29: aload_0
      30: aload_1
      31: invokestatic  #40                 // Method java/util/Collections.unmodifiableSet:(Ljava/util/Set;)Ljava/util/Set;
      34: putfield      #42                 // Field algs:Ljava/util/Set;
      37: aload_2
      38: ifnonnull     51
      41: new           #27                 // class java/lang/IllegalArgumentException
      44: dup
      45: ldc           #44                 // String The supported encryption methods must not be null
      47: invokespecial #32                 // Method java/lang/IllegalArgumentException."<init>":(Ljava/lang/String;)V
      50: athrow
      51: aload_0
      52: aload_2
      53: putfield      #46                 // Field encs:Ljava/util/Set;
      56: return

  public java.util.Set<com.nimbusds.jose.JWEAlgorithm> supportedJWEAlgorithms();
    Code:
       0: aload_0
       1: getfield      #42                 // Field algs:Ljava/util/Set;
       4: areturn

  public java.util.Set<com.nimbusds.jose.EncryptionMethod> supportedEncryptionMethods();
    Code:
       0: aload_0
       1: getfield      #46                 // Field encs:Ljava/util/Set;
       4: areturn

  public com.nimbusds.jose.jca.JWEJCAContext getJCAContext();
    Code:
       0: aload_0
       1: getfield      #25                 // Field jcaContext:Lcom/nimbusds/jose/jca/JWEJCAContext;
       4: areturn

  public com.nimbusds.jose.jca.JCAContext getJCAContext();
    Code:
       0: aload_0
       1: invokevirtual #58                 // Method getJCAContext:()Lcom/nimbusds/jose/jca/JWEJCAContext;
       4: areturn
}
