Compiled from "MACProvider.java"
public abstract class com.nimbusds.jose.crypto.impl.MACProvider extends com.nimbusds.jose.crypto.impl.BaseJWSProvider {
  public static final java.util.Set<com.nimbusds.jose.JWSAlgorithm> SUPPORTED_ALGORITHMS;

  private final byte[] secret;

  protected static java.lang.String getJCAAlgorithmName(com.nimbusds.jose.JWSAlgorithm) throws com.nimbusds.jose.JOSEException;
    Code:
       0: aload_0
       1: getstatic     #20                 // Field com/nimbusds/jose/JWSAlgorithm.HS256:Lcom/nimbusds/jose/JWSAlgorithm;
       4: invokevirtual #24                 // Method com/nimbusds/jose/JWSAlgorithm.equals:(Ljava/lang/Object;)Z
       7: ifeq          13
      10: ldc           #26                 // String HMACSHA256
      12: areturn
      13: aload_0
      14: getstatic     #29                 // Field com/nimbusds/jose/JWSAlgorithm.HS384:Lcom/nimbusds/jose/JWSAlgorithm;
      17: invokevirtual #24                 // Method com/nimbusds/jose/JWSAlgorithm.equals:(Ljava/lang/Object;)Z
      20: ifeq          26
      23: ldc           #31                 // String HMACSHA384
      25: areturn
      26: aload_0
      27: getstatic     #34                 // Field com/nimbusds/jose/JWSAlgorithm.HS512:Lcom/nimbusds/jose/JWSAlgorithm;
      30: invokevirtual #24                 // Method com/nimbusds/jose/JWSAlgorithm.equals:(Ljava/lang/Object;)Z
      33: ifeq          39
      36: ldc           #36                 // String HMACSHA512
      38: areturn
      39: new           #14                 // class com/nimbusds/jose/JOSEException
      42: dup
      43: aload_0
      44: getstatic     #38                 // Field SUPPORTED_ALGORITHMS:Ljava/util/Set;
      47: invokestatic  #44                 // Method com/nimbusds/jose/crypto/impl/AlgorithmSupportMessage.unsupportedJWSAlgorithm:(Lcom/nimbusds/jose/JWSAlgorithm;Ljava/util/Collection;)Ljava/lang/String;
      50: invokespecial #48                 // Method com/nimbusds/jose/JOSEException."<init>":(Ljava/lang/String;)V
      53: athrow

  protected com.nimbusds.jose.crypto.impl.MACProvider(byte[], java.util.Set<com.nimbusds.jose.JWSAlgorithm>) throws com.nimbusds.jose.KeyLengthException;
    Code:
       0: aload_0
       1: aload_2
       2: invokespecial #56                 // Method com/nimbusds/jose/crypto/impl/BaseJWSProvider."<init>":(Ljava/util/Set;)V
       5: aload_1
       6: arraylength
       7: bipush        32
       9: if_icmpge     22
      12: new           #53                 // class com/nimbusds/jose/KeyLengthException
      15: dup
      16: ldc           #58                 // String The secret length must be at least 256 bits
      18: invokespecial #59                 // Method com/nimbusds/jose/KeyLengthException."<init>":(Ljava/lang/String;)V
      21: athrow
      22: aload_0
      23: aload_1
      24: putfield      #64                 // Field secret:[B
      27: return

  public javax.crypto.SecretKey getSecretKey();
    Code:
       0: new           #71                 // class javax/crypto/spec/SecretKeySpec
       3: dup
       4: aload_0
       5: getfield      #64                 // Field secret:[B
       8: ldc           #73                 // String MAC
      10: invokespecial #76                 // Method javax/crypto/spec/SecretKeySpec."<init>":([BLjava/lang/String;)V
      13: areturn

  public byte[] getSecret();
    Code:
       0: aload_0
       1: getfield      #64                 // Field secret:[B
       4: areturn

  public java.lang.String getSecretString();
    Code:
       0: new           #82                 // class java/lang/String
       3: dup
       4: aload_0
       5: getfield      #64                 // Field secret:[B
       8: getstatic     #88                 // Field com/nimbusds/jose/util/StandardCharset.UTF_8:Ljava/nio/charset/Charset;
      11: invokespecial #91                 // Method java/lang/String."<init>":([BLjava/nio/charset/Charset;)V
      14: areturn

  static {};
    Code:
       0: new           #95                 // class java/util/LinkedHashSet
       3: dup
       4: invokespecial #97                 // Method java/util/LinkedHashSet."<init>":()V
       7: astore_0
       8: aload_0
       9: getstatic     #20                 // Field com/nimbusds/jose/JWSAlgorithm.HS256:Lcom/nimbusds/jose/JWSAlgorithm;
      12: invokeinterface #100,  2          // InterfaceMethod java/util/Set.add:(Ljava/lang/Object;)Z
      17: pop
      18: aload_0
      19: getstatic     #29                 // Field com/nimbusds/jose/JWSAlgorithm.HS384:Lcom/nimbusds/jose/JWSAlgorithm;
      22: invokeinterface #100,  2          // InterfaceMethod java/util/Set.add:(Ljava/lang/Object;)Z
      27: pop
      28: aload_0
      29: getstatic     #34                 // Field com/nimbusds/jose/JWSAlgorithm.HS512:Lcom/nimbusds/jose/JWSAlgorithm;
      32: invokeinterface #100,  2          // InterfaceMethod java/util/Set.add:(Ljava/lang/Object;)Z
      37: pop
      38: aload_0
      39: invokestatic  #106                // Method java/util/Collections.unmodifiableSet:(Ljava/util/Set;)Ljava/util/Set;
      42: putstatic     #38                 // Field SUPPORTED_ALGORITHMS:Ljava/util/Set;
      45: return
}
