Compiled from "Enumerated.java"
public abstract class com.arjuna.webservices.util.Enumerated implements java.io.Serializable {
  private final java.lang.Object value;

  protected com.arjuna.webservices.util.Enumerated(java.lang.Object);
    Code:
       0: aload_0
       1: invokespecial #1                  // Method java/lang/Object."<init>":()V
       4: aload_0
       5: aload_1
       6: putfield      #2                  // Field value:Ljava/lang/Object;
       9: return

  public boolean equals(java.lang.Object);
    Code:
       0: aload_1
       1: aload_0
       2: if_acmpne     7
       5: iconst_1
       6: ireturn
       7: aload_1
       8: ifnull        58
      11: aload_1
      12: invokevirtual #3                  // Method java/lang/Object.getClass:()Ljava/lang/Class;
      15: aload_0
      16: invokevirtual #3                  // Method java/lang/Object.getClass:()Ljava/lang/Class;
      19: if_acmpne     58
      22: aload_1
      23: checkcast     #4                  // class com/arjuna/webservices/util/Enumerated
      26: getfield      #2                  // Field value:Ljava/lang/Object;
      29: astore_2
      30: aload_0
      31: getfield      #2                  // Field value:Ljava/lang/Object;
      34: ifnonnull     49
      37: aload_2
      38: ifnonnull     45
      41: iconst_1
      42: goto          57
      45: iconst_0
      46: goto          57
      49: aload_0
      50: getfield      #2                  // Field value:Ljava/lang/Object;
      53: aload_2
      54: invokevirtual #5                  // Method java/lang/Object.equals:(Ljava/lang/Object;)Z
      57: ireturn
      58: iconst_0
      59: ireturn

  public int hashCode();
    Code:
       0: aload_0
       1: getfield      #2                  // Field value:Ljava/lang/Object;
       4: ifnonnull     11
       7: iconst_0
       8: goto          18
      11: aload_0
      12: getfield      #2                  // Field value:Ljava/lang/Object;
      15: invokevirtual #6                  // Method java/lang/Object.hashCode:()I
      18: ireturn

  public java.lang.Object getKey();
    Code:
       0: aload_0
       1: getfield      #2                  // Field value:Ljava/lang/Object;
       4: areturn

  public java.lang.String toString();
    Code:
       0: aload_0
       1: getfield      #2                  // Field value:Ljava/lang/Object;
       4: ifnonnull     12
       7: ldc           #7                  // String <null>
       9: goto          19
      12: aload_0
      13: getfield      #2                  // Field value:Ljava/lang/Object;
      16: invokevirtual #8                  // Method java/lang/Object.toString:()Ljava/lang/String;
      19: areturn

  protected abstract com.arjuna.webservices.util.Enumerated resolveEnum(java.lang.Object) throws com.arjuna.webservices.util.InvalidEnumerationException;

  protected java.lang.Object readResolve() throws java.io.ObjectStreamException;
    Code:
       0: aload_0
       1: aload_0
       2: getfield      #2                  // Field value:Ljava/lang/Object;
       5: invokevirtual #9                  // Method resolveEnum:(Ljava/lang/Object;)Lcom/arjuna/webservices/util/Enumerated;
       8: areturn
       9: astore_1
      10: new           #11                 // class java/io/InvalidObjectException
      13: dup
      14: aload_1
      15: invokevirtual #12                 // Method com/arjuna/webservices/util/InvalidEnumerationException.getMessage:()Ljava/lang/String;
      18: invokespecial #13                 // Method java/io/InvalidObjectException."<init>":(Ljava/lang/String;)V
      21: athrow
    Exception table:
       from    to  target type
           0     8     9   Class com/arjuna/webservices/util/InvalidEnumerationException

  protected static java.util.Map generateMap(com.arjuna.webservices.util.Enumerated[]);
    Code:
       0: aload_0
       1: ifnonnull     8
       4: iconst_0
       5: goto          10
       8: aload_0
       9: arraylength
      10: istore_1
      11: iload_1
      12: ifne          22
      15: getstatic     #14                 // Field java/util/Collections.EMPTY_MAP:Ljava/util/Map;
      18: astore_2
      19: goto          62
      22: new           #15                 // class java/util/HashMap
      25: dup
      26: invokespecial #16                 // Method java/util/HashMap."<init>":()V
      29: astore_2
      30: iconst_0
      31: istore_3
      32: iload_3
      33: iload_1
      34: if_icmpge     62
      37: aload_0
      38: iload_3
      39: aaload
      40: astore        4
      42: aload_2
      43: aload         4
      45: invokevirtual #17                 // Method getKey:()Ljava/lang/Object;
      48: aload         4
      50: invokeinterface #18,  3           // InterfaceMethod java/util/Map.put:(Ljava/lang/Object;Ljava/lang/Object;)Ljava/lang/Object;
      55: pop
      56: iinc          3, 1
      59: goto          32
      62: aload_2
      63: areturn
}
