Compiled from "LogDiagnosticContextRecoveryInterceptor.java"
public final class org.jboss.as.ejb3.component.interceptors.LogDiagnosticContextRecoveryInterceptor implements org.jboss.invocation.Interceptor {
  private static final org.jboss.as.ejb3.component.interceptors.LogDiagnosticContextRecoveryInterceptor INSTANCE;

  private static final org.jboss.invocation.ImmediateInterceptorFactory FACTORY;

  private org.jboss.as.ejb3.component.interceptors.LogDiagnosticContextRecoveryInterceptor();
    Code:
       0: aload_0
       1: invokespecial #1                  // Method java/lang/Object."<init>":()V
       4: return

  public static org.jboss.invocation.ImmediateInterceptorFactory getFactory();
    Code:
       0: getstatic     #2                  // Field FACTORY:Lorg/jboss/invocation/ImmediateInterceptorFactory;
       3: areturn

  public static org.jboss.as.ejb3.component.interceptors.LogDiagnosticContextRecoveryInterceptor getInstance();
    Code:
       0: getstatic     #3                  // Field INSTANCE:Lorg/jboss/as/ejb3/component/interceptors/LogDiagnosticContextRecoveryInterceptor;
       3: areturn

  public java.lang.Object processInvocation(org.jboss.invocation.InterceptorContext) throws java.lang.Exception;
    Code:
       0: invokestatic  #4                  // Method org/jboss/logging/MDC.getMap:()Ljava/util/Map;
       3: astore_2
       4: aload_2
       5: ifnull        48
       8: aload_2
       9: invokeinterface #5,  1            // InterfaceMethod java/util/Map.keySet:()Ljava/util/Set;
      14: invokeinterface #6,  1            // InterfaceMethod java/util/Set.iterator:()Ljava/util/Iterator;
      19: astore_3
      20: aload_3
      21: invokeinterface #7,  1            // InterfaceMethod java/util/Iterator.hasNext:()Z
      26: ifeq          48
      29: aload_3
      30: invokeinterface #8,  1            // InterfaceMethod java/util/Iterator.next:()Ljava/lang/Object;
      35: checkcast     #9                  // class java/lang/String
      38: astore        4
      40: aload         4
      42: invokestatic  #10                 // Method org/jboss/logging/MDC.remove:(Ljava/lang/String;)V
      45: goto          20
      48: aload_1
      49: getstatic     #11                 // Field org/jboss/as/ejb3/component/interceptors/StoredLogDiagnosticContext.KEY:Ljava/lang/Object;
      52: invokevirtual #12                 // Method org/jboss/invocation/InterceptorContext.getPrivateData:(Ljava/lang/Object;)Ljava/lang/Object;
      55: checkcast     #13                 // class org/jboss/as/ejb3/component/interceptors/StoredLogDiagnosticContext
      58: astore_3
      59: aload_1
      60: getstatic     #11                 // Field org/jboss/as/ejb3/component/interceptors/StoredLogDiagnosticContext.KEY:Ljava/lang/Object;
      63: aconst_null
      64: invokevirtual #14                 // Method org/jboss/invocation/InterceptorContext.putPrivateData:(Ljava/lang/Object;Ljava/lang/Object;)Ljava/lang/Object;
      67: pop
      68: aload_3
      69: ifnull        267
      72: aload_3
      73: invokevirtual #15                 // Method org/jboss/as/ejb3/component/interceptors/StoredLogDiagnosticContext.getMdc:()Ljava/util/Map;
      76: ifnull        267
      79: aload_3
      80: invokevirtual #15                 // Method org/jboss/as/ejb3/component/interceptors/StoredLogDiagnosticContext.getMdc:()Ljava/util/Map;
      83: invokeinterface #16,  1           // InterfaceMethod java/util/Map.entrySet:()Ljava/util/Set;
      88: invokeinterface #6,  1            // InterfaceMethod java/util/Set.iterator:()Ljava/util/Iterator;
      93: astore        4
      95: aload         4
      97: invokeinterface #7,  1            // InterfaceMethod java/util/Iterator.hasNext:()Z
     102: ifeq          141
     105: aload         4
     107: invokeinterface #8,  1            // InterfaceMethod java/util/Iterator.next:()Ljava/lang/Object;
     112: checkcast     #17                 // class java/util/Map$Entry
     115: astore        5
     117: aload         5
     119: invokeinterface #18,  1           // InterfaceMethod java/util/Map$Entry.getKey:()Ljava/lang/Object;
     124: checkcast     #9                  // class java/lang/String
     127: aload         5
     129: invokeinterface #19,  1           // InterfaceMethod java/util/Map$Entry.getValue:()Ljava/lang/Object;
     134: invokestatic  #20                 // Method org/jboss/logging/MDC.put:(Ljava/lang/String;Ljava/lang/Object;)Ljava/lang/Object;
     137: pop
     138: goto          95
     141: invokestatic  #21                 // Method org/jboss/logging/NDC.getDepth:()I
     144: istore        4
     146: aload_3
     147: invokevirtual #22                 // Method org/jboss/as/ejb3/component/interceptors/StoredLogDiagnosticContext.getNdc:()Ljava/lang/String;
     150: invokestatic  #23                 // Method org/jboss/logging/NDC.push:(Ljava/lang/String;)V
     153: aload_1
     154: invokevirtual #24                 // Method org/jboss/invocation/InterceptorContext.proceed:()Ljava/lang/Object;
     157: astore        5
     159: iload         4
     161: invokestatic  #25                 // Method org/jboss/logging/NDC.setMaxDepth:(I)V
     164: invokestatic  #4                  // Method org/jboss/logging/MDC.getMap:()Ljava/util/Map;
     167: invokeinterface #5,  1            // InterfaceMethod java/util/Map.keySet:()Ljava/util/Set;
     172: invokeinterface #6,  1            // InterfaceMethod java/util/Set.iterator:()Ljava/util/Iterator;
     177: astore        6
     179: aload         6
     181: invokeinterface #7,  1            // InterfaceMethod java/util/Iterator.hasNext:()Z
     186: ifeq          209
     189: aload         6
     191: invokeinterface #8,  1            // InterfaceMethod java/util/Iterator.next:()Ljava/lang/Object;
     196: checkcast     #9                  // class java/lang/String
     199: astore        7
     201: aload         7
     203: invokestatic  #10                 // Method org/jboss/logging/MDC.remove:(Ljava/lang/String;)V
     206: goto          179
     209: aload         5
     211: areturn
     212: astore        8
     214: iload         4
     216: invokestatic  #25                 // Method org/jboss/logging/NDC.setMaxDepth:(I)V
     219: invokestatic  #4                  // Method org/jboss/logging/MDC.getMap:()Ljava/util/Map;
     222: invokeinterface #5,  1            // InterfaceMethod java/util/Map.keySet:()Ljava/util/Set;
     227: invokeinterface #6,  1            // InterfaceMethod java/util/Set.iterator:()Ljava/util/Iterator;
     232: astore        9
     234: aload         9
     236: invokeinterface #7,  1            // InterfaceMethod java/util/Iterator.hasNext:()Z
     241: ifeq          264
     244: aload         9
     246: invokeinterface #8,  1            // InterfaceMethod java/util/Iterator.next:()Ljava/lang/Object;
     251: checkcast     #9                  // class java/lang/String
     254: astore        10
     256: aload         10
     258: invokestatic  #10                 // Method org/jboss/logging/MDC.remove:(Ljava/lang/String;)V
     261: goto          234
     264: aload         8
     266: athrow
     267: aload_1
     268: invokevirtual #24                 // Method org/jboss/invocation/InterceptorContext.proceed:()Ljava/lang/Object;
     271: areturn
    Exception table:
       from    to  target type
         153   159   212   any
         212   214   212   any

  static {};
    Code:
       0: new           #26                 // class org/jboss/as/ejb3/component/interceptors/LogDiagnosticContextRecoveryInterceptor
       3: dup
       4: invokespecial #27                 // Method "<init>":()V
       7: putstatic     #3                  // Field INSTANCE:Lorg/jboss/as/ejb3/component/interceptors/LogDiagnosticContextRecoveryInterceptor;
      10: new           #28                 // class org/jboss/invocation/ImmediateInterceptorFactory
      13: dup
      14: getstatic     #3                  // Field INSTANCE:Lorg/jboss/as/ejb3/component/interceptors/LogDiagnosticContextRecoveryInterceptor;
      17: invokespecial #29                 // Method org/jboss/invocation/ImmediateInterceptorFactory."<init>":(Lorg/jboss/invocation/Interceptor;)V
      20: putstatic     #2                  // Field FACTORY:Lorg/jboss/invocation/ImmediateInterceptorFactory;
      23: return
}
