Compiled from "CouchbaseProperties.java"
public class org.springframework.boot.autoconfigure.couchbase.CouchbaseProperties$Ssl {
  private java.lang.Boolean enabled;

  private java.lang.String keyStore;

  private java.lang.String keyStorePassword;

  public org.springframework.boot.autoconfigure.couchbase.CouchbaseProperties$Ssl();
    Code:
       0: aload_0
       1: invokespecial #1                  // Method java/lang/Object."<init>":()V
       4: return

  public java.lang.Boolean getEnabled();
    Code:
       0: aload_0
       1: getfield      #2                  // Field enabled:Ljava/lang/Boolean;
       4: ifnull        17
       7: aload_0
       8: getfield      #2                  // Field enabled:Ljava/lang/Boolean;
      11: invokevirtual #3                  // Method java/lang/Boolean.booleanValue:()Z
      14: goto          24
      17: aload_0
      18: getfield      #4                  // Field keyStore:Ljava/lang/String;
      21: invokestatic  #5                  // Method org/springframework/util/StringUtils.hasText:(Ljava/lang/String;)Z
      24: invokestatic  #6                  // Method java/lang/Boolean.valueOf:(Z)Ljava/lang/Boolean;
      27: areturn

  public void setEnabled(java.lang.Boolean);
    Code:
       0: aload_0
       1: aload_1
       2: putfield      #2                  // Field enabled:Ljava/lang/Boolean;
       5: return

  public java.lang.String getKeyStore();
    Code:
       0: aload_0
       1: getfield      #4                  // Field keyStore:Ljava/lang/String;
       4: areturn

  public void setKeyStore(java.lang.String);
    Code:
       0: aload_0
       1: aload_1
       2: putfield      #4                  // Field keyStore:Ljava/lang/String;
       5: return

  public java.lang.String getKeyStorePassword();
    Code:
       0: aload_0
       1: getfield      #7                  // Field keyStorePassword:Ljava/lang/String;
       4: areturn

  public void setKeyStorePassword(java.lang.String);
    Code:
       0: aload_0
       1: aload_1
       2: putfield      #7                  // Field keyStorePassword:Ljava/lang/String;
       5: return
}
