Compiled from "FilterOperatorEnumFactory.java"
public class org.hl7.fhir.dstu3.model.codesystems.FilterOperatorEnumFactory implements org.hl7.fhir.dstu3.model.EnumFactory<org.hl7.fhir.dstu3.model.codesystems.FilterOperator> {
  public org.hl7.fhir.dstu3.model.codesystems.FilterOperatorEnumFactory();
    Code:
       0: aload_0
       1: invokespecial #1                  // Method java/lang/Object."<init>":()V
       4: return

  public org.hl7.fhir.dstu3.model.codesystems.FilterOperator fromCode(java.lang.String) throws java.lang.IllegalArgumentException;
    Code:
       0: aload_1
       1: ifnull        13
       4: ldc           #2                  // String
       6: aload_1
       7: invokevirtual #3                  // Method java/lang/String.equals:(Ljava/lang/Object;)Z
      10: ifeq          15
      13: aconst_null
      14: areturn
      15: ldc           #4                  // String =
      17: aload_1
      18: invokevirtual #3                  // Method java/lang/String.equals:(Ljava/lang/Object;)Z
      21: ifeq          28
      24: getstatic     #5                  // Field org/hl7/fhir/dstu3/model/codesystems/FilterOperator.EQUAL:Lorg/hl7/fhir/dstu3/model/codesystems/FilterOperator;
      27: areturn
      28: ldc           #6                  // String is-a
      30: aload_1
      31: invokevirtual #3                  // Method java/lang/String.equals:(Ljava/lang/Object;)Z
      34: ifeq          41
      37: getstatic     #7                  // Field org/hl7/fhir/dstu3/model/codesystems/FilterOperator.ISA:Lorg/hl7/fhir/dstu3/model/codesystems/FilterOperator;
      40: areturn
      41: ldc           #8                  // String descendent-of
      43: aload_1
      44: invokevirtual #3                  // Method java/lang/String.equals:(Ljava/lang/Object;)Z
      47: ifeq          54
      50: getstatic     #9                  // Field org/hl7/fhir/dstu3/model/codesystems/FilterOperator.DESCENDENTOF:Lorg/hl7/fhir/dstu3/model/codesystems/FilterOperator;
      53: areturn
      54: ldc           #10                 // String is-not-a
      56: aload_1
      57: invokevirtual #3                  // Method java/lang/String.equals:(Ljava/lang/Object;)Z
      60: ifeq          67
      63: getstatic     #11                 // Field org/hl7/fhir/dstu3/model/codesystems/FilterOperator.ISNOTA:Lorg/hl7/fhir/dstu3/model/codesystems/FilterOperator;
      66: areturn
      67: ldc           #12                 // String regex
      69: aload_1
      70: invokevirtual #3                  // Method java/lang/String.equals:(Ljava/lang/Object;)Z
      73: ifeq          80
      76: getstatic     #13                 // Field org/hl7/fhir/dstu3/model/codesystems/FilterOperator.REGEX:Lorg/hl7/fhir/dstu3/model/codesystems/FilterOperator;
      79: areturn
      80: ldc           #14                 // String in
      82: aload_1
      83: invokevirtual #3                  // Method java/lang/String.equals:(Ljava/lang/Object;)Z
      86: ifeq          93
      89: getstatic     #15                 // Field org/hl7/fhir/dstu3/model/codesystems/FilterOperator.IN:Lorg/hl7/fhir/dstu3/model/codesystems/FilterOperator;
      92: areturn
      93: ldc           #16                 // String not-in
      95: aload_1
      96: invokevirtual #3                  // Method java/lang/String.equals:(Ljava/lang/Object;)Z
      99: ifeq          106
     102: getstatic     #17                 // Field org/hl7/fhir/dstu3/model/codesystems/FilterOperator.NOTIN:Lorg/hl7/fhir/dstu3/model/codesystems/FilterOperator;
     105: areturn
     106: ldc           #18                 // String generalizes
     108: aload_1
     109: invokevirtual #3                  // Method java/lang/String.equals:(Ljava/lang/Object;)Z
     112: ifeq          119
     115: getstatic     #19                 // Field org/hl7/fhir/dstu3/model/codesystems/FilterOperator.GENERALIZES:Lorg/hl7/fhir/dstu3/model/codesystems/FilterOperator;
     118: areturn
     119: ldc           #20                 // String exists
     121: aload_1
     122: invokevirtual #3                  // Method java/lang/String.equals:(Ljava/lang/Object;)Z
     125: ifeq          132
     128: getstatic     #21                 // Field org/hl7/fhir/dstu3/model/codesystems/FilterOperator.EXISTS:Lorg/hl7/fhir/dstu3/model/codesystems/FilterOperator;
     131: areturn
     132: new           #22                 // class java/lang/IllegalArgumentException
     135: dup
     136: new           #23                 // class java/lang/StringBuilder
     139: dup
     140: invokespecial #24                 // Method java/lang/StringBuilder."<init>":()V
     143: ldc           #25                 // String Unknown FilterOperator code \'
     145: invokevirtual #26                 // Method java/lang/StringBuilder.append:(Ljava/lang/String;)Ljava/lang/StringBuilder;
     148: aload_1
     149: invokevirtual #26                 // Method java/lang/StringBuilder.append:(Ljava/lang/String;)Ljava/lang/StringBuilder;
     152: ldc           #27                 // String \'
     154: invokevirtual #26                 // Method java/lang/StringBuilder.append:(Ljava/lang/String;)Ljava/lang/StringBuilder;
     157: invokevirtual #28                 // Method java/lang/StringBuilder.toString:()Ljava/lang/String;
     160: invokespecial #29                 // Method java/lang/IllegalArgumentException."<init>":(Ljava/lang/String;)V
     163: athrow

  public java.lang.String toCode(org.hl7.fhir.dstu3.model.codesystems.FilterOperator);
    Code:
       0: aload_1
       1: getstatic     #5                  // Field org/hl7/fhir/dstu3/model/codesystems/FilterOperator.EQUAL:Lorg/hl7/fhir/dstu3/model/codesystems/FilterOperator;
       4: if_acmpne     10
       7: ldc           #4                  // String =
       9: areturn
      10: aload_1
      11: getstatic     #7                  // Field org/hl7/fhir/dstu3/model/codesystems/FilterOperator.ISA:Lorg/hl7/fhir/dstu3/model/codesystems/FilterOperator;
      14: if_acmpne     20
      17: ldc           #6                  // String is-a
      19: areturn
      20: aload_1
      21: getstatic     #9                  // Field org/hl7/fhir/dstu3/model/codesystems/FilterOperator.DESCENDENTOF:Lorg/hl7/fhir/dstu3/model/codesystems/FilterOperator;
      24: if_acmpne     30
      27: ldc           #8                  // String descendent-of
      29: areturn
      30: aload_1
      31: getstatic     #11                 // Field org/hl7/fhir/dstu3/model/codesystems/FilterOperator.ISNOTA:Lorg/hl7/fhir/dstu3/model/codesystems/FilterOperator;
      34: if_acmpne     40
      37: ldc           #10                 // String is-not-a
      39: areturn
      40: aload_1
      41: getstatic     #13                 // Field org/hl7/fhir/dstu3/model/codesystems/FilterOperator.REGEX:Lorg/hl7/fhir/dstu3/model/codesystems/FilterOperator;
      44: if_acmpne     50
      47: ldc           #12                 // String regex
      49: areturn
      50: aload_1
      51: getstatic     #15                 // Field org/hl7/fhir/dstu3/model/codesystems/FilterOperator.IN:Lorg/hl7/fhir/dstu3/model/codesystems/FilterOperator;
      54: if_acmpne     60
      57: ldc           #14                 // String in
      59: areturn
      60: aload_1
      61: getstatic     #17                 // Field org/hl7/fhir/dstu3/model/codesystems/FilterOperator.NOTIN:Lorg/hl7/fhir/dstu3/model/codesystems/FilterOperator;
      64: if_acmpne     70
      67: ldc           #16                 // String not-in
      69: areturn
      70: aload_1
      71: getstatic     #19                 // Field org/hl7/fhir/dstu3/model/codesystems/FilterOperator.GENERALIZES:Lorg/hl7/fhir/dstu3/model/codesystems/FilterOperator;
      74: if_acmpne     80
      77: ldc           #18                 // String generalizes
      79: areturn
      80: aload_1
      81: getstatic     #21                 // Field org/hl7/fhir/dstu3/model/codesystems/FilterOperator.EXISTS:Lorg/hl7/fhir/dstu3/model/codesystems/FilterOperator;
      84: if_acmpne     90
      87: ldc           #20                 // String exists
      89: areturn
      90: ldc           #30                 // String ?
      92: areturn

  public java.lang.String toSystem(org.hl7.fhir.dstu3.model.codesystems.FilterOperator);
    Code:
       0: aload_1
       1: invokevirtual #31                 // Method org/hl7/fhir/dstu3/model/codesystems/FilterOperator.getSystem:()Ljava/lang/String;
       4: areturn

  public java.lang.String toSystem(java.lang.Enum);
    Code:
       0: aload_0
       1: aload_1
       2: checkcast     #32                 // class org/hl7/fhir/dstu3/model/codesystems/FilterOperator
       5: invokevirtual #33                 // Method toSystem:(Lorg/hl7/fhir/dstu3/model/codesystems/FilterOperator;)Ljava/lang/String;
       8: areturn

  public java.lang.String toCode(java.lang.Enum);
    Code:
       0: aload_0
       1: aload_1
       2: checkcast     #32                 // class org/hl7/fhir/dstu3/model/codesystems/FilterOperator
       5: invokevirtual #34                 // Method toCode:(Lorg/hl7/fhir/dstu3/model/codesystems/FilterOperator;)Ljava/lang/String;
       8: areturn

  public java.lang.Enum fromCode(java.lang.String) throws java.lang.IllegalArgumentException;
    Code:
       0: aload_0
       1: aload_1
       2: invokevirtual #35                 // Method fromCode:(Ljava/lang/String;)Lorg/hl7/fhir/dstu3/model/codesystems/FilterOperator;
       5: areturn
}
