Compiled from "Fundsreserve.java"
public final class org.hl7.fhir.dstu3.model.codesystems.Fundsreserve extends java.lang.Enum<org.hl7.fhir.dstu3.model.codesystems.Fundsreserve> {
  public static final org.hl7.fhir.dstu3.model.codesystems.Fundsreserve PATIENT;

  public static final org.hl7.fhir.dstu3.model.codesystems.Fundsreserve PROVIDER;

  public static final org.hl7.fhir.dstu3.model.codesystems.Fundsreserve NONE;

  public static final org.hl7.fhir.dstu3.model.codesystems.Fundsreserve NULL;

  private static final org.hl7.fhir.dstu3.model.codesystems.Fundsreserve[] $VALUES;

  public static org.hl7.fhir.dstu3.model.codesystems.Fundsreserve[] values();
    Code:
       0: getstatic     #1                  // Field $VALUES:[Lorg/hl7/fhir/dstu3/model/codesystems/Fundsreserve;
       3: invokevirtual #2                  // Method "[Lorg/hl7/fhir/dstu3/model/codesystems/Fundsreserve;".clone:()Ljava/lang/Object;
       6: checkcast     #3                  // class "[Lorg/hl7/fhir/dstu3/model/codesystems/Fundsreserve;"
       9: areturn

  public static org.hl7.fhir.dstu3.model.codesystems.Fundsreserve valueOf(java.lang.String);
    Code:
       0: ldc           #4                  // class org/hl7/fhir/dstu3/model/codesystems/Fundsreserve
       2: aload_0
       3: invokestatic  #5                  // Method java/lang/Enum.valueOf:(Ljava/lang/Class;Ljava/lang/String;)Ljava/lang/Enum;
       6: checkcast     #4                  // class org/hl7/fhir/dstu3/model/codesystems/Fundsreserve
       9: areturn

  private org.hl7.fhir.dstu3.model.codesystems.Fundsreserve();
    Code:
       0: aload_0
       1: aload_1
       2: iload_2
       3: invokespecial #6                  // Method java/lang/Enum."<init>":(Ljava/lang/String;I)V
       6: return

  public static org.hl7.fhir.dstu3.model.codesystems.Fundsreserve fromCode(java.lang.String) throws org.hl7.fhir.exceptions.FHIRException;
    Code:
       0: aload_0
       1: ifnull        13
       4: ldc           #7                  // String
       6: aload_0
       7: invokevirtual #8                  // Method java/lang/String.equals:(Ljava/lang/Object;)Z
      10: ifeq          15
      13: aconst_null
      14: areturn
      15: ldc           #9                  // String patient
      17: aload_0
      18: invokevirtual #8                  // Method java/lang/String.equals:(Ljava/lang/Object;)Z
      21: ifeq          28
      24: getstatic     #10                 // Field PATIENT:Lorg/hl7/fhir/dstu3/model/codesystems/Fundsreserve;
      27: areturn
      28: ldc           #11                 // String provider
      30: aload_0
      31: invokevirtual #8                  // Method java/lang/String.equals:(Ljava/lang/Object;)Z
      34: ifeq          41
      37: getstatic     #12                 // Field PROVIDER:Lorg/hl7/fhir/dstu3/model/codesystems/Fundsreserve;
      40: areturn
      41: ldc           #13                 // String none
      43: aload_0
      44: invokevirtual #8                  // Method java/lang/String.equals:(Ljava/lang/Object;)Z
      47: ifeq          54
      50: getstatic     #14                 // Field NONE:Lorg/hl7/fhir/dstu3/model/codesystems/Fundsreserve;
      53: areturn
      54: new           #15                 // class org/hl7/fhir/exceptions/FHIRException
      57: dup
      58: new           #16                 // class java/lang/StringBuilder
      61: dup
      62: invokespecial #17                 // Method java/lang/StringBuilder."<init>":()V
      65: ldc           #18                 // String Unknown Fundsreserve code \'
      67: invokevirtual #19                 // Method java/lang/StringBuilder.append:(Ljava/lang/String;)Ljava/lang/StringBuilder;
      70: aload_0
      71: invokevirtual #19                 // Method java/lang/StringBuilder.append:(Ljava/lang/String;)Ljava/lang/StringBuilder;
      74: ldc           #20                 // String \'
      76: invokevirtual #19                 // Method java/lang/StringBuilder.append:(Ljava/lang/String;)Ljava/lang/StringBuilder;
      79: invokevirtual #21                 // Method java/lang/StringBuilder.toString:()Ljava/lang/String;
      82: invokespecial #22                 // Method org/hl7/fhir/exceptions/FHIRException."<init>":(Ljava/lang/String;)V
      85: athrow

  public java.lang.String toCode();
    Code:
       0: getstatic     #23                 // Field org/hl7/fhir/dstu3/model/codesystems/Fundsreserve$1.$SwitchMap$org$hl7$fhir$dstu3$model$codesystems$Fundsreserve:[I
       3: aload_0
       4: invokevirtual #24                 // Method ordinal:()I
       7: iaload
       8: tableswitch   { // 1 to 4
                     1: 40
                     2: 43
                     3: 46
                     4: 49
               default: 51
          }
      40: ldc           #9                  // String patient
      42: areturn
      43: ldc           #11                 // String provider
      45: areturn
      46: ldc           #13                 // String none
      48: areturn
      49: aconst_null
      50: areturn
      51: ldc           #25                 // String ?
      53: areturn

  public java.lang.String getSystem();
    Code:
       0: ldc           #26                 // String http://hl7.org/fhir/fundsreserve
       2: areturn

  public java.lang.String getDefinition();
    Code:
       0: getstatic     #23                 // Field org/hl7/fhir/dstu3/model/codesystems/Fundsreserve$1.$SwitchMap$org$hl7$fhir$dstu3$model$codesystems$Fundsreserve:[I
       3: aload_0
       4: invokevirtual #24                 // Method ordinal:()I
       7: iaload
       8: tableswitch   { // 1 to 4
                     1: 40
                     2: 43
                     3: 46
                     4: 49
               default: 51
          }
      40: ldc           #27                 // String The payor is requested to reserve funds for the provision of the named services by any provider for settlement of future claims related to this request.
      42: areturn
      43: ldc           #28                 // String The payor is requested to reserve funds solely for the named provider for settlement of future claims related to this request.
      45: areturn
      46: ldc           #29                 // String The payor is not being requested to reserve any funds for the settlement of future claims.
      48: areturn
      49: aconst_null
      50: areturn
      51: ldc           #25                 // String ?
      53: areturn

  public java.lang.String getDisplay();
    Code:
       0: getstatic     #23                 // Field org/hl7/fhir/dstu3/model/codesystems/Fundsreserve$1.$SwitchMap$org$hl7$fhir$dstu3$model$codesystems$Fundsreserve:[I
       3: aload_0
       4: invokevirtual #24                 // Method ordinal:()I
       7: iaload
       8: tableswitch   { // 1 to 4
                     1: 40
                     2: 43
                     3: 46
                     4: 49
               default: 51
          }
      40: ldc           #30                 // String Patient
      42: areturn
      43: ldc           #31                 // String Provider
      45: areturn
      46: ldc           #32                 // String None
      48: areturn
      49: aconst_null
      50: areturn
      51: ldc           #25                 // String ?
      53: areturn

  static {};
    Code:
       0: new           #4                  // class org/hl7/fhir/dstu3/model/codesystems/Fundsreserve
       3: dup
       4: ldc           #33                 // String PATIENT
       6: iconst_0
       7: invokespecial #34                 // Method "<init>":(Ljava/lang/String;I)V
      10: putstatic     #10                 // Field PATIENT:Lorg/hl7/fhir/dstu3/model/codesystems/Fundsreserve;
      13: new           #4                  // class org/hl7/fhir/dstu3/model/codesystems/Fundsreserve
      16: dup
      17: ldc           #35                 // String PROVIDER
      19: iconst_1
      20: invokespecial #34                 // Method "<init>":(Ljava/lang/String;I)V
      23: putstatic     #12                 // Field PROVIDER:Lorg/hl7/fhir/dstu3/model/codesystems/Fundsreserve;
      26: new           #4                  // class org/hl7/fhir/dstu3/model/codesystems/Fundsreserve
      29: dup
      30: ldc           #36                 // String NONE
      32: iconst_2
      33: invokespecial #34                 // Method "<init>":(Ljava/lang/String;I)V
      36: putstatic     #14                 // Field NONE:Lorg/hl7/fhir/dstu3/model/codesystems/Fundsreserve;
      39: new           #4                  // class org/hl7/fhir/dstu3/model/codesystems/Fundsreserve
      42: dup
      43: ldc           #37                 // String NULL
      45: iconst_3
      46: invokespecial #34                 // Method "<init>":(Ljava/lang/String;I)V
      49: putstatic     #38                 // Field NULL:Lorg/hl7/fhir/dstu3/model/codesystems/Fundsreserve;
      52: iconst_4
      53: anewarray     #4                  // class org/hl7/fhir/dstu3/model/codesystems/Fundsreserve
      56: dup
      57: iconst_0
      58: getstatic     #10                 // Field PATIENT:Lorg/hl7/fhir/dstu3/model/codesystems/Fundsreserve;
      61: aastore
      62: dup
      63: iconst_1
      64: getstatic     #12                 // Field PROVIDER:Lorg/hl7/fhir/dstu3/model/codesystems/Fundsreserve;
      67: aastore
      68: dup
      69: iconst_2
      70: getstatic     #14                 // Field NONE:Lorg/hl7/fhir/dstu3/model/codesystems/Fundsreserve;
      73: aastore
      74: dup
      75: iconst_3
      76: getstatic     #38                 // Field NULL:Lorg/hl7/fhir/dstu3/model/codesystems/Fundsreserve;
      79: aastore
      80: putstatic     #1                  // Field $VALUES:[Lorg/hl7/fhir/dstu3/model/codesystems/Fundsreserve;
      83: return
}
