Compiled from "LibraryType.java"
public final class org.hl7.fhir.dstu3.model.codesystems.LibraryType extends java.lang.Enum<org.hl7.fhir.dstu3.model.codesystems.LibraryType> {
  public static final org.hl7.fhir.dstu3.model.codesystems.LibraryType LOGICLIBRARY;

  public static final org.hl7.fhir.dstu3.model.codesystems.LibraryType MODELDEFINITION;

  public static final org.hl7.fhir.dstu3.model.codesystems.LibraryType ASSETCOLLECTION;

  public static final org.hl7.fhir.dstu3.model.codesystems.LibraryType MODULEDEFINITION;

  public static final org.hl7.fhir.dstu3.model.codesystems.LibraryType NULL;

  private static final org.hl7.fhir.dstu3.model.codesystems.LibraryType[] $VALUES;

  public static org.hl7.fhir.dstu3.model.codesystems.LibraryType[] values();
    Code:
       0: getstatic     #1                  // Field $VALUES:[Lorg/hl7/fhir/dstu3/model/codesystems/LibraryType;
       3: invokevirtual #2                  // Method "[Lorg/hl7/fhir/dstu3/model/codesystems/LibraryType;".clone:()Ljava/lang/Object;
       6: checkcast     #3                  // class "[Lorg/hl7/fhir/dstu3/model/codesystems/LibraryType;"
       9: areturn

  public static org.hl7.fhir.dstu3.model.codesystems.LibraryType valueOf(java.lang.String);
    Code:
       0: ldc           #4                  // class org/hl7/fhir/dstu3/model/codesystems/LibraryType
       2: aload_0
       3: invokestatic  #5                  // Method java/lang/Enum.valueOf:(Ljava/lang/Class;Ljava/lang/String;)Ljava/lang/Enum;
       6: checkcast     #4                  // class org/hl7/fhir/dstu3/model/codesystems/LibraryType
       9: areturn

  private org.hl7.fhir.dstu3.model.codesystems.LibraryType();
    Code:
       0: aload_0
       1: aload_1
       2: iload_2
       3: invokespecial #6                  // Method java/lang/Enum."<init>":(Ljava/lang/String;I)V
       6: return

  public static org.hl7.fhir.dstu3.model.codesystems.LibraryType fromCode(java.lang.String) throws org.hl7.fhir.exceptions.FHIRException;
    Code:
       0: aload_0
       1: ifnull        13
       4: ldc           #7                  // String
       6: aload_0
       7: invokevirtual #8                  // Method java/lang/String.equals:(Ljava/lang/Object;)Z
      10: ifeq          15
      13: aconst_null
      14: areturn
      15: ldc           #9                  // String logic-library
      17: aload_0
      18: invokevirtual #8                  // Method java/lang/String.equals:(Ljava/lang/Object;)Z
      21: ifeq          28
      24: getstatic     #10                 // Field LOGICLIBRARY:Lorg/hl7/fhir/dstu3/model/codesystems/LibraryType;
      27: areturn
      28: ldc           #11                 // String model-definition
      30: aload_0
      31: invokevirtual #8                  // Method java/lang/String.equals:(Ljava/lang/Object;)Z
      34: ifeq          41
      37: getstatic     #12                 // Field MODELDEFINITION:Lorg/hl7/fhir/dstu3/model/codesystems/LibraryType;
      40: areturn
      41: ldc           #13                 // String asset-collection
      43: aload_0
      44: invokevirtual #8                  // Method java/lang/String.equals:(Ljava/lang/Object;)Z
      47: ifeq          54
      50: getstatic     #14                 // Field ASSETCOLLECTION:Lorg/hl7/fhir/dstu3/model/codesystems/LibraryType;
      53: areturn
      54: ldc           #15                 // String module-definition
      56: aload_0
      57: invokevirtual #8                  // Method java/lang/String.equals:(Ljava/lang/Object;)Z
      60: ifeq          67
      63: getstatic     #16                 // Field MODULEDEFINITION:Lorg/hl7/fhir/dstu3/model/codesystems/LibraryType;
      66: areturn
      67: new           #17                 // class org/hl7/fhir/exceptions/FHIRException
      70: dup
      71: new           #18                 // class java/lang/StringBuilder
      74: dup
      75: invokespecial #19                 // Method java/lang/StringBuilder."<init>":()V
      78: ldc           #20                 // String Unknown LibraryType code \'
      80: invokevirtual #21                 // Method java/lang/StringBuilder.append:(Ljava/lang/String;)Ljava/lang/StringBuilder;
      83: aload_0
      84: invokevirtual #21                 // Method java/lang/StringBuilder.append:(Ljava/lang/String;)Ljava/lang/StringBuilder;
      87: ldc           #22                 // String \'
      89: invokevirtual #21                 // Method java/lang/StringBuilder.append:(Ljava/lang/String;)Ljava/lang/StringBuilder;
      92: invokevirtual #23                 // Method java/lang/StringBuilder.toString:()Ljava/lang/String;
      95: invokespecial #24                 // Method org/hl7/fhir/exceptions/FHIRException."<init>":(Ljava/lang/String;)V
      98: athrow

  public java.lang.String toCode();
    Code:
       0: getstatic     #25                 // Field org/hl7/fhir/dstu3/model/codesystems/LibraryType$1.$SwitchMap$org$hl7$fhir$dstu3$model$codesystems$LibraryType:[I
       3: aload_0
       4: invokevirtual #26                 // Method ordinal:()I
       7: iaload
       8: tableswitch   { // 1 to 5
                     1: 44
                     2: 47
                     3: 50
                     4: 53
                     5: 56
               default: 58
          }
      44: ldc           #9                  // String logic-library
      46: areturn
      47: ldc           #11                 // String model-definition
      49: areturn
      50: ldc           #13                 // String asset-collection
      52: areturn
      53: ldc           #15                 // String module-definition
      55: areturn
      56: aconst_null
      57: areturn
      58: ldc           #27                 // String ?
      60: areturn

  public java.lang.String getSystem();
    Code:
       0: ldc           #28                 // String http://hl7.org/fhir/library-type
       2: areturn

  public java.lang.String getDefinition();
    Code:
       0: getstatic     #25                 // Field org/hl7/fhir/dstu3/model/codesystems/LibraryType$1.$SwitchMap$org$hl7$fhir$dstu3$model$codesystems$LibraryType:[I
       3: aload_0
       4: invokevirtual #26                 // Method ordinal:()I
       7: iaload
       8: tableswitch   { // 1 to 5
                     1: 44
                     2: 47
                     3: 50
                     4: 53
                     5: 56
               default: 58
          }
      44: ldc           #29                 // String The resource is a shareable library of formalized knowledge
      46: areturn
      47: ldc           #30                 // String The resource is a definition of an information model
      49: areturn
      50: ldc           #31                 // String The resource is a collection of knowledge assets
      52: areturn
      53: ldc           #32                 // String The resource defines the dependencies, parameters, and data requirements for a particular module or evaluation context
      55: areturn
      56: aconst_null
      57: areturn
      58: ldc           #27                 // String ?
      60: areturn

  public java.lang.String getDisplay();
    Code:
       0: getstatic     #25                 // Field org/hl7/fhir/dstu3/model/codesystems/LibraryType$1.$SwitchMap$org$hl7$fhir$dstu3$model$codesystems$LibraryType:[I
       3: aload_0
       4: invokevirtual #26                 // Method ordinal:()I
       7: iaload
       8: tableswitch   { // 1 to 5
                     1: 44
                     2: 47
                     3: 50
                     4: 53
                     5: 56
               default: 58
          }
      44: ldc           #33                 // String Logic Library
      46: areturn
      47: ldc           #34                 // String Model Definition
      49: areturn
      50: ldc           #35                 // String Asset Collection
      52: areturn
      53: ldc           #36                 // String Module Definition
      55: areturn
      56: aconst_null
      57: areturn
      58: ldc           #27                 // String ?
      60: areturn

  static {};
    Code:
       0: new           #4                  // class org/hl7/fhir/dstu3/model/codesystems/LibraryType
       3: dup
       4: ldc           #37                 // String LOGICLIBRARY
       6: iconst_0
       7: invokespecial #38                 // Method "<init>":(Ljava/lang/String;I)V
      10: putstatic     #10                 // Field LOGICLIBRARY:Lorg/hl7/fhir/dstu3/model/codesystems/LibraryType;
      13: new           #4                  // class org/hl7/fhir/dstu3/model/codesystems/LibraryType
      16: dup
      17: ldc           #39                 // String MODELDEFINITION
      19: iconst_1
      20: invokespecial #38                 // Method "<init>":(Ljava/lang/String;I)V
      23: putstatic     #12                 // Field MODELDEFINITION:Lorg/hl7/fhir/dstu3/model/codesystems/LibraryType;
      26: new           #4                  // class org/hl7/fhir/dstu3/model/codesystems/LibraryType
      29: dup
      30: ldc           #40                 // String ASSETCOLLECTION
      32: iconst_2
      33: invokespecial #38                 // Method "<init>":(Ljava/lang/String;I)V
      36: putstatic     #14                 // Field ASSETCOLLECTION:Lorg/hl7/fhir/dstu3/model/codesystems/LibraryType;
      39: new           #4                  // class org/hl7/fhir/dstu3/model/codesystems/LibraryType
      42: dup
      43: ldc           #41                 // String MODULEDEFINITION
      45: iconst_3
      46: invokespecial #38                 // Method "<init>":(Ljava/lang/String;I)V
      49: putstatic     #16                 // Field MODULEDEFINITION:Lorg/hl7/fhir/dstu3/model/codesystems/LibraryType;
      52: new           #4                  // class org/hl7/fhir/dstu3/model/codesystems/LibraryType
      55: dup
      56: ldc           #42                 // String NULL
      58: iconst_4
      59: invokespecial #38                 // Method "<init>":(Ljava/lang/String;I)V
      62: putstatic     #43                 // Field NULL:Lorg/hl7/fhir/dstu3/model/codesystems/LibraryType;
      65: iconst_5
      66: anewarray     #4                  // class org/hl7/fhir/dstu3/model/codesystems/LibraryType
      69: dup
      70: iconst_0
      71: getstatic     #10                 // Field LOGICLIBRARY:Lorg/hl7/fhir/dstu3/model/codesystems/LibraryType;
      74: aastore
      75: dup
      76: iconst_1
      77: getstatic     #12                 // Field MODELDEFINITION:Lorg/hl7/fhir/dstu3/model/codesystems/LibraryType;
      80: aastore
      81: dup
      82: iconst_2
      83: getstatic     #14                 // Field ASSETCOLLECTION:Lorg/hl7/fhir/dstu3/model/codesystems/LibraryType;
      86: aastore
      87: dup
      88: iconst_3
      89: getstatic     #16                 // Field MODULEDEFINITION:Lorg/hl7/fhir/dstu3/model/codesystems/LibraryType;
      92: aastore
      93: dup
      94: iconst_4
      95: getstatic     #43                 // Field NULL:Lorg/hl7/fhir/dstu3/model/codesystems/LibraryType;
      98: aastore
      99: putstatic     #1                  // Field $VALUES:[Lorg/hl7/fhir/dstu3/model/codesystems/LibraryType;
     102: return
}
