Compiled from "MeasurementPrinciple.java"
public final class org.hl7.fhir.dstu3.model.codesystems.MeasurementPrinciple extends java.lang.Enum<org.hl7.fhir.dstu3.model.codesystems.MeasurementPrinciple> {
  public static final org.hl7.fhir.dstu3.model.codesystems.MeasurementPrinciple OTHER;

  public static final org.hl7.fhir.dstu3.model.codesystems.MeasurementPrinciple CHEMICAL;

  public static final org.hl7.fhir.dstu3.model.codesystems.MeasurementPrinciple ELECTRICAL;

  public static final org.hl7.fhir.dstu3.model.codesystems.MeasurementPrinciple IMPEDANCE;

  public static final org.hl7.fhir.dstu3.model.codesystems.MeasurementPrinciple NUCLEAR;

  public static final org.hl7.fhir.dstu3.model.codesystems.MeasurementPrinciple OPTICAL;

  public static final org.hl7.fhir.dstu3.model.codesystems.MeasurementPrinciple THERMAL;

  public static final org.hl7.fhir.dstu3.model.codesystems.MeasurementPrinciple BIOLOGICAL;

  public static final org.hl7.fhir.dstu3.model.codesystems.MeasurementPrinciple MECHANICAL;

  public static final org.hl7.fhir.dstu3.model.codesystems.MeasurementPrinciple ACOUSTICAL;

  public static final org.hl7.fhir.dstu3.model.codesystems.MeasurementPrinciple MANUAL;

  public static final org.hl7.fhir.dstu3.model.codesystems.MeasurementPrinciple NULL;

  private static final org.hl7.fhir.dstu3.model.codesystems.MeasurementPrinciple[] $VALUES;

  public static org.hl7.fhir.dstu3.model.codesystems.MeasurementPrinciple[] values();
    Code:
       0: getstatic     #1                  // Field $VALUES:[Lorg/hl7/fhir/dstu3/model/codesystems/MeasurementPrinciple;
       3: invokevirtual #2                  // Method "[Lorg/hl7/fhir/dstu3/model/codesystems/MeasurementPrinciple;".clone:()Ljava/lang/Object;
       6: checkcast     #3                  // class "[Lorg/hl7/fhir/dstu3/model/codesystems/MeasurementPrinciple;"
       9: areturn

  public static org.hl7.fhir.dstu3.model.codesystems.MeasurementPrinciple valueOf(java.lang.String);
    Code:
       0: ldc           #4                  // class org/hl7/fhir/dstu3/model/codesystems/MeasurementPrinciple
       2: aload_0
       3: invokestatic  #5                  // Method java/lang/Enum.valueOf:(Ljava/lang/Class;Ljava/lang/String;)Ljava/lang/Enum;
       6: checkcast     #4                  // class org/hl7/fhir/dstu3/model/codesystems/MeasurementPrinciple
       9: areturn

  private org.hl7.fhir.dstu3.model.codesystems.MeasurementPrinciple();
    Code:
       0: aload_0
       1: aload_1
       2: iload_2
       3: invokespecial #6                  // Method java/lang/Enum."<init>":(Ljava/lang/String;I)V
       6: return

  public static org.hl7.fhir.dstu3.model.codesystems.MeasurementPrinciple fromCode(java.lang.String) throws org.hl7.fhir.exceptions.FHIRException;
    Code:
       0: aload_0
       1: ifnull        13
       4: ldc           #7                  // String
       6: aload_0
       7: invokevirtual #8                  // Method java/lang/String.equals:(Ljava/lang/Object;)Z
      10: ifeq          15
      13: aconst_null
      14: areturn
      15: ldc           #9                  // String other
      17: aload_0
      18: invokevirtual #8                  // Method java/lang/String.equals:(Ljava/lang/Object;)Z
      21: ifeq          28
      24: getstatic     #10                 // Field OTHER:Lorg/hl7/fhir/dstu3/model/codesystems/MeasurementPrinciple;
      27: areturn
      28: ldc           #11                 // String chemical
      30: aload_0
      31: invokevirtual #8                  // Method java/lang/String.equals:(Ljava/lang/Object;)Z
      34: ifeq          41
      37: getstatic     #12                 // Field CHEMICAL:Lorg/hl7/fhir/dstu3/model/codesystems/MeasurementPrinciple;
      40: areturn
      41: ldc           #13                 // String electrical
      43: aload_0
      44: invokevirtual #8                  // Method java/lang/String.equals:(Ljava/lang/Object;)Z
      47: ifeq          54
      50: getstatic     #14                 // Field ELECTRICAL:Lorg/hl7/fhir/dstu3/model/codesystems/MeasurementPrinciple;
      53: areturn
      54: ldc           #15                 // String impedance
      56: aload_0
      57: invokevirtual #8                  // Method java/lang/String.equals:(Ljava/lang/Object;)Z
      60: ifeq          67
      63: getstatic     #16                 // Field IMPEDANCE:Lorg/hl7/fhir/dstu3/model/codesystems/MeasurementPrinciple;
      66: areturn
      67: ldc           #17                 // String nuclear
      69: aload_0
      70: invokevirtual #8                  // Method java/lang/String.equals:(Ljava/lang/Object;)Z
      73: ifeq          80
      76: getstatic     #18                 // Field NUCLEAR:Lorg/hl7/fhir/dstu3/model/codesystems/MeasurementPrinciple;
      79: areturn
      80: ldc           #19                 // String optical
      82: aload_0
      83: invokevirtual #8                  // Method java/lang/String.equals:(Ljava/lang/Object;)Z
      86: ifeq          93
      89: getstatic     #20                 // Field OPTICAL:Lorg/hl7/fhir/dstu3/model/codesystems/MeasurementPrinciple;
      92: areturn
      93: ldc           #21                 // String thermal
      95: aload_0
      96: invokevirtual #8                  // Method java/lang/String.equals:(Ljava/lang/Object;)Z
      99: ifeq          106
     102: getstatic     #22                 // Field THERMAL:Lorg/hl7/fhir/dstu3/model/codesystems/MeasurementPrinciple;
     105: areturn
     106: ldc           #23                 // String biological
     108: aload_0
     109: invokevirtual #8                  // Method java/lang/String.equals:(Ljava/lang/Object;)Z
     112: ifeq          119
     115: getstatic     #24                 // Field BIOLOGICAL:Lorg/hl7/fhir/dstu3/model/codesystems/MeasurementPrinciple;
     118: areturn
     119: ldc           #25                 // String mechanical
     121: aload_0
     122: invokevirtual #8                  // Method java/lang/String.equals:(Ljava/lang/Object;)Z
     125: ifeq          132
     128: getstatic     #26                 // Field MECHANICAL:Lorg/hl7/fhir/dstu3/model/codesystems/MeasurementPrinciple;
     131: areturn
     132: ldc           #27                 // String acoustical
     134: aload_0
     135: invokevirtual #8                  // Method java/lang/String.equals:(Ljava/lang/Object;)Z
     138: ifeq          145
     141: getstatic     #28                 // Field ACOUSTICAL:Lorg/hl7/fhir/dstu3/model/codesystems/MeasurementPrinciple;
     144: areturn
     145: ldc           #29                 // String manual
     147: aload_0
     148: invokevirtual #8                  // Method java/lang/String.equals:(Ljava/lang/Object;)Z
     151: ifeq          158
     154: getstatic     #30                 // Field MANUAL:Lorg/hl7/fhir/dstu3/model/codesystems/MeasurementPrinciple;
     157: areturn
     158: new           #31                 // class org/hl7/fhir/exceptions/FHIRException
     161: dup
     162: new           #32                 // class java/lang/StringBuilder
     165: dup
     166: invokespecial #33                 // Method java/lang/StringBuilder."<init>":()V
     169: ldc           #34                 // String Unknown MeasurementPrinciple code \'
     171: invokevirtual #35                 // Method java/lang/StringBuilder.append:(Ljava/lang/String;)Ljava/lang/StringBuilder;
     174: aload_0
     175: invokevirtual #35                 // Method java/lang/StringBuilder.append:(Ljava/lang/String;)Ljava/lang/StringBuilder;
     178: ldc           #36                 // String \'
     180: invokevirtual #35                 // Method java/lang/StringBuilder.append:(Ljava/lang/String;)Ljava/lang/StringBuilder;
     183: invokevirtual #37                 // Method java/lang/StringBuilder.toString:()Ljava/lang/String;
     186: invokespecial #38                 // Method org/hl7/fhir/exceptions/FHIRException."<init>":(Ljava/lang/String;)V
     189: athrow

  public java.lang.String toCode();
    Code:
       0: getstatic     #39                 // Field org/hl7/fhir/dstu3/model/codesystems/MeasurementPrinciple$1.$SwitchMap$org$hl7$fhir$dstu3$model$codesystems$MeasurementPrinciple:[I
       3: aload_0
       4: invokevirtual #40                 // Method ordinal:()I
       7: iaload
       8: tableswitch   { // 1 to 12
                     1: 72
                     2: 75
                     3: 78
                     4: 81
                     5: 84
                     6: 87
                     7: 90
                     8: 93
                     9: 96
                    10: 99
                    11: 102
                    12: 105
               default: 107
          }
      72: ldc           #9                  // String other
      74: areturn
      75: ldc           #11                 // String chemical
      77: areturn
      78: ldc           #13                 // String electrical
      80: areturn
      81: ldc           #15                 // String impedance
      83: areturn
      84: ldc           #17                 // String nuclear
      86: areturn
      87: ldc           #19                 // String optical
      89: areturn
      90: ldc           #21                 // String thermal
      92: areturn
      93: ldc           #23                 // String biological
      95: areturn
      96: ldc           #25                 // String mechanical
      98: areturn
      99: ldc           #27                 // String acoustical
     101: areturn
     102: ldc           #29                 // String manual
     104: areturn
     105: aconst_null
     106: areturn
     107: ldc           #41                 // String ?
     109: areturn

  public java.lang.String getSystem();
    Code:
       0: ldc           #42                 // String http://hl7.org/fhir/measurement-principle
       2: areturn

  public java.lang.String getDefinition();
    Code:
       0: getstatic     #39                 // Field org/hl7/fhir/dstu3/model/codesystems/MeasurementPrinciple$1.$SwitchMap$org$hl7$fhir$dstu3$model$codesystems$MeasurementPrinciple:[I
       3: aload_0
       4: invokevirtual #40                 // Method ordinal:()I
       7: iaload
       8: tableswitch   { // 1 to 12
                     1: 72
                     2: 75
                     3: 78
                     4: 81
                     5: 84
                     6: 87
                     7: 90
                     8: 93
                     9: 96
                    10: 99
                    11: 102
                    12: 105
               default: 107
          }
      72: ldc           #43                 // String Measurement principle isn\'t in the list.
      74: areturn
      75: ldc           #44                 // String Measurement is done using the chemical principle.
      77: areturn
      78: ldc           #45                 // String Measurement is done using the electrical principle.
      80: areturn
      81: ldc           #46                 // String Measurement is done using the impedance principle.
      83: areturn
      84: ldc           #47                 // String Measurement is done using the nuclear principle.
      86: areturn
      87: ldc           #48                 // String Measurement is done using the optical principle.
      89: areturn
      90: ldc           #49                 // String Measurement is done using the thermal principle.
      92: areturn
      93: ldc           #50                 // String Measurement is done using the biological principle.
      95: areturn
      96: ldc           #51                 // String Measurement is done using the mechanical principle.
      98: areturn
      99: ldc           #52                 // String Measurement is done using the acoustical principle.
     101: areturn
     102: ldc           #53                 // String Measurement is done using the manual principle.
     104: areturn
     105: aconst_null
     106: areturn
     107: ldc           #41                 // String ?
     109: areturn

  public java.lang.String getDisplay();
    Code:
       0: getstatic     #39                 // Field org/hl7/fhir/dstu3/model/codesystems/MeasurementPrinciple$1.$SwitchMap$org$hl7$fhir$dstu3$model$codesystems$MeasurementPrinciple:[I
       3: aload_0
       4: invokevirtual #40                 // Method ordinal:()I
       7: iaload
       8: tableswitch   { // 1 to 12
                     1: 72
                     2: 75
                     3: 78
                     4: 81
                     5: 84
                     6: 87
                     7: 90
                     8: 93
                     9: 96
                    10: 99
                    11: 102
                    12: 105
               default: 107
          }
      72: ldc           #54                 // String MSP Other
      74: areturn
      75: ldc           #55                 // String MSP Chemical
      77: areturn
      78: ldc           #56                 // String MSP Electrical
      80: areturn
      81: ldc           #57                 // String MSP Impedance
      83: areturn
      84: ldc           #58                 // String MSP Nuclear
      86: areturn
      87: ldc           #59                 // String MSP Optical
      89: areturn
      90: ldc           #60                 // String MSP Thermal
      92: areturn
      93: ldc           #61                 // String MSP Biological
      95: areturn
      96: ldc           #62                 // String MSP Mechanical
      98: areturn
      99: ldc           #63                 // String MSP Acoustical
     101: areturn
     102: ldc           #64                 // String MSP Manual
     104: areturn
     105: aconst_null
     106: areturn
     107: ldc           #41                 // String ?
     109: areturn

  static {};
    Code:
       0: new           #4                  // class org/hl7/fhir/dstu3/model/codesystems/MeasurementPrinciple
       3: dup
       4: ldc           #65                 // String OTHER
       6: iconst_0
       7: invokespecial #66                 // Method "<init>":(Ljava/lang/String;I)V
      10: putstatic     #10                 // Field OTHER:Lorg/hl7/fhir/dstu3/model/codesystems/MeasurementPrinciple;
      13: new           #4                  // class org/hl7/fhir/dstu3/model/codesystems/MeasurementPrinciple
      16: dup
      17: ldc           #67                 // String CHEMICAL
      19: iconst_1
      20: invokespecial #66                 // Method "<init>":(Ljava/lang/String;I)V
      23: putstatic     #12                 // Field CHEMICAL:Lorg/hl7/fhir/dstu3/model/codesystems/MeasurementPrinciple;
      26: new           #4                  // class org/hl7/fhir/dstu3/model/codesystems/MeasurementPrinciple
      29: dup
      30: ldc           #68                 // String ELECTRICAL
      32: iconst_2
      33: invokespecial #66                 // Method "<init>":(Ljava/lang/String;I)V
      36: putstatic     #14                 // Field ELECTRICAL:Lorg/hl7/fhir/dstu3/model/codesystems/MeasurementPrinciple;
      39: new           #4                  // class org/hl7/fhir/dstu3/model/codesystems/MeasurementPrinciple
      42: dup
      43: ldc           #69                 // String IMPEDANCE
      45: iconst_3
      46: invokespecial #66                 // Method "<init>":(Ljava/lang/String;I)V
      49: putstatic     #16                 // Field IMPEDANCE:Lorg/hl7/fhir/dstu3/model/codesystems/MeasurementPrinciple;
      52: new           #4                  // class org/hl7/fhir/dstu3/model/codesystems/MeasurementPrinciple
      55: dup
      56: ldc           #70                 // String NUCLEAR
      58: iconst_4
      59: invokespecial #66                 // Method "<init>":(Ljava/lang/String;I)V
      62: putstatic     #18                 // Field NUCLEAR:Lorg/hl7/fhir/dstu3/model/codesystems/MeasurementPrinciple;
      65: new           #4                  // class org/hl7/fhir/dstu3/model/codesystems/MeasurementPrinciple
      68: dup
      69: ldc           #71                 // String OPTICAL
      71: iconst_5
      72: invokespecial #66                 // Method "<init>":(Ljava/lang/String;I)V
      75: putstatic     #20                 // Field OPTICAL:Lorg/hl7/fhir/dstu3/model/codesystems/MeasurementPrinciple;
      78: new           #4                  // class org/hl7/fhir/dstu3/model/codesystems/MeasurementPrinciple
      81: dup
      82: ldc           #72                 // String THERMAL
      84: bipush        6
      86: invokespecial #66                 // Method "<init>":(Ljava/lang/String;I)V
      89: putstatic     #22                 // Field THERMAL:Lorg/hl7/fhir/dstu3/model/codesystems/MeasurementPrinciple;
      92: new           #4                  // class org/hl7/fhir/dstu3/model/codesystems/MeasurementPrinciple
      95: dup
      96: ldc           #73                 // String BIOLOGICAL
      98: bipush        7
     100: invokespecial #66                 // Method "<init>":(Ljava/lang/String;I)V
     103: putstatic     #24                 // Field BIOLOGICAL:Lorg/hl7/fhir/dstu3/model/codesystems/MeasurementPrinciple;
     106: new           #4                  // class org/hl7/fhir/dstu3/model/codesystems/MeasurementPrinciple
     109: dup
     110: ldc           #74                 // String MECHANICAL
     112: bipush        8
     114: invokespecial #66                 // Method "<init>":(Ljava/lang/String;I)V
     117: putstatic     #26                 // Field MECHANICAL:Lorg/hl7/fhir/dstu3/model/codesystems/MeasurementPrinciple;
     120: new           #4                  // class org/hl7/fhir/dstu3/model/codesystems/MeasurementPrinciple
     123: dup
     124: ldc           #75                 // String ACOUSTICAL
     126: bipush        9
     128: invokespecial #66                 // Method "<init>":(Ljava/lang/String;I)V
     131: putstatic     #28                 // Field ACOUSTICAL:Lorg/hl7/fhir/dstu3/model/codesystems/MeasurementPrinciple;
     134: new           #4                  // class org/hl7/fhir/dstu3/model/codesystems/MeasurementPrinciple
     137: dup
     138: ldc           #76                 // String MANUAL
     140: bipush        10
     142: invokespecial #66                 // Method "<init>":(Ljava/lang/String;I)V
     145: putstatic     #30                 // Field MANUAL:Lorg/hl7/fhir/dstu3/model/codesystems/MeasurementPrinciple;
     148: new           #4                  // class org/hl7/fhir/dstu3/model/codesystems/MeasurementPrinciple
     151: dup
     152: ldc           #77                 // String NULL
     154: bipush        11
     156: invokespecial #66                 // Method "<init>":(Ljava/lang/String;I)V
     159: putstatic     #78                 // Field NULL:Lorg/hl7/fhir/dstu3/model/codesystems/MeasurementPrinciple;
     162: bipush        12
     164: anewarray     #4                  // class org/hl7/fhir/dstu3/model/codesystems/MeasurementPrinciple
     167: dup
     168: iconst_0
     169: getstatic     #10                 // Field OTHER:Lorg/hl7/fhir/dstu3/model/codesystems/MeasurementPrinciple;
     172: aastore
     173: dup
     174: iconst_1
     175: getstatic     #12                 // Field CHEMICAL:Lorg/hl7/fhir/dstu3/model/codesystems/MeasurementPrinciple;
     178: aastore
     179: dup
     180: iconst_2
     181: getstatic     #14                 // Field ELECTRICAL:Lorg/hl7/fhir/dstu3/model/codesystems/MeasurementPrinciple;
     184: aastore
     185: dup
     186: iconst_3
     187: getstatic     #16                 // Field IMPEDANCE:Lorg/hl7/fhir/dstu3/model/codesystems/MeasurementPrinciple;
     190: aastore
     191: dup
     192: iconst_4
     193: getstatic     #18                 // Field NUCLEAR:Lorg/hl7/fhir/dstu3/model/codesystems/MeasurementPrinciple;
     196: aastore
     197: dup
     198: iconst_5
     199: getstatic     #20                 // Field OPTICAL:Lorg/hl7/fhir/dstu3/model/codesystems/MeasurementPrinciple;
     202: aastore
     203: dup
     204: bipush        6
     206: getstatic     #22                 // Field THERMAL:Lorg/hl7/fhir/dstu3/model/codesystems/MeasurementPrinciple;
     209: aastore
     210: dup
     211: bipush        7
     213: getstatic     #24                 // Field BIOLOGICAL:Lorg/hl7/fhir/dstu3/model/codesystems/MeasurementPrinciple;
     216: aastore
     217: dup
     218: bipush        8
     220: getstatic     #26                 // Field MECHANICAL:Lorg/hl7/fhir/dstu3/model/codesystems/MeasurementPrinciple;
     223: aastore
     224: dup
     225: bipush        9
     227: getstatic     #28                 // Field ACOUSTICAL:Lorg/hl7/fhir/dstu3/model/codesystems/MeasurementPrinciple;
     230: aastore
     231: dup
     232: bipush        10
     234: getstatic     #30                 // Field MANUAL:Lorg/hl7/fhir/dstu3/model/codesystems/MeasurementPrinciple;
     237: aastore
     238: dup
     239: bipush        11
     241: getstatic     #78                 // Field NULL:Lorg/hl7/fhir/dstu3/model/codesystems/MeasurementPrinciple;
     244: aastore
     245: putstatic     #1                  // Field $VALUES:[Lorg/hl7/fhir/dstu3/model/codesystems/MeasurementPrinciple;
     248: return
}
