Compiled from "MetricCategory.java"
class org.hl7.fhir.dstu3.model.codesystems.MetricCategory$1 {
  static final int[] $SwitchMap$org$hl7$fhir$dstu3$model$codesystems$MetricCategory;

  static {};
    Code:
       0: invokestatic  #1                  // Method org/hl7/fhir/dstu3/model/codesystems/MetricCategory.values:()[Lorg/hl7/fhir/dstu3/model/codesystems/MetricCategory;
       3: arraylength
       4: newarray       int
       6: putstatic     #2                  // Field $SwitchMap$org$hl7$fhir$dstu3$model$codesystems$MetricCategory:[I
       9: getstatic     #2                  // Field $SwitchMap$org$hl7$fhir$dstu3$model$codesystems$MetricCategory:[I
      12: getstatic     #3                  // Field org/hl7/fhir/dstu3/model/codesystems/MetricCategory.MEASUREMENT:Lorg/hl7/fhir/dstu3/model/codesystems/MetricCategory;
      15: invokevirtual #4                  // Method org/hl7/fhir/dstu3/model/codesystems/MetricCategory.ordinal:()I
      18: iconst_1
      19: iastore
      20: goto          24
      23: astore_0
      24: getstatic     #2                  // Field $SwitchMap$org$hl7$fhir$dstu3$model$codesystems$MetricCategory:[I
      27: getstatic     #6                  // Field org/hl7/fhir/dstu3/model/codesystems/MetricCategory.SETTING:Lorg/hl7/fhir/dstu3/model/codesystems/MetricCategory;
      30: invokevirtual #4                  // Method org/hl7/fhir/dstu3/model/codesystems/MetricCategory.ordinal:()I
      33: iconst_2
      34: iastore
      35: goto          39
      38: astore_0
      39: getstatic     #2                  // Field $SwitchMap$org$hl7$fhir$dstu3$model$codesystems$MetricCategory:[I
      42: getstatic     #7                  // Field org/hl7/fhir/dstu3/model/codesystems/MetricCategory.CALCULATION:Lorg/hl7/fhir/dstu3/model/codesystems/MetricCategory;
      45: invokevirtual #4                  // Method org/hl7/fhir/dstu3/model/codesystems/MetricCategory.ordinal:()I
      48: iconst_3
      49: iastore
      50: goto          54
      53: astore_0
      54: getstatic     #2                  // Field $SwitchMap$org$hl7$fhir$dstu3$model$codesystems$MetricCategory:[I
      57: getstatic     #8                  // Field org/hl7/fhir/dstu3/model/codesystems/MetricCategory.UNSPECIFIED:Lorg/hl7/fhir/dstu3/model/codesystems/MetricCategory;
      60: invokevirtual #4                  // Method org/hl7/fhir/dstu3/model/codesystems/MetricCategory.ordinal:()I
      63: iconst_4
      64: iastore
      65: goto          69
      68: astore_0
      69: getstatic     #2                  // Field $SwitchMap$org$hl7$fhir$dstu3$model$codesystems$MetricCategory:[I
      72: getstatic     #9                  // Field org/hl7/fhir/dstu3/model/codesystems/MetricCategory.NULL:Lorg/hl7/fhir/dstu3/model/codesystems/MetricCategory;
      75: invokevirtual #4                  // Method org/hl7/fhir/dstu3/model/codesystems/MetricCategory.ordinal:()I
      78: iconst_5
      79: iastore
      80: goto          84
      83: astore_0
      84: return
    Exception table:
       from    to  target type
           9    20    23   Class java/lang/NoSuchFieldError
          24    35    38   Class java/lang/NoSuchFieldError
          39    50    53   Class java/lang/NoSuchFieldError
          54    65    68   Class java/lang/NoSuchFieldError
          69    80    83   Class java/lang/NoSuchFieldError
}
