Compiled from "RequestStatusEnumFactory.java"
public class org.hl7.fhir.dstu3.model.codesystems.RequestStatusEnumFactory implements org.hl7.fhir.dstu3.model.EnumFactory<org.hl7.fhir.dstu3.model.codesystems.RequestStatus> {
  public org.hl7.fhir.dstu3.model.codesystems.RequestStatusEnumFactory();
    Code:
       0: aload_0
       1: invokespecial #1                  // Method java/lang/Object."<init>":()V
       4: return

  public org.hl7.fhir.dstu3.model.codesystems.RequestStatus fromCode(java.lang.String) throws java.lang.IllegalArgumentException;
    Code:
       0: aload_1
       1: ifnull        13
       4: ldc           #2                  // String
       6: aload_1
       7: invokevirtual #3                  // Method java/lang/String.equals:(Ljava/lang/Object;)Z
      10: ifeq          15
      13: aconst_null
      14: areturn
      15: ldc           #4                  // String draft
      17: aload_1
      18: invokevirtual #3                  // Method java/lang/String.equals:(Ljava/lang/Object;)Z
      21: ifeq          28
      24: getstatic     #5                  // Field org/hl7/fhir/dstu3/model/codesystems/RequestStatus.DRAFT:Lorg/hl7/fhir/dstu3/model/codesystems/RequestStatus;
      27: areturn
      28: ldc           #6                  // String active
      30: aload_1
      31: invokevirtual #3                  // Method java/lang/String.equals:(Ljava/lang/Object;)Z
      34: ifeq          41
      37: getstatic     #7                  // Field org/hl7/fhir/dstu3/model/codesystems/RequestStatus.ACTIVE:Lorg/hl7/fhir/dstu3/model/codesystems/RequestStatus;
      40: areturn
      41: ldc           #8                  // String suspended
      43: aload_1
      44: invokevirtual #3                  // Method java/lang/String.equals:(Ljava/lang/Object;)Z
      47: ifeq          54
      50: getstatic     #9                  // Field org/hl7/fhir/dstu3/model/codesystems/RequestStatus.SUSPENDED:Lorg/hl7/fhir/dstu3/model/codesystems/RequestStatus;
      53: areturn
      54: ldc           #10                 // String cancelled
      56: aload_1
      57: invokevirtual #3                  // Method java/lang/String.equals:(Ljava/lang/Object;)Z
      60: ifeq          67
      63: getstatic     #11                 // Field org/hl7/fhir/dstu3/model/codesystems/RequestStatus.CANCELLED:Lorg/hl7/fhir/dstu3/model/codesystems/RequestStatus;
      66: areturn
      67: ldc           #12                 // String completed
      69: aload_1
      70: invokevirtual #3                  // Method java/lang/String.equals:(Ljava/lang/Object;)Z
      73: ifeq          80
      76: getstatic     #13                 // Field org/hl7/fhir/dstu3/model/codesystems/RequestStatus.COMPLETED:Lorg/hl7/fhir/dstu3/model/codesystems/RequestStatus;
      79: areturn
      80: ldc           #14                 // String entered-in-error
      82: aload_1
      83: invokevirtual #3                  // Method java/lang/String.equals:(Ljava/lang/Object;)Z
      86: ifeq          93
      89: getstatic     #15                 // Field org/hl7/fhir/dstu3/model/codesystems/RequestStatus.ENTEREDINERROR:Lorg/hl7/fhir/dstu3/model/codesystems/RequestStatus;
      92: areturn
      93: ldc           #16                 // String unknown
      95: aload_1
      96: invokevirtual #3                  // Method java/lang/String.equals:(Ljava/lang/Object;)Z
      99: ifeq          106
     102: getstatic     #17                 // Field org/hl7/fhir/dstu3/model/codesystems/RequestStatus.UNKNOWN:Lorg/hl7/fhir/dstu3/model/codesystems/RequestStatus;
     105: areturn
     106: new           #18                 // class java/lang/IllegalArgumentException
     109: dup
     110: new           #19                 // class java/lang/StringBuilder
     113: dup
     114: invokespecial #20                 // Method java/lang/StringBuilder."<init>":()V
     117: ldc           #21                 // String Unknown RequestStatus code \'
     119: invokevirtual #22                 // Method java/lang/StringBuilder.append:(Ljava/lang/String;)Ljava/lang/StringBuilder;
     122: aload_1
     123: invokevirtual #22                 // Method java/lang/StringBuilder.append:(Ljava/lang/String;)Ljava/lang/StringBuilder;
     126: ldc           #23                 // String \'
     128: invokevirtual #22                 // Method java/lang/StringBuilder.append:(Ljava/lang/String;)Ljava/lang/StringBuilder;
     131: invokevirtual #24                 // Method java/lang/StringBuilder.toString:()Ljava/lang/String;
     134: invokespecial #25                 // Method java/lang/IllegalArgumentException."<init>":(Ljava/lang/String;)V
     137: athrow

  public java.lang.String toCode(org.hl7.fhir.dstu3.model.codesystems.RequestStatus);
    Code:
       0: aload_1
       1: getstatic     #5                  // Field org/hl7/fhir/dstu3/model/codesystems/RequestStatus.DRAFT:Lorg/hl7/fhir/dstu3/model/codesystems/RequestStatus;
       4: if_acmpne     10
       7: ldc           #4                  // String draft
       9: areturn
      10: aload_1
      11: getstatic     #7                  // Field org/hl7/fhir/dstu3/model/codesystems/RequestStatus.ACTIVE:Lorg/hl7/fhir/dstu3/model/codesystems/RequestStatus;
      14: if_acmpne     20
      17: ldc           #6                  // String active
      19: areturn
      20: aload_1
      21: getstatic     #9                  // Field org/hl7/fhir/dstu3/model/codesystems/RequestStatus.SUSPENDED:Lorg/hl7/fhir/dstu3/model/codesystems/RequestStatus;
      24: if_acmpne     30
      27: ldc           #8                  // String suspended
      29: areturn
      30: aload_1
      31: getstatic     #11                 // Field org/hl7/fhir/dstu3/model/codesystems/RequestStatus.CANCELLED:Lorg/hl7/fhir/dstu3/model/codesystems/RequestStatus;
      34: if_acmpne     40
      37: ldc           #10                 // String cancelled
      39: areturn
      40: aload_1
      41: getstatic     #13                 // Field org/hl7/fhir/dstu3/model/codesystems/RequestStatus.COMPLETED:Lorg/hl7/fhir/dstu3/model/codesystems/RequestStatus;
      44: if_acmpne     50
      47: ldc           #12                 // String completed
      49: areturn
      50: aload_1
      51: getstatic     #15                 // Field org/hl7/fhir/dstu3/model/codesystems/RequestStatus.ENTEREDINERROR:Lorg/hl7/fhir/dstu3/model/codesystems/RequestStatus;
      54: if_acmpne     60
      57: ldc           #14                 // String entered-in-error
      59: areturn
      60: aload_1
      61: getstatic     #17                 // Field org/hl7/fhir/dstu3/model/codesystems/RequestStatus.UNKNOWN:Lorg/hl7/fhir/dstu3/model/codesystems/RequestStatus;
      64: if_acmpne     70
      67: ldc           #16                 // String unknown
      69: areturn
      70: ldc           #26                 // String ?
      72: areturn

  public java.lang.String toSystem(org.hl7.fhir.dstu3.model.codesystems.RequestStatus);
    Code:
       0: aload_1
       1: invokevirtual #27                 // Method org/hl7/fhir/dstu3/model/codesystems/RequestStatus.getSystem:()Ljava/lang/String;
       4: areturn

  public java.lang.String toSystem(java.lang.Enum);
    Code:
       0: aload_0
       1: aload_1
       2: checkcast     #28                 // class org/hl7/fhir/dstu3/model/codesystems/RequestStatus
       5: invokevirtual #29                 // Method toSystem:(Lorg/hl7/fhir/dstu3/model/codesystems/RequestStatus;)Ljava/lang/String;
       8: areturn

  public java.lang.String toCode(java.lang.Enum);
    Code:
       0: aload_0
       1: aload_1
       2: checkcast     #28                 // class org/hl7/fhir/dstu3/model/codesystems/RequestStatus
       5: invokevirtual #30                 // Method toCode:(Lorg/hl7/fhir/dstu3/model/codesystems/RequestStatus;)Ljava/lang/String;
       8: areturn

  public java.lang.Enum fromCode(java.lang.String) throws java.lang.IllegalArgumentException;
    Code:
       0: aload_0
       1: aload_1
       2: invokevirtual #31                 // Method fromCode:(Ljava/lang/String;)Lorg/hl7/fhir/dstu3/model/codesystems/RequestStatus;
       5: areturn
}
