Compiled from "RestfulSecurityService.java"
public final class org.hl7.fhir.dstu3.model.codesystems.RestfulSecurityService extends java.lang.Enum<org.hl7.fhir.dstu3.model.codesystems.RestfulSecurityService> {
  public static final org.hl7.fhir.dstu3.model.codesystems.RestfulSecurityService OAUTH;

  public static final org.hl7.fhir.dstu3.model.codesystems.RestfulSecurityService SMARTONFHIR;

  public static final org.hl7.fhir.dstu3.model.codesystems.RestfulSecurityService NTLM;

  public static final org.hl7.fhir.dstu3.model.codesystems.RestfulSecurityService BASIC;

  public static final org.hl7.fhir.dstu3.model.codesystems.RestfulSecurityService KERBEROS;

  public static final org.hl7.fhir.dstu3.model.codesystems.RestfulSecurityService CERTIFICATES;

  public static final org.hl7.fhir.dstu3.model.codesystems.RestfulSecurityService NULL;

  private static final org.hl7.fhir.dstu3.model.codesystems.RestfulSecurityService[] $VALUES;

  public static org.hl7.fhir.dstu3.model.codesystems.RestfulSecurityService[] values();
    Code:
       0: getstatic     #1                  // Field $VALUES:[Lorg/hl7/fhir/dstu3/model/codesystems/RestfulSecurityService;
       3: invokevirtual #2                  // Method "[Lorg/hl7/fhir/dstu3/model/codesystems/RestfulSecurityService;".clone:()Ljava/lang/Object;
       6: checkcast     #3                  // class "[Lorg/hl7/fhir/dstu3/model/codesystems/RestfulSecurityService;"
       9: areturn

  public static org.hl7.fhir.dstu3.model.codesystems.RestfulSecurityService valueOf(java.lang.String);
    Code:
       0: ldc           #4                  // class org/hl7/fhir/dstu3/model/codesystems/RestfulSecurityService
       2: aload_0
       3: invokestatic  #5                  // Method java/lang/Enum.valueOf:(Ljava/lang/Class;Ljava/lang/String;)Ljava/lang/Enum;
       6: checkcast     #4                  // class org/hl7/fhir/dstu3/model/codesystems/RestfulSecurityService
       9: areturn

  private org.hl7.fhir.dstu3.model.codesystems.RestfulSecurityService();
    Code:
       0: aload_0
       1: aload_1
       2: iload_2
       3: invokespecial #6                  // Method java/lang/Enum."<init>":(Ljava/lang/String;I)V
       6: return

  public static org.hl7.fhir.dstu3.model.codesystems.RestfulSecurityService fromCode(java.lang.String) throws org.hl7.fhir.exceptions.FHIRException;
    Code:
       0: aload_0
       1: ifnull        13
       4: ldc           #7                  // String
       6: aload_0
       7: invokevirtual #8                  // Method java/lang/String.equals:(Ljava/lang/Object;)Z
      10: ifeq          15
      13: aconst_null
      14: areturn
      15: ldc           #9                  // String OAuth
      17: aload_0
      18: invokevirtual #8                  // Method java/lang/String.equals:(Ljava/lang/Object;)Z
      21: ifeq          28
      24: getstatic     #10                 // Field OAUTH:Lorg/hl7/fhir/dstu3/model/codesystems/RestfulSecurityService;
      27: areturn
      28: ldc           #11                 // String SMART-on-FHIR
      30: aload_0
      31: invokevirtual #8                  // Method java/lang/String.equals:(Ljava/lang/Object;)Z
      34: ifeq          41
      37: getstatic     #12                 // Field SMARTONFHIR:Lorg/hl7/fhir/dstu3/model/codesystems/RestfulSecurityService;
      40: areturn
      41: ldc           #13                 // String NTLM
      43: aload_0
      44: invokevirtual #8                  // Method java/lang/String.equals:(Ljava/lang/Object;)Z
      47: ifeq          54
      50: getstatic     #14                 // Field NTLM:Lorg/hl7/fhir/dstu3/model/codesystems/RestfulSecurityService;
      53: areturn
      54: ldc           #15                 // String Basic
      56: aload_0
      57: invokevirtual #8                  // Method java/lang/String.equals:(Ljava/lang/Object;)Z
      60: ifeq          67
      63: getstatic     #16                 // Field BASIC:Lorg/hl7/fhir/dstu3/model/codesystems/RestfulSecurityService;
      66: areturn
      67: ldc           #17                 // String Kerberos
      69: aload_0
      70: invokevirtual #8                  // Method java/lang/String.equals:(Ljava/lang/Object;)Z
      73: ifeq          80
      76: getstatic     #18                 // Field KERBEROS:Lorg/hl7/fhir/dstu3/model/codesystems/RestfulSecurityService;
      79: areturn
      80: ldc           #19                 // String Certificates
      82: aload_0
      83: invokevirtual #8                  // Method java/lang/String.equals:(Ljava/lang/Object;)Z
      86: ifeq          93
      89: getstatic     #20                 // Field CERTIFICATES:Lorg/hl7/fhir/dstu3/model/codesystems/RestfulSecurityService;
      92: areturn
      93: new           #21                 // class org/hl7/fhir/exceptions/FHIRException
      96: dup
      97: new           #22                 // class java/lang/StringBuilder
     100: dup
     101: invokespecial #23                 // Method java/lang/StringBuilder."<init>":()V
     104: ldc           #24                 // String Unknown RestfulSecurityService code \'
     106: invokevirtual #25                 // Method java/lang/StringBuilder.append:(Ljava/lang/String;)Ljava/lang/StringBuilder;
     109: aload_0
     110: invokevirtual #25                 // Method java/lang/StringBuilder.append:(Ljava/lang/String;)Ljava/lang/StringBuilder;
     113: ldc           #26                 // String \'
     115: invokevirtual #25                 // Method java/lang/StringBuilder.append:(Ljava/lang/String;)Ljava/lang/StringBuilder;
     118: invokevirtual #27                 // Method java/lang/StringBuilder.toString:()Ljava/lang/String;
     121: invokespecial #28                 // Method org/hl7/fhir/exceptions/FHIRException."<init>":(Ljava/lang/String;)V
     124: athrow

  public java.lang.String toCode();
    Code:
       0: getstatic     #29                 // Field org/hl7/fhir/dstu3/model/codesystems/RestfulSecurityService$1.$SwitchMap$org$hl7$fhir$dstu3$model$codesystems$RestfulSecurityService:[I
       3: aload_0
       4: invokevirtual #30                 // Method ordinal:()I
       7: iaload
       8: tableswitch   { // 1 to 7
                     1: 52
                     2: 55
                     3: 58
                     4: 61
                     5: 64
                     6: 67
                     7: 70
               default: 72
          }
      52: ldc           #9                  // String OAuth
      54: areturn
      55: ldc           #11                 // String SMART-on-FHIR
      57: areturn
      58: ldc           #13                 // String NTLM
      60: areturn
      61: ldc           #15                 // String Basic
      63: areturn
      64: ldc           #17                 // String Kerberos
      66: areturn
      67: ldc           #19                 // String Certificates
      69: areturn
      70: aconst_null
      71: areturn
      72: ldc           #31                 // String ?
      74: areturn

  public java.lang.String getSystem();
    Code:
       0: ldc           #32                 // String http://hl7.org/fhir/restful-security-service
       2: areturn

  public java.lang.String getDefinition();
    Code:
       0: getstatic     #29                 // Field org/hl7/fhir/dstu3/model/codesystems/RestfulSecurityService$1.$SwitchMap$org$hl7$fhir$dstu3$model$codesystems$RestfulSecurityService:[I
       3: aload_0
       4: invokevirtual #30                 // Method ordinal:()I
       7: iaload
       8: tableswitch   { // 1 to 7
                     1: 52
                     2: 55
                     3: 58
                     4: 61
                     5: 64
                     6: 67
                     7: 70
               default: 72
          }
      52: ldc           #33                 // String Oauth (unspecified version see oauth.net).
      54: areturn
      55: ldc           #34                 // String OAuth2 using SMART-on-FHIR profile (see http://docs.smarthealthit.org/).
      57: areturn
      58: ldc           #35                 // String Microsoft NTLM Authentication.
      60: areturn
      61: ldc           #36                 // String Basic authentication defined in HTTP specification.
      63: areturn
      64: ldc           #37                 // String see http://www.ietf.org/rfc/rfc4120.txt.
      66: areturn
      67: ldc           #38                 // String SSL where client must have a certificate registered with the server.
      69: areturn
      70: aconst_null
      71: areturn
      72: ldc           #31                 // String ?
      74: areturn

  public java.lang.String getDisplay();
    Code:
       0: getstatic     #29                 // Field org/hl7/fhir/dstu3/model/codesystems/RestfulSecurityService$1.$SwitchMap$org$hl7$fhir$dstu3$model$codesystems$RestfulSecurityService:[I
       3: aload_0
       4: invokevirtual #30                 // Method ordinal:()I
       7: iaload
       8: tableswitch   { // 1 to 7
                     1: 52
                     2: 55
                     3: 58
                     4: 61
                     5: 64
                     6: 67
                     7: 70
               default: 72
          }
      52: ldc           #9                  // String OAuth
      54: areturn
      55: ldc           #11                 // String SMART-on-FHIR
      57: areturn
      58: ldc           #13                 // String NTLM
      60: areturn
      61: ldc           #15                 // String Basic
      63: areturn
      64: ldc           #17                 // String Kerberos
      66: areturn
      67: ldc           #19                 // String Certificates
      69: areturn
      70: aconst_null
      71: areturn
      72: ldc           #31                 // String ?
      74: areturn

  static {};
    Code:
       0: new           #4                  // class org/hl7/fhir/dstu3/model/codesystems/RestfulSecurityService
       3: dup
       4: ldc           #39                 // String OAUTH
       6: iconst_0
       7: invokespecial #40                 // Method "<init>":(Ljava/lang/String;I)V
      10: putstatic     #10                 // Field OAUTH:Lorg/hl7/fhir/dstu3/model/codesystems/RestfulSecurityService;
      13: new           #4                  // class org/hl7/fhir/dstu3/model/codesystems/RestfulSecurityService
      16: dup
      17: ldc           #41                 // String SMARTONFHIR
      19: iconst_1
      20: invokespecial #40                 // Method "<init>":(Ljava/lang/String;I)V
      23: putstatic     #12                 // Field SMARTONFHIR:Lorg/hl7/fhir/dstu3/model/codesystems/RestfulSecurityService;
      26: new           #4                  // class org/hl7/fhir/dstu3/model/codesystems/RestfulSecurityService
      29: dup
      30: ldc           #13                 // String NTLM
      32: iconst_2
      33: invokespecial #40                 // Method "<init>":(Ljava/lang/String;I)V
      36: putstatic     #14                 // Field NTLM:Lorg/hl7/fhir/dstu3/model/codesystems/RestfulSecurityService;
      39: new           #4                  // class org/hl7/fhir/dstu3/model/codesystems/RestfulSecurityService
      42: dup
      43: ldc           #42                 // String BASIC
      45: iconst_3
      46: invokespecial #40                 // Method "<init>":(Ljava/lang/String;I)V
      49: putstatic     #16                 // Field BASIC:Lorg/hl7/fhir/dstu3/model/codesystems/RestfulSecurityService;
      52: new           #4                  // class org/hl7/fhir/dstu3/model/codesystems/RestfulSecurityService
      55: dup
      56: ldc           #43                 // String KERBEROS
      58: iconst_4
      59: invokespecial #40                 // Method "<init>":(Ljava/lang/String;I)V
      62: putstatic     #18                 // Field KERBEROS:Lorg/hl7/fhir/dstu3/model/codesystems/RestfulSecurityService;
      65: new           #4                  // class org/hl7/fhir/dstu3/model/codesystems/RestfulSecurityService
      68: dup
      69: ldc           #44                 // String CERTIFICATES
      71: iconst_5
      72: invokespecial #40                 // Method "<init>":(Ljava/lang/String;I)V
      75: putstatic     #20                 // Field CERTIFICATES:Lorg/hl7/fhir/dstu3/model/codesystems/RestfulSecurityService;
      78: new           #4                  // class org/hl7/fhir/dstu3/model/codesystems/RestfulSecurityService
      81: dup
      82: ldc           #45                 // String NULL
      84: bipush        6
      86: invokespecial #40                 // Method "<init>":(Ljava/lang/String;I)V
      89: putstatic     #46                 // Field NULL:Lorg/hl7/fhir/dstu3/model/codesystems/RestfulSecurityService;
      92: bipush        7
      94: anewarray     #4                  // class org/hl7/fhir/dstu3/model/codesystems/RestfulSecurityService
      97: dup
      98: iconst_0
      99: getstatic     #10                 // Field OAUTH:Lorg/hl7/fhir/dstu3/model/codesystems/RestfulSecurityService;
     102: aastore
     103: dup
     104: iconst_1
     105: getstatic     #12                 // Field SMARTONFHIR:Lorg/hl7/fhir/dstu3/model/codesystems/RestfulSecurityService;
     108: aastore
     109: dup
     110: iconst_2
     111: getstatic     #14                 // Field NTLM:Lorg/hl7/fhir/dstu3/model/codesystems/RestfulSecurityService;
     114: aastore
     115: dup
     116: iconst_3
     117: getstatic     #16                 // Field BASIC:Lorg/hl7/fhir/dstu3/model/codesystems/RestfulSecurityService;
     120: aastore
     121: dup
     122: iconst_4
     123: getstatic     #18                 // Field KERBEROS:Lorg/hl7/fhir/dstu3/model/codesystems/RestfulSecurityService;
     126: aastore
     127: dup
     128: iconst_5
     129: getstatic     #20                 // Field CERTIFICATES:Lorg/hl7/fhir/dstu3/model/codesystems/RestfulSecurityService;
     132: aastore
     133: dup
     134: bipush        6
     136: getstatic     #46                 // Field NULL:Lorg/hl7/fhir/dstu3/model/codesystems/RestfulSecurityService;
     139: aastore
     140: putstatic     #1                  // Field $VALUES:[Lorg/hl7/fhir/dstu3/model/codesystems/RestfulSecurityService;
     143: return
}
