Compiled from "SupplyrequestStatus.java"
public final class org.hl7.fhir.dstu3.model.codesystems.SupplyrequestStatus extends java.lang.Enum<org.hl7.fhir.dstu3.model.codesystems.SupplyrequestStatus> {
  public static final org.hl7.fhir.dstu3.model.codesystems.SupplyrequestStatus DRAFT;

  public static final org.hl7.fhir.dstu3.model.codesystems.SupplyrequestStatus ACTIVE;

  public static final org.hl7.fhir.dstu3.model.codesystems.SupplyrequestStatus SUSPENDED;

  public static final org.hl7.fhir.dstu3.model.codesystems.SupplyrequestStatus CANCELLED;

  public static final org.hl7.fhir.dstu3.model.codesystems.SupplyrequestStatus COMPLETED;

  public static final org.hl7.fhir.dstu3.model.codesystems.SupplyrequestStatus ENTEREDINERROR;

  public static final org.hl7.fhir.dstu3.model.codesystems.SupplyrequestStatus UNKNOWN;

  public static final org.hl7.fhir.dstu3.model.codesystems.SupplyrequestStatus NULL;

  private static final org.hl7.fhir.dstu3.model.codesystems.SupplyrequestStatus[] $VALUES;

  public static org.hl7.fhir.dstu3.model.codesystems.SupplyrequestStatus[] values();
    Code:
       0: getstatic     #1                  // Field $VALUES:[Lorg/hl7/fhir/dstu3/model/codesystems/SupplyrequestStatus;
       3: invokevirtual #2                  // Method "[Lorg/hl7/fhir/dstu3/model/codesystems/SupplyrequestStatus;".clone:()Ljava/lang/Object;
       6: checkcast     #3                  // class "[Lorg/hl7/fhir/dstu3/model/codesystems/SupplyrequestStatus;"
       9: areturn

  public static org.hl7.fhir.dstu3.model.codesystems.SupplyrequestStatus valueOf(java.lang.String);
    Code:
       0: ldc           #4                  // class org/hl7/fhir/dstu3/model/codesystems/SupplyrequestStatus
       2: aload_0
       3: invokestatic  #5                  // Method java/lang/Enum.valueOf:(Ljava/lang/Class;Ljava/lang/String;)Ljava/lang/Enum;
       6: checkcast     #4                  // class org/hl7/fhir/dstu3/model/codesystems/SupplyrequestStatus
       9: areturn

  private org.hl7.fhir.dstu3.model.codesystems.SupplyrequestStatus();
    Code:
       0: aload_0
       1: aload_1
       2: iload_2
       3: invokespecial #6                  // Method java/lang/Enum."<init>":(Ljava/lang/String;I)V
       6: return

  public static org.hl7.fhir.dstu3.model.codesystems.SupplyrequestStatus fromCode(java.lang.String) throws org.hl7.fhir.exceptions.FHIRException;
    Code:
       0: aload_0
       1: ifnull        13
       4: ldc           #7                  // String
       6: aload_0
       7: invokevirtual #8                  // Method java/lang/String.equals:(Ljava/lang/Object;)Z
      10: ifeq          15
      13: aconst_null
      14: areturn
      15: ldc           #9                  // String draft
      17: aload_0
      18: invokevirtual #8                  // Method java/lang/String.equals:(Ljava/lang/Object;)Z
      21: ifeq          28
      24: getstatic     #10                 // Field DRAFT:Lorg/hl7/fhir/dstu3/model/codesystems/SupplyrequestStatus;
      27: areturn
      28: ldc           #11                 // String active
      30: aload_0
      31: invokevirtual #8                  // Method java/lang/String.equals:(Ljava/lang/Object;)Z
      34: ifeq          41
      37: getstatic     #12                 // Field ACTIVE:Lorg/hl7/fhir/dstu3/model/codesystems/SupplyrequestStatus;
      40: areturn
      41: ldc           #13                 // String suspended
      43: aload_0
      44: invokevirtual #8                  // Method java/lang/String.equals:(Ljava/lang/Object;)Z
      47: ifeq          54
      50: getstatic     #14                 // Field SUSPENDED:Lorg/hl7/fhir/dstu3/model/codesystems/SupplyrequestStatus;
      53: areturn
      54: ldc           #15                 // String cancelled
      56: aload_0
      57: invokevirtual #8                  // Method java/lang/String.equals:(Ljava/lang/Object;)Z
      60: ifeq          67
      63: getstatic     #16                 // Field CANCELLED:Lorg/hl7/fhir/dstu3/model/codesystems/SupplyrequestStatus;
      66: areturn
      67: ldc           #17                 // String completed
      69: aload_0
      70: invokevirtual #8                  // Method java/lang/String.equals:(Ljava/lang/Object;)Z
      73: ifeq          80
      76: getstatic     #18                 // Field COMPLETED:Lorg/hl7/fhir/dstu3/model/codesystems/SupplyrequestStatus;
      79: areturn
      80: ldc           #19                 // String entered-in-error
      82: aload_0
      83: invokevirtual #8                  // Method java/lang/String.equals:(Ljava/lang/Object;)Z
      86: ifeq          93
      89: getstatic     #20                 // Field ENTEREDINERROR:Lorg/hl7/fhir/dstu3/model/codesystems/SupplyrequestStatus;
      92: areturn
      93: ldc           #21                 // String unknown
      95: aload_0
      96: invokevirtual #8                  // Method java/lang/String.equals:(Ljava/lang/Object;)Z
      99: ifeq          106
     102: getstatic     #22                 // Field UNKNOWN:Lorg/hl7/fhir/dstu3/model/codesystems/SupplyrequestStatus;
     105: areturn
     106: new           #23                 // class org/hl7/fhir/exceptions/FHIRException
     109: dup
     110: new           #24                 // class java/lang/StringBuilder
     113: dup
     114: invokespecial #25                 // Method java/lang/StringBuilder."<init>":()V
     117: ldc           #26                 // String Unknown SupplyrequestStatus code \'
     119: invokevirtual #27                 // Method java/lang/StringBuilder.append:(Ljava/lang/String;)Ljava/lang/StringBuilder;
     122: aload_0
     123: invokevirtual #27                 // Method java/lang/StringBuilder.append:(Ljava/lang/String;)Ljava/lang/StringBuilder;
     126: ldc           #28                 // String \'
     128: invokevirtual #27                 // Method java/lang/StringBuilder.append:(Ljava/lang/String;)Ljava/lang/StringBuilder;
     131: invokevirtual #29                 // Method java/lang/StringBuilder.toString:()Ljava/lang/String;
     134: invokespecial #30                 // Method org/hl7/fhir/exceptions/FHIRException."<init>":(Ljava/lang/String;)V
     137: athrow

  public java.lang.String toCode();
    Code:
       0: getstatic     #31                 // Field org/hl7/fhir/dstu3/model/codesystems/SupplyrequestStatus$1.$SwitchMap$org$hl7$fhir$dstu3$model$codesystems$SupplyrequestStatus:[I
       3: aload_0
       4: invokevirtual #32                 // Method ordinal:()I
       7: iaload
       8: tableswitch   { // 1 to 8
                     1: 56
                     2: 59
                     3: 62
                     4: 65
                     5: 68
                     6: 71
                     7: 74
                     8: 77
               default: 79
          }
      56: ldc           #9                  // String draft
      58: areturn
      59: ldc           #11                 // String active
      61: areturn
      62: ldc           #13                 // String suspended
      64: areturn
      65: ldc           #15                 // String cancelled
      67: areturn
      68: ldc           #17                 // String completed
      70: areturn
      71: ldc           #19                 // String entered-in-error
      73: areturn
      74: ldc           #21                 // String unknown
      76: areturn
      77: aconst_null
      78: areturn
      79: ldc           #33                 // String ?
      81: areturn

  public java.lang.String getSystem();
    Code:
       0: ldc           #34                 // String http://hl7.org/fhir/supplyrequest-status
       2: areturn

  public java.lang.String getDefinition();
    Code:
       0: getstatic     #31                 // Field org/hl7/fhir/dstu3/model/codesystems/SupplyrequestStatus$1.$SwitchMap$org$hl7$fhir$dstu3$model$codesystems$SupplyrequestStatus:[I
       3: aload_0
       4: invokevirtual #32                 // Method ordinal:()I
       7: iaload
       8: tableswitch   { // 1 to 8
                     1: 56
                     2: 59
                     3: 62
                     4: 65
                     5: 68
                     6: 71
                     7: 74
                     8: 77
               default: 79
          }
      56: ldc           #35                 // String The request has been created but is not yet complete or ready for action
      58: areturn
      59: ldc           #36                 // String The request is ready to be acted upon
      61: areturn
      62: ldc           #37                 // String The authorization/request to act has been temporarily withdrawn but is expected to resume in the future
      64: areturn
      65: ldc           #38                 // String The authorization/request to act has been terminated prior to the full completion of the intended actions.  No further activity should occur.
      67: areturn
      68: ldc           #39                 // String Activity against the request has been sufficiently completed to the satisfaction of the requester
      70: areturn
      71: ldc           #40                 // String This electronic record should never have existed, though it is possible that real-world decisions were based on it.  (If real-world activity has occurred, the status should be \"cancelled\" rather than \"entered-in-error\".)
      73: areturn
      74: ldc           #41                 // String The authoring system does not know which of the status values currently applies for this request.  Note: This concept is not to be used for \"other\" - one of the listed statuses is presumed to apply, it\'s just not known which one.
      76: areturn
      77: aconst_null
      78: areturn
      79: ldc           #33                 // String ?
      81: areturn

  public java.lang.String getDisplay();
    Code:
       0: getstatic     #31                 // Field org/hl7/fhir/dstu3/model/codesystems/SupplyrequestStatus$1.$SwitchMap$org$hl7$fhir$dstu3$model$codesystems$SupplyrequestStatus:[I
       3: aload_0
       4: invokevirtual #32                 // Method ordinal:()I
       7: iaload
       8: tableswitch   { // 1 to 8
                     1: 56
                     2: 59
                     3: 62
                     4: 65
                     5: 68
                     6: 71
                     7: 74
                     8: 77
               default: 79
          }
      56: ldc           #42                 // String Draft
      58: areturn
      59: ldc           #43                 // String Active
      61: areturn
      62: ldc           #44                 // String Suspended
      64: areturn
      65: ldc           #45                 // String Cancelled
      67: areturn
      68: ldc           #46                 // String Completed
      70: areturn
      71: ldc           #47                 // String Entered in Error
      73: areturn
      74: ldc           #48                 // String Unknown
      76: areturn
      77: aconst_null
      78: areturn
      79: ldc           #33                 // String ?
      81: areturn

  static {};
    Code:
       0: new           #4                  // class org/hl7/fhir/dstu3/model/codesystems/SupplyrequestStatus
       3: dup
       4: ldc           #49                 // String DRAFT
       6: iconst_0
       7: invokespecial #50                 // Method "<init>":(Ljava/lang/String;I)V
      10: putstatic     #10                 // Field DRAFT:Lorg/hl7/fhir/dstu3/model/codesystems/SupplyrequestStatus;
      13: new           #4                  // class org/hl7/fhir/dstu3/model/codesystems/SupplyrequestStatus
      16: dup
      17: ldc           #51                 // String ACTIVE
      19: iconst_1
      20: invokespecial #50                 // Method "<init>":(Ljava/lang/String;I)V
      23: putstatic     #12                 // Field ACTIVE:Lorg/hl7/fhir/dstu3/model/codesystems/SupplyrequestStatus;
      26: new           #4                  // class org/hl7/fhir/dstu3/model/codesystems/SupplyrequestStatus
      29: dup
      30: ldc           #52                 // String SUSPENDED
      32: iconst_2
      33: invokespecial #50                 // Method "<init>":(Ljava/lang/String;I)V
      36: putstatic     #14                 // Field SUSPENDED:Lorg/hl7/fhir/dstu3/model/codesystems/SupplyrequestStatus;
      39: new           #4                  // class org/hl7/fhir/dstu3/model/codesystems/SupplyrequestStatus
      42: dup
      43: ldc           #53                 // String CANCELLED
      45: iconst_3
      46: invokespecial #50                 // Method "<init>":(Ljava/lang/String;I)V
      49: putstatic     #16                 // Field CANCELLED:Lorg/hl7/fhir/dstu3/model/codesystems/SupplyrequestStatus;
      52: new           #4                  // class org/hl7/fhir/dstu3/model/codesystems/SupplyrequestStatus
      55: dup
      56: ldc           #54                 // String COMPLETED
      58: iconst_4
      59: invokespecial #50                 // Method "<init>":(Ljava/lang/String;I)V
      62: putstatic     #18                 // Field COMPLETED:Lorg/hl7/fhir/dstu3/model/codesystems/SupplyrequestStatus;
      65: new           #4                  // class org/hl7/fhir/dstu3/model/codesystems/SupplyrequestStatus
      68: dup
      69: ldc           #55                 // String ENTEREDINERROR
      71: iconst_5
      72: invokespecial #50                 // Method "<init>":(Ljava/lang/String;I)V
      75: putstatic     #20                 // Field ENTEREDINERROR:Lorg/hl7/fhir/dstu3/model/codesystems/SupplyrequestStatus;
      78: new           #4                  // class org/hl7/fhir/dstu3/model/codesystems/SupplyrequestStatus
      81: dup
      82: ldc           #56                 // String UNKNOWN
      84: bipush        6
      86: invokespecial #50                 // Method "<init>":(Ljava/lang/String;I)V
      89: putstatic     #22                 // Field UNKNOWN:Lorg/hl7/fhir/dstu3/model/codesystems/SupplyrequestStatus;
      92: new           #4                  // class org/hl7/fhir/dstu3/model/codesystems/SupplyrequestStatus
      95: dup
      96: ldc           #57                 // String NULL
      98: bipush        7
     100: invokespecial #50                 // Method "<init>":(Ljava/lang/String;I)V
     103: putstatic     #58                 // Field NULL:Lorg/hl7/fhir/dstu3/model/codesystems/SupplyrequestStatus;
     106: bipush        8
     108: anewarray     #4                  // class org/hl7/fhir/dstu3/model/codesystems/SupplyrequestStatus
     111: dup
     112: iconst_0
     113: getstatic     #10                 // Field DRAFT:Lorg/hl7/fhir/dstu3/model/codesystems/SupplyrequestStatus;
     116: aastore
     117: dup
     118: iconst_1
     119: getstatic     #12                 // Field ACTIVE:Lorg/hl7/fhir/dstu3/model/codesystems/SupplyrequestStatus;
     122: aastore
     123: dup
     124: iconst_2
     125: getstatic     #14                 // Field SUSPENDED:Lorg/hl7/fhir/dstu3/model/codesystems/SupplyrequestStatus;
     128: aastore
     129: dup
     130: iconst_3
     131: getstatic     #16                 // Field CANCELLED:Lorg/hl7/fhir/dstu3/model/codesystems/SupplyrequestStatus;
     134: aastore
     135: dup
     136: iconst_4
     137: getstatic     #18                 // Field COMPLETED:Lorg/hl7/fhir/dstu3/model/codesystems/SupplyrequestStatus;
     140: aastore
     141: dup
     142: iconst_5
     143: getstatic     #20                 // Field ENTEREDINERROR:Lorg/hl7/fhir/dstu3/model/codesystems/SupplyrequestStatus;
     146: aastore
     147: dup
     148: bipush        6
     150: getstatic     #22                 // Field UNKNOWN:Lorg/hl7/fhir/dstu3/model/codesystems/SupplyrequestStatus;
     153: aastore
     154: dup
     155: bipush        7
     157: getstatic     #58                 // Field NULL:Lorg/hl7/fhir/dstu3/model/codesystems/SupplyrequestStatus;
     160: aastore
     161: putstatic     #1                  // Field $VALUES:[Lorg/hl7/fhir/dstu3/model/codesystems/SupplyrequestStatus;
     164: return
}
