Compiled from "V3ActRelationshipCheckpoint.java"
public final class org.hl7.fhir.dstu3.model.codesystems.V3ActRelationshipCheckpoint extends java.lang.Enum<org.hl7.fhir.dstu3.model.codesystems.V3ActRelationshipCheckpoint> {
  public static final org.hl7.fhir.dstu3.model.codesystems.V3ActRelationshipCheckpoint B;

  public static final org.hl7.fhir.dstu3.model.codesystems.V3ActRelationshipCheckpoint E;

  public static final org.hl7.fhir.dstu3.model.codesystems.V3ActRelationshipCheckpoint S;

  public static final org.hl7.fhir.dstu3.model.codesystems.V3ActRelationshipCheckpoint T;

  public static final org.hl7.fhir.dstu3.model.codesystems.V3ActRelationshipCheckpoint X;

  public static final org.hl7.fhir.dstu3.model.codesystems.V3ActRelationshipCheckpoint NULL;

  private static final org.hl7.fhir.dstu3.model.codesystems.V3ActRelationshipCheckpoint[] $VALUES;

  public static org.hl7.fhir.dstu3.model.codesystems.V3ActRelationshipCheckpoint[] values();
    Code:
       0: getstatic     #1                  // Field $VALUES:[Lorg/hl7/fhir/dstu3/model/codesystems/V3ActRelationshipCheckpoint;
       3: invokevirtual #2                  // Method "[Lorg/hl7/fhir/dstu3/model/codesystems/V3ActRelationshipCheckpoint;".clone:()Ljava/lang/Object;
       6: checkcast     #3                  // class "[Lorg/hl7/fhir/dstu3/model/codesystems/V3ActRelationshipCheckpoint;"
       9: areturn

  public static org.hl7.fhir.dstu3.model.codesystems.V3ActRelationshipCheckpoint valueOf(java.lang.String);
    Code:
       0: ldc           #4                  // class org/hl7/fhir/dstu3/model/codesystems/V3ActRelationshipCheckpoint
       2: aload_0
       3: invokestatic  #5                  // Method java/lang/Enum.valueOf:(Ljava/lang/Class;Ljava/lang/String;)Ljava/lang/Enum;
       6: checkcast     #4                  // class org/hl7/fhir/dstu3/model/codesystems/V3ActRelationshipCheckpoint
       9: areturn

  private org.hl7.fhir.dstu3.model.codesystems.V3ActRelationshipCheckpoint();
    Code:
       0: aload_0
       1: aload_1
       2: iload_2
       3: invokespecial #6                  // Method java/lang/Enum."<init>":(Ljava/lang/String;I)V
       6: return

  public static org.hl7.fhir.dstu3.model.codesystems.V3ActRelationshipCheckpoint fromCode(java.lang.String) throws org.hl7.fhir.exceptions.FHIRException;
    Code:
       0: aload_0
       1: ifnull        13
       4: ldc           #7                  // String
       6: aload_0
       7: invokevirtual #8                  // Method java/lang/String.equals:(Ljava/lang/Object;)Z
      10: ifeq          15
      13: aconst_null
      14: areturn
      15: ldc           #9                  // String B
      17: aload_0
      18: invokevirtual #8                  // Method java/lang/String.equals:(Ljava/lang/Object;)Z
      21: ifeq          28
      24: getstatic     #10                 // Field B:Lorg/hl7/fhir/dstu3/model/codesystems/V3ActRelationshipCheckpoint;
      27: areturn
      28: ldc           #11                 // String E
      30: aload_0
      31: invokevirtual #8                  // Method java/lang/String.equals:(Ljava/lang/Object;)Z
      34: ifeq          41
      37: getstatic     #12                 // Field E:Lorg/hl7/fhir/dstu3/model/codesystems/V3ActRelationshipCheckpoint;
      40: areturn
      41: ldc           #13                 // String S
      43: aload_0
      44: invokevirtual #8                  // Method java/lang/String.equals:(Ljava/lang/Object;)Z
      47: ifeq          54
      50: getstatic     #14                 // Field S:Lorg/hl7/fhir/dstu3/model/codesystems/V3ActRelationshipCheckpoint;
      53: areturn
      54: ldc           #15                 // String T
      56: aload_0
      57: invokevirtual #8                  // Method java/lang/String.equals:(Ljava/lang/Object;)Z
      60: ifeq          67
      63: getstatic     #16                 // Field T:Lorg/hl7/fhir/dstu3/model/codesystems/V3ActRelationshipCheckpoint;
      66: areturn
      67: ldc           #17                 // String X
      69: aload_0
      70: invokevirtual #8                  // Method java/lang/String.equals:(Ljava/lang/Object;)Z
      73: ifeq          80
      76: getstatic     #18                 // Field X:Lorg/hl7/fhir/dstu3/model/codesystems/V3ActRelationshipCheckpoint;
      79: areturn
      80: new           #19                 // class org/hl7/fhir/exceptions/FHIRException
      83: dup
      84: new           #20                 // class java/lang/StringBuilder
      87: dup
      88: invokespecial #21                 // Method java/lang/StringBuilder."<init>":()V
      91: ldc           #22                 // String Unknown V3ActRelationshipCheckpoint code \'
      93: invokevirtual #23                 // Method java/lang/StringBuilder.append:(Ljava/lang/String;)Ljava/lang/StringBuilder;
      96: aload_0
      97: invokevirtual #23                 // Method java/lang/StringBuilder.append:(Ljava/lang/String;)Ljava/lang/StringBuilder;
     100: ldc           #24                 // String \'
     102: invokevirtual #23                 // Method java/lang/StringBuilder.append:(Ljava/lang/String;)Ljava/lang/StringBuilder;
     105: invokevirtual #25                 // Method java/lang/StringBuilder.toString:()Ljava/lang/String;
     108: invokespecial #26                 // Method org/hl7/fhir/exceptions/FHIRException."<init>":(Ljava/lang/String;)V
     111: athrow

  public java.lang.String toCode();
    Code:
       0: getstatic     #27                 // Field org/hl7/fhir/dstu3/model/codesystems/V3ActRelationshipCheckpoint$1.$SwitchMap$org$hl7$fhir$dstu3$model$codesystems$V3ActRelationshipCheckpoint:[I
       3: aload_0
       4: invokevirtual #28                 // Method ordinal:()I
       7: iaload
       8: tableswitch   { // 1 to 6
                     1: 48
                     2: 51
                     3: 54
                     4: 57
                     5: 60
                     6: 63
               default: 65
          }
      48: ldc           #9                  // String B
      50: areturn
      51: ldc           #11                 // String E
      53: areturn
      54: ldc           #13                 // String S
      56: areturn
      57: ldc           #15                 // String T
      59: areturn
      60: ldc           #17                 // String X
      62: areturn
      63: aconst_null
      64: areturn
      65: ldc           #29                 // String ?
      67: areturn

  public java.lang.String getSystem();
    Code:
       0: ldc           #30                 // String http://hl7.org/fhir/v3/ActRelationshipCheckpoint
       2: areturn

  public java.lang.String getDefinition();
    Code:
       0: getstatic     #27                 // Field org/hl7/fhir/dstu3/model/codesystems/V3ActRelationshipCheckpoint$1.$SwitchMap$org$hl7$fhir$dstu3$model$codesystems$V3ActRelationshipCheckpoint:[I
       3: aload_0
       4: invokevirtual #28                 // Method ordinal:()I
       7: iaload
       8: tableswitch   { // 1 to 6
                     1: 48
                     2: 51
                     3: 54
                     4: 57
                     5: 60
                     6: 63
               default: 65
          }
      48: ldc           #31                 // String Condition is tested every time before execution of the service (WHILE condition DO service).
      50: areturn
      51: ldc           #32                 // String Condition is tested at the end of a repeated service execution.  The service is repeated only if the condition is true (DO service WHILE condition).
      53: areturn
      54: ldc           #33                 // String Condition is tested once before the service is executed (IF condition THEN service).
      56: areturn
      57: ldc           #34                 // String Condition must be true throughout the execution and the service is interrupted (asynchronously) as soon as the condition turns false (asynchronous WHILE loop).  The service must be interruptible.
      59: areturn
      60: ldc           #35                 // String Condition is a loop checkpoint, i.e. it is a step of an activity plan and, if negative causes the containing loop to exit.
      62: areturn
      63: aconst_null
      64: areturn
      65: ldc           #29                 // String ?
      67: areturn

  public java.lang.String getDisplay();
    Code:
       0: getstatic     #27                 // Field org/hl7/fhir/dstu3/model/codesystems/V3ActRelationshipCheckpoint$1.$SwitchMap$org$hl7$fhir$dstu3$model$codesystems$V3ActRelationshipCheckpoint:[I
       3: aload_0
       4: invokevirtual #28                 // Method ordinal:()I
       7: iaload
       8: tableswitch   { // 1 to 6
                     1: 48
                     2: 51
                     3: 54
                     4: 57
                     5: 60
                     6: 63
               default: 65
          }
      48: ldc           #36                 // String beginning
      50: areturn
      51: ldc           #37                 // String end
      53: areturn
      54: ldc           #38                 // String entry
      56: areturn
      57: ldc           #39                 // String through
      59: areturn
      60: ldc           #40                 // String exit
      62: areturn
      63: aconst_null
      64: areturn
      65: ldc           #29                 // String ?
      67: areturn

  static {};
    Code:
       0: new           #4                  // class org/hl7/fhir/dstu3/model/codesystems/V3ActRelationshipCheckpoint
       3: dup
       4: ldc           #9                  // String B
       6: iconst_0
       7: invokespecial #41                 // Method "<init>":(Ljava/lang/String;I)V
      10: putstatic     #10                 // Field B:Lorg/hl7/fhir/dstu3/model/codesystems/V3ActRelationshipCheckpoint;
      13: new           #4                  // class org/hl7/fhir/dstu3/model/codesystems/V3ActRelationshipCheckpoint
      16: dup
      17: ldc           #11                 // String E
      19: iconst_1
      20: invokespecial #41                 // Method "<init>":(Ljava/lang/String;I)V
      23: putstatic     #12                 // Field E:Lorg/hl7/fhir/dstu3/model/codesystems/V3ActRelationshipCheckpoint;
      26: new           #4                  // class org/hl7/fhir/dstu3/model/codesystems/V3ActRelationshipCheckpoint
      29: dup
      30: ldc           #13                 // String S
      32: iconst_2
      33: invokespecial #41                 // Method "<init>":(Ljava/lang/String;I)V
      36: putstatic     #14                 // Field S:Lorg/hl7/fhir/dstu3/model/codesystems/V3ActRelationshipCheckpoint;
      39: new           #4                  // class org/hl7/fhir/dstu3/model/codesystems/V3ActRelationshipCheckpoint
      42: dup
      43: ldc           #15                 // String T
      45: iconst_3
      46: invokespecial #41                 // Method "<init>":(Ljava/lang/String;I)V
      49: putstatic     #16                 // Field T:Lorg/hl7/fhir/dstu3/model/codesystems/V3ActRelationshipCheckpoint;
      52: new           #4                  // class org/hl7/fhir/dstu3/model/codesystems/V3ActRelationshipCheckpoint
      55: dup
      56: ldc           #17                 // String X
      58: iconst_4
      59: invokespecial #41                 // Method "<init>":(Ljava/lang/String;I)V
      62: putstatic     #18                 // Field X:Lorg/hl7/fhir/dstu3/model/codesystems/V3ActRelationshipCheckpoint;
      65: new           #4                  // class org/hl7/fhir/dstu3/model/codesystems/V3ActRelationshipCheckpoint
      68: dup
      69: ldc           #42                 // String NULL
      71: iconst_5
      72: invokespecial #41                 // Method "<init>":(Ljava/lang/String;I)V
      75: putstatic     #43                 // Field NULL:Lorg/hl7/fhir/dstu3/model/codesystems/V3ActRelationshipCheckpoint;
      78: bipush        6
      80: anewarray     #4                  // class org/hl7/fhir/dstu3/model/codesystems/V3ActRelationshipCheckpoint
      83: dup
      84: iconst_0
      85: getstatic     #10                 // Field B:Lorg/hl7/fhir/dstu3/model/codesystems/V3ActRelationshipCheckpoint;
      88: aastore
      89: dup
      90: iconst_1
      91: getstatic     #12                 // Field E:Lorg/hl7/fhir/dstu3/model/codesystems/V3ActRelationshipCheckpoint;
      94: aastore
      95: dup
      96: iconst_2
      97: getstatic     #14                 // Field S:Lorg/hl7/fhir/dstu3/model/codesystems/V3ActRelationshipCheckpoint;
     100: aastore
     101: dup
     102: iconst_3
     103: getstatic     #16                 // Field T:Lorg/hl7/fhir/dstu3/model/codesystems/V3ActRelationshipCheckpoint;
     106: aastore
     107: dup
     108: iconst_4
     109: getstatic     #18                 // Field X:Lorg/hl7/fhir/dstu3/model/codesystems/V3ActRelationshipCheckpoint;
     112: aastore
     113: dup
     114: iconst_5
     115: getstatic     #43                 // Field NULL:Lorg/hl7/fhir/dstu3/model/codesystems/V3ActRelationshipCheckpoint;
     118: aastore
     119: putstatic     #1                  // Field $VALUES:[Lorg/hl7/fhir/dstu3/model/codesystems/V3ActRelationshipCheckpoint;
     122: return
}
