Compiled from "V3Confidentiality.java"
public final class org.hl7.fhir.dstu3.model.codesystems.V3Confidentiality extends java.lang.Enum<org.hl7.fhir.dstu3.model.codesystems.V3Confidentiality> {
  public static final org.hl7.fhir.dstu3.model.codesystems.V3Confidentiality _CONFIDENTIALITY;

  public static final org.hl7.fhir.dstu3.model.codesystems.V3Confidentiality L;

  public static final org.hl7.fhir.dstu3.model.codesystems.V3Confidentiality M;

  public static final org.hl7.fhir.dstu3.model.codesystems.V3Confidentiality N;

  public static final org.hl7.fhir.dstu3.model.codesystems.V3Confidentiality R;

  public static final org.hl7.fhir.dstu3.model.codesystems.V3Confidentiality U;

  public static final org.hl7.fhir.dstu3.model.codesystems.V3Confidentiality V;

  public static final org.hl7.fhir.dstu3.model.codesystems.V3Confidentiality _CONFIDENTIALITYBYACCESSKIND;

  public static final org.hl7.fhir.dstu3.model.codesystems.V3Confidentiality B;

  public static final org.hl7.fhir.dstu3.model.codesystems.V3Confidentiality D;

  public static final org.hl7.fhir.dstu3.model.codesystems.V3Confidentiality I;

  public static final org.hl7.fhir.dstu3.model.codesystems.V3Confidentiality _CONFIDENTIALITYBYINFOTYPE;

  public static final org.hl7.fhir.dstu3.model.codesystems.V3Confidentiality ETH;

  public static final org.hl7.fhir.dstu3.model.codesystems.V3Confidentiality HIV;

  public static final org.hl7.fhir.dstu3.model.codesystems.V3Confidentiality PSY;

  public static final org.hl7.fhir.dstu3.model.codesystems.V3Confidentiality SDV;

  public static final org.hl7.fhir.dstu3.model.codesystems.V3Confidentiality _CONFIDENTIALITYMODIFIERS;

  public static final org.hl7.fhir.dstu3.model.codesystems.V3Confidentiality C;

  public static final org.hl7.fhir.dstu3.model.codesystems.V3Confidentiality S;

  public static final org.hl7.fhir.dstu3.model.codesystems.V3Confidentiality T;

  public static final org.hl7.fhir.dstu3.model.codesystems.V3Confidentiality NULL;

  private static final org.hl7.fhir.dstu3.model.codesystems.V3Confidentiality[] $VALUES;

  public static org.hl7.fhir.dstu3.model.codesystems.V3Confidentiality[] values();
    Code:
       0: getstatic     #1                  // Field $VALUES:[Lorg/hl7/fhir/dstu3/model/codesystems/V3Confidentiality;
       3: invokevirtual #2                  // Method "[Lorg/hl7/fhir/dstu3/model/codesystems/V3Confidentiality;".clone:()Ljava/lang/Object;
       6: checkcast     #3                  // class "[Lorg/hl7/fhir/dstu3/model/codesystems/V3Confidentiality;"
       9: areturn

  public static org.hl7.fhir.dstu3.model.codesystems.V3Confidentiality valueOf(java.lang.String);
    Code:
       0: ldc           #4                  // class org/hl7/fhir/dstu3/model/codesystems/V3Confidentiality
       2: aload_0
       3: invokestatic  #5                  // Method java/lang/Enum.valueOf:(Ljava/lang/Class;Ljava/lang/String;)Ljava/lang/Enum;
       6: checkcast     #4                  // class org/hl7/fhir/dstu3/model/codesystems/V3Confidentiality
       9: areturn

  private org.hl7.fhir.dstu3.model.codesystems.V3Confidentiality();
    Code:
       0: aload_0
       1: aload_1
       2: iload_2
       3: invokespecial #6                  // Method java/lang/Enum."<init>":(Ljava/lang/String;I)V
       6: return

  public static org.hl7.fhir.dstu3.model.codesystems.V3Confidentiality fromCode(java.lang.String) throws org.hl7.fhir.exceptions.FHIRException;
    Code:
       0: aload_0
       1: ifnull        13
       4: ldc           #7                  // String
       6: aload_0
       7: invokevirtual #8                  // Method java/lang/String.equals:(Ljava/lang/Object;)Z
      10: ifeq          15
      13: aconst_null
      14: areturn
      15: ldc           #9                  // String _Confidentiality
      17: aload_0
      18: invokevirtual #8                  // Method java/lang/String.equals:(Ljava/lang/Object;)Z
      21: ifeq          28
      24: getstatic     #10                 // Field _CONFIDENTIALITY:Lorg/hl7/fhir/dstu3/model/codesystems/V3Confidentiality;
      27: areturn
      28: ldc           #11                 // String L
      30: aload_0
      31: invokevirtual #8                  // Method java/lang/String.equals:(Ljava/lang/Object;)Z
      34: ifeq          41
      37: getstatic     #12                 // Field L:Lorg/hl7/fhir/dstu3/model/codesystems/V3Confidentiality;
      40: areturn
      41: ldc           #13                 // String M
      43: aload_0
      44: invokevirtual #8                  // Method java/lang/String.equals:(Ljava/lang/Object;)Z
      47: ifeq          54
      50: getstatic     #14                 // Field M:Lorg/hl7/fhir/dstu3/model/codesystems/V3Confidentiality;
      53: areturn
      54: ldc           #15                 // String N
      56: aload_0
      57: invokevirtual #8                  // Method java/lang/String.equals:(Ljava/lang/Object;)Z
      60: ifeq          67
      63: getstatic     #16                 // Field N:Lorg/hl7/fhir/dstu3/model/codesystems/V3Confidentiality;
      66: areturn
      67: ldc           #17                 // String R
      69: aload_0
      70: invokevirtual #8                  // Method java/lang/String.equals:(Ljava/lang/Object;)Z
      73: ifeq          80
      76: getstatic     #18                 // Field R:Lorg/hl7/fhir/dstu3/model/codesystems/V3Confidentiality;
      79: areturn
      80: ldc           #19                 // String U
      82: aload_0
      83: invokevirtual #8                  // Method java/lang/String.equals:(Ljava/lang/Object;)Z
      86: ifeq          93
      89: getstatic     #20                 // Field U:Lorg/hl7/fhir/dstu3/model/codesystems/V3Confidentiality;
      92: areturn
      93: ldc           #21                 // String V
      95: aload_0
      96: invokevirtual #8                  // Method java/lang/String.equals:(Ljava/lang/Object;)Z
      99: ifeq          106
     102: getstatic     #22                 // Field V:Lorg/hl7/fhir/dstu3/model/codesystems/V3Confidentiality;
     105: areturn
     106: ldc           #23                 // String _ConfidentialityByAccessKind
     108: aload_0
     109: invokevirtual #8                  // Method java/lang/String.equals:(Ljava/lang/Object;)Z
     112: ifeq          119
     115: getstatic     #24                 // Field _CONFIDENTIALITYBYACCESSKIND:Lorg/hl7/fhir/dstu3/model/codesystems/V3Confidentiality;
     118: areturn
     119: ldc           #25                 // String B
     121: aload_0
     122: invokevirtual #8                  // Method java/lang/String.equals:(Ljava/lang/Object;)Z
     125: ifeq          132
     128: getstatic     #26                 // Field B:Lorg/hl7/fhir/dstu3/model/codesystems/V3Confidentiality;
     131: areturn
     132: ldc           #27                 // String D
     134: aload_0
     135: invokevirtual #8                  // Method java/lang/String.equals:(Ljava/lang/Object;)Z
     138: ifeq          145
     141: getstatic     #28                 // Field D:Lorg/hl7/fhir/dstu3/model/codesystems/V3Confidentiality;
     144: areturn
     145: ldc           #29                 // String I
     147: aload_0
     148: invokevirtual #8                  // Method java/lang/String.equals:(Ljava/lang/Object;)Z
     151: ifeq          158
     154: getstatic     #30                 // Field I:Lorg/hl7/fhir/dstu3/model/codesystems/V3Confidentiality;
     157: areturn
     158: ldc           #31                 // String _ConfidentialityByInfoType
     160: aload_0
     161: invokevirtual #8                  // Method java/lang/String.equals:(Ljava/lang/Object;)Z
     164: ifeq          171
     167: getstatic     #32                 // Field _CONFIDENTIALITYBYINFOTYPE:Lorg/hl7/fhir/dstu3/model/codesystems/V3Confidentiality;
     170: areturn
     171: ldc           #33                 // String ETH
     173: aload_0
     174: invokevirtual #8                  // Method java/lang/String.equals:(Ljava/lang/Object;)Z
     177: ifeq          184
     180: getstatic     #34                 // Field ETH:Lorg/hl7/fhir/dstu3/model/codesystems/V3Confidentiality;
     183: areturn
     184: ldc           #35                 // String HIV
     186: aload_0
     187: invokevirtual #8                  // Method java/lang/String.equals:(Ljava/lang/Object;)Z
     190: ifeq          197
     193: getstatic     #36                 // Field HIV:Lorg/hl7/fhir/dstu3/model/codesystems/V3Confidentiality;
     196: areturn
     197: ldc           #37                 // String PSY
     199: aload_0
     200: invokevirtual #8                  // Method java/lang/String.equals:(Ljava/lang/Object;)Z
     203: ifeq          210
     206: getstatic     #38                 // Field PSY:Lorg/hl7/fhir/dstu3/model/codesystems/V3Confidentiality;
     209: areturn
     210: ldc           #39                 // String SDV
     212: aload_0
     213: invokevirtual #8                  // Method java/lang/String.equals:(Ljava/lang/Object;)Z
     216: ifeq          223
     219: getstatic     #40                 // Field SDV:Lorg/hl7/fhir/dstu3/model/codesystems/V3Confidentiality;
     222: areturn
     223: ldc           #41                 // String _ConfidentialityModifiers
     225: aload_0
     226: invokevirtual #8                  // Method java/lang/String.equals:(Ljava/lang/Object;)Z
     229: ifeq          236
     232: getstatic     #42                 // Field _CONFIDENTIALITYMODIFIERS:Lorg/hl7/fhir/dstu3/model/codesystems/V3Confidentiality;
     235: areturn
     236: ldc           #43                 // String C
     238: aload_0
     239: invokevirtual #8                  // Method java/lang/String.equals:(Ljava/lang/Object;)Z
     242: ifeq          249
     245: getstatic     #44                 // Field C:Lorg/hl7/fhir/dstu3/model/codesystems/V3Confidentiality;
     248: areturn
     249: ldc           #45                 // String S
     251: aload_0
     252: invokevirtual #8                  // Method java/lang/String.equals:(Ljava/lang/Object;)Z
     255: ifeq          262
     258: getstatic     #46                 // Field S:Lorg/hl7/fhir/dstu3/model/codesystems/V3Confidentiality;
     261: areturn
     262: ldc           #47                 // String T
     264: aload_0
     265: invokevirtual #8                  // Method java/lang/String.equals:(Ljava/lang/Object;)Z
     268: ifeq          275
     271: getstatic     #48                 // Field T:Lorg/hl7/fhir/dstu3/model/codesystems/V3Confidentiality;
     274: areturn
     275: new           #49                 // class org/hl7/fhir/exceptions/FHIRException
     278: dup
     279: new           #50                 // class java/lang/StringBuilder
     282: dup
     283: invokespecial #51                 // Method java/lang/StringBuilder."<init>":()V
     286: ldc           #52                 // String Unknown V3Confidentiality code \'
     288: invokevirtual #53                 // Method java/lang/StringBuilder.append:(Ljava/lang/String;)Ljava/lang/StringBuilder;
     291: aload_0
     292: invokevirtual #53                 // Method java/lang/StringBuilder.append:(Ljava/lang/String;)Ljava/lang/StringBuilder;
     295: ldc           #54                 // String \'
     297: invokevirtual #53                 // Method java/lang/StringBuilder.append:(Ljava/lang/String;)Ljava/lang/StringBuilder;
     300: invokevirtual #55                 // Method java/lang/StringBuilder.toString:()Ljava/lang/String;
     303: invokespecial #56                 // Method org/hl7/fhir/exceptions/FHIRException."<init>":(Ljava/lang/String;)V
     306: athrow

  public java.lang.String toCode();
    Code:
       0: getstatic     #57                 // Field org/hl7/fhir/dstu3/model/codesystems/V3Confidentiality$1.$SwitchMap$org$hl7$fhir$dstu3$model$codesystems$V3Confidentiality:[I
       3: aload_0
       4: invokevirtual #58                 // Method ordinal:()I
       7: iaload
       8: tableswitch   { // 1 to 21
                     1: 108
                     2: 111
                     3: 114
                     4: 117
                     5: 120
                     6: 123
                     7: 126
                     8: 129
                     9: 132
                    10: 135
                    11: 138
                    12: 141
                    13: 144
                    14: 147
                    15: 150
                    16: 153
                    17: 156
                    18: 159
                    19: 162
                    20: 165
                    21: 168
               default: 170
          }
     108: ldc           #9                  // String _Confidentiality
     110: areturn
     111: ldc           #11                 // String L
     113: areturn
     114: ldc           #13                 // String M
     116: areturn
     117: ldc           #15                 // String N
     119: areturn
     120: ldc           #17                 // String R
     122: areturn
     123: ldc           #19                 // String U
     125: areturn
     126: ldc           #21                 // String V
     128: areturn
     129: ldc           #23                 // String _ConfidentialityByAccessKind
     131: areturn
     132: ldc           #25                 // String B
     134: areturn
     135: ldc           #27                 // String D
     137: areturn
     138: ldc           #29                 // String I
     140: areturn
     141: ldc           #31                 // String _ConfidentialityByInfoType
     143: areturn
     144: ldc           #33                 // String ETH
     146: areturn
     147: ldc           #35                 // String HIV
     149: areturn
     150: ldc           #37                 // String PSY
     152: areturn
     153: ldc           #39                 // String SDV
     155: areturn
     156: ldc           #41                 // String _ConfidentialityModifiers
     158: areturn
     159: ldc           #43                 // String C
     161: areturn
     162: ldc           #45                 // String S
     164: areturn
     165: ldc           #47                 // String T
     167: areturn
     168: aconst_null
     169: areturn
     170: ldc           #59                 // String ?
     172: areturn

  public java.lang.String getSystem();
    Code:
       0: ldc           #60                 // String http://hl7.org/fhir/v3/Confidentiality
       2: areturn

  public java.lang.String getDefinition();
    Code:
       0: getstatic     #57                 // Field org/hl7/fhir/dstu3/model/codesystems/V3Confidentiality$1.$SwitchMap$org$hl7$fhir$dstu3$model$codesystems$V3Confidentiality:[I
       3: aload_0
       4: invokevirtual #58                 // Method ordinal:()I
       7: iaload
       8: tableswitch   { // 1 to 21
                     1: 108
                     2: 111
                     3: 114
                     4: 117
                     5: 120
                     6: 123
                     7: 126
                     8: 129
                     9: 132
                    10: 135
                    11: 138
                    12: 141
                    13: 144
                    14: 147
                    15: 150
                    16: 153
                    17: 156
                    18: 159
                    19: 162
                    20: 165
                    21: 168
               default: 170
          }
     108: ldc           #61                 // String A specializable code and its leaf codes used in Confidentiality value sets to value the Act.Confidentiality and Role.Confidentiality attribute in accordance with the definition for concept domain \"Confidentiality\".
     110: areturn
     111: ldc           #62                 // String Definition: Privacy metadata indicating that the information has been de-identified, and there are mitigating circumstances that prevent re-identification, which minimize risk of harm from unauthorized disclosure.  The information requires protection to maintain low sensitivity.\r\n\n                        \n                           Examples: Includes anonymized, pseudonymized, or non-personally identifiable information such as HIPAA limited data sets.\r\n\n                        \n                           Map: No clear map to ISO 13606-4 Sensitivity Level (1) Care Management:   RECORD_COMPONENTs that might need to be accessed by a wide range of administrative staff to manage the subject of care\'s access to health services.\r\n\n                        \n                           Usage Note: This metadata indicates the receiver may have an obligation to comply with a data use agreement.
     113: areturn
     114: ldc           #63                 // String Definition: Privacy metadata indicating moderately sensitive information, which presents moderate risk of harm if disclosed without authorization.\r\n\n                        \n                           Examples: Includes allergies of non-sensitive nature used inform food service; health information a patient authorizes to be used for marketing, released to a bank for a health credit card or savings account; or information in personal health record systems that are not governed under health privacy laws.\r\n\n                        \n                           Map: Partial Map to ISO 13606-4 Sensitivity Level (2) Clinical Management:  Less sensitive RECORD_COMPONENTs that might need to be accessed by a wider range of personnel not all of whom are actively caring for the patient (e.g. radiology staff).\r\n\n                        \n                           Usage Note: This metadata indicates that the receiver may be obligated to comply with the receiver\'s terms of use or privacy policies.
     116: areturn
     117: ldc           #64                 // String Definition: Privacy metadata indicating that the information is typical, non-stigmatizing health information, which presents typical risk of harm if disclosed without authorization.\r\n\n                        \n                           Examples: In the US, this includes what HIPAA identifies as the minimum necessary protected health information (PHI) given a covered purpose of use (treatment, payment, or operations).  Includes typical, non-stigmatizing health information disclosed in an application for health, workers compensation, disability, or life insurance.\r\n\n                        \n                           Map: Partial Map to ISO 13606-4 Sensitivity Level (3) Clinical Care:   Default for normal clinical care access (i.e. most clinical staff directly caring for the patient should be able to access nearly all of the EHR).   Maps to normal confidentiality for treatment information but not to ancillary care, payment and operations.\r\n\n                        \n                           Usage Note: This metadata indicates that the receiver may be obligated to comply with applicable jurisdictional privacy law or disclosure authorization.
     119: areturn
     120: ldc           #65                 // String Privacy metadata indicating highly sensitive, potentially stigmatizing information, which presents a high risk to the information subject if disclosed without authorization. May be pre-empted by jurisdictional law, e.g., for public health reporting or emergency treatment.\r\n\n                        \n                           Examples: Includes information that is additionally protected such as sensitive conditions mental health, HIV, substance abuse, domestic violence, child abuse, genetic disease, and reproductive health; or sensitive demographic information such as a patient\'s standing as an employee or a celebrity. May be used to indicate proprietary or classified information that is not related to an individual, e.g., secret ingredients in a therapeutic substance; or the name of a manufacturer.\r\n\n                        \n                           Map: Partial Map to ISO 13606-4 Sensitivity Level (3) Clinical Care: Default for normal clinical care access (i.e. most clinical staff directly caring for the patient should be able to access nearly all of the EHR). Maps to normal confidentiality for treatment information but not to ancillary care, payment and operations..\r\n\n                        \n                           Usage Note: This metadata indicates that the receiver may be obligated to comply with applicable, prevailing (default) jurisdictional privacy law or disclosure authorization..
     122: areturn
     123: ldc           #66                 // String Definition: Privacy metadata indicating that the information is not classified as sensitive.\r\n\n                        \n                           Examples: Includes publicly available information, e.g., business name, phone, email or physical address.\r\n\n                        \n                           Usage Note: This metadata indicates that the receiver has no obligation to consider additional policies when making access control decisions.   Note that in some jurisdictions, personally identifiable information must be protected as confidential, so it would not be appropriate to assign a confidentiality code of \"unrestricted\"  to that information even if it is publicly available.
     125: areturn
     126: ldc           #67                 // String . Privacy metadata indicating that the information is extremely sensitive and likely stigmatizing health information that presents a very high risk if disclosed without authorization.  This information must be kept in the highest confidence.  \r\n\n                        \n                           Examples:  Includes information about a victim of abuse, patient requested information sensitivity, and taboo subjects relating to health status that must be discussed with the patient by an attending provider before sharing with the patient.  May also include information held under â€œlegal lockâ€? or attorney-client privilege\r\n\n                        \n                           Map:  This metadata indicates that the receiver may not disclose this information except as directed by the information custodian, who may be the information subject.\r\n\n                        \n                           Usage Note:  This metadata indicates that the receiver may not disclose this information except as directed by the information custodian, who may be the information subject.
     128: areturn
     129: ldc           #68                 // String Description: By accessing subject / role and relationship based  rights  (These concepts are mutually exclusive, one and only one is required for a valid confidentiality coding.)\r\n\n                        \n                           Deprecation Comment:Deprecated due to updated confidentiality codes under ActCode
     131: areturn
     132: ldc           #69                 // String Description: Since the service class can represent knowledge structures that may be considered a trade or business secret, there is sometimes (though rarely) the need to flag those items as of business level confidentiality.  However, no patient related information may ever be of this confidentiality level.\r\n\n                        \n                           Deprecation Comment: Replced by ActCode.B
     134: areturn
     135: ldc           #70                 // String Description: Only clinicians may see this item, billing and administration persons can not access this item without special permission.\r\n\n                        \n                           Deprecation Comment:Deprecated due to updated confidentiality codes under ActCode
     137: areturn
     138: ldc           #71                 // String Description: Access only to individual persons who are mentioned explicitly as actors of this service and whose actor type warrants that access (cf. to actor type code).\r\n\n                        \n                           Deprecation Comment:Deprecated due to updated confidentiality codes under ActCode
     140: areturn
     141: ldc           #72                 // String Description: By information type, only for service catalog entries (multiples allowed). Not to be used with actual patient data!\r\n\n                        \n                           Deprecation Comment:Deprecated due to updated confidentiality codes under ActCode
     143: areturn
     144: ldc           #73                 // String Description: Alcohol/drug-abuse related item\r\n\n                        \n                           Deprecation Comment:Replced by ActCode.ETH
     146: areturn
     147: ldc           #74                 // String Description: HIV and AIDS related item\r\n\n                        \n                           Deprecation Comment:Replced by ActCode.HIV
     149: areturn
     150: ldc           #75                 // String Description: Psychiatry related item\r\n\n                        \n                           Deprecation Comment:Replced by ActCode.PSY
     152: areturn
     153: ldc           #76                 // String Description: Sexual assault / domestic violence related item\r\n\n                        \n                           Deprecation Comment:Replced by ActCode.SDV
     155: areturn
     156: ldc           #77                 // String Description: Modifiers of role based access rights  (multiple allowed)\r\n\n                        \n                           Deprecation Comment:Deprecated due to updated confidentiality codes under ActCode
     158: areturn
     159: ldc           #78                 // String Description: Celebrities are people of public interest (VIP) including employees, whose information require special protection.\r\n\n                        \n                           Deprecation Comment:Replced by ActCode.CEL
     161: areturn
     162: ldc           #79                 // String Description: \n                        \r\nInformation for which the patient seeks heightened confidentiality. Sensitive information is not to be shared with family members.  Information reported by the patient about family members is sensitive by default. Flag can be set or cleared on patient\'s request.\n                           Deprecation Comment:Deprecated due to updated confidentiality codes under ActCode
     164: areturn
     165: ldc           #80                 // String Description: Information not to be disclosed or discussed with patient except through physician assigned to patient in this case.  This is usually a temporary constraint only, example use is a new fatal diagnosis or finding, such as malignancy or HIV.\r\n\n                        \n                           Deprecation Note:Replced by ActCode.TBOO
     167: areturn
     168: aconst_null
     169: areturn
     170: ldc           #59                 // String ?
     172: areturn

  public java.lang.String getDisplay();
    Code:
       0: getstatic     #57                 // Field org/hl7/fhir/dstu3/model/codesystems/V3Confidentiality$1.$SwitchMap$org$hl7$fhir$dstu3$model$codesystems$V3Confidentiality:[I
       3: aload_0
       4: invokevirtual #58                 // Method ordinal:()I
       7: iaload
       8: tableswitch   { // 1 to 21
                     1: 108
                     2: 111
                     3: 114
                     4: 117
                     5: 120
                     6: 123
                     7: 126
                     8: 129
                     9: 132
                    10: 135
                    11: 138
                    12: 141
                    13: 144
                    14: 147
                    15: 150
                    16: 153
                    17: 156
                    18: 159
                    19: 162
                    20: 165
                    21: 168
               default: 170
          }
     108: ldc           #81                 // String Confidentiality
     110: areturn
     111: ldc           #82                 // String low
     113: areturn
     114: ldc           #83                 // String moderate
     116: areturn
     117: ldc           #84                 // String normal
     119: areturn
     120: ldc           #85                 // String restricted
     122: areturn
     123: ldc           #86                 // String unrestricted
     125: areturn
     126: ldc           #87                 // String very restricted
     128: areturn
     129: ldc           #88                 // String ConfidentialityByAccessKind
     131: areturn
     132: ldc           #89                 // String business
     134: areturn
     135: ldc           #90                 // String clinician
     137: areturn
     138: ldc           #91                 // String individual
     140: areturn
     141: ldc           #92                 // String ConfidentialityByInfoType
     143: areturn
     144: ldc           #93                 // String substance abuse related
     146: areturn
     147: ldc           #94                 // String HIV related
     149: areturn
     150: ldc           #95                 // String psychiatry relate
     152: areturn
     153: ldc           #96                 // String sexual and domestic violence related
     155: areturn
     156: ldc           #97                 // String ConfidentialityModifiers
     158: areturn
     159: ldc           #98                 // String celebrity
     161: areturn
     162: ldc           #99                 // String sensitive
     164: areturn
     165: ldc           #100                // String taboo
     167: areturn
     168: aconst_null
     169: areturn
     170: ldc           #59                 // String ?
     172: areturn

  static {};
    Code:
       0: new           #4                  // class org/hl7/fhir/dstu3/model/codesystems/V3Confidentiality
       3: dup
       4: ldc           #101                // String _CONFIDENTIALITY
       6: iconst_0
       7: invokespecial #102                // Method "<init>":(Ljava/lang/String;I)V
      10: putstatic     #10                 // Field _CONFIDENTIALITY:Lorg/hl7/fhir/dstu3/model/codesystems/V3Confidentiality;
      13: new           #4                  // class org/hl7/fhir/dstu3/model/codesystems/V3Confidentiality
      16: dup
      17: ldc           #11                 // String L
      19: iconst_1
      20: invokespecial #102                // Method "<init>":(Ljava/lang/String;I)V
      23: putstatic     #12                 // Field L:Lorg/hl7/fhir/dstu3/model/codesystems/V3Confidentiality;
      26: new           #4                  // class org/hl7/fhir/dstu3/model/codesystems/V3Confidentiality
      29: dup
      30: ldc           #13                 // String M
      32: iconst_2
      33: invokespecial #102                // Method "<init>":(Ljava/lang/String;I)V
      36: putstatic     #14                 // Field M:Lorg/hl7/fhir/dstu3/model/codesystems/V3Confidentiality;
      39: new           #4                  // class org/hl7/fhir/dstu3/model/codesystems/V3Confidentiality
      42: dup
      43: ldc           #15                 // String N
      45: iconst_3
      46: invokespecial #102                // Method "<init>":(Ljava/lang/String;I)V
      49: putstatic     #16                 // Field N:Lorg/hl7/fhir/dstu3/model/codesystems/V3Confidentiality;
      52: new           #4                  // class org/hl7/fhir/dstu3/model/codesystems/V3Confidentiality
      55: dup
      56: ldc           #17                 // String R
      58: iconst_4
      59: invokespecial #102                // Method "<init>":(Ljava/lang/String;I)V
      62: putstatic     #18                 // Field R:Lorg/hl7/fhir/dstu3/model/codesystems/V3Confidentiality;
      65: new           #4                  // class org/hl7/fhir/dstu3/model/codesystems/V3Confidentiality
      68: dup
      69: ldc           #19                 // String U
      71: iconst_5
      72: invokespecial #102                // Method "<init>":(Ljava/lang/String;I)V
      75: putstatic     #20                 // Field U:Lorg/hl7/fhir/dstu3/model/codesystems/V3Confidentiality;
      78: new           #4                  // class org/hl7/fhir/dstu3/model/codesystems/V3Confidentiality
      81: dup
      82: ldc           #21                 // String V
      84: bipush        6
      86: invokespecial #102                // Method "<init>":(Ljava/lang/String;I)V
      89: putstatic     #22                 // Field V:Lorg/hl7/fhir/dstu3/model/codesystems/V3Confidentiality;
      92: new           #4                  // class org/hl7/fhir/dstu3/model/codesystems/V3Confidentiality
      95: dup
      96: ldc           #103                // String _CONFIDENTIALITYBYACCESSKIND
      98: bipush        7
     100: invokespecial #102                // Method "<init>":(Ljava/lang/String;I)V
     103: putstatic     #24                 // Field _CONFIDENTIALITYBYACCESSKIND:Lorg/hl7/fhir/dstu3/model/codesystems/V3Confidentiality;
     106: new           #4                  // class org/hl7/fhir/dstu3/model/codesystems/V3Confidentiality
     109: dup
     110: ldc           #25                 // String B
     112: bipush        8
     114: invokespecial #102                // Method "<init>":(Ljava/lang/String;I)V
     117: putstatic     #26                 // Field B:Lorg/hl7/fhir/dstu3/model/codesystems/V3Confidentiality;
     120: new           #4                  // class org/hl7/fhir/dstu3/model/codesystems/V3Confidentiality
     123: dup
     124: ldc           #27                 // String D
     126: bipush        9
     128: invokespecial #102                // Method "<init>":(Ljava/lang/String;I)V
     131: putstatic     #28                 // Field D:Lorg/hl7/fhir/dstu3/model/codesystems/V3Confidentiality;
     134: new           #4                  // class org/hl7/fhir/dstu3/model/codesystems/V3Confidentiality
     137: dup
     138: ldc           #29                 // String I
     140: bipush        10
     142: invokespecial #102                // Method "<init>":(Ljava/lang/String;I)V
     145: putstatic     #30                 // Field I:Lorg/hl7/fhir/dstu3/model/codesystems/V3Confidentiality;
     148: new           #4                  // class org/hl7/fhir/dstu3/model/codesystems/V3Confidentiality
     151: dup
     152: ldc           #104                // String _CONFIDENTIALITYBYINFOTYPE
     154: bipush        11
     156: invokespecial #102                // Method "<init>":(Ljava/lang/String;I)V
     159: putstatic     #32                 // Field _CONFIDENTIALITYBYINFOTYPE:Lorg/hl7/fhir/dstu3/model/codesystems/V3Confidentiality;
     162: new           #4                  // class org/hl7/fhir/dstu3/model/codesystems/V3Confidentiality
     165: dup
     166: ldc           #33                 // String ETH
     168: bipush        12
     170: invokespecial #102                // Method "<init>":(Ljava/lang/String;I)V
     173: putstatic     #34                 // Field ETH:Lorg/hl7/fhir/dstu3/model/codesystems/V3Confidentiality;
     176: new           #4                  // class org/hl7/fhir/dstu3/model/codesystems/V3Confidentiality
     179: dup
     180: ldc           #35                 // String HIV
     182: bipush        13
     184: invokespecial #102                // Method "<init>":(Ljava/lang/String;I)V
     187: putstatic     #36                 // Field HIV:Lorg/hl7/fhir/dstu3/model/codesystems/V3Confidentiality;
     190: new           #4                  // class org/hl7/fhir/dstu3/model/codesystems/V3Confidentiality
     193: dup
     194: ldc           #37                 // String PSY
     196: bipush        14
     198: invokespecial #102                // Method "<init>":(Ljava/lang/String;I)V
     201: putstatic     #38                 // Field PSY:Lorg/hl7/fhir/dstu3/model/codesystems/V3Confidentiality;
     204: new           #4                  // class org/hl7/fhir/dstu3/model/codesystems/V3Confidentiality
     207: dup
     208: ldc           #39                 // String SDV
     210: bipush        15
     212: invokespecial #102                // Method "<init>":(Ljava/lang/String;I)V
     215: putstatic     #40                 // Field SDV:Lorg/hl7/fhir/dstu3/model/codesystems/V3Confidentiality;
     218: new           #4                  // class org/hl7/fhir/dstu3/model/codesystems/V3Confidentiality
     221: dup
     222: ldc           #105                // String _CONFIDENTIALITYMODIFIERS
     224: bipush        16
     226: invokespecial #102                // Method "<init>":(Ljava/lang/String;I)V
     229: putstatic     #42                 // Field _CONFIDENTIALITYMODIFIERS:Lorg/hl7/fhir/dstu3/model/codesystems/V3Confidentiality;
     232: new           #4                  // class org/hl7/fhir/dstu3/model/codesystems/V3Confidentiality
     235: dup
     236: ldc           #43                 // String C
     238: bipush        17
     240: invokespecial #102                // Method "<init>":(Ljava/lang/String;I)V
     243: putstatic     #44                 // Field C:Lorg/hl7/fhir/dstu3/model/codesystems/V3Confidentiality;
     246: new           #4                  // class org/hl7/fhir/dstu3/model/codesystems/V3Confidentiality
     249: dup
     250: ldc           #45                 // String S
     252: bipush        18
     254: invokespecial #102                // Method "<init>":(Ljava/lang/String;I)V
     257: putstatic     #46                 // Field S:Lorg/hl7/fhir/dstu3/model/codesystems/V3Confidentiality;
     260: new           #4                  // class org/hl7/fhir/dstu3/model/codesystems/V3Confidentiality
     263: dup
     264: ldc           #47                 // String T
     266: bipush        19
     268: invokespecial #102                // Method "<init>":(Ljava/lang/String;I)V
     271: putstatic     #48                 // Field T:Lorg/hl7/fhir/dstu3/model/codesystems/V3Confidentiality;
     274: new           #4                  // class org/hl7/fhir/dstu3/model/codesystems/V3Confidentiality
     277: dup
     278: ldc           #106                // String NULL
     280: bipush        20
     282: invokespecial #102                // Method "<init>":(Ljava/lang/String;I)V
     285: putstatic     #107                // Field NULL:Lorg/hl7/fhir/dstu3/model/codesystems/V3Confidentiality;
     288: bipush        21
     290: anewarray     #4                  // class org/hl7/fhir/dstu3/model/codesystems/V3Confidentiality
     293: dup
     294: iconst_0
     295: getstatic     #10                 // Field _CONFIDENTIALITY:Lorg/hl7/fhir/dstu3/model/codesystems/V3Confidentiality;
     298: aastore
     299: dup
     300: iconst_1
     301: getstatic     #12                 // Field L:Lorg/hl7/fhir/dstu3/model/codesystems/V3Confidentiality;
     304: aastore
     305: dup
     306: iconst_2
     307: getstatic     #14                 // Field M:Lorg/hl7/fhir/dstu3/model/codesystems/V3Confidentiality;
     310: aastore
     311: dup
     312: iconst_3
     313: getstatic     #16                 // Field N:Lorg/hl7/fhir/dstu3/model/codesystems/V3Confidentiality;
     316: aastore
     317: dup
     318: iconst_4
     319: getstatic     #18                 // Field R:Lorg/hl7/fhir/dstu3/model/codesystems/V3Confidentiality;
     322: aastore
     323: dup
     324: iconst_5
     325: getstatic     #20                 // Field U:Lorg/hl7/fhir/dstu3/model/codesystems/V3Confidentiality;
     328: aastore
     329: dup
     330: bipush        6
     332: getstatic     #22                 // Field V:Lorg/hl7/fhir/dstu3/model/codesystems/V3Confidentiality;
     335: aastore
     336: dup
     337: bipush        7
     339: getstatic     #24                 // Field _CONFIDENTIALITYBYACCESSKIND:Lorg/hl7/fhir/dstu3/model/codesystems/V3Confidentiality;
     342: aastore
     343: dup
     344: bipush        8
     346: getstatic     #26                 // Field B:Lorg/hl7/fhir/dstu3/model/codesystems/V3Confidentiality;
     349: aastore
     350: dup
     351: bipush        9
     353: getstatic     #28                 // Field D:Lorg/hl7/fhir/dstu3/model/codesystems/V3Confidentiality;
     356: aastore
     357: dup
     358: bipush        10
     360: getstatic     #30                 // Field I:Lorg/hl7/fhir/dstu3/model/codesystems/V3Confidentiality;
     363: aastore
     364: dup
     365: bipush        11
     367: getstatic     #32                 // Field _CONFIDENTIALITYBYINFOTYPE:Lorg/hl7/fhir/dstu3/model/codesystems/V3Confidentiality;
     370: aastore
     371: dup
     372: bipush        12
     374: getstatic     #34                 // Field ETH:Lorg/hl7/fhir/dstu3/model/codesystems/V3Confidentiality;
     377: aastore
     378: dup
     379: bipush        13
     381: getstatic     #36                 // Field HIV:Lorg/hl7/fhir/dstu3/model/codesystems/V3Confidentiality;
     384: aastore
     385: dup
     386: bipush        14
     388: getstatic     #38                 // Field PSY:Lorg/hl7/fhir/dstu3/model/codesystems/V3Confidentiality;
     391: aastore
     392: dup
     393: bipush        15
     395: getstatic     #40                 // Field SDV:Lorg/hl7/fhir/dstu3/model/codesystems/V3Confidentiality;
     398: aastore
     399: dup
     400: bipush        16
     402: getstatic     #42                 // Field _CONFIDENTIALITYMODIFIERS:Lorg/hl7/fhir/dstu3/model/codesystems/V3Confidentiality;
     405: aastore
     406: dup
     407: bipush        17
     409: getstatic     #44                 // Field C:Lorg/hl7/fhir/dstu3/model/codesystems/V3Confidentiality;
     412: aastore
     413: dup
     414: bipush        18
     416: getstatic     #46                 // Field S:Lorg/hl7/fhir/dstu3/model/codesystems/V3Confidentiality;
     419: aastore
     420: dup
     421: bipush        19
     423: getstatic     #48                 // Field T:Lorg/hl7/fhir/dstu3/model/codesystems/V3Confidentiality;
     426: aastore
     427: dup
     428: bipush        20
     430: getstatic     #107                // Field NULL:Lorg/hl7/fhir/dstu3/model/codesystems/V3Confidentiality;
     433: aastore
     434: putstatic     #1                  // Field $VALUES:[Lorg/hl7/fhir/dstu3/model/codesystems/V3Confidentiality;
     437: return
}
