Compiled from "V3EntityHandling.java"
public final class org.hl7.fhir.dstu3.model.codesystems.V3EntityHandling extends java.lang.Enum<org.hl7.fhir.dstu3.model.codesystems.V3EntityHandling> {
  public static final org.hl7.fhir.dstu3.model.codesystems.V3EntityHandling AMB;

  public static final org.hl7.fhir.dstu3.model.codesystems.V3EntityHandling C37;

  public static final org.hl7.fhir.dstu3.model.codesystems.V3EntityHandling CAMB;

  public static final org.hl7.fhir.dstu3.model.codesystems.V3EntityHandling CATM;

  public static final org.hl7.fhir.dstu3.model.codesystems.V3EntityHandling CFRZ;

  public static final org.hl7.fhir.dstu3.model.codesystems.V3EntityHandling CREF;

  public static final org.hl7.fhir.dstu3.model.codesystems.V3EntityHandling DFRZ;

  public static final org.hl7.fhir.dstu3.model.codesystems.V3EntityHandling DRY;

  public static final org.hl7.fhir.dstu3.model.codesystems.V3EntityHandling FRZ;

  public static final org.hl7.fhir.dstu3.model.codesystems.V3EntityHandling MTLF;

  public static final org.hl7.fhir.dstu3.model.codesystems.V3EntityHandling NTR;

  public static final org.hl7.fhir.dstu3.model.codesystems.V3EntityHandling PRTL;

  public static final org.hl7.fhir.dstu3.model.codesystems.V3EntityHandling PSA;

  public static final org.hl7.fhir.dstu3.model.codesystems.V3EntityHandling PSO;

  public static final org.hl7.fhir.dstu3.model.codesystems.V3EntityHandling REF;

  public static final org.hl7.fhir.dstu3.model.codesystems.V3EntityHandling SBU;

  public static final org.hl7.fhir.dstu3.model.codesystems.V3EntityHandling UFRZ;

  public static final org.hl7.fhir.dstu3.model.codesystems.V3EntityHandling UPR;

  public static final org.hl7.fhir.dstu3.model.codesystems.V3EntityHandling NULL;

  private static final org.hl7.fhir.dstu3.model.codesystems.V3EntityHandling[] $VALUES;

  public static org.hl7.fhir.dstu3.model.codesystems.V3EntityHandling[] values();
    Code:
       0: getstatic     #1                  // Field $VALUES:[Lorg/hl7/fhir/dstu3/model/codesystems/V3EntityHandling;
       3: invokevirtual #2                  // Method "[Lorg/hl7/fhir/dstu3/model/codesystems/V3EntityHandling;".clone:()Ljava/lang/Object;
       6: checkcast     #3                  // class "[Lorg/hl7/fhir/dstu3/model/codesystems/V3EntityHandling;"
       9: areturn

  public static org.hl7.fhir.dstu3.model.codesystems.V3EntityHandling valueOf(java.lang.String);
    Code:
       0: ldc           #4                  // class org/hl7/fhir/dstu3/model/codesystems/V3EntityHandling
       2: aload_0
       3: invokestatic  #5                  // Method java/lang/Enum.valueOf:(Ljava/lang/Class;Ljava/lang/String;)Ljava/lang/Enum;
       6: checkcast     #4                  // class org/hl7/fhir/dstu3/model/codesystems/V3EntityHandling
       9: areturn

  private org.hl7.fhir.dstu3.model.codesystems.V3EntityHandling();
    Code:
       0: aload_0
       1: aload_1
       2: iload_2
       3: invokespecial #6                  // Method java/lang/Enum."<init>":(Ljava/lang/String;I)V
       6: return

  public static org.hl7.fhir.dstu3.model.codesystems.V3EntityHandling fromCode(java.lang.String) throws org.hl7.fhir.exceptions.FHIRException;
    Code:
       0: aload_0
       1: ifnull        13
       4: ldc           #7                  // String
       6: aload_0
       7: invokevirtual #8                  // Method java/lang/String.equals:(Ljava/lang/Object;)Z
      10: ifeq          15
      13: aconst_null
      14: areturn
      15: ldc           #9                  // String AMB
      17: aload_0
      18: invokevirtual #8                  // Method java/lang/String.equals:(Ljava/lang/Object;)Z
      21: ifeq          28
      24: getstatic     #10                 // Field AMB:Lorg/hl7/fhir/dstu3/model/codesystems/V3EntityHandling;
      27: areturn
      28: ldc           #11                 // String C37
      30: aload_0
      31: invokevirtual #8                  // Method java/lang/String.equals:(Ljava/lang/Object;)Z
      34: ifeq          41
      37: getstatic     #12                 // Field C37:Lorg/hl7/fhir/dstu3/model/codesystems/V3EntityHandling;
      40: areturn
      41: ldc           #13                 // String CAMB
      43: aload_0
      44: invokevirtual #8                  // Method java/lang/String.equals:(Ljava/lang/Object;)Z
      47: ifeq          54
      50: getstatic     #14                 // Field CAMB:Lorg/hl7/fhir/dstu3/model/codesystems/V3EntityHandling;
      53: areturn
      54: ldc           #15                 // String CATM
      56: aload_0
      57: invokevirtual #8                  // Method java/lang/String.equals:(Ljava/lang/Object;)Z
      60: ifeq          67
      63: getstatic     #16                 // Field CATM:Lorg/hl7/fhir/dstu3/model/codesystems/V3EntityHandling;
      66: areturn
      67: ldc           #17                 // String CFRZ
      69: aload_0
      70: invokevirtual #8                  // Method java/lang/String.equals:(Ljava/lang/Object;)Z
      73: ifeq          80
      76: getstatic     #18                 // Field CFRZ:Lorg/hl7/fhir/dstu3/model/codesystems/V3EntityHandling;
      79: areturn
      80: ldc           #19                 // String CREF
      82: aload_0
      83: invokevirtual #8                  // Method java/lang/String.equals:(Ljava/lang/Object;)Z
      86: ifeq          93
      89: getstatic     #20                 // Field CREF:Lorg/hl7/fhir/dstu3/model/codesystems/V3EntityHandling;
      92: areturn
      93: ldc           #21                 // String DFRZ
      95: aload_0
      96: invokevirtual #8                  // Method java/lang/String.equals:(Ljava/lang/Object;)Z
      99: ifeq          106
     102: getstatic     #22                 // Field DFRZ:Lorg/hl7/fhir/dstu3/model/codesystems/V3EntityHandling;
     105: areturn
     106: ldc           #23                 // String DRY
     108: aload_0
     109: invokevirtual #8                  // Method java/lang/String.equals:(Ljava/lang/Object;)Z
     112: ifeq          119
     115: getstatic     #24                 // Field DRY:Lorg/hl7/fhir/dstu3/model/codesystems/V3EntityHandling;
     118: areturn
     119: ldc           #25                 // String FRZ
     121: aload_0
     122: invokevirtual #8                  // Method java/lang/String.equals:(Ljava/lang/Object;)Z
     125: ifeq          132
     128: getstatic     #26                 // Field FRZ:Lorg/hl7/fhir/dstu3/model/codesystems/V3EntityHandling;
     131: areturn
     132: ldc           #27                 // String MTLF
     134: aload_0
     135: invokevirtual #8                  // Method java/lang/String.equals:(Ljava/lang/Object;)Z
     138: ifeq          145
     141: getstatic     #28                 // Field MTLF:Lorg/hl7/fhir/dstu3/model/codesystems/V3EntityHandling;
     144: areturn
     145: ldc           #29                 // String NTR
     147: aload_0
     148: invokevirtual #8                  // Method java/lang/String.equals:(Ljava/lang/Object;)Z
     151: ifeq          158
     154: getstatic     #30                 // Field NTR:Lorg/hl7/fhir/dstu3/model/codesystems/V3EntityHandling;
     157: areturn
     158: ldc           #31                 // String PRTL
     160: aload_0
     161: invokevirtual #8                  // Method java/lang/String.equals:(Ljava/lang/Object;)Z
     164: ifeq          171
     167: getstatic     #32                 // Field PRTL:Lorg/hl7/fhir/dstu3/model/codesystems/V3EntityHandling;
     170: areturn
     171: ldc           #33                 // String PSA
     173: aload_0
     174: invokevirtual #8                  // Method java/lang/String.equals:(Ljava/lang/Object;)Z
     177: ifeq          184
     180: getstatic     #34                 // Field PSA:Lorg/hl7/fhir/dstu3/model/codesystems/V3EntityHandling;
     183: areturn
     184: ldc           #35                 // String PSO
     186: aload_0
     187: invokevirtual #8                  // Method java/lang/String.equals:(Ljava/lang/Object;)Z
     190: ifeq          197
     193: getstatic     #36                 // Field PSO:Lorg/hl7/fhir/dstu3/model/codesystems/V3EntityHandling;
     196: areturn
     197: ldc           #37                 // String REF
     199: aload_0
     200: invokevirtual #8                  // Method java/lang/String.equals:(Ljava/lang/Object;)Z
     203: ifeq          210
     206: getstatic     #38                 // Field REF:Lorg/hl7/fhir/dstu3/model/codesystems/V3EntityHandling;
     209: areturn
     210: ldc           #39                 // String SBU
     212: aload_0
     213: invokevirtual #8                  // Method java/lang/String.equals:(Ljava/lang/Object;)Z
     216: ifeq          223
     219: getstatic     #40                 // Field SBU:Lorg/hl7/fhir/dstu3/model/codesystems/V3EntityHandling;
     222: areturn
     223: ldc           #41                 // String UFRZ
     225: aload_0
     226: invokevirtual #8                  // Method java/lang/String.equals:(Ljava/lang/Object;)Z
     229: ifeq          236
     232: getstatic     #42                 // Field UFRZ:Lorg/hl7/fhir/dstu3/model/codesystems/V3EntityHandling;
     235: areturn
     236: ldc           #43                 // String UPR
     238: aload_0
     239: invokevirtual #8                  // Method java/lang/String.equals:(Ljava/lang/Object;)Z
     242: ifeq          249
     245: getstatic     #44                 // Field UPR:Lorg/hl7/fhir/dstu3/model/codesystems/V3EntityHandling;
     248: areturn
     249: new           #45                 // class org/hl7/fhir/exceptions/FHIRException
     252: dup
     253: new           #46                 // class java/lang/StringBuilder
     256: dup
     257: invokespecial #47                 // Method java/lang/StringBuilder."<init>":()V
     260: ldc           #48                 // String Unknown V3EntityHandling code \'
     262: invokevirtual #49                 // Method java/lang/StringBuilder.append:(Ljava/lang/String;)Ljava/lang/StringBuilder;
     265: aload_0
     266: invokevirtual #49                 // Method java/lang/StringBuilder.append:(Ljava/lang/String;)Ljava/lang/StringBuilder;
     269: ldc           #50                 // String \'
     271: invokevirtual #49                 // Method java/lang/StringBuilder.append:(Ljava/lang/String;)Ljava/lang/StringBuilder;
     274: invokevirtual #51                 // Method java/lang/StringBuilder.toString:()Ljava/lang/String;
     277: invokespecial #52                 // Method org/hl7/fhir/exceptions/FHIRException."<init>":(Ljava/lang/String;)V
     280: athrow

  public java.lang.String toCode();
    Code:
       0: getstatic     #53                 // Field org/hl7/fhir/dstu3/model/codesystems/V3EntityHandling$1.$SwitchMap$org$hl7$fhir$dstu3$model$codesystems$V3EntityHandling:[I
       3: aload_0
       4: invokevirtual #54                 // Method ordinal:()I
       7: iaload
       8: tableswitch   { // 1 to 19
                     1: 100
                     2: 103
                     3: 106
                     4: 109
                     5: 112
                     6: 115
                     7: 118
                     8: 121
                     9: 124
                    10: 127
                    11: 130
                    12: 133
                    13: 136
                    14: 139
                    15: 142
                    16: 145
                    17: 148
                    18: 151
                    19: 154
               default: 156
          }
     100: ldc           #9                  // String AMB
     102: areturn
     103: ldc           #11                 // String C37
     105: areturn
     106: ldc           #13                 // String CAMB
     108: areturn
     109: ldc           #15                 // String CATM
     111: areturn
     112: ldc           #17                 // String CFRZ
     114: areturn
     115: ldc           #19                 // String CREF
     117: areturn
     118: ldc           #21                 // String DFRZ
     120: areturn
     121: ldc           #23                 // String DRY
     123: areturn
     124: ldc           #25                 // String FRZ
     126: areturn
     127: ldc           #27                 // String MTLF
     129: areturn
     130: ldc           #29                 // String NTR
     132: areturn
     133: ldc           #31                 // String PRTL
     135: areturn
     136: ldc           #33                 // String PSA
     138: areturn
     139: ldc           #35                 // String PSO
     141: areturn
     142: ldc           #37                 // String REF
     144: areturn
     145: ldc           #39                 // String SBU
     147: areturn
     148: ldc           #41                 // String UFRZ
     150: areturn
     151: ldc           #43                 // String UPR
     153: areturn
     154: aconst_null
     155: areturn
     156: ldc           #55                 // String ?
     158: areturn

  public java.lang.String getSystem();
    Code:
       0: ldc           #56                 // String http://hl7.org/fhir/v3/EntityHandling
       2: areturn

  public java.lang.String getDefinition();
    Code:
       0: getstatic     #53                 // Field org/hl7/fhir/dstu3/model/codesystems/V3EntityHandling$1.$SwitchMap$org$hl7$fhir$dstu3$model$codesystems$V3EntityHandling:[I
       3: aload_0
       4: invokevirtual #54                 // Method ordinal:()I
       7: iaload
       8: tableswitch   { // 1 to 19
                     1: 100
                     2: 103
                     3: 106
                     4: 109
                     5: 112
                     6: 115
                     7: 118
                     8: 121
                     9: 124
                    10: 127
                    11: 130
                    12: 133
                    13: 136
                    14: 139
                    15: 142
                    16: 145
                    17: 148
                    18: 151
                    19: 154
               default: 156
          }
     100: ldc           #57                 // String Keep at ambient temperature, 22 +/- 2C
     102: areturn
     103: ldc           #58                 // String Critical to keep at body temperature 36-38C
     105: areturn
     106: ldc           #59                 // String Critical ambient - must not be refrigerated or frozen.
     108: areturn
     109: ldc           #60                 // String Critical. Do not expose to atmosphere.  Do not uncap.
     111: areturn
     112: ldc           #61                 // String Critical frozen. Specimen must not be allowed to thaw until immediately prior to testing.
     114: areturn
     115: ldc           #62                 // String Critical refrigerated - must not be allowed to freeze or warm until imediately prior to testing.
     117: areturn
     118: ldc           #63                 // String Deep Frozen -16 to -20C.
     120: areturn
     121: ldc           #64                 // String Keep in a dry environment
     123: areturn
     124: ldc           #65                 // String Keep frozen below 0 ?C
     126: areturn
     127: ldc           #66                 // String Container is free of heavy metals, including lead.
     129: areturn
     130: ldc           #67                 // String Keep in liquid nitrogen
     132: areturn
     133: ldc           #68                 // String Protect from light (eg. Wrap in aluminum foil).
     135: areturn
     136: ldc           #69                 // String Do not shake
     138: areturn
     139: ldc           #70                 // String Protect against shock
     141: areturn
     142: ldc           #71                 // String Keep at refrigerated temperature:4-8C Accidental warming or freezing is of little consequence.
     144: areturn
     145: ldc           #72                 // String Shake thoroughly before using
     147: areturn
     148: ldc           #73                 // String Ultra cold frozen -75 to -85C.  Ultra cold freezer is typically at temperature of dry ice.
     150: areturn
     151: ldc           #74                 // String Keep upright, do not turn upside down
     153: areturn
     154: aconst_null
     155: areturn
     156: ldc           #55                 // String ?
     158: areturn

  public java.lang.String getDisplay();
    Code:
       0: getstatic     #53                 // Field org/hl7/fhir/dstu3/model/codesystems/V3EntityHandling$1.$SwitchMap$org$hl7$fhir$dstu3$model$codesystems$V3EntityHandling:[I
       3: aload_0
       4: invokevirtual #54                 // Method ordinal:()I
       7: iaload
       8: tableswitch   { // 1 to 19
                     1: 100
                     2: 103
                     3: 106
                     4: 109
                     5: 112
                     6: 115
                     7: 118
                     8: 121
                     9: 124
                    10: 127
                    11: 130
                    12: 133
                    13: 136
                    14: 139
                    15: 142
                    16: 145
                    17: 148
                    18: 151
                    19: 154
               default: 156
          }
     100: ldc           #75                 // String Ambient Temperature
     102: areturn
     103: ldc           #76                 // String Body Temperature
     105: areturn
     106: ldc           #77                 // String Critical Ambient temperature
     108: areturn
     109: ldc           #78                 // String Protect from Air
     111: areturn
     112: ldc           #79                 // String Critical frozen
     114: areturn
     115: ldc           #80                 // String Critical refrigerated temperature
     117: areturn
     118: ldc           #81                 // String Deep Frozen
     120: areturn
     121: ldc           #82                 // String dry
     123: areturn
     124: ldc           #83                 // String frozen
     126: areturn
     127: ldc           #84                 // String Metal Free
     129: areturn
     130: ldc           #85                 // String nitrogen
     132: areturn
     133: ldc           #86                 // String Protect from Light
     135: areturn
     136: ldc           #87                 // String do not shake
     138: areturn
     139: ldc           #88                 // String no shock
     141: areturn
     142: ldc           #89                 // String Refrigerated temperature
     144: areturn
     145: ldc           #90                 // String Shake before use
     147: areturn
     148: ldc           #91                 // String Ultra frozen
     150: areturn
     151: ldc           #92                 // String upright
     153: areturn
     154: aconst_null
     155: areturn
     156: ldc           #55                 // String ?
     158: areturn

  static {};
    Code:
       0: new           #4                  // class org/hl7/fhir/dstu3/model/codesystems/V3EntityHandling
       3: dup
       4: ldc           #9                  // String AMB
       6: iconst_0
       7: invokespecial #93                 // Method "<init>":(Ljava/lang/String;I)V
      10: putstatic     #10                 // Field AMB:Lorg/hl7/fhir/dstu3/model/codesystems/V3EntityHandling;
      13: new           #4                  // class org/hl7/fhir/dstu3/model/codesystems/V3EntityHandling
      16: dup
      17: ldc           #11                 // String C37
      19: iconst_1
      20: invokespecial #93                 // Method "<init>":(Ljava/lang/String;I)V
      23: putstatic     #12                 // Field C37:Lorg/hl7/fhir/dstu3/model/codesystems/V3EntityHandling;
      26: new           #4                  // class org/hl7/fhir/dstu3/model/codesystems/V3EntityHandling
      29: dup
      30: ldc           #13                 // String CAMB
      32: iconst_2
      33: invokespecial #93                 // Method "<init>":(Ljava/lang/String;I)V
      36: putstatic     #14                 // Field CAMB:Lorg/hl7/fhir/dstu3/model/codesystems/V3EntityHandling;
      39: new           #4                  // class org/hl7/fhir/dstu3/model/codesystems/V3EntityHandling
      42: dup
      43: ldc           #15                 // String CATM
      45: iconst_3
      46: invokespecial #93                 // Method "<init>":(Ljava/lang/String;I)V
      49: putstatic     #16                 // Field CATM:Lorg/hl7/fhir/dstu3/model/codesystems/V3EntityHandling;
      52: new           #4                  // class org/hl7/fhir/dstu3/model/codesystems/V3EntityHandling
      55: dup
      56: ldc           #17                 // String CFRZ
      58: iconst_4
      59: invokespecial #93                 // Method "<init>":(Ljava/lang/String;I)V
      62: putstatic     #18                 // Field CFRZ:Lorg/hl7/fhir/dstu3/model/codesystems/V3EntityHandling;
      65: new           #4                  // class org/hl7/fhir/dstu3/model/codesystems/V3EntityHandling
      68: dup
      69: ldc           #19                 // String CREF
      71: iconst_5
      72: invokespecial #93                 // Method "<init>":(Ljava/lang/String;I)V
      75: putstatic     #20                 // Field CREF:Lorg/hl7/fhir/dstu3/model/codesystems/V3EntityHandling;
      78: new           #4                  // class org/hl7/fhir/dstu3/model/codesystems/V3EntityHandling
      81: dup
      82: ldc           #21                 // String DFRZ
      84: bipush        6
      86: invokespecial #93                 // Method "<init>":(Ljava/lang/String;I)V
      89: putstatic     #22                 // Field DFRZ:Lorg/hl7/fhir/dstu3/model/codesystems/V3EntityHandling;
      92: new           #4                  // class org/hl7/fhir/dstu3/model/codesystems/V3EntityHandling
      95: dup
      96: ldc           #23                 // String DRY
      98: bipush        7
     100: invokespecial #93                 // Method "<init>":(Ljava/lang/String;I)V
     103: putstatic     #24                 // Field DRY:Lorg/hl7/fhir/dstu3/model/codesystems/V3EntityHandling;
     106: new           #4                  // class org/hl7/fhir/dstu3/model/codesystems/V3EntityHandling
     109: dup
     110: ldc           #25                 // String FRZ
     112: bipush        8
     114: invokespecial #93                 // Method "<init>":(Ljava/lang/String;I)V
     117: putstatic     #26                 // Field FRZ:Lorg/hl7/fhir/dstu3/model/codesystems/V3EntityHandling;
     120: new           #4                  // class org/hl7/fhir/dstu3/model/codesystems/V3EntityHandling
     123: dup
     124: ldc           #27                 // String MTLF
     126: bipush        9
     128: invokespecial #93                 // Method "<init>":(Ljava/lang/String;I)V
     131: putstatic     #28                 // Field MTLF:Lorg/hl7/fhir/dstu3/model/codesystems/V3EntityHandling;
     134: new           #4                  // class org/hl7/fhir/dstu3/model/codesystems/V3EntityHandling
     137: dup
     138: ldc           #29                 // String NTR
     140: bipush        10
     142: invokespecial #93                 // Method "<init>":(Ljava/lang/String;I)V
     145: putstatic     #30                 // Field NTR:Lorg/hl7/fhir/dstu3/model/codesystems/V3EntityHandling;
     148: new           #4                  // class org/hl7/fhir/dstu3/model/codesystems/V3EntityHandling
     151: dup
     152: ldc           #31                 // String PRTL
     154: bipush        11
     156: invokespecial #93                 // Method "<init>":(Ljava/lang/String;I)V
     159: putstatic     #32                 // Field PRTL:Lorg/hl7/fhir/dstu3/model/codesystems/V3EntityHandling;
     162: new           #4                  // class org/hl7/fhir/dstu3/model/codesystems/V3EntityHandling
     165: dup
     166: ldc           #33                 // String PSA
     168: bipush        12
     170: invokespecial #93                 // Method "<init>":(Ljava/lang/String;I)V
     173: putstatic     #34                 // Field PSA:Lorg/hl7/fhir/dstu3/model/codesystems/V3EntityHandling;
     176: new           #4                  // class org/hl7/fhir/dstu3/model/codesystems/V3EntityHandling
     179: dup
     180: ldc           #35                 // String PSO
     182: bipush        13
     184: invokespecial #93                 // Method "<init>":(Ljava/lang/String;I)V
     187: putstatic     #36                 // Field PSO:Lorg/hl7/fhir/dstu3/model/codesystems/V3EntityHandling;
     190: new           #4                  // class org/hl7/fhir/dstu3/model/codesystems/V3EntityHandling
     193: dup
     194: ldc           #37                 // String REF
     196: bipush        14
     198: invokespecial #93                 // Method "<init>":(Ljava/lang/String;I)V
     201: putstatic     #38                 // Field REF:Lorg/hl7/fhir/dstu3/model/codesystems/V3EntityHandling;
     204: new           #4                  // class org/hl7/fhir/dstu3/model/codesystems/V3EntityHandling
     207: dup
     208: ldc           #39                 // String SBU
     210: bipush        15
     212: invokespecial #93                 // Method "<init>":(Ljava/lang/String;I)V
     215: putstatic     #40                 // Field SBU:Lorg/hl7/fhir/dstu3/model/codesystems/V3EntityHandling;
     218: new           #4                  // class org/hl7/fhir/dstu3/model/codesystems/V3EntityHandling
     221: dup
     222: ldc           #41                 // String UFRZ
     224: bipush        16
     226: invokespecial #93                 // Method "<init>":(Ljava/lang/String;I)V
     229: putstatic     #42                 // Field UFRZ:Lorg/hl7/fhir/dstu3/model/codesystems/V3EntityHandling;
     232: new           #4                  // class org/hl7/fhir/dstu3/model/codesystems/V3EntityHandling
     235: dup
     236: ldc           #43                 // String UPR
     238: bipush        17
     240: invokespecial #93                 // Method "<init>":(Ljava/lang/String;I)V
     243: putstatic     #44                 // Field UPR:Lorg/hl7/fhir/dstu3/model/codesystems/V3EntityHandling;
     246: new           #4                  // class org/hl7/fhir/dstu3/model/codesystems/V3EntityHandling
     249: dup
     250: ldc           #94                 // String NULL
     252: bipush        18
     254: invokespecial #93                 // Method "<init>":(Ljava/lang/String;I)V
     257: putstatic     #95                 // Field NULL:Lorg/hl7/fhir/dstu3/model/codesystems/V3EntityHandling;
     260: bipush        19
     262: anewarray     #4                  // class org/hl7/fhir/dstu3/model/codesystems/V3EntityHandling
     265: dup
     266: iconst_0
     267: getstatic     #10                 // Field AMB:Lorg/hl7/fhir/dstu3/model/codesystems/V3EntityHandling;
     270: aastore
     271: dup
     272: iconst_1
     273: getstatic     #12                 // Field C37:Lorg/hl7/fhir/dstu3/model/codesystems/V3EntityHandling;
     276: aastore
     277: dup
     278: iconst_2
     279: getstatic     #14                 // Field CAMB:Lorg/hl7/fhir/dstu3/model/codesystems/V3EntityHandling;
     282: aastore
     283: dup
     284: iconst_3
     285: getstatic     #16                 // Field CATM:Lorg/hl7/fhir/dstu3/model/codesystems/V3EntityHandling;
     288: aastore
     289: dup
     290: iconst_4
     291: getstatic     #18                 // Field CFRZ:Lorg/hl7/fhir/dstu3/model/codesystems/V3EntityHandling;
     294: aastore
     295: dup
     296: iconst_5
     297: getstatic     #20                 // Field CREF:Lorg/hl7/fhir/dstu3/model/codesystems/V3EntityHandling;
     300: aastore
     301: dup
     302: bipush        6
     304: getstatic     #22                 // Field DFRZ:Lorg/hl7/fhir/dstu3/model/codesystems/V3EntityHandling;
     307: aastore
     308: dup
     309: bipush        7
     311: getstatic     #24                 // Field DRY:Lorg/hl7/fhir/dstu3/model/codesystems/V3EntityHandling;
     314: aastore
     315: dup
     316: bipush        8
     318: getstatic     #26                 // Field FRZ:Lorg/hl7/fhir/dstu3/model/codesystems/V3EntityHandling;
     321: aastore
     322: dup
     323: bipush        9
     325: getstatic     #28                 // Field MTLF:Lorg/hl7/fhir/dstu3/model/codesystems/V3EntityHandling;
     328: aastore
     329: dup
     330: bipush        10
     332: getstatic     #30                 // Field NTR:Lorg/hl7/fhir/dstu3/model/codesystems/V3EntityHandling;
     335: aastore
     336: dup
     337: bipush        11
     339: getstatic     #32                 // Field PRTL:Lorg/hl7/fhir/dstu3/model/codesystems/V3EntityHandling;
     342: aastore
     343: dup
     344: bipush        12
     346: getstatic     #34                 // Field PSA:Lorg/hl7/fhir/dstu3/model/codesystems/V3EntityHandling;
     349: aastore
     350: dup
     351: bipush        13
     353: getstatic     #36                 // Field PSO:Lorg/hl7/fhir/dstu3/model/codesystems/V3EntityHandling;
     356: aastore
     357: dup
     358: bipush        14
     360: getstatic     #38                 // Field REF:Lorg/hl7/fhir/dstu3/model/codesystems/V3EntityHandling;
     363: aastore
     364: dup
     365: bipush        15
     367: getstatic     #40                 // Field SBU:Lorg/hl7/fhir/dstu3/model/codesystems/V3EntityHandling;
     370: aastore
     371: dup
     372: bipush        16
     374: getstatic     #42                 // Field UFRZ:Lorg/hl7/fhir/dstu3/model/codesystems/V3EntityHandling;
     377: aastore
     378: dup
     379: bipush        17
     381: getstatic     #44                 // Field UPR:Lorg/hl7/fhir/dstu3/model/codesystems/V3EntityHandling;
     384: aastore
     385: dup
     386: bipush        18
     388: getstatic     #95                 // Field NULL:Lorg/hl7/fhir/dstu3/model/codesystems/V3EntityHandling;
     391: aastore
     392: putstatic     #1                  // Field $VALUES:[Lorg/hl7/fhir/dstu3/model/codesystems/V3EntityHandling;
     395: return
}
