Compiled from "V3PersonDisabilityTypeEnumFactory.java"
public class org.hl7.fhir.dstu3.model.codesystems.V3PersonDisabilityTypeEnumFactory implements org.hl7.fhir.dstu3.model.EnumFactory<org.hl7.fhir.dstu3.model.codesystems.V3PersonDisabilityType> {
  public org.hl7.fhir.dstu3.model.codesystems.V3PersonDisabilityTypeEnumFactory();
    Code:
       0: aload_0
       1: invokespecial #1                  // Method java/lang/Object."<init>":()V
       4: return

  public org.hl7.fhir.dstu3.model.codesystems.V3PersonDisabilityType fromCode(java.lang.String) throws java.lang.IllegalArgumentException;
    Code:
       0: aload_1
       1: ifnull        13
       4: ldc           #2                  // String
       6: aload_1
       7: invokevirtual #3                  // Method java/lang/String.equals:(Ljava/lang/Object;)Z
      10: ifeq          15
      13: aconst_null
      14: areturn
      15: ldc           #4                  // String 1
      17: aload_1
      18: invokevirtual #3                  // Method java/lang/String.equals:(Ljava/lang/Object;)Z
      21: ifeq          28
      24: getstatic     #5                  // Field org/hl7/fhir/dstu3/model/codesystems/V3PersonDisabilityType._1:Lorg/hl7/fhir/dstu3/model/codesystems/V3PersonDisabilityType;
      27: areturn
      28: ldc           #6                  // String 2
      30: aload_1
      31: invokevirtual #3                  // Method java/lang/String.equals:(Ljava/lang/Object;)Z
      34: ifeq          41
      37: getstatic     #7                  // Field org/hl7/fhir/dstu3/model/codesystems/V3PersonDisabilityType._2:Lorg/hl7/fhir/dstu3/model/codesystems/V3PersonDisabilityType;
      40: areturn
      41: ldc           #8                  // String 3
      43: aload_1
      44: invokevirtual #3                  // Method java/lang/String.equals:(Ljava/lang/Object;)Z
      47: ifeq          54
      50: getstatic     #9                  // Field org/hl7/fhir/dstu3/model/codesystems/V3PersonDisabilityType._3:Lorg/hl7/fhir/dstu3/model/codesystems/V3PersonDisabilityType;
      53: areturn
      54: ldc           #10                 // String 4
      56: aload_1
      57: invokevirtual #3                  // Method java/lang/String.equals:(Ljava/lang/Object;)Z
      60: ifeq          67
      63: getstatic     #11                 // Field org/hl7/fhir/dstu3/model/codesystems/V3PersonDisabilityType._4:Lorg/hl7/fhir/dstu3/model/codesystems/V3PersonDisabilityType;
      66: areturn
      67: ldc           #12                 // String 5
      69: aload_1
      70: invokevirtual #3                  // Method java/lang/String.equals:(Ljava/lang/Object;)Z
      73: ifeq          80
      76: getstatic     #13                 // Field org/hl7/fhir/dstu3/model/codesystems/V3PersonDisabilityType._5:Lorg/hl7/fhir/dstu3/model/codesystems/V3PersonDisabilityType;
      79: areturn
      80: ldc           #14                 // String CB
      82: aload_1
      83: invokevirtual #3                  // Method java/lang/String.equals:(Ljava/lang/Object;)Z
      86: ifeq          93
      89: getstatic     #15                 // Field org/hl7/fhir/dstu3/model/codesystems/V3PersonDisabilityType.CB:Lorg/hl7/fhir/dstu3/model/codesystems/V3PersonDisabilityType;
      92: areturn
      93: ldc           #16                 // String CR
      95: aload_1
      96: invokevirtual #3                  // Method java/lang/String.equals:(Ljava/lang/Object;)Z
      99: ifeq          106
     102: getstatic     #17                 // Field org/hl7/fhir/dstu3/model/codesystems/V3PersonDisabilityType.CR:Lorg/hl7/fhir/dstu3/model/codesystems/V3PersonDisabilityType;
     105: areturn
     106: ldc           #18                 // String G
     108: aload_1
     109: invokevirtual #3                  // Method java/lang/String.equals:(Ljava/lang/Object;)Z
     112: ifeq          119
     115: getstatic     #19                 // Field org/hl7/fhir/dstu3/model/codesystems/V3PersonDisabilityType.G:Lorg/hl7/fhir/dstu3/model/codesystems/V3PersonDisabilityType;
     118: areturn
     119: ldc           #20                 // String WC
     121: aload_1
     122: invokevirtual #3                  // Method java/lang/String.equals:(Ljava/lang/Object;)Z
     125: ifeq          132
     128: getstatic     #21                 // Field org/hl7/fhir/dstu3/model/codesystems/V3PersonDisabilityType.WC:Lorg/hl7/fhir/dstu3/model/codesystems/V3PersonDisabilityType;
     131: areturn
     132: ldc           #22                 // String WK
     134: aload_1
     135: invokevirtual #3                  // Method java/lang/String.equals:(Ljava/lang/Object;)Z
     138: ifeq          145
     141: getstatic     #23                 // Field org/hl7/fhir/dstu3/model/codesystems/V3PersonDisabilityType.WK:Lorg/hl7/fhir/dstu3/model/codesystems/V3PersonDisabilityType;
     144: areturn
     145: new           #24                 // class java/lang/IllegalArgumentException
     148: dup
     149: new           #25                 // class java/lang/StringBuilder
     152: dup
     153: invokespecial #26                 // Method java/lang/StringBuilder."<init>":()V
     156: ldc           #27                 // String Unknown V3PersonDisabilityType code \'
     158: invokevirtual #28                 // Method java/lang/StringBuilder.append:(Ljava/lang/String;)Ljava/lang/StringBuilder;
     161: aload_1
     162: invokevirtual #28                 // Method java/lang/StringBuilder.append:(Ljava/lang/String;)Ljava/lang/StringBuilder;
     165: ldc           #29                 // String \'
     167: invokevirtual #28                 // Method java/lang/StringBuilder.append:(Ljava/lang/String;)Ljava/lang/StringBuilder;
     170: invokevirtual #30                 // Method java/lang/StringBuilder.toString:()Ljava/lang/String;
     173: invokespecial #31                 // Method java/lang/IllegalArgumentException."<init>":(Ljava/lang/String;)V
     176: athrow

  public java.lang.String toCode(org.hl7.fhir.dstu3.model.codesystems.V3PersonDisabilityType);
    Code:
       0: aload_1
       1: getstatic     #5                  // Field org/hl7/fhir/dstu3/model/codesystems/V3PersonDisabilityType._1:Lorg/hl7/fhir/dstu3/model/codesystems/V3PersonDisabilityType;
       4: if_acmpne     10
       7: ldc           #4                  // String 1
       9: areturn
      10: aload_1
      11: getstatic     #7                  // Field org/hl7/fhir/dstu3/model/codesystems/V3PersonDisabilityType._2:Lorg/hl7/fhir/dstu3/model/codesystems/V3PersonDisabilityType;
      14: if_acmpne     20
      17: ldc           #6                  // String 2
      19: areturn
      20: aload_1
      21: getstatic     #9                  // Field org/hl7/fhir/dstu3/model/codesystems/V3PersonDisabilityType._3:Lorg/hl7/fhir/dstu3/model/codesystems/V3PersonDisabilityType;
      24: if_acmpne     30
      27: ldc           #8                  // String 3
      29: areturn
      30: aload_1
      31: getstatic     #11                 // Field org/hl7/fhir/dstu3/model/codesystems/V3PersonDisabilityType._4:Lorg/hl7/fhir/dstu3/model/codesystems/V3PersonDisabilityType;
      34: if_acmpne     40
      37: ldc           #10                 // String 4
      39: areturn
      40: aload_1
      41: getstatic     #13                 // Field org/hl7/fhir/dstu3/model/codesystems/V3PersonDisabilityType._5:Lorg/hl7/fhir/dstu3/model/codesystems/V3PersonDisabilityType;
      44: if_acmpne     50
      47: ldc           #12                 // String 5
      49: areturn
      50: aload_1
      51: getstatic     #15                 // Field org/hl7/fhir/dstu3/model/codesystems/V3PersonDisabilityType.CB:Lorg/hl7/fhir/dstu3/model/codesystems/V3PersonDisabilityType;
      54: if_acmpne     60
      57: ldc           #14                 // String CB
      59: areturn
      60: aload_1
      61: getstatic     #17                 // Field org/hl7/fhir/dstu3/model/codesystems/V3PersonDisabilityType.CR:Lorg/hl7/fhir/dstu3/model/codesystems/V3PersonDisabilityType;
      64: if_acmpne     70
      67: ldc           #16                 // String CR
      69: areturn
      70: aload_1
      71: getstatic     #19                 // Field org/hl7/fhir/dstu3/model/codesystems/V3PersonDisabilityType.G:Lorg/hl7/fhir/dstu3/model/codesystems/V3PersonDisabilityType;
      74: if_acmpne     80
      77: ldc           #18                 // String G
      79: areturn
      80: aload_1
      81: getstatic     #21                 // Field org/hl7/fhir/dstu3/model/codesystems/V3PersonDisabilityType.WC:Lorg/hl7/fhir/dstu3/model/codesystems/V3PersonDisabilityType;
      84: if_acmpne     90
      87: ldc           #20                 // String WC
      89: areturn
      90: aload_1
      91: getstatic     #23                 // Field org/hl7/fhir/dstu3/model/codesystems/V3PersonDisabilityType.WK:Lorg/hl7/fhir/dstu3/model/codesystems/V3PersonDisabilityType;
      94: if_acmpne     100
      97: ldc           #22                 // String WK
      99: areturn
     100: ldc           #32                 // String ?
     102: areturn

  public java.lang.String toSystem(org.hl7.fhir.dstu3.model.codesystems.V3PersonDisabilityType);
    Code:
       0: aload_1
       1: invokevirtual #33                 // Method org/hl7/fhir/dstu3/model/codesystems/V3PersonDisabilityType.getSystem:()Ljava/lang/String;
       4: areturn

  public java.lang.String toSystem(java.lang.Enum);
    Code:
       0: aload_0
       1: aload_1
       2: checkcast     #34                 // class org/hl7/fhir/dstu3/model/codesystems/V3PersonDisabilityType
       5: invokevirtual #35                 // Method toSystem:(Lorg/hl7/fhir/dstu3/model/codesystems/V3PersonDisabilityType;)Ljava/lang/String;
       8: areturn

  public java.lang.String toCode(java.lang.Enum);
    Code:
       0: aload_0
       1: aload_1
       2: checkcast     #34                 // class org/hl7/fhir/dstu3/model/codesystems/V3PersonDisabilityType
       5: invokevirtual #36                 // Method toCode:(Lorg/hl7/fhir/dstu3/model/codesystems/V3PersonDisabilityType;)Ljava/lang/String;
       8: areturn

  public java.lang.Enum fromCode(java.lang.String) throws java.lang.IllegalArgumentException;
    Code:
       0: aload_0
       1: aload_1
       2: invokevirtual #37                 // Method fromCode:(Ljava/lang/String;)Lorg/hl7/fhir/dstu3/model/codesystems/V3PersonDisabilityType;
       5: areturn
}
