Compiled from "ArtemisEmbeddedConfigurationFactory.java"
class org.springframework.boot.autoconfigure.jms.artemis.ArtemisEmbeddedConfigurationFactory {
  private static final org.apache.commons.logging.Log logger;

  private final org.springframework.boot.autoconfigure.jms.artemis.ArtemisProperties$Embedded properties;

  org.springframework.boot.autoconfigure.jms.artemis.ArtemisEmbeddedConfigurationFactory(org.springframework.boot.autoconfigure.jms.artemis.ArtemisProperties);
    Code:
       0: aload_0
       1: invokespecial #1                  // Method java/lang/Object."<init>":()V
       4: aload_0
       5: aload_1
       6: invokevirtual #2                  // Method org/springframework/boot/autoconfigure/jms/artemis/ArtemisProperties.getEmbedded:()Lorg/springframework/boot/autoconfigure/jms/artemis/ArtemisProperties$Embedded;
       9: putfield      #3                  // Field properties:Lorg/springframework/boot/autoconfigure/jms/artemis/ArtemisProperties$Embedded;
      12: return

  public org.apache.activemq.artemis.core.config.Configuration createConfiguration();
    Code:
       0: new           #4                  // class org/apache/activemq/artemis/core/config/impl/ConfigurationImpl
       3: dup
       4: invokespecial #5                  // Method org/apache/activemq/artemis/core/config/impl/ConfigurationImpl."<init>":()V
       7: astore_1
       8: aload_1
       9: iconst_0
      10: invokevirtual #6                  // Method org/apache/activemq/artemis/core/config/impl/ConfigurationImpl.setSecurityEnabled:(Z)Lorg/apache/activemq/artemis/core/config/impl/ConfigurationImpl;
      13: pop
      14: aload_1
      15: aload_0
      16: getfield      #3                  // Field properties:Lorg/springframework/boot/autoconfigure/jms/artemis/ArtemisProperties$Embedded;
      19: invokevirtual #7                  // Method org/springframework/boot/autoconfigure/jms/artemis/ArtemisProperties$Embedded.isPersistent:()Z
      22: invokevirtual #8                  // Method org/apache/activemq/artemis/core/config/impl/ConfigurationImpl.setPersistenceEnabled:(Z)Lorg/apache/activemq/artemis/core/config/impl/ConfigurationImpl;
      25: pop
      26: aload_0
      27: invokespecial #9                  // Method getDataDir:()Ljava/lang/String;
      30: astore_2
      31: aload_1
      32: new           #10                 // class java/lang/StringBuilder
      35: dup
      36: invokespecial #11                 // Method java/lang/StringBuilder."<init>":()V
      39: aload_2
      40: invokevirtual #12                 // Method java/lang/StringBuilder.append:(Ljava/lang/String;)Ljava/lang/StringBuilder;
      43: ldc           #13                 // String /journal
      45: invokevirtual #12                 // Method java/lang/StringBuilder.append:(Ljava/lang/String;)Ljava/lang/StringBuilder;
      48: invokevirtual #14                 // Method java/lang/StringBuilder.toString:()Ljava/lang/String;
      51: invokevirtual #15                 // Method org/apache/activemq/artemis/core/config/impl/ConfigurationImpl.setJournalDirectory:(Ljava/lang/String;)Lorg/apache/activemq/artemis/core/config/impl/ConfigurationImpl;
      54: pop
      55: aload_0
      56: getfield      #3                  // Field properties:Lorg/springframework/boot/autoconfigure/jms/artemis/ArtemisProperties$Embedded;
      59: invokevirtual #7                  // Method org/springframework/boot/autoconfigure/jms/artemis/ArtemisProperties$Embedded.isPersistent:()Z
      62: ifeq          145
      65: aload_1
      66: getstatic     #16                 // Field org/apache/activemq/artemis/core/server/JournalType.NIO:Lorg/apache/activemq/artemis/core/server/JournalType;
      69: invokevirtual #17                 // Method org/apache/activemq/artemis/core/config/impl/ConfigurationImpl.setJournalType:(Lorg/apache/activemq/artemis/core/server/JournalType;)Lorg/apache/activemq/artemis/core/config/impl/ConfigurationImpl;
      72: pop
      73: aload_1
      74: new           #10                 // class java/lang/StringBuilder
      77: dup
      78: invokespecial #11                 // Method java/lang/StringBuilder."<init>":()V
      81: aload_2
      82: invokevirtual #12                 // Method java/lang/StringBuilder.append:(Ljava/lang/String;)Ljava/lang/StringBuilder;
      85: ldc           #18                 // String /largemessages
      87: invokevirtual #12                 // Method java/lang/StringBuilder.append:(Ljava/lang/String;)Ljava/lang/StringBuilder;
      90: invokevirtual #14                 // Method java/lang/StringBuilder.toString:()Ljava/lang/String;
      93: invokevirtual #19                 // Method org/apache/activemq/artemis/core/config/impl/ConfigurationImpl.setLargeMessagesDirectory:(Ljava/lang/String;)Lorg/apache/activemq/artemis/core/config/impl/ConfigurationImpl;
      96: pop
      97: aload_1
      98: new           #10                 // class java/lang/StringBuilder
     101: dup
     102: invokespecial #11                 // Method java/lang/StringBuilder."<init>":()V
     105: aload_2
     106: invokevirtual #12                 // Method java/lang/StringBuilder.append:(Ljava/lang/String;)Ljava/lang/StringBuilder;
     109: ldc           #20                 // String /bindings
     111: invokevirtual #12                 // Method java/lang/StringBuilder.append:(Ljava/lang/String;)Ljava/lang/StringBuilder;
     114: invokevirtual #14                 // Method java/lang/StringBuilder.toString:()Ljava/lang/String;
     117: invokevirtual #21                 // Method org/apache/activemq/artemis/core/config/impl/ConfigurationImpl.setBindingsDirectory:(Ljava/lang/String;)Lorg/apache/activemq/artemis/core/config/impl/ConfigurationImpl;
     120: pop
     121: aload_1
     122: new           #10                 // class java/lang/StringBuilder
     125: dup
     126: invokespecial #11                 // Method java/lang/StringBuilder."<init>":()V
     129: aload_2
     130: invokevirtual #12                 // Method java/lang/StringBuilder.append:(Ljava/lang/String;)Ljava/lang/StringBuilder;
     133: ldc           #22                 // String /paging
     135: invokevirtual #12                 // Method java/lang/StringBuilder.append:(Ljava/lang/String;)Ljava/lang/StringBuilder;
     138: invokevirtual #14                 // Method java/lang/StringBuilder.toString:()Ljava/lang/String;
     141: invokevirtual #23                 // Method org/apache/activemq/artemis/core/config/impl/ConfigurationImpl.setPagingDirectory:(Ljava/lang/String;)Lorg/apache/activemq/artemis/core/config/impl/ConfigurationImpl;
     144: pop
     145: new           #24                 // class org/apache/activemq/artemis/api/core/TransportConfiguration
     148: dup
     149: ldc           #25                 // class org/apache/activemq/artemis/core/remoting/impl/invm/InVMAcceptorFactory
     151: invokevirtual #26                 // Method java/lang/Class.getName:()Ljava/lang/String;
     154: aload_0
     155: getfield      #3                  // Field properties:Lorg/springframework/boot/autoconfigure/jms/artemis/ArtemisProperties$Embedded;
     158: invokevirtual #27                 // Method org/springframework/boot/autoconfigure/jms/artemis/ArtemisProperties$Embedded.generateTransportParameters:()Ljava/util/Map;
     161: invokespecial #28                 // Method org/apache/activemq/artemis/api/core/TransportConfiguration."<init>":(Ljava/lang/String;Ljava/util/Map;)V
     164: astore_3
     165: aload_1
     166: invokevirtual #29                 // Method org/apache/activemq/artemis/core/config/impl/ConfigurationImpl.getAcceptorConfigurations:()Ljava/util/Set;
     169: aload_3
     170: invokeinterface #30,  2           // InterfaceMethod java/util/Set.add:(Ljava/lang/Object;)Z
     175: pop
     176: aload_0
     177: getfield      #3                  // Field properties:Lorg/springframework/boot/autoconfigure/jms/artemis/ArtemisProperties$Embedded;
     180: invokevirtual #31                 // Method org/springframework/boot/autoconfigure/jms/artemis/ArtemisProperties$Embedded.isDefaultClusterPassword:()Z
     183: ifeq          219
     186: getstatic     #32                 // Field logger:Lorg/apache/commons/logging/Log;
     189: new           #10                 // class java/lang/StringBuilder
     192: dup
     193: invokespecial #11                 // Method java/lang/StringBuilder."<init>":()V
     196: ldc           #33                 // String Using default Artemis cluster password:
     198: invokevirtual #12                 // Method java/lang/StringBuilder.append:(Ljava/lang/String;)Ljava/lang/StringBuilder;
     201: aload_0
     202: getfield      #3                  // Field properties:Lorg/springframework/boot/autoconfigure/jms/artemis/ArtemisProperties$Embedded;
     205: invokevirtual #34                 // Method org/springframework/boot/autoconfigure/jms/artemis/ArtemisProperties$Embedded.getClusterPassword:()Ljava/lang/String;
     208: invokevirtual #12                 // Method java/lang/StringBuilder.append:(Ljava/lang/String;)Ljava/lang/StringBuilder;
     211: invokevirtual #14                 // Method java/lang/StringBuilder.toString:()Ljava/lang/String;
     214: invokeinterface #35,  2           // InterfaceMethod org/apache/commons/logging/Log.debug:(Ljava/lang/Object;)V
     219: aload_1
     220: aload_0
     221: getfield      #3                  // Field properties:Lorg/springframework/boot/autoconfigure/jms/artemis/ArtemisProperties$Embedded;
     224: invokevirtual #34                 // Method org/springframework/boot/autoconfigure/jms/artemis/ArtemisProperties$Embedded.getClusterPassword:()Ljava/lang/String;
     227: invokevirtual #36                 // Method org/apache/activemq/artemis/core/config/impl/ConfigurationImpl.setClusterPassword:(Ljava/lang/String;)Lorg/apache/activemq/artemis/core/config/impl/ConfigurationImpl;
     230: pop
     231: aload_1
     232: areturn

  private java.lang.String getDataDir();
    Code:
       0: aload_0
       1: getfield      #3                  // Field properties:Lorg/springframework/boot/autoconfigure/jms/artemis/ArtemisProperties$Embedded;
       4: invokevirtual #37                 // Method org/springframework/boot/autoconfigure/jms/artemis/ArtemisProperties$Embedded.getDataDirectory:()Ljava/lang/String;
       7: ifnull        18
      10: aload_0
      11: getfield      #3                  // Field properties:Lorg/springframework/boot/autoconfigure/jms/artemis/ArtemisProperties$Embedded;
      14: invokevirtual #37                 // Method org/springframework/boot/autoconfigure/jms/artemis/ArtemisProperties$Embedded.getDataDirectory:()Ljava/lang/String;
      17: areturn
      18: ldc           #38                 // String java.io.tmpdir
      20: invokestatic  #39                 // Method java/lang/System.getProperty:(Ljava/lang/String;)Ljava/lang/String;
      23: astore_1
      24: new           #40                 // class java/io/File
      27: dup
      28: aload_1
      29: ldc           #41                 // String artemis-data
      31: invokespecial #42                 // Method java/io/File."<init>":(Ljava/lang/String;Ljava/lang/String;)V
      34: invokevirtual #43                 // Method java/io/File.getAbsolutePath:()Ljava/lang/String;
      37: areturn

  static {};
    Code:
       0: ldc           #44                 // class org/springframework/boot/autoconfigure/jms/artemis/ArtemisEmbeddedConfigurationFactory
       2: invokestatic  #45                 // Method org/apache/commons/logging/LogFactory.getLog:(Ljava/lang/Class;)Lorg/apache/commons/logging/Log;
       5: putstatic     #32                 // Field logger:Lorg/apache/commons/logging/Log;
       8: return
}
