Compiled from "DefaultMapper.java"
public class com.thoughtworks.xstream.mapper.DefaultMapper implements com.thoughtworks.xstream.mapper.Mapper {
  private static java.lang.String XSTREAM_PACKAGE_ROOT;

  private final java.lang.ClassLoader classLoader;

  public com.thoughtworks.xstream.mapper.DefaultMapper(java.lang.ClassLoader);
    Code:
       0: aload_0
       1: invokespecial #1                  // Method java/lang/Object."<init>":()V
       4: aload_0
       5: aload_1
       6: putfield      #2                  // Field classLoader:Ljava/lang/ClassLoader;
       9: return

  public java.lang.String serializedClass(java.lang.Class);
    Code:
       0: aload_1
       1: invokevirtual #3                  // Method java/lang/Class.getName:()Ljava/lang/String;
       4: areturn

  public java.lang.Class realClass(java.lang.String);
    Code:
       0: aload_1
       1: getstatic     #4                  // Field XSTREAM_PACKAGE_ROOT:Ljava/lang/String;
       4: invokevirtual #5                  // Method java/lang/String.startsWith:(Ljava/lang/String;)Z
       7: ifeq          21
      10: ldc_w         #6                  // class com/thoughtworks/xstream/mapper/DefaultMapper
      13: invokevirtual #7                  // Method java/lang/Class.getClassLoader:()Ljava/lang/ClassLoader;
      16: aload_1
      17: invokevirtual #8                  // Method java/lang/ClassLoader.loadClass:(Ljava/lang/String;)Ljava/lang/Class;
      20: areturn
      21: aload_1
      22: iconst_0
      23: invokevirtual #9                  // Method java/lang/String.charAt:(I)C
      26: bipush        91
      28: if_icmpeq     40
      31: aload_0
      32: getfield      #2                  // Field classLoader:Ljava/lang/ClassLoader;
      35: aload_1
      36: invokevirtual #8                  // Method java/lang/ClassLoader.loadClass:(Ljava/lang/String;)Ljava/lang/Class;
      39: areturn
      40: aload_1
      41: ldc           #10                 // String ;
      43: invokevirtual #11                 // Method java/lang/String.endsWith:(Ljava/lang/String;)Z
      46: ifeq          62
      49: aload_1
      50: invokevirtual #12                 // Method java/lang/String.toString:()Ljava/lang/String;
      53: iconst_0
      54: aload_0
      55: getfield      #2                  // Field classLoader:Ljava/lang/ClassLoader;
      58: invokestatic  #13                 // Method java/lang/Class.forName:(Ljava/lang/String;ZLjava/lang/ClassLoader;)Ljava/lang/Class;
      61: areturn
      62: aload_1
      63: invokevirtual #12                 // Method java/lang/String.toString:()Ljava/lang/String;
      66: invokestatic  #14                 // Method java/lang/Class.forName:(Ljava/lang/String;)Ljava/lang/Class;
      69: areturn
      70: astore_2
      71: new           #16                 // class com/thoughtworks/xstream/mapper/CannotResolveClassException
      74: dup
      75: aload_1
      76: invokespecial #17                 // Method com/thoughtworks/xstream/mapper/CannotResolveClassException."<init>":(Ljava/lang/String;)V
      79: athrow
    Exception table:
       from    to  target type
           0    20    70   Class java/lang/ClassNotFoundException
          21    39    70   Class java/lang/ClassNotFoundException
          40    61    70   Class java/lang/ClassNotFoundException
          62    69    70   Class java/lang/ClassNotFoundException

  public java.lang.Class defaultImplementationOf(java.lang.Class);
    Code:
       0: aload_1
       1: areturn

  public java.lang.String aliasForAttribute(java.lang.String);
    Code:
       0: aload_1
       1: areturn

  public java.lang.String attributeForAlias(java.lang.String);
    Code:
       0: aload_1
       1: areturn

  public java.lang.String aliasForSystemAttribute(java.lang.String);
    Code:
       0: aload_1
       1: areturn

  public boolean isImmutableValueType(java.lang.Class);
    Code:
       0: iconst_0
       1: ireturn

  public java.lang.String getFieldNameForItemTypeAndName(java.lang.Class, java.lang.Class, java.lang.String);
    Code:
       0: aconst_null
       1: areturn

  public java.lang.Class getItemTypeForItemFieldName(java.lang.Class, java.lang.String);
    Code:
       0: aconst_null
       1: areturn

  public com.thoughtworks.xstream.mapper.Mapper$ImplicitCollectionMapping getImplicitCollectionDefForFieldName(java.lang.Class, java.lang.String);
    Code:
       0: aconst_null
       1: areturn

  public boolean shouldSerializeMember(java.lang.Class, java.lang.String);
    Code:
       0: iconst_1
       1: ireturn

  public java.lang.String lookupName(java.lang.Class);
    Code:
       0: aload_0
       1: aload_1
       2: invokevirtual #18                 // Method serializedClass:(Ljava/lang/Class;)Ljava/lang/String;
       5: areturn

  public java.lang.Class lookupType(java.lang.String);
    Code:
       0: aload_0
       1: aload_1
       2: invokevirtual #19                 // Method realClass:(Ljava/lang/String;)Ljava/lang/Class;
       5: areturn

  public java.lang.String serializedMember(java.lang.Class, java.lang.String);
    Code:
       0: aload_2
       1: areturn

  public java.lang.String realMember(java.lang.Class, java.lang.String);
    Code:
       0: aload_2
       1: areturn

  public com.thoughtworks.xstream.converters.SingleValueConverter getConverterFromAttribute(java.lang.String);
    Code:
       0: aconst_null
       1: areturn

  public com.thoughtworks.xstream.converters.SingleValueConverter getConverterFromItemType(java.lang.String, java.lang.Class);
    Code:
       0: aconst_null
       1: areturn

  public com.thoughtworks.xstream.converters.SingleValueConverter getConverterFromItemType(java.lang.Class);
    Code:
       0: aconst_null
       1: areturn

  public com.thoughtworks.xstream.converters.SingleValueConverter getConverterFromItemType(java.lang.String, java.lang.Class, java.lang.Class);
    Code:
       0: aconst_null
       1: areturn

  public com.thoughtworks.xstream.converters.Converter getLocalConverter(java.lang.Class, java.lang.String);
    Code:
       0: aconst_null
       1: areturn

  public com.thoughtworks.xstream.mapper.Mapper lookupMapperOfType(java.lang.Class);
    Code:
       0: aconst_null
       1: areturn

  public java.lang.String aliasForAttribute(java.lang.Class, java.lang.String);
    Code:
       0: aload_2
       1: areturn

  public java.lang.String attributeForAlias(java.lang.Class, java.lang.String);
    Code:
       0: aload_2
       1: areturn

  public com.thoughtworks.xstream.converters.SingleValueConverter getConverterFromAttribute(java.lang.Class, java.lang.String);
    Code:
       0: aconst_null
       1: areturn

  public com.thoughtworks.xstream.converters.SingleValueConverter getConverterFromAttribute(java.lang.Class, java.lang.String, java.lang.Class);
    Code:
       0: aconst_null
       1: areturn

  static {};
    Code:
       0: ldc_w         #6                  // class com/thoughtworks/xstream/mapper/DefaultMapper
       3: invokevirtual #3                  // Method java/lang/Class.getName:()Ljava/lang/String;
       6: astore_0
       7: aload_0
       8: ldc           #20                 // String .xstream.
      10: invokevirtual #21                 // Method java/lang/String.indexOf:(Ljava/lang/String;)I
      13: istore_1
      14: iload_1
      15: ifle          30
      18: aload_0
      19: iconst_0
      20: iload_1
      21: bipush        9
      23: iadd
      24: invokevirtual #22                 // Method java/lang/String.substring:(II)Ljava/lang/String;
      27: goto          31
      30: aconst_null
      31: putstatic     #4                  // Field XSTREAM_PACKAGE_ROOT:Ljava/lang/String;
      34: return
}
