Compiled from "action.kt"
final class net.mamoe.mirai.api.http.adapter.reverse.ReverseAuthDTO {
  public static final net.mamoe.mirai.api.http.adapter.reverse.ReverseAuthDTO$Companion Companion;

  private final java.lang.String verifyKey;

  private final java.lang.String sessionKey;

  private final java.lang.Long qq;

  public net.mamoe.mirai.api.http.adapter.reverse.ReverseAuthDTO(java.lang.String, java.lang.String, java.lang.Long);
    Code:
       0: aload_0
       1: invokespecial #10                 // Method java/lang/Object."<init>":()V
       4: aload_0
       5: aload_1
       6: putfield      #14                 // Field verifyKey:Ljava/lang/String;
       9: aload_0
      10: aload_2
      11: putfield      #17                 // Field sessionKey:Ljava/lang/String;
      14: aload_0
      15: aload_3
      16: putfield      #21                 // Field qq:Ljava/lang/Long;
      19: return

  public final java.lang.String getVerifyKey();
    Code:
       0: aload_0
       1: getfield      #14                 // Field verifyKey:Ljava/lang/String;
       4: areturn

  public final java.lang.String getSessionKey();
    Code:
       0: aload_0
       1: getfield      #17                 // Field sessionKey:Ljava/lang/String;
       4: areturn

  public final java.lang.Long getQq();
    Code:
       0: aload_0
       1: getfield      #21                 // Field qq:Ljava/lang/Long;
       4: areturn

  public final java.lang.String component1();
    Code:
       0: aload_0
       1: getfield      #14                 // Field verifyKey:Ljava/lang/String;
       4: areturn

  public final java.lang.String component2();
    Code:
       0: aload_0
       1: getfield      #17                 // Field sessionKey:Ljava/lang/String;
       4: areturn

  public final java.lang.Long component3();
    Code:
       0: aload_0
       1: getfield      #21                 // Field qq:Ljava/lang/Long;
       4: areturn

  public final net.mamoe.mirai.api.http.adapter.reverse.ReverseAuthDTO copy(java.lang.String, java.lang.String, java.lang.Long);
    Code:
       0: new           #2                  // class net/mamoe/mirai/api/http/adapter/reverse/ReverseAuthDTO
       3: dup
       4: aload_1
       5: aload_2
       6: aload_3
       7: invokespecial #36                 // Method "<init>":(Ljava/lang/String;Ljava/lang/String;Ljava/lang/Long;)V
      10: areturn

  public static net.mamoe.mirai.api.http.adapter.reverse.ReverseAuthDTO copy$default(net.mamoe.mirai.api.http.adapter.reverse.ReverseAuthDTO, java.lang.String, java.lang.String, java.lang.Long, int, java.lang.Object);
    Code:
       0: iload         4
       2: iconst_1
       3: iand
       4: ifeq          12
       7: aload_0
       8: getfield      #14                 // Field verifyKey:Ljava/lang/String;
      11: astore_1
      12: iload         4
      14: iconst_2
      15: iand
      16: ifeq          24
      19: aload_0
      20: getfield      #17                 // Field sessionKey:Ljava/lang/String;
      23: astore_2
      24: iload         4
      26: iconst_4
      27: iand
      28: ifeq          36
      31: aload_0
      32: getfield      #21                 // Field qq:Ljava/lang/Long;
      35: astore_3
      36: aload_0
      37: aload_1
      38: aload_2
      39: aload_3
      40: invokevirtual #40                 // Method copy:(Ljava/lang/String;Ljava/lang/String;Ljava/lang/Long;)Lnet/mamoe/mirai/api/http/adapter/reverse/ReverseAuthDTO;
      43: areturn

  public java.lang.String toString();
    Code:
       0: new           #43                 // class java/lang/StringBuilder
       3: dup
       4: invokespecial #44                 // Method java/lang/StringBuilder."<init>":()V
       7: ldc           #46                 // String ReverseAuthDTO(verifyKey=
       9: invokevirtual #50                 // Method java/lang/StringBuilder.append:(Ljava/lang/String;)Ljava/lang/StringBuilder;
      12: aload_0
      13: getfield      #14                 // Field verifyKey:Ljava/lang/String;
      16: invokevirtual #53                 // Method java/lang/StringBuilder.append:(Ljava/lang/Object;)Ljava/lang/StringBuilder;
      19: ldc           #55                 // String , sessionKey=
      21: invokevirtual #50                 // Method java/lang/StringBuilder.append:(Ljava/lang/String;)Ljava/lang/StringBuilder;
      24: aload_0
      25: getfield      #17                 // Field sessionKey:Ljava/lang/String;
      28: invokevirtual #53                 // Method java/lang/StringBuilder.append:(Ljava/lang/Object;)Ljava/lang/StringBuilder;
      31: ldc           #57                 // String , qq=
      33: invokevirtual #50                 // Method java/lang/StringBuilder.append:(Ljava/lang/String;)Ljava/lang/StringBuilder;
      36: aload_0
      37: getfield      #21                 // Field qq:Ljava/lang/Long;
      40: invokevirtual #53                 // Method java/lang/StringBuilder.append:(Ljava/lang/Object;)Ljava/lang/StringBuilder;
      43: bipush        41
      45: invokevirtual #60                 // Method java/lang/StringBuilder.append:(C)Ljava/lang/StringBuilder;
      48: invokevirtual #62                 // Method java/lang/StringBuilder.toString:()Ljava/lang/String;
      51: areturn

  public int hashCode();
    Code:
       0: aload_0
       1: getfield      #14                 // Field verifyKey:Ljava/lang/String;
       4: ifnonnull     11
       7: iconst_0
       8: goto          18
      11: aload_0
      12: getfield      #14                 // Field verifyKey:Ljava/lang/String;
      15: invokevirtual #68                 // Method java/lang/String.hashCode:()I
      18: istore_1
      19: iload_1
      20: bipush        31
      22: imul
      23: aload_0
      24: getfield      #17                 // Field sessionKey:Ljava/lang/String;
      27: ifnonnull     34
      30: iconst_0
      31: goto          41
      34: aload_0
      35: getfield      #17                 // Field sessionKey:Ljava/lang/String;
      38: invokevirtual #68                 // Method java/lang/String.hashCode:()I
      41: iadd
      42: istore_1
      43: iload_1
      44: bipush        31
      46: imul
      47: aload_0
      48: getfield      #21                 // Field qq:Ljava/lang/Long;
      51: ifnonnull     58
      54: iconst_0
      55: goto          65
      58: aload_0
      59: getfield      #21                 // Field qq:Ljava/lang/Long;
      62: invokevirtual #69                 // Method java/lang/Object.hashCode:()I
      65: iadd
      66: istore_1
      67: iload_1
      68: ireturn

  public boolean equals(java.lang.Object);
    Code:
       0: aload_0
       1: aload_1
       2: if_acmpne     7
       5: iconst_1
       6: ireturn
       7: aload_1
       8: instanceof    #2                  // class net/mamoe/mirai/api/http/adapter/reverse/ReverseAuthDTO
      11: ifne          16
      14: iconst_0
      15: ireturn
      16: aload_1
      17: checkcast     #2                  // class net/mamoe/mirai/api/http/adapter/reverse/ReverseAuthDTO
      20: astore_2
      21: aload_0
      22: getfield      #14                 // Field verifyKey:Ljava/lang/String;
      25: aload_2
      26: getfield      #14                 // Field verifyKey:Ljava/lang/String;
      29: invokestatic  #79                 // Method kotlin/jvm/internal/Intrinsics.areEqual:(Ljava/lang/Object;Ljava/lang/Object;)Z
      32: ifne          37
      35: iconst_0
      36: ireturn
      37: aload_0
      38: getfield      #17                 // Field sessionKey:Ljava/lang/String;
      41: aload_2
      42: getfield      #17                 // Field sessionKey:Ljava/lang/String;
      45: invokestatic  #79                 // Method kotlin/jvm/internal/Intrinsics.areEqual:(Ljava/lang/Object;Ljava/lang/Object;)Z
      48: ifne          53
      51: iconst_0
      52: ireturn
      53: aload_0
      54: getfield      #21                 // Field qq:Ljava/lang/Long;
      57: aload_2
      58: getfield      #21                 // Field qq:Ljava/lang/Long;
      61: invokestatic  #79                 // Method kotlin/jvm/internal/Intrinsics.areEqual:(Ljava/lang/Object;Ljava/lang/Object;)Z
      64: ifne          69
      67: iconst_0
      68: ireturn
      69: iconst_1
      70: ireturn

  public static final void write$Self(net.mamoe.mirai.api.http.adapter.reverse.ReverseAuthDTO, kotlinx.serialization.encoding.CompositeEncoder, kotlinx.serialization.descriptors.SerialDescriptor);
    Code:
       0: aload_0
       1: ldc           #86                 // String self
       3: invokestatic  #90                 // Method kotlin/jvm/internal/Intrinsics.checkNotNullParameter:(Ljava/lang/Object;Ljava/lang/String;)V
       6: aload_1
       7: ldc           #92                 // String output
       9: invokestatic  #90                 // Method kotlin/jvm/internal/Intrinsics.checkNotNullParameter:(Ljava/lang/Object;Ljava/lang/String;)V
      12: aload_2
      13: ldc           #94                 // String serialDesc
      15: invokestatic  #90                 // Method kotlin/jvm/internal/Intrinsics.checkNotNullParameter:(Ljava/lang/Object;Ljava/lang/String;)V
      18: aload_1
      19: aload_2
      20: iconst_0
      21: getstatic     #100                // Field kotlinx/serialization/internal/StringSerializer.INSTANCE:Lkotlinx/serialization/internal/StringSerializer;
      24: checkcast     #102                // class kotlinx/serialization/SerializationStrategy
      27: aload_0
      28: getfield      #14                 // Field verifyKey:Ljava/lang/String;
      31: invokeinterface #108,  5          // InterfaceMethod kotlinx/serialization/encoding/CompositeEncoder.encodeNullableSerializableElement:(Lkotlinx/serialization/descriptors/SerialDescriptor;ILkotlinx/serialization/SerializationStrategy;Ljava/lang/Object;)V
      36: aload_1
      37: aload_2
      38: iconst_1
      39: getstatic     #100                // Field kotlinx/serialization/internal/StringSerializer.INSTANCE:Lkotlinx/serialization/internal/StringSerializer;
      42: checkcast     #102                // class kotlinx/serialization/SerializationStrategy
      45: aload_0
      46: getfield      #17                 // Field sessionKey:Ljava/lang/String;
      49: invokeinterface #108,  5          // InterfaceMethod kotlinx/serialization/encoding/CompositeEncoder.encodeNullableSerializableElement:(Lkotlinx/serialization/descriptors/SerialDescriptor;ILkotlinx/serialization/SerializationStrategy;Ljava/lang/Object;)V
      54: aload_1
      55: aload_2
      56: iconst_2
      57: getstatic     #113                // Field kotlinx/serialization/internal/LongSerializer.INSTANCE:Lkotlinx/serialization/internal/LongSerializer;
      60: checkcast     #102                // class kotlinx/serialization/SerializationStrategy
      63: aload_0
      64: getfield      #21                 // Field qq:Ljava/lang/Long;
      67: invokeinterface #108,  5          // InterfaceMethod kotlinx/serialization/encoding/CompositeEncoder.encodeNullableSerializableElement:(Lkotlinx/serialization/descriptors/SerialDescriptor;ILkotlinx/serialization/SerializationStrategy;Ljava/lang/Object;)V
      72: return

  public net.mamoe.mirai.api.http.adapter.reverse.ReverseAuthDTO(int, java.lang.String, java.lang.String, java.lang.Long, kotlinx.serialization.internal.SerializationConstructorMarker);
    Code:
       0: bipush        7
       2: bipush        7
       4: iload_1
       5: iand
       6: if_icmpeq     21
       9: iload_1
      10: bipush        7
      12: getstatic     #132                // Field net/mamoe/mirai/api/http/adapter/reverse/ReverseAuthDTO$$serializer.INSTANCE:Lnet/mamoe/mirai/api/http/adapter/reverse/ReverseAuthDTO$$serializer;
      15: invokevirtual #136                // Method net/mamoe/mirai/api/http/adapter/reverse/ReverseAuthDTO$$serializer.getDescriptor:()Lkotlinx/serialization/descriptors/SerialDescriptor;
      18: invokestatic  #142                // Method kotlinx/serialization/internal/PluginExceptionsKt.throwMissingFieldException:(IILkotlinx/serialization/descriptors/SerialDescriptor;)V
      21: aload_0
      22: invokespecial #10                 // Method java/lang/Object."<init>":()V
      25: aload_0
      26: aload_2
      27: putfield      #14                 // Field verifyKey:Ljava/lang/String;
      30: aload_0
      31: aload_3
      32: putfield      #17                 // Field sessionKey:Ljava/lang/String;
      35: aload_0
      36: aload         4
      38: putfield      #21                 // Field qq:Ljava/lang/Long;
      41: return

  static {};
    Code:
       0: new           #148                // class net/mamoe/mirai/api/http/adapter/reverse/ReverseAuthDTO$Companion
       3: dup
       4: aconst_null
       5: invokespecial #151                // Method net/mamoe/mirai/api/http/adapter/reverse/ReverseAuthDTO$Companion."<init>":(Lkotlin/jvm/internal/DefaultConstructorMarker;)V
       8: putstatic     #155                // Field Companion:Lnet/mamoe/mirai/api/http/adapter/reverse/ReverseAuthDTO$Companion;
      11: return
}
