Compiled from "AbstractNettyHandler.java"
final class io.grpc.netty.AbstractNettyHandler$AllowPingLimiter implements io.grpc.netty.AbstractNettyHandler$PingLimiter {
  private io.grpc.netty.AbstractNettyHandler$AllowPingLimiter();
    Code:
       0: aload_0
       1: invokespecial #2                  // Method java/lang/Object."<init>":()V
       4: return

  public boolean isPingAllowed();
    Code:
       0: iconst_1
       1: ireturn

  io.grpc.netty.AbstractNettyHandler$AllowPingLimiter(io.grpc.netty.AbstractNettyHandler$1);
    Code:
       0: aload_0
       1: invokespecial #1                  // Method "<init>":()V
       4: return
}
