Compiled from "FixedTrustManagerFactory.java"
final class io.grpc.netty.FixedTrustManagerFactory extends javax.net.ssl.TrustManagerFactory {
  public io.grpc.netty.FixedTrustManagerFactory(java.util.List<javax.net.ssl.TrustManager>);
    Code:
       0: aload_0
       1: new           #1                  // class io/grpc/netty/FixedTrustManagerFactory$FixedTrustManagerFactorySpi
       4: dup
       5: aload_1
       6: invokespecial #2                  // Method io/grpc/netty/FixedTrustManagerFactory$FixedTrustManagerFactorySpi."<init>":(Ljava/util/List;)V
       9: new           #3                  // class io/grpc/netty/UnhelpfulSecurityProvider
      12: dup
      13: invokespecial #4                  // Method io/grpc/netty/UnhelpfulSecurityProvider."<init>":()V
      16: ldc           #5                  // String FakeAlgorithm
      18: invokespecial #6                  // Method javax/net/ssl/TrustManagerFactory."<init>":(Ljavax/net/ssl/TrustManagerFactorySpi;Ljava/security/Provider;Ljava/lang/String;)V
      21: return
}
