Compiled from "GrpcHttp2OutboundHeaders.java"
class io.grpc.netty.GrpcHttp2OutboundHeaders$Itr implements java.util.Map$Entry<java.lang.CharSequence, java.lang.CharSequence>, java.util.Iterator<java.util.Map$Entry<java.lang.CharSequence, java.lang.CharSequence>> {
  private int idx;

  private io.netty.util.AsciiString[] current;

  private io.netty.util.AsciiString key;

  private io.netty.util.AsciiString value;

  final io.grpc.netty.GrpcHttp2OutboundHeaders this$0;

  private io.grpc.netty.GrpcHttp2OutboundHeaders$Itr(io.grpc.netty.GrpcHttp2OutboundHeaders);
    Code:
       0: aload_0
       1: aload_1
       2: putfield      #2                  // Field this$0:Lio/grpc/netty/GrpcHttp2OutboundHeaders;
       5: aload_0
       6: invokespecial #3                  // Method java/lang/Object."<init>":()V
       9: aload_0
      10: aload_0
      11: getfield      #2                  // Field this$0:Lio/grpc/netty/GrpcHttp2OutboundHeaders;
      14: invokestatic  #4                  // Method io/grpc/netty/GrpcHttp2OutboundHeaders.access$100:(Lio/grpc/netty/GrpcHttp2OutboundHeaders;)[Lio/netty/util/AsciiString;
      17: arraylength
      18: ifeq          31
      21: aload_0
      22: getfield      #2                  // Field this$0:Lio/grpc/netty/GrpcHttp2OutboundHeaders;
      25: invokestatic  #4                  // Method io/grpc/netty/GrpcHttp2OutboundHeaders.access$100:(Lio/grpc/netty/GrpcHttp2OutboundHeaders;)[Lio/netty/util/AsciiString;
      28: goto          38
      31: aload_0
      32: getfield      #2                  // Field this$0:Lio/grpc/netty/GrpcHttp2OutboundHeaders;
      35: invokestatic  #5                  // Method io/grpc/netty/GrpcHttp2OutboundHeaders.access$200:(Lio/grpc/netty/GrpcHttp2OutboundHeaders;)[Lio/netty/util/AsciiString;
      38: putfield      #6                  // Field current:[Lio/netty/util/AsciiString;
      41: return

  public boolean hasNext();
    Code:
       0: aload_0
       1: getfield      #7                  // Field idx:I
       4: aload_0
       5: getfield      #6                  // Field current:[Lio/netty/util/AsciiString;
       8: arraylength
       9: if_icmpge     16
      12: iconst_1
      13: goto          17
      16: iconst_0
      17: ireturn

  public java.util.Map$Entry<java.lang.CharSequence, java.lang.CharSequence> next();
    Code:
       0: aload_0
       1: invokevirtual #8                  // Method hasNext:()Z
       4: ifeq          89
       7: aload_0
       8: aload_0
       9: getfield      #6                  // Field current:[Lio/netty/util/AsciiString;
      12: aload_0
      13: getfield      #7                  // Field idx:I
      16: aaload
      17: putfield      #9                  // Field key:Lio/netty/util/AsciiString;
      20: aload_0
      21: aload_0
      22: getfield      #6                  // Field current:[Lio/netty/util/AsciiString;
      25: aload_0
      26: getfield      #7                  // Field idx:I
      29: iconst_1
      30: iadd
      31: aaload
      32: putfield      #10                 // Field value:Lio/netty/util/AsciiString;
      35: aload_0
      36: dup
      37: getfield      #7                  // Field idx:I
      40: iconst_2
      41: iadd
      42: putfield      #7                  // Field idx:I
      45: aload_0
      46: getfield      #7                  // Field idx:I
      49: aload_0
      50: getfield      #6                  // Field current:[Lio/netty/util/AsciiString;
      53: arraylength
      54: if_icmplt     87
      57: aload_0
      58: getfield      #6                  // Field current:[Lio/netty/util/AsciiString;
      61: aload_0
      62: getfield      #2                  // Field this$0:Lio/grpc/netty/GrpcHttp2OutboundHeaders;
      65: invokestatic  #4                  // Method io/grpc/netty/GrpcHttp2OutboundHeaders.access$100:(Lio/grpc/netty/GrpcHttp2OutboundHeaders;)[Lio/netty/util/AsciiString;
      68: if_acmpne     87
      71: aload_0
      72: aload_0
      73: getfield      #2                  // Field this$0:Lio/grpc/netty/GrpcHttp2OutboundHeaders;
      76: invokestatic  #5                  // Method io/grpc/netty/GrpcHttp2OutboundHeaders.access$200:(Lio/grpc/netty/GrpcHttp2OutboundHeaders;)[Lio/netty/util/AsciiString;
      79: putfield      #6                  // Field current:[Lio/netty/util/AsciiString;
      82: aload_0
      83: iconst_0
      84: putfield      #7                  // Field idx:I
      87: aload_0
      88: areturn
      89: new           #11                 // class java/util/NoSuchElementException
      92: dup
      93: invokespecial #12                 // Method java/util/NoSuchElementException."<init>":()V
      96: athrow

  public java.lang.CharSequence getKey();
    Code:
       0: aload_0
       1: getfield      #9                  // Field key:Lio/netty/util/AsciiString;
       4: areturn

  public java.lang.CharSequence getValue();
    Code:
       0: aload_0
       1: getfield      #10                 // Field value:Lio/netty/util/AsciiString;
       4: areturn

  public java.lang.CharSequence setValue(java.lang.CharSequence);
    Code:
       0: new           #13                 // class java/lang/UnsupportedOperationException
       3: dup
       4: invokespecial #14                 // Method java/lang/UnsupportedOperationException."<init>":()V
       7: athrow

  public void remove();
    Code:
       0: new           #13                 // class java/lang/UnsupportedOperationException
       3: dup
       4: invokespecial #14                 // Method java/lang/UnsupportedOperationException."<init>":()V
       7: athrow

  public java.lang.Object setValue(java.lang.Object);
    Code:
       0: aload_0
       1: aload_1
       2: checkcast     #15                 // class java/lang/CharSequence
       5: invokevirtual #16                 // Method setValue:(Ljava/lang/CharSequence;)Ljava/lang/CharSequence;
       8: areturn

  public java.lang.Object getValue();
    Code:
       0: aload_0
       1: invokevirtual #17                 // Method getValue:()Ljava/lang/CharSequence;
       4: areturn

  public java.lang.Object getKey();
    Code:
       0: aload_0
       1: invokevirtual #18                 // Method getKey:()Ljava/lang/CharSequence;
       4: areturn

  public java.lang.Object next();
    Code:
       0: aload_0
       1: invokevirtual #19                 // Method next:()Ljava/util/Map$Entry;
       4: areturn

  io.grpc.netty.GrpcHttp2OutboundHeaders$Itr(io.grpc.netty.GrpcHttp2OutboundHeaders, io.grpc.netty.GrpcHttp2OutboundHeaders$1);
    Code:
       0: aload_0
       1: aload_1
       2: invokespecial #1                  // Method "<init>":(Lio/grpc/netty/GrpcHttp2OutboundHeaders;)V
       5: return
}
