Compiled from "NettyServerHandler.java"
class io.grpc.netty.NettyServerHandler$4 implements io.netty.handler.codec.http2.Http2StreamVisitor {
  final io.grpc.Status val$status;

  final io.grpc.netty.NettyServerHandler this$0;

  io.grpc.netty.NettyServerHandler$4(io.grpc.netty.NettyServerHandler, io.grpc.Status);
    Code:
       0: aload_0
       1: aload_1
       2: putfield      #1                  // Field this$0:Lio/grpc/netty/NettyServerHandler;
       5: aload_0
       6: aload_2
       7: putfield      #2                  // Field val$status:Lio/grpc/Status;
      10: aload_0
      11: invokespecial #3                  // Method java/lang/Object."<init>":()V
      14: return

  public boolean visit(io.netty.handler.codec.http2.Http2Stream) throws io.netty.handler.codec.http2.Http2Exception;
    Code:
       0: aload_0
       1: getfield      #1                  // Field this$0:Lio/grpc/netty/NettyServerHandler;
       4: aload_1
       5: invokestatic  #4                  // Method io/grpc/netty/NettyServerHandler.access$400:(Lio/grpc/netty/NettyServerHandler;Lio/netty/handler/codec/http2/Http2Stream;)Lio/grpc/netty/NettyServerStream$TransportState;
       8: astore_2
       9: aload_2
      10: ifnull        21
      13: aload_2
      14: aload_0
      15: getfield      #2                  // Field val$status:Lio/grpc/Status;
      18: invokevirtual #5                  // Method io/grpc/netty/NettyServerStream$TransportState.transportReportStatus:(Lio/grpc/Status;)V
      21: iconst_1
      22: ireturn
}
