Compiled from "NettyClientHandler.java"
class io.grpc.netty.NettyClientHandler$1 extends io.grpc.internal.InUseStateAggregator<io.netty.handler.codec.http2.Http2Stream> {
  final io.grpc.netty.NettyClientHandler this$0;

  io.grpc.netty.NettyClientHandler$1(io.grpc.netty.NettyClientHandler);
    Code:
       0: aload_0
       1: aload_1
       2: putfield      #1                  // Field this$0:Lio/grpc/netty/NettyClientHandler;
       5: aload_0
       6: invokespecial #2                  // Method io/grpc/internal/InUseStateAggregator."<init>":()V
       9: return

  protected void handleInUse();
    Code:
       0: aload_0
       1: getfield      #1                  // Field this$0:Lio/grpc/netty/NettyClientHandler;
       4: invokestatic  #3                  // Method io/grpc/netty/NettyClientHandler.access$000:(Lio/grpc/netty/NettyClientHandler;)Lio/grpc/netty/ClientTransportLifecycleManager;
       7: iconst_1
       8: invokevirtual #4                  // Method io/grpc/netty/ClientTransportLifecycleManager.notifyInUse:(Z)V
      11: return

  protected void handleNotInUse();
    Code:
       0: aload_0
       1: getfield      #1                  // Field this$0:Lio/grpc/netty/NettyClientHandler;
       4: invokestatic  #3                  // Method io/grpc/netty/NettyClientHandler.access$000:(Lio/grpc/netty/NettyClientHandler;)Lio/grpc/netty/ClientTransportLifecycleManager;
       7: iconst_0
       8: invokevirtual #4                  // Method io/grpc/netty/ClientTransportLifecycleManager.notifyInUse:(Z)V
      11: return
}
