Compiled from "NettyServerTransport.java"
final class io.grpc.netty.NettyServerTransport$1TerminationNotifier implements io.netty.channel.ChannelFutureListener {
  boolean done;

  final io.grpc.netty.NettyServerTransport this$0;

  io.grpc.netty.NettyServerTransport$1TerminationNotifier(io.grpc.netty.NettyServerTransport);
    Code:
       0: aload_0
       1: aload_1
       2: putfield      #1                  // Field this$0:Lio/grpc/netty/NettyServerTransport;
       5: aload_0
       6: invokespecial #2                  // Method java/lang/Object."<init>":()V
       9: return

  public void operationComplete(io.netty.channel.ChannelFuture) throws java.lang.Exception;
    Code:
       0: aload_0
       1: getfield      #3                  // Field done:Z
       4: ifne          29
       7: aload_0
       8: iconst_1
       9: putfield      #3                  // Field done:Z
      12: aload_0
      13: getfield      #1                  // Field this$0:Lio/grpc/netty/NettyServerTransport;
      16: aload_0
      17: getfield      #1                  // Field this$0:Lio/grpc/netty/NettyServerTransport;
      20: invokestatic  #4                  // Method io/grpc/netty/NettyServerTransport.access$000:(Lio/grpc/netty/NettyServerTransport;)Lio/grpc/netty/NettyServerHandler;
      23: invokevirtual #5                  // Method io/grpc/netty/NettyServerHandler.connectionError:()Ljava/lang/Throwable;
      26: invokestatic  #6                  // Method io/grpc/netty/NettyServerTransport.access$100:(Lio/grpc/netty/NettyServerTransport;Ljava/lang/Throwable;)V
      29: return

  public void operationComplete(io.netty.util.concurrent.Future) throws java.lang.Exception;
    Code:
       0: aload_0
       1: aload_1
       2: checkcast     #7                  // class io/netty/channel/ChannelFuture
       5: invokevirtual #8                  // Method operationComplete:(Lio/netty/channel/ChannelFuture;)V
       8: return
}
