Compiled from "WriteQueue.java"
class io.grpc.netty.WriteQueue$1 implements java.lang.Runnable {
  final io.grpc.netty.WriteQueue this$0;

  io.grpc.netty.WriteQueue$1(io.grpc.netty.WriteQueue);
    Code:
       0: aload_0
       1: aload_1
       2: putfield      #1                  // Field this$0:Lio/grpc/netty/WriteQueue;
       5: aload_0
       6: invokespecial #2                  // Method java/lang/Object."<init>":()V
       9: return

  public void run();
    Code:
       0: aload_0
       1: getfield      #1                  // Field this$0:Lio/grpc/netty/WriteQueue;
       4: invokestatic  #3                  // Method io/grpc/netty/WriteQueue.access$000:(Lio/grpc/netty/WriteQueue;)V
       7: return
}
