Compiled from "JMSConnectionFactoryDefinitionDescriptorProcessor.java"
public class org.wildfly.extension.messaging.activemq.deployment.JMSConnectionFactoryDefinitionDescriptorProcessor extends org.jboss.as.ee.resource.definition.ResourceDefinitionDescriptorProcessor {
  public org.wildfly.extension.messaging.activemq.deployment.JMSConnectionFactoryDefinitionDescriptorProcessor();
    Code:
       0: aload_0
       1: invokespecial #1                  // Method org/jboss/as/ee/resource/definition/ResourceDefinitionDescriptorProcessor."<init>":()V
       4: return

  protected void processEnvironment(org.jboss.metadata.javaee.spec.RemoteEnvironment, org.jboss.as.ee.resource.definition.ResourceDefinitionDescriptorProcessor$ResourceDefinitionInjectionSources) throws org.jboss.as.server.deployment.DeploymentUnitProcessingException;
    Code:
       0: aload_1
       1: invokeinterface #2,  1            // InterfaceMethod org/jboss/metadata/javaee/spec/RemoteEnvironment.getJmsConnectionFactories:()Lorg/jboss/metadata/javaee/spec/JMSConnectionFactoriesMetaData;
       6: astore_3
       7: aload_3
       8: ifnull        52
      11: aload_3
      12: invokevirtual #3                  // Method org/jboss/metadata/javaee/spec/JMSConnectionFactoriesMetaData.iterator:()Ljava/util/Iterator;
      15: astore        4
      17: aload         4
      19: invokeinterface #4,  1            // InterfaceMethod java/util/Iterator.hasNext:()Z
      24: ifeq          52
      27: aload         4
      29: invokeinterface #5,  1            // InterfaceMethod java/util/Iterator.next:()Ljava/lang/Object;
      34: checkcast     #6                  // class org/jboss/metadata/javaee/spec/JMSConnectionFactoryMetaData
      37: astore        5
      39: aload_2
      40: aload_0
      41: aload         5
      43: invokespecial #7                  // Method getResourceDefinitionInjectionSource:(Lorg/jboss/metadata/javaee/spec/JMSConnectionFactoryMetaData;)Lorg/jboss/as/ee/resource/definition/ResourceDefinitionInjectionSource;
      46: invokevirtual #8                  // Method org/jboss/as/ee/resource/definition/ResourceDefinitionDescriptorProcessor$ResourceDefinitionInjectionSources.addResourceDefinitionInjectionSource:(Lorg/jboss/as/ee/resource/definition/ResourceDefinitionInjectionSource;)V
      49: goto          17
      52: return

  private org.jboss.as.ee.resource.definition.ResourceDefinitionInjectionSource getResourceDefinitionInjectionSource(org.jboss.metadata.javaee.spec.JMSConnectionFactoryMetaData);
    Code:
       0: new           #9                  // class org/wildfly/extension/messaging/activemq/deployment/JMSConnectionFactoryDefinitionInjectionSource
       3: dup
       4: aload_1
       5: invokevirtual #10                 // Method org/jboss/metadata/javaee/spec/JMSConnectionFactoryMetaData.getName:()Ljava/lang/String;
       8: invokespecial #11                 // Method org/wildfly/extension/messaging/activemq/deployment/JMSConnectionFactoryDefinitionInjectionSource."<init>":(Ljava/lang/String;)V
      11: astore_2
      12: aload_2
      13: aload_1
      14: invokevirtual #12                 // Method org/jboss/metadata/javaee/spec/JMSConnectionFactoryMetaData.getInterfaceName:()Ljava/lang/String;
      17: invokevirtual #13                 // Method org/wildfly/extension/messaging/activemq/deployment/JMSConnectionFactoryDefinitionInjectionSource.setInterfaceName:(Ljava/lang/String;)V
      20: aload_2
      21: aload_1
      22: invokevirtual #14                 // Method org/jboss/metadata/javaee/spec/JMSConnectionFactoryMetaData.getClassName:()Ljava/lang/String;
      25: invokevirtual #15                 // Method org/wildfly/extension/messaging/activemq/deployment/JMSConnectionFactoryDefinitionInjectionSource.setClassName:(Ljava/lang/String;)V
      28: aload_2
      29: aload_1
      30: invokevirtual #16                 // Method org/jboss/metadata/javaee/spec/JMSConnectionFactoryMetaData.getResourceAdapter:()Ljava/lang/String;
      33: invokevirtual #17                 // Method org/wildfly/extension/messaging/activemq/deployment/JMSConnectionFactoryDefinitionInjectionSource.setResourceAdapter:(Ljava/lang/String;)V
      36: aload_2
      37: aload_1
      38: invokevirtual #18                 // Method org/jboss/metadata/javaee/spec/JMSConnectionFactoryMetaData.getUser:()Ljava/lang/String;
      41: invokevirtual #19                 // Method org/wildfly/extension/messaging/activemq/deployment/JMSConnectionFactoryDefinitionInjectionSource.setUser:(Ljava/lang/String;)V
      44: aload_2
      45: aload_1
      46: invokevirtual #20                 // Method org/jboss/metadata/javaee/spec/JMSConnectionFactoryMetaData.getPassword:()Ljava/lang/String;
      49: invokevirtual #21                 // Method org/wildfly/extension/messaging/activemq/deployment/JMSConnectionFactoryDefinitionInjectionSource.setPassword:(Ljava/lang/String;)V
      52: aload_2
      53: aload_1
      54: invokevirtual #22                 // Method org/jboss/metadata/javaee/spec/JMSConnectionFactoryMetaData.getClientId:()Ljava/lang/String;
      57: invokevirtual #23                 // Method org/wildfly/extension/messaging/activemq/deployment/JMSConnectionFactoryDefinitionInjectionSource.setClientId:(Ljava/lang/String;)V
      60: aload_2
      61: aload_1
      62: invokevirtual #24                 // Method org/jboss/metadata/javaee/spec/JMSConnectionFactoryMetaData.getProperties:()Lorg/jboss/metadata/javaee/spec/PropertiesMetaData;
      65: invokevirtual #25                 // Method org/wildfly/extension/messaging/activemq/deployment/JMSConnectionFactoryDefinitionInjectionSource.addProperties:(Lorg/jboss/metadata/javaee/spec/PropertiesMetaData;)V
      68: aload_2
      69: aload_1
      70: invokevirtual #26                 // Method org/jboss/metadata/javaee/spec/JMSConnectionFactoryMetaData.isTransactional:()Z
      73: invokevirtual #27                 // Method org/wildfly/extension/messaging/activemq/deployment/JMSConnectionFactoryDefinitionInjectionSource.setTransactional:(Z)V
      76: aload_2
      77: aload_1
      78: invokevirtual #28                 // Method org/jboss/metadata/javaee/spec/JMSConnectionFactoryMetaData.getMaxPoolSize:()I
      81: invokevirtual #29                 // Method org/wildfly/extension/messaging/activemq/deployment/JMSConnectionFactoryDefinitionInjectionSource.setMaxPoolSize:(I)V
      84: aload_2
      85: aload_1
      86: invokevirtual #30                 // Method org/jboss/metadata/javaee/spec/JMSConnectionFactoryMetaData.getMinPoolSize:()I
      89: invokevirtual #31                 // Method org/wildfly/extension/messaging/activemq/deployment/JMSConnectionFactoryDefinitionInjectionSource.setMinPoolSize:(I)V
      92: aload_2
      93: areturn
}
