Compiled from "JMSDestinationDefinitionInjectionSource.java"
public class org.wildfly.extension.messaging.activemq.deployment.JMSDestinationDefinitionInjectionSource extends org.jboss.as.ee.resource.definition.ResourceDefinitionInjectionSource {
  private final java.lang.String interfaceName;

  private java.lang.String description;

  private java.lang.String className;

  private java.lang.String resourceAdapter;

  private java.lang.String destinationName;

  public org.wildfly.extension.messaging.activemq.deployment.JMSDestinationDefinitionInjectionSource(java.lang.String, java.lang.String);
    Code:
       0: aload_0
       1: aload_1
       2: invokespecial #3                  // Method org/jboss/as/ee/resource/definition/ResourceDefinitionInjectionSource."<init>":(Ljava/lang/String;)V
       5: aload_0
       6: aload_2
       7: putfield      #4                  // Field interfaceName:Ljava/lang/String;
      10: return

  void setDescription(java.lang.String);
    Code:
       0: aload_0
       1: aload_1
       2: putfield      #5                  // Field description:Ljava/lang/String;
       5: return

  void setClassName(java.lang.String);
    Code:
       0: aload_0
       1: aload_1
       2: putfield      #6                  // Field className:Ljava/lang/String;
       5: return

  void setResourceAdapter(java.lang.String);
    Code:
       0: aload_0
       1: aload_1
       2: putfield      #7                  // Field resourceAdapter:Ljava/lang/String;
       5: return

  void setDestinationName(java.lang.String);
    Code:
       0: aload_0
       1: aload_1
       2: putfield      #8                  // Field destinationName:Ljava/lang/String;
       5: return

  private java.lang.String uniqueName(org.jboss.as.ee.component.InjectionSource$ResolutionContext);
    Code:
       0: aload_0
       1: getfield      #8                  // Field destinationName:Ljava/lang/String;
       4: ifnull        22
       7: aload_0
       8: getfield      #8                  // Field destinationName:Ljava/lang/String;
      11: invokevirtual #9                  // Method java/lang/String.isEmpty:()Z
      14: ifne          22
      17: aload_0
      18: getfield      #8                  // Field destinationName:Ljava/lang/String;
      21: areturn
      22: new           #10                 // class java/lang/StringBuilder
      25: dup
      26: invokespecial #11                 // Method java/lang/StringBuilder."<init>":()V
      29: astore_2
      30: aload_2
      31: new           #10                 // class java/lang/StringBuilder
      34: dup
      35: invokespecial #11                 // Method java/lang/StringBuilder."<init>":()V
      38: aload_1
      39: invokevirtual #12                 // Method org/jboss/as/ee/component/InjectionSource$ResolutionContext.getApplicationName:()Ljava/lang/String;
      42: invokevirtual #13                 // Method java/lang/StringBuilder.append:(Ljava/lang/String;)Ljava/lang/StringBuilder;
      45: ldc           #14                 // String _
      47: invokevirtual #13                 // Method java/lang/StringBuilder.append:(Ljava/lang/String;)Ljava/lang/StringBuilder;
      50: invokevirtual #15                 // Method java/lang/StringBuilder.toString:()Ljava/lang/String;
      53: invokevirtual #13                 // Method java/lang/StringBuilder.append:(Ljava/lang/String;)Ljava/lang/StringBuilder;
      56: pop
      57: aload_2
      58: new           #10                 // class java/lang/StringBuilder
      61: dup
      62: invokespecial #11                 // Method java/lang/StringBuilder."<init>":()V
      65: aload_1
      66: invokevirtual #16                 // Method org/jboss/as/ee/component/InjectionSource$ResolutionContext.getModuleName:()Ljava/lang/String;
      69: invokevirtual #13                 // Method java/lang/StringBuilder.append:(Ljava/lang/String;)Ljava/lang/StringBuilder;
      72: ldc           #14                 // String _
      74: invokevirtual #13                 // Method java/lang/StringBuilder.append:(Ljava/lang/String;)Ljava/lang/StringBuilder;
      77: invokevirtual #15                 // Method java/lang/StringBuilder.toString:()Ljava/lang/String;
      80: invokevirtual #13                 // Method java/lang/StringBuilder.append:(Ljava/lang/String;)Ljava/lang/StringBuilder;
      83: pop
      84: aload_1
      85: invokevirtual #17                 // Method org/jboss/as/ee/component/InjectionSource$ResolutionContext.getComponentName:()Ljava/lang/String;
      88: ifnull        118
      91: aload_2
      92: new           #10                 // class java/lang/StringBuilder
      95: dup
      96: invokespecial #11                 // Method java/lang/StringBuilder."<init>":()V
      99: aload_1
     100: invokevirtual #17                 // Method org/jboss/as/ee/component/InjectionSource$ResolutionContext.getComponentName:()Ljava/lang/String;
     103: invokevirtual #13                 // Method java/lang/StringBuilder.append:(Ljava/lang/String;)Ljava/lang/StringBuilder;
     106: ldc           #14                 // String _
     108: invokevirtual #13                 // Method java/lang/StringBuilder.append:(Ljava/lang/String;)Ljava/lang/StringBuilder;
     111: invokevirtual #15                 // Method java/lang/StringBuilder.toString:()Ljava/lang/String;
     114: invokevirtual #13                 // Method java/lang/StringBuilder.append:(Ljava/lang/String;)Ljava/lang/StringBuilder;
     117: pop
     118: aload_2
     119: aload_0
     120: getfield      #2                  // Field jndiName:Ljava/lang/String;
     123: invokevirtual #13                 // Method java/lang/StringBuilder.append:(Ljava/lang/String;)Ljava/lang/StringBuilder;
     126: pop
     127: aload_2
     128: invokevirtual #15                 // Method java/lang/StringBuilder.toString:()Ljava/lang/String;
     131: areturn

  public void getResourceValue(org.jboss.as.ee.component.InjectionSource$ResolutionContext, org.jboss.msc.service.ServiceBuilder<?>, org.jboss.as.server.deployment.DeploymentPhaseContext, org.jboss.msc.inject.Injector<org.jboss.as.naming.ManagedReferenceFactory>) throws org.jboss.as.server.deployment.DeploymentUnitProcessingException;
    Code:
       0: aload_3
       1: invokeinterface #18,  1           // InterfaceMethod org/jboss/as/server/deployment/DeploymentPhaseContext.getDeploymentUnit:()Lorg/jboss/as/server/deployment/DeploymentUnit;
       6: astore        5
       8: aload_0
       9: aload_1
      10: invokespecial #19                 // Method uniqueName:(Lorg/jboss/as/ee/component/InjectionSource$ResolutionContext;)Ljava/lang/String;
      13: astore        6
      15: aload_0
      16: invokespecial #20                 // Method getActiveMQServerName:()Ljava/lang/String;
      19: invokestatic  #21                 // Method org/wildfly/extension/messaging/activemq/MessagingServices.getActiveMQServiceName:(Ljava/lang/String;)Lorg/jboss/msc/service/ServiceName;
      22: astore        7
      24: aload_0
      25: getfield      #4                  // Field interfaceName:Ljava/lang/String;
      28: ldc           #22                 // class javax/jms/Queue
      30: invokevirtual #23                 // Method java/lang/Class.getName:()Ljava/lang/String;
      33: invokevirtual #24                 // Method java/lang/String.equals:(Ljava/lang/Object;)Z
      36: ifeq          61
      39: aload_0
      40: aload         6
      42: aload_3
      43: invokeinterface #25,  1           // InterfaceMethod org/jboss/as/server/deployment/DeploymentPhaseContext.getServiceTarget:()Lorg/jboss/msc/service/ServiceTarget;
      48: aload         7
      50: aload_2
      51: aload         5
      53: aload         4
      55: invokespecial #26                 // Method startQueue:(Ljava/lang/String;Lorg/jboss/msc/service/ServiceTarget;Lorg/jboss/msc/service/ServiceName;Lorg/jboss/msc/service/ServiceBuilder;Lorg/jboss/as/server/deployment/DeploymentUnit;Lorg/jboss/msc/inject/Injector;)V
      58: goto          80
      61: aload_0
      62: aload         6
      64: aload_3
      65: invokeinterface #25,  1           // InterfaceMethod org/jboss/as/server/deployment/DeploymentPhaseContext.getServiceTarget:()Lorg/jboss/msc/service/ServiceTarget;
      70: aload         7
      72: aload_2
      73: aload         5
      75: aload         4
      77: invokespecial #27                 // Method startTopic:(Ljava/lang/String;Lorg/jboss/msc/service/ServiceTarget;Lorg/jboss/msc/service/ServiceName;Lorg/jboss/msc/service/ServiceBuilder;Lorg/jboss/as/server/deployment/DeploymentUnit;Lorg/jboss/msc/inject/Injector;)V
      80: goto          95
      83: astore        7
      85: new           #29                 // class org/jboss/as/server/deployment/DeploymentUnitProcessingException
      88: dup
      89: aload         7
      91: invokespecial #30                 // Method org/jboss/as/server/deployment/DeploymentUnitProcessingException."<init>":(Ljava/lang/Throwable;)V
      94: athrow
      95: return
    Exception table:
       from    to  target type
          15    80    83   Class java/lang/Exception

  private void startQueue(java.lang.String, org.jboss.msc.service.ServiceTarget, org.jboss.msc.service.ServiceName, org.jboss.msc.service.ServiceBuilder<?>, org.jboss.as.server.deployment.DeploymentUnit, org.jboss.msc.inject.Injector<org.jboss.as.naming.ManagedReferenceFactory>);
    Code:
       0: aload_0
       1: getfield      #31                 // Field properties:Ljava/util/Map;
       4: getstatic     #32                 // Field org/wildfly/extension/messaging/activemq/CommonAttributes.SELECTOR:Lorg/jboss/as/controller/SimpleAttributeDefinition;
       7: invokevirtual #33                 // Method org/jboss/as/controller/SimpleAttributeDefinition.getName:()Ljava/lang/String;
      10: invokeinterface #34,  2           // InterfaceMethod java/util/Map.containsKey:(Ljava/lang/Object;)Z
      15: ifeq          39
      18: aload_0
      19: getfield      #31                 // Field properties:Ljava/util/Map;
      22: getstatic     #32                 // Field org/wildfly/extension/messaging/activemq/CommonAttributes.SELECTOR:Lorg/jboss/as/controller/SimpleAttributeDefinition;
      25: invokevirtual #33                 // Method org/jboss/as/controller/SimpleAttributeDefinition.getName:()Ljava/lang/String;
      28: invokeinterface #35,  2           // InterfaceMethod java/util/Map.get:(Ljava/lang/Object;)Ljava/lang/Object;
      33: checkcast     #36                 // class java/lang/String
      36: goto          40
      39: aconst_null
      40: astore        7
      42: aload_0
      43: getfield      #31                 // Field properties:Ljava/util/Map;
      46: getstatic     #37                 // Field org/wildfly/extension/messaging/activemq/CommonAttributes.DURABLE:Lorg/jboss/as/controller/SimpleAttributeDefinition;
      49: invokevirtual #33                 // Method org/jboss/as/controller/SimpleAttributeDefinition.getName:()Ljava/lang/String;
      52: invokeinterface #34,  2           // InterfaceMethod java/util/Map.containsKey:(Ljava/lang/Object;)Z
      57: ifeq          87
      60: aload_0
      61: getfield      #31                 // Field properties:Ljava/util/Map;
      64: getstatic     #37                 // Field org/wildfly/extension/messaging/activemq/CommonAttributes.DURABLE:Lorg/jboss/as/controller/SimpleAttributeDefinition;
      67: invokevirtual #33                 // Method org/jboss/as/controller/SimpleAttributeDefinition.getName:()Ljava/lang/String;
      70: invokeinterface #35,  2           // InterfaceMethod java/util/Map.get:(Ljava/lang/Object;)Ljava/lang/Object;
      75: checkcast     #36                 // class java/lang/String
      78: invokestatic  #38                 // Method java/lang/Boolean.valueOf:(Ljava/lang/String;)Ljava/lang/Boolean;
      81: invokevirtual #39                 // Method java/lang/Boolean.booleanValue:()Z
      84: goto          96
      87: getstatic     #37                 // Field org/wildfly/extension/messaging/activemq/CommonAttributes.DURABLE:Lorg/jboss/as/controller/SimpleAttributeDefinition;
      90: invokevirtual #40                 // Method org/jboss/as/controller/SimpleAttributeDefinition.getDefaultValue:()Lorg/jboss/dmr/ModelNode;
      93: invokevirtual #41                 // Method org/jboss/dmr/ModelNode.asBoolean:()Z
      96: istore        8
      98: new           #42                 // class org/jboss/dmr/ModelNode
     101: dup
     102: invokespecial #43                 // Method org/jboss/dmr/ModelNode."<init>":()V
     105: astore        9
     107: aload         9
     109: ldc           #44                 // String name
     111: invokevirtual #45                 // Method org/jboss/dmr/ModelNode.get:(Ljava/lang/String;)Lorg/jboss/dmr/ModelNode;
     114: aload_1
     115: invokevirtual #46                 // Method org/jboss/dmr/ModelNode.set:(Ljava/lang/String;)Lorg/jboss/dmr/ModelNode;
     118: pop
     119: aload         9
     121: getstatic     #37                 // Field org/wildfly/extension/messaging/activemq/CommonAttributes.DURABLE:Lorg/jboss/as/controller/SimpleAttributeDefinition;
     124: invokevirtual #33                 // Method org/jboss/as/controller/SimpleAttributeDefinition.getName:()Ljava/lang/String;
     127: invokevirtual #45                 // Method org/jboss/dmr/ModelNode.get:(Ljava/lang/String;)Lorg/jboss/dmr/ModelNode;
     130: iload         8
     132: invokevirtual #47                 // Method org/jboss/dmr/ModelNode.set:(Z)Lorg/jboss/dmr/ModelNode;
     135: pop
     136: aload         7
     138: ifnull        158
     141: aload         9
     143: getstatic     #32                 // Field org/wildfly/extension/messaging/activemq/CommonAttributes.SELECTOR:Lorg/jboss/as/controller/SimpleAttributeDefinition;
     146: invokevirtual #33                 // Method org/jboss/as/controller/SimpleAttributeDefinition.getName:()Ljava/lang/String;
     149: invokevirtual #45                 // Method org/jboss/dmr/ModelNode.get:(Ljava/lang/String;)Lorg/jboss/dmr/ModelNode;
     152: aload         7
     154: invokevirtual #46                 // Method org/jboss/dmr/ModelNode.set:(Ljava/lang/String;)Lorg/jboss/dmr/ModelNode;
     157: pop
     158: aload         9
     160: ldc           #48                 // String entries
     162: invokevirtual #45                 // Method org/jboss/dmr/ModelNode.get:(Ljava/lang/String;)Lorg/jboss/dmr/ModelNode;
     165: aload_0
     166: getfield      #2                  // Field jndiName:Ljava/lang/String;
     169: invokevirtual #49                 // Method org/jboss/dmr/ModelNode.add:(Ljava/lang/String;)Lorg/jboss/dmr/ModelNode;
     172: pop
     173: aload_1
     174: aload_2
     175: aload_3
     176: aload         7
     178: iload         8
     180: iconst_0
     181: anewarray     #36                 // class java/lang/String
     184: invokestatic  #50                 // Method org/wildfly/extension/messaging/activemq/jms/JMSQueueService.installService:(Ljava/lang/String;Lorg/jboss/msc/service/ServiceTarget;Lorg/jboss/msc/service/ServiceName;Ljava/lang/String;Z[Ljava/lang/String;)Lorg/jboss/msc/service/Service;
     187: astore        10
     189: aload_0
     190: aload         4
     192: aload         6
     194: aload         10
     196: invokespecial #51                 // Method inject:(Lorg/jboss/msc/service/ServiceBuilder;Lorg/jboss/msc/inject/Injector;Lorg/jboss/msc/service/Service;)V
     199: ldc           #52                 // String server
     201: aload_0
     202: invokespecial #20                 // Method getActiveMQServerName:()Ljava/lang/String;
     205: invokestatic  #53                 // Method org/jboss/as/controller/PathElement.pathElement:(Ljava/lang/String;Ljava/lang/String;)Lorg/jboss/as/controller/PathElement;
     208: astore        11
     210: ldc           #54                 // String jms-queue
     212: aload_1
     213: invokestatic  #53                 // Method org/jboss/as/controller/PathElement.pathElement:(Ljava/lang/String;Ljava/lang/String;)Lorg/jboss/as/controller/PathElement;
     216: astore        12
     218: aload         5
     220: getstatic     #55                 // Field org/jboss/as/server/deployment/Attachments.DEPLOYMENT_RESOURCE_SUPPORT:Lorg/jboss/as/server/deployment/AttachmentKey;
     223: invokeinterface #56,  2           // InterfaceMethod org/jboss/as/server/deployment/DeploymentUnit.getAttachment:(Lorg/jboss/as/server/deployment/AttachmentKey;)Ljava/lang/Object;
     228: checkcast     #57                 // class org/jboss/as/server/deployment/DeploymentResourceSupport
     231: astore        13
     233: aload         13
     235: ldc           #59                 // String messaging-activemq
     237: aload         11
     239: invokevirtual #60                 // Method org/jboss/as/server/deployment/DeploymentResourceSupport.getDeploymentSubModel:(Ljava/lang/String;Lorg/jboss/as/controller/PathElement;)Lorg/jboss/dmr/ModelNode;
     242: pop
     243: iconst_2
     244: anewarray     #61                 // class org/jboss/as/controller/PathElement
     247: dup
     248: iconst_0
     249: aload         11
     251: aastore
     252: dup
     253: iconst_1
     254: aload         12
     256: aastore
     257: invokestatic  #62                 // Method org/jboss/as/controller/PathAddress.pathAddress:([Lorg/jboss/as/controller/PathElement;)Lorg/jboss/as/controller/PathAddress;
     260: astore        14
     262: aload         14
     264: aload         5
     266: invokestatic  #63                 // Method org/wildfly/extension/messaging/activemq/deployment/MessagingXmlInstallDeploymentUnitProcessor.createDeploymentSubModel:(Lorg/jboss/as/controller/PathAddress;Lorg/jboss/as/server/deployment/DeploymentUnit;)Lorg/jboss/as/controller/registry/ManagementResourceRegistration;
     269: pop
     270: getstatic     #64                 // Field org/wildfly/extension/messaging/activemq/jms/JMSQueueConfigurationRuntimeHandler.INSTANCE:Lorg/wildfly/extension/messaging/activemq/jms/JMSQueueConfigurationRuntimeHandler;
     273: aload_0
     274: invokespecial #20                 // Method getActiveMQServerName:()Ljava/lang/String;
     277: aload_1
     278: aload         9
     280: invokevirtual #65                 // Method org/wildfly/extension/messaging/activemq/jms/JMSQueueConfigurationRuntimeHandler.registerResource:(Ljava/lang/String;Ljava/lang/String;Ljava/lang/Object;)V
     283: return

  private void startTopic(java.lang.String, org.jboss.msc.service.ServiceTarget, org.jboss.msc.service.ServiceName, org.jboss.msc.service.ServiceBuilder<?>, org.jboss.as.server.deployment.DeploymentUnit, org.jboss.msc.inject.Injector<org.jboss.as.naming.ManagedReferenceFactory>);
    Code:
       0: new           #42                 // class org/jboss/dmr/ModelNode
       3: dup
       4: invokespecial #43                 // Method org/jboss/dmr/ModelNode."<init>":()V
       7: astore        7
       9: aload         7
      11: ldc           #44                 // String name
      13: invokevirtual #45                 // Method org/jboss/dmr/ModelNode.get:(Ljava/lang/String;)Lorg/jboss/dmr/ModelNode;
      16: aload_1
      17: invokevirtual #46                 // Method org/jboss/dmr/ModelNode.set:(Ljava/lang/String;)Lorg/jboss/dmr/ModelNode;
      20: pop
      21: aload         7
      23: ldc           #48                 // String entries
      25: invokevirtual #45                 // Method org/jboss/dmr/ModelNode.get:(Ljava/lang/String;)Lorg/jboss/dmr/ModelNode;
      28: aload_0
      29: getfield      #2                  // Field jndiName:Ljava/lang/String;
      32: invokevirtual #49                 // Method org/jboss/dmr/ModelNode.add:(Ljava/lang/String;)Lorg/jboss/dmr/ModelNode;
      35: pop
      36: aload_1
      37: aload_3
      38: aload_2
      39: iconst_0
      40: anewarray     #36                 // class java/lang/String
      43: invokestatic  #66                 // Method org/wildfly/extension/messaging/activemq/jms/JMSTopicService.installService:(Ljava/lang/String;Lorg/jboss/msc/service/ServiceName;Lorg/jboss/msc/service/ServiceTarget;[Ljava/lang/String;)Lorg/wildfly/extension/messaging/activemq/jms/JMSTopicService;
      46: astore        8
      48: aload_0
      49: aload         4
      51: aload         6
      53: aload         8
      55: invokespecial #51                 // Method inject:(Lorg/jboss/msc/service/ServiceBuilder;Lorg/jboss/msc/inject/Injector;Lorg/jboss/msc/service/Service;)V
      58: ldc           #52                 // String server
      60: aload_0
      61: invokespecial #20                 // Method getActiveMQServerName:()Ljava/lang/String;
      64: invokestatic  #53                 // Method org/jboss/as/controller/PathElement.pathElement:(Ljava/lang/String;Ljava/lang/String;)Lorg/jboss/as/controller/PathElement;
      67: astore        9
      69: ldc           #67                 // String jms-topic
      71: aload_1
      72: invokestatic  #53                 // Method org/jboss/as/controller/PathElement.pathElement:(Ljava/lang/String;Ljava/lang/String;)Lorg/jboss/as/controller/PathElement;
      75: astore        10
      77: aload         5
      79: getstatic     #55                 // Field org/jboss/as/server/deployment/Attachments.DEPLOYMENT_RESOURCE_SUPPORT:Lorg/jboss/as/server/deployment/AttachmentKey;
      82: invokeinterface #56,  2           // InterfaceMethod org/jboss/as/server/deployment/DeploymentUnit.getAttachment:(Lorg/jboss/as/server/deployment/AttachmentKey;)Ljava/lang/Object;
      87: checkcast     #57                 // class org/jboss/as/server/deployment/DeploymentResourceSupport
      90: astore        11
      92: aload         11
      94: ldc           #59                 // String messaging-activemq
      96: aload         9
      98: invokevirtual #60                 // Method org/jboss/as/server/deployment/DeploymentResourceSupport.getDeploymentSubModel:(Ljava/lang/String;Lorg/jboss/as/controller/PathElement;)Lorg/jboss/dmr/ModelNode;
     101: pop
     102: iconst_2
     103: anewarray     #61                 // class org/jboss/as/controller/PathElement
     106: dup
     107: iconst_0
     108: aload         9
     110: aastore
     111: dup
     112: iconst_1
     113: aload         10
     115: aastore
     116: invokestatic  #62                 // Method org/jboss/as/controller/PathAddress.pathAddress:([Lorg/jboss/as/controller/PathElement;)Lorg/jboss/as/controller/PathAddress;
     119: astore        12
     121: aload         12
     123: aload         5
     125: invokestatic  #63                 // Method org/wildfly/extension/messaging/activemq/deployment/MessagingXmlInstallDeploymentUnitProcessor.createDeploymentSubModel:(Lorg/jboss/as/controller/PathAddress;Lorg/jboss/as/server/deployment/DeploymentUnit;)Lorg/jboss/as/controller/registry/ManagementResourceRegistration;
     128: pop
     129: getstatic     #68                 // Field org/wildfly/extension/messaging/activemq/jms/JMSTopicConfigurationRuntimeHandler.INSTANCE:Lorg/wildfly/extension/messaging/activemq/jms/JMSTopicConfigurationRuntimeHandler;
     132: aload_0
     133: invokespecial #20                 // Method getActiveMQServerName:()Ljava/lang/String;
     136: aload_1
     137: aload         7
     139: invokevirtual #69                 // Method org/wildfly/extension/messaging/activemq/jms/JMSTopicConfigurationRuntimeHandler.registerResource:(Ljava/lang/String;Ljava/lang/String;Ljava/lang/Object;)V
     142: return

  private <D extends javax.jms.Destination> void inject(org.jboss.msc.service.ServiceBuilder<?>, org.jboss.msc.inject.Injector<org.jboss.as.naming.ManagedReferenceFactory>, org.jboss.msc.service.Service<D>);
    Code:
       0: new           #70                 // class org/wildfly/extension/messaging/activemq/deployment/MessagingJMSDestinationManagedReferenceFactory
       3: dup
       4: aload_3
       5: invokespecial #71                 // Method org/wildfly/extension/messaging/activemq/deployment/MessagingJMSDestinationManagedReferenceFactory."<init>":(Lorg/jboss/msc/service/Service;)V
       8: astore        4
      10: aload_1
      11: aload_2
      12: aload         4
      14: invokeinterface #72,  3           // InterfaceMethod org/jboss/msc/service/ServiceBuilder.addInjection:(Lorg/jboss/msc/inject/Injector;Ljava/lang/Object;)Lorg/jboss/msc/service/ServiceBuilder;
      19: new           #73                 // class org/wildfly/extension/messaging/activemq/deployment/JMSDestinationDefinitionInjectionSource$1
      22: dup
      23: aload_0
      24: invokespecial #74                 // Method org/wildfly/extension/messaging/activemq/deployment/JMSDestinationDefinitionInjectionSource$1."<init>":(Lorg/wildfly/extension/messaging/activemq/deployment/JMSDestinationDefinitionInjectionSource;)V
      27: invokeinterface #75,  2           // InterfaceMethod org/jboss/msc/service/ServiceBuilder.addListener:(Lorg/jboss/msc/service/ServiceListener;)Lorg/jboss/msc/service/ServiceBuilder;
      32: pop
      33: return

  private java.lang.String getActiveMQServerName();
    Code:
       0: aload_0
       1: getfield      #31                 // Field properties:Ljava/util/Map;
       4: ldc           #52                 // String server
       6: invokeinterface #34,  2           // InterfaceMethod java/util/Map.containsKey:(Ljava/lang/Object;)Z
      11: ifeq          31
      14: aload_0
      15: getfield      #31                 // Field properties:Ljava/util/Map;
      18: ldc           #52                 // String server
      20: invokeinterface #35,  2           // InterfaceMethod java/util/Map.get:(Ljava/lang/Object;)Ljava/lang/Object;
      25: checkcast     #36                 // class java/lang/String
      28: goto          33
      31: ldc           #76                 // String default
      33: areturn

  public boolean equals(java.lang.Object);
    Code:
       0: aload_0
       1: aload_1
       2: if_acmpne     7
       5: iconst_1
       6: ireturn
       7: aload_1
       8: ifnull        22
      11: aload_0
      12: invokevirtual #77                 // Method java/lang/Object.getClass:()Ljava/lang/Class;
      15: aload_1
      16: invokevirtual #77                 // Method java/lang/Object.getClass:()Ljava/lang/Class;
      19: if_acmpeq     24
      22: iconst_0
      23: ireturn
      24: aload_0
      25: aload_1
      26: invokespecial #78                 // Method org/jboss/as/ee/resource/definition/ResourceDefinitionInjectionSource.equals:(Ljava/lang/Object;)Z
      29: ifne          34
      32: iconst_0
      33: ireturn
      34: aload_1
      35: checkcast     #79                 // class org/wildfly/extension/messaging/activemq/deployment/JMSDestinationDefinitionInjectionSource
      38: astore_2
      39: aload_0
      40: getfield      #6                  // Field className:Ljava/lang/String;
      43: ifnull        63
      46: aload_0
      47: getfield      #6                  // Field className:Ljava/lang/String;
      50: aload_2
      51: getfield      #6                  // Field className:Ljava/lang/String;
      54: invokevirtual #24                 // Method java/lang/String.equals:(Ljava/lang/Object;)Z
      57: ifne          72
      60: goto          70
      63: aload_2
      64: getfield      #6                  // Field className:Ljava/lang/String;
      67: ifnull        72
      70: iconst_0
      71: ireturn
      72: aload_0
      73: getfield      #5                  // Field description:Ljava/lang/String;
      76: ifnull        96
      79: aload_0
      80: getfield      #5                  // Field description:Ljava/lang/String;
      83: aload_2
      84: getfield      #5                  // Field description:Ljava/lang/String;
      87: invokevirtual #24                 // Method java/lang/String.equals:(Ljava/lang/Object;)Z
      90: ifne          105
      93: goto          103
      96: aload_2
      97: getfield      #5                  // Field description:Ljava/lang/String;
     100: ifnull        105
     103: iconst_0
     104: ireturn
     105: aload_0
     106: getfield      #8                  // Field destinationName:Ljava/lang/String;
     109: ifnull        129
     112: aload_0
     113: getfield      #8                  // Field destinationName:Ljava/lang/String;
     116: aload_2
     117: getfield      #8                  // Field destinationName:Ljava/lang/String;
     120: invokevirtual #24                 // Method java/lang/String.equals:(Ljava/lang/Object;)Z
     123: ifne          138
     126: goto          136
     129: aload_2
     130: getfield      #8                  // Field destinationName:Ljava/lang/String;
     133: ifnull        138
     136: iconst_0
     137: ireturn
     138: aload_0
     139: getfield      #4                  // Field interfaceName:Ljava/lang/String;
     142: ifnull        162
     145: aload_0
     146: getfield      #4                  // Field interfaceName:Ljava/lang/String;
     149: aload_2
     150: getfield      #4                  // Field interfaceName:Ljava/lang/String;
     153: invokevirtual #24                 // Method java/lang/String.equals:(Ljava/lang/Object;)Z
     156: ifne          171
     159: goto          169
     162: aload_2
     163: getfield      #4                  // Field interfaceName:Ljava/lang/String;
     166: ifnull        171
     169: iconst_0
     170: ireturn
     171: aload_0
     172: getfield      #7                  // Field resourceAdapter:Ljava/lang/String;
     175: ifnull        195
     178: aload_0
     179: getfield      #7                  // Field resourceAdapter:Ljava/lang/String;
     182: aload_2
     183: getfield      #7                  // Field resourceAdapter:Ljava/lang/String;
     186: invokevirtual #24                 // Method java/lang/String.equals:(Ljava/lang/Object;)Z
     189: ifne          204
     192: goto          202
     195: aload_2
     196: getfield      #7                  // Field resourceAdapter:Ljava/lang/String;
     199: ifnull        204
     202: iconst_0
     203: ireturn
     204: iconst_1
     205: ireturn

  public int hashCode();
    Code:
       0: aload_0
       1: invokespecial #80                 // Method org/jboss/as/ee/resource/definition/ResourceDefinitionInjectionSource.hashCode:()I
       4: istore_1
       5: bipush        31
       7: iload_1
       8: imul
       9: aload_0
      10: getfield      #4                  // Field interfaceName:Ljava/lang/String;
      13: ifnull        26
      16: aload_0
      17: getfield      #4                  // Field interfaceName:Ljava/lang/String;
      20: invokevirtual #81                 // Method java/lang/String.hashCode:()I
      23: goto          27
      26: iconst_0
      27: iadd
      28: istore_1
      29: bipush        31
      31: iload_1
      32: imul
      33: aload_0
      34: getfield      #5                  // Field description:Ljava/lang/String;
      37: ifnull        50
      40: aload_0
      41: getfield      #5                  // Field description:Ljava/lang/String;
      44: invokevirtual #81                 // Method java/lang/String.hashCode:()I
      47: goto          51
      50: iconst_0
      51: iadd
      52: istore_1
      53: bipush        31
      55: iload_1
      56: imul
      57: aload_0
      58: getfield      #6                  // Field className:Ljava/lang/String;
      61: ifnull        74
      64: aload_0
      65: getfield      #6                  // Field className:Ljava/lang/String;
      68: invokevirtual #81                 // Method java/lang/String.hashCode:()I
      71: goto          75
      74: iconst_0
      75: iadd
      76: istore_1
      77: bipush        31
      79: iload_1
      80: imul
      81: aload_0
      82: getfield      #7                  // Field resourceAdapter:Ljava/lang/String;
      85: ifnull        98
      88: aload_0
      89: getfield      #7                  // Field resourceAdapter:Ljava/lang/String;
      92: invokevirtual #81                 // Method java/lang/String.hashCode:()I
      95: goto          99
      98: iconst_0
      99: iadd
     100: istore_1
     101: bipush        31
     103: iload_1
     104: imul
     105: aload_0
     106: getfield      #8                  // Field destinationName:Ljava/lang/String;
     109: ifnull        122
     112: aload_0
     113: getfield      #8                  // Field destinationName:Ljava/lang/String;
     116: invokevirtual #81                 // Method java/lang/String.hashCode:()I
     119: goto          123
     122: iconst_0
     123: iadd
     124: istore_1
     125: iload_1
     126: ireturn

  static java.lang.String access$000(org.wildfly.extension.messaging.activemq.deployment.JMSDestinationDefinitionInjectionSource);
    Code:
       0: aload_0
       1: getfield      #2                  // Field jndiName:Ljava/lang/String;
       4: areturn

  static java.lang.String access$100(org.wildfly.extension.messaging.activemq.deployment.JMSDestinationDefinitionInjectionSource);
    Code:
       0: aload_0
       1: getfield      #2                  // Field jndiName:Ljava/lang/String;
       4: areturn

  static java.lang.String access$200(org.wildfly.extension.messaging.activemq.deployment.JMSDestinationDefinitionInjectionSource);
    Code:
       0: aload_0
       1: getfield      #2                  // Field jndiName:Ljava/lang/String;
       4: areturn
}
