Compiled from "ImmutableSortedMap.java"
class com.google.common.collect.ImmutableSortedMap$1EntrySet$1 extends com.google.common.collect.ImmutableAsList<java.util.Map$Entry<K, V>> {
  final com.google.common.collect.ImmutableSortedMap$1EntrySet this$1;

  com.google.common.collect.ImmutableSortedMap$1EntrySet$1(com.google.common.collect.ImmutableSortedMap$1EntrySet);
    Code:
       0: aload_0
       1: aload_1
       2: putfield      #1                  // Field this$1:Lcom/google/common/collect/ImmutableSortedMap$1EntrySet;
       5: aload_0
       6: invokespecial #2                  // Method com/google/common/collect/ImmutableAsList."<init>":()V
       9: return

  public java.util.Map$Entry<K, V> get(int);
    Code:
       0: new           #3                  // class java/util/AbstractMap$SimpleImmutableEntry
       3: dup
       4: aload_0
       5: getfield      #1                  // Field this$1:Lcom/google/common/collect/ImmutableSortedMap$1EntrySet;
       8: getfield      #4                  // Field com/google/common/collect/ImmutableSortedMap$1EntrySet.this$0:Lcom/google/common/collect/ImmutableSortedMap;
      11: invokestatic  #5                  // Method com/google/common/collect/ImmutableSortedMap.access$200:(Lcom/google/common/collect/ImmutableSortedMap;)Lcom/google/common/collect/RegularImmutableSortedSet;
      14: invokevirtual #6                  // Method com/google/common/collect/RegularImmutableSortedSet.asList:()Lcom/google/common/collect/ImmutableList;
      17: iload_1
      18: invokevirtual #7                  // Method com/google/common/collect/ImmutableList.get:(I)Ljava/lang/Object;
      21: aload_0
      22: getfield      #1                  // Field this$1:Lcom/google/common/collect/ImmutableSortedMap$1EntrySet;
      25: getfield      #4                  // Field com/google/common/collect/ImmutableSortedMap$1EntrySet.this$0:Lcom/google/common/collect/ImmutableSortedMap;
      28: invokestatic  #8                  // Method com/google/common/collect/ImmutableSortedMap.access$300:(Lcom/google/common/collect/ImmutableSortedMap;)Lcom/google/common/collect/ImmutableList;
      31: iload_1
      32: invokevirtual #7                  // Method com/google/common/collect/ImmutableList.get:(I)Ljava/lang/Object;
      35: invokespecial #9                  // Method java/util/AbstractMap$SimpleImmutableEntry."<init>":(Ljava/lang/Object;Ljava/lang/Object;)V
      38: areturn

  public java.util.Spliterator<java.util.Map$Entry<K, V>> spliterator();
    Code:
       0: aload_0
       1: invokevirtual #10                 // Method size:()I
       4: sipush        1297
       7: aload_0
       8: invokedynamic #12,  0             // InvokeDynamic #0:apply:(Lcom/google/common/collect/ImmutableSortedMap$1EntrySet$1;)Ljava/util/function/IntFunction;
      13: invokestatic  #13                 // Method com/google/common/collect/CollectSpliterators.indexed:(IILjava/util/function/IntFunction;)Ljava/util/Spliterator;
      16: areturn

  com.google.common.collect.ImmutableCollection<java.util.Map$Entry<K, V>> delegateCollection();
    Code:
       0: aload_0
       1: getfield      #1                  // Field this$1:Lcom/google/common/collect/ImmutableSortedMap$1EntrySet;
       4: areturn

  public java.lang.Object get(int);
    Code:
       0: aload_0
       1: iload_1
       2: invokevirtual #14                 // Method get:(I)Ljava/util/Map$Entry;
       5: areturn
}
