Compiled from "Tables.java"
class com.google.common.collect.Tables$TransformedTable$1 implements com.google.common.base.Function<com.google.common.collect.Table$Cell<R, C, V1>, com.google.common.collect.Table$Cell<R, C, V2>> {
  final com.google.common.collect.Tables$TransformedTable this$0;

  com.google.common.collect.Tables$TransformedTable$1(com.google.common.collect.Tables$TransformedTable);
    Code:
       0: aload_0
       1: aload_1
       2: putfield      #1                  // Field this$0:Lcom/google/common/collect/Tables$TransformedTable;
       5: aload_0
       6: invokespecial #2                  // Method java/lang/Object."<init>":()V
       9: return

  public com.google.common.collect.Table$Cell<R, C, V2> apply(com.google.common.collect.Table$Cell<R, C, V1>);
    Code:
       0: aload_1
       1: invokeinterface #3,  1            // InterfaceMethod com/google/common/collect/Table$Cell.getRowKey:()Ljava/lang/Object;
       6: aload_1
       7: invokeinterface #4,  1            // InterfaceMethod com/google/common/collect/Table$Cell.getColumnKey:()Ljava/lang/Object;
      12: aload_0
      13: getfield      #1                  // Field this$0:Lcom/google/common/collect/Tables$TransformedTable;
      16: getfield      #5                  // Field com/google/common/collect/Tables$TransformedTable.function:Lcom/google/common/base/Function;
      19: aload_1
      20: invokeinterface #6,  1            // InterfaceMethod com/google/common/collect/Table$Cell.getValue:()Ljava/lang/Object;
      25: invokeinterface #7,  2            // InterfaceMethod com/google/common/base/Function.apply:(Ljava/lang/Object;)Ljava/lang/Object;
      30: invokestatic  #8                  // Method com/google/common/collect/Tables.immutableCell:(Ljava/lang/Object;Ljava/lang/Object;Ljava/lang/Object;)Lcom/google/common/collect/Table$Cell;
      33: areturn

  public java.lang.Object apply(java.lang.Object);
    Code:
       0: aload_0
       1: aload_1
       2: checkcast     #9                  // class com/google/common/collect/Table$Cell
       5: invokevirtual #10                 // Method apply:(Lcom/google/common/collect/Table$Cell;)Lcom/google/common/collect/Table$Cell;
       8: areturn
}
