Compiled from "FD.java"
public class org.jgroups.protocols.FD extends org.jgroups.stack.Protocol {
  protected long timeout;

  protected int max_tries;

  boolean msg_counts_as_heartbeat;

  protected int num_heartbeats;

  protected int num_suspect_events;

  protected final org.jgroups.util.BoundedList<java.lang.String> suspect_history;

  protected org.jgroups.Address local_addr;

  protected volatile long last_ack;

  protected final java.util.concurrent.atomic.AtomicInteger num_tries;

  protected final java.util.concurrent.locks.Lock lock;

  protected volatile org.jgroups.Address ping_dest;

  protected final java.util.List<org.jgroups.Address> members;

  protected final java.util.List<org.jgroups.Address> pingable_mbrs;

  protected org.jgroups.util.TimeScheduler timer;

  protected java.util.concurrent.Future<?> monitor_future;

  protected final org.jgroups.protocols.FD$Broadcaster bcast_task;

  public org.jgroups.protocols.FD();
    Code:
       0: aload_0
       1: invokespecial #5                  // Method org/jgroups/stack/Protocol."<init>":()V
       4: aload_0
       5: ldc2_w        #6                  // long 3000l
       8: putfield      #8                  // Field timeout:J
      11: aload_0
      12: iconst_5
      13: putfield      #9                  // Field max_tries:I
      16: aload_0
      17: iconst_1
      18: putfield      #10                 // Field msg_counts_as_heartbeat:Z
      21: aload_0
      22: new           #11                 // class org/jgroups/util/BoundedList
      25: dup
      26: bipush        20
      28: invokespecial #12                 // Method org/jgroups/util/BoundedList."<init>":(I)V
      31: putfield      #13                 // Field suspect_history:Lorg/jgroups/util/BoundedList;
      34: aload_0
      35: invokestatic  #14                 // Method java/lang/System.nanoTime:()J
      38: putfield      #15                 // Field last_ack:J
      41: aload_0
      42: new           #16                 // class java/util/concurrent/atomic/AtomicInteger
      45: dup
      46: iconst_0
      47: invokespecial #17                 // Method java/util/concurrent/atomic/AtomicInteger."<init>":(I)V
      50: putfield      #18                 // Field num_tries:Ljava/util/concurrent/atomic/AtomicInteger;
      53: aload_0
      54: new           #19                 // class java/util/concurrent/locks/ReentrantLock
      57: dup
      58: invokespecial #20                 // Method java/util/concurrent/locks/ReentrantLock."<init>":()V
      61: putfield      #21                 // Field lock:Ljava/util/concurrent/locks/Lock;
      64: aload_0
      65: new           #22                 // class java/util/ArrayList
      68: dup
      69: invokespecial #23                 // Method java/util/ArrayList."<init>":()V
      72: putfield      #24                 // Field members:Ljava/util/List;
      75: aload_0
      76: new           #22                 // class java/util/ArrayList
      79: dup
      80: invokespecial #23                 // Method java/util/ArrayList."<init>":()V
      83: putfield      #25                 // Field pingable_mbrs:Ljava/util/List;
      86: aload_0
      87: aconst_null
      88: putfield      #26                 // Field monitor_future:Ljava/util/concurrent/Future;
      91: aload_0
      92: new           #27                 // class org/jgroups/protocols/FD$Broadcaster
      95: dup
      96: aload_0
      97: invokespecial #28                 // Method org/jgroups/protocols/FD$Broadcaster."<init>":(Lorg/jgroups/protocols/FD;)V
     100: putfield      #29                 // Field bcast_task:Lorg/jgroups/protocols/FD$Broadcaster;
     103: return

  public java.lang.String getLocalAddress();
    Code:
       0: aload_0
       1: getfield      #30                 // Field local_addr:Lorg/jgroups/Address;
       4: ifnull        17
       7: aload_0
       8: getfield      #30                 // Field local_addr:Lorg/jgroups/Address;
      11: invokevirtual #31                 // Method java/lang/Object.toString:()Ljava/lang/String;
      14: goto          19
      17: ldc           #32                 // String null
      19: areturn

  public java.lang.String getMembers();
    Code:
       0: aload_0
       1: getfield      #24                 // Field members:Ljava/util/List;
       4: ifnull        17
       7: aload_0
       8: getfield      #24                 // Field members:Ljava/util/List;
      11: invokevirtual #31                 // Method java/lang/Object.toString:()Ljava/lang/String;
      14: goto          19
      17: ldc           #32                 // String null
      19: areturn

  public java.lang.String getPingableMembers();
    Code:
       0: aload_0
       1: getfield      #25                 // Field pingable_mbrs:Ljava/util/List;
       4: ifnull        17
       7: aload_0
       8: getfield      #25                 // Field pingable_mbrs:Ljava/util/List;
      11: invokevirtual #31                 // Method java/lang/Object.toString:()Ljava/lang/String;
      14: goto          19
      17: ldc           #32                 // String null
      19: areturn

  public java.lang.String getPingDest();
    Code:
       0: aload_0
       1: getfield      #33                 // Field ping_dest:Lorg/jgroups/Address;
       4: ifnull        17
       7: aload_0
       8: getfield      #33                 // Field ping_dest:Lorg/jgroups/Address;
      11: invokevirtual #31                 // Method java/lang/Object.toString:()Ljava/lang/String;
      14: goto          19
      17: ldc           #32                 // String null
      19: areturn

  public int getNumberOfHeartbeatsSent();
    Code:
       0: aload_0
       1: getfield      #34                 // Field num_heartbeats:I
       4: ireturn

  public int getNumSuspectEventsGenerated();
    Code:
       0: aload_0
       1: getfield      #35                 // Field num_suspect_events:I
       4: ireturn

  public long getTimeout();
    Code:
       0: aload_0
       1: getfield      #8                  // Field timeout:J
       4: lreturn

  public void setTimeout(long);
    Code:
       0: aload_0
       1: lload_1
       2: putfield      #8                  // Field timeout:J
       5: return

  public int getMaxTries();
    Code:
       0: aload_0
       1: getfield      #9                  // Field max_tries:I
       4: ireturn

  public void setMaxTries(int);
    Code:
       0: aload_0
       1: iload_1
       2: putfield      #9                  // Field max_tries:I
       5: return

  public int getCurrentNumTries();
    Code:
       0: aload_0
       1: getfield      #18                 // Field num_tries:Ljava/util/concurrent/atomic/AtomicInteger;
       4: invokevirtual #36                 // Method java/util/concurrent/atomic/AtomicInteger.get:()I
       7: ireturn

  public java.lang.String printSuspectHistory();
    Code:
       0: new           #37                 // class java/lang/StringBuilder
       3: dup
       4: invokespecial #38                 // Method java/lang/StringBuilder."<init>":()V
       7: astore_1
       8: aload_0
       9: getfield      #13                 // Field suspect_history:Lorg/jgroups/util/BoundedList;
      12: invokevirtual #39                 // Method org/jgroups/util/BoundedList.iterator:()Ljava/util/Iterator;
      15: astore_2
      16: aload_2
      17: invokeinterface #40,  1           // InterfaceMethod java/util/Iterator.hasNext:()Z
      22: ifeq          49
      25: aload_2
      26: invokeinterface #41,  1           // InterfaceMethod java/util/Iterator.next:()Ljava/lang/Object;
      31: checkcast     #42                 // class java/lang/String
      34: astore_3
      35: aload_1
      36: aload_3
      37: invokevirtual #43                 // Method java/lang/StringBuilder.append:(Ljava/lang/String;)Ljava/lang/StringBuilder;
      40: ldc           #44                 // String \n
      42: invokevirtual #43                 // Method java/lang/StringBuilder.append:(Ljava/lang/String;)Ljava/lang/StringBuilder;
      45: pop
      46: goto          16
      49: aload_1
      50: invokevirtual #45                 // Method java/lang/StringBuilder.toString:()Ljava/lang/String;
      53: areturn

  public void resetStats();
    Code:
       0: aload_0
       1: aload_0
       2: iconst_0
       3: dup_x1
       4: putfield      #35                 // Field num_suspect_events:I
       7: putfield      #34                 // Field num_heartbeats:I
      10: aload_0
      11: getfield      #13                 // Field suspect_history:Lorg/jgroups/util/BoundedList;
      14: invokevirtual #46                 // Method org/jgroups/util/BoundedList.clear:()V
      17: return

  public void init() throws java.lang.Exception;
    Code:
       0: aload_0
       1: aload_0
       2: invokevirtual #47                 // Method getTransport:()Lorg/jgroups/protocols/TP;
       5: invokevirtual #48                 // Method org/jgroups/protocols/TP.getTimer:()Lorg/jgroups/util/TimeScheduler;
       8: putfield      #49                 // Field timer:Lorg/jgroups/util/TimeScheduler;
      11: aload_0
      12: getfield      #49                 // Field timer:Lorg/jgroups/util/TimeScheduler;
      15: ifnonnull     28
      18: new           #50                 // class java/lang/Exception
      21: dup
      22: ldc           #51                 // String timer cannot be retrieved
      24: invokespecial #52                 // Method java/lang/Exception."<init>":(Ljava/lang/String;)V
      27: athrow
      28: return

  public void stop();
    Code:
       0: aload_0
       1: getfield      #21                 // Field lock:Ljava/util/concurrent/locks/Lock;
       4: invokeinterface #53,  1           // InterfaceMethod java/util/concurrent/locks/Lock.lock:()V
       9: aload_0
      10: aconst_null
      11: putfield      #33                 // Field ping_dest:Lorg/jgroups/Address;
      14: aload_0
      15: invokevirtual #54                 // Method stopMonitor:()V
      18: aload_0
      19: getfield      #21                 // Field lock:Ljava/util/concurrent/locks/Lock;
      22: invokeinterface #55,  1           // InterfaceMethod java/util/concurrent/locks/Lock.unlock:()V
      27: goto          42
      30: astore_1
      31: aload_0
      32: getfield      #21                 // Field lock:Ljava/util/concurrent/locks/Lock;
      35: invokeinterface #55,  1           // InterfaceMethod java/util/concurrent/locks/Lock.unlock:()V
      40: aload_1
      41: athrow
      42: return
    Exception table:
       from    to  target type
           9    18    30   any
          30    31    30   any

  protected org.jgroups.Address getPingDest(java.util.List<org.jgroups.Address>);
    Code:
       0: aconst_null
       1: astore_3
       2: aload_1
       3: ifnull        23
       6: aload_1
       7: invokeinterface #56,  1           // InterfaceMethod java/util/List.size:()I
      12: iconst_2
      13: if_icmplt     23
      16: aload_0
      17: getfield      #30                 // Field local_addr:Lorg/jgroups/Address;
      20: ifnonnull     25
      23: aconst_null
      24: areturn
      25: iconst_0
      26: istore        4
      28: iload         4
      30: aload_1
      31: invokeinterface #56,  1           // InterfaceMethod java/util/List.size:()I
      36: if_icmpge     112
      39: aload_1
      40: iload         4
      42: invokeinterface #57,  2           // InterfaceMethod java/util/List.get:(I)Ljava/lang/Object;
      47: checkcast     #58                 // class org/jgroups/Address
      50: astore_2
      51: aload_0
      52: getfield      #30                 // Field local_addr:Lorg/jgroups/Address;
      55: aload_2
      56: invokevirtual #59                 // Method java/lang/Object.equals:(Ljava/lang/Object;)Z
      59: ifeq          106
      62: iload         4
      64: iconst_1
      65: iadd
      66: aload_1
      67: invokeinterface #56,  1           // InterfaceMethod java/util/List.size:()I
      72: if_icmplt     89
      75: aload_1
      76: iconst_0
      77: invokeinterface #57,  2           // InterfaceMethod java/util/List.get:(I)Ljava/lang/Object;
      82: checkcast     #58                 // class org/jgroups/Address
      85: astore_3
      86: goto          112
      89: aload_1
      90: iload         4
      92: iconst_1
      93: iadd
      94: invokeinterface #57,  2           // InterfaceMethod java/util/List.get:(I)Ljava/lang/Object;
      99: checkcast     #58                 // class org/jgroups/Address
     102: astore_3
     103: goto          112
     106: iinc          4, 1
     109: goto          28
     112: aload_3
     113: areturn

  public void stopFailureDetection();
    Code:
       0: aload_0
       1: invokevirtual #54                 // Method stopMonitor:()V
       4: return

  public void startFailureDetection();
    Code:
       0: aload_0
       1: invokevirtual #60                 // Method startMonitor:()V
       4: return

  protected void startMonitor();
    Code:
       0: aload_0
       1: getfield      #26                 // Field monitor_future:Ljava/util/concurrent/Future;
       4: ifnull        19
       7: aload_0
       8: getfield      #26                 // Field monitor_future:Ljava/util/concurrent/Future;
      11: invokeinterface #61,  1           // InterfaceMethod java/util/concurrent/Future.isDone:()Z
      16: ifeq          66
      19: aload_0
      20: invokestatic  #14                 // Method java/lang/System.nanoTime:()J
      23: putfield      #15                 // Field last_ack:J
      26: aload_0
      27: aload_0
      28: getfield      #49                 // Field timer:Lorg/jgroups/util/TimeScheduler;
      31: new           #62                 // class org/jgroups/protocols/FD$Monitor
      34: dup
      35: aload_0
      36: invokespecial #63                 // Method org/jgroups/protocols/FD$Monitor."<init>":(Lorg/jgroups/protocols/FD;)V
      39: aload_0
      40: getfield      #8                  // Field timeout:J
      43: aload_0
      44: getfield      #8                  // Field timeout:J
      47: getstatic     #64                 // Field java/util/concurrent/TimeUnit.MILLISECONDS:Ljava/util/concurrent/TimeUnit;
      50: invokeinterface #65,  7           // InterfaceMethod org/jgroups/util/TimeScheduler.scheduleWithFixedDelay:(Ljava/lang/Runnable;JJLjava/util/concurrent/TimeUnit;)Ljava/util/concurrent/Future;
      55: putfield      #26                 // Field monitor_future:Ljava/util/concurrent/Future;
      58: aload_0
      59: getfield      #18                 // Field num_tries:Ljava/util/concurrent/atomic/AtomicInteger;
      62: iconst_1
      63: invokevirtual #66                 // Method java/util/concurrent/atomic/AtomicInteger.set:(I)V
      66: return

  protected void stopMonitor();
    Code:
       0: aload_0
       1: getfield      #26                 // Field monitor_future:Ljava/util/concurrent/Future;
       4: ifnull        23
       7: aload_0
       8: getfield      #26                 // Field monitor_future:Ljava/util/concurrent/Future;
      11: iconst_1
      12: invokeinterface #67,  2           // InterfaceMethod java/util/concurrent/Future.cancel:(Z)Z
      17: pop
      18: aload_0
      19: aconst_null
      20: putfield      #26                 // Field monitor_future:Ljava/util/concurrent/Future;
      23: return

  public boolean isMonitorRunning();
    Code:
       0: aload_0
       1: getfield      #26                 // Field monitor_future:Ljava/util/concurrent/Future;
       4: ifnull        23
       7: aload_0
       8: getfield      #26                 // Field monitor_future:Ljava/util/concurrent/Future;
      11: invokeinterface #61,  1           // InterfaceMethod java/util/concurrent/Future.isDone:()Z
      16: ifne          23
      19: iconst_1
      20: goto          24
      23: iconst_0
      24: ireturn

  public java.lang.Object up(org.jgroups.Event);
    Code:
       0: aload_1
       1: invokevirtual #68                 // Method org/jgroups/Event.getType:()I
       4: lookupswitch  { // 1
                     1: 24
               default: 444
          }
      24: aload_1
      25: invokevirtual #69                 // Method org/jgroups/Event.getArg:()Ljava/lang/Object;
      28: checkcast     #70                 // class org/jgroups/Message
      31: astore_2
      32: aload_2
      33: aload_0
      34: getfield      #3                  // Field id:S
      37: invokevirtual #71                 // Method org/jgroups/Message.getHeader:(S)Lorg/jgroups/Header;
      40: checkcast     #72                 // class org/jgroups/protocols/FD$FdHeader
      43: astore_3
      44: aload_3
      45: ifnonnull     66
      48: aload_0
      49: getfield      #10                 // Field msg_counts_as_heartbeat:Z
      52: ifeq          444
      55: aload_0
      56: aload_2
      57: invokevirtual #73                 // Method org/jgroups/Message.getSrc:()Lorg/jgroups/Address;
      60: invokevirtual #74                 // Method updateTimestamp:(Lorg/jgroups/Address;)V
      63: goto          444
      66: aload_3
      67: getfield      #75                 // Field org/jgroups/protocols/FD$FdHeader.type:B
      70: tableswitch   { // 0 to 3
                     0: 100
                     1: 142
                     2: 153
                     3: 365
               default: 442
          }
     100: aload_2
     101: invokevirtual #73                 // Method org/jgroups/Message.getSrc:()Lorg/jgroups/Address;
     104: astore        4
     106: aload_0
     107: getfield      #2                  // Field log:Lorg/jgroups/logging/Log;
     110: ldc           #76                 // String %s: received are-you-alive from %s, sending response
     112: iconst_2
     113: anewarray     #77                 // class java/lang/Object
     116: dup
     117: iconst_0
     118: aload_0
     119: getfield      #30                 // Field local_addr:Lorg/jgroups/Address;
     122: aastore
     123: dup
     124: iconst_1
     125: aload         4
     127: aastore
     128: invokeinterface #78,  3           // InterfaceMethod org/jgroups/logging/Log.trace:(Ljava/lang/String;[Ljava/lang/Object;)V
     133: aload_0
     134: aload         4
     136: invokevirtual #79                 // Method sendHeartbeatResponse:(Lorg/jgroups/Address;)V
     139: goto          442
     142: aload_0
     143: aload_3
     144: getfield      #80                 // Field org/jgroups/protocols/FD$FdHeader.from:Lorg/jgroups/Address;
     147: invokevirtual #74                 // Method updateTimestamp:(Lorg/jgroups/Address;)V
     150: goto          442
     153: aload_3
     154: getfield      #81                 // Field org/jgroups/protocols/FD$FdHeader.mbrs:Ljava/util/Collection;
     157: ifnonnull     162
     160: aconst_null
     161: areturn
     162: aload_0
     163: getfield      #2                  // Field log:Lorg/jgroups/logging/Log;
     166: ldc           #82                 // String %s: received suspect message: %s
     168: iconst_2
     169: anewarray     #77                 // class java/lang/Object
     172: dup
     173: iconst_0
     174: aload_0
     175: getfield      #30                 // Field local_addr:Lorg/jgroups/Address;
     178: aastore
     179: dup
     180: iconst_1
     181: aload_3
     182: aastore
     183: invokeinterface #78,  3           // InterfaceMethod org/jgroups/logging/Log.trace:(Ljava/lang/String;[Ljava/lang/Object;)V
     188: aload_3
     189: getfield      #81                 // Field org/jgroups/protocols/FD$FdHeader.mbrs:Ljava/util/Collection;
     192: invokeinterface #83,  1           // InterfaceMethod java/util/Collection.iterator:()Ljava/util/Iterator;
     197: astore        5
     199: aload         5
     201: invokeinterface #40,  1           // InterfaceMethod java/util/Iterator.hasNext:()Z
     206: ifeq          362
     209: aload         5
     211: invokeinterface #41,  1           // InterfaceMethod java/util/Iterator.next:()Ljava/lang/Object;
     216: checkcast     #58                 // class org/jgroups/Address
     219: astore        6
     221: aload_0
     222: getfield      #30                 // Field local_addr:Lorg/jgroups/Address;
     225: ifnull        280
     228: aload         6
     230: aload_0
     231: getfield      #30                 // Field local_addr:Lorg/jgroups/Address;
     234: invokevirtual #59                 // Method java/lang/Object.equals:(Ljava/lang/Object;)Z
     237: ifeq          280
     240: aload_0
     241: getfield      #2                  // Field log:Lorg/jgroups/logging/Log;
     244: ldc           #84                 // String %s: I was suspected by %s; ignoring the SUSPECT message and sending back a HEARTBEAT_ACK
     246: iconst_2
     247: anewarray     #77                 // class java/lang/Object
     250: dup
     251: iconst_0
     252: aload_0
     253: getfield      #30                 // Field local_addr:Lorg/jgroups/Address;
     256: aastore
     257: dup
     258: iconst_1
     259: aload_2
     260: invokevirtual #85                 // Method org/jgroups/Message.src:()Lorg/jgroups/Address;
     263: aastore
     264: invokeinterface #86,  3           // InterfaceMethod org/jgroups/logging/Log.warn:(Ljava/lang/String;[Ljava/lang/Object;)V
     269: aload_0
     270: aload_2
     271: invokevirtual #73                 // Method org/jgroups/Message.getSrc:()Lorg/jgroups/Address;
     274: invokevirtual #79                 // Method sendHeartbeatResponse:(Lorg/jgroups/Address;)V
     277: goto          199
     280: aload_0
     281: getfield      #21                 // Field lock:Ljava/util/concurrent/locks/Lock;
     284: invokeinterface #53,  1           // InterfaceMethod java/util/concurrent/locks/Lock.lock:()V
     289: aload_0
     290: aload         6
     292: invokevirtual #87                 // Method computePingDest:(Lorg/jgroups/Address;)V
     295: aload_0
     296: getfield      #21                 // Field lock:Ljava/util/concurrent/locks/Lock;
     299: invokeinterface #55,  1           // InterfaceMethod java/util/concurrent/locks/Lock.unlock:()V
     304: goto          321
     307: astore        7
     309: aload_0
     310: getfield      #21                 // Field lock:Ljava/util/concurrent/locks/Lock;
     313: invokeinterface #55,  1           // InterfaceMethod java/util/concurrent/locks/Lock.unlock:()V
     318: aload         7
     320: athrow
     321: aload_0
     322: getfield      #88                 // Field up_prot:Lorg/jgroups/stack/Protocol;
     325: new           #89                 // class org/jgroups/Event
     328: dup
     329: bipush        9
     331: aload         6
     333: invokespecial #90                 // Method org/jgroups/Event."<init>":(ILjava/lang/Object;)V
     336: invokevirtual #91                 // Method org/jgroups/stack/Protocol.up:(Lorg/jgroups/Event;)Ljava/lang/Object;
     339: pop
     340: aload_0
     341: getfield      #1                  // Field down_prot:Lorg/jgroups/stack/Protocol;
     344: new           #89                 // class org/jgroups/Event
     347: dup
     348: bipush        9
     350: aload         6
     352: invokespecial #90                 // Method org/jgroups/Event."<init>":(ILjava/lang/Object;)V
     355: invokevirtual #92                 // Method org/jgroups/stack/Protocol.down:(Lorg/jgroups/Event;)Ljava/lang/Object;
     358: pop
     359: goto          199
     362: goto          442
     365: aload_3
     366: getfield      #81                 // Field org/jgroups/protocols/FD$FdHeader.mbrs:Ljava/util/Collection;
     369: ifnonnull     374
     372: aconst_null
     373: areturn
     374: aload_0
     375: getfield      #2                  // Field log:Lorg/jgroups/logging/Log;
     378: ldc           #93                 // String %s: received unsuspect message: %s
     380: iconst_2
     381: anewarray     #77                 // class java/lang/Object
     384: dup
     385: iconst_0
     386: aload_0
     387: getfield      #30                 // Field local_addr:Lorg/jgroups/Address;
     390: aastore
     391: dup
     392: iconst_1
     393: aload_3
     394: aastore
     395: invokeinterface #78,  3           // InterfaceMethod org/jgroups/logging/Log.trace:(Ljava/lang/String;[Ljava/lang/Object;)V
     400: aload_3
     401: getfield      #81                 // Field org/jgroups/protocols/FD$FdHeader.mbrs:Ljava/util/Collection;
     404: invokeinterface #83,  1           // InterfaceMethod java/util/Collection.iterator:()Ljava/util/Iterator;
     409: astore        5
     411: aload         5
     413: invokeinterface #40,  1           // InterfaceMethod java/util/Iterator.hasNext:()Z
     418: ifeq          442
     421: aload         5
     423: invokeinterface #41,  1           // InterfaceMethod java/util/Iterator.next:()Ljava/lang/Object;
     428: checkcast     #58                 // class org/jgroups/Address
     431: astore        6
     433: aload_0
     434: aload         6
     436: invokevirtual #94                 // Method unsuspect:(Lorg/jgroups/Address;)V
     439: goto          411
     442: aconst_null
     443: areturn
     444: aload_0
     445: getfield      #88                 // Field up_prot:Lorg/jgroups/stack/Protocol;
     448: aload_1
     449: invokevirtual #91                 // Method org/jgroups/stack/Protocol.up:(Lorg/jgroups/Event;)Ljava/lang/Object;
     452: areturn
    Exception table:
       from    to  target type
         289   295   307   any
         307   309   307   any

  public void up(org.jgroups.util.MessageBatch);
    Code:
       0: aload_1
       1: aload_0
       2: getfield      #3                  // Field id:S
       5: iconst_1
       6: invokevirtual #95                 // Method org/jgroups/util/MessageBatch.getMatchingMessages:(SZ)Ljava/util/Collection;
       9: astore_2
      10: iconst_0
      11: istore_3
      12: aload_2
      13: ifnull        92
      16: aload_2
      17: invokeinterface #83,  1           // InterfaceMethod java/util/Collection.iterator:()Ljava/util/Iterator;
      22: astore        4
      24: aload         4
      26: invokeinterface #40,  1           // InterfaceMethod java/util/Iterator.hasNext:()Z
      31: ifeq          92
      34: aload         4
      36: invokeinterface #41,  1           // InterfaceMethod java/util/Iterator.next:()Ljava/lang/Object;
      41: checkcast     #70                 // class org/jgroups/Message
      44: astore        5
      46: aload         5
      48: aload_0
      49: getfield      #3                  // Field id:S
      52: invokevirtual #71                 // Method org/jgroups/Message.getHeader:(S)Lorg/jgroups/Header;
      55: checkcast     #72                 // class org/jgroups/protocols/FD$FdHeader
      58: astore        6
      60: aload         6
      62: getfield      #75                 // Field org/jgroups/protocols/FD$FdHeader.type:B
      65: iconst_1
      66: if_icmpne     74
      69: iconst_1
      70: istore_3
      71: goto          89
      74: aload_0
      75: new           #89                 // class org/jgroups/Event
      78: dup
      79: iconst_1
      80: aload         5
      82: invokespecial #90                 // Method org/jgroups/Event."<init>":(ILjava/lang/Object;)V
      85: invokevirtual #96                 // Method up:(Lorg/jgroups/Event;)Ljava/lang/Object;
      88: pop
      89: goto          24
      92: iload_3
      93: ifne          110
      96: aload_0
      97: getfield      #10                 // Field msg_counts_as_heartbeat:Z
     100: ifeq          118
     103: aload_1
     104: invokevirtual #97                 // Method org/jgroups/util/MessageBatch.sender:()Lorg/jgroups/Address;
     107: ifnull        118
     110: aload_0
     111: aload_1
     112: invokevirtual #97                 // Method org/jgroups/util/MessageBatch.sender:()Lorg/jgroups/Address;
     115: invokevirtual #74                 // Method updateTimestamp:(Lorg/jgroups/Address;)V
     118: aload_1
     119: invokevirtual #98                 // Method org/jgroups/util/MessageBatch.isEmpty:()Z
     122: ifne          133
     125: aload_0
     126: getfield      #88                 // Field up_prot:Lorg/jgroups/stack/Protocol;
     129: aload_1
     130: invokevirtual #99                 // Method org/jgroups/stack/Protocol.up:(Lorg/jgroups/util/MessageBatch;)V
     133: return

  public java.lang.Object down(org.jgroups.Event);
    Code:
       0: aload_1
       1: invokevirtual #68                 // Method org/jgroups/Event.getType:()I
       4: lookupswitch  { // 3
                     6: 40
                     8: 290
                    51: 159
               default: 301
          }
      40: aload_0
      41: getfield      #1                  // Field down_prot:Lorg/jgroups/stack/Protocol;
      44: aload_1
      45: invokevirtual #92                 // Method org/jgroups/stack/Protocol.down:(Lorg/jgroups/Event;)Ljava/lang/Object;
      48: astore_2
      49: aload_1
      50: invokevirtual #69                 // Method org/jgroups/Event.getArg:()Ljava/lang/Object;
      53: checkcast     #100                // class org/jgroups/View
      56: astore_3
      57: aload_0
      58: getfield      #21                 // Field lock:Ljava/util/concurrent/locks/Lock;
      61: invokeinterface #53,  1           // InterfaceMethod java/util/concurrent/locks/Lock.lock:()V
      66: aload_0
      67: getfield      #24                 // Field members:Ljava/util/List;
      70: invokeinterface #101,  1          // InterfaceMethod java/util/List.clear:()V
      75: aload_0
      76: getfield      #24                 // Field members:Ljava/util/List;
      79: aload_3
      80: invokevirtual #102                // Method org/jgroups/View.getMembers:()Ljava/util/List;
      83: invokeinterface #103,  2          // InterfaceMethod java/util/List.addAll:(Ljava/util/Collection;)Z
      88: pop
      89: aload_0
      90: getfield      #29                 // Field bcast_task:Lorg/jgroups/protocols/FD$Broadcaster;
      93: aload_0
      94: getfield      #24                 // Field members:Ljava/util/List;
      97: invokevirtual #104                // Method org/jgroups/protocols/FD$Broadcaster.adjustSuspectedMembers:(Ljava/util/List;)V
     100: aload_0
     101: aconst_null
     102: invokevirtual #87                 // Method computePingDest:(Lorg/jgroups/Address;)V
     105: aload_3
     106: invokevirtual #105                // Method org/jgroups/View.size:()I
     109: iconst_1
     110: if_icmpgt     120
     113: aload_0
     114: invokevirtual #54                 // Method stopMonitor:()V
     117: goto          131
     120: aload_0
     121: invokevirtual #106                // Method isMonitorRunning:()Z
     124: ifne          131
     127: aload_0
     128: invokevirtual #60                 // Method startMonitor:()V
     131: aload_0
     132: getfield      #21                 // Field lock:Ljava/util/concurrent/locks/Lock;
     135: invokeinterface #55,  1           // InterfaceMethod java/util/concurrent/locks/Lock.unlock:()V
     140: goto          157
     143: astore        4
     145: aload_0
     146: getfield      #21                 // Field lock:Ljava/util/concurrent/locks/Lock;
     149: invokeinterface #55,  1           // InterfaceMethod java/util/concurrent/locks/Lock.unlock:()V
     154: aload         4
     156: athrow
     157: aload_2
     158: areturn
     159: new           #72                 // class org/jgroups/protocols/FD$FdHeader
     162: dup
     163: iconst_3
     164: invokespecial #107                // Method org/jgroups/protocols/FD$FdHeader."<init>":(B)V
     167: astore        4
     169: aload         4
     171: new           #22                 // class java/util/ArrayList
     174: dup
     175: invokespecial #23                 // Method java/util/ArrayList."<init>":()V
     178: putfield      #81                 // Field org/jgroups/protocols/FD$FdHeader.mbrs:Ljava/util/Collection;
     181: aload         4
     183: getfield      #81                 // Field org/jgroups/protocols/FD$FdHeader.mbrs:Ljava/util/Collection;
     186: aload_1
     187: invokevirtual #69                 // Method org/jgroups/Event.getArg:()Ljava/lang/Object;
     190: checkcast     #58                 // class org/jgroups/Address
     193: invokeinterface #108,  2          // InterfaceMethod java/util/Collection.add:(Ljava/lang/Object;)Z
     198: pop
     199: aload         4
     201: aload_0
     202: getfield      #30                 // Field local_addr:Lorg/jgroups/Address;
     205: putfield      #80                 // Field org/jgroups/protocols/FD$FdHeader.from:Lorg/jgroups/Address;
     208: new           #70                 // class org/jgroups/Message
     211: dup
     212: invokespecial #109                // Method org/jgroups/Message."<init>":()V
     215: iconst_1
     216: anewarray     #110                // class org/jgroups/Message$Flag
     219: dup
     220: iconst_0
     221: getstatic     #111                // Field org/jgroups/Message$Flag.INTERNAL:Lorg/jgroups/Message$Flag;
     224: aastore
     225: invokevirtual #112                // Method org/jgroups/Message.setFlag:([Lorg/jgroups/Message$Flag;)Lorg/jgroups/Message;
     228: aload_0
     229: getfield      #3                  // Field id:S
     232: aload         4
     234: invokevirtual #113                // Method org/jgroups/Message.putHeader:(SLorg/jgroups/Header;)Lorg/jgroups/Message;
     237: astore        5
     239: aload_0
     240: getfield      #2                  // Field log:Lorg/jgroups/logging/Log;
     243: ldc           #114                // String %s: broadcasting UNSUSPECT message (mbrs=%s)
     245: iconst_2
     246: anewarray     #77                 // class java/lang/Object
     249: dup
     250: iconst_0
     251: aload_0
     252: getfield      #30                 // Field local_addr:Lorg/jgroups/Address;
     255: aastore
     256: dup
     257: iconst_1
     258: aload         4
     260: getfield      #81                 // Field org/jgroups/protocols/FD$FdHeader.mbrs:Ljava/util/Collection;
     263: aastore
     264: invokeinterface #78,  3           // InterfaceMethod org/jgroups/logging/Log.trace:(Ljava/lang/String;[Ljava/lang/Object;)V
     269: aload_0
     270: getfield      #1                  // Field down_prot:Lorg/jgroups/stack/Protocol;
     273: new           #89                 // class org/jgroups/Event
     276: dup
     277: iconst_1
     278: aload         5
     280: invokespecial #90                 // Method org/jgroups/Event."<init>":(ILjava/lang/Object;)V
     283: invokevirtual #92                 // Method org/jgroups/stack/Protocol.down:(Lorg/jgroups/Event;)Ljava/lang/Object;
     286: pop
     287: goto          301
     290: aload_0
     291: aload_1
     292: invokevirtual #69                 // Method org/jgroups/Event.getArg:()Ljava/lang/Object;
     295: checkcast     #58                 // class org/jgroups/Address
     298: putfield      #30                 // Field local_addr:Lorg/jgroups/Address;
     301: aload_0
     302: getfield      #1                  // Field down_prot:Lorg/jgroups/stack/Protocol;
     305: aload_1
     306: invokevirtual #92                 // Method org/jgroups/stack/Protocol.down:(Lorg/jgroups/Event;)Ljava/lang/Object;
     309: areturn
    Exception table:
       from    to  target type
          66   131   143   any
         143   145   143   any

  protected void sendHeartbeatResponse(org.jgroups.Address);
    Code:
       0: new           #70                 // class org/jgroups/Message
       3: dup
       4: aload_1
       5: invokespecial #115                // Method org/jgroups/Message."<init>":(Lorg/jgroups/Address;)V
       8: iconst_1
       9: anewarray     #110                // class org/jgroups/Message$Flag
      12: dup
      13: iconst_0
      14: getstatic     #111                // Field org/jgroups/Message$Flag.INTERNAL:Lorg/jgroups/Message$Flag;
      17: aastore
      18: invokevirtual #112                // Method org/jgroups/Message.setFlag:([Lorg/jgroups/Message$Flag;)Lorg/jgroups/Message;
      21: astore_2
      22: new           #72                 // class org/jgroups/protocols/FD$FdHeader
      25: dup
      26: iconst_1
      27: invokespecial #107                // Method org/jgroups/protocols/FD$FdHeader."<init>":(B)V
      30: astore_3
      31: aload_3
      32: aload_0
      33: getfield      #30                 // Field local_addr:Lorg/jgroups/Address;
      36: putfield      #80                 // Field org/jgroups/protocols/FD$FdHeader.from:Lorg/jgroups/Address;
      39: aload_2
      40: aload_0
      41: getfield      #3                  // Field id:S
      44: aload_3
      45: invokevirtual #113                // Method org/jgroups/Message.putHeader:(SLorg/jgroups/Header;)Lorg/jgroups/Message;
      48: pop
      49: aload_0
      50: getfield      #1                  // Field down_prot:Lorg/jgroups/stack/Protocol;
      53: new           #89                 // class org/jgroups/Event
      56: dup
      57: iconst_1
      58: aload_2
      59: invokespecial #90                 // Method org/jgroups/Event."<init>":(ILjava/lang/Object;)V
      62: invokevirtual #92                 // Method org/jgroups/stack/Protocol.down:(Lorg/jgroups/Event;)Ljava/lang/Object;
      65: pop
      66: return

  protected void unsuspect(org.jgroups.Address);
    Code:
       0: aload_0
       1: getfield      #21                 // Field lock:Ljava/util/concurrent/locks/Lock;
       4: invokeinterface #53,  1           // InterfaceMethod java/util/concurrent/locks/Lock.lock:()V
       9: aload_0
      10: getfield      #29                 // Field bcast_task:Lorg/jgroups/protocols/FD$Broadcaster;
      13: aload_1
      14: invokevirtual #116                // Method org/jgroups/protocols/FD$Broadcaster.removeSuspectedMember:(Lorg/jgroups/Address;)V
      17: aload_0
      18: aconst_null
      19: invokevirtual #87                 // Method computePingDest:(Lorg/jgroups/Address;)V
      22: aload_0
      23: getfield      #21                 // Field lock:Ljava/util/concurrent/locks/Lock;
      26: invokeinterface #55,  1           // InterfaceMethod java/util/concurrent/locks/Lock.unlock:()V
      31: goto          46
      34: astore_2
      35: aload_0
      36: getfield      #21                 // Field lock:Ljava/util/concurrent/locks/Lock;
      39: invokeinterface #55,  1           // InterfaceMethod java/util/concurrent/locks/Lock.unlock:()V
      44: aload_2
      45: athrow
      46: return
    Exception table:
       from    to  target type
           9    22    34   any
          34    35    34   any

  protected void updateTimestamp(org.jgroups.Address);
    Code:
       0: aload_1
       1: ifnull        30
       4: aload_1
       5: aload_0
       6: getfield      #33                 // Field ping_dest:Lorg/jgroups/Address;
       9: invokevirtual #59                 // Method java/lang/Object.equals:(Ljava/lang/Object;)Z
      12: ifeq          30
      15: aload_0
      16: invokestatic  #14                 // Method java/lang/System.nanoTime:()J
      19: putfield      #15                 // Field last_ack:J
      22: aload_0
      23: getfield      #18                 // Field num_tries:Ljava/util/concurrent/atomic/AtomicInteger;
      26: iconst_1
      27: invokevirtual #66                 // Method java/util/concurrent/atomic/AtomicInteger.set:(I)V
      30: return

  protected void computePingDest(org.jgroups.Address);
    Code:
       0: aload_1
       1: ifnull        18
       4: aload_0
       5: getfield      #25                 // Field pingable_mbrs:Ljava/util/List;
       8: aload_1
       9: invokeinterface #117,  2          // InterfaceMethod java/util/List.remove:(Ljava/lang/Object;)Z
      14: pop
      15: goto          58
      18: aload_0
      19: getfield      #25                 // Field pingable_mbrs:Ljava/util/List;
      22: invokeinterface #101,  1          // InterfaceMethod java/util/List.clear:()V
      27: aload_0
      28: getfield      #25                 // Field pingable_mbrs:Ljava/util/List;
      31: aload_0
      32: getfield      #24                 // Field members:Ljava/util/List;
      35: invokeinterface #103,  2          // InterfaceMethod java/util/List.addAll:(Ljava/util/Collection;)Z
      40: pop
      41: aload_0
      42: getfield      #25                 // Field pingable_mbrs:Ljava/util/List;
      45: aload_0
      46: getfield      #29                 // Field bcast_task:Lorg/jgroups/protocols/FD$Broadcaster;
      49: invokevirtual #118                // Method org/jgroups/protocols/FD$Broadcaster.getSuspectedMembers:()Ljava/util/List;
      52: invokeinterface #119,  2          // InterfaceMethod java/util/List.removeAll:(Ljava/util/Collection;)Z
      57: pop
      58: aload_0
      59: getfield      #33                 // Field ping_dest:Lorg/jgroups/Address;
      62: astore_2
      63: aload_0
      64: aload_0
      65: aload_0
      66: getfield      #25                 // Field pingable_mbrs:Ljava/util/List;
      69: invokevirtual #120                // Method getPingDest:(Ljava/util/List;)Lorg/jgroups/Address;
      72: putfield      #33                 // Field ping_dest:Lorg/jgroups/Address;
      75: aload_2
      76: aload_0
      77: getfield      #33                 // Field ping_dest:Lorg/jgroups/Address;
      80: invokestatic  #121                // Method org/jgroups/util/Util.different:(Ljava/lang/Object;Ljava/lang/Object;)Z
      83: ifeq          101
      86: aload_0
      87: getfield      #18                 // Field num_tries:Ljava/util/concurrent/atomic/AtomicInteger;
      90: iconst_1
      91: invokevirtual #66                 // Method java/util/concurrent/atomic/AtomicInteger.set:(I)V
      94: aload_0
      95: invokestatic  #14                 // Method java/lang/System.nanoTime:()J
      98: putfield      #15                 // Field last_ack:J
     101: return

  static org.jgroups.logging.Log access$000(org.jgroups.protocols.FD);
    Code:
       0: aload_0
       1: getfield      #2                  // Field log:Lorg/jgroups/logging/Log;
       4: areturn

  static short access$100(org.jgroups.protocols.FD);
    Code:
       0: aload_0
       1: getfield      #3                  // Field id:S
       4: ireturn

  static org.jgroups.logging.Log access$200(org.jgroups.protocols.FD);
    Code:
       0: aload_0
       1: getfield      #2                  // Field log:Lorg/jgroups/logging/Log;
       4: areturn

  static org.jgroups.stack.Protocol access$300(org.jgroups.protocols.FD);
    Code:
       0: aload_0
       1: getfield      #1                  // Field down_prot:Lorg/jgroups/stack/Protocol;
       4: areturn

  static org.jgroups.logging.Log access$400(org.jgroups.protocols.FD);
    Code:
       0: aload_0
       1: getfield      #2                  // Field log:Lorg/jgroups/logging/Log;
       4: areturn

  static boolean access$500(org.jgroups.protocols.FD);
    Code:
       0: aload_0
       1: getfield      #4                  // Field stats:Z
       4: ireturn

  static org.jgroups.logging.Log access$600(org.jgroups.protocols.FD);
    Code:
       0: aload_0
       1: getfield      #2                  // Field log:Lorg/jgroups/logging/Log;
       4: areturn

  static short access$700(org.jgroups.protocols.FD);
    Code:
       0: aload_0
       1: getfield      #3                  // Field id:S
       4: ireturn

  static org.jgroups.logging.Log access$800(org.jgroups.protocols.FD);
    Code:
       0: aload_0
       1: getfield      #2                  // Field log:Lorg/jgroups/logging/Log;
       4: areturn

  static org.jgroups.stack.Protocol access$900(org.jgroups.protocols.FD);
    Code:
       0: aload_0
       1: getfield      #1                  // Field down_prot:Lorg/jgroups/stack/Protocol;
       4: areturn
}
