Compiled from "SWIFT_PING.java"
class org.jgroups.protocols.SWIFT_PING$Keystone_V_2_0_Auth implements org.jgroups.protocols.SWIFT_PING$Authenticator {
  private static final java.lang.String JSON_RESPONSE_PARSING_SCRIPT;

  private static java.lang.Object scriptEngineLock;

  private static javax.script.ScriptEngine scriptEngine;

  private java.lang.String tenant;

  private java.net.URL authUrl;

  private java.lang.String username;

  private java.lang.String password;

  public org.jgroups.protocols.SWIFT_PING$Keystone_V_2_0_Auth(java.lang.String, java.net.URL, java.lang.String, java.lang.String);
    Code:
       0: aload_0
       1: invokespecial #1                  // Method java/lang/Object."<init>":()V
       4: aload_0
       5: aload_1
       6: putfield      #2                  // Field tenant:Ljava/lang/String;
       9: aload_0
      10: aload_2
      11: putfield      #3                  // Field authUrl:Ljava/net/URL;
      14: aload_0
      15: aload_3
      16: putfield      #4                  // Field username:Ljava/lang/String;
      19: aload_0
      20: aload         4
      22: putfield      #5                  // Field password:Ljava/lang/String;
      25: return

  public void validateParams();
    Code:
       0: aload_0
       1: getfield      #2                  // Field tenant:Ljava/lang/String;
       4: ldc           #6                  // String tenant
       6: invokestatic  #7                  // Method org/jgroups/protocols/SWIFT_PING$Utils.validateNotEmpty:(Ljava/lang/String;Ljava/lang/String;)V
       9: return

  public org.jgroups.protocols.SWIFT_PING$Credentials authenticate() throws java.lang.Exception;
    Code:
       0: new           #8                  // class org/jgroups/protocols/SWIFT_PING$ConnBuilder
       3: dup
       4: aload_0
       5: getfield      #3                  // Field authUrl:Ljava/net/URL;
       8: invokespecial #9                  // Method org/jgroups/protocols/SWIFT_PING$ConnBuilder."<init>":(Ljava/net/URL;)V
      11: ldc           #10                 // String Content-type
      13: ldc           #11                 // String application/json
      15: invokevirtual #12                 // Method org/jgroups/protocols/SWIFT_PING$ConnBuilder.addHeader:(Ljava/lang/String;Ljava/lang/String;)Lorg/jgroups/protocols/SWIFT_PING$ConnBuilder;
      18: ldc           #13                 // String Accept
      20: ldc           #11                 // String application/json
      22: invokevirtual #12                 // Method org/jgroups/protocols/SWIFT_PING$ConnBuilder.addHeader:(Ljava/lang/String;Ljava/lang/String;)Lorg/jgroups/protocols/SWIFT_PING$ConnBuilder;
      25: invokevirtual #14                 // Method org/jgroups/protocols/SWIFT_PING$ConnBuilder.getConnection:()Ljava/net/HttpURLConnection;
      28: astore_1
      29: new           #15                 // class java/lang/StringBuilder
      32: dup
      33: invokespecial #16                 // Method java/lang/StringBuilder."<init>":()V
      36: astore_2
      37: aload_2
      38: ldc           #17                 // String {\"auth\": {\"tenantName\": \"
      40: invokevirtual #18                 // Method java/lang/StringBuilder.append:(Ljava/lang/String;)Ljava/lang/StringBuilder;
      43: aload_0
      44: getfield      #2                  // Field tenant:Ljava/lang/String;
      47: invokevirtual #18                 // Method java/lang/StringBuilder.append:(Ljava/lang/String;)Ljava/lang/StringBuilder;
      50: ldc           #19                 // String \", \"passwordCredentials\": {\"username\": \"
      52: invokevirtual #18                 // Method java/lang/StringBuilder.append:(Ljava/lang/String;)Ljava/lang/StringBuilder;
      55: aload_0
      56: getfield      #4                  // Field username:Ljava/lang/String;
      59: invokevirtual #18                 // Method java/lang/StringBuilder.append:(Ljava/lang/String;)Ljava/lang/StringBuilder;
      62: ldc           #20                 // String \", \"password\": \"
      64: invokevirtual #18                 // Method java/lang/StringBuilder.append:(Ljava/lang/String;)Ljava/lang/StringBuilder;
      67: aload_0
      68: getfield      #5                  // Field password:Ljava/lang/String;
      71: invokevirtual #18                 // Method java/lang/StringBuilder.append:(Ljava/lang/String;)Ljava/lang/StringBuilder;
      74: ldc           #21                 // String \"}}}
      76: invokevirtual #18                 // Method java/lang/StringBuilder.append:(Ljava/lang/String;)Ljava/lang/StringBuilder;
      79: pop
      80: aload_1
      81: aload_2
      82: invokevirtual #22                 // Method java/lang/StringBuilder.toString:()Ljava/lang/String;
      85: invokevirtual #23                 // Method java/lang/String.getBytes:()[B
      88: iconst_1
      89: invokestatic  #24                 // Method org/jgroups/protocols/SWIFT_PING$Utils.doOperation:(Ljava/net/HttpURLConnection;[BZ)Lorg/jgroups/protocols/SWIFT_PING$HttpResponse;
      92: astore_3
      93: aload_3
      94: invokevirtual #25                 // Method org/jgroups/protocols/SWIFT_PING$HttpResponse.isSuccessCode:()Z
      97: ifeq          199
     100: aload_0
     101: new           #26                 // class java/lang/String
     104: dup
     105: aload_3
     106: invokestatic  #27                 // Method org/jgroups/protocols/SWIFT_PING$HttpResponse.access$000:(Lorg/jgroups/protocols/SWIFT_PING$HttpResponse;)[B
     109: ldc           #28                 // String UTF-8
     111: invokespecial #29                 // Method java/lang/String."<init>":([BLjava/lang/String;)V
     114: invokevirtual #30                 // Method parseJsonResponse:(Ljava/lang/String;)Ljava/util/Map;
     117: astore        4
     119: aload         4
     121: ldc           #31                 // String id
     123: invokeinterface #32,  2           // InterfaceMethod java/util/Map.get:(Ljava/lang/Object;)Ljava/lang/Object;
     128: checkcast     #26                 // class java/lang/String
     131: astore        5
     133: aload         4
     135: ldc           #33                 // String url
     137: invokeinterface #32,  2           // InterfaceMethod java/util/Map.get:(Ljava/lang/Object;)Ljava/lang/Object;
     142: checkcast     #26                 // class java/lang/String
     145: astore        6
     147: aload         5
     149: ifnonnull     162
     152: new           #34                 // class java/lang/IllegalStateException
     155: dup
     156: ldc           #35                 // String Missing token id in authentication response
     158: invokespecial #36                 // Method java/lang/IllegalStateException."<init>":(Ljava/lang/String;)V
     161: athrow
     162: aload         6
     164: ifnonnull     177
     167: new           #34                 // class java/lang/IllegalStateException
     170: dup
     171: ldc           #37                 // String Missing storage service URL in authentication response
     173: invokespecial #36                 // Method java/lang/IllegalStateException."<init>":(Ljava/lang/String;)V
     176: athrow
     177: invokestatic  #38                 // Method org/jgroups/protocols/SWIFT_PING.access$100:()Lorg/jgroups/logging/Log;
     180: ldc           #39                 // String Authentication successful
     182: invokeinterface #40,  2           // InterfaceMethod org/jgroups/logging/Log.trace:(Ljava/lang/String;)V
     187: new           #41                 // class org/jgroups/protocols/SWIFT_PING$Credentials
     190: dup
     191: aload         5
     193: aload         6
     195: invokespecial #42                 // Method org/jgroups/protocols/SWIFT_PING$Credentials."<init>":(Ljava/lang/String;Ljava/lang/String;)V
     198: areturn
     199: new           #34                 // class java/lang/IllegalStateException
     202: dup
     203: new           #15                 // class java/lang/StringBuilder
     206: dup
     207: invokespecial #16                 // Method java/lang/StringBuilder."<init>":()V
     210: ldc           #43                 // String Error authenticating to the service. Please check your credentials. Code =
     212: invokevirtual #18                 // Method java/lang/StringBuilder.append:(Ljava/lang/String;)Ljava/lang/StringBuilder;
     215: aload_3
     216: invokestatic  #44                 // Method org/jgroups/protocols/SWIFT_PING$HttpResponse.access$200:(Lorg/jgroups/protocols/SWIFT_PING$HttpResponse;)I
     219: invokevirtual #45                 // Method java/lang/StringBuilder.append:(I)Ljava/lang/StringBuilder;
     222: invokevirtual #22                 // Method java/lang/StringBuilder.toString:()Ljava/lang/String;
     225: invokespecial #36                 // Method java/lang/IllegalStateException."<init>":(Ljava/lang/String;)V
     228: athrow

  protected java.util.Map<java.lang.String, java.lang.String> parseJsonResponse(java.lang.String) throws javax.script.ScriptException;
    Code:
       0: getstatic     #46                 // Field scriptEngineLock:Ljava/lang/Object;
       3: dup
       4: astore_2
       5: monitorenter
       6: getstatic     #47                 // Field scriptEngine:Ljavax/script/ScriptEngine;
       9: ifnonnull     43
      12: new           #48                 // class javax/script/ScriptEngineManager
      15: dup
      16: invokespecial #49                 // Method javax/script/ScriptEngineManager."<init>":()V
      19: ldc           #50                 // String JavaScript
      21: invokevirtual #51                 // Method javax/script/ScriptEngineManager.getEngineByName:(Ljava/lang/String;)Ljavax/script/ScriptEngine;
      24: putstatic     #47                 // Field scriptEngine:Ljavax/script/ScriptEngine;
      27: getstatic     #47                 // Field scriptEngine:Ljavax/script/ScriptEngine;
      30: ifnonnull     43
      33: new           #52                 // class java/lang/RuntimeException
      36: dup
      37: ldc           #53                 // String Failed to load JavaScript script engine
      39: invokespecial #54                 // Method java/lang/RuntimeException."<init>":(Ljava/lang/String;)V
      42: athrow
      43: new           #55                 // class javax/script/SimpleBindings
      46: dup
      47: invokespecial #56                 // Method javax/script/SimpleBindings."<init>":()V
      50: astore_3
      51: aload_3
      52: ldc           #57                 // String json
      54: aload_1
      55: invokeinterface #58,  3           // InterfaceMethod javax/script/Bindings.put:(Ljava/lang/String;Ljava/lang/Object;)Ljava/lang/Object;
      60: pop
      61: getstatic     #47                 // Field scriptEngine:Ljavax/script/ScriptEngine;
      64: ldc           #59                 // String var response = JSON.parse(json);var result = {};result.id = response.access.token.id;var serviceCatalog = response.access.serviceCatalog;for (var i = 0; i < serviceCatalog.length; i++) {    var service = serviceCatalog[i];    if (service.type == \"object-store\") {        result.url = service.endpoints[0].publicURL;        break;    }}result;
      66: aload_3
      67: invokeinterface #60,  3           // InterfaceMethod javax/script/ScriptEngine.eval:(Ljava/lang/String;Ljavax/script/Bindings;)Ljava/lang/Object;
      72: checkcast     #61                 // class java/util/Map
      75: aload_2
      76: monitorexit
      77: areturn
      78: astore        4
      80: aload_2
      81: monitorexit
      82: aload         4
      84: athrow
    Exception table:
       from    to  target type
           6    77    78   any
          78    82    78   any

  static {};
    Code:
       0: new           #62                 // class java/lang/Object
       3: dup
       4: invokespecial #1                  // Method java/lang/Object."<init>":()V
       7: putstatic     #46                 // Field scriptEngineLock:Ljava/lang/Object;
      10: return
}
