Compiled from "TCP_NIO.java"
public class org.jgroups.protocols.TCP_NIO extends org.jgroups.protocols.BasicTCP implements org.jgroups.blocks.BasicConnectionTable$Receiver {
  private int reader_threads;

  private int writer_threads;

  private int processor_threads;

  private int processor_minThreads;

  private int processor_maxThreads;

  private int processor_queueSize;

  private long processor_keepAliveTime;

  private org.jgroups.blocks.ConnectionTableNIO ct;

  public org.jgroups.protocols.TCP_NIO();
    Code:
       0: aload_0
       1: invokespecial #1                  // Method org/jgroups/protocols/BasicTCP."<init>":()V
       4: aload_0
       5: iconst_3
       6: putfield      #2                  // Field reader_threads:I
       9: aload_0
      10: iconst_3
      11: putfield      #3                  // Field writer_threads:I
      14: aload_0
      15: iconst_5
      16: putfield      #4                  // Field processor_threads:I
      19: aload_0
      20: iconst_5
      21: putfield      #5                  // Field processor_minThreads:I
      24: aload_0
      25: iconst_5
      26: putfield      #6                  // Field processor_maxThreads:I
      29: aload_0
      30: bipush        100
      32: putfield      #7                  // Field processor_queueSize:I
      35: aload_0
      36: ldc2_w        #8                  // long 9223372036854775807l
      39: putfield      #10                 // Field processor_keepAliveTime:J
      42: return

  protected org.jgroups.blocks.ConnectionTableNIO getConnectionTable(long, long, java.net.InetAddress, java.net.InetAddress, int, int, int) throws java.lang.Exception;
    Code:
       0: aconst_null
       1: astore        10
       3: lload_1
       4: lconst_0
       5: lcmp
       6: ifne          39
       9: lload_3
      10: lconst_0
      11: lcmp
      12: ifne          39
      15: new           #11                 // class org/jgroups/blocks/ConnectionTableNIO
      18: dup
      19: aload_0
      20: aload         5
      22: aload         6
      24: iload         7
      26: iload         8
      28: iload         9
      30: iconst_0
      31: invokespecial #12                 // Method org/jgroups/blocks/ConnectionTableNIO."<init>":(Lorg/jgroups/blocks/BasicConnectionTable$Receiver;Ljava/net/InetAddress;Ljava/net/InetAddress;IIIZ)V
      34: astore        10
      36: goto          162
      39: lload_1
      40: lconst_0
      41: lcmp
      42: ifne          89
      45: ldc2_w        #13                 // long 5000l
      48: lstore_1
      49: aload_0
      50: getfield      #15                 // Field log:Lorg/jgroups/logging/Log;
      53: invokeinterface #16,  1           // InterfaceMethod org/jgroups/logging/Log.isWarnEnabled:()Z
      58: ifeq          89
      61: aload_0
      62: getfield      #15                 // Field log:Lorg/jgroups/logging/Log;
      65: new           #17                 // class java/lang/StringBuilder
      68: dup
      69: invokespecial #18                 // Method java/lang/StringBuilder."<init>":()V
      72: ldc           #19                 // String reaper_interval was 0, set it to
      74: invokevirtual #20                 // Method java/lang/StringBuilder.append:(Ljava/lang/String;)Ljava/lang/StringBuilder;
      77: lload_1
      78: invokevirtual #21                 // Method java/lang/StringBuilder.append:(J)Ljava/lang/StringBuilder;
      81: invokevirtual #22                 // Method java/lang/StringBuilder.toString:()Ljava/lang/String;
      84: invokeinterface #23,  2           // InterfaceMethod org/jgroups/logging/Log.warn:(Ljava/lang/String;)V
      89: lload_3
      90: lconst_0
      91: lcmp
      92: ifne          139
      95: ldc2_w        #24                 // long 300000l
      98: lstore_3
      99: aload_0
     100: getfield      #15                 // Field log:Lorg/jgroups/logging/Log;
     103: invokeinterface #16,  1           // InterfaceMethod org/jgroups/logging/Log.isWarnEnabled:()Z
     108: ifeq          139
     111: aload_0
     112: getfield      #15                 // Field log:Lorg/jgroups/logging/Log;
     115: new           #17                 // class java/lang/StringBuilder
     118: dup
     119: invokespecial #18                 // Method java/lang/StringBuilder."<init>":()V
     122: ldc           #26                 // String conn_expire_time was 0, set it to
     124: invokevirtual #20                 // Method java/lang/StringBuilder.append:(Ljava/lang/String;)Ljava/lang/StringBuilder;
     127: lload_3
     128: invokevirtual #21                 // Method java/lang/StringBuilder.append:(J)Ljava/lang/StringBuilder;
     131: invokevirtual #22                 // Method java/lang/StringBuilder.toString:()Ljava/lang/String;
     134: invokeinterface #23,  2           // InterfaceMethod org/jgroups/logging/Log.warn:(Ljava/lang/String;)V
     139: new           #11                 // class org/jgroups/blocks/ConnectionTableNIO
     142: dup
     143: aload_0
     144: aload         5
     146: aload         6
     148: iload         7
     150: iload         8
     152: iload         9
     154: lload_1
     155: lload_3
     156: iconst_0
     157: invokespecial #27                 // Method org/jgroups/blocks/ConnectionTableNIO."<init>":(Lorg/jgroups/blocks/BasicConnectionTable$Receiver;Ljava/net/InetAddress;Ljava/net/InetAddress;IIIJJZ)V
     160: astore        10
     162: aload         10
     164: aload_0
     165: invokevirtual #28                 // Method getThreadFactory:()Lorg/jgroups/util/ThreadFactory;
     168: invokevirtual #29                 // Method org/jgroups/blocks/ConnectionTableNIO.setThreadFactory:(Lorg/jgroups/util/ThreadFactory;)V
     171: aload         10
     173: aload_0
     174: invokevirtual #30                 // Method getProcessorMaxThreads:()I
     177: invokevirtual #31                 // Method org/jgroups/blocks/ConnectionTableNIO.setProcessorMaxThreads:(I)V
     180: aload         10
     182: aload_0
     183: invokevirtual #32                 // Method getProcessorQueueSize:()I
     186: invokevirtual #33                 // Method org/jgroups/blocks/ConnectionTableNIO.setProcessorQueueSize:(I)V
     189: aload         10
     191: aload_0
     192: invokevirtual #34                 // Method getProcessorMinThreads:()I
     195: invokevirtual #35                 // Method org/jgroups/blocks/ConnectionTableNIO.setProcessorMinThreads:(I)V
     198: aload         10
     200: aload_0
     201: invokevirtual #36                 // Method getProcessorKeepAliveTime:()J
     204: invokevirtual #37                 // Method org/jgroups/blocks/ConnectionTableNIO.setProcessorKeepAliveTime:(J)V
     207: aload         10
     209: aload_0
     210: invokevirtual #38                 // Method getProcessorThreads:()I
     213: invokevirtual #39                 // Method org/jgroups/blocks/ConnectionTableNIO.setProcessorThreads:(I)V
     216: aload         10
     218: invokevirtual #40                 // Method org/jgroups/blocks/ConnectionTableNIO.start:()V
     221: aload         10
     223: areturn

  public java.lang.String printConnections();
    Code:
       0: aload_0
       1: getfield      #41                 // Field ct:Lorg/jgroups/blocks/ConnectionTableNIO;
       4: invokevirtual #42                 // Method org/jgroups/blocks/ConnectionTableNIO.toString:()Ljava/lang/String;
       7: areturn

  protected org.jgroups.PhysicalAddress getPhysicalAddress();
    Code:
       0: aload_0
       1: getfield      #41                 // Field ct:Lorg/jgroups/blocks/ConnectionTableNIO;
       4: ifnull        20
       7: aload_0
       8: getfield      #41                 // Field ct:Lorg/jgroups/blocks/ConnectionTableNIO;
      11: invokevirtual #43                 // Method org/jgroups/blocks/ConnectionTableNIO.getLocalAddress:()Lorg/jgroups/Address;
      14: checkcast     #44                 // class org/jgroups/PhysicalAddress
      17: goto          21
      20: aconst_null
      21: areturn

  public void send(org.jgroups.Address, byte[], int, int) throws java.lang.Exception;
    Code:
       0: aload_0
       1: getfield      #41                 // Field ct:Lorg/jgroups/blocks/ConnectionTableNIO;
       4: aload_1
       5: aload_2
       6: iload_3
       7: iload         4
       9: invokevirtual #45                 // Method org/jgroups/blocks/ConnectionTableNIO.send:(Lorg/jgroups/Address;[BII)V
      12: return

  public void start() throws java.lang.Exception;
    Code:
       0: aload_0
       1: aload_0
       2: aload_0
       3: getfield      #46                 // Field reaper_interval:J
       6: aload_0
       7: getfield      #47                 // Field conn_expire_time:J
      10: aload_0
      11: getfield      #48                 // Field bind_addr:Ljava/net/InetAddress;
      14: aload_0
      15: getfield      #49                 // Field external_addr:Ljava/net/InetAddress;
      18: aload_0
      19: getfield      #50                 // Field external_port:I
      22: aload_0
      23: getfield      #51                 // Field bind_port:I
      26: aload_0
      27: getfield      #51                 // Field bind_port:I
      30: aload_0
      31: getfield      #52                 // Field port_range:I
      34: iadd
      35: invokevirtual #53                 // Method getConnectionTable:(JJLjava/net/InetAddress;Ljava/net/InetAddress;III)Lorg/jgroups/blocks/ConnectionTableNIO;
      38: putfield      #41                 // Field ct:Lorg/jgroups/blocks/ConnectionTableNIO;
      41: aload_0
      42: getfield      #41                 // Field ct:Lorg/jgroups/blocks/ConnectionTableNIO;
      45: aload_0
      46: getfield      #54                 // Field use_send_queues:Z
      49: invokevirtual #55                 // Method org/jgroups/blocks/ConnectionTableNIO.setUseSendQueues:(Z)V
      52: aload_0
      53: getfield      #41                 // Field ct:Lorg/jgroups/blocks/ConnectionTableNIO;
      56: aload_0
      57: getfield      #56                 // Field recv_buf_size:I
      60: invokevirtual #57                 // Method org/jgroups/blocks/ConnectionTableNIO.setReceiveBufferSize:(I)V
      63: aload_0
      64: getfield      #41                 // Field ct:Lorg/jgroups/blocks/ConnectionTableNIO;
      67: aload_0
      68: getfield      #58                 // Field send_buf_size:I
      71: invokevirtual #59                 // Method org/jgroups/blocks/ConnectionTableNIO.setSendBufferSize:(I)V
      74: aload_0
      75: getfield      #41                 // Field ct:Lorg/jgroups/blocks/ConnectionTableNIO;
      78: aload_0
      79: getfield      #60                 // Field sock_conn_timeout:I
      82: invokevirtual #61                 // Method org/jgroups/blocks/ConnectionTableNIO.setSocketConnectionTimeout:(I)V
      85: aload_0
      86: getfield      #41                 // Field ct:Lorg/jgroups/blocks/ConnectionTableNIO;
      89: aload_0
      90: getfield      #62                 // Field peer_addr_read_timeout:I
      93: invokevirtual #63                 // Method org/jgroups/blocks/ConnectionTableNIO.setPeerAddressReadTimeout:(I)V
      96: aload_0
      97: getfield      #41                 // Field ct:Lorg/jgroups/blocks/ConnectionTableNIO;
     100: aload_0
     101: getfield      #64                 // Field tcp_nodelay:Z
     104: invokevirtual #65                 // Method org/jgroups/blocks/ConnectionTableNIO.setTcpNodelay:(Z)V
     107: aload_0
     108: getfield      #41                 // Field ct:Lorg/jgroups/blocks/ConnectionTableNIO;
     111: aload_0
     112: getfield      #66                 // Field linger:I
     115: invokevirtual #67                 // Method org/jgroups/blocks/ConnectionTableNIO.setLinger:(I)V
     118: aload_0
     119: invokespecial #68                 // Method org/jgroups/protocols/BasicTCP.start:()V
     122: return

  public void retainAll(java.util.Collection<org.jgroups.Address>);
    Code:
       0: aload_0
       1: getfield      #41                 // Field ct:Lorg/jgroups/blocks/ConnectionTableNIO;
       4: aload_1
       5: invokevirtual #69                 // Method org/jgroups/blocks/ConnectionTableNIO.retainAll:(Ljava/util/Collection;)V
       8: return

  public void stop();
    Code:
       0: aload_0
       1: getfield      #41                 // Field ct:Lorg/jgroups/blocks/ConnectionTableNIO;
       4: invokevirtual #70                 // Method org/jgroups/blocks/ConnectionTableNIO.stop:()V
       7: aload_0
       8: invokespecial #71                 // Method org/jgroups/protocols/BasicTCP.stop:()V
      11: return

  public int getReaderThreads();
    Code:
       0: aload_0
       1: getfield      #2                  // Field reader_threads:I
       4: ireturn

  public int getWriterThreads();
    Code:
       0: aload_0
       1: getfield      #3                  // Field writer_threads:I
       4: ireturn

  public int getProcessorThreads();
    Code:
       0: aload_0
       1: getfield      #4                  // Field processor_threads:I
       4: ireturn

  public int getProcessorMinThreads();
    Code:
       0: aload_0
       1: getfield      #5                  // Field processor_minThreads:I
       4: ireturn

  public int getProcessorMaxThreads();
    Code:
       0: aload_0
       1: getfield      #6                  // Field processor_maxThreads:I
       4: ireturn

  public int getProcessorQueueSize();
    Code:
       0: aload_0
       1: getfield      #7                  // Field processor_queueSize:I
       4: ireturn

  public long getProcessorKeepAliveTime();
    Code:
       0: aload_0
       1: getfield      #10                 // Field processor_keepAliveTime:J
       4: lreturn

  public int getOpenConnections();
    Code:
       0: aload_0
       1: getfield      #41                 // Field ct:Lorg/jgroups/blocks/ConnectionTableNIO;
       4: invokevirtual #72                 // Method org/jgroups/blocks/ConnectionTableNIO.getNumConnections:()I
       7: ireturn
}
