public class org.bouncycastle.jcajce.provider.symmetric.util.BaseKeyGenerator extends javax.crypto.KeyGeneratorSpi {
  protected java.lang.String algName;

  protected int keySize;

  protected int defaultKeySize;

  protected org.bouncycastle.crypto.CipherKeyGenerator engine;

  protected boolean uninitialised;

  protected org.bouncycastle.jcajce.provider.symmetric.util.BaseKeyGenerator(java.lang.String, int, org.bouncycastle.crypto.CipherKeyGenerator);
    Code:
       0: aload_0
       1: invokespecial #69                 // Method javax/crypto/KeyGeneratorSpi."<init>":()V
       4: aload_0
       5: iconst_1
       6: putfield      #62                 // Field uninitialised:Z
       9: aload_0
      10: aload_1
      11: putfield      #63                 // Field algName:Ljava/lang/String;
      14: aload_0
      15: aload_0
      16: iload_2
      17: dup_x1
      18: putfield      #60                 // Field defaultKeySize:I
      21: putfield      #61                 // Field keySize:I
      24: aload_0
      25: aload_3
      26: putfield      #64                 // Field engine:Lorg/bouncycastle/crypto/CipherKeyGenerator;
      29: return

  protected void engineInit(java.security.spec.AlgorithmParameterSpec, java.security.SecureRandom) throws java.security.InvalidAlgorithmParameterException;
    Code:
       0: new           #28                 // class java/security/InvalidAlgorithmParameterException
       3: dup
       4: ldc           #1                  // String Not Implemented
       6: invokespecial #66                 // Method java/security/InvalidAlgorithmParameterException."<init>":(Ljava/lang/String;)V
       9: athrow

  protected void engineInit(java.security.SecureRandom);
    Code:
       0: aload_1
       1: ifnull        28
       4: aload_0
       5: getfield      #64                 // Field engine:Lorg/bouncycastle/crypto/CipherKeyGenerator;
       8: new           #34                 // class org/bouncycastle/crypto/KeyGenerationParameters
      11: dup
      12: aload_1
      13: aload_0
      14: getfield      #60                 // Field defaultKeySize:I
      17: invokespecial #73                 // Method org/bouncycastle/crypto/KeyGenerationParameters."<init>":(Ljava/security/SecureRandom;I)V
      20: invokevirtual #72                 // Method org/bouncycastle/crypto/CipherKeyGenerator.init:(Lorg/bouncycastle/crypto/KeyGenerationParameters;)V
      23: aload_0
      24: iconst_0
      25: putfield      #62                 // Field uninitialised:Z
      28: return

  protected void engineInit(int, java.security.SecureRandom);
    Code:
       0: aload_2
       1: ifnonnull     12
       4: new           #30                 // class java/security/SecureRandom
       7: dup
       8: invokespecial #68                 // Method java/security/SecureRandom."<init>":()V
      11: astore_2
      12: aload_0
      13: getfield      #64                 // Field engine:Lorg/bouncycastle/crypto/CipherKeyGenerator;
      16: new           #34                 // class org/bouncycastle/crypto/KeyGenerationParameters
      19: dup
      20: aload_2
      21: iload_1
      22: invokespecial #73                 // Method org/bouncycastle/crypto/KeyGenerationParameters."<init>":(Ljava/security/SecureRandom;I)V
      25: invokevirtual #72                 // Method org/bouncycastle/crypto/CipherKeyGenerator.init:(Lorg/bouncycastle/crypto/KeyGenerationParameters;)V
      28: aload_0
      29: iconst_0
      30: putfield      #62                 // Field uninitialised:Z
      33: goto          49
      36: astore_3
      37: new           #29                 // class java/security/InvalidParameterException
      40: dup
      41: aload_3
      42: invokevirtual #65                 // Method java/lang/IllegalArgumentException.getMessage:()Ljava/lang/String;
      45: invokespecial #67                 // Method java/security/InvalidParameterException."<init>":(Ljava/lang/String;)V
      48: athrow
      49: return
    Exception table:
       from    to  target type
           0    33    36   Class java/lang/IllegalArgumentException

  protected javax.crypto.SecretKey engineGenerateKey();
    Code:
       0: aload_0
       1: getfield      #62                 // Field uninitialised:Z
       4: ifeq          37
       7: aload_0
       8: getfield      #64                 // Field engine:Lorg/bouncycastle/crypto/CipherKeyGenerator;
      11: new           #34                 // class org/bouncycastle/crypto/KeyGenerationParameters
      14: dup
      15: new           #30                 // class java/security/SecureRandom
      18: dup
      19: invokespecial #68                 // Method java/security/SecureRandom."<init>":()V
      22: aload_0
      23: getfield      #60                 // Field defaultKeySize:I
      26: invokespecial #73                 // Method org/bouncycastle/crypto/KeyGenerationParameters."<init>":(Ljava/security/SecureRandom;I)V
      29: invokevirtual #72                 // Method org/bouncycastle/crypto/CipherKeyGenerator.init:(Lorg/bouncycastle/crypto/KeyGenerationParameters;)V
      32: aload_0
      33: iconst_0
      34: putfield      #62                 // Field uninitialised:Z
      37: new           #32                 // class javax/crypto/spec/SecretKeySpec
      40: dup
      41: aload_0
      42: getfield      #64                 // Field engine:Lorg/bouncycastle/crypto/CipherKeyGenerator;
      45: invokevirtual #71                 // Method org/bouncycastle/crypto/CipherKeyGenerator.generateKey:()[B
      48: aload_0
      49: getfield      #63                 // Field algName:Ljava/lang/String;
      52: invokespecial #70                 // Method javax/crypto/spec/SecretKeySpec."<init>":([BLjava/lang/String;)V
      55: areturn
}
