Compiled from "EndpointDiscoverer.java"
class org.springframework.boot.actuate.endpoint.annotation.EndpointDiscoverer$EndpointBean {
  private final java.lang.String beanName;

  private final java.lang.Object bean;

  private final java.lang.String id;

  private boolean enabledByDefault;

  private final java.lang.Class<?> filter;

  private java.util.Set<org.springframework.boot.actuate.endpoint.annotation.EndpointDiscoverer$ExtensionBean> extensions;

  org.springframework.boot.actuate.endpoint.annotation.EndpointDiscoverer$EndpointBean(java.lang.String, java.lang.Object);
    Code:
       0: aload_0
       1: invokespecial #1                  // Method java/lang/Object."<init>":()V
       4: aload_0
       5: new           #2                  // class java/util/LinkedHashSet
       8: dup
       9: invokespecial #3                  // Method java/util/LinkedHashSet."<init>":()V
      12: putfield      #4                  // Field extensions:Ljava/util/Set;
      15: aload_2
      16: invokevirtual #5                  // Method java/lang/Object.getClass:()Ljava/lang/Class;
      19: ldc           #6                  // class org/springframework/boot/actuate/endpoint/annotation/Endpoint
      21: iconst_1
      22: iconst_1
      23: invokestatic  #7                  // Method org/springframework/core/annotation/AnnotatedElementUtils.findMergedAnnotationAttributes:(Ljava/lang/reflect/AnnotatedElement;Ljava/lang/Class;ZZ)Lorg/springframework/core/annotation/AnnotationAttributes;
      26: astore_3
      27: aload_0
      28: aload_1
      29: putfield      #8                  // Field beanName:Ljava/lang/String;
      32: aload_0
      33: aload_2
      34: putfield      #9                  // Field bean:Ljava/lang/Object;
      37: aload_0
      38: aload_3
      39: ldc           #10                 // String id
      41: invokevirtual #11                 // Method org/springframework/core/annotation/AnnotationAttributes.getString:(Ljava/lang/String;)Ljava/lang/String;
      44: putfield      #12                 // Field id:Ljava/lang/String;
      47: aload_0
      48: aload_3
      49: ldc           #13                 // String enableByDefault
      51: invokevirtual #14                 // Method org/springframework/core/annotation/AnnotationAttributes.get:(Ljava/lang/Object;)Ljava/lang/Object;
      54: checkcast     #15                 // class java/lang/Boolean
      57: invokevirtual #16                 // Method java/lang/Boolean.booleanValue:()Z
      60: putfield      #17                 // Field enabledByDefault:Z
      63: aload_0
      64: aload_0
      65: aload_0
      66: getfield      #9                  // Field bean:Ljava/lang/Object;
      69: invokevirtual #5                  // Method java/lang/Object.getClass:()Ljava/lang/Class;
      72: invokespecial #18                 // Method getFilter:(Ljava/lang/Class;)Ljava/lang/Class;
      75: putfield      #19                 // Field filter:Ljava/lang/Class;
      78: aload_0
      79: getfield      #12                 // Field id:Ljava/lang/String;
      82: invokestatic  #20                 // Method org/springframework/util/StringUtils.hasText:(Ljava/lang/String;)Z
      85: aload_2
      86: invokedynamic #21,  0             // InvokeDynamic #0:get:(Ljava/lang/Object;)Ljava/util/function/Supplier;
      91: invokestatic  #22                 // Method org/springframework/util/Assert.state:(ZLjava/util/function/Supplier;)V
      94: return

  public void addExtension(org.springframework.boot.actuate.endpoint.annotation.EndpointDiscoverer$ExtensionBean);
    Code:
       0: aload_0
       1: getfield      #4                  // Field extensions:Ljava/util/Set;
       4: aload_1
       5: invokeinterface #23,  2           // InterfaceMethod java/util/Set.add:(Ljava/lang/Object;)Z
      10: pop
      11: return

  public java.util.Set<org.springframework.boot.actuate.endpoint.annotation.EndpointDiscoverer$ExtensionBean> getExtensions();
    Code:
       0: aload_0
       1: getfield      #4                  // Field extensions:Ljava/util/Set;
       4: areturn

  private java.lang.Class<?> getFilter(java.lang.Class<?>);
    Code:
       0: aload_1
       1: ldc           #24                 // class org/springframework/boot/actuate/endpoint/annotation/FilteredEndpoint
       3: invokestatic  #25                 // Method org/springframework/core/annotation/AnnotatedElementUtils.getMergedAnnotationAttributes:(Ljava/lang/reflect/AnnotatedElement;Ljava/lang/Class;)Lorg/springframework/core/annotation/AnnotationAttributes;
       6: astore_2
       7: aload_2
       8: ifnonnull     13
      11: aconst_null
      12: areturn
      13: aload_2
      14: ldc           #26                 // String value
      16: invokevirtual #27                 // Method org/springframework/core/annotation/AnnotationAttributes.getClass:(Ljava/lang/String;)Ljava/lang/Class;
      19: areturn

  public java.lang.String getBeanName();
    Code:
       0: aload_0
       1: getfield      #8                  // Field beanName:Ljava/lang/String;
       4: areturn

  public java.lang.Object getBean();
    Code:
       0: aload_0
       1: getfield      #9                  // Field bean:Ljava/lang/Object;
       4: areturn

  public java.lang.String getId();
    Code:
       0: aload_0
       1: getfield      #12                 // Field id:Ljava/lang/String;
       4: areturn

  public java.lang.Class<?> getType();
    Code:
       0: aload_0
       1: getfield      #9                  // Field bean:Ljava/lang/Object;
       4: invokevirtual #5                  // Method java/lang/Object.getClass:()Ljava/lang/Class;
       7: areturn

  public boolean isEnabledByDefault();
    Code:
       0: aload_0
       1: getfield      #17                 // Field enabledByDefault:Z
       4: ireturn

  public java.lang.Class<?> getFilter();
    Code:
       0: aload_0
       1: getfield      #19                 // Field filter:Ljava/lang/Class;
       4: areturn

  private static java.lang.String lambda$new$0(java.lang.Object);
    Code:
       0: new           #28                 // class java/lang/StringBuilder
       3: dup
       4: invokespecial #29                 // Method java/lang/StringBuilder."<init>":()V
       7: ldc           #30                 // String No @Endpoint id attribute specified for
       9: invokevirtual #31                 // Method java/lang/StringBuilder.append:(Ljava/lang/String;)Ljava/lang/StringBuilder;
      12: aload_0
      13: invokevirtual #5                  // Method java/lang/Object.getClass:()Ljava/lang/Class;
      16: invokevirtual #32                 // Method java/lang/Class.getName:()Ljava/lang/String;
      19: invokevirtual #31                 // Method java/lang/StringBuilder.append:(Ljava/lang/String;)Ljava/lang/StringBuilder;
      22: invokevirtual #33                 // Method java/lang/StringBuilder.toString:()Ljava/lang/String;
      25: areturn
}
