Compiled from "MapHolderParser.java"
public class org.jpmml.evaluator.visitors.MapHolderParser extends org.jpmml.evaluator.visitors.AbstractParser {
  public org.jpmml.evaluator.visitors.MapHolderParser();
    Code:
       0: aload_0
       1: invokespecial #1                  // Method org/jpmml/evaluator/visitors/AbstractParser."<init>":()V
       4: return

  public org.dmg.pmml.VisitorAction visit(org.dmg.pmml.naive_bayes.BayesInputs);
    Code:
       0: aload_1
       1: invokevirtual #2                  // Method org/dmg/pmml/naive_bayes/BayesInputs.hasBayesInputs:()Z
       4: ifeq          134
       7: aload_1
       8: invokevirtual #3                  // Method org/dmg/pmml/naive_bayes/BayesInputs.getBayesInputs:()Ljava/util/List;
      11: astore_2
      12: aload_2
      13: invokeinterface #4,  1            // InterfaceMethod java/util/List.listIterator:()Ljava/util/ListIterator;
      18: astore_3
      19: aload_3
      20: invokeinterface #5,  1            // InterfaceMethod java/util/ListIterator.hasNext:()Z
      25: ifeq          134
      28: aload_3
      29: invokeinterface #6,  1            // InterfaceMethod java/util/ListIterator.next:()Ljava/lang/Object;
      34: checkcast     #7                  // class org/dmg/pmml/naive_bayes/BayesInput
      37: astore        4
      39: aload         4
      41: invokevirtual #8                  // Method org/dmg/pmml/naive_bayes/BayesInput.getField:()Lorg/dmg/pmml/FieldName;
      44: astore        5
      46: aload         5
      48: ifnonnull     64
      51: new           #9                  // class org/jpmml/evaluator/MissingAttributeException
      54: dup
      55: aload         4
      57: getstatic     #10                 // Field org/dmg/pmml/naive_bayes/PMMLAttributes.BAYESINPUT_FIELD:Ljava/lang/reflect/Field;
      60: invokespecial #11                 // Method org/jpmml/evaluator/MissingAttributeException."<init>":(Lorg/dmg/pmml/PMMLObject;Ljava/lang/reflect/Field;)V
      63: athrow
      64: aload         4
      66: invokevirtual #12                 // Method org/dmg/pmml/naive_bayes/BayesInput.getDerivedField:()Lorg/dmg/pmml/DerivedField;
      69: astore        7
      71: aload         7
      73: ifnull        101
      76: aload         7
      78: invokevirtual #13                 // Method org/dmg/pmml/DerivedField.getDataType:()Lorg/dmg/pmml/DataType;
      81: astore        6
      83: aload         6
      85: ifnonnull     109
      88: new           #9                  // class org/jpmml/evaluator/MissingAttributeException
      91: dup
      92: aload         7
      94: getstatic     #14                 // Field org/dmg/pmml/PMMLAttributes.DERIVEDFIELD_DATATYPE:Ljava/lang/reflect/Field;
      97: invokespecial #11                 // Method org/jpmml/evaluator/MissingAttributeException."<init>":(Lorg/dmg/pmml/PMMLObject;Ljava/lang/reflect/Field;)V
     100: athrow
     101: aload_0
     102: aload         5
     104: invokevirtual #15                 // Method resolveDataType:(Lorg/dmg/pmml/FieldName;)Lorg/dmg/pmml/DataType;
     107: astore        6
     109: aload         6
     111: ifnull        131
     114: aload_3
     115: new           #16                 // class org/jpmml/evaluator/naive_bayes/RichBayesInput
     118: dup
     119: aload         6
     121: aload         4
     123: invokespecial #17                 // Method org/jpmml/evaluator/naive_bayes/RichBayesInput."<init>":(Lorg/dmg/pmml/DataType;Lorg/dmg/pmml/naive_bayes/BayesInput;)V
     126: invokeinterface #18,  2           // InterfaceMethod java/util/ListIterator.set:(Ljava/lang/Object;)V
     131: goto          19
     134: aload_0
     135: aload_1
     136: invokespecial #19                 // Method org/jpmml/evaluator/visitors/AbstractParser.visit:(Lorg/dmg/pmml/naive_bayes/BayesInputs;)Lorg/dmg/pmml/VisitorAction;
     139: areturn

  public org.dmg.pmml.VisitorAction visit(org.dmg.pmml.DataDictionary);
    Code:
       0: aload_1
       1: invokevirtual #20                 // Method org/dmg/pmml/DataDictionary.hasDataFields:()Z
       4: ifeq          65
       7: aload_1
       8: invokevirtual #21                 // Method org/dmg/pmml/DataDictionary.getDataFields:()Ljava/util/List;
      11: astore_2
      12: aload_2
      13: invokeinterface #4,  1            // InterfaceMethod java/util/List.listIterator:()Ljava/util/ListIterator;
      18: astore_3
      19: aload_3
      20: invokeinterface #5,  1            // InterfaceMethod java/util/ListIterator.hasNext:()Z
      25: ifeq          65
      28: aload_3
      29: invokeinterface #6,  1            // InterfaceMethod java/util/ListIterator.next:()Ljava/lang/Object;
      34: checkcast     #22                 // class org/dmg/pmml/DataField
      37: astore        4
      39: aload         4
      41: invokevirtual #23                 // Method org/dmg/pmml/DataField.hasValues:()Z
      44: ifeq          62
      47: aload_3
      48: new           #24                 // class org/jpmml/evaluator/RichDataField
      51: dup
      52: aload         4
      54: invokespecial #25                 // Method org/jpmml/evaluator/RichDataField."<init>":(Lorg/dmg/pmml/DataField;)V
      57: invokeinterface #18,  2           // InterfaceMethod java/util/ListIterator.set:(Ljava/lang/Object;)V
      62: goto          19
      65: aload_0
      66: aload_1
      67: invokespecial #26                 // Method org/jpmml/evaluator/visitors/AbstractParser.visit:(Lorg/dmg/pmml/DataDictionary;)Lorg/dmg/pmml/VisitorAction;
      70: areturn

  public org.dmg.pmml.VisitorAction visit(org.dmg.pmml.general_regression.GeneralRegressionModel);
    Code:
       0: aload_1
       1: invokevirtual #27                 // Method org/dmg/pmml/general_regression/GeneralRegressionModel.getBaseCumHazardTables:()Lorg/dmg/pmml/general_regression/BaseCumHazardTables;
       4: astore_2
       5: aload_2
       6: ifnull        45
       9: aload_1
      10: invokevirtual #28                 // Method org/dmg/pmml/general_regression/GeneralRegressionModel.getBaselineStrataVariable:()Lorg/dmg/pmml/FieldName;
      13: astore_3
      14: aload_3
      15: ifnull        45
      18: aload_0
      19: aload_3
      20: invokevirtual #15                 // Method resolveDataType:(Lorg/dmg/pmml/FieldName;)Lorg/dmg/pmml/DataType;
      23: astore        4
      25: aload         4
      27: ifnull        45
      30: aload_1
      31: new           #29                 // class org/jpmml/evaluator/general_regression/RichBaseCumHazardTables
      34: dup
      35: aload         4
      37: aload_2
      38: invokespecial #30                 // Method org/jpmml/evaluator/general_regression/RichBaseCumHazardTables."<init>":(Lorg/dmg/pmml/DataType;Lorg/dmg/pmml/general_regression/BaseCumHazardTables;)V
      41: invokevirtual #31                 // Method org/dmg/pmml/general_regression/GeneralRegressionModel.setBaseCumHazardTables:(Lorg/dmg/pmml/general_regression/BaseCumHazardTables;)Lorg/dmg/pmml/general_regression/GeneralRegressionModel;
      44: pop
      45: aload_0
      46: aload_1
      47: invokespecial #32                 // Method org/jpmml/evaluator/visitors/AbstractParser.visit:(Lorg/dmg/pmml/general_regression/GeneralRegressionModel;)Lorg/dmg/pmml/VisitorAction;
      50: areturn

  public org.dmg.pmml.VisitorAction visit(org.dmg.pmml.LocalTransformations);
    Code:
       0: aload_0
       1: aload_1
       2: invokespecial #33                 // Method processDerivedFields:(Lorg/dmg/pmml/HasDerivedFields;)V
       5: aload_0
       6: aload_1
       7: invokespecial #34                 // Method org/jpmml/evaluator/visitors/AbstractParser.visit:(Lorg/dmg/pmml/LocalTransformations;)Lorg/dmg/pmml/VisitorAction;
      10: areturn

  public org.dmg.pmml.VisitorAction visit(org.dmg.pmml.Output);
    Code:
       0: aload_1
       1: invokevirtual #35                 // Method org/dmg/pmml/Output.hasOutputFields:()Z
       4: ifeq          65
       7: aload_1
       8: invokevirtual #36                 // Method org/dmg/pmml/Output.getOutputFields:()Ljava/util/List;
      11: astore_2
      12: aload_2
      13: invokeinterface #4,  1            // InterfaceMethod java/util/List.listIterator:()Ljava/util/ListIterator;
      18: astore_3
      19: aload_3
      20: invokeinterface #5,  1            // InterfaceMethod java/util/ListIterator.hasNext:()Z
      25: ifeq          65
      28: aload_3
      29: invokeinterface #6,  1            // InterfaceMethod java/util/ListIterator.next:()Ljava/lang/Object;
      34: checkcast     #37                 // class org/dmg/pmml/OutputField
      37: astore        4
      39: aload         4
      41: invokevirtual #38                 // Method org/dmg/pmml/OutputField.hasValues:()Z
      44: ifeq          62
      47: aload_3
      48: new           #39                 // class org/jpmml/evaluator/RichOutputField
      51: dup
      52: aload         4
      54: invokespecial #40                 // Method org/jpmml/evaluator/RichOutputField."<init>":(Lorg/dmg/pmml/OutputField;)V
      57: invokeinterface #18,  2           // InterfaceMethod java/util/ListIterator.set:(Ljava/lang/Object;)V
      62: goto          19
      65: aload_0
      66: aload_1
      67: invokespecial #41                 // Method org/jpmml/evaluator/visitors/AbstractParser.visit:(Lorg/dmg/pmml/Output;)Lorg/dmg/pmml/VisitorAction;
      70: areturn

  public org.dmg.pmml.VisitorAction visit(org.dmg.pmml.TransformationDictionary);
    Code:
       0: aload_0
       1: aload_1
       2: invokespecial #33                 // Method processDerivedFields:(Lorg/dmg/pmml/HasDerivedFields;)V
       5: aload_0
       6: aload_1
       7: invokespecial #42                 // Method org/jpmml/evaluator/visitors/AbstractParser.visit:(Lorg/dmg/pmml/TransformationDictionary;)Lorg/dmg/pmml/VisitorAction;
      10: areturn

  private void processDerivedFields(org.dmg.pmml.HasDerivedFields<?>);
    Code:
       0: aload_1
       1: invokeinterface #43,  1           // InterfaceMethod org/dmg/pmml/HasDerivedFields.hasDerivedFields:()Z
       6: ifeq          69
       9: aload_1
      10: invokeinterface #44,  1           // InterfaceMethod org/dmg/pmml/HasDerivedFields.getDerivedFields:()Ljava/util/List;
      15: astore_2
      16: aload_2
      17: invokeinterface #4,  1            // InterfaceMethod java/util/List.listIterator:()Ljava/util/ListIterator;
      22: astore_3
      23: aload_3
      24: invokeinterface #5,  1            // InterfaceMethod java/util/ListIterator.hasNext:()Z
      29: ifeq          69
      32: aload_3
      33: invokeinterface #6,  1            // InterfaceMethod java/util/ListIterator.next:()Ljava/lang/Object;
      38: checkcast     #45                 // class org/dmg/pmml/DerivedField
      41: astore        4
      43: aload         4
      45: invokevirtual #46                 // Method org/dmg/pmml/DerivedField.hasValues:()Z
      48: ifeq          66
      51: aload_3
      52: new           #47                 // class org/jpmml/evaluator/RichDerivedField
      55: dup
      56: aload         4
      58: invokespecial #48                 // Method org/jpmml/evaluator/RichDerivedField."<init>":(Lorg/dmg/pmml/DerivedField;)V
      61: invokeinterface #18,  2           // InterfaceMethod java/util/ListIterator.set:(Ljava/lang/Object;)V
      66: goto          23
      69: return

  public org.dmg.pmml.PMMLObject popParent();
    Code:
       0: aload_0
       1: invokespecial #49                 // Method org/jpmml/evaluator/visitors/AbstractParser.popParent:()Lorg/dmg/pmml/PMMLObject;
       4: areturn

  public void reset();
    Code:
       0: aload_0
       1: invokespecial #50                 // Method org/jpmml/evaluator/visitors/AbstractParser.reset:()V
       4: return
}
