Compiled from "ScoreDistributionInterner.java"
public class org.jpmml.evaluator.visitors.ScoreDistributionInterner extends org.jpmml.model.visitors.AbstractVisitor {
  private org.jpmml.evaluator.visitors.ElementHashMap<org.dmg.pmml.ScoreDistribution> cache;

  public org.jpmml.evaluator.visitors.ScoreDistributionInterner();
    Code:
       0: aload_0
       1: invokespecial #1                  // Method org/jpmml/model/visitors/AbstractVisitor."<init>":()V
       4: aload_0
       5: new           #2                  // class org/jpmml/evaluator/visitors/ScoreDistributionInterner$1
       8: dup
       9: aload_0
      10: invokespecial #3                  // Method org/jpmml/evaluator/visitors/ScoreDistributionInterner$1."<init>":(Lorg/jpmml/evaluator/visitors/ScoreDistributionInterner;)V
      13: putfield      #4                  // Field cache:Lorg/jpmml/evaluator/visitors/ElementHashMap;
      16: return

  public org.dmg.pmml.VisitorAction visit(org.dmg.pmml.tree.Node);
    Code:
       0: aload_1
       1: invokevirtual #5                  // Method org/dmg/pmml/tree/Node.hasScoreDistributions:()Z
       4: ifeq          50
       7: aload_1
       8: invokevirtual #6                  // Method org/dmg/pmml/tree/Node.getScoreDistributions:()Ljava/util/List;
      11: astore_2
      12: aload_2
      13: invokeinterface #7,  1            // InterfaceMethod java/util/List.listIterator:()Ljava/util/ListIterator;
      18: astore_3
      19: aload_3
      20: invokeinterface #8,  1            // InterfaceMethod java/util/ListIterator.hasNext:()Z
      25: ifeq          50
      28: aload_3
      29: aload_0
      30: aload_3
      31: invokeinterface #9,  1            // InterfaceMethod java/util/ListIterator.next:()Ljava/lang/Object;
      36: checkcast     #10                 // class org/dmg/pmml/ScoreDistribution
      39: invokespecial #11                 // Method intern:(Lorg/dmg/pmml/ScoreDistribution;)Lorg/dmg/pmml/ScoreDistribution;
      42: invokeinterface #12,  2           // InterfaceMethod java/util/ListIterator.set:(Ljava/lang/Object;)V
      47: goto          19
      50: aload_0
      51: aload_1
      52: invokespecial #13                 // Method org/jpmml/model/visitors/AbstractVisitor.visit:(Lorg/dmg/pmml/tree/Node;)Lorg/dmg/pmml/VisitorAction;
      55: areturn

  private org.dmg.pmml.ScoreDistribution intern(org.dmg.pmml.ScoreDistribution);
    Code:
       0: aload_1
       1: ifnull        11
       4: aload_1
       5: invokevirtual #14                 // Method org/dmg/pmml/ScoreDistribution.hasExtensions:()Z
       8: ifeq          13
      11: aload_1
      12: areturn
      13: aload_0
      14: getfield      #4                  // Field cache:Lorg/jpmml/evaluator/visitors/ElementHashMap;
      17: aload_1
      18: invokevirtual #15                 // Method org/jpmml/evaluator/visitors/ElementHashMap.intern:(Lorg/dmg/pmml/PMMLObject;)Lorg/dmg/pmml/PMMLObject;
      21: checkcast     #10                 // class org/dmg/pmml/ScoreDistribution
      24: areturn
}
