Compiled from "KeywordsImpl.java"
public class org.opensaml.saml.ext.saml2mdui.impl.KeywordsImpl extends org.opensaml.saml.common.AbstractSAMLObject implements org.opensaml.saml.ext.saml2mdui.Keywords {
  private java.lang.String lang;

  private java.util.List<java.lang.String> data;

  protected org.opensaml.saml.ext.saml2mdui.impl.KeywordsImpl(java.lang.String, java.lang.String, java.lang.String);
    Code:
       0: aload_0
       1: aload_1
       2: aload_2
       3: aload_3
       4: invokespecial #1                  // Method org/opensaml/saml/common/AbstractSAMLObject."<init>":(Ljava/lang/String;Ljava/lang/String;Ljava/lang/String;)V
       7: return

  public java.util.List<org.opensaml.core.xml.XMLObject> getOrderedChildren();
    Code:
       0: aconst_null
       1: areturn

  public java.lang.String getXMLLang();
    Code:
       0: aload_0
       1: getfield      #2                  // Field lang:Ljava/lang/String;
       4: areturn

  public void setXMLLang(java.lang.String);
    Code:
       0: aload_1
       1: ifnull        15
       4: aload_1
       5: invokestatic  #3                  // Method com/google/common/base/Strings.isNullOrEmpty:(Ljava/lang/String;)Z
       8: ifne          15
      11: iconst_1
      12: goto          16
      15: iconst_0
      16: istore_2
      17: aload_0
      18: aload_0
      19: aload_0
      20: getfield      #2                  // Field lang:Ljava/lang/String;
      23: aload_1
      24: invokevirtual #4                  // Method prepareForAssignment:(Ljava/lang/String;Ljava/lang/String;)Ljava/lang/String;
      27: putfield      #2                  // Field lang:Ljava/lang/String;
      30: aload_0
      31: getstatic     #5                  // Field org/opensaml/core/xml/LangBearing.XML_LANG_ATTR_NAME:Ljavax/xml/namespace/QName;
      34: iload_2
      35: invokevirtual #6                  // Method manageQualifiedAttributeNamespace:(Ljavax/xml/namespace/QName;Z)V
      38: return

  public java.util.List<java.lang.String> getKeywords();
    Code:
       0: aload_0
       1: getfield      #7                  // Field data:Ljava/util/List;
       4: areturn

  public void setKeywords(java.util.List<java.lang.String>);
    Code:
       0: aload_0
       1: aload_0
       2: aload_0
       3: getfield      #7                  // Field data:Ljava/util/List;
       6: aload_1
       7: invokevirtual #8                  // Method prepareForAssignment:(Ljava/lang/Object;Ljava/lang/Object;)Ljava/lang/Object;
      10: checkcast     #9                  // class java/util/List
      13: putfield      #7                  // Field data:Ljava/util/List;
      16: return

  public int hashCode();
    Code:
       0: aload_0
       1: getfield      #2                  // Field lang:Ljava/lang/String;
       4: invokevirtual #10                 // Method java/lang/String.hashCode:()I
       7: istore_1
       8: aload_0
       9: getfield      #7                  // Field data:Ljava/util/List;
      12: invokeinterface #11,  1           // InterfaceMethod java/util/List.iterator:()Ljava/util/Iterator;
      17: astore_2
      18: aload_2
      19: invokeinterface #12,  1           // InterfaceMethod java/util/Iterator.hasNext:()Z
      24: ifeq          50
      27: aload_2
      28: invokeinterface #13,  1           // InterfaceMethod java/util/Iterator.next:()Ljava/lang/Object;
      33: checkcast     #14                 // class java/lang/String
      36: astore_3
      37: iload_1
      38: bipush        31
      40: imul
      41: aload_3
      42: invokevirtual #10                 // Method java/lang/String.hashCode:()I
      45: iadd
      46: istore_1
      47: goto          18
      50: iload_1
      51: ireturn
}
