Compiled from "DefaultSymbolTable.java"
public class org.sonar.api.batch.sensor.symbol.internal.DefaultSymbolTable extends org.sonar.api.batch.sensor.internal.DefaultStorable implements org.sonar.api.batch.sensor.symbol.NewSymbolTable {
  private final java.util.Map<org.sonar.api.batch.fs.TextRange, java.util.Set<org.sonar.api.batch.fs.TextRange>> referencesBySymbol;

  private org.sonar.api.batch.fs.internal.DefaultInputFile inputFile;

  public org.sonar.api.batch.sensor.symbol.internal.DefaultSymbolTable(org.sonar.api.batch.sensor.internal.SensorStorage);
    Code:
       0: aload_0
       1: aload_1
       2: invokespecial #21                 // Method org/sonar/api/batch/sensor/internal/DefaultStorable."<init>":(Lorg/sonar/api/batch/sensor/internal/SensorStorage;)V
       5: aload_0
       6: new           #23                 // class java/util/LinkedHashMap
       9: dup
      10: invokespecial #26                 // Method java/util/LinkedHashMap."<init>":()V
      13: putfield      #28                 // Field referencesBySymbol:Ljava/util/Map;
      16: return

  public java.util.Map<org.sonar.api.batch.fs.TextRange, java.util.Set<org.sonar.api.batch.fs.TextRange>> getReferencesBySymbol();
    Code:
       0: aload_0
       1: getfield      #28                 // Field referencesBySymbol:Ljava/util/Map;
       4: areturn

  public org.sonar.api.batch.sensor.symbol.internal.DefaultSymbolTable onFile(org.sonar.api.batch.fs.InputFile);
    Code:
       0: aload_1
       1: ldc           #38                 // String file can\'t be null
       3: invokestatic  #44                 // Method org/sonar/api/internal/google/common/base/Preconditions.checkNotNull:(Ljava/lang/Object;Ljava/lang/Object;)Ljava/lang/Object;
       6: pop
       7: aload_0
       8: aload_1
       9: checkcast     #46                 // class org/sonar/api/batch/fs/internal/DefaultInputFile
      12: putfield      #48                 // Field inputFile:Lorg/sonar/api/batch/fs/internal/DefaultInputFile;
      15: aload_0
      16: areturn

  public org.sonar.api.batch.fs.InputFile inputFile();
    Code:
       0: aload_0
       1: getfield      #48                 // Field inputFile:Lorg/sonar/api/batch/fs/internal/DefaultInputFile;
       4: areturn

  public org.sonar.api.batch.sensor.symbol.NewSymbol newSymbol(int, int, int, int);
    Code:
       0: aload_0
       1: invokespecial #57                 // Method checkInputFileNotNull:()V
       4: aload_0
       5: getfield      #48                 // Field inputFile:Lorg/sonar/api/batch/fs/internal/DefaultInputFile;
       8: iload_1
       9: iload_2
      10: iload_3
      11: iload         4
      13: invokevirtual #61                 // Method org/sonar/api/batch/fs/internal/DefaultInputFile.newRange:(IIII)Lorg/sonar/api/batch/fs/TextRange;
      16: astore        5
      18: goto          55
      21: astore        6
      23: new           #63                 // class java/lang/IllegalArgumentException
      26: dup
      27: new           #65                 // class java/lang/StringBuilder
      30: dup
      31: invokespecial #66                 // Method java/lang/StringBuilder."<init>":()V
      34: ldc           #68                 // String Unable to create symbol on file
      36: invokevirtual #72                 // Method java/lang/StringBuilder.append:(Ljava/lang/String;)Ljava/lang/StringBuilder;
      39: aload_0
      40: getfield      #48                 // Field inputFile:Lorg/sonar/api/batch/fs/internal/DefaultInputFile;
      43: invokevirtual #75                 // Method java/lang/StringBuilder.append:(Ljava/lang/Object;)Ljava/lang/StringBuilder;
      46: invokevirtual #79                 // Method java/lang/StringBuilder.toString:()Ljava/lang/String;
      49: aload         6
      51: invokespecial #82                 // Method java/lang/IllegalArgumentException."<init>":(Ljava/lang/String;Ljava/lang/Throwable;)V
      54: athrow
      55: aload_0
      56: aload         5
      58: invokevirtual #87                 // Method newSymbol:(Lorg/sonar/api/batch/fs/TextRange;)Lorg/sonar/api/batch/sensor/symbol/NewSymbol;
      61: areturn
    Exception table:
       from    to  target type
           4    18    21   Class java/lang/Exception

  public org.sonar.api.batch.sensor.symbol.NewSymbol newSymbol(int, int);
    Code:
       0: aload_0
       1: invokespecial #57                 // Method checkInputFileNotNull:()V
       4: aload_0
       5: getfield      #48                 // Field inputFile:Lorg/sonar/api/batch/fs/internal/DefaultInputFile;
       8: iload_1
       9: iload_2
      10: invokevirtual #100                // Method org/sonar/api/batch/fs/internal/DefaultInputFile.newRange:(II)Lorg/sonar/api/batch/fs/TextRange;
      13: astore_3
      14: goto          51
      17: astore        4
      19: new           #63                 // class java/lang/IllegalArgumentException
      22: dup
      23: new           #65                 // class java/lang/StringBuilder
      26: dup
      27: invokespecial #66                 // Method java/lang/StringBuilder."<init>":()V
      30: ldc           #68                 // String Unable to create symbol on file
      32: invokevirtual #72                 // Method java/lang/StringBuilder.append:(Ljava/lang/String;)Ljava/lang/StringBuilder;
      35: aload_0
      36: getfield      #48                 // Field inputFile:Lorg/sonar/api/batch/fs/internal/DefaultInputFile;
      39: invokevirtual #75                 // Method java/lang/StringBuilder.append:(Ljava/lang/Object;)Ljava/lang/StringBuilder;
      42: invokevirtual #79                 // Method java/lang/StringBuilder.toString:()Ljava/lang/String;
      45: aload         4
      47: invokespecial #82                 // Method java/lang/IllegalArgumentException."<init>":(Ljava/lang/String;Ljava/lang/Throwable;)V
      50: athrow
      51: aload_0
      52: aload_3
      53: invokevirtual #87                 // Method newSymbol:(Lorg/sonar/api/batch/fs/TextRange;)Lorg/sonar/api/batch/sensor/symbol/NewSymbol;
      56: areturn
    Exception table:
       from    to  target type
           4    14    17   Class java/lang/Exception

  public org.sonar.api.batch.sensor.symbol.NewSymbol newSymbol(org.sonar.api.batch.fs.TextRange);
    Code:
       0: aload_0
       1: invokespecial #57                 // Method checkInputFileNotNull:()V
       4: new           #104                // class java/util/TreeSet
       7: dup
       8: new           #12                 // class org/sonar/api/batch/sensor/symbol/internal/DefaultSymbolTable$1
      11: dup
      12: aload_0
      13: invokespecial #107                // Method org/sonar/api/batch/sensor/symbol/internal/DefaultSymbolTable$1."<init>":(Lorg/sonar/api/batch/sensor/symbol/internal/DefaultSymbolTable;)V
      16: invokespecial #110                // Method java/util/TreeSet."<init>":(Ljava/util/Comparator;)V
      19: astore_2
      20: aload_0
      21: getfield      #28                 // Field referencesBySymbol:Ljava/util/Map;
      24: aload_1
      25: aload_2
      26: invokeinterface #115,  3          // InterfaceMethod java/util/Map.put:(Ljava/lang/Object;Ljava/lang/Object;)Ljava/lang/Object;
      31: pop
      32: new           #9                  // class org/sonar/api/batch/sensor/symbol/internal/DefaultSymbolTable$DefaultSymbol
      35: dup
      36: aload_0
      37: getfield      #48                 // Field inputFile:Lorg/sonar/api/batch/fs/internal/DefaultInputFile;
      40: aload_1
      41: aload_2
      42: invokespecial #118                // Method org/sonar/api/batch/sensor/symbol/internal/DefaultSymbolTable$DefaultSymbol."<init>":(Lorg/sonar/api/batch/fs/internal/DefaultInputFile;Lorg/sonar/api/batch/fs/TextRange;Ljava/util/Collection;)V
      45: areturn

  protected void doSave();
    Code:
       0: aload_0
       1: invokespecial #57                 // Method checkInputFileNotNull:()V
       4: aload_0
       5: getfield      #125                // Field storage:Lorg/sonar/api/batch/sensor/internal/SensorStorage;
       8: aload_0
       9: invokeinterface #130,  2          // InterfaceMethod org/sonar/api/batch/sensor/internal/SensorStorage.store:(Lorg/sonar/api/batch/sensor/symbol/internal/DefaultSymbolTable;)V
      14: return

  private void checkInputFileNotNull();
    Code:
       0: aload_0
       1: getfield      #48                 // Field inputFile:Lorg/sonar/api/batch/fs/internal/DefaultInputFile;
       4: ifnull        11
       7: iconst_1
       8: goto          12
      11: iconst_0
      12: ldc           #132                // String Call onFile() first
      14: invokestatic  #136                // Method org/sonar/api/internal/google/common/base/Preconditions.checkState:(ZLjava/lang/Object;)V
      17: return

  public org.sonar.api.batch.sensor.symbol.NewSymbolTable onFile(org.sonar.api.batch.fs.InputFile);
    Code:
       0: aload_0
       1: aload_1
       2: invokevirtual #139                // Method onFile:(Lorg/sonar/api/batch/fs/InputFile;)Lorg/sonar/api/batch/sensor/symbol/internal/DefaultSymbolTable;
       5: areturn
}
