Compiled from "CookieParamProcessor.java"
public class org.jboss.resteasy.client.jaxrs.internal.proxy.processors.invocation.CookieParamProcessor implements org.jboss.resteasy.client.jaxrs.internal.proxy.processors.InvocationProcessor {
  private java.lang.String cookieName;

  public org.jboss.resteasy.client.jaxrs.internal.proxy.processors.invocation.CookieParamProcessor(java.lang.String);
    Code:
       0: aload_0
       1: invokespecial #1                  // Method java/lang/Object."<init>":()V
       4: aload_0
       5: aload_1
       6: putfield      #2                  // Field cookieName:Ljava/lang/String;
       9: return

  public java.lang.String getCookieName();
    Code:
       0: aload_0
       1: getfield      #2                  // Field cookieName:Ljava/lang/String;
       4: areturn

  public void process(org.jboss.resteasy.client.jaxrs.internal.ClientInvocationBuilder, java.lang.Object);
    Code:
       0: aload_2
       1: ifnonnull     5
       4: return
       5: aload_2
       6: instanceof    #3                  // class javax/ws/rs/core/Cookie
       9: ifeq          26
      12: aload_2
      13: checkcast     #3                  // class javax/ws/rs/core/Cookie
      16: astore_3
      17: aload_1
      18: aload_3
      19: invokevirtual #4                  // Method org/jboss/resteasy/client/jaxrs/internal/ClientInvocationBuilder.cookie:(Ljavax/ws/rs/core/Cookie;)Ljavax/ws/rs/client/Invocation$Builder;
      22: pop
      23: goto          53
      26: aload_1
      27: new           #3                  // class javax/ws/rs/core/Cookie
      30: dup
      31: aload_0
      32: getfield      #2                  // Field cookieName:Ljava/lang/String;
      35: aload_1
      36: invokevirtual #5                  // Method org/jboss/resteasy/client/jaxrs/internal/ClientInvocationBuilder.getInvocation:()Lorg/jboss/resteasy/client/jaxrs/internal/ClientInvocation;
      39: invokevirtual #6                  // Method org/jboss/resteasy/client/jaxrs/internal/ClientInvocation.getClientConfiguration:()Lorg/jboss/resteasy/client/jaxrs/internal/ClientConfiguration;
      42: aload_2
      43: invokevirtual #7                  // Method org/jboss/resteasy/client/jaxrs/internal/ClientConfiguration.toString:(Ljava/lang/Object;)Ljava/lang/String;
      46: invokespecial #8                  // Method javax/ws/rs/core/Cookie."<init>":(Ljava/lang/String;Ljava/lang/String;)V
      49: invokevirtual #4                  // Method org/jboss/resteasy/client/jaxrs/internal/ClientInvocationBuilder.cookie:(Ljavax/ws/rs/core/Cookie;)Ljavax/ws/rs/client/Invocation$Builder;
      52: pop
      53: return
}
