Compiled from "AbstractSequentialFile.java"
final class org.apache.activemq.artemis.core.io.AbstractSequentialFile$DelegateCallback implements org.apache.activemq.artemis.core.io.IOCallback {
  final java.util.List<org.apache.activemq.artemis.core.io.IOCallback> delegates;

  private org.apache.activemq.artemis.core.io.AbstractSequentialFile$DelegateCallback(java.util.List<org.apache.activemq.artemis.core.io.IOCallback>);
    Code:
       0: aload_0
       1: invokespecial #2                  // Method java/lang/Object."<init>":()V
       4: aload_0
       5: aload_1
       6: putfield      #3                  // Field delegates:Ljava/util/List;
       9: return

  public void done();
    Code:
       0: aload_0
       1: getfield      #3                  // Field delegates:Ljava/util/List;
       4: invokeinterface #4,  1            // InterfaceMethod java/util/List.iterator:()Ljava/util/Iterator;
       9: astore_1
      10: aload_1
      11: invokeinterface #5,  1            // InterfaceMethod java/util/Iterator.hasNext:()Z
      16: ifeq          51
      19: aload_1
      20: invokeinterface #6,  1            // InterfaceMethod java/util/Iterator.next:()Ljava/lang/Object;
      25: checkcast     #7                  // class org/apache/activemq/artemis/core/io/IOCallback
      28: astore_2
      29: aload_2
      30: invokeinterface #8,  1            // InterfaceMethod org/apache/activemq/artemis/core/io/IOCallback.done:()V
      35: goto          48
      38: astore_3
      39: getstatic     #10                 // Field org/apache/activemq/artemis/journal/ActiveMQJournalLogger.LOGGER:Lorg/apache/activemq/artemis/journal/ActiveMQJournalLogger;
      42: aload_3
      43: invokeinterface #11,  2           // InterfaceMethod org/apache/activemq/artemis/journal/ActiveMQJournalLogger.errorCompletingCallback:(Ljava/lang/Throwable;)V
      48: goto          10
      51: return
    Exception table:
       from    to  target type
          29    35    38   Class java/lang/Throwable

  public void onError(int, java.lang.String);
    Code:
       0: aload_0
       1: getfield      #3                  // Field delegates:Ljava/util/List;
       4: invokeinterface #4,  1            // InterfaceMethod java/util/List.iterator:()Ljava/util/Iterator;
       9: astore_3
      10: aload_3
      11: invokeinterface #5,  1            // InterfaceMethod java/util/Iterator.hasNext:()Z
      16: ifeq          57
      19: aload_3
      20: invokeinterface #6,  1            // InterfaceMethod java/util/Iterator.next:()Ljava/lang/Object;
      25: checkcast     #7                  // class org/apache/activemq/artemis/core/io/IOCallback
      28: astore        4
      30: aload         4
      32: iload_1
      33: aload_2
      34: invokeinterface #12,  3           // InterfaceMethod org/apache/activemq/artemis/core/io/IOCallback.onError:(ILjava/lang/String;)V
      39: goto          54
      42: astore        5
      44: getstatic     #10                 // Field org/apache/activemq/artemis/journal/ActiveMQJournalLogger.LOGGER:Lorg/apache/activemq/artemis/journal/ActiveMQJournalLogger;
      47: aload         5
      49: invokeinterface #13,  2           // InterfaceMethod org/apache/activemq/artemis/journal/ActiveMQJournalLogger.errorCallingErrorCallback:(Ljava/lang/Throwable;)V
      54: goto          10
      57: return
    Exception table:
       from    to  target type
          30    39    42   Class java/lang/Throwable

  org.apache.activemq.artemis.core.io.AbstractSequentialFile$DelegateCallback(java.util.List, org.apache.activemq.artemis.core.io.AbstractSequentialFile$1);
    Code:
       0: aload_0
       1: aload_1
       2: invokespecial #1                  // Method "<init>":(Ljava/util/List;)V
       5: return
}
