Compiled from "AbstractClassTestingTypeFilter.java"
public abstract class org.springframework.core.type.filter.AbstractClassTestingTypeFilter implements org.springframework.core.type.filter.TypeFilter {
  public org.springframework.core.type.filter.AbstractClassTestingTypeFilter();
    Code:
       0: aload_0
       1: invokespecial #1                  // Method java/lang/Object."<init>":()V
       4: return

  public final boolean match(org.springframework.core.type.classreading.MetadataReader, org.springframework.core.type.classreading.MetadataReaderFactory) throws java.io.IOException;
    Code:
       0: aload_0
       1: aload_1
       2: invokeinterface #2,  1            // InterfaceMethod org/springframework/core/type/classreading/MetadataReader.getClassMetadata:()Lorg/springframework/core/type/ClassMetadata;
       7: invokevirtual #3                  // Method match:(Lorg/springframework/core/type/ClassMetadata;)Z
      10: ireturn

  protected abstract boolean match(org.springframework.core.type.ClassMetadata);
}
