Compiled from "InboundTransactionCurrentImple.java"
public class com.arjuna.ats.internal.jbossatx.jts.InboundTransactionCurrentImple extends org.omg.CORBA.LocalObject implements org.jboss.iiop.tm.InboundTransactionCurrent {
  public com.arjuna.ats.internal.jbossatx.jts.InboundTransactionCurrentImple();
    Code:
       0: aload_0
       1: invokespecial #1                  // Method org/omg/CORBA/LocalObject."<init>":()V
       4: return

  public javax.transaction.Transaction getCurrentTransaction();
    Code:
       0: getstatic     #2                  // Field com/arjuna/ats/jbossatx/logging/jbossatxLogger.logger:Lorg/jboss/logging/Logger;
       3: invokevirtual #3                  // Method org/jboss/logging/Logger.isTraceEnabled:()Z
       6: ifeq          17
       9: getstatic     #2                  // Field com/arjuna/ats/jbossatx/logging/jbossatxLogger.logger:Lorg/jboss/logging/Logger;
      12: ldc           #4                  // String InboundTransactionCurrentImple.getCurrentTransaction() called
      14: invokevirtual #5                  // Method org/jboss/logging/Logger.trace:(Ljava/lang/Object;)V
      17: aconst_null
      18: astore_1
      19: aconst_null
      20: astore_2
      21: invokestatic  #6                  // Method org/jboss/tm/TransactionManagerLocator.getInstance:()Lorg/jboss/tm/TransactionManagerLocator;
      24: invokevirtual #7                  // Method org/jboss/tm/TransactionManagerLocator.getTransactionManager:()Ljavax/transaction/TransactionManager;
      27: astore_1
      28: aload_1
      29: invokeinterface #8,  1            // InterfaceMethod javax/transaction/TransactionManager.getTransaction:()Ljavax/transaction/Transaction;
      34: astore_2
      35: aload_2
      36: ifnull        46
      39: aload_1
      40: invokeinterface #9,  1            // InterfaceMethod javax/transaction/TransactionManager.suspend:()Ljavax/transaction/Transaction;
      45: pop
      46: goto          70
      49: astore_3
      50: getstatic     #11                 // Field com/arjuna/ats/jbossatx/logging/jbossatxLogger.i18NLogger:Lcom/arjuna/ats/jbossatx/logging/jbossatxI18NLogger;
      53: aload_3
      54: invokeinterface #12,  2           // InterfaceMethod com/arjuna/ats/jbossatx/logging/jbossatxI18NLogger.error_jts_InboundTransactionCurrentImple_exception:(Ljava/lang/Throwable;)V
      59: new           #13                 // class java/lang/RuntimeException
      62: dup
      63: ldc           #14                 // String InboundTransactionCurrentImple unable to determine inbound transaction context
      65: aload_3
      66: invokespecial #15                 // Method java/lang/RuntimeException."<init>":(Ljava/lang/String;Ljava/lang/Throwable;)V
      69: athrow
      70: getstatic     #2                  // Field com/arjuna/ats/jbossatx/logging/jbossatxLogger.logger:Lorg/jboss/logging/Logger;
      73: invokevirtual #3                  // Method org/jboss/logging/Logger.isTraceEnabled:()Z
      76: ifeq          104
      79: getstatic     #2                  // Field com/arjuna/ats/jbossatx/logging/jbossatxLogger.logger:Lorg/jboss/logging/Logger;
      82: new           #16                 // class java/lang/StringBuilder
      85: dup
      86: invokespecial #17                 // Method java/lang/StringBuilder."<init>":()V
      89: ldc           #18                 // String InboundTransactionCurrentImple.getCurrentTransaction() returning tx=
      91: invokevirtual #19                 // Method java/lang/StringBuilder.append:(Ljava/lang/String;)Ljava/lang/StringBuilder;
      94: aload_2
      95: invokevirtual #20                 // Method java/lang/StringBuilder.append:(Ljava/lang/Object;)Ljava/lang/StringBuilder;
      98: invokevirtual #21                 // Method java/lang/StringBuilder.toString:()Ljava/lang/String;
     101: invokevirtual #5                  // Method org/jboss/logging/Logger.trace:(Ljava/lang/Object;)V
     104: aload_2
     105: areturn
    Exception table:
       from    to  target type
          21    46    49   Class java/lang/Exception
}
