Compiled from "IterableUtil.java"
public final class org.assertj.core.util.IterableUtil {
  public static boolean isNullOrEmpty(java.lang.Iterable<?>);
    Code:
       0: aload_0
       1: ifnonnull     6
       4: iconst_1
       5: ireturn
       6: aload_0
       7: instanceof    #9                  // class java/util/Collection
      10: ifeq          27
      13: aload_0
      14: checkcast     #9                  // class java/util/Collection
      17: invokeinterface #13,  1           // InterfaceMethod java/util/Collection.isEmpty:()Z
      22: ifeq          27
      25: iconst_1
      26: ireturn
      27: aload_0
      28: invokeinterface #19,  1           // InterfaceMethod java/lang/Iterable.iterator:()Ljava/util/Iterator;
      33: invokeinterface #24,  1           // InterfaceMethod java/util/Iterator.hasNext:()Z
      38: ifne          45
      41: iconst_1
      42: goto          46
      45: iconst_0
      46: ireturn

  public static int sizeOf(java.lang.Iterable<?>);
    Code:
       0: aload_0
       1: ldc           #31                 // String Iterable must not be null
       3: invokestatic  #37                 // Method org/assertj/core/util/Preconditions.checkNotNull:(Ljava/lang/Object;Ljava/lang/String;)Ljava/lang/Object;
       6: pop
       7: aload_0
       8: instanceof    #9                  // class java/util/Collection
      11: ifeq          24
      14: aload_0
      15: checkcast     #9                  // class java/util/Collection
      18: invokeinterface #41,  1           // InterfaceMethod java/util/Collection.size:()I
      23: ireturn
      24: iconst_0
      25: istore_1
      26: aload_0
      27: invokeinterface #19,  1           // InterfaceMethod java/lang/Iterable.iterator:()Ljava/util/Iterator;
      32: astore_2
      33: aload_2
      34: invokeinterface #24,  1           // InterfaceMethod java/util/Iterator.hasNext:()Z
      39: ifeq          55
      42: iinc          1, 1
      45: aload_2
      46: invokeinterface #45,  1           // InterfaceMethod java/util/Iterator.next:()Ljava/lang/Object;
      51: pop
      52: goto          33
      55: iload_1
      56: ireturn

  public static <T> java.util.List<T> nonNullElementsIn(java.lang.Iterable<? extends T>);
    Code:
       0: aload_0
       1: invokestatic  #52                 // Method isNullOrEmpty:(Ljava/lang/Iterable;)Z
       4: ifeq          11
       7: invokestatic  #58                 // Method java/util/Collections.emptyList:()Ljava/util/List;
      10: areturn
      11: new           #60                 // class java/util/ArrayList
      14: dup
      15: invokespecial #64                 // Method java/util/ArrayList."<init>":()V
      18: astore_1
      19: aload_0
      20: invokeinterface #19,  1           // InterfaceMethod java/lang/Iterable.iterator:()Ljava/util/Iterator;
      25: astore_2
      26: aload_2
      27: invokeinterface #24,  1           // InterfaceMethod java/util/Iterator.hasNext:()Z
      32: ifeq          57
      35: aload_2
      36: invokeinterface #45,  1           // InterfaceMethod java/util/Iterator.next:()Ljava/lang/Object;
      41: astore_3
      42: aload_3
      43: ifnull        54
      46: aload_1
      47: aload_3
      48: invokeinterface #70,  2           // InterfaceMethod java/util/List.add:(Ljava/lang/Object;)Z
      53: pop
      54: goto          26
      57: aload_1
      58: areturn

  public static <T> T[] toArray(java.lang.Iterable<? extends T>);
    Code:
       0: aload_0
       1: ifnonnull     6
       4: aconst_null
       5: areturn
       6: aload_0
       7: invokestatic  #86                 // Method org/assertj/core/util/Lists.newArrayList:(Ljava/lang/Iterable;)Ljava/util/ArrayList;
      10: invokevirtual #89                 // Method java/util/ArrayList.toArray:()[Ljava/lang/Object;
      13: checkcast     #91                 // class "[Ljava/lang/Object;"
      16: areturn

  public static <T> T[] toArray(java.lang.Iterable<? extends T>, java.lang.Class<T>);
    Code:
       0: aload_0
       1: ifnonnull     6
       4: aconst_null
       5: areturn
       6: aload_0
       7: invokestatic  #96                 // Method toCollection:(Ljava/lang/Iterable;)Ljava/util/Collection;
      10: astore_2
      11: aload_1
      12: aload_2
      13: invokeinterface #41,  1           // InterfaceMethod java/util/Collection.size:()I
      18: invokestatic  #100                // Method newArray:(Ljava/lang/Class;I)[Ljava/lang/Object;
      21: astore_3
      22: aload_2
      23: aload_3
      24: invokeinterface #103,  2          // InterfaceMethod java/util/Collection.toArray:([Ljava/lang/Object;)[Ljava/lang/Object;
      29: areturn

  public static <T> java.util.Collection<T> toCollection(java.lang.Iterable<T>);
    Code:
       0: aload_0
       1: instanceof    #9                  // class java/util/Collection
       4: ifeq          14
       7: aload_0
       8: checkcast     #9                  // class java/util/Collection
      11: goto          18
      14: aload_0
      15: invokestatic  #86                 // Method org/assertj/core/util/Lists.newArrayList:(Ljava/lang/Iterable;)Ljava/util/ArrayList;
      18: areturn

  public static <T> java.lang.Iterable<T> iterable(T...);
    Code:
       0: aload_0
       1: ifnonnull     6
       4: aconst_null
       5: areturn
       6: invokestatic  #117                // Method org/assertj/core/util/Lists.newArrayList:()Ljava/util/ArrayList;
       9: astore_1
      10: aload_1
      11: aload_0
      12: invokestatic  #121                // Method java/util/Collections.addAll:(Ljava/util/Collection;[Ljava/lang/Object;)Z
      15: pop
      16: aload_1
      17: areturn

  public static <T> java.util.Iterator<T> iterator(T...);
    Code:
       0: aload_0
       1: ifnonnull     6
       4: aconst_null
       5: areturn
       6: aload_0
       7: invokestatic  #128                // Method iterable:([Ljava/lang/Object;)Ljava/lang/Iterable;
      10: invokeinterface #19,  1           // InterfaceMethod java/lang/Iterable.iterator:()Ljava/util/Iterator;
      15: areturn

  private static <T> T[] newArray(java.lang.Class<T>, int);
    Code:
       0: aload_0
       1: iload_1
       2: invokestatic  #134                // Method java/lang/reflect/Array.newInstance:(Ljava/lang/Class;I)Ljava/lang/Object;
       5: checkcast     #91                 // class "[Ljava/lang/Object;"
       8: checkcast     #91                 // class "[Ljava/lang/Object;"
      11: areturn

  private org.assertj.core.util.IterableUtil();
    Code:
       0: aload_0
       1: invokespecial #136                // Method java/lang/Object."<init>":()V
       4: return
}
