Compiled from "Strings.java"
public final class org.assertj.core.util.Strings {
  public static boolean isNullOrEmpty(java.lang.String);
    Code:
       0: aload_0
       1: ifnull        11
       4: aload_0
       5: invokevirtual #19                 // Method java/lang/String.length:()I
       8: ifne          15
      11: iconst_1
      12: goto          16
      15: iconst_0
      16: ireturn

  public static java.lang.String quote(java.lang.String);
    Code:
       0: aload_0
       1: ifnull        28
       4: iconst_3
       5: anewarray     #4                  // class java/lang/Object
       8: dup
       9: iconst_0
      10: ldc           #25                 // String \'
      12: aastore
      13: dup
      14: iconst_1
      15: aload_0
      16: aastore
      17: dup
      18: iconst_2
      19: ldc           #25                 // String \'
      21: aastore
      22: invokestatic  #29                 // Method concat:([Ljava/lang/Object;)Ljava/lang/String;
      25: goto          29
      28: aconst_null
      29: areturn

  public static java.lang.Object quote(java.lang.Object);
    Code:
       0: aload_0
       1: instanceof    #15                 // class java/lang/String
       4: ifeq          17
       7: aload_0
       8: invokevirtual #34                 // Method java/lang/Object.toString:()Ljava/lang/String;
      11: invokestatic  #36                 // Method quote:(Ljava/lang/String;)Ljava/lang/String;
      14: goto          18
      17: aload_0
      18: areturn

  public static java.lang.String concat(java.lang.Object...);
    Code:
       0: aload_0
       1: invokestatic  #43                 // Method org/assertj/core/util/Arrays.isNullOrEmpty:([Ljava/lang/Object;)Z
       4: ifeq          9
       7: aconst_null
       8: areturn
       9: new           #45                 // class java/lang/StringBuilder
      12: dup
      13: invokespecial #49                 // Method java/lang/StringBuilder."<init>":()V
      16: astore_1
      17: aload_0
      18: astore_2
      19: aload_2
      20: arraylength
      21: istore_3
      22: iconst_0
      23: istore        4
      25: iload         4
      27: iload_3
      28: if_icmpge     50
      31: aload_2
      32: iload         4
      34: aaload
      35: astore        5
      37: aload_1
      38: aload         5
      40: invokevirtual #55                 // Method java/lang/StringBuilder.append:(Ljava/lang/Object;)Ljava/lang/StringBuilder;
      43: pop
      44: iinc          4, 1
      47: goto          25
      50: aload_1
      51: invokevirtual #56                 // Method java/lang/StringBuilder.toString:()Ljava/lang/String;
      54: areturn

  public static java.lang.String formatIfArgs(java.lang.String, java.lang.Object...);
    Code:
       0: aload_1
       1: invokestatic  #43                 // Method org/assertj/core/util/Arrays.isNullOrEmpty:([Ljava/lang/Object;)Z
       4: ifeq          25
       7: aload_0
       8: ldc           #63                 // String %([^n])
      10: ldc           #65                 // String %%$1
      12: invokevirtual #69                 // Method java/lang/String.replaceAll:(Ljava/lang/String;Ljava/lang/String;)Ljava/lang/String;
      15: iconst_0
      16: anewarray     #4                  // class java/lang/Object
      19: invokestatic  #72                 // Method java/lang/String.format:(Ljava/lang/String;[Ljava/lang/Object;)Ljava/lang/String;
      22: goto          30
      25: aload_0
      26: aload_1
      27: invokestatic  #72                 // Method java/lang/String.format:(Ljava/lang/String;[Ljava/lang/Object;)Ljava/lang/String;
      30: areturn

  public static org.assertj.core.util.Strings$StringsToJoin join(java.lang.String...);
    Code:
       0: new           #10                 // class org/assertj/core/util/Strings$StringsToJoin
       3: dup
       4: aload_0
       5: invokespecial #79                 // Method org/assertj/core/util/Strings$StringsToJoin."<init>":([Ljava/lang/String;)V
       8: areturn

  public static org.assertj.core.util.Strings$StringsToJoin join(java.lang.Iterable<?>);
    Code:
       0: invokestatic  #88                 // Method org/assertj/core/util/Lists.newArrayList:()Ljava/util/ArrayList;
       3: astore_1
       4: aload_0
       5: invokeinterface #94,  1           // InterfaceMethod java/lang/Iterable.iterator:()Ljava/util/Iterator;
      10: astore_2
      11: aload_2
      12: invokeinterface #102,  1          // InterfaceMethod java/util/Iterator.hasNext:()Z
      17: ifeq          41
      20: aload_2
      21: invokeinterface #106,  1          // InterfaceMethod java/util/Iterator.next:()Ljava/lang/Object;
      26: astore_3
      27: aload_1
      28: aload_3
      29: invokestatic  #110                // Method java/lang/String.valueOf:(Ljava/lang/Object;)Ljava/lang/String;
      32: invokeinterface #114,  2          // InterfaceMethod java/util/List.add:(Ljava/lang/Object;)Z
      37: pop
      38: goto          11
      41: new           #10                 // class org/assertj/core/util/Strings$StringsToJoin
      44: dup
      45: aload_1
      46: aload_1
      47: invokeinterface #117,  1          // InterfaceMethod java/util/List.size:()I
      52: anewarray     #15                 // class java/lang/String
      55: invokeinterface #121,  2          // InterfaceMethod java/util/List.toArray:([Ljava/lang/Object;)[Ljava/lang/Object;
      60: checkcast     #122                // class "[Ljava/lang/String;"
      63: invokespecial #79                 // Method org/assertj/core/util/Strings$StringsToJoin."<init>":([Ljava/lang/String;)V
      66: areturn

  public static org.assertj.core.util.Strings$StringToAppend append(java.lang.String);
    Code:
       0: new           #7                  // class org/assertj/core/util/Strings$StringToAppend
       3: dup
       4: aload_0
       5: invokespecial #131                // Method org/assertj/core/util/Strings$StringToAppend."<init>":(Ljava/lang/String;)V
       8: areturn

  private org.assertj.core.util.Strings();
    Code:
       0: aload_0
       1: invokespecial #133                // Method java/lang/Object."<init>":()V
       4: return
}
