Compiled from "TransportConfigChecker.java"
public class org.joyqueue.client.internal.transport.config.TransportConfigChecker {
  public org.joyqueue.client.internal.transport.config.TransportConfigChecker();
    Code:
       0: aload_0
       1: invokespecial #1                  // Method java/lang/Object."<init>":()V
       4: return

  public static void check(org.joyqueue.client.internal.transport.config.TransportConfig);
    Code:
       0: aload_0
       1: ifnull        8
       4: iconst_1
       5: goto          9
       8: iconst_0
       9: ldc           #2                  // String transport not null
      11: invokestatic  #3                  // Method com/google/common/base/Preconditions.checkArgument:(ZLjava/lang/Object;)V
      14: aload_0
      15: invokevirtual #4                  // Method org/joyqueue/client/internal/transport/config/TransportConfig.getConnections:()I
      18: iconst_1
      19: if_icmplt     26
      22: iconst_1
      23: goto          27
      26: iconst_0
      27: ldc           #5                  // String transport.connections must be greater than 0
      29: invokestatic  #3                  // Method com/google/common/base/Preconditions.checkArgument:(ZLjava/lang/Object;)V
      32: return
}
