Compiled from "ValueEnum.java"
final class org.h2.value.ValueEnum$Validation extends java.lang.Enum<org.h2.value.ValueEnum$Validation> {
  public static final org.h2.value.ValueEnum$Validation DUPLICATE;

  public static final org.h2.value.ValueEnum$Validation EMPTY;

  public static final org.h2.value.ValueEnum$Validation INVALID;

  public static final org.h2.value.ValueEnum$Validation VALID;

  private static final org.h2.value.ValueEnum$Validation[] $VALUES;

  public static org.h2.value.ValueEnum$Validation[] values();
    Code:
       0: getstatic     #1                  // Field $VALUES:[Lorg/h2/value/ValueEnum$Validation;
       3: invokevirtual #2                  // Method "[Lorg/h2/value/ValueEnum$Validation;".clone:()Ljava/lang/Object;
       6: checkcast     #3                  // class "[Lorg/h2/value/ValueEnum$Validation;"
       9: areturn

  public static org.h2.value.ValueEnum$Validation valueOf(java.lang.String);
    Code:
       0: ldc_w         #4                  // class org/h2/value/ValueEnum$Validation
       3: aload_0
       4: invokestatic  #5                  // Method java/lang/Enum.valueOf:(Ljava/lang/Class;Ljava/lang/String;)Ljava/lang/Enum;
       7: checkcast     #4                  // class org/h2/value/ValueEnum$Validation
      10: areturn

  private org.h2.value.ValueEnum$Validation();
    Code:
       0: aload_0
       1: aload_1
       2: iload_2
       3: invokespecial #6                  // Method java/lang/Enum."<init>":(Ljava/lang/String;I)V
       6: return

  static {};
    Code:
       0: new           #4                  // class org/h2/value/ValueEnum$Validation
       3: dup
       4: ldc           #7                  // String DUPLICATE
       6: iconst_0
       7: invokespecial #8                  // Method "<init>":(Ljava/lang/String;I)V
      10: putstatic     #9                  // Field DUPLICATE:Lorg/h2/value/ValueEnum$Validation;
      13: new           #4                  // class org/h2/value/ValueEnum$Validation
      16: dup
      17: ldc           #10                 // String EMPTY
      19: iconst_1
      20: invokespecial #8                  // Method "<init>":(Ljava/lang/String;I)V
      23: putstatic     #11                 // Field EMPTY:Lorg/h2/value/ValueEnum$Validation;
      26: new           #4                  // class org/h2/value/ValueEnum$Validation
      29: dup
      30: ldc           #12                 // String INVALID
      32: iconst_2
      33: invokespecial #8                  // Method "<init>":(Ljava/lang/String;I)V
      36: putstatic     #13                 // Field INVALID:Lorg/h2/value/ValueEnum$Validation;
      39: new           #4                  // class org/h2/value/ValueEnum$Validation
      42: dup
      43: ldc           #14                 // String VALID
      45: iconst_3
      46: invokespecial #8                  // Method "<init>":(Ljava/lang/String;I)V
      49: putstatic     #15                 // Field VALID:Lorg/h2/value/ValueEnum$Validation;
      52: iconst_4
      53: anewarray     #4                  // class org/h2/value/ValueEnum$Validation
      56: dup
      57: iconst_0
      58: getstatic     #9                  // Field DUPLICATE:Lorg/h2/value/ValueEnum$Validation;
      61: aastore
      62: dup
      63: iconst_1
      64: getstatic     #11                 // Field EMPTY:Lorg/h2/value/ValueEnum$Validation;
      67: aastore
      68: dup
      69: iconst_2
      70: getstatic     #13                 // Field INVALID:Lorg/h2/value/ValueEnum$Validation;
      73: aastore
      74: dup
      75: iconst_3
      76: getstatic     #15                 // Field VALID:Lorg/h2/value/ValueEnum$Validation;
      79: aastore
      80: putstatic     #1                  // Field $VALUES:[Lorg/h2/value/ValueEnum$Validation;
      83: return
}
