Compiled from "AbstractRepositoryRouteResourceHandler.java"
public abstract class org.sonatype.nexus.rest.routes.AbstractRepositoryRouteResourceHandler extends org.sonatype.nexus.rest.AbstractNexusResourceHandler {
  public org.sonatype.nexus.rest.routes.AbstractRepositoryRouteResourceHandler(org.restlet.Context, org.restlet.data.Request, org.restlet.data.Response);
    Code:
       0: aload_0
       1: aload_1
       2: aload_2
       3: aload_3
       4: invokespecial #1                  // Method org/sonatype/nexus/rest/AbstractNexusResourceHandler."<init>":(Lorg/restlet/Context;Lorg/restlet/data/Request;Lorg/restlet/data/Response;)V
       7: return

  protected java.util.List<org.sonatype.nexus.rest.model.RepositoryRouteMemberRepository> getRepositoryRouteMemberRepositoryList(org.restlet.data.Reference, java.util.List<java.lang.String>) throws org.sonatype.nexus.proxy.NoSuchRepositoryException;
    Code:
       0: new           #2                  // class java/util/ArrayList
       3: dup
       4: aload_2
       5: invokeinterface #3,  1            // InterfaceMethod java/util/List.size:()I
      10: invokespecial #4                  // Method java/util/ArrayList."<init>":(I)V
      13: astore_3
      14: aload_2
      15: invokeinterface #5,  1            // InterfaceMethod java/util/List.iterator:()Ljava/util/Iterator;
      20: astore        4
      22: aload         4
      24: invokeinterface #6,  1            // InterfaceMethod java/util/Iterator.hasNext:()Z
      29: ifeq          140
      32: aload         4
      34: invokeinterface #7,  1            // InterfaceMethod java/util/Iterator.next:()Ljava/lang/Object;
      39: checkcast     #8                  // class java/lang/String
      42: astore        5
      44: new           #9                  // class org/sonatype/nexus/rest/model/RepositoryRouteMemberRepository
      47: dup
      48: invokespecial #10                 // Method org/sonatype/nexus/rest/model/RepositoryRouteMemberRepository."<init>":()V
      51: astore        6
      53: ldc           #11                 // String *
      55: aload         5
      57: invokevirtual #12                 // Method java/lang/String.equals:(Ljava/lang/Object;)Z
      60: ifeq          86
      63: aload         6
      65: ldc           #11                 // String *
      67: invokevirtual #13                 // Method org/sonatype/nexus/rest/model/RepositoryRouteMemberRepository.setId:(Ljava/lang/String;)V
      70: aload         6
      72: ldc           #14                 // String ALL
      74: invokevirtual #15                 // Method org/sonatype/nexus/rest/model/RepositoryRouteMemberRepository.setName:(Ljava/lang/String;)V
      77: aload         6
      79: aconst_null
      80: invokevirtual #16                 // Method org/sonatype/nexus/rest/model/RepositoryRouteMemberRepository.setResourceURI:(Ljava/lang/String;)V
      83: goto          128
      86: aload         6
      88: aload         5
      90: invokevirtual #13                 // Method org/sonatype/nexus/rest/model/RepositoryRouteMemberRepository.setId:(Ljava/lang/String;)V
      93: aload         6
      95: aload_0
      96: invokevirtual #17                 // Method getNexus:()Lorg/sonatype/nexus/Nexus;
      99: aload         5
     101: invokeinterface #18,  2           // InterfaceMethod org/sonatype/nexus/Nexus.getRepository:(Ljava/lang/String;)Lorg/sonatype/nexus/proxy/repository/Repository;
     106: invokeinterface #19,  1           // InterfaceMethod org/sonatype/nexus/proxy/repository/Repository.getName:()Ljava/lang/String;
     111: invokevirtual #15                 // Method org/sonatype/nexus/rest/model/RepositoryRouteMemberRepository.setName:(Ljava/lang/String;)V
     114: aload         6
     116: aload_0
     117: aload         5
     119: invokevirtual #20                 // Method calculateRepositoryReference:(Ljava/lang/String;)Lorg/restlet/data/Reference;
     122: invokevirtual #21                 // Method org/restlet/data/Reference.toString:()Ljava/lang/String;
     125: invokevirtual #16                 // Method org/sonatype/nexus/rest/model/RepositoryRouteMemberRepository.setResourceURI:(Ljava/lang/String;)V
     128: aload_3
     129: aload         6
     131: invokeinterface #22,  2           // InterfaceMethod java/util/List.add:(Ljava/lang/Object;)Z
     136: pop
     137: goto          22
     140: aload_3
     141: areturn

  protected java.lang.String resource2configType(java.lang.String);
    Code:
       0: ldc           #23                 // String inclusive
       2: aload_1
       3: invokevirtual #12                 // Method java/lang/String.equals:(Ljava/lang/Object;)Z
       6: ifeq          12
       9: ldc           #23                 // String inclusive
      11: areturn
      12: ldc           #24                 // String exclusive
      14: aload_1
      15: invokevirtual #12                 // Method java/lang/String.equals:(Ljava/lang/Object;)Z
      18: ifeq          24
      21: ldc           #24                 // String exclusive
      23: areturn
      24: ldc           #25                 // String blocking
      26: aload_1
      27: invokevirtual #12                 // Method java/lang/String.equals:(Ljava/lang/Object;)Z
      30: ifeq          36
      33: ldc           #25                 // String blocking
      35: areturn
      36: aconst_null
      37: areturn

  protected java.lang.String config2resourceType(java.lang.String);
    Code:
       0: ldc           #23                 // String inclusive
       2: aload_1
       3: invokevirtual #12                 // Method java/lang/String.equals:(Ljava/lang/Object;)Z
       6: ifeq          12
       9: ldc           #23                 // String inclusive
      11: areturn
      12: ldc           #24                 // String exclusive
      14: aload_1
      15: invokevirtual #12                 // Method java/lang/String.equals:(Ljava/lang/Object;)Z
      18: ifeq          24
      21: ldc           #24                 // String exclusive
      23: areturn
      24: ldc           #25                 // String blocking
      26: aload_1
      27: invokevirtual #12                 // Method java/lang/String.equals:(Ljava/lang/Object;)Z
      30: ifeq          36
      33: ldc           #25                 // String blocking
      35: areturn
      36: aconst_null
      37: areturn
}
