Compiled from "ChoiceBoxSkin.java"
public class javafx.scene.control.skin.ChoiceBoxSkin<T> extends javafx.scene.control.SkinBase<javafx.scene.control.ChoiceBox<T>> {
  private javafx.collections.ObservableList<T> choiceBoxItems;

  private javafx.scene.control.ContextMenu popup;

  private javafx.scene.layout.StackPane openButton;

  private final javafx.scene.control.ToggleGroup toggleGroup;

  private javafx.scene.control.SelectionModel<T> selectionModel;

  private javafx.scene.control.Label label;

  private final com.sun.javafx.scene.control.behavior.BehaviorBase<javafx.scene.control.ChoiceBox<T>> behavior;

  private final javafx.collections.ListChangeListener<T> choiceBoxItemsListener;

  private final javafx.collections.WeakListChangeListener<T> weakChoiceBoxItemsListener;

  private final javafx.beans.InvalidationListener itemsObserver;

  private javafx.beans.InvalidationListener selectionChangeListener;

  public javafx.scene.control.skin.ChoiceBoxSkin(javafx.scene.control.ChoiceBox<T>);
    Code:
       0: aload_0
       1: aload_1
       2: invokespecial #5                  // Method javafx/scene/control/SkinBase."<init>":(Ljavafx/scene/control/Control;)V
       5: aload_0
       6: new           #6                  // class javafx/scene/control/ToggleGroup
       9: dup
      10: invokespecial #7                  // Method javafx/scene/control/ToggleGroup."<init>":()V
      13: putfield      #4                  // Field toggleGroup:Ljavafx/scene/control/ToggleGroup;
      16: aload_0
      17: new           #8                  // class javafx/scene/control/skin/ChoiceBoxSkin$1
      20: dup
      21: aload_0
      22: invokespecial #9                  // Method javafx/scene/control/skin/ChoiceBoxSkin$1."<init>":(Ljavafx/scene/control/skin/ChoiceBoxSkin;)V
      25: putfield      #10                 // Field choiceBoxItemsListener:Ljavafx/collections/ListChangeListener;
      28: aload_0
      29: new           #11                 // class javafx/collections/WeakListChangeListener
      32: dup
      33: aload_0
      34: getfield      #10                 // Field choiceBoxItemsListener:Ljavafx/collections/ListChangeListener;
      37: invokespecial #12                 // Method javafx/collections/WeakListChangeListener."<init>":(Ljavafx/collections/ListChangeListener;)V
      40: putfield      #13                 // Field weakChoiceBoxItemsListener:Ljavafx/collections/WeakListChangeListener;
      43: aload_0
      44: aload_0
      45: invokedynamic #14,  0             // InvokeDynamic #0:invalidated:(Ljavafx/scene/control/skin/ChoiceBoxSkin;)Ljavafx/beans/InvalidationListener;
      50: putfield      #15                 // Field selectionChangeListener:Ljavafx/beans/InvalidationListener;
      53: aload_0
      54: new           #16                 // class com/sun/javafx/scene/control/behavior/ChoiceBoxBehavior
      57: dup
      58: aload_1
      59: invokespecial #17                 // Method com/sun/javafx/scene/control/behavior/ChoiceBoxBehavior."<init>":(Ljavafx/scene/control/ChoiceBox;)V
      62: putfield      #18                 // Field behavior:Lcom/sun/javafx/scene/control/behavior/BehaviorBase;
      65: aload_0
      66: invokespecial #19                 // Method initialize:()V
      69: aload_0
      70: aload_0
      71: invokedynamic #20,  0             // InvokeDynamic #1:invalidated:(Ljavafx/scene/control/skin/ChoiceBoxSkin;)Ljavafx/beans/InvalidationListener;
      76: putfield      #21                 // Field itemsObserver:Ljavafx/beans/InvalidationListener;
      79: aload_1
      80: invokevirtual #22                 // Method javafx/scene/control/ChoiceBox.itemsProperty:()Ljavafx/beans/property/ObjectProperty;
      83: new           #23                 // class javafx/beans/WeakInvalidationListener
      86: dup
      87: aload_0
      88: getfield      #21                 // Field itemsObserver:Ljavafx/beans/InvalidationListener;
      91: invokespecial #24                 // Method javafx/beans/WeakInvalidationListener."<init>":(Ljavafx/beans/InvalidationListener;)V
      94: invokevirtual #25                 // Method javafx/beans/property/ObjectProperty.addListener:(Ljavafx/beans/InvalidationListener;)V
      97: aload_1
      98: invokevirtual #26                 // Method javafx/scene/control/ChoiceBox.requestLayout:()V
     101: aload_0
     102: aload_1
     103: invokevirtual #27                 // Method javafx/scene/control/ChoiceBox.selectionModelProperty:()Ljavafx/beans/property/ObjectProperty;
     106: aload_0
     107: invokedynamic #28,  0             // InvokeDynamic #2:accept:(Ljavafx/scene/control/skin/ChoiceBoxSkin;)Ljava/util/function/Consumer;
     112: invokevirtual #29                 // Method registerChangeListener:(Ljavafx/beans/value/ObservableValue;Ljava/util/function/Consumer;)V
     115: aload_0
     116: aload_1
     117: invokevirtual #30                 // Method javafx/scene/control/ChoiceBox.showingProperty:()Ljavafx/beans/property/ReadOnlyBooleanProperty;
     120: aload_0
     121: invokedynamic #31,  0             // InvokeDynamic #3:accept:(Ljavafx/scene/control/skin/ChoiceBoxSkin;)Ljava/util/function/Consumer;
     126: invokevirtual #29                 // Method registerChangeListener:(Ljavafx/beans/value/ObservableValue;Ljava/util/function/Consumer;)V
     129: aload_0
     130: aload_1
     131: invokevirtual #22                 // Method javafx/scene/control/ChoiceBox.itemsProperty:()Ljavafx/beans/property/ObjectProperty;
     134: aload_0
     135: invokedynamic #32,  0             // InvokeDynamic #4:accept:(Ljavafx/scene/control/skin/ChoiceBoxSkin;)Ljava/util/function/Consumer;
     140: invokevirtual #29                 // Method registerChangeListener:(Ljavafx/beans/value/ObservableValue;Ljava/util/function/Consumer;)V
     143: aload_0
     144: aload_1
     145: invokevirtual #33                 // Method javafx/scene/control/ChoiceBox.getSelectionModel:()Ljavafx/scene/control/SingleSelectionModel;
     148: invokevirtual #34                 // Method javafx/scene/control/SingleSelectionModel.selectedItemProperty:()Ljavafx/beans/property/ReadOnlyObjectProperty;
     151: aload_0
     152: invokedynamic #35,  0             // InvokeDynamic #5:accept:(Ljavafx/scene/control/skin/ChoiceBoxSkin;)Ljava/util/function/Consumer;
     157: invokevirtual #29                 // Method registerChangeListener:(Ljavafx/beans/value/ObservableValue;Ljava/util/function/Consumer;)V
     160: aload_0
     161: aload_1
     162: invokevirtual #36                 // Method javafx/scene/control/ChoiceBox.converterProperty:()Ljavafx/beans/property/ObjectProperty;
     165: aload_0
     166: invokedynamic #37,  0             // InvokeDynamic #6:accept:(Ljavafx/scene/control/skin/ChoiceBoxSkin;)Ljava/util/function/Consumer;
     171: invokevirtual #29                 // Method registerChangeListener:(Ljavafx/beans/value/ObservableValue;Ljava/util/function/Consumer;)V
     174: return

  public void dispose();
    Code:
       0: aload_0
       1: invokespecial #38                 // Method javafx/scene/control/SkinBase.dispose:()V
       4: aload_0
       5: getfield      #18                 // Field behavior:Lcom/sun/javafx/scene/control/behavior/BehaviorBase;
       8: ifnull        18
      11: aload_0
      12: getfield      #18                 // Field behavior:Lcom/sun/javafx/scene/control/behavior/BehaviorBase;
      15: invokevirtual #39                 // Method com/sun/javafx/scene/control/behavior/BehaviorBase.dispose:()V
      18: return

  protected void layoutChildren(double, double, double, double);
    Code:
       0: aload_0
       1: getfield      #40                 // Field openButton:Ljavafx/scene/layout/StackPane;
       4: ldc2_w        #41                 // double -1.0d
       7: invokevirtual #43                 // Method javafx/scene/layout/StackPane.prefWidth:(D)D
      10: dstore        9
      12: aload_0
      13: getfield      #44                 // Field label:Ljavafx/scene/control/Label;
      16: dload_1
      17: dload_3
      18: dload         5
      20: dload         7
      22: invokevirtual #45                 // Method javafx/scene/control/Label.resizeRelocate:(DDDD)V
      25: aload_0
      26: getfield      #40                 // Field openButton:Ljavafx/scene/layout/StackPane;
      29: dload         9
      31: aload_0
      32: getfield      #40                 // Field openButton:Ljavafx/scene/layout/StackPane;
      35: ldc2_w        #41                 // double -1.0d
      38: invokevirtual #46                 // Method javafx/scene/layout/StackPane.prefHeight:(D)D
      41: invokevirtual #47                 // Method javafx/scene/layout/StackPane.resize:(DD)V
      44: aload_0
      45: aload_0
      46: getfield      #40                 // Field openButton:Ljavafx/scene/layout/StackPane;
      49: dload_1
      50: dload         5
      52: dadd
      53: dload         9
      55: dsub
      56: dload_3
      57: dload         9
      59: dload         7
      61: dconst_0
      62: getstatic     #48                 // Field javafx/geometry/HPos.CENTER:Ljavafx/geometry/HPos;
      65: getstatic     #49                 // Field javafx/geometry/VPos.CENTER:Ljavafx/geometry/VPos;
      68: invokevirtual #50                 // Method positionInArea:(Ljavafx/scene/Node;DDDDDLjavafx/geometry/HPos;Ljavafx/geometry/VPos;)V
      71: return

  protected double computeMinWidth(double, double, double, double, double);
    Code:
       0: aload_0
       1: getfield      #44                 // Field label:Ljavafx/scene/control/Label;
       4: ldc2_w        #41                 // double -1.0d
       7: invokevirtual #51                 // Method javafx/scene/control/Label.minWidth:(D)D
      10: aload_0
      11: getfield      #40                 // Field openButton:Ljavafx/scene/layout/StackPane;
      14: ldc2_w        #41                 // double -1.0d
      17: invokevirtual #52                 // Method javafx/scene/layout/StackPane.minWidth:(D)D
      20: dadd
      21: dstore        11
      23: aload_0
      24: getfield      #3                  // Field popup:Ljavafx/scene/control/ContextMenu;
      27: ldc2_w        #41                 // double -1.0d
      30: invokevirtual #53                 // Method javafx/scene/control/ContextMenu.minWidth:(D)D
      33: dstore        13
      35: dload         9
      37: dload         11
      39: dload         13
      41: invokestatic  #54                 // Method java/lang/Math.max:(DD)D
      44: dadd
      45: dload         5
      47: dadd
      48: dreturn

  protected double computeMinHeight(double, double, double, double, double);
    Code:
       0: aload_0
       1: getfield      #44                 // Field label:Ljavafx/scene/control/Label;
       4: ldc2_w        #41                 // double -1.0d
       7: invokevirtual #55                 // Method javafx/scene/control/Label.minHeight:(D)D
      10: dstore        11
      12: aload_0
      13: getfield      #40                 // Field openButton:Ljavafx/scene/layout/StackPane;
      16: ldc2_w        #41                 // double -1.0d
      19: invokevirtual #56                 // Method javafx/scene/layout/StackPane.minHeight:(D)D
      22: dstore        13
      24: dload_3
      25: dload         11
      27: dload         13
      29: invokestatic  #54                 // Method java/lang/Math.max:(DD)D
      32: dadd
      33: dload         7
      35: dadd
      36: dreturn

  protected double computePrefWidth(double, double, double, double, double);
    Code:
       0: aload_0
       1: getfield      #44                 // Field label:Ljavafx/scene/control/Label;
       4: ldc2_w        #41                 // double -1.0d
       7: invokevirtual #57                 // Method javafx/scene/control/Label.prefWidth:(D)D
      10: aload_0
      11: getfield      #40                 // Field openButton:Ljavafx/scene/layout/StackPane;
      14: ldc2_w        #41                 // double -1.0d
      17: invokevirtual #43                 // Method javafx/scene/layout/StackPane.prefWidth:(D)D
      20: dadd
      21: dstore        11
      23: aload_0
      24: getfield      #3                  // Field popup:Ljavafx/scene/control/ContextMenu;
      27: ldc2_w        #41                 // double -1.0d
      30: invokevirtual #58                 // Method javafx/scene/control/ContextMenu.prefWidth:(D)D
      33: dstore        13
      35: dload         13
      37: dconst_0
      38: dcmpg
      39: ifgt          91
      42: aload_0
      43: getfield      #3                  // Field popup:Ljavafx/scene/control/ContextMenu;
      46: invokevirtual #59                 // Method javafx/scene/control/ContextMenu.getItems:()Ljavafx/collections/ObservableList;
      49: invokeinterface #60,  1           // InterfaceMethod javafx/collections/ObservableList.size:()I
      54: ifle          91
      57: new           #61                 // class javafx/scene/text/Text
      60: dup
      61: aload_0
      62: getfield      #3                  // Field popup:Ljavafx/scene/control/ContextMenu;
      65: invokevirtual #59                 // Method javafx/scene/control/ContextMenu.getItems:()Ljavafx/collections/ObservableList;
      68: iconst_0
      69: invokeinterface #62,  2           // InterfaceMethod javafx/collections/ObservableList.get:(I)Ljava/lang/Object;
      74: checkcast     #63                 // class javafx/scene/control/MenuItem
      77: invokevirtual #64                 // Method javafx/scene/control/MenuItem.getText:()Ljava/lang/String;
      80: invokespecial #65                 // Method javafx/scene/text/Text."<init>":(Ljava/lang/String;)V
      83: ldc2_w        #41                 // double -1.0d
      86: invokevirtual #66                 // Method javafx/scene/text/Text.prefWidth:(D)D
      89: dstore        13
      91: aload_0
      92: getfield      #3                  // Field popup:Ljavafx/scene/control/ContextMenu;
      95: invokevirtual #59                 // Method javafx/scene/control/ContextMenu.getItems:()Ljavafx/collections/ObservableList;
      98: invokeinterface #60,  1           // InterfaceMethod javafx/collections/ObservableList.size:()I
     103: ifne          112
     106: ldc2_w        #67                 // double 50.0d
     109: goto          125
     112: dload         9
     114: dload         11
     116: dload         13
     118: invokestatic  #54                 // Method java/lang/Math.max:(DD)D
     121: dadd
     122: dload         5
     124: dadd
     125: dreturn

  protected double computePrefHeight(double, double, double, double, double);
    Code:
       0: aload_0
       1: getfield      #44                 // Field label:Ljavafx/scene/control/Label;
       4: ldc2_w        #41                 // double -1.0d
       7: invokevirtual #69                 // Method javafx/scene/control/Label.prefHeight:(D)D
      10: dstore        11
      12: aload_0
      13: getfield      #40                 // Field openButton:Ljavafx/scene/layout/StackPane;
      16: ldc2_w        #41                 // double -1.0d
      19: invokevirtual #46                 // Method javafx/scene/layout/StackPane.prefHeight:(D)D
      22: dstore        13
      24: dload_3
      25: dload         11
      27: dload         13
      29: invokestatic  #54                 // Method java/lang/Math.max:(DD)D
      32: dadd
      33: dload         7
      35: dadd
      36: dreturn

  protected double computeMaxHeight(double, double, double, double, double);
    Code:
       0: aload_0
       1: invokevirtual #70                 // Method getSkinnable:()Ljavafx/scene/control/Control;
       4: checkcast     #71                 // class javafx/scene/control/ChoiceBox
       7: dload_1
       8: invokevirtual #72                 // Method javafx/scene/control/ChoiceBox.prefHeight:(D)D
      11: dreturn

  protected double computeMaxWidth(double, double, double, double, double);
    Code:
       0: aload_0
       1: invokevirtual #70                 // Method getSkinnable:()Ljavafx/scene/control/Control;
       4: checkcast     #71                 // class javafx/scene/control/ChoiceBox
       7: dload_1
       8: invokevirtual #73                 // Method javafx/scene/control/ChoiceBox.prefWidth:(D)D
      11: dreturn

  private void initialize();
    Code:
       0: aload_0
       1: invokespecial #74                 // Method updateChoiceBoxItems:()V
       4: aload_0
       5: new           #75                 // class javafx/scene/control/Label
       8: dup
       9: invokespecial #76                 // Method javafx/scene/control/Label."<init>":()V
      12: putfield      #44                 // Field label:Ljavafx/scene/control/Label;
      15: aload_0
      16: getfield      #44                 // Field label:Ljavafx/scene/control/Label;
      19: iconst_0
      20: invokevirtual #77                 // Method javafx/scene/control/Label.setMnemonicParsing:(Z)V
      23: aload_0
      24: new           #78                 // class javafx/scene/layout/StackPane
      27: dup
      28: invokespecial #79                 // Method javafx/scene/layout/StackPane."<init>":()V
      31: putfield      #40                 // Field openButton:Ljavafx/scene/layout/StackPane;
      34: aload_0
      35: getfield      #40                 // Field openButton:Ljavafx/scene/layout/StackPane;
      38: invokevirtual #80                 // Method javafx/scene/layout/StackPane.getStyleClass:()Ljavafx/collections/ObservableList;
      41: iconst_1
      42: anewarray     #81                 // class java/lang/String
      45: dup
      46: iconst_0
      47: ldc           #82                 // String open-button
      49: aastore
      50: invokeinterface #83,  2           // InterfaceMethod javafx/collections/ObservableList.setAll:([Ljava/lang/Object;)Z
      55: pop
      56: new           #78                 // class javafx/scene/layout/StackPane
      59: dup
      60: invokespecial #79                 // Method javafx/scene/layout/StackPane."<init>":()V
      63: astore_1
      64: aload_1
      65: invokevirtual #80                 // Method javafx/scene/layout/StackPane.getStyleClass:()Ljavafx/collections/ObservableList;
      68: iconst_1
      69: anewarray     #81                 // class java/lang/String
      72: dup
      73: iconst_0
      74: ldc           #84                 // String arrow
      76: aastore
      77: invokeinterface #83,  2           // InterfaceMethod javafx/collections/ObservableList.setAll:([Ljava/lang/Object;)Z
      82: pop
      83: aload_0
      84: getfield      #40                 // Field openButton:Ljavafx/scene/layout/StackPane;
      87: invokevirtual #85                 // Method javafx/scene/layout/StackPane.getChildren:()Ljavafx/collections/ObservableList;
      90: invokeinterface #86,  1           // InterfaceMethod javafx/collections/ObservableList.clear:()V
      95: aload_0
      96: getfield      #40                 // Field openButton:Ljavafx/scene/layout/StackPane;
      99: invokevirtual #85                 // Method javafx/scene/layout/StackPane.getChildren:()Ljavafx/collections/ObservableList;
     102: iconst_1
     103: anewarray     #87                 // class javafx/scene/Node
     106: dup
     107: iconst_0
     108: aload_1
     109: aastore
     110: invokeinterface #88,  2           // InterfaceMethod javafx/collections/ObservableList.addAll:([Ljava/lang/Object;)Z
     115: pop
     116: aload_0
     117: new           #89                 // class javafx/scene/control/ContextMenu
     120: dup
     121: invokespecial #90                 // Method javafx/scene/control/ContextMenu."<init>":()V
     124: putfield      #3                  // Field popup:Ljavafx/scene/control/ContextMenu;
     127: aload_0
     128: getfield      #3                  // Field popup:Ljavafx/scene/control/ContextMenu;
     131: invokevirtual #91                 // Method javafx/scene/control/ContextMenu.showingProperty:()Ljavafx/beans/property/ReadOnlyBooleanProperty;
     134: aload_0
     135: invokedynamic #92,  0             // InvokeDynamic #7:changed:(Ljavafx/scene/control/skin/ChoiceBoxSkin;)Ljavafx/beans/value/ChangeListener;
     140: invokevirtual #93                 // Method javafx/beans/property/ReadOnlyBooleanProperty.addListener:(Ljavafx/beans/value/ChangeListener;)V
     143: aload_0
     144: getfield      #3                  // Field popup:Ljavafx/scene/control/ContextMenu;
     147: ldc           #94                 // String choice-box-popup-menu
     149: invokevirtual #95                 // Method javafx/scene/control/ContextMenu.setId:(Ljava/lang/String;)V
     152: aload_0
     153: invokevirtual #96                 // Method getChildren:()Ljavafx/collections/ObservableList;
     156: iconst_2
     157: anewarray     #87                 // class javafx/scene/Node
     160: dup
     161: iconst_0
     162: aload_0
     163: getfield      #44                 // Field label:Ljavafx/scene/control/Label;
     166: aastore
     167: dup
     168: iconst_1
     169: aload_0
     170: getfield      #40                 // Field openButton:Ljavafx/scene/layout/StackPane;
     173: aastore
     174: invokeinterface #83,  2           // InterfaceMethod javafx/collections/ObservableList.setAll:([Ljava/lang/Object;)Z
     179: pop
     180: aload_0
     181: invokespecial #97                 // Method updatePopupItems:()V
     184: aload_0
     185: invokespecial #98                 // Method updateSelectionModel:()V
     188: aload_0
     189: invokespecial #1                  // Method updateSelection:()V
     192: aload_0
     193: getfield      #99                 // Field selectionModel:Ljavafx/scene/control/SelectionModel;
     196: ifnull        219
     199: aload_0
     200: getfield      #99                 // Field selectionModel:Ljavafx/scene/control/SelectionModel;
     203: invokevirtual #100                // Method javafx/scene/control/SelectionModel.getSelectedIndex:()I
     206: iconst_m1
     207: if_icmpne     219
     210: aload_0
     211: getfield      #44                 // Field label:Ljavafx/scene/control/Label;
     214: ldc           #101                // String
     216: invokevirtual #102                // Method javafx/scene/control/Label.setText:(Ljava/lang/String;)V
     219: return

  private void updateChoiceBoxItems();
    Code:
       0: aload_0
       1: getfield      #103                // Field choiceBoxItems:Ljavafx/collections/ObservableList;
       4: ifnull        20
       7: aload_0
       8: getfield      #103                // Field choiceBoxItems:Ljavafx/collections/ObservableList;
      11: aload_0
      12: getfield      #13                 // Field weakChoiceBoxItemsListener:Ljavafx/collections/WeakListChangeListener;
      15: invokeinterface #104,  2          // InterfaceMethod javafx/collections/ObservableList.removeListener:(Ljavafx/collections/ListChangeListener;)V
      20: aload_0
      21: aload_0
      22: invokevirtual #70                 // Method getSkinnable:()Ljavafx/scene/control/Control;
      25: checkcast     #71                 // class javafx/scene/control/ChoiceBox
      28: invokevirtual #105                // Method javafx/scene/control/ChoiceBox.getItems:()Ljavafx/collections/ObservableList;
      31: putfield      #103                // Field choiceBoxItems:Ljavafx/collections/ObservableList;
      34: aload_0
      35: getfield      #103                // Field choiceBoxItems:Ljavafx/collections/ObservableList;
      38: ifnull        54
      41: aload_0
      42: getfield      #103                // Field choiceBoxItems:Ljavafx/collections/ObservableList;
      45: aload_0
      46: getfield      #13                 // Field weakChoiceBoxItemsListener:Ljavafx/collections/WeakListChangeListener;
      49: invokeinterface #106,  2          // InterfaceMethod javafx/collections/ObservableList.addListener:(Ljavafx/collections/ListChangeListener;)V
      54: return

  java.lang.String getChoiceBoxSelectedText();
    Code:
       0: aload_0
       1: getfield      #44                 // Field label:Ljavafx/scene/control/Label;
       4: invokevirtual #107                // Method javafx/scene/control/Label.getText:()Ljava/lang/String;
       7: areturn

  private void addPopupItem(T, int);
    Code:
       0: aconst_null
       1: astore_3
       2: aload_1
       3: instanceof    #108                // class javafx/scene/control/Separator
       6: ifeq          20
       9: new           #109                // class javafx/scene/control/SeparatorMenuItem
      12: dup
      13: invokespecial #110                // Method javafx/scene/control/SeparatorMenuItem."<init>":()V
      16: astore_3
      17: goto          120
      20: aload_1
      21: instanceof    #109                // class javafx/scene/control/SeparatorMenuItem
      24: ifeq          35
      27: aload_1
      28: checkcast     #109                // class javafx/scene/control/SeparatorMenuItem
      31: astore_3
      32: goto          120
      35: aload_0
      36: invokevirtual #70                 // Method getSkinnable:()Ljavafx/scene/control/Control;
      39: checkcast     #71                 // class javafx/scene/control/ChoiceBox
      42: invokevirtual #111                // Method javafx/scene/control/ChoiceBox.getConverter:()Ljavafx/util/StringConverter;
      45: astore        4
      47: aload         4
      49: ifnonnull     68
      52: aload_1
      53: ifnonnull     61
      56: ldc           #101                // String
      58: goto          74
      61: aload_1
      62: invokevirtual #112                // Method java/lang/Object.toString:()Ljava/lang/String;
      65: goto          74
      68: aload         4
      70: aload_1
      71: invokevirtual #113                // Method javafx/util/StringConverter.toString:(Ljava/lang/Object;)Ljava/lang/String;
      74: astore        5
      76: new           #114                // class javafx/scene/control/RadioMenuItem
      79: dup
      80: aload         5
      82: invokespecial #115                // Method javafx/scene/control/RadioMenuItem."<init>":(Ljava/lang/String;)V
      85: astore        6
      87: aload         6
      89: ldc           #116                // String choice-box-menu-item
      91: invokevirtual #117                // Method javafx/scene/control/RadioMenuItem.setId:(Ljava/lang/String;)V
      94: aload         6
      96: aload_0
      97: getfield      #4                  // Field toggleGroup:Ljavafx/scene/control/ToggleGroup;
     100: invokevirtual #118                // Method javafx/scene/control/RadioMenuItem.setToggleGroup:(Ljavafx/scene/control/ToggleGroup;)V
     103: aload         6
     105: aload_0
     106: aload_1
     107: aload         6
     109: invokedynamic #119,  0            // InvokeDynamic #8:handle:(Ljavafx/scene/control/skin/ChoiceBoxSkin;Ljava/lang/Object;Ljavafx/scene/control/RadioMenuItem;)Ljavafx/event/EventHandler;
     114: invokevirtual #120                // Method javafx/scene/control/RadioMenuItem.setOnAction:(Ljavafx/event/EventHandler;)V
     117: aload         6
     119: astore_3
     120: aload_3
     121: iconst_0
     122: invokevirtual #121                // Method javafx/scene/control/MenuItem.setMnemonicParsing:(Z)V
     125: aload_0
     126: getfield      #3                  // Field popup:Ljavafx/scene/control/ContextMenu;
     129: invokevirtual #59                 // Method javafx/scene/control/ContextMenu.getItems:()Ljavafx/collections/ObservableList;
     132: iload_2
     133: aload_3
     134: invokeinterface #122,  3          // InterfaceMethod javafx/collections/ObservableList.add:(ILjava/lang/Object;)V
     139: return

  private void updatePopupItems();
    Code:
       0: aload_0
       1: getfield      #4                  // Field toggleGroup:Ljavafx/scene/control/ToggleGroup;
       4: invokevirtual #123                // Method javafx/scene/control/ToggleGroup.getToggles:()Ljavafx/collections/ObservableList;
       7: invokeinterface #86,  1           // InterfaceMethod javafx/collections/ObservableList.clear:()V
      12: aload_0
      13: getfield      #3                  // Field popup:Ljavafx/scene/control/ContextMenu;
      16: invokevirtual #59                 // Method javafx/scene/control/ContextMenu.getItems:()Ljavafx/collections/ObservableList;
      19: invokeinterface #86,  1           // InterfaceMethod javafx/collections/ObservableList.clear:()V
      24: aload_0
      25: getfield      #4                  // Field toggleGroup:Ljavafx/scene/control/ToggleGroup;
      28: aconst_null
      29: invokevirtual #124                // Method javafx/scene/control/ToggleGroup.selectToggle:(Ljavafx/scene/control/Toggle;)V
      32: iconst_0
      33: istore_1
      34: iload_1
      35: aload_0
      36: getfield      #103                // Field choiceBoxItems:Ljavafx/collections/ObservableList;
      39: invokeinterface #60,  1           // InterfaceMethod javafx/collections/ObservableList.size:()I
      44: if_icmpge     70
      47: aload_0
      48: getfield      #103                // Field choiceBoxItems:Ljavafx/collections/ObservableList;
      51: iload_1
      52: invokeinterface #62,  2           // InterfaceMethod javafx/collections/ObservableList.get:(I)Ljava/lang/Object;
      57: astore_2
      58: aload_0
      59: aload_2
      60: iload_1
      61: invokespecial #2                  // Method addPopupItem:(Ljava/lang/Object;I)V
      64: iinc          1, 1
      67: goto          34
      70: return

  private void updateSelectionModel();
    Code:
       0: aload_0
       1: getfield      #99                 // Field selectionModel:Ljavafx/scene/control/SelectionModel;
       4: ifnull        21
       7: aload_0
       8: getfield      #99                 // Field selectionModel:Ljavafx/scene/control/SelectionModel;
      11: invokevirtual #125                // Method javafx/scene/control/SelectionModel.selectedIndexProperty:()Ljavafx/beans/property/ReadOnlyIntegerProperty;
      14: aload_0
      15: getfield      #15                 // Field selectionChangeListener:Ljavafx/beans/InvalidationListener;
      18: invokevirtual #126                // Method javafx/beans/property/ReadOnlyIntegerProperty.removeListener:(Ljavafx/beans/InvalidationListener;)V
      21: aload_0
      22: aload_0
      23: invokevirtual #70                 // Method getSkinnable:()Ljavafx/scene/control/Control;
      26: checkcast     #71                 // class javafx/scene/control/ChoiceBox
      29: invokevirtual #33                 // Method javafx/scene/control/ChoiceBox.getSelectionModel:()Ljavafx/scene/control/SingleSelectionModel;
      32: putfield      #99                 // Field selectionModel:Ljavafx/scene/control/SelectionModel;
      35: aload_0
      36: getfield      #99                 // Field selectionModel:Ljavafx/scene/control/SelectionModel;
      39: ifnull        56
      42: aload_0
      43: getfield      #99                 // Field selectionModel:Ljavafx/scene/control/SelectionModel;
      46: invokevirtual #125                // Method javafx/scene/control/SelectionModel.selectedIndexProperty:()Ljavafx/beans/property/ReadOnlyIntegerProperty;
      49: aload_0
      50: getfield      #15                 // Field selectionChangeListener:Ljavafx/beans/InvalidationListener;
      53: invokevirtual #127                // Method javafx/beans/property/ReadOnlyIntegerProperty.addListener:(Ljavafx/beans/InvalidationListener;)V
      56: return

  private void updateSelection();
    Code:
       0: aload_0
       1: getfield      #99                 // Field selectionModel:Ljavafx/scene/control/SelectionModel;
       4: ifnull        17
       7: aload_0
       8: getfield      #99                 // Field selectionModel:Ljavafx/scene/control/SelectionModel;
      11: invokevirtual #128                // Method javafx/scene/control/SelectionModel.isEmpty:()Z
      14: ifeq          37
      17: aload_0
      18: getfield      #4                  // Field toggleGroup:Ljavafx/scene/control/ToggleGroup;
      21: aconst_null
      22: invokevirtual #124                // Method javafx/scene/control/ToggleGroup.selectToggle:(Ljavafx/scene/control/Toggle;)V
      25: aload_0
      26: getfield      #44                 // Field label:Ljavafx/scene/control/Label;
      29: ldc           #101                // String
      31: invokevirtual #102                // Method javafx/scene/control/Label.setText:(Ljava/lang/String;)V
      34: goto          158
      37: aload_0
      38: getfield      #99                 // Field selectionModel:Ljavafx/scene/control/SelectionModel;
      41: invokevirtual #100                // Method javafx/scene/control/SelectionModel.getSelectedIndex:()I
      44: istore_1
      45: iload_1
      46: iconst_m1
      47: if_icmpeq     66
      50: iload_1
      51: aload_0
      52: getfield      #3                  // Field popup:Ljavafx/scene/control/ContextMenu;
      55: invokevirtual #59                 // Method javafx/scene/control/ContextMenu.getItems:()Ljavafx/collections/ObservableList;
      58: invokeinterface #60,  1           // InterfaceMethod javafx/collections/ObservableList.size:()I
      63: if_icmple     76
      66: aload_0
      67: getfield      #44                 // Field label:Ljavafx/scene/control/Label;
      70: ldc           #101                // String
      72: invokevirtual #102                // Method javafx/scene/control/Label.setText:(Ljava/lang/String;)V
      75: return
      76: iload_1
      77: aload_0
      78: getfield      #3                  // Field popup:Ljavafx/scene/control/ContextMenu;
      81: invokevirtual #59                 // Method javafx/scene/control/ContextMenu.getItems:()Ljavafx/collections/ObservableList;
      84: invokeinterface #60,  1           // InterfaceMethod javafx/collections/ObservableList.size:()I
      89: if_icmpge     158
      92: aload_0
      93: getfield      #3                  // Field popup:Ljavafx/scene/control/ContextMenu;
      96: invokevirtual #59                 // Method javafx/scene/control/ContextMenu.getItems:()Ljavafx/collections/ObservableList;
      99: iload_1
     100: invokeinterface #62,  2           // InterfaceMethod javafx/collections/ObservableList.get:(I)Ljava/lang/Object;
     105: checkcast     #63                 // class javafx/scene/control/MenuItem
     108: astore_2
     109: aload_2
     110: instanceof    #114                // class javafx/scene/control/RadioMenuItem
     113: ifeq          132
     116: aload_2
     117: checkcast     #114                // class javafx/scene/control/RadioMenuItem
     120: iconst_1
     121: invokevirtual #129                // Method javafx/scene/control/RadioMenuItem.setSelected:(Z)V
     124: aload_0
     125: getfield      #4                  // Field toggleGroup:Ljavafx/scene/control/ToggleGroup;
     128: aconst_null
     129: invokevirtual #124                // Method javafx/scene/control/ToggleGroup.selectToggle:(Ljavafx/scene/control/Toggle;)V
     132: aload_0
     133: getfield      #44                 // Field label:Ljavafx/scene/control/Label;
     136: aload_0
     137: getfield      #3                  // Field popup:Ljavafx/scene/control/ContextMenu;
     140: invokevirtual #59                 // Method javafx/scene/control/ContextMenu.getItems:()Ljavafx/collections/ObservableList;
     143: iload_1
     144: invokeinterface #62,  2           // InterfaceMethod javafx/collections/ObservableList.get:(I)Ljava/lang/Object;
     149: checkcast     #63                 // class javafx/scene/control/MenuItem
     152: invokevirtual #64                 // Method javafx/scene/control/MenuItem.getText:()Ljava/lang/String;
     155: invokevirtual #102                // Method javafx/scene/control/Label.setText:(Ljava/lang/String;)V
     158: return

  private void lambda$new$8(javafx.beans.Observable);
    Code:
       0: aload_0
       1: invokespecial #1                  // Method updateSelection:()V
       4: return

  private void lambda$addPopupItem$7(java.lang.Object, javafx.scene.control.RadioMenuItem, javafx.event.ActionEvent);
    Code:
       0: aload_0
       1: getfield      #99                 // Field selectionModel:Ljavafx/scene/control/SelectionModel;
       4: ifnonnull     8
       7: return
       8: aload_0
       9: invokevirtual #70                 // Method getSkinnable:()Ljavafx/scene/control/Control;
      12: checkcast     #71                 // class javafx/scene/control/ChoiceBox
      15: invokevirtual #105                // Method javafx/scene/control/ChoiceBox.getItems:()Ljavafx/collections/ObservableList;
      18: aload_1
      19: invokeinterface #130,  2          // InterfaceMethod javafx/collections/ObservableList.indexOf:(Ljava/lang/Object;)I
      24: istore        4
      26: aload_0
      27: getfield      #99                 // Field selectionModel:Ljavafx/scene/control/SelectionModel;
      30: iload         4
      32: invokevirtual #131                // Method javafx/scene/control/SelectionModel.select:(I)V
      35: aload_2
      36: iconst_1
      37: invokevirtual #129                // Method javafx/scene/control/RadioMenuItem.setSelected:(Z)V
      40: return

  private void lambda$initialize$6(javafx.beans.value.ObservableValue, java.lang.Boolean, java.lang.Boolean);
    Code:
       0: aload_3
       1: invokevirtual #132                // Method java/lang/Boolean.booleanValue:()Z
       4: ifne          17
       7: aload_0
       8: invokevirtual #70                 // Method getSkinnable:()Ljavafx/scene/control/Control;
      11: checkcast     #71                 // class javafx/scene/control/ChoiceBox
      14: invokevirtual #133                // Method javafx/scene/control/ChoiceBox.hide:()V
      17: return

  private void lambda$new$5(javafx.beans.value.ObservableValue);
    Code:
       0: aload_0
       1: invokespecial #74                 // Method updateChoiceBoxItems:()V
       4: aload_0
       5: invokespecial #97                 // Method updatePopupItems:()V
       8: return

  private void lambda$new$4(javafx.beans.value.ObservableValue);
    Code:
       0: aload_0
       1: invokevirtual #70                 // Method getSkinnable:()Ljavafx/scene/control/Control;
       4: checkcast     #71                 // class javafx/scene/control/ChoiceBox
       7: invokevirtual #33                 // Method javafx/scene/control/ChoiceBox.getSelectionModel:()Ljavafx/scene/control/SingleSelectionModel;
      10: ifnull        64
      13: aload_0
      14: invokevirtual #70                 // Method getSkinnable:()Ljavafx/scene/control/Control;
      17: checkcast     #71                 // class javafx/scene/control/ChoiceBox
      20: invokevirtual #33                 // Method javafx/scene/control/ChoiceBox.getSelectionModel:()Ljavafx/scene/control/SingleSelectionModel;
      23: invokevirtual #134                // Method javafx/scene/control/SingleSelectionModel.getSelectedIndex:()I
      26: istore_2
      27: iload_2
      28: iconst_m1
      29: if_icmpeq     64
      32: aload_0
      33: getfield      #3                  // Field popup:Ljavafx/scene/control/ContextMenu;
      36: invokevirtual #59                 // Method javafx/scene/control/ContextMenu.getItems:()Ljavafx/collections/ObservableList;
      39: iload_2
      40: invokeinterface #62,  2           // InterfaceMethod javafx/collections/ObservableList.get:(I)Ljava/lang/Object;
      45: checkcast     #63                 // class javafx/scene/control/MenuItem
      48: astore_3
      49: aload_3
      50: instanceof    #114                // class javafx/scene/control/RadioMenuItem
      53: ifeq          64
      56: aload_3
      57: checkcast     #114                // class javafx/scene/control/RadioMenuItem
      60: iconst_1
      61: invokevirtual #129                // Method javafx/scene/control/RadioMenuItem.setSelected:(Z)V
      64: return

  private void lambda$new$3(javafx.beans.value.ObservableValue);
    Code:
       0: aload_0
       1: invokespecial #74                 // Method updateChoiceBoxItems:()V
       4: aload_0
       5: invokespecial #97                 // Method updatePopupItems:()V
       8: aload_0
       9: invokespecial #98                 // Method updateSelectionModel:()V
      12: aload_0
      13: invokespecial #1                  // Method updateSelection:()V
      16: aload_0
      17: getfield      #99                 // Field selectionModel:Ljavafx/scene/control/SelectionModel;
      20: ifnull        43
      23: aload_0
      24: getfield      #99                 // Field selectionModel:Ljavafx/scene/control/SelectionModel;
      27: invokevirtual #100                // Method javafx/scene/control/SelectionModel.getSelectedIndex:()I
      30: iconst_m1
      31: if_icmpne     43
      34: aload_0
      35: getfield      #44                 // Field label:Ljavafx/scene/control/Label;
      38: ldc           #101                // String
      40: invokevirtual #102                // Method javafx/scene/control/Label.setText:(Ljava/lang/String;)V
      43: return

  private void lambda$new$2(javafx.beans.value.ObservableValue);
    Code:
       0: aload_0
       1: invokevirtual #70                 // Method getSkinnable:()Ljavafx/scene/control/Control;
       4: checkcast     #71                 // class javafx/scene/control/ChoiceBox
       7: invokevirtual #135                // Method javafx/scene/control/ChoiceBox.isShowing:()Z
      10: ifeq          227
      13: aconst_null
      14: astore_2
      15: aload_0
      16: invokevirtual #70                 // Method getSkinnable:()Ljavafx/scene/control/Control;
      19: checkcast     #71                 // class javafx/scene/control/ChoiceBox
      22: invokevirtual #33                 // Method javafx/scene/control/ChoiceBox.getSelectionModel:()Ljavafx/scene/control/SingleSelectionModel;
      25: astore_3
      26: aload_3
      27: ifnonnull     31
      30: return
      31: aload_3
      32: invokevirtual #100                // Method javafx/scene/control/SelectionModel.getSelectedIndex:()I
      35: i2l
      36: lstore        4
      38: aload_0
      39: getfield      #103                // Field choiceBoxItems:Ljavafx/collections/ObservableList;
      42: invokeinterface #60,  1           // InterfaceMethod javafx/collections/ObservableList.size:()I
      47: istore        6
      49: lload         4
      51: lconst_0
      52: lcmp
      53: iflt          69
      56: lload         4
      58: iload         6
      60: i2l
      61: lcmp
      62: ifge          69
      65: iconst_1
      66: goto          70
      69: iconst_0
      70: istore        7
      72: iload         7
      74: ifeq          118
      77: aload_0
      78: getfield      #3                  // Field popup:Ljavafx/scene/control/ContextMenu;
      81: invokevirtual #59                 // Method javafx/scene/control/ContextMenu.getItems:()Ljavafx/collections/ObservableList;
      84: lload         4
      86: l2i
      87: invokeinterface #62,  2           // InterfaceMethod javafx/collections/ObservableList.get:(I)Ljava/lang/Object;
      92: checkcast     #63                 // class javafx/scene/control/MenuItem
      95: astore_2
      96: aload_2
      97: ifnull        140
     100: aload_2
     101: instanceof    #114                // class javafx/scene/control/RadioMenuItem
     104: ifeq          140
     107: aload_2
     108: checkcast     #114                // class javafx/scene/control/RadioMenuItem
     111: iconst_1
     112: invokevirtual #129                // Method javafx/scene/control/RadioMenuItem.setSelected:(Z)V
     115: goto          140
     118: iload         6
     120: ifle          140
     123: aload_0
     124: getfield      #3                  // Field popup:Ljavafx/scene/control/ContextMenu;
     127: invokevirtual #59                 // Method javafx/scene/control/ContextMenu.getItems:()Ljavafx/collections/ObservableList;
     130: iconst_0
     131: invokeinterface #62,  2           // InterfaceMethod javafx/collections/ObservableList.get:(I)Ljava/lang/Object;
     136: checkcast     #63                 // class javafx/scene/control/MenuItem
     139: astore_2
     140: aload_0
     141: invokevirtual #70                 // Method getSkinnable:()Ljavafx/scene/control/Control;
     144: checkcast     #71                 // class javafx/scene/control/ChoiceBox
     147: invokevirtual #136                // Method javafx/scene/control/ChoiceBox.autosize:()V
     150: dconst_0
     151: dstore        8
     153: aload_0
     154: getfield      #3                  // Field popup:Ljavafx/scene/control/ContextMenu;
     157: invokevirtual #137                // Method javafx/scene/control/ContextMenu.getSkin:()Ljavafx/scene/control/Skin;
     160: ifnull        205
     163: aload_0
     164: getfield      #3                  // Field popup:Ljavafx/scene/control/ContextMenu;
     167: invokevirtual #137                // Method javafx/scene/control/ContextMenu.getSkin:()Ljavafx/scene/control/Skin;
     170: invokeinterface #138,  1          // InterfaceMethod javafx/scene/control/Skin.getNode:()Ljavafx/scene/Node;
     175: checkcast     #139                // class com/sun/javafx/scene/control/ContextMenuContent
     178: astore        10
     180: aload         10
     182: ifnull        205
     185: lload         4
     187: ldc2_w        #140                // long -1l
     190: lcmp
     191: ifeq          205
     194: aload         10
     196: lload         4
     198: l2i
     199: invokevirtual #142                // Method com/sun/javafx/scene/control/ContextMenuContent.getMenuYOffset:(I)D
     202: dneg
     203: dstore        8
     205: aload_0
     206: getfield      #3                  // Field popup:Ljavafx/scene/control/ContextMenu;
     209: aload_0
     210: invokevirtual #70                 // Method getSkinnable:()Ljavafx/scene/control/Control;
     213: getstatic     #143                // Field javafx/geometry/Side.BOTTOM:Ljavafx/geometry/Side;
     216: ldc2_w        #144                // double 2.0d
     219: dload         8
     221: invokevirtual #146                // Method javafx/scene/control/ContextMenu.show:(Ljavafx/scene/Node;Ljavafx/geometry/Side;DD)V
     224: goto          234
     227: aload_0
     228: getfield      #3                  // Field popup:Ljavafx/scene/control/ContextMenu;
     231: invokevirtual #147                // Method javafx/scene/control/ContextMenu.hide:()V
     234: return

  private void lambda$new$1(javafx.beans.value.ObservableValue);
    Code:
       0: aload_0
       1: invokespecial #98                 // Method updateSelectionModel:()V
       4: return

  private void lambda$new$0(javafx.beans.Observable);
    Code:
       0: aload_0
       1: invokespecial #74                 // Method updateChoiceBoxItems:()V
       4: return

  static javafx.scene.control.ToggleGroup access$000(javafx.scene.control.skin.ChoiceBoxSkin);
    Code:
       0: aload_0
       1: getfield      #4                  // Field toggleGroup:Ljavafx/scene/control/ToggleGroup;
       4: areturn

  static javafx.scene.control.ContextMenu access$100(javafx.scene.control.skin.ChoiceBoxSkin);
    Code:
       0: aload_0
       1: getfield      #3                  // Field popup:Ljavafx/scene/control/ContextMenu;
       4: areturn

  static void access$200(javafx.scene.control.skin.ChoiceBoxSkin, java.lang.Object, int);
    Code:
       0: aload_0
       1: aload_1
       2: iload_2
       3: invokespecial #2                  // Method addPopupItem:(Ljava/lang/Object;I)V
       6: return

  static void access$300(javafx.scene.control.skin.ChoiceBoxSkin);
    Code:
       0: aload_0
       1: invokespecial #1                  // Method updateSelection:()V
       4: return
}
