Compiled from "PaginationSkin.java"
class javafx.scene.control.skin.PaginationSkin$2 implements javafx.event.EventHandler<javafx.event.ActionEvent> {
  final javafx.scene.control.skin.PaginationSkin this$0;

  javafx.scene.control.skin.PaginationSkin$2(javafx.scene.control.skin.PaginationSkin);
    Code:
       0: aload_0
       1: aload_1
       2: putfield      #1                  // Field this$0:Ljavafx/scene/control/skin/PaginationSkin;
       5: aload_0
       6: invokespecial #2                  // Method java/lang/Object."<init>":()V
       9: return

  public void handle(javafx.event.ActionEvent);
    Code:
       0: aload_0
       1: getfield      #1                  // Field this$0:Ljavafx/scene/control/skin/PaginationSkin;
       4: invokestatic  #3                  // Method javafx/scene/control/skin/PaginationSkin.access$400:(Ljavafx/scene/control/skin/PaginationSkin;)Ljavafx/scene/layout/StackPane;
       7: dconst_0
       8: invokevirtual #4                  // Method javafx/scene/layout/StackPane.setTranslateX:(D)V
      11: aload_0
      12: getfield      #1                  // Field this$0:Ljavafx/scene/control/skin/PaginationSkin;
      15: invokestatic  #5                  // Method javafx/scene/control/skin/PaginationSkin.access$500:(Ljavafx/scene/control/skin/PaginationSkin;)Ljavafx/scene/layout/StackPane;
      18: dconst_0
      19: invokevirtual #4                  // Method javafx/scene/layout/StackPane.setTranslateX:(D)V
      22: aload_0
      23: getfield      #1                  // Field this$0:Ljavafx/scene/control/skin/PaginationSkin;
      26: invokestatic  #5                  // Method javafx/scene/control/skin/PaginationSkin.access$500:(Ljavafx/scene/control/skin/PaginationSkin;)Ljavafx/scene/layout/StackPane;
      29: iconst_0
      30: invokevirtual #6                  // Method javafx/scene/layout/StackPane.setVisible:(Z)V
      33: aload_0
      34: getfield      #1                  // Field this$0:Ljavafx/scene/control/skin/PaginationSkin;
      37: aconst_null
      38: invokestatic  #7                  // Method javafx/scene/control/skin/PaginationSkin.access$102:(Ljavafx/scene/control/skin/PaginationSkin;Ljavafx/animation/Timeline;)Ljavafx/animation/Timeline;
      41: pop
      42: return

  public void handle(javafx.event.Event);
    Code:
       0: aload_0
       1: aload_1
       2: checkcast     #8                  // class javafx/event/ActionEvent
       5: invokevirtual #9                  // Method handle:(Ljavafx/event/ActionEvent;)V
       8: return
}
