Compiled from "ProgressIndicatorSkin.java"
class javafx.scene.control.skin.ProgressIndicatorSkin$IndeterminateSpinner$IndicatorPaths extends javafx.scene.layout.Pane {
  final javafx.scene.control.skin.ProgressIndicatorSkin$IndeterminateSpinner this$1;

  private javafx.scene.control.skin.ProgressIndicatorSkin$IndeterminateSpinner$IndicatorPaths(javafx.scene.control.skin.ProgressIndicatorSkin$IndeterminateSpinner);
    Code:
       0: aload_0
       1: aload_1
       2: putfield      #2                  // Field this$1:Ljavafx/scene/control/skin/ProgressIndicatorSkin$IndeterminateSpinner;
       5: aload_0
       6: invokespecial #3                  // Method javafx/scene/layout/Pane."<init>":()V
       9: return

  protected double computePrefWidth(double);
    Code:
       0: dconst_0
       1: dstore_3
       2: aload_0
       3: invokevirtual #4                  // Method getChildren:()Ljavafx/collections/ObservableList;
       6: invokeinterface #5,  1            // InterfaceMethod javafx/collections/ObservableList.iterator:()Ljava/util/Iterator;
      11: astore        5
      13: aload         5
      15: invokeinterface #6,  1            // InterfaceMethod java/util/Iterator.hasNext:()Z
      20: ifeq          91
      23: aload         5
      25: invokeinterface #7,  1            // InterfaceMethod java/util/Iterator.next:()Ljava/lang/Object;
      30: checkcast     #8                  // class javafx/scene/Node
      33: astore        6
      35: aload         6
      37: instanceof    #9                  // class javafx/scene/layout/Region
      40: ifeq          88
      43: aload         6
      45: checkcast     #9                  // class javafx/scene/layout/Region
      48: astore        7
      50: aload         7
      52: invokevirtual #10                 // Method javafx/scene/layout/Region.getShape:()Ljavafx/scene/shape/Shape;
      55: ifnull        77
      58: dload_3
      59: aload         7
      61: invokevirtual #10                 // Method javafx/scene/layout/Region.getShape:()Ljavafx/scene/shape/Shape;
      64: invokevirtual #11                 // Method javafx/scene/shape/Shape.getLayoutBounds:()Ljavafx/geometry/Bounds;
      67: invokevirtual #12                 // Method javafx/geometry/Bounds.getMaxX:()D
      70: invokestatic  #13                 // Method java/lang/Math.max:(DD)D
      73: dstore_3
      74: goto          88
      77: dload_3
      78: aload         7
      80: dload_1
      81: invokevirtual #14                 // Method javafx/scene/layout/Region.prefWidth:(D)D
      84: invokestatic  #13                 // Method java/lang/Math.max:(DD)D
      87: dstore_3
      88: goto          13
      91: dload_3
      92: dreturn

  protected double computePrefHeight(double);
    Code:
       0: dconst_0
       1: dstore_3
       2: aload_0
       3: invokevirtual #4                  // Method getChildren:()Ljavafx/collections/ObservableList;
       6: invokeinterface #5,  1            // InterfaceMethod javafx/collections/ObservableList.iterator:()Ljava/util/Iterator;
      11: astore        5
      13: aload         5
      15: invokeinterface #6,  1            // InterfaceMethod java/util/Iterator.hasNext:()Z
      20: ifeq          91
      23: aload         5
      25: invokeinterface #7,  1            // InterfaceMethod java/util/Iterator.next:()Ljava/lang/Object;
      30: checkcast     #8                  // class javafx/scene/Node
      33: astore        6
      35: aload         6
      37: instanceof    #9                  // class javafx/scene/layout/Region
      40: ifeq          88
      43: aload         6
      45: checkcast     #9                  // class javafx/scene/layout/Region
      48: astore        7
      50: aload         7
      52: invokevirtual #10                 // Method javafx/scene/layout/Region.getShape:()Ljavafx/scene/shape/Shape;
      55: ifnull        77
      58: dload_3
      59: aload         7
      61: invokevirtual #10                 // Method javafx/scene/layout/Region.getShape:()Ljavafx/scene/shape/Shape;
      64: invokevirtual #11                 // Method javafx/scene/shape/Shape.getLayoutBounds:()Ljavafx/geometry/Bounds;
      67: invokevirtual #15                 // Method javafx/geometry/Bounds.getMaxY:()D
      70: invokestatic  #13                 // Method java/lang/Math.max:(DD)D
      73: dstore_3
      74: goto          88
      77: dload_3
      78: aload         7
      80: dload_1
      81: invokevirtual #16                 // Method javafx/scene/layout/Region.prefHeight:(D)D
      84: invokestatic  #13                 // Method java/lang/Math.max:(DD)D
      87: dstore_3
      88: goto          13
      91: dload_3
      92: dreturn

  protected void layoutChildren();
    Code:
       0: aload_0
       1: invokevirtual #17                 // Method getWidth:()D
       4: aload_0
       5: ldc2_w        #18                 // double -1.0d
       8: invokevirtual #20                 // Method computePrefWidth:(D)D
      11: ddiv
      12: dstore_1
      13: aload_0
      14: invokevirtual #4                  // Method getChildren:()Ljavafx/collections/ObservableList;
      17: invokeinterface #5,  1            // InterfaceMethod javafx/collections/ObservableList.iterator:()Ljava/util/Iterator;
      22: astore_3
      23: aload_3
      24: invokeinterface #6,  1            // InterfaceMethod java/util/Iterator.hasNext:()Z
      29: ifeq          133
      32: aload_3
      33: invokeinterface #7,  1            // InterfaceMethod java/util/Iterator.next:()Ljava/lang/Object;
      38: checkcast     #8                  // class javafx/scene/Node
      41: astore        4
      43: aload         4
      45: instanceof    #9                  // class javafx/scene/layout/Region
      48: ifeq          130
      51: aload         4
      53: checkcast     #9                  // class javafx/scene/layout/Region
      56: astore        5
      58: aload         5
      60: invokevirtual #10                 // Method javafx/scene/layout/Region.getShape:()Ljavafx/scene/shape/Shape;
      63: ifnull        125
      66: aload         5
      68: aload         5
      70: invokevirtual #10                 // Method javafx/scene/layout/Region.getShape:()Ljavafx/scene/shape/Shape;
      73: invokevirtual #11                 // Method javafx/scene/shape/Shape.getLayoutBounds:()Ljavafx/geometry/Bounds;
      76: invokevirtual #12                 // Method javafx/geometry/Bounds.getMaxX:()D
      79: aload         5
      81: invokevirtual #10                 // Method javafx/scene/layout/Region.getShape:()Ljavafx/scene/shape/Shape;
      84: invokevirtual #11                 // Method javafx/scene/shape/Shape.getLayoutBounds:()Ljavafx/geometry/Bounds;
      87: invokevirtual #15                 // Method javafx/geometry/Bounds.getMaxY:()D
      90: invokevirtual #21                 // Method javafx/scene/layout/Region.resize:(DD)V
      93: aload         5
      95: invokevirtual #22                 // Method javafx/scene/layout/Region.getTransforms:()Ljavafx/collections/ObservableList;
      98: iconst_1
      99: anewarray     #23                 // class javafx/scene/transform/Transform
     102: dup
     103: iconst_0
     104: new           #24                 // class javafx/scene/transform/Scale
     107: dup
     108: dload_1
     109: dload_1
     110: dconst_0
     111: dconst_0
     112: invokespecial #25                 // Method javafx/scene/transform/Scale."<init>":(DDDD)V
     115: aastore
     116: invokeinterface #26,  2           // InterfaceMethod javafx/collections/ObservableList.setAll:([Ljava/lang/Object;)Z
     121: pop
     122: goto          130
     125: aload         5
     127: invokevirtual #27                 // Method javafx/scene/layout/Region.autosize:()V
     130: goto          23
     133: return

  javafx.scene.control.skin.ProgressIndicatorSkin$IndeterminateSpinner$IndicatorPaths(javafx.scene.control.skin.ProgressIndicatorSkin$IndeterminateSpinner, javafx.scene.control.skin.ProgressIndicatorSkin$1);
    Code:
       0: aload_0
       1: aload_1
       2: invokespecial #1                  // Method "<init>":(Ljavafx/scene/control/skin/ProgressIndicatorSkin$IndeterminateSpinner;)V
       5: return
}
