Compiled from "ScrollBarSkin.java"
class javafx.scene.control.skin.ScrollBarSkin$EndButton extends javafx.scene.layout.Region {
  private javafx.scene.layout.Region arrow;

  private javafx.scene.control.skin.ScrollBarSkin$EndButton(java.lang.String, java.lang.String);
    Code:
       0: aload_0
       1: invokespecial #2                  // Method javafx/scene/layout/Region."<init>":()V
       4: aload_0
       5: invokevirtual #3                  // Method getStyleClass:()Ljavafx/collections/ObservableList;
       8: iconst_1
       9: anewarray     #4                  // class java/lang/String
      12: dup
      13: iconst_0
      14: aload_1
      15: aastore
      16: invokeinterface #5,  2            // InterfaceMethod javafx/collections/ObservableList.setAll:([Ljava/lang/Object;)Z
      21: pop
      22: aload_0
      23: new           #6                  // class javafx/scene/layout/Region
      26: dup
      27: invokespecial #2                  // Method javafx/scene/layout/Region."<init>":()V
      30: putfield      #7                  // Field arrow:Ljavafx/scene/layout/Region;
      33: aload_0
      34: getfield      #7                  // Field arrow:Ljavafx/scene/layout/Region;
      37: invokevirtual #8                  // Method javafx/scene/layout/Region.getStyleClass:()Ljavafx/collections/ObservableList;
      40: iconst_1
      41: anewarray     #4                  // class java/lang/String
      44: dup
      45: iconst_0
      46: aload_2
      47: aastore
      48: invokeinterface #5,  2            // InterfaceMethod javafx/collections/ObservableList.setAll:([Ljava/lang/Object;)Z
      53: pop
      54: aload_0
      55: invokevirtual #9                  // Method getChildren:()Ljavafx/collections/ObservableList;
      58: iconst_1
      59: anewarray     #10                 // class javafx/scene/Node
      62: dup
      63: iconst_0
      64: aload_0
      65: getfield      #7                  // Field arrow:Ljavafx/scene/layout/Region;
      68: aastore
      69: invokeinterface #5,  2            // InterfaceMethod javafx/collections/ObservableList.setAll:([Ljava/lang/Object;)Z
      74: pop
      75: aload_0
      76: invokevirtual #11                 // Method requestLayout:()V
      79: return

  protected void layoutChildren();
    Code:
       0: aload_0
       1: invokevirtual #12                 // Method snappedTopInset:()D
       4: dstore_1
       5: aload_0
       6: invokevirtual #13                 // Method snappedLeftInset:()D
       9: dstore_3
      10: aload_0
      11: invokevirtual #14                 // Method snappedBottomInset:()D
      14: dstore        5
      16: aload_0
      17: invokevirtual #15                 // Method snappedRightInset:()D
      20: dstore        7
      22: aload_0
      23: aload_0
      24: getfield      #7                  // Field arrow:Ljavafx/scene/layout/Region;
      27: ldc2_w        #16                 // double -1.0d
      30: invokevirtual #18                 // Method javafx/scene/layout/Region.prefWidth:(D)D
      33: invokevirtual #19                 // Method snapSizeX:(D)D
      36: dstore        9
      38: aload_0
      39: aload_0
      40: getfield      #7                  // Field arrow:Ljavafx/scene/layout/Region;
      43: ldc2_w        #16                 // double -1.0d
      46: invokevirtual #20                 // Method javafx/scene/layout/Region.prefHeight:(D)D
      49: invokevirtual #21                 // Method snapSizeY:(D)D
      52: dstore        11
      54: aload_0
      55: aload_0
      56: invokevirtual #22                 // Method getHeight:()D
      59: dload_1
      60: dload         5
      62: dadd
      63: dload         11
      65: dadd
      66: dsub
      67: ldc2_w        #23                 // double 2.0d
      70: ddiv
      71: invokevirtual #25                 // Method snapPositionY:(D)D
      74: dstore        13
      76: aload_0
      77: aload_0
      78: invokevirtual #26                 // Method getWidth:()D
      81: dload_3
      82: dload         7
      84: dadd
      85: dload         9
      87: dadd
      88: dsub
      89: ldc2_w        #23                 // double 2.0d
      92: ddiv
      93: invokevirtual #27                 // Method snapPositionX:(D)D
      96: dstore        15
      98: aload_0
      99: getfield      #7                  // Field arrow:Ljavafx/scene/layout/Region;
     102: dload         15
     104: dload_3
     105: dadd
     106: dload         13
     108: dload_1
     109: dadd
     110: dload         9
     112: dload         11
     114: invokevirtual #28                 // Method javafx/scene/layout/Region.resizeRelocate:(DDDD)V
     117: return

  protected double computeMinHeight(double);
    Code:
       0: aload_0
       1: ldc2_w        #16                 // double -1.0d
       4: invokevirtual #29                 // Method prefHeight:(D)D
       7: dreturn

  protected double computeMinWidth(double);
    Code:
       0: aload_0
       1: ldc2_w        #16                 // double -1.0d
       4: invokevirtual #30                 // Method prefWidth:(D)D
       7: dreturn

  protected double computePrefWidth(double);
    Code:
       0: aload_0
       1: invokevirtual #13                 // Method snappedLeftInset:()D
       4: dstore_3
       5: aload_0
       6: invokevirtual #15                 // Method snappedRightInset:()D
       9: dstore        5
      11: aload_0
      12: aload_0
      13: getfield      #7                  // Field arrow:Ljavafx/scene/layout/Region;
      16: ldc2_w        #16                 // double -1.0d
      19: invokevirtual #18                 // Method javafx/scene/layout/Region.prefWidth:(D)D
      22: invokevirtual #19                 // Method snapSizeX:(D)D
      25: dstore        7
      27: dload_3
      28: dload         7
      30: dadd
      31: dload         5
      33: dadd
      34: dreturn

  protected double computePrefHeight(double);
    Code:
       0: aload_0
       1: invokevirtual #12                 // Method snappedTopInset:()D
       4: dstore_3
       5: aload_0
       6: invokevirtual #14                 // Method snappedBottomInset:()D
       9: dstore        5
      11: aload_0
      12: aload_0
      13: getfield      #7                  // Field arrow:Ljavafx/scene/layout/Region;
      16: ldc2_w        #16                 // double -1.0d
      19: invokevirtual #20                 // Method javafx/scene/layout/Region.prefHeight:(D)D
      22: invokevirtual #21                 // Method snapSizeY:(D)D
      25: dstore        7
      27: dload_3
      28: dload         7
      30: dadd
      31: dload         5
      33: dadd
      34: dreturn

  javafx.scene.control.skin.ScrollBarSkin$EndButton(java.lang.String, java.lang.String, javafx.scene.control.skin.ScrollBarSkin$1);
    Code:
       0: aload_0
       1: aload_1
       2: aload_2
       3: invokespecial #1                  // Method "<init>":(Ljava/lang/String;Ljava/lang/String;)V
       6: return
}
