Compiled from "TableViewSkinBase.java"
class javafx.scene.control.skin.TableViewSkinBase$1 implements javafx.beans.InvalidationListener {
  private java.lang.ref.WeakReference<javafx.collections.ObservableList<S>> weakItemsRef;

  final javafx.beans.property.ObjectProperty val$itemsProperty;

  final javafx.scene.control.skin.TableViewSkinBase this$0;

  javafx.scene.control.skin.TableViewSkinBase$1(javafx.scene.control.skin.TableViewSkinBase, javafx.beans.property.ObjectProperty);
    Code:
       0: aload_0
       1: aload_1
       2: putfield      #1                  // Field this$0:Ljavafx/scene/control/skin/TableViewSkinBase;
       5: aload_0
       6: aload_2
       7: putfield      #2                  // Field val$itemsProperty:Ljavafx/beans/property/ObjectProperty;
      10: aload_0
      11: invokespecial #3                  // Method java/lang/Object."<init>":()V
      14: aload_0
      15: new           #4                  // class java/lang/ref/WeakReference
      18: dup
      19: aload_0
      20: getfield      #2                  // Field val$itemsProperty:Ljavafx/beans/property/ObjectProperty;
      23: invokevirtual #5                  // Method javafx/beans/property/ObjectProperty.get:()Ljava/lang/Object;
      26: checkcast     #6                  // class javafx/collections/ObservableList
      29: invokespecial #7                  // Method java/lang/ref/WeakReference."<init>":(Ljava/lang/Object;)V
      32: putfield      #8                  // Field weakItemsRef:Ljava/lang/ref/WeakReference;
      35: return

  public void invalidated(javafx.beans.Observable);
    Code:
       0: aload_0
       1: getfield      #8                  // Field weakItemsRef:Ljava/lang/ref/WeakReference;
       4: invokevirtual #9                  // Method java/lang/ref/WeakReference.get:()Ljava/lang/Object;
       7: checkcast     #6                  // class javafx/collections/ObservableList
      10: astore_2
      11: aload_0
      12: new           #4                  // class java/lang/ref/WeakReference
      15: dup
      16: aload_0
      17: getfield      #2                  // Field val$itemsProperty:Ljavafx/beans/property/ObjectProperty;
      20: invokevirtual #5                  // Method javafx/beans/property/ObjectProperty.get:()Ljava/lang/Object;
      23: checkcast     #6                  // class javafx/collections/ObservableList
      26: invokespecial #7                  // Method java/lang/ref/WeakReference."<init>":(Ljava/lang/Object;)V
      29: putfield      #8                  // Field weakItemsRef:Ljava/lang/ref/WeakReference;
      32: aload_0
      33: getfield      #1                  // Field this$0:Ljavafx/scene/control/skin/TableViewSkinBase;
      36: aload_2
      37: aload_0
      38: getfield      #2                  // Field val$itemsProperty:Ljavafx/beans/property/ObjectProperty;
      41: invokevirtual #5                  // Method javafx/beans/property/ObjectProperty.get:()Ljava/lang/Object;
      44: checkcast     #6                  // class javafx/collections/ObservableList
      47: invokestatic  #10                 // Method javafx/scene/control/skin/TableViewSkinBase.access$000:(Ljavafx/scene/control/skin/TableViewSkinBase;Ljavafx/collections/ObservableList;Ljavafx/collections/ObservableList;)V
      50: return
}
