Compiled from "TextFieldSkin.java"
class javafx.scene.control.skin.TextFieldSkin$5 extends javafx.beans.binding.BooleanBinding {
  final javafx.scene.control.TextField val$control;

  final javafx.scene.control.skin.TextFieldSkin this$0;

  javafx.scene.control.skin.TextFieldSkin$5(javafx.scene.control.skin.TextFieldSkin, javafx.scene.control.TextField);
    Code:
       0: aload_0
       1: aload_1
       2: putfield      #1                  // Field this$0:Ljavafx/scene/control/skin/TextFieldSkin;
       5: aload_0
       6: aload_2
       7: putfield      #2                  // Field val$control:Ljavafx/scene/control/TextField;
      10: aload_0
      11: invokespecial #3                  // Method javafx/beans/binding/BooleanBinding."<init>":()V
      14: aload_0
      15: iconst_3
      16: anewarray     #4                  // class javafx/beans/Observable
      19: dup
      20: iconst_0
      21: aload_0
      22: getfield      #2                  // Field val$control:Ljavafx/scene/control/TextField;
      25: invokevirtual #5                  // Method javafx/scene/control/TextField.textProperty:()Ljavafx/beans/property/StringProperty;
      28: aastore
      29: dup
      30: iconst_1
      31: aload_0
      32: getfield      #2                  // Field val$control:Ljavafx/scene/control/TextField;
      35: invokevirtual #6                  // Method javafx/scene/control/TextField.promptTextProperty:()Ljavafx/beans/property/StringProperty;
      38: aastore
      39: dup
      40: iconst_2
      41: aload_0
      42: getfield      #1                  // Field this$0:Ljavafx/scene/control/skin/TextFieldSkin;
      45: invokevirtual #7                  // Method javafx/scene/control/skin/TextFieldSkin.promptTextFillProperty:()Ljavafx/beans/property/ObjectProperty;
      48: aastore
      49: invokevirtual #8                  // Method bind:([Ljavafx/beans/Observable;)V
      52: return

  protected boolean computeValue();
    Code:
       0: aload_0
       1: getfield      #2                  // Field val$control:Ljavafx/scene/control/TextField;
       4: invokevirtual #9                  // Method javafx/scene/control/TextField.getText:()Ljava/lang/String;
       7: astore_1
       8: aload_0
       9: getfield      #2                  // Field val$control:Ljavafx/scene/control/TextField;
      12: invokevirtual #10                 // Method javafx/scene/control/TextField.getPromptText:()Ljava/lang/String;
      15: astore_2
      16: aload_1
      17: ifnull        27
      20: aload_1
      21: invokevirtual #11                 // Method java/lang/String.isEmpty:()Z
      24: ifeq          58
      27: aload_2
      28: ifnull        58
      31: aload_2
      32: invokevirtual #11                 // Method java/lang/String.isEmpty:()Z
      35: ifne          58
      38: aload_0
      39: getfield      #1                  // Field this$0:Ljavafx/scene/control/skin/TextFieldSkin;
      42: invokevirtual #12                 // Method javafx/scene/control/skin/TextFieldSkin.getPromptTextFill:()Ljavafx/scene/paint/Paint;
      45: getstatic     #13                 // Field javafx/scene/paint/Color.TRANSPARENT:Ljavafx/scene/paint/Color;
      48: invokevirtual #14                 // Method java/lang/Object.equals:(Ljava/lang/Object;)Z
      51: ifne          58
      54: iconst_1
      55: goto          59
      58: iconst_0
      59: ireturn
}
