Compiled from "TextFieldSkin.java"
class javafx.scene.control.skin.TextFieldSkin$4 extends javafx.beans.binding.DoubleBinding {
  final javafx.scene.control.skin.TextFieldSkin this$0;

  javafx.scene.control.skin.TextFieldSkin$4(javafx.scene.control.skin.TextFieldSkin);
    Code:
       0: aload_0
       1: aload_1
       2: putfield      #1                  // Field this$0:Ljavafx/scene/control/skin/TextFieldSkin;
       5: aload_0
       6: invokespecial #2                  // Method javafx/beans/binding/DoubleBinding."<init>":()V
       9: aload_0
      10: iconst_1
      11: anewarray     #3                  // class javafx/beans/Observable
      14: dup
      15: iconst_0
      16: aload_0
      17: getfield      #1                  // Field this$0:Ljavafx/scene/control/skin/TextFieldSkin;
      20: invokevirtual #4                  // Method javafx/scene/control/skin/TextFieldSkin.caretVisibleProperty:()Ljavafx/beans/value/ObservableBooleanValue;
      23: aastore
      24: invokevirtual #5                  // Method bind:([Ljavafx/beans/Observable;)V
      27: return

  protected double computeValue();
    Code:
       0: aload_0
       1: getfield      #1                  // Field this$0:Ljavafx/scene/control/skin/TextFieldSkin;
       4: invokevirtual #4                  // Method javafx/scene/control/skin/TextFieldSkin.caretVisibleProperty:()Ljavafx/beans/value/ObservableBooleanValue;
       7: invokeinterface #6,  1            // InterfaceMethod javafx/beans/value/ObservableBooleanValue.get:()Z
      12: ifeq          19
      15: dconst_1
      16: goto          20
      19: dconst_0
      20: dreturn
}
