Compiled from "VirtualFlow.java"
class javafx.scene.control.skin.VirtualFlow$8 extends javafx.beans.property.SimpleObjectProperty<javafx.util.Callback<javafx.scene.control.skin.VirtualFlow<T>, T>> {
  final javafx.scene.control.skin.VirtualFlow this$0;

  javafx.scene.control.skin.VirtualFlow$8(javafx.scene.control.skin.VirtualFlow, java.lang.Object, java.lang.String);
    Code:
       0: aload_0
       1: aload_1
       2: putfield      #1                  // Field this$0:Ljavafx/scene/control/skin/VirtualFlow;
       5: aload_0
       6: aload_2
       7: aload_3
       8: invokespecial #2                  // Method javafx/beans/property/SimpleObjectProperty."<init>":(Ljava/lang/Object;Ljava/lang/String;)V
      11: return

  protected void invalidated();
    Code:
       0: aload_0
       1: invokevirtual #3                  // Method get:()Ljava/lang/Object;
       4: ifnull        50
       7: aload_0
       8: getfield      #1                  // Field this$0:Ljavafx/scene/control/skin/VirtualFlow;
      11: aconst_null
      12: putfield      #4                  // Field javafx/scene/control/skin/VirtualFlow.accumCell:Ljavafx/scene/control/IndexedCell;
      15: aload_0
      16: getfield      #1                  // Field this$0:Ljavafx/scene/control/skin/VirtualFlow;
      19: iconst_1
      20: invokestatic  #5                  // Method javafx/scene/control/skin/VirtualFlow.access$1500:(Ljavafx/scene/control/skin/VirtualFlow;Z)V
      23: aload_0
      24: getfield      #1                  // Field this$0:Ljavafx/scene/control/skin/VirtualFlow;
      27: invokevirtual #6                  // Method javafx/scene/control/skin/VirtualFlow.recreateCells:()V
      30: aload_0
      31: getfield      #1                  // Field this$0:Ljavafx/scene/control/skin/VirtualFlow;
      34: invokevirtual #7                  // Method javafx/scene/control/skin/VirtualFlow.getParent:()Ljavafx/scene/Parent;
      37: ifnull        50
      40: aload_0
      41: getfield      #1                  // Field this$0:Ljavafx/scene/control/skin/VirtualFlow;
      44: invokevirtual #7                  // Method javafx/scene/control/skin/VirtualFlow.getParent:()Ljavafx/scene/Parent;
      47: invokevirtual #8                  // Method javafx/scene/Parent.requestLayout:()V
      50: return
}
