Compiled from "HttpClientConfig.scala"
public class io.youi.client.HttpClientConfig implements scala.Product,java.io.Serializable {
  private final int retries;

  private final scala.concurrent.duration.FiniteDuration retryDelay;

  private final io.youi.client.intercept.Interceptor interceptor;

  private final io.youi.client.ConnectionPool connectionPool;

  private final java.nio.file.Path saveDirectory;

  private final scala.concurrent.duration.FiniteDuration timeout;

  private final scala.Option<scala.concurrent.duration.FiniteDuration> pingInterval;

  private final io.youi.client.DNS dns;

  private final boolean dropNullValuesInJson;

  private final scala.Option<io.youi.client.SessionManager> sessionManager;

  private final boolean failOnHttpStatus;

  private final boolean validateSSLCertificates;

  public static boolean $lessinit$greater$default$12();
    Code:
       0: getstatic     #42                 // Field io/youi/client/HttpClientConfig$.MODULE$:Lio/youi/client/HttpClientConfig$;
       3: invokevirtual #44                 // Method io/youi/client/HttpClientConfig$.$lessinit$greater$default$12:()Z
       6: ireturn

  public static boolean $lessinit$greater$default$11();
    Code:
       0: getstatic     #42                 // Field io/youi/client/HttpClientConfig$.MODULE$:Lio/youi/client/HttpClientConfig$;
       3: invokevirtual #47                 // Method io/youi/client/HttpClientConfig$.$lessinit$greater$default$11:()Z
       6: ireturn

  public static scala.Option<io.youi.client.SessionManager> $lessinit$greater$default$10();
    Code:
       0: getstatic     #42                 // Field io/youi/client/HttpClientConfig$.MODULE$:Lio/youi/client/HttpClientConfig$;
       3: invokevirtual #52                 // Method io/youi/client/HttpClientConfig$.$lessinit$greater$default$10:()Lscala/Option;
       6: areturn

  public static boolean $lessinit$greater$default$9();
    Code:
       0: getstatic     #42                 // Field io/youi/client/HttpClientConfig$.MODULE$:Lio/youi/client/HttpClientConfig$;
       3: invokevirtual #55                 // Method io/youi/client/HttpClientConfig$.$lessinit$greater$default$9:()Z
       6: ireturn

  public static io.youi.client.DNS $lessinit$greater$default$8();
    Code:
       0: getstatic     #42                 // Field io/youi/client/HttpClientConfig$.MODULE$:Lio/youi/client/HttpClientConfig$;
       3: invokevirtual #59                 // Method io/youi/client/HttpClientConfig$.$lessinit$greater$default$8:()Lio/youi/client/DNS;
       6: areturn

  public static scala.Option<scala.concurrent.duration.FiniteDuration> $lessinit$greater$default$7();
    Code:
       0: getstatic     #42                 // Field io/youi/client/HttpClientConfig$.MODULE$:Lio/youi/client/HttpClientConfig$;
       3: invokevirtual #63                 // Method io/youi/client/HttpClientConfig$.$lessinit$greater$default$7:()Lscala/Option;
       6: areturn

  public static scala.concurrent.duration.FiniteDuration $lessinit$greater$default$6();
    Code:
       0: getstatic     #42                 // Field io/youi/client/HttpClientConfig$.MODULE$:Lio/youi/client/HttpClientConfig$;
       3: invokevirtual #67                 // Method io/youi/client/HttpClientConfig$.$lessinit$greater$default$6:()Lscala/concurrent/duration/FiniteDuration;
       6: areturn

  public static java.nio.file.Path $lessinit$greater$default$5();
    Code:
       0: getstatic     #42                 // Field io/youi/client/HttpClientConfig$.MODULE$:Lio/youi/client/HttpClientConfig$;
       3: invokevirtual #71                 // Method io/youi/client/HttpClientConfig$.$lessinit$greater$default$5:()Ljava/nio/file/Path;
       6: areturn

  public static io.youi.client.ConnectionPool $lessinit$greater$default$4();
    Code:
       0: getstatic     #42                 // Field io/youi/client/HttpClientConfig$.MODULE$:Lio/youi/client/HttpClientConfig$;
       3: invokevirtual #75                 // Method io/youi/client/HttpClientConfig$.$lessinit$greater$default$4:()Lio/youi/client/ConnectionPool;
       6: areturn

  public static io.youi.client.intercept.Interceptor $lessinit$greater$default$3();
    Code:
       0: getstatic     #42                 // Field io/youi/client/HttpClientConfig$.MODULE$:Lio/youi/client/HttpClientConfig$;
       3: invokevirtual #79                 // Method io/youi/client/HttpClientConfig$.$lessinit$greater$default$3:()Lio/youi/client/intercept/Interceptor;
       6: areturn

  public static scala.concurrent.duration.FiniteDuration $lessinit$greater$default$2();
    Code:
       0: getstatic     #42                 // Field io/youi/client/HttpClientConfig$.MODULE$:Lio/youi/client/HttpClientConfig$;
       3: invokevirtual #82                 // Method io/youi/client/HttpClientConfig$.$lessinit$greater$default$2:()Lscala/concurrent/duration/FiniteDuration;
       6: areturn

  public static int $lessinit$greater$default$1();
    Code:
       0: getstatic     #42                 // Field io/youi/client/HttpClientConfig$.MODULE$:Lio/youi/client/HttpClientConfig$;
       3: invokevirtual #86                 // Method io/youi/client/HttpClientConfig$.$lessinit$greater$default$1:()I
       6: ireturn

  public static scala.Option<scala.Tuple12<java.lang.Object, scala.concurrent.duration.FiniteDuration, io.youi.client.intercept.Interceptor, io.youi.client.ConnectionPool, java.nio.file.Path, scala.concurrent.duration.FiniteDuration, scala.Option<scala.concurrent.duration.FiniteDuration>, io.youi.client.DNS, java.lang.Object, scala.Option<io.youi.client.SessionManager>, java.lang.Object, java.lang.Object>> unapply(io.youi.client.HttpClientConfig);
    Code:
       0: getstatic     #42                 // Field io/youi/client/HttpClientConfig$.MODULE$:Lio/youi/client/HttpClientConfig$;
       3: aload_0
       4: invokevirtual #92                 // Method io/youi/client/HttpClientConfig$.unapply:(Lio/youi/client/HttpClientConfig;)Lscala/Option;
       7: areturn

  public static boolean apply$default$12();
    Code:
       0: getstatic     #42                 // Field io/youi/client/HttpClientConfig$.MODULE$:Lio/youi/client/HttpClientConfig$;
       3: invokevirtual #95                 // Method io/youi/client/HttpClientConfig$.apply$default$12:()Z
       6: ireturn

  public static boolean apply$default$11();
    Code:
       0: getstatic     #42                 // Field io/youi/client/HttpClientConfig$.MODULE$:Lio/youi/client/HttpClientConfig$;
       3: invokevirtual #98                 // Method io/youi/client/HttpClientConfig$.apply$default$11:()Z
       6: ireturn

  public static scala.Option<io.youi.client.SessionManager> apply$default$10();
    Code:
       0: getstatic     #42                 // Field io/youi/client/HttpClientConfig$.MODULE$:Lio/youi/client/HttpClientConfig$;
       3: invokevirtual #101                // Method io/youi/client/HttpClientConfig$.apply$default$10:()Lscala/Option;
       6: areturn

  public static boolean apply$default$9();
    Code:
       0: getstatic     #42                 // Field io/youi/client/HttpClientConfig$.MODULE$:Lio/youi/client/HttpClientConfig$;
       3: invokevirtual #104                // Method io/youi/client/HttpClientConfig$.apply$default$9:()Z
       6: ireturn

  public static io.youi.client.DNS apply$default$8();
    Code:
       0: getstatic     #42                 // Field io/youi/client/HttpClientConfig$.MODULE$:Lio/youi/client/HttpClientConfig$;
       3: invokevirtual #107                // Method io/youi/client/HttpClientConfig$.apply$default$8:()Lio/youi/client/DNS;
       6: areturn

  public static scala.Option<scala.concurrent.duration.FiniteDuration> apply$default$7();
    Code:
       0: getstatic     #42                 // Field io/youi/client/HttpClientConfig$.MODULE$:Lio/youi/client/HttpClientConfig$;
       3: invokevirtual #110                // Method io/youi/client/HttpClientConfig$.apply$default$7:()Lscala/Option;
       6: areturn

  public static scala.concurrent.duration.FiniteDuration apply$default$6();
    Code:
       0: getstatic     #42                 // Field io/youi/client/HttpClientConfig$.MODULE$:Lio/youi/client/HttpClientConfig$;
       3: invokevirtual #113                // Method io/youi/client/HttpClientConfig$.apply$default$6:()Lscala/concurrent/duration/FiniteDuration;
       6: areturn

  public static java.nio.file.Path apply$default$5();
    Code:
       0: getstatic     #42                 // Field io/youi/client/HttpClientConfig$.MODULE$:Lio/youi/client/HttpClientConfig$;
       3: invokevirtual #116                // Method io/youi/client/HttpClientConfig$.apply$default$5:()Ljava/nio/file/Path;
       6: areturn

  public static io.youi.client.ConnectionPool apply$default$4();
    Code:
       0: getstatic     #42                 // Field io/youi/client/HttpClientConfig$.MODULE$:Lio/youi/client/HttpClientConfig$;
       3: invokevirtual #119                // Method io/youi/client/HttpClientConfig$.apply$default$4:()Lio/youi/client/ConnectionPool;
       6: areturn

  public static io.youi.client.intercept.Interceptor apply$default$3();
    Code:
       0: getstatic     #42                 // Field io/youi/client/HttpClientConfig$.MODULE$:Lio/youi/client/HttpClientConfig$;
       3: invokevirtual #122                // Method io/youi/client/HttpClientConfig$.apply$default$3:()Lio/youi/client/intercept/Interceptor;
       6: areturn

  public static scala.concurrent.duration.FiniteDuration apply$default$2();
    Code:
       0: getstatic     #42                 // Field io/youi/client/HttpClientConfig$.MODULE$:Lio/youi/client/HttpClientConfig$;
       3: invokevirtual #125                // Method io/youi/client/HttpClientConfig$.apply$default$2:()Lscala/concurrent/duration/FiniteDuration;
       6: areturn

  public static int apply$default$1();
    Code:
       0: getstatic     #42                 // Field io/youi/client/HttpClientConfig$.MODULE$:Lio/youi/client/HttpClientConfig$;
       3: invokevirtual #128                // Method io/youi/client/HttpClientConfig$.apply$default$1:()I
       6: ireturn

  public static io.youi.client.HttpClientConfig apply(int, scala.concurrent.duration.FiniteDuration, io.youi.client.intercept.Interceptor, io.youi.client.ConnectionPool, java.nio.file.Path, scala.concurrent.duration.FiniteDuration, scala.Option<scala.concurrent.duration.FiniteDuration>, io.youi.client.DNS, boolean, scala.Option<io.youi.client.SessionManager>, boolean, boolean);
    Code:
       0: getstatic     #42                 // Field io/youi/client/HttpClientConfig$.MODULE$:Lio/youi/client/HttpClientConfig$;
       3: iload_0
       4: aload_1
       5: aload_2
       6: aload_3
       7: aload         4
       9: aload         5
      11: aload         6
      13: aload         7
      15: iload         8
      17: aload         9
      19: iload         10
      21: iload         11
      23: invokevirtual #133                // Method io/youi/client/HttpClientConfig$.apply:(ILscala/concurrent/duration/FiniteDuration;Lio/youi/client/intercept/Interceptor;Lio/youi/client/ConnectionPool;Ljava/nio/file/Path;Lscala/concurrent/duration/FiniteDuration;Lscala/Option;Lio/youi/client/DNS;ZLscala/Option;ZZ)Lio/youi/client/HttpClientConfig;
      26: areturn

  public static reactify.Var<io.youi.client.HttpClientConfig> default();
    Code:
       0: getstatic     #42                 // Field io/youi/client/HttpClientConfig$.MODULE$:Lio/youi/client/HttpClientConfig$;
       3: invokevirtual #138                // Method io/youi/client/HttpClientConfig$.default:()Lreactify/Var;
       6: areturn

  public scala.collection.Iterator<java.lang.String> productElementNames();
    Code:
       0: aload_0
       1: invokestatic  #145                // InterfaceMethod scala/Product.productElementNames$:(Lscala/Product;)Lscala/collection/Iterator;
       4: areturn

  public int retries();
    Code:
       0: aload_0
       1: getfield      #149                // Field retries:I
       4: ireturn

  public scala.concurrent.duration.FiniteDuration retryDelay();
    Code:
       0: aload_0
       1: getfield      #151                // Field retryDelay:Lscala/concurrent/duration/FiniteDuration;
       4: areturn

  public io.youi.client.intercept.Interceptor interceptor();
    Code:
       0: aload_0
       1: getfield      #153                // Field interceptor:Lio/youi/client/intercept/Interceptor;
       4: areturn

  public io.youi.client.ConnectionPool connectionPool();
    Code:
       0: aload_0
       1: getfield      #155                // Field connectionPool:Lio/youi/client/ConnectionPool;
       4: areturn

  public java.nio.file.Path saveDirectory();
    Code:
       0: aload_0
       1: getfield      #157                // Field saveDirectory:Ljava/nio/file/Path;
       4: areturn

  public scala.concurrent.duration.FiniteDuration timeout();
    Code:
       0: aload_0
       1: getfield      #159                // Field timeout:Lscala/concurrent/duration/FiniteDuration;
       4: areturn

  public scala.Option<scala.concurrent.duration.FiniteDuration> pingInterval();
    Code:
       0: aload_0
       1: getfield      #161                // Field pingInterval:Lscala/Option;
       4: areturn

  public io.youi.client.DNS dns();
    Code:
       0: aload_0
       1: getfield      #163                // Field dns:Lio/youi/client/DNS;
       4: areturn

  public boolean dropNullValuesInJson();
    Code:
       0: aload_0
       1: getfield      #165                // Field dropNullValuesInJson:Z
       4: ireturn

  public scala.Option<io.youi.client.SessionManager> sessionManager();
    Code:
       0: aload_0
       1: getfield      #167                // Field sessionManager:Lscala/Option;
       4: areturn

  public boolean failOnHttpStatus();
    Code:
       0: aload_0
       1: getfield      #169                // Field failOnHttpStatus:Z
       4: ireturn

  public boolean validateSSLCertificates();
    Code:
       0: aload_0
       1: getfield      #171                // Field validateSSLCertificates:Z
       4: ireturn

  public io.youi.client.HttpClientConfig retries(int);
    Code:
       0: aload_0
       1: iload_1
       2: aload_0
       3: invokevirtual #175                // Method copy$default$2:()Lscala/concurrent/duration/FiniteDuration;
       6: aload_0
       7: invokevirtual #178                // Method copy$default$3:()Lio/youi/client/intercept/Interceptor;
      10: aload_0
      11: invokevirtual #181                // Method copy$default$4:()Lio/youi/client/ConnectionPool;
      14: aload_0
      15: invokevirtual #184                // Method copy$default$5:()Ljava/nio/file/Path;
      18: aload_0
      19: invokevirtual #187                // Method copy$default$6:()Lscala/concurrent/duration/FiniteDuration;
      22: aload_0
      23: invokevirtual #190                // Method copy$default$7:()Lscala/Option;
      26: aload_0
      27: invokevirtual #193                // Method copy$default$8:()Lio/youi/client/DNS;
      30: aload_0
      31: invokevirtual #196                // Method copy$default$9:()Z
      34: aload_0
      35: invokevirtual #199                // Method copy$default$10:()Lscala/Option;
      38: aload_0
      39: invokevirtual #202                // Method copy$default$11:()Z
      42: aload_0
      43: invokevirtual #205                // Method copy$default$12:()Z
      46: invokevirtual #208                // Method copy:(ILscala/concurrent/duration/FiniteDuration;Lio/youi/client/intercept/Interceptor;Lio/youi/client/ConnectionPool;Ljava/nio/file/Path;Lscala/concurrent/duration/FiniteDuration;Lscala/Option;Lio/youi/client/DNS;ZLscala/Option;ZZ)Lio/youi/client/HttpClientConfig;
      49: areturn

  public io.youi.client.HttpClientConfig retryDelay(scala.concurrent.duration.FiniteDuration);
    Code:
       0: aload_1
       1: astore_2
       2: aload_0
       3: invokevirtual #212                // Method copy$default$1:()I
       6: istore_3
       7: aload_0
       8: invokevirtual #178                // Method copy$default$3:()Lio/youi/client/intercept/Interceptor;
      11: astore        4
      13: aload_0
      14: invokevirtual #181                // Method copy$default$4:()Lio/youi/client/ConnectionPool;
      17: astore        5
      19: aload_0
      20: invokevirtual #184                // Method copy$default$5:()Ljava/nio/file/Path;
      23: astore        6
      25: aload_0
      26: invokevirtual #187                // Method copy$default$6:()Lscala/concurrent/duration/FiniteDuration;
      29: astore        7
      31: aload_0
      32: invokevirtual #190                // Method copy$default$7:()Lscala/Option;
      35: astore        8
      37: aload_0
      38: invokevirtual #193                // Method copy$default$8:()Lio/youi/client/DNS;
      41: astore        9
      43: aload_0
      44: invokevirtual #196                // Method copy$default$9:()Z
      47: istore        10
      49: aload_0
      50: invokevirtual #199                // Method copy$default$10:()Lscala/Option;
      53: astore        11
      55: aload_0
      56: invokevirtual #202                // Method copy$default$11:()Z
      59: istore        12
      61: aload_0
      62: invokevirtual #205                // Method copy$default$12:()Z
      65: istore        13
      67: aload_0
      68: iload_3
      69: aload_2
      70: aload         4
      72: aload         5
      74: aload         6
      76: aload         7
      78: aload         8
      80: aload         9
      82: iload         10
      84: aload         11
      86: iload         12
      88: iload         13
      90: invokevirtual #208                // Method copy:(ILscala/concurrent/duration/FiniteDuration;Lio/youi/client/intercept/Interceptor;Lio/youi/client/ConnectionPool;Ljava/nio/file/Path;Lscala/concurrent/duration/FiniteDuration;Lscala/Option;Lio/youi/client/DNS;ZLscala/Option;ZZ)Lio/youi/client/HttpClientConfig;
      93: areturn

  public io.youi.client.HttpClientConfig interceptor(io.youi.client.intercept.Interceptor);
    Code:
       0: aload_1
       1: astore_2
       2: aload_0
       3: invokevirtual #212                // Method copy$default$1:()I
       6: istore_3
       7: aload_0
       8: invokevirtual #175                // Method copy$default$2:()Lscala/concurrent/duration/FiniteDuration;
      11: astore        4
      13: aload_0
      14: invokevirtual #181                // Method copy$default$4:()Lio/youi/client/ConnectionPool;
      17: astore        5
      19: aload_0
      20: invokevirtual #184                // Method copy$default$5:()Ljava/nio/file/Path;
      23: astore        6
      25: aload_0
      26: invokevirtual #187                // Method copy$default$6:()Lscala/concurrent/duration/FiniteDuration;
      29: astore        7
      31: aload_0
      32: invokevirtual #190                // Method copy$default$7:()Lscala/Option;
      35: astore        8
      37: aload_0
      38: invokevirtual #193                // Method copy$default$8:()Lio/youi/client/DNS;
      41: astore        9
      43: aload_0
      44: invokevirtual #196                // Method copy$default$9:()Z
      47: istore        10
      49: aload_0
      50: invokevirtual #199                // Method copy$default$10:()Lscala/Option;
      53: astore        11
      55: aload_0
      56: invokevirtual #202                // Method copy$default$11:()Z
      59: istore        12
      61: aload_0
      62: invokevirtual #205                // Method copy$default$12:()Z
      65: istore        13
      67: aload_0
      68: iload_3
      69: aload         4
      71: aload_2
      72: aload         5
      74: aload         6
      76: aload         7
      78: aload         8
      80: aload         9
      82: iload         10
      84: aload         11
      86: iload         12
      88: iload         13
      90: invokevirtual #208                // Method copy:(ILscala/concurrent/duration/FiniteDuration;Lio/youi/client/intercept/Interceptor;Lio/youi/client/ConnectionPool;Ljava/nio/file/Path;Lscala/concurrent/duration/FiniteDuration;Lscala/Option;Lio/youi/client/DNS;ZLscala/Option;ZZ)Lio/youi/client/HttpClientConfig;
      93: areturn

  public io.youi.client.HttpClientConfig connectionPool(io.youi.client.ConnectionPool);
    Code:
       0: aload_1
       1: astore_2
       2: aload_0
       3: invokevirtual #212                // Method copy$default$1:()I
       6: istore_3
       7: aload_0
       8: invokevirtual #175                // Method copy$default$2:()Lscala/concurrent/duration/FiniteDuration;
      11: astore        4
      13: aload_0
      14: invokevirtual #178                // Method copy$default$3:()Lio/youi/client/intercept/Interceptor;
      17: astore        5
      19: aload_0
      20: invokevirtual #184                // Method copy$default$5:()Ljava/nio/file/Path;
      23: astore        6
      25: aload_0
      26: invokevirtual #187                // Method copy$default$6:()Lscala/concurrent/duration/FiniteDuration;
      29: astore        7
      31: aload_0
      32: invokevirtual #190                // Method copy$default$7:()Lscala/Option;
      35: astore        8
      37: aload_0
      38: invokevirtual #193                // Method copy$default$8:()Lio/youi/client/DNS;
      41: astore        9
      43: aload_0
      44: invokevirtual #196                // Method copy$default$9:()Z
      47: istore        10
      49: aload_0
      50: invokevirtual #199                // Method copy$default$10:()Lscala/Option;
      53: astore        11
      55: aload_0
      56: invokevirtual #202                // Method copy$default$11:()Z
      59: istore        12
      61: aload_0
      62: invokevirtual #205                // Method copy$default$12:()Z
      65: istore        13
      67: aload_0
      68: iload_3
      69: aload         4
      71: aload         5
      73: aload_2
      74: aload         6
      76: aload         7
      78: aload         8
      80: aload         9
      82: iload         10
      84: aload         11
      86: iload         12
      88: iload         13
      90: invokevirtual #208                // Method copy:(ILscala/concurrent/duration/FiniteDuration;Lio/youi/client/intercept/Interceptor;Lio/youi/client/ConnectionPool;Ljava/nio/file/Path;Lscala/concurrent/duration/FiniteDuration;Lscala/Option;Lio/youi/client/DNS;ZLscala/Option;ZZ)Lio/youi/client/HttpClientConfig;
      93: areturn

  public io.youi.client.HttpClientConfig saveDirectory(java.nio.file.Path);
    Code:
       0: aload_1
       1: astore_2
       2: aload_0
       3: invokevirtual #212                // Method copy$default$1:()I
       6: istore_3
       7: aload_0
       8: invokevirtual #175                // Method copy$default$2:()Lscala/concurrent/duration/FiniteDuration;
      11: astore        4
      13: aload_0
      14: invokevirtual #178                // Method copy$default$3:()Lio/youi/client/intercept/Interceptor;
      17: astore        5
      19: aload_0
      20: invokevirtual #181                // Method copy$default$4:()Lio/youi/client/ConnectionPool;
      23: astore        6
      25: aload_0
      26: invokevirtual #187                // Method copy$default$6:()Lscala/concurrent/duration/FiniteDuration;
      29: astore        7
      31: aload_0
      32: invokevirtual #190                // Method copy$default$7:()Lscala/Option;
      35: astore        8
      37: aload_0
      38: invokevirtual #193                // Method copy$default$8:()Lio/youi/client/DNS;
      41: astore        9
      43: aload_0
      44: invokevirtual #196                // Method copy$default$9:()Z
      47: istore        10
      49: aload_0
      50: invokevirtual #199                // Method copy$default$10:()Lscala/Option;
      53: astore        11
      55: aload_0
      56: invokevirtual #202                // Method copy$default$11:()Z
      59: istore        12
      61: aload_0
      62: invokevirtual #205                // Method copy$default$12:()Z
      65: istore        13
      67: aload_0
      68: iload_3
      69: aload         4
      71: aload         5
      73: aload         6
      75: aload_2
      76: aload         7
      78: aload         8
      80: aload         9
      82: iload         10
      84: aload         11
      86: iload         12
      88: iload         13
      90: invokevirtual #208                // Method copy:(ILscala/concurrent/duration/FiniteDuration;Lio/youi/client/intercept/Interceptor;Lio/youi/client/ConnectionPool;Ljava/nio/file/Path;Lscala/concurrent/duration/FiniteDuration;Lscala/Option;Lio/youi/client/DNS;ZLscala/Option;ZZ)Lio/youi/client/HttpClientConfig;
      93: areturn

  public io.youi.client.HttpClientConfig timeout(scala.concurrent.duration.FiniteDuration);
    Code:
       0: aload_1
       1: astore_2
       2: aload_0
       3: invokevirtual #212                // Method copy$default$1:()I
       6: istore_3
       7: aload_0
       8: invokevirtual #175                // Method copy$default$2:()Lscala/concurrent/duration/FiniteDuration;
      11: astore        4
      13: aload_0
      14: invokevirtual #178                // Method copy$default$3:()Lio/youi/client/intercept/Interceptor;
      17: astore        5
      19: aload_0
      20: invokevirtual #181                // Method copy$default$4:()Lio/youi/client/ConnectionPool;
      23: astore        6
      25: aload_0
      26: invokevirtual #184                // Method copy$default$5:()Ljava/nio/file/Path;
      29: astore        7
      31: aload_0
      32: invokevirtual #190                // Method copy$default$7:()Lscala/Option;
      35: astore        8
      37: aload_0
      38: invokevirtual #193                // Method copy$default$8:()Lio/youi/client/DNS;
      41: astore        9
      43: aload_0
      44: invokevirtual #196                // Method copy$default$9:()Z
      47: istore        10
      49: aload_0
      50: invokevirtual #199                // Method copy$default$10:()Lscala/Option;
      53: astore        11
      55: aload_0
      56: invokevirtual #202                // Method copy$default$11:()Z
      59: istore        12
      61: aload_0
      62: invokevirtual #205                // Method copy$default$12:()Z
      65: istore        13
      67: aload_0
      68: iload_3
      69: aload         4
      71: aload         5
      73: aload         6
      75: aload         7
      77: aload_2
      78: aload         8
      80: aload         9
      82: iload         10
      84: aload         11
      86: iload         12
      88: iload         13
      90: invokevirtual #208                // Method copy:(ILscala/concurrent/duration/FiniteDuration;Lio/youi/client/intercept/Interceptor;Lio/youi/client/ConnectionPool;Ljava/nio/file/Path;Lscala/concurrent/duration/FiniteDuration;Lscala/Option;Lio/youi/client/DNS;ZLscala/Option;ZZ)Lio/youi/client/HttpClientConfig;
      93: areturn

  public io.youi.client.HttpClientConfig pingInterval(scala.Option<scala.concurrent.duration.FiniteDuration>);
    Code:
       0: aload_1
       1: astore_2
       2: aload_0
       3: invokevirtual #212                // Method copy$default$1:()I
       6: istore_3
       7: aload_0
       8: invokevirtual #175                // Method copy$default$2:()Lscala/concurrent/duration/FiniteDuration;
      11: astore        4
      13: aload_0
      14: invokevirtual #178                // Method copy$default$3:()Lio/youi/client/intercept/Interceptor;
      17: astore        5
      19: aload_0
      20: invokevirtual #181                // Method copy$default$4:()Lio/youi/client/ConnectionPool;
      23: astore        6
      25: aload_0
      26: invokevirtual #184                // Method copy$default$5:()Ljava/nio/file/Path;
      29: astore        7
      31: aload_0
      32: invokevirtual #187                // Method copy$default$6:()Lscala/concurrent/duration/FiniteDuration;
      35: astore        8
      37: aload_0
      38: invokevirtual #193                // Method copy$default$8:()Lio/youi/client/DNS;
      41: astore        9
      43: aload_0
      44: invokevirtual #196                // Method copy$default$9:()Z
      47: istore        10
      49: aload_0
      50: invokevirtual #199                // Method copy$default$10:()Lscala/Option;
      53: astore        11
      55: aload_0
      56: invokevirtual #202                // Method copy$default$11:()Z
      59: istore        12
      61: aload_0
      62: invokevirtual #205                // Method copy$default$12:()Z
      65: istore        13
      67: aload_0
      68: iload_3
      69: aload         4
      71: aload         5
      73: aload         6
      75: aload         7
      77: aload         8
      79: aload_2
      80: aload         9
      82: iload         10
      84: aload         11
      86: iload         12
      88: iload         13
      90: invokevirtual #208                // Method copy:(ILscala/concurrent/duration/FiniteDuration;Lio/youi/client/intercept/Interceptor;Lio/youi/client/ConnectionPool;Ljava/nio/file/Path;Lscala/concurrent/duration/FiniteDuration;Lscala/Option;Lio/youi/client/DNS;ZLscala/Option;ZZ)Lio/youi/client/HttpClientConfig;
      93: areturn

  public io.youi.client.HttpClientConfig dns(io.youi.client.DNS);
    Code:
       0: aload_1
       1: astore_2
       2: aload_0
       3: invokevirtual #212                // Method copy$default$1:()I
       6: istore_3
       7: aload_0
       8: invokevirtual #175                // Method copy$default$2:()Lscala/concurrent/duration/FiniteDuration;
      11: astore        4
      13: aload_0
      14: invokevirtual #178                // Method copy$default$3:()Lio/youi/client/intercept/Interceptor;
      17: astore        5
      19: aload_0
      20: invokevirtual #181                // Method copy$default$4:()Lio/youi/client/ConnectionPool;
      23: astore        6
      25: aload_0
      26: invokevirtual #184                // Method copy$default$5:()Ljava/nio/file/Path;
      29: astore        7
      31: aload_0
      32: invokevirtual #187                // Method copy$default$6:()Lscala/concurrent/duration/FiniteDuration;
      35: astore        8
      37: aload_0
      38: invokevirtual #190                // Method copy$default$7:()Lscala/Option;
      41: astore        9
      43: aload_0
      44: invokevirtual #196                // Method copy$default$9:()Z
      47: istore        10
      49: aload_0
      50: invokevirtual #199                // Method copy$default$10:()Lscala/Option;
      53: astore        11
      55: aload_0
      56: invokevirtual #202                // Method copy$default$11:()Z
      59: istore        12
      61: aload_0
      62: invokevirtual #205                // Method copy$default$12:()Z
      65: istore        13
      67: aload_0
      68: iload_3
      69: aload         4
      71: aload         5
      73: aload         6
      75: aload         7
      77: aload         8
      79: aload         9
      81: aload_2
      82: iload         10
      84: aload         11
      86: iload         12
      88: iload         13
      90: invokevirtual #208                // Method copy:(ILscala/concurrent/duration/FiniteDuration;Lio/youi/client/intercept/Interceptor;Lio/youi/client/ConnectionPool;Ljava/nio/file/Path;Lscala/concurrent/duration/FiniteDuration;Lscala/Option;Lio/youi/client/DNS;ZLscala/Option;ZZ)Lio/youi/client/HttpClientConfig;
      93: areturn

  public io.youi.client.HttpClientConfig sessionManager(io.youi.client.SessionManager);
    Code:
       0: new           #233                // class scala/Some
       3: dup
       4: aload_1
       5: invokespecial #237                // Method scala/Some."<init>":(Ljava/lang/Object;)V
       8: astore_2
       9: aload_0
      10: invokevirtual #212                // Method copy$default$1:()I
      13: istore_3
      14: aload_0
      15: invokevirtual #175                // Method copy$default$2:()Lscala/concurrent/duration/FiniteDuration;
      18: astore        4
      20: aload_0
      21: invokevirtual #178                // Method copy$default$3:()Lio/youi/client/intercept/Interceptor;
      24: astore        5
      26: aload_0
      27: invokevirtual #181                // Method copy$default$4:()Lio/youi/client/ConnectionPool;
      30: astore        6
      32: aload_0
      33: invokevirtual #184                // Method copy$default$5:()Ljava/nio/file/Path;
      36: astore        7
      38: aload_0
      39: invokevirtual #187                // Method copy$default$6:()Lscala/concurrent/duration/FiniteDuration;
      42: astore        8
      44: aload_0
      45: invokevirtual #190                // Method copy$default$7:()Lscala/Option;
      48: astore        9
      50: aload_0
      51: invokevirtual #193                // Method copy$default$8:()Lio/youi/client/DNS;
      54: astore        10
      56: aload_0
      57: invokevirtual #196                // Method copy$default$9:()Z
      60: istore        11
      62: aload_0
      63: invokevirtual #202                // Method copy$default$11:()Z
      66: istore        12
      68: aload_0
      69: invokevirtual #205                // Method copy$default$12:()Z
      72: istore        13
      74: aload_0
      75: iload_3
      76: aload         4
      78: aload         5
      80: aload         6
      82: aload         7
      84: aload         8
      86: aload         9
      88: aload         10
      90: iload         11
      92: aload_2
      93: iload         12
      95: iload         13
      97: invokevirtual #208                // Method copy:(ILscala/concurrent/duration/FiniteDuration;Lio/youi/client/intercept/Interceptor;Lio/youi/client/ConnectionPool;Ljava/nio/file/Path;Lscala/concurrent/duration/FiniteDuration;Lscala/Option;Lio/youi/client/DNS;ZLscala/Option;ZZ)Lio/youi/client/HttpClientConfig;
     100: areturn

  public io.youi.client.HttpClientConfig session(io.youi.client.Session);
    Code:
       0: new           #233                // class scala/Some
       3: dup
       4: new           #243                // class io/youi/client/SessionManager
       7: dup
       8: aload_1
       9: invokespecial #246                // Method io/youi/client/SessionManager."<init>":(Lio/youi/client/Session;)V
      12: invokespecial #237                // Method scala/Some."<init>":(Ljava/lang/Object;)V
      15: astore_2
      16: aload_0
      17: invokevirtual #212                // Method copy$default$1:()I
      20: istore_3
      21: aload_0
      22: invokevirtual #175                // Method copy$default$2:()Lscala/concurrent/duration/FiniteDuration;
      25: astore        4
      27: aload_0
      28: invokevirtual #178                // Method copy$default$3:()Lio/youi/client/intercept/Interceptor;
      31: astore        5
      33: aload_0
      34: invokevirtual #181                // Method copy$default$4:()Lio/youi/client/ConnectionPool;
      37: astore        6
      39: aload_0
      40: invokevirtual #184                // Method copy$default$5:()Ljava/nio/file/Path;
      43: astore        7
      45: aload_0
      46: invokevirtual #187                // Method copy$default$6:()Lscala/concurrent/duration/FiniteDuration;
      49: astore        8
      51: aload_0
      52: invokevirtual #190                // Method copy$default$7:()Lscala/Option;
      55: astore        9
      57: aload_0
      58: invokevirtual #193                // Method copy$default$8:()Lio/youi/client/DNS;
      61: astore        10
      63: aload_0
      64: invokevirtual #196                // Method copy$default$9:()Z
      67: istore        11
      69: aload_0
      70: invokevirtual #202                // Method copy$default$11:()Z
      73: istore        12
      75: aload_0
      76: invokevirtual #205                // Method copy$default$12:()Z
      79: istore        13
      81: aload_0
      82: iload_3
      83: aload         4
      85: aload         5
      87: aload         6
      89: aload         7
      91: aload         8
      93: aload         9
      95: aload         10
      97: iload         11
      99: aload_2
     100: iload         12
     102: iload         13
     104: invokevirtual #208                // Method copy:(ILscala/concurrent/duration/FiniteDuration;Lio/youi/client/intercept/Interceptor;Lio/youi/client/ConnectionPool;Ljava/nio/file/Path;Lscala/concurrent/duration/FiniteDuration;Lscala/Option;Lio/youi/client/DNS;ZLscala/Option;ZZ)Lio/youi/client/HttpClientConfig;
     107: areturn

  public io.youi.client.HttpClientConfig failOnHttpStatus(boolean);
    Code:
       0: iload_1
       1: istore_2
       2: aload_0
       3: invokevirtual #212                // Method copy$default$1:()I
       6: istore_3
       7: aload_0
       8: invokevirtual #175                // Method copy$default$2:()Lscala/concurrent/duration/FiniteDuration;
      11: astore        4
      13: aload_0
      14: invokevirtual #178                // Method copy$default$3:()Lio/youi/client/intercept/Interceptor;
      17: astore        5
      19: aload_0
      20: invokevirtual #181                // Method copy$default$4:()Lio/youi/client/ConnectionPool;
      23: astore        6
      25: aload_0
      26: invokevirtual #184                // Method copy$default$5:()Ljava/nio/file/Path;
      29: astore        7
      31: aload_0
      32: invokevirtual #187                // Method copy$default$6:()Lscala/concurrent/duration/FiniteDuration;
      35: astore        8
      37: aload_0
      38: invokevirtual #190                // Method copy$default$7:()Lscala/Option;
      41: astore        9
      43: aload_0
      44: invokevirtual #193                // Method copy$default$8:()Lio/youi/client/DNS;
      47: astore        10
      49: aload_0
      50: invokevirtual #196                // Method copy$default$9:()Z
      53: istore        11
      55: aload_0
      56: invokevirtual #199                // Method copy$default$10:()Lscala/Option;
      59: astore        12
      61: aload_0
      62: invokevirtual #205                // Method copy$default$12:()Z
      65: istore        13
      67: aload_0
      68: iload_3
      69: aload         4
      71: aload         5
      73: aload         6
      75: aload         7
      77: aload         8
      79: aload         9
      81: aload         10
      83: iload         11
      85: aload         12
      87: iload_2
      88: iload         13
      90: invokevirtual #208                // Method copy:(ILscala/concurrent/duration/FiniteDuration;Lio/youi/client/intercept/Interceptor;Lio/youi/client/ConnectionPool;Ljava/nio/file/Path;Lscala/concurrent/duration/FiniteDuration;Lscala/Option;Lio/youi/client/DNS;ZLscala/Option;ZZ)Lio/youi/client/HttpClientConfig;
      93: areturn

  public io.youi.client.HttpClientConfig copy(int, scala.concurrent.duration.FiniteDuration, io.youi.client.intercept.Interceptor, io.youi.client.ConnectionPool, java.nio.file.Path, scala.concurrent.duration.FiniteDuration, scala.Option<scala.concurrent.duration.FiniteDuration>, io.youi.client.DNS, boolean, scala.Option<io.youi.client.SessionManager>, boolean, boolean);
    Code:
       0: new           #2                  // class io/youi/client/HttpClientConfig
       3: dup
       4: iload_1
       5: aload_2
       6: aload_3
       7: aload         4
       9: aload         5
      11: aload         6
      13: aload         7
      15: aload         8
      17: iload         9
      19: aload         10
      21: iload         11
      23: iload         12
      25: invokespecial #251                // Method "<init>":(ILscala/concurrent/duration/FiniteDuration;Lio/youi/client/intercept/Interceptor;Lio/youi/client/ConnectionPool;Ljava/nio/file/Path;Lscala/concurrent/duration/FiniteDuration;Lscala/Option;Lio/youi/client/DNS;ZLscala/Option;ZZ)V
      28: areturn

  public int copy$default$1();
    Code:
       0: aload_0
       1: invokevirtual #253                // Method retries:()I
       4: ireturn

  public scala.Option<io.youi.client.SessionManager> copy$default$10();
    Code:
       0: aload_0
       1: invokevirtual #255                // Method sessionManager:()Lscala/Option;
       4: areturn

  public boolean copy$default$11();
    Code:
       0: aload_0
       1: invokevirtual #257                // Method failOnHttpStatus:()Z
       4: ireturn

  public boolean copy$default$12();
    Code:
       0: aload_0
       1: invokevirtual #259                // Method validateSSLCertificates:()Z
       4: ireturn

  public scala.concurrent.duration.FiniteDuration copy$default$2();
    Code:
       0: aload_0
       1: invokevirtual #261                // Method retryDelay:()Lscala/concurrent/duration/FiniteDuration;
       4: areturn

  public io.youi.client.intercept.Interceptor copy$default$3();
    Code:
       0: aload_0
       1: invokevirtual #263                // Method interceptor:()Lio/youi/client/intercept/Interceptor;
       4: areturn

  public io.youi.client.ConnectionPool copy$default$4();
    Code:
       0: aload_0
       1: invokevirtual #265                // Method connectionPool:()Lio/youi/client/ConnectionPool;
       4: areturn

  public java.nio.file.Path copy$default$5();
    Code:
       0: aload_0
       1: invokevirtual #267                // Method saveDirectory:()Ljava/nio/file/Path;
       4: areturn

  public scala.concurrent.duration.FiniteDuration copy$default$6();
    Code:
       0: aload_0
       1: invokevirtual #269                // Method timeout:()Lscala/concurrent/duration/FiniteDuration;
       4: areturn

  public scala.Option<scala.concurrent.duration.FiniteDuration> copy$default$7();
    Code:
       0: aload_0
       1: invokevirtual #271                // Method pingInterval:()Lscala/Option;
       4: areturn

  public io.youi.client.DNS copy$default$8();
    Code:
       0: aload_0
       1: invokevirtual #273                // Method dns:()Lio/youi/client/DNS;
       4: areturn

  public boolean copy$default$9();
    Code:
       0: aload_0
       1: invokevirtual #275                // Method dropNullValuesInJson:()Z
       4: ireturn

  public java.lang.String productPrefix();
    Code:
       0: ldc_w         #279                // String HttpClientConfig
       3: areturn

  public int productArity();
    Code:
       0: bipush        12
       2: ireturn

  public java.lang.Object productElement(int);
    Code:
       0: iload_1
       1: istore_2
       2: iload_2
       3: tableswitch   { // 0 to 11
                     0: 64
                     1: 74
                     2: 81
                     3: 88
                     4: 95
                     5: 102
                     6: 109
                     7: 116
                     8: 123
                     9: 133
                    10: 140
                    11: 150
               default: 160
          }
      64: aload_0
      65: invokevirtual #253                // Method retries:()I
      68: invokestatic  #288                // Method scala/runtime/BoxesRunTime.boxToInteger:(I)Ljava/lang/Integer;
      71: goto          167
      74: aload_0
      75: invokevirtual #261                // Method retryDelay:()Lscala/concurrent/duration/FiniteDuration;
      78: goto          167
      81: aload_0
      82: invokevirtual #263                // Method interceptor:()Lio/youi/client/intercept/Interceptor;
      85: goto          167
      88: aload_0
      89: invokevirtual #265                // Method connectionPool:()Lio/youi/client/ConnectionPool;
      92: goto          167
      95: aload_0
      96: invokevirtual #267                // Method saveDirectory:()Ljava/nio/file/Path;
      99: goto          167
     102: aload_0
     103: invokevirtual #269                // Method timeout:()Lscala/concurrent/duration/FiniteDuration;
     106: goto          167
     109: aload_0
     110: invokevirtual #271                // Method pingInterval:()Lscala/Option;
     113: goto          167
     116: aload_0
     117: invokevirtual #273                // Method dns:()Lio/youi/client/DNS;
     120: goto          167
     123: aload_0
     124: invokevirtual #275                // Method dropNullValuesInJson:()Z
     127: invokestatic  #292                // Method scala/runtime/BoxesRunTime.boxToBoolean:(Z)Ljava/lang/Boolean;
     130: goto          167
     133: aload_0
     134: invokevirtual #255                // Method sessionManager:()Lscala/Option;
     137: goto          167
     140: aload_0
     141: invokevirtual #257                // Method failOnHttpStatus:()Z
     144: invokestatic  #292                // Method scala/runtime/BoxesRunTime.boxToBoolean:(Z)Ljava/lang/Boolean;
     147: goto          167
     150: aload_0
     151: invokevirtual #259                // Method validateSSLCertificates:()Z
     154: invokestatic  #292                // Method scala/runtime/BoxesRunTime.boxToBoolean:(Z)Ljava/lang/Boolean;
     157: goto          167
     160: iload_1
     161: invokestatic  #297                // Method scala/runtime/Statics.ioobe:(I)Ljava/lang/Object;
     164: goto          167
     167: areturn

  public scala.collection.Iterator<java.lang.Object> productIterator();
    Code:
       0: getstatic     #304                // Field scala/runtime/ScalaRunTime$.MODULE$:Lscala/runtime/ScalaRunTime$;
       3: aload_0
       4: invokevirtual #307                // Method scala/runtime/ScalaRunTime$.typedProductIterator:(Lscala/Product;)Lscala/collection/Iterator;
       7: areturn

  public boolean canEqual(java.lang.Object);
    Code:
       0: aload_1
       1: instanceof    #2                  // class io/youi/client/HttpClientConfig
       4: ireturn

  public java.lang.String productElementName(int);
    Code:
       0: iload_1
       1: istore_2
       2: iload_2
       3: tableswitch   { // 0 to 11
                     0: 64
                     1: 70
                     2: 76
                     3: 82
                     4: 88
                     5: 94
                     6: 100
                     7: 106
                     8: 112
                     9: 118
                    10: 124
                    11: 130
               default: 136
          }
      64: ldc_w         #313                // String retries
      67: goto          146
      70: ldc_w         #314                // String retryDelay
      73: goto          146
      76: ldc_w         #315                // String interceptor
      79: goto          146
      82: ldc_w         #316                // String connectionPool
      85: goto          146
      88: ldc_w         #317                // String saveDirectory
      91: goto          146
      94: ldc_w         #318                // String timeout
      97: goto          146
     100: ldc_w         #319                // String pingInterval
     103: goto          146
     106: ldc_w         #320                // String dns
     109: goto          146
     112: ldc_w         #321                // String dropNullValuesInJson
     115: goto          146
     118: ldc_w         #322                // String sessionManager
     121: goto          146
     124: ldc_w         #323                // String failOnHttpStatus
     127: goto          146
     130: ldc_w         #324                // String validateSSLCertificates
     133: goto          146
     136: iload_1
     137: invokestatic  #297                // Method scala/runtime/Statics.ioobe:(I)Ljava/lang/Object;
     140: checkcast     #326                // class java/lang/String
     143: goto          146
     146: areturn

  public int hashCode();
    Code:
       0: ldc_w         #328                // int -889275714
       3: istore_1
       4: iload_1
       5: aload_0
       6: invokevirtual #330                // Method productPrefix:()Ljava/lang/String;
       9: invokevirtual #332                // Method java/lang/String.hashCode:()I
      12: invokestatic  #336                // Method scala/runtime/Statics.mix:(II)I
      15: istore_1
      16: iload_1
      17: aload_0
      18: invokevirtual #253                // Method retries:()I
      21: invokestatic  #336                // Method scala/runtime/Statics.mix:(II)I
      24: istore_1
      25: iload_1
      26: aload_0
      27: invokevirtual #261                // Method retryDelay:()Lscala/concurrent/duration/FiniteDuration;
      30: invokestatic  #340                // Method scala/runtime/Statics.anyHash:(Ljava/lang/Object;)I
      33: invokestatic  #336                // Method scala/runtime/Statics.mix:(II)I
      36: istore_1
      37: iload_1
      38: aload_0
      39: invokevirtual #263                // Method interceptor:()Lio/youi/client/intercept/Interceptor;
      42: invokestatic  #340                // Method scala/runtime/Statics.anyHash:(Ljava/lang/Object;)I
      45: invokestatic  #336                // Method scala/runtime/Statics.mix:(II)I
      48: istore_1
      49: iload_1
      50: aload_0
      51: invokevirtual #265                // Method connectionPool:()Lio/youi/client/ConnectionPool;
      54: invokestatic  #340                // Method scala/runtime/Statics.anyHash:(Ljava/lang/Object;)I
      57: invokestatic  #336                // Method scala/runtime/Statics.mix:(II)I
      60: istore_1
      61: iload_1
      62: aload_0
      63: invokevirtual #267                // Method saveDirectory:()Ljava/nio/file/Path;
      66: invokestatic  #340                // Method scala/runtime/Statics.anyHash:(Ljava/lang/Object;)I
      69: invokestatic  #336                // Method scala/runtime/Statics.mix:(II)I
      72: istore_1
      73: iload_1
      74: aload_0
      75: invokevirtual #269                // Method timeout:()Lscala/concurrent/duration/FiniteDuration;
      78: invokestatic  #340                // Method scala/runtime/Statics.anyHash:(Ljava/lang/Object;)I
      81: invokestatic  #336                // Method scala/runtime/Statics.mix:(II)I
      84: istore_1
      85: iload_1
      86: aload_0
      87: invokevirtual #271                // Method pingInterval:()Lscala/Option;
      90: invokestatic  #340                // Method scala/runtime/Statics.anyHash:(Ljava/lang/Object;)I
      93: invokestatic  #336                // Method scala/runtime/Statics.mix:(II)I
      96: istore_1
      97: iload_1
      98: aload_0
      99: invokevirtual #273                // Method dns:()Lio/youi/client/DNS;
     102: invokestatic  #340                // Method scala/runtime/Statics.anyHash:(Ljava/lang/Object;)I
     105: invokestatic  #336                // Method scala/runtime/Statics.mix:(II)I
     108: istore_1
     109: iload_1
     110: aload_0
     111: invokevirtual #275                // Method dropNullValuesInJson:()Z
     114: ifeq          123
     117: sipush        1231
     120: goto          126
     123: sipush        1237
     126: invokestatic  #336                // Method scala/runtime/Statics.mix:(II)I
     129: istore_1
     130: iload_1
     131: aload_0
     132: invokevirtual #255                // Method sessionManager:()Lscala/Option;
     135: invokestatic  #340                // Method scala/runtime/Statics.anyHash:(Ljava/lang/Object;)I
     138: invokestatic  #336                // Method scala/runtime/Statics.mix:(II)I
     141: istore_1
     142: iload_1
     143: aload_0
     144: invokevirtual #257                // Method failOnHttpStatus:()Z
     147: ifeq          156
     150: sipush        1231
     153: goto          159
     156: sipush        1237
     159: invokestatic  #336                // Method scala/runtime/Statics.mix:(II)I
     162: istore_1
     163: iload_1
     164: aload_0
     165: invokevirtual #259                // Method validateSSLCertificates:()Z
     168: ifeq          177
     171: sipush        1231
     174: goto          180
     177: sipush        1237
     180: invokestatic  #336                // Method scala/runtime/Statics.mix:(II)I
     183: istore_1
     184: iload_1
     185: bipush        12
     187: invokestatic  #343                // Method scala/runtime/Statics.finalizeHash:(II)I
     190: ireturn

  public java.lang.String toString();
    Code:
       0: getstatic     #304                // Field scala/runtime/ScalaRunTime$.MODULE$:Lscala/runtime/ScalaRunTime$;
       3: aload_0
       4: invokevirtual #348                // Method scala/runtime/ScalaRunTime$._toString:(Lscala/Product;)Ljava/lang/String;
       7: areturn

  public boolean equals(java.lang.Object);
    Code:
       0: aload_0
       1: aload_1
       2: if_acmpeq     358
       5: aload_1
       6: astore_3
       7: aload_3
       8: instanceof    #2                  // class io/youi/client/HttpClientConfig
      11: ifeq          19
      14: iconst_1
      15: istore_2
      16: goto          27
      19: goto          22
      22: iconst_0
      23: istore_2
      24: goto          27
      27: iload_2
      28: ifeq          362
      31: aload_1
      32: checkcast     #2                  // class io/youi/client/HttpClientConfig
      35: astore        4
      37: aload_0
      38: invokevirtual #253                // Method retries:()I
      41: aload         4
      43: invokevirtual #253                // Method retries:()I
      46: if_icmpne     354
      49: aload_0
      50: invokevirtual #275                // Method dropNullValuesInJson:()Z
      53: aload         4
      55: invokevirtual #275                // Method dropNullValuesInJson:()Z
      58: if_icmpne     354
      61: aload_0
      62: invokevirtual #257                // Method failOnHttpStatus:()Z
      65: aload         4
      67: invokevirtual #257                // Method failOnHttpStatus:()Z
      70: if_icmpne     354
      73: aload_0
      74: invokevirtual #259                // Method validateSSLCertificates:()Z
      77: aload         4
      79: invokevirtual #259                // Method validateSSLCertificates:()Z
      82: if_icmpne     354
      85: aload_0
      86: invokevirtual #261                // Method retryDelay:()Lscala/concurrent/duration/FiniteDuration;
      89: aload         4
      91: invokevirtual #261                // Method retryDelay:()Lscala/concurrent/duration/FiniteDuration;
      94: astore        5
      96: dup
      97: ifnonnull     109
     100: pop
     101: aload         5
     103: ifnull        117
     106: goto          354
     109: aload         5
     111: invokevirtual #351                // Method java/lang/Object.equals:(Ljava/lang/Object;)Z
     114: ifeq          354
     117: aload_0
     118: invokevirtual #263                // Method interceptor:()Lio/youi/client/intercept/Interceptor;
     121: aload         4
     123: invokevirtual #263                // Method interceptor:()Lio/youi/client/intercept/Interceptor;
     126: astore        6
     128: dup
     129: ifnonnull     141
     132: pop
     133: aload         6
     135: ifnull        149
     138: goto          354
     141: aload         6
     143: invokevirtual #351                // Method java/lang/Object.equals:(Ljava/lang/Object;)Z
     146: ifeq          354
     149: aload_0
     150: invokevirtual #265                // Method connectionPool:()Lio/youi/client/ConnectionPool;
     153: aload         4
     155: invokevirtual #265                // Method connectionPool:()Lio/youi/client/ConnectionPool;
     158: astore        7
     160: dup
     161: ifnonnull     173
     164: pop
     165: aload         7
     167: ifnull        181
     170: goto          354
     173: aload         7
     175: invokevirtual #351                // Method java/lang/Object.equals:(Ljava/lang/Object;)Z
     178: ifeq          354
     181: aload_0
     182: invokevirtual #267                // Method saveDirectory:()Ljava/nio/file/Path;
     185: aload         4
     187: invokevirtual #267                // Method saveDirectory:()Ljava/nio/file/Path;
     190: astore        8
     192: dup
     193: ifnonnull     205
     196: pop
     197: aload         8
     199: ifnull        213
     202: goto          354
     205: aload         8
     207: invokevirtual #351                // Method java/lang/Object.equals:(Ljava/lang/Object;)Z
     210: ifeq          354
     213: aload_0
     214: invokevirtual #269                // Method timeout:()Lscala/concurrent/duration/FiniteDuration;
     217: aload         4
     219: invokevirtual #269                // Method timeout:()Lscala/concurrent/duration/FiniteDuration;
     222: astore        9
     224: dup
     225: ifnonnull     237
     228: pop
     229: aload         9
     231: ifnull        245
     234: goto          354
     237: aload         9
     239: invokevirtual #351                // Method java/lang/Object.equals:(Ljava/lang/Object;)Z
     242: ifeq          354
     245: aload_0
     246: invokevirtual #271                // Method pingInterval:()Lscala/Option;
     249: aload         4
     251: invokevirtual #271                // Method pingInterval:()Lscala/Option;
     254: astore        10
     256: dup
     257: ifnonnull     269
     260: pop
     261: aload         10
     263: ifnull        277
     266: goto          354
     269: aload         10
     271: invokevirtual #351                // Method java/lang/Object.equals:(Ljava/lang/Object;)Z
     274: ifeq          354
     277: aload_0
     278: invokevirtual #273                // Method dns:()Lio/youi/client/DNS;
     281: aload         4
     283: invokevirtual #273                // Method dns:()Lio/youi/client/DNS;
     286: astore        11
     288: dup
     289: ifnonnull     301
     292: pop
     293: aload         11
     295: ifnull        309
     298: goto          354
     301: aload         11
     303: invokevirtual #351                // Method java/lang/Object.equals:(Ljava/lang/Object;)Z
     306: ifeq          354
     309: aload_0
     310: invokevirtual #255                // Method sessionManager:()Lscala/Option;
     313: aload         4
     315: invokevirtual #255                // Method sessionManager:()Lscala/Option;
     318: astore        12
     320: dup
     321: ifnonnull     333
     324: pop
     325: aload         12
     327: ifnull        341
     330: goto          354
     333: aload         12
     335: invokevirtual #351                // Method java/lang/Object.equals:(Ljava/lang/Object;)Z
     338: ifeq          354
     341: aload         4
     343: aload_0
     344: invokevirtual #353                // Method canEqual:(Ljava/lang/Object;)Z
     347: ifeq          354
     350: iconst_1
     351: goto          355
     354: iconst_0
     355: ifeq          362
     358: iconst_1
     359: goto          363
     362: iconst_0
     363: ireturn

  public io.youi.client.HttpClientConfig(int, scala.concurrent.duration.FiniteDuration, io.youi.client.intercept.Interceptor, io.youi.client.ConnectionPool, java.nio.file.Path, scala.concurrent.duration.FiniteDuration, scala.Option<scala.concurrent.duration.FiniteDuration>, io.youi.client.DNS, boolean, scala.Option<io.youi.client.SessionManager>, boolean, boolean);
    Code:
       0: aload_0
       1: iload_1
       2: putfield      #149                // Field retries:I
       5: aload_0
       6: aload_2
       7: putfield      #151                // Field retryDelay:Lscala/concurrent/duration/FiniteDuration;
      10: aload_0
      11: aload_3
      12: putfield      #153                // Field interceptor:Lio/youi/client/intercept/Interceptor;
      15: aload_0
      16: aload         4
      18: putfield      #155                // Field connectionPool:Lio/youi/client/ConnectionPool;
      21: aload_0
      22: aload         5
      24: putfield      #157                // Field saveDirectory:Ljava/nio/file/Path;
      27: aload_0
      28: aload         6
      30: putfield      #159                // Field timeout:Lscala/concurrent/duration/FiniteDuration;
      33: aload_0
      34: aload         7
      36: putfield      #161                // Field pingInterval:Lscala/Option;
      39: aload_0
      40: aload         8
      42: putfield      #163                // Field dns:Lio/youi/client/DNS;
      45: aload_0
      46: iload         9
      48: putfield      #165                // Field dropNullValuesInJson:Z
      51: aload_0
      52: aload         10
      54: putfield      #167                // Field sessionManager:Lscala/Option;
      57: aload_0
      58: iload         11
      60: putfield      #169                // Field failOnHttpStatus:Z
      63: aload_0
      64: iload         12
      66: putfield      #171                // Field validateSSLCertificates:Z
      69: aload_0
      70: invokespecial #369                // Method java/lang/Object."<init>":()V
      73: aload_0
      74: invokestatic  #373                // InterfaceMethod scala/Product.$init$:(Lscala/Product;)V
      77: return
}
