Compiled from "ActionFactory.java"
class org.eclipse.ui.actions.ActionFactory$14 extends org.eclipse.ui.actions.ActionFactory {
  org.eclipse.ui.actions.ActionFactory$14(java.lang.String, java.lang.String);
    Code:
       0: aload_0
       1: aload_1
       2: aload_2
       3: invokespecial #94                 // Method org/eclipse/ui/actions/ActionFactory."<init>":(Ljava/lang/String;Ljava/lang/String;)V
       6: return

  public org.eclipse.ui.actions.ActionFactory$IWorkbenchAction create(org.eclipse.ui.IWorkbenchWindow);
    Code:
       0: aload_1
       1: ifnonnull     12
       4: new           #45                 // class java/lang/IllegalArgumentException
       7: dup
       8: invokespecial #93                 // Method java/lang/IllegalArgumentException."<init>":()V
      11: athrow
      12: new           #53                 // class org/eclipse/ui/actions/RetargetAction
      15: dup
      16: aload_0
      17: invokevirtual #96                 // Method getId:()Ljava/lang/String;
      20: getstatic     #91                 // Field org/eclipse/ui/internal/WorkbenchMessages.Workbench_delete:Ljava/lang/String;
      23: invokespecial #102                // Method org/eclipse/ui/actions/RetargetAction."<init>":(Ljava/lang/String;Ljava/lang/String;)V
      26: astore_2
      27: aload_2
      28: getstatic     #92                 // Field org/eclipse/ui/internal/WorkbenchMessages.Workbench_deleteToolTip:Ljava/lang/String;
      31: invokevirtual #99                 // Method org/eclipse/ui/actions/RetargetAction.setToolTipText:(Ljava/lang/String;)V
      34: aload_1
      35: invokeinterface #107,  1          // InterfaceMethod org/eclipse/ui/IWorkbenchWindow.getPartService:()Lorg/eclipse/ui/IPartService;
      40: aload_2
      41: invokeinterface #103,  2          // InterfaceMethod org/eclipse/ui/IPartService.addPartListener:(Lorg/eclipse/ui/IPartListener;)V
      46: aload_2
      47: aload_0
      48: invokevirtual #95                 // Method getCommandId:()Ljava/lang/String;
      51: invokevirtual #98                 // Method org/eclipse/ui/actions/RetargetAction.setActionDefinitionId:(Ljava/lang/String;)V
      54: aload_2
      55: iconst_0
      56: invokevirtual #97                 // Method org/eclipse/ui/actions/RetargetAction.enableAccelerator:(Z)V
      59: aload_1
      60: invokeinterface #108,  1          // InterfaceMethod org/eclipse/ui/IWorkbenchWindow.getWorkbench:()Lorg/eclipse/ui/IWorkbench;
      65: invokeinterface #106,  1          // InterfaceMethod org/eclipse/ui/IWorkbench.getHelpSystem:()Lorg/eclipse/ui/help/IWorkbenchHelpSystem;
      70: aload_2
      71: ldc           #3                  // String org.eclipse.ui.delete_retarget_action_context
      73: invokeinterface #109,  3          // InterfaceMethod org/eclipse/ui/help/IWorkbenchHelpSystem.setHelp:(Lorg/eclipse/jface/action/IAction;Ljava/lang/String;)V
      78: aload_1
      79: invokeinterface #108,  1          // InterfaceMethod org/eclipse/ui/IWorkbenchWindow.getWorkbench:()Lorg/eclipse/ui/IWorkbench;
      84: invokeinterface #105,  1          // InterfaceMethod org/eclipse/ui/IWorkbench.getSharedImages:()Lorg/eclipse/ui/ISharedImages;
      89: astore_3
      90: aload_2
      91: aload_3
      92: ldc           #1                  // String IMG_TOOL_DELETE
      94: invokeinterface #104,  2          // InterfaceMethod org/eclipse/ui/ISharedImages.getImageDescriptor:(Ljava/lang/String;)Lorg/eclipse/jface/resource/ImageDescriptor;
      99: invokevirtual #101                // Method org/eclipse/ui/actions/RetargetAction.setImageDescriptor:(Lorg/eclipse/jface/resource/ImageDescriptor;)V
     102: aload_2
     103: aload_3
     104: ldc           #2                  // String IMG_TOOL_DELETE_DISABLED
     106: invokeinterface #104,  2          // InterfaceMethod org/eclipse/ui/ISharedImages.getImageDescriptor:(Ljava/lang/String;)Lorg/eclipse/jface/resource/ImageDescriptor;
     111: invokevirtual #100                // Method org/eclipse/ui/actions/RetargetAction.setDisabledImageDescriptor:(Lorg/eclipse/jface/resource/ImageDescriptor;)V
     114: aload_2
     115: areturn
}
