Compiled from "ContributedAction.java"
class org.eclipse.ui.actions.ContributedAction$1 implements org.eclipse.ui.IPartListener {
  final org.eclipse.ui.actions.ContributedAction this$0;

  private final org.eclipse.ui.IWorkbenchPart val$currentPart;

  org.eclipse.ui.actions.ContributedAction$1(org.eclipse.ui.actions.ContributedAction, org.eclipse.ui.IWorkbenchPart);
    Code:
       0: aload_0
       1: aload_1
       2: putfield      #35                 // Field this$0:Lorg/eclipse/ui/actions/ContributedAction;
       5: aload_0
       6: aload_2
       7: putfield      #34                 // Field val$currentPart:Lorg/eclipse/ui/IWorkbenchPart;
      10: aload_0
      11: invokespecial #36                 // Method java/lang/Object."<init>":()V
      14: return

  public void partActivated(org.eclipse.ui.IWorkbenchPart);
    Code:
       0: return

  public void partBroughtToTop(org.eclipse.ui.IWorkbenchPart);
    Code:
       0: return

  public void partClosed(org.eclipse.ui.IWorkbenchPart);
    Code:
       0: aload_1
       1: aload_0
       2: getfield      #34                 // Field val$currentPart:Lorg/eclipse/ui/IWorkbenchPart;
       5: if_acmpne     15
       8: aload_0
       9: getfield      #35                 // Field this$0:Lorg/eclipse/ui/actions/ContributedAction;
      12: invokevirtual #37                 // Method org/eclipse/ui/actions/ContributedAction.disposeAction:()V
      15: return

  public void partDeactivated(org.eclipse.ui.IWorkbenchPart);
    Code:
       0: return

  public void partOpened(org.eclipse.ui.IWorkbenchPart);
    Code:
       0: return
}
