Compiled from "ExportResourcesAction.java"
public class org.eclipse.ui.actions.ExportResourcesAction extends org.eclipse.ui.actions.BaseSelectionListenerAction implements org.eclipse.ui.actions.ActionFactory$IWorkbenchAction {
  private org.eclipse.ui.actions.ActionFactory$IWorkbenchAction action;

  private org.eclipse.ui.IWorkbenchWindow workbenchWindow;

  public org.eclipse.ui.actions.ExportResourcesAction(org.eclipse.ui.IWorkbenchWindow);
    Code:
       0: aload_0
       1: aload_1
       2: getstatic     #104                // Field org/eclipse/ui/internal/WorkbenchMessages.ExportResourcesAction_text:Ljava/lang/String;
       5: invokespecial #115                // Method "<init>":(Lorg/eclipse/ui/IWorkbenchWindow;Ljava/lang/String;)V
       8: return

  public org.eclipse.ui.actions.ExportResourcesAction(org.eclipse.ui.IWorkbenchWindow, java.lang.String);
    Code:
       0: aload_0
       1: aload_2
       2: invokespecial #107                // Method org/eclipse/ui/actions/BaseSelectionListenerAction."<init>":(Ljava/lang/String;)V
       5: aload_1
       6: ifnonnull     17
       9: new           #43                 // class java/lang/IllegalArgumentException
      12: dup
      13: invokespecial #105                // Method java/lang/IllegalArgumentException."<init>":()V
      16: athrow
      17: aload_0
      18: aload_1
      19: putfield      #102                // Field workbenchWindow:Lorg/eclipse/ui/IWorkbenchWindow;
      22: aload_0
      23: getstatic     #101                // Field org/eclipse/ui/actions/ActionFactory.EXPORT:Lorg/eclipse/ui/actions/ActionFactory;
      26: aload_1
      27: invokevirtual #106                // Method org/eclipse/ui/actions/ActionFactory.create:(Lorg/eclipse/ui/IWorkbenchWindow;)Lorg/eclipse/ui/actions/ActionFactory$IWorkbenchAction;
      30: putfield      #103                // Field action:Lorg/eclipse/ui/actions/ActionFactory$IWorkbenchAction;
      33: aload_0
      34: aload_0
      35: getfield      #103                // Field action:Lorg/eclipse/ui/actions/ActionFactory$IWorkbenchAction;
      38: invokeinterface #123,  1          // InterfaceMethod org/eclipse/ui/actions/ActionFactory$IWorkbenchAction.getText:()Ljava/lang/String;
      43: invokevirtual #110                // Method setText:(Ljava/lang/String;)V
      46: aload_0
      47: aload_0
      48: getfield      #103                // Field action:Lorg/eclipse/ui/actions/ActionFactory$IWorkbenchAction;
      51: invokeinterface #124,  1          // InterfaceMethod org/eclipse/ui/actions/ActionFactory$IWorkbenchAction.getToolTipText:()Ljava/lang/String;
      56: invokevirtual #111                // Method setToolTipText:(Ljava/lang/String;)V
      59: aload_0
      60: aload_0
      61: getfield      #103                // Field action:Lorg/eclipse/ui/actions/ActionFactory$IWorkbenchAction;
      64: invokeinterface #122,  1          // InterfaceMethod org/eclipse/ui/actions/ActionFactory$IWorkbenchAction.getId:()Ljava/lang/String;
      69: invokevirtual #109                // Method setId:(Ljava/lang/String;)V
      72: aload_0
      73: aload_0
      74: getfield      #103                // Field action:Lorg/eclipse/ui/actions/ActionFactory$IWorkbenchAction;
      77: invokeinterface #121,  1          // InterfaceMethod org/eclipse/ui/actions/ActionFactory$IWorkbenchAction.getActionDefinitionId:()Ljava/lang/String;
      82: invokevirtual #108                // Method setActionDefinitionId:(Ljava/lang/String;)V
      85: aload_1
      86: invokeinterface #118,  1          // InterfaceMethod org/eclipse/ui/IWorkbenchWindow.getWorkbench:()Lorg/eclipse/ui/IWorkbench;
      91: invokeinterface #117,  1          // InterfaceMethod org/eclipse/ui/IWorkbench.getHelpSystem:()Lorg/eclipse/ui/help/IWorkbenchHelpSystem;
      96: aload_0
      97: ldc           #1                  // String org.eclipse.ui.export_action_context
      99: invokeinterface #126,  3          // InterfaceMethod org/eclipse/ui/help/IWorkbenchHelpSystem.setHelp:(Lorg/eclipse/jface/action/IAction;Ljava/lang/String;)V
     104: aload_0
     105: aload_0
     106: getfield      #103                // Field action:Lorg/eclipse/ui/actions/ActionFactory$IWorkbenchAction;
     109: invokeinterface #125,  1          // InterfaceMethod org/eclipse/ui/actions/ActionFactory$IWorkbenchAction.getImageDescriptor:()Lorg/eclipse/jface/resource/ImageDescriptor;
     114: invokevirtual #112                // Method setImageDescriptor:(Lorg/eclipse/jface/resource/ImageDescriptor;)V
     117: return

  public org.eclipse.ui.actions.ExportResourcesAction(org.eclipse.ui.IWorkbench);
    Code:
       0: aload_0
       1: aload_1
       2: invokeinterface #116,  1          // InterfaceMethod org/eclipse/ui/IWorkbench.getActiveWorkbenchWindow:()Lorg/eclipse/ui/IWorkbenchWindow;
       7: invokespecial #114                // Method "<init>":(Lorg/eclipse/ui/IWorkbenchWindow;)V
      10: return

  public org.eclipse.ui.actions.ExportResourcesAction(org.eclipse.ui.IWorkbench, java.lang.String);
    Code:
       0: aload_0
       1: aload_1
       2: invokeinterface #116,  1          // InterfaceMethod org/eclipse/ui/IWorkbench.getActiveWorkbenchWindow:()Lorg/eclipse/ui/IWorkbenchWindow;
       7: aload_2
       8: invokespecial #115                // Method "<init>":(Lorg/eclipse/ui/IWorkbenchWindow;Ljava/lang/String;)V
      11: return

  public void run();
    Code:
       0: aload_0
       1: getfield      #102                // Field workbenchWindow:Lorg/eclipse/ui/IWorkbenchWindow;
       4: ifnonnull     8
       7: return
       8: aload_0
       9: getfield      #103                // Field action:Lorg/eclipse/ui/actions/ActionFactory$IWorkbenchAction;
      12: invokeinterface #120,  1          // InterfaceMethod org/eclipse/ui/actions/ActionFactory$IWorkbenchAction.run:()V
      17: return

  public void setSelection(org.eclipse.jface.viewers.IStructuredSelection);
    Code:
       0: aload_0
       1: aload_1
       2: invokevirtual #113                // Method selectionChanged:(Lorg/eclipse/jface/viewers/IStructuredSelection;)V
       5: return

  public void dispose();
    Code:
       0: aload_0
       1: aconst_null
       2: putfield      #102                // Field workbenchWindow:Lorg/eclipse/ui/IWorkbenchWindow;
       5: aload_0
       6: getfield      #103                // Field action:Lorg/eclipse/ui/actions/ActionFactory$IWorkbenchAction;
       9: ifnull        21
      12: aload_0
      13: getfield      #103                // Field action:Lorg/eclipse/ui/actions/ActionFactory$IWorkbenchAction;
      16: invokeinterface #119,  1          // InterfaceMethod org/eclipse/ui/actions/ActionFactory$IWorkbenchAction.dispose:()V
      21: aload_0
      22: aconst_null
      23: putfield      #103                // Field action:Lorg/eclipse/ui/actions/ActionFactory$IWorkbenchAction;
      26: return
}
