Compiled from "TokenBufferSerializer.java"
public class io.dekorate.deps.jackson.databind.ser.std.TokenBufferSerializer extends io.dekorate.deps.jackson.databind.ser.std.StdSerializer<io.dekorate.deps.jackson.databind.util.TokenBuffer> {
  public io.dekorate.deps.jackson.databind.ser.std.TokenBufferSerializer();
    Code:
       0: aload_0
       1: ldc           #11                 // class io/dekorate/deps/jackson/databind/util/TokenBuffer
       3: invokespecial #14                 // Method io/dekorate/deps/jackson/databind/ser/std/StdSerializer."<init>":(Ljava/lang/Class;)V
       6: return

  public void serialize(io.dekorate.deps.jackson.databind.util.TokenBuffer, io.dekorate.deps.jackson.core.JsonGenerator, io.dekorate.deps.jackson.databind.SerializerProvider) throws java.io.IOException;
    Code:
       0: aload_1
       1: aload_2
       2: invokevirtual #23                 // Method io/dekorate/deps/jackson/databind/util/TokenBuffer.serialize:(Lio/dekorate/deps/jackson/core/JsonGenerator;)V
       5: return

  public final void serializeWithType(io.dekorate.deps.jackson.databind.util.TokenBuffer, io.dekorate.deps.jackson.core.JsonGenerator, io.dekorate.deps.jackson.databind.SerializerProvider, io.dekorate.deps.jackson.databind.jsontype.TypeSerializer) throws java.io.IOException;
    Code:
       0: aload         4
       2: aload_2
       3: aload         4
       5: aload_1
       6: getstatic     #37                 // Field io/dekorate/deps/jackson/core/JsonToken.VALUE_EMBEDDED_OBJECT:Lio/dekorate/deps/jackson/core/JsonToken;
       9: invokevirtual #43                 // Method io/dekorate/deps/jackson/databind/jsontype/TypeSerializer.typeId:(Ljava/lang/Object;Lio/dekorate/deps/jackson/core/JsonToken;)Lio/dekorate/deps/jackson/core/type/WritableTypeId;
      12: invokevirtual #47                 // Method io/dekorate/deps/jackson/databind/jsontype/TypeSerializer.writeTypePrefix:(Lio/dekorate/deps/jackson/core/JsonGenerator;Lio/dekorate/deps/jackson/core/type/WritableTypeId;)Lio/dekorate/deps/jackson/core/type/WritableTypeId;
      15: astore        5
      17: aload_0
      18: aload_1
      19: aload_2
      20: aload_3
      21: invokevirtual #49                 // Method serialize:(Lio/dekorate/deps/jackson/databind/util/TokenBuffer;Lio/dekorate/deps/jackson/core/JsonGenerator;Lio/dekorate/deps/jackson/databind/SerializerProvider;)V
      24: aload         4
      26: aload_2
      27: aload         5
      29: invokevirtual #52                 // Method io/dekorate/deps/jackson/databind/jsontype/TypeSerializer.writeTypeSuffix:(Lio/dekorate/deps/jackson/core/JsonGenerator;Lio/dekorate/deps/jackson/core/type/WritableTypeId;)Lio/dekorate/deps/jackson/core/type/WritableTypeId;
      32: pop
      33: return

  public io.dekorate.deps.jackson.databind.JsonNode getSchema(io.dekorate.deps.jackson.databind.SerializerProvider, java.lang.reflect.Type);
    Code:
       0: aload_0
       1: ldc           #61                 // String any
       3: iconst_1
       4: invokevirtual #65                 // Method createSchemaNode:(Ljava/lang/String;Z)Lio/dekorate/deps/jackson/databind/node/ObjectNode;
       7: areturn

  public void acceptJsonFormatVisitor(io.dekorate.deps.jackson.databind.jsonFormatVisitors.JsonFormatVisitorWrapper, io.dekorate.deps.jackson.databind.JavaType) throws io.dekorate.deps.jackson.databind.JsonMappingException;
    Code:
       0: aload_1
       1: aload_2
       2: invokeinterface #77,  2           // InterfaceMethod io/dekorate/deps/jackson/databind/jsonFormatVisitors/JsonFormatVisitorWrapper.expectAnyFormat:(Lio/dekorate/deps/jackson/databind/JavaType;)Lio/dekorate/deps/jackson/databind/jsonFormatVisitors/JsonAnyFormatVisitor;
       7: pop
       8: return

  public void serialize(java.lang.Object, io.dekorate.deps.jackson.core.JsonGenerator, io.dekorate.deps.jackson.databind.SerializerProvider) throws java.io.IOException;
    Code:
       0: aload_0
       1: aload_1
       2: checkcast     #11                 // class io/dekorate/deps/jackson/databind/util/TokenBuffer
       5: aload_2
       6: aload_3
       7: invokevirtual #49                 // Method serialize:(Lio/dekorate/deps/jackson/databind/util/TokenBuffer;Lio/dekorate/deps/jackson/core/JsonGenerator;Lio/dekorate/deps/jackson/databind/SerializerProvider;)V
      10: return

  public void serializeWithType(java.lang.Object, io.dekorate.deps.jackson.core.JsonGenerator, io.dekorate.deps.jackson.databind.SerializerProvider, io.dekorate.deps.jackson.databind.jsontype.TypeSerializer) throws java.io.IOException;
    Code:
       0: aload_0
       1: aload_1
       2: checkcast     #11                 // class io/dekorate/deps/jackson/databind/util/TokenBuffer
       5: aload_2
       6: aload_3
       7: aload         4
       9: invokevirtual #84                 // Method serializeWithType:(Lio/dekorate/deps/jackson/databind/util/TokenBuffer;Lio/dekorate/deps/jackson/core/JsonGenerator;Lio/dekorate/deps/jackson/databind/SerializerProvider;Lio/dekorate/deps/jackson/databind/jsontype/TypeSerializer;)V
      12: return
}
