Compiled from "ConfigDocsModule.scala"
public class zio.config.ConfigDocsModule$ConfigDocs$Sequence$ extends scala.runtime.AbstractFunction2<zio.config.ConfigDocsModule$ConfigDocs, scala.collection.immutable.List<zio.config.ConfigDocsModule$ConfigDocs>, zio.config.ConfigDocsModule$ConfigDocs$Sequence> implements scala.Serializable {
  public final zio.config.ConfigDocsModule$ConfigDocs$ $outer;

  public final java.lang.String toString();
    Code:
       0: ldc           #14                 // String Sequence
       2: areturn

  public zio.config.ConfigDocsModule$ConfigDocs$Sequence apply(zio.config.ConfigDocsModule$ConfigDocs, scala.collection.immutable.List<zio.config.ConfigDocsModule$ConfigDocs>);
    Code:
       0: new           #20                 // class zio/config/ConfigDocsModule$ConfigDocs$Sequence
       3: dup
       4: aload_0
       5: invokevirtual #24                 // Method zio$config$ConfigDocsModule$ConfigDocs$Sequence$$$outer:()Lzio/config/ConfigDocsModule$ConfigDocs$;
       8: aload_1
       9: aload_2
      10: invokespecial #28                 // Method zio/config/ConfigDocsModule$ConfigDocs$Sequence."<init>":(Lzio/config/ConfigDocsModule$ConfigDocs$;Lzio/config/ConfigDocsModule$ConfigDocs;Lscala/collection/immutable/List;)V
      13: areturn

  public scala.Option<scala.Tuple2<zio.config.ConfigDocsModule$ConfigDocs, scala.collection.immutable.List<zio.config.ConfigDocsModule$ConfigDocs>>> unapply(zio.config.ConfigDocsModule$ConfigDocs$Sequence);
    Code:
       0: aload_1
       1: ifnonnull     10
       4: getstatic     #40                 // Field scala/None$.MODULE$:Lscala/None$;
       7: goto          32
      10: new           #42                 // class scala/Some
      13: dup
      14: new           #44                 // class scala/Tuple2
      17: dup
      18: aload_1
      19: invokevirtual #47                 // Method zio/config/ConfigDocsModule$ConfigDocs$Sequence.schemaDocs:()Lzio/config/ConfigDocsModule$ConfigDocs;
      22: aload_1
      23: invokevirtual #50                 // Method zio/config/ConfigDocsModule$ConfigDocs$Sequence.valueDocs:()Lscala/collection/immutable/List;
      26: invokespecial #53                 // Method scala/Tuple2."<init>":(Ljava/lang/Object;Ljava/lang/Object;)V
      29: invokespecial #56                 // Method scala/Some."<init>":(Ljava/lang/Object;)V
      32: areturn

  public scala.collection.immutable.List<zio.config.ConfigDocsModule$ConfigDocs> $lessinit$greater$default$2();
    Code:
       0: getstatic     #66                 // Field scala/collection/immutable/List$.MODULE$:Lscala/collection/immutable/List$;
       3: invokevirtual #69                 // Method scala/collection/immutable/List$.empty:()Lscala/collection/immutable/List;
       6: areturn

  public scala.collection.immutable.List<zio.config.ConfigDocsModule$ConfigDocs> apply$default$2();
    Code:
       0: getstatic     #66                 // Field scala/collection/immutable/List$.MODULE$:Lscala/collection/immutable/List$;
       3: invokevirtual #69                 // Method scala/collection/immutable/List$.empty:()Lscala/collection/immutable/List;
       6: areturn

  public zio.config.ConfigDocsModule$ConfigDocs$ zio$config$ConfigDocsModule$ConfigDocs$Sequence$$$outer();
    Code:
       0: aload_0
       1: getfield      #72                 // Field $outer:Lzio/config/ConfigDocsModule$ConfigDocs$;
       4: areturn

  public java.lang.Object apply(java.lang.Object, java.lang.Object);
    Code:
       0: aload_0
       1: aload_1
       2: checkcast     #75                 // class zio/config/ConfigDocsModule$ConfigDocs
       5: aload_2
       6: checkcast     #77                 // class scala/collection/immutable/List
       9: invokevirtual #79                 // Method apply:(Lzio/config/ConfigDocsModule$ConfigDocs;Lscala/collection/immutable/List;)Lzio/config/ConfigDocsModule$ConfigDocs$Sequence;
      12: areturn

  public zio.config.ConfigDocsModule$ConfigDocs$Sequence$(zio.config.ConfigDocsModule$ConfigDocs$);
    Code:
       0: aload_1
       1: ifnonnull     6
       4: aconst_null
       5: athrow
       6: aload_0
       7: aload_1
       8: putfield      #72                 // Field $outer:Lzio/config/ConfigDocsModule$ConfigDocs$;
      11: aload_0
      12: invokespecial #86                 // Method scala/runtime/AbstractFunction2."<init>":()V
      15: return
}
