Compiled from "ConfigSourceModule.scala"
public class zio.config.ConfigSourceModule$ConfigSourceName$ extends scala.runtime.AbstractFunction1<java.lang.String, zio.config.ConfigSourceModule$ConfigSourceName> implements scala.Serializable {
  public final zio.config.ConfigSourceModule $outer;

  public final java.lang.String toString();
    Code:
       0: ldc           #14                 // String ConfigSourceName
       2: areturn

  public zio.config.ConfigSourceModule$ConfigSourceName apply(java.lang.String);
    Code:
       0: new           #20                 // class zio/config/ConfigSourceModule$ConfigSourceName
       3: dup
       4: aload_0
       5: invokevirtual #24                 // Method zio$config$ConfigSourceModule$ConfigSourceName$$$outer:()Lzio/config/ConfigSourceModule;
       8: aload_1
       9: invokespecial #28                 // Method zio/config/ConfigSourceModule$ConfigSourceName."<init>":(Lzio/config/ConfigSourceModule;Ljava/lang/String;)V
      12: areturn

  public scala.Option<java.lang.String> unapply(zio.config.ConfigSourceModule$ConfigSourceName);
    Code:
       0: aload_1
       1: ifnonnull     10
       4: getstatic     #38                 // Field scala/None$.MODULE$:Lscala/None$;
       7: goto          21
      10: new           #40                 // class scala/Some
      13: dup
      14: aload_1
      15: invokevirtual #42                 // Method zio/config/ConfigSourceModule$ConfigSourceName.name:()Ljava/lang/String;
      18: invokespecial #45                 // Method scala/Some."<init>":(Ljava/lang/Object;)V
      21: areturn

  public zio.config.ConfigSourceModule zio$config$ConfigSourceModule$ConfigSourceName$$$outer();
    Code:
       0: aload_0
       1: getfield      #51                 // Field $outer:Lzio/config/ConfigSourceModule;
       4: areturn

  public java.lang.Object apply(java.lang.Object);
    Code:
       0: aload_0
       1: aload_1
       2: checkcast     #54                 // class java/lang/String
       5: invokevirtual #56                 // Method apply:(Ljava/lang/String;)Lzio/config/ConfigSourceModule$ConfigSourceName;
       8: areturn

  public zio.config.ConfigSourceModule$ConfigSourceName$(zio.config.ConfigSourceModule);
    Code:
       0: aload_1
       1: ifnonnull     6
       4: aconst_null
       5: athrow
       6: aload_0
       7: aload_1
       8: putfield      #51                 // Field $outer:Lzio/config/ConfigSourceModule;
      11: aload_0
      12: invokespecial #62                 // Method scala/runtime/AbstractFunction1."<init>":()V
      15: return
}
