Compiled from "KeyConversionFunctions.scala"
public final class zio.config.KeyConversionFunctions$$anonfun$camelToDelimiter$1 extends scala.runtime.AbstractFunction1<java.lang.Object, java.lang.Object> implements scala.Serializable {
  public static final long serialVersionUID;

  public final int apply(char);
    Code:
       0: iload_1
       1: ireturn

  public final java.lang.Object apply(java.lang.Object);
    Code:
       0: aload_0
       1: aload_1
       2: invokestatic  #30                 // Method scala/runtime/BoxesRunTime.unboxToChar:(Ljava/lang/Object;)C
       5: invokevirtual #32                 // Method apply:(C)I
       8: invokestatic  #36                 // Method scala/runtime/BoxesRunTime.boxToInteger:(I)Ljava/lang/Integer;
      11: areturn

  public zio.config.KeyConversionFunctions$$anonfun$camelToDelimiter$1(zio.config.KeyConversionFunctions);
    Code:
       0: aload_0
       1: invokespecial #43                 // Method scala/runtime/AbstractFunction1."<init>":()V
       4: return
}
