Compiled from "ProductBuilder.scala"
public final class zio.config.ProductBuilder$ProductBuilder$ProductBuilder$ProductBuilder$ProductBuilder$ProductBuilder$ProductBuilder$ProductBuilder$ProductBuilder$ProductBuilder$$anonfun$apply$27 extends scala.runtime.AbstractFunction1<N, scala.Option<scala.Tuple2<scala.Tuple2<scala.Tuple2<scala.Tuple2<scala.Tuple2<scala.Tuple2<scala.Tuple2<scala.Tuple2<scala.Tuple2<scala.Tuple2<A, B>, C>, D>, E>, H>, I>, J>, K>, L>, M>>> implements scala.Serializable {
  public static final long serialVersionUID;

  private final scala.Function1 gg$9;

  public final scala.Option<scala.Tuple2<scala.Tuple2<scala.Tuple2<scala.Tuple2<scala.Tuple2<scala.Tuple2<scala.Tuple2<scala.Tuple2<scala.Tuple2<scala.Tuple2<A, B>, C>, D>, E>, H>, I>, J>, K>, L>, M>> apply(N);
    Code:
       0: aload_0
       1: getfield      #22                 // Field gg$9:Lscala/Function1;
       4: aload_1
       5: invokeinterface #27,  2           // InterfaceMethod scala/Function1.apply:(Ljava/lang/Object;)Ljava/lang/Object;
      10: checkcast     #29                 // class scala/Option
      13: new           #31                 // class zio/config/ProductBuilder$ProductBuilder$ProductBuilder$ProductBuilder$ProductBuilder$ProductBuilder$ProductBuilder$ProductBuilder$ProductBuilder$ProductBuilder$$anonfun$apply$27$$anonfun$apply$28
      16: dup
      17: aload_0
      18: invokespecial #35                 // Method zio/config/ProductBuilder$ProductBuilder$ProductBuilder$ProductBuilder$ProductBuilder$ProductBuilder$ProductBuilder$ProductBuilder$ProductBuilder$ProductBuilder$$anonfun$apply$27$$anonfun$apply$28."<init>":(Lzio/config/ProductBuilder$ProductBuilder$ProductBuilder$ProductBuilder$ProductBuilder$ProductBuilder$ProductBuilder$ProductBuilder$ProductBuilder$ProductBuilder$$anonfun$apply$27;)V
      21: invokevirtual #39                 // Method scala/Option.map:(Lscala/Function1;)Lscala/Option;
      24: areturn

  public final java.lang.Object apply(java.lang.Object);
    Code:
       0: aload_0
       1: aload_1
       2: invokevirtual #45                 // Method apply:(Ljava/lang/Object;)Lscala/Option;
       5: areturn

  public zio.config.ProductBuilder$ProductBuilder$ProductBuilder$ProductBuilder$ProductBuilder$ProductBuilder$ProductBuilder$ProductBuilder$ProductBuilder$ProductBuilder$$anonfun$apply$27(zio.config.ProductBuilder<F, A, B>.ProductBuilder<C>.ProductBuilder<D>.ProductBuilder<E>.ProductBuilder<H>.ProductBuilder<I>.ProductBuilder<J>.ProductBuilder<K>.ProductBuilder<L>.ProductBuilder<M>);
    Code:
       0: aload_0
       1: aload_2
       2: putfield      #22                 // Field gg$9:Lscala/Function1;
       5: aload_0
       6: invokespecial #50                 // Method scala/runtime/AbstractFunction1."<init>":()V
       9: return
}
