Compiled from "PropertyType.scala"
public final class zio.config.PropertyType$ZioDurationType$$anonfun$read$21 extends scala.runtime.AbstractFunction1<scala.concurrent.duration.Duration, java.time.Duration> implements scala.Serializable {
  public static final long serialVersionUID;

  public final java.time.Duration apply(scala.concurrent.duration.Duration);
    Code:
       0: getstatic     #25                 // Field zio/duration/package$Duration$.MODULE$:Lzio/duration/package$Duration$;
       3: aload_1
       4: invokevirtual #28                 // Method zio/duration/package$Duration$.fromScala:(Lscala/concurrent/duration/Duration;)Ljava/time/Duration;
       7: areturn

  public final java.lang.Object apply(java.lang.Object);
    Code:
       0: aload_0
       1: aload_1
       2: checkcast     #35                 // class scala/concurrent/duration/Duration
       5: invokevirtual #37                 // Method apply:(Lscala/concurrent/duration/Duration;)Ljava/time/Duration;
       8: areturn

  public zio.config.PropertyType$ZioDurationType$$anonfun$read$21();
    Code:
       0: aload_0
       1: invokespecial #43                 // Method scala/runtime/AbstractFunction1."<init>":()V
       4: return
}
