Compiled from "VersionSpecificSupport.scala"
public class zio.config.VersionSpecificSupport$RightBiasedEither<L, R> {
  private final scala.util.Either<L, R> e;

  public <R2> scala.util.Either<L, R2> map(scala.Function1<R, R2>);
    Code:
       0: aload_0
       1: getfield      #13                 // Field e:Lscala/util/Either;
       4: astore_2
       5: aload_2
       6: instanceof    #15                 // class scala/util/Left
       9: ifeq          39
      12: aload_2
      13: checkcast     #15                 // class scala/util/Left
      16: astore_3
      17: aload_3
      18: invokevirtual #19                 // Method scala/util/Left.a:()Ljava/lang/Object;
      21: astore        4
      23: getstatic     #25                 // Field scala/package$.MODULE$:Lscala/package$;
      26: invokevirtual #29                 // Method scala/package$.Left:()Lscala/util/Left$;
      29: aload         4
      31: invokevirtual #35                 // Method scala/util/Left$.apply:(Ljava/lang/Object;)Lscala/util/Left;
      34: astore        5
      36: goto          78
      39: aload_2
      40: instanceof    #37                 // class scala/util/Right
      43: ifeq          81
      46: aload_2
      47: checkcast     #37                 // class scala/util/Right
      50: astore        6
      52: aload         6
      54: invokevirtual #40                 // Method scala/util/Right.b:()Ljava/lang/Object;
      57: astore        7
      59: getstatic     #25                 // Field scala/package$.MODULE$:Lscala/package$;
      62: invokevirtual #44                 // Method scala/package$.Right:()Lscala/util/Right$;
      65: aload_1
      66: aload         7
      68: invokeinterface #49,  2           // InterfaceMethod scala/Function1.apply:(Ljava/lang/Object;)Ljava/lang/Object;
      73: invokevirtual #54                 // Method scala/util/Right$.apply:(Ljava/lang/Object;)Lscala/util/Right;
      76: astore        5
      78: aload         5
      80: areturn
      81: new           #56                 // class scala/MatchError
      84: dup
      85: aload_2
      86: invokespecial #60                 // Method scala/MatchError."<init>":(Ljava/lang/Object;)V
      89: athrow

  public zio.config.VersionSpecificSupport$RightBiasedEither(scala.util.Either<L, R>);
    Code:
       0: aload_0
       1: aload_1
       2: putfield      #13                 // Field e:Lscala/util/Either;
       5: aload_0
       6: invokespecial #71                 // Method java/lang/Object."<init>":()V
       9: return
}
