Compiled from "FailableCache.java"
public abstract class com.google.inject.internal.FailableCache<K, V> {
  private final java.util.Map<K, java.lang.Object> delegate;

  public com.google.inject.internal.FailableCache();
    Code:
       0: aload_0
       1: invokespecial #15                 // Method java/lang/Object."<init>":()V
       4: aload_0
       5: new           #17                 // class com/google/common/collect/MapMaker
       8: dup
       9: invokespecial #18                 // Method com/google/common/collect/MapMaker."<init>":()V
      12: new           #8                  // class com/google/inject/internal/FailableCache$1
      15: dup
      16: aload_0
      17: invokespecial #21                 // Method com/google/inject/internal/FailableCache$1."<init>":(Lcom/google/inject/internal/FailableCache;)V
      20: invokevirtual #25                 // Method com/google/common/collect/MapMaker.makeComputingMap:(Lcom/google/common/base/Function;)Ljava/util/concurrent/ConcurrentMap;
      23: putfield      #27                 // Field delegate:Ljava/util/Map;
      26: return

  protected abstract V create(K, com.google.inject.internal.Errors) throws com.google.inject.internal.ErrorsException;

  public V get(K, com.google.inject.internal.Errors) throws com.google.inject.internal.ErrorsException;
    Code:
       0: aload_0
       1: getfield      #27                 // Field delegate:Ljava/util/Map;
       4: aload_1
       5: invokeinterface #40,  2           // InterfaceMethod java/util/Map.get:(Ljava/lang/Object;)Ljava/lang/Object;
      10: astore_3
      11: aload_3
      12: instanceof    #42                 // class com/google/inject/internal/Errors
      15: ifeq          32
      18: aload_2
      19: aload_3
      20: checkcast     #42                 // class com/google/inject/internal/Errors
      23: invokevirtual #46                 // Method com/google/inject/internal/Errors.merge:(Lcom/google/inject/internal/Errors;)Lcom/google/inject/internal/Errors;
      26: pop
      27: aload_2
      28: invokevirtual #50                 // Method com/google/inject/internal/Errors.toException:()Lcom/google/inject/internal/ErrorsException;
      31: athrow
      32: aload_3
      33: astore        4
      35: aload         4
      37: areturn

  boolean remove(K);
    Code:
       0: aload_0
       1: getfield      #27                 // Field delegate:Ljava/util/Map;
       4: aload_1
       5: invokeinterface #62,  2           // InterfaceMethod java/util/Map.remove:(Ljava/lang/Object;)Ljava/lang/Object;
      10: ifnull        17
      13: iconst_1
      14: goto          18
      17: iconst_0
      18: ireturn
}
