Compiled from "InjectorImpl.java"
class com.google.inject.internal.InjectorImpl$3$1 implements com.google.inject.internal.ContextualCallable<T> {
  final com.google.inject.internal.Errors val$errors;

  final com.google.inject.internal.InjectorImpl$3 this$1;

  com.google.inject.internal.InjectorImpl$3$1(com.google.inject.internal.InjectorImpl$3, com.google.inject.internal.Errors);
    Code:
       0: aload_0
       1: aload_1
       2: putfield      #21                 // Field this$1:Lcom/google/inject/internal/InjectorImpl$3;
       5: aload_0
       6: aload_2
       7: putfield      #23                 // Field val$errors:Lcom/google/inject/internal/Errors;
      10: aload_0
      11: invokespecial #26                 // Method java/lang/Object."<init>":()V
      14: return

  public T call(com.google.inject.internal.InternalContext) throws com.google.inject.internal.ErrorsException;
    Code:
       0: aload_1
       1: aload_0
       2: getfield      #21                 // Field this$1:Lcom/google/inject/internal/InjectorImpl$3;
       5: getfield      #36                 // Field com/google/inject/internal/InjectorImpl$3.val$dependency:Lcom/google/inject/spi/Dependency;
       8: aload_0
       9: getfield      #21                 // Field this$1:Lcom/google/inject/internal/InjectorImpl$3;
      12: getfield      #40                 // Field com/google/inject/internal/InjectorImpl$3.val$binding:Lcom/google/inject/internal/BindingImpl;
      15: invokevirtual #45                 // Method com/google/inject/internal/BindingImpl.getSource:()Ljava/lang/Object;
      18: invokevirtual #51                 // Method com/google/inject/internal/InternalContext.pushDependency:(Lcom/google/inject/spi/Dependency;Ljava/lang/Object;)Lcom/google/inject/spi/Dependency;
      21: astore_2
      22: aload_0
      23: getfield      #21                 // Field this$1:Lcom/google/inject/internal/InjectorImpl$3;
      26: getfield      #40                 // Field com/google/inject/internal/InjectorImpl$3.val$binding:Lcom/google/inject/internal/BindingImpl;
      29: invokevirtual #55                 // Method com/google/inject/internal/BindingImpl.getInternalFactory:()Lcom/google/inject/internal/InternalFactory;
      32: aload_0
      33: getfield      #23                 // Field val$errors:Lcom/google/inject/internal/Errors;
      36: aload_1
      37: aload_0
      38: getfield      #21                 // Field this$1:Lcom/google/inject/internal/InjectorImpl$3;
      41: getfield      #36                 // Field com/google/inject/internal/InjectorImpl$3.val$dependency:Lcom/google/inject/spi/Dependency;
      44: iconst_0
      45: invokeinterface #60,  5           // InterfaceMethod com/google/inject/internal/InternalFactory.get:(Lcom/google/inject/internal/Errors;Lcom/google/inject/internal/InternalContext;Lcom/google/inject/spi/Dependency;Z)Ljava/lang/Object;
      50: astore_3
      51: aload_1
      52: aload_2
      53: invokevirtual #64                 // Method com/google/inject/internal/InternalContext.popStateAndSetDependency:(Lcom/google/inject/spi/Dependency;)V
      56: aload_3
      57: areturn
      58: astore        4
      60: aload_1
      61: aload_2
      62: invokevirtual #64                 // Method com/google/inject/internal/InternalContext.popStateAndSetDependency:(Lcom/google/inject/spi/Dependency;)V
      65: aload         4
      67: athrow
    Exception table:
       from    to  target type
          22    51    58   any
          58    60    58   any
}
