Compiled from "TypeConverterBindingProcessor.java"
class com.google.inject.internal.TypeConverterBindingProcessor$6 extends com.google.inject.matcher.AbstractMatcher<com.google.inject.TypeLiteral<?>> {
  final com.google.inject.matcher.Matcher val$typeMatcher;

  final com.google.inject.internal.TypeConverterBindingProcessor this$0;

  com.google.inject.internal.TypeConverterBindingProcessor$6(com.google.inject.internal.TypeConverterBindingProcessor, com.google.inject.matcher.Matcher);
    Code:
       0: aload_0
       1: aload_1
       2: putfield      #19                 // Field this$0:Lcom/google/inject/internal/TypeConverterBindingProcessor;
       5: aload_0
       6: aload_2
       7: putfield      #21                 // Field val$typeMatcher:Lcom/google/inject/matcher/Matcher;
      10: aload_0
      11: invokespecial #24                 // Method com/google/inject/matcher/AbstractMatcher."<init>":()V
      14: return

  public boolean matches(com.google.inject.TypeLiteral<?>);
    Code:
       0: aload_1
       1: invokevirtual #34                 // Method com/google/inject/TypeLiteral.getType:()Ljava/lang/reflect/Type;
       4: astore_2
       5: aload_2
       6: instanceof    #36                 // class java/lang/Class
       9: ifne          14
      12: iconst_0
      13: ireturn
      14: aload_2
      15: checkcast     #36                 // class java/lang/Class
      18: astore_3
      19: aload_0
      20: getfield      #21                 // Field val$typeMatcher:Lcom/google/inject/matcher/Matcher;
      23: aload_3
      24: invokeinterface #41,  2           // InterfaceMethod com/google/inject/matcher/Matcher.matches:(Ljava/lang/Object;)Z
      29: ireturn

  public java.lang.String toString();
    Code:
       0: aload_0
       1: getfield      #21                 // Field val$typeMatcher:Lcom/google/inject/matcher/Matcher;
       4: invokevirtual #55                 // Method java/lang/Object.toString:()Ljava/lang/String;
       7: areturn

  public boolean matches(java.lang.Object);
    Code:
       0: aload_0
       1: aload_1
       2: checkcast     #30                 // class com/google/inject/TypeLiteral
       5: invokevirtual #57                 // Method matches:(Lcom/google/inject/TypeLiteral;)Z
       8: ireturn
}
