Compiled from "AkkaProtocolTransport.scala"
public final class akka.remote.transport.HandshakeInfo implements scala.Product,scala.Serializable {
  private final akka.actor.Address origin;

  private final int uid;

  private final scala.Option<java.lang.String> cookie;

  public static scala.Option<scala.Tuple3<akka.actor.Address, java.lang.Object, scala.Option<java.lang.String>>> unapply(akka.remote.transport.HandshakeInfo);
    Code:
       0: getstatic     #20                 // Field akka/remote/transport/HandshakeInfo$.MODULE$:Lakka/remote/transport/HandshakeInfo$;
       3: aload_0
       4: invokevirtual #22                 // Method akka/remote/transport/HandshakeInfo$.unapply:(Lakka/remote/transport/HandshakeInfo;)Lscala/Option;
       7: areturn

  public static akka.remote.transport.HandshakeInfo apply(akka.actor.Address, int, scala.Option<java.lang.String>);
    Code:
       0: getstatic     #20                 // Field akka/remote/transport/HandshakeInfo$.MODULE$:Lakka/remote/transport/HandshakeInfo$;
       3: aload_0
       4: iload_1
       5: aload_2
       6: invokevirtual #26                 // Method akka/remote/transport/HandshakeInfo$.apply:(Lakka/actor/Address;ILscala/Option;)Lakka/remote/transport/HandshakeInfo;
       9: areturn

  public static scala.Function1<scala.Tuple3<akka.actor.Address, java.lang.Object, scala.Option<java.lang.String>>, akka.remote.transport.HandshakeInfo> tupled();
    Code:
       0: getstatic     #20                 // Field akka/remote/transport/HandshakeInfo$.MODULE$:Lakka/remote/transport/HandshakeInfo$;
       3: invokevirtual #30                 // Method akka/remote/transport/HandshakeInfo$.tupled:()Lscala/Function1;
       6: areturn

  public static scala.Function1<akka.actor.Address, scala.Function1<java.lang.Object, scala.Function1<scala.Option<java.lang.String>, akka.remote.transport.HandshakeInfo>>> curried();
    Code:
       0: getstatic     #20                 // Field akka/remote/transport/HandshakeInfo$.MODULE$:Lakka/remote/transport/HandshakeInfo$;
       3: invokevirtual #33                 // Method akka/remote/transport/HandshakeInfo$.curried:()Lscala/Function1;
       6: areturn

  public akka.actor.Address origin();
    Code:
       0: aload_0
       1: getfield      #43                 // Field origin:Lakka/actor/Address;
       4: areturn

  public int uid();
    Code:
       0: aload_0
       1: getfield      #48                 // Field uid:I
       4: ireturn

  public scala.Option<java.lang.String> cookie();
    Code:
       0: aload_0
       1: getfield      #51                 // Field cookie:Lscala/Option;
       4: areturn

  public akka.remote.transport.HandshakeInfo copy(akka.actor.Address, int, scala.Option<java.lang.String>);
    Code:
       0: new           #2                  // class akka/remote/transport/HandshakeInfo
       3: dup
       4: aload_1
       5: iload_2
       6: aload_3
       7: invokespecial #56                 // Method "<init>":(Lakka/actor/Address;ILscala/Option;)V
      10: areturn

  public akka.actor.Address copy$default$1();
    Code:
       0: aload_0
       1: invokevirtual #59                 // Method origin:()Lakka/actor/Address;
       4: areturn

  public int copy$default$2();
    Code:
       0: aload_0
       1: invokevirtual #62                 // Method uid:()I
       4: ireturn

  public scala.Option<java.lang.String> copy$default$3();
    Code:
       0: aload_0
       1: invokevirtual #65                 // Method cookie:()Lscala/Option;
       4: areturn

  public java.lang.String productPrefix();
    Code:
       0: ldc           #69                 // String HandshakeInfo
       2: areturn

  public int productArity();
    Code:
       0: iconst_3
       1: ireturn

  public java.lang.Object productElement(int);
    Code:
       0: iload_1
       1: istore_2
       2: iload_2
       3: tableswitch   { // 0 to 2
                     0: 60
                     1: 50
                     2: 43
               default: 28
          }
      28: new           #74                 // class java/lang/IndexOutOfBoundsException
      31: dup
      32: iload_1
      33: invokestatic  #80                 // Method scala/runtime/BoxesRunTime.boxToInteger:(I)Ljava/lang/Integer;
      36: invokevirtual #83                 // Method java/lang/Object.toString:()Ljava/lang/String;
      39: invokespecial #86                 // Method java/lang/IndexOutOfBoundsException."<init>":(Ljava/lang/String;)V
      42: athrow
      43: aload_0
      44: invokevirtual #65                 // Method cookie:()Lscala/Option;
      47: goto          64
      50: aload_0
      51: invokevirtual #62                 // Method uid:()I
      54: invokestatic  #80                 // Method scala/runtime/BoxesRunTime.boxToInteger:(I)Ljava/lang/Integer;
      57: goto          64
      60: aload_0
      61: invokevirtual #59                 // Method origin:()Lakka/actor/Address;
      64: areturn

  public scala.collection.Iterator<java.lang.Object> productIterator();
    Code:
       0: getstatic     #94                 // Field scala/runtime/ScalaRunTime$.MODULE$:Lscala/runtime/ScalaRunTime$;
       3: aload_0
       4: invokevirtual #98                 // Method scala/runtime/ScalaRunTime$.typedProductIterator:(Lscala/Product;)Lscala/collection/Iterator;
       7: areturn

  public boolean canEqual(java.lang.Object);
    Code:
       0: aload_1
       1: instanceof    #2                  // class akka/remote/transport/HandshakeInfo
       4: ireturn

  public int hashCode();
    Code:
       0: ldc           #103                // int -889275714
       2: istore_1
       3: iload_1
       4: aload_0
       5: invokevirtual #59                 // Method origin:()Lakka/actor/Address;
       8: invokestatic  #109                // Method scala/runtime/Statics.anyHash:(Ljava/lang/Object;)I
      11: invokestatic  #113                // Method scala/runtime/Statics.mix:(II)I
      14: istore_1
      15: iload_1
      16: aload_0
      17: invokevirtual #62                 // Method uid:()I
      20: invokestatic  #113                // Method scala/runtime/Statics.mix:(II)I
      23: istore_1
      24: iload_1
      25: aload_0
      26: invokevirtual #65                 // Method cookie:()Lscala/Option;
      29: invokestatic  #109                // Method scala/runtime/Statics.anyHash:(Ljava/lang/Object;)I
      32: invokestatic  #113                // Method scala/runtime/Statics.mix:(II)I
      35: istore_1
      36: iload_1
      37: iconst_3
      38: invokestatic  #116                // Method scala/runtime/Statics.finalizeHash:(II)I
      41: ireturn

  public java.lang.String toString();
    Code:
       0: getstatic     #94                 // Field scala/runtime/ScalaRunTime$.MODULE$:Lscala/runtime/ScalaRunTime$;
       3: aload_0
       4: invokevirtual #120                // Method scala/runtime/ScalaRunTime$._toString:(Lscala/Product;)Ljava/lang/String;
       7: areturn

  public boolean equals(java.lang.Object);
    Code:
       0: aload_0
       1: aload_1
       2: if_acmpeq     115
       5: aload_1
       6: astore_2
       7: aload_2
       8: instanceof    #2                  // class akka/remote/transport/HandshakeInfo
      11: ifeq          19
      14: iconst_1
      15: istore_3
      16: goto          21
      19: iconst_0
      20: istore_3
      21: iload_3
      22: ifeq          119
      25: aload_1
      26: checkcast     #2                  // class akka/remote/transport/HandshakeInfo
      29: astore        4
      31: aload_0
      32: invokevirtual #59                 // Method origin:()Lakka/actor/Address;
      35: aload         4
      37: invokevirtual #59                 // Method origin:()Lakka/actor/Address;
      40: astore        5
      42: dup
      43: ifnonnull     55
      46: pop
      47: aload         5
      49: ifnull        63
      52: goto          111
      55: aload         5
      57: invokevirtual #123                // Method java/lang/Object.equals:(Ljava/lang/Object;)Z
      60: ifeq          111
      63: aload_0
      64: invokevirtual #62                 // Method uid:()I
      67: aload         4
      69: invokevirtual #62                 // Method uid:()I
      72: if_icmpne     111
      75: aload_0
      76: invokevirtual #65                 // Method cookie:()Lscala/Option;
      79: aload         4
      81: invokevirtual #65                 // Method cookie:()Lscala/Option;
      84: astore        6
      86: dup
      87: ifnonnull     99
      90: pop
      91: aload         6
      93: ifnull        107
      96: goto          111
      99: aload         6
     101: invokevirtual #123                // Method java/lang/Object.equals:(Ljava/lang/Object;)Z
     104: ifeq          111
     107: iconst_1
     108: goto          112
     111: iconst_0
     112: ifeq          119
     115: iconst_1
     116: goto          120
     119: iconst_0
     120: ireturn

  public akka.remote.transport.HandshakeInfo(akka.actor.Address, int, scala.Option<java.lang.String>);
    Code:
       0: aload_0
       1: aload_1
       2: putfield      #43                 // Field origin:Lakka/actor/Address;
       5: aload_0
       6: iload_2
       7: putfield      #48                 // Field uid:I
      10: aload_0
      11: aload_3
      12: putfield      #51                 // Field cookie:Lscala/Option;
      15: aload_0
      16: invokespecial #130                // Method java/lang/Object."<init>":()V
      19: aload_0
      20: invokestatic  #136                // Method scala/Product$class.$init$:(Lscala/Product;)V
      23: return
}
