Compiled from "ThrottlerTransportAdapter.scala"
public final class akka.remote.transport.ThrottlerManager$$anonfun$ready$1$$anonfun$applyOrElse$4 extends scala.runtime.AbstractFunction1<scala.collection.immutable.List<akka.remote.transport.ThrottlerTransportAdapter$SetThrottleAck$>, akka.remote.transport.ThrottlerTransportAdapter$SetThrottleAck$> implements scala.Serializable {
  public static final long serialVersionUID;

  public final akka.remote.transport.ThrottlerTransportAdapter$SetThrottleAck$ apply(scala.collection.immutable.List<akka.remote.transport.ThrottlerTransportAdapter$SetThrottleAck$>);
    Code:
       0: getstatic     #25                 // Field akka/remote/transport/ThrottlerTransportAdapter$SetThrottleAck$.MODULE$:Lakka/remote/transport/ThrottlerTransportAdapter$SetThrottleAck$;
       3: areturn

  public final java.lang.Object apply(java.lang.Object);
    Code:
       0: aload_0
       1: aload_1
       2: checkcast     #32                 // class scala/collection/immutable/List
       5: invokevirtual #34                 // Method apply:(Lscala/collection/immutable/List;)Lakka/remote/transport/ThrottlerTransportAdapter$SetThrottleAck$;
       8: areturn

  public akka.remote.transport.ThrottlerManager$$anonfun$ready$1$$anonfun$applyOrElse$4(akka.remote.transport.ThrottlerManager$$anonfun$ready$1);
    Code:
       0: aload_0
       1: invokespecial #41                 // Method scala/runtime/AbstractFunction1."<init>":()V
       4: return
}
