Compiled from "Transport.scala"
public class akka.remote.transport.Transport$ActorAssociationEventListener$ extends scala.runtime.AbstractFunction1<akka.actor.ActorRef, akka.remote.transport.Transport$ActorAssociationEventListener> implements scala.Serializable {
  public static final akka.remote.transport.Transport$ActorAssociationEventListener$ MODULE$;

  public static {};
    Code:
       0: new           #2                  // class akka/remote/transport/Transport$ActorAssociationEventListener$
       3: invokespecial #15                 // Method "<init>":()V
       6: return

  public final java.lang.String toString();
    Code:
       0: ldc           #19                 // String ActorAssociationEventListener
       2: areturn

  public akka.remote.transport.Transport$ActorAssociationEventListener apply(akka.actor.ActorRef);
    Code:
       0: new           #24                 // class akka/remote/transport/Transport$ActorAssociationEventListener
       3: dup
       4: aload_1
       5: invokespecial #27                 // Method akka/remote/transport/Transport$ActorAssociationEventListener."<init>":(Lakka/actor/ActorRef;)V
       8: areturn

  public scala.Option<akka.actor.ActorRef> unapply(akka.remote.transport.Transport$ActorAssociationEventListener);
    Code:
       0: aload_1
       1: ifnonnull     10
       4: getstatic     #36                 // Field scala/None$.MODULE$:Lscala/None$;
       7: goto          21
      10: new           #38                 // class scala/Some
      13: dup
      14: aload_1
      15: invokevirtual #41                 // Method akka/remote/transport/Transport$ActorAssociationEventListener.actor:()Lakka/actor/ActorRef;
      18: invokespecial #44                 // Method scala/Some."<init>":(Ljava/lang/Object;)V
      21: areturn

  private java.lang.Object readResolve();
    Code:
       0: getstatic     #52                 // Field MODULE$:Lakka/remote/transport/Transport$ActorAssociationEventListener$;
       3: areturn

  public java.lang.Object apply(java.lang.Object);
    Code:
       0: aload_0
       1: aload_1
       2: checkcast     #55                 // class akka/actor/ActorRef
       5: invokevirtual #57                 // Method apply:(Lakka/actor/ActorRef;)Lakka/remote/transport/Transport$ActorAssociationEventListener;
       8: areturn

  public akka.remote.transport.Transport$ActorAssociationEventListener$();
    Code:
       0: aload_0
       1: invokespecial #60                 // Method scala/runtime/AbstractFunction1."<init>":()V
       4: aload_0
       5: putstatic     #52                 // Field MODULE$:Lakka/remote/transport/Transport$ActorAssociationEventListener$;
       8: return
}
