Compiled from "AbstractIndexedFileCacheBacking.java"
public abstract class org.aspectj.weaver.tools.cache.AbstractIndexedFileCacheBacking extends org.aspectj.weaver.tools.cache.AbstractFileCacheBacking {
  public static final java.lang.String INDEX_FILE;

  protected static final org.aspectj.weaver.tools.cache.AbstractIndexedFileCacheBacking$IndexEntry[] EMPTY_INDEX;

  protected static final java.lang.String[] EMPTY_KEYS;

  private final java.io.File indexFile;

  protected org.aspectj.weaver.tools.cache.AbstractIndexedFileCacheBacking(java.io.File);
    Code:
       0: aload_0
       1: aload_1
       2: invokespecial #1                  // Method org/aspectj/weaver/tools/cache/AbstractFileCacheBacking."<init>":(Ljava/io/File;)V
       5: aload_0
       6: new           #2                  // class java/io/File
       9: dup
      10: aload_1
      11: ldc           #4                  // String cache.idx
      13: invokespecial #5                  // Method java/io/File."<init>":(Ljava/io/File;Ljava/lang/String;)V
      16: putfield      #6                  // Field indexFile:Ljava/io/File;
      19: return

  public java.io.File getIndexFile();
    Code:
       0: aload_0
       1: getfield      #6                  // Field indexFile:Ljava/io/File;
       4: areturn

  public java.lang.String[] getKeys(java.lang.String);
    Code:
       0: aload_0
       1: invokevirtual #7                  // Method getIndex:()Ljava/util/Map;
       4: astore_2
       5: aload_2
       6: ifnull        18
       9: aload_2
      10: invokeinterface #8,  1            // InterfaceMethod java/util/Map.isEmpty:()Z
      15: ifeq          22
      18: getstatic     #9                  // Field EMPTY_KEYS:[Ljava/lang/String;
      21: areturn
      22: new           #10                 // class java/util/LinkedList
      25: dup
      26: invokespecial #11                 // Method java/util/LinkedList."<init>":()V
      29: astore_3
      30: aload_2
      31: dup
      32: astore        4
      34: monitorenter
      35: aload_2
      36: invokeinterface #12,  1           // InterfaceMethod java/util/Map.keySet:()Ljava/util/Set;
      41: invokeinterface #13,  1           // InterfaceMethod java/util/Set.iterator:()Ljava/util/Iterator;
      46: astore        5
      48: aload         5
      50: invokeinterface #14,  1           // InterfaceMethod java/util/Iterator.hasNext:()Z
      55: ifeq          91
      58: aload         5
      60: invokeinterface #15,  1           // InterfaceMethod java/util/Iterator.next:()Ljava/lang/Object;
      65: checkcast     #16                 // class java/lang/String
      68: astore        6
      70: aload         6
      72: aload_1
      73: invokevirtual #17                 // Method java/lang/String.matches:(Ljava/lang/String;)Z
      76: ifeq          88
      79: aload_3
      80: aload         6
      82: invokeinterface #18,  2           // InterfaceMethod java/util/Collection.add:(Ljava/lang/Object;)Z
      87: pop
      88: goto          48
      91: aload         4
      93: monitorexit
      94: goto          105
      97: astore        7
      99: aload         4
     101: monitorexit
     102: aload         7
     104: athrow
     105: aload_3
     106: invokeinterface #19,  1           // InterfaceMethod java/util/Collection.isEmpty:()Z
     111: ifeq          118
     114: getstatic     #9                  // Field EMPTY_KEYS:[Ljava/lang/String;
     117: areturn
     118: aload_3
     119: aload_3
     120: invokeinterface #20,  1           // InterfaceMethod java/util/Collection.size:()I
     125: anewarray     #16                 // class java/lang/String
     128: invokeinterface #21,  2           // InterfaceMethod java/util/Collection.toArray:([Ljava/lang/Object;)[Ljava/lang/Object;
     133: checkcast     #22                 // class "[Ljava/lang/String;"
     136: areturn
    Exception table:
       from    to  target type
          35    94    97   any
          97   102    97   any

  protected java.util.Map<java.lang.String, org.aspectj.weaver.tools.cache.AbstractIndexedFileCacheBacking$IndexEntry> readIndex();
    Code:
       0: aload_0
       1: aload_0
       2: invokevirtual #23                 // Method getCacheDirectory:()Ljava/io/File;
       5: aload_0
       6: invokevirtual #24                 // Method getIndexFile:()Ljava/io/File;
       9: invokevirtual #25                 // Method readIndex:(Ljava/io/File;Ljava/io/File;)Ljava/util/Map;
      12: areturn

  protected void writeIndex();
    Code:
       0: aload_0
       1: aload_0
       2: invokevirtual #24                 // Method getIndexFile:()Ljava/io/File;
       5: invokevirtual #26                 // Method writeIndex:(Ljava/io/File;)V
       8: return

  protected void writeIndex(java.io.File);
    Code:
       0: aload_0
       1: aload_1
       2: aload_0
       3: invokevirtual #7                  // Method getIndex:()Ljava/util/Map;
       6: invokevirtual #27                 // Method writeIndex:(Ljava/io/File;Ljava/util/Map;)V
       9: goto          88
      12: astore_2
      13: aload_0
      14: getfield      #29                 // Field logger:Lorg/aspectj/weaver/tools/Trace;
      17: ifnull        88
      20: aload_0
      21: getfield      #29                 // Field logger:Lorg/aspectj/weaver/tools/Trace;
      24: invokeinterface #30,  1           // InterfaceMethod org/aspectj/weaver/tools/Trace.isTraceEnabled:()Z
      29: ifeq          88
      32: aload_0
      33: getfield      #29                 // Field logger:Lorg/aspectj/weaver/tools/Trace;
      36: new           #31                 // class java/lang/StringBuilder
      39: dup
      40: invokespecial #32                 // Method java/lang/StringBuilder."<init>":()V
      43: ldc           #33                 // String writeIndex(
      45: invokevirtual #34                 // Method java/lang/StringBuilder.append:(Ljava/lang/String;)Ljava/lang/StringBuilder;
      48: aload_1
      49: invokevirtual #35                 // Method java/lang/StringBuilder.append:(Ljava/lang/Object;)Ljava/lang/StringBuilder;
      52: ldc           #36                 // String )
      54: invokevirtual #34                 // Method java/lang/StringBuilder.append:(Ljava/lang/String;)Ljava/lang/StringBuilder;
      57: aload_2
      58: invokevirtual #37                 // Method java/lang/Object.getClass:()Ljava/lang/Class;
      61: invokevirtual #38                 // Method java/lang/Class.getSimpleName:()Ljava/lang/String;
      64: invokevirtual #34                 // Method java/lang/StringBuilder.append:(Ljava/lang/String;)Ljava/lang/StringBuilder;
      67: ldc           #39                 // String :
      69: invokevirtual #34                 // Method java/lang/StringBuilder.append:(Ljava/lang/String;)Ljava/lang/StringBuilder;
      72: aload_2
      73: invokevirtual #40                 // Method java/lang/Exception.getMessage:()Ljava/lang/String;
      76: invokevirtual #34                 // Method java/lang/StringBuilder.append:(Ljava/lang/String;)Ljava/lang/StringBuilder;
      79: invokevirtual #41                 // Method java/lang/StringBuilder.toString:()Ljava/lang/String;
      82: aload_2
      83: invokeinterface #42,  3           // InterfaceMethod org/aspectj/weaver/tools/Trace.warn:(Ljava/lang/String;Ljava/lang/Throwable;)V
      88: return
    Exception table:
       from    to  target type
           0     9    12   Class java/lang/Exception

  protected abstract java.util.Map<java.lang.String, org.aspectj.weaver.tools.cache.AbstractIndexedFileCacheBacking$IndexEntry> getIndex();

  protected java.util.Map<java.lang.String, org.aspectj.weaver.tools.cache.AbstractIndexedFileCacheBacking$IndexEntry> readIndex(java.io.File, java.io.File);
    Code:
       0: new           #43                 // class java/util/TreeMap
       3: dup
       4: invokespecial #44                 // Method java/util/TreeMap."<init>":()V
       7: astore_3
       8: aload_0
       9: aload_2
      10: invokevirtual #45                 // Method readIndex:(Ljava/io/File;)[Lorg/aspectj/weaver/tools/cache/AbstractIndexedFileCacheBacking$IndexEntry;
      13: astore        4
      15: aload         4
      17: invokestatic  #46                 // Method org/aspectj/util/LangUtil.isEmpty:([Ljava/lang/Object;)Z
      20: ifeq          77
      23: aload_0
      24: getfield      #29                 // Field logger:Lorg/aspectj/weaver/tools/Trace;
      27: ifnull        75
      30: aload_0
      31: getfield      #29                 // Field logger:Lorg/aspectj/weaver/tools/Trace;
      34: invokeinterface #30,  1           // InterfaceMethod org/aspectj/weaver/tools/Trace.isTraceEnabled:()Z
      39: ifeq          75
      42: aload_0
      43: getfield      #29                 // Field logger:Lorg/aspectj/weaver/tools/Trace;
      46: new           #31                 // class java/lang/StringBuilder
      49: dup
      50: invokespecial #32                 // Method java/lang/StringBuilder."<init>":()V
      53: ldc           #47                 // String readIndex(
      55: invokevirtual #34                 // Method java/lang/StringBuilder.append:(Ljava/lang/String;)Ljava/lang/StringBuilder;
      58: aload_2
      59: invokevirtual #35                 // Method java/lang/StringBuilder.append:(Ljava/lang/Object;)Ljava/lang/StringBuilder;
      62: ldc           #48                 // String ) no index entries
      64: invokevirtual #34                 // Method java/lang/StringBuilder.append:(Ljava/lang/String;)Ljava/lang/StringBuilder;
      67: invokevirtual #41                 // Method java/lang/StringBuilder.toString:()Ljava/lang/String;
      70: invokeinterface #49,  2           // InterfaceMethod org/aspectj/weaver/tools/Trace.debug:(Ljava/lang/String;)V
      75: aload_3
      76: areturn
      77: aload         4
      79: astore        5
      81: aload         5
      83: arraylength
      84: istore        6
      86: iconst_0
      87: istore        7
      89: iload         7
      91: iload         6
      93: if_icmpge     200
      96: aload         5
      98: iload         7
     100: aaload
     101: astore        8
     103: aload_0
     104: aload_1
     105: aload         8
     107: invokevirtual #50                 // Method resolveIndexMapEntry:(Ljava/io/File;Lorg/aspectj/weaver/tools/cache/AbstractIndexedFileCacheBacking$IndexEntry;)Lorg/aspectj/weaver/tools/cache/AbstractIndexedFileCacheBacking$IndexEntry;
     110: astore        9
     112: aload         9
     114: ifnull        134
     117: aload_3
     118: aload         9
     120: getfield      #51                 // Field org/aspectj/weaver/tools/cache/AbstractIndexedFileCacheBacking$IndexEntry.key:Ljava/lang/String;
     123: aload         9
     125: invokeinterface #52,  3           // InterfaceMethod java/util/Map.put:(Ljava/lang/Object;Ljava/lang/Object;)Ljava/lang/Object;
     130: pop
     131: goto          194
     134: aload_0
     135: getfield      #29                 // Field logger:Lorg/aspectj/weaver/tools/Trace;
     138: ifnull        194
     141: aload_0
     142: getfield      #29                 // Field logger:Lorg/aspectj/weaver/tools/Trace;
     145: invokeinterface #30,  1           // InterfaceMethod org/aspectj/weaver/tools/Trace.isTraceEnabled:()Z
     150: ifeq          194
     153: aload_0
     154: getfield      #29                 // Field logger:Lorg/aspectj/weaver/tools/Trace;
     157: new           #31                 // class java/lang/StringBuilder
     160: dup
     161: invokespecial #32                 // Method java/lang/StringBuilder."<init>":()V
     164: ldc           #47                 // String readIndex(
     166: invokevirtual #34                 // Method java/lang/StringBuilder.append:(Ljava/lang/String;)Ljava/lang/StringBuilder;
     169: aload_2
     170: invokevirtual #35                 // Method java/lang/StringBuilder.append:(Ljava/lang/Object;)Ljava/lang/StringBuilder;
     173: ldc           #53                 // String ) skip
     175: invokevirtual #34                 // Method java/lang/StringBuilder.append:(Ljava/lang/String;)Ljava/lang/StringBuilder;
     178: aload         8
     180: getfield      #51                 // Field org/aspectj/weaver/tools/cache/AbstractIndexedFileCacheBacking$IndexEntry.key:Ljava/lang/String;
     183: invokevirtual #34                 // Method java/lang/StringBuilder.append:(Ljava/lang/String;)Ljava/lang/StringBuilder;
     186: invokevirtual #41                 // Method java/lang/StringBuilder.toString:()Ljava/lang/String;
     189: invokeinterface #49,  2           // InterfaceMethod org/aspectj/weaver/tools/Trace.debug:(Ljava/lang/String;)V
     194: iinc          7, 1
     197: goto          89
     200: aload_3
     201: areturn

  protected org.aspectj.weaver.tools.cache.AbstractIndexedFileCacheBacking$IndexEntry resolveIndexMapEntry(java.io.File, org.aspectj.weaver.tools.cache.AbstractIndexedFileCacheBacking$IndexEntry);
    Code:
       0: aload_2
       1: areturn

  public org.aspectj.weaver.tools.cache.AbstractIndexedFileCacheBacking$IndexEntry[] readIndex(java.io.File);
    Code:
       0: aload_1
       1: invokevirtual #54                 // Method java/io/File.canRead:()Z
       4: ifne          11
       7: getstatic     #55                 // Field EMPTY_INDEX:[Lorg/aspectj/weaver/tools/cache/AbstractIndexedFileCacheBacking$IndexEntry;
      10: areturn
      11: aconst_null
      12: astore_2
      13: new           #56                 // class java/io/ObjectInputStream
      16: dup
      17: new           #57                 // class java/io/FileInputStream
      20: dup
      21: aload_1
      22: invokespecial #58                 // Method java/io/FileInputStream."<init>":(Ljava/io/File;)V
      25: invokespecial #59                 // Method java/io/ObjectInputStream."<init>":(Ljava/io/InputStream;)V
      28: astore_2
      29: aload_2
      30: invokevirtual #60                 // Method java/io/ObjectInputStream.readObject:()Ljava/lang/Object;
      33: checkcast     #61                 // class "[Lorg/aspectj/weaver/tools/cache/AbstractIndexedFileCacheBacking$IndexEntry;"
      36: checkcast     #61                 // class "[Lorg/aspectj/weaver/tools/cache/AbstractIndexedFileCacheBacking$IndexEntry;"
      39: astore_3
      40: aload_0
      41: aload_2
      42: aload_1
      43: invokevirtual #62                 // Method close:(Ljava/io/InputStream;Ljava/io/File;)V
      46: aload_3
      47: areturn
      48: astore_3
      49: aload_0
      50: getfield      #29                 // Field logger:Lorg/aspectj/weaver/tools/Trace;
      53: ifnull        127
      56: aload_0
      57: getfield      #29                 // Field logger:Lorg/aspectj/weaver/tools/Trace;
      60: invokeinterface #30,  1           // InterfaceMethod org/aspectj/weaver/tools/Trace.isTraceEnabled:()Z
      65: ifeq          127
      68: aload_0
      69: getfield      #29                 // Field logger:Lorg/aspectj/weaver/tools/Trace;
      72: new           #31                 // class java/lang/StringBuilder
      75: dup
      76: invokespecial #32                 // Method java/lang/StringBuilder."<init>":()V
      79: ldc           #63                 // String Failed (
      81: invokevirtual #34                 // Method java/lang/StringBuilder.append:(Ljava/lang/String;)Ljava/lang/StringBuilder;
      84: aload_3
      85: invokevirtual #37                 // Method java/lang/Object.getClass:()Ljava/lang/Class;
      88: invokevirtual #38                 // Method java/lang/Class.getSimpleName:()Ljava/lang/String;
      91: invokevirtual #34                 // Method java/lang/StringBuilder.append:(Ljava/lang/String;)Ljava/lang/StringBuilder;
      94: ldc           #64                 // String ) to read index from
      96: invokevirtual #34                 // Method java/lang/StringBuilder.append:(Ljava/lang/String;)Ljava/lang/StringBuilder;
      99: aload_1
     100: invokevirtual #65                 // Method java/io/File.getAbsolutePath:()Ljava/lang/String;
     103: invokevirtual #34                 // Method java/lang/StringBuilder.append:(Ljava/lang/String;)Ljava/lang/StringBuilder;
     106: ldc           #66                 // String  :
     108: invokevirtual #34                 // Method java/lang/StringBuilder.append:(Ljava/lang/String;)Ljava/lang/StringBuilder;
     111: aload_3
     112: invokevirtual #40                 // Method java/lang/Exception.getMessage:()Ljava/lang/String;
     115: invokevirtual #34                 // Method java/lang/StringBuilder.append:(Ljava/lang/String;)Ljava/lang/StringBuilder;
     118: invokevirtual #41                 // Method java/lang/StringBuilder.toString:()Ljava/lang/String;
     121: aload_3
     122: invokeinterface #67,  3           // InterfaceMethod org/aspectj/weaver/tools/Trace.error:(Ljava/lang/String;Ljava/lang/Throwable;)V
     127: aload_0
     128: aload_1
     129: invokevirtual #68                 // Method delete:(Ljava/io/File;)V
     132: aload_0
     133: aload_2
     134: aload_1
     135: invokevirtual #62                 // Method close:(Ljava/io/InputStream;Ljava/io/File;)V
     138: goto          152
     141: astore        4
     143: aload_0
     144: aload_2
     145: aload_1
     146: invokevirtual #62                 // Method close:(Ljava/io/InputStream;Ljava/io/File;)V
     149: aload         4
     151: athrow
     152: getstatic     #55                 // Field EMPTY_INDEX:[Lorg/aspectj/weaver/tools/cache/AbstractIndexedFileCacheBacking$IndexEntry;
     155: areturn
    Exception table:
       from    to  target type
          13    40    48   Class java/lang/Exception
          13    40   141   any
          48   132   141   any
         141   143   141   any

  protected void writeIndex(java.io.File, java.util.Map<java.lang.String, ? extends org.aspectj.weaver.tools.cache.AbstractIndexedFileCacheBacking$IndexEntry>) throws java.io.IOException;
    Code:
       0: aload_0
       1: aload_1
       2: aload_2
       3: invokestatic  #69                 // Method org/aspectj/util/LangUtil.isEmpty:(Ljava/util/Map;)Z
       6: ifeq          15
       9: invokestatic  #70                 // Method java/util/Collections.emptyList:()Ljava/util/List;
      12: goto          21
      15: aload_2
      16: invokeinterface #71,  1           // InterfaceMethod java/util/Map.values:()Ljava/util/Collection;
      21: invokevirtual #72                 // Method writeIndex:(Ljava/io/File;Ljava/util/Collection;)V
      24: return

  protected void writeIndex(java.io.File, org.aspectj.weaver.tools.cache.AbstractIndexedFileCacheBacking$IndexEntry...) throws java.io.IOException;
    Code:
       0: aload_0
       1: aload_1
       2: aload_2
       3: invokestatic  #46                 // Method org/aspectj/util/LangUtil.isEmpty:([Ljava/lang/Object;)Z
       6: ifeq          15
       9: invokestatic  #70                 // Method java/util/Collections.emptyList:()Ljava/util/List;
      12: goto          19
      15: aload_2
      16: invokestatic  #73                 // Method java/util/Arrays.asList:([Ljava/lang/Object;)Ljava/util/List;
      19: invokevirtual #72                 // Method writeIndex:(Ljava/io/File;Ljava/util/Collection;)V
      22: return

  protected void writeIndex(java.io.File, java.util.Collection<? extends org.aspectj.weaver.tools.cache.AbstractIndexedFileCacheBacking$IndexEntry>) throws java.io.IOException;
    Code:
       0: aload_1
       1: invokevirtual #74                 // Method java/io/File.getParentFile:()Ljava/io/File;
       4: astore_3
       5: aload_3
       6: invokevirtual #75                 // Method java/io/File.exists:()Z
       9: ifne          49
      12: aload_3
      13: invokevirtual #76                 // Method java/io/File.mkdirs:()Z
      16: ifne          49
      19: new           #77                 // class java/io/IOException
      22: dup
      23: new           #31                 // class java/lang/StringBuilder
      26: dup
      27: invokespecial #32                 // Method java/lang/StringBuilder."<init>":()V
      30: ldc           #78                 // String Failed to create path to
      32: invokevirtual #34                 // Method java/lang/StringBuilder.append:(Ljava/lang/String;)Ljava/lang/StringBuilder;
      35: aload_1
      36: invokevirtual #65                 // Method java/io/File.getAbsolutePath:()Ljava/lang/String;
      39: invokevirtual #34                 // Method java/lang/StringBuilder.append:(Ljava/lang/String;)Ljava/lang/StringBuilder;
      42: invokevirtual #41                 // Method java/lang/StringBuilder.toString:()Ljava/lang/String;
      45: invokespecial #79                 // Method java/io/IOException."<init>":(Ljava/lang/String;)V
      48: athrow
      49: aload_2
      50: invokestatic  #80                 // Method org/aspectj/util/LangUtil.isEmpty:(Ljava/util/Collection;)Z
      53: ifeq          60
      56: iconst_0
      57: goto          66
      60: aload_2
      61: invokeinterface #20,  1           // InterfaceMethod java/util/Collection.size:()I
      66: istore        4
      68: iload         4
      70: ifgt          77
      73: aconst_null
      74: goto          91
      77: aload_2
      78: iload         4
      80: anewarray     #81                 // class org/aspectj/weaver/tools/cache/AbstractIndexedFileCacheBacking$IndexEntry
      83: invokeinterface #21,  2           // InterfaceMethod java/util/Collection.toArray:([Ljava/lang/Object;)[Ljava/lang/Object;
      88: checkcast     #61                 // class "[Lorg/aspectj/weaver/tools/cache/AbstractIndexedFileCacheBacking$IndexEntry;"
      91: astore        5
      93: aload         5
      95: invokestatic  #46                 // Method org/aspectj/util/LangUtil.isEmpty:([Ljava/lang/Object;)Z
      98: ifeq          146
     101: aload_1
     102: invokevirtual #75                 // Method java/io/File.exists:()Z
     105: ifeq          145
     108: aload_1
     109: invokevirtual #82                 // Method java/io/File.delete:()Z
     112: ifne          145
     115: new           #83                 // class java/io/StreamCorruptedException
     118: dup
     119: new           #31                 // class java/lang/StringBuilder
     122: dup
     123: invokespecial #32                 // Method java/lang/StringBuilder."<init>":()V
     126: ldc           #84                 // String Failed to clean up index file at
     128: invokevirtual #34                 // Method java/lang/StringBuilder.append:(Ljava/lang/String;)Ljava/lang/StringBuilder;
     131: aload_1
     132: invokevirtual #65                 // Method java/io/File.getAbsolutePath:()Ljava/lang/String;
     135: invokevirtual #34                 // Method java/lang/StringBuilder.append:(Ljava/lang/String;)Ljava/lang/StringBuilder;
     138: invokevirtual #41                 // Method java/lang/StringBuilder.toString:()Ljava/lang/String;
     141: invokespecial #85                 // Method java/io/StreamCorruptedException."<init>":(Ljava/lang/String;)V
     144: athrow
     145: return
     146: new           #86                 // class java/io/ObjectOutputStream
     149: dup
     150: new           #87                 // class java/io/BufferedOutputStream
     153: dup
     154: new           #88                 // class java/io/FileOutputStream
     157: dup
     158: aload_1
     159: invokespecial #89                 // Method java/io/FileOutputStream."<init>":(Ljava/io/File;)V
     162: sipush        4096
     165: invokespecial #90                 // Method java/io/BufferedOutputStream."<init>":(Ljava/io/OutputStream;I)V
     168: invokespecial #91                 // Method java/io/ObjectOutputStream."<init>":(Ljava/io/OutputStream;)V
     171: astore        6
     173: aload         6
     175: aload         5
     177: invokevirtual #92                 // Method java/io/ObjectOutputStream.writeObject:(Ljava/lang/Object;)V
     180: aload_0
     181: aload         6
     183: aload_1
     184: invokevirtual #93                 // Method close:(Ljava/io/OutputStream;Ljava/io/File;)V
     187: goto          202
     190: astore        7
     192: aload_0
     193: aload         6
     195: aload_1
     196: invokevirtual #93                 // Method close:(Ljava/io/OutputStream;Ljava/io/File;)V
     199: aload         7
     201: athrow
     202: return
    Exception table:
       from    to  target type
         173   180   190   any
         190   192   190   any

  public static final org.aspectj.weaver.tools.cache.AbstractIndexedFileCacheBacking$IndexEntry createIndexEntry(org.aspectj.weaver.tools.cache.CachedClassEntry, byte[]);
    Code:
       0: aload_0
       1: ifnonnull     6
       4: aconst_null
       5: areturn
       6: new           #81                 // class org/aspectj/weaver/tools/cache/AbstractIndexedFileCacheBacking$IndexEntry
       9: dup
      10: invokespecial #94                 // Method org/aspectj/weaver/tools/cache/AbstractIndexedFileCacheBacking$IndexEntry."<init>":()V
      13: astore_2
      14: aload_2
      15: aload_0
      16: invokevirtual #95                 // Method org/aspectj/weaver/tools/cache/CachedClassEntry.getKey:()Ljava/lang/String;
      19: putfield      #51                 // Field org/aspectj/weaver/tools/cache/AbstractIndexedFileCacheBacking$IndexEntry.key:Ljava/lang/String;
      22: aload_2
      23: aload_0
      24: invokevirtual #96                 // Method org/aspectj/weaver/tools/cache/CachedClassEntry.isGenerated:()Z
      27: putfield      #97                 // Field org/aspectj/weaver/tools/cache/AbstractIndexedFileCacheBacking$IndexEntry.generated:Z
      30: aload_2
      31: aload_0
      32: invokevirtual #98                 // Method org/aspectj/weaver/tools/cache/CachedClassEntry.isIgnored:()Z
      35: putfield      #99                 // Field org/aspectj/weaver/tools/cache/AbstractIndexedFileCacheBacking$IndexEntry.ignored:Z
      38: aload_2
      39: aload_1
      40: invokestatic  #100                // Method crc:([B)J
      43: putfield      #101                // Field org/aspectj/weaver/tools/cache/AbstractIndexedFileCacheBacking$IndexEntry.crcClass:J
      46: aload_0
      47: invokevirtual #98                 // Method org/aspectj/weaver/tools/cache/CachedClassEntry.isIgnored:()Z
      50: ifne          64
      53: aload_2
      54: aload_0
      55: invokevirtual #102                // Method org/aspectj/weaver/tools/cache/CachedClassEntry.getBytes:()[B
      58: invokestatic  #100                // Method crc:([B)J
      61: putfield      #103                // Field org/aspectj/weaver/tools/cache/AbstractIndexedFileCacheBacking$IndexEntry.crcWeaved:J
      64: aload_2
      65: areturn

  static {};
    Code:
       0: iconst_0
       1: anewarray     #81                 // class org/aspectj/weaver/tools/cache/AbstractIndexedFileCacheBacking$IndexEntry
       4: putstatic     #55                 // Field EMPTY_INDEX:[Lorg/aspectj/weaver/tools/cache/AbstractIndexedFileCacheBacking$IndexEntry;
       7: iconst_0
       8: anewarray     #16                 // class java/lang/String
      11: putstatic     #9                  // Field EMPTY_KEYS:[Ljava/lang/String;
      14: return
}
