public abstract class org.bouncycastle.math.ec.ECPoint {
  protected static final org.bouncycastle.math.ec.ECFieldElement[] EMPTY_ZS;

  protected org.bouncycastle.math.ec.ECCurve curve;

  protected org.bouncycastle.math.ec.ECFieldElement x;

  protected org.bouncycastle.math.ec.ECFieldElement y;

  protected org.bouncycastle.math.ec.ECFieldElement[] zs;

  protected java.util.Hashtable preCompTable;

  protected static org.bouncycastle.math.ec.ECFieldElement[] getInitialZCoords(org.bouncycastle.math.ec.ECCurve);
    Code:
       0: aconst_null
       1: aload_0
       2: if_acmpne     9
       5: iconst_0
       6: goto          13
       9: aload_0
      10: invokevirtual #251                // Method org/bouncycastle/math/ec/ECCurve.getCoordinateSystem:()I
      13: istore_1
      14: iload_1
      15: lookupswitch  { // 2
                     0: 40
                     5: 40
               default: 44
          }
      40: getstatic     #236                // Field EMPTY_ZS:[Lorg/bouncycastle/math/ec/ECFieldElement;
      43: areturn
      44: aload_0
      45: getstatic     #231                // Field org/bouncycastle/math/ec/ECConstants.ONE:Ljava/math/BigInteger;
      48: invokevirtual #259                // Method org/bouncycastle/math/ec/ECCurve.fromBigInteger:(Ljava/math/BigInteger;)Lorg/bouncycastle/math/ec/ECFieldElement;
      51: astore_2
      52: iload_1
      53: tableswitch   { // 1 to 6
                     1: 92
                     2: 92
                     3: 101
                     4: 118
                     5: 134
                     6: 92
               default: 134
          }
      92: iconst_1
      93: anewarray     #122                // class org/bouncycastle/math/ec/ECFieldElement
      96: dup
      97: iconst_0
      98: aload_2
      99: aastore
     100: areturn
     101: iconst_3
     102: anewarray     #122                // class org/bouncycastle/math/ec/ECFieldElement
     105: dup
     106: iconst_0
     107: aload_2
     108: aastore
     109: dup
     110: iconst_1
     111: aload_2
     112: aastore
     113: dup
     114: iconst_2
     115: aload_2
     116: aastore
     117: areturn
     118: iconst_2
     119: anewarray     #122                // class org/bouncycastle/math/ec/ECFieldElement
     122: dup
     123: iconst_0
     124: aload_2
     125: aastore
     126: dup
     127: iconst_1
     128: aload_0
     129: invokevirtual #256                // Method org/bouncycastle/math/ec/ECCurve.getA:()Lorg/bouncycastle/math/ec/ECFieldElement;
     132: aastore
     133: areturn
     134: new           #112                // class java/lang/IllegalArgumentException
     137: dup
     138: ldc           #7                  // String unknown coordinate system
     140: invokespecial #238                // Method java/lang/IllegalArgumentException."<init>":(Ljava/lang/String;)V
     143: athrow

  protected org.bouncycastle.math.ec.ECPoint(org.bouncycastle.math.ec.ECCurve, org.bouncycastle.math.ec.ECFieldElement, org.bouncycastle.math.ec.ECFieldElement);
    Code:
       0: aload_0
       1: aload_1
       2: aload_2
       3: aload_3
       4: aload_1
       5: invokestatic  #289                // Method getInitialZCoords:(Lorg/bouncycastle/math/ec/ECCurve;)[Lorg/bouncycastle/math/ec/ECFieldElement;
       8: invokespecial #294                // Method "<init>":(Lorg/bouncycastle/math/ec/ECCurve;Lorg/bouncycastle/math/ec/ECFieldElement;Lorg/bouncycastle/math/ec/ECFieldElement;[Lorg/bouncycastle/math/ec/ECFieldElement;)V
      11: return

  protected org.bouncycastle.math.ec.ECPoint(org.bouncycastle.math.ec.ECCurve, org.bouncycastle.math.ec.ECFieldElement, org.bouncycastle.math.ec.ECFieldElement, org.bouncycastle.math.ec.ECFieldElement[]);
    Code:
       0: aload_0
       1: invokespecial #241                // Method java/lang/Object."<init>":()V
       4: aload_0
       5: aconst_null
       6: putfield      #232                // Field preCompTable:Ljava/util/Hashtable;
       9: aload_0
      10: aload_1
      11: putfield      #233                // Field curve:Lorg/bouncycastle/math/ec/ECCurve;
      14: aload_0
      15: aload_2
      16: putfield      #234                // Field x:Lorg/bouncycastle/math/ec/ECFieldElement;
      19: aload_0
      20: aload_3
      21: putfield      #235                // Field y:Lorg/bouncycastle/math/ec/ECFieldElement;
      24: aload_0
      25: aload         4
      27: putfield      #237                // Field zs:[Lorg/bouncycastle/math/ec/ECFieldElement;
      30: return

  protected abstract boolean satisfiesCurveEquation();

  protected boolean satisfiesOrder();
    Code:
       0: getstatic     #231                // Field org/bouncycastle/math/ec/ECConstants.ONE:Ljava/math/BigInteger;
       3: aload_0
       4: getfield      #233                // Field curve:Lorg/bouncycastle/math/ec/ECCurve;
       7: invokevirtual #253                // Method org/bouncycastle/math/ec/ECCurve.getCofactor:()Ljava/math/BigInteger;
      10: invokevirtual #248                // Method java/math/BigInteger.equals:(Ljava/lang/Object;)Z
      13: ifeq          18
      16: iconst_1
      17: ireturn
      18: aload_0
      19: getfield      #233                // Field curve:Lorg/bouncycastle/math/ec/ECCurve;
      22: invokevirtual #254                // Method org/bouncycastle/math/ec/ECCurve.getOrder:()Ljava/math/BigInteger;
      25: astore_1
      26: aload_1
      27: ifnull        41
      30: aload_0
      31: aload_1
      32: invokestatic  #250                // Method org/bouncycastle/math/ec/ECAlgorithms.referenceMultiply:(Lorg/bouncycastle/math/ec/ECPoint;Ljava/math/BigInteger;)Lorg/bouncycastle/math/ec/ECPoint;
      35: invokevirtual #275                // Method isInfinity:()Z
      38: ifeq          45
      41: iconst_1
      42: goto          46
      45: iconst_0
      46: ireturn

  public final org.bouncycastle.math.ec.ECPoint getDetachedPoint();
    Code:
       0: aload_0
       1: invokevirtual #286                // Method normalize:()Lorg/bouncycastle/math/ec/ECPoint;
       4: invokevirtual #285                // Method detach:()Lorg/bouncycastle/math/ec/ECPoint;
       7: areturn

  public org.bouncycastle.math.ec.ECCurve getCurve();
    Code:
       0: aload_0
       1: getfield      #233                // Field curve:Lorg/bouncycastle/math/ec/ECCurve;
       4: areturn

  protected abstract org.bouncycastle.math.ec.ECPoint detach();

  protected int getCurveCoordinateSystem();
    Code:
       0: aconst_null
       1: aload_0
       2: getfield      #233                // Field curve:Lorg/bouncycastle/math/ec/ECCurve;
       5: if_acmpne     12
       8: iconst_0
       9: goto          19
      12: aload_0
      13: getfield      #233                // Field curve:Lorg/bouncycastle/math/ec/ECCurve;
      16: invokevirtual #251                // Method org/bouncycastle/math/ec/ECCurve.getCoordinateSystem:()I
      19: ireturn

  public org.bouncycastle.math.ec.ECFieldElement getAffineXCoord();
    Code:
       0: aload_0
       1: invokevirtual #273                // Method checkNormalized:()V
       4: aload_0
       5: invokevirtual #281                // Method getXCoord:()Lorg/bouncycastle/math/ec/ECFieldElement;
       8: areturn

  public org.bouncycastle.math.ec.ECFieldElement getAffineYCoord();
    Code:
       0: aload_0
       1: invokevirtual #273                // Method checkNormalized:()V
       4: aload_0
       5: invokevirtual #282                // Method getYCoord:()Lorg/bouncycastle/math/ec/ECFieldElement;
       8: areturn

  public org.bouncycastle.math.ec.ECFieldElement getXCoord();
    Code:
       0: aload_0
       1: getfield      #234                // Field x:Lorg/bouncycastle/math/ec/ECFieldElement;
       4: areturn

  public org.bouncycastle.math.ec.ECFieldElement getYCoord();
    Code:
       0: aload_0
       1: getfield      #235                // Field y:Lorg/bouncycastle/math/ec/ECFieldElement;
       4: areturn

  public org.bouncycastle.math.ec.ECFieldElement getZCoord(int);
    Code:
       0: iload_1
       1: iflt          13
       4: iload_1
       5: aload_0
       6: getfield      #237                // Field zs:[Lorg/bouncycastle/math/ec/ECFieldElement;
       9: arraylength
      10: if_icmplt     17
      13: aconst_null
      14: goto          23
      17: aload_0
      18: getfield      #237                // Field zs:[Lorg/bouncycastle/math/ec/ECFieldElement;
      21: iload_1
      22: aaload
      23: areturn

  public org.bouncycastle.math.ec.ECFieldElement[] getZCoords();
    Code:
       0: aload_0
       1: getfield      #237                // Field zs:[Lorg/bouncycastle/math/ec/ECFieldElement;
       4: arraylength
       5: istore_1
       6: iload_1
       7: ifne          14
      10: getstatic     #236                // Field EMPTY_ZS:[Lorg/bouncycastle/math/ec/ECFieldElement;
      13: areturn
      14: iload_1
      15: anewarray     #122                // class org/bouncycastle/math/ec/ECFieldElement
      18: astore_2
      19: aload_0
      20: getfield      #237                // Field zs:[Lorg/bouncycastle/math/ec/ECFieldElement;
      23: iconst_0
      24: aload_2
      25: iconst_0
      26: iload_1
      27: invokestatic  #247                // Method java/lang/System.arraycopy:(Ljava/lang/Object;ILjava/lang/Object;II)V
      30: aload_2
      31: areturn

  public final org.bouncycastle.math.ec.ECFieldElement getRawXCoord();
    Code:
       0: aload_0
       1: getfield      #234                // Field x:Lorg/bouncycastle/math/ec/ECFieldElement;
       4: areturn

  public final org.bouncycastle.math.ec.ECFieldElement getRawYCoord();
    Code:
       0: aload_0
       1: getfield      #235                // Field y:Lorg/bouncycastle/math/ec/ECFieldElement;
       4: areturn

  protected final org.bouncycastle.math.ec.ECFieldElement[] getRawZCoords();
    Code:
       0: aload_0
       1: getfield      #237                // Field zs:[Lorg/bouncycastle/math/ec/ECFieldElement;
       4: areturn

  protected void checkNormalized();
    Code:
       0: aload_0
       1: invokevirtual #276                // Method isNormalized:()Z
       4: ifne          17
       7: new           #113                // class java/lang/IllegalStateException
      10: dup
      11: ldc           #6                  // String point not in normal form
      13: invokespecial #239                // Method java/lang/IllegalStateException."<init>":(Ljava/lang/String;)V
      16: athrow
      17: return

  public boolean isNormalized();
    Code:
       0: aload_0
       1: invokevirtual #272                // Method getCurveCoordinateSystem:()I
       4: istore_1
       5: iload_1
       6: ifeq          33
       9: iload_1
      10: iconst_5
      11: if_icmpeq     33
      14: aload_0
      15: invokevirtual #275                // Method isInfinity:()Z
      18: ifne          33
      21: aload_0
      22: getfield      #237                // Field zs:[Lorg/bouncycastle/math/ec/ECFieldElement;
      25: iconst_0
      26: aaload
      27: invokevirtual #265                // Method org/bouncycastle/math/ec/ECFieldElement.isOne:()Z
      30: ifeq          37
      33: iconst_1
      34: goto          38
      37: iconst_0
      38: ireturn

  public org.bouncycastle.math.ec.ECPoint normalize();
    Code:
       0: aload_0
       1: invokevirtual #275                // Method isInfinity:()Z
       4: ifeq          9
       7: aload_0
       8: areturn
       9: aload_0
      10: invokevirtual #272                // Method getCurveCoordinateSystem:()I
      13: lookupswitch  { // 2
                     0: 40
                     5: 40
               default: 42
          }
      40: aload_0
      41: areturn
      42: aload_0
      43: iconst_0
      44: invokevirtual #284                // Method getZCoord:(I)Lorg/bouncycastle/math/ec/ECFieldElement;
      47: astore_1
      48: aload_1
      49: invokevirtual #265                // Method org/bouncycastle/math/ec/ECFieldElement.isOne:()Z
      52: ifeq          57
      55: aload_0
      56: areturn
      57: aconst_null
      58: aload_0
      59: getfield      #233                // Field curve:Lorg/bouncycastle/math/ec/ECCurve;
      62: if_acmpne     75
      65: new           #113                // class java/lang/IllegalStateException
      68: dup
      69: ldc           #2                  // String Detached points must be in affine coordinates
      71: invokespecial #239                // Method java/lang/IllegalStateException."<init>":(Ljava/lang/String;)V
      74: athrow
      75: invokestatic  #249                // Method org/bouncycastle/crypto/CryptoServicesRegistrar.getSecureRandom:()Ljava/security/SecureRandom;
      78: astore_2
      79: aload_0
      80: getfield      #233                // Field curve:Lorg/bouncycastle/math/ec/ECCurve;
      83: aload_2
      84: invokevirtual #260                // Method org/bouncycastle/math/ec/ECCurve.randomFieldElementMult:(Ljava/security/SecureRandom;)Lorg/bouncycastle/math/ec/ECFieldElement;
      87: astore_3
      88: aload_1
      89: aload_3
      90: invokevirtual #271                // Method org/bouncycastle/math/ec/ECFieldElement.multiply:(Lorg/bouncycastle/math/ec/ECFieldElement;)Lorg/bouncycastle/math/ec/ECFieldElement;
      93: invokevirtual #268                // Method org/bouncycastle/math/ec/ECFieldElement.invert:()Lorg/bouncycastle/math/ec/ECFieldElement;
      96: aload_3
      97: invokevirtual #271                // Method org/bouncycastle/math/ec/ECFieldElement.multiply:(Lorg/bouncycastle/math/ec/ECFieldElement;)Lorg/bouncycastle/math/ec/ECFieldElement;
     100: astore        4
     102: aload_0
     103: aload         4
     105: invokevirtual #290                // Method normalize:(Lorg/bouncycastle/math/ec/ECFieldElement;)Lorg/bouncycastle/math/ec/ECPoint;
     108: areturn

  org.bouncycastle.math.ec.ECPoint normalize(org.bouncycastle.math.ec.ECFieldElement);
    Code:
       0: aload_0
       1: invokevirtual #272                // Method getCurveCoordinateSystem:()I
       4: tableswitch   { // 1 to 6
                     1: 44
                     2: 51
                     3: 51
                     4: 51
                     5: 69
                     6: 44
               default: 69
          }
      44: aload_0
      45: aload_1
      46: aload_1
      47: invokevirtual #293                // Method createScaledPoint:(Lorg/bouncycastle/math/ec/ECFieldElement;Lorg/bouncycastle/math/ec/ECFieldElement;)Lorg/bouncycastle/math/ec/ECPoint;
      50: areturn
      51: aload_1
      52: invokevirtual #270                // Method org/bouncycastle/math/ec/ECFieldElement.square:()Lorg/bouncycastle/math/ec/ECFieldElement;
      55: astore_2
      56: aload_2
      57: aload_1
      58: invokevirtual #271                // Method org/bouncycastle/math/ec/ECFieldElement.multiply:(Lorg/bouncycastle/math/ec/ECFieldElement;)Lorg/bouncycastle/math/ec/ECFieldElement;
      61: astore_3
      62: aload_0
      63: aload_2
      64: aload_3
      65: invokevirtual #293                // Method createScaledPoint:(Lorg/bouncycastle/math/ec/ECFieldElement;Lorg/bouncycastle/math/ec/ECFieldElement;)Lorg/bouncycastle/math/ec/ECPoint;
      68: areturn
      69: new           #113                // class java/lang/IllegalStateException
      72: dup
      73: ldc           #5                  // String not a projective coordinate system
      75: invokespecial #239                // Method java/lang/IllegalStateException."<init>":(Ljava/lang/String;)V
      78: athrow

  protected org.bouncycastle.math.ec.ECPoint createScaledPoint(org.bouncycastle.math.ec.ECFieldElement, org.bouncycastle.math.ec.ECFieldElement);
    Code:
       0: aload_0
       1: invokevirtual #278                // Method getCurve:()Lorg/bouncycastle/math/ec/ECCurve;
       4: aload_0
       5: invokevirtual #279                // Method getRawXCoord:()Lorg/bouncycastle/math/ec/ECFieldElement;
       8: aload_1
       9: invokevirtual #271                // Method org/bouncycastle/math/ec/ECFieldElement.multiply:(Lorg/bouncycastle/math/ec/ECFieldElement;)Lorg/bouncycastle/math/ec/ECFieldElement;
      12: aload_0
      13: invokevirtual #280                // Method getRawYCoord:()Lorg/bouncycastle/math/ec/ECFieldElement;
      16: aload_2
      17: invokevirtual #271                // Method org/bouncycastle/math/ec/ECFieldElement.multiply:(Lorg/bouncycastle/math/ec/ECFieldElement;)Lorg/bouncycastle/math/ec/ECFieldElement;
      20: invokevirtual #262                // Method org/bouncycastle/math/ec/ECCurve.createRawPoint:(Lorg/bouncycastle/math/ec/ECFieldElement;Lorg/bouncycastle/math/ec/ECFieldElement;)Lorg/bouncycastle/math/ec/ECPoint;
      23: areturn

  public boolean isInfinity();
    Code:
       0: aload_0
       1: getfield      #234                // Field x:Lorg/bouncycastle/math/ec/ECFieldElement;
       4: ifnull        34
       7: aload_0
       8: getfield      #235                // Field y:Lorg/bouncycastle/math/ec/ECFieldElement;
      11: ifnull        34
      14: aload_0
      15: getfield      #237                // Field zs:[Lorg/bouncycastle/math/ec/ECFieldElement;
      18: arraylength
      19: ifle          38
      22: aload_0
      23: getfield      #237                // Field zs:[Lorg/bouncycastle/math/ec/ECFieldElement;
      26: iconst_0
      27: aaload
      28: invokevirtual #266                // Method org/bouncycastle/math/ec/ECFieldElement.isZero:()Z
      31: ifeq          38
      34: iconst_1
      35: goto          39
      38: iconst_0
      39: ireturn

  public boolean isValid();
    Code:
       0: aload_0
       1: iconst_0
       2: iconst_1
       3: invokevirtual #277                // Method implIsValid:(ZZ)Z
       6: ireturn

  boolean isValidPartial();
    Code:
       0: aload_0
       1: iconst_0
       2: iconst_0
       3: invokevirtual #277                // Method implIsValid:(ZZ)Z
       6: ireturn

  boolean implIsValid(boolean, boolean);
    Code:
       0: aload_0
       1: invokevirtual #275                // Method isInfinity:()Z
       4: ifeq          9
       7: iconst_1
       8: ireturn
       9: aload_0
      10: invokevirtual #278                // Method getCurve:()Lorg/bouncycastle/math/ec/ECCurve;
      13: aload_0
      14: ldc           #4                  // String bc_validity
      16: new           #125                // class org/bouncycastle/math/ec/ECPoint$1
      19: dup
      20: aload_0
      21: iload_1
      22: iload_2
      23: invokespecial #295                // Method org/bouncycastle/math/ec/ECPoint$1."<init>":(Lorg/bouncycastle/math/ec/ECPoint;ZZ)V
      26: invokevirtual #264                // Method org/bouncycastle/math/ec/ECCurve.precompute:(Lorg/bouncycastle/math/ec/ECPoint;Ljava/lang/String;Lorg/bouncycastle/math/ec/PreCompCallback;)Lorg/bouncycastle/math/ec/PreCompInfo;
      29: checkcast     #130                // class org/bouncycastle/math/ec/ValidityPrecompInfo
      32: astore_3
      33: aload_3
      34: invokevirtual #296                // Method org/bouncycastle/math/ec/ValidityPrecompInfo.hasFailed:()Z
      37: ifne          44
      40: iconst_1
      41: goto          45
      44: iconst_0
      45: ireturn

  public org.bouncycastle.math.ec.ECPoint scaleX(org.bouncycastle.math.ec.ECFieldElement);
    Code:
       0: aload_0
       1: invokevirtual #275                // Method isInfinity:()Z
       4: ifeq          11
       7: aload_0
       8: goto          34
      11: aload_0
      12: invokevirtual #278                // Method getCurve:()Lorg/bouncycastle/math/ec/ECCurve;
      15: aload_0
      16: invokevirtual #279                // Method getRawXCoord:()Lorg/bouncycastle/math/ec/ECFieldElement;
      19: aload_1
      20: invokevirtual #271                // Method org/bouncycastle/math/ec/ECFieldElement.multiply:(Lorg/bouncycastle/math/ec/ECFieldElement;)Lorg/bouncycastle/math/ec/ECFieldElement;
      23: aload_0
      24: invokevirtual #280                // Method getRawYCoord:()Lorg/bouncycastle/math/ec/ECFieldElement;
      27: aload_0
      28: invokevirtual #283                // Method getRawZCoords:()[Lorg/bouncycastle/math/ec/ECFieldElement;
      31: invokevirtual #263                // Method org/bouncycastle/math/ec/ECCurve.createRawPoint:(Lorg/bouncycastle/math/ec/ECFieldElement;Lorg/bouncycastle/math/ec/ECFieldElement;[Lorg/bouncycastle/math/ec/ECFieldElement;)Lorg/bouncycastle/math/ec/ECPoint;
      34: areturn

  public org.bouncycastle.math.ec.ECPoint scaleXNegateY(org.bouncycastle.math.ec.ECFieldElement);
    Code:
       0: aload_0
       1: invokevirtual #275                // Method isInfinity:()Z
       4: ifeq          11
       7: aload_0
       8: goto          37
      11: aload_0
      12: invokevirtual #278                // Method getCurve:()Lorg/bouncycastle/math/ec/ECCurve;
      15: aload_0
      16: invokevirtual #279                // Method getRawXCoord:()Lorg/bouncycastle/math/ec/ECFieldElement;
      19: aload_1
      20: invokevirtual #271                // Method org/bouncycastle/math/ec/ECFieldElement.multiply:(Lorg/bouncycastle/math/ec/ECFieldElement;)Lorg/bouncycastle/math/ec/ECFieldElement;
      23: aload_0
      24: invokevirtual #280                // Method getRawYCoord:()Lorg/bouncycastle/math/ec/ECFieldElement;
      27: invokevirtual #269                // Method org/bouncycastle/math/ec/ECFieldElement.negate:()Lorg/bouncycastle/math/ec/ECFieldElement;
      30: aload_0
      31: invokevirtual #283                // Method getRawZCoords:()[Lorg/bouncycastle/math/ec/ECFieldElement;
      34: invokevirtual #263                // Method org/bouncycastle/math/ec/ECCurve.createRawPoint:(Lorg/bouncycastle/math/ec/ECFieldElement;Lorg/bouncycastle/math/ec/ECFieldElement;[Lorg/bouncycastle/math/ec/ECFieldElement;)Lorg/bouncycastle/math/ec/ECPoint;
      37: areturn

  public org.bouncycastle.math.ec.ECPoint scaleY(org.bouncycastle.math.ec.ECFieldElement);
    Code:
       0: aload_0
       1: invokevirtual #275                // Method isInfinity:()Z
       4: ifeq          11
       7: aload_0
       8: goto          34
      11: aload_0
      12: invokevirtual #278                // Method getCurve:()Lorg/bouncycastle/math/ec/ECCurve;
      15: aload_0
      16: invokevirtual #279                // Method getRawXCoord:()Lorg/bouncycastle/math/ec/ECFieldElement;
      19: aload_0
      20: invokevirtual #280                // Method getRawYCoord:()Lorg/bouncycastle/math/ec/ECFieldElement;
      23: aload_1
      24: invokevirtual #271                // Method org/bouncycastle/math/ec/ECFieldElement.multiply:(Lorg/bouncycastle/math/ec/ECFieldElement;)Lorg/bouncycastle/math/ec/ECFieldElement;
      27: aload_0
      28: invokevirtual #283                // Method getRawZCoords:()[Lorg/bouncycastle/math/ec/ECFieldElement;
      31: invokevirtual #263                // Method org/bouncycastle/math/ec/ECCurve.createRawPoint:(Lorg/bouncycastle/math/ec/ECFieldElement;Lorg/bouncycastle/math/ec/ECFieldElement;[Lorg/bouncycastle/math/ec/ECFieldElement;)Lorg/bouncycastle/math/ec/ECPoint;
      34: areturn

  public org.bouncycastle.math.ec.ECPoint scaleYNegateX(org.bouncycastle.math.ec.ECFieldElement);
    Code:
       0: aload_0
       1: invokevirtual #275                // Method isInfinity:()Z
       4: ifeq          11
       7: aload_0
       8: goto          37
      11: aload_0
      12: invokevirtual #278                // Method getCurve:()Lorg/bouncycastle/math/ec/ECCurve;
      15: aload_0
      16: invokevirtual #279                // Method getRawXCoord:()Lorg/bouncycastle/math/ec/ECFieldElement;
      19: invokevirtual #269                // Method org/bouncycastle/math/ec/ECFieldElement.negate:()Lorg/bouncycastle/math/ec/ECFieldElement;
      22: aload_0
      23: invokevirtual #280                // Method getRawYCoord:()Lorg/bouncycastle/math/ec/ECFieldElement;
      26: aload_1
      27: invokevirtual #271                // Method org/bouncycastle/math/ec/ECFieldElement.multiply:(Lorg/bouncycastle/math/ec/ECFieldElement;)Lorg/bouncycastle/math/ec/ECFieldElement;
      30: aload_0
      31: invokevirtual #283                // Method getRawZCoords:()[Lorg/bouncycastle/math/ec/ECFieldElement;
      34: invokevirtual #263                // Method org/bouncycastle/math/ec/ECCurve.createRawPoint:(Lorg/bouncycastle/math/ec/ECFieldElement;Lorg/bouncycastle/math/ec/ECFieldElement;[Lorg/bouncycastle/math/ec/ECFieldElement;)Lorg/bouncycastle/math/ec/ECPoint;
      37: areturn

  public boolean equals(org.bouncycastle.math.ec.ECPoint);
    Code:
       0: aconst_null
       1: aload_1
       2: if_acmpne     7
       5: iconst_0
       6: ireturn
       7: aload_0
       8: invokevirtual #278                // Method getCurve:()Lorg/bouncycastle/math/ec/ECCurve;
      11: astore_2
      12: aload_1
      13: invokevirtual #278                // Method getCurve:()Lorg/bouncycastle/math/ec/ECCurve;
      16: astore_3
      17: aconst_null
      18: aload_2
      19: if_acmpne     26
      22: iconst_1
      23: goto          27
      26: iconst_0
      27: istore        4
      29: aconst_null
      30: aload_3
      31: if_acmpne     38
      34: iconst_1
      35: goto          39
      38: iconst_0
      39: istore        5
      41: aload_0
      42: invokevirtual #275                // Method isInfinity:()Z
      45: istore        6
      47: aload_1
      48: invokevirtual #275                // Method isInfinity:()Z
      51: istore        7
      53: iload         6
      55: ifne          63
      58: iload         7
      60: ifeq          97
      63: iload         6
      65: ifeq          95
      68: iload         7
      70: ifeq          95
      73: iload         4
      75: ifne          91
      78: iload         5
      80: ifne          91
      83: aload_2
      84: aload_3
      85: invokevirtual #255                // Method org/bouncycastle/math/ec/ECCurve.equals:(Lorg/bouncycastle/math/ec/ECCurve;)Z
      88: ifeq          95
      91: iconst_1
      92: goto          96
      95: iconst_0
      96: ireturn
      97: aload_0
      98: astore        8
     100: aload_1
     101: astore        9
     103: iload         4
     105: ifeq          116
     108: iload         5
     110: ifeq          116
     113: goto          193
     116: iload         4
     118: ifeq          131
     121: aload         9
     123: invokevirtual #286                // Method normalize:()Lorg/bouncycastle/math/ec/ECPoint;
     126: astore        9
     128: goto          193
     131: iload         5
     133: ifeq          146
     136: aload         8
     138: invokevirtual #286                // Method normalize:()Lorg/bouncycastle/math/ec/ECPoint;
     141: astore        8
     143: goto          193
     146: aload_2
     147: aload_3
     148: invokevirtual #255                // Method org/bouncycastle/math/ec/ECCurve.equals:(Lorg/bouncycastle/math/ec/ECCurve;)Z
     151: ifne          156
     154: iconst_0
     155: ireturn
     156: iconst_2
     157: anewarray     #124                // class org/bouncycastle/math/ec/ECPoint
     160: dup
     161: iconst_0
     162: aload_0
     163: aastore
     164: dup
     165: iconst_1
     166: aload_2
     167: aload         9
     169: invokevirtual #261                // Method org/bouncycastle/math/ec/ECCurve.importPoint:(Lorg/bouncycastle/math/ec/ECPoint;)Lorg/bouncycastle/math/ec/ECPoint;
     172: aastore
     173: astore        10
     175: aload_2
     176: aload         10
     178: invokevirtual #258                // Method org/bouncycastle/math/ec/ECCurve.normalizeAll:([Lorg/bouncycastle/math/ec/ECPoint;)V
     181: aload         10
     183: iconst_0
     184: aaload
     185: astore        8
     187: aload         10
     189: iconst_1
     190: aaload
     191: astore        9
     193: aload         8
     195: invokevirtual #281                // Method getXCoord:()Lorg/bouncycastle/math/ec/ECFieldElement;
     198: aload         9
     200: invokevirtual #281                // Method getXCoord:()Lorg/bouncycastle/math/ec/ECFieldElement;
     203: invokevirtual #242                // Method java/lang/Object.equals:(Ljava/lang/Object;)Z
     206: ifeq          229
     209: aload         8
     211: invokevirtual #282                // Method getYCoord:()Lorg/bouncycastle/math/ec/ECFieldElement;
     214: aload         9
     216: invokevirtual #282                // Method getYCoord:()Lorg/bouncycastle/math/ec/ECFieldElement;
     219: invokevirtual #242                // Method java/lang/Object.equals:(Ljava/lang/Object;)Z
     222: ifeq          229
     225: iconst_1
     226: goto          230
     229: iconst_0
     230: ireturn

  public boolean equals(java.lang.Object);
    Code:
       0: aload_1
       1: aload_0
       2: if_acmpne     7
       5: iconst_1
       6: ireturn
       7: aload_1
       8: instanceof    #124                // class org/bouncycastle/math/ec/ECPoint
      11: ifne          16
      14: iconst_0
      15: ireturn
      16: aload_0
      17: aload_1
      18: checkcast     #124                // class org/bouncycastle/math/ec/ECPoint
      21: invokevirtual #288                // Method equals:(Lorg/bouncycastle/math/ec/ECPoint;)Z
      24: ireturn

  public int hashCode();
    Code:
       0: aload_0
       1: invokevirtual #278                // Method getCurve:()Lorg/bouncycastle/math/ec/ECCurve;
       4: astore_1
       5: aconst_null
       6: aload_1
       7: if_acmpne     14
      10: iconst_0
      11: goto          20
      14: aload_1
      15: invokevirtual #252                // Method org/bouncycastle/math/ec/ECCurve.hashCode:()I
      18: iconst_m1
      19: ixor
      20: istore_2
      21: aload_0
      22: invokevirtual #275                // Method isInfinity:()Z
      25: ifne          60
      28: aload_0
      29: invokevirtual #286                // Method normalize:()Lorg/bouncycastle/math/ec/ECPoint;
      32: astore_3
      33: iload_2
      34: aload_3
      35: invokevirtual #281                // Method getXCoord:()Lorg/bouncycastle/math/ec/ECFieldElement;
      38: invokevirtual #240                // Method java/lang/Object.hashCode:()I
      41: bipush        17
      43: imul
      44: ixor
      45: istore_2
      46: iload_2
      47: aload_3
      48: invokevirtual #282                // Method getYCoord:()Lorg/bouncycastle/math/ec/ECFieldElement;
      51: invokevirtual #240                // Method java/lang/Object.hashCode:()I
      54: sipush        257
      57: imul
      58: ixor
      59: istore_2
      60: iload_2
      61: ireturn

  public java.lang.String toString();
    Code:
       0: aload_0
       1: invokevirtual #275                // Method isInfinity:()Z
       4: ifeq          10
       7: ldc           #3                  // String INF
       9: areturn
      10: new           #115                // class java/lang/StringBuffer
      13: dup
      14: invokespecial #243                // Method java/lang/StringBuffer."<init>":()V
      17: astore_1
      18: aload_1
      19: bipush        40
      21: invokevirtual #245                // Method java/lang/StringBuffer.append:(C)Ljava/lang/StringBuffer;
      24: pop
      25: aload_1
      26: aload_0
      27: invokevirtual #279                // Method getRawXCoord:()Lorg/bouncycastle/math/ec/ECFieldElement;
      30: invokevirtual #246                // Method java/lang/StringBuffer.append:(Ljava/lang/Object;)Ljava/lang/StringBuffer;
      33: pop
      34: aload_1
      35: bipush        44
      37: invokevirtual #245                // Method java/lang/StringBuffer.append:(C)Ljava/lang/StringBuffer;
      40: pop
      41: aload_1
      42: aload_0
      43: invokevirtual #280                // Method getRawYCoord:()Lorg/bouncycastle/math/ec/ECFieldElement;
      46: invokevirtual #246                // Method java/lang/StringBuffer.append:(Ljava/lang/Object;)Ljava/lang/StringBuffer;
      49: pop
      50: iconst_0
      51: istore_2
      52: iload_2
      53: aload_0
      54: getfield      #237                // Field zs:[Lorg/bouncycastle/math/ec/ECFieldElement;
      57: arraylength
      58: if_icmpge     85
      61: aload_1
      62: bipush        44
      64: invokevirtual #245                // Method java/lang/StringBuffer.append:(C)Ljava/lang/StringBuffer;
      67: pop
      68: aload_1
      69: aload_0
      70: getfield      #237                // Field zs:[Lorg/bouncycastle/math/ec/ECFieldElement;
      73: iload_2
      74: aaload
      75: invokevirtual #246                // Method java/lang/StringBuffer.append:(Ljava/lang/Object;)Ljava/lang/StringBuffer;
      78: pop
      79: iinc          2, 1
      82: goto          52
      85: aload_1
      86: bipush        41
      88: invokevirtual #245                // Method java/lang/StringBuffer.append:(C)Ljava/lang/StringBuffer;
      91: pop
      92: aload_1
      93: invokevirtual #244                // Method java/lang/StringBuffer.toString:()Ljava/lang/String;
      96: areturn

  public byte[] getEncoded(boolean);
    Code:
       0: aload_0
       1: invokevirtual #275                // Method isInfinity:()Z
       4: ifeq          11
       7: iconst_1
       8: newarray       byte
      10: areturn
      11: aload_0
      12: invokevirtual #286                // Method normalize:()Lorg/bouncycastle/math/ec/ECPoint;
      15: astore_2
      16: aload_2
      17: invokevirtual #281                // Method getXCoord:()Lorg/bouncycastle/math/ec/ECFieldElement;
      20: invokevirtual #267                // Method org/bouncycastle/math/ec/ECFieldElement.getEncoded:()[B
      23: astore_3
      24: iload_1
      25: ifeq          66
      28: aload_3
      29: arraylength
      30: iconst_1
      31: iadd
      32: newarray       byte
      34: astore        4
      36: aload         4
      38: iconst_0
      39: aload_2
      40: invokevirtual #274                // Method getCompressionYTilde:()Z
      43: ifeq          50
      46: iconst_3
      47: goto          51
      50: iconst_2
      51: i2b
      52: bastore
      53: aload_3
      54: iconst_0
      55: aload         4
      57: iconst_1
      58: aload_3
      59: arraylength
      60: invokestatic  #247                // Method java/lang/System.arraycopy:(Ljava/lang/Object;ILjava/lang/Object;II)V
      63: aload         4
      65: areturn
      66: aload_2
      67: invokevirtual #282                // Method getYCoord:()Lorg/bouncycastle/math/ec/ECFieldElement;
      70: invokevirtual #267                // Method org/bouncycastle/math/ec/ECFieldElement.getEncoded:()[B
      73: astore        4
      75: aload_3
      76: arraylength
      77: aload         4
      79: arraylength
      80: iadd
      81: iconst_1
      82: iadd
      83: newarray       byte
      85: astore        5
      87: aload         5
      89: iconst_0
      90: iconst_4
      91: bastore
      92: aload_3
      93: iconst_0
      94: aload         5
      96: iconst_1
      97: aload_3
      98: arraylength
      99: invokestatic  #247                // Method java/lang/System.arraycopy:(Ljava/lang/Object;ILjava/lang/Object;II)V
     102: aload         4
     104: iconst_0
     105: aload         5
     107: aload_3
     108: arraylength
     109: iconst_1
     110: iadd
     111: aload         4
     113: arraylength
     114: invokestatic  #247                // Method java/lang/System.arraycopy:(Ljava/lang/Object;ILjava/lang/Object;II)V
     117: aload         5
     119: areturn

  protected abstract boolean getCompressionYTilde();

  public abstract org.bouncycastle.math.ec.ECPoint add(org.bouncycastle.math.ec.ECPoint);

  public abstract org.bouncycastle.math.ec.ECPoint negate();

  public abstract org.bouncycastle.math.ec.ECPoint subtract(org.bouncycastle.math.ec.ECPoint);

  public org.bouncycastle.math.ec.ECPoint timesPow2(int);
    Code:
       0: iload_1
       1: ifge          14
       4: new           #112                // class java/lang/IllegalArgumentException
       7: dup
       8: ldc           #1                  // String \'e\' cannot be negative
      10: invokespecial #238                // Method java/lang/IllegalArgumentException."<init>":(Ljava/lang/String;)V
      13: athrow
      14: aload_0
      15: astore_2
      16: iinc          1, -1
      19: iload_1
      20: iflt          31
      23: aload_2
      24: invokevirtual #287                // Method twice:()Lorg/bouncycastle/math/ec/ECPoint;
      27: astore_2
      28: goto          16
      31: aload_2
      32: areturn

  public abstract org.bouncycastle.math.ec.ECPoint twice();

  public org.bouncycastle.math.ec.ECPoint twicePlus(org.bouncycastle.math.ec.ECPoint);
    Code:
       0: aload_0
       1: invokevirtual #287                // Method twice:()Lorg/bouncycastle/math/ec/ECPoint;
       4: aload_1
       5: invokevirtual #291                // Method add:(Lorg/bouncycastle/math/ec/ECPoint;)Lorg/bouncycastle/math/ec/ECPoint;
       8: areturn

  public org.bouncycastle.math.ec.ECPoint threeTimes();
    Code:
       0: aload_0
       1: aload_0
       2: invokevirtual #292                // Method twicePlus:(Lorg/bouncycastle/math/ec/ECPoint;)Lorg/bouncycastle/math/ec/ECPoint;
       5: areturn

  public org.bouncycastle.math.ec.ECPoint multiply(java.math.BigInteger);
    Code:
       0: aload_0
       1: invokevirtual #278                // Method getCurve:()Lorg/bouncycastle/math/ec/ECCurve;
       4: invokevirtual #257                // Method org/bouncycastle/math/ec/ECCurve.getMultiplier:()Lorg/bouncycastle/math/ec/ECMultiplier;
       7: aload_0
       8: aload_1
       9: invokeinterface #297,  3          // InterfaceMethod org/bouncycastle/math/ec/ECMultiplier.multiply:(Lorg/bouncycastle/math/ec/ECPoint;Ljava/math/BigInteger;)Lorg/bouncycastle/math/ec/ECPoint;
      14: areturn

  static {};
    Code:
       0: iconst_0
       1: anewarray     #122                // class org/bouncycastle/math/ec/ECFieldElement
       4: putstatic     #236                // Field EMPTY_ZS:[Lorg/bouncycastle/math/ec/ECFieldElement;
       7: return
}
