Compiled from "EventFiringMouse.java"
public class org.openqa.selenium.support.events.internal.EventFiringMouse implements org.openqa.selenium.Mouse {
  private final org.openqa.selenium.WebDriver driver;

  private final org.openqa.selenium.support.events.WebDriverEventListener dispatcher;

  private final org.openqa.selenium.Mouse mouse;

  public org.openqa.selenium.support.events.internal.EventFiringMouse(org.openqa.selenium.WebDriver, org.openqa.selenium.support.events.WebDriverEventListener);
    Code:
       0: aload_0
       1: invokespecial #1                  // Method java/lang/Object."<init>":()V
       4: aload_0
       5: aload_1
       6: putfield      #2                  // Field driver:Lorg/openqa/selenium/WebDriver;
       9: aload_0
      10: aload_2
      11: putfield      #3                  // Field dispatcher:Lorg/openqa/selenium/support/events/WebDriverEventListener;
      14: aload_0
      15: aload_0
      16: getfield      #2                  // Field driver:Lorg/openqa/selenium/WebDriver;
      19: checkcast     #4                  // class org/openqa/selenium/HasInputDevices
      22: invokeinterface #5,  1            // InterfaceMethod org/openqa/selenium/HasInputDevices.getMouse:()Lorg/openqa/selenium/Mouse;
      27: putfield      #6                  // Field mouse:Lorg/openqa/selenium/Mouse;
      30: return

  public void click(org.openqa.selenium.interactions.internal.Coordinates);
    Code:
       0: aload_0
       1: getfield      #6                  // Field mouse:Lorg/openqa/selenium/Mouse;
       4: aload_1
       5: invokeinterface #7,  2            // InterfaceMethod org/openqa/selenium/Mouse.click:(Lorg/openqa/selenium/interactions/internal/Coordinates;)V
      10: return

  public void doubleClick(org.openqa.selenium.interactions.internal.Coordinates);
    Code:
       0: aload_0
       1: getfield      #6                  // Field mouse:Lorg/openqa/selenium/Mouse;
       4: aload_1
       5: invokeinterface #8,  2            // InterfaceMethod org/openqa/selenium/Mouse.doubleClick:(Lorg/openqa/selenium/interactions/internal/Coordinates;)V
      10: return

  public void mouseDown(org.openqa.selenium.interactions.internal.Coordinates);
    Code:
       0: aload_0
       1: getfield      #6                  // Field mouse:Lorg/openqa/selenium/Mouse;
       4: aload_1
       5: invokeinterface #9,  2            // InterfaceMethod org/openqa/selenium/Mouse.mouseDown:(Lorg/openqa/selenium/interactions/internal/Coordinates;)V
      10: return

  public void mouseUp(org.openqa.selenium.interactions.internal.Coordinates);
    Code:
       0: aload_0
       1: getfield      #6                  // Field mouse:Lorg/openqa/selenium/Mouse;
       4: aload_1
       5: invokeinterface #10,  2           // InterfaceMethod org/openqa/selenium/Mouse.mouseUp:(Lorg/openqa/selenium/interactions/internal/Coordinates;)V
      10: return

  public void mouseMove(org.openqa.selenium.interactions.internal.Coordinates);
    Code:
       0: aload_0
       1: getfield      #6                  // Field mouse:Lorg/openqa/selenium/Mouse;
       4: aload_1
       5: invokeinterface #11,  2           // InterfaceMethod org/openqa/selenium/Mouse.mouseMove:(Lorg/openqa/selenium/interactions/internal/Coordinates;)V
      10: return

  public void mouseMove(org.openqa.selenium.interactions.internal.Coordinates, long, long);
    Code:
       0: aload_0
       1: getfield      #6                  // Field mouse:Lorg/openqa/selenium/Mouse;
       4: aload_1
       5: lload_2
       6: lload         4
       8: invokeinterface #12,  6           // InterfaceMethod org/openqa/selenium/Mouse.mouseMove:(Lorg/openqa/selenium/interactions/internal/Coordinates;JJ)V
      13: return

  public void contextClick(org.openqa.selenium.interactions.internal.Coordinates);
    Code:
       0: aload_0
       1: getfield      #6                  // Field mouse:Lorg/openqa/selenium/Mouse;
       4: aload_1
       5: invokeinterface #13,  2           // InterfaceMethod org/openqa/selenium/Mouse.contextClick:(Lorg/openqa/selenium/interactions/internal/Coordinates;)V
      10: return
}
