Compiled from "EventFiringKeyboard.java"
public class org.openqa.selenium.support.events.internal.EventFiringKeyboard implements org.openqa.selenium.Keyboard {
  private final org.openqa.selenium.WebDriver driver;

  private final org.openqa.selenium.support.events.WebDriverEventListener dispatcher;

  private final org.openqa.selenium.Keyboard keyboard;

  public org.openqa.selenium.support.events.internal.EventFiringKeyboard(org.openqa.selenium.WebDriver, org.openqa.selenium.support.events.WebDriverEventListener);
    Code:
       0: aload_0
       1: invokespecial #1                  // Method java/lang/Object."<init>":()V
       4: aload_0
       5: aload_1
       6: putfield      #2                  // Field driver:Lorg/openqa/selenium/WebDriver;
       9: aload_0
      10: aload_2
      11: putfield      #3                  // Field dispatcher:Lorg/openqa/selenium/support/events/WebDriverEventListener;
      14: aload_0
      15: aload_0
      16: getfield      #2                  // Field driver:Lorg/openqa/selenium/WebDriver;
      19: checkcast     #4                  // class org/openqa/selenium/HasInputDevices
      22: invokeinterface #5,  1            // InterfaceMethod org/openqa/selenium/HasInputDevices.getKeyboard:()Lorg/openqa/selenium/Keyboard;
      27: putfield      #6                  // Field keyboard:Lorg/openqa/selenium/Keyboard;
      30: return

  public void sendKeys(java.lang.CharSequence...);
    Code:
       0: aload_0
       1: getfield      #6                  // Field keyboard:Lorg/openqa/selenium/Keyboard;
       4: aload_1
       5: invokeinterface #7,  2            // InterfaceMethod org/openqa/selenium/Keyboard.sendKeys:([Ljava/lang/CharSequence;)V
      10: return

  public void pressKey(org.openqa.selenium.Keys);
    Code:
       0: aload_0
       1: getfield      #6                  // Field keyboard:Lorg/openqa/selenium/Keyboard;
       4: aload_1
       5: invokeinterface #8,  2            // InterfaceMethod org/openqa/selenium/Keyboard.pressKey:(Lorg/openqa/selenium/Keys;)V
      10: return

  public void releaseKey(org.openqa.selenium.Keys);
    Code:
       0: aload_0
       1: getfield      #6                  // Field keyboard:Lorg/openqa/selenium/Keyboard;
       4: aload_1
       5: invokeinterface #9,  2            // InterfaceMethod org/openqa/selenium/Keyboard.releaseKey:(Lorg/openqa/selenium/Keys;)V
      10: return
}
