Compiled from "FixedPrincipalExtractor.java"
public class org.springframework.boot.autoconfigure.security.oauth2.resource.FixedPrincipalExtractor implements org.springframework.boot.autoconfigure.security.oauth2.resource.PrincipalExtractor {
  private static final java.lang.String[] PRINCIPAL_KEYS;

  public org.springframework.boot.autoconfigure.security.oauth2.resource.FixedPrincipalExtractor();
    Code:
       0: aload_0
       1: invokespecial #1                  // Method java/lang/Object."<init>":()V
       4: return

  public java.lang.Object extractPrincipal(java.util.Map<java.lang.String, java.lang.Object>);
    Code:
       0: getstatic     #2                  // Field PRINCIPAL_KEYS:[Ljava/lang/String;
       3: astore_2
       4: aload_2
       5: arraylength
       6: istore_3
       7: iconst_0
       8: istore        4
      10: iload         4
      12: iload_3
      13: if_icmpge     48
      16: aload_2
      17: iload         4
      19: aaload
      20: astore        5
      22: aload_1
      23: aload         5
      25: invokeinterface #3,  2            // InterfaceMethod java/util/Map.containsKey:(Ljava/lang/Object;)Z
      30: ifeq          42
      33: aload_1
      34: aload         5
      36: invokeinterface #4,  2            // InterfaceMethod java/util/Map.get:(Ljava/lang/Object;)Ljava/lang/Object;
      41: areturn
      42: iinc          4, 1
      45: goto          10
      48: aconst_null
      49: areturn

  static {};
    Code:
       0: bipush        7
       2: anewarray     #5                  // class java/lang/String
       5: dup
       6: iconst_0
       7: ldc           #6                  // String user
       9: aastore
      10: dup
      11: iconst_1
      12: ldc           #7                  // String username
      14: aastore
      15: dup
      16: iconst_2
      17: ldc           #8                  // String userid
      19: aastore
      20: dup
      21: iconst_3
      22: ldc           #9                  // String user_id
      24: aastore
      25: dup
      26: iconst_4
      27: ldc           #10                 // String login
      29: aastore
      30: dup
      31: iconst_5
      32: ldc           #11                 // String id
      34: aastore
      35: dup
      36: bipush        6
      38: ldc           #12                 // String name
      40: aastore
      41: putstatic     #2                  // Field PRINCIPAL_KEYS:[Ljava/lang/String;
      44: return
}
