Compiled from "MultiDelimiterStringSearchInterpolator.java"
public class org.codehaus.plexus.interpolation.multi.MultiDelimiterStringSearchInterpolator implements org.codehaus.plexus.interpolation.Interpolator {
  private static final int MAX_TRIES;

  private java.util.Map existingAnswers;

  private java.util.List valueSources;

  private java.util.List postProcessors;

  private boolean cacheAnswers;

  private java.util.LinkedHashSet delimiters;

  private java.lang.String escapeString;

  public org.codehaus.plexus.interpolation.multi.MultiDelimiterStringSearchInterpolator();
    Code:
       0: aload_0
       1: invokespecial #1                  // Method java/lang/Object."<init>":()V
       4: aload_0
       5: new           #2                  // class java/util/HashMap
       8: dup
       9: invokespecial #3                  // Method java/util/HashMap."<init>":()V
      12: putfield      #4                  // Field existingAnswers:Ljava/util/Map;
      15: aload_0
      16: new           #5                  // class java/util/ArrayList
      19: dup
      20: invokespecial #6                  // Method java/util/ArrayList."<init>":()V
      23: putfield      #7                  // Field valueSources:Ljava/util/List;
      26: aload_0
      27: new           #5                  // class java/util/ArrayList
      30: dup
      31: invokespecial #6                  // Method java/util/ArrayList."<init>":()V
      34: putfield      #8                  // Field postProcessors:Ljava/util/List;
      37: aload_0
      38: iconst_0
      39: putfield      #9                  // Field cacheAnswers:Z
      42: aload_0
      43: new           #10                 // class java/util/LinkedHashSet
      46: dup
      47: invokespecial #11                 // Method java/util/LinkedHashSet."<init>":()V
      50: putfield      #12                 // Field delimiters:Ljava/util/LinkedHashSet;
      53: aload_0
      54: getfield      #12                 // Field delimiters:Ljava/util/LinkedHashSet;
      57: getstatic     #13                 // Field org/codehaus/plexus/interpolation/multi/DelimiterSpecification.DEFAULT_SPEC:Lorg/codehaus/plexus/interpolation/multi/DelimiterSpecification;
      60: invokevirtual #14                 // Method java/util/LinkedHashSet.add:(Ljava/lang/Object;)Z
      63: pop
      64: return

  public org.codehaus.plexus.interpolation.multi.MultiDelimiterStringSearchInterpolator addDelimiterSpec(java.lang.String);
    Code:
       0: aload_1
       1: ifnonnull     6
       4: aload_0
       5: areturn
       6: aload_0
       7: getfield      #12                 // Field delimiters:Ljava/util/LinkedHashSet;
      10: aload_1
      11: invokestatic  #15                 // Method org/codehaus/plexus/interpolation/multi/DelimiterSpecification.parse:(Ljava/lang/String;)Lorg/codehaus/plexus/interpolation/multi/DelimiterSpecification;
      14: invokevirtual #14                 // Method java/util/LinkedHashSet.add:(Ljava/lang/Object;)Z
      17: pop
      18: aload_0
      19: areturn

  public boolean removeDelimiterSpec(java.lang.String);
    Code:
       0: aload_1
       1: ifnonnull     6
       4: iconst_0
       5: ireturn
       6: aload_0
       7: getfield      #12                 // Field delimiters:Ljava/util/LinkedHashSet;
      10: aload_1
      11: invokestatic  #15                 // Method org/codehaus/plexus/interpolation/multi/DelimiterSpecification.parse:(Ljava/lang/String;)Lorg/codehaus/plexus/interpolation/multi/DelimiterSpecification;
      14: invokevirtual #16                 // Method java/util/LinkedHashSet.remove:(Ljava/lang/Object;)Z
      17: ireturn

  public org.codehaus.plexus.interpolation.multi.MultiDelimiterStringSearchInterpolator withValueSource(org.codehaus.plexus.interpolation.ValueSource);
    Code:
       0: aload_0
       1: aload_1
       2: invokevirtual #17                 // Method addValueSource:(Lorg/codehaus/plexus/interpolation/ValueSource;)V
       5: aload_0
       6: areturn

  public org.codehaus.plexus.interpolation.multi.MultiDelimiterStringSearchInterpolator withPostProcessor(org.codehaus.plexus.interpolation.InterpolationPostProcessor);
    Code:
       0: aload_0
       1: aload_1
       2: invokevirtual #18                 // Method addPostProcessor:(Lorg/codehaus/plexus/interpolation/InterpolationPostProcessor;)V
       5: aload_0
       6: areturn

  public void addValueSource(org.codehaus.plexus.interpolation.ValueSource);
    Code:
       0: aload_0
       1: getfield      #7                  // Field valueSources:Ljava/util/List;
       4: aload_1
       5: invokeinterface #19,  2           // InterfaceMethod java/util/List.add:(Ljava/lang/Object;)Z
      10: pop
      11: return

  public void removeValuesSource(org.codehaus.plexus.interpolation.ValueSource);
    Code:
       0: aload_0
       1: getfield      #7                  // Field valueSources:Ljava/util/List;
       4: aload_1
       5: invokeinterface #20,  2           // InterfaceMethod java/util/List.remove:(Ljava/lang/Object;)Z
      10: pop
      11: return

  public void addPostProcessor(org.codehaus.plexus.interpolation.InterpolationPostProcessor);
    Code:
       0: aload_0
       1: getfield      #8                  // Field postProcessors:Ljava/util/List;
       4: aload_1
       5: invokeinterface #19,  2           // InterfaceMethod java/util/List.add:(Ljava/lang/Object;)Z
      10: pop
      11: return

  public void removePostProcessor(org.codehaus.plexus.interpolation.InterpolationPostProcessor);
    Code:
       0: aload_0
       1: getfield      #8                  // Field postProcessors:Ljava/util/List;
       4: aload_1
       5: invokeinterface #20,  2           // InterfaceMethod java/util/List.remove:(Ljava/lang/Object;)Z
      10: pop
      11: return

  public java.lang.String interpolate(java.lang.String, java.lang.String) throws org.codehaus.plexus.interpolation.InterpolationException;
    Code:
       0: aload_0
       1: aload_1
       2: new           #21                 // class org/codehaus/plexus/interpolation/SimpleRecursionInterceptor
       5: dup
       6: invokespecial #22                 // Method org/codehaus/plexus/interpolation/SimpleRecursionInterceptor."<init>":()V
       9: invokevirtual #23                 // Method interpolate:(Ljava/lang/String;Lorg/codehaus/plexus/interpolation/RecursionInterceptor;)Ljava/lang/String;
      12: areturn

  public java.lang.String interpolate(java.lang.String, java.lang.String, org.codehaus.plexus.interpolation.RecursionInterceptor) throws org.codehaus.plexus.interpolation.InterpolationException;
    Code:
       0: aload_0
       1: aload_1
       2: aload_3
       3: invokevirtual #23                 // Method interpolate:(Ljava/lang/String;Lorg/codehaus/plexus/interpolation/RecursionInterceptor;)Ljava/lang/String;
       6: areturn

  public java.lang.String interpolate(java.lang.String) throws org.codehaus.plexus.interpolation.InterpolationException;
    Code:
       0: aload_0
       1: aload_1
       2: new           #21                 // class org/codehaus/plexus/interpolation/SimpleRecursionInterceptor
       5: dup
       6: invokespecial #22                 // Method org/codehaus/plexus/interpolation/SimpleRecursionInterceptor."<init>":()V
       9: invokevirtual #23                 // Method interpolate:(Ljava/lang/String;Lorg/codehaus/plexus/interpolation/RecursionInterceptor;)Ljava/lang/String;
      12: areturn

  public java.lang.String interpolate(java.lang.String, org.codehaus.plexus.interpolation.RecursionInterceptor) throws org.codehaus.plexus.interpolation.InterpolationException;
    Code:
       0: aload_0
       1: aload_1
       2: aload_2
       3: new           #24                 // class java/util/HashSet
       6: dup
       7: invokespecial #25                 // Method java/util/HashSet."<init>":()V
      10: invokespecial #26                 // Method interpolate:(Ljava/lang/String;Lorg/codehaus/plexus/interpolation/RecursionInterceptor;Ljava/util/Set;)Ljava/lang/String;
      13: astore_3
      14: aload_0
      15: getfield      #9                  // Field cacheAnswers:Z
      18: ifne          30
      21: aload_0
      22: getfield      #4                  // Field existingAnswers:Ljava/util/Map;
      25: invokeinterface #27,  1           // InterfaceMethod java/util/Map.clear:()V
      30: aload_3
      31: areturn
      32: astore        4
      34: aload_0
      35: getfield      #9                  // Field cacheAnswers:Z
      38: ifne          50
      41: aload_0
      42: getfield      #4                  // Field existingAnswers:Ljava/util/Map;
      45: invokeinterface #27,  1           // InterfaceMethod java/util/Map.clear:()V
      50: aload         4
      52: athrow
    Exception table:
       from    to  target type
           0    14    32   any
          32    34    32   any

  private java.lang.String interpolate(java.lang.String, org.codehaus.plexus.interpolation.RecursionInterceptor, java.util.Set) throws org.codehaus.plexus.interpolation.InterpolationException;
    Code:
       0: aload_1
       1: ifnonnull     7
       4: ldc           #28                 // String
       6: areturn
       7: new           #29                 // class java/lang/StringBuffer
      10: dup
      11: aload_1
      12: invokevirtual #30                 // Method java/lang/String.length:()I
      15: iconst_2
      16: imul
      17: invokespecial #31                 // Method java/lang/StringBuffer."<init>":(I)V
      20: astore        4
      22: aload_1
      23: astore        5
      25: iconst_0
      26: istore        6
      28: iinc          6, 1
      31: aload         4
      33: invokevirtual #32                 // Method java/lang/StringBuffer.length:()I
      36: ifle          52
      39: aload         4
      41: invokevirtual #33                 // Method java/lang/StringBuffer.toString:()Ljava/lang/String;
      44: astore        5
      46: aload         4
      48: iconst_0
      49: invokevirtual #34                 // Method java/lang/StringBuffer.setLength:(I)V
      52: iconst_m1
      53: istore        7
      55: iconst_m1
      56: istore        8
      58: aconst_null
      59: astore        9
      61: aload_0
      62: aload_1
      63: iload         8
      65: invokespecial #35                 // Method select:(Ljava/lang/String;I)Lorg/codehaus/plexus/interpolation/multi/DelimiterSpecification;
      68: dup
      69: astore        9
      71: ifnull        623
      74: aload         9
      76: invokevirtual #36                 // Method org/codehaus/plexus/interpolation/multi/DelimiterSpecification.getBegin:()Ljava/lang/String;
      79: astore        10
      81: aload         9
      83: invokevirtual #37                 // Method org/codehaus/plexus/interpolation/multi/DelimiterSpecification.getEnd:()Ljava/lang/String;
      86: astore        11
      88: aload         9
      90: invokevirtual #38                 // Method org/codehaus/plexus/interpolation/multi/DelimiterSpecification.getNextStartIndex:()I
      93: istore        7
      95: aload         4
      97: aload_1
      98: iload         8
     100: iconst_1
     101: iadd
     102: iload         7
     104: invokevirtual #39                 // Method java/lang/String.substring:(II)Ljava/lang/String;
     107: invokevirtual #40                 // Method java/lang/StringBuffer.append:(Ljava/lang/String;)Ljava/lang/StringBuffer;
     110: pop
     111: aload_1
     112: aload         11
     114: iload         7
     116: iconst_1
     117: iadd
     118: invokevirtual #41                 // Method java/lang/String.indexOf:(Ljava/lang/String;I)I
     121: istore        8
     123: iload         8
     125: ifge          131
     128: goto          623
     131: aload_1
     132: iload         7
     134: iload         8
     136: aload         11
     138: invokevirtual #30                 // Method java/lang/String.length:()I
     141: iadd
     142: invokevirtual #39                 // Method java/lang/String.substring:(II)Ljava/lang/String;
     145: astore        12
     147: aload         12
     149: aload         10
     151: invokevirtual #30                 // Method java/lang/String.length:()I
     154: aload         12
     156: invokevirtual #30                 // Method java/lang/String.length:()I
     159: aload         11
     161: invokevirtual #30                 // Method java/lang/String.length:()I
     164: isub
     165: invokevirtual #39                 // Method java/lang/String.substring:(II)Ljava/lang/String;
     168: astore        13
     170: iload         7
     172: iflt          276
     175: aload_0
     176: getfield      #42                 // Field escapeString:Ljava/lang/String;
     179: ifnull        276
     182: aload_0
     183: getfield      #42                 // Field escapeString:Ljava/lang/String;
     186: invokevirtual #30                 // Method java/lang/String.length:()I
     189: ifle          276
     192: iload         7
     194: ifne          201
     197: iconst_0
     198: goto          211
     201: iload         7
     203: aload_0
     204: getfield      #42                 // Field escapeString:Ljava/lang/String;
     207: invokevirtual #30                 // Method java/lang/String.length:()I
     210: isub
     211: istore        14
     213: iload         14
     215: iflt          276
     218: aload_1
     219: iload         14
     221: iload         7
     223: invokevirtual #39                 // Method java/lang/String.substring:(II)Ljava/lang/String;
     226: astore        15
     228: aload         15
     230: ifnull        276
     233: aload_0
     234: getfield      #42                 // Field escapeString:Ljava/lang/String;
     237: aload         15
     239: invokevirtual #43                 // Method java/lang/String.equals:(Ljava/lang/Object;)Z
     242: ifeq          276
     245: aload         4
     247: aload         12
     249: invokevirtual #40                 // Method java/lang/StringBuffer.append:(Ljava/lang/String;)Ljava/lang/StringBuffer;
     252: pop
     253: aload         4
     255: iload         14
     257: iload         14
     259: aload_0
     260: getfield      #42                 // Field escapeString:Ljava/lang/String;
     263: invokevirtual #30                 // Method java/lang/String.length:()I
     266: iadd
     267: ldc           #28                 // String
     269: invokevirtual #44                 // Method java/lang/StringBuffer.replace:(IILjava/lang/String;)Ljava/lang/StringBuffer;
     272: pop
     273: goto          61
     276: iconst_0
     277: istore        14
     279: aload_3
     280: aload         12
     282: invokeinterface #45,  2           // InterfaceMethod java/util/Set.contains:(Ljava/lang/Object;)Z
     287: ifne          589
     290: aload         13
     292: ldc           #46                 // String .
     294: invokevirtual #47                 // Method java/lang/String.startsWith:(Ljava/lang/String;)Z
     297: ifeq          308
     300: aload         13
     302: iconst_1
     303: invokevirtual #48                 // Method java/lang/String.substring:(I)Ljava/lang/String;
     306: astore        13
     308: aload_2
     309: aload         13
     311: invokeinterface #49,  2           // InterfaceMethod org/codehaus/plexus/interpolation/RecursionInterceptor.hasRecursiveExpression:(Ljava/lang/String;)Z
     316: ifeq          332
     319: new           #50                 // class org/codehaus/plexus/interpolation/InterpolationCycleException
     322: dup
     323: aload_2
     324: aload         13
     326: aload         12
     328: invokespecial #51                 // Method org/codehaus/plexus/interpolation/InterpolationCycleException."<init>":(Lorg/codehaus/plexus/interpolation/RecursionInterceptor;Ljava/lang/String;Ljava/lang/String;)V
     331: athrow
     332: aload_2
     333: aload         13
     335: invokeinterface #52,  2           // InterfaceMethod org/codehaus/plexus/interpolation/RecursionInterceptor.expressionResolutionStarted:(Ljava/lang/String;)V
     340: aload_0
     341: getfield      #4                  // Field existingAnswers:Ljava/util/Map;
     344: aload         13
     346: invokeinterface #53,  2           // InterfaceMethod java/util/Map.get:(Ljava/lang/Object;)Ljava/lang/Object;
     351: astore        15
     353: aconst_null
     354: astore        16
     356: aload_0
     357: getfield      #7                  // Field valueSources:Ljava/util/List;
     360: invokeinterface #54,  1           // InterfaceMethod java/util/List.iterator:()Ljava/util/Iterator;
     365: astore        17
     367: aload         17
     369: invokeinterface #55,  1           // InterfaceMethod java/util/Iterator.hasNext:()Z
     374: ifeq          434
     377: aload         15
     379: ifnonnull     434
     382: aload         17
     384: invokeinterface #56,  1           // InterfaceMethod java/util/Iterator.next:()Ljava/lang/Object;
     389: checkcast     #57                 // class org/codehaus/plexus/interpolation/ValueSource
     392: astore        18
     394: aload         18
     396: aload         13
     398: invokeinterface #58,  2           // InterfaceMethod org/codehaus/plexus/interpolation/ValueSource.getValue:(Ljava/lang/String;)Ljava/lang/Object;
     403: astore        15
     405: aload         15
     407: ifnull        431
     410: aload         15
     412: invokevirtual #59                 // Method java/lang/Object.toString:()Ljava/lang/String;
     415: aload         12
     417: invokevirtual #60                 // Method java/lang/String.indexOf:(Ljava/lang/String;)I
     420: iconst_m1
     421: if_icmple     431
     424: aload         15
     426: astore        16
     428: aconst_null
     429: astore        15
     431: goto          367
     434: aload         15
     436: ifnonnull     457
     439: aload         16
     441: ifnull        457
     444: new           #50                 // class org/codehaus/plexus/interpolation/InterpolationCycleException
     447: dup
     448: aload_2
     449: aload         13
     451: aload         12
     453: invokespecial #51                 // Method org/codehaus/plexus/interpolation/InterpolationCycleException."<init>":(Lorg/codehaus/plexus/interpolation/RecursionInterceptor;Ljava/lang/String;Ljava/lang/String;)V
     456: athrow
     457: aload         15
     459: ifnull        572
     462: aload_0
     463: aload         15
     465: invokestatic  #61                 // Method java/lang/String.valueOf:(Ljava/lang/Object;)Ljava/lang/String;
     468: aload_2
     469: aload_3
     470: invokespecial #26                 // Method interpolate:(Ljava/lang/String;Lorg/codehaus/plexus/interpolation/RecursionInterceptor;Ljava/util/Set;)Ljava/lang/String;
     473: astore        15
     475: aload_0
     476: getfield      #8                  // Field postProcessors:Ljava/util/List;
     479: ifnull        555
     482: aload_0
     483: getfield      #8                  // Field postProcessors:Ljava/util/List;
     486: invokeinterface #62,  1           // InterfaceMethod java/util/List.isEmpty:()Z
     491: ifne          555
     494: aload_0
     495: getfield      #8                  // Field postProcessors:Ljava/util/List;
     498: invokeinterface #54,  1           // InterfaceMethod java/util/List.iterator:()Ljava/util/Iterator;
     503: astore        17
     505: aload         17
     507: invokeinterface #55,  1           // InterfaceMethod java/util/Iterator.hasNext:()Z
     512: ifeq          555
     515: aload         17
     517: invokeinterface #56,  1           // InterfaceMethod java/util/Iterator.next:()Ljava/lang/Object;
     522: checkcast     #63                 // class org/codehaus/plexus/interpolation/InterpolationPostProcessor
     525: astore        18
     527: aload         18
     529: aload         13
     531: aload         15
     533: invokeinterface #64,  3           // InterfaceMethod org/codehaus/plexus/interpolation/InterpolationPostProcessor.execute:(Ljava/lang/String;Ljava/lang/Object;)Ljava/lang/Object;
     538: astore        19
     540: aload         19
     542: ifnull        552
     545: aload         19
     547: astore        15
     549: goto          555
     552: goto          505
     555: aload         4
     557: aload         15
     559: invokestatic  #61                 // Method java/lang/String.valueOf:(Ljava/lang/Object;)Ljava/lang/String;
     562: invokevirtual #40                 // Method java/lang/StringBuffer.append:(Ljava/lang/String;)Ljava/lang/StringBuffer;
     565: pop
     566: iconst_1
     567: istore        14
     569: goto          581
     572: aload_3
     573: aload         12
     575: invokeinterface #65,  2           // InterfaceMethod java/util/Set.add:(Ljava/lang/Object;)Z
     580: pop
     581: aload_2
     582: aload         13
     584: invokeinterface #66,  2           // InterfaceMethod org/codehaus/plexus/interpolation/RecursionInterceptor.expressionResolutionFinished:(Ljava/lang/String;)V
     589: iload         14
     591: ifne          602
     594: aload         4
     596: aload         12
     598: invokevirtual #40                 // Method java/lang/StringBuffer.append:(Ljava/lang/String;)Ljava/lang/StringBuffer;
     601: pop
     602: iload         8
     604: iconst_m1
     605: if_icmple     620
     608: iload         8
     610: aload         11
     612: invokevirtual #30                 // Method java/lang/String.length:()I
     615: iconst_1
     616: isub
     617: iadd
     618: istore        8
     620: goto          61
     623: iload         8
     625: iconst_m1
     626: if_icmpne     654
     629: iload         7
     631: iconst_m1
     632: if_icmple     654
     635: aload         4
     637: aload_1
     638: iload         7
     640: aload_1
     641: invokevirtual #30                 // Method java/lang/String.length:()I
     644: invokevirtual #39                 // Method java/lang/String.substring:(II)Ljava/lang/String;
     647: invokevirtual #40                 // Method java/lang/StringBuffer.append:(Ljava/lang/String;)Ljava/lang/StringBuffer;
     650: pop
     651: goto          681
     654: iload         8
     656: aload_1
     657: invokevirtual #30                 // Method java/lang/String.length:()I
     660: if_icmpge     681
     663: aload         4
     665: aload_1
     666: iload         8
     668: iconst_1
     669: iadd
     670: aload_1
     671: invokevirtual #30                 // Method java/lang/String.length:()I
     674: invokevirtual #39                 // Method java/lang/String.substring:(II)Ljava/lang/String;
     677: invokevirtual #40                 // Method java/lang/StringBuffer.append:(Ljava/lang/String;)Ljava/lang/StringBuffer;
     680: pop
     681: aload         5
     683: aload         4
     685: invokevirtual #33                 // Method java/lang/StringBuffer.toString:()Ljava/lang/String;
     688: invokevirtual #43                 // Method java/lang/String.equals:(Ljava/lang/Object;)Z
     691: ifne          701
     694: iload         6
     696: bipush        10
     698: if_icmplt     28
     701: aload         4
     703: invokevirtual #33                 // Method java/lang/StringBuffer.toString:()Ljava/lang/String;
     706: areturn

  private org.codehaus.plexus.interpolation.multi.DelimiterSpecification select(java.lang.String, int);
    Code:
       0: aconst_null
       1: astore_3
       2: aload_0
       3: getfield      #12                 // Field delimiters:Ljava/util/LinkedHashSet;
       6: invokevirtual #67                 // Method java/util/LinkedHashSet.iterator:()Ljava/util/Iterator;
       9: astore        4
      11: aload         4
      13: invokeinterface #55,  1           // InterfaceMethod java/util/Iterator.hasNext:()Z
      18: ifeq          75
      21: aload         4
      23: invokeinterface #56,  1           // InterfaceMethod java/util/Iterator.next:()Ljava/lang/Object;
      28: checkcast     #68                 // class org/codehaus/plexus/interpolation/multi/DelimiterSpecification
      31: astore        5
      33: aload         5
      35: invokevirtual #69                 // Method org/codehaus/plexus/interpolation/multi/DelimiterSpecification.clearNextStart:()V
      38: aload_3
      39: ifnonnull     72
      42: aload_1
      43: aload         5
      45: invokevirtual #36                 // Method org/codehaus/plexus/interpolation/multi/DelimiterSpecification.getBegin:()Ljava/lang/String;
      48: iload_2
      49: iconst_1
      50: iadd
      51: invokevirtual #41                 // Method java/lang/String.indexOf:(Ljava/lang/String;I)I
      54: istore        6
      56: iload         6
      58: iconst_m1
      59: if_icmple     72
      62: aload         5
      64: iload         6
      66: invokevirtual #70                 // Method org/codehaus/plexus/interpolation/multi/DelimiterSpecification.setNextStartIndex:(I)V
      69: aload         5
      71: astore_3
      72: goto          11
      75: aload_3
      76: areturn

  public java.util.List getFeedback();
    Code:
       0: new           #5                  // class java/util/ArrayList
       3: dup
       4: invokespecial #6                  // Method java/util/ArrayList."<init>":()V
       7: astore_1
       8: aload_0
       9: getfield      #7                  // Field valueSources:Ljava/util/List;
      12: invokeinterface #54,  1           // InterfaceMethod java/util/List.iterator:()Ljava/util/Iterator;
      17: astore_2
      18: aload_2
      19: invokeinterface #55,  1           // InterfaceMethod java/util/Iterator.hasNext:()Z
      24: ifeq          72
      27: aload_2
      28: invokeinterface #56,  1           // InterfaceMethod java/util/Iterator.next:()Ljava/lang/Object;
      33: checkcast     #57                 // class org/codehaus/plexus/interpolation/ValueSource
      36: astore_3
      37: aload_3
      38: invokeinterface #71,  1           // InterfaceMethod org/codehaus/plexus/interpolation/ValueSource.getFeedback:()Ljava/util/List;
      43: astore        4
      45: aload         4
      47: ifnull        69
      50: aload         4
      52: invokeinterface #62,  1           // InterfaceMethod java/util/List.isEmpty:()Z
      57: ifne          69
      60: aload_1
      61: aload         4
      63: invokeinterface #72,  2           // InterfaceMethod java/util/List.addAll:(Ljava/util/Collection;)Z
      68: pop
      69: goto          18
      72: aload_1
      73: areturn

  public void clearFeedback();
    Code:
       0: aload_0
       1: getfield      #7                  // Field valueSources:Ljava/util/List;
       4: invokeinterface #54,  1           // InterfaceMethod java/util/List.iterator:()Ljava/util/Iterator;
       9: astore_1
      10: aload_1
      11: invokeinterface #55,  1           // InterfaceMethod java/util/Iterator.hasNext:()Z
      16: ifeq          38
      19: aload_1
      20: invokeinterface #56,  1           // InterfaceMethod java/util/Iterator.next:()Ljava/lang/Object;
      25: checkcast     #57                 // class org/codehaus/plexus/interpolation/ValueSource
      28: astore_2
      29: aload_2
      30: invokeinterface #73,  1           // InterfaceMethod org/codehaus/plexus/interpolation/ValueSource.clearFeedback:()V
      35: goto          10
      38: return

  public boolean isCacheAnswers();
    Code:
       0: aload_0
       1: getfield      #9                  // Field cacheAnswers:Z
       4: ireturn

  public void setCacheAnswers(boolean);
    Code:
       0: aload_0
       1: iload_1
       2: putfield      #9                  // Field cacheAnswers:Z
       5: return

  public void clearAnswers();
    Code:
       0: aload_0
       1: getfield      #4                  // Field existingAnswers:Ljava/util/Map;
       4: invokeinterface #27,  1           // InterfaceMethod java/util/Map.clear:()V
       9: return

  public java.lang.String getEscapeString();
    Code:
       0: aload_0
       1: getfield      #42                 // Field escapeString:Ljava/lang/String;
       4: areturn

  public void setEscapeString(java.lang.String);
    Code:
       0: aload_0
       1: aload_1
       2: putfield      #42                 // Field escapeString:Ljava/lang/String;
       5: return

  public org.codehaus.plexus.interpolation.multi.MultiDelimiterStringSearchInterpolator setDelimiterSpecs(java.util.LinkedHashSet);
    Code:
       0: aload_0
       1: getfield      #12                 // Field delimiters:Ljava/util/LinkedHashSet;
       4: invokevirtual #74                 // Method java/util/LinkedHashSet.clear:()V
       7: aload_1
       8: invokevirtual #67                 // Method java/util/LinkedHashSet.iterator:()Ljava/util/Iterator;
      11: astore_2
      12: aload_2
      13: invokeinterface #55,  1           // InterfaceMethod java/util/Iterator.hasNext:()Z
      18: ifeq          53
      21: aload_2
      22: invokeinterface #56,  1           // InterfaceMethod java/util/Iterator.next:()Ljava/lang/Object;
      27: checkcast     #75                 // class java/lang/String
      30: astore_3
      31: aload_3
      32: ifnonnull     38
      35: goto          12
      38: aload_0
      39: getfield      #12                 // Field delimiters:Ljava/util/LinkedHashSet;
      42: aload_3
      43: invokestatic  #15                 // Method org/codehaus/plexus/interpolation/multi/DelimiterSpecification.parse:(Ljava/lang/String;)Lorg/codehaus/plexus/interpolation/multi/DelimiterSpecification;
      46: invokevirtual #14                 // Method java/util/LinkedHashSet.add:(Ljava/lang/Object;)Z
      49: pop
      50: goto          12
      53: aload_0
      54: areturn
}
