Compiled from "ConnectorPOATie.java"
public class org.omg.XA.ConnectorPOATie extends org.omg.XA.ConnectorPOA {
  private org.omg.XA.ConnectorOperations _impl;

  private org.omg.PortableServer.POA _poa;

  public org.omg.XA.ConnectorPOATie(org.omg.XA.ConnectorOperations);
    Code:
       0: aload_0
       1: invokespecial #1                  // Method org/omg/XA/ConnectorPOA."<init>":()V
       4: aload_0
       5: aload_1
       6: putfield      #2                  // Field _impl:Lorg/omg/XA/ConnectorOperations;
       9: return

  public org.omg.XA.ConnectorPOATie(org.omg.XA.ConnectorOperations, org.omg.PortableServer.POA);
    Code:
       0: aload_0
       1: invokespecial #1                  // Method org/omg/XA/ConnectorPOA."<init>":()V
       4: aload_0
       5: aload_1
       6: putfield      #2                  // Field _impl:Lorg/omg/XA/ConnectorOperations;
       9: aload_0
      10: aload_2
      11: putfield      #3                  // Field _poa:Lorg/omg/PortableServer/POA;
      14: return

  public org.omg.XA.ConnectorOperations _delegate();
    Code:
       0: aload_0
       1: getfield      #2                  // Field _impl:Lorg/omg/XA/ConnectorOperations;
       4: areturn

  public void _delegate(org.omg.XA.ConnectorOperations);
    Code:
       0: aload_0
       1: aload_1
       2: putfield      #2                  // Field _impl:Lorg/omg/XA/ConnectorOperations;
       5: return

  public org.omg.PortableServer.POA _default_POA();
    Code:
       0: aload_0
       1: getfield      #3                  // Field _poa:Lorg/omg/PortableServer/POA;
       4: ifnull        12
       7: aload_0
       8: getfield      #3                  // Field _poa:Lorg/omg/PortableServer/POA;
      11: areturn
      12: aload_0
      13: invokespecial #4                  // Method org/omg/XA/ConnectorPOA._default_POA:()Lorg/omg/PortableServer/POA;
      16: areturn

  public org.omg.XA.ResourceManager create_resource_manager(java.lang.String, org.omg.XA.XASwitch, java.lang.String, java.lang.String, short, boolean, boolean, org.omg.XA.CurrentConnectionHolder);
    Code:
       0: aload_0
       1: getfield      #2                  // Field _impl:Lorg/omg/XA/ConnectorOperations;
       4: aload_1
       5: aload_2
       6: aload_3
       7: aload         4
       9: iload         5
      11: iload         6
      13: iload         7
      15: aload         8
      17: invokeinterface #5,  9            // InterfaceMethod org/omg/XA/ConnectorOperations.create_resource_manager:(Ljava/lang/String;Lorg/omg/XA/XASwitch;Ljava/lang/String;Ljava/lang/String;SZZLorg/omg/XA/CurrentConnectionHolder;)Lorg/omg/XA/ResourceManager;
      22: areturn

  public org.omg.XA.CurrentConnection connect_to_resource_manager(org.omg.XA.ResourceManager, org.omg.XA.XASwitch, java.lang.String, java.lang.String, short, boolean, boolean);
    Code:
       0: aload_0
       1: getfield      #2                  // Field _impl:Lorg/omg/XA/ConnectorOperations;
       4: aload_1
       5: aload_2
       6: aload_3
       7: aload         4
       9: iload         5
      11: iload         6
      13: iload         7
      15: invokeinterface #6,  8            // InterfaceMethod org/omg/XA/ConnectorOperations.connect_to_resource_manager:(Lorg/omg/XA/ResourceManager;Lorg/omg/XA/XASwitch;Ljava/lang/String;Ljava/lang/String;SZZ)Lorg/omg/XA/CurrentConnection;
      20: areturn
}
