Compiled from "LoggerContext.java"
class org.apache.logging.log4j.core.LoggerContext$1 implements java.lang.Runnable {
  final long val$shutdownTimeoutMillis;

  final org.apache.logging.log4j.core.LoggerContext this$0;

  org.apache.logging.log4j.core.LoggerContext$1(org.apache.logging.log4j.core.LoggerContext, long);
    Code:
       0: aload_0
       1: aload_1
       2: putfield      #1                  // Field this$0:Lorg/apache/logging/log4j/core/LoggerContext;
       5: aload_0
       6: lload_2
       7: putfield      #2                  // Field val$shutdownTimeoutMillis:J
      10: aload_0
      11: invokespecial #3                  // Method java/lang/Object."<init>":()V
      14: return

  public void run();
    Code:
       0: aload_0
       1: getfield      #1                  // Field this$0:Lorg/apache/logging/log4j/core/LoggerContext;
       4: astore_1
       5: getstatic     #4                  // Field org/apache/logging/log4j/core/AbstractLifeCycle.LOGGER:Lorg/apache/logging/log4j/Logger;
       8: getstatic     #5                  // Field org/apache/logging/log4j/core/util/ShutdownCallbackRegistry.SHUTDOWN_HOOK_MARKER:Lorg/apache/logging/log4j/Marker;
      11: ldc           #6                  // String Stopping LoggerContext[name={}, {}]
      13: aload_1
      14: invokevirtual #7                  // Method org/apache/logging/log4j/core/LoggerContext.getName:()Ljava/lang/String;
      17: aload_1
      18: invokeinterface #8,  5            // InterfaceMethod org/apache/logging/log4j/Logger.debug:(Lorg/apache/logging/log4j/Marker;Ljava/lang/String;Ljava/lang/Object;Ljava/lang/Object;)V
      23: aload_1
      24: aload_0
      25: getfield      #2                  // Field val$shutdownTimeoutMillis:J
      28: getstatic     #9                  // Field java/util/concurrent/TimeUnit.MILLISECONDS:Ljava/util/concurrent/TimeUnit;
      31: invokevirtual #10                 // Method org/apache/logging/log4j/core/LoggerContext.stop:(JLjava/util/concurrent/TimeUnit;)Z
      34: pop
      35: return

  public java.lang.String toString();
    Code:
       0: new           #11                 // class java/lang/StringBuilder
       3: dup
       4: invokespecial #12                 // Method java/lang/StringBuilder."<init>":()V
       7: ldc           #13                 // String Shutdown callback for LoggerContext[name=
       9: invokevirtual #14                 // Method java/lang/StringBuilder.append:(Ljava/lang/String;)Ljava/lang/StringBuilder;
      12: aload_0
      13: getfield      #1                  // Field this$0:Lorg/apache/logging/log4j/core/LoggerContext;
      16: invokevirtual #7                  // Method org/apache/logging/log4j/core/LoggerContext.getName:()Ljava/lang/String;
      19: invokevirtual #14                 // Method java/lang/StringBuilder.append:(Ljava/lang/String;)Ljava/lang/StringBuilder;
      22: bipush        93
      24: invokevirtual #15                 // Method java/lang/StringBuilder.append:(C)Ljava/lang/StringBuilder;
      27: invokevirtual #16                 // Method java/lang/StringBuilder.toString:()Ljava/lang/String;
      30: areturn
}
