Compiled from "ManagedProcessEngineFactoryBeanTest.java"
public class org.camunda.bpm.engine.spring.test.container.ManagedProcessEngineFactoryBeanTest {
  public org.camunda.bpm.engine.spring.test.container.ManagedProcessEngineFactoryBeanTest();
    Code:
       0: aload_0
       1: invokespecial #1                  // Method java/lang/Object."<init>":()V
       4: return

  public void testProcessApplicationDeployment();
    Code:
       0: invokestatic  #2                  // Method org/camunda/bpm/BpmPlatform.getDefaultProcessEngine:()Lorg/camunda/bpm/engine/ProcessEngine;
       3: invokestatic  #3                  // Method org/junit/Assert.assertNull:(Ljava/lang/Object;)V
       6: lconst_0
       7: invokestatic  #4                  // Method org/camunda/bpm/BpmPlatform.getProcessEngineService:()Lorg/camunda/bpm/ProcessEngineService;
      10: invokeinterface #5,  1            // InterfaceMethod org/camunda/bpm/ProcessEngineService.getProcessEngines:()Ljava/util/List;
      15: invokeinterface #6,  1            // InterfaceMethod java/util/List.size:()I
      20: i2l
      21: invokestatic  #7                  // Method org/junit/Assert.assertEquals:(JJ)V
      24: new           #8                  // class org/springframework/context/support/ClassPathXmlApplicationContext
      27: dup
      28: ldc           #9                  // String org/camunda/bpm/engine/spring/test/container/ManagedProcessEngineFactoryBean-context.xml
      30: invokespecial #10                 // Method org/springframework/context/support/ClassPathXmlApplicationContext."<init>":(Ljava/lang/String;)V
      33: astore_1
      34: aload_1
      35: invokevirtual #11                 // Method org/springframework/context/support/AbstractApplicationContext.start:()V
      38: invokestatic  #2                  // Method org/camunda/bpm/BpmPlatform.getDefaultProcessEngine:()Lorg/camunda/bpm/engine/ProcessEngine;
      41: invokestatic  #12                 // Method org/junit/Assert.assertNotNull:(Ljava/lang/Object;)V
      44: aload_1
      45: invokevirtual #13                 // Method org/springframework/context/support/AbstractApplicationContext.close:()V
      48: invokestatic  #2                  // Method org/camunda/bpm/BpmPlatform.getDefaultProcessEngine:()Lorg/camunda/bpm/engine/ProcessEngine;
      51: invokestatic  #3                  // Method org/junit/Assert.assertNull:(Ljava/lang/Object;)V
      54: lconst_0
      55: invokestatic  #4                  // Method org/camunda/bpm/BpmPlatform.getProcessEngineService:()Lorg/camunda/bpm/ProcessEngineService;
      58: invokeinterface #5,  1            // InterfaceMethod org/camunda/bpm/ProcessEngineService.getProcessEngines:()Ljava/util/List;
      63: invokeinterface #6,  1            // InterfaceMethod java/util/List.size:()I
      68: i2l
      69: invokestatic  #7                  // Method org/junit/Assert.assertEquals:(JJ)V
      72: return
}
