Compiled from "IncompleteDeploymentReplaceException.java"
public class org.jboss.as.controller.client.helpers.domain.IncompleteDeploymentReplaceException extends org.jboss.as.controller.client.helpers.domain.InvalidDeploymentPlanException {
  private static final long serialVersionUID;

  public org.jboss.as.controller.client.helpers.domain.IncompleteDeploymentReplaceException(java.lang.String, java.lang.String...);
    Code:
       0: aload_0
       1: getstatic     #1                  // Field org/jboss/as/controller/client/logging/ControllerClientLogger.ROOT_LOGGER:Lorg/jboss/as/controller/client/logging/ControllerClientLogger;
       4: aload_1
       5: aload_2
       6: invokestatic  #2                  // Method createMissingGroups:([Ljava/lang/String;)Ljava/lang/String;
       9: invokeinterface #3,  3            // InterfaceMethod org/jboss/as/controller/client/logging/ControllerClientLogger.incompleteDeploymentReplace:(Ljava/lang/String;Ljava/lang/String;)Ljava/lang/String;
      14: invokespecial #4                  // Method org/jboss/as/controller/client/helpers/domain/InvalidDeploymentPlanException."<init>":(Ljava/lang/String;)V
      17: return

  private static java.lang.String createMissingGroups(java.lang.String[]);
    Code:
       0: new           #5                  // class java/lang/StringBuilder
       3: dup
       4: invokespecial #6                  // Method java/lang/StringBuilder."<init>":()V
       7: astore_1
       8: iconst_0
       9: istore_2
      10: iload_2
      11: aload_0
      12: arraylength
      13: if_icmpge     41
      16: iload_2
      17: ifle          27
      20: aload_1
      21: ldc           #7                  // String ,
      23: invokevirtual #8                  // Method java/lang/StringBuilder.append:(Ljava/lang/String;)Ljava/lang/StringBuilder;
      26: pop
      27: aload_1
      28: aload_0
      29: iload_2
      30: aaload
      31: invokevirtual #8                  // Method java/lang/StringBuilder.append:(Ljava/lang/String;)Ljava/lang/StringBuilder;
      34: pop
      35: iinc          2, 1
      38: goto          10
      41: aload_1
      42: invokevirtual #9                  // Method java/lang/StringBuilder.toString:()Ljava/lang/String;
      45: areturn
}
