Compiled from "IWorkerContext.java"
public class org.hl7.fhir.dstu3.context.IWorkerContext$ValidationResult {
  private org.hl7.fhir.dstu3.model.CodeSystem$ConceptDefinitionComponent definition;

  private org.hl7.fhir.utilities.validation.ValidationMessage$IssueSeverity severity;

  private java.lang.String message;

  private org.hl7.fhir.dstu3.terminologies.ValueSetExpander$TerminologyServiceErrorClass errorClass;

  public org.hl7.fhir.dstu3.context.IWorkerContext$ValidationResult(org.hl7.fhir.utilities.validation.ValidationMessage$IssueSeverity, java.lang.String);
    Code:
       0: aload_0
       1: invokespecial #1                  // Method java/lang/Object."<init>":()V
       4: aload_0
       5: aload_1
       6: putfield      #2                  // Field severity:Lorg/hl7/fhir/utilities/validation/ValidationMessage$IssueSeverity;
       9: aload_0
      10: aload_2
      11: putfield      #3                  // Field message:Ljava/lang/String;
      14: return

  public org.hl7.fhir.dstu3.context.IWorkerContext$ValidationResult(org.hl7.fhir.dstu3.model.CodeSystem$ConceptDefinitionComponent);
    Code:
       0: aload_0
       1: invokespecial #1                  // Method java/lang/Object."<init>":()V
       4: aload_0
       5: aload_1
       6: putfield      #4                  // Field definition:Lorg/hl7/fhir/dstu3/model/CodeSystem$ConceptDefinitionComponent;
       9: return

  public org.hl7.fhir.dstu3.context.IWorkerContext$ValidationResult(org.hl7.fhir.utilities.validation.ValidationMessage$IssueSeverity, java.lang.String, org.hl7.fhir.dstu3.model.CodeSystem$ConceptDefinitionComponent);
    Code:
       0: aload_0
       1: invokespecial #1                  // Method java/lang/Object."<init>":()V
       4: aload_0
       5: aload_1
       6: putfield      #2                  // Field severity:Lorg/hl7/fhir/utilities/validation/ValidationMessage$IssueSeverity;
       9: aload_0
      10: aload_2
      11: putfield      #3                  // Field message:Ljava/lang/String;
      14: aload_0
      15: aload_3
      16: putfield      #4                  // Field definition:Lorg/hl7/fhir/dstu3/model/CodeSystem$ConceptDefinitionComponent;
      19: return

  public org.hl7.fhir.dstu3.context.IWorkerContext$ValidationResult(org.hl7.fhir.utilities.validation.ValidationMessage$IssueSeverity, java.lang.String, org.hl7.fhir.dstu3.terminologies.ValueSetExpander$TerminologyServiceErrorClass);
    Code:
       0: aload_0
       1: invokespecial #1                  // Method java/lang/Object."<init>":()V
       4: aload_0
       5: aload_1
       6: putfield      #2                  // Field severity:Lorg/hl7/fhir/utilities/validation/ValidationMessage$IssueSeverity;
       9: aload_0
      10: aload_2
      11: putfield      #3                  // Field message:Ljava/lang/String;
      14: aload_0
      15: aload_3
      16: putfield      #5                  // Field errorClass:Lorg/hl7/fhir/dstu3/terminologies/ValueSetExpander$TerminologyServiceErrorClass;
      19: return

  public boolean isOk();
    Code:
       0: aload_0
       1: getfield      #4                  // Field definition:Lorg/hl7/fhir/dstu3/model/CodeSystem$ConceptDefinitionComponent;
       4: ifnull        11
       7: iconst_1
       8: goto          12
      11: iconst_0
      12: ireturn

  public java.lang.String getDisplay();
    Code:
       0: aload_0
       1: getfield      #4                  // Field definition:Lorg/hl7/fhir/dstu3/model/CodeSystem$ConceptDefinitionComponent;
       4: ifnonnull     11
       7: aconst_null
       8: goto          18
      11: aload_0
      12: getfield      #4                  // Field definition:Lorg/hl7/fhir/dstu3/model/CodeSystem$ConceptDefinitionComponent;
      15: invokevirtual #6                  // Method org/hl7/fhir/dstu3/model/CodeSystem$ConceptDefinitionComponent.getDisplay:()Ljava/lang/String;
      18: areturn

  public org.hl7.fhir.dstu3.model.CodeSystem$ConceptDefinitionComponent asConceptDefinition();
    Code:
       0: aload_0
       1: getfield      #4                  // Field definition:Lorg/hl7/fhir/dstu3/model/CodeSystem$ConceptDefinitionComponent;
       4: areturn

  public org.hl7.fhir.utilities.validation.ValidationMessage$IssueSeverity getSeverity();
    Code:
       0: aload_0
       1: getfield      #2                  // Field severity:Lorg/hl7/fhir/utilities/validation/ValidationMessage$IssueSeverity;
       4: areturn

  public java.lang.String getMessage();
    Code:
       0: aload_0
       1: getfield      #3                  // Field message:Ljava/lang/String;
       4: areturn

  public boolean IsNoService();
    Code:
       0: aload_0
       1: getfield      #5                  // Field errorClass:Lorg/hl7/fhir/dstu3/terminologies/ValueSetExpander$TerminologyServiceErrorClass;
       4: getstatic     #7                  // Field org/hl7/fhir/dstu3/terminologies/ValueSetExpander$TerminologyServiceErrorClass.NOSERVICE:Lorg/hl7/fhir/dstu3/terminologies/ValueSetExpander$TerminologyServiceErrorClass;
       7: if_acmpne     14
      10: iconst_1
      11: goto          15
      14: iconst_0
      15: ireturn

  public org.hl7.fhir.dstu3.terminologies.ValueSetExpander$TerminologyServiceErrorClass getErrorClass();
    Code:
       0: aload_0
       1: getfield      #5                  // Field errorClass:Lorg/hl7/fhir/dstu3/terminologies/ValueSetExpander$TerminologyServiceErrorClass;
       4: areturn
}
