Compiled from "RemoteRepository.java"
public class org.sonatype.aether.repository.RemoteRepository implements org.sonatype.aether.repository.ArtifactRepository {
  private static final java.util.regex.Pattern URL_PATTERN;

  private java.lang.String id;

  private java.lang.String type;

  private java.lang.String url;

  private org.sonatype.aether.repository.RepositoryPolicy releasePolicy;

  private org.sonatype.aether.repository.RepositoryPolicy snapshotPolicy;

  private org.sonatype.aether.repository.Proxy proxy;

  private org.sonatype.aether.repository.Authentication authentication;

  private java.util.List<org.sonatype.aether.repository.RemoteRepository> mirroredRepositories;

  private boolean repositoryManager;

  public org.sonatype.aether.repository.RemoteRepository();
    Code:
       0: aload_0
       1: invokespecial #1                  // Method java/lang/Object."<init>":()V
       4: aload_0
       5: ldc           #2                  // String
       7: putfield      #3                  // Field id:Ljava/lang/String;
      10: aload_0
      11: ldc           #2                  // String
      13: putfield      #4                  // Field type:Ljava/lang/String;
      16: aload_0
      17: ldc           #2                  // String
      19: putfield      #5                  // Field url:Ljava/lang/String;
      22: aload_0
      23: invokestatic  #6                  // Method java/util/Collections.emptyList:()Ljava/util/List;
      26: putfield      #7                  // Field mirroredRepositories:Ljava/util/List;
      29: aload_0
      30: iconst_1
      31: aconst_null
      32: invokevirtual #8                  // Method setPolicy:(ZLorg/sonatype/aether/repository/RepositoryPolicy;)Lorg/sonatype/aether/repository/RemoteRepository;
      35: pop
      36: aload_0
      37: iconst_0
      38: aconst_null
      39: invokevirtual #8                  // Method setPolicy:(ZLorg/sonatype/aether/repository/RepositoryPolicy;)Lorg/sonatype/aether/repository/RemoteRepository;
      42: pop
      43: return

  public org.sonatype.aether.repository.RemoteRepository(org.sonatype.aether.repository.RemoteRepository);
    Code:
       0: aload_0
       1: invokespecial #1                  // Method java/lang/Object."<init>":()V
       4: aload_0
       5: ldc           #2                  // String
       7: putfield      #3                  // Field id:Ljava/lang/String;
      10: aload_0
      11: ldc           #2                  // String
      13: putfield      #4                  // Field type:Ljava/lang/String;
      16: aload_0
      17: ldc           #2                  // String
      19: putfield      #5                  // Field url:Ljava/lang/String;
      22: aload_0
      23: invokestatic  #6                  // Method java/util/Collections.emptyList:()Ljava/util/List;
      26: putfield      #7                  // Field mirroredRepositories:Ljava/util/List;
      29: aload_0
      30: aload_1
      31: invokevirtual #9                  // Method getId:()Ljava/lang/String;
      34: invokevirtual #10                 // Method setId:(Ljava/lang/String;)Lorg/sonatype/aether/repository/RemoteRepository;
      37: pop
      38: aload_0
      39: aload_1
      40: invokevirtual #11                 // Method getContentType:()Ljava/lang/String;
      43: invokevirtual #12                 // Method setContentType:(Ljava/lang/String;)Lorg/sonatype/aether/repository/RemoteRepository;
      46: pop
      47: aload_0
      48: aload_1
      49: invokevirtual #13                 // Method getUrl:()Ljava/lang/String;
      52: invokevirtual #14                 // Method setUrl:(Ljava/lang/String;)Lorg/sonatype/aether/repository/RemoteRepository;
      55: pop
      56: aload_0
      57: iconst_1
      58: aload_1
      59: iconst_1
      60: invokevirtual #15                 // Method getPolicy:(Z)Lorg/sonatype/aether/repository/RepositoryPolicy;
      63: invokevirtual #8                  // Method setPolicy:(ZLorg/sonatype/aether/repository/RepositoryPolicy;)Lorg/sonatype/aether/repository/RemoteRepository;
      66: pop
      67: aload_0
      68: iconst_0
      69: aload_1
      70: iconst_0
      71: invokevirtual #15                 // Method getPolicy:(Z)Lorg/sonatype/aether/repository/RepositoryPolicy;
      74: invokevirtual #8                  // Method setPolicy:(ZLorg/sonatype/aether/repository/RepositoryPolicy;)Lorg/sonatype/aether/repository/RemoteRepository;
      77: pop
      78: aload_0
      79: aload_1
      80: invokevirtual #16                 // Method getAuthentication:()Lorg/sonatype/aether/repository/Authentication;
      83: invokevirtual #17                 // Method setAuthentication:(Lorg/sonatype/aether/repository/Authentication;)Lorg/sonatype/aether/repository/RemoteRepository;
      86: pop
      87: aload_0
      88: aload_1
      89: invokevirtual #18                 // Method getProxy:()Lorg/sonatype/aether/repository/Proxy;
      92: invokevirtual #19                 // Method setProxy:(Lorg/sonatype/aether/repository/Proxy;)Lorg/sonatype/aether/repository/RemoteRepository;
      95: pop
      96: aload_0
      97: aload_1
      98: invokevirtual #20                 // Method getMirroredRepositories:()Ljava/util/List;
     101: invokevirtual #21                 // Method setMirroredRepositories:(Ljava/util/List;)Lorg/sonatype/aether/repository/RemoteRepository;
     104: pop
     105: aload_0
     106: aload_1
     107: invokevirtual #22                 // Method isRepositoryManager:()Z
     110: invokevirtual #23                 // Method setRepositoryManager:(Z)Lorg/sonatype/aether/repository/RemoteRepository;
     113: pop
     114: return

  public org.sonatype.aether.repository.RemoteRepository(java.lang.String, java.lang.String, java.lang.String);
    Code:
       0: aload_0
       1: invokespecial #1                  // Method java/lang/Object."<init>":()V
       4: aload_0
       5: ldc           #2                  // String
       7: putfield      #3                  // Field id:Ljava/lang/String;
      10: aload_0
      11: ldc           #2                  // String
      13: putfield      #4                  // Field type:Ljava/lang/String;
      16: aload_0
      17: ldc           #2                  // String
      19: putfield      #5                  // Field url:Ljava/lang/String;
      22: aload_0
      23: invokestatic  #6                  // Method java/util/Collections.emptyList:()Ljava/util/List;
      26: putfield      #7                  // Field mirroredRepositories:Ljava/util/List;
      29: aload_0
      30: aload_1
      31: invokevirtual #10                 // Method setId:(Ljava/lang/String;)Lorg/sonatype/aether/repository/RemoteRepository;
      34: pop
      35: aload_0
      36: aload_2
      37: invokevirtual #12                 // Method setContentType:(Ljava/lang/String;)Lorg/sonatype/aether/repository/RemoteRepository;
      40: pop
      41: aload_0
      42: aload_3
      43: invokevirtual #14                 // Method setUrl:(Ljava/lang/String;)Lorg/sonatype/aether/repository/RemoteRepository;
      46: pop
      47: aload_0
      48: iconst_1
      49: aconst_null
      50: invokevirtual #8                  // Method setPolicy:(ZLorg/sonatype/aether/repository/RepositoryPolicy;)Lorg/sonatype/aether/repository/RemoteRepository;
      53: pop
      54: aload_0
      55: iconst_0
      56: aconst_null
      57: invokevirtual #8                  // Method setPolicy:(ZLorg/sonatype/aether/repository/RepositoryPolicy;)Lorg/sonatype/aether/repository/RemoteRepository;
      60: pop
      61: return

  public java.lang.String getId();
    Code:
       0: aload_0
       1: getfield      #3                  // Field id:Ljava/lang/String;
       4: areturn

  public org.sonatype.aether.repository.RemoteRepository setId(java.lang.String);
    Code:
       0: aload_0
       1: aload_1
       2: ifnull        9
       5: aload_1
       6: goto          11
       9: ldc           #2                  // String
      11: putfield      #3                  // Field id:Ljava/lang/String;
      14: aload_0
      15: areturn

  public java.lang.String getContentType();
    Code:
       0: aload_0
       1: getfield      #4                  // Field type:Ljava/lang/String;
       4: areturn

  public org.sonatype.aether.repository.RemoteRepository setContentType(java.lang.String);
    Code:
       0: aload_0
       1: aload_1
       2: ifnull        9
       5: aload_1
       6: goto          11
       9: ldc           #2                  // String
      11: putfield      #4                  // Field type:Ljava/lang/String;
      14: aload_0
      15: areturn

  public java.lang.String getUrl();
    Code:
       0: aload_0
       1: getfield      #5                  // Field url:Ljava/lang/String;
       4: areturn

  public org.sonatype.aether.repository.RemoteRepository setUrl(java.lang.String);
    Code:
       0: aload_0
       1: aload_1
       2: ifnull        9
       5: aload_1
       6: goto          11
       9: ldc           #2                  // String
      11: putfield      #5                  // Field url:Ljava/lang/String;
      14: aload_0
      15: areturn

  public java.lang.String getProtocol();
    Code:
       0: getstatic     #24                 // Field URL_PATTERN:Ljava/util/regex/Pattern;
       3: aload_0
       4: getfield      #5                  // Field url:Ljava/lang/String;
       7: invokevirtual #25                 // Method java/util/regex/Pattern.matcher:(Ljava/lang/CharSequence;)Ljava/util/regex/Matcher;
      10: astore_1
      11: aload_1
      12: invokevirtual #26                 // Method java/util/regex/Matcher.matches:()Z
      15: ifeq          24
      18: aload_1
      19: iconst_1
      20: invokevirtual #27                 // Method java/util/regex/Matcher.group:(I)Ljava/lang/String;
      23: areturn
      24: ldc           #2                  // String
      26: areturn

  public java.lang.String getHost();
    Code:
       0: getstatic     #24                 // Field URL_PATTERN:Ljava/util/regex/Pattern;
       3: aload_0
       4: getfield      #5                  // Field url:Ljava/lang/String;
       7: invokevirtual #25                 // Method java/util/regex/Pattern.matcher:(Ljava/lang/CharSequence;)Ljava/util/regex/Matcher;
      10: astore_1
      11: aload_1
      12: invokevirtual #26                 // Method java/util/regex/Matcher.matches:()Z
      15: ifeq          30
      18: aload_1
      19: iconst_5
      20: invokevirtual #27                 // Method java/util/regex/Matcher.group:(I)Ljava/lang/String;
      23: astore_2
      24: aload_2
      25: ifnull        30
      28: aload_2
      29: areturn
      30: ldc           #2                  // String
      32: areturn

  public org.sonatype.aether.repository.RepositoryPolicy getPolicy(boolean);
    Code:
       0: iload_1
       1: ifeq          11
       4: aload_0
       5: getfield      #28                 // Field snapshotPolicy:Lorg/sonatype/aether/repository/RepositoryPolicy;
       8: goto          15
      11: aload_0
      12: getfield      #29                 // Field releasePolicy:Lorg/sonatype/aether/repository/RepositoryPolicy;
      15: areturn

  public org.sonatype.aether.repository.RemoteRepository setPolicy(boolean, org.sonatype.aether.repository.RepositoryPolicy);
    Code:
       0: aload_2
       1: ifnonnull     12
       4: new           #30                 // class org/sonatype/aether/repository/RepositoryPolicy
       7: dup
       8: invokespecial #31                 // Method org/sonatype/aether/repository/RepositoryPolicy."<init>":()V
      11: astore_2
      12: iload_1
      13: ifeq          24
      16: aload_0
      17: aload_2
      18: putfield      #28                 // Field snapshotPolicy:Lorg/sonatype/aether/repository/RepositoryPolicy;
      21: goto          29
      24: aload_0
      25: aload_2
      26: putfield      #29                 // Field releasePolicy:Lorg/sonatype/aether/repository/RepositoryPolicy;
      29: aload_0
      30: areturn

  public org.sonatype.aether.repository.Proxy getProxy();
    Code:
       0: aload_0
       1: getfield      #32                 // Field proxy:Lorg/sonatype/aether/repository/Proxy;
       4: areturn

  public org.sonatype.aether.repository.RemoteRepository setProxy(org.sonatype.aether.repository.Proxy);
    Code:
       0: aload_0
       1: aload_1
       2: putfield      #32                 // Field proxy:Lorg/sonatype/aether/repository/Proxy;
       5: aload_0
       6: areturn

  public org.sonatype.aether.repository.Authentication getAuthentication();
    Code:
       0: aload_0
       1: getfield      #33                 // Field authentication:Lorg/sonatype/aether/repository/Authentication;
       4: areturn

  public org.sonatype.aether.repository.RemoteRepository setAuthentication(org.sonatype.aether.repository.Authentication);
    Code:
       0: aload_0
       1: aload_1
       2: putfield      #33                 // Field authentication:Lorg/sonatype/aether/repository/Authentication;
       5: aload_0
       6: areturn

  public java.util.List<org.sonatype.aether.repository.RemoteRepository> getMirroredRepositories();
    Code:
       0: aload_0
       1: getfield      #7                  // Field mirroredRepositories:Ljava/util/List;
       4: areturn

  public org.sonatype.aether.repository.RemoteRepository setMirroredRepositories(java.util.List<org.sonatype.aether.repository.RemoteRepository>);
    Code:
       0: aload_1
       1: ifnull        13
       4: aload_1
       5: invokeinterface #34,  1           // InterfaceMethod java/util/List.isEmpty:()Z
      10: ifeq          23
      13: aload_0
      14: invokestatic  #6                  // Method java/util/Collections.emptyList:()Ljava/util/List;
      17: putfield      #7                  // Field mirroredRepositories:Ljava/util/List;
      20: goto          28
      23: aload_0
      24: aload_1
      25: putfield      #7                  // Field mirroredRepositories:Ljava/util/List;
      28: aload_0
      29: areturn

  public boolean isRepositoryManager();
    Code:
       0: aload_0
       1: getfield      #35                 // Field repositoryManager:Z
       4: ireturn

  public org.sonatype.aether.repository.RemoteRepository setRepositoryManager(boolean);
    Code:
       0: aload_0
       1: iload_1
       2: putfield      #35                 // Field repositoryManager:Z
       5: aload_0
       6: areturn

  public java.lang.String toString();
    Code:
       0: new           #36                 // class java/lang/StringBuilder
       3: dup
       4: sipush        256
       7: invokespecial #37                 // Method java/lang/StringBuilder."<init>":(I)V
      10: astore_1
      11: aload_1
      12: aload_0
      13: invokevirtual #9                  // Method getId:()Ljava/lang/String;
      16: invokevirtual #38                 // Method java/lang/StringBuilder.append:(Ljava/lang/String;)Ljava/lang/StringBuilder;
      19: pop
      20: aload_1
      21: ldc           #39                 // String  (
      23: invokevirtual #38                 // Method java/lang/StringBuilder.append:(Ljava/lang/String;)Ljava/lang/StringBuilder;
      26: aload_0
      27: invokevirtual #13                 // Method getUrl:()Ljava/lang/String;
      30: invokevirtual #38                 // Method java/lang/StringBuilder.append:(Ljava/lang/String;)Ljava/lang/StringBuilder;
      33: pop
      34: aload_0
      35: iconst_0
      36: invokevirtual #15                 // Method getPolicy:(Z)Lorg/sonatype/aether/repository/RepositoryPolicy;
      39: invokevirtual #40                 // Method org/sonatype/aether/repository/RepositoryPolicy.isEnabled:()Z
      42: istore_2
      43: aload_0
      44: iconst_1
      45: invokevirtual #15                 // Method getPolicy:(Z)Lorg/sonatype/aether/repository/RepositoryPolicy;
      48: invokevirtual #40                 // Method org/sonatype/aether/repository/RepositoryPolicy.isEnabled:()Z
      51: istore_3
      52: iload_2
      53: ifeq          70
      56: iload_3
      57: ifeq          70
      60: aload_1
      61: ldc           #41                 // String , releases+snapshots
      63: invokevirtual #38                 // Method java/lang/StringBuilder.append:(Ljava/lang/String;)Ljava/lang/StringBuilder;
      66: pop
      67: goto          105
      70: iload_2
      71: ifeq          84
      74: aload_1
      75: ldc           #42                 // String , releases
      77: invokevirtual #38                 // Method java/lang/StringBuilder.append:(Ljava/lang/String;)Ljava/lang/StringBuilder;
      80: pop
      81: goto          105
      84: iload_3
      85: ifeq          98
      88: aload_1
      89: ldc           #43                 // String , snapshots
      91: invokevirtual #38                 // Method java/lang/StringBuilder.append:(Ljava/lang/String;)Ljava/lang/StringBuilder;
      94: pop
      95: goto          105
      98: aload_1
      99: ldc           #44                 // String , disabled
     101: invokevirtual #38                 // Method java/lang/StringBuilder.append:(Ljava/lang/String;)Ljava/lang/StringBuilder;
     104: pop
     105: aload_0
     106: invokevirtual #22                 // Method isRepositoryManager:()Z
     109: ifeq          119
     112: aload_1
     113: ldc           #45                 // String , managed
     115: invokevirtual #38                 // Method java/lang/StringBuilder.append:(Ljava/lang/String;)Ljava/lang/StringBuilder;
     118: pop
     119: aload_1
     120: ldc           #46                 // String )
     122: invokevirtual #38                 // Method java/lang/StringBuilder.append:(Ljava/lang/String;)Ljava/lang/StringBuilder;
     125: pop
     126: aload_1
     127: invokevirtual #47                 // Method java/lang/StringBuilder.toString:()Ljava/lang/String;
     130: areturn

  public boolean equals(java.lang.Object);
    Code:
       0: aload_0
       1: aload_1
       2: if_acmpne     7
       5: iconst_1
       6: ireturn
       7: aload_1
       8: ifnull        25
      11: aload_0
      12: invokevirtual #48                 // Method java/lang/Object.getClass:()Ljava/lang/Class;
      15: aload_1
      16: invokevirtual #48                 // Method java/lang/Object.getClass:()Ljava/lang/Class;
      19: invokevirtual #49                 // Method java/lang/Object.equals:(Ljava/lang/Object;)Z
      22: ifne          27
      25: iconst_0
      26: ireturn
      27: aload_1
      28: checkcast     #50                 // class org/sonatype/aether/repository/RemoteRepository
      31: astore_2
      32: aload_0
      33: getfield      #5                  // Field url:Ljava/lang/String;
      36: aload_2
      37: getfield      #5                  // Field url:Ljava/lang/String;
      40: invokestatic  #51                 // Method eq:(Ljava/lang/Object;Ljava/lang/Object;)Z
      43: ifeq          159
      46: aload_0
      47: getfield      #4                  // Field type:Ljava/lang/String;
      50: aload_2
      51: getfield      #4                  // Field type:Ljava/lang/String;
      54: invokestatic  #51                 // Method eq:(Ljava/lang/Object;Ljava/lang/Object;)Z
      57: ifeq          159
      60: aload_0
      61: getfield      #3                  // Field id:Ljava/lang/String;
      64: aload_2
      65: getfield      #3                  // Field id:Ljava/lang/String;
      68: invokestatic  #51                 // Method eq:(Ljava/lang/Object;Ljava/lang/Object;)Z
      71: ifeq          159
      74: aload_0
      75: getfield      #29                 // Field releasePolicy:Lorg/sonatype/aether/repository/RepositoryPolicy;
      78: aload_2
      79: getfield      #29                 // Field releasePolicy:Lorg/sonatype/aether/repository/RepositoryPolicy;
      82: invokestatic  #51                 // Method eq:(Ljava/lang/Object;Ljava/lang/Object;)Z
      85: ifeq          159
      88: aload_0
      89: getfield      #28                 // Field snapshotPolicy:Lorg/sonatype/aether/repository/RepositoryPolicy;
      92: aload_2
      93: getfield      #28                 // Field snapshotPolicy:Lorg/sonatype/aether/repository/RepositoryPolicy;
      96: invokestatic  #51                 // Method eq:(Ljava/lang/Object;Ljava/lang/Object;)Z
      99: ifeq          159
     102: aload_0
     103: getfield      #32                 // Field proxy:Lorg/sonatype/aether/repository/Proxy;
     106: aload_2
     107: getfield      #32                 // Field proxy:Lorg/sonatype/aether/repository/Proxy;
     110: invokestatic  #51                 // Method eq:(Ljava/lang/Object;Ljava/lang/Object;)Z
     113: ifeq          159
     116: aload_0
     117: getfield      #33                 // Field authentication:Lorg/sonatype/aether/repository/Authentication;
     120: aload_2
     121: getfield      #33                 // Field authentication:Lorg/sonatype/aether/repository/Authentication;
     124: invokestatic  #51                 // Method eq:(Ljava/lang/Object;Ljava/lang/Object;)Z
     127: ifeq          159
     130: aload_0
     131: getfield      #7                  // Field mirroredRepositories:Ljava/util/List;
     134: aload_2
     135: getfield      #7                  // Field mirroredRepositories:Ljava/util/List;
     138: invokestatic  #51                 // Method eq:(Ljava/lang/Object;Ljava/lang/Object;)Z
     141: ifeq          159
     144: aload_0
     145: getfield      #35                 // Field repositoryManager:Z
     148: aload_2
     149: getfield      #35                 // Field repositoryManager:Z
     152: if_icmpne     159
     155: iconst_1
     156: goto          160
     159: iconst_0
     160: ireturn

  private static <T> boolean eq(T, T);
    Code:
       0: aload_0
       1: ifnull        12
       4: aload_0
       5: aload_1
       6: invokevirtual #49                 // Method java/lang/Object.equals:(Ljava/lang/Object;)Z
       9: goto          21
      12: aload_1
      13: ifnonnull     20
      16: iconst_1
      17: goto          21
      20: iconst_0
      21: ireturn

  public int hashCode();
    Code:
       0: bipush        17
       2: istore_1
       3: iload_1
       4: bipush        31
       6: imul
       7: aload_0
       8: getfield      #5                  // Field url:Ljava/lang/String;
      11: invokestatic  #52                 // Method hash:(Ljava/lang/Object;)I
      14: iadd
      15: istore_1
      16: iload_1
      17: bipush        31
      19: imul
      20: aload_0
      21: getfield      #4                  // Field type:Ljava/lang/String;
      24: invokestatic  #52                 // Method hash:(Ljava/lang/Object;)I
      27: iadd
      28: istore_1
      29: iload_1
      30: bipush        31
      32: imul
      33: aload_0
      34: getfield      #3                  // Field id:Ljava/lang/String;
      37: invokestatic  #52                 // Method hash:(Ljava/lang/Object;)I
      40: iadd
      41: istore_1
      42: iload_1
      43: bipush        31
      45: imul
      46: aload_0
      47: getfield      #29                 // Field releasePolicy:Lorg/sonatype/aether/repository/RepositoryPolicy;
      50: invokestatic  #52                 // Method hash:(Ljava/lang/Object;)I
      53: iadd
      54: istore_1
      55: iload_1
      56: bipush        31
      58: imul
      59: aload_0
      60: getfield      #28                 // Field snapshotPolicy:Lorg/sonatype/aether/repository/RepositoryPolicy;
      63: invokestatic  #52                 // Method hash:(Ljava/lang/Object;)I
      66: iadd
      67: istore_1
      68: iload_1
      69: bipush        31
      71: imul
      72: aload_0
      73: getfield      #32                 // Field proxy:Lorg/sonatype/aether/repository/Proxy;
      76: invokestatic  #52                 // Method hash:(Ljava/lang/Object;)I
      79: iadd
      80: istore_1
      81: iload_1
      82: bipush        31
      84: imul
      85: aload_0
      86: getfield      #33                 // Field authentication:Lorg/sonatype/aether/repository/Authentication;
      89: invokestatic  #52                 // Method hash:(Ljava/lang/Object;)I
      92: iadd
      93: istore_1
      94: iload_1
      95: bipush        31
      97: imul
      98: aload_0
      99: getfield      #7                  // Field mirroredRepositories:Ljava/util/List;
     102: invokestatic  #52                 // Method hash:(Ljava/lang/Object;)I
     105: iadd
     106: istore_1
     107: iload_1
     108: bipush        31
     110: imul
     111: aload_0
     112: getfield      #35                 // Field repositoryManager:Z
     115: ifeq          122
     118: iconst_1
     119: goto          123
     122: iconst_0
     123: iadd
     124: istore_1
     125: iload_1
     126: ireturn

  private static int hash(java.lang.Object);
    Code:
       0: aload_0
       1: ifnull        11
       4: aload_0
       5: invokevirtual #53                 // Method java/lang/Object.hashCode:()I
       8: goto          12
      11: iconst_0
      12: ireturn

  static {};
    Code:
       0: ldc           #54                 // String ([^:/]+(:[^:/]{2,}+(?=://))?):(//([^@/]*@)?([^/:]+))?.*
       2: invokestatic  #55                 // Method java/util/regex/Pattern.compile:(Ljava/lang/String;)Ljava/util/regex/Pattern;
       5: putstatic     #24                 // Field URL_PATTERN:Ljava/util/regex/Pattern;
       8: return
}
