Compiled from "FileProfileActivator.java"
public class org.apache.maven.model.profile.activation.FileProfileActivator implements org.apache.maven.model.profile.activation.ProfileActivator {
  private org.apache.maven.model.path.PathTranslator pathTranslator;

  public org.apache.maven.model.profile.activation.FileProfileActivator();
    Code:
       0: aload_0
       1: invokespecial #1                  // Method java/lang/Object."<init>":()V
       4: return

  public org.apache.maven.model.profile.activation.FileProfileActivator setPathTranslator(org.apache.maven.model.path.PathTranslator);
    Code:
       0: aload_0
       1: aload_1
       2: putfield      #2                  // Field pathTranslator:Lorg/apache/maven/model/path/PathTranslator;
       5: aload_0
       6: areturn

  public boolean isActive(org.apache.maven.model.Profile, org.apache.maven.model.profile.ProfileActivationContext, org.apache.maven.model.building.ModelProblemCollector);
    Code:
       0: aload_1
       1: invokevirtual #3                  // Method org/apache/maven/model/Profile.getActivation:()Lorg/apache/maven/model/Activation;
       4: astore        4
       6: aload         4
       8: ifnonnull     13
      11: iconst_0
      12: ireturn
      13: aload         4
      15: invokevirtual #4                  // Method org/apache/maven/model/Activation.getFile:()Lorg/apache/maven/model/ActivationFile;
      18: astore        5
      20: aload         5
      22: ifnonnull     27
      25: iconst_0
      26: ireturn
      27: aload         5
      29: invokevirtual #5                  // Method org/apache/maven/model/ActivationFile.getExists:()Ljava/lang/String;
      32: invokestatic  #6                  // Method org/codehaus/plexus/util/StringUtils.isNotEmpty:(Ljava/lang/String;)Z
      35: ifeq          51
      38: aload         5
      40: invokevirtual #5                  // Method org/apache/maven/model/ActivationFile.getExists:()Ljava/lang/String;
      43: astore        6
      45: iconst_0
      46: istore        7
      48: goto          77
      51: aload         5
      53: invokevirtual #7                  // Method org/apache/maven/model/ActivationFile.getMissing:()Ljava/lang/String;
      56: invokestatic  #6                  // Method org/codehaus/plexus/util/StringUtils.isNotEmpty:(Ljava/lang/String;)Z
      59: ifeq          75
      62: aload         5
      64: invokevirtual #7                  // Method org/apache/maven/model/ActivationFile.getMissing:()Ljava/lang/String;
      67: astore        6
      69: iconst_1
      70: istore        7
      72: goto          77
      75: iconst_0
      76: ireturn
      77: new           #8                  // class org/codehaus/plexus/interpolation/RegexBasedInterpolator
      80: dup
      81: invokespecial #9                  // Method org/codehaus/plexus/interpolation/RegexBasedInterpolator."<init>":()V
      84: astore        8
      86: aload_2
      87: invokeinterface #10,  1           // InterfaceMethod org/apache/maven/model/profile/ProfileActivationContext.getProjectDirectory:()Ljava/io/File;
      92: astore        9
      94: aload         9
      96: ifnull        118
      99: aload         8
     101: new           #11                 // class org/apache/maven/model/profile/activation/FileProfileActivator$1
     104: dup
     105: aload_0
     106: iconst_0
     107: aload         9
     109: invokespecial #12                 // Method org/apache/maven/model/profile/activation/FileProfileActivator$1."<init>":(Lorg/apache/maven/model/profile/activation/FileProfileActivator;ZLjava/io/File;)V
     112: invokevirtual #13                 // Method org/codehaus/plexus/interpolation/RegexBasedInterpolator.addValueSource:(Lorg/codehaus/plexus/interpolation/ValueSource;)V
     115: goto          130
     118: aload         6
     120: ldc           #14                 // String ${basedir}
     122: invokevirtual #15                 // Method java/lang/String.indexOf:(Ljava/lang/String;)I
     125: iflt          130
     128: iconst_0
     129: ireturn
     130: aload         8
     132: new           #16                 // class org/codehaus/plexus/interpolation/MapBasedValueSource
     135: dup
     136: aload_2
     137: invokeinterface #17,  1           // InterfaceMethod org/apache/maven/model/profile/ProfileActivationContext.getUserProperties:()Ljava/util/Map;
     142: invokespecial #18                 // Method org/codehaus/plexus/interpolation/MapBasedValueSource."<init>":(Ljava/util/Map;)V
     145: invokevirtual #13                 // Method org/codehaus/plexus/interpolation/RegexBasedInterpolator.addValueSource:(Lorg/codehaus/plexus/interpolation/ValueSource;)V
     148: aload         8
     150: new           #16                 // class org/codehaus/plexus/interpolation/MapBasedValueSource
     153: dup
     154: aload_2
     155: invokeinterface #19,  1           // InterfaceMethod org/apache/maven/model/profile/ProfileActivationContext.getSystemProperties:()Ljava/util/Map;
     160: invokespecial #18                 // Method org/codehaus/plexus/interpolation/MapBasedValueSource."<init>":(Ljava/util/Map;)V
     163: invokevirtual #13                 // Method org/codehaus/plexus/interpolation/RegexBasedInterpolator.addValueSource:(Lorg/codehaus/plexus/interpolation/ValueSource;)V
     166: aload         8
     168: aload         6
     170: ldc           #20                 // String
     172: invokevirtual #21                 // Method org/codehaus/plexus/interpolation/RegexBasedInterpolator.interpolate:(Ljava/lang/String;Ljava/lang/String;)Ljava/lang/String;
     175: astore        6
     177: goto          257
     180: astore        10
     182: aload_3
     183: getstatic     #23                 // Field org/apache/maven/model/building/ModelProblem$Severity.ERROR:Lorg/apache/maven/model/building/ModelProblem$Severity;
     186: new           #24                 // class java/lang/StringBuilder
     189: dup
     190: invokespecial #25                 // Method java/lang/StringBuilder."<init>":()V
     193: ldc           #26                 // String Failed to interpolate file location
     195: invokevirtual #27                 // Method java/lang/StringBuilder.append:(Ljava/lang/String;)Ljava/lang/StringBuilder;
     198: aload         6
     200: invokevirtual #27                 // Method java/lang/StringBuilder.append:(Ljava/lang/String;)Ljava/lang/StringBuilder;
     203: ldc           #28                 // String  for profile
     205: invokevirtual #27                 // Method java/lang/StringBuilder.append:(Ljava/lang/String;)Ljava/lang/StringBuilder;
     208: aload_1
     209: invokevirtual #29                 // Method org/apache/maven/model/Profile.getId:()Ljava/lang/String;
     212: invokevirtual #27                 // Method java/lang/StringBuilder.append:(Ljava/lang/String;)Ljava/lang/StringBuilder;
     215: ldc           #30                 // String :
     217: invokevirtual #27                 // Method java/lang/StringBuilder.append:(Ljava/lang/String;)Ljava/lang/StringBuilder;
     220: aload         10
     222: invokevirtual #31                 // Method java/lang/Exception.getMessage:()Ljava/lang/String;
     225: invokevirtual #27                 // Method java/lang/StringBuilder.append:(Ljava/lang/String;)Ljava/lang/StringBuilder;
     228: invokevirtual #32                 // Method java/lang/StringBuilder.toString:()Ljava/lang/String;
     231: aload         5
     233: iload         7
     235: ifeq          243
     238: ldc           #33                 // String missing
     240: goto          245
     243: ldc           #34                 // String exists
     245: invokevirtual #35                 // Method org/apache/maven/model/ActivationFile.getLocation:(Ljava/lang/Object;)Lorg/apache/maven/model/InputLocation;
     248: aload         10
     250: invokeinterface #36,  5           // InterfaceMethod org/apache/maven/model/building/ModelProblemCollector.add:(Lorg/apache/maven/model/building/ModelProblem$Severity;Ljava/lang/String;Lorg/apache/maven/model/InputLocation;Ljava/lang/Exception;)V
     255: iconst_0
     256: ireturn
     257: aload_0
     258: getfield      #2                  // Field pathTranslator:Lorg/apache/maven/model/path/PathTranslator;
     261: aload         6
     263: aload         9
     265: invokeinterface #37,  3           // InterfaceMethod org/apache/maven/model/path/PathTranslator.alignToBaseDirectory:(Ljava/lang/String;Ljava/io/File;)Ljava/lang/String;
     270: astore        6
     272: new           #38                 // class java/io/File
     275: dup
     276: aload         6
     278: invokespecial #39                 // Method java/io/File."<init>":(Ljava/lang/String;)V
     281: astore        10
     283: aload         10
     285: invokevirtual #40                 // Method java/io/File.isAbsolute:()Z
     288: ifne          293
     291: iconst_0
     292: ireturn
     293: aload         10
     295: invokevirtual #41                 // Method java/io/File.exists:()Z
     298: istore        11
     300: iload         7
     302: ifeq          318
     305: iload         11
     307: ifne          314
     310: iconst_1
     311: goto          320
     314: iconst_0
     315: goto          320
     318: iload         11
     320: ireturn
    Exception table:
       from    to  target type
         166   177   180   Class java/lang/Exception
}
