Compiled from "PropertyProfileActivator.java"
public class org.apache.maven.model.profile.activation.PropertyProfileActivator implements org.apache.maven.model.profile.activation.ProfileActivator {
  public org.apache.maven.model.profile.activation.PropertyProfileActivator();
    Code:
       0: aload_0
       1: invokespecial #1                  // Method java/lang/Object."<init>":()V
       4: return

  public boolean isActive(org.apache.maven.model.Profile, org.apache.maven.model.profile.ProfileActivationContext, org.apache.maven.model.building.ModelProblemCollector);
    Code:
       0: iconst_0
       1: istore        4
       3: aload_1
       4: invokevirtual #2                  // Method org/apache/maven/model/Profile.getActivation:()Lorg/apache/maven/model/Activation;
       7: astore        5
       9: aload         5
      11: ifnull        263
      14: aload         5
      16: invokevirtual #3                  // Method org/apache/maven/model/Activation.getProperty:()Lorg/apache/maven/model/ActivationProperty;
      19: astore        6
      21: aload         6
      23: ifnull        263
      26: aload         6
      28: invokevirtual #4                  // Method org/apache/maven/model/ActivationProperty.getName:()Ljava/lang/String;
      31: astore        7
      33: iconst_0
      34: istore        8
      36: aload         7
      38: ifnull        62
      41: aload         7
      43: ldc           #5                  // String !
      45: invokevirtual #6                  // Method java/lang/String.startsWith:(Ljava/lang/String;)Z
      48: ifeq          62
      51: iconst_1
      52: istore        8
      54: aload         7
      56: iconst_1
      57: invokevirtual #7                  // Method java/lang/String.substring:(I)Ljava/lang/String;
      60: astore        7
      62: aload         7
      64: ifnull        75
      67: aload         7
      69: invokevirtual #8                  // Method java/lang/String.length:()I
      72: ifgt          116
      75: aload_3
      76: getstatic     #9                  // Field org/apache/maven/model/building/ModelProblem$Severity.ERROR:Lorg/apache/maven/model/building/ModelProblem$Severity;
      79: new           #10                 // class java/lang/StringBuilder
      82: dup
      83: invokespecial #11                 // Method java/lang/StringBuilder."<init>":()V
      86: ldc           #12                 // String The property name is required to activate the profile
      88: invokevirtual #13                 // Method java/lang/StringBuilder.append:(Ljava/lang/String;)Ljava/lang/StringBuilder;
      91: aload_1
      92: invokevirtual #14                 // Method org/apache/maven/model/Profile.getId:()Ljava/lang/String;
      95: invokevirtual #13                 // Method java/lang/StringBuilder.append:(Ljava/lang/String;)Ljava/lang/StringBuilder;
      98: invokevirtual #15                 // Method java/lang/StringBuilder.toString:()Ljava/lang/String;
     101: aload         6
     103: ldc           #16                 // String
     105: invokevirtual #17                 // Method org/apache/maven/model/ActivationProperty.getLocation:(Ljava/lang/Object;)Lorg/apache/maven/model/InputLocation;
     108: aconst_null
     109: invokeinterface #18,  5           // InterfaceMethod org/apache/maven/model/building/ModelProblemCollector.add:(Lorg/apache/maven/model/building/ModelProblem$Severity;Ljava/lang/String;Lorg/apache/maven/model/InputLocation;Ljava/lang/Exception;)V
     114: iconst_0
     115: ireturn
     116: aload_2
     117: invokeinterface #19,  1           // InterfaceMethod org/apache/maven/model/profile/ProfileActivationContext.getUserProperties:()Ljava/util/Map;
     122: aload         7
     124: invokeinterface #20,  2           // InterfaceMethod java/util/Map.get:(Ljava/lang/Object;)Ljava/lang/Object;
     129: checkcast     #21                 // class java/lang/String
     132: astore        9
     134: aload         9
     136: ifnonnull     157
     139: aload_2
     140: invokeinterface #22,  1           // InterfaceMethod org/apache/maven/model/profile/ProfileActivationContext.getSystemProperties:()Ljava/util/Map;
     145: aload         7
     147: invokeinterface #20,  2           // InterfaceMethod java/util/Map.get:(Ljava/lang/Object;)Ljava/lang/Object;
     152: checkcast     #21                 // class java/lang/String
     155: astore        9
     157: aload         6
     159: invokevirtual #23                 // Method org/apache/maven/model/ActivationProperty.getValue:()Ljava/lang/String;
     162: astore        10
     164: aload         10
     166: invokestatic  #24                 // Method org/codehaus/plexus/util/StringUtils.isNotEmpty:(Ljava/lang/String;)Z
     169: ifeq          232
     172: iconst_0
     173: istore        11
     175: aload         10
     177: ldc           #5                  // String !
     179: invokevirtual #6                  // Method java/lang/String.startsWith:(Ljava/lang/String;)Z
     182: ifeq          196
     185: iconst_1
     186: istore        11
     188: aload         10
     190: iconst_1
     191: invokevirtual #7                  // Method java/lang/String.substring:(I)Ljava/lang/String;
     194: astore        10
     196: aload         10
     198: aload         9
     200: invokevirtual #25                 // Method java/lang/String.equals:(Ljava/lang/Object;)Z
     203: istore        12
     205: iload         11
     207: ifeq          225
     210: iload         12
     212: ifne          219
     215: iconst_1
     216: goto          220
     219: iconst_0
     220: istore        4
     222: goto          229
     225: iload         12
     227: istore        4
     229: goto          263
     232: aload         9
     234: invokestatic  #24                 // Method org/codehaus/plexus/util/StringUtils.isNotEmpty:(Ljava/lang/String;)Z
     237: istore        11
     239: iload         8
     241: ifeq          259
     244: iload         11
     246: ifne          253
     249: iconst_1
     250: goto          254
     253: iconst_0
     254: istore        4
     256: goto          263
     259: iload         11
     261: istore        4
     263: iload         4
     265: ireturn
}
