Compiled from "IdentitySet.java"
public class org.mockito.internal.util.collections.IdentitySet {
  private final java.util.LinkedList list;

  public org.mockito.internal.util.collections.IdentitySet();
    Code:
       0: aload_0
       1: invokespecial #1                  // Method java/lang/Object."<init>":()V
       4: aload_0
       5: new           #2                  // class java/util/LinkedList
       8: dup
       9: invokespecial #3                  // Method java/util/LinkedList."<init>":()V
      12: putfield      #4                  // Field list:Ljava/util/LinkedList;
      15: return

  public boolean contains(java.lang.Object);
    Code:
       0: aload_0
       1: getfield      #4                  // Field list:Ljava/util/LinkedList;
       4: invokevirtual #5                  // Method java/util/LinkedList.iterator:()Ljava/util/Iterator;
       7: astore_2
       8: aload_2
       9: invokeinterface #6,  1            // InterfaceMethod java/util/Iterator.hasNext:()Z
      14: ifeq          34
      17: aload_2
      18: invokeinterface #7,  1            // InterfaceMethod java/util/Iterator.next:()Ljava/lang/Object;
      23: astore_3
      24: aload_3
      25: aload_1
      26: if_acmpne     31
      29: iconst_1
      30: ireturn
      31: goto          8
      34: iconst_0
      35: ireturn

  public void add(java.lang.Object);
    Code:
       0: aload_0
       1: getfield      #4                  // Field list:Ljava/util/LinkedList;
       4: aload_1
       5: invokevirtual #8                  // Method java/util/LinkedList.add:(Ljava/lang/Object;)Z
       8: pop
       9: return
}
