Compiled from "ActionMethodTestCase.java"
public class juzu.impl.plugin.controller.ActionMethodTestCase extends juzu.test.AbstractTestCase {
  private java.lang.Class<?> aClass;

  private juzu.impl.plugin.application.descriptor.ApplicationDescriptor descriptor;

  private juzu.impl.plugin.controller.descriptor.ControllersDescriptor controllerDescriptor;

  public juzu.impl.plugin.controller.ActionMethodTestCase();
    Code:
       0: aload_0
       1: invokespecial #1                  // Method juzu/test/AbstractTestCase."<init>":()V
       4: return

  public void setUp() throws java.lang.Exception;
    Code:
       0: aload_0
       1: ldc           #2                  // String plugin.controller.method.action
       3: invokevirtual #3                  // Method compiler:(Ljava/lang/String;)Ljuzu/test/CompilerAssert;
       6: astore_1
       7: aload_1
       8: invokevirtual #4                  // Method juzu/test/CompilerAssert.assertCompile:()Ljuzu/impl/compiler/Compiler;
      11: pop
      12: aload_0
      13: aload_1
      14: ldc           #5                  // String plugin.controller.method.action.A
      16: invokevirtual #6                  // Method juzu/test/CompilerAssert.assertClass:(Ljava/lang/String;)Ljava/lang/Class;
      19: putfield      #7                  // Field aClass:Ljava/lang/Class;
      22: aload_1
      23: ldc           #8                  // String plugin.controller.method.action.A_
      25: invokevirtual #6                  // Method juzu/test/CompilerAssert.assertClass:(Ljava/lang/String;)Ljava/lang/Class;
      28: pop
      29: aload_1
      30: ldc           #9                  // String plugin.controller.method.action.Application
      32: invokevirtual #6                  // Method juzu/test/CompilerAssert.assertClass:(Ljava/lang/String;)Ljava/lang/Class;
      35: astore_2
      36: aload_0
      37: aload_2
      38: invokestatic  #10                 // Method juzu/impl/plugin/application/descriptor/ApplicationDescriptor.create:(Ljava/lang/Class;)Ljuzu/impl/plugin/application/descriptor/ApplicationDescriptor;
      41: putfield      #11                 // Field descriptor:Ljuzu/impl/plugin/application/descriptor/ApplicationDescriptor;
      44: aload_0
      45: new           #12                 // class juzu/impl/plugin/controller/descriptor/ControllersDescriptor
      48: dup
      49: aload_0
      50: getfield      #11                 // Field descriptor:Ljuzu/impl/plugin/application/descriptor/ApplicationDescriptor;
      53: invokespecial #13                 // Method juzu/impl/plugin/controller/descriptor/ControllersDescriptor."<init>":(Ljuzu/impl/plugin/application/descriptor/ApplicationDescriptor;)V
      56: putfield      #14                 // Field controllerDescriptor:Ljuzu/impl/plugin/controller/descriptor/ControllersDescriptor;
      59: return

  public void testNoArg() throws java.lang.Exception;
    Code:
       0: aload_0
       1: getfield      #14                 // Field controllerDescriptor:Ljuzu/impl/plugin/controller/descriptor/ControllersDescriptor;
       4: aload_0
       5: getfield      #7                  // Field aClass:Ljava/lang/Class;
       8: ldc           #15                 // String noArg
      10: iconst_0
      11: anewarray     #16                 // class java/lang/Class
      14: invokevirtual #17                 // Method juzu/impl/plugin/controller/descriptor/ControllersDescriptor.getMethod:(Ljava/lang/Class;Ljava/lang/String;[Ljava/lang/Class;)Ljuzu/impl/request/Method;
      17: astore_1
      18: ldc           #15                 // String noArg
      20: aload_1
      21: invokevirtual #18                 // Method juzu/impl/request/Method.getName:()Ljava/lang/String;
      24: invokestatic  #19                 // Method assertEquals:(Ljava/lang/String;Ljava/lang/String;)V
      27: getstatic     #20                 // Field juzu/request/Phase.ACTION:Ljuzu/request/Phase$Action;
      30: aload_1
      31: invokevirtual #21                 // Method juzu/impl/request/Method.getPhase:()Ljuzu/request/Phase;
      34: invokestatic  #22                 // Method assertEquals:(Ljava/lang/Object;Ljava/lang/Object;)V
      37: invokestatic  #23                 // Method java/util/Collections.emptyList:()Ljava/util/List;
      40: aload_1
      41: invokevirtual #24                 // Method juzu/impl/request/Method.getParameters:()Ljava/util/List;
      44: invokestatic  #25                 // Method assertEquals:(Ljava/util/List;Ljava/lang/Iterable;)V
      47: return

  public void testStringArg() throws java.lang.Exception;
    Code:
       0: aload_0
       1: getfield      #14                 // Field controllerDescriptor:Ljuzu/impl/plugin/controller/descriptor/ControllersDescriptor;
       4: aload_0
       5: getfield      #7                  // Field aClass:Ljava/lang/Class;
       8: ldc           #26                 // String oneArg
      10: iconst_1
      11: anewarray     #16                 // class java/lang/Class
      14: dup
      15: iconst_0
      16: ldc_w         #27                 // class java/lang/String
      19: aastore
      20: invokevirtual #17                 // Method juzu/impl/plugin/controller/descriptor/ControllersDescriptor.getMethod:(Ljava/lang/Class;Ljava/lang/String;[Ljava/lang/Class;)Ljuzu/impl/request/Method;
      23: astore_1
      24: ldc           #26                 // String oneArg
      26: aload_1
      27: invokevirtual #18                 // Method juzu/impl/request/Method.getName:()Ljava/lang/String;
      30: invokestatic  #19                 // Method assertEquals:(Ljava/lang/String;Ljava/lang/String;)V
      33: getstatic     #20                 // Field juzu/request/Phase.ACTION:Ljuzu/request/Phase$Action;
      36: aload_1
      37: invokevirtual #21                 // Method juzu/impl/request/Method.getPhase:()Ljuzu/request/Phase;
      40: invokestatic  #22                 // Method assertEquals:(Ljava/lang/Object;Ljava/lang/Object;)V
      43: iconst_1
      44: anewarray     #28                 // class juzu/impl/request/PhaseParameter
      47: dup
      48: iconst_0
      49: new           #28                 // class juzu/impl/request/PhaseParameter
      52: dup
      53: ldc           #29                 // String foo
      55: aconst_null
      56: getstatic     #30                 // Field juzu/impl/common/Cardinality.SINGLE:Ljuzu/impl/common/Cardinality;
      59: aconst_null
      60: invokespecial #31                 // Method juzu/impl/request/PhaseParameter."<init>":(Ljava/lang/String;Ljava/lang/Class;Ljuzu/impl/common/Cardinality;Ljava/lang/String;)V
      63: aastore
      64: invokestatic  #32                 // Method java/util/Arrays.asList:([Ljava/lang/Object;)Ljava/util/List;
      67: aload_1
      68: invokevirtual #24                 // Method juzu/impl/request/Method.getParameters:()Ljava/util/List;
      71: invokestatic  #25                 // Method assertEquals:(Ljava/util/List;Ljava/lang/Iterable;)V
      74: return
}
