Compiled from "CloseableIterator.java"
public abstract class org.sonar.core.util.CloseableIterator<O> implements java.util.Iterator<O>, java.lang.AutoCloseable {
  private O nextObject;

  boolean isClosed;

  private static final org.sonar.core.util.CloseableIterator<?> EMPTY_CLOSEABLE_ITERATOR;

  public org.sonar.core.util.CloseableIterator();
    Code:
       0: aload_0
       1: invokespecial #1                  // Method java/lang/Object."<init>":()V
       4: aload_0
       5: aconst_null
       6: putfield      #2                  // Field nextObject:Ljava/lang/Object;
       9: aload_0
      10: iconst_0
      11: putfield      #3                  // Field isClosed:Z
      14: return

  public static <T> org.sonar.core.util.CloseableIterator<T> emptyCloseableIterator();
    Code:
       0: getstatic     #4                  // Field EMPTY_CLOSEABLE_ITERATOR:Lorg/sonar/core/util/CloseableIterator;
       3: areturn

  public static <T> org.sonar.core.util.CloseableIterator<T> from(java.util.Iterator<T>);
    Code:
       0: aload_0
       1: invokestatic  #5                  // Method java/util/Objects.requireNonNull:(Ljava/lang/Object;)Ljava/lang/Object;
       4: pop
       5: aload_0
       6: instanceof    #6                  // class java/lang/AutoCloseable
       9: ifne          16
      12: iconst_1
      13: goto          17
      16: iconst_0
      17: ldc           #7                  // String This method does not support creating a CloseableIterator from an Iterator which is Closeable
      19: invokestatic  #8                  // Method com/google/common/base/Preconditions.checkArgument:(ZLjava/lang/Object;)V
      22: new           #9                  // class org/sonar/core/util/CloseableIterator$RegularIteratorWrapper
      25: dup
      26: aload_0
      27: invokespecial #10                 // Method org/sonar/core/util/CloseableIterator$RegularIteratorWrapper."<init>":(Ljava/util/Iterator;)V
      30: areturn

  public static <T> org.sonar.core.util.CloseableIterator<T> wrap(org.sonar.core.util.CloseableIterator<T>, java.lang.AutoCloseable...);
    Code:
       0: new           #11                 // class org/sonar/core/util/CloseableIterator$CloseablesIteratorWrapper
       3: dup
       4: aload_0
       5: aload_1
       6: aconst_null
       7: invokespecial #12                 // Method org/sonar/core/util/CloseableIterator$CloseablesIteratorWrapper."<init>":(Lorg/sonar/core/util/CloseableIterator;[Ljava/lang/AutoCloseable;Lorg/sonar/core/util/CloseableIterator$1;)V
      10: areturn

  public boolean hasNext();
    Code:
       0: aload_0
       1: getfield      #3                  // Field isClosed:Z
       4: ifeq          9
       7: iconst_0
       8: ireturn
       9: aload_0
      10: getfield      #2                  // Field nextObject:Ljava/lang/Object;
      13: ifnonnull     23
      16: aload_0
      17: invokespecial #13                 // Method bufferNext:()Ljava/lang/Object;
      20: ifnull        27
      23: iconst_1
      24: goto          28
      27: iconst_0
      28: istore_1
      29: iload_1
      30: ifne          37
      33: aload_0
      34: invokevirtual #14                 // Method close:()V
      37: iload_1
      38: ireturn

  private O bufferNext();
    Code:
       0: aload_0
       1: aload_0
       2: invokevirtual #15                 // Method doNext:()Ljava/lang/Object;
       5: putfield      #2                  // Field nextObject:Ljava/lang/Object;
       8: aload_0
       9: getfield      #2                  // Field nextObject:Ljava/lang/Object;
      12: areturn
      13: astore_1
      14: aload_0
      15: invokevirtual #14                 // Method close:()V
      18: aload_1
      19: athrow
    Exception table:
       from    to  target type
           0    12    13   Class java/lang/RuntimeException

  protected abstract O doNext();

  public O next();
    Code:
       0: aload_0
       1: invokevirtual #17                 // Method hasNext:()Z
       4: ifne          15
       7: new           #18                 // class java/util/NoSuchElementException
      10: dup
      11: invokespecial #19                 // Method java/util/NoSuchElementException."<init>":()V
      14: athrow
      15: aload_0
      16: getfield      #2                  // Field nextObject:Ljava/lang/Object;
      19: astore_1
      20: aload_0
      21: aconst_null
      22: putfield      #2                  // Field nextObject:Ljava/lang/Object;
      25: aload_1
      26: areturn

  public final void remove();
    Code:
       0: aload_0
       1: invokevirtual #20                 // Method doRemove:()V
       4: goto          14
       7: astore_1
       8: aload_0
       9: invokevirtual #14                 // Method close:()V
      12: aload_1
      13: athrow
      14: return
    Exception table:
       from    to  target type
           0     4     7   Class java/lang/RuntimeException

  protected void doRemove();
    Code:
       0: new           #21                 // class java/lang/UnsupportedOperationException
       3: dup
       4: ldc           #22                 // String remove() is not supported by default. Override doRemove() if needed.
       6: invokespecial #23                 // Method java/lang/UnsupportedOperationException."<init>":(Ljava/lang/String;)V
       9: athrow

  public final void close();
    Code:
       0: aload_0
       1: invokevirtual #24                 // Method doClose:()V
       4: aload_0
       5: iconst_1
       6: putfield      #3                  // Field isClosed:Z
       9: goto          18
      12: astore_1
      13: aload_1
      14: invokestatic  #26                 // Method com/google/common/base/Throwables.propagate:(Ljava/lang/Throwable;)Ljava/lang/RuntimeException;
      17: pop
      18: return
    Exception table:
       from    to  target type
           0     9    12   Class java/lang/Exception

  protected abstract void doClose() throws java.lang.Exception;

  static {};
    Code:
       0: new           #27                 // class org/sonar/core/util/CloseableIterator$1
       3: dup
       4: invokespecial #28                 // Method org/sonar/core/util/CloseableIterator$1."<init>":()V
       7: putstatic     #4                  // Field EMPTY_CLOSEABLE_ITERATOR:Lorg/sonar/core/util/CloseableIterator;
      10: return
}
