Compiled from "CoordinationOutcome.java"
public class com.arjuna.mw.wscf.model.twophase.outcomes.CoordinationOutcome implements com.arjuna.mw.wsas.activity.Outcome {
  private com.arjuna.mw.wsas.completionstatus.CompletionStatus _status;

  private int _twophaseOutcome;

  public com.arjuna.mw.wscf.model.twophase.outcomes.CoordinationOutcome(int);
    Code:
       0: aload_0
       1: invokestatic  #1                  // Method com/arjuna/mw/wsas/completionstatus/Success.instance:()Lcom/arjuna/mw/wsas/completionstatus/Success;
       4: iload_1
       5: invokespecial #2                  // Method "<init>":(Lcom/arjuna/mw/wsas/completionstatus/CompletionStatus;I)V
       8: return

  public com.arjuna.mw.wscf.model.twophase.outcomes.CoordinationOutcome(com.arjuna.mw.wsas.completionstatus.CompletionStatus, int);
    Code:
       0: aload_0
       1: invokespecial #3                  // Method java/lang/Object."<init>":()V
       4: aload_0
       5: aload_1
       6: putfield      #4                  // Field _status:Lcom/arjuna/mw/wsas/completionstatus/CompletionStatus;
       9: aload_0
      10: iload_2
      11: putfield      #5                  // Field _twophaseOutcome:I
      14: return

  public final int result();
    Code:
       0: aload_0
       1: getfield      #5                  // Field _twophaseOutcome:I
       4: ireturn

  public java.lang.String name() throws com.arjuna.mw.wsas.exceptions.SystemException;
    Code:
       0: ldc           #6                  // String org.w3c.wscf.twophase.outcomes.CoordinationOutcome
       2: areturn

  public com.arjuna.mw.wsas.completionstatus.CompletionStatus completedStatus() throws com.arjuna.mw.wsas.exceptions.SystemException;
    Code:
       0: aload_0
       1: getfield      #4                  // Field _status:Lcom/arjuna/mw/wsas/completionstatus/CompletionStatus;
       4: areturn

  public java.lang.Object data() throws com.arjuna.mw.wsas.exceptions.SystemException;
    Code:
       0: aconst_null
       1: areturn

  public java.lang.String toString();
    Code:
       0: new           #7                  // class java/lang/StringBuilder
       3: dup
       4: invokespecial #8                  // Method java/lang/StringBuilder."<init>":()V
       7: ldc           #9                  // String com.arjuna.mw.wscf.twophase.outcomes.CoordinationOutcome:
       9: invokevirtual #10                 // Method java/lang/StringBuilder.append:(Ljava/lang/String;)Ljava/lang/StringBuilder;
      12: aload_0
      13: getfield      #5                  // Field _twophaseOutcome:I
      16: invokestatic  #11                 // Method com/arjuna/mw/wscf/model/twophase/common/TwoPhaseResult.stringForm:(I)Ljava/lang/String;
      19: invokevirtual #10                 // Method java/lang/StringBuilder.append:(Ljava/lang/String;)Ljava/lang/StringBuilder;
      22: invokevirtual #12                 // Method java/lang/StringBuilder.toString:()Ljava/lang/String;
      25: areturn
}
