Compiled from "AutoValue_AlarmCallbackSummary.java"
final class org.graylog2.rest.models.alarmcallbacks.AutoValue_AlarmCallbackSummary extends org.graylog2.rest.models.alarmcallbacks.$AutoValue_AlarmCallbackSummary {
  org.graylog2.rest.models.alarmcallbacks.AutoValue_AlarmCallbackSummary(java.lang.String, java.lang.String, java.lang.String, java.lang.String, java.util.Map<java.lang.String, java.lang.Object>, java.util.Date, java.lang.String);
    Code:
       0: aload_0
       1: aload_1
       2: aload_2
       3: aload_3
       4: aload         4
       6: aload         5
       8: aload         6
      10: aload         7
      12: invokespecial #1                  // Method org/graylog2/rest/models/alarmcallbacks/$AutoValue_AlarmCallbackSummary."<init>":(Ljava/lang/String;Ljava/lang/String;Ljava/lang/String;Ljava/lang/String;Ljava/util/Map;Ljava/util/Date;Ljava/lang/String;)V
      15: return

  public final java.lang.String getId();
    Code:
       0: aload_0
       1: invokevirtual #2                  // Method id:()Ljava/lang/String;
       4: areturn

  public final java.lang.String getStreamId();
    Code:
       0: aload_0
       1: invokevirtual #3                  // Method streamId:()Ljava/lang/String;
       4: areturn

  public final java.lang.String getType();
    Code:
       0: aload_0
       1: invokevirtual #4                  // Method type:()Ljava/lang/String;
       4: areturn

  public final java.lang.String getTitle();
    Code:
       0: aload_0
       1: invokevirtual #5                  // Method title:()Ljava/lang/String;
       4: areturn

  public final java.util.Map<java.lang.String, java.lang.Object> getConfiguration();
    Code:
       0: aload_0
       1: invokevirtual #6                  // Method configuration:()Ljava/util/Map;
       4: areturn

  public final java.util.Date getCreatedAt();
    Code:
       0: aload_0
       1: invokevirtual #7                  // Method createdAt:()Ljava/util/Date;
       4: areturn

  public final java.lang.String getCreatorUserId();
    Code:
       0: aload_0
       1: invokevirtual #8                  // Method creatorUserId:()Ljava/lang/String;
       4: areturn
}
