Compiled from "EditGrapheme.scala"
public final class de.sciss.lucre.edit.EditGrapheme {
  public static <T extends de.sciss.lucre.Txn<T>> void add(de.sciss.proc.Grapheme$Modifiable<T>, de.sciss.lucre.LongObj<T>, de.sciss.lucre.Obj<T>, T);
    Code:
       0: getstatic     #25                 // Field de/sciss/lucre/edit/EditGrapheme$.MODULE$:Lde/sciss/lucre/edit/EditGrapheme$;
       3: aload_0
       4: aload_1
       5: aload_2
       6: aload_3
       7: invokevirtual #27                 // Method de/sciss/lucre/edit/EditGrapheme$.add:(Lde/sciss/proc/Grapheme$Modifiable;Lde/sciss/lucre/LongObj;Lde/sciss/lucre/Obj;Lde/sciss/lucre/Txn;)V
      10: return

  public static <T extends de.sciss.lucre.Txn<T>> void addUndo(de.sciss.proc.Grapheme$Modifiable<T>, de.sciss.lucre.LongObj<T>, de.sciss.lucre.Obj<T>, T, de.sciss.lucre.edit.UndoManager<T>);
    Code:
       0: getstatic     #25                 // Field de/sciss/lucre/edit/EditGrapheme$.MODULE$:Lde/sciss/lucre/edit/EditGrapheme$;
       3: aload_0
       4: aload_1
       5: aload_2
       6: aload_3
       7: aload         4
       9: invokevirtual #32                 // Method de/sciss/lucre/edit/EditGrapheme$.addUndo:(Lde/sciss/proc/Grapheme$Modifiable;Lde/sciss/lucre/LongObj;Lde/sciss/lucre/Obj;Lde/sciss/lucre/Txn;Lde/sciss/lucre/edit/UndoManager;)V
      12: return

  public static <T extends de.sciss.lucre.Txn<T>> void remove(de.sciss.proc.Grapheme$Modifiable<T>, de.sciss.lucre.LongObj<T>, de.sciss.lucre.Obj<T>, T);
    Code:
       0: getstatic     #25                 // Field de/sciss/lucre/edit/EditGrapheme$.MODULE$:Lde/sciss/lucre/edit/EditGrapheme$;
       3: aload_0
       4: aload_1
       5: aload_2
       6: aload_3
       7: invokevirtual #35                 // Method de/sciss/lucre/edit/EditGrapheme$.remove:(Lde/sciss/proc/Grapheme$Modifiable;Lde/sciss/lucre/LongObj;Lde/sciss/lucre/Obj;Lde/sciss/lucre/Txn;)V
      10: return

  public static <T extends de.sciss.lucre.Txn<T>> void removeUndo(de.sciss.proc.Grapheme$Modifiable<T>, de.sciss.lucre.LongObj<T>, de.sciss.lucre.Obj<T>, T, de.sciss.lucre.edit.UndoManager<T>);
    Code:
       0: getstatic     #25                 // Field de/sciss/lucre/edit/EditGrapheme$.MODULE$:Lde/sciss/lucre/edit/EditGrapheme$;
       3: aload_0
       4: aload_1
       5: aload_2
       6: aload_3
       7: aload         4
       9: invokevirtual #38                 // Method de/sciss/lucre/edit/EditGrapheme$.removeUndo:(Lde/sciss/proc/Grapheme$Modifiable;Lde/sciss/lucre/LongObj;Lde/sciss/lucre/Obj;Lde/sciss/lucre/Txn;Lde/sciss/lucre/edit/UndoManager;)V
      12: return
}
