Compiled from "EnumDeserializer.java"
public class org.elasticsearch.hadoop.thirdparty.codehaus.jackson.map.deser.EnumDeserializer extends org.elasticsearch.hadoop.thirdparty.codehaus.jackson.map.deser.StdScalarDeserializer<java.lang.Enum<?>> {
  final org.elasticsearch.hadoop.thirdparty.codehaus.jackson.map.deser.EnumResolver<?> _resolver;

  public org.elasticsearch.hadoop.thirdparty.codehaus.jackson.map.deser.EnumDeserializer(org.elasticsearch.hadoop.thirdparty.codehaus.jackson.map.deser.EnumResolver<?>);
    Code:
       0: aload_0
       1: ldc           #23                 // class java/lang/Enum
       3: invokespecial #26                 // Method org/elasticsearch/hadoop/thirdparty/codehaus/jackson/map/deser/StdScalarDeserializer."<init>":(Ljava/lang/Class;)V
       6: aload_0
       7: aload_1
       8: putfield      #28                 // Field _resolver:Lorg/elasticsearch/hadoop/thirdparty/codehaus/jackson/map/deser/EnumResolver;
      11: return

  public static org.elasticsearch.hadoop.thirdparty.codehaus.jackson.map.JsonDeserializer<?> deserializerForCreator(org.elasticsearch.hadoop.thirdparty.codehaus.jackson.map.DeserializationConfig, java.lang.Class<?>, org.elasticsearch.hadoop.thirdparty.codehaus.jackson.map.introspect.AnnotatedMethod);
    Code:
       0: aload_2
       1: iconst_0
       2: invokevirtual #40                 // Method org/elasticsearch/hadoop/thirdparty/codehaus/jackson/map/introspect/AnnotatedMethod.getParameterType:(I)Ljava/lang/reflect/Type;
       5: ldc           #42                 // class java/lang/String
       7: if_acmpeq     42
      10: new           #44                 // class java/lang/IllegalArgumentException
      13: dup
      14: new           #46                 // class java/lang/StringBuilder
      17: dup
      18: invokespecial #49                 // Method java/lang/StringBuilder."<init>":()V
      21: ldc           #51                 // String Parameter #0 type for factory method (
      23: invokevirtual #55                 // Method java/lang/StringBuilder.append:(Ljava/lang/String;)Ljava/lang/StringBuilder;
      26: aload_2
      27: invokevirtual #58                 // Method java/lang/StringBuilder.append:(Ljava/lang/Object;)Ljava/lang/StringBuilder;
      30: ldc           #60                 // String ) not suitable, must be java.lang.String
      32: invokevirtual #55                 // Method java/lang/StringBuilder.append:(Ljava/lang/String;)Ljava/lang/StringBuilder;
      35: invokevirtual #64                 // Method java/lang/StringBuilder.toString:()Ljava/lang/String;
      38: invokespecial #67                 // Method java/lang/IllegalArgumentException."<init>":(Ljava/lang/String;)V
      41: athrow
      42: aload_0
      43: getstatic     #71                 // Field org/elasticsearch/hadoop/thirdparty/codehaus/jackson/map/DeserializationConfig$Feature.CAN_OVERRIDE_ACCESS_MODIFIERS:Lorg/elasticsearch/hadoop/thirdparty/codehaus/jackson/map/DeserializationConfig$Feature;
      46: invokevirtual #75                 // Method org/elasticsearch/hadoop/thirdparty/codehaus/jackson/map/DeserializationConfig.isEnabled:(Lorg/elasticsearch/hadoop/thirdparty/codehaus/jackson/map/DeserializationConfig$Feature;)Z
      49: ifeq          59
      52: aload_2
      53: invokevirtual #79                 // Method org/elasticsearch/hadoop/thirdparty/codehaus/jackson/map/introspect/AnnotatedMethod.getMember:()Ljava/lang/reflect/Member;
      56: invokestatic  #85                 // Method org/elasticsearch/hadoop/thirdparty/codehaus/jackson/map/util/ClassUtil.checkAndFixAccess:(Ljava/lang/reflect/Member;)V
      59: new           #9                  // class org/elasticsearch/hadoop/thirdparty/codehaus/jackson/map/deser/EnumDeserializer$FactoryBasedDeserializer
      62: dup
      63: aload_1
      64: aload_2
      65: invokespecial #88                 // Method org/elasticsearch/hadoop/thirdparty/codehaus/jackson/map/deser/EnumDeserializer$FactoryBasedDeserializer."<init>":(Ljava/lang/Class;Lorg/elasticsearch/hadoop/thirdparty/codehaus/jackson/map/introspect/AnnotatedMethod;)V
      68: areturn

  public java.lang.Enum<?> deserialize(org.elasticsearch.hadoop.thirdparty.codehaus.jackson.JsonParser, org.elasticsearch.hadoop.thirdparty.codehaus.jackson.map.DeserializationContext) throws java.io.IOException, org.elasticsearch.hadoop.thirdparty.codehaus.jackson.JsonProcessingException;
    Code:
       0: aload_1
       1: invokevirtual #108                // Method org/elasticsearch/hadoop/thirdparty/codehaus/jackson/JsonParser.getCurrentToken:()Lorg/elasticsearch/hadoop/thirdparty/codehaus/jackson/JsonToken;
       4: astore_3
       5: aload_3
       6: getstatic     #114                // Field org/elasticsearch/hadoop/thirdparty/codehaus/jackson/JsonToken.VALUE_STRING:Lorg/elasticsearch/hadoop/thirdparty/codehaus/jackson/JsonToken;
       9: if_acmpeq     19
      12: aload_3
      13: getstatic     #117                // Field org/elasticsearch/hadoop/thirdparty/codehaus/jackson/JsonToken.FIELD_NAME:Lorg/elasticsearch/hadoop/thirdparty/codehaus/jackson/JsonToken;
      16: if_acmpne     58
      19: aload_1
      20: invokevirtual #120                // Method org/elasticsearch/hadoop/thirdparty/codehaus/jackson/JsonParser.getText:()Ljava/lang/String;
      23: astore        4
      25: aload_0
      26: getfield      #28                 // Field _resolver:Lorg/elasticsearch/hadoop/thirdparty/codehaus/jackson/map/deser/EnumResolver;
      29: aload         4
      31: invokevirtual #126                // Method org/elasticsearch/hadoop/thirdparty/codehaus/jackson/map/deser/EnumResolver.findEnum:(Ljava/lang/String;)Ljava/lang/Enum;
      34: astore        5
      36: aload         5
      38: ifnonnull     55
      41: aload_2
      42: aload_0
      43: getfield      #28                 // Field _resolver:Lorg/elasticsearch/hadoop/thirdparty/codehaus/jackson/map/deser/EnumResolver;
      46: invokevirtual #130                // Method org/elasticsearch/hadoop/thirdparty/codehaus/jackson/map/deser/EnumResolver.getEnumClass:()Ljava/lang/Class;
      49: ldc           #132                // String value not one of declared Enum instance names
      51: invokevirtual #138                // Method org/elasticsearch/hadoop/thirdparty/codehaus/jackson/map/DeserializationContext.weirdStringException:(Ljava/lang/Class;Ljava/lang/String;)Lorg/elasticsearch/hadoop/thirdparty/codehaus/jackson/map/JsonMappingException;
      54: athrow
      55: aload         5
      57: areturn
      58: aload_3
      59: getstatic     #141                // Field org/elasticsearch/hadoop/thirdparty/codehaus/jackson/JsonToken.VALUE_NUMBER_INT:Lorg/elasticsearch/hadoop/thirdparty/codehaus/jackson/JsonToken;
      62: if_acmpne     149
      65: aload_2
      66: getstatic     #144                // Field org/elasticsearch/hadoop/thirdparty/codehaus/jackson/map/DeserializationConfig$Feature.FAIL_ON_NUMBERS_FOR_ENUMS:Lorg/elasticsearch/hadoop/thirdparty/codehaus/jackson/map/DeserializationConfig$Feature;
      69: invokevirtual #145                // Method org/elasticsearch/hadoop/thirdparty/codehaus/jackson/map/DeserializationContext.isEnabled:(Lorg/elasticsearch/hadoop/thirdparty/codehaus/jackson/map/DeserializationConfig$Feature;)Z
      72: ifeq          82
      75: aload_2
      76: ldc           #147                // String Not allowed to deserialize Enum value out of JSON number (disable DeserializationConfig.Feature.FAIL_ON_NUMBERS_FOR_ENUMS to allow)
      78: invokevirtual #151                // Method org/elasticsearch/hadoop/thirdparty/codehaus/jackson/map/DeserializationContext.mappingException:(Ljava/lang/String;)Lorg/elasticsearch/hadoop/thirdparty/codehaus/jackson/map/JsonMappingException;
      81: athrow
      82: aload_1
      83: invokevirtual #155                // Method org/elasticsearch/hadoop/thirdparty/codehaus/jackson/JsonParser.getIntValue:()I
      86: istore        4
      88: aload_0
      89: getfield      #28                 // Field _resolver:Lorg/elasticsearch/hadoop/thirdparty/codehaus/jackson/map/deser/EnumResolver;
      92: iload         4
      94: invokevirtual #159                // Method org/elasticsearch/hadoop/thirdparty/codehaus/jackson/map/deser/EnumResolver.getEnum:(I)Ljava/lang/Enum;
      97: astore        5
      99: aload         5
     101: ifnonnull     146
     104: aload_2
     105: aload_0
     106: getfield      #28                 // Field _resolver:Lorg/elasticsearch/hadoop/thirdparty/codehaus/jackson/map/deser/EnumResolver;
     109: invokevirtual #130                // Method org/elasticsearch/hadoop/thirdparty/codehaus/jackson/map/deser/EnumResolver.getEnumClass:()Ljava/lang/Class;
     112: new           #46                 // class java/lang/StringBuilder
     115: dup
     116: invokespecial #49                 // Method java/lang/StringBuilder."<init>":()V
     119: ldc           #161                // String index value outside legal index range [0..
     121: invokevirtual #55                 // Method java/lang/StringBuilder.append:(Ljava/lang/String;)Ljava/lang/StringBuilder;
     124: aload_0
     125: getfield      #28                 // Field _resolver:Lorg/elasticsearch/hadoop/thirdparty/codehaus/jackson/map/deser/EnumResolver;
     128: invokevirtual #164                // Method org/elasticsearch/hadoop/thirdparty/codehaus/jackson/map/deser/EnumResolver.lastValidIndex:()I
     131: invokevirtual #167                // Method java/lang/StringBuilder.append:(I)Ljava/lang/StringBuilder;
     134: ldc           #169                // String ]
     136: invokevirtual #55                 // Method java/lang/StringBuilder.append:(Ljava/lang/String;)Ljava/lang/StringBuilder;
     139: invokevirtual #64                 // Method java/lang/StringBuilder.toString:()Ljava/lang/String;
     142: invokevirtual #172                // Method org/elasticsearch/hadoop/thirdparty/codehaus/jackson/map/DeserializationContext.weirdNumberException:(Ljava/lang/Class;Ljava/lang/String;)Lorg/elasticsearch/hadoop/thirdparty/codehaus/jackson/map/JsonMappingException;
     145: athrow
     146: aload         5
     148: areturn
     149: aload_2
     150: aload_0
     151: getfield      #28                 // Field _resolver:Lorg/elasticsearch/hadoop/thirdparty/codehaus/jackson/map/deser/EnumResolver;
     154: invokevirtual #130                // Method org/elasticsearch/hadoop/thirdparty/codehaus/jackson/map/deser/EnumResolver.getEnumClass:()Ljava/lang/Class;
     157: invokevirtual #175                // Method org/elasticsearch/hadoop/thirdparty/codehaus/jackson/map/DeserializationContext.mappingException:(Ljava/lang/Class;)Lorg/elasticsearch/hadoop/thirdparty/codehaus/jackson/map/JsonMappingException;
     160: athrow

  public java.lang.Object deserialize(org.elasticsearch.hadoop.thirdparty.codehaus.jackson.JsonParser, org.elasticsearch.hadoop.thirdparty.codehaus.jackson.map.DeserializationContext) throws java.io.IOException, org.elasticsearch.hadoop.thirdparty.codehaus.jackson.JsonProcessingException;
    Code:
       0: aload_0
       1: aload_1
       2: aload_2
       3: invokevirtual #190                // Method deserialize:(Lorg/elasticsearch/hadoop/thirdparty/codehaus/jackson/JsonParser;Lorg/elasticsearch/hadoop/thirdparty/codehaus/jackson/map/DeserializationContext;)Ljava/lang/Enum;
       6: areturn
}
