Compiled from "FromStringDeserializer.java"
public class org.elasticsearch.hadoop.thirdparty.codehaus.jackson.map.deser.FromStringDeserializer$InetAddressDeserializer extends org.elasticsearch.hadoop.thirdparty.codehaus.jackson.map.deser.FromStringDeserializer<java.net.InetAddress> {
  public org.elasticsearch.hadoop.thirdparty.codehaus.jackson.map.deser.FromStringDeserializer$InetAddressDeserializer();
    Code:
       0: aload_0
       1: ldc           #11                 // class java/net/InetAddress
       3: invokespecial #14                 // Method org/elasticsearch/hadoop/thirdparty/codehaus/jackson/map/deser/FromStringDeserializer."<init>":(Ljava/lang/Class;)V
       6: return

  protected java.net.InetAddress _deserialize(java.lang.String, org.elasticsearch.hadoop.thirdparty.codehaus.jackson.map.DeserializationContext) throws java.io.IOException;
    Code:
       0: aload_1
       1: invokestatic  #24                 // Method java/net/InetAddress.getByName:(Ljava/lang/String;)Ljava/net/InetAddress;
       4: areturn

  protected java.lang.Object _deserialize(java.lang.String, org.elasticsearch.hadoop.thirdparty.codehaus.jackson.map.DeserializationContext) throws java.io.IOException, org.elasticsearch.hadoop.thirdparty.codehaus.jackson.JsonProcessingException;
    Code:
       0: aload_0
       1: aload_1
       2: aload_2
       3: invokevirtual #33                 // Method _deserialize:(Ljava/lang/String;Lorg/elasticsearch/hadoop/thirdparty/codehaus/jackson/map/DeserializationContext;)Ljava/net/InetAddress;
       6: areturn
}
