Compiled from "httpMessage.kt"
final class org.http4k.kotest.HttpMessageKt$haveBody$5 extends kotlin.jvm.internal.Lambda implements kotlin.jvm.functions.Function1<org.http4k.core.HttpMessage, java.lang.String> {
  final org.http4k.format.Json<NODE> $this_haveBody;

  org.http4k.kotest.HttpMessageKt$haveBody$5(org.http4k.format.Json<NODE>);
    Code:
       0: aload_0
       1: aload_1
       2: putfield      #14                 // Field $this_haveBody:Lorg/http4k/format/Json;
       5: aload_0
       6: iconst_1
       7: invokespecial #17                 // Method kotlin/jvm/internal/Lambda."<init>":(I)V
      10: return

  public final java.lang.String invoke(org.http4k.core.HttpMessage);
    Code:
       0: aload_1
       1: ldc           #25                 // String m
       3: invokestatic  #31                 // Method kotlin/jvm/internal/Intrinsics.checkNotNullParameter:(Ljava/lang/Object;Ljava/lang/String;)V
       6: aload_0
       7: getfield      #14                 // Field $this_haveBody:Lorg/http4k/format/Json;
      10: aload_0
      11: getfield      #14                 // Field $this_haveBody:Lorg/http4k/format/Json;
      14: aload_1
      15: invokeinterface #37,  1           // InterfaceMethod org/http4k/core/HttpMessage.bodyString:()Ljava/lang/String;
      20: invokeinterface #43,  2           // InterfaceMethod org/http4k/format/Json.parse:(Ljava/lang/String;)Ljava/lang/Object;
      25: invokeinterface #47,  2           // InterfaceMethod org/http4k/format/Json.compact:(Ljava/lang/Object;)Ljava/lang/String;
      30: areturn

  public java.lang.Object invoke(java.lang.Object);
    Code:
       0: aload_0
       1: aload_1
       2: checkcast     #33                 // class org/http4k/core/HttpMessage
       5: invokevirtual #51                 // Method invoke:(Lorg/http4k/core/HttpMessage;)Ljava/lang/String;
       8: areturn
}
