Compiled from "NexusStatus.java"
public class org.sonatype.nexus.client.core.NexusStatus {
  private final java.lang.String appName;

  private final java.lang.String formattedAppName;

  private final java.lang.String version;

  private final java.lang.String apiVersion;

  private final java.lang.String editionLong;

  private final java.lang.String editionShort;

  private final java.lang.String state;

  private final java.util.Date initializedAt;

  private final java.util.Date startedAt;

  private final java.util.Date lastConfigChange;

  private final long lastConfigGeneration;

  private final boolean firstStart;

  private final boolean instanceUpgraded;

  private final boolean configurationUpgraded;

  private final java.lang.String baseUrl;

  public org.sonatype.nexus.client.core.NexusStatus(java.lang.String, java.lang.String, java.lang.String, java.lang.String, java.lang.String, java.lang.String, java.lang.String, java.util.Date, java.util.Date, java.util.Date, long, boolean, boolean, boolean, java.lang.String);
    Code:
       0: aload_0
       1: invokespecial #1                  // Method java/lang/Object."<init>":()V
       4: aload_0
       5: aload_1
       6: putfield      #2                  // Field appName:Ljava/lang/String;
       9: aload_0
      10: aload_2
      11: putfield      #3                  // Field formattedAppName:Ljava/lang/String;
      14: aload_0
      15: aload_3
      16: putfield      #4                  // Field version:Ljava/lang/String;
      19: aload_0
      20: aload         4
      22: putfield      #5                  // Field apiVersion:Ljava/lang/String;
      25: aload_0
      26: aload         5
      28: putfield      #6                  // Field editionLong:Ljava/lang/String;
      31: aload_0
      32: aload         6
      34: putfield      #7                  // Field editionShort:Ljava/lang/String;
      37: aload_0
      38: aload         7
      40: putfield      #8                  // Field state:Ljava/lang/String;
      43: aload_0
      44: aload         8
      46: putfield      #9                  // Field initializedAt:Ljava/util/Date;
      49: aload_0
      50: aload         9
      52: putfield      #10                 // Field startedAt:Ljava/util/Date;
      55: aload_0
      56: aload         10
      58: putfield      #11                 // Field lastConfigChange:Ljava/util/Date;
      61: aload_0
      62: lload         11
      64: putfield      #12                 // Field lastConfigGeneration:J
      67: aload_0
      68: iload         13
      70: putfield      #13                 // Field firstStart:Z
      73: aload_0
      74: iload         14
      76: putfield      #14                 // Field instanceUpgraded:Z
      79: aload_0
      80: iload         15
      82: putfield      #15                 // Field configurationUpgraded:Z
      85: aload_0
      86: aload         16
      88: putfield      #16                 // Field baseUrl:Ljava/lang/String;
      91: return

  public java.lang.String getAppName();
    Code:
       0: aload_0
       1: getfield      #2                  // Field appName:Ljava/lang/String;
       4: areturn

  public java.lang.String getFormattedAppName();
    Code:
       0: aload_0
       1: getfield      #3                  // Field formattedAppName:Ljava/lang/String;
       4: areturn

  public java.lang.String getVersion();
    Code:
       0: aload_0
       1: getfield      #4                  // Field version:Ljava/lang/String;
       4: areturn

  public java.lang.String getApiVersion();
    Code:
       0: aload_0
       1: getfield      #5                  // Field apiVersion:Ljava/lang/String;
       4: areturn

  public java.lang.String getEditionLong();
    Code:
       0: aload_0
       1: getfield      #6                  // Field editionLong:Ljava/lang/String;
       4: areturn

  public java.lang.String getEditionShort();
    Code:
       0: aload_0
       1: getfield      #7                  // Field editionShort:Ljava/lang/String;
       4: areturn

  public java.lang.String getState();
    Code:
       0: aload_0
       1: getfield      #8                  // Field state:Ljava/lang/String;
       4: areturn

  public java.util.Date getInitializedAt();
    Code:
       0: aload_0
       1: getfield      #9                  // Field initializedAt:Ljava/util/Date;
       4: areturn

  public java.util.Date getStartedAt();
    Code:
       0: aload_0
       1: getfield      #10                 // Field startedAt:Ljava/util/Date;
       4: areturn

  public java.util.Date getLastConfigChange();
    Code:
       0: aload_0
       1: getfield      #11                 // Field lastConfigChange:Ljava/util/Date;
       4: areturn

  public long getLastConfigGeneration();
    Code:
       0: aload_0
       1: getfield      #12                 // Field lastConfigGeneration:J
       4: lreturn

  public boolean isFirstStart();
    Code:
       0: aload_0
       1: getfield      #13                 // Field firstStart:Z
       4: ireturn

  public boolean isInstanceUpgraded();
    Code:
       0: aload_0
       1: getfield      #14                 // Field instanceUpgraded:Z
       4: ireturn

  public boolean isConfigurationUpgraded();
    Code:
       0: aload_0
       1: getfield      #15                 // Field configurationUpgraded:Z
       4: ireturn

  public java.lang.String getBaseUrl();
    Code:
       0: aload_0
       1: getfield      #16                 // Field baseUrl:Ljava/lang/String;
       4: areturn

  public java.lang.String toString();
    Code:
       0: new           #17                 // class java/lang/StringBuilder
       3: dup
       4: invokespecial #18                 // Method java/lang/StringBuilder."<init>":()V
       7: ldc           #19                 // String NexusStatus [appName=
       9: invokevirtual #20                 // Method java/lang/StringBuilder.append:(Ljava/lang/String;)Ljava/lang/StringBuilder;
      12: aload_0
      13: getfield      #2                  // Field appName:Ljava/lang/String;
      16: invokevirtual #20                 // Method java/lang/StringBuilder.append:(Ljava/lang/String;)Ljava/lang/StringBuilder;
      19: ldc           #21                 // String , version=
      21: invokevirtual #20                 // Method java/lang/StringBuilder.append:(Ljava/lang/String;)Ljava/lang/StringBuilder;
      24: aload_0
      25: getfield      #4                  // Field version:Ljava/lang/String;
      28: invokevirtual #20                 // Method java/lang/StringBuilder.append:(Ljava/lang/String;)Ljava/lang/StringBuilder;
      31: ldc           #22                 // String , editionShort=
      33: invokevirtual #20                 // Method java/lang/StringBuilder.append:(Ljava/lang/String;)Ljava/lang/StringBuilder;
      36: aload_0
      37: getfield      #7                  // Field editionShort:Ljava/lang/String;
      40: invokevirtual #20                 // Method java/lang/StringBuilder.append:(Ljava/lang/String;)Ljava/lang/StringBuilder;
      43: ldc           #23                 // String ]
      45: invokevirtual #20                 // Method java/lang/StringBuilder.append:(Ljava/lang/String;)Ljava/lang/StringBuilder;
      48: invokevirtual #24                 // Method java/lang/StringBuilder.toString:()Ljava/lang/String;
      51: areturn
}
