Compiled from "facet.kt"
public final class org.jetbrains.kotlinx.ggdsl.letsplot.facet.FacetKt {
  public static final void facetGrid(org.jetbrains.kotlinx.ggdsl.dsl.PlotContext, org.jetbrains.kotlinx.ggdsl.ir.data.DataSource<?>, org.jetbrains.kotlinx.ggdsl.ir.data.DataSource<?>, org.jetbrains.kotlinx.ggdsl.letsplot.facet.ScalesSharing, org.jetbrains.kotlinx.ggdsl.letsplot.facet.OrderDirection, org.jetbrains.kotlinx.ggdsl.letsplot.facet.OrderDirection, java.lang.String, java.lang.String);
    Code:
       0: aload_0
       1: ldc           #11                 // String <this>
       3: invokestatic  #17                 // Method kotlin/jvm/internal/Intrinsics.checkNotNullParameter:(Ljava/lang/Object;Ljava/lang/String;)V
       6: aload         4
       8: ldc           #19                 // String xOrder
      10: invokestatic  #17                 // Method kotlin/jvm/internal/Intrinsics.checkNotNullParameter:(Ljava/lang/Object;Ljava/lang/String;)V
      13: aload         5
      15: ldc           #21                 // String yOrder
      17: invokestatic  #17                 // Method kotlin/jvm/internal/Intrinsics.checkNotNullParameter:(Ljava/lang/Object;Ljava/lang/String;)V
      20: nop
      21: aload_0
      22: invokevirtual #27                 // Method org/jetbrains/kotlinx/ggdsl/dsl/PlotContext.getFeatures:()Ljava/util/Map;
      25: getstatic     #33                 // Field org/jetbrains/kotlinx/ggdsl/letsplot/facet/FacetGridFeature.Companion:Lorg/jetbrains/kotlinx/ggdsl/letsplot/facet/FacetGridFeature$Companion;
      28: invokevirtual #39                 // Method org/jetbrains/kotlinx/ggdsl/letsplot/facet/FacetGridFeature$Companion.getFEATURE_NAME:()Lorg/jetbrains/kotlinx/ggdsl/ir/feature/FeatureName;
      31: new           #29                 // class org/jetbrains/kotlinx/ggdsl/letsplot/facet/FacetGridFeature
      34: dup
      35: aload_1
      36: dup
      37: ifnull        46
      40: invokevirtual #45                 // Method org/jetbrains/kotlinx/ggdsl/ir/data/DataSource.getId:()Ljava/lang/String;
      43: goto          48
      46: pop
      47: aconst_null
      48: aload_2
      49: dup
      50: ifnull        59
      53: invokevirtual #45                 // Method org/jetbrains/kotlinx/ggdsl/ir/data/DataSource.getId:()Ljava/lang/String;
      56: goto          61
      59: pop
      60: aconst_null
      61: aload_3
      62: aload         4
      64: aload         5
      66: aload         6
      68: aload         7
      70: invokespecial #49                 // Method org/jetbrains/kotlinx/ggdsl/letsplot/facet/FacetGridFeature."<init>":(Ljava/lang/String;Ljava/lang/String;Lorg/jetbrains/kotlinx/ggdsl/letsplot/facet/ScalesSharing;Lorg/jetbrains/kotlinx/ggdsl/letsplot/facet/OrderDirection;Lorg/jetbrains/kotlinx/ggdsl/letsplot/facet/OrderDirection;Ljava/lang/String;Ljava/lang/String;)V
      73: invokeinterface #55,  3           // InterfaceMethod java/util/Map.put:(Ljava/lang/Object;Ljava/lang/Object;)Ljava/lang/Object;
      78: pop
      79: return

  public static void facetGrid$default(org.jetbrains.kotlinx.ggdsl.dsl.PlotContext, org.jetbrains.kotlinx.ggdsl.ir.data.DataSource, org.jetbrains.kotlinx.ggdsl.ir.data.DataSource, org.jetbrains.kotlinx.ggdsl.letsplot.facet.ScalesSharing, org.jetbrains.kotlinx.ggdsl.letsplot.facet.OrderDirection, org.jetbrains.kotlinx.ggdsl.letsplot.facet.OrderDirection, java.lang.String, java.lang.String, int, java.lang.Object);
    Code:
       0: iload         8
       2: iconst_1
       3: iand
       4: ifeq          9
       7: aconst_null
       8: astore_1
       9: iload         8
      11: iconst_2
      12: iand
      13: ifeq          18
      16: aconst_null
      17: astore_2
      18: iload         8
      20: iconst_4
      21: iand
      22: ifeq          27
      25: aconst_null
      26: astore_3
      27: iload         8
      29: bipush        8
      31: iand
      32: ifeq          43
      35: getstatic     #79                 // Field org/jetbrains/kotlinx/ggdsl/letsplot/facet/OrderDirection.Companion:Lorg/jetbrains/kotlinx/ggdsl/letsplot/facet/OrderDirection$Companion;
      38: invokevirtual #85                 // Method org/jetbrains/kotlinx/ggdsl/letsplot/facet/OrderDirection$Companion.getASCENDING:()Lorg/jetbrains/kotlinx/ggdsl/letsplot/facet/OrderDirection;
      41: astore        4
      43: iload         8
      45: bipush        16
      47: iand
      48: ifeq          59
      51: getstatic     #79                 // Field org/jetbrains/kotlinx/ggdsl/letsplot/facet/OrderDirection.Companion:Lorg/jetbrains/kotlinx/ggdsl/letsplot/facet/OrderDirection$Companion;
      54: invokevirtual #85                 // Method org/jetbrains/kotlinx/ggdsl/letsplot/facet/OrderDirection$Companion.getASCENDING:()Lorg/jetbrains/kotlinx/ggdsl/letsplot/facet/OrderDirection;
      57: astore        5
      59: iload         8
      61: bipush        32
      63: iand
      64: ifeq          70
      67: aconst_null
      68: astore        6
      70: iload         8
      72: bipush        64
      74: iand
      75: ifeq          81
      78: aconst_null
      79: astore        7
      81: aload_0
      82: aload_1
      83: aload_2
      84: aload_3
      85: aload         4
      87: aload         5
      89: aload         6
      91: aload         7
      93: invokestatic  #87                 // Method facetGrid:(Lorg/jetbrains/kotlinx/ggdsl/dsl/PlotContext;Lorg/jetbrains/kotlinx/ggdsl/ir/data/DataSource;Lorg/jetbrains/kotlinx/ggdsl/ir/data/DataSource;Lorg/jetbrains/kotlinx/ggdsl/letsplot/facet/ScalesSharing;Lorg/jetbrains/kotlinx/ggdsl/letsplot/facet/OrderDirection;Lorg/jetbrains/kotlinx/ggdsl/letsplot/facet/OrderDirection;Ljava/lang/String;Ljava/lang/String;)V
      96: return

  public static final void facetWrap(org.jetbrains.kotlinx.ggdsl.dsl.PlotContext, org.jetbrains.kotlinx.ggdsl.ir.data.DataSource<?>[], java.lang.Integer, java.lang.Integer, org.jetbrains.kotlinx.ggdsl.letsplot.facet.OrderDirection, org.jetbrains.kotlinx.ggdsl.letsplot.facet.ScalesSharing, org.jetbrains.kotlinx.ggdsl.letsplot.facet.Direction);
    Code:
       0: aload_0
       1: ldc           #11                 // String <this>
       3: invokestatic  #17                 // Method kotlin/jvm/internal/Intrinsics.checkNotNullParameter:(Ljava/lang/Object;Ljava/lang/String;)V
       6: aload_1
       7: ldc           #92                 // String facets
       9: invokestatic  #17                 // Method kotlin/jvm/internal/Intrinsics.checkNotNullParameter:(Ljava/lang/Object;Ljava/lang/String;)V
      12: aload         4
      14: ldc           #94                 // String order
      16: invokestatic  #17                 // Method kotlin/jvm/internal/Intrinsics.checkNotNullParameter:(Ljava/lang/Object;Ljava/lang/String;)V
      19: aload         5
      21: ldc           #95                 // String scalesSharing
      23: invokestatic  #17                 // Method kotlin/jvm/internal/Intrinsics.checkNotNullParameter:(Ljava/lang/Object;Ljava/lang/String;)V
      26: aload         6
      28: ldc           #97                 // String direction
      30: invokestatic  #17                 // Method kotlin/jvm/internal/Intrinsics.checkNotNullParameter:(Ljava/lang/Object;Ljava/lang/String;)V
      33: aload_0
      34: invokevirtual #27                 // Method org/jetbrains/kotlinx/ggdsl/dsl/PlotContext.getFeatures:()Ljava/util/Map;
      37: astore        7
      39: getstatic     #102                // Field org/jetbrains/kotlinx/ggdsl/letsplot/facet/FacetWrapFeature.Companion:Lorg/jetbrains/kotlinx/ggdsl/letsplot/facet/FacetWrapFeature$Companion;
      42: invokevirtual #105                // Method org/jetbrains/kotlinx/ggdsl/letsplot/facet/FacetWrapFeature$Companion.getFEATURE_NAME:()Lorg/jetbrains/kotlinx/ggdsl/ir/feature/FeatureName;
      45: astore        8
      47: aload_1
      48: astore        9
      50: iconst_0
      51: istore        10
      53: aload         9
      55: astore        11
      57: new           #107                // class java/util/ArrayList
      60: dup
      61: aload         9
      63: arraylength
      64: invokespecial #110                // Method java/util/ArrayList."<init>":(I)V
      67: checkcast     #112                // class java/util/Collection
      70: astore        12
      72: iconst_0
      73: istore        13
      75: iconst_0
      76: istore        14
      78: aload         11
      80: arraylength
      81: istore        15
      83: iload         14
      85: iload         15
      87: if_icmpge     128
      90: aload         11
      92: iload         14
      94: aaload
      95: astore        16
      97: aload         12
      99: aload         16
     101: astore        17
     103: astore        19
     105: iconst_0
     106: istore        18
     108: aload         17
     110: invokevirtual #45                 // Method org/jetbrains/kotlinx/ggdsl/ir/data/DataSource.getId:()Ljava/lang/String;
     113: aload         19
     115: swap
     116: invokeinterface #116,  2          // InterfaceMethod java/util/Collection.add:(Ljava/lang/Object;)Z
     121: pop
     122: iinc          14, 1
     125: goto          83
     128: aload         12
     130: checkcast     #118                // class java/util/List
     133: nop
     134: aload_2
     135: aload_3
     136: aload         4
     138: aload         5
     140: aload         6
     142: aconst_null
     143: bipush        64
     145: aconst_null
     146: astore        20
     148: istore        21
     150: astore        22
     152: astore        23
     154: astore        24
     156: astore        25
     158: astore        26
     160: astore        27
     162: astore        28
     164: new           #99                 // class org/jetbrains/kotlinx/ggdsl/letsplot/facet/FacetWrapFeature
     167: dup
     168: aload         28
     170: aload         27
     172: aload         26
     174: aload         25
     176: aload         24
     178: aload         23
     180: aload         22
     182: iload         21
     184: aload         20
     186: invokespecial #121                // Method org/jetbrains/kotlinx/ggdsl/letsplot/facet/FacetWrapFeature."<init>":(Ljava/util/List;Ljava/lang/Integer;Ljava/lang/Integer;Lorg/jetbrains/kotlinx/ggdsl/letsplot/facet/OrderDirection;Lorg/jetbrains/kotlinx/ggdsl/letsplot/facet/ScalesSharing;Lorg/jetbrains/kotlinx/ggdsl/letsplot/facet/Direction;Ljava/lang/String;ILkotlin/jvm/internal/DefaultConstructorMarker;)V
     189: astore        9
     191: aload         7
     193: aload         8
     195: aload         9
     197: invokeinterface #55,  3           // InterfaceMethod java/util/Map.put:(Ljava/lang/Object;Ljava/lang/Object;)Ljava/lang/Object;
     202: pop
     203: return

  public static void facetWrap$default(org.jetbrains.kotlinx.ggdsl.dsl.PlotContext, org.jetbrains.kotlinx.ggdsl.ir.data.DataSource[], java.lang.Integer, java.lang.Integer, org.jetbrains.kotlinx.ggdsl.letsplot.facet.OrderDirection, org.jetbrains.kotlinx.ggdsl.letsplot.facet.ScalesSharing, org.jetbrains.kotlinx.ggdsl.letsplot.facet.Direction, int, java.lang.Object);
    Code:
       0: iload         7
       2: iconst_2
       3: iand
       4: ifeq          9
       7: aconst_null
       8: astore_2
       9: iload         7
      11: iconst_4
      12: iand
      13: ifeq          18
      16: aconst_null
      17: astore_3
      18: iload         7
      20: bipush        8
      22: iand
      23: ifeq          34
      26: getstatic     #79                 // Field org/jetbrains/kotlinx/ggdsl/letsplot/facet/OrderDirection.Companion:Lorg/jetbrains/kotlinx/ggdsl/letsplot/facet/OrderDirection$Companion;
      29: invokevirtual #85                 // Method org/jetbrains/kotlinx/ggdsl/letsplot/facet/OrderDirection$Companion.getASCENDING:()Lorg/jetbrains/kotlinx/ggdsl/letsplot/facet/OrderDirection;
      32: astore        4
      34: iload         7
      36: bipush        16
      38: iand
      39: ifeq          50
      42: getstatic     #149                // Field org/jetbrains/kotlinx/ggdsl/letsplot/facet/ScalesSharing.Companion:Lorg/jetbrains/kotlinx/ggdsl/letsplot/facet/ScalesSharing$Companion;
      45: invokevirtual #155                // Method org/jetbrains/kotlinx/ggdsl/letsplot/facet/ScalesSharing$Companion.getFIXED:()Lorg/jetbrains/kotlinx/ggdsl/letsplot/facet/ScalesSharing;
      48: astore        5
      50: iload         7
      52: bipush        32
      54: iand
      55: ifeq          66
      58: getstatic     #158                // Field org/jetbrains/kotlinx/ggdsl/letsplot/facet/Direction.Companion:Lorg/jetbrains/kotlinx/ggdsl/letsplot/facet/Direction$Companion;
      61: invokevirtual #164                // Method org/jetbrains/kotlinx/ggdsl/letsplot/facet/Direction$Companion.getHORIZONTAL:()Lorg/jetbrains/kotlinx/ggdsl/letsplot/facet/Direction;
      64: astore        6
      66: aload_0
      67: aload_1
      68: aload_2
      69: aload_3
      70: aload         4
      72: aload         5
      74: aload         6
      76: invokestatic  #166                // Method facetWrap:(Lorg/jetbrains/kotlinx/ggdsl/dsl/PlotContext;[Lorg/jetbrains/kotlinx/ggdsl/ir/data/DataSource;Ljava/lang/Integer;Ljava/lang/Integer;Lorg/jetbrains/kotlinx/ggdsl/letsplot/facet/OrderDirection;Lorg/jetbrains/kotlinx/ggdsl/letsplot/facet/ScalesSharing;Lorg/jetbrains/kotlinx/ggdsl/letsplot/facet/Direction;)V
      79: return
}
