Compiled from "AbstractReferenceMarshaller.java"
class com.thoughtworks.xstream.core.AbstractReferenceMarshaller$Id {
  private java.lang.Object item;

  private com.thoughtworks.xstream.io.path.Path path;

  public com.thoughtworks.xstream.core.AbstractReferenceMarshaller$Id(java.lang.Object, com.thoughtworks.xstream.io.path.Path);
    Code:
       0: aload_0
       1: invokespecial #1                  // Method java/lang/Object."<init>":()V
       4: aload_0
       5: aload_1
       6: putfield      #2                  // Field item:Ljava/lang/Object;
       9: aload_0
      10: aload_2
      11: putfield      #3                  // Field path:Lcom/thoughtworks/xstream/io/path/Path;
      14: return

  protected java.lang.Object getItem();
    Code:
       0: aload_0
       1: getfield      #2                  // Field item:Ljava/lang/Object;
       4: areturn

  protected com.thoughtworks.xstream.io.path.Path getPath();
    Code:
       0: aload_0
       1: getfield      #3                  // Field path:Lcom/thoughtworks/xstream/io/path/Path;
       4: areturn
}
