Compiled from "TooltipRenderer.java"
public class de.larmic.butterfaces.component.renderkit.html_basic.TooltipRenderer extends de.larmic.butterfaces.component.base.renderer.HtmlBasicRenderer {
  public de.larmic.butterfaces.component.renderkit.html_basic.TooltipRenderer();
    Code:
       0: aload_0
       1: invokespecial #1                  // Method de/larmic/butterfaces/component/base/renderer/HtmlBasicRenderer."<init>":()V
       4: return

  public void encodeEnd(javax.faces.context.FacesContext, javax.faces.component.UIComponent) throws java.io.IOException;
    Code:
       0: aload_2
       1: invokevirtual #2                  // Method javax/faces/component/UIComponent.isRendered:()Z
       4: ifne          8
       7: return
       8: aload_2
       9: checkcast     #3                  // class de/larmic/butterfaces/component/html/HtmlTooltip
      12: astore_3
      13: aload_1
      14: invokevirtual #4                  // Method javax/faces/context/FacesContext.getResponseWriter:()Ljavax/faces/context/ResponseWriter;
      17: astore        4
      19: invokestatic  #5                  // Method javax/faces/context/FacesContext.getCurrentInstance:()Ljavax/faces/context/FacesContext;
      22: invokestatic  #6                  // Method javax/faces/component/UINamingContainer.getSeparatorChar:(Ljavax/faces/context/FacesContext;)C
      25: istore        5
      27: aload_2
      28: invokevirtual #7                  // Method javax/faces/component/UIComponent.getClientId:()Ljava/lang/String;
      31: new           #8                  // class java/lang/StringBuilder
      34: dup
      35: invokespecial #9                  // Method java/lang/StringBuilder."<init>":()V
      38: iload         5
      40: invokevirtual #10                 // Method java/lang/StringBuilder.append:(C)Ljava/lang/StringBuilder;
      43: ldc           #11                 // String
      45: invokevirtual #12                 // Method java/lang/StringBuilder.append:(Ljava/lang/String;)Ljava/lang/StringBuilder;
      48: invokevirtual #13                 // Method java/lang/StringBuilder.toString:()Ljava/lang/String;
      51: ldc           #14                 // String _
      53: invokevirtual #15                 // Method java/lang/String.replace:(Ljava/lang/CharSequence;Ljava/lang/CharSequence;)Ljava/lang/String;
      56: astore        6
      58: aload_0
      59: aload_3
      60: invokespecial #16                 // Method getForElement:(Lde/larmic/butterfaces/component/html/HtmlTooltip;)Ljava/lang/String;
      63: astore        7
      65: aload         7
      67: invokestatic  #17                 // Method de/larmic/butterfaces/util/StringUtils.isNotEmpty:(Ljava/lang/String;)Z
      70: ifeq          660
      73: aload         4
      75: ldc           #18                 // String span
      77: aload_3
      78: invokevirtual #19                 // Method javax/faces/context/ResponseWriter.startElement:(Ljava/lang/String;Ljavax/faces/component/UIComponent;)V
      81: aload         4
      83: ldc           #20                 // String name
      85: aload         6
      87: aconst_null
      88: invokevirtual #21                 // Method javax/faces/context/ResponseWriter.writeAttribute:(Ljava/lang/String;Ljava/lang/Object;Ljava/lang/String;)V
      91: aload         4
      93: ldc           #22                 // String class
      95: ldc           #23                 // String butter-component-tooltip-temp-content
      97: aconst_null
      98: invokevirtual #21                 // Method javax/faces/context/ResponseWriter.writeAttribute:(Ljava/lang/String;Ljava/lang/Object;Ljava/lang/String;)V
     101: aload_3
     102: invokevirtual #24                 // Method de/larmic/butterfaces/component/html/HtmlTooltip.getFor:()Ljava/lang/String;
     105: invokestatic  #25                 // Method de/larmic/butterfaces/util/StringUtils.isEmpty:(Ljava/lang/String;)Z
     108: ifeq          132
     111: aload_3
     112: invokevirtual #26                 // Method de/larmic/butterfaces/component/html/HtmlTooltip.getParent:()Ljavax/faces/component/UIComponent;
     115: instanceof    #27                 // class de/larmic/butterfaces/component/html/feature/Tooltip
     118: ifeq          132
     121: aload_0
     122: aload_1
     123: aload         4
     125: aload_3
     126: invokevirtual #26                 // Method de/larmic/butterfaces/component/html/HtmlTooltip.getParent:()Ljavax/faces/component/UIComponent;
     129: invokespecial #28                 // Method renderValidationErrors:(Ljavax/faces/context/FacesContext;Ljavax/faces/context/ResponseWriter;Ljavax/faces/component/UIComponent;)V
     132: aload_3
     133: invokevirtual #29                 // Method de/larmic/butterfaces/component/html/HtmlTooltip.getChildren:()Ljava/util/List;
     136: invokeinterface #30,  1           // InterfaceMethod java/util/List.iterator:()Ljava/util/Iterator;
     141: astore        8
     143: aload         8
     145: invokeinterface #31,  1           // InterfaceMethod java/util/Iterator.hasNext:()Z
     150: ifeq          174
     153: aload         8
     155: invokeinterface #32,  1           // InterfaceMethod java/util/Iterator.next:()Ljava/lang/Object;
     160: checkcast     #33                 // class javax/faces/component/UIComponent
     163: astore        9
     165: aload         9
     167: aload_1
     168: invokevirtual #34                 // Method javax/faces/component/UIComponent.encodeAll:(Ljavax/faces/context/FacesContext;)V
     171: goto          143
     174: aload         4
     176: ldc           #18                 // String span
     178: invokevirtual #35                 // Method javax/faces/context/ResponseWriter.endElement:(Ljava/lang/String;)V
     181: aload         4
     183: ldc           #36                 // String script
     185: aload_3
     186: invokevirtual #19                 // Method javax/faces/context/ResponseWriter.startElement:(Ljava/lang/String;Ljavax/faces/component/UIComponent;)V
     189: aload         4
     191: ldc           #37                 // String jQuery(document).ready(function() {\n
     193: aconst_null
     194: invokevirtual #38                 // Method javax/faces/context/ResponseWriter.writeText:(Ljava/lang/Object;Ljava/lang/String;)V
     197: aload         4
     199: ldc           #39                 // String    jQuery(
     201: aconst_null
     202: invokevirtual #38                 // Method javax/faces/context/ResponseWriter.writeText:(Ljava/lang/Object;Ljava/lang/String;)V
     205: aload         4
     207: aload         7
     209: aconst_null
     210: invokevirtual #38                 // Method javax/faces/context/ResponseWriter.writeText:(Ljava/lang/Object;Ljava/lang/String;)V
     213: aload         4
     215: ldc           #40                 // String )._butterTooltip({\n
     217: aconst_null
     218: invokevirtual #38                 // Method javax/faces/context/ResponseWriter.writeText:(Ljava/lang/Object;Ljava/lang/String;)V
     221: aload         4
     223: ldc           #41                 // String       trigger:
     225: aconst_null
     226: invokevirtual #38                 // Method javax/faces/context/ResponseWriter.writeText:(Ljava/lang/Object;Ljava/lang/String;)V
     229: aload         4
     231: aload_0
     232: aload_3
     233: invokevirtual #42                 // Method de/larmic/butterfaces/component/html/HtmlTooltip.getTrigger:()Ljava/lang/String;
     236: invokespecial #43                 // Method getNullSafeStringParameter:(Ljava/lang/String;)Ljava/lang/String;
     239: aconst_null
     240: invokevirtual #38                 // Method javax/faces/context/ResponseWriter.writeText:(Ljava/lang/Object;Ljava/lang/String;)V
     243: aload         4
     245: ldc           #44                 // String ,\n      title:
     247: aconst_null
     248: invokevirtual #38                 // Method javax/faces/context/ResponseWriter.writeText:(Ljava/lang/Object;Ljava/lang/String;)V
     251: aload         4
     253: aload_0
     254: aload_3
     255: invokevirtual #45                 // Method de/larmic/butterfaces/component/html/HtmlTooltip.getTitle:()Ljava/lang/String;
     258: invokespecial #43                 // Method getNullSafeStringParameter:(Ljava/lang/String;)Ljava/lang/String;
     261: aconst_null
     262: invokevirtual #38                 // Method javax/faces/context/ResponseWriter.writeText:(Ljava/lang/Object;Ljava/lang/String;)V
     265: aload         4
     267: ldc           #46                 // String ,\n      placement:
     269: aconst_null
     270: invokevirtual #38                 // Method javax/faces/context/ResponseWriter.writeText:(Ljava/lang/Object;Ljava/lang/String;)V
     273: aload         4
     275: aload_0
     276: aload_3
     277: invokevirtual #47                 // Method de/larmic/butterfaces/component/html/HtmlTooltip.getPlacement:()Ljava/lang/String;
     280: invokespecial #43                 // Method getNullSafeStringParameter:(Ljava/lang/String;)Ljava/lang/String;
     283: aconst_null
     284: invokevirtual #38                 // Method javax/faces/context/ResponseWriter.writeText:(Ljava/lang/Object;Ljava/lang/String;)V
     287: aload         4
     289: ldc           #48                 // String ,\n      placementFunction:
     291: aconst_null
     292: invokevirtual #38                 // Method javax/faces/context/ResponseWriter.writeText:(Ljava/lang/Object;Ljava/lang/String;)V
     295: aload         4
     297: aload_0
     298: aload_3
     299: invokevirtual #49                 // Method de/larmic/butterfaces/component/html/HtmlTooltip.getPlacementFunction:()Ljava/lang/String;
     302: invokespecial #50                 // Method getNullSafeFunctionParameter:(Ljava/lang/String;)Ljava/lang/String;
     305: aconst_null
     306: invokevirtual #38                 // Method javax/faces/context/ResponseWriter.writeText:(Ljava/lang/Object;Ljava/lang/String;)V
     309: aload         4
     311: ldc           #51                 // String ,\n      contentByName: \'
     313: aconst_null
     314: invokevirtual #38                 // Method javax/faces/context/ResponseWriter.writeText:(Ljava/lang/Object;Ljava/lang/String;)V
     317: aload         4
     319: aload         6
     321: aconst_null
     322: invokevirtual #38                 // Method javax/faces/context/ResponseWriter.writeText:(Ljava/lang/Object;Ljava/lang/String;)V
     325: aload         4
     327: ldc           #52                 // String \',\n      minVerticalOffset:
     329: aconst_null
     330: invokevirtual #38                 // Method javax/faces/context/ResponseWriter.writeText:(Ljava/lang/Object;Ljava/lang/String;)V
     333: aload         4
     335: aload_0
     336: aload_3
     337: invokevirtual #53                 // Method de/larmic/butterfaces/component/html/HtmlTooltip.getMinVerticalOffset:()Ljava/lang/Integer;
     340: invokespecial #54                 // Method getNullSafeIntegerParameter:(Ljava/lang/Integer;)Ljava/lang/String;
     343: aconst_null
     344: invokevirtual #38                 // Method javax/faces/context/ResponseWriter.writeText:(Ljava/lang/Object;Ljava/lang/String;)V
     347: aload         4
     349: ldc           #55                 // String ,\n      minHorizontalOffset:
     351: aconst_null
     352: invokevirtual #38                 // Method javax/faces/context/ResponseWriter.writeText:(Ljava/lang/Object;Ljava/lang/String;)V
     355: aload         4
     357: aload_0
     358: aload_3
     359: invokevirtual #56                 // Method de/larmic/butterfaces/component/html/HtmlTooltip.getMinHorizontalOffset:()Ljava/lang/Integer;
     362: invokespecial #54                 // Method getNullSafeIntegerParameter:(Ljava/lang/Integer;)Ljava/lang/String;
     365: aconst_null
     366: invokevirtual #38                 // Method javax/faces/context/ResponseWriter.writeText:(Ljava/lang/Object;Ljava/lang/String;)V
     369: aload         4
     371: ldc           #57                 // String ,\n      viewport:
     373: aconst_null
     374: invokevirtual #38                 // Method javax/faces/context/ResponseWriter.writeText:(Ljava/lang/Object;Ljava/lang/String;)V
     377: aload         4
     379: new           #8                  // class java/lang/StringBuilder
     382: dup
     383: invokespecial #9                  // Method java/lang/StringBuilder."<init>":()V
     386: ldc           #58                 // String \'
     388: invokevirtual #12                 // Method java/lang/StringBuilder.append:(Ljava/lang/String;)Ljava/lang/StringBuilder;
     391: aload_3
     392: invokevirtual #59                 // Method de/larmic/butterfaces/component/html/HtmlTooltip.getViewport:()Ljava/lang/String;
     395: ldc           #60                 // String body
     397: invokestatic  #61                 // Method de/larmic/butterfaces/util/StringUtils.getNotNullValue:(Ljava/lang/String;Ljava/lang/String;)Ljava/lang/String;
     400: invokevirtual #12                 // Method java/lang/StringBuilder.append:(Ljava/lang/String;)Ljava/lang/StringBuilder;
     403: ldc           #58                 // String \'
     405: invokevirtual #12                 // Method java/lang/StringBuilder.append:(Ljava/lang/String;)Ljava/lang/StringBuilder;
     408: invokevirtual #13                 // Method java/lang/StringBuilder.toString:()Ljava/lang/String;
     411: aconst_null
     412: invokevirtual #38                 // Method javax/faces/context/ResponseWriter.writeText:(Ljava/lang/Object;Ljava/lang/String;)V
     415: aload         4
     417: ldc           #62                 // String \n   })\n});
     419: aconst_null
     420: invokevirtual #38                 // Method javax/faces/context/ResponseWriter.writeText:(Ljava/lang/Object;Ljava/lang/String;)V
     423: aload_3
     424: invokevirtual #63                 // Method de/larmic/butterfaces/component/html/HtmlTooltip.getOnShow:()Ljava/lang/String;
     427: invokestatic  #17                 // Method de/larmic/butterfaces/util/StringUtils.isNotEmpty:(Ljava/lang/String;)Z
     430: ifne          463
     433: aload_3
     434: invokevirtual #64                 // Method de/larmic/butterfaces/component/html/HtmlTooltip.getOnShown:()Ljava/lang/String;
     437: invokestatic  #17                 // Method de/larmic/butterfaces/util/StringUtils.isNotEmpty:(Ljava/lang/String;)Z
     440: ifne          463
     443: aload_3
     444: invokevirtual #65                 // Method de/larmic/butterfaces/component/html/HtmlTooltip.getOnHide:()Ljava/lang/String;
     447: invokestatic  #17                 // Method de/larmic/butterfaces/util/StringUtils.isNotEmpty:(Ljava/lang/String;)Z
     450: ifne          463
     453: aload_3
     454: invokevirtual #66                 // Method de/larmic/butterfaces/component/html/HtmlTooltip.getOnHidden:()Ljava/lang/String;
     457: invokestatic  #17                 // Method de/larmic/butterfaces/util/StringUtils.isNotEmpty:(Ljava/lang/String;)Z
     460: ifeq          523
     463: aload_0
     464: aload         7
     466: aload_3
     467: invokevirtual #63                 // Method de/larmic/butterfaces/component/html/HtmlTooltip.getOnShow:()Ljava/lang/String;
     470: ldc           #67                 // String show.bs.popover
     472: aload_2
     473: aload         4
     475: invokespecial #68                 // Method encodePopoverEvent:(Ljava/lang/String;Ljava/lang/String;Ljava/lang/String;Ljavax/faces/component/UIComponent;Ljavax/faces/context/ResponseWriter;)V
     478: aload_0
     479: aload         7
     481: aload_3
     482: invokevirtual #64                 // Method de/larmic/butterfaces/component/html/HtmlTooltip.getOnShown:()Ljava/lang/String;
     485: ldc           #69                 // String shown.bs.popover
     487: aload_2
     488: aload         4
     490: invokespecial #68                 // Method encodePopoverEvent:(Ljava/lang/String;Ljava/lang/String;Ljava/lang/String;Ljavax/faces/component/UIComponent;Ljavax/faces/context/ResponseWriter;)V
     493: aload_0
     494: aload         7
     496: aload_3
     497: invokevirtual #65                 // Method de/larmic/butterfaces/component/html/HtmlTooltip.getOnHide:()Ljava/lang/String;
     500: ldc           #70                 // String hide.bs.popover
     502: aload_2
     503: aload         4
     505: invokespecial #68                 // Method encodePopoverEvent:(Ljava/lang/String;Ljava/lang/String;Ljava/lang/String;Ljavax/faces/component/UIComponent;Ljavax/faces/context/ResponseWriter;)V
     508: aload_0
     509: aload         7
     511: aload_3
     512: invokevirtual #66                 // Method de/larmic/butterfaces/component/html/HtmlTooltip.getOnHidden:()Ljava/lang/String;
     515: ldc           #71                 // String hidden.bs.popover
     517: aload_2
     518: aload         4
     520: invokespecial #68                 // Method encodePopoverEvent:(Ljava/lang/String;Ljava/lang/String;Ljava/lang/String;Ljavax/faces/component/UIComponent;Ljavax/faces/context/ResponseWriter;)V
     523: aload_3
     524: invokevirtual #24                 // Method de/larmic/butterfaces/component/html/HtmlTooltip.getFor:()Ljava/lang/String;
     527: invokestatic  #25                 // Method de/larmic/butterfaces/util/StringUtils.isEmpty:(Ljava/lang/String;)Z
     530: ifeq          653
     533: aload_0
     534: aload_3
     535: invokespecial #72                 // Method isTooltipParentReadonly:(Lde/larmic/butterfaces/component/html/HtmlTooltip;)Z
     538: ifeq          653
     541: aload         4
     543: ldc           #73                 // String jQuery(document).ready(function() {
     545: aconst_null
     546: invokevirtual #38                 // Method javax/faces/context/ResponseWriter.writeText:(Ljava/lang/Object;Ljava/lang/String;)V
     549: aload         4
     551: new           #8                  // class java/lang/StringBuilder
     554: dup
     555: invokespecial #9                  // Method java/lang/StringBuilder."<init>":()V
     558: ldc           #74                 // String \n    jQuery(
     560: invokevirtual #12                 // Method java/lang/StringBuilder.append:(Ljava/lang/String;)Ljava/lang/StringBuilder;
     563: aload_0
     564: aload_3
     565: invokespecial #75                 // Method createParentForElement:(Lde/larmic/butterfaces/component/html/HtmlTooltip;)Ljava/lang/String;
     568: invokevirtual #12                 // Method java/lang/StringBuilder.append:(Ljava/lang/String;)Ljava/lang/StringBuilder;
     571: ldc           #76                 // String ).find(\'.butter-component-label\').on(\'
     573: invokevirtual #12                 // Method java/lang/StringBuilder.append:(Ljava/lang/String;)Ljava/lang/StringBuilder;
     576: aload_0
     577: aload_3
     578: invokevirtual #42                 // Method de/larmic/butterfaces/component/html/HtmlTooltip.getTrigger:()Ljava/lang/String;
     581: invokespecial #77                 // Method convertTooltipTriggerToJavaScriptEvent:(Ljava/lang/String;)Ljava/lang/String;
     584: invokevirtual #12                 // Method java/lang/StringBuilder.append:(Ljava/lang/String;)Ljava/lang/StringBuilder;
     587: ldc           #78                 // String \', function(e) {
     589: invokevirtual #12                 // Method java/lang/StringBuilder.append:(Ljava/lang/String;)Ljava/lang/StringBuilder;
     592: invokevirtual #13                 // Method java/lang/StringBuilder.toString:()Ljava/lang/String;
     595: aload_2
     596: aconst_null
     597: invokevirtual #79                 // Method javax/faces/context/ResponseWriter.writeText:(Ljava/lang/Object;Ljavax/faces/component/UIComponent;Ljava/lang/String;)V
     600: aload         4
     602: new           #8                  // class java/lang/StringBuilder
     605: dup
     606: invokespecial #9                  // Method java/lang/StringBuilder."<init>":()V
     609: ldc           #80                 // String \n        jQuery(
     611: invokevirtual #12                 // Method java/lang/StringBuilder.append:(Ljava/lang/String;)Ljava/lang/StringBuilder;
     614: aload_0
     615: aload_3
     616: invokespecial #81                 // Method createParentReadonlyForElement:(Lde/larmic/butterfaces/component/html/HtmlTooltip;)Ljava/lang/String;
     619: invokevirtual #12                 // Method java/lang/StringBuilder.append:(Ljava/lang/String;)Ljava/lang/StringBuilder;
     622: ldc           #82                 // String ).trigger(e.type);
     624: invokevirtual #12                 // Method java/lang/StringBuilder.append:(Ljava/lang/String;)Ljava/lang/StringBuilder;
     627: invokevirtual #13                 // Method java/lang/StringBuilder.toString:()Ljava/lang/String;
     630: aload_2
     631: aconst_null
     632: invokevirtual #79                 // Method javax/faces/context/ResponseWriter.writeText:(Ljava/lang/Object;Ljavax/faces/component/UIComponent;Ljava/lang/String;)V
     635: aload         4
     637: ldc           #83                 // String \n    });
     639: aload_2
     640: aconst_null
     641: invokevirtual #79                 // Method javax/faces/context/ResponseWriter.writeText:(Ljava/lang/Object;Ljavax/faces/component/UIComponent;Ljava/lang/String;)V
     644: aload         4
     646: ldc           #84                 // String \n});\n
     648: aload_2
     649: aconst_null
     650: invokevirtual #79                 // Method javax/faces/context/ResponseWriter.writeText:(Ljava/lang/Object;Ljavax/faces/component/UIComponent;Ljava/lang/String;)V
     653: aload         4
     655: ldc           #36                 // String script
     657: invokevirtual #35                 // Method javax/faces/context/ResponseWriter.endElement:(Ljava/lang/String;)V
     660: return

  private java.lang.String convertTooltipTriggerToJavaScriptEvent(java.lang.String);
    Code:
       0: ldc           #85                 // String click
       2: aload_1
       3: invokevirtual #86                 // Method java/lang/String.equalsIgnoreCase:(Ljava/lang/String;)Z
       6: ifeq          12
       9: ldc           #85                 // String click
      11: areturn
      12: ldc           #87                 // String focus
      14: aload_1
      15: invokevirtual #86                 // Method java/lang/String.equalsIgnoreCase:(Ljava/lang/String;)Z
      18: ifeq          24
      21: ldc           #87                 // String focus
      23: areturn
      24: ldc           #88                 // String manual
      26: aload_1
      27: invokevirtual #86                 // Method java/lang/String.equalsIgnoreCase:(Ljava/lang/String;)Z
      30: ifeq          36
      33: ldc           #11                 // String
      35: areturn
      36: ldc           #89                 // String mouseenter mouseleave
      38: areturn

  private void encodePopoverEvent(java.lang.String, java.lang.String, java.lang.String, javax.faces.component.UIComponent, javax.faces.context.ResponseWriter) throws java.io.IOException;
    Code:
       0: aload_2
       1: invokestatic  #17                 // Method de/larmic/butterfaces/util/StringUtils.isNotEmpty:(Ljava/lang/String;)Z
       4: ifeq          108
       7: aload         5
       9: ldc           #37                 // String jQuery(document).ready(function() {\n
      11: aconst_null
      12: invokevirtual #38                 // Method javax/faces/context/ResponseWriter.writeText:(Ljava/lang/Object;Ljava/lang/String;)V
      15: aload         5
      17: new           #8                  // class java/lang/StringBuilder
      20: dup
      21: invokespecial #9                  // Method java/lang/StringBuilder."<init>":()V
      24: ldc           #90                 // String     jQuery(
      26: invokevirtual #12                 // Method java/lang/StringBuilder.append:(Ljava/lang/String;)Ljava/lang/StringBuilder;
      29: aload_1
      30: invokevirtual #12                 // Method java/lang/StringBuilder.append:(Ljava/lang/String;)Ljava/lang/StringBuilder;
      33: ldc           #91                 // String ).on(\'
      35: invokevirtual #12                 // Method java/lang/StringBuilder.append:(Ljava/lang/String;)Ljava/lang/StringBuilder;
      38: aload_3
      39: invokevirtual #12                 // Method java/lang/StringBuilder.append:(Ljava/lang/String;)Ljava/lang/StringBuilder;
      42: ldc           #92                 // String \', function() {\n
      44: invokevirtual #12                 // Method java/lang/StringBuilder.append:(Ljava/lang/String;)Ljava/lang/StringBuilder;
      47: invokevirtual #13                 // Method java/lang/StringBuilder.toString:()Ljava/lang/String;
      50: aload         4
      52: aconst_null
      53: invokevirtual #79                 // Method javax/faces/context/ResponseWriter.writeText:(Ljava/lang/Object;Ljavax/faces/component/UIComponent;Ljava/lang/String;)V
      56: aload         5
      58: new           #8                  // class java/lang/StringBuilder
      61: dup
      62: invokespecial #9                  // Method java/lang/StringBuilder."<init>":()V
      65: ldc           #93                 // String
      67: invokevirtual #12                 // Method java/lang/StringBuilder.append:(Ljava/lang/String;)Ljava/lang/StringBuilder;
      70: aload_2
      71: invokevirtual #12                 // Method java/lang/StringBuilder.append:(Ljava/lang/String;)Ljava/lang/StringBuilder;
      74: ldc           #94                 // String ;\n
      76: invokevirtual #12                 // Method java/lang/StringBuilder.append:(Ljava/lang/String;)Ljava/lang/StringBuilder;
      79: invokevirtual #13                 // Method java/lang/StringBuilder.toString:()Ljava/lang/String;
      82: aload         4
      84: aconst_null
      85: invokevirtual #79                 // Method javax/faces/context/ResponseWriter.writeText:(Ljava/lang/Object;Ljavax/faces/component/UIComponent;Ljava/lang/String;)V
      88: aload         5
      90: ldc           #95                 // String     });\n
      92: aload         4
      94: aconst_null
      95: invokevirtual #79                 // Method javax/faces/context/ResponseWriter.writeText:(Ljava/lang/Object;Ljavax/faces/component/UIComponent;Ljava/lang/String;)V
      98: aload         5
     100: ldc           #96                 // String });\n
     102: aload         4
     104: aconst_null
     105: invokevirtual #79                 // Method javax/faces/context/ResponseWriter.writeText:(Ljava/lang/Object;Ljavax/faces/component/UIComponent;Ljava/lang/String;)V
     108: return

  private void renderValidationErrors(javax.faces.context.FacesContext, javax.faces.context.ResponseWriter, javax.faces.component.UIComponent) throws java.io.IOException;
    Code:
       0: aload_1
       1: invokevirtual #97                 // Method javax/faces/context/FacesContext.getClientIdsWithMessages:()Ljava/util/Iterator;
       4: astore        4
       6: aload         4
       8: invokeinterface #31,  1           // InterfaceMethod java/util/Iterator.hasNext:()Z
      13: ifeq          130
      16: aload         4
      18: invokeinterface #32,  1           // InterfaceMethod java/util/Iterator.next:()Ljava/lang/Object;
      23: checkcast     #98                 // class java/lang/String
      26: astore        5
      28: aload_3
      29: invokevirtual #7                  // Method javax/faces/component/UIComponent.getClientId:()Ljava/lang/String;
      32: aload         5
      34: invokevirtual #99                 // Method java/lang/String.equals:(Ljava/lang/Object;)Z
      37: ifeq          127
      40: aload_1
      41: aload         5
      43: invokevirtual #100                // Method javax/faces/context/FacesContext.getMessages:(Ljava/lang/String;)Ljava/util/Iterator;
      46: astore        6
      48: aload_2
      49: ldc           #102                // String div
      51: aload_3
      52: invokevirtual #19                 // Method javax/faces/context/ResponseWriter.startElement:(Ljava/lang/String;Ljavax/faces/component/UIComponent;)V
      55: aload_2
      56: ldc           #22                 // String class
      58: ldc           #103                // String butter-component-tooltip-validation-error
      60: aconst_null
      61: invokevirtual #21                 // Method javax/faces/context/ResponseWriter.writeAttribute:(Ljava/lang/String;Ljava/lang/Object;Ljava/lang/String;)V
      64: aload_2
      65: ldc           #104                // String ul
      67: aload_3
      68: invokevirtual #19                 // Method javax/faces/context/ResponseWriter.startElement:(Ljava/lang/String;Ljavax/faces/component/UIComponent;)V
      71: aload         6
      73: invokeinterface #31,  1           // InterfaceMethod java/util/Iterator.hasNext:()Z
      78: ifeq          115
      81: aload_2
      82: ldc           #105                // String li
      84: aload_3
      85: invokevirtual #19                 // Method javax/faces/context/ResponseWriter.startElement:(Ljava/lang/String;Ljavax/faces/component/UIComponent;)V
      88: aload_2
      89: aload         6
      91: invokeinterface #32,  1           // InterfaceMethod java/util/Iterator.next:()Ljava/lang/Object;
      96: checkcast     #106                // class javax/faces/application/FacesMessage
      99: invokevirtual #107                // Method javax/faces/application/FacesMessage.getDetail:()Ljava/lang/String;
     102: aconst_null
     103: invokevirtual #38                 // Method javax/faces/context/ResponseWriter.writeText:(Ljava/lang/Object;Ljava/lang/String;)V
     106: aload_2
     107: ldc           #105                // String li
     109: invokevirtual #35                 // Method javax/faces/context/ResponseWriter.endElement:(Ljava/lang/String;)V
     112: goto          71
     115: aload_2
     116: ldc           #104                // String ul
     118: invokevirtual #35                 // Method javax/faces/context/ResponseWriter.endElement:(Ljava/lang/String;)V
     121: aload_2
     122: ldc           #102                // String div
     124: invokevirtual #35                 // Method javax/faces/context/ResponseWriter.endElement:(Ljava/lang/String;)V
     127: goto          6
     130: return

  private java.lang.String getForElement(de.larmic.butterfaces.component.html.HtmlTooltip);
    Code:
       0: aload_1
       1: invokevirtual #24                 // Method de/larmic/butterfaces/component/html/HtmlTooltip.getFor:()Ljava/lang/String;
       4: invokestatic  #17                 // Method de/larmic/butterfaces/util/StringUtils.isNotEmpty:(Ljava/lang/String;)Z
       7: ifeq          38
      10: new           #8                  // class java/lang/StringBuilder
      13: dup
      14: invokespecial #9                  // Method java/lang/StringBuilder."<init>":()V
      17: ldc           #58                 // String \'
      19: invokevirtual #12                 // Method java/lang/StringBuilder.append:(Ljava/lang/String;)Ljava/lang/StringBuilder;
      22: aload_1
      23: invokevirtual #24                 // Method de/larmic/butterfaces/component/html/HtmlTooltip.getFor:()Ljava/lang/String;
      26: invokevirtual #12                 // Method java/lang/StringBuilder.append:(Ljava/lang/String;)Ljava/lang/StringBuilder;
      29: ldc           #58                 // String \'
      31: invokevirtual #12                 // Method java/lang/StringBuilder.append:(Ljava/lang/String;)Ljava/lang/StringBuilder;
      34: invokevirtual #13                 // Method java/lang/StringBuilder.toString:()Ljava/lang/String;
      37: areturn
      38: aload_1
      39: invokevirtual #26                 // Method de/larmic/butterfaces/component/html/HtmlTooltip.getParent:()Ljavax/faces/component/UIComponent;
      42: instanceof    #27                 // class de/larmic/butterfaces/component/html/feature/Tooltip
      45: ifeq          98
      48: aload_1
      49: invokevirtual #26                 // Method de/larmic/butterfaces/component/html/HtmlTooltip.getParent:()Ljavax/faces/component/UIComponent;
      52: astore_2
      53: aload_2
      54: instanceof    #108                // class de/larmic/butterfaces/component/html/feature/Readonly
      57: ifeq          92
      60: aload_2
      61: instanceof    #109                // class de/larmic/butterfaces/component/html/text/HtmlTags
      64: ifne          92
      67: aload_2
      68: instanceof    #110                // class de/larmic/butterfaces/component/html/text/HtmlTreeBox
      71: ifne          92
      74: aload_2
      75: checkcast     #108                // class de/larmic/butterfaces/component/html/feature/Readonly
      78: invokeinterface #111,  1          // InterfaceMethod de/larmic/butterfaces/component/html/feature/Readonly.isReadonly:()Z
      83: ifeq          92
      86: aload_0
      87: aload_1
      88: invokespecial #81                 // Method createParentReadonlyForElement:(Lde/larmic/butterfaces/component/html/HtmlTooltip;)Ljava/lang/String;
      91: areturn
      92: aload_0
      93: aload_1
      94: invokespecial #75                 // Method createParentForElement:(Lde/larmic/butterfaces/component/html/HtmlTooltip;)Ljava/lang/String;
      97: areturn
      98: aconst_null
      99: areturn

  private java.lang.String createParentReadonlyForElement(de.larmic.butterfaces.component.html.HtmlTooltip);
    Code:
       0: new           #8                  // class java/lang/StringBuilder
       3: dup
       4: invokespecial #9                  // Method java/lang/StringBuilder."<init>":()V
       7: aload_0
       8: aload_1
       9: invokespecial #75                 // Method createParentForElement:(Lde/larmic/butterfaces/component/html/HtmlTooltip;)Ljava/lang/String;
      12: invokevirtual #12                 // Method java/lang/StringBuilder.append:(Ljava/lang/String;)Ljava/lang/StringBuilder;
      15: ldc           #112                // String ).find(\'.butter-component-value-readonly-wrapper\'
      17: invokevirtual #12                 // Method java/lang/StringBuilder.append:(Ljava/lang/String;)Ljava/lang/StringBuilder;
      20: invokevirtual #13                 // Method java/lang/StringBuilder.toString:()Ljava/lang/String;
      23: areturn

  private java.lang.String createParentForElement(de.larmic.butterfaces.component.html.HtmlTooltip);
    Code:
       0: new           #8                  // class java/lang/StringBuilder
       3: dup
       4: invokespecial #9                  // Method java/lang/StringBuilder."<init>":()V
       7: ldc           #113                // String document.getElementById(\'
       9: invokevirtual #12                 // Method java/lang/StringBuilder.append:(Ljava/lang/String;)Ljava/lang/StringBuilder;
      12: aload_1
      13: invokevirtual #26                 // Method de/larmic/butterfaces/component/html/HtmlTooltip.getParent:()Ljavax/faces/component/UIComponent;
      16: invokevirtual #7                  // Method javax/faces/component/UIComponent.getClientId:()Ljava/lang/String;
      19: invokevirtual #12                 // Method java/lang/StringBuilder.append:(Ljava/lang/String;)Ljava/lang/StringBuilder;
      22: ldc           #114                // String \')
      24: invokevirtual #12                 // Method java/lang/StringBuilder.append:(Ljava/lang/String;)Ljava/lang/StringBuilder;
      27: invokevirtual #13                 // Method java/lang/StringBuilder.toString:()Ljava/lang/String;
      30: areturn

  private boolean isTooltipParentReadonly(de.larmic.butterfaces.component.html.HtmlTooltip);
    Code:
       0: aload_1
       1: invokevirtual #26                 // Method de/larmic/butterfaces/component/html/HtmlTooltip.getParent:()Ljavax/faces/component/UIComponent;
       4: instanceof    #27                 // class de/larmic/butterfaces/component/html/feature/Tooltip
       7: ifeq          49
      10: aload_1
      11: invokevirtual #26                 // Method de/larmic/butterfaces/component/html/HtmlTooltip.getParent:()Ljavax/faces/component/UIComponent;
      14: instanceof    #109                // class de/larmic/butterfaces/component/html/text/HtmlTags
      17: ifne          49
      20: aload_1
      21: invokevirtual #26                 // Method de/larmic/butterfaces/component/html/HtmlTooltip.getParent:()Ljavax/faces/component/UIComponent;
      24: instanceof    #108                // class de/larmic/butterfaces/component/html/feature/Readonly
      27: ifeq          49
      30: aload_1
      31: invokevirtual #26                 // Method de/larmic/butterfaces/component/html/HtmlTooltip.getParent:()Ljavax/faces/component/UIComponent;
      34: checkcast     #108                // class de/larmic/butterfaces/component/html/feature/Readonly
      37: invokeinterface #111,  1          // InterfaceMethod de/larmic/butterfaces/component/html/feature/Readonly.isReadonly:()Z
      42: ifeq          49
      45: iconst_1
      46: goto          50
      49: iconst_0
      50: ireturn

  private java.lang.String getNullSafeStringParameter(java.lang.String);
    Code:
       0: new           #8                  // class java/lang/StringBuilder
       3: dup
       4: invokespecial #9                  // Method java/lang/StringBuilder."<init>":()V
       7: ldc           #58                 // String \'
       9: invokevirtual #12                 // Method java/lang/StringBuilder.append:(Ljava/lang/String;)Ljava/lang/StringBuilder;
      12: aload_1
      13: invokestatic  #115                // Method de/larmic/butterfaces/util/StringUtils.getNullSafeValue:(Ljava/lang/String;)Ljava/lang/String;
      16: invokevirtual #12                 // Method java/lang/StringBuilder.append:(Ljava/lang/String;)Ljava/lang/StringBuilder;
      19: ldc           #58                 // String \'
      21: invokevirtual #12                 // Method java/lang/StringBuilder.append:(Ljava/lang/String;)Ljava/lang/StringBuilder;
      24: invokevirtual #13                 // Method java/lang/StringBuilder.toString:()Ljava/lang/String;
      27: areturn

  private java.lang.String getNullSafeFunctionParameter(java.lang.String);
    Code:
       0: aload_1
       1: invokestatic  #115                // Method de/larmic/butterfaces/util/StringUtils.getNullSafeValue:(Ljava/lang/String;)Ljava/lang/String;
       4: astore_2
       5: aload_2
       6: invokestatic  #17                 // Method de/larmic/butterfaces/util/StringUtils.isNotEmpty:(Ljava/lang/String;)Z
       9: ifeq          16
      12: aload_2
      13: goto          18
      16: ldc           #116                // String \'\'
      18: areturn

  private java.lang.String getNullSafeIntegerParameter(java.lang.Integer);
    Code:
       0: aload_1
       1: ifnonnull     9
       4: ldc           #116                // String \'\'
       6: goto          13
       9: aload_1
      10: invokestatic  #117                // Method java/lang/String.valueOf:(Ljava/lang/Object;)Ljava/lang/String;
      13: areturn
}
