Compiled from "AutoScalingSettingsUpdate.java"
final class software.amazon.awssdk.services.dynamodb.model.AutoScalingSettingsUpdate$BuilderImpl implements software.amazon.awssdk.services.dynamodb.model.AutoScalingSettingsUpdate$Builder {
  private java.lang.Long minimumUnits;

  private java.lang.Long maximumUnits;

  private java.lang.Boolean autoScalingDisabled;

  private java.lang.String autoScalingRoleArn;

  private software.amazon.awssdk.services.dynamodb.model.AutoScalingPolicyUpdate scalingPolicyUpdate;

  private software.amazon.awssdk.services.dynamodb.model.AutoScalingSettingsUpdate$BuilderImpl();
    Code:
       0: aload_0
       1: invokespecial #8                  // Method java/lang/Object."<init>":()V
       4: return

  private software.amazon.awssdk.services.dynamodb.model.AutoScalingSettingsUpdate$BuilderImpl(software.amazon.awssdk.services.dynamodb.model.AutoScalingSettingsUpdate);
    Code:
       0: aload_0
       1: invokespecial #8                  // Method java/lang/Object."<init>":()V
       4: aload_0
       5: aload_1
       6: invokestatic  #9                  // Method software/amazon/awssdk/services/dynamodb/model/AutoScalingSettingsUpdate.access$700:(Lsoftware/amazon/awssdk/services/dynamodb/model/AutoScalingSettingsUpdate;)Ljava/lang/Long;
       9: invokevirtual #10                 // Method minimumUnits:(Ljava/lang/Long;)Lsoftware/amazon/awssdk/services/dynamodb/model/AutoScalingSettingsUpdate$Builder;
      12: pop
      13: aload_0
      14: aload_1
      15: invokestatic  #11                 // Method software/amazon/awssdk/services/dynamodb/model/AutoScalingSettingsUpdate.access$800:(Lsoftware/amazon/awssdk/services/dynamodb/model/AutoScalingSettingsUpdate;)Ljava/lang/Long;
      18: invokevirtual #12                 // Method maximumUnits:(Ljava/lang/Long;)Lsoftware/amazon/awssdk/services/dynamodb/model/AutoScalingSettingsUpdate$Builder;
      21: pop
      22: aload_0
      23: aload_1
      24: invokestatic  #13                 // Method software/amazon/awssdk/services/dynamodb/model/AutoScalingSettingsUpdate.access$900:(Lsoftware/amazon/awssdk/services/dynamodb/model/AutoScalingSettingsUpdate;)Ljava/lang/Boolean;
      27: invokevirtual #14                 // Method autoScalingDisabled:(Ljava/lang/Boolean;)Lsoftware/amazon/awssdk/services/dynamodb/model/AutoScalingSettingsUpdate$Builder;
      30: pop
      31: aload_0
      32: aload_1
      33: invokestatic  #15                 // Method software/amazon/awssdk/services/dynamodb/model/AutoScalingSettingsUpdate.access$1000:(Lsoftware/amazon/awssdk/services/dynamodb/model/AutoScalingSettingsUpdate;)Ljava/lang/String;
      36: invokevirtual #16                 // Method autoScalingRoleArn:(Ljava/lang/String;)Lsoftware/amazon/awssdk/services/dynamodb/model/AutoScalingSettingsUpdate$Builder;
      39: pop
      40: aload_0
      41: aload_1
      42: invokestatic  #17                 // Method software/amazon/awssdk/services/dynamodb/model/AutoScalingSettingsUpdate.access$1100:(Lsoftware/amazon/awssdk/services/dynamodb/model/AutoScalingSettingsUpdate;)Lsoftware/amazon/awssdk/services/dynamodb/model/AutoScalingPolicyUpdate;
      45: invokevirtual #18                 // Method scalingPolicyUpdate:(Lsoftware/amazon/awssdk/services/dynamodb/model/AutoScalingPolicyUpdate;)Lsoftware/amazon/awssdk/services/dynamodb/model/AutoScalingSettingsUpdate$Builder;
      48: pop
      49: return

  public final java.lang.Long getMinimumUnits();
    Code:
       0: aload_0
       1: getfield      #7                  // Field minimumUnits:Ljava/lang/Long;
       4: areturn

  public final void setMinimumUnits(java.lang.Long);
    Code:
       0: aload_0
       1: aload_1
       2: putfield      #7                  // Field minimumUnits:Ljava/lang/Long;
       5: return

  public final software.amazon.awssdk.services.dynamodb.model.AutoScalingSettingsUpdate$Builder minimumUnits(java.lang.Long);
    Code:
       0: aload_0
       1: aload_1
       2: putfield      #7                  // Field minimumUnits:Ljava/lang/Long;
       5: aload_0
       6: areturn

  public final java.lang.Long getMaximumUnits();
    Code:
       0: aload_0
       1: getfield      #6                  // Field maximumUnits:Ljava/lang/Long;
       4: areturn

  public final void setMaximumUnits(java.lang.Long);
    Code:
       0: aload_0
       1: aload_1
       2: putfield      #6                  // Field maximumUnits:Ljava/lang/Long;
       5: return

  public final software.amazon.awssdk.services.dynamodb.model.AutoScalingSettingsUpdate$Builder maximumUnits(java.lang.Long);
    Code:
       0: aload_0
       1: aload_1
       2: putfield      #6                  // Field maximumUnits:Ljava/lang/Long;
       5: aload_0
       6: areturn

  public final java.lang.Boolean getAutoScalingDisabled();
    Code:
       0: aload_0
       1: getfield      #5                  // Field autoScalingDisabled:Ljava/lang/Boolean;
       4: areturn

  public final void setAutoScalingDisabled(java.lang.Boolean);
    Code:
       0: aload_0
       1: aload_1
       2: putfield      #5                  // Field autoScalingDisabled:Ljava/lang/Boolean;
       5: return

  public final software.amazon.awssdk.services.dynamodb.model.AutoScalingSettingsUpdate$Builder autoScalingDisabled(java.lang.Boolean);
    Code:
       0: aload_0
       1: aload_1
       2: putfield      #5                  // Field autoScalingDisabled:Ljava/lang/Boolean;
       5: aload_0
       6: areturn

  public final java.lang.String getAutoScalingRoleArn();
    Code:
       0: aload_0
       1: getfield      #4                  // Field autoScalingRoleArn:Ljava/lang/String;
       4: areturn

  public final void setAutoScalingRoleArn(java.lang.String);
    Code:
       0: aload_0
       1: aload_1
       2: putfield      #4                  // Field autoScalingRoleArn:Ljava/lang/String;
       5: return

  public final software.amazon.awssdk.services.dynamodb.model.AutoScalingSettingsUpdate$Builder autoScalingRoleArn(java.lang.String);
    Code:
       0: aload_0
       1: aload_1
       2: putfield      #4                  // Field autoScalingRoleArn:Ljava/lang/String;
       5: aload_0
       6: areturn

  public final software.amazon.awssdk.services.dynamodb.model.AutoScalingPolicyUpdate$Builder getScalingPolicyUpdate();
    Code:
       0: aload_0
       1: getfield      #3                  // Field scalingPolicyUpdate:Lsoftware/amazon/awssdk/services/dynamodb/model/AutoScalingPolicyUpdate;
       4: ifnull        17
       7: aload_0
       8: getfield      #3                  // Field scalingPolicyUpdate:Lsoftware/amazon/awssdk/services/dynamodb/model/AutoScalingPolicyUpdate;
      11: invokevirtual #19                 // Method software/amazon/awssdk/services/dynamodb/model/AutoScalingPolicyUpdate.toBuilder:()Lsoftware/amazon/awssdk/services/dynamodb/model/AutoScalingPolicyUpdate$Builder;
      14: goto          18
      17: aconst_null
      18: areturn

  public final void setScalingPolicyUpdate(software.amazon.awssdk.services.dynamodb.model.AutoScalingPolicyUpdate$BuilderImpl);
    Code:
       0: aload_0
       1: aload_1
       2: ifnull        12
       5: aload_1
       6: invokevirtual #20                 // Method software/amazon/awssdk/services/dynamodb/model/AutoScalingPolicyUpdate$BuilderImpl.build:()Lsoftware/amazon/awssdk/services/dynamodb/model/AutoScalingPolicyUpdate;
       9: goto          13
      12: aconst_null
      13: putfield      #3                  // Field scalingPolicyUpdate:Lsoftware/amazon/awssdk/services/dynamodb/model/AutoScalingPolicyUpdate;
      16: return

  public final software.amazon.awssdk.services.dynamodb.model.AutoScalingSettingsUpdate$Builder scalingPolicyUpdate(software.amazon.awssdk.services.dynamodb.model.AutoScalingPolicyUpdate);
    Code:
       0: aload_0
       1: aload_1
       2: putfield      #3                  // Field scalingPolicyUpdate:Lsoftware/amazon/awssdk/services/dynamodb/model/AutoScalingPolicyUpdate;
       5: aload_0
       6: areturn

  public software.amazon.awssdk.services.dynamodb.model.AutoScalingSettingsUpdate build();
    Code:
       0: new           #21                 // class software/amazon/awssdk/services/dynamodb/model/AutoScalingSettingsUpdate
       3: dup
       4: aload_0
       5: aconst_null
       6: invokespecial #22                 // Method software/amazon/awssdk/services/dynamodb/model/AutoScalingSettingsUpdate."<init>":(Lsoftware/amazon/awssdk/services/dynamodb/model/AutoScalingSettingsUpdate$BuilderImpl;Lsoftware/amazon/awssdk/services/dynamodb/model/AutoScalingSettingsUpdate$1;)V
       9: areturn

  public java.util.List<software.amazon.awssdk.core.SdkField<?>> sdkFields();
    Code:
       0: invokestatic  #23                 // Method software/amazon/awssdk/services/dynamodb/model/AutoScalingSettingsUpdate.access$1300:()Ljava/util/List;
       3: areturn

  public java.lang.Object build();
    Code:
       0: aload_0
       1: invokevirtual #24                 // Method build:()Lsoftware/amazon/awssdk/services/dynamodb/model/AutoScalingSettingsUpdate;
       4: areturn

  static java.lang.Long access$000(software.amazon.awssdk.services.dynamodb.model.AutoScalingSettingsUpdate$BuilderImpl);
    Code:
       0: aload_0
       1: getfield      #7                  // Field minimumUnits:Ljava/lang/Long;
       4: areturn

  static java.lang.Long access$100(software.amazon.awssdk.services.dynamodb.model.AutoScalingSettingsUpdate$BuilderImpl);
    Code:
       0: aload_0
       1: getfield      #6                  // Field maximumUnits:Ljava/lang/Long;
       4: areturn

  static java.lang.Boolean access$200(software.amazon.awssdk.services.dynamodb.model.AutoScalingSettingsUpdate$BuilderImpl);
    Code:
       0: aload_0
       1: getfield      #5                  // Field autoScalingDisabled:Ljava/lang/Boolean;
       4: areturn

  static java.lang.String access$300(software.amazon.awssdk.services.dynamodb.model.AutoScalingSettingsUpdate$BuilderImpl);
    Code:
       0: aload_0
       1: getfield      #4                  // Field autoScalingRoleArn:Ljava/lang/String;
       4: areturn

  static software.amazon.awssdk.services.dynamodb.model.AutoScalingPolicyUpdate access$400(software.amazon.awssdk.services.dynamodb.model.AutoScalingSettingsUpdate$BuilderImpl);
    Code:
       0: aload_0
       1: getfield      #3                  // Field scalingPolicyUpdate:Lsoftware/amazon/awssdk/services/dynamodb/model/AutoScalingPolicyUpdate;
       4: areturn

  software.amazon.awssdk.services.dynamodb.model.AutoScalingSettingsUpdate$BuilderImpl(software.amazon.awssdk.services.dynamodb.model.AutoScalingSettingsUpdate, software.amazon.awssdk.services.dynamodb.model.AutoScalingSettingsUpdate$1);
    Code:
       0: aload_0
       1: aload_1
       2: invokespecial #2                  // Method "<init>":(Lsoftware/amazon/awssdk/services/dynamodb/model/AutoScalingSettingsUpdate;)V
       5: return

  software.amazon.awssdk.services.dynamodb.model.AutoScalingSettingsUpdate$BuilderImpl(software.amazon.awssdk.services.dynamodb.model.AutoScalingSettingsUpdate$1);
    Code:
       0: aload_0
       1: invokespecial #1                  // Method "<init>":()V
       4: return
}
