Compiled from "BatchStatementErrorCodeEnum.java"
public final class software.amazon.awssdk.services.dynamodb.model.BatchStatementErrorCodeEnum extends java.lang.Enum<software.amazon.awssdk.services.dynamodb.model.BatchStatementErrorCodeEnum> {
  public static final software.amazon.awssdk.services.dynamodb.model.BatchStatementErrorCodeEnum CONDITIONAL_CHECK_FAILED;

  public static final software.amazon.awssdk.services.dynamodb.model.BatchStatementErrorCodeEnum ITEM_COLLECTION_SIZE_LIMIT_EXCEEDED;

  public static final software.amazon.awssdk.services.dynamodb.model.BatchStatementErrorCodeEnum REQUEST_LIMIT_EXCEEDED;

  public static final software.amazon.awssdk.services.dynamodb.model.BatchStatementErrorCodeEnum VALIDATION_ERROR;

  public static final software.amazon.awssdk.services.dynamodb.model.BatchStatementErrorCodeEnum PROVISIONED_THROUGHPUT_EXCEEDED;

  public static final software.amazon.awssdk.services.dynamodb.model.BatchStatementErrorCodeEnum TRANSACTION_CONFLICT;

  public static final software.amazon.awssdk.services.dynamodb.model.BatchStatementErrorCodeEnum THROTTLING_ERROR;

  public static final software.amazon.awssdk.services.dynamodb.model.BatchStatementErrorCodeEnum INTERNAL_SERVER_ERROR;

  public static final software.amazon.awssdk.services.dynamodb.model.BatchStatementErrorCodeEnum RESOURCE_NOT_FOUND;

  public static final software.amazon.awssdk.services.dynamodb.model.BatchStatementErrorCodeEnum ACCESS_DENIED;

  public static final software.amazon.awssdk.services.dynamodb.model.BatchStatementErrorCodeEnum DUPLICATE_ITEM;

  public static final software.amazon.awssdk.services.dynamodb.model.BatchStatementErrorCodeEnum UNKNOWN_TO_SDK_VERSION;

  private static final java.util.Map<java.lang.String, software.amazon.awssdk.services.dynamodb.model.BatchStatementErrorCodeEnum> VALUE_MAP;

  private final java.lang.String value;

  private static final software.amazon.awssdk.services.dynamodb.model.BatchStatementErrorCodeEnum[] $VALUES;

  public static software.amazon.awssdk.services.dynamodb.model.BatchStatementErrorCodeEnum[] values();
    Code:
       0: getstatic     #1                  // Field $VALUES:[Lsoftware/amazon/awssdk/services/dynamodb/model/BatchStatementErrorCodeEnum;
       3: invokevirtual #2                  // Method "[Lsoftware/amazon/awssdk/services/dynamodb/model/BatchStatementErrorCodeEnum;".clone:()Ljava/lang/Object;
       6: checkcast     #3                  // class "[Lsoftware/amazon/awssdk/services/dynamodb/model/BatchStatementErrorCodeEnum;"
       9: areturn

  public static software.amazon.awssdk.services.dynamodb.model.BatchStatementErrorCodeEnum valueOf(java.lang.String);
    Code:
       0: ldc           #4                  // class software/amazon/awssdk/services/dynamodb/model/BatchStatementErrorCodeEnum
       2: aload_0
       3: invokestatic  #5                  // Method java/lang/Enum.valueOf:(Ljava/lang/Class;Ljava/lang/String;)Ljava/lang/Enum;
       6: checkcast     #4                  // class software/amazon/awssdk/services/dynamodb/model/BatchStatementErrorCodeEnum
       9: areturn

  private software.amazon.awssdk.services.dynamodb.model.BatchStatementErrorCodeEnum(java.lang.String);
    Code:
       0: aload_0
       1: aload_1
       2: iload_2
       3: invokespecial #6                  // Method java/lang/Enum."<init>":(Ljava/lang/String;I)V
       6: aload_0
       7: aload_3
       8: putfield      #7                  // Field value:Ljava/lang/String;
      11: return

  public java.lang.String toString();
    Code:
       0: aload_0
       1: getfield      #7                  // Field value:Ljava/lang/String;
       4: invokestatic  #8                  // Method java/lang/String.valueOf:(Ljava/lang/Object;)Ljava/lang/String;
       7: areturn

  public static software.amazon.awssdk.services.dynamodb.model.BatchStatementErrorCodeEnum fromValue(java.lang.String);
    Code:
       0: aload_0
       1: ifnonnull     6
       4: aconst_null
       5: areturn
       6: getstatic     #9                  // Field VALUE_MAP:Ljava/util/Map;
       9: aload_0
      10: getstatic     #10                 // Field UNKNOWN_TO_SDK_VERSION:Lsoftware/amazon/awssdk/services/dynamodb/model/BatchStatementErrorCodeEnum;
      13: invokeinterface #11,  3           // InterfaceMethod java/util/Map.getOrDefault:(Ljava/lang/Object;Ljava/lang/Object;)Ljava/lang/Object;
      18: checkcast     #4                  // class software/amazon/awssdk/services/dynamodb/model/BatchStatementErrorCodeEnum
      21: areturn

  public static java.util.Set<software.amazon.awssdk.services.dynamodb.model.BatchStatementErrorCodeEnum> knownValues();
    Code:
       0: ldc           #4                  // class software/amazon/awssdk/services/dynamodb/model/BatchStatementErrorCodeEnum
       2: invokestatic  #12                 // Method java/util/EnumSet.allOf:(Ljava/lang/Class;)Ljava/util/EnumSet;
       5: astore_0
       6: aload_0
       7: getstatic     #10                 // Field UNKNOWN_TO_SDK_VERSION:Lsoftware/amazon/awssdk/services/dynamodb/model/BatchStatementErrorCodeEnum;
      10: invokeinterface #13,  2           // InterfaceMethod java/util/Set.remove:(Ljava/lang/Object;)Z
      15: pop
      16: aload_0
      17: areturn

  static {};
    Code:
       0: new           #4                  // class software/amazon/awssdk/services/dynamodb/model/BatchStatementErrorCodeEnum
       3: dup
       4: ldc           #14                 // String CONDITIONAL_CHECK_FAILED
       6: iconst_0
       7: ldc           #15                 // String ConditionalCheckFailed
       9: invokespecial #16                 // Method "<init>":(Ljava/lang/String;ILjava/lang/String;)V
      12: putstatic     #17                 // Field CONDITIONAL_CHECK_FAILED:Lsoftware/amazon/awssdk/services/dynamodb/model/BatchStatementErrorCodeEnum;
      15: new           #4                  // class software/amazon/awssdk/services/dynamodb/model/BatchStatementErrorCodeEnum
      18: dup
      19: ldc           #18                 // String ITEM_COLLECTION_SIZE_LIMIT_EXCEEDED
      21: iconst_1
      22: ldc           #19                 // String ItemCollectionSizeLimitExceeded
      24: invokespecial #16                 // Method "<init>":(Ljava/lang/String;ILjava/lang/String;)V
      27: putstatic     #20                 // Field ITEM_COLLECTION_SIZE_LIMIT_EXCEEDED:Lsoftware/amazon/awssdk/services/dynamodb/model/BatchStatementErrorCodeEnum;
      30: new           #4                  // class software/amazon/awssdk/services/dynamodb/model/BatchStatementErrorCodeEnum
      33: dup
      34: ldc           #21                 // String REQUEST_LIMIT_EXCEEDED
      36: iconst_2
      37: ldc           #22                 // String RequestLimitExceeded
      39: invokespecial #16                 // Method "<init>":(Ljava/lang/String;ILjava/lang/String;)V
      42: putstatic     #23                 // Field REQUEST_LIMIT_EXCEEDED:Lsoftware/amazon/awssdk/services/dynamodb/model/BatchStatementErrorCodeEnum;
      45: new           #4                  // class software/amazon/awssdk/services/dynamodb/model/BatchStatementErrorCodeEnum
      48: dup
      49: ldc           #24                 // String VALIDATION_ERROR
      51: iconst_3
      52: ldc           #25                 // String ValidationError
      54: invokespecial #16                 // Method "<init>":(Ljava/lang/String;ILjava/lang/String;)V
      57: putstatic     #26                 // Field VALIDATION_ERROR:Lsoftware/amazon/awssdk/services/dynamodb/model/BatchStatementErrorCodeEnum;
      60: new           #4                  // class software/amazon/awssdk/services/dynamodb/model/BatchStatementErrorCodeEnum
      63: dup
      64: ldc           #27                 // String PROVISIONED_THROUGHPUT_EXCEEDED
      66: iconst_4
      67: ldc           #28                 // String ProvisionedThroughputExceeded
      69: invokespecial #16                 // Method "<init>":(Ljava/lang/String;ILjava/lang/String;)V
      72: putstatic     #29                 // Field PROVISIONED_THROUGHPUT_EXCEEDED:Lsoftware/amazon/awssdk/services/dynamodb/model/BatchStatementErrorCodeEnum;
      75: new           #4                  // class software/amazon/awssdk/services/dynamodb/model/BatchStatementErrorCodeEnum
      78: dup
      79: ldc           #30                 // String TRANSACTION_CONFLICT
      81: iconst_5
      82: ldc           #31                 // String TransactionConflict
      84: invokespecial #16                 // Method "<init>":(Ljava/lang/String;ILjava/lang/String;)V
      87: putstatic     #32                 // Field TRANSACTION_CONFLICT:Lsoftware/amazon/awssdk/services/dynamodb/model/BatchStatementErrorCodeEnum;
      90: new           #4                  // class software/amazon/awssdk/services/dynamodb/model/BatchStatementErrorCodeEnum
      93: dup
      94: ldc           #33                 // String THROTTLING_ERROR
      96: bipush        6
      98: ldc           #34                 // String ThrottlingError
     100: invokespecial #16                 // Method "<init>":(Ljava/lang/String;ILjava/lang/String;)V
     103: putstatic     #35                 // Field THROTTLING_ERROR:Lsoftware/amazon/awssdk/services/dynamodb/model/BatchStatementErrorCodeEnum;
     106: new           #4                  // class software/amazon/awssdk/services/dynamodb/model/BatchStatementErrorCodeEnum
     109: dup
     110: ldc           #36                 // String INTERNAL_SERVER_ERROR
     112: bipush        7
     114: ldc           #37                 // String InternalServerError
     116: invokespecial #16                 // Method "<init>":(Ljava/lang/String;ILjava/lang/String;)V
     119: putstatic     #38                 // Field INTERNAL_SERVER_ERROR:Lsoftware/amazon/awssdk/services/dynamodb/model/BatchStatementErrorCodeEnum;
     122: new           #4                  // class software/amazon/awssdk/services/dynamodb/model/BatchStatementErrorCodeEnum
     125: dup
     126: ldc           #39                 // String RESOURCE_NOT_FOUND
     128: bipush        8
     130: ldc           #40                 // String ResourceNotFound
     132: invokespecial #16                 // Method "<init>":(Ljava/lang/String;ILjava/lang/String;)V
     135: putstatic     #41                 // Field RESOURCE_NOT_FOUND:Lsoftware/amazon/awssdk/services/dynamodb/model/BatchStatementErrorCodeEnum;
     138: new           #4                  // class software/amazon/awssdk/services/dynamodb/model/BatchStatementErrorCodeEnum
     141: dup
     142: ldc           #42                 // String ACCESS_DENIED
     144: bipush        9
     146: ldc           #43                 // String AccessDenied
     148: invokespecial #16                 // Method "<init>":(Ljava/lang/String;ILjava/lang/String;)V
     151: putstatic     #44                 // Field ACCESS_DENIED:Lsoftware/amazon/awssdk/services/dynamodb/model/BatchStatementErrorCodeEnum;
     154: new           #4                  // class software/amazon/awssdk/services/dynamodb/model/BatchStatementErrorCodeEnum
     157: dup
     158: ldc           #45                 // String DUPLICATE_ITEM
     160: bipush        10
     162: ldc           #46                 // String DuplicateItem
     164: invokespecial #16                 // Method "<init>":(Ljava/lang/String;ILjava/lang/String;)V
     167: putstatic     #47                 // Field DUPLICATE_ITEM:Lsoftware/amazon/awssdk/services/dynamodb/model/BatchStatementErrorCodeEnum;
     170: new           #4                  // class software/amazon/awssdk/services/dynamodb/model/BatchStatementErrorCodeEnum
     173: dup
     174: ldc           #48                 // String UNKNOWN_TO_SDK_VERSION
     176: bipush        11
     178: aconst_null
     179: invokespecial #16                 // Method "<init>":(Ljava/lang/String;ILjava/lang/String;)V
     182: putstatic     #10                 // Field UNKNOWN_TO_SDK_VERSION:Lsoftware/amazon/awssdk/services/dynamodb/model/BatchStatementErrorCodeEnum;
     185: bipush        12
     187: anewarray     #4                  // class software/amazon/awssdk/services/dynamodb/model/BatchStatementErrorCodeEnum
     190: dup
     191: iconst_0
     192: getstatic     #17                 // Field CONDITIONAL_CHECK_FAILED:Lsoftware/amazon/awssdk/services/dynamodb/model/BatchStatementErrorCodeEnum;
     195: aastore
     196: dup
     197: iconst_1
     198: getstatic     #20                 // Field ITEM_COLLECTION_SIZE_LIMIT_EXCEEDED:Lsoftware/amazon/awssdk/services/dynamodb/model/BatchStatementErrorCodeEnum;
     201: aastore
     202: dup
     203: iconst_2
     204: getstatic     #23                 // Field REQUEST_LIMIT_EXCEEDED:Lsoftware/amazon/awssdk/services/dynamodb/model/BatchStatementErrorCodeEnum;
     207: aastore
     208: dup
     209: iconst_3
     210: getstatic     #26                 // Field VALIDATION_ERROR:Lsoftware/amazon/awssdk/services/dynamodb/model/BatchStatementErrorCodeEnum;
     213: aastore
     214: dup
     215: iconst_4
     216: getstatic     #29                 // Field PROVISIONED_THROUGHPUT_EXCEEDED:Lsoftware/amazon/awssdk/services/dynamodb/model/BatchStatementErrorCodeEnum;
     219: aastore
     220: dup
     221: iconst_5
     222: getstatic     #32                 // Field TRANSACTION_CONFLICT:Lsoftware/amazon/awssdk/services/dynamodb/model/BatchStatementErrorCodeEnum;
     225: aastore
     226: dup
     227: bipush        6
     229: getstatic     #35                 // Field THROTTLING_ERROR:Lsoftware/amazon/awssdk/services/dynamodb/model/BatchStatementErrorCodeEnum;
     232: aastore
     233: dup
     234: bipush        7
     236: getstatic     #38                 // Field INTERNAL_SERVER_ERROR:Lsoftware/amazon/awssdk/services/dynamodb/model/BatchStatementErrorCodeEnum;
     239: aastore
     240: dup
     241: bipush        8
     243: getstatic     #41                 // Field RESOURCE_NOT_FOUND:Lsoftware/amazon/awssdk/services/dynamodb/model/BatchStatementErrorCodeEnum;
     246: aastore
     247: dup
     248: bipush        9
     250: getstatic     #44                 // Field ACCESS_DENIED:Lsoftware/amazon/awssdk/services/dynamodb/model/BatchStatementErrorCodeEnum;
     253: aastore
     254: dup
     255: bipush        10
     257: getstatic     #47                 // Field DUPLICATE_ITEM:Lsoftware/amazon/awssdk/services/dynamodb/model/BatchStatementErrorCodeEnum;
     260: aastore
     261: dup
     262: bipush        11
     264: getstatic     #10                 // Field UNKNOWN_TO_SDK_VERSION:Lsoftware/amazon/awssdk/services/dynamodb/model/BatchStatementErrorCodeEnum;
     267: aastore
     268: putstatic     #1                  // Field $VALUES:[Lsoftware/amazon/awssdk/services/dynamodb/model/BatchStatementErrorCodeEnum;
     271: ldc           #4                  // class software/amazon/awssdk/services/dynamodb/model/BatchStatementErrorCodeEnum
     273: invokedynamic #49,  0             // InvokeDynamic #0:apply:()Ljava/util/function/Function;
     278: invokestatic  #50                 // Method software/amazon/awssdk/utils/internal/EnumUtils.uniqueIndex:(Ljava/lang/Class;Ljava/util/function/Function;)Ljava/util/Map;
     281: putstatic     #9                  // Field VALUE_MAP:Ljava/util/Map;
     284: return
}
