Compiled from "DescribeTimeToLiveResponse.java"
final class software.amazon.awssdk.services.dynamodb.model.DescribeTimeToLiveResponse$BuilderImpl extends software.amazon.awssdk.services.dynamodb.model.DynamoDbResponse$BuilderImpl implements software.amazon.awssdk.services.dynamodb.model.DescribeTimeToLiveResponse$Builder {
  private software.amazon.awssdk.services.dynamodb.model.TimeToLiveDescription timeToLiveDescription;

  private software.amazon.awssdk.services.dynamodb.model.DescribeTimeToLiveResponse$BuilderImpl();
    Code:
       0: aload_0
       1: invokespecial #4                  // Method software/amazon/awssdk/services/dynamodb/model/DynamoDbResponse$BuilderImpl."<init>":()V
       4: return

  private software.amazon.awssdk.services.dynamodb.model.DescribeTimeToLiveResponse$BuilderImpl(software.amazon.awssdk.services.dynamodb.model.DescribeTimeToLiveResponse);
    Code:
       0: aload_0
       1: aload_1
       2: invokespecial #5                  // Method software/amazon/awssdk/services/dynamodb/model/DynamoDbResponse$BuilderImpl."<init>":(Lsoftware/amazon/awssdk/services/dynamodb/model/DynamoDbResponse;)V
       5: aload_0
       6: aload_1
       7: invokestatic  #6                  // Method software/amazon/awssdk/services/dynamodb/model/DescribeTimeToLiveResponse.access$300:(Lsoftware/amazon/awssdk/services/dynamodb/model/DescribeTimeToLiveResponse;)Lsoftware/amazon/awssdk/services/dynamodb/model/TimeToLiveDescription;
      10: invokevirtual #7                  // Method timeToLiveDescription:(Lsoftware/amazon/awssdk/services/dynamodb/model/TimeToLiveDescription;)Lsoftware/amazon/awssdk/services/dynamodb/model/DescribeTimeToLiveResponse$Builder;
      13: pop
      14: return

  public final software.amazon.awssdk.services.dynamodb.model.TimeToLiveDescription$Builder getTimeToLiveDescription();
    Code:
       0: aload_0
       1: getfield      #3                  // Field timeToLiveDescription:Lsoftware/amazon/awssdk/services/dynamodb/model/TimeToLiveDescription;
       4: ifnull        17
       7: aload_0
       8: getfield      #3                  // Field timeToLiveDescription:Lsoftware/amazon/awssdk/services/dynamodb/model/TimeToLiveDescription;
      11: invokevirtual #8                  // Method software/amazon/awssdk/services/dynamodb/model/TimeToLiveDescription.toBuilder:()Lsoftware/amazon/awssdk/services/dynamodb/model/TimeToLiveDescription$Builder;
      14: goto          18
      17: aconst_null
      18: areturn

  public final void setTimeToLiveDescription(software.amazon.awssdk.services.dynamodb.model.TimeToLiveDescription$BuilderImpl);
    Code:
       0: aload_0
       1: aload_1
       2: ifnull        12
       5: aload_1
       6: invokevirtual #9                  // Method software/amazon/awssdk/services/dynamodb/model/TimeToLiveDescription$BuilderImpl.build:()Lsoftware/amazon/awssdk/services/dynamodb/model/TimeToLiveDescription;
       9: goto          13
      12: aconst_null
      13: putfield      #3                  // Field timeToLiveDescription:Lsoftware/amazon/awssdk/services/dynamodb/model/TimeToLiveDescription;
      16: return

  public final software.amazon.awssdk.services.dynamodb.model.DescribeTimeToLiveResponse$Builder timeToLiveDescription(software.amazon.awssdk.services.dynamodb.model.TimeToLiveDescription);
    Code:
       0: aload_0
       1: aload_1
       2: putfield      #3                  // Field timeToLiveDescription:Lsoftware/amazon/awssdk/services/dynamodb/model/TimeToLiveDescription;
       5: aload_0
       6: areturn

  public software.amazon.awssdk.services.dynamodb.model.DescribeTimeToLiveResponse build();
    Code:
       0: new           #10                 // class software/amazon/awssdk/services/dynamodb/model/DescribeTimeToLiveResponse
       3: dup
       4: aload_0
       5: aconst_null
       6: invokespecial #11                 // Method software/amazon/awssdk/services/dynamodb/model/DescribeTimeToLiveResponse."<init>":(Lsoftware/amazon/awssdk/services/dynamodb/model/DescribeTimeToLiveResponse$BuilderImpl;Lsoftware/amazon/awssdk/services/dynamodb/model/DescribeTimeToLiveResponse$1;)V
       9: areturn

  public java.util.List<software.amazon.awssdk.core.SdkField<?>> sdkFields();
    Code:
       0: invokestatic  #12                 // Method software/amazon/awssdk/services/dynamodb/model/DescribeTimeToLiveResponse.access$500:()Ljava/util/List;
       3: areturn

  public software.amazon.awssdk.services.dynamodb.model.DynamoDbResponse build();
    Code:
       0: aload_0
       1: invokevirtual #13                 // Method build:()Lsoftware/amazon/awssdk/services/dynamodb/model/DescribeTimeToLiveResponse;
       4: areturn

  public software.amazon.awssdk.awscore.AwsResponse build();
    Code:
       0: aload_0
       1: invokevirtual #13                 // Method build:()Lsoftware/amazon/awssdk/services/dynamodb/model/DescribeTimeToLiveResponse;
       4: areturn

  public software.amazon.awssdk.core.SdkResponse build();
    Code:
       0: aload_0
       1: invokevirtual #13                 // Method build:()Lsoftware/amazon/awssdk/services/dynamodb/model/DescribeTimeToLiveResponse;
       4: areturn

  public java.lang.Object build();
    Code:
       0: aload_0
       1: invokevirtual #13                 // Method build:()Lsoftware/amazon/awssdk/services/dynamodb/model/DescribeTimeToLiveResponse;
       4: areturn

  static software.amazon.awssdk.services.dynamodb.model.TimeToLiveDescription access$000(software.amazon.awssdk.services.dynamodb.model.DescribeTimeToLiveResponse$BuilderImpl);
    Code:
       0: aload_0
       1: getfield      #3                  // Field timeToLiveDescription:Lsoftware/amazon/awssdk/services/dynamodb/model/TimeToLiveDescription;
       4: areturn

  software.amazon.awssdk.services.dynamodb.model.DescribeTimeToLiveResponse$BuilderImpl(software.amazon.awssdk.services.dynamodb.model.DescribeTimeToLiveResponse, software.amazon.awssdk.services.dynamodb.model.DescribeTimeToLiveResponse$1);
    Code:
       0: aload_0
       1: aload_1
       2: invokespecial #2                  // Method "<init>":(Lsoftware/amazon/awssdk/services/dynamodb/model/DescribeTimeToLiveResponse;)V
       5: return

  software.amazon.awssdk.services.dynamodb.model.DescribeTimeToLiveResponse$BuilderImpl(software.amazon.awssdk.services.dynamodb.model.DescribeTimeToLiveResponse$1);
    Code:
       0: aload_0
       1: invokespecial #1                  // Method "<init>":()V
       4: return
}
