Compiled from "ExecuteTransactionRequest.java"
final class software.amazon.awssdk.services.dynamodb.model.ExecuteTransactionRequest$BuilderImpl extends software.amazon.awssdk.services.dynamodb.model.DynamoDbRequest$BuilderImpl implements software.amazon.awssdk.services.dynamodb.model.ExecuteTransactionRequest$Builder {
  private java.util.List<software.amazon.awssdk.services.dynamodb.model.ParameterizedStatement> transactStatements;

  private java.lang.String clientRequestToken;

  private java.lang.String returnConsumedCapacity;

  private software.amazon.awssdk.services.dynamodb.model.ExecuteTransactionRequest$BuilderImpl();
    Code:
       0: aload_0
       1: invokespecial #6                  // Method software/amazon/awssdk/services/dynamodb/model/DynamoDbRequest$BuilderImpl."<init>":()V
       4: aload_0
       5: invokestatic  #7                  // Method software/amazon/awssdk/core/util/DefaultSdkAutoConstructList.getInstance:()Lsoftware/amazon/awssdk/core/util/DefaultSdkAutoConstructList;
       8: putfield      #5                  // Field transactStatements:Ljava/util/List;
      11: return

  private software.amazon.awssdk.services.dynamodb.model.ExecuteTransactionRequest$BuilderImpl(software.amazon.awssdk.services.dynamodb.model.ExecuteTransactionRequest);
    Code:
       0: aload_0
       1: aload_1
       2: invokespecial #8                  // Method software/amazon/awssdk/services/dynamodb/model/DynamoDbRequest$BuilderImpl."<init>":(Lsoftware/amazon/awssdk/services/dynamodb/model/DynamoDbRequest;)V
       5: aload_0
       6: invokestatic  #7                  // Method software/amazon/awssdk/core/util/DefaultSdkAutoConstructList.getInstance:()Lsoftware/amazon/awssdk/core/util/DefaultSdkAutoConstructList;
       9: putfield      #5                  // Field transactStatements:Ljava/util/List;
      12: aload_0
      13: aload_1
      14: invokestatic  #9                  // Method software/amazon/awssdk/services/dynamodb/model/ExecuteTransactionRequest.access$500:(Lsoftware/amazon/awssdk/services/dynamodb/model/ExecuteTransactionRequest;)Ljava/util/List;
      17: invokevirtual #10                 // Method transactStatements:(Ljava/util/Collection;)Lsoftware/amazon/awssdk/services/dynamodb/model/ExecuteTransactionRequest$Builder;
      20: pop
      21: aload_0
      22: aload_1
      23: invokestatic  #11                 // Method software/amazon/awssdk/services/dynamodb/model/ExecuteTransactionRequest.access$600:(Lsoftware/amazon/awssdk/services/dynamodb/model/ExecuteTransactionRequest;)Ljava/lang/String;
      26: invokevirtual #12                 // Method clientRequestToken:(Ljava/lang/String;)Lsoftware/amazon/awssdk/services/dynamodb/model/ExecuteTransactionRequest$Builder;
      29: pop
      30: aload_0
      31: aload_1
      32: invokestatic  #13                 // Method software/amazon/awssdk/services/dynamodb/model/ExecuteTransactionRequest.access$700:(Lsoftware/amazon/awssdk/services/dynamodb/model/ExecuteTransactionRequest;)Ljava/lang/String;
      35: invokevirtual #14                 // Method returnConsumedCapacity:(Ljava/lang/String;)Lsoftware/amazon/awssdk/services/dynamodb/model/ExecuteTransactionRequest$Builder;
      38: pop
      39: return

  public final java.util.List<software.amazon.awssdk.services.dynamodb.model.ParameterizedStatement$Builder> getTransactStatements();
    Code:
       0: aload_0
       1: getfield      #5                  // Field transactStatements:Ljava/util/List;
       4: invokestatic  #15                 // Method software/amazon/awssdk/services/dynamodb/model/ParameterizedStatementsCopier.copyToBuilder:(Ljava/util/Collection;)Ljava/util/List;
       7: astore_1
       8: aload_1
       9: instanceof    #16                 // class software/amazon/awssdk/core/util/SdkAutoConstructList
      12: ifeq          17
      15: aconst_null
      16: areturn
      17: aload_1
      18: areturn

  public final void setTransactStatements(java.util.Collection<software.amazon.awssdk.services.dynamodb.model.ParameterizedStatement$BuilderImpl>);
    Code:
       0: aload_0
       1: aload_1
       2: invokestatic  #17                 // Method software/amazon/awssdk/services/dynamodb/model/ParameterizedStatementsCopier.copyFromBuilder:(Ljava/util/Collection;)Ljava/util/List;
       5: putfield      #5                  // Field transactStatements:Ljava/util/List;
       8: return

  public final software.amazon.awssdk.services.dynamodb.model.ExecuteTransactionRequest$Builder transactStatements(java.util.Collection<software.amazon.awssdk.services.dynamodb.model.ParameterizedStatement>);
    Code:
       0: aload_0
       1: aload_1
       2: invokestatic  #18                 // Method software/amazon/awssdk/services/dynamodb/model/ParameterizedStatementsCopier.copy:(Ljava/util/Collection;)Ljava/util/List;
       5: putfield      #5                  // Field transactStatements:Ljava/util/List;
       8: aload_0
       9: areturn

  public final software.amazon.awssdk.services.dynamodb.model.ExecuteTransactionRequest$Builder transactStatements(software.amazon.awssdk.services.dynamodb.model.ParameterizedStatement...);
    Code:
       0: aload_0
       1: aload_1
       2: invokestatic  #19                 // Method java/util/Arrays.asList:([Ljava/lang/Object;)Ljava/util/List;
       5: invokevirtual #10                 // Method transactStatements:(Ljava/util/Collection;)Lsoftware/amazon/awssdk/services/dynamodb/model/ExecuteTransactionRequest$Builder;
       8: pop
       9: aload_0
      10: areturn

  public final software.amazon.awssdk.services.dynamodb.model.ExecuteTransactionRequest$Builder transactStatements(java.util.function.Consumer<software.amazon.awssdk.services.dynamodb.model.ParameterizedStatement$Builder>...);
    Code:
       0: aload_0
       1: aload_1
       2: invokestatic  #20                 // InterfaceMethod java/util/stream/Stream.of:([Ljava/lang/Object;)Ljava/util/stream/Stream;
       5: invokedynamic #21,  0             // InvokeDynamic #0:apply:()Ljava/util/function/Function;
      10: invokeinterface #22,  2           // InterfaceMethod java/util/stream/Stream.map:(Ljava/util/function/Function;)Ljava/util/stream/Stream;
      15: invokestatic  #23                 // Method java/util/stream/Collectors.toList:()Ljava/util/stream/Collector;
      18: invokeinterface #24,  2           // InterfaceMethod java/util/stream/Stream.collect:(Ljava/util/stream/Collector;)Ljava/lang/Object;
      23: checkcast     #25                 // class java/util/Collection
      26: invokevirtual #10                 // Method transactStatements:(Ljava/util/Collection;)Lsoftware/amazon/awssdk/services/dynamodb/model/ExecuteTransactionRequest$Builder;
      29: pop
      30: aload_0
      31: areturn

  public final java.lang.String getClientRequestToken();
    Code:
       0: aload_0
       1: getfield      #4                  // Field clientRequestToken:Ljava/lang/String;
       4: areturn

  public final void setClientRequestToken(java.lang.String);
    Code:
       0: aload_0
       1: aload_1
       2: putfield      #4                  // Field clientRequestToken:Ljava/lang/String;
       5: return

  public final software.amazon.awssdk.services.dynamodb.model.ExecuteTransactionRequest$Builder clientRequestToken(java.lang.String);
    Code:
       0: aload_0
       1: aload_1
       2: putfield      #4                  // Field clientRequestToken:Ljava/lang/String;
       5: aload_0
       6: areturn

  public final java.lang.String getReturnConsumedCapacity();
    Code:
       0: aload_0
       1: getfield      #3                  // Field returnConsumedCapacity:Ljava/lang/String;
       4: areturn

  public final void setReturnConsumedCapacity(java.lang.String);
    Code:
       0: aload_0
       1: aload_1
       2: putfield      #3                  // Field returnConsumedCapacity:Ljava/lang/String;
       5: return

  public final software.amazon.awssdk.services.dynamodb.model.ExecuteTransactionRequest$Builder returnConsumedCapacity(java.lang.String);
    Code:
       0: aload_0
       1: aload_1
       2: putfield      #3                  // Field returnConsumedCapacity:Ljava/lang/String;
       5: aload_0
       6: areturn

  public final software.amazon.awssdk.services.dynamodb.model.ExecuteTransactionRequest$Builder returnConsumedCapacity(software.amazon.awssdk.services.dynamodb.model.ReturnConsumedCapacity);
    Code:
       0: aload_0
       1: aload_1
       2: ifnonnull     9
       5: aconst_null
       6: goto          13
       9: aload_1
      10: invokevirtual #26                 // Method software/amazon/awssdk/services/dynamodb/model/ReturnConsumedCapacity.toString:()Ljava/lang/String;
      13: invokevirtual #14                 // Method returnConsumedCapacity:(Ljava/lang/String;)Lsoftware/amazon/awssdk/services/dynamodb/model/ExecuteTransactionRequest$Builder;
      16: pop
      17: aload_0
      18: areturn

  public software.amazon.awssdk.services.dynamodb.model.ExecuteTransactionRequest$Builder overrideConfiguration(software.amazon.awssdk.awscore.AwsRequestOverrideConfiguration);
    Code:
       0: aload_0
       1: aload_1
       2: invokespecial #27                 // Method software/amazon/awssdk/services/dynamodb/model/DynamoDbRequest$BuilderImpl.overrideConfiguration:(Lsoftware/amazon/awssdk/awscore/AwsRequestOverrideConfiguration;)Lsoftware/amazon/awssdk/awscore/AwsRequest$Builder;
       5: pop
       6: aload_0
       7: areturn

  public software.amazon.awssdk.services.dynamodb.model.ExecuteTransactionRequest$Builder overrideConfiguration(java.util.function.Consumer<software.amazon.awssdk.awscore.AwsRequestOverrideConfiguration$Builder>);
    Code:
       0: aload_0
       1: aload_1
       2: invokespecial #28                 // Method software/amazon/awssdk/services/dynamodb/model/DynamoDbRequest$BuilderImpl.overrideConfiguration:(Ljava/util/function/Consumer;)Lsoftware/amazon/awssdk/awscore/AwsRequest$Builder;
       5: pop
       6: aload_0
       7: areturn

  public software.amazon.awssdk.services.dynamodb.model.ExecuteTransactionRequest build();
    Code:
       0: new           #29                 // class software/amazon/awssdk/services/dynamodb/model/ExecuteTransactionRequest
       3: dup
       4: aload_0
       5: aconst_null
       6: invokespecial #30                 // Method software/amazon/awssdk/services/dynamodb/model/ExecuteTransactionRequest."<init>":(Lsoftware/amazon/awssdk/services/dynamodb/model/ExecuteTransactionRequest$BuilderImpl;Lsoftware/amazon/awssdk/services/dynamodb/model/ExecuteTransactionRequest$1;)V
       9: areturn

  public java.util.List<software.amazon.awssdk.core.SdkField<?>> sdkFields();
    Code:
       0: invokestatic  #31                 // Method software/amazon/awssdk/services/dynamodb/model/ExecuteTransactionRequest.access$900:()Ljava/util/List;
       3: areturn

  public software.amazon.awssdk.services.dynamodb.model.DynamoDbRequest build();
    Code:
       0: aload_0
       1: invokevirtual #32                 // Method build:()Lsoftware/amazon/awssdk/services/dynamodb/model/ExecuteTransactionRequest;
       4: areturn

  public software.amazon.awssdk.awscore.AwsRequest build();
    Code:
       0: aload_0
       1: invokevirtual #32                 // Method build:()Lsoftware/amazon/awssdk/services/dynamodb/model/ExecuteTransactionRequest;
       4: areturn

  public software.amazon.awssdk.awscore.AwsRequest$Builder overrideConfiguration(java.util.function.Consumer);
    Code:
       0: aload_0
       1: aload_1
       2: invokevirtual #33                 // Method overrideConfiguration:(Ljava/util/function/Consumer;)Lsoftware/amazon/awssdk/services/dynamodb/model/ExecuteTransactionRequest$Builder;
       5: areturn

  public software.amazon.awssdk.awscore.AwsRequest$Builder overrideConfiguration(software.amazon.awssdk.awscore.AwsRequestOverrideConfiguration);
    Code:
       0: aload_0
       1: aload_1
       2: invokevirtual #34                 // Method overrideConfiguration:(Lsoftware/amazon/awssdk/awscore/AwsRequestOverrideConfiguration;)Lsoftware/amazon/awssdk/services/dynamodb/model/ExecuteTransactionRequest$Builder;
       5: areturn

  public software.amazon.awssdk.core.SdkRequest build();
    Code:
       0: aload_0
       1: invokevirtual #32                 // Method build:()Lsoftware/amazon/awssdk/services/dynamodb/model/ExecuteTransactionRequest;
       4: areturn

  public java.lang.Object build();
    Code:
       0: aload_0
       1: invokevirtual #32                 // Method build:()Lsoftware/amazon/awssdk/services/dynamodb/model/ExecuteTransactionRequest;
       4: areturn

  private static software.amazon.awssdk.services.dynamodb.model.ParameterizedStatement lambda$transactStatements$0(java.util.function.Consumer);
    Code:
       0: invokestatic  #35                 // Method software/amazon/awssdk/services/dynamodb/model/ParameterizedStatement.builder:()Lsoftware/amazon/awssdk/services/dynamodb/model/ParameterizedStatement$Builder;
       3: aload_0
       4: invokeinterface #36,  2           // InterfaceMethod software/amazon/awssdk/services/dynamodb/model/ParameterizedStatement$Builder.applyMutation:(Ljava/util/function/Consumer;)Lsoftware/amazon/awssdk/utils/builder/SdkBuilder;
       9: checkcast     #37                 // class software/amazon/awssdk/services/dynamodb/model/ParameterizedStatement$Builder
      12: invokeinterface #38,  1           // InterfaceMethod software/amazon/awssdk/services/dynamodb/model/ParameterizedStatement$Builder.build:()Ljava/lang/Object;
      17: checkcast     #39                 // class software/amazon/awssdk/services/dynamodb/model/ParameterizedStatement
      20: areturn

  static java.util.List access$000(software.amazon.awssdk.services.dynamodb.model.ExecuteTransactionRequest$BuilderImpl);
    Code:
       0: aload_0
       1: getfield      #5                  // Field transactStatements:Ljava/util/List;
       4: areturn

  static java.lang.String access$100(software.amazon.awssdk.services.dynamodb.model.ExecuteTransactionRequest$BuilderImpl);
    Code:
       0: aload_0
       1: getfield      #4                  // Field clientRequestToken:Ljava/lang/String;
       4: areturn

  static java.lang.String access$200(software.amazon.awssdk.services.dynamodb.model.ExecuteTransactionRequest$BuilderImpl);
    Code:
       0: aload_0
       1: getfield      #3                  // Field returnConsumedCapacity:Ljava/lang/String;
       4: areturn

  software.amazon.awssdk.services.dynamodb.model.ExecuteTransactionRequest$BuilderImpl(software.amazon.awssdk.services.dynamodb.model.ExecuteTransactionRequest, software.amazon.awssdk.services.dynamodb.model.ExecuteTransactionRequest$1);
    Code:
       0: aload_0
       1: aload_1
       2: invokespecial #2                  // Method "<init>":(Lsoftware/amazon/awssdk/services/dynamodb/model/ExecuteTransactionRequest;)V
       5: return

  software.amazon.awssdk.services.dynamodb.model.ExecuteTransactionRequest$BuilderImpl(software.amazon.awssdk.services.dynamodb.model.ExecuteTransactionRequest$1);
    Code:
       0: aload_0
       1: invokespecial #1                  // Method "<init>":()V
       4: return
}
