Compiled from "GlobalSecondaryIndexInfo.java"
public interface software.amazon.awssdk.services.dynamodb.model.GlobalSecondaryIndexInfo$Builder extends software.amazon.awssdk.core.SdkPojo, software.amazon.awssdk.utils.builder.CopyableBuilder<software.amazon.awssdk.services.dynamodb.model.GlobalSecondaryIndexInfo$Builder, software.amazon.awssdk.services.dynamodb.model.GlobalSecondaryIndexInfo> {
  public abstract software.amazon.awssdk.services.dynamodb.model.GlobalSecondaryIndexInfo$Builder indexName(java.lang.String);

  public abstract software.amazon.awssdk.services.dynamodb.model.GlobalSecondaryIndexInfo$Builder keySchema(java.util.Collection<software.amazon.awssdk.services.dynamodb.model.KeySchemaElement>);

  public abstract software.amazon.awssdk.services.dynamodb.model.GlobalSecondaryIndexInfo$Builder keySchema(software.amazon.awssdk.services.dynamodb.model.KeySchemaElement...);

  public abstract software.amazon.awssdk.services.dynamodb.model.GlobalSecondaryIndexInfo$Builder keySchema(java.util.function.Consumer<software.amazon.awssdk.services.dynamodb.model.KeySchemaElement$Builder>...);

  public abstract software.amazon.awssdk.services.dynamodb.model.GlobalSecondaryIndexInfo$Builder projection(software.amazon.awssdk.services.dynamodb.model.Projection);

  public default software.amazon.awssdk.services.dynamodb.model.GlobalSecondaryIndexInfo$Builder projection(java.util.function.Consumer<software.amazon.awssdk.services.dynamodb.model.Projection$Builder>);
    Code:
       0: aload_0
       1: invokestatic  #1                  // Method software/amazon/awssdk/services/dynamodb/model/Projection.builder:()Lsoftware/amazon/awssdk/services/dynamodb/model/Projection$Builder;
       4: aload_1
       5: invokeinterface #2,  2            // InterfaceMethod software/amazon/awssdk/services/dynamodb/model/Projection$Builder.applyMutation:(Ljava/util/function/Consumer;)Lsoftware/amazon/awssdk/utils/builder/SdkBuilder;
      10: checkcast     #3                  // class software/amazon/awssdk/services/dynamodb/model/Projection$Builder
      13: invokeinterface #4,  1            // InterfaceMethod software/amazon/awssdk/services/dynamodb/model/Projection$Builder.build:()Ljava/lang/Object;
      18: checkcast     #5                  // class software/amazon/awssdk/services/dynamodb/model/Projection
      21: invokeinterface #6,  2            // InterfaceMethod projection:(Lsoftware/amazon/awssdk/services/dynamodb/model/Projection;)Lsoftware/amazon/awssdk/services/dynamodb/model/GlobalSecondaryIndexInfo$Builder;
      26: areturn

  public abstract software.amazon.awssdk.services.dynamodb.model.GlobalSecondaryIndexInfo$Builder provisionedThroughput(software.amazon.awssdk.services.dynamodb.model.ProvisionedThroughput);

  public default software.amazon.awssdk.services.dynamodb.model.GlobalSecondaryIndexInfo$Builder provisionedThroughput(java.util.function.Consumer<software.amazon.awssdk.services.dynamodb.model.ProvisionedThroughput$Builder>);
    Code:
       0: aload_0
       1: invokestatic  #7                  // Method software/amazon/awssdk/services/dynamodb/model/ProvisionedThroughput.builder:()Lsoftware/amazon/awssdk/services/dynamodb/model/ProvisionedThroughput$Builder;
       4: aload_1
       5: invokeinterface #8,  2            // InterfaceMethod software/amazon/awssdk/services/dynamodb/model/ProvisionedThroughput$Builder.applyMutation:(Ljava/util/function/Consumer;)Lsoftware/amazon/awssdk/utils/builder/SdkBuilder;
      10: checkcast     #9                  // class software/amazon/awssdk/services/dynamodb/model/ProvisionedThroughput$Builder
      13: invokeinterface #10,  1           // InterfaceMethod software/amazon/awssdk/services/dynamodb/model/ProvisionedThroughput$Builder.build:()Ljava/lang/Object;
      18: checkcast     #11                 // class software/amazon/awssdk/services/dynamodb/model/ProvisionedThroughput
      21: invokeinterface #12,  2           // InterfaceMethod provisionedThroughput:(Lsoftware/amazon/awssdk/services/dynamodb/model/ProvisionedThroughput;)Lsoftware/amazon/awssdk/services/dynamodb/model/GlobalSecondaryIndexInfo$Builder;
      26: areturn
}
