Compiled from "ImportTableDescription.java"
final class software.amazon.awssdk.services.dynamodb.model.ImportTableDescription$BuilderImpl implements software.amazon.awssdk.services.dynamodb.model.ImportTableDescription$Builder {
  private java.lang.String importArn;

  private java.lang.String importStatus;

  private java.lang.String tableArn;

  private java.lang.String tableId;

  private java.lang.String clientToken;

  private software.amazon.awssdk.services.dynamodb.model.S3BucketSource s3BucketSource;

  private java.lang.Long errorCount;

  private java.lang.String cloudWatchLogGroupArn;

  private java.lang.String inputFormat;

  private software.amazon.awssdk.services.dynamodb.model.InputFormatOptions inputFormatOptions;

  private java.lang.String inputCompressionType;

  private software.amazon.awssdk.services.dynamodb.model.TableCreationParameters tableCreationParameters;

  private java.time.Instant startTime;

  private java.time.Instant endTime;

  private java.lang.Long processedSizeBytes;

  private java.lang.Long processedItemCount;

  private java.lang.Long importedItemCount;

  private java.lang.String failureCode;

  private java.lang.String failureMessage;

  private software.amazon.awssdk.services.dynamodb.model.ImportTableDescription$BuilderImpl();
    Code:
       0: aload_0
       1: invokespecial #22                 // Method java/lang/Object."<init>":()V
       4: return

  private software.amazon.awssdk.services.dynamodb.model.ImportTableDescription$BuilderImpl(software.amazon.awssdk.services.dynamodb.model.ImportTableDescription);
    Code:
       0: aload_0
       1: invokespecial #22                 // Method java/lang/Object."<init>":()V
       4: aload_0
       5: aload_1
       6: invokestatic  #23                 // Method software/amazon/awssdk/services/dynamodb/model/ImportTableDescription.access$2100:(Lsoftware/amazon/awssdk/services/dynamodb/model/ImportTableDescription;)Ljava/lang/String;
       9: invokevirtual #24                 // Method importArn:(Ljava/lang/String;)Lsoftware/amazon/awssdk/services/dynamodb/model/ImportTableDescription$Builder;
      12: pop
      13: aload_0
      14: aload_1
      15: invokestatic  #25                 // Method software/amazon/awssdk/services/dynamodb/model/ImportTableDescription.access$2200:(Lsoftware/amazon/awssdk/services/dynamodb/model/ImportTableDescription;)Ljava/lang/String;
      18: invokevirtual #26                 // Method importStatus:(Ljava/lang/String;)Lsoftware/amazon/awssdk/services/dynamodb/model/ImportTableDescription$Builder;
      21: pop
      22: aload_0
      23: aload_1
      24: invokestatic  #27                 // Method software/amazon/awssdk/services/dynamodb/model/ImportTableDescription.access$2300:(Lsoftware/amazon/awssdk/services/dynamodb/model/ImportTableDescription;)Ljava/lang/String;
      27: invokevirtual #28                 // Method tableArn:(Ljava/lang/String;)Lsoftware/amazon/awssdk/services/dynamodb/model/ImportTableDescription$Builder;
      30: pop
      31: aload_0
      32: aload_1
      33: invokestatic  #29                 // Method software/amazon/awssdk/services/dynamodb/model/ImportTableDescription.access$2400:(Lsoftware/amazon/awssdk/services/dynamodb/model/ImportTableDescription;)Ljava/lang/String;
      36: invokevirtual #30                 // Method tableId:(Ljava/lang/String;)Lsoftware/amazon/awssdk/services/dynamodb/model/ImportTableDescription$Builder;
      39: pop
      40: aload_0
      41: aload_1
      42: invokestatic  #31                 // Method software/amazon/awssdk/services/dynamodb/model/ImportTableDescription.access$2500:(Lsoftware/amazon/awssdk/services/dynamodb/model/ImportTableDescription;)Ljava/lang/String;
      45: invokevirtual #32                 // Method clientToken:(Ljava/lang/String;)Lsoftware/amazon/awssdk/services/dynamodb/model/ImportTableDescription$Builder;
      48: pop
      49: aload_0
      50: aload_1
      51: invokestatic  #33                 // Method software/amazon/awssdk/services/dynamodb/model/ImportTableDescription.access$2600:(Lsoftware/amazon/awssdk/services/dynamodb/model/ImportTableDescription;)Lsoftware/amazon/awssdk/services/dynamodb/model/S3BucketSource;
      54: invokevirtual #34                 // Method s3BucketSource:(Lsoftware/amazon/awssdk/services/dynamodb/model/S3BucketSource;)Lsoftware/amazon/awssdk/services/dynamodb/model/ImportTableDescription$Builder;
      57: pop
      58: aload_0
      59: aload_1
      60: invokestatic  #35                 // Method software/amazon/awssdk/services/dynamodb/model/ImportTableDescription.access$2700:(Lsoftware/amazon/awssdk/services/dynamodb/model/ImportTableDescription;)Ljava/lang/Long;
      63: invokevirtual #36                 // Method errorCount:(Ljava/lang/Long;)Lsoftware/amazon/awssdk/services/dynamodb/model/ImportTableDescription$Builder;
      66: pop
      67: aload_0
      68: aload_1
      69: invokestatic  #37                 // Method software/amazon/awssdk/services/dynamodb/model/ImportTableDescription.access$2800:(Lsoftware/amazon/awssdk/services/dynamodb/model/ImportTableDescription;)Ljava/lang/String;
      72: invokevirtual #38                 // Method cloudWatchLogGroupArn:(Ljava/lang/String;)Lsoftware/amazon/awssdk/services/dynamodb/model/ImportTableDescription$Builder;
      75: pop
      76: aload_0
      77: aload_1
      78: invokestatic  #39                 // Method software/amazon/awssdk/services/dynamodb/model/ImportTableDescription.access$2900:(Lsoftware/amazon/awssdk/services/dynamodb/model/ImportTableDescription;)Ljava/lang/String;
      81: invokevirtual #40                 // Method inputFormat:(Ljava/lang/String;)Lsoftware/amazon/awssdk/services/dynamodb/model/ImportTableDescription$Builder;
      84: pop
      85: aload_0
      86: aload_1
      87: invokestatic  #41                 // Method software/amazon/awssdk/services/dynamodb/model/ImportTableDescription.access$3000:(Lsoftware/amazon/awssdk/services/dynamodb/model/ImportTableDescription;)Lsoftware/amazon/awssdk/services/dynamodb/model/InputFormatOptions;
      90: invokevirtual #42                 // Method inputFormatOptions:(Lsoftware/amazon/awssdk/services/dynamodb/model/InputFormatOptions;)Lsoftware/amazon/awssdk/services/dynamodb/model/ImportTableDescription$Builder;
      93: pop
      94: aload_0
      95: aload_1
      96: invokestatic  #43                 // Method software/amazon/awssdk/services/dynamodb/model/ImportTableDescription.access$3100:(Lsoftware/amazon/awssdk/services/dynamodb/model/ImportTableDescription;)Ljava/lang/String;
      99: invokevirtual #44                 // Method inputCompressionType:(Ljava/lang/String;)Lsoftware/amazon/awssdk/services/dynamodb/model/ImportTableDescription$Builder;
     102: pop
     103: aload_0
     104: aload_1
     105: invokestatic  #45                 // Method software/amazon/awssdk/services/dynamodb/model/ImportTableDescription.access$3200:(Lsoftware/amazon/awssdk/services/dynamodb/model/ImportTableDescription;)Lsoftware/amazon/awssdk/services/dynamodb/model/TableCreationParameters;
     108: invokevirtual #46                 // Method tableCreationParameters:(Lsoftware/amazon/awssdk/services/dynamodb/model/TableCreationParameters;)Lsoftware/amazon/awssdk/services/dynamodb/model/ImportTableDescription$Builder;
     111: pop
     112: aload_0
     113: aload_1
     114: invokestatic  #47                 // Method software/amazon/awssdk/services/dynamodb/model/ImportTableDescription.access$3300:(Lsoftware/amazon/awssdk/services/dynamodb/model/ImportTableDescription;)Ljava/time/Instant;
     117: invokevirtual #48                 // Method startTime:(Ljava/time/Instant;)Lsoftware/amazon/awssdk/services/dynamodb/model/ImportTableDescription$Builder;
     120: pop
     121: aload_0
     122: aload_1
     123: invokestatic  #49                 // Method software/amazon/awssdk/services/dynamodb/model/ImportTableDescription.access$3400:(Lsoftware/amazon/awssdk/services/dynamodb/model/ImportTableDescription;)Ljava/time/Instant;
     126: invokevirtual #50                 // Method endTime:(Ljava/time/Instant;)Lsoftware/amazon/awssdk/services/dynamodb/model/ImportTableDescription$Builder;
     129: pop
     130: aload_0
     131: aload_1
     132: invokestatic  #51                 // Method software/amazon/awssdk/services/dynamodb/model/ImportTableDescription.access$3500:(Lsoftware/amazon/awssdk/services/dynamodb/model/ImportTableDescription;)Ljava/lang/Long;
     135: invokevirtual #52                 // Method processedSizeBytes:(Ljava/lang/Long;)Lsoftware/amazon/awssdk/services/dynamodb/model/ImportTableDescription$Builder;
     138: pop
     139: aload_0
     140: aload_1
     141: invokestatic  #53                 // Method software/amazon/awssdk/services/dynamodb/model/ImportTableDescription.access$3600:(Lsoftware/amazon/awssdk/services/dynamodb/model/ImportTableDescription;)Ljava/lang/Long;
     144: invokevirtual #54                 // Method processedItemCount:(Ljava/lang/Long;)Lsoftware/amazon/awssdk/services/dynamodb/model/ImportTableDescription$Builder;
     147: pop
     148: aload_0
     149: aload_1
     150: invokestatic  #55                 // Method software/amazon/awssdk/services/dynamodb/model/ImportTableDescription.access$3700:(Lsoftware/amazon/awssdk/services/dynamodb/model/ImportTableDescription;)Ljava/lang/Long;
     153: invokevirtual #56                 // Method importedItemCount:(Ljava/lang/Long;)Lsoftware/amazon/awssdk/services/dynamodb/model/ImportTableDescription$Builder;
     156: pop
     157: aload_0
     158: aload_1
     159: invokestatic  #57                 // Method software/amazon/awssdk/services/dynamodb/model/ImportTableDescription.access$3800:(Lsoftware/amazon/awssdk/services/dynamodb/model/ImportTableDescription;)Ljava/lang/String;
     162: invokevirtual #58                 // Method failureCode:(Ljava/lang/String;)Lsoftware/amazon/awssdk/services/dynamodb/model/ImportTableDescription$Builder;
     165: pop
     166: aload_0
     167: aload_1
     168: invokestatic  #59                 // Method software/amazon/awssdk/services/dynamodb/model/ImportTableDescription.access$3900:(Lsoftware/amazon/awssdk/services/dynamodb/model/ImportTableDescription;)Ljava/lang/String;
     171: invokevirtual #60                 // Method failureMessage:(Ljava/lang/String;)Lsoftware/amazon/awssdk/services/dynamodb/model/ImportTableDescription$Builder;
     174: pop
     175: return

  public final java.lang.String getImportArn();
    Code:
       0: aload_0
       1: getfield      #21                 // Field importArn:Ljava/lang/String;
       4: areturn

  public final void setImportArn(java.lang.String);
    Code:
       0: aload_0
       1: aload_1
       2: putfield      #21                 // Field importArn:Ljava/lang/String;
       5: return

  public final software.amazon.awssdk.services.dynamodb.model.ImportTableDescription$Builder importArn(java.lang.String);
    Code:
       0: aload_0
       1: aload_1
       2: putfield      #21                 // Field importArn:Ljava/lang/String;
       5: aload_0
       6: areturn

  public final java.lang.String getImportStatus();
    Code:
       0: aload_0
       1: getfield      #20                 // Field importStatus:Ljava/lang/String;
       4: areturn

  public final void setImportStatus(java.lang.String);
    Code:
       0: aload_0
       1: aload_1
       2: putfield      #20                 // Field importStatus:Ljava/lang/String;
       5: return

  public final software.amazon.awssdk.services.dynamodb.model.ImportTableDescription$Builder importStatus(java.lang.String);
    Code:
       0: aload_0
       1: aload_1
       2: putfield      #20                 // Field importStatus:Ljava/lang/String;
       5: aload_0
       6: areturn

  public final software.amazon.awssdk.services.dynamodb.model.ImportTableDescription$Builder importStatus(software.amazon.awssdk.services.dynamodb.model.ImportStatus);
    Code:
       0: aload_0
       1: aload_1
       2: ifnonnull     9
       5: aconst_null
       6: goto          13
       9: aload_1
      10: invokevirtual #61                 // Method software/amazon/awssdk/services/dynamodb/model/ImportStatus.toString:()Ljava/lang/String;
      13: invokevirtual #26                 // Method importStatus:(Ljava/lang/String;)Lsoftware/amazon/awssdk/services/dynamodb/model/ImportTableDescription$Builder;
      16: pop
      17: aload_0
      18: areturn

  public final java.lang.String getTableArn();
    Code:
       0: aload_0
       1: getfield      #19                 // Field tableArn:Ljava/lang/String;
       4: areturn

  public final void setTableArn(java.lang.String);
    Code:
       0: aload_0
       1: aload_1
       2: putfield      #19                 // Field tableArn:Ljava/lang/String;
       5: return

  public final software.amazon.awssdk.services.dynamodb.model.ImportTableDescription$Builder tableArn(java.lang.String);
    Code:
       0: aload_0
       1: aload_1
       2: putfield      #19                 // Field tableArn:Ljava/lang/String;
       5: aload_0
       6: areturn

  public final java.lang.String getTableId();
    Code:
       0: aload_0
       1: getfield      #18                 // Field tableId:Ljava/lang/String;
       4: areturn

  public final void setTableId(java.lang.String);
    Code:
       0: aload_0
       1: aload_1
       2: putfield      #18                 // Field tableId:Ljava/lang/String;
       5: return

  public final software.amazon.awssdk.services.dynamodb.model.ImportTableDescription$Builder tableId(java.lang.String);
    Code:
       0: aload_0
       1: aload_1
       2: putfield      #18                 // Field tableId:Ljava/lang/String;
       5: aload_0
       6: areturn

  public final java.lang.String getClientToken();
    Code:
       0: aload_0
       1: getfield      #17                 // Field clientToken:Ljava/lang/String;
       4: areturn

  public final void setClientToken(java.lang.String);
    Code:
       0: aload_0
       1: aload_1
       2: putfield      #17                 // Field clientToken:Ljava/lang/String;
       5: return

  public final software.amazon.awssdk.services.dynamodb.model.ImportTableDescription$Builder clientToken(java.lang.String);
    Code:
       0: aload_0
       1: aload_1
       2: putfield      #17                 // Field clientToken:Ljava/lang/String;
       5: aload_0
       6: areturn

  public final software.amazon.awssdk.services.dynamodb.model.S3BucketSource$Builder getS3BucketSource();
    Code:
       0: aload_0
       1: getfield      #16                 // Field s3BucketSource:Lsoftware/amazon/awssdk/services/dynamodb/model/S3BucketSource;
       4: ifnull        17
       7: aload_0
       8: getfield      #16                 // Field s3BucketSource:Lsoftware/amazon/awssdk/services/dynamodb/model/S3BucketSource;
      11: invokevirtual #62                 // Method software/amazon/awssdk/services/dynamodb/model/S3BucketSource.toBuilder:()Lsoftware/amazon/awssdk/services/dynamodb/model/S3BucketSource$Builder;
      14: goto          18
      17: aconst_null
      18: areturn

  public final void setS3BucketSource(software.amazon.awssdk.services.dynamodb.model.S3BucketSource$BuilderImpl);
    Code:
       0: aload_0
       1: aload_1
       2: ifnull        12
       5: aload_1
       6: invokevirtual #63                 // Method software/amazon/awssdk/services/dynamodb/model/S3BucketSource$BuilderImpl.build:()Lsoftware/amazon/awssdk/services/dynamodb/model/S3BucketSource;
       9: goto          13
      12: aconst_null
      13: putfield      #16                 // Field s3BucketSource:Lsoftware/amazon/awssdk/services/dynamodb/model/S3BucketSource;
      16: return

  public final software.amazon.awssdk.services.dynamodb.model.ImportTableDescription$Builder s3BucketSource(software.amazon.awssdk.services.dynamodb.model.S3BucketSource);
    Code:
       0: aload_0
       1: aload_1
       2: putfield      #16                 // Field s3BucketSource:Lsoftware/amazon/awssdk/services/dynamodb/model/S3BucketSource;
       5: aload_0
       6: areturn

  public final java.lang.Long getErrorCount();
    Code:
       0: aload_0
       1: getfield      #15                 // Field errorCount:Ljava/lang/Long;
       4: areturn

  public final void setErrorCount(java.lang.Long);
    Code:
       0: aload_0
       1: aload_1
       2: putfield      #15                 // Field errorCount:Ljava/lang/Long;
       5: return

  public final software.amazon.awssdk.services.dynamodb.model.ImportTableDescription$Builder errorCount(java.lang.Long);
    Code:
       0: aload_0
       1: aload_1
       2: putfield      #15                 // Field errorCount:Ljava/lang/Long;
       5: aload_0
       6: areturn

  public final java.lang.String getCloudWatchLogGroupArn();
    Code:
       0: aload_0
       1: getfield      #14                 // Field cloudWatchLogGroupArn:Ljava/lang/String;
       4: areturn

  public final void setCloudWatchLogGroupArn(java.lang.String);
    Code:
       0: aload_0
       1: aload_1
       2: putfield      #14                 // Field cloudWatchLogGroupArn:Ljava/lang/String;
       5: return

  public final software.amazon.awssdk.services.dynamodb.model.ImportTableDescription$Builder cloudWatchLogGroupArn(java.lang.String);
    Code:
       0: aload_0
       1: aload_1
       2: putfield      #14                 // Field cloudWatchLogGroupArn:Ljava/lang/String;
       5: aload_0
       6: areturn

  public final java.lang.String getInputFormat();
    Code:
       0: aload_0
       1: getfield      #13                 // Field inputFormat:Ljava/lang/String;
       4: areturn

  public final void setInputFormat(java.lang.String);
    Code:
       0: aload_0
       1: aload_1
       2: putfield      #13                 // Field inputFormat:Ljava/lang/String;
       5: return

  public final software.amazon.awssdk.services.dynamodb.model.ImportTableDescription$Builder inputFormat(java.lang.String);
    Code:
       0: aload_0
       1: aload_1
       2: putfield      #13                 // Field inputFormat:Ljava/lang/String;
       5: aload_0
       6: areturn

  public final software.amazon.awssdk.services.dynamodb.model.ImportTableDescription$Builder inputFormat(software.amazon.awssdk.services.dynamodb.model.InputFormat);
    Code:
       0: aload_0
       1: aload_1
       2: ifnonnull     9
       5: aconst_null
       6: goto          13
       9: aload_1
      10: invokevirtual #64                 // Method software/amazon/awssdk/services/dynamodb/model/InputFormat.toString:()Ljava/lang/String;
      13: invokevirtual #40                 // Method inputFormat:(Ljava/lang/String;)Lsoftware/amazon/awssdk/services/dynamodb/model/ImportTableDescription$Builder;
      16: pop
      17: aload_0
      18: areturn

  public final software.amazon.awssdk.services.dynamodb.model.InputFormatOptions$Builder getInputFormatOptions();
    Code:
       0: aload_0
       1: getfield      #12                 // Field inputFormatOptions:Lsoftware/amazon/awssdk/services/dynamodb/model/InputFormatOptions;
       4: ifnull        17
       7: aload_0
       8: getfield      #12                 // Field inputFormatOptions:Lsoftware/amazon/awssdk/services/dynamodb/model/InputFormatOptions;
      11: invokevirtual #65                 // Method software/amazon/awssdk/services/dynamodb/model/InputFormatOptions.toBuilder:()Lsoftware/amazon/awssdk/services/dynamodb/model/InputFormatOptions$Builder;
      14: goto          18
      17: aconst_null
      18: areturn

  public final void setInputFormatOptions(software.amazon.awssdk.services.dynamodb.model.InputFormatOptions$BuilderImpl);
    Code:
       0: aload_0
       1: aload_1
       2: ifnull        12
       5: aload_1
       6: invokevirtual #66                 // Method software/amazon/awssdk/services/dynamodb/model/InputFormatOptions$BuilderImpl.build:()Lsoftware/amazon/awssdk/services/dynamodb/model/InputFormatOptions;
       9: goto          13
      12: aconst_null
      13: putfield      #12                 // Field inputFormatOptions:Lsoftware/amazon/awssdk/services/dynamodb/model/InputFormatOptions;
      16: return

  public final software.amazon.awssdk.services.dynamodb.model.ImportTableDescription$Builder inputFormatOptions(software.amazon.awssdk.services.dynamodb.model.InputFormatOptions);
    Code:
       0: aload_0
       1: aload_1
       2: putfield      #12                 // Field inputFormatOptions:Lsoftware/amazon/awssdk/services/dynamodb/model/InputFormatOptions;
       5: aload_0
       6: areturn

  public final java.lang.String getInputCompressionType();
    Code:
       0: aload_0
       1: getfield      #11                 // Field inputCompressionType:Ljava/lang/String;
       4: areturn

  public final void setInputCompressionType(java.lang.String);
    Code:
       0: aload_0
       1: aload_1
       2: putfield      #11                 // Field inputCompressionType:Ljava/lang/String;
       5: return

  public final software.amazon.awssdk.services.dynamodb.model.ImportTableDescription$Builder inputCompressionType(java.lang.String);
    Code:
       0: aload_0
       1: aload_1
       2: putfield      #11                 // Field inputCompressionType:Ljava/lang/String;
       5: aload_0
       6: areturn

  public final software.amazon.awssdk.services.dynamodb.model.ImportTableDescription$Builder inputCompressionType(software.amazon.awssdk.services.dynamodb.model.InputCompressionType);
    Code:
       0: aload_0
       1: aload_1
       2: ifnonnull     9
       5: aconst_null
       6: goto          13
       9: aload_1
      10: invokevirtual #67                 // Method software/amazon/awssdk/services/dynamodb/model/InputCompressionType.toString:()Ljava/lang/String;
      13: invokevirtual #44                 // Method inputCompressionType:(Ljava/lang/String;)Lsoftware/amazon/awssdk/services/dynamodb/model/ImportTableDescription$Builder;
      16: pop
      17: aload_0
      18: areturn

  public final software.amazon.awssdk.services.dynamodb.model.TableCreationParameters$Builder getTableCreationParameters();
    Code:
       0: aload_0
       1: getfield      #10                 // Field tableCreationParameters:Lsoftware/amazon/awssdk/services/dynamodb/model/TableCreationParameters;
       4: ifnull        17
       7: aload_0
       8: getfield      #10                 // Field tableCreationParameters:Lsoftware/amazon/awssdk/services/dynamodb/model/TableCreationParameters;
      11: invokevirtual #68                 // Method software/amazon/awssdk/services/dynamodb/model/TableCreationParameters.toBuilder:()Lsoftware/amazon/awssdk/services/dynamodb/model/TableCreationParameters$Builder;
      14: goto          18
      17: aconst_null
      18: areturn

  public final void setTableCreationParameters(software.amazon.awssdk.services.dynamodb.model.TableCreationParameters$BuilderImpl);
    Code:
       0: aload_0
       1: aload_1
       2: ifnull        12
       5: aload_1
       6: invokevirtual #69                 // Method software/amazon/awssdk/services/dynamodb/model/TableCreationParameters$BuilderImpl.build:()Lsoftware/amazon/awssdk/services/dynamodb/model/TableCreationParameters;
       9: goto          13
      12: aconst_null
      13: putfield      #10                 // Field tableCreationParameters:Lsoftware/amazon/awssdk/services/dynamodb/model/TableCreationParameters;
      16: return

  public final software.amazon.awssdk.services.dynamodb.model.ImportTableDescription$Builder tableCreationParameters(software.amazon.awssdk.services.dynamodb.model.TableCreationParameters);
    Code:
       0: aload_0
       1: aload_1
       2: putfield      #10                 // Field tableCreationParameters:Lsoftware/amazon/awssdk/services/dynamodb/model/TableCreationParameters;
       5: aload_0
       6: areturn

  public final java.time.Instant getStartTime();
    Code:
       0: aload_0
       1: getfield      #9                  // Field startTime:Ljava/time/Instant;
       4: areturn

  public final void setStartTime(java.time.Instant);
    Code:
       0: aload_0
       1: aload_1
       2: putfield      #9                  // Field startTime:Ljava/time/Instant;
       5: return

  public final software.amazon.awssdk.services.dynamodb.model.ImportTableDescription$Builder startTime(java.time.Instant);
    Code:
       0: aload_0
       1: aload_1
       2: putfield      #9                  // Field startTime:Ljava/time/Instant;
       5: aload_0
       6: areturn

  public final java.time.Instant getEndTime();
    Code:
       0: aload_0
       1: getfield      #8                  // Field endTime:Ljava/time/Instant;
       4: areturn

  public final void setEndTime(java.time.Instant);
    Code:
       0: aload_0
       1: aload_1
       2: putfield      #8                  // Field endTime:Ljava/time/Instant;
       5: return

  public final software.amazon.awssdk.services.dynamodb.model.ImportTableDescription$Builder endTime(java.time.Instant);
    Code:
       0: aload_0
       1: aload_1
       2: putfield      #8                  // Field endTime:Ljava/time/Instant;
       5: aload_0
       6: areturn

  public final java.lang.Long getProcessedSizeBytes();
    Code:
       0: aload_0
       1: getfield      #7                  // Field processedSizeBytes:Ljava/lang/Long;
       4: areturn

  public final void setProcessedSizeBytes(java.lang.Long);
    Code:
       0: aload_0
       1: aload_1
       2: putfield      #7                  // Field processedSizeBytes:Ljava/lang/Long;
       5: return

  public final software.amazon.awssdk.services.dynamodb.model.ImportTableDescription$Builder processedSizeBytes(java.lang.Long);
    Code:
       0: aload_0
       1: aload_1
       2: putfield      #7                  // Field processedSizeBytes:Ljava/lang/Long;
       5: aload_0
       6: areturn

  public final java.lang.Long getProcessedItemCount();
    Code:
       0: aload_0
       1: getfield      #6                  // Field processedItemCount:Ljava/lang/Long;
       4: areturn

  public final void setProcessedItemCount(java.lang.Long);
    Code:
       0: aload_0
       1: aload_1
       2: putfield      #6                  // Field processedItemCount:Ljava/lang/Long;
       5: return

  public final software.amazon.awssdk.services.dynamodb.model.ImportTableDescription$Builder processedItemCount(java.lang.Long);
    Code:
       0: aload_0
       1: aload_1
       2: putfield      #6                  // Field processedItemCount:Ljava/lang/Long;
       5: aload_0
       6: areturn

  public final java.lang.Long getImportedItemCount();
    Code:
       0: aload_0
       1: getfield      #5                  // Field importedItemCount:Ljava/lang/Long;
       4: areturn

  public final void setImportedItemCount(java.lang.Long);
    Code:
       0: aload_0
       1: aload_1
       2: putfield      #5                  // Field importedItemCount:Ljava/lang/Long;
       5: return

  public final software.amazon.awssdk.services.dynamodb.model.ImportTableDescription$Builder importedItemCount(java.lang.Long);
    Code:
       0: aload_0
       1: aload_1
       2: putfield      #5                  // Field importedItemCount:Ljava/lang/Long;
       5: aload_0
       6: areturn

  public final java.lang.String getFailureCode();
    Code:
       0: aload_0
       1: getfield      #4                  // Field failureCode:Ljava/lang/String;
       4: areturn

  public final void setFailureCode(java.lang.String);
    Code:
       0: aload_0
       1: aload_1
       2: putfield      #4                  // Field failureCode:Ljava/lang/String;
       5: return

  public final software.amazon.awssdk.services.dynamodb.model.ImportTableDescription$Builder failureCode(java.lang.String);
    Code:
       0: aload_0
       1: aload_1
       2: putfield      #4                  // Field failureCode:Ljava/lang/String;
       5: aload_0
       6: areturn

  public final java.lang.String getFailureMessage();
    Code:
       0: aload_0
       1: getfield      #3                  // Field failureMessage:Ljava/lang/String;
       4: areturn

  public final void setFailureMessage(java.lang.String);
    Code:
       0: aload_0
       1: aload_1
       2: putfield      #3                  // Field failureMessage:Ljava/lang/String;
       5: return

  public final software.amazon.awssdk.services.dynamodb.model.ImportTableDescription$Builder failureMessage(java.lang.String);
    Code:
       0: aload_0
       1: aload_1
       2: putfield      #3                  // Field failureMessage:Ljava/lang/String;
       5: aload_0
       6: areturn

  public software.amazon.awssdk.services.dynamodb.model.ImportTableDescription build();
    Code:
       0: new           #70                 // class software/amazon/awssdk/services/dynamodb/model/ImportTableDescription
       3: dup
       4: aload_0
       5: aconst_null
       6: invokespecial #71                 // Method software/amazon/awssdk/services/dynamodb/model/ImportTableDescription."<init>":(Lsoftware/amazon/awssdk/services/dynamodb/model/ImportTableDescription$BuilderImpl;Lsoftware/amazon/awssdk/services/dynamodb/model/ImportTableDescription$1;)V
       9: areturn

  public java.util.List<software.amazon.awssdk.core.SdkField<?>> sdkFields();
    Code:
       0: invokestatic  #72                 // Method software/amazon/awssdk/services/dynamodb/model/ImportTableDescription.access$4100:()Ljava/util/List;
       3: areturn

  public java.lang.Object build();
    Code:
       0: aload_0
       1: invokevirtual #73                 // Method build:()Lsoftware/amazon/awssdk/services/dynamodb/model/ImportTableDescription;
       4: areturn

  static java.lang.String access$000(software.amazon.awssdk.services.dynamodb.model.ImportTableDescription$BuilderImpl);
    Code:
       0: aload_0
       1: getfield      #21                 // Field importArn:Ljava/lang/String;
       4: areturn

  static java.lang.String access$100(software.amazon.awssdk.services.dynamodb.model.ImportTableDescription$BuilderImpl);
    Code:
       0: aload_0
       1: getfield      #20                 // Field importStatus:Ljava/lang/String;
       4: areturn

  static java.lang.String access$200(software.amazon.awssdk.services.dynamodb.model.ImportTableDescription$BuilderImpl);
    Code:
       0: aload_0
       1: getfield      #19                 // Field tableArn:Ljava/lang/String;
       4: areturn

  static java.lang.String access$300(software.amazon.awssdk.services.dynamodb.model.ImportTableDescription$BuilderImpl);
    Code:
       0: aload_0
       1: getfield      #18                 // Field tableId:Ljava/lang/String;
       4: areturn

  static java.lang.String access$400(software.amazon.awssdk.services.dynamodb.model.ImportTableDescription$BuilderImpl);
    Code:
       0: aload_0
       1: getfield      #17                 // Field clientToken:Ljava/lang/String;
       4: areturn

  static software.amazon.awssdk.services.dynamodb.model.S3BucketSource access$500(software.amazon.awssdk.services.dynamodb.model.ImportTableDescription$BuilderImpl);
    Code:
       0: aload_0
       1: getfield      #16                 // Field s3BucketSource:Lsoftware/amazon/awssdk/services/dynamodb/model/S3BucketSource;
       4: areturn

  static java.lang.Long access$600(software.amazon.awssdk.services.dynamodb.model.ImportTableDescription$BuilderImpl);
    Code:
       0: aload_0
       1: getfield      #15                 // Field errorCount:Ljava/lang/Long;
       4: areturn

  static java.lang.String access$700(software.amazon.awssdk.services.dynamodb.model.ImportTableDescription$BuilderImpl);
    Code:
       0: aload_0
       1: getfield      #14                 // Field cloudWatchLogGroupArn:Ljava/lang/String;
       4: areturn

  static java.lang.String access$800(software.amazon.awssdk.services.dynamodb.model.ImportTableDescription$BuilderImpl);
    Code:
       0: aload_0
       1: getfield      #13                 // Field inputFormat:Ljava/lang/String;
       4: areturn

  static software.amazon.awssdk.services.dynamodb.model.InputFormatOptions access$900(software.amazon.awssdk.services.dynamodb.model.ImportTableDescription$BuilderImpl);
    Code:
       0: aload_0
       1: getfield      #12                 // Field inputFormatOptions:Lsoftware/amazon/awssdk/services/dynamodb/model/InputFormatOptions;
       4: areturn

  static java.lang.String access$1000(software.amazon.awssdk.services.dynamodb.model.ImportTableDescription$BuilderImpl);
    Code:
       0: aload_0
       1: getfield      #11                 // Field inputCompressionType:Ljava/lang/String;
       4: areturn

  static software.amazon.awssdk.services.dynamodb.model.TableCreationParameters access$1100(software.amazon.awssdk.services.dynamodb.model.ImportTableDescription$BuilderImpl);
    Code:
       0: aload_0
       1: getfield      #10                 // Field tableCreationParameters:Lsoftware/amazon/awssdk/services/dynamodb/model/TableCreationParameters;
       4: areturn

  static java.time.Instant access$1200(software.amazon.awssdk.services.dynamodb.model.ImportTableDescription$BuilderImpl);
    Code:
       0: aload_0
       1: getfield      #9                  // Field startTime:Ljava/time/Instant;
       4: areturn

  static java.time.Instant access$1300(software.amazon.awssdk.services.dynamodb.model.ImportTableDescription$BuilderImpl);
    Code:
       0: aload_0
       1: getfield      #8                  // Field endTime:Ljava/time/Instant;
       4: areturn

  static java.lang.Long access$1400(software.amazon.awssdk.services.dynamodb.model.ImportTableDescription$BuilderImpl);
    Code:
       0: aload_0
       1: getfield      #7                  // Field processedSizeBytes:Ljava/lang/Long;
       4: areturn

  static java.lang.Long access$1500(software.amazon.awssdk.services.dynamodb.model.ImportTableDescription$BuilderImpl);
    Code:
       0: aload_0
       1: getfield      #6                  // Field processedItemCount:Ljava/lang/Long;
       4: areturn

  static java.lang.Long access$1600(software.amazon.awssdk.services.dynamodb.model.ImportTableDescription$BuilderImpl);
    Code:
       0: aload_0
       1: getfield      #5                  // Field importedItemCount:Ljava/lang/Long;
       4: areturn

  static java.lang.String access$1700(software.amazon.awssdk.services.dynamodb.model.ImportTableDescription$BuilderImpl);
    Code:
       0: aload_0
       1: getfield      #4                  // Field failureCode:Ljava/lang/String;
       4: areturn

  static java.lang.String access$1800(software.amazon.awssdk.services.dynamodb.model.ImportTableDescription$BuilderImpl);
    Code:
       0: aload_0
       1: getfield      #3                  // Field failureMessage:Ljava/lang/String;
       4: areturn

  software.amazon.awssdk.services.dynamodb.model.ImportTableDescription$BuilderImpl(software.amazon.awssdk.services.dynamodb.model.ImportTableDescription, software.amazon.awssdk.services.dynamodb.model.ImportTableDescription$1);
    Code:
       0: aload_0
       1: aload_1
       2: invokespecial #2                  // Method "<init>":(Lsoftware/amazon/awssdk/services/dynamodb/model/ImportTableDescription;)V
       5: return

  software.amazon.awssdk.services.dynamodb.model.ImportTableDescription$BuilderImpl(software.amazon.awssdk.services.dynamodb.model.ImportTableDescription$1);
    Code:
       0: aload_0
       1: invokespecial #1                  // Method "<init>":()V
       4: return
}
