Compiled from "ImportTableDescription.java"
public final class software.amazon.awssdk.services.dynamodb.model.ImportTableDescription implements software.amazon.awssdk.core.SdkPojo, java.io.Serializable, software.amazon.awssdk.utils.builder.ToCopyableBuilder<software.amazon.awssdk.services.dynamodb.model.ImportTableDescription$Builder, software.amazon.awssdk.services.dynamodb.model.ImportTableDescription> {
  private static final software.amazon.awssdk.core.SdkField<java.lang.String> IMPORT_ARN_FIELD;

  private static final software.amazon.awssdk.core.SdkField<java.lang.String> IMPORT_STATUS_FIELD;

  private static final software.amazon.awssdk.core.SdkField<java.lang.String> TABLE_ARN_FIELD;

  private static final software.amazon.awssdk.core.SdkField<java.lang.String> TABLE_ID_FIELD;

  private static final software.amazon.awssdk.core.SdkField<java.lang.String> CLIENT_TOKEN_FIELD;

  private static final software.amazon.awssdk.core.SdkField<software.amazon.awssdk.services.dynamodb.model.S3BucketSource> S3_BUCKET_SOURCE_FIELD;

  private static final software.amazon.awssdk.core.SdkField<java.lang.Long> ERROR_COUNT_FIELD;

  private static final software.amazon.awssdk.core.SdkField<java.lang.String> CLOUD_WATCH_LOG_GROUP_ARN_FIELD;

  private static final software.amazon.awssdk.core.SdkField<java.lang.String> INPUT_FORMAT_FIELD;

  private static final software.amazon.awssdk.core.SdkField<software.amazon.awssdk.services.dynamodb.model.InputFormatOptions> INPUT_FORMAT_OPTIONS_FIELD;

  private static final software.amazon.awssdk.core.SdkField<java.lang.String> INPUT_COMPRESSION_TYPE_FIELD;

  private static final software.amazon.awssdk.core.SdkField<software.amazon.awssdk.services.dynamodb.model.TableCreationParameters> TABLE_CREATION_PARAMETERS_FIELD;

  private static final software.amazon.awssdk.core.SdkField<java.time.Instant> START_TIME_FIELD;

  private static final software.amazon.awssdk.core.SdkField<java.time.Instant> END_TIME_FIELD;

  private static final software.amazon.awssdk.core.SdkField<java.lang.Long> PROCESSED_SIZE_BYTES_FIELD;

  private static final software.amazon.awssdk.core.SdkField<java.lang.Long> PROCESSED_ITEM_COUNT_FIELD;

  private static final software.amazon.awssdk.core.SdkField<java.lang.Long> IMPORTED_ITEM_COUNT_FIELD;

  private static final software.amazon.awssdk.core.SdkField<java.lang.String> FAILURE_CODE_FIELD;

  private static final software.amazon.awssdk.core.SdkField<java.lang.String> FAILURE_MESSAGE_FIELD;

  private static final java.util.List<software.amazon.awssdk.core.SdkField<?>> SDK_FIELDS;

  private static final long serialVersionUID;

  private final java.lang.String importArn;

  private final java.lang.String importStatus;

  private final java.lang.String tableArn;

  private final java.lang.String tableId;

  private final java.lang.String clientToken;

  private final software.amazon.awssdk.services.dynamodb.model.S3BucketSource s3BucketSource;

  private final java.lang.Long errorCount;

  private final java.lang.String cloudWatchLogGroupArn;

  private final java.lang.String inputFormat;

  private final software.amazon.awssdk.services.dynamodb.model.InputFormatOptions inputFormatOptions;

  private final java.lang.String inputCompressionType;

  private final software.amazon.awssdk.services.dynamodb.model.TableCreationParameters tableCreationParameters;

  private final java.time.Instant startTime;

  private final java.time.Instant endTime;

  private final java.lang.Long processedSizeBytes;

  private final java.lang.Long processedItemCount;

  private final java.lang.Long importedItemCount;

  private final java.lang.String failureCode;

  private final java.lang.String failureMessage;

  private software.amazon.awssdk.services.dynamodb.model.ImportTableDescription(software.amazon.awssdk.services.dynamodb.model.ImportTableDescription$BuilderImpl);
    Code:
       0: aload_0
       1: invokespecial #22                 // Method java/lang/Object."<init>":()V
       4: aload_0
       5: aload_1
       6: invokestatic  #23                 // Method software/amazon/awssdk/services/dynamodb/model/ImportTableDescription$BuilderImpl.access$000:(Lsoftware/amazon/awssdk/services/dynamodb/model/ImportTableDescription$BuilderImpl;)Ljava/lang/String;
       9: putfield      #21                 // Field importArn:Ljava/lang/String;
      12: aload_0
      13: aload_1
      14: invokestatic  #24                 // Method software/amazon/awssdk/services/dynamodb/model/ImportTableDescription$BuilderImpl.access$100:(Lsoftware/amazon/awssdk/services/dynamodb/model/ImportTableDescription$BuilderImpl;)Ljava/lang/String;
      17: putfield      #20                 // Field importStatus:Ljava/lang/String;
      20: aload_0
      21: aload_1
      22: invokestatic  #25                 // Method software/amazon/awssdk/services/dynamodb/model/ImportTableDescription$BuilderImpl.access$200:(Lsoftware/amazon/awssdk/services/dynamodb/model/ImportTableDescription$BuilderImpl;)Ljava/lang/String;
      25: putfield      #19                 // Field tableArn:Ljava/lang/String;
      28: aload_0
      29: aload_1
      30: invokestatic  #26                 // Method software/amazon/awssdk/services/dynamodb/model/ImportTableDescription$BuilderImpl.access$300:(Lsoftware/amazon/awssdk/services/dynamodb/model/ImportTableDescription$BuilderImpl;)Ljava/lang/String;
      33: putfield      #18                 // Field tableId:Ljava/lang/String;
      36: aload_0
      37: aload_1
      38: invokestatic  #27                 // Method software/amazon/awssdk/services/dynamodb/model/ImportTableDescription$BuilderImpl.access$400:(Lsoftware/amazon/awssdk/services/dynamodb/model/ImportTableDescription$BuilderImpl;)Ljava/lang/String;
      41: putfield      #17                 // Field clientToken:Ljava/lang/String;
      44: aload_0
      45: aload_1
      46: invokestatic  #28                 // Method software/amazon/awssdk/services/dynamodb/model/ImportTableDescription$BuilderImpl.access$500:(Lsoftware/amazon/awssdk/services/dynamodb/model/ImportTableDescription$BuilderImpl;)Lsoftware/amazon/awssdk/services/dynamodb/model/S3BucketSource;
      49: putfield      #16                 // Field s3BucketSource:Lsoftware/amazon/awssdk/services/dynamodb/model/S3BucketSource;
      52: aload_0
      53: aload_1
      54: invokestatic  #29                 // Method software/amazon/awssdk/services/dynamodb/model/ImportTableDescription$BuilderImpl.access$600:(Lsoftware/amazon/awssdk/services/dynamodb/model/ImportTableDescription$BuilderImpl;)Ljava/lang/Long;
      57: putfield      #15                 // Field errorCount:Ljava/lang/Long;
      60: aload_0
      61: aload_1
      62: invokestatic  #30                 // Method software/amazon/awssdk/services/dynamodb/model/ImportTableDescription$BuilderImpl.access$700:(Lsoftware/amazon/awssdk/services/dynamodb/model/ImportTableDescription$BuilderImpl;)Ljava/lang/String;
      65: putfield      #14                 // Field cloudWatchLogGroupArn:Ljava/lang/String;
      68: aload_0
      69: aload_1
      70: invokestatic  #31                 // Method software/amazon/awssdk/services/dynamodb/model/ImportTableDescription$BuilderImpl.access$800:(Lsoftware/amazon/awssdk/services/dynamodb/model/ImportTableDescription$BuilderImpl;)Ljava/lang/String;
      73: putfield      #13                 // Field inputFormat:Ljava/lang/String;
      76: aload_0
      77: aload_1
      78: invokestatic  #32                 // Method software/amazon/awssdk/services/dynamodb/model/ImportTableDescription$BuilderImpl.access$900:(Lsoftware/amazon/awssdk/services/dynamodb/model/ImportTableDescription$BuilderImpl;)Lsoftware/amazon/awssdk/services/dynamodb/model/InputFormatOptions;
      81: putfield      #12                 // Field inputFormatOptions:Lsoftware/amazon/awssdk/services/dynamodb/model/InputFormatOptions;
      84: aload_0
      85: aload_1
      86: invokestatic  #33                 // Method software/amazon/awssdk/services/dynamodb/model/ImportTableDescription$BuilderImpl.access$1000:(Lsoftware/amazon/awssdk/services/dynamodb/model/ImportTableDescription$BuilderImpl;)Ljava/lang/String;
      89: putfield      #11                 // Field inputCompressionType:Ljava/lang/String;
      92: aload_0
      93: aload_1
      94: invokestatic  #34                 // Method software/amazon/awssdk/services/dynamodb/model/ImportTableDescription$BuilderImpl.access$1100:(Lsoftware/amazon/awssdk/services/dynamodb/model/ImportTableDescription$BuilderImpl;)Lsoftware/amazon/awssdk/services/dynamodb/model/TableCreationParameters;
      97: putfield      #10                 // Field tableCreationParameters:Lsoftware/amazon/awssdk/services/dynamodb/model/TableCreationParameters;
     100: aload_0
     101: aload_1
     102: invokestatic  #35                 // Method software/amazon/awssdk/services/dynamodb/model/ImportTableDescription$BuilderImpl.access$1200:(Lsoftware/amazon/awssdk/services/dynamodb/model/ImportTableDescription$BuilderImpl;)Ljava/time/Instant;
     105: putfield      #9                  // Field startTime:Ljava/time/Instant;
     108: aload_0
     109: aload_1
     110: invokestatic  #36                 // Method software/amazon/awssdk/services/dynamodb/model/ImportTableDescription$BuilderImpl.access$1300:(Lsoftware/amazon/awssdk/services/dynamodb/model/ImportTableDescription$BuilderImpl;)Ljava/time/Instant;
     113: putfield      #8                  // Field endTime:Ljava/time/Instant;
     116: aload_0
     117: aload_1
     118: invokestatic  #37                 // Method software/amazon/awssdk/services/dynamodb/model/ImportTableDescription$BuilderImpl.access$1400:(Lsoftware/amazon/awssdk/services/dynamodb/model/ImportTableDescription$BuilderImpl;)Ljava/lang/Long;
     121: putfield      #7                  // Field processedSizeBytes:Ljava/lang/Long;
     124: aload_0
     125: aload_1
     126: invokestatic  #38                 // Method software/amazon/awssdk/services/dynamodb/model/ImportTableDescription$BuilderImpl.access$1500:(Lsoftware/amazon/awssdk/services/dynamodb/model/ImportTableDescription$BuilderImpl;)Ljava/lang/Long;
     129: putfield      #6                  // Field processedItemCount:Ljava/lang/Long;
     132: aload_0
     133: aload_1
     134: invokestatic  #39                 // Method software/amazon/awssdk/services/dynamodb/model/ImportTableDescription$BuilderImpl.access$1600:(Lsoftware/amazon/awssdk/services/dynamodb/model/ImportTableDescription$BuilderImpl;)Ljava/lang/Long;
     137: putfield      #5                  // Field importedItemCount:Ljava/lang/Long;
     140: aload_0
     141: aload_1
     142: invokestatic  #40                 // Method software/amazon/awssdk/services/dynamodb/model/ImportTableDescription$BuilderImpl.access$1700:(Lsoftware/amazon/awssdk/services/dynamodb/model/ImportTableDescription$BuilderImpl;)Ljava/lang/String;
     145: putfield      #4                  // Field failureCode:Ljava/lang/String;
     148: aload_0
     149: aload_1
     150: invokestatic  #41                 // Method software/amazon/awssdk/services/dynamodb/model/ImportTableDescription$BuilderImpl.access$1800:(Lsoftware/amazon/awssdk/services/dynamodb/model/ImportTableDescription$BuilderImpl;)Ljava/lang/String;
     153: putfield      #3                  // Field failureMessage:Ljava/lang/String;
     156: return

  public final java.lang.String importArn();
    Code:
       0: aload_0
       1: getfield      #21                 // Field importArn:Ljava/lang/String;
       4: areturn

  public final software.amazon.awssdk.services.dynamodb.model.ImportStatus importStatus();
    Code:
       0: aload_0
       1: getfield      #20                 // Field importStatus:Ljava/lang/String;
       4: invokestatic  #42                 // Method software/amazon/awssdk/services/dynamodb/model/ImportStatus.fromValue:(Ljava/lang/String;)Lsoftware/amazon/awssdk/services/dynamodb/model/ImportStatus;
       7: areturn

  public final java.lang.String importStatusAsString();
    Code:
       0: aload_0
       1: getfield      #20                 // Field importStatus:Ljava/lang/String;
       4: areturn

  public final java.lang.String tableArn();
    Code:
       0: aload_0
       1: getfield      #19                 // Field tableArn:Ljava/lang/String;
       4: areturn

  public final java.lang.String tableId();
    Code:
       0: aload_0
       1: getfield      #18                 // Field tableId:Ljava/lang/String;
       4: areturn

  public final java.lang.String clientToken();
    Code:
       0: aload_0
       1: getfield      #17                 // Field clientToken:Ljava/lang/String;
       4: areturn

  public final software.amazon.awssdk.services.dynamodb.model.S3BucketSource s3BucketSource();
    Code:
       0: aload_0
       1: getfield      #16                 // Field s3BucketSource:Lsoftware/amazon/awssdk/services/dynamodb/model/S3BucketSource;
       4: areturn

  public final java.lang.Long errorCount();
    Code:
       0: aload_0
       1: getfield      #15                 // Field errorCount:Ljava/lang/Long;
       4: areturn

  public final java.lang.String cloudWatchLogGroupArn();
    Code:
       0: aload_0
       1: getfield      #14                 // Field cloudWatchLogGroupArn:Ljava/lang/String;
       4: areturn

  public final software.amazon.awssdk.services.dynamodb.model.InputFormat inputFormat();
    Code:
       0: aload_0
       1: getfield      #13                 // Field inputFormat:Ljava/lang/String;
       4: invokestatic  #43                 // Method software/amazon/awssdk/services/dynamodb/model/InputFormat.fromValue:(Ljava/lang/String;)Lsoftware/amazon/awssdk/services/dynamodb/model/InputFormat;
       7: areturn

  public final java.lang.String inputFormatAsString();
    Code:
       0: aload_0
       1: getfield      #13                 // Field inputFormat:Ljava/lang/String;
       4: areturn

  public final software.amazon.awssdk.services.dynamodb.model.InputFormatOptions inputFormatOptions();
    Code:
       0: aload_0
       1: getfield      #12                 // Field inputFormatOptions:Lsoftware/amazon/awssdk/services/dynamodb/model/InputFormatOptions;
       4: areturn

  public final software.amazon.awssdk.services.dynamodb.model.InputCompressionType inputCompressionType();
    Code:
       0: aload_0
       1: getfield      #11                 // Field inputCompressionType:Ljava/lang/String;
       4: invokestatic  #44                 // Method software/amazon/awssdk/services/dynamodb/model/InputCompressionType.fromValue:(Ljava/lang/String;)Lsoftware/amazon/awssdk/services/dynamodb/model/InputCompressionType;
       7: areturn

  public final java.lang.String inputCompressionTypeAsString();
    Code:
       0: aload_0
       1: getfield      #11                 // Field inputCompressionType:Ljava/lang/String;
       4: areturn

  public final software.amazon.awssdk.services.dynamodb.model.TableCreationParameters tableCreationParameters();
    Code:
       0: aload_0
       1: getfield      #10                 // Field tableCreationParameters:Lsoftware/amazon/awssdk/services/dynamodb/model/TableCreationParameters;
       4: areturn

  public final java.time.Instant startTime();
    Code:
       0: aload_0
       1: getfield      #9                  // Field startTime:Ljava/time/Instant;
       4: areturn

  public final java.time.Instant endTime();
    Code:
       0: aload_0
       1: getfield      #8                  // Field endTime:Ljava/time/Instant;
       4: areturn

  public final java.lang.Long processedSizeBytes();
    Code:
       0: aload_0
       1: getfield      #7                  // Field processedSizeBytes:Ljava/lang/Long;
       4: areturn

  public final java.lang.Long processedItemCount();
    Code:
       0: aload_0
       1: getfield      #6                  // Field processedItemCount:Ljava/lang/Long;
       4: areturn

  public final java.lang.Long importedItemCount();
    Code:
       0: aload_0
       1: getfield      #5                  // Field importedItemCount:Ljava/lang/Long;
       4: areturn

  public final java.lang.String failureCode();
    Code:
       0: aload_0
       1: getfield      #4                  // Field failureCode:Ljava/lang/String;
       4: areturn

  public final java.lang.String failureMessage();
    Code:
       0: aload_0
       1: getfield      #3                  // Field failureMessage:Ljava/lang/String;
       4: areturn

  public software.amazon.awssdk.services.dynamodb.model.ImportTableDescription$Builder toBuilder();
    Code:
       0: new           #45                 // class software/amazon/awssdk/services/dynamodb/model/ImportTableDescription$BuilderImpl
       3: dup
       4: aload_0
       5: aconst_null
       6: invokespecial #46                 // Method software/amazon/awssdk/services/dynamodb/model/ImportTableDescription$BuilderImpl."<init>":(Lsoftware/amazon/awssdk/services/dynamodb/model/ImportTableDescription;Lsoftware/amazon/awssdk/services/dynamodb/model/ImportTableDescription$1;)V
       9: areturn

  public static software.amazon.awssdk.services.dynamodb.model.ImportTableDescription$Builder builder();
    Code:
       0: new           #45                 // class software/amazon/awssdk/services/dynamodb/model/ImportTableDescription$BuilderImpl
       3: dup
       4: aconst_null
       5: invokespecial #47                 // Method software/amazon/awssdk/services/dynamodb/model/ImportTableDescription$BuilderImpl."<init>":(Lsoftware/amazon/awssdk/services/dynamodb/model/ImportTableDescription$1;)V
       8: areturn

  public static java.lang.Class<? extends software.amazon.awssdk.services.dynamodb.model.ImportTableDescription$Builder> serializableBuilderClass();
    Code:
       0: ldc           #45                 // class software/amazon/awssdk/services/dynamodb/model/ImportTableDescription$BuilderImpl
       2: areturn

  public final int hashCode();
    Code:
       0: iconst_1
       1: istore_1
       2: bipush        31
       4: iload_1
       5: imul
       6: aload_0
       7: invokevirtual #48                 // Method importArn:()Ljava/lang/String;
      10: invokestatic  #49                 // Method java/util/Objects.hashCode:(Ljava/lang/Object;)I
      13: iadd
      14: istore_1
      15: bipush        31
      17: iload_1
      18: imul
      19: aload_0
      20: invokevirtual #50                 // Method importStatusAsString:()Ljava/lang/String;
      23: invokestatic  #49                 // Method java/util/Objects.hashCode:(Ljava/lang/Object;)I
      26: iadd
      27: istore_1
      28: bipush        31
      30: iload_1
      31: imul
      32: aload_0
      33: invokevirtual #51                 // Method tableArn:()Ljava/lang/String;
      36: invokestatic  #49                 // Method java/util/Objects.hashCode:(Ljava/lang/Object;)I
      39: iadd
      40: istore_1
      41: bipush        31
      43: iload_1
      44: imul
      45: aload_0
      46: invokevirtual #52                 // Method tableId:()Ljava/lang/String;
      49: invokestatic  #49                 // Method java/util/Objects.hashCode:(Ljava/lang/Object;)I
      52: iadd
      53: istore_1
      54: bipush        31
      56: iload_1
      57: imul
      58: aload_0
      59: invokevirtual #53                 // Method clientToken:()Ljava/lang/String;
      62: invokestatic  #49                 // Method java/util/Objects.hashCode:(Ljava/lang/Object;)I
      65: iadd
      66: istore_1
      67: bipush        31
      69: iload_1
      70: imul
      71: aload_0
      72: invokevirtual #54                 // Method s3BucketSource:()Lsoftware/amazon/awssdk/services/dynamodb/model/S3BucketSource;
      75: invokestatic  #49                 // Method java/util/Objects.hashCode:(Ljava/lang/Object;)I
      78: iadd
      79: istore_1
      80: bipush        31
      82: iload_1
      83: imul
      84: aload_0
      85: invokevirtual #55                 // Method errorCount:()Ljava/lang/Long;
      88: invokestatic  #49                 // Method java/util/Objects.hashCode:(Ljava/lang/Object;)I
      91: iadd
      92: istore_1
      93: bipush        31
      95: iload_1
      96: imul
      97: aload_0
      98: invokevirtual #56                 // Method cloudWatchLogGroupArn:()Ljava/lang/String;
     101: invokestatic  #49                 // Method java/util/Objects.hashCode:(Ljava/lang/Object;)I
     104: iadd
     105: istore_1
     106: bipush        31
     108: iload_1
     109: imul
     110: aload_0
     111: invokevirtual #57                 // Method inputFormatAsString:()Ljava/lang/String;
     114: invokestatic  #49                 // Method java/util/Objects.hashCode:(Ljava/lang/Object;)I
     117: iadd
     118: istore_1
     119: bipush        31
     121: iload_1
     122: imul
     123: aload_0
     124: invokevirtual #58                 // Method inputFormatOptions:()Lsoftware/amazon/awssdk/services/dynamodb/model/InputFormatOptions;
     127: invokestatic  #49                 // Method java/util/Objects.hashCode:(Ljava/lang/Object;)I
     130: iadd
     131: istore_1
     132: bipush        31
     134: iload_1
     135: imul
     136: aload_0
     137: invokevirtual #59                 // Method inputCompressionTypeAsString:()Ljava/lang/String;
     140: invokestatic  #49                 // Method java/util/Objects.hashCode:(Ljava/lang/Object;)I
     143: iadd
     144: istore_1
     145: bipush        31
     147: iload_1
     148: imul
     149: aload_0
     150: invokevirtual #60                 // Method tableCreationParameters:()Lsoftware/amazon/awssdk/services/dynamodb/model/TableCreationParameters;
     153: invokestatic  #49                 // Method java/util/Objects.hashCode:(Ljava/lang/Object;)I
     156: iadd
     157: istore_1
     158: bipush        31
     160: iload_1
     161: imul
     162: aload_0
     163: invokevirtual #61                 // Method startTime:()Ljava/time/Instant;
     166: invokestatic  #49                 // Method java/util/Objects.hashCode:(Ljava/lang/Object;)I
     169: iadd
     170: istore_1
     171: bipush        31
     173: iload_1
     174: imul
     175: aload_0
     176: invokevirtual #62                 // Method endTime:()Ljava/time/Instant;
     179: invokestatic  #49                 // Method java/util/Objects.hashCode:(Ljava/lang/Object;)I
     182: iadd
     183: istore_1
     184: bipush        31
     186: iload_1
     187: imul
     188: aload_0
     189: invokevirtual #63                 // Method processedSizeBytes:()Ljava/lang/Long;
     192: invokestatic  #49                 // Method java/util/Objects.hashCode:(Ljava/lang/Object;)I
     195: iadd
     196: istore_1
     197: bipush        31
     199: iload_1
     200: imul
     201: aload_0
     202: invokevirtual #64                 // Method processedItemCount:()Ljava/lang/Long;
     205: invokestatic  #49                 // Method java/util/Objects.hashCode:(Ljava/lang/Object;)I
     208: iadd
     209: istore_1
     210: bipush        31
     212: iload_1
     213: imul
     214: aload_0
     215: invokevirtual #65                 // Method importedItemCount:()Ljava/lang/Long;
     218: invokestatic  #49                 // Method java/util/Objects.hashCode:(Ljava/lang/Object;)I
     221: iadd
     222: istore_1
     223: bipush        31
     225: iload_1
     226: imul
     227: aload_0
     228: invokevirtual #66                 // Method failureCode:()Ljava/lang/String;
     231: invokestatic  #49                 // Method java/util/Objects.hashCode:(Ljava/lang/Object;)I
     234: iadd
     235: istore_1
     236: bipush        31
     238: iload_1
     239: imul
     240: aload_0
     241: invokevirtual #67                 // Method failureMessage:()Ljava/lang/String;
     244: invokestatic  #49                 // Method java/util/Objects.hashCode:(Ljava/lang/Object;)I
     247: iadd
     248: istore_1
     249: iload_1
     250: ireturn

  public final boolean equals(java.lang.Object);
    Code:
       0: aload_0
       1: aload_1
       2: invokevirtual #68                 // Method equalsBySdkFields:(Ljava/lang/Object;)Z
       5: ireturn

  public final boolean equalsBySdkFields(java.lang.Object);
    Code:
       0: aload_0
       1: aload_1
       2: if_acmpne     7
       5: iconst_1
       6: ireturn
       7: aload_1
       8: ifnonnull     13
      11: iconst_0
      12: ireturn
      13: aload_1
      14: instanceof    #69                 // class software/amazon/awssdk/services/dynamodb/model/ImportTableDescription
      17: ifne          22
      20: iconst_0
      21: ireturn
      22: aload_1
      23: checkcast     #69                 // class software/amazon/awssdk/services/dynamodb/model/ImportTableDescription
      26: astore_2
      27: aload_0
      28: invokevirtual #48                 // Method importArn:()Ljava/lang/String;
      31: aload_2
      32: invokevirtual #48                 // Method importArn:()Ljava/lang/String;
      35: invokestatic  #70                 // Method java/util/Objects.equals:(Ljava/lang/Object;Ljava/lang/Object;)Z
      38: ifeq          297
      41: aload_0
      42: invokevirtual #50                 // Method importStatusAsString:()Ljava/lang/String;
      45: aload_2
      46: invokevirtual #50                 // Method importStatusAsString:()Ljava/lang/String;
      49: invokestatic  #70                 // Method java/util/Objects.equals:(Ljava/lang/Object;Ljava/lang/Object;)Z
      52: ifeq          297
      55: aload_0
      56: invokevirtual #51                 // Method tableArn:()Ljava/lang/String;
      59: aload_2
      60: invokevirtual #51                 // Method tableArn:()Ljava/lang/String;
      63: invokestatic  #70                 // Method java/util/Objects.equals:(Ljava/lang/Object;Ljava/lang/Object;)Z
      66: ifeq          297
      69: aload_0
      70: invokevirtual #52                 // Method tableId:()Ljava/lang/String;
      73: aload_2
      74: invokevirtual #52                 // Method tableId:()Ljava/lang/String;
      77: invokestatic  #70                 // Method java/util/Objects.equals:(Ljava/lang/Object;Ljava/lang/Object;)Z
      80: ifeq          297
      83: aload_0
      84: invokevirtual #53                 // Method clientToken:()Ljava/lang/String;
      87: aload_2
      88: invokevirtual #53                 // Method clientToken:()Ljava/lang/String;
      91: invokestatic  #70                 // Method java/util/Objects.equals:(Ljava/lang/Object;Ljava/lang/Object;)Z
      94: ifeq          297
      97: aload_0
      98: invokevirtual #54                 // Method s3BucketSource:()Lsoftware/amazon/awssdk/services/dynamodb/model/S3BucketSource;
     101: aload_2
     102: invokevirtual #54                 // Method s3BucketSource:()Lsoftware/amazon/awssdk/services/dynamodb/model/S3BucketSource;
     105: invokestatic  #70                 // Method java/util/Objects.equals:(Ljava/lang/Object;Ljava/lang/Object;)Z
     108: ifeq          297
     111: aload_0
     112: invokevirtual #55                 // Method errorCount:()Ljava/lang/Long;
     115: aload_2
     116: invokevirtual #55                 // Method errorCount:()Ljava/lang/Long;
     119: invokestatic  #70                 // Method java/util/Objects.equals:(Ljava/lang/Object;Ljava/lang/Object;)Z
     122: ifeq          297
     125: aload_0
     126: invokevirtual #56                 // Method cloudWatchLogGroupArn:()Ljava/lang/String;
     129: aload_2
     130: invokevirtual #56                 // Method cloudWatchLogGroupArn:()Ljava/lang/String;
     133: invokestatic  #70                 // Method java/util/Objects.equals:(Ljava/lang/Object;Ljava/lang/Object;)Z
     136: ifeq          297
     139: aload_0
     140: invokevirtual #57                 // Method inputFormatAsString:()Ljava/lang/String;
     143: aload_2
     144: invokevirtual #57                 // Method inputFormatAsString:()Ljava/lang/String;
     147: invokestatic  #70                 // Method java/util/Objects.equals:(Ljava/lang/Object;Ljava/lang/Object;)Z
     150: ifeq          297
     153: aload_0
     154: invokevirtual #58                 // Method inputFormatOptions:()Lsoftware/amazon/awssdk/services/dynamodb/model/InputFormatOptions;
     157: aload_2
     158: invokevirtual #58                 // Method inputFormatOptions:()Lsoftware/amazon/awssdk/services/dynamodb/model/InputFormatOptions;
     161: invokestatic  #70                 // Method java/util/Objects.equals:(Ljava/lang/Object;Ljava/lang/Object;)Z
     164: ifeq          297
     167: aload_0
     168: invokevirtual #59                 // Method inputCompressionTypeAsString:()Ljava/lang/String;
     171: aload_2
     172: invokevirtual #59                 // Method inputCompressionTypeAsString:()Ljava/lang/String;
     175: invokestatic  #70                 // Method java/util/Objects.equals:(Ljava/lang/Object;Ljava/lang/Object;)Z
     178: ifeq          297
     181: aload_0
     182: invokevirtual #60                 // Method tableCreationParameters:()Lsoftware/amazon/awssdk/services/dynamodb/model/TableCreationParameters;
     185: aload_2
     186: invokevirtual #60                 // Method tableCreationParameters:()Lsoftware/amazon/awssdk/services/dynamodb/model/TableCreationParameters;
     189: invokestatic  #70                 // Method java/util/Objects.equals:(Ljava/lang/Object;Ljava/lang/Object;)Z
     192: ifeq          297
     195: aload_0
     196: invokevirtual #61                 // Method startTime:()Ljava/time/Instant;
     199: aload_2
     200: invokevirtual #61                 // Method startTime:()Ljava/time/Instant;
     203: invokestatic  #70                 // Method java/util/Objects.equals:(Ljava/lang/Object;Ljava/lang/Object;)Z
     206: ifeq          297
     209: aload_0
     210: invokevirtual #62                 // Method endTime:()Ljava/time/Instant;
     213: aload_2
     214: invokevirtual #62                 // Method endTime:()Ljava/time/Instant;
     217: invokestatic  #70                 // Method java/util/Objects.equals:(Ljava/lang/Object;Ljava/lang/Object;)Z
     220: ifeq          297
     223: aload_0
     224: invokevirtual #63                 // Method processedSizeBytes:()Ljava/lang/Long;
     227: aload_2
     228: invokevirtual #63                 // Method processedSizeBytes:()Ljava/lang/Long;
     231: invokestatic  #70                 // Method java/util/Objects.equals:(Ljava/lang/Object;Ljava/lang/Object;)Z
     234: ifeq          297
     237: aload_0
     238: invokevirtual #64                 // Method processedItemCount:()Ljava/lang/Long;
     241: aload_2
     242: invokevirtual #64                 // Method processedItemCount:()Ljava/lang/Long;
     245: invokestatic  #70                 // Method java/util/Objects.equals:(Ljava/lang/Object;Ljava/lang/Object;)Z
     248: ifeq          297
     251: aload_0
     252: invokevirtual #65                 // Method importedItemCount:()Ljava/lang/Long;
     255: aload_2
     256: invokevirtual #65                 // Method importedItemCount:()Ljava/lang/Long;
     259: invokestatic  #70                 // Method java/util/Objects.equals:(Ljava/lang/Object;Ljava/lang/Object;)Z
     262: ifeq          297
     265: aload_0
     266: invokevirtual #66                 // Method failureCode:()Ljava/lang/String;
     269: aload_2
     270: invokevirtual #66                 // Method failureCode:()Ljava/lang/String;
     273: invokestatic  #70                 // Method java/util/Objects.equals:(Ljava/lang/Object;Ljava/lang/Object;)Z
     276: ifeq          297
     279: aload_0
     280: invokevirtual #67                 // Method failureMessage:()Ljava/lang/String;
     283: aload_2
     284: invokevirtual #67                 // Method failureMessage:()Ljava/lang/String;
     287: invokestatic  #70                 // Method java/util/Objects.equals:(Ljava/lang/Object;Ljava/lang/Object;)Z
     290: ifeq          297
     293: iconst_1
     294: goto          298
     297: iconst_0
     298: ireturn

  public final java.lang.String toString();
    Code:
       0: ldc           #71                 // String ImportTableDescription
       2: invokestatic  #72                 // Method software/amazon/awssdk/utils/ToString.builder:(Ljava/lang/String;)Lsoftware/amazon/awssdk/utils/ToString;
       5: ldc           #73                 // String ImportArn
       7: aload_0
       8: invokevirtual #48                 // Method importArn:()Ljava/lang/String;
      11: invokevirtual #74                 // Method software/amazon/awssdk/utils/ToString.add:(Ljava/lang/String;Ljava/lang/Object;)Lsoftware/amazon/awssdk/utils/ToString;
      14: ldc           #75                 // String ImportStatus
      16: aload_0
      17: invokevirtual #50                 // Method importStatusAsString:()Ljava/lang/String;
      20: invokevirtual #74                 // Method software/amazon/awssdk/utils/ToString.add:(Ljava/lang/String;Ljava/lang/Object;)Lsoftware/amazon/awssdk/utils/ToString;
      23: ldc           #76                 // String TableArn
      25: aload_0
      26: invokevirtual #51                 // Method tableArn:()Ljava/lang/String;
      29: invokevirtual #74                 // Method software/amazon/awssdk/utils/ToString.add:(Ljava/lang/String;Ljava/lang/Object;)Lsoftware/amazon/awssdk/utils/ToString;
      32: ldc           #77                 // String TableId
      34: aload_0
      35: invokevirtual #52                 // Method tableId:()Ljava/lang/String;
      38: invokevirtual #74                 // Method software/amazon/awssdk/utils/ToString.add:(Ljava/lang/String;Ljava/lang/Object;)Lsoftware/amazon/awssdk/utils/ToString;
      41: ldc           #78                 // String ClientToken
      43: aload_0
      44: invokevirtual #53                 // Method clientToken:()Ljava/lang/String;
      47: invokevirtual #74                 // Method software/amazon/awssdk/utils/ToString.add:(Ljava/lang/String;Ljava/lang/Object;)Lsoftware/amazon/awssdk/utils/ToString;
      50: ldc           #79                 // String S3BucketSource
      52: aload_0
      53: invokevirtual #54                 // Method s3BucketSource:()Lsoftware/amazon/awssdk/services/dynamodb/model/S3BucketSource;
      56: invokevirtual #74                 // Method software/amazon/awssdk/utils/ToString.add:(Ljava/lang/String;Ljava/lang/Object;)Lsoftware/amazon/awssdk/utils/ToString;
      59: ldc           #80                 // String ErrorCount
      61: aload_0
      62: invokevirtual #55                 // Method errorCount:()Ljava/lang/Long;
      65: invokevirtual #74                 // Method software/amazon/awssdk/utils/ToString.add:(Ljava/lang/String;Ljava/lang/Object;)Lsoftware/amazon/awssdk/utils/ToString;
      68: ldc           #81                 // String CloudWatchLogGroupArn
      70: aload_0
      71: invokevirtual #56                 // Method cloudWatchLogGroupArn:()Ljava/lang/String;
      74: invokevirtual #74                 // Method software/amazon/awssdk/utils/ToString.add:(Ljava/lang/String;Ljava/lang/Object;)Lsoftware/amazon/awssdk/utils/ToString;
      77: ldc           #82                 // String InputFormat
      79: aload_0
      80: invokevirtual #57                 // Method inputFormatAsString:()Ljava/lang/String;
      83: invokevirtual #74                 // Method software/amazon/awssdk/utils/ToString.add:(Ljava/lang/String;Ljava/lang/Object;)Lsoftware/amazon/awssdk/utils/ToString;
      86: ldc           #83                 // String InputFormatOptions
      88: aload_0
      89: invokevirtual #58                 // Method inputFormatOptions:()Lsoftware/amazon/awssdk/services/dynamodb/model/InputFormatOptions;
      92: invokevirtual #74                 // Method software/amazon/awssdk/utils/ToString.add:(Ljava/lang/String;Ljava/lang/Object;)Lsoftware/amazon/awssdk/utils/ToString;
      95: ldc           #84                 // String InputCompressionType
      97: aload_0
      98: invokevirtual #59                 // Method inputCompressionTypeAsString:()Ljava/lang/String;
     101: invokevirtual #74                 // Method software/amazon/awssdk/utils/ToString.add:(Ljava/lang/String;Ljava/lang/Object;)Lsoftware/amazon/awssdk/utils/ToString;
     104: ldc           #85                 // String TableCreationParameters
     106: aload_0
     107: invokevirtual #60                 // Method tableCreationParameters:()Lsoftware/amazon/awssdk/services/dynamodb/model/TableCreationParameters;
     110: invokevirtual #74                 // Method software/amazon/awssdk/utils/ToString.add:(Ljava/lang/String;Ljava/lang/Object;)Lsoftware/amazon/awssdk/utils/ToString;
     113: ldc           #86                 // String StartTime
     115: aload_0
     116: invokevirtual #61                 // Method startTime:()Ljava/time/Instant;
     119: invokevirtual #74                 // Method software/amazon/awssdk/utils/ToString.add:(Ljava/lang/String;Ljava/lang/Object;)Lsoftware/amazon/awssdk/utils/ToString;
     122: ldc           #87                 // String EndTime
     124: aload_0
     125: invokevirtual #62                 // Method endTime:()Ljava/time/Instant;
     128: invokevirtual #74                 // Method software/amazon/awssdk/utils/ToString.add:(Ljava/lang/String;Ljava/lang/Object;)Lsoftware/amazon/awssdk/utils/ToString;
     131: ldc           #88                 // String ProcessedSizeBytes
     133: aload_0
     134: invokevirtual #63                 // Method processedSizeBytes:()Ljava/lang/Long;
     137: invokevirtual #74                 // Method software/amazon/awssdk/utils/ToString.add:(Ljava/lang/String;Ljava/lang/Object;)Lsoftware/amazon/awssdk/utils/ToString;
     140: ldc           #89                 // String ProcessedItemCount
     142: aload_0
     143: invokevirtual #64                 // Method processedItemCount:()Ljava/lang/Long;
     146: invokevirtual #74                 // Method software/amazon/awssdk/utils/ToString.add:(Ljava/lang/String;Ljava/lang/Object;)Lsoftware/amazon/awssdk/utils/ToString;
     149: ldc           #90                 // String ImportedItemCount
     151: aload_0
     152: invokevirtual #65                 // Method importedItemCount:()Ljava/lang/Long;
     155: invokevirtual #74                 // Method software/amazon/awssdk/utils/ToString.add:(Ljava/lang/String;Ljava/lang/Object;)Lsoftware/amazon/awssdk/utils/ToString;
     158: ldc           #91                 // String FailureCode
     160: aload_0
     161: invokevirtual #66                 // Method failureCode:()Ljava/lang/String;
     164: invokevirtual #74                 // Method software/amazon/awssdk/utils/ToString.add:(Ljava/lang/String;Ljava/lang/Object;)Lsoftware/amazon/awssdk/utils/ToString;
     167: ldc           #92                 // String FailureMessage
     169: aload_0
     170: invokevirtual #67                 // Method failureMessage:()Ljava/lang/String;
     173: invokevirtual #74                 // Method software/amazon/awssdk/utils/ToString.add:(Ljava/lang/String;Ljava/lang/Object;)Lsoftware/amazon/awssdk/utils/ToString;
     176: invokevirtual #93                 // Method software/amazon/awssdk/utils/ToString.build:()Ljava/lang/String;
     179: areturn

  public final <T> java.util.Optional<T> getValueForField(java.lang.String, java.lang.Class<T>);
    Code:
       0: aload_1
       1: astore_3
       2: iconst_m1
       3: istore        4
       5: aload_3
       6: invokevirtual #94                 // Method java/lang/String.hashCode:()I
       9: lookupswitch  { // 19
           -1885244393: 187
           -1095810514: 406
           -1066072827: 247
            -830804017: 202
            -691310585: 262
            -577761624: 278
            -555866505: 438
            -125326801: 358
              57410088: 374
             111747433: 217
             131833629: 310
             515715832: 422
             985097281: 294
            1221066934: 326
            1483875534: 232
            1541484892: 390
            1588020029: 454
            1795412056: 172
            1999895159: 342
               default: 467
          }
     172: aload_3
     173: ldc           #73                 // String ImportArn
     175: invokevirtual #95                 // Method java/lang/String.equals:(Ljava/lang/Object;)Z
     178: ifeq          467
     181: iconst_0
     182: istore        4
     184: goto          467
     187: aload_3
     188: ldc           #75                 // String ImportStatus
     190: invokevirtual #95                 // Method java/lang/String.equals:(Ljava/lang/Object;)Z
     193: ifeq          467
     196: iconst_1
     197: istore        4
     199: goto          467
     202: aload_3
     203: ldc           #76                 // String TableArn
     205: invokevirtual #95                 // Method java/lang/String.equals:(Ljava/lang/Object;)Z
     208: ifeq          467
     211: iconst_2
     212: istore        4
     214: goto          467
     217: aload_3
     218: ldc           #77                 // String TableId
     220: invokevirtual #95                 // Method java/lang/String.equals:(Ljava/lang/Object;)Z
     223: ifeq          467
     226: iconst_3
     227: istore        4
     229: goto          467
     232: aload_3
     233: ldc           #78                 // String ClientToken
     235: invokevirtual #95                 // Method java/lang/String.equals:(Ljava/lang/Object;)Z
     238: ifeq          467
     241: iconst_4
     242: istore        4
     244: goto          467
     247: aload_3
     248: ldc           #79                 // String S3BucketSource
     250: invokevirtual #95                 // Method java/lang/String.equals:(Ljava/lang/Object;)Z
     253: ifeq          467
     256: iconst_5
     257: istore        4
     259: goto          467
     262: aload_3
     263: ldc           #80                 // String ErrorCount
     265: invokevirtual #95                 // Method java/lang/String.equals:(Ljava/lang/Object;)Z
     268: ifeq          467
     271: bipush        6
     273: istore        4
     275: goto          467
     278: aload_3
     279: ldc           #81                 // String CloudWatchLogGroupArn
     281: invokevirtual #95                 // Method java/lang/String.equals:(Ljava/lang/Object;)Z
     284: ifeq          467
     287: bipush        7
     289: istore        4
     291: goto          467
     294: aload_3
     295: ldc           #82                 // String InputFormat
     297: invokevirtual #95                 // Method java/lang/String.equals:(Ljava/lang/Object;)Z
     300: ifeq          467
     303: bipush        8
     305: istore        4
     307: goto          467
     310: aload_3
     311: ldc           #83                 // String InputFormatOptions
     313: invokevirtual #95                 // Method java/lang/String.equals:(Ljava/lang/Object;)Z
     316: ifeq          467
     319: bipush        9
     321: istore        4
     323: goto          467
     326: aload_3
     327: ldc           #84                 // String InputCompressionType
     329: invokevirtual #95                 // Method java/lang/String.equals:(Ljava/lang/Object;)Z
     332: ifeq          467
     335: bipush        10
     337: istore        4
     339: goto          467
     342: aload_3
     343: ldc           #85                 // String TableCreationParameters
     345: invokevirtual #95                 // Method java/lang/String.equals:(Ljava/lang/Object;)Z
     348: ifeq          467
     351: bipush        11
     353: istore        4
     355: goto          467
     358: aload_3
     359: ldc           #86                 // String StartTime
     361: invokevirtual #95                 // Method java/lang/String.equals:(Ljava/lang/Object;)Z
     364: ifeq          467
     367: bipush        12
     369: istore        4
     371: goto          467
     374: aload_3
     375: ldc           #87                 // String EndTime
     377: invokevirtual #95                 // Method java/lang/String.equals:(Ljava/lang/Object;)Z
     380: ifeq          467
     383: bipush        13
     385: istore        4
     387: goto          467
     390: aload_3
     391: ldc           #88                 // String ProcessedSizeBytes
     393: invokevirtual #95                 // Method java/lang/String.equals:(Ljava/lang/Object;)Z
     396: ifeq          467
     399: bipush        14
     401: istore        4
     403: goto          467
     406: aload_3
     407: ldc           #89                 // String ProcessedItemCount
     409: invokevirtual #95                 // Method java/lang/String.equals:(Ljava/lang/Object;)Z
     412: ifeq          467
     415: bipush        15
     417: istore        4
     419: goto          467
     422: aload_3
     423: ldc           #90                 // String ImportedItemCount
     425: invokevirtual #95                 // Method java/lang/String.equals:(Ljava/lang/Object;)Z
     428: ifeq          467
     431: bipush        16
     433: istore        4
     435: goto          467
     438: aload_3
     439: ldc           #91                 // String FailureCode
     441: invokevirtual #95                 // Method java/lang/String.equals:(Ljava/lang/Object;)Z
     444: ifeq          467
     447: bipush        17
     449: istore        4
     451: goto          467
     454: aload_3
     455: ldc           #92                 // String FailureMessage
     457: invokevirtual #95                 // Method java/lang/String.equals:(Ljava/lang/Object;)Z
     460: ifeq          467
     463: bipush        18
     465: istore        4
     467: iload         4
     469: tableswitch   { // 0 to 18
                     0: 560
                     1: 572
                     2: 584
                     3: 596
                     4: 608
                     5: 620
                     6: 632
                     7: 644
                     8: 656
                     9: 668
                    10: 680
                    11: 692
                    12: 704
                    13: 716
                    14: 728
                    15: 740
                    16: 752
                    17: 764
                    18: 776
               default: 788
          }
     560: aload_2
     561: aload_0
     562: invokevirtual #48                 // Method importArn:()Ljava/lang/String;
     565: invokevirtual #96                 // Method java/lang/Class.cast:(Ljava/lang/Object;)Ljava/lang/Object;
     568: invokestatic  #97                 // Method java/util/Optional.ofNullable:(Ljava/lang/Object;)Ljava/util/Optional;
     571: areturn
     572: aload_2
     573: aload_0
     574: invokevirtual #50                 // Method importStatusAsString:()Ljava/lang/String;
     577: invokevirtual #96                 // Method java/lang/Class.cast:(Ljava/lang/Object;)Ljava/lang/Object;
     580: invokestatic  #97                 // Method java/util/Optional.ofNullable:(Ljava/lang/Object;)Ljava/util/Optional;
     583: areturn
     584: aload_2
     585: aload_0
     586: invokevirtual #51                 // Method tableArn:()Ljava/lang/String;
     589: invokevirtual #96                 // Method java/lang/Class.cast:(Ljava/lang/Object;)Ljava/lang/Object;
     592: invokestatic  #97                 // Method java/util/Optional.ofNullable:(Ljava/lang/Object;)Ljava/util/Optional;
     595: areturn
     596: aload_2
     597: aload_0
     598: invokevirtual #52                 // Method tableId:()Ljava/lang/String;
     601: invokevirtual #96                 // Method java/lang/Class.cast:(Ljava/lang/Object;)Ljava/lang/Object;
     604: invokestatic  #97                 // Method java/util/Optional.ofNullable:(Ljava/lang/Object;)Ljava/util/Optional;
     607: areturn
     608: aload_2
     609: aload_0
     610: invokevirtual #53                 // Method clientToken:()Ljava/lang/String;
     613: invokevirtual #96                 // Method java/lang/Class.cast:(Ljava/lang/Object;)Ljava/lang/Object;
     616: invokestatic  #97                 // Method java/util/Optional.ofNullable:(Ljava/lang/Object;)Ljava/util/Optional;
     619: areturn
     620: aload_2
     621: aload_0
     622: invokevirtual #54                 // Method s3BucketSource:()Lsoftware/amazon/awssdk/services/dynamodb/model/S3BucketSource;
     625: invokevirtual #96                 // Method java/lang/Class.cast:(Ljava/lang/Object;)Ljava/lang/Object;
     628: invokestatic  #97                 // Method java/util/Optional.ofNullable:(Ljava/lang/Object;)Ljava/util/Optional;
     631: areturn
     632: aload_2
     633: aload_0
     634: invokevirtual #55                 // Method errorCount:()Ljava/lang/Long;
     637: invokevirtual #96                 // Method java/lang/Class.cast:(Ljava/lang/Object;)Ljava/lang/Object;
     640: invokestatic  #97                 // Method java/util/Optional.ofNullable:(Ljava/lang/Object;)Ljava/util/Optional;
     643: areturn
     644: aload_2
     645: aload_0
     646: invokevirtual #56                 // Method cloudWatchLogGroupArn:()Ljava/lang/String;
     649: invokevirtual #96                 // Method java/lang/Class.cast:(Ljava/lang/Object;)Ljava/lang/Object;
     652: invokestatic  #97                 // Method java/util/Optional.ofNullable:(Ljava/lang/Object;)Ljava/util/Optional;
     655: areturn
     656: aload_2
     657: aload_0
     658: invokevirtual #57                 // Method inputFormatAsString:()Ljava/lang/String;
     661: invokevirtual #96                 // Method java/lang/Class.cast:(Ljava/lang/Object;)Ljava/lang/Object;
     664: invokestatic  #97                 // Method java/util/Optional.ofNullable:(Ljava/lang/Object;)Ljava/util/Optional;
     667: areturn
     668: aload_2
     669: aload_0
     670: invokevirtual #58                 // Method inputFormatOptions:()Lsoftware/amazon/awssdk/services/dynamodb/model/InputFormatOptions;
     673: invokevirtual #96                 // Method java/lang/Class.cast:(Ljava/lang/Object;)Ljava/lang/Object;
     676: invokestatic  #97                 // Method java/util/Optional.ofNullable:(Ljava/lang/Object;)Ljava/util/Optional;
     679: areturn
     680: aload_2
     681: aload_0
     682: invokevirtual #59                 // Method inputCompressionTypeAsString:()Ljava/lang/String;
     685: invokevirtual #96                 // Method java/lang/Class.cast:(Ljava/lang/Object;)Ljava/lang/Object;
     688: invokestatic  #97                 // Method java/util/Optional.ofNullable:(Ljava/lang/Object;)Ljava/util/Optional;
     691: areturn
     692: aload_2
     693: aload_0
     694: invokevirtual #60                 // Method tableCreationParameters:()Lsoftware/amazon/awssdk/services/dynamodb/model/TableCreationParameters;
     697: invokevirtual #96                 // Method java/lang/Class.cast:(Ljava/lang/Object;)Ljava/lang/Object;
     700: invokestatic  #97                 // Method java/util/Optional.ofNullable:(Ljava/lang/Object;)Ljava/util/Optional;
     703: areturn
     704: aload_2
     705: aload_0
     706: invokevirtual #61                 // Method startTime:()Ljava/time/Instant;
     709: invokevirtual #96                 // Method java/lang/Class.cast:(Ljava/lang/Object;)Ljava/lang/Object;
     712: invokestatic  #97                 // Method java/util/Optional.ofNullable:(Ljava/lang/Object;)Ljava/util/Optional;
     715: areturn
     716: aload_2
     717: aload_0
     718: invokevirtual #62                 // Method endTime:()Ljava/time/Instant;
     721: invokevirtual #96                 // Method java/lang/Class.cast:(Ljava/lang/Object;)Ljava/lang/Object;
     724: invokestatic  #97                 // Method java/util/Optional.ofNullable:(Ljava/lang/Object;)Ljava/util/Optional;
     727: areturn
     728: aload_2
     729: aload_0
     730: invokevirtual #63                 // Method processedSizeBytes:()Ljava/lang/Long;
     733: invokevirtual #96                 // Method java/lang/Class.cast:(Ljava/lang/Object;)Ljava/lang/Object;
     736: invokestatic  #97                 // Method java/util/Optional.ofNullable:(Ljava/lang/Object;)Ljava/util/Optional;
     739: areturn
     740: aload_2
     741: aload_0
     742: invokevirtual #64                 // Method processedItemCount:()Ljava/lang/Long;
     745: invokevirtual #96                 // Method java/lang/Class.cast:(Ljava/lang/Object;)Ljava/lang/Object;
     748: invokestatic  #97                 // Method java/util/Optional.ofNullable:(Ljava/lang/Object;)Ljava/util/Optional;
     751: areturn
     752: aload_2
     753: aload_0
     754: invokevirtual #65                 // Method importedItemCount:()Ljava/lang/Long;
     757: invokevirtual #96                 // Method java/lang/Class.cast:(Ljava/lang/Object;)Ljava/lang/Object;
     760: invokestatic  #97                 // Method java/util/Optional.ofNullable:(Ljava/lang/Object;)Ljava/util/Optional;
     763: areturn
     764: aload_2
     765: aload_0
     766: invokevirtual #66                 // Method failureCode:()Ljava/lang/String;
     769: invokevirtual #96                 // Method java/lang/Class.cast:(Ljava/lang/Object;)Ljava/lang/Object;
     772: invokestatic  #97                 // Method java/util/Optional.ofNullable:(Ljava/lang/Object;)Ljava/util/Optional;
     775: areturn
     776: aload_2
     777: aload_0
     778: invokevirtual #67                 // Method failureMessage:()Ljava/lang/String;
     781: invokevirtual #96                 // Method java/lang/Class.cast:(Ljava/lang/Object;)Ljava/lang/Object;
     784: invokestatic  #97                 // Method java/util/Optional.ofNullable:(Ljava/lang/Object;)Ljava/util/Optional;
     787: areturn
     788: invokestatic  #98                 // Method java/util/Optional.empty:()Ljava/util/Optional;
     791: areturn

  public final java.util.List<software.amazon.awssdk.core.SdkField<?>> sdkFields();
    Code:
       0: getstatic     #1                  // Field SDK_FIELDS:Ljava/util/List;
       3: areturn

  private static <T> java.util.function.Function<java.lang.Object, T> getter(java.util.function.Function<software.amazon.awssdk.services.dynamodb.model.ImportTableDescription, T>);
    Code:
       0: aload_0
       1: invokedynamic #99,  0             // InvokeDynamic #0:apply:(Ljava/util/function/Function;)Ljava/util/function/Function;
       6: areturn

  private static <T> java.util.function.BiConsumer<java.lang.Object, T> setter(java.util.function.BiConsumer<software.amazon.awssdk.services.dynamodb.model.ImportTableDescription$Builder, T>);
    Code:
       0: aload_0
       1: invokedynamic #100,  0            // InvokeDynamic #1:accept:(Ljava/util/function/BiConsumer;)Ljava/util/function/BiConsumer;
       6: areturn

  public software.amazon.awssdk.utils.builder.CopyableBuilder toBuilder();
    Code:
       0: aload_0
       1: invokevirtual #101                // Method toBuilder:()Lsoftware/amazon/awssdk/services/dynamodb/model/ImportTableDescription$Builder;
       4: areturn

  private static void lambda$setter$1(java.util.function.BiConsumer, java.lang.Object, java.lang.Object);
    Code:
       0: aload_0
       1: aload_1
       2: checkcast     #102                // class software/amazon/awssdk/services/dynamodb/model/ImportTableDescription$Builder
       5: aload_2
       6: invokeinterface #103,  3          // InterfaceMethod java/util/function/BiConsumer.accept:(Ljava/lang/Object;Ljava/lang/Object;)V
      11: return

  private static java.lang.Object lambda$getter$0(java.util.function.Function, java.lang.Object);
    Code:
       0: aload_0
       1: aload_1
       2: checkcast     #69                 // class software/amazon/awssdk/services/dynamodb/model/ImportTableDescription
       5: invokeinterface #104,  2          // InterfaceMethod java/util/function/Function.apply:(Ljava/lang/Object;)Ljava/lang/Object;
      10: areturn

  static java.lang.String access$2100(software.amazon.awssdk.services.dynamodb.model.ImportTableDescription);
    Code:
       0: aload_0
       1: getfield      #21                 // Field importArn:Ljava/lang/String;
       4: areturn

  static java.lang.String access$2200(software.amazon.awssdk.services.dynamodb.model.ImportTableDescription);
    Code:
       0: aload_0
       1: getfield      #20                 // Field importStatus:Ljava/lang/String;
       4: areturn

  static java.lang.String access$2300(software.amazon.awssdk.services.dynamodb.model.ImportTableDescription);
    Code:
       0: aload_0
       1: getfield      #19                 // Field tableArn:Ljava/lang/String;
       4: areturn

  static java.lang.String access$2400(software.amazon.awssdk.services.dynamodb.model.ImportTableDescription);
    Code:
       0: aload_0
       1: getfield      #18                 // Field tableId:Ljava/lang/String;
       4: areturn

  static java.lang.String access$2500(software.amazon.awssdk.services.dynamodb.model.ImportTableDescription);
    Code:
       0: aload_0
       1: getfield      #17                 // Field clientToken:Ljava/lang/String;
       4: areturn

  static software.amazon.awssdk.services.dynamodb.model.S3BucketSource access$2600(software.amazon.awssdk.services.dynamodb.model.ImportTableDescription);
    Code:
       0: aload_0
       1: getfield      #16                 // Field s3BucketSource:Lsoftware/amazon/awssdk/services/dynamodb/model/S3BucketSource;
       4: areturn

  static java.lang.Long access$2700(software.amazon.awssdk.services.dynamodb.model.ImportTableDescription);
    Code:
       0: aload_0
       1: getfield      #15                 // Field errorCount:Ljava/lang/Long;
       4: areturn

  static java.lang.String access$2800(software.amazon.awssdk.services.dynamodb.model.ImportTableDescription);
    Code:
       0: aload_0
       1: getfield      #14                 // Field cloudWatchLogGroupArn:Ljava/lang/String;
       4: areturn

  static java.lang.String access$2900(software.amazon.awssdk.services.dynamodb.model.ImportTableDescription);
    Code:
       0: aload_0
       1: getfield      #13                 // Field inputFormat:Ljava/lang/String;
       4: areturn

  static software.amazon.awssdk.services.dynamodb.model.InputFormatOptions access$3000(software.amazon.awssdk.services.dynamodb.model.ImportTableDescription);
    Code:
       0: aload_0
       1: getfield      #12                 // Field inputFormatOptions:Lsoftware/amazon/awssdk/services/dynamodb/model/InputFormatOptions;
       4: areturn

  static java.lang.String access$3100(software.amazon.awssdk.services.dynamodb.model.ImportTableDescription);
    Code:
       0: aload_0
       1: getfield      #11                 // Field inputCompressionType:Ljava/lang/String;
       4: areturn

  static software.amazon.awssdk.services.dynamodb.model.TableCreationParameters access$3200(software.amazon.awssdk.services.dynamodb.model.ImportTableDescription);
    Code:
       0: aload_0
       1: getfield      #10                 // Field tableCreationParameters:Lsoftware/amazon/awssdk/services/dynamodb/model/TableCreationParameters;
       4: areturn

  static java.time.Instant access$3300(software.amazon.awssdk.services.dynamodb.model.ImportTableDescription);
    Code:
       0: aload_0
       1: getfield      #9                  // Field startTime:Ljava/time/Instant;
       4: areturn

  static java.time.Instant access$3400(software.amazon.awssdk.services.dynamodb.model.ImportTableDescription);
    Code:
       0: aload_0
       1: getfield      #8                  // Field endTime:Ljava/time/Instant;
       4: areturn

  static java.lang.Long access$3500(software.amazon.awssdk.services.dynamodb.model.ImportTableDescription);
    Code:
       0: aload_0
       1: getfield      #7                  // Field processedSizeBytes:Ljava/lang/Long;
       4: areturn

  static java.lang.Long access$3600(software.amazon.awssdk.services.dynamodb.model.ImportTableDescription);
    Code:
       0: aload_0
       1: getfield      #6                  // Field processedItemCount:Ljava/lang/Long;
       4: areturn

  static java.lang.Long access$3700(software.amazon.awssdk.services.dynamodb.model.ImportTableDescription);
    Code:
       0: aload_0
       1: getfield      #5                  // Field importedItemCount:Ljava/lang/Long;
       4: areturn

  static java.lang.String access$3800(software.amazon.awssdk.services.dynamodb.model.ImportTableDescription);
    Code:
       0: aload_0
       1: getfield      #4                  // Field failureCode:Ljava/lang/String;
       4: areturn

  static java.lang.String access$3900(software.amazon.awssdk.services.dynamodb.model.ImportTableDescription);
    Code:
       0: aload_0
       1: getfield      #3                  // Field failureMessage:Ljava/lang/String;
       4: areturn

  software.amazon.awssdk.services.dynamodb.model.ImportTableDescription(software.amazon.awssdk.services.dynamodb.model.ImportTableDescription$BuilderImpl, software.amazon.awssdk.services.dynamodb.model.ImportTableDescription$1);
    Code:
       0: aload_0
       1: aload_1
       2: invokespecial #2                  // Method "<init>":(Lsoftware/amazon/awssdk/services/dynamodb/model/ImportTableDescription$BuilderImpl;)V
       5: return

  static java.util.List access$4100();
    Code:
       0: getstatic     #1                  // Field SDK_FIELDS:Ljava/util/List;
       3: areturn

  static {};
    Code:
       0: getstatic     #105                // Field software/amazon/awssdk/core/protocol/MarshallingType.STRING:Lsoftware/amazon/awssdk/core/protocol/MarshallingType;
       3: invokestatic  #106                // Method software/amazon/awssdk/core/SdkField.builder:(Lsoftware/amazon/awssdk/core/protocol/MarshallingType;)Lsoftware/amazon/awssdk/core/SdkField$Builder;
       6: ldc           #73                 // String ImportArn
       8: invokevirtual #107                // Method software/amazon/awssdk/core/SdkField$Builder.memberName:(Ljava/lang/String;)Lsoftware/amazon/awssdk/core/SdkField$Builder;
      11: invokedynamic #108,  0            // InvokeDynamic #2:apply:()Ljava/util/function/Function;
      16: invokestatic  #109                // Method getter:(Ljava/util/function/Function;)Ljava/util/function/Function;
      19: invokevirtual #110                // Method software/amazon/awssdk/core/SdkField$Builder.getter:(Ljava/util/function/Function;)Lsoftware/amazon/awssdk/core/SdkField$Builder;
      22: invokedynamic #111,  0            // InvokeDynamic #3:accept:()Ljava/util/function/BiConsumer;
      27: invokestatic  #112                // Method setter:(Ljava/util/function/BiConsumer;)Ljava/util/function/BiConsumer;
      30: invokevirtual #113                // Method software/amazon/awssdk/core/SdkField$Builder.setter:(Ljava/util/function/BiConsumer;)Lsoftware/amazon/awssdk/core/SdkField$Builder;
      33: iconst_1
      34: anewarray     #114                // class software/amazon/awssdk/core/traits/Trait
      37: dup
      38: iconst_0
      39: invokestatic  #115                // Method software/amazon/awssdk/core/traits/LocationTrait.builder:()Lsoftware/amazon/awssdk/core/traits/LocationTrait$Builder;
      42: getstatic     #116                // Field software/amazon/awssdk/core/protocol/MarshallLocation.PAYLOAD:Lsoftware/amazon/awssdk/core/protocol/MarshallLocation;
      45: invokevirtual #117                // Method software/amazon/awssdk/core/traits/LocationTrait$Builder.location:(Lsoftware/amazon/awssdk/core/protocol/MarshallLocation;)Lsoftware/amazon/awssdk/core/traits/LocationTrait$Builder;
      48: ldc           #73                 // String ImportArn
      50: invokevirtual #118                // Method software/amazon/awssdk/core/traits/LocationTrait$Builder.locationName:(Ljava/lang/String;)Lsoftware/amazon/awssdk/core/traits/LocationTrait$Builder;
      53: invokevirtual #119                // Method software/amazon/awssdk/core/traits/LocationTrait$Builder.build:()Lsoftware/amazon/awssdk/core/traits/LocationTrait;
      56: aastore
      57: invokevirtual #120                // Method software/amazon/awssdk/core/SdkField$Builder.traits:([Lsoftware/amazon/awssdk/core/traits/Trait;)Lsoftware/amazon/awssdk/core/SdkField$Builder;
      60: invokevirtual #121                // Method software/amazon/awssdk/core/SdkField$Builder.build:()Lsoftware/amazon/awssdk/core/SdkField;
      63: putstatic     #122                // Field IMPORT_ARN_FIELD:Lsoftware/amazon/awssdk/core/SdkField;
      66: getstatic     #105                // Field software/amazon/awssdk/core/protocol/MarshallingType.STRING:Lsoftware/amazon/awssdk/core/protocol/MarshallingType;
      69: invokestatic  #106                // Method software/amazon/awssdk/core/SdkField.builder:(Lsoftware/amazon/awssdk/core/protocol/MarshallingType;)Lsoftware/amazon/awssdk/core/SdkField$Builder;
      72: ldc           #75                 // String ImportStatus
      74: invokevirtual #107                // Method software/amazon/awssdk/core/SdkField$Builder.memberName:(Ljava/lang/String;)Lsoftware/amazon/awssdk/core/SdkField$Builder;
      77: invokedynamic #123,  0            // InvokeDynamic #4:apply:()Ljava/util/function/Function;
      82: invokestatic  #109                // Method getter:(Ljava/util/function/Function;)Ljava/util/function/Function;
      85: invokevirtual #110                // Method software/amazon/awssdk/core/SdkField$Builder.getter:(Ljava/util/function/Function;)Lsoftware/amazon/awssdk/core/SdkField$Builder;
      88: invokedynamic #124,  0            // InvokeDynamic #5:accept:()Ljava/util/function/BiConsumer;
      93: invokestatic  #112                // Method setter:(Ljava/util/function/BiConsumer;)Ljava/util/function/BiConsumer;
      96: invokevirtual #113                // Method software/amazon/awssdk/core/SdkField$Builder.setter:(Ljava/util/function/BiConsumer;)Lsoftware/amazon/awssdk/core/SdkField$Builder;
      99: iconst_1
     100: anewarray     #114                // class software/amazon/awssdk/core/traits/Trait
     103: dup
     104: iconst_0
     105: invokestatic  #115                // Method software/amazon/awssdk/core/traits/LocationTrait.builder:()Lsoftware/amazon/awssdk/core/traits/LocationTrait$Builder;
     108: getstatic     #116                // Field software/amazon/awssdk/core/protocol/MarshallLocation.PAYLOAD:Lsoftware/amazon/awssdk/core/protocol/MarshallLocation;
     111: invokevirtual #117                // Method software/amazon/awssdk/core/traits/LocationTrait$Builder.location:(Lsoftware/amazon/awssdk/core/protocol/MarshallLocation;)Lsoftware/amazon/awssdk/core/traits/LocationTrait$Builder;
     114: ldc           #75                 // String ImportStatus
     116: invokevirtual #118                // Method software/amazon/awssdk/core/traits/LocationTrait$Builder.locationName:(Ljava/lang/String;)Lsoftware/amazon/awssdk/core/traits/LocationTrait$Builder;
     119: invokevirtual #119                // Method software/amazon/awssdk/core/traits/LocationTrait$Builder.build:()Lsoftware/amazon/awssdk/core/traits/LocationTrait;
     122: aastore
     123: invokevirtual #120                // Method software/amazon/awssdk/core/SdkField$Builder.traits:([Lsoftware/amazon/awssdk/core/traits/Trait;)Lsoftware/amazon/awssdk/core/SdkField$Builder;
     126: invokevirtual #121                // Method software/amazon/awssdk/core/SdkField$Builder.build:()Lsoftware/amazon/awssdk/core/SdkField;
     129: putstatic     #125                // Field IMPORT_STATUS_FIELD:Lsoftware/amazon/awssdk/core/SdkField;
     132: getstatic     #105                // Field software/amazon/awssdk/core/protocol/MarshallingType.STRING:Lsoftware/amazon/awssdk/core/protocol/MarshallingType;
     135: invokestatic  #106                // Method software/amazon/awssdk/core/SdkField.builder:(Lsoftware/amazon/awssdk/core/protocol/MarshallingType;)Lsoftware/amazon/awssdk/core/SdkField$Builder;
     138: ldc           #76                 // String TableArn
     140: invokevirtual #107                // Method software/amazon/awssdk/core/SdkField$Builder.memberName:(Ljava/lang/String;)Lsoftware/amazon/awssdk/core/SdkField$Builder;
     143: invokedynamic #126,  0            // InvokeDynamic #6:apply:()Ljava/util/function/Function;
     148: invokestatic  #109                // Method getter:(Ljava/util/function/Function;)Ljava/util/function/Function;
     151: invokevirtual #110                // Method software/amazon/awssdk/core/SdkField$Builder.getter:(Ljava/util/function/Function;)Lsoftware/amazon/awssdk/core/SdkField$Builder;
     154: invokedynamic #127,  0            // InvokeDynamic #7:accept:()Ljava/util/function/BiConsumer;
     159: invokestatic  #112                // Method setter:(Ljava/util/function/BiConsumer;)Ljava/util/function/BiConsumer;
     162: invokevirtual #113                // Method software/amazon/awssdk/core/SdkField$Builder.setter:(Ljava/util/function/BiConsumer;)Lsoftware/amazon/awssdk/core/SdkField$Builder;
     165: iconst_1
     166: anewarray     #114                // class software/amazon/awssdk/core/traits/Trait
     169: dup
     170: iconst_0
     171: invokestatic  #115                // Method software/amazon/awssdk/core/traits/LocationTrait.builder:()Lsoftware/amazon/awssdk/core/traits/LocationTrait$Builder;
     174: getstatic     #116                // Field software/amazon/awssdk/core/protocol/MarshallLocation.PAYLOAD:Lsoftware/amazon/awssdk/core/protocol/MarshallLocation;
     177: invokevirtual #117                // Method software/amazon/awssdk/core/traits/LocationTrait$Builder.location:(Lsoftware/amazon/awssdk/core/protocol/MarshallLocation;)Lsoftware/amazon/awssdk/core/traits/LocationTrait$Builder;
     180: ldc           #76                 // String TableArn
     182: invokevirtual #118                // Method software/amazon/awssdk/core/traits/LocationTrait$Builder.locationName:(Ljava/lang/String;)Lsoftware/amazon/awssdk/core/traits/LocationTrait$Builder;
     185: invokevirtual #119                // Method software/amazon/awssdk/core/traits/LocationTrait$Builder.build:()Lsoftware/amazon/awssdk/core/traits/LocationTrait;
     188: aastore
     189: invokevirtual #120                // Method software/amazon/awssdk/core/SdkField$Builder.traits:([Lsoftware/amazon/awssdk/core/traits/Trait;)Lsoftware/amazon/awssdk/core/SdkField$Builder;
     192: invokevirtual #121                // Method software/amazon/awssdk/core/SdkField$Builder.build:()Lsoftware/amazon/awssdk/core/SdkField;
     195: putstatic     #128                // Field TABLE_ARN_FIELD:Lsoftware/amazon/awssdk/core/SdkField;
     198: getstatic     #105                // Field software/amazon/awssdk/core/protocol/MarshallingType.STRING:Lsoftware/amazon/awssdk/core/protocol/MarshallingType;
     201: invokestatic  #106                // Method software/amazon/awssdk/core/SdkField.builder:(Lsoftware/amazon/awssdk/core/protocol/MarshallingType;)Lsoftware/amazon/awssdk/core/SdkField$Builder;
     204: ldc           #77                 // String TableId
     206: invokevirtual #107                // Method software/amazon/awssdk/core/SdkField$Builder.memberName:(Ljava/lang/String;)Lsoftware/amazon/awssdk/core/SdkField$Builder;
     209: invokedynamic #129,  0            // InvokeDynamic #8:apply:()Ljava/util/function/Function;
     214: invokestatic  #109                // Method getter:(Ljava/util/function/Function;)Ljava/util/function/Function;
     217: invokevirtual #110                // Method software/amazon/awssdk/core/SdkField$Builder.getter:(Ljava/util/function/Function;)Lsoftware/amazon/awssdk/core/SdkField$Builder;
     220: invokedynamic #130,  0            // InvokeDynamic #9:accept:()Ljava/util/function/BiConsumer;
     225: invokestatic  #112                // Method setter:(Ljava/util/function/BiConsumer;)Ljava/util/function/BiConsumer;
     228: invokevirtual #113                // Method software/amazon/awssdk/core/SdkField$Builder.setter:(Ljava/util/function/BiConsumer;)Lsoftware/amazon/awssdk/core/SdkField$Builder;
     231: iconst_1
     232: anewarray     #114                // class software/amazon/awssdk/core/traits/Trait
     235: dup
     236: iconst_0
     237: invokestatic  #115                // Method software/amazon/awssdk/core/traits/LocationTrait.builder:()Lsoftware/amazon/awssdk/core/traits/LocationTrait$Builder;
     240: getstatic     #116                // Field software/amazon/awssdk/core/protocol/MarshallLocation.PAYLOAD:Lsoftware/amazon/awssdk/core/protocol/MarshallLocation;
     243: invokevirtual #117                // Method software/amazon/awssdk/core/traits/LocationTrait$Builder.location:(Lsoftware/amazon/awssdk/core/protocol/MarshallLocation;)Lsoftware/amazon/awssdk/core/traits/LocationTrait$Builder;
     246: ldc           #77                 // String TableId
     248: invokevirtual #118                // Method software/amazon/awssdk/core/traits/LocationTrait$Builder.locationName:(Ljava/lang/String;)Lsoftware/amazon/awssdk/core/traits/LocationTrait$Builder;
     251: invokevirtual #119                // Method software/amazon/awssdk/core/traits/LocationTrait$Builder.build:()Lsoftware/amazon/awssdk/core/traits/LocationTrait;
     254: aastore
     255: invokevirtual #120                // Method software/amazon/awssdk/core/SdkField$Builder.traits:([Lsoftware/amazon/awssdk/core/traits/Trait;)Lsoftware/amazon/awssdk/core/SdkField$Builder;
     258: invokevirtual #121                // Method software/amazon/awssdk/core/SdkField$Builder.build:()Lsoftware/amazon/awssdk/core/SdkField;
     261: putstatic     #131                // Field TABLE_ID_FIELD:Lsoftware/amazon/awssdk/core/SdkField;
     264: getstatic     #105                // Field software/amazon/awssdk/core/protocol/MarshallingType.STRING:Lsoftware/amazon/awssdk/core/protocol/MarshallingType;
     267: invokestatic  #106                // Method software/amazon/awssdk/core/SdkField.builder:(Lsoftware/amazon/awssdk/core/protocol/MarshallingType;)Lsoftware/amazon/awssdk/core/SdkField$Builder;
     270: ldc           #78                 // String ClientToken
     272: invokevirtual #107                // Method software/amazon/awssdk/core/SdkField$Builder.memberName:(Ljava/lang/String;)Lsoftware/amazon/awssdk/core/SdkField$Builder;
     275: invokedynamic #132,  0            // InvokeDynamic #10:apply:()Ljava/util/function/Function;
     280: invokestatic  #109                // Method getter:(Ljava/util/function/Function;)Ljava/util/function/Function;
     283: invokevirtual #110                // Method software/amazon/awssdk/core/SdkField$Builder.getter:(Ljava/util/function/Function;)Lsoftware/amazon/awssdk/core/SdkField$Builder;
     286: invokedynamic #133,  0            // InvokeDynamic #11:accept:()Ljava/util/function/BiConsumer;
     291: invokestatic  #112                // Method setter:(Ljava/util/function/BiConsumer;)Ljava/util/function/BiConsumer;
     294: invokevirtual #113                // Method software/amazon/awssdk/core/SdkField$Builder.setter:(Ljava/util/function/BiConsumer;)Lsoftware/amazon/awssdk/core/SdkField$Builder;
     297: iconst_1
     298: anewarray     #114                // class software/amazon/awssdk/core/traits/Trait
     301: dup
     302: iconst_0
     303: invokestatic  #115                // Method software/amazon/awssdk/core/traits/LocationTrait.builder:()Lsoftware/amazon/awssdk/core/traits/LocationTrait$Builder;
     306: getstatic     #116                // Field software/amazon/awssdk/core/protocol/MarshallLocation.PAYLOAD:Lsoftware/amazon/awssdk/core/protocol/MarshallLocation;
     309: invokevirtual #117                // Method software/amazon/awssdk/core/traits/LocationTrait$Builder.location:(Lsoftware/amazon/awssdk/core/protocol/MarshallLocation;)Lsoftware/amazon/awssdk/core/traits/LocationTrait$Builder;
     312: ldc           #78                 // String ClientToken
     314: invokevirtual #118                // Method software/amazon/awssdk/core/traits/LocationTrait$Builder.locationName:(Ljava/lang/String;)Lsoftware/amazon/awssdk/core/traits/LocationTrait$Builder;
     317: invokevirtual #119                // Method software/amazon/awssdk/core/traits/LocationTrait$Builder.build:()Lsoftware/amazon/awssdk/core/traits/LocationTrait;
     320: aastore
     321: invokevirtual #120                // Method software/amazon/awssdk/core/SdkField$Builder.traits:([Lsoftware/amazon/awssdk/core/traits/Trait;)Lsoftware/amazon/awssdk/core/SdkField$Builder;
     324: invokevirtual #121                // Method software/amazon/awssdk/core/SdkField$Builder.build:()Lsoftware/amazon/awssdk/core/SdkField;
     327: putstatic     #134                // Field CLIENT_TOKEN_FIELD:Lsoftware/amazon/awssdk/core/SdkField;
     330: getstatic     #135                // Field software/amazon/awssdk/core/protocol/MarshallingType.SDK_POJO:Lsoftware/amazon/awssdk/core/protocol/MarshallingType;
     333: invokestatic  #106                // Method software/amazon/awssdk/core/SdkField.builder:(Lsoftware/amazon/awssdk/core/protocol/MarshallingType;)Lsoftware/amazon/awssdk/core/SdkField$Builder;
     336: ldc           #79                 // String S3BucketSource
     338: invokevirtual #107                // Method software/amazon/awssdk/core/SdkField$Builder.memberName:(Ljava/lang/String;)Lsoftware/amazon/awssdk/core/SdkField$Builder;
     341: invokedynamic #136,  0            // InvokeDynamic #12:apply:()Ljava/util/function/Function;
     346: invokestatic  #109                // Method getter:(Ljava/util/function/Function;)Ljava/util/function/Function;
     349: invokevirtual #110                // Method software/amazon/awssdk/core/SdkField$Builder.getter:(Ljava/util/function/Function;)Lsoftware/amazon/awssdk/core/SdkField$Builder;
     352: invokedynamic #137,  0            // InvokeDynamic #13:accept:()Ljava/util/function/BiConsumer;
     357: invokestatic  #112                // Method setter:(Ljava/util/function/BiConsumer;)Ljava/util/function/BiConsumer;
     360: invokevirtual #113                // Method software/amazon/awssdk/core/SdkField$Builder.setter:(Ljava/util/function/BiConsumer;)Lsoftware/amazon/awssdk/core/SdkField$Builder;
     363: invokedynamic #138,  0            // InvokeDynamic #14:get:()Ljava/util/function/Supplier;
     368: invokevirtual #139                // Method software/amazon/awssdk/core/SdkField$Builder.constructor:(Ljava/util/function/Supplier;)Lsoftware/amazon/awssdk/core/SdkField$Builder;
     371: iconst_1
     372: anewarray     #114                // class software/amazon/awssdk/core/traits/Trait
     375: dup
     376: iconst_0
     377: invokestatic  #115                // Method software/amazon/awssdk/core/traits/LocationTrait.builder:()Lsoftware/amazon/awssdk/core/traits/LocationTrait$Builder;
     380: getstatic     #116                // Field software/amazon/awssdk/core/protocol/MarshallLocation.PAYLOAD:Lsoftware/amazon/awssdk/core/protocol/MarshallLocation;
     383: invokevirtual #117                // Method software/amazon/awssdk/core/traits/LocationTrait$Builder.location:(Lsoftware/amazon/awssdk/core/protocol/MarshallLocation;)Lsoftware/amazon/awssdk/core/traits/LocationTrait$Builder;
     386: ldc           #79                 // String S3BucketSource
     388: invokevirtual #118                // Method software/amazon/awssdk/core/traits/LocationTrait$Builder.locationName:(Ljava/lang/String;)Lsoftware/amazon/awssdk/core/traits/LocationTrait$Builder;
     391: invokevirtual #119                // Method software/amazon/awssdk/core/traits/LocationTrait$Builder.build:()Lsoftware/amazon/awssdk/core/traits/LocationTrait;
     394: aastore
     395: invokevirtual #120                // Method software/amazon/awssdk/core/SdkField$Builder.traits:([Lsoftware/amazon/awssdk/core/traits/Trait;)Lsoftware/amazon/awssdk/core/SdkField$Builder;
     398: invokevirtual #121                // Method software/amazon/awssdk/core/SdkField$Builder.build:()Lsoftware/amazon/awssdk/core/SdkField;
     401: putstatic     #140                // Field S3_BUCKET_SOURCE_FIELD:Lsoftware/amazon/awssdk/core/SdkField;
     404: getstatic     #141                // Field software/amazon/awssdk/core/protocol/MarshallingType.LONG:Lsoftware/amazon/awssdk/core/protocol/MarshallingType;
     407: invokestatic  #106                // Method software/amazon/awssdk/core/SdkField.builder:(Lsoftware/amazon/awssdk/core/protocol/MarshallingType;)Lsoftware/amazon/awssdk/core/SdkField$Builder;
     410: ldc           #80                 // String ErrorCount
     412: invokevirtual #107                // Method software/amazon/awssdk/core/SdkField$Builder.memberName:(Ljava/lang/String;)Lsoftware/amazon/awssdk/core/SdkField$Builder;
     415: invokedynamic #142,  0            // InvokeDynamic #15:apply:()Ljava/util/function/Function;
     420: invokestatic  #109                // Method getter:(Ljava/util/function/Function;)Ljava/util/function/Function;
     423: invokevirtual #110                // Method software/amazon/awssdk/core/SdkField$Builder.getter:(Ljava/util/function/Function;)Lsoftware/amazon/awssdk/core/SdkField$Builder;
     426: invokedynamic #143,  0            // InvokeDynamic #16:accept:()Ljava/util/function/BiConsumer;
     431: invokestatic  #112                // Method setter:(Ljava/util/function/BiConsumer;)Ljava/util/function/BiConsumer;
     434: invokevirtual #113                // Method software/amazon/awssdk/core/SdkField$Builder.setter:(Ljava/util/function/BiConsumer;)Lsoftware/amazon/awssdk/core/SdkField$Builder;
     437: iconst_1
     438: anewarray     #114                // class software/amazon/awssdk/core/traits/Trait
     441: dup
     442: iconst_0
     443: invokestatic  #115                // Method software/amazon/awssdk/core/traits/LocationTrait.builder:()Lsoftware/amazon/awssdk/core/traits/LocationTrait$Builder;
     446: getstatic     #116                // Field software/amazon/awssdk/core/protocol/MarshallLocation.PAYLOAD:Lsoftware/amazon/awssdk/core/protocol/MarshallLocation;
     449: invokevirtual #117                // Method software/amazon/awssdk/core/traits/LocationTrait$Builder.location:(Lsoftware/amazon/awssdk/core/protocol/MarshallLocation;)Lsoftware/amazon/awssdk/core/traits/LocationTrait$Builder;
     452: ldc           #80                 // String ErrorCount
     454: invokevirtual #118                // Method software/amazon/awssdk/core/traits/LocationTrait$Builder.locationName:(Ljava/lang/String;)Lsoftware/amazon/awssdk/core/traits/LocationTrait$Builder;
     457: invokevirtual #119                // Method software/amazon/awssdk/core/traits/LocationTrait$Builder.build:()Lsoftware/amazon/awssdk/core/traits/LocationTrait;
     460: aastore
     461: invokevirtual #120                // Method software/amazon/awssdk/core/SdkField$Builder.traits:([Lsoftware/amazon/awssdk/core/traits/Trait;)Lsoftware/amazon/awssdk/core/SdkField$Builder;
     464: invokevirtual #121                // Method software/amazon/awssdk/core/SdkField$Builder.build:()Lsoftware/amazon/awssdk/core/SdkField;
     467: putstatic     #144                // Field ERROR_COUNT_FIELD:Lsoftware/amazon/awssdk/core/SdkField;
     470: getstatic     #105                // Field software/amazon/awssdk/core/protocol/MarshallingType.STRING:Lsoftware/amazon/awssdk/core/protocol/MarshallingType;
     473: invokestatic  #106                // Method software/amazon/awssdk/core/SdkField.builder:(Lsoftware/amazon/awssdk/core/protocol/MarshallingType;)Lsoftware/amazon/awssdk/core/SdkField$Builder;
     476: ldc           #81                 // String CloudWatchLogGroupArn
     478: invokevirtual #107                // Method software/amazon/awssdk/core/SdkField$Builder.memberName:(Ljava/lang/String;)Lsoftware/amazon/awssdk/core/SdkField$Builder;
     481: invokedynamic #145,  0            // InvokeDynamic #17:apply:()Ljava/util/function/Function;
     486: invokestatic  #109                // Method getter:(Ljava/util/function/Function;)Ljava/util/function/Function;
     489: invokevirtual #110                // Method software/amazon/awssdk/core/SdkField$Builder.getter:(Ljava/util/function/Function;)Lsoftware/amazon/awssdk/core/SdkField$Builder;
     492: invokedynamic #146,  0            // InvokeDynamic #18:accept:()Ljava/util/function/BiConsumer;
     497: invokestatic  #112                // Method setter:(Ljava/util/function/BiConsumer;)Ljava/util/function/BiConsumer;
     500: invokevirtual #113                // Method software/amazon/awssdk/core/SdkField$Builder.setter:(Ljava/util/function/BiConsumer;)Lsoftware/amazon/awssdk/core/SdkField$Builder;
     503: iconst_1
     504: anewarray     #114                // class software/amazon/awssdk/core/traits/Trait
     507: dup
     508: iconst_0
     509: invokestatic  #115                // Method software/amazon/awssdk/core/traits/LocationTrait.builder:()Lsoftware/amazon/awssdk/core/traits/LocationTrait$Builder;
     512: getstatic     #116                // Field software/amazon/awssdk/core/protocol/MarshallLocation.PAYLOAD:Lsoftware/amazon/awssdk/core/protocol/MarshallLocation;
     515: invokevirtual #117                // Method software/amazon/awssdk/core/traits/LocationTrait$Builder.location:(Lsoftware/amazon/awssdk/core/protocol/MarshallLocation;)Lsoftware/amazon/awssdk/core/traits/LocationTrait$Builder;
     518: ldc           #81                 // String CloudWatchLogGroupArn
     520: invokevirtual #118                // Method software/amazon/awssdk/core/traits/LocationTrait$Builder.locationName:(Ljava/lang/String;)Lsoftware/amazon/awssdk/core/traits/LocationTrait$Builder;
     523: invokevirtual #119                // Method software/amazon/awssdk/core/traits/LocationTrait$Builder.build:()Lsoftware/amazon/awssdk/core/traits/LocationTrait;
     526: aastore
     527: invokevirtual #120                // Method software/amazon/awssdk/core/SdkField$Builder.traits:([Lsoftware/amazon/awssdk/core/traits/Trait;)Lsoftware/amazon/awssdk/core/SdkField$Builder;
     530: invokevirtual #121                // Method software/amazon/awssdk/core/SdkField$Builder.build:()Lsoftware/amazon/awssdk/core/SdkField;
     533: putstatic     #147                // Field CLOUD_WATCH_LOG_GROUP_ARN_FIELD:Lsoftware/amazon/awssdk/core/SdkField;
     536: getstatic     #105                // Field software/amazon/awssdk/core/protocol/MarshallingType.STRING:Lsoftware/amazon/awssdk/core/protocol/MarshallingType;
     539: invokestatic  #106                // Method software/amazon/awssdk/core/SdkField.builder:(Lsoftware/amazon/awssdk/core/protocol/MarshallingType;)Lsoftware/amazon/awssdk/core/SdkField$Builder;
     542: ldc           #82                 // String InputFormat
     544: invokevirtual #107                // Method software/amazon/awssdk/core/SdkField$Builder.memberName:(Ljava/lang/String;)Lsoftware/amazon/awssdk/core/SdkField$Builder;
     547: invokedynamic #148,  0            // InvokeDynamic #19:apply:()Ljava/util/function/Function;
     552: invokestatic  #109                // Method getter:(Ljava/util/function/Function;)Ljava/util/function/Function;
     555: invokevirtual #110                // Method software/amazon/awssdk/core/SdkField$Builder.getter:(Ljava/util/function/Function;)Lsoftware/amazon/awssdk/core/SdkField$Builder;
     558: invokedynamic #149,  0            // InvokeDynamic #20:accept:()Ljava/util/function/BiConsumer;
     563: invokestatic  #112                // Method setter:(Ljava/util/function/BiConsumer;)Ljava/util/function/BiConsumer;
     566: invokevirtual #113                // Method software/amazon/awssdk/core/SdkField$Builder.setter:(Ljava/util/function/BiConsumer;)Lsoftware/amazon/awssdk/core/SdkField$Builder;
     569: iconst_1
     570: anewarray     #114                // class software/amazon/awssdk/core/traits/Trait
     573: dup
     574: iconst_0
     575: invokestatic  #115                // Method software/amazon/awssdk/core/traits/LocationTrait.builder:()Lsoftware/amazon/awssdk/core/traits/LocationTrait$Builder;
     578: getstatic     #116                // Field software/amazon/awssdk/core/protocol/MarshallLocation.PAYLOAD:Lsoftware/amazon/awssdk/core/protocol/MarshallLocation;
     581: invokevirtual #117                // Method software/amazon/awssdk/core/traits/LocationTrait$Builder.location:(Lsoftware/amazon/awssdk/core/protocol/MarshallLocation;)Lsoftware/amazon/awssdk/core/traits/LocationTrait$Builder;
     584: ldc           #82                 // String InputFormat
     586: invokevirtual #118                // Method software/amazon/awssdk/core/traits/LocationTrait$Builder.locationName:(Ljava/lang/String;)Lsoftware/amazon/awssdk/core/traits/LocationTrait$Builder;
     589: invokevirtual #119                // Method software/amazon/awssdk/core/traits/LocationTrait$Builder.build:()Lsoftware/amazon/awssdk/core/traits/LocationTrait;
     592: aastore
     593: invokevirtual #120                // Method software/amazon/awssdk/core/SdkField$Builder.traits:([Lsoftware/amazon/awssdk/core/traits/Trait;)Lsoftware/amazon/awssdk/core/SdkField$Builder;
     596: invokevirtual #121                // Method software/amazon/awssdk/core/SdkField$Builder.build:()Lsoftware/amazon/awssdk/core/SdkField;
     599: putstatic     #150                // Field INPUT_FORMAT_FIELD:Lsoftware/amazon/awssdk/core/SdkField;
     602: getstatic     #135                // Field software/amazon/awssdk/core/protocol/MarshallingType.SDK_POJO:Lsoftware/amazon/awssdk/core/protocol/MarshallingType;
     605: invokestatic  #106                // Method software/amazon/awssdk/core/SdkField.builder:(Lsoftware/amazon/awssdk/core/protocol/MarshallingType;)Lsoftware/amazon/awssdk/core/SdkField$Builder;
     608: ldc           #83                 // String InputFormatOptions
     610: invokevirtual #107                // Method software/amazon/awssdk/core/SdkField$Builder.memberName:(Ljava/lang/String;)Lsoftware/amazon/awssdk/core/SdkField$Builder;
     613: invokedynamic #151,  0            // InvokeDynamic #21:apply:()Ljava/util/function/Function;
     618: invokestatic  #109                // Method getter:(Ljava/util/function/Function;)Ljava/util/function/Function;
     621: invokevirtual #110                // Method software/amazon/awssdk/core/SdkField$Builder.getter:(Ljava/util/function/Function;)Lsoftware/amazon/awssdk/core/SdkField$Builder;
     624: invokedynamic #152,  0            // InvokeDynamic #22:accept:()Ljava/util/function/BiConsumer;
     629: invokestatic  #112                // Method setter:(Ljava/util/function/BiConsumer;)Ljava/util/function/BiConsumer;
     632: invokevirtual #113                // Method software/amazon/awssdk/core/SdkField$Builder.setter:(Ljava/util/function/BiConsumer;)Lsoftware/amazon/awssdk/core/SdkField$Builder;
     635: invokedynamic #153,  0            // InvokeDynamic #23:get:()Ljava/util/function/Supplier;
     640: invokevirtual #139                // Method software/amazon/awssdk/core/SdkField$Builder.constructor:(Ljava/util/function/Supplier;)Lsoftware/amazon/awssdk/core/SdkField$Builder;
     643: iconst_1
     644: anewarray     #114                // class software/amazon/awssdk/core/traits/Trait
     647: dup
     648: iconst_0
     649: invokestatic  #115                // Method software/amazon/awssdk/core/traits/LocationTrait.builder:()Lsoftware/amazon/awssdk/core/traits/LocationTrait$Builder;
     652: getstatic     #116                // Field software/amazon/awssdk/core/protocol/MarshallLocation.PAYLOAD:Lsoftware/amazon/awssdk/core/protocol/MarshallLocation;
     655: invokevirtual #117                // Method software/amazon/awssdk/core/traits/LocationTrait$Builder.location:(Lsoftware/amazon/awssdk/core/protocol/MarshallLocation;)Lsoftware/amazon/awssdk/core/traits/LocationTrait$Builder;
     658: ldc           #83                 // String InputFormatOptions
     660: invokevirtual #118                // Method software/amazon/awssdk/core/traits/LocationTrait$Builder.locationName:(Ljava/lang/String;)Lsoftware/amazon/awssdk/core/traits/LocationTrait$Builder;
     663: invokevirtual #119                // Method software/amazon/awssdk/core/traits/LocationTrait$Builder.build:()Lsoftware/amazon/awssdk/core/traits/LocationTrait;
     666: aastore
     667: invokevirtual #120                // Method software/amazon/awssdk/core/SdkField$Builder.traits:([Lsoftware/amazon/awssdk/core/traits/Trait;)Lsoftware/amazon/awssdk/core/SdkField$Builder;
     670: invokevirtual #121                // Method software/amazon/awssdk/core/SdkField$Builder.build:()Lsoftware/amazon/awssdk/core/SdkField;
     673: putstatic     #154                // Field INPUT_FORMAT_OPTIONS_FIELD:Lsoftware/amazon/awssdk/core/SdkField;
     676: getstatic     #105                // Field software/amazon/awssdk/core/protocol/MarshallingType.STRING:Lsoftware/amazon/awssdk/core/protocol/MarshallingType;
     679: invokestatic  #106                // Method software/amazon/awssdk/core/SdkField.builder:(Lsoftware/amazon/awssdk/core/protocol/MarshallingType;)Lsoftware/amazon/awssdk/core/SdkField$Builder;
     682: ldc           #84                 // String InputCompressionType
     684: invokevirtual #107                // Method software/amazon/awssdk/core/SdkField$Builder.memberName:(Ljava/lang/String;)Lsoftware/amazon/awssdk/core/SdkField$Builder;
     687: invokedynamic #155,  0            // InvokeDynamic #24:apply:()Ljava/util/function/Function;
     692: invokestatic  #109                // Method getter:(Ljava/util/function/Function;)Ljava/util/function/Function;
     695: invokevirtual #110                // Method software/amazon/awssdk/core/SdkField$Builder.getter:(Ljava/util/function/Function;)Lsoftware/amazon/awssdk/core/SdkField$Builder;
     698: invokedynamic #156,  0            // InvokeDynamic #25:accept:()Ljava/util/function/BiConsumer;
     703: invokestatic  #112                // Method setter:(Ljava/util/function/BiConsumer;)Ljava/util/function/BiConsumer;
     706: invokevirtual #113                // Method software/amazon/awssdk/core/SdkField$Builder.setter:(Ljava/util/function/BiConsumer;)Lsoftware/amazon/awssdk/core/SdkField$Builder;
     709: iconst_1
     710: anewarray     #114                // class software/amazon/awssdk/core/traits/Trait
     713: dup
     714: iconst_0
     715: invokestatic  #115                // Method software/amazon/awssdk/core/traits/LocationTrait.builder:()Lsoftware/amazon/awssdk/core/traits/LocationTrait$Builder;
     718: getstatic     #116                // Field software/amazon/awssdk/core/protocol/MarshallLocation.PAYLOAD:Lsoftware/amazon/awssdk/core/protocol/MarshallLocation;
     721: invokevirtual #117                // Method software/amazon/awssdk/core/traits/LocationTrait$Builder.location:(Lsoftware/amazon/awssdk/core/protocol/MarshallLocation;)Lsoftware/amazon/awssdk/core/traits/LocationTrait$Builder;
     724: ldc           #84                 // String InputCompressionType
     726: invokevirtual #118                // Method software/amazon/awssdk/core/traits/LocationTrait$Builder.locationName:(Ljava/lang/String;)Lsoftware/amazon/awssdk/core/traits/LocationTrait$Builder;
     729: invokevirtual #119                // Method software/amazon/awssdk/core/traits/LocationTrait$Builder.build:()Lsoftware/amazon/awssdk/core/traits/LocationTrait;
     732: aastore
     733: invokevirtual #120                // Method software/amazon/awssdk/core/SdkField$Builder.traits:([Lsoftware/amazon/awssdk/core/traits/Trait;)Lsoftware/amazon/awssdk/core/SdkField$Builder;
     736: invokevirtual #121                // Method software/amazon/awssdk/core/SdkField$Builder.build:()Lsoftware/amazon/awssdk/core/SdkField;
     739: putstatic     #157                // Field INPUT_COMPRESSION_TYPE_FIELD:Lsoftware/amazon/awssdk/core/SdkField;
     742: getstatic     #135                // Field software/amazon/awssdk/core/protocol/MarshallingType.SDK_POJO:Lsoftware/amazon/awssdk/core/protocol/MarshallingType;
     745: invokestatic  #106                // Method software/amazon/awssdk/core/SdkField.builder:(Lsoftware/amazon/awssdk/core/protocol/MarshallingType;)Lsoftware/amazon/awssdk/core/SdkField$Builder;
     748: ldc           #85                 // String TableCreationParameters
     750: invokevirtual #107                // Method software/amazon/awssdk/core/SdkField$Builder.memberName:(Ljava/lang/String;)Lsoftware/amazon/awssdk/core/SdkField$Builder;
     753: invokedynamic #158,  0            // InvokeDynamic #26:apply:()Ljava/util/function/Function;
     758: invokestatic  #109                // Method getter:(Ljava/util/function/Function;)Ljava/util/function/Function;
     761: invokevirtual #110                // Method software/amazon/awssdk/core/SdkField$Builder.getter:(Ljava/util/function/Function;)Lsoftware/amazon/awssdk/core/SdkField$Builder;
     764: invokedynamic #159,  0            // InvokeDynamic #27:accept:()Ljava/util/function/BiConsumer;
     769: invokestatic  #112                // Method setter:(Ljava/util/function/BiConsumer;)Ljava/util/function/BiConsumer;
     772: invokevirtual #113                // Method software/amazon/awssdk/core/SdkField$Builder.setter:(Ljava/util/function/BiConsumer;)Lsoftware/amazon/awssdk/core/SdkField$Builder;
     775: invokedynamic #160,  0            // InvokeDynamic #28:get:()Ljava/util/function/Supplier;
     780: invokevirtual #139                // Method software/amazon/awssdk/core/SdkField$Builder.constructor:(Ljava/util/function/Supplier;)Lsoftware/amazon/awssdk/core/SdkField$Builder;
     783: iconst_1
     784: anewarray     #114                // class software/amazon/awssdk/core/traits/Trait
     787: dup
     788: iconst_0
     789: invokestatic  #115                // Method software/amazon/awssdk/core/traits/LocationTrait.builder:()Lsoftware/amazon/awssdk/core/traits/LocationTrait$Builder;
     792: getstatic     #116                // Field software/amazon/awssdk/core/protocol/MarshallLocation.PAYLOAD:Lsoftware/amazon/awssdk/core/protocol/MarshallLocation;
     795: invokevirtual #117                // Method software/amazon/awssdk/core/traits/LocationTrait$Builder.location:(Lsoftware/amazon/awssdk/core/protocol/MarshallLocation;)Lsoftware/amazon/awssdk/core/traits/LocationTrait$Builder;
     798: ldc           #85                 // String TableCreationParameters
     800: invokevirtual #118                // Method software/amazon/awssdk/core/traits/LocationTrait$Builder.locationName:(Ljava/lang/String;)Lsoftware/amazon/awssdk/core/traits/LocationTrait$Builder;
     803: invokevirtual #119                // Method software/amazon/awssdk/core/traits/LocationTrait$Builder.build:()Lsoftware/amazon/awssdk/core/traits/LocationTrait;
     806: aastore
     807: invokevirtual #120                // Method software/amazon/awssdk/core/SdkField$Builder.traits:([Lsoftware/amazon/awssdk/core/traits/Trait;)Lsoftware/amazon/awssdk/core/SdkField$Builder;
     810: invokevirtual #121                // Method software/amazon/awssdk/core/SdkField$Builder.build:()Lsoftware/amazon/awssdk/core/SdkField;
     813: putstatic     #161                // Field TABLE_CREATION_PARAMETERS_FIELD:Lsoftware/amazon/awssdk/core/SdkField;
     816: getstatic     #162                // Field software/amazon/awssdk/core/protocol/MarshallingType.INSTANT:Lsoftware/amazon/awssdk/core/protocol/MarshallingType;
     819: invokestatic  #106                // Method software/amazon/awssdk/core/SdkField.builder:(Lsoftware/amazon/awssdk/core/protocol/MarshallingType;)Lsoftware/amazon/awssdk/core/SdkField$Builder;
     822: ldc           #86                 // String StartTime
     824: invokevirtual #107                // Method software/amazon/awssdk/core/SdkField$Builder.memberName:(Ljava/lang/String;)Lsoftware/amazon/awssdk/core/SdkField$Builder;
     827: invokedynamic #163,  0            // InvokeDynamic #29:apply:()Ljava/util/function/Function;
     832: invokestatic  #109                // Method getter:(Ljava/util/function/Function;)Ljava/util/function/Function;
     835: invokevirtual #110                // Method software/amazon/awssdk/core/SdkField$Builder.getter:(Ljava/util/function/Function;)Lsoftware/amazon/awssdk/core/SdkField$Builder;
     838: invokedynamic #164,  0            // InvokeDynamic #30:accept:()Ljava/util/function/BiConsumer;
     843: invokestatic  #112                // Method setter:(Ljava/util/function/BiConsumer;)Ljava/util/function/BiConsumer;
     846: invokevirtual #113                // Method software/amazon/awssdk/core/SdkField$Builder.setter:(Ljava/util/function/BiConsumer;)Lsoftware/amazon/awssdk/core/SdkField$Builder;
     849: iconst_1
     850: anewarray     #114                // class software/amazon/awssdk/core/traits/Trait
     853: dup
     854: iconst_0
     855: invokestatic  #115                // Method software/amazon/awssdk/core/traits/LocationTrait.builder:()Lsoftware/amazon/awssdk/core/traits/LocationTrait$Builder;
     858: getstatic     #116                // Field software/amazon/awssdk/core/protocol/MarshallLocation.PAYLOAD:Lsoftware/amazon/awssdk/core/protocol/MarshallLocation;
     861: invokevirtual #117                // Method software/amazon/awssdk/core/traits/LocationTrait$Builder.location:(Lsoftware/amazon/awssdk/core/protocol/MarshallLocation;)Lsoftware/amazon/awssdk/core/traits/LocationTrait$Builder;
     864: ldc           #86                 // String StartTime
     866: invokevirtual #118                // Method software/amazon/awssdk/core/traits/LocationTrait$Builder.locationName:(Ljava/lang/String;)Lsoftware/amazon/awssdk/core/traits/LocationTrait$Builder;
     869: invokevirtual #119                // Method software/amazon/awssdk/core/traits/LocationTrait$Builder.build:()Lsoftware/amazon/awssdk/core/traits/LocationTrait;
     872: aastore
     873: invokevirtual #120                // Method software/amazon/awssdk/core/SdkField$Builder.traits:([Lsoftware/amazon/awssdk/core/traits/Trait;)Lsoftware/amazon/awssdk/core/SdkField$Builder;
     876: invokevirtual #121                // Method software/amazon/awssdk/core/SdkField$Builder.build:()Lsoftware/amazon/awssdk/core/SdkField;
     879: putstatic     #165                // Field START_TIME_FIELD:Lsoftware/amazon/awssdk/core/SdkField;
     882: getstatic     #162                // Field software/amazon/awssdk/core/protocol/MarshallingType.INSTANT:Lsoftware/amazon/awssdk/core/protocol/MarshallingType;
     885: invokestatic  #106                // Method software/amazon/awssdk/core/SdkField.builder:(Lsoftware/amazon/awssdk/core/protocol/MarshallingType;)Lsoftware/amazon/awssdk/core/SdkField$Builder;
     888: ldc           #87                 // String EndTime
     890: invokevirtual #107                // Method software/amazon/awssdk/core/SdkField$Builder.memberName:(Ljava/lang/String;)Lsoftware/amazon/awssdk/core/SdkField$Builder;
     893: invokedynamic #166,  0            // InvokeDynamic #31:apply:()Ljava/util/function/Function;
     898: invokestatic  #109                // Method getter:(Ljava/util/function/Function;)Ljava/util/function/Function;
     901: invokevirtual #110                // Method software/amazon/awssdk/core/SdkField$Builder.getter:(Ljava/util/function/Function;)Lsoftware/amazon/awssdk/core/SdkField$Builder;
     904: invokedynamic #167,  0            // InvokeDynamic #32:accept:()Ljava/util/function/BiConsumer;
     909: invokestatic  #112                // Method setter:(Ljava/util/function/BiConsumer;)Ljava/util/function/BiConsumer;
     912: invokevirtual #113                // Method software/amazon/awssdk/core/SdkField$Builder.setter:(Ljava/util/function/BiConsumer;)Lsoftware/amazon/awssdk/core/SdkField$Builder;
     915: iconst_1
     916: anewarray     #114                // class software/amazon/awssdk/core/traits/Trait
     919: dup
     920: iconst_0
     921: invokestatic  #115                // Method software/amazon/awssdk/core/traits/LocationTrait.builder:()Lsoftware/amazon/awssdk/core/traits/LocationTrait$Builder;
     924: getstatic     #116                // Field software/amazon/awssdk/core/protocol/MarshallLocation.PAYLOAD:Lsoftware/amazon/awssdk/core/protocol/MarshallLocation;
     927: invokevirtual #117                // Method software/amazon/awssdk/core/traits/LocationTrait$Builder.location:(Lsoftware/amazon/awssdk/core/protocol/MarshallLocation;)Lsoftware/amazon/awssdk/core/traits/LocationTrait$Builder;
     930: ldc           #87                 // String EndTime
     932: invokevirtual #118                // Method software/amazon/awssdk/core/traits/LocationTrait$Builder.locationName:(Ljava/lang/String;)Lsoftware/amazon/awssdk/core/traits/LocationTrait$Builder;
     935: invokevirtual #119                // Method software/amazon/awssdk/core/traits/LocationTrait$Builder.build:()Lsoftware/amazon/awssdk/core/traits/LocationTrait;
     938: aastore
     939: invokevirtual #120                // Method software/amazon/awssdk/core/SdkField$Builder.traits:([Lsoftware/amazon/awssdk/core/traits/Trait;)Lsoftware/amazon/awssdk/core/SdkField$Builder;
     942: invokevirtual #121                // Method software/amazon/awssdk/core/SdkField$Builder.build:()Lsoftware/amazon/awssdk/core/SdkField;
     945: putstatic     #168                // Field END_TIME_FIELD:Lsoftware/amazon/awssdk/core/SdkField;
     948: getstatic     #141                // Field software/amazon/awssdk/core/protocol/MarshallingType.LONG:Lsoftware/amazon/awssdk/core/protocol/MarshallingType;
     951: invokestatic  #106                // Method software/amazon/awssdk/core/SdkField.builder:(Lsoftware/amazon/awssdk/core/protocol/MarshallingType;)Lsoftware/amazon/awssdk/core/SdkField$Builder;
     954: ldc           #88                 // String ProcessedSizeBytes
     956: invokevirtual #107                // Method software/amazon/awssdk/core/SdkField$Builder.memberName:(Ljava/lang/String;)Lsoftware/amazon/awssdk/core/SdkField$Builder;
     959: invokedynamic #169,  0            // InvokeDynamic #33:apply:()Ljava/util/function/Function;
     964: invokestatic  #109                // Method getter:(Ljava/util/function/Function;)Ljava/util/function/Function;
     967: invokevirtual #110                // Method software/amazon/awssdk/core/SdkField$Builder.getter:(Ljava/util/function/Function;)Lsoftware/amazon/awssdk/core/SdkField$Builder;
     970: invokedynamic #170,  0            // InvokeDynamic #34:accept:()Ljava/util/function/BiConsumer;
     975: invokestatic  #112                // Method setter:(Ljava/util/function/BiConsumer;)Ljava/util/function/BiConsumer;
     978: invokevirtual #113                // Method software/amazon/awssdk/core/SdkField$Builder.setter:(Ljava/util/function/BiConsumer;)Lsoftware/amazon/awssdk/core/SdkField$Builder;
     981: iconst_1
     982: anewarray     #114                // class software/amazon/awssdk/core/traits/Trait
     985: dup
     986: iconst_0
     987: invokestatic  #115                // Method software/amazon/awssdk/core/traits/LocationTrait.builder:()Lsoftware/amazon/awssdk/core/traits/LocationTrait$Builder;
     990: getstatic     #116                // Field software/amazon/awssdk/core/protocol/MarshallLocation.PAYLOAD:Lsoftware/amazon/awssdk/core/protocol/MarshallLocation;
     993: invokevirtual #117                // Method software/amazon/awssdk/core/traits/LocationTrait$Builder.location:(Lsoftware/amazon/awssdk/core/protocol/MarshallLocation;)Lsoftware/amazon/awssdk/core/traits/LocationTrait$Builder;
     996: ldc           #88                 // String ProcessedSizeBytes
     998: invokevirtual #118                // Method software/amazon/awssdk/core/traits/LocationTrait$Builder.locationName:(Ljava/lang/String;)Lsoftware/amazon/awssdk/core/traits/LocationTrait$Builder;
    1001: invokevirtual #119                // Method software/amazon/awssdk/core/traits/LocationTrait$Builder.build:()Lsoftware/amazon/awssdk/core/traits/LocationTrait;
    1004: aastore
    1005: invokevirtual #120                // Method software/amazon/awssdk/core/SdkField$Builder.traits:([Lsoftware/amazon/awssdk/core/traits/Trait;)Lsoftware/amazon/awssdk/core/SdkField$Builder;
    1008: invokevirtual #121                // Method software/amazon/awssdk/core/SdkField$Builder.build:()Lsoftware/amazon/awssdk/core/SdkField;
    1011: putstatic     #171                // Field PROCESSED_SIZE_BYTES_FIELD:Lsoftware/amazon/awssdk/core/SdkField;
    1014: getstatic     #141                // Field software/amazon/awssdk/core/protocol/MarshallingType.LONG:Lsoftware/amazon/awssdk/core/protocol/MarshallingType;
    1017: invokestatic  #106                // Method software/amazon/awssdk/core/SdkField.builder:(Lsoftware/amazon/awssdk/core/protocol/MarshallingType;)Lsoftware/amazon/awssdk/core/SdkField$Builder;
    1020: ldc           #89                 // String ProcessedItemCount
    1022: invokevirtual #107                // Method software/amazon/awssdk/core/SdkField$Builder.memberName:(Ljava/lang/String;)Lsoftware/amazon/awssdk/core/SdkField$Builder;
    1025: invokedynamic #172,  0            // InvokeDynamic #35:apply:()Ljava/util/function/Function;
    1030: invokestatic  #109                // Method getter:(Ljava/util/function/Function;)Ljava/util/function/Function;
    1033: invokevirtual #110                // Method software/amazon/awssdk/core/SdkField$Builder.getter:(Ljava/util/function/Function;)Lsoftware/amazon/awssdk/core/SdkField$Builder;
    1036: invokedynamic #173,  0            // InvokeDynamic #36:accept:()Ljava/util/function/BiConsumer;
    1041: invokestatic  #112                // Method setter:(Ljava/util/function/BiConsumer;)Ljava/util/function/BiConsumer;
    1044: invokevirtual #113                // Method software/amazon/awssdk/core/SdkField$Builder.setter:(Ljava/util/function/BiConsumer;)Lsoftware/amazon/awssdk/core/SdkField$Builder;
    1047: iconst_1
    1048: anewarray     #114                // class software/amazon/awssdk/core/traits/Trait
    1051: dup
    1052: iconst_0
    1053: invokestatic  #115                // Method software/amazon/awssdk/core/traits/LocationTrait.builder:()Lsoftware/amazon/awssdk/core/traits/LocationTrait$Builder;
    1056: getstatic     #116                // Field software/amazon/awssdk/core/protocol/MarshallLocation.PAYLOAD:Lsoftware/amazon/awssdk/core/protocol/MarshallLocation;
    1059: invokevirtual #117                // Method software/amazon/awssdk/core/traits/LocationTrait$Builder.location:(Lsoftware/amazon/awssdk/core/protocol/MarshallLocation;)Lsoftware/amazon/awssdk/core/traits/LocationTrait$Builder;
    1062: ldc           #89                 // String ProcessedItemCount
    1064: invokevirtual #118                // Method software/amazon/awssdk/core/traits/LocationTrait$Builder.locationName:(Ljava/lang/String;)Lsoftware/amazon/awssdk/core/traits/LocationTrait$Builder;
    1067: invokevirtual #119                // Method software/amazon/awssdk/core/traits/LocationTrait$Builder.build:()Lsoftware/amazon/awssdk/core/traits/LocationTrait;
    1070: aastore
    1071: invokevirtual #120                // Method software/amazon/awssdk/core/SdkField$Builder.traits:([Lsoftware/amazon/awssdk/core/traits/Trait;)Lsoftware/amazon/awssdk/core/SdkField$Builder;
    1074: invokevirtual #121                // Method software/amazon/awssdk/core/SdkField$Builder.build:()Lsoftware/amazon/awssdk/core/SdkField;
    1077: putstatic     #174                // Field PROCESSED_ITEM_COUNT_FIELD:Lsoftware/amazon/awssdk/core/SdkField;
    1080: getstatic     #141                // Field software/amazon/awssdk/core/protocol/MarshallingType.LONG:Lsoftware/amazon/awssdk/core/protocol/MarshallingType;
    1083: invokestatic  #106                // Method software/amazon/awssdk/core/SdkField.builder:(Lsoftware/amazon/awssdk/core/protocol/MarshallingType;)Lsoftware/amazon/awssdk/core/SdkField$Builder;
    1086: ldc           #90                 // String ImportedItemCount
    1088: invokevirtual #107                // Method software/amazon/awssdk/core/SdkField$Builder.memberName:(Ljava/lang/String;)Lsoftware/amazon/awssdk/core/SdkField$Builder;
    1091: invokedynamic #175,  0            // InvokeDynamic #37:apply:()Ljava/util/function/Function;
    1096: invokestatic  #109                // Method getter:(Ljava/util/function/Function;)Ljava/util/function/Function;
    1099: invokevirtual #110                // Method software/amazon/awssdk/core/SdkField$Builder.getter:(Ljava/util/function/Function;)Lsoftware/amazon/awssdk/core/SdkField$Builder;
    1102: invokedynamic #176,  0            // InvokeDynamic #38:accept:()Ljava/util/function/BiConsumer;
    1107: invokestatic  #112                // Method setter:(Ljava/util/function/BiConsumer;)Ljava/util/function/BiConsumer;
    1110: invokevirtual #113                // Method software/amazon/awssdk/core/SdkField$Builder.setter:(Ljava/util/function/BiConsumer;)Lsoftware/amazon/awssdk/core/SdkField$Builder;
    1113: iconst_1
    1114: anewarray     #114                // class software/amazon/awssdk/core/traits/Trait
    1117: dup
    1118: iconst_0
    1119: invokestatic  #115                // Method software/amazon/awssdk/core/traits/LocationTrait.builder:()Lsoftware/amazon/awssdk/core/traits/LocationTrait$Builder;
    1122: getstatic     #116                // Field software/amazon/awssdk/core/protocol/MarshallLocation.PAYLOAD:Lsoftware/amazon/awssdk/core/protocol/MarshallLocation;
    1125: invokevirtual #117                // Method software/amazon/awssdk/core/traits/LocationTrait$Builder.location:(Lsoftware/amazon/awssdk/core/protocol/MarshallLocation;)Lsoftware/amazon/awssdk/core/traits/LocationTrait$Builder;
    1128: ldc           #90                 // String ImportedItemCount
    1130: invokevirtual #118                // Method software/amazon/awssdk/core/traits/LocationTrait$Builder.locationName:(Ljava/lang/String;)Lsoftware/amazon/awssdk/core/traits/LocationTrait$Builder;
    1133: invokevirtual #119                // Method software/amazon/awssdk/core/traits/LocationTrait$Builder.build:()Lsoftware/amazon/awssdk/core/traits/LocationTrait;
    1136: aastore
    1137: invokevirtual #120                // Method software/amazon/awssdk/core/SdkField$Builder.traits:([Lsoftware/amazon/awssdk/core/traits/Trait;)Lsoftware/amazon/awssdk/core/SdkField$Builder;
    1140: invokevirtual #121                // Method software/amazon/awssdk/core/SdkField$Builder.build:()Lsoftware/amazon/awssdk/core/SdkField;
    1143: putstatic     #177                // Field IMPORTED_ITEM_COUNT_FIELD:Lsoftware/amazon/awssdk/core/SdkField;
    1146: getstatic     #105                // Field software/amazon/awssdk/core/protocol/MarshallingType.STRING:Lsoftware/amazon/awssdk/core/protocol/MarshallingType;
    1149: invokestatic  #106                // Method software/amazon/awssdk/core/SdkField.builder:(Lsoftware/amazon/awssdk/core/protocol/MarshallingType;)Lsoftware/amazon/awssdk/core/SdkField$Builder;
    1152: ldc           #91                 // String FailureCode
    1154: invokevirtual #107                // Method software/amazon/awssdk/core/SdkField$Builder.memberName:(Ljava/lang/String;)Lsoftware/amazon/awssdk/core/SdkField$Builder;
    1157: invokedynamic #178,  0            // InvokeDynamic #39:apply:()Ljava/util/function/Function;
    1162: invokestatic  #109                // Method getter:(Ljava/util/function/Function;)Ljava/util/function/Function;
    1165: invokevirtual #110                // Method software/amazon/awssdk/core/SdkField$Builder.getter:(Ljava/util/function/Function;)Lsoftware/amazon/awssdk/core/SdkField$Builder;
    1168: invokedynamic #179,  0            // InvokeDynamic #40:accept:()Ljava/util/function/BiConsumer;
    1173: invokestatic  #112                // Method setter:(Ljava/util/function/BiConsumer;)Ljava/util/function/BiConsumer;
    1176: invokevirtual #113                // Method software/amazon/awssdk/core/SdkField$Builder.setter:(Ljava/util/function/BiConsumer;)Lsoftware/amazon/awssdk/core/SdkField$Builder;
    1179: iconst_1
    1180: anewarray     #114                // class software/amazon/awssdk/core/traits/Trait
    1183: dup
    1184: iconst_0
    1185: invokestatic  #115                // Method software/amazon/awssdk/core/traits/LocationTrait.builder:()Lsoftware/amazon/awssdk/core/traits/LocationTrait$Builder;
    1188: getstatic     #116                // Field software/amazon/awssdk/core/protocol/MarshallLocation.PAYLOAD:Lsoftware/amazon/awssdk/core/protocol/MarshallLocation;
    1191: invokevirtual #117                // Method software/amazon/awssdk/core/traits/LocationTrait$Builder.location:(Lsoftware/amazon/awssdk/core/protocol/MarshallLocation;)Lsoftware/amazon/awssdk/core/traits/LocationTrait$Builder;
    1194: ldc           #91                 // String FailureCode
    1196: invokevirtual #118                // Method software/amazon/awssdk/core/traits/LocationTrait$Builder.locationName:(Ljava/lang/String;)Lsoftware/amazon/awssdk/core/traits/LocationTrait$Builder;
    1199: invokevirtual #119                // Method software/amazon/awssdk/core/traits/LocationTrait$Builder.build:()Lsoftware/amazon/awssdk/core/traits/LocationTrait;
    1202: aastore
    1203: invokevirtual #120                // Method software/amazon/awssdk/core/SdkField$Builder.traits:([Lsoftware/amazon/awssdk/core/traits/Trait;)Lsoftware/amazon/awssdk/core/SdkField$Builder;
    1206: invokevirtual #121                // Method software/amazon/awssdk/core/SdkField$Builder.build:()Lsoftware/amazon/awssdk/core/SdkField;
    1209: putstatic     #180                // Field FAILURE_CODE_FIELD:Lsoftware/amazon/awssdk/core/SdkField;
    1212: getstatic     #105                // Field software/amazon/awssdk/core/protocol/MarshallingType.STRING:Lsoftware/amazon/awssdk/core/protocol/MarshallingType;
    1215: invokestatic  #106                // Method software/amazon/awssdk/core/SdkField.builder:(Lsoftware/amazon/awssdk/core/protocol/MarshallingType;)Lsoftware/amazon/awssdk/core/SdkField$Builder;
    1218: ldc           #92                 // String FailureMessage
    1220: invokevirtual #107                // Method software/amazon/awssdk/core/SdkField$Builder.memberName:(Ljava/lang/String;)Lsoftware/amazon/awssdk/core/SdkField$Builder;
    1223: invokedynamic #181,  0            // InvokeDynamic #41:apply:()Ljava/util/function/Function;
    1228: invokestatic  #109                // Method getter:(Ljava/util/function/Function;)Ljava/util/function/Function;
    1231: invokevirtual #110                // Method software/amazon/awssdk/core/SdkField$Builder.getter:(Ljava/util/function/Function;)Lsoftware/amazon/awssdk/core/SdkField$Builder;
    1234: invokedynamic #182,  0            // InvokeDynamic #42:accept:()Ljava/util/function/BiConsumer;
    1239: invokestatic  #112                // Method setter:(Ljava/util/function/BiConsumer;)Ljava/util/function/BiConsumer;
    1242: invokevirtual #113                // Method software/amazon/awssdk/core/SdkField$Builder.setter:(Ljava/util/function/BiConsumer;)Lsoftware/amazon/awssdk/core/SdkField$Builder;
    1245: iconst_1
    1246: anewarray     #114                // class software/amazon/awssdk/core/traits/Trait
    1249: dup
    1250: iconst_0
    1251: invokestatic  #115                // Method software/amazon/awssdk/core/traits/LocationTrait.builder:()Lsoftware/amazon/awssdk/core/traits/LocationTrait$Builder;
    1254: getstatic     #116                // Field software/amazon/awssdk/core/protocol/MarshallLocation.PAYLOAD:Lsoftware/amazon/awssdk/core/protocol/MarshallLocation;
    1257: invokevirtual #117                // Method software/amazon/awssdk/core/traits/LocationTrait$Builder.location:(Lsoftware/amazon/awssdk/core/protocol/MarshallLocation;)Lsoftware/amazon/awssdk/core/traits/LocationTrait$Builder;
    1260: ldc           #92                 // String FailureMessage
    1262: invokevirtual #118                // Method software/amazon/awssdk/core/traits/LocationTrait$Builder.locationName:(Ljava/lang/String;)Lsoftware/amazon/awssdk/core/traits/LocationTrait$Builder;
    1265: invokevirtual #119                // Method software/amazon/awssdk/core/traits/LocationTrait$Builder.build:()Lsoftware/amazon/awssdk/core/traits/LocationTrait;
    1268: aastore
    1269: invokevirtual #120                // Method software/amazon/awssdk/core/SdkField$Builder.traits:([Lsoftware/amazon/awssdk/core/traits/Trait;)Lsoftware/amazon/awssdk/core/SdkField$Builder;
    1272: invokevirtual #121                // Method software/amazon/awssdk/core/SdkField$Builder.build:()Lsoftware/amazon/awssdk/core/SdkField;
    1275: putstatic     #183                // Field FAILURE_MESSAGE_FIELD:Lsoftware/amazon/awssdk/core/SdkField;
    1278: bipush        19
    1280: anewarray     #184                // class software/amazon/awssdk/core/SdkField
    1283: dup
    1284: iconst_0
    1285: getstatic     #122                // Field IMPORT_ARN_FIELD:Lsoftware/amazon/awssdk/core/SdkField;
    1288: aastore
    1289: dup
    1290: iconst_1
    1291: getstatic     #125                // Field IMPORT_STATUS_FIELD:Lsoftware/amazon/awssdk/core/SdkField;
    1294: aastore
    1295: dup
    1296: iconst_2
    1297: getstatic     #128                // Field TABLE_ARN_FIELD:Lsoftware/amazon/awssdk/core/SdkField;
    1300: aastore
    1301: dup
    1302: iconst_3
    1303: getstatic     #131                // Field TABLE_ID_FIELD:Lsoftware/amazon/awssdk/core/SdkField;
    1306: aastore
    1307: dup
    1308: iconst_4
    1309: getstatic     #134                // Field CLIENT_TOKEN_FIELD:Lsoftware/amazon/awssdk/core/SdkField;
    1312: aastore
    1313: dup
    1314: iconst_5
    1315: getstatic     #140                // Field S3_BUCKET_SOURCE_FIELD:Lsoftware/amazon/awssdk/core/SdkField;
    1318: aastore
    1319: dup
    1320: bipush        6
    1322: getstatic     #144                // Field ERROR_COUNT_FIELD:Lsoftware/amazon/awssdk/core/SdkField;
    1325: aastore
    1326: dup
    1327: bipush        7
    1329: getstatic     #147                // Field CLOUD_WATCH_LOG_GROUP_ARN_FIELD:Lsoftware/amazon/awssdk/core/SdkField;
    1332: aastore
    1333: dup
    1334: bipush        8
    1336: getstatic     #150                // Field INPUT_FORMAT_FIELD:Lsoftware/amazon/awssdk/core/SdkField;
    1339: aastore
    1340: dup
    1341: bipush        9
    1343: getstatic     #154                // Field INPUT_FORMAT_OPTIONS_FIELD:Lsoftware/amazon/awssdk/core/SdkField;
    1346: aastore
    1347: dup
    1348: bipush        10
    1350: getstatic     #157                // Field INPUT_COMPRESSION_TYPE_FIELD:Lsoftware/amazon/awssdk/core/SdkField;
    1353: aastore
    1354: dup
    1355: bipush        11
    1357: getstatic     #161                // Field TABLE_CREATION_PARAMETERS_FIELD:Lsoftware/amazon/awssdk/core/SdkField;
    1360: aastore
    1361: dup
    1362: bipush        12
    1364: getstatic     #165                // Field START_TIME_FIELD:Lsoftware/amazon/awssdk/core/SdkField;
    1367: aastore
    1368: dup
    1369: bipush        13
    1371: getstatic     #168                // Field END_TIME_FIELD:Lsoftware/amazon/awssdk/core/SdkField;
    1374: aastore
    1375: dup
    1376: bipush        14
    1378: getstatic     #171                // Field PROCESSED_SIZE_BYTES_FIELD:Lsoftware/amazon/awssdk/core/SdkField;
    1381: aastore
    1382: dup
    1383: bipush        15
    1385: getstatic     #174                // Field PROCESSED_ITEM_COUNT_FIELD:Lsoftware/amazon/awssdk/core/SdkField;
    1388: aastore
    1389: dup
    1390: bipush        16
    1392: getstatic     #177                // Field IMPORTED_ITEM_COUNT_FIELD:Lsoftware/amazon/awssdk/core/SdkField;
    1395: aastore
    1396: dup
    1397: bipush        17
    1399: getstatic     #180                // Field FAILURE_CODE_FIELD:Lsoftware/amazon/awssdk/core/SdkField;
    1402: aastore
    1403: dup
    1404: bipush        18
    1406: getstatic     #183                // Field FAILURE_MESSAGE_FIELD:Lsoftware/amazon/awssdk/core/SdkField;
    1409: aastore
    1410: invokestatic  #185                // Method java/util/Arrays.asList:([Ljava/lang/Object;)Ljava/util/List;
    1413: invokestatic  #186                // Method java/util/Collections.unmodifiableList:(Ljava/util/List;)Ljava/util/List;
    1416: putstatic     #1                  // Field SDK_FIELDS:Ljava/util/List;
    1419: return
}
