Compiled from "Shard.java"
final class software.amazon.awssdk.services.dynamodb.model.Shard$BuilderImpl implements software.amazon.awssdk.services.dynamodb.model.Shard$Builder {
  private java.lang.String shardId;

  private software.amazon.awssdk.services.dynamodb.model.SequenceNumberRange sequenceNumberRange;

  private java.lang.String parentShardId;

  private software.amazon.awssdk.services.dynamodb.model.Shard$BuilderImpl();
    Code:
       0: aload_0
       1: invokespecial #6                  // Method java/lang/Object."<init>":()V
       4: return

  private software.amazon.awssdk.services.dynamodb.model.Shard$BuilderImpl(software.amazon.awssdk.services.dynamodb.model.Shard);
    Code:
       0: aload_0
       1: invokespecial #6                  // Method java/lang/Object."<init>":()V
       4: aload_0
       5: aload_1
       6: invokestatic  #7                  // Method software/amazon/awssdk/services/dynamodb/model/Shard.access$500:(Lsoftware/amazon/awssdk/services/dynamodb/model/Shard;)Ljava/lang/String;
       9: invokevirtual #8                  // Method shardId:(Ljava/lang/String;)Lsoftware/amazon/awssdk/services/dynamodb/model/Shard$Builder;
      12: pop
      13: aload_0
      14: aload_1
      15: invokestatic  #9                  // Method software/amazon/awssdk/services/dynamodb/model/Shard.access$600:(Lsoftware/amazon/awssdk/services/dynamodb/model/Shard;)Lsoftware/amazon/awssdk/services/dynamodb/model/SequenceNumberRange;
      18: invokevirtual #10                 // Method sequenceNumberRange:(Lsoftware/amazon/awssdk/services/dynamodb/model/SequenceNumberRange;)Lsoftware/amazon/awssdk/services/dynamodb/model/Shard$Builder;
      21: pop
      22: aload_0
      23: aload_1
      24: invokestatic  #11                 // Method software/amazon/awssdk/services/dynamodb/model/Shard.access$700:(Lsoftware/amazon/awssdk/services/dynamodb/model/Shard;)Ljava/lang/String;
      27: invokevirtual #12                 // Method parentShardId:(Ljava/lang/String;)Lsoftware/amazon/awssdk/services/dynamodb/model/Shard$Builder;
      30: pop
      31: return

  public final java.lang.String getShardId();
    Code:
       0: aload_0
       1: getfield      #5                  // Field shardId:Ljava/lang/String;
       4: areturn

  public final void setShardId(java.lang.String);
    Code:
       0: aload_0
       1: aload_1
       2: putfield      #5                  // Field shardId:Ljava/lang/String;
       5: return

  public final software.amazon.awssdk.services.dynamodb.model.Shard$Builder shardId(java.lang.String);
    Code:
       0: aload_0
       1: aload_1
       2: putfield      #5                  // Field shardId:Ljava/lang/String;
       5: aload_0
       6: areturn

  public final software.amazon.awssdk.services.dynamodb.model.SequenceNumberRange$Builder getSequenceNumberRange();
    Code:
       0: aload_0
       1: getfield      #4                  // Field sequenceNumberRange:Lsoftware/amazon/awssdk/services/dynamodb/model/SequenceNumberRange;
       4: ifnull        17
       7: aload_0
       8: getfield      #4                  // Field sequenceNumberRange:Lsoftware/amazon/awssdk/services/dynamodb/model/SequenceNumberRange;
      11: invokevirtual #13                 // Method software/amazon/awssdk/services/dynamodb/model/SequenceNumberRange.toBuilder:()Lsoftware/amazon/awssdk/services/dynamodb/model/SequenceNumberRange$Builder;
      14: goto          18
      17: aconst_null
      18: areturn

  public final void setSequenceNumberRange(software.amazon.awssdk.services.dynamodb.model.SequenceNumberRange$BuilderImpl);
    Code:
       0: aload_0
       1: aload_1
       2: ifnull        12
       5: aload_1
       6: invokevirtual #14                 // Method software/amazon/awssdk/services/dynamodb/model/SequenceNumberRange$BuilderImpl.build:()Lsoftware/amazon/awssdk/services/dynamodb/model/SequenceNumberRange;
       9: goto          13
      12: aconst_null
      13: putfield      #4                  // Field sequenceNumberRange:Lsoftware/amazon/awssdk/services/dynamodb/model/SequenceNumberRange;
      16: return

  public final software.amazon.awssdk.services.dynamodb.model.Shard$Builder sequenceNumberRange(software.amazon.awssdk.services.dynamodb.model.SequenceNumberRange);
    Code:
       0: aload_0
       1: aload_1
       2: putfield      #4                  // Field sequenceNumberRange:Lsoftware/amazon/awssdk/services/dynamodb/model/SequenceNumberRange;
       5: aload_0
       6: areturn

  public final java.lang.String getParentShardId();
    Code:
       0: aload_0
       1: getfield      #3                  // Field parentShardId:Ljava/lang/String;
       4: areturn

  public final void setParentShardId(java.lang.String);
    Code:
       0: aload_0
       1: aload_1
       2: putfield      #3                  // Field parentShardId:Ljava/lang/String;
       5: return

  public final software.amazon.awssdk.services.dynamodb.model.Shard$Builder parentShardId(java.lang.String);
    Code:
       0: aload_0
       1: aload_1
       2: putfield      #3                  // Field parentShardId:Ljava/lang/String;
       5: aload_0
       6: areturn

  public software.amazon.awssdk.services.dynamodb.model.Shard build();
    Code:
       0: new           #15                 // class software/amazon/awssdk/services/dynamodb/model/Shard
       3: dup
       4: aload_0
       5: aconst_null
       6: invokespecial #16                 // Method software/amazon/awssdk/services/dynamodb/model/Shard."<init>":(Lsoftware/amazon/awssdk/services/dynamodb/model/Shard$BuilderImpl;Lsoftware/amazon/awssdk/services/dynamodb/model/Shard$1;)V
       9: areturn

  public java.util.List<software.amazon.awssdk.core.SdkField<?>> sdkFields();
    Code:
       0: invokestatic  #17                 // Method software/amazon/awssdk/services/dynamodb/model/Shard.access$900:()Ljava/util/List;
       3: areturn

  public java.lang.Object build();
    Code:
       0: aload_0
       1: invokevirtual #18                 // Method build:()Lsoftware/amazon/awssdk/services/dynamodb/model/Shard;
       4: areturn

  static java.lang.String access$000(software.amazon.awssdk.services.dynamodb.model.Shard$BuilderImpl);
    Code:
       0: aload_0
       1: getfield      #5                  // Field shardId:Ljava/lang/String;
       4: areturn

  static software.amazon.awssdk.services.dynamodb.model.SequenceNumberRange access$100(software.amazon.awssdk.services.dynamodb.model.Shard$BuilderImpl);
    Code:
       0: aload_0
       1: getfield      #4                  // Field sequenceNumberRange:Lsoftware/amazon/awssdk/services/dynamodb/model/SequenceNumberRange;
       4: areturn

  static java.lang.String access$200(software.amazon.awssdk.services.dynamodb.model.Shard$BuilderImpl);
    Code:
       0: aload_0
       1: getfield      #3                  // Field parentShardId:Ljava/lang/String;
       4: areturn

  software.amazon.awssdk.services.dynamodb.model.Shard$BuilderImpl(software.amazon.awssdk.services.dynamodb.model.Shard, software.amazon.awssdk.services.dynamodb.model.Shard$1);
    Code:
       0: aload_0
       1: aload_1
       2: invokespecial #2                  // Method "<init>":(Lsoftware/amazon/awssdk/services/dynamodb/model/Shard;)V
       5: return

  software.amazon.awssdk.services.dynamodb.model.Shard$BuilderImpl(software.amazon.awssdk.services.dynamodb.model.Shard$1);
    Code:
       0: aload_0
       1: invokespecial #1                  // Method "<init>":()V
       4: return
}
