Compiled from "StreamDescription.java"
public final class software.amazon.awssdk.services.dynamodb.model.StreamDescription implements software.amazon.awssdk.core.SdkPojo, java.io.Serializable, software.amazon.awssdk.utils.builder.ToCopyableBuilder<software.amazon.awssdk.services.dynamodb.model.StreamDescription$Builder, software.amazon.awssdk.services.dynamodb.model.StreamDescription> {
  private static final software.amazon.awssdk.core.SdkField<java.lang.String> STREAM_ARN_FIELD;

  private static final software.amazon.awssdk.core.SdkField<java.lang.String> STREAM_LABEL_FIELD;

  private static final software.amazon.awssdk.core.SdkField<java.lang.String> STREAM_STATUS_FIELD;

  private static final software.amazon.awssdk.core.SdkField<java.lang.String> STREAM_VIEW_TYPE_FIELD;

  private static final software.amazon.awssdk.core.SdkField<java.time.Instant> CREATION_REQUEST_DATE_TIME_FIELD;

  private static final software.amazon.awssdk.core.SdkField<java.lang.String> TABLE_NAME_FIELD;

  private static final software.amazon.awssdk.core.SdkField<java.util.List<software.amazon.awssdk.services.dynamodb.model.KeySchemaElement>> KEY_SCHEMA_FIELD;

  private static final software.amazon.awssdk.core.SdkField<java.util.List<software.amazon.awssdk.services.dynamodb.model.Shard>> SHARDS_FIELD;

  private static final software.amazon.awssdk.core.SdkField<java.lang.String> LAST_EVALUATED_SHARD_ID_FIELD;

  private static final java.util.List<software.amazon.awssdk.core.SdkField<?>> SDK_FIELDS;

  private static final long serialVersionUID;

  private final java.lang.String streamArn;

  private final java.lang.String streamLabel;

  private final java.lang.String streamStatus;

  private final java.lang.String streamViewType;

  private final java.time.Instant creationRequestDateTime;

  private final java.lang.String tableName;

  private final java.util.List<software.amazon.awssdk.services.dynamodb.model.KeySchemaElement> keySchema;

  private final java.util.List<software.amazon.awssdk.services.dynamodb.model.Shard> shards;

  private final java.lang.String lastEvaluatedShardId;

  private software.amazon.awssdk.services.dynamodb.model.StreamDescription(software.amazon.awssdk.services.dynamodb.model.StreamDescription$BuilderImpl);
    Code:
       0: aload_0
       1: invokespecial #12                 // Method java/lang/Object."<init>":()V
       4: aload_0
       5: aload_1
       6: invokestatic  #13                 // Method software/amazon/awssdk/services/dynamodb/model/StreamDescription$BuilderImpl.access$000:(Lsoftware/amazon/awssdk/services/dynamodb/model/StreamDescription$BuilderImpl;)Ljava/lang/String;
       9: putfield      #11                 // Field streamArn:Ljava/lang/String;
      12: aload_0
      13: aload_1
      14: invokestatic  #14                 // Method software/amazon/awssdk/services/dynamodb/model/StreamDescription$BuilderImpl.access$100:(Lsoftware/amazon/awssdk/services/dynamodb/model/StreamDescription$BuilderImpl;)Ljava/lang/String;
      17: putfield      #10                 // Field streamLabel:Ljava/lang/String;
      20: aload_0
      21: aload_1
      22: invokestatic  #15                 // Method software/amazon/awssdk/services/dynamodb/model/StreamDescription$BuilderImpl.access$200:(Lsoftware/amazon/awssdk/services/dynamodb/model/StreamDescription$BuilderImpl;)Ljava/lang/String;
      25: putfield      #9                  // Field streamStatus:Ljava/lang/String;
      28: aload_0
      29: aload_1
      30: invokestatic  #16                 // Method software/amazon/awssdk/services/dynamodb/model/StreamDescription$BuilderImpl.access$300:(Lsoftware/amazon/awssdk/services/dynamodb/model/StreamDescription$BuilderImpl;)Ljava/lang/String;
      33: putfield      #8                  // Field streamViewType:Ljava/lang/String;
      36: aload_0
      37: aload_1
      38: invokestatic  #17                 // Method software/amazon/awssdk/services/dynamodb/model/StreamDescription$BuilderImpl.access$400:(Lsoftware/amazon/awssdk/services/dynamodb/model/StreamDescription$BuilderImpl;)Ljava/time/Instant;
      41: putfield      #7                  // Field creationRequestDateTime:Ljava/time/Instant;
      44: aload_0
      45: aload_1
      46: invokestatic  #18                 // Method software/amazon/awssdk/services/dynamodb/model/StreamDescription$BuilderImpl.access$500:(Lsoftware/amazon/awssdk/services/dynamodb/model/StreamDescription$BuilderImpl;)Ljava/lang/String;
      49: putfield      #6                  // Field tableName:Ljava/lang/String;
      52: aload_0
      53: aload_1
      54: invokestatic  #19                 // Method software/amazon/awssdk/services/dynamodb/model/StreamDescription$BuilderImpl.access$600:(Lsoftware/amazon/awssdk/services/dynamodb/model/StreamDescription$BuilderImpl;)Ljava/util/List;
      57: putfield      #5                  // Field keySchema:Ljava/util/List;
      60: aload_0
      61: aload_1
      62: invokestatic  #20                 // Method software/amazon/awssdk/services/dynamodb/model/StreamDescription$BuilderImpl.access$700:(Lsoftware/amazon/awssdk/services/dynamodb/model/StreamDescription$BuilderImpl;)Ljava/util/List;
      65: putfield      #4                  // Field shards:Ljava/util/List;
      68: aload_0
      69: aload_1
      70: invokestatic  #21                 // Method software/amazon/awssdk/services/dynamodb/model/StreamDescription$BuilderImpl.access$800:(Lsoftware/amazon/awssdk/services/dynamodb/model/StreamDescription$BuilderImpl;)Ljava/lang/String;
      73: putfield      #3                  // Field lastEvaluatedShardId:Ljava/lang/String;
      76: return

  public final java.lang.String streamArn();
    Code:
       0: aload_0
       1: getfield      #11                 // Field streamArn:Ljava/lang/String;
       4: areturn

  public final java.lang.String streamLabel();
    Code:
       0: aload_0
       1: getfield      #10                 // Field streamLabel:Ljava/lang/String;
       4: areturn

  public final software.amazon.awssdk.services.dynamodb.model.StreamStatus streamStatus();
    Code:
       0: aload_0
       1: getfield      #9                  // Field streamStatus:Ljava/lang/String;
       4: invokestatic  #22                 // Method software/amazon/awssdk/services/dynamodb/model/StreamStatus.fromValue:(Ljava/lang/String;)Lsoftware/amazon/awssdk/services/dynamodb/model/StreamStatus;
       7: areturn

  public final java.lang.String streamStatusAsString();
    Code:
       0: aload_0
       1: getfield      #9                  // Field streamStatus:Ljava/lang/String;
       4: areturn

  public final software.amazon.awssdk.services.dynamodb.model.StreamViewType streamViewType();
    Code:
       0: aload_0
       1: getfield      #8                  // Field streamViewType:Ljava/lang/String;
       4: invokestatic  #23                 // Method software/amazon/awssdk/services/dynamodb/model/StreamViewType.fromValue:(Ljava/lang/String;)Lsoftware/amazon/awssdk/services/dynamodb/model/StreamViewType;
       7: areturn

  public final java.lang.String streamViewTypeAsString();
    Code:
       0: aload_0
       1: getfield      #8                  // Field streamViewType:Ljava/lang/String;
       4: areturn

  public final java.time.Instant creationRequestDateTime();
    Code:
       0: aload_0
       1: getfield      #7                  // Field creationRequestDateTime:Ljava/time/Instant;
       4: areturn

  public final java.lang.String tableName();
    Code:
       0: aload_0
       1: getfield      #6                  // Field tableName:Ljava/lang/String;
       4: areturn

  public final boolean hasKeySchema();
    Code:
       0: aload_0
       1: getfield      #5                  // Field keySchema:Ljava/util/List;
       4: ifnull        21
       7: aload_0
       8: getfield      #5                  // Field keySchema:Ljava/util/List;
      11: instanceof    #24                 // class software/amazon/awssdk/core/util/SdkAutoConstructList
      14: ifne          21
      17: iconst_1
      18: goto          22
      21: iconst_0
      22: ireturn

  public final java.util.List<software.amazon.awssdk.services.dynamodb.model.KeySchemaElement> keySchema();
    Code:
       0: aload_0
       1: getfield      #5                  // Field keySchema:Ljava/util/List;
       4: areturn

  public final boolean hasShards();
    Code:
       0: aload_0
       1: getfield      #4                  // Field shards:Ljava/util/List;
       4: ifnull        21
       7: aload_0
       8: getfield      #4                  // Field shards:Ljava/util/List;
      11: instanceof    #24                 // class software/amazon/awssdk/core/util/SdkAutoConstructList
      14: ifne          21
      17: iconst_1
      18: goto          22
      21: iconst_0
      22: ireturn

  public final java.util.List<software.amazon.awssdk.services.dynamodb.model.Shard> shards();
    Code:
       0: aload_0
       1: getfield      #4                  // Field shards:Ljava/util/List;
       4: areturn

  public final java.lang.String lastEvaluatedShardId();
    Code:
       0: aload_0
       1: getfield      #3                  // Field lastEvaluatedShardId:Ljava/lang/String;
       4: areturn

  public software.amazon.awssdk.services.dynamodb.model.StreamDescription$Builder toBuilder();
    Code:
       0: new           #25                 // class software/amazon/awssdk/services/dynamodb/model/StreamDescription$BuilderImpl
       3: dup
       4: aload_0
       5: aconst_null
       6: invokespecial #26                 // Method software/amazon/awssdk/services/dynamodb/model/StreamDescription$BuilderImpl."<init>":(Lsoftware/amazon/awssdk/services/dynamodb/model/StreamDescription;Lsoftware/amazon/awssdk/services/dynamodb/model/StreamDescription$1;)V
       9: areturn

  public static software.amazon.awssdk.services.dynamodb.model.StreamDescription$Builder builder();
    Code:
       0: new           #25                 // class software/amazon/awssdk/services/dynamodb/model/StreamDescription$BuilderImpl
       3: dup
       4: aconst_null
       5: invokespecial #27                 // Method software/amazon/awssdk/services/dynamodb/model/StreamDescription$BuilderImpl."<init>":(Lsoftware/amazon/awssdk/services/dynamodb/model/StreamDescription$1;)V
       8: areturn

  public static java.lang.Class<? extends software.amazon.awssdk.services.dynamodb.model.StreamDescription$Builder> serializableBuilderClass();
    Code:
       0: ldc           #25                 // class software/amazon/awssdk/services/dynamodb/model/StreamDescription$BuilderImpl
       2: areturn

  public final int hashCode();
    Code:
       0: iconst_1
       1: istore_1
       2: bipush        31
       4: iload_1
       5: imul
       6: aload_0
       7: invokevirtual #28                 // Method streamArn:()Ljava/lang/String;
      10: invokestatic  #29                 // Method java/util/Objects.hashCode:(Ljava/lang/Object;)I
      13: iadd
      14: istore_1
      15: bipush        31
      17: iload_1
      18: imul
      19: aload_0
      20: invokevirtual #30                 // Method streamLabel:()Ljava/lang/String;
      23: invokestatic  #29                 // Method java/util/Objects.hashCode:(Ljava/lang/Object;)I
      26: iadd
      27: istore_1
      28: bipush        31
      30: iload_1
      31: imul
      32: aload_0
      33: invokevirtual #31                 // Method streamStatusAsString:()Ljava/lang/String;
      36: invokestatic  #29                 // Method java/util/Objects.hashCode:(Ljava/lang/Object;)I
      39: iadd
      40: istore_1
      41: bipush        31
      43: iload_1
      44: imul
      45: aload_0
      46: invokevirtual #32                 // Method streamViewTypeAsString:()Ljava/lang/String;
      49: invokestatic  #29                 // Method java/util/Objects.hashCode:(Ljava/lang/Object;)I
      52: iadd
      53: istore_1
      54: bipush        31
      56: iload_1
      57: imul
      58: aload_0
      59: invokevirtual #33                 // Method creationRequestDateTime:()Ljava/time/Instant;
      62: invokestatic  #29                 // Method java/util/Objects.hashCode:(Ljava/lang/Object;)I
      65: iadd
      66: istore_1
      67: bipush        31
      69: iload_1
      70: imul
      71: aload_0
      72: invokevirtual #34                 // Method tableName:()Ljava/lang/String;
      75: invokestatic  #29                 // Method java/util/Objects.hashCode:(Ljava/lang/Object;)I
      78: iadd
      79: istore_1
      80: bipush        31
      82: iload_1
      83: imul
      84: aload_0
      85: invokevirtual #35                 // Method hasKeySchema:()Z
      88: ifeq          98
      91: aload_0
      92: invokevirtual #36                 // Method keySchema:()Ljava/util/List;
      95: goto          99
      98: aconst_null
      99: invokestatic  #29                 // Method java/util/Objects.hashCode:(Ljava/lang/Object;)I
     102: iadd
     103: istore_1
     104: bipush        31
     106: iload_1
     107: imul
     108: aload_0
     109: invokevirtual #37                 // Method hasShards:()Z
     112: ifeq          122
     115: aload_0
     116: invokevirtual #38                 // Method shards:()Ljava/util/List;
     119: goto          123
     122: aconst_null
     123: invokestatic  #29                 // Method java/util/Objects.hashCode:(Ljava/lang/Object;)I
     126: iadd
     127: istore_1
     128: bipush        31
     130: iload_1
     131: imul
     132: aload_0
     133: invokevirtual #39                 // Method lastEvaluatedShardId:()Ljava/lang/String;
     136: invokestatic  #29                 // Method java/util/Objects.hashCode:(Ljava/lang/Object;)I
     139: iadd
     140: istore_1
     141: iload_1
     142: ireturn

  public final boolean equals(java.lang.Object);
    Code:
       0: aload_0
       1: aload_1
       2: invokevirtual #40                 // Method equalsBySdkFields:(Ljava/lang/Object;)Z
       5: ireturn

  public final boolean equalsBySdkFields(java.lang.Object);
    Code:
       0: aload_0
       1: aload_1
       2: if_acmpne     7
       5: iconst_1
       6: ireturn
       7: aload_1
       8: ifnonnull     13
      11: iconst_0
      12: ireturn
      13: aload_1
      14: instanceof    #41                 // class software/amazon/awssdk/services/dynamodb/model/StreamDescription
      17: ifne          22
      20: iconst_0
      21: ireturn
      22: aload_1
      23: checkcast     #41                 // class software/amazon/awssdk/services/dynamodb/model/StreamDescription
      26: astore_2
      27: aload_0
      28: invokevirtual #28                 // Method streamArn:()Ljava/lang/String;
      31: aload_2
      32: invokevirtual #28                 // Method streamArn:()Ljava/lang/String;
      35: invokestatic  #42                 // Method java/util/Objects.equals:(Ljava/lang/Object;Ljava/lang/Object;)Z
      38: ifeq          179
      41: aload_0
      42: invokevirtual #30                 // Method streamLabel:()Ljava/lang/String;
      45: aload_2
      46: invokevirtual #30                 // Method streamLabel:()Ljava/lang/String;
      49: invokestatic  #42                 // Method java/util/Objects.equals:(Ljava/lang/Object;Ljava/lang/Object;)Z
      52: ifeq          179
      55: aload_0
      56: invokevirtual #31                 // Method streamStatusAsString:()Ljava/lang/String;
      59: aload_2
      60: invokevirtual #31                 // Method streamStatusAsString:()Ljava/lang/String;
      63: invokestatic  #42                 // Method java/util/Objects.equals:(Ljava/lang/Object;Ljava/lang/Object;)Z
      66: ifeq          179
      69: aload_0
      70: invokevirtual #32                 // Method streamViewTypeAsString:()Ljava/lang/String;
      73: aload_2
      74: invokevirtual #32                 // Method streamViewTypeAsString:()Ljava/lang/String;
      77: invokestatic  #42                 // Method java/util/Objects.equals:(Ljava/lang/Object;Ljava/lang/Object;)Z
      80: ifeq          179
      83: aload_0
      84: invokevirtual #33                 // Method creationRequestDateTime:()Ljava/time/Instant;
      87: aload_2
      88: invokevirtual #33                 // Method creationRequestDateTime:()Ljava/time/Instant;
      91: invokestatic  #42                 // Method java/util/Objects.equals:(Ljava/lang/Object;Ljava/lang/Object;)Z
      94: ifeq          179
      97: aload_0
      98: invokevirtual #34                 // Method tableName:()Ljava/lang/String;
     101: aload_2
     102: invokevirtual #34                 // Method tableName:()Ljava/lang/String;
     105: invokestatic  #42                 // Method java/util/Objects.equals:(Ljava/lang/Object;Ljava/lang/Object;)Z
     108: ifeq          179
     111: aload_0
     112: invokevirtual #35                 // Method hasKeySchema:()Z
     115: aload_2
     116: invokevirtual #35                 // Method hasKeySchema:()Z
     119: if_icmpne     179
     122: aload_0
     123: invokevirtual #36                 // Method keySchema:()Ljava/util/List;
     126: aload_2
     127: invokevirtual #36                 // Method keySchema:()Ljava/util/List;
     130: invokestatic  #42                 // Method java/util/Objects.equals:(Ljava/lang/Object;Ljava/lang/Object;)Z
     133: ifeq          179
     136: aload_0
     137: invokevirtual #37                 // Method hasShards:()Z
     140: aload_2
     141: invokevirtual #37                 // Method hasShards:()Z
     144: if_icmpne     179
     147: aload_0
     148: invokevirtual #38                 // Method shards:()Ljava/util/List;
     151: aload_2
     152: invokevirtual #38                 // Method shards:()Ljava/util/List;
     155: invokestatic  #42                 // Method java/util/Objects.equals:(Ljava/lang/Object;Ljava/lang/Object;)Z
     158: ifeq          179
     161: aload_0
     162: invokevirtual #39                 // Method lastEvaluatedShardId:()Ljava/lang/String;
     165: aload_2
     166: invokevirtual #39                 // Method lastEvaluatedShardId:()Ljava/lang/String;
     169: invokestatic  #42                 // Method java/util/Objects.equals:(Ljava/lang/Object;Ljava/lang/Object;)Z
     172: ifeq          179
     175: iconst_1
     176: goto          180
     179: iconst_0
     180: ireturn

  public final java.lang.String toString();
    Code:
       0: ldc           #43                 // String StreamDescription
       2: invokestatic  #44                 // Method software/amazon/awssdk/utils/ToString.builder:(Ljava/lang/String;)Lsoftware/amazon/awssdk/utils/ToString;
       5: ldc           #45                 // String StreamArn
       7: aload_0
       8: invokevirtual #28                 // Method streamArn:()Ljava/lang/String;
      11: invokevirtual #46                 // Method software/amazon/awssdk/utils/ToString.add:(Ljava/lang/String;Ljava/lang/Object;)Lsoftware/amazon/awssdk/utils/ToString;
      14: ldc           #47                 // String StreamLabel
      16: aload_0
      17: invokevirtual #30                 // Method streamLabel:()Ljava/lang/String;
      20: invokevirtual #46                 // Method software/amazon/awssdk/utils/ToString.add:(Ljava/lang/String;Ljava/lang/Object;)Lsoftware/amazon/awssdk/utils/ToString;
      23: ldc           #48                 // String StreamStatus
      25: aload_0
      26: invokevirtual #31                 // Method streamStatusAsString:()Ljava/lang/String;
      29: invokevirtual #46                 // Method software/amazon/awssdk/utils/ToString.add:(Ljava/lang/String;Ljava/lang/Object;)Lsoftware/amazon/awssdk/utils/ToString;
      32: ldc           #49                 // String StreamViewType
      34: aload_0
      35: invokevirtual #32                 // Method streamViewTypeAsString:()Ljava/lang/String;
      38: invokevirtual #46                 // Method software/amazon/awssdk/utils/ToString.add:(Ljava/lang/String;Ljava/lang/Object;)Lsoftware/amazon/awssdk/utils/ToString;
      41: ldc           #50                 // String CreationRequestDateTime
      43: aload_0
      44: invokevirtual #33                 // Method creationRequestDateTime:()Ljava/time/Instant;
      47: invokevirtual #46                 // Method software/amazon/awssdk/utils/ToString.add:(Ljava/lang/String;Ljava/lang/Object;)Lsoftware/amazon/awssdk/utils/ToString;
      50: ldc           #51                 // String TableName
      52: aload_0
      53: invokevirtual #34                 // Method tableName:()Ljava/lang/String;
      56: invokevirtual #46                 // Method software/amazon/awssdk/utils/ToString.add:(Ljava/lang/String;Ljava/lang/Object;)Lsoftware/amazon/awssdk/utils/ToString;
      59: ldc           #52                 // String KeySchema
      61: aload_0
      62: invokevirtual #35                 // Method hasKeySchema:()Z
      65: ifeq          75
      68: aload_0
      69: invokevirtual #36                 // Method keySchema:()Ljava/util/List;
      72: goto          76
      75: aconst_null
      76: invokevirtual #46                 // Method software/amazon/awssdk/utils/ToString.add:(Ljava/lang/String;Ljava/lang/Object;)Lsoftware/amazon/awssdk/utils/ToString;
      79: ldc           #53                 // String Shards
      81: aload_0
      82: invokevirtual #37                 // Method hasShards:()Z
      85: ifeq          95
      88: aload_0
      89: invokevirtual #38                 // Method shards:()Ljava/util/List;
      92: goto          96
      95: aconst_null
      96: invokevirtual #46                 // Method software/amazon/awssdk/utils/ToString.add:(Ljava/lang/String;Ljava/lang/Object;)Lsoftware/amazon/awssdk/utils/ToString;
      99: ldc           #54                 // String LastEvaluatedShardId
     101: aload_0
     102: invokevirtual #39                 // Method lastEvaluatedShardId:()Ljava/lang/String;
     105: invokevirtual #46                 // Method software/amazon/awssdk/utils/ToString.add:(Ljava/lang/String;Ljava/lang/Object;)Lsoftware/amazon/awssdk/utils/ToString;
     108: invokevirtual #55                 // Method software/amazon/awssdk/utils/ToString.build:()Ljava/lang/String;
     111: areturn

  public final <T> java.util.Optional<T> getValueForField(java.lang.String, java.lang.Class<T>);
    Code:
       0: aload_1
       1: astore_3
       2: iconst_m1
       3: istore        4
       5: aload_3
       6: invokevirtual #56                 // Method java/lang/String.hashCode:()I
       9: lookupswitch  { // 9
           -2002904316: 214
           -1873727925: 152
           -1819699083: 198
           -1267089486: 122
           -1017735372: 107
               -303936: 182
              15250265: 167
            1688314525: 92
            1974887231: 137
               default: 227
          }
      92: aload_3
      93: ldc           #45                 // String StreamArn
      95: invokevirtual #57                 // Method java/lang/String.equals:(Ljava/lang/Object;)Z
      98: ifeq          227
     101: iconst_0
     102: istore        4
     104: goto          227
     107: aload_3
     108: ldc           #47                 // String StreamLabel
     110: invokevirtual #57                 // Method java/lang/String.equals:(Ljava/lang/Object;)Z
     113: ifeq          227
     116: iconst_1
     117: istore        4
     119: goto          227
     122: aload_3
     123: ldc           #48                 // String StreamStatus
     125: invokevirtual #57                 // Method java/lang/String.equals:(Ljava/lang/Object;)Z
     128: ifeq          227
     131: iconst_2
     132: istore        4
     134: goto          227
     137: aload_3
     138: ldc           #49                 // String StreamViewType
     140: invokevirtual #57                 // Method java/lang/String.equals:(Ljava/lang/Object;)Z
     143: ifeq          227
     146: iconst_3
     147: istore        4
     149: goto          227
     152: aload_3
     153: ldc           #50                 // String CreationRequestDateTime
     155: invokevirtual #57                 // Method java/lang/String.equals:(Ljava/lang/Object;)Z
     158: ifeq          227
     161: iconst_4
     162: istore        4
     164: goto          227
     167: aload_3
     168: ldc           #51                 // String TableName
     170: invokevirtual #57                 // Method java/lang/String.equals:(Ljava/lang/Object;)Z
     173: ifeq          227
     176: iconst_5
     177: istore        4
     179: goto          227
     182: aload_3
     183: ldc           #52                 // String KeySchema
     185: invokevirtual #57                 // Method java/lang/String.equals:(Ljava/lang/Object;)Z
     188: ifeq          227
     191: bipush        6
     193: istore        4
     195: goto          227
     198: aload_3
     199: ldc           #53                 // String Shards
     201: invokevirtual #57                 // Method java/lang/String.equals:(Ljava/lang/Object;)Z
     204: ifeq          227
     207: bipush        7
     209: istore        4
     211: goto          227
     214: aload_3
     215: ldc           #54                 // String LastEvaluatedShardId
     217: invokevirtual #57                 // Method java/lang/String.equals:(Ljava/lang/Object;)Z
     220: ifeq          227
     223: bipush        8
     225: istore        4
     227: iload         4
     229: tableswitch   { // 0 to 8
                     0: 280
                     1: 292
                     2: 304
                     3: 316
                     4: 328
                     5: 340
                     6: 352
                     7: 364
                     8: 376
               default: 388
          }
     280: aload_2
     281: aload_0
     282: invokevirtual #28                 // Method streamArn:()Ljava/lang/String;
     285: invokevirtual #58                 // Method java/lang/Class.cast:(Ljava/lang/Object;)Ljava/lang/Object;
     288: invokestatic  #59                 // Method java/util/Optional.ofNullable:(Ljava/lang/Object;)Ljava/util/Optional;
     291: areturn
     292: aload_2
     293: aload_0
     294: invokevirtual #30                 // Method streamLabel:()Ljava/lang/String;
     297: invokevirtual #58                 // Method java/lang/Class.cast:(Ljava/lang/Object;)Ljava/lang/Object;
     300: invokestatic  #59                 // Method java/util/Optional.ofNullable:(Ljava/lang/Object;)Ljava/util/Optional;
     303: areturn
     304: aload_2
     305: aload_0
     306: invokevirtual #31                 // Method streamStatusAsString:()Ljava/lang/String;
     309: invokevirtual #58                 // Method java/lang/Class.cast:(Ljava/lang/Object;)Ljava/lang/Object;
     312: invokestatic  #59                 // Method java/util/Optional.ofNullable:(Ljava/lang/Object;)Ljava/util/Optional;
     315: areturn
     316: aload_2
     317: aload_0
     318: invokevirtual #32                 // Method streamViewTypeAsString:()Ljava/lang/String;
     321: invokevirtual #58                 // Method java/lang/Class.cast:(Ljava/lang/Object;)Ljava/lang/Object;
     324: invokestatic  #59                 // Method java/util/Optional.ofNullable:(Ljava/lang/Object;)Ljava/util/Optional;
     327: areturn
     328: aload_2
     329: aload_0
     330: invokevirtual #33                 // Method creationRequestDateTime:()Ljava/time/Instant;
     333: invokevirtual #58                 // Method java/lang/Class.cast:(Ljava/lang/Object;)Ljava/lang/Object;
     336: invokestatic  #59                 // Method java/util/Optional.ofNullable:(Ljava/lang/Object;)Ljava/util/Optional;
     339: areturn
     340: aload_2
     341: aload_0
     342: invokevirtual #34                 // Method tableName:()Ljava/lang/String;
     345: invokevirtual #58                 // Method java/lang/Class.cast:(Ljava/lang/Object;)Ljava/lang/Object;
     348: invokestatic  #59                 // Method java/util/Optional.ofNullable:(Ljava/lang/Object;)Ljava/util/Optional;
     351: areturn
     352: aload_2
     353: aload_0
     354: invokevirtual #36                 // Method keySchema:()Ljava/util/List;
     357: invokevirtual #58                 // Method java/lang/Class.cast:(Ljava/lang/Object;)Ljava/lang/Object;
     360: invokestatic  #59                 // Method java/util/Optional.ofNullable:(Ljava/lang/Object;)Ljava/util/Optional;
     363: areturn
     364: aload_2
     365: aload_0
     366: invokevirtual #38                 // Method shards:()Ljava/util/List;
     369: invokevirtual #58                 // Method java/lang/Class.cast:(Ljava/lang/Object;)Ljava/lang/Object;
     372: invokestatic  #59                 // Method java/util/Optional.ofNullable:(Ljava/lang/Object;)Ljava/util/Optional;
     375: areturn
     376: aload_2
     377: aload_0
     378: invokevirtual #39                 // Method lastEvaluatedShardId:()Ljava/lang/String;
     381: invokevirtual #58                 // Method java/lang/Class.cast:(Ljava/lang/Object;)Ljava/lang/Object;
     384: invokestatic  #59                 // Method java/util/Optional.ofNullable:(Ljava/lang/Object;)Ljava/util/Optional;
     387: areturn
     388: invokestatic  #60                 // Method java/util/Optional.empty:()Ljava/util/Optional;
     391: areturn

  public final java.util.List<software.amazon.awssdk.core.SdkField<?>> sdkFields();
    Code:
       0: getstatic     #1                  // Field SDK_FIELDS:Ljava/util/List;
       3: areturn

  private static <T> java.util.function.Function<java.lang.Object, T> getter(java.util.function.Function<software.amazon.awssdk.services.dynamodb.model.StreamDescription, T>);
    Code:
       0: aload_0
       1: invokedynamic #61,  0             // InvokeDynamic #0:apply:(Ljava/util/function/Function;)Ljava/util/function/Function;
       6: areturn

  private static <T> java.util.function.BiConsumer<java.lang.Object, T> setter(java.util.function.BiConsumer<software.amazon.awssdk.services.dynamodb.model.StreamDescription$Builder, T>);
    Code:
       0: aload_0
       1: invokedynamic #62,  0             // InvokeDynamic #1:accept:(Ljava/util/function/BiConsumer;)Ljava/util/function/BiConsumer;
       6: areturn

  public software.amazon.awssdk.utils.builder.CopyableBuilder toBuilder();
    Code:
       0: aload_0
       1: invokevirtual #63                 // Method toBuilder:()Lsoftware/amazon/awssdk/services/dynamodb/model/StreamDescription$Builder;
       4: areturn

  private static void lambda$setter$1(java.util.function.BiConsumer, java.lang.Object, java.lang.Object);
    Code:
       0: aload_0
       1: aload_1
       2: checkcast     #64                 // class software/amazon/awssdk/services/dynamodb/model/StreamDescription$Builder
       5: aload_2
       6: invokeinterface #65,  3           // InterfaceMethod java/util/function/BiConsumer.accept:(Ljava/lang/Object;Ljava/lang/Object;)V
      11: return

  private static java.lang.Object lambda$getter$0(java.util.function.Function, java.lang.Object);
    Code:
       0: aload_0
       1: aload_1
       2: checkcast     #41                 // class software/amazon/awssdk/services/dynamodb/model/StreamDescription
       5: invokeinterface #66,  2           // InterfaceMethod java/util/function/Function.apply:(Ljava/lang/Object;)Ljava/lang/Object;
      10: areturn

  static java.lang.String access$1100(software.amazon.awssdk.services.dynamodb.model.StreamDescription);
    Code:
       0: aload_0
       1: getfield      #11                 // Field streamArn:Ljava/lang/String;
       4: areturn

  static java.lang.String access$1200(software.amazon.awssdk.services.dynamodb.model.StreamDescription);
    Code:
       0: aload_0
       1: getfield      #10                 // Field streamLabel:Ljava/lang/String;
       4: areturn

  static java.lang.String access$1300(software.amazon.awssdk.services.dynamodb.model.StreamDescription);
    Code:
       0: aload_0
       1: getfield      #9                  // Field streamStatus:Ljava/lang/String;
       4: areturn

  static java.lang.String access$1400(software.amazon.awssdk.services.dynamodb.model.StreamDescription);
    Code:
       0: aload_0
       1: getfield      #8                  // Field streamViewType:Ljava/lang/String;
       4: areturn

  static java.time.Instant access$1500(software.amazon.awssdk.services.dynamodb.model.StreamDescription);
    Code:
       0: aload_0
       1: getfield      #7                  // Field creationRequestDateTime:Ljava/time/Instant;
       4: areturn

  static java.lang.String access$1600(software.amazon.awssdk.services.dynamodb.model.StreamDescription);
    Code:
       0: aload_0
       1: getfield      #6                  // Field tableName:Ljava/lang/String;
       4: areturn

  static java.util.List access$1700(software.amazon.awssdk.services.dynamodb.model.StreamDescription);
    Code:
       0: aload_0
       1: getfield      #5                  // Field keySchema:Ljava/util/List;
       4: areturn

  static java.util.List access$1800(software.amazon.awssdk.services.dynamodb.model.StreamDescription);
    Code:
       0: aload_0
       1: getfield      #4                  // Field shards:Ljava/util/List;
       4: areturn

  static java.lang.String access$1900(software.amazon.awssdk.services.dynamodb.model.StreamDescription);
    Code:
       0: aload_0
       1: getfield      #3                  // Field lastEvaluatedShardId:Ljava/lang/String;
       4: areturn

  software.amazon.awssdk.services.dynamodb.model.StreamDescription(software.amazon.awssdk.services.dynamodb.model.StreamDescription$BuilderImpl, software.amazon.awssdk.services.dynamodb.model.StreamDescription$1);
    Code:
       0: aload_0
       1: aload_1
       2: invokespecial #2                  // Method "<init>":(Lsoftware/amazon/awssdk/services/dynamodb/model/StreamDescription$BuilderImpl;)V
       5: return

  static java.util.List access$2100();
    Code:
       0: getstatic     #1                  // Field SDK_FIELDS:Ljava/util/List;
       3: areturn

  static {};
    Code:
       0: getstatic     #67                 // Field software/amazon/awssdk/core/protocol/MarshallingType.STRING:Lsoftware/amazon/awssdk/core/protocol/MarshallingType;
       3: invokestatic  #68                 // Method software/amazon/awssdk/core/SdkField.builder:(Lsoftware/amazon/awssdk/core/protocol/MarshallingType;)Lsoftware/amazon/awssdk/core/SdkField$Builder;
       6: ldc           #45                 // String StreamArn
       8: invokevirtual #69                 // Method software/amazon/awssdk/core/SdkField$Builder.memberName:(Ljava/lang/String;)Lsoftware/amazon/awssdk/core/SdkField$Builder;
      11: invokedynamic #70,  0             // InvokeDynamic #2:apply:()Ljava/util/function/Function;
      16: invokestatic  #71                 // Method getter:(Ljava/util/function/Function;)Ljava/util/function/Function;
      19: invokevirtual #72                 // Method software/amazon/awssdk/core/SdkField$Builder.getter:(Ljava/util/function/Function;)Lsoftware/amazon/awssdk/core/SdkField$Builder;
      22: invokedynamic #73,  0             // InvokeDynamic #3:accept:()Ljava/util/function/BiConsumer;
      27: invokestatic  #74                 // Method setter:(Ljava/util/function/BiConsumer;)Ljava/util/function/BiConsumer;
      30: invokevirtual #75                 // Method software/amazon/awssdk/core/SdkField$Builder.setter:(Ljava/util/function/BiConsumer;)Lsoftware/amazon/awssdk/core/SdkField$Builder;
      33: iconst_1
      34: anewarray     #76                 // class software/amazon/awssdk/core/traits/Trait
      37: dup
      38: iconst_0
      39: invokestatic  #77                 // Method software/amazon/awssdk/core/traits/LocationTrait.builder:()Lsoftware/amazon/awssdk/core/traits/LocationTrait$Builder;
      42: getstatic     #78                 // Field software/amazon/awssdk/core/protocol/MarshallLocation.PAYLOAD:Lsoftware/amazon/awssdk/core/protocol/MarshallLocation;
      45: invokevirtual #79                 // Method software/amazon/awssdk/core/traits/LocationTrait$Builder.location:(Lsoftware/amazon/awssdk/core/protocol/MarshallLocation;)Lsoftware/amazon/awssdk/core/traits/LocationTrait$Builder;
      48: ldc           #45                 // String StreamArn
      50: invokevirtual #80                 // Method software/amazon/awssdk/core/traits/LocationTrait$Builder.locationName:(Ljava/lang/String;)Lsoftware/amazon/awssdk/core/traits/LocationTrait$Builder;
      53: invokevirtual #81                 // Method software/amazon/awssdk/core/traits/LocationTrait$Builder.build:()Lsoftware/amazon/awssdk/core/traits/LocationTrait;
      56: aastore
      57: invokevirtual #82                 // Method software/amazon/awssdk/core/SdkField$Builder.traits:([Lsoftware/amazon/awssdk/core/traits/Trait;)Lsoftware/amazon/awssdk/core/SdkField$Builder;
      60: invokevirtual #83                 // Method software/amazon/awssdk/core/SdkField$Builder.build:()Lsoftware/amazon/awssdk/core/SdkField;
      63: putstatic     #84                 // Field STREAM_ARN_FIELD:Lsoftware/amazon/awssdk/core/SdkField;
      66: getstatic     #67                 // Field software/amazon/awssdk/core/protocol/MarshallingType.STRING:Lsoftware/amazon/awssdk/core/protocol/MarshallingType;
      69: invokestatic  #68                 // Method software/amazon/awssdk/core/SdkField.builder:(Lsoftware/amazon/awssdk/core/protocol/MarshallingType;)Lsoftware/amazon/awssdk/core/SdkField$Builder;
      72: ldc           #47                 // String StreamLabel
      74: invokevirtual #69                 // Method software/amazon/awssdk/core/SdkField$Builder.memberName:(Ljava/lang/String;)Lsoftware/amazon/awssdk/core/SdkField$Builder;
      77: invokedynamic #85,  0             // InvokeDynamic #4:apply:()Ljava/util/function/Function;
      82: invokestatic  #71                 // Method getter:(Ljava/util/function/Function;)Ljava/util/function/Function;
      85: invokevirtual #72                 // Method software/amazon/awssdk/core/SdkField$Builder.getter:(Ljava/util/function/Function;)Lsoftware/amazon/awssdk/core/SdkField$Builder;
      88: invokedynamic #86,  0             // InvokeDynamic #5:accept:()Ljava/util/function/BiConsumer;
      93: invokestatic  #74                 // Method setter:(Ljava/util/function/BiConsumer;)Ljava/util/function/BiConsumer;
      96: invokevirtual #75                 // Method software/amazon/awssdk/core/SdkField$Builder.setter:(Ljava/util/function/BiConsumer;)Lsoftware/amazon/awssdk/core/SdkField$Builder;
      99: iconst_1
     100: anewarray     #76                 // class software/amazon/awssdk/core/traits/Trait
     103: dup
     104: iconst_0
     105: invokestatic  #77                 // Method software/amazon/awssdk/core/traits/LocationTrait.builder:()Lsoftware/amazon/awssdk/core/traits/LocationTrait$Builder;
     108: getstatic     #78                 // Field software/amazon/awssdk/core/protocol/MarshallLocation.PAYLOAD:Lsoftware/amazon/awssdk/core/protocol/MarshallLocation;
     111: invokevirtual #79                 // Method software/amazon/awssdk/core/traits/LocationTrait$Builder.location:(Lsoftware/amazon/awssdk/core/protocol/MarshallLocation;)Lsoftware/amazon/awssdk/core/traits/LocationTrait$Builder;
     114: ldc           #47                 // String StreamLabel
     116: invokevirtual #80                 // Method software/amazon/awssdk/core/traits/LocationTrait$Builder.locationName:(Ljava/lang/String;)Lsoftware/amazon/awssdk/core/traits/LocationTrait$Builder;
     119: invokevirtual #81                 // Method software/amazon/awssdk/core/traits/LocationTrait$Builder.build:()Lsoftware/amazon/awssdk/core/traits/LocationTrait;
     122: aastore
     123: invokevirtual #82                 // Method software/amazon/awssdk/core/SdkField$Builder.traits:([Lsoftware/amazon/awssdk/core/traits/Trait;)Lsoftware/amazon/awssdk/core/SdkField$Builder;
     126: invokevirtual #83                 // Method software/amazon/awssdk/core/SdkField$Builder.build:()Lsoftware/amazon/awssdk/core/SdkField;
     129: putstatic     #87                 // Field STREAM_LABEL_FIELD:Lsoftware/amazon/awssdk/core/SdkField;
     132: getstatic     #67                 // Field software/amazon/awssdk/core/protocol/MarshallingType.STRING:Lsoftware/amazon/awssdk/core/protocol/MarshallingType;
     135: invokestatic  #68                 // Method software/amazon/awssdk/core/SdkField.builder:(Lsoftware/amazon/awssdk/core/protocol/MarshallingType;)Lsoftware/amazon/awssdk/core/SdkField$Builder;
     138: ldc           #48                 // String StreamStatus
     140: invokevirtual #69                 // Method software/amazon/awssdk/core/SdkField$Builder.memberName:(Ljava/lang/String;)Lsoftware/amazon/awssdk/core/SdkField$Builder;
     143: invokedynamic #88,  0             // InvokeDynamic #6:apply:()Ljava/util/function/Function;
     148: invokestatic  #71                 // Method getter:(Ljava/util/function/Function;)Ljava/util/function/Function;
     151: invokevirtual #72                 // Method software/amazon/awssdk/core/SdkField$Builder.getter:(Ljava/util/function/Function;)Lsoftware/amazon/awssdk/core/SdkField$Builder;
     154: invokedynamic #89,  0             // InvokeDynamic #7:accept:()Ljava/util/function/BiConsumer;
     159: invokestatic  #74                 // Method setter:(Ljava/util/function/BiConsumer;)Ljava/util/function/BiConsumer;
     162: invokevirtual #75                 // Method software/amazon/awssdk/core/SdkField$Builder.setter:(Ljava/util/function/BiConsumer;)Lsoftware/amazon/awssdk/core/SdkField$Builder;
     165: iconst_1
     166: anewarray     #76                 // class software/amazon/awssdk/core/traits/Trait
     169: dup
     170: iconst_0
     171: invokestatic  #77                 // Method software/amazon/awssdk/core/traits/LocationTrait.builder:()Lsoftware/amazon/awssdk/core/traits/LocationTrait$Builder;
     174: getstatic     #78                 // Field software/amazon/awssdk/core/protocol/MarshallLocation.PAYLOAD:Lsoftware/amazon/awssdk/core/protocol/MarshallLocation;
     177: invokevirtual #79                 // Method software/amazon/awssdk/core/traits/LocationTrait$Builder.location:(Lsoftware/amazon/awssdk/core/protocol/MarshallLocation;)Lsoftware/amazon/awssdk/core/traits/LocationTrait$Builder;
     180: ldc           #48                 // String StreamStatus
     182: invokevirtual #80                 // Method software/amazon/awssdk/core/traits/LocationTrait$Builder.locationName:(Ljava/lang/String;)Lsoftware/amazon/awssdk/core/traits/LocationTrait$Builder;
     185: invokevirtual #81                 // Method software/amazon/awssdk/core/traits/LocationTrait$Builder.build:()Lsoftware/amazon/awssdk/core/traits/LocationTrait;
     188: aastore
     189: invokevirtual #82                 // Method software/amazon/awssdk/core/SdkField$Builder.traits:([Lsoftware/amazon/awssdk/core/traits/Trait;)Lsoftware/amazon/awssdk/core/SdkField$Builder;
     192: invokevirtual #83                 // Method software/amazon/awssdk/core/SdkField$Builder.build:()Lsoftware/amazon/awssdk/core/SdkField;
     195: putstatic     #90                 // Field STREAM_STATUS_FIELD:Lsoftware/amazon/awssdk/core/SdkField;
     198: getstatic     #67                 // Field software/amazon/awssdk/core/protocol/MarshallingType.STRING:Lsoftware/amazon/awssdk/core/protocol/MarshallingType;
     201: invokestatic  #68                 // Method software/amazon/awssdk/core/SdkField.builder:(Lsoftware/amazon/awssdk/core/protocol/MarshallingType;)Lsoftware/amazon/awssdk/core/SdkField$Builder;
     204: ldc           #49                 // String StreamViewType
     206: invokevirtual #69                 // Method software/amazon/awssdk/core/SdkField$Builder.memberName:(Ljava/lang/String;)Lsoftware/amazon/awssdk/core/SdkField$Builder;
     209: invokedynamic #91,  0             // InvokeDynamic #8:apply:()Ljava/util/function/Function;
     214: invokestatic  #71                 // Method getter:(Ljava/util/function/Function;)Ljava/util/function/Function;
     217: invokevirtual #72                 // Method software/amazon/awssdk/core/SdkField$Builder.getter:(Ljava/util/function/Function;)Lsoftware/amazon/awssdk/core/SdkField$Builder;
     220: invokedynamic #92,  0             // InvokeDynamic #9:accept:()Ljava/util/function/BiConsumer;
     225: invokestatic  #74                 // Method setter:(Ljava/util/function/BiConsumer;)Ljava/util/function/BiConsumer;
     228: invokevirtual #75                 // Method software/amazon/awssdk/core/SdkField$Builder.setter:(Ljava/util/function/BiConsumer;)Lsoftware/amazon/awssdk/core/SdkField$Builder;
     231: iconst_1
     232: anewarray     #76                 // class software/amazon/awssdk/core/traits/Trait
     235: dup
     236: iconst_0
     237: invokestatic  #77                 // Method software/amazon/awssdk/core/traits/LocationTrait.builder:()Lsoftware/amazon/awssdk/core/traits/LocationTrait$Builder;
     240: getstatic     #78                 // Field software/amazon/awssdk/core/protocol/MarshallLocation.PAYLOAD:Lsoftware/amazon/awssdk/core/protocol/MarshallLocation;
     243: invokevirtual #79                 // Method software/amazon/awssdk/core/traits/LocationTrait$Builder.location:(Lsoftware/amazon/awssdk/core/protocol/MarshallLocation;)Lsoftware/amazon/awssdk/core/traits/LocationTrait$Builder;
     246: ldc           #49                 // String StreamViewType
     248: invokevirtual #80                 // Method software/amazon/awssdk/core/traits/LocationTrait$Builder.locationName:(Ljava/lang/String;)Lsoftware/amazon/awssdk/core/traits/LocationTrait$Builder;
     251: invokevirtual #81                 // Method software/amazon/awssdk/core/traits/LocationTrait$Builder.build:()Lsoftware/amazon/awssdk/core/traits/LocationTrait;
     254: aastore
     255: invokevirtual #82                 // Method software/amazon/awssdk/core/SdkField$Builder.traits:([Lsoftware/amazon/awssdk/core/traits/Trait;)Lsoftware/amazon/awssdk/core/SdkField$Builder;
     258: invokevirtual #83                 // Method software/amazon/awssdk/core/SdkField$Builder.build:()Lsoftware/amazon/awssdk/core/SdkField;
     261: putstatic     #93                 // Field STREAM_VIEW_TYPE_FIELD:Lsoftware/amazon/awssdk/core/SdkField;
     264: getstatic     #94                 // Field software/amazon/awssdk/core/protocol/MarshallingType.INSTANT:Lsoftware/amazon/awssdk/core/protocol/MarshallingType;
     267: invokestatic  #68                 // Method software/amazon/awssdk/core/SdkField.builder:(Lsoftware/amazon/awssdk/core/protocol/MarshallingType;)Lsoftware/amazon/awssdk/core/SdkField$Builder;
     270: ldc           #50                 // String CreationRequestDateTime
     272: invokevirtual #69                 // Method software/amazon/awssdk/core/SdkField$Builder.memberName:(Ljava/lang/String;)Lsoftware/amazon/awssdk/core/SdkField$Builder;
     275: invokedynamic #95,  0             // InvokeDynamic #10:apply:()Ljava/util/function/Function;
     280: invokestatic  #71                 // Method getter:(Ljava/util/function/Function;)Ljava/util/function/Function;
     283: invokevirtual #72                 // Method software/amazon/awssdk/core/SdkField$Builder.getter:(Ljava/util/function/Function;)Lsoftware/amazon/awssdk/core/SdkField$Builder;
     286: invokedynamic #96,  0             // InvokeDynamic #11:accept:()Ljava/util/function/BiConsumer;
     291: invokestatic  #74                 // Method setter:(Ljava/util/function/BiConsumer;)Ljava/util/function/BiConsumer;
     294: invokevirtual #75                 // Method software/amazon/awssdk/core/SdkField$Builder.setter:(Ljava/util/function/BiConsumer;)Lsoftware/amazon/awssdk/core/SdkField$Builder;
     297: iconst_1
     298: anewarray     #76                 // class software/amazon/awssdk/core/traits/Trait
     301: dup
     302: iconst_0
     303: invokestatic  #77                 // Method software/amazon/awssdk/core/traits/LocationTrait.builder:()Lsoftware/amazon/awssdk/core/traits/LocationTrait$Builder;
     306: getstatic     #78                 // Field software/amazon/awssdk/core/protocol/MarshallLocation.PAYLOAD:Lsoftware/amazon/awssdk/core/protocol/MarshallLocation;
     309: invokevirtual #79                 // Method software/amazon/awssdk/core/traits/LocationTrait$Builder.location:(Lsoftware/amazon/awssdk/core/protocol/MarshallLocation;)Lsoftware/amazon/awssdk/core/traits/LocationTrait$Builder;
     312: ldc           #50                 // String CreationRequestDateTime
     314: invokevirtual #80                 // Method software/amazon/awssdk/core/traits/LocationTrait$Builder.locationName:(Ljava/lang/String;)Lsoftware/amazon/awssdk/core/traits/LocationTrait$Builder;
     317: invokevirtual #81                 // Method software/amazon/awssdk/core/traits/LocationTrait$Builder.build:()Lsoftware/amazon/awssdk/core/traits/LocationTrait;
     320: aastore
     321: invokevirtual #82                 // Method software/amazon/awssdk/core/SdkField$Builder.traits:([Lsoftware/amazon/awssdk/core/traits/Trait;)Lsoftware/amazon/awssdk/core/SdkField$Builder;
     324: invokevirtual #83                 // Method software/amazon/awssdk/core/SdkField$Builder.build:()Lsoftware/amazon/awssdk/core/SdkField;
     327: putstatic     #97                 // Field CREATION_REQUEST_DATE_TIME_FIELD:Lsoftware/amazon/awssdk/core/SdkField;
     330: getstatic     #67                 // Field software/amazon/awssdk/core/protocol/MarshallingType.STRING:Lsoftware/amazon/awssdk/core/protocol/MarshallingType;
     333: invokestatic  #68                 // Method software/amazon/awssdk/core/SdkField.builder:(Lsoftware/amazon/awssdk/core/protocol/MarshallingType;)Lsoftware/amazon/awssdk/core/SdkField$Builder;
     336: ldc           #51                 // String TableName
     338: invokevirtual #69                 // Method software/amazon/awssdk/core/SdkField$Builder.memberName:(Ljava/lang/String;)Lsoftware/amazon/awssdk/core/SdkField$Builder;
     341: invokedynamic #98,  0             // InvokeDynamic #12:apply:()Ljava/util/function/Function;
     346: invokestatic  #71                 // Method getter:(Ljava/util/function/Function;)Ljava/util/function/Function;
     349: invokevirtual #72                 // Method software/amazon/awssdk/core/SdkField$Builder.getter:(Ljava/util/function/Function;)Lsoftware/amazon/awssdk/core/SdkField$Builder;
     352: invokedynamic #99,  0             // InvokeDynamic #13:accept:()Ljava/util/function/BiConsumer;
     357: invokestatic  #74                 // Method setter:(Ljava/util/function/BiConsumer;)Ljava/util/function/BiConsumer;
     360: invokevirtual #75                 // Method software/amazon/awssdk/core/SdkField$Builder.setter:(Ljava/util/function/BiConsumer;)Lsoftware/amazon/awssdk/core/SdkField$Builder;
     363: iconst_1
     364: anewarray     #76                 // class software/amazon/awssdk/core/traits/Trait
     367: dup
     368: iconst_0
     369: invokestatic  #77                 // Method software/amazon/awssdk/core/traits/LocationTrait.builder:()Lsoftware/amazon/awssdk/core/traits/LocationTrait$Builder;
     372: getstatic     #78                 // Field software/amazon/awssdk/core/protocol/MarshallLocation.PAYLOAD:Lsoftware/amazon/awssdk/core/protocol/MarshallLocation;
     375: invokevirtual #79                 // Method software/amazon/awssdk/core/traits/LocationTrait$Builder.location:(Lsoftware/amazon/awssdk/core/protocol/MarshallLocation;)Lsoftware/amazon/awssdk/core/traits/LocationTrait$Builder;
     378: ldc           #51                 // String TableName
     380: invokevirtual #80                 // Method software/amazon/awssdk/core/traits/LocationTrait$Builder.locationName:(Ljava/lang/String;)Lsoftware/amazon/awssdk/core/traits/LocationTrait$Builder;
     383: invokevirtual #81                 // Method software/amazon/awssdk/core/traits/LocationTrait$Builder.build:()Lsoftware/amazon/awssdk/core/traits/LocationTrait;
     386: aastore
     387: invokevirtual #82                 // Method software/amazon/awssdk/core/SdkField$Builder.traits:([Lsoftware/amazon/awssdk/core/traits/Trait;)Lsoftware/amazon/awssdk/core/SdkField$Builder;
     390: invokevirtual #83                 // Method software/amazon/awssdk/core/SdkField$Builder.build:()Lsoftware/amazon/awssdk/core/SdkField;
     393: putstatic     #100                // Field TABLE_NAME_FIELD:Lsoftware/amazon/awssdk/core/SdkField;
     396: getstatic     #101                // Field software/amazon/awssdk/core/protocol/MarshallingType.LIST:Lsoftware/amazon/awssdk/core/protocol/MarshallingType;
     399: invokestatic  #68                 // Method software/amazon/awssdk/core/SdkField.builder:(Lsoftware/amazon/awssdk/core/protocol/MarshallingType;)Lsoftware/amazon/awssdk/core/SdkField$Builder;
     402: ldc           #52                 // String KeySchema
     404: invokevirtual #69                 // Method software/amazon/awssdk/core/SdkField$Builder.memberName:(Ljava/lang/String;)Lsoftware/amazon/awssdk/core/SdkField$Builder;
     407: invokedynamic #102,  0            // InvokeDynamic #14:apply:()Ljava/util/function/Function;
     412: invokestatic  #71                 // Method getter:(Ljava/util/function/Function;)Ljava/util/function/Function;
     415: invokevirtual #72                 // Method software/amazon/awssdk/core/SdkField$Builder.getter:(Ljava/util/function/Function;)Lsoftware/amazon/awssdk/core/SdkField$Builder;
     418: invokedynamic #103,  0            // InvokeDynamic #15:accept:()Ljava/util/function/BiConsumer;
     423: invokestatic  #74                 // Method setter:(Ljava/util/function/BiConsumer;)Ljava/util/function/BiConsumer;
     426: invokevirtual #75                 // Method software/amazon/awssdk/core/SdkField$Builder.setter:(Ljava/util/function/BiConsumer;)Lsoftware/amazon/awssdk/core/SdkField$Builder;
     429: iconst_2
     430: anewarray     #76                 // class software/amazon/awssdk/core/traits/Trait
     433: dup
     434: iconst_0
     435: invokestatic  #77                 // Method software/amazon/awssdk/core/traits/LocationTrait.builder:()Lsoftware/amazon/awssdk/core/traits/LocationTrait$Builder;
     438: getstatic     #78                 // Field software/amazon/awssdk/core/protocol/MarshallLocation.PAYLOAD:Lsoftware/amazon/awssdk/core/protocol/MarshallLocation;
     441: invokevirtual #79                 // Method software/amazon/awssdk/core/traits/LocationTrait$Builder.location:(Lsoftware/amazon/awssdk/core/protocol/MarshallLocation;)Lsoftware/amazon/awssdk/core/traits/LocationTrait$Builder;
     444: ldc           #52                 // String KeySchema
     446: invokevirtual #80                 // Method software/amazon/awssdk/core/traits/LocationTrait$Builder.locationName:(Ljava/lang/String;)Lsoftware/amazon/awssdk/core/traits/LocationTrait$Builder;
     449: invokevirtual #81                 // Method software/amazon/awssdk/core/traits/LocationTrait$Builder.build:()Lsoftware/amazon/awssdk/core/traits/LocationTrait;
     452: aastore
     453: dup
     454: iconst_1
     455: invokestatic  #104                // Method software/amazon/awssdk/core/traits/ListTrait.builder:()Lsoftware/amazon/awssdk/core/traits/ListTrait$Builder;
     458: aconst_null
     459: invokevirtual #105                // Method software/amazon/awssdk/core/traits/ListTrait$Builder.memberLocationName:(Ljava/lang/String;)Lsoftware/amazon/awssdk/core/traits/ListTrait$Builder;
     462: getstatic     #106                // Field software/amazon/awssdk/core/protocol/MarshallingType.SDK_POJO:Lsoftware/amazon/awssdk/core/protocol/MarshallingType;
     465: invokestatic  #68                 // Method software/amazon/awssdk/core/SdkField.builder:(Lsoftware/amazon/awssdk/core/protocol/MarshallingType;)Lsoftware/amazon/awssdk/core/SdkField$Builder;
     468: invokedynamic #107,  0            // InvokeDynamic #16:get:()Ljava/util/function/Supplier;
     473: invokevirtual #108                // Method software/amazon/awssdk/core/SdkField$Builder.constructor:(Ljava/util/function/Supplier;)Lsoftware/amazon/awssdk/core/SdkField$Builder;
     476: iconst_1
     477: anewarray     #76                 // class software/amazon/awssdk/core/traits/Trait
     480: dup
     481: iconst_0
     482: invokestatic  #77                 // Method software/amazon/awssdk/core/traits/LocationTrait.builder:()Lsoftware/amazon/awssdk/core/traits/LocationTrait$Builder;
     485: getstatic     #78                 // Field software/amazon/awssdk/core/protocol/MarshallLocation.PAYLOAD:Lsoftware/amazon/awssdk/core/protocol/MarshallLocation;
     488: invokevirtual #79                 // Method software/amazon/awssdk/core/traits/LocationTrait$Builder.location:(Lsoftware/amazon/awssdk/core/protocol/MarshallLocation;)Lsoftware/amazon/awssdk/core/traits/LocationTrait$Builder;
     491: ldc           #109                // String member
     493: invokevirtual #80                 // Method software/amazon/awssdk/core/traits/LocationTrait$Builder.locationName:(Ljava/lang/String;)Lsoftware/amazon/awssdk/core/traits/LocationTrait$Builder;
     496: invokevirtual #81                 // Method software/amazon/awssdk/core/traits/LocationTrait$Builder.build:()Lsoftware/amazon/awssdk/core/traits/LocationTrait;
     499: aastore
     500: invokevirtual #82                 // Method software/amazon/awssdk/core/SdkField$Builder.traits:([Lsoftware/amazon/awssdk/core/traits/Trait;)Lsoftware/amazon/awssdk/core/SdkField$Builder;
     503: invokevirtual #83                 // Method software/amazon/awssdk/core/SdkField$Builder.build:()Lsoftware/amazon/awssdk/core/SdkField;
     506: invokevirtual #110                // Method software/amazon/awssdk/core/traits/ListTrait$Builder.memberFieldInfo:(Lsoftware/amazon/awssdk/core/SdkField;)Lsoftware/amazon/awssdk/core/traits/ListTrait$Builder;
     509: invokevirtual #111                // Method software/amazon/awssdk/core/traits/ListTrait$Builder.build:()Lsoftware/amazon/awssdk/core/traits/ListTrait;
     512: aastore
     513: invokevirtual #82                 // Method software/amazon/awssdk/core/SdkField$Builder.traits:([Lsoftware/amazon/awssdk/core/traits/Trait;)Lsoftware/amazon/awssdk/core/SdkField$Builder;
     516: invokevirtual #83                 // Method software/amazon/awssdk/core/SdkField$Builder.build:()Lsoftware/amazon/awssdk/core/SdkField;
     519: putstatic     #112                // Field KEY_SCHEMA_FIELD:Lsoftware/amazon/awssdk/core/SdkField;
     522: getstatic     #101                // Field software/amazon/awssdk/core/protocol/MarshallingType.LIST:Lsoftware/amazon/awssdk/core/protocol/MarshallingType;
     525: invokestatic  #68                 // Method software/amazon/awssdk/core/SdkField.builder:(Lsoftware/amazon/awssdk/core/protocol/MarshallingType;)Lsoftware/amazon/awssdk/core/SdkField$Builder;
     528: ldc           #53                 // String Shards
     530: invokevirtual #69                 // Method software/amazon/awssdk/core/SdkField$Builder.memberName:(Ljava/lang/String;)Lsoftware/amazon/awssdk/core/SdkField$Builder;
     533: invokedynamic #113,  0            // InvokeDynamic #17:apply:()Ljava/util/function/Function;
     538: invokestatic  #71                 // Method getter:(Ljava/util/function/Function;)Ljava/util/function/Function;
     541: invokevirtual #72                 // Method software/amazon/awssdk/core/SdkField$Builder.getter:(Ljava/util/function/Function;)Lsoftware/amazon/awssdk/core/SdkField$Builder;
     544: invokedynamic #114,  0            // InvokeDynamic #18:accept:()Ljava/util/function/BiConsumer;
     549: invokestatic  #74                 // Method setter:(Ljava/util/function/BiConsumer;)Ljava/util/function/BiConsumer;
     552: invokevirtual #75                 // Method software/amazon/awssdk/core/SdkField$Builder.setter:(Ljava/util/function/BiConsumer;)Lsoftware/amazon/awssdk/core/SdkField$Builder;
     555: iconst_2
     556: anewarray     #76                 // class software/amazon/awssdk/core/traits/Trait
     559: dup
     560: iconst_0
     561: invokestatic  #77                 // Method software/amazon/awssdk/core/traits/LocationTrait.builder:()Lsoftware/amazon/awssdk/core/traits/LocationTrait$Builder;
     564: getstatic     #78                 // Field software/amazon/awssdk/core/protocol/MarshallLocation.PAYLOAD:Lsoftware/amazon/awssdk/core/protocol/MarshallLocation;
     567: invokevirtual #79                 // Method software/amazon/awssdk/core/traits/LocationTrait$Builder.location:(Lsoftware/amazon/awssdk/core/protocol/MarshallLocation;)Lsoftware/amazon/awssdk/core/traits/LocationTrait$Builder;
     570: ldc           #53                 // String Shards
     572: invokevirtual #80                 // Method software/amazon/awssdk/core/traits/LocationTrait$Builder.locationName:(Ljava/lang/String;)Lsoftware/amazon/awssdk/core/traits/LocationTrait$Builder;
     575: invokevirtual #81                 // Method software/amazon/awssdk/core/traits/LocationTrait$Builder.build:()Lsoftware/amazon/awssdk/core/traits/LocationTrait;
     578: aastore
     579: dup
     580: iconst_1
     581: invokestatic  #104                // Method software/amazon/awssdk/core/traits/ListTrait.builder:()Lsoftware/amazon/awssdk/core/traits/ListTrait$Builder;
     584: aconst_null
     585: invokevirtual #105                // Method software/amazon/awssdk/core/traits/ListTrait$Builder.memberLocationName:(Ljava/lang/String;)Lsoftware/amazon/awssdk/core/traits/ListTrait$Builder;
     588: getstatic     #106                // Field software/amazon/awssdk/core/protocol/MarshallingType.SDK_POJO:Lsoftware/amazon/awssdk/core/protocol/MarshallingType;
     591: invokestatic  #68                 // Method software/amazon/awssdk/core/SdkField.builder:(Lsoftware/amazon/awssdk/core/protocol/MarshallingType;)Lsoftware/amazon/awssdk/core/SdkField$Builder;
     594: invokedynamic #115,  0            // InvokeDynamic #19:get:()Ljava/util/function/Supplier;
     599: invokevirtual #108                // Method software/amazon/awssdk/core/SdkField$Builder.constructor:(Ljava/util/function/Supplier;)Lsoftware/amazon/awssdk/core/SdkField$Builder;
     602: iconst_1
     603: anewarray     #76                 // class software/amazon/awssdk/core/traits/Trait
     606: dup
     607: iconst_0
     608: invokestatic  #77                 // Method software/amazon/awssdk/core/traits/LocationTrait.builder:()Lsoftware/amazon/awssdk/core/traits/LocationTrait$Builder;
     611: getstatic     #78                 // Field software/amazon/awssdk/core/protocol/MarshallLocation.PAYLOAD:Lsoftware/amazon/awssdk/core/protocol/MarshallLocation;
     614: invokevirtual #79                 // Method software/amazon/awssdk/core/traits/LocationTrait$Builder.location:(Lsoftware/amazon/awssdk/core/protocol/MarshallLocation;)Lsoftware/amazon/awssdk/core/traits/LocationTrait$Builder;
     617: ldc           #109                // String member
     619: invokevirtual #80                 // Method software/amazon/awssdk/core/traits/LocationTrait$Builder.locationName:(Ljava/lang/String;)Lsoftware/amazon/awssdk/core/traits/LocationTrait$Builder;
     622: invokevirtual #81                 // Method software/amazon/awssdk/core/traits/LocationTrait$Builder.build:()Lsoftware/amazon/awssdk/core/traits/LocationTrait;
     625: aastore
     626: invokevirtual #82                 // Method software/amazon/awssdk/core/SdkField$Builder.traits:([Lsoftware/amazon/awssdk/core/traits/Trait;)Lsoftware/amazon/awssdk/core/SdkField$Builder;
     629: invokevirtual #83                 // Method software/amazon/awssdk/core/SdkField$Builder.build:()Lsoftware/amazon/awssdk/core/SdkField;
     632: invokevirtual #110                // Method software/amazon/awssdk/core/traits/ListTrait$Builder.memberFieldInfo:(Lsoftware/amazon/awssdk/core/SdkField;)Lsoftware/amazon/awssdk/core/traits/ListTrait$Builder;
     635: invokevirtual #111                // Method software/amazon/awssdk/core/traits/ListTrait$Builder.build:()Lsoftware/amazon/awssdk/core/traits/ListTrait;
     638: aastore
     639: invokevirtual #82                 // Method software/amazon/awssdk/core/SdkField$Builder.traits:([Lsoftware/amazon/awssdk/core/traits/Trait;)Lsoftware/amazon/awssdk/core/SdkField$Builder;
     642: invokevirtual #83                 // Method software/amazon/awssdk/core/SdkField$Builder.build:()Lsoftware/amazon/awssdk/core/SdkField;
     645: putstatic     #116                // Field SHARDS_FIELD:Lsoftware/amazon/awssdk/core/SdkField;
     648: getstatic     #67                 // Field software/amazon/awssdk/core/protocol/MarshallingType.STRING:Lsoftware/amazon/awssdk/core/protocol/MarshallingType;
     651: invokestatic  #68                 // Method software/amazon/awssdk/core/SdkField.builder:(Lsoftware/amazon/awssdk/core/protocol/MarshallingType;)Lsoftware/amazon/awssdk/core/SdkField$Builder;
     654: ldc           #54                 // String LastEvaluatedShardId
     656: invokevirtual #69                 // Method software/amazon/awssdk/core/SdkField$Builder.memberName:(Ljava/lang/String;)Lsoftware/amazon/awssdk/core/SdkField$Builder;
     659: invokedynamic #117,  0            // InvokeDynamic #20:apply:()Ljava/util/function/Function;
     664: invokestatic  #71                 // Method getter:(Ljava/util/function/Function;)Ljava/util/function/Function;
     667: invokevirtual #72                 // Method software/amazon/awssdk/core/SdkField$Builder.getter:(Ljava/util/function/Function;)Lsoftware/amazon/awssdk/core/SdkField$Builder;
     670: invokedynamic #118,  0            // InvokeDynamic #21:accept:()Ljava/util/function/BiConsumer;
     675: invokestatic  #74                 // Method setter:(Ljava/util/function/BiConsumer;)Ljava/util/function/BiConsumer;
     678: invokevirtual #75                 // Method software/amazon/awssdk/core/SdkField$Builder.setter:(Ljava/util/function/BiConsumer;)Lsoftware/amazon/awssdk/core/SdkField$Builder;
     681: iconst_1
     682: anewarray     #76                 // class software/amazon/awssdk/core/traits/Trait
     685: dup
     686: iconst_0
     687: invokestatic  #77                 // Method software/amazon/awssdk/core/traits/LocationTrait.builder:()Lsoftware/amazon/awssdk/core/traits/LocationTrait$Builder;
     690: getstatic     #78                 // Field software/amazon/awssdk/core/protocol/MarshallLocation.PAYLOAD:Lsoftware/amazon/awssdk/core/protocol/MarshallLocation;
     693: invokevirtual #79                 // Method software/amazon/awssdk/core/traits/LocationTrait$Builder.location:(Lsoftware/amazon/awssdk/core/protocol/MarshallLocation;)Lsoftware/amazon/awssdk/core/traits/LocationTrait$Builder;
     696: ldc           #54                 // String LastEvaluatedShardId
     698: invokevirtual #80                 // Method software/amazon/awssdk/core/traits/LocationTrait$Builder.locationName:(Ljava/lang/String;)Lsoftware/amazon/awssdk/core/traits/LocationTrait$Builder;
     701: invokevirtual #81                 // Method software/amazon/awssdk/core/traits/LocationTrait$Builder.build:()Lsoftware/amazon/awssdk/core/traits/LocationTrait;
     704: aastore
     705: invokevirtual #82                 // Method software/amazon/awssdk/core/SdkField$Builder.traits:([Lsoftware/amazon/awssdk/core/traits/Trait;)Lsoftware/amazon/awssdk/core/SdkField$Builder;
     708: invokevirtual #83                 // Method software/amazon/awssdk/core/SdkField$Builder.build:()Lsoftware/amazon/awssdk/core/SdkField;
     711: putstatic     #119                // Field LAST_EVALUATED_SHARD_ID_FIELD:Lsoftware/amazon/awssdk/core/SdkField;
     714: bipush        9
     716: anewarray     #120                // class software/amazon/awssdk/core/SdkField
     719: dup
     720: iconst_0
     721: getstatic     #84                 // Field STREAM_ARN_FIELD:Lsoftware/amazon/awssdk/core/SdkField;
     724: aastore
     725: dup
     726: iconst_1
     727: getstatic     #87                 // Field STREAM_LABEL_FIELD:Lsoftware/amazon/awssdk/core/SdkField;
     730: aastore
     731: dup
     732: iconst_2
     733: getstatic     #90                 // Field STREAM_STATUS_FIELD:Lsoftware/amazon/awssdk/core/SdkField;
     736: aastore
     737: dup
     738: iconst_3
     739: getstatic     #93                 // Field STREAM_VIEW_TYPE_FIELD:Lsoftware/amazon/awssdk/core/SdkField;
     742: aastore
     743: dup
     744: iconst_4
     745: getstatic     #97                 // Field CREATION_REQUEST_DATE_TIME_FIELD:Lsoftware/amazon/awssdk/core/SdkField;
     748: aastore
     749: dup
     750: iconst_5
     751: getstatic     #100                // Field TABLE_NAME_FIELD:Lsoftware/amazon/awssdk/core/SdkField;
     754: aastore
     755: dup
     756: bipush        6
     758: getstatic     #112                // Field KEY_SCHEMA_FIELD:Lsoftware/amazon/awssdk/core/SdkField;
     761: aastore
     762: dup
     763: bipush        7
     765: getstatic     #116                // Field SHARDS_FIELD:Lsoftware/amazon/awssdk/core/SdkField;
     768: aastore
     769: dup
     770: bipush        8
     772: getstatic     #119                // Field LAST_EVALUATED_SHARD_ID_FIELD:Lsoftware/amazon/awssdk/core/SdkField;
     775: aastore
     776: invokestatic  #121                // Method java/util/Arrays.asList:([Ljava/lang/Object;)Ljava/util/List;
     779: invokestatic  #122                // Method java/util/Collections.unmodifiableList:(Ljava/util/List;)Ljava/util/List;
     782: putstatic     #1                  // Field SDK_FIELDS:Ljava/util/List;
     785: return
}
