Compiled from "UpdateReplicationGroupMemberAction.java"
public interface software.amazon.awssdk.services.dynamodb.model.UpdateReplicationGroupMemberAction$Builder extends software.amazon.awssdk.core.SdkPojo, software.amazon.awssdk.utils.builder.CopyableBuilder<software.amazon.awssdk.services.dynamodb.model.UpdateReplicationGroupMemberAction$Builder, software.amazon.awssdk.services.dynamodb.model.UpdateReplicationGroupMemberAction> {
  public abstract software.amazon.awssdk.services.dynamodb.model.UpdateReplicationGroupMemberAction$Builder regionName(java.lang.String);

  public abstract software.amazon.awssdk.services.dynamodb.model.UpdateReplicationGroupMemberAction$Builder kmsMasterKeyId(java.lang.String);

  public abstract software.amazon.awssdk.services.dynamodb.model.UpdateReplicationGroupMemberAction$Builder provisionedThroughputOverride(software.amazon.awssdk.services.dynamodb.model.ProvisionedThroughputOverride);

  public default software.amazon.awssdk.services.dynamodb.model.UpdateReplicationGroupMemberAction$Builder provisionedThroughputOverride(java.util.function.Consumer<software.amazon.awssdk.services.dynamodb.model.ProvisionedThroughputOverride$Builder>);
    Code:
       0: aload_0
       1: invokestatic  #1                  // Method software/amazon/awssdk/services/dynamodb/model/ProvisionedThroughputOverride.builder:()Lsoftware/amazon/awssdk/services/dynamodb/model/ProvisionedThroughputOverride$Builder;
       4: aload_1
       5: invokeinterface #2,  2            // InterfaceMethod software/amazon/awssdk/services/dynamodb/model/ProvisionedThroughputOverride$Builder.applyMutation:(Ljava/util/function/Consumer;)Lsoftware/amazon/awssdk/utils/builder/SdkBuilder;
      10: checkcast     #3                  // class software/amazon/awssdk/services/dynamodb/model/ProvisionedThroughputOverride$Builder
      13: invokeinterface #4,  1            // InterfaceMethod software/amazon/awssdk/services/dynamodb/model/ProvisionedThroughputOverride$Builder.build:()Ljava/lang/Object;
      18: checkcast     #5                  // class software/amazon/awssdk/services/dynamodb/model/ProvisionedThroughputOverride
      21: invokeinterface #6,  2            // InterfaceMethod provisionedThroughputOverride:(Lsoftware/amazon/awssdk/services/dynamodb/model/ProvisionedThroughputOverride;)Lsoftware/amazon/awssdk/services/dynamodb/model/UpdateReplicationGroupMemberAction$Builder;
      26: areturn

  public abstract software.amazon.awssdk.services.dynamodb.model.UpdateReplicationGroupMemberAction$Builder globalSecondaryIndexes(java.util.Collection<software.amazon.awssdk.services.dynamodb.model.ReplicaGlobalSecondaryIndex>);

  public abstract software.amazon.awssdk.services.dynamodb.model.UpdateReplicationGroupMemberAction$Builder globalSecondaryIndexes(software.amazon.awssdk.services.dynamodb.model.ReplicaGlobalSecondaryIndex...);

  public abstract software.amazon.awssdk.services.dynamodb.model.UpdateReplicationGroupMemberAction$Builder globalSecondaryIndexes(java.util.function.Consumer<software.amazon.awssdk.services.dynamodb.model.ReplicaGlobalSecondaryIndex$Builder>...);

  public abstract software.amazon.awssdk.services.dynamodb.model.UpdateReplicationGroupMemberAction$Builder tableClassOverride(java.lang.String);

  public abstract software.amazon.awssdk.services.dynamodb.model.UpdateReplicationGroupMemberAction$Builder tableClassOverride(software.amazon.awssdk.services.dynamodb.model.TableClass);
}
