Compiled from "UpdateContributorInsightsResponse.java"
final class software.amazon.awssdk.services.dynamodb.model.UpdateContributorInsightsResponse$BuilderImpl extends software.amazon.awssdk.services.dynamodb.model.DynamoDbResponse$BuilderImpl implements software.amazon.awssdk.services.dynamodb.model.UpdateContributorInsightsResponse$Builder {
  private java.lang.String tableName;

  private java.lang.String indexName;

  private java.lang.String contributorInsightsStatus;

  private software.amazon.awssdk.services.dynamodb.model.UpdateContributorInsightsResponse$BuilderImpl();
    Code:
       0: aload_0
       1: invokespecial #6                  // Method software/amazon/awssdk/services/dynamodb/model/DynamoDbResponse$BuilderImpl."<init>":()V
       4: return

  private software.amazon.awssdk.services.dynamodb.model.UpdateContributorInsightsResponse$BuilderImpl(software.amazon.awssdk.services.dynamodb.model.UpdateContributorInsightsResponse);
    Code:
       0: aload_0
       1: aload_1
       2: invokespecial #7                  // Method software/amazon/awssdk/services/dynamodb/model/DynamoDbResponse$BuilderImpl."<init>":(Lsoftware/amazon/awssdk/services/dynamodb/model/DynamoDbResponse;)V
       5: aload_0
       6: aload_1
       7: invokestatic  #8                  // Method software/amazon/awssdk/services/dynamodb/model/UpdateContributorInsightsResponse.access$500:(Lsoftware/amazon/awssdk/services/dynamodb/model/UpdateContributorInsightsResponse;)Ljava/lang/String;
      10: invokevirtual #9                  // Method tableName:(Ljava/lang/String;)Lsoftware/amazon/awssdk/services/dynamodb/model/UpdateContributorInsightsResponse$Builder;
      13: pop
      14: aload_0
      15: aload_1
      16: invokestatic  #10                 // Method software/amazon/awssdk/services/dynamodb/model/UpdateContributorInsightsResponse.access$600:(Lsoftware/amazon/awssdk/services/dynamodb/model/UpdateContributorInsightsResponse;)Ljava/lang/String;
      19: invokevirtual #11                 // Method indexName:(Ljava/lang/String;)Lsoftware/amazon/awssdk/services/dynamodb/model/UpdateContributorInsightsResponse$Builder;
      22: pop
      23: aload_0
      24: aload_1
      25: invokestatic  #12                 // Method software/amazon/awssdk/services/dynamodb/model/UpdateContributorInsightsResponse.access$700:(Lsoftware/amazon/awssdk/services/dynamodb/model/UpdateContributorInsightsResponse;)Ljava/lang/String;
      28: invokevirtual #13                 // Method contributorInsightsStatus:(Ljava/lang/String;)Lsoftware/amazon/awssdk/services/dynamodb/model/UpdateContributorInsightsResponse$Builder;
      31: pop
      32: return

  public final java.lang.String getTableName();
    Code:
       0: aload_0
       1: getfield      #5                  // Field tableName:Ljava/lang/String;
       4: areturn

  public final void setTableName(java.lang.String);
    Code:
       0: aload_0
       1: aload_1
       2: putfield      #5                  // Field tableName:Ljava/lang/String;
       5: return

  public final software.amazon.awssdk.services.dynamodb.model.UpdateContributorInsightsResponse$Builder tableName(java.lang.String);
    Code:
       0: aload_0
       1: aload_1
       2: putfield      #5                  // Field tableName:Ljava/lang/String;
       5: aload_0
       6: areturn

  public final java.lang.String getIndexName();
    Code:
       0: aload_0
       1: getfield      #4                  // Field indexName:Ljava/lang/String;
       4: areturn

  public final void setIndexName(java.lang.String);
    Code:
       0: aload_0
       1: aload_1
       2: putfield      #4                  // Field indexName:Ljava/lang/String;
       5: return

  public final software.amazon.awssdk.services.dynamodb.model.UpdateContributorInsightsResponse$Builder indexName(java.lang.String);
    Code:
       0: aload_0
       1: aload_1
       2: putfield      #4                  // Field indexName:Ljava/lang/String;
       5: aload_0
       6: areturn

  public final java.lang.String getContributorInsightsStatus();
    Code:
       0: aload_0
       1: getfield      #3                  // Field contributorInsightsStatus:Ljava/lang/String;
       4: areturn

  public final void setContributorInsightsStatus(java.lang.String);
    Code:
       0: aload_0
       1: aload_1
       2: putfield      #3                  // Field contributorInsightsStatus:Ljava/lang/String;
       5: return

  public final software.amazon.awssdk.services.dynamodb.model.UpdateContributorInsightsResponse$Builder contributorInsightsStatus(java.lang.String);
    Code:
       0: aload_0
       1: aload_1
       2: putfield      #3                  // Field contributorInsightsStatus:Ljava/lang/String;
       5: aload_0
       6: areturn

  public final software.amazon.awssdk.services.dynamodb.model.UpdateContributorInsightsResponse$Builder contributorInsightsStatus(software.amazon.awssdk.services.dynamodb.model.ContributorInsightsStatus);
    Code:
       0: aload_0
       1: aload_1
       2: ifnonnull     9
       5: aconst_null
       6: goto          13
       9: aload_1
      10: invokevirtual #14                 // Method software/amazon/awssdk/services/dynamodb/model/ContributorInsightsStatus.toString:()Ljava/lang/String;
      13: invokevirtual #13                 // Method contributorInsightsStatus:(Ljava/lang/String;)Lsoftware/amazon/awssdk/services/dynamodb/model/UpdateContributorInsightsResponse$Builder;
      16: pop
      17: aload_0
      18: areturn

  public software.amazon.awssdk.services.dynamodb.model.UpdateContributorInsightsResponse build();
    Code:
       0: new           #15                 // class software/amazon/awssdk/services/dynamodb/model/UpdateContributorInsightsResponse
       3: dup
       4: aload_0
       5: aconst_null
       6: invokespecial #16                 // Method software/amazon/awssdk/services/dynamodb/model/UpdateContributorInsightsResponse."<init>":(Lsoftware/amazon/awssdk/services/dynamodb/model/UpdateContributorInsightsResponse$BuilderImpl;Lsoftware/amazon/awssdk/services/dynamodb/model/UpdateContributorInsightsResponse$1;)V
       9: areturn

  public java.util.List<software.amazon.awssdk.core.SdkField<?>> sdkFields();
    Code:
       0: invokestatic  #17                 // Method software/amazon/awssdk/services/dynamodb/model/UpdateContributorInsightsResponse.access$900:()Ljava/util/List;
       3: areturn

  public software.amazon.awssdk.services.dynamodb.model.DynamoDbResponse build();
    Code:
       0: aload_0
       1: invokevirtual #18                 // Method build:()Lsoftware/amazon/awssdk/services/dynamodb/model/UpdateContributorInsightsResponse;
       4: areturn

  public software.amazon.awssdk.awscore.AwsResponse build();
    Code:
       0: aload_0
       1: invokevirtual #18                 // Method build:()Lsoftware/amazon/awssdk/services/dynamodb/model/UpdateContributorInsightsResponse;
       4: areturn

  public software.amazon.awssdk.core.SdkResponse build();
    Code:
       0: aload_0
       1: invokevirtual #18                 // Method build:()Lsoftware/amazon/awssdk/services/dynamodb/model/UpdateContributorInsightsResponse;
       4: areturn

  public java.lang.Object build();
    Code:
       0: aload_0
       1: invokevirtual #18                 // Method build:()Lsoftware/amazon/awssdk/services/dynamodb/model/UpdateContributorInsightsResponse;
       4: areturn

  static java.lang.String access$000(software.amazon.awssdk.services.dynamodb.model.UpdateContributorInsightsResponse$BuilderImpl);
    Code:
       0: aload_0
       1: getfield      #5                  // Field tableName:Ljava/lang/String;
       4: areturn

  static java.lang.String access$100(software.amazon.awssdk.services.dynamodb.model.UpdateContributorInsightsResponse$BuilderImpl);
    Code:
       0: aload_0
       1: getfield      #4                  // Field indexName:Ljava/lang/String;
       4: areturn

  static java.lang.String access$200(software.amazon.awssdk.services.dynamodb.model.UpdateContributorInsightsResponse$BuilderImpl);
    Code:
       0: aload_0
       1: getfield      #3                  // Field contributorInsightsStatus:Ljava/lang/String;
       4: areturn

  software.amazon.awssdk.services.dynamodb.model.UpdateContributorInsightsResponse$BuilderImpl(software.amazon.awssdk.services.dynamodb.model.UpdateContributorInsightsResponse, software.amazon.awssdk.services.dynamodb.model.UpdateContributorInsightsResponse$1);
    Code:
       0: aload_0
       1: aload_1
       2: invokespecial #2                  // Method "<init>":(Lsoftware/amazon/awssdk/services/dynamodb/model/UpdateContributorInsightsResponse;)V
       5: return

  software.amazon.awssdk.services.dynamodb.model.UpdateContributorInsightsResponse$BuilderImpl(software.amazon.awssdk.services.dynamodb.model.UpdateContributorInsightsResponse$1);
    Code:
       0: aload_0
       1: invokespecial #1                  // Method "<init>":()V
       4: return
}
