Compiled from "ProtocolConnectionManager.java"
class org.jboss.as.protocol.ProtocolConnectionManager$EstablishingConnection implements org.jboss.as.protocol.ProtocolConnectionManager$ConnectTask {
  private final org.jboss.as.protocol.ProtocolConnectionManager$ConnectTask next;

  private final org.jboss.as.protocol.ProtocolConnectionManager$ConnectionOpenHandler openHandler;

  private final org.jboss.as.protocol.ProtocolConnectionConfiguration configuration;

  protected org.jboss.as.protocol.ProtocolConnectionManager$EstablishingConnection(org.jboss.as.protocol.ProtocolConnectionConfiguration, org.jboss.as.protocol.ProtocolConnectionManager$ConnectionOpenHandler);
    Code:
       0: aload_0
       1: invokespecial #1                  // Method java/lang/Object."<init>":()V
       4: aload_0
       5: aload_1
       6: putfield      #2                  // Field configuration:Lorg/jboss/as/protocol/ProtocolConnectionConfiguration;
       9: aload_0
      10: aload_2
      11: putfield      #3                  // Field openHandler:Lorg/jboss/as/protocol/ProtocolConnectionManager$ConnectionOpenHandler;
      14: aload_0
      15: aload_0
      16: putfield      #4                  // Field next:Lorg/jboss/as/protocol/ProtocolConnectionManager$ConnectTask;
      19: return

  protected org.jboss.as.protocol.ProtocolConnectionManager$EstablishingConnection(org.jboss.as.protocol.ProtocolConnectionConfiguration, org.jboss.as.protocol.ProtocolConnectionManager$ConnectionOpenHandler, org.jboss.as.protocol.ProtocolConnectionManager$ConnectTask);
    Code:
       0: aload_0
       1: invokespecial #1                  // Method java/lang/Object."<init>":()V
       4: aload_0
       5: aload_1
       6: putfield      #2                  // Field configuration:Lorg/jboss/as/protocol/ProtocolConnectionConfiguration;
       9: aload_0
      10: aload_2
      11: putfield      #3                  // Field openHandler:Lorg/jboss/as/protocol/ProtocolConnectionManager$ConnectionOpenHandler;
      14: aload_0
      15: aload_3
      16: putfield      #4                  // Field next:Lorg/jboss/as/protocol/ProtocolConnectionManager$ConnectTask;
      19: return

  public org.jboss.as.protocol.ProtocolConnectionManager$ConnectionOpenHandler getConnectionOpenedHandler();
    Code:
       0: aload_0
       1: getfield      #3                  // Field openHandler:Lorg/jboss/as/protocol/ProtocolConnectionManager$ConnectionOpenHandler;
       4: areturn

  public org.jboss.remoting3.Connection connect() throws java.io.IOException;
    Code:
       0: aload_0
       1: getfield      #2                  // Field configuration:Lorg/jboss/as/protocol/ProtocolConnectionConfiguration;
       4: invokestatic  #5                  // Method org/jboss/as/protocol/ProtocolConnectionUtils.connectSync:(Lorg/jboss/as/protocol/ProtocolConnectionConfiguration;)Lorg/jboss/remoting3/Connection;
       7: areturn

  public org.jboss.as.protocol.ProtocolConnectionManager$ConnectTask connectionClosed();
    Code:
       0: aload_0
       1: getfield      #4                  // Field next:Lorg/jboss/as/protocol/ProtocolConnectionManager$ConnectTask;
       4: areturn

  public void shutdown();
    Code:
       0: return
}
