Compiled from "Jsr250MethodSecurityMetadataSource.java"
public class org.springframework.security.access.annotation.Jsr250MethodSecurityMetadataSource extends org.springframework.security.access.method.AbstractFallbackMethodSecurityMetadataSource {
  private java.lang.String defaultRolePrefix;

  public org.springframework.security.access.annotation.Jsr250MethodSecurityMetadataSource();
    Code:
       0: aload_0
       1: invokespecial #1                  // Method org/springframework/security/access/method/AbstractFallbackMethodSecurityMetadataSource."<init>":()V
       4: aload_0
       5: ldc           #2                  // String ROLE_
       7: putfield      #3                  // Field defaultRolePrefix:Ljava/lang/String;
      10: return

  public void setDefaultRolePrefix(java.lang.String);
    Code:
       0: aload_0
       1: aload_1
       2: putfield      #3                  // Field defaultRolePrefix:Ljava/lang/String;
       5: return

  protected java.util.Collection<org.springframework.security.access.ConfigAttribute> findAttributes(java.lang.Class<?>);
    Code:
       0: aload_0
       1: aload_1
       2: invokevirtual #4                  // Method java/lang/Class.getAnnotations:()[Ljava/lang/annotation/Annotation;
       5: invokespecial #5                  // Method processAnnotations:([Ljava/lang/annotation/Annotation;)Ljava/util/List;
       8: areturn

  protected java.util.Collection<org.springframework.security.access.ConfigAttribute> findAttributes(java.lang.reflect.Method, java.lang.Class<?>);
    Code:
       0: aload_0
       1: aload_1
       2: invokestatic  #6                  // Method org/springframework/core/annotation/AnnotationUtils.getAnnotations:(Ljava/lang/reflect/Method;)[Ljava/lang/annotation/Annotation;
       5: invokespecial #5                  // Method processAnnotations:([Ljava/lang/annotation/Annotation;)Ljava/util/List;
       8: areturn

  public java.util.Collection<org.springframework.security.access.ConfigAttribute> getAllConfigAttributes();
    Code:
       0: aconst_null
       1: areturn

  private java.util.List<org.springframework.security.access.ConfigAttribute> processAnnotations(java.lang.annotation.Annotation[]);
    Code:
       0: aload_1
       1: ifnull        9
       4: aload_1
       5: arraylength
       6: ifne          11
       9: aconst_null
      10: areturn
      11: new           #7                  // class java/util/ArrayList
      14: dup
      15: invokespecial #8                  // Method java/util/ArrayList."<init>":()V
      18: astore_2
      19: aload_1
      20: astore_3
      21: aload_3
      22: arraylength
      23: istore        4
      25: iconst_0
      26: istore        5
      28: iload         5
      30: iload         4
      32: if_icmpge     165
      35: aload_3
      36: iload         5
      38: aaload
      39: astore        6
      41: aload         6
      43: instanceof    #9                  // class javax/annotation/security/DenyAll
      46: ifeq          61
      49: aload_2
      50: getstatic     #10                 // Field org/springframework/security/access/annotation/Jsr250SecurityConfig.DENY_ALL_ATTRIBUTE:Lorg/springframework/security/access/annotation/Jsr250SecurityConfig;
      53: invokeinterface #11,  2           // InterfaceMethod java/util/List.add:(Ljava/lang/Object;)Z
      58: pop
      59: aload_2
      60: areturn
      61: aload         6
      63: instanceof    #12                 // class javax/annotation/security/PermitAll
      66: ifeq          81
      69: aload_2
      70: getstatic     #13                 // Field org/springframework/security/access/annotation/Jsr250SecurityConfig.PERMIT_ALL_ATTRIBUTE:Lorg/springframework/security/access/annotation/Jsr250SecurityConfig;
      73: invokeinterface #11,  2           // InterfaceMethod java/util/List.add:(Ljava/lang/Object;)Z
      78: pop
      79: aload_2
      80: areturn
      81: aload         6
      83: instanceof    #14                 // class javax/annotation/security/RolesAllowed
      86: ifeq          159
      89: aload         6
      91: checkcast     #14                 // class javax/annotation/security/RolesAllowed
      94: astore        7
      96: aload         7
      98: invokeinterface #15,  1           // InterfaceMethod javax/annotation/security/RolesAllowed.value:()[Ljava/lang/String;
     103: astore        8
     105: aload         8
     107: arraylength
     108: istore        9
     110: iconst_0
     111: istore        10
     113: iload         10
     115: iload         9
     117: if_icmpge     157
     120: aload         8
     122: iload         10
     124: aaload
     125: astore        11
     127: aload_0
     128: aload         11
     130: invokespecial #16                 // Method getRoleWithDefaultPrefix:(Ljava/lang/String;)Ljava/lang/String;
     133: astore        12
     135: aload_2
     136: new           #17                 // class org/springframework/security/access/annotation/Jsr250SecurityConfig
     139: dup
     140: aload         12
     142: invokespecial #18                 // Method org/springframework/security/access/annotation/Jsr250SecurityConfig."<init>":(Ljava/lang/String;)V
     145: invokeinterface #11,  2           // InterfaceMethod java/util/List.add:(Ljava/lang/Object;)Z
     150: pop
     151: iinc          10, 1
     154: goto          113
     157: aload_2
     158: areturn
     159: iinc          5, 1
     162: goto          28
     165: aconst_null
     166: areturn

  private java.lang.String getRoleWithDefaultPrefix(java.lang.String);
    Code:
       0: aload_1
       1: ifnonnull     6
       4: aload_1
       5: areturn
       6: aload_0
       7: getfield      #3                  // Field defaultRolePrefix:Ljava/lang/String;
      10: ifnull        23
      13: aload_0
      14: getfield      #3                  // Field defaultRolePrefix:Ljava/lang/String;
      17: invokevirtual #19                 // Method java/lang/String.length:()I
      20: ifne          25
      23: aload_1
      24: areturn
      25: aload_1
      26: aload_0
      27: getfield      #3                  // Field defaultRolePrefix:Ljava/lang/String;
      30: invokevirtual #20                 // Method java/lang/String.startsWith:(Ljava/lang/String;)Z
      33: ifeq          38
      36: aload_1
      37: areturn
      38: new           #21                 // class java/lang/StringBuilder
      41: dup
      42: invokespecial #22                 // Method java/lang/StringBuilder."<init>":()V
      45: aload_0
      46: getfield      #3                  // Field defaultRolePrefix:Ljava/lang/String;
      49: invokevirtual #23                 // Method java/lang/StringBuilder.append:(Ljava/lang/String;)Ljava/lang/StringBuilder;
      52: aload_1
      53: invokevirtual #23                 // Method java/lang/StringBuilder.append:(Ljava/lang/String;)Ljava/lang/StringBuilder;
      56: invokevirtual #24                 // Method java/lang/StringBuilder.toString:()Ljava/lang/String;
      59: areturn
}
