Compiled from "RequestParamMapMethodArgumentResolver.java"
public class org.springframework.web.method.annotation.RequestParamMapMethodArgumentResolver implements org.springframework.web.method.support.HandlerMethodArgumentResolver {
  public org.springframework.web.method.annotation.RequestParamMapMethodArgumentResolver();
    Code:
       0: aload_0
       1: invokespecial #1                  // Method java/lang/Object."<init>":()V
       4: return

  public boolean supportsParameter(org.springframework.core.MethodParameter);
    Code:
       0: aload_1
       1: ldc           #2                  // class org/springframework/web/bind/annotation/RequestParam
       3: invokevirtual #3                  // Method org/springframework/core/MethodParameter.getParameterAnnotation:(Ljava/lang/Class;)Ljava/lang/annotation/Annotation;
       6: checkcast     #2                  // class org/springframework/web/bind/annotation/RequestParam
       9: astore_2
      10: aload_2
      11: ifnull        42
      14: ldc           #4                  // class java/util/Map
      16: aload_1
      17: invokevirtual #5                  // Method org/springframework/core/MethodParameter.getParameterType:()Ljava/lang/Class;
      20: invokevirtual #6                  // Method java/lang/Class.isAssignableFrom:(Ljava/lang/Class;)Z
      23: ifeq          42
      26: aload_2
      27: invokeinterface #7,  1            // InterfaceMethod org/springframework/web/bind/annotation/RequestParam.name:()Ljava/lang/String;
      32: invokestatic  #8                  // Method org/springframework/util/StringUtils.hasText:(Ljava/lang/String;)Z
      35: ifne          42
      38: iconst_1
      39: goto          43
      42: iconst_0
      43: ireturn

  public java.lang.Object resolveArgument(org.springframework.core.MethodParameter, org.springframework.web.method.support.ModelAndViewContainer, org.springframework.web.context.request.NativeWebRequest, org.springframework.web.bind.support.WebDataBinderFactory) throws java.lang.Exception;
    Code:
       0: aload_1
       1: invokestatic  #9                  // Method org/springframework/core/ResolvableType.forMethodParameter:(Lorg/springframework/core/MethodParameter;)Lorg/springframework/core/ResolvableType;
       4: astore        5
       6: ldc           #10                 // class org/springframework/util/MultiValueMap
       8: aload_1
       9: invokevirtual #5                  // Method org/springframework/core/MethodParameter.getParameterType:()Ljava/lang/Class;
      12: invokevirtual #6                  // Method java/lang/Class.isAssignableFrom:(Ljava/lang/Class;)Z
      15: ifeq          236
      18: aload         5
      20: ldc           #10                 // class org/springframework/util/MultiValueMap
      22: invokevirtual #11                 // Method org/springframework/core/ResolvableType.as:(Ljava/lang/Class;)Lorg/springframework/core/ResolvableType;
      25: iconst_1
      26: newarray       int
      28: dup
      29: iconst_0
      30: iconst_1
      31: iastore
      32: invokevirtual #12                 // Method org/springframework/core/ResolvableType.getGeneric:([I)Lorg/springframework/core/ResolvableType;
      35: invokevirtual #13                 // Method org/springframework/core/ResolvableType.resolve:()Ljava/lang/Class;
      38: astore        6
      40: aload         6
      42: ldc           #14                 // class org/springframework/web/multipart/MultipartFile
      44: if_acmpne     77
      47: aload_3
      48: invokestatic  #15                 // Method org/springframework/web/multipart/support/MultipartResolutionDelegate.resolveMultipartRequest:(Lorg/springframework/web/context/request/NativeWebRequest;)Lorg/springframework/web/multipart/MultipartRequest;
      51: astore        7
      53: aload         7
      55: ifnull        68
      58: aload         7
      60: invokeinterface #16,  1           // InterfaceMethod org/springframework/web/multipart/MultipartRequest.getMultiFileMap:()Lorg/springframework/util/MultiValueMap;
      65: goto          76
      68: new           #17                 // class org/springframework/util/LinkedMultiValueMap
      71: dup
      72: iconst_0
      73: invokespecial #18                 // Method org/springframework/util/LinkedMultiValueMap."<init>":(I)V
      76: areturn
      77: aload         6
      79: ldc           #19                 // class javax/servlet/http/Part
      81: if_acmpne     195
      84: aload_3
      85: ldc           #20                 // class javax/servlet/http/HttpServletRequest
      87: invokeinterface #21,  2           // InterfaceMethod org/springframework/web/context/request/NativeWebRequest.getNativeRequest:(Ljava/lang/Class;)Ljava/lang/Object;
      92: checkcast     #20                 // class javax/servlet/http/HttpServletRequest
      95: astore        7
      97: aload         7
      99: ifnull        186
     102: aload         7
     104: invokestatic  #22                 // Method org/springframework/web/multipart/support/MultipartResolutionDelegate.isMultipartRequest:(Ljavax/servlet/http/HttpServletRequest;)Z
     107: ifeq          186
     110: aload         7
     112: invokeinterface #23,  1           // InterfaceMethod javax/servlet/http/HttpServletRequest.getParts:()Ljava/util/Collection;
     117: astore        8
     119: new           #17                 // class org/springframework/util/LinkedMultiValueMap
     122: dup
     123: aload         8
     125: invokeinterface #24,  1           // InterfaceMethod java/util/Collection.size:()I
     130: invokespecial #18                 // Method org/springframework/util/LinkedMultiValueMap."<init>":(I)V
     133: astore        9
     135: aload         8
     137: invokeinterface #25,  1           // InterfaceMethod java/util/Collection.iterator:()Ljava/util/Iterator;
     142: astore        10
     144: aload         10
     146: invokeinterface #26,  1           // InterfaceMethod java/util/Iterator.hasNext:()Z
     151: ifeq          183
     154: aload         10
     156: invokeinterface #27,  1           // InterfaceMethod java/util/Iterator.next:()Ljava/lang/Object;
     161: checkcast     #19                 // class javax/servlet/http/Part
     164: astore        11
     166: aload         9
     168: aload         11
     170: invokeinterface #28,  1           // InterfaceMethod javax/servlet/http/Part.getName:()Ljava/lang/String;
     175: aload         11
     177: invokevirtual #29                 // Method org/springframework/util/LinkedMultiValueMap.add:(Ljava/lang/Object;Ljava/lang/Object;)V
     180: goto          144
     183: aload         9
     185: areturn
     186: new           #17                 // class org/springframework/util/LinkedMultiValueMap
     189: dup
     190: iconst_0
     191: invokespecial #18                 // Method org/springframework/util/LinkedMultiValueMap."<init>":(I)V
     194: areturn
     195: aload_3
     196: invokeinterface #30,  1           // InterfaceMethod org/springframework/web/context/request/NativeWebRequest.getParameterMap:()Ljava/util/Map;
     201: astore        7
     203: new           #17                 // class org/springframework/util/LinkedMultiValueMap
     206: dup
     207: aload         7
     209: invokeinterface #31,  1           // InterfaceMethod java/util/Map.size:()I
     214: invokespecial #18                 // Method org/springframework/util/LinkedMultiValueMap."<init>":(I)V
     217: astore        8
     219: aload         7
     221: aload         8
     223: invokedynamic #32,  0             // InvokeDynamic #0:accept:(Lorg/springframework/util/MultiValueMap;)Ljava/util/function/BiConsumer;
     228: invokeinterface #33,  2           // InterfaceMethod java/util/Map.forEach:(Ljava/util/function/BiConsumer;)V
     233: aload         8
     235: areturn
     236: aload         5
     238: invokevirtual #34                 // Method org/springframework/core/ResolvableType.asMap:()Lorg/springframework/core/ResolvableType;
     241: iconst_1
     242: newarray       int
     244: dup
     245: iconst_0
     246: iconst_1
     247: iastore
     248: invokevirtual #12                 // Method org/springframework/core/ResolvableType.getGeneric:([I)Lorg/springframework/core/ResolvableType;
     251: invokevirtual #13                 // Method org/springframework/core/ResolvableType.resolve:()Ljava/lang/Class;
     254: astore        6
     256: aload         6
     258: ldc           #14                 // class org/springframework/web/multipart/MultipartFile
     260: if_acmpne     293
     263: aload_3
     264: invokestatic  #15                 // Method org/springframework/web/multipart/support/MultipartResolutionDelegate.resolveMultipartRequest:(Lorg/springframework/web/context/request/NativeWebRequest;)Lorg/springframework/web/multipart/MultipartRequest;
     267: astore        7
     269: aload         7
     271: ifnull        284
     274: aload         7
     276: invokeinterface #35,  1           // InterfaceMethod org/springframework/web/multipart/MultipartRequest.getFileMap:()Ljava/util/Map;
     281: goto          292
     284: new           #36                 // class java/util/LinkedHashMap
     287: dup
     288: iconst_0
     289: invokespecial #37                 // Method java/util/LinkedHashMap."<init>":(I)V
     292: areturn
     293: aload         6
     295: ldc           #19                 // class javax/servlet/http/Part
     297: if_acmpne     427
     300: aload_3
     301: ldc           #20                 // class javax/servlet/http/HttpServletRequest
     303: invokeinterface #21,  2           // InterfaceMethod org/springframework/web/context/request/NativeWebRequest.getNativeRequest:(Ljava/lang/Class;)Ljava/lang/Object;
     308: checkcast     #20                 // class javax/servlet/http/HttpServletRequest
     311: astore        7
     313: aload         7
     315: ifnull        418
     318: aload         7
     320: invokestatic  #22                 // Method org/springframework/web/multipart/support/MultipartResolutionDelegate.isMultipartRequest:(Ljavax/servlet/http/HttpServletRequest;)Z
     323: ifeq          418
     326: aload         7
     328: invokeinterface #23,  1           // InterfaceMethod javax/servlet/http/HttpServletRequest.getParts:()Ljava/util/Collection;
     333: astore        8
     335: new           #36                 // class java/util/LinkedHashMap
     338: dup
     339: aload         8
     341: invokeinterface #24,  1           // InterfaceMethod java/util/Collection.size:()I
     346: invokespecial #37                 // Method java/util/LinkedHashMap."<init>":(I)V
     349: astore        9
     351: aload         8
     353: invokeinterface #25,  1           // InterfaceMethod java/util/Collection.iterator:()Ljava/util/Iterator;
     358: astore        10
     360: aload         10
     362: invokeinterface #26,  1           // InterfaceMethod java/util/Iterator.hasNext:()Z
     367: ifeq          415
     370: aload         10
     372: invokeinterface #27,  1           // InterfaceMethod java/util/Iterator.next:()Ljava/lang/Object;
     377: checkcast     #19                 // class javax/servlet/http/Part
     380: astore        11
     382: aload         9
     384: aload         11
     386: invokeinterface #28,  1           // InterfaceMethod javax/servlet/http/Part.getName:()Ljava/lang/String;
     391: invokevirtual #38                 // Method java/util/LinkedHashMap.containsKey:(Ljava/lang/Object;)Z
     394: ifne          412
     397: aload         9
     399: aload         11
     401: invokeinterface #28,  1           // InterfaceMethod javax/servlet/http/Part.getName:()Ljava/lang/String;
     406: aload         11
     408: invokevirtual #39                 // Method java/util/LinkedHashMap.put:(Ljava/lang/Object;Ljava/lang/Object;)Ljava/lang/Object;
     411: pop
     412: goto          360
     415: aload         9
     417: areturn
     418: new           #36                 // class java/util/LinkedHashMap
     421: dup
     422: iconst_0
     423: invokespecial #37                 // Method java/util/LinkedHashMap."<init>":(I)V
     426: areturn
     427: aload_3
     428: invokeinterface #30,  1           // InterfaceMethod org/springframework/web/context/request/NativeWebRequest.getParameterMap:()Ljava/util/Map;
     433: astore        7
     435: new           #36                 // class java/util/LinkedHashMap
     438: dup
     439: aload         7
     441: invokeinterface #31,  1           // InterfaceMethod java/util/Map.size:()I
     446: invokespecial #37                 // Method java/util/LinkedHashMap."<init>":(I)V
     449: astore        8
     451: aload         7
     453: aload         8
     455: invokedynamic #40,  0             // InvokeDynamic #1:accept:(Ljava/util/Map;)Ljava/util/function/BiConsumer;
     460: invokeinterface #33,  2           // InterfaceMethod java/util/Map.forEach:(Ljava/util/function/BiConsumer;)V
     465: aload         8
     467: areturn

  private static void lambda$resolveArgument$1(java.util.Map, java.lang.String, java.lang.String[]);
    Code:
       0: aload_2
       1: arraylength
       2: ifle          16
       5: aload_0
       6: aload_1
       7: aload_2
       8: iconst_0
       9: aaload
      10: invokeinterface #41,  3           // InterfaceMethod java/util/Map.put:(Ljava/lang/Object;Ljava/lang/Object;)Ljava/lang/Object;
      15: pop
      16: return

  private static void lambda$resolveArgument$0(org.springframework.util.MultiValueMap, java.lang.String, java.lang.String[]);
    Code:
       0: aload_2
       1: astore_3
       2: aload_3
       3: arraylength
       4: istore        4
       6: iconst_0
       7: istore        5
       9: iload         5
      11: iload         4
      13: if_icmpge     37
      16: aload_3
      17: iload         5
      19: aaload
      20: astore        6
      22: aload_0
      23: aload_1
      24: aload         6
      26: invokeinterface #42,  3           // InterfaceMethod org/springframework/util/MultiValueMap.add:(Ljava/lang/Object;Ljava/lang/Object;)V
      31: iinc          5, 1
      34: goto          9
      37: return
}
