Compiled from "CERT.java"
public class won.protocol.vocabulary.CERT {
  public static final java.lang.String BASE_URI;

  public static final java.lang.String DEFAULT_PREFIX;

  private static org.apache.jena.rdf.model.Model m;

  public static final org.apache.jena.rdf.model.Property KEY;

  public static final org.apache.jena.rdf.model.Property PUBLIC_KEY;

  public static final org.apache.jena.rdf.model.Property RSA_PUBLIC_KEY;

  public won.protocol.vocabulary.CERT();
    Code:
       0: aload_0
       1: invokespecial #1                  // Method java/lang/Object."<init>":()V
       4: return

  public static java.lang.String getURI();
    Code:
       0: ldc           #3                  // String http://www.w3.org/ns/auth/cert#
       2: areturn

  static {};
    Code:
       0: invokestatic  #4                  // Method org/apache/jena/rdf/model/ModelFactory.createDefaultModel:()Lorg/apache/jena/rdf/model/Model;
       3: putstatic     #5                  // Field m:Lorg/apache/jena/rdf/model/Model;
       6: getstatic     #5                  // Field m:Lorg/apache/jena/rdf/model/Model;
       9: ldc           #6                  // String http://www.w3.org/ns/auth/cert#key
      11: invokeinterface #7,  2            // InterfaceMethod org/apache/jena/rdf/model/Model.createProperty:(Ljava/lang/String;)Lorg/apache/jena/rdf/model/Property;
      16: putstatic     #8                  // Field KEY:Lorg/apache/jena/rdf/model/Property;
      19: getstatic     #5                  // Field m:Lorg/apache/jena/rdf/model/Model;
      22: ldc           #9                  // String http://www.w3.org/ns/auth/cert#PublicKey
      24: invokeinterface #7,  2            // InterfaceMethod org/apache/jena/rdf/model/Model.createProperty:(Ljava/lang/String;)Lorg/apache/jena/rdf/model/Property;
      29: putstatic     #10                 // Field PUBLIC_KEY:Lorg/apache/jena/rdf/model/Property;
      32: getstatic     #5                  // Field m:Lorg/apache/jena/rdf/model/Model;
      35: ldc           #11                 // String http://www.w3.org/ns/auth/cert#RSAPublicKey
      37: invokeinterface #7,  2            // InterfaceMethod org/apache/jena/rdf/model/Model.createProperty:(Ljava/lang/String;)Lorg/apache/jena/rdf/model/Property;
      42: putstatic     #12                 // Field RSA_PUBLIC_KEY:Lorg/apache/jena/rdf/model/Property;
      45: return
}
