Compiled from "WONMSG.java"
public class won.protocol.vocabulary.WONMSG {
  public static final java.lang.String BASE_URI;

  public static final java.lang.String DEFAULT_PREFIX;

  private static org.apache.jena.rdf.model.Model m;

  public static final java.lang.String PROTOCOL_VERSION_STRING;

  public static final org.apache.jena.rdf.model.Property PROTOCOL_VERSION;

  public static final java.lang.String FromOwnerString;

  public static final java.lang.String FromSystemString;

  public static final java.lang.String FromExternalString;

  public static final org.apache.jena.rdf.model.Resource FromOwner;

  public static final org.apache.jena.rdf.model.Resource FromSystem;

  public static final org.apache.jena.rdf.model.Resource FromExternal;

  public static final java.lang.String CreateMessageString;

  public static final java.lang.String ReplaceMessageString;

  public static final java.lang.String ChangeNotificationMessageString;

  public static final java.lang.String ConnectMessageString;

  public static final java.lang.String DeactivateMessageString;

  public static final java.lang.String ActivateMessageString;

  public static final java.lang.String OpenMessageString;

  public static final java.lang.String CloseMessageString;

  public static final java.lang.String DeleteMessageString;

  public static final java.lang.String ConnectionMessageString;

  public static final java.lang.String AtomMessageString;

  public static final java.lang.String SocketHintMessageString;

  public static final java.lang.String AtomHintMessageString;

  public static final java.lang.String HintFeedbackMessageString;

  public static final java.lang.String FailureResponseString;

  public static final java.lang.String SuccessResponseString;

  public static final org.apache.jena.rdf.model.Resource CreateMessage;

  public static final org.apache.jena.rdf.model.Resource ReplaceMessage;

  public static final org.apache.jena.rdf.model.Resource ChangeNotificationMessage;

  public static final org.apache.jena.rdf.model.Resource ConnectMessage;

  public static final org.apache.jena.rdf.model.Resource DeactivateMessage;

  public static final org.apache.jena.rdf.model.Resource ActivateMessage;

  public static final org.apache.jena.rdf.model.Resource OpenMessage;

  public static final org.apache.jena.rdf.model.Resource CloseMessage;

  public static final org.apache.jena.rdf.model.Resource DeleteMessage;

  public static final org.apache.jena.rdf.model.Resource ConnectionMessage;

  public static final org.apache.jena.rdf.model.Resource AtomMessage;

  public static final org.apache.jena.rdf.model.Resource SocketHintMessage;

  public static final org.apache.jena.rdf.model.Resource AtomHintMessage;

  public static final org.apache.jena.rdf.model.Resource HintFeedbackMessage;

  public static final org.apache.jena.rdf.model.Resource SuccessResponse;

  public static final org.apache.jena.rdf.model.Resource FailureResponse;

  public static final org.apache.jena.rdf.model.Resource HintNotificationMessage;

  public static final org.apache.jena.rdf.model.Resource AtomCreatedNotificationMessage;

  public static final org.apache.jena.rdf.model.Resource CreateResponseMessage;

  public static final org.apache.jena.rdf.model.Resource ConnectResponseMessage;

  public static final org.apache.jena.rdf.model.Resource AtomStateResponseMessage;

  public static final org.apache.jena.rdf.model.Resource CloseResponseMessage;

  public static final org.apache.jena.rdf.model.Resource OpenResponseMessage;

  public static final org.apache.jena.rdf.model.Resource ConnectionMessageResponseMessage;

  public static final org.apache.jena.rdf.model.Resource SuccessResponseState;

  public static final org.apache.jena.rdf.model.Resource FailureResponseState;

  public static final org.apache.jena.rdf.model.Resource DuplicateAtomIdResponseState;

  public static final org.apache.jena.rdf.model.Resource DuplicateConnectionIdResponseState;

  public static final org.apache.jena.rdf.model.Resource DuplicateMessageIdResponseState;

  public static final org.apache.jena.rdf.model.Property responseStateProperty;

  public static final org.apache.jena.rdf.model.Resource EnvelopeGraph;

  public static final org.apache.jena.rdf.model.Resource ForwardedEnvelopeGraph;

  public static final org.apache.jena.rdf.model.Property containsEnvelope;

  public static final org.apache.jena.rdf.model.Property recipient;

  public static final org.apache.jena.rdf.model.Property recipientAtom;

  public static final org.apache.jena.rdf.model.Property recipientNode;

  public static final org.apache.jena.rdf.model.Property sender;

  public static final org.apache.jena.rdf.model.Property senderAtom;

  public static final org.apache.jena.rdf.model.Property senderNode;

  public static final org.apache.jena.rdf.model.Property messageType;

  public static final org.apache.jena.rdf.model.Property content;

  public static final org.apache.jena.rdf.model.Property isResponseTo;

  public static final org.apache.jena.rdf.model.Property isRemoteResponseTo;

  public static final org.apache.jena.rdf.model.Property isResponseToMessageType;

  public static final org.apache.jena.rdf.model.Property correspondingRemoteMessage;

  public static final org.apache.jena.rdf.model.Property forwardedMessage;

  public static final org.apache.jena.rdf.model.Property injectIntoConnection;

  public static final org.apache.jena.rdf.model.Property previousMessage;

  public static final org.apache.jena.rdf.model.Property sentTimestamp;

  public static final org.apache.jena.rdf.model.Property receivedTimestamp;

  public static final org.apache.jena.rdf.model.Property containsSignature;

  public static final org.apache.jena.rdf.model.Property signedGraph;

  public static final org.apache.jena.rdf.model.Property signatureValue;

  public static final org.apache.jena.rdf.model.Property hash;

  public static final org.apache.jena.rdf.model.Property signatureGraph;

  public static final org.apache.jena.rdf.model.Property publicKeyFingerprint;

  public static final org.apache.jena.rdf.model.Property recipientSocket;

  public static final org.apache.jena.rdf.model.Property senderSocket;

  public static final org.apache.jena.rdf.model.Property contentType;

  public static final org.apache.jena.rdf.model.Property hintScore;

  public static final org.apache.jena.rdf.model.Property hintTargetAtom;

  public static final org.apache.jena.rdf.model.Property hintTargetSocket;

  public static final java.lang.String GRAPH_URI_FRAGMENT;

  public won.protocol.vocabulary.WONMSG();
    Code:
       0: aload_0
       1: invokespecial #2                  // Method java/lang/Object."<init>":()V
       4: return

  public static boolean isResponseMessageType(org.apache.jena.rdf.model.Resource);
    Code:
       0: aload_0
       1: getstatic     #3                  // Field CreateResponseMessage:Lorg/apache/jena/rdf/model/Resource;
       4: invokeinterface #4,  2            // InterfaceMethod org/apache/jena/rdf/model/Resource.equals:(Ljava/lang/Object;)Z
       9: ifne          72
      12: aload_0
      13: getstatic     #5                  // Field ConnectResponseMessage:Lorg/apache/jena/rdf/model/Resource;
      16: invokeinterface #4,  2            // InterfaceMethod org/apache/jena/rdf/model/Resource.equals:(Ljava/lang/Object;)Z
      21: ifne          72
      24: aload_0
      25: getstatic     #6                  // Field AtomStateResponseMessage:Lorg/apache/jena/rdf/model/Resource;
      28: invokeinterface #4,  2            // InterfaceMethod org/apache/jena/rdf/model/Resource.equals:(Ljava/lang/Object;)Z
      33: ifne          72
      36: aload_0
      37: getstatic     #7                  // Field CloseResponseMessage:Lorg/apache/jena/rdf/model/Resource;
      40: invokeinterface #4,  2            // InterfaceMethod org/apache/jena/rdf/model/Resource.equals:(Ljava/lang/Object;)Z
      45: ifne          72
      48: aload_0
      49: getstatic     #8                  // Field OpenResponseMessage:Lorg/apache/jena/rdf/model/Resource;
      52: invokeinterface #4,  2            // InterfaceMethod org/apache/jena/rdf/model/Resource.equals:(Ljava/lang/Object;)Z
      57: ifne          72
      60: aload_0
      61: getstatic     #9                  // Field ConnectionMessageResponseMessage:Lorg/apache/jena/rdf/model/Resource;
      64: invokeinterface #4,  2            // InterfaceMethod org/apache/jena/rdf/model/Resource.equals:(Ljava/lang/Object;)Z
      69: ifeq          74
      72: iconst_1
      73: ireturn
      74: iconst_0
      75: ireturn

  public static java.lang.String getURI();
    Code:
       0: ldc           #10                 // String https://w3id.org/won/message#
       2: areturn

  public static org.apache.jena.rdf.model.Resource toResource(java.net.URI);
    Code:
       0: getstatic     #11                 // Field m:Lorg/apache/jena/rdf/model/Model;
       3: aload_0
       4: invokevirtual #12                 // Method java/net/URI.toString:()Ljava/lang/String;
       7: invokeinterface #13,  2           // InterfaceMethod org/apache/jena/rdf/model/Model.getResource:(Ljava/lang/String;)Lorg/apache/jena/rdf/model/Resource;
      12: areturn

  static {};
    Code:
       0: invokestatic  #14                 // Method org/apache/jena/rdf/model/ModelFactory.createDefaultModel:()Lorg/apache/jena/rdf/model/Model;
       3: putstatic     #11                 // Field m:Lorg/apache/jena/rdf/model/Model;
       6: getstatic     #11                 // Field m:Lorg/apache/jena/rdf/model/Model;
       9: ldc           #15                 // String https://w3id.org/won/message#protocolVersion
      11: invokeinterface #16,  2           // InterfaceMethod org/apache/jena/rdf/model/Model.createProperty:(Ljava/lang/String;)Lorg/apache/jena/rdf/model/Property;
      16: putstatic     #17                 // Field PROTOCOL_VERSION:Lorg/apache/jena/rdf/model/Property;
      19: getstatic     #11                 // Field m:Lorg/apache/jena/rdf/model/Model;
      22: ldc           #18                 // String https://w3id.org/won/message#FromOwner
      24: invokeinterface #19,  2           // InterfaceMethod org/apache/jena/rdf/model/Model.createResource:(Ljava/lang/String;)Lorg/apache/jena/rdf/model/Resource;
      29: putstatic     #20                 // Field FromOwner:Lorg/apache/jena/rdf/model/Resource;
      32: getstatic     #11                 // Field m:Lorg/apache/jena/rdf/model/Model;
      35: ldc           #21                 // String https://w3id.org/won/message#FromSystem
      37: invokeinterface #19,  2           // InterfaceMethod org/apache/jena/rdf/model/Model.createResource:(Ljava/lang/String;)Lorg/apache/jena/rdf/model/Resource;
      42: putstatic     #22                 // Field FromSystem:Lorg/apache/jena/rdf/model/Resource;
      45: getstatic     #11                 // Field m:Lorg/apache/jena/rdf/model/Model;
      48: ldc           #23                 // String https://w3id.org/won/message#FromExternal
      50: invokeinterface #19,  2           // InterfaceMethod org/apache/jena/rdf/model/Model.createResource:(Ljava/lang/String;)Lorg/apache/jena/rdf/model/Resource;
      55: putstatic     #24                 // Field FromExternal:Lorg/apache/jena/rdf/model/Resource;
      58: getstatic     #11                 // Field m:Lorg/apache/jena/rdf/model/Model;
      61: ldc           #25                 // String https://w3id.org/won/message#CreateMessage
      63: invokeinterface #19,  2           // InterfaceMethod org/apache/jena/rdf/model/Model.createResource:(Ljava/lang/String;)Lorg/apache/jena/rdf/model/Resource;
      68: putstatic     #26                 // Field CreateMessage:Lorg/apache/jena/rdf/model/Resource;
      71: getstatic     #11                 // Field m:Lorg/apache/jena/rdf/model/Model;
      74: ldc           #27                 // String https://w3id.org/won/message#ReplaceMessage
      76: invokeinterface #19,  2           // InterfaceMethod org/apache/jena/rdf/model/Model.createResource:(Ljava/lang/String;)Lorg/apache/jena/rdf/model/Resource;
      81: putstatic     #28                 // Field ReplaceMessage:Lorg/apache/jena/rdf/model/Resource;
      84: getstatic     #11                 // Field m:Lorg/apache/jena/rdf/model/Model;
      87: ldc           #29                 // String https://w3id.org/won/message#ChangeNotificationMessage
      89: invokeinterface #19,  2           // InterfaceMethod org/apache/jena/rdf/model/Model.createResource:(Ljava/lang/String;)Lorg/apache/jena/rdf/model/Resource;
      94: putstatic     #30                 // Field ChangeNotificationMessage:Lorg/apache/jena/rdf/model/Resource;
      97: getstatic     #11                 // Field m:Lorg/apache/jena/rdf/model/Model;
     100: ldc           #31                 // String https://w3id.org/won/message#ConnectMessage
     102: invokeinterface #19,  2           // InterfaceMethod org/apache/jena/rdf/model/Model.createResource:(Ljava/lang/String;)Lorg/apache/jena/rdf/model/Resource;
     107: putstatic     #32                 // Field ConnectMessage:Lorg/apache/jena/rdf/model/Resource;
     110: getstatic     #11                 // Field m:Lorg/apache/jena/rdf/model/Model;
     113: ldc           #33                 // String https://w3id.org/won/message#DeactivateMessage
     115: invokeinterface #19,  2           // InterfaceMethod org/apache/jena/rdf/model/Model.createResource:(Ljava/lang/String;)Lorg/apache/jena/rdf/model/Resource;
     120: putstatic     #34                 // Field DeactivateMessage:Lorg/apache/jena/rdf/model/Resource;
     123: getstatic     #11                 // Field m:Lorg/apache/jena/rdf/model/Model;
     126: ldc           #35                 // String https://w3id.org/won/message#ActivateMessage
     128: invokeinterface #19,  2           // InterfaceMethod org/apache/jena/rdf/model/Model.createResource:(Ljava/lang/String;)Lorg/apache/jena/rdf/model/Resource;
     133: putstatic     #36                 // Field ActivateMessage:Lorg/apache/jena/rdf/model/Resource;
     136: getstatic     #11                 // Field m:Lorg/apache/jena/rdf/model/Model;
     139: ldc           #37                 // String https://w3id.org/won/message#OpenMessage
     141: invokeinterface #19,  2           // InterfaceMethod org/apache/jena/rdf/model/Model.createResource:(Ljava/lang/String;)Lorg/apache/jena/rdf/model/Resource;
     146: putstatic     #38                 // Field OpenMessage:Lorg/apache/jena/rdf/model/Resource;
     149: getstatic     #11                 // Field m:Lorg/apache/jena/rdf/model/Model;
     152: ldc           #39                 // String https://w3id.org/won/message#CloseMessage
     154: invokeinterface #19,  2           // InterfaceMethod org/apache/jena/rdf/model/Model.createResource:(Ljava/lang/String;)Lorg/apache/jena/rdf/model/Resource;
     159: putstatic     #40                 // Field CloseMessage:Lorg/apache/jena/rdf/model/Resource;
     162: getstatic     #11                 // Field m:Lorg/apache/jena/rdf/model/Model;
     165: ldc           #41                 // String https://w3id.org/won/message#DeleteMessage
     167: invokeinterface #19,  2           // InterfaceMethod org/apache/jena/rdf/model/Model.createResource:(Ljava/lang/String;)Lorg/apache/jena/rdf/model/Resource;
     172: putstatic     #42                 // Field DeleteMessage:Lorg/apache/jena/rdf/model/Resource;
     175: getstatic     #11                 // Field m:Lorg/apache/jena/rdf/model/Model;
     178: ldc           #43                 // String https://w3id.org/won/message#ConnectionMessage
     180: invokeinterface #19,  2           // InterfaceMethod org/apache/jena/rdf/model/Model.createResource:(Ljava/lang/String;)Lorg/apache/jena/rdf/model/Resource;
     185: putstatic     #44                 // Field ConnectionMessage:Lorg/apache/jena/rdf/model/Resource;
     188: getstatic     #11                 // Field m:Lorg/apache/jena/rdf/model/Model;
     191: ldc           #45                 // String https://w3id.org/won/message#AtomMessage
     193: invokeinterface #19,  2           // InterfaceMethod org/apache/jena/rdf/model/Model.createResource:(Ljava/lang/String;)Lorg/apache/jena/rdf/model/Resource;
     198: putstatic     #46                 // Field AtomMessage:Lorg/apache/jena/rdf/model/Resource;
     201: getstatic     #11                 // Field m:Lorg/apache/jena/rdf/model/Model;
     204: ldc           #47                 // String https://w3id.org/won/message#SocketHintMessage
     206: invokeinterface #19,  2           // InterfaceMethod org/apache/jena/rdf/model/Model.createResource:(Ljava/lang/String;)Lorg/apache/jena/rdf/model/Resource;
     211: putstatic     #48                 // Field SocketHintMessage:Lorg/apache/jena/rdf/model/Resource;
     214: getstatic     #11                 // Field m:Lorg/apache/jena/rdf/model/Model;
     217: ldc           #49                 // String https://w3id.org/won/message#AtomHintMessage
     219: invokeinterface #19,  2           // InterfaceMethod org/apache/jena/rdf/model/Model.createResource:(Ljava/lang/String;)Lorg/apache/jena/rdf/model/Resource;
     224: putstatic     #50                 // Field AtomHintMessage:Lorg/apache/jena/rdf/model/Resource;
     227: getstatic     #11                 // Field m:Lorg/apache/jena/rdf/model/Model;
     230: ldc           #51                 // String https://w3id.org/won/message#HintFeedbackMessage
     232: invokeinterface #19,  2           // InterfaceMethod org/apache/jena/rdf/model/Model.createResource:(Ljava/lang/String;)Lorg/apache/jena/rdf/model/Resource;
     237: putstatic     #52                 // Field HintFeedbackMessage:Lorg/apache/jena/rdf/model/Resource;
     240: getstatic     #11                 // Field m:Lorg/apache/jena/rdf/model/Model;
     243: ldc           #53                 // String https://w3id.org/won/message#SuccessResponse
     245: invokeinterface #19,  2           // InterfaceMethod org/apache/jena/rdf/model/Model.createResource:(Ljava/lang/String;)Lorg/apache/jena/rdf/model/Resource;
     250: putstatic     #54                 // Field SuccessResponse:Lorg/apache/jena/rdf/model/Resource;
     253: getstatic     #11                 // Field m:Lorg/apache/jena/rdf/model/Model;
     256: ldc           #55                 // String https://w3id.org/won/message#FailureResponse
     258: invokeinterface #19,  2           // InterfaceMethod org/apache/jena/rdf/model/Model.createResource:(Ljava/lang/String;)Lorg/apache/jena/rdf/model/Resource;
     263: putstatic     #56                 // Field FailureResponse:Lorg/apache/jena/rdf/model/Resource;
     266: getstatic     #11                 // Field m:Lorg/apache/jena/rdf/model/Model;
     269: ldc           #57                 // String https://w3id.org/won/message#HintNotificationMessage
     271: invokeinterface #19,  2           // InterfaceMethod org/apache/jena/rdf/model/Model.createResource:(Ljava/lang/String;)Lorg/apache/jena/rdf/model/Resource;
     276: putstatic     #58                 // Field HintNotificationMessage:Lorg/apache/jena/rdf/model/Resource;
     279: getstatic     #11                 // Field m:Lorg/apache/jena/rdf/model/Model;
     282: ldc           #59                 // String https://w3id.org/won/message#AtomCreatedNotificationMessage
     284: invokeinterface #19,  2           // InterfaceMethod org/apache/jena/rdf/model/Model.createResource:(Ljava/lang/String;)Lorg/apache/jena/rdf/model/Resource;
     289: putstatic     #60                 // Field AtomCreatedNotificationMessage:Lorg/apache/jena/rdf/model/Resource;
     292: getstatic     #11                 // Field m:Lorg/apache/jena/rdf/model/Model;
     295: ldc           #61                 // String https://w3id.org/won/message#CreateResponseMessage
     297: invokeinterface #19,  2           // InterfaceMethod org/apache/jena/rdf/model/Model.createResource:(Ljava/lang/String;)Lorg/apache/jena/rdf/model/Resource;
     302: putstatic     #3                  // Field CreateResponseMessage:Lorg/apache/jena/rdf/model/Resource;
     305: getstatic     #11                 // Field m:Lorg/apache/jena/rdf/model/Model;
     308: ldc           #62                 // String https://w3id.org/won/message#ConnectResponseMessage
     310: invokeinterface #19,  2           // InterfaceMethod org/apache/jena/rdf/model/Model.createResource:(Ljava/lang/String;)Lorg/apache/jena/rdf/model/Resource;
     315: putstatic     #5                  // Field ConnectResponseMessage:Lorg/apache/jena/rdf/model/Resource;
     318: getstatic     #11                 // Field m:Lorg/apache/jena/rdf/model/Model;
     321: ldc           #63                 // String https://w3id.org/won/message#AtomStateResponseMessage
     323: invokeinterface #19,  2           // InterfaceMethod org/apache/jena/rdf/model/Model.createResource:(Ljava/lang/String;)Lorg/apache/jena/rdf/model/Resource;
     328: putstatic     #6                  // Field AtomStateResponseMessage:Lorg/apache/jena/rdf/model/Resource;
     331: getstatic     #11                 // Field m:Lorg/apache/jena/rdf/model/Model;
     334: ldc           #64                 // String https://w3id.org/won/message#CloseResponseMessage
     336: invokeinterface #19,  2           // InterfaceMethod org/apache/jena/rdf/model/Model.createResource:(Ljava/lang/String;)Lorg/apache/jena/rdf/model/Resource;
     341: putstatic     #7                  // Field CloseResponseMessage:Lorg/apache/jena/rdf/model/Resource;
     344: getstatic     #11                 // Field m:Lorg/apache/jena/rdf/model/Model;
     347: ldc           #65                 // String https://w3id.org/won/message#OpenResponseMessage
     349: invokeinterface #19,  2           // InterfaceMethod org/apache/jena/rdf/model/Model.createResource:(Ljava/lang/String;)Lorg/apache/jena/rdf/model/Resource;
     354: putstatic     #8                  // Field OpenResponseMessage:Lorg/apache/jena/rdf/model/Resource;
     357: getstatic     #11                 // Field m:Lorg/apache/jena/rdf/model/Model;
     360: ldc           #66                 // String https://w3id.org/won/message#ConnectionMessageResponseMessage
     362: invokeinterface #19,  2           // InterfaceMethod org/apache/jena/rdf/model/Model.createResource:(Ljava/lang/String;)Lorg/apache/jena/rdf/model/Resource;
     367: putstatic     #9                  // Field ConnectionMessageResponseMessage:Lorg/apache/jena/rdf/model/Resource;
     370: getstatic     #11                 // Field m:Lorg/apache/jena/rdf/model/Model;
     373: ldc           #53                 // String https://w3id.org/won/message#SuccessResponse
     375: invokeinterface #19,  2           // InterfaceMethod org/apache/jena/rdf/model/Model.createResource:(Ljava/lang/String;)Lorg/apache/jena/rdf/model/Resource;
     380: putstatic     #67                 // Field SuccessResponseState:Lorg/apache/jena/rdf/model/Resource;
     383: getstatic     #11                 // Field m:Lorg/apache/jena/rdf/model/Model;
     386: ldc           #55                 // String https://w3id.org/won/message#FailureResponse
     388: invokeinterface #19,  2           // InterfaceMethod org/apache/jena/rdf/model/Model.createResource:(Ljava/lang/String;)Lorg/apache/jena/rdf/model/Resource;
     393: putstatic     #68                 // Field FailureResponseState:Lorg/apache/jena/rdf/model/Resource;
     396: getstatic     #11                 // Field m:Lorg/apache/jena/rdf/model/Model;
     399: ldc           #69                 // String https://w3id.org/won/message#DuplicateAtomIdResponse
     401: invokeinterface #19,  2           // InterfaceMethod org/apache/jena/rdf/model/Model.createResource:(Ljava/lang/String;)Lorg/apache/jena/rdf/model/Resource;
     406: putstatic     #70                 // Field DuplicateAtomIdResponseState:Lorg/apache/jena/rdf/model/Resource;
     409: getstatic     #11                 // Field m:Lorg/apache/jena/rdf/model/Model;
     412: ldc           #71                 // String https://w3id.org/won/message#DuplicateConnectionIdResponse
     414: invokeinterface #19,  2           // InterfaceMethod org/apache/jena/rdf/model/Model.createResource:(Ljava/lang/String;)Lorg/apache/jena/rdf/model/Resource;
     419: putstatic     #72                 // Field DuplicateConnectionIdResponseState:Lorg/apache/jena/rdf/model/Resource;
     422: getstatic     #11                 // Field m:Lorg/apache/jena/rdf/model/Model;
     425: ldc           #73                 // String https://w3id.org/won/message#DuplicateMessageIdResponse
     427: invokeinterface #19,  2           // InterfaceMethod org/apache/jena/rdf/model/Model.createResource:(Ljava/lang/String;)Lorg/apache/jena/rdf/model/Resource;
     432: putstatic     #74                 // Field DuplicateMessageIdResponseState:Lorg/apache/jena/rdf/model/Resource;
     435: getstatic     #11                 // Field m:Lorg/apache/jena/rdf/model/Model;
     438: ldc           #75                 // String https://w3id.org/won/message#responseStateProperty
     440: invokeinterface #16,  2           // InterfaceMethod org/apache/jena/rdf/model/Model.createProperty:(Ljava/lang/String;)Lorg/apache/jena/rdf/model/Property;
     445: putstatic     #76                 // Field responseStateProperty:Lorg/apache/jena/rdf/model/Property;
     448: getstatic     #11                 // Field m:Lorg/apache/jena/rdf/model/Model;
     451: ldc           #77                 // String https://w3id.org/won/message#EnvelopeGraph
     453: invokeinterface #19,  2           // InterfaceMethod org/apache/jena/rdf/model/Model.createResource:(Ljava/lang/String;)Lorg/apache/jena/rdf/model/Resource;
     458: putstatic     #78                 // Field EnvelopeGraph:Lorg/apache/jena/rdf/model/Resource;
     461: getstatic     #11                 // Field m:Lorg/apache/jena/rdf/model/Model;
     464: ldc           #79                 // String https://w3id.org/won/message#ForwardedEnvelopeGraph
     466: invokeinterface #19,  2           // InterfaceMethod org/apache/jena/rdf/model/Model.createResource:(Ljava/lang/String;)Lorg/apache/jena/rdf/model/Resource;
     471: putstatic     #80                 // Field ForwardedEnvelopeGraph:Lorg/apache/jena/rdf/model/Resource;
     474: getstatic     #11                 // Field m:Lorg/apache/jena/rdf/model/Model;
     477: ldc           #10                 // String https://w3id.org/won/message#
     479: ldc           #81                 // String containsEnvelope
     481: invokeinterface #82,  3           // InterfaceMethod org/apache/jena/rdf/model/Model.createProperty:(Ljava/lang/String;Ljava/lang/String;)Lorg/apache/jena/rdf/model/Property;
     486: putstatic     #83                 // Field containsEnvelope:Lorg/apache/jena/rdf/model/Property;
     489: getstatic     #11                 // Field m:Lorg/apache/jena/rdf/model/Model;
     492: ldc           #10                 // String https://w3id.org/won/message#
     494: ldc           #84                 // String recipient
     496: invokeinterface #82,  3           // InterfaceMethod org/apache/jena/rdf/model/Model.createProperty:(Ljava/lang/String;Ljava/lang/String;)Lorg/apache/jena/rdf/model/Property;
     501: putstatic     #85                 // Field recipient:Lorg/apache/jena/rdf/model/Property;
     504: getstatic     #11                 // Field m:Lorg/apache/jena/rdf/model/Model;
     507: ldc           #10                 // String https://w3id.org/won/message#
     509: ldc           #86                 // String recipientAtom
     511: invokeinterface #82,  3           // InterfaceMethod org/apache/jena/rdf/model/Model.createProperty:(Ljava/lang/String;Ljava/lang/String;)Lorg/apache/jena/rdf/model/Property;
     516: putstatic     #87                 // Field recipientAtom:Lorg/apache/jena/rdf/model/Property;
     519: getstatic     #11                 // Field m:Lorg/apache/jena/rdf/model/Model;
     522: ldc           #10                 // String https://w3id.org/won/message#
     524: ldc           #88                 // String recipientNode
     526: invokeinterface #82,  3           // InterfaceMethod org/apache/jena/rdf/model/Model.createProperty:(Ljava/lang/String;Ljava/lang/String;)Lorg/apache/jena/rdf/model/Property;
     531: putstatic     #89                 // Field recipientNode:Lorg/apache/jena/rdf/model/Property;
     534: getstatic     #11                 // Field m:Lorg/apache/jena/rdf/model/Model;
     537: ldc           #10                 // String https://w3id.org/won/message#
     539: ldc           #90                 // String sender
     541: invokeinterface #82,  3           // InterfaceMethod org/apache/jena/rdf/model/Model.createProperty:(Ljava/lang/String;Ljava/lang/String;)Lorg/apache/jena/rdf/model/Property;
     546: putstatic     #91                 // Field sender:Lorg/apache/jena/rdf/model/Property;
     549: getstatic     #11                 // Field m:Lorg/apache/jena/rdf/model/Model;
     552: ldc           #10                 // String https://w3id.org/won/message#
     554: ldc           #92                 // String senderAtom
     556: invokeinterface #82,  3           // InterfaceMethod org/apache/jena/rdf/model/Model.createProperty:(Ljava/lang/String;Ljava/lang/String;)Lorg/apache/jena/rdf/model/Property;
     561: putstatic     #93                 // Field senderAtom:Lorg/apache/jena/rdf/model/Property;
     564: getstatic     #11                 // Field m:Lorg/apache/jena/rdf/model/Model;
     567: ldc           #10                 // String https://w3id.org/won/message#
     569: ldc           #94                 // String senderNode
     571: invokeinterface #82,  3           // InterfaceMethod org/apache/jena/rdf/model/Model.createProperty:(Ljava/lang/String;Ljava/lang/String;)Lorg/apache/jena/rdf/model/Property;
     576: putstatic     #95                 // Field senderNode:Lorg/apache/jena/rdf/model/Property;
     579: getstatic     #11                 // Field m:Lorg/apache/jena/rdf/model/Model;
     582: ldc           #10                 // String https://w3id.org/won/message#
     584: ldc           #96                 // String messageType
     586: invokeinterface #82,  3           // InterfaceMethod org/apache/jena/rdf/model/Model.createProperty:(Ljava/lang/String;Ljava/lang/String;)Lorg/apache/jena/rdf/model/Property;
     591: putstatic     #97                 // Field messageType:Lorg/apache/jena/rdf/model/Property;
     594: getstatic     #11                 // Field m:Lorg/apache/jena/rdf/model/Model;
     597: ldc           #10                 // String https://w3id.org/won/message#
     599: ldc           #98                 // String content
     601: invokeinterface #82,  3           // InterfaceMethod org/apache/jena/rdf/model/Model.createProperty:(Ljava/lang/String;Ljava/lang/String;)Lorg/apache/jena/rdf/model/Property;
     606: putstatic     #99                 // Field content:Lorg/apache/jena/rdf/model/Property;
     609: getstatic     #11                 // Field m:Lorg/apache/jena/rdf/model/Model;
     612: ldc           #10                 // String https://w3id.org/won/message#
     614: ldc           #100                // String isResponseTo
     616: invokeinterface #82,  3           // InterfaceMethod org/apache/jena/rdf/model/Model.createProperty:(Ljava/lang/String;Ljava/lang/String;)Lorg/apache/jena/rdf/model/Property;
     621: putstatic     #101                // Field isResponseTo:Lorg/apache/jena/rdf/model/Property;
     624: getstatic     #11                 // Field m:Lorg/apache/jena/rdf/model/Model;
     627: ldc           #10                 // String https://w3id.org/won/message#
     629: ldc           #102                // String isRemoteResponseTo
     631: invokeinterface #82,  3           // InterfaceMethod org/apache/jena/rdf/model/Model.createProperty:(Ljava/lang/String;Ljava/lang/String;)Lorg/apache/jena/rdf/model/Property;
     636: putstatic     #103                // Field isRemoteResponseTo:Lorg/apache/jena/rdf/model/Property;
     639: getstatic     #11                 // Field m:Lorg/apache/jena/rdf/model/Model;
     642: ldc           #10                 // String https://w3id.org/won/message#
     644: ldc           #104                // String isResponseToMessageType
     646: invokeinterface #82,  3           // InterfaceMethod org/apache/jena/rdf/model/Model.createProperty:(Ljava/lang/String;Ljava/lang/String;)Lorg/apache/jena/rdf/model/Property;
     651: putstatic     #105                // Field isResponseToMessageType:Lorg/apache/jena/rdf/model/Property;
     654: getstatic     #11                 // Field m:Lorg/apache/jena/rdf/model/Model;
     657: ldc           #10                 // String https://w3id.org/won/message#
     659: ldc           #106                // String correspondingRemoteMessage
     661: invokeinterface #82,  3           // InterfaceMethod org/apache/jena/rdf/model/Model.createProperty:(Ljava/lang/String;Ljava/lang/String;)Lorg/apache/jena/rdf/model/Property;
     666: putstatic     #107                // Field correspondingRemoteMessage:Lorg/apache/jena/rdf/model/Property;
     669: getstatic     #11                 // Field m:Lorg/apache/jena/rdf/model/Model;
     672: ldc           #10                 // String https://w3id.org/won/message#
     674: ldc           #108                // String forwardedMessage
     676: invokeinterface #82,  3           // InterfaceMethod org/apache/jena/rdf/model/Model.createProperty:(Ljava/lang/String;Ljava/lang/String;)Lorg/apache/jena/rdf/model/Property;
     681: putstatic     #109                // Field forwardedMessage:Lorg/apache/jena/rdf/model/Property;
     684: getstatic     #11                 // Field m:Lorg/apache/jena/rdf/model/Model;
     687: ldc           #10                 // String https://w3id.org/won/message#
     689: ldc           #110                // String injectIntoConnection
     691: invokeinterface #82,  3           // InterfaceMethod org/apache/jena/rdf/model/Model.createProperty:(Ljava/lang/String;Ljava/lang/String;)Lorg/apache/jena/rdf/model/Property;
     696: putstatic     #111                // Field injectIntoConnection:Lorg/apache/jena/rdf/model/Property;
     699: getstatic     #11                 // Field m:Lorg/apache/jena/rdf/model/Model;
     702: ldc           #112                // String https://w3id.org/won/message#previousMessage
     704: invokeinterface #16,  2           // InterfaceMethod org/apache/jena/rdf/model/Model.createProperty:(Ljava/lang/String;)Lorg/apache/jena/rdf/model/Property;
     709: putstatic     #113                // Field previousMessage:Lorg/apache/jena/rdf/model/Property;
     712: getstatic     #11                 // Field m:Lorg/apache/jena/rdf/model/Model;
     715: ldc           #10                 // String https://w3id.org/won/message#
     717: ldc           #114                // String sentTimestamp
     719: invokeinterface #82,  3           // InterfaceMethod org/apache/jena/rdf/model/Model.createProperty:(Ljava/lang/String;Ljava/lang/String;)Lorg/apache/jena/rdf/model/Property;
     724: putstatic     #115                // Field sentTimestamp:Lorg/apache/jena/rdf/model/Property;
     727: getstatic     #11                 // Field m:Lorg/apache/jena/rdf/model/Model;
     730: ldc           #10                 // String https://w3id.org/won/message#
     732: ldc           #116                // String receivedTimestamp
     734: invokeinterface #82,  3           // InterfaceMethod org/apache/jena/rdf/model/Model.createProperty:(Ljava/lang/String;Ljava/lang/String;)Lorg/apache/jena/rdf/model/Property;
     739: putstatic     #117                // Field receivedTimestamp:Lorg/apache/jena/rdf/model/Property;
     742: getstatic     #11                 // Field m:Lorg/apache/jena/rdf/model/Model;
     745: ldc           #10                 // String https://w3id.org/won/message#
     747: ldc           #118                // String containsSignature
     749: invokeinterface #82,  3           // InterfaceMethod org/apache/jena/rdf/model/Model.createProperty:(Ljava/lang/String;Ljava/lang/String;)Lorg/apache/jena/rdf/model/Property;
     754: putstatic     #119                // Field containsSignature:Lorg/apache/jena/rdf/model/Property;
     757: getstatic     #11                 // Field m:Lorg/apache/jena/rdf/model/Model;
     760: ldc           #10                 // String https://w3id.org/won/message#
     762: ldc           #120                // String signedGraph
     764: invokeinterface #82,  3           // InterfaceMethod org/apache/jena/rdf/model/Model.createProperty:(Ljava/lang/String;Ljava/lang/String;)Lorg/apache/jena/rdf/model/Property;
     769: putstatic     #121                // Field signedGraph:Lorg/apache/jena/rdf/model/Property;
     772: getstatic     #11                 // Field m:Lorg/apache/jena/rdf/model/Model;
     775: ldc           #10                 // String https://w3id.org/won/message#
     777: ldc           #122                // String signatureValue
     779: invokeinterface #82,  3           // InterfaceMethod org/apache/jena/rdf/model/Model.createProperty:(Ljava/lang/String;Ljava/lang/String;)Lorg/apache/jena/rdf/model/Property;
     784: putstatic     #123                // Field signatureValue:Lorg/apache/jena/rdf/model/Property;
     787: getstatic     #11                 // Field m:Lorg/apache/jena/rdf/model/Model;
     790: ldc           #10                 // String https://w3id.org/won/message#
     792: ldc           #124                // String hash
     794: invokeinterface #82,  3           // InterfaceMethod org/apache/jena/rdf/model/Model.createProperty:(Ljava/lang/String;Ljava/lang/String;)Lorg/apache/jena/rdf/model/Property;
     799: putstatic     #125                // Field hash:Lorg/apache/jena/rdf/model/Property;
     802: getstatic     #11                 // Field m:Lorg/apache/jena/rdf/model/Model;
     805: ldc           #10                 // String https://w3id.org/won/message#
     807: ldc           #126                // String signatureGraph
     809: invokeinterface #82,  3           // InterfaceMethod org/apache/jena/rdf/model/Model.createProperty:(Ljava/lang/String;Ljava/lang/String;)Lorg/apache/jena/rdf/model/Property;
     814: putstatic     #127                // Field signatureGraph:Lorg/apache/jena/rdf/model/Property;
     817: getstatic     #11                 // Field m:Lorg/apache/jena/rdf/model/Model;
     820: ldc           #10                 // String https://w3id.org/won/message#
     822: ldc           #128                // String publicKeyFingerprint
     824: invokeinterface #82,  3           // InterfaceMethod org/apache/jena/rdf/model/Model.createProperty:(Ljava/lang/String;Ljava/lang/String;)Lorg/apache/jena/rdf/model/Property;
     829: putstatic     #129                // Field publicKeyFingerprint:Lorg/apache/jena/rdf/model/Property;
     832: getstatic     #11                 // Field m:Lorg/apache/jena/rdf/model/Model;
     835: ldc           #10                 // String https://w3id.org/won/message#
     837: ldc           #130                // String recipientSocket
     839: invokeinterface #82,  3           // InterfaceMethod org/apache/jena/rdf/model/Model.createProperty:(Ljava/lang/String;Ljava/lang/String;)Lorg/apache/jena/rdf/model/Property;
     844: putstatic     #131                // Field recipientSocket:Lorg/apache/jena/rdf/model/Property;
     847: getstatic     #11                 // Field m:Lorg/apache/jena/rdf/model/Model;
     850: ldc           #10                 // String https://w3id.org/won/message#
     852: ldc           #132                // String senderSocket
     854: invokeinterface #82,  3           // InterfaceMethod org/apache/jena/rdf/model/Model.createProperty:(Ljava/lang/String;Ljava/lang/String;)Lorg/apache/jena/rdf/model/Property;
     859: putstatic     #133                // Field senderSocket:Lorg/apache/jena/rdf/model/Property;
     862: getstatic     #11                 // Field m:Lorg/apache/jena/rdf/model/Model;
     865: ldc           #10                 // String https://w3id.org/won/message#
     867: ldc           #134                // String contentType
     869: invokeinterface #82,  3           // InterfaceMethod org/apache/jena/rdf/model/Model.createProperty:(Ljava/lang/String;Ljava/lang/String;)Lorg/apache/jena/rdf/model/Property;
     874: putstatic     #135                // Field contentType:Lorg/apache/jena/rdf/model/Property;
     877: getstatic     #11                 // Field m:Lorg/apache/jena/rdf/model/Model;
     880: ldc           #10                 // String https://w3id.org/won/message#
     882: ldc           #136                // String hintScore
     884: invokeinterface #82,  3           // InterfaceMethod org/apache/jena/rdf/model/Model.createProperty:(Ljava/lang/String;Ljava/lang/String;)Lorg/apache/jena/rdf/model/Property;
     889: putstatic     #137                // Field hintScore:Lorg/apache/jena/rdf/model/Property;
     892: getstatic     #11                 // Field m:Lorg/apache/jena/rdf/model/Model;
     895: ldc           #10                 // String https://w3id.org/won/message#
     897: ldc           #138                // String hintTargetAtom
     899: invokeinterface #82,  3           // InterfaceMethod org/apache/jena/rdf/model/Model.createProperty:(Ljava/lang/String;Ljava/lang/String;)Lorg/apache/jena/rdf/model/Property;
     904: putstatic     #139                // Field hintTargetAtom:Lorg/apache/jena/rdf/model/Property;
     907: getstatic     #11                 // Field m:Lorg/apache/jena/rdf/model/Model;
     910: ldc           #10                 // String https://w3id.org/won/message#
     912: ldc           #140                // String hintTargetSocket
     914: invokeinterface #82,  3           // InterfaceMethod org/apache/jena/rdf/model/Model.createProperty:(Ljava/lang/String;Ljava/lang/String;)Lorg/apache/jena/rdf/model/Property;
     919: putstatic     #141                // Field hintTargetSocket:Lorg/apache/jena/rdf/model/Property;
     922: return
}
