Compiled from "move.kt"
final class org.jetbrains.kotlinx.dataframe.impl.api.MoveKt$afterOrBefore$refNode$1 extends kotlin.jvm.internal.Lambda implements kotlin.jvm.functions.Function1<org.jetbrains.kotlinx.dataframe.columns.ColumnPath, org.jetbrains.kotlinx.dataframe.impl.columns.tree.ColumnPosition> {
  final org.jetbrains.kotlinx.dataframe.api.MoveClause<T, C> $this_afterOrBefore;

  org.jetbrains.kotlinx.dataframe.impl.api.MoveKt$afterOrBefore$refNode$1(org.jetbrains.kotlinx.dataframe.api.MoveClause<T, C>);
    Code:
       0: aload_0
       1: aload_1
       2: putfield      #14                 // Field $this_afterOrBefore:Lorg/jetbrains/kotlinx/dataframe/api/MoveClause;
       5: aload_0
       6: iconst_1
       7: invokespecial #17                 // Method kotlin/jvm/internal/Lambda."<init>":(I)V
      10: return

  public final org.jetbrains.kotlinx.dataframe.impl.columns.tree.ColumnPosition invoke(org.jetbrains.kotlinx.dataframe.columns.ColumnPath);
    Code:
       0: aload_1
       1: ldc           #25                 // String it
       3: invokestatic  #31                 // Method kotlin/jvm/internal/Intrinsics.checkNotNullParameter:(Ljava/lang/Object;Ljava/lang/String;)V
       6: aload_1
       7: iconst_1
       8: invokevirtual #37                 // Method org/jetbrains/kotlinx/dataframe/columns/ColumnPath.dropLast:(I)Lorg/jetbrains/kotlinx/dataframe/columns/ColumnPath;
      11: astore_2
      12: aload_2
      13: invokevirtual #41                 // Method org/jetbrains/kotlinx/dataframe/columns/ColumnPath.isEmpty:()Z
      16: ifeq          29
      19: aload_0
      20: getfield      #14                 // Field $this_afterOrBefore:Lorg/jetbrains/kotlinx/dataframe/api/MoveClause;
      23: invokevirtual #47                 // Method org/jetbrains/kotlinx/dataframe/api/MoveClause.getDf$dataframe:()Lorg/jetbrains/kotlinx/dataframe/DataFrame;
      26: goto          46
      29: aload_0
      30: getfield      #14                 // Field $this_afterOrBefore:Lorg/jetbrains/kotlinx/dataframe/api/MoveClause;
      33: invokevirtual #47                 // Method org/jetbrains/kotlinx/dataframe/api/MoveClause.getDf$dataframe:()Lorg/jetbrains/kotlinx/dataframe/DataFrame;
      36: checkcast     #49                 // class org/jetbrains/kotlinx/dataframe/ColumnsContainer
      39: aload_2
      40: invokestatic  #55                 // Method org/jetbrains/kotlinx/dataframe/api/DataFrameGetKt.getColumnGroup:(Lorg/jetbrains/kotlinx/dataframe/ColumnsContainer;Lorg/jetbrains/kotlinx/dataframe/columns/ColumnPath;)Lorg/jetbrains/kotlinx/dataframe/columns/ColumnGroup;
      43: checkcast     #57                 // class org/jetbrains/kotlinx/dataframe/DataFrame
      46: astore_3
      47: aload_3
      48: aload_1
      49: checkcast     #59                 // class java/util/List
      52: invokestatic  #65                 // Method kotlin/collections/CollectionsKt.last:(Ljava/util/List;)Ljava/lang/Object;
      55: checkcast     #67                 // class java/lang/String
      58: invokeinterface #71,  2           // InterfaceMethod org/jetbrains/kotlinx/dataframe/DataFrame.getColumnIndex:(Ljava/lang/String;)I
      63: istore        4
      65: aload_0
      66: getfield      #14                 // Field $this_afterOrBefore:Lorg/jetbrains/kotlinx/dataframe/api/MoveClause;
      69: invokevirtual #47                 // Method org/jetbrains/kotlinx/dataframe/api/MoveClause.getDf$dataframe:()Lorg/jetbrains/kotlinx/dataframe/DataFrame;
      72: checkcast     #49                 // class org/jetbrains/kotlinx/dataframe/ColumnsContainer
      75: iload         4
      77: invokestatic  #75                 // Method org/jetbrains/kotlinx/dataframe/api/DataFrameGetKt.getColumn:(Lorg/jetbrains/kotlinx/dataframe/ColumnsContainer;I)Lorg/jetbrains/kotlinx/dataframe/DataColumn;
      80: astore        5
      82: new           #77                 // class org/jetbrains/kotlinx/dataframe/impl/columns/tree/ColumnPosition
      85: dup
      86: iload         4
      88: iconst_0
      89: aload         5
      91: invokespecial #80                 // Method org/jetbrains/kotlinx/dataframe/impl/columns/tree/ColumnPosition."<init>":(IZLorg/jetbrains/kotlinx/dataframe/DataColumn;)V
      94: areturn

  public java.lang.Object invoke(java.lang.Object);
    Code:
       0: aload_0
       1: aload_1
       2: checkcast     #33                 // class org/jetbrains/kotlinx/dataframe/columns/ColumnPath
       5: invokevirtual #91                 // Method invoke:(Lorg/jetbrains/kotlinx/dataframe/columns/ColumnPath;)Lorg/jetbrains/kotlinx/dataframe/impl/columns/tree/ColumnPosition;
       8: areturn
}
