Compiled from "parse.kt"
final class org.jetbrains.kotlinx.dataframe.impl.api.Parsers$additionalParsers$1 extends kotlin.jvm.internal.Lambda implements kotlin.jvm.functions.Function1<org.jetbrains.kotlinx.dataframe.api.ParserOptions, kotlin.jvm.functions.Function1<? super java.lang.String, ? extends java.time.LocalDate>> {
  public static final org.jetbrains.kotlinx.dataframe.impl.api.Parsers$additionalParsers$1 INSTANCE;

  org.jetbrains.kotlinx.dataframe.impl.api.Parsers$additionalParsers$1();
    Code:
       0: aload_0
       1: iconst_1
       2: invokespecial #12                 // Method kotlin/jvm/internal/Lambda."<init>":(I)V
       5: return

  public final kotlin.jvm.functions.Function1<java.lang.String, java.time.LocalDate> invoke(org.jetbrains.kotlinx.dataframe.api.ParserOptions);
    Code:
       0: aload_1
       1: dup
       2: ifnonnull     10
       5: pop
       6: aconst_null
       7: goto          13
      10: invokevirtual #25                 // Method org/jetbrains/kotlinx/dataframe/api/ParserOptions.getDateTimeFormatter$dataframe:()Ljava/time/format/DateTimeFormatter;
      13: astore_2
      14: new           #27                 // class org/jetbrains/kotlinx/dataframe/impl/api/Parsers$additionalParsers$1$parser$1
      17: dup
      18: aload_2
      19: invokespecial #30                 // Method org/jetbrains/kotlinx/dataframe/impl/api/Parsers$additionalParsers$1$parser$1."<init>":(Ljava/time/format/DateTimeFormatter;)V
      22: checkcast     #7                  // class kotlin/jvm/functions/Function1
      25: astore_3
      26: aload_3
      27: areturn

  public java.lang.Object invoke(java.lang.Object);
    Code:
       0: aload_0
       1: aload_1
       2: checkcast     #21                 // class org/jetbrains/kotlinx/dataframe/api/ParserOptions
       5: invokevirtual #41                 // Method invoke:(Lorg/jetbrains/kotlinx/dataframe/api/ParserOptions;)Lkotlin/jvm/functions/Function1;
       8: areturn

  static {};
    Code:
       0: new           #2                  // class org/jetbrains/kotlinx/dataframe/impl/api/Parsers$additionalParsers$1
       3: dup
       4: invokespecial #46                 // Method "<init>":()V
       7: putstatic     #49                 // Field INSTANCE:Lorg/jetbrains/kotlinx/dataframe/impl/api/Parsers$additionalParsers$1;
      10: return
}
