Compiled from "sort.kt"
public final class org.jetbrains.kotlinx.dataframe.impl.api.SortFlag extends java.lang.Enum<org.jetbrains.kotlinx.dataframe.impl.api.SortFlag> {
  public static final org.jetbrains.kotlinx.dataframe.impl.api.SortFlag Reversed;

  public static final org.jetbrains.kotlinx.dataframe.impl.api.SortFlag NullsLast;

  private static final org.jetbrains.kotlinx.dataframe.impl.api.SortFlag[] $VALUES;

  private org.jetbrains.kotlinx.dataframe.impl.api.SortFlag();
    Code:
       0: aload_0
       1: aload_1
       2: iload_2
       3: invokespecial #10                 // Method java/lang/Enum."<init>":(Ljava/lang/String;I)V
       6: return

  public static org.jetbrains.kotlinx.dataframe.impl.api.SortFlag[] values();
    Code:
       0: getstatic     #22                 // Field $VALUES:[Lorg/jetbrains/kotlinx/dataframe/impl/api/SortFlag;
       3: invokevirtual #28                 // Method "[Ljava/lang/Object;".clone:()Ljava/lang/Object;
       6: checkcast     #29                 // class "[Lorg/jetbrains/kotlinx/dataframe/impl/api/SortFlag;"
       9: areturn

  public static org.jetbrains.kotlinx.dataframe.impl.api.SortFlag valueOf(java.lang.String);
    Code:
       0: ldc           #2                  // class org/jetbrains/kotlinx/dataframe/impl/api/SortFlag
       2: aload_0
       3: invokestatic  #34                 // Method java/lang/Enum.valueOf:(Ljava/lang/Class;Ljava/lang/String;)Ljava/lang/Enum;
       6: checkcast     #2                  // class org/jetbrains/kotlinx/dataframe/impl/api/SortFlag
       9: areturn

  private static final org.jetbrains.kotlinx.dataframe.impl.api.SortFlag[] $values();
    Code:
       0: iconst_2
       1: anewarray     #2                  // class org/jetbrains/kotlinx/dataframe/impl/api/SortFlag
       4: astore_0
       5: aload_0
       6: iconst_0
       7: getstatic     #39                 // Field Reversed:Lorg/jetbrains/kotlinx/dataframe/impl/api/SortFlag;
      10: aastore
      11: aload_0
      12: iconst_1
      13: getstatic     #42                 // Field NullsLast:Lorg/jetbrains/kotlinx/dataframe/impl/api/SortFlag;
      16: aastore
      17: aload_0
      18: areturn

  static {};
    Code:
       0: new           #2                  // class org/jetbrains/kotlinx/dataframe/impl/api/SortFlag
       3: dup
       4: ldc           #44                 // String Reversed
       6: iconst_0
       7: invokespecial #45                 // Method "<init>":(Ljava/lang/String;I)V
      10: putstatic     #39                 // Field Reversed:Lorg/jetbrains/kotlinx/dataframe/impl/api/SortFlag;
      13: new           #2                  // class org/jetbrains/kotlinx/dataframe/impl/api/SortFlag
      16: dup
      17: ldc           #46                 // String NullsLast
      19: iconst_1
      20: invokespecial #45                 // Method "<init>":(Ljava/lang/String;I)V
      23: putstatic     #42                 // Field NullsLast:Lorg/jetbrains/kotlinx/dataframe/impl/api/SortFlag;
      26: invokestatic  #48                 // Method $values:()[Lorg/jetbrains/kotlinx/dataframe/impl/api/SortFlag;
      29: putstatic     #22                 // Field $VALUES:[Lorg/jetbrains/kotlinx/dataframe/impl/api/SortFlag;
      32: return
}
