Compiled from "AbstractUserAgentAnalyzerDirect.java"
public abstract class nl.basjes.parse.useragent.AbstractUserAgentAnalyzerDirect$AbstractUserAgentAnalyzerDirectBuilder<UAA extends nl.basjes.parse.useragent.AbstractUserAgentAnalyzerDirect, B extends nl.basjes.parse.useragent.AbstractUserAgentAnalyzerDirect$AbstractUserAgentAnalyzerDirectBuilder<UAA, B>> {
  private final UAA uaa;

  private boolean didBuildStep;

  private int preheatIterations;

  private final java.util.List<java.lang.String> resources;

  private final java.util.List<java.lang.String> optionalResources;

  private final java.util.List<java.lang.String> yamlRules;

  private final java.util.List<nl.basjes.parse.useragent.calculate.FieldCalculator> fieldCalculators;

  protected final java.util.Set<java.lang.String> allFieldsForWhichACalculatorExists;

  protected void failIfAlreadyBuilt();
    Code:
       0: aload_0
       1: getfield      #30                 // Field didBuildStep:Z
       4: ifeq          17
       7: new           #32                 // class java/lang/IllegalStateException
      10: dup
      11: ldc           #34                 // String A builder can provide only a single instance. It is not allowed to set values after doing build()
      13: invokespecial #38                 // Method java/lang/IllegalStateException."<init>":(Ljava/lang/String;)V
      16: athrow
      17: return

  protected nl.basjes.parse.useragent.AbstractUserAgentAnalyzerDirect$AbstractUserAgentAnalyzerDirectBuilder(UAA);
    Code:
       0: aload_0
       1: invokespecial #45                 // Method java/lang/Object."<init>":()V
       4: aload_0
       5: iconst_0
       6: putfield      #30                 // Field didBuildStep:Z
       9: aload_0
      10: iconst_0
      11: putfield      #47                 // Field preheatIterations:I
      14: aload_0
      15: new           #49                 // class java/util/ArrayList
      18: dup
      19: invokespecial #50                 // Method java/util/ArrayList."<init>":()V
      22: putfield      #52                 // Field resources:Ljava/util/List;
      25: aload_0
      26: new           #49                 // class java/util/ArrayList
      29: dup
      30: invokespecial #50                 // Method java/util/ArrayList."<init>":()V
      33: putfield      #54                 // Field optionalResources:Ljava/util/List;
      36: aload_0
      37: new           #49                 // class java/util/ArrayList
      40: dup
      41: invokespecial #50                 // Method java/util/ArrayList."<init>":()V
      44: putfield      #56                 // Field yamlRules:Ljava/util/List;
      47: aload_0
      48: new           #49                 // class java/util/ArrayList
      51: dup
      52: invokespecial #50                 // Method java/util/ArrayList."<init>":()V
      55: putfield      #58                 // Field fieldCalculators:Ljava/util/List;
      58: aload_0
      59: new           #60                 // class java/util/HashSet
      62: dup
      63: invokespecial #61                 // Method java/util/HashSet."<init>":()V
      66: putfield      #63                 // Field allFieldsForWhichACalculatorExists:Ljava/util/Set;
      69: aload_0
      70: aload_1
      71: putfield      #65                 // Field uaa:Lnl/basjes/parse/useragent/AbstractUserAgentAnalyzerDirect;
      74: aload_0
      75: getfield      #65                 // Field uaa:Lnl/basjes/parse/useragent/AbstractUserAgentAnalyzerDirect;
      78: iconst_0
      79: invokevirtual #69                 // Method nl/basjes/parse/useragent/AbstractUserAgentAnalyzerDirect.setShowMatcherStats:(Z)V
      82: aload_0
      83: getfield      #52                 // Field resources:Ljava/util/List;
      86: ldc           #71                 // String classpath*:UserAgents/**/*.yaml
      88: invokeinterface #77,  2           // InterfaceMethod java/util/List.add:(Ljava/lang/Object;)Z
      93: pop
      94: return

  public B dropDefaultResources();
    Code:
       0: aload_0
       1: invokevirtual #83                 // Method failIfAlreadyBuilt:()V
       4: aload_0
       5: getfield      #52                 // Field resources:Ljava/util/List;
       8: ldc           #71                 // String classpath*:UserAgents/**/*.yaml
      10: invokeinterface #86,  2           // InterfaceMethod java/util/List.remove:(Ljava/lang/Object;)Z
      15: pop
      16: aload_0
      17: areturn

  public B addResources(java.lang.String);
    Code:
       0: aload_0
       1: invokevirtual #83                 // Method failIfAlreadyBuilt:()V
       4: aload_0
       5: getfield      #52                 // Field resources:Ljava/util/List;
       8: aload_1
       9: invokeinterface #77,  2           // InterfaceMethod java/util/List.add:(Ljava/lang/Object;)Z
      14: pop
      15: aload_0
      16: areturn

  public B addOptionalResources(java.lang.String);
    Code:
       0: aload_0
       1: invokevirtual #83                 // Method failIfAlreadyBuilt:()V
       4: aload_0
       5: getfield      #54                 // Field optionalResources:Ljava/util/List;
       8: aload_1
       9: invokeinterface #77,  2           // InterfaceMethod java/util/List.add:(Ljava/lang/Object;)Z
      14: pop
      15: aload_0
      16: areturn

  public B addYamlRule(java.lang.String);
    Code:
       0: aload_0
       1: invokevirtual #83                 // Method failIfAlreadyBuilt:()V
       4: aload_0
       5: getfield      #56                 // Field yamlRules:Ljava/util/List;
       8: aload_1
       9: invokeinterface #77,  2           // InterfaceMethod java/util/List.add:(Ljava/lang/Object;)Z
      14: pop
      15: aload_0
      16: areturn

  public B preheat(int);
    Code:
       0: aload_0
       1: invokevirtual #83                 // Method failIfAlreadyBuilt:()V
       4: aload_0
       5: iload_1
       6: putfield      #47                 // Field preheatIterations:I
       9: aload_0
      10: areturn

  public B preheat();
    Code:
       0: aload_0
       1: invokevirtual #83                 // Method failIfAlreadyBuilt:()V
       4: aload_0
       5: iconst_m1
       6: putfield      #47                 // Field preheatIterations:I
       9: aload_0
      10: areturn

  public B withField(java.lang.String);
    Code:
       0: aload_0
       1: invokevirtual #83                 // Method failIfAlreadyBuilt:()V
       4: aload_0
       5: getfield      #65                 // Field uaa:Lnl/basjes/parse/useragent/AbstractUserAgentAnalyzerDirect;
       8: getfield      #102                // Field nl/basjes/parse/useragent/AbstractUserAgentAnalyzerDirect.wantedFieldNames:Ljava/util/Set;
      11: ifnonnull     28
      14: aload_0
      15: getfield      #65                 // Field uaa:Lnl/basjes/parse/useragent/AbstractUserAgentAnalyzerDirect;
      18: new           #104                // class java/util/TreeSet
      21: dup
      22: invokespecial #105                // Method java/util/TreeSet."<init>":()V
      25: putfield      #102                // Field nl/basjes/parse/useragent/AbstractUserAgentAnalyzerDirect.wantedFieldNames:Ljava/util/Set;
      28: aload_0
      29: getfield      #65                 // Field uaa:Lnl/basjes/parse/useragent/AbstractUserAgentAnalyzerDirect;
      32: getfield      #102                // Field nl/basjes/parse/useragent/AbstractUserAgentAnalyzerDirect.wantedFieldNames:Ljava/util/Set;
      35: aload_1
      36: invokeinterface #108,  2          // InterfaceMethod java/util/Set.add:(Ljava/lang/Object;)Z
      41: pop
      42: aload_0
      43: areturn

  public B withFields(java.util.Collection<java.lang.String>);
    Code:
       0: aload_1
       1: invokeinterface #118,  1          // InterfaceMethod java/util/Collection.iterator:()Ljava/util/Iterator;
       6: astore_2
       7: aload_2
       8: invokeinterface #124,  1          // InterfaceMethod java/util/Iterator.hasNext:()Z
      13: ifeq          35
      16: aload_2
      17: invokeinterface #128,  1          // InterfaceMethod java/util/Iterator.next:()Ljava/lang/Object;
      22: checkcast     #130                // class java/lang/String
      25: astore_3
      26: aload_0
      27: aload_3
      28: invokevirtual #132                // Method withField:(Ljava/lang/String;)Lnl/basjes/parse/useragent/AbstractUserAgentAnalyzerDirect$AbstractUserAgentAnalyzerDirectBuilder;
      31: pop
      32: goto          7
      35: aload_0
      36: areturn

  public B withFields(java.lang.String...);
    Code:
       0: aload_1
       1: astore_2
       2: aload_2
       3: arraylength
       4: istore_3
       5: iconst_0
       6: istore        4
       8: iload         4
      10: iload_3
      11: if_icmpge     33
      14: aload_2
      15: iload         4
      17: aaload
      18: astore        5
      20: aload_0
      21: aload         5
      23: invokevirtual #132                // Method withField:(Ljava/lang/String;)Lnl/basjes/parse/useragent/AbstractUserAgentAnalyzerDirect$AbstractUserAgentAnalyzerDirectBuilder;
      26: pop
      27: iinc          4, 1
      30: goto          8
      33: aload_0
      34: areturn

  public B withAllFields();
    Code:
       0: aload_0
       1: invokevirtual #83                 // Method failIfAlreadyBuilt:()V
       4: aload_0
       5: getfield      #65                 // Field uaa:Lnl/basjes/parse/useragent/AbstractUserAgentAnalyzerDirect;
       8: aconst_null
       9: putfield      #102                // Field nl/basjes/parse/useragent/AbstractUserAgentAnalyzerDirect.wantedFieldNames:Ljava/util/Set;
      12: aload_0
      13: areturn

  public B showMatcherLoadStats();
    Code:
       0: aload_0
       1: invokevirtual #83                 // Method failIfAlreadyBuilt:()V
       4: aload_0
       5: getfield      #65                 // Field uaa:Lnl/basjes/parse/useragent/AbstractUserAgentAnalyzerDirect;
       8: iconst_1
       9: invokevirtual #69                 // Method nl/basjes/parse/useragent/AbstractUserAgentAnalyzerDirect.setShowMatcherStats:(Z)V
      12: aload_0
      13: areturn

  public B hideMatcherLoadStats();
    Code:
       0: aload_0
       1: invokevirtual #83                 // Method failIfAlreadyBuilt:()V
       4: aload_0
       5: getfield      #65                 // Field uaa:Lnl/basjes/parse/useragent/AbstractUserAgentAnalyzerDirect;
       8: iconst_0
       9: invokevirtual #69                 // Method nl/basjes/parse/useragent/AbstractUserAgentAnalyzerDirect.setShowMatcherStats:(Z)V
      12: aload_0
      13: areturn

  public B withUserAgentMaxLength(int);
    Code:
       0: aload_0
       1: invokevirtual #83                 // Method failIfAlreadyBuilt:()V
       4: aload_0
       5: getfield      #65                 // Field uaa:Lnl/basjes/parse/useragent/AbstractUserAgentAnalyzerDirect;
       8: iload_1
       9: invokevirtual #147                // Method nl/basjes/parse/useragent/AbstractUserAgentAnalyzerDirect.setUserAgentMaxLength:(I)V
      12: aload_0
      13: areturn

  public B keepTests();
    Code:
       0: aload_0
       1: invokevirtual #83                 // Method failIfAlreadyBuilt:()V
       4: aload_0
       5: getfield      #65                 // Field uaa:Lnl/basjes/parse/useragent/AbstractUserAgentAnalyzerDirect;
       8: invokevirtual #151                // Method nl/basjes/parse/useragent/AbstractUserAgentAnalyzerDirect.keepTests:()V
      11: aload_0
      12: areturn

  public B dropTests();
    Code:
       0: aload_0
       1: invokevirtual #83                 // Method failIfAlreadyBuilt:()V
       4: aload_0
       5: getfield      #65                 // Field uaa:Lnl/basjes/parse/useragent/AbstractUserAgentAnalyzerDirect;
       8: invokevirtual #154                // Method nl/basjes/parse/useragent/AbstractUserAgentAnalyzerDirect.dropTests:()V
      11: aload_0
      12: areturn

  public B delayInitialization();
    Code:
       0: aload_0
       1: invokevirtual #83                 // Method failIfAlreadyBuilt:()V
       4: aload_0
       5: getfield      #65                 // Field uaa:Lnl/basjes/parse/useragent/AbstractUserAgentAnalyzerDirect;
       8: invokevirtual #157                // Method nl/basjes/parse/useragent/AbstractUserAgentAnalyzerDirect.delayInitialization:()V
      11: aload_0
      12: areturn

  public B immediateInitialization();
    Code:
       0: aload_0
       1: invokevirtual #83                 // Method failIfAlreadyBuilt:()V
       4: aload_0
       5: getfield      #65                 // Field uaa:Lnl/basjes/parse/useragent/AbstractUserAgentAnalyzerDirect;
       8: invokevirtual #160                // Method nl/basjes/parse/useragent/AbstractUserAgentAnalyzerDirect.immediateInitialization:()V
      11: aload_0
      12: areturn

  private void registerFieldCalculator(nl.basjes.parse.useragent.calculate.FieldCalculator);
    Code:
       0: aload_1
       1: invokevirtual #168                // Method nl/basjes/parse/useragent/calculate/FieldCalculator.getCalculatedFieldName:()Ljava/lang/String;
       4: astore_2
       5: aload_0
       6: getfield      #63                 // Field allFieldsForWhichACalculatorExists:Ljava/util/Set;
       9: aload_2
      10: invokeinterface #108,  2          // InterfaceMethod java/util/Set.add:(Ljava/lang/Object;)Z
      15: pop
      16: aload_0
      17: getfield      #65                 // Field uaa:Lnl/basjes/parse/useragent/AbstractUserAgentAnalyzerDirect;
      20: aload_2
      21: invokevirtual #172                // Method nl/basjes/parse/useragent/AbstractUserAgentAnalyzerDirect.isWantedField:(Ljava/lang/String;)Z
      24: ifeq          65
      27: aload_0
      28: getfield      #58                 // Field fieldCalculators:Ljava/util/List;
      31: aload_1
      32: invokeinterface #77,  2           // InterfaceMethod java/util/List.add:(Ljava/lang/Object;)Z
      37: pop
      38: aload_0
      39: getfield      #65                 // Field uaa:Lnl/basjes/parse/useragent/AbstractUserAgentAnalyzerDirect;
      42: getfield      #102                // Field nl/basjes/parse/useragent/AbstractUserAgentAnalyzerDirect.wantedFieldNames:Ljava/util/Set;
      45: ifnull        65
      48: aload_0
      49: getfield      #65                 // Field uaa:Lnl/basjes/parse/useragent/AbstractUserAgentAnalyzerDirect;
      52: getfield      #102                // Field nl/basjes/parse/useragent/AbstractUserAgentAnalyzerDirect.wantedFieldNames:Ljava/util/Set;
      55: aload_1
      56: invokevirtual #176                // Method nl/basjes/parse/useragent/calculate/FieldCalculator.getDependencies:()Ljava/util/Set;
      59: invokeinterface #180,  2          // InterfaceMethod java/util/Set.addAll:(Ljava/util/Collection;)Z
      64: pop
      65: return

  protected void verifyCalculatorDependencyOrdering();
    Code:
       0: new           #60                 // class java/util/HashSet
       3: dup
       4: invokespecial #61                 // Method java/util/HashSet."<init>":()V
       7: astore_1
       8: aload_0
       9: getfield      #58                 // Field fieldCalculators:Ljava/util/List;
      12: invokeinterface #185,  1          // InterfaceMethod java/util/List.iterator:()Ljava/util/Iterator;
      17: astore_2
      18: aload_2
      19: invokeinterface #124,  1          // InterfaceMethod java/util/Iterator.hasNext:()Z
      24: ifeq          157
      27: aload_2
      28: invokeinterface #128,  1          // InterfaceMethod java/util/Iterator.next:()Ljava/lang/Object;
      33: checkcast     #164                // class nl/basjes/parse/useragent/calculate/FieldCalculator
      36: astore_3
      37: aload_3
      38: invokevirtual #176                // Method nl/basjes/parse/useragent/calculate/FieldCalculator.getDependencies:()Ljava/util/Set;
      41: invokeinterface #186,  1          // InterfaceMethod java/util/Set.iterator:()Ljava/util/Iterator;
      46: astore        4
      48: aload         4
      50: invokeinterface #124,  1          // InterfaceMethod java/util/Iterator.hasNext:()Z
      55: ifeq          143
      58: aload         4
      60: invokeinterface #128,  1          // InterfaceMethod java/util/Iterator.next:()Ljava/lang/Object;
      65: checkcast     #130                // class java/lang/String
      68: astore        5
      70: aload_0
      71: getfield      #63                 // Field allFieldsForWhichACalculatorExists:Ljava/util/Set;
      74: aload         5
      76: invokeinterface #189,  2          // InterfaceMethod java/util/Set.contains:(Ljava/lang/Object;)Z
      81: ifeq          140
      84: aload_1
      85: aload         5
      87: invokeinterface #189,  2          // InterfaceMethod java/util/Set.contains:(Ljava/lang/Object;)Z
      92: ifne          140
      95: new           #191                // class nl/basjes/parse/useragent/analyze/InvalidParserConfigurationException
      98: dup
      99: new           #193                // class java/lang/StringBuilder
     102: dup
     103: invokespecial #194                // Method java/lang/StringBuilder."<init>":()V
     106: ldc           #196                // String Calculator ordering is wrong:For
     108: invokevirtual #200                // Method java/lang/StringBuilder.append:(Ljava/lang/String;)Ljava/lang/StringBuilder;
     111: aload_3
     112: invokevirtual #168                // Method nl/basjes/parse/useragent/calculate/FieldCalculator.getCalculatedFieldName:()Ljava/lang/String;
     115: invokevirtual #200                // Method java/lang/StringBuilder.append:(Ljava/lang/String;)Ljava/lang/StringBuilder;
     118: ldc           #202                // String  we need
     120: invokevirtual #200                // Method java/lang/StringBuilder.append:(Ljava/lang/String;)Ljava/lang/StringBuilder;
     123: aload         5
     125: invokevirtual #200                // Method java/lang/StringBuilder.append:(Ljava/lang/String;)Ljava/lang/StringBuilder;
     128: ldc           #204                // String  which is a calculated field but it has not yet been calculated.
     130: invokevirtual #200                // Method java/lang/StringBuilder.append:(Ljava/lang/String;)Ljava/lang/StringBuilder;
     133: invokevirtual #207                // Method java/lang/StringBuilder.toString:()Ljava/lang/String;
     136: invokespecial #208                // Method nl/basjes/parse/useragent/analyze/InvalidParserConfigurationException."<init>":(Ljava/lang/String;)V
     139: athrow
     140: goto          48
     143: aload_1
     144: aload_3
     145: invokevirtual #168                // Method nl/basjes/parse/useragent/calculate/FieldCalculator.getCalculatedFieldName:()Ljava/lang/String;
     148: invokeinterface #108,  2          // InterfaceMethod java/util/Set.add:(Ljava/lang/Object;)Z
     153: pop
     154: goto          18
     157: return

  public UAA build();
    Code:
       0: aload_0
       1: invokevirtual #83                 // Method failIfAlreadyBuilt:()V
       4: aload_0
       5: getfield      #65                 // Field uaa:Lnl/basjes/parse/useragent/AbstractUserAgentAnalyzerDirect;
       8: invokevirtual #216                // Method nl/basjes/parse/useragent/AbstractUserAgentAnalyzerDirect.initTransientFields:()V
      11: invokestatic  #221                // Method nl/basjes/parse/useragent/utils/CheckLoggingDependencies.verifyLoggingDependencies:()V
      14: aload_0
      15: getfield      #65                 // Field uaa:Lnl/basjes/parse/useragent/AbstractUserAgentAnalyzerDirect;
      18: getfield      #102                // Field nl/basjes/parse/useragent/AbstractUserAgentAnalyzerDirect.wantedFieldNames:Ljava/util/Set;
      21: ifnull        54
      24: aload_0
      25: getfield      #65                 // Field uaa:Lnl/basjes/parse/useragent/AbstractUserAgentAnalyzerDirect;
      28: getfield      #102                // Field nl/basjes/parse/useragent/AbstractUserAgentAnalyzerDirect.wantedFieldNames:Ljava/util/Set;
      31: ldc           #223                // String __Set_ALL_Fields__
      33: invokeinterface #108,  2          // InterfaceMethod java/util/Set.add:(Ljava/lang/Object;)Z
      38: pop
      39: aload_0
      40: getfield      #65                 // Field uaa:Lnl/basjes/parse/useragent/AbstractUserAgentAnalyzerDirect;
      43: getfield      #102                // Field nl/basjes/parse/useragent/AbstractUserAgentAnalyzerDirect.wantedFieldNames:Ljava/util/Set;
      46: ldc           #225                // String DeviceClass
      48: invokeinterface #108,  2          // InterfaceMethod java/util/Set.add:(Ljava/lang/Object;)Z
      53: pop
      54: aload_0
      55: new           #227                // class nl/basjes/parse/useragent/calculate/ConcatNONDuplicatedCalculator
      58: dup
      59: ldc           #229                // String AgentNameVersionMajor
      61: ldc           #231                // String AgentName
      63: ldc           #233                // String AgentVersionMajor
      65: invokespecial #236                // Method nl/basjes/parse/useragent/calculate/ConcatNONDuplicatedCalculator."<init>":(Ljava/lang/String;Ljava/lang/String;Ljava/lang/String;)V
      68: invokespecial #238                // Method registerFieldCalculator:(Lnl/basjes/parse/useragent/calculate/FieldCalculator;)V
      71: aload_0
      72: new           #227                // class nl/basjes/parse/useragent/calculate/ConcatNONDuplicatedCalculator
      75: dup
      76: ldc           #240                // String AgentNameVersion
      78: ldc           #231                // String AgentName
      80: ldc           #242                // String AgentVersion
      82: invokespecial #236                // Method nl/basjes/parse/useragent/calculate/ConcatNONDuplicatedCalculator."<init>":(Ljava/lang/String;Ljava/lang/String;Ljava/lang/String;)V
      85: invokespecial #238                // Method registerFieldCalculator:(Lnl/basjes/parse/useragent/calculate/FieldCalculator;)V
      88: aload_0
      89: new           #244                // class nl/basjes/parse/useragent/calculate/MajorVersionCalculator
      92: dup
      93: ldc           #233                // String AgentVersionMajor
      95: ldc           #242                // String AgentVersion
      97: invokespecial #247                // Method nl/basjes/parse/useragent/calculate/MajorVersionCalculator."<init>":(Ljava/lang/String;Ljava/lang/String;)V
     100: invokespecial #238                // Method registerFieldCalculator:(Lnl/basjes/parse/useragent/calculate/FieldCalculator;)V
     103: aload_0
     104: new           #227                // class nl/basjes/parse/useragent/calculate/ConcatNONDuplicatedCalculator
     107: dup
     108: ldc           #249                // String WebviewAppNameVersionMajor
     110: ldc           #251                // String WebviewAppName
     112: ldc           #253                // String WebviewAppVersionMajor
     114: invokespecial #236                // Method nl/basjes/parse/useragent/calculate/ConcatNONDuplicatedCalculator."<init>":(Ljava/lang/String;Ljava/lang/String;Ljava/lang/String;)V
     117: invokespecial #238                // Method registerFieldCalculator:(Lnl/basjes/parse/useragent/calculate/FieldCalculator;)V
     120: aload_0
     121: new           #227                // class nl/basjes/parse/useragent/calculate/ConcatNONDuplicatedCalculator
     124: dup
     125: ldc           #255                // String WebviewAppNameVersion
     127: ldc           #251                // String WebviewAppName
     129: ldc_w         #257                // String WebviewAppVersion
     132: invokespecial #236                // Method nl/basjes/parse/useragent/calculate/ConcatNONDuplicatedCalculator."<init>":(Ljava/lang/String;Ljava/lang/String;Ljava/lang/String;)V
     135: invokespecial #238                // Method registerFieldCalculator:(Lnl/basjes/parse/useragent/calculate/FieldCalculator;)V
     138: aload_0
     139: new           #244                // class nl/basjes/parse/useragent/calculate/MajorVersionCalculator
     142: dup
     143: ldc           #253                // String WebviewAppVersionMajor
     145: ldc_w         #257                // String WebviewAppVersion
     148: invokespecial #247                // Method nl/basjes/parse/useragent/calculate/MajorVersionCalculator."<init>":(Ljava/lang/String;Ljava/lang/String;)V
     151: invokespecial #238                // Method registerFieldCalculator:(Lnl/basjes/parse/useragent/calculate/FieldCalculator;)V
     154: aload_0
     155: new           #227                // class nl/basjes/parse/useragent/calculate/ConcatNONDuplicatedCalculator
     158: dup
     159: ldc_w         #259                // String LayoutEngineNameVersionMajor
     162: ldc_w         #261                // String LayoutEngineName
     165: ldc_w         #263                // String LayoutEngineVersionMajor
     168: invokespecial #236                // Method nl/basjes/parse/useragent/calculate/ConcatNONDuplicatedCalculator."<init>":(Ljava/lang/String;Ljava/lang/String;Ljava/lang/String;)V
     171: invokespecial #238                // Method registerFieldCalculator:(Lnl/basjes/parse/useragent/calculate/FieldCalculator;)V
     174: aload_0
     175: new           #227                // class nl/basjes/parse/useragent/calculate/ConcatNONDuplicatedCalculator
     178: dup
     179: ldc_w         #265                // String LayoutEngineNameVersion
     182: ldc_w         #261                // String LayoutEngineName
     185: ldc_w         #267                // String LayoutEngineVersion
     188: invokespecial #236                // Method nl/basjes/parse/useragent/calculate/ConcatNONDuplicatedCalculator."<init>":(Ljava/lang/String;Ljava/lang/String;Ljava/lang/String;)V
     191: invokespecial #238                // Method registerFieldCalculator:(Lnl/basjes/parse/useragent/calculate/FieldCalculator;)V
     194: aload_0
     195: new           #244                // class nl/basjes/parse/useragent/calculate/MajorVersionCalculator
     198: dup
     199: ldc_w         #263                // String LayoutEngineVersionMajor
     202: ldc_w         #267                // String LayoutEngineVersion
     205: invokespecial #247                // Method nl/basjes/parse/useragent/calculate/MajorVersionCalculator."<init>":(Ljava/lang/String;Ljava/lang/String;)V
     208: invokespecial #238                // Method registerFieldCalculator:(Lnl/basjes/parse/useragent/calculate/FieldCalculator;)V
     211: aload_0
     212: new           #244                // class nl/basjes/parse/useragent/calculate/MajorVersionCalculator
     215: dup
     216: ldc_w         #269                // String OperatingSystemNameVersionMajor
     219: ldc_w         #271                // String OperatingSystemNameVersion
     222: invokespecial #247                // Method nl/basjes/parse/useragent/calculate/MajorVersionCalculator."<init>":(Ljava/lang/String;Ljava/lang/String;)V
     225: invokespecial #238                // Method registerFieldCalculator:(Lnl/basjes/parse/useragent/calculate/FieldCalculator;)V
     228: aload_0
     229: new           #227                // class nl/basjes/parse/useragent/calculate/ConcatNONDuplicatedCalculator
     232: dup
     233: ldc_w         #271                // String OperatingSystemNameVersion
     236: ldc_w         #273                // String OperatingSystemName
     239: ldc_w         #275                // String OperatingSystemVersion
     242: invokespecial #236                // Method nl/basjes/parse/useragent/calculate/ConcatNONDuplicatedCalculator."<init>":(Ljava/lang/String;Ljava/lang/String;Ljava/lang/String;)V
     245: invokespecial #238                // Method registerFieldCalculator:(Lnl/basjes/parse/useragent/calculate/FieldCalculator;)V
     248: aload_0
     249: new           #244                // class nl/basjes/parse/useragent/calculate/MajorVersionCalculator
     252: dup
     253: ldc_w         #277                // String OperatingSystemVersionMajor
     256: ldc_w         #275                // String OperatingSystemVersion
     259: invokespecial #247                // Method nl/basjes/parse/useragent/calculate/MajorVersionCalculator."<init>":(Ljava/lang/String;Ljava/lang/String;)V
     262: invokespecial #238                // Method registerFieldCalculator:(Lnl/basjes/parse/useragent/calculate/FieldCalculator;)V
     265: aload_0
     266: new           #279                // class nl/basjes/parse/useragent/calculate/CalculateAgentClass
     269: dup
     270: invokespecial #280                // Method nl/basjes/parse/useragent/calculate/CalculateAgentClass."<init>":()V
     273: invokespecial #238                // Method registerFieldCalculator:(Lnl/basjes/parse/useragent/calculate/FieldCalculator;)V
     276: aload_0
     277: new           #282                // class nl/basjes/parse/useragent/calculate/CalculateAgentName
     280: dup
     281: invokespecial #283                // Method nl/basjes/parse/useragent/calculate/CalculateAgentName."<init>":()V
     284: invokespecial #238                // Method registerFieldCalculator:(Lnl/basjes/parse/useragent/calculate/FieldCalculator;)V
     287: aload_0
     288: new           #285                // class nl/basjes/parse/useragent/calculate/CalculateNetworkType
     291: dup
     292: invokespecial #286                // Method nl/basjes/parse/useragent/calculate/CalculateNetworkType."<init>":()V
     295: invokespecial #238                // Method registerFieldCalculator:(Lnl/basjes/parse/useragent/calculate/FieldCalculator;)V
     298: aload_0
     299: new           #288                // class nl/basjes/parse/useragent/calculate/CalculateDeviceName
     302: dup
     303: invokespecial #289                // Method nl/basjes/parse/useragent/calculate/CalculateDeviceName."<init>":()V
     306: invokespecial #238                // Method registerFieldCalculator:(Lnl/basjes/parse/useragent/calculate/FieldCalculator;)V
     309: aload_0
     310: new           #291                // class nl/basjes/parse/useragent/calculate/CalculateDeviceBrand
     313: dup
     314: invokespecial #292                // Method nl/basjes/parse/useragent/calculate/CalculateDeviceBrand."<init>":()V
     317: invokespecial #238                // Method registerFieldCalculator:(Lnl/basjes/parse/useragent/calculate/FieldCalculator;)V
     320: aload_0
     321: new           #294                // class nl/basjes/parse/useragent/calculate/CalculateAgentEmail
     324: dup
     325: invokespecial #295                // Method nl/basjes/parse/useragent/calculate/CalculateAgentEmail."<init>":()V
     328: invokespecial #238                // Method registerFieldCalculator:(Lnl/basjes/parse/useragent/calculate/FieldCalculator;)V
     331: aload_0
     332: getfield      #58                 // Field fieldCalculators:Ljava/util/List;
     335: invokestatic  #301                // Method java/util/Collections.reverse:(Ljava/util/List;)V
     338: aload_0
     339: getfield      #65                 // Field uaa:Lnl/basjes/parse/useragent/AbstractUserAgentAnalyzerDirect;
     342: aload_0
     343: getfield      #58                 // Field fieldCalculators:Ljava/util/List;
     346: invokevirtual #304                // Method nl/basjes/parse/useragent/AbstractUserAgentAnalyzerDirect.setFieldCalculators:(Ljava/util/List;)V
     349: aload_0
     350: getfield      #65                 // Field uaa:Lnl/basjes/parse/useragent/AbstractUserAgentAnalyzerDirect;
     353: invokevirtual #307                // Method nl/basjes/parse/useragent/AbstractUserAgentAnalyzerDirect.getShowMatcherStats:()Z
     356: istore_1
     357: new           #309                // class nl/basjes/parse/useragent/config/ConfigLoader
     360: dup
     361: iload_1
     362: invokespecial #311                // Method nl/basjes/parse/useragent/config/ConfigLoader."<init>":(Z)V
     365: aload_0
     366: getfield      #52                 // Field resources:Ljava/util/List;
     369: iconst_0
     370: invokevirtual #315                // Method nl/basjes/parse/useragent/config/ConfigLoader.addResource:(Ljava/util/List;Z)Lnl/basjes/parse/useragent/config/ConfigLoader;
     373: aload_0
     374: getfield      #54                 // Field optionalResources:Ljava/util/List;
     377: iconst_1
     378: invokevirtual #315                // Method nl/basjes/parse/useragent/config/ConfigLoader.addResource:(Ljava/util/List;Z)Lnl/basjes/parse/useragent/config/ConfigLoader;
     381: astore_2
     382: aload_0
     383: getfield      #65                 // Field uaa:Lnl/basjes/parse/useragent/AbstractUserAgentAnalyzerDirect;
     386: invokevirtual #318                // Method nl/basjes/parse/useragent/AbstractUserAgentAnalyzerDirect.willKeepTests:()Z
     389: ifeq          400
     392: aload_2
     393: invokevirtual #321                // Method nl/basjes/parse/useragent/config/ConfigLoader.keepTests:()Lnl/basjes/parse/useragent/config/ConfigLoader;
     396: pop
     397: goto          405
     400: aload_2
     401: invokevirtual #323                // Method nl/basjes/parse/useragent/config/ConfigLoader.dropTests:()Lnl/basjes/parse/useragent/config/ConfigLoader;
     404: pop
     405: iconst_1
     406: istore_3
     407: aload_0
     408: getfield      #56                 // Field yamlRules:Ljava/util/List;
     411: invokeinterface #185,  1          // InterfaceMethod java/util/List.iterator:()Ljava/util/Iterator;
     416: astore        4
     418: aload         4
     420: invokeinterface #124,  1          // InterfaceMethod java/util/Iterator.hasNext:()Z
     425: ifeq          473
     428: aload         4
     430: invokeinterface #128,  1          // InterfaceMethod java/util/Iterator.next:()Ljava/lang/Object;
     435: checkcast     #130                // class java/lang/String
     438: astore        5
     440: aload_2
     441: aload         5
     443: new           #193                // class java/lang/StringBuilder
     446: dup
     447: invokespecial #194                // Method java/lang/StringBuilder."<init>":()V
     450: ldc_w         #325                // String Manually Inserted Rules
     453: invokevirtual #200                // Method java/lang/StringBuilder.append:(Ljava/lang/String;)Ljava/lang/StringBuilder;
     456: iload_3
     457: iinc          3, 1
     460: invokevirtual #328                // Method java/lang/StringBuilder.append:(I)Ljava/lang/StringBuilder;
     463: invokevirtual #207                // Method java/lang/StringBuilder.toString:()Ljava/lang/String;
     466: invokevirtual #332                // Method nl/basjes/parse/useragent/config/ConfigLoader.addYaml:(Ljava/lang/String;Ljava/lang/String;)Lnl/basjes/parse/useragent/config/ConfigLoader;
     469: pop
     470: goto          418
     473: aload_0
     474: getfield      #65                 // Field uaa:Lnl/basjes/parse/useragent/AbstractUserAgentAnalyzerDirect;
     477: aload_2
     478: invokevirtual #336                // Method nl/basjes/parse/useragent/config/ConfigLoader.load:()Lnl/basjes/parse/useragent/config/AnalyzerConfig;
     481: invokevirtual #340                // Method nl/basjes/parse/useragent/AbstractUserAgentAnalyzerDirect.addAnalyzerConfig:(Lnl/basjes/parse/useragent/config/AnalyzerConfig;)V
     484: aload_0
     485: getfield      #65                 // Field uaa:Lnl/basjes/parse/useragent/AbstractUserAgentAnalyzerDirect;
     488: invokevirtual #343                // Method nl/basjes/parse/useragent/AbstractUserAgentAnalyzerDirect.finalizeLoadingRules:()V
     491: aload_0
     492: getfield      #47                 // Field preheatIterations:I
     495: ifge          509
     498: aload_0
     499: getfield      #65                 // Field uaa:Lnl/basjes/parse/useragent/AbstractUserAgentAnalyzerDirect;
     502: invokevirtual #347                // Method nl/basjes/parse/useragent/AbstractUserAgentAnalyzerDirect.preHeat:()J
     505: pop2
     506: goto          529
     509: aload_0
     510: getfield      #47                 // Field preheatIterations:I
     513: ifle          529
     516: aload_0
     517: getfield      #65                 // Field uaa:Lnl/basjes/parse/useragent/AbstractUserAgentAnalyzerDirect;
     520: aload_0
     521: getfield      #47                 // Field preheatIterations:I
     524: i2l
     525: invokevirtual #350                // Method nl/basjes/parse/useragent/AbstractUserAgentAnalyzerDirect.preHeat:(J)J
     528: pop2
     529: aload_0
     530: iconst_1
     531: putfield      #30                 // Field didBuildStep:Z
     534: aload_0
     535: getfield      #65                 // Field uaa:Lnl/basjes/parse/useragent/AbstractUserAgentAnalyzerDirect;
     538: areturn
}
