Compiled from "AgentField.java"
public class nl.basjes.parse.useragent.AgentField$MutableAgentField implements nl.basjes.parse.useragent.AgentField {
  final java.lang.String defaultValue;

  java.lang.String value;

  long confidence;

  private nl.basjes.parse.useragent.AgentField$MutableAgentField();
    Code:
       0: aload_0
       1: invokespecial #17                 // Method java/lang/Object."<init>":()V
       4: aload_0
       5: aconst_null
       6: putfield      #19                 // Field defaultValue:Ljava/lang/String;
       9: return

  nl.basjes.parse.useragent.AgentField$MutableAgentField(java.lang.String);
    Code:
       0: aload_0
       1: invokespecial #17                 // Method java/lang/Object."<init>":()V
       4: aload_0
       5: aload_1
       6: putfield      #19                 // Field defaultValue:Ljava/lang/String;
       9: aload_0
      10: invokevirtual #25                 // Method reset:()V
      13: return

  public void reset();
    Code:
       0: aload_0
       1: aconst_null
       2: putfield      #27                 // Field value:Ljava/lang/String;
       5: aload_0
       6: ldc2_w        #28                 // long -1l
       9: putfield      #31                 // Field confidence:J
      12: return

  public java.lang.String getValue();
    Code:
       0: aload_0
       1: getfield      #27                 // Field value:Ljava/lang/String;
       4: ifnonnull     12
       7: aload_0
       8: getfield      #19                 // Field defaultValue:Ljava/lang/String;
      11: areturn
      12: aload_0
      13: getfield      #27                 // Field value:Ljava/lang/String;
      16: areturn

  public boolean isDefaultValue();
    Code:
       0: aload_0
       1: getfield      #31                 // Field confidence:J
       4: lconst_0
       5: lcmp
       6: iflt          16
       9: aload_0
      10: getfield      #27                 // Field value:Ljava/lang/String;
      13: ifnonnull     20
      16: iconst_1
      17: goto          21
      20: iconst_0
      21: ireturn

  public java.lang.String getDefaultValue();
    Code:
       0: aload_0
       1: getfield      #19                 // Field defaultValue:Ljava/lang/String;
       4: areturn

  public long getConfidence();
    Code:
       0: aload_0
       1: getfield      #31                 // Field confidence:J
       4: lreturn

  public boolean setValue(nl.basjes.parse.useragent.AgentField$MutableAgentField);
    Code:
       0: aload_0
       1: aload_1
       2: getfield      #27                 // Field value:Ljava/lang/String;
       5: aload_1
       6: getfield      #31                 // Field confidence:J
       9: invokevirtual #43                 // Method setValue:(Ljava/lang/String;J)Z
      12: ireturn

  public boolean setValue(java.lang.String, long);
    Code:
       0: lload_2
       1: aload_0
       2: getfield      #31                 // Field confidence:J
       5: lcmp
       6: ifle          17
       9: aload_0
      10: aload_1
      11: lload_2
      12: invokevirtual #48                 // Method setValueForced:(Ljava/lang/String;J)V
      15: iconst_1
      16: ireturn
      17: iconst_0
      18: ireturn

  public void setValueForced(java.lang.String, long);
    Code:
       0: aload_0
       1: lload_2
       2: putfield      #31                 // Field confidence:J
       5: ldc           #52                 // String <<<null>>>
       7: aload_1
       8: invokevirtual #58                 // Method java/lang/String.equals:(Ljava/lang/Object;)Z
      11: ifeq          22
      14: aload_0
      15: aconst_null
      16: putfield      #27                 // Field value:Ljava/lang/String;
      19: goto          27
      22: aload_0
      23: aload_1
      24: putfield      #27                 // Field value:Ljava/lang/String;
      27: return

  public boolean equals(java.lang.Object);
    Code:
       0: aload_0
       1: aload_1
       2: invokevirtual #61                 // Method afEquals:(Ljava/lang/Object;)Z
       5: ireturn

  public int hashCode();
    Code:
       0: aload_0
       1: invokevirtual #68                 // Method afHashCode:()I
       4: ireturn

  public java.lang.String toString();
    Code:
       0: aload_0
       1: invokevirtual #72                 // Method afToString:()Ljava/lang/String;
       4: areturn
}
