Compiled from "CancelStatementResponse.scala"
public interface zio.aws.redshiftdata.model.CancelStatementResponse$ReadOnly {
  public static zio.aws.redshiftdata.model.CancelStatementResponse asEditable$(zio.aws.redshiftdata.model.CancelStatementResponse$ReadOnly);
    Code:
       0: aload_0
       1: invokespecial #20                 // InterfaceMethod asEditable:()Lzio/aws/redshiftdata/model/CancelStatementResponse;
       4: areturn

  public default zio.aws.redshiftdata.model.CancelStatementResponse asEditable();
    Code:
       0: new           #12                 // class zio/aws/redshiftdata/model/CancelStatementResponse
       3: dup
       4: aload_0
       5: invokeinterface #25,  1           // InterfaceMethod status:()Lscala/Option;
      10: invokedynamic #43,  0             // InvokeDynamic #0:apply:()Lscala/Function1;
      15: invokevirtual #49                 // Method scala/Option.map:(Lscala/Function1;)Lscala/Option;
      18: invokespecial #53                 // Method zio/aws/redshiftdata/model/CancelStatementResponse."<init>":(Lscala/Option;)V
      21: areturn

  public abstract scala.Option<java.lang.Object> status();

  public static zio.ZIO getStatus$(zio.aws.redshiftdata.model.CancelStatementResponse$ReadOnly);
    Code:
       0: aload_0
       1: invokespecial #61                 // InterfaceMethod getStatus:()Lzio/ZIO;
       4: areturn

  public default zio.ZIO<java.lang.Object, zio.aws.core.AwsError, java.lang.Object> getStatus();
    Code:
       0: getstatic     #68                 // Field zio/aws/core/AwsError$.MODULE$:Lzio/aws/core/AwsError$;
       3: ldc           #69                 // String status
       5: aload_0
       6: invokedynamic #81,  0             // InvokeDynamic #1:apply:(Lzio/aws/redshiftdata/model/CancelStatementResponse$ReadOnly;)Lscala/Function0;
      11: invokevirtual #85                 // Method zio/aws/core/AwsError$.unwrapOptionField:(Ljava/lang/String;Lscala/Function0;)Lzio/ZIO;
      14: areturn

  public static boolean $anonfun$asEditable$1(boolean);
    Code:
       0: iload_0
       1: ireturn

  public static scala.Option $anonfun$getStatus$1(zio.aws.redshiftdata.model.CancelStatementResponse$ReadOnly);
    Code:
       0: aload_0
       1: invokeinterface #25,  1           // InterfaceMethod status:()Lscala/Option;
       6: areturn

  public static void $init$(zio.aws.redshiftdata.model.CancelStatementResponse$ReadOnly);
    Code:
       0: return

  public static java.lang.Object $anonfun$asEditable$1$adapted(java.lang.Object);
    Code:
       0: aload_0
       1: invokestatic  #97                 // Method scala/runtime/BoxesRunTime.unboxToBoolean:(Ljava/lang/Object;)Z
       4: invokestatic  #99                 // InterfaceMethod $anonfun$asEditable$1:(Z)Z
       7: invokestatic  #103                // Method scala/runtime/BoxesRunTime.boxToBoolean:(Z)Ljava/lang/Boolean;
      10: areturn

  private static java.lang.Object $deserializeLambda$(java.lang.invoke.SerializedLambda);
    Code:
       0: aload_0
       1: invokedynamic #116,  0            // InvokeDynamic #2:lambdaDeserialize:(Ljava/lang/invoke/SerializedLambda;)Ljava/lang/Object;
       6: areturn
}
