Compiled from "PGXAConnection.java"
class org.postgresql.xa.PGXAConnection$ConnectionHandler implements java.lang.reflect.InvocationHandler {
  private final java.sql.Connection con;

  final org.postgresql.xa.PGXAConnection this$0;

  org.postgresql.xa.PGXAConnection$ConnectionHandler(org.postgresql.xa.PGXAConnection, java.sql.Connection);
    Code:
       0: aload_0
       1: aload_1
       2: putfield      #21                 // Field this$0:Lorg/postgresql/xa/PGXAConnection;
       5: aload_0
       6: invokespecial #24                 // Method java/lang/Object."<init>":()V
       9: aload_0
      10: aload_2
      11: putfield      #26                 // Field con:Ljava/sql/Connection;
      14: return

  public java.lang.Object invoke(java.lang.Object, java.lang.reflect.Method, java.lang.Object[]) throws java.lang.Throwable;
    Code:
       0: aload_0
       1: getfield      #21                 // Field this$0:Lorg/postgresql/xa/PGXAConnection;
       4: invokestatic  #38                 // Method org/postgresql/xa/PGXAConnection.access$000:(Lorg/postgresql/xa/PGXAConnection;)Lorg/postgresql/xa/PGXAConnection$State;
       7: getstatic     #42                 // Field org/postgresql/xa/PGXAConnection$State.IDLE:Lorg/postgresql/xa/PGXAConnection$State;
      10: if_acmpeq     91
      13: aload_2
      14: invokevirtual #48                 // Method java/lang/reflect/Method.getName:()Ljava/lang/String;
      17: astore        4
      19: aload         4
      21: ldc           #50                 // String commit
      23: invokevirtual #56                 // Method java/lang/String.equals:(Ljava/lang/Object;)Z
      26: ifne          71
      29: aload         4
      31: ldc           #58                 // String rollback
      33: invokevirtual #56                 // Method java/lang/String.equals:(Ljava/lang/Object;)Z
      36: ifne          71
      39: aload         4
      41: ldc           #60                 // String setSavePoint
      43: invokevirtual #56                 // Method java/lang/String.equals:(Ljava/lang/Object;)Z
      46: ifne          71
      49: aload         4
      51: ldc           #62                 // String setAutoCommit
      53: invokevirtual #56                 // Method java/lang/String.equals:(Ljava/lang/Object;)Z
      56: ifeq          91
      59: aload_3
      60: iconst_0
      61: aaload
      62: checkcast     #64                 // class java/lang/Boolean
      65: invokevirtual #68                 // Method java/lang/Boolean.booleanValue:()Z
      68: ifeq          91
      71: new           #70                 // class org/postgresql/util/PSQLException
      74: dup
      75: ldc           #72                 // String Transaction control methods setAutoCommit(true), commit, rollback and setSavePoint not allowed while an XA transaction is active.
      77: iconst_0
      78: anewarray     #4                  // class java/lang/Object
      81: invokestatic  #78                 // Method org/postgresql/util/GT.tr:(Ljava/lang/String;[Ljava/lang/Object;)Ljava/lang/String;
      84: getstatic     #84                 // Field org/postgresql/util/PSQLState.OBJECT_NOT_IN_STATE:Lorg/postgresql/util/PSQLState;
      87: invokespecial #87                 // Method org/postgresql/util/PSQLException."<init>":(Ljava/lang/String;Lorg/postgresql/util/PSQLState;)V
      90: athrow
      91: aload_2
      92: invokevirtual #48                 // Method java/lang/reflect/Method.getName:()Ljava/lang/String;
      95: ldc           #88                 // String equals
      97: invokevirtual #56                 // Method java/lang/String.equals:(Ljava/lang/Object;)Z
     100: ifeq          150
     103: aload_3
     104: iconst_0
     105: aaload
     106: astore        4
     108: aload         4
     110: invokevirtual #92                 // Method java/lang/Object.getClass:()Ljava/lang/Class;
     113: invokestatic  #98                 // Method java/lang/reflect/Proxy.isProxyClass:(Ljava/lang/Class;)Z
     116: ifeq          150
     119: aload         4
     121: invokestatic  #102                // Method java/lang/reflect/Proxy.getInvocationHandler:(Ljava/lang/Object;)Ljava/lang/reflect/InvocationHandler;
     124: astore        5
     126: aload         5
     128: instanceof    #2                  // class org/postgresql/xa/PGXAConnection$ConnectionHandler
     131: ifeq          150
     134: iconst_1
     135: anewarray     #4                  // class java/lang/Object
     138: dup
     139: iconst_0
     140: aload         5
     142: checkcast     #2                  // class org/postgresql/xa/PGXAConnection$ConnectionHandler
     145: getfield      #26                 // Field con:Ljava/sql/Connection;
     148: aastore
     149: astore_3
     150: aload_2
     151: aload_0
     152: getfield      #26                 // Field con:Ljava/sql/Connection;
     155: aload_3
     156: invokevirtual #105                // Method java/lang/reflect/Method.invoke:(Ljava/lang/Object;[Ljava/lang/Object;)Ljava/lang/Object;
     159: areturn
     160: astore        4
     162: aload         4
     164: invokevirtual #109                // Method java/lang/reflect/InvocationTargetException.getTargetException:()Ljava/lang/Throwable;
     167: athrow
    Exception table:
       from    to  target type
          91   159   160   Class java/lang/reflect/InvocationTargetException
}
