public class org.bouncycastle.jcajce.provider.asymmetric.GM$Mappings extends org.bouncycastle.jcajce.provider.util.AsymmetricAlgorithmProvider {
  public org.bouncycastle.jcajce.provider.asymmetric.GM$Mappings();
    Code:
       0: aload_0
       1: invokespecial #157                // Method org/bouncycastle/jcajce/provider/util/AsymmetricAlgorithmProvider."<init>":()V
       4: return

  public void configure(org.bouncycastle.jcajce.provider.config.ConfigurableProvider);
    Code:
       0: aload_1
       1: ldc           #28                 // String Signature.SHA256WITHSM2
       3: ldc           #41                 // String org.bouncycastle.jcajce.provider.asymmetric.ec.GMSignatureSpi$sha256WithSM2
       5: invokeinterface #158,  3          // InterfaceMethod org/bouncycastle/jcajce/provider/config/ConfigurableProvider.addAlgorithm:(Ljava/lang/String;Ljava/lang/String;)V
      10: aload_1
      11: new           #110                // class java/lang/StringBuilder
      14: dup
      15: invokespecial #153                // Method java/lang/StringBuilder."<init>":()V
      18: ldc           #3                  // String Alg.Alias.Signature.
      20: invokevirtual #156                // Method java/lang/StringBuilder.append:(Ljava/lang/String;)Ljava/lang/StringBuilder;
      23: getstatic     #151                // Field org/bouncycastle/asn1/gm/GMObjectIdentifiers.sm2sign_with_sha256:Lorg/bouncycastle/asn1/ASN1ObjectIdentifier;
      26: invokevirtual #155                // Method java/lang/StringBuilder.append:(Ljava/lang/Object;)Ljava/lang/StringBuilder;
      29: invokevirtual #154                // Method java/lang/StringBuilder.toString:()Ljava/lang/String;
      32: ldc           #15                 // String SHA256WITHSM2
      34: invokeinterface #158,  3          // InterfaceMethod org/bouncycastle/jcajce/provider/config/ConfigurableProvider.addAlgorithm:(Ljava/lang/String;Ljava/lang/String;)V
      39: aload_1
      40: ldc           #29                 // String Signature.SM3WITHSM2
      42: ldc           #42                 // String org.bouncycastle.jcajce.provider.asymmetric.ec.GMSignatureSpi$sm3WithSM2
      44: invokeinterface #158,  3          // InterfaceMethod org/bouncycastle/jcajce/provider/config/ConfigurableProvider.addAlgorithm:(Ljava/lang/String;Ljava/lang/String;)V
      49: aload_1
      50: new           #110                // class java/lang/StringBuilder
      53: dup
      54: invokespecial #153                // Method java/lang/StringBuilder."<init>":()V
      57: ldc           #3                  // String Alg.Alias.Signature.
      59: invokevirtual #156                // Method java/lang/StringBuilder.append:(Ljava/lang/String;)Ljava/lang/StringBuilder;
      62: getstatic     #152                // Field org/bouncycastle/asn1/gm/GMObjectIdentifiers.sm2sign_with_sm3:Lorg/bouncycastle/asn1/ASN1ObjectIdentifier;
      65: invokevirtual #155                // Method java/lang/StringBuilder.append:(Ljava/lang/Object;)Ljava/lang/StringBuilder;
      68: invokevirtual #154                // Method java/lang/StringBuilder.toString:()Ljava/lang/String;
      71: ldc           #27                 // String SM3WITHSM2
      73: invokeinterface #158,  3          // InterfaceMethod org/bouncycastle/jcajce/provider/config/ConfigurableProvider.addAlgorithm:(Ljava/lang/String;Ljava/lang/String;)V
      78: aload_1
      79: ldc           #4                  // String Cipher.SM2
      81: ldc           #30                 // String org.bouncycastle.jcajce.provider.asymmetric.ec.GMCipherSpi$SM2
      83: invokeinterface #158,  3          // InterfaceMethod org/bouncycastle/jcajce/provider/config/ConfigurableProvider.addAlgorithm:(Ljava/lang/String;Ljava/lang/String;)V
      88: aload_1
      89: ldc           #2                  // String Alg.Alias.Cipher.SM2WITHSM3
      91: ldc           #16                 // String SM2
      93: invokeinterface #158,  3          // InterfaceMethod org/bouncycastle/jcajce/provider/config/ConfigurableProvider.addAlgorithm:(Ljava/lang/String;Ljava/lang/String;)V
      98: aload_1
      99: new           #110                // class java/lang/StringBuilder
     102: dup
     103: invokespecial #153                // Method java/lang/StringBuilder."<init>":()V
     106: ldc           #1                  // String Alg.Alias.Cipher.
     108: invokevirtual #156                // Method java/lang/StringBuilder.append:(Ljava/lang/String;)Ljava/lang/StringBuilder;
     111: getstatic     #149                // Field org/bouncycastle/asn1/gm/GMObjectIdentifiers.sm2encrypt_with_sm3:Lorg/bouncycastle/asn1/ASN1ObjectIdentifier;
     114: invokevirtual #155                // Method java/lang/StringBuilder.append:(Ljava/lang/Object;)Ljava/lang/StringBuilder;
     117: invokevirtual #154                // Method java/lang/StringBuilder.toString:()Ljava/lang/String;
     120: ldc           #16                 // String SM2
     122: invokeinterface #158,  3          // InterfaceMethod org/bouncycastle/jcajce/provider/config/ConfigurableProvider.addAlgorithm:(Ljava/lang/String;Ljava/lang/String;)V
     127: aload_1
     128: ldc           #5                  // String Cipher.SM2WITHBLAKE2B
     130: ldc           #31                 // String org.bouncycastle.jcajce.provider.asymmetric.ec.GMCipherSpi$SM2withBlake2b
     132: invokeinterface #158,  3          // InterfaceMethod org/bouncycastle/jcajce/provider/config/ConfigurableProvider.addAlgorithm:(Ljava/lang/String;Ljava/lang/String;)V
     137: aload_1
     138: new           #110                // class java/lang/StringBuilder
     141: dup
     142: invokespecial #153                // Method java/lang/StringBuilder."<init>":()V
     145: ldc           #1                  // String Alg.Alias.Cipher.
     147: invokevirtual #156                // Method java/lang/StringBuilder.append:(Ljava/lang/String;)Ljava/lang/StringBuilder;
     150: getstatic     #140                // Field org/bouncycastle/asn1/gm/GMObjectIdentifiers.sm2encrypt_with_blake2b512:Lorg/bouncycastle/asn1/ASN1ObjectIdentifier;
     153: invokevirtual #155                // Method java/lang/StringBuilder.append:(Ljava/lang/Object;)Ljava/lang/StringBuilder;
     156: invokevirtual #154                // Method java/lang/StringBuilder.toString:()Ljava/lang/String;
     159: ldc           #17                 // String SM2WITHBLAKE2B
     161: invokeinterface #158,  3          // InterfaceMethod org/bouncycastle/jcajce/provider/config/ConfigurableProvider.addAlgorithm:(Ljava/lang/String;Ljava/lang/String;)V
     166: aload_1
     167: ldc           #6                  // String Cipher.SM2WITHBLAKE2S
     169: ldc           #32                 // String org.bouncycastle.jcajce.provider.asymmetric.ec.GMCipherSpi$SM2withBlake2s
     171: invokeinterface #158,  3          // InterfaceMethod org/bouncycastle/jcajce/provider/config/ConfigurableProvider.addAlgorithm:(Ljava/lang/String;Ljava/lang/String;)V
     176: aload_1
     177: new           #110                // class java/lang/StringBuilder
     180: dup
     181: invokespecial #153                // Method java/lang/StringBuilder."<init>":()V
     184: ldc           #1                  // String Alg.Alias.Cipher.
     186: invokevirtual #156                // Method java/lang/StringBuilder.append:(Ljava/lang/String;)Ljava/lang/StringBuilder;
     189: getstatic     #141                // Field org/bouncycastle/asn1/gm/GMObjectIdentifiers.sm2encrypt_with_blake2s256:Lorg/bouncycastle/asn1/ASN1ObjectIdentifier;
     192: invokevirtual #155                // Method java/lang/StringBuilder.append:(Ljava/lang/Object;)Ljava/lang/StringBuilder;
     195: invokevirtual #154                // Method java/lang/StringBuilder.toString:()Ljava/lang/String;
     198: ldc           #18                 // String SM2WITHBLAKE2S
     200: invokeinterface #158,  3          // InterfaceMethod org/bouncycastle/jcajce/provider/config/ConfigurableProvider.addAlgorithm:(Ljava/lang/String;Ljava/lang/String;)V
     205: aload_1
     206: ldc           #14                 // String Cipher.SM2WITHWHIRLPOOL
     208: ldc           #40                 // String org.bouncycastle.jcajce.provider.asymmetric.ec.GMCipherSpi$SM2withWhirlpool
     210: invokeinterface #158,  3          // InterfaceMethod org/bouncycastle/jcajce/provider/config/ConfigurableProvider.addAlgorithm:(Ljava/lang/String;Ljava/lang/String;)V
     215: aload_1
     216: new           #110                // class java/lang/StringBuilder
     219: dup
     220: invokespecial #153                // Method java/lang/StringBuilder."<init>":()V
     223: ldc           #1                  // String Alg.Alias.Cipher.
     225: invokevirtual #156                // Method java/lang/StringBuilder.append:(Ljava/lang/String;)Ljava/lang/StringBuilder;
     228: getstatic     #150                // Field org/bouncycastle/asn1/gm/GMObjectIdentifiers.sm2encrypt_with_whirlpool:Lorg/bouncycastle/asn1/ASN1ObjectIdentifier;
     231: invokevirtual #155                // Method java/lang/StringBuilder.append:(Ljava/lang/Object;)Ljava/lang/StringBuilder;
     234: invokevirtual #154                // Method java/lang/StringBuilder.toString:()Ljava/lang/String;
     237: ldc           #26                 // String SM2WITHWHIRLPOOL
     239: invokeinterface #158,  3          // InterfaceMethod org/bouncycastle/jcajce/provider/config/ConfigurableProvider.addAlgorithm:(Ljava/lang/String;Ljava/lang/String;)V
     244: aload_1
     245: ldc           #7                  // String Cipher.SM2WITHMD5
     247: ldc           #33                 // String org.bouncycastle.jcajce.provider.asymmetric.ec.GMCipherSpi$SM2withMD5
     249: invokeinterface #158,  3          // InterfaceMethod org/bouncycastle/jcajce/provider/config/ConfigurableProvider.addAlgorithm:(Ljava/lang/String;Ljava/lang/String;)V
     254: aload_1
     255: new           #110                // class java/lang/StringBuilder
     258: dup
     259: invokespecial #153                // Method java/lang/StringBuilder."<init>":()V
     262: ldc           #1                  // String Alg.Alias.Cipher.
     264: invokevirtual #156                // Method java/lang/StringBuilder.append:(Ljava/lang/String;)Ljava/lang/StringBuilder;
     267: getstatic     #142                // Field org/bouncycastle/asn1/gm/GMObjectIdentifiers.sm2encrypt_with_md5:Lorg/bouncycastle/asn1/ASN1ObjectIdentifier;
     270: invokevirtual #155                // Method java/lang/StringBuilder.append:(Ljava/lang/Object;)Ljava/lang/StringBuilder;
     273: invokevirtual #154                // Method java/lang/StringBuilder.toString:()Ljava/lang/String;
     276: ldc           #19                 // String SM2WITHMD5
     278: invokeinterface #158,  3          // InterfaceMethod org/bouncycastle/jcajce/provider/config/ConfigurableProvider.addAlgorithm:(Ljava/lang/String;Ljava/lang/String;)V
     283: aload_1
     284: ldc           #8                  // String Cipher.SM2WITHRIPEMD160
     286: ldc           #34                 // String org.bouncycastle.jcajce.provider.asymmetric.ec.GMCipherSpi$SM2withRMD
     288: invokeinterface #158,  3          // InterfaceMethod org/bouncycastle/jcajce/provider/config/ConfigurableProvider.addAlgorithm:(Ljava/lang/String;Ljava/lang/String;)V
     293: aload_1
     294: new           #110                // class java/lang/StringBuilder
     297: dup
     298: invokespecial #153                // Method java/lang/StringBuilder."<init>":()V
     301: ldc           #1                  // String Alg.Alias.Cipher.
     303: invokevirtual #156                // Method java/lang/StringBuilder.append:(Ljava/lang/String;)Ljava/lang/StringBuilder;
     306: getstatic     #143                // Field org/bouncycastle/asn1/gm/GMObjectIdentifiers.sm2encrypt_with_rmd160:Lorg/bouncycastle/asn1/ASN1ObjectIdentifier;
     309: invokevirtual #155                // Method java/lang/StringBuilder.append:(Ljava/lang/Object;)Ljava/lang/StringBuilder;
     312: invokevirtual #154                // Method java/lang/StringBuilder.toString:()Ljava/lang/String;
     315: ldc           #20                 // String SM2WITHRIPEMD160
     317: invokeinterface #158,  3          // InterfaceMethod org/bouncycastle/jcajce/provider/config/ConfigurableProvider.addAlgorithm:(Ljava/lang/String;Ljava/lang/String;)V
     322: aload_1
     323: ldc           #9                  // String Cipher.SM2WITHSHA1
     325: ldc           #35                 // String org.bouncycastle.jcajce.provider.asymmetric.ec.GMCipherSpi$SM2withSha1
     327: invokeinterface #158,  3          // InterfaceMethod org/bouncycastle/jcajce/provider/config/ConfigurableProvider.addAlgorithm:(Ljava/lang/String;Ljava/lang/String;)V
     332: aload_1
     333: new           #110                // class java/lang/StringBuilder
     336: dup
     337: invokespecial #153                // Method java/lang/StringBuilder."<init>":()V
     340: ldc           #1                  // String Alg.Alias.Cipher.
     342: invokevirtual #156                // Method java/lang/StringBuilder.append:(Ljava/lang/String;)Ljava/lang/StringBuilder;
     345: getstatic     #144                // Field org/bouncycastle/asn1/gm/GMObjectIdentifiers.sm2encrypt_with_sha1:Lorg/bouncycastle/asn1/ASN1ObjectIdentifier;
     348: invokevirtual #155                // Method java/lang/StringBuilder.append:(Ljava/lang/Object;)Ljava/lang/StringBuilder;
     351: invokevirtual #154                // Method java/lang/StringBuilder.toString:()Ljava/lang/String;
     354: ldc           #21                 // String SM2WITHSHA1
     356: invokeinterface #158,  3          // InterfaceMethod org/bouncycastle/jcajce/provider/config/ConfigurableProvider.addAlgorithm:(Ljava/lang/String;Ljava/lang/String;)V
     361: aload_1
     362: ldc           #10                 // String Cipher.SM2WITHSHA224
     364: ldc           #36                 // String org.bouncycastle.jcajce.provider.asymmetric.ec.GMCipherSpi$SM2withSha224
     366: invokeinterface #158,  3          // InterfaceMethod org/bouncycastle/jcajce/provider/config/ConfigurableProvider.addAlgorithm:(Ljava/lang/String;Ljava/lang/String;)V
     371: aload_1
     372: new           #110                // class java/lang/StringBuilder
     375: dup
     376: invokespecial #153                // Method java/lang/StringBuilder."<init>":()V
     379: ldc           #1                  // String Alg.Alias.Cipher.
     381: invokevirtual #156                // Method java/lang/StringBuilder.append:(Ljava/lang/String;)Ljava/lang/StringBuilder;
     384: getstatic     #145                // Field org/bouncycastle/asn1/gm/GMObjectIdentifiers.sm2encrypt_with_sha224:Lorg/bouncycastle/asn1/ASN1ObjectIdentifier;
     387: invokevirtual #155                // Method java/lang/StringBuilder.append:(Ljava/lang/Object;)Ljava/lang/StringBuilder;
     390: invokevirtual #154                // Method java/lang/StringBuilder.toString:()Ljava/lang/String;
     393: ldc           #22                 // String SM2WITHSHA224
     395: invokeinterface #158,  3          // InterfaceMethod org/bouncycastle/jcajce/provider/config/ConfigurableProvider.addAlgorithm:(Ljava/lang/String;Ljava/lang/String;)V
     400: aload_1
     401: ldc           #11                 // String Cipher.SM2WITHSHA256
     403: ldc           #37                 // String org.bouncycastle.jcajce.provider.asymmetric.ec.GMCipherSpi$SM2withSha256
     405: invokeinterface #158,  3          // InterfaceMethod org/bouncycastle/jcajce/provider/config/ConfigurableProvider.addAlgorithm:(Ljava/lang/String;Ljava/lang/String;)V
     410: aload_1
     411: new           #110                // class java/lang/StringBuilder
     414: dup
     415: invokespecial #153                // Method java/lang/StringBuilder."<init>":()V
     418: ldc           #1                  // String Alg.Alias.Cipher.
     420: invokevirtual #156                // Method java/lang/StringBuilder.append:(Ljava/lang/String;)Ljava/lang/StringBuilder;
     423: getstatic     #146                // Field org/bouncycastle/asn1/gm/GMObjectIdentifiers.sm2encrypt_with_sha256:Lorg/bouncycastle/asn1/ASN1ObjectIdentifier;
     426: invokevirtual #155                // Method java/lang/StringBuilder.append:(Ljava/lang/Object;)Ljava/lang/StringBuilder;
     429: invokevirtual #154                // Method java/lang/StringBuilder.toString:()Ljava/lang/String;
     432: ldc           #23                 // String SM2WITHSHA256
     434: invokeinterface #158,  3          // InterfaceMethod org/bouncycastle/jcajce/provider/config/ConfigurableProvider.addAlgorithm:(Ljava/lang/String;Ljava/lang/String;)V
     439: aload_1
     440: ldc           #12                 // String Cipher.SM2WITHSHA384
     442: ldc           #38                 // String org.bouncycastle.jcajce.provider.asymmetric.ec.GMCipherSpi$SM2withSha384
     444: invokeinterface #158,  3          // InterfaceMethod org/bouncycastle/jcajce/provider/config/ConfigurableProvider.addAlgorithm:(Ljava/lang/String;Ljava/lang/String;)V
     449: aload_1
     450: new           #110                // class java/lang/StringBuilder
     453: dup
     454: invokespecial #153                // Method java/lang/StringBuilder."<init>":()V
     457: ldc           #1                  // String Alg.Alias.Cipher.
     459: invokevirtual #156                // Method java/lang/StringBuilder.append:(Ljava/lang/String;)Ljava/lang/StringBuilder;
     462: getstatic     #147                // Field org/bouncycastle/asn1/gm/GMObjectIdentifiers.sm2encrypt_with_sha384:Lorg/bouncycastle/asn1/ASN1ObjectIdentifier;
     465: invokevirtual #155                // Method java/lang/StringBuilder.append:(Ljava/lang/Object;)Ljava/lang/StringBuilder;
     468: invokevirtual #154                // Method java/lang/StringBuilder.toString:()Ljava/lang/String;
     471: ldc           #24                 // String SM2WITHSHA384
     473: invokeinterface #158,  3          // InterfaceMethod org/bouncycastle/jcajce/provider/config/ConfigurableProvider.addAlgorithm:(Ljava/lang/String;Ljava/lang/String;)V
     478: aload_1
     479: ldc           #13                 // String Cipher.SM2WITHSHA512
     481: ldc           #39                 // String org.bouncycastle.jcajce.provider.asymmetric.ec.GMCipherSpi$SM2withSha512
     483: invokeinterface #158,  3          // InterfaceMethod org/bouncycastle/jcajce/provider/config/ConfigurableProvider.addAlgorithm:(Ljava/lang/String;Ljava/lang/String;)V
     488: aload_1
     489: new           #110                // class java/lang/StringBuilder
     492: dup
     493: invokespecial #153                // Method java/lang/StringBuilder."<init>":()V
     496: ldc           #1                  // String Alg.Alias.Cipher.
     498: invokevirtual #156                // Method java/lang/StringBuilder.append:(Ljava/lang/String;)Ljava/lang/StringBuilder;
     501: getstatic     #148                // Field org/bouncycastle/asn1/gm/GMObjectIdentifiers.sm2encrypt_with_sha512:Lorg/bouncycastle/asn1/ASN1ObjectIdentifier;
     504: invokevirtual #155                // Method java/lang/StringBuilder.append:(Ljava/lang/Object;)Ljava/lang/StringBuilder;
     507: invokevirtual #154                // Method java/lang/StringBuilder.toString:()Ljava/lang/String;
     510: ldc           #25                 // String SM2WITHSHA512
     512: invokeinterface #158,  3          // InterfaceMethod org/bouncycastle/jcajce/provider/config/ConfigurableProvider.addAlgorithm:(Ljava/lang/String;Ljava/lang/String;)V
     517: return
}
