Compiled from "GeneralRegressionModelEvaluator.java"
final class org.jpmml.evaluator.general_regression.GeneralRegressionModelEvaluator$5 extends com.google.common.cache.CacheLoader<org.dmg.pmml.general_regression.GeneralRegressionModel, com.google.common.collect.BiMap<org.dmg.pmml.FieldName, org.dmg.pmml.general_regression.Predictor>> {
  org.jpmml.evaluator.general_regression.GeneralRegressionModelEvaluator$5();
    Code:
       0: aload_0
       1: invokespecial #1                  // Method com/google/common/cache/CacheLoader."<init>":()V
       4: return

  public com.google.common.collect.BiMap<org.dmg.pmml.FieldName, org.dmg.pmml.general_regression.Predictor> load(org.dmg.pmml.general_regression.GeneralRegressionModel);
    Code:
       0: aload_1
       1: invokevirtual #2                  // Method org/dmg/pmml/general_regression/GeneralRegressionModel.getCovariateList:()Lorg/dmg/pmml/general_regression/CovariateList;
       4: invokestatic  #3                  // Method org/jpmml/evaluator/general_regression/GeneralRegressionModelEvaluator.access$900:(Lorg/dmg/pmml/general_regression/PredictorList;)Lcom/google/common/collect/BiMap;
       7: invokestatic  #4                  // Method com/google/common/collect/ImmutableBiMap.copyOf:(Ljava/util/Map;)Lcom/google/common/collect/ImmutableBiMap;
      10: areturn

  public java.lang.Object load(java.lang.Object) throws java.lang.Exception;
    Code:
       0: aload_0
       1: aload_1
       2: checkcast     #5                  // class org/dmg/pmml/general_regression/GeneralRegressionModel
       5: invokevirtual #6                  // Method load:(Lorg/dmg/pmml/general_regression/GeneralRegressionModel;)Lcom/google/common/collect/BiMap;
       8: areturn
}
