Compiled from "Timer.kt"
public final class kotlin.concurrent.TimersKt$timerTask$1 extends java.util.TimerTask {
  final kotlin.jvm.functions.Function1 $action;

  public void run();
    Code:
       0: aload_0
       1: getfield      #15                 // Field $action:Lkotlin/jvm/functions/Function1;
       4: aload_0
       5: invokeinterface #21,  2           // InterfaceMethod kotlin/jvm/functions/Function1.invoke:(Ljava/lang/Object;)Ljava/lang/Object;
      10: pop
      11: return

  public kotlin.concurrent.TimersKt$timerTask$1(kotlin.jvm.functions.Function1);
    Code:
       0: aload_0
       1: aload_1
       2: putfield      #15                 // Field $action:Lkotlin/jvm/functions/Function1;
       5: aload_0
       6: invokespecial #27                 // Method java/util/TimerTask."<init>":()V
       9: return
}
