Compiled from "ByteBufferInputStream.java"
class io.lettuce.core.codec.ByteBufferInputStream extends java.io.InputStream {
  private final java.nio.ByteBuffer buffer;

  public io.lettuce.core.codec.ByteBufferInputStream(java.nio.ByteBuffer);
    Code:
       0: aload_0
       1: invokespecial #1                  // Method java/io/InputStream."<init>":()V
       4: aload_0
       5: aload_1
       6: putfield      #2                  // Field buffer:Ljava/nio/ByteBuffer;
       9: return

  public int available() throws java.io.IOException;
    Code:
       0: aload_0
       1: getfield      #2                  // Field buffer:Ljava/nio/ByteBuffer;
       4: invokevirtual #3                  // Method java/nio/ByteBuffer.remaining:()I
       7: ireturn

  public int read() throws java.io.IOException;
    Code:
       0: aload_0
       1: getfield      #2                  // Field buffer:Ljava/nio/ByteBuffer;
       4: invokevirtual #3                  // Method java/nio/ByteBuffer.remaining:()I
       7: ifle          22
      10: aload_0
      11: getfield      #2                  // Field buffer:Ljava/nio/ByteBuffer;
      14: invokevirtual #4                  // Method java/nio/ByteBuffer.get:()B
      17: sipush        255
      20: iand
      21: ireturn
      22: iconst_m1
      23: ireturn
}
