Compiled from "StatusResultMatchers.java"
class org.springframework.test.web.servlet.result.StatusResultMatchers$7 implements org.springframework.test.web.servlet.ResultMatcher {
  final org.springframework.test.web.servlet.result.StatusResultMatchers this$0;

  org.springframework.test.web.servlet.result.StatusResultMatchers$7(org.springframework.test.web.servlet.result.StatusResultMatchers);
    Code:
       0: aload_0
       1: aload_1
       2: putfield      #1                  // Field this$0:Lorg/springframework/test/web/servlet/result/StatusResultMatchers;
       5: aload_0
       6: invokespecial #2                  // Method java/lang/Object."<init>":()V
       9: return

  public void match(org.springframework.test.web.servlet.MvcResult) throws java.lang.Exception;
    Code:
       0: new           #3                  // class java/lang/StringBuilder
       3: dup
       4: invokespecial #4                  // Method java/lang/StringBuilder."<init>":()V
       7: ldc           #5                  // String Range for response status value
       9: invokevirtual #6                  // Method java/lang/StringBuilder.append:(Ljava/lang/String;)Ljava/lang/StringBuilder;
      12: aload_1
      13: invokeinterface #7,  1            // InterfaceMethod org/springframework/test/web/servlet/MvcResult.getResponse:()Lorg/springframework/mock/web/MockHttpServletResponse;
      18: invokevirtual #8                  // Method org/springframework/mock/web/MockHttpServletResponse.getStatus:()I
      21: invokevirtual #9                  // Method java/lang/StringBuilder.append:(I)Ljava/lang/StringBuilder;
      24: invokevirtual #10                 // Method java/lang/StringBuilder.toString:()Ljava/lang/String;
      27: getstatic     #11                 // Field org/springframework/http/HttpStatus$Series.SERVER_ERROR:Lorg/springframework/http/HttpStatus$Series;
      30: aload_0
      31: getfield      #1                  // Field this$0:Lorg/springframework/test/web/servlet/result/StatusResultMatchers;
      34: aload_1
      35: invokestatic  #12                 // Method org/springframework/test/web/servlet/result/StatusResultMatchers.access$000:(Lorg/springframework/test/web/servlet/result/StatusResultMatchers;Lorg/springframework/test/web/servlet/MvcResult;)Lorg/springframework/http/HttpStatus$Series;
      38: invokestatic  #13                 // Method org/springframework/test/util/AssertionErrors.assertEquals:(Ljava/lang/String;Ljava/lang/Object;Ljava/lang/Object;)V
      41: return
}
