Compiled from "ActiveProjectArtifact.java"
public class org.apache.maven.project.artifact.ActiveProjectArtifact implements org.apache.maven.artifact.Artifact {
  private final org.apache.maven.artifact.Artifact artifact;

  private final org.apache.maven.project.MavenProject project;

  public org.apache.maven.project.artifact.ActiveProjectArtifact(org.apache.maven.project.MavenProject, org.apache.maven.artifact.Artifact);
    Code:
       0: aload_0
       1: invokespecial #1                  // Method java/lang/Object."<init>":()V
       4: aload_0
       5: aload_2
       6: putfield      #2                  // Field artifact:Lorg/apache/maven/artifact/Artifact;
       9: aload_0
      10: aload_1
      11: putfield      #3                  // Field project:Lorg/apache/maven/project/MavenProject;
      14: aload_2
      15: aload_1
      16: invokevirtual #4                  // Method org/apache/maven/project/MavenProject.getArtifact:()Lorg/apache/maven/artifact/Artifact;
      19: invokeinterface #5,  1            // InterfaceMethod org/apache/maven/artifact/Artifact.getFile:()Ljava/io/File;
      24: invokeinterface #6,  2            // InterfaceMethod org/apache/maven/artifact/Artifact.setFile:(Ljava/io/File;)V
      29: aload_2
      30: iconst_1
      31: invokeinterface #7,  2            // InterfaceMethod org/apache/maven/artifact/Artifact.setResolved:(Z)V
      36: return

  public java.io.File getFile();
    Code:
       0: aload_0
       1: getfield      #3                  // Field project:Lorg/apache/maven/project/MavenProject;
       4: invokevirtual #4                  // Method org/apache/maven/project/MavenProject.getArtifact:()Lorg/apache/maven/artifact/Artifact;
       7: invokeinterface #5,  1            // InterfaceMethod org/apache/maven/artifact/Artifact.getFile:()Ljava/io/File;
      12: areturn

  public java.lang.String getGroupId();
    Code:
       0: aload_0
       1: getfield      #2                  // Field artifact:Lorg/apache/maven/artifact/Artifact;
       4: invokeinterface #8,  1            // InterfaceMethod org/apache/maven/artifact/Artifact.getGroupId:()Ljava/lang/String;
       9: areturn

  public java.lang.String getArtifactId();
    Code:
       0: aload_0
       1: getfield      #2                  // Field artifact:Lorg/apache/maven/artifact/Artifact;
       4: invokeinterface #9,  1            // InterfaceMethod org/apache/maven/artifact/Artifact.getArtifactId:()Ljava/lang/String;
       9: areturn

  public java.lang.String getVersion();
    Code:
       0: aload_0
       1: getfield      #2                  // Field artifact:Lorg/apache/maven/artifact/Artifact;
       4: invokeinterface #10,  1           // InterfaceMethod org/apache/maven/artifact/Artifact.getVersion:()Ljava/lang/String;
       9: areturn

  public void setVersion(java.lang.String);
    Code:
       0: aload_0
       1: getfield      #2                  // Field artifact:Lorg/apache/maven/artifact/Artifact;
       4: aload_1
       5: invokeinterface #11,  2           // InterfaceMethod org/apache/maven/artifact/Artifact.setVersion:(Ljava/lang/String;)V
      10: return

  public java.lang.String getScope();
    Code:
       0: aload_0
       1: getfield      #2                  // Field artifact:Lorg/apache/maven/artifact/Artifact;
       4: invokeinterface #12,  1           // InterfaceMethod org/apache/maven/artifact/Artifact.getScope:()Ljava/lang/String;
       9: areturn

  public java.lang.String getType();
    Code:
       0: aload_0
       1: getfield      #2                  // Field artifact:Lorg/apache/maven/artifact/Artifact;
       4: invokeinterface #13,  1           // InterfaceMethod org/apache/maven/artifact/Artifact.getType:()Ljava/lang/String;
       9: areturn

  public java.lang.String getClassifier();
    Code:
       0: aload_0
       1: getfield      #2                  // Field artifact:Lorg/apache/maven/artifact/Artifact;
       4: invokeinterface #14,  1           // InterfaceMethod org/apache/maven/artifact/Artifact.getClassifier:()Ljava/lang/String;
       9: areturn

  public boolean hasClassifier();
    Code:
       0: aload_0
       1: getfield      #2                  // Field artifact:Lorg/apache/maven/artifact/Artifact;
       4: invokeinterface #15,  1           // InterfaceMethod org/apache/maven/artifact/Artifact.hasClassifier:()Z
       9: ireturn

  public void setFile(java.io.File);
    Code:
       0: aload_0
       1: getfield      #2                  // Field artifact:Lorg/apache/maven/artifact/Artifact;
       4: aload_1
       5: invokeinterface #6,  2            // InterfaceMethod org/apache/maven/artifact/Artifact.setFile:(Ljava/io/File;)V
      10: aload_0
      11: getfield      #3                  // Field project:Lorg/apache/maven/project/MavenProject;
      14: invokevirtual #4                  // Method org/apache/maven/project/MavenProject.getArtifact:()Lorg/apache/maven/artifact/Artifact;
      17: aload_1
      18: invokeinterface #6,  2            // InterfaceMethod org/apache/maven/artifact/Artifact.setFile:(Ljava/io/File;)V
      23: return

  public java.lang.String getBaseVersion();
    Code:
       0: aload_0
       1: getfield      #2                  // Field artifact:Lorg/apache/maven/artifact/Artifact;
       4: invokeinterface #16,  1           // InterfaceMethod org/apache/maven/artifact/Artifact.getBaseVersion:()Ljava/lang/String;
       9: areturn

  public void setBaseVersion(java.lang.String);
    Code:
       0: aload_0
       1: getfield      #2                  // Field artifact:Lorg/apache/maven/artifact/Artifact;
       4: aload_1
       5: invokeinterface #17,  2           // InterfaceMethod org/apache/maven/artifact/Artifact.setBaseVersion:(Ljava/lang/String;)V
      10: return

  public java.lang.String getId();
    Code:
       0: aload_0
       1: getfield      #2                  // Field artifact:Lorg/apache/maven/artifact/Artifact;
       4: invokeinterface #18,  1           // InterfaceMethod org/apache/maven/artifact/Artifact.getId:()Ljava/lang/String;
       9: areturn

  public java.lang.String getDependencyConflictId();
    Code:
       0: aload_0
       1: getfield      #2                  // Field artifact:Lorg/apache/maven/artifact/Artifact;
       4: invokeinterface #19,  1           // InterfaceMethod org/apache/maven/artifact/Artifact.getDependencyConflictId:()Ljava/lang/String;
       9: areturn

  public void addMetadata(org.apache.maven.artifact.metadata.ArtifactMetadata);
    Code:
       0: aload_0
       1: getfield      #2                  // Field artifact:Lorg/apache/maven/artifact/Artifact;
       4: aload_1
       5: invokeinterface #20,  2           // InterfaceMethod org/apache/maven/artifact/Artifact.addMetadata:(Lorg/apache/maven/artifact/metadata/ArtifactMetadata;)V
      10: return

  public java.util.Collection<org.apache.maven.artifact.metadata.ArtifactMetadata> getMetadataList();
    Code:
       0: aload_0
       1: getfield      #2                  // Field artifact:Lorg/apache/maven/artifact/Artifact;
       4: invokeinterface #21,  1           // InterfaceMethod org/apache/maven/artifact/Artifact.getMetadataList:()Ljava/util/Collection;
       9: areturn

  public void setRepository(org.apache.maven.artifact.repository.ArtifactRepository);
    Code:
       0: aload_0
       1: getfield      #2                  // Field artifact:Lorg/apache/maven/artifact/Artifact;
       4: aload_1
       5: invokeinterface #22,  2           // InterfaceMethod org/apache/maven/artifact/Artifact.setRepository:(Lorg/apache/maven/artifact/repository/ArtifactRepository;)V
      10: return

  public org.apache.maven.artifact.repository.ArtifactRepository getRepository();
    Code:
       0: aload_0
       1: getfield      #2                  // Field artifact:Lorg/apache/maven/artifact/Artifact;
       4: invokeinterface #23,  1           // InterfaceMethod org/apache/maven/artifact/Artifact.getRepository:()Lorg/apache/maven/artifact/repository/ArtifactRepository;
       9: areturn

  public void updateVersion(java.lang.String, org.apache.maven.artifact.repository.ArtifactRepository);
    Code:
       0: aload_0
       1: getfield      #2                  // Field artifact:Lorg/apache/maven/artifact/Artifact;
       4: aload_1
       5: aload_2
       6: invokeinterface #24,  3           // InterfaceMethod org/apache/maven/artifact/Artifact.updateVersion:(Ljava/lang/String;Lorg/apache/maven/artifact/repository/ArtifactRepository;)V
      11: return

  public java.lang.String getDownloadUrl();
    Code:
       0: aload_0
       1: getfield      #2                  // Field artifact:Lorg/apache/maven/artifact/Artifact;
       4: invokeinterface #25,  1           // InterfaceMethod org/apache/maven/artifact/Artifact.getDownloadUrl:()Ljava/lang/String;
       9: areturn

  public void setDownloadUrl(java.lang.String);
    Code:
       0: aload_0
       1: getfield      #2                  // Field artifact:Lorg/apache/maven/artifact/Artifact;
       4: aload_1
       5: invokeinterface #26,  2           // InterfaceMethod org/apache/maven/artifact/Artifact.setDownloadUrl:(Ljava/lang/String;)V
      10: return

  public org.apache.maven.artifact.resolver.filter.ArtifactFilter getDependencyFilter();
    Code:
       0: aload_0
       1: getfield      #2                  // Field artifact:Lorg/apache/maven/artifact/Artifact;
       4: invokeinterface #27,  1           // InterfaceMethod org/apache/maven/artifact/Artifact.getDependencyFilter:()Lorg/apache/maven/artifact/resolver/filter/ArtifactFilter;
       9: areturn

  public void setDependencyFilter(org.apache.maven.artifact.resolver.filter.ArtifactFilter);
    Code:
       0: aload_0
       1: getfield      #2                  // Field artifact:Lorg/apache/maven/artifact/Artifact;
       4: aload_1
       5: invokeinterface #28,  2           // InterfaceMethod org/apache/maven/artifact/Artifact.setDependencyFilter:(Lorg/apache/maven/artifact/resolver/filter/ArtifactFilter;)V
      10: return

  public org.apache.maven.artifact.handler.ArtifactHandler getArtifactHandler();
    Code:
       0: aload_0
       1: getfield      #2                  // Field artifact:Lorg/apache/maven/artifact/Artifact;
       4: invokeinterface #29,  1           // InterfaceMethod org/apache/maven/artifact/Artifact.getArtifactHandler:()Lorg/apache/maven/artifact/handler/ArtifactHandler;
       9: areturn

  public java.util.List<java.lang.String> getDependencyTrail();
    Code:
       0: aload_0
       1: getfield      #2                  // Field artifact:Lorg/apache/maven/artifact/Artifact;
       4: invokeinterface #30,  1           // InterfaceMethod org/apache/maven/artifact/Artifact.getDependencyTrail:()Ljava/util/List;
       9: areturn

  public void setDependencyTrail(java.util.List<java.lang.String>);
    Code:
       0: aload_0
       1: getfield      #2                  // Field artifact:Lorg/apache/maven/artifact/Artifact;
       4: aload_1
       5: invokeinterface #31,  2           // InterfaceMethod org/apache/maven/artifact/Artifact.setDependencyTrail:(Ljava/util/List;)V
      10: return

  public void setScope(java.lang.String);
    Code:
       0: aload_0
       1: getfield      #2                  // Field artifact:Lorg/apache/maven/artifact/Artifact;
       4: aload_1
       5: invokeinterface #32,  2           // InterfaceMethod org/apache/maven/artifact/Artifact.setScope:(Ljava/lang/String;)V
      10: return

  public org.apache.maven.artifact.versioning.VersionRange getVersionRange();
    Code:
       0: aload_0
       1: getfield      #2                  // Field artifact:Lorg/apache/maven/artifact/Artifact;
       4: invokeinterface #33,  1           // InterfaceMethod org/apache/maven/artifact/Artifact.getVersionRange:()Lorg/apache/maven/artifact/versioning/VersionRange;
       9: areturn

  public void setVersionRange(org.apache.maven.artifact.versioning.VersionRange);
    Code:
       0: aload_0
       1: getfield      #2                  // Field artifact:Lorg/apache/maven/artifact/Artifact;
       4: aload_1
       5: invokeinterface #34,  2           // InterfaceMethod org/apache/maven/artifact/Artifact.setVersionRange:(Lorg/apache/maven/artifact/versioning/VersionRange;)V
      10: return

  public void selectVersion(java.lang.String);
    Code:
       0: aload_0
       1: getfield      #2                  // Field artifact:Lorg/apache/maven/artifact/Artifact;
       4: aload_1
       5: invokeinterface #35,  2           // InterfaceMethod org/apache/maven/artifact/Artifact.selectVersion:(Ljava/lang/String;)V
      10: return

  public void setGroupId(java.lang.String);
    Code:
       0: aload_0
       1: getfield      #2                  // Field artifact:Lorg/apache/maven/artifact/Artifact;
       4: aload_1
       5: invokeinterface #36,  2           // InterfaceMethod org/apache/maven/artifact/Artifact.setGroupId:(Ljava/lang/String;)V
      10: return

  public void setArtifactId(java.lang.String);
    Code:
       0: aload_0
       1: getfield      #2                  // Field artifact:Lorg/apache/maven/artifact/Artifact;
       4: aload_1
       5: invokeinterface #37,  2           // InterfaceMethod org/apache/maven/artifact/Artifact.setArtifactId:(Ljava/lang/String;)V
      10: return

  public boolean isSnapshot();
    Code:
       0: aload_0
       1: getfield      #2                  // Field artifact:Lorg/apache/maven/artifact/Artifact;
       4: invokeinterface #38,  1           // InterfaceMethod org/apache/maven/artifact/Artifact.isSnapshot:()Z
       9: ireturn

  public int compareTo(org.apache.maven.artifact.Artifact);
    Code:
       0: aload_0
       1: getfield      #2                  // Field artifact:Lorg/apache/maven/artifact/Artifact;
       4: aload_1
       5: invokeinterface #39,  2           // InterfaceMethod org/apache/maven/artifact/Artifact.compareTo:(Ljava/lang/Object;)I
      10: ireturn

  public void setResolved(boolean);
    Code:
       0: aload_0
       1: getfield      #2                  // Field artifact:Lorg/apache/maven/artifact/Artifact;
       4: iload_1
       5: invokeinterface #7,  2            // InterfaceMethod org/apache/maven/artifact/Artifact.setResolved:(Z)V
      10: return

  public boolean isResolved();
    Code:
       0: aload_0
       1: getfield      #2                  // Field artifact:Lorg/apache/maven/artifact/Artifact;
       4: invokeinterface #40,  1           // InterfaceMethod org/apache/maven/artifact/Artifact.isResolved:()Z
       9: ireturn

  public void setResolvedVersion(java.lang.String);
    Code:
       0: aload_0
       1: getfield      #2                  // Field artifact:Lorg/apache/maven/artifact/Artifact;
       4: aload_1
       5: invokeinterface #41,  2           // InterfaceMethod org/apache/maven/artifact/Artifact.setResolvedVersion:(Ljava/lang/String;)V
      10: return

  public void setArtifactHandler(org.apache.maven.artifact.handler.ArtifactHandler);
    Code:
       0: aload_0
       1: getfield      #2                  // Field artifact:Lorg/apache/maven/artifact/Artifact;
       4: aload_1
       5: invokeinterface #42,  2           // InterfaceMethod org/apache/maven/artifact/Artifact.setArtifactHandler:(Lorg/apache/maven/artifact/handler/ArtifactHandler;)V
      10: return

  public java.lang.String toString();
    Code:
       0: new           #43                 // class java/lang/StringBuilder
       3: dup
       4: invokespecial #44                 // Method java/lang/StringBuilder."<init>":()V
       7: ldc           #45                 // String active project artifact:\n\tartifact =
       9: invokevirtual #46                 // Method java/lang/StringBuilder.append:(Ljava/lang/String;)Ljava/lang/StringBuilder;
      12: aload_0
      13: getfield      #2                  // Field artifact:Lorg/apache/maven/artifact/Artifact;
      16: invokevirtual #47                 // Method java/lang/StringBuilder.append:(Ljava/lang/Object;)Ljava/lang/StringBuilder;
      19: ldc           #48                 // String ;\n\tproject:
      21: invokevirtual #46                 // Method java/lang/StringBuilder.append:(Ljava/lang/String;)Ljava/lang/StringBuilder;
      24: aload_0
      25: getfield      #3                  // Field project:Lorg/apache/maven/project/MavenProject;
      28: invokevirtual #47                 // Method java/lang/StringBuilder.append:(Ljava/lang/Object;)Ljava/lang/StringBuilder;
      31: invokevirtual #49                 // Method java/lang/StringBuilder.toString:()Ljava/lang/String;
      34: areturn

  public boolean isRelease();
    Code:
       0: aload_0
       1: getfield      #2                  // Field artifact:Lorg/apache/maven/artifact/Artifact;
       4: invokeinterface #50,  1           // InterfaceMethod org/apache/maven/artifact/Artifact.isRelease:()Z
       9: ireturn

  public void setRelease(boolean);
    Code:
       0: aload_0
       1: getfield      #2                  // Field artifact:Lorg/apache/maven/artifact/Artifact;
       4: iload_1
       5: invokeinterface #51,  2           // InterfaceMethod org/apache/maven/artifact/Artifact.setRelease:(Z)V
      10: return

  public java.util.List<org.apache.maven.artifact.versioning.ArtifactVersion> getAvailableVersions();
    Code:
       0: aload_0
       1: getfield      #2                  // Field artifact:Lorg/apache/maven/artifact/Artifact;
       4: invokeinterface #52,  1           // InterfaceMethod org/apache/maven/artifact/Artifact.getAvailableVersions:()Ljava/util/List;
       9: areturn

  public void setAvailableVersions(java.util.List<org.apache.maven.artifact.versioning.ArtifactVersion>);
    Code:
       0: aload_0
       1: getfield      #2                  // Field artifact:Lorg/apache/maven/artifact/Artifact;
       4: aload_1
       5: invokeinterface #53,  2           // InterfaceMethod org/apache/maven/artifact/Artifact.setAvailableVersions:(Ljava/util/List;)V
      10: return

  public boolean isOptional();
    Code:
       0: aload_0
       1: getfield      #2                  // Field artifact:Lorg/apache/maven/artifact/Artifact;
       4: invokeinterface #54,  1           // InterfaceMethod org/apache/maven/artifact/Artifact.isOptional:()Z
       9: ireturn

  public org.apache.maven.artifact.versioning.ArtifactVersion getSelectedVersion() throws org.apache.maven.artifact.versioning.OverConstrainedVersionException;
    Code:
       0: aload_0
       1: getfield      #2                  // Field artifact:Lorg/apache/maven/artifact/Artifact;
       4: invokeinterface #55,  1           // InterfaceMethod org/apache/maven/artifact/Artifact.getSelectedVersion:()Lorg/apache/maven/artifact/versioning/ArtifactVersion;
       9: areturn

  public boolean isSelectedVersionKnown() throws org.apache.maven.artifact.versioning.OverConstrainedVersionException;
    Code:
       0: aload_0
       1: getfield      #2                  // Field artifact:Lorg/apache/maven/artifact/Artifact;
       4: invokeinterface #56,  1           // InterfaceMethod org/apache/maven/artifact/Artifact.isSelectedVersionKnown:()Z
       9: ireturn

  public void setOptional(boolean);
    Code:
       0: aload_0
       1: getfield      #2                  // Field artifact:Lorg/apache/maven/artifact/Artifact;
       4: iload_1
       5: invokeinterface #57,  2           // InterfaceMethod org/apache/maven/artifact/Artifact.setOptional:(Z)V
      10: return

  public int hashCode();
    Code:
       0: bipush        17
       2: istore_1
       3: bipush        37
       5: iload_1
       6: imul
       7: aload_0
       8: invokevirtual #58                 // Method getGroupId:()Ljava/lang/String;
      11: invokevirtual #59                 // Method java/lang/String.hashCode:()I
      14: iadd
      15: istore_1
      16: bipush        37
      18: iload_1
      19: imul
      20: aload_0
      21: invokevirtual #60                 // Method getArtifactId:()Ljava/lang/String;
      24: invokevirtual #59                 // Method java/lang/String.hashCode:()I
      27: iadd
      28: istore_1
      29: bipush        37
      31: iload_1
      32: imul
      33: aload_0
      34: invokevirtual #61                 // Method getType:()Ljava/lang/String;
      37: invokevirtual #59                 // Method java/lang/String.hashCode:()I
      40: iadd
      41: istore_1
      42: aload_0
      43: invokevirtual #62                 // Method getVersion:()Ljava/lang/String;
      46: ifnull        62
      49: bipush        37
      51: iload_1
      52: imul
      53: aload_0
      54: invokevirtual #62                 // Method getVersion:()Ljava/lang/String;
      57: invokevirtual #59                 // Method java/lang/String.hashCode:()I
      60: iadd
      61: istore_1
      62: bipush        37
      64: iload_1
      65: imul
      66: aload_0
      67: invokevirtual #63                 // Method getClassifier:()Ljava/lang/String;
      70: ifnull        83
      73: aload_0
      74: invokevirtual #63                 // Method getClassifier:()Ljava/lang/String;
      77: invokevirtual #59                 // Method java/lang/String.hashCode:()I
      80: goto          84
      83: iconst_0
      84: iadd
      85: istore_1
      86: iload_1
      87: ireturn

  public boolean equals(java.lang.Object);
    Code:
       0: aload_1
       1: aload_0
       2: if_acmpne     7
       5: iconst_1
       6: ireturn
       7: aload_1
       8: instanceof    #64                 // class org/apache/maven/artifact/Artifact
      11: ifne          16
      14: iconst_0
      15: ireturn
      16: aload_1
      17: checkcast     #64                 // class org/apache/maven/artifact/Artifact
      20: astore_2
      21: aload_2
      22: invokeinterface #8,  1            // InterfaceMethod org/apache/maven/artifact/Artifact.getGroupId:()Ljava/lang/String;
      27: aload_0
      28: invokevirtual #58                 // Method getGroupId:()Ljava/lang/String;
      31: invokevirtual #65                 // Method java/lang/String.equals:(Ljava/lang/Object;)Z
      34: ifne          39
      37: iconst_0
      38: ireturn
      39: aload_2
      40: invokeinterface #9,  1            // InterfaceMethod org/apache/maven/artifact/Artifact.getArtifactId:()Ljava/lang/String;
      45: aload_0
      46: invokevirtual #60                 // Method getArtifactId:()Ljava/lang/String;
      49: invokevirtual #65                 // Method java/lang/String.equals:(Ljava/lang/Object;)Z
      52: ifne          57
      55: iconst_0
      56: ireturn
      57: aload_2
      58: invokeinterface #10,  1           // InterfaceMethod org/apache/maven/artifact/Artifact.getVersion:()Ljava/lang/String;
      63: aload_0
      64: invokevirtual #62                 // Method getVersion:()Ljava/lang/String;
      67: invokevirtual #65                 // Method java/lang/String.equals:(Ljava/lang/Object;)Z
      70: ifne          75
      73: iconst_0
      74: ireturn
      75: aload_2
      76: invokeinterface #13,  1           // InterfaceMethod org/apache/maven/artifact/Artifact.getType:()Ljava/lang/String;
      81: aload_0
      82: invokevirtual #61                 // Method getType:()Ljava/lang/String;
      85: invokevirtual #65                 // Method java/lang/String.equals:(Ljava/lang/Object;)Z
      88: ifne          93
      91: iconst_0
      92: ireturn
      93: aload_2
      94: invokeinterface #14,  1           // InterfaceMethod org/apache/maven/artifact/Artifact.getClassifier:()Ljava/lang/String;
      99: ifnonnull     112
     102: aload_0
     103: invokevirtual #63                 // Method getClassifier:()Ljava/lang/String;
     106: ifnull        130
     109: goto          128
     112: aload_2
     113: invokeinterface #14,  1           // InterfaceMethod org/apache/maven/artifact/Artifact.getClassifier:()Ljava/lang/String;
     118: aload_0
     119: invokevirtual #63                 // Method getClassifier:()Ljava/lang/String;
     122: invokevirtual #65                 // Method java/lang/String.equals:(Ljava/lang/Object;)Z
     125: ifne          130
     128: iconst_0
     129: ireturn
     130: iconst_1
     131: ireturn

  public int compareTo(java.lang.Object);
    Code:
       0: aload_0
       1: aload_1
       2: checkcast     #64                 // class org/apache/maven/artifact/Artifact
       5: invokevirtual #66                 // Method compareTo:(Lorg/apache/maven/artifact/Artifact;)I
       8: ireturn
}
