Compiled from "MemoryAwareThreadPoolExecutor.java"
class org.jboss.netty.handler.execution.MemoryAwareThreadPoolExecutor$Limiter {
  final long limit;

  private long counter;

  private int waiters;

  org.jboss.netty.handler.execution.MemoryAwareThreadPoolExecutor$Limiter(long);
    Code:
       0: aload_0
       1: invokespecial #1                  // Method java/lang/Object."<init>":()V
       4: aload_0
       5: lload_1
       6: putfield      #2                  // Field limit:J
       9: return

  synchronized void increase(long);
    Code:
       0: aload_0
       1: getfield      #3                  // Field counter:J
       4: aload_0
       5: getfield      #2                  // Field limit:J
       8: lcmp
       9: iflt          70
      12: aload_0
      13: dup
      14: getfield      #4                  // Field waiters:I
      17: iconst_1
      18: iadd
      19: putfield      #4                  // Field waiters:I
      22: aload_0
      23: invokevirtual #5                  // Method java/lang/Object.wait:()V
      26: jsr           53
      29: goto          67
      32: astore_3
      33: invokestatic  #7                  // Method java/lang/Thread.currentThread:()Ljava/lang/Thread;
      36: invokevirtual #8                  // Method java/lang/Thread.interrupt:()V
      39: jsr           53
      42: goto          67
      45: astore        4
      47: jsr           53
      50: aload         4
      52: athrow
      53: astore        5
      55: aload_0
      56: dup
      57: getfield      #4                  // Field waiters:I
      60: iconst_1
      61: isub
      62: putfield      #4                  // Field waiters:I
      65: ret           5
      67: goto          0
      70: aload_0
      71: dup
      72: getfield      #3                  // Field counter:J
      75: lload_1
      76: ladd
      77: putfield      #3                  // Field counter:J
      80: return
    Exception table:
       from    to  target type
          22    26    32   Class java/lang/InterruptedException
          22    29    45   any
          32    42    45   any
          45    50    45   any

  synchronized void decrease(long);
    Code:
       0: aload_0
       1: dup
       2: getfield      #3                  // Field counter:J
       5: lload_1
       6: lsub
       7: putfield      #3                  // Field counter:J
      10: aload_0
      11: getfield      #3                  // Field counter:J
      14: aload_0
      15: getfield      #2                  // Field limit:J
      18: lcmp
      19: ifge          33
      22: aload_0
      23: getfield      #4                  // Field waiters:I
      26: ifle          33
      29: aload_0
      30: invokevirtual #9                  // Method java/lang/Object.notifyAll:()V
      33: return
}
