Compiled from "ReverseProxyHandlerHost.java"
final class org.wildfly.extension.undertow.handlers.ReverseProxyHandlerHost$ReverseProxyHostService implements org.jboss.msc.service.Service<org.wildfly.extension.undertow.handlers.ReverseProxyHandlerHost$ReverseProxyHostService> {
  private final org.jboss.msc.value.InjectedValue<io.undertow.server.HttpHandler> proxyHandler;

  private final org.jboss.msc.value.InjectedValue<org.jboss.as.network.OutboundSocketBinding> socketBinding;

  private final org.jboss.msc.value.InjectedValue<org.jboss.as.domain.management.SecurityRealm> securityRealm;

  private final java.lang.String instanceId;

  private final java.lang.String scheme;

  private final java.lang.String path;

  private org.wildfly.extension.undertow.handlers.ReverseProxyHandlerHost$ReverseProxyHostService(java.lang.String, java.lang.String, java.lang.String);
    Code:
       0: aload_0
       1: invokespecial #5                  // Method java/lang/Object."<init>":()V
       4: aload_0
       5: new           #6                  // class org/jboss/msc/value/InjectedValue
       8: dup
       9: invokespecial #7                  // Method org/jboss/msc/value/InjectedValue."<init>":()V
      12: putfield      #2                  // Field proxyHandler:Lorg/jboss/msc/value/InjectedValue;
      15: aload_0
      16: new           #6                  // class org/jboss/msc/value/InjectedValue
      19: dup
      20: invokespecial #7                  // Method org/jboss/msc/value/InjectedValue."<init>":()V
      23: putfield      #3                  // Field socketBinding:Lorg/jboss/msc/value/InjectedValue;
      26: aload_0
      27: new           #6                  // class org/jboss/msc/value/InjectedValue
      30: dup
      31: invokespecial #7                  // Method org/jboss/msc/value/InjectedValue."<init>":()V
      34: putfield      #1                  // Field securityRealm:Lorg/jboss/msc/value/InjectedValue;
      37: aload_0
      38: aload_2
      39: putfield      #8                  // Field instanceId:Ljava/lang/String;
      42: aload_0
      43: aload_1
      44: putfield      #9                  // Field scheme:Ljava/lang/String;
      47: aload_0
      48: aload_3
      49: putfield      #10                 // Field path:Ljava/lang/String;
      52: return

  private java.net.URI getUri() throws java.net.URISyntaxException;
    Code:
       0: aload_0
       1: getfield      #3                  // Field socketBinding:Lorg/jboss/msc/value/InjectedValue;
       4: invokevirtual #11                 // Method org/jboss/msc/value/InjectedValue.getValue:()Ljava/lang/Object;
       7: checkcast     #12                 // class org/jboss/as/network/OutboundSocketBinding
      10: astore_1
      11: new           #13                 // class java/net/URI
      14: dup
      15: aload_0
      16: getfield      #9                  // Field scheme:Ljava/lang/String;
      19: aconst_null
      20: aload_1
      21: invokevirtual #14                 // Method org/jboss/as/network/OutboundSocketBinding.getUnresolvedDestinationAddress:()Ljava/lang/String;
      24: aload_1
      25: invokevirtual #15                 // Method org/jboss/as/network/OutboundSocketBinding.getDestinationPort:()I
      28: aload_0
      29: getfield      #10                 // Field path:Ljava/lang/String;
      32: aconst_null
      33: aconst_null
      34: invokespecial #16                 // Method java/net/URI."<init>":(Ljava/lang/String;Ljava/lang/String;Ljava/lang/String;ILjava/lang/String;Ljava/lang/String;Ljava/lang/String;)V
      37: areturn

  public void start(org.jboss.msc.service.StartContext) throws org.jboss.msc.service.StartException;
    Code:
       0: aload_0
       1: getfield      #2                  // Field proxyHandler:Lorg/jboss/msc/value/InjectedValue;
       4: invokevirtual #11                 // Method org/jboss/msc/value/InjectedValue.getValue:()Ljava/lang/Object;
       7: instanceof    #17                 // class org/wildfly/extension/undertow/deployment/GlobalRequestControllerHandler
      10: ifeq          29
      13: aload_0
      14: getfield      #2                  // Field proxyHandler:Lorg/jboss/msc/value/InjectedValue;
      17: invokevirtual #11                 // Method org/jboss/msc/value/InjectedValue.getValue:()Ljava/lang/Object;
      20: checkcast     #17                 // class org/wildfly/extension/undertow/deployment/GlobalRequestControllerHandler
      23: invokevirtual #18                 // Method org/wildfly/extension/undertow/deployment/GlobalRequestControllerHandler.getNext:()Lio/undertow/server/HttpHandler;
      26: goto          39
      29: aload_0
      30: getfield      #2                  // Field proxyHandler:Lorg/jboss/msc/value/InjectedValue;
      33: invokevirtual #11                 // Method org/jboss/msc/value/InjectedValue.getValue:()Ljava/lang/Object;
      36: checkcast     #19                 // class io/undertow/server/HttpHandler
      39: checkcast     #20                 // class io/undertow/server/handlers/proxy/ProxyHandler
      42: checkcast     #20                 // class io/undertow/server/handlers/proxy/ProxyHandler
      45: astore_2
      46: aload_2
      47: invokevirtual #21                 // Method io/undertow/server/handlers/proxy/ProxyHandler.getProxyClient:()Lio/undertow/server/handlers/proxy/ProxyClient;
      50: checkcast     #22                 // class io/undertow/server/handlers/proxy/LoadBalancingProxyClient
      53: astore_3
      54: aload_0
      55: getfield      #1                  // Field securityRealm:Lorg/jboss/msc/value/InjectedValue;
      58: invokevirtual #23                 // Method org/jboss/msc/value/InjectedValue.getOptionalValue:()Ljava/lang/Object;
      61: ifnonnull     80
      64: aload_3
      65: aload_0
      66: invokespecial #24                 // Method getUri:()Ljava/net/URI;
      69: aload_0
      70: getfield      #8                  // Field instanceId:Ljava/lang/String;
      73: invokevirtual #25                 // Method io/undertow/server/handlers/proxy/LoadBalancingProxyClient.addHost:(Ljava/net/URI;Ljava/lang/String;)Lio/undertow/server/handlers/proxy/LoadBalancingProxyClient;
      76: pop
      77: goto          150
      80: aload_0
      81: getfield      #1                  // Field securityRealm:Lorg/jboss/msc/value/InjectedValue;
      84: invokevirtual #23                 // Method org/jboss/msc/value/InjectedValue.getOptionalValue:()Ljava/lang/Object;
      87: checkcast     #26                 // class org/jboss/as/domain/management/SecurityRealm
      90: invokeinterface #27,  1           // InterfaceMethod org/jboss/as/domain/management/SecurityRealm.getSSLContext:()Ljavax/net/ssl/SSLContext;
      95: astore        4
      97: invokestatic  #28                 // Method org/xnio/OptionMap.builder:()Lorg/xnio/OptionMap$Builder;
     100: astore        5
     102: aload         5
     104: getstatic     #29                 // Field org/xnio/Options.USE_DIRECT_BUFFERS:Lorg/xnio/Option;
     107: iconst_1
     108: invokevirtual #30                 // Method org/xnio/OptionMap$Builder.set:(Lorg/xnio/Option;Z)Lorg/xnio/OptionMap$Builder;
     111: pop
     112: aload         5
     114: invokevirtual #31                 // Method org/xnio/OptionMap$Builder.getMap:()Lorg/xnio/OptionMap;
     117: astore        6
     119: new           #32                 // class io/undertow/protocols/ssl/UndertowXnioSsl
     122: dup
     123: invokestatic  #33                 // Method org/xnio/Xnio.getInstance:()Lorg/xnio/Xnio;
     126: aload         6
     128: aload         4
     130: invokespecial #34                 // Method io/undertow/protocols/ssl/UndertowXnioSsl."<init>":(Lorg/xnio/Xnio;Lorg/xnio/OptionMap;Ljavax/net/ssl/SSLContext;)V
     133: astore        7
     135: aload_3
     136: aload_0
     137: invokespecial #24                 // Method getUri:()Ljava/net/URI;
     140: aload_0
     141: getfield      #8                  // Field instanceId:Ljava/lang/String;
     144: aload         7
     146: invokevirtual #35                 // Method io/undertow/server/handlers/proxy/LoadBalancingProxyClient.addHost:(Ljava/net/URI;Ljava/lang/String;Lorg/xnio/ssl/XnioSsl;)Lio/undertow/server/handlers/proxy/LoadBalancingProxyClient;
     149: pop
     150: goto          165
     153: astore        4
     155: new           #37                 // class org/jboss/msc/service/StartException
     158: dup
     159: aload         4
     161: invokespecial #38                 // Method org/jboss/msc/service/StartException."<init>":(Ljava/lang/Throwable;)V
     164: athrow
     165: return
    Exception table:
       from    to  target type
          54   150   153   Class java/net/URISyntaxException

  public void stop(org.jboss.msc.service.StopContext);
    Code:
       0: aload_0
       1: getfield      #2                  // Field proxyHandler:Lorg/jboss/msc/value/InjectedValue;
       4: invokevirtual #11                 // Method org/jboss/msc/value/InjectedValue.getValue:()Ljava/lang/Object;
       7: instanceof    #17                 // class org/wildfly/extension/undertow/deployment/GlobalRequestControllerHandler
      10: ifeq          29
      13: aload_0
      14: getfield      #2                  // Field proxyHandler:Lorg/jboss/msc/value/InjectedValue;
      17: invokevirtual #11                 // Method org/jboss/msc/value/InjectedValue.getValue:()Ljava/lang/Object;
      20: checkcast     #17                 // class org/wildfly/extension/undertow/deployment/GlobalRequestControllerHandler
      23: invokevirtual #18                 // Method org/wildfly/extension/undertow/deployment/GlobalRequestControllerHandler.getNext:()Lio/undertow/server/HttpHandler;
      26: goto          39
      29: aload_0
      30: getfield      #2                  // Field proxyHandler:Lorg/jboss/msc/value/InjectedValue;
      33: invokevirtual #11                 // Method org/jboss/msc/value/InjectedValue.getValue:()Ljava/lang/Object;
      36: checkcast     #19                 // class io/undertow/server/HttpHandler
      39: checkcast     #20                 // class io/undertow/server/handlers/proxy/ProxyHandler
      42: checkcast     #20                 // class io/undertow/server/handlers/proxy/ProxyHandler
      45: astore_2
      46: aload_2
      47: invokevirtual #21                 // Method io/undertow/server/handlers/proxy/ProxyHandler.getProxyClient:()Lio/undertow/server/handlers/proxy/ProxyClient;
      50: checkcast     #22                 // class io/undertow/server/handlers/proxy/LoadBalancingProxyClient
      53: astore_3
      54: aload_3
      55: aload_0
      56: invokespecial #24                 // Method getUri:()Ljava/net/URI;
      59: invokevirtual #39                 // Method io/undertow/server/handlers/proxy/LoadBalancingProxyClient.removeHost:(Ljava/net/URI;)Lio/undertow/server/handlers/proxy/LoadBalancingProxyClient;
      62: pop
      63: goto          78
      66: astore        4
      68: new           #40                 // class java/lang/RuntimeException
      71: dup
      72: aload         4
      74: invokespecial #41                 // Method java/lang/RuntimeException."<init>":(Ljava/lang/Throwable;)V
      77: athrow
      78: return
    Exception table:
       from    to  target type
          54    63    66   Class java/net/URISyntaxException

  public org.wildfly.extension.undertow.handlers.ReverseProxyHandlerHost$ReverseProxyHostService getValue() throws java.lang.IllegalStateException, java.lang.IllegalArgumentException;
    Code:
       0: aload_0
       1: areturn

  public java.lang.Object getValue() throws java.lang.IllegalStateException, java.lang.IllegalArgumentException;
    Code:
       0: aload_0
       1: invokevirtual #42                 // Method getValue:()Lorg/wildfly/extension/undertow/handlers/ReverseProxyHandlerHost$ReverseProxyHostService;
       4: areturn

  org.wildfly.extension.undertow.handlers.ReverseProxyHandlerHost$ReverseProxyHostService(java.lang.String, java.lang.String, java.lang.String, org.wildfly.extension.undertow.handlers.ReverseProxyHandlerHost$1);
    Code:
       0: aload_0
       1: aload_1
       2: aload_2
       3: aload_3
       4: invokespecial #4                  // Method "<init>":(Ljava/lang/String;Ljava/lang/String;Ljava/lang/String;)V
       7: return

  static org.jboss.msc.value.InjectedValue access$200(org.wildfly.extension.undertow.handlers.ReverseProxyHandlerHost$ReverseProxyHostService);
    Code:
       0: aload_0
       1: getfield      #3                  // Field socketBinding:Lorg/jboss/msc/value/InjectedValue;
       4: areturn

  static org.jboss.msc.value.InjectedValue access$300(org.wildfly.extension.undertow.handlers.ReverseProxyHandlerHost$ReverseProxyHostService);
    Code:
       0: aload_0
       1: getfield      #2                  // Field proxyHandler:Lorg/jboss/msc/value/InjectedValue;
       4: areturn

  static org.jboss.msc.value.InjectedValue access$400(org.wildfly.extension.undertow.handlers.ReverseProxyHandlerHost$ReverseProxyHostService);
    Code:
       0: aload_0
       1: getfield      #1                  // Field securityRealm:Lorg/jboss/msc/value/InjectedValue;
       4: areturn
}
