Compiled from "IncludeAction.java"
public class ch.qos.logback.core.joran.action.IncludeAction extends ch.qos.logback.core.joran.action.Action {
  private static final java.lang.String FILE_ATTR;

  private static final java.lang.String URL_ATTR;

  private static final java.lang.String RESOURCE_ATTR;

  private static final java.lang.String OPTIONAL_ATTR;

  private java.lang.String attributeInUse;

  private boolean optional;

  ch.qos.logback.core.model.Model parentModel;

  ch.qos.logback.core.model.IncludeModel includeModel;

  boolean inError;

  public ch.qos.logback.core.joran.action.IncludeAction();
    Code:
       0: aload_0
       1: invokespecial #3                  // Method ch/qos/logback/core/joran/action/Action."<init>":()V
       4: aload_0
       5: iconst_0
       6: putfield      #9                  // Field inError:Z
       9: return

  public void begin(ch.qos.logback.core.joran.spi.SaxEventInterpretationContext, java.lang.String, org.xml.sax.Attributes) throws ch.qos.logback.core.joran.spi.ActionException;
    Code:
       0: aload_0
       1: aconst_null
       2: putfield      #15                 // Field parentModel:Lch/qos/logback/core/model/Model;
       5: aload_0
       6: aconst_null
       7: putfield      #19                 // Field includeModel:Lch/qos/logback/core/model/IncludeModel;
      10: new           #23                 // class ch/qos/logback/core/joran/event/SaxEventRecorder
      13: dup
      14: aload_0
      15: getfield      #25                 // Field context:Lch/qos/logback/core/Context;
      18: invokespecial #29                 // Method ch/qos/logback/core/joran/event/SaxEventRecorder."<init>":(Lch/qos/logback/core/Context;)V
      21: astore        4
      23: aload_3
      24: ldc           #32                 // String optional
      26: invokeinterface #34,  2           // InterfaceMethod org/xml/sax/Attributes.getValue:(Ljava/lang/String;)Ljava/lang/String;
      31: astore        5
      33: aload_0
      34: aload_1
      35: aload_2
      36: aload_3
      37: aload         5
      39: invokevirtual #40                 // Method createModelForAlternateUse:(Lch/qos/logback/core/joran/spi/SaxEventInterpretationContext;Ljava/lang/String;Lorg/xml/sax/Attributes;Ljava/lang/String;)V
      42: aload_0
      43: aconst_null
      44: putfield      #44                 // Field attributeInUse:Ljava/lang/String;
      47: aload_0
      48: aload         5
      50: iconst_0
      51: invokestatic  #48                 // Method ch/qos/logback/core/util/OptionHelper.toBoolean:(Ljava/lang/String;Z)Z
      54: putfield      #54                 // Field optional:Z
      57: aload_0
      58: aload_3
      59: invokevirtual #56                 // Method checkAttributes:(Lorg/xml/sax/Attributes;)Z
      62: ifne          71
      65: aload_0
      66: iconst_1
      67: putfield      #9                  // Field inError:Z
      70: return
      71: aload_0
      72: aload_1
      73: aload_3
      74: invokevirtual #60                 // Method getInputStream:(Lch/qos/logback/core/joran/spi/SaxEventInterpretationContext;Lorg/xml/sax/Attributes;)Ljava/io/InputStream;
      77: astore        6
      79: aload         6
      81: ifnull        114
      84: aload_0
      85: aload         6
      87: aload         4
      89: invokevirtual #64                 // Method parseAndRecord:(Ljava/io/InputStream;Lch/qos/logback/core/joran/event/SaxEventRecorder;)V
      92: aload_0
      93: aload         4
      95: invokevirtual #68                 // Method trimHeadAndTail:(Lch/qos/logback/core/joran/event/SaxEventRecorder;)V
      98: aload_1
      99: invokevirtual #72                 // Method ch/qos/logback/core/joran/spi/SaxEventInterpretationContext.getSaxEventInterpreter:()Lch/qos/logback/core/joran/spi/SaxEventInterpreter;
     102: invokevirtual #78                 // Method ch/qos/logback/core/joran/spi/SaxEventInterpreter.getEventPlayer:()Lch/qos/logback/core/joran/spi/EventPlayer;
     105: aload         4
     107: invokevirtual #84                 // Method ch/qos/logback/core/joran/event/SaxEventRecorder.getSaxEventList:()Ljava/util/List;
     110: iconst_2
     111: invokevirtual #88                 // Method ch/qos/logback/core/joran/spi/EventPlayer.addEventsDynamically:(Ljava/util/List;I)V
     114: aload_0
     115: aload         6
     117: invokevirtual #94                 // Method close:(Ljava/io/InputStream;)V
     120: goto          160
     123: astore        7
     125: aload_0
     126: aload_0
     127: getfield      #44                 // Field attributeInUse:Ljava/lang/String;
     130: invokedynamic #100,  0            // InvokeDynamic #0:makeConcatWithConstants:(Ljava/lang/String;)Ljava/lang/String;
     135: aload         7
     137: invokevirtual #103                // Method addError:(Ljava/lang/String;Ljava/lang/Throwable;)V
     140: aload_0
     141: aload         6
     143: invokevirtual #94                 // Method close:(Ljava/io/InputStream;)V
     146: goto          160
     149: astore        8
     151: aload_0
     152: aload         6
     154: invokevirtual #94                 // Method close:(Ljava/io/InputStream;)V
     157: aload         8
     159: athrow
     160: return
    Exception table:
       from    to  target type
          79   114   123   Class ch/qos/logback/core/joran/spi/JoranException
          79   114   149   any
         123   140   149   any
         149   151   149   any

  private void createModelForAlternateUse(ch.qos.logback.core.joran.spi.SaxEventInterpretationContext, java.lang.String, org.xml.sax.Attributes, java.lang.String);
    Code:
       0: aload_0
       1: new           #107                // class ch/qos/logback/core/model/IncludeModel
       4: dup
       5: invokespecial #109                // Method ch/qos/logback/core/model/IncludeModel."<init>":()V
       8: putfield      #19                 // Field includeModel:Lch/qos/logback/core/model/IncludeModel;
      11: aload_0
      12: getfield      #19                 // Field includeModel:Lch/qos/logback/core/model/IncludeModel;
      15: aload         4
      17: invokevirtual #110                // Method ch/qos/logback/core/model/IncludeModel.setOptional:(Ljava/lang/String;)V
      20: aload_0
      21: aload_0
      22: getfield      #19                 // Field includeModel:Lch/qos/logback/core/model/IncludeModel;
      25: aload_2
      26: aload_3
      27: invokevirtual #114                // Method fillInIncludeModelAttributes:(Lch/qos/logback/core/model/IncludeModel;Ljava/lang/String;Lorg/xml/sax/Attributes;)V
      30: aload_1
      31: invokevirtual #118                // Method ch/qos/logback/core/joran/spi/SaxEventInterpretationContext.isModelStackEmpty:()Z
      34: ifne          45
      37: aload_0
      38: aload_1
      39: invokevirtual #122                // Method ch/qos/logback/core/joran/spi/SaxEventInterpretationContext.peekModel:()Lch/qos/logback/core/model/Model;
      42: putfield      #15                 // Field parentModel:Lch/qos/logback/core/model/Model;
      45: aload_1
      46: invokestatic  #126                // Method getLineNumber:(Lch/qos/logback/core/joran/spi/SaxEventInterpretationContext;)I
      49: istore        5
      51: aload_0
      52: getfield      #19                 // Field includeModel:Lch/qos/logback/core/model/IncludeModel;
      55: iload         5
      57: invokevirtual #130                // Method ch/qos/logback/core/model/IncludeModel.setLineNumber:(I)V
      60: aload_1
      61: aload_0
      62: getfield      #19                 // Field includeModel:Lch/qos/logback/core/model/IncludeModel;
      65: invokevirtual #134                // Method ch/qos/logback/core/joran/spi/SaxEventInterpretationContext.pushModel:(Lch/qos/logback/core/model/Model;)V
      68: return

  private void fillInIncludeModelAttributes(ch.qos.logback.core.model.IncludeModel, java.lang.String, org.xml.sax.Attributes);
    Code:
       0: aload_0
       1: getfield      #19                 // Field includeModel:Lch/qos/logback/core/model/IncludeModel;
       4: aload_2
       5: invokevirtual #138                // Method ch/qos/logback/core/model/IncludeModel.setTag:(Ljava/lang/String;)V
       8: aload_3
       9: ldc           #141                // String file
      11: invokeinterface #34,  2           // InterfaceMethod org/xml/sax/Attributes.getValue:(Ljava/lang/String;)Ljava/lang/String;
      16: astore        4
      18: aload_3
      19: ldc           #143                // String url
      21: invokeinterface #34,  2           // InterfaceMethod org/xml/sax/Attributes.getValue:(Ljava/lang/String;)Ljava/lang/String;
      26: astore        5
      28: aload_3
      29: ldc           #145                // String resource
      31: invokeinterface #34,  2           // InterfaceMethod org/xml/sax/Attributes.getValue:(Ljava/lang/String;)Ljava/lang/String;
      36: astore        6
      38: aload_0
      39: getfield      #19                 // Field includeModel:Lch/qos/logback/core/model/IncludeModel;
      42: aload         4
      44: invokevirtual #147                // Method ch/qos/logback/core/model/IncludeModel.setFile:(Ljava/lang/String;)V
      47: aload_0
      48: getfield      #19                 // Field includeModel:Lch/qos/logback/core/model/IncludeModel;
      51: aload         5
      53: invokevirtual #150                // Method ch/qos/logback/core/model/IncludeModel.setUrl:(Ljava/lang/String;)V
      56: aload_0
      57: getfield      #19                 // Field includeModel:Lch/qos/logback/core/model/IncludeModel;
      60: aload         6
      62: invokevirtual #153                // Method ch/qos/logback/core/model/IncludeModel.setResource:(Ljava/lang/String;)V
      65: return

  void close(java.io.InputStream);
    Code:
       0: aload_1
       1: ifnull        12
       4: aload_1
       5: invokevirtual #156                // Method java/io/InputStream.close:()V
       8: goto          12
      11: astore_2
      12: return
    Exception table:
       from    to  target type
           4     8    11   Class java/io/IOException

  private boolean checkAttributes(org.xml.sax.Attributes);
    Code:
       0: aload_1
       1: ldc           #141                // String file
       3: invokeinterface #34,  2           // InterfaceMethod org/xml/sax/Attributes.getValue:(Ljava/lang/String;)Ljava/lang/String;
       8: astore_2
       9: aload_1
      10: ldc           #143                // String url
      12: invokeinterface #34,  2           // InterfaceMethod org/xml/sax/Attributes.getValue:(Ljava/lang/String;)Ljava/lang/String;
      17: astore_3
      18: aload_1
      19: ldc           #145                // String resource
      21: invokeinterface #34,  2           // InterfaceMethod org/xml/sax/Attributes.getValue:(Ljava/lang/String;)Ljava/lang/String;
      26: astore        4
      28: iconst_0
      29: istore        5
      31: aload_2
      32: invokestatic  #162                // Method ch/qos/logback/core/util/OptionHelper.isNullOrEmpty:(Ljava/lang/String;)Z
      35: ifne          41
      38: iinc          5, 1
      41: aload_3
      42: invokestatic  #162                // Method ch/qos/logback/core/util/OptionHelper.isNullOrEmpty:(Ljava/lang/String;)Z
      45: ifne          51
      48: iinc          5, 1
      51: aload         4
      53: invokestatic  #162                // Method ch/qos/logback/core/util/OptionHelper.isNullOrEmpty:(Ljava/lang/String;)Z
      56: ifne          62
      59: iinc          5, 1
      62: iload         5
      64: ifne          75
      67: aload_0
      68: ldc           #166                // String One of \"path\", \"resource\" or \"url\" attributes must be set.
      70: invokevirtual #168                // Method addError:(Ljava/lang/String;)V
      73: iconst_0
      74: ireturn
      75: iload         5
      77: iconst_1
      78: if_icmple     89
      81: aload_0
      82: ldc           #170                // String Only one of \"file\", \"url\" or \"resource\" attributes should be set.
      84: invokevirtual #168                // Method addError:(Ljava/lang/String;)V
      87: iconst_0
      88: ireturn
      89: iload         5
      91: iconst_1
      92: if_icmpne     97
      95: iconst_1
      96: ireturn
      97: new           #172                // class java/lang/IllegalStateException
     100: dup
     101: iload         5
     103: invokedynamic #174,  0            // InvokeDynamic #1:makeConcatWithConstants:(I)Ljava/lang/String;
     108: invokespecial #177                // Method java/lang/IllegalStateException."<init>":(Ljava/lang/String;)V
     111: athrow

  java.net.URL attributeToURL(java.lang.String);
    Code:
       0: new           #179                // class java/net/URL
       3: dup
       4: aload_1
       5: invokespecial #181                // Method java/net/URL."<init>":(Ljava/lang/String;)V
       8: areturn
       9: astore_2
      10: aload_1
      11: invokedynamic #184,  0            // InvokeDynamic #2:makeConcatWithConstants:(Ljava/lang/String;)Ljava/lang/String;
      16: astore_3
      17: aload_0
      18: aload_3
      19: aload_2
      20: invokevirtual #103                // Method addError:(Ljava/lang/String;Ljava/lang/Throwable;)V
      23: aconst_null
      24: areturn
    Exception table:
       from    to  target type
           0     8     9   Class java/net/MalformedURLException

  java.io.InputStream openURL(java.net.URL);
    Code:
       0: aload_1
       1: invokevirtual #185                // Method java/net/URL.openStream:()Ljava/io/InputStream;
       4: areturn
       5: astore_2
       6: aload_0
       7: aload_1
       8: invokevirtual #189                // Method java/net/URL.toString:()Ljava/lang/String;
      11: invokedynamic #193,  0            // InvokeDynamic #3:makeConcatWithConstants:(Ljava/lang/String;)Ljava/lang/String;
      16: invokevirtual #194                // Method optionalWarning:(Ljava/lang/String;)V
      19: aconst_null
      20: areturn
    Exception table:
       from    to  target type
           0     4     5   Class java/io/IOException

  java.net.URL resourceAsURL(java.lang.String);
    Code:
       0: aload_1
       1: invokestatic  #197                // Method ch/qos/logback/core/util/Loader.getResourceBySelfClassLoader:(Ljava/lang/String;)Ljava/net/URL;
       4: astore_2
       5: aload_2
       6: ifnonnull     21
       9: aload_0
      10: aload_1
      11: invokedynamic #203,  0            // InvokeDynamic #4:makeConcatWithConstants:(Ljava/lang/String;)Ljava/lang/String;
      16: invokevirtual #194                // Method optionalWarning:(Ljava/lang/String;)V
      19: aconst_null
      20: areturn
      21: aload_2
      22: areturn

  private void optionalWarning(java.lang.String);
    Code:
       0: aload_0
       1: getfield      #54                 // Field optional:Z
       4: ifne          12
       7: aload_0
       8: aload_1
       9: invokevirtual #204                // Method addWarn:(Ljava/lang/String;)V
      12: return

  java.net.URL filePathAsURL(java.lang.String);
    Code:
       0: new           #207                // class java/io/File
       3: dup
       4: aload_1
       5: invokespecial #209                // Method java/io/File."<init>":(Ljava/lang/String;)V
       8: invokevirtual #210                // Method java/io/File.toURI:()Ljava/net/URI;
      11: astore_2
      12: aload_2
      13: invokevirtual #214                // Method java/net/URI.toURL:()Ljava/net/URL;
      16: areturn
      17: astore_3
      18: aload_3
      19: invokevirtual #220                // Method java/net/MalformedURLException.printStackTrace:()V
      22: aconst_null
      23: areturn
    Exception table:
       from    to  target type
          12    16    17   Class java/net/MalformedURLException

  java.net.URL getInputURL(ch.qos.logback.core.joran.spi.SaxEventInterpretationContext, org.xml.sax.Attributes);
    Code:
       0: aload_2
       1: ldc           #141                // String file
       3: invokeinterface #34,  2           // InterfaceMethod org/xml/sax/Attributes.getValue:(Ljava/lang/String;)Ljava/lang/String;
       8: astore_3
       9: aload_2
      10: ldc           #143                // String url
      12: invokeinterface #34,  2           // InterfaceMethod org/xml/sax/Attributes.getValue:(Ljava/lang/String;)Ljava/lang/String;
      17: astore        4
      19: aload_2
      20: ldc           #145                // String resource
      22: invokeinterface #34,  2           // InterfaceMethod org/xml/sax/Attributes.getValue:(Ljava/lang/String;)Ljava/lang/String;
      27: astore        5
      29: aload_3
      30: invokestatic  #162                // Method ch/qos/logback/core/util/OptionHelper.isNullOrEmpty:(Ljava/lang/String;)Z
      33: ifne          54
      36: aload_0
      37: aload_1
      38: aload_3
      39: invokevirtual #223                // Method ch/qos/logback/core/joran/spi/SaxEventInterpretationContext.subst:(Ljava/lang/String;)Ljava/lang/String;
      42: putfield      #44                 // Field attributeInUse:Ljava/lang/String;
      45: aload_0
      46: aload_0
      47: getfield      #44                 // Field attributeInUse:Ljava/lang/String;
      50: invokevirtual #226                // Method filePathAsURL:(Ljava/lang/String;)Ljava/net/URL;
      53: areturn
      54: aload         4
      56: invokestatic  #162                // Method ch/qos/logback/core/util/OptionHelper.isNullOrEmpty:(Ljava/lang/String;)Z
      59: ifne          81
      62: aload_0
      63: aload_1
      64: aload         4
      66: invokevirtual #223                // Method ch/qos/logback/core/joran/spi/SaxEventInterpretationContext.subst:(Ljava/lang/String;)Ljava/lang/String;
      69: putfield      #44                 // Field attributeInUse:Ljava/lang/String;
      72: aload_0
      73: aload_0
      74: getfield      #44                 // Field attributeInUse:Ljava/lang/String;
      77: invokevirtual #229                // Method attributeToURL:(Ljava/lang/String;)Ljava/net/URL;
      80: areturn
      81: aload         5
      83: invokestatic  #162                // Method ch/qos/logback/core/util/OptionHelper.isNullOrEmpty:(Ljava/lang/String;)Z
      86: ifne          108
      89: aload_0
      90: aload_1
      91: aload         5
      93: invokevirtual #223                // Method ch/qos/logback/core/joran/spi/SaxEventInterpretationContext.subst:(Ljava/lang/String;)Ljava/lang/String;
      96: putfield      #44                 // Field attributeInUse:Ljava/lang/String;
      99: aload_0
     100: aload_0
     101: getfield      #44                 // Field attributeInUse:Ljava/lang/String;
     104: invokevirtual #232                // Method resourceAsURL:(Ljava/lang/String;)Ljava/net/URL;
     107: areturn
     108: new           #172                // class java/lang/IllegalStateException
     111: dup
     112: ldc           #235                // String A URL stream should have been returned
     114: invokespecial #177                // Method java/lang/IllegalStateException."<init>":(Ljava/lang/String;)V
     117: athrow

  java.io.InputStream getInputStream(ch.qos.logback.core.joran.spi.SaxEventInterpretationContext, org.xml.sax.Attributes);
    Code:
       0: aload_0
       1: aload_1
       2: aload_2
       3: invokevirtual #237                // Method getInputURL:(Lch/qos/logback/core/joran/spi/SaxEventInterpretationContext;Lorg/xml/sax/Attributes;)Ljava/net/URL;
       6: astore_3
       7: aload_3
       8: ifnonnull     13
      11: aconst_null
      12: areturn
      13: aload_0
      14: getfield      #25                 // Field context:Lch/qos/logback/core/Context;
      17: aload_3
      18: invokestatic  #241                // Method ch/qos/logback/core/joran/util/ConfigurationWatchListUtil.addToWatchList:(Lch/qos/logback/core/Context;Ljava/net/URL;)V
      21: aload_0
      22: aload_3
      23: invokevirtual #247                // Method openURL:(Ljava/net/URL;)Ljava/io/InputStream;
      26: areturn

  private void trimHeadAndTail(ch.qos.logback.core.joran.event.SaxEventRecorder);
    Code:
       0: aload_1
       1: invokevirtual #84                 // Method ch/qos/logback/core/joran/event/SaxEventRecorder.getSaxEventList:()Ljava/util/List;
       4: astore_2
       5: aload_2
       6: invokeinterface #251,  1          // InterfaceMethod java/util/List.size:()I
      11: ifne          15
      14: return
      15: aload_2
      16: iconst_0
      17: invokeinterface #257,  2          // InterfaceMethod java/util/List.get:(I)Ljava/lang/Object;
      22: checkcast     #261                // class ch/qos/logback/core/joran/event/SaxEvent
      25: astore_3
      26: aload_3
      27: ifnull        51
      30: aload_3
      31: getfield      #263                // Field ch/qos/logback/core/joran/event/SaxEvent.qName:Ljava/lang/String;
      34: ldc_w         #266                // String included
      37: invokevirtual #268                // Method java/lang/String.equalsIgnoreCase:(Ljava/lang/String;)Z
      40: ifeq          51
      43: aload_2
      44: iconst_0
      45: invokeinterface #273,  2          // InterfaceMethod java/util/List.remove:(I)Ljava/lang/Object;
      50: pop
      51: aload_2
      52: aload_2
      53: invokeinterface #251,  1          // InterfaceMethod java/util/List.size:()I
      58: iconst_1
      59: isub
      60: invokeinterface #257,  2          // InterfaceMethod java/util/List.get:(I)Ljava/lang/Object;
      65: checkcast     #261                // class ch/qos/logback/core/joran/event/SaxEvent
      68: astore        4
      70: aload         4
      72: ifnull        104
      75: aload         4
      77: getfield      #263                // Field ch/qos/logback/core/joran/event/SaxEvent.qName:Ljava/lang/String;
      80: ldc_w         #266                // String included
      83: invokevirtual #268                // Method java/lang/String.equalsIgnoreCase:(Ljava/lang/String;)Z
      86: ifeq          104
      89: aload_2
      90: aload_2
      91: invokeinterface #251,  1          // InterfaceMethod java/util/List.size:()I
      96: iconst_1
      97: isub
      98: invokeinterface #273,  2          // InterfaceMethod java/util/List.remove:(I)Ljava/lang/Object;
     103: pop
     104: return

  private void parseAndRecord(java.io.InputStream, ch.qos.logback.core.joran.event.SaxEventRecorder) throws ch.qos.logback.core.joran.spi.JoranException;
    Code:
       0: aload_2
       1: aload_0
       2: getfield      #25                 // Field context:Lch/qos/logback/core/Context;
       5: invokevirtual #276                // Method ch/qos/logback/core/joran/event/SaxEventRecorder.setContext:(Lch/qos/logback/core/Context;)V
       8: aload_2
       9: aload_1
      10: invokevirtual #279                // Method ch/qos/logback/core/joran/event/SaxEventRecorder.recordEvents:(Ljava/io/InputStream;)V
      13: return

  public void end(ch.qos.logback.core.joran.spi.SaxEventInterpretationContext, java.lang.String) throws ch.qos.logback.core.joran.spi.ActionException;
    Code:
       0: aload_0
       1: getfield      #9                  // Field inError:Z
       4: ifeq          8
       7: return
       8: aload_1
       9: invokevirtual #122                // Method ch/qos/logback/core/joran/spi/SaxEventInterpretationContext.peekModel:()Lch/qos/logback/core/model/Model;
      12: astore_3
      13: aload_3
      14: aload_0
      15: getfield      #19                 // Field includeModel:Lch/qos/logback/core/model/IncludeModel;
      18: if_acmpeq     44
      21: aload_0
      22: aload_0
      23: getfield      #19                 // Field includeModel:Lch/qos/logback/core/model/IncludeModel;
      26: invokevirtual #282                // Method ch/qos/logback/core/model/IncludeModel.idString:()Ljava/lang/String;
      29: invokedynamic #285,  0            // InvokeDynamic #5:makeConcatWithConstants:(Ljava/lang/String;)Ljava/lang/String;
      34: invokevirtual #204                // Method addWarn:(Ljava/lang/String;)V
      37: aload_0
      38: ldc_w         #286                // String This is wholly unexpected.
      41: invokevirtual #204                // Method addWarn:(Ljava/lang/String;)V
      44: aload_0
      45: getfield      #15                 // Field parentModel:Lch/qos/logback/core/model/Model;
      48: ifnull        67
      51: aload_0
      52: getfield      #15                 // Field parentModel:Lch/qos/logback/core/model/Model;
      55: aload_0
      56: getfield      #19                 // Field includeModel:Lch/qos/logback/core/model/IncludeModel;
      59: invokevirtual #288                // Method ch/qos/logback/core/model/Model.addSubModel:(Lch/qos/logback/core/model/Model;)V
      62: aload_1
      63: invokevirtual #293                // Method ch/qos/logback/core/joran/spi/SaxEventInterpretationContext.popModel:()Lch/qos/logback/core/model/Model;
      66: pop
      67: return
}
