Compiled from "DefaultCookieSpecProvider.java"
public class org.apache.http.impl.cookie.DefaultCookieSpecProvider implements org.apache.http.cookie.CookieSpecProvider {
  private final org.apache.http.impl.cookie.DefaultCookieSpecProvider$CompatibilityLevel compatibilityLevel;

  private final org.apache.http.conn.util.PublicSuffixMatcher publicSuffixMatcher;

  private final java.lang.String[] datepatterns;

  private final boolean oneHeader;

  private volatile org.apache.http.cookie.CookieSpec cookieSpec;

  public org.apache.http.impl.cookie.DefaultCookieSpecProvider(org.apache.http.impl.cookie.DefaultCookieSpecProvider$CompatibilityLevel, org.apache.http.conn.util.PublicSuffixMatcher, java.lang.String[], boolean);
    Code:
       0: aload_0
       1: invokespecial #1                  // Method java/lang/Object."<init>":()V
       4: aload_0
       5: aload_1
       6: ifnull        13
       9: aload_1
      10: goto          16
      13: getstatic     #2                  // Field org/apache/http/impl/cookie/DefaultCookieSpecProvider$CompatibilityLevel.DEFAULT:Lorg/apache/http/impl/cookie/DefaultCookieSpecProvider$CompatibilityLevel;
      16: putfield      #3                  // Field compatibilityLevel:Lorg/apache/http/impl/cookie/DefaultCookieSpecProvider$CompatibilityLevel;
      19: aload_0
      20: aload_2
      21: putfield      #4                  // Field publicSuffixMatcher:Lorg/apache/http/conn/util/PublicSuffixMatcher;
      24: aload_0
      25: aload_3
      26: putfield      #5                  // Field datepatterns:[Ljava/lang/String;
      29: aload_0
      30: iload         4
      32: putfield      #6                  // Field oneHeader:Z
      35: return

  public org.apache.http.impl.cookie.DefaultCookieSpecProvider(org.apache.http.impl.cookie.DefaultCookieSpecProvider$CompatibilityLevel, org.apache.http.conn.util.PublicSuffixMatcher);
    Code:
       0: aload_0
       1: aload_1
       2: aload_2
       3: aconst_null
       4: iconst_0
       5: invokespecial #7                  // Method "<init>":(Lorg/apache/http/impl/cookie/DefaultCookieSpecProvider$CompatibilityLevel;Lorg/apache/http/conn/util/PublicSuffixMatcher;[Ljava/lang/String;Z)V
       8: return

  public org.apache.http.impl.cookie.DefaultCookieSpecProvider(org.apache.http.conn.util.PublicSuffixMatcher);
    Code:
       0: aload_0
       1: getstatic     #2                  // Field org/apache/http/impl/cookie/DefaultCookieSpecProvider$CompatibilityLevel.DEFAULT:Lorg/apache/http/impl/cookie/DefaultCookieSpecProvider$CompatibilityLevel;
       4: aload_1
       5: aconst_null
       6: iconst_0
       7: invokespecial #7                  // Method "<init>":(Lorg/apache/http/impl/cookie/DefaultCookieSpecProvider$CompatibilityLevel;Lorg/apache/http/conn/util/PublicSuffixMatcher;[Ljava/lang/String;Z)V
      10: return

  public org.apache.http.impl.cookie.DefaultCookieSpecProvider();
    Code:
       0: aload_0
       1: getstatic     #2                  // Field org/apache/http/impl/cookie/DefaultCookieSpecProvider$CompatibilityLevel.DEFAULT:Lorg/apache/http/impl/cookie/DefaultCookieSpecProvider$CompatibilityLevel;
       4: aconst_null
       5: aconst_null
       6: iconst_0
       7: invokespecial #7                  // Method "<init>":(Lorg/apache/http/impl/cookie/DefaultCookieSpecProvider$CompatibilityLevel;Lorg/apache/http/conn/util/PublicSuffixMatcher;[Ljava/lang/String;Z)V
      10: return

  public org.apache.http.cookie.CookieSpec create(org.apache.http.protocol.HttpContext);
    Code:
       0: aload_0
       1: getfield      #8                  // Field cookieSpec:Lorg/apache/http/cookie/CookieSpec;
       4: ifnonnull     368
       7: aload_0
       8: dup
       9: astore_2
      10: monitorenter
      11: aload_0
      12: getfield      #8                  // Field cookieSpec:Lorg/apache/http/cookie/CookieSpec;
      15: ifnonnull     356
      18: new           #9                  // class org/apache/http/impl/cookie/RFC2965Spec
      21: dup
      22: aload_0
      23: getfield      #6                  // Field oneHeader:Z
      26: bipush        9
      28: anewarray     #10                 // class org/apache/http/cookie/CommonCookieAttributeHandler
      31: dup
      32: iconst_0
      33: new           #11                 // class org/apache/http/impl/cookie/RFC2965VersionAttributeHandler
      36: dup
      37: invokespecial #12                 // Method org/apache/http/impl/cookie/RFC2965VersionAttributeHandler."<init>":()V
      40: aastore
      41: dup
      42: iconst_1
      43: new           #13                 // class org/apache/http/impl/cookie/BasicPathHandler
      46: dup
      47: invokespecial #14                 // Method org/apache/http/impl/cookie/BasicPathHandler."<init>":()V
      50: aastore
      51: dup
      52: iconst_2
      53: new           #15                 // class org/apache/http/impl/cookie/RFC2965DomainAttributeHandler
      56: dup
      57: invokespecial #16                 // Method org/apache/http/impl/cookie/RFC2965DomainAttributeHandler."<init>":()V
      60: aload_0
      61: getfield      #4                  // Field publicSuffixMatcher:Lorg/apache/http/conn/util/PublicSuffixMatcher;
      64: invokestatic  #17                 // Method org/apache/http/impl/cookie/PublicSuffixDomainFilter.decorate:(Lorg/apache/http/cookie/CommonCookieAttributeHandler;Lorg/apache/http/conn/util/PublicSuffixMatcher;)Lorg/apache/http/cookie/CommonCookieAttributeHandler;
      67: aastore
      68: dup
      69: iconst_3
      70: new           #18                 // class org/apache/http/impl/cookie/RFC2965PortAttributeHandler
      73: dup
      74: invokespecial #19                 // Method org/apache/http/impl/cookie/RFC2965PortAttributeHandler."<init>":()V
      77: aastore
      78: dup
      79: iconst_4
      80: new           #20                 // class org/apache/http/impl/cookie/BasicMaxAgeHandler
      83: dup
      84: invokespecial #21                 // Method org/apache/http/impl/cookie/BasicMaxAgeHandler."<init>":()V
      87: aastore
      88: dup
      89: iconst_5
      90: new           #22                 // class org/apache/http/impl/cookie/BasicSecureHandler
      93: dup
      94: invokespecial #23                 // Method org/apache/http/impl/cookie/BasicSecureHandler."<init>":()V
      97: aastore
      98: dup
      99: bipush        6
     101: new           #24                 // class org/apache/http/impl/cookie/BasicCommentHandler
     104: dup
     105: invokespecial #25                 // Method org/apache/http/impl/cookie/BasicCommentHandler."<init>":()V
     108: aastore
     109: dup
     110: bipush        7
     112: new           #26                 // class org/apache/http/impl/cookie/RFC2965CommentUrlAttributeHandler
     115: dup
     116: invokespecial #27                 // Method org/apache/http/impl/cookie/RFC2965CommentUrlAttributeHandler."<init>":()V
     119: aastore
     120: dup
     121: bipush        8
     123: new           #28                 // class org/apache/http/impl/cookie/RFC2965DiscardAttributeHandler
     126: dup
     127: invokespecial #29                 // Method org/apache/http/impl/cookie/RFC2965DiscardAttributeHandler."<init>":()V
     130: aastore
     131: invokespecial #30                 // Method org/apache/http/impl/cookie/RFC2965Spec."<init>":(Z[Lorg/apache/http/cookie/CommonCookieAttributeHandler;)V
     134: astore_3
     135: new           #31                 // class org/apache/http/impl/cookie/RFC2109Spec
     138: dup
     139: aload_0
     140: getfield      #6                  // Field oneHeader:Z
     143: bipush        6
     145: anewarray     #10                 // class org/apache/http/cookie/CommonCookieAttributeHandler
     148: dup
     149: iconst_0
     150: new           #32                 // class org/apache/http/impl/cookie/RFC2109VersionHandler
     153: dup
     154: invokespecial #33                 // Method org/apache/http/impl/cookie/RFC2109VersionHandler."<init>":()V
     157: aastore
     158: dup
     159: iconst_1
     160: new           #13                 // class org/apache/http/impl/cookie/BasicPathHandler
     163: dup
     164: invokespecial #14                 // Method org/apache/http/impl/cookie/BasicPathHandler."<init>":()V
     167: aastore
     168: dup
     169: iconst_2
     170: new           #34                 // class org/apache/http/impl/cookie/RFC2109DomainHandler
     173: dup
     174: invokespecial #35                 // Method org/apache/http/impl/cookie/RFC2109DomainHandler."<init>":()V
     177: aload_0
     178: getfield      #4                  // Field publicSuffixMatcher:Lorg/apache/http/conn/util/PublicSuffixMatcher;
     181: invokestatic  #17                 // Method org/apache/http/impl/cookie/PublicSuffixDomainFilter.decorate:(Lorg/apache/http/cookie/CommonCookieAttributeHandler;Lorg/apache/http/conn/util/PublicSuffixMatcher;)Lorg/apache/http/cookie/CommonCookieAttributeHandler;
     184: aastore
     185: dup
     186: iconst_3
     187: new           #20                 // class org/apache/http/impl/cookie/BasicMaxAgeHandler
     190: dup
     191: invokespecial #21                 // Method org/apache/http/impl/cookie/BasicMaxAgeHandler."<init>":()V
     194: aastore
     195: dup
     196: iconst_4
     197: new           #22                 // class org/apache/http/impl/cookie/BasicSecureHandler
     200: dup
     201: invokespecial #23                 // Method org/apache/http/impl/cookie/BasicSecureHandler."<init>":()V
     204: aastore
     205: dup
     206: iconst_5
     207: new           #24                 // class org/apache/http/impl/cookie/BasicCommentHandler
     210: dup
     211: invokespecial #25                 // Method org/apache/http/impl/cookie/BasicCommentHandler."<init>":()V
     214: aastore
     215: invokespecial #36                 // Method org/apache/http/impl/cookie/RFC2109Spec."<init>":(Z[Lorg/apache/http/cookie/CommonCookieAttributeHandler;)V
     218: astore        4
     220: new           #37                 // class org/apache/http/impl/cookie/NetscapeDraftSpec
     223: dup
     224: iconst_5
     225: anewarray     #10                 // class org/apache/http/cookie/CommonCookieAttributeHandler
     228: dup
     229: iconst_0
     230: new           #38                 // class org/apache/http/impl/cookie/BasicDomainHandler
     233: dup
     234: invokespecial #39                 // Method org/apache/http/impl/cookie/BasicDomainHandler."<init>":()V
     237: aload_0
     238: getfield      #4                  // Field publicSuffixMatcher:Lorg/apache/http/conn/util/PublicSuffixMatcher;
     241: invokestatic  #17                 // Method org/apache/http/impl/cookie/PublicSuffixDomainFilter.decorate:(Lorg/apache/http/cookie/CommonCookieAttributeHandler;Lorg/apache/http/conn/util/PublicSuffixMatcher;)Lorg/apache/http/cookie/CommonCookieAttributeHandler;
     244: aastore
     245: dup
     246: iconst_1
     247: aload_0
     248: getfield      #3                  // Field compatibilityLevel:Lorg/apache/http/impl/cookie/DefaultCookieSpecProvider$CompatibilityLevel;
     251: getstatic     #40                 // Field org/apache/http/impl/cookie/DefaultCookieSpecProvider$CompatibilityLevel.IE_MEDIUM_SECURITY:Lorg/apache/http/impl/cookie/DefaultCookieSpecProvider$CompatibilityLevel;
     254: if_acmpne     268
     257: new           #41                 // class org/apache/http/impl/cookie/DefaultCookieSpecProvider$1
     260: dup
     261: aload_0
     262: invokespecial #42                 // Method org/apache/http/impl/cookie/DefaultCookieSpecProvider$1."<init>":(Lorg/apache/http/impl/cookie/DefaultCookieSpecProvider;)V
     265: goto          275
     268: new           #13                 // class org/apache/http/impl/cookie/BasicPathHandler
     271: dup
     272: invokespecial #14                 // Method org/apache/http/impl/cookie/BasicPathHandler."<init>":()V
     275: aastore
     276: dup
     277: iconst_2
     278: new           #22                 // class org/apache/http/impl/cookie/BasicSecureHandler
     281: dup
     282: invokespecial #23                 // Method org/apache/http/impl/cookie/BasicSecureHandler."<init>":()V
     285: aastore
     286: dup
     287: iconst_3
     288: new           #24                 // class org/apache/http/impl/cookie/BasicCommentHandler
     291: dup
     292: invokespecial #25                 // Method org/apache/http/impl/cookie/BasicCommentHandler."<init>":()V
     295: aastore
     296: dup
     297: iconst_4
     298: new           #43                 // class org/apache/http/impl/cookie/BasicExpiresHandler
     301: dup
     302: aload_0
     303: getfield      #5                  // Field datepatterns:[Ljava/lang/String;
     306: ifnull        322
     309: aload_0
     310: getfield      #5                  // Field datepatterns:[Ljava/lang/String;
     313: invokevirtual #44                 // Method "[Ljava/lang/String;".clone:()Ljava/lang/Object;
     316: checkcast     #45                 // class "[Ljava/lang/String;"
     319: goto          331
     322: iconst_1
     323: anewarray     #46                 // class java/lang/String
     326: dup
     327: iconst_0
     328: ldc           #47                 // String EEE, dd-MMM-yy HH:mm:ss z
     330: aastore
     331: invokespecial #48                 // Method org/apache/http/impl/cookie/BasicExpiresHandler."<init>":([Ljava/lang/String;)V
     334: aastore
     335: invokespecial #49                 // Method org/apache/http/impl/cookie/NetscapeDraftSpec."<init>":([Lorg/apache/http/cookie/CommonCookieAttributeHandler;)V
     338: astore        5
     340: aload_0
     341: new           #50                 // class org/apache/http/impl/cookie/DefaultCookieSpec
     344: dup
     345: aload_3
     346: aload         4
     348: aload         5
     350: invokespecial #51                 // Method org/apache/http/impl/cookie/DefaultCookieSpec."<init>":(Lorg/apache/http/impl/cookie/RFC2965Spec;Lorg/apache/http/impl/cookie/RFC2109Spec;Lorg/apache/http/impl/cookie/NetscapeDraftSpec;)V
     353: putfield      #8                  // Field cookieSpec:Lorg/apache/http/cookie/CookieSpec;
     356: aload_2
     357: monitorexit
     358: goto          368
     361: astore        6
     363: aload_2
     364: monitorexit
     365: aload         6
     367: athrow
     368: aload_0
     369: getfield      #8                  // Field cookieSpec:Lorg/apache/http/cookie/CookieSpec;
     372: areturn
    Exception table:
       from    to  target type
          11   358   361   any
         361   365   361   any
}
