Compiled from "ConfigurationDynamicLoadProviderConsumer.java"
public interface org.wildfly.swarm.config.modcluster.mod_cluster_config.ConfigurationDynamicLoadProviderConsumer<T extends org.wildfly.swarm.config.modcluster.mod_cluster_config.ConfigurationDynamicLoadProvider<T>> {
  public abstract void accept(T);

  public default org.wildfly.swarm.config.modcluster.mod_cluster_config.ConfigurationDynamicLoadProviderConsumer<T> andThen(org.wildfly.swarm.config.modcluster.mod_cluster_config.ConfigurationDynamicLoadProviderConsumer<T>);
    Code:
       0: aload_0
       1: aload_1
       2: invokedynamic #1,  0              // InvokeDynamic #0:accept:(Lorg/wildfly/swarm/config/modcluster/mod_cluster_config/ConfigurationDynamicLoadProviderConsumer;Lorg/wildfly/swarm/config/modcluster/mod_cluster_config/ConfigurationDynamicLoadProviderConsumer;)Lorg/wildfly/swarm/config/modcluster/mod_cluster_config/ConfigurationDynamicLoadProviderConsumer;
       7: areturn

  private void lambda$andThen$39(org.wildfly.swarm.config.modcluster.mod_cluster_config.ConfigurationDynamicLoadProviderConsumer, org.wildfly.swarm.config.modcluster.mod_cluster_config.ConfigurationDynamicLoadProvider);
    Code:
       0: aload_0
       1: aload_2
       2: invokeinterface #2,  2            // InterfaceMethod accept:(Lorg/wildfly/swarm/config/modcluster/mod_cluster_config/ConfigurationDynamicLoadProvider;)V
       7: aload_1
       8: aload_2
       9: invokeinterface #2,  2            // InterfaceMethod accept:(Lorg/wildfly/swarm/config/modcluster/mod_cluster_config/ConfigurationDynamicLoadProvider;)V
      14: return
}
