Compiled from "CollectResult.java"
public class org.sonatype.aether.collection.CollectResult {
  private final org.sonatype.aether.collection.CollectRequest request;

  private final java.util.List<java.lang.Exception> exceptions;

  private org.sonatype.aether.graph.DependencyNode root;

  public org.sonatype.aether.collection.CollectResult(org.sonatype.aether.collection.CollectRequest);
    Code:
       0: aload_0
       1: invokespecial #1                  // Method java/lang/Object."<init>":()V
       4: aload_1
       5: ifnonnull     18
       8: new           #2                  // class java/lang/IllegalArgumentException
      11: dup
      12: ldc           #3                  // String dependency collection request has not been specified
      14: invokespecial #4                  // Method java/lang/IllegalArgumentException."<init>":(Ljava/lang/String;)V
      17: athrow
      18: aload_0
      19: aload_1
      20: putfield      #5                  // Field request:Lorg/sonatype/aether/collection/CollectRequest;
      23: aload_0
      24: new           #6                  // class java/util/ArrayList
      27: dup
      28: iconst_4
      29: invokespecial #7                  // Method java/util/ArrayList."<init>":(I)V
      32: putfield      #8                  // Field exceptions:Ljava/util/List;
      35: return

  public org.sonatype.aether.collection.CollectRequest getRequest();
    Code:
       0: aload_0
       1: getfield      #5                  // Field request:Lorg/sonatype/aether/collection/CollectRequest;
       4: areturn

  public java.util.List<java.lang.Exception> getExceptions();
    Code:
       0: aload_0
       1: getfield      #8                  // Field exceptions:Ljava/util/List;
       4: areturn

  public org.sonatype.aether.collection.CollectResult addException(java.lang.Exception);
    Code:
       0: aload_1
       1: ifnull        15
       4: aload_0
       5: getfield      #8                  // Field exceptions:Ljava/util/List;
       8: aload_1
       9: invokeinterface #9,  2            // InterfaceMethod java/util/List.add:(Ljava/lang/Object;)Z
      14: pop
      15: aload_0
      16: areturn

  public org.sonatype.aether.graph.DependencyNode getRoot();
    Code:
       0: aload_0
       1: getfield      #10                 // Field root:Lorg/sonatype/aether/graph/DependencyNode;
       4: areturn

  public org.sonatype.aether.collection.CollectResult setRoot(org.sonatype.aether.graph.DependencyNode);
    Code:
       0: aload_0
       1: aload_1
       2: putfield      #10                 // Field root:Lorg/sonatype/aether/graph/DependencyNode;
       5: aload_0
       6: areturn

  public java.lang.String toString();
    Code:
       0: aload_0
       1: invokevirtual #11                 // Method getRoot:()Lorg/sonatype/aether/graph/DependencyNode;
       4: invokestatic  #12                 // Method java/lang/String.valueOf:(Ljava/lang/Object;)Ljava/lang/String;
       7: areturn
}
