Compiled from "Expression.scala"
public final class wvlet.airframe.sql.model.Expression$$anon$1 implements scala.PartialFunction<wvlet.airframe.sql.model.Expression, scala.runtime.BoxedUnit> {
  private final scala.PartialFunction cond$1;

  private final scala.collection.mutable.Builder l$1;

  public wvlet.airframe.sql.model.Expression$$anon$1(scala.PartialFunction, scala.collection.mutable.Builder);
    Code:
       0: aload_0
       1: aload_1
       2: putfield      #25                 // Field cond$1:Lscala/PartialFunction;
       5: aload_0
       6: aload_2
       7: putfield      #27                 // Field l$1:Lscala/collection/mutable/Builder;
      10: aload_0
      11: invokespecial #30                 // Method java/lang/Object."<init>":()V
      14: aload_0
      15: invokestatic  #34                 // InterfaceMethod scala/PartialFunction.$init$:(Lscala/PartialFunction;)V
      18: return

  public scala.Function1 compose(scala.Function1);
    Code:
       0: aload_0
       1: aload_1
       2: invokestatic  #43                 // InterfaceMethod scala/Function1.compose$:(Lscala/Function1;Lscala/Function1;)Lscala/Function1;
       5: areturn

  public java.lang.String toString();
    Code:
       0: aload_0
       1: invokestatic  #50                 // InterfaceMethod scala/Function1.toString$:(Lscala/Function1;)Ljava/lang/String;
       4: areturn

  public boolean apply$mcZI$sp(int);
    Code:
       0: aload_0
       1: iload_1
       2: invokestatic  #57                 // InterfaceMethod scala/Function1.apply$mcZI$sp$:(Lscala/Function1;I)Z
       5: ireturn

  public boolean apply$mcZJ$sp(long);
    Code:
       0: aload_0
       1: lload_1
       2: invokestatic  #64                 // InterfaceMethod scala/Function1.apply$mcZJ$sp$:(Lscala/Function1;J)Z
       5: ireturn

  public boolean apply$mcZF$sp(float);
    Code:
       0: aload_0
       1: fload_1
       2: invokestatic  #71                 // InterfaceMethod scala/Function1.apply$mcZF$sp$:(Lscala/Function1;F)Z
       5: ireturn

  public boolean apply$mcZD$sp(double);
    Code:
       0: aload_0
       1: dload_1
       2: invokestatic  #78                 // InterfaceMethod scala/Function1.apply$mcZD$sp$:(Lscala/Function1;D)Z
       5: ireturn

  public int apply$mcII$sp(int);
    Code:
       0: aload_0
       1: iload_1
       2: invokestatic  #85                 // InterfaceMethod scala/Function1.apply$mcII$sp$:(Lscala/Function1;I)I
       5: ireturn

  public int apply$mcIJ$sp(long);
    Code:
       0: aload_0
       1: lload_1
       2: invokestatic  #91                 // InterfaceMethod scala/Function1.apply$mcIJ$sp$:(Lscala/Function1;J)I
       5: ireturn

  public int apply$mcIF$sp(float);
    Code:
       0: aload_0
       1: fload_1
       2: invokestatic  #97                 // InterfaceMethod scala/Function1.apply$mcIF$sp$:(Lscala/Function1;F)I
       5: ireturn

  public int apply$mcID$sp(double);
    Code:
       0: aload_0
       1: dload_1
       2: invokestatic  #103                // InterfaceMethod scala/Function1.apply$mcID$sp$:(Lscala/Function1;D)I
       5: ireturn

  public double apply$mcDI$sp(int);
    Code:
       0: aload_0
       1: iload_1
       2: invokestatic  #109                // InterfaceMethod scala/Function1.apply$mcDI$sp$:(Lscala/Function1;I)D
       5: dreturn

  public double apply$mcDJ$sp(long);
    Code:
       0: aload_0
       1: lload_1
       2: invokestatic  #115                // InterfaceMethod scala/Function1.apply$mcDJ$sp$:(Lscala/Function1;J)D
       5: dreturn

  public double apply$mcDF$sp(float);
    Code:
       0: aload_0
       1: fload_1
       2: invokestatic  #121                // InterfaceMethod scala/Function1.apply$mcDF$sp$:(Lscala/Function1;F)D
       5: dreturn

  public double apply$mcDD$sp(double);
    Code:
       0: aload_0
       1: dload_1
       2: invokestatic  #127                // InterfaceMethod scala/Function1.apply$mcDD$sp$:(Lscala/Function1;D)D
       5: dreturn

  public long apply$mcJI$sp(int);
    Code:
       0: aload_0
       1: iload_1
       2: invokestatic  #133                // InterfaceMethod scala/Function1.apply$mcJI$sp$:(Lscala/Function1;I)J
       5: lreturn

  public long apply$mcJJ$sp(long);
    Code:
       0: aload_0
       1: lload_1
       2: invokestatic  #139                // InterfaceMethod scala/Function1.apply$mcJJ$sp$:(Lscala/Function1;J)J
       5: lreturn

  public long apply$mcJF$sp(float);
    Code:
       0: aload_0
       1: fload_1
       2: invokestatic  #145                // InterfaceMethod scala/Function1.apply$mcJF$sp$:(Lscala/Function1;F)J
       5: lreturn

  public long apply$mcJD$sp(double);
    Code:
       0: aload_0
       1: dload_1
       2: invokestatic  #151                // InterfaceMethod scala/Function1.apply$mcJD$sp$:(Lscala/Function1;D)J
       5: lreturn

  public float apply$mcFI$sp(int);
    Code:
       0: aload_0
       1: iload_1
       2: invokestatic  #157                // InterfaceMethod scala/Function1.apply$mcFI$sp$:(Lscala/Function1;I)F
       5: freturn

  public float apply$mcFJ$sp(long);
    Code:
       0: aload_0
       1: lload_1
       2: invokestatic  #163                // InterfaceMethod scala/Function1.apply$mcFJ$sp$:(Lscala/Function1;J)F
       5: freturn

  public float apply$mcFF$sp(float);
    Code:
       0: aload_0
       1: fload_1
       2: invokestatic  #169                // InterfaceMethod scala/Function1.apply$mcFF$sp$:(Lscala/Function1;F)F
       5: freturn

  public float apply$mcFD$sp(double);
    Code:
       0: aload_0
       1: dload_1
       2: invokestatic  #175                // InterfaceMethod scala/Function1.apply$mcFD$sp$:(Lscala/Function1;D)F
       5: freturn

  public void apply$mcVI$sp(int);
    Code:
       0: aload_0
       1: iload_1
       2: invokestatic  #181                // InterfaceMethod scala/Function1.apply$mcVI$sp$:(Lscala/Function1;I)V
       5: return

  public void apply$mcVJ$sp(long);
    Code:
       0: aload_0
       1: lload_1
       2: invokestatic  #187                // InterfaceMethod scala/Function1.apply$mcVJ$sp$:(Lscala/Function1;J)V
       5: return

  public void apply$mcVF$sp(float);
    Code:
       0: aload_0
       1: fload_1
       2: invokestatic  #193                // InterfaceMethod scala/Function1.apply$mcVF$sp$:(Lscala/Function1;F)V
       5: return

  public void apply$mcVD$sp(double);
    Code:
       0: aload_0
       1: dload_1
       2: invokestatic  #199                // InterfaceMethod scala/Function1.apply$mcVD$sp$:(Lscala/Function1;D)V
       5: return

  public scala.Option unapply(java.lang.Object);
    Code:
       0: aload_0
       1: aload_1
       2: invokestatic  #206                // InterfaceMethod scala/PartialFunction.unapply$:(Lscala/PartialFunction;Ljava/lang/Object;)Lscala/Option;
       5: areturn

  public scala.PartialFunction elementWise();
    Code:
       0: aload_0
       1: invokestatic  #213                // InterfaceMethod scala/PartialFunction.elementWise$:(Lscala/PartialFunction;)Lscala/PartialFunction;
       4: areturn

  public scala.PartialFunction orElse(scala.PartialFunction);
    Code:
       0: aload_0
       1: aload_1
       2: invokestatic  #219                // InterfaceMethod scala/PartialFunction.orElse$:(Lscala/PartialFunction;Lscala/PartialFunction;)Lscala/PartialFunction;
       5: areturn

  public scala.PartialFunction andThen(scala.Function1);
    Code:
       0: aload_0
       1: aload_1
       2: invokestatic  #226                // InterfaceMethod scala/PartialFunction.andThen$:(Lscala/PartialFunction;Lscala/Function1;)Lscala/PartialFunction;
       5: areturn

  public scala.PartialFunction andThen(scala.PartialFunction);
    Code:
       0: aload_0
       1: aload_1
       2: invokestatic  #228                // InterfaceMethod scala/PartialFunction.andThen$:(Lscala/PartialFunction;Lscala/PartialFunction;)Lscala/PartialFunction;
       5: areturn

  public scala.PartialFunction compose(scala.PartialFunction);
    Code:
       0: aload_0
       1: aload_1
       2: invokestatic  #230                // InterfaceMethod scala/PartialFunction.compose$:(Lscala/PartialFunction;Lscala/PartialFunction;)Lscala/PartialFunction;
       5: areturn

  public scala.Function1 lift();
    Code:
       0: aload_0
       1: invokestatic  #236                // InterfaceMethod scala/PartialFunction.lift$:(Lscala/PartialFunction;)Lscala/Function1;
       4: areturn

  public java.lang.Object applyOrElse(java.lang.Object, scala.Function1);
    Code:
       0: aload_0
       1: aload_1
       2: aload_2
       3: invokestatic  #244                // InterfaceMethod scala/PartialFunction.applyOrElse$:(Lscala/PartialFunction;Ljava/lang/Object;Lscala/Function1;)Ljava/lang/Object;
       6: areturn

  public scala.Function1 runWith(scala.Function1);
    Code:
       0: aload_0
       1: aload_1
       2: invokestatic  #250                // InterfaceMethod scala/PartialFunction.runWith$:(Lscala/PartialFunction;Lscala/Function1;)Lscala/Function1;
       5: areturn

  public boolean isDefinedAt(wvlet.airframe.sql.model.Expression);
    Code:
       0: aload_0
       1: getfield      #25                 // Field cond$1:Lscala/PartialFunction;
       4: aload_1
       5: invokeinterface #255,  2          // InterfaceMethod scala/PartialFunction.isDefinedAt:(Ljava/lang/Object;)Z
      10: ireturn

  public void apply(wvlet.airframe.sql.model.Expression);
    Code:
       0: aload_0
       1: getfield      #25                 // Field cond$1:Lscala/PartialFunction;
       4: aload_1
       5: invokeinterface #262,  2          // InterfaceMethod scala/PartialFunction.apply:(Ljava/lang/Object;)Ljava/lang/Object;
      10: invokestatic  #267                // Method scala/runtime/BoxesRunTime.unboxToBoolean:(Ljava/lang/Object;)Z
      13: ifeq          28
      16: aload_0
      17: getfield      #27                 // Field l$1:Lscala/collection/mutable/Builder;
      20: aload_1
      21: invokeinterface #273,  2          // InterfaceMethod scala/collection/mutable/Builder.$plus$eq:(Ljava/lang/Object;)Lscala/collection/mutable/Growable;
      26: pop
      27: return
      28: return

  public boolean isDefinedAt(java.lang.Object);
    Code:
       0: aload_0
       1: aload_1
       2: checkcast     #12                 // class wvlet/airframe/sql/model/Expression
       5: invokevirtual #275                // Method isDefinedAt:(Lwvlet/airframe/sql/model/Expression;)Z
       8: ireturn

  public java.lang.Object apply(java.lang.Object);
    Code:
       0: aload_0
       1: aload_1
       2: checkcast     #12                 // class wvlet/airframe/sql/model/Expression
       5: invokevirtual #277                // Method apply:(Lwvlet/airframe/sql/model/Expression;)V
       8: getstatic     #283                // Field scala/runtime/BoxedUnit.UNIT:Lscala/runtime/BoxedUnit;
      11: areturn

  public scala.Function1 andThen(scala.Function1);
    Code:
       0: aload_0
       1: aload_1
       2: invokevirtual #285                // Method andThen:(Lscala/Function1;)Lscala/PartialFunction;
       5: areturn
}
