Compiled from "RedisAbstractConfig.java"
public final class org.apache.pulsar.io.redis.RedisAbstractConfig$ClientMode extends java.lang.Enum<org.apache.pulsar.io.redis.RedisAbstractConfig$ClientMode> {
  public static final org.apache.pulsar.io.redis.RedisAbstractConfig$ClientMode STANDALONE;

  public static final org.apache.pulsar.io.redis.RedisAbstractConfig$ClientMode CLUSTER;

  private static final org.apache.pulsar.io.redis.RedisAbstractConfig$ClientMode[] $VALUES;

  public static org.apache.pulsar.io.redis.RedisAbstractConfig$ClientMode[] values();
    Code:
       0: getstatic     #1                  // Field $VALUES:[Lorg/apache/pulsar/io/redis/RedisAbstractConfig$ClientMode;
       3: invokevirtual #2                  // Method "[Lorg/apache/pulsar/io/redis/RedisAbstractConfig$ClientMode;".clone:()Ljava/lang/Object;
       6: checkcast     #3                  // class "[Lorg/apache/pulsar/io/redis/RedisAbstractConfig$ClientMode;"
       9: areturn

  public static org.apache.pulsar.io.redis.RedisAbstractConfig$ClientMode valueOf(java.lang.String);
    Code:
       0: ldc           #4                  // class org/apache/pulsar/io/redis/RedisAbstractConfig$ClientMode
       2: aload_0
       3: invokestatic  #5                  // Method java/lang/Enum.valueOf:(Ljava/lang/Class;Ljava/lang/String;)Ljava/lang/Enum;
       6: checkcast     #4                  // class org/apache/pulsar/io/redis/RedisAbstractConfig$ClientMode
       9: areturn

  private org.apache.pulsar.io.redis.RedisAbstractConfig$ClientMode();
    Code:
       0: aload_0
       1: aload_1
       2: iload_2
       3: invokespecial #6                  // Method java/lang/Enum."<init>":(Ljava/lang/String;I)V
       6: return

  static {};
    Code:
       0: new           #4                  // class org/apache/pulsar/io/redis/RedisAbstractConfig$ClientMode
       3: dup
       4: ldc           #7                  // String STANDALONE
       6: iconst_0
       7: invokespecial #8                  // Method "<init>":(Ljava/lang/String;I)V
      10: putstatic     #9                  // Field STANDALONE:Lorg/apache/pulsar/io/redis/RedisAbstractConfig$ClientMode;
      13: new           #4                  // class org/apache/pulsar/io/redis/RedisAbstractConfig$ClientMode
      16: dup
      17: ldc           #10                 // String CLUSTER
      19: iconst_1
      20: invokespecial #8                  // Method "<init>":(Ljava/lang/String;I)V
      23: putstatic     #11                 // Field CLUSTER:Lorg/apache/pulsar/io/redis/RedisAbstractConfig$ClientMode;
      26: iconst_2
      27: anewarray     #4                  // class org/apache/pulsar/io/redis/RedisAbstractConfig$ClientMode
      30: dup
      31: iconst_0
      32: getstatic     #9                  // Field STANDALONE:Lorg/apache/pulsar/io/redis/RedisAbstractConfig$ClientMode;
      35: aastore
      36: dup
      37: iconst_1
      38: getstatic     #11                 // Field CLUSTER:Lorg/apache/pulsar/io/redis/RedisAbstractConfig$ClientMode;
      41: aastore
      42: putstatic     #1                  // Field $VALUES:[Lorg/apache/pulsar/io/redis/RedisAbstractConfig$ClientMode;
      45: return
}
