Compiled from "ResourceConfigClass.java"
public class org.smallmind.web.jersey.spring.ResourceConfigClass extends org.smallmind.web.jersey.spring.ResourceConfigExtension {
  java.lang.Class<?> value;

  public org.smallmind.web.jersey.spring.ResourceConfigClass();
    Code:
       0: aload_0
       1: invokespecial #12                 // Method org/smallmind/web/jersey/spring/ResourceConfigExtension."<init>":()V
       4: return

  public java.lang.Class<?> getValue();
    Code:
       0: aload_0
       1: getfield      #22                 // Field value:Ljava/lang/Class;
       4: areturn

  public void setValue(java.lang.Class<?>);
    Code:
       0: aload_0
       1: aload_1
       2: putfield      #22                 // Field value:Ljava/lang/Class;
       5: return

  public void apply(org.glassfish.jersey.server.ResourceConfig);
    Code:
       0: aload_1
       1: aload_0
       2: getfield      #22                 // Field value:Ljava/lang/Class;
       5: invokevirtual #30                 // Method org/glassfish/jersey/server/ResourceConfig.register:(Ljava/lang/Class;)Lorg/glassfish/jersey/server/ResourceConfig;
       8: pop
       9: return
}
