Compiled from "PolicyV1beta1AllowedHostPathFluentImpl.java"
public class io.kubernetes.client.openapi.models.PolicyV1beta1AllowedHostPathFluentImpl<A extends io.kubernetes.client.openapi.models.PolicyV1beta1AllowedHostPathFluent<A>> extends io.kubernetes.client.fluent.BaseFluent<A> implements io.kubernetes.client.openapi.models.PolicyV1beta1AllowedHostPathFluent<A> {
  private java.lang.String pathPrefix;

  private java.lang.Boolean readOnly;

  public io.kubernetes.client.openapi.models.PolicyV1beta1AllowedHostPathFluentImpl();
    Code:
       0: aload_0
       1: invokespecial #1                  // Method io/kubernetes/client/fluent/BaseFluent."<init>":()V
       4: return

  public io.kubernetes.client.openapi.models.PolicyV1beta1AllowedHostPathFluentImpl(io.kubernetes.client.openapi.models.PolicyV1beta1AllowedHostPath);
    Code:
       0: aload_0
       1: invokespecial #1                  // Method io/kubernetes/client/fluent/BaseFluent."<init>":()V
       4: aload_0
       5: aload_1
       6: invokevirtual #2                  // Method io/kubernetes/client/openapi/models/PolicyV1beta1AllowedHostPath.getPathPrefix:()Ljava/lang/String;
       9: invokevirtual #3                  // Method withPathPrefix:(Ljava/lang/String;)Lio/kubernetes/client/openapi/models/PolicyV1beta1AllowedHostPathFluent;
      12: pop
      13: aload_0
      14: aload_1
      15: invokevirtual #4                  // Method io/kubernetes/client/openapi/models/PolicyV1beta1AllowedHostPath.getReadOnly:()Ljava/lang/Boolean;
      18: invokevirtual #5                  // Method withReadOnly:(Ljava/lang/Boolean;)Lio/kubernetes/client/openapi/models/PolicyV1beta1AllowedHostPathFluent;
      21: pop
      22: return

  public java.lang.String getPathPrefix();
    Code:
       0: aload_0
       1: getfield      #6                  // Field pathPrefix:Ljava/lang/String;
       4: areturn

  public A withPathPrefix(java.lang.String);
    Code:
       0: aload_0
       1: aload_1
       2: putfield      #6                  // Field pathPrefix:Ljava/lang/String;
       5: aload_0
       6: areturn

  public java.lang.Boolean hasPathPrefix();
    Code:
       0: aload_0
       1: getfield      #6                  // Field pathPrefix:Ljava/lang/String;
       4: ifnull        11
       7: iconst_1
       8: goto          12
      11: iconst_0
      12: invokestatic  #7                  // Method java/lang/Boolean.valueOf:(Z)Ljava/lang/Boolean;
      15: areturn

  public A withNewPathPrefix(java.lang.String);
    Code:
       0: aload_0
       1: new           #8                  // class java/lang/String
       4: dup
       5: aload_1
       6: invokespecial #9                  // Method java/lang/String."<init>":(Ljava/lang/String;)V
       9: invokevirtual #3                  // Method withPathPrefix:(Ljava/lang/String;)Lio/kubernetes/client/openapi/models/PolicyV1beta1AllowedHostPathFluent;
      12: areturn

  public A withNewPathPrefix(java.lang.StringBuilder);
    Code:
       0: aload_0
       1: new           #8                  // class java/lang/String
       4: dup
       5: aload_1
       6: invokespecial #10                 // Method java/lang/String."<init>":(Ljava/lang/StringBuilder;)V
       9: invokevirtual #3                  // Method withPathPrefix:(Ljava/lang/String;)Lio/kubernetes/client/openapi/models/PolicyV1beta1AllowedHostPathFluent;
      12: areturn

  public A withNewPathPrefix(java.lang.StringBuffer);
    Code:
       0: aload_0
       1: new           #8                  // class java/lang/String
       4: dup
       5: aload_1
       6: invokespecial #11                 // Method java/lang/String."<init>":(Ljava/lang/StringBuffer;)V
       9: invokevirtual #3                  // Method withPathPrefix:(Ljava/lang/String;)Lio/kubernetes/client/openapi/models/PolicyV1beta1AllowedHostPathFluent;
      12: areturn

  public java.lang.Boolean isReadOnly();
    Code:
       0: aload_0
       1: getfield      #12                 // Field readOnly:Ljava/lang/Boolean;
       4: areturn

  public A withReadOnly(java.lang.Boolean);
    Code:
       0: aload_0
       1: aload_1
       2: putfield      #12                 // Field readOnly:Ljava/lang/Boolean;
       5: aload_0
       6: areturn

  public java.lang.Boolean hasReadOnly();
    Code:
       0: aload_0
       1: getfield      #12                 // Field readOnly:Ljava/lang/Boolean;
       4: ifnull        11
       7: iconst_1
       8: goto          12
      11: iconst_0
      12: invokestatic  #7                  // Method java/lang/Boolean.valueOf:(Z)Ljava/lang/Boolean;
      15: areturn

  public A withNewReadOnly(java.lang.String);
    Code:
       0: aload_0
       1: new           #13                 // class java/lang/Boolean
       4: dup
       5: aload_1
       6: invokespecial #14                 // Method java/lang/Boolean."<init>":(Ljava/lang/String;)V
       9: invokevirtual #5                  // Method withReadOnly:(Ljava/lang/Boolean;)Lio/kubernetes/client/openapi/models/PolicyV1beta1AllowedHostPathFluent;
      12: areturn

  public A withNewReadOnly(boolean);
    Code:
       0: aload_0
       1: new           #13                 // class java/lang/Boolean
       4: dup
       5: iload_1
       6: invokespecial #15                 // Method java/lang/Boolean."<init>":(Z)V
       9: invokevirtual #5                  // Method withReadOnly:(Ljava/lang/Boolean;)Lio/kubernetes/client/openapi/models/PolicyV1beta1AllowedHostPathFluent;
      12: areturn

  public boolean equals(java.lang.Object);
    Code:
       0: aload_0
       1: aload_1
       2: if_acmpne     7
       5: iconst_1
       6: ireturn
       7: aload_1
       8: ifnull        22
      11: aload_0
      12: invokevirtual #16                 // Method java/lang/Object.getClass:()Ljava/lang/Class;
      15: aload_1
      16: invokevirtual #16                 // Method java/lang/Object.getClass:()Ljava/lang/Class;
      19: if_acmpeq     24
      22: iconst_0
      23: ireturn
      24: aload_1
      25: checkcast     #17                 // class io/kubernetes/client/openapi/models/PolicyV1beta1AllowedHostPathFluentImpl
      28: astore_2
      29: aload_0
      30: getfield      #6                  // Field pathPrefix:Ljava/lang/String;
      33: ifnull        53
      36: aload_0
      37: getfield      #6                  // Field pathPrefix:Ljava/lang/String;
      40: aload_2
      41: getfield      #6                  // Field pathPrefix:Ljava/lang/String;
      44: invokevirtual #18                 // Method java/lang/String.equals:(Ljava/lang/Object;)Z
      47: ifne          62
      50: goto          60
      53: aload_2
      54: getfield      #6                  // Field pathPrefix:Ljava/lang/String;
      57: ifnull        62
      60: iconst_0
      61: ireturn
      62: aload_0
      63: getfield      #12                 // Field readOnly:Ljava/lang/Boolean;
      66: ifnull        86
      69: aload_0
      70: getfield      #12                 // Field readOnly:Ljava/lang/Boolean;
      73: aload_2
      74: getfield      #12                 // Field readOnly:Ljava/lang/Boolean;
      77: invokevirtual #19                 // Method java/lang/Boolean.equals:(Ljava/lang/Object;)Z
      80: ifne          95
      83: goto          93
      86: aload_2
      87: getfield      #12                 // Field readOnly:Ljava/lang/Boolean;
      90: ifnull        95
      93: iconst_0
      94: ireturn
      95: iconst_1
      96: ireturn
}
