Compiled from "V1alpha1WebhookFluentImpl.java"
public class io.kubernetes.client.openapi.models.V1alpha1WebhookFluentImpl$ThrottleNestedImpl<N> extends io.kubernetes.client.openapi.models.V1alpha1WebhookThrottleConfigFluentImpl<io.kubernetes.client.openapi.models.V1alpha1WebhookFluent$ThrottleNested<N>> implements io.kubernetes.client.openapi.models.V1alpha1WebhookFluent$ThrottleNested<N>, io.kubernetes.client.fluent.Nested<N> {
  private final io.kubernetes.client.openapi.models.V1alpha1WebhookThrottleConfigBuilder builder;

  final io.kubernetes.client.openapi.models.V1alpha1WebhookFluentImpl this$0;

  io.kubernetes.client.openapi.models.V1alpha1WebhookFluentImpl$ThrottleNestedImpl(io.kubernetes.client.openapi.models.V1alpha1WebhookFluentImpl, io.kubernetes.client.openapi.models.V1alpha1WebhookThrottleConfig);
    Code:
       0: aload_0
       1: aload_1
       2: putfield      #1                  // Field this$0:Lio/kubernetes/client/openapi/models/V1alpha1WebhookFluentImpl;
       5: aload_0
       6: invokespecial #2                  // Method io/kubernetes/client/openapi/models/V1alpha1WebhookThrottleConfigFluentImpl."<init>":()V
       9: aload_0
      10: new           #3                  // class io/kubernetes/client/openapi/models/V1alpha1WebhookThrottleConfigBuilder
      13: dup
      14: aload_0
      15: aload_2
      16: invokespecial #4                  // Method io/kubernetes/client/openapi/models/V1alpha1WebhookThrottleConfigBuilder."<init>":(Lio/kubernetes/client/openapi/models/V1alpha1WebhookThrottleConfigFluent;Lio/kubernetes/client/openapi/models/V1alpha1WebhookThrottleConfig;)V
      19: putfield      #5                  // Field builder:Lio/kubernetes/client/openapi/models/V1alpha1WebhookThrottleConfigBuilder;
      22: return

  io.kubernetes.client.openapi.models.V1alpha1WebhookFluentImpl$ThrottleNestedImpl(io.kubernetes.client.openapi.models.V1alpha1WebhookFluentImpl);
    Code:
       0: aload_0
       1: aload_1
       2: putfield      #1                  // Field this$0:Lio/kubernetes/client/openapi/models/V1alpha1WebhookFluentImpl;
       5: aload_0
       6: invokespecial #2                  // Method io/kubernetes/client/openapi/models/V1alpha1WebhookThrottleConfigFluentImpl."<init>":()V
       9: aload_0
      10: new           #3                  // class io/kubernetes/client/openapi/models/V1alpha1WebhookThrottleConfigBuilder
      13: dup
      14: aload_0
      15: invokespecial #6                  // Method io/kubernetes/client/openapi/models/V1alpha1WebhookThrottleConfigBuilder."<init>":(Lio/kubernetes/client/openapi/models/V1alpha1WebhookThrottleConfigFluent;)V
      18: putfield      #5                  // Field builder:Lio/kubernetes/client/openapi/models/V1alpha1WebhookThrottleConfigBuilder;
      21: return

  public N and();
    Code:
       0: aload_0
       1: getfield      #1                  // Field this$0:Lio/kubernetes/client/openapi/models/V1alpha1WebhookFluentImpl;
       4: aload_0
       5: getfield      #5                  // Field builder:Lio/kubernetes/client/openapi/models/V1alpha1WebhookThrottleConfigBuilder;
       8: invokevirtual #7                  // Method io/kubernetes/client/openapi/models/V1alpha1WebhookThrottleConfigBuilder.build:()Lio/kubernetes/client/openapi/models/V1alpha1WebhookThrottleConfig;
      11: invokevirtual #8                  // Method io/kubernetes/client/openapi/models/V1alpha1WebhookFluentImpl.withThrottle:(Lio/kubernetes/client/openapi/models/V1alpha1WebhookThrottleConfig;)Lio/kubernetes/client/openapi/models/V1alpha1WebhookFluent;
      14: areturn

  public N endThrottle();
    Code:
       0: aload_0
       1: invokevirtual #9                  // Method and:()Ljava/lang/Object;
       4: areturn
}
