Compiled from "V1beta1CustomResourceDefinitionFluentImpl.java"
public class io.kubernetes.client.openapi.models.V1beta1CustomResourceDefinitionFluentImpl$SpecNestedImpl<N> extends io.kubernetes.client.openapi.models.V1beta1CustomResourceDefinitionSpecFluentImpl<io.kubernetes.client.openapi.models.V1beta1CustomResourceDefinitionFluent$SpecNested<N>> implements io.kubernetes.client.openapi.models.V1beta1CustomResourceDefinitionFluent$SpecNested<N>, io.kubernetes.client.fluent.Nested<N> {
  private final io.kubernetes.client.openapi.models.V1beta1CustomResourceDefinitionSpecBuilder builder;

  final io.kubernetes.client.openapi.models.V1beta1CustomResourceDefinitionFluentImpl this$0;

  io.kubernetes.client.openapi.models.V1beta1CustomResourceDefinitionFluentImpl$SpecNestedImpl(io.kubernetes.client.openapi.models.V1beta1CustomResourceDefinitionFluentImpl, io.kubernetes.client.openapi.models.V1beta1CustomResourceDefinitionSpec);
    Code:
       0: aload_0
       1: aload_1
       2: putfield      #1                  // Field this$0:Lio/kubernetes/client/openapi/models/V1beta1CustomResourceDefinitionFluentImpl;
       5: aload_0
       6: invokespecial #2                  // Method io/kubernetes/client/openapi/models/V1beta1CustomResourceDefinitionSpecFluentImpl."<init>":()V
       9: aload_0
      10: new           #3                  // class io/kubernetes/client/openapi/models/V1beta1CustomResourceDefinitionSpecBuilder
      13: dup
      14: aload_0
      15: aload_2
      16: invokespecial #4                  // Method io/kubernetes/client/openapi/models/V1beta1CustomResourceDefinitionSpecBuilder."<init>":(Lio/kubernetes/client/openapi/models/V1beta1CustomResourceDefinitionSpecFluent;Lio/kubernetes/client/openapi/models/V1beta1CustomResourceDefinitionSpec;)V
      19: putfield      #5                  // Field builder:Lio/kubernetes/client/openapi/models/V1beta1CustomResourceDefinitionSpecBuilder;
      22: return

  io.kubernetes.client.openapi.models.V1beta1CustomResourceDefinitionFluentImpl$SpecNestedImpl(io.kubernetes.client.openapi.models.V1beta1CustomResourceDefinitionFluentImpl);
    Code:
       0: aload_0
       1: aload_1
       2: putfield      #1                  // Field this$0:Lio/kubernetes/client/openapi/models/V1beta1CustomResourceDefinitionFluentImpl;
       5: aload_0
       6: invokespecial #2                  // Method io/kubernetes/client/openapi/models/V1beta1CustomResourceDefinitionSpecFluentImpl."<init>":()V
       9: aload_0
      10: new           #3                  // class io/kubernetes/client/openapi/models/V1beta1CustomResourceDefinitionSpecBuilder
      13: dup
      14: aload_0
      15: invokespecial #6                  // Method io/kubernetes/client/openapi/models/V1beta1CustomResourceDefinitionSpecBuilder."<init>":(Lio/kubernetes/client/openapi/models/V1beta1CustomResourceDefinitionSpecFluent;)V
      18: putfield      #5                  // Field builder:Lio/kubernetes/client/openapi/models/V1beta1CustomResourceDefinitionSpecBuilder;
      21: return

  public N and();
    Code:
       0: aload_0
       1: getfield      #1                  // Field this$0:Lio/kubernetes/client/openapi/models/V1beta1CustomResourceDefinitionFluentImpl;
       4: aload_0
       5: getfield      #5                  // Field builder:Lio/kubernetes/client/openapi/models/V1beta1CustomResourceDefinitionSpecBuilder;
       8: invokevirtual #7                  // Method io/kubernetes/client/openapi/models/V1beta1CustomResourceDefinitionSpecBuilder.build:()Lio/kubernetes/client/openapi/models/V1beta1CustomResourceDefinitionSpec;
      11: invokevirtual #8                  // Method io/kubernetes/client/openapi/models/V1beta1CustomResourceDefinitionFluentImpl.withSpec:(Lio/kubernetes/client/openapi/models/V1beta1CustomResourceDefinitionSpec;)Lio/kubernetes/client/openapi/models/V1beta1CustomResourceDefinitionFluent;
      14: areturn

  public N endSpec();
    Code:
       0: aload_0
       1: invokevirtual #9                  // Method and:()Ljava/lang/Object;
       4: areturn
}
