Compiled from "V1beta1CustomResourceDefinitionVersionBuilder.java"
public class io.kubernetes.client.openapi.models.V1beta1CustomResourceDefinitionVersionBuilder extends io.kubernetes.client.openapi.models.V1beta1CustomResourceDefinitionVersionFluentImpl<io.kubernetes.client.openapi.models.V1beta1CustomResourceDefinitionVersionBuilder> implements io.kubernetes.client.fluent.VisitableBuilder<io.kubernetes.client.openapi.models.V1beta1CustomResourceDefinitionVersion, io.kubernetes.client.openapi.models.V1beta1CustomResourceDefinitionVersionBuilder> {
  io.kubernetes.client.openapi.models.V1beta1CustomResourceDefinitionVersionFluent<?> fluent;

  java.lang.Boolean validationEnabled;

  public io.kubernetes.client.openapi.models.V1beta1CustomResourceDefinitionVersionBuilder();
    Code:
       0: aload_0
       1: iconst_1
       2: invokestatic  #1                  // Method java/lang/Boolean.valueOf:(Z)Ljava/lang/Boolean;
       5: invokespecial #2                  // Method "<init>":(Ljava/lang/Boolean;)V
       8: return

  public io.kubernetes.client.openapi.models.V1beta1CustomResourceDefinitionVersionBuilder(java.lang.Boolean);
    Code:
       0: aload_0
       1: new           #3                  // class io/kubernetes/client/openapi/models/V1beta1CustomResourceDefinitionVersion
       4: dup
       5: invokespecial #4                  // Method io/kubernetes/client/openapi/models/V1beta1CustomResourceDefinitionVersion."<init>":()V
       8: aload_1
       9: invokespecial #5                  // Method "<init>":(Lio/kubernetes/client/openapi/models/V1beta1CustomResourceDefinitionVersion;Ljava/lang/Boolean;)V
      12: return

  public io.kubernetes.client.openapi.models.V1beta1CustomResourceDefinitionVersionBuilder(io.kubernetes.client.openapi.models.V1beta1CustomResourceDefinitionVersionFluent<?>);
    Code:
       0: aload_0
       1: aload_1
       2: iconst_1
       3: invokestatic  #1                  // Method java/lang/Boolean.valueOf:(Z)Ljava/lang/Boolean;
       6: invokespecial #6                  // Method "<init>":(Lio/kubernetes/client/openapi/models/V1beta1CustomResourceDefinitionVersionFluent;Ljava/lang/Boolean;)V
       9: return

  public io.kubernetes.client.openapi.models.V1beta1CustomResourceDefinitionVersionBuilder(io.kubernetes.client.openapi.models.V1beta1CustomResourceDefinitionVersionFluent<?>, java.lang.Boolean);
    Code:
       0: aload_0
       1: aload_1
       2: new           #3                  // class io/kubernetes/client/openapi/models/V1beta1CustomResourceDefinitionVersion
       5: dup
       6: invokespecial #4                  // Method io/kubernetes/client/openapi/models/V1beta1CustomResourceDefinitionVersion."<init>":()V
       9: aload_2
      10: invokespecial #7                  // Method "<init>":(Lio/kubernetes/client/openapi/models/V1beta1CustomResourceDefinitionVersionFluent;Lio/kubernetes/client/openapi/models/V1beta1CustomResourceDefinitionVersion;Ljava/lang/Boolean;)V
      13: return

  public io.kubernetes.client.openapi.models.V1beta1CustomResourceDefinitionVersionBuilder(io.kubernetes.client.openapi.models.V1beta1CustomResourceDefinitionVersionFluent<?>, io.kubernetes.client.openapi.models.V1beta1CustomResourceDefinitionVersion);
    Code:
       0: aload_0
       1: aload_1
       2: aload_2
       3: iconst_1
       4: invokestatic  #1                  // Method java/lang/Boolean.valueOf:(Z)Ljava/lang/Boolean;
       7: invokespecial #7                  // Method "<init>":(Lio/kubernetes/client/openapi/models/V1beta1CustomResourceDefinitionVersionFluent;Lio/kubernetes/client/openapi/models/V1beta1CustomResourceDefinitionVersion;Ljava/lang/Boolean;)V
      10: return

  public io.kubernetes.client.openapi.models.V1beta1CustomResourceDefinitionVersionBuilder(io.kubernetes.client.openapi.models.V1beta1CustomResourceDefinitionVersionFluent<?>, io.kubernetes.client.openapi.models.V1beta1CustomResourceDefinitionVersion, java.lang.Boolean);
    Code:
       0: aload_0
       1: invokespecial #8                  // Method io/kubernetes/client/openapi/models/V1beta1CustomResourceDefinitionVersionFluentImpl."<init>":()V
       4: aload_0
       5: aload_1
       6: putfield      #9                  // Field fluent:Lio/kubernetes/client/openapi/models/V1beta1CustomResourceDefinitionVersionFluent;
       9: aload_1
      10: aload_2
      11: invokevirtual #10                 // Method io/kubernetes/client/openapi/models/V1beta1CustomResourceDefinitionVersion.getAdditionalPrinterColumns:()Ljava/util/List;
      14: invokeinterface #11,  2           // InterfaceMethod io/kubernetes/client/openapi/models/V1beta1CustomResourceDefinitionVersionFluent.withAdditionalPrinterColumns:(Ljava/util/List;)Lio/kubernetes/client/openapi/models/V1beta1CustomResourceDefinitionVersionFluent;
      19: pop
      20: aload_1
      21: aload_2
      22: invokevirtual #12                 // Method io/kubernetes/client/openapi/models/V1beta1CustomResourceDefinitionVersion.getName:()Ljava/lang/String;
      25: invokeinterface #13,  2           // InterfaceMethod io/kubernetes/client/openapi/models/V1beta1CustomResourceDefinitionVersionFluent.withName:(Ljava/lang/String;)Lio/kubernetes/client/openapi/models/V1beta1CustomResourceDefinitionVersionFluent;
      30: pop
      31: aload_1
      32: aload_2
      33: invokevirtual #14                 // Method io/kubernetes/client/openapi/models/V1beta1CustomResourceDefinitionVersion.getSchema:()Lio/kubernetes/client/openapi/models/V1beta1CustomResourceValidation;
      36: invokeinterface #15,  2           // InterfaceMethod io/kubernetes/client/openapi/models/V1beta1CustomResourceDefinitionVersionFluent.withSchema:(Lio/kubernetes/client/openapi/models/V1beta1CustomResourceValidation;)Lio/kubernetes/client/openapi/models/V1beta1CustomResourceDefinitionVersionFluent;
      41: pop
      42: aload_1
      43: aload_2
      44: invokevirtual #16                 // Method io/kubernetes/client/openapi/models/V1beta1CustomResourceDefinitionVersion.getServed:()Ljava/lang/Boolean;
      47: invokeinterface #17,  2           // InterfaceMethod io/kubernetes/client/openapi/models/V1beta1CustomResourceDefinitionVersionFluent.withServed:(Ljava/lang/Boolean;)Lio/kubernetes/client/openapi/models/V1beta1CustomResourceDefinitionVersionFluent;
      52: pop
      53: aload_1
      54: aload_2
      55: invokevirtual #18                 // Method io/kubernetes/client/openapi/models/V1beta1CustomResourceDefinitionVersion.getStorage:()Ljava/lang/Boolean;
      58: invokeinterface #19,  2           // InterfaceMethod io/kubernetes/client/openapi/models/V1beta1CustomResourceDefinitionVersionFluent.withStorage:(Ljava/lang/Boolean;)Lio/kubernetes/client/openapi/models/V1beta1CustomResourceDefinitionVersionFluent;
      63: pop
      64: aload_1
      65: aload_2
      66: invokevirtual #20                 // Method io/kubernetes/client/openapi/models/V1beta1CustomResourceDefinitionVersion.getSubresources:()Lio/kubernetes/client/openapi/models/V1beta1CustomResourceSubresources;
      69: invokeinterface #21,  2           // InterfaceMethod io/kubernetes/client/openapi/models/V1beta1CustomResourceDefinitionVersionFluent.withSubresources:(Lio/kubernetes/client/openapi/models/V1beta1CustomResourceSubresources;)Lio/kubernetes/client/openapi/models/V1beta1CustomResourceDefinitionVersionFluent;
      74: pop
      75: aload_0
      76: aload_3
      77: putfield      #22                 // Field validationEnabled:Ljava/lang/Boolean;
      80: return

  public io.kubernetes.client.openapi.models.V1beta1CustomResourceDefinitionVersionBuilder(io.kubernetes.client.openapi.models.V1beta1CustomResourceDefinitionVersion);
    Code:
       0: aload_0
       1: aload_1
       2: iconst_1
       3: invokestatic  #1                  // Method java/lang/Boolean.valueOf:(Z)Ljava/lang/Boolean;
       6: invokespecial #5                  // Method "<init>":(Lio/kubernetes/client/openapi/models/V1beta1CustomResourceDefinitionVersion;Ljava/lang/Boolean;)V
       9: return

  public io.kubernetes.client.openapi.models.V1beta1CustomResourceDefinitionVersionBuilder(io.kubernetes.client.openapi.models.V1beta1CustomResourceDefinitionVersion, java.lang.Boolean);
    Code:
       0: aload_0
       1: invokespecial #8                  // Method io/kubernetes/client/openapi/models/V1beta1CustomResourceDefinitionVersionFluentImpl."<init>":()V
       4: aload_0
       5: aload_0
       6: putfield      #9                  // Field fluent:Lio/kubernetes/client/openapi/models/V1beta1CustomResourceDefinitionVersionFluent;
       9: aload_0
      10: aload_1
      11: invokevirtual #10                 // Method io/kubernetes/client/openapi/models/V1beta1CustomResourceDefinitionVersion.getAdditionalPrinterColumns:()Ljava/util/List;
      14: invokevirtual #23                 // Method withAdditionalPrinterColumns:(Ljava/util/List;)Lio/kubernetes/client/openapi/models/V1beta1CustomResourceDefinitionVersionFluent;
      17: pop
      18: aload_0
      19: aload_1
      20: invokevirtual #12                 // Method io/kubernetes/client/openapi/models/V1beta1CustomResourceDefinitionVersion.getName:()Ljava/lang/String;
      23: invokevirtual #24                 // Method withName:(Ljava/lang/String;)Lio/kubernetes/client/openapi/models/V1beta1CustomResourceDefinitionVersionFluent;
      26: pop
      27: aload_0
      28: aload_1
      29: invokevirtual #14                 // Method io/kubernetes/client/openapi/models/V1beta1CustomResourceDefinitionVersion.getSchema:()Lio/kubernetes/client/openapi/models/V1beta1CustomResourceValidation;
      32: invokevirtual #25                 // Method withSchema:(Lio/kubernetes/client/openapi/models/V1beta1CustomResourceValidation;)Lio/kubernetes/client/openapi/models/V1beta1CustomResourceDefinitionVersionFluent;
      35: pop
      36: aload_0
      37: aload_1
      38: invokevirtual #16                 // Method io/kubernetes/client/openapi/models/V1beta1CustomResourceDefinitionVersion.getServed:()Ljava/lang/Boolean;
      41: invokevirtual #26                 // Method withServed:(Ljava/lang/Boolean;)Lio/kubernetes/client/openapi/models/V1beta1CustomResourceDefinitionVersionFluent;
      44: pop
      45: aload_0
      46: aload_1
      47: invokevirtual #18                 // Method io/kubernetes/client/openapi/models/V1beta1CustomResourceDefinitionVersion.getStorage:()Ljava/lang/Boolean;
      50: invokevirtual #27                 // Method withStorage:(Ljava/lang/Boolean;)Lio/kubernetes/client/openapi/models/V1beta1CustomResourceDefinitionVersionFluent;
      53: pop
      54: aload_0
      55: aload_1
      56: invokevirtual #20                 // Method io/kubernetes/client/openapi/models/V1beta1CustomResourceDefinitionVersion.getSubresources:()Lio/kubernetes/client/openapi/models/V1beta1CustomResourceSubresources;
      59: invokevirtual #28                 // Method withSubresources:(Lio/kubernetes/client/openapi/models/V1beta1CustomResourceSubresources;)Lio/kubernetes/client/openapi/models/V1beta1CustomResourceDefinitionVersionFluent;
      62: pop
      63: aload_0
      64: aload_2
      65: putfield      #22                 // Field validationEnabled:Ljava/lang/Boolean;
      68: return

  public io.kubernetes.client.openapi.models.V1beta1CustomResourceDefinitionVersion build();
    Code:
       0: new           #3                  // class io/kubernetes/client/openapi/models/V1beta1CustomResourceDefinitionVersion
       3: dup
       4: invokespecial #4                  // Method io/kubernetes/client/openapi/models/V1beta1CustomResourceDefinitionVersion."<init>":()V
       7: astore_1
       8: aload_1
       9: aload_0
      10: getfield      #9                  // Field fluent:Lio/kubernetes/client/openapi/models/V1beta1CustomResourceDefinitionVersionFluent;
      13: invokeinterface #29,  1           // InterfaceMethod io/kubernetes/client/openapi/models/V1beta1CustomResourceDefinitionVersionFluent.getAdditionalPrinterColumns:()Ljava/util/List;
      18: invokevirtual #30                 // Method io/kubernetes/client/openapi/models/V1beta1CustomResourceDefinitionVersion.setAdditionalPrinterColumns:(Ljava/util/List;)V
      21: aload_1
      22: aload_0
      23: getfield      #9                  // Field fluent:Lio/kubernetes/client/openapi/models/V1beta1CustomResourceDefinitionVersionFluent;
      26: invokeinterface #31,  1           // InterfaceMethod io/kubernetes/client/openapi/models/V1beta1CustomResourceDefinitionVersionFluent.getName:()Ljava/lang/String;
      31: invokevirtual #32                 // Method io/kubernetes/client/openapi/models/V1beta1CustomResourceDefinitionVersion.setName:(Ljava/lang/String;)V
      34: aload_1
      35: aload_0
      36: getfield      #9                  // Field fluent:Lio/kubernetes/client/openapi/models/V1beta1CustomResourceDefinitionVersionFluent;
      39: invokeinterface #33,  1           // InterfaceMethod io/kubernetes/client/openapi/models/V1beta1CustomResourceDefinitionVersionFluent.getSchema:()Lio/kubernetes/client/openapi/models/V1beta1CustomResourceValidation;
      44: invokevirtual #34                 // Method io/kubernetes/client/openapi/models/V1beta1CustomResourceDefinitionVersion.setSchema:(Lio/kubernetes/client/openapi/models/V1beta1CustomResourceValidation;)V
      47: aload_1
      48: aload_0
      49: getfield      #9                  // Field fluent:Lio/kubernetes/client/openapi/models/V1beta1CustomResourceDefinitionVersionFluent;
      52: invokeinterface #35,  1           // InterfaceMethod io/kubernetes/client/openapi/models/V1beta1CustomResourceDefinitionVersionFluent.isServed:()Ljava/lang/Boolean;
      57: invokevirtual #36                 // Method io/kubernetes/client/openapi/models/V1beta1CustomResourceDefinitionVersion.setServed:(Ljava/lang/Boolean;)V
      60: aload_1
      61: aload_0
      62: getfield      #9                  // Field fluent:Lio/kubernetes/client/openapi/models/V1beta1CustomResourceDefinitionVersionFluent;
      65: invokeinterface #37,  1           // InterfaceMethod io/kubernetes/client/openapi/models/V1beta1CustomResourceDefinitionVersionFluent.isStorage:()Ljava/lang/Boolean;
      70: invokevirtual #38                 // Method io/kubernetes/client/openapi/models/V1beta1CustomResourceDefinitionVersion.setStorage:(Ljava/lang/Boolean;)V
      73: aload_1
      74: aload_0
      75: getfield      #9                  // Field fluent:Lio/kubernetes/client/openapi/models/V1beta1CustomResourceDefinitionVersionFluent;
      78: invokeinterface #39,  1           // InterfaceMethod io/kubernetes/client/openapi/models/V1beta1CustomResourceDefinitionVersionFluent.getSubresources:()Lio/kubernetes/client/openapi/models/V1beta1CustomResourceSubresources;
      83: invokevirtual #40                 // Method io/kubernetes/client/openapi/models/V1beta1CustomResourceDefinitionVersion.setSubresources:(Lio/kubernetes/client/openapi/models/V1beta1CustomResourceSubresources;)V
      86: aload_1
      87: areturn

  public boolean equals(java.lang.Object);
    Code:
       0: aload_0
       1: aload_1
       2: if_acmpne     7
       5: iconst_1
       6: ireturn
       7: aload_1
       8: ifnull        22
      11: aload_0
      12: invokevirtual #41                 // Method java/lang/Object.getClass:()Ljava/lang/Class;
      15: aload_1
      16: invokevirtual #41                 // Method java/lang/Object.getClass:()Ljava/lang/Class;
      19: if_acmpeq     24
      22: iconst_0
      23: ireturn
      24: aload_0
      25: aload_1
      26: invokespecial #42                 // Method io/kubernetes/client/openapi/models/V1beta1CustomResourceDefinitionVersionFluentImpl.equals:(Ljava/lang/Object;)Z
      29: ifne          34
      32: iconst_0
      33: ireturn
      34: aload_1
      35: checkcast     #43                 // class io/kubernetes/client/openapi/models/V1beta1CustomResourceDefinitionVersionBuilder
      38: astore_2
      39: aload_0
      40: getfield      #9                  // Field fluent:Lio/kubernetes/client/openapi/models/V1beta1CustomResourceDefinitionVersionFluent;
      43: ifnull        71
      46: aload_0
      47: getfield      #9                  // Field fluent:Lio/kubernetes/client/openapi/models/V1beta1CustomResourceDefinitionVersionFluent;
      50: aload_0
      51: if_acmpeq     71
      54: aload_0
      55: getfield      #9                  // Field fluent:Lio/kubernetes/client/openapi/models/V1beta1CustomResourceDefinitionVersionFluent;
      58: aload_2
      59: getfield      #9                  // Field fluent:Lio/kubernetes/client/openapi/models/V1beta1CustomResourceDefinitionVersionFluent;
      62: invokevirtual #44                 // Method java/lang/Object.equals:(Ljava/lang/Object;)Z
      65: ifne          88
      68: goto          86
      71: aload_2
      72: getfield      #9                  // Field fluent:Lio/kubernetes/client/openapi/models/V1beta1CustomResourceDefinitionVersionFluent;
      75: ifnull        88
      78: aload_0
      79: getfield      #9                  // Field fluent:Lio/kubernetes/client/openapi/models/V1beta1CustomResourceDefinitionVersionFluent;
      82: aload_0
      83: if_acmpeq     88
      86: iconst_0
      87: ireturn
      88: aload_0
      89: getfield      #22                 // Field validationEnabled:Ljava/lang/Boolean;
      92: ifnull        112
      95: aload_0
      96: getfield      #22                 // Field validationEnabled:Ljava/lang/Boolean;
      99: aload_2
     100: getfield      #22                 // Field validationEnabled:Ljava/lang/Boolean;
     103: invokevirtual #45                 // Method java/lang/Boolean.equals:(Ljava/lang/Object;)Z
     106: ifne          121
     109: goto          119
     112: aload_2
     113: getfield      #22                 // Field validationEnabled:Ljava/lang/Boolean;
     116: ifnull        121
     119: iconst_0
     120: ireturn
     121: iconst_1
     122: ireturn

  public java.lang.Object build();
    Code:
       0: aload_0
       1: invokevirtual #46                 // Method build:()Lio/kubernetes/client/openapi/models/V1beta1CustomResourceDefinitionVersion;
       4: areturn
}
