Compiled from "V1beta1CertificateSigningRequestStatusFluentImpl.java"
public class io.kubernetes.client.openapi.models.V1beta1CertificateSigningRequestStatusFluentImpl$ConditionsNestedImpl<N> extends io.kubernetes.client.openapi.models.V1beta1CertificateSigningRequestConditionFluentImpl<io.kubernetes.client.openapi.models.V1beta1CertificateSigningRequestStatusFluent$ConditionsNested<N>> implements io.kubernetes.client.openapi.models.V1beta1CertificateSigningRequestStatusFluent$ConditionsNested<N>, io.kubernetes.client.fluent.Nested<N> {
  private final io.kubernetes.client.openapi.models.V1beta1CertificateSigningRequestConditionBuilder builder;

  private final int index;

  final io.kubernetes.client.openapi.models.V1beta1CertificateSigningRequestStatusFluentImpl this$0;

  io.kubernetes.client.openapi.models.V1beta1CertificateSigningRequestStatusFluentImpl$ConditionsNestedImpl(io.kubernetes.client.openapi.models.V1beta1CertificateSigningRequestStatusFluentImpl, int, io.kubernetes.client.openapi.models.V1beta1CertificateSigningRequestCondition);
    Code:
       0: aload_0
       1: aload_1
       2: putfield      #1                  // Field this$0:Lio/kubernetes/client/openapi/models/V1beta1CertificateSigningRequestStatusFluentImpl;
       5: aload_0
       6: invokespecial #2                  // Method io/kubernetes/client/openapi/models/V1beta1CertificateSigningRequestConditionFluentImpl."<init>":()V
       9: aload_0
      10: iload_2
      11: putfield      #3                  // Field index:I
      14: aload_0
      15: new           #4                  // class io/kubernetes/client/openapi/models/V1beta1CertificateSigningRequestConditionBuilder
      18: dup
      19: aload_0
      20: aload_3
      21: invokespecial #5                  // Method io/kubernetes/client/openapi/models/V1beta1CertificateSigningRequestConditionBuilder."<init>":(Lio/kubernetes/client/openapi/models/V1beta1CertificateSigningRequestConditionFluent;Lio/kubernetes/client/openapi/models/V1beta1CertificateSigningRequestCondition;)V
      24: putfield      #6                  // Field builder:Lio/kubernetes/client/openapi/models/V1beta1CertificateSigningRequestConditionBuilder;
      27: return

  io.kubernetes.client.openapi.models.V1beta1CertificateSigningRequestStatusFluentImpl$ConditionsNestedImpl(io.kubernetes.client.openapi.models.V1beta1CertificateSigningRequestStatusFluentImpl);
    Code:
       0: aload_0
       1: aload_1
       2: putfield      #1                  // Field this$0:Lio/kubernetes/client/openapi/models/V1beta1CertificateSigningRequestStatusFluentImpl;
       5: aload_0
       6: invokespecial #2                  // Method io/kubernetes/client/openapi/models/V1beta1CertificateSigningRequestConditionFluentImpl."<init>":()V
       9: aload_0
      10: iconst_m1
      11: putfield      #3                  // Field index:I
      14: aload_0
      15: new           #4                  // class io/kubernetes/client/openapi/models/V1beta1CertificateSigningRequestConditionBuilder
      18: dup
      19: aload_0
      20: invokespecial #7                  // Method io/kubernetes/client/openapi/models/V1beta1CertificateSigningRequestConditionBuilder."<init>":(Lio/kubernetes/client/openapi/models/V1beta1CertificateSigningRequestConditionFluent;)V
      23: putfield      #6                  // Field builder:Lio/kubernetes/client/openapi/models/V1beta1CertificateSigningRequestConditionBuilder;
      26: return

  public N and();
    Code:
       0: aload_0
       1: getfield      #1                  // Field this$0:Lio/kubernetes/client/openapi/models/V1beta1CertificateSigningRequestStatusFluentImpl;
       4: aload_0
       5: getfield      #3                  // Field index:I
       8: aload_0
       9: getfield      #6                  // Field builder:Lio/kubernetes/client/openapi/models/V1beta1CertificateSigningRequestConditionBuilder;
      12: invokevirtual #8                  // Method io/kubernetes/client/openapi/models/V1beta1CertificateSigningRequestConditionBuilder.build:()Lio/kubernetes/client/openapi/models/V1beta1CertificateSigningRequestCondition;
      15: invokevirtual #9                  // Method io/kubernetes/client/openapi/models/V1beta1CertificateSigningRequestStatusFluentImpl.setToConditions:(ILio/kubernetes/client/openapi/models/V1beta1CertificateSigningRequestCondition;)Lio/kubernetes/client/openapi/models/V1beta1CertificateSigningRequestStatusFluent;
      18: areturn

  public N endCondition();
    Code:
       0: aload_0
       1: invokevirtual #10                 // Method and:()Ljava/lang/Object;
       4: areturn
}
