Compiled from "V1beta1StatefulSetFluentImpl.java"
public class io.kubernetes.client.openapi.models.V1beta1StatefulSetFluentImpl$SpecNestedImpl<N> extends io.kubernetes.client.openapi.models.V1beta1StatefulSetSpecFluentImpl<io.kubernetes.client.openapi.models.V1beta1StatefulSetFluent$SpecNested<N>> implements io.kubernetes.client.openapi.models.V1beta1StatefulSetFluent$SpecNested<N>, io.kubernetes.client.fluent.Nested<N> {
  private final io.kubernetes.client.openapi.models.V1beta1StatefulSetSpecBuilder builder;

  final io.kubernetes.client.openapi.models.V1beta1StatefulSetFluentImpl this$0;

  io.kubernetes.client.openapi.models.V1beta1StatefulSetFluentImpl$SpecNestedImpl(io.kubernetes.client.openapi.models.V1beta1StatefulSetFluentImpl, io.kubernetes.client.openapi.models.V1beta1StatefulSetSpec);
    Code:
       0: aload_0
       1: aload_1
       2: putfield      #1                  // Field this$0:Lio/kubernetes/client/openapi/models/V1beta1StatefulSetFluentImpl;
       5: aload_0
       6: invokespecial #2                  // Method io/kubernetes/client/openapi/models/V1beta1StatefulSetSpecFluentImpl."<init>":()V
       9: aload_0
      10: new           #3                  // class io/kubernetes/client/openapi/models/V1beta1StatefulSetSpecBuilder
      13: dup
      14: aload_0
      15: aload_2
      16: invokespecial #4                  // Method io/kubernetes/client/openapi/models/V1beta1StatefulSetSpecBuilder."<init>":(Lio/kubernetes/client/openapi/models/V1beta1StatefulSetSpecFluent;Lio/kubernetes/client/openapi/models/V1beta1StatefulSetSpec;)V
      19: putfield      #5                  // Field builder:Lio/kubernetes/client/openapi/models/V1beta1StatefulSetSpecBuilder;
      22: return

  io.kubernetes.client.openapi.models.V1beta1StatefulSetFluentImpl$SpecNestedImpl(io.kubernetes.client.openapi.models.V1beta1StatefulSetFluentImpl);
    Code:
       0: aload_0
       1: aload_1
       2: putfield      #1                  // Field this$0:Lio/kubernetes/client/openapi/models/V1beta1StatefulSetFluentImpl;
       5: aload_0
       6: invokespecial #2                  // Method io/kubernetes/client/openapi/models/V1beta1StatefulSetSpecFluentImpl."<init>":()V
       9: aload_0
      10: new           #3                  // class io/kubernetes/client/openapi/models/V1beta1StatefulSetSpecBuilder
      13: dup
      14: aload_0
      15: invokespecial #6                  // Method io/kubernetes/client/openapi/models/V1beta1StatefulSetSpecBuilder."<init>":(Lio/kubernetes/client/openapi/models/V1beta1StatefulSetSpecFluent;)V
      18: putfield      #5                  // Field builder:Lio/kubernetes/client/openapi/models/V1beta1StatefulSetSpecBuilder;
      21: return

  public N and();
    Code:
       0: aload_0
       1: getfield      #1                  // Field this$0:Lio/kubernetes/client/openapi/models/V1beta1StatefulSetFluentImpl;
       4: aload_0
       5: getfield      #5                  // Field builder:Lio/kubernetes/client/openapi/models/V1beta1StatefulSetSpecBuilder;
       8: invokevirtual #7                  // Method io/kubernetes/client/openapi/models/V1beta1StatefulSetSpecBuilder.build:()Lio/kubernetes/client/openapi/models/V1beta1StatefulSetSpec;
      11: invokevirtual #8                  // Method io/kubernetes/client/openapi/models/V1beta1StatefulSetFluentImpl.withSpec:(Lio/kubernetes/client/openapi/models/V1beta1StatefulSetSpec;)Lio/kubernetes/client/openapi/models/V1beta1StatefulSetFluent;
      14: areturn

  public N endSpec();
    Code:
       0: aload_0
       1: invokevirtual #9                  // Method and:()Ljava/lang/Object;
       4: areturn
}
