Compiled from "V1beta1CustomResourceDefinitionNamesBuilder.java"
public class io.kubernetes.client.openapi.models.V1beta1CustomResourceDefinitionNamesBuilder extends io.kubernetes.client.openapi.models.V1beta1CustomResourceDefinitionNamesFluentImpl<io.kubernetes.client.openapi.models.V1beta1CustomResourceDefinitionNamesBuilder> implements io.kubernetes.client.fluent.VisitableBuilder<io.kubernetes.client.openapi.models.V1beta1CustomResourceDefinitionNames, io.kubernetes.client.openapi.models.V1beta1CustomResourceDefinitionNamesBuilder> {
  io.kubernetes.client.openapi.models.V1beta1CustomResourceDefinitionNamesFluent<?> fluent;

  java.lang.Boolean validationEnabled;

  public io.kubernetes.client.openapi.models.V1beta1CustomResourceDefinitionNamesBuilder();
    Code:
       0: aload_0
       1: iconst_1
       2: invokestatic  #1                  // Method java/lang/Boolean.valueOf:(Z)Ljava/lang/Boolean;
       5: invokespecial #2                  // Method "<init>":(Ljava/lang/Boolean;)V
       8: return

  public io.kubernetes.client.openapi.models.V1beta1CustomResourceDefinitionNamesBuilder(java.lang.Boolean);
    Code:
       0: aload_0
       1: new           #3                  // class io/kubernetes/client/openapi/models/V1beta1CustomResourceDefinitionNames
       4: dup
       5: invokespecial #4                  // Method io/kubernetes/client/openapi/models/V1beta1CustomResourceDefinitionNames."<init>":()V
       8: aload_1
       9: invokespecial #5                  // Method "<init>":(Lio/kubernetes/client/openapi/models/V1beta1CustomResourceDefinitionNames;Ljava/lang/Boolean;)V
      12: return

  public io.kubernetes.client.openapi.models.V1beta1CustomResourceDefinitionNamesBuilder(io.kubernetes.client.openapi.models.V1beta1CustomResourceDefinitionNamesFluent<?>);
    Code:
       0: aload_0
       1: aload_1
       2: iconst_1
       3: invokestatic  #1                  // Method java/lang/Boolean.valueOf:(Z)Ljava/lang/Boolean;
       6: invokespecial #6                  // Method "<init>":(Lio/kubernetes/client/openapi/models/V1beta1CustomResourceDefinitionNamesFluent;Ljava/lang/Boolean;)V
       9: return

  public io.kubernetes.client.openapi.models.V1beta1CustomResourceDefinitionNamesBuilder(io.kubernetes.client.openapi.models.V1beta1CustomResourceDefinitionNamesFluent<?>, java.lang.Boolean);
    Code:
       0: aload_0
       1: aload_1
       2: new           #3                  // class io/kubernetes/client/openapi/models/V1beta1CustomResourceDefinitionNames
       5: dup
       6: invokespecial #4                  // Method io/kubernetes/client/openapi/models/V1beta1CustomResourceDefinitionNames."<init>":()V
       9: aload_2
      10: invokespecial #7                  // Method "<init>":(Lio/kubernetes/client/openapi/models/V1beta1CustomResourceDefinitionNamesFluent;Lio/kubernetes/client/openapi/models/V1beta1CustomResourceDefinitionNames;Ljava/lang/Boolean;)V
      13: return

  public io.kubernetes.client.openapi.models.V1beta1CustomResourceDefinitionNamesBuilder(io.kubernetes.client.openapi.models.V1beta1CustomResourceDefinitionNamesFluent<?>, io.kubernetes.client.openapi.models.V1beta1CustomResourceDefinitionNames);
    Code:
       0: aload_0
       1: aload_1
       2: aload_2
       3: iconst_1
       4: invokestatic  #1                  // Method java/lang/Boolean.valueOf:(Z)Ljava/lang/Boolean;
       7: invokespecial #7                  // Method "<init>":(Lio/kubernetes/client/openapi/models/V1beta1CustomResourceDefinitionNamesFluent;Lio/kubernetes/client/openapi/models/V1beta1CustomResourceDefinitionNames;Ljava/lang/Boolean;)V
      10: return

  public io.kubernetes.client.openapi.models.V1beta1CustomResourceDefinitionNamesBuilder(io.kubernetes.client.openapi.models.V1beta1CustomResourceDefinitionNamesFluent<?>, io.kubernetes.client.openapi.models.V1beta1CustomResourceDefinitionNames, java.lang.Boolean);
    Code:
       0: aload_0
       1: invokespecial #8                  // Method io/kubernetes/client/openapi/models/V1beta1CustomResourceDefinitionNamesFluentImpl."<init>":()V
       4: aload_0
       5: aload_1
       6: putfield      #9                  // Field fluent:Lio/kubernetes/client/openapi/models/V1beta1CustomResourceDefinitionNamesFluent;
       9: aload_1
      10: aload_2
      11: invokevirtual #10                 // Method io/kubernetes/client/openapi/models/V1beta1CustomResourceDefinitionNames.getCategories:()Ljava/util/List;
      14: invokeinterface #11,  2           // InterfaceMethod io/kubernetes/client/openapi/models/V1beta1CustomResourceDefinitionNamesFluent.withCategories:(Ljava/util/List;)Lio/kubernetes/client/openapi/models/V1beta1CustomResourceDefinitionNamesFluent;
      19: pop
      20: aload_1
      21: aload_2
      22: invokevirtual #12                 // Method io/kubernetes/client/openapi/models/V1beta1CustomResourceDefinitionNames.getKind:()Ljava/lang/String;
      25: invokeinterface #13,  2           // InterfaceMethod io/kubernetes/client/openapi/models/V1beta1CustomResourceDefinitionNamesFluent.withKind:(Ljava/lang/String;)Lio/kubernetes/client/openapi/models/V1beta1CustomResourceDefinitionNamesFluent;
      30: pop
      31: aload_1
      32: aload_2
      33: invokevirtual #14                 // Method io/kubernetes/client/openapi/models/V1beta1CustomResourceDefinitionNames.getListKind:()Ljava/lang/String;
      36: invokeinterface #15,  2           // InterfaceMethod io/kubernetes/client/openapi/models/V1beta1CustomResourceDefinitionNamesFluent.withListKind:(Ljava/lang/String;)Lio/kubernetes/client/openapi/models/V1beta1CustomResourceDefinitionNamesFluent;
      41: pop
      42: aload_1
      43: aload_2
      44: invokevirtual #16                 // Method io/kubernetes/client/openapi/models/V1beta1CustomResourceDefinitionNames.getPlural:()Ljava/lang/String;
      47: invokeinterface #17,  2           // InterfaceMethod io/kubernetes/client/openapi/models/V1beta1CustomResourceDefinitionNamesFluent.withPlural:(Ljava/lang/String;)Lio/kubernetes/client/openapi/models/V1beta1CustomResourceDefinitionNamesFluent;
      52: pop
      53: aload_1
      54: aload_2
      55: invokevirtual #18                 // Method io/kubernetes/client/openapi/models/V1beta1CustomResourceDefinitionNames.getShortNames:()Ljava/util/List;
      58: invokeinterface #19,  2           // InterfaceMethod io/kubernetes/client/openapi/models/V1beta1CustomResourceDefinitionNamesFluent.withShortNames:(Ljava/util/List;)Lio/kubernetes/client/openapi/models/V1beta1CustomResourceDefinitionNamesFluent;
      63: pop
      64: aload_1
      65: aload_2
      66: invokevirtual #20                 // Method io/kubernetes/client/openapi/models/V1beta1CustomResourceDefinitionNames.getSingular:()Ljava/lang/String;
      69: invokeinterface #21,  2           // InterfaceMethod io/kubernetes/client/openapi/models/V1beta1CustomResourceDefinitionNamesFluent.withSingular:(Ljava/lang/String;)Lio/kubernetes/client/openapi/models/V1beta1CustomResourceDefinitionNamesFluent;
      74: pop
      75: aload_0
      76: aload_3
      77: putfield      #22                 // Field validationEnabled:Ljava/lang/Boolean;
      80: return

  public io.kubernetes.client.openapi.models.V1beta1CustomResourceDefinitionNamesBuilder(io.kubernetes.client.openapi.models.V1beta1CustomResourceDefinitionNames);
    Code:
       0: aload_0
       1: aload_1
       2: iconst_1
       3: invokestatic  #1                  // Method java/lang/Boolean.valueOf:(Z)Ljava/lang/Boolean;
       6: invokespecial #5                  // Method "<init>":(Lio/kubernetes/client/openapi/models/V1beta1CustomResourceDefinitionNames;Ljava/lang/Boolean;)V
       9: return

  public io.kubernetes.client.openapi.models.V1beta1CustomResourceDefinitionNamesBuilder(io.kubernetes.client.openapi.models.V1beta1CustomResourceDefinitionNames, java.lang.Boolean);
    Code:
       0: aload_0
       1: invokespecial #8                  // Method io/kubernetes/client/openapi/models/V1beta1CustomResourceDefinitionNamesFluentImpl."<init>":()V
       4: aload_0
       5: aload_0
       6: putfield      #9                  // Field fluent:Lio/kubernetes/client/openapi/models/V1beta1CustomResourceDefinitionNamesFluent;
       9: aload_0
      10: aload_1
      11: invokevirtual #10                 // Method io/kubernetes/client/openapi/models/V1beta1CustomResourceDefinitionNames.getCategories:()Ljava/util/List;
      14: invokevirtual #23                 // Method withCategories:(Ljava/util/List;)Lio/kubernetes/client/openapi/models/V1beta1CustomResourceDefinitionNamesFluent;
      17: pop
      18: aload_0
      19: aload_1
      20: invokevirtual #12                 // Method io/kubernetes/client/openapi/models/V1beta1CustomResourceDefinitionNames.getKind:()Ljava/lang/String;
      23: invokevirtual #24                 // Method withKind:(Ljava/lang/String;)Lio/kubernetes/client/openapi/models/V1beta1CustomResourceDefinitionNamesFluent;
      26: pop
      27: aload_0
      28: aload_1
      29: invokevirtual #14                 // Method io/kubernetes/client/openapi/models/V1beta1CustomResourceDefinitionNames.getListKind:()Ljava/lang/String;
      32: invokevirtual #25                 // Method withListKind:(Ljava/lang/String;)Lio/kubernetes/client/openapi/models/V1beta1CustomResourceDefinitionNamesFluent;
      35: pop
      36: aload_0
      37: aload_1
      38: invokevirtual #16                 // Method io/kubernetes/client/openapi/models/V1beta1CustomResourceDefinitionNames.getPlural:()Ljava/lang/String;
      41: invokevirtual #26                 // Method withPlural:(Ljava/lang/String;)Lio/kubernetes/client/openapi/models/V1beta1CustomResourceDefinitionNamesFluent;
      44: pop
      45: aload_0
      46: aload_1
      47: invokevirtual #18                 // Method io/kubernetes/client/openapi/models/V1beta1CustomResourceDefinitionNames.getShortNames:()Ljava/util/List;
      50: invokevirtual #27                 // Method withShortNames:(Ljava/util/List;)Lio/kubernetes/client/openapi/models/V1beta1CustomResourceDefinitionNamesFluent;
      53: pop
      54: aload_0
      55: aload_1
      56: invokevirtual #20                 // Method io/kubernetes/client/openapi/models/V1beta1CustomResourceDefinitionNames.getSingular:()Ljava/lang/String;
      59: invokevirtual #28                 // Method withSingular:(Ljava/lang/String;)Lio/kubernetes/client/openapi/models/V1beta1CustomResourceDefinitionNamesFluent;
      62: pop
      63: aload_0
      64: aload_2
      65: putfield      #22                 // Field validationEnabled:Ljava/lang/Boolean;
      68: return

  public io.kubernetes.client.openapi.models.V1beta1CustomResourceDefinitionNames build();
    Code:
       0: new           #3                  // class io/kubernetes/client/openapi/models/V1beta1CustomResourceDefinitionNames
       3: dup
       4: invokespecial #4                  // Method io/kubernetes/client/openapi/models/V1beta1CustomResourceDefinitionNames."<init>":()V
       7: astore_1
       8: aload_1
       9: aload_0
      10: getfield      #9                  // Field fluent:Lio/kubernetes/client/openapi/models/V1beta1CustomResourceDefinitionNamesFluent;
      13: invokeinterface #29,  1           // InterfaceMethod io/kubernetes/client/openapi/models/V1beta1CustomResourceDefinitionNamesFluent.getCategories:()Ljava/util/List;
      18: invokevirtual #30                 // Method io/kubernetes/client/openapi/models/V1beta1CustomResourceDefinitionNames.setCategories:(Ljava/util/List;)V
      21: aload_1
      22: aload_0
      23: getfield      #9                  // Field fluent:Lio/kubernetes/client/openapi/models/V1beta1CustomResourceDefinitionNamesFluent;
      26: invokeinterface #31,  1           // InterfaceMethod io/kubernetes/client/openapi/models/V1beta1CustomResourceDefinitionNamesFluent.getKind:()Ljava/lang/String;
      31: invokevirtual #32                 // Method io/kubernetes/client/openapi/models/V1beta1CustomResourceDefinitionNames.setKind:(Ljava/lang/String;)V
      34: aload_1
      35: aload_0
      36: getfield      #9                  // Field fluent:Lio/kubernetes/client/openapi/models/V1beta1CustomResourceDefinitionNamesFluent;
      39: invokeinterface #33,  1           // InterfaceMethod io/kubernetes/client/openapi/models/V1beta1CustomResourceDefinitionNamesFluent.getListKind:()Ljava/lang/String;
      44: invokevirtual #34                 // Method io/kubernetes/client/openapi/models/V1beta1CustomResourceDefinitionNames.setListKind:(Ljava/lang/String;)V
      47: aload_1
      48: aload_0
      49: getfield      #9                  // Field fluent:Lio/kubernetes/client/openapi/models/V1beta1CustomResourceDefinitionNamesFluent;
      52: invokeinterface #35,  1           // InterfaceMethod io/kubernetes/client/openapi/models/V1beta1CustomResourceDefinitionNamesFluent.getPlural:()Ljava/lang/String;
      57: invokevirtual #36                 // Method io/kubernetes/client/openapi/models/V1beta1CustomResourceDefinitionNames.setPlural:(Ljava/lang/String;)V
      60: aload_1
      61: aload_0
      62: getfield      #9                  // Field fluent:Lio/kubernetes/client/openapi/models/V1beta1CustomResourceDefinitionNamesFluent;
      65: invokeinterface #37,  1           // InterfaceMethod io/kubernetes/client/openapi/models/V1beta1CustomResourceDefinitionNamesFluent.getShortNames:()Ljava/util/List;
      70: invokevirtual #38                 // Method io/kubernetes/client/openapi/models/V1beta1CustomResourceDefinitionNames.setShortNames:(Ljava/util/List;)V
      73: aload_1
      74: aload_0
      75: getfield      #9                  // Field fluent:Lio/kubernetes/client/openapi/models/V1beta1CustomResourceDefinitionNamesFluent;
      78: invokeinterface #39,  1           // InterfaceMethod io/kubernetes/client/openapi/models/V1beta1CustomResourceDefinitionNamesFluent.getSingular:()Ljava/lang/String;
      83: invokevirtual #40                 // Method io/kubernetes/client/openapi/models/V1beta1CustomResourceDefinitionNames.setSingular:(Ljava/lang/String;)V
      86: aload_1
      87: areturn

  public boolean equals(java.lang.Object);
    Code:
       0: aload_0
       1: aload_1
       2: if_acmpne     7
       5: iconst_1
       6: ireturn
       7: aload_1
       8: ifnull        22
      11: aload_0
      12: invokevirtual #41                 // Method java/lang/Object.getClass:()Ljava/lang/Class;
      15: aload_1
      16: invokevirtual #41                 // Method java/lang/Object.getClass:()Ljava/lang/Class;
      19: if_acmpeq     24
      22: iconst_0
      23: ireturn
      24: aload_0
      25: aload_1
      26: invokespecial #42                 // Method io/kubernetes/client/openapi/models/V1beta1CustomResourceDefinitionNamesFluentImpl.equals:(Ljava/lang/Object;)Z
      29: ifne          34
      32: iconst_0
      33: ireturn
      34: aload_1
      35: checkcast     #43                 // class io/kubernetes/client/openapi/models/V1beta1CustomResourceDefinitionNamesBuilder
      38: astore_2
      39: aload_0
      40: getfield      #9                  // Field fluent:Lio/kubernetes/client/openapi/models/V1beta1CustomResourceDefinitionNamesFluent;
      43: ifnull        71
      46: aload_0
      47: getfield      #9                  // Field fluent:Lio/kubernetes/client/openapi/models/V1beta1CustomResourceDefinitionNamesFluent;
      50: aload_0
      51: if_acmpeq     71
      54: aload_0
      55: getfield      #9                  // Field fluent:Lio/kubernetes/client/openapi/models/V1beta1CustomResourceDefinitionNamesFluent;
      58: aload_2
      59: getfield      #9                  // Field fluent:Lio/kubernetes/client/openapi/models/V1beta1CustomResourceDefinitionNamesFluent;
      62: invokevirtual #44                 // Method java/lang/Object.equals:(Ljava/lang/Object;)Z
      65: ifne          88
      68: goto          86
      71: aload_2
      72: getfield      #9                  // Field fluent:Lio/kubernetes/client/openapi/models/V1beta1CustomResourceDefinitionNamesFluent;
      75: ifnull        88
      78: aload_0
      79: getfield      #9                  // Field fluent:Lio/kubernetes/client/openapi/models/V1beta1CustomResourceDefinitionNamesFluent;
      82: aload_0
      83: if_acmpeq     88
      86: iconst_0
      87: ireturn
      88: aload_0
      89: getfield      #22                 // Field validationEnabled:Ljava/lang/Boolean;
      92: ifnull        112
      95: aload_0
      96: getfield      #22                 // Field validationEnabled:Ljava/lang/Boolean;
      99: aload_2
     100: getfield      #22                 // Field validationEnabled:Ljava/lang/Boolean;
     103: invokevirtual #45                 // Method java/lang/Boolean.equals:(Ljava/lang/Object;)Z
     106: ifne          121
     109: goto          119
     112: aload_2
     113: getfield      #22                 // Field validationEnabled:Ljava/lang/Boolean;
     116: ifnull        121
     119: iconst_0
     120: ireturn
     121: iconst_1
     122: ireturn

  public java.lang.Object build();
    Code:
       0: aload_0
       1: invokevirtual #46                 // Method build:()Lio/kubernetes/client/openapi/models/V1beta1CustomResourceDefinitionNames;
       4: areturn
}
