Compiled from "V1CustomResourceDefinitionSpec.java"
public class io.kubernetes.client.openapi.models.V1CustomResourceDefinitionSpec {
  public static final java.lang.String SERIALIZED_NAME_CONVERSION;

  private io.kubernetes.client.openapi.models.V1CustomResourceConversion conversion;

  public static final java.lang.String SERIALIZED_NAME_GROUP;

  private java.lang.String group;

  public static final java.lang.String SERIALIZED_NAME_NAMES;

  private io.kubernetes.client.openapi.models.V1CustomResourceDefinitionNames names;

  public static final java.lang.String SERIALIZED_NAME_PRESERVE_UNKNOWN_FIELDS;

  private java.lang.Boolean preserveUnknownFields;

  public static final java.lang.String SERIALIZED_NAME_SCOPE;

  private java.lang.String scope;

  public static final java.lang.String SERIALIZED_NAME_VERSIONS;

  private java.util.List<io.kubernetes.client.openapi.models.V1CustomResourceDefinitionVersion> versions;

  public io.kubernetes.client.openapi.models.V1CustomResourceDefinitionSpec();
    Code:
       0: aload_0
       1: invokespecial #1                  // Method java/lang/Object."<init>":()V
       4: aload_0
       5: new           #2                  // class java/util/ArrayList
       8: dup
       9: invokespecial #3                  // Method java/util/ArrayList."<init>":()V
      12: putfield      #4                  // Field versions:Ljava/util/List;
      15: return

  public io.kubernetes.client.openapi.models.V1CustomResourceDefinitionSpec conversion(io.kubernetes.client.openapi.models.V1CustomResourceConversion);
    Code:
       0: aload_0
       1: aload_1
       2: putfield      #5                  // Field conversion:Lio/kubernetes/client/openapi/models/V1CustomResourceConversion;
       5: aload_0
       6: areturn

  public io.kubernetes.client.openapi.models.V1CustomResourceConversion getConversion();
    Code:
       0: aload_0
       1: getfield      #5                  // Field conversion:Lio/kubernetes/client/openapi/models/V1CustomResourceConversion;
       4: areturn

  public void setConversion(io.kubernetes.client.openapi.models.V1CustomResourceConversion);
    Code:
       0: aload_0
       1: aload_1
       2: putfield      #5                  // Field conversion:Lio/kubernetes/client/openapi/models/V1CustomResourceConversion;
       5: return

  public io.kubernetes.client.openapi.models.V1CustomResourceDefinitionSpec group(java.lang.String);
    Code:
       0: aload_0
       1: aload_1
       2: putfield      #6                  // Field group:Ljava/lang/String;
       5: aload_0
       6: areturn

  public java.lang.String getGroup();
    Code:
       0: aload_0
       1: getfield      #6                  // Field group:Ljava/lang/String;
       4: areturn

  public void setGroup(java.lang.String);
    Code:
       0: aload_0
       1: aload_1
       2: putfield      #6                  // Field group:Ljava/lang/String;
       5: return

  public io.kubernetes.client.openapi.models.V1CustomResourceDefinitionSpec names(io.kubernetes.client.openapi.models.V1CustomResourceDefinitionNames);
    Code:
       0: aload_0
       1: aload_1
       2: putfield      #7                  // Field names:Lio/kubernetes/client/openapi/models/V1CustomResourceDefinitionNames;
       5: aload_0
       6: areturn

  public io.kubernetes.client.openapi.models.V1CustomResourceDefinitionNames getNames();
    Code:
       0: aload_0
       1: getfield      #7                  // Field names:Lio/kubernetes/client/openapi/models/V1CustomResourceDefinitionNames;
       4: areturn

  public void setNames(io.kubernetes.client.openapi.models.V1CustomResourceDefinitionNames);
    Code:
       0: aload_0
       1: aload_1
       2: putfield      #7                  // Field names:Lio/kubernetes/client/openapi/models/V1CustomResourceDefinitionNames;
       5: return

  public io.kubernetes.client.openapi.models.V1CustomResourceDefinitionSpec preserveUnknownFields(java.lang.Boolean);
    Code:
       0: aload_0
       1: aload_1
       2: putfield      #8                  // Field preserveUnknownFields:Ljava/lang/Boolean;
       5: aload_0
       6: areturn

  public java.lang.Boolean getPreserveUnknownFields();
    Code:
       0: aload_0
       1: getfield      #8                  // Field preserveUnknownFields:Ljava/lang/Boolean;
       4: areturn

  public void setPreserveUnknownFields(java.lang.Boolean);
    Code:
       0: aload_0
       1: aload_1
       2: putfield      #8                  // Field preserveUnknownFields:Ljava/lang/Boolean;
       5: return

  public io.kubernetes.client.openapi.models.V1CustomResourceDefinitionSpec scope(java.lang.String);
    Code:
       0: aload_0
       1: aload_1
       2: putfield      #9                  // Field scope:Ljava/lang/String;
       5: aload_0
       6: areturn

  public java.lang.String getScope();
    Code:
       0: aload_0
       1: getfield      #9                  // Field scope:Ljava/lang/String;
       4: areturn

  public void setScope(java.lang.String);
    Code:
       0: aload_0
       1: aload_1
       2: putfield      #9                  // Field scope:Ljava/lang/String;
       5: return

  public io.kubernetes.client.openapi.models.V1CustomResourceDefinitionSpec versions(java.util.List<io.kubernetes.client.openapi.models.V1CustomResourceDefinitionVersion>);
    Code:
       0: aload_0
       1: aload_1
       2: putfield      #4                  // Field versions:Ljava/util/List;
       5: aload_0
       6: areturn

  public io.kubernetes.client.openapi.models.V1CustomResourceDefinitionSpec addVersionsItem(io.kubernetes.client.openapi.models.V1CustomResourceDefinitionVersion);
    Code:
       0: aload_0
       1: getfield      #4                  // Field versions:Ljava/util/List;
       4: aload_1
       5: invokeinterface #10,  2           // InterfaceMethod java/util/List.add:(Ljava/lang/Object;)Z
      10: pop
      11: aload_0
      12: areturn

  public java.util.List<io.kubernetes.client.openapi.models.V1CustomResourceDefinitionVersion> getVersions();
    Code:
       0: aload_0
       1: getfield      #4                  // Field versions:Ljava/util/List;
       4: areturn

  public void setVersions(java.util.List<io.kubernetes.client.openapi.models.V1CustomResourceDefinitionVersion>);
    Code:
       0: aload_0
       1: aload_1
       2: putfield      #4                  // Field versions:Ljava/util/List;
       5: return

  public boolean equals(java.lang.Object);
    Code:
       0: aload_0
       1: aload_1
       2: if_acmpne     7
       5: iconst_1
       6: ireturn
       7: aload_1
       8: ifnull        22
      11: aload_0
      12: invokevirtual #11                 // Method java/lang/Object.getClass:()Ljava/lang/Class;
      15: aload_1
      16: invokevirtual #11                 // Method java/lang/Object.getClass:()Ljava/lang/Class;
      19: if_acmpeq     24
      22: iconst_0
      23: ireturn
      24: aload_1
      25: checkcast     #12                 // class io/kubernetes/client/openapi/models/V1CustomResourceDefinitionSpec
      28: astore_2
      29: aload_0
      30: getfield      #5                  // Field conversion:Lio/kubernetes/client/openapi/models/V1CustomResourceConversion;
      33: aload_2
      34: getfield      #5                  // Field conversion:Lio/kubernetes/client/openapi/models/V1CustomResourceConversion;
      37: invokestatic  #13                 // Method java/util/Objects.equals:(Ljava/lang/Object;Ljava/lang/Object;)Z
      40: ifeq          117
      43: aload_0
      44: getfield      #6                  // Field group:Ljava/lang/String;
      47: aload_2
      48: getfield      #6                  // Field group:Ljava/lang/String;
      51: invokestatic  #13                 // Method java/util/Objects.equals:(Ljava/lang/Object;Ljava/lang/Object;)Z
      54: ifeq          117
      57: aload_0
      58: getfield      #7                  // Field names:Lio/kubernetes/client/openapi/models/V1CustomResourceDefinitionNames;
      61: aload_2
      62: getfield      #7                  // Field names:Lio/kubernetes/client/openapi/models/V1CustomResourceDefinitionNames;
      65: invokestatic  #13                 // Method java/util/Objects.equals:(Ljava/lang/Object;Ljava/lang/Object;)Z
      68: ifeq          117
      71: aload_0
      72: getfield      #8                  // Field preserveUnknownFields:Ljava/lang/Boolean;
      75: aload_2
      76: getfield      #8                  // Field preserveUnknownFields:Ljava/lang/Boolean;
      79: invokestatic  #13                 // Method java/util/Objects.equals:(Ljava/lang/Object;Ljava/lang/Object;)Z
      82: ifeq          117
      85: aload_0
      86: getfield      #9                  // Field scope:Ljava/lang/String;
      89: aload_2
      90: getfield      #9                  // Field scope:Ljava/lang/String;
      93: invokestatic  #13                 // Method java/util/Objects.equals:(Ljava/lang/Object;Ljava/lang/Object;)Z
      96: ifeq          117
      99: aload_0
     100: getfield      #4                  // Field versions:Ljava/util/List;
     103: aload_2
     104: getfield      #4                  // Field versions:Ljava/util/List;
     107: invokestatic  #13                 // Method java/util/Objects.equals:(Ljava/lang/Object;Ljava/lang/Object;)Z
     110: ifeq          117
     113: iconst_1
     114: goto          118
     117: iconst_0
     118: ireturn

  public int hashCode();
    Code:
       0: bipush        6
       2: anewarray     #14                 // class java/lang/Object
       5: dup
       6: iconst_0
       7: aload_0
       8: getfield      #5                  // Field conversion:Lio/kubernetes/client/openapi/models/V1CustomResourceConversion;
      11: aastore
      12: dup
      13: iconst_1
      14: aload_0
      15: getfield      #6                  // Field group:Ljava/lang/String;
      18: aastore
      19: dup
      20: iconst_2
      21: aload_0
      22: getfield      #7                  // Field names:Lio/kubernetes/client/openapi/models/V1CustomResourceDefinitionNames;
      25: aastore
      26: dup
      27: iconst_3
      28: aload_0
      29: getfield      #8                  // Field preserveUnknownFields:Ljava/lang/Boolean;
      32: aastore
      33: dup
      34: iconst_4
      35: aload_0
      36: getfield      #9                  // Field scope:Ljava/lang/String;
      39: aastore
      40: dup
      41: iconst_5
      42: aload_0
      43: getfield      #4                  // Field versions:Ljava/util/List;
      46: aastore
      47: invokestatic  #15                 // Method java/util/Objects.hash:([Ljava/lang/Object;)I
      50: ireturn

  public java.lang.String toString();
    Code:
       0: new           #16                 // class java/lang/StringBuilder
       3: dup
       4: invokespecial #17                 // Method java/lang/StringBuilder."<init>":()V
       7: astore_1
       8: aload_1
       9: ldc           #18                 // String class V1CustomResourceDefinitionSpec {\n
      11: invokevirtual #19                 // Method java/lang/StringBuilder.append:(Ljava/lang/String;)Ljava/lang/StringBuilder;
      14: pop
      15: aload_1
      16: ldc           #20                 // String     conversion:
      18: invokevirtual #19                 // Method java/lang/StringBuilder.append:(Ljava/lang/String;)Ljava/lang/StringBuilder;
      21: aload_0
      22: aload_0
      23: getfield      #5                  // Field conversion:Lio/kubernetes/client/openapi/models/V1CustomResourceConversion;
      26: invokespecial #21                 // Method toIndentedString:(Ljava/lang/Object;)Ljava/lang/String;
      29: invokevirtual #19                 // Method java/lang/StringBuilder.append:(Ljava/lang/String;)Ljava/lang/StringBuilder;
      32: ldc           #22                 // String \n
      34: invokevirtual #19                 // Method java/lang/StringBuilder.append:(Ljava/lang/String;)Ljava/lang/StringBuilder;
      37: pop
      38: aload_1
      39: ldc           #23                 // String     group:
      41: invokevirtual #19                 // Method java/lang/StringBuilder.append:(Ljava/lang/String;)Ljava/lang/StringBuilder;
      44: aload_0
      45: aload_0
      46: getfield      #6                  // Field group:Ljava/lang/String;
      49: invokespecial #21                 // Method toIndentedString:(Ljava/lang/Object;)Ljava/lang/String;
      52: invokevirtual #19                 // Method java/lang/StringBuilder.append:(Ljava/lang/String;)Ljava/lang/StringBuilder;
      55: ldc           #22                 // String \n
      57: invokevirtual #19                 // Method java/lang/StringBuilder.append:(Ljava/lang/String;)Ljava/lang/StringBuilder;
      60: pop
      61: aload_1
      62: ldc           #24                 // String     names:
      64: invokevirtual #19                 // Method java/lang/StringBuilder.append:(Ljava/lang/String;)Ljava/lang/StringBuilder;
      67: aload_0
      68: aload_0
      69: getfield      #7                  // Field names:Lio/kubernetes/client/openapi/models/V1CustomResourceDefinitionNames;
      72: invokespecial #21                 // Method toIndentedString:(Ljava/lang/Object;)Ljava/lang/String;
      75: invokevirtual #19                 // Method java/lang/StringBuilder.append:(Ljava/lang/String;)Ljava/lang/StringBuilder;
      78: ldc           #22                 // String \n
      80: invokevirtual #19                 // Method java/lang/StringBuilder.append:(Ljava/lang/String;)Ljava/lang/StringBuilder;
      83: pop
      84: aload_1
      85: ldc           #25                 // String     preserveUnknownFields:
      87: invokevirtual #19                 // Method java/lang/StringBuilder.append:(Ljava/lang/String;)Ljava/lang/StringBuilder;
      90: aload_0
      91: aload_0
      92: getfield      #8                  // Field preserveUnknownFields:Ljava/lang/Boolean;
      95: invokespecial #21                 // Method toIndentedString:(Ljava/lang/Object;)Ljava/lang/String;
      98: invokevirtual #19                 // Method java/lang/StringBuilder.append:(Ljava/lang/String;)Ljava/lang/StringBuilder;
     101: ldc           #22                 // String \n
     103: invokevirtual #19                 // Method java/lang/StringBuilder.append:(Ljava/lang/String;)Ljava/lang/StringBuilder;
     106: pop
     107: aload_1
     108: ldc           #26                 // String     scope:
     110: invokevirtual #19                 // Method java/lang/StringBuilder.append:(Ljava/lang/String;)Ljava/lang/StringBuilder;
     113: aload_0
     114: aload_0
     115: getfield      #9                  // Field scope:Ljava/lang/String;
     118: invokespecial #21                 // Method toIndentedString:(Ljava/lang/Object;)Ljava/lang/String;
     121: invokevirtual #19                 // Method java/lang/StringBuilder.append:(Ljava/lang/String;)Ljava/lang/StringBuilder;
     124: ldc           #22                 // String \n
     126: invokevirtual #19                 // Method java/lang/StringBuilder.append:(Ljava/lang/String;)Ljava/lang/StringBuilder;
     129: pop
     130: aload_1
     131: ldc           #27                 // String     versions:
     133: invokevirtual #19                 // Method java/lang/StringBuilder.append:(Ljava/lang/String;)Ljava/lang/StringBuilder;
     136: aload_0
     137: aload_0
     138: getfield      #4                  // Field versions:Ljava/util/List;
     141: invokespecial #21                 // Method toIndentedString:(Ljava/lang/Object;)Ljava/lang/String;
     144: invokevirtual #19                 // Method java/lang/StringBuilder.append:(Ljava/lang/String;)Ljava/lang/StringBuilder;
     147: ldc           #22                 // String \n
     149: invokevirtual #19                 // Method java/lang/StringBuilder.append:(Ljava/lang/String;)Ljava/lang/StringBuilder;
     152: pop
     153: aload_1
     154: ldc           #28                 // String }
     156: invokevirtual #19                 // Method java/lang/StringBuilder.append:(Ljava/lang/String;)Ljava/lang/StringBuilder;
     159: pop
     160: aload_1
     161: invokevirtual #29                 // Method java/lang/StringBuilder.toString:()Ljava/lang/String;
     164: areturn

  private java.lang.String toIndentedString(java.lang.Object);
    Code:
       0: aload_1
       1: ifnonnull     7
       4: ldc           #30                 // String null
       6: areturn
       7: aload_1
       8: invokevirtual #31                 // Method java/lang/Object.toString:()Ljava/lang/String;
      11: ldc           #22                 // String \n
      13: ldc           #32                 // String \n
      15: invokevirtual #33                 // Method java/lang/String.replace:(Ljava/lang/CharSequence;Ljava/lang/CharSequence;)Ljava/lang/String;
      18: areturn
}
