Compiled from "V1InitializersFluentImpl.java"
public class io.kubernetes.client.openapi.models.V1InitializersFluentImpl$PendingNestedImpl<N> extends io.kubernetes.client.openapi.models.V1InitializerFluentImpl<io.kubernetes.client.openapi.models.V1InitializersFluent$PendingNested<N>> implements io.kubernetes.client.openapi.models.V1InitializersFluent$PendingNested<N>, io.kubernetes.client.fluent.Nested<N> {
  private final io.kubernetes.client.openapi.models.V1InitializerBuilder builder;

  private final int index;

  final io.kubernetes.client.openapi.models.V1InitializersFluentImpl this$0;

  io.kubernetes.client.openapi.models.V1InitializersFluentImpl$PendingNestedImpl(io.kubernetes.client.openapi.models.V1InitializersFluentImpl, int, io.kubernetes.client.openapi.models.V1Initializer);
    Code:
       0: aload_0
       1: aload_1
       2: putfield      #1                  // Field this$0:Lio/kubernetes/client/openapi/models/V1InitializersFluentImpl;
       5: aload_0
       6: invokespecial #2                  // Method io/kubernetes/client/openapi/models/V1InitializerFluentImpl."<init>":()V
       9: aload_0
      10: iload_2
      11: putfield      #3                  // Field index:I
      14: aload_0
      15: new           #4                  // class io/kubernetes/client/openapi/models/V1InitializerBuilder
      18: dup
      19: aload_0
      20: aload_3
      21: invokespecial #5                  // Method io/kubernetes/client/openapi/models/V1InitializerBuilder."<init>":(Lio/kubernetes/client/openapi/models/V1InitializerFluent;Lio/kubernetes/client/openapi/models/V1Initializer;)V
      24: putfield      #6                  // Field builder:Lio/kubernetes/client/openapi/models/V1InitializerBuilder;
      27: return

  io.kubernetes.client.openapi.models.V1InitializersFluentImpl$PendingNestedImpl(io.kubernetes.client.openapi.models.V1InitializersFluentImpl);
    Code:
       0: aload_0
       1: aload_1
       2: putfield      #1                  // Field this$0:Lio/kubernetes/client/openapi/models/V1InitializersFluentImpl;
       5: aload_0
       6: invokespecial #2                  // Method io/kubernetes/client/openapi/models/V1InitializerFluentImpl."<init>":()V
       9: aload_0
      10: iconst_m1
      11: putfield      #3                  // Field index:I
      14: aload_0
      15: new           #4                  // class io/kubernetes/client/openapi/models/V1InitializerBuilder
      18: dup
      19: aload_0
      20: invokespecial #7                  // Method io/kubernetes/client/openapi/models/V1InitializerBuilder."<init>":(Lio/kubernetes/client/openapi/models/V1InitializerFluent;)V
      23: putfield      #6                  // Field builder:Lio/kubernetes/client/openapi/models/V1InitializerBuilder;
      26: return

  public N and();
    Code:
       0: aload_0
       1: getfield      #1                  // Field this$0:Lio/kubernetes/client/openapi/models/V1InitializersFluentImpl;
       4: aload_0
       5: getfield      #3                  // Field index:I
       8: aload_0
       9: getfield      #6                  // Field builder:Lio/kubernetes/client/openapi/models/V1InitializerBuilder;
      12: invokevirtual #8                  // Method io/kubernetes/client/openapi/models/V1InitializerBuilder.build:()Lio/kubernetes/client/openapi/models/V1Initializer;
      15: invokevirtual #9                  // Method io/kubernetes/client/openapi/models/V1InitializersFluentImpl.setToPending:(ILio/kubernetes/client/openapi/models/V1Initializer;)Lio/kubernetes/client/openapi/models/V1InitializersFluent;
      18: areturn

  public N endPending();
    Code:
       0: aload_0
       1: invokevirtual #10                 // Method and:()Ljava/lang/Object;
       4: areturn
}
