Compiled from "V1ReplicationControllerFluentImpl.java"
public class io.kubernetes.client.openapi.models.V1ReplicationControllerFluentImpl$SpecNestedImpl<N> extends io.kubernetes.client.openapi.models.V1ReplicationControllerSpecFluentImpl<io.kubernetes.client.openapi.models.V1ReplicationControllerFluent$SpecNested<N>> implements io.kubernetes.client.openapi.models.V1ReplicationControllerFluent$SpecNested<N>, io.kubernetes.client.fluent.Nested<N> {
  private final io.kubernetes.client.openapi.models.V1ReplicationControllerSpecBuilder builder;

  final io.kubernetes.client.openapi.models.V1ReplicationControllerFluentImpl this$0;

  io.kubernetes.client.openapi.models.V1ReplicationControllerFluentImpl$SpecNestedImpl(io.kubernetes.client.openapi.models.V1ReplicationControllerFluentImpl, io.kubernetes.client.openapi.models.V1ReplicationControllerSpec);
    Code:
       0: aload_0
       1: aload_1
       2: putfield      #1                  // Field this$0:Lio/kubernetes/client/openapi/models/V1ReplicationControllerFluentImpl;
       5: aload_0
       6: invokespecial #2                  // Method io/kubernetes/client/openapi/models/V1ReplicationControllerSpecFluentImpl."<init>":()V
       9: aload_0
      10: new           #3                  // class io/kubernetes/client/openapi/models/V1ReplicationControllerSpecBuilder
      13: dup
      14: aload_0
      15: aload_2
      16: invokespecial #4                  // Method io/kubernetes/client/openapi/models/V1ReplicationControllerSpecBuilder."<init>":(Lio/kubernetes/client/openapi/models/V1ReplicationControllerSpecFluent;Lio/kubernetes/client/openapi/models/V1ReplicationControllerSpec;)V
      19: putfield      #5                  // Field builder:Lio/kubernetes/client/openapi/models/V1ReplicationControllerSpecBuilder;
      22: return

  io.kubernetes.client.openapi.models.V1ReplicationControllerFluentImpl$SpecNestedImpl(io.kubernetes.client.openapi.models.V1ReplicationControllerFluentImpl);
    Code:
       0: aload_0
       1: aload_1
       2: putfield      #1                  // Field this$0:Lio/kubernetes/client/openapi/models/V1ReplicationControllerFluentImpl;
       5: aload_0
       6: invokespecial #2                  // Method io/kubernetes/client/openapi/models/V1ReplicationControllerSpecFluentImpl."<init>":()V
       9: aload_0
      10: new           #3                  // class io/kubernetes/client/openapi/models/V1ReplicationControllerSpecBuilder
      13: dup
      14: aload_0
      15: invokespecial #6                  // Method io/kubernetes/client/openapi/models/V1ReplicationControllerSpecBuilder."<init>":(Lio/kubernetes/client/openapi/models/V1ReplicationControllerSpecFluent;)V
      18: putfield      #5                  // Field builder:Lio/kubernetes/client/openapi/models/V1ReplicationControllerSpecBuilder;
      21: return

  public N and();
    Code:
       0: aload_0
       1: getfield      #1                  // Field this$0:Lio/kubernetes/client/openapi/models/V1ReplicationControllerFluentImpl;
       4: aload_0
       5: getfield      #5                  // Field builder:Lio/kubernetes/client/openapi/models/V1ReplicationControllerSpecBuilder;
       8: invokevirtual #7                  // Method io/kubernetes/client/openapi/models/V1ReplicationControllerSpecBuilder.build:()Lio/kubernetes/client/openapi/models/V1ReplicationControllerSpec;
      11: invokevirtual #8                  // Method io/kubernetes/client/openapi/models/V1ReplicationControllerFluentImpl.withSpec:(Lio/kubernetes/client/openapi/models/V1ReplicationControllerSpec;)Lio/kubernetes/client/openapi/models/V1ReplicationControllerFluent;
      14: areturn

  public N endSpec();
    Code:
       0: aload_0
       1: invokevirtual #9                  // Method and:()Ljava/lang/Object;
       4: areturn
}
