Compiled from "V1StatefulSetSpecFluentImpl.java"
public class io.kubernetes.client.openapi.models.V1StatefulSetSpecFluentImpl$UpdateStrategyNestedImpl<N> extends io.kubernetes.client.openapi.models.V1StatefulSetUpdateStrategyFluentImpl<io.kubernetes.client.openapi.models.V1StatefulSetSpecFluent$UpdateStrategyNested<N>> implements io.kubernetes.client.openapi.models.V1StatefulSetSpecFluent$UpdateStrategyNested<N>, io.kubernetes.client.fluent.Nested<N> {
  private final io.kubernetes.client.openapi.models.V1StatefulSetUpdateStrategyBuilder builder;

  final io.kubernetes.client.openapi.models.V1StatefulSetSpecFluentImpl this$0;

  io.kubernetes.client.openapi.models.V1StatefulSetSpecFluentImpl$UpdateStrategyNestedImpl(io.kubernetes.client.openapi.models.V1StatefulSetSpecFluentImpl, io.kubernetes.client.openapi.models.V1StatefulSetUpdateStrategy);
    Code:
       0: aload_0
       1: aload_1
       2: putfield      #1                  // Field this$0:Lio/kubernetes/client/openapi/models/V1StatefulSetSpecFluentImpl;
       5: aload_0
       6: invokespecial #2                  // Method io/kubernetes/client/openapi/models/V1StatefulSetUpdateStrategyFluentImpl."<init>":()V
       9: aload_0
      10: new           #3                  // class io/kubernetes/client/openapi/models/V1StatefulSetUpdateStrategyBuilder
      13: dup
      14: aload_0
      15: aload_2
      16: invokespecial #4                  // Method io/kubernetes/client/openapi/models/V1StatefulSetUpdateStrategyBuilder."<init>":(Lio/kubernetes/client/openapi/models/V1StatefulSetUpdateStrategyFluent;Lio/kubernetes/client/openapi/models/V1StatefulSetUpdateStrategy;)V
      19: putfield      #5                  // Field builder:Lio/kubernetes/client/openapi/models/V1StatefulSetUpdateStrategyBuilder;
      22: return

  io.kubernetes.client.openapi.models.V1StatefulSetSpecFluentImpl$UpdateStrategyNestedImpl(io.kubernetes.client.openapi.models.V1StatefulSetSpecFluentImpl);
    Code:
       0: aload_0
       1: aload_1
       2: putfield      #1                  // Field this$0:Lio/kubernetes/client/openapi/models/V1StatefulSetSpecFluentImpl;
       5: aload_0
       6: invokespecial #2                  // Method io/kubernetes/client/openapi/models/V1StatefulSetUpdateStrategyFluentImpl."<init>":()V
       9: aload_0
      10: new           #3                  // class io/kubernetes/client/openapi/models/V1StatefulSetUpdateStrategyBuilder
      13: dup
      14: aload_0
      15: invokespecial #6                  // Method io/kubernetes/client/openapi/models/V1StatefulSetUpdateStrategyBuilder."<init>":(Lio/kubernetes/client/openapi/models/V1StatefulSetUpdateStrategyFluent;)V
      18: putfield      #5                  // Field builder:Lio/kubernetes/client/openapi/models/V1StatefulSetUpdateStrategyBuilder;
      21: return

  public N and();
    Code:
       0: aload_0
       1: getfield      #1                  // Field this$0:Lio/kubernetes/client/openapi/models/V1StatefulSetSpecFluentImpl;
       4: aload_0
       5: getfield      #5                  // Field builder:Lio/kubernetes/client/openapi/models/V1StatefulSetUpdateStrategyBuilder;
       8: invokevirtual #7                  // Method io/kubernetes/client/openapi/models/V1StatefulSetUpdateStrategyBuilder.build:()Lio/kubernetes/client/openapi/models/V1StatefulSetUpdateStrategy;
      11: invokevirtual #8                  // Method io/kubernetes/client/openapi/models/V1StatefulSetSpecFluentImpl.withUpdateStrategy:(Lio/kubernetes/client/openapi/models/V1StatefulSetUpdateStrategy;)Lio/kubernetes/client/openapi/models/V1StatefulSetSpecFluent;
      14: areturn

  public N endUpdateStrategy();
    Code:
       0: aload_0
       1: invokevirtual #9                  // Method and:()Ljava/lang/Object;
       4: areturn
}
