Compiled from "V1VolumeProjectionFluentImpl.java"
public class io.kubernetes.client.openapi.models.V1VolumeProjectionFluentImpl$DownwardAPINestedImpl<N> extends io.kubernetes.client.openapi.models.V1DownwardAPIProjectionFluentImpl<io.kubernetes.client.openapi.models.V1VolumeProjectionFluent$DownwardAPINested<N>> implements io.kubernetes.client.openapi.models.V1VolumeProjectionFluent$DownwardAPINested<N>, io.kubernetes.client.fluent.Nested<N> {
  private final io.kubernetes.client.openapi.models.V1DownwardAPIProjectionBuilder builder;

  final io.kubernetes.client.openapi.models.V1VolumeProjectionFluentImpl this$0;

  io.kubernetes.client.openapi.models.V1VolumeProjectionFluentImpl$DownwardAPINestedImpl(io.kubernetes.client.openapi.models.V1VolumeProjectionFluentImpl, io.kubernetes.client.openapi.models.V1DownwardAPIProjection);
    Code:
       0: aload_0
       1: aload_1
       2: putfield      #1                  // Field this$0:Lio/kubernetes/client/openapi/models/V1VolumeProjectionFluentImpl;
       5: aload_0
       6: invokespecial #2                  // Method io/kubernetes/client/openapi/models/V1DownwardAPIProjectionFluentImpl."<init>":()V
       9: aload_0
      10: new           #3                  // class io/kubernetes/client/openapi/models/V1DownwardAPIProjectionBuilder
      13: dup
      14: aload_0
      15: aload_2
      16: invokespecial #4                  // Method io/kubernetes/client/openapi/models/V1DownwardAPIProjectionBuilder."<init>":(Lio/kubernetes/client/openapi/models/V1DownwardAPIProjectionFluent;Lio/kubernetes/client/openapi/models/V1DownwardAPIProjection;)V
      19: putfield      #5                  // Field builder:Lio/kubernetes/client/openapi/models/V1DownwardAPIProjectionBuilder;
      22: return

  io.kubernetes.client.openapi.models.V1VolumeProjectionFluentImpl$DownwardAPINestedImpl(io.kubernetes.client.openapi.models.V1VolumeProjectionFluentImpl);
    Code:
       0: aload_0
       1: aload_1
       2: putfield      #1                  // Field this$0:Lio/kubernetes/client/openapi/models/V1VolumeProjectionFluentImpl;
       5: aload_0
       6: invokespecial #2                  // Method io/kubernetes/client/openapi/models/V1DownwardAPIProjectionFluentImpl."<init>":()V
       9: aload_0
      10: new           #3                  // class io/kubernetes/client/openapi/models/V1DownwardAPIProjectionBuilder
      13: dup
      14: aload_0
      15: invokespecial #6                  // Method io/kubernetes/client/openapi/models/V1DownwardAPIProjectionBuilder."<init>":(Lio/kubernetes/client/openapi/models/V1DownwardAPIProjectionFluent;)V
      18: putfield      #5                  // Field builder:Lio/kubernetes/client/openapi/models/V1DownwardAPIProjectionBuilder;
      21: return

  public N and();
    Code:
       0: aload_0
       1: getfield      #1                  // Field this$0:Lio/kubernetes/client/openapi/models/V1VolumeProjectionFluentImpl;
       4: aload_0
       5: getfield      #5                  // Field builder:Lio/kubernetes/client/openapi/models/V1DownwardAPIProjectionBuilder;
       8: invokevirtual #7                  // Method io/kubernetes/client/openapi/models/V1DownwardAPIProjectionBuilder.build:()Lio/kubernetes/client/openapi/models/V1DownwardAPIProjection;
      11: invokevirtual #8                  // Method io/kubernetes/client/openapi/models/V1VolumeProjectionFluentImpl.withDownwardAPI:(Lio/kubernetes/client/openapi/models/V1DownwardAPIProjection;)Lio/kubernetes/client/openapi/models/V1VolumeProjectionFluent;
      14: areturn

  public N endDownwardAPI();
    Code:
       0: aload_0
       1: invokevirtual #9                  // Method and:()Ljava/lang/Object;
       4: areturn
}
