Compiled from "V2beta1MetricStatusFluentImpl.java"
public class io.kubernetes.client.openapi.models.V2beta1MetricStatusFluentImpl$ExternalNestedImpl<N> extends io.kubernetes.client.openapi.models.V2beta1ExternalMetricStatusFluentImpl<io.kubernetes.client.openapi.models.V2beta1MetricStatusFluent$ExternalNested<N>> implements io.kubernetes.client.openapi.models.V2beta1MetricStatusFluent$ExternalNested<N>, io.kubernetes.client.fluent.Nested<N> {
  private final io.kubernetes.client.openapi.models.V2beta1ExternalMetricStatusBuilder builder;

  final io.kubernetes.client.openapi.models.V2beta1MetricStatusFluentImpl this$0;

  io.kubernetes.client.openapi.models.V2beta1MetricStatusFluentImpl$ExternalNestedImpl(io.kubernetes.client.openapi.models.V2beta1MetricStatusFluentImpl, io.kubernetes.client.openapi.models.V2beta1ExternalMetricStatus);
    Code:
       0: aload_0
       1: aload_1
       2: putfield      #1                  // Field this$0:Lio/kubernetes/client/openapi/models/V2beta1MetricStatusFluentImpl;
       5: aload_0
       6: invokespecial #2                  // Method io/kubernetes/client/openapi/models/V2beta1ExternalMetricStatusFluentImpl."<init>":()V
       9: aload_0
      10: new           #3                  // class io/kubernetes/client/openapi/models/V2beta1ExternalMetricStatusBuilder
      13: dup
      14: aload_0
      15: aload_2
      16: invokespecial #4                  // Method io/kubernetes/client/openapi/models/V2beta1ExternalMetricStatusBuilder."<init>":(Lio/kubernetes/client/openapi/models/V2beta1ExternalMetricStatusFluent;Lio/kubernetes/client/openapi/models/V2beta1ExternalMetricStatus;)V
      19: putfield      #5                  // Field builder:Lio/kubernetes/client/openapi/models/V2beta1ExternalMetricStatusBuilder;
      22: return

  io.kubernetes.client.openapi.models.V2beta1MetricStatusFluentImpl$ExternalNestedImpl(io.kubernetes.client.openapi.models.V2beta1MetricStatusFluentImpl);
    Code:
       0: aload_0
       1: aload_1
       2: putfield      #1                  // Field this$0:Lio/kubernetes/client/openapi/models/V2beta1MetricStatusFluentImpl;
       5: aload_0
       6: invokespecial #2                  // Method io/kubernetes/client/openapi/models/V2beta1ExternalMetricStatusFluentImpl."<init>":()V
       9: aload_0
      10: new           #3                  // class io/kubernetes/client/openapi/models/V2beta1ExternalMetricStatusBuilder
      13: dup
      14: aload_0
      15: invokespecial #6                  // Method io/kubernetes/client/openapi/models/V2beta1ExternalMetricStatusBuilder."<init>":(Lio/kubernetes/client/openapi/models/V2beta1ExternalMetricStatusFluent;)V
      18: putfield      #5                  // Field builder:Lio/kubernetes/client/openapi/models/V2beta1ExternalMetricStatusBuilder;
      21: return

  public N and();
    Code:
       0: aload_0
       1: getfield      #1                  // Field this$0:Lio/kubernetes/client/openapi/models/V2beta1MetricStatusFluentImpl;
       4: aload_0
       5: getfield      #5                  // Field builder:Lio/kubernetes/client/openapi/models/V2beta1ExternalMetricStatusBuilder;
       8: invokevirtual #7                  // Method io/kubernetes/client/openapi/models/V2beta1ExternalMetricStatusBuilder.build:()Lio/kubernetes/client/openapi/models/V2beta1ExternalMetricStatus;
      11: invokevirtual #8                  // Method io/kubernetes/client/openapi/models/V2beta1MetricStatusFluentImpl.withExternal:(Lio/kubernetes/client/openapi/models/V2beta1ExternalMetricStatus;)Lio/kubernetes/client/openapi/models/V2beta1MetricStatusFluent;
      14: areturn

  public N endExternal();
    Code:
       0: aload_0
       1: invokevirtual #9                  // Method and:()Ljava/lang/Object;
       4: areturn
}
