Compiled from "BulkCommands.java"
public abstract class org.elasticsearch.hadoop.serialization.bulk.BulkCommands {
  public org.elasticsearch.hadoop.serialization.bulk.BulkCommands();
    Code:
       0: aload_0
       1: invokespecial #1                  // Method java/lang/Object."<init>":()V
       4: return

  public static org.elasticsearch.hadoop.serialization.bulk.BulkCommand create(org.elasticsearch.hadoop.cfg.Settings, org.elasticsearch.hadoop.serialization.bulk.MetadataExtractor, org.elasticsearch.hadoop.util.EsMajorVersion);
    Code:
       0: aload_0
       1: invokevirtual #7                  // Method org/elasticsearch/hadoop/cfg/Settings.getOperation:()Ljava/lang/String;
       4: astore_3
       5: aconst_null
       6: astore        4
       8: ldc           #15                 // String create
      10: aload_3
      11: invokevirtual #17                 // Method java/lang/String.equals:(Ljava/lang/Object;)Z
      14: ifeq          32
      17: new           #23                 // class org/elasticsearch/hadoop/serialization/bulk/CreateBulkFactory
      20: dup
      21: aload_0
      22: aload_1
      23: aload_2
      24: invokespecial #25                 // Method org/elasticsearch/hadoop/serialization/bulk/CreateBulkFactory."<init>":(Lorg/elasticsearch/hadoop/cfg/Settings;Lorg/elasticsearch/hadoop/serialization/bulk/MetadataExtractor;Lorg/elasticsearch/hadoop/util/EsMajorVersion;)V
      27: astore        4
      29: goto          156
      32: ldc           #28                 // String index
      34: aload_3
      35: invokevirtual #17                 // Method java/lang/String.equals:(Ljava/lang/Object;)Z
      38: ifeq          56
      41: new           #30                 // class org/elasticsearch/hadoop/serialization/bulk/IndexBulkFactory
      44: dup
      45: aload_0
      46: aload_1
      47: aload_2
      48: invokespecial #32                 // Method org/elasticsearch/hadoop/serialization/bulk/IndexBulkFactory."<init>":(Lorg/elasticsearch/hadoop/cfg/Settings;Lorg/elasticsearch/hadoop/serialization/bulk/MetadataExtractor;Lorg/elasticsearch/hadoop/util/EsMajorVersion;)V
      51: astore        4
      53: goto          156
      56: ldc           #33                 // String update
      58: aload_3
      59: invokevirtual #17                 // Method java/lang/String.equals:(Ljava/lang/Object;)Z
      62: ifeq          80
      65: new           #35                 // class org/elasticsearch/hadoop/serialization/bulk/UpdateBulkFactory
      68: dup
      69: aload_0
      70: aload_1
      71: aload_2
      72: invokespecial #37                 // Method org/elasticsearch/hadoop/serialization/bulk/UpdateBulkFactory."<init>":(Lorg/elasticsearch/hadoop/cfg/Settings;Lorg/elasticsearch/hadoop/serialization/bulk/MetadataExtractor;Lorg/elasticsearch/hadoop/util/EsMajorVersion;)V
      75: astore        4
      77: goto          156
      80: ldc           #38                 // String upsert
      82: aload_3
      83: invokevirtual #17                 // Method java/lang/String.equals:(Ljava/lang/Object;)Z
      86: ifeq          105
      89: new           #35                 // class org/elasticsearch/hadoop/serialization/bulk/UpdateBulkFactory
      92: dup
      93: aload_0
      94: iconst_1
      95: aload_1
      96: aload_2
      97: invokespecial #40                 // Method org/elasticsearch/hadoop/serialization/bulk/UpdateBulkFactory."<init>":(Lorg/elasticsearch/hadoop/cfg/Settings;ZLorg/elasticsearch/hadoop/serialization/bulk/MetadataExtractor;Lorg/elasticsearch/hadoop/util/EsMajorVersion;)V
     100: astore        4
     102: goto          156
     105: ldc           #43                 // String delete
     107: aload_3
     108: invokevirtual #17                 // Method java/lang/String.equals:(Ljava/lang/Object;)Z
     111: ifeq          129
     114: new           #45                 // class org/elasticsearch/hadoop/serialization/bulk/DeleteBulkFactory
     117: dup
     118: aload_0
     119: aload_1
     120: aload_2
     121: invokespecial #47                 // Method org/elasticsearch/hadoop/serialization/bulk/DeleteBulkFactory."<init>":(Lorg/elasticsearch/hadoop/cfg/Settings;Lorg/elasticsearch/hadoop/serialization/bulk/MetadataExtractor;Lorg/elasticsearch/hadoop/util/EsMajorVersion;)V
     124: astore        4
     126: goto          156
     129: new           #48                 // class org/elasticsearch/hadoop/EsHadoopIllegalArgumentException
     132: dup
     133: new           #50                 // class java/lang/StringBuilder
     136: dup
     137: invokespecial #52                 // Method java/lang/StringBuilder."<init>":()V
     140: ldc           #53                 // String Unsupported bulk operation
     142: invokevirtual #55                 // Method java/lang/StringBuilder.append:(Ljava/lang/String;)Ljava/lang/StringBuilder;
     145: aload_3
     146: invokevirtual #55                 // Method java/lang/StringBuilder.append:(Ljava/lang/String;)Ljava/lang/StringBuilder;
     149: invokevirtual #59                 // Method java/lang/StringBuilder.toString:()Ljava/lang/String;
     152: invokespecial #62                 // Method org/elasticsearch/hadoop/EsHadoopIllegalArgumentException."<init>":(Ljava/lang/String;)V
     155: athrow
     156: aload         4
     158: invokeinterface #65,  1           // InterfaceMethod org/elasticsearch/hadoop/serialization/bulk/BulkFactory.createBulk:()Lorg/elasticsearch/hadoop/serialization/bulk/BulkCommand;
     163: areturn
}
