Compiled from "PerEntityPoolingMetadataExtractor.java"
class org.elasticsearch.hadoop.serialization.bulk.PerEntityPoolingMetadataExtractor$UnsupportedMetadataFieldExtractor extends org.elasticsearch.hadoop.serialization.bulk.PerEntityPoolingMetadataExtractor$StaticFieldExtractor {
  private org.elasticsearch.hadoop.serialization.bulk.MetadataExtractor$Metadata unsupportedMetadata;

  private org.elasticsearch.hadoop.util.EsMajorVersion version;

  public org.elasticsearch.hadoop.serialization.bulk.PerEntityPoolingMetadataExtractor$UnsupportedMetadataFieldExtractor(org.elasticsearch.hadoop.serialization.bulk.MetadataExtractor$Metadata, org.elasticsearch.hadoop.util.EsMajorVersion);
    Code:
       0: aload_0
       1: invokespecial #1                  // Method org/elasticsearch/hadoop/serialization/bulk/PerEntityPoolingMetadataExtractor$StaticFieldExtractor."<init>":()V
       4: aload_0
       5: aload_1
       6: putfield      #7                  // Field unsupportedMetadata:Lorg/elasticsearch/hadoop/serialization/bulk/MetadataExtractor$Metadata;
       9: aload_0
      10: aload_2
      11: putfield      #13                 // Field version:Lorg/elasticsearch/hadoop/util/EsMajorVersion;
      14: return

  public java.lang.Object field(java.lang.Object);
    Code:
       0: new           #17                 // class org/elasticsearch/hadoop/EsHadoopUnsupportedOperationException
       3: dup
       4: new           #19                 // class java/lang/StringBuilder
       7: dup
       8: invokespecial #21                 // Method java/lang/StringBuilder."<init>":()V
      11: ldc           #22                 // String Unsupported metadata tag [
      13: invokevirtual #24                 // Method java/lang/StringBuilder.append:(Ljava/lang/String;)Ljava/lang/StringBuilder;
      16: aload_0
      17: getfield      #7                  // Field unsupportedMetadata:Lorg/elasticsearch/hadoop/serialization/bulk/MetadataExtractor$Metadata;
      20: invokevirtual #28                 // Method org/elasticsearch/hadoop/serialization/bulk/MetadataExtractor$Metadata.getName:()Ljava/lang/String;
      23: invokevirtual #24                 // Method java/lang/StringBuilder.append:(Ljava/lang/String;)Ljava/lang/StringBuilder;
      26: ldc           #34                 // String ] for Elasticsearch version [
      28: invokevirtual #24                 // Method java/lang/StringBuilder.append:(Ljava/lang/String;)Ljava/lang/StringBuilder;
      31: aload_0
      32: getfield      #13                 // Field version:Lorg/elasticsearch/hadoop/util/EsMajorVersion;
      35: invokevirtual #36                 // Method org/elasticsearch/hadoop/util/EsMajorVersion.toString:()Ljava/lang/String;
      38: invokevirtual #24                 // Method java/lang/StringBuilder.append:(Ljava/lang/String;)Ljava/lang/StringBuilder;
      41: ldc           #41                 // String ]. Bailing out...
      43: invokevirtual #24                 // Method java/lang/StringBuilder.append:(Ljava/lang/String;)Ljava/lang/StringBuilder;
      46: invokevirtual #43                 // Method java/lang/StringBuilder.toString:()Ljava/lang/String;
      49: invokespecial #44                 // Method org/elasticsearch/hadoop/EsHadoopUnsupportedOperationException."<init>":(Ljava/lang/String;)V
      52: athrow
}
