Compiled from "JBossAppMetaData.java"
public class org.jboss.metadata.ear.jboss.JBossAppMetaData extends org.jboss.metadata.ear.spec.EarMetaData {
  private static final long serialVersionUID;

  private java.lang.String securityDomain;

  private java.lang.String unauthenticatedPrincipal;

  private java.lang.String distinctName;

  public org.jboss.metadata.ear.jboss.JBossAppMetaData();
    Code:
       0: aload_0
       1: getstatic     #1                  // Field org/jboss/metadata/ear/spec/EarVersion.APP_7_0:Lorg/jboss/metadata/ear/spec/EarVersion;
       4: invokespecial #2                  // Method org/jboss/metadata/ear/spec/EarMetaData."<init>":(Lorg/jboss/metadata/ear/spec/EarVersion;)V
       7: return

  public org.jboss.metadata.ear.jboss.JBossAppMetaData(org.jboss.metadata.ear.spec.EarVersion);
    Code:
       0: aload_0
       1: aload_1
       2: invokespecial #2                  // Method org/jboss/metadata/ear/spec/EarMetaData."<init>":(Lorg/jboss/metadata/ear/spec/EarVersion;)V
       5: return

  public java.lang.String getSecurityDomain();
    Code:
       0: aload_0
       1: getfield      #3                  // Field securityDomain:Ljava/lang/String;
       4: areturn

  public void setSecurityDomain(java.lang.String);
    Code:
       0: aload_0
       1: aload_1
       2: putfield      #3                  // Field securityDomain:Ljava/lang/String;
       5: return

  public java.lang.String getUnauthenticatedPrincipal();
    Code:
       0: aload_0
       1: getfield      #4                  // Field unauthenticatedPrincipal:Ljava/lang/String;
       4: areturn

  public void setUnauthenticatedPrincipal(java.lang.String);
    Code:
       0: aload_0
       1: aload_1
       2: putfield      #4                  // Field unauthenticatedPrincipal:Ljava/lang/String;
       5: return

  public void setDistinctName(java.lang.String);
    Code:
       0: aload_0
       1: aload_1
       2: putfield      #5                  // Field distinctName:Ljava/lang/String;
       5: return

  public java.lang.String getDistinctName();
    Code:
       0: aload_0
       1: getfield      #5                  // Field distinctName:Ljava/lang/String;
       4: areturn
}
