Compiled from "ModelPerformance.java"
final class software.amazon.awssdk.services.lookoutvision.model.ModelPerformance$BuilderImpl implements software.amazon.awssdk.services.lookoutvision.model.ModelPerformance$Builder {
  private java.lang.Float f1Score;

  private java.lang.Float recall;

  private java.lang.Float precision;

  private software.amazon.awssdk.services.lookoutvision.model.ModelPerformance$BuilderImpl();
    Code:
       0: aload_0
       1: invokespecial #6                  // Method java/lang/Object."<init>":()V
       4: return

  private software.amazon.awssdk.services.lookoutvision.model.ModelPerformance$BuilderImpl(software.amazon.awssdk.services.lookoutvision.model.ModelPerformance);
    Code:
       0: aload_0
       1: invokespecial #6                  // Method java/lang/Object."<init>":()V
       4: aload_0
       5: aload_1
       6: invokestatic  #7                  // Method software/amazon/awssdk/services/lookoutvision/model/ModelPerformance.access$500:(Lsoftware/amazon/awssdk/services/lookoutvision/model/ModelPerformance;)Ljava/lang/Float;
       9: invokevirtual #8                  // Method f1Score:(Ljava/lang/Float;)Lsoftware/amazon/awssdk/services/lookoutvision/model/ModelPerformance$Builder;
      12: pop
      13: aload_0
      14: aload_1
      15: invokestatic  #9                  // Method software/amazon/awssdk/services/lookoutvision/model/ModelPerformance.access$600:(Lsoftware/amazon/awssdk/services/lookoutvision/model/ModelPerformance;)Ljava/lang/Float;
      18: invokevirtual #10                 // Method recall:(Ljava/lang/Float;)Lsoftware/amazon/awssdk/services/lookoutvision/model/ModelPerformance$Builder;
      21: pop
      22: aload_0
      23: aload_1
      24: invokestatic  #11                 // Method software/amazon/awssdk/services/lookoutvision/model/ModelPerformance.access$700:(Lsoftware/amazon/awssdk/services/lookoutvision/model/ModelPerformance;)Ljava/lang/Float;
      27: invokevirtual #12                 // Method precision:(Ljava/lang/Float;)Lsoftware/amazon/awssdk/services/lookoutvision/model/ModelPerformance$Builder;
      30: pop
      31: return

  public final java.lang.Float getF1Score();
    Code:
       0: aload_0
       1: getfield      #5                  // Field f1Score:Ljava/lang/Float;
       4: areturn

  public final void setF1Score(java.lang.Float);
    Code:
       0: aload_0
       1: aload_1
       2: putfield      #5                  // Field f1Score:Ljava/lang/Float;
       5: return

  public final software.amazon.awssdk.services.lookoutvision.model.ModelPerformance$Builder f1Score(java.lang.Float);
    Code:
       0: aload_0
       1: aload_1
       2: putfield      #5                  // Field f1Score:Ljava/lang/Float;
       5: aload_0
       6: areturn

  public final java.lang.Float getRecall();
    Code:
       0: aload_0
       1: getfield      #4                  // Field recall:Ljava/lang/Float;
       4: areturn

  public final void setRecall(java.lang.Float);
    Code:
       0: aload_0
       1: aload_1
       2: putfield      #4                  // Field recall:Ljava/lang/Float;
       5: return

  public final software.amazon.awssdk.services.lookoutvision.model.ModelPerformance$Builder recall(java.lang.Float);
    Code:
       0: aload_0
       1: aload_1
       2: putfield      #4                  // Field recall:Ljava/lang/Float;
       5: aload_0
       6: areturn

  public final java.lang.Float getPrecision();
    Code:
       0: aload_0
       1: getfield      #3                  // Field precision:Ljava/lang/Float;
       4: areturn

  public final void setPrecision(java.lang.Float);
    Code:
       0: aload_0
       1: aload_1
       2: putfield      #3                  // Field precision:Ljava/lang/Float;
       5: return

  public final software.amazon.awssdk.services.lookoutvision.model.ModelPerformance$Builder precision(java.lang.Float);
    Code:
       0: aload_0
       1: aload_1
       2: putfield      #3                  // Field precision:Ljava/lang/Float;
       5: aload_0
       6: areturn

  public software.amazon.awssdk.services.lookoutvision.model.ModelPerformance build();
    Code:
       0: new           #13                 // class software/amazon/awssdk/services/lookoutvision/model/ModelPerformance
       3: dup
       4: aload_0
       5: aconst_null
       6: invokespecial #14                 // Method software/amazon/awssdk/services/lookoutvision/model/ModelPerformance."<init>":(Lsoftware/amazon/awssdk/services/lookoutvision/model/ModelPerformance$BuilderImpl;Lsoftware/amazon/awssdk/services/lookoutvision/model/ModelPerformance$1;)V
       9: areturn

  public java.util.List<software.amazon.awssdk.core.SdkField<?>> sdkFields();
    Code:
       0: invokestatic  #15                 // Method software/amazon/awssdk/services/lookoutvision/model/ModelPerformance.access$900:()Ljava/util/List;
       3: areturn

  public java.lang.Object build();
    Code:
       0: aload_0
       1: invokevirtual #16                 // Method build:()Lsoftware/amazon/awssdk/services/lookoutvision/model/ModelPerformance;
       4: areturn

  static java.lang.Float access$000(software.amazon.awssdk.services.lookoutvision.model.ModelPerformance$BuilderImpl);
    Code:
       0: aload_0
       1: getfield      #5                  // Field f1Score:Ljava/lang/Float;
       4: areturn

  static java.lang.Float access$100(software.amazon.awssdk.services.lookoutvision.model.ModelPerformance$BuilderImpl);
    Code:
       0: aload_0
       1: getfield      #4                  // Field recall:Ljava/lang/Float;
       4: areturn

  static java.lang.Float access$200(software.amazon.awssdk.services.lookoutvision.model.ModelPerformance$BuilderImpl);
    Code:
       0: aload_0
       1: getfield      #3                  // Field precision:Ljava/lang/Float;
       4: areturn

  software.amazon.awssdk.services.lookoutvision.model.ModelPerformance$BuilderImpl(software.amazon.awssdk.services.lookoutvision.model.ModelPerformance, software.amazon.awssdk.services.lookoutvision.model.ModelPerformance$1);
    Code:
       0: aload_0
       1: aload_1
       2: invokespecial #2                  // Method "<init>":(Lsoftware/amazon/awssdk/services/lookoutvision/model/ModelPerformance;)V
       5: return

  software.amazon.awssdk.services.lookoutvision.model.ModelPerformance$BuilderImpl(software.amazon.awssdk.services.lookoutvision.model.ModelPerformance$1);
    Code:
       0: aload_0
       1: invokespecial #1                  // Method "<init>":()V
       4: return
}
