Compiled from "BinaryStreamImpl.java"
public class org.hibernate.engine.jdbc.internal.BinaryStreamImpl extends java.io.ByteArrayInputStream implements org.hibernate.engine.jdbc.BinaryStream {
  private final int length;

  public org.hibernate.engine.jdbc.internal.BinaryStreamImpl(byte[]);
    Code:
       0: aload_0
       1: aload_1
       2: invokespecial #1                  // Method java/io/ByteArrayInputStream."<init>":([B)V
       5: aload_0
       6: aload_1
       7: arraylength
       8: putfield      #2                  // Field length:I
      11: return

  public java.io.InputStream getInputStream();
    Code:
       0: aload_0
       1: areturn

  public byte[] getBytes();
    Code:
       0: aload_0
       1: getfield      #3                  // Field buf:[B
       4: areturn

  public long getLength();
    Code:
       0: aload_0
       1: getfield      #2                  // Field length:I
       4: i2l
       5: lreturn

  public void release();
    Code:
       0: aload_0
       1: invokespecial #4                  // Method java/io/ByteArrayInputStream.close:()V
       4: goto          8
       7: astore_1
       8: return
    Exception table:
       from    to  target type
           0     4     7   Class java/io/IOException
}
