Compiled from "ReadTimeoutTestCase.java"
class io.undertow.server.ReadTimeoutTestCase$2 extends org.apache.http.entity.AbstractHttpEntity {
  final io.undertow.server.ReadTimeoutTestCase this$0;

  io.undertow.server.ReadTimeoutTestCase$2(io.undertow.server.ReadTimeoutTestCase);
    Code:
       0: aload_0
       1: aload_1
       2: putfield      #1                  // Field this$0:Lio/undertow/server/ReadTimeoutTestCase;
       5: aload_0
       6: invokespecial #2                  // Method org/apache/http/entity/AbstractHttpEntity."<init>":()V
       9: return

  public java.io.InputStream getContent() throws java.io.IOException, java.lang.IllegalStateException;
    Code:
       0: aconst_null
       1: areturn

  public void writeTo(java.io.OutputStream) throws java.io.IOException;
    Code:
       0: iconst_0
       1: istore_2
       2: iload_2
       3: iconst_5
       4: if_icmpge     42
       7: aload_1
       8: bipush        42
      10: invokevirtual #3                  // Method java/io/OutputStream.write:(I)V
      13: aload_1
      14: invokevirtual #4                  // Method java/io/OutputStream.flush:()V
      17: ldc2_w        #5                  // long 200l
      20: invokestatic  #7                  // Method java/lang/Thread.sleep:(J)V
      23: goto          36
      26: astore_3
      27: new           #9                  // class java/lang/RuntimeException
      30: dup
      31: aload_3
      32: invokespecial #10                 // Method java/lang/RuntimeException."<init>":(Ljava/lang/Throwable;)V
      35: athrow
      36: iinc          2, 1
      39: goto          2
      42: return
    Exception table:
       from    to  target type
          17    23    26   Class java/lang/InterruptedException

  public boolean isStreaming();
    Code:
       0: iconst_1
       1: ireturn

  public boolean isRepeatable();
    Code:
       0: iconst_0
       1: ireturn

  public long getContentLength();
    Code:
       0: ldc2_w        #11                 // long 5l
       3: lreturn
}
