Compiled from "BindingsEndpoint.java"
public class org.springframework.cloud.stream.endpoint.BindingsEndpoint {
  private final java.util.List<org.springframework.cloud.stream.binding.InputBindingLifecycle> inputBindingLifecycles;

  private final java.util.List<org.springframework.cloud.stream.binding.OutputBindingLifecycle> outputBindingsLifecycles;

  private final com.fasterxml.jackson.databind.ObjectMapper objectMapper;

  public org.springframework.cloud.stream.endpoint.BindingsEndpoint(java.util.List<org.springframework.cloud.stream.binding.InputBindingLifecycle>, java.util.List<org.springframework.cloud.stream.binding.OutputBindingLifecycle>);
    Code:
       0: aload_0
       1: invokespecial #1                  // Method java/lang/Object."<init>":()V
       4: aload_1
       5: ldc           #2                  // String \'inputBindingLifecycles\' must not be null or empty
       7: invokestatic  #3                  // Method org/springframework/util/Assert.notEmpty:(Ljava/util/Collection;Ljava/lang/String;)V
      10: aload_0
      11: aload_1
      12: putfield      #4                  // Field inputBindingLifecycles:Ljava/util/List;
      15: aload_0
      16: aload_2
      17: putfield      #5                  // Field outputBindingsLifecycles:Ljava/util/List;
      20: aload_0
      21: new           #6                  // class com/fasterxml/jackson/databind/ObjectMapper
      24: dup
      25: invokespecial #7                  // Method com/fasterxml/jackson/databind/ObjectMapper."<init>":()V
      28: putfield      #8                  // Field objectMapper:Lcom/fasterxml/jackson/databind/ObjectMapper;
      31: return

  public void changeState(java.lang.String, org.springframework.cloud.stream.endpoint.BindingsEndpoint$State);
    Code:
       0: aload_0
       1: aload_1
       2: invokespecial #9                  // Method locateBinding:(Ljava/lang/String;)Lorg/springframework/cloud/stream/binder/Binding;
       5: astore_3
       6: aload_3
       7: ifnull        84
      10: getstatic     #10                 // Field org/springframework/cloud/stream/endpoint/BindingsEndpoint$1.$SwitchMap$org$springframework$cloud$stream$endpoint$BindingsEndpoint$State:[I
      13: aload_2
      14: invokevirtual #11                 // Method org/springframework/cloud/stream/endpoint/BindingsEndpoint$State.ordinal:()I
      17: iaload
      18: tableswitch   { // 1 to 4
                     1: 48
                     2: 57
                     3: 66
                     4: 75
               default: 84
          }
      48: aload_3
      49: invokeinterface #12,  1           // InterfaceMethod org/springframework/cloud/stream/binder/Binding.start:()V
      54: goto          84
      57: aload_3
      58: invokeinterface #13,  1           // InterfaceMethod org/springframework/cloud/stream/binder/Binding.stop:()V
      63: goto          84
      66: aload_3
      67: invokeinterface #14,  1           // InterfaceMethod org/springframework/cloud/stream/binder/Binding.pause:()V
      72: goto          84
      75: aload_3
      76: invokeinterface #15,  1           // InterfaceMethod org/springframework/cloud/stream/binder/Binding.resume:()V
      81: goto          84
      84: return

  public java.util.List<?> queryStates();
    Code:
       0: new           #16                 // class java/util/ArrayList
       3: dup
       4: aload_0
       5: invokespecial #17                 // Method gatherInputBindings:()Ljava/util/List;
       8: invokespecial #18                 // Method java/util/ArrayList."<init>":(Ljava/util/Collection;)V
      11: astore_1
      12: aload_1
      13: aload_0
      14: invokespecial #19                 // Method gatherOutputBindings:()Ljava/util/List;
      17: invokeinterface #20,  2           // InterfaceMethod java/util/List.addAll:(Ljava/util/Collection;)Z
      22: pop
      23: aload_0
      24: getfield      #8                  // Field objectMapper:Lcom/fasterxml/jackson/databind/ObjectMapper;
      27: aload_1
      28: ldc           #21                 // class java/util/List
      30: invokevirtual #22                 // Method com/fasterxml/jackson/databind/ObjectMapper.convertValue:(Ljava/lang/Object;Ljava/lang/Class;)Ljava/lang/Object;
      33: checkcast     #21                 // class java/util/List
      36: areturn

  public org.springframework.cloud.stream.binder.Binding<?> queryState(java.lang.String);
    Code:
       0: aload_1
       1: ldc           #23                 // String \'name\' must not be null
       3: invokestatic  #24                 // Method org/springframework/util/Assert.notNull:(Ljava/lang/Object;Ljava/lang/String;)V
       6: aload_0
       7: aload_1
       8: invokespecial #9                  // Method locateBinding:(Ljava/lang/String;)Lorg/springframework/cloud/stream/binder/Binding;
      11: areturn

  private java.util.List<org.springframework.cloud.stream.binder.Binding<?>> gatherInputBindings();
    Code:
       0: new           #16                 // class java/util/ArrayList
       3: dup
       4: invokespecial #25                 // Method java/util/ArrayList."<init>":()V
       7: astore_1
       8: aload_0
       9: getfield      #4                  // Field inputBindingLifecycles:Ljava/util/List;
      12: invokeinterface #26,  1           // InterfaceMethod java/util/List.iterator:()Ljava/util/Iterator;
      17: astore_2
      18: aload_2
      19: invokeinterface #27,  1           // InterfaceMethod java/util/Iterator.hasNext:()Z
      24: ifeq          67
      27: aload_2
      28: invokeinterface #28,  1           // InterfaceMethod java/util/Iterator.next:()Ljava/lang/Object;
      33: checkcast     #29                 // class org/springframework/cloud/stream/binding/InputBindingLifecycle
      36: astore_3
      37: new           #30                 // class org/springframework/beans/DirectFieldAccessor
      40: dup
      41: aload_3
      42: invokespecial #31                 // Method org/springframework/beans/DirectFieldAccessor."<init>":(Ljava/lang/Object;)V
      45: ldc           #32                 // String inputBindings
      47: invokevirtual #33                 // Method org/springframework/beans/DirectFieldAccessor.getPropertyValue:(Ljava/lang/String;)Ljava/lang/Object;
      50: checkcast     #34                 // class java/util/Collection
      53: astore        4
      55: aload_1
      56: aload         4
      58: invokeinterface #20,  2           // InterfaceMethod java/util/List.addAll:(Ljava/util/Collection;)Z
      63: pop
      64: goto          18
      67: aload_1
      68: areturn

  private java.util.List<org.springframework.cloud.stream.binder.Binding<?>> gatherOutputBindings();
    Code:
       0: new           #16                 // class java/util/ArrayList
       3: dup
       4: invokespecial #25                 // Method java/util/ArrayList."<init>":()V
       7: astore_1
       8: aload_0
       9: getfield      #5                  // Field outputBindingsLifecycles:Ljava/util/List;
      12: invokeinterface #26,  1           // InterfaceMethod java/util/List.iterator:()Ljava/util/Iterator;
      17: astore_2
      18: aload_2
      19: invokeinterface #27,  1           // InterfaceMethod java/util/Iterator.hasNext:()Z
      24: ifeq          67
      27: aload_2
      28: invokeinterface #28,  1           // InterfaceMethod java/util/Iterator.next:()Ljava/lang/Object;
      33: checkcast     #35                 // class org/springframework/cloud/stream/binding/OutputBindingLifecycle
      36: astore_3
      37: new           #30                 // class org/springframework/beans/DirectFieldAccessor
      40: dup
      41: aload_3
      42: invokespecial #31                 // Method org/springframework/beans/DirectFieldAccessor."<init>":(Ljava/lang/Object;)V
      45: ldc           #36                 // String outputBindings
      47: invokevirtual #33                 // Method org/springframework/beans/DirectFieldAccessor.getPropertyValue:(Ljava/lang/String;)Ljava/lang/Object;
      50: checkcast     #34                 // class java/util/Collection
      53: astore        4
      55: aload_1
      56: aload         4
      58: invokeinterface #20,  2           // InterfaceMethod java/util/List.addAll:(Ljava/util/Collection;)Z
      63: pop
      64: goto          18
      67: aload_1
      68: areturn

  private org.springframework.cloud.stream.binder.Binding<?> locateBinding(java.lang.String);
    Code:
       0: aload_0
       1: invokespecial #17                 // Method gatherInputBindings:()Ljava/util/List;
       4: invokeinterface #37,  1           // InterfaceMethod java/util/List.stream:()Ljava/util/stream/Stream;
       9: aload_0
      10: invokespecial #19                 // Method gatherOutputBindings:()Ljava/util/List;
      13: invokeinterface #37,  1           // InterfaceMethod java/util/List.stream:()Ljava/util/stream/Stream;
      18: invokestatic  #38                 // InterfaceMethod java/util/stream/Stream.concat:(Ljava/util/stream/Stream;Ljava/util/stream/Stream;)Ljava/util/stream/Stream;
      21: astore_2
      22: aload_2
      23: aload_1
      24: invokedynamic #39,  0             // InvokeDynamic #0:test:(Ljava/lang/String;)Ljava/util/function/Predicate;
      29: invokeinterface #40,  2           // InterfaceMethod java/util/stream/Stream.filter:(Ljava/util/function/Predicate;)Ljava/util/stream/Stream;
      34: invokeinterface #41,  1           // InterfaceMethod java/util/stream/Stream.findFirst:()Ljava/util/Optional;
      39: aconst_null
      40: invokevirtual #42                 // Method java/util/Optional.orElse:(Ljava/lang/Object;)Ljava/lang/Object;
      43: checkcast     #43                 // class org/springframework/cloud/stream/binder/Binding
      46: areturn

  private static boolean lambda$locateBinding$0(java.lang.String, org.springframework.cloud.stream.binder.Binding);
    Code:
       0: aload_0
       1: aload_1
       2: invokeinterface #44,  1           // InterfaceMethod org/springframework/cloud/stream/binder/Binding.getName:()Ljava/lang/String;
       7: invokevirtual #45                 // Method java/lang/String.equals:(Ljava/lang/Object;)Z
      10: ireturn
}
