Compiled from "StandardAuxiliaryDatabaseObjectExporter.java"
public class org.hibernate.tool.schema.internal.StandardAuxiliaryDatabaseObjectExporter implements org.hibernate.tool.schema.spi.Exporter<org.hibernate.boot.model.relational.AuxiliaryDatabaseObject> {
  private final org.hibernate.dialect.Dialect dialect;

  public org.hibernate.tool.schema.internal.StandardAuxiliaryDatabaseObjectExporter(org.hibernate.dialect.Dialect);
    Code:
       0: aload_0
       1: invokespecial #1                  // Method java/lang/Object."<init>":()V
       4: aload_0
       5: aload_1
       6: putfield      #2                  // Field dialect:Lorg/hibernate/dialect/Dialect;
       9: return

  public java.lang.String[] getSqlCreateStrings(org.hibernate.boot.model.relational.AuxiliaryDatabaseObject, org.hibernate.boot.Metadata);
    Code:
       0: aload_1
       1: aload_0
       2: getfield      #2                  // Field dialect:Lorg/hibernate/dialect/Dialect;
       5: invokeinterface #3,  2            // InterfaceMethod org/hibernate/boot/model/relational/AuxiliaryDatabaseObject.sqlCreateStrings:(Lorg/hibernate/dialect/Dialect;)[Ljava/lang/String;
      10: areturn

  public java.lang.String[] getSqlDropStrings(org.hibernate.boot.model.relational.AuxiliaryDatabaseObject, org.hibernate.boot.Metadata);
    Code:
       0: aload_1
       1: aload_0
       2: getfield      #2                  // Field dialect:Lorg/hibernate/dialect/Dialect;
       5: invokeinterface #4,  2            // InterfaceMethod org/hibernate/boot/model/relational/AuxiliaryDatabaseObject.sqlDropStrings:(Lorg/hibernate/dialect/Dialect;)[Ljava/lang/String;
      10: areturn

  public java.lang.String[] getSqlDropStrings(org.hibernate.boot.model.relational.Exportable, org.hibernate.boot.Metadata);
    Code:
       0: aload_0
       1: aload_1
       2: checkcast     #5                  // class org/hibernate/boot/model/relational/AuxiliaryDatabaseObject
       5: aload_2
       6: invokevirtual #6                  // Method getSqlDropStrings:(Lorg/hibernate/boot/model/relational/AuxiliaryDatabaseObject;Lorg/hibernate/boot/Metadata;)[Ljava/lang/String;
       9: areturn

  public java.lang.String[] getSqlCreateStrings(org.hibernate.boot.model.relational.Exportable, org.hibernate.boot.Metadata);
    Code:
       0: aload_0
       1: aload_1
       2: checkcast     #5                  // class org/hibernate/boot/model/relational/AuxiliaryDatabaseObject
       5: aload_2
       6: invokevirtual #7                  // Method getSqlCreateStrings:(Lorg/hibernate/boot/model/relational/AuxiliaryDatabaseObject;Lorg/hibernate/boot/Metadata;)[Ljava/lang/String;
       9: areturn
}
