Compiled from "DefaultBHttpClientConnectionFactory.java"
public class org.apache.http.impl.DefaultBHttpClientConnectionFactory implements org.apache.http.HttpConnectionFactory<org.apache.http.impl.DefaultBHttpClientConnection> {
  public static final org.apache.http.impl.DefaultBHttpClientConnectionFactory INSTANCE;

  private final org.apache.http.config.ConnectionConfig cconfig;

  private final org.apache.http.entity.ContentLengthStrategy incomingContentStrategy;

  private final org.apache.http.entity.ContentLengthStrategy outgoingContentStrategy;

  private final org.apache.http.io.HttpMessageWriterFactory<org.apache.http.HttpRequest> requestWriterFactory;

  private final org.apache.http.io.HttpMessageParserFactory<org.apache.http.HttpResponse> responseParserFactory;

  public org.apache.http.impl.DefaultBHttpClientConnectionFactory(org.apache.http.config.ConnectionConfig, org.apache.http.entity.ContentLengthStrategy, org.apache.http.entity.ContentLengthStrategy, org.apache.http.io.HttpMessageWriterFactory<org.apache.http.HttpRequest>, org.apache.http.io.HttpMessageParserFactory<org.apache.http.HttpResponse>);
    Code:
       0: aload_0
       1: invokespecial #1                  // Method java/lang/Object."<init>":()V
       4: aload_0
       5: aload_1
       6: ifnull        13
       9: aload_1
      10: goto          16
      13: getstatic     #2                  // Field org/apache/http/config/ConnectionConfig.DEFAULT:Lorg/apache/http/config/ConnectionConfig;
      16: putfield      #3                  // Field cconfig:Lorg/apache/http/config/ConnectionConfig;
      19: aload_0
      20: aload_2
      21: putfield      #4                  // Field incomingContentStrategy:Lorg/apache/http/entity/ContentLengthStrategy;
      24: aload_0
      25: aload_3
      26: putfield      #5                  // Field outgoingContentStrategy:Lorg/apache/http/entity/ContentLengthStrategy;
      29: aload_0
      30: aload         4
      32: putfield      #6                  // Field requestWriterFactory:Lorg/apache/http/io/HttpMessageWriterFactory;
      35: aload_0
      36: aload         5
      38: putfield      #7                  // Field responseParserFactory:Lorg/apache/http/io/HttpMessageParserFactory;
      41: return

  public org.apache.http.impl.DefaultBHttpClientConnectionFactory(org.apache.http.config.ConnectionConfig, org.apache.http.io.HttpMessageWriterFactory<org.apache.http.HttpRequest>, org.apache.http.io.HttpMessageParserFactory<org.apache.http.HttpResponse>);
    Code:
       0: aload_0
       1: aload_1
       2: aconst_null
       3: aconst_null
       4: aload_2
       5: aload_3
       6: invokespecial #8                  // Method "<init>":(Lorg/apache/http/config/ConnectionConfig;Lorg/apache/http/entity/ContentLengthStrategy;Lorg/apache/http/entity/ContentLengthStrategy;Lorg/apache/http/io/HttpMessageWriterFactory;Lorg/apache/http/io/HttpMessageParserFactory;)V
       9: return

  public org.apache.http.impl.DefaultBHttpClientConnectionFactory(org.apache.http.config.ConnectionConfig);
    Code:
       0: aload_0
       1: aload_1
       2: aconst_null
       3: aconst_null
       4: aconst_null
       5: aconst_null
       6: invokespecial #8                  // Method "<init>":(Lorg/apache/http/config/ConnectionConfig;Lorg/apache/http/entity/ContentLengthStrategy;Lorg/apache/http/entity/ContentLengthStrategy;Lorg/apache/http/io/HttpMessageWriterFactory;Lorg/apache/http/io/HttpMessageParserFactory;)V
       9: return

  public org.apache.http.impl.DefaultBHttpClientConnectionFactory();
    Code:
       0: aload_0
       1: aconst_null
       2: aconst_null
       3: aconst_null
       4: aconst_null
       5: aconst_null
       6: invokespecial #8                  // Method "<init>":(Lorg/apache/http/config/ConnectionConfig;Lorg/apache/http/entity/ContentLengthStrategy;Lorg/apache/http/entity/ContentLengthStrategy;Lorg/apache/http/io/HttpMessageWriterFactory;Lorg/apache/http/io/HttpMessageParserFactory;)V
       9: return

  public org.apache.http.impl.DefaultBHttpClientConnection createConnection(java.net.Socket) throws java.io.IOException;
    Code:
       0: new           #9                  // class org/apache/http/impl/DefaultBHttpClientConnection
       3: dup
       4: aload_0
       5: getfield      #3                  // Field cconfig:Lorg/apache/http/config/ConnectionConfig;
       8: invokevirtual #10                 // Method org/apache/http/config/ConnectionConfig.getBufferSize:()I
      11: aload_0
      12: getfield      #3                  // Field cconfig:Lorg/apache/http/config/ConnectionConfig;
      15: invokevirtual #11                 // Method org/apache/http/config/ConnectionConfig.getFragmentSizeHint:()I
      18: aload_0
      19: getfield      #3                  // Field cconfig:Lorg/apache/http/config/ConnectionConfig;
      22: invokestatic  #12                 // Method org/apache/http/impl/ConnSupport.createDecoder:(Lorg/apache/http/config/ConnectionConfig;)Ljava/nio/charset/CharsetDecoder;
      25: aload_0
      26: getfield      #3                  // Field cconfig:Lorg/apache/http/config/ConnectionConfig;
      29: invokestatic  #13                 // Method org/apache/http/impl/ConnSupport.createEncoder:(Lorg/apache/http/config/ConnectionConfig;)Ljava/nio/charset/CharsetEncoder;
      32: aload_0
      33: getfield      #3                  // Field cconfig:Lorg/apache/http/config/ConnectionConfig;
      36: invokevirtual #14                 // Method org/apache/http/config/ConnectionConfig.getMessageConstraints:()Lorg/apache/http/config/MessageConstraints;
      39: aload_0
      40: getfield      #4                  // Field incomingContentStrategy:Lorg/apache/http/entity/ContentLengthStrategy;
      43: aload_0
      44: getfield      #5                  // Field outgoingContentStrategy:Lorg/apache/http/entity/ContentLengthStrategy;
      47: aload_0
      48: getfield      #6                  // Field requestWriterFactory:Lorg/apache/http/io/HttpMessageWriterFactory;
      51: aload_0
      52: getfield      #7                  // Field responseParserFactory:Lorg/apache/http/io/HttpMessageParserFactory;
      55: invokespecial #15                 // Method org/apache/http/impl/DefaultBHttpClientConnection."<init>":(IILjava/nio/charset/CharsetDecoder;Ljava/nio/charset/CharsetEncoder;Lorg/apache/http/config/MessageConstraints;Lorg/apache/http/entity/ContentLengthStrategy;Lorg/apache/http/entity/ContentLengthStrategy;Lorg/apache/http/io/HttpMessageWriterFactory;Lorg/apache/http/io/HttpMessageParserFactory;)V
      58: astore_2
      59: aload_2
      60: aload_1
      61: invokevirtual #16                 // Method org/apache/http/impl/DefaultBHttpClientConnection.bind:(Ljava/net/Socket;)V
      64: aload_2
      65: areturn

  public org.apache.http.HttpConnection createConnection(java.net.Socket) throws java.io.IOException;
    Code:
       0: aload_0
       1: aload_1
       2: invokevirtual #17                 // Method createConnection:(Ljava/net/Socket;)Lorg/apache/http/impl/DefaultBHttpClientConnection;
       5: areturn

  static {};
    Code:
       0: new           #18                 // class org/apache/http/impl/DefaultBHttpClientConnectionFactory
       3: dup
       4: invokespecial #19                 // Method "<init>":()V
       7: putstatic     #20                 // Field INSTANCE:Lorg/apache/http/impl/DefaultBHttpClientConnectionFactory;
      10: return
}
