Compiled from "JsonReader.java"
final class zipkin2.internal.gson.stream.JsonReader$1 extends zipkin2.internal.gson.internal.JsonReaderInternalAccess {
  zipkin2.internal.gson.stream.JsonReader$1();
    Code:
       0: aload_0
       1: invokespecial #11                 // Method zipkin2/internal/gson/internal/JsonReaderInternalAccess."<init>":()V
       4: return

  public void promoteNameToValue(zipkin2.internal.gson.stream.JsonReader) throws java.io.IOException;
    Code:
       0: aload_1
       1: instanceof    #19                 // class zipkin2/internal/gson/internal/bind/JsonTreeReader
       4: ifeq          15
       7: aload_1
       8: checkcast     #19                 // class zipkin2/internal/gson/internal/bind/JsonTreeReader
      11: invokevirtual #21                 // Method zipkin2/internal/gson/internal/bind/JsonTreeReader.promoteNameToValue:()V
      14: return
      15: aload_1
      16: getfield      #25                 // Field zipkin2/internal/gson/stream/JsonReader.peeked:I
      19: istore_2
      20: iload_2
      21: ifne          29
      24: aload_1
      25: invokevirtual #29                 // Method zipkin2/internal/gson/stream/JsonReader.doPeek:()I
      28: istore_2
      29: iload_2
      30: bipush        13
      32: if_icmpne     44
      35: aload_1
      36: bipush        9
      38: putfield      #25                 // Field zipkin2/internal/gson/stream/JsonReader.peeked:I
      41: goto          111
      44: iload_2
      45: bipush        12
      47: if_icmpne     59
      50: aload_1
      51: bipush        8
      53: putfield      #25                 // Field zipkin2/internal/gson/stream/JsonReader.peeked:I
      56: goto          111
      59: iload_2
      60: bipush        14
      62: if_icmpne     74
      65: aload_1
      66: bipush        10
      68: putfield      #25                 // Field zipkin2/internal/gson/stream/JsonReader.peeked:I
      71: goto          111
      74: new           #31                 // class java/lang/IllegalStateException
      77: dup
      78: new           #33                 // class java/lang/StringBuilder
      81: dup
      82: invokespecial #34                 // Method java/lang/StringBuilder."<init>":()V
      85: ldc           #36                 // String Expected a name but was
      87: invokevirtual #40                 // Method java/lang/StringBuilder.append:(Ljava/lang/String;)Ljava/lang/StringBuilder;
      90: aload_1
      91: invokevirtual #44                 // Method zipkin2/internal/gson/stream/JsonReader.peek:()Lzipkin2/internal/gson/stream/JsonToken;
      94: invokevirtual #47                 // Method java/lang/StringBuilder.append:(Ljava/lang/Object;)Ljava/lang/StringBuilder;
      97: aload_1
      98: invokevirtual #51                 // Method zipkin2/internal/gson/stream/JsonReader.locationString:()Ljava/lang/String;
     101: invokevirtual #40                 // Method java/lang/StringBuilder.append:(Ljava/lang/String;)Ljava/lang/StringBuilder;
     104: invokevirtual #54                 // Method java/lang/StringBuilder.toString:()Ljava/lang/String;
     107: invokespecial #57                 // Method java/lang/IllegalStateException."<init>":(Ljava/lang/String;)V
     110: athrow
     111: return
}
