Compiled from "HelpButton.java"
public class org.jboss.as.cli.gui.component.HelpButton extends javax.swing.JButton {
  private javax.swing.JScrollPane helpScroller;

  public org.jboss.as.cli.gui.component.HelpButton(java.lang.String);
    Code:
       0: aload_0
       1: ldc           #2                  // String Help
       3: invokespecial #3                  // Method javax/swing/JButton."<init>":(Ljava/lang/String;)V
       6: aload_0
       7: aload_1
       8: invokespecial #4                  // Method readHelpFile:(Ljava/lang/String;)V
      11: goto          39
      14: astore_2
      15: aload_0
      16: new           #6                  // class java/lang/StringBuilder
      19: dup
      20: invokespecial #7                  // Method java/lang/StringBuilder."<init>":()V
      23: ldc           #8                  // String Unable to read
      25: invokevirtual #9                  // Method java/lang/StringBuilder.append:(Ljava/lang/String;)Ljava/lang/StringBuilder;
      28: aload_1
      29: invokevirtual #9                  // Method java/lang/StringBuilder.append:(Ljava/lang/String;)Ljava/lang/StringBuilder;
      32: invokevirtual #10                 // Method java/lang/StringBuilder.toString:()Ljava/lang/String;
      35: invokestatic  #11                 // Method javax/swing/JOptionPane.showMessageDialog:(Ljava/awt/Component;Ljava/lang/Object;)V
      38: return
      39: aload_0
      40: new           #12                 // class org/jboss/as/cli/gui/component/HelpButton$1
      43: dup
      44: aload_0
      45: invokespecial #13                 // Method org/jboss/as/cli/gui/component/HelpButton$1."<init>":(Lorg/jboss/as/cli/gui/component/HelpButton;)V
      48: invokevirtual #14                 // Method addActionListener:(Ljava/awt/event/ActionListener;)V
      51: return
    Exception table:
       from    to  target type
           6    11    14   Class java/io/IOException

  private void readHelpFile(java.lang.String) throws java.io.IOException;
    Code:
       0: aload_0
       1: invokevirtual #15                 // Method java/lang/Object.getClass:()Ljava/lang/Class;
       4: new           #6                  // class java/lang/StringBuilder
       7: dup
       8: invokespecial #7                  // Method java/lang/StringBuilder."<init>":()V
      11: ldc           #16                 // String /help/
      13: invokevirtual #9                  // Method java/lang/StringBuilder.append:(Ljava/lang/String;)Ljava/lang/StringBuilder;
      16: aload_1
      17: invokevirtual #9                  // Method java/lang/StringBuilder.append:(Ljava/lang/String;)Ljava/lang/StringBuilder;
      20: invokevirtual #10                 // Method java/lang/StringBuilder.toString:()Ljava/lang/String;
      23: invokevirtual #17                 // Method java/lang/Class.getResourceAsStream:(Ljava/lang/String;)Ljava/io/InputStream;
      26: astore_2
      27: new           #18                 // class javax/swing/JEditorPane
      30: dup
      31: invokespecial #19                 // Method javax/swing/JEditorPane."<init>":()V
      34: astore_3
      35: aload_3
      36: aload_2
      37: aconst_null
      38: invokevirtual #20                 // Method javax/swing/JEditorPane.read:(Ljava/io/InputStream;Ljava/lang/Object;)V
      41: aload_3
      42: iconst_0
      43: invokevirtual #21                 // Method javax/swing/JEditorPane.setEditable:(Z)V
      46: aload_0
      47: new           #22                 // class javax/swing/JScrollPane
      50: dup
      51: aload_3
      52: invokespecial #23                 // Method javax/swing/JScrollPane."<init>":(Ljava/awt/Component;)V
      55: putfield      #1                  // Field helpScroller:Ljavax/swing/JScrollPane;
      58: return

  static javax.swing.JScrollPane access$000(org.jboss.as.cli.gui.component.HelpButton);
    Code:
       0: aload_0
       1: getfield      #1                  // Field helpScroller:Ljavax/swing/JScrollPane;
       4: areturn
}
