Compiled from "TabsMenu.java"
class org.jboss.as.cli.gui.component.TabsMenu$GoToTabAction extends javax.swing.AbstractAction {
  private int index;

  final org.jboss.as.cli.gui.component.TabsMenu this$0;

  public org.jboss.as.cli.gui.component.TabsMenu$GoToTabAction(org.jboss.as.cli.gui.component.TabsMenu, int, java.lang.String);
    Code:
       0: aload_0
       1: aload_1
       2: putfield      #1                  // Field this$0:Lorg/jboss/as/cli/gui/component/TabsMenu;
       5: aload_0
       6: aload_3
       7: invokespecial #2                  // Method javax/swing/AbstractAction."<init>":(Ljava/lang/String;)V
      10: aload_0
      11: iload_2
      12: putfield      #3                  // Field index:I
      15: return

  public void actionPerformed(java.awt.event.ActionEvent);
    Code:
       0: aload_0
       1: getfield      #1                  // Field this$0:Lorg/jboss/as/cli/gui/component/TabsMenu;
       4: invokestatic  #4                  // Method org/jboss/as/cli/gui/component/TabsMenu.access$100:(Lorg/jboss/as/cli/gui/component/TabsMenu;)Lorg/jboss/as/cli/gui/CliGuiContext;
       7: invokevirtual #5                  // Method org/jboss/as/cli/gui/CliGuiContext.getTabs:()Ljavax/swing/JTabbedPane;
      10: aload_0
      11: getfield      #3                  // Field index:I
      14: invokevirtual #6                  // Method javax/swing/JTabbedPane.setSelectedIndex:(I)V
      17: return
}
