Compiled from "Login.java"
public class org.apache.zookeeper.Login {
  org.apache.log4j.Logger LOG;

  public javax.security.auth.callback.CallbackHandler callbackHandler;

  private static final float TICKET_RENEW_WINDOW;

  private static final float TICKET_RENEW_JITTER;

  private static final long MIN_TIME_BEFORE_RELOGIN;

  private javax.security.auth.Subject subject;

  private java.lang.Thread t;

  private boolean isKrbTicket;

  private boolean isUsingTicketCache;

  private boolean isUsingKeytab;

  private static java.util.Random rng;

  private javax.security.auth.login.LoginContext login;

  private java.lang.String loginContextName;

  private java.lang.String keytabFile;

  private java.lang.String principal;

  private long lastLogin;

  public org.apache.zookeeper.Login(java.lang.String, javax.security.auth.callback.CallbackHandler) throws javax.security.auth.login.LoginException;
    Code:
       0: aload_0
       1: invokespecial #6                  // Method java/lang/Object."<init>":()V
       4: aload_0
       5: ldc_w         #7                  // class org/apache/zookeeper/Login
       8: invokestatic  #8                  // Method org/apache/log4j/Logger.getLogger:(Ljava/lang/Class;)Lorg/apache/log4j/Logger;
      11: putfield      #9                  // Field LOG:Lorg/apache/log4j/Logger;
      14: aload_0
      15: aconst_null
      16: putfield      #10                 // Field subject:Ljavax/security/auth/Subject;
      19: aload_0
      20: aconst_null
      21: putfield      #11                 // Field t:Ljava/lang/Thread;
      24: aload_0
      25: iconst_0
      26: putfield      #12                 // Field isKrbTicket:Z
      29: aload_0
      30: iconst_0
      31: putfield      #3                  // Field isUsingTicketCache:Z
      34: aload_0
      35: iconst_0
      36: putfield      #13                 // Field isUsingKeytab:Z
      39: aload_0
      40: aconst_null
      41: putfield      #14                 // Field login:Ljavax/security/auth/login/LoginContext;
      44: aload_0
      45: aconst_null
      46: putfield      #15                 // Field loginContextName:Ljava/lang/String;
      49: aload_0
      50: aconst_null
      51: putfield      #16                 // Field keytabFile:Ljava/lang/String;
      54: aload_0
      55: aconst_null
      56: putfield      #2                  // Field principal:Ljava/lang/String;
      59: aload_0
      60: lconst_0
      61: putfield      #17                 // Field lastLogin:J
      64: aload_0
      65: aload_2
      66: putfield      #18                 // Field callbackHandler:Ljavax/security/auth/callback/CallbackHandler;
      69: aload_0
      70: aload_0
      71: aload_1
      72: invokespecial #19                 // Method login:(Ljava/lang/String;)Ljavax/security/auth/login/LoginContext;
      75: putfield      #14                 // Field login:Ljavax/security/auth/login/LoginContext;
      78: aload_0
      79: aload_1
      80: putfield      #15                 // Field loginContextName:Ljava/lang/String;
      83: aload_0
      84: aload_0
      85: getfield      #14                 // Field login:Ljavax/security/auth/login/LoginContext;
      88: invokevirtual #20                 // Method javax/security/auth/login/LoginContext.getSubject:()Ljavax/security/auth/Subject;
      91: putfield      #10                 // Field subject:Ljavax/security/auth/Subject;
      94: aload_0
      95: aload_0
      96: getfield      #10                 // Field subject:Ljavax/security/auth/Subject;
      99: ldc_w         #21                 // class javax/security/auth/kerberos/KerberosTicket
     102: invokevirtual #22                 // Method javax/security/auth/Subject.getPrivateCredentials:(Ljava/lang/Class;)Ljava/util/Set;
     105: invokeinterface #23,  1           // InterfaceMethod java/util/Set.isEmpty:()Z
     110: ifne          117
     113: iconst_1
     114: goto          118
     117: iconst_0
     118: putfield      #12                 // Field isKrbTicket:Z
     121: invokestatic  #24                 // Method javax/security/auth/login/Configuration.getConfiguration:()Ljavax/security/auth/login/Configuration;
     124: aload_1
     125: invokevirtual #25                 // Method javax/security/auth/login/Configuration.getAppConfigurationEntry:(Ljava/lang/String;)[Ljavax/security/auth/login/AppConfigurationEntry;
     128: astore_3
     129: aload_3
     130: astore        4
     132: aload         4
     134: arraylength
     135: istore        5
     137: iconst_0
     138: istore        6
     140: iload         6
     142: iload         5
     144: if_icmpge     277
     147: aload         4
     149: iload         6
     151: aaload
     152: astore        7
     154: aload         7
     156: invokevirtual #26                 // Method javax/security/auth/login/AppConfigurationEntry.getOptions:()Ljava/util/Map;
     159: ldc           #27                 // String useTicketCache
     161: invokeinterface #28,  2           // InterfaceMethod java/util/Map.get:(Ljava/lang/Object;)Ljava/lang/Object;
     166: ifnull        201
     169: aload         7
     171: invokevirtual #26                 // Method javax/security/auth/login/AppConfigurationEntry.getOptions:()Ljava/util/Map;
     174: ldc           #27                 // String useTicketCache
     176: invokeinterface #28,  2           // InterfaceMethod java/util/Map.get:(Ljava/lang/Object;)Ljava/lang/Object;
     181: checkcast     #29                 // class java/lang/String
     184: astore        8
     186: aload         8
     188: ldc           #30                 // String true
     190: invokevirtual #31                 // Method java/lang/String.equals:(Ljava/lang/Object;)Z
     193: ifeq          201
     196: aload_0
     197: iconst_1
     198: putfield      #3                  // Field isUsingTicketCache:Z
     201: aload         7
     203: invokevirtual #26                 // Method javax/security/auth/login/AppConfigurationEntry.getOptions:()Ljava/util/Map;
     206: ldc           #32                 // String keyTab
     208: invokeinterface #28,  2           // InterfaceMethod java/util/Map.get:(Ljava/lang/Object;)Ljava/lang/Object;
     213: ifnull        240
     216: aload_0
     217: aload         7
     219: invokevirtual #26                 // Method javax/security/auth/login/AppConfigurationEntry.getOptions:()Ljava/util/Map;
     222: ldc           #32                 // String keyTab
     224: invokeinterface #28,  2           // InterfaceMethod java/util/Map.get:(Ljava/lang/Object;)Ljava/lang/Object;
     229: checkcast     #29                 // class java/lang/String
     232: putfield      #16                 // Field keytabFile:Ljava/lang/String;
     235: aload_0
     236: iconst_1
     237: putfield      #13                 // Field isUsingKeytab:Z
     240: aload         7
     242: invokevirtual #26                 // Method javax/security/auth/login/AppConfigurationEntry.getOptions:()Ljava/util/Map;
     245: ldc           #33                 // String principal
     247: invokeinterface #28,  2           // InterfaceMethod java/util/Map.get:(Ljava/lang/Object;)Ljava/lang/Object;
     252: ifnull        277
     255: aload_0
     256: aload         7
     258: invokevirtual #26                 // Method javax/security/auth/login/AppConfigurationEntry.getOptions:()Ljava/util/Map;
     261: ldc           #33                 // String principal
     263: invokeinterface #28,  2           // InterfaceMethod java/util/Map.get:(Ljava/lang/Object;)Ljava/lang/Object;
     268: checkcast     #29                 // class java/lang/String
     271: putfield      #2                  // Field principal:Ljava/lang/String;
     274: goto          277
     277: aload_0
     278: getfield      #12                 // Field isKrbTicket:Z
     281: ifne          285
     284: return
     285: aload_0
     286: new           #34                 // class java/lang/Thread
     289: dup
     290: new           #35                 // class org/apache/zookeeper/Login$1
     293: dup
     294: aload_0
     295: invokespecial #36                 // Method org/apache/zookeeper/Login$1."<init>":(Lorg/apache/zookeeper/Login;)V
     298: invokespecial #37                 // Method java/lang/Thread."<init>":(Ljava/lang/Runnable;)V
     301: putfield      #11                 // Field t:Ljava/lang/Thread;
     304: aload_0
     305: getfield      #11                 // Field t:Ljava/lang/Thread;
     308: iconst_1
     309: invokevirtual #38                 // Method java/lang/Thread.setDaemon:(Z)V
     312: return

  public void startThreadIfNeeded();
    Code:
       0: aload_0
       1: getfield      #11                 // Field t:Ljava/lang/Thread;
       4: ifnull        14
       7: aload_0
       8: getfield      #11                 // Field t:Ljava/lang/Thread;
      11: invokevirtual #39                 // Method java/lang/Thread.start:()V
      14: return

  public void shutdown();
    Code:
       0: aload_0
       1: getfield      #11                 // Field t:Ljava/lang/Thread;
       4: ifnull        61
       7: aload_0
       8: getfield      #11                 // Field t:Ljava/lang/Thread;
      11: invokevirtual #40                 // Method java/lang/Thread.isAlive:()Z
      14: ifeq          61
      17: aload_0
      18: getfield      #11                 // Field t:Ljava/lang/Thread;
      21: invokevirtual #41                 // Method java/lang/Thread.interrupt:()V
      24: aload_0
      25: getfield      #11                 // Field t:Ljava/lang/Thread;
      28: invokevirtual #42                 // Method java/lang/Thread.join:()V
      31: goto          61
      34: astore_1
      35: aload_0
      36: getfield      #9                  // Field LOG:Lorg/apache/log4j/Logger;
      39: new           #44                 // class java/lang/StringBuilder
      42: dup
      43: invokespecial #45                 // Method java/lang/StringBuilder."<init>":()V
      46: ldc           #46                 // String error while waiting for Login thread to shutdown:
      48: invokevirtual #47                 // Method java/lang/StringBuilder.append:(Ljava/lang/String;)Ljava/lang/StringBuilder;
      51: aload_1
      52: invokevirtual #48                 // Method java/lang/StringBuilder.append:(Ljava/lang/Object;)Ljava/lang/StringBuilder;
      55: invokevirtual #49                 // Method java/lang/StringBuilder.toString:()Ljava/lang/String;
      58: invokevirtual #50                 // Method org/apache/log4j/Logger.warn:(Ljava/lang/Object;)V
      61: return
    Exception table:
       from    to  target type
          24    31    34   Class java/lang/InterruptedException

  public javax.security.auth.Subject getSubject();
    Code:
       0: aload_0
       1: getfield      #10                 // Field subject:Ljavax/security/auth/Subject;
       4: areturn

  public java.lang.String getLoginContextName();
    Code:
       0: aload_0
       1: getfield      #15                 // Field loginContextName:Ljava/lang/String;
       4: areturn

  private synchronized javax.security.auth.login.LoginContext login(java.lang.String) throws javax.security.auth.login.LoginException;
    Code:
       0: aload_1
       1: ifnonnull     65
       4: new           #51                 // class javax/security/auth/login/LoginException
       7: dup
       8: new           #44                 // class java/lang/StringBuilder
      11: dup
      12: invokespecial #45                 // Method java/lang/StringBuilder."<init>":()V
      15: ldc           #52                 // String loginContext name (JAAS file section header) was null. Please check your java.security.login.auth.config (=
      17: invokevirtual #47                 // Method java/lang/StringBuilder.append:(Ljava/lang/String;)Ljava/lang/StringBuilder;
      20: ldc           #53                 // String java.security.login.auth.config
      22: invokestatic  #54                 // Method java/lang/System.getProperty:(Ljava/lang/String;)Ljava/lang/String;
      25: invokevirtual #47                 // Method java/lang/StringBuilder.append:(Ljava/lang/String;)Ljava/lang/StringBuilder;
      28: ldc           #55                 // String ) and your
      30: invokevirtual #47                 // Method java/lang/StringBuilder.append:(Ljava/lang/String;)Ljava/lang/StringBuilder;
      33: ldc           #56                 // String zookeeper.sasl.clientconfig
      35: invokevirtual #47                 // Method java/lang/StringBuilder.append:(Ljava/lang/String;)Ljava/lang/StringBuilder;
      38: ldc           #57                 // String (=
      40: invokevirtual #47                 // Method java/lang/StringBuilder.append:(Ljava/lang/String;)Ljava/lang/StringBuilder;
      43: ldc           #56                 // String zookeeper.sasl.clientconfig
      45: ldc           #58                 // String Client
      47: invokestatic  #59                 // Method java/lang/System.getProperty:(Ljava/lang/String;Ljava/lang/String;)Ljava/lang/String;
      50: invokevirtual #47                 // Method java/lang/StringBuilder.append:(Ljava/lang/String;)Ljava/lang/StringBuilder;
      53: ldc           #60                 // String )
      55: invokevirtual #47                 // Method java/lang/StringBuilder.append:(Ljava/lang/String;)Ljava/lang/StringBuilder;
      58: invokevirtual #49                 // Method java/lang/StringBuilder.toString:()Ljava/lang/String;
      61: invokespecial #61                 // Method javax/security/auth/login/LoginException."<init>":(Ljava/lang/String;)V
      64: athrow
      65: new           #62                 // class javax/security/auth/login/LoginContext
      68: dup
      69: aload_1
      70: aload_0
      71: getfield      #18                 // Field callbackHandler:Ljavax/security/auth/callback/CallbackHandler;
      74: invokespecial #63                 // Method javax/security/auth/login/LoginContext."<init>":(Ljava/lang/String;Ljavax/security/auth/callback/CallbackHandler;)V
      77: astore_2
      78: aload_2
      79: invokevirtual #64                 // Method javax/security/auth/login/LoginContext.login:()V
      82: aload_0
      83: getfield      #9                  // Field LOG:Lorg/apache/log4j/Logger;
      86: ldc           #65                 // String successfully logged in.
      88: invokevirtual #66                 // Method org/apache/log4j/Logger.info:(Ljava/lang/Object;)V
      91: aload_2
      92: areturn

  private long getRefreshTime(javax.security.auth.kerberos.KerberosTicket);
    Code:
       0: aload_1
       1: invokevirtual #67                 // Method javax/security/auth/kerberos/KerberosTicket.getStartTime:()Ljava/util/Date;
       4: invokevirtual #68                 // Method java/util/Date.getTime:()J
       7: lstore_2
       8: aload_1
       9: invokevirtual #69                 // Method javax/security/auth/kerberos/KerberosTicket.getEndTime:()Ljava/util/Date;
      12: invokevirtual #68                 // Method java/util/Date.getTime:()J
      15: lstore        4
      17: aload_0
      18: getfield      #9                  // Field LOG:Lorg/apache/log4j/Logger;
      21: new           #44                 // class java/lang/StringBuilder
      24: dup
      25: invokespecial #45                 // Method java/lang/StringBuilder."<init>":()V
      28: ldc           #70                 // String TGT valid starting at:
      30: invokevirtual #47                 // Method java/lang/StringBuilder.append:(Ljava/lang/String;)Ljava/lang/StringBuilder;
      33: aload_1
      34: invokevirtual #67                 // Method javax/security/auth/kerberos/KerberosTicket.getStartTime:()Ljava/util/Date;
      37: invokevirtual #71                 // Method java/util/Date.toString:()Ljava/lang/String;
      40: invokevirtual #47                 // Method java/lang/StringBuilder.append:(Ljava/lang/String;)Ljava/lang/StringBuilder;
      43: invokevirtual #49                 // Method java/lang/StringBuilder.toString:()Ljava/lang/String;
      46: invokevirtual #66                 // Method org/apache/log4j/Logger.info:(Ljava/lang/Object;)V
      49: aload_0
      50: getfield      #9                  // Field LOG:Lorg/apache/log4j/Logger;
      53: new           #44                 // class java/lang/StringBuilder
      56: dup
      57: invokespecial #45                 // Method java/lang/StringBuilder."<init>":()V
      60: ldc           #72                 // String TGT expires:
      62: invokevirtual #47                 // Method java/lang/StringBuilder.append:(Ljava/lang/String;)Ljava/lang/StringBuilder;
      65: aload_1
      66: invokevirtual #69                 // Method javax/security/auth/kerberos/KerberosTicket.getEndTime:()Ljava/util/Date;
      69: invokevirtual #71                 // Method java/util/Date.toString:()Ljava/lang/String;
      72: invokevirtual #47                 // Method java/lang/StringBuilder.append:(Ljava/lang/String;)Ljava/lang/StringBuilder;
      75: invokevirtual #49                 // Method java/lang/StringBuilder.toString:()Ljava/lang/String;
      78: invokevirtual #66                 // Method org/apache/log4j/Logger.info:(Ljava/lang/Object;)V
      81: lload_2
      82: lload         4
      84: lload_2
      85: lsub
      86: l2d
      87: ldc2_w        #73                 // double 0.800000011920929d
      90: ldc2_w        #75                 // double 0.05000000074505806d
      93: getstatic     #77                 // Field rng:Ljava/util/Random;
      96: invokevirtual #78                 // Method java/util/Random.nextDouble:()D
      99: dmul
     100: dadd
     101: dmul
     102: d2l
     103: ladd
     104: lstore        6
     106: lload         6
     108: lload         4
     110: lcmp
     111: ifle          118
     114: invokestatic  #79                 // Method java/lang/System.currentTimeMillis:()J
     117: lreturn
     118: lload         6
     120: lreturn

  private synchronized javax.security.auth.kerberos.KerberosTicket getTGT();
    Code:
       0: aload_0
       1: getfield      #10                 // Field subject:Ljavax/security/auth/Subject;
       4: ldc_w         #21                 // class javax/security/auth/kerberos/KerberosTicket
       7: invokevirtual #22                 // Method javax/security/auth/Subject.getPrivateCredentials:(Ljava/lang/Class;)Ljava/util/Set;
      10: astore_1
      11: aload_1
      12: invokeinterface #80,  1           // InterfaceMethod java/util/Set.iterator:()Ljava/util/Iterator;
      17: astore_2
      18: aload_2
      19: invokeinterface #81,  1           // InterfaceMethod java/util/Iterator.hasNext:()Z
      24: ifeq          126
      27: aload_2
      28: invokeinterface #82,  1           // InterfaceMethod java/util/Iterator.next:()Ljava/lang/Object;
      33: checkcast     #21                 // class javax/security/auth/kerberos/KerberosTicket
      36: astore_3
      37: aload_3
      38: invokevirtual #83                 // Method javax/security/auth/kerberos/KerberosTicket.getServer:()Ljavax/security/auth/kerberos/KerberosPrincipal;
      41: astore        4
      43: aload         4
      45: invokevirtual #84                 // Method javax/security/auth/kerberos/KerberosPrincipal.getName:()Ljava/lang/String;
      48: new           #44                 // class java/lang/StringBuilder
      51: dup
      52: invokespecial #45                 // Method java/lang/StringBuilder."<init>":()V
      55: ldc           #85                 // String krbtgt/
      57: invokevirtual #47                 // Method java/lang/StringBuilder.append:(Ljava/lang/String;)Ljava/lang/StringBuilder;
      60: aload         4
      62: invokevirtual #86                 // Method javax/security/auth/kerberos/KerberosPrincipal.getRealm:()Ljava/lang/String;
      65: invokevirtual #47                 // Method java/lang/StringBuilder.append:(Ljava/lang/String;)Ljava/lang/StringBuilder;
      68: ldc           #87                 // String @
      70: invokevirtual #47                 // Method java/lang/StringBuilder.append:(Ljava/lang/String;)Ljava/lang/StringBuilder;
      73: aload         4
      75: invokevirtual #86                 // Method javax/security/auth/kerberos/KerberosPrincipal.getRealm:()Ljava/lang/String;
      78: invokevirtual #47                 // Method java/lang/StringBuilder.append:(Ljava/lang/String;)Ljava/lang/StringBuilder;
      81: invokevirtual #49                 // Method java/lang/StringBuilder.toString:()Ljava/lang/String;
      84: invokevirtual #31                 // Method java/lang/String.equals:(Ljava/lang/Object;)Z
      87: ifeq          123
      90: aload_0
      91: getfield      #9                  // Field LOG:Lorg/apache/log4j/Logger;
      94: new           #44                 // class java/lang/StringBuilder
      97: dup
      98: invokespecial #45                 // Method java/lang/StringBuilder."<init>":()V
     101: ldc           #88                 // String Found tgt
     103: invokevirtual #47                 // Method java/lang/StringBuilder.append:(Ljava/lang/String;)Ljava/lang/StringBuilder;
     106: aload_3
     107: invokevirtual #48                 // Method java/lang/StringBuilder.append:(Ljava/lang/Object;)Ljava/lang/StringBuilder;
     110: ldc           #89                 // String .
     112: invokevirtual #47                 // Method java/lang/StringBuilder.append:(Ljava/lang/String;)Ljava/lang/StringBuilder;
     115: invokevirtual #49                 // Method java/lang/StringBuilder.toString:()Ljava/lang/String;
     118: invokevirtual #90                 // Method org/apache/log4j/Logger.debug:(Ljava/lang/Object;)V
     121: aload_3
     122: areturn
     123: goto          18
     126: aconst_null
     127: areturn

  private boolean hasSufficientTimeElapsed();
    Code:
       0: invokestatic  #79                 // Method java/lang/System.currentTimeMillis:()J
       3: lstore_1
       4: lload_1
       5: aload_0
       6: invokespecial #91                 // Method getLastLogin:()J
       9: lsub
      10: ldc2_w        #92                 // long 60000l
      13: lcmp
      14: ifge          28
      17: aload_0
      18: getfield      #9                  // Field LOG:Lorg/apache/log4j/Logger;
      21: ldc           #94                 // String Not attempting to re-login since the last re-login was attempted less than 60 seconds before.
      23: invokevirtual #50                 // Method org/apache/log4j/Logger.warn:(Ljava/lang/Object;)V
      26: iconst_0
      27: ireturn
      28: aload_0
      29: lload_1
      30: invokespecial #95                 // Method setLastLogin:(J)V
      33: iconst_1
      34: ireturn

  private javax.security.auth.login.LoginContext getLogin();
    Code:
       0: aload_0
       1: getfield      #14                 // Field login:Ljavax/security/auth/login/LoginContext;
       4: areturn

  private void setLogin(javax.security.auth.login.LoginContext);
    Code:
       0: aload_0
       1: aload_1
       2: putfield      #14                 // Field login:Ljavax/security/auth/login/LoginContext;
       5: return

  private void setLastLogin(long);
    Code:
       0: aload_0
       1: lload_1
       2: putfield      #17                 // Field lastLogin:J
       5: return

  private long getLastLogin();
    Code:
       0: aload_0
       1: getfield      #17                 // Field lastLogin:J
       4: lreturn

  private synchronized void reLogin() throws javax.security.auth.login.LoginException;
    Code:
       0: aload_0
       1: getfield      #12                 // Field isKrbTicket:Z
       4: ifne          8
       7: return
       8: aload_0
       9: invokespecial #96                 // Method getLogin:()Ljavax/security/auth/login/LoginContext;
      12: astore_1
      13: aload_1
      14: ifnonnull     27
      17: new           #51                 // class javax/security/auth/login/LoginException
      20: dup
      21: ldc           #97                 // String login must be done first
      23: invokespecial #61                 // Method javax/security/auth/login/LoginException."<init>":(Ljava/lang/String;)V
      26: athrow
      27: aload_0
      28: invokespecial #98                 // Method hasSufficientTimeElapsed:()Z
      31: ifne          35
      34: return
      35: aload_0
      36: getfield      #9                  // Field LOG:Lorg/apache/log4j/Logger;
      39: new           #44                 // class java/lang/StringBuilder
      42: dup
      43: invokespecial #45                 // Method java/lang/StringBuilder."<init>":()V
      46: ldc           #99                 // String Initiating logout for
      48: invokevirtual #47                 // Method java/lang/StringBuilder.append:(Ljava/lang/String;)Ljava/lang/StringBuilder;
      51: aload_0
      52: getfield      #2                  // Field principal:Ljava/lang/String;
      55: invokevirtual #47                 // Method java/lang/StringBuilder.append:(Ljava/lang/String;)Ljava/lang/StringBuilder;
      58: invokevirtual #49                 // Method java/lang/StringBuilder.toString:()Ljava/lang/String;
      61: invokevirtual #66                 // Method org/apache/log4j/Logger.info:(Ljava/lang/Object;)V
      64: ldc_w         #7                  // class org/apache/zookeeper/Login
      67: dup
      68: astore_2
      69: monitorenter
      70: aload_1
      71: invokevirtual #100                // Method javax/security/auth/login/LoginContext.logout:()V
      74: new           #62                 // class javax/security/auth/login/LoginContext
      77: dup
      78: aload_0
      79: getfield      #15                 // Field loginContextName:Ljava/lang/String;
      82: aload_0
      83: invokevirtual #101                // Method getSubject:()Ljavax/security/auth/Subject;
      86: invokespecial #102                // Method javax/security/auth/login/LoginContext."<init>":(Ljava/lang/String;Ljavax/security/auth/Subject;)V
      89: astore_1
      90: aload_0
      91: getfield      #9                  // Field LOG:Lorg/apache/log4j/Logger;
      94: new           #44                 // class java/lang/StringBuilder
      97: dup
      98: invokespecial #45                 // Method java/lang/StringBuilder."<init>":()V
     101: ldc           #103                // String Initiating re-login for
     103: invokevirtual #47                 // Method java/lang/StringBuilder.append:(Ljava/lang/String;)Ljava/lang/StringBuilder;
     106: aload_0
     107: getfield      #2                  // Field principal:Ljava/lang/String;
     110: invokevirtual #47                 // Method java/lang/StringBuilder.append:(Ljava/lang/String;)Ljava/lang/StringBuilder;
     113: invokevirtual #49                 // Method java/lang/StringBuilder.toString:()Ljava/lang/String;
     116: invokevirtual #66                 // Method org/apache/log4j/Logger.info:(Ljava/lang/Object;)V
     119: aload_1
     120: invokevirtual #64                 // Method javax/security/auth/login/LoginContext.login:()V
     123: aload_0
     124: aload_1
     125: invokespecial #104                // Method setLogin:(Ljavax/security/auth/login/LoginContext;)V
     128: aload_2
     129: monitorexit
     130: goto          138
     133: astore_3
     134: aload_2
     135: monitorexit
     136: aload_3
     137: athrow
     138: return
    Exception table:
       from    to  target type
          70   130   133   any
         133   136   133   any

  static javax.security.auth.kerberos.KerberosTicket access$000(org.apache.zookeeper.Login);
    Code:
       0: aload_0
       1: invokespecial #5                  // Method getTGT:()Ljavax/security/auth/kerberos/KerberosTicket;
       4: areturn

  static long access$100(org.apache.zookeeper.Login, javax.security.auth.kerberos.KerberosTicket);
    Code:
       0: aload_0
       1: aload_1
       2: invokespecial #4                  // Method getRefreshTime:(Ljavax/security/auth/kerberos/KerberosTicket;)J
       5: lreturn

  static boolean access$200(org.apache.zookeeper.Login);
    Code:
       0: aload_0
       1: getfield      #3                  // Field isUsingTicketCache:Z
       4: ireturn

  static java.lang.String access$300(org.apache.zookeeper.Login);
    Code:
       0: aload_0
       1: getfield      #2                  // Field principal:Ljava/lang/String;
       4: areturn

  static void access$400(org.apache.zookeeper.Login) throws javax.security.auth.login.LoginException;
    Code:
       0: aload_0
       1: invokespecial #1                  // Method reLogin:()V
       4: return

  static {};
    Code:
       0: new           #105                // class java/util/Random
       3: dup
       4: invokespecial #106                // Method java/util/Random."<init>":()V
       7: putstatic     #77                 // Field rng:Ljava/util/Random;
      10: return
}
