Compiled from "OpResult.java"
public class org.apache.zookeeper.OpResult$CheckResult extends org.apache.zookeeper.OpResult {
  public org.apache.zookeeper.OpResult$CheckResult();
    Code:
       0: aload_0
       1: bipush        13
       3: aconst_null
       4: invokespecial #1                  // Method org/apache/zookeeper/OpResult."<init>":(ILorg/apache/zookeeper/OpResult$1;)V
       7: return

  public boolean equals(java.lang.Object);
    Code:
       0: aload_0
       1: aload_1
       2: if_acmpne     7
       5: iconst_1
       6: ireturn
       7: aload_1
       8: instanceof    #2                  // class org/apache/zookeeper/OpResult$CheckResult
      11: ifne          16
      14: iconst_0
      15: ireturn
      16: aload_1
      17: checkcast     #2                  // class org/apache/zookeeper/OpResult$CheckResult
      20: astore_2
      21: aload_0
      22: invokevirtual #3                  // Method getType:()I
      25: aload_2
      26: invokevirtual #3                  // Method getType:()I
      29: if_icmpne     36
      32: iconst_1
      33: goto          37
      36: iconst_0
      37: ireturn

  public int hashCode();
    Code:
       0: aload_0
       1: invokevirtual #3                  // Method getType:()I
       4: ireturn
}
