Compiled from "TransactionCache.java"
public class com.arjuna.ats.internal.jts.recovery.transactions.TransactionCache {
  private static final java.util.Hashtable _theCache;

  private static final int attemptsBeforeConversion;

  public com.arjuna.ats.internal.jts.recovery.transactions.TransactionCache();
    Code:
       0: aload_0
       1: invokespecial #1                  // Method java/lang/Object."<init>":()V
       4: return

  public static org.omg.CosTransactions.Status get_status(com.arjuna.ats.arjuna.common.Uid, java.lang.String) throws org.omg.CORBA.SystemException;
    Code:
       0: getstatic     #2                  // Field org/omg/CosTransactions/Status.StatusUnknown:Lorg/omg/CosTransactions/Status;
       3: astore_2
       4: aload_0
       5: aload_1
       6: invokestatic  #3                  // Method get:(Lcom/arjuna/ats/arjuna/common/Uid;Ljava/lang/String;)Lcom/arjuna/ats/internal/jts/recovery/transactions/TransactionCacheItem;
       9: astore_3
      10: aload_3
      11: ifnull        57
      14: aload_3
      15: dup
      16: astore        4
      18: monitorenter
      19: aload_3
      20: invokevirtual #4                  // Method com/arjuna/ats/internal/jts/recovery/transactions/TransactionCacheItem.freshTransaction:()Lcom/arjuna/ats/internal/jts/recovery/transactions/RecoveringTransaction;
      23: astore        5
      25: aload         5
      27: ifnull        43
      30: aload         5
      32: invokeinterface #5,  1            // InterfaceMethod com/arjuna/ats/internal/jts/recovery/transactions/RecoveringTransaction.get_status:()Lorg/omg/CosTransactions/Status;
      37: astore_2
      38: aload_3
      39: aload_2
      40: invokevirtual #6                  // Method com/arjuna/ats/internal/jts/recovery/transactions/TransactionCacheItem.setStatus:(Lorg/omg/CosTransactions/Status;)V
      43: aload         4
      45: monitorexit
      46: goto          57
      49: astore        6
      51: aload         4
      53: monitorexit
      54: aload         6
      56: athrow
      57: aload_2
      58: areturn
    Exception table:
       from    to  target type
          19    46    49   any
          49    54    49   any

  public static org.omg.CosTransactions.Status getCachedStatus(com.arjuna.ats.arjuna.common.Uid) throws org.omg.CORBA.SystemException;
    Code:
       0: aload_0
       1: invokestatic  #7                  // Method getKnown:(Lcom/arjuna/ats/arjuna/common/Uid;)Lcom/arjuna/ats/internal/jts/recovery/transactions/TransactionCacheItem;
       4: astore_1
       5: aload_1
       6: ifnull        14
       9: aload_1
      10: invokevirtual #8                  // Method com/arjuna/ats/internal/jts/recovery/transactions/TransactionCacheItem.getStatus:()Lorg/omg/CosTransactions/Status;
      13: areturn
      14: getstatic     #9                  // Field org/omg/CosTransactions/Status.StatusNoTransaction:Lorg/omg/CosTransactions/Status;
      17: areturn

  public static org.omg.CosTransactions.Status getOriginalStatus(com.arjuna.ats.arjuna.common.Uid, java.lang.String) throws org.omg.CORBA.SystemException;
    Code:
       0: getstatic     #2                  // Field org/omg/CosTransactions/Status.StatusUnknown:Lorg/omg/CosTransactions/Status;
       3: astore_2
       4: aload_0
       5: aload_1
       6: invokestatic  #3                  // Method get:(Lcom/arjuna/ats/arjuna/common/Uid;Ljava/lang/String;)Lcom/arjuna/ats/internal/jts/recovery/transactions/TransactionCacheItem;
       9: astore_3
      10: aload_3
      11: ifnull        89
      14: aload_3
      15: dup
      16: astore        4
      18: monitorenter
      19: aload_3
      20: invokevirtual #4                  // Method com/arjuna/ats/internal/jts/recovery/transactions/TransactionCacheItem.freshTransaction:()Lcom/arjuna/ats/internal/jts/recovery/transactions/RecoveringTransaction;
      23: astore        5
      25: aload         5
      27: ifnull        58
      30: getstatic     #10                 // Field com/arjuna/ats/jts/logging/jtsLogger.logger:Lorg/jboss/logging/Logger;
      33: invokevirtual #11                 // Method org/jboss/logging/Logger.isDebugEnabled:()Z
      36: ifeq          47
      39: getstatic     #10                 // Field com/arjuna/ats/jts/logging/jtsLogger.logger:Lorg/jboss/logging/Logger;
      42: ldc           #12                 // String asking the tran for original status
      44: invokevirtual #13                 // Method org/jboss/logging/Logger.debug:(Ljava/lang/Object;)V
      47: aload         5
      49: invokeinterface #14,  1           // InterfaceMethod com/arjuna/ats/internal/jts/recovery/transactions/RecoveringTransaction.getOriginalStatus:()Lorg/omg/CosTransactions/Status;
      54: astore_2
      55: goto          75
      58: getstatic     #10                 // Field com/arjuna/ats/jts/logging/jtsLogger.logger:Lorg/jboss/logging/Logger;
      61: invokevirtual #11                 // Method org/jboss/logging/Logger.isDebugEnabled:()Z
      64: ifeq          75
      67: getstatic     #10                 // Field com/arjuna/ats/jts/logging/jtsLogger.logger:Lorg/jboss/logging/Logger;
      70: ldc           #15                 // String no transaction in cache so not asking for original status
      72: invokevirtual #13                 // Method org/jboss/logging/Logger.debug:(Ljava/lang/Object;)V
      75: aload         4
      77: monitorexit
      78: goto          89
      81: astore        6
      83: aload         4
      85: monitorexit
      86: aload         6
      88: athrow
      89: aload_2
      90: areturn
    Exception table:
       from    to  target type
          19    78    81   any
          81    86    81   any

  public static int getRecoveryStatus(com.arjuna.ats.arjuna.common.Uid, java.lang.String);
    Code:
       0: iconst_0
       1: istore_2
       2: aload_0
       3: aload_1
       4: invokestatic  #3                  // Method get:(Lcom/arjuna/ats/arjuna/common/Uid;Ljava/lang/String;)Lcom/arjuna/ats/internal/jts/recovery/transactions/TransactionCacheItem;
       7: astore_3
       8: aload_3
       9: ifnull        50
      12: aload_3
      13: dup
      14: astore        4
      16: monitorenter
      17: aload_3
      18: invokevirtual #17                 // Method com/arjuna/ats/internal/jts/recovery/transactions/TransactionCacheItem.transaction:()Lcom/arjuna/ats/internal/jts/recovery/transactions/RecoveringTransaction;
      21: astore        5
      23: aload         5
      25: ifnull        36
      28: aload         5
      30: invokeinterface #18,  1           // InterfaceMethod com/arjuna/ats/internal/jts/recovery/transactions/RecoveringTransaction.getRecoveryStatus:()I
      35: istore_2
      36: aload         4
      38: monitorexit
      39: goto          50
      42: astore        6
      44: aload         4
      46: monitorexit
      47: aload         6
      49: athrow
      50: iload_2
      51: ireturn
    Exception table:
       from    to  target type
          17    39    42   any
          42    47    42   any

  public static void addResourceRecord(com.arjuna.ats.arjuna.common.Uid, java.lang.String, com.arjuna.ats.arjuna.common.Uid, org.omg.CosTransactions.Resource);
    Code:
       0: aload_0
       1: aload_1
       2: invokestatic  #3                  // Method get:(Lcom/arjuna/ats/arjuna/common/Uid;Ljava/lang/String;)Lcom/arjuna/ats/internal/jts/recovery/transactions/TransactionCacheItem;
       5: astore        4
       7: aload         4
       9: ifnull        69
      12: aload         4
      14: dup
      15: astore        5
      17: monitorenter
      18: aload         4
      20: invokevirtual #4                  // Method com/arjuna/ats/internal/jts/recovery/transactions/TransactionCacheItem.freshTransaction:()Lcom/arjuna/ats/internal/jts/recovery/transactions/RecoveringTransaction;
      23: astore        6
      25: aload         6
      27: ifnull        55
      30: aload         6
      32: invokeinterface #18,  1           // InterfaceMethod com/arjuna/ats/internal/jts/recovery/transactions/RecoveringTransaction.getRecoveryStatus:()I
      37: iconst_2
      38: if_icmpeq     50
      41: aload         6
      43: aload_2
      44: aload_3
      45: invokeinterface #19,  3           // InterfaceMethod com/arjuna/ats/internal/jts/recovery/transactions/RecoveringTransaction.addResourceRecord:(Lcom/arjuna/ats/arjuna/common/Uid;Lorg/omg/CosTransactions/Resource;)V
      50: aload         4
      52: invokevirtual #20                 // Method com/arjuna/ats/internal/jts/recovery/transactions/TransactionCacheItem.resetAttemptCount:()V
      55: aload         5
      57: monitorexit
      58: goto          69
      61: astore        7
      63: aload         5
      65: monitorexit
      66: aload         7
      68: athrow
      69: return
    Exception table:
       from    to  target type
          18    58    61   any
          61    66    61   any

  public static void replayPhase2(com.arjuna.ats.arjuna.common.Uid, java.lang.String);
    Code:
       0: aload_0
       1: aload_1
       2: invokestatic  #3                  // Method get:(Lcom/arjuna/ats/arjuna/common/Uid;Ljava/lang/String;)Lcom/arjuna/ats/internal/jts/recovery/transactions/TransactionCacheItem;
       5: astore_2
       6: aload_2
       7: ifnull        213
      10: aload_2
      11: dup
      12: astore_3
      13: monitorenter
      14: iconst_0
      15: istore        4
      17: aload_2
      18: invokevirtual #4                  // Method com/arjuna/ats/internal/jts/recovery/transactions/TransactionCacheItem.freshTransaction:()Lcom/arjuna/ats/internal/jts/recovery/transactions/RecoveringTransaction;
      21: astore        5
      23: aload         5
      25: ifnull        176
      28: aload         5
      30: invokeinterface #18,  1           // InterfaceMethod com/arjuna/ats/internal/jts/recovery/transactions/RecoveringTransaction.getRecoveryStatus:()I
      35: iconst_2
      36: if_icmpeq     176
      39: iconst_0
      40: istore        6
      42: aload_2
      43: invokevirtual #8                  // Method com/arjuna/ats/internal/jts/recovery/transactions/TransactionCacheItem.getStatus:()Lorg/omg/CosTransactions/Status;
      46: getstatic     #21                 // Field org/omg/CosTransactions/Status.StatusCommitted:Lorg/omg/CosTransactions/Status;
      49: if_acmpne     119
      52: aload_2
      53: invokevirtual #22                 // Method com/arjuna/ats/internal/jts/recovery/transactions/TransactionCacheItem.countAttempts:()I
      56: istore        7
      58: iload         7
      60: getstatic     #23                 // Field attemptsBeforeConversion:I
      63: if_icmplt     119
      66: aload         5
      68: invokeinterface #24,  1           // InterfaceMethod com/arjuna/ats/internal/jts/recovery/transactions/RecoveringTransaction.assumeComplete:()Z
      73: istore        6
      75: iload         6
      77: ifeq          119
      80: getstatic     #10                 // Field com/arjuna/ats/jts/logging/jtsLogger.logger:Lorg/jboss/logging/Logger;
      83: invokevirtual #11                 // Method org/jboss/logging/Logger.isDebugEnabled:()Z
      86: ifeq          119
      89: getstatic     #10                 // Field com/arjuna/ats/jts/logging/jtsLogger.logger:Lorg/jboss/logging/Logger;
      92: new           #25                 // class java/lang/StringBuilder
      95: dup
      96: invokespecial #26                 // Method java/lang/StringBuilder."<init>":()V
      99: ldc           #27                 // String  Transaction
     101: invokevirtual #28                 // Method java/lang/StringBuilder.append:(Ljava/lang/String;)Ljava/lang/StringBuilder;
     104: aload_0
     105: invokevirtual #29                 // Method java/lang/StringBuilder.append:(Ljava/lang/Object;)Ljava/lang/StringBuilder;
     108: ldc           #30                 // String  assumed complete - changing type.
     110: invokevirtual #28                 // Method java/lang/StringBuilder.append:(Ljava/lang/String;)Ljava/lang/StringBuilder;
     113: invokevirtual #31                 // Method java/lang/StringBuilder.toString:()Ljava/lang/String;
     116: invokevirtual #13                 // Method org/jboss/logging/Logger.debug:(Ljava/lang/Object;)V
     119: aload         5
     121: invokeinterface #32,  1           // InterfaceMethod com/arjuna/ats/internal/jts/recovery/transactions/RecoveringTransaction.replayPhase2:()V
     126: aload_2
     127: aload         5
     129: invokeinterface #5,  1            // InterfaceMethod com/arjuna/ats/internal/jts/recovery/transactions/RecoveringTransaction.get_status:()Lorg/omg/CosTransactions/Status;
     134: invokevirtual #6                  // Method com/arjuna/ats/internal/jts/recovery/transactions/TransactionCacheItem.setStatus:(Lorg/omg/CosTransactions/Status;)V
     137: aload         5
     139: invokeinterface #33,  1           // InterfaceMethod com/arjuna/ats/internal/jts/recovery/transactions/RecoveringTransaction.allCompleted:()Z
     144: istore        4
     146: iload         6
     148: ifeq          176
     151: iload         4
     153: ifne          176
     156: getstatic     #34                 // Field com/arjuna/ats/jts/logging/jtsLogger.i18NLogger:Lcom/arjuna/ats/jts/logging/jtsI18NLogger;
     159: aload_0
     160: invokeinterface #35,  2           // InterfaceMethod com/arjuna/ats/jts/logging/jtsI18NLogger.info_recovery_transactions_TransactionCache_4:(Lcom/arjuna/ats/arjuna/common/Uid;)V
     165: aload         5
     167: invokeinterface #36,  1           // InterfaceMethod com/arjuna/ats/internal/jts/recovery/transactions/RecoveringTransaction.removeOldStoreEntry:()V
     172: aload_2
     173: invokevirtual #37                 // Method com/arjuna/ats/internal/jts/recovery/transactions/TransactionCacheItem.updateType:()V
     176: iload         4
     178: ifeq          197
     181: getstatic     #34                 // Field com/arjuna/ats/jts/logging/jtsLogger.i18NLogger:Lcom/arjuna/ats/jts/logging/jtsI18NLogger;
     184: aload_0
     185: invokeinterface #38,  2           // InterfaceMethod com/arjuna/ats/jts/logging/jtsI18NLogger.info_recovery_transactions_TransactionCache_5:(Lcom/arjuna/ats/arjuna/common/Uid;)V
     190: aload_0
     191: invokestatic  #39                 // Method remove:(Lcom/arjuna/ats/arjuna/common/Uid;)V
     194: goto          201
     197: aload_2
     198: invokevirtual #40                 // Method com/arjuna/ats/internal/jts/recovery/transactions/TransactionCacheItem.clearTransaction:()V
     201: aload_3
     202: monitorexit
     203: goto          213
     206: astore        8
     208: aload_3
     209: monitorexit
     210: aload         8
     212: athrow
     213: return
    Exception table:
       from    to  target type
          14   203   206   any
         206   210   206   any

  private static synchronized com.arjuna.ats.internal.jts.recovery.transactions.TransactionCacheItem getKnown(com.arjuna.ats.arjuna.common.Uid);
    Code:
       0: getstatic     #41                 // Field _theCache:Ljava/util/Hashtable;
       3: aload_0
       4: invokevirtual #42                 // Method java/util/Hashtable.get:(Ljava/lang/Object;)Ljava/lang/Object;
       7: checkcast     #43                 // class com/arjuna/ats/internal/jts/recovery/transactions/TransactionCacheItem
      10: astore_1
      11: aload_1
      12: areturn

  private static synchronized com.arjuna.ats.internal.jts.recovery.transactions.TransactionCacheItem get(com.arjuna.ats.arjuna.common.Uid, java.lang.String);
    Code:
       0: getstatic     #41                 // Field _theCache:Ljava/util/Hashtable;
       3: aload_0
       4: invokevirtual #42                 // Method java/util/Hashtable.get:(Ljava/lang/Object;)Ljava/lang/Object;
       7: checkcast     #43                 // class com/arjuna/ats/internal/jts/recovery/transactions/TransactionCacheItem
      10: astore_2
      11: aload_2
      12: ifnonnull     34
      15: new           #43                 // class com/arjuna/ats/internal/jts/recovery/transactions/TransactionCacheItem
      18: dup
      19: aload_0
      20: aload_1
      21: invokespecial #44                 // Method com/arjuna/ats/internal/jts/recovery/transactions/TransactionCacheItem."<init>":(Lcom/arjuna/ats/arjuna/common/Uid;Ljava/lang/String;)V
      24: astore_2
      25: getstatic     #41                 // Field _theCache:Ljava/util/Hashtable;
      28: aload_0
      29: aload_2
      30: invokevirtual #45                 // Method java/util/Hashtable.put:(Ljava/lang/Object;Ljava/lang/Object;)Ljava/lang/Object;
      33: pop
      34: aload_2
      35: areturn

  private static void remove(com.arjuna.ats.arjuna.common.Uid);
    Code:
       0: getstatic     #41                 // Field _theCache:Ljava/util/Hashtable;
       3: aload_0
       4: invokevirtual #42                 // Method java/util/Hashtable.get:(Ljava/lang/Object;)Ljava/lang/Object;
       7: checkcast     #43                 // class com/arjuna/ats/internal/jts/recovery/transactions/TransactionCacheItem
      10: astore_1
      11: aload_1
      12: ifnonnull     57
      15: getstatic     #10                 // Field com/arjuna/ats/jts/logging/jtsLogger.logger:Lorg/jboss/logging/Logger;
      18: invokevirtual #11                 // Method org/jboss/logging/Logger.isDebugEnabled:()Z
      21: ifeq          118
      24: getstatic     #10                 // Field com/arjuna/ats/jts/logging/jtsLogger.logger:Lorg/jboss/logging/Logger;
      27: new           #25                 // class java/lang/StringBuilder
      30: dup
      31: invokespecial #26                 // Method java/lang/StringBuilder."<init>":()V
      34: ldc           #46                 // String TransactionCache.remove
      36: invokevirtual #28                 // Method java/lang/StringBuilder.append:(Ljava/lang/String;)Ljava/lang/StringBuilder;
      39: aload_0
      40: invokevirtual #29                 // Method java/lang/StringBuilder.append:(Ljava/lang/Object;)Ljava/lang/StringBuilder;
      43: ldc           #47                 // String : transaction not in cache
      45: invokevirtual #28                 // Method java/lang/StringBuilder.append:(Ljava/lang/String;)Ljava/lang/StringBuilder;
      48: invokevirtual #31                 // Method java/lang/StringBuilder.toString:()Ljava/lang/String;
      51: invokevirtual #13                 // Method org/jboss/logging/Logger.debug:(Ljava/lang/Object;)V
      54: goto          118
      57: aload_1
      58: dup
      59: astore_2
      60: monitorenter
      61: getstatic     #41                 // Field _theCache:Ljava/util/Hashtable;
      64: aload_0
      65: invokevirtual #48                 // Method java/util/Hashtable.remove:(Ljava/lang/Object;)Ljava/lang/Object;
      68: pop
      69: aload_2
      70: monitorexit
      71: goto          79
      74: astore_3
      75: aload_2
      76: monitorexit
      77: aload_3
      78: athrow
      79: getstatic     #10                 // Field com/arjuna/ats/jts/logging/jtsLogger.logger:Lorg/jboss/logging/Logger;
      82: invokevirtual #11                 // Method org/jboss/logging/Logger.isDebugEnabled:()Z
      85: ifeq          118
      88: getstatic     #10                 // Field com/arjuna/ats/jts/logging/jtsLogger.logger:Lorg/jboss/logging/Logger;
      91: new           #25                 // class java/lang/StringBuilder
      94: dup
      95: invokespecial #26                 // Method java/lang/StringBuilder."<init>":()V
      98: ldc           #46                 // String TransactionCache.remove
     100: invokevirtual #28                 // Method java/lang/StringBuilder.append:(Ljava/lang/String;)Ljava/lang/StringBuilder;
     103: aload_0
     104: invokevirtual #29                 // Method java/lang/StringBuilder.append:(Ljava/lang/Object;)Ljava/lang/StringBuilder;
     107: ldc           #49                 // String : removed transaction from cache
     109: invokevirtual #28                 // Method java/lang/StringBuilder.append:(Ljava/lang/String;)Ljava/lang/StringBuilder;
     112: invokevirtual #31                 // Method java/lang/StringBuilder.toString:()Ljava/lang/String;
     115: invokevirtual #13                 // Method org/jboss/logging/Logger.debug:(Ljava/lang/Object;)V
     118: return
    Exception table:
       from    to  target type
          61    71    74   any
          74    77    74   any

  static {};
    Code:
       0: new           #50                 // class java/util/Hashtable
       3: dup
       4: invokespecial #51                 // Method java/util/Hashtable."<init>":()V
       7: putstatic     #41                 // Field _theCache:Ljava/util/Hashtable;
      10: invokestatic  #52                 // Method com/arjuna/ats/jts/common/jtsPropertyManager.getJTSEnvironmentBean:()Lcom/arjuna/ats/jts/common/JTSEnvironmentBean;
      13: invokevirtual #53                 // Method com/arjuna/ats/jts/common/JTSEnvironmentBean.getCommitedTransactionRetryLimit:()I
      16: putstatic     #23                 // Field attemptsBeforeConversion:I
      19: return
}
