Compiled from "LoadEvent.java"
public class org.hibernate.event.spi.LoadEvent extends org.hibernate.event.spi.AbstractEvent {
  public static final org.hibernate.LockMode DEFAULT_LOCK_MODE;

  public static final org.hibernate.LockOptions DEFAULT_LOCK_OPTIONS;

  private java.io.Serializable entityId;

  private java.lang.String entityClassName;

  private java.lang.Object instanceToLoad;

  private org.hibernate.LockOptions lockOptions;

  private boolean isAssociationFetch;

  private java.lang.Object result;

  private org.hibernate.event.spi.PostLoadEvent postLoadEvent;

  public org.hibernate.event.spi.LoadEvent(java.io.Serializable, java.lang.Object, org.hibernate.event.spi.EventSource);
    Code:
       0: aload_0
       1: aload_1
       2: aconst_null
       3: aload_2
       4: getstatic     #1                  // Field DEFAULT_LOCK_OPTIONS:Lorg/hibernate/LockOptions;
       7: iconst_0
       8: aload_3
       9: invokespecial #2                  // Method "<init>":(Ljava/io/Serializable;Ljava/lang/String;Ljava/lang/Object;Lorg/hibernate/LockOptions;ZLorg/hibernate/event/spi/EventSource;)V
      12: return

  public org.hibernate.event.spi.LoadEvent(java.io.Serializable, java.lang.String, org.hibernate.LockMode, org.hibernate.event.spi.EventSource);
    Code:
       0: aload_0
       1: aload_1
       2: aload_2
       3: aconst_null
       4: aload_3
       5: iconst_0
       6: aload         4
       8: invokespecial #3                  // Method "<init>":(Ljava/io/Serializable;Ljava/lang/String;Ljava/lang/Object;Lorg/hibernate/LockMode;ZLorg/hibernate/event/spi/EventSource;)V
      11: return

  public org.hibernate.event.spi.LoadEvent(java.io.Serializable, java.lang.String, org.hibernate.LockOptions, org.hibernate.event.spi.EventSource);
    Code:
       0: aload_0
       1: aload_1
       2: aload_2
       3: aconst_null
       4: aload_3
       5: iconst_0
       6: aload         4
       8: invokespecial #2                  // Method "<init>":(Ljava/io/Serializable;Ljava/lang/String;Ljava/lang/Object;Lorg/hibernate/LockOptions;ZLorg/hibernate/event/spi/EventSource;)V
      11: return

  public org.hibernate.event.spi.LoadEvent(java.io.Serializable, java.lang.String, boolean, org.hibernate.event.spi.EventSource);
    Code:
       0: aload_0
       1: aload_1
       2: aload_2
       3: aconst_null
       4: getstatic     #1                  // Field DEFAULT_LOCK_OPTIONS:Lorg/hibernate/LockOptions;
       7: iload_3
       8: aload         4
      10: invokespecial #2                  // Method "<init>":(Ljava/io/Serializable;Ljava/lang/String;Ljava/lang/Object;Lorg/hibernate/LockOptions;ZLorg/hibernate/event/spi/EventSource;)V
      13: return

  public boolean isAssociationFetch();
    Code:
       0: aload_0
       1: getfield      #4                  // Field isAssociationFetch:Z
       4: ireturn

  private org.hibernate.event.spi.LoadEvent(java.io.Serializable, java.lang.String, java.lang.Object, org.hibernate.LockMode, boolean, org.hibernate.event.spi.EventSource);
    Code:
       0: aload_0
       1: aload_1
       2: aload_2
       3: aload_3
       4: aload         4
       6: getstatic     #5                  // Field DEFAULT_LOCK_MODE:Lorg/hibernate/LockMode;
       9: if_acmpne     18
      12: getstatic     #1                  // Field DEFAULT_LOCK_OPTIONS:Lorg/hibernate/LockOptions;
      15: goto          30
      18: new           #6                  // class org/hibernate/LockOptions
      21: dup
      22: invokespecial #7                  // Method org/hibernate/LockOptions."<init>":()V
      25: aload         4
      27: invokevirtual #8                  // Method org/hibernate/LockOptions.setLockMode:(Lorg/hibernate/LockMode;)Lorg/hibernate/LockOptions;
      30: iload         5
      32: aload         6
      34: invokespecial #2                  // Method "<init>":(Ljava/io/Serializable;Ljava/lang/String;Ljava/lang/Object;Lorg/hibernate/LockOptions;ZLorg/hibernate/event/spi/EventSource;)V
      37: return

  private org.hibernate.event.spi.LoadEvent(java.io.Serializable, java.lang.String, java.lang.Object, org.hibernate.LockOptions, boolean, org.hibernate.event.spi.EventSource);
    Code:
       0: aload_0
       1: aload         6
       3: invokespecial #9                  // Method org/hibernate/event/spi/AbstractEvent."<init>":(Lorg/hibernate/event/spi/EventSource;)V
       6: aload_1
       7: ifnonnull     20
      10: new           #10                 // class java/lang/IllegalArgumentException
      13: dup
      14: ldc           #11                 // String id to load is required for loading
      16: invokespecial #12                 // Method java/lang/IllegalArgumentException."<init>":(Ljava/lang/String;)V
      19: athrow
      20: aload         4
      22: invokevirtual #13                 // Method org/hibernate/LockOptions.getLockMode:()Lorg/hibernate/LockMode;
      25: getstatic     #14                 // Field org/hibernate/LockMode.WRITE:Lorg/hibernate/LockMode;
      28: if_acmpne     41
      31: new           #10                 // class java/lang/IllegalArgumentException
      34: dup
      35: ldc           #15                 // String Invalid lock mode for loading
      37: invokespecial #12                 // Method java/lang/IllegalArgumentException."<init>":(Ljava/lang/String;)V
      40: athrow
      41: aload         4
      43: invokevirtual #13                 // Method org/hibernate/LockOptions.getLockMode:()Lorg/hibernate/LockMode;
      46: ifnonnull     58
      49: aload         4
      51: getstatic     #5                  // Field DEFAULT_LOCK_MODE:Lorg/hibernate/LockMode;
      54: invokevirtual #8                  // Method org/hibernate/LockOptions.setLockMode:(Lorg/hibernate/LockMode;)Lorg/hibernate/LockOptions;
      57: pop
      58: aload_0
      59: aload_1
      60: putfield      #16                 // Field entityId:Ljava/io/Serializable;
      63: aload_0
      64: aload_2
      65: putfield      #17                 // Field entityClassName:Ljava/lang/String;
      68: aload_0
      69: aload_3
      70: putfield      #18                 // Field instanceToLoad:Ljava/lang/Object;
      73: aload_0
      74: aload         4
      76: putfield      #19                 // Field lockOptions:Lorg/hibernate/LockOptions;
      79: aload_0
      80: iload         5
      82: putfield      #4                  // Field isAssociationFetch:Z
      85: aload_0
      86: new           #20                 // class org/hibernate/event/spi/PostLoadEvent
      89: dup
      90: aload         6
      92: invokespecial #21                 // Method org/hibernate/event/spi/PostLoadEvent."<init>":(Lorg/hibernate/event/spi/EventSource;)V
      95: putfield      #22                 // Field postLoadEvent:Lorg/hibernate/event/spi/PostLoadEvent;
      98: return

  public java.io.Serializable getEntityId();
    Code:
       0: aload_0
       1: getfield      #16                 // Field entityId:Ljava/io/Serializable;
       4: areturn

  public void setEntityId(java.io.Serializable);
    Code:
       0: aload_0
       1: aload_1
       2: putfield      #16                 // Field entityId:Ljava/io/Serializable;
       5: return

  public java.lang.String getEntityClassName();
    Code:
       0: aload_0
       1: getfield      #17                 // Field entityClassName:Ljava/lang/String;
       4: areturn

  public void setEntityClassName(java.lang.String);
    Code:
       0: aload_0
       1: aload_1
       2: putfield      #17                 // Field entityClassName:Ljava/lang/String;
       5: return

  public java.lang.Object getInstanceToLoad();
    Code:
       0: aload_0
       1: getfield      #18                 // Field instanceToLoad:Ljava/lang/Object;
       4: areturn

  public void setInstanceToLoad(java.lang.Object);
    Code:
       0: aload_0
       1: aload_1
       2: putfield      #18                 // Field instanceToLoad:Ljava/lang/Object;
       5: return

  public org.hibernate.LockOptions getLockOptions();
    Code:
       0: aload_0
       1: getfield      #19                 // Field lockOptions:Lorg/hibernate/LockOptions;
       4: areturn

  public org.hibernate.LockMode getLockMode();
    Code:
       0: aload_0
       1: getfield      #19                 // Field lockOptions:Lorg/hibernate/LockOptions;
       4: invokevirtual #13                 // Method org/hibernate/LockOptions.getLockMode:()Lorg/hibernate/LockMode;
       7: areturn

  public void setLockMode(org.hibernate.LockMode);
    Code:
       0: aload_1
       1: aload_0
       2: getfield      #19                 // Field lockOptions:Lorg/hibernate/LockOptions;
       5: invokevirtual #13                 // Method org/hibernate/LockOptions.getLockMode:()Lorg/hibernate/LockMode;
       8: if_acmpeq     24
      11: aload_0
      12: invokespecial #23                 // Method writingOnLockOptions:()V
      15: aload_0
      16: getfield      #19                 // Field lockOptions:Lorg/hibernate/LockOptions;
      19: aload_1
      20: invokevirtual #8                  // Method org/hibernate/LockOptions.setLockMode:(Lorg/hibernate/LockMode;)Lorg/hibernate/LockOptions;
      23: pop
      24: return

  private void writingOnLockOptions();
    Code:
       0: aload_0
       1: getfield      #19                 // Field lockOptions:Lorg/hibernate/LockOptions;
       4: getstatic     #1                  // Field DEFAULT_LOCK_OPTIONS:Lorg/hibernate/LockOptions;
       7: if_acmpne     21
      10: aload_0
      11: new           #6                  // class org/hibernate/LockOptions
      14: dup
      15: invokespecial #7                  // Method org/hibernate/LockOptions."<init>":()V
      18: putfield      #19                 // Field lockOptions:Lorg/hibernate/LockOptions;
      21: return

  public void setLockTimeout(int);
    Code:
       0: iload_1
       1: aload_0
       2: getfield      #19                 // Field lockOptions:Lorg/hibernate/LockOptions;
       5: invokevirtual #24                 // Method org/hibernate/LockOptions.getTimeOut:()I
       8: if_icmpeq     24
      11: aload_0
      12: invokespecial #23                 // Method writingOnLockOptions:()V
      15: aload_0
      16: getfield      #19                 // Field lockOptions:Lorg/hibernate/LockOptions;
      19: iload_1
      20: invokevirtual #25                 // Method org/hibernate/LockOptions.setTimeOut:(I)Lorg/hibernate/LockOptions;
      23: pop
      24: return

  public int getLockTimeout();
    Code:
       0: aload_0
       1: getfield      #19                 // Field lockOptions:Lorg/hibernate/LockOptions;
       4: invokevirtual #24                 // Method org/hibernate/LockOptions.getTimeOut:()I
       7: ireturn

  public void setLockScope(boolean);
    Code:
       0: aload_0
       1: getfield      #19                 // Field lockOptions:Lorg/hibernate/LockOptions;
       4: invokevirtual #26                 // Method org/hibernate/LockOptions.getScope:()Z
       7: iload_1
       8: if_icmpeq     24
      11: aload_0
      12: invokespecial #23                 // Method writingOnLockOptions:()V
      15: aload_0
      16: getfield      #19                 // Field lockOptions:Lorg/hibernate/LockOptions;
      19: iload_1
      20: invokevirtual #27                 // Method org/hibernate/LockOptions.setScope:(Z)Lorg/hibernate/LockOptions;
      23: pop
      24: return

  public boolean getLockScope();
    Code:
       0: aload_0
       1: getfield      #19                 // Field lockOptions:Lorg/hibernate/LockOptions;
       4: invokevirtual #26                 // Method org/hibernate/LockOptions.getScope:()Z
       7: ireturn

  public java.lang.Object getResult();
    Code:
       0: aload_0
       1: getfield      #28                 // Field result:Ljava/lang/Object;
       4: areturn

  public void setResult(java.lang.Object);
    Code:
       0: aload_0
       1: aload_1
       2: putfield      #28                 // Field result:Ljava/lang/Object;
       5: return

  public org.hibernate.event.spi.PostLoadEvent getPostLoadEvent();
    Code:
       0: aload_0
       1: getfield      #22                 // Field postLoadEvent:Lorg/hibernate/event/spi/PostLoadEvent;
       4: areturn

  public void setPostLoadEvent(org.hibernate.event.spi.PostLoadEvent);
    Code:
       0: aload_0
       1: aload_1
       2: putfield      #22                 // Field postLoadEvent:Lorg/hibernate/event/spi/PostLoadEvent;
       5: return

  static {};
    Code:
       0: getstatic     #29                 // Field org/hibernate/LockMode.NONE:Lorg/hibernate/LockMode;
       3: putstatic     #5                  // Field DEFAULT_LOCK_MODE:Lorg/hibernate/LockMode;
       6: new           #30                 // class org/hibernate/event/spi/LoadEvent$1
       9: dup
      10: invokespecial #31                 // Method org/hibernate/event/spi/LoadEvent$1."<init>":()V
      13: putstatic     #1                  // Field DEFAULT_LOCK_OPTIONS:Lorg/hibernate/LockOptions;
      16: return
}
