Compiled from "WSHandler.java"
public abstract class org.apache.wss4j.dom.handler.WSHandler {
  private static final org.slf4j.Logger LOG;

  protected java.util.Map<java.lang.String, org.apache.wss4j.common.crypto.Crypto> cryptos;

  private boolean doDebug;

  public org.apache.wss4j.dom.handler.WSHandler();
    Code:
       0: aload_0
       1: invokespecial #1                  // Method java/lang/Object."<init>":()V
       4: aload_0
       5: new           #2                  // class java/util/concurrent/ConcurrentHashMap
       8: dup
       9: invokespecial #3                  // Method java/util/concurrent/ConcurrentHashMap."<init>":()V
      12: putfield      #4                  // Field cryptos:Ljava/util/Map;
      15: aload_0
      16: getstatic     #5                  // Field LOG:Lorg/slf4j/Logger;
      19: invokeinterface #6,  1            // InterfaceMethod org/slf4j/Logger.isDebugEnabled:()Z
      24: putfield      #7                  // Field doDebug:Z
      27: return

  protected void doSenderAction(org.w3c.dom.Document, org.apache.wss4j.dom.handler.RequestData, java.util.List<org.apache.wss4j.dom.handler.HandlerAction>, boolean) throws org.apache.wss4j.common.ext.WSSecurityException;
    Code:
       0: aload_2
       1: invokevirtual #8                  // Method org/apache/wss4j/dom/handler/RequestData.getWssConfig:()Lorg/apache/wss4j/dom/engine/WSSConfig;
       4: astore        5
       6: aload         5
       8: ifnonnull     22
      11: invokestatic  #9                  // Method org/apache/wss4j/dom/engine/WSSConfig.getNewInstance:()Lorg/apache/wss4j/dom/engine/WSSConfig;
      14: astore        5
      16: aload_2
      17: aload         5
      19: invokevirtual #10                 // Method org/apache/wss4j/dom/handler/RequestData.setWssConfig:(Lorg/apache/wss4j/dom/engine/WSSConfig;)V
      22: aload_2
      23: invokevirtual #11                 // Method org/apache/wss4j/dom/handler/RequestData.getMsgContext:()Ljava/lang/Object;
      26: astore        6
      28: aload_2
      29: aload_0
      30: aload         6
      32: ldc           #12                 // String useEncodedPasswords
      34: iconst_0
      35: invokevirtual #13                 // Method decodeBooleanConfigValue:(Ljava/lang/Object;Ljava/lang/String;Z)Z
      38: invokevirtual #14                 // Method org/apache/wss4j/dom/handler/RequestData.setEncodePasswords:(Z)V
      41: aload_2
      42: aload_0
      43: aload         6
      45: ldc           #15                 // String precisionInMilliseconds
      47: iconst_1
      48: invokevirtual #13                 // Method decodeBooleanConfigValue:(Ljava/lang/Object;Ljava/lang/String;Z)Z
      51: invokevirtual #16                 // Method org/apache/wss4j/dom/handler/RequestData.setPrecisionInMilliSeconds:(Z)V
      54: aload_2
      55: aload_0
      56: aload         6
      58: ldc           #17                 // String addInclusivePrefixes
      60: iconst_1
      61: invokevirtual #13                 // Method decodeBooleanConfigValue:(Ljava/lang/Object;Ljava/lang/String;Z)Z
      64: invokevirtual #18                 // Method org/apache/wss4j/dom/handler/RequestData.setAddInclusivePrefixes:(Z)V
      67: aload_2
      68: aload_0
      69: aload         6
      71: ldc           #19                 // String enableSignatureConfirmation
      73: iconst_0
      74: invokevirtual #13                 // Method decodeBooleanConfigValue:(Ljava/lang/Object;Ljava/lang/String;Z)Z
      77: invokevirtual #20                 // Method org/apache/wss4j/dom/handler/RequestData.setEnableSignatureConfirmation:(Z)V
      80: aload_2
      81: aload_0
      82: aload_2
      83: iconst_1
      84: invokevirtual #21                 // Method decodeTimeToLive:(Lorg/apache/wss4j/dom/handler/RequestData;Z)I
      87: invokevirtual #22                 // Method org/apache/wss4j/dom/handler/RequestData.setTimeStampTTL:(I)V
      90: aload_0
      91: ldc           #23                 // String actor
      93: aload         6
      95: invokevirtual #24                 // Method getString:(Ljava/lang/String;Ljava/lang/Object;)Ljava/lang/String;
      98: astore        7
     100: aload_2
     101: aload         7
     103: invokevirtual #25                 // Method org/apache/wss4j/dom/handler/RequestData.setActor:(Ljava/lang/String;)V
     106: aload_0
     107: aload         6
     109: ldc           #26                 // String mustUnderstand
     111: iconst_1
     112: invokevirtual #13                 // Method decodeBooleanConfigValue:(Ljava/lang/Object;Ljava/lang/String;Z)Z
     115: istore        8
     117: new           #27                 // class org/apache/wss4j/dom/message/WSSecHeader
     120: dup
     121: aload         7
     123: iload         8
     125: aload_1
     126: invokespecial #28                 // Method org/apache/wss4j/dom/message/WSSecHeader."<init>":(Ljava/lang/String;ZLorg/w3c/dom/Document;)V
     129: astore        9
     131: aload         9
     133: invokevirtual #29                 // Method org/apache/wss4j/dom/message/WSSecHeader.insertSecurityHeader:()Lorg/w3c/dom/Element;
     136: pop
     137: aload_2
     138: aload         9
     140: invokevirtual #30                 // Method org/apache/wss4j/dom/handler/RequestData.setSecHeader:(Lorg/apache/wss4j/dom/message/WSSecHeader;)V
     143: aload_2
     144: aload_1
     145: invokeinterface #31,  1           // InterfaceMethod org/w3c/dom/Document.getDocumentElement:()Lorg/w3c/dom/Element;
     150: invokestatic  #32                 // Method org/apache/wss4j/dom/util/WSSecurityUtil.getSOAPConstants:(Lorg/w3c/dom/Element;)Lorg/apache/wss4j/dom/SOAPConstants;
     153: invokevirtual #33                 // Method org/apache/wss4j/dom/handler/RequestData.setSoapConstants:(Lorg/apache/wss4j/dom/SOAPConstants;)V
     156: aload_2
     157: invokevirtual #34                 // Method org/apache/wss4j/dom/handler/RequestData.getCallbackHandler:()Ljavax/security/auth/callback/CallbackHandler;
     160: ifnonnull     176
     163: aload_0
     164: aload_2
     165: invokevirtual #35                 // Method getPasswordCallbackHandler:(Lorg/apache/wss4j/dom/handler/RequestData;)Ljavax/security/auth/callback/CallbackHandler;
     168: astore        10
     170: aload_2
     171: aload         10
     173: invokevirtual #36                 // Method org/apache/wss4j/dom/handler/RequestData.setCallbackHandler:(Ljavax/security/auth/callback/CallbackHandler;)V
     176: aload_0
     177: aload         6
     179: ldc           #37                 // String storeBytesInAttachment
     181: iconst_0
     182: invokevirtual #13                 // Method decodeBooleanConfigValue:(Ljava/lang/Object;Ljava/lang/String;Z)Z
     185: istore        10
     187: aload_2
     188: iload         10
     190: invokevirtual #38                 // Method org/apache/wss4j/dom/handler/RequestData.setStoreBytesInAttachment:(Z)V
     193: iconst_0
     194: istore        11
     196: aload_3
     197: invokeinterface #39,  1           // InterfaceMethod java/util/List.iterator:()Ljava/util/Iterator;
     202: astore        12
     204: aload         12
     206: invokeinterface #40,  1           // InterfaceMethod java/util/Iterator.hasNext:()Z
     211: ifeq          537
     214: aload         12
     216: invokeinterface #41,  1           // InterfaceMethod java/util/Iterator.next:()Ljava/lang/Object;
     221: checkcast     #42                 // class org/apache/wss4j/dom/handler/HandlerAction
     224: astore        13
     226: aload         13
     228: invokevirtual #43                 // Method org/apache/wss4j/dom/handler/HandlerAction.getAction:()Ljava/lang/Integer;
     231: invokevirtual #44                 // Method java/lang/Integer.intValue:()I
     234: sipush        128
     237: if_icmpne     248
     240: aload_2
     241: iconst_1
     242: invokevirtual #20                 // Method org/apache/wss4j/dom/handler/RequestData.setEnableSignatureConfirmation:(Z)V
     245: goto          534
     248: aload         13
     250: invokevirtual #43                 // Method org/apache/wss4j/dom/handler/HandlerAction.getAction:()Ljava/lang/Integer;
     253: invokevirtual #44                 // Method java/lang/Integer.intValue:()I
     256: iconst_1
     257: if_icmpne     276
     260: aload         13
     262: invokevirtual #45                 // Method org/apache/wss4j/dom/handler/HandlerAction.getActionToken:()Lorg/apache/wss4j/common/SecurityActionToken;
     265: ifnonnull     276
     268: aload_0
     269: aload_2
     270: invokevirtual #46                 // Method decodeUTParameter:(Lorg/apache/wss4j/dom/handler/RequestData;)V
     273: goto          534
     276: aload         13
     278: invokevirtual #43                 // Method org/apache/wss4j/dom/handler/HandlerAction.getAction:()Ljava/lang/Integer;
     281: invokevirtual #44                 // Method java/lang/Integer.intValue:()I
     284: bipush        64
     286: if_icmpne     310
     289: aload         13
     291: invokevirtual #45                 // Method org/apache/wss4j/dom/handler/HandlerAction.getActionToken:()Lorg/apache/wss4j/common/SecurityActionToken;
     294: ifnonnull     310
     297: aload_0
     298: aload_2
     299: invokevirtual #46                 // Method decodeUTParameter:(Lorg/apache/wss4j/dom/handler/RequestData;)V
     302: aload_0
     303: aload_2
     304: invokevirtual #47                 // Method decodeSignatureParameter:(Lorg/apache/wss4j/dom/handler/RequestData;)V
     307: goto          534
     310: aload         13
     312: invokevirtual #43                 // Method org/apache/wss4j/dom/handler/HandlerAction.getAction:()Ljava/lang/Integer;
     315: invokevirtual #44                 // Method java/lang/Integer.intValue:()I
     318: iconst_2
     319: if_icmpeq     335
     322: aload         13
     324: invokevirtual #43                 // Method org/apache/wss4j/dom/handler/HandlerAction.getAction:()Ljava/lang/Integer;
     327: invokevirtual #44                 // Method java/lang/Integer.intValue:()I
     330: ldc           #48                 // int 32768
     332: if_icmpne     420
     335: aload         13
     337: invokevirtual #45                 // Method org/apache/wss4j/dom/handler/HandlerAction.getActionToken:()Lorg/apache/wss4j/common/SecurityActionToken;
     340: ifnonnull     420
     343: aload_2
     344: invokevirtual #49                 // Method org/apache/wss4j/dom/handler/RequestData.getSignatureToken:()Lorg/apache/wss4j/common/SignatureActionToken;
     347: astore        14
     349: aload         14
     351: ifnonnull     369
     354: new           #50                 // class org/apache/wss4j/common/SignatureActionToken
     357: dup
     358: invokespecial #51                 // Method org/apache/wss4j/common/SignatureActionToken."<init>":()V
     361: astore        14
     363: aload_2
     364: aload         14
     366: invokevirtual #52                 // Method org/apache/wss4j/dom/handler/RequestData.setSignatureToken:(Lorg/apache/wss4j/common/SignatureActionToken;)V
     369: aload         14
     371: invokevirtual #53                 // Method org/apache/wss4j/common/SignatureActionToken.getCrypto:()Lorg/apache/wss4j/common/crypto/Crypto;
     374: ifnonnull     387
     377: aload         14
     379: aload_0
     380: aload_2
     381: invokevirtual #54                 // Method loadSignatureCrypto:(Lorg/apache/wss4j/dom/handler/RequestData;)Lorg/apache/wss4j/common/crypto/Crypto;
     384: invokevirtual #55                 // Method org/apache/wss4j/common/SignatureActionToken.setCrypto:(Lorg/apache/wss4j/common/crypto/Crypto;)V
     387: aload_0
     388: aload_2
     389: invokevirtual #47                 // Method decodeSignatureParameter:(Lorg/apache/wss4j/dom/handler/RequestData;)V
     392: iload         11
     394: ifeq          417
     397: iload         10
     399: ifeq          417
     402: getstatic     #5                  // Field LOG:Lorg/slf4j/Logger;
     405: ldc           #56                 // String Turning off storeBytesInAttachment as we have encryption before signature. The danger here is that the actual encryption bytes will not be signed
     407: invokeinterface #57,  2           // InterfaceMethod org/slf4j/Logger.warn:(Ljava/lang/String;)V
     412: aload_2
     413: iconst_0
     414: invokevirtual #38                 // Method org/apache/wss4j/dom/handler/RequestData.setStoreBytesInAttachment:(Z)V
     417: goto          534
     420: aload         13
     422: invokevirtual #43                 // Method org/apache/wss4j/dom/handler/HandlerAction.getAction:()Ljava/lang/Integer;
     425: invokevirtual #44                 // Method java/lang/Integer.intValue:()I
     428: bipush        16
     430: if_icmpne     449
     433: aload         13
     435: invokevirtual #45                 // Method org/apache/wss4j/dom/handler/HandlerAction.getActionToken:()Lorg/apache/wss4j/common/SecurityActionToken;
     438: ifnonnull     449
     441: aload_0
     442: aload_2
     443: invokevirtual #47                 // Method decodeSignatureParameter:(Lorg/apache/wss4j/dom/handler/RequestData;)V
     446: goto          534
     449: aload         13
     451: invokevirtual #43                 // Method org/apache/wss4j/dom/handler/HandlerAction.getAction:()Ljava/lang/Integer;
     454: invokevirtual #44                 // Method java/lang/Integer.intValue:()I
     457: iconst_4
     458: if_icmpeq     474
     461: aload         13
     463: invokevirtual #43                 // Method org/apache/wss4j/dom/handler/HandlerAction.getAction:()Ljava/lang/Integer;
     466: invokevirtual #44                 // Method java/lang/Integer.intValue:()I
     469: ldc           #58                 // int 65536
     471: if_icmpne     534
     474: aload         13
     476: invokevirtual #45                 // Method org/apache/wss4j/dom/handler/HandlerAction.getActionToken:()Lorg/apache/wss4j/common/SecurityActionToken;
     479: ifnonnull     534
     482: iconst_1
     483: istore        11
     485: aload_2
     486: invokevirtual #59                 // Method org/apache/wss4j/dom/handler/RequestData.getEncryptionToken:()Lorg/apache/wss4j/common/EncryptionActionToken;
     489: astore        14
     491: aload         14
     493: ifnonnull     511
     496: new           #60                 // class org/apache/wss4j/common/EncryptionActionToken
     499: dup
     500: invokespecial #61                 // Method org/apache/wss4j/common/EncryptionActionToken."<init>":()V
     503: astore        14
     505: aload_2
     506: aload         14
     508: invokevirtual #62                 // Method org/apache/wss4j/dom/handler/RequestData.setEncryptionToken:(Lorg/apache/wss4j/common/EncryptionActionToken;)V
     511: aload         14
     513: invokevirtual #63                 // Method org/apache/wss4j/common/EncryptionActionToken.getCrypto:()Lorg/apache/wss4j/common/crypto/Crypto;
     516: ifnonnull     529
     519: aload         14
     521: aload_0
     522: aload_2
     523: invokevirtual #64                 // Method loadEncryptionCrypto:(Lorg/apache/wss4j/dom/handler/RequestData;)Lorg/apache/wss4j/common/crypto/Crypto;
     526: invokevirtual #65                 // Method org/apache/wss4j/common/EncryptionActionToken.setCrypto:(Lorg/apache/wss4j/common/crypto/Crypto;)V
     529: aload_0
     530: aload_2
     531: invokevirtual #66                 // Method decodeEncryptionParameter:(Lorg/apache/wss4j/dom/handler/RequestData;)V
     534: goto          204
     537: aload_2
     538: invokevirtual #49                 // Method org/apache/wss4j/dom/handler/RequestData.getSignatureToken:()Lorg/apache/wss4j/common/SignatureActionToken;
     541: astore        12
     543: aload         12
     545: ifnonnull     563
     548: new           #50                 // class org/apache/wss4j/common/SignatureActionToken
     551: dup
     552: invokespecial #51                 // Method org/apache/wss4j/common/SignatureActionToken."<init>":()V
     555: astore        12
     557: aload_2
     558: aload         12
     560: invokevirtual #52                 // Method org/apache/wss4j/dom/handler/RequestData.setSignatureToken:(Lorg/apache/wss4j/common/SignatureActionToken;)V
     563: aload         12
     565: invokevirtual #67                 // Method org/apache/wss4j/common/SignatureActionToken.getParts:()Ljava/util/List;
     568: invokeinterface #68,  1           // InterfaceMethod java/util/List.isEmpty:()Z
     573: ifeq          591
     576: aload         12
     578: invokevirtual #67                 // Method org/apache/wss4j/common/SignatureActionToken.getParts:()Ljava/util/List;
     581: aload_1
     582: invokestatic  #69                 // Method org/apache/wss4j/dom/util/WSSecurityUtil.getDefaultEncryptionPart:(Lorg/w3c/dom/Document;)Lorg/apache/wss4j/common/WSEncryptionPart;
     585: invokeinterface #70,  2           // InterfaceMethod java/util/List.add:(Ljava/lang/Object;)Z
     590: pop
     591: aload_2
     592: invokevirtual #71                 // Method org/apache/wss4j/dom/handler/RequestData.isEnableSignatureConfirmation:()Z
     595: ifeq          640
     598: iload         4
     600: ifne          640
     603: aload_0
     604: aload_2
     605: invokevirtual #11                 // Method org/apache/wss4j/dom/handler/RequestData.getMsgContext:()Ljava/lang/Object;
     608: ldc           #72                 // String _sigConfDone_
     610: invokevirtual #73                 // Method getProperty:(Ljava/lang/Object;Ljava/lang/String;)Ljava/lang/Object;
     613: checkcast     #74                 // class java/lang/String
     616: astore        13
     618: aload         13
     620: ifnonnull     640
     623: aload         5
     625: sipush        128
     628: invokevirtual #75                 // Method org/apache/wss4j/dom/engine/WSSConfig.getAction:(I)Lorg/apache/wss4j/dom/action/Action;
     631: aload_0
     632: aconst_null
     633: aload_1
     634: aload_2
     635: invokeinterface #76,  5           // InterfaceMethod org/apache/wss4j/dom/action/Action.execute:(Lorg/apache/wss4j/dom/handler/WSHandler;Lorg/apache/wss4j/common/SecurityActionToken;Lorg/w3c/dom/Document;Lorg/apache/wss4j/dom/handler/RequestData;)V
     640: aload_3
     641: astore        13
     643: aload_0
     644: aload_3
     645: aload_2
     646: invokespecial #77                 // Method getSignatureActionThatSignsATimestamp:(Ljava/util/List;Lorg/apache/wss4j/dom/handler/RequestData;)Lorg/apache/wss4j/dom/handler/HandlerAction;
     649: astore        14
     651: aload         14
     653: ifnull        713
     656: new           #78                 // class java/util/ArrayList
     659: dup
     660: aload_3
     661: invokespecial #79                 // Method java/util/ArrayList."<init>":(Ljava/util/Collection;)V
     664: astore        13
     666: aload         13
     668: aload_3
     669: invokestatic  #80                 // Method java/util/Collections.copy:(Ljava/util/List;Ljava/util/List;)V
     672: aload_3
     673: aload         14
     675: invokeinterface #81,  2           // InterfaceMethod java/util/List.indexOf:(Ljava/lang/Object;)I
     680: istore        15
     682: aload         13
     684: aload         14
     686: invokeinterface #82,  2           // InterfaceMethod java/util/List.remove:(Ljava/lang/Object;)Z
     691: pop
     692: aload         13
     694: aload         14
     696: invokeinterface #70,  2           // InterfaceMethod java/util/List.add:(Ljava/lang/Object;)Z
     701: pop
     702: aload_2
     703: iconst_1
     704: invokevirtual #83                 // Method org/apache/wss4j/dom/handler/RequestData.setAppendSignatureAfterTimestamp:(Z)V
     707: aload_2
     708: iload         15
     710: invokevirtual #84                 // Method org/apache/wss4j/dom/handler/RequestData.setOriginalSignatureActionPosition:(I)V
     713: aload         13
     715: invokeinterface #39,  1           // InterfaceMethod java/util/List.iterator:()Ljava/util/Iterator;
     720: astore        15
     722: aload         15
     724: invokeinterface #40,  1           // InterfaceMethod java/util/Iterator.hasNext:()Z
     729: ifeq          823
     732: aload         15
     734: invokeinterface #41,  1           // InterfaceMethod java/util/Iterator.next:()Ljava/lang/Object;
     739: checkcast     #42                 // class org/apache/wss4j/dom/handler/HandlerAction
     742: astore        16
     744: aload_0
     745: getfield      #7                  // Field doDebug:Z
     748: ifeq          782
     751: getstatic     #5                  // Field LOG:Lorg/slf4j/Logger;
     754: new           #85                 // class java/lang/StringBuilder
     757: dup
     758: invokespecial #86                 // Method java/lang/StringBuilder."<init>":()V
     761: ldc           #87                 // String Performing Action:
     763: invokevirtual #88                 // Method java/lang/StringBuilder.append:(Ljava/lang/String;)Ljava/lang/StringBuilder;
     766: aload         16
     768: invokevirtual #43                 // Method org/apache/wss4j/dom/handler/HandlerAction.getAction:()Ljava/lang/Integer;
     771: invokevirtual #89                 // Method java/lang/StringBuilder.append:(Ljava/lang/Object;)Ljava/lang/StringBuilder;
     774: invokevirtual #90                 // Method java/lang/StringBuilder.toString:()Ljava/lang/String;
     777: invokeinterface #91,  2           // InterfaceMethod org/slf4j/Logger.debug:(Ljava/lang/String;)V
     782: iconst_0
     783: aload         16
     785: invokevirtual #43                 // Method org/apache/wss4j/dom/handler/HandlerAction.getAction:()Ljava/lang/Integer;
     788: invokevirtual #44                 // Method java/lang/Integer.intValue:()I
     791: if_icmpeq     820
     794: aload         5
     796: aload         16
     798: invokevirtual #43                 // Method org/apache/wss4j/dom/handler/HandlerAction.getAction:()Ljava/lang/Integer;
     801: invokevirtual #44                 // Method java/lang/Integer.intValue:()I
     804: invokevirtual #75                 // Method org/apache/wss4j/dom/engine/WSSConfig.getAction:(I)Lorg/apache/wss4j/dom/action/Action;
     807: aload_0
     808: aload         16
     810: invokevirtual #45                 // Method org/apache/wss4j/dom/handler/HandlerAction.getActionToken:()Lorg/apache/wss4j/common/SecurityActionToken;
     813: aload_1
     814: aload_2
     815: invokeinterface #76,  5           // InterfaceMethod org/apache/wss4j/dom/action/Action.execute:(Lorg/apache/wss4j/dom/handler/WSHandler;Lorg/apache/wss4j/common/SecurityActionToken;Lorg/w3c/dom/Document;Lorg/apache/wss4j/dom/handler/RequestData;)V
     820: goto          722
     823: aload_2
     824: invokevirtual #71                 // Method org/apache/wss4j/dom/handler/RequestData.isEnableSignatureConfirmation:()Z
     827: ifeq          940
     830: iload         4
     832: ifeq          940
     835: aload_2
     836: invokevirtual #92                 // Method org/apache/wss4j/dom/handler/RequestData.getSignatureValues:()Ljava/util/List;
     839: invokeinterface #93,  1           // InterfaceMethod java/util/List.size:()I
     844: ifle          940
     847: aload_0
     848: aload_2
     849: invokevirtual #11                 // Method org/apache/wss4j/dom/handler/RequestData.getMsgContext:()Ljava/lang/Object;
     852: ldc           #94                 // String _sendSignatureValues_
     854: invokevirtual #73                 // Method getProperty:(Ljava/lang/Object;Ljava/lang/String;)Ljava/lang/Object;
     857: checkcast     #95                 // class java/util/Set
     860: astore        15
     862: aload         15
     864: ifnonnull     888
     867: new           #96                 // class java/util/HashSet
     870: dup
     871: invokespecial #97                 // Method java/util/HashSet."<init>":()V
     874: astore        15
     876: aload_0
     877: aload_2
     878: invokevirtual #11                 // Method org/apache/wss4j/dom/handler/RequestData.getMsgContext:()Ljava/lang/Object;
     881: ldc           #94                 // String _sendSignatureValues_
     883: aload         15
     885: invokevirtual #98                 // Method setProperty:(Ljava/lang/Object;Ljava/lang/String;Ljava/lang/Object;)V
     888: aload_2
     889: invokevirtual #92                 // Method org/apache/wss4j/dom/handler/RequestData.getSignatureValues:()Ljava/util/List;
     892: invokeinterface #39,  1           // InterfaceMethod java/util/List.iterator:()Ljava/util/Iterator;
     897: astore        16
     899: aload         16
     901: invokeinterface #40,  1           // InterfaceMethod java/util/Iterator.hasNext:()Z
     906: ifeq          940
     909: aload         16
     911: invokeinterface #41,  1           // InterfaceMethod java/util/Iterator.next:()Ljava/lang/Object;
     916: checkcast     #99                 // class "[B"
     919: astore        17
     921: aload         15
     923: aload         17
     925: invokestatic  #100                // Method java/util/Arrays.hashCode:([B)I
     928: invokestatic  #101                // Method java/lang/Integer.valueOf:(I)Ljava/lang/Integer;
     931: invokeinterface #102,  2          // InterfaceMethod java/util/Set.add:(Ljava/lang/Object;)Z
     936: pop
     937: goto          899
     940: return

  private org.apache.wss4j.dom.handler.HandlerAction getSignatureActionThatSignsATimestamp(java.util.List<org.apache.wss4j.dom.handler.HandlerAction>, org.apache.wss4j.dom.handler.RequestData);
    Code:
       0: aload_1
       1: invokeinterface #39,  1           // InterfaceMethod java/util/List.iterator:()Ljava/util/Iterator;
       6: astore_3
       7: aload_3
       8: invokeinterface #40,  1           // InterfaceMethod java/util/Iterator.hasNext:()Z
      13: ifeq          222
      16: aload_3
      17: invokeinterface #41,  1           // InterfaceMethod java/util/Iterator.next:()Ljava/lang/Object;
      22: checkcast     #42                 // class org/apache/wss4j/dom/handler/HandlerAction
      25: astore        4
      27: aload         4
      29: invokevirtual #43                 // Method org/apache/wss4j/dom/handler/HandlerAction.getAction:()Ljava/lang/Integer;
      32: invokevirtual #44                 // Method java/lang/Integer.intValue:()I
      35: bipush        32
      37: if_icmpne     42
      40: aconst_null
      41: areturn
      42: aload         4
      44: invokevirtual #43                 // Method org/apache/wss4j/dom/handler/HandlerAction.getAction:()Ljava/lang/Integer;
      47: invokevirtual #44                 // Method java/lang/Integer.intValue:()I
      50: iconst_2
      51: if_icmpne     219
      54: aload         4
      56: invokevirtual #45                 // Method org/apache/wss4j/dom/handler/HandlerAction.getActionToken:()Lorg/apache/wss4j/common/SecurityActionToken;
      59: ifnull        151
      62: aload         4
      64: invokevirtual #45                 // Method org/apache/wss4j/dom/handler/HandlerAction.getActionToken:()Lorg/apache/wss4j/common/SecurityActionToken;
      67: checkcast     #103                // class org/apache/wss4j/common/SignatureEncryptionActionToken
      70: invokevirtual #104                // Method org/apache/wss4j/common/SignatureEncryptionActionToken.getParts:()Ljava/util/List;
      73: ifnull        151
      76: aload         4
      78: invokevirtual #45                 // Method org/apache/wss4j/dom/handler/HandlerAction.getActionToken:()Lorg/apache/wss4j/common/SecurityActionToken;
      81: checkcast     #103                // class org/apache/wss4j/common/SignatureEncryptionActionToken
      84: invokevirtual #104                // Method org/apache/wss4j/common/SignatureEncryptionActionToken.getParts:()Ljava/util/List;
      87: invokeinterface #39,  1           // InterfaceMethod java/util/List.iterator:()Ljava/util/Iterator;
      92: astore        5
      94: aload         5
      96: invokeinterface #40,  1           // InterfaceMethod java/util/Iterator.hasNext:()Z
     101: ifeq          148
     104: aload         5
     106: invokeinterface #41,  1           // InterfaceMethod java/util/Iterator.next:()Ljava/lang/Object;
     111: checkcast     #105                // class org/apache/wss4j/common/WSEncryptionPart
     114: astore        6
     116: ldc           #106                // String http://docs.oasis-open.org/wss/2004/01/oasis-200401-wss-wssecurity-utility-1.0.xsd
     118: aload         6
     120: invokevirtual #107                // Method org/apache/wss4j/common/WSEncryptionPart.getNamespace:()Ljava/lang/String;
     123: invokevirtual #108                // Method java/lang/String.equals:(Ljava/lang/Object;)Z
     126: ifeq          145
     129: ldc           #109                // String Timestamp
     131: aload         6
     133: invokevirtual #110                // Method org/apache/wss4j/common/WSEncryptionPart.getName:()Ljava/lang/String;
     136: invokevirtual #108                // Method java/lang/String.equals:(Ljava/lang/Object;)Z
     139: ifeq          145
     142: aload         4
     144: areturn
     145: goto          94
     148: goto          219
     151: aload_2
     152: invokevirtual #49                 // Method org/apache/wss4j/dom/handler/RequestData.getSignatureToken:()Lorg/apache/wss4j/common/SignatureActionToken;
     155: invokevirtual #67                 // Method org/apache/wss4j/common/SignatureActionToken.getParts:()Ljava/util/List;
     158: invokeinterface #39,  1           // InterfaceMethod java/util/List.iterator:()Ljava/util/Iterator;
     163: astore        5
     165: aload         5
     167: invokeinterface #40,  1           // InterfaceMethod java/util/Iterator.hasNext:()Z
     172: ifeq          219
     175: aload         5
     177: invokeinterface #41,  1           // InterfaceMethod java/util/Iterator.next:()Ljava/lang/Object;
     182: checkcast     #105                // class org/apache/wss4j/common/WSEncryptionPart
     185: astore        6
     187: ldc           #106                // String http://docs.oasis-open.org/wss/2004/01/oasis-200401-wss-wssecurity-utility-1.0.xsd
     189: aload         6
     191: invokevirtual #107                // Method org/apache/wss4j/common/WSEncryptionPart.getNamespace:()Ljava/lang/String;
     194: invokevirtual #108                // Method java/lang/String.equals:(Ljava/lang/Object;)Z
     197: ifeq          216
     200: ldc           #109                // String Timestamp
     202: aload         6
     204: invokevirtual #110                // Method org/apache/wss4j/common/WSEncryptionPart.getName:()Ljava/lang/String;
     207: invokevirtual #108                // Method java/lang/String.equals:(Ljava/lang/Object;)Z
     210: ifeq          216
     213: aload         4
     215: areturn
     216: goto          165
     219: goto          7
     222: aconst_null
     223: areturn

  protected void doReceiverAction(java.util.List<java.lang.Integer>, org.apache.wss4j.dom.handler.RequestData) throws org.apache.wss4j.common.ext.WSSecurityException;
    Code:
       0: aload_2
       1: invokevirtual #8                  // Method org/apache/wss4j/dom/handler/RequestData.getWssConfig:()Lorg/apache/wss4j/dom/engine/WSSConfig;
       4: astore_3
       5: aload_3
       6: ifnonnull     18
       9: invokestatic  #9                  // Method org/apache/wss4j/dom/engine/WSSConfig.getNewInstance:()Lorg/apache/wss4j/dom/engine/WSSConfig;
      12: astore_3
      13: aload_2
      14: aload_3
      15: invokevirtual #10                 // Method org/apache/wss4j/dom/handler/RequestData.setWssConfig:(Lorg/apache/wss4j/dom/engine/WSSConfig;)V
      18: aload_2
      19: invokevirtual #11                 // Method org/apache/wss4j/dom/handler/RequestData.getMsgContext:()Ljava/lang/Object;
      22: astore        4
      24: aload_0
      25: aload         4
      27: ldc           #19                 // String enableSignatureConfirmation
      29: iconst_0
      30: invokevirtual #13                 // Method decodeBooleanConfigValue:(Ljava/lang/Object;Ljava/lang/String;Z)Z
      33: istore        5
      35: aload_2
      36: iload         5
      38: ifne          56
      41: aload_1
      42: sipush        128
      45: invokestatic  #101                // Method java/lang/Integer.valueOf:(I)Ljava/lang/Integer;
      48: invokeinterface #111,  2          // InterfaceMethod java/util/List.contains:(Ljava/lang/Object;)Z
      53: ifeq          60
      56: iconst_1
      57: goto          61
      60: iconst_0
      61: invokevirtual #20                 // Method org/apache/wss4j/dom/handler/RequestData.setEnableSignatureConfirmation:(Z)V
      64: aload_2
      65: aload_0
      66: aload         4
      68: ldc           #112                // String timestampStrict
      70: iconst_1
      71: invokevirtual #13                 // Method decodeBooleanConfigValue:(Ljava/lang/Object;Ljava/lang/String;Z)Z
      74: invokevirtual #113                // Method org/apache/wss4j/dom/handler/RequestData.setTimeStampStrict:(Z)V
      77: aload_2
      78: aload_0
      79: aload_2
      80: invokevirtual #114                // Method decodePasswordType:(Lorg/apache/wss4j/dom/handler/RequestData;)Ljava/lang/String;
      83: invokevirtual #115                // Method org/apache/wss4j/dom/handler/RequestData.setRequiredPasswordType:(Ljava/lang/String;)V
      86: aload_2
      87: aload_0
      88: aload_2
      89: iconst_1
      90: invokevirtual #21                 // Method decodeTimeToLive:(Lorg/apache/wss4j/dom/handler/RequestData;Z)I
      93: invokevirtual #22                 // Method org/apache/wss4j/dom/handler/RequestData.setTimeStampTTL:(I)V
      96: aload_2
      97: aload_0
      98: aload_2
      99: iconst_1
     100: invokevirtual #116                // Method decodeFutureTimeToLive:(Lorg/apache/wss4j/dom/handler/RequestData;Z)I
     103: invokevirtual #117                // Method org/apache/wss4j/dom/handler/RequestData.setTimeStampFutureTTL:(I)V
     106: aload_2
     107: aload_0
     108: aload_2
     109: iconst_0
     110: invokevirtual #21                 // Method decodeTimeToLive:(Lorg/apache/wss4j/dom/handler/RequestData;Z)I
     113: invokevirtual #118                // Method org/apache/wss4j/dom/handler/RequestData.setUtTTL:(I)V
     116: aload_2
     117: aload_0
     118: aload_2
     119: iconst_0
     120: invokevirtual #116                // Method decodeFutureTimeToLive:(Lorg/apache/wss4j/dom/handler/RequestData;Z)I
     123: invokevirtual #119                // Method org/apache/wss4j/dom/handler/RequestData.setUtFutureTTL:(I)V
     126: aload_2
     127: aload_0
     128: aload         4
     130: ldc           #120                // String handleCustomPasswordTypes
     132: iconst_0
     133: invokevirtual #13                 // Method decodeBooleanConfigValue:(Ljava/lang/Object;Ljava/lang/String;Z)Z
     136: invokevirtual #121                // Method org/apache/wss4j/dom/handler/RequestData.setHandleCustomPasswordTypes:(Z)V
     139: aload_2
     140: aload_0
     141: aload         4
     143: ldc           #12                 // String useEncodedPasswords
     145: iconst_0
     146: invokevirtual #13                 // Method decodeBooleanConfigValue:(Ljava/lang/Object;Ljava/lang/String;Z)Z
     149: invokevirtual #14                 // Method org/apache/wss4j/dom/handler/RequestData.setEncodePasswords:(Z)V
     152: aload_2
     153: aload_0
     154: aload         4
     156: ldc           #122                // String allowNamespaceQualifiedPasswordTypes
     158: iconst_0
     159: invokevirtual #13                 // Method decodeBooleanConfigValue:(Ljava/lang/Object;Ljava/lang/String;Z)Z
     162: invokevirtual #123                // Method org/apache/wss4j/dom/handler/RequestData.setAllowNamespaceQualifiedPasswordTypes:(Z)V
     165: aload_2
     166: aload_0
     167: aload         4
     169: ldc           #124                // String allowUsernameTokenNoPassword
     171: iconst_0
     172: invokevirtual #13                 // Method decodeBooleanConfigValue:(Ljava/lang/Object;Ljava/lang/String;Z)Z
     175: invokevirtual #125                // Method org/apache/wss4j/dom/handler/RequestData.setAllowUsernameTokenNoPassword:(Z)V
     178: aload_2
     179: aload_0
     180: aload         4
     182: ldc           #126                // String validateSamlSubjectConfirmation
     184: iconst_1
     185: invokevirtual #13                 // Method decodeBooleanConfigValue:(Ljava/lang/Object;Ljava/lang/String;Z)Z
     188: invokevirtual #127                // Method org/apache/wss4j/dom/handler/RequestData.setValidateSamlSubjectConfirmation:(Z)V
     191: aload_0
     192: aload         4
     194: ldc           #128                // String isBSPCompliant
     196: iconst_1
     197: invokevirtual #13                 // Method decodeBooleanConfigValue:(Ljava/lang/Object;Ljava/lang/String;Z)Z
     200: istore        6
     202: iload         6
     204: ifne          212
     207: aload_2
     208: iconst_1
     209: invokevirtual #129                // Method org/apache/wss4j/dom/handler/RequestData.setDisableBSPEnforcement:(Z)V
     212: aload_2
     213: invokevirtual #34                 // Method org/apache/wss4j/dom/handler/RequestData.getCallbackHandler:()Ljavax/security/auth/callback/CallbackHandler;
     216: ifnonnull     232
     219: aload_0
     220: aload_2
     221: invokevirtual #35                 // Method getPasswordCallbackHandler:(Lorg/apache/wss4j/dom/handler/RequestData;)Ljavax/security/auth/callback/CallbackHandler;
     224: astore        7
     226: aload_2
     227: aload         7
     229: invokevirtual #36                 // Method org/apache/wss4j/dom/handler/RequestData.setCallbackHandler:(Ljavax/security/auth/callback/CallbackHandler;)V
     232: aload_1
     233: iconst_2
     234: invokestatic  #101                // Method java/lang/Integer.valueOf:(I)Ljava/lang/Integer;
     237: invokeinterface #111,  2          // InterfaceMethod java/util/List.contains:(Ljava/lang/Object;)Z
     242: ifne          273
     245: aload_1
     246: bipush        16
     248: invokestatic  #101                // Method java/lang/Integer.valueOf:(I)Ljava/lang/Integer;
     251: invokeinterface #111,  2          // InterfaceMethod java/util/List.contains:(Ljava/lang/Object;)Z
     256: ifne          273
     259: aload_1
     260: bipush        8
     262: invokestatic  #101                // Method java/lang/Integer.valueOf:(I)Ljava/lang/Integer;
     265: invokeinterface #111,  2          // InterfaceMethod java/util/List.contains:(Ljava/lang/Object;)Z
     270: ifeq          278
     273: aload_0
     274: aload_2
     275: invokevirtual #130                // Method decodeSignatureParameter2:(Lorg/apache/wss4j/dom/handler/RequestData;)V
     278: aload_1
     279: iconst_4
     280: invokestatic  #101                // Method java/lang/Integer.valueOf:(I)Ljava/lang/Integer;
     283: invokeinterface #111,  2          // InterfaceMethod java/util/List.contains:(Ljava/lang/Object;)Z
     288: ifeq          296
     291: aload_0
     292: aload_2
     293: invokevirtual #131                // Method decodeDecryptionParameter:(Lorg/apache/wss4j/dom/handler/RequestData;)V
     296: aload_2
     297: aload_0
     298: aload         4
     300: ldc           #132                // String requireSignedEncryptedDataElements
     302: iconst_0
     303: invokevirtual #13                 // Method decodeBooleanConfigValue:(Ljava/lang/Object;Ljava/lang/String;Z)Z
     306: invokevirtual #133                // Method org/apache/wss4j/dom/handler/RequestData.setRequireSignedEncryptedDataElements:(Z)V
     309: aload_2
     310: aload_0
     311: aload         4
     313: ldc           #134                // String requireTimestampExpires
     315: iconst_0
     316: invokevirtual #13                 // Method decodeBooleanConfigValue:(Ljava/lang/Object;Ljava/lang/String;Z)Z
     319: invokevirtual #135                // Method org/apache/wss4j/dom/handler/RequestData.setRequireTimestampExpires:(Z)V
     322: return

  protected boolean checkReceiverResults(java.util.List<org.apache.wss4j.dom.engine.WSSecurityEngineResult>, java.util.List<java.lang.Integer>);
    Code:
       0: aload_2
       1: invokeinterface #93,  1           // InterfaceMethod java/util/List.size:()I
       6: istore_3
       7: iconst_0
       8: istore        4
      10: aload_1
      11: invokeinterface #39,  1           // InterfaceMethod java/util/List.iterator:()Ljava/util/Iterator;
      16: astore        5
      18: aload         5
      20: invokeinterface #40,  1           // InterfaceMethod java/util/Iterator.hasNext:()Z
      25: ifeq          116
      28: aload         5
      30: invokeinterface #41,  1           // InterfaceMethod java/util/Iterator.next:()Ljava/lang/Object;
      35: checkcast     #136                // class org/apache/wss4j/dom/engine/WSSecurityEngineResult
      38: astore        6
      40: aload         6
      42: ldc           #137                // String action
      44: invokevirtual #138                // Method org/apache/wss4j/dom/engine/WSSecurityEngineResult.get:(Ljava/lang/Object;)Ljava/lang/Object;
      47: checkcast     #139                // class java/lang/Integer
      50: astore        7
      52: aload         7
      54: ifnull        113
      57: aload         7
      59: invokevirtual #44                 // Method java/lang/Integer.intValue:()I
      62: istore        8
      64: iload         8
      66: sipush        128
      69: if_icmpeq     18
      72: iload         8
      74: sipush        4096
      77: if_icmpne     83
      80: goto          18
      83: iload         4
      85: iload_3
      86: if_icmpge     111
      89: aload_2
      90: iload         4
      92: iinc          4, 1
      95: invokeinterface #140,  2          // InterfaceMethod java/util/List.get:(I)Ljava/lang/Object;
     100: checkcast     #139                // class java/lang/Integer
     103: invokevirtual #44                 // Method java/lang/Integer.intValue:()I
     106: iload         8
     108: if_icmpeq     113
     111: iconst_0
     112: ireturn
     113: goto          18
     116: iload         4
     118: iload_3
     119: if_icmpeq     124
     122: iconst_0
     123: ireturn
     124: iconst_1
     125: ireturn

  protected boolean checkReceiverResultsAnyOrder(java.util.List<org.apache.wss4j.dom.engine.WSSecurityEngineResult>, java.util.List<java.lang.Integer>);
    Code:
       0: new           #78                 // class java/util/ArrayList
       3: dup
       4: aload_2
       5: invokeinterface #93,  1           // InterfaceMethod java/util/List.size:()I
      10: invokespecial #141                // Method java/util/ArrayList."<init>":(I)V
      13: astore_3
      14: aload_2
      15: invokeinterface #39,  1           // InterfaceMethod java/util/List.iterator:()Ljava/util/Iterator;
      20: astore        4
      22: aload         4
      24: invokeinterface #40,  1           // InterfaceMethod java/util/Iterator.hasNext:()Z
      29: ifeq          56
      32: aload         4
      34: invokeinterface #41,  1           // InterfaceMethod java/util/Iterator.next:()Ljava/lang/Object;
      39: checkcast     #139                // class java/lang/Integer
      42: astore        5
      44: aload_3
      45: aload         5
      47: invokeinterface #70,  2           // InterfaceMethod java/util/List.add:(Ljava/lang/Object;)Z
      52: pop
      53: goto          22
      56: aload_1
      57: invokeinterface #39,  1           // InterfaceMethod java/util/List.iterator:()Ljava/util/Iterator;
      62: astore        4
      64: aload         4
      66: invokeinterface #40,  1           // InterfaceMethod java/util/Iterator.hasNext:()Z
      71: ifeq          182
      74: aload         4
      76: invokeinterface #41,  1           // InterfaceMethod java/util/Iterator.next:()Ljava/lang/Object;
      81: checkcast     #136                // class org/apache/wss4j/dom/engine/WSSecurityEngineResult
      84: astore        5
      86: aload         5
      88: ldc           #137                // String action
      90: invokevirtual #138                // Method org/apache/wss4j/dom/engine/WSSecurityEngineResult.get:(Ljava/lang/Object;)Ljava/lang/Object;
      93: checkcast     #139                // class java/lang/Integer
      96: astore        6
      98: aload         6
     100: ifnull        179
     103: aload         6
     105: invokevirtual #44                 // Method java/lang/Integer.intValue:()I
     108: istore        7
     110: iload         7
     112: sipush        128
     115: if_icmpeq     64
     118: iload         7
     120: sipush        4096
     123: if_icmpne     129
     126: goto          64
     129: iload         7
     131: iconst_4
     132: if_icmpne     166
     135: aload         5
     137: ldc           #142                // String data-ref-uris
     139: invokevirtual #138                // Method org/apache/wss4j/dom/engine/WSSecurityEngineResult.get:(Ljava/lang/Object;)Ljava/lang/Object;
     142: ifnull        64
     145: aload         5
     147: ldc           #142                // String data-ref-uris
     149: invokevirtual #138                // Method org/apache/wss4j/dom/engine/WSSecurityEngineResult.get:(Ljava/lang/Object;)Ljava/lang/Object;
     152: checkcast     #143                // class java/util/List
     155: invokeinterface #68,  1           // InterfaceMethod java/util/List.isEmpty:()Z
     160: ifeq          166
     163: goto          64
     166: aload_3
     167: aload         6
     169: invokeinterface #82,  2           // InterfaceMethod java/util/List.remove:(Ljava/lang/Object;)Z
     174: ifne          179
     177: iconst_0
     178: ireturn
     179: goto          64
     182: aload_3
     183: invokeinterface #68,  1           // InterfaceMethod java/util/List.isEmpty:()Z
     188: ifne          193
     191: iconst_0
     192: ireturn
     193: iconst_1
     194: ireturn

  protected void checkSignatureConfirmation(org.apache.wss4j.dom.handler.RequestData, org.apache.wss4j.dom.handler.WSHandlerResult) throws org.apache.wss4j.common.ext.WSSecurityException;
    Code:
       0: aload_0
       1: getfield      #7                  // Field doDebug:Z
       4: ifeq          17
       7: getstatic     #5                  // Field LOG:Lorg/slf4j/Logger;
      10: ldc           #144                // String Check Signature confirmation
      12: invokeinterface #91,  2           // InterfaceMethod org/slf4j/Logger.debug:(Ljava/lang/String;)V
      17: aload_0
      18: aload_1
      19: invokevirtual #11                 // Method org/apache/wss4j/dom/handler/RequestData.getMsgContext:()Ljava/lang/Object;
      22: ldc           #94                 // String _sendSignatureValues_
      24: invokevirtual #73                 // Method getProperty:(Ljava/lang/Object;Ljava/lang/String;)Ljava/lang/Object;
      27: checkcast     #95                 // class java/util/Set
      30: astore_3
      31: aload_2
      32: invokevirtual #145                // Method org/apache/wss4j/dom/handler/WSHandlerResult.getActionResults:()Ljava/util/Map;
      35: sipush        128
      38: invokestatic  #101                // Method java/lang/Integer.valueOf:(I)Ljava/lang/Integer;
      41: invokeinterface #146,  2          // InterfaceMethod java/util/Map.get:(Ljava/lang/Object;)Ljava/lang/Object;
      46: checkcast     #143                // class java/util/List
      49: astore        4
      51: aload         4
      53: ifnull        217
      56: aload         4
      58: invokeinterface #39,  1           // InterfaceMethod java/util/List.iterator:()Ljava/util/Iterator;
      63: astore        5
      65: aload         5
      67: invokeinterface #40,  1           // InterfaceMethod java/util/Iterator.hasNext:()Z
      72: ifeq          217
      75: aload         5
      77: invokeinterface #41,  1           // InterfaceMethod java/util/Iterator.next:()Ljava/lang/Object;
      82: checkcast     #136                // class org/apache/wss4j/dom/engine/WSSecurityEngineResult
      85: astore        6
      87: aload         6
      89: ldc           #147                // String signature-confirmation
      91: invokevirtual #138                // Method org/apache/wss4j/dom/engine/WSSecurityEngineResult.get:(Ljava/lang/Object;)Ljava/lang/Object;
      94: checkcast     #148                // class org/apache/wss4j/dom/message/token/SignatureConfirmation
      97: astore        7
      99: aload         7
     101: ifnull        214
     104: aload         7
     106: invokevirtual #149                // Method org/apache/wss4j/dom/message/token/SignatureConfirmation.getSignatureValue:()[B
     109: ifnull        214
     112: aload_3
     113: ifnull        125
     116: aload_3
     117: invokeinterface #150,  1          // InterfaceMethod java/util/Set.size:()I
     122: ifne          156
     125: aload         7
     127: invokevirtual #149                // Method org/apache/wss4j/dom/message/token/SignatureConfirmation.getSignatureValue:()[B
     130: arraylength
     131: ifeq          214
     134: new           #151                // class org/apache/wss4j/common/ext/WSSecurityException
     137: dup
     138: getstatic     #152                // Field org/apache/wss4j/common/ext/WSSecurityException$ErrorCode.INVALID_SECURITY:Lorg/apache/wss4j/common/ext/WSSecurityException$ErrorCode;
     141: ldc           #153                // String empty
     143: iconst_1
     144: anewarray     #154                // class java/lang/Object
     147: dup
     148: iconst_0
     149: ldc           #155                // String Received a SignatureConfirmation element, but there are no stored signature values
     151: aastore
     152: invokespecial #156                // Method org/apache/wss4j/common/ext/WSSecurityException."<init>":(Lorg/apache/wss4j/common/ext/WSSecurityException$ErrorCode;Ljava/lang/String;[Ljava/lang/Object;)V
     155: athrow
     156: aload         7
     158: invokevirtual #149                // Method org/apache/wss4j/dom/message/token/SignatureConfirmation.getSignatureValue:()[B
     161: invokestatic  #100                // Method java/util/Arrays.hashCode:([B)I
     164: invokestatic  #101                // Method java/lang/Integer.valueOf:(I)Ljava/lang/Integer;
     167: astore        8
     169: aload_3
     170: aload         8
     172: invokeinterface #157,  2          // InterfaceMethod java/util/Set.contains:(Ljava/lang/Object;)Z
     177: ifeq          192
     180: aload_3
     181: aload         8
     183: invokeinterface #158,  2          // InterfaceMethod java/util/Set.remove:(Ljava/lang/Object;)Z
     188: pop
     189: goto          214
     192: new           #151                // class org/apache/wss4j/common/ext/WSSecurityException
     195: dup
     196: getstatic     #159                // Field org/apache/wss4j/common/ext/WSSecurityException$ErrorCode.FAILURE:Lorg/apache/wss4j/common/ext/WSSecurityException$ErrorCode;
     199: ldc           #153                // String empty
     201: iconst_1
     202: anewarray     #154                // class java/lang/Object
     205: dup
     206: iconst_0
     207: ldc           #160                // String Received a SignatureConfirmation element, but there are no matching stored signature values
     209: aastore
     210: invokespecial #156                // Method org/apache/wss4j/common/ext/WSSecurityException."<init>":(Lorg/apache/wss4j/common/ext/WSSecurityException$ErrorCode;Ljava/lang/String;[Ljava/lang/Object;)V
     213: athrow
     214: goto          65
     217: aload_3
     218: ifnull        252
     221: aload_3
     222: invokeinterface #161,  1          // InterfaceMethod java/util/Set.isEmpty:()Z
     227: ifne          252
     230: new           #151                // class org/apache/wss4j/common/ext/WSSecurityException
     233: dup
     234: getstatic     #159                // Field org/apache/wss4j/common/ext/WSSecurityException$ErrorCode.FAILURE:Lorg/apache/wss4j/common/ext/WSSecurityException$ErrorCode;
     237: ldc           #153                // String empty
     239: iconst_1
     240: anewarray     #154                // class java/lang/Object
     243: dup
     244: iconst_0
     245: ldc           #162                // String Check Signature confirmation: the stored signature values list is not empty
     247: aastore
     248: invokespecial #156                // Method org/apache/wss4j/common/ext/WSSecurityException."<init>":(Lorg/apache/wss4j/common/ext/WSSecurityException$ErrorCode;Ljava/lang/String;[Ljava/lang/Object;)V
     251: athrow
     252: return

  protected void decodeUTParameter(org.apache.wss4j.dom.handler.RequestData) throws org.apache.wss4j.common.ext.WSSecurityException;
    Code:
       0: aload_1
       1: invokevirtual #11                 // Method org/apache/wss4j/dom/handler/RequestData.getMsgContext:()Ljava/lang/Object;
       4: astore_2
       5: aload_0
       6: ldc           #163                // String passwordType
       8: aload_2
       9: invokevirtual #24                 // Method getString:(Ljava/lang/String;Ljava/lang/Object;)Ljava/lang/String;
      12: astore_3
      13: aload_3
      14: ifnull        109
      17: ldc           #164                // String PasswordText
      19: aload_3
      20: invokevirtual #108                // Method java/lang/String.equals:(Ljava/lang/Object;)Z
      23: ifeq          35
      26: aload_1
      27: ldc           #165                // String http://docs.oasis-open.org/wss/2004/01/oasis-200401-wss-username-token-profile-1.0#PasswordText
      29: invokevirtual #166                // Method org/apache/wss4j/dom/handler/RequestData.setPwType:(Ljava/lang/String;)V
      32: goto          109
      35: ldc           #167                // String PasswordDigest
      37: aload_3
      38: invokevirtual #108                // Method java/lang/String.equals:(Ljava/lang/Object;)Z
      41: ifeq          53
      44: aload_1
      45: ldc           #168                // String http://docs.oasis-open.org/wss/2004/01/oasis-200401-wss-username-token-profile-1.0#PasswordDigest
      47: invokevirtual #166                // Method org/apache/wss4j/dom/handler/RequestData.setPwType:(Ljava/lang/String;)V
      50: goto          109
      53: ldc           #169                // String PasswordNone
      55: aload_3
      56: invokevirtual #108                // Method java/lang/String.equals:(Ljava/lang/Object;)Z
      59: ifeq          70
      62: aload_1
      63: aconst_null
      64: invokevirtual #166                // Method org/apache/wss4j/dom/handler/RequestData.setPwType:(Ljava/lang/String;)V
      67: goto          109
      70: new           #151                // class org/apache/wss4j/common/ext/WSSecurityException
      73: dup
      74: getstatic     #159                // Field org/apache/wss4j/common/ext/WSSecurityException$ErrorCode.FAILURE:Lorg/apache/wss4j/common/ext/WSSecurityException$ErrorCode;
      77: ldc           #153                // String empty
      79: iconst_1
      80: anewarray     #154                // class java/lang/Object
      83: dup
      84: iconst_0
      85: new           #85                 // class java/lang/StringBuilder
      88: dup
      89: invokespecial #86                 // Method java/lang/StringBuilder."<init>":()V
      92: ldc           #170                // String Unknown password type encoding:
      94: invokevirtual #88                 // Method java/lang/StringBuilder.append:(Ljava/lang/String;)Ljava/lang/StringBuilder;
      97: aload_3
      98: invokevirtual #88                 // Method java/lang/StringBuilder.append:(Ljava/lang/String;)Ljava/lang/StringBuilder;
     101: invokevirtual #90                 // Method java/lang/StringBuilder.toString:()Ljava/lang/String;
     104: aastore
     105: invokespecial #156                // Method org/apache/wss4j/common/ext/WSSecurityException."<init>":(Lorg/apache/wss4j/common/ext/WSSecurityException$ErrorCode;Ljava/lang/String;[Ljava/lang/Object;)V
     108: athrow
     109: aload_0
     110: aload_2
     111: ldc           #171                // String addUsernameTokenNonce
     113: iconst_0
     114: invokevirtual #13                 // Method decodeBooleanConfigValue:(Ljava/lang/Object;Ljava/lang/String;Z)Z
     117: istore        4
     119: aload_1
     120: iload         4
     122: invokevirtual #172                // Method org/apache/wss4j/dom/handler/RequestData.setAddUsernameTokenNonce:(Z)V
     125: aload_0
     126: aload_2
     127: ldc           #173                // String addUsernameTokenCreated
     129: iconst_0
     130: invokevirtual #13                 // Method decodeBooleanConfigValue:(Ljava/lang/Object;Ljava/lang/String;Z)Z
     133: istore        5
     135: aload_1
     136: iload         5
     138: invokevirtual #174                // Method org/apache/wss4j/dom/handler/RequestData.setAddUsernameTokenCreated:(Z)V
     141: aload_0
     142: ldc           #175                // String useDerivedKeyForMAC
     144: aload_2
     145: invokevirtual #24                 // Method getString:(Ljava/lang/String;Ljava/lang/Object;)Ljava/lang/String;
     148: astore        6
     150: aload         6
     152: invokestatic  #176                // Method java/lang/Boolean.parseBoolean:(Ljava/lang/String;)Z
     155: istore        7
     157: iload         7
     159: ifeq          168
     162: aload_1
     163: iload         7
     165: invokevirtual #177                // Method org/apache/wss4j/dom/handler/RequestData.setUseDerivedKeyForMAC:(Z)V
     168: aload_0
     169: ldc           #178                // String derivedKeyIterations
     171: aload_2
     172: invokevirtual #24                 // Method getString:(Ljava/lang/String;Ljava/lang/Object;)Ljava/lang/String;
     175: astore        8
     177: aload         8
     179: ifnull        195
     182: aload         8
     184: invokestatic  #179                // Method java/lang/Integer.parseInt:(Ljava/lang/String;)I
     187: istore        9
     189: aload_1
     190: iload         9
     192: invokevirtual #180                // Method org/apache/wss4j/dom/handler/RequestData.setDerivedKeyIterations:(I)V
     195: return

  protected void decodeSignatureParameter(org.apache.wss4j.dom.handler.RequestData) throws org.apache.wss4j.common.ext.WSSecurityException;
    Code:
       0: aload_1
       1: invokevirtual #11                 // Method org/apache/wss4j/dom/handler/RequestData.getMsgContext:()Ljava/lang/Object;
       4: astore_2
       5: aload_0
       6: ldc           #181                // String signatureUser
       8: aload_2
       9: invokevirtual #24                 // Method getString:(Ljava/lang/String;Ljava/lang/Object;)Ljava/lang/String;
      12: astore_3
      13: aload_1
      14: invokevirtual #49                 // Method org/apache/wss4j/dom/handler/RequestData.getSignatureToken:()Lorg/apache/wss4j/common/SignatureActionToken;
      17: astore        4
      19: aload         4
      21: ifnonnull     39
      24: new           #50                 // class org/apache/wss4j/common/SignatureActionToken
      27: dup
      28: invokespecial #51                 // Method org/apache/wss4j/common/SignatureActionToken."<init>":()V
      31: astore        4
      33: aload_1
      34: aload         4
      36: invokevirtual #52                 // Method org/apache/wss4j/dom/handler/RequestData.setSignatureToken:(Lorg/apache/wss4j/common/SignatureActionToken;)V
      39: aload_3
      40: ifnull        52
      43: aload         4
      45: aload_3
      46: invokevirtual #182                // Method org/apache/wss4j/common/SignatureActionToken.setUser:(Ljava/lang/String;)V
      49: goto          61
      52: aload         4
      54: aload_1
      55: invokevirtual #183                // Method org/apache/wss4j/dom/handler/RequestData.getUsername:()Ljava/lang/String;
      58: invokevirtual #182                // Method org/apache/wss4j/common/SignatureActionToken.setUser:(Ljava/lang/String;)V
      61: aload_0
      62: ldc           #184                // String signatureKeyIdentifier
      64: aload_2
      65: invokevirtual #24                 // Method getString:(Ljava/lang/String;Ljava/lang/Object;)Ljava/lang/String;
      68: astore        5
      70: aload         5
      72: ifnull        190
      75: aload         5
      77: invokestatic  #185                // Method org/apache/wss4j/dom/handler/WSHandlerConstants.getKeyIdentifier:(Ljava/lang/String;)Ljava/lang/Integer;
      80: astore        6
      82: aload         6
      84: ifnonnull     109
      87: new           #151                // class org/apache/wss4j/common/ext/WSSecurityException
      90: dup
      91: getstatic     #159                // Field org/apache/wss4j/common/ext/WSSecurityException$ErrorCode.FAILURE:Lorg/apache/wss4j/common/ext/WSSecurityException$ErrorCode;
      94: ldc           #153                // String empty
      96: iconst_1
      97: anewarray     #154                // class java/lang/Object
     100: dup
     101: iconst_0
     102: ldc           #186                // String WSHandler: Signature: unknown key identification
     104: aastore
     105: invokespecial #156                // Method org/apache/wss4j/common/ext/WSSecurityException."<init>":(Lorg/apache/wss4j/common/ext/WSSecurityException$ErrorCode;Ljava/lang/String;[Ljava/lang/Object;)V
     108: athrow
     109: aload         6
     111: invokevirtual #44                 // Method java/lang/Integer.intValue:()I
     114: istore        7
     116: iload         7
     118: iconst_2
     119: if_icmpeq     183
     122: iload         7
     124: iconst_1
     125: if_icmpeq     183
     128: iload         7
     130: iconst_3
     131: if_icmpeq     183
     134: iload         7
     136: iconst_4
     137: if_icmpeq     183
     140: iload         7
     142: bipush        8
     144: if_icmpeq     183
     147: iload         7
     149: bipush        10
     151: if_icmpeq     183
     154: iload         7
     156: bipush        13
     158: if_icmpeq     183
     161: new           #151                // class org/apache/wss4j/common/ext/WSSecurityException
     164: dup
     165: getstatic     #159                // Field org/apache/wss4j/common/ext/WSSecurityException$ErrorCode.FAILURE:Lorg/apache/wss4j/common/ext/WSSecurityException$ErrorCode;
     168: ldc           #153                // String empty
     170: iconst_1
     171: anewarray     #154                // class java/lang/Object
     174: dup
     175: iconst_0
     176: ldc           #187                // String WSHandler: Signature: illegal key identification
     178: aastore
     179: invokespecial #156                // Method org/apache/wss4j/common/ext/WSSecurityException."<init>":(Lorg/apache/wss4j/common/ext/WSSecurityException$ErrorCode;Ljava/lang/String;[Ljava/lang/Object;)V
     182: athrow
     183: aload         4
     185: iload         7
     187: invokevirtual #188                // Method org/apache/wss4j/common/SignatureActionToken.setKeyIdentifierId:(I)V
     190: aload_0
     191: ldc           #189                // String signatureAlgorithm
     193: aload_2
     194: invokevirtual #24                 // Method getString:(Ljava/lang/String;Ljava/lang/Object;)Ljava/lang/String;
     197: astore        6
     199: aload         4
     201: aload         6
     203: invokevirtual #190                // Method org/apache/wss4j/common/SignatureActionToken.setSignatureAlgorithm:(Ljava/lang/String;)V
     206: aload_0
     207: ldc           #191                // String derivedTokenReference
     209: aload_2
     210: invokevirtual #24                 // Method getString:(Ljava/lang/String;Ljava/lang/Object;)Ljava/lang/String;
     213: astore        7
     215: aload         4
     217: aload         7
     219: invokevirtual #192                // Method org/apache/wss4j/common/SignatureActionToken.setDerivedKeyTokenReference:(Ljava/lang/String;)V
     222: aload_0
     223: ldc           #193                // String derivedTokenKeyIdentifier
     225: aload_2
     226: invokevirtual #24                 // Method getString:(Ljava/lang/String;Ljava/lang/Object;)Ljava/lang/String;
     229: astore        8
     231: aload         8
     233: ifnull        253
     236: aload         8
     238: invokestatic  #185                // Method org/apache/wss4j/dom/handler/WSHandlerConstants.getKeyIdentifier:(Ljava/lang/String;)Ljava/lang/Integer;
     241: astore        9
     243: aload         4
     245: aload         9
     247: invokevirtual #44                 // Method java/lang/Integer.intValue:()I
     250: invokevirtual #194                // Method org/apache/wss4j/common/SignatureActionToken.setDerivedKeyIdentifier:(I)V
     253: aload_0
     254: ldc           #195                // String derivedSignatureKeyLength
     256: aload_2
     257: invokevirtual #24                 // Method getString:(Ljava/lang/String;Ljava/lang/Object;)Ljava/lang/String;
     260: astore        9
     262: aload         9
     264: ifnull        322
     267: aload         9
     269: invokestatic  #179                // Method java/lang/Integer.parseInt:(Ljava/lang/String;)I
     272: istore        10
     274: iload         10
     276: ifle          286
     279: aload         4
     281: iload         10
     283: invokevirtual #196                // Method org/apache/wss4j/common/SignatureActionToken.setDerivedKeyLength:(I)V
     286: goto          322
     289: astore        10
     291: getstatic     #5                  // Field LOG:Lorg/slf4j/Logger;
     294: new           #85                 // class java/lang/StringBuilder
     297: dup
     298: invokespecial #86                 // Method java/lang/StringBuilder."<init>":()V
     301: ldc           #198                // String Error in configuring a derived key length:
     303: invokevirtual #88                 // Method java/lang/StringBuilder.append:(Ljava/lang/String;)Ljava/lang/StringBuilder;
     306: aload         10
     308: invokevirtual #199                // Method java/lang/NumberFormatException.getMessage:()Ljava/lang/String;
     311: invokevirtual #88                 // Method java/lang/StringBuilder.append:(Ljava/lang/String;)Ljava/lang/StringBuilder;
     314: invokevirtual #90                 // Method java/lang/StringBuilder.toString:()Ljava/lang/String;
     317: invokeinterface #57,  2           // InterfaceMethod org/slf4j/Logger.warn:(Ljava/lang/String;)V
     322: aload_0
     323: ldc           #200                // String signatureDigestAlgorithm
     325: aload_2
     326: invokevirtual #24                 // Method getString:(Ljava/lang/String;Ljava/lang/Object;)Ljava/lang/String;
     329: astore        10
     331: aload         4
     333: aload         10
     335: invokevirtual #201                // Method org/apache/wss4j/common/SignatureActionToken.setDigestAlgorithm:(Ljava/lang/String;)V
     338: aload_0
     339: ldc           #202                // String signatureC14nAlgorithm
     341: aload_2
     342: invokevirtual #24                 // Method getString:(Ljava/lang/String;Ljava/lang/Object;)Ljava/lang/String;
     345: astore        11
     347: aload         4
     349: aload         11
     351: invokevirtual #203                // Method org/apache/wss4j/common/SignatureActionToken.setC14nAlgorithm:(Ljava/lang/String;)V
     354: aload_0
     355: aload_2
     356: ldc           #204                // String use200512Namespace
     358: iconst_1
     359: invokevirtual #13                 // Method decodeBooleanConfigValue:(Ljava/lang/Object;Ljava/lang/String;Z)Z
     362: istore        12
     364: aload_1
     365: iload         12
     367: invokevirtual #205                // Method org/apache/wss4j/dom/handler/RequestData.setUse200512Namespace:(Z)V
     370: aload_0
     371: ldc           #206                // String signatureParts
     373: aload_2
     374: invokevirtual #24                 // Method getString:(Ljava/lang/String;Ljava/lang/Object;)Ljava/lang/String;
     377: astore        13
     379: aload         13
     381: ifnull        397
     384: aload_0
     385: iconst_1
     386: aload         13
     388: aload         4
     390: invokevirtual #67                 // Method org/apache/wss4j/common/SignatureActionToken.getParts:()Ljava/util/List;
     393: aload_1
     394: invokespecial #207                // Method splitEncParts:(ZLjava/lang/String;Ljava/util/List;Lorg/apache/wss4j/dom/handler/RequestData;)V
     397: aload_0
     398: ldc           #208                // String optionalSignatureParts
     400: aload_2
     401: invokevirtual #24                 // Method getString:(Ljava/lang/String;Ljava/lang/Object;)Ljava/lang/String;
     404: astore        13
     406: aload         13
     408: ifnull        424
     411: aload_0
     412: iconst_0
     413: aload         13
     415: aload         4
     417: invokevirtual #67                 // Method org/apache/wss4j/common/SignatureActionToken.getParts:()Ljava/util/List;
     420: aload_1
     421: invokespecial #207                // Method splitEncParts:(ZLjava/lang/String;Ljava/util/List;Lorg/apache/wss4j/dom/handler/RequestData;)V
     424: aload_0
     425: aload_2
     426: ldc           #209                // String useSingleCertificate
     428: iconst_1
     429: invokevirtual #13                 // Method decodeBooleanConfigValue:(Ljava/lang/Object;Ljava/lang/String;Z)Z
     432: istore        14
     434: aload         4
     436: iload         14
     438: invokevirtual #210                // Method org/apache/wss4j/common/SignatureActionToken.setUseSingleCert:(Z)V
     441: aload_0
     442: aload_2
     443: ldc           #211                // String includeSignatureToken
     445: iconst_0
     446: invokevirtual #13                 // Method decodeBooleanConfigValue:(Ljava/lang/Object;Ljava/lang/String;Z)Z
     449: istore        15
     451: aload         4
     453: iload         15
     455: invokevirtual #212                // Method org/apache/wss4j/common/SignatureActionToken.setIncludeToken:(Z)V
     458: return
    Exception table:
       from    to  target type
         267   286   289   Class java/lang/NumberFormatException

  protected void decodeAlgorithmSuite(org.apache.wss4j.dom.handler.RequestData) throws org.apache.wss4j.common.ext.WSSecurityException;
    Code:
       0: aload_1
       1: invokevirtual #11                 // Method org/apache/wss4j/dom/handler/RequestData.getMsgContext:()Ljava/lang/Object;
       4: astore_2
       5: aload_2
       6: ifnull        16
       9: aload_1
      10: invokevirtual #213                // Method org/apache/wss4j/dom/handler/RequestData.getAlgorithmSuite:()Lorg/apache/wss4j/common/crypto/AlgorithmSuite;
      13: ifnull        17
      16: return
      17: new           #214                // class org/apache/wss4j/common/crypto/AlgorithmSuite
      20: dup
      21: invokespecial #215                // Method org/apache/wss4j/common/crypto/AlgorithmSuite."<init>":()V
      24: astore_3
      25: aload_0
      26: ldc           #189                // String signatureAlgorithm
      28: aload_2
      29: invokevirtual #24                 // Method getString:(Ljava/lang/String;Ljava/lang/Object;)Ljava/lang/String;
      32: astore        4
      34: aload         4
      36: ifnull        55
      39: ldc           #216                // String
      41: aload         4
      43: invokevirtual #108                // Method java/lang/String.equals:(Ljava/lang/Object;)Z
      46: ifne          55
      49: aload_3
      50: aload         4
      52: invokevirtual #217                // Method org/apache/wss4j/common/crypto/AlgorithmSuite.addSignatureMethod:(Ljava/lang/String;)V
      55: aload_0
      56: ldc           #200                // String signatureDigestAlgorithm
      58: aload_2
      59: invokevirtual #24                 // Method getString:(Ljava/lang/String;Ljava/lang/Object;)Ljava/lang/String;
      62: astore        5
      64: aload         5
      66: ifnull        85
      69: ldc           #216                // String
      71: aload         5
      73: invokevirtual #108                // Method java/lang/String.equals:(Ljava/lang/Object;)Z
      76: ifne          85
      79: aload_3
      80: aload         5
      82: invokevirtual #218                // Method org/apache/wss4j/common/crypto/AlgorithmSuite.addDigestAlgorithm:(Ljava/lang/String;)V
      85: aload_0
      86: ldc           #219                // String encryptionSymAlgorithm
      88: aload_2
      89: invokevirtual #24                 // Method getString:(Ljava/lang/String;Ljava/lang/Object;)Ljava/lang/String;
      92: astore        6
      94: aload         6
      96: ifnull        115
      99: ldc           #216                // String
     101: aload         6
     103: invokevirtual #108                // Method java/lang/String.equals:(Ljava/lang/Object;)Z
     106: ifne          115
     109: aload_3
     110: aload         6
     112: invokevirtual #220                // Method org/apache/wss4j/common/crypto/AlgorithmSuite.addEncryptionMethod:(Ljava/lang/String;)V
     115: aload_0
     116: ldc           #221                // String encryptionKeyTransportAlgorithm
     118: aload_2
     119: invokevirtual #24                 // Method getString:(Ljava/lang/String;Ljava/lang/Object;)Ljava/lang/String;
     122: astore        7
     124: aload         7
     126: ifnull        145
     129: ldc           #216                // String
     131: aload         7
     133: invokevirtual #108                // Method java/lang/String.equals:(Ljava/lang/Object;)Z
     136: ifne          145
     139: aload_3
     140: aload         7
     142: invokevirtual #222                // Method org/apache/wss4j/common/crypto/AlgorithmSuite.addKeyWrapAlgorithm:(Ljava/lang/String;)V
     145: aload_1
     146: aload_3
     147: invokevirtual #223                // Method org/apache/wss4j/dom/handler/RequestData.setAlgorithmSuite:(Lorg/apache/wss4j/common/crypto/AlgorithmSuite;)V
     150: return

  protected void decodeEncryptionParameter(org.apache.wss4j.dom.handler.RequestData) throws org.apache.wss4j.common.ext.WSSecurityException;
    Code:
       0: aload_1
       1: invokevirtual #11                 // Method org/apache/wss4j/dom/handler/RequestData.getMsgContext:()Ljava/lang/Object;
       4: astore_2
       5: aload_1
       6: invokevirtual #59                 // Method org/apache/wss4j/dom/handler/RequestData.getEncryptionToken:()Lorg/apache/wss4j/common/EncryptionActionToken;
       9: astore_3
      10: aload_3
      11: ifnonnull     27
      14: new           #60                 // class org/apache/wss4j/common/EncryptionActionToken
      17: dup
      18: invokespecial #61                 // Method org/apache/wss4j/common/EncryptionActionToken."<init>":()V
      21: astore_3
      22: aload_1
      23: aload_3
      24: invokevirtual #62                 // Method org/apache/wss4j/dom/handler/RequestData.setEncryptionToken:(Lorg/apache/wss4j/common/EncryptionActionToken;)V
      27: aload_0
      28: ldc           #224                // String encryptionKeyIdentifier
      30: aload_2
      31: invokevirtual #24                 // Method getString:(Ljava/lang/String;Ljava/lang/Object;)Ljava/lang/String;
      34: astore        4
      36: aload         4
      38: ifnull        148
      41: aload         4
      43: invokestatic  #185                // Method org/apache/wss4j/dom/handler/WSHandlerConstants.getKeyIdentifier:(Ljava/lang/String;)Ljava/lang/Integer;
      46: astore        5
      48: aload         5
      50: ifnonnull     75
      53: new           #151                // class org/apache/wss4j/common/ext/WSSecurityException
      56: dup
      57: getstatic     #159                // Field org/apache/wss4j/common/ext/WSSecurityException$ErrorCode.FAILURE:Lorg/apache/wss4j/common/ext/WSSecurityException$ErrorCode;
      60: ldc           #153                // String empty
      62: iconst_1
      63: anewarray     #154                // class java/lang/Object
      66: dup
      67: iconst_0
      68: ldc           #225                // String WSHandler: Encryption: unknown key identification
      70: aastore
      71: invokespecial #156                // Method org/apache/wss4j/common/ext/WSSecurityException."<init>":(Lorg/apache/wss4j/common/ext/WSSecurityException$ErrorCode;Ljava/lang/String;[Ljava/lang/Object;)V
      74: athrow
      75: aload         5
      77: invokevirtual #44                 // Method java/lang/Integer.intValue:()I
      80: istore        6
      82: aload_3
      83: iload         6
      85: invokevirtual #226                // Method org/apache/wss4j/common/EncryptionActionToken.setKeyIdentifierId:(I)V
      88: iload         6
      90: iconst_2
      91: if_icmpeq     148
      94: iload         6
      96: iconst_3
      97: if_icmpeq     148
     100: iload         6
     102: iconst_4
     103: if_icmpeq     148
     106: iload         6
     108: iconst_1
     109: if_icmpeq     148
     112: iload         6
     114: bipush        8
     116: if_icmpeq     148
     119: iload         6
     121: bipush        10
     123: if_icmpeq     148
     126: new           #151                // class org/apache/wss4j/common/ext/WSSecurityException
     129: dup
     130: getstatic     #159                // Field org/apache/wss4j/common/ext/WSSecurityException$ErrorCode.FAILURE:Lorg/apache/wss4j/common/ext/WSSecurityException$ErrorCode;
     133: ldc           #153                // String empty
     135: iconst_1
     136: anewarray     #154                // class java/lang/Object
     139: dup
     140: iconst_0
     141: ldc           #227                // String WSHandler: Encryption: illegal key identification
     143: aastore
     144: invokespecial #156                // Method org/apache/wss4j/common/ext/WSSecurityException."<init>":(Lorg/apache/wss4j/common/ext/WSSecurityException$ErrorCode;Ljava/lang/String;[Ljava/lang/Object;)V
     147: athrow
     148: aload_0
     149: ldc           #219                // String encryptionSymAlgorithm
     151: aload_2
     152: invokevirtual #24                 // Method getString:(Ljava/lang/String;Ljava/lang/Object;)Ljava/lang/String;
     155: astore        5
     157: aload_3
     158: aload         5
     160: invokevirtual #228                // Method org/apache/wss4j/common/EncryptionActionToken.setSymmetricAlgorithm:(Ljava/lang/String;)V
     163: aload_0
     164: ldc           #221                // String encryptionKeyTransportAlgorithm
     166: aload_2
     167: invokevirtual #24                 // Method getString:(Ljava/lang/String;Ljava/lang/Object;)Ljava/lang/String;
     170: astore        6
     172: aload_3
     173: aload         6
     175: invokevirtual #229                // Method org/apache/wss4j/common/EncryptionActionToken.setKeyTransportAlgorithm:(Ljava/lang/String;)V
     178: aload_0
     179: ldc           #191                // String derivedTokenReference
     181: aload_2
     182: invokevirtual #24                 // Method getString:(Ljava/lang/String;Ljava/lang/Object;)Ljava/lang/String;
     185: astore        7
     187: aload_3
     188: aload         7
     190: invokevirtual #230                // Method org/apache/wss4j/common/EncryptionActionToken.setDerivedKeyTokenReference:(Ljava/lang/String;)V
     193: aload_0
     194: ldc           #193                // String derivedTokenKeyIdentifier
     196: aload_2
     197: invokevirtual #24                 // Method getString:(Ljava/lang/String;Ljava/lang/Object;)Ljava/lang/String;
     200: astore        8
     202: aload         8
     204: ifnull        223
     207: aload         8
     209: invokestatic  #185                // Method org/apache/wss4j/dom/handler/WSHandlerConstants.getKeyIdentifier:(Ljava/lang/String;)Ljava/lang/Integer;
     212: astore        9
     214: aload_3
     215: aload         9
     217: invokevirtual #44                 // Method java/lang/Integer.intValue:()I
     220: invokevirtual #231                // Method org/apache/wss4j/common/EncryptionActionToken.setDerivedKeyIdentifier:(I)V
     223: aload_0
     224: ldc           #232                // String derivedEncryptionKeyLength
     226: aload_2
     227: invokevirtual #24                 // Method getString:(Ljava/lang/String;Ljava/lang/Object;)Ljava/lang/String;
     230: astore        9
     232: aload         9
     234: ifnull        291
     237: aload         9
     239: invokestatic  #179                // Method java/lang/Integer.parseInt:(Ljava/lang/String;)I
     242: istore        10
     244: iload         10
     246: ifle          255
     249: aload_3
     250: iload         10
     252: invokevirtual #233                // Method org/apache/wss4j/common/EncryptionActionToken.setDerivedKeyLength:(I)V
     255: goto          291
     258: astore        10
     260: getstatic     #5                  // Field LOG:Lorg/slf4j/Logger;
     263: new           #85                 // class java/lang/StringBuilder
     266: dup
     267: invokespecial #86                 // Method java/lang/StringBuilder."<init>":()V
     270: ldc           #198                // String Error in configuring a derived key length:
     272: invokevirtual #88                 // Method java/lang/StringBuilder.append:(Ljava/lang/String;)Ljava/lang/StringBuilder;
     275: aload         10
     277: invokevirtual #199                // Method java/lang/NumberFormatException.getMessage:()Ljava/lang/String;
     280: invokevirtual #88                 // Method java/lang/StringBuilder.append:(Ljava/lang/String;)Ljava/lang/StringBuilder;
     283: invokevirtual #90                 // Method java/lang/StringBuilder.toString:()Ljava/lang/String;
     286: invokeinterface #57,  2           // InterfaceMethod org/slf4j/Logger.warn:(Ljava/lang/String;)V
     291: aload_0
     292: aload_2
     293: ldc           #204                // String use200512Namespace
     295: iconst_1
     296: invokevirtual #13                 // Method decodeBooleanConfigValue:(Ljava/lang/Object;Ljava/lang/String;Z)Z
     299: istore        10
     301: aload_1
     302: iload         10
     304: invokevirtual #205                // Method org/apache/wss4j/dom/handler/RequestData.setUse200512Namespace:(Z)V
     307: aload_0
     308: aload_2
     309: ldc           #234                // String getSecretKeyFromCallbackHandler
     311: iconst_0
     312: invokevirtual #13                 // Method decodeBooleanConfigValue:(Ljava/lang/Object;Ljava/lang/String;Z)Z
     315: istore        11
     317: aload_3
     318: iload         11
     320: invokevirtual #235                // Method org/apache/wss4j/common/EncryptionActionToken.setGetSymmetricKeyFromCallbackHandler:(Z)V
     323: aload_0
     324: ldc           #236                // String encryptionDigestAlgorithm
     326: aload_2
     327: invokevirtual #24                 // Method getString:(Ljava/lang/String;Ljava/lang/Object;)Ljava/lang/String;
     330: astore        12
     332: aload_3
     333: aload         12
     335: invokevirtual #237                // Method org/apache/wss4j/common/EncryptionActionToken.setDigestAlgorithm:(Ljava/lang/String;)V
     338: aload_0
     339: ldc           #238                // String encryptionMGFAlgorithm
     341: aload_2
     342: invokevirtual #24                 // Method getString:(Ljava/lang/String;Ljava/lang/Object;)Ljava/lang/String;
     345: astore        13
     347: aload_3
     348: aload         13
     350: invokevirtual #239                // Method org/apache/wss4j/common/EncryptionActionToken.setMgfAlgorithm:(Ljava/lang/String;)V
     353: aload_0
     354: ldc           #240                // String encryptSymmetricEncryptionKey
     356: aload_2
     357: invokevirtual #24                 // Method getString:(Ljava/lang/String;Ljava/lang/Object;)Ljava/lang/String;
     360: astore        14
     362: aload         14
     364: ifnull        380
     367: aload         14
     369: invokestatic  #176                // Method java/lang/Boolean.parseBoolean:(Ljava/lang/String;)Z
     372: istore        15
     374: aload_3
     375: iload         15
     377: invokevirtual #241                // Method org/apache/wss4j/common/EncryptionActionToken.setEncSymmetricEncryptionKey:(Z)V
     380: aload_0
     381: ldc           #242                // String encryptionUser
     383: aload_2
     384: invokevirtual #24                 // Method getString:(Ljava/lang/String;Ljava/lang/Object;)Ljava/lang/String;
     387: astore        15
     389: aload         15
     391: ifnull        403
     394: aload_3
     395: aload         15
     397: invokevirtual #243                // Method org/apache/wss4j/common/EncryptionActionToken.setUser:(Ljava/lang/String;)V
     400: goto          411
     403: aload_3
     404: aload_1
     405: invokevirtual #183                // Method org/apache/wss4j/dom/handler/RequestData.getUsername:()Ljava/lang/String;
     408: invokevirtual #243                // Method org/apache/wss4j/common/EncryptionActionToken.setUser:(Ljava/lang/String;)V
     411: aload_3
     412: invokevirtual #244                // Method org/apache/wss4j/common/EncryptionActionToken.isEncSymmetricEncryptionKey:()Z
     415: ifeq          447
     418: aload_3
     419: invokevirtual #245                // Method org/apache/wss4j/common/EncryptionActionToken.getUser:()Ljava/lang/String;
     422: ifnonnull     447
     425: new           #151                // class org/apache/wss4j/common/ext/WSSecurityException
     428: dup
     429: getstatic     #159                // Field org/apache/wss4j/common/ext/WSSecurityException$ErrorCode.FAILURE:Lorg/apache/wss4j/common/ext/WSSecurityException$ErrorCode;
     432: ldc           #153                // String empty
     434: iconst_1
     435: anewarray     #154                // class java/lang/Object
     438: dup
     439: iconst_0
     440: ldc           #246                // String WSHandler: Encryption: no username
     442: aastore
     443: invokespecial #156                // Method org/apache/wss4j/common/ext/WSSecurityException."<init>":(Lorg/apache/wss4j/common/ext/WSSecurityException$ErrorCode;Ljava/lang/String;[Ljava/lang/Object;)V
     446: athrow
     447: aload_0
     448: aload_1
     449: invokespecial #247                // Method handleSpecialUser:(Lorg/apache/wss4j/dom/handler/RequestData;)V
     452: aload_0
     453: ldc           #248                // String encryptionParts
     455: aload_2
     456: invokevirtual #24                 // Method getString:(Ljava/lang/String;Ljava/lang/Object;)Ljava/lang/String;
     459: astore        16
     461: aload         16
     463: ifnull        478
     466: aload_0
     467: iconst_1
     468: aload         16
     470: aload_3
     471: invokevirtual #249                // Method org/apache/wss4j/common/EncryptionActionToken.getParts:()Ljava/util/List;
     474: aload_1
     475: invokespecial #207                // Method splitEncParts:(ZLjava/lang/String;Ljava/util/List;Lorg/apache/wss4j/dom/handler/RequestData;)V
     478: aload_0
     479: ldc           #250                // String optionalEncryptionParts
     481: aload_2
     482: invokevirtual #24                 // Method getString:(Ljava/lang/String;Ljava/lang/Object;)Ljava/lang/String;
     485: astore        16
     487: aload         16
     489: ifnull        504
     492: aload_0
     493: iconst_0
     494: aload         16
     496: aload_3
     497: invokevirtual #249                // Method org/apache/wss4j/common/EncryptionActionToken.getParts:()Ljava/util/List;
     500: aload_1
     501: invokespecial #207                // Method splitEncParts:(ZLjava/lang/String;Ljava/util/List;Lorg/apache/wss4j/dom/handler/RequestData;)V
     504: aload_0
     505: aload_2
     506: ldc           #251                // String includeEncryptionToken
     508: iconst_0
     509: invokevirtual #13                 // Method decodeBooleanConfigValue:(Ljava/lang/Object;Ljava/lang/String;Z)Z
     512: istore        17
     514: aload_3
     515: iload         17
     517: invokevirtual #252                // Method org/apache/wss4j/common/EncryptionActionToken.setIncludeToken:(Z)V
     520: return
    Exception table:
       from    to  target type
         237   255   258   Class java/lang/NumberFormatException

  public int decodeTimeToLive(org.apache.wss4j.dom.handler.RequestData, boolean);
    Code:
       0: ldc           #253                // String timeToLive
       2: astore_3
       3: iload_2
       4: ifne          10
       7: ldc           #254                // String utTimeToLive
       9: astore_3
      10: aload_0
      11: aload_3
      12: aload_1
      13: invokevirtual #11                 // Method org/apache/wss4j/dom/handler/RequestData.getMsgContext:()Ljava/lang/Object;
      16: invokevirtual #24                 // Method getString:(Ljava/lang/String;Ljava/lang/Object;)Ljava/lang/String;
      19: astore        4
      21: sipush        300
      24: istore        5
      26: aload         4
      28: ifnull        54
      31: aload         4
      33: invokestatic  #179                // Method java/lang/Integer.parseInt:(Ljava/lang/String;)I
      36: istore        6
      38: iload         6
      40: ifge          46
      43: iload         5
      45: ireturn
      46: iload         6
      48: ireturn
      49: astore        6
      51: iload         5
      53: ireturn
      54: iload         5
      56: ireturn
    Exception table:
       from    to  target type
          31    45    49   Class java/lang/NumberFormatException
          46    48    49   Class java/lang/NumberFormatException

  protected int decodeFutureTimeToLive(org.apache.wss4j.dom.handler.RequestData, boolean);
    Code:
       0: ldc           #255                // String futureTimeToLive
       2: astore_3
       3: iload_2
       4: ifne          11
       7: ldc_w         #256                // String utFutureTimeToLive
      10: astore_3
      11: aload_0
      12: aload_3
      13: aload_1
      14: invokevirtual #11                 // Method org/apache/wss4j/dom/handler/RequestData.getMsgContext:()Ljava/lang/Object;
      17: invokevirtual #24                 // Method getString:(Ljava/lang/String;Ljava/lang/Object;)Ljava/lang/String;
      20: astore        4
      22: bipush        60
      24: istore        5
      26: aload         4
      28: ifnull        54
      31: aload         4
      33: invokestatic  #179                // Method java/lang/Integer.parseInt:(Ljava/lang/String;)I
      36: istore        6
      38: iload         6
      40: ifge          46
      43: iload         5
      45: ireturn
      46: iload         6
      48: ireturn
      49: astore        6
      51: iload         5
      53: ireturn
      54: iload         5
      56: ireturn
    Exception table:
       from    to  target type
          31    45    49   Class java/lang/NumberFormatException
          46    48    49   Class java/lang/NumberFormatException

  protected java.lang.String decodePasswordType(org.apache.wss4j.dom.handler.RequestData) throws org.apache.wss4j.common.ext.WSSecurityException;
    Code:
       0: aload_0
       1: ldc           #163                // String passwordType
       3: aload_1
       4: invokevirtual #11                 // Method org/apache/wss4j/dom/handler/RequestData.getMsgContext:()Ljava/lang/Object;
       7: invokevirtual #24                 // Method getString:(Ljava/lang/String;Ljava/lang/Object;)Ljava/lang/String;
      10: astore_2
      11: aload_2
      12: ifnull        39
      15: ldc           #164                // String PasswordText
      17: aload_2
      18: invokevirtual #108                // Method java/lang/String.equals:(Ljava/lang/Object;)Z
      21: ifeq          27
      24: ldc           #165                // String http://docs.oasis-open.org/wss/2004/01/oasis-200401-wss-username-token-profile-1.0#PasswordText
      26: areturn
      27: ldc           #167                // String PasswordDigest
      29: aload_2
      30: invokevirtual #108                // Method java/lang/String.equals:(Ljava/lang/Object;)Z
      33: ifeq          39
      36: ldc           #168                // String http://docs.oasis-open.org/wss/2004/01/oasis-200401-wss-username-token-profile-1.0#PasswordDigest
      38: areturn
      39: aconst_null
      40: areturn

  protected boolean decodeBooleanConfigValue(java.lang.Object, java.lang.String, boolean) throws org.apache.wss4j.common.ext.WSSecurityException;
    Code:
       0: aload_0
       1: aload_2
       2: aload_1
       3: invokevirtual #24                 // Method getString:(Ljava/lang/String;Ljava/lang/Object;)Ljava/lang/String;
       6: astore        4
       8: aload         4
      10: ifnonnull     15
      13: iload_3
      14: ireturn
      15: ldc_w         #257                // String 0
      18: aload         4
      20: invokevirtual #108                // Method java/lang/String.equals:(Ljava/lang/Object;)Z
      23: ifne          37
      26: ldc_w         #258                // String false
      29: aload         4
      31: invokevirtual #108                // Method java/lang/String.equals:(Ljava/lang/Object;)Z
      34: ifeq          39
      37: iconst_0
      38: ireturn
      39: ldc_w         #259                // String 1
      42: aload         4
      44: invokevirtual #108                // Method java/lang/String.equals:(Ljava/lang/Object;)Z
      47: ifne          61
      50: ldc_w         #260                // String true
      53: aload         4
      55: invokevirtual #108                // Method java/lang/String.equals:(Ljava/lang/Object;)Z
      58: ifeq          63
      61: iconst_1
      62: ireturn
      63: new           #151                // class org/apache/wss4j/common/ext/WSSecurityException
      66: dup
      67: getstatic     #159                // Field org/apache/wss4j/common/ext/WSSecurityException$ErrorCode.FAILURE:Lorg/apache/wss4j/common/ext/WSSecurityException$ErrorCode;
      70: ldc           #153                // String empty
      72: iconst_1
      73: anewarray     #154                // class java/lang/Object
      76: dup
      77: iconst_0
      78: new           #85                 // class java/lang/StringBuilder
      81: dup
      82: invokespecial #86                 // Method java/lang/StringBuilder."<init>":()V
      85: ldc_w         #261                // String WSHandler: illegal
      88: invokevirtual #88                 // Method java/lang/StringBuilder.append:(Ljava/lang/String;)Ljava/lang/StringBuilder;
      91: aload_2
      92: invokevirtual #88                 // Method java/lang/StringBuilder.append:(Ljava/lang/String;)Ljava/lang/StringBuilder;
      95: ldc_w         #262                // String  parameter
      98: invokevirtual #88                 // Method java/lang/StringBuilder.append:(Ljava/lang/String;)Ljava/lang/StringBuilder;
     101: invokevirtual #90                 // Method java/lang/StringBuilder.toString:()Ljava/lang/String;
     104: aastore
     105: invokespecial #156                // Method org/apache/wss4j/common/ext/WSSecurityException."<init>":(Lorg/apache/wss4j/common/ext/WSSecurityException$ErrorCode;Ljava/lang/String;[Ljava/lang/Object;)V
     108: athrow

  public org.apache.wss4j.common.crypto.Crypto loadSignatureCrypto(org.apache.wss4j.dom.handler.RequestData) throws org.apache.wss4j.common.ext.WSSecurityException;
    Code:
       0: aload_0
       1: ldc_w         #263                // String signaturePropFile
       4: ldc_w         #264                // String signaturePropRefId
       7: aload_1
       8: invokevirtual #265                // Method loadCrypto:(Ljava/lang/String;Ljava/lang/String;Lorg/apache/wss4j/dom/handler/RequestData;)Lorg/apache/wss4j/common/crypto/Crypto;
      11: areturn

  public org.apache.wss4j.common.crypto.Crypto loadSignatureVerificationCrypto(org.apache.wss4j.dom.handler.RequestData) throws org.apache.wss4j.common.ext.WSSecurityException;
    Code:
       0: aload_0
       1: ldc_w         #266                // String signatureVerificationPropFile
       4: ldc_w         #267                // String signatureVerificationPropRefId
       7: aload_1
       8: invokevirtual #265                // Method loadCrypto:(Ljava/lang/String;Ljava/lang/String;Lorg/apache/wss4j/dom/handler/RequestData;)Lorg/apache/wss4j/common/crypto/Crypto;
      11: areturn

  protected org.apache.wss4j.common.crypto.Crypto loadDecryptionCrypto(org.apache.wss4j.dom.handler.RequestData) throws org.apache.wss4j.common.ext.WSSecurityException;
    Code:
       0: aload_0
       1: ldc_w         #268                // String decryptionPropFile
       4: ldc_w         #269                // String decryptionPropRefId
       7: aload_1
       8: invokevirtual #265                // Method loadCrypto:(Ljava/lang/String;Ljava/lang/String;Lorg/apache/wss4j/dom/handler/RequestData;)Lorg/apache/wss4j/common/crypto/Crypto;
      11: areturn

  protected org.apache.wss4j.common.crypto.Crypto loadEncryptionCrypto(org.apache.wss4j.dom.handler.RequestData) throws org.apache.wss4j.common.ext.WSSecurityException;
    Code:
       0: aload_0
       1: ldc_w         #270                // String encryptionPropFile
       4: ldc_w         #271                // String encryptionPropRefId
       7: aload_1
       8: invokevirtual #265                // Method loadCrypto:(Ljava/lang/String;Ljava/lang/String;Lorg/apache/wss4j/dom/handler/RequestData;)Lorg/apache/wss4j/common/crypto/Crypto;
      11: areturn

  protected org.apache.wss4j.common.crypto.Crypto loadCrypto(java.lang.String, java.lang.String, org.apache.wss4j.dom.handler.RequestData) throws org.apache.wss4j.common.ext.WSSecurityException;
    Code:
       0: aload_3
       1: invokevirtual #11                 // Method org/apache/wss4j/dom/handler/RequestData.getMsgContext:()Ljava/lang/Object;
       4: astore        4
       6: aconst_null
       7: astore        5
       9: aload_0
      10: aload_2
      11: aload         4
      13: invokevirtual #24                 // Method getString:(Ljava/lang/String;Ljava/lang/Object;)Ljava/lang/String;
      16: astore        6
      18: aload         6
      20: ifnull        179
      23: aload_0
      24: getfield      #4                  // Field cryptos:Ljava/util/Map;
      27: aload         6
      29: invokeinterface #146,  2          // InterfaceMethod java/util/Map.get:(Ljava/lang/Object;)Ljava/lang/Object;
      34: checkcast     #272                // class org/apache/wss4j/common/crypto/Crypto
      37: astore        5
      39: aload         5
      41: ifnonnull     129
      44: aload_0
      45: aload         4
      47: aload         6
      49: invokevirtual #73                 // Method getProperty:(Ljava/lang/Object;Ljava/lang/String;)Ljava/lang/Object;
      52: astore        7
      54: aload         7
      56: instanceof    #273                // class java/util/Properties
      59: ifeq          100
      62: aload         7
      64: checkcast     #273                // class java/util/Properties
      67: ldc_w         #274                // class org/apache/wss4j/common/crypto/CryptoFactory
      70: invokestatic  #275                // Method org/apache/wss4j/common/util/Loader.getClassLoader:(Ljava/lang/Class;)Ljava/lang/ClassLoader;
      73: aload_0
      74: aload_3
      75: invokevirtual #276                // Method getPasswordEncryptor:(Lorg/apache/wss4j/dom/handler/RequestData;)Lorg/apache/wss4j/common/crypto/PasswordEncryptor;
      78: invokestatic  #277                // Method org/apache/wss4j/common/crypto/CryptoFactory.getInstance:(Ljava/util/Properties;Ljava/lang/ClassLoader;Lorg/apache/wss4j/common/crypto/PasswordEncryptor;)Lorg/apache/wss4j/common/crypto/Crypto;
      81: astore        5
      83: aload_0
      84: getfield      #4                  // Field cryptos:Ljava/util/Map;
      87: aload         6
      89: aload         5
      91: invokeinterface #278,  3          // InterfaceMethod java/util/Map.put:(Ljava/lang/Object;Ljava/lang/Object;)Ljava/lang/Object;
      96: pop
      97: goto          129
     100: aload         7
     102: instanceof    #272                // class org/apache/wss4j/common/crypto/Crypto
     105: ifeq          129
     108: aload         7
     110: checkcast     #272                // class org/apache/wss4j/common/crypto/Crypto
     113: astore        5
     115: aload_0
     116: getfield      #4                  // Field cryptos:Ljava/util/Map;
     119: aload         6
     121: aload         5
     123: invokeinterface #278,  3          // InterfaceMethod java/util/Map.put:(Ljava/lang/Object;Ljava/lang/Object;)Ljava/lang/Object;
     128: pop
     129: aload         5
     131: ifnonnull     179
     134: getstatic     #5                  // Field LOG:Lorg/slf4j/Logger;
     137: new           #85                 // class java/lang/StringBuilder
     140: dup
     141: invokespecial #86                 // Method java/lang/StringBuilder."<init>":()V
     144: ldc_w         #279                // String The Crypto reference
     147: invokevirtual #88                 // Method java/lang/StringBuilder.append:(Ljava/lang/String;)Ljava/lang/StringBuilder;
     150: aload         6
     152: invokevirtual #88                 // Method java/lang/StringBuilder.append:(Ljava/lang/String;)Ljava/lang/StringBuilder;
     155: ldc_w         #280                // String  specified by
     158: invokevirtual #88                 // Method java/lang/StringBuilder.append:(Ljava/lang/String;)Ljava/lang/StringBuilder;
     161: aload_2
     162: invokevirtual #88                 // Method java/lang/StringBuilder.append:(Ljava/lang/String;)Ljava/lang/StringBuilder;
     165: ldc_w         #281                // String  could not be loaded
     168: invokevirtual #88                 // Method java/lang/StringBuilder.append:(Ljava/lang/String;)Ljava/lang/StringBuilder;
     171: invokevirtual #90                 // Method java/lang/StringBuilder.toString:()Ljava/lang/String;
     174: invokeinterface #57,  2           // InterfaceMethod org/slf4j/Logger.warn:(Ljava/lang/String;)V
     179: aload         5
     181: ifnonnull     292
     184: aload_0
     185: aload_1
     186: aload         4
     188: invokevirtual #24                 // Method getString:(Ljava/lang/String;Ljava/lang/Object;)Ljava/lang/String;
     191: astore        7
     193: aload         7
     195: ifnull        292
     198: aload_0
     199: getfield      #4                  // Field cryptos:Ljava/util/Map;
     202: aload         7
     204: invokeinterface #146,  2          // InterfaceMethod java/util/Map.get:(Ljava/lang/Object;)Ljava/lang/Object;
     209: checkcast     #272                // class org/apache/wss4j/common/crypto/Crypto
     212: astore        5
     214: aload         5
     216: ifnonnull     242
     219: aload_0
     220: aload         7
     222: aload_3
     223: invokevirtual #282                // Method loadCryptoFromPropertiesFile:(Ljava/lang/String;Lorg/apache/wss4j/dom/handler/RequestData;)Lorg/apache/wss4j/common/crypto/Crypto;
     226: astore        5
     228: aload_0
     229: getfield      #4                  // Field cryptos:Ljava/util/Map;
     232: aload         7
     234: aload         5
     236: invokeinterface #278,  3          // InterfaceMethod java/util/Map.put:(Ljava/lang/Object;Ljava/lang/Object;)Ljava/lang/Object;
     241: pop
     242: aload         5
     244: ifnonnull     292
     247: getstatic     #5                  // Field LOG:Lorg/slf4j/Logger;
     250: new           #85                 // class java/lang/StringBuilder
     253: dup
     254: invokespecial #86                 // Method java/lang/StringBuilder."<init>":()V
     257: ldc_w         #283                // String The Crypto properties file
     260: invokevirtual #88                 // Method java/lang/StringBuilder.append:(Ljava/lang/String;)Ljava/lang/StringBuilder;
     263: aload         7
     265: invokevirtual #88                 // Method java/lang/StringBuilder.append:(Ljava/lang/String;)Ljava/lang/StringBuilder;
     268: ldc_w         #280                // String  specified by
     271: invokevirtual #88                 // Method java/lang/StringBuilder.append:(Ljava/lang/String;)Ljava/lang/StringBuilder;
     274: aload_1
     275: invokevirtual #88                 // Method java/lang/StringBuilder.append:(Ljava/lang/String;)Ljava/lang/StringBuilder;
     278: ldc_w         #284                // String  could not be loaded or found
     281: invokevirtual #88                 // Method java/lang/StringBuilder.append:(Ljava/lang/String;)Ljava/lang/StringBuilder;
     284: invokevirtual #90                 // Method java/lang/StringBuilder.toString:()Ljava/lang/String;
     287: invokeinterface #57,  2           // InterfaceMethod org/slf4j/Logger.warn:(Ljava/lang/String;)V
     292: aload         5
     294: areturn

  protected org.apache.wss4j.common.crypto.Crypto loadCryptoFromPropertiesFile(java.lang.String, org.apache.wss4j.dom.handler.RequestData) throws org.apache.wss4j.common.ext.WSSecurityException;
    Code:
       0: aload_0
       1: aload_2
       2: invokevirtual #11                 // Method org/apache/wss4j/dom/handler/RequestData.getMsgContext:()Ljava/lang/Object;
       5: invokevirtual #285                // Method getClassLoader:(Ljava/lang/Object;)Ljava/lang/ClassLoader;
       8: astore_3
       9: aload_1
      10: aload_3
      11: invokestatic  #286                // Method org/apache/wss4j/common/crypto/CryptoFactory.getProperties:(Ljava/lang/String;Ljava/lang/ClassLoader;)Ljava/util/Properties;
      14: astore        4
      16: aload         4
      18: aload_3
      19: aload_0
      20: aload_2
      21: invokevirtual #276                // Method getPasswordEncryptor:(Lorg/apache/wss4j/dom/handler/RequestData;)Lorg/apache/wss4j/common/crypto/PasswordEncryptor;
      24: invokestatic  #277                // Method org/apache/wss4j/common/crypto/CryptoFactory.getInstance:(Ljava/util/Properties;Ljava/lang/ClassLoader;Lorg/apache/wss4j/common/crypto/PasswordEncryptor;)Lorg/apache/wss4j/common/crypto/Crypto;
      27: areturn

  public javax.security.auth.callback.CallbackHandler getCallbackHandler(java.lang.String, java.lang.String, org.apache.wss4j.dom.handler.RequestData) throws org.apache.wss4j.common.ext.WSSecurityException;
    Code:
       0: aload_3
       1: invokevirtual #11                 // Method org/apache/wss4j/dom/handler/RequestData.getMsgContext:()Ljava/lang/Object;
       4: astore        4
       6: aload_0
       7: aload_2
       8: invokevirtual #287                // Method getOption:(Ljava/lang/String;)Ljava/lang/Object;
      11: checkcast     #288                // class javax/security/auth/callback/CallbackHandler
      14: astore        5
      16: aload         5
      18: ifnonnull     33
      21: aload_0
      22: aload         4
      24: aload_2
      25: invokevirtual #73                 // Method getProperty:(Ljava/lang/Object;Ljava/lang/String;)Ljava/lang/Object;
      28: checkcast     #288                // class javax/security/auth/callback/CallbackHandler
      31: astore        5
      33: aload         5
      35: ifnonnull     61
      38: aload_0
      39: aload_1
      40: aload         4
      42: invokevirtual #24                 // Method getString:(Ljava/lang/String;Ljava/lang/Object;)Ljava/lang/String;
      45: astore        6
      47: aload         6
      49: ifnull        61
      52: aload_0
      53: aload         6
      55: aload_3
      56: invokespecial #289                // Method loadCallbackHandler:(Ljava/lang/String;Lorg/apache/wss4j/dom/handler/RequestData;)Ljavax/security/auth/callback/CallbackHandler;
      59: astore        5
      61: aload         5
      63: areturn

  public javax.security.auth.callback.CallbackHandler getPasswordCallbackHandler(org.apache.wss4j.dom.handler.RequestData) throws org.apache.wss4j.common.ext.WSSecurityException;
    Code:
       0: aload_0
       1: ldc_w         #290                // String passwordCallbackClass
       4: ldc_w         #291                // String passwordCallbackRef
       7: aload_1
       8: invokevirtual #292                // Method getCallbackHandler:(Ljava/lang/String;Ljava/lang/String;Lorg/apache/wss4j/dom/handler/RequestData;)Ljavax/security/auth/callback/CallbackHandler;
      11: areturn

  private javax.security.auth.callback.CallbackHandler loadCallbackHandler(java.lang.String, org.apache.wss4j.dom.handler.RequestData) throws org.apache.wss4j.common.ext.WSSecurityException;
    Code:
       0: aconst_null
       1: astore_3
       2: aconst_null
       3: astore        4
       5: aload_0
       6: aload_2
       7: invokevirtual #11                 // Method org/apache/wss4j/dom/handler/RequestData.getMsgContext:()Ljava/lang/Object;
      10: invokevirtual #285                // Method getClassLoader:(Ljava/lang/Object;)Ljava/lang/ClassLoader;
      13: aload_1
      14: ldc_w         #288                // class javax/security/auth/callback/CallbackHandler
      17: invokestatic  #293                // Method org/apache/wss4j/common/util/Loader.loadClass:(Ljava/lang/ClassLoader;Ljava/lang/String;Ljava/lang/Class;)Ljava/lang/Class;
      20: astore_3
      21: goto          68
      24: astore        5
      26: new           #151                // class org/apache/wss4j/common/ext/WSSecurityException
      29: dup
      30: getstatic     #159                // Field org/apache/wss4j/common/ext/WSSecurityException$ErrorCode.FAILURE:Lorg/apache/wss4j/common/ext/WSSecurityException$ErrorCode;
      33: aload         5
      35: ldc           #153                // String empty
      37: iconst_1
      38: anewarray     #154                // class java/lang/Object
      41: dup
      42: iconst_0
      43: new           #85                 // class java/lang/StringBuilder
      46: dup
      47: invokespecial #86                 // Method java/lang/StringBuilder."<init>":()V
      50: ldc_w         #295                // String WSHandler: cannot load callback handler class:
      53: invokevirtual #88                 // Method java/lang/StringBuilder.append:(Ljava/lang/String;)Ljava/lang/StringBuilder;
      56: aload_1
      57: invokevirtual #88                 // Method java/lang/StringBuilder.append:(Ljava/lang/String;)Ljava/lang/StringBuilder;
      60: invokevirtual #90                 // Method java/lang/StringBuilder.toString:()Ljava/lang/String;
      63: aastore
      64: invokespecial #296                // Method org/apache/wss4j/common/ext/WSSecurityException."<init>":(Lorg/apache/wss4j/common/ext/WSSecurityException$ErrorCode;Ljava/lang/Exception;Ljava/lang/String;[Ljava/lang/Object;)V
      67: athrow
      68: aload_3
      69: invokevirtual #297                // Method java/lang/Class.newInstance:()Ljava/lang/Object;
      72: checkcast     #288                // class javax/security/auth/callback/CallbackHandler
      75: astore        4
      77: goto          124
      80: astore        5
      82: new           #151                // class org/apache/wss4j/common/ext/WSSecurityException
      85: dup
      86: getstatic     #159                // Field org/apache/wss4j/common/ext/WSSecurityException$ErrorCode.FAILURE:Lorg/apache/wss4j/common/ext/WSSecurityException$ErrorCode;
      89: aload         5
      91: ldc           #153                // String empty
      93: iconst_1
      94: anewarray     #154                // class java/lang/Object
      97: dup
      98: iconst_0
      99: new           #85                 // class java/lang/StringBuilder
     102: dup
     103: invokespecial #86                 // Method java/lang/StringBuilder."<init>":()V
     106: ldc_w         #299                // String WSHandler: cannot create instance of callback handler:
     109: invokevirtual #88                 // Method java/lang/StringBuilder.append:(Ljava/lang/String;)Ljava/lang/StringBuilder;
     112: aload_1
     113: invokevirtual #88                 // Method java/lang/StringBuilder.append:(Ljava/lang/String;)Ljava/lang/StringBuilder;
     116: invokevirtual #90                 // Method java/lang/StringBuilder.toString:()Ljava/lang/String;
     119: aastore
     120: invokespecial #296                // Method org/apache/wss4j/common/ext/WSSecurityException."<init>":(Lorg/apache/wss4j/common/ext/WSSecurityException$ErrorCode;Ljava/lang/Exception;Ljava/lang/String;[Ljava/lang/Object;)V
     123: athrow
     124: aload         4
     126: areturn
    Exception table:
       from    to  target type
           5    21    24   Class java/lang/ClassNotFoundException
          68    77    80   Class java/lang/Exception

  protected org.apache.wss4j.common.crypto.PasswordEncryptor getPasswordEncryptor(org.apache.wss4j.dom.handler.RequestData);
    Code:
       0: aload_1
       1: invokevirtual #300                // Method org/apache/wss4j/dom/handler/RequestData.getPasswordEncryptor:()Lorg/apache/wss4j/common/crypto/PasswordEncryptor;
       4: astore_2
       5: aload_2
       6: ifnonnull     29
       9: aload_0
      10: ldc_w         #301                // String passwordEncryptorInstance
      13: invokevirtual #287                // Method getOption:(Ljava/lang/String;)Ljava/lang/Object;
      16: astore_3
      17: aload_3
      18: instanceof    #302                // class org/apache/wss4j/common/crypto/PasswordEncryptor
      21: ifeq          29
      24: aload_3
      25: checkcast     #302                // class org/apache/wss4j/common/crypto/PasswordEncryptor
      28: astore_2
      29: aload_2
      30: ifnonnull     62
      33: aload_1
      34: invokevirtual #11                 // Method org/apache/wss4j/dom/handler/RequestData.getMsgContext:()Ljava/lang/Object;
      37: astore_3
      38: aload_0
      39: aload_3
      40: ldc_w         #301                // String passwordEncryptorInstance
      43: invokevirtual #73                 // Method getProperty:(Ljava/lang/Object;Ljava/lang/String;)Ljava/lang/Object;
      46: astore        4
      48: aload         4
      50: instanceof    #302                // class org/apache/wss4j/common/crypto/PasswordEncryptor
      53: ifeq          62
      56: aload         4
      58: checkcast     #302                // class org/apache/wss4j/common/crypto/PasswordEncryptor
      61: astore_2
      62: aload_2
      63: ifnonnull     84
      66: aload_1
      67: invokevirtual #34                 // Method org/apache/wss4j/dom/handler/RequestData.getCallbackHandler:()Ljavax/security/auth/callback/CallbackHandler;
      70: astore_3
      71: aload_3
      72: ifnull        84
      75: new           #303                // class org/apache/wss4j/common/crypto/JasyptPasswordEncryptor
      78: dup
      79: aload_3
      80: invokespecial #304                // Method org/apache/wss4j/common/crypto/JasyptPasswordEncryptor."<init>":(Ljavax/security/auth/callback/CallbackHandler;)V
      83: astore_2
      84: aload_2
      85: areturn

  public org.apache.wss4j.common.ext.WSPasswordCallback getPasswordCB(java.lang.String, int, javax.security.auth.callback.CallbackHandler, org.apache.wss4j.dom.handler.RequestData) throws org.apache.wss4j.common.ext.WSSecurityException;
    Code:
       0: aload_3
       1: ifnull        12
       4: aload_0
       5: aload_3
       6: aload_1
       7: iload_2
       8: invokespecial #305                // Method performPasswordCallback:(Ljavax/security/auth/callback/CallbackHandler;Ljava/lang/String;I)Lorg/apache/wss4j/common/ext/WSPasswordCallback;
      11: areturn
      12: aload_0
      13: aload         4
      15: invokevirtual #11                 // Method org/apache/wss4j/dom/handler/RequestData.getMsgContext:()Ljava/lang/Object;
      18: invokevirtual #306                // Method getPassword:(Ljava/lang/Object;)Ljava/lang/String;
      21: astore        5
      23: aload         5
      25: ifnonnull     74
      28: ldc_w         #307                // String provided null or empty password
      31: astore        6
      33: new           #151                // class org/apache/wss4j/common/ext/WSSecurityException
      36: dup
      37: getstatic     #159                // Field org/apache/wss4j/common/ext/WSSecurityException$ErrorCode.FAILURE:Lorg/apache/wss4j/common/ext/WSSecurityException$ErrorCode;
      40: ldc           #153                // String empty
      42: iconst_1
      43: anewarray     #154                // class java/lang/Object
      46: dup
      47: iconst_0
      48: new           #85                 // class java/lang/StringBuilder
      51: dup
      52: invokespecial #86                 // Method java/lang/StringBuilder."<init>":()V
      55: ldc_w         #308                // String WSHandler: application
      58: invokevirtual #88                 // Method java/lang/StringBuilder.append:(Ljava/lang/String;)Ljava/lang/StringBuilder;
      61: aload         6
      63: invokevirtual #88                 // Method java/lang/StringBuilder.append:(Ljava/lang/String;)Ljava/lang/StringBuilder;
      66: invokevirtual #90                 // Method java/lang/StringBuilder.toString:()Ljava/lang/String;
      69: aastore
      70: invokespecial #156                // Method org/apache/wss4j/common/ext/WSSecurityException."<init>":(Lorg/apache/wss4j/common/ext/WSSecurityException$ErrorCode;Ljava/lang/String;[Ljava/lang/Object;)V
      73: athrow
      74: aload_0
      75: aload_1
      76: iload_2
      77: invokespecial #309                // Method constructPasswordCallback:(Ljava/lang/String;I)Lorg/apache/wss4j/common/ext/WSPasswordCallback;
      80: astore        6
      82: aload         6
      84: aload         5
      86: invokevirtual #310                // Method org/apache/wss4j/common/ext/WSPasswordCallback.setPassword:(Ljava/lang/String;)V
      89: aload         6
      91: areturn

  private org.apache.wss4j.common.ext.WSPasswordCallback performPasswordCallback(javax.security.auth.callback.CallbackHandler, java.lang.String, int) throws org.apache.wss4j.common.ext.WSSecurityException;
    Code:
       0: aload_0
       1: aload_2
       2: iload_3
       3: invokespecial #309                // Method constructPasswordCallback:(Ljava/lang/String;I)Lorg/apache/wss4j/common/ext/WSPasswordCallback;
       6: astore        4
       8: iconst_1
       9: anewarray     #311                // class javax/security/auth/callback/Callback
      12: astore        5
      14: aload         5
      16: iconst_0
      17: aload         4
      19: aastore
      20: aload_1
      21: aload         5
      23: invokeinterface #312,  2          // InterfaceMethod javax/security/auth/callback/CallbackHandler.handle:([Ljavax/security/auth/callback/Callback;)V
      28: goto          58
      31: astore        6
      33: new           #151                // class org/apache/wss4j/common/ext/WSSecurityException
      36: dup
      37: getstatic     #159                // Field org/apache/wss4j/common/ext/WSSecurityException$ErrorCode.FAILURE:Lorg/apache/wss4j/common/ext/WSSecurityException$ErrorCode;
      40: aload         6
      42: ldc           #153                // String empty
      44: iconst_1
      45: anewarray     #154                // class java/lang/Object
      48: dup
      49: iconst_0
      50: ldc_w         #313                // String WSHandler: password callback failed
      53: aastore
      54: invokespecial #296                // Method org/apache/wss4j/common/ext/WSSecurityException."<init>":(Lorg/apache/wss4j/common/ext/WSSecurityException$ErrorCode;Ljava/lang/Exception;Ljava/lang/String;[Ljava/lang/Object;)V
      57: athrow
      58: aload         4
      60: areturn
    Exception table:
       from    to  target type
          20    28    31   Class java/lang/Exception

  private org.apache.wss4j.common.ext.WSPasswordCallback constructPasswordCallback(java.lang.String, int) throws org.apache.wss4j.common.ext.WSSecurityException;
    Code:
       0: iconst_0
       1: istore_3
       2: iload_2
       3: lookupswitch  { // 6
                     1: 60
                     2: 65
                     4: 76
                    64: 60
                 32768: 70
                 65536: 82
               default: 85
          }
      60: iconst_2
      61: istore_3
      62: goto          85
      65: iconst_3
      66: istore_3
      67: goto          85
      70: bipush        9
      72: istore_3
      73: goto          85
      76: bipush        9
      78: istore_3
      79: goto          85
      82: bipush        9
      84: istore_3
      85: new           #314                // class org/apache/wss4j/common/ext/WSPasswordCallback
      88: dup
      89: aload_1
      90: iload_3
      91: invokespecial #315                // Method org/apache/wss4j/common/ext/WSPasswordCallback."<init>":(Ljava/lang/String;I)V
      94: areturn

  private void splitEncParts(boolean, java.lang.String, java.util.List<org.apache.wss4j.common.WSEncryptionPart>, org.apache.wss4j.dom.handler.RequestData) throws org.apache.wss4j.common.ext.WSSecurityException;
    Code:
       0: aconst_null
       1: astore        5
       3: aload_2
       4: ldc_w         #316                // String ;
       7: invokevirtual #317                // Method java/lang/String.split:(Ljava/lang/String;)[Ljava/lang/String;
      10: astore        6
      12: iconst_0
      13: istore        7
      15: iload         7
      17: aload         6
      19: arraylength
      20: if_icmpge     412
      23: aload         6
      25: iload         7
      27: aaload
      28: ldc_w         #318                // String }
      31: invokevirtual #317                // Method java/lang/String.split:(Ljava/lang/String;)[Ljava/lang/String;
      34: astore        8
      36: aload         8
      38: arraylength
      39: iconst_1
      40: if_icmpne     119
      43: aload_0
      44: getfield      #7                  // Field doDebug:Z
      47: ifeq          87
      50: getstatic     #5                  // Field LOG:Lorg/slf4j/Logger;
      53: new           #85                 // class java/lang/StringBuilder
      56: dup
      57: invokespecial #86                 // Method java/lang/StringBuilder."<init>":()V
      60: ldc_w         #319                // String single partDef: \'
      63: invokevirtual #88                 // Method java/lang/StringBuilder.append:(Ljava/lang/String;)Ljava/lang/StringBuilder;
      66: aload         8
      68: iconst_0
      69: aaload
      70: invokevirtual #88                 // Method java/lang/StringBuilder.append:(Ljava/lang/String;)Ljava/lang/StringBuilder;
      73: ldc_w         #320                // String \'
      76: invokevirtual #88                 // Method java/lang/StringBuilder.append:(Ljava/lang/String;)Ljava/lang/StringBuilder;
      79: invokevirtual #90                 // Method java/lang/StringBuilder.toString:()Ljava/lang/String;
      82: invokeinterface #91,  2           // InterfaceMethod org/slf4j/Logger.debug:(Ljava/lang/String;)V
      87: new           #105                // class org/apache/wss4j/common/WSEncryptionPart
      90: dup
      91: aload         8
      93: iconst_0
      94: aaload
      95: invokevirtual #321                // Method java/lang/String.trim:()Ljava/lang/String;
      98: aload         4
     100: invokevirtual #322                // Method org/apache/wss4j/dom/handler/RequestData.getSoapConstants:()Lorg/apache/wss4j/dom/SOAPConstants;
     103: invokeinterface #323,  1          // InterfaceMethod org/apache/wss4j/dom/SOAPConstants.getEnvelopeURI:()Ljava/lang/String;
     108: ldc_w         #324                // String Content
     111: invokespecial #325                // Method org/apache/wss4j/common/WSEncryptionPart."<init>":(Ljava/lang/String;Ljava/lang/String;Ljava/lang/String;)V
     114: astore        5
     116: goto          391
     119: aload         8
     121: arraylength
     122: iconst_2
     123: if_icmpne     164
     126: aload         8
     128: iconst_0
     129: aaload
     130: invokevirtual #321                // Method java/lang/String.trim:()Ljava/lang/String;
     133: iconst_1
     134: invokevirtual #326                // Method java/lang/String.substring:(I)Ljava/lang/String;
     137: astore        9
     139: aload         8
     141: iconst_1
     142: aaload
     143: invokevirtual #321                // Method java/lang/String.trim:()Ljava/lang/String;
     146: astore        10
     148: new           #105                // class org/apache/wss4j/common/WSEncryptionPart
     151: dup
     152: aload         10
     154: aload         9
     156: invokespecial #327                // Method org/apache/wss4j/common/WSEncryptionPart."<init>":(Ljava/lang/String;Ljava/lang/String;)V
     159: astore        5
     161: goto          391
     164: aload         8
     166: arraylength
     167: iconst_3
     168: if_icmpne     351
     171: aload         8
     173: iconst_0
     174: aaload
     175: invokevirtual #321                // Method java/lang/String.trim:()Ljava/lang/String;
     178: astore        9
     180: aload         9
     182: invokevirtual #328                // Method java/lang/String.length:()I
     185: iconst_1
     186: if_icmpgt     197
     189: ldc_w         #324                // String Content
     192: astore        9
     194: goto          205
     197: aload         9
     199: iconst_1
     200: invokevirtual #326                // Method java/lang/String.substring:(I)Ljava/lang/String;
     203: astore        9
     205: aload         8
     207: iconst_1
     208: aaload
     209: invokevirtual #321                // Method java/lang/String.trim:()Ljava/lang/String;
     212: astore        10
     214: aload         10
     216: invokevirtual #328                // Method java/lang/String.length:()I
     219: iconst_1
     220: if_icmpgt     238
     223: aload         4
     225: invokevirtual #322                // Method org/apache/wss4j/dom/handler/RequestData.getSoapConstants:()Lorg/apache/wss4j/dom/SOAPConstants;
     228: invokeinterface #323,  1          // InterfaceMethod org/apache/wss4j/dom/SOAPConstants.getEnvelopeURI:()Ljava/lang/String;
     233: astore        10
     235: goto          260
     238: aload         10
     240: iconst_1
     241: invokevirtual #326                // Method java/lang/String.substring:(I)Ljava/lang/String;
     244: astore        10
     246: aload         10
     248: ldc_w         #329                // String Null
     251: invokevirtual #108                // Method java/lang/String.equals:(Ljava/lang/Object;)Z
     254: ifeq          260
     257: aconst_null
     258: astore        10
     260: aload         8
     262: iconst_2
     263: aaload
     264: invokevirtual #321                // Method java/lang/String.trim:()Ljava/lang/String;
     267: astore        11
     269: aload_0
     270: getfield      #7                  // Field doDebug:Z
     273: ifeq          333
     276: getstatic     #5                  // Field LOG:Lorg/slf4j/Logger;
     279: new           #85                 // class java/lang/StringBuilder
     282: dup
     283: invokespecial #86                 // Method java/lang/StringBuilder."<init>":()V
     286: ldc_w         #330                // String partDefs: \'
     289: invokevirtual #88                 // Method java/lang/StringBuilder.append:(Ljava/lang/String;)Ljava/lang/StringBuilder;
     292: aload         9
     294: invokevirtual #88                 // Method java/lang/StringBuilder.append:(Ljava/lang/String;)Ljava/lang/StringBuilder;
     297: ldc_w         #331                // String \' ,\'
     300: invokevirtual #88                 // Method java/lang/StringBuilder.append:(Ljava/lang/String;)Ljava/lang/StringBuilder;
     303: aload         10
     305: invokevirtual #88                 // Method java/lang/StringBuilder.append:(Ljava/lang/String;)Ljava/lang/StringBuilder;
     308: ldc_w         #331                // String \' ,\'
     311: invokevirtual #88                 // Method java/lang/StringBuilder.append:(Ljava/lang/String;)Ljava/lang/StringBuilder;
     314: aload         11
     316: invokevirtual #88                 // Method java/lang/StringBuilder.append:(Ljava/lang/String;)Ljava/lang/StringBuilder;
     319: ldc_w         #320                // String \'
     322: invokevirtual #88                 // Method java/lang/StringBuilder.append:(Ljava/lang/String;)Ljava/lang/StringBuilder;
     325: invokevirtual #90                 // Method java/lang/StringBuilder.toString:()Ljava/lang/String;
     328: invokeinterface #91,  2           // InterfaceMethod org/slf4j/Logger.debug:(Ljava/lang/String;)V
     333: new           #105                // class org/apache/wss4j/common/WSEncryptionPart
     336: dup
     337: aload         11
     339: aload         10
     341: aload         9
     343: invokespecial #325                // Method org/apache/wss4j/common/WSEncryptionPart."<init>":(Ljava/lang/String;Ljava/lang/String;Ljava/lang/String;)V
     346: astore        5
     348: goto          391
     351: new           #151                // class org/apache/wss4j/common/ext/WSSecurityException
     354: dup
     355: getstatic     #159                // Field org/apache/wss4j/common/ext/WSSecurityException$ErrorCode.FAILURE:Lorg/apache/wss4j/common/ext/WSSecurityException$ErrorCode;
     358: ldc           #153                // String empty
     360: iconst_1
     361: anewarray     #154                // class java/lang/Object
     364: dup
     365: iconst_0
     366: new           #85                 // class java/lang/StringBuilder
     369: dup
     370: invokespecial #86                 // Method java/lang/StringBuilder."<init>":()V
     373: ldc_w         #332                // String WSHandler: wrong part definition:
     376: invokevirtual #88                 // Method java/lang/StringBuilder.append:(Ljava/lang/String;)Ljava/lang/StringBuilder;
     379: aload_2
     380: invokevirtual #88                 // Method java/lang/StringBuilder.append:(Ljava/lang/String;)Ljava/lang/StringBuilder;
     383: invokevirtual #90                 // Method java/lang/StringBuilder.toString:()Ljava/lang/String;
     386: aastore
     387: invokespecial #156                // Method org/apache/wss4j/common/ext/WSSecurityException."<init>":(Lorg/apache/wss4j/common/ext/WSSecurityException$ErrorCode;Ljava/lang/String;[Ljava/lang/Object;)V
     390: athrow
     391: aload         5
     393: iload_1
     394: invokevirtual #333                // Method org/apache/wss4j/common/WSEncryptionPart.setRequired:(Z)V
     397: aload_3
     398: aload         5
     400: invokeinterface #70,  2           // InterfaceMethod java/util/List.add:(Ljava/lang/Object;)Z
     405: pop
     406: iinc          7, 1
     409: goto          15
     412: return

  private void handleSpecialUser(org.apache.wss4j.dom.handler.RequestData);
    Code:
       0: aload_1
       1: invokevirtual #59                 // Method org/apache/wss4j/dom/handler/RequestData.getEncryptionToken:()Lorg/apache/wss4j/common/EncryptionActionToken;
       4: astore_2
       5: aload_2
       6: ifnull        22
       9: ldc_w         #334                // String useReqSigCert
      12: aload_2
      13: invokevirtual #245                // Method org/apache/wss4j/common/EncryptionActionToken.getUser:()Ljava/lang/String;
      16: invokevirtual #108                // Method java/lang/String.equals:(Ljava/lang/Object;)Z
      19: ifne          23
      22: return
      23: aload_0
      24: aload_1
      25: invokevirtual #11                 // Method org/apache/wss4j/dom/handler/RequestData.getMsgContext:()Ljava/lang/Object;
      28: ldc_w         #335                // String RECV_RESULTS
      31: invokevirtual #73                 // Method getProperty:(Ljava/lang/Object;Ljava/lang/String;)Ljava/lang/Object;
      34: checkcast     #143                // class java/util/List
      37: astore_3
      38: aload_3
      39: ifnonnull     43
      42: return
      43: aload_3
      44: invokeinterface #39,  1           // InterfaceMethod java/util/List.iterator:()Ljava/util/Iterator;
      49: astore        4
      51: aload         4
      53: invokeinterface #40,  1           // InterfaceMethod java/util/Iterator.hasNext:()Z
      58: ifeq          185
      61: aload         4
      63: invokeinterface #41,  1           // InterfaceMethod java/util/Iterator.next:()Ljava/lang/Object;
      68: checkcast     #336                // class org/apache/wss4j/dom/handler/WSHandlerResult
      71: astore        5
      73: aload         5
      75: invokevirtual #337                // Method org/apache/wss4j/dom/handler/WSHandlerResult.getActor:()Ljava/lang/String;
      78: astore        6
      80: aload_1
      81: invokevirtual #338                // Method org/apache/wss4j/dom/handler/RequestData.getActor:()Ljava/lang/String;
      84: aload         6
      86: invokestatic  #339                // Method org/apache/wss4j/dom/util/WSSecurityUtil.isActorEqual:(Ljava/lang/String;Ljava/lang/String;)Z
      89: ifne          95
      92: goto          51
      95: aload         5
      97: invokevirtual #340                // Method org/apache/wss4j/dom/handler/WSHandlerResult.getResults:()Ljava/util/List;
     100: astore        7
     102: aload         7
     104: invokeinterface #39,  1           // InterfaceMethod java/util/List.iterator:()Ljava/util/Iterator;
     109: astore        8
     111: aload         8
     113: invokeinterface #40,  1           // InterfaceMethod java/util/Iterator.hasNext:()Z
     118: ifeq          182
     121: aload         8
     123: invokeinterface #41,  1           // InterfaceMethod java/util/Iterator.next:()Ljava/lang/Object;
     128: checkcast     #136                // class org/apache/wss4j/dom/engine/WSSecurityEngineResult
     131: astore        9
     133: aload         9
     135: ldc           #137                // String action
     137: invokevirtual #138                // Method org/apache/wss4j/dom/engine/WSSecurityEngineResult.get:(Ljava/lang/Object;)Ljava/lang/Object;
     140: checkcast     #139                // class java/lang/Integer
     143: astore        10
     145: aload         10
     147: ifnull        179
     150: aload         10
     152: invokevirtual #44                 // Method java/lang/Integer.intValue:()I
     155: iconst_2
     156: if_icmpne     179
     159: aload         9
     161: ldc_w         #341                // String x509-certificate
     164: invokevirtual #138                // Method org/apache/wss4j/dom/engine/WSSecurityEngineResult.get:(Ljava/lang/Object;)Ljava/lang/Object;
     167: checkcast     #342                // class java/security/cert/X509Certificate
     170: astore        11
     172: aload_2
     173: aload         11
     175: invokevirtual #343                // Method org/apache/wss4j/common/EncryptionActionToken.setCertificate:(Ljava/security/cert/X509Certificate;)V
     178: return
     179: goto          111
     182: goto          51
     185: return

  protected void decodeSignatureParameter2(org.apache.wss4j.dom.handler.RequestData) throws org.apache.wss4j.common.ext.WSSecurityException;
    Code:
       0: aload_1
       1: invokevirtual #344                // Method org/apache/wss4j/dom/handler/RequestData.getSigVerCrypto:()Lorg/apache/wss4j/common/crypto/Crypto;
       4: ifnonnull     16
       7: aload_1
       8: aload_0
       9: aload_1
      10: invokevirtual #345                // Method loadSignatureVerificationCrypto:(Lorg/apache/wss4j/dom/handler/RequestData;)Lorg/apache/wss4j/common/crypto/Crypto;
      13: invokevirtual #346                // Method org/apache/wss4j/dom/handler/RequestData.setSigVerCrypto:(Lorg/apache/wss4j/common/crypto/Crypto;)V
      16: aload_1
      17: invokevirtual #344                // Method org/apache/wss4j/dom/handler/RequestData.getSigVerCrypto:()Lorg/apache/wss4j/common/crypto/Crypto;
      20: ifnonnull     32
      23: aload_1
      24: aload_0
      25: aload_1
      26: invokevirtual #54                 // Method loadSignatureCrypto:(Lorg/apache/wss4j/dom/handler/RequestData;)Lorg/apache/wss4j/common/crypto/Crypto;
      29: invokevirtual #346                // Method org/apache/wss4j/dom/handler/RequestData.setSigVerCrypto:(Lorg/apache/wss4j/common/crypto/Crypto;)V
      32: aload_0
      33: aload_1
      34: invokevirtual #11                 // Method org/apache/wss4j/dom/handler/RequestData.getMsgContext:()Ljava/lang/Object;
      37: ldc_w         #347                // String enableRevocation
      40: iconst_0
      41: invokevirtual #13                 // Method decodeBooleanConfigValue:(Ljava/lang/Object;Ljava/lang/String;Z)Z
      44: istore_2
      45: aload_1
      46: iload_2
      47: invokevirtual #348                // Method org/apache/wss4j/dom/handler/RequestData.setEnableRevocation:(Z)V
      50: aload_0
      51: ldc_w         #349                // String sigSubjectCertConstraints
      54: aload_1
      55: invokevirtual #11                 // Method org/apache/wss4j/dom/handler/RequestData.getMsgContext:()Ljava/lang/Object;
      58: invokevirtual #24                 // Method getString:(Ljava/lang/String;Ljava/lang/Object;)Ljava/lang/String;
      61: astore_3
      62: aload_3
      63: ifnull        179
      66: aload_3
      67: ldc_w         #350                // String ,
      70: invokevirtual #317                // Method java/lang/String.split:(Ljava/lang/String;)[Ljava/lang/String;
      73: astore        4
      75: aload         4
      77: ifnull        179
      80: new           #78                 // class java/util/ArrayList
      83: dup
      84: aload         4
      86: arraylength
      87: invokespecial #141                // Method java/util/ArrayList."<init>":(I)V
      90: astore        5
      92: aload         4
      94: astore        6
      96: aload         6
      98: arraylength
      99: istore        7
     101: iconst_0
     102: istore        8
     104: iload         8
     106: iload         7
     108: if_icmpge     173
     111: aload         6
     113: iload         8
     115: aaload
     116: astore        9
     118: aload         5
     120: aload         9
     122: invokevirtual #321                // Method java/lang/String.trim:()Ljava/lang/String;
     125: invokestatic  #351                // Method java/util/regex/Pattern.compile:(Ljava/lang/String;)Ljava/util/regex/Pattern;
     128: invokeinterface #352,  2          // InterfaceMethod java/util/Collection.add:(Ljava/lang/Object;)Z
     133: pop
     134: goto          167
     137: astore        10
     139: getstatic     #5                  // Field LOG:Lorg/slf4j/Logger;
     142: aload         10
     144: invokevirtual #354                // Method java/util/regex/PatternSyntaxException.getMessage:()Ljava/lang/String;
     147: aload         10
     149: invokeinterface #355,  3          // InterfaceMethod org/slf4j/Logger.debug:(Ljava/lang/String;Ljava/lang/Throwable;)V
     154: new           #151                // class org/apache/wss4j/common/ext/WSSecurityException
     157: dup
     158: getstatic     #159                // Field org/apache/wss4j/common/ext/WSSecurityException$ErrorCode.FAILURE:Lorg/apache/wss4j/common/ext/WSSecurityException$ErrorCode;
     161: aload         10
     163: invokespecial #356                // Method org/apache/wss4j/common/ext/WSSecurityException."<init>":(Lorg/apache/wss4j/common/ext/WSSecurityException$ErrorCode;Ljava/lang/Exception;)V
     166: athrow
     167: iinc          8, 1
     170: goto          104
     173: aload_1
     174: aload         5
     176: invokevirtual #357                // Method org/apache/wss4j/dom/handler/RequestData.setSubjectCertConstraints:(Ljava/util/Collection;)V
     179: aload_0
     180: aload_1
     181: invokevirtual #11                 // Method org/apache/wss4j/dom/handler/RequestData.getMsgContext:()Ljava/lang/Object;
     184: ldc_w         #358                // String expandXOPIncludeForSignature
     187: iconst_1
     188: invokevirtual #13                 // Method decodeBooleanConfigValue:(Ljava/lang/Object;Ljava/lang/String;Z)Z
     191: istore        4
     193: aload_1
     194: iload         4
     196: invokevirtual #359                // Method org/apache/wss4j/dom/handler/RequestData.setExpandXopIncludeForSignature:(Z)V
     199: return
    Exception table:
       from    to  target type
         118   134   137   Class java/util/regex/PatternSyntaxException

  protected void decodeDecryptionParameter(org.apache.wss4j.dom.handler.RequestData) throws org.apache.wss4j.common.ext.WSSecurityException;
    Code:
       0: aload_1
       1: invokevirtual #360                // Method org/apache/wss4j/dom/handler/RequestData.getDecCrypto:()Lorg/apache/wss4j/common/crypto/Crypto;
       4: ifnonnull     16
       7: aload_1
       8: aload_0
       9: aload_1
      10: invokevirtual #361                // Method loadDecryptionCrypto:(Lorg/apache/wss4j/dom/handler/RequestData;)Lorg/apache/wss4j/common/crypto/Crypto;
      13: invokevirtual #362                // Method org/apache/wss4j/dom/handler/RequestData.setDecCrypto:(Lorg/apache/wss4j/common/crypto/Crypto;)V
      16: aload_0
      17: aload_1
      18: invokevirtual #11                 // Method org/apache/wss4j/dom/handler/RequestData.getMsgContext:()Ljava/lang/Object;
      21: ldc_w         #363                // String allowRSA15KeyTransportAlgorithm
      24: iconst_0
      25: invokevirtual #13                 // Method decodeBooleanConfigValue:(Ljava/lang/Object;Ljava/lang/String;Z)Z
      28: istore_2
      29: aload_1
      30: iload_2
      31: invokevirtual #364                // Method org/apache/wss4j/dom/handler/RequestData.setAllowRSA15KeyTransportAlgorithm:(Z)V
      34: return

  public java.lang.String getString(java.lang.String, java.lang.Object);
    Code:
       0: aload_1
       1: ifnonnull     15
       4: new           #365                // class java/lang/IllegalArgumentException
       7: dup
       8: ldc_w         #366                // String Key cannot be null
      11: invokespecial #367                // Method java/lang/IllegalArgumentException."<init>":(Ljava/lang/String;)V
      14: athrow
      15: aload_0
      16: aload_1
      17: invokevirtual #368                // Method getStringOption:(Ljava/lang/String;)Ljava/lang/String;
      20: astore_3
      21: aload_3
      22: ifnull        27
      25: aload_3
      26: areturn
      27: aload_2
      28: ifnonnull     42
      31: new           #365                // class java/lang/IllegalArgumentException
      34: dup
      35: ldc_w         #369                // String Message context cannot be null
      38: invokespecial #367                // Method java/lang/IllegalArgumentException."<init>":(Ljava/lang/String;)V
      41: athrow
      42: aload_0
      43: aload_2
      44: aload_1
      45: invokevirtual #73                 // Method getProperty:(Ljava/lang/Object;Ljava/lang/String;)Ljava/lang/Object;
      48: checkcast     #74                 // class java/lang/String
      51: areturn

  public java.lang.String getStringOption(java.lang.String);
    Code:
       0: aload_0
       1: aload_1
       2: invokevirtual #287                // Method getOption:(Ljava/lang/String;)Ljava/lang/Object;
       5: astore_2
       6: aload_2
       7: instanceof    #74                 // class java/lang/String
      10: ifeq          18
      13: aload_2
      14: checkcast     #74                 // class java/lang/String
      17: areturn
      18: aconst_null
      19: areturn

  public java.lang.ClassLoader getClassLoader(java.lang.Object);
    Code:
       0: invokestatic  #370                // Method org/apache/wss4j/common/util/Loader.getTCL:()Ljava/lang/ClassLoader;
       3: areturn
       4: astore_2
       5: aconst_null
       6: areturn
    Exception table:
       from    to  target type
           0     3     4   Class java/lang/Exception

  public abstract java.lang.Object getOption(java.lang.String);

  public abstract java.lang.Object getProperty(java.lang.Object, java.lang.String);

  public abstract void setProperty(java.lang.Object, java.lang.String, java.lang.Object);

  public abstract java.lang.String getPassword(java.lang.Object);

  public abstract void setPassword(java.lang.Object, java.lang.String);

  static {};
    Code:
       0: ldc_w         #371                // class org/apache/wss4j/dom/handler/WSHandler
       3: invokestatic  #372                // Method org/slf4j/LoggerFactory.getLogger:(Ljava/lang/Class;)Lorg/slf4j/Logger;
       6: putstatic     #5                  // Field LOG:Lorg/slf4j/Logger;
       9: return
}
