Compiled from "ManagementContextAutoConfiguration.java"
class org.springframework.boot.actuate.autoconfigure.web.server.ManagementContextAutoConfiguration$SameManagementContextConfiguration implements org.springframework.beans.factory.SmartInitializingSingleton {
  private final org.springframework.core.env.Environment environment;

  org.springframework.boot.actuate.autoconfigure.web.server.ManagementContextAutoConfiguration$SameManagementContextConfiguration(org.springframework.core.env.Environment);
    Code:
       0: aload_0
       1: invokespecial #1                  // Method java/lang/Object."<init>":()V
       4: aload_0
       5: aload_1
       6: putfield      #2                  // Field environment:Lorg/springframework/core/env/Environment;
       9: return

  public void afterSingletonsInstantiated();
    Code:
       0: aload_0
       1: invokespecial #3                  // Method verifySslConfiguration:()V
       4: aload_0
       5: getfield      #2                  // Field environment:Lorg/springframework/core/env/Environment;
       8: instanceof    #4                  // class org/springframework/core/env/ConfigurableEnvironment
      11: ifeq          25
      14: aload_0
      15: aload_0
      16: getfield      #2                  // Field environment:Lorg/springframework/core/env/Environment;
      19: checkcast     #4                  // class org/springframework/core/env/ConfigurableEnvironment
      22: invokespecial #5                  // Method addLocalManagementPortPropertyAlias:(Lorg/springframework/core/env/ConfigurableEnvironment;)V
      25: return

  private void verifySslConfiguration();
    Code:
       0: aload_0
       1: getfield      #2                  // Field environment:Lorg/springframework/core/env/Environment;
       4: ldc           #6                  // String management.server.ssl.enabled
       6: ldc           #7                  // class java/lang/Boolean
       8: iconst_0
       9: invokestatic  #8                  // Method java/lang/Boolean.valueOf:(Z)Ljava/lang/Boolean;
      12: invokeinterface #9,  4            // InterfaceMethod org/springframework/core/env/Environment.getProperty:(Ljava/lang/String;Ljava/lang/Class;Ljava/lang/Object;)Ljava/lang/Object;
      17: checkcast     #7                  // class java/lang/Boolean
      20: astore_1
      21: aload_1
      22: invokevirtual #10                 // Method java/lang/Boolean.booleanValue:()Z
      25: ifne          32
      28: iconst_1
      29: goto          33
      32: iconst_0
      33: ldc           #11                 // String Management-specific SSL cannot be configured as the management server is not listening on a separate port
      35: invokestatic  #12                 // Method org/springframework/util/Assert.state:(ZLjava/lang/String;)V
      38: return

  private void addLocalManagementPortPropertyAlias(org.springframework.core.env.ConfigurableEnvironment);
    Code:
       0: aload_1
       1: invokeinterface #13,  1           // InterfaceMethod org/springframework/core/env/ConfigurableEnvironment.getPropertySources:()Lorg/springframework/core/env/MutablePropertySources;
       6: new           #14                 // class org/springframework/boot/actuate/autoconfigure/web/server/ManagementContextAutoConfiguration$SameManagementContextConfiguration$1
       9: dup
      10: aload_0
      11: ldc           #15                 // String Management Server
      13: aload_1
      14: invokespecial #16                 // Method org/springframework/boot/actuate/autoconfigure/web/server/ManagementContextAutoConfiguration$SameManagementContextConfiguration$1."<init>":(Lorg/springframework/boot/actuate/autoconfigure/web/server/ManagementContextAutoConfiguration$SameManagementContextConfiguration;Ljava/lang/String;Lorg/springframework/core/env/ConfigurableEnvironment;)V
      17: invokevirtual #17                 // Method org/springframework/core/env/MutablePropertySources.addLast:(Lorg/springframework/core/env/PropertySource;)V
      20: return
}
