Compiled from "ConfiguredBuildGitCommitLink.java"
public class net.nemerosa.ontrack.extension.git.model.ConfiguredBuildGitCommitLink<T> {
  private final net.nemerosa.ontrack.extension.git.model.BuildGitCommitLink<T> link;

  private final T data;

  public net.nemerosa.ontrack.extension.git.model.ConfiguredBuildGitCommitLink<T> clone(java.util.function.Function<java.lang.String, java.lang.String>);
    Code:
       0: new           #1                  // class net/nemerosa/ontrack/extension/git/model/ConfiguredBuildGitCommitLink
       3: dup
       4: aload_0
       5: getfield      #2                  // Field link:Lnet/nemerosa/ontrack/extension/git/model/BuildGitCommitLink;
       8: aload_0
       9: getfield      #2                  // Field link:Lnet/nemerosa/ontrack/extension/git/model/BuildGitCommitLink;
      12: aload_0
      13: getfield      #3                  // Field data:Ljava/lang/Object;
      16: aload_1
      17: invokeinterface #4,  3            // InterfaceMethod net/nemerosa/ontrack/extension/git/model/BuildGitCommitLink.clone:(Ljava/lang/Object;Ljava/util/function/Function;)Ljava/lang/Object;
      22: invokespecial #5                  // Method "<init>":(Lnet/nemerosa/ontrack/extension/git/model/BuildGitCommitLink;Ljava/lang/Object;)V
      25: areturn

  public java.lang.String getCommitFromBuild(net.nemerosa.ontrack.model.structure.Build);
    Code:
       0: aload_0
       1: getfield      #2                  // Field link:Lnet/nemerosa/ontrack/extension/git/model/BuildGitCommitLink;
       4: aload_1
       5: aload_0
       6: getfield      #3                  // Field data:Ljava/lang/Object;
       9: invokeinterface #6,  3            // InterfaceMethod net/nemerosa/ontrack/extension/git/model/BuildGitCommitLink.getCommitFromBuild:(Lnet/nemerosa/ontrack/model/structure/Build;Ljava/lang/Object;)Ljava/lang/String;
      14: areturn

  public boolean isBuildNameValid(java.lang.String);
    Code:
       0: aload_0
       1: getfield      #2                  // Field link:Lnet/nemerosa/ontrack/extension/git/model/BuildGitCommitLink;
       4: aload_1
       5: aload_0
       6: getfield      #3                  // Field data:Ljava/lang/Object;
       9: invokeinterface #7,  3            // InterfaceMethod net/nemerosa/ontrack/extension/git/model/BuildGitCommitLink.isBuildNameValid:(Ljava/lang/String;Ljava/lang/Object;)Z
      14: ireturn

  public net.nemerosa.ontrack.model.structure.ServiceConfiguration toServiceConfiguration();
    Code:
       0: new           #8                  // class net/nemerosa/ontrack/model/structure/ServiceConfiguration
       3: dup
       4: aload_0
       5: getfield      #2                  // Field link:Lnet/nemerosa/ontrack/extension/git/model/BuildGitCommitLink;
       8: invokeinterface #9,  1            // InterfaceMethod net/nemerosa/ontrack/extension/git/model/BuildGitCommitLink.getId:()Ljava/lang/String;
      13: aload_0
      14: getfield      #2                  // Field link:Lnet/nemerosa/ontrack/extension/git/model/BuildGitCommitLink;
      17: aload_0
      18: getfield      #3                  // Field data:Ljava/lang/Object;
      21: invokeinterface #10,  2           // InterfaceMethod net/nemerosa/ontrack/extension/git/model/BuildGitCommitLink.toJson:(Ljava/lang/Object;)Lcom/fasterxml/jackson/databind/JsonNode;
      26: invokespecial #11                 // Method net/nemerosa/ontrack/model/structure/ServiceConfiguration."<init>":(Ljava/lang/String;Lcom/fasterxml/jackson/databind/JsonNode;)V
      29: areturn

  public net.nemerosa.ontrack.extension.git.model.ConfiguredBuildGitCommitLink(net.nemerosa.ontrack.extension.git.model.BuildGitCommitLink<T>, T);
    Code:
       0: aload_0
       1: invokespecial #12                 // Method java/lang/Object."<init>":()V
       4: aload_0
       5: aload_1
       6: putfield      #2                  // Field link:Lnet/nemerosa/ontrack/extension/git/model/BuildGitCommitLink;
       9: aload_0
      10: aload_2
      11: putfield      #3                  // Field data:Ljava/lang/Object;
      14: return

  public net.nemerosa.ontrack.extension.git.model.BuildGitCommitLink<T> getLink();
    Code:
       0: aload_0
       1: getfield      #2                  // Field link:Lnet/nemerosa/ontrack/extension/git/model/BuildGitCommitLink;
       4: areturn

  public T getData();
    Code:
       0: aload_0
       1: getfield      #3                  // Field data:Ljava/lang/Object;
       4: areturn

  public boolean equals(java.lang.Object);
    Code:
       0: aload_1
       1: aload_0
       2: if_acmpne     7
       5: iconst_1
       6: ireturn
       7: aload_1
       8: instanceof    #1                  // class net/nemerosa/ontrack/extension/git/model/ConfiguredBuildGitCommitLink
      11: ifne          16
      14: iconst_0
      15: ireturn
      16: aload_1
      17: checkcast     #1                  // class net/nemerosa/ontrack/extension/git/model/ConfiguredBuildGitCommitLink
      20: astore_2
      21: aload_2
      22: aload_0
      23: invokevirtual #13                 // Method canEqual:(Ljava/lang/Object;)Z
      26: ifne          31
      29: iconst_0
      30: ireturn
      31: aload_0
      32: invokevirtual #14                 // Method getLink:()Lnet/nemerosa/ontrack/extension/git/model/BuildGitCommitLink;
      35: astore_3
      36: aload_2
      37: invokevirtual #14                 // Method getLink:()Lnet/nemerosa/ontrack/extension/git/model/BuildGitCommitLink;
      40: astore        4
      42: aload_3
      43: ifnonnull     54
      46: aload         4
      48: ifnull        65
      51: goto          63
      54: aload_3
      55: aload         4
      57: invokevirtual #15                 // Method java/lang/Object.equals:(Ljava/lang/Object;)Z
      60: ifne          65
      63: iconst_0
      64: ireturn
      65: aload_0
      66: invokevirtual #16                 // Method getData:()Ljava/lang/Object;
      69: astore        5
      71: aload_2
      72: invokevirtual #16                 // Method getData:()Ljava/lang/Object;
      75: astore        6
      77: aload         5
      79: ifnonnull     90
      82: aload         6
      84: ifnull        102
      87: goto          100
      90: aload         5
      92: aload         6
      94: invokevirtual #15                 // Method java/lang/Object.equals:(Ljava/lang/Object;)Z
      97: ifne          102
     100: iconst_0
     101: ireturn
     102: iconst_1
     103: ireturn

  protected boolean canEqual(java.lang.Object);
    Code:
       0: aload_1
       1: instanceof    #1                  // class net/nemerosa/ontrack/extension/git/model/ConfiguredBuildGitCommitLink
       4: ireturn

  public int hashCode();
    Code:
       0: bipush        59
       2: istore_1
       3: iconst_1
       4: istore_2
       5: aload_0
       6: invokevirtual #14                 // Method getLink:()Lnet/nemerosa/ontrack/extension/git/model/BuildGitCommitLink;
       9: astore_3
      10: iload_2
      11: bipush        59
      13: imul
      14: aload_3
      15: ifnonnull     23
      18: bipush        43
      20: goto          27
      23: aload_3
      24: invokevirtual #17                 // Method java/lang/Object.hashCode:()I
      27: iadd
      28: istore_2
      29: aload_0
      30: invokevirtual #16                 // Method getData:()Ljava/lang/Object;
      33: astore        4
      35: iload_2
      36: bipush        59
      38: imul
      39: aload         4
      41: ifnonnull     49
      44: bipush        43
      46: goto          54
      49: aload         4
      51: invokevirtual #17                 // Method java/lang/Object.hashCode:()I
      54: iadd
      55: istore_2
      56: iload_2
      57: ireturn

  public java.lang.String toString();
    Code:
       0: new           #18                 // class java/lang/StringBuilder
       3: dup
       4: invokespecial #19                 // Method java/lang/StringBuilder."<init>":()V
       7: ldc           #20                 // String ConfiguredBuildGitCommitLink(link=
       9: invokevirtual #21                 // Method java/lang/StringBuilder.append:(Ljava/lang/String;)Ljava/lang/StringBuilder;
      12: aload_0
      13: invokevirtual #14                 // Method getLink:()Lnet/nemerosa/ontrack/extension/git/model/BuildGitCommitLink;
      16: invokevirtual #22                 // Method java/lang/StringBuilder.append:(Ljava/lang/Object;)Ljava/lang/StringBuilder;
      19: ldc           #23                 // String , data=
      21: invokevirtual #21                 // Method java/lang/StringBuilder.append:(Ljava/lang/String;)Ljava/lang/StringBuilder;
      24: aload_0
      25: invokevirtual #16                 // Method getData:()Ljava/lang/Object;
      28: invokevirtual #22                 // Method java/lang/StringBuilder.append:(Ljava/lang/Object;)Ljava/lang/StringBuilder;
      31: ldc           #24                 // String )
      33: invokevirtual #21                 // Method java/lang/StringBuilder.append:(Ljava/lang/String;)Ljava/lang/StringBuilder;
      36: invokevirtual #25                 // Method java/lang/StringBuilder.toString:()Ljava/lang/String;
      39: areturn
}
