Compiled from "GitChangeLogIssue.java"
public class net.nemerosa.ontrack.extension.git.model.GitChangeLogIssue extends net.nemerosa.ontrack.extension.scm.model.SCMChangeLogIssue {
  private final java.util.List<net.nemerosa.ontrack.extension.git.model.GitUICommit> commits;

  protected net.nemerosa.ontrack.extension.git.model.GitChangeLogIssue(net.nemerosa.ontrack.extension.issues.model.Issue, java.util.List<net.nemerosa.ontrack.extension.git.model.GitUICommit>);
    Code:
       0: aload_0
       1: aload_1
       2: invokespecial #1                  // Method net/nemerosa/ontrack/extension/scm/model/SCMChangeLogIssue."<init>":(Lnet/nemerosa/ontrack/extension/issues/model/Issue;)V
       5: aload_0
       6: aload_2
       7: putfield      #2                  // Field commits:Ljava/util/List;
      10: return

  public static net.nemerosa.ontrack.extension.git.model.GitChangeLogIssue of(net.nemerosa.ontrack.extension.issues.model.Issue, net.nemerosa.ontrack.extension.git.model.GitUICommit);
    Code:
       0: new           #3                  // class net/nemerosa/ontrack/extension/git/model/GitChangeLogIssue
       3: dup
       4: aload_0
       5: new           #4                  // class java/util/ArrayList
       8: dup
       9: aload_1
      10: invokestatic  #5                  // Method java/util/Collections.singletonList:(Ljava/lang/Object;)Ljava/util/List;
      13: invokespecial #6                  // Method java/util/ArrayList."<init>":(Ljava/util/Collection;)V
      16: invokespecial #7                  // Method "<init>":(Lnet/nemerosa/ontrack/extension/issues/model/Issue;Ljava/util/List;)V
      19: areturn

  public net.nemerosa.ontrack.extension.git.model.GitChangeLogIssue add(net.nemerosa.ontrack.extension.git.model.GitUICommit);
    Code:
       0: aload_0
       1: getfield      #2                  // Field commits:Ljava/util/List;
       4: aload_1
       5: invokeinterface #8,  2            // InterfaceMethod java/util/List.add:(Ljava/lang/Object;)Z
      10: pop
      11: aload_0
      12: areturn

  public boolean equals(java.lang.Object);
    Code:
       0: aload_1
       1: aload_0
       2: if_acmpne     7
       5: iconst_1
       6: ireturn
       7: aload_1
       8: instanceof    #3                  // class net/nemerosa/ontrack/extension/git/model/GitChangeLogIssue
      11: ifne          16
      14: iconst_0
      15: ireturn
      16: aload_1
      17: checkcast     #3                  // class net/nemerosa/ontrack/extension/git/model/GitChangeLogIssue
      20: astore_2
      21: aload_2
      22: aload_0
      23: invokevirtual #9                  // Method canEqual:(Ljava/lang/Object;)Z
      26: ifne          31
      29: iconst_0
      30: ireturn
      31: aload_0
      32: invokevirtual #10                 // Method getCommits:()Ljava/util/List;
      35: astore_3
      36: aload_2
      37: invokevirtual #10                 // Method getCommits:()Ljava/util/List;
      40: astore        4
      42: aload_3
      43: ifnonnull     54
      46: aload         4
      48: ifnull        65
      51: goto          63
      54: aload_3
      55: aload         4
      57: invokevirtual #11                 // Method java/lang/Object.equals:(Ljava/lang/Object;)Z
      60: ifne          65
      63: iconst_0
      64: ireturn
      65: iconst_1
      66: ireturn

  protected boolean canEqual(java.lang.Object);
    Code:
       0: aload_1
       1: instanceof    #3                  // class net/nemerosa/ontrack/extension/git/model/GitChangeLogIssue
       4: ireturn

  public int hashCode();
    Code:
       0: bipush        59
       2: istore_1
       3: iconst_1
       4: istore_2
       5: aload_0
       6: invokevirtual #10                 // Method getCommits:()Ljava/util/List;
       9: astore_3
      10: iload_2
      11: bipush        59
      13: imul
      14: aload_3
      15: ifnonnull     23
      18: bipush        43
      20: goto          27
      23: aload_3
      24: invokevirtual #12                 // Method java/lang/Object.hashCode:()I
      27: iadd
      28: istore_2
      29: iload_2
      30: ireturn

  public java.util.List<net.nemerosa.ontrack.extension.git.model.GitUICommit> getCommits();
    Code:
       0: aload_0
       1: getfield      #2                  // Field commits:Ljava/util/List;
       4: areturn

  public java.lang.String toString();
    Code:
       0: new           #13                 // class java/lang/StringBuilder
       3: dup
       4: invokespecial #14                 // Method java/lang/StringBuilder."<init>":()V
       7: ldc           #15                 // String GitChangeLogIssue(commits=
       9: invokevirtual #16                 // Method java/lang/StringBuilder.append:(Ljava/lang/String;)Ljava/lang/StringBuilder;
      12: aload_0
      13: invokevirtual #10                 // Method getCommits:()Ljava/util/List;
      16: invokevirtual #17                 // Method java/lang/StringBuilder.append:(Ljava/lang/Object;)Ljava/lang/StringBuilder;
      19: ldc           #18                 // String )
      21: invokevirtual #16                 // Method java/lang/StringBuilder.append:(Ljava/lang/String;)Ljava/lang/StringBuilder;
      24: invokevirtual #19                 // Method java/lang/StringBuilder.toString:()Ljava/lang/String;
      27: areturn
}
