Compiled from "ShiroAuthenticationFilter.java"
public class org.graylog2.shared.security.ShiroAuthenticationFilter implements javax.ws.rs.container.ContainerRequestFilter {
  private static final org.slf4j.Logger LOG;

  public org.graylog2.shared.security.ShiroAuthenticationFilter();
    Code:
       0: aload_0
       1: invokespecial #1                  // Method java/lang/Object."<init>":()V
       4: return

  public void filter(javax.ws.rs.container.ContainerRequestContext) throws java.io.IOException;
    Code:
       0: aload_1
       1: invokeinterface #2,  1            // InterfaceMethod javax/ws/rs/container/ContainerRequestContext.getSecurityContext:()Ljavax/ws/rs/core/SecurityContext;
       6: astore_2
       7: aload_2
       8: instanceof    #3                  // class org/graylog2/shared/security/ShiroSecurityContext
      11: ifeq          129
      14: aload_2
      15: checkcast     #3                  // class org/graylog2/shared/security/ShiroSecurityContext
      18: astore_3
      19: aload_3
      20: invokevirtual #4                  // Method org/graylog2/shared/security/ShiroSecurityContext.getSubject:()Lorg/apache/shiro/subject/Subject;
      23: astore        4
      25: getstatic     #5                  // Field LOG:Lorg/slf4j/Logger;
      28: ldc           #6                  // String Authenticating... {}
      30: aload         4
      32: invokeinterface #7,  3            // InterfaceMethod org/slf4j/Logger.trace:(Ljava/lang/String;Ljava/lang/Object;)V
      37: aload         4
      39: invokeinterface #8,  1            // InterfaceMethod org/apache/shiro/subject/Subject.isAuthenticated:()Z
      44: ifne          126
      47: getstatic     #5                  // Field LOG:Lorg/slf4j/Logger;
      50: ldc           #9                  // String Logging in {}
      52: aload         4
      54: invokeinterface #7,  3            // InterfaceMethod org/slf4j/Logger.trace:(Ljava/lang/String;Ljava/lang/Object;)V
      59: aload_3
      60: invokevirtual #10                 // Method org/graylog2/shared/security/ShiroSecurityContext.loginSubject:()V
      63: goto          126
      66: astore        5
      68: getstatic     #5                  // Field LOG:Lorg/slf4j/Logger;
      71: ldc           #12                 // String Unable to authenticate user, account is locked.
      73: aload         5
      75: invokeinterface #13,  3           // InterfaceMethod org/slf4j/Logger.debug:(Ljava/lang/String;Ljava/lang/Throwable;)V
      80: new           #14                 // class javax/ws/rs/NotAuthorizedException
      83: dup
      84: aload         5
      86: ldc           #15                 // String Basic realm=\"Graylog Server\"
      88: iconst_0
      89: anewarray     #16                 // class java/lang/Object
      92: invokespecial #17                 // Method javax/ws/rs/NotAuthorizedException."<init>":(Ljava/lang/Throwable;Ljava/lang/Object;[Ljava/lang/Object;)V
      95: athrow
      96: astore        5
      98: getstatic     #5                  // Field LOG:Lorg/slf4j/Logger;
     101: ldc           #19                 // String Unable to authenticate user.
     103: aload         5
     105: invokeinterface #13,  3           // InterfaceMethod org/slf4j/Logger.debug:(Ljava/lang/String;Ljava/lang/Throwable;)V
     110: new           #14                 // class javax/ws/rs/NotAuthorizedException
     113: dup
     114: aload         5
     116: ldc           #15                 // String Basic realm=\"Graylog Server\"
     118: iconst_0
     119: anewarray     #16                 // class java/lang/Object
     122: invokespecial #17                 // Method javax/ws/rs/NotAuthorizedException."<init>":(Ljava/lang/Throwable;Ljava/lang/Object;[Ljava/lang/Object;)V
     125: athrow
     126: goto          143
     129: new           #14                 // class javax/ws/rs/NotAuthorizedException
     132: dup
     133: ldc           #15                 // String Basic realm=\"Graylog Server\"
     135: iconst_0
     136: anewarray     #16                 // class java/lang/Object
     139: invokespecial #20                 // Method javax/ws/rs/NotAuthorizedException."<init>":(Ljava/lang/Object;[Ljava/lang/Object;)V
     142: athrow
     143: return
    Exception table:
       from    to  target type
          47    63    66   Class org/apache/shiro/authc/LockedAccountException
          47    63    96   Class org/apache/shiro/authc/AuthenticationException

  static {};
    Code:
       0: ldc           #21                 // class org/graylog2/shared/security/ShiroAuthenticationFilter
       2: invokestatic  #22                 // Method org/slf4j/LoggerFactory.getLogger:(Ljava/lang/Class;)Lorg/slf4j/Logger;
       5: putstatic     #5                  // Field LOG:Lorg/slf4j/Logger;
       8: return
}
