Compiled from "CryptoStreamUtils.java"
public class org.apache.hadoop.crypto.CryptoStreamUtils {
  private static final int MIN_BUFFER_SIZE;

  private static final org.slf4j.Logger LOG;

  public org.apache.hadoop.crypto.CryptoStreamUtils();
    Code:
       0: aload_0
       1: invokespecial #2                  // Method java/lang/Object."<init>":()V
       4: return

  public static void freeDB(java.nio.ByteBuffer);
    Code:
       0: getstatic     #3                  // Field org/apache/hadoop/util/CleanerUtil.UNMAP_SUPPORTED:Z
       3: ifeq          33
       6: invokestatic  #4                  // Method org/apache/hadoop/util/CleanerUtil.getCleaner:()Lorg/apache/hadoop/util/CleanerUtil$BufferCleaner;
       9: aload_0
      10: invokeinterface #5,  2            // InterfaceMethod org/apache/hadoop/util/CleanerUtil$BufferCleaner.freeBuffer:(Ljava/nio/ByteBuffer;)V
      15: goto          44
      18: astore_1
      19: getstatic     #7                  // Field LOG:Lorg/slf4j/Logger;
      22: ldc           #8                  // String Failed to free the buffer
      24: aload_1
      25: invokeinterface #9,  3            // InterfaceMethod org/slf4j/Logger.info:(Ljava/lang/String;Ljava/lang/Throwable;)V
      30: goto          44
      33: getstatic     #7                  // Field LOG:Lorg/slf4j/Logger;
      36: getstatic     #10                 // Field org/apache/hadoop/util/CleanerUtil.UNMAP_NOT_SUPPORTED_REASON:Ljava/lang/String;
      39: invokeinterface #11,  2           // InterfaceMethod org/slf4j/Logger.trace:(Ljava/lang/String;)V
      44: return
    Exception table:
       from    to  target type
           6    15    18   Class java/io/IOException

  public static int getBufferSize(org.apache.hadoop.conf.Configuration);
    Code:
       0: aload_0
       1: ldc           #12                 // String hadoop.security.crypto.buffer.size
       3: sipush        8192
       6: invokevirtual #13                 // Method org/apache/hadoop/conf/Configuration.getInt:(Ljava/lang/String;I)I
       9: ireturn

  public static void checkCodec(org.apache.hadoop.crypto.CryptoCodec);
    Code:
       0: aload_0
       1: invokevirtual #14                 // Method org/apache/hadoop/crypto/CryptoCodec.getCipherSuite:()Lorg/apache/hadoop/crypto/CipherSuite;
       4: getstatic     #15                 // Field org/apache/hadoop/crypto/CipherSuite.AES_CTR_NOPADDING:Lorg/apache/hadoop/crypto/CipherSuite;
       7: if_acmpeq     20
      10: new           #16                 // class org/apache/hadoop/crypto/UnsupportedCodecException
      13: dup
      14: ldc           #17                 // String AES/CTR/NoPadding is required
      16: invokespecial #18                 // Method org/apache/hadoop/crypto/UnsupportedCodecException."<init>":(Ljava/lang/String;)V
      19: athrow
      20: return

  public static int checkBufferSize(org.apache.hadoop.crypto.CryptoCodec, int);
    Code:
       0: iload_1
       1: sipush        512
       4: if_icmplt     11
       7: iconst_1
       8: goto          12
      11: iconst_0
      12: ldc           #20                 // String Minimum value of buffer size is 512.
      14: invokestatic  #21                 // Method com/google/common/base/Preconditions.checkArgument:(ZLjava/lang/Object;)V
      17: iload_1
      18: iload_1
      19: aload_0
      20: invokevirtual #14                 // Method org/apache/hadoop/crypto/CryptoCodec.getCipherSuite:()Lorg/apache/hadoop/crypto/CipherSuite;
      23: invokevirtual #22                 // Method org/apache/hadoop/crypto/CipherSuite.getAlgorithmBlockSize:()I
      26: irem
      27: isub
      28: ireturn

  public static long getInputStreamOffset(java.io.InputStream) throws java.io.IOException;
    Code:
       0: aload_0
       1: instanceof    #23                 // class org/apache/hadoop/fs/Seekable
       4: ifeq          17
       7: aload_0
       8: checkcast     #23                 // class org/apache/hadoop/fs/Seekable
      11: invokeinterface #24,  1           // InterfaceMethod org/apache/hadoop/fs/Seekable.getPos:()J
      16: lreturn
      17: lconst_0
      18: lreturn

  static {};
    Code:
       0: ldc           #19                 // class org/apache/hadoop/crypto/CryptoStreamUtils
       2: invokestatic  #25                 // Method org/slf4j/LoggerFactory.getLogger:(Ljava/lang/Class;)Lorg/slf4j/Logger;
       5: putstatic     #7                  // Field LOG:Lorg/slf4j/Logger;
       8: return
}
