Compiled from "OpensslCipher.java"
final class org.apache.hadoop.crypto.OpensslCipher$Padding extends java.lang.Enum<org.apache.hadoop.crypto.OpensslCipher$Padding> {
  public static final org.apache.hadoop.crypto.OpensslCipher$Padding NoPadding;

  private static final org.apache.hadoop.crypto.OpensslCipher$Padding[] $VALUES;

  public static org.apache.hadoop.crypto.OpensslCipher$Padding[] values();
    Code:
       0: getstatic     #1                  // Field $VALUES:[Lorg/apache/hadoop/crypto/OpensslCipher$Padding;
       3: invokevirtual #2                  // Method "[Lorg/apache/hadoop/crypto/OpensslCipher$Padding;".clone:()Ljava/lang/Object;
       6: checkcast     #3                  // class "[Lorg/apache/hadoop/crypto/OpensslCipher$Padding;"
       9: areturn

  public static org.apache.hadoop.crypto.OpensslCipher$Padding valueOf(java.lang.String);
    Code:
       0: ldc           #4                  // class org/apache/hadoop/crypto/OpensslCipher$Padding
       2: aload_0
       3: invokestatic  #5                  // Method java/lang/Enum.valueOf:(Ljava/lang/Class;Ljava/lang/String;)Ljava/lang/Enum;
       6: checkcast     #4                  // class org/apache/hadoop/crypto/OpensslCipher$Padding
       9: areturn

  private org.apache.hadoop.crypto.OpensslCipher$Padding();
    Code:
       0: aload_0
       1: aload_1
       2: iload_2
       3: invokespecial #6                  // Method java/lang/Enum."<init>":(Ljava/lang/String;I)V
       6: return

  static int get(java.lang.String) throws javax.crypto.NoSuchPaddingException;
    Code:
       0: aload_0
       1: invokestatic  #7                  // Method valueOf:(Ljava/lang/String;)Lorg/apache/hadoop/crypto/OpensslCipher$Padding;
       4: invokevirtual #8                  // Method ordinal:()I
       7: ireturn
       8: astore_1
       9: new           #10                 // class javax/crypto/NoSuchPaddingException
      12: dup
      13: new           #11                 // class java/lang/StringBuilder
      16: dup
      17: invokespecial #12                 // Method java/lang/StringBuilder."<init>":()V
      20: ldc           #13                 // String Doesn\'t support padding:
      22: invokevirtual #14                 // Method java/lang/StringBuilder.append:(Ljava/lang/String;)Ljava/lang/StringBuilder;
      25: aload_0
      26: invokevirtual #14                 // Method java/lang/StringBuilder.append:(Ljava/lang/String;)Ljava/lang/StringBuilder;
      29: invokevirtual #15                 // Method java/lang/StringBuilder.toString:()Ljava/lang/String;
      32: invokespecial #16                 // Method javax/crypto/NoSuchPaddingException."<init>":(Ljava/lang/String;)V
      35: athrow
    Exception table:
       from    to  target type
           0     7     8   Class java/lang/Exception

  static {};
    Code:
       0: new           #4                  // class org/apache/hadoop/crypto/OpensslCipher$Padding
       3: dup
       4: ldc           #17                 // String NoPadding
       6: iconst_0
       7: invokespecial #18                 // Method "<init>":(Ljava/lang/String;I)V
      10: putstatic     #19                 // Field NoPadding:Lorg/apache/hadoop/crypto/OpensslCipher$Padding;
      13: iconst_1
      14: anewarray     #4                  // class org/apache/hadoop/crypto/OpensslCipher$Padding
      17: dup
      18: iconst_0
      19: getstatic     #19                 // Field NoPadding:Lorg/apache/hadoop/crypto/OpensslCipher$Padding;
      22: aastore
      23: putstatic     #1                  // Field $VALUES:[Lorg/apache/hadoop/crypto/OpensslCipher$Padding;
      26: return
}
