Compiled from "LongType.java"
public class org.hibernate.ogm.type.LongType extends org.hibernate.ogm.type.AbstractGenericBasicType<java.lang.Long> {
  public static final org.hibernate.ogm.type.LongType INSTANCE;

  public org.hibernate.ogm.type.LongType();
    Code:
       0: aload_0
       1: getstatic     #1                  // Field org/hibernate/ogm/type/descriptor/PassThroughGridTypeDescriptor.INSTANCE:Lorg/hibernate/ogm/type/descriptor/PassThroughGridTypeDescriptor;
       4: getstatic     #2                  // Field org/hibernate/type/descriptor/java/LongTypeDescriptor.INSTANCE:Lorg/hibernate/type/descriptor/java/LongTypeDescriptor;
       7: invokespecial #3                  // Method org/hibernate/ogm/type/AbstractGenericBasicType."<init>":(Lorg/hibernate/ogm/type/descriptor/GridTypeDescriptor;Lorg/hibernate/type/descriptor/java/JavaTypeDescriptor;)V
      10: return

  public java.lang.String getName();
    Code:
       0: ldc           #4                  // String long
       2: areturn

  public java.lang.String[] getRegistrationKeys();
    Code:
       0: iconst_3
       1: anewarray     #5                  // class java/lang/String
       4: dup
       5: iconst_0
       6: aload_0
       7: invokevirtual #6                  // Method getName:()Ljava/lang/String;
      10: aastore
      11: dup
      12: iconst_1
      13: getstatic     #7                  // Field java/lang/Long.TYPE:Ljava/lang/Class;
      16: invokevirtual #8                  // Method java/lang/Class.getName:()Ljava/lang/String;
      19: aastore
      20: dup
      21: iconst_2
      22: ldc_w         #9                  // class java/lang/Long
      25: invokevirtual #8                  // Method java/lang/Class.getName:()Ljava/lang/String;
      28: aastore
      29: areturn

  public int getColumnSpan(org.hibernate.engine.spi.Mapping) throws org.hibernate.MappingException;
    Code:
       0: iconst_1
       1: ireturn

  static {};
    Code:
       0: new           #10                 // class org/hibernate/ogm/type/LongType
       3: dup
       4: invokespecial #11                 // Method "<init>":()V
       7: putstatic     #12                 // Field INSTANCE:Lorg/hibernate/ogm/type/LongType;
      10: return
}
