Compiled from "FileCachingHttpClientBuilder.java"
public class net.shibboleth.utilities.java.support.httpclient.FileCachingHttpClientBuilder extends net.shibboleth.utilities.java.support.httpclient.HttpClientBuilder {
  private java.io.File cacheDir;

  private int maxCacheEntries;

  private long maxCacheEntrySize;

  private long maintentanceTaskInterval;

  private org.apache.http.impl.client.cache.ManagedHttpCacheStorage managedStorage;

  public net.shibboleth.utilities.java.support.httpclient.FileCachingHttpClientBuilder();
    Code:
       0: aload_0
       1: invokestatic  #1                  // Method org/apache/http/impl/client/cache/CachingHttpClientBuilder.create:()Lorg/apache/http/impl/client/cache/CachingHttpClientBuilder;
       4: invokespecial #2                  // Method "<init>":(Lorg/apache/http/impl/client/cache/CachingHttpClientBuilder;)V
       7: return

  public net.shibboleth.utilities.java.support.httpclient.FileCachingHttpClientBuilder(org.apache.http.impl.client.cache.CachingHttpClientBuilder);
    Code:
       0: aload_0
       1: aload_1
       2: invokespecial #3                  // Method net/shibboleth/utilities/java/support/httpclient/HttpClientBuilder."<init>":(Lorg/apache/http/impl/client/HttpClientBuilder;)V
       5: aload_0
       6: new           #4                  // class java/io/File
       9: dup
      10: new           #5                  // class java/lang/StringBuilder
      13: dup
      14: invokespecial #6                  // Method java/lang/StringBuilder."<init>":()V
      17: ldc           #7                  // String java.io.tmpdir
      19: invokestatic  #8                  // Method java/lang/System.getProperty:(Ljava/lang/String;)Ljava/lang/String;
      22: invokevirtual #9                  // Method java/lang/StringBuilder.append:(Ljava/lang/String;)Ljava/lang/StringBuilder;
      25: getstatic     #10                 // Field java/io/File.separator:Ljava/lang/String;
      28: invokevirtual #9                  // Method java/lang/StringBuilder.append:(Ljava/lang/String;)Ljava/lang/StringBuilder;
      31: ldc           #11                 // String wwwcache
      33: invokevirtual #9                  // Method java/lang/StringBuilder.append:(Ljava/lang/String;)Ljava/lang/StringBuilder;
      36: invokevirtual #12                 // Method java/lang/StringBuilder.toString:()Ljava/lang/String;
      39: invokespecial #13                 // Method java/io/File."<init>":(Ljava/lang/String;)V
      42: putfield      #14                 // Field cacheDir:Ljava/io/File;
      45: aload_0
      46: bipush        100
      48: putfield      #15                 // Field maxCacheEntries:I
      51: aload_0
      52: ldc2_w        #16                 // long 10485760l
      55: putfield      #18                 // Field maxCacheEntrySize:J
      58: aload_0
      59: ldc2_w        #19                 // long 1800000l
      62: putfield      #21                 // Field maintentanceTaskInterval:J
      65: return

  public java.io.File getCacheDirectory();
    Code:
       0: aload_0
       1: getfield      #14                 // Field cacheDir:Ljava/io/File;
       4: areturn

  public void setCacheDirectory(java.lang.String);
    Code:
       0: aload_1
       1: invokestatic  #22                 // Method net/shibboleth/utilities/java/support/primitive/StringSupport.trimOrNull:(Ljava/lang/String;)Ljava/lang/String;
       4: ldc           #23                 // String Cache directory path can not be null or empty
       6: invokestatic  #24                 // Method net/shibboleth/utilities/java/support/logic/Constraint.isNotNull:(Ljava/lang/Object;Ljava/lang/String;)Ljava/lang/Object;
       9: checkcast     #25                 // class java/lang/String
      12: astore_2
      13: aload_0
      14: new           #4                  // class java/io/File
      17: dup
      18: aload_2
      19: invokespecial #13                 // Method java/io/File."<init>":(Ljava/lang/String;)V
      22: putfield      #14                 // Field cacheDir:Ljava/io/File;
      25: return

  public void setCacheDirectory(java.io.File);
    Code:
       0: aload_0
       1: aload_1
       2: ldc           #26                 // String Cache directory can not be null
       4: invokestatic  #24                 // Method net/shibboleth/utilities/java/support/logic/Constraint.isNotNull:(Ljava/lang/Object;Ljava/lang/String;)Ljava/lang/Object;
       7: checkcast     #4                  // class java/io/File
      10: putfield      #14                 // Field cacheDir:Ljava/io/File;
      13: return

  public int getMaxCacheEntries();
    Code:
       0: aload_0
       1: getfield      #15                 // Field maxCacheEntries:I
       4: ireturn

  public void setMaxCacheEntries(int);
    Code:
       0: aload_0
       1: lconst_0
       2: iload_1
       3: i2l
       4: ldc           #27                 // String Maximum number of cache entries must be greater than 0
       6: invokestatic  #28                 // Method net/shibboleth/utilities/java/support/logic/Constraint.isGreaterThan:(JJLjava/lang/String;)J
       9: l2i
      10: putfield      #15                 // Field maxCacheEntries:I
      13: return

  public long getMaxCacheEntrySize();
    Code:
       0: aload_0
       1: getfield      #18                 // Field maxCacheEntrySize:J
       4: lreturn

  public void setMaxCacheEntrySize(long);
    Code:
       0: aload_0
       1: lconst_0
       2: lload_1
       3: ldc           #29                 // String Maximum cache entry size must be greater than 0
       5: invokestatic  #28                 // Method net/shibboleth/utilities/java/support/logic/Constraint.isGreaterThan:(JJLjava/lang/String;)J
       8: l2i
       9: i2l
      10: putfield      #18                 // Field maxCacheEntrySize:J
      13: return

  public long getMaintentanceTaskInterval();
    Code:
       0: aload_0
       1: getfield      #21                 // Field maintentanceTaskInterval:J
       4: lreturn

  public void setMaintentanceTaskInterval(long);
    Code:
       0: aload_0
       1: lconst_0
       2: lload_1
       3: ldc           #30                 // String Maintenance task interval must be greater than 0
       5: invokestatic  #28                 // Method net/shibboleth/utilities/java/support/logic/Constraint.isGreaterThan:(JJLjava/lang/String;)J
       8: putfield      #21                 // Field maintentanceTaskInterval:J
      11: return

  protected void decorateApacheBuilder() throws java.lang.Exception;
    Code:
       0: aload_0
       1: invokespecial #31                 // Method net/shibboleth/utilities/java/support/httpclient/HttpClientBuilder.decorateApacheBuilder:()V
       4: aload_0
       5: getfield      #14                 // Field cacheDir:Ljava/io/File;
       8: invokevirtual #32                 // Method java/io/File.exists:()Z
      11: ifne          57
      14: aload_0
      15: getfield      #14                 // Field cacheDir:Ljava/io/File;
      18: invokevirtual #33                 // Method java/io/File.mkdirs:()Z
      21: ifne          57
      24: new           #34                 // class java/io/IOException
      27: dup
      28: new           #5                  // class java/lang/StringBuilder
      31: dup
      32: invokespecial #6                  // Method java/lang/StringBuilder."<init>":()V
      35: ldc           #35                 // String Unable to create cache directory
      37: invokevirtual #9                  // Method java/lang/StringBuilder.append:(Ljava/lang/String;)Ljava/lang/StringBuilder;
      40: aload_0
      41: getfield      #14                 // Field cacheDir:Ljava/io/File;
      44: invokevirtual #36                 // Method java/io/File.getAbsolutePath:()Ljava/lang/String;
      47: invokevirtual #9                  // Method java/lang/StringBuilder.append:(Ljava/lang/String;)Ljava/lang/StringBuilder;
      50: invokevirtual #12                 // Method java/lang/StringBuilder.toString:()Ljava/lang/String;
      53: invokespecial #37                 // Method java/io/IOException."<init>":(Ljava/lang/String;)V
      56: athrow
      57: aload_0
      58: getfield      #14                 // Field cacheDir:Ljava/io/File;
      61: invokevirtual #38                 // Method java/io/File.canRead:()Z
      64: ifne          105
      67: new           #34                 // class java/io/IOException
      70: dup
      71: new           #5                  // class java/lang/StringBuilder
      74: dup
      75: invokespecial #6                  // Method java/lang/StringBuilder."<init>":()V
      78: ldc           #39                 // String Cache directory \'
      80: invokevirtual #9                  // Method java/lang/StringBuilder.append:(Ljava/lang/String;)Ljava/lang/StringBuilder;
      83: aload_0
      84: getfield      #14                 // Field cacheDir:Ljava/io/File;
      87: invokevirtual #36                 // Method java/io/File.getAbsolutePath:()Ljava/lang/String;
      90: invokevirtual #9                  // Method java/lang/StringBuilder.append:(Ljava/lang/String;)Ljava/lang/StringBuilder;
      93: ldc           #40                 // String \' is not readable
      95: invokevirtual #9                  // Method java/lang/StringBuilder.append:(Ljava/lang/String;)Ljava/lang/StringBuilder;
      98: invokevirtual #12                 // Method java/lang/StringBuilder.toString:()Ljava/lang/String;
     101: invokespecial #37                 // Method java/io/IOException."<init>":(Ljava/lang/String;)V
     104: athrow
     105: aload_0
     106: getfield      #14                 // Field cacheDir:Ljava/io/File;
     109: invokevirtual #41                 // Method java/io/File.canWrite:()Z
     112: ifne          153
     115: new           #34                 // class java/io/IOException
     118: dup
     119: new           #5                  // class java/lang/StringBuilder
     122: dup
     123: invokespecial #6                  // Method java/lang/StringBuilder."<init>":()V
     126: ldc           #39                 // String Cache directory \'
     128: invokevirtual #9                  // Method java/lang/StringBuilder.append:(Ljava/lang/String;)Ljava/lang/StringBuilder;
     131: aload_0
     132: getfield      #14                 // Field cacheDir:Ljava/io/File;
     135: invokevirtual #36                 // Method java/io/File.getAbsolutePath:()Ljava/lang/String;
     138: invokevirtual #9                  // Method java/lang/StringBuilder.append:(Ljava/lang/String;)Ljava/lang/StringBuilder;
     141: ldc           #42                 // String \' is not writable
     143: invokevirtual #9                  // Method java/lang/StringBuilder.append:(Ljava/lang/String;)Ljava/lang/StringBuilder;
     146: invokevirtual #12                 // Method java/lang/StringBuilder.toString:()Ljava/lang/String;
     149: invokespecial #37                 // Method java/io/IOException."<init>":(Ljava/lang/String;)V
     152: athrow
     153: aload_0
     154: invokevirtual #43                 // Method getApacheBuilder:()Lorg/apache/http/impl/client/HttpClientBuilder;
     157: checkcast     #44                 // class org/apache/http/impl/client/cache/CachingHttpClientBuilder
     160: astore_1
     161: invokestatic  #45                 // Method org/apache/http/impl/client/cache/CacheConfig.custom:()Lorg/apache/http/impl/client/cache/CacheConfig$Builder;
     164: astore_2
     165: aload_2
     166: aload_0
     167: getfield      #15                 // Field maxCacheEntries:I
     170: invokevirtual #46                 // Method org/apache/http/impl/client/cache/CacheConfig$Builder.setMaxCacheEntries:(I)Lorg/apache/http/impl/client/cache/CacheConfig$Builder;
     173: pop
     174: aload_2
     175: aload_0
     176: getfield      #18                 // Field maxCacheEntrySize:J
     179: invokevirtual #47                 // Method org/apache/http/impl/client/cache/CacheConfig$Builder.setMaxObjectSize:(J)Lorg/apache/http/impl/client/cache/CacheConfig$Builder;
     182: pop
     183: aload_2
     184: iconst_0
     185: invokevirtual #48                 // Method org/apache/http/impl/client/cache/CacheConfig$Builder.setHeuristicCachingEnabled:(Z)Lorg/apache/http/impl/client/cache/CacheConfig$Builder;
     188: pop
     189: aload_2
     190: iconst_0
     191: invokevirtual #49                 // Method org/apache/http/impl/client/cache/CacheConfig$Builder.setSharedCache:(Z)Lorg/apache/http/impl/client/cache/CacheConfig$Builder;
     194: pop
     195: aload_2
     196: invokevirtual #50                 // Method org/apache/http/impl/client/cache/CacheConfig$Builder.build:()Lorg/apache/http/impl/client/cache/CacheConfig;
     199: astore_3
     200: aload_1
     201: aload_3
     202: invokevirtual #51                 // Method org/apache/http/impl/client/cache/CachingHttpClientBuilder.setCacheConfig:(Lorg/apache/http/impl/client/cache/CacheConfig;)Lorg/apache/http/impl/client/cache/CachingHttpClientBuilder;
     205: pop
     206: aload_1
     207: new           #52                 // class org/apache/http/impl/client/cache/FileResourceFactory
     210: dup
     211: aload_0
     212: getfield      #14                 // Field cacheDir:Ljava/io/File;
     215: invokespecial #53                 // Method org/apache/http/impl/client/cache/FileResourceFactory."<init>":(Ljava/io/File;)V
     218: invokevirtual #54                 // Method org/apache/http/impl/client/cache/CachingHttpClientBuilder.setResourceFactory:(Lorg/apache/http/client/cache/ResourceFactory;)Lorg/apache/http/impl/client/cache/CachingHttpClientBuilder;
     221: pop
     222: aload_0
     223: new           #55                 // class org/apache/http/impl/client/cache/ManagedHttpCacheStorage
     226: dup
     227: aload_3
     228: invokespecial #56                 // Method org/apache/http/impl/client/cache/ManagedHttpCacheStorage."<init>":(Lorg/apache/http/impl/client/cache/CacheConfig;)V
     231: putfield      #57                 // Field managedStorage:Lorg/apache/http/impl/client/cache/ManagedHttpCacheStorage;
     234: aload_1
     235: aload_0
     236: getfield      #57                 // Field managedStorage:Lorg/apache/http/impl/client/cache/ManagedHttpCacheStorage;
     239: invokevirtual #58                 // Method org/apache/http/impl/client/cache/CachingHttpClientBuilder.setHttpCacheStorage:(Lorg/apache/http/client/cache/HttpCacheStorage;)Lorg/apache/http/impl/client/cache/CachingHttpClientBuilder;
     242: pop
     243: return

  public synchronized org.apache.http.client.HttpClient buildClient() throws java.lang.Exception;
    Code:
       0: aload_0
       1: invokespecial #59                 // Method net/shibboleth/utilities/java/support/httpclient/HttpClientBuilder.buildClient:()Lorg/apache/http/client/HttpClient;
       4: checkcast     #60                 // class org/apache/http/impl/client/CloseableHttpClient
       7: astore_1
       8: aload_0
       9: getfield      #57                 // Field managedStorage:Lorg/apache/http/impl/client/cache/ManagedHttpCacheStorage;
      12: astore_2
      13: aload_0
      14: aconst_null
      15: putfield      #57                 // Field managedStorage:Lorg/apache/http/impl/client/cache/ManagedHttpCacheStorage;
      18: new           #61                 // class net/shibboleth/utilities/java/support/httpclient/FileCachingHttpClientBuilder$StorageManagingHttpClient
      21: dup
      22: aload_1
      23: aload_2
      24: aload_0
      25: invokevirtual #62                 // Method getMaintentanceTaskInterval:()J
      28: invokespecial #63                 // Method net/shibboleth/utilities/java/support/httpclient/FileCachingHttpClientBuilder$StorageManagingHttpClient."<init>":(Lorg/apache/http/impl/client/CloseableHttpClient;Lorg/apache/http/impl/client/cache/ManagedHttpCacheStorage;J)V
      31: areturn
}
