Compiled from "ArtifactResolveImpl.java"
public class org.opensaml.saml2.core.impl.ArtifactResolveImpl extends org.opensaml.saml2.core.impl.RequestAbstractTypeImpl implements org.opensaml.saml2.core.ArtifactResolve {
  private org.opensaml.saml2.core.Artifact artifact;

  protected org.opensaml.saml2.core.impl.ArtifactResolveImpl(java.lang.String, java.lang.String, java.lang.String);
    Code:
       0: aload_0
       1: aload_1
       2: aload_2
       3: aload_3
       4: invokespecial #1                  // Method org/opensaml/saml2/core/impl/RequestAbstractTypeImpl."<init>":(Ljava/lang/String;Ljava/lang/String;Ljava/lang/String;)V
       7: return

  public org.opensaml.saml2.core.Artifact getArtifact();
    Code:
       0: aload_0
       1: getfield      #2                  // Field artifact:Lorg/opensaml/saml2/core/Artifact;
       4: areturn

  public void setArtifact(org.opensaml.saml2.core.Artifact);
    Code:
       0: aload_0
       1: aload_0
       2: aload_0
       3: getfield      #2                  // Field artifact:Lorg/opensaml/saml2/core/Artifact;
       6: aload_1
       7: invokevirtual #3                  // Method prepareForAssignment:(Lorg/opensaml/xml/XMLObject;Lorg/opensaml/xml/XMLObject;)Lorg/opensaml/xml/XMLObject;
      10: checkcast     #4                  // class org/opensaml/saml2/core/Artifact
      13: putfield      #2                  // Field artifact:Lorg/opensaml/saml2/core/Artifact;
      16: return

  public java.util.List<org.opensaml.xml.XMLObject> getOrderedChildren();
    Code:
       0: new           #5                  // class java/util/ArrayList
       3: dup
       4: invokespecial #6                  // Method java/util/ArrayList."<init>":()V
       7: astore_1
       8: aload_0
       9: invokespecial #7                  // Method org/opensaml/saml2/core/impl/RequestAbstractTypeImpl.getOrderedChildren:()Ljava/util/List;
      12: ifnull        24
      15: aload_1
      16: aload_0
      17: invokespecial #7                  // Method org/opensaml/saml2/core/impl/RequestAbstractTypeImpl.getOrderedChildren:()Ljava/util/List;
      20: invokevirtual #8                  // Method java/util/ArrayList.addAll:(Ljava/util/Collection;)Z
      23: pop
      24: aload_0
      25: getfield      #2                  // Field artifact:Lorg/opensaml/saml2/core/Artifact;
      28: ifnull        40
      31: aload_1
      32: aload_0
      33: getfield      #2                  // Field artifact:Lorg/opensaml/saml2/core/Artifact;
      36: invokevirtual #9                  // Method java/util/ArrayList.add:(Ljava/lang/Object;)Z
      39: pop
      40: aload_1
      41: invokevirtual #10                 // Method java/util/ArrayList.size:()I
      44: ifne          49
      47: aconst_null
      48: areturn
      49: aload_1
      50: invokestatic  #11                 // Method java/util/Collections.unmodifiableList:(Ljava/util/List;)Ljava/util/List;
      53: areturn
}
