Compiled from "ManageNameIDRequestImpl.java"
public class org.opensaml.saml2.core.impl.ManageNameIDRequestImpl extends org.opensaml.saml2.core.impl.RequestAbstractTypeImpl implements org.opensaml.saml2.core.ManageNameIDRequest {
  private org.opensaml.saml2.core.NameID nameID;

  private org.opensaml.saml2.core.EncryptedID encryptedID;

  private org.opensaml.saml2.core.NewID newID;

  private org.opensaml.saml2.core.NewEncryptedID newEncryptedID;

  private org.opensaml.saml2.core.Terminate terminate;

  protected org.opensaml.saml2.core.impl.ManageNameIDRequestImpl(java.lang.String, java.lang.String, java.lang.String);
    Code:
       0: aload_0
       1: aload_1
       2: aload_2
       3: aload_3
       4: invokespecial #1                  // Method org/opensaml/saml2/core/impl/RequestAbstractTypeImpl."<init>":(Ljava/lang/String;Ljava/lang/String;Ljava/lang/String;)V
       7: return

  public org.opensaml.saml2.core.NameID getNameID();
    Code:
       0: aload_0
       1: getfield      #2                  // Field nameID:Lorg/opensaml/saml2/core/NameID;
       4: areturn

  public void setNameID(org.opensaml.saml2.core.NameID);
    Code:
       0: aload_0
       1: aload_0
       2: aload_0
       3: getfield      #2                  // Field nameID:Lorg/opensaml/saml2/core/NameID;
       6: aload_1
       7: invokevirtual #3                  // Method prepareForAssignment:(Lorg/opensaml/xml/XMLObject;Lorg/opensaml/xml/XMLObject;)Lorg/opensaml/xml/XMLObject;
      10: checkcast     #4                  // class org/opensaml/saml2/core/NameID
      13: putfield      #2                  // Field nameID:Lorg/opensaml/saml2/core/NameID;
      16: return

  public org.opensaml.saml2.core.EncryptedID getEncryptedID();
    Code:
       0: aload_0
       1: getfield      #5                  // Field encryptedID:Lorg/opensaml/saml2/core/EncryptedID;
       4: areturn

  public void setEncryptedID(org.opensaml.saml2.core.EncryptedID);
    Code:
       0: aload_0
       1: aload_0
       2: aload_0
       3: getfield      #5                  // Field encryptedID:Lorg/opensaml/saml2/core/EncryptedID;
       6: aload_1
       7: invokevirtual #3                  // Method prepareForAssignment:(Lorg/opensaml/xml/XMLObject;Lorg/opensaml/xml/XMLObject;)Lorg/opensaml/xml/XMLObject;
      10: checkcast     #6                  // class org/opensaml/saml2/core/EncryptedID
      13: putfield      #5                  // Field encryptedID:Lorg/opensaml/saml2/core/EncryptedID;
      16: return

  public org.opensaml.saml2.core.NewID getNewID();
    Code:
       0: aload_0
       1: getfield      #7                  // Field newID:Lorg/opensaml/saml2/core/NewID;
       4: areturn

  public void setNewID(org.opensaml.saml2.core.NewID);
    Code:
       0: aload_0
       1: aload_0
       2: aload_0
       3: getfield      #7                  // Field newID:Lorg/opensaml/saml2/core/NewID;
       6: aload_1
       7: invokevirtual #3                  // Method prepareForAssignment:(Lorg/opensaml/xml/XMLObject;Lorg/opensaml/xml/XMLObject;)Lorg/opensaml/xml/XMLObject;
      10: checkcast     #8                  // class org/opensaml/saml2/core/NewID
      13: putfield      #7                  // Field newID:Lorg/opensaml/saml2/core/NewID;
      16: return

  public org.opensaml.saml2.core.NewEncryptedID getNewEncryptedID();
    Code:
       0: aload_0
       1: getfield      #9                  // Field newEncryptedID:Lorg/opensaml/saml2/core/NewEncryptedID;
       4: areturn

  public void setNewEncryptedID(org.opensaml.saml2.core.NewEncryptedID);
    Code:
       0: aload_0
       1: aload_0
       2: aload_0
       3: getfield      #9                  // Field newEncryptedID:Lorg/opensaml/saml2/core/NewEncryptedID;
       6: aload_1
       7: invokevirtual #3                  // Method prepareForAssignment:(Lorg/opensaml/xml/XMLObject;Lorg/opensaml/xml/XMLObject;)Lorg/opensaml/xml/XMLObject;
      10: checkcast     #10                 // class org/opensaml/saml2/core/NewEncryptedID
      13: putfield      #9                  // Field newEncryptedID:Lorg/opensaml/saml2/core/NewEncryptedID;
      16: return

  public org.opensaml.saml2.core.Terminate getTerminate();
    Code:
       0: aload_0
       1: getfield      #11                 // Field terminate:Lorg/opensaml/saml2/core/Terminate;
       4: areturn

  public void setTerminate(org.opensaml.saml2.core.Terminate);
    Code:
       0: aload_0
       1: aload_0
       2: aload_0
       3: getfield      #11                 // Field terminate:Lorg/opensaml/saml2/core/Terminate;
       6: aload_1
       7: invokevirtual #3                  // Method prepareForAssignment:(Lorg/opensaml/xml/XMLObject;Lorg/opensaml/xml/XMLObject;)Lorg/opensaml/xml/XMLObject;
      10: checkcast     #12                 // class org/opensaml/saml2/core/Terminate
      13: putfield      #11                 // Field terminate:Lorg/opensaml/saml2/core/Terminate;
      16: return

  public java.util.List<org.opensaml.xml.XMLObject> getOrderedChildren();
    Code:
       0: new           #13                 // class java/util/ArrayList
       3: dup
       4: invokespecial #14                 // Method java/util/ArrayList."<init>":()V
       7: astore_1
       8: aload_0
       9: invokespecial #15                 // Method org/opensaml/saml2/core/impl/RequestAbstractTypeImpl.getOrderedChildren:()Ljava/util/List;
      12: ifnull        24
      15: aload_1
      16: aload_0
      17: invokespecial #15                 // Method org/opensaml/saml2/core/impl/RequestAbstractTypeImpl.getOrderedChildren:()Ljava/util/List;
      20: invokevirtual #16                 // Method java/util/ArrayList.addAll:(Ljava/util/Collection;)Z
      23: pop
      24: aload_0
      25: getfield      #2                  // Field nameID:Lorg/opensaml/saml2/core/NameID;
      28: ifnull        40
      31: aload_1
      32: aload_0
      33: getfield      #2                  // Field nameID:Lorg/opensaml/saml2/core/NameID;
      36: invokevirtual #17                 // Method java/util/ArrayList.add:(Ljava/lang/Object;)Z
      39: pop
      40: aload_0
      41: getfield      #5                  // Field encryptedID:Lorg/opensaml/saml2/core/EncryptedID;
      44: ifnull        56
      47: aload_1
      48: aload_0
      49: getfield      #5                  // Field encryptedID:Lorg/opensaml/saml2/core/EncryptedID;
      52: invokevirtual #17                 // Method java/util/ArrayList.add:(Ljava/lang/Object;)Z
      55: pop
      56: aload_0
      57: getfield      #7                  // Field newID:Lorg/opensaml/saml2/core/NewID;
      60: ifnull        72
      63: aload_1
      64: aload_0
      65: getfield      #7                  // Field newID:Lorg/opensaml/saml2/core/NewID;
      68: invokevirtual #17                 // Method java/util/ArrayList.add:(Ljava/lang/Object;)Z
      71: pop
      72: aload_0
      73: getfield      #9                  // Field newEncryptedID:Lorg/opensaml/saml2/core/NewEncryptedID;
      76: ifnull        88
      79: aload_1
      80: aload_0
      81: getfield      #9                  // Field newEncryptedID:Lorg/opensaml/saml2/core/NewEncryptedID;
      84: invokevirtual #17                 // Method java/util/ArrayList.add:(Ljava/lang/Object;)Z
      87: pop
      88: aload_0
      89: getfield      #11                 // Field terminate:Lorg/opensaml/saml2/core/Terminate;
      92: ifnull        104
      95: aload_1
      96: aload_0
      97: getfield      #11                 // Field terminate:Lorg/opensaml/saml2/core/Terminate;
     100: invokevirtual #17                 // Method java/util/ArrayList.add:(Ljava/lang/Object;)Z
     103: pop
     104: aload_1
     105: invokevirtual #18                 // Method java/util/ArrayList.size:()I
     108: ifne          113
     111: aconst_null
     112: areturn
     113: aload_1
     114: invokestatic  #19                 // Method java/util/Collections.unmodifiableList:(Ljava/util/List;)Ljava/util/List;
     117: areturn
}
