Compiled from "TripleLongPriorityQueue.java"
public class org.apache.pulsar.common.util.collections.TripleLongPriorityQueue implements java.lang.AutoCloseable {
  private static final int SIZE_OF_LONG;

  private static final int DEFAULT_INITIAL_CAPACITY;

  private static final int ITEMS_COUNT;

  private static final int TUPLE_SIZE;

  private final io.netty.buffer.ByteBuf buffer;

  private int capacity;

  private int size;

  public org.apache.pulsar.common.util.collections.TripleLongPriorityQueue();
    Code:
       0: aload_0
       1: bipush        16
       3: invokespecial #2                  // Method "<init>":(I)V
       6: return

  public org.apache.pulsar.common.util.collections.TripleLongPriorityQueue(int);
    Code:
       0: aload_0
       1: invokespecial #3                  // Method java/lang/Object."<init>":()V
       4: aload_0
       5: iload_1
       6: putfield      #4                  // Field capacity:I
       9: aload_0
      10: getstatic     #5                  // Field io/netty/buffer/PooledByteBufAllocator.DEFAULT:Lio/netty/buffer/PooledByteBufAllocator;
      13: iload_1
      14: iconst_3
      15: imul
      16: bipush        8
      18: imul
      19: invokevirtual #6                  // Method io/netty/buffer/PooledByteBufAllocator.directBuffer:(I)Lio/netty/buffer/ByteBuf;
      22: putfield      #7                  // Field buffer:Lio/netty/buffer/ByteBuf;
      25: aload_0
      26: iconst_0
      27: putfield      #8                  // Field size:I
      30: return

  public void close();
    Code:
       0: aload_0
       1: getfield      #7                  // Field buffer:Lio/netty/buffer/ByteBuf;
       4: invokevirtual #9                  // Method io/netty/buffer/ByteBuf.release:()Z
       7: pop
       8: return

  public void add(long, long, long);
    Code:
       0: aload_0
       1: getfield      #8                  // Field size:I
       4: aload_0
       5: getfield      #4                  // Field capacity:I
       8: if_icmpne     15
      11: aload_0
      12: invokespecial #10                 // Method increaseCapacity:()V
      15: aload_0
      16: aload_0
      17: getfield      #8                  // Field size:I
      20: lload_1
      21: lload_3
      22: lload         5
      24: invokespecial #11                 // Method put:(IJJJ)V
      27: aload_0
      28: aload_0
      29: getfield      #8                  // Field size:I
      32: invokespecial #12                 // Method siftUp:(I)V
      35: aload_0
      36: dup
      37: getfield      #8                  // Field size:I
      40: iconst_1
      41: iadd
      42: putfield      #8                  // Field size:I
      45: return

  public long peekN1();
    Code:
       0: aload_0
       1: getfield      #8                  // Field size:I
       4: ifeq          11
       7: iconst_1
       8: goto          12
      11: iconst_0
      12: invokestatic  #13                 // Method com/google/common/base/Preconditions.checkArgument:(Z)V
      15: aload_0
      16: getfield      #7                  // Field buffer:Lio/netty/buffer/ByteBuf;
      19: iconst_0
      20: invokevirtual #14                 // Method io/netty/buffer/ByteBuf.getLong:(I)J
      23: lreturn

  public long peekN2();
    Code:
       0: aload_0
       1: getfield      #8                  // Field size:I
       4: ifeq          11
       7: iconst_1
       8: goto          12
      11: iconst_0
      12: invokestatic  #13                 // Method com/google/common/base/Preconditions.checkArgument:(Z)V
      15: aload_0
      16: getfield      #7                  // Field buffer:Lio/netty/buffer/ByteBuf;
      19: bipush        8
      21: invokevirtual #14                 // Method io/netty/buffer/ByteBuf.getLong:(I)J
      24: lreturn

  public long peekN3();
    Code:
       0: aload_0
       1: getfield      #8                  // Field size:I
       4: ifeq          11
       7: iconst_1
       8: goto          12
      11: iconst_0
      12: invokestatic  #13                 // Method com/google/common/base/Preconditions.checkArgument:(Z)V
      15: aload_0
      16: getfield      #7                  // Field buffer:Lio/netty/buffer/ByteBuf;
      19: bipush        16
      21: invokevirtual #14                 // Method io/netty/buffer/ByteBuf.getLong:(I)J
      24: lreturn

  public void pop();
    Code:
       0: aload_0
       1: getfield      #8                  // Field size:I
       4: ifeq          11
       7: iconst_1
       8: goto          12
      11: iconst_0
      12: invokestatic  #13                 // Method com/google/common/base/Preconditions.checkArgument:(Z)V
      15: aload_0
      16: iconst_0
      17: aload_0
      18: getfield      #8                  // Field size:I
      21: iconst_1
      22: isub
      23: invokespecial #15                 // Method swap:(II)V
      26: aload_0
      27: dup
      28: getfield      #8                  // Field size:I
      31: iconst_1
      32: isub
      33: putfield      #8                  // Field size:I
      36: aload_0
      37: iconst_0
      38: invokespecial #16                 // Method siftDown:(I)V
      41: return

  public boolean isEmpty();
    Code:
       0: aload_0
       1: getfield      #8                  // Field size:I
       4: ifne          11
       7: iconst_1
       8: goto          12
      11: iconst_0
      12: ireturn

  public int size();
    Code:
       0: aload_0
       1: getfield      #8                  // Field size:I
       4: ireturn

  public void clear();
    Code:
       0: aload_0
       1: getfield      #7                  // Field buffer:Lio/netty/buffer/ByteBuf;
       4: invokevirtual #17                 // Method io/netty/buffer/ByteBuf.clear:()Lio/netty/buffer/ByteBuf;
       7: pop
       8: aload_0
       9: iconst_0
      10: putfield      #8                  // Field size:I
      13: return

  private void increaseCapacity();
    Code:
       0: aload_0
       1: dup
       2: getfield      #4                  // Field capacity:I
       5: aload_0
       6: getfield      #4                  // Field capacity:I
       9: sipush        256
      12: if_icmpgt     22
      15: aload_0
      16: getfield      #4                  // Field capacity:I
      19: goto          28
      22: aload_0
      23: getfield      #4                  // Field capacity:I
      26: iconst_2
      27: idiv
      28: iadd
      29: putfield      #4                  // Field capacity:I
      32: aload_0
      33: getfield      #7                  // Field buffer:Lio/netty/buffer/ByteBuf;
      36: aload_0
      37: getfield      #4                  // Field capacity:I
      40: bipush        24
      42: imul
      43: invokevirtual #18                 // Method io/netty/buffer/ByteBuf.capacity:(I)Lio/netty/buffer/ByteBuf;
      46: pop
      47: return

  private void siftUp(int);
    Code:
       0: iload_1
       1: ifle          33
       4: iload_1
       5: iconst_1
       6: isub
       7: iconst_2
       8: idiv
       9: istore_2
      10: aload_0
      11: iload_1
      12: iload_2
      13: invokespecial #19                 // Method compare:(II)I
      16: iflt          22
      19: goto          33
      22: aload_0
      23: iload_1
      24: iload_2
      25: invokespecial #15                 // Method swap:(II)V
      28: iload_2
      29: istore_1
      30: goto          0
      33: return

  private void siftDown(int);
    Code:
       0: aload_0
       1: getfield      #8                  // Field size:I
       4: iconst_2
       5: idiv
       6: istore_2
       7: iload_1
       8: iload_2
       9: if_icmpge     84
      12: iconst_2
      13: iload_1
      14: imul
      15: iconst_1
      16: iadd
      17: istore_3
      18: iconst_2
      19: iload_1
      20: imul
      21: iconst_2
      22: iadd
      23: istore        4
      25: iload_1
      26: istore        5
      28: aload_0
      29: iload_1
      30: iload_3
      31: invokespecial #19                 // Method compare:(II)I
      34: ifle          40
      37: iload_3
      38: istore        5
      40: iload         4
      42: aload_0
      43: getfield      #8                  // Field size:I
      46: if_icmpge     64
      49: aload_0
      50: iload         5
      52: iload         4
      54: invokespecial #19                 // Method compare:(II)I
      57: ifle          64
      60: iload         4
      62: istore        5
      64: iload         5
      66: iload_1
      67: if_icmpne     71
      70: return
      71: aload_0
      72: iload_1
      73: iload         5
      75: invokespecial #15                 // Method swap:(II)V
      78: iload         5
      80: istore_1
      81: goto          7
      84: return

  private void put(int, long, long, long);
    Code:
       0: iload_1
       1: bipush        24
       3: imul
       4: istore        8
       6: aload_0
       7: getfield      #7                  // Field buffer:Lio/netty/buffer/ByteBuf;
      10: iload         8
      12: lload_2
      13: invokevirtual #20                 // Method io/netty/buffer/ByteBuf.setLong:(IJ)Lio/netty/buffer/ByteBuf;
      16: pop
      17: aload_0
      18: getfield      #7                  // Field buffer:Lio/netty/buffer/ByteBuf;
      21: iload         8
      23: bipush        8
      25: iadd
      26: lload         4
      28: invokevirtual #20                 // Method io/netty/buffer/ByteBuf.setLong:(IJ)Lio/netty/buffer/ByteBuf;
      31: pop
      32: aload_0
      33: getfield      #7                  // Field buffer:Lio/netty/buffer/ByteBuf;
      36: iload         8
      38: bipush        16
      40: iadd
      41: lload         6
      43: invokevirtual #20                 // Method io/netty/buffer/ByteBuf.setLong:(IJ)Lio/netty/buffer/ByteBuf;
      46: pop
      47: return

  private int compare(int, int);
    Code:
       0: iload_1
       1: bipush        24
       3: imul
       4: istore_3
       5: iload_2
       6: bipush        24
       8: imul
       9: istore        4
      11: aload_0
      12: getfield      #7                  // Field buffer:Lio/netty/buffer/ByteBuf;
      15: iload_3
      16: invokevirtual #14                 // Method io/netty/buffer/ByteBuf.getLong:(I)J
      19: aload_0
      20: getfield      #7                  // Field buffer:Lio/netty/buffer/ByteBuf;
      23: iload         4
      25: invokevirtual #14                 // Method io/netty/buffer/ByteBuf.getLong:(I)J
      28: invokestatic  #21                 // Method java/lang/Long.compare:(JJ)I
      31: istore        5
      33: iload         5
      35: ifeq          41
      38: iload         5
      40: ireturn
      41: aload_0
      42: getfield      #7                  // Field buffer:Lio/netty/buffer/ByteBuf;
      45: iload_3
      46: bipush        8
      48: iadd
      49: invokevirtual #14                 // Method io/netty/buffer/ByteBuf.getLong:(I)J
      52: aload_0
      53: getfield      #7                  // Field buffer:Lio/netty/buffer/ByteBuf;
      56: iload         4
      58: bipush        8
      60: iadd
      61: invokevirtual #14                 // Method io/netty/buffer/ByteBuf.getLong:(I)J
      64: invokestatic  #21                 // Method java/lang/Long.compare:(JJ)I
      67: istore        6
      69: iload         6
      71: ifeq          77
      74: iload         6
      76: ireturn
      77: aload_0
      78: getfield      #7                  // Field buffer:Lio/netty/buffer/ByteBuf;
      81: iload_3
      82: bipush        16
      84: iadd
      85: invokevirtual #14                 // Method io/netty/buffer/ByteBuf.getLong:(I)J
      88: aload_0
      89: getfield      #7                  // Field buffer:Lio/netty/buffer/ByteBuf;
      92: iload         4
      94: bipush        16
      96: iadd
      97: invokevirtual #14                 // Method io/netty/buffer/ByteBuf.getLong:(I)J
     100: invokestatic  #21                 // Method java/lang/Long.compare:(JJ)I
     103: ireturn

  private void swap(int, int);
    Code:
       0: iload_1
       1: bipush        24
       3: imul
       4: istore_3
       5: iload_2
       6: bipush        24
       8: imul
       9: istore        4
      11: aload_0
      12: getfield      #7                  // Field buffer:Lio/netty/buffer/ByteBuf;
      15: iload_3
      16: invokevirtual #14                 // Method io/netty/buffer/ByteBuf.getLong:(I)J
      19: lstore        5
      21: aload_0
      22: getfield      #7                  // Field buffer:Lio/netty/buffer/ByteBuf;
      25: iload_3
      26: bipush        8
      28: iadd
      29: invokevirtual #14                 // Method io/netty/buffer/ByteBuf.getLong:(I)J
      32: lstore        7
      34: aload_0
      35: getfield      #7                  // Field buffer:Lio/netty/buffer/ByteBuf;
      38: iload_3
      39: bipush        16
      41: iadd
      42: invokevirtual #14                 // Method io/netty/buffer/ByteBuf.getLong:(I)J
      45: lstore        9
      47: aload_0
      48: getfield      #7                  // Field buffer:Lio/netty/buffer/ByteBuf;
      51: iload_3
      52: aload_0
      53: getfield      #7                  // Field buffer:Lio/netty/buffer/ByteBuf;
      56: iload         4
      58: invokevirtual #14                 // Method io/netty/buffer/ByteBuf.getLong:(I)J
      61: invokevirtual #20                 // Method io/netty/buffer/ByteBuf.setLong:(IJ)Lio/netty/buffer/ByteBuf;
      64: pop
      65: aload_0
      66: getfield      #7                  // Field buffer:Lio/netty/buffer/ByteBuf;
      69: iload_3
      70: bipush        8
      72: iadd
      73: aload_0
      74: getfield      #7                  // Field buffer:Lio/netty/buffer/ByteBuf;
      77: iload         4
      79: bipush        8
      81: iadd
      82: invokevirtual #14                 // Method io/netty/buffer/ByteBuf.getLong:(I)J
      85: invokevirtual #20                 // Method io/netty/buffer/ByteBuf.setLong:(IJ)Lio/netty/buffer/ByteBuf;
      88: pop
      89: aload_0
      90: getfield      #7                  // Field buffer:Lio/netty/buffer/ByteBuf;
      93: iload_3
      94: bipush        16
      96: iadd
      97: aload_0
      98: getfield      #7                  // Field buffer:Lio/netty/buffer/ByteBuf;
     101: iload         4
     103: bipush        16
     105: iadd
     106: invokevirtual #14                 // Method io/netty/buffer/ByteBuf.getLong:(I)J
     109: invokevirtual #20                 // Method io/netty/buffer/ByteBuf.setLong:(IJ)Lio/netty/buffer/ByteBuf;
     112: pop
     113: aload_0
     114: getfield      #7                  // Field buffer:Lio/netty/buffer/ByteBuf;
     117: iload         4
     119: lload         5
     121: invokevirtual #20                 // Method io/netty/buffer/ByteBuf.setLong:(IJ)Lio/netty/buffer/ByteBuf;
     124: pop
     125: aload_0
     126: getfield      #7                  // Field buffer:Lio/netty/buffer/ByteBuf;
     129: iload         4
     131: bipush        8
     133: iadd
     134: lload         7
     136: invokevirtual #20                 // Method io/netty/buffer/ByteBuf.setLong:(IJ)Lio/netty/buffer/ByteBuf;
     139: pop
     140: aload_0
     141: getfield      #7                  // Field buffer:Lio/netty/buffer/ByteBuf;
     144: iload         4
     146: bipush        16
     148: iadd
     149: lload         9
     151: invokevirtual #20                 // Method io/netty/buffer/ByteBuf.setLong:(IJ)Lio/netty/buffer/ByteBuf;
     154: pop
     155: return
}
