Compiled from "recursions.scala"
public class morphir.ir.recursions$TypeCase$Variable$ implements java.io.Serializable {
  public static final morphir.ir.recursions$TypeCase$Variable$ MODULE$;

  public static {};
    Code:
       0: new           #2                  // class morphir/ir/recursions$TypeCase$Variable$
       3: dup
       4: invokespecial #23                 // Method "<init>":()V
       7: putstatic     #25                 // Field MODULE$:Lmorphir/ir/recursions$TypeCase$Variable$;
      10: return

  public final java.lang.String toString();
    Code:
       0: ldc           #28                 // String Variable
       2: areturn

  public <Attrib> morphir.ir.recursions$TypeCase$Variable<Attrib> apply(Attrib);
    Code:
       0: new           #14                 // class morphir/ir/recursions$TypeCase$Variable
       3: dup
       4: aload_1
       5: invokespecial #36                 // Method morphir/ir/recursions$TypeCase$Variable."<init>":(Ljava/lang/Object;)V
       8: areturn

  public <Attrib> scala.Option<Attrib> unapply(morphir.ir.recursions$TypeCase$Variable<Attrib>);
    Code:
       0: aload_1
       1: ifnonnull     10
       4: getstatic     #46                 // Field scala/None$.MODULE$:Lscala/None$;
       7: goto          21
      10: new           #48                 // class scala/Some
      13: dup
      14: aload_1
      15: invokevirtual #51                 // Method morphir/ir/recursions$TypeCase$Variable.a:()Ljava/lang/Object;
      18: invokespecial #52                 // Method scala/Some."<init>":(Ljava/lang/Object;)V
      21: areturn

  private java.lang.Object writeReplace();
    Code:
       0: new           #58                 // class scala/runtime/ModuleSerializationProxy
       3: dup
       4: ldc           #2                  // class morphir/ir/recursions$TypeCase$Variable$
       6: invokespecial #61                 // Method scala/runtime/ModuleSerializationProxy."<init>":(Ljava/lang/Class;)V
       9: areturn

  public morphir.ir.recursions$TypeCase$Variable$();
    Code:
       0: aload_0
       1: invokespecial #62                 // Method java/lang/Object."<init>":()V
       4: return
}
