Compiled from "TerminationParticipantClient.java"
public class com.arjuna.webservices11.wsarjtx.client.TerminationParticipantClient {
  private static final com.arjuna.webservices11.wsarjtx.client.TerminationParticipantClient CLIENT;

  private java.lang.String completedAction;

  private java.lang.String closedAction;

  private java.lang.String cancelledAction;

  private java.lang.String faultedAction;

  private java.lang.String soapFaultAction;

  private org.jboss.ws.api.addressing.MAPEndpoint terminationCoordinator;

  private org.jboss.ws.api.addressing.MAPEndpoint secureTerminationCoordinator;

  private com.arjuna.webservices11.wsarjtx.client.TerminationParticipantClient();
    Code:
       0: aload_0
       1: invokespecial #1                  // Method java/lang/Object."<init>":()V
       4: aload_0
       5: aconst_null
       6: putfield      #2                  // Field completedAction:Ljava/lang/String;
       9: aload_0
      10: aconst_null
      11: putfield      #3                  // Field closedAction:Ljava/lang/String;
      14: aload_0
      15: aconst_null
      16: putfield      #4                  // Field cancelledAction:Ljava/lang/String;
      19: aload_0
      20: aconst_null
      21: putfield      #5                  // Field faultedAction:Ljava/lang/String;
      24: aload_0
      25: aconst_null
      26: putfield      #6                  // Field soapFaultAction:Ljava/lang/String;
      29: invokestatic  #7                  // Method com/arjuna/webservices11/util/PrivilegedMapBuilderFactory.getInstance:()Lcom/arjuna/webservices11/util/PrivilegedMapBuilderFactory;
      32: invokevirtual #8                  // Method com/arjuna/webservices11/util/PrivilegedMapBuilderFactory.getBuilderInstance:()Lorg/jboss/ws/api/addressing/MAPBuilder;
      35: astore_1
      36: aload_0
      37: ldc           #10                 // String http://schemas.arjuna.com/ws/2005/10/wsarjtx/Completed
      39: putfield      #2                  // Field completedAction:Ljava/lang/String;
      42: aload_0
      43: ldc           #11                 // String http://schemas.arjuna.com/ws/2005/10/wsarjtx/Closed
      45: putfield      #3                  // Field closedAction:Ljava/lang/String;
      48: aload_0
      49: ldc           #12                 // String http://schemas.arjuna.com/ws/2005/10/wsarjtx/Cancelled
      51: putfield      #4                  // Field cancelledAction:Ljava/lang/String;
      54: aload_0
      55: ldc           #13                 // String http://schemas.arjuna.com/ws/2005/10/wsarjtx/Faulted
      57: putfield      #5                  // Field faultedAction:Ljava/lang/String;
      60: aload_0
      61: ldc           #14                 // String http://schemas.arjuna.com/ws/2005/10/wsarjtx/Fault
      63: putfield      #6                  // Field soapFaultAction:Ljava/lang/String;
      66: invokestatic  #15                 // Method com/arjuna/webservices11/util/PrivilegedServiceRegistryFactory.getInstance:()Lcom/arjuna/webservices11/util/PrivilegedServiceRegistryFactory;
      69: invokevirtual #16                 // Method com/arjuna/webservices11/util/PrivilegedServiceRegistryFactory.getServiceRegistry:()Lcom/arjuna/webservices11/ServiceRegistry;
      72: astore_2
      73: aload_2
      74: ldc           #18                 // String TerminationCoordinatorService
      76: iconst_0
      77: invokevirtual #19                 // Method com/arjuna/webservices11/ServiceRegistry.getServiceURI:(Ljava/lang/String;Z)Ljava/lang/String;
      80: astore_3
      81: aload_2
      82: ldc           #18                 // String TerminationCoordinatorService
      84: iconst_1
      85: invokevirtual #19                 // Method com/arjuna/webservices11/ServiceRegistry.getServiceURI:(Ljava/lang/String;Z)Ljava/lang/String;
      88: astore        4
      90: aload_0
      91: aload_1
      92: aload_3
      93: invokeinterface #20,  2           // InterfaceMethod org/jboss/ws/api/addressing/MAPBuilder.newEndpoint:(Ljava/lang/String;)Lorg/jboss/ws/api/addressing/MAPEndpoint;
      98: putfield      #21                 // Field terminationCoordinator:Lorg/jboss/ws/api/addressing/MAPEndpoint;
     101: aload_0
     102: aload_1
     103: aload         4
     105: invokeinterface #20,  2           // InterfaceMethod org/jboss/ws/api/addressing/MAPBuilder.newEndpoint:(Ljava/lang/String;)Lorg/jboss/ws/api/addressing/MAPEndpoint;
     110: putfield      #22                 // Field secureTerminationCoordinator:Lorg/jboss/ws/api/addressing/MAPEndpoint;
     113: return

  public void sendCompleted(javax.xml.ws.wsaddressing.W3CEndpointReference, org.jboss.ws.api.addressing.MAP, com.arjuna.webservices11.wsarj.InstanceIdentifier) throws com.arjuna.webservices.SoapFault, java.io.IOException;
    Code:
       0: aload_0
       1: aload_1
       2: invokevirtual #23                 // Method getCoordinator:(Ljavax/xml/ws/wsaddressing/W3CEndpointReference;)Lorg/jboss/ws/api/addressing/MAPEndpoint;
       5: astore        4
       7: aload_2
       8: aload         4
      10: aload_3
      11: invokestatic  #24                 // Method com/arjuna/webservices11/wsaddr/AddressingHelper.installFromFaultTo:(Lorg/jboss/ws/api/addressing/MAP;Lorg/jboss/ws/api/addressing/MAPEndpoint;Lcom/arjuna/webservices11/wsarj/InstanceIdentifier;)V
      14: aload_0
      15: aload_1
      16: aload_2
      17: aload_3
      18: aload_0
      19: getfield      #2                  // Field completedAction:Ljava/lang/String;
      22: invokespecial #25                 // Method getPort:(Ljavax/xml/ws/wsaddressing/W3CEndpointReference;Lorg/jboss/ws/api/addressing/MAP;Lcom/arjuna/webservices11/wsarj/InstanceIdentifier;Ljava/lang/String;)Lcom/arjuna/schemas/ws/_2005/_10/wsarjtx/TerminationParticipantPortType;
      25: astore        5
      27: new           #26                 // class com/arjuna/schemas/ws/_2005/_10/wsarjtx/NotificationType
      30: dup
      31: invokespecial #27                 // Method com/arjuna/schemas/ws/_2005/_10/wsarjtx/NotificationType."<init>":()V
      34: astore        6
      36: aload         5
      38: aload         6
      40: invokeinterface #28,  2           // InterfaceMethod com/arjuna/schemas/ws/_2005/_10/wsarjtx/TerminationParticipantPortType.completedOperation:(Lcom/arjuna/schemas/ws/_2005/_10/wsarjtx/NotificationType;)V
      45: return

  public void sendClosed(javax.xml.ws.wsaddressing.W3CEndpointReference, org.jboss.ws.api.addressing.MAP, com.arjuna.webservices11.wsarj.InstanceIdentifier) throws com.arjuna.webservices.SoapFault, java.io.IOException;
    Code:
       0: aload_0
       1: aload_1
       2: invokevirtual #23                 // Method getCoordinator:(Ljavax/xml/ws/wsaddressing/W3CEndpointReference;)Lorg/jboss/ws/api/addressing/MAPEndpoint;
       5: astore        4
       7: aload_2
       8: aload         4
      10: aload_3
      11: invokestatic  #24                 // Method com/arjuna/webservices11/wsaddr/AddressingHelper.installFromFaultTo:(Lorg/jboss/ws/api/addressing/MAP;Lorg/jboss/ws/api/addressing/MAPEndpoint;Lcom/arjuna/webservices11/wsarj/InstanceIdentifier;)V
      14: aload_0
      15: aload_1
      16: aload_2
      17: aload_3
      18: aload_0
      19: getfield      #3                  // Field closedAction:Ljava/lang/String;
      22: invokespecial #25                 // Method getPort:(Ljavax/xml/ws/wsaddressing/W3CEndpointReference;Lorg/jboss/ws/api/addressing/MAP;Lcom/arjuna/webservices11/wsarj/InstanceIdentifier;Ljava/lang/String;)Lcom/arjuna/schemas/ws/_2005/_10/wsarjtx/TerminationParticipantPortType;
      25: astore        5
      27: new           #26                 // class com/arjuna/schemas/ws/_2005/_10/wsarjtx/NotificationType
      30: dup
      31: invokespecial #27                 // Method com/arjuna/schemas/ws/_2005/_10/wsarjtx/NotificationType."<init>":()V
      34: astore        6
      36: aload         5
      38: aload         6
      40: invokeinterface #29,  2           // InterfaceMethod com/arjuna/schemas/ws/_2005/_10/wsarjtx/TerminationParticipantPortType.closedOperation:(Lcom/arjuna/schemas/ws/_2005/_10/wsarjtx/NotificationType;)V
      45: return

  public void sendCancelled(javax.xml.ws.wsaddressing.W3CEndpointReference, org.jboss.ws.api.addressing.MAP, com.arjuna.webservices11.wsarj.InstanceIdentifier) throws com.arjuna.webservices.SoapFault, java.io.IOException;
    Code:
       0: aload_0
       1: aload_1
       2: invokevirtual #23                 // Method getCoordinator:(Ljavax/xml/ws/wsaddressing/W3CEndpointReference;)Lorg/jboss/ws/api/addressing/MAPEndpoint;
       5: astore        4
       7: aload_2
       8: aload         4
      10: aload_3
      11: invokestatic  #24                 // Method com/arjuna/webservices11/wsaddr/AddressingHelper.installFromFaultTo:(Lorg/jboss/ws/api/addressing/MAP;Lorg/jboss/ws/api/addressing/MAPEndpoint;Lcom/arjuna/webservices11/wsarj/InstanceIdentifier;)V
      14: aload_0
      15: aload_1
      16: aload_2
      17: aload_3
      18: aload_0
      19: getfield      #4                  // Field cancelledAction:Ljava/lang/String;
      22: invokespecial #25                 // Method getPort:(Ljavax/xml/ws/wsaddressing/W3CEndpointReference;Lorg/jboss/ws/api/addressing/MAP;Lcom/arjuna/webservices11/wsarj/InstanceIdentifier;Ljava/lang/String;)Lcom/arjuna/schemas/ws/_2005/_10/wsarjtx/TerminationParticipantPortType;
      25: astore        5
      27: new           #26                 // class com/arjuna/schemas/ws/_2005/_10/wsarjtx/NotificationType
      30: dup
      31: invokespecial #27                 // Method com/arjuna/schemas/ws/_2005/_10/wsarjtx/NotificationType."<init>":()V
      34: astore        6
      36: aload         5
      38: aload         6
      40: invokeinterface #30,  2           // InterfaceMethod com/arjuna/schemas/ws/_2005/_10/wsarjtx/TerminationParticipantPortType.cancelledOperation:(Lcom/arjuna/schemas/ws/_2005/_10/wsarjtx/NotificationType;)V
      45: return

  public void sendFaulted(javax.xml.ws.wsaddressing.W3CEndpointReference, org.jboss.ws.api.addressing.MAP, com.arjuna.webservices11.wsarj.InstanceIdentifier) throws com.arjuna.webservices.SoapFault, java.io.IOException;
    Code:
       0: aload_0
       1: aload_1
       2: invokevirtual #23                 // Method getCoordinator:(Ljavax/xml/ws/wsaddressing/W3CEndpointReference;)Lorg/jboss/ws/api/addressing/MAPEndpoint;
       5: astore        4
       7: aload_2
       8: aload         4
      10: aload_3
      11: invokestatic  #24                 // Method com/arjuna/webservices11/wsaddr/AddressingHelper.installFromFaultTo:(Lorg/jboss/ws/api/addressing/MAP;Lorg/jboss/ws/api/addressing/MAPEndpoint;Lcom/arjuna/webservices11/wsarj/InstanceIdentifier;)V
      14: aload_0
      15: aload_1
      16: aload_2
      17: aload_3
      18: aload_0
      19: getfield      #5                  // Field faultedAction:Ljava/lang/String;
      22: invokespecial #25                 // Method getPort:(Ljavax/xml/ws/wsaddressing/W3CEndpointReference;Lorg/jboss/ws/api/addressing/MAP;Lcom/arjuna/webservices11/wsarj/InstanceIdentifier;Ljava/lang/String;)Lcom/arjuna/schemas/ws/_2005/_10/wsarjtx/TerminationParticipantPortType;
      25: astore        5
      27: new           #26                 // class com/arjuna/schemas/ws/_2005/_10/wsarjtx/NotificationType
      30: dup
      31: invokespecial #27                 // Method com/arjuna/schemas/ws/_2005/_10/wsarjtx/NotificationType."<init>":()V
      34: astore        6
      36: aload         5
      38: aload         6
      40: invokeinterface #31,  2           // InterfaceMethod com/arjuna/schemas/ws/_2005/_10/wsarjtx/TerminationParticipantPortType.faultedOperation:(Lcom/arjuna/schemas/ws/_2005/_10/wsarjtx/NotificationType;)V
      45: return

  public void sendSoapFault(javax.xml.ws.wsaddressing.W3CEndpointReference, org.jboss.ws.api.addressing.MAP, com.arjuna.webservices.SoapFault, com.arjuna.webservices11.wsarj.InstanceIdentifier) throws com.arjuna.webservices.SoapFault, java.io.IOException;
    Code:
       0: aload_2
       1: invokestatic  #32                 // Method com/arjuna/webservices11/wsaddr/AddressingHelper.installNoneReplyTo:(Lorg/jboss/ws/api/addressing/MAP;)V
       4: aload_0
       5: aload_1
       6: aload_2
       7: aload         4
       9: aload_0
      10: getfield      #6                  // Field soapFaultAction:Ljava/lang/String;
      13: invokespecial #25                 // Method getPort:(Ljavax/xml/ws/wsaddressing/W3CEndpointReference;Lorg/jboss/ws/api/addressing/MAP;Lcom/arjuna/webservices11/wsarj/InstanceIdentifier;Ljava/lang/String;)Lcom/arjuna/schemas/ws/_2005/_10/wsarjtx/TerminationParticipantPortType;
      16: astore        5
      18: aload_3
      19: checkcast     #33                 // class com/arjuna/webservices11/SoapFault11
      22: astore        6
      24: aload         6
      26: invokevirtual #34                 // Method com/arjuna/webservices11/SoapFault11.toFault:()Lorg/xmlsoap/schemas/soap/envelope/Fault;
      29: astore        7
      31: aload         5
      33: aload         7
      35: invokeinterface #35,  2           // InterfaceMethod com/arjuna/schemas/ws/_2005/_10/wsarjtx/TerminationParticipantPortType.faultOperation:(Lorg/xmlsoap/schemas/soap/envelope/Fault;)V
      40: return

  public void sendSoapFault(com.arjuna.webservices.SoapFault, org.jboss.ws.api.addressing.MAP, com.arjuna.webservices11.wsarj.InstanceIdentifier) throws com.arjuna.webservices.SoapFault, java.io.IOException;
    Code:
       0: aload_0
       1: aload_2
       2: aload_3
       3: aload_0
       4: getfield      #6                  // Field soapFaultAction:Ljava/lang/String;
       7: invokespecial #36                 // Method getPort:(Lorg/jboss/ws/api/addressing/MAP;Lcom/arjuna/webservices11/wsarj/InstanceIdentifier;Ljava/lang/String;)Lcom/arjuna/schemas/ws/_2005/_10/wsarjtx/TerminationParticipantPortType;
      10: astore        4
      12: aload_1
      13: checkcast     #33                 // class com/arjuna/webservices11/SoapFault11
      16: astore        5
      18: aload         5
      20: invokevirtual #34                 // Method com/arjuna/webservices11/SoapFault11.toFault:()Lorg/xmlsoap/schemas/soap/envelope/Fault;
      23: astore        6
      25: aload         4
      27: aload         6
      29: invokeinterface #35,  2           // InterfaceMethod com/arjuna/schemas/ws/_2005/_10/wsarjtx/TerminationParticipantPortType.faultOperation:(Lorg/xmlsoap/schemas/soap/envelope/Fault;)V
      34: return

  org.jboss.ws.api.addressing.MAPEndpoint getCoordinator(javax.xml.ws.wsaddressing.W3CEndpointReference);
    Code:
       0: ldc           #37                 // class com/arjuna/webservices11/wsaddr/NativeEndpointReference
       2: aload_1
       3: invokestatic  #38                 // Method com/arjuna/webservices11/wsaddr/EndpointHelper.transform:(Ljava/lang/Class;Ljavax/xml/ws/EndpointReference;)Ljavax/xml/ws/EndpointReference;
       6: checkcast     #37                 // class com/arjuna/webservices11/wsaddr/NativeEndpointReference
       9: astore_2
      10: aload_2
      11: invokevirtual #39                 // Method com/arjuna/webservices11/wsaddr/NativeEndpointReference.getAddress:()Ljava/lang/String;
      14: astore_3
      15: aload_3
      16: ldc           #40                 // String https
      18: invokevirtual #41                 // Method java/lang/String.startsWith:(Ljava/lang/String;)Z
      21: ifeq          29
      24: aload_0
      25: getfield      #22                 // Field secureTerminationCoordinator:Lorg/jboss/ws/api/addressing/MAPEndpoint;
      28: areturn
      29: aload_0
      30: getfield      #21                 // Field terminationCoordinator:Lorg/jboss/ws/api/addressing/MAPEndpoint;
      33: areturn

  public static com.arjuna.webservices11.wsarjtx.client.TerminationParticipantClient getClient();
    Code:
       0: getstatic     #42                 // Field CLIENT:Lcom/arjuna/webservices11/wsarjtx/client/TerminationParticipantClient;
       3: areturn

  private com.arjuna.schemas.ws._2005._10.wsarjtx.TerminationParticipantPortType getPort(javax.xml.ws.wsaddressing.W3CEndpointReference, org.jboss.ws.api.addressing.MAP, com.arjuna.webservices11.wsarj.InstanceIdentifier, java.lang.String);
    Code:
       0: aload_1
       1: aload         4
       3: aload_2
       4: invokestatic  #43                 // Method com/arjuna/webservices11/wsarjtx/client/WSARJTXClient.getTerminationParticipantPort:(Ljavax/xml/ws/wsaddressing/W3CEndpointReference;Ljava/lang/String;Lorg/jboss/ws/api/addressing/MAP;)Lcom/arjuna/schemas/ws/_2005/_10/wsarjtx/TerminationParticipantPortType;
       7: areturn

  private com.arjuna.schemas.ws._2005._10.wsarjtx.TerminationParticipantPortType getPort(org.jboss.ws.api.addressing.MAP, com.arjuna.webservices11.wsarj.InstanceIdentifier, java.lang.String);
    Code:
       0: aload_1
       1: invokestatic  #32                 // Method com/arjuna/webservices11/wsaddr/AddressingHelper.installNoneReplyTo:(Lorg/jboss/ws/api/addressing/MAP;)V
       4: aload_2
       5: aload_3
       6: aload_1
       7: invokestatic  #44                 // Method com/arjuna/webservices11/wsarjtx/client/WSARJTXClient.getTerminationParticipantPort:(Lcom/arjuna/webservices11/wsarj/InstanceIdentifier;Ljava/lang/String;Lorg/jboss/ws/api/addressing/MAP;)Lcom/arjuna/schemas/ws/_2005/_10/wsarjtx/TerminationParticipantPortType;
      10: areturn

  static {};
    Code:
       0: new           #45                 // class com/arjuna/webservices11/wsarjtx/client/TerminationParticipantClient
       3: dup
       4: invokespecial #46                 // Method "<init>":()V
       7: putstatic     #42                 // Field CLIENT:Lcom/arjuna/webservices11/wsarjtx/client/TerminationParticipantClient;
      10: return
}
