Compiled from "JvmClassName.java"
public class kotlin.reflect.jvm.internal.impl.resolve.jvm.JvmClassName {
  private final java.lang.String internalName;

  private kotlin.reflect.jvm.internal.impl.name.FqName fqName;

  public static kotlin.reflect.jvm.internal.impl.resolve.jvm.JvmClassName byInternalName(java.lang.String);
    Code:
       0: aload_0
       1: ifnonnull     8
       4: iconst_0
       5: invokestatic  #46                 // Method $$$reportNull$$$0:(I)V
       8: new           #24                 // class kotlin/reflect/jvm/internal/impl/resolve/jvm/JvmClassName
      11: dup
      12: aload_0
      13: invokespecial #47                 // Method "<init>":(Ljava/lang/String;)V
      16: areturn

  public static kotlin.reflect.jvm.internal.impl.resolve.jvm.JvmClassName byClassId(kotlin.reflect.jvm.internal.impl.name.ClassId);
    Code:
       0: aload_0
       1: ifnonnull     8
       4: iconst_1
       5: invokestatic  #46                 // Method $$$reportNull$$$0:(I)V
       8: aload_0
       9: invokevirtual #41                 // Method kotlin/reflect/jvm/internal/impl/name/ClassId.getPackageFqName:()Lkotlin/reflect/jvm/internal/impl/name/FqName;
      12: astore_1
      13: aload_0
      14: invokevirtual #42                 // Method kotlin/reflect/jvm/internal/impl/name/ClassId.getRelativeClassName:()Lkotlin/reflect/jvm/internal/impl/name/FqName;
      17: invokevirtual #44                 // Method kotlin/reflect/jvm/internal/impl/name/FqName.asString:()Ljava/lang/String;
      20: bipush        46
      22: bipush        36
      24: invokevirtual #36                 // Method java/lang/String.replace:(CC)Ljava/lang/String;
      27: astore_2
      28: aload_1
      29: invokevirtual #45                 // Method kotlin/reflect/jvm/internal/impl/name/FqName.isRoot:()Z
      32: ifeq          46
      35: new           #24                 // class kotlin/reflect/jvm/internal/impl/resolve/jvm/JvmClassName
      38: dup
      39: aload_2
      40: invokespecial #47                 // Method "<init>":(Ljava/lang/String;)V
      43: goto          86
      46: new           #24                 // class kotlin/reflect/jvm/internal/impl/resolve/jvm/JvmClassName
      49: dup
      50: new           #21                 // class java/lang/StringBuilder
      53: dup
      54: invokespecial #38                 // Method java/lang/StringBuilder."<init>":()V
      57: aload_1
      58: invokevirtual #44                 // Method kotlin/reflect/jvm/internal/impl/name/FqName.asString:()Ljava/lang/String;
      61: bipush        46
      63: bipush        47
      65: invokevirtual #36                 // Method java/lang/String.replace:(CC)Ljava/lang/String;
      68: invokevirtual #39                 // Method java/lang/StringBuilder.append:(Ljava/lang/String;)Ljava/lang/StringBuilder;
      71: ldc           #1                  // String /
      73: invokevirtual #39                 // Method java/lang/StringBuilder.append:(Ljava/lang/String;)Ljava/lang/StringBuilder;
      76: aload_2
      77: invokevirtual #39                 // Method java/lang/StringBuilder.append:(Ljava/lang/String;)Ljava/lang/StringBuilder;
      80: invokevirtual #40                 // Method java/lang/StringBuilder.toString:()Ljava/lang/String;
      83: invokespecial #47                 // Method "<init>":(Ljava/lang/String;)V
      86: areturn

  public static kotlin.reflect.jvm.internal.impl.resolve.jvm.JvmClassName byFqNameWithoutInnerClasses(kotlin.reflect.jvm.internal.impl.name.FqName);
    Code:
       0: aload_0
       1: ifnonnull     8
       4: iconst_2
       5: invokestatic  #46                 // Method $$$reportNull$$$0:(I)V
       8: new           #24                 // class kotlin/reflect/jvm/internal/impl/resolve/jvm/JvmClassName
      11: dup
      12: aload_0
      13: invokevirtual #44                 // Method kotlin/reflect/jvm/internal/impl/name/FqName.asString:()Ljava/lang/String;
      16: bipush        46
      18: bipush        47
      20: invokevirtual #36                 // Method java/lang/String.replace:(CC)Ljava/lang/String;
      23: invokespecial #47                 // Method "<init>":(Ljava/lang/String;)V
      26: astore_1
      27: aload_1
      28: aload_0
      29: putfield      #26                 // Field fqName:Lkotlin/reflect/jvm/internal/impl/name/FqName;
      32: aload_1
      33: dup
      34: ifnonnull     41
      37: iconst_3
      38: invokestatic  #46                 // Method $$$reportNull$$$0:(I)V
      41: areturn

  private kotlin.reflect.jvm.internal.impl.resolve.jvm.JvmClassName(java.lang.String);
    Code:
       0: aload_1
       1: ifnonnull     8
       4: iconst_5
       5: invokestatic  #46                 // Method $$$reportNull$$$0:(I)V
       8: aload_0
       9: invokespecial #30                 // Method java/lang/Object."<init>":()V
      12: aload_0
      13: aload_1
      14: putfield      #27                 // Field internalName:Ljava/lang/String;
      17: return

  public kotlin.reflect.jvm.internal.impl.name.FqName getFqNameForTopLevelClassMaybeWithDollars();
    Code:
       0: new           #23                 // class kotlin/reflect/jvm/internal/impl/name/FqName
       3: dup
       4: aload_0
       5: getfield      #27                 // Field internalName:Ljava/lang/String;
       8: bipush        47
      10: bipush        46
      12: invokevirtual #36                 // Method java/lang/String.replace:(CC)Ljava/lang/String;
      15: invokespecial #43                 // Method kotlin/reflect/jvm/internal/impl/name/FqName."<init>":(Ljava/lang/String;)V
      18: areturn

  public kotlin.reflect.jvm.internal.impl.name.FqName getPackageFqName();
    Code:
       0: aload_0
       1: getfield      #27                 // Field internalName:Ljava/lang/String;
       4: ldc           #1                  // String /
       6: invokevirtual #35                 // Method java/lang/String.lastIndexOf:(Ljava/lang/String;)I
       9: istore_1
      10: iload_1
      11: iconst_m1
      12: if_icmpne     28
      15: getstatic     #25                 // Field kotlin/reflect/jvm/internal/impl/name/FqName.ROOT:Lkotlin/reflect/jvm/internal/impl/name/FqName;
      18: dup
      19: ifnonnull     27
      22: bipush        7
      24: invokestatic  #46                 // Method $$$reportNull$$$0:(I)V
      27: areturn
      28: new           #23                 // class kotlin/reflect/jvm/internal/impl/name/FqName
      31: dup
      32: aload_0
      33: getfield      #27                 // Field internalName:Ljava/lang/String;
      36: iconst_0
      37: iload_1
      38: invokevirtual #37                 // Method java/lang/String.substring:(II)Ljava/lang/String;
      41: bipush        47
      43: bipush        46
      45: invokevirtual #36                 // Method java/lang/String.replace:(CC)Ljava/lang/String;
      48: invokespecial #43                 // Method kotlin/reflect/jvm/internal/impl/name/FqName."<init>":(Ljava/lang/String;)V
      51: areturn

  public java.lang.String getInternalName();
    Code:
       0: aload_0
       1: getfield      #27                 // Field internalName:Ljava/lang/String;
       4: dup
       5: ifnonnull     13
       8: bipush        8
      10: invokestatic  #46                 // Method $$$reportNull$$$0:(I)V
      13: areturn

  public java.lang.String toString();
    Code:
       0: aload_0
       1: getfield      #27                 // Field internalName:Ljava/lang/String;
       4: areturn

  public boolean equals(java.lang.Object);
    Code:
       0: aload_0
       1: aload_1
       2: if_acmpne     7
       5: iconst_1
       6: ireturn
       7: aload_1
       8: ifnull        22
      11: aload_0
      12: invokevirtual #31                 // Method java/lang/Object.getClass:()Ljava/lang/Class;
      15: aload_1
      16: invokevirtual #31                 // Method java/lang/Object.getClass:()Ljava/lang/Class;
      19: if_acmpeq     24
      22: iconst_0
      23: ireturn
      24: aload_0
      25: getfield      #27                 // Field internalName:Ljava/lang/String;
      28: aload_1
      29: checkcast     #24                 // class kotlin/reflect/jvm/internal/impl/resolve/jvm/JvmClassName
      32: getfield      #27                 // Field internalName:Ljava/lang/String;
      35: invokevirtual #32                 // Method java/lang/String.equals:(Ljava/lang/Object;)Z
      38: ireturn

  public int hashCode();
    Code:
       0: aload_0
       1: getfield      #27                 // Field internalName:Ljava/lang/String;
       4: invokevirtual #34                 // Method java/lang/String.hashCode:()I
       7: ireturn

  private static void $$$reportNull$$$0(int);
    Code:
       0: iload_0
       1: tableswitch   { // 0 to 8
                     0: 52
                     1: 52
                     2: 52
                     3: 57
                     4: 52
                     5: 52
                     6: 57
                     7: 57
                     8: 57
               default: 52
          }
      52: ldc           #4                  // String Argument for @NotNull parameter \'%s\' of %s.%s must not be null
      54: goto          62
      57: ldc           #3                  // String @NotNull method %s.%s must not return null
      59: goto          62
      62: iload_0
      63: tableswitch   { // 0 to 8
                     0: 112
                     1: 112
                     2: 112
                     3: 116
                     4: 112
                     5: 112
                     6: 116
                     7: 116
                     8: 116
               default: 112
          }
     112: iconst_3
     113: goto          120
     116: iconst_2
     117: goto          120
     120: anewarray     #18                 // class java/lang/Object
     123: iload_0
     124: tableswitch   { // 0 to 8
                     0: 176
                     1: 184
                     2: 192
                     3: 200
                     4: 192
                     5: 176
                     6: 200
                     7: 200
                     8: 200
               default: 176
          }
     176: dup
     177: iconst_0
     178: ldc           #13                 // String internalName
     180: aastore
     181: goto          208
     184: dup
     185: iconst_0
     186: ldc           #8                  // String classId
     188: aastore
     189: goto          208
     192: dup
     193: iconst_0
     194: ldc           #9                  // String fqName
     196: aastore
     197: goto          208
     200: dup
     201: iconst_0
     202: ldc           #14                 // String kotlin/reflect/jvm/internal/impl/resolve/jvm/JvmClassName
     204: aastore
     205: goto          208
     208: iload_0
     209: tableswitch   { // 0 to 8
                     0: 260
                     1: 260
                     2: 260
                     3: 268
                     4: 260
                     5: 260
                     6: 276
                     7: 284
                     8: 292
               default: 260
          }
     260: dup
     261: iconst_1
     262: ldc           #14                 // String kotlin/reflect/jvm/internal/impl/resolve/jvm/JvmClassName
     264: aastore
     265: goto          300
     268: dup
     269: iconst_1
     270: ldc           #6                  // String byFqNameWithoutInnerClasses
     272: aastore
     273: goto          300
     276: dup
     277: iconst_1
     278: ldc           #10                 // String getFqNameForClassNameWithoutDollars
     280: aastore
     281: goto          300
     284: dup
     285: iconst_1
     286: ldc           #12                 // String getPackageFqName
     288: aastore
     289: goto          300
     292: dup
     293: iconst_1
     294: ldc           #11                 // String getInternalName
     296: aastore
     297: goto          300
     300: iload_0
     301: tableswitch   { // 0 to 8
                     0: 352
                     1: 360
                     2: 368
                     3: 376
                     4: 368
                     5: 379
                     6: 376
                     7: 376
                     8: 376
               default: 352
          }
     352: dup
     353: iconst_2
     354: ldc           #7                  // String byInternalName
     356: aastore
     357: goto          387
     360: dup
     361: iconst_2
     362: ldc           #5                  // String byClassId
     364: aastore
     365: goto          387
     368: dup
     369: iconst_2
     370: ldc           #6                  // String byFqNameWithoutInnerClasses
     372: aastore
     373: goto          387
     376: goto          387
     379: dup
     380: iconst_2
     381: ldc           #2                  // String <init>
     383: aastore
     384: goto          387
     387: invokestatic  #33                 // Method java/lang/String.format:(Ljava/lang/String;[Ljava/lang/Object;)Ljava/lang/String;
     390: iload_0
     391: tableswitch   { // 0 to 8
                     0: 440
                     1: 440
                     2: 440
                     3: 451
                     4: 440
                     5: 440
                     6: 451
                     7: 451
                     8: 451
               default: 440
          }
     440: new           #16                 // class java/lang/IllegalArgumentException
     443: dup_x1
     444: swap
     445: invokespecial #28                 // Method java/lang/IllegalArgumentException."<init>":(Ljava/lang/String;)V
     448: goto          462
     451: new           #17                 // class java/lang/IllegalStateException
     454: dup_x1
     455: swap
     456: invokespecial #29                 // Method java/lang/IllegalStateException."<init>":(Ljava/lang/String;)V
     459: goto          462
     462: athrow
}
