Compiled from "SyntheticJavaPartsProvider.kt"
public final class kotlin.reflect.jvm.internal.impl.resolve.jvm.SyntheticJavaPartsProvider$Companion {
  static final kotlin.reflect.jvm.internal.impl.resolve.jvm.SyntheticJavaPartsProvider$Companion $$INSTANCE;

  private static final kotlin.reflect.jvm.internal.impl.resolve.jvm.CompositeSyntheticJavaPartsProvider EMPTY;

  private kotlin.reflect.jvm.internal.impl.resolve.jvm.SyntheticJavaPartsProvider$Companion();
    Code:
       0: aload_0
       1: invokespecial #8                  // Method java/lang/Object."<init>":()V
       4: return

  public final kotlin.reflect.jvm.internal.impl.resolve.jvm.CompositeSyntheticJavaPartsProvider getEMPTY();
    Code:
       0: getstatic     #7                  // Field EMPTY:Lkotlin/reflect/jvm/internal/impl/resolve/jvm/CompositeSyntheticJavaPartsProvider;
       3: areturn

  static {};
    Code:
       0: new           #5                  // class kotlin/reflect/jvm/internal/impl/resolve/jvm/SyntheticJavaPartsProvider$Companion
       3: dup
       4: invokespecial #11                 // Method "<init>":()V
       7: putstatic     #6                  // Field $$INSTANCE:Lkotlin/reflect/jvm/internal/impl/resolve/jvm/SyntheticJavaPartsProvider$Companion;
      10: new           #3                  // class kotlin/reflect/jvm/internal/impl/resolve/jvm/CompositeSyntheticJavaPartsProvider
      13: dup
      14: invokestatic  #9                  // Method kotlin/collections/CollectionsKt.emptyList:()Ljava/util/List;
      17: invokespecial #10                 // Method kotlin/reflect/jvm/internal/impl/resolve/jvm/CompositeSyntheticJavaPartsProvider."<init>":(Ljava/util/List;)V
      20: putstatic     #7                  // Field EMPTY:Lkotlin/reflect/jvm/internal/impl/resolve/jvm/CompositeSyntheticJavaPartsProvider;
      23: return
}
