Compiled from "WSForretningsmessigUnntak.java"
public abstract class no.nav.tjeneste.virksomhet.brukervarsel.v1.feil.WSForretningsmessigUnntak implements org.jvnet.jaxb2_commons.lang.Equals2,org.jvnet.jaxb2_commons.lang.HashCode2 {
  protected java.lang.String feilkilde;

  protected java.lang.String feilaarsak;

  protected java.lang.String feilmelding;

  protected javax.xml.datatype.XMLGregorianCalendar tidspunkt;

  public no.nav.tjeneste.virksomhet.brukervarsel.v1.feil.WSForretningsmessigUnntak();
    Code:
       0: aload_0
       1: invokespecial #1                  // Method java/lang/Object."<init>":()V
       4: return

  public java.lang.String getFeilkilde();
    Code:
       0: aload_0
       1: getfield      #2                  // Field feilkilde:Ljava/lang/String;
       4: areturn

  public void setFeilkilde(java.lang.String);
    Code:
       0: aload_0
       1: aload_1
       2: putfield      #2                  // Field feilkilde:Ljava/lang/String;
       5: return

  public java.lang.String getFeilaarsak();
    Code:
       0: aload_0
       1: getfield      #3                  // Field feilaarsak:Ljava/lang/String;
       4: areturn

  public void setFeilaarsak(java.lang.String);
    Code:
       0: aload_0
       1: aload_1
       2: putfield      #3                  // Field feilaarsak:Ljava/lang/String;
       5: return

  public java.lang.String getFeilmelding();
    Code:
       0: aload_0
       1: getfield      #4                  // Field feilmelding:Ljava/lang/String;
       4: areturn

  public void setFeilmelding(java.lang.String);
    Code:
       0: aload_0
       1: aload_1
       2: putfield      #4                  // Field feilmelding:Ljava/lang/String;
       5: return

  public javax.xml.datatype.XMLGregorianCalendar getTidspunkt();
    Code:
       0: aload_0
       1: getfield      #5                  // Field tidspunkt:Ljavax/xml/datatype/XMLGregorianCalendar;
       4: areturn

  public void setTidspunkt(javax.xml.datatype.XMLGregorianCalendar);
    Code:
       0: aload_0
       1: aload_1
       2: putfield      #5                  // Field tidspunkt:Ljavax/xml/datatype/XMLGregorianCalendar;
       5: return

  public no.nav.tjeneste.virksomhet.brukervarsel.v1.feil.WSForretningsmessigUnntak withFeilkilde(java.lang.String);
    Code:
       0: aload_0
       1: aload_1
       2: invokevirtual #6                  // Method setFeilkilde:(Ljava/lang/String;)V
       5: aload_0
       6: areturn

  public no.nav.tjeneste.virksomhet.brukervarsel.v1.feil.WSForretningsmessigUnntak withFeilaarsak(java.lang.String);
    Code:
       0: aload_0
       1: aload_1
       2: invokevirtual #7                  // Method setFeilaarsak:(Ljava/lang/String;)V
       5: aload_0
       6: areturn

  public no.nav.tjeneste.virksomhet.brukervarsel.v1.feil.WSForretningsmessigUnntak withFeilmelding(java.lang.String);
    Code:
       0: aload_0
       1: aload_1
       2: invokevirtual #8                  // Method setFeilmelding:(Ljava/lang/String;)V
       5: aload_0
       6: areturn

  public no.nav.tjeneste.virksomhet.brukervarsel.v1.feil.WSForretningsmessigUnntak withTidspunkt(javax.xml.datatype.XMLGregorianCalendar);
    Code:
       0: aload_0
       1: aload_1
       2: invokevirtual #9                  // Method setTidspunkt:(Ljavax/xml/datatype/XMLGregorianCalendar;)V
       5: aload_0
       6: areturn

  public int hashCode(org.jvnet.jaxb2_commons.locator.ObjectLocator, org.jvnet.jaxb2_commons.lang.HashCodeStrategy2);
    Code:
       0: iconst_1
       1: istore_3
       2: aload_0
       3: invokevirtual #10                 // Method getFeilkilde:()Ljava/lang/String;
       6: astore        4
       8: aload_2
       9: aload_1
      10: ldc           #11                 // String feilkilde
      12: aload         4
      14: invokestatic  #12                 // Method org/jvnet/jaxb2_commons/locator/util/LocatorUtils.property:(Lorg/jvnet/jaxb2_commons/locator/ObjectLocator;Ljava/lang/String;Ljava/lang/Object;)Lorg/jvnet/jaxb2_commons/locator/PropertyObjectLocator;
      17: iload_3
      18: aload         4
      20: aload_0
      21: getfield      #2                  // Field feilkilde:Ljava/lang/String;
      24: ifnull        31
      27: iconst_1
      28: goto          32
      31: iconst_0
      32: invokeinterface #13,  5           // InterfaceMethod org/jvnet/jaxb2_commons/lang/HashCodeStrategy2.hashCode:(Lorg/jvnet/jaxb2_commons/locator/ObjectLocator;ILjava/lang/Object;Z)I
      37: istore_3
      38: aload_0
      39: invokevirtual #14                 // Method getFeilaarsak:()Ljava/lang/String;
      42: astore        4
      44: aload_2
      45: aload_1
      46: ldc           #15                 // String feilaarsak
      48: aload         4
      50: invokestatic  #12                 // Method org/jvnet/jaxb2_commons/locator/util/LocatorUtils.property:(Lorg/jvnet/jaxb2_commons/locator/ObjectLocator;Ljava/lang/String;Ljava/lang/Object;)Lorg/jvnet/jaxb2_commons/locator/PropertyObjectLocator;
      53: iload_3
      54: aload         4
      56: aload_0
      57: getfield      #3                  // Field feilaarsak:Ljava/lang/String;
      60: ifnull        67
      63: iconst_1
      64: goto          68
      67: iconst_0
      68: invokeinterface #13,  5           // InterfaceMethod org/jvnet/jaxb2_commons/lang/HashCodeStrategy2.hashCode:(Lorg/jvnet/jaxb2_commons/locator/ObjectLocator;ILjava/lang/Object;Z)I
      73: istore_3
      74: aload_0
      75: invokevirtual #16                 // Method getFeilmelding:()Ljava/lang/String;
      78: astore        4
      80: aload_2
      81: aload_1
      82: ldc           #17                 // String feilmelding
      84: aload         4
      86: invokestatic  #12                 // Method org/jvnet/jaxb2_commons/locator/util/LocatorUtils.property:(Lorg/jvnet/jaxb2_commons/locator/ObjectLocator;Ljava/lang/String;Ljava/lang/Object;)Lorg/jvnet/jaxb2_commons/locator/PropertyObjectLocator;
      89: iload_3
      90: aload         4
      92: aload_0
      93: getfield      #4                  // Field feilmelding:Ljava/lang/String;
      96: ifnull        103
      99: iconst_1
     100: goto          104
     103: iconst_0
     104: invokeinterface #13,  5           // InterfaceMethod org/jvnet/jaxb2_commons/lang/HashCodeStrategy2.hashCode:(Lorg/jvnet/jaxb2_commons/locator/ObjectLocator;ILjava/lang/Object;Z)I
     109: istore_3
     110: aload_0
     111: invokevirtual #18                 // Method getTidspunkt:()Ljavax/xml/datatype/XMLGregorianCalendar;
     114: astore        4
     116: aload_2
     117: aload_1
     118: ldc           #19                 // String tidspunkt
     120: aload         4
     122: invokestatic  #12                 // Method org/jvnet/jaxb2_commons/locator/util/LocatorUtils.property:(Lorg/jvnet/jaxb2_commons/locator/ObjectLocator;Ljava/lang/String;Ljava/lang/Object;)Lorg/jvnet/jaxb2_commons/locator/PropertyObjectLocator;
     125: iload_3
     126: aload         4
     128: aload_0
     129: getfield      #5                  // Field tidspunkt:Ljavax/xml/datatype/XMLGregorianCalendar;
     132: ifnull        139
     135: iconst_1
     136: goto          140
     139: iconst_0
     140: invokeinterface #13,  5           // InterfaceMethod org/jvnet/jaxb2_commons/lang/HashCodeStrategy2.hashCode:(Lorg/jvnet/jaxb2_commons/locator/ObjectLocator;ILjava/lang/Object;Z)I
     145: istore_3
     146: iload_3
     147: ireturn

  public int hashCode();
    Code:
       0: getstatic     #20                 // Field org/jvnet/jaxb2_commons/lang/JAXBHashCodeStrategy.INSTANCE:Lorg/jvnet/jaxb2_commons/lang/JAXBHashCodeStrategy;
       3: astore_1
       4: aload_0
       5: aconst_null
       6: aload_1
       7: invokevirtual #21                 // Method hashCode:(Lorg/jvnet/jaxb2_commons/locator/ObjectLocator;Lorg/jvnet/jaxb2_commons/lang/HashCodeStrategy2;)I
      10: ireturn

  public boolean equals(org.jvnet.jaxb2_commons.locator.ObjectLocator, org.jvnet.jaxb2_commons.locator.ObjectLocator, java.lang.Object, org.jvnet.jaxb2_commons.lang.EqualsStrategy2);
    Code:
       0: aload_3
       1: ifnull        15
       4: aload_0
       5: invokevirtual #22                 // Method java/lang/Object.getClass:()Ljava/lang/Class;
       8: aload_3
       9: invokevirtual #22                 // Method java/lang/Object.getClass:()Ljava/lang/Class;
      12: if_acmpeq     17
      15: iconst_0
      16: ireturn
      17: aload_0
      18: aload_3
      19: if_acmpne     24
      22: iconst_1
      23: ireturn
      24: aload_3
      25: checkcast     #23                 // class no/nav/tjeneste/virksomhet/brukervarsel/v1/feil/WSForretningsmessigUnntak
      28: astore        5
      30: aload_0
      31: invokevirtual #10                 // Method getFeilkilde:()Ljava/lang/String;
      34: astore        6
      36: aload         5
      38: invokevirtual #10                 // Method getFeilkilde:()Ljava/lang/String;
      41: astore        7
      43: aload         4
      45: aload_1
      46: ldc           #11                 // String feilkilde
      48: aload         6
      50: invokestatic  #12                 // Method org/jvnet/jaxb2_commons/locator/util/LocatorUtils.property:(Lorg/jvnet/jaxb2_commons/locator/ObjectLocator;Ljava/lang/String;Ljava/lang/Object;)Lorg/jvnet/jaxb2_commons/locator/PropertyObjectLocator;
      53: aload_2
      54: ldc           #11                 // String feilkilde
      56: aload         7
      58: invokestatic  #12                 // Method org/jvnet/jaxb2_commons/locator/util/LocatorUtils.property:(Lorg/jvnet/jaxb2_commons/locator/ObjectLocator;Ljava/lang/String;Ljava/lang/Object;)Lorg/jvnet/jaxb2_commons/locator/PropertyObjectLocator;
      61: aload         6
      63: aload         7
      65: aload_0
      66: getfield      #2                  // Field feilkilde:Ljava/lang/String;
      69: ifnull        76
      72: iconst_1
      73: goto          77
      76: iconst_0
      77: aload         5
      79: getfield      #2                  // Field feilkilde:Ljava/lang/String;
      82: ifnull        89
      85: iconst_1
      86: goto          90
      89: iconst_0
      90: invokeinterface #24,  7           // InterfaceMethod org/jvnet/jaxb2_commons/lang/EqualsStrategy2.equals:(Lorg/jvnet/jaxb2_commons/locator/ObjectLocator;Lorg/jvnet/jaxb2_commons/locator/ObjectLocator;Ljava/lang/Object;Ljava/lang/Object;ZZ)Z
      95: ifne          100
      98: iconst_0
      99: ireturn
     100: aload_0
     101: invokevirtual #14                 // Method getFeilaarsak:()Ljava/lang/String;
     104: astore        6
     106: aload         5
     108: invokevirtual #14                 // Method getFeilaarsak:()Ljava/lang/String;
     111: astore        7
     113: aload         4
     115: aload_1
     116: ldc           #15                 // String feilaarsak
     118: aload         6
     120: invokestatic  #12                 // Method org/jvnet/jaxb2_commons/locator/util/LocatorUtils.property:(Lorg/jvnet/jaxb2_commons/locator/ObjectLocator;Ljava/lang/String;Ljava/lang/Object;)Lorg/jvnet/jaxb2_commons/locator/PropertyObjectLocator;
     123: aload_2
     124: ldc           #15                 // String feilaarsak
     126: aload         7
     128: invokestatic  #12                 // Method org/jvnet/jaxb2_commons/locator/util/LocatorUtils.property:(Lorg/jvnet/jaxb2_commons/locator/ObjectLocator;Ljava/lang/String;Ljava/lang/Object;)Lorg/jvnet/jaxb2_commons/locator/PropertyObjectLocator;
     131: aload         6
     133: aload         7
     135: aload_0
     136: getfield      #3                  // Field feilaarsak:Ljava/lang/String;
     139: ifnull        146
     142: iconst_1
     143: goto          147
     146: iconst_0
     147: aload         5
     149: getfield      #3                  // Field feilaarsak:Ljava/lang/String;
     152: ifnull        159
     155: iconst_1
     156: goto          160
     159: iconst_0
     160: invokeinterface #24,  7           // InterfaceMethod org/jvnet/jaxb2_commons/lang/EqualsStrategy2.equals:(Lorg/jvnet/jaxb2_commons/locator/ObjectLocator;Lorg/jvnet/jaxb2_commons/locator/ObjectLocator;Ljava/lang/Object;Ljava/lang/Object;ZZ)Z
     165: ifne          170
     168: iconst_0
     169: ireturn
     170: aload_0
     171: invokevirtual #16                 // Method getFeilmelding:()Ljava/lang/String;
     174: astore        6
     176: aload         5
     178: invokevirtual #16                 // Method getFeilmelding:()Ljava/lang/String;
     181: astore        7
     183: aload         4
     185: aload_1
     186: ldc           #17                 // String feilmelding
     188: aload         6
     190: invokestatic  #12                 // Method org/jvnet/jaxb2_commons/locator/util/LocatorUtils.property:(Lorg/jvnet/jaxb2_commons/locator/ObjectLocator;Ljava/lang/String;Ljava/lang/Object;)Lorg/jvnet/jaxb2_commons/locator/PropertyObjectLocator;
     193: aload_2
     194: ldc           #17                 // String feilmelding
     196: aload         7
     198: invokestatic  #12                 // Method org/jvnet/jaxb2_commons/locator/util/LocatorUtils.property:(Lorg/jvnet/jaxb2_commons/locator/ObjectLocator;Ljava/lang/String;Ljava/lang/Object;)Lorg/jvnet/jaxb2_commons/locator/PropertyObjectLocator;
     201: aload         6
     203: aload         7
     205: aload_0
     206: getfield      #4                  // Field feilmelding:Ljava/lang/String;
     209: ifnull        216
     212: iconst_1
     213: goto          217
     216: iconst_0
     217: aload         5
     219: getfield      #4                  // Field feilmelding:Ljava/lang/String;
     222: ifnull        229
     225: iconst_1
     226: goto          230
     229: iconst_0
     230: invokeinterface #24,  7           // InterfaceMethod org/jvnet/jaxb2_commons/lang/EqualsStrategy2.equals:(Lorg/jvnet/jaxb2_commons/locator/ObjectLocator;Lorg/jvnet/jaxb2_commons/locator/ObjectLocator;Ljava/lang/Object;Ljava/lang/Object;ZZ)Z
     235: ifne          240
     238: iconst_0
     239: ireturn
     240: aload_0
     241: invokevirtual #18                 // Method getTidspunkt:()Ljavax/xml/datatype/XMLGregorianCalendar;
     244: astore        6
     246: aload         5
     248: invokevirtual #18                 // Method getTidspunkt:()Ljavax/xml/datatype/XMLGregorianCalendar;
     251: astore        7
     253: aload         4
     255: aload_1
     256: ldc           #19                 // String tidspunkt
     258: aload         6
     260: invokestatic  #12                 // Method org/jvnet/jaxb2_commons/locator/util/LocatorUtils.property:(Lorg/jvnet/jaxb2_commons/locator/ObjectLocator;Ljava/lang/String;Ljava/lang/Object;)Lorg/jvnet/jaxb2_commons/locator/PropertyObjectLocator;
     263: aload_2
     264: ldc           #19                 // String tidspunkt
     266: aload         7
     268: invokestatic  #12                 // Method org/jvnet/jaxb2_commons/locator/util/LocatorUtils.property:(Lorg/jvnet/jaxb2_commons/locator/ObjectLocator;Ljava/lang/String;Ljava/lang/Object;)Lorg/jvnet/jaxb2_commons/locator/PropertyObjectLocator;
     271: aload         6
     273: aload         7
     275: aload_0
     276: getfield      #5                  // Field tidspunkt:Ljavax/xml/datatype/XMLGregorianCalendar;
     279: ifnull        286
     282: iconst_1
     283: goto          287
     286: iconst_0
     287: aload         5
     289: getfield      #5                  // Field tidspunkt:Ljavax/xml/datatype/XMLGregorianCalendar;
     292: ifnull        299
     295: iconst_1
     296: goto          300
     299: iconst_0
     300: invokeinterface #24,  7           // InterfaceMethod org/jvnet/jaxb2_commons/lang/EqualsStrategy2.equals:(Lorg/jvnet/jaxb2_commons/locator/ObjectLocator;Lorg/jvnet/jaxb2_commons/locator/ObjectLocator;Ljava/lang/Object;Ljava/lang/Object;ZZ)Z
     305: ifne          310
     308: iconst_0
     309: ireturn
     310: iconst_1
     311: ireturn

  public boolean equals(java.lang.Object);
    Code:
       0: getstatic     #25                 // Field org/jvnet/jaxb2_commons/lang/JAXBEqualsStrategy.INSTANCE:Lorg/jvnet/jaxb2_commons/lang/JAXBEqualsStrategy;
       3: astore_2
       4: aload_0
       5: aconst_null
       6: aconst_null
       7: aload_1
       8: aload_2
       9: invokevirtual #26                 // Method equals:(Lorg/jvnet/jaxb2_commons/locator/ObjectLocator;Lorg/jvnet/jaxb2_commons/locator/ObjectLocator;Ljava/lang/Object;Lorg/jvnet/jaxb2_commons/lang/EqualsStrategy2;)Z
      12: ireturn
}
