Compiled from "SQLAnonymizer.scala"
public final class wvlet.airframe.sql.analyzer.SQLAnonymizer$ implements wvlet.log.LoggingMethods,wvlet.log.LazyLogger,wvlet.log.LogSupport,java.io.Serializable {
  public static wvlet.log.Logger logger$lzy1;

  public long 0bitmap$1;

  public static final wvlet.airframe.sql.analyzer.SQLAnonymizer$ MODULE$;

  private wvlet.airframe.sql.analyzer.SQLAnonymizer$();
    Code:
       0: aload_0
       1: invokespecial #41                 // Method java/lang/Object."<init>":()V
       4: return

  public static {};
    Code:
       0: new           #2                  // class wvlet/airframe/sql/analyzer/SQLAnonymizer$
       3: dup
       4: invokespecial #44                 // Method "<init>":()V
       7: putstatic     #46                 // Field MODULE$:Lwvlet/airframe/sql/analyzer/SQLAnonymizer$;
      10: return

  public wvlet.log.Logger wvlet$log$LoggingMethods$$inline$logger();
    Code:
       0: aload_0
       1: invokestatic  #52                 // InterfaceMethod wvlet/log/LoggingMethods.wvlet$log$LoggingMethods$$inline$logger$:(Lwvlet/log/LoggingMethods;)Lwvlet/log/Logger;
       4: areturn

  public wvlet.log.LoggerMacros$ wvlet$log$LoggingMethods$$inline$LoggerMacros();
    Code:
       0: aload_0
       1: invokestatic  #58                 // InterfaceMethod wvlet/log/LoggingMethods.wvlet$log$LoggingMethods$$inline$LoggerMacros$:(Lwvlet/log/LoggingMethods;)Lwvlet/log/LoggerMacros$;
       4: areturn

  public wvlet.log.Logger logger();
    Code:
       0: getstatic     #66                 // Field scala/runtime/LazyVals$.MODULE$:Lscala/runtime/LazyVals$;
       3: aload_0
       4: getstatic     #69                 // Field wvlet/airframe/sql/analyzer/SQLAnonymizer.OFFSET$_m_0:J
       7: invokevirtual #73                 // Method scala/runtime/LazyVals$.get:(Ljava/lang/Object;J)J
      10: lstore_1
      11: getstatic     #66                 // Field scala/runtime/LazyVals$.MODULE$:Lscala/runtime/LazyVals$;
      14: lload_1
      15: iconst_0
      16: invokevirtual #77                 // Method scala/runtime/LazyVals$.STATE:(JI)J
      19: lstore_3
      20: lload_3
      21: ldc2_w        #78                 // long 3l
      24: lcmp
      25: ifne          32
      28: getstatic     #81                 // Field logger$lzy1:Lwvlet/log/Logger;
      31: areturn
      32: lload_3
      33: lconst_0
      34: lcmp
      35: ifne          110
      38: getstatic     #66                 // Field scala/runtime/LazyVals$.MODULE$:Lscala/runtime/LazyVals$;
      41: aload_0
      42: getstatic     #69                 // Field wvlet/airframe/sql/analyzer/SQLAnonymizer.OFFSET$_m_0:J
      45: lload_1
      46: iconst_1
      47: iconst_0
      48: invokevirtual #85                 // Method scala/runtime/LazyVals$.CAS:(Ljava/lang/Object;JJII)Z
      51: ifeq          107
      54: aload_0
      55: invokestatic  #89                 // InterfaceMethod wvlet/log/LazyLogger.logger$:(Lwvlet/log/LazyLogger;)Lwvlet/log/Logger;
      58: astore        5
      60: aload         5
      62: putstatic     #81                 // Field logger$lzy1:Lwvlet/log/Logger;
      65: getstatic     #66                 // Field scala/runtime/LazyVals$.MODULE$:Lscala/runtime/LazyVals$;
      68: aload_0
      69: getstatic     #69                 // Field wvlet/airframe/sql/analyzer/SQLAnonymizer.OFFSET$_m_0:J
      72: iconst_3
      73: iconst_0
      74: invokevirtual #93                 // Method scala/runtime/LazyVals$.setFlag:(Ljava/lang/Object;JII)V
      77: aload         5
      79: areturn
      80: nop
      81: nop
      82: athrow
      83: astore        6
      85: getstatic     #66                 // Field scala/runtime/LazyVals$.MODULE$:Lscala/runtime/LazyVals$;
      88: aload_0
      89: getstatic     #69                 // Field wvlet/airframe/sql/analyzer/SQLAnonymizer.OFFSET$_m_0:J
      92: iconst_0
      93: iconst_0
      94: invokevirtual #93                 // Method scala/runtime/LazyVals$.setFlag:(Ljava/lang/Object;JII)V
      97: aload         6
      99: athrow
     100: nop
     101: nop
     102: athrow
     103: athrow
     104: nop
     105: nop
     106: athrow
     107: goto          0
     110: getstatic     #66                 // Field scala/runtime/LazyVals$.MODULE$:Lscala/runtime/LazyVals$;
     113: aload_0
     114: getstatic     #69                 // Field wvlet/airframe/sql/analyzer/SQLAnonymizer.OFFSET$_m_0:J
     117: lload_1
     118: iconst_0
     119: invokevirtual #97                 // Method scala/runtime/LazyVals$.wait4Notification:(Ljava/lang/Object;JJI)V
     122: goto          0
    Exception table:
       from    to  target type
          54    80    83   Class java/lang/Throwable

  private java.lang.Object writeReplace();
    Code:
       0: new           #101                // class scala/runtime/ModuleSerializationProxy
       3: dup
       4: ldc           #2                  // class wvlet/airframe/sql/analyzer/SQLAnonymizer$
       6: invokespecial #104                // Method scala/runtime/ModuleSerializationProxy."<init>":(Ljava/lang/Class;)V
       9: areturn

  public java.lang.String anonymize(java.lang.String);
    Code:
       0: getstatic     #112                // Field wvlet/airframe/sql/parser/SQLParser$.MODULE$:Lwvlet/airframe/sql/parser/SQLParser$;
       3: aload_1
       4: invokevirtual #116                // Method wvlet/airframe/sql/parser/SQLParser$.parse:(Ljava/lang/String;)Lwvlet/airframe/sql/model/LogicalPlan;
       7: astore_2
       8: new           #17                 // class wvlet/airframe/sql/analyzer/SQLAnonymizer$DictBuilder
      11: dup
      12: invokespecial #117                // Method wvlet/airframe/sql/analyzer/SQLAnonymizer$DictBuilder."<init>":()V
      15: aload_2
      16: invokevirtual #121                // Method wvlet/airframe/sql/analyzer/SQLAnonymizer$DictBuilder.add:(Lwvlet/airframe/sql/model/LogicalPlan;)Lwvlet/airframe/sql/analyzer/SQLAnonymizer$DictBuilder;
      19: invokevirtual #125                // Method wvlet/airframe/sql/analyzer/SQLAnonymizer$DictBuilder.build:()Lscala/collection/immutable/Map;
      22: astore_3
      23: aload_0
      24: aload_2
      25: aload_3
      26: invokevirtual #128                // Method anonymize:(Lwvlet/airframe/sql/model/LogicalPlan;Lscala/collection/immutable/Map;)Lwvlet/airframe/sql/model/LogicalPlan;
      29: astore        4
      31: getstatic     #133                // Field wvlet/airframe/sql/parser/SQLGenerator$.MODULE$:Lwvlet/airframe/sql/parser/SQLGenerator$;
      34: aload         4
      36: invokevirtual #137                // Method wvlet/airframe/sql/parser/SQLGenerator$.print:(Lwvlet/airframe/sql/model/LogicalPlan;)Ljava/lang/String;
      39: areturn

  public wvlet.airframe.sql.model.LogicalPlan anonymize(wvlet.airframe.sql.model.LogicalPlan, scala.collection.immutable.Map<wvlet.airframe.sql.model.Expression, wvlet.airframe.sql.model.Expression>);
    Code:
       0: new           #15                 // class wvlet/airframe/sql/analyzer/SQLAnonymizer$$anon$2
       3: dup
       4: aload_2
       5: invokespecial #147                // Method wvlet/airframe/sql/analyzer/SQLAnonymizer$$anon$2."<init>":(Lscala/collection/immutable/Map;)V
       8: astore_3
       9: aload_1
      10: aload_3
      11: invokeinterface #153,  2          // InterfaceMethod wvlet/airframe/sql/model/LogicalPlan.transformExpressions:(Lscala/PartialFunction;)Lwvlet/airframe/sql/model/LogicalPlan;
      16: areturn

  public scala.collection.immutable.Map<wvlet.airframe.sql.model.Expression, wvlet.airframe.sql.model.Expression> buildAnonymizationDictionary(scala.collection.immutable.Seq<java.lang.String>);
    Code:
       0: aload_0
       1: astore_2
       2: aload_2
       3: invokevirtual #160                // Method wvlet$log$LoggingMethods$$inline$logger:()Lwvlet/log/Logger;
       6: getstatic     #163                // Field wvlet/log/LogLevel$DEBUG$.MODULE$:Lwvlet/log/LogLevel$DEBUG$;
       9: invokevirtual #169                // Method wvlet/log/Logger.isEnabled:(Lwvlet/log/LogLevel;)Z
      12: ifeq          41
      15: aload_2
      16: invokevirtual #160                // Method wvlet$log$LoggingMethods$$inline$logger:()Lwvlet/log/Logger;
      19: getstatic     #163                // Field wvlet/log/LogLevel$DEBUG$.MODULE$:Lwvlet/log/LogLevel$DEBUG$;
      22: getstatic     #174                // Field wvlet/log/LogSource$.MODULE$:Lwvlet/log/LogSource$;
      25: ldc           #176                // String
      27: ldc           #177                // String SQLAnonymizer.scala
      29: bipush        55
      31: bipush        40
      33: invokevirtual #181                // Method wvlet/log/LogSource$.apply:(Ljava/lang/String;Ljava/lang/String;II)Lwvlet/log/LogSource;
      36: ldc           #183                // String Building a token dictionary
      38: invokevirtual #187                // Method wvlet/log/Logger.log:(Lwvlet/log/LogLevel;Lwvlet/log/LogSource;Ljava/lang/Object;)V
      41: new           #17                 // class wvlet/airframe/sql/analyzer/SQLAnonymizer$DictBuilder
      44: dup
      45: invokespecial #117                // Method wvlet/airframe/sql/analyzer/SQLAnonymizer$DictBuilder."<init>":()V
      48: astore_3
      49: aload_1
      50: aload_0
      51: aload_3
      52: invokedynamic #208,  0            // InvokeDynamic #0:apply:(Lwvlet/airframe/sql/analyzer/SQLAnonymizer$;Lwvlet/airframe/sql/analyzer/SQLAnonymizer$DictBuilder;)Lscala/Function1;
      57: invokeinterface #214,  2          // InterfaceMethod scala/collection/immutable/Seq.foreach:(Lscala/Function1;)V
      62: aload_3
      63: invokevirtual #125                // Method wvlet/airframe/sql/analyzer/SQLAnonymizer$DictBuilder.build:()Lscala/collection/immutable/Map;
      66: areturn

  private final java.lang.Object buildAnonymizationDictionary$$anonfun$1(wvlet.airframe.sql.analyzer.SQLAnonymizer$DictBuilder, java.lang.String);
    Code:
       0: getstatic     #112                // Field wvlet/airframe/sql/parser/SQLParser$.MODULE$:Lwvlet/airframe/sql/parser/SQLParser$;
       3: aload_2
       4: invokevirtual #116                // Method wvlet/airframe/sql/parser/SQLParser$.parse:(Ljava/lang/String;)Lwvlet/airframe/sql/model/LogicalPlan;
       7: astore_3
       8: aload_1
       9: aload_3
      10: invokevirtual #121                // Method wvlet/airframe/sql/analyzer/SQLAnonymizer$DictBuilder.add:(Lwvlet/airframe/sql/model/LogicalPlan;)Lwvlet/airframe/sql/analyzer/SQLAnonymizer$DictBuilder;
      13: goto          68
      16: astore        4
      18: aload_0
      19: astore        5
      21: aload         5
      23: invokevirtual #160                // Method wvlet$log$LoggingMethods$$inline$logger:()Lwvlet/log/Logger;
      26: getstatic     #225                // Field wvlet/log/LogLevel$WARN$.MODULE$:Lwvlet/log/LogLevel$WARN$;
      29: invokevirtual #169                // Method wvlet/log/Logger.isEnabled:(Lwvlet/log/LogLevel;)Z
      32: ifeq          62
      35: aload         5
      37: invokevirtual #160                // Method wvlet$log$LoggingMethods$$inline$logger:()Lwvlet/log/Logger;
      40: getstatic     #225                // Field wvlet/log/LogLevel$WARN$.MODULE$:Lwvlet/log/LogLevel$WARN$;
      43: getstatic     #174                // Field wvlet/log/LogSource$.MODULE$:Lwvlet/log/LogSource$;
      46: ldc           #176                // String
      48: ldc           #177                // String SQLAnonymizer.scala
      50: bipush        63
      52: bipush        17
      54: invokevirtual #181                // Method wvlet/log/LogSource$.apply:(Ljava/lang/String;Ljava/lang/String;II)Lwvlet/log/LogSource;
      57: aload         4
      59: invokevirtual #187                // Method wvlet/log/Logger.log:(Lwvlet/log/LogLevel;Lwvlet/log/LogSource;Ljava/lang/Object;)V
      62: getstatic     #231                // Field scala/runtime/BoxedUnit.UNIT:Lscala/runtime/BoxedUnit;
      65: goto          68
      68: areturn
    Exception table:
       from    to  target type
           0    13    16   Class java/lang/Exception

  public static final java.lang.String wvlet$airframe$sql$analyzer$SQLAnonymizer$DictBuilder$$anon$3$$_$applyOrElse$$anonfun$1(wvlet.airframe.sql.analyzer.SQLAnonymizer$SymbolTable, java.lang.String);
    Code:
       0: aload_0
       1: aload_1
       2: invokevirtual #242                // Method wvlet/airframe/sql/analyzer/SQLAnonymizer$SymbolTable.lookup:(Ljava/lang/String;)Ljava/lang/String;
       5: areturn

  public static final java.lang.String wvlet$airframe$sql$analyzer$SQLAnonymizer$DictBuilder$$anon$3$$_$_$$anonfun$1(wvlet.airframe.sql.analyzer.SQLAnonymizer$SymbolTable, java.lang.String);
    Code:
       0: aload_0
       1: aload_1
       2: invokevirtual #242                // Method wvlet/airframe/sql/analyzer/SQLAnonymizer$SymbolTable.lookup:(Ljava/lang/String;)Ljava/lang/String;
       5: areturn

  private static java.lang.Object $deserializeLambda$(java.lang.invoke.SerializedLambda);
    Code:
       0: aload_0
       1: invokedynamic #257,  0            // InvokeDynamic #1:lambdaDeserialize:(Ljava/lang/invoke/SerializedLambda;)Ljava/lang/Object;
       6: areturn
}
