Compiled from "ReadOnlyBooleanProperty.java"
class javafx.beans.property.ReadOnlyBooleanProperty$2 extends javafx.beans.property.ReadOnlyObjectPropertyBase<java.lang.Boolean> {
  private boolean valid;

  private final javafx.beans.InvalidationListener listener;

  final javafx.beans.property.ReadOnlyBooleanProperty this$0;

  javafx.beans.property.ReadOnlyBooleanProperty$2(javafx.beans.property.ReadOnlyBooleanProperty);
    Code:
       0: aload_0
       1: aload_1
       2: putfield      #1                  // Field this$0:Ljavafx/beans/property/ReadOnlyBooleanProperty;
       5: aload_0
       6: invokespecial #2                  // Method javafx/beans/property/ReadOnlyObjectPropertyBase."<init>":()V
       9: aload_0
      10: iconst_1
      11: putfield      #3                  // Field valid:Z
      14: aload_0
      15: aload_0
      16: invokedynamic #4,  0              // InvokeDynamic #0:invalidated:(Ljavafx/beans/property/ReadOnlyBooleanProperty$2;)Ljavafx/beans/InvalidationListener;
      21: putfield      #5                  // Field listener:Ljavafx/beans/InvalidationListener;
      24: aload_0
      25: getfield      #1                  // Field this$0:Ljavafx/beans/property/ReadOnlyBooleanProperty;
      28: new           #6                  // class javafx/beans/WeakInvalidationListener
      31: dup
      32: aload_0
      33: getfield      #5                  // Field listener:Ljavafx/beans/InvalidationListener;
      36: invokespecial #7                  // Method javafx/beans/WeakInvalidationListener."<init>":(Ljavafx/beans/InvalidationListener;)V
      39: invokevirtual #8                  // Method javafx/beans/property/ReadOnlyBooleanProperty.addListener:(Ljavafx/beans/InvalidationListener;)V
      42: return

  public java.lang.Object getBean();
    Code:
       0: aconst_null
       1: areturn

  public java.lang.String getName();
    Code:
       0: aload_0
       1: getfield      #1                  // Field this$0:Ljavafx/beans/property/ReadOnlyBooleanProperty;
       4: invokevirtual #9                  // Method javafx/beans/property/ReadOnlyBooleanProperty.getName:()Ljava/lang/String;
       7: areturn

  public java.lang.Boolean get();
    Code:
       0: aload_0
       1: iconst_1
       2: putfield      #3                  // Field valid:Z
       5: aload_0
       6: getfield      #1                  // Field this$0:Ljavafx/beans/property/ReadOnlyBooleanProperty;
       9: invokevirtual #10                 // Method javafx/beans/property/ReadOnlyBooleanProperty.getValue:()Ljava/lang/Boolean;
      12: areturn

  public java.lang.Object get();
    Code:
       0: aload_0
       1: invokevirtual #11                 // Method get:()Ljava/lang/Boolean;
       4: areturn

  private void lambda$$0(javafx.beans.Observable);
    Code:
       0: aload_0
       1: getfield      #3                  // Field valid:Z
       4: ifeq          16
       7: aload_0
       8: iconst_0
       9: putfield      #3                  // Field valid:Z
      12: aload_0
      13: invokevirtual #12                 // Method fireValueChangedEvent:()V
      16: return
}
