Compiled from "ReadOnlyListPropertyBase.java"
public abstract class javafx.beans.property.ReadOnlyListPropertyBase<E> extends javafx.beans.property.ReadOnlyListProperty<E> {
  private com.sun.javafx.binding.ListExpressionHelper<E> helper;

  public javafx.beans.property.ReadOnlyListPropertyBase();
    Code:
       0: aload_0
       1: invokespecial #1                  // Method javafx/beans/property/ReadOnlyListProperty."<init>":()V
       4: return

  public void addListener(javafx.beans.InvalidationListener);
    Code:
       0: aload_0
       1: aload_0
       2: getfield      #2                  // Field helper:Lcom/sun/javafx/binding/ListExpressionHelper;
       5: aload_0
       6: aload_1
       7: invokestatic  #3                  // Method com/sun/javafx/binding/ListExpressionHelper.addListener:(Lcom/sun/javafx/binding/ListExpressionHelper;Ljavafx/beans/value/ObservableListValue;Ljavafx/beans/InvalidationListener;)Lcom/sun/javafx/binding/ListExpressionHelper;
      10: putfield      #2                  // Field helper:Lcom/sun/javafx/binding/ListExpressionHelper;
      13: return

  public void removeListener(javafx.beans.InvalidationListener);
    Code:
       0: aload_0
       1: aload_0
       2: getfield      #2                  // Field helper:Lcom/sun/javafx/binding/ListExpressionHelper;
       5: aload_1
       6: invokestatic  #4                  // Method com/sun/javafx/binding/ListExpressionHelper.removeListener:(Lcom/sun/javafx/binding/ListExpressionHelper;Ljavafx/beans/InvalidationListener;)Lcom/sun/javafx/binding/ListExpressionHelper;
       9: putfield      #2                  // Field helper:Lcom/sun/javafx/binding/ListExpressionHelper;
      12: return

  public void addListener(javafx.beans.value.ChangeListener<? super javafx.collections.ObservableList<E>>);
    Code:
       0: aload_0
       1: aload_0
       2: getfield      #2                  // Field helper:Lcom/sun/javafx/binding/ListExpressionHelper;
       5: aload_0
       6: aload_1
       7: invokestatic  #5                  // Method com/sun/javafx/binding/ListExpressionHelper.addListener:(Lcom/sun/javafx/binding/ListExpressionHelper;Ljavafx/beans/value/ObservableListValue;Ljavafx/beans/value/ChangeListener;)Lcom/sun/javafx/binding/ListExpressionHelper;
      10: putfield      #2                  // Field helper:Lcom/sun/javafx/binding/ListExpressionHelper;
      13: return

  public void removeListener(javafx.beans.value.ChangeListener<? super javafx.collections.ObservableList<E>>);
    Code:
       0: aload_0
       1: aload_0
       2: getfield      #2                  // Field helper:Lcom/sun/javafx/binding/ListExpressionHelper;
       5: aload_1
       6: invokestatic  #6                  // Method com/sun/javafx/binding/ListExpressionHelper.removeListener:(Lcom/sun/javafx/binding/ListExpressionHelper;Ljavafx/beans/value/ChangeListener;)Lcom/sun/javafx/binding/ListExpressionHelper;
       9: putfield      #2                  // Field helper:Lcom/sun/javafx/binding/ListExpressionHelper;
      12: return

  public void addListener(javafx.collections.ListChangeListener<? super E>);
    Code:
       0: aload_0
       1: aload_0
       2: getfield      #2                  // Field helper:Lcom/sun/javafx/binding/ListExpressionHelper;
       5: aload_0
       6: aload_1
       7: invokestatic  #7                  // Method com/sun/javafx/binding/ListExpressionHelper.addListener:(Lcom/sun/javafx/binding/ListExpressionHelper;Ljavafx/beans/value/ObservableListValue;Ljavafx/collections/ListChangeListener;)Lcom/sun/javafx/binding/ListExpressionHelper;
      10: putfield      #2                  // Field helper:Lcom/sun/javafx/binding/ListExpressionHelper;
      13: return

  public void removeListener(javafx.collections.ListChangeListener<? super E>);
    Code:
       0: aload_0
       1: aload_0
       2: getfield      #2                  // Field helper:Lcom/sun/javafx/binding/ListExpressionHelper;
       5: aload_1
       6: invokestatic  #8                  // Method com/sun/javafx/binding/ListExpressionHelper.removeListener:(Lcom/sun/javafx/binding/ListExpressionHelper;Ljavafx/collections/ListChangeListener;)Lcom/sun/javafx/binding/ListExpressionHelper;
       9: putfield      #2                  // Field helper:Lcom/sun/javafx/binding/ListExpressionHelper;
      12: return

  protected void fireValueChangedEvent();
    Code:
       0: aload_0
       1: getfield      #2                  // Field helper:Lcom/sun/javafx/binding/ListExpressionHelper;
       4: invokestatic  #9                  // Method com/sun/javafx/binding/ListExpressionHelper.fireValueChangedEvent:(Lcom/sun/javafx/binding/ListExpressionHelper;)V
       7: return

  protected void fireValueChangedEvent(javafx.collections.ListChangeListener$Change<? extends E>);
    Code:
       0: aload_0
       1: getfield      #2                  // Field helper:Lcom/sun/javafx/binding/ListExpressionHelper;
       4: aload_1
       5: invokestatic  #10                 // Method com/sun/javafx/binding/ListExpressionHelper.fireValueChangedEvent:(Lcom/sun/javafx/binding/ListExpressionHelper;Ljavafx/collections/ListChangeListener$Change;)V
       8: return
}
