Compiled from "ReadOnlyObjectWrapper.java"
public class javafx.beans.property.ReadOnlyObjectWrapper<T> extends javafx.beans.property.SimpleObjectProperty<T> {
  private javafx.beans.property.ReadOnlyObjectWrapper<T>.ReadOnlyPropertyImpl readOnlyProperty;

  public javafx.beans.property.ReadOnlyObjectWrapper();
    Code:
       0: aload_0
       1: invokespecial #1                  // Method javafx/beans/property/SimpleObjectProperty."<init>":()V
       4: return

  public javafx.beans.property.ReadOnlyObjectWrapper(T);
    Code:
       0: aload_0
       1: aload_1
       2: invokespecial #2                  // Method javafx/beans/property/SimpleObjectProperty."<init>":(Ljava/lang/Object;)V
       5: return

  public javafx.beans.property.ReadOnlyObjectWrapper(java.lang.Object, java.lang.String);
    Code:
       0: aload_0
       1: aload_1
       2: aload_2
       3: invokespecial #3                  // Method javafx/beans/property/SimpleObjectProperty."<init>":(Ljava/lang/Object;Ljava/lang/String;)V
       6: return

  public javafx.beans.property.ReadOnlyObjectWrapper(java.lang.Object, java.lang.String, T);
    Code:
       0: aload_0
       1: aload_1
       2: aload_2
       3: aload_3
       4: invokespecial #4                  // Method javafx/beans/property/SimpleObjectProperty."<init>":(Ljava/lang/Object;Ljava/lang/String;Ljava/lang/Object;)V
       7: return

  public javafx.beans.property.ReadOnlyObjectProperty<T> getReadOnlyProperty();
    Code:
       0: aload_0
       1: getfield      #5                  // Field readOnlyProperty:Ljavafx/beans/property/ReadOnlyObjectWrapper$ReadOnlyPropertyImpl;
       4: ifnonnull     20
       7: aload_0
       8: new           #6                  // class javafx/beans/property/ReadOnlyObjectWrapper$ReadOnlyPropertyImpl
      11: dup
      12: aload_0
      13: aconst_null
      14: invokespecial #7                  // Method javafx/beans/property/ReadOnlyObjectWrapper$ReadOnlyPropertyImpl."<init>":(Ljavafx/beans/property/ReadOnlyObjectWrapper;Ljavafx/beans/property/ReadOnlyObjectWrapper$1;)V
      17: putfield      #5                  // Field readOnlyProperty:Ljavafx/beans/property/ReadOnlyObjectWrapper$ReadOnlyPropertyImpl;
      20: aload_0
      21: getfield      #5                  // Field readOnlyProperty:Ljavafx/beans/property/ReadOnlyObjectWrapper$ReadOnlyPropertyImpl;
      24: areturn

  protected void fireValueChangedEvent();
    Code:
       0: aload_0
       1: invokespecial #8                  // Method javafx/beans/property/SimpleObjectProperty.fireValueChangedEvent:()V
       4: aload_0
       5: getfield      #5                  // Field readOnlyProperty:Ljavafx/beans/property/ReadOnlyObjectWrapper$ReadOnlyPropertyImpl;
       8: ifnull        18
      11: aload_0
      12: getfield      #5                  // Field readOnlyProperty:Ljavafx/beans/property/ReadOnlyObjectWrapper$ReadOnlyPropertyImpl;
      15: invokevirtual #9                  // Method javafx/beans/property/ReadOnlyObjectWrapper$ReadOnlyPropertyImpl.fireValueChangedEvent:()V
      18: return
}
