Compiled from "CookieBufferingFilter.java"
class net.shibboleth.utilities.java.support.net.CookieBufferingFilter$CookieBufferingHttpServletResponseProxy extends javax.servlet.http.HttpServletResponseWrapper {
  private java.util.Map<java.lang.String, javax.servlet.http.Cookie> cookieMap;

  final net.shibboleth.utilities.java.support.net.CookieBufferingFilter this$0;

  public net.shibboleth.utilities.java.support.net.CookieBufferingFilter$CookieBufferingHttpServletResponseProxy(net.shibboleth.utilities.java.support.net.CookieBufferingFilter, javax.servlet.http.HttpServletResponse);
    Code:
       0: aload_0
       1: aload_1
       2: putfield      #1                  // Field this$0:Lnet/shibboleth/utilities/java/support/net/CookieBufferingFilter;
       5: aload_0
       6: aload_2
       7: invokespecial #2                  // Method javax/servlet/http/HttpServletResponseWrapper."<init>":(Ljavax/servlet/http/HttpServletResponse;)V
      10: aload_0
      11: new           #3                  // class java/util/HashMap
      14: dup
      15: invokespecial #4                  // Method java/util/HashMap."<init>":()V
      18: putfield      #5                  // Field cookieMap:Ljava/util/Map;
      21: return

  public void addCookie(javax.servlet.http.Cookie);
    Code:
       0: aload_0
       1: getfield      #5                  // Field cookieMap:Ljava/util/Map;
       4: aload_1
       5: invokevirtual #6                  // Method javax/servlet/http/Cookie.getName:()Ljava/lang/String;
       8: aload_1
       9: invokeinterface #7,  3            // InterfaceMethod java/util/Map.put:(Ljava/lang/Object;Ljava/lang/Object;)Ljava/lang/Object;
      14: pop
      15: return

  protected java.util.Map<java.lang.String, javax.servlet.http.Cookie> getCookies();
    Code:
       0: aload_0
       1: getfield      #5                  // Field cookieMap:Ljava/util/Map;
       4: areturn

  public javax.servlet.ServletOutputStream getOutputStream() throws java.io.IOException;
    Code:
       0: aload_0
       1: invokevirtual #8                  // Method dumpCookies:()V
       4: aload_0
       5: invokespecial #9                  // Method javax/servlet/http/HttpServletResponseWrapper.getOutputStream:()Ljavax/servlet/ServletOutputStream;
       8: areturn

  public java.io.PrintWriter getWriter() throws java.io.IOException;
    Code:
       0: aload_0
       1: invokevirtual #8                  // Method dumpCookies:()V
       4: aload_0
       5: invokespecial #10                 // Method javax/servlet/http/HttpServletResponseWrapper.getWriter:()Ljava/io/PrintWriter;
       8: areturn

  public void sendError(int, java.lang.String) throws java.io.IOException;
    Code:
       0: aload_0
       1: invokevirtual #8                  // Method dumpCookies:()V
       4: aload_0
       5: iload_1
       6: aload_2
       7: invokespecial #11                 // Method javax/servlet/http/HttpServletResponseWrapper.sendError:(ILjava/lang/String;)V
      10: return

  public void sendError(int) throws java.io.IOException;
    Code:
       0: aload_0
       1: invokevirtual #8                  // Method dumpCookies:()V
       4: aload_0
       5: iload_1
       6: invokespecial #12                 // Method javax/servlet/http/HttpServletResponseWrapper.sendError:(I)V
       9: return

  public void sendRedirect(java.lang.String) throws java.io.IOException;
    Code:
       0: aload_0
       1: invokevirtual #8                  // Method dumpCookies:()V
       4: aload_0
       5: aload_1
       6: invokespecial #13                 // Method javax/servlet/http/HttpServletResponseWrapper.sendRedirect:(Ljava/lang/String;)V
       9: return

  protected void dumpCookies();
    Code:
       0: aload_0
       1: getfield      #5                  // Field cookieMap:Ljava/util/Map;
       4: invokeinterface #14,  1           // InterfaceMethod java/util/Map.values:()Ljava/util/Collection;
       9: invokeinterface #15,  1           // InterfaceMethod java/util/Collection.iterator:()Ljava/util/Iterator;
      14: astore_1
      15: aload_1
      16: invokeinterface #16,  1           // InterfaceMethod java/util/Iterator.hasNext:()Z
      21: ifeq          50
      24: aload_1
      25: invokeinterface #17,  1           // InterfaceMethod java/util/Iterator.next:()Ljava/lang/Object;
      30: checkcast     #18                 // class javax/servlet/http/Cookie
      33: astore_2
      34: aload_0
      35: invokevirtual #19                 // Method getResponse:()Ljavax/servlet/ServletResponse;
      38: checkcast     #20                 // class javax/servlet/http/HttpServletResponse
      41: aload_2
      42: invokeinterface #21,  2           // InterfaceMethod javax/servlet/http/HttpServletResponse.addCookie:(Ljavax/servlet/http/Cookie;)V
      47: goto          15
      50: aload_0
      51: getfield      #5                  // Field cookieMap:Ljava/util/Map;
      54: invokeinterface #22,  1           // InterfaceMethod java/util/Map.clear:()V
      59: return
}
