Compiled from "PickerResultJavascriptSubject.java"
public class edu.internet2.middleware.grouper.grouperUi.beans.subjectPicker.PickerResultJavascriptSubject implements java.io.Serializable {
  private edu.internet2.middleware.grouper.grouperUi.beans.subjectPicker.SubjectPickerJavascriptBean subject;

  private int index;

  private java.lang.String screenLabel;

  public int getIndex();
    Code:
       0: aload_0
       1: getfield      #1                  // Field index:I
       4: ireturn

  public void setIndex(int);
    Code:
       0: aload_0
       1: iload_1
       2: putfield      #1                  // Field index:I
       5: return

  public edu.internet2.middleware.grouper.grouperUi.beans.subjectPicker.PickerResultJavascriptSubject(edu.internet2.middleware.grouper.grouperUi.beans.subjectPicker.SubjectPickerJavascriptBean);
    Code:
       0: aload_0
       1: invokespecial #2                  // Method java/lang/Object."<init>":()V
       4: aload_0
       5: iconst_0
       6: putfield      #1                  // Field index:I
       9: aload_0
      10: aload_1
      11: putfield      #3                  // Field subject:Ledu/internet2/middleware/grouper/grouperUi/beans/subjectPicker/SubjectPickerJavascriptBean;
      14: aload_0
      15: aconst_null
      16: putfield      #4                  // Field screenLabel:Ljava/lang/String;
      19: return

  public java.lang.String getScreenLabel();
    Code:
       0: aload_0
       1: getfield      #4                  // Field screenLabel:Ljava/lang/String;
       4: areturn

  public java.lang.String getSubjectId();
    Code:
       0: aload_0
       1: getfield      #3                  // Field subject:Ledu/internet2/middleware/grouper/grouperUi/beans/subjectPicker/SubjectPickerJavascriptBean;
       4: invokevirtual #5                  // Method edu/internet2/middleware/grouper/grouperUi/beans/subjectPicker/SubjectPickerJavascriptBean.getId:()Ljava/lang/String;
       7: astore_1
       8: aload_1
       9: areturn

  public edu.internet2.middleware.grouper.grouperUi.beans.subjectPicker.SubjectPickerJavascriptBean getSubject();
    Code:
       0: aload_0
       1: getfield      #3                  // Field subject:Ledu/internet2/middleware/grouper/grouperUi/beans/subjectPicker/SubjectPickerJavascriptBean;
       4: areturn
}
