Compiled from "DaemonSetStatusBuilder.java"
public class io.dekorate.deps.kubernetes.api.model.apps.DaemonSetStatusBuilder extends io.dekorate.deps.kubernetes.api.model.apps.DaemonSetStatusFluentImpl<io.dekorate.deps.kubernetes.api.model.apps.DaemonSetStatusBuilder> implements io.dekorate.deps.kubernetes.api.builder.VisitableBuilder<io.dekorate.deps.kubernetes.api.model.apps.DaemonSetStatus, io.dekorate.deps.kubernetes.api.model.apps.DaemonSetStatusBuilder> {
  io.dekorate.deps.kubernetes.api.model.apps.DaemonSetStatusFluent<?> fluent;

  java.lang.Boolean validationEnabled;

  public io.dekorate.deps.kubernetes.api.model.apps.DaemonSetStatusBuilder();
    Code:
       0: aload_0
       1: iconst_1
       2: invokestatic  #21                 // Method java/lang/Boolean.valueOf:(Z)Ljava/lang/Boolean;
       5: invokespecial #24                 // Method "<init>":(Ljava/lang/Boolean;)V
       8: return

  public io.dekorate.deps.kubernetes.api.model.apps.DaemonSetStatusBuilder(java.lang.Boolean);
    Code:
       0: aload_0
       1: new           #28                 // class io/dekorate/deps/kubernetes/api/model/apps/DaemonSetStatus
       4: dup
       5: invokespecial #30                 // Method io/dekorate/deps/kubernetes/api/model/apps/DaemonSetStatus."<init>":()V
       8: aload_1
       9: invokespecial #33                 // Method "<init>":(Lio/dekorate/deps/kubernetes/api/model/apps/DaemonSetStatus;Ljava/lang/Boolean;)V
      12: return

  public io.dekorate.deps.kubernetes.api.model.apps.DaemonSetStatusBuilder(io.dekorate.deps.kubernetes.api.model.apps.DaemonSetStatusFluent<?>);
    Code:
       0: aload_0
       1: aload_1
       2: iconst_1
       3: invokestatic  #21                 // Method java/lang/Boolean.valueOf:(Z)Ljava/lang/Boolean;
       6: invokespecial #38                 // Method "<init>":(Lio/dekorate/deps/kubernetes/api/model/apps/DaemonSetStatusFluent;Ljava/lang/Boolean;)V
       9: return

  public io.dekorate.deps.kubernetes.api.model.apps.DaemonSetStatusBuilder(io.dekorate.deps.kubernetes.api.model.apps.DaemonSetStatusFluent<?>, java.lang.Boolean);
    Code:
       0: aload_0
       1: aload_1
       2: new           #28                 // class io/dekorate/deps/kubernetes/api/model/apps/DaemonSetStatus
       5: dup
       6: invokespecial #30                 // Method io/dekorate/deps/kubernetes/api/model/apps/DaemonSetStatus."<init>":()V
       9: aload_2
      10: invokespecial #42                 // Method "<init>":(Lio/dekorate/deps/kubernetes/api/model/apps/DaemonSetStatusFluent;Lio/dekorate/deps/kubernetes/api/model/apps/DaemonSetStatus;Ljava/lang/Boolean;)V
      13: return

  public io.dekorate.deps.kubernetes.api.model.apps.DaemonSetStatusBuilder(io.dekorate.deps.kubernetes.api.model.apps.DaemonSetStatusFluent<?>, io.dekorate.deps.kubernetes.api.model.apps.DaemonSetStatus);
    Code:
       0: aload_0
       1: aload_1
       2: aload_2
       3: iconst_1
       4: invokestatic  #21                 // Method java/lang/Boolean.valueOf:(Z)Ljava/lang/Boolean;
       7: invokespecial #42                 // Method "<init>":(Lio/dekorate/deps/kubernetes/api/model/apps/DaemonSetStatusFluent;Lio/dekorate/deps/kubernetes/api/model/apps/DaemonSetStatus;Ljava/lang/Boolean;)V
      10: return

  public io.dekorate.deps.kubernetes.api.model.apps.DaemonSetStatusBuilder(io.dekorate.deps.kubernetes.api.model.apps.DaemonSetStatusFluent<?>, io.dekorate.deps.kubernetes.api.model.apps.DaemonSetStatus, java.lang.Boolean);
    Code:
       0: aload_0
       1: invokespecial #48                 // Method io/dekorate/deps/kubernetes/api/model/apps/DaemonSetStatusFluentImpl."<init>":()V
       4: aload_0
       5: aload_1
       6: putfield      #50                 // Field fluent:Lio/dekorate/deps/kubernetes/api/model/apps/DaemonSetStatusFluent;
       9: aload_1
      10: aload_2
      11: invokevirtual #54                 // Method io/dekorate/deps/kubernetes/api/model/apps/DaemonSetStatus.getCollisionCount:()Ljava/lang/Integer;
      14: invokeinterface #60,  2           // InterfaceMethod io/dekorate/deps/kubernetes/api/model/apps/DaemonSetStatusFluent.withCollisionCount:(Ljava/lang/Integer;)Lio/dekorate/deps/kubernetes/api/model/apps/DaemonSetStatusFluent;
      19: pop
      20: aload_1
      21: aload_2
      22: invokevirtual #64                 // Method io/dekorate/deps/kubernetes/api/model/apps/DaemonSetStatus.getConditions:()Ljava/util/List;
      25: invokeinterface #68,  2           // InterfaceMethod io/dekorate/deps/kubernetes/api/model/apps/DaemonSetStatusFluent.withConditions:(Ljava/util/List;)Lio/dekorate/deps/kubernetes/api/model/apps/DaemonSetStatusFluent;
      30: pop
      31: aload_1
      32: aload_2
      33: invokevirtual #71                 // Method io/dekorate/deps/kubernetes/api/model/apps/DaemonSetStatus.getCurrentNumberScheduled:()Ljava/lang/Integer;
      36: invokeinterface #74,  2           // InterfaceMethod io/dekorate/deps/kubernetes/api/model/apps/DaemonSetStatusFluent.withCurrentNumberScheduled:(Ljava/lang/Integer;)Lio/dekorate/deps/kubernetes/api/model/apps/DaemonSetStatusFluent;
      41: pop
      42: aload_1
      43: aload_2
      44: invokevirtual #77                 // Method io/dekorate/deps/kubernetes/api/model/apps/DaemonSetStatus.getDesiredNumberScheduled:()Ljava/lang/Integer;
      47: invokeinterface #80,  2           // InterfaceMethod io/dekorate/deps/kubernetes/api/model/apps/DaemonSetStatusFluent.withDesiredNumberScheduled:(Ljava/lang/Integer;)Lio/dekorate/deps/kubernetes/api/model/apps/DaemonSetStatusFluent;
      52: pop
      53: aload_1
      54: aload_2
      55: invokevirtual #83                 // Method io/dekorate/deps/kubernetes/api/model/apps/DaemonSetStatus.getNumberAvailable:()Ljava/lang/Integer;
      58: invokeinterface #86,  2           // InterfaceMethod io/dekorate/deps/kubernetes/api/model/apps/DaemonSetStatusFluent.withNumberAvailable:(Ljava/lang/Integer;)Lio/dekorate/deps/kubernetes/api/model/apps/DaemonSetStatusFluent;
      63: pop
      64: aload_1
      65: aload_2
      66: invokevirtual #89                 // Method io/dekorate/deps/kubernetes/api/model/apps/DaemonSetStatus.getNumberMisscheduled:()Ljava/lang/Integer;
      69: invokeinterface #92,  2           // InterfaceMethod io/dekorate/deps/kubernetes/api/model/apps/DaemonSetStatusFluent.withNumberMisscheduled:(Ljava/lang/Integer;)Lio/dekorate/deps/kubernetes/api/model/apps/DaemonSetStatusFluent;
      74: pop
      75: aload_1
      76: aload_2
      77: invokevirtual #95                 // Method io/dekorate/deps/kubernetes/api/model/apps/DaemonSetStatus.getNumberReady:()Ljava/lang/Integer;
      80: invokeinterface #98,  2           // InterfaceMethod io/dekorate/deps/kubernetes/api/model/apps/DaemonSetStatusFluent.withNumberReady:(Ljava/lang/Integer;)Lio/dekorate/deps/kubernetes/api/model/apps/DaemonSetStatusFluent;
      85: pop
      86: aload_1
      87: aload_2
      88: invokevirtual #101                // Method io/dekorate/deps/kubernetes/api/model/apps/DaemonSetStatus.getNumberUnavailable:()Ljava/lang/Integer;
      91: invokeinterface #104,  2          // InterfaceMethod io/dekorate/deps/kubernetes/api/model/apps/DaemonSetStatusFluent.withNumberUnavailable:(Ljava/lang/Integer;)Lio/dekorate/deps/kubernetes/api/model/apps/DaemonSetStatusFluent;
      96: pop
      97: aload_1
      98: aload_2
      99: invokevirtual #108                // Method io/dekorate/deps/kubernetes/api/model/apps/DaemonSetStatus.getObservedGeneration:()Ljava/lang/Long;
     102: invokeinterface #112,  2          // InterfaceMethod io/dekorate/deps/kubernetes/api/model/apps/DaemonSetStatusFluent.withObservedGeneration:(Ljava/lang/Long;)Lio/dekorate/deps/kubernetes/api/model/apps/DaemonSetStatusFluent;
     107: pop
     108: aload_1
     109: aload_2
     110: invokevirtual #115                // Method io/dekorate/deps/kubernetes/api/model/apps/DaemonSetStatus.getUpdatedNumberScheduled:()Ljava/lang/Integer;
     113: invokeinterface #118,  2          // InterfaceMethod io/dekorate/deps/kubernetes/api/model/apps/DaemonSetStatusFluent.withUpdatedNumberScheduled:(Ljava/lang/Integer;)Lio/dekorate/deps/kubernetes/api/model/apps/DaemonSetStatusFluent;
     118: pop
     119: aload_0
     120: aload_3
     121: putfield      #120                // Field validationEnabled:Ljava/lang/Boolean;
     124: return

  public io.dekorate.deps.kubernetes.api.model.apps.DaemonSetStatusBuilder(io.dekorate.deps.kubernetes.api.model.apps.DaemonSetStatus);
    Code:
       0: aload_0
       1: aload_1
       2: iconst_1
       3: invokestatic  #21                 // Method java/lang/Boolean.valueOf:(Z)Ljava/lang/Boolean;
       6: invokespecial #33                 // Method "<init>":(Lio/dekorate/deps/kubernetes/api/model/apps/DaemonSetStatus;Ljava/lang/Boolean;)V
       9: return

  public io.dekorate.deps.kubernetes.api.model.apps.DaemonSetStatusBuilder(io.dekorate.deps.kubernetes.api.model.apps.DaemonSetStatus, java.lang.Boolean);
    Code:
       0: aload_0
       1: invokespecial #48                 // Method io/dekorate/deps/kubernetes/api/model/apps/DaemonSetStatusFluentImpl."<init>":()V
       4: aload_0
       5: aload_0
       6: putfield      #50                 // Field fluent:Lio/dekorate/deps/kubernetes/api/model/apps/DaemonSetStatusFluent;
       9: aload_0
      10: aload_1
      11: invokevirtual #54                 // Method io/dekorate/deps/kubernetes/api/model/apps/DaemonSetStatus.getCollisionCount:()Ljava/lang/Integer;
      14: invokevirtual #122                // Method withCollisionCount:(Ljava/lang/Integer;)Lio/dekorate/deps/kubernetes/api/model/apps/DaemonSetStatusFluent;
      17: pop
      18: aload_0
      19: aload_1
      20: invokevirtual #64                 // Method io/dekorate/deps/kubernetes/api/model/apps/DaemonSetStatus.getConditions:()Ljava/util/List;
      23: invokevirtual #123                // Method withConditions:(Ljava/util/List;)Lio/dekorate/deps/kubernetes/api/model/apps/DaemonSetStatusFluent;
      26: pop
      27: aload_0
      28: aload_1
      29: invokevirtual #71                 // Method io/dekorate/deps/kubernetes/api/model/apps/DaemonSetStatus.getCurrentNumberScheduled:()Ljava/lang/Integer;
      32: invokevirtual #124                // Method withCurrentNumberScheduled:(Ljava/lang/Integer;)Lio/dekorate/deps/kubernetes/api/model/apps/DaemonSetStatusFluent;
      35: pop
      36: aload_0
      37: aload_1
      38: invokevirtual #77                 // Method io/dekorate/deps/kubernetes/api/model/apps/DaemonSetStatus.getDesiredNumberScheduled:()Ljava/lang/Integer;
      41: invokevirtual #125                // Method withDesiredNumberScheduled:(Ljava/lang/Integer;)Lio/dekorate/deps/kubernetes/api/model/apps/DaemonSetStatusFluent;
      44: pop
      45: aload_0
      46: aload_1
      47: invokevirtual #83                 // Method io/dekorate/deps/kubernetes/api/model/apps/DaemonSetStatus.getNumberAvailable:()Ljava/lang/Integer;
      50: invokevirtual #126                // Method withNumberAvailable:(Ljava/lang/Integer;)Lio/dekorate/deps/kubernetes/api/model/apps/DaemonSetStatusFluent;
      53: pop
      54: aload_0
      55: aload_1
      56: invokevirtual #89                 // Method io/dekorate/deps/kubernetes/api/model/apps/DaemonSetStatus.getNumberMisscheduled:()Ljava/lang/Integer;
      59: invokevirtual #127                // Method withNumberMisscheduled:(Ljava/lang/Integer;)Lio/dekorate/deps/kubernetes/api/model/apps/DaemonSetStatusFluent;
      62: pop
      63: aload_0
      64: aload_1
      65: invokevirtual #95                 // Method io/dekorate/deps/kubernetes/api/model/apps/DaemonSetStatus.getNumberReady:()Ljava/lang/Integer;
      68: invokevirtual #128                // Method withNumberReady:(Ljava/lang/Integer;)Lio/dekorate/deps/kubernetes/api/model/apps/DaemonSetStatusFluent;
      71: pop
      72: aload_0
      73: aload_1
      74: invokevirtual #101                // Method io/dekorate/deps/kubernetes/api/model/apps/DaemonSetStatus.getNumberUnavailable:()Ljava/lang/Integer;
      77: invokevirtual #129                // Method withNumberUnavailable:(Ljava/lang/Integer;)Lio/dekorate/deps/kubernetes/api/model/apps/DaemonSetStatusFluent;
      80: pop
      81: aload_0
      82: aload_1
      83: invokevirtual #108                // Method io/dekorate/deps/kubernetes/api/model/apps/DaemonSetStatus.getObservedGeneration:()Ljava/lang/Long;
      86: invokevirtual #130                // Method withObservedGeneration:(Ljava/lang/Long;)Lio/dekorate/deps/kubernetes/api/model/apps/DaemonSetStatusFluent;
      89: pop
      90: aload_0
      91: aload_1
      92: invokevirtual #115                // Method io/dekorate/deps/kubernetes/api/model/apps/DaemonSetStatus.getUpdatedNumberScheduled:()Ljava/lang/Integer;
      95: invokevirtual #131                // Method withUpdatedNumberScheduled:(Ljava/lang/Integer;)Lio/dekorate/deps/kubernetes/api/model/apps/DaemonSetStatusFluent;
      98: pop
      99: aload_0
     100: aload_2
     101: putfield      #120                // Field validationEnabled:Ljava/lang/Boolean;
     104: return

  public io.dekorate.deps.kubernetes.api.model.apps.DaemonSetStatus build();
    Code:
       0: new           #28                 // class io/dekorate/deps/kubernetes/api/model/apps/DaemonSetStatus
       3: dup
       4: aload_0
       5: getfield      #50                 // Field fluent:Lio/dekorate/deps/kubernetes/api/model/apps/DaemonSetStatusFluent;
       8: invokeinterface #134,  1          // InterfaceMethod io/dekorate/deps/kubernetes/api/model/apps/DaemonSetStatusFluent.getCollisionCount:()Ljava/lang/Integer;
      13: aload_0
      14: getfield      #50                 // Field fluent:Lio/dekorate/deps/kubernetes/api/model/apps/DaemonSetStatusFluent;
      17: invokeinterface #135,  1          // InterfaceMethod io/dekorate/deps/kubernetes/api/model/apps/DaemonSetStatusFluent.getConditions:()Ljava/util/List;
      22: aload_0
      23: getfield      #50                 // Field fluent:Lio/dekorate/deps/kubernetes/api/model/apps/DaemonSetStatusFluent;
      26: invokeinterface #136,  1          // InterfaceMethod io/dekorate/deps/kubernetes/api/model/apps/DaemonSetStatusFluent.getCurrentNumberScheduled:()Ljava/lang/Integer;
      31: aload_0
      32: getfield      #50                 // Field fluent:Lio/dekorate/deps/kubernetes/api/model/apps/DaemonSetStatusFluent;
      35: invokeinterface #137,  1          // InterfaceMethod io/dekorate/deps/kubernetes/api/model/apps/DaemonSetStatusFluent.getDesiredNumberScheduled:()Ljava/lang/Integer;
      40: aload_0
      41: getfield      #50                 // Field fluent:Lio/dekorate/deps/kubernetes/api/model/apps/DaemonSetStatusFluent;
      44: invokeinterface #138,  1          // InterfaceMethod io/dekorate/deps/kubernetes/api/model/apps/DaemonSetStatusFluent.getNumberAvailable:()Ljava/lang/Integer;
      49: aload_0
      50: getfield      #50                 // Field fluent:Lio/dekorate/deps/kubernetes/api/model/apps/DaemonSetStatusFluent;
      53: invokeinterface #139,  1          // InterfaceMethod io/dekorate/deps/kubernetes/api/model/apps/DaemonSetStatusFluent.getNumberMisscheduled:()Ljava/lang/Integer;
      58: aload_0
      59: getfield      #50                 // Field fluent:Lio/dekorate/deps/kubernetes/api/model/apps/DaemonSetStatusFluent;
      62: invokeinterface #140,  1          // InterfaceMethod io/dekorate/deps/kubernetes/api/model/apps/DaemonSetStatusFluent.getNumberReady:()Ljava/lang/Integer;
      67: aload_0
      68: getfield      #50                 // Field fluent:Lio/dekorate/deps/kubernetes/api/model/apps/DaemonSetStatusFluent;
      71: invokeinterface #141,  1          // InterfaceMethod io/dekorate/deps/kubernetes/api/model/apps/DaemonSetStatusFluent.getNumberUnavailable:()Ljava/lang/Integer;
      76: aload_0
      77: getfield      #50                 // Field fluent:Lio/dekorate/deps/kubernetes/api/model/apps/DaemonSetStatusFluent;
      80: invokeinterface #142,  1          // InterfaceMethod io/dekorate/deps/kubernetes/api/model/apps/DaemonSetStatusFluent.getObservedGeneration:()Ljava/lang/Long;
      85: aload_0
      86: getfield      #50                 // Field fluent:Lio/dekorate/deps/kubernetes/api/model/apps/DaemonSetStatusFluent;
      89: invokeinterface #143,  1          // InterfaceMethod io/dekorate/deps/kubernetes/api/model/apps/DaemonSetStatusFluent.getUpdatedNumberScheduled:()Ljava/lang/Integer;
      94: invokespecial #146                // Method io/dekorate/deps/kubernetes/api/model/apps/DaemonSetStatus."<init>":(Ljava/lang/Integer;Ljava/util/List;Ljava/lang/Integer;Ljava/lang/Integer;Ljava/lang/Integer;Ljava/lang/Integer;Ljava/lang/Integer;Ljava/lang/Integer;Ljava/lang/Long;Ljava/lang/Integer;)V
      97: astore_1
      98: aload_1
      99: areturn

  public boolean equals(java.lang.Object);
    Code:
       0: aload_0
       1: aload_1
       2: if_acmpne     7
       5: iconst_1
       6: ireturn
       7: aload_1
       8: ifnull        22
      11: aload_0
      12: invokevirtual #155                // Method java/lang/Object.getClass:()Ljava/lang/Class;
      15: aload_1
      16: invokevirtual #155                // Method java/lang/Object.getClass:()Ljava/lang/Class;
      19: if_acmpeq     24
      22: iconst_0
      23: ireturn
      24: aload_0
      25: aload_1
      26: invokespecial #157                // Method io/dekorate/deps/kubernetes/api/model/apps/DaemonSetStatusFluentImpl.equals:(Ljava/lang/Object;)Z
      29: ifne          34
      32: iconst_0
      33: ireturn
      34: aload_1
      35: checkcast     #2                  // class io/dekorate/deps/kubernetes/api/model/apps/DaemonSetStatusBuilder
      38: astore_2
      39: aload_0
      40: getfield      #50                 // Field fluent:Lio/dekorate/deps/kubernetes/api/model/apps/DaemonSetStatusFluent;
      43: ifnull        71
      46: aload_0
      47: getfield      #50                 // Field fluent:Lio/dekorate/deps/kubernetes/api/model/apps/DaemonSetStatusFluent;
      50: aload_0
      51: if_acmpeq     71
      54: aload_0
      55: getfield      #50                 // Field fluent:Lio/dekorate/deps/kubernetes/api/model/apps/DaemonSetStatusFluent;
      58: aload_2
      59: getfield      #50                 // Field fluent:Lio/dekorate/deps/kubernetes/api/model/apps/DaemonSetStatusFluent;
      62: invokevirtual #158                // Method java/lang/Object.equals:(Ljava/lang/Object;)Z
      65: ifne          88
      68: goto          86
      71: aload_2
      72: getfield      #50                 // Field fluent:Lio/dekorate/deps/kubernetes/api/model/apps/DaemonSetStatusFluent;
      75: ifnull        88
      78: aload_0
      79: getfield      #50                 // Field fluent:Lio/dekorate/deps/kubernetes/api/model/apps/DaemonSetStatusFluent;
      82: aload_0
      83: if_acmpeq     88
      86: iconst_0
      87: ireturn
      88: aload_0
      89: getfield      #120                // Field validationEnabled:Ljava/lang/Boolean;
      92: ifnull        112
      95: aload_0
      96: getfield      #120                // Field validationEnabled:Ljava/lang/Boolean;
      99: aload_2
     100: getfield      #120                // Field validationEnabled:Ljava/lang/Boolean;
     103: invokevirtual #159                // Method java/lang/Boolean.equals:(Ljava/lang/Object;)Z
     106: ifne          121
     109: goto          119
     112: aload_2
     113: getfield      #120                // Field validationEnabled:Ljava/lang/Boolean;
     116: ifnull        121
     119: iconst_0
     120: ireturn
     121: iconst_1
     122: ireturn

  public java.lang.Object build();
    Code:
       0: aload_0
       1: invokevirtual #165                // Method build:()Lio/dekorate/deps/kubernetes/api/model/apps/DaemonSetStatus;
       4: areturn
}
