Compiled from "DeploymentStrategyFluentImpl.java"
public class io.dekorate.deps.kubernetes.api.model.apps.DeploymentStrategyFluentImpl$RollingUpdateNestedImpl<N> extends io.dekorate.deps.kubernetes.api.model.apps.RollingUpdateDeploymentFluentImpl<io.dekorate.deps.kubernetes.api.model.apps.DeploymentStrategyFluent$RollingUpdateNested<N>> implements io.dekorate.deps.kubernetes.api.model.apps.DeploymentStrategyFluent$RollingUpdateNested<N>, io.dekorate.deps.kubernetes.api.builder.Nested<N> {
  private final io.dekorate.deps.kubernetes.api.model.apps.RollingUpdateDeploymentBuilder builder;

  final io.dekorate.deps.kubernetes.api.model.apps.DeploymentStrategyFluentImpl this$0;

  io.dekorate.deps.kubernetes.api.model.apps.DeploymentStrategyFluentImpl$RollingUpdateNestedImpl(io.dekorate.deps.kubernetes.api.model.apps.DeploymentStrategyFluentImpl, io.dekorate.deps.kubernetes.api.model.apps.RollingUpdateDeployment);
    Code:
       0: aload_0
       1: aload_1
       2: putfield      #24                 // Field this$0:Lio/dekorate/deps/kubernetes/api/model/apps/DeploymentStrategyFluentImpl;
       5: aload_0
       6: invokespecial #27                 // Method io/dekorate/deps/kubernetes/api/model/apps/RollingUpdateDeploymentFluentImpl."<init>":()V
       9: aload_0
      10: new           #29                 // class io/dekorate/deps/kubernetes/api/model/apps/RollingUpdateDeploymentBuilder
      13: dup
      14: aload_0
      15: aload_2
      16: invokespecial #32                 // Method io/dekorate/deps/kubernetes/api/model/apps/RollingUpdateDeploymentBuilder."<init>":(Lio/dekorate/deps/kubernetes/api/model/apps/RollingUpdateDeploymentFluent;Lio/dekorate/deps/kubernetes/api/model/apps/RollingUpdateDeployment;)V
      19: putfield      #34                 // Field builder:Lio/dekorate/deps/kubernetes/api/model/apps/RollingUpdateDeploymentBuilder;
      22: return

  io.dekorate.deps.kubernetes.api.model.apps.DeploymentStrategyFluentImpl$RollingUpdateNestedImpl(io.dekorate.deps.kubernetes.api.model.apps.DeploymentStrategyFluentImpl);
    Code:
       0: aload_0
       1: aload_1
       2: putfield      #24                 // Field this$0:Lio/dekorate/deps/kubernetes/api/model/apps/DeploymentStrategyFluentImpl;
       5: aload_0
       6: invokespecial #27                 // Method io/dekorate/deps/kubernetes/api/model/apps/RollingUpdateDeploymentFluentImpl."<init>":()V
       9: aload_0
      10: new           #29                 // class io/dekorate/deps/kubernetes/api/model/apps/RollingUpdateDeploymentBuilder
      13: dup
      14: aload_0
      15: invokespecial #43                 // Method io/dekorate/deps/kubernetes/api/model/apps/RollingUpdateDeploymentBuilder."<init>":(Lio/dekorate/deps/kubernetes/api/model/apps/RollingUpdateDeploymentFluent;)V
      18: putfield      #34                 // Field builder:Lio/dekorate/deps/kubernetes/api/model/apps/RollingUpdateDeploymentBuilder;
      21: return

  public N and();
    Code:
       0: aload_0
       1: getfield      #24                 // Field this$0:Lio/dekorate/deps/kubernetes/api/model/apps/DeploymentStrategyFluentImpl;
       4: aload_0
       5: getfield      #34                 // Field builder:Lio/dekorate/deps/kubernetes/api/model/apps/RollingUpdateDeploymentBuilder;
       8: invokevirtual #50                 // Method io/dekorate/deps/kubernetes/api/model/apps/RollingUpdateDeploymentBuilder.build:()Lio/dekorate/deps/kubernetes/api/model/apps/RollingUpdateDeployment;
      11: invokevirtual #54                 // Method io/dekorate/deps/kubernetes/api/model/apps/DeploymentStrategyFluentImpl.withRollingUpdate:(Lio/dekorate/deps/kubernetes/api/model/apps/RollingUpdateDeployment;)Lio/dekorate/deps/kubernetes/api/model/apps/DeploymentStrategyFluent;
      14: areturn

  public N endRollingUpdate();
    Code:
       0: aload_0
       1: invokevirtual #57                 // Method and:()Ljava/lang/Object;
       4: areturn
}
