Compiled from "LoginConfig.java"
public class org.apache.tomcat.util.descriptor.web.LoginConfig extends org.apache.tomcat.util.descriptor.web.XmlEncodingBase implements java.io.Serializable {
  private static final long serialVersionUID;

  private java.lang.String authMethod;

  private java.lang.String errorPage;

  private java.lang.String loginPage;

  private java.lang.String realmName;

  public org.apache.tomcat.util.descriptor.web.LoginConfig();
    Code:
       0: aload_0
       1: invokespecial #1                  // Method org/apache/tomcat/util/descriptor/web/XmlEncodingBase."<init>":()V
       4: aload_0
       5: aconst_null
       6: putfield      #2                  // Field authMethod:Ljava/lang/String;
       9: aload_0
      10: aconst_null
      11: putfield      #3                  // Field errorPage:Ljava/lang/String;
      14: aload_0
      15: aconst_null
      16: putfield      #4                  // Field loginPage:Ljava/lang/String;
      19: aload_0
      20: aconst_null
      21: putfield      #5                  // Field realmName:Ljava/lang/String;
      24: return

  public org.apache.tomcat.util.descriptor.web.LoginConfig(java.lang.String, java.lang.String, java.lang.String, java.lang.String);
    Code:
       0: aload_0
       1: invokespecial #1                  // Method org/apache/tomcat/util/descriptor/web/XmlEncodingBase."<init>":()V
       4: aload_0
       5: aconst_null
       6: putfield      #2                  // Field authMethod:Ljava/lang/String;
       9: aload_0
      10: aconst_null
      11: putfield      #3                  // Field errorPage:Ljava/lang/String;
      14: aload_0
      15: aconst_null
      16: putfield      #4                  // Field loginPage:Ljava/lang/String;
      19: aload_0
      20: aconst_null
      21: putfield      #5                  // Field realmName:Ljava/lang/String;
      24: aload_0
      25: aload_1
      26: invokevirtual #6                  // Method setAuthMethod:(Ljava/lang/String;)V
      29: aload_0
      30: aload_2
      31: invokevirtual #7                  // Method setRealmName:(Ljava/lang/String;)V
      34: aload_0
      35: aload_3
      36: invokevirtual #8                  // Method setLoginPage:(Ljava/lang/String;)V
      39: aload_0
      40: aload         4
      42: invokevirtual #9                  // Method setErrorPage:(Ljava/lang/String;)V
      45: return

  public java.lang.String getAuthMethod();
    Code:
       0: aload_0
       1: getfield      #2                  // Field authMethod:Ljava/lang/String;
       4: areturn

  public void setAuthMethod(java.lang.String);
    Code:
       0: aload_0
       1: aload_1
       2: putfield      #2                  // Field authMethod:Ljava/lang/String;
       5: return

  public java.lang.String getErrorPage();
    Code:
       0: aload_0
       1: getfield      #3                  // Field errorPage:Ljava/lang/String;
       4: areturn

  public void setErrorPage(java.lang.String);
    Code:
       0: aload_0
       1: aload_1
       2: aload_0
       3: invokevirtual #10                 // Method getCharset:()Ljava/nio/charset/Charset;
       6: invokestatic  #11                 // Method org/apache/tomcat/util/buf/UDecoder.URLDecode:(Ljava/lang/String;Ljava/nio/charset/Charset;)Ljava/lang/String;
       9: putfield      #3                  // Field errorPage:Ljava/lang/String;
      12: return

  public java.lang.String getLoginPage();
    Code:
       0: aload_0
       1: getfield      #4                  // Field loginPage:Ljava/lang/String;
       4: areturn

  public void setLoginPage(java.lang.String);
    Code:
       0: aload_0
       1: aload_1
       2: aload_0
       3: invokevirtual #10                 // Method getCharset:()Ljava/nio/charset/Charset;
       6: invokestatic  #11                 // Method org/apache/tomcat/util/buf/UDecoder.URLDecode:(Ljava/lang/String;Ljava/nio/charset/Charset;)Ljava/lang/String;
       9: putfield      #4                  // Field loginPage:Ljava/lang/String;
      12: return

  public java.lang.String getRealmName();
    Code:
       0: aload_0
       1: getfield      #5                  // Field realmName:Ljava/lang/String;
       4: areturn

  public void setRealmName(java.lang.String);
    Code:
       0: aload_0
       1: aload_1
       2: putfield      #5                  // Field realmName:Ljava/lang/String;
       5: return

  public java.lang.String toString();
    Code:
       0: new           #12                 // class java/lang/StringBuilder
       3: dup
       4: ldc           #13                 // String LoginConfig[
       6: invokespecial #14                 // Method java/lang/StringBuilder."<init>":(Ljava/lang/String;)V
       9: astore_1
      10: aload_1
      11: ldc           #15                 // String authMethod=
      13: invokevirtual #16                 // Method java/lang/StringBuilder.append:(Ljava/lang/String;)Ljava/lang/StringBuilder;
      16: pop
      17: aload_1
      18: aload_0
      19: getfield      #2                  // Field authMethod:Ljava/lang/String;
      22: invokevirtual #16                 // Method java/lang/StringBuilder.append:(Ljava/lang/String;)Ljava/lang/StringBuilder;
      25: pop
      26: aload_0
      27: getfield      #5                  // Field realmName:Ljava/lang/String;
      30: ifnull        49
      33: aload_1
      34: ldc           #17                 // String , realmName=
      36: invokevirtual #16                 // Method java/lang/StringBuilder.append:(Ljava/lang/String;)Ljava/lang/StringBuilder;
      39: pop
      40: aload_1
      41: aload_0
      42: getfield      #5                  // Field realmName:Ljava/lang/String;
      45: invokevirtual #16                 // Method java/lang/StringBuilder.append:(Ljava/lang/String;)Ljava/lang/StringBuilder;
      48: pop
      49: aload_0
      50: getfield      #4                  // Field loginPage:Ljava/lang/String;
      53: ifnull        72
      56: aload_1
      57: ldc           #18                 // String , loginPage=
      59: invokevirtual #16                 // Method java/lang/StringBuilder.append:(Ljava/lang/String;)Ljava/lang/StringBuilder;
      62: pop
      63: aload_1
      64: aload_0
      65: getfield      #4                  // Field loginPage:Ljava/lang/String;
      68: invokevirtual #16                 // Method java/lang/StringBuilder.append:(Ljava/lang/String;)Ljava/lang/StringBuilder;
      71: pop
      72: aload_0
      73: getfield      #3                  // Field errorPage:Ljava/lang/String;
      76: ifnull        95
      79: aload_1
      80: ldc           #19                 // String , errorPage=
      82: invokevirtual #16                 // Method java/lang/StringBuilder.append:(Ljava/lang/String;)Ljava/lang/StringBuilder;
      85: pop
      86: aload_1
      87: aload_0
      88: getfield      #3                  // Field errorPage:Ljava/lang/String;
      91: invokevirtual #16                 // Method java/lang/StringBuilder.append:(Ljava/lang/String;)Ljava/lang/StringBuilder;
      94: pop
      95: aload_1
      96: ldc           #20                 // String ]
      98: invokevirtual #16                 // Method java/lang/StringBuilder.append:(Ljava/lang/String;)Ljava/lang/StringBuilder;
     101: pop
     102: aload_1
     103: invokevirtual #21                 // Method java/lang/StringBuilder.toString:()Ljava/lang/String;
     106: areturn

  public int hashCode();
    Code:
       0: bipush        31
       2: istore_1
       3: iconst_1
       4: istore_2
       5: bipush        31
       7: iload_2
       8: imul
       9: aload_0
      10: getfield      #2                  // Field authMethod:Ljava/lang/String;
      13: ifnonnull     20
      16: iconst_0
      17: goto          27
      20: aload_0
      21: getfield      #2                  // Field authMethod:Ljava/lang/String;
      24: invokevirtual #22                 // Method java/lang/String.hashCode:()I
      27: iadd
      28: istore_2
      29: bipush        31
      31: iload_2
      32: imul
      33: aload_0
      34: getfield      #3                  // Field errorPage:Ljava/lang/String;
      37: ifnonnull     44
      40: iconst_0
      41: goto          51
      44: aload_0
      45: getfield      #3                  // Field errorPage:Ljava/lang/String;
      48: invokevirtual #22                 // Method java/lang/String.hashCode:()I
      51: iadd
      52: istore_2
      53: bipush        31
      55: iload_2
      56: imul
      57: aload_0
      58: getfield      #4                  // Field loginPage:Ljava/lang/String;
      61: ifnonnull     68
      64: iconst_0
      65: goto          75
      68: aload_0
      69: getfield      #4                  // Field loginPage:Ljava/lang/String;
      72: invokevirtual #22                 // Method java/lang/String.hashCode:()I
      75: iadd
      76: istore_2
      77: bipush        31
      79: iload_2
      80: imul
      81: aload_0
      82: getfield      #5                  // Field realmName:Ljava/lang/String;
      85: ifnonnull     92
      88: iconst_0
      89: goto          99
      92: aload_0
      93: getfield      #5                  // Field realmName:Ljava/lang/String;
      96: invokevirtual #22                 // Method java/lang/String.hashCode:()I
      99: iadd
     100: istore_2
     101: iload_2
     102: ireturn

  public boolean equals(java.lang.Object);
    Code:
       0: aload_0
       1: aload_1
       2: if_acmpne     7
       5: iconst_1
       6: ireturn
       7: aload_1
       8: instanceof    #23                 // class org/apache/tomcat/util/descriptor/web/LoginConfig
      11: ifne          16
      14: iconst_0
      15: ireturn
      16: aload_1
      17: checkcast     #23                 // class org/apache/tomcat/util/descriptor/web/LoginConfig
      20: astore_2
      21: aload_0
      22: getfield      #2                  // Field authMethod:Ljava/lang/String;
      25: ifnonnull     37
      28: aload_2
      29: getfield      #2                  // Field authMethod:Ljava/lang/String;
      32: ifnull        53
      35: iconst_0
      36: ireturn
      37: aload_0
      38: getfield      #2                  // Field authMethod:Ljava/lang/String;
      41: aload_2
      42: getfield      #2                  // Field authMethod:Ljava/lang/String;
      45: invokevirtual #24                 // Method java/lang/String.equals:(Ljava/lang/Object;)Z
      48: ifne          53
      51: iconst_0
      52: ireturn
      53: aload_0
      54: getfield      #3                  // Field errorPage:Ljava/lang/String;
      57: ifnonnull     69
      60: aload_2
      61: getfield      #3                  // Field errorPage:Ljava/lang/String;
      64: ifnull        85
      67: iconst_0
      68: ireturn
      69: aload_0
      70: getfield      #3                  // Field errorPage:Ljava/lang/String;
      73: aload_2
      74: getfield      #3                  // Field errorPage:Ljava/lang/String;
      77: invokevirtual #24                 // Method java/lang/String.equals:(Ljava/lang/Object;)Z
      80: ifne          85
      83: iconst_0
      84: ireturn
      85: aload_0
      86: getfield      #4                  // Field loginPage:Ljava/lang/String;
      89: ifnonnull     101
      92: aload_2
      93: getfield      #4                  // Field loginPage:Ljava/lang/String;
      96: ifnull        117
      99: iconst_0
     100: ireturn
     101: aload_0
     102: getfield      #4                  // Field loginPage:Ljava/lang/String;
     105: aload_2
     106: getfield      #4                  // Field loginPage:Ljava/lang/String;
     109: invokevirtual #24                 // Method java/lang/String.equals:(Ljava/lang/Object;)Z
     112: ifne          117
     115: iconst_0
     116: ireturn
     117: aload_0
     118: getfield      #5                  // Field realmName:Ljava/lang/String;
     121: ifnonnull     133
     124: aload_2
     125: getfield      #5                  // Field realmName:Ljava/lang/String;
     128: ifnull        149
     131: iconst_0
     132: ireturn
     133: aload_0
     134: getfield      #5                  // Field realmName:Ljava/lang/String;
     137: aload_2
     138: getfield      #5                  // Field realmName:Ljava/lang/String;
     141: invokevirtual #24                 // Method java/lang/String.equals:(Ljava/lang/Object;)Z
     144: ifne          149
     147: iconst_0
     148: ireturn
     149: iconst_1
     150: ireturn
}
