Compiled from "AdapterLocationMapper.java"
public class org.apache.jena.riot.adapters.AdapterLocationMapper extends org.apache.jena.util.LocationMapper {
  private final org.apache.jena.riot.system.stream.LocationMapper mapper;

  public org.apache.jena.riot.adapters.AdapterLocationMapper(org.apache.jena.riot.system.stream.LocationMapper);
    Code:
       0: aload_0
       1: invokespecial #1                  // Method org/apache/jena/util/LocationMapper."<init>":()V
       4: aload_0
       5: aload_1
       6: putfield      #2                  // Field mapper:Lorg/apache/jena/riot/system/stream/LocationMapper;
       9: return

  public java.lang.String altMapping(java.lang.String, java.lang.String);
    Code:
       0: aload_0
       1: getfield      #2                  // Field mapper:Lorg/apache/jena/riot/system/stream/LocationMapper;
       4: aload_1
       5: aload_2
       6: invokevirtual #3                  // Method org/apache/jena/riot/system/stream/LocationMapper.altMapping:(Ljava/lang/String;Ljava/lang/String;)Ljava/lang/String;
       9: areturn

  public void addAltEntry(java.lang.String, java.lang.String);
    Code:
       0: aload_0
       1: getfield      #2                  // Field mapper:Lorg/apache/jena/riot/system/stream/LocationMapper;
       4: aload_1
       5: aload_2
       6: invokevirtual #4                  // Method org/apache/jena/riot/system/stream/LocationMapper.addAltEntry:(Ljava/lang/String;Ljava/lang/String;)V
       9: return

  public void addAltPrefix(java.lang.String, java.lang.String);
    Code:
       0: aload_0
       1: getfield      #2                  // Field mapper:Lorg/apache/jena/riot/system/stream/LocationMapper;
       4: aload_1
       5: aload_2
       6: invokevirtual #5                  // Method org/apache/jena/riot/system/stream/LocationMapper.addAltPrefix:(Ljava/lang/String;Ljava/lang/String;)V
       9: return

  public java.util.Iterator<java.lang.String> listAltEntries();
    Code:
       0: aload_0
       1: getfield      #2                  // Field mapper:Lorg/apache/jena/riot/system/stream/LocationMapper;
       4: invokevirtual #6                  // Method org/apache/jena/riot/system/stream/LocationMapper.listAltEntries:()Ljava/util/Iterator;
       7: areturn

  public java.util.Iterator<java.lang.String> listAltPrefixes();
    Code:
       0: aload_0
       1: getfield      #2                  // Field mapper:Lorg/apache/jena/riot/system/stream/LocationMapper;
       4: invokevirtual #6                  // Method org/apache/jena/riot/system/stream/LocationMapper.listAltEntries:()Ljava/util/Iterator;
       7: areturn

  public void removeAltEntry(java.lang.String);
    Code:
       0: aload_0
       1: getfield      #2                  // Field mapper:Lorg/apache/jena/riot/system/stream/LocationMapper;
       4: aload_1
       5: invokevirtual #7                  // Method org/apache/jena/riot/system/stream/LocationMapper.removeAltEntry:(Ljava/lang/String;)V
       8: return

  public void removeAltPrefix(java.lang.String);
    Code:
       0: aload_0
       1: getfield      #2                  // Field mapper:Lorg/apache/jena/riot/system/stream/LocationMapper;
       4: aload_1
       5: invokevirtual #8                  // Method org/apache/jena/riot/system/stream/LocationMapper.removeAltPrefix:(Ljava/lang/String;)V
       8: return

  public java.lang.String getAltEntry(java.lang.String);
    Code:
       0: aload_0
       1: getfield      #2                  // Field mapper:Lorg/apache/jena/riot/system/stream/LocationMapper;
       4: aload_1
       5: invokevirtual #9                  // Method org/apache/jena/riot/system/stream/LocationMapper.getAltEntry:(Ljava/lang/String;)Ljava/lang/String;
       8: areturn

  public java.lang.String getAltPrefix(java.lang.String);
    Code:
       0: aload_0
       1: getfield      #2                  // Field mapper:Lorg/apache/jena/riot/system/stream/LocationMapper;
       4: aload_1
       5: invokevirtual #10                 // Method org/apache/jena/riot/system/stream/LocationMapper.getAltPrefix:(Ljava/lang/String;)Ljava/lang/String;
       8: areturn

  public int hashCode();
    Code:
       0: aload_0
       1: getfield      #2                  // Field mapper:Lorg/apache/jena/riot/system/stream/LocationMapper;
       4: invokevirtual #11                 // Method org/apache/jena/riot/system/stream/LocationMapper.hashCode:()I
       7: ireturn

  public boolean equals(java.lang.Object);
    Code:
       0: aload_0
       1: getfield      #2                  // Field mapper:Lorg/apache/jena/riot/system/stream/LocationMapper;
       4: aload_1
       5: invokevirtual #12                 // Method org/apache/jena/riot/system/stream/LocationMapper.equals:(Ljava/lang/Object;)Z
       8: ireturn

  public java.lang.String toString();
    Code:
       0: aload_0
       1: getfield      #2                  // Field mapper:Lorg/apache/jena/riot/system/stream/LocationMapper;
       4: invokevirtual #13                 // Method org/apache/jena/riot/system/stream/LocationMapper.toString:()Ljava/lang/String;
       7: areturn

  public void toModel(org.apache.jena.rdf.model.Model);
    Code:
       0: aload_0
       1: getfield      #2                  // Field mapper:Lorg/apache/jena/riot/system/stream/LocationMapper;
       4: aload_1
       5: invokevirtual #14                 // Method org/apache/jena/riot/system/stream/LocationMapper.toModel:(Lorg/apache/jena/rdf/model/Model;)V
       8: return
}
