Compiled from "Ranges.kt"
public final class kotlin.ranges.CharRange$Companion {
  private kotlin.ranges.CharRange$Companion();
    Code:
       0: aload_0
       1: invokespecial #8                  // Method java/lang/Object."<init>":()V
       4: return

  public final kotlin.ranges.CharRange getEMPTY();
    Code:
       0: invokestatic  #18                 // Method kotlin/ranges/CharRange.access$getEMPTY$cp:()Lkotlin/ranges/CharRange;
       3: areturn

  public kotlin.ranges.CharRange$Companion(kotlin.jvm.internal.DefaultConstructorMarker);
    Code:
       0: aload_0
       1: invokespecial #20                 // Method "<init>":()V
       4: return
}
