Compiled from "BaseLdapUserSearchResource.java"
public final class org.jboss.as.domain.management.security.BaseLdapUserSearchResource$UserSearchType extends java.lang.Enum<org.jboss.as.domain.management.security.BaseLdapUserSearchResource$UserSearchType> {
  public static final org.jboss.as.domain.management.security.BaseLdapUserSearchResource$UserSearchType USERNAME_IS_DN;

  public static final org.jboss.as.domain.management.security.BaseLdapUserSearchResource$UserSearchType USERNAME_FILTER;

  public static final org.jboss.as.domain.management.security.BaseLdapUserSearchResource$UserSearchType ADVANCED_FILTER;

  private final java.lang.String modelValue;

  private static final org.jboss.as.domain.management.security.BaseLdapUserSearchResource$UserSearchType[] $VALUES;

  public static org.jboss.as.domain.management.security.BaseLdapUserSearchResource$UserSearchType[] values();
    Code:
       0: getstatic     #1                  // Field $VALUES:[Lorg/jboss/as/domain/management/security/BaseLdapUserSearchResource$UserSearchType;
       3: invokevirtual #2                  // Method "[Lorg/jboss/as/domain/management/security/BaseLdapUserSearchResource$UserSearchType;".clone:()Ljava/lang/Object;
       6: checkcast     #3                  // class "[Lorg/jboss/as/domain/management/security/BaseLdapUserSearchResource$UserSearchType;"
       9: areturn

  public static org.jboss.as.domain.management.security.BaseLdapUserSearchResource$UserSearchType valueOf(java.lang.String);
    Code:
       0: ldc           #4                  // class org/jboss/as/domain/management/security/BaseLdapUserSearchResource$UserSearchType
       2: aload_0
       3: invokestatic  #5                  // Method java/lang/Enum.valueOf:(Ljava/lang/Class;Ljava/lang/String;)Ljava/lang/Enum;
       6: checkcast     #4                  // class org/jboss/as/domain/management/security/BaseLdapUserSearchResource$UserSearchType
       9: areturn

  private org.jboss.as.domain.management.security.BaseLdapUserSearchResource$UserSearchType(java.lang.String);
    Code:
       0: aload_0
       1: aload_1
       2: iload_2
       3: invokespecial #6                  // Method java/lang/Enum."<init>":(Ljava/lang/String;I)V
       6: aload_0
       7: aload_3
       8: putfield      #7                  // Field modelValue:Ljava/lang/String;
      11: return

  public java.lang.String getModelValue();
    Code:
       0: aload_0
       1: getfield      #7                  // Field modelValue:Ljava/lang/String;
       4: areturn

  static {};
    Code:
       0: new           #4                  // class org/jboss/as/domain/management/security/BaseLdapUserSearchResource$UserSearchType
       3: dup
       4: ldc           #8                  // String USERNAME_IS_DN
       6: iconst_0
       7: ldc           #10                 // String username-is-dn
       9: invokespecial #11                 // Method "<init>":(Ljava/lang/String;ILjava/lang/String;)V
      12: putstatic     #12                 // Field USERNAME_IS_DN:Lorg/jboss/as/domain/management/security/BaseLdapUserSearchResource$UserSearchType;
      15: new           #4                  // class org/jboss/as/domain/management/security/BaseLdapUserSearchResource$UserSearchType
      18: dup
      19: ldc           #13                 // String USERNAME_FILTER
      21: iconst_1
      22: ldc           #14                 // String username-filter
      24: invokespecial #11                 // Method "<init>":(Ljava/lang/String;ILjava/lang/String;)V
      27: putstatic     #15                 // Field USERNAME_FILTER:Lorg/jboss/as/domain/management/security/BaseLdapUserSearchResource$UserSearchType;
      30: new           #4                  // class org/jboss/as/domain/management/security/BaseLdapUserSearchResource$UserSearchType
      33: dup
      34: ldc           #16                 // String ADVANCED_FILTER
      36: iconst_2
      37: ldc           #17                 // String advanced-filter
      39: invokespecial #11                 // Method "<init>":(Ljava/lang/String;ILjava/lang/String;)V
      42: putstatic     #18                 // Field ADVANCED_FILTER:Lorg/jboss/as/domain/management/security/BaseLdapUserSearchResource$UserSearchType;
      45: iconst_3
      46: anewarray     #4                  // class org/jboss/as/domain/management/security/BaseLdapUserSearchResource$UserSearchType
      49: dup
      50: iconst_0
      51: getstatic     #12                 // Field USERNAME_IS_DN:Lorg/jboss/as/domain/management/security/BaseLdapUserSearchResource$UserSearchType;
      54: aastore
      55: dup
      56: iconst_1
      57: getstatic     #15                 // Field USERNAME_FILTER:Lorg/jboss/as/domain/management/security/BaseLdapUserSearchResource$UserSearchType;
      60: aastore
      61: dup
      62: iconst_2
      63: getstatic     #18                 // Field ADVANCED_FILTER:Lorg/jboss/as/domain/management/security/BaseLdapUserSearchResource$UserSearchType;
      66: aastore
      67: putstatic     #1                  // Field $VALUES:[Lorg/jboss/as/domain/management/security/BaseLdapUserSearchResource$UserSearchType;
      70: return
}
