Compiled from "JaasCallbackHandler.java"
public class org.jboss.as.domain.management.security.JaasCallbackHandler implements org.jboss.msc.service.Service<org.jboss.as.domain.management.security.CallbackHandlerService>, org.jboss.as.domain.management.security.CallbackHandlerService, javax.security.auth.callback.CallbackHandler {
  private static final java.lang.String SERVICE_SUFFIX;

  private static final java.util.Map<java.lang.String, java.lang.String> configurationOptions;

  private final java.lang.String realm;

  private final java.lang.String name;

  private final boolean assignGroups;

  private final org.jboss.msc.value.InjectedValue<org.jboss.as.core.security.ServerSecurityManager> securityManagerValue;

  public org.jboss.as.domain.management.security.JaasCallbackHandler(java.lang.String, java.lang.String, boolean);
    Code:
       0: aload_0
       1: invokespecial #2                  // Method java/lang/Object."<init>":()V
       4: aload_0
       5: new           #3                  // class org/jboss/msc/value/InjectedValue
       8: dup
       9: invokespecial #4                  // Method org/jboss/msc/value/InjectedValue."<init>":()V
      12: putfield      #5                  // Field securityManagerValue:Lorg/jboss/msc/value/InjectedValue;
      15: aload_0
      16: aload_1
      17: putfield      #6                  // Field realm:Ljava/lang/String;
      20: aload_0
      21: aload_2
      22: putfield      #7                  // Field name:Ljava/lang/String;
      25: aload_0
      26: iload_3
      27: putfield      #8                  // Field assignGroups:Z
      30: return

  public org.jboss.as.domain.management.AuthMechanism getPreferredMechanism();
    Code:
       0: getstatic     #9                  // Field org/jboss/as/domain/management/AuthMechanism.PLAIN:Lorg/jboss/as/domain/management/AuthMechanism;
       3: areturn

  public java.util.Set<org.jboss.as.domain.management.AuthMechanism> getSupplementaryMechanisms();
    Code:
       0: invokestatic  #10                 // Method java/util/Collections.emptySet:()Ljava/util/Set;
       3: areturn

  public java.util.Map<java.lang.String, java.lang.String> getConfigurationOptions();
    Code:
       0: getstatic     #11                 // Field configurationOptions:Ljava/util/Map;
       3: areturn

  public javax.security.auth.callback.CallbackHandler getCallbackHandler(java.util.Map<java.lang.String, java.lang.Object>);
    Code:
       0: aload_0
       1: areturn

  public boolean isReadyForHttpChallenge();
    Code:
       0: iconst_1
       1: ireturn

  public void handle(javax.security.auth.callback.Callback[]) throws java.io.IOException, javax.security.auth.callback.UnsupportedCallbackException;
    Code:
       0: aload_1
       1: arraylength
       2: iconst_1
       3: if_icmpne     62
       6: aload_1
       7: iconst_0
       8: aaload
       9: instanceof    #12                 // class javax/security/sasl/AuthorizeCallback
      12: ifeq          62
      15: aload_1
      16: iconst_0
      17: aaload
      18: checkcast     #12                 // class javax/security/sasl/AuthorizeCallback
      21: astore_2
      22: aload_2
      23: invokevirtual #13                 // Method javax/security/sasl/AuthorizeCallback.getAuthenticationID:()Ljava/lang/String;
      26: aload_2
      27: invokevirtual #14                 // Method javax/security/sasl/AuthorizeCallback.getAuthorizationID:()Ljava/lang/String;
      30: invokevirtual #15                 // Method java/lang/String.equals:(Ljava/lang/Object;)Z
      33: istore_3
      34: iload_3
      35: ifne          56
      38: getstatic     #16                 // Field org/jboss/as/domain/management/logging/DomainManagementLogger.SECURITY_LOGGER:Lorg/jboss/as/domain/management/logging/DomainManagementLogger;
      41: ldc           #17                 // String Checking \'AuthorizeCallback\', authorized=false, authenticationID=%s, authorizationID=%s.
      43: aload_2
      44: invokevirtual #13                 // Method javax/security/sasl/AuthorizeCallback.getAuthenticationID:()Ljava/lang/String;
      47: aload_2
      48: invokevirtual #14                 // Method javax/security/sasl/AuthorizeCallback.getAuthorizationID:()Ljava/lang/String;
      51: invokeinterface #18,  4           // InterfaceMethod org/jboss/as/domain/management/logging/DomainManagementLogger.tracef:(Ljava/lang/String;Ljava/lang/Object;Ljava/lang/Object;)V
      56: aload_2
      57: iload_3
      58: invokevirtual #19                 // Method javax/security/sasl/AuthorizeCallback.setAuthorized:(Z)V
      61: return
      62: aconst_null
      63: astore_2
      64: aconst_null
      65: astore_3
      66: aconst_null
      67: astore        4
      69: aload_1
      70: astore        5
      72: aload         5
      74: arraylength
      75: istore        6
      77: iconst_0
      78: istore        7
      80: iload         7
      82: iload         6
      84: if_icmpge     173
      87: aload         5
      89: iload         7
      91: aaload
      92: astore        8
      94: aload         8
      96: instanceof    #20                 // class javax/security/auth/callback/NameCallback
      99: ifeq          111
     102: aload         8
     104: checkcast     #20                 // class javax/security/auth/callback/NameCallback
     107: astore_2
     108: goto          167
     111: aload         8
     113: instanceof    #21                 // class javax/security/sasl/RealmCallback
     116: ifeq          122
     119: goto          167
     122: aload         8
     124: instanceof    #22                 // class org/jboss/sasl/callback/VerifyPasswordCallback
     127: ifeq          139
     130: aload         8
     132: checkcast     #22                 // class org/jboss/sasl/callback/VerifyPasswordCallback
     135: astore_3
     136: goto          167
     139: aload         8
     141: instanceof    #23                 // class org/jboss/as/domain/management/security/SubjectCallback
     144: ifeq          157
     147: aload         8
     149: checkcast     #23                 // class org/jboss/as/domain/management/security/SubjectCallback
     152: astore        4
     154: goto          167
     157: new           #24                 // class javax/security/auth/callback/UnsupportedCallbackException
     160: dup
     161: aload         8
     163: invokespecial #25                 // Method javax/security/auth/callback/UnsupportedCallbackException."<init>":(Ljavax/security/auth/callback/Callback;)V
     166: athrow
     167: iinc          7, 1
     170: goto          80
     173: aload_2
     174: ifnonnull     196
     177: getstatic     #16                 // Field org/jboss/as/domain/management/logging/DomainManagementLogger.SECURITY_LOGGER:Lorg/jboss/as/domain/management/logging/DomainManagementLogger;
     180: ldc           #26                 // String No username supplied in Callbacks.
     182: invokeinterface #27,  2           // InterfaceMethod org/jboss/as/domain/management/logging/DomainManagementLogger.trace:(Ljava/lang/Object;)V
     187: getstatic     #28                 // Field org/jboss/as/domain/management/logging/DomainManagementLogger.ROOT_LOGGER:Lorg/jboss/as/domain/management/logging/DomainManagementLogger;
     190: invokeinterface #29,  1           // InterfaceMethod org/jboss/as/domain/management/logging/DomainManagementLogger.noUsername:()Ljava/io/IOException;
     195: athrow
     196: aload_2
     197: invokevirtual #30                 // Method javax/security/auth/callback/NameCallback.getDefaultName:()Ljava/lang/String;
     200: astore        5
     202: aload         5
     204: ifnull        215
     207: aload         5
     209: invokevirtual #31                 // Method java/lang/String.length:()I
     212: ifne          234
     215: getstatic     #16                 // Field org/jboss/as/domain/management/logging/DomainManagementLogger.SECURITY_LOGGER:Lorg/jboss/as/domain/management/logging/DomainManagementLogger;
     218: ldc           #32                 // String NameCallback either has no username or is 0 length.
     220: invokeinterface #27,  2           // InterfaceMethod org/jboss/as/domain/management/logging/DomainManagementLogger.trace:(Ljava/lang/Object;)V
     225: getstatic     #28                 // Field org/jboss/as/domain/management/logging/DomainManagementLogger.ROOT_LOGGER:Lorg/jboss/as/domain/management/logging/DomainManagementLogger;
     228: invokeinterface #29,  1           // InterfaceMethod org/jboss/as/domain/management/logging/DomainManagementLogger.noUsername:()Ljava/io/IOException;
     233: athrow
     234: aload_3
     235: ifnull        245
     238: aload_3
     239: invokevirtual #33                 // Method org/jboss/sasl/callback/VerifyPasswordCallback.getPassword:()Ljava/lang/String;
     242: ifnonnull     264
     245: getstatic     #16                 // Field org/jboss/as/domain/management/logging/DomainManagementLogger.SECURITY_LOGGER:Lorg/jboss/as/domain/management/logging/DomainManagementLogger;
     248: ldc           #34                 // String No password to verify.
     250: invokeinterface #27,  2           // InterfaceMethod org/jboss/as/domain/management/logging/DomainManagementLogger.trace:(Ljava/lang/Object;)V
     255: getstatic     #28                 // Field org/jboss/as/domain/management/logging/DomainManagementLogger.ROOT_LOGGER:Lorg/jboss/as/domain/management/logging/DomainManagementLogger;
     258: invokeinterface #35,  1           // InterfaceMethod org/jboss/as/domain/management/logging/DomainManagementLogger.noPassword:()Ljava/io/IOException;
     263: athrow
     264: aload_3
     265: invokevirtual #33                 // Method org/jboss/sasl/callback/VerifyPasswordCallback.getPassword:()Ljava/lang/String;
     268: invokevirtual #36                 // Method java/lang/String.toCharArray:()[C
     271: astore        6
     273: aload         4
     275: ifnull        294
     278: aload         4
     280: invokevirtual #37                 // Method org/jboss/as/domain/management/security/SubjectCallback.getSubject:()Ljavax/security/auth/Subject;
     283: ifnull        294
     286: aload         4
     288: invokevirtual #37                 // Method org/jboss/as/domain/management/security/SubjectCallback.getSubject:()Ljavax/security/auth/Subject;
     291: goto          301
     294: new           #38                 // class javax/security/auth/Subject
     297: dup
     298: invokespecial #39                 // Method javax/security/auth/Subject."<init>":()V
     301: astore        7
     303: aload_0
     304: getfield      #5                  // Field securityManagerValue:Lorg/jboss/msc/value/InjectedValue;
     307: invokevirtual #40                 // Method org/jboss/msc/value/InjectedValue.getOptionalValue:()Ljava/lang/Object;
     310: checkcast     #41                 // class org/jboss/as/core/security/ServerSecurityManager
     313: dup
     314: astore        8
     316: ifnull        589
     319: aload         8
     321: aload_0
     322: getfield      #7                  // Field name:Ljava/lang/String;
     325: aload         5
     327: aload         6
     329: aload         7
     331: invokeinterface #42,  5           // InterfaceMethod org/jboss/as/core/security/ServerSecurityManager.push:(Ljava/lang/String;Ljava/lang/String;[CLjavax/security/auth/Subject;)V
     336: aload         8
     338: invokeinterface #43,  1           // InterfaceMethod org/jboss/as/core/security/ServerSecurityManager.authenticate:()V
     343: aload_3
     344: iconst_1
     345: invokevirtual #44                 // Method org/jboss/sasl/callback/VerifyPasswordCallback.setVerified:(Z)V
     348: aload         8
     350: invokeinterface #45,  1           // InterfaceMethod org/jboss/as/core/security/ServerSecurityManager.getSubject:()Ljavax/security/auth/Subject;
     355: astore        7
     357: aload         7
     359: invokevirtual #46                 // Method javax/security/auth/Subject.getPrivateCredentials:()Ljava/util/Set;
     362: new           #47                 // class org/jboss/as/domain/management/security/PasswordCredential
     365: dup
     366: aload         5
     368: aload         6
     370: invokespecial #48                 // Method org/jboss/as/domain/management/security/PasswordCredential."<init>":(Ljava/lang/String;[C)V
     373: invokeinterface #49,  2           // InterfaceMethod java/util/Set.add:(Ljava/lang/Object;)Z
     378: pop
     379: aload_0
     380: getfield      #8                  // Field assignGroups:Z
     383: ifeq          503
     386: aload         7
     388: invokevirtual #50                 // Method javax/security/auth/Subject.getPrincipals:()Ljava/util/Set;
     391: astore        9
     393: aload         7
     395: ldc           #51                 // class org/jboss/security/SimpleGroup
     397: invokevirtual #52                 // Method javax/security/auth/Subject.getPrincipals:(Ljava/lang/Class;)Ljava/util/Set;
     400: astore        10
     402: aload         10
     404: invokeinterface #53,  1           // InterfaceMethod java/util/Set.iterator:()Ljava/util/Iterator;
     409: astore        11
     411: aload         11
     413: invokeinterface #54,  1           // InterfaceMethod java/util/Iterator.hasNext:()Z
     418: ifeq          503
     421: aload         11
     423: invokeinterface #55,  1           // InterfaceMethod java/util/Iterator.next:()Ljava/lang/Object;
     428: checkcast     #51                 // class org/jboss/security/SimpleGroup
     431: astore        12
     433: ldc           #56                 // String Roles
     435: aload         12
     437: invokevirtual #57                 // Method org/jboss/security/SimpleGroup.getName:()Ljava/lang/String;
     440: invokevirtual #15                 // Method java/lang/String.equals:(Ljava/lang/Object;)Z
     443: ifeq          500
     446: aload         12
     448: invokevirtual #58                 // Method org/jboss/security/SimpleGroup.members:()Ljava/util/Enumeration;
     451: astore        13
     453: aload         13
     455: invokeinterface #59,  1           // InterfaceMethod java/util/Enumeration.hasMoreElements:()Z
     460: ifeq          500
     463: aload         9
     465: new           #60                 // class org/jboss/as/core/security/RealmGroup
     468: dup
     469: aload_0
     470: getfield      #6                  // Field realm:Ljava/lang/String;
     473: aload         13
     475: invokeinterface #61,  1           // InterfaceMethod java/util/Enumeration.nextElement:()Ljava/lang/Object;
     480: checkcast     #62                 // class java/security/Principal
     483: invokeinterface #63,  1           // InterfaceMethod java/security/Principal.getName:()Ljava/lang/String;
     488: invokespecial #64                 // Method org/jboss/as/core/security/RealmGroup."<init>":(Ljava/lang/String;Ljava/lang/String;)V
     491: invokeinterface #49,  2           // InterfaceMethod java/util/Set.add:(Ljava/lang/Object;)Z
     496: pop
     497: goto          453
     500: goto          411
     503: aload         4
     505: ifnull        515
     508: aload         4
     510: aload         7
     512: invokevirtual #65                 // Method org/jboss/as/domain/management/security/SubjectCallback.setSubject:(Ljavax/security/auth/Subject;)V
     515: aload         8
     517: invokeinterface #66,  1           // InterfaceMethod org/jboss/as/core/security/ServerSecurityManager.pop:()V
     522: goto          586
     525: astore        9
     527: getstatic     #16                 // Field org/jboss/as/domain/management/logging/DomainManagementLogger.SECURITY_LOGGER:Lorg/jboss/as/domain/management/logging/DomainManagementLogger;
     530: new           #68                 // class java/lang/StringBuilder
     533: dup
     534: invokespecial #69                 // Method java/lang/StringBuilder."<init>":()V
     537: ldc           #70                 // String Failed to verify password in JAAS callbackhandler
     539: invokevirtual #71                 // Method java/lang/StringBuilder.append:(Ljava/lang/String;)Ljava/lang/StringBuilder;
     542: aload_0
     543: getfield      #7                  // Field name:Ljava/lang/String;
     546: invokevirtual #71                 // Method java/lang/StringBuilder.append:(Ljava/lang/String;)Ljava/lang/StringBuilder;
     549: invokevirtual #72                 // Method java/lang/StringBuilder.toString:()Ljava/lang/String;
     552: aload         9
     554: invokeinterface #73,  3           // InterfaceMethod org/jboss/as/domain/management/logging/DomainManagementLogger.debug:(Ljava/lang/Object;Ljava/lang/Throwable;)V
     559: aload_3
     560: iconst_0
     561: invokevirtual #44                 // Method org/jboss/sasl/callback/VerifyPasswordCallback.setVerified:(Z)V
     564: aload         8
     566: invokeinterface #66,  1           // InterfaceMethod org/jboss/as/core/security/ServerSecurityManager.pop:()V
     571: goto          586
     574: astore        14
     576: aload         8
     578: invokeinterface #66,  1           // InterfaceMethod org/jboss/as/core/security/ServerSecurityManager.pop:()V
     583: aload         14
     585: athrow
     586: goto          826
     589: new           #74                 // class javax/security/auth/login/LoginContext
     592: dup
     593: aload_0
     594: getfield      #7                  // Field name:Ljava/lang/String;
     597: aload         7
     599: new           #75                 // class org/jboss/as/domain/management/security/JaasCallbackHandler$1
     602: dup
     603: aload_0
     604: aload         5
     606: aload         6
     608: invokespecial #76                 // Method org/jboss/as/domain/management/security/JaasCallbackHandler$1."<init>":(Lorg/jboss/as/domain/management/security/JaasCallbackHandler;Ljava/lang/String;[C)V
     611: invokespecial #77                 // Method javax/security/auth/login/LoginContext."<init>":(Ljava/lang/String;Ljavax/security/auth/Subject;Ljavax/security/auth/callback/CallbackHandler;)V
     614: astore        9
     616: aload         9
     618: invokevirtual #78                 // Method javax/security/auth/login/LoginContext.login:()V
     621: aload_3
     622: iconst_1
     623: invokevirtual #44                 // Method org/jboss/sasl/callback/VerifyPasswordCallback.setVerified:(Z)V
     626: aload         7
     628: invokevirtual #46                 // Method javax/security/auth/Subject.getPrivateCredentials:()Ljava/util/Set;
     631: new           #47                 // class org/jboss/as/domain/management/security/PasswordCredential
     634: dup
     635: aload         5
     637: aload         6
     639: invokespecial #48                 // Method org/jboss/as/domain/management/security/PasswordCredential."<init>":(Ljava/lang/String;[C)V
     642: invokeinterface #49,  2           // InterfaceMethod java/util/Set.add:(Ljava/lang/Object;)Z
     647: pop
     648: aload_0
     649: getfield      #8                  // Field assignGroups:Z
     652: ifeq          772
     655: aload         7
     657: invokevirtual #50                 // Method javax/security/auth/Subject.getPrincipals:()Ljava/util/Set;
     660: astore        10
     662: aload         7
     664: ldc           #51                 // class org/jboss/security/SimpleGroup
     666: invokevirtual #52                 // Method javax/security/auth/Subject.getPrincipals:(Ljava/lang/Class;)Ljava/util/Set;
     669: astore        11
     671: aload         11
     673: invokeinterface #53,  1           // InterfaceMethod java/util/Set.iterator:()Ljava/util/Iterator;
     678: astore        12
     680: aload         12
     682: invokeinterface #54,  1           // InterfaceMethod java/util/Iterator.hasNext:()Z
     687: ifeq          772
     690: aload         12
     692: invokeinterface #55,  1           // InterfaceMethod java/util/Iterator.next:()Ljava/lang/Object;
     697: checkcast     #51                 // class org/jboss/security/SimpleGroup
     700: astore        13
     702: ldc           #56                 // String Roles
     704: aload         13
     706: invokevirtual #57                 // Method org/jboss/security/SimpleGroup.getName:()Ljava/lang/String;
     709: invokevirtual #15                 // Method java/lang/String.equals:(Ljava/lang/Object;)Z
     712: ifeq          769
     715: aload         13
     717: invokevirtual #58                 // Method org/jboss/security/SimpleGroup.members:()Ljava/util/Enumeration;
     720: astore        14
     722: aload         14
     724: invokeinterface #59,  1           // InterfaceMethod java/util/Enumeration.hasMoreElements:()Z
     729: ifeq          769
     732: aload         10
     734: new           #60                 // class org/jboss/as/core/security/RealmGroup
     737: dup
     738: aload_0
     739: getfield      #6                  // Field realm:Ljava/lang/String;
     742: aload         14
     744: invokeinterface #61,  1           // InterfaceMethod java/util/Enumeration.nextElement:()Ljava/lang/Object;
     749: checkcast     #62                 // class java/security/Principal
     752: invokeinterface #63,  1           // InterfaceMethod java/security/Principal.getName:()Ljava/lang/String;
     757: invokespecial #64                 // Method org/jboss/as/core/security/RealmGroup."<init>":(Ljava/lang/String;Ljava/lang/String;)V
     760: invokeinterface #49,  2           // InterfaceMethod java/util/Set.add:(Ljava/lang/Object;)Z
     765: pop
     766: goto          722
     769: goto          680
     772: aload         4
     774: ifnull        784
     777: aload         4
     779: aload         7
     781: invokevirtual #65                 // Method org/jboss/as/domain/management/security/SubjectCallback.setSubject:(Ljavax/security/auth/Subject;)V
     784: goto          826
     787: astore        9
     789: getstatic     #16                 // Field org/jboss/as/domain/management/logging/DomainManagementLogger.SECURITY_LOGGER:Lorg/jboss/as/domain/management/logging/DomainManagementLogger;
     792: new           #68                 // class java/lang/StringBuilder
     795: dup
     796: invokespecial #69                 // Method java/lang/StringBuilder."<init>":()V
     799: ldc           #80                 // String Login failed in JAAS callbackhandler
     801: invokevirtual #71                 // Method java/lang/StringBuilder.append:(Ljava/lang/String;)Ljava/lang/StringBuilder;
     804: aload_0
     805: getfield      #7                  // Field name:Ljava/lang/String;
     808: invokevirtual #71                 // Method java/lang/StringBuilder.append:(Ljava/lang/String;)Ljava/lang/StringBuilder;
     811: invokevirtual #72                 // Method java/lang/StringBuilder.toString:()Ljava/lang/String;
     814: aload         9
     816: invokeinterface #73,  3           // InterfaceMethod org/jboss/as/domain/management/logging/DomainManagementLogger.debug:(Ljava/lang/Object;Ljava/lang/Throwable;)V
     821: aload_3
     822: iconst_0
     823: invokevirtual #44                 // Method org/jboss/sasl/callback/VerifyPasswordCallback.setVerified:(Z)V
     826: return
    Exception table:
       from    to  target type
         319   515   525   Class java/lang/SecurityException
         319   515   574   any
         525   564   574   any
         574   576   574   any
         589   784   787   Class javax/security/auth/login/LoginException

  public void start(org.jboss.msc.service.StartContext) throws org.jboss.msc.service.StartException;
    Code:
       0: return

  public void stop(org.jboss.msc.service.StopContext);
    Code:
       0: return

  public org.jboss.msc.value.InjectedValue<org.jboss.as.core.security.ServerSecurityManager> getSecurityManagerValue();
    Code:
       0: aload_0
       1: getfield      #5                  // Field securityManagerValue:Lorg/jboss/msc/value/InjectedValue;
       4: areturn

  public org.jboss.as.domain.management.security.CallbackHandlerService getValue() throws java.lang.IllegalStateException, java.lang.IllegalArgumentException;
    Code:
       0: aload_0
       1: areturn

  public java.lang.Object getValue() throws java.lang.IllegalStateException, java.lang.IllegalArgumentException;
    Code:
       0: aload_0
       1: invokevirtual #81                 // Method getValue:()Lorg/jboss/as/domain/management/security/CallbackHandlerService;
       4: areturn

  static {};
    Code:
       0: new           #82                 // class java/util/HashMap
       3: dup
       4: iconst_2
       5: invokespecial #83                 // Method java/util/HashMap."<init>":(I)V
       8: astore_0
       9: aload_0
      10: ldc           #84                 // String org.jboss.as.domain.management.subject_callback_supported
      12: getstatic     #85                 // Field java/lang/Boolean.TRUE:Ljava/lang/Boolean;
      15: invokevirtual #86                 // Method java/lang/Boolean.toString:()Ljava/lang/String;
      18: invokeinterface #87,  3           // InterfaceMethod java/util/Map.put:(Ljava/lang/Object;Ljava/lang/Object;)Ljava/lang/Object;
      23: pop
      24: aload_0
      25: ldc           #88                 // String org.jboss.as.domain.management.verify_password_callback_supported
      27: getstatic     #85                 // Field java/lang/Boolean.TRUE:Ljava/lang/Boolean;
      30: invokevirtual #86                 // Method java/lang/Boolean.toString:()Ljava/lang/String;
      33: invokeinterface #87,  3           // InterfaceMethod java/util/Map.put:(Ljava/lang/Object;Ljava/lang/Object;)Ljava/lang/Object;
      38: pop
      39: aload_0
      40: invokestatic  #89                 // Method java/util/Collections.unmodifiableMap:(Ljava/util/Map;)Ljava/util/Map;
      43: putstatic     #11                 // Field configurationOptions:Ljava/util/Map;
      46: return
}
