Compiled from "ProviderTrustManagerService.java"
public class org.jboss.as.domain.management.security.ProviderTrustManagerService extends org.jboss.as.domain.management.security.AbstractTrustManagerService {
  private volatile java.lang.String provider;

  private volatile char[] storePassword;

  private volatile java.security.KeyStore theKeyStore;

  org.jboss.as.domain.management.security.ProviderTrustManagerService(java.lang.String, char[]);
    Code:
       0: aload_0
       1: invokespecial #1                  // Method org/jboss/as/domain/management/security/AbstractTrustManagerService."<init>":()V
       4: aload_0
       5: aload_1
       6: putfield      #2                  // Field provider:Ljava/lang/String;
       9: aload_0
      10: aload_2
      11: putfield      #3                  // Field storePassword:[C
      14: return

  public void start(org.jboss.msc.service.StartContext) throws org.jboss.msc.service.StartException;
    Code:
       0: aload_0
       1: getfield      #2                  // Field provider:Ljava/lang/String;
       4: invokestatic  #4                  // Method java/security/KeyStore.getInstance:(Ljava/lang/String;)Ljava/security/KeyStore;
       7: astore_2
       8: aload_2
       9: aconst_null
      10: aload_0
      11: getfield      #3                  // Field storePassword:[C
      14: invokevirtual #5                  // Method java/security/KeyStore.load:(Ljava/io/InputStream;[C)V
      17: aload_0
      18: aload_2
      19: putfield      #6                  // Field theKeyStore:Ljava/security/KeyStore;
      22: goto          69
      25: astore_2
      26: getstatic     #8                  // Field org/jboss/as/domain/management/logging/DomainManagementLogger.ROOT_LOGGER:Lorg/jboss/as/domain/management/logging/DomainManagementLogger;
      29: aload_2
      30: invokeinterface #9,  2            // InterfaceMethod org/jboss/as/domain/management/logging/DomainManagementLogger.unableToStart:(Ljava/lang/Throwable;)Lorg/jboss/msc/service/StartException;
      35: athrow
      36: astore_2
      37: getstatic     #8                  // Field org/jboss/as/domain/management/logging/DomainManagementLogger.ROOT_LOGGER:Lorg/jboss/as/domain/management/logging/DomainManagementLogger;
      40: aload_2
      41: invokeinterface #9,  2            // InterfaceMethod org/jboss/as/domain/management/logging/DomainManagementLogger.unableToStart:(Ljava/lang/Throwable;)Lorg/jboss/msc/service/StartException;
      46: athrow
      47: astore_2
      48: getstatic     #8                  // Field org/jboss/as/domain/management/logging/DomainManagementLogger.ROOT_LOGGER:Lorg/jboss/as/domain/management/logging/DomainManagementLogger;
      51: aload_2
      52: invokeinterface #9,  2            // InterfaceMethod org/jboss/as/domain/management/logging/DomainManagementLogger.unableToStart:(Ljava/lang/Throwable;)Lorg/jboss/msc/service/StartException;
      57: athrow
      58: astore_2
      59: getstatic     #8                  // Field org/jboss/as/domain/management/logging/DomainManagementLogger.ROOT_LOGGER:Lorg/jboss/as/domain/management/logging/DomainManagementLogger;
      62: aload_2
      63: invokeinterface #9,  2            // InterfaceMethod org/jboss/as/domain/management/logging/DomainManagementLogger.unableToStart:(Ljava/lang/Throwable;)Lorg/jboss/msc/service/StartException;
      68: athrow
      69: aload_0
      70: aload_1
      71: invokespecial #13                 // Method org/jboss/as/domain/management/security/AbstractTrustManagerService.start:(Lorg/jboss/msc/service/StartContext;)V
      74: return
    Exception table:
       from    to  target type
           0    22    25   Class java/security/KeyStoreException
           0    22    36   Class java/security/NoSuchAlgorithmException
           0    22    47   Class java/security/cert/CertificateException
           0    22    58   Class java/io/IOException

  public void stop(org.jboss.msc.service.StopContext);
    Code:
       0: aload_0
       1: aload_1
       2: invokespecial #14                 // Method org/jboss/as/domain/management/security/AbstractTrustManagerService.stop:(Lorg/jboss/msc/service/StopContext;)V
       5: aload_0
       6: aconst_null
       7: putfield      #6                  // Field theKeyStore:Ljava/security/KeyStore;
      10: return

  protected java.security.KeyStore loadTrustStore();
    Code:
       0: aload_0
       1: getfield      #6                  // Field theKeyStore:Ljava/security/KeyStore;
       4: areturn

  public javax.net.ssl.TrustManager[] getValue() throws java.lang.IllegalStateException, java.lang.IllegalArgumentException;
    Code:
       0: aload_0
       1: invokespecial #15                 // Method org/jboss/as/domain/management/security/AbstractTrustManagerService.getValue:()[Ljavax/net/ssl/TrustManager;
       4: areturn
}
