Compiled from "WrapperSSLContext.java"
class org.jboss.as.domain.management.security.WrapperSSLContext$WrapperSpi extends javax.net.ssl.SSLContextSpi {
  private final java.lang.String[] enabledCipherSuites;

  private final java.lang.String[] enabledProtocols;

  private final javax.net.ssl.SSLContext wrapped;

  private org.jboss.as.domain.management.security.WrapperSSLContext$WrapperSpi(javax.net.ssl.SSLContext, java.lang.String[], java.lang.String[]);
    Code:
       0: aload_0
       1: invokespecial #4                  // Method javax/net/ssl/SSLContextSpi."<init>":()V
       4: aload_0
       5: aload_1
       6: putfield      #5                  // Field wrapped:Ljavax/net/ssl/SSLContext;
       9: aload_0
      10: aload_2
      11: putfield      #2                  // Field enabledCipherSuites:[Ljava/lang/String;
      14: aload_0
      15: aload_3
      16: putfield      #1                  // Field enabledProtocols:[Ljava/lang/String;
      19: return

  protected javax.net.ssl.SSLEngine engineCreateSSLEngine();
    Code:
       0: aload_0
       1: getfield      #5                  // Field wrapped:Ljavax/net/ssl/SSLContext;
       4: invokevirtual #6                  // Method javax/net/ssl/SSLContext.createSSLEngine:()Ljavax/net/ssl/SSLEngine;
       7: astore_1
       8: aload_0
       9: aload_1
      10: invokespecial #7                  // Method setSslParams:(Ljavax/net/ssl/SSLEngine;)V
      13: aload_1
      14: areturn

  protected javax.net.ssl.SSLEngine engineCreateSSLEngine(java.lang.String, int);
    Code:
       0: aload_0
       1: getfield      #5                  // Field wrapped:Ljavax/net/ssl/SSLContext;
       4: aload_1
       5: iload_2
       6: invokevirtual #8                  // Method javax/net/ssl/SSLContext.createSSLEngine:(Ljava/lang/String;I)Ljavax/net/ssl/SSLEngine;
       9: astore_3
      10: aload_0
      11: aload_3
      12: invokespecial #7                  // Method setSslParams:(Ljavax/net/ssl/SSLEngine;)V
      15: aload_3
      16: areturn

  private void setSslParams(javax.net.ssl.SSLEngine);
    Code:
       0: aload_0
       1: getfield      #2                  // Field enabledCipherSuites:[Ljava/lang/String;
       4: arraylength
       5: ifle          16
       8: aload_1
       9: aload_0
      10: getfield      #2                  // Field enabledCipherSuites:[Ljava/lang/String;
      13: invokevirtual #9                  // Method javax/net/ssl/SSLEngine.setEnabledCipherSuites:([Ljava/lang/String;)V
      16: aload_0
      17: getfield      #1                  // Field enabledProtocols:[Ljava/lang/String;
      20: arraylength
      21: ifle          32
      24: aload_1
      25: aload_0
      26: getfield      #1                  // Field enabledProtocols:[Ljava/lang/String;
      29: invokevirtual #10                 // Method javax/net/ssl/SSLEngine.setEnabledProtocols:([Ljava/lang/String;)V
      32: return

  protected javax.net.ssl.SSLSessionContext engineGetClientSessionContext();
    Code:
       0: aload_0
       1: getfield      #5                  // Field wrapped:Ljavax/net/ssl/SSLContext;
       4: invokevirtual #11                 // Method javax/net/ssl/SSLContext.getClientSessionContext:()Ljavax/net/ssl/SSLSessionContext;
       7: areturn

  protected javax.net.ssl.SSLSessionContext engineGetServerSessionContext();
    Code:
       0: aload_0
       1: getfield      #5                  // Field wrapped:Ljavax/net/ssl/SSLContext;
       4: invokevirtual #12                 // Method javax/net/ssl/SSLContext.getServerSessionContext:()Ljavax/net/ssl/SSLSessionContext;
       7: areturn

  protected javax.net.ssl.SSLServerSocketFactory engineGetServerSocketFactory();
    Code:
       0: new           #13                 // class org/jboss/as/domain/management/security/WrapperSSLContext$WrapperSpi$WrapperSSLServerSocketFactory
       3: dup
       4: aload_0
       5: aload_0
       6: getfield      #5                  // Field wrapped:Ljavax/net/ssl/SSLContext;
       9: invokevirtual #14                 // Method javax/net/ssl/SSLContext.getServerSocketFactory:()Ljavax/net/ssl/SSLServerSocketFactory;
      12: aconst_null
      13: invokespecial #15                 // Method org/jboss/as/domain/management/security/WrapperSSLContext$WrapperSpi$WrapperSSLServerSocketFactory."<init>":(Lorg/jboss/as/domain/management/security/WrapperSSLContext$WrapperSpi;Ljavax/net/ssl/SSLServerSocketFactory;Lorg/jboss/as/domain/management/security/WrapperSSLContext$1;)V
      16: areturn

  protected javax.net.ssl.SSLSocketFactory engineGetSocketFactory();
    Code:
       0: new           #16                 // class org/jboss/as/domain/management/security/WrapperSSLContext$WrapperSpi$WrapperSSLSocketFactory
       3: dup
       4: aload_0
       5: aload_0
       6: getfield      #5                  // Field wrapped:Ljavax/net/ssl/SSLContext;
       9: invokevirtual #17                 // Method javax/net/ssl/SSLContext.getSocketFactory:()Ljavax/net/ssl/SSLSocketFactory;
      12: aconst_null
      13: invokespecial #18                 // Method org/jboss/as/domain/management/security/WrapperSSLContext$WrapperSpi$WrapperSSLSocketFactory."<init>":(Lorg/jboss/as/domain/management/security/WrapperSSLContext$WrapperSpi;Ljavax/net/ssl/SSLSocketFactory;Lorg/jboss/as/domain/management/security/WrapperSSLContext$1;)V
      16: areturn

  protected void engineInit(javax.net.ssl.KeyManager[], javax.net.ssl.TrustManager[], java.security.SecureRandom) throws java.security.KeyManagementException;
    Code:
       0: aload_0
       1: getfield      #5                  // Field wrapped:Ljavax/net/ssl/SSLContext;
       4: aload_1
       5: aload_2
       6: aload_3
       7: invokevirtual #19                 // Method javax/net/ssl/SSLContext.init:([Ljavax/net/ssl/KeyManager;[Ljavax/net/ssl/TrustManager;Ljava/security/SecureRandom;)V
      10: return

  org.jboss.as.domain.management.security.WrapperSSLContext$WrapperSpi(javax.net.ssl.SSLContext, java.lang.String[], java.lang.String[], org.jboss.as.domain.management.security.WrapperSSLContext$1);
    Code:
       0: aload_0
       1: aload_1
       2: aload_2
       3: aload_3
       4: invokespecial #3                  // Method "<init>":(Ljavax/net/ssl/SSLContext;[Ljava/lang/String;[Ljava/lang/String;)V
       7: return

  static java.lang.String[] access$300(org.jboss.as.domain.management.security.WrapperSSLContext$WrapperSpi);
    Code:
       0: aload_0
       1: getfield      #2                  // Field enabledCipherSuites:[Ljava/lang/String;
       4: areturn

  static java.lang.String[] access$400(org.jboss.as.domain.management.security.WrapperSSLContext$WrapperSpi);
    Code:
       0: aload_0
       1: getfield      #1                  // Field enabledProtocols:[Ljava/lang/String;
       4: areturn
}
