Compiled from "AutoConfigurationReportEndpoint.java"
public class org.springframework.boot.actuate.endpoint.AutoConfigurationReportEndpoint extends org.springframework.boot.actuate.endpoint.AbstractEndpoint<org.springframework.boot.actuate.endpoint.AutoConfigurationReportEndpoint$Report> {
  private org.springframework.boot.autoconfigure.condition.ConditionEvaluationReport autoConfigurationReport;

  public org.springframework.boot.actuate.endpoint.AutoConfigurationReportEndpoint();
    Code:
       0: aload_0
       1: ldc           #1                  // String autoconfig
       3: invokespecial #2                  // Method org/springframework/boot/actuate/endpoint/AbstractEndpoint."<init>":(Ljava/lang/String;)V
       6: return

  public org.springframework.boot.actuate.endpoint.AutoConfigurationReportEndpoint$Report invoke();
    Code:
       0: new           #3                  // class org/springframework/boot/actuate/endpoint/AutoConfigurationReportEndpoint$Report
       3: dup
       4: aload_0
       5: getfield      #4                  // Field autoConfigurationReport:Lorg/springframework/boot/autoconfigure/condition/ConditionEvaluationReport;
       8: invokespecial #5                  // Method org/springframework/boot/actuate/endpoint/AutoConfigurationReportEndpoint$Report."<init>":(Lorg/springframework/boot/autoconfigure/condition/ConditionEvaluationReport;)V
      11: areturn

  public java.lang.Object invoke();
    Code:
       0: aload_0
       1: invokevirtual #6                  // Method invoke:()Lorg/springframework/boot/actuate/endpoint/AutoConfigurationReportEndpoint$Report;
       4: areturn
}
