Compiled from "BeansEndpoint.java"
public class org.springframework.boot.actuate.endpoint.BeansEndpoint extends org.springframework.boot.actuate.endpoint.AbstractEndpoint<java.util.List<java.lang.Object>> implements org.springframework.context.ApplicationContextAware {
  private final org.springframework.context.support.LiveBeansView liveBeansView;

  private final org.springframework.boot.json.JsonParser parser;

  public org.springframework.boot.actuate.endpoint.BeansEndpoint();
    Code:
       0: aload_0
       1: ldc           #1                  // String beans
       3: invokespecial #2                  // Method org/springframework/boot/actuate/endpoint/AbstractEndpoint."<init>":(Ljava/lang/String;)V
       6: aload_0
       7: new           #3                  // class org/springframework/context/support/LiveBeansView
      10: dup
      11: invokespecial #4                  // Method org/springframework/context/support/LiveBeansView."<init>":()V
      14: putfield      #5                  // Field liveBeansView:Lorg/springframework/context/support/LiveBeansView;
      17: aload_0
      18: invokestatic  #6                  // Method org/springframework/boot/json/JsonParserFactory.getJsonParser:()Lorg/springframework/boot/json/JsonParser;
      21: putfield      #7                  // Field parser:Lorg/springframework/boot/json/JsonParser;
      24: return

  public void setApplicationContext(org.springframework.context.ApplicationContext) throws org.springframework.beans.BeansException;
    Code:
       0: aload_1
       1: invokeinterface #8,  1            // InterfaceMethod org/springframework/context/ApplicationContext.getEnvironment:()Lorg/springframework/core/env/Environment;
       6: ldc           #9                  // String spring.liveBeansView.mbeanDomain
       8: invokeinterface #10,  2           // InterfaceMethod org/springframework/core/env/Environment.getProperty:(Ljava/lang/String;)Ljava/lang/String;
      13: ifnonnull     24
      16: aload_0
      17: getfield      #5                  // Field liveBeansView:Lorg/springframework/context/support/LiveBeansView;
      20: aload_1
      21: invokevirtual #11                 // Method org/springframework/context/support/LiveBeansView.setApplicationContext:(Lorg/springframework/context/ApplicationContext;)V
      24: return

  public java.util.List<java.lang.Object> invoke();
    Code:
       0: aload_0
       1: getfield      #7                  // Field parser:Lorg/springframework/boot/json/JsonParser;
       4: aload_0
       5: getfield      #5                  // Field liveBeansView:Lorg/springframework/context/support/LiveBeansView;
       8: invokevirtual #12                 // Method org/springframework/context/support/LiveBeansView.getSnapshotAsJson:()Ljava/lang/String;
      11: invokeinterface #13,  2           // InterfaceMethod org/springframework/boot/json/JsonParser.parseList:(Ljava/lang/String;)Ljava/util/List;
      16: areturn

  public java.lang.Object invoke();
    Code:
       0: aload_0
       1: invokevirtual #14                 // Method invoke:()Ljava/util/List;
       4: areturn
}
