Compiled from "DumpEndpoint.java"
public class org.springframework.boot.actuate.endpoint.DumpEndpoint extends org.springframework.boot.actuate.endpoint.AbstractEndpoint<java.util.List<java.lang.management.ThreadInfo>> {
  public org.springframework.boot.actuate.endpoint.DumpEndpoint();
    Code:
       0: aload_0
       1: ldc           #1                  // String dump
       3: invokespecial #2                  // Method org/springframework/boot/actuate/endpoint/AbstractEndpoint."<init>":(Ljava/lang/String;)V
       6: return

  public java.util.List<java.lang.management.ThreadInfo> invoke();
    Code:
       0: invokestatic  #3                  // Method java/lang/management/ManagementFactory.getThreadMXBean:()Ljava/lang/management/ThreadMXBean;
       3: iconst_1
       4: iconst_1
       5: invokeinterface #4,  3            // InterfaceMethod java/lang/management/ThreadMXBean.dumpAllThreads:(ZZ)[Ljava/lang/management/ThreadInfo;
      10: invokestatic  #5                  // Method java/util/Arrays.asList:([Ljava/lang/Object;)Ljava/util/List;
      13: areturn

  public java.lang.Object invoke();
    Code:
       0: aload_0
       1: invokevirtual #6                  // Method invoke:()Ljava/util/List;
       4: areturn
}
