Compiled from "DefaultAlgorithmSuiteLoader.java"
public class org.apache.cxf.ws.security.policy.custom.DefaultAlgorithmSuiteLoader$GCMAlgorithmSuite extends org.apache.wss4j.policy.model.AlgorithmSuite {
  org.apache.cxf.ws.security.policy.custom.DefaultAlgorithmSuiteLoader$GCMAlgorithmSuite(org.apache.wss4j.policy.SPConstants$SPVersion, org.apache.neethi.Policy);
    Code:
       0: aload_0
       1: aload_1
       2: aload_2
       3: invokespecial #1                  // Method org/apache/wss4j/policy/model/AlgorithmSuite."<init>":(Lorg/apache/wss4j/policy/SPConstants$SPVersion;Lorg/apache/neethi/Policy;)V
       6: return

  protected org.apache.wss4j.policy.model.AbstractSecurityAssertion cloneAssertion(org.apache.neethi.Policy);
    Code:
       0: new           #2                  // class org/apache/cxf/ws/security/policy/custom/DefaultAlgorithmSuiteLoader$GCMAlgorithmSuite
       3: dup
       4: aload_0
       5: invokevirtual #3                  // Method getVersion:()Lorg/apache/wss4j/policy/SPConstants$SPVersion;
       8: aload_1
       9: invokespecial #4                  // Method "<init>":(Lorg/apache/wss4j/policy/SPConstants$SPVersion;Lorg/apache/neethi/Policy;)V
      12: areturn

  protected void parseCustomAssertion(org.apache.neethi.Assertion);
    Code:
       0: aload_1
       1: invokeinterface #5,  1            // InterfaceMethod org/apache/neethi/Assertion.getName:()Ljavax/xml/namespace/QName;
       6: invokevirtual #6                  // Method javax/xml/namespace/QName.getLocalPart:()Ljava/lang/String;
       9: astore_2
      10: aload_1
      11: invokeinterface #5,  1            // InterfaceMethod org/apache/neethi/Assertion.getName:()Ljavax/xml/namespace/QName;
      16: invokevirtual #7                  // Method javax/xml/namespace/QName.getNamespaceURI:()Ljava/lang/String;
      19: astore_3
      20: ldc           #8                  // String http://cxf.apache.org/custom/security-policy
      22: aload_3
      23: invokevirtual #9                  // Method java/lang/String.equals:(Ljava/lang/Object;)Z
      26: ifne          30
      29: return
      30: ldc           #10                 // String Basic128GCM
      32: aload_2
      33: invokevirtual #9                  // Method java/lang/String.equals:(Ljava/lang/Object;)Z
      36: ifeq          67
      39: aload_0
      40: getstatic     #11                 // Field algorithmSuiteTypes:Ljava/util/Map;
      43: ldc           #10                 // String Basic128GCM
      45: invokeinterface #12,  2           // InterfaceMethod java/util/Map.get:(Ljava/lang/Object;)Ljava/lang/Object;
      50: checkcast     #13                 // class org/apache/wss4j/policy/model/AlgorithmSuite$AlgorithmSuiteType
      53: invokevirtual #14                 // Method setAlgorithmSuiteType:(Lorg/apache/wss4j/policy/model/AlgorithmSuite$AlgorithmSuiteType;)V
      56: aload_0
      57: invokevirtual #15                 // Method getAlgorithmSuiteType:()Lorg/apache/wss4j/policy/model/AlgorithmSuite$AlgorithmSuiteType;
      60: aload_3
      61: invokevirtual #16                 // Method org/apache/wss4j/policy/model/AlgorithmSuite$AlgorithmSuiteType.setNamespace:(Ljava/lang/String;)V
      64: goto          138
      67: ldc           #17                 // String Basic192GCM
      69: aload_2
      70: invokevirtual #9                  // Method java/lang/String.equals:(Ljava/lang/Object;)Z
      73: ifeq          104
      76: aload_0
      77: getstatic     #11                 // Field algorithmSuiteTypes:Ljava/util/Map;
      80: ldc           #17                 // String Basic192GCM
      82: invokeinterface #12,  2           // InterfaceMethod java/util/Map.get:(Ljava/lang/Object;)Ljava/lang/Object;
      87: checkcast     #13                 // class org/apache/wss4j/policy/model/AlgorithmSuite$AlgorithmSuiteType
      90: invokevirtual #14                 // Method setAlgorithmSuiteType:(Lorg/apache/wss4j/policy/model/AlgorithmSuite$AlgorithmSuiteType;)V
      93: aload_0
      94: invokevirtual #15                 // Method getAlgorithmSuiteType:()Lorg/apache/wss4j/policy/model/AlgorithmSuite$AlgorithmSuiteType;
      97: aload_3
      98: invokevirtual #16                 // Method org/apache/wss4j/policy/model/AlgorithmSuite$AlgorithmSuiteType.setNamespace:(Ljava/lang/String;)V
     101: goto          138
     104: ldc           #18                 // String Basic256GCM
     106: aload_2
     107: invokevirtual #9                  // Method java/lang/String.equals:(Ljava/lang/Object;)Z
     110: ifeq          138
     113: aload_0
     114: getstatic     #11                 // Field algorithmSuiteTypes:Ljava/util/Map;
     117: ldc           #18                 // String Basic256GCM
     119: invokeinterface #12,  2           // InterfaceMethod java/util/Map.get:(Ljava/lang/Object;)Ljava/lang/Object;
     124: checkcast     #13                 // class org/apache/wss4j/policy/model/AlgorithmSuite$AlgorithmSuiteType
     127: invokevirtual #14                 // Method setAlgorithmSuiteType:(Lorg/apache/wss4j/policy/model/AlgorithmSuite$AlgorithmSuiteType;)V
     130: aload_0
     131: invokevirtual #15                 // Method getAlgorithmSuiteType:()Lorg/apache/wss4j/policy/model/AlgorithmSuite$AlgorithmSuiteType;
     134: aload_3
     135: invokevirtual #16                 // Method org/apache/wss4j/policy/model/AlgorithmSuite$AlgorithmSuiteType.setNamespace:(Ljava/lang/String;)V
     138: return

  static {};
    Code:
       0: getstatic     #11                 // Field algorithmSuiteTypes:Ljava/util/Map;
       3: ldc           #10                 // String Basic128GCM
       5: new           #13                 // class org/apache/wss4j/policy/model/AlgorithmSuite$AlgorithmSuiteType
       8: dup
       9: ldc           #10                 // String Basic128GCM
      11: ldc           #19                 // String http://www.w3.org/2000/09/xmldsig#sha1
      13: ldc           #20                 // String http://www.w3.org/2009/xmlenc11#aes128-gcm
      15: ldc           #21                 // String http://www.w3.org/2001/04/xmlenc#kw-aes128
      17: ldc           #22                 // String http://www.w3.org/2001/04/xmlenc#rsa-oaep-mgf1p
      19: ldc           #23                 // String http://schemas.xmlsoap.org/ws/2005/02/sc/dk/p_sha1
      21: ldc           #23                 // String http://schemas.xmlsoap.org/ws/2005/02/sc/dk/p_sha1
      23: sipush        128
      26: sipush        128
      29: sipush        128
      32: sipush        256
      35: sipush        1024
      38: sipush        4096
      41: invokespecial #24                 // Method org/apache/wss4j/policy/model/AlgorithmSuite$AlgorithmSuiteType."<init>":(Ljava/lang/String;Ljava/lang/String;Ljava/lang/String;Ljava/lang/String;Ljava/lang/String;Ljava/lang/String;Ljava/lang/String;IIIIII)V
      44: invokeinterface #25,  3           // InterfaceMethod java/util/Map.put:(Ljava/lang/Object;Ljava/lang/Object;)Ljava/lang/Object;
      49: pop
      50: getstatic     #11                 // Field algorithmSuiteTypes:Ljava/util/Map;
      53: ldc           #17                 // String Basic192GCM
      55: new           #13                 // class org/apache/wss4j/policy/model/AlgorithmSuite$AlgorithmSuiteType
      58: dup
      59: ldc           #17                 // String Basic192GCM
      61: ldc           #19                 // String http://www.w3.org/2000/09/xmldsig#sha1
      63: ldc           #26                 // String http://www.w3.org/2009/xmlenc11#aes192-gcm
      65: ldc           #27                 // String http://www.w3.org/2001/04/xmlenc#kw-aes192
      67: ldc           #22                 // String http://www.w3.org/2001/04/xmlenc#rsa-oaep-mgf1p
      69: ldc           #23                 // String http://schemas.xmlsoap.org/ws/2005/02/sc/dk/p_sha1
      71: ldc           #23                 // String http://schemas.xmlsoap.org/ws/2005/02/sc/dk/p_sha1
      73: sipush        192
      76: sipush        192
      79: sipush        192
      82: sipush        256
      85: sipush        1024
      88: sipush        4096
      91: invokespecial #24                 // Method org/apache/wss4j/policy/model/AlgorithmSuite$AlgorithmSuiteType."<init>":(Ljava/lang/String;Ljava/lang/String;Ljava/lang/String;Ljava/lang/String;Ljava/lang/String;Ljava/lang/String;Ljava/lang/String;IIIIII)V
      94: invokeinterface #25,  3           // InterfaceMethod java/util/Map.put:(Ljava/lang/Object;Ljava/lang/Object;)Ljava/lang/Object;
      99: pop
     100: getstatic     #11                 // Field algorithmSuiteTypes:Ljava/util/Map;
     103: ldc           #18                 // String Basic256GCM
     105: new           #13                 // class org/apache/wss4j/policy/model/AlgorithmSuite$AlgorithmSuiteType
     108: dup
     109: ldc           #18                 // String Basic256GCM
     111: ldc           #19                 // String http://www.w3.org/2000/09/xmldsig#sha1
     113: ldc           #28                 // String http://www.w3.org/2009/xmlenc11#aes256-gcm
     115: ldc           #29                 // String http://www.w3.org/2001/04/xmlenc#kw-aes256
     117: ldc           #22                 // String http://www.w3.org/2001/04/xmlenc#rsa-oaep-mgf1p
     119: ldc           #23                 // String http://schemas.xmlsoap.org/ws/2005/02/sc/dk/p_sha1
     121: ldc           #23                 // String http://schemas.xmlsoap.org/ws/2005/02/sc/dk/p_sha1
     123: sipush        256
     126: sipush        192
     129: sipush        256
     132: sipush        256
     135: sipush        1024
     138: sipush        4096
     141: invokespecial #24                 // Method org/apache/wss4j/policy/model/AlgorithmSuite$AlgorithmSuiteType."<init>":(Ljava/lang/String;Ljava/lang/String;Ljava/lang/String;Ljava/lang/String;Ljava/lang/String;Ljava/lang/String;Ljava/lang/String;IIIIII)V
     144: invokeinterface #25,  3           // InterfaceMethod java/util/Map.put:(Ljava/lang/Object;Ljava/lang/Object;)Ljava/lang/Object;
     149: pop
     150: return
}
