Compiled from "ComponentContainer.java"
final class org.sonar.core.platform.ComponentContainer$ExtendedDefaultPicoContainer extends org.picocontainer.DefaultPicoContainer {
  private org.sonar.core.platform.ComponentContainer$ExtendedDefaultPicoContainer(org.picocontainer.ComponentFactory, org.picocontainer.LifecycleStrategy, org.picocontainer.PicoContainer);
    Code:
       0: aload_0
       1: aload_1
       2: aload_2
       3: aload_3
       4: invokespecial #2                  // Method org/picocontainer/DefaultPicoContainer."<init>":(Lorg/picocontainer/ComponentFactory;Lorg/picocontainer/LifecycleStrategy;Lorg/picocontainer/PicoContainer;)V
       7: return

  private org.sonar.core.platform.ComponentContainer$ExtendedDefaultPicoContainer(org.picocontainer.ComponentFactory, org.picocontainer.LifecycleStrategy, org.picocontainer.PicoContainer, org.picocontainer.ComponentMonitor);
    Code:
       0: aload_0
       1: aload_1
       2: aload_2
       3: aload_3
       4: aload         4
       6: invokespecial #3                  // Method org/picocontainer/DefaultPicoContainer."<init>":(Lorg/picocontainer/ComponentFactory;Lorg/picocontainer/LifecycleStrategy;Lorg/picocontainer/PicoContainer;Lorg/picocontainer/ComponentMonitor;)V
       9: return

  public java.lang.Object getComponent(java.lang.Object, java.lang.Class<? extends java.lang.annotation.Annotation>);
    Code:
       0: aload_0
       1: aload_1
       2: aload_2
       3: invokespecial #4                  // Method org/picocontainer/DefaultPicoContainer.getComponent:(Ljava/lang/Object;Ljava/lang/Class;)Ljava/lang/Object;
       6: areturn
       7: astore_3
       8: new           #6                  // class java/lang/IllegalStateException
      11: dup
      12: new           #7                  // class java/lang/StringBuilder
      15: dup
      16: invokespecial #8                  // Method java/lang/StringBuilder."<init>":()V
      19: ldc           #9                  // String Unable to load component
      21: invokevirtual #10                 // Method java/lang/StringBuilder.append:(Ljava/lang/String;)Ljava/lang/StringBuilder;
      24: aload_1
      25: invokevirtual #11                 // Method java/lang/StringBuilder.append:(Ljava/lang/Object;)Ljava/lang/StringBuilder;
      28: invokevirtual #12                 // Method java/lang/StringBuilder.toString:()Ljava/lang/String;
      31: aload_3
      32: invokespecial #13                 // Method java/lang/IllegalStateException."<init>":(Ljava/lang/String;Ljava/lang/Throwable;)V
      35: athrow
    Exception table:
       from    to  target type
           0     6     7   Class java/lang/Throwable

  public org.picocontainer.MutablePicoContainer makeChildContainer();
    Code:
       0: new           #14                 // class org/sonar/core/platform/ComponentContainer$ExtendedDefaultPicoContainer
       3: dup
       4: aload_0
       5: getfield      #15                 // Field componentFactory:Lorg/picocontainer/ComponentFactory;
       8: aload_0
       9: getfield      #16                 // Field lifecycleStrategy:Lorg/picocontainer/LifecycleStrategy;
      12: aload_0
      13: aload_0
      14: getfield      #17                 // Field componentMonitor:Lorg/picocontainer/ComponentMonitor;
      17: invokespecial #18                 // Method "<init>":(Lorg/picocontainer/ComponentFactory;Lorg/picocontainer/LifecycleStrategy;Lorg/picocontainer/PicoContainer;Lorg/picocontainer/ComponentMonitor;)V
      20: astore_1
      21: aload_0
      22: aload_1
      23: invokevirtual #19                 // Method addChildContainer:(Lorg/picocontainer/PicoContainer;)Lorg/picocontainer/MutablePicoContainer;
      26: pop
      27: aload_1
      28: areturn

  org.sonar.core.platform.ComponentContainer$ExtendedDefaultPicoContainer(org.picocontainer.ComponentFactory, org.picocontainer.LifecycleStrategy, org.picocontainer.PicoContainer, org.sonar.core.platform.ComponentContainer$1);
    Code:
       0: aload_0
       1: aload_1
       2: aload_2
       3: aload_3
       4: invokespecial #1                  // Method "<init>":(Lorg/picocontainer/ComponentFactory;Lorg/picocontainer/LifecycleStrategy;Lorg/picocontainer/PicoContainer;)V
       7: return
}
