Compiled from "HttpInvokerServiceExporter.java"
public class org.springframework.remoting.httpinvoker.HttpInvokerServiceExporter extends org.springframework.remoting.rmi.RemoteInvocationSerializingExporter implements org.springframework.web.HttpRequestHandler {
  public org.springframework.remoting.httpinvoker.HttpInvokerServiceExporter();
    Code:
       0: aload_0
       1: invokespecial #1                  // Method org/springframework/remoting/rmi/RemoteInvocationSerializingExporter."<init>":()V
       4: return

  public void handleRequest(javax.servlet.http.HttpServletRequest, javax.servlet.http.HttpServletResponse) throws javax.servlet.ServletException, java.io.IOException;
    Code:
       0: aload_0
       1: aload_1
       2: invokevirtual #2                  // Method readRemoteInvocation:(Ljavax/servlet/http/HttpServletRequest;)Lorg/springframework/remoting/support/RemoteInvocation;
       5: astore_3
       6: aload_0
       7: aload_3
       8: aload_0
       9: invokevirtual #3                  // Method getProxy:()Ljava/lang/Object;
      12: invokevirtual #4                  // Method invokeAndCreateResult:(Lorg/springframework/remoting/support/RemoteInvocation;Ljava/lang/Object;)Lorg/springframework/remoting/support/RemoteInvocationResult;
      15: astore        4
      17: aload_0
      18: aload_1
      19: aload_2
      20: aload         4
      22: invokevirtual #5                  // Method writeRemoteInvocationResult:(Ljavax/servlet/http/HttpServletRequest;Ljavax/servlet/http/HttpServletResponse;Lorg/springframework/remoting/support/RemoteInvocationResult;)V
      25: goto          40
      28: astore_3
      29: new           #7                  // class org/springframework/web/util/NestedServletException
      32: dup
      33: ldc           #8                  // String Class not found during deserialization
      35: aload_3
      36: invokespecial #9                  // Method org/springframework/web/util/NestedServletException."<init>":(Ljava/lang/String;Ljava/lang/Throwable;)V
      39: athrow
      40: return
    Exception table:
       from    to  target type
           0    25    28   Class java/lang/ClassNotFoundException

  protected org.springframework.remoting.support.RemoteInvocation readRemoteInvocation(javax.servlet.http.HttpServletRequest) throws java.io.IOException, java.lang.ClassNotFoundException;
    Code:
       0: aload_0
       1: aload_1
       2: aload_1
       3: invokeinterface #10,  1           // InterfaceMethod javax/servlet/http/HttpServletRequest.getInputStream:()Ljavax/servlet/ServletInputStream;
       8: invokevirtual #11                 // Method readRemoteInvocation:(Ljavax/servlet/http/HttpServletRequest;Ljava/io/InputStream;)Lorg/springframework/remoting/support/RemoteInvocation;
      11: areturn

  protected org.springframework.remoting.support.RemoteInvocation readRemoteInvocation(javax.servlet.http.HttpServletRequest, java.io.InputStream) throws java.io.IOException, java.lang.ClassNotFoundException;
    Code:
       0: aload_0
       1: aload_0
       2: aload_1
       3: aload_2
       4: invokevirtual #12                 // Method decorateInputStream:(Ljavax/servlet/http/HttpServletRequest;Ljava/io/InputStream;)Ljava/io/InputStream;
       7: invokevirtual #13                 // Method createObjectInputStream:(Ljava/io/InputStream;)Ljava/io/ObjectInputStream;
      10: astore_3
      11: aload_0
      12: aload_3
      13: invokevirtual #14                 // Method doReadRemoteInvocation:(Ljava/io/ObjectInputStream;)Lorg/springframework/remoting/support/RemoteInvocation;
      16: astore        4
      18: aload_3
      19: invokevirtual #15                 // Method java/io/ObjectInputStream.close:()V
      22: aload         4
      24: areturn
      25: astore        5
      27: aload_3
      28: invokevirtual #15                 // Method java/io/ObjectInputStream.close:()V
      31: aload         5
      33: athrow
    Exception table:
       from    to  target type
          11    18    25   any
          25    27    25   any

  protected java.io.InputStream decorateInputStream(javax.servlet.http.HttpServletRequest, java.io.InputStream) throws java.io.IOException;
    Code:
       0: aload_2
       1: areturn

  protected void writeRemoteInvocationResult(javax.servlet.http.HttpServletRequest, javax.servlet.http.HttpServletResponse, org.springframework.remoting.support.RemoteInvocationResult) throws java.io.IOException;
    Code:
       0: aload_2
       1: aload_0
       2: invokevirtual #16                 // Method getContentType:()Ljava/lang/String;
       5: invokeinterface #17,  2           // InterfaceMethod javax/servlet/http/HttpServletResponse.setContentType:(Ljava/lang/String;)V
      10: aload_0
      11: aload_1
      12: aload_2
      13: aload_3
      14: aload_2
      15: invokeinterface #18,  1           // InterfaceMethod javax/servlet/http/HttpServletResponse.getOutputStream:()Ljavax/servlet/ServletOutputStream;
      20: invokevirtual #19                 // Method writeRemoteInvocationResult:(Ljavax/servlet/http/HttpServletRequest;Ljavax/servlet/http/HttpServletResponse;Lorg/springframework/remoting/support/RemoteInvocationResult;Ljava/io/OutputStream;)V
      23: return

  protected void writeRemoteInvocationResult(javax.servlet.http.HttpServletRequest, javax.servlet.http.HttpServletResponse, org.springframework.remoting.support.RemoteInvocationResult, java.io.OutputStream) throws java.io.IOException;
    Code:
       0: aload_0
       1: new           #20                 // class org/springframework/remoting/httpinvoker/HttpInvokerServiceExporter$FlushGuardedOutputStream
       4: dup
       5: aload_0
       6: aload_1
       7: aload_2
       8: aload         4
      10: invokevirtual #21                 // Method decorateOutputStream:(Ljavax/servlet/http/HttpServletRequest;Ljavax/servlet/http/HttpServletResponse;Ljava/io/OutputStream;)Ljava/io/OutputStream;
      13: invokespecial #22                 // Method org/springframework/remoting/httpinvoker/HttpInvokerServiceExporter$FlushGuardedOutputStream."<init>":(Ljava/io/OutputStream;)V
      16: invokevirtual #23                 // Method createObjectOutputStream:(Ljava/io/OutputStream;)Ljava/io/ObjectOutputStream;
      19: astore        5
      21: aload_0
      22: aload_3
      23: aload         5
      25: invokevirtual #24                 // Method doWriteRemoteInvocationResult:(Lorg/springframework/remoting/support/RemoteInvocationResult;Ljava/io/ObjectOutputStream;)V
      28: aload         5
      30: invokevirtual #25                 // Method java/io/ObjectOutputStream.close:()V
      33: goto          46
      36: astore        6
      38: aload         5
      40: invokevirtual #25                 // Method java/io/ObjectOutputStream.close:()V
      43: aload         6
      45: athrow
      46: return
    Exception table:
       from    to  target type
          21    28    36   any
          36    38    36   any

  protected java.io.OutputStream decorateOutputStream(javax.servlet.http.HttpServletRequest, javax.servlet.http.HttpServletResponse, java.io.OutputStream) throws java.io.IOException;
    Code:
       0: aload_3
       1: areturn
}
