Compiled from "Maps.java"
class com.google.common.collect.Maps$SortedAsMapView<K, V> extends com.google.common.collect.Maps$AsMapView<K, V> implements java.util.SortedMap<K, V> {
  com.google.common.collect.Maps$SortedAsMapView(java.util.SortedSet<K>, com.google.common.base.Function<? super K, V>);
    Code:
       0: aload_0
       1: aload_1
       2: aload_2
       3: invokespecial #1                  // Method com/google/common/collect/Maps$AsMapView."<init>":(Ljava/util/Set;Lcom/google/common/base/Function;)V
       6: return

  java.util.SortedSet<K> backingSet();
    Code:
       0: aload_0
       1: invokespecial #2                  // Method com/google/common/collect/Maps$AsMapView.backingSet:()Ljava/util/Set;
       4: checkcast     #3                  // class java/util/SortedSet
       7: areturn

  public java.util.Comparator<? super K> comparator();
    Code:
       0: aload_0
       1: invokevirtual #4                  // Method backingSet:()Ljava/util/SortedSet;
       4: invokeinterface #5,  1            // InterfaceMethod java/util/SortedSet.comparator:()Ljava/util/Comparator;
       9: areturn

  public java.util.Set<K> keySet();
    Code:
       0: aload_0
       1: invokevirtual #4                  // Method backingSet:()Ljava/util/SortedSet;
       4: invokestatic  #6                  // Method com/google/common/collect/Maps.access$300:(Ljava/util/SortedSet;)Ljava/util/SortedSet;
       7: areturn

  public java.util.SortedMap<K, V> subMap(K, K);
    Code:
       0: aload_0
       1: invokevirtual #4                  // Method backingSet:()Ljava/util/SortedSet;
       4: aload_1
       5: aload_2
       6: invokeinterface #7,  3            // InterfaceMethod java/util/SortedSet.subSet:(Ljava/lang/Object;Ljava/lang/Object;)Ljava/util/SortedSet;
      11: aload_0
      12: getfield      #8                  // Field function:Lcom/google/common/base/Function;
      15: invokestatic  #9                  // Method com/google/common/collect/Maps.asMap:(Ljava/util/SortedSet;Lcom/google/common/base/Function;)Ljava/util/SortedMap;
      18: areturn

  public java.util.SortedMap<K, V> headMap(K);
    Code:
       0: aload_0
       1: invokevirtual #4                  // Method backingSet:()Ljava/util/SortedSet;
       4: aload_1
       5: invokeinterface #10,  2           // InterfaceMethod java/util/SortedSet.headSet:(Ljava/lang/Object;)Ljava/util/SortedSet;
      10: aload_0
      11: getfield      #8                  // Field function:Lcom/google/common/base/Function;
      14: invokestatic  #9                  // Method com/google/common/collect/Maps.asMap:(Ljava/util/SortedSet;Lcom/google/common/base/Function;)Ljava/util/SortedMap;
      17: areturn

  public java.util.SortedMap<K, V> tailMap(K);
    Code:
       0: aload_0
       1: invokevirtual #4                  // Method backingSet:()Ljava/util/SortedSet;
       4: aload_1
       5: invokeinterface #11,  2           // InterfaceMethod java/util/SortedSet.tailSet:(Ljava/lang/Object;)Ljava/util/SortedSet;
      10: aload_0
      11: getfield      #8                  // Field function:Lcom/google/common/base/Function;
      14: invokestatic  #9                  // Method com/google/common/collect/Maps.asMap:(Ljava/util/SortedSet;Lcom/google/common/base/Function;)Ljava/util/SortedMap;
      17: areturn

  public K firstKey();
    Code:
       0: aload_0
       1: invokevirtual #4                  // Method backingSet:()Ljava/util/SortedSet;
       4: invokeinterface #12,  1           // InterfaceMethod java/util/SortedSet.first:()Ljava/lang/Object;
       9: areturn

  public K lastKey();
    Code:
       0: aload_0
       1: invokevirtual #4                  // Method backingSet:()Ljava/util/SortedSet;
       4: invokeinterface #13,  1           // InterfaceMethod java/util/SortedSet.last:()Ljava/lang/Object;
       9: areturn

  java.util.Set backingSet();
    Code:
       0: aload_0
       1: invokevirtual #4                  // Method backingSet:()Ljava/util/SortedSet;
       4: areturn
}
