Compiled from "CodecUtils.java"
public final class com.amazonaws.util.CodecUtils extends java.lang.Enum<com.amazonaws.util.CodecUtils> {
  private static final com.amazonaws.util.CodecUtils[] $VALUES;

  public static com.amazonaws.util.CodecUtils[] values();
    Code:
       0: getstatic     #1                  // Field $VALUES:[Lcom/amazonaws/util/CodecUtils;
       3: invokevirtual #2                  // Method "[Lcom/amazonaws/util/CodecUtils;".clone:()Ljava/lang/Object;
       6: checkcast     #3                  // class "[Lcom/amazonaws/util/CodecUtils;"
       9: areturn

  public static com.amazonaws.util.CodecUtils valueOf(java.lang.String);
    Code:
       0: ldc           #4                  // class com/amazonaws/util/CodecUtils
       2: aload_0
       3: invokestatic  #5                  // Method java/lang/Enum.valueOf:(Ljava/lang/Class;Ljava/lang/String;)Ljava/lang/Enum;
       6: checkcast     #4                  // class com/amazonaws/util/CodecUtils
       9: areturn

  private com.amazonaws.util.CodecUtils();
    Code:
       0: aload_0
       1: aload_1
       2: iload_2
       3: invokespecial #6                  // Method java/lang/Enum."<init>":(Ljava/lang/String;I)V
       6: return

  static int sanitize(java.lang.String, byte[]);
    Code:
       0: aload_1
       1: arraylength
       2: istore_2
       3: aload_0
       4: invokevirtual #7                  // Method java/lang/String.toCharArray:()[C
       7: astore_3
       8: iconst_0
       9: istore        4
      11: iconst_0
      12: istore        5
      14: iload         5
      16: iload_2
      17: if_icmpge     110
      20: aload_3
      21: iload         5
      23: caload
      24: istore        6
      26: iload         6
      28: bipush        13
      30: if_icmpeq     104
      33: iload         6
      35: bipush        10
      37: if_icmpeq     104
      40: iload         6
      42: bipush        32
      44: if_icmpne     50
      47: goto          104
      50: iload         6
      52: bipush        127
      54: if_icmple     94
      57: new           #9                  // class java/lang/IllegalArgumentException
      60: dup
      61: new           #10                 // class java/lang/StringBuilder
      64: dup
      65: invokespecial #11                 // Method java/lang/StringBuilder."<init>":()V
      68: ldc           #12                 // String Invalid character found at position
      70: invokevirtual #13                 // Method java/lang/StringBuilder.append:(Ljava/lang/String;)Ljava/lang/StringBuilder;
      73: iload         5
      75: invokevirtual #14                 // Method java/lang/StringBuilder.append:(I)Ljava/lang/StringBuilder;
      78: ldc           #15                 // String  for
      80: invokevirtual #13                 // Method java/lang/StringBuilder.append:(Ljava/lang/String;)Ljava/lang/StringBuilder;
      83: aload_0
      84: invokevirtual #13                 // Method java/lang/StringBuilder.append:(Ljava/lang/String;)Ljava/lang/StringBuilder;
      87: invokevirtual #16                 // Method java/lang/StringBuilder.toString:()Ljava/lang/String;
      90: invokespecial #17                 // Method java/lang/IllegalArgumentException."<init>":(Ljava/lang/String;)V
      93: athrow
      94: aload_1
      95: iload         4
      97: iinc          4, 1
     100: iload         6
     102: i2b
     103: bastore
     104: iinc          5, 1
     107: goto          14
     110: iload         4
     112: ireturn

  public static byte[] toBytesDirect(java.lang.String);
    Code:
       0: aload_0
       1: invokevirtual #7                  // Method java/lang/String.toCharArray:()[C
       4: astore_1
       5: aload_1
       6: arraylength
       7: newarray       byte
       9: astore_2
      10: iconst_0
      11: istore_3
      12: iload_3
      13: aload_2
      14: arraylength
      15: if_icmpge     78
      18: aload_1
      19: iload_3
      20: caload
      21: istore        4
      23: iload         4
      25: bipush        127
      27: if_icmple     66
      30: new           #9                  // class java/lang/IllegalArgumentException
      33: dup
      34: new           #10                 // class java/lang/StringBuilder
      37: dup
      38: invokespecial #11                 // Method java/lang/StringBuilder."<init>":()V
      41: ldc           #12                 // String Invalid character found at position
      43: invokevirtual #13                 // Method java/lang/StringBuilder.append:(Ljava/lang/String;)Ljava/lang/StringBuilder;
      46: iload_3
      47: invokevirtual #14                 // Method java/lang/StringBuilder.append:(I)Ljava/lang/StringBuilder;
      50: ldc           #15                 // String  for
      52: invokevirtual #13                 // Method java/lang/StringBuilder.append:(Ljava/lang/String;)Ljava/lang/StringBuilder;
      55: aload_0
      56: invokevirtual #13                 // Method java/lang/StringBuilder.append:(Ljava/lang/String;)Ljava/lang/StringBuilder;
      59: invokevirtual #16                 // Method java/lang/StringBuilder.toString:()Ljava/lang/String;
      62: invokespecial #17                 // Method java/lang/IllegalArgumentException."<init>":(Ljava/lang/String;)V
      65: athrow
      66: aload_2
      67: iload_3
      68: iload         4
      70: i2b
      71: bastore
      72: iinc          3, 1
      75: goto          12
      78: aload_2
      79: areturn

  public static java.lang.String toStringDirect(byte[]);
    Code:
       0: aload_0
       1: arraylength
       2: newarray       char
       4: astore_1
       5: iconst_0
       6: istore_2
       7: aload_0
       8: astore_3
       9: aload_3
      10: arraylength
      11: istore        4
      13: iconst_0
      14: istore        5
      16: iload         5
      18: iload         4
      20: if_icmpge     44
      23: aload_3
      24: iload         5
      26: baload
      27: istore        6
      29: aload_1
      30: iload_2
      31: iinc          2, 1
      34: iload         6
      36: i2c
      37: castore
      38: iinc          5, 1
      41: goto          16
      44: new           #18                 // class java/lang/String
      47: dup
      48: aload_1
      49: invokespecial #19                 // Method java/lang/String."<init>":([C)V
      52: areturn

  static void sanityCheckLastPos(int, int);
    Code:
       0: iload_0
       1: iload_1
       2: iand
       3: ifeq          16
       6: new           #9                  // class java/lang/IllegalArgumentException
       9: dup
      10: ldc           #20                 // String Invalid last non-pad character detected
      12: invokespecial #17                 // Method java/lang/IllegalArgumentException."<init>":(Ljava/lang/String;)V
      15: athrow
      16: return

  static {};
    Code:
       0: iconst_0
       1: anewarray     #4                  // class com/amazonaws/util/CodecUtils
       4: putstatic     #1                  // Field $VALUES:[Lcom/amazonaws/util/CodecUtils;
       7: return
}
