Compiled from "JavaVersionParser.java"
public class com.amazonaws.util.JavaVersionParser {
  public static final java.lang.String JAVA_VERSION_PROPERTY;

  private static java.lang.String MAJOR_VERSION_FAMILY_PATTERN;

  private static java.lang.String MAJOR_VERSION_PATTERN;

  private static java.lang.String MAINTENANCE_NUMBER_PATTERN;

  private static java.lang.String UPDATE_NUMBER_PATTERN;

  private static java.util.regex.Pattern VERSION_REGEX;

  private static final com.amazonaws.util.JavaVersionParser$JavaVersion currentJavaVersion;

  private com.amazonaws.util.JavaVersionParser();
    Code:
       0: aload_0
       1: invokespecial #1                  // Method java/lang/Object."<init>":()V
       4: return

  public static com.amazonaws.util.JavaVersionParser$JavaVersion getCurrentJavaVersion();
    Code:
       0: getstatic     #2                  // Field currentJavaVersion:Lcom/amazonaws/util/JavaVersionParser$JavaVersion;
       3: areturn

  public static com.amazonaws.util.JavaVersionParser$JavaVersion parseJavaVersion(java.lang.String);
    Code:
       0: aload_0
       1: invokestatic  #3                  // Method com/amazonaws/util/StringUtils.isNullOrEmpty:(Ljava/lang/String;)Z
       4: ifne          74
       7: getstatic     #4                  // Field VERSION_REGEX:Ljava/util/regex/Pattern;
      10: aload_0
      11: invokevirtual #5                  // Method java/util/regex/Pattern.matcher:(Ljava/lang/CharSequence;)Ljava/util/regex/Matcher;
      14: astore_1
      15: aload_1
      16: invokevirtual #6                  // Method java/util/regex/Matcher.matches:()Z
      19: ifeq          74
      22: aload_1
      23: iconst_1
      24: invokevirtual #7                  // Method java/util/regex/Matcher.group:(I)Ljava/lang/String;
      27: invokestatic  #8                  // Method com/amazonaws/util/NumberUtils.tryParseInt:(Ljava/lang/String;)Ljava/lang/Integer;
      30: astore_2
      31: aload_1
      32: iconst_2
      33: invokevirtual #7                  // Method java/util/regex/Matcher.group:(I)Ljava/lang/String;
      36: invokestatic  #8                  // Method com/amazonaws/util/NumberUtils.tryParseInt:(Ljava/lang/String;)Ljava/lang/Integer;
      39: astore_3
      40: aload_1
      41: iconst_3
      42: invokevirtual #7                  // Method java/util/regex/Matcher.group:(I)Ljava/lang/String;
      45: invokestatic  #8                  // Method com/amazonaws/util/NumberUtils.tryParseInt:(Ljava/lang/String;)Ljava/lang/Integer;
      48: astore        4
      50: aload_1
      51: iconst_4
      52: invokevirtual #7                  // Method java/util/regex/Matcher.group:(I)Ljava/lang/String;
      55: invokestatic  #8                  // Method com/amazonaws/util/NumberUtils.tryParseInt:(Ljava/lang/String;)Ljava/lang/Integer;
      58: astore        5
      60: new           #9                  // class com/amazonaws/util/JavaVersionParser$JavaVersion
      63: dup
      64: aload_2
      65: aload_3
      66: aload         4
      68: aload         5
      70: invokespecial #10                 // Method com/amazonaws/util/JavaVersionParser$JavaVersion."<init>":(Ljava/lang/Integer;Ljava/lang/Integer;Ljava/lang/Integer;Ljava/lang/Integer;)V
      73: areturn
      74: getstatic     #11                 // Field com/amazonaws/util/JavaVersionParser$JavaVersion.UNKNOWN:Lcom/amazonaws/util/JavaVersionParser$JavaVersion;
      77: areturn

  static {};
    Code:
       0: ldc           #12                 // String \\d+
       2: putstatic     #13                 // Field MAJOR_VERSION_FAMILY_PATTERN:Ljava/lang/String;
       5: ldc           #12                 // String \\d+
       7: putstatic     #14                 // Field MAJOR_VERSION_PATTERN:Ljava/lang/String;
      10: ldc           #12                 // String \\d+
      12: putstatic     #15                 // Field MAINTENANCE_NUMBER_PATTERN:Ljava/lang/String;
      15: ldc           #12                 // String \\d+
      17: putstatic     #16                 // Field UPDATE_NUMBER_PATTERN:Ljava/lang/String;
      20: ldc           #17                 // String (%s)\\.(%s)\\.(%s)(?:_(%s))?.*
      22: iconst_4
      23: anewarray     #18                 // class java/lang/Object
      26: dup
      27: iconst_0
      28: getstatic     #13                 // Field MAJOR_VERSION_FAMILY_PATTERN:Ljava/lang/String;
      31: aastore
      32: dup
      33: iconst_1
      34: getstatic     #14                 // Field MAJOR_VERSION_PATTERN:Ljava/lang/String;
      37: aastore
      38: dup
      39: iconst_2
      40: getstatic     #15                 // Field MAINTENANCE_NUMBER_PATTERN:Ljava/lang/String;
      43: aastore
      44: dup
      45: iconst_3
      46: getstatic     #16                 // Field UPDATE_NUMBER_PATTERN:Ljava/lang/String;
      49: aastore
      50: invokestatic  #19                 // Method java/lang/String.format:(Ljava/lang/String;[Ljava/lang/Object;)Ljava/lang/String;
      53: invokestatic  #20                 // Method java/util/regex/Pattern.compile:(Ljava/lang/String;)Ljava/util/regex/Pattern;
      56: putstatic     #4                  // Field VERSION_REGEX:Ljava/util/regex/Pattern;
      59: ldc           #22                 // String java.version
      61: invokestatic  #23                 // Method java/lang/System.getProperty:(Ljava/lang/String;)Ljava/lang/String;
      64: invokestatic  #24                 // Method parseJavaVersion:(Ljava/lang/String;)Lcom/amazonaws/util/JavaVersionParser$JavaVersion;
      67: putstatic     #2                  // Field currentJavaVersion:Lcom/amazonaws/util/JavaVersionParser$JavaVersion;
      70: return
}
