Compiled from "Md5Utils.java"
public class com.amazonaws.util.Md5Utils {
  private static final int SIXTEEN_K;

  public com.amazonaws.util.Md5Utils();
    Code:
       0: aload_0
       1: invokespecial #1                  // Method java/lang/Object."<init>":()V
       4: return

  public static byte[] computeMD5Hash(java.io.InputStream) throws java.io.IOException;
    Code:
       0: new           #2                  // class java/io/BufferedInputStream
       3: dup
       4: aload_0
       5: invokespecial #3                  // Method java/io/BufferedInputStream."<init>":(Ljava/io/InputStream;)V
       8: astore_1
       9: ldc           #4                  // String MD5
      11: invokestatic  #5                  // Method java/security/MessageDigest.getInstance:(Ljava/lang/String;)Ljava/security/MessageDigest;
      14: astore_2
      15: sipush        16384
      18: newarray       byte
      20: astore_3
      21: aload_1
      22: aload_3
      23: iconst_0
      24: aload_3
      25: arraylength
      26: invokevirtual #7                  // Method java/io/BufferedInputStream.read:([BII)I
      29: dup
      30: istore        4
      32: iconst_m1
      33: if_icmpeq     47
      36: aload_2
      37: aload_3
      38: iconst_0
      39: iload         4
      41: invokevirtual #8                  // Method java/security/MessageDigest.update:([BII)V
      44: goto          21
      47: aload_2
      48: invokevirtual #9                  // Method java/security/MessageDigest.digest:()[B
      51: astore        5
      53: aload_1
      54: invokevirtual #10                 // Method java/io/BufferedInputStream.close:()V
      57: goto          92
      60: astore        6
      62: ldc           #6                  // class com/amazonaws/util/Md5Utils
      64: invokestatic  #12                 // Method org/apache/commons/logging/LogFactory.getLog:(Ljava/lang/Class;)Lorg/apache/commons/logging/Log;
      67: new           #13                 // class java/lang/StringBuilder
      70: dup
      71: invokespecial #14                 // Method java/lang/StringBuilder."<init>":()V
      74: ldc           #15                 // String Unable to close input stream of hash candidate:
      76: invokevirtual #16                 // Method java/lang/StringBuilder.append:(Ljava/lang/String;)Ljava/lang/StringBuilder;
      79: aload         6
      81: invokevirtual #17                 // Method java/lang/StringBuilder.append:(Ljava/lang/Object;)Ljava/lang/StringBuilder;
      84: invokevirtual #18                 // Method java/lang/StringBuilder.toString:()Ljava/lang/String;
      87: invokeinterface #19,  2           // InterfaceMethod org/apache/commons/logging/Log.debug:(Ljava/lang/Object;)V
      92: aload         5
      94: areturn
      95: astore_2
      96: new           #21                 // class java/lang/IllegalStateException
      99: dup
     100: aload_2
     101: invokespecial #22                 // Method java/lang/IllegalStateException."<init>":(Ljava/lang/Throwable;)V
     104: athrow
     105: astore        7
     107: aload_1
     108: invokevirtual #10                 // Method java/io/BufferedInputStream.close:()V
     111: goto          146
     114: astore        8
     116: ldc           #6                  // class com/amazonaws/util/Md5Utils
     118: invokestatic  #12                 // Method org/apache/commons/logging/LogFactory.getLog:(Ljava/lang/Class;)Lorg/apache/commons/logging/Log;
     121: new           #13                 // class java/lang/StringBuilder
     124: dup
     125: invokespecial #14                 // Method java/lang/StringBuilder."<init>":()V
     128: ldc           #15                 // String Unable to close input stream of hash candidate:
     130: invokevirtual #16                 // Method java/lang/StringBuilder.append:(Ljava/lang/String;)Ljava/lang/StringBuilder;
     133: aload         8
     135: invokevirtual #17                 // Method java/lang/StringBuilder.append:(Ljava/lang/Object;)Ljava/lang/StringBuilder;
     138: invokevirtual #18                 // Method java/lang/StringBuilder.toString:()Ljava/lang/String;
     141: invokeinterface #19,  2           // InterfaceMethod org/apache/commons/logging/Log.debug:(Ljava/lang/Object;)V
     146: aload         7
     148: athrow
    Exception table:
       from    to  target type
          53    57    60   Class java/lang/Exception
           9    53    95   Class java/security/NoSuchAlgorithmException
           9    53   105   any
         107   111   114   Class java/lang/Exception
          95   107   105   any

  public static java.lang.String md5AsBase64(java.io.InputStream) throws java.io.IOException;
    Code:
       0: aload_0
       1: invokestatic  #23                 // Method computeMD5Hash:(Ljava/io/InputStream;)[B
       4: invokestatic  #24                 // Method com/amazonaws/util/Base64.encodeAsString:([B)Ljava/lang/String;
       7: areturn

  public static byte[] computeMD5Hash(byte[]);
    Code:
       0: ldc           #4                  // String MD5
       2: invokestatic  #5                  // Method java/security/MessageDigest.getInstance:(Ljava/lang/String;)Ljava/security/MessageDigest;
       5: astore_1
       6: aload_1
       7: aload_0
       8: invokevirtual #25                 // Method java/security/MessageDigest.digest:([B)[B
      11: areturn
      12: astore_1
      13: new           #21                 // class java/lang/IllegalStateException
      16: dup
      17: aload_1
      18: invokespecial #22                 // Method java/lang/IllegalStateException."<init>":(Ljava/lang/Throwable;)V
      21: athrow
    Exception table:
       from    to  target type
           0    11    12   Class java/security/NoSuchAlgorithmException

  public static java.lang.String md5AsBase64(byte[]);
    Code:
       0: aload_0
       1: invokestatic  #26                 // Method computeMD5Hash:([B)[B
       4: invokestatic  #24                 // Method com/amazonaws/util/Base64.encodeAsString:([B)Ljava/lang/String;
       7: areturn

  public static byte[] computeMD5Hash(java.io.File) throws java.io.FileNotFoundException, java.io.IOException;
    Code:
       0: new           #27                 // class java/io/FileInputStream
       3: dup
       4: aload_0
       5: invokespecial #28                 // Method java/io/FileInputStream."<init>":(Ljava/io/File;)V
       8: invokestatic  #23                 // Method computeMD5Hash:(Ljava/io/InputStream;)[B
      11: areturn

  public static java.lang.String md5AsBase64(java.io.File) throws java.io.FileNotFoundException, java.io.IOException;
    Code:
       0: aload_0
       1: invokestatic  #29                 // Method computeMD5Hash:(Ljava/io/File;)[B
       4: invokestatic  #24                 // Method com/amazonaws/util/Base64.encodeAsString:([B)Ljava/lang/String;
       7: areturn
}
