Compiled from "TimingInfoFullSupport.java"
class com.amazonaws.util.TimingInfoFullSupport extends com.amazonaws.util.TimingInfo {
  private final java.util.Map<java.lang.String, java.util.List<com.amazonaws.util.TimingInfo>> subMeasurementsByName;

  private final java.util.Map<java.lang.String, java.lang.Number> countersByName;

  com.amazonaws.util.TimingInfoFullSupport(java.lang.Long, long, java.lang.Long);
    Code:
       0: aload_0
       1: aload_1
       2: lload_2
       3: aload         4
       5: invokespecial #1                  // Method com/amazonaws/util/TimingInfo."<init>":(Ljava/lang/Long;JLjava/lang/Long;)V
       8: aload_0
       9: new           #2                  // class java/util/HashMap
      12: dup
      13: invokespecial #3                  // Method java/util/HashMap."<init>":()V
      16: putfield      #4                  // Field subMeasurementsByName:Ljava/util/Map;
      19: aload_0
      20: new           #2                  // class java/util/HashMap
      23: dup
      24: invokespecial #3                  // Method java/util/HashMap."<init>":()V
      27: putfield      #5                  // Field countersByName:Ljava/util/Map;
      30: return

  public void addSubMeasurement(java.lang.String, com.amazonaws.util.TimingInfo);
    Code:
       0: aload_0
       1: getfield      #4                  // Field subMeasurementsByName:Ljava/util/Map;
       4: aload_1
       5: invokeinterface #6,  2            // InterfaceMethod java/util/Map.get:(Ljava/lang/Object;)Ljava/lang/Object;
      10: checkcast     #7                  // class java/util/List
      13: astore_3
      14: aload_3
      15: ifnonnull     38
      18: new           #8                  // class java/util/ArrayList
      21: dup
      22: invokespecial #9                  // Method java/util/ArrayList."<init>":()V
      25: astore_3
      26: aload_0
      27: getfield      #4                  // Field subMeasurementsByName:Ljava/util/Map;
      30: aload_1
      31: aload_3
      32: invokeinterface #10,  3           // InterfaceMethod java/util/Map.put:(Ljava/lang/Object;Ljava/lang/Object;)Ljava/lang/Object;
      37: pop
      38: aload_2
      39: invokevirtual #11                 // Method com/amazonaws/util/TimingInfo.isEndTimeKnown:()Z
      42: ifeq          56
      45: aload_3
      46: aload_2
      47: invokeinterface #12,  2           // InterfaceMethod java/util/List.add:(Ljava/lang/Object;)Z
      52: pop
      53: goto          87
      56: aload_0
      57: invokevirtual #13                 // Method java/lang/Object.getClass:()Ljava/lang/Class;
      60: invokestatic  #14                 // Method org/apache/commons/logging/LogFactory.getLog:(Ljava/lang/Class;)Lorg/apache/commons/logging/Log;
      63: new           #15                 // class java/lang/StringBuilder
      66: dup
      67: invokespecial #16                 // Method java/lang/StringBuilder."<init>":()V
      70: ldc           #17                 // String Skip submeasurement timing info with no end time for
      72: invokevirtual #18                 // Method java/lang/StringBuilder.append:(Ljava/lang/String;)Ljava/lang/StringBuilder;
      75: aload_1
      76: invokevirtual #18                 // Method java/lang/StringBuilder.append:(Ljava/lang/String;)Ljava/lang/StringBuilder;
      79: invokevirtual #19                 // Method java/lang/StringBuilder.toString:()Ljava/lang/String;
      82: invokeinterface #20,  2           // InterfaceMethod org/apache/commons/logging/Log.debug:(Ljava/lang/Object;)V
      87: return

  public com.amazonaws.util.TimingInfo getSubMeasurement(java.lang.String);
    Code:
       0: aload_0
       1: aload_1
       2: iconst_0
       3: invokevirtual #21                 // Method getSubMeasurement:(Ljava/lang/String;I)Lcom/amazonaws/util/TimingInfo;
       6: areturn

  public com.amazonaws.util.TimingInfo getSubMeasurement(java.lang.String, int);
    Code:
       0: aload_0
       1: getfield      #4                  // Field subMeasurementsByName:Ljava/util/Map;
       4: aload_1
       5: invokeinterface #6,  2            // InterfaceMethod java/util/Map.get:(Ljava/lang/Object;)Ljava/lang/Object;
      10: checkcast     #7                  // class java/util/List
      13: astore_3
      14: iload_2
      15: iflt          41
      18: aload_3
      19: ifnull        41
      22: aload_3
      23: invokeinterface #22,  1           // InterfaceMethod java/util/List.size:()I
      28: ifeq          41
      31: iload_2
      32: aload_3
      33: invokeinterface #22,  1           // InterfaceMethod java/util/List.size:()I
      38: if_icmplt     43
      41: aconst_null
      42: areturn
      43: aload_3
      44: iload_2
      45: invokeinterface #23,  2           // InterfaceMethod java/util/List.get:(I)Ljava/lang/Object;
      50: checkcast     #24                 // class com/amazonaws/util/TimingInfo
      53: areturn

  public com.amazonaws.util.TimingInfo getLastSubMeasurement(java.lang.String);
    Code:
       0: aload_0
       1: getfield      #4                  // Field subMeasurementsByName:Ljava/util/Map;
       4: ifnull        19
       7: aload_0
       8: getfield      #4                  // Field subMeasurementsByName:Ljava/util/Map;
      11: invokeinterface #25,  1           // InterfaceMethod java/util/Map.size:()I
      16: ifne          21
      19: aconst_null
      20: areturn
      21: aload_0
      22: getfield      #4                  // Field subMeasurementsByName:Ljava/util/Map;
      25: aload_1
      26: invokeinterface #6,  2            // InterfaceMethod java/util/Map.get:(Ljava/lang/Object;)Ljava/lang/Object;
      31: checkcast     #7                  // class java/util/List
      34: astore_2
      35: aload_2
      36: ifnull        48
      39: aload_2
      40: invokeinterface #22,  1           // InterfaceMethod java/util/List.size:()I
      45: ifne          50
      48: aconst_null
      49: areturn
      50: aload_2
      51: aload_2
      52: invokeinterface #22,  1           // InterfaceMethod java/util/List.size:()I
      57: iconst_1
      58: isub
      59: invokeinterface #23,  2           // InterfaceMethod java/util/List.get:(I)Ljava/lang/Object;
      64: checkcast     #24                 // class com/amazonaws/util/TimingInfo
      67: areturn

  public java.util.List<com.amazonaws.util.TimingInfo> getAllSubMeasurements(java.lang.String);
    Code:
       0: aload_0
       1: getfield      #4                  // Field subMeasurementsByName:Ljava/util/Map;
       4: aload_1
       5: invokeinterface #6,  2            // InterfaceMethod java/util/Map.get:(Ljava/lang/Object;)Ljava/lang/Object;
      10: checkcast     #7                  // class java/util/List
      13: areturn

  public java.util.Map<java.lang.String, java.util.List<com.amazonaws.util.TimingInfo>> getSubMeasurementsByName();
    Code:
       0: aload_0
       1: getfield      #4                  // Field subMeasurementsByName:Ljava/util/Map;
       4: areturn

  public java.lang.Number getCounter(java.lang.String);
    Code:
       0: aload_0
       1: getfield      #5                  // Field countersByName:Ljava/util/Map;
       4: aload_1
       5: invokeinterface #6,  2            // InterfaceMethod java/util/Map.get:(Ljava/lang/Object;)Ljava/lang/Object;
      10: checkcast     #26                 // class java/lang/Number
      13: areturn

  public java.util.Map<java.lang.String, java.lang.Number> getAllCounters();
    Code:
       0: aload_0
       1: getfield      #5                  // Field countersByName:Ljava/util/Map;
       4: areturn

  public void setCounter(java.lang.String, long);
    Code:
       0: aload_0
       1: getfield      #5                  // Field countersByName:Ljava/util/Map;
       4: aload_1
       5: lload_2
       6: invokestatic  #27                 // Method java/lang/Long.valueOf:(J)Ljava/lang/Long;
       9: invokeinterface #10,  3           // InterfaceMethod java/util/Map.put:(Ljava/lang/Object;Ljava/lang/Object;)Ljava/lang/Object;
      14: pop
      15: return

  public void incrementCounter(java.lang.String);
    Code:
       0: iconst_0
       1: istore_2
       2: aload_0
       3: aload_1
       4: invokevirtual #28                 // Method getCounter:(Ljava/lang/String;)Ljava/lang/Number;
       7: astore_3
       8: aload_3
       9: ifnull        17
      12: aload_3
      13: invokevirtual #29                 // Method java/lang/Number.intValue:()I
      16: istore_2
      17: aload_0
      18: aload_1
      19: iinc          2, 1
      22: iload_2
      23: i2l
      24: invokevirtual #30                 // Method setCounter:(Ljava/lang/String;J)V
      27: return
}
