Compiled from "DigestGenerator.java"
public class org.apache.axiom.om.util.DigestGenerator {
  public static final java.lang.String md5DigestAlgorithm;

  public static final java.lang.String shaDigestAlgorithm;

  public static final java.lang.String sha1DigestAlgorithm;

  public org.apache.axiom.om.util.DigestGenerator();
    Code:
       0: aload_0
       1: invokespecial #1                  // Method java/lang/Object."<init>":()V
       4: return

  public byte[] getDigest(org.apache.axiom.om.OMDocument, java.lang.String) throws org.apache.axiom.om.OMException;
    Code:
       0: iconst_0
       1: newarray       byte
       3: astore_3
       4: aload_2
       5: invokestatic  #2                  // Method java/security/MessageDigest.getInstance:(Ljava/lang/String;)Ljava/security/MessageDigest;
       8: astore        4
      10: new           #3                  // class java/io/ByteArrayOutputStream
      13: dup
      14: invokespecial #4                  // Method java/io/ByteArrayOutputStream."<init>":()V
      17: astore        5
      19: new           #5                  // class java/io/DataOutputStream
      22: dup
      23: aload         5
      25: invokespecial #6                  // Method java/io/DataOutputStream."<init>":(Ljava/io/OutputStream;)V
      28: astore        6
      30: aload         6
      32: bipush        9
      34: invokevirtual #7                  // Method java/io/DataOutputStream.writeInt:(I)V
      37: aload_0
      38: aload_1
      39: invokevirtual #8                  // Method getValidElements:(Lorg/apache/axiom/om/OMDocument;)Ljava/util/Collection;
      42: astore        7
      44: aload         6
      46: aload         7
      48: invokeinterface #9,  1            // InterfaceMethod java/util/Collection.size:()I
      53: invokevirtual #7                  // Method java/io/DataOutputStream.writeInt:(I)V
      56: aload         7
      58: invokeinterface #10,  1           // InterfaceMethod java/util/Collection.iterator:()Ljava/util/Iterator;
      63: astore        8
      65: aload         8
      67: invokeinterface #11,  1           // InterfaceMethod java/util/Iterator.hasNext:()Z
      72: ifeq          145
      75: aload         8
      77: invokeinterface #12,  1           // InterfaceMethod java/util/Iterator.next:()Ljava/lang/Object;
      82: checkcast     #13                 // class org/apache/axiom/om/OMNode
      85: astore        9
      87: aload         9
      89: invokeinterface #14,  1           // InterfaceMethod org/apache/axiom/om/OMNode.getType:()I
      94: iconst_3
      95: if_icmpne     116
      98: aload         6
     100: aload_0
     101: aload         9
     103: checkcast     #15                 // class org/apache/axiom/om/OMProcessingInstruction
     106: aload_2
     107: invokevirtual #16                 // Method getDigest:(Lorg/apache/axiom/om/OMProcessingInstruction;Ljava/lang/String;)[B
     110: invokevirtual #17                 // Method java/io/DataOutputStream.write:([B)V
     113: goto          142
     116: aload         9
     118: invokeinterface #14,  1           // InterfaceMethod org/apache/axiom/om/OMNode.getType:()I
     123: iconst_1
     124: if_icmpne     142
     127: aload         6
     129: aload_0
     130: aload         9
     132: checkcast     #18                 // class org/apache/axiom/om/OMElement
     135: aload_2
     136: invokevirtual #19                 // Method getDigest:(Lorg/apache/axiom/om/OMElement;Ljava/lang/String;)[B
     139: invokevirtual #17                 // Method java/io/DataOutputStream.write:([B)V
     142: goto          65
     145: aload         6
     147: invokevirtual #20                 // Method java/io/DataOutputStream.close:()V
     150: aload         4
     152: aload         5
     154: invokevirtual #21                 // Method java/io/ByteArrayOutputStream.toByteArray:()[B
     157: invokevirtual #22                 // Method java/security/MessageDigest.update:([B)V
     160: aload         4
     162: invokevirtual #23                 // Method java/security/MessageDigest.digest:()[B
     165: astore_3
     166: goto          193
     169: astore        4
     171: new           #25                 // class org/apache/axiom/om/OMException
     174: dup
     175: aload         4
     177: invokespecial #26                 // Method org/apache/axiom/om/OMException."<init>":(Ljava/lang/Throwable;)V
     180: athrow
     181: astore        4
     183: new           #25                 // class org/apache/axiom/om/OMException
     186: dup
     187: aload         4
     189: invokespecial #26                 // Method org/apache/axiom/om/OMException."<init>":(Ljava/lang/Throwable;)V
     192: athrow
     193: aload_3
     194: areturn
    Exception table:
       from    to  target type
           4   166   169   Class java/security/NoSuchAlgorithmException
           4   166   181   Class java/io/IOException

  public byte[] getDigest(org.apache.axiom.om.OMNode, java.lang.String);
    Code:
       0: aload_1
       1: invokeinterface #14,  1           // InterfaceMethod org/apache/axiom/om/OMNode.getType:()I
       6: iconst_1
       7: if_icmpne     20
      10: aload_0
      11: aload_1
      12: checkcast     #18                 // class org/apache/axiom/om/OMElement
      15: aload_2
      16: invokevirtual #19                 // Method getDigest:(Lorg/apache/axiom/om/OMElement;Ljava/lang/String;)[B
      19: areturn
      20: aload_1
      21: invokeinterface #14,  1           // InterfaceMethod org/apache/axiom/om/OMNode.getType:()I
      26: iconst_4
      27: if_icmpne     40
      30: aload_0
      31: aload_1
      32: checkcast     #28                 // class org/apache/axiom/om/OMText
      35: aload_2
      36: invokevirtual #29                 // Method getDigest:(Lorg/apache/axiom/om/OMText;Ljava/lang/String;)[B
      39: areturn
      40: aload_1
      41: invokeinterface #14,  1           // InterfaceMethod org/apache/axiom/om/OMNode.getType:()I
      46: iconst_3
      47: if_icmpne     60
      50: aload_0
      51: aload_1
      52: checkcast     #15                 // class org/apache/axiom/om/OMProcessingInstruction
      55: aload_2
      56: invokevirtual #16                 // Method getDigest:(Lorg/apache/axiom/om/OMProcessingInstruction;Ljava/lang/String;)[B
      59: areturn
      60: iconst_0
      61: newarray       byte
      63: areturn

  public byte[] getDigest(org.apache.axiom.om.OMElement, java.lang.String) throws org.apache.axiom.om.OMException;
    Code:
       0: iconst_0
       1: newarray       byte
       3: astore_3
       4: aload_2
       5: invokestatic  #2                  // Method java/security/MessageDigest.getInstance:(Ljava/lang/String;)Ljava/security/MessageDigest;
       8: astore        4
      10: new           #3                  // class java/io/ByteArrayOutputStream
      13: dup
      14: invokespecial #4                  // Method java/io/ByteArrayOutputStream."<init>":()V
      17: astore        5
      19: new           #5                  // class java/io/DataOutputStream
      22: dup
      23: aload         5
      25: invokespecial #6                  // Method java/io/DataOutputStream."<init>":(Ljava/io/OutputStream;)V
      28: astore        6
      30: aload         6
      32: iconst_1
      33: invokevirtual #7                  // Method java/io/DataOutputStream.writeInt:(I)V
      36: aload         6
      38: aload_0
      39: aload_1
      40: invokevirtual #30                 // Method getExpandedName:(Lorg/apache/axiom/om/OMElement;)Ljava/lang/String;
      43: ldc           #31                 // String UnicodeBigUnmarked
      45: invokevirtual #32                 // Method java/lang/String.getBytes:(Ljava/lang/String;)[B
      48: invokevirtual #17                 // Method java/io/DataOutputStream.write:([B)V
      51: aload         6
      53: iconst_0
      54: invokevirtual #33                 // Method java/io/DataOutputStream.write:(I)V
      57: aload         6
      59: iconst_0
      60: invokevirtual #33                 // Method java/io/DataOutputStream.write:(I)V
      63: aload_0
      64: aload_1
      65: invokevirtual #34                 // Method getAttributesWithoutNS:(Lorg/apache/axiom/om/OMElement;)Ljava/util/Collection;
      68: astore        7
      70: aload         6
      72: aload         7
      74: invokeinterface #9,  1            // InterfaceMethod java/util/Collection.size:()I
      79: invokevirtual #7                  // Method java/io/DataOutputStream.writeInt:(I)V
      82: aload         7
      84: invokeinterface #10,  1           // InterfaceMethod java/util/Collection.iterator:()Ljava/util/Iterator;
      89: astore        8
      91: aload         8
      93: invokeinterface #11,  1           // InterfaceMethod java/util/Iterator.hasNext:()Z
      98: ifeq          124
     101: aload         6
     103: aload_0
     104: aload         8
     106: invokeinterface #12,  1           // InterfaceMethod java/util/Iterator.next:()Ljava/lang/Object;
     111: checkcast     #35                 // class org/apache/axiom/om/OMAttribute
     114: aload_2
     115: invokevirtual #36                 // Method getDigest:(Lorg/apache/axiom/om/OMAttribute;Ljava/lang/String;)[B
     118: invokevirtual #17                 // Method java/io/DataOutputStream.write:([B)V
     121: goto          91
     124: aload_1
     125: invokeinterface #37,  1           // InterfaceMethod org/apache/axiom/om/OMElement.getFirstOMChild:()Lorg/apache/axiom/om/OMNode;
     130: astore        9
     132: iconst_0
     133: istore        10
     135: aload_1
     136: invokeinterface #38,  1           // InterfaceMethod org/apache/axiom/om/OMElement.getChildren:()Ljava/util/Iterator;
     141: astore        8
     143: aload         8
     145: invokeinterface #11,  1           // InterfaceMethod java/util/Iterator.hasNext:()Z
     150: ifeq          195
     153: aload         8
     155: invokeinterface #12,  1           // InterfaceMethod java/util/Iterator.next:()Ljava/lang/Object;
     160: checkcast     #13                 // class org/apache/axiom/om/OMNode
     163: astore        11
     165: aload         11
     167: instanceof    #18                 // class org/apache/axiom/om/OMElement
     170: ifne          189
     173: aload         11
     175: instanceof    #28                 // class org/apache/axiom/om/OMText
     178: ifne          189
     181: aload         11
     183: instanceof    #15                 // class org/apache/axiom/om/OMProcessingInstruction
     186: ifeq          192
     189: iinc          10, 1
     192: goto          143
     195: aload         6
     197: iload         10
     199: invokevirtual #7                  // Method java/io/DataOutputStream.writeInt:(I)V
     202: aload         9
     204: ifnull        231
     207: aload         6
     209: aload_0
     210: aload         9
     212: aload_2
     213: invokevirtual #39                 // Method getDigest:(Lorg/apache/axiom/om/OMNode;Ljava/lang/String;)[B
     216: invokevirtual #17                 // Method java/io/DataOutputStream.write:([B)V
     219: aload         9
     221: invokeinterface #40,  1           // InterfaceMethod org/apache/axiom/om/OMNode.getNextOMSibling:()Lorg/apache/axiom/om/OMNode;
     226: astore        9
     228: goto          202
     231: aload         6
     233: invokevirtual #20                 // Method java/io/DataOutputStream.close:()V
     236: aload         4
     238: aload         5
     240: invokevirtual #21                 // Method java/io/ByteArrayOutputStream.toByteArray:()[B
     243: invokevirtual #22                 // Method java/security/MessageDigest.update:([B)V
     246: aload         4
     248: invokevirtual #23                 // Method java/security/MessageDigest.digest:()[B
     251: astore_3
     252: goto          279
     255: astore        4
     257: new           #25                 // class org/apache/axiom/om/OMException
     260: dup
     261: aload         4
     263: invokespecial #26                 // Method org/apache/axiom/om/OMException."<init>":(Ljava/lang/Throwable;)V
     266: athrow
     267: astore        4
     269: new           #25                 // class org/apache/axiom/om/OMException
     272: dup
     273: aload         4
     275: invokespecial #26                 // Method org/apache/axiom/om/OMException."<init>":(Ljava/lang/Throwable;)V
     278: athrow
     279: aload_3
     280: areturn
    Exception table:
       from    to  target type
           4   252   255   Class java/security/NoSuchAlgorithmException
           4   252   267   Class java/io/IOException

  public byte[] getDigest(org.apache.axiom.om.OMProcessingInstruction, java.lang.String) throws org.apache.axiom.om.OMException;
    Code:
       0: iconst_0
       1: newarray       byte
       3: astore_3
       4: aload_2
       5: invokestatic  #2                  // Method java/security/MessageDigest.getInstance:(Ljava/lang/String;)Ljava/security/MessageDigest;
       8: astore        4
      10: aload         4
      12: iconst_0
      13: invokevirtual #41                 // Method java/security/MessageDigest.update:(B)V
      16: aload         4
      18: iconst_0
      19: invokevirtual #41                 // Method java/security/MessageDigest.update:(B)V
      22: aload         4
      24: iconst_0
      25: invokevirtual #41                 // Method java/security/MessageDigest.update:(B)V
      28: aload         4
      30: bipush        7
      32: invokevirtual #41                 // Method java/security/MessageDigest.update:(B)V
      35: aload         4
      37: aload_1
      38: invokeinterface #42,  1           // InterfaceMethod org/apache/axiom/om/OMProcessingInstruction.getTarget:()Ljava/lang/String;
      43: ldc           #31                 // String UnicodeBigUnmarked
      45: invokevirtual #32                 // Method java/lang/String.getBytes:(Ljava/lang/String;)[B
      48: invokevirtual #22                 // Method java/security/MessageDigest.update:([B)V
      51: aload         4
      53: iconst_0
      54: invokevirtual #41                 // Method java/security/MessageDigest.update:(B)V
      57: aload         4
      59: iconst_0
      60: invokevirtual #41                 // Method java/security/MessageDigest.update:(B)V
      63: aload         4
      65: aload_1
      66: invokeinterface #43,  1           // InterfaceMethod org/apache/axiom/om/OMProcessingInstruction.getValue:()Ljava/lang/String;
      71: ldc           #31                 // String UnicodeBigUnmarked
      73: invokevirtual #32                 // Method java/lang/String.getBytes:(Ljava/lang/String;)[B
      76: invokevirtual #22                 // Method java/security/MessageDigest.update:([B)V
      79: aload         4
      81: invokevirtual #23                 // Method java/security/MessageDigest.digest:()[B
      84: astore_3
      85: goto          112
      88: astore        4
      90: new           #25                 // class org/apache/axiom/om/OMException
      93: dup
      94: aload         4
      96: invokespecial #26                 // Method org/apache/axiom/om/OMException."<init>":(Ljava/lang/Throwable;)V
      99: athrow
     100: astore        4
     102: new           #25                 // class org/apache/axiom/om/OMException
     105: dup
     106: aload         4
     108: invokespecial #26                 // Method org/apache/axiom/om/OMException."<init>":(Ljava/lang/Throwable;)V
     111: athrow
     112: aload_3
     113: areturn
    Exception table:
       from    to  target type
           4    85    88   Class java/security/NoSuchAlgorithmException
           4    85   100   Class java/io/UnsupportedEncodingException

  public byte[] getDigest(org.apache.axiom.om.OMAttribute, java.lang.String) throws org.apache.axiom.om.OMException;
    Code:
       0: iconst_0
       1: newarray       byte
       3: astore_3
       4: aload_1
       5: invokeinterface #45,  1           // InterfaceMethod org/apache/axiom/om/OMAttribute.getLocalName:()Ljava/lang/String;
      10: ldc           #46                 // String xmlns
      12: invokevirtual #47                 // Method java/lang/String.equals:(Ljava/lang/Object;)Z
      15: ifne          138
      18: aload_1
      19: invokeinterface #45,  1           // InterfaceMethod org/apache/axiom/om/OMAttribute.getLocalName:()Ljava/lang/String;
      24: ldc           #48                 // String xmlns:
      26: invokevirtual #49                 // Method java/lang/String.startsWith:(Ljava/lang/String;)Z
      29: ifne          138
      32: aload_2
      33: invokestatic  #2                  // Method java/security/MessageDigest.getInstance:(Ljava/lang/String;)Ljava/security/MessageDigest;
      36: astore        4
      38: aload         4
      40: iconst_0
      41: invokevirtual #41                 // Method java/security/MessageDigest.update:(B)V
      44: aload         4
      46: iconst_0
      47: invokevirtual #41                 // Method java/security/MessageDigest.update:(B)V
      50: aload         4
      52: iconst_0
      53: invokevirtual #41                 // Method java/security/MessageDigest.update:(B)V
      56: aload         4
      58: iconst_2
      59: invokevirtual #41                 // Method java/security/MessageDigest.update:(B)V
      62: aload         4
      64: aload_0
      65: aload_1
      66: invokevirtual #50                 // Method getExpandedName:(Lorg/apache/axiom/om/OMAttribute;)Ljava/lang/String;
      69: ldc           #31                 // String UnicodeBigUnmarked
      71: invokevirtual #32                 // Method java/lang/String.getBytes:(Ljava/lang/String;)[B
      74: invokevirtual #22                 // Method java/security/MessageDigest.update:([B)V
      77: aload         4
      79: iconst_0
      80: invokevirtual #41                 // Method java/security/MessageDigest.update:(B)V
      83: aload         4
      85: iconst_0
      86: invokevirtual #41                 // Method java/security/MessageDigest.update:(B)V
      89: aload         4
      91: aload_1
      92: invokeinterface #51,  1           // InterfaceMethod org/apache/axiom/om/OMAttribute.getAttributeValue:()Ljava/lang/String;
      97: ldc           #31                 // String UnicodeBigUnmarked
      99: invokevirtual #32                 // Method java/lang/String.getBytes:(Ljava/lang/String;)[B
     102: invokevirtual #22                 // Method java/security/MessageDigest.update:([B)V
     105: aload         4
     107: invokevirtual #23                 // Method java/security/MessageDigest.digest:()[B
     110: astore_3
     111: goto          138
     114: astore        4
     116: new           #25                 // class org/apache/axiom/om/OMException
     119: dup
     120: aload         4
     122: invokespecial #26                 // Method org/apache/axiom/om/OMException."<init>":(Ljava/lang/Throwable;)V
     125: athrow
     126: astore        4
     128: new           #25                 // class org/apache/axiom/om/OMException
     131: dup
     132: aload         4
     134: invokespecial #26                 // Method org/apache/axiom/om/OMException."<init>":(Ljava/lang/Throwable;)V
     137: athrow
     138: aload_3
     139: areturn
    Exception table:
       from    to  target type
          32   111   114   Class java/security/NoSuchAlgorithmException
          32   111   126   Class java/io/UnsupportedEncodingException

  public byte[] getDigest(org.apache.axiom.om.OMText, java.lang.String) throws org.apache.axiom.om.OMException;
    Code:
       0: iconst_0
       1: newarray       byte
       3: astore_3
       4: aload_2
       5: invokestatic  #2                  // Method java/security/MessageDigest.getInstance:(Ljava/lang/String;)Ljava/security/MessageDigest;
       8: astore        4
      10: aload         4
      12: iconst_0
      13: invokevirtual #41                 // Method java/security/MessageDigest.update:(B)V
      16: aload         4
      18: iconst_0
      19: invokevirtual #41                 // Method java/security/MessageDigest.update:(B)V
      22: aload         4
      24: iconst_0
      25: invokevirtual #41                 // Method java/security/MessageDigest.update:(B)V
      28: aload         4
      30: iconst_3
      31: invokevirtual #41                 // Method java/security/MessageDigest.update:(B)V
      34: aload         4
      36: aload_1
      37: invokeinterface #52,  1           // InterfaceMethod org/apache/axiom/om/OMText.getText:()Ljava/lang/String;
      42: ldc           #31                 // String UnicodeBigUnmarked
      44: invokevirtual #32                 // Method java/lang/String.getBytes:(Ljava/lang/String;)[B
      47: invokevirtual #22                 // Method java/security/MessageDigest.update:([B)V
      50: aload         4
      52: invokevirtual #23                 // Method java/security/MessageDigest.digest:()[B
      55: astore_3
      56: goto          83
      59: astore        4
      61: new           #25                 // class org/apache/axiom/om/OMException
      64: dup
      65: aload         4
      67: invokespecial #26                 // Method org/apache/axiom/om/OMException."<init>":(Ljava/lang/Throwable;)V
      70: athrow
      71: astore        4
      73: new           #25                 // class org/apache/axiom/om/OMException
      76: dup
      77: aload         4
      79: invokespecial #26                 // Method org/apache/axiom/om/OMException."<init>":(Ljava/lang/Throwable;)V
      82: athrow
      83: aload_3
      84: areturn
    Exception table:
       from    to  target type
           4    56    59   Class java/security/NoSuchAlgorithmException
           4    56    71   Class java/io/UnsupportedEncodingException

  public java.lang.String getExpandedName(org.apache.axiom.om.OMElement);
    Code:
       0: aload_0
       1: aload_1
       2: invokespecial #53                 // Method internalGetExpandedName:(Lorg/apache/axiom/om/OMNamedInformationItem;)Ljava/lang/String;
       5: areturn

  public java.lang.String getExpandedName(org.apache.axiom.om.OMAttribute);
    Code:
       0: aload_0
       1: aload_1
       2: invokespecial #53                 // Method internalGetExpandedName:(Lorg/apache/axiom/om/OMNamedInformationItem;)Ljava/lang/String;
       5: areturn

  private java.lang.String internalGetExpandedName(org.apache.axiom.om.OMNamedInformationItem);
    Code:
       0: aload_1
       1: invokeinterface #54,  1           // InterfaceMethod org/apache/axiom/om/OMNamedInformationItem.getNamespaceURI:()Ljava/lang/String;
       6: astore_2
       7: aload_2
       8: ifnonnull     20
      11: aload_1
      12: invokeinterface #55,  1           // InterfaceMethod org/apache/axiom/om/OMNamedInformationItem.getLocalName:()Ljava/lang/String;
      17: goto          48
      20: new           #56                 // class java/lang/StringBuilder
      23: dup
      24: invokespecial #57                 // Method java/lang/StringBuilder."<init>":()V
      27: aload_2
      28: invokevirtual #58                 // Method java/lang/StringBuilder.append:(Ljava/lang/String;)Ljava/lang/StringBuilder;
      31: ldc           #59                 // String :
      33: invokevirtual #58                 // Method java/lang/StringBuilder.append:(Ljava/lang/String;)Ljava/lang/StringBuilder;
      36: aload_1
      37: invokeinterface #55,  1           // InterfaceMethod org/apache/axiom/om/OMNamedInformationItem.getLocalName:()Ljava/lang/String;
      42: invokevirtual #58                 // Method java/lang/StringBuilder.append:(Ljava/lang/String;)Ljava/lang/StringBuilder;
      45: invokevirtual #60                 // Method java/lang/StringBuilder.toString:()Ljava/lang/String;
      48: areturn

  public java.util.Collection getAttributesWithoutNS(org.apache.axiom.om.OMElement);
    Code:
       0: new           #61                 // class java/util/TreeMap
       3: dup
       4: invokespecial #62                 // Method java/util/TreeMap."<init>":()V
       7: astore_2
       8: aload_1
       9: invokeinterface #63,  1           // InterfaceMethod org/apache/axiom/om/OMElement.getAllAttributes:()Ljava/util/Iterator;
      14: astore_3
      15: aload_3
      16: invokeinterface #11,  1           // InterfaceMethod java/util/Iterator.hasNext:()Z
      21: ifeq          83
      24: aload_3
      25: invokeinterface #12,  1           // InterfaceMethod java/util/Iterator.next:()Ljava/lang/Object;
      30: checkcast     #35                 // class org/apache/axiom/om/OMAttribute
      33: astore        4
      35: aload         4
      37: invokeinterface #45,  1           // InterfaceMethod org/apache/axiom/om/OMAttribute.getLocalName:()Ljava/lang/String;
      42: ldc           #46                 // String xmlns
      44: invokevirtual #47                 // Method java/lang/String.equals:(Ljava/lang/Object;)Z
      47: ifne          80
      50: aload         4
      52: invokeinterface #45,  1           // InterfaceMethod org/apache/axiom/om/OMAttribute.getLocalName:()Ljava/lang/String;
      57: ldc           #48                 // String xmlns:
      59: invokevirtual #49                 // Method java/lang/String.startsWith:(Ljava/lang/String;)Z
      62: ifne          80
      65: aload_2
      66: aload_0
      67: aload         4
      69: invokevirtual #50                 // Method getExpandedName:(Lorg/apache/axiom/om/OMAttribute;)Ljava/lang/String;
      72: aload         4
      74: invokeinterface #64,  3           // InterfaceMethod java/util/SortedMap.put:(Ljava/lang/Object;Ljava/lang/Object;)Ljava/lang/Object;
      79: pop
      80: goto          15
      83: aload_2
      84: invokeinterface #65,  1           // InterfaceMethod java/util/SortedMap.values:()Ljava/util/Collection;
      89: areturn

  public java.util.Collection getValidElements(org.apache.axiom.om.OMDocument);
    Code:
       0: new           #66                 // class java/util/ArrayList
       3: dup
       4: invokespecial #67                 // Method java/util/ArrayList."<init>":()V
       7: astore_2
       8: aload_1
       9: invokeinterface #68,  1           // InterfaceMethod org/apache/axiom/om/OMDocument.getChildren:()Ljava/util/Iterator;
      14: astore_3
      15: aload_3
      16: invokeinterface #11,  1           // InterfaceMethod java/util/Iterator.hasNext:()Z
      21: ifeq          67
      24: aload_3
      25: invokeinterface #12,  1           // InterfaceMethod java/util/Iterator.next:()Ljava/lang/Object;
      30: checkcast     #13                 // class org/apache/axiom/om/OMNode
      33: astore        4
      35: aload         4
      37: invokeinterface #14,  1           // InterfaceMethod org/apache/axiom/om/OMNode.getType:()I
      42: iconst_1
      43: if_icmpeq     57
      46: aload         4
      48: invokeinterface #14,  1           // InterfaceMethod org/apache/axiom/om/OMNode.getType:()I
      53: iconst_3
      54: if_icmpne     64
      57: aload_2
      58: aload         4
      60: invokevirtual #69                 // Method java/util/ArrayList.add:(Ljava/lang/Object;)Z
      63: pop
      64: goto          15
      67: aload_2
      68: areturn

  public java.lang.String getStringRepresentation(byte[]);
    Code:
       0: ldc           #70                 // String
       2: astore_2
       3: iconst_0
       4: istore_3
       5: iload_3
       6: aload_1
       7: arraylength
       8: if_icmpge     38
      11: new           #56                 // class java/lang/StringBuilder
      14: dup
      15: invokespecial #57                 // Method java/lang/StringBuilder."<init>":()V
      18: aload_2
      19: invokevirtual #58                 // Method java/lang/StringBuilder.append:(Ljava/lang/String;)Ljava/lang/StringBuilder;
      22: aload_1
      23: iload_3
      24: baload
      25: invokevirtual #71                 // Method java/lang/StringBuilder.append:(I)Ljava/lang/StringBuilder;
      28: invokevirtual #60                 // Method java/lang/StringBuilder.toString:()Ljava/lang/String;
      31: astore_2
      32: iinc          3, 1
      35: goto          5
      38: aload_2
      39: areturn

  public boolean compareOMNode(org.apache.axiom.om.OMNode, org.apache.axiom.om.OMNode, java.lang.String);
    Code:
       0: aload_0
       1: aload_1
       2: aload_3
       3: invokevirtual #39                 // Method getDigest:(Lorg/apache/axiom/om/OMNode;Ljava/lang/String;)[B
       6: aload_0
       7: aload_2
       8: aload_3
       9: invokevirtual #39                 // Method getDigest:(Lorg/apache/axiom/om/OMNode;Ljava/lang/String;)[B
      12: invokestatic  #72                 // Method java/util/Arrays.equals:([B[B)Z
      15: ireturn

  public boolean compareOMDocument(org.apache.axiom.om.OMDocument, org.apache.axiom.om.OMDocument, java.lang.String);
    Code:
       0: aload_0
       1: aload_1
       2: aload_3
       3: invokevirtual #73                 // Method getDigest:(Lorg/apache/axiom/om/OMDocument;Ljava/lang/String;)[B
       6: aload_0
       7: aload_2
       8: aload_3
       9: invokevirtual #73                 // Method getDigest:(Lorg/apache/axiom/om/OMDocument;Ljava/lang/String;)[B
      12: invokestatic  #72                 // Method java/util/Arrays.equals:([B[B)Z
      15: ireturn

  public boolean compareOMAttribute(org.apache.axiom.om.OMAttribute, org.apache.axiom.om.OMAttribute, java.lang.String);
    Code:
       0: aload_0
       1: aload_1
       2: aload_3
       3: invokevirtual #36                 // Method getDigest:(Lorg/apache/axiom/om/OMAttribute;Ljava/lang/String;)[B
       6: aload_0
       7: aload_2
       8: aload_3
       9: invokevirtual #36                 // Method getDigest:(Lorg/apache/axiom/om/OMAttribute;Ljava/lang/String;)[B
      12: invokestatic  #72                 // Method java/util/Arrays.equals:([B[B)Z
      15: ireturn
}
