Compiled from "AbstractStreamSinkConduit.java"
public abstract class org.xnio.conduits.AbstractStreamSinkConduit<D extends org.xnio.conduits.StreamSinkConduit> extends org.xnio.conduits.AbstractSinkConduit<D> implements org.xnio.conduits.StreamSinkConduit {
  protected org.xnio.conduits.AbstractStreamSinkConduit(D);
    Code:
       0: aload_0
       1: aload_1
       2: invokespecial #13                 // Method org/xnio/conduits/AbstractSinkConduit."<init>":(Lorg/xnio/conduits/SinkConduit;)V
       5: return

  public long transferFrom(java.nio.channels.FileChannel, long, long) throws java.io.IOException;
    Code:
       0: aload_0
       1: getfield      #26                 // Field next:Lorg/xnio/conduits/Conduit;
       4: checkcast     #7                  // class org/xnio/conduits/StreamSinkConduit
       7: aload_1
       8: lload_2
       9: lload         4
      11: invokeinterface #28,  6           // InterfaceMethod org/xnio/conduits/StreamSinkConduit.transferFrom:(Ljava/nio/channels/FileChannel;JJ)J
      16: lreturn

  public long transferFrom(org.xnio.channels.StreamSourceChannel, long, java.nio.ByteBuffer) throws java.io.IOException;
    Code:
       0: aload_0
       1: getfield      #26                 // Field next:Lorg/xnio/conduits/Conduit;
       4: checkcast     #7                  // class org/xnio/conduits/StreamSinkConduit
       7: aload_1
       8: lload_2
       9: aload         4
      11: invokeinterface #36,  5           // InterfaceMethod org/xnio/conduits/StreamSinkConduit.transferFrom:(Lorg/xnio/channels/StreamSourceChannel;JLjava/nio/ByteBuffer;)J
      16: lreturn

  public int write(java.nio.ByteBuffer) throws java.io.IOException;
    Code:
       0: aload_0
       1: getfield      #26                 // Field next:Lorg/xnio/conduits/Conduit;
       4: checkcast     #7                  // class org/xnio/conduits/StreamSinkConduit
       7: aload_1
       8: invokeinterface #44,  2           // InterfaceMethod org/xnio/conduits/StreamSinkConduit.write:(Ljava/nio/ByteBuffer;)I
      13: ireturn

  public long write(java.nio.ByteBuffer[], int, int) throws java.io.IOException;
    Code:
       0: aload_0
       1: getfield      #26                 // Field next:Lorg/xnio/conduits/Conduit;
       4: checkcast     #7                  // class org/xnio/conduits/StreamSinkConduit
       7: aload_1
       8: iload_2
       9: iload_3
      10: invokeinterface #47,  4           // InterfaceMethod org/xnio/conduits/StreamSinkConduit.write:([Ljava/nio/ByteBuffer;II)J
      15: lreturn

  public int writeFinal(java.nio.ByteBuffer) throws java.io.IOException;
    Code:
       0: aload_0
       1: getfield      #26                 // Field next:Lorg/xnio/conduits/Conduit;
       4: checkcast     #7                  // class org/xnio/conduits/StreamSinkConduit
       7: aload_1
       8: invokeinterface #55,  2           // InterfaceMethod org/xnio/conduits/StreamSinkConduit.writeFinal:(Ljava/nio/ByteBuffer;)I
      13: ireturn

  public long writeFinal(java.nio.ByteBuffer[], int, int) throws java.io.IOException;
    Code:
       0: aload_0
       1: getfield      #26                 // Field next:Lorg/xnio/conduits/Conduit;
       4: checkcast     #7                  // class org/xnio/conduits/StreamSinkConduit
       7: aload_1
       8: iload_2
       9: iload_3
      10: invokeinterface #57,  4           // InterfaceMethod org/xnio/conduits/StreamSinkConduit.writeFinal:([Ljava/nio/ByteBuffer;II)J
      15: lreturn
}
