Compiled from "MessageStreamSinkConduit.java"
public final class org.xnio.conduits.MessageStreamSinkConduit extends org.xnio.conduits.AbstractSinkConduit<org.xnio.conduits.MessageSinkConduit> implements org.xnio.conduits.StreamSinkConduit {
  public org.xnio.conduits.MessageStreamSinkConduit(org.xnio.conduits.MessageSinkConduit);
    Code:
       0: aload_0
       1: aload_1
       2: invokespecial #13                 // Method org/xnio/conduits/AbstractSinkConduit."<init>":(Lorg/xnio/conduits/SinkConduit;)V
       5: return

  public long transferFrom(java.nio.channels.FileChannel, long, long) throws java.io.IOException;
    Code:
       0: aload_1
       1: lload_2
       2: lload         4
       4: new           #23                 // class org/xnio/conduits/ConduitWritableByteChannel
       7: dup
       8: aload_0
       9: invokespecial #26                 // Method org/xnio/conduits/ConduitWritableByteChannel."<init>":(Lorg/xnio/conduits/StreamSinkConduit;)V
      12: invokevirtual #32                 // Method java/nio/channels/FileChannel.transferTo:(JJLjava/nio/channels/WritableByteChannel;)J
      15: lreturn

  public long transferFrom(org.xnio.channels.StreamSourceChannel, long, java.nio.ByteBuffer) throws java.io.IOException;
    Code:
       0: aload_1
       1: lload_2
       2: aload         4
       4: aload_0
       5: invokestatic  #44                 // Method org/xnio/conduits/Conduits.transfer:(Ljava/nio/channels/ReadableByteChannel;JLjava/nio/ByteBuffer;Lorg/xnio/conduits/StreamSinkConduit;)J
       8: lreturn

  public int write(java.nio.ByteBuffer) throws java.io.IOException;
    Code:
       0: aload_1
       1: invokevirtual #56                 // Method java/nio/ByteBuffer.remaining:()I
       4: istore_2
       5: aload_0
       6: getfield      #59                 // Field next:Lorg/xnio/conduits/Conduit;
       9: checkcast     #61                 // class org/xnio/conduits/MessageSinkConduit
      12: aload_1
      13: invokeinterface #65,  2           // InterfaceMethod org/xnio/conduits/MessageSinkConduit.send:(Ljava/nio/ByteBuffer;)Z
      18: ifeq          25
      21: iload_2
      22: goto          26
      25: iconst_0
      26: ireturn

  public long write(java.nio.ByteBuffer[], int, int) throws java.io.IOException;
    Code:
       0: aload_1
       1: iload_2
       2: iload_3
       3: invokestatic  #72                 // Method org/xnio/Buffers.remaining:([Ljava/nio/Buffer;II)J
       6: lstore        4
       8: aload_0
       9: getfield      #59                 // Field next:Lorg/xnio/conduits/Conduit;
      12: checkcast     #61                 // class org/xnio/conduits/MessageSinkConduit
      15: aload_1
      16: iload_2
      17: iload_3
      18: invokeinterface #75,  4           // InterfaceMethod org/xnio/conduits/MessageSinkConduit.send:([Ljava/nio/ByteBuffer;II)Z
      23: ifeq          31
      26: lload         4
      28: goto          32
      31: lconst_0
      32: lreturn

  public int writeFinal(java.nio.ByteBuffer) throws java.io.IOException;
    Code:
       0: aload_0
       1: aload_1
       2: invokestatic  #84                 // Method org/xnio/conduits/Conduits.writeFinalBasic:(Lorg/xnio/conduits/StreamSinkConduit;Ljava/nio/ByteBuffer;)I
       5: ireturn

  public long writeFinal(java.nio.ByteBuffer[], int, int) throws java.io.IOException;
    Code:
       0: aload_0
       1: aload_1
       2: iload_2
       3: iload_3
       4: invokestatic  #87                 // Method org/xnio/conduits/Conduits.writeFinalBasic:(Lorg/xnio/conduits/StreamSinkConduit;[Ljava/nio/ByteBuffer;II)J
       7: lreturn
}
