Compiled from "SecurityActions.java"
final class org.jboss.security.mapping.providers.role.SecurityActions$3 implements java.security.PrivilegedAction<java.net.URL> {
  final java.net.URLClassLoader val$cl;

  final java.lang.String val$name;

  org.jboss.security.mapping.providers.role.SecurityActions$3(java.net.URLClassLoader, java.lang.String);
    Code:
       0: aload_0
       1: aload_1
       2: putfield      #1                  // Field val$cl:Ljava/net/URLClassLoader;
       5: aload_0
       6: aload_2
       7: putfield      #2                  // Field val$name:Ljava/lang/String;
      10: aload_0
      11: invokespecial #3                  // Method java/lang/Object."<init>":()V
      14: return

  public java.net.URL run();
    Code:
       0: aload_0
       1: getfield      #1                  // Field val$cl:Ljava/net/URLClassLoader;
       4: aload_0
       5: getfield      #2                  // Field val$name:Ljava/lang/String;
       8: invokevirtual #4                  // Method java/net/URLClassLoader.findResource:(Ljava/lang/String;)Ljava/net/URL;
      11: areturn

  public java.lang.Object run();
    Code:
       0: aload_0
       1: invokevirtual #5                  // Method run:()Ljava/net/URL;
       4: areturn
}
