Compiled from "CachingMappingDiscoverer.java"
class org.springframework.hateoas.core.CachingMappingDiscoverer$2 implements org.springframework.hateoas.core.CachingMappingDiscoverer$CachedCall {
  final java.lang.reflect.Method val$method;

  final org.springframework.hateoas.core.CachingMappingDiscoverer this$0;

  org.springframework.hateoas.core.CachingMappingDiscoverer$2(org.springframework.hateoas.core.CachingMappingDiscoverer, java.lang.reflect.Method);
    Code:
       0: aload_0
       1: aload_1
       2: putfield      #1                  // Field this$0:Lorg/springframework/hateoas/core/CachingMappingDiscoverer;
       5: aload_0
       6: aload_2
       7: putfield      #2                  // Field val$method:Ljava/lang/reflect/Method;
      10: aload_0
      11: invokespecial #3                  // Method java/lang/Object."<init>":()V
      14: return

  public java.lang.String getMapping();
    Code:
       0: aload_0
       1: getfield      #1                  // Field this$0:Lorg/springframework/hateoas/core/CachingMappingDiscoverer;
       4: invokestatic  #4                  // Method org/springframework/hateoas/core/CachingMappingDiscoverer.access$000:(Lorg/springframework/hateoas/core/CachingMappingDiscoverer;)Lorg/springframework/hateoas/core/MappingDiscoverer;
       7: aload_0
       8: getfield      #2                  // Field val$method:Ljava/lang/reflect/Method;
      11: invokeinterface #5,  2            // InterfaceMethod org/springframework/hateoas/core/MappingDiscoverer.getMapping:(Ljava/lang/reflect/Method;)Ljava/lang/String;
      16: areturn
}
