Compiled from "MethodParameters.java"
class org.springframework.hateoas.core.MethodParameters$AnnotationNamingMethodParameter extends org.springframework.core.annotation.SynthesizingMethodParameter {
  private final org.springframework.hateoas.core.AnnotationAttribute attribute;

  private java.lang.String name;

  public org.springframework.hateoas.core.MethodParameters$AnnotationNamingMethodParameter(java.lang.reflect.Method, int, org.springframework.hateoas.core.AnnotationAttribute);
    Code:
       0: aload_0
       1: aload_1
       2: iload_2
       3: invokespecial #1                  // Method org/springframework/core/annotation/SynthesizingMethodParameter."<init>":(Ljava/lang/reflect/Method;I)V
       6: aload_0
       7: aload_3
       8: putfield      #2                  // Field attribute:Lorg/springframework/hateoas/core/AnnotationAttribute;
      11: return

  public java.lang.String getParameterName();
    Code:
       0: aload_0
       1: getfield      #3                  // Field name:Ljava/lang/String;
       4: ifnull        12
       7: aload_0
       8: getfield      #3                  // Field name:Ljava/lang/String;
      11: areturn
      12: aload_0
      13: getfield      #2                  // Field attribute:Lorg/springframework/hateoas/core/AnnotationAttribute;
      16: ifnull        42
      19: aload_0
      20: getfield      #2                  // Field attribute:Lorg/springframework/hateoas/core/AnnotationAttribute;
      23: aload_0
      24: invokevirtual #4                  // Method org/springframework/hateoas/core/AnnotationAttribute.getValueFrom:(Lorg/springframework/core/MethodParameter;)Ljava/lang/String;
      27: astore_1
      28: aload_1
      29: ifnull        42
      32: aload_0
      33: aload_1
      34: putfield      #3                  // Field name:Ljava/lang/String;
      37: aload_0
      38: getfield      #3                  // Field name:Ljava/lang/String;
      41: areturn
      42: aload_0
      43: aload_0
      44: invokespecial #5                  // Method org/springframework/core/annotation/SynthesizingMethodParameter.getParameterName:()Ljava/lang/String;
      47: putfield      #3                  // Field name:Ljava/lang/String;
      50: aload_0
      51: getfield      #3                  // Field name:Ljava/lang/String;
      54: areturn
}
