Compiled from "AbstractInvocationHandler.java"
public abstract class net.openhft.chronicle.core.util.AbstractInvocationHandler implements java.lang.reflect.InvocationHandler {
  private static final net.openhft.chronicle.core.ClassLocal<java.lang.invoke.MethodHandles$Lookup> PRIVATE_LOOKUP;

  private static final java.lang.Object[] NO_ARGS;

  private net.openhft.chronicle.core.io.Closeable closeable;

  protected net.openhft.chronicle.core.util.AbstractInvocationHandler(java.util.function.Supplier<java.util.Map>);
    Code:
       0: aload_0
       1: invokespecial #1                  // Method java/lang/Object."<init>":()V
       4: aload_1
       5: invokeinterface #2,  1            // InterfaceMethod java/util/function/Supplier.get:()Ljava/lang/Object;
      10: checkcast     #3                  // class java/util/Map
      13: astore_2
      14: aload_1
      15: invokeinterface #2,  1            // InterfaceMethod java/util/function/Supplier.get:()Ljava/lang/Object;
      20: checkcast     #3                  // class java/util/Map
      23: astore_3
      24: return

  private static java.lang.invoke.MethodHandles$Lookup acquireLookup(java.lang.Class<?>);
    Code:
       0: ldc           #4                  // class java/lang/invoke/MethodHandles$Lookup
       2: iconst_2
       3: anewarray     #5                  // class java/lang/Class
       6: dup
       7: iconst_0
       8: ldc           #5                  // class java/lang/Class
      10: aastore
      11: dup
      12: iconst_1
      13: getstatic     #6                  // Field java/lang/Integer.TYPE:Ljava/lang/Class;
      16: aastore
      17: invokevirtual #7                  // Method java/lang/Class.getDeclaredConstructor:([Ljava/lang/Class;)Ljava/lang/reflect/Constructor;
      20: astore_1
      21: aload_1
      22: invokevirtual #8                  // Method java/lang/reflect/Constructor.isAccessible:()Z
      25: ifne          32
      28: aload_1
      29: invokestatic  #9                  // Method net/openhft/chronicle/core/Jvm.setAccessible:(Ljava/lang/reflect/AccessibleObject;)V
      32: aload_1
      33: iconst_2
      34: anewarray     #10                 // class java/lang/Object
      37: dup
      38: iconst_0
      39: aload_0
      40: aastore
      41: dup
      42: iconst_1
      43: iconst_2
      44: invokestatic  #11                 // Method java/lang/Integer.valueOf:(I)Ljava/lang/Integer;
      47: aastore
      48: invokevirtual #12                 // Method java/lang/reflect/Constructor.newInstance:([Ljava/lang/Object;)Ljava/lang/Object;
      51: checkcast     #4                  // class java/lang/invoke/MethodHandles$Lookup
      54: areturn
      55: astore_1
      56: ldc           #4                  // class java/lang/invoke/MethodHandles$Lookup
      58: ldc           #18                 // String IMPL_LOOKUP
      60: invokevirtual #19                 // Method java/lang/Class.getDeclaredField:(Ljava/lang/String;)Ljava/lang/reflect/Field;
      63: astore_1
      64: aload_1
      65: invokestatic  #9                  // Method net/openhft/chronicle/core/Jvm.setAccessible:(Ljava/lang/reflect/AccessibleObject;)V
      68: aload_1
      69: aconst_null
      70: invokevirtual #20                 // Method java/lang/reflect/Field.get:(Ljava/lang/Object;)Ljava/lang/Object;
      73: checkcast     #4                  // class java/lang/invoke/MethodHandles$Lookup
      76: areturn
      77: astore_1
      78: invokestatic  #22                 // Method java/lang/invoke/MethodHandles.lookup:()Ljava/lang/invoke/MethodHandles$Lookup;
      81: areturn
    Exception table:
       from    to  target type
           0    54    55   Class java/lang/NoSuchMethodException
           0    54    55   Class java/lang/InstantiationException
           0    54    55   Class java/lang/IllegalAccessException
           0    54    55   Class java/lang/reflect/InvocationTargetException
           0    54    55   Class java/lang/IllegalArgumentException
          56    76    77   Class java/lang/Exception

  public final java.lang.Object invoke(java.lang.Object, java.lang.reflect.Method, java.lang.Object[]) throws java.lang.Throwable;
    Code:
       0: aload_2
       1: invokevirtual #23                 // Method java/lang/reflect/Method.getDeclaringClass:()Ljava/lang/Class;
       4: astore        4
       6: aload         4
       8: ldc           #10                 // class java/lang/Object
      10: if_acmpne     20
      13: aload_2
      14: aload_0
      15: aload_3
      16: invokevirtual #24                 // Method java/lang/reflect/Method.invoke:(Ljava/lang/Object;[Ljava/lang/Object;)Ljava/lang/Object;
      19: areturn
      20: aload         4
      22: ldc           #25                 // class net/openhft/chronicle/core/io/Closeable
      24: if_acmpne     48
      27: aload_2
      28: invokevirtual #26                 // Method java/lang/reflect/Method.getName:()Ljava/lang/String;
      31: ldc           #27                 // String close
      33: invokevirtual #28                 // Method java/lang/String.equals:(Ljava/lang/Object;)Z
      36: ifeq          48
      39: aload_0
      40: getfield      #29                 // Field closeable:Lnet/openhft/chronicle/core/io/Closeable;
      43: invokestatic  #30                 // InterfaceMethod net/openhft/chronicle/core/io/Closeable.closeQuietly:(Ljava/lang/Object;)V
      46: aconst_null
      47: areturn
      48: aload_3
      49: ifnonnull     56
      52: getstatic     #31                 // Field NO_ARGS:[Ljava/lang/Object;
      55: astore_3
      56: aload_0
      57: aload_1
      58: aload_2
      59: aload_3
      60: invokevirtual #32                 // Method doInvoke:(Ljava/lang/Object;Ljava/lang/reflect/Method;[Ljava/lang/Object;)Ljava/lang/Object;
      63: astore        5
      65: aload         5
      67: ifnonnull     83
      70: aload_2
      71: invokevirtual #33                 // Method java/lang/reflect/Method.getReturnType:()Ljava/lang/Class;
      74: aload_1
      75: invokevirtual #34                 // Method java/lang/Class.isInstance:(Ljava/lang/Object;)Z
      78: ifeq          83
      81: aload_1
      82: areturn
      83: aload         5
      85: ifnonnull     98
      88: aload_2
      89: invokevirtual #33                 // Method java/lang/reflect/Method.getReturnType:()Ljava/lang/Class;
      92: invokestatic  #35                 // Method net/openhft/chronicle/core/util/ObjectUtils.defaultValue:(Ljava/lang/Class;)Ljava/lang/Object;
      95: goto          100
      98: aload         5
     100: areturn

  protected abstract java.lang.Object doInvoke(java.lang.Object, java.lang.reflect.Method, java.lang.Object[]) throws java.lang.reflect.InvocationTargetException, java.lang.IllegalAccessException, java.lang.IllegalStateException, java.nio.BufferOverflowException, java.nio.BufferUnderflowException, java.lang.IllegalArgumentException, java.lang.ArithmeticException;

  java.lang.invoke.MethodHandle methodHandleForProxy(java.lang.Object, java.lang.reflect.Method);
    Code:
       0: aload_2
       1: invokevirtual #23                 // Method java/lang/reflect/Method.getDeclaringClass:()Ljava/lang/Class;
       4: astore_3
       5: getstatic     #36                 // Field PRIVATE_LOOKUP:Lnet/openhft/chronicle/core/ClassLocal;
       8: aload_3
       9: invokevirtual #37                 // Method net/openhft/chronicle/core/ClassLocal.get:(Ljava/lang/Class;)Ljava/lang/Object;
      12: checkcast     #4                  // class java/lang/invoke/MethodHandles$Lookup
      15: astore        4
      17: aload         4
      19: aload_3
      20: invokevirtual #38                 // Method java/lang/invoke/MethodHandles$Lookup.in:(Ljava/lang/Class;)Ljava/lang/invoke/MethodHandles$Lookup;
      23: aload_2
      24: aload_3
      25: invokevirtual #39                 // Method java/lang/invoke/MethodHandles$Lookup.unreflectSpecial:(Ljava/lang/reflect/Method;Ljava/lang/Class;)Ljava/lang/invoke/MethodHandle;
      28: aload_1
      29: invokevirtual #40                 // Method java/lang/invoke/MethodHandle.bindTo:(Ljava/lang/Object;)Ljava/lang/invoke/MethodHandle;
      32: areturn
      33: astore_3
      34: new           #41                 // class java/lang/AssertionError
      37: dup
      38: aload_3
      39: invokespecial #42                 // Method java/lang/AssertionError."<init>":(Ljava/lang/Object;)V
      42: athrow
    Exception table:
       from    to  target type
           0    32    33   Class java/lang/IllegalAccessException

  public void onClose(net.openhft.chronicle.core.io.Closeable);
    Code:
       0: aload_0
       1: aload_1
       2: putfield      #29                 // Field closeable:Lnet/openhft/chronicle/core/io/Closeable;
       5: return

  static {};
    Code:
       0: invokedynamic #43,  0             // InvokeDynamic #0:apply:()Ljava/util/function/Function;
       5: invokestatic  #44                 // Method net/openhft/chronicle/core/ClassLocal.withInitial:(Ljava/util/function/Function;)Lnet/openhft/chronicle/core/ClassLocal;
       8: putstatic     #36                 // Field PRIVATE_LOOKUP:Lnet/openhft/chronicle/core/ClassLocal;
      11: iconst_0
      12: anewarray     #10                 // class java/lang/Object
      15: putstatic     #31                 // Field NO_ARGS:[Ljava/lang/Object;
      18: return
}
