Compiled from "ObjectUtils.java"
final class net.openhft.chronicle.core.util.ObjectUtils$2 implements java.lang.reflect.InvocationHandler {
  final java.util.function.BiFunction val$biFunction;

  net.openhft.chronicle.core.util.ObjectUtils$2(java.util.function.BiFunction);
    Code:
       0: aload_0
       1: aload_1
       2: putfield      #1                  // Field val$biFunction:Ljava/util/function/BiFunction;
       5: aload_0
       6: invokespecial #2                  // Method java/lang/Object."<init>":()V
       9: return

  public java.lang.Object invoke(java.lang.Object, java.lang.reflect.Method, java.lang.Object[]) throws java.lang.Throwable;
    Code:
       0: aload_2
       1: invokevirtual #3                  // Method java/lang/reflect/Method.getDeclaringClass:()Ljava/lang/Class;
       4: ldc           #4                  // class java/lang/Object
       6: if_acmpne     16
       9: aload_2
      10: aload_0
      11: aload_3
      12: invokevirtual #5                  // Method java/lang/reflect/Method.invoke:(Ljava/lang/Object;[Ljava/lang/Object;)Ljava/lang/Object;
      15: areturn
      16: aload_0
      17: getfield      #1                  // Field val$biFunction:Ljava/util/function/BiFunction;
      20: aload_2
      21: aload_3
      22: invokeinterface #6,  3            // InterfaceMethod java/util/function/BiFunction.apply:(Ljava/lang/Object;Ljava/lang/Object;)Ljava/lang/Object;
      27: areturn
}
