Compiled from "UploadPartCopyRequestIterable.java"
class software.amazon.awssdk.services.s3.internal.crt.UploadPartCopyRequestIterable$UploadPartCopyRequestIterator implements java.util.Iterator<software.amazon.awssdk.services.s3.model.UploadPartCopyRequest> {
  final software.amazon.awssdk.services.s3.internal.crt.UploadPartCopyRequestIterable this$0;

  private software.amazon.awssdk.services.s3.internal.crt.UploadPartCopyRequestIterable$UploadPartCopyRequestIterator(software.amazon.awssdk.services.s3.internal.crt.UploadPartCopyRequestIterable);
    Code:
       0: aload_0
       1: aload_1
       2: putfield      #2                  // Field this$0:Lsoftware/amazon/awssdk/services/s3/internal/crt/UploadPartCopyRequestIterable;
       5: aload_0
       6: invokespecial #3                  // Method java/lang/Object."<init>":()V
       9: return

  public boolean hasNext();
    Code:
       0: aload_0
       1: getfield      #2                  // Field this$0:Lsoftware/amazon/awssdk/services/s3/internal/crt/UploadPartCopyRequestIterable;
       4: invokestatic  #4                  // Method software/amazon/awssdk/services/s3/internal/crt/UploadPartCopyRequestIterable.access$100:(Lsoftware/amazon/awssdk/services/s3/internal/crt/UploadPartCopyRequestIterable;)J
       7: lconst_0
       8: lcmp
       9: ifle          16
      12: iconst_1
      13: goto          17
      16: iconst_0
      17: ireturn

  public software.amazon.awssdk.services.s3.model.UploadPartCopyRequest next();
    Code:
       0: aload_0
       1: invokevirtual #5                  // Method hasNext:()Z
       4: ifne          17
       7: new           #6                  // class java/util/NoSuchElementException
      10: dup
      11: ldc           #7                  // String No UploadPartCopyRequest available
      13: invokespecial #8                  // Method java/util/NoSuchElementException."<init>":(Ljava/lang/String;)V
      16: athrow
      17: aload_0
      18: getfield      #2                  // Field this$0:Lsoftware/amazon/awssdk/services/s3/internal/crt/UploadPartCopyRequestIterable;
      21: invokestatic  #9                  // Method software/amazon/awssdk/services/s3/internal/crt/UploadPartCopyRequestIterable.access$200:(Lsoftware/amazon/awssdk/services/s3/internal/crt/UploadPartCopyRequestIterable;)J
      24: aload_0
      25: getfield      #2                  // Field this$0:Lsoftware/amazon/awssdk/services/s3/internal/crt/UploadPartCopyRequestIterable;
      28: invokestatic  #4                  // Method software/amazon/awssdk/services/s3/internal/crt/UploadPartCopyRequestIterable.access$100:(Lsoftware/amazon/awssdk/services/s3/internal/crt/UploadPartCopyRequestIterable;)J
      31: invokestatic  #10                 // Method java/lang/Math.min:(JJ)J
      34: lstore_1
      35: aload_0
      36: lload_1
      37: invokespecial #11                 // Method range:(J)Ljava/lang/String;
      40: astore_3
      41: aload_0
      42: getfield      #2                  // Field this$0:Lsoftware/amazon/awssdk/services/s3/internal/crt/UploadPartCopyRequestIterable;
      45: invokestatic  #12                 // Method software/amazon/awssdk/services/s3/internal/crt/UploadPartCopyRequestIterable.access$300:(Lsoftware/amazon/awssdk/services/s3/internal/crt/UploadPartCopyRequestIterable;)Lsoftware/amazon/awssdk/services/s3/model/CopyObjectRequest;
      48: aload_0
      49: getfield      #2                  // Field this$0:Lsoftware/amazon/awssdk/services/s3/internal/crt/UploadPartCopyRequestIterable;
      52: invokestatic  #13                 // Method software/amazon/awssdk/services/s3/internal/crt/UploadPartCopyRequestIterable.access$400:(Lsoftware/amazon/awssdk/services/s3/internal/crt/UploadPartCopyRequestIterable;)I
      55: aload_0
      56: getfield      #2                  // Field this$0:Lsoftware/amazon/awssdk/services/s3/internal/crt/UploadPartCopyRequestIterable;
      59: invokestatic  #14                 // Method software/amazon/awssdk/services/s3/internal/crt/UploadPartCopyRequestIterable.access$500:(Lsoftware/amazon/awssdk/services/s3/internal/crt/UploadPartCopyRequestIterable;)Ljava/lang/String;
      62: aload_3
      63: invokestatic  #15                 // Method software/amazon/awssdk/services/s3/internal/crt/CopyRequestConversionUtils.toUploadPartCopyRequest:(Lsoftware/amazon/awssdk/services/s3/model/CopyObjectRequest;ILjava/lang/String;Ljava/lang/String;)Lsoftware/amazon/awssdk/services/s3/model/UploadPartCopyRequest;
      66: astore        4
      68: aload_0
      69: getfield      #2                  // Field this$0:Lsoftware/amazon/awssdk/services/s3/internal/crt/UploadPartCopyRequestIterable;
      72: invokestatic  #16                 // Method software/amazon/awssdk/services/s3/internal/crt/UploadPartCopyRequestIterable.access$408:(Lsoftware/amazon/awssdk/services/s3/internal/crt/UploadPartCopyRequestIterable;)I
      75: pop
      76: aload_0
      77: getfield      #2                  // Field this$0:Lsoftware/amazon/awssdk/services/s3/internal/crt/UploadPartCopyRequestIterable;
      80: aload_0
      81: getfield      #2                  // Field this$0:Lsoftware/amazon/awssdk/services/s3/internal/crt/UploadPartCopyRequestIterable;
      84: invokestatic  #17                 // Method software/amazon/awssdk/services/s3/internal/crt/UploadPartCopyRequestIterable.access$600:(Lsoftware/amazon/awssdk/services/s3/internal/crt/UploadPartCopyRequestIterable;)J
      87: lload_1
      88: ladd
      89: invokestatic  #18                 // Method software/amazon/awssdk/services/s3/internal/crt/UploadPartCopyRequestIterable.access$602:(Lsoftware/amazon/awssdk/services/s3/internal/crt/UploadPartCopyRequestIterable;J)J
      92: pop2
      93: aload_0
      94: getfield      #2                  // Field this$0:Lsoftware/amazon/awssdk/services/s3/internal/crt/UploadPartCopyRequestIterable;
      97: aload_0
      98: getfield      #2                  // Field this$0:Lsoftware/amazon/awssdk/services/s3/internal/crt/UploadPartCopyRequestIterable;
     101: invokestatic  #4                  // Method software/amazon/awssdk/services/s3/internal/crt/UploadPartCopyRequestIterable.access$100:(Lsoftware/amazon/awssdk/services/s3/internal/crt/UploadPartCopyRequestIterable;)J
     104: lload_1
     105: lsub
     106: invokestatic  #19                 // Method software/amazon/awssdk/services/s3/internal/crt/UploadPartCopyRequestIterable.access$102:(Lsoftware/amazon/awssdk/services/s3/internal/crt/UploadPartCopyRequestIterable;J)J
     109: pop2
     110: aload         4
     112: areturn

  private java.lang.String range(long);
    Code:
       0: new           #20                 // class java/lang/StringBuilder
       3: dup
       4: invokespecial #21                 // Method java/lang/StringBuilder."<init>":()V
       7: ldc           #22                 // String bytes=
       9: invokevirtual #23                 // Method java/lang/StringBuilder.append:(Ljava/lang/String;)Ljava/lang/StringBuilder;
      12: aload_0
      13: getfield      #2                  // Field this$0:Lsoftware/amazon/awssdk/services/s3/internal/crt/UploadPartCopyRequestIterable;
      16: invokestatic  #17                 // Method software/amazon/awssdk/services/s3/internal/crt/UploadPartCopyRequestIterable.access$600:(Lsoftware/amazon/awssdk/services/s3/internal/crt/UploadPartCopyRequestIterable;)J
      19: invokevirtual #24                 // Method java/lang/StringBuilder.append:(J)Ljava/lang/StringBuilder;
      22: ldc           #25                 // String -
      24: invokevirtual #23                 // Method java/lang/StringBuilder.append:(Ljava/lang/String;)Ljava/lang/StringBuilder;
      27: aload_0
      28: getfield      #2                  // Field this$0:Lsoftware/amazon/awssdk/services/s3/internal/crt/UploadPartCopyRequestIterable;
      31: invokestatic  #17                 // Method software/amazon/awssdk/services/s3/internal/crt/UploadPartCopyRequestIterable.access$600:(Lsoftware/amazon/awssdk/services/s3/internal/crt/UploadPartCopyRequestIterable;)J
      34: lload_1
      35: ladd
      36: lconst_1
      37: lsub
      38: invokevirtual #24                 // Method java/lang/StringBuilder.append:(J)Ljava/lang/StringBuilder;
      41: invokevirtual #26                 // Method java/lang/StringBuilder.toString:()Ljava/lang/String;
      44: areturn

  public java.lang.Object next();
    Code:
       0: aload_0
       1: invokevirtual #27                 // Method next:()Lsoftware/amazon/awssdk/services/s3/model/UploadPartCopyRequest;
       4: areturn

  software.amazon.awssdk.services.s3.internal.crt.UploadPartCopyRequestIterable$UploadPartCopyRequestIterator(software.amazon.awssdk.services.s3.internal.crt.UploadPartCopyRequestIterable, software.amazon.awssdk.services.s3.internal.crt.UploadPartCopyRequestIterable$1);
    Code:
       0: aload_0
       1: aload_1
       2: invokespecial #1                  // Method "<init>":(Lsoftware/amazon/awssdk/services/s3/internal/crt/UploadPartCopyRequestIterable;)V
       5: return
}
