Compiled from "PreviewDatafeedResponse.java"
public class org.elasticsearch.client.ml.PreviewDatafeedResponse extends org.elasticsearch.action.ActionResponse implements org.elasticsearch.common.xcontent.ToXContentObject {
  private org.elasticsearch.common.bytes.BytesReference preview;

  public static org.elasticsearch.client.ml.PreviewDatafeedResponse fromXContent(org.elasticsearch.common.xcontent.XContentParser) throws java.io.IOException;
    Code:
       0: invokestatic  #1                  // Method org/elasticsearch/common/xcontent/XContentFactory.jsonBuilder:()Lorg/elasticsearch/common/xcontent/XContentBuilder;
       3: astore_1
       4: aload_0
       5: invokeinterface #2,  1            // InterfaceMethod org/elasticsearch/common/xcontent/XContentParser.nextToken:()Lorg/elasticsearch/common/xcontent/XContentParser$Token;
      10: pop
      11: aload_1
      12: aload_0
      13: invokevirtual #3                  // Method org/elasticsearch/common/xcontent/XContentBuilder.copyCurrentStructure:(Lorg/elasticsearch/common/xcontent/XContentParser;)Lorg/elasticsearch/common/xcontent/XContentBuilder;
      16: pop
      17: new           #4                  // class org/elasticsearch/client/ml/PreviewDatafeedResponse
      20: dup
      21: aload_1
      22: invokestatic  #5                  // Method org/elasticsearch/common/bytes/BytesReference.bytes:(Lorg/elasticsearch/common/xcontent/XContentBuilder;)Lorg/elasticsearch/common/bytes/BytesReference;
      25: invokespecial #6                  // Method "<init>":(Lorg/elasticsearch/common/bytes/BytesReference;)V
      28: astore_2
      29: aload_1
      30: ifnull        37
      33: aload_1
      34: invokevirtual #7                  // Method org/elasticsearch/common/xcontent/XContentBuilder.close:()V
      37: aload_2
      38: areturn
      39: astore_2
      40: aload_1
      41: ifnull        57
      44: aload_1
      45: invokevirtual #7                  // Method org/elasticsearch/common/xcontent/XContentBuilder.close:()V
      48: goto          57
      51: astore_3
      52: aload_2
      53: aload_3
      54: invokevirtual #9                  // Method java/lang/Throwable.addSuppressed:(Ljava/lang/Throwable;)V
      57: aload_2
      58: athrow
    Exception table:
       from    to  target type
           4    29    39   Class java/lang/Throwable
          44    48    51   Class java/lang/Throwable

  public org.elasticsearch.client.ml.PreviewDatafeedResponse(org.elasticsearch.common.bytes.BytesReference);
    Code:
       0: aload_0
       1: invokespecial #10                 // Method org/elasticsearch/action/ActionResponse."<init>":()V
       4: aload_0
       5: aload_1
       6: putfield      #11                 // Field preview:Lorg/elasticsearch/common/bytes/BytesReference;
       9: return

  public org.elasticsearch.common.bytes.BytesReference getPreview();
    Code:
       0: aload_0
       1: getfield      #11                 // Field preview:Lorg/elasticsearch/common/bytes/BytesReference;
       4: areturn

  public java.util.List<java.util.Map<java.lang.String, java.lang.Object>> getDataList() throws java.io.IOException;
    Code:
       0: aload_0
       1: getfield      #11                 // Field preview:Lorg/elasticsearch/common/bytes/BytesReference;
       4: invokevirtual #12                 // Method org/elasticsearch/common/bytes/BytesReference.streamInput:()Lorg/elasticsearch/common/io/stream/StreamInput;
       7: astore_1
       8: getstatic     #13                 // Field org/elasticsearch/common/xcontent/XContentType.JSON:Lorg/elasticsearch/common/xcontent/XContentType;
      11: invokevirtual #14                 // Method org/elasticsearch/common/xcontent/XContentType.xContent:()Lorg/elasticsearch/common/xcontent/XContent;
      14: getstatic     #15                 // Field org/elasticsearch/common/xcontent/NamedXContentRegistry.EMPTY:Lorg/elasticsearch/common/xcontent/NamedXContentRegistry;
      17: getstatic     #16                 // Field org/elasticsearch/common/xcontent/DeprecationHandler.THROW_UNSUPPORTED_OPERATION:Lorg/elasticsearch/common/xcontent/DeprecationHandler;
      20: aload_1
      21: invokeinterface #17,  4           // InterfaceMethod org/elasticsearch/common/xcontent/XContent.createParser:(Lorg/elasticsearch/common/xcontent/NamedXContentRegistry;Lorg/elasticsearch/common/xcontent/DeprecationHandler;Ljava/io/InputStream;)Lorg/elasticsearch/common/xcontent/XContentParser;
      26: astore_2
      27: aload_2
      28: invokeinterface #2,  1            // InterfaceMethod org/elasticsearch/common/xcontent/XContentParser.nextToken:()Lorg/elasticsearch/common/xcontent/XContentParser$Token;
      33: astore_3
      34: aload_3
      35: getstatic     #18                 // Field org/elasticsearch/common/xcontent/XContentParser$Token.START_ARRAY:Lorg/elasticsearch/common/xcontent/XContentParser$Token;
      38: if_acmpne     96
      41: aload_2
      42: invokeinterface #19,  1           // InterfaceMethod org/elasticsearch/common/xcontent/XContentParser.listOrderedMap:()Ljava/util/List;
      47: invokeinterface #20,  1           // InterfaceMethod java/util/List.stream:()Ljava/util/stream/Stream;
      52: invokedynamic #21,  0             // InvokeDynamic #0:apply:()Ljava/util/function/Function;
      57: invokeinterface #22,  2           // InterfaceMethod java/util/stream/Stream.map:(Ljava/util/function/Function;)Ljava/util/stream/Stream;
      62: invokestatic  #23                 // Method java/util/stream/Collectors.toList:()Ljava/util/stream/Collector;
      65: invokeinterface #24,  2           // InterfaceMethod java/util/stream/Stream.collect:(Ljava/util/stream/Collector;)Ljava/lang/Object;
      70: checkcast     #25                 // class java/util/List
      73: astore        4
      75: aload_2
      76: ifnull        85
      79: aload_2
      80: invokeinterface #26,  1           // InterfaceMethod org/elasticsearch/common/xcontent/XContentParser.close:()V
      85: aload_1
      86: ifnull        93
      89: aload_1
      90: invokevirtual #27                 // Method org/elasticsearch/common/io/stream/StreamInput.close:()V
      93: aload         4
      95: areturn
      96: aload_2
      97: invokeinterface #28,  1           // InterfaceMethod org/elasticsearch/common/xcontent/XContentParser.mapOrdered:()Ljava/util/Map;
     102: invokestatic  #29                 // Method java/util/Collections.singletonList:(Ljava/lang/Object;)Ljava/util/List;
     105: astore        4
     107: aload_2
     108: ifnull        117
     111: aload_2
     112: invokeinterface #26,  1           // InterfaceMethod org/elasticsearch/common/xcontent/XContentParser.close:()V
     117: aload_1
     118: ifnull        125
     121: aload_1
     122: invokevirtual #27                 // Method org/elasticsearch/common/io/stream/StreamInput.close:()V
     125: aload         4
     127: areturn
     128: astore_3
     129: aload_2
     130: ifnull        150
     133: aload_2
     134: invokeinterface #26,  1           // InterfaceMethod org/elasticsearch/common/xcontent/XContentParser.close:()V
     139: goto          150
     142: astore        4
     144: aload_3
     145: aload         4
     147: invokevirtual #9                  // Method java/lang/Throwable.addSuppressed:(Ljava/lang/Throwable;)V
     150: aload_3
     151: athrow
     152: astore_2
     153: aload_1
     154: ifnull        170
     157: aload_1
     158: invokevirtual #27                 // Method org/elasticsearch/common/io/stream/StreamInput.close:()V
     161: goto          170
     164: astore_3
     165: aload_2
     166: aload_3
     167: invokevirtual #9                  // Method java/lang/Throwable.addSuppressed:(Ljava/lang/Throwable;)V
     170: aload_2
     171: athrow
    Exception table:
       from    to  target type
          27    75   128   Class java/lang/Throwable
          96   107   128   Class java/lang/Throwable
         133   139   142   Class java/lang/Throwable
           8    85   152   Class java/lang/Throwable
          96   117   152   Class java/lang/Throwable
         128   152   152   Class java/lang/Throwable
         157   161   164   Class java/lang/Throwable

  public org.elasticsearch.common.xcontent.XContentBuilder toXContent(org.elasticsearch.common.xcontent.XContentBuilder, org.elasticsearch.common.xcontent.ToXContent$Params) throws java.io.IOException;
    Code:
       0: aload_0
       1: getfield      #11                 // Field preview:Lorg/elasticsearch/common/bytes/BytesReference;
       4: invokevirtual #12                 // Method org/elasticsearch/common/bytes/BytesReference.streamInput:()Lorg/elasticsearch/common/io/stream/StreamInput;
       7: astore_3
       8: aload_1
       9: aload_3
      10: getstatic     #13                 // Field org/elasticsearch/common/xcontent/XContentType.JSON:Lorg/elasticsearch/common/xcontent/XContentType;
      13: invokevirtual #30                 // Method org/elasticsearch/common/xcontent/XContentBuilder.rawValue:(Ljava/io/InputStream;Lorg/elasticsearch/common/xcontent/XContentType;)Lorg/elasticsearch/common/xcontent/XContentBuilder;
      16: pop
      17: aload_3
      18: ifnull        53
      21: aload_3
      22: invokevirtual #31                 // Method java/io/InputStream.close:()V
      25: goto          53
      28: astore        4
      30: aload_3
      31: ifnull        50
      34: aload_3
      35: invokevirtual #31                 // Method java/io/InputStream.close:()V
      38: goto          50
      41: astore        5
      43: aload         4
      45: aload         5
      47: invokevirtual #9                  // Method java/lang/Throwable.addSuppressed:(Ljava/lang/Throwable;)V
      50: aload         4
      52: athrow
      53: aload_1
      54: areturn
    Exception table:
       from    to  target type
           8    17    28   Class java/lang/Throwable
          34    38    41   Class java/lang/Throwable

  public int hashCode();
    Code:
       0: iconst_1
       1: anewarray     #32                 // class java/lang/Object
       4: dup
       5: iconst_0
       6: aload_0
       7: getfield      #11                 // Field preview:Lorg/elasticsearch/common/bytes/BytesReference;
      10: aastore
      11: invokestatic  #33                 // Method java/util/Objects.hash:([Ljava/lang/Object;)I
      14: ireturn

  public boolean equals(java.lang.Object);
    Code:
       0: aload_1
       1: ifnonnull     6
       4: iconst_0
       5: ireturn
       6: aload_0
       7: invokevirtual #34                 // Method java/lang/Object.getClass:()Ljava/lang/Class;
      10: aload_1
      11: invokevirtual #34                 // Method java/lang/Object.getClass:()Ljava/lang/Class;
      14: if_acmpeq     19
      17: iconst_0
      18: ireturn
      19: aload_1
      20: checkcast     #4                  // class org/elasticsearch/client/ml/PreviewDatafeedResponse
      23: astore_2
      24: aload_0
      25: getfield      #11                 // Field preview:Lorg/elasticsearch/common/bytes/BytesReference;
      28: aload_2
      29: getfield      #11                 // Field preview:Lorg/elasticsearch/common/bytes/BytesReference;
      32: invokestatic  #35                 // Method java/util/Objects.equals:(Ljava/lang/Object;Ljava/lang/Object;)Z
      35: ireturn

  public final java.lang.String toString();
    Code:
       0: aload_0
       1: invokestatic  #36                 // Method org/elasticsearch/common/Strings.toString:(Lorg/elasticsearch/common/xcontent/ToXContent;)Ljava/lang/String;
       4: areturn

  private static java.util.Map lambda$getDataList$0(java.lang.Object);
    Code:
       0: aload_0
       1: checkcast     #37                 // class java/util/Map
       4: areturn
}
