Compiled from "AbstractStoreTests.java"
public abstract class org.pac4j.core.store.AbstractStoreTests<S extends org.pac4j.core.store.Store> implements org.pac4j.core.util.TestsConstants {
  public org.pac4j.core.store.AbstractStoreTests();
    Code:
       0: aload_0
       1: invokespecial #1                  // Method java/lang/Object."<init>":()V
       4: return

  protected abstract S buildStore();

  public void testSetRemoveGet();
    Code:
       0: aload_0
       1: invokevirtual #2                  // Method buildStore:()Lorg/pac4j/core/store/Store;
       4: astore_1
       5: aload_1
       6: ldc           #4                  // String key
       8: ldc           #5                  // String value
      10: invokeinterface #6,  3            // InterfaceMethod org/pac4j/core/store/Store.set:(Ljava/lang/Object;Ljava/lang/Object;)V
      15: ldc           #5                  // String value
      17: aload_1
      18: ldc           #4                  // String key
      20: invokeinterface #7,  2            // InterfaceMethod org/pac4j/core/store/Store.get:(Ljava/lang/Object;)Ljava/util/Optional;
      25: invokevirtual #8                  // Method java/util/Optional.get:()Ljava/lang/Object;
      28: invokestatic  #9                  // Method org/junit/Assert.assertEquals:(Ljava/lang/Object;Ljava/lang/Object;)V
      31: aload_1
      32: ldc           #4                  // String key
      34: invokeinterface #10,  2           // InterfaceMethod org/pac4j/core/store/Store.remove:(Ljava/lang/Object;)V
      39: aload_1
      40: ldc           #4                  // String key
      42: invokeinterface #7,  2            // InterfaceMethod org/pac4j/core/store/Store.get:(Ljava/lang/Object;)Ljava/util/Optional;
      47: invokevirtual #11                 // Method java/util/Optional.isPresent:()Z
      50: invokestatic  #12                 // Method org/junit/Assert.assertFalse:(Z)V
      53: return

  public void testSetExpiredGet();
    Code:
       0: aload_0
       1: invokevirtual #2                  // Method buildStore:()Lorg/pac4j/core/store/Store;
       4: astore_1
       5: aload_1
       6: ldc           #4                  // String key
       8: ldc           #5                  // String value
      10: invokeinterface #6,  3            // InterfaceMethod org/pac4j/core/store/Store.set:(Ljava/lang/Object;Ljava/lang/Object;)V
      15: ldc           #5                  // String value
      17: aload_1
      18: ldc           #4                  // String key
      20: invokeinterface #7,  2            // InterfaceMethod org/pac4j/core/store/Store.get:(Ljava/lang/Object;)Ljava/util/Optional;
      25: invokevirtual #8                  // Method java/util/Optional.get:()Ljava/lang/Object;
      28: invokestatic  #9                  // Method org/junit/Assert.assertEquals:(Ljava/lang/Object;Ljava/lang/Object;)V
      31: ldc2_w        #13                 // long 2000l
      34: invokestatic  #15                 // Method java/lang/Thread.sleep:(J)V
      37: goto          50
      40: astore_2
      41: new           #17                 // class java/lang/RuntimeException
      44: dup
      45: aload_2
      46: invokespecial #18                 // Method java/lang/RuntimeException."<init>":(Ljava/lang/Throwable;)V
      49: athrow
      50: aload_1
      51: ldc           #4                  // String key
      53: invokeinterface #7,  2            // InterfaceMethod org/pac4j/core/store/Store.get:(Ljava/lang/Object;)Ljava/util/Optional;
      58: invokevirtual #11                 // Method java/util/Optional.isPresent:()Z
      61: invokestatic  #12                 // Method org/junit/Assert.assertFalse:(Z)V
      64: return
    Exception table:
       from    to  target type
          31    37    40   Class java/lang/InterruptedException

  public void testSetNullValue();
    Code:
       0: aload_0
       1: invokevirtual #2                  // Method buildStore:()Lorg/pac4j/core/store/Store;
       4: astore_1
       5: aload_1
       6: ldc           #4                  // String key
       8: ldc           #5                  // String value
      10: invokeinterface #6,  3            // InterfaceMethod org/pac4j/core/store/Store.set:(Ljava/lang/Object;Ljava/lang/Object;)V
      15: ldc           #5                  // String value
      17: aload_1
      18: ldc           #4                  // String key
      20: invokeinterface #7,  2            // InterfaceMethod org/pac4j/core/store/Store.get:(Ljava/lang/Object;)Ljava/util/Optional;
      25: invokevirtual #8                  // Method java/util/Optional.get:()Ljava/lang/Object;
      28: invokestatic  #9                  // Method org/junit/Assert.assertEquals:(Ljava/lang/Object;Ljava/lang/Object;)V
      31: aload_1
      32: ldc           #4                  // String key
      34: aconst_null
      35: invokeinterface #6,  3            // InterfaceMethod org/pac4j/core/store/Store.set:(Ljava/lang/Object;Ljava/lang/Object;)V
      40: aload_1
      41: ldc           #4                  // String key
      43: invokeinterface #7,  2            // InterfaceMethod org/pac4j/core/store/Store.get:(Ljava/lang/Object;)Ljava/util/Optional;
      48: invokevirtual #11                 // Method java/util/Optional.isPresent:()Z
      51: invokestatic  #12                 // Method org/junit/Assert.assertFalse:(Z)V
      54: return

  public void testMissingObject();
    Code:
       0: aload_0
       1: invokevirtual #2                  // Method buildStore:()Lorg/pac4j/core/store/Store;
       4: astore_1
       5: aload_1
       6: ldc           #4                  // String key
       8: invokeinterface #7,  2            // InterfaceMethod org/pac4j/core/store/Store.get:(Ljava/lang/Object;)Ljava/util/Optional;
      13: invokevirtual #11                 // Method java/util/Optional.isPresent:()Z
      16: invokestatic  #12                 // Method org/junit/Assert.assertFalse:(Z)V
      19: return

  public void testNullKeyGet();
    Code:
       0: aload_0
       1: invokevirtual #2                  // Method buildStore:()Lorg/pac4j/core/store/Store;
       4: astore_1
       5: aload_1
       6: invokedynamic #19,  0             // InvokeDynamic #0:execute:(Lorg/pac4j/core/store/Store;)Lorg/pac4j/core/util/Executable;
      11: ldc           #20                 // class org/pac4j/core/exception/TechnicalException
      13: ldc           #21                 // String key cannot be null
      15: invokestatic  #22                 // Method org/pac4j/core/util/TestsHelper.expectException:(Lorg/pac4j/core/util/Executable;Ljava/lang/Class;Ljava/lang/String;)V
      18: return

  public void testNullKeySet();
    Code:
       0: aload_0
       1: invokevirtual #2                  // Method buildStore:()Lorg/pac4j/core/store/Store;
       4: astore_1
       5: aload_1
       6: invokedynamic #23,  0             // InvokeDynamic #1:execute:(Lorg/pac4j/core/store/Store;)Lorg/pac4j/core/util/Executable;
      11: ldc           #20                 // class org/pac4j/core/exception/TechnicalException
      13: ldc           #21                 // String key cannot be null
      15: invokestatic  #22                 // Method org/pac4j/core/util/TestsHelper.expectException:(Lorg/pac4j/core/util/Executable;Ljava/lang/Class;Ljava/lang/String;)V
      18: return

  public void testNullKeyRemove();
    Code:
       0: aload_0
       1: invokevirtual #2                  // Method buildStore:()Lorg/pac4j/core/store/Store;
       4: astore_1
       5: aload_1
       6: invokedynamic #24,  0             // InvokeDynamic #2:execute:(Lorg/pac4j/core/store/Store;)Lorg/pac4j/core/util/Executable;
      11: ldc           #20                 // class org/pac4j/core/exception/TechnicalException
      13: ldc           #21                 // String key cannot be null
      15: invokestatic  #22                 // Method org/pac4j/core/util/TestsHelper.expectException:(Lorg/pac4j/core/util/Executable;Ljava/lang/Class;Ljava/lang/String;)V
      18: return

  private static void lambda$testNullKeyRemove$2(org.pac4j.core.store.Store) throws java.lang.Exception;
    Code:
       0: aload_0
       1: aconst_null
       2: invokeinterface #10,  2           // InterfaceMethod org/pac4j/core/store/Store.remove:(Ljava/lang/Object;)V
       7: return

  private static void lambda$testNullKeySet$1(org.pac4j.core.store.Store) throws java.lang.Exception;
    Code:
       0: aload_0
       1: aconst_null
       2: ldc           #5                  // String value
       4: invokeinterface #6,  3            // InterfaceMethod org/pac4j/core/store/Store.set:(Ljava/lang/Object;Ljava/lang/Object;)V
       9: return

  private static void lambda$testNullKeyGet$0(org.pac4j.core.store.Store) throws java.lang.Exception;
    Code:
       0: aload_0
       1: aconst_null
       2: invokeinterface #7,  2            // InterfaceMethod org/pac4j/core/store/Store.get:(Ljava/lang/Object;)Ljava/util/Optional;
       7: pop
       8: return
}
