Compiled from "GuavaStoreTests.java"
public final class org.pac4j.core.store.GuavaStoreTests extends org.pac4j.core.store.AbstractStoreTests<org.pac4j.core.store.GuavaStore> {
  public org.pac4j.core.store.GuavaStoreTests();
    Code:
       0: aload_0
       1: invokespecial #1                  // Method org/pac4j/core/store/AbstractStoreTests."<init>":()V
       4: return

  protected org.pac4j.core.store.GuavaStore buildStore();
    Code:
       0: new           #2                  // class org/pac4j/core/store/GuavaStore
       3: dup
       4: bipush        10
       6: sipush        1000
       9: getstatic     #3                  // Field java/util/concurrent/TimeUnit.MILLISECONDS:Ljava/util/concurrent/TimeUnit;
      12: invokespecial #4                  // Method org/pac4j/core/store/GuavaStore."<init>":(IILjava/util/concurrent/TimeUnit;)V
      15: areturn

  public void testBadSize();
    Code:
       0: new           #2                  // class org/pac4j/core/store/GuavaStore
       3: dup
       4: invokespecial #5                  // Method org/pac4j/core/store/GuavaStore."<init>":()V
       7: astore_1
       8: aload_1
       9: bipush        15
      11: invokevirtual #6                  // Method org/pac4j/core/store/GuavaStore.setTimeout:(I)V
      14: aload_1
      15: getstatic     #7                  // Field java/util/concurrent/TimeUnit.SECONDS:Ljava/util/concurrent/TimeUnit;
      18: invokevirtual #8                  // Method org/pac4j/core/store/GuavaStore.setTimeUnit:(Ljava/util/concurrent/TimeUnit;)V
      21: aload_1
      22: dup
      23: invokestatic  #9                  // Method java/util/Objects.requireNonNull:(Ljava/lang/Object;)Ljava/lang/Object;
      26: pop
      27: invokedynamic #10,  0             // InvokeDynamic #0:execute:(Lorg/pac4j/core/store/GuavaStore;)Lorg/pac4j/core/util/Executable;
      32: ldc           #11                 // class org/pac4j/core/exception/TechnicalException
      34: ldc           #12                 // String size mut be greater than zero
      36: invokestatic  #13                 // Method org/pac4j/core/util/TestsHelper.expectException:(Lorg/pac4j/core/util/Executable;Ljava/lang/Class;Ljava/lang/String;)V
      39: return

  public void testBadTimeout();
    Code:
       0: new           #2                  // class org/pac4j/core/store/GuavaStore
       3: dup
       4: invokespecial #5                  // Method org/pac4j/core/store/GuavaStore."<init>":()V
       7: astore_1
       8: aload_1
       9: bipush        15
      11: invokevirtual #14                 // Method org/pac4j/core/store/GuavaStore.setSize:(I)V
      14: aload_1
      15: getstatic     #7                  // Field java/util/concurrent/TimeUnit.SECONDS:Ljava/util/concurrent/TimeUnit;
      18: invokevirtual #8                  // Method org/pac4j/core/store/GuavaStore.setTimeUnit:(Ljava/util/concurrent/TimeUnit;)V
      21: aload_1
      22: dup
      23: invokestatic  #9                  // Method java/util/Objects.requireNonNull:(Ljava/lang/Object;)Ljava/lang/Object;
      26: pop
      27: invokedynamic #10,  0             // InvokeDynamic #0:execute:(Lorg/pac4j/core/store/GuavaStore;)Lorg/pac4j/core/util/Executable;
      32: ldc           #11                 // class org/pac4j/core/exception/TechnicalException
      34: ldc           #15                 // String timeout must be greater than zero
      36: invokestatic  #13                 // Method org/pac4j/core/util/TestsHelper.expectException:(Lorg/pac4j/core/util/Executable;Ljava/lang/Class;Ljava/lang/String;)V
      39: return

  public void testBadTimeUnit();
    Code:
       0: new           #2                  // class org/pac4j/core/store/GuavaStore
       3: dup
       4: invokespecial #5                  // Method org/pac4j/core/store/GuavaStore."<init>":()V
       7: astore_1
       8: aload_1
       9: bipush        15
      11: invokevirtual #14                 // Method org/pac4j/core/store/GuavaStore.setSize:(I)V
      14: aload_1
      15: bipush        20
      17: invokevirtual #6                  // Method org/pac4j/core/store/GuavaStore.setTimeout:(I)V
      20: aload_1
      21: dup
      22: invokestatic  #9                  // Method java/util/Objects.requireNonNull:(Ljava/lang/Object;)Ljava/lang/Object;
      25: pop
      26: invokedynamic #10,  0             // InvokeDynamic #0:execute:(Lorg/pac4j/core/store/GuavaStore;)Lorg/pac4j/core/util/Executable;
      31: ldc           #11                 // class org/pac4j/core/exception/TechnicalException
      33: ldc           #16                 // String timeUnit cannot be null
      35: invokestatic  #13                 // Method org/pac4j/core/util/TestsHelper.expectException:(Lorg/pac4j/core/util/Executable;Ljava/lang/Class;Ljava/lang/String;)V
      38: return

  protected org.pac4j.core.store.Store buildStore();
    Code:
       0: aload_0
       1: invokevirtual #17                 // Method buildStore:()Lorg/pac4j/core/store/GuavaStore;
       4: areturn
}
