Compiled from "XppDom.java"
public class com.thoughtworks.xstream.io.xml.xppdom.XppDom implements java.io.Serializable {
  private static final long serialVersionUID;

  private java.lang.String name;

  private java.lang.String value;

  private java.util.Map attributes;

  private java.util.List childList;

  private transient java.util.Map childMap;

  private com.thoughtworks.xstream.io.xml.xppdom.XppDom parent;

  public com.thoughtworks.xstream.io.xml.xppdom.XppDom(java.lang.String);
    Code:
       0: aload_0
       1: invokespecial #1                  // Method java/lang/Object."<init>":()V
       4: aload_0
       5: aload_1
       6: putfield      #2                  // Field name:Ljava/lang/String;
       9: aload_0
      10: new           #3                  // class java/util/ArrayList
      13: dup
      14: invokespecial #4                  // Method java/util/ArrayList."<init>":()V
      17: putfield      #5                  // Field childList:Ljava/util/List;
      20: aload_0
      21: new           #6                  // class java/util/HashMap
      24: dup
      25: invokespecial #7                  // Method java/util/HashMap."<init>":()V
      28: putfield      #8                  // Field childMap:Ljava/util/Map;
      31: return

  public java.lang.String getName();
    Code:
       0: aload_0
       1: getfield      #2                  // Field name:Ljava/lang/String;
       4: areturn

  public java.lang.String getValue();
    Code:
       0: aload_0
       1: getfield      #9                  // Field value:Ljava/lang/String;
       4: areturn

  public void setValue(java.lang.String);
    Code:
       0: aload_0
       1: aload_1
       2: putfield      #9                  // Field value:Ljava/lang/String;
       5: return

  public java.lang.String[] getAttributeNames();
    Code:
       0: aconst_null
       1: aload_0
       2: getfield      #10                 // Field attributes:Ljava/util/Map;
       5: if_acmpne     13
       8: iconst_0
       9: anewarray     #11                 // class java/lang/String
      12: areturn
      13: aload_0
      14: getfield      #10                 // Field attributes:Ljava/util/Map;
      17: invokeinterface #12,  1           // InterfaceMethod java/util/Map.keySet:()Ljava/util/Set;
      22: iconst_0
      23: anewarray     #11                 // class java/lang/String
      26: invokeinterface #13,  2           // InterfaceMethod java/util/Set.toArray:([Ljava/lang/Object;)[Ljava/lang/Object;
      31: checkcast     #14                 // class "[Ljava/lang/String;"
      34: checkcast     #14                 // class "[Ljava/lang/String;"
      37: areturn

  public java.lang.String getAttribute(java.lang.String);
    Code:
       0: aconst_null
       1: aload_0
       2: getfield      #10                 // Field attributes:Ljava/util/Map;
       5: if_acmpeq     24
       8: aload_0
       9: getfield      #10                 // Field attributes:Ljava/util/Map;
      12: aload_1
      13: invokeinterface #15,  2           // InterfaceMethod java/util/Map.get:(Ljava/lang/Object;)Ljava/lang/Object;
      18: checkcast     #11                 // class java/lang/String
      21: goto          25
      24: aconst_null
      25: areturn

  public void setAttribute(java.lang.String, java.lang.String);
    Code:
       0: aconst_null
       1: aload_0
       2: getfield      #10                 // Field attributes:Ljava/util/Map;
       5: if_acmpne     19
       8: aload_0
       9: new           #6                  // class java/util/HashMap
      12: dup
      13: invokespecial #7                  // Method java/util/HashMap."<init>":()V
      16: putfield      #10                 // Field attributes:Ljava/util/Map;
      19: aload_0
      20: getfield      #10                 // Field attributes:Ljava/util/Map;
      23: aload_1
      24: aload_2
      25: invokeinterface #16,  3           // InterfaceMethod java/util/Map.put:(Ljava/lang/Object;Ljava/lang/Object;)Ljava/lang/Object;
      30: pop
      31: return

  public com.thoughtworks.xstream.io.xml.xppdom.XppDom getChild(int);
    Code:
       0: aload_0
       1: getfield      #5                  // Field childList:Ljava/util/List;
       4: iload_1
       5: invokeinterface #17,  2           // InterfaceMethod java/util/List.get:(I)Ljava/lang/Object;
      10: checkcast     #18                 // class com/thoughtworks/xstream/io/xml/xppdom/XppDom
      13: areturn

  public com.thoughtworks.xstream.io.xml.xppdom.XppDom getChild(java.lang.String);
    Code:
       0: aload_0
       1: getfield      #8                  // Field childMap:Ljava/util/Map;
       4: aload_1
       5: invokeinterface #15,  2           // InterfaceMethod java/util/Map.get:(Ljava/lang/Object;)Ljava/lang/Object;
      10: checkcast     #18                 // class com/thoughtworks/xstream/io/xml/xppdom/XppDom
      13: areturn

  public void addChild(com.thoughtworks.xstream.io.xml.xppdom.XppDom);
    Code:
       0: aload_1
       1: aload_0
       2: invokevirtual #19                 // Method setParent:(Lcom/thoughtworks/xstream/io/xml/xppdom/XppDom;)V
       5: aload_0
       6: getfield      #5                  // Field childList:Ljava/util/List;
       9: aload_1
      10: invokeinterface #20,  2           // InterfaceMethod java/util/List.add:(Ljava/lang/Object;)Z
      15: pop
      16: aload_0
      17: getfield      #8                  // Field childMap:Ljava/util/Map;
      20: aload_1
      21: invokevirtual #21                 // Method getName:()Ljava/lang/String;
      24: aload_1
      25: invokeinterface #16,  3           // InterfaceMethod java/util/Map.put:(Ljava/lang/Object;Ljava/lang/Object;)Ljava/lang/Object;
      30: pop
      31: return

  public com.thoughtworks.xstream.io.xml.xppdom.XppDom[] getChildren();
    Code:
       0: aconst_null
       1: aload_0
       2: getfield      #5                  // Field childList:Ljava/util/List;
       5: if_acmpne     13
       8: iconst_0
       9: anewarray     #18                 // class com/thoughtworks/xstream/io/xml/xppdom/XppDom
      12: areturn
      13: aload_0
      14: getfield      #5                  // Field childList:Ljava/util/List;
      17: iconst_0
      18: anewarray     #18                 // class com/thoughtworks/xstream/io/xml/xppdom/XppDom
      21: invokeinterface #22,  2           // InterfaceMethod java/util/List.toArray:([Ljava/lang/Object;)[Ljava/lang/Object;
      26: checkcast     #23                 // class "[Lcom/thoughtworks/xstream/io/xml/xppdom/XppDom;"
      29: checkcast     #23                 // class "[Lcom/thoughtworks/xstream/io/xml/xppdom/XppDom;"
      32: areturn

  public com.thoughtworks.xstream.io.xml.xppdom.XppDom[] getChildren(java.lang.String);
    Code:
       0: aconst_null
       1: aload_0
       2: getfield      #5                  // Field childList:Ljava/util/List;
       5: if_acmpne     13
       8: iconst_0
       9: anewarray     #18                 // class com/thoughtworks/xstream/io/xml/xppdom/XppDom
      12: areturn
      13: new           #3                  // class java/util/ArrayList
      16: dup
      17: invokespecial #4                  // Method java/util/ArrayList."<init>":()V
      20: astore_2
      21: aload_0
      22: getfield      #5                  // Field childList:Ljava/util/List;
      25: invokeinterface #24,  1           // InterfaceMethod java/util/List.size:()I
      30: istore_3
      31: iconst_0
      32: istore        4
      34: iload         4
      36: iload_3
      37: if_icmpge     81
      40: aload_0
      41: getfield      #5                  // Field childList:Ljava/util/List;
      44: iload         4
      46: invokeinterface #17,  2           // InterfaceMethod java/util/List.get:(I)Ljava/lang/Object;
      51: checkcast     #18                 // class com/thoughtworks/xstream/io/xml/xppdom/XppDom
      54: astore        5
      56: aload_1
      57: aload         5
      59: invokevirtual #21                 // Method getName:()Ljava/lang/String;
      62: invokevirtual #25                 // Method java/lang/String.equals:(Ljava/lang/Object;)Z
      65: ifeq          75
      68: aload_2
      69: aload         5
      71: invokevirtual #26                 // Method java/util/ArrayList.add:(Ljava/lang/Object;)Z
      74: pop
      75: iinc          4, 1
      78: goto          34
      81: aload_2
      82: iconst_0
      83: anewarray     #18                 // class com/thoughtworks/xstream/io/xml/xppdom/XppDom
      86: invokevirtual #27                 // Method java/util/ArrayList.toArray:([Ljava/lang/Object;)[Ljava/lang/Object;
      89: checkcast     #23                 // class "[Lcom/thoughtworks/xstream/io/xml/xppdom/XppDom;"
      92: checkcast     #23                 // class "[Lcom/thoughtworks/xstream/io/xml/xppdom/XppDom;"
      95: areturn

  public int getChildCount();
    Code:
       0: aconst_null
       1: aload_0
       2: getfield      #5                  // Field childList:Ljava/util/List;
       5: if_acmpne     10
       8: iconst_0
       9: ireturn
      10: aload_0
      11: getfield      #5                  // Field childList:Ljava/util/List;
      14: invokeinterface #24,  1           // InterfaceMethod java/util/List.size:()I
      19: ireturn

  public com.thoughtworks.xstream.io.xml.xppdom.XppDom getParent();
    Code:
       0: aload_0
       1: getfield      #28                 // Field parent:Lcom/thoughtworks/xstream/io/xml/xppdom/XppDom;
       4: areturn

  public void setParent(com.thoughtworks.xstream.io.xml.xppdom.XppDom);
    Code:
       0: aload_0
       1: aload_1
       2: putfield      #28                 // Field parent:Lcom/thoughtworks/xstream/io/xml/xppdom/XppDom;
       5: return

  java.lang.Object readResolve();
    Code:
       0: aload_0
       1: new           #6                  // class java/util/HashMap
       4: dup
       5: invokespecial #7                  // Method java/util/HashMap."<init>":()V
       8: putfield      #8                  // Field childMap:Ljava/util/Map;
      11: aload_0
      12: getfield      #5                  // Field childList:Ljava/util/List;
      15: invokeinterface #29,  1           // InterfaceMethod java/util/List.iterator:()Ljava/util/Iterator;
      20: astore_1
      21: aload_1
      22: invokeinterface #30,  1           // InterfaceMethod java/util/Iterator.hasNext:()Z
      27: ifeq          58
      30: aload_1
      31: invokeinterface #31,  1           // InterfaceMethod java/util/Iterator.next:()Ljava/lang/Object;
      36: checkcast     #18                 // class com/thoughtworks/xstream/io/xml/xppdom/XppDom
      39: astore_2
      40: aload_0
      41: getfield      #8                  // Field childMap:Ljava/util/Map;
      44: aload_2
      45: invokevirtual #21                 // Method getName:()Ljava/lang/String;
      48: aload_2
      49: invokeinterface #16,  3           // InterfaceMethod java/util/Map.put:(Ljava/lang/Object;Ljava/lang/Object;)Ljava/lang/Object;
      54: pop
      55: goto          21
      58: aload_0
      59: areturn

  public static com.thoughtworks.xstream.io.xml.xppdom.XppDom build(org.xmlpull.v1.XmlPullParser) throws org.xmlpull.v1.XmlPullParserException, java.io.IOException;
    Code:
       0: new           #3                  // class java/util/ArrayList
       3: dup
       4: invokespecial #4                  // Method java/util/ArrayList."<init>":()V
       7: astore_1
       8: new           #3                  // class java/util/ArrayList
      11: dup
      12: invokespecial #4                  // Method java/util/ArrayList."<init>":()V
      15: astore_2
      16: aconst_null
      17: astore_3
      18: aload_0
      19: invokeinterface #32,  1           // InterfaceMethod org/xmlpull/v1/XmlPullParser.getEventType:()I
      24: istore        4
      26: iload         4
      28: iconst_1
      29: if_icmpeq     303
      32: iload         4
      34: iconst_2
      35: if_icmpne     171
      38: aload_0
      39: invokeinterface #33,  1           // InterfaceMethod org/xmlpull/v1/XmlPullParser.getName:()Ljava/lang/String;
      44: astore        5
      46: new           #34                 // class com/thoughtworks/xstream/io/xml/xppdom/Xpp3Dom
      49: dup
      50: aload         5
      52: invokespecial #35                 // Method com/thoughtworks/xstream/io/xml/xppdom/Xpp3Dom."<init>":(Ljava/lang/String;)V
      55: astore        6
      57: aload_1
      58: invokeinterface #24,  1           // InterfaceMethod java/util/List.size:()I
      63: istore        7
      65: iload         7
      67: ifle          92
      70: aload_1
      71: iload         7
      73: iconst_1
      74: isub
      75: invokeinterface #17,  2           // InterfaceMethod java/util/List.get:(I)Ljava/lang/Object;
      80: checkcast     #18                 // class com/thoughtworks/xstream/io/xml/xppdom/XppDom
      83: astore        8
      85: aload         8
      87: aload         6
      89: invokevirtual #36                 // Method addChild:(Lcom/thoughtworks/xstream/io/xml/xppdom/XppDom;)V
      92: aload_1
      93: aload         6
      95: invokeinterface #20,  2           // InterfaceMethod java/util/List.add:(Ljava/lang/Object;)Z
     100: pop
     101: aload_2
     102: new           #37                 // class java/lang/StringBuffer
     105: dup
     106: invokespecial #38                 // Method java/lang/StringBuffer."<init>":()V
     109: invokeinterface #20,  2           // InterfaceMethod java/util/List.add:(Ljava/lang/Object;)Z
     114: pop
     115: aload_0
     116: invokeinterface #39,  1           // InterfaceMethod org/xmlpull/v1/XmlPullParser.getAttributeCount:()I
     121: istore        8
     123: iconst_0
     124: istore        9
     126: iload         9
     128: iload         8
     130: if_icmpge     168
     133: aload_0
     134: iload         9
     136: invokeinterface #40,  2           // InterfaceMethod org/xmlpull/v1/XmlPullParser.getAttributeName:(I)Ljava/lang/String;
     141: astore        10
     143: aload_0
     144: iload         9
     146: invokeinterface #41,  2           // InterfaceMethod org/xmlpull/v1/XmlPullParser.getAttributeValue:(I)Ljava/lang/String;
     151: astore        11
     153: aload         6
     155: aload         10
     157: aload         11
     159: invokevirtual #42                 // Method setAttribute:(Ljava/lang/String;Ljava/lang/String;)V
     162: iinc          9, 1
     165: goto          126
     168: goto          292
     171: iload         4
     173: iconst_4
     174: if_icmpne     215
     177: aload_2
     178: invokeinterface #24,  1           // InterfaceMethod java/util/List.size:()I
     183: iconst_1
     184: isub
     185: istore        5
     187: aload_2
     188: iload         5
     190: invokeinterface #17,  2           // InterfaceMethod java/util/List.get:(I)Ljava/lang/Object;
     195: checkcast     #37                 // class java/lang/StringBuffer
     198: astore        6
     200: aload         6
     202: aload_0
     203: invokeinterface #43,  1           // InterfaceMethod org/xmlpull/v1/XmlPullParser.getText:()Ljava/lang/String;
     208: invokevirtual #44                 // Method java/lang/StringBuffer.append:(Ljava/lang/String;)Ljava/lang/StringBuffer;
     211: pop
     212: goto          292
     215: iload         4
     217: iconst_3
     218: if_icmpne     292
     221: aload_1
     222: invokeinterface #24,  1           // InterfaceMethod java/util/List.size:()I
     227: iconst_1
     228: isub
     229: istore        5
     231: aload_1
     232: iload         5
     234: invokeinterface #45,  2           // InterfaceMethod java/util/List.remove:(I)Ljava/lang/Object;
     239: checkcast     #18                 // class com/thoughtworks/xstream/io/xml/xppdom/XppDom
     242: astore        6
     244: aload_2
     245: iload         5
     247: invokeinterface #45,  2           // InterfaceMethod java/util/List.remove:(I)Ljava/lang/Object;
     252: invokevirtual #46                 // Method java/lang/Object.toString:()Ljava/lang/String;
     255: astore        7
     257: iconst_0
     258: aload         7
     260: invokevirtual #47                 // Method java/lang/String.length:()I
     263: if_icmpne     272
     266: aconst_null
     267: astore        8
     269: goto          276
     272: aload         7
     274: astore        8
     276: aload         6
     278: aload         8
     280: invokevirtual #48                 // Method setValue:(Ljava/lang/String;)V
     283: iconst_0
     284: iload         5
     286: if_icmpne     292
     289: aload         6
     291: astore_3
     292: aload_0
     293: invokeinterface #49,  1           // InterfaceMethod org/xmlpull/v1/XmlPullParser.next:()I
     298: istore        4
     300: goto          26
     303: aload_3
     304: areturn
}
