Compiled from "DataColumn.kt"
public final class org.jetbrains.kotlinx.dataframe.DataColumnKt {
  public static final java.lang.String getName(org.jetbrains.kotlinx.dataframe.DataColumn<?>);
    Code:
       0: aload_0
       1: ldc           #10                 // String <this>
       3: invokestatic  #16                 // Method kotlin/jvm/internal/Intrinsics.checkNotNullParameter:(Ljava/lang/Object;Ljava/lang/String;)V
       6: aload_0
       7: invokeinterface #22,  1           // InterfaceMethod org/jetbrains/kotlinx/dataframe/DataColumn.name:()Ljava/lang/String;
      12: areturn

  public static final org.jetbrains.kotlinx.dataframe.columns.ColumnPath getPath(org.jetbrains.kotlinx.dataframe.DataColumn<?>);
    Code:
       0: aload_0
       1: ldc           #10                 // String <this>
       3: invokestatic  #16                 // Method kotlin/jvm/internal/Intrinsics.checkNotNullParameter:(Ljava/lang/Object;Ljava/lang/String;)V
       6: aload_0
       7: invokeinterface #31,  1           // InterfaceMethod org/jetbrains/kotlinx/dataframe/DataColumn.path:()Lorg/jetbrains/kotlinx/dataframe/columns/ColumnPath;
      12: areturn

  public static final <T> java.lang.Iterable<T> getValues(org.jetbrains.kotlinx.dataframe.DataColumn<? extends T>);
    Code:
       0: aload_0
       1: ldc           #10                 // String <this>
       3: invokestatic  #16                 // Method kotlin/jvm/internal/Intrinsics.checkNotNullParameter:(Ljava/lang/Object;Ljava/lang/String;)V
       6: aload_0
       7: invokeinterface #39,  1           // InterfaceMethod org/jetbrains/kotlinx/dataframe/DataColumn.values:()Ljava/lang/Iterable;
      12: areturn

  public static final boolean getHasNulls(org.jetbrains.kotlinx.dataframe.DataColumn<?>);
    Code:
       0: aload_0
       1: ldc           #10                 // String <this>
       3: invokestatic  #16                 // Method kotlin/jvm/internal/Intrinsics.checkNotNullParameter:(Ljava/lang/Object;Ljava/lang/String;)V
       6: aload_0
       7: invokeinterface #47,  1           // InterfaceMethod org/jetbrains/kotlinx/dataframe/DataColumn.hasNulls:()Z
      12: ireturn

  public static final int getSize(org.jetbrains.kotlinx.dataframe.DataColumn<?>);
    Code:
       0: aload_0
       1: ldc           #10                 // String <this>
       3: invokestatic  #16                 // Method kotlin/jvm/internal/Intrinsics.checkNotNullParameter:(Ljava/lang/Object;Ljava/lang/String;)V
       6: aload_0
       7: invokeinterface #55,  1           // InterfaceMethod org/jetbrains/kotlinx/dataframe/DataColumn.size:()I
      12: ireturn

  public static final kotlin.ranges.IntRange getIndices(org.jetbrains.kotlinx.dataframe.DataColumn<?>);
    Code:
       0: aload_0
       1: ldc           #10                 // String <this>
       3: invokestatic  #16                 // Method kotlin/jvm/internal/Intrinsics.checkNotNullParameter:(Ljava/lang/Object;Ljava/lang/String;)V
       6: aload_0
       7: invokestatic  #62                 // Method indices:(Lorg/jetbrains/kotlinx/dataframe/DataColumn;)Lkotlin/ranges/IntRange;
      10: areturn

  public static final kotlin.reflect.KType getType(org.jetbrains.kotlinx.dataframe.DataColumn<?>);
    Code:
       0: aload_0
       1: ldc           #10                 // String <this>
       3: invokestatic  #16                 // Method kotlin/jvm/internal/Intrinsics.checkNotNullParameter:(Ljava/lang/Object;Ljava/lang/String;)V
       6: aload_0
       7: invokeinterface #70,  1           // InterfaceMethod org/jetbrains/kotlinx/dataframe/DataColumn.type:()Lkotlin/reflect/KType;
      12: areturn

  public static final org.jetbrains.kotlinx.dataframe.columns.ColumnKind getKind(org.jetbrains.kotlinx.dataframe.DataColumn<?>);
    Code:
       0: aload_0
       1: ldc           #10                 // String <this>
       3: invokestatic  #16                 // Method kotlin/jvm/internal/Intrinsics.checkNotNullParameter:(Ljava/lang/Object;Ljava/lang/String;)V
       6: aload_0
       7: invokeinterface #78,  1           // InterfaceMethod org/jetbrains/kotlinx/dataframe/DataColumn.kind:()Lorg/jetbrains/kotlinx/dataframe/columns/ColumnKind;
      12: areturn

  public static final kotlin.reflect.KClass<?> getTypeClass(org.jetbrains.kotlinx.dataframe.DataColumn<?>);
    Code:
       0: aload_0
       1: ldc           #10                 // String <this>
       3: invokestatic  #16                 // Method kotlin/jvm/internal/Intrinsics.checkNotNullParameter:(Ljava/lang/Object;Ljava/lang/String;)V
       6: aload_0
       7: invokestatic  #84                 // Method getType:(Lorg/jetbrains/kotlinx/dataframe/DataColumn;)Lkotlin/reflect/KType;
      10: invokeinterface #90,  1           // InterfaceMethod kotlin/reflect/KType.getClassifier:()Lkotlin/reflect/KClassifier;
      15: dup
      16: ifnonnull     30
      19: pop
      20: new           #92                 // class java/lang/NullPointerException
      23: dup
      24: ldc           #94                 // String null cannot be cast to non-null type kotlin.reflect.KClass<*>
      26: invokespecial #98                 // Method java/lang/NullPointerException."<init>":(Ljava/lang/String;)V
      29: athrow
      30: checkcast     #100                // class kotlin/reflect/KClass
      33: areturn

  public static final kotlin.ranges.IntRange indices(org.jetbrains.kotlinx.dataframe.DataColumn<?>);
    Code:
       0: aload_0
       1: ldc           #10                 // String <this>
       3: invokestatic  #16                 // Method kotlin/jvm/internal/Intrinsics.checkNotNullParameter:(Ljava/lang/Object;Ljava/lang/String;)V
       6: iconst_0
       7: aload_0
       8: checkcast     #105                // class org/jetbrains/kotlinx/dataframe/columns/BaseColumn
      11: invokestatic  #110                // Method org/jetbrains/kotlinx/dataframe/columns/BaseColumnKt.getSize:(Lorg/jetbrains/kotlinx/dataframe/columns/BaseColumn;)I
      14: invokestatic  #116                // Method kotlin/ranges/RangesKt.until:(II)Lkotlin/ranges/IntRange;
      17: areturn
}
