Compiled from "constructors.kt"
public final class org.jetbrains.kotlinx.dataframe.DataFrameBuilder {
  private final java.util.List<java.lang.String> header;

  public org.jetbrains.kotlinx.dataframe.DataFrameBuilder(java.util.List<java.lang.String>);
    Code:
       0: aload_1
       1: ldc           #10                 // String header
       3: invokestatic  #16                 // Method kotlin/jvm/internal/Intrinsics.checkNotNullParameter:(Ljava/lang/Object;Ljava/lang/String;)V
       6: aload_0
       7: invokespecial #19                 // Method java/lang/Object."<init>":()V
      10: aload_0
      11: aload_1
      12: putfield      #22                 // Field header:Ljava/util/List;
      15: return

  public final org.jetbrains.kotlinx.dataframe.DataFrame<?> invoke(org.jetbrains.kotlinx.dataframe.DataColumn<?>...);
    Code:
       0: aload_1
       1: ldc           #29                 // String columns
       3: invokestatic  #16                 // Method kotlin/jvm/internal/Intrinsics.checkNotNullParameter:(Ljava/lang/Object;Ljava/lang/String;)V
       6: aload_0
       7: aload_1
       8: invokestatic  #35                 // Method kotlin/collections/ArraysKt.asIterable:([Ljava/lang/Object;)Ljava/lang/Iterable;
      11: invokevirtual #38                 // Method invoke:(Ljava/lang/Iterable;)Lorg/jetbrains/kotlinx/dataframe/DataFrame;
      14: areturn

  public final org.jetbrains.kotlinx.dataframe.DataFrame<?> invoke(java.lang.Iterable<? extends org.jetbrains.kotlinx.dataframe.DataColumn<?>>);
    Code:
       0: aload_1
       1: ldc           #29                 // String columns
       3: invokestatic  #16                 // Method kotlin/jvm/internal/Intrinsics.checkNotNullParameter:(Ljava/lang/Object;Ljava/lang/String;)V
       6: aload_1
       7: invokestatic  #46                 // Method org/jetbrains/kotlinx/dataframe/impl/UtilsKt.asList:(Ljava/lang/Iterable;)Ljava/util/List;
      10: astore_2
      11: aload_2
      12: invokeinterface #52,  1           // InterfaceMethod java/util/List.size:()I
      17: aload_0
      18: getfield      #22                 // Field header:Ljava/util/List;
      21: invokeinterface #52,  1           // InterfaceMethod java/util/List.size:()I
      26: if_icmpne     33
      29: iconst_1
      30: goto          34
      33: iconst_0
      34: ifne          57
      37: iconst_0
      38: istore        4
      40: ldc           #54                 // String Number of columns differs from number of column names
      42: astore        4
      44: new           #56                 // class java/lang/IllegalArgumentException
      47: dup
      48: aload         4
      50: invokevirtual #60                 // Method java/lang/Object.toString:()Ljava/lang/String;
      53: invokespecial #63                 // Method java/lang/IllegalArgumentException."<init>":(Ljava/lang/String;)V
      56: athrow
      57: aload_2
      58: checkcast     #65                 // class java/lang/Iterable
      61: astore_3
      62: iconst_0
      63: istore        4
      65: aload_3
      66: astore        5
      68: new           #67                 // class java/util/ArrayList
      71: dup
      72: aload_3
      73: bipush        10
      75: invokestatic  #73                 // Method kotlin/collections/CollectionsKt.collectionSizeOrDefault:(Ljava/lang/Iterable;I)I
      78: invokespecial #76                 // Method java/util/ArrayList."<init>":(I)V
      81: checkcast     #78                 // class java/util/Collection
      84: astore        6
      86: iconst_0
      87: istore        7
      89: iconst_0
      90: istore        8
      92: aload         5
      94: invokeinterface #82,  1           // InterfaceMethod java/lang/Iterable.iterator:()Ljava/util/Iterator;
      99: astore        9
     101: aload         9
     103: invokeinterface #88,  1           // InterfaceMethod java/util/Iterator.hasNext:()Z
     108: ifeq          193
     111: aload         9
     113: invokeinterface #92,  1           // InterfaceMethod java/util/Iterator.next:()Ljava/lang/Object;
     118: astore        10
     120: aload         6
     122: iload         8
     124: istore        11
     126: iload         11
     128: iconst_1
     129: iadd
     130: istore        8
     132: iload         11
     134: istore        11
     136: iload         11
     138: ifge          144
     141: invokestatic  #95                 // Method kotlin/collections/CollectionsKt.throwIndexOverflow:()V
     144: iload         11
     146: aload         10
     148: checkcast     #97                 // class org/jetbrains/kotlinx/dataframe/DataColumn
     151: astore        12
     153: istore        13
     155: astore        15
     157: iconst_0
     158: istore        14
     160: aload         12
     162: aload_0
     163: getfield      #22                 // Field header:Ljava/util/List;
     166: iload         13
     168: invokeinterface #101,  2          // InterfaceMethod java/util/List.get:(I)Ljava/lang/Object;
     173: checkcast     #103                // class java/lang/String
     176: invokeinterface #107,  2          // InterfaceMethod org/jetbrains/kotlinx/dataframe/DataColumn.rename:(Ljava/lang/String;)Lorg/jetbrains/kotlinx/dataframe/DataColumn;
     181: aload         15
     183: swap
     184: invokeinterface #111,  2          // InterfaceMethod java/util/Collection.add:(Ljava/lang/Object;)Z
     189: pop
     190: goto          101
     193: aload         6
     195: checkcast     #48                 // class java/util/List
     198: nop
     199: checkcast     #65                 // class java/lang/Iterable
     202: invokestatic  #116                // Method org/jetbrains/kotlinx/dataframe/api/DataFrameIterableKt.toDataFrameAnyColumn:(Ljava/lang/Iterable;)Lorg/jetbrains/kotlinx/dataframe/DataFrame;
     205: areturn

  public final org.jetbrains.kotlinx.dataframe.DataFrame<?> invoke(java.lang.Object...);
    Code:
       0: aload_1
       1: ldc           #137                // String values
       3: invokestatic  #16                 // Method kotlin/jvm/internal/Intrinsics.checkNotNullParameter:(Ljava/lang/Object;Ljava/lang/String;)V
       6: aload_0
       7: aload_1
       8: invokestatic  #35                 // Method kotlin/collections/ArraysKt.asIterable:([Ljava/lang/Object;)Ljava/lang/Iterable;
      11: invokevirtual #140                // Method invoke1:(Ljava/lang/Iterable;)Lorg/jetbrains/kotlinx/dataframe/DataFrame;
      14: areturn

  public final org.jetbrains.kotlinx.dataframe.DataFrame<?> invoke1(java.lang.Iterable<? extends java.lang.Object>);
    Code:
       0: aload_1
       1: ldc           #137                // String values
       3: invokestatic  #16                 // Method kotlin/jvm/internal/Intrinsics.checkNotNullParameter:(Ljava/lang/Object;Ljava/lang/String;)V
       6: aload_1
       7: invokestatic  #46                 // Method org/jetbrains/kotlinx/dataframe/impl/UtilsKt.asList:(Ljava/lang/Iterable;)Ljava/util/List;
      10: astore_2
      11: aload_0
      12: getfield      #22                 // Field header:Ljava/util/List;
      15: invokeinterface #52,  1           // InterfaceMethod java/util/List.size:()I
      20: istore_3
      21: aload_0
      22: getfield      #22                 // Field header:Ljava/util/List;
      25: invokeinterface #52,  1           // InterfaceMethod java/util/List.size:()I
      30: ifle          48
      33: aload_2
      34: invokeinterface #52,  1           // InterfaceMethod java/util/List.size:()I
      39: iload_3
      40: irem
      41: ifne          48
      44: iconst_1
      45: goto          49
      48: iconst_0
      49: ifne          103
      52: iconst_0
      53: istore        5
      55: new           #146                // class java/lang/StringBuilder
      58: dup
      59: invokespecial #147                // Method java/lang/StringBuilder."<init>":()V
      62: ldc           #149                // String Number of values
      64: invokevirtual #153                // Method java/lang/StringBuilder.append:(Ljava/lang/String;)Ljava/lang/StringBuilder;
      67: aload_2
      68: invokeinterface #52,  1           // InterfaceMethod java/util/List.size:()I
      73: invokevirtual #156                // Method java/lang/StringBuilder.append:(I)Ljava/lang/StringBuilder;
      76: ldc           #158                // String  is not divisible by number of columns
      78: invokevirtual #153                // Method java/lang/StringBuilder.append:(Ljava/lang/String;)Ljava/lang/StringBuilder;
      81: iload_3
      82: invokevirtual #156                // Method java/lang/StringBuilder.append:(I)Ljava/lang/StringBuilder;
      85: invokevirtual #159                // Method java/lang/StringBuilder.toString:()Ljava/lang/String;
      88: astore        5
      90: new           #56                 // class java/lang/IllegalArgumentException
      93: dup
      94: aload         5
      96: invokevirtual #60                 // Method java/lang/Object.toString:()Ljava/lang/String;
      99: invokespecial #63                 // Method java/lang/IllegalArgumentException."<init>":(Ljava/lang/String;)V
     102: athrow
     103: aload_2
     104: invokeinterface #52,  1           // InterfaceMethod java/util/List.size:()I
     109: iload_3
     110: idiv
     111: istore        4
     113: iconst_0
     114: iload_3
     115: invokestatic  #165                // Method kotlin/ranges/RangesKt.until:(II)Lkotlin/ranges/IntRange;
     118: checkcast     #65                 // class java/lang/Iterable
     121: astore        5
     123: iconst_0
     124: istore        6
     126: aload         5
     128: astore        7
     130: new           #67                 // class java/util/ArrayList
     133: dup
     134: aload         5
     136: bipush        10
     138: invokestatic  #73                 // Method kotlin/collections/CollectionsKt.collectionSizeOrDefault:(Ljava/lang/Iterable;I)I
     141: invokespecial #76                 // Method java/util/ArrayList."<init>":(I)V
     144: checkcast     #78                 // class java/util/Collection
     147: astore        8
     149: iconst_0
     150: istore        9
     152: aload         7
     154: invokeinterface #82,  1           // InterfaceMethod java/lang/Iterable.iterator:()Ljava/util/Iterator;
     159: astore        10
     161: aload         10
     163: invokeinterface #88,  1           // InterfaceMethod java/util/Iterator.hasNext:()Z
     168: ifeq          342
     171: aload         10
     173: checkcast     #167                // class kotlin/collections/IntIterator
     176: invokevirtual #170                // Method kotlin/collections/IntIterator.nextInt:()I
     179: istore        11
     181: aload         8
     183: iload         11
     185: istore        12
     187: astore        25
     189: iconst_0
     190: istore        13
     192: iconst_0
     193: iload         4
     195: invokestatic  #165                // Method kotlin/ranges/RangesKt.until:(II)Lkotlin/ranges/IntRange;
     198: checkcast     #65                 // class java/lang/Iterable
     201: astore        14
     203: iconst_0
     204: istore        15
     206: aload         14
     208: astore        16
     210: new           #67                 // class java/util/ArrayList
     213: dup
     214: aload         14
     216: bipush        10
     218: invokestatic  #73                 // Method kotlin/collections/CollectionsKt.collectionSizeOrDefault:(Ljava/lang/Iterable;I)I
     221: invokespecial #76                 // Method java/util/ArrayList."<init>":(I)V
     224: checkcast     #78                 // class java/util/Collection
     227: astore        17
     229: iconst_0
     230: istore        18
     232: aload         16
     234: invokeinterface #82,  1           // InterfaceMethod java/lang/Iterable.iterator:()Ljava/util/Iterator;
     239: astore        19
     241: aload         19
     243: invokeinterface #88,  1           // InterfaceMethod java/util/Iterator.hasNext:()Z
     248: ifeq          297
     251: aload         19
     253: checkcast     #167                // class kotlin/collections/IntIterator
     256: invokevirtual #170                // Method kotlin/collections/IntIterator.nextInt:()I
     259: istore        20
     261: aload         17
     263: iload         20
     265: istore        21
     267: astore        22
     269: iconst_0
     270: istore        23
     272: aload_2
     273: iload         21
     275: iload_3
     276: imul
     277: iload         12
     279: iadd
     280: invokeinterface #101,  2          // InterfaceMethod java/util/List.get:(I)Ljava/lang/Object;
     285: aload         22
     287: swap
     288: invokeinterface #111,  2          // InterfaceMethod java/util/Collection.add:(Ljava/lang/Object;)Z
     293: pop
     294: goto          241
     297: aload         17
     299: checkcast     #48                 // class java/util/List
     302: nop
     303: astore        24
     305: getstatic     #174                // Field org/jetbrains/kotlinx/dataframe/DataColumn.Companion:Lorg/jetbrains/kotlinx/dataframe/DataColumn$Companion;
     308: aload_0
     309: getfield      #22                 // Field header:Ljava/util/List;
     312: iload         12
     314: invokeinterface #101,  2          // InterfaceMethod java/util/List.get:(I)Ljava/lang/Object;
     319: checkcast     #103                // class java/lang/String
     322: aload         24
     324: aconst_null
     325: iconst_4
     326: aconst_null
     327: invokestatic  #180                // Method org/jetbrains/kotlinx/dataframe/DataColumn$Companion.createWithTypeInference$default:(Lorg/jetbrains/kotlinx/dataframe/DataColumn$Companion;Ljava/lang/String;Ljava/util/List;Ljava/lang/Boolean;ILjava/lang/Object;)Lorg/jetbrains/kotlinx/dataframe/DataColumn;
     330: aload         25
     332: swap
     333: invokeinterface #111,  2          // InterfaceMethod java/util/Collection.add:(Ljava/lang/Object;)Z
     338: pop
     339: goto          161
     342: aload         8
     344: checkcast     #48                 // class java/util/List
     347: nop
     348: checkcast     #65                 // class java/lang/Iterable
     351: invokestatic  #116                // Method org/jetbrains/kotlinx/dataframe/api/DataFrameIterableKt.toDataFrameAnyColumn:(Ljava/lang/Iterable;)Lorg/jetbrains/kotlinx/dataframe/DataFrame;
     354: areturn

  public final org.jetbrains.kotlinx.dataframe.DataFrame<?> invoke(kotlin.sequences.Sequence<? extends java.lang.Object>);
    Code:
       0: aload_1
       1: ldc           #196                // String args
       3: invokestatic  #16                 // Method kotlin/jvm/internal/Intrinsics.checkNotNullParameter:(Ljava/lang/Object;Ljava/lang/String;)V
       6: aload_0
       7: aload_1
       8: invokestatic  #202                // Method kotlin/sequences/SequencesKt.toList:(Lkotlin/sequences/Sequence;)Ljava/util/List;
      11: checkcast     #78                 // class java/util/Collection
      14: astore_3
      15: iconst_0
      16: istore        4
      18: aload_3
      19: astore        5
      21: aload         5
      23: iconst_0
      24: anewarray     #4                  // class java/lang/Object
      27: invokeinterface #206,  2          // InterfaceMethod java/util/Collection.toArray:([Ljava/lang/Object;)[Ljava/lang/Object;
      32: dup
      33: ifnonnull     47
      36: pop
      37: new           #208                // class java/lang/NullPointerException
      40: dup
      41: ldc           #210                // String null cannot be cast to non-null type kotlin.Array<T of kotlin.collections.ArraysKt__ArraysJVMKt.toTypedArray>
      43: invokespecial #211                // Method java/lang/NullPointerException."<init>":(Ljava/lang/String;)V
      46: athrow
      47: astore_2
      48: aload_2
      49: aload_2
      50: arraylength
      51: invokestatic  #217                // Method java/util/Arrays.copyOf:([Ljava/lang/Object;I)[Ljava/lang/Object;
      54: invokevirtual #219                // Method invoke:([Ljava/lang/Object;)Lorg/jetbrains/kotlinx/dataframe/DataFrame;
      57: areturn

  public final org.jetbrains.kotlinx.dataframe.DataFrame<?> withColumns(kotlin.jvm.functions.Function1<? super java.lang.String, ? extends org.jetbrains.kotlinx.dataframe.DataColumn<?>>);
    Code:
       0: aload_1
       1: ldc           #231                // String columnBuilder
       3: invokestatic  #16                 // Method kotlin/jvm/internal/Intrinsics.checkNotNullParameter:(Ljava/lang/Object;Ljava/lang/String;)V
       6: aload_0
       7: getfield      #22                 // Field header:Ljava/util/List;
      10: checkcast     #65                 // class java/lang/Iterable
      13: astore_2
      14: iconst_0
      15: istore_3
      16: aload_2
      17: astore        4
      19: new           #67                 // class java/util/ArrayList
      22: dup
      23: aload_2
      24: bipush        10
      26: invokestatic  #73                 // Method kotlin/collections/CollectionsKt.collectionSizeOrDefault:(Ljava/lang/Iterable;I)I
      29: invokespecial #76                 // Method java/util/ArrayList."<init>":(I)V
      32: checkcast     #78                 // class java/util/Collection
      35: astore        5
      37: iconst_0
      38: istore        6
      40: aload         4
      42: invokeinterface #82,  1           // InterfaceMethod java/lang/Iterable.iterator:()Ljava/util/Iterator;
      47: astore        7
      49: aload         7
      51: invokeinterface #88,  1           // InterfaceMethod java/util/Iterator.hasNext:()Z
      56: ifeq          87
      59: aload         7
      61: invokeinterface #92,  1           // InterfaceMethod java/util/Iterator.next:()Ljava/lang/Object;
      66: astore        8
      68: aload         5
      70: aload_1
      71: aload         8
      73: invokeinterface #236,  2          // InterfaceMethod kotlin/jvm/functions/Function1.invoke:(Ljava/lang/Object;)Ljava/lang/Object;
      78: invokeinterface #111,  2          // InterfaceMethod java/util/Collection.add:(Ljava/lang/Object;)Z
      83: pop
      84: goto          49
      87: aload         5
      89: checkcast     #48                 // class java/util/List
      92: nop
      93: checkcast     #65                 // class java/lang/Iterable
      96: invokestatic  #116                // Method org/jetbrains/kotlinx/dataframe/api/DataFrameIterableKt.toDataFrameAnyColumn:(Ljava/lang/Iterable;)Lorg/jetbrains/kotlinx/dataframe/DataFrame;
      99: areturn

  public final <T> org.jetbrains.kotlinx.dataframe.DataFrame<?> invoke(kotlin.jvm.functions.Function1<? super java.lang.String, ? extends java.lang.Iterable<? extends T>>);
    Code:
       0: aload_1
       1: ldc           #240                // String valuesBuilder
       3: invokestatic  #16                 // Method kotlin/jvm/internal/Intrinsics.checkNotNullParameter:(Ljava/lang/Object;Ljava/lang/String;)V
       6: iconst_0
       7: istore_2
       8: aload_0
       9: invokestatic  #243                // Method kotlin/jvm/internal/Intrinsics.needClassReification:()V
      12: new           #245                // class org/jetbrains/kotlinx/dataframe/DataFrameBuilder$invoke$3
      15: dup
      16: aload_1
      17: invokespecial #248                // Method org/jetbrains/kotlinx/dataframe/DataFrameBuilder$invoke$3."<init>":(Lkotlin/jvm/functions/Function1;)V
      20: checkcast     #233                // class kotlin/jvm/functions/Function1
      23: invokevirtual #250                // Method withColumns:(Lkotlin/jvm/functions/Function1;)Lorg/jetbrains/kotlinx/dataframe/DataFrame;
      26: areturn

  public final <C> org.jetbrains.kotlinx.dataframe.DataFrame<?> fill(int, C);
    Code:
       0: iconst_0
       1: istore_3
       2: aload_0
       3: invokestatic  #243                // Method kotlin/jvm/internal/Intrinsics.needClassReification:()V
       6: new           #256                // class org/jetbrains/kotlinx/dataframe/DataFrameBuilder$fill$1
       9: dup
      10: iload_1
      11: aload_2
      12: invokespecial #259                // Method org/jetbrains/kotlinx/dataframe/DataFrameBuilder$fill$1."<init>":(ILjava/lang/Object;)V
      15: checkcast     #233                // class kotlin/jvm/functions/Function1
      18: invokevirtual #250                // Method withColumns:(Lkotlin/jvm/functions/Function1;)Lorg/jetbrains/kotlinx/dataframe/DataFrame;
      21: areturn

  public final <C> org.jetbrains.kotlinx.dataframe.DataFrame<?> nulls(int);
    Code:
       0: iconst_0
       1: istore_2
       2: aload_0
       3: astore_3
       4: aconst_null
       5: astore        4
       7: iconst_0
       8: istore        5
      10: aload_3
      11: invokestatic  #243                // Method kotlin/jvm/internal/Intrinsics.needClassReification:()V
      14: new           #266                // class org/jetbrains/kotlinx/dataframe/DataFrameBuilder$nulls$$inlined$fill$1
      17: dup
      18: iload_1
      19: aload         4
      21: invokespecial #267                // Method org/jetbrains/kotlinx/dataframe/DataFrameBuilder$nulls$$inlined$fill$1."<init>":(ILjava/lang/Object;)V
      24: checkcast     #233                // class kotlin/jvm/functions/Function1
      27: invokevirtual #250                // Method withColumns:(Lkotlin/jvm/functions/Function1;)Lorg/jetbrains/kotlinx/dataframe/DataFrame;
      30: areturn

  public final <C> org.jetbrains.kotlinx.dataframe.DataFrame<?> fillIndexed(int, kotlin.jvm.functions.Function2<? super java.lang.Integer, ? super java.lang.String, ? extends C>);
    Code:
       0: aload_2
       1: ldc_w         #275                // String init
       4: invokestatic  #16                 // Method kotlin/jvm/internal/Intrinsics.checkNotNullParameter:(Ljava/lang/Object;Ljava/lang/String;)V
       7: iconst_0
       8: istore_3
       9: aload_0
      10: invokestatic  #243                // Method kotlin/jvm/internal/Intrinsics.needClassReification:()V
      13: new           #277                // class org/jetbrains/kotlinx/dataframe/DataFrameBuilder$fillIndexed$1
      16: dup
      17: iload_1
      18: aload_2
      19: invokespecial #280                // Method org/jetbrains/kotlinx/dataframe/DataFrameBuilder$fillIndexed$1."<init>":(ILkotlin/jvm/functions/Function2;)V
      22: checkcast     #233                // class kotlin/jvm/functions/Function1
      25: invokevirtual #250                // Method withColumns:(Lkotlin/jvm/functions/Function1;)Lorg/jetbrains/kotlinx/dataframe/DataFrame;
      28: areturn

  public final <C> org.jetbrains.kotlinx.dataframe.DataFrame<?> fill(int, kotlin.jvm.functions.Function1<? super java.lang.Integer, ? extends C>);
    Code:
       0: aload_2
       1: ldc_w         #275                // String init
       4: invokestatic  #16                 // Method kotlin/jvm/internal/Intrinsics.checkNotNullParameter:(Ljava/lang/Object;Ljava/lang/String;)V
       7: iconst_0
       8: istore_3
       9: aload_0
      10: invokestatic  #243                // Method kotlin/jvm/internal/Intrinsics.needClassReification:()V
      13: new           #286                // class org/jetbrains/kotlinx/dataframe/DataFrameBuilder$fill$2
      16: dup
      17: iload_1
      18: aload_2
      19: invokespecial #289                // Method org/jetbrains/kotlinx/dataframe/DataFrameBuilder$fill$2."<init>":(ILkotlin/jvm/functions/Function1;)V
      22: checkcast     #233                // class kotlin/jvm/functions/Function1
      25: invokevirtual #250                // Method withColumns:(Lkotlin/jvm/functions/Function1;)Lorg/jetbrains/kotlinx/dataframe/DataFrame;
      28: areturn

  private final <C> org.jetbrains.kotlinx.dataframe.DataFrame<?> fillNotNull(int, kotlin.jvm.functions.Function1<? super java.lang.Integer, ? extends C>);
    Code:
       0: iconst_0
       1: istore_3
       2: aload_0
       3: invokestatic  #243                // Method kotlin/jvm/internal/Intrinsics.needClassReification:()V
       6: new           #292                // class org/jetbrains/kotlinx/dataframe/DataFrameBuilder$fillNotNull$1
       9: dup
      10: iload_1
      11: aload_2
      12: invokespecial #293                // Method org/jetbrains/kotlinx/dataframe/DataFrameBuilder$fillNotNull$1."<init>":(ILkotlin/jvm/functions/Function1;)V
      15: checkcast     #233                // class kotlin/jvm/functions/Function1
      18: invokevirtual #250                // Method withColumns:(Lkotlin/jvm/functions/Function1;)Lorg/jetbrains/kotlinx/dataframe/DataFrame;
      21: areturn

  public final org.jetbrains.kotlinx.dataframe.DataFrame<?> randomInt(int);
    Code:
       0: aload_0
       1: astore_2
       2: iconst_0
       3: istore_3
       4: aload_2
       5: new           #298                // class org/jetbrains/kotlinx/dataframe/DataFrameBuilder$randomInt$$inlined$fillNotNull$1
       8: dup
       9: iload_1
      10: invokespecial #299                // Method org/jetbrains/kotlinx/dataframe/DataFrameBuilder$randomInt$$inlined$fillNotNull$1."<init>":(I)V
      13: checkcast     #233                // class kotlin/jvm/functions/Function1
      16: invokevirtual #250                // Method withColumns:(Lkotlin/jvm/functions/Function1;)Lorg/jetbrains/kotlinx/dataframe/DataFrame;
      19: areturn

  public final org.jetbrains.kotlinx.dataframe.DataFrame<?> randomInt(int, kotlin.ranges.IntRange);
    Code:
       0: aload_2
       1: ldc_w         #303                // String range
       4: invokestatic  #16                 // Method kotlin/jvm/internal/Intrinsics.checkNotNullParameter:(Ljava/lang/Object;Ljava/lang/String;)V
       7: aload_0
       8: astore_3
       9: iconst_0
      10: istore        4
      12: aload_3
      13: new           #305                // class org/jetbrains/kotlinx/dataframe/DataFrameBuilder$randomInt$$inlined$fillNotNull$2
      16: dup
      17: iload_1
      18: aload_2
      19: invokespecial #308                // Method org/jetbrains/kotlinx/dataframe/DataFrameBuilder$randomInt$$inlined$fillNotNull$2."<init>":(ILkotlin/ranges/IntRange;)V
      22: checkcast     #233                // class kotlin/jvm/functions/Function1
      25: invokevirtual #250                // Method withColumns:(Lkotlin/jvm/functions/Function1;)Lorg/jetbrains/kotlinx/dataframe/DataFrame;
      28: areturn

  public final org.jetbrains.kotlinx.dataframe.DataFrame<?> randomDouble(int);
    Code:
       0: aload_0
       1: astore_2
       2: iconst_0
       3: istore_3
       4: aload_2
       5: new           #312                // class org/jetbrains/kotlinx/dataframe/DataFrameBuilder$randomDouble$$inlined$fillNotNull$1
       8: dup
       9: iload_1
      10: invokespecial #313                // Method org/jetbrains/kotlinx/dataframe/DataFrameBuilder$randomDouble$$inlined$fillNotNull$1."<init>":(I)V
      13: checkcast     #233                // class kotlin/jvm/functions/Function1
      16: invokevirtual #250                // Method withColumns:(Lkotlin/jvm/functions/Function1;)Lorg/jetbrains/kotlinx/dataframe/DataFrame;
      19: areturn

  public final org.jetbrains.kotlinx.dataframe.DataFrame<?> randomDouble(int, kotlin.ranges.ClosedRange<java.lang.Double>);
    Code:
       0: aload_2
       1: ldc_w         #303                // String range
       4: invokestatic  #16                 // Method kotlin/jvm/internal/Intrinsics.checkNotNullParameter:(Ljava/lang/Object;Ljava/lang/String;)V
       7: aload_0
       8: astore_3
       9: iconst_0
      10: istore        4
      12: aload_3
      13: new           #317                // class org/jetbrains/kotlinx/dataframe/DataFrameBuilder$randomDouble$$inlined$fillNotNull$2
      16: dup
      17: iload_1
      18: aload_2
      19: invokespecial #320                // Method org/jetbrains/kotlinx/dataframe/DataFrameBuilder$randomDouble$$inlined$fillNotNull$2."<init>":(ILkotlin/ranges/ClosedRange;)V
      22: checkcast     #233                // class kotlin/jvm/functions/Function1
      25: invokevirtual #250                // Method withColumns:(Lkotlin/jvm/functions/Function1;)Lorg/jetbrains/kotlinx/dataframe/DataFrame;
      28: areturn

  public final org.jetbrains.kotlinx.dataframe.DataFrame<?> randomFloat(int);
    Code:
       0: aload_0
       1: astore_2
       2: iconst_0
       3: istore_3
       4: aload_2
       5: new           #324                // class org/jetbrains/kotlinx/dataframe/DataFrameBuilder$randomFloat$$inlined$fillNotNull$1
       8: dup
       9: iload_1
      10: invokespecial #325                // Method org/jetbrains/kotlinx/dataframe/DataFrameBuilder$randomFloat$$inlined$fillNotNull$1."<init>":(I)V
      13: checkcast     #233                // class kotlin/jvm/functions/Function1
      16: invokevirtual #250                // Method withColumns:(Lkotlin/jvm/functions/Function1;)Lorg/jetbrains/kotlinx/dataframe/DataFrame;
      19: areturn

  public final org.jetbrains.kotlinx.dataframe.DataFrame<?> randomLong(int);
    Code:
       0: aload_0
       1: astore_2
       2: iconst_0
       3: istore_3
       4: aload_2
       5: new           #328                // class org/jetbrains/kotlinx/dataframe/DataFrameBuilder$randomLong$$inlined$fillNotNull$1
       8: dup
       9: iload_1
      10: invokespecial #329                // Method org/jetbrains/kotlinx/dataframe/DataFrameBuilder$randomLong$$inlined$fillNotNull$1."<init>":(I)V
      13: checkcast     #233                // class kotlin/jvm/functions/Function1
      16: invokevirtual #250                // Method withColumns:(Lkotlin/jvm/functions/Function1;)Lorg/jetbrains/kotlinx/dataframe/DataFrame;
      19: areturn

  public final org.jetbrains.kotlinx.dataframe.DataFrame<?> randomLong(int, kotlin.ranges.ClosedRange<java.lang.Long>);
    Code:
       0: aload_2
       1: ldc_w         #303                // String range
       4: invokestatic  #16                 // Method kotlin/jvm/internal/Intrinsics.checkNotNullParameter:(Ljava/lang/Object;Ljava/lang/String;)V
       7: aload_0
       8: astore_3
       9: iconst_0
      10: istore        4
      12: aload_3
      13: new           #332                // class org/jetbrains/kotlinx/dataframe/DataFrameBuilder$randomLong$$inlined$fillNotNull$2
      16: dup
      17: iload_1
      18: aload_2
      19: invokespecial #333                // Method org/jetbrains/kotlinx/dataframe/DataFrameBuilder$randomLong$$inlined$fillNotNull$2."<init>":(ILkotlin/ranges/ClosedRange;)V
      22: checkcast     #233                // class kotlin/jvm/functions/Function1
      25: invokevirtual #250                // Method withColumns:(Lkotlin/jvm/functions/Function1;)Lorg/jetbrains/kotlinx/dataframe/DataFrame;
      28: areturn

  public final org.jetbrains.kotlinx.dataframe.DataFrame<?> randomBoolean(int);
    Code:
       0: aload_0
       1: astore_2
       2: iconst_0
       3: istore_3
       4: aload_2
       5: new           #336                // class org/jetbrains/kotlinx/dataframe/DataFrameBuilder$randomBoolean$$inlined$fillNotNull$1
       8: dup
       9: iload_1
      10: invokespecial #337                // Method org/jetbrains/kotlinx/dataframe/DataFrameBuilder$randomBoolean$$inlined$fillNotNull$1."<init>":(I)V
      13: checkcast     #233                // class kotlin/jvm/functions/Function1
      16: invokevirtual #250                // Method withColumns:(Lkotlin/jvm/functions/Function1;)Lorg/jetbrains/kotlinx/dataframe/DataFrame;
      19: areturn
}
