Compiled from "StructureMapUtilities.java"
public class org.hl7.fhir.dstu3.utils.StructureMapUtilities$TargetWriter {
  private java.util.Map<java.lang.String, java.lang.String> newResources;

  private java.util.List<org.hl7.fhir.dstu3.utils.StructureMapUtilities$StringPair> assignments;

  private java.util.List<org.hl7.fhir.dstu3.utils.StructureMapUtilities$StringPair> keyProps;

  private org.hl7.fhir.utilities.CommaSeparatedStringBuilder txt;

  final org.hl7.fhir.dstu3.utils.StructureMapUtilities this$0;

  public org.hl7.fhir.dstu3.utils.StructureMapUtilities$TargetWriter(org.hl7.fhir.dstu3.utils.StructureMapUtilities);
    Code:
       0: aload_0
       1: aload_1
       2: putfield      #1                  // Field this$0:Lorg/hl7/fhir/dstu3/utils/StructureMapUtilities;
       5: aload_0
       6: invokespecial #2                  // Method java/lang/Object."<init>":()V
       9: aload_0
      10: new           #3                  // class java/util/HashMap
      13: dup
      14: invokespecial #4                  // Method java/util/HashMap."<init>":()V
      17: putfield      #5                  // Field newResources:Ljava/util/Map;
      20: aload_0
      21: new           #6                  // class java/util/ArrayList
      24: dup
      25: invokespecial #7                  // Method java/util/ArrayList."<init>":()V
      28: putfield      #8                  // Field assignments:Ljava/util/List;
      31: aload_0
      32: new           #6                  // class java/util/ArrayList
      35: dup
      36: invokespecial #7                  // Method java/util/ArrayList."<init>":()V
      39: putfield      #9                  // Field keyProps:Ljava/util/List;
      42: aload_0
      43: new           #10                 // class org/hl7/fhir/utilities/CommaSeparatedStringBuilder
      46: dup
      47: invokespecial #11                 // Method org/hl7/fhir/utilities/CommaSeparatedStringBuilder."<init>":()V
      50: putfield      #12                 // Field txt:Lorg/hl7/fhir/utilities/CommaSeparatedStringBuilder;
      53: return

  public void newResource(java.lang.String, java.lang.String);
    Code:
       0: aload_0
       1: getfield      #5                  // Field newResources:Ljava/util/Map;
       4: aload_1
       5: aload_2
       6: invokeinterface #13,  3           // InterfaceMethod java/util/Map.put:(Ljava/lang/Object;Ljava/lang/Object;)Ljava/lang/Object;
      11: pop
      12: aload_0
      13: getfield      #12                 // Field txt:Lorg/hl7/fhir/utilities/CommaSeparatedStringBuilder;
      16: new           #14                 // class java/lang/StringBuilder
      19: dup
      20: invokespecial #15                 // Method java/lang/StringBuilder."<init>":()V
      23: ldc           #16                 // String new
      25: invokevirtual #17                 // Method java/lang/StringBuilder.append:(Ljava/lang/String;)Ljava/lang/StringBuilder;
      28: aload_2
      29: invokevirtual #17                 // Method java/lang/StringBuilder.append:(Ljava/lang/String;)Ljava/lang/StringBuilder;
      32: invokevirtual #18                 // Method java/lang/StringBuilder.toString:()Ljava/lang/String;
      35: invokevirtual #19                 // Method org/hl7/fhir/utilities/CommaSeparatedStringBuilder.append:(Ljava/lang/String;)V
      38: return

  public void valueAssignment(java.lang.String, java.lang.String);
    Code:
       0: aload_0
       1: getfield      #8                  // Field assignments:Ljava/util/List;
       4: new           #20                 // class org/hl7/fhir/dstu3/utils/StructureMapUtilities$StringPair
       7: dup
       8: aload_0
       9: getfield      #1                  // Field this$0:Lorg/hl7/fhir/dstu3/utils/StructureMapUtilities;
      12: aload_1
      13: aload_2
      14: invokespecial #21                 // Method org/hl7/fhir/dstu3/utils/StructureMapUtilities$StringPair."<init>":(Lorg/hl7/fhir/dstu3/utils/StructureMapUtilities;Ljava/lang/String;Ljava/lang/String;)V
      17: invokeinterface #22,  2           // InterfaceMethod java/util/List.add:(Ljava/lang/Object;)Z
      22: pop
      23: aload_0
      24: getfield      #12                 // Field txt:Lorg/hl7/fhir/utilities/CommaSeparatedStringBuilder;
      27: aload_2
      28: invokevirtual #19                 // Method org/hl7/fhir/utilities/CommaSeparatedStringBuilder.append:(Ljava/lang/String;)V
      31: return

  public void keyAssignment(java.lang.String, java.lang.String);
    Code:
       0: aload_0
       1: getfield      #9                  // Field keyProps:Ljava/util/List;
       4: new           #20                 // class org/hl7/fhir/dstu3/utils/StructureMapUtilities$StringPair
       7: dup
       8: aload_0
       9: getfield      #1                  // Field this$0:Lorg/hl7/fhir/dstu3/utils/StructureMapUtilities;
      12: aload_1
      13: aload_2
      14: invokespecial #21                 // Method org/hl7/fhir/dstu3/utils/StructureMapUtilities$StringPair."<init>":(Lorg/hl7/fhir/dstu3/utils/StructureMapUtilities;Ljava/lang/String;Ljava/lang/String;)V
      17: invokeinterface #22,  2           // InterfaceMethod java/util/List.add:(Ljava/lang/Object;)Z
      22: pop
      23: aload_0
      24: getfield      #12                 // Field txt:Lorg/hl7/fhir/utilities/CommaSeparatedStringBuilder;
      27: aload_2
      28: invokevirtual #19                 // Method org/hl7/fhir/utilities/CommaSeparatedStringBuilder.append:(Ljava/lang/String;)V
      31: return

  public void commit(org.hl7.fhir.utilities.xhtml.XhtmlNode);
    Code:
       0: aload_0
       1: getfield      #5                  // Field newResources:Ljava/util/Map;
       4: invokeinterface #23,  1           // InterfaceMethod java/util/Map.size:()I
       9: iconst_1
      10: if_icmpne     192
      13: aload_0
      14: getfield      #8                  // Field assignments:Ljava/util/List;
      17: invokeinterface #24,  1           // InterfaceMethod java/util/List.size:()I
      22: iconst_1
      23: if_icmpne     192
      26: aload_0
      27: getfield      #5                  // Field newResources:Ljava/util/Map;
      30: aload_0
      31: getfield      #8                  // Field assignments:Ljava/util/List;
      34: iconst_0
      35: invokeinterface #25,  2           // InterfaceMethod java/util/List.get:(I)Ljava/lang/Object;
      40: checkcast     #20                 // class org/hl7/fhir/dstu3/utils/StructureMapUtilities$StringPair
      43: invokevirtual #26                 // Method org/hl7/fhir/dstu3/utils/StructureMapUtilities$StringPair.getVar:()Ljava/lang/String;
      46: invokeinterface #27,  2           // InterfaceMethod java/util/Map.containsKey:(Ljava/lang/Object;)Z
      51: ifeq          192
      54: aload_0
      55: getfield      #9                  // Field keyProps:Ljava/util/List;
      58: invokeinterface #24,  1           // InterfaceMethod java/util/List.size:()I
      63: iconst_1
      64: if_icmpne     192
      67: aload_0
      68: getfield      #5                  // Field newResources:Ljava/util/Map;
      71: aload_0
      72: getfield      #9                  // Field keyProps:Ljava/util/List;
      75: iconst_0
      76: invokeinterface #25,  2           // InterfaceMethod java/util/List.get:(I)Ljava/lang/Object;
      81: checkcast     #20                 // class org/hl7/fhir/dstu3/utils/StructureMapUtilities$StringPair
      84: invokevirtual #26                 // Method org/hl7/fhir/dstu3/utils/StructureMapUtilities$StringPair.getVar:()Ljava/lang/String;
      87: invokeinterface #27,  2           // InterfaceMethod java/util/Map.containsKey:(Ljava/lang/Object;)Z
      92: ifeq          192
      95: aload_1
      96: new           #14                 // class java/lang/StringBuilder
      99: dup
     100: invokespecial #15                 // Method java/lang/StringBuilder."<init>":()V
     103: ldc           #16                 // String new
     105: invokevirtual #17                 // Method java/lang/StringBuilder.append:(Ljava/lang/String;)Ljava/lang/StringBuilder;
     108: aload_0
     109: getfield      #8                  // Field assignments:Ljava/util/List;
     112: iconst_0
     113: invokeinterface #25,  2           // InterfaceMethod java/util/List.get:(I)Ljava/lang/Object;
     118: checkcast     #20                 // class org/hl7/fhir/dstu3/utils/StructureMapUtilities$StringPair
     121: invokestatic  #28                 // Method org/hl7/fhir/dstu3/utils/StructureMapUtilities$StringPair.access$1100:(Lorg/hl7/fhir/dstu3/utils/StructureMapUtilities$StringPair;)Ljava/lang/String;
     124: invokevirtual #17                 // Method java/lang/StringBuilder.append:(Ljava/lang/String;)Ljava/lang/StringBuilder;
     127: ldc           #29                 // String  (
     129: invokevirtual #17                 // Method java/lang/StringBuilder.append:(Ljava/lang/String;)Ljava/lang/StringBuilder;
     132: aload_0
     133: getfield      #9                  // Field keyProps:Ljava/util/List;
     136: iconst_0
     137: invokeinterface #25,  2           // InterfaceMethod java/util/List.get:(I)Ljava/lang/Object;
     142: checkcast     #20                 // class org/hl7/fhir/dstu3/utils/StructureMapUtilities$StringPair
     145: invokestatic  #28                 // Method org/hl7/fhir/dstu3/utils/StructureMapUtilities$StringPair.access$1100:(Lorg/hl7/fhir/dstu3/utils/StructureMapUtilities$StringPair;)Ljava/lang/String;
     148: aload_0
     149: getfield      #9                  // Field keyProps:Ljava/util/List;
     152: iconst_0
     153: invokeinterface #25,  2           // InterfaceMethod java/util/List.get:(I)Ljava/lang/Object;
     158: checkcast     #20                 // class org/hl7/fhir/dstu3/utils/StructureMapUtilities$StringPair
     161: invokestatic  #28                 // Method org/hl7/fhir/dstu3/utils/StructureMapUtilities$StringPair.access$1100:(Lorg/hl7/fhir/dstu3/utils/StructureMapUtilities$StringPair;)Ljava/lang/String;
     164: ldc           #30                 // String .
     166: invokevirtual #31                 // Method java/lang/String.indexOf:(Ljava/lang/String;)I
     169: iconst_1
     170: iadd
     171: invokevirtual #32                 // Method java/lang/String.substring:(I)Ljava/lang/String;
     174: invokevirtual #17                 // Method java/lang/StringBuilder.append:(Ljava/lang/String;)Ljava/lang/StringBuilder;
     177: ldc           #33                 // String )
     179: invokevirtual #17                 // Method java/lang/StringBuilder.append:(Ljava/lang/String;)Ljava/lang/StringBuilder;
     182: invokevirtual #18                 // Method java/lang/StringBuilder.toString:()Ljava/lang/String;
     185: invokevirtual #34                 // Method org/hl7/fhir/utilities/xhtml/XhtmlNode.addText:(Ljava/lang/String;)Lorg/hl7/fhir/utilities/xhtml/XhtmlNode;
     188: pop
     189: goto          312
     192: aload_0
     193: getfield      #5                  // Field newResources:Ljava/util/Map;
     196: invokeinterface #23,  1           // InterfaceMethod java/util/Map.size:()I
     201: iconst_1
     202: if_icmpne     300
     205: aload_0
     206: getfield      #8                  // Field assignments:Ljava/util/List;
     209: invokeinterface #24,  1           // InterfaceMethod java/util/List.size:()I
     214: iconst_1
     215: if_icmpne     300
     218: aload_0
     219: getfield      #5                  // Field newResources:Ljava/util/Map;
     222: aload_0
     223: getfield      #8                  // Field assignments:Ljava/util/List;
     226: iconst_0
     227: invokeinterface #25,  2           // InterfaceMethod java/util/List.get:(I)Ljava/lang/Object;
     232: checkcast     #20                 // class org/hl7/fhir/dstu3/utils/StructureMapUtilities$StringPair
     235: invokevirtual #26                 // Method org/hl7/fhir/dstu3/utils/StructureMapUtilities$StringPair.getVar:()Ljava/lang/String;
     238: invokeinterface #27,  2           // InterfaceMethod java/util/Map.containsKey:(Ljava/lang/Object;)Z
     243: ifeq          300
     246: aload_0
     247: getfield      #9                  // Field keyProps:Ljava/util/List;
     250: invokeinterface #24,  1           // InterfaceMethod java/util/List.size:()I
     255: ifne          300
     258: aload_1
     259: new           #14                 // class java/lang/StringBuilder
     262: dup
     263: invokespecial #15                 // Method java/lang/StringBuilder."<init>":()V
     266: ldc           #16                 // String new
     268: invokevirtual #17                 // Method java/lang/StringBuilder.append:(Ljava/lang/String;)Ljava/lang/StringBuilder;
     271: aload_0
     272: getfield      #8                  // Field assignments:Ljava/util/List;
     275: iconst_0
     276: invokeinterface #25,  2           // InterfaceMethod java/util/List.get:(I)Ljava/lang/Object;
     281: checkcast     #20                 // class org/hl7/fhir/dstu3/utils/StructureMapUtilities$StringPair
     284: invokestatic  #28                 // Method org/hl7/fhir/dstu3/utils/StructureMapUtilities$StringPair.access$1100:(Lorg/hl7/fhir/dstu3/utils/StructureMapUtilities$StringPair;)Ljava/lang/String;
     287: invokevirtual #17                 // Method java/lang/StringBuilder.append:(Ljava/lang/String;)Ljava/lang/StringBuilder;
     290: invokevirtual #18                 // Method java/lang/StringBuilder.toString:()Ljava/lang/String;
     293: invokevirtual #34                 // Method org/hl7/fhir/utilities/xhtml/XhtmlNode.addText:(Ljava/lang/String;)Lorg/hl7/fhir/utilities/xhtml/XhtmlNode;
     296: pop
     297: goto          312
     300: aload_1
     301: aload_0
     302: getfield      #12                 // Field txt:Lorg/hl7/fhir/utilities/CommaSeparatedStringBuilder;
     305: invokevirtual #35                 // Method org/hl7/fhir/utilities/CommaSeparatedStringBuilder.toString:()Ljava/lang/String;
     308: invokevirtual #34                 // Method org/hl7/fhir/utilities/xhtml/XhtmlNode.addText:(Ljava/lang/String;)Lorg/hl7/fhir/utilities/xhtml/XhtmlNode;
     311: pop
     312: return
}
