Compiled from "FilterExprImpl.java"
final class org.leo.aws.ddb.utils.FilterExprImpl$GroupImpl implements org.leo.aws.ddb.utils.Group {
  private org.leo.aws.ddb.utils.FilterExprImpl$AbstractOperator operator;

  private final org.leo.aws.ddb.utils.FilterExprImpl filterExpr;

  private final org.leo.aws.ddb.utils.Expr expr;

  private org.leo.aws.ddb.utils.FilterExprImpl$GroupImpl(org.leo.aws.ddb.utils.FilterExprImpl, org.leo.aws.ddb.utils.Expr);
    Code:
       0: aload_0
       1: invokespecial #17                 // Method java/lang/Object."<init>":()V
       4: aload_0
       5: aload_1
       6: putfield      #20                 // Field filterExpr:Lorg/leo/aws/ddb/utils/FilterExprImpl;
       9: aload_0
      10: aload_2
      11: putfield      #22                 // Field expr:Lorg/leo/aws/ddb/utils/Expr;
      14: return

  public org.leo.aws.ddb.utils.Operator and();
    Code:
       0: aload_0
       1: new           #30                 // class org/leo/aws/ddb/utils/FilterExprImpl$And
       4: dup
       5: aload_0
       6: getfield      #20                 // Field filterExpr:Lorg/leo/aws/ddb/utils/FilterExprImpl;
       9: invokespecial #32                 // Method org/leo/aws/ddb/utils/FilterExprImpl$And."<init>":(Lorg/leo/aws/ddb/utils/FilterExprImpl;)V
      12: dup_x1
      13: putfield      #35                 // Field operator:Lorg/leo/aws/ddb/utils/FilterExprImpl$AbstractOperator;
      16: areturn

  public org.leo.aws.ddb.utils.Operator or();
    Code:
       0: aload_0
       1: new           #38                 // class org/leo/aws/ddb/utils/FilterExprImpl$Or
       4: dup
       5: aload_0
       6: getfield      #20                 // Field filterExpr:Lorg/leo/aws/ddb/utils/FilterExprImpl;
       9: invokespecial #40                 // Method org/leo/aws/ddb/utils/FilterExprImpl$Or."<init>":(Lorg/leo/aws/ddb/utils/FilterExprImpl;)V
      12: dup_x1
      13: putfield      #35                 // Field operator:Lorg/leo/aws/ddb/utils/FilterExprImpl$AbstractOperator;
      16: areturn

  public java.lang.String expression();
    Code:
       0: aload_0
       1: getfield      #35                 // Field operator:Lorg/leo/aws/ddb/utils/FilterExprImpl$AbstractOperator;
       4: ifnull        41
       7: ldc           #43                 // String ({0}) {1}
       9: iconst_2
      10: anewarray     #3                  // class java/lang/Object
      13: dup
      14: iconst_0
      15: aload_0
      16: getfield      #22                 // Field expr:Lorg/leo/aws/ddb/utils/Expr;
      19: invokeinterface #45,  1           // InterfaceMethod org/leo/aws/ddb/utils/Expr.expression:()Ljava/lang/String;
      24: aastore
      25: dup
      26: iconst_1
      27: aload_0
      28: getfield      #35                 // Field operator:Lorg/leo/aws/ddb/utils/FilterExprImpl$AbstractOperator;
      31: invokevirtual #49                 // Method org/leo/aws/ddb/utils/FilterExprImpl$AbstractOperator.expression:()Ljava/lang/String;
      34: aastore
      35: invokestatic  #52                 // Method java/text/MessageFormat.format:(Ljava/lang/String;[Ljava/lang/Object;)Ljava/lang/String;
      38: goto          62
      41: ldc           #58                 // String ({0})
      43: iconst_1
      44: anewarray     #3                  // class java/lang/Object
      47: dup
      48: iconst_0
      49: aload_0
      50: getfield      #22                 // Field expr:Lorg/leo/aws/ddb/utils/Expr;
      53: invokeinterface #45,  1           // InterfaceMethod org/leo/aws/ddb/utils/Expr.expression:()Ljava/lang/String;
      58: aastore
      59: invokestatic  #52                 // Method java/text/MessageFormat.format:(Ljava/lang/String;[Ljava/lang/Object;)Ljava/lang/String;
      62: areturn

  public java.util.Map<java.lang.String, java.lang.String> attributeNameMap();
    Code:
       0: invokestatic  #67                 // Method com/google/common/collect/ImmutableMap.builder:()Lcom/google/common/collect/ImmutableMap$Builder;
       3: aload_0
       4: getfield      #22                 // Field expr:Lorg/leo/aws/ddb/utils/Expr;
       7: invokeinterface #73,  1           // InterfaceMethod org/leo/aws/ddb/utils/Expr.attributeNameMap:()Ljava/util/Map;
      12: invokevirtual #75                 // Method com/google/common/collect/ImmutableMap$Builder.putAll:(Ljava/util/Map;)Lcom/google/common/collect/ImmutableMap$Builder;
      15: astore_1
      16: aload_0
      17: getfield      #35                 // Field operator:Lorg/leo/aws/ddb/utils/FilterExprImpl$AbstractOperator;
      20: ifnull        35
      23: aload_1
      24: aload_0
      25: getfield      #35                 // Field operator:Lorg/leo/aws/ddb/utils/FilterExprImpl$AbstractOperator;
      28: invokevirtual #81                 // Method org/leo/aws/ddb/utils/FilterExprImpl$AbstractOperator.attributeNameMap:()Ljava/util/Map;
      31: invokevirtual #75                 // Method com/google/common/collect/ImmutableMap$Builder.putAll:(Ljava/util/Map;)Lcom/google/common/collect/ImmutableMap$Builder;
      34: pop
      35: aload_1
      36: invokevirtual #82                 // Method com/google/common/collect/ImmutableMap$Builder.build:()Lcom/google/common/collect/ImmutableMap;
      39: areturn

  public java.util.Map<java.lang.String, software.amazon.awssdk.services.dynamodb.model.AttributeValue> attributeValueMap();
    Code:
       0: invokestatic  #67                 // Method com/google/common/collect/ImmutableMap.builder:()Lcom/google/common/collect/ImmutableMap$Builder;
       3: aload_0
       4: getfield      #22                 // Field expr:Lorg/leo/aws/ddb/utils/Expr;
       7: invokeinterface #91,  1           // InterfaceMethod org/leo/aws/ddb/utils/Expr.attributeValueMap:()Ljava/util/Map;
      12: invokevirtual #75                 // Method com/google/common/collect/ImmutableMap$Builder.putAll:(Ljava/util/Map;)Lcom/google/common/collect/ImmutableMap$Builder;
      15: astore_1
      16: aload_0
      17: getfield      #35                 // Field operator:Lorg/leo/aws/ddb/utils/FilterExprImpl$AbstractOperator;
      20: ifnull        35
      23: aload_1
      24: aload_0
      25: getfield      #35                 // Field operator:Lorg/leo/aws/ddb/utils/FilterExprImpl$AbstractOperator;
      28: invokevirtual #93                 // Method org/leo/aws/ddb/utils/FilterExprImpl$AbstractOperator.attributeValueMap:()Ljava/util/Map;
      31: invokevirtual #75                 // Method com/google/common/collect/ImmutableMap$Builder.putAll:(Ljava/util/Map;)Lcom/google/common/collect/ImmutableMap$Builder;
      34: pop
      35: aload_1
      36: invokevirtual #82                 // Method com/google/common/collect/ImmutableMap$Builder.build:()Lcom/google/common/collect/ImmutableMap;
      39: areturn

  public org.leo.aws.ddb.utils.Expr buildFilterExpression();
    Code:
       0: aload_0
       1: getfield      #35                 // Field operator:Lorg/leo/aws/ddb/utils/FilterExprImpl$AbstractOperator;
       4: ifnull        17
       7: new           #97                 // class org/leo/aws/ddb/utils/exceptions/UtilsException
      10: dup
      11: ldc           #99                 // String Invalid expression.
      13: invokespecial #101                // Method org/leo/aws/ddb/utils/exceptions/UtilsException."<init>":(Ljava/lang/String;)V
      16: athrow
      17: new           #104                // class org/leo/aws/ddb/utils/FilterExprImpl$ExprImpl
      20: dup
      21: aload_0
      22: getfield      #20                 // Field filterExpr:Lorg/leo/aws/ddb/utils/FilterExprImpl;
      25: invokespecial #106                // Method org/leo/aws/ddb/utils/FilterExprImpl$ExprImpl."<init>":(Lorg/leo/aws/ddb/utils/FilterExprImpl;)V
      28: astore_1
      29: aload_0
      30: invokevirtual #107                // Method java/lang/Object.getClass:()Ljava/lang/Class;
      33: invokevirtual #111                // Method java/lang/Class.getClassLoader:()Ljava/lang/ClassLoader;
      36: iconst_1
      37: anewarray     #112                // class java/lang/Class
      40: dup
      41: iconst_0
      42: ldc           #46                 // class org/leo/aws/ddb/utils/Expr
      44: aastore
      45: aload_1
      46: invokedynamic #117,  0            // InvokeDynamic #0:invoke:(Lorg/leo/aws/ddb/utils/Expr;)Ljava/lang/reflect/InvocationHandler;
      51: invokestatic  #121                // Method java/lang/reflect/Proxy.newProxyInstance:(Ljava/lang/ClassLoader;[Ljava/lang/Class;Ljava/lang/reflect/InvocationHandler;)Ljava/lang/Object;
      54: checkcast     #46                 // class org/leo/aws/ddb/utils/Expr
      57: areturn

  private static java.lang.Object lambda$0(org.leo.aws.ddb.utils.Expr, java.lang.Object, java.lang.reflect.Method, java.lang.Object[]) throws java.lang.Throwable;
    Code:
       0: aload_2
       1: aload_0
       2: aload_3
       3: invokevirtual #132                // Method java/lang/reflect/Method.invoke:(Ljava/lang/Object;[Ljava/lang/Object;)Ljava/lang/Object;
       6: areturn
}
