Compiled from "DescriptorUtils.kt"
final class kotlin.reflect.jvm.internal.impl.resolve.descriptorUtil.DescriptorUtilsKt$declaresOrInheritsDefaultValue$1<N> implements kotlin.reflect.jvm.internal.impl.utils.DFS$Neighbors<N> {
  public static final kotlin.reflect.jvm.internal.impl.resolve.descriptorUtil.DescriptorUtilsKt$declaresOrInheritsDefaultValue$1 INSTANCE;

  public java.lang.Iterable getNeighbors(java.lang.Object);
    Code:
       0: aload_0
       1: aload_1
       2: checkcast     #10                 // class kotlin/reflect/jvm/internal/impl/descriptors/ValueParameterDescriptor
       5: invokevirtual #20                 // Method getNeighbors:(Lkotlin/reflect/jvm/internal/impl/descriptors/ValueParameterDescriptor;)Ljava/util/List;
       8: checkcast     #2                  // class java/lang/Iterable
      11: areturn

  public final java.util.List<kotlin.reflect.jvm.internal.impl.descriptors.ValueParameterDescriptor> getNeighbors(kotlin.reflect.jvm.internal.impl.descriptors.ValueParameterDescriptor);
    Code:
       0: aload_1
       1: dup
       2: ldc           #1                  // String current
       4: invokestatic  #18                 // Method kotlin/jvm/internal/Intrinsics.checkExpressionValueIsNotNull:(Ljava/lang/Object;Ljava/lang/String;)V
       7: invokeinterface #26,  1           // InterfaceMethod kotlin/reflect/jvm/internal/impl/descriptors/ValueParameterDescriptor.getOverriddenDescriptors:()Ljava/util/Collection;
      12: checkcast     #2                  // class java/lang/Iterable
      15: astore_2
      16: aload_2
      17: astore_3
      18: new           #4                  // class java/util/ArrayList
      21: dup
      22: aload_2
      23: bipush        10
      25: invokestatic  #17                 // Method kotlin/collections/CollectionsKt.collectionSizeOrDefault:(Ljava/lang/Iterable;I)I
      28: invokespecial #16                 // Method java/util/ArrayList."<init>":(I)V
      31: checkcast     #5                  // class java/util/Collection
      34: astore        4
      36: aload_3
      37: invokeinterface #21,  1           // InterfaceMethod java/lang/Iterable.iterator:()Ljava/util/Iterator;
      42: astore        5
      44: aload         5
      46: invokeinterface #23,  1           // InterfaceMethod java/util/Iterator.hasNext:()Z
      51: ifeq          96
      54: aload         5
      56: invokeinterface #24,  1           // InterfaceMethod java/util/Iterator.next:()Ljava/lang/Object;
      61: astore        6
      63: aload         4
      65: aload         6
      67: checkcast     #10                 // class kotlin/reflect/jvm/internal/impl/descriptors/ValueParameterDescriptor
      70: astore        7
      72: astore        11
      74: aload         7
      76: invokeinterface #25,  1           // InterfaceMethod kotlin/reflect/jvm/internal/impl/descriptors/ValueParameterDescriptor.getOriginal:()Lkotlin/reflect/jvm/internal/impl/descriptors/ValueParameterDescriptor;
      81: astore        12
      83: aload         11
      85: aload         12
      87: invokeinterface #22,  2           // InterfaceMethod java/util/Collection.add:(Ljava/lang/Object;)Z
      92: pop
      93: goto          44
      96: aload         4
      98: checkcast     #7                  // class java/util/List
     101: areturn

  kotlin.reflect.jvm.internal.impl.resolve.descriptorUtil.DescriptorUtilsKt$declaresOrInheritsDefaultValue$1();
    Code:
       0: aload_0
       1: invokespecial #15                 // Method java/lang/Object."<init>":()V
       4: return

  static {};
    Code:
       0: new           #12                 // class kotlin/reflect/jvm/internal/impl/resolve/descriptorUtil/DescriptorUtilsKt$declaresOrInheritsDefaultValue$1
       3: dup
       4: invokespecial #19                 // Method "<init>":()V
       7: putstatic     #14                 // Field INSTANCE:Lkotlin/reflect/jvm/internal/impl/resolve/descriptorUtil/DescriptorUtilsKt$declaresOrInheritsDefaultValue$1;
      10: return
}
