Compiled from "MockServerWebExchange.java"
public final class org.springframework.mock.web.server.MockServerWebExchange extends org.springframework.web.server.adapter.DefaultServerWebExchange {
  private org.springframework.mock.web.server.MockServerWebExchange(org.springframework.mock.http.server.reactive.MockServerHttpRequest);
    Code:
       0: aload_0
       1: aload_1
       2: new           #1                  // class org/springframework/mock/http/server/reactive/MockServerHttpResponse
       5: dup
       6: invokespecial #2                  // Method org/springframework/mock/http/server/reactive/MockServerHttpResponse."<init>":()V
       9: new           #3                  // class org/springframework/web/server/session/DefaultWebSessionManager
      12: dup
      13: invokespecial #4                  // Method org/springframework/web/server/session/DefaultWebSessionManager."<init>":()V
      16: invokestatic  #5                  // InterfaceMethod org/springframework/http/codec/ServerCodecConfigurer.create:()Lorg/springframework/http/codec/ServerCodecConfigurer;
      19: new           #6                  // class org/springframework/web/server/i18n/AcceptHeaderLocaleContextResolver
      22: dup
      23: invokespecial #7                  // Method org/springframework/web/server/i18n/AcceptHeaderLocaleContextResolver."<init>":()V
      26: invokespecial #8                  // Method org/springframework/web/server/adapter/DefaultServerWebExchange."<init>":(Lorg/springframework/http/server/reactive/ServerHttpRequest;Lorg/springframework/http/server/reactive/ServerHttpResponse;Lorg/springframework/web/server/session/WebSessionManager;Lorg/springframework/http/codec/ServerCodecConfigurer;Lorg/springframework/web/server/i18n/LocaleContextResolver;)V
      29: return

  public org.springframework.mock.http.server.reactive.MockServerHttpResponse getResponse();
    Code:
       0: aload_0
       1: invokespecial #9                  // Method org/springframework/web/server/adapter/DefaultServerWebExchange.getResponse:()Lorg/springframework/http/server/reactive/ServerHttpResponse;
       4: checkcast     #1                  // class org/springframework/mock/http/server/reactive/MockServerHttpResponse
       7: areturn

  public static org.springframework.mock.web.server.MockServerWebExchange from(org.springframework.mock.http.server.reactive.MockServerHttpRequest);
    Code:
       0: new           #10                 // class org/springframework/mock/web/server/MockServerWebExchange
       3: dup
       4: aload_0
       5: invokespecial #11                 // Method "<init>":(Lorg/springframework/mock/http/server/reactive/MockServerHttpRequest;)V
       8: areturn

  public static org.springframework.mock.web.server.MockServerWebExchange from(org.springframework.mock.http.server.reactive.MockServerHttpRequest$BaseBuilder<?>);
    Code:
       0: new           #10                 // class org/springframework/mock/web/server/MockServerWebExchange
       3: dup
       4: aload_0
       5: invokeinterface #12,  1           // InterfaceMethod org/springframework/mock/http/server/reactive/MockServerHttpRequest$BaseBuilder.build:()Lorg/springframework/mock/http/server/reactive/MockServerHttpRequest;
      10: invokespecial #11                 // Method "<init>":(Lorg/springframework/mock/http/server/reactive/MockServerHttpRequest;)V
      13: areturn

  public org.springframework.http.server.reactive.ServerHttpResponse getResponse();
    Code:
       0: aload_0
       1: invokevirtual #13                 // Method getResponse:()Lorg/springframework/mock/http/server/reactive/MockServerHttpResponse;
       4: areturn
}
