Compiled from "HashCodeAndEqualsPlugin.java"
public class org.modelmapper.internal.bytebuddy.build.HashCodeAndEqualsPlugin implements org.modelmapper.internal.bytebuddy.build.Plugin {
  public org.modelmapper.internal.bytebuddy.build.HashCodeAndEqualsPlugin();
    Code:
       0: aload_0
       1: invokespecial #56                 // Method java/lang/Object."<init>":()V
       4: return

  public boolean matches(org.modelmapper.internal.bytebuddy.description.type.TypeDescription);
    Code:
       0: aload_1
       1: invokeinterface #66,  1           // InterfaceMethod org/modelmapper/internal/bytebuddy/description/type/TypeDescription.getDeclaredAnnotations:()Lorg/modelmapper/internal/bytebuddy/description/annotation/AnnotationList;
       6: ldc           #18                 // class org/modelmapper/internal/bytebuddy/build/HashCodeAndEqualsPlugin$Enhance
       8: invokeinterface #72,  2           // InterfaceMethod org/modelmapper/internal/bytebuddy/description/annotation/AnnotationList.isAnnotationPresent:(Ljava/lang/Class;)Z
      13: ireturn

  public org.modelmapper.internal.bytebuddy.dynamic.DynamicType$Builder<?> apply(org.modelmapper.internal.bytebuddy.dynamic.DynamicType$Builder<?>, org.modelmapper.internal.bytebuddy.description.type.TypeDescription);
    Code:
       0: aload_2
       1: invokeinterface #66,  1           // InterfaceMethod org/modelmapper/internal/bytebuddy/description/type/TypeDescription.getDeclaredAnnotations:()Lorg/modelmapper/internal/bytebuddy/description/annotation/AnnotationList;
       6: ldc           #18                 // class org/modelmapper/internal/bytebuddy/build/HashCodeAndEqualsPlugin$Enhance
       8: invokeinterface #80,  2           // InterfaceMethod org/modelmapper/internal/bytebuddy/description/annotation/AnnotationList.ofType:(Ljava/lang/Class;)Lorg/modelmapper/internal/bytebuddy/description/annotation/AnnotationDescription$Loadable;
      13: invokeinterface #84,  1           // InterfaceMethod org/modelmapper/internal/bytebuddy/description/annotation/AnnotationDescription$Loadable.loadSilent:()Ljava/lang/annotation/Annotation;
      18: checkcast     #18                 // class org/modelmapper/internal/bytebuddy/build/HashCodeAndEqualsPlugin$Enhance
      21: astore_3
      22: aload_2
      23: invokeinterface #88,  1           // InterfaceMethod org/modelmapper/internal/bytebuddy/description/type/TypeDescription.getDeclaredMethods:()Lorg/modelmapper/internal/bytebuddy/description/method/MethodList;
      28: invokestatic  #94                 // Method org/modelmapper/internal/bytebuddy/matcher/ElementMatchers.isHashCode:()Lorg/modelmapper/internal/bytebuddy/matcher/ElementMatcher$Junction;
      31: invokeinterface #100,  2          // InterfaceMethod org/modelmapper/internal/bytebuddy/description/method/MethodList.filter:(Lorg/modelmapper/internal/bytebuddy/matcher/ElementMatcher;)Lorg/modelmapper/internal/bytebuddy/matcher/FilterableList;
      36: checkcast     #96                 // class org/modelmapper/internal/bytebuddy/description/method/MethodList
      39: invokeinterface #104,  1          // InterfaceMethod org/modelmapper/internal/bytebuddy/description/method/MethodList.isEmpty:()Z
      44: ifeq          123
      47: aload_1
      48: invokestatic  #94                 // Method org/modelmapper/internal/bytebuddy/matcher/ElementMatchers.isHashCode:()Lorg/modelmapper/internal/bytebuddy/matcher/ElementMatcher$Junction;
      51: invokeinterface #108,  2          // InterfaceMethod org/modelmapper/internal/bytebuddy/dynamic/DynamicType$Builder.method:(Lorg/modelmapper/internal/bytebuddy/matcher/ElementMatcher;)Lorg/modelmapper/internal/bytebuddy/dynamic/DynamicType$Builder$MethodDefinition$ImplementationDefinition;
      56: aload_3
      57: invokeinterface #112,  1          // InterfaceMethod org/modelmapper/internal/bytebuddy/build/HashCodeAndEqualsPlugin$Enhance.invokeSuper:()Lorg/modelmapper/internal/bytebuddy/build/HashCodeAndEqualsPlugin$Enhance$InvokeSuper;
      62: aload_2
      63: invokevirtual #116                // Method org/modelmapper/internal/bytebuddy/build/HashCodeAndEqualsPlugin$Enhance$InvokeSuper.hashCodeMethod:(Lorg/modelmapper/internal/bytebuddy/description/type/TypeDescription;)Lorg/modelmapper/internal/bytebuddy/implementation/HashCodeMethod;
      66: aload_3
      67: invokeinterface #119,  1          // InterfaceMethod org/modelmapper/internal/bytebuddy/build/HashCodeAndEqualsPlugin$Enhance.includeSyntheticFields:()Z
      72: ifeq          81
      75: invokestatic  #122                // Method org/modelmapper/internal/bytebuddy/matcher/ElementMatchers.none:()Lorg/modelmapper/internal/bytebuddy/matcher/ElementMatcher$Junction;
      78: goto          84
      81: invokestatic  #127                // Method org/modelmapper/internal/bytebuddy/matcher/ElementMatchers.isSynthetic:()Lorg/modelmapper/internal/bytebuddy/matcher/ElementMatcher$Junction;
      84: invokevirtual #131                // Method org/modelmapper/internal/bytebuddy/implementation/HashCodeMethod.withIgnoredFields:(Lorg/modelmapper/internal/bytebuddy/matcher/ElementMatcher;)Lorg/modelmapper/internal/bytebuddy/implementation/HashCodeMethod;
      87: new           #12                 // class org/modelmapper/internal/bytebuddy/build/HashCodeAndEqualsPlugin$ValueMatcher
      90: dup
      91: getstatic     #135                // Field org/modelmapper/internal/bytebuddy/build/HashCodeAndEqualsPlugin$ValueHandling$Sort.IGNORE:Lorg/modelmapper/internal/bytebuddy/build/HashCodeAndEqualsPlugin$ValueHandling$Sort;
      94: invokespecial #138                // Method org/modelmapper/internal/bytebuddy/build/HashCodeAndEqualsPlugin$ValueMatcher."<init>":(Lorg/modelmapper/internal/bytebuddy/build/HashCodeAndEqualsPlugin$ValueHandling$Sort;)V
      97: invokevirtual #131                // Method org/modelmapper/internal/bytebuddy/implementation/HashCodeMethod.withIgnoredFields:(Lorg/modelmapper/internal/bytebuddy/matcher/ElementMatcher;)Lorg/modelmapper/internal/bytebuddy/implementation/HashCodeMethod;
     100: aload_0
     101: new           #12                 // class org/modelmapper/internal/bytebuddy/build/HashCodeAndEqualsPlugin$ValueMatcher
     104: dup
     105: getstatic     #141                // Field org/modelmapper/internal/bytebuddy/build/HashCodeAndEqualsPlugin$ValueHandling$Sort.REVERSE_NULLABILITY:Lorg/modelmapper/internal/bytebuddy/build/HashCodeAndEqualsPlugin$ValueHandling$Sort;
     108: invokespecial #138                // Method org/modelmapper/internal/bytebuddy/build/HashCodeAndEqualsPlugin$ValueMatcher."<init>":(Lorg/modelmapper/internal/bytebuddy/build/HashCodeAndEqualsPlugin$ValueHandling$Sort;)V
     111: invokevirtual #145                // Method nonNullable:(Lorg/modelmapper/internal/bytebuddy/matcher/ElementMatcher;)Lorg/modelmapper/internal/bytebuddy/matcher/ElementMatcher;
     114: invokevirtual #148                // Method org/modelmapper/internal/bytebuddy/implementation/HashCodeMethod.withNonNullableFields:(Lorg/modelmapper/internal/bytebuddy/matcher/ElementMatcher;)Lorg/modelmapper/internal/bytebuddy/implementation/HashCodeMethod;
     117: invokeinterface #152,  2          // InterfaceMethod org/modelmapper/internal/bytebuddy/dynamic/DynamicType$Builder$MethodDefinition$ImplementationDefinition.intercept:(Lorg/modelmapper/internal/bytebuddy/implementation/Implementation;)Lorg/modelmapper/internal/bytebuddy/dynamic/DynamicType$Builder$MethodDefinition$ReceiverTypeDefinition;
     122: astore_1
     123: aload_2
     124: invokeinterface #88,  1           // InterfaceMethod org/modelmapper/internal/bytebuddy/description/type/TypeDescription.getDeclaredMethods:()Lorg/modelmapper/internal/bytebuddy/description/method/MethodList;
     129: invokestatic  #155                // Method org/modelmapper/internal/bytebuddy/matcher/ElementMatchers.isEquals:()Lorg/modelmapper/internal/bytebuddy/matcher/ElementMatcher$Junction;
     132: invokeinterface #100,  2          // InterfaceMethod org/modelmapper/internal/bytebuddy/description/method/MethodList.filter:(Lorg/modelmapper/internal/bytebuddy/matcher/ElementMatcher;)Lorg/modelmapper/internal/bytebuddy/matcher/FilterableList;
     137: checkcast     #96                 // class org/modelmapper/internal/bytebuddy/description/method/MethodList
     140: invokeinterface #104,  1          // InterfaceMethod org/modelmapper/internal/bytebuddy/description/method/MethodList.isEmpty:()Z
     145: ifeq          245
     148: aload_3
     149: invokeinterface #112,  1          // InterfaceMethod org/modelmapper/internal/bytebuddy/build/HashCodeAndEqualsPlugin$Enhance.invokeSuper:()Lorg/modelmapper/internal/bytebuddy/build/HashCodeAndEqualsPlugin$Enhance$InvokeSuper;
     154: aload_2
     155: invokevirtual #159                // Method org/modelmapper/internal/bytebuddy/build/HashCodeAndEqualsPlugin$Enhance$InvokeSuper.equalsMethod:(Lorg/modelmapper/internal/bytebuddy/description/type/TypeDescription;)Lorg/modelmapper/internal/bytebuddy/implementation/EqualsMethod;
     158: aload_3
     159: invokeinterface #119,  1          // InterfaceMethod org/modelmapper/internal/bytebuddy/build/HashCodeAndEqualsPlugin$Enhance.includeSyntheticFields:()Z
     164: ifeq          173
     167: invokestatic  #122                // Method org/modelmapper/internal/bytebuddy/matcher/ElementMatchers.none:()Lorg/modelmapper/internal/bytebuddy/matcher/ElementMatcher$Junction;
     170: goto          176
     173: invokestatic  #127                // Method org/modelmapper/internal/bytebuddy/matcher/ElementMatchers.isSynthetic:()Lorg/modelmapper/internal/bytebuddy/matcher/ElementMatcher$Junction;
     176: invokevirtual #164                // Method org/modelmapper/internal/bytebuddy/implementation/EqualsMethod.withIgnoredFields:(Lorg/modelmapper/internal/bytebuddy/matcher/ElementMatcher;)Lorg/modelmapper/internal/bytebuddy/implementation/EqualsMethod;
     179: new           #12                 // class org/modelmapper/internal/bytebuddy/build/HashCodeAndEqualsPlugin$ValueMatcher
     182: dup
     183: getstatic     #135                // Field org/modelmapper/internal/bytebuddy/build/HashCodeAndEqualsPlugin$ValueHandling$Sort.IGNORE:Lorg/modelmapper/internal/bytebuddy/build/HashCodeAndEqualsPlugin$ValueHandling$Sort;
     186: invokespecial #138                // Method org/modelmapper/internal/bytebuddy/build/HashCodeAndEqualsPlugin$ValueMatcher."<init>":(Lorg/modelmapper/internal/bytebuddy/build/HashCodeAndEqualsPlugin$ValueHandling$Sort;)V
     189: invokevirtual #164                // Method org/modelmapper/internal/bytebuddy/implementation/EqualsMethod.withIgnoredFields:(Lorg/modelmapper/internal/bytebuddy/matcher/ElementMatcher;)Lorg/modelmapper/internal/bytebuddy/implementation/EqualsMethod;
     192: aload_0
     193: new           #12                 // class org/modelmapper/internal/bytebuddy/build/HashCodeAndEqualsPlugin$ValueMatcher
     196: dup
     197: getstatic     #141                // Field org/modelmapper/internal/bytebuddy/build/HashCodeAndEqualsPlugin$ValueHandling$Sort.REVERSE_NULLABILITY:Lorg/modelmapper/internal/bytebuddy/build/HashCodeAndEqualsPlugin$ValueHandling$Sort;
     200: invokespecial #138                // Method org/modelmapper/internal/bytebuddy/build/HashCodeAndEqualsPlugin$ValueMatcher."<init>":(Lorg/modelmapper/internal/bytebuddy/build/HashCodeAndEqualsPlugin$ValueHandling$Sort;)V
     203: invokevirtual #145                // Method nonNullable:(Lorg/modelmapper/internal/bytebuddy/matcher/ElementMatcher;)Lorg/modelmapper/internal/bytebuddy/matcher/ElementMatcher;
     206: invokevirtual #166                // Method org/modelmapper/internal/bytebuddy/implementation/EqualsMethod.withNonNullableFields:(Lorg/modelmapper/internal/bytebuddy/matcher/ElementMatcher;)Lorg/modelmapper/internal/bytebuddy/implementation/EqualsMethod;
     209: astore        4
     211: aload_1
     212: invokestatic  #155                // Method org/modelmapper/internal/bytebuddy/matcher/ElementMatchers.isEquals:()Lorg/modelmapper/internal/bytebuddy/matcher/ElementMatcher$Junction;
     215: invokeinterface #108,  2          // InterfaceMethod org/modelmapper/internal/bytebuddy/dynamic/DynamicType$Builder.method:(Lorg/modelmapper/internal/bytebuddy/matcher/ElementMatcher;)Lorg/modelmapper/internal/bytebuddy/dynamic/DynamicType$Builder$MethodDefinition$ImplementationDefinition;
     220: aload_3
     221: invokeinterface #169,  1          // InterfaceMethod org/modelmapper/internal/bytebuddy/build/HashCodeAndEqualsPlugin$Enhance.permitSubclassEquality:()Z
     226: ifeq          237
     229: aload         4
     231: invokevirtual #173                // Method org/modelmapper/internal/bytebuddy/implementation/EqualsMethod.withSubclassEquality:()Lorg/modelmapper/internal/bytebuddy/implementation/Implementation;
     234: goto          239
     237: aload         4
     239: invokeinterface #152,  2          // InterfaceMethod org/modelmapper/internal/bytebuddy/dynamic/DynamicType$Builder$MethodDefinition$ImplementationDefinition.intercept:(Lorg/modelmapper/internal/bytebuddy/implementation/Implementation;)Lorg/modelmapper/internal/bytebuddy/dynamic/DynamicType$Builder$MethodDefinition$ReceiverTypeDefinition;
     244: astore_1
     245: aload_1
     246: areturn

  protected org.modelmapper.internal.bytebuddy.matcher.ElementMatcher<org.modelmapper.internal.bytebuddy.description.field.FieldDescription> nonNullable(org.modelmapper.internal.bytebuddy.matcher.ElementMatcher<org.modelmapper.internal.bytebuddy.description.field.FieldDescription>);
    Code:
       0: aload_1
       1: areturn

  public boolean matches(java.lang.Object);
    Code:
       0: aload_0
       1: aload_1
       2: checkcast     #62                 // class org/modelmapper/internal/bytebuddy/description/type/TypeDescription
       5: invokevirtual #187                // Method matches:(Lorg/modelmapper/internal/bytebuddy/description/type/TypeDescription;)Z
       8: ireturn

  public boolean equals(java.lang.Object);
    Code:
       0: aload_0
       1: aload_1
       2: if_acmpne     7
       5: iconst_1
       6: ireturn
       7: aload_1
       8: ifnonnull     13
      11: iconst_0
      12: ireturn
      13: aload_0
      14: invokevirtual #192                // Method java/lang/Object.getClass:()Ljava/lang/Class;
      17: aload_1
      18: invokevirtual #192                // Method java/lang/Object.getClass:()Ljava/lang/Class;
      21: if_acmpeq     26
      24: iconst_0
      25: ireturn
      26: iconst_1
      27: ireturn

  public int hashCode();
    Code:
       0: bipush        17
       2: ireturn
}
