Compiled from "EclRecordParser.java"
public class org.hpccsystems.ws.client.antlr.EclRecordParser$Eclfield_recrefContext extends org.antlr.v4.runtime.ParserRuleContext {
  public org.antlr.v4.runtime.tree.TerminalNode OPAREN();
    Code:
       0: aload_0
       1: bipush        16
       3: iconst_0
       4: invokevirtual #2                  // Method getToken:(II)Lorg/antlr/v4/runtime/tree/TerminalNode;
       7: areturn

  public org.antlr.v4.runtime.tree.TerminalNode TOKEN();
    Code:
       0: aload_0
       1: bipush        31
       3: iconst_0
       4: invokevirtual #2                  // Method getToken:(II)Lorg/antlr/v4/runtime/tree/TerminalNode;
       7: areturn

  public org.antlr.v4.runtime.tree.TerminalNode CPAREN();
    Code:
       0: aload_0
       1: bipush        17
       3: iconst_0
       4: invokevirtual #2                  // Method getToken:(II)Lorg/antlr/v4/runtime/tree/TerminalNode;
       7: areturn

  public org.hpccsystems.ws.client.antlr.EclRecordParser$Eclfield_recrefContext(org.antlr.v4.runtime.ParserRuleContext, int);
    Code:
       0: aload_0
       1: aload_1
       2: iload_2
       3: invokespecial #3                  // Method org/antlr/v4/runtime/ParserRuleContext."<init>":(Lorg/antlr/v4/runtime/ParserRuleContext;I)V
       6: return

  public int getRuleIndex();
    Code:
       0: bipush        9
       2: ireturn

  public void enterRule(org.antlr.v4.runtime.tree.ParseTreeListener);
    Code:
       0: aload_1
       1: instanceof    #4                  // class org/hpccsystems/ws/client/antlr/EclRecordListener
       4: ifeq          17
       7: aload_1
       8: checkcast     #4                  // class org/hpccsystems/ws/client/antlr/EclRecordListener
      11: aload_0
      12: invokeinterface #5,  2            // InterfaceMethod org/hpccsystems/ws/client/antlr/EclRecordListener.enterEclfield_recref:(Lorg/hpccsystems/ws/client/antlr/EclRecordParser$Eclfield_recrefContext;)V
      17: return

  public void exitRule(org.antlr.v4.runtime.tree.ParseTreeListener);
    Code:
       0: aload_1
       1: instanceof    #4                  // class org/hpccsystems/ws/client/antlr/EclRecordListener
       4: ifeq          17
       7: aload_1
       8: checkcast     #4                  // class org/hpccsystems/ws/client/antlr/EclRecordListener
      11: aload_0
      12: invokeinterface #6,  2            // InterfaceMethod org/hpccsystems/ws/client/antlr/EclRecordListener.exitEclfield_recref:(Lorg/hpccsystems/ws/client/antlr/EclRecordParser$Eclfield_recrefContext;)V
      17: return
}
