Compiled from "ErrorListener.java"
public class org.hpccsystems.ws.client.antlr.ErrorListener extends org.antlr.v4.runtime.BaseErrorListener {
  private org.hpccsystems.ws.client.antlr.EclRecordReader parent;

  private org.hpccsystems.ws.client.antlr.ErrorStrategy errorHandler;

  java.util.List<java.lang.String> errors;

  public org.hpccsystems.ws.client.antlr.ErrorListener();
    Code:
       0: aload_0
       1: invokespecial #1                  // Method org/antlr/v4/runtime/BaseErrorListener."<init>":()V
       4: aload_0
       5: new           #2                  // class org/hpccsystems/ws/client/antlr/ErrorStrategy
       8: dup
       9: invokespecial #3                  // Method org/hpccsystems/ws/client/antlr/ErrorStrategy."<init>":()V
      12: putfield      #4                  // Field errorHandler:Lorg/hpccsystems/ws/client/antlr/ErrorStrategy;
      15: aload_0
      16: new           #5                  // class java/util/ArrayList
      19: dup
      20: invokespecial #6                  // Method java/util/ArrayList."<init>":()V
      23: putfield      #7                  // Field errors:Ljava/util/List;
      26: return

  public void attach(org.antlr.v4.runtime.Parser);
    Code:
       0: aload_0
       1: getfield      #7                  // Field errors:Ljava/util/List;
       4: invokeinterface #8,  1            // InterfaceMethod java/util/List.clear:()V
       9: aload_1
      10: invokevirtual #9                  // Method org/antlr/v4/runtime/Parser.removeErrorListeners:()V
      13: aload_1
      14: aload_0
      15: invokevirtual #10                 // Method org/antlr/v4/runtime/Parser.addErrorListener:(Lorg/antlr/v4/runtime/ANTLRErrorListener;)V
      18: aload_1
      19: aload_0
      20: getfield      #4                  // Field errorHandler:Lorg/hpccsystems/ws/client/antlr/ErrorStrategy;
      23: invokevirtual #11                 // Method org/antlr/v4/runtime/Parser.setErrorHandler:(Lorg/antlr/v4/runtime/ANTLRErrorStrategy;)V
      26: return

  public void attach(org.antlr.v4.runtime.Lexer);
    Code:
       0: aload_1
       1: invokevirtual #12                 // Method org/antlr/v4/runtime/Lexer.removeErrorListeners:()V
       4: aload_1
       5: aload_0
       6: invokevirtual #13                 // Method org/antlr/v4/runtime/Lexer.addErrorListener:(Lorg/antlr/v4/runtime/ANTLRErrorListener;)V
       9: return

  public void syntaxError(org.antlr.v4.runtime.Recognizer<?, ?>, java.lang.Object, int, int, java.lang.String, org.antlr.v4.runtime.RecognitionException);
    Code:
       0: aload         6
       2: ifnull        18
       5: aload_0
       6: aload_1
       7: aload         6
       9: iload_3
      10: iload         4
      12: aload_2
      13: invokespecial #14                 // Method getErrorMessage:(Lorg/antlr/v4/runtime/Recognizer;Lorg/antlr/v4/runtime/RecognitionException;IILjava/lang/Object;)Ljava/lang/String;
      16: astore        5
      18: aload_0
      19: getfield      #7                  // Field errors:Ljava/util/List;
      22: aload         5
      24: invokeinterface #15,  2           // InterfaceMethod java/util/List.add:(Ljava/lang/Object;)Z
      29: pop
      30: return

  public java.util.List<java.lang.String> getErrors();
    Code:
       0: aload_0
       1: getfield      #7                  // Field errors:Ljava/util/List;
       4: areturn

  public void setParent(org.hpccsystems.ws.client.antlr.EclRecordReader);
    Code:
       0: aload_0
       1: aload_1
       2: putfield      #16                 // Field parent:Lorg/hpccsystems/ws/client/antlr/EclRecordReader;
       5: return

  private java.lang.String getErrorMessage(org.antlr.v4.runtime.Recognizer<?, ?>, org.antlr.v4.runtime.RecognitionException, int, int, java.lang.Object);
    Code:
       0: new           #17                 // class java/lang/StringBuilder
       3: dup
       4: invokespecial #18                 // Method java/lang/StringBuilder."<init>":()V
       7: astore        6
       9: aload_2
      10: instanceof    #19                 // class org/antlr/v4/runtime/InputMismatchException
      13: ifeq          69
      16: aload_2
      17: checkcast     #19                 // class org/antlr/v4/runtime/InputMismatchException
      20: astore        7
      22: aload         7
      24: invokevirtual #20                 // Method org/antlr/v4/runtime/InputMismatchException.getExpectedTokens:()Lorg/antlr/v4/runtime/misc/IntervalSet;
      27: aload_1
      28: invokevirtual #21                 // Method org/antlr/v4/runtime/Recognizer.getVocabulary:()Lorg/antlr/v4/runtime/Vocabulary;
      31: invokevirtual #22                 // Method org/antlr/v4/runtime/misc/IntervalSet.toString:(Lorg/antlr/v4/runtime/Vocabulary;)Ljava/lang/String;
      34: astore        8
      36: aload         6
      38: ldc           #23                 // String MISMATCHED_TOKEN
      40: invokevirtual #24                 // Method java/lang/StringBuilder.append:(Ljava/lang/String;)Ljava/lang/StringBuilder;
      43: aload_2
      44: invokevirtual #25                 // Method org/antlr/v4/runtime/RecognitionException.getOffendingToken:()Lorg/antlr/v4/runtime/Token;
      47: invokeinterface #26,  1           // InterfaceMethod org/antlr/v4/runtime/Token.getText:()Ljava/lang/String;
      52: invokevirtual #24                 // Method java/lang/StringBuilder.append:(Ljava/lang/String;)Ljava/lang/StringBuilder;
      55: ldc           #27                 // String  , expected one of
      57: invokevirtual #24                 // Method java/lang/StringBuilder.append:(Ljava/lang/String;)Ljava/lang/StringBuilder;
      60: aload         8
      62: invokevirtual #24                 // Method java/lang/StringBuilder.append:(Ljava/lang/String;)Ljava/lang/StringBuilder;
      65: pop
      66: goto          192
      69: aload_2
      70: instanceof    #28                 // class org/antlr/v4/runtime/NoViableAltException
      73: ifeq          98
      76: aload         6
      78: ldc           #29                 // String NO_PARSE_ALTERNATIVE,
      80: invokevirtual #24                 // Method java/lang/StringBuilder.append:(Ljava/lang/String;)Ljava/lang/StringBuilder;
      83: aload_0
      84: aload_2
      85: invokevirtual #25                 // Method org/antlr/v4/runtime/RecognitionException.getOffendingToken:()Lorg/antlr/v4/runtime/Token;
      88: invokespecial #30                 // Method getTokenErrorDisplay:(Lorg/antlr/v4/runtime/Token;)Ljava/lang/String;
      91: invokevirtual #24                 // Method java/lang/StringBuilder.append:(Ljava/lang/String;)Ljava/lang/StringBuilder;
      94: pop
      95: goto          192
      98: aload_2
      99: instanceof    #31                 // class org/antlr/v4/runtime/LexerNoViableAltException
     102: ifeq          127
     105: aload         6
     107: ldc           #29                 // String NO_PARSE_ALTERNATIVE,
     109: invokevirtual #24                 // Method java/lang/StringBuilder.append:(Ljava/lang/String;)Ljava/lang/StringBuilder;
     112: aload_0
     113: aload_2
     114: invokevirtual #25                 // Method org/antlr/v4/runtime/RecognitionException.getOffendingToken:()Lorg/antlr/v4/runtime/Token;
     117: invokespecial #30                 // Method getTokenErrorDisplay:(Lorg/antlr/v4/runtime/Token;)Ljava/lang/String;
     120: invokevirtual #24                 // Method java/lang/StringBuilder.append:(Ljava/lang/String;)Ljava/lang/StringBuilder;
     123: pop
     124: goto          192
     127: aload_2
     128: instanceof    #32                 // class org/antlr/v4/runtime/FailedPredicateException
     131: ifeq          177
     134: aload_2
     135: checkcast     #32                 // class org/antlr/v4/runtime/FailedPredicateException
     138: astore        7
     140: aload         6
     142: ldc           #33                 // String FAILED_PARSE_PREDICATE,
     144: invokevirtual #24                 // Method java/lang/StringBuilder.append:(Ljava/lang/String;)Ljava/lang/StringBuilder;
     147: aload_1
     148: invokevirtual #34                 // Method org/antlr/v4/runtime/Recognizer.getRuleNames:()[Ljava/lang/String;
     151: aload         7
     153: invokevirtual #35                 // Method org/antlr/v4/runtime/FailedPredicateException.getRuleIndex:()I
     156: aaload
     157: invokevirtual #24                 // Method java/lang/StringBuilder.append:(Ljava/lang/String;)Ljava/lang/StringBuilder;
     160: ldc           #36                 // String ,
     162: invokevirtual #24                 // Method java/lang/StringBuilder.append:(Ljava/lang/String;)Ljava/lang/StringBuilder;
     165: aload         7
     167: invokevirtual #37                 // Method org/antlr/v4/runtime/FailedPredicateException.getPredicate:()Ljava/lang/String;
     170: invokevirtual #24                 // Method java/lang/StringBuilder.append:(Ljava/lang/String;)Ljava/lang/StringBuilder;
     173: pop
     174: goto          192
     177: aload         6
     179: ldc           #38                 // String GENERAL_PARSE_ERROR,
     181: invokevirtual #24                 // Method java/lang/StringBuilder.append:(Ljava/lang/String;)Ljava/lang/StringBuilder;
     184: aload_2
     185: invokevirtual #39                 // Method org/antlr/v4/runtime/RecognitionException.getMessage:()Ljava/lang/String;
     188: invokevirtual #24                 // Method java/lang/StringBuilder.append:(Ljava/lang/String;)Ljava/lang/StringBuilder;
     191: pop
     192: new           #17                 // class java/lang/StringBuilder
     195: dup
     196: ldc           #40                 // String
     198: invokespecial #41                 // Method java/lang/StringBuilder."<init>":(Ljava/lang/String;)V
     201: astore        7
     203: aload_2
     204: invokevirtual #25                 // Method org/antlr/v4/runtime/RecognitionException.getOffendingToken:()Lorg/antlr/v4/runtime/Token;
     207: ifnull        289
     210: aload         7
     212: ldc           #42                 // String  at line
     214: invokevirtual #24                 // Method java/lang/StringBuilder.append:(Ljava/lang/String;)Ljava/lang/StringBuilder;
     217: aload_2
     218: invokevirtual #25                 // Method org/antlr/v4/runtime/RecognitionException.getOffendingToken:()Lorg/antlr/v4/runtime/Token;
     221: invokeinterface #43,  1           // InterfaceMethod org/antlr/v4/runtime/Token.getLine:()I
     226: invokevirtual #44                 // Method java/lang/StringBuilder.append:(I)Ljava/lang/StringBuilder;
     229: ldc           #45                 // String , char
     231: invokevirtual #24                 // Method java/lang/StringBuilder.append:(Ljava/lang/String;)Ljava/lang/StringBuilder;
     234: aload_2
     235: invokevirtual #25                 // Method org/antlr/v4/runtime/RecognitionException.getOffendingToken:()Lorg/antlr/v4/runtime/Token;
     238: invokeinterface #46,  1           // InterfaceMethod org/antlr/v4/runtime/Token.getCharPositionInLine:()I
     243: invokevirtual #44                 // Method java/lang/StringBuilder.append:(I)Ljava/lang/StringBuilder;
     246: ldc           #47                 // String -
     248: invokevirtual #24                 // Method java/lang/StringBuilder.append:(Ljava/lang/String;)Ljava/lang/StringBuilder;
     251: aload_2
     252: invokevirtual #25                 // Method org/antlr/v4/runtime/RecognitionException.getOffendingToken:()Lorg/antlr/v4/runtime/Token;
     255: invokeinterface #46,  1           // InterfaceMethod org/antlr/v4/runtime/Token.getCharPositionInLine:()I
     260: invokevirtual #44                 // Method java/lang/StringBuilder.append:(I)Ljava/lang/StringBuilder;
     263: aload_2
     264: invokevirtual #25                 // Method org/antlr/v4/runtime/RecognitionException.getOffendingToken:()Lorg/antlr/v4/runtime/Token;
     267: invokeinterface #48,  1           // InterfaceMethod org/antlr/v4/runtime/Token.getStopIndex:()I
     272: aload_2
     273: invokevirtual #25                 // Method org/antlr/v4/runtime/RecognitionException.getOffendingToken:()Lorg/antlr/v4/runtime/Token;
     276: invokeinterface #49,  1           // InterfaceMethod org/antlr/v4/runtime/Token.getStartIndex:()I
     281: isub
     282: invokevirtual #44                 // Method java/lang/StringBuilder.append:(I)Ljava/lang/StringBuilder;
     285: pop
     286: goto          311
     289: aload         7
     291: ldc           #42                 // String  at line
     293: invokevirtual #24                 // Method java/lang/StringBuilder.append:(Ljava/lang/String;)Ljava/lang/StringBuilder;
     296: iload_3
     297: invokevirtual #44                 // Method java/lang/StringBuilder.append:(I)Ljava/lang/StringBuilder;
     300: ldc           #45                 // String , char
     302: invokevirtual #24                 // Method java/lang/StringBuilder.append:(Ljava/lang/String;)Ljava/lang/StringBuilder;
     305: iload         4
     307: invokevirtual #44                 // Method java/lang/StringBuilder.append:(I)Ljava/lang/StringBuilder;
     310: pop
     311: new           #17                 // class java/lang/StringBuilder
     314: dup
     315: invokespecial #18                 // Method java/lang/StringBuilder."<init>":()V
     318: aload         6
     320: invokevirtual #50                 // Method java/lang/StringBuilder.toString:()Ljava/lang/String;
     323: invokevirtual #24                 // Method java/lang/StringBuilder.append:(Ljava/lang/String;)Ljava/lang/StringBuilder;
     326: aload         7
     328: invokevirtual #50                 // Method java/lang/StringBuilder.toString:()Ljava/lang/String;
     331: invokevirtual #24                 // Method java/lang/StringBuilder.append:(Ljava/lang/String;)Ljava/lang/StringBuilder;
     334: invokevirtual #50                 // Method java/lang/StringBuilder.toString:()Ljava/lang/String;
     337: areturn

  private java.lang.String getTokenErrorDisplay(org.antlr.v4.runtime.Token);
    Code:
       0: aload_1
       1: ifnonnull     7
       4: ldc           #51                 // String <no token>
       6: areturn
       7: aload_1
       8: invokeinterface #26,  1           // InterfaceMethod org/antlr/v4/runtime/Token.getText:()Ljava/lang/String;
      13: astore_2
      14: aload_2
      15: ifnonnull     61
      18: aload_1
      19: invokeinterface #52,  1           // InterfaceMethod org/antlr/v4/runtime/Token.getType:()I
      24: iconst_m1
      25: if_icmpne     31
      28: ldc           #54                 // String <EOF>
      30: areturn
      31: new           #17                 // class java/lang/StringBuilder
      34: dup
      35: invokespecial #18                 // Method java/lang/StringBuilder."<init>":()V
      38: ldc           #55                 // String <
      40: invokevirtual #24                 // Method java/lang/StringBuilder.append:(Ljava/lang/String;)Ljava/lang/StringBuilder;
      43: aload_1
      44: invokeinterface #52,  1           // InterfaceMethod org/antlr/v4/runtime/Token.getType:()I
      49: invokevirtual #44                 // Method java/lang/StringBuilder.append:(I)Ljava/lang/StringBuilder;
      52: ldc           #56                 // String >
      54: invokevirtual #24                 // Method java/lang/StringBuilder.append:(Ljava/lang/String;)Ljava/lang/StringBuilder;
      57: invokevirtual #50                 // Method java/lang/StringBuilder.toString:()Ljava/lang/String;
      60: areturn
      61: aload_2
      62: ldc           #57                 // String \n
      64: ldc           #58                 // String \\n
      66: invokevirtual #59                 // Method java/lang/String.replace:(Ljava/lang/CharSequence;Ljava/lang/CharSequence;)Ljava/lang/String;
      69: astore_2
      70: aload_2
      71: ldc           #60                 // String \r
      73: ldc           #61                 // String \\r
      75: invokevirtual #59                 // Method java/lang/String.replace:(Ljava/lang/CharSequence;Ljava/lang/CharSequence;)Ljava/lang/String;
      78: astore_2
      79: aload_2
      80: ldc           #62                 // String \t
      82: ldc           #63                 // String \\t
      84: invokevirtual #59                 // Method java/lang/String.replace:(Ljava/lang/CharSequence;Ljava/lang/CharSequence;)Ljava/lang/String;
      87: astore_2
      88: new           #17                 // class java/lang/StringBuilder
      91: dup
      92: invokespecial #18                 // Method java/lang/StringBuilder."<init>":()V
      95: ldc           #64                 // String \'
      97: invokevirtual #24                 // Method java/lang/StringBuilder.append:(Ljava/lang/String;)Ljava/lang/StringBuilder;
     100: aload_2
     101: invokevirtual #24                 // Method java/lang/StringBuilder.append:(Ljava/lang/String;)Ljava/lang/StringBuilder;
     104: ldc           #64                 // String \'
     106: invokevirtual #24                 // Method java/lang/StringBuilder.append:(Ljava/lang/String;)Ljava/lang/StringBuilder;
     109: invokevirtual #50                 // Method java/lang/StringBuilder.toString:()Ljava/lang/String;
     112: areturn
}
