Compiled from "ResourceCalculatorProcessTree.java"
public abstract class org.apache.hadoop.yarn.util.ResourceCalculatorProcessTree extends org.apache.hadoop.conf.Configured {
  static final org.apache.commons.logging.Log LOG;

  public static final int UNAVAILABLE;

  public org.apache.hadoop.yarn.util.ResourceCalculatorProcessTree(java.lang.String);
    Code:
       0: aload_0
       1: invokespecial #1                  // Method org/apache/hadoop/conf/Configured."<init>":()V
       4: return

  public void initialize() throws org.apache.hadoop.yarn.exceptions.YarnException;
    Code:
       0: return

  public abstract void updateProcessTree();

  public abstract java.lang.String getProcessTreeDump();

  public long getVirtualMemorySize();
    Code:
       0: aload_0
       1: iconst_0
       2: invokevirtual #2                  // Method getVirtualMemorySize:(I)J
       5: lreturn

  public long getRssMemorySize();
    Code:
       0: aload_0
       1: iconst_0
       2: invokevirtual #3                  // Method getRssMemorySize:(I)J
       5: lreturn

  public long getVirtualMemorySize(int);
    Code:
       0: ldc2_w        #5                  // long -1l
       3: lreturn

  public long getRssMemorySize(int);
    Code:
       0: ldc2_w        #5                  // long -1l
       3: lreturn

  public long getCumulativeCpuTime();
    Code:
       0: ldc2_w        #5                  // long -1l
       3: lreturn

  public float getCpuUsagePercent();
    Code:
       0: ldc           #7                  // float -1.0f
       2: freturn

  public abstract boolean checkPidPgrpidForMatch();

  public static org.apache.hadoop.yarn.util.ResourceCalculatorProcessTree getResourceCalculatorProcessTree(java.lang.String, java.lang.Class<? extends org.apache.hadoop.yarn.util.ResourceCalculatorProcessTree>, org.apache.hadoop.conf.Configuration);
    Code:
       0: aload_1
       1: ifnull        59
       4: aload_1
       5: iconst_1
       6: anewarray     #8                  // class java/lang/Class
       9: dup
      10: iconst_0
      11: ldc           #9                  // class java/lang/String
      13: aastore
      14: invokevirtual #10                 // Method java/lang/Class.getConstructor:([Ljava/lang/Class;)Ljava/lang/reflect/Constructor;
      17: astore_3
      18: aload_3
      19: iconst_1
      20: anewarray     #11                 // class java/lang/Object
      23: dup
      24: iconst_0
      25: aload_0
      26: aastore
      27: invokevirtual #12                 // Method java/lang/reflect/Constructor.newInstance:([Ljava/lang/Object;)Ljava/lang/Object;
      30: checkcast     #4                  // class org/apache/hadoop/yarn/util/ResourceCalculatorProcessTree
      33: astore        4
      35: aload         4
      37: aload_2
      38: invokevirtual #13                 // Method setConf:(Lorg/apache/hadoop/conf/Configuration;)V
      41: aload         4
      43: invokevirtual #14                 // Method initialize:()V
      46: aload         4
      48: areturn
      49: astore_3
      50: new           #16                 // class java/lang/RuntimeException
      53: dup
      54: aload_3
      55: invokespecial #17                 // Method java/lang/RuntimeException."<init>":(Ljava/lang/Throwable;)V
      58: athrow
      59: invokestatic  #18                 // Method org/apache/hadoop/yarn/util/ProcfsBasedProcessTree.isAvailable:()Z
      62: ifeq          74
      65: new           #19                 // class org/apache/hadoop/yarn/util/ProcfsBasedProcessTree
      68: dup
      69: aload_0
      70: invokespecial #20                 // Method org/apache/hadoop/yarn/util/ProcfsBasedProcessTree."<init>":(Ljava/lang/String;)V
      73: areturn
      74: invokestatic  #21                 // Method org/apache/hadoop/yarn/util/WindowsBasedProcessTree.isAvailable:()Z
      77: ifeq          89
      80: new           #22                 // class org/apache/hadoop/yarn/util/WindowsBasedProcessTree
      83: dup
      84: aload_0
      85: invokespecial #23                 // Method org/apache/hadoop/yarn/util/WindowsBasedProcessTree."<init>":(Ljava/lang/String;)V
      88: areturn
      89: aconst_null
      90: areturn
    Exception table:
       from    to  target type
           4    48    49   Class java/lang/Exception

  static {};
    Code:
       0: ldc           #4                  // class org/apache/hadoop/yarn/util/ResourceCalculatorProcessTree
       2: invokestatic  #24                 // Method org/apache/commons/logging/LogFactory.getLog:(Ljava/lang/Class;)Lorg/apache/commons/logging/Log;
       5: putstatic     #25                 // Field LOG:Lorg/apache/commons/logging/Log;
       8: return
}
