Compiled from "BackoffOptions.scala"
public final class akka.pattern.BackoffOptionsImpl implements akka.pattern.BackoffOptions,scala.Product,scala.Serializable {
  private final akka.pattern.BackoffType backoffType;

  private final akka.actor.Props childProps;

  private final java.lang.String childName;

  private final scala.concurrent.duration.FiniteDuration minBackoff;

  private final scala.concurrent.duration.FiniteDuration maxBackoff;

  private final double randomFactor;

  private final scala.Option<akka.pattern.BackoffReset> reset;

  private final akka.actor.OneForOneStrategy supervisorStrategy;

  private final akka.pattern.BackoffReset backoffReset;

  public static akka.actor.OneForOneStrategy $lessinit$greater$default$8();
    Code:
       0: getstatic     #22                 // Field akka/pattern/BackoffOptionsImpl$.MODULE$:Lakka/pattern/BackoffOptionsImpl$;
       3: invokevirtual #24                 // Method akka/pattern/BackoffOptionsImpl$.$lessinit$greater$default$8:()Lakka/actor/OneForOneStrategy;
       6: areturn

  public static scala.Option<akka.pattern.BackoffReset> $lessinit$greater$default$7();
    Code:
       0: getstatic     #22                 // Field akka/pattern/BackoffOptionsImpl$.MODULE$:Lakka/pattern/BackoffOptionsImpl$;
       3: invokevirtual #28                 // Method akka/pattern/BackoffOptionsImpl$.$lessinit$greater$default$7:()Lscala/Option;
       6: areturn

  public static akka.pattern.BackoffType $lessinit$greater$default$1();
    Code:
       0: getstatic     #22                 // Field akka/pattern/BackoffOptionsImpl$.MODULE$:Lakka/pattern/BackoffOptionsImpl$;
       3: invokevirtual #32                 // Method akka/pattern/BackoffOptionsImpl$.$lessinit$greater$default$1:()Lakka/pattern/BackoffType;
       6: areturn

  public static akka.actor.OneForOneStrategy apply$default$8();
    Code:
       0: getstatic     #22                 // Field akka/pattern/BackoffOptionsImpl$.MODULE$:Lakka/pattern/BackoffOptionsImpl$;
       3: invokevirtual #35                 // Method akka/pattern/BackoffOptionsImpl$.apply$default$8:()Lakka/actor/OneForOneStrategy;
       6: areturn

  public static scala.Option<akka.pattern.BackoffReset> apply$default$7();
    Code:
       0: getstatic     #22                 // Field akka/pattern/BackoffOptionsImpl$.MODULE$:Lakka/pattern/BackoffOptionsImpl$;
       3: invokevirtual #38                 // Method akka/pattern/BackoffOptionsImpl$.apply$default$7:()Lscala/Option;
       6: areturn

  public static akka.pattern.BackoffType apply$default$1();
    Code:
       0: getstatic     #22                 // Field akka/pattern/BackoffOptionsImpl$.MODULE$:Lakka/pattern/BackoffOptionsImpl$;
       3: invokevirtual #41                 // Method akka/pattern/BackoffOptionsImpl$.apply$default$1:()Lakka/pattern/BackoffType;
       6: areturn

  public static scala.Option<scala.Tuple8<akka.pattern.BackoffType, akka.actor.Props, java.lang.String, scala.concurrent.duration.FiniteDuration, scala.concurrent.duration.FiniteDuration, java.lang.Object, scala.Option<akka.pattern.BackoffReset>, akka.actor.OneForOneStrategy>> unapply(akka.pattern.BackoffOptionsImpl);
    Code:
       0: getstatic     #22                 // Field akka/pattern/BackoffOptionsImpl$.MODULE$:Lakka/pattern/BackoffOptionsImpl$;
       3: aload_0
       4: invokevirtual #45                 // Method akka/pattern/BackoffOptionsImpl$.unapply:(Lakka/pattern/BackoffOptionsImpl;)Lscala/Option;
       7: areturn

  public static akka.pattern.BackoffOptionsImpl apply(akka.pattern.BackoffType, akka.actor.Props, java.lang.String, scala.concurrent.duration.FiniteDuration, scala.concurrent.duration.FiniteDuration, double, scala.Option<akka.pattern.BackoffReset>, akka.actor.OneForOneStrategy);
    Code:
       0: getstatic     #22                 // Field akka/pattern/BackoffOptionsImpl$.MODULE$:Lakka/pattern/BackoffOptionsImpl$;
       3: aload_0
       4: aload_1
       5: aload_2
       6: aload_3
       7: aload         4
       9: dload         5
      11: aload         7
      13: aload         8
      15: invokevirtual #49                 // Method akka/pattern/BackoffOptionsImpl$.apply:(Lakka/pattern/BackoffType;Lakka/actor/Props;Ljava/lang/String;Lscala/concurrent/duration/FiniteDuration;Lscala/concurrent/duration/FiniteDuration;DLscala/Option;Lakka/actor/OneForOneStrategy;)Lakka/pattern/BackoffOptionsImpl;
      18: areturn

  public static scala.Function1<scala.Tuple8<akka.pattern.BackoffType, akka.actor.Props, java.lang.String, scala.concurrent.duration.FiniteDuration, scala.concurrent.duration.FiniteDuration, java.lang.Object, scala.Option<akka.pattern.BackoffReset>, akka.actor.OneForOneStrategy>, akka.pattern.BackoffOptionsImpl> tupled();
    Code:
       0: getstatic     #22                 // Field akka/pattern/BackoffOptionsImpl$.MODULE$:Lakka/pattern/BackoffOptionsImpl$;
       3: invokevirtual #53                 // Method akka/pattern/BackoffOptionsImpl$.tupled:()Lscala/Function1;
       6: areturn

  public static scala.Function1<akka.pattern.BackoffType, scala.Function1<akka.actor.Props, scala.Function1<java.lang.String, scala.Function1<scala.concurrent.duration.FiniteDuration, scala.Function1<scala.concurrent.duration.FiniteDuration, scala.Function1<java.lang.Object, scala.Function1<scala.Option<akka.pattern.BackoffReset>, scala.Function1<akka.actor.OneForOneStrategy, akka.pattern.BackoffOptionsImpl>>>>>>>> curried();
    Code:
       0: getstatic     #22                 // Field akka/pattern/BackoffOptionsImpl$.MODULE$:Lakka/pattern/BackoffOptionsImpl$;
       3: invokevirtual #56                 // Method akka/pattern/BackoffOptionsImpl$.curried:()Lscala/Function1;
       6: areturn

  public akka.pattern.BackoffType backoffType();
    Code:
       0: aload_0
       1: getfield      #76                 // Field backoffType:Lakka/pattern/BackoffType;
       4: areturn

  public akka.actor.Props childProps();
    Code:
       0: aload_0
       1: getfield      #81                 // Field childProps:Lakka/actor/Props;
       4: areturn

  public java.lang.String childName();
    Code:
       0: aload_0
       1: getfield      #84                 // Field childName:Ljava/lang/String;
       4: areturn

  public scala.concurrent.duration.FiniteDuration minBackoff();
    Code:
       0: aload_0
       1: getfield      #87                 // Field minBackoff:Lscala/concurrent/duration/FiniteDuration;
       4: areturn

  public scala.concurrent.duration.FiniteDuration maxBackoff();
    Code:
       0: aload_0
       1: getfield      #89                 // Field maxBackoff:Lscala/concurrent/duration/FiniteDuration;
       4: areturn

  public double randomFactor();
    Code:
       0: aload_0
       1: getfield      #92                 // Field randomFactor:D
       4: dreturn

  public scala.Option<akka.pattern.BackoffReset> reset();
    Code:
       0: aload_0
       1: getfield      #94                 // Field reset:Lscala/Option;
       4: areturn

  public akka.actor.OneForOneStrategy supervisorStrategy();
    Code:
       0: aload_0
       1: getfield      #96                 // Field supervisorStrategy:Lakka/actor/OneForOneStrategy;
       4: areturn

  public akka.pattern.BackoffReset backoffReset();
    Code:
       0: aload_0
       1: getfield      #99                 // Field backoffReset:Lakka/pattern/BackoffReset;
       4: areturn

  public akka.pattern.BackoffOptionsImpl withAutoReset(scala.concurrent.duration.FiniteDuration);
    Code:
       0: new           #103                // class scala/Some
       3: dup
       4: new           #105                // class akka/pattern/AutoReset
       7: dup
       8: aload_1
       9: invokespecial #109                // Method akka/pattern/AutoReset."<init>":(Lscala/concurrent/duration/FiniteDuration;)V
      12: invokespecial #112                // Method scala/Some."<init>":(Ljava/lang/Object;)V
      15: astore_2
      16: aload_0
      17: invokevirtual #115                // Method copy$default$1:()Lakka/pattern/BackoffType;
      20: astore_3
      21: aload_0
      22: invokevirtual #118                // Method copy$default$2:()Lakka/actor/Props;
      25: astore        4
      27: aload_0
      28: invokevirtual #121                // Method copy$default$3:()Ljava/lang/String;
      31: astore        5
      33: aload_0
      34: invokevirtual #124                // Method copy$default$4:()Lscala/concurrent/duration/FiniteDuration;
      37: astore        6
      39: aload_0
      40: invokevirtual #127                // Method copy$default$5:()Lscala/concurrent/duration/FiniteDuration;
      43: astore        7
      45: aload_0
      46: invokevirtual #130                // Method copy$default$6:()D
      49: dstore        8
      51: aload_0
      52: invokevirtual #133                // Method copy$default$8:()Lakka/actor/OneForOneStrategy;
      55: astore        10
      57: aload_0
      58: aload_3
      59: aload         4
      61: aload         5
      63: aload         6
      65: aload         7
      67: dload         8
      69: aload_2
      70: aload         10
      72: invokevirtual #136                // Method copy:(Lakka/pattern/BackoffType;Lakka/actor/Props;Ljava/lang/String;Lscala/concurrent/duration/FiniteDuration;Lscala/concurrent/duration/FiniteDuration;DLscala/Option;Lakka/actor/OneForOneStrategy;)Lakka/pattern/BackoffOptionsImpl;
      75: areturn

  public akka.pattern.BackoffOptionsImpl withManualReset();
    Code:
       0: new           #103                // class scala/Some
       3: dup
       4: getstatic     #153                // Field akka/pattern/ManualReset$.MODULE$:Lakka/pattern/ManualReset$;
       7: invokespecial #112                // Method scala/Some."<init>":(Ljava/lang/Object;)V
      10: astore_1
      11: aload_0
      12: invokevirtual #115                // Method copy$default$1:()Lakka/pattern/BackoffType;
      15: astore_2
      16: aload_0
      17: invokevirtual #118                // Method copy$default$2:()Lakka/actor/Props;
      20: astore_3
      21: aload_0
      22: invokevirtual #121                // Method copy$default$3:()Ljava/lang/String;
      25: astore        4
      27: aload_0
      28: invokevirtual #124                // Method copy$default$4:()Lscala/concurrent/duration/FiniteDuration;
      31: astore        5
      33: aload_0
      34: invokevirtual #127                // Method copy$default$5:()Lscala/concurrent/duration/FiniteDuration;
      37: astore        6
      39: aload_0
      40: invokevirtual #130                // Method copy$default$6:()D
      43: dstore        7
      45: aload_0
      46: invokevirtual #133                // Method copy$default$8:()Lakka/actor/OneForOneStrategy;
      49: astore        9
      51: aload_0
      52: aload_2
      53: aload_3
      54: aload         4
      56: aload         5
      58: aload         6
      60: dload         7
      62: aload_1
      63: aload         9
      65: invokevirtual #136                // Method copy:(Lakka/pattern/BackoffType;Lakka/actor/Props;Ljava/lang/String;Lscala/concurrent/duration/FiniteDuration;Lscala/concurrent/duration/FiniteDuration;DLscala/Option;Lakka/actor/OneForOneStrategy;)Lakka/pattern/BackoffOptionsImpl;
      68: areturn

  public akka.pattern.BackoffOptionsImpl withSupervisorStrategy(akka.actor.OneForOneStrategy);
    Code:
       0: aload_1
       1: astore_2
       2: aload_0
       3: invokevirtual #115                // Method copy$default$1:()Lakka/pattern/BackoffType;
       6: astore_3
       7: aload_0
       8: invokevirtual #118                // Method copy$default$2:()Lakka/actor/Props;
      11: astore        4
      13: aload_0
      14: invokevirtual #121                // Method copy$default$3:()Ljava/lang/String;
      17: astore        5
      19: aload_0
      20: invokevirtual #124                // Method copy$default$4:()Lscala/concurrent/duration/FiniteDuration;
      23: astore        6
      25: aload_0
      26: invokevirtual #127                // Method copy$default$5:()Lscala/concurrent/duration/FiniteDuration;
      29: astore        7
      31: aload_0
      32: invokevirtual #130                // Method copy$default$6:()D
      35: dstore        8
      37: aload_0
      38: invokevirtual #166                // Method copy$default$7:()Lscala/Option;
      41: astore        10
      43: aload_0
      44: aload_3
      45: aload         4
      47: aload         5
      49: aload         6
      51: aload         7
      53: dload         8
      55: aload         10
      57: aload_2
      58: invokevirtual #136                // Method copy:(Lakka/pattern/BackoffType;Lakka/actor/Props;Ljava/lang/String;Lscala/concurrent/duration/FiniteDuration;Lscala/concurrent/duration/FiniteDuration;DLscala/Option;Lakka/actor/OneForOneStrategy;)Lakka/pattern/BackoffOptionsImpl;
      61: areturn

  public akka.pattern.BackoffOptionsImpl withDefaultStoppingStrategy();
    Code:
       0: new           #177                // class akka/actor/OneForOneStrategy
       3: dup
       4: getstatic     #182                // Field akka/actor/OneForOneStrategy$.MODULE$:Lakka/actor/OneForOneStrategy$;
       7: invokevirtual #185                // Method akka/actor/OneForOneStrategy$.apply$default$1:()I
      10: getstatic     #182                // Field akka/actor/OneForOneStrategy$.MODULE$:Lakka/actor/OneForOneStrategy$;
      13: invokevirtual #189                // Method akka/actor/OneForOneStrategy$.apply$default$2:()Lscala/concurrent/duration/Duration;
      16: getstatic     #182                // Field akka/actor/OneForOneStrategy$.MODULE$:Lakka/actor/OneForOneStrategy$;
      19: invokevirtual #193                // Method akka/actor/OneForOneStrategy$.apply$default$3:()Z
      22: getstatic     #198                // Field akka/actor/SupervisorStrategy$.MODULE$:Lakka/actor/SupervisorStrategy$;
      25: invokevirtual #202                // Method akka/actor/SupervisorStrategy$.stoppingStrategy:()Lakka/actor/SupervisorStrategy;
      28: invokevirtual #208                // Method akka/actor/SupervisorStrategy.decider:()Lscala/PartialFunction;
      31: invokespecial #211                // Method akka/actor/OneForOneStrategy."<init>":(ILscala/concurrent/duration/Duration;ZLscala/PartialFunction;)V
      34: astore_1
      35: aload_0
      36: invokevirtual #115                // Method copy$default$1:()Lakka/pattern/BackoffType;
      39: astore_2
      40: aload_0
      41: invokevirtual #118                // Method copy$default$2:()Lakka/actor/Props;
      44: astore_3
      45: aload_0
      46: invokevirtual #121                // Method copy$default$3:()Ljava/lang/String;
      49: astore        4
      51: aload_0
      52: invokevirtual #124                // Method copy$default$4:()Lscala/concurrent/duration/FiniteDuration;
      55: astore        5
      57: aload_0
      58: invokevirtual #127                // Method copy$default$5:()Lscala/concurrent/duration/FiniteDuration;
      61: astore        6
      63: aload_0
      64: invokevirtual #130                // Method copy$default$6:()D
      67: dstore        7
      69: aload_0
      70: invokevirtual #166                // Method copy$default$7:()Lscala/Option;
      73: astore        9
      75: aload_0
      76: aload_2
      77: aload_3
      78: aload         4
      80: aload         5
      82: aload         6
      84: dload         7
      86: aload         9
      88: aload_1
      89: invokevirtual #136                // Method copy:(Lakka/pattern/BackoffType;Lakka/actor/Props;Ljava/lang/String;Lscala/concurrent/duration/FiniteDuration;Lscala/concurrent/duration/FiniteDuration;DLscala/Option;Lakka/actor/OneForOneStrategy;)Lakka/pattern/BackoffOptionsImpl;
      92: areturn

  public akka.actor.Props props();
    Code:
       0: getstatic     #225                // Field scala/Predef$.MODULE$:Lscala/Predef$;
       3: aload_0
       4: invokevirtual #227                // Method minBackoff:()Lscala/concurrent/duration/FiniteDuration;
       7: getstatic     #232                // Field scala/concurrent/duration/Duration$.MODULE$:Lscala/concurrent/duration/Duration$;
      10: invokevirtual #235                // Method scala/concurrent/duration/Duration$.Zero:()Lscala/concurrent/duration/FiniteDuration;
      13: invokevirtual #241                // Method scala/concurrent/duration/FiniteDuration.$greater:(Ljava/lang/Object;)Z
      16: new           #243                // class akka/pattern/BackoffOptionsImpl$$anonfun$props$1
      19: dup
      20: aload_0
      21: invokespecial #246                // Method akka/pattern/BackoffOptionsImpl$$anonfun$props$1."<init>":(Lakka/pattern/BackoffOptionsImpl;)V
      24: invokevirtual #250                // Method scala/Predef$.require:(ZLscala/Function0;)V
      27: getstatic     #225                // Field scala/Predef$.MODULE$:Lscala/Predef$;
      30: aload_0
      31: invokevirtual #252                // Method maxBackoff:()Lscala/concurrent/duration/FiniteDuration;
      34: aload_0
      35: invokevirtual #227                // Method minBackoff:()Lscala/concurrent/duration/FiniteDuration;
      38: invokevirtual #255                // Method scala/concurrent/duration/FiniteDuration.$greater$eq:(Ljava/lang/Object;)Z
      41: new           #257                // class akka/pattern/BackoffOptionsImpl$$anonfun$props$2
      44: dup
      45: aload_0
      46: invokespecial #258                // Method akka/pattern/BackoffOptionsImpl$$anonfun$props$2."<init>":(Lakka/pattern/BackoffOptionsImpl;)V
      49: invokevirtual #250                // Method scala/Predef$.require:(ZLscala/Function0;)V
      52: getstatic     #225                // Field scala/Predef$.MODULE$:Lscala/Predef$;
      55: dconst_0
      56: aload_0
      57: invokevirtual #260                // Method randomFactor:()D
      60: dcmpg
      61: ifgt          77
      64: aload_0
      65: invokevirtual #260                // Method randomFactor:()D
      68: dconst_1
      69: dcmpg
      70: ifgt          77
      73: iconst_1
      74: goto          78
      77: iconst_0
      78: new           #262                // class akka/pattern/BackoffOptionsImpl$$anonfun$props$3
      81: dup
      82: aload_0
      83: invokespecial #263                // Method akka/pattern/BackoffOptionsImpl$$anonfun$props$3."<init>":(Lakka/pattern/BackoffOptionsImpl;)V
      86: invokevirtual #250                // Method scala/Predef$.require:(ZLscala/Function0;)V
      89: aload_0
      90: invokevirtual #265                // Method backoffReset:()Lakka/pattern/BackoffReset;
      93: astore_1
      94: aload_1
      95: instanceof    #105                // class akka/pattern/AutoReset
      98: ifeq          152
     101: aload_1
     102: checkcast     #105                // class akka/pattern/AutoReset
     105: astore_2
     106: aload_2
     107: invokevirtual #267                // Method akka/pattern/AutoReset.resetBackoff:()Lscala/concurrent/duration/FiniteDuration;
     110: astore_3
     111: getstatic     #225                // Field scala/Predef$.MODULE$:Lscala/Predef$;
     114: aload_0
     115: invokevirtual #227                // Method minBackoff:()Lscala/concurrent/duration/FiniteDuration;
     118: aload_3
     119: invokevirtual #270                // Method scala/concurrent/duration/FiniteDuration.$less$eq:(Ljava/lang/Object;)Z
     122: ifeq          140
     125: aload_3
     126: aload_0
     127: invokevirtual #252                // Method maxBackoff:()Lscala/concurrent/duration/FiniteDuration;
     130: invokevirtual #270                // Method scala/concurrent/duration/FiniteDuration.$less$eq:(Ljava/lang/Object;)Z
     133: ifeq          140
     136: iconst_1
     137: goto          141
     140: iconst_0
     141: invokevirtual #273                // Method scala/Predef$.require:(Z)V
     144: getstatic     #279                // Field scala/runtime/BoxedUnit.UNIT:Lscala/runtime/BoxedUnit;
     147: astore        4
     149: goto          157
     152: getstatic     #279                // Field scala/runtime/BoxedUnit.UNIT:Lscala/runtime/BoxedUnit;
     155: astore        4
     157: aload_0
     158: invokevirtual #281                // Method backoffType:()Lakka/pattern/BackoffType;
     161: astore        5
     163: getstatic     #286                // Field akka/pattern/RestartImpliesFailure$.MODULE$:Lakka/pattern/RestartImpliesFailure$;
     166: aload         5
     168: invokevirtual #289                // Method java/lang/Object.equals:(Ljava/lang/Object;)Z
     171: ifeq          202
     174: getstatic     #294                // Field akka/actor/Props$.MODULE$:Lakka/actor/Props$;
     177: new           #296                // class akka/pattern/BackoffOptionsImpl$$anonfun$props$4
     180: dup
     181: aload_0
     182: invokespecial #297                // Method akka/pattern/BackoffOptionsImpl$$anonfun$props$4."<init>":(Lakka/pattern/BackoffOptionsImpl;)V
     185: getstatic     #302                // Field scala/reflect/ClassTag$.MODULE$:Lscala/reflect/ClassTag$;
     188: ldc_w         #304                // class akka/pattern/BackoffOnRestartSupervisor
     191: invokevirtual #307                // Method scala/reflect/ClassTag$.apply:(Ljava/lang/Class;)Lscala/reflect/ClassTag;
     194: invokevirtual #310                // Method akka/actor/Props$.apply:(Lscala/Function0;Lscala/reflect/ClassTag;)Lakka/actor/Props;
     197: astore        6
     199: goto          238
     202: getstatic     #315                // Field akka/pattern/StopImpliesFailure$.MODULE$:Lakka/pattern/StopImpliesFailure$;
     205: aload         5
     207: invokevirtual #289                // Method java/lang/Object.equals:(Ljava/lang/Object;)Z
     210: ifeq          241
     213: getstatic     #294                // Field akka/actor/Props$.MODULE$:Lakka/actor/Props$;
     216: new           #317                // class akka/pattern/BackoffOptionsImpl$$anonfun$props$5
     219: dup
     220: aload_0
     221: invokespecial #318                // Method akka/pattern/BackoffOptionsImpl$$anonfun$props$5."<init>":(Lakka/pattern/BackoffOptionsImpl;)V
     224: getstatic     #302                // Field scala/reflect/ClassTag$.MODULE$:Lscala/reflect/ClassTag$;
     227: ldc_w         #320                // class akka/pattern/BackoffSupervisor
     230: invokevirtual #307                // Method scala/reflect/ClassTag$.apply:(Ljava/lang/Class;)Lscala/reflect/ClassTag;
     233: invokevirtual #310                // Method akka/actor/Props$.apply:(Lscala/Function0;Lscala/reflect/ClassTag;)Lakka/actor/Props;
     236: astore        6
     238: aload         6
     240: areturn
     241: new           #322                // class scala/MatchError
     244: dup
     245: aload         5
     247: invokespecial #323                // Method scala/MatchError."<init>":(Ljava/lang/Object;)V
     250: athrow

  public akka.pattern.BackoffOptionsImpl copy(akka.pattern.BackoffType, akka.actor.Props, java.lang.String, scala.concurrent.duration.FiniteDuration, scala.concurrent.duration.FiniteDuration, double, scala.Option<akka.pattern.BackoffReset>, akka.actor.OneForOneStrategy);
    Code:
       0: new           #2                  // class akka/pattern/BackoffOptionsImpl
       3: dup
       4: aload_1
       5: aload_2
       6: aload_3
       7: aload         4
       9: aload         5
      11: dload         6
      13: aload         8
      15: aload         9
      17: invokespecial #332                // Method "<init>":(Lakka/pattern/BackoffType;Lakka/actor/Props;Ljava/lang/String;Lscala/concurrent/duration/FiniteDuration;Lscala/concurrent/duration/FiniteDuration;DLscala/Option;Lakka/actor/OneForOneStrategy;)V
      20: areturn

  public akka.pattern.BackoffType copy$default$1();
    Code:
       0: aload_0
       1: invokevirtual #281                // Method backoffType:()Lakka/pattern/BackoffType;
       4: areturn

  public akka.actor.Props copy$default$2();
    Code:
       0: aload_0
       1: invokevirtual #334                // Method childProps:()Lakka/actor/Props;
       4: areturn

  public java.lang.String copy$default$3();
    Code:
       0: aload_0
       1: invokevirtual #336                // Method childName:()Ljava/lang/String;
       4: areturn

  public scala.concurrent.duration.FiniteDuration copy$default$4();
    Code:
       0: aload_0
       1: invokevirtual #227                // Method minBackoff:()Lscala/concurrent/duration/FiniteDuration;
       4: areturn

  public scala.concurrent.duration.FiniteDuration copy$default$5();
    Code:
       0: aload_0
       1: invokevirtual #252                // Method maxBackoff:()Lscala/concurrent/duration/FiniteDuration;
       4: areturn

  public double copy$default$6();
    Code:
       0: aload_0
       1: invokevirtual #260                // Method randomFactor:()D
       4: dreturn

  public scala.Option<akka.pattern.BackoffReset> copy$default$7();
    Code:
       0: aload_0
       1: invokevirtual #338                // Method reset:()Lscala/Option;
       4: areturn

  public akka.actor.OneForOneStrategy copy$default$8();
    Code:
       0: aload_0
       1: invokevirtual #340                // Method supervisorStrategy:()Lakka/actor/OneForOneStrategy;
       4: areturn

  public java.lang.String productPrefix();
    Code:
       0: ldc_w         #343                // String BackoffOptionsImpl
       3: areturn

  public int productArity();
    Code:
       0: bipush        8
       2: ireturn

  public java.lang.Object productElement(int);
    Code:
       0: iload_1
       1: istore_2
       2: iload_2
       3: tableswitch   { // 0 to 7
                     0: 115
                     1: 108
                     2: 101
                     3: 94
                     4: 87
                     5: 77
                     6: 70
                     7: 63
               default: 48
          }
      48: new           #348                // class java/lang/IndexOutOfBoundsException
      51: dup
      52: iload_1
      53: invokestatic  #354                // Method scala/runtime/BoxesRunTime.boxToInteger:(I)Ljava/lang/Integer;
      56: invokevirtual #357                // Method java/lang/Object.toString:()Ljava/lang/String;
      59: invokespecial #360                // Method java/lang/IndexOutOfBoundsException."<init>":(Ljava/lang/String;)V
      62: athrow
      63: aload_0
      64: invokevirtual #340                // Method supervisorStrategy:()Lakka/actor/OneForOneStrategy;
      67: goto          119
      70: aload_0
      71: invokevirtual #338                // Method reset:()Lscala/Option;
      74: goto          119
      77: aload_0
      78: invokevirtual #260                // Method randomFactor:()D
      81: invokestatic  #364                // Method scala/runtime/BoxesRunTime.boxToDouble:(D)Ljava/lang/Double;
      84: goto          119
      87: aload_0
      88: invokevirtual #252                // Method maxBackoff:()Lscala/concurrent/duration/FiniteDuration;
      91: goto          119
      94: aload_0
      95: invokevirtual #227                // Method minBackoff:()Lscala/concurrent/duration/FiniteDuration;
      98: goto          119
     101: aload_0
     102: invokevirtual #336                // Method childName:()Ljava/lang/String;
     105: goto          119
     108: aload_0
     109: invokevirtual #334                // Method childProps:()Lakka/actor/Props;
     112: goto          119
     115: aload_0
     116: invokevirtual #281                // Method backoffType:()Lakka/pattern/BackoffType;
     119: areturn

  public scala.collection.Iterator<java.lang.Object> productIterator();
    Code:
       0: getstatic     #372                // Field scala/runtime/ScalaRunTime$.MODULE$:Lscala/runtime/ScalaRunTime$;
       3: aload_0
       4: invokevirtual #376                // Method scala/runtime/ScalaRunTime$.typedProductIterator:(Lscala/Product;)Lscala/collection/Iterator;
       7: areturn

  public boolean canEqual(java.lang.Object);
    Code:
       0: aload_1
       1: instanceof    #2                  // class akka/pattern/BackoffOptionsImpl
       4: ireturn

  public int hashCode();
    Code:
       0: ldc_w         #380                // int -889275714
       3: istore_1
       4: iload_1
       5: aload_0
       6: invokevirtual #281                // Method backoffType:()Lakka/pattern/BackoffType;
       9: invokestatic  #386                // Method scala/runtime/Statics.anyHash:(Ljava/lang/Object;)I
      12: invokestatic  #390                // Method scala/runtime/Statics.mix:(II)I
      15: istore_1
      16: iload_1
      17: aload_0
      18: invokevirtual #334                // Method childProps:()Lakka/actor/Props;
      21: invokestatic  #386                // Method scala/runtime/Statics.anyHash:(Ljava/lang/Object;)I
      24: invokestatic  #390                // Method scala/runtime/Statics.mix:(II)I
      27: istore_1
      28: iload_1
      29: aload_0
      30: invokevirtual #336                // Method childName:()Ljava/lang/String;
      33: invokestatic  #386                // Method scala/runtime/Statics.anyHash:(Ljava/lang/Object;)I
      36: invokestatic  #390                // Method scala/runtime/Statics.mix:(II)I
      39: istore_1
      40: iload_1
      41: aload_0
      42: invokevirtual #227                // Method minBackoff:()Lscala/concurrent/duration/FiniteDuration;
      45: invokestatic  #386                // Method scala/runtime/Statics.anyHash:(Ljava/lang/Object;)I
      48: invokestatic  #390                // Method scala/runtime/Statics.mix:(II)I
      51: istore_1
      52: iload_1
      53: aload_0
      54: invokevirtual #252                // Method maxBackoff:()Lscala/concurrent/duration/FiniteDuration;
      57: invokestatic  #386                // Method scala/runtime/Statics.anyHash:(Ljava/lang/Object;)I
      60: invokestatic  #390                // Method scala/runtime/Statics.mix:(II)I
      63: istore_1
      64: iload_1
      65: aload_0
      66: invokevirtual #260                // Method randomFactor:()D
      69: invokestatic  #394                // Method scala/runtime/Statics.doubleHash:(D)I
      72: invokestatic  #390                // Method scala/runtime/Statics.mix:(II)I
      75: istore_1
      76: iload_1
      77: aload_0
      78: invokevirtual #338                // Method reset:()Lscala/Option;
      81: invokestatic  #386                // Method scala/runtime/Statics.anyHash:(Ljava/lang/Object;)I
      84: invokestatic  #390                // Method scala/runtime/Statics.mix:(II)I
      87: istore_1
      88: iload_1
      89: aload_0
      90: invokevirtual #340                // Method supervisorStrategy:()Lakka/actor/OneForOneStrategy;
      93: invokestatic  #386                // Method scala/runtime/Statics.anyHash:(Ljava/lang/Object;)I
      96: invokestatic  #390                // Method scala/runtime/Statics.mix:(II)I
      99: istore_1
     100: iload_1
     101: bipush        8
     103: invokestatic  #397                // Method scala/runtime/Statics.finalizeHash:(II)I
     106: ireturn

  public java.lang.String toString();
    Code:
       0: getstatic     #372                // Field scala/runtime/ScalaRunTime$.MODULE$:Lscala/runtime/ScalaRunTime$;
       3: aload_0
       4: invokevirtual #401                // Method scala/runtime/ScalaRunTime$._toString:(Lscala/Product;)Ljava/lang/String;
       7: areturn

  public boolean equals(java.lang.Object);
    Code:
       0: aload_0
       1: aload_1
       2: if_acmpeq     276
       5: aload_1
       6: astore_2
       7: aload_2
       8: instanceof    #2                  // class akka/pattern/BackoffOptionsImpl
      11: ifeq          19
      14: iconst_1
      15: istore_3
      16: goto          21
      19: iconst_0
      20: istore_3
      21: iload_3
      22: ifeq          280
      25: aload_1
      26: checkcast     #2                  // class akka/pattern/BackoffOptionsImpl
      29: astore        4
      31: aload_0
      32: invokevirtual #281                // Method backoffType:()Lakka/pattern/BackoffType;
      35: aload         4
      37: invokevirtual #281                // Method backoffType:()Lakka/pattern/BackoffType;
      40: astore        5
      42: dup
      43: ifnonnull     55
      46: pop
      47: aload         5
      49: ifnull        63
      52: goto          272
      55: aload         5
      57: invokevirtual #289                // Method java/lang/Object.equals:(Ljava/lang/Object;)Z
      60: ifeq          272
      63: aload_0
      64: invokevirtual #334                // Method childProps:()Lakka/actor/Props;
      67: aload         4
      69: invokevirtual #334                // Method childProps:()Lakka/actor/Props;
      72: astore        6
      74: dup
      75: ifnonnull     87
      78: pop
      79: aload         6
      81: ifnull        95
      84: goto          272
      87: aload         6
      89: invokevirtual #289                // Method java/lang/Object.equals:(Ljava/lang/Object;)Z
      92: ifeq          272
      95: aload_0
      96: invokevirtual #336                // Method childName:()Ljava/lang/String;
      99: aload         4
     101: invokevirtual #336                // Method childName:()Ljava/lang/String;
     104: astore        7
     106: dup
     107: ifnonnull     119
     110: pop
     111: aload         7
     113: ifnull        127
     116: goto          272
     119: aload         7
     121: invokevirtual #289                // Method java/lang/Object.equals:(Ljava/lang/Object;)Z
     124: ifeq          272
     127: aload_0
     128: invokevirtual #227                // Method minBackoff:()Lscala/concurrent/duration/FiniteDuration;
     131: aload         4
     133: invokevirtual #227                // Method minBackoff:()Lscala/concurrent/duration/FiniteDuration;
     136: astore        8
     138: dup
     139: ifnonnull     151
     142: pop
     143: aload         8
     145: ifnull        159
     148: goto          272
     151: aload         8
     153: invokevirtual #289                // Method java/lang/Object.equals:(Ljava/lang/Object;)Z
     156: ifeq          272
     159: aload_0
     160: invokevirtual #252                // Method maxBackoff:()Lscala/concurrent/duration/FiniteDuration;
     163: aload         4
     165: invokevirtual #252                // Method maxBackoff:()Lscala/concurrent/duration/FiniteDuration;
     168: astore        9
     170: dup
     171: ifnonnull     183
     174: pop
     175: aload         9
     177: ifnull        191
     180: goto          272
     183: aload         9
     185: invokevirtual #289                // Method java/lang/Object.equals:(Ljava/lang/Object;)Z
     188: ifeq          272
     191: aload_0
     192: invokevirtual #260                // Method randomFactor:()D
     195: aload         4
     197: invokevirtual #260                // Method randomFactor:()D
     200: dcmpl
     201: ifne          272
     204: aload_0
     205: invokevirtual #338                // Method reset:()Lscala/Option;
     208: aload         4
     210: invokevirtual #338                // Method reset:()Lscala/Option;
     213: astore        10
     215: dup
     216: ifnonnull     228
     219: pop
     220: aload         10
     222: ifnull        236
     225: goto          272
     228: aload         10
     230: invokevirtual #289                // Method java/lang/Object.equals:(Ljava/lang/Object;)Z
     233: ifeq          272
     236: aload_0
     237: invokevirtual #340                // Method supervisorStrategy:()Lakka/actor/OneForOneStrategy;
     240: aload         4
     242: invokevirtual #340                // Method supervisorStrategy:()Lakka/actor/OneForOneStrategy;
     245: astore        11
     247: dup
     248: ifnonnull     260
     251: pop
     252: aload         11
     254: ifnull        268
     257: goto          272
     260: aload         11
     262: invokevirtual #289                // Method java/lang/Object.equals:(Ljava/lang/Object;)Z
     265: ifeq          272
     268: iconst_1
     269: goto          273
     272: iconst_0
     273: ifeq          280
     276: iconst_1
     277: goto          281
     280: iconst_0
     281: ireturn

  public akka.pattern.BackoffOptions withDefaultStoppingStrategy();
    Code:
       0: aload_0
       1: invokevirtual #408                // Method withDefaultStoppingStrategy:()Lakka/pattern/BackoffOptionsImpl;
       4: areturn

  public akka.pattern.BackoffOptions withSupervisorStrategy(akka.actor.OneForOneStrategy);
    Code:
       0: aload_0
       1: aload_1
       2: invokevirtual #411                // Method withSupervisorStrategy:(Lakka/actor/OneForOneStrategy;)Lakka/pattern/BackoffOptionsImpl;
       5: areturn

  public akka.pattern.BackoffOptions withManualReset();
    Code:
       0: aload_0
       1: invokevirtual #413                // Method withManualReset:()Lakka/pattern/BackoffOptionsImpl;
       4: areturn

  public akka.pattern.BackoffOptions withAutoReset(scala.concurrent.duration.FiniteDuration);
    Code:
       0: aload_0
       1: aload_1
       2: invokevirtual #416                // Method withAutoReset:(Lscala/concurrent/duration/FiniteDuration;)Lakka/pattern/BackoffOptionsImpl;
       5: areturn

  public akka.pattern.BackoffOptionsImpl(akka.pattern.BackoffType, akka.actor.Props, java.lang.String, scala.concurrent.duration.FiniteDuration, scala.concurrent.duration.FiniteDuration, double, scala.Option<akka.pattern.BackoffReset>, akka.actor.OneForOneStrategy);
    Code:
       0: aload_0
       1: aload_1
       2: putfield      #76                 // Field backoffType:Lakka/pattern/BackoffType;
       5: aload_0
       6: aload_2
       7: putfield      #81                 // Field childProps:Lakka/actor/Props;
      10: aload_0
      11: aload_3
      12: putfield      #84                 // Field childName:Ljava/lang/String;
      15: aload_0
      16: aload         4
      18: putfield      #87                 // Field minBackoff:Lscala/concurrent/duration/FiniteDuration;
      21: aload_0
      22: aload         5
      24: putfield      #89                 // Field maxBackoff:Lscala/concurrent/duration/FiniteDuration;
      27: aload_0
      28: dload         6
      30: putfield      #92                 // Field randomFactor:D
      33: aload_0
      34: aload         8
      36: putfield      #94                 // Field reset:Lscala/Option;
      39: aload_0
      40: aload         9
      42: putfield      #96                 // Field supervisorStrategy:Lakka/actor/OneForOneStrategy;
      45: aload_0
      46: invokespecial #419                // Method java/lang/Object."<init>":()V
      49: aload_0
      50: invokestatic  #425                // Method scala/Product$class.$init$:(Lscala/Product;)V
      53: aload_0
      54: aload         8
      56: new           #427                // class akka/pattern/BackoffOptionsImpl$$anonfun$1
      59: dup
      60: aload_0
      61: invokespecial #428                // Method akka/pattern/BackoffOptionsImpl$$anonfun$1."<init>":(Lakka/pattern/BackoffOptionsImpl;)V
      64: invokevirtual #432                // Method scala/Option.getOrElse:(Lscala/Function0;)Ljava/lang/Object;
      67: checkcast     #325                // class akka/pattern/BackoffReset
      70: putfield      #99                 // Field backoffReset:Lakka/pattern/BackoffReset;
      73: return
}
