Compiled from "BackoffOnRestartSupervisor.scala"
public final class akka.pattern.BackoffOnRestartSupervisor$$anonfun$1 extends scala.runtime.AbstractPartialFunction<java.lang.Throwable, akka.actor.SupervisorStrategy$Directive> implements scala.Serializable {
  public static final long serialVersionUID;

  private final akka.pattern.BackoffOnRestartSupervisor $outer;

  public final <A1 extends java.lang.Throwable, B1> B1 applyOrElse(A1, scala.Function1<A1, B1>);
    Code:
       0: aload_1
       1: astore_3
       2: aload_0
       3: getfield      #20                 // Field $outer:Lakka/pattern/BackoffOnRestartSupervisor;
       6: invokevirtual #24                 // Method akka/pattern/BackoffOnRestartSupervisor.akka$pattern$BackoffOnRestartSupervisor$$super$supervisorStrategy:()Lakka/actor/SupervisorStrategy;
       9: invokevirtual #30                 // Method akka/actor/SupervisorStrategy.decider:()Lscala/PartialFunction;
      12: aload_3
      13: new           #32                 // class akka/pattern/BackoffOnRestartSupervisor$$anonfun$1$$anonfun$2
      16: dup
      17: aload_0
      18: invokespecial #36                 // Method akka/pattern/BackoffOnRestartSupervisor$$anonfun$1$$anonfun$2."<init>":(Lakka/pattern/BackoffOnRestartSupervisor$$anonfun$1;)V
      21: invokeinterface #41,  3           // InterfaceMethod scala/PartialFunction.applyOrElse:(Ljava/lang/Object;Lscala/Function1;)Ljava/lang/Object;
      26: checkcast     #43                 // class akka/actor/SupervisorStrategy$Directive
      29: astore        5
      31: aload_0
      32: getfield      #20                 // Field $outer:Lakka/pattern/BackoffOnRestartSupervisor;
      35: getfield      #47                 // Field akka/pattern/BackoffOnRestartSupervisor.akka$pattern$BackoffOnRestartSupervisor$$strategy:Lakka/actor/OneForOneStrategy;
      38: invokevirtual #50                 // Method akka/actor/OneForOneStrategy.decider:()Lscala/PartialFunction;
      41: aload_3
      42: new           #52                 // class akka/pattern/BackoffOnRestartSupervisor$$anonfun$1$$anonfun$3
      45: dup
      46: aload_0
      47: aload         5
      49: invokespecial #55                 // Method akka/pattern/BackoffOnRestartSupervisor$$anonfun$1$$anonfun$3."<init>":(Lakka/pattern/BackoffOnRestartSupervisor$$anonfun$1;Lakka/actor/SupervisorStrategy$Directive;)V
      52: invokeinterface #41,  3           // InterfaceMethod scala/PartialFunction.applyOrElse:(Ljava/lang/Object;Lscala/Function1;)Ljava/lang/Object;
      57: checkcast     #43                 // class akka/actor/SupervisorStrategy$Directive
      60: astore        6
      62: getstatic     #61                 // Field akka/actor/SupervisorStrategy$Restart$.MODULE$:Lakka/actor/SupervisorStrategy$Restart$;
      65: aload         6
      67: invokevirtual #67                 // Method java/lang/Object.equals:(Ljava/lang/Object;)Z
      70: ifeq          123
      73: aload_0
      74: getfield      #20                 // Field $outer:Lakka/pattern/BackoffOnRestartSupervisor;
      77: invokevirtual #71                 // Method akka/pattern/BackoffOnRestartSupervisor.sender:()Lakka/actor/ActorRef;
      80: astore        8
      82: aload_0
      83: getfield      #20                 // Field $outer:Lakka/pattern/BackoffOnRestartSupervisor;
      86: invokevirtual #75                 // Method akka/pattern/BackoffOnRestartSupervisor.context:()Lakka/actor/ActorContext;
      89: aload_0
      90: getfield      #20                 // Field $outer:Lakka/pattern/BackoffOnRestartSupervisor;
      93: aload         8
      95: invokevirtual #79                 // Method akka/pattern/BackoffOnRestartSupervisor.waitChildTerminatedBeforeBackoff:(Lakka/actor/ActorRef;)Lscala/PartialFunction;
      98: aload_0
      99: getfield      #20                 // Field $outer:Lakka/pattern/BackoffOnRestartSupervisor;
     102: invokevirtual #82                 // Method akka/pattern/BackoffOnRestartSupervisor.handleBackoff:()Lscala/PartialFunction;
     105: invokeinterface #86,  2           // InterfaceMethod scala/PartialFunction.orElse:(Lscala/PartialFunction;)Lscala/PartialFunction;
     110: invokeinterface #92,  2           // InterfaceMethod akka/actor/ActorContext.become:(Lscala/PartialFunction;)V
     115: getstatic     #97                 // Field akka/actor/SupervisorStrategy$Stop$.MODULE$:Lakka/actor/SupervisorStrategy$Stop$;
     118: astore        7
     120: goto          127
     123: aload         6
     125: astore        7
     127: aload         7
     129: astore        4
     131: aload         4
     133: areturn

  public final boolean isDefinedAt(java.lang.Throwable);
    Code:
       0: aload_1
       1: astore_2
       2: iconst_1
       3: istore_3
       4: iload_3
       5: ireturn

  public final boolean isDefinedAt(java.lang.Object);
    Code:
       0: aload_0
       1: aload_1
       2: checkcast     #109                // class java/lang/Throwable
       5: invokevirtual #115                // Method isDefinedAt:(Ljava/lang/Throwable;)Z
       8: ireturn

  public final java.lang.Object applyOrElse(java.lang.Object, scala.Function1);
    Code:
       0: aload_0
       1: aload_1
       2: checkcast     #109                // class java/lang/Throwable
       5: aload_2
       6: invokevirtual #119                // Method applyOrElse:(Ljava/lang/Throwable;Lscala/Function1;)Ljava/lang/Object;
       9: areturn

  public akka.pattern.BackoffOnRestartSupervisor$$anonfun$1(akka.pattern.BackoffOnRestartSupervisor);
    Code:
       0: aload_1
       1: ifnonnull     6
       4: aconst_null
       5: athrow
       6: aload_0
       7: aload_1
       8: putfield      #20                 // Field $outer:Lakka/pattern/BackoffOnRestartSupervisor;
      11: aload_0
      12: invokespecial #123                // Method scala/runtime/AbstractPartialFunction."<init>":()V
      15: return
}
