Compiled from "CircuitBreaker.scala"
public final class akka.pattern.CircuitBreakerOpenException$ implements scala.Serializable {
  public static final akka.pattern.CircuitBreakerOpenException$ MODULE$;

  public static {};
    Code:
       0: new           #2                  // class akka/pattern/CircuitBreakerOpenException$
       3: invokespecial #14                 // Method "<init>":()V
       6: return

  public java.lang.String $lessinit$greater$default$2();
    Code:
       0: ldc           #18                 // String Circuit Breaker is open; calls are failing fast
       2: areturn

  private java.lang.Object readResolve();
    Code:
       0: getstatic     #23                 // Field MODULE$:Lakka/pattern/CircuitBreakerOpenException$;
       3: areturn

  private akka.pattern.CircuitBreakerOpenException$();
    Code:
       0: aload_0
       1: invokespecial #24                 // Method java/lang/Object."<init>":()V
       4: aload_0
       5: putstatic     #23                 // Field MODULE$:Lakka/pattern/CircuitBreakerOpenException$;
       8: return
}
