Compiled from "CircuitBreaker.scala"
public final class akka.pattern.CircuitBreaker$$anon$3 implements java.lang.Runnable {
  private final scala.Function0 callback$1;

  public void run();
    Code:
       0: aload_0
       1: getfield      #18                 // Field callback$1:Lscala/Function0;
       4: invokeinterface #23,  1           // InterfaceMethod scala/Function0.apply$mcV$sp:()V
       9: return

  public akka.pattern.CircuitBreaker$$anon$3(akka.pattern.CircuitBreaker, scala.Function0);
    Code:
       0: aload_0
       1: aload_2
       2: putfield      #18                 // Field callback$1:Lscala/Function0;
       5: aload_0
       6: invokespecial #29                 // Method java/lang/Object."<init>":()V
       9: return
}
