Compiled from "InputSampler.java"
public class org.apache.hadoop.mapred.lib.InputSampler$RandomSampler<K, V> extends org.apache.hadoop.mapreduce.lib.partition.InputSampler$RandomSampler<K, V> implements org.apache.hadoop.mapred.lib.InputSampler$Sampler<K, V> {
  public org.apache.hadoop.mapred.lib.InputSampler$RandomSampler(double, int);
    Code:
       0: aload_0
       1: dload_1
       2: iload_3
       3: ldc           #2                  // int 2147483647
       5: invokespecial #3                  // Method "<init>":(DII)V
       8: return

  public org.apache.hadoop.mapred.lib.InputSampler$RandomSampler(double, int, int);
    Code:
       0: aload_0
       1: dload_1
       2: iload_3
       3: iload         4
       5: invokespecial #4                  // Method org/apache/hadoop/mapreduce/lib/partition/InputSampler$RandomSampler."<init>":(DII)V
       8: return

  public K[] getSample(org.apache.hadoop.mapred.InputFormat<K, V>, org.apache.hadoop.mapred.JobConf) throws java.io.IOException;
    Code:
       0: aload_1
       1: aload_2
       2: aload_2
       3: invokevirtual #5                  // Method org/apache/hadoop/mapred/JobConf.getNumMapTasks:()I
       6: invokeinterface #6,  3            // InterfaceMethod org/apache/hadoop/mapred/InputFormat.getSplits:(Lorg/apache/hadoop/mapred/JobConf;I)[Lorg/apache/hadoop/mapred/InputSplit;
      11: astore_3
      12: new           #7                  // class java/util/ArrayList
      15: dup
      16: aload_0
      17: getfield      #8                  // Field numSamples:I
      20: invokespecial #9                  // Method java/util/ArrayList."<init>":(I)V
      23: astore        4
      25: aload_0
      26: getfield      #10                 // Field maxSplitsSampled:I
      29: aload_3
      30: arraylength
      31: invokestatic  #11                 // Method java/lang/Math.min:(II)I
      34: istore        5
      36: new           #12                 // class java/util/Random
      39: dup
      40: invokespecial #13                 // Method java/util/Random."<init>":()V
      43: astore        6
      45: aload         6
      47: invokevirtual #14                 // Method java/util/Random.nextLong:()J
      50: lstore        7
      52: aload         6
      54: lload         7
      56: invokevirtual #15                 // Method java/util/Random.setSeed:(J)V
      59: invokestatic  #16                 // Method org/apache/hadoop/mapred/lib/InputSampler.access$000:()Lorg/slf4j/Logger;
      62: new           #17                 // class java/lang/StringBuilder
      65: dup
      66: invokespecial #18                 // Method java/lang/StringBuilder."<init>":()V
      69: ldc           #19                 // String seed:
      71: invokevirtual #20                 // Method java/lang/StringBuilder.append:(Ljava/lang/String;)Ljava/lang/StringBuilder;
      74: lload         7
      76: invokevirtual #21                 // Method java/lang/StringBuilder.append:(J)Ljava/lang/StringBuilder;
      79: invokevirtual #22                 // Method java/lang/StringBuilder.toString:()Ljava/lang/String;
      82: invokeinterface #23,  2           // InterfaceMethod org/slf4j/Logger.debug:(Ljava/lang/String;)V
      87: iconst_0
      88: istore        9
      90: iload         9
      92: aload_3
      93: arraylength
      94: if_icmpge     132
      97: aload_3
      98: iload         9
     100: aaload
     101: astore        10
     103: aload         6
     105: aload_3
     106: arraylength
     107: invokevirtual #24                 // Method java/util/Random.nextInt:(I)I
     110: istore        11
     112: aload_3
     113: iload         9
     115: aload_3
     116: iload         11
     118: aaload
     119: aastore
     120: aload_3
     121: iload         11
     123: aload         10
     125: aastore
     126: iinc          9, 1
     129: goto          90
     132: iconst_0
     133: istore        9
     135: iload         9
     137: iload         5
     139: if_icmplt     161
     142: iload         9
     144: aload_3
     145: arraylength
     146: if_icmpge     322
     149: aload         4
     151: invokevirtual #25                 // Method java/util/ArrayList.size:()I
     154: aload_0
     155: getfield      #8                  // Field numSamples:I
     158: if_icmpge     322
     161: aload_1
     162: aload_3
     163: iload         9
     165: aaload
     166: aload_2
     167: getstatic     #26                 // Field org/apache/hadoop/mapred/Reporter.NULL:Lorg/apache/hadoop/mapred/Reporter;
     170: invokeinterface #27,  4           // InterfaceMethod org/apache/hadoop/mapred/InputFormat.getRecordReader:(Lorg/apache/hadoop/mapred/InputSplit;Lorg/apache/hadoop/mapred/JobConf;Lorg/apache/hadoop/mapred/Reporter;)Lorg/apache/hadoop/mapred/RecordReader;
     175: astore        10
     177: aload         10
     179: invokeinterface #28,  1           // InterfaceMethod org/apache/hadoop/mapred/RecordReader.createKey:()Ljava/lang/Object;
     184: astore        11
     186: aload         10
     188: invokeinterface #29,  1           // InterfaceMethod org/apache/hadoop/mapred/RecordReader.createValue:()Ljava/lang/Object;
     193: astore        12
     195: aload         10
     197: aload         11
     199: aload         12
     201: invokeinterface #30,  3           // InterfaceMethod org/apache/hadoop/mapred/RecordReader.next:(Ljava/lang/Object;Ljava/lang/Object;)Z
     206: ifeq          309
     209: aload         6
     211: invokevirtual #31                 // Method java/util/Random.nextDouble:()D
     214: aload_0
     215: getfield      #32                 // Field freq:D
     218: dcmpg
     219: ifgt          195
     222: aload         4
     224: invokevirtual #25                 // Method java/util/ArrayList.size:()I
     227: aload_0
     228: getfield      #8                  // Field numSamples:I
     231: if_icmpge     245
     234: aload         4
     236: aload         11
     238: invokevirtual #33                 // Method java/util/ArrayList.add:(Ljava/lang/Object;)Z
     241: pop
     242: goto          297
     245: aload         6
     247: aload_0
     248: getfield      #8                  // Field numSamples:I
     251: invokevirtual #24                 // Method java/util/Random.nextInt:(I)I
     254: istore        13
     256: iload         13
     258: aload_0
     259: getfield      #8                  // Field numSamples:I
     262: if_icmpeq     275
     265: aload         4
     267: iload         13
     269: aload         11
     271: invokevirtual #34                 // Method java/util/ArrayList.set:(ILjava/lang/Object;)Ljava/lang/Object;
     274: pop
     275: aload_0
     276: dup
     277: getfield      #32                 // Field freq:D
     280: aload_0
     281: getfield      #8                  // Field numSamples:I
     284: iconst_1
     285: isub
     286: i2d
     287: aload_0
     288: getfield      #8                  // Field numSamples:I
     291: i2d
     292: ddiv
     293: dmul
     294: putfield      #32                 // Field freq:D
     297: aload         10
     299: invokeinterface #28,  1           // InterfaceMethod org/apache/hadoop/mapred/RecordReader.createKey:()Ljava/lang/Object;
     304: astore        11
     306: goto          195
     309: aload         10
     311: invokeinterface #35,  1           // InterfaceMethod org/apache/hadoop/mapred/RecordReader.close:()V
     316: iinc          9, 1
     319: goto          135
     322: aload         4
     324: invokevirtual #36                 // Method java/util/ArrayList.toArray:()[Ljava/lang/Object;
     327: checkcast     #37                 // class "[Ljava/lang/Object;"
     330: areturn
}
