Compiled from "LazyOutputFormat.java"
class org.apache.hadoop.mapred.lib.LazyOutputFormat$LazyRecordWriter<K, V> extends org.apache.hadoop.mapred.lib.FilterOutputFormat$FilterRecordWriter<K, V> {
  final org.apache.hadoop.mapred.OutputFormat of;

  final java.lang.String name;

  final org.apache.hadoop.util.Progressable progress;

  final org.apache.hadoop.mapred.JobConf job;

  public org.apache.hadoop.mapred.lib.LazyOutputFormat$LazyRecordWriter(org.apache.hadoop.mapred.JobConf, org.apache.hadoop.mapred.OutputFormat, java.lang.String, org.apache.hadoop.util.Progressable) throws java.io.IOException;
    Code:
       0: aload_0
       1: invokespecial #1                  // Method org/apache/hadoop/mapred/lib/FilterOutputFormat$FilterRecordWriter."<init>":()V
       4: aload_0
       5: aload_2
       6: putfield      #2                  // Field of:Lorg/apache/hadoop/mapred/OutputFormat;
       9: aload_0
      10: aload_1
      11: putfield      #3                  // Field job:Lorg/apache/hadoop/mapred/JobConf;
      14: aload_0
      15: aload_3
      16: putfield      #4                  // Field name:Ljava/lang/String;
      19: aload_0
      20: aload         4
      22: putfield      #5                  // Field progress:Lorg/apache/hadoop/util/Progressable;
      25: return

  public void close(org.apache.hadoop.mapred.Reporter) throws java.io.IOException;
    Code:
       0: aload_0
       1: getfield      #6                  // Field rawWriter:Lorg/apache/hadoop/mapred/RecordWriter;
       4: ifnull        17
       7: aload_0
       8: getfield      #6                  // Field rawWriter:Lorg/apache/hadoop/mapred/RecordWriter;
      11: aload_1
      12: invokeinterface #7,  2            // InterfaceMethod org/apache/hadoop/mapred/RecordWriter.close:(Lorg/apache/hadoop/mapred/Reporter;)V
      17: return

  public void write(K, V) throws java.io.IOException;
    Code:
       0: aload_0
       1: getfield      #6                  // Field rawWriter:Lorg/apache/hadoop/mapred/RecordWriter;
       4: ifnonnull     11
       7: aload_0
       8: invokespecial #8                  // Method createRecordWriter:()V
      11: aload_0
      12: aload_1
      13: aload_2
      14: invokespecial #9                  // Method org/apache/hadoop/mapred/lib/FilterOutputFormat$FilterRecordWriter.write:(Ljava/lang/Object;Ljava/lang/Object;)V
      17: return

  private void createRecordWriter() throws java.io.IOException;
    Code:
       0: aload_0
       1: getfield      #3                  // Field job:Lorg/apache/hadoop/mapred/JobConf;
       4: invokestatic  #10                 // Method org/apache/hadoop/fs/FileSystem.get:(Lorg/apache/hadoop/conf/Configuration;)Lorg/apache/hadoop/fs/FileSystem;
       7: astore_1
       8: aload_0
       9: aload_0
      10: getfield      #2                  // Field of:Lorg/apache/hadoop/mapred/OutputFormat;
      13: aload_1
      14: aload_0
      15: getfield      #3                  // Field job:Lorg/apache/hadoop/mapred/JobConf;
      18: aload_0
      19: getfield      #4                  // Field name:Ljava/lang/String;
      22: aload_0
      23: getfield      #5                  // Field progress:Lorg/apache/hadoop/util/Progressable;
      26: invokeinterface #11,  5           // InterfaceMethod org/apache/hadoop/mapred/OutputFormat.getRecordWriter:(Lorg/apache/hadoop/fs/FileSystem;Lorg/apache/hadoop/mapred/JobConf;Ljava/lang/String;Lorg/apache/hadoop/util/Progressable;)Lorg/apache/hadoop/mapred/RecordWriter;
      31: putfield      #6                  // Field rawWriter:Lorg/apache/hadoop/mapred/RecordWriter;
      34: return
}
