Compiled from "LockOptions.java"
public class org.hibernate.LockOptions implements java.io.Serializable {
  public static final org.hibernate.LockOptions NONE;

  public static final org.hibernate.LockOptions READ;

  public static final org.hibernate.LockOptions UPGRADE;

  public static final int NO_WAIT;

  public static final int WAIT_FOREVER;

  public static final int SKIP_LOCKED;

  private org.hibernate.LockMode lockMode;

  private int timeout;

  private java.util.Map<java.lang.String, org.hibernate.LockMode> aliasSpecificLockModes;

  private boolean scope;

  public org.hibernate.LockOptions();
    Code:
       0: aload_0
       1: invokespecial #1                  // Method java/lang/Object."<init>":()V
       4: aload_0
       5: getstatic     #2                  // Field org/hibernate/LockMode.NONE:Lorg/hibernate/LockMode;
       8: putfield      #3                  // Field lockMode:Lorg/hibernate/LockMode;
      11: aload_0
      12: iconst_m1
      13: putfield      #5                  // Field timeout:I
      16: return

  public org.hibernate.LockOptions(org.hibernate.LockMode);
    Code:
       0: aload_0
       1: invokespecial #1                  // Method java/lang/Object."<init>":()V
       4: aload_0
       5: getstatic     #2                  // Field org/hibernate/LockMode.NONE:Lorg/hibernate/LockMode;
       8: putfield      #3                  // Field lockMode:Lorg/hibernate/LockMode;
      11: aload_0
      12: iconst_m1
      13: putfield      #5                  // Field timeout:I
      16: aload_0
      17: aload_1
      18: putfield      #3                  // Field lockMode:Lorg/hibernate/LockMode;
      21: return

  public org.hibernate.LockMode getLockMode();
    Code:
       0: aload_0
       1: getfield      #3                  // Field lockMode:Lorg/hibernate/LockMode;
       4: areturn

  public org.hibernate.LockOptions setLockMode(org.hibernate.LockMode);
    Code:
       0: aload_0
       1: aload_1
       2: putfield      #3                  // Field lockMode:Lorg/hibernate/LockMode;
       5: aload_0
       6: areturn

  public org.hibernate.LockOptions setAliasSpecificLockMode(java.lang.String, org.hibernate.LockMode);
    Code:
       0: aload_0
       1: getfield      #6                  // Field aliasSpecificLockModes:Ljava/util/Map;
       4: ifnonnull     18
       7: aload_0
       8: new           #7                  // class java/util/HashMap
      11: dup
      12: invokespecial #8                  // Method java/util/HashMap."<init>":()V
      15: putfield      #6                  // Field aliasSpecificLockModes:Ljava/util/Map;
      18: aload_0
      19: getfield      #6                  // Field aliasSpecificLockModes:Ljava/util/Map;
      22: aload_1
      23: aload_2
      24: invokeinterface #9,  3            // InterfaceMethod java/util/Map.put:(Ljava/lang/Object;Ljava/lang/Object;)Ljava/lang/Object;
      29: pop
      30: aload_0
      31: areturn

  public org.hibernate.LockMode getAliasSpecificLockMode(java.lang.String);
    Code:
       0: aload_0
       1: getfield      #6                  // Field aliasSpecificLockModes:Ljava/util/Map;
       4: ifnonnull     9
       7: aconst_null
       8: areturn
       9: aload_0
      10: getfield      #6                  // Field aliasSpecificLockModes:Ljava/util/Map;
      13: aload_1
      14: invokeinterface #10,  2           // InterfaceMethod java/util/Map.get:(Ljava/lang/Object;)Ljava/lang/Object;
      19: checkcast     #11                 // class org/hibernate/LockMode
      22: areturn

  public org.hibernate.LockMode getEffectiveLockMode(java.lang.String);
    Code:
       0: aload_0
       1: aload_1
       2: invokevirtual #12                 // Method getAliasSpecificLockMode:(Ljava/lang/String;)Lorg/hibernate/LockMode;
       5: astore_2
       6: aload_2
       7: ifnonnull     15
      10: aload_0
      11: getfield      #3                  // Field lockMode:Lorg/hibernate/LockMode;
      14: astore_2
      15: aload_2
      16: ifnonnull     25
      19: getstatic     #2                  // Field org/hibernate/LockMode.NONE:Lorg/hibernate/LockMode;
      22: goto          26
      25: aload_2
      26: areturn

  public boolean hasAliasSpecificLockModes();
    Code:
       0: aload_0
       1: getfield      #6                  // Field aliasSpecificLockModes:Ljava/util/Map;
       4: ifnull        23
       7: aload_0
       8: getfield      #6                  // Field aliasSpecificLockModes:Ljava/util/Map;
      11: invokeinterface #13,  1           // InterfaceMethod java/util/Map.isEmpty:()Z
      16: ifne          23
      19: iconst_1
      20: goto          24
      23: iconst_0
      24: ireturn

  public int getAliasLockCount();
    Code:
       0: aload_0
       1: getfield      #6                  // Field aliasSpecificLockModes:Ljava/util/Map;
       4: ifnonnull     9
       7: iconst_0
       8: ireturn
       9: aload_0
      10: getfield      #6                  // Field aliasSpecificLockModes:Ljava/util/Map;
      13: invokeinterface #14,  1           // InterfaceMethod java/util/Map.size:()I
      18: ireturn

  public java.util.Iterator getAliasLockIterator();
    Code:
       0: aload_0
       1: getfield      #6                  // Field aliasSpecificLockModes:Ljava/util/Map;
       4: ifnonnull     16
       7: invokestatic  #15                 // Method java/util/Collections.emptyList:()Ljava/util/List;
      10: invokeinterface #16,  1           // InterfaceMethod java/util/List.iterator:()Ljava/util/Iterator;
      15: areturn
      16: aload_0
      17: getfield      #6                  // Field aliasSpecificLockModes:Ljava/util/Map;
      20: invokeinterface #17,  1           // InterfaceMethod java/util/Map.entrySet:()Ljava/util/Set;
      25: invokeinterface #18,  1           // InterfaceMethod java/util/Set.iterator:()Ljava/util/Iterator;
      30: areturn

  public org.hibernate.LockMode findGreatestLockMode();
    Code:
       0: aload_0
       1: invokevirtual #19                 // Method getLockMode:()Lorg/hibernate/LockMode;
       4: astore_1
       5: aload_1
       6: ifnonnull     13
       9: getstatic     #2                  // Field org/hibernate/LockMode.NONE:Lorg/hibernate/LockMode;
      12: astore_1
      13: aload_0
      14: getfield      #6                  // Field aliasSpecificLockModes:Ljava/util/Map;
      17: ifnonnull     22
      20: aload_1
      21: areturn
      22: aload_0
      23: getfield      #6                  // Field aliasSpecificLockModes:Ljava/util/Map;
      26: invokeinterface #20,  1           // InterfaceMethod java/util/Map.values:()Ljava/util/Collection;
      31: invokeinterface #21,  1           // InterfaceMethod java/util/Collection.iterator:()Ljava/util/Iterator;
      36: astore_2
      37: aload_2
      38: invokeinterface #22,  1           // InterfaceMethod java/util/Iterator.hasNext:()Z
      43: ifeq          69
      46: aload_2
      47: invokeinterface #23,  1           // InterfaceMethod java/util/Iterator.next:()Ljava/lang/Object;
      52: checkcast     #11                 // class org/hibernate/LockMode
      55: astore_3
      56: aload_3
      57: aload_1
      58: invokevirtual #24                 // Method org/hibernate/LockMode.greaterThan:(Lorg/hibernate/LockMode;)Z
      61: ifeq          66
      64: aload_3
      65: astore_1
      66: goto          37
      69: aload_1
      70: areturn

  public int getTimeOut();
    Code:
       0: aload_0
       1: getfield      #5                  // Field timeout:I
       4: ireturn

  public org.hibernate.LockOptions setTimeOut(int);
    Code:
       0: aload_0
       1: iload_1
       2: putfield      #5                  // Field timeout:I
       5: aload_0
       6: areturn

  public boolean getScope();
    Code:
       0: aload_0
       1: getfield      #25                 // Field scope:Z
       4: ireturn

  public org.hibernate.LockOptions setScope(boolean);
    Code:
       0: aload_0
       1: iload_1
       2: putfield      #25                 // Field scope:Z
       5: aload_0
       6: areturn

  public org.hibernate.LockOptions makeCopy();
    Code:
       0: new           #4                  // class org/hibernate/LockOptions
       3: dup
       4: invokespecial #26                 // Method "<init>":()V
       7: astore_1
       8: aload_0
       9: aload_1
      10: invokestatic  #27                 // Method copy:(Lorg/hibernate/LockOptions;Lorg/hibernate/LockOptions;)Lorg/hibernate/LockOptions;
      13: pop
      14: aload_1
      15: areturn

  public static org.hibernate.LockOptions copy(org.hibernate.LockOptions, org.hibernate.LockOptions);
    Code:
       0: aload_1
       1: aload_0
       2: invokevirtual #19                 // Method getLockMode:()Lorg/hibernate/LockMode;
       5: invokevirtual #28                 // Method setLockMode:(Lorg/hibernate/LockMode;)Lorg/hibernate/LockOptions;
       8: pop
       9: aload_1
      10: aload_0
      11: invokevirtual #29                 // Method getScope:()Z
      14: invokevirtual #30                 // Method setScope:(Z)Lorg/hibernate/LockOptions;
      17: pop
      18: aload_1
      19: aload_0
      20: invokevirtual #31                 // Method getTimeOut:()I
      23: invokevirtual #32                 // Method setTimeOut:(I)Lorg/hibernate/LockOptions;
      26: pop
      27: aload_0
      28: getfield      #6                  // Field aliasSpecificLockModes:Ljava/util/Map;
      31: ifnull        49
      34: aload_1
      35: new           #7                  // class java/util/HashMap
      38: dup
      39: aload_0
      40: getfield      #6                  // Field aliasSpecificLockModes:Ljava/util/Map;
      43: invokespecial #33                 // Method java/util/HashMap."<init>":(Ljava/util/Map;)V
      46: putfield      #6                  // Field aliasSpecificLockModes:Ljava/util/Map;
      49: aload_1
      50: areturn

  static {};
    Code:
       0: new           #4                  // class org/hibernate/LockOptions
       3: dup
       4: getstatic     #2                  // Field org/hibernate/LockMode.NONE:Lorg/hibernate/LockMode;
       7: invokespecial #34                 // Method "<init>":(Lorg/hibernate/LockMode;)V
      10: putstatic     #35                 // Field NONE:Lorg/hibernate/LockOptions;
      13: new           #4                  // class org/hibernate/LockOptions
      16: dup
      17: getstatic     #36                 // Field org/hibernate/LockMode.READ:Lorg/hibernate/LockMode;
      20: invokespecial #34                 // Method "<init>":(Lorg/hibernate/LockMode;)V
      23: putstatic     #37                 // Field READ:Lorg/hibernate/LockOptions;
      26: new           #4                  // class org/hibernate/LockOptions
      29: dup
      30: getstatic     #38                 // Field org/hibernate/LockMode.UPGRADE:Lorg/hibernate/LockMode;
      33: invokespecial #34                 // Method "<init>":(Lorg/hibernate/LockMode;)V
      36: putstatic     #39                 // Field UPGRADE:Lorg/hibernate/LockOptions;
      39: return
}
