Compiled from "JettyHandlerWrappers.java"
final class org.springframework.boot.web.embedded.jetty.JettyHandlerWrappers {
  private org.springframework.boot.web.embedded.jetty.JettyHandlerWrappers();
    Code:
       0: aload_0
       1: invokespecial #1                  // Method java/lang/Object."<init>":()V
       4: return

  static org.eclipse.jetty.server.handler.HandlerWrapper createGzipHandlerWrapper(org.springframework.boot.web.server.Compression);
    Code:
       0: new           #2                  // class org/eclipse/jetty/server/handler/gzip/GzipHandler
       3: dup
       4: invokespecial #3                  // Method org/eclipse/jetty/server/handler/gzip/GzipHandler."<init>":()V
       7: astore_1
       8: aload_1
       9: aload_0
      10: invokevirtual #4                  // Method org/springframework/boot/web/server/Compression.getMinResponseSize:()Lorg/springframework/util/unit/DataSize;
      13: invokevirtual #5                  // Method org/springframework/util/unit/DataSize.toBytes:()J
      16: l2i
      17: invokevirtual #6                  // Method org/eclipse/jetty/server/handler/gzip/GzipHandler.setMinGzipSize:(I)V
      20: aload_1
      21: aload_0
      22: invokevirtual #7                  // Method org/springframework/boot/web/server/Compression.getMimeTypes:()[Ljava/lang/String;
      25: invokevirtual #8                  // Method org/eclipse/jetty/server/handler/gzip/GzipHandler.setIncludedMimeTypes:([Ljava/lang/String;)V
      28: invokestatic  #9                  // Method org/eclipse/jetty/http/HttpMethod.values:()[Lorg/eclipse/jetty/http/HttpMethod;
      31: astore_2
      32: aload_2
      33: arraylength
      34: istore_3
      35: iconst_0
      36: istore        4
      38: iload         4
      40: iload_3
      41: if_icmpge     72
      44: aload_2
      45: iload         4
      47: aaload
      48: astore        5
      50: aload_1
      51: iconst_1
      52: anewarray     #10                 // class java/lang/String
      55: dup
      56: iconst_0
      57: aload         5
      59: invokevirtual #11                 // Method org/eclipse/jetty/http/HttpMethod.name:()Ljava/lang/String;
      62: aastore
      63: invokevirtual #12                 // Method org/eclipse/jetty/server/handler/gzip/GzipHandler.addIncludedMethods:([Ljava/lang/String;)V
      66: iinc          4, 1
      69: goto          38
      72: aload_0
      73: invokevirtual #13                 // Method org/springframework/boot/web/server/Compression.getExcludedUserAgents:()[Ljava/lang/String;
      76: ifnull        87
      79: aload_1
      80: aload_0
      81: invokevirtual #13                 // Method org/springframework/boot/web/server/Compression.getExcludedUserAgents:()[Ljava/lang/String;
      84: invokevirtual #14                 // Method org/eclipse/jetty/server/handler/gzip/GzipHandler.setExcludedAgentPatterns:([Ljava/lang/String;)V
      87: aload_1
      88: areturn

  static org.eclipse.jetty.server.handler.HandlerWrapper createServerHeaderHandlerWrapper(java.lang.String);
    Code:
       0: new           #15                 // class org/springframework/boot/web/embedded/jetty/JettyHandlerWrappers$ServerHeaderHandler
       3: dup
       4: aload_0
       5: invokespecial #16                 // Method org/springframework/boot/web/embedded/jetty/JettyHandlerWrappers$ServerHeaderHandler."<init>":(Ljava/lang/String;)V
       8: areturn
}
