Compiled from "JAXWSThreadFactory.java"
class org.apache.axis2.jaxws.utility.JAXWSThreadFactory$2 implements java.security.PrivilegedExceptionAction {
  final java.lang.Runnable val$r;

  final org.apache.axis2.jaxws.utility.JAXWSThreadFactory this$0;

  org.apache.axis2.jaxws.utility.JAXWSThreadFactory$2(org.apache.axis2.jaxws.utility.JAXWSThreadFactory, java.lang.Runnable);
    Code:
       0: aload_0
       1: aload_1
       2: putfield      #1                  // Field this$0:Lorg/apache/axis2/jaxws/utility/JAXWSThreadFactory;
       5: aload_0
       6: aload_2
       7: putfield      #2                  // Field val$r:Ljava/lang/Runnable;
      10: aload_0
      11: invokespecial #3                  // Method java/lang/Object."<init>":()V
      14: return

  public java.lang.Object run();
    Code:
       0: new           #4                  // class java/lang/Thread
       3: dup
       4: aload_0
       5: getfield      #1                  // Field this$0:Lorg/apache/axis2/jaxws/utility/JAXWSThreadFactory;
       8: invokestatic  #5                  // Method org/apache/axis2/jaxws/utility/JAXWSThreadFactory.access$100:(Lorg/apache/axis2/jaxws/utility/JAXWSThreadFactory;)Ljava/lang/ThreadGroup;
      11: aload_0
      12: getfield      #2                  // Field val$r:Ljava/lang/Runnable;
      15: invokespecial #6                  // Method java/lang/Thread."<init>":(Ljava/lang/ThreadGroup;Ljava/lang/Runnable;)V
      18: astore_1
      19: aload_1
      20: iconst_1
      21: invokevirtual #7                  // Method java/lang/Thread.setDaemon:(Z)V
      24: aload_1
      25: areturn
}
