Compiled from "Map.scala"
public final class scalaz.$eq$eq$greater$greater$ extends scalaz.MapInstances {
  public static final scalaz.$eq$eq$greater$greater$ MODULE$;

  public static {};
    Code:
       0: new           #2                  // class scalaz/$eq$eq$greater$greater$
       3: dup
       4: invokespecial #56                 // Method "<init>":()V
       7: putstatic     #58                 // Field MODULE$:Lscalaz/$eq$eq$greater$greater$;
      10: return

  public final <A, B> scalaz.$eq$eq$greater$greater<A, B> apply(scala.collection.immutable.Seq<scala.Tuple2<A, B>>, scalaz.Order<A>);
    Code:
       0: aload_1
       1: getstatic     #66                 // Field scalaz/$eq$eq$greater$greater$Tip$.MODULE$:Lscalaz/$eq$eq$greater$greater$Tip$;
       4: invokevirtual #69                 // Method scalaz/$eq$eq$greater$greater$Tip$.apply:()Lscalaz/$eq$eq$greater$greater;
       7: aload_2
       8: invokedynamic #90,  0             // InvokeDynamic #0:apply:(Lscalaz/Order;)Lscala/Function2;
      13: invokeinterface #96,  3           // InterfaceMethod scala/collection/immutable/Seq.foldLeft:(Ljava/lang/Object;Lscala/Function2;)Ljava/lang/Object;
      18: checkcast     #14                 // class scalaz/$eq$eq$greater$greater
      21: areturn

  public final <A, B> scalaz.$eq$eq$greater$greater<A, B> empty();
    Code:
       0: getstatic     #66                 // Field scalaz/$eq$eq$greater$greater$Tip$.MODULE$:Lscalaz/$eq$eq$greater$greater$Tip$;
       3: invokevirtual #69                 // Method scalaz/$eq$eq$greater$greater$Tip$.apply:()Lscalaz/$eq$eq$greater$greater;
       6: areturn

  public final <A, B> scalaz.$eq$eq$greater$greater<A, B> singleton(A, B);
    Code:
       0: new           #12                 // class scalaz/$eq$eq$greater$greater$Bin
       3: dup
       4: aload_1
       5: aload_2
       6: getstatic     #66                 // Field scalaz/$eq$eq$greater$greater$Tip$.MODULE$:Lscalaz/$eq$eq$greater$greater$Tip$;
       9: invokevirtual #69                 // Method scalaz/$eq$eq$greater$greater$Tip$.apply:()Lscalaz/$eq$eq$greater$greater;
      12: getstatic     #66                 // Field scalaz/$eq$eq$greater$greater$Tip$.MODULE$:Lscalaz/$eq$eq$greater$greater$Tip$;
      15: invokevirtual #69                 // Method scalaz/$eq$eq$greater$greater$Tip$.apply:()Lscalaz/$eq$eq$greater$greater;
      18: invokespecial #108                // Method scalaz/$eq$eq$greater$greater$Bin."<init>":(Ljava/lang/Object;Ljava/lang/Object;Lscalaz/$eq$eq$greater$greater;Lscalaz/$eq$eq$greater$greater;)V
      21: areturn

  public final <A, B> scalaz.$eq$eq$greater$greater<A, B> fromList(scala.collection.immutable.List<scala.Tuple2<A, B>>, scalaz.Order<A>);
    Code:
       0: aload_1
       1: getstatic     #66                 // Field scalaz/$eq$eq$greater$greater$Tip$.MODULE$:Lscalaz/$eq$eq$greater$greater$Tip$;
       4: invokevirtual #69                 // Method scalaz/$eq$eq$greater$greater$Tip$.apply:()Lscalaz/$eq$eq$greater$greater;
       7: aload_2
       8: invokedynamic #119,  0            // InvokeDynamic #1:apply:(Lscalaz/Order;)Lscala/Function2;
      13: invokevirtual #122                // Method scala/collection/immutable/List.foldLeft:(Ljava/lang/Object;Lscala/Function2;)Ljava/lang/Object;
      16: checkcast     #14                 // class scalaz/$eq$eq$greater$greater
      19: areturn

  public final <A, B> scalaz.$eq$eq$greater$greater<A, B> fromIList(scalaz.IList<scala.Tuple2<A, B>>, scalaz.Order<A>);
    Code:
       0: aload_1
       1: getstatic     #66                 // Field scalaz/$eq$eq$greater$greater$Tip$.MODULE$:Lscalaz/$eq$eq$greater$greater$Tip$;
       4: invokevirtual #69                 // Method scalaz/$eq$eq$greater$greater$Tip$.apply:()Lscalaz/$eq$eq$greater$greater;
       7: astore_3
       8: ifnonnull     13
      11: aconst_null
      12: athrow
      13: aload_1
      14: aload_3
      15: astore        5
      17: astore        4
      19: aload         4
      21: instanceof    #129                // class scalaz/INil
      24: ifeq          30
      27: aload         5
      29: areturn
      30: aload         4
      32: instanceof    #131                // class scalaz/ICons
      35: ifeq          79
      38: aload         4
      40: checkcast     #131                // class scalaz/ICons
      43: astore        6
      45: aload         6
      47: invokevirtual #135                // Method scalaz/ICons.head:()Ljava/lang/Object;
      50: astore        7
      52: aload         6
      54: invokevirtual #139                // Method scalaz/ICons.tail:()Lscalaz/IList;
      57: aload         7
      59: checkcast     #141                // class scala/Tuple2
      62: astore        8
      64: aload_2
      65: aload         5
      67: aload         8
      69: invokestatic  #144                // Method $anonfun$fromIList$1:(Lscalaz/Order;Lscalaz/$eq$eq$greater$greater;Lscala/Tuple2;)Lscalaz/$eq$eq$greater$greater;
      72: astore        5
      74: astore        4
      76: goto          19
      79: new           #146                // class scala/MatchError
      82: dup
      83: aload         4
      85: invokespecial #149                // Method scala/MatchError."<init>":(Ljava/lang/Object;)V
      88: athrow

  public final <A, B> scalaz.$eq$eq$greater$greater<A, B> fromListWith(scala.collection.immutable.List<scala.Tuple2<A, B>>, scala.Function2<B, B, B>, scalaz.Order<A>);
    Code:
       0: aload_2
       1: invokedynamic #171,  0            // InvokeDynamic #2:apply:(Lscala/Function2;)Lscala/Function3;
       6: astore        4
       8: aload_1
       9: getstatic     #66                 // Field scalaz/$eq$eq$greater$greater$Tip$.MODULE$:Lscalaz/$eq$eq$greater$greater$Tip$;
      12: invokevirtual #69                 // Method scalaz/$eq$eq$greater$greater$Tip$.apply:()Lscalaz/$eq$eq$greater$greater;
      15: aload         4
      17: aload_3
      18: invokedynamic #179,  0            // InvokeDynamic #3:apply:(Lscala/Function3;Lscalaz/Order;)Lscala/Function2;
      23: invokevirtual #122                // Method scala/collection/immutable/List.foldLeft:(Ljava/lang/Object;Lscala/Function2;)Ljava/lang/Object;
      26: checkcast     #14                 // class scalaz/$eq$eq$greater$greater
      29: areturn

  public final <A, B> scalaz.$eq$eq$greater$greater<A, B> fromIListWith(scalaz.IList<scala.Tuple2<A, B>>, scala.Function2<B, B, B>, scalaz.Order<A>);
    Code:
       0: aload_2
       1: invokedynamic #191,  0            // InvokeDynamic #4:apply:(Lscala/Function2;)Lscala/Function3;
       6: astore        4
       8: aload_1
       9: getstatic     #66                 // Field scalaz/$eq$eq$greater$greater$Tip$.MODULE$:Lscalaz/$eq$eq$greater$greater$Tip$;
      12: invokevirtual #69                 // Method scalaz/$eq$eq$greater$greater$Tip$.apply:()Lscalaz/$eq$eq$greater$greater;
      15: astore        5
      17: ifnonnull     22
      20: aconst_null
      21: athrow
      22: aload_1
      23: aload         5
      25: astore        7
      27: astore        6
      29: aload         6
      31: instanceof    #129                // class scalaz/INil
      34: ifeq          42
      37: aload         7
      39: goto          798
      42: aload         6
      44: instanceof    #131                // class scalaz/ICons
      47: ifeq          788
      50: aload         6
      52: checkcast     #131                // class scalaz/ICons
      55: astore        8
      57: aload         8
      59: invokevirtual #135                // Method scalaz/ICons.head:()Ljava/lang/Object;
      62: astore        9
      64: aload         8
      66: invokevirtual #139                // Method scalaz/ICons.tail:()Lscalaz/IList;
      69: aload         7
      71: aload         9
      73: checkcast     #141                // class scala/Tuple2
      76: astore        11
      78: checkcast     #14                 // class scalaz/$eq$eq$greater$greater
      81: astore        10
      83: aload         10
      85: aload         11
      87: invokevirtual #194                // Method scala/Tuple2._1:()Ljava/lang/Object;
      90: aload         11
      92: invokevirtual #197                // Method scala/Tuple2._2:()Ljava/lang/Object;
      95: astore        13
      97: astore        12
      99: ifnonnull     104
     102: aconst_null
     103: athrow
     104: aload         10
     106: instanceof    #17                 // class scalaz/$eq$eq$greater$greater$Tip
     109: ifeq          125
     112: getstatic     #58                 // Field MODULE$:Lscalaz/$eq$eq$greater$greater$;
     115: aload         12
     117: aload         13
     119: invokevirtual #199                // Method singleton:(Ljava/lang/Object;Ljava/lang/Object;)Lscalaz/$eq$eq$greater$greater;
     122: goto          757
     125: aload         10
     127: instanceof    #12                 // class scalaz/$eq$eq$greater$greater$Bin
     130: ifeq          747
     133: aload         10
     135: checkcast     #12                 // class scalaz/$eq$eq$greater$greater$Bin
     138: astore        14
     140: aload         14
     142: invokevirtual #201                // Method scalaz/$eq$eq$greater$greater$Bin.k:()Ljava/lang/Object;
     145: astore        15
     147: aload         14
     149: invokevirtual #204                // Method scalaz/$eq$eq$greater$greater$Bin.v:()Ljava/lang/Object;
     152: astore        16
     154: aload         14
     156: invokevirtual #206                // Method scalaz/$eq$eq$greater$greater$Bin.l:()Lscalaz/$eq$eq$greater$greater;
     159: astore        17
     161: aload         14
     163: invokevirtual #209                // Method scalaz/$eq$eq$greater$greater$Bin.r:()Lscalaz/$eq$eq$greater$greater;
     166: astore        18
     168: aload_3
     169: aload         12
     171: aload         15
     173: invokeinterface #215,  3          // InterfaceMethod scalaz/Order.order:(Ljava/lang/Object;Ljava/lang/Object;)Lscalaz/Ordering;
     178: astore        19
     180: getstatic     #218                // Field scalaz/Ordering$LT$.MODULE$:Lscalaz/Ordering$LT$;
     183: aload         19
     185: invokevirtual #224                // Method java/lang/Object.equals:(Ljava/lang/Object;)Z
     188: ifeq          440
     191: getstatic     #58                 // Field MODULE$:Lscalaz/$eq$eq$greater$greater$;
     194: aload         15
     196: aload         16
     198: aload         17
     200: ifnonnull     205
     203: aconst_null
     204: athrow
     205: aload         17
     207: instanceof    #17                 // class scalaz/$eq$eq$greater$greater$Tip
     210: ifeq          226
     213: getstatic     #58                 // Field MODULE$:Lscalaz/$eq$eq$greater$greater$;
     216: aload         12
     218: aload         13
     220: invokevirtual #199                // Method singleton:(Ljava/lang/Object;Ljava/lang/Object;)Lscalaz/$eq$eq$greater$greater;
     223: goto          414
     226: aload         17
     228: instanceof    #12                 // class scalaz/$eq$eq$greater$greater$Bin
     231: ifeq          404
     234: aload         17
     236: checkcast     #12                 // class scalaz/$eq$eq$greater$greater$Bin
     239: astore        20
     241: aload         20
     243: invokevirtual #201                // Method scalaz/$eq$eq$greater$greater$Bin.k:()Ljava/lang/Object;
     246: astore        21
     248: aload         20
     250: invokevirtual #204                // Method scalaz/$eq$eq$greater$greater$Bin.v:()Ljava/lang/Object;
     253: astore        22
     255: aload         20
     257: invokevirtual #206                // Method scalaz/$eq$eq$greater$greater$Bin.l:()Lscalaz/$eq$eq$greater$greater;
     260: astore        23
     262: aload         20
     264: invokevirtual #209                // Method scalaz/$eq$eq$greater$greater$Bin.r:()Lscalaz/$eq$eq$greater$greater;
     267: astore        24
     269: aload_3
     270: aload         12
     272: aload         21
     274: invokeinterface #215,  3          // InterfaceMethod scalaz/Order.order:(Ljava/lang/Object;Ljava/lang/Object;)Lscalaz/Ordering;
     279: astore        25
     281: getstatic     #218                // Field scalaz/Ordering$LT$.MODULE$:Lscalaz/Ordering$LT$;
     284: aload         25
     286: invokevirtual #224                // Method java/lang/Object.equals:(Ljava/lang/Object;)Z
     289: ifeq          319
     292: getstatic     #58                 // Field MODULE$:Lscalaz/$eq$eq$greater$greater$;
     295: aload         21
     297: aload         22
     299: aload         23
     301: aload         4
     303: aload         12
     305: aload         13
     307: aload_3
     308: invokevirtual #228                // Method scalaz/$eq$eq$greater$greater.insertWithKey:(Lscala/Function3;Ljava/lang/Object;Ljava/lang/Object;Lscalaz/Order;)Lscalaz/$eq$eq$greater$greater;
     311: aload         24
     313: invokevirtual #232                // Method balanceL:(Ljava/lang/Object;Ljava/lang/Object;Lscalaz/$eq$eq$greater$greater;Lscalaz/$eq$eq$greater$greater;)Lscalaz/$eq$eq$greater$greater;
     316: goto          414
     319: getstatic     #235                // Field scalaz/Ordering$GT$.MODULE$:Lscalaz/Ordering$GT$;
     322: aload         25
     324: invokevirtual #224                // Method java/lang/Object.equals:(Ljava/lang/Object;)Z
     327: ifeq          357
     330: getstatic     #58                 // Field MODULE$:Lscalaz/$eq$eq$greater$greater$;
     333: aload         21
     335: aload         22
     337: aload         23
     339: aload         24
     341: aload         4
     343: aload         12
     345: aload         13
     347: aload_3
     348: invokevirtual #228                // Method scalaz/$eq$eq$greater$greater.insertWithKey:(Lscala/Function3;Ljava/lang/Object;Ljava/lang/Object;Lscalaz/Order;)Lscalaz/$eq$eq$greater$greater;
     351: invokevirtual #238                // Method balanceR:(Ljava/lang/Object;Ljava/lang/Object;Lscalaz/$eq$eq$greater$greater;Lscalaz/$eq$eq$greater$greater;)Lscalaz/$eq$eq$greater$greater;
     354: goto          414
     357: getstatic     #241                // Field scalaz/Ordering$EQ$.MODULE$:Lscalaz/Ordering$EQ$;
     360: aload         25
     362: invokevirtual #224                // Method java/lang/Object.equals:(Ljava/lang/Object;)Z
     365: ifeq          394
     368: new           #12                 // class scalaz/$eq$eq$greater$greater$Bin
     371: dup
     372: aload         12
     374: aload_2
     375: aload         13
     377: aload         22
     379: invokeinterface #245,  3          // InterfaceMethod scala/Function2.apply:(Ljava/lang/Object;Ljava/lang/Object;)Ljava/lang/Object;
     384: aload         23
     386: aload         24
     388: invokespecial #108                // Method scalaz/$eq$eq$greater$greater$Bin."<init>":(Ljava/lang/Object;Ljava/lang/Object;Lscalaz/$eq$eq$greater$greater;Lscalaz/$eq$eq$greater$greater;)V
     391: goto          414
     394: new           #146                // class scala/MatchError
     397: dup
     398: aload         25
     400: invokespecial #149                // Method scala/MatchError."<init>":(Ljava/lang/Object;)V
     403: athrow
     404: new           #146                // class scala/MatchError
     407: dup
     408: aload         17
     410: invokespecial #149                // Method scala/MatchError."<init>":(Ljava/lang/Object;)V
     413: athrow
     414: aconst_null
     415: astore        20
     417: aconst_null
     418: astore        21
     420: aconst_null
     421: astore        22
     423: aconst_null
     424: astore        23
     426: aconst_null
     427: astore        24
     429: aconst_null
     430: astore        25
     432: aload         18
     434: invokevirtual #232                // Method balanceL:(Ljava/lang/Object;Ljava/lang/Object;Lscalaz/$eq$eq$greater$greater;Lscalaz/$eq$eq$greater$greater;)Lscalaz/$eq$eq$greater$greater;
     437: goto          757
     440: getstatic     #235                // Field scalaz/Ordering$GT$.MODULE$:Lscalaz/Ordering$GT$;
     443: aload         19
     445: invokevirtual #224                // Method java/lang/Object.equals:(Ljava/lang/Object;)Z
     448: ifeq          700
     451: getstatic     #58                 // Field MODULE$:Lscalaz/$eq$eq$greater$greater$;
     454: aload         15
     456: aload         16
     458: aload         17
     460: aload         18
     462: ifnonnull     467
     465: aconst_null
     466: athrow
     467: aload         18
     469: instanceof    #17                 // class scalaz/$eq$eq$greater$greater$Tip
     472: ifeq          488
     475: getstatic     #58                 // Field MODULE$:Lscalaz/$eq$eq$greater$greater$;
     478: aload         12
     480: aload         13
     482: invokevirtual #199                // Method singleton:(Ljava/lang/Object;Ljava/lang/Object;)Lscalaz/$eq$eq$greater$greater;
     485: goto          676
     488: aload         18
     490: instanceof    #12                 // class scalaz/$eq$eq$greater$greater$Bin
     493: ifeq          666
     496: aload         18
     498: checkcast     #12                 // class scalaz/$eq$eq$greater$greater$Bin
     501: astore        26
     503: aload         26
     505: invokevirtual #201                // Method scalaz/$eq$eq$greater$greater$Bin.k:()Ljava/lang/Object;
     508: astore        27
     510: aload         26
     512: invokevirtual #204                // Method scalaz/$eq$eq$greater$greater$Bin.v:()Ljava/lang/Object;
     515: astore        28
     517: aload         26
     519: invokevirtual #206                // Method scalaz/$eq$eq$greater$greater$Bin.l:()Lscalaz/$eq$eq$greater$greater;
     522: astore        29
     524: aload         26
     526: invokevirtual #209                // Method scalaz/$eq$eq$greater$greater$Bin.r:()Lscalaz/$eq$eq$greater$greater;
     529: astore        30
     531: aload_3
     532: aload         12
     534: aload         27
     536: invokeinterface #215,  3          // InterfaceMethod scalaz/Order.order:(Ljava/lang/Object;Ljava/lang/Object;)Lscalaz/Ordering;
     541: astore        31
     543: getstatic     #218                // Field scalaz/Ordering$LT$.MODULE$:Lscalaz/Ordering$LT$;
     546: aload         31
     548: invokevirtual #224                // Method java/lang/Object.equals:(Ljava/lang/Object;)Z
     551: ifeq          581
     554: getstatic     #58                 // Field MODULE$:Lscalaz/$eq$eq$greater$greater$;
     557: aload         27
     559: aload         28
     561: aload         29
     563: aload         4
     565: aload         12
     567: aload         13
     569: aload_3
     570: invokevirtual #228                // Method scalaz/$eq$eq$greater$greater.insertWithKey:(Lscala/Function3;Ljava/lang/Object;Ljava/lang/Object;Lscalaz/Order;)Lscalaz/$eq$eq$greater$greater;
     573: aload         30
     575: invokevirtual #232                // Method balanceL:(Ljava/lang/Object;Ljava/lang/Object;Lscalaz/$eq$eq$greater$greater;Lscalaz/$eq$eq$greater$greater;)Lscalaz/$eq$eq$greater$greater;
     578: goto          676
     581: getstatic     #235                // Field scalaz/Ordering$GT$.MODULE$:Lscalaz/Ordering$GT$;
     584: aload         31
     586: invokevirtual #224                // Method java/lang/Object.equals:(Ljava/lang/Object;)Z
     589: ifeq          619
     592: getstatic     #58                 // Field MODULE$:Lscalaz/$eq$eq$greater$greater$;
     595: aload         27
     597: aload         28
     599: aload         29
     601: aload         30
     603: aload         4
     605: aload         12
     607: aload         13
     609: aload_3
     610: invokevirtual #228                // Method scalaz/$eq$eq$greater$greater.insertWithKey:(Lscala/Function3;Ljava/lang/Object;Ljava/lang/Object;Lscalaz/Order;)Lscalaz/$eq$eq$greater$greater;
     613: invokevirtual #238                // Method balanceR:(Ljava/lang/Object;Ljava/lang/Object;Lscalaz/$eq$eq$greater$greater;Lscalaz/$eq$eq$greater$greater;)Lscalaz/$eq$eq$greater$greater;
     616: goto          676
     619: getstatic     #241                // Field scalaz/Ordering$EQ$.MODULE$:Lscalaz/Ordering$EQ$;
     622: aload         31
     624: invokevirtual #224                // Method java/lang/Object.equals:(Ljava/lang/Object;)Z
     627: ifeq          656
     630: new           #12                 // class scalaz/$eq$eq$greater$greater$Bin
     633: dup
     634: aload         12
     636: aload_2
     637: aload         13
     639: aload         28
     641: invokeinterface #245,  3          // InterfaceMethod scala/Function2.apply:(Ljava/lang/Object;Ljava/lang/Object;)Ljava/lang/Object;
     646: aload         29
     648: aload         30
     650: invokespecial #108                // Method scalaz/$eq$eq$greater$greater$Bin."<init>":(Ljava/lang/Object;Ljava/lang/Object;Lscalaz/$eq$eq$greater$greater;Lscalaz/$eq$eq$greater$greater;)V
     653: goto          676
     656: new           #146                // class scala/MatchError
     659: dup
     660: aload         31
     662: invokespecial #149                // Method scala/MatchError."<init>":(Ljava/lang/Object;)V
     665: athrow
     666: new           #146                // class scala/MatchError
     669: dup
     670: aload         18
     672: invokespecial #149                // Method scala/MatchError."<init>":(Ljava/lang/Object;)V
     675: athrow
     676: aconst_null
     677: astore        26
     679: aconst_null
     680: astore        27
     682: aconst_null
     683: astore        28
     685: aconst_null
     686: astore        29
     688: aconst_null
     689: astore        30
     691: aconst_null
     692: astore        31
     694: invokevirtual #238                // Method balanceR:(Ljava/lang/Object;Ljava/lang/Object;Lscalaz/$eq$eq$greater$greater;Lscalaz/$eq$eq$greater$greater;)Lscalaz/$eq$eq$greater$greater;
     697: goto          757
     700: getstatic     #241                // Field scalaz/Ordering$EQ$.MODULE$:Lscalaz/Ordering$EQ$;
     703: aload         19
     705: invokevirtual #224                // Method java/lang/Object.equals:(Ljava/lang/Object;)Z
     708: ifeq          737
     711: new           #12                 // class scalaz/$eq$eq$greater$greater$Bin
     714: dup
     715: aload         12
     717: aload_2
     718: aload         13
     720: aload         16
     722: invokeinterface #245,  3          // InterfaceMethod scala/Function2.apply:(Ljava/lang/Object;Ljava/lang/Object;)Ljava/lang/Object;
     727: aload         17
     729: aload         18
     731: invokespecial #108                // Method scalaz/$eq$eq$greater$greater$Bin."<init>":(Ljava/lang/Object;Ljava/lang/Object;Lscalaz/$eq$eq$greater$greater;Lscalaz/$eq$eq$greater$greater;)V
     734: goto          757
     737: new           #146                // class scala/MatchError
     740: dup
     741: aload         19
     743: invokespecial #149                // Method scala/MatchError."<init>":(Ljava/lang/Object;)V
     746: athrow
     747: new           #146                // class scala/MatchError
     750: dup
     751: aload         10
     753: invokespecial #149                // Method scala/MatchError."<init>":(Ljava/lang/Object;)V
     756: athrow
     757: aconst_null
     758: astore        12
     760: aconst_null
     761: astore        13
     763: aconst_null
     764: astore        14
     766: aconst_null
     767: astore        15
     769: aconst_null
     770: astore        16
     772: aconst_null
     773: astore        17
     775: aconst_null
     776: astore        18
     778: aconst_null
     779: astore        19
     781: astore        7
     783: astore        6
     785: goto          29
     788: new           #146                // class scala/MatchError
     791: dup
     792: aload         6
     794: invokespecial #149                // Method scala/MatchError."<init>":(Ljava/lang/Object;)V
     797: athrow
     798: checkcast     #14                 // class scalaz/$eq$eq$greater$greater
     801: areturn

  public final <A, B> scalaz.$eq$eq$greater$greater<A, B> fromListWithKey(scala.collection.immutable.List<scala.Tuple2<A, B>>, scala.Function3<A, B, B, B>, scalaz.Order<A>);
    Code:
       0: aload_1
       1: getstatic     #66                 // Field scalaz/$eq$eq$greater$greater$Tip$.MODULE$:Lscalaz/$eq$eq$greater$greater$Tip$;
       4: invokevirtual #69                 // Method scalaz/$eq$eq$greater$greater$Tip$.apply:()Lscalaz/$eq$eq$greater$greater;
       7: aload_2
       8: aload_3
       9: invokedynamic #179,  0            // InvokeDynamic #3:apply:(Lscala/Function3;Lscalaz/Order;)Lscala/Function2;
      14: invokevirtual #122                // Method scala/collection/immutable/List.foldLeft:(Ljava/lang/Object;Lscala/Function2;)Ljava/lang/Object;
      17: checkcast     #14                 // class scalaz/$eq$eq$greater$greater
      20: areturn

  public final <A, B> scalaz.$eq$eq$greater$greater<A, B> fromIListWithKey(scalaz.IList<scala.Tuple2<A, B>>, scala.Function3<A, B, B, B>, scalaz.Order<A>);
    Code:
       0: aload_1
       1: getstatic     #66                 // Field scalaz/$eq$eq$greater$greater$Tip$.MODULE$:Lscalaz/$eq$eq$greater$greater$Tip$;
       4: invokevirtual #69                 // Method scalaz/$eq$eq$greater$greater$Tip$.apply:()Lscalaz/$eq$eq$greater$greater;
       7: astore        4
       9: ifnonnull     14
      12: aconst_null
      13: athrow
      14: aload_1
      15: aload         4
      17: astore        6
      19: astore        5
      21: aload         5
      23: instanceof    #129                // class scalaz/INil
      26: ifeq          34
      29: aload         6
      31: goto          792
      34: aload         5
      36: instanceof    #131                // class scalaz/ICons
      39: ifeq          782
      42: aload         5
      44: checkcast     #131                // class scalaz/ICons
      47: astore        7
      49: aload         7
      51: invokevirtual #135                // Method scalaz/ICons.head:()Ljava/lang/Object;
      54: astore        8
      56: aload         7
      58: invokevirtual #139                // Method scalaz/ICons.tail:()Lscalaz/IList;
      61: aload         6
      63: aload         8
      65: checkcast     #141                // class scala/Tuple2
      68: astore        10
      70: checkcast     #14                 // class scalaz/$eq$eq$greater$greater
      73: astore        9
      75: aload         9
      77: aload         10
      79: invokevirtual #194                // Method scala/Tuple2._1:()Ljava/lang/Object;
      82: aload         10
      84: invokevirtual #197                // Method scala/Tuple2._2:()Ljava/lang/Object;
      87: astore        12
      89: astore        11
      91: ifnonnull     96
      94: aconst_null
      95: athrow
      96: aload         9
      98: instanceof    #17                 // class scalaz/$eq$eq$greater$greater$Tip
     101: ifeq          117
     104: getstatic     #58                 // Field MODULE$:Lscalaz/$eq$eq$greater$greater$;
     107: aload         11
     109: aload         12
     111: invokevirtual #199                // Method singleton:(Ljava/lang/Object;Ljava/lang/Object;)Lscalaz/$eq$eq$greater$greater;
     114: goto          751
     117: aload         9
     119: instanceof    #12                 // class scalaz/$eq$eq$greater$greater$Bin
     122: ifeq          741
     125: aload         9
     127: checkcast     #12                 // class scalaz/$eq$eq$greater$greater$Bin
     130: astore        13
     132: aload         13
     134: invokevirtual #201                // Method scalaz/$eq$eq$greater$greater$Bin.k:()Ljava/lang/Object;
     137: astore        14
     139: aload         13
     141: invokevirtual #204                // Method scalaz/$eq$eq$greater$greater$Bin.v:()Ljava/lang/Object;
     144: astore        15
     146: aload         13
     148: invokevirtual #206                // Method scalaz/$eq$eq$greater$greater$Bin.l:()Lscalaz/$eq$eq$greater$greater;
     151: astore        16
     153: aload         13
     155: invokevirtual #209                // Method scalaz/$eq$eq$greater$greater$Bin.r:()Lscalaz/$eq$eq$greater$greater;
     158: astore        17
     160: aload_3
     161: aload         11
     163: aload         14
     165: invokeinterface #215,  3          // InterfaceMethod scalaz/Order.order:(Ljava/lang/Object;Ljava/lang/Object;)Lscalaz/Ordering;
     170: astore        18
     172: getstatic     #218                // Field scalaz/Ordering$LT$.MODULE$:Lscalaz/Ordering$LT$;
     175: aload         18
     177: invokevirtual #224                // Method java/lang/Object.equals:(Ljava/lang/Object;)Z
     180: ifeq          432
     183: getstatic     #58                 // Field MODULE$:Lscalaz/$eq$eq$greater$greater$;
     186: aload         14
     188: aload         15
     190: aload         16
     192: ifnonnull     197
     195: aconst_null
     196: athrow
     197: aload         16
     199: instanceof    #17                 // class scalaz/$eq$eq$greater$greater$Tip
     202: ifeq          218
     205: getstatic     #58                 // Field MODULE$:Lscalaz/$eq$eq$greater$greater$;
     208: aload         11
     210: aload         12
     212: invokevirtual #199                // Method singleton:(Ljava/lang/Object;Ljava/lang/Object;)Lscalaz/$eq$eq$greater$greater;
     215: goto          406
     218: aload         16
     220: instanceof    #12                 // class scalaz/$eq$eq$greater$greater$Bin
     223: ifeq          396
     226: aload         16
     228: checkcast     #12                 // class scalaz/$eq$eq$greater$greater$Bin
     231: astore        19
     233: aload         19
     235: invokevirtual #201                // Method scalaz/$eq$eq$greater$greater$Bin.k:()Ljava/lang/Object;
     238: astore        20
     240: aload         19
     242: invokevirtual #204                // Method scalaz/$eq$eq$greater$greater$Bin.v:()Ljava/lang/Object;
     245: astore        21
     247: aload         19
     249: invokevirtual #206                // Method scalaz/$eq$eq$greater$greater$Bin.l:()Lscalaz/$eq$eq$greater$greater;
     252: astore        22
     254: aload         19
     256: invokevirtual #209                // Method scalaz/$eq$eq$greater$greater$Bin.r:()Lscalaz/$eq$eq$greater$greater;
     259: astore        23
     261: aload_3
     262: aload         11
     264: aload         20
     266: invokeinterface #215,  3          // InterfaceMethod scalaz/Order.order:(Ljava/lang/Object;Ljava/lang/Object;)Lscalaz/Ordering;
     271: astore        24
     273: getstatic     #218                // Field scalaz/Ordering$LT$.MODULE$:Lscalaz/Ordering$LT$;
     276: aload         24
     278: invokevirtual #224                // Method java/lang/Object.equals:(Ljava/lang/Object;)Z
     281: ifeq          310
     284: getstatic     #58                 // Field MODULE$:Lscalaz/$eq$eq$greater$greater$;
     287: aload         20
     289: aload         21
     291: aload         22
     293: aload_2
     294: aload         11
     296: aload         12
     298: aload_3
     299: invokevirtual #228                // Method scalaz/$eq$eq$greater$greater.insertWithKey:(Lscala/Function3;Ljava/lang/Object;Ljava/lang/Object;Lscalaz/Order;)Lscalaz/$eq$eq$greater$greater;
     302: aload         23
     304: invokevirtual #232                // Method balanceL:(Ljava/lang/Object;Ljava/lang/Object;Lscalaz/$eq$eq$greater$greater;Lscalaz/$eq$eq$greater$greater;)Lscalaz/$eq$eq$greater$greater;
     307: goto          406
     310: getstatic     #235                // Field scalaz/Ordering$GT$.MODULE$:Lscalaz/Ordering$GT$;
     313: aload         24
     315: invokevirtual #224                // Method java/lang/Object.equals:(Ljava/lang/Object;)Z
     318: ifeq          347
     321: getstatic     #58                 // Field MODULE$:Lscalaz/$eq$eq$greater$greater$;
     324: aload         20
     326: aload         21
     328: aload         22
     330: aload         23
     332: aload_2
     333: aload         11
     335: aload         12
     337: aload_3
     338: invokevirtual #228                // Method scalaz/$eq$eq$greater$greater.insertWithKey:(Lscala/Function3;Ljava/lang/Object;Ljava/lang/Object;Lscalaz/Order;)Lscalaz/$eq$eq$greater$greater;
     341: invokevirtual #238                // Method balanceR:(Ljava/lang/Object;Ljava/lang/Object;Lscalaz/$eq$eq$greater$greater;Lscalaz/$eq$eq$greater$greater;)Lscalaz/$eq$eq$greater$greater;
     344: goto          406
     347: getstatic     #241                // Field scalaz/Ordering$EQ$.MODULE$:Lscalaz/Ordering$EQ$;
     350: aload         24
     352: invokevirtual #224                // Method java/lang/Object.equals:(Ljava/lang/Object;)Z
     355: ifeq          386
     358: new           #12                 // class scalaz/$eq$eq$greater$greater$Bin
     361: dup
     362: aload         11
     364: aload_2
     365: aload         11
     367: aload         12
     369: aload         21
     371: invokeinterface #273,  4          // InterfaceMethod scala/Function3.apply:(Ljava/lang/Object;Ljava/lang/Object;Ljava/lang/Object;)Ljava/lang/Object;
     376: aload         22
     378: aload         23
     380: invokespecial #108                // Method scalaz/$eq$eq$greater$greater$Bin."<init>":(Ljava/lang/Object;Ljava/lang/Object;Lscalaz/$eq$eq$greater$greater;Lscalaz/$eq$eq$greater$greater;)V
     383: goto          406
     386: new           #146                // class scala/MatchError
     389: dup
     390: aload         24
     392: invokespecial #149                // Method scala/MatchError."<init>":(Ljava/lang/Object;)V
     395: athrow
     396: new           #146                // class scala/MatchError
     399: dup
     400: aload         16
     402: invokespecial #149                // Method scala/MatchError."<init>":(Ljava/lang/Object;)V
     405: athrow
     406: aconst_null
     407: astore        19
     409: aconst_null
     410: astore        20
     412: aconst_null
     413: astore        21
     415: aconst_null
     416: astore        22
     418: aconst_null
     419: astore        23
     421: aconst_null
     422: astore        24
     424: aload         17
     426: invokevirtual #232                // Method balanceL:(Ljava/lang/Object;Ljava/lang/Object;Lscalaz/$eq$eq$greater$greater;Lscalaz/$eq$eq$greater$greater;)Lscalaz/$eq$eq$greater$greater;
     429: goto          751
     432: getstatic     #235                // Field scalaz/Ordering$GT$.MODULE$:Lscalaz/Ordering$GT$;
     435: aload         18
     437: invokevirtual #224                // Method java/lang/Object.equals:(Ljava/lang/Object;)Z
     440: ifeq          692
     443: getstatic     #58                 // Field MODULE$:Lscalaz/$eq$eq$greater$greater$;
     446: aload         14
     448: aload         15
     450: aload         16
     452: aload         17
     454: ifnonnull     459
     457: aconst_null
     458: athrow
     459: aload         17
     461: instanceof    #17                 // class scalaz/$eq$eq$greater$greater$Tip
     464: ifeq          480
     467: getstatic     #58                 // Field MODULE$:Lscalaz/$eq$eq$greater$greater$;
     470: aload         11
     472: aload         12
     474: invokevirtual #199                // Method singleton:(Ljava/lang/Object;Ljava/lang/Object;)Lscalaz/$eq$eq$greater$greater;
     477: goto          668
     480: aload         17
     482: instanceof    #12                 // class scalaz/$eq$eq$greater$greater$Bin
     485: ifeq          658
     488: aload         17
     490: checkcast     #12                 // class scalaz/$eq$eq$greater$greater$Bin
     493: astore        25
     495: aload         25
     497: invokevirtual #201                // Method scalaz/$eq$eq$greater$greater$Bin.k:()Ljava/lang/Object;
     500: astore        26
     502: aload         25
     504: invokevirtual #204                // Method scalaz/$eq$eq$greater$greater$Bin.v:()Ljava/lang/Object;
     507: astore        27
     509: aload         25
     511: invokevirtual #206                // Method scalaz/$eq$eq$greater$greater$Bin.l:()Lscalaz/$eq$eq$greater$greater;
     514: astore        28
     516: aload         25
     518: invokevirtual #209                // Method scalaz/$eq$eq$greater$greater$Bin.r:()Lscalaz/$eq$eq$greater$greater;
     521: astore        29
     523: aload_3
     524: aload         11
     526: aload         26
     528: invokeinterface #215,  3          // InterfaceMethod scalaz/Order.order:(Ljava/lang/Object;Ljava/lang/Object;)Lscalaz/Ordering;
     533: astore        30
     535: getstatic     #218                // Field scalaz/Ordering$LT$.MODULE$:Lscalaz/Ordering$LT$;
     538: aload         30
     540: invokevirtual #224                // Method java/lang/Object.equals:(Ljava/lang/Object;)Z
     543: ifeq          572
     546: getstatic     #58                 // Field MODULE$:Lscalaz/$eq$eq$greater$greater$;
     549: aload         26
     551: aload         27
     553: aload         28
     555: aload_2
     556: aload         11
     558: aload         12
     560: aload_3
     561: invokevirtual #228                // Method scalaz/$eq$eq$greater$greater.insertWithKey:(Lscala/Function3;Ljava/lang/Object;Ljava/lang/Object;Lscalaz/Order;)Lscalaz/$eq$eq$greater$greater;
     564: aload         29
     566: invokevirtual #232                // Method balanceL:(Ljava/lang/Object;Ljava/lang/Object;Lscalaz/$eq$eq$greater$greater;Lscalaz/$eq$eq$greater$greater;)Lscalaz/$eq$eq$greater$greater;
     569: goto          668
     572: getstatic     #235                // Field scalaz/Ordering$GT$.MODULE$:Lscalaz/Ordering$GT$;
     575: aload         30
     577: invokevirtual #224                // Method java/lang/Object.equals:(Ljava/lang/Object;)Z
     580: ifeq          609
     583: getstatic     #58                 // Field MODULE$:Lscalaz/$eq$eq$greater$greater$;
     586: aload         26
     588: aload         27
     590: aload         28
     592: aload         29
     594: aload_2
     595: aload         11
     597: aload         12
     599: aload_3
     600: invokevirtual #228                // Method scalaz/$eq$eq$greater$greater.insertWithKey:(Lscala/Function3;Ljava/lang/Object;Ljava/lang/Object;Lscalaz/Order;)Lscalaz/$eq$eq$greater$greater;
     603: invokevirtual #238                // Method balanceR:(Ljava/lang/Object;Ljava/lang/Object;Lscalaz/$eq$eq$greater$greater;Lscalaz/$eq$eq$greater$greater;)Lscalaz/$eq$eq$greater$greater;
     606: goto          668
     609: getstatic     #241                // Field scalaz/Ordering$EQ$.MODULE$:Lscalaz/Ordering$EQ$;
     612: aload         30
     614: invokevirtual #224                // Method java/lang/Object.equals:(Ljava/lang/Object;)Z
     617: ifeq          648
     620: new           #12                 // class scalaz/$eq$eq$greater$greater$Bin
     623: dup
     624: aload         11
     626: aload_2
     627: aload         11
     629: aload         12
     631: aload         27
     633: invokeinterface #273,  4          // InterfaceMethod scala/Function3.apply:(Ljava/lang/Object;Ljava/lang/Object;Ljava/lang/Object;)Ljava/lang/Object;
     638: aload         28
     640: aload         29
     642: invokespecial #108                // Method scalaz/$eq$eq$greater$greater$Bin."<init>":(Ljava/lang/Object;Ljava/lang/Object;Lscalaz/$eq$eq$greater$greater;Lscalaz/$eq$eq$greater$greater;)V
     645: goto          668
     648: new           #146                // class scala/MatchError
     651: dup
     652: aload         30
     654: invokespecial #149                // Method scala/MatchError."<init>":(Ljava/lang/Object;)V
     657: athrow
     658: new           #146                // class scala/MatchError
     661: dup
     662: aload         17
     664: invokespecial #149                // Method scala/MatchError."<init>":(Ljava/lang/Object;)V
     667: athrow
     668: aconst_null
     669: astore        25
     671: aconst_null
     672: astore        26
     674: aconst_null
     675: astore        27
     677: aconst_null
     678: astore        28
     680: aconst_null
     681: astore        29
     683: aconst_null
     684: astore        30
     686: invokevirtual #238                // Method balanceR:(Ljava/lang/Object;Ljava/lang/Object;Lscalaz/$eq$eq$greater$greater;Lscalaz/$eq$eq$greater$greater;)Lscalaz/$eq$eq$greater$greater;
     689: goto          751
     692: getstatic     #241                // Field scalaz/Ordering$EQ$.MODULE$:Lscalaz/Ordering$EQ$;
     695: aload         18
     697: invokevirtual #224                // Method java/lang/Object.equals:(Ljava/lang/Object;)Z
     700: ifeq          731
     703: new           #12                 // class scalaz/$eq$eq$greater$greater$Bin
     706: dup
     707: aload         11
     709: aload_2
     710: aload         11
     712: aload         12
     714: aload         15
     716: invokeinterface #273,  4          // InterfaceMethod scala/Function3.apply:(Ljava/lang/Object;Ljava/lang/Object;Ljava/lang/Object;)Ljava/lang/Object;
     721: aload         16
     723: aload         17
     725: invokespecial #108                // Method scalaz/$eq$eq$greater$greater$Bin."<init>":(Ljava/lang/Object;Ljava/lang/Object;Lscalaz/$eq$eq$greater$greater;Lscalaz/$eq$eq$greater$greater;)V
     728: goto          751
     731: new           #146                // class scala/MatchError
     734: dup
     735: aload         18
     737: invokespecial #149                // Method scala/MatchError."<init>":(Ljava/lang/Object;)V
     740: athrow
     741: new           #146                // class scala/MatchError
     744: dup
     745: aload         9
     747: invokespecial #149                // Method scala/MatchError."<init>":(Ljava/lang/Object;)V
     750: athrow
     751: aconst_null
     752: astore        11
     754: aconst_null
     755: astore        12
     757: aconst_null
     758: astore        13
     760: aconst_null
     761: astore        14
     763: aconst_null
     764: astore        15
     766: aconst_null
     767: astore        16
     769: aconst_null
     770: astore        17
     772: aconst_null
     773: astore        18
     775: astore        6
     777: astore        5
     779: goto          21
     782: new           #146                // class scala/MatchError
     785: dup
     786: aload         5
     788: invokespecial #149                // Method scala/MatchError."<init>":(Ljava/lang/Object;)V
     791: athrow
     792: checkcast     #14                 // class scalaz/$eq$eq$greater$greater
     795: areturn

  public final <F, A, B> scalaz.$eq$eq$greater$greater<A, B> fromFoldable(F, scalaz.Foldable<F>, scalaz.Order<A>);
    Code:
       0: getstatic     #284                // Field scalaz/Foldable$.MODULE$:Lscalaz/Foldable$;
       3: pop
       4: aload_2
       5: aload_1
       6: getstatic     #66                 // Field scalaz/$eq$eq$greater$greater$Tip$.MODULE$:Lscalaz/$eq$eq$greater$greater$Tip$;
       9: invokevirtual #69                 // Method scalaz/$eq$eq$greater$greater$Tip$.apply:()Lscalaz/$eq$eq$greater$greater;
      12: aload_3
      13: invokedynamic #289,  0            // InvokeDynamic #5:apply:(Lscalaz/Order;)Lscala/Function2;
      18: invokeinterface #294,  4          // InterfaceMethod scalaz/Foldable.foldLeft:(Ljava/lang/Object;Ljava/lang/Object;Lscala/Function2;)Ljava/lang/Object;
      23: checkcast     #14                 // class scalaz/$eq$eq$greater$greater
      26: areturn

  public final <F, A, B> scalaz.$eq$eq$greater$greater<A, B> fromFoldableWith(F, scala.Function2<B, B, B>, scalaz.Foldable<F>, scalaz.Order<A>);
    Code:
       0: aload_2
       1: invokedynamic #305,  0            // InvokeDynamic #6:apply:(Lscala/Function2;)Lscala/Function3;
       6: astore        5
       8: getstatic     #284                // Field scalaz/Foldable$.MODULE$:Lscalaz/Foldable$;
      11: pop
      12: aload_3
      13: aload_1
      14: getstatic     #66                 // Field scalaz/$eq$eq$greater$greater$Tip$.MODULE$:Lscalaz/$eq$eq$greater$greater$Tip$;
      17: invokevirtual #69                 // Method scalaz/$eq$eq$greater$greater$Tip$.apply:()Lscalaz/$eq$eq$greater$greater;
      20: aload         5
      22: aload         4
      24: invokedynamic #310,  0            // InvokeDynamic #7:apply:(Lscala/Function3;Lscalaz/Order;)Lscala/Function2;
      29: invokeinterface #294,  4          // InterfaceMethod scalaz/Foldable.foldLeft:(Ljava/lang/Object;Ljava/lang/Object;Lscala/Function2;)Ljava/lang/Object;
      34: checkcast     #14                 // class scalaz/$eq$eq$greater$greater
      37: areturn

  public final <F, A, B> scalaz.$eq$eq$greater$greater<A, B> fromFoldableWithKey(F, scala.Function3<A, B, B, B>, scalaz.Foldable<F>, scalaz.Order<A>);
    Code:
       0: getstatic     #284                // Field scalaz/Foldable$.MODULE$:Lscalaz/Foldable$;
       3: pop
       4: aload_3
       5: aload_1
       6: getstatic     #66                 // Field scalaz/$eq$eq$greater$greater$Tip$.MODULE$:Lscalaz/$eq$eq$greater$greater$Tip$;
       9: invokevirtual #69                 // Method scalaz/$eq$eq$greater$greater$Tip$.apply:()Lscalaz/$eq$eq$greater$greater;
      12: aload_2
      13: aload         4
      15: invokedynamic #310,  0            // InvokeDynamic #7:apply:(Lscala/Function3;Lscalaz/Order;)Lscala/Function2;
      20: invokeinterface #294,  4          // InterfaceMethod scalaz/Foldable.foldLeft:(Ljava/lang/Object;Ljava/lang/Object;Lscala/Function2;)Ljava/lang/Object;
      25: checkcast     #14                 // class scalaz/$eq$eq$greater$greater
      28: areturn

  public final <A, B> scalaz.$eq$eq$greater$greater<A, B> fromSet(scalaz.ISet<A>, scala.Function1<A, B>, scalaz.Order<A>);
    Code:
       0: aload_1
       1: instanceof    #27                 // class scalaz/ISet$Tip
       4: ifeq          14
       7: getstatic     #66                 // Field scalaz/$eq$eq$greater$greater$Tip$.MODULE$:Lscalaz/$eq$eq$greater$greater$Tip$;
      10: invokevirtual #69                 // Method scalaz/$eq$eq$greater$greater$Tip$.apply:()Lscalaz/$eq$eq$greater$greater;
      13: areturn
      14: aload_1
      15: instanceof    #23                 // class scalaz/ISet$Bin
      18: ifeq          82
      21: aload_1
      22: checkcast     #23                 // class scalaz/ISet$Bin
      25: astore        4
      27: aload         4
      29: invokevirtual #324                // Method scalaz/ISet$Bin.a:()Ljava/lang/Object;
      32: astore        5
      34: aload         4
      36: invokevirtual #327                // Method scalaz/ISet$Bin.l:()Lscalaz/ISet;
      39: astore        6
      41: aload         4
      43: invokevirtual #329                // Method scalaz/ISet$Bin.r:()Lscalaz/ISet;
      46: astore        7
      48: new           #12                 // class scalaz/$eq$eq$greater$greater$Bin
      51: dup
      52: aload         5
      54: aload_2
      55: aload         5
      57: invokeinterface #334,  2          // InterfaceMethod scala/Function1.apply:(Ljava/lang/Object;)Ljava/lang/Object;
      62: aload_0
      63: aload         6
      65: aload_2
      66: aload_3
      67: invokevirtual #336                // Method fromSet:(Lscalaz/ISet;Lscala/Function1;Lscalaz/Order;)Lscalaz/$eq$eq$greater$greater;
      70: aload_0
      71: aload         7
      73: aload_2
      74: aload_3
      75: invokevirtual #336                // Method fromSet:(Lscalaz/ISet;Lscala/Function1;Lscalaz/Order;)Lscalaz/$eq$eq$greater$greater;
      78: invokespecial #108                // Method scalaz/$eq$eq$greater$greater$Bin."<init>":(Ljava/lang/Object;Ljava/lang/Object;Lscalaz/$eq$eq$greater$greater;Lscalaz/$eq$eq$greater$greater;)V
      81: areturn
      82: new           #146                // class scala/MatchError
      85: dup
      86: aload_1
      87: invokespecial #149                // Method scala/MatchError."<init>":(Ljava/lang/Object;)V
      90: athrow

  public final <A, B> scalaz.$eq$eq$greater$greater<A, B> unions(scalaz.IList<scalaz.$eq$eq$greater$greater<A, B>>, scalaz.Order<A>);
    Code:
       0: aload_1
       1: getstatic     #66                 // Field scalaz/$eq$eq$greater$greater$Tip$.MODULE$:Lscalaz/$eq$eq$greater$greater$Tip$;
       4: invokevirtual #69                 // Method scalaz/$eq$eq$greater$greater$Tip$.apply:()Lscalaz/$eq$eq$greater$greater;
       7: astore_3
       8: ifnonnull     13
      11: aconst_null
      12: athrow
      13: aload_1
      14: aload_3
      15: astore        5
      17: astore        4
      19: aload         4
      21: instanceof    #129                // class scalaz/INil
      24: ifeq          30
      27: aload         5
      29: areturn
      30: aload         4
      32: instanceof    #131                // class scalaz/ICons
      35: ifeq          75
      38: aload         4
      40: checkcast     #131                // class scalaz/ICons
      43: astore        6
      45: aload         6
      47: invokevirtual #135                // Method scalaz/ICons.head:()Ljava/lang/Object;
      50: astore        7
      52: aload         6
      54: invokevirtual #139                // Method scalaz/ICons.tail:()Lscalaz/IList;
      57: aload         5
      59: aload         7
      61: checkcast     #14                 // class scalaz/$eq$eq$greater$greater
      64: aload_2
      65: invokevirtual #346                // Method scalaz/$eq$eq$greater$greater.union:(Lscalaz/$eq$eq$greater$greater;Lscalaz/Order;)Lscalaz/$eq$eq$greater$greater;
      68: astore        5
      70: astore        4
      72: goto          19
      75: new           #146                // class scala/MatchError
      78: dup
      79: aload         4
      81: invokespecial #149                // Method scala/MatchError."<init>":(Ljava/lang/Object;)V
      84: athrow

  public final <A, B> scalaz.$eq$eq$greater$greater<A, B> unionsWith(scala.Function2<B, B, B>, scalaz.IList<scalaz.$eq$eq$greater$greater<A, B>>, scalaz.Order<A>);
    Code:
       0: aload_2
       1: getstatic     #66                 // Field scalaz/$eq$eq$greater$greater$Tip$.MODULE$:Lscalaz/$eq$eq$greater$greater$Tip$;
       4: invokevirtual #69                 // Method scalaz/$eq$eq$greater$greater$Tip$.apply:()Lscalaz/$eq$eq$greater$greater;
       7: astore        4
       9: ifnonnull     14
      12: aconst_null
      13: athrow
      14: aload_2
      15: aload         4
      17: astore        6
      19: astore        5
      21: aload         5
      23: instanceof    #129                // class scalaz/INil
      26: ifeq          32
      29: aload         6
      31: areturn
      32: aload         5
      34: instanceof    #131                // class scalaz/ICons
      37: ifeq          1910
      40: aload         5
      42: checkcast     #131                // class scalaz/ICons
      45: astore        7
      47: aload         7
      49: invokevirtual #135                // Method scalaz/ICons.head:()Ljava/lang/Object;
      52: astore        8
      54: aload         7
      56: invokevirtual #139                // Method scalaz/ICons.tail:()Lscalaz/IList;
      59: aload         8
      61: checkcast     #14                 // class scalaz/$eq$eq$greater$greater
      64: astore        9
      66: aload         6
      68: ifnonnull     73
      71: aconst_null
      72: athrow
      73: aload_1
      74: invokedynamic #355,  0            // InvokeDynamic #8:apply:(Lscala/Function2;)Lscala/Function3;
      79: astore        10
      81: getstatic     #58                 // Field MODULE$:Lscalaz/$eq$eq$greater$greater$;
      84: aload         10
      86: invokedynamic #365,  0            // InvokeDynamic #9:apply:(Lscala/Function3;)Lscala/Function3;
      91: invokedynamic #375,  0            // InvokeDynamic #10:apply:()Lscala/Function1;
      96: invokedynamic #380,  0            // InvokeDynamic #11:apply:()Lscala/Function1;
     101: astore        14
     103: astore        13
     105: astore        12
     107: astore        11
     109: aload         6
     111: instanceof    #17                 // class scalaz/$eq$eq$greater$greater$Tip
     114: ifeq          122
     117: aload         9
     119: goto          1807
     122: aload         9
     124: instanceof    #17                 // class scalaz/$eq$eq$greater$greater$Tip
     127: ifeq          135
     130: aload         6
     132: goto          1807
     135: getstatic     #385                // Field scalaz/Maybe$.MODULE$:Lscalaz/Maybe$;
     138: pop
     139: getstatic     #388                // Field scalaz/Maybe$Empty$.MODULE$:Lscalaz/Maybe$Empty$;
     142: invokevirtual #391                // Method scalaz/Maybe$Empty$.apply:()Lscalaz/Maybe;
     145: getstatic     #385                // Field scalaz/Maybe$.MODULE$:Lscalaz/Maybe$;
     148: pop
     149: getstatic     #388                // Field scalaz/Maybe$Empty$.MODULE$:Lscalaz/Maybe$Empty$;
     152: invokevirtual #391                // Method scalaz/Maybe$Empty$.apply:()Lscalaz/Maybe;
     155: astore        16
     157: astore        15
     159: new           #141                // class scala/Tuple2
     162: dup
     163: aload         6
     165: aload         9
     167: invokespecial #394                // Method scala/Tuple2."<init>":(Ljava/lang/Object;Ljava/lang/Object;)V
     170: astore        17
     172: aload         9
     174: instanceof    #17                 // class scalaz/$eq$eq$greater$greater$Tip
     177: ifeq          185
     180: aload         6
     182: goto          1726
     185: aload         6
     187: instanceof    #17                 // class scalaz/$eq$eq$greater$greater$Tip
     190: ifeq          264
     193: aload         9
     195: instanceof    #12                 // class scalaz/$eq$eq$greater$greater$Bin
     198: ifeq          264
     201: aload         9
     203: checkcast     #12                 // class scalaz/$eq$eq$greater$greater$Bin
     206: astore        18
     208: aload         18
     210: invokevirtual #201                // Method scalaz/$eq$eq$greater$greater$Bin.k:()Ljava/lang/Object;
     213: astore        19
     215: aload         18
     217: invokevirtual #204                // Method scalaz/$eq$eq$greater$greater$Bin.v:()Ljava/lang/Object;
     220: astore        20
     222: aload         18
     224: invokevirtual #206                // Method scalaz/$eq$eq$greater$greater$Bin.l:()Lscalaz/$eq$eq$greater$greater;
     227: astore        21
     229: aload         18
     231: invokevirtual #209                // Method scalaz/$eq$eq$greater$greater$Bin.r:()Lscalaz/$eq$eq$greater$greater;
     234: astore        22
     236: aload         11
     238: aload         19
     240: aload         20
     242: aload         21
     244: aload         15
     246: aload_3
     247: invokevirtual #398                // Method scalaz/$eq$eq$greater$greater.scalaz$$eq$eq$greater$greater$$filterGt:(Lscalaz/Maybe;Lscalaz/Order;)Lscalaz/$eq$eq$greater$greater;
     250: aload         22
     252: aload         16
     254: aload_3
     255: invokevirtual #401                // Method scalaz/$eq$eq$greater$greater.scalaz$$eq$eq$greater$greater$$filterLt:(Lscalaz/Maybe;Lscalaz/Order;)Lscalaz/$eq$eq$greater$greater;
     258: invokevirtual #404                // Method link:(Ljava/lang/Object;Ljava/lang/Object;Lscalaz/$eq$eq$greater$greater;Lscalaz/$eq$eq$greater$greater;)Lscalaz/$eq$eq$greater$greater;
     261: goto          1726
     264: aload         6
     266: instanceof    #12                 // class scalaz/$eq$eq$greater$greater$Bin
     269: ifeq          1716
     272: aload         6
     274: checkcast     #12                 // class scalaz/$eq$eq$greater$greater$Bin
     277: astore        23
     279: aload         23
     281: invokevirtual #201                // Method scalaz/$eq$eq$greater$greater$Bin.k:()Ljava/lang/Object;
     284: astore        24
     286: aload         23
     288: invokevirtual #204                // Method scalaz/$eq$eq$greater$greater$Bin.v:()Ljava/lang/Object;
     291: astore        25
     293: aload         23
     295: invokevirtual #206                // Method scalaz/$eq$eq$greater$greater$Bin.l:()Lscalaz/$eq$eq$greater$greater;
     298: astore        26
     300: aload         23
     302: invokevirtual #209                // Method scalaz/$eq$eq$greater$greater$Bin.r:()Lscalaz/$eq$eq$greater$greater;
     305: astore        27
     307: getstatic     #385                // Field scalaz/Maybe$.MODULE$:Lscalaz/Maybe$;
     310: pop
     311: new           #37                 // class scalaz/Maybe$Just
     314: dup
     315: aload         24
     317: invokespecial #405                // Method scalaz/Maybe$Just."<init>":(Ljava/lang/Object;)V
     320: astore        28
     322: aload         11
     324: aload         15
     326: aload         28
     328: aload         9
     330: aload_3
     331: invokevirtual #409                // Method trim:(Lscalaz/Maybe;Lscalaz/Maybe;Lscalaz/$eq$eq$greater$greater;Lscalaz/Order;)Lscalaz/$eq$eq$greater$greater;
     334: astore        42
     336: new           #141                // class scala/Tuple2
     339: dup
     340: aload         26
     342: aload         42
     344: invokespecial #394                // Method scala/Tuple2."<init>":(Ljava/lang/Object;Ljava/lang/Object;)V
     347: astore        43
     349: aload         42
     351: instanceof    #17                 // class scalaz/$eq$eq$greater$greater$Tip
     354: ifeq          362
     357: aload         26
     359: goto          818
     362: aload         26
     364: instanceof    #17                 // class scalaz/$eq$eq$greater$greater$Tip
     367: ifeq          445
     370: aload         42
     372: instanceof    #12                 // class scalaz/$eq$eq$greater$greater$Bin
     375: ifeq          445
     378: aload         42
     380: checkcast     #12                 // class scalaz/$eq$eq$greater$greater$Bin
     383: astore        44
     385: aload         44
     387: invokevirtual #201                // Method scalaz/$eq$eq$greater$greater$Bin.k:()Ljava/lang/Object;
     390: astore        45
     392: aload         44
     394: invokevirtual #204                // Method scalaz/$eq$eq$greater$greater$Bin.v:()Ljava/lang/Object;
     397: astore        46
     399: aload         44
     401: invokevirtual #206                // Method scalaz/$eq$eq$greater$greater$Bin.l:()Lscalaz/$eq$eq$greater$greater;
     404: astore        47
     406: aload         44
     408: invokevirtual #209                // Method scalaz/$eq$eq$greater$greater$Bin.r:()Lscalaz/$eq$eq$greater$greater;
     411: astore        48
     413: aload         11
     415: aload         45
     417: aload         46
     419: aload         47
     421: aload         15
     423: aload_3
     424: invokevirtual #398                // Method scalaz/$eq$eq$greater$greater.scalaz$$eq$eq$greater$greater$$filterGt:(Lscalaz/Maybe;Lscalaz/Order;)Lscalaz/$eq$eq$greater$greater;
     427: aload         48
     429: aload         28
     431: aload_3
     432: invokevirtual #401                // Method scalaz/$eq$eq$greater$greater.scalaz$$eq$eq$greater$greater$$filterLt:(Lscalaz/Maybe;Lscalaz/Order;)Lscalaz/$eq$eq$greater$greater;
     435: invokevirtual #404                // Method link:(Ljava/lang/Object;Ljava/lang/Object;Lscalaz/$eq$eq$greater$greater;Lscalaz/$eq$eq$greater$greater;)Lscalaz/$eq$eq$greater$greater;
     438: astore        49
     440: aload         49
     442: goto          818
     445: aload         26
     447: instanceof    #12                 // class scalaz/$eq$eq$greater$greater$Bin
     450: ifeq          808
     453: aload         26
     455: checkcast     #12                 // class scalaz/$eq$eq$greater$greater$Bin
     458: astore        50
     460: aload         50
     462: invokevirtual #201                // Method scalaz/$eq$eq$greater$greater$Bin.k:()Ljava/lang/Object;
     465: astore        51
     467: aload         50
     469: invokevirtual #204                // Method scalaz/$eq$eq$greater$greater$Bin.v:()Ljava/lang/Object;
     472: astore        52
     474: aload         50
     476: invokevirtual #206                // Method scalaz/$eq$eq$greater$greater$Bin.l:()Lscalaz/$eq$eq$greater$greater;
     479: astore        53
     481: aload         50
     483: invokevirtual #209                // Method scalaz/$eq$eq$greater$greater$Bin.r:()Lscalaz/$eq$eq$greater$greater;
     486: astore        54
     488: getstatic     #385                // Field scalaz/Maybe$.MODULE$:Lscalaz/Maybe$;
     491: pop
     492: new           #37                 // class scalaz/Maybe$Just
     495: dup
     496: aload         51
     498: invokespecial #405                // Method scalaz/Maybe$Just."<init>":(Ljava/lang/Object;)V
     501: astore        55
     503: aload         11
     505: aload         15
     507: aload         55
     509: aload         53
     511: aload         11
     513: aload         15
     515: aload         55
     517: aload         42
     519: aload_3
     520: invokevirtual #409                // Method trim:(Lscalaz/Maybe;Lscalaz/Maybe;Lscalaz/$eq$eq$greater$greater;Lscalaz/Order;)Lscalaz/$eq$eq$greater$greater;
     523: aload         13
     525: aload_3
     526: aload         14
     528: aload         12
     530: invokespecial #413                // Method hedgeMerge$1:(Lscalaz/Maybe;Lscalaz/Maybe;Lscalaz/$eq$eq$greater$greater;Lscalaz/$eq$eq$greater$greater;Lscala/Function1;Lscalaz/Order;Lscala/Function1;Lscala/Function3;)Lscalaz/$eq$eq$greater$greater;
     533: astore        56
     535: aload         11
     537: aload         51
     539: aload         28
     541: aload         42
     543: aload_3
     544: invokevirtual #417                // Method trimLookupLo:(Ljava/lang/Object;Lscalaz/Maybe;Lscalaz/$eq$eq$greater$greater;Lscalaz/Order;)Lscala/Tuple2;
     547: astore        57
     549: aload         57
     551: ifnull        577
     554: aload         57
     556: invokevirtual #194                // Method scala/Tuple2._1:()Ljava/lang/Object;
     559: checkcast     #31                 // class scalaz/Maybe
     562: astore        58
     564: aload         57
     566: invokevirtual #197                // Method scala/Tuple2._2:()Ljava/lang/Object;
     569: checkcast     #14                 // class scalaz/$eq$eq$greater$greater
     572: astore        59
     574: goto          586
     577: new           #146                // class scala/MatchError
     580: dup
     581: aconst_null
     582: invokespecial #149                // Method scala/MatchError."<init>":(Ljava/lang/Object;)V
     585: athrow
     586: aload         11
     588: aload         55
     590: aload         28
     592: aload         54
     594: aload         59
     596: aload         13
     598: aload_3
     599: aload         14
     601: aload         12
     603: invokespecial #413                // Method hedgeMerge$1:(Lscalaz/Maybe;Lscalaz/Maybe;Lscalaz/$eq$eq$greater$greater;Lscalaz/$eq$eq$greater$greater;Lscala/Function1;Lscalaz/Order;Lscala/Function1;Lscala/Function3;)Lscalaz/$eq$eq$greater$greater;
     606: astore        60
     608: aload         58
     610: instanceof    #29                 // class scalaz/Maybe$Empty
     613: ifeq          723
     616: aload         11
     618: aload         51
     620: aload         52
     622: invokevirtual #199                // Method singleton:(Ljava/lang/Object;Ljava/lang/Object;)Lscalaz/$eq$eq$greater$greater;
     625: astore        61
     627: aload         61
     629: instanceof    #17                 // class scalaz/$eq$eq$greater$greater$Tip
     632: ifeq          645
     635: aload         56
     637: aload         60
     639: invokevirtual #420                // Method scalaz/$eq$eq$greater$greater.merge:(Lscalaz/$eq$eq$greater$greater;)Lscalaz/$eq$eq$greater$greater;
     642: goto          818
     645: aload         61
     647: instanceof    #12                 // class scalaz/$eq$eq$greater$greater$Bin
     650: ifeq          713
     653: aload         61
     655: checkcast     #12                 // class scalaz/$eq$eq$greater$greater$Bin
     658: astore        62
     660: aload         62
     662: invokevirtual #204                // Method scalaz/$eq$eq$greater$greater$Bin.v:()Ljava/lang/Object;
     665: astore        63
     667: aload         62
     669: invokevirtual #206                // Method scalaz/$eq$eq$greater$greater$Bin.l:()Lscalaz/$eq$eq$greater$greater;
     672: astore        64
     674: aload         62
     676: invokevirtual #209                // Method scalaz/$eq$eq$greater$greater$Bin.r:()Lscalaz/$eq$eq$greater$greater;
     679: astore        65
     681: aload         64
     683: instanceof    #17                 // class scalaz/$eq$eq$greater$greater$Tip
     686: ifeq          713
     689: aload         65
     691: instanceof    #17                 // class scalaz/$eq$eq$greater$greater$Tip
     694: ifeq          713
     697: aload         11
     699: aload         51
     701: aload         63
     703: aload         56
     705: aload         60
     707: invokevirtual #404                // Method link:(Ljava/lang/Object;Ljava/lang/Object;Lscalaz/$eq$eq$greater$greater;Lscalaz/$eq$eq$greater$greater;)Lscalaz/$eq$eq$greater$greater;
     710: goto          818
     713: getstatic     #425                // Field scala/sys/package$.MODULE$:Lscala/sys/package$;
     716: ldc_w         #427                // String mergeWithKey: Given function g1 does not fulfil required conditions (see documentation)
     719: invokevirtual #431                // Method scala/sys/package$.error:(Ljava/lang/String;)Lscala/runtime/Nothing$;
     722: athrow
     723: aload         58
     725: instanceof    #37                 // class scalaz/Maybe$Just
     728: ifeq          798
     731: aload         58
     733: checkcast     #37                 // class scalaz/Maybe$Just
     736: astore        66
     738: aload         66
     740: invokevirtual #434                // Method scalaz/Maybe$Just.get:()Ljava/lang/Object;
     743: astore        67
     745: getstatic     #385                // Field scalaz/Maybe$.MODULE$:Lscalaz/Maybe$;
     748: pop
     749: aload_1
     750: aload         51
     752: aload         52
     754: aload         67
     756: invokestatic  #353                // Method scalaz/$eq$eq$greater$greater.$anonfun$unionWith$1:(Lscala/Function2;Ljava/lang/Object;Ljava/lang/Object;Ljava/lang/Object;)Ljava/lang/Object;
     759: astore        97
     761: new           #37                 // class scalaz/Maybe$Just
     764: dup
     765: aload         97
     767: invokespecial #405                // Method scalaz/Maybe$Just."<init>":(Ljava/lang/Object;)V
     770: aconst_null
     771: astore        97
     773: astore        68
     775: aload         68
     777: invokevirtual #434                // Method scalaz/Maybe$Just.get:()Ljava/lang/Object;
     780: astore        69
     782: aload         11
     784: aload         51
     786: aload         69
     788: aload         56
     790: aload         60
     792: invokevirtual #404                // Method link:(Ljava/lang/Object;Ljava/lang/Object;Lscalaz/$eq$eq$greater$greater;Lscalaz/$eq$eq$greater$greater;)Lscalaz/$eq$eq$greater$greater;
     795: goto          818
     798: new           #146                // class scala/MatchError
     801: dup
     802: aload         58
     804: invokespecial #149                // Method scala/MatchError."<init>":(Ljava/lang/Object;)V
     807: athrow
     808: new           #146                // class scala/MatchError
     811: dup
     812: aload         43
     814: invokespecial #149                // Method scala/MatchError."<init>":(Ljava/lang/Object;)V
     817: athrow
     818: aconst_null
     819: astore        42
     821: aconst_null
     822: astore        43
     824: aconst_null
     825: astore        44
     827: aconst_null
     828: astore        45
     830: aconst_null
     831: astore        46
     833: aconst_null
     834: astore        47
     836: aconst_null
     837: astore        48
     839: aconst_null
     840: astore        49
     842: aconst_null
     843: astore        50
     845: aconst_null
     846: astore        51
     848: aconst_null
     849: astore        52
     851: aconst_null
     852: astore        53
     854: aconst_null
     855: astore        54
     857: aconst_null
     858: astore        55
     860: aconst_null
     861: astore        56
     863: aconst_null
     864: astore        57
     866: aconst_null
     867: astore        58
     869: aconst_null
     870: astore        59
     872: aconst_null
     873: astore        60
     875: aconst_null
     876: astore        61
     878: aconst_null
     879: astore        62
     881: aconst_null
     882: astore        63
     884: aconst_null
     885: astore        64
     887: aconst_null
     888: astore        65
     890: aconst_null
     891: astore        66
     893: aconst_null
     894: astore        67
     896: aconst_null
     897: astore        68
     899: aconst_null
     900: astore        69
     902: astore        29
     904: aload         11
     906: aload         24
     908: aload         16
     910: aload         9
     912: aload_3
     913: invokevirtual #417                // Method trimLookupLo:(Ljava/lang/Object;Lscalaz/Maybe;Lscalaz/$eq$eq$greater$greater;Lscalaz/Order;)Lscala/Tuple2;
     916: astore        30
     918: aload         30
     920: ifnull        946
     923: aload         30
     925: invokevirtual #194                // Method scala/Tuple2._1:()Ljava/lang/Object;
     928: checkcast     #31                 // class scalaz/Maybe
     931: astore        31
     933: aload         30
     935: invokevirtual #197                // Method scala/Tuple2._2:()Ljava/lang/Object;
     938: checkcast     #14                 // class scalaz/$eq$eq$greater$greater
     941: astore        32
     943: goto          955
     946: new           #146                // class scala/MatchError
     949: dup
     950: aconst_null
     951: invokespecial #149                // Method scala/MatchError."<init>":(Ljava/lang/Object;)V
     954: athrow
     955: new           #141                // class scala/Tuple2
     958: dup
     959: aload         27
     961: aload         32
     963: invokespecial #394                // Method scala/Tuple2."<init>":(Ljava/lang/Object;Ljava/lang/Object;)V
     966: astore        70
     968: aload         32
     970: instanceof    #17                 // class scalaz/$eq$eq$greater$greater$Tip
     973: ifeq          981
     976: aload         27
     978: goto          1437
     981: aload         27
     983: instanceof    #17                 // class scalaz/$eq$eq$greater$greater$Tip
     986: ifeq          1064
     989: aload         32
     991: instanceof    #12                 // class scalaz/$eq$eq$greater$greater$Bin
     994: ifeq          1064
     997: aload         32
     999: checkcast     #12                 // class scalaz/$eq$eq$greater$greater$Bin
    1002: astore        71
    1004: aload         71
    1006: invokevirtual #201                // Method scalaz/$eq$eq$greater$greater$Bin.k:()Ljava/lang/Object;
    1009: astore        72
    1011: aload         71
    1013: invokevirtual #204                // Method scalaz/$eq$eq$greater$greater$Bin.v:()Ljava/lang/Object;
    1016: astore        73
    1018: aload         71
    1020: invokevirtual #206                // Method scalaz/$eq$eq$greater$greater$Bin.l:()Lscalaz/$eq$eq$greater$greater;
    1023: astore        74
    1025: aload         71
    1027: invokevirtual #209                // Method scalaz/$eq$eq$greater$greater$Bin.r:()Lscalaz/$eq$eq$greater$greater;
    1030: astore        75
    1032: aload         11
    1034: aload         72
    1036: aload         73
    1038: aload         74
    1040: aload         28
    1042: aload_3
    1043: invokevirtual #398                // Method scalaz/$eq$eq$greater$greater.scalaz$$eq$eq$greater$greater$$filterGt:(Lscalaz/Maybe;Lscalaz/Order;)Lscalaz/$eq$eq$greater$greater;
    1046: aload         75
    1048: aload         16
    1050: aload_3
    1051: invokevirtual #401                // Method scalaz/$eq$eq$greater$greater.scalaz$$eq$eq$greater$greater$$filterLt:(Lscalaz/Maybe;Lscalaz/Order;)Lscalaz/$eq$eq$greater$greater;
    1054: invokevirtual #404                // Method link:(Ljava/lang/Object;Ljava/lang/Object;Lscalaz/$eq$eq$greater$greater;Lscalaz/$eq$eq$greater$greater;)Lscalaz/$eq$eq$greater$greater;
    1057: astore        76
    1059: aload         76
    1061: goto          1437
    1064: aload         27
    1066: instanceof    #12                 // class scalaz/$eq$eq$greater$greater$Bin
    1069: ifeq          1427
    1072: aload         27
    1074: checkcast     #12                 // class scalaz/$eq$eq$greater$greater$Bin
    1077: astore        77
    1079: aload         77
    1081: invokevirtual #201                // Method scalaz/$eq$eq$greater$greater$Bin.k:()Ljava/lang/Object;
    1084: astore        78
    1086: aload         77
    1088: invokevirtual #204                // Method scalaz/$eq$eq$greater$greater$Bin.v:()Ljava/lang/Object;
    1091: astore        79
    1093: aload         77
    1095: invokevirtual #206                // Method scalaz/$eq$eq$greater$greater$Bin.l:()Lscalaz/$eq$eq$greater$greater;
    1098: astore        80
    1100: aload         77
    1102: invokevirtual #209                // Method scalaz/$eq$eq$greater$greater$Bin.r:()Lscalaz/$eq$eq$greater$greater;
    1105: astore        81
    1107: getstatic     #385                // Field scalaz/Maybe$.MODULE$:Lscalaz/Maybe$;
    1110: pop
    1111: new           #37                 // class scalaz/Maybe$Just
    1114: dup
    1115: aload         78
    1117: invokespecial #405                // Method scalaz/Maybe$Just."<init>":(Ljava/lang/Object;)V
    1120: astore        82
    1122: aload         11
    1124: aload         28
    1126: aload         82
    1128: aload         80
    1130: aload         11
    1132: aload         28
    1134: aload         82
    1136: aload         32
    1138: aload_3
    1139: invokevirtual #409                // Method trim:(Lscalaz/Maybe;Lscalaz/Maybe;Lscalaz/$eq$eq$greater$greater;Lscalaz/Order;)Lscalaz/$eq$eq$greater$greater;
    1142: aload         13
    1144: aload_3
    1145: aload         14
    1147: aload         12
    1149: invokespecial #413                // Method hedgeMerge$1:(Lscalaz/Maybe;Lscalaz/Maybe;Lscalaz/$eq$eq$greater$greater;Lscalaz/$eq$eq$greater$greater;Lscala/Function1;Lscalaz/Order;Lscala/Function1;Lscala/Function3;)Lscalaz/$eq$eq$greater$greater;
    1152: astore        83
    1154: aload         11
    1156: aload         78
    1158: aload         16
    1160: aload         32
    1162: aload_3
    1163: invokevirtual #417                // Method trimLookupLo:(Ljava/lang/Object;Lscalaz/Maybe;Lscalaz/$eq$eq$greater$greater;Lscalaz/Order;)Lscala/Tuple2;
    1166: astore        84
    1168: aload         84
    1170: ifnull        1196
    1173: aload         84
    1175: invokevirtual #194                // Method scala/Tuple2._1:()Ljava/lang/Object;
    1178: checkcast     #31                 // class scalaz/Maybe
    1181: astore        85
    1183: aload         84
    1185: invokevirtual #197                // Method scala/Tuple2._2:()Ljava/lang/Object;
    1188: checkcast     #14                 // class scalaz/$eq$eq$greater$greater
    1191: astore        86
    1193: goto          1205
    1196: new           #146                // class scala/MatchError
    1199: dup
    1200: aconst_null
    1201: invokespecial #149                // Method scala/MatchError."<init>":(Ljava/lang/Object;)V
    1204: athrow
    1205: aload         11
    1207: aload         82
    1209: aload         16
    1211: aload         81
    1213: aload         86
    1215: aload         13
    1217: aload_3
    1218: aload         14
    1220: aload         12
    1222: invokespecial #413                // Method hedgeMerge$1:(Lscalaz/Maybe;Lscalaz/Maybe;Lscalaz/$eq$eq$greater$greater;Lscalaz/$eq$eq$greater$greater;Lscala/Function1;Lscalaz/Order;Lscala/Function1;Lscala/Function3;)Lscalaz/$eq$eq$greater$greater;
    1225: astore        87
    1227: aload         85
    1229: instanceof    #29                 // class scalaz/Maybe$Empty
    1232: ifeq          1342
    1235: aload         11
    1237: aload         78
    1239: aload         79
    1241: invokevirtual #199                // Method singleton:(Ljava/lang/Object;Ljava/lang/Object;)Lscalaz/$eq$eq$greater$greater;
    1244: astore        88
    1246: aload         88
    1248: instanceof    #17                 // class scalaz/$eq$eq$greater$greater$Tip
    1251: ifeq          1264
    1254: aload         83
    1256: aload         87
    1258: invokevirtual #420                // Method scalaz/$eq$eq$greater$greater.merge:(Lscalaz/$eq$eq$greater$greater;)Lscalaz/$eq$eq$greater$greater;
    1261: goto          1437
    1264: aload         88
    1266: instanceof    #12                 // class scalaz/$eq$eq$greater$greater$Bin
    1269: ifeq          1332
    1272: aload         88
    1274: checkcast     #12                 // class scalaz/$eq$eq$greater$greater$Bin
    1277: astore        89
    1279: aload         89
    1281: invokevirtual #204                // Method scalaz/$eq$eq$greater$greater$Bin.v:()Ljava/lang/Object;
    1284: astore        90
    1286: aload         89
    1288: invokevirtual #206                // Method scalaz/$eq$eq$greater$greater$Bin.l:()Lscalaz/$eq$eq$greater$greater;
    1291: astore        91
    1293: aload         89
    1295: invokevirtual #209                // Method scalaz/$eq$eq$greater$greater$Bin.r:()Lscalaz/$eq$eq$greater$greater;
    1298: astore        92
    1300: aload         91
    1302: instanceof    #17                 // class scalaz/$eq$eq$greater$greater$Tip
    1305: ifeq          1332
    1308: aload         92
    1310: instanceof    #17                 // class scalaz/$eq$eq$greater$greater$Tip
    1313: ifeq          1332
    1316: aload         11
    1318: aload         78
    1320: aload         90
    1322: aload         83
    1324: aload         87
    1326: invokevirtual #404                // Method link:(Ljava/lang/Object;Ljava/lang/Object;Lscalaz/$eq$eq$greater$greater;Lscalaz/$eq$eq$greater$greater;)Lscalaz/$eq$eq$greater$greater;
    1329: goto          1437
    1332: getstatic     #425                // Field scala/sys/package$.MODULE$:Lscala/sys/package$;
    1335: ldc_w         #427                // String mergeWithKey: Given function g1 does not fulfil required conditions (see documentation)
    1338: invokevirtual #431                // Method scala/sys/package$.error:(Ljava/lang/String;)Lscala/runtime/Nothing$;
    1341: athrow
    1342: aload         85
    1344: instanceof    #37                 // class scalaz/Maybe$Just
    1347: ifeq          1417
    1350: aload         85
    1352: checkcast     #37                 // class scalaz/Maybe$Just
    1355: astore        93
    1357: aload         93
    1359: invokevirtual #434                // Method scalaz/Maybe$Just.get:()Ljava/lang/Object;
    1362: astore        94
    1364: getstatic     #385                // Field scalaz/Maybe$.MODULE$:Lscalaz/Maybe$;
    1367: pop
    1368: aload_1
    1369: aload         78
    1371: aload         79
    1373: aload         94
    1375: invokestatic  #353                // Method scalaz/$eq$eq$greater$greater.$anonfun$unionWith$1:(Lscala/Function2;Ljava/lang/Object;Ljava/lang/Object;Ljava/lang/Object;)Ljava/lang/Object;
    1378: astore        98
    1380: new           #37                 // class scalaz/Maybe$Just
    1383: dup
    1384: aload         98
    1386: invokespecial #405                // Method scalaz/Maybe$Just."<init>":(Ljava/lang/Object;)V
    1389: aconst_null
    1390: astore        98
    1392: astore        95
    1394: aload         95
    1396: invokevirtual #434                // Method scalaz/Maybe$Just.get:()Ljava/lang/Object;
    1399: astore        96
    1401: aload         11
    1403: aload         78
    1405: aload         96
    1407: aload         83
    1409: aload         87
    1411: invokevirtual #404                // Method link:(Ljava/lang/Object;Ljava/lang/Object;Lscalaz/$eq$eq$greater$greater;Lscalaz/$eq$eq$greater$greater;)Lscalaz/$eq$eq$greater$greater;
    1414: goto          1437
    1417: new           #146                // class scala/MatchError
    1420: dup
    1421: aload         85
    1423: invokespecial #149                // Method scala/MatchError."<init>":(Ljava/lang/Object;)V
    1426: athrow
    1427: new           #146                // class scala/MatchError
    1430: dup
    1431: aload         70
    1433: invokespecial #149                // Method scala/MatchError."<init>":(Ljava/lang/Object;)V
    1436: athrow
    1437: aconst_null
    1438: astore        70
    1440: aconst_null
    1441: astore        71
    1443: aconst_null
    1444: astore        72
    1446: aconst_null
    1447: astore        73
    1449: aconst_null
    1450: astore        74
    1452: aconst_null
    1453: astore        75
    1455: aconst_null
    1456: astore        76
    1458: aconst_null
    1459: astore        77
    1461: aconst_null
    1462: astore        78
    1464: aconst_null
    1465: astore        79
    1467: aconst_null
    1468: astore        80
    1470: aconst_null
    1471: astore        81
    1473: aconst_null
    1474: astore        82
    1476: aconst_null
    1477: astore        83
    1479: aconst_null
    1480: astore        84
    1482: aconst_null
    1483: astore        85
    1485: aconst_null
    1486: astore        86
    1488: aconst_null
    1489: astore        87
    1491: aconst_null
    1492: astore        88
    1494: aconst_null
    1495: astore        89
    1497: aconst_null
    1498: astore        90
    1500: aconst_null
    1501: astore        91
    1503: aconst_null
    1504: astore        92
    1506: aconst_null
    1507: astore        93
    1509: aconst_null
    1510: astore        94
    1512: aconst_null
    1513: astore        95
    1515: aconst_null
    1516: astore        96
    1518: astore        33
    1520: aload         31
    1522: instanceof    #29                 // class scalaz/Maybe$Empty
    1525: ifeq          1635
    1528: aload         11
    1530: aload         24
    1532: aload         25
    1534: invokevirtual #199                // Method singleton:(Ljava/lang/Object;Ljava/lang/Object;)Lscalaz/$eq$eq$greater$greater;
    1537: astore        34
    1539: aload         34
    1541: instanceof    #17                 // class scalaz/$eq$eq$greater$greater$Tip
    1544: ifeq          1557
    1547: aload         29
    1549: aload         33
    1551: invokevirtual #420                // Method scalaz/$eq$eq$greater$greater.merge:(Lscalaz/$eq$eq$greater$greater;)Lscalaz/$eq$eq$greater$greater;
    1554: goto          1726
    1557: aload         34
    1559: instanceof    #12                 // class scalaz/$eq$eq$greater$greater$Bin
    1562: ifeq          1625
    1565: aload         34
    1567: checkcast     #12                 // class scalaz/$eq$eq$greater$greater$Bin
    1570: astore        35
    1572: aload         35
    1574: invokevirtual #204                // Method scalaz/$eq$eq$greater$greater$Bin.v:()Ljava/lang/Object;
    1577: astore        36
    1579: aload         35
    1581: invokevirtual #206                // Method scalaz/$eq$eq$greater$greater$Bin.l:()Lscalaz/$eq$eq$greater$greater;
    1584: astore        37
    1586: aload         35
    1588: invokevirtual #209                // Method scalaz/$eq$eq$greater$greater$Bin.r:()Lscalaz/$eq$eq$greater$greater;
    1591: astore        38
    1593: aload         37
    1595: instanceof    #17                 // class scalaz/$eq$eq$greater$greater$Tip
    1598: ifeq          1625
    1601: aload         38
    1603: instanceof    #17                 // class scalaz/$eq$eq$greater$greater$Tip
    1606: ifeq          1625
    1609: aload         11
    1611: aload         24
    1613: aload         36
    1615: aload         29
    1617: aload         33
    1619: invokevirtual #404                // Method link:(Ljava/lang/Object;Ljava/lang/Object;Lscalaz/$eq$eq$greater$greater;Lscalaz/$eq$eq$greater$greater;)Lscalaz/$eq$eq$greater$greater;
    1622: goto          1726
    1625: getstatic     #425                // Field scala/sys/package$.MODULE$:Lscala/sys/package$;
    1628: ldc_w         #427                // String mergeWithKey: Given function g1 does not fulfil required conditions (see documentation)
    1631: invokevirtual #431                // Method scala/sys/package$.error:(Ljava/lang/String;)Lscala/runtime/Nothing$;
    1634: athrow
    1635: aload         31
    1637: instanceof    #37                 // class scalaz/Maybe$Just
    1640: ifeq          1706
    1643: aload         31
    1645: checkcast     #37                 // class scalaz/Maybe$Just
    1648: invokevirtual #434                // Method scalaz/Maybe$Just.get:()Ljava/lang/Object;
    1651: astore        39
    1653: getstatic     #385                // Field scalaz/Maybe$.MODULE$:Lscalaz/Maybe$;
    1656: pop
    1657: aload_1
    1658: aload         24
    1660: aload         25
    1662: aload         39
    1664: invokestatic  #353                // Method scalaz/$eq$eq$greater$greater.$anonfun$unionWith$1:(Lscala/Function2;Ljava/lang/Object;Ljava/lang/Object;Ljava/lang/Object;)Ljava/lang/Object;
    1667: astore        99
    1669: new           #37                 // class scalaz/Maybe$Just
    1672: dup
    1673: aload         99
    1675: invokespecial #405                // Method scalaz/Maybe$Just."<init>":(Ljava/lang/Object;)V
    1678: aconst_null
    1679: astore        99
    1681: astore        40
    1683: aload         40
    1685: invokevirtual #434                // Method scalaz/Maybe$Just.get:()Ljava/lang/Object;
    1688: astore        41
    1690: aload         11
    1692: aload         24
    1694: aload         41
    1696: aload         29
    1698: aload         33
    1700: invokevirtual #404                // Method link:(Ljava/lang/Object;Ljava/lang/Object;Lscalaz/$eq$eq$greater$greater;Lscalaz/$eq$eq$greater$greater;)Lscalaz/$eq$eq$greater$greater;
    1703: goto          1726
    1706: new           #146                // class scala/MatchError
    1709: dup
    1710: aload         31
    1712: invokespecial #149                // Method scala/MatchError."<init>":(Ljava/lang/Object;)V
    1715: athrow
    1716: new           #146                // class scala/MatchError
    1719: dup
    1720: aload         17
    1722: invokespecial #149                // Method scala/MatchError."<init>":(Ljava/lang/Object;)V
    1725: athrow
    1726: aconst_null
    1727: astore        15
    1729: aconst_null
    1730: astore        16
    1732: aconst_null
    1733: astore        17
    1735: aconst_null
    1736: astore        18
    1738: aconst_null
    1739: astore        19
    1741: aconst_null
    1742: astore        20
    1744: aconst_null
    1745: astore        21
    1747: aconst_null
    1748: astore        22
    1750: aconst_null
    1751: astore        23
    1753: aconst_null
    1754: astore        24
    1756: aconst_null
    1757: astore        25
    1759: aconst_null
    1760: astore        26
    1762: aconst_null
    1763: astore        27
    1765: aconst_null
    1766: astore        28
    1768: aconst_null
    1769: astore        29
    1771: aconst_null
    1772: astore        30
    1774: aconst_null
    1775: astore        31
    1777: aconst_null
    1778: astore        32
    1780: aconst_null
    1781: astore        33
    1783: aconst_null
    1784: astore        34
    1786: aconst_null
    1787: astore        35
    1789: aconst_null
    1790: astore        36
    1792: aconst_null
    1793: astore        37
    1795: aconst_null
    1796: astore        38
    1798: aconst_null
    1799: astore        39
    1801: aconst_null
    1802: astore        40
    1804: aconst_null
    1805: astore        41
    1807: aconst_null
    1808: astore        11
    1810: aconst_null
    1811: astore        12
    1813: aconst_null
    1814: astore        13
    1816: aconst_null
    1817: astore        14
    1819: aconst_null
    1820: astore        15
    1822: aconst_null
    1823: astore        16
    1825: aconst_null
    1826: astore        17
    1828: aconst_null
    1829: astore        18
    1831: aconst_null
    1832: astore        19
    1834: aconst_null
    1835: astore        20
    1837: aconst_null
    1838: astore        21
    1840: aconst_null
    1841: astore        22
    1843: aconst_null
    1844: astore        23
    1846: aconst_null
    1847: astore        24
    1849: aconst_null
    1850: astore        25
    1852: aconst_null
    1853: astore        26
    1855: aconst_null
    1856: astore        27
    1858: aconst_null
    1859: astore        28
    1861: aconst_null
    1862: astore        29
    1864: aconst_null
    1865: astore        30
    1867: aconst_null
    1868: astore        31
    1870: aconst_null
    1871: astore        32
    1873: aconst_null
    1874: astore        33
    1876: aconst_null
    1877: astore        34
    1879: aconst_null
    1880: astore        35
    1882: aconst_null
    1883: astore        36
    1885: aconst_null
    1886: astore        37
    1888: aconst_null
    1889: astore        38
    1891: aconst_null
    1892: astore        39
    1894: aconst_null
    1895: astore        40
    1897: aconst_null
    1898: astore        41
    1900: aconst_null
    1901: astore        10
    1903: astore        6
    1905: astore        5
    1907: goto          21
    1910: new           #146                // class scala/MatchError
    1913: dup
    1914: aload         5
    1916: invokespecial #149                // Method scala/MatchError."<init>":(Ljava/lang/Object;)V
    1919: athrow

  public final int ratio();
    Code:
       0: iconst_2
       1: ireturn

  public final int delta();
    Code:
       0: iconst_3
       1: ireturn

  public <A, B> scalaz.$eq$eq$greater$greater<A, B> balance(A, B, scalaz.$eq$eq$greater$greater<A, B>, scalaz.$eq$eq$greater$greater<A, B>);
    Code:
       0: aload_3
       1: instanceof    #17                 // class scalaz/$eq$eq$greater$greater$Tip
       4: ifeq          457
       7: iconst_0
       8: istore        5
      10: aconst_null
      11: astore        6
      13: aload         4
      15: instanceof    #17                 // class scalaz/$eq$eq$greater$greater$Tip
      18: ifeq          28
      21: aload_0
      22: aload_1
      23: aload_2
      24: invokevirtual #199                // Method singleton:(Ljava/lang/Object;Ljava/lang/Object;)Lscalaz/$eq$eq$greater$greater;
      27: areturn
      28: aload         4
      30: instanceof    #12                 // class scalaz/$eq$eq$greater$greater$Bin
      33: ifeq          94
      36: iconst_1
      37: istore        5
      39: aload         4
      41: checkcast     #12                 // class scalaz/$eq$eq$greater$greater$Bin
      44: astore        6
      46: aload         6
      48: invokevirtual #206                // Method scalaz/$eq$eq$greater$greater$Bin.l:()Lscalaz/$eq$eq$greater$greater;
      51: astore        7
      53: aload         6
      55: invokevirtual #209                // Method scalaz/$eq$eq$greater$greater$Bin.r:()Lscalaz/$eq$eq$greater$greater;
      58: astore        8
      60: aload         7
      62: instanceof    #17                 // class scalaz/$eq$eq$greater$greater$Tip
      65: ifeq          94
      68: aload         8
      70: instanceof    #17                 // class scalaz/$eq$eq$greater$greater$Tip
      73: ifeq          94
      76: new           #12                 // class scalaz/$eq$eq$greater$greater$Bin
      79: dup
      80: aload_1
      81: aload_2
      82: getstatic     #66                 // Field scalaz/$eq$eq$greater$greater$Tip$.MODULE$:Lscalaz/$eq$eq$greater$greater$Tip$;
      85: invokevirtual #69                 // Method scalaz/$eq$eq$greater$greater$Tip$.apply:()Lscalaz/$eq$eq$greater$greater;
      88: aload         4
      90: invokespecial #108                // Method scalaz/$eq$eq$greater$greater$Bin."<init>":(Ljava/lang/Object;Ljava/lang/Object;Lscalaz/$eq$eq$greater$greater;Lscalaz/$eq$eq$greater$greater;)V
      93: areturn
      94: iload         5
      96: ifeq          170
      99: aload         6
     101: invokevirtual #201                // Method scalaz/$eq$eq$greater$greater$Bin.k:()Ljava/lang/Object;
     104: astore        9
     106: aload         6
     108: invokevirtual #204                // Method scalaz/$eq$eq$greater$greater$Bin.v:()Ljava/lang/Object;
     111: astore        10
     113: aload         6
     115: invokevirtual #206                // Method scalaz/$eq$eq$greater$greater$Bin.l:()Lscalaz/$eq$eq$greater$greater;
     118: astore        11
     120: aload         6
     122: invokevirtual #209                // Method scalaz/$eq$eq$greater$greater$Bin.r:()Lscalaz/$eq$eq$greater$greater;
     125: astore        12
     127: aload         11
     129: instanceof    #17                 // class scalaz/$eq$eq$greater$greater$Tip
     132: ifeq          170
     135: aload         12
     137: instanceof    #12                 // class scalaz/$eq$eq$greater$greater$Bin
     140: ifeq          170
     143: aload         12
     145: checkcast     #12                 // class scalaz/$eq$eq$greater$greater$Bin
     148: astore        13
     150: new           #12                 // class scalaz/$eq$eq$greater$greater$Bin
     153: dup
     154: aload         9
     156: aload         10
     158: aload_0
     159: aload_1
     160: aload_2
     161: invokevirtual #199                // Method singleton:(Ljava/lang/Object;Ljava/lang/Object;)Lscalaz/$eq$eq$greater$greater;
     164: aload         13
     166: invokespecial #108                // Method scalaz/$eq$eq$greater$greater$Bin."<init>":(Ljava/lang/Object;Ljava/lang/Object;Lscalaz/$eq$eq$greater$greater;Lscalaz/$eq$eq$greater$greater;)V
     169: areturn
     170: iload         5
     172: ifeq          266
     175: aload         6
     177: invokevirtual #201                // Method scalaz/$eq$eq$greater$greater$Bin.k:()Ljava/lang/Object;
     180: astore        14
     182: aload         6
     184: invokevirtual #204                // Method scalaz/$eq$eq$greater$greater$Bin.v:()Ljava/lang/Object;
     187: astore        15
     189: aload         6
     191: invokevirtual #206                // Method scalaz/$eq$eq$greater$greater$Bin.l:()Lscalaz/$eq$eq$greater$greater;
     194: astore        16
     196: aload         6
     198: invokevirtual #209                // Method scalaz/$eq$eq$greater$greater$Bin.r:()Lscalaz/$eq$eq$greater$greater;
     201: astore        17
     203: aload         16
     205: instanceof    #12                 // class scalaz/$eq$eq$greater$greater$Bin
     208: ifeq          266
     211: aload         16
     213: checkcast     #12                 // class scalaz/$eq$eq$greater$greater$Bin
     216: astore        18
     218: aload         18
     220: invokevirtual #201                // Method scalaz/$eq$eq$greater$greater$Bin.k:()Ljava/lang/Object;
     223: astore        19
     225: aload         18
     227: invokevirtual #204                // Method scalaz/$eq$eq$greater$greater$Bin.v:()Ljava/lang/Object;
     230: astore        20
     232: aload         17
     234: instanceof    #17                 // class scalaz/$eq$eq$greater$greater$Tip
     237: ifeq          266
     240: new           #12                 // class scalaz/$eq$eq$greater$greater$Bin
     243: dup
     244: aload         19
     246: aload         20
     248: aload_0
     249: aload_1
     250: aload_2
     251: invokevirtual #199                // Method singleton:(Ljava/lang/Object;Ljava/lang/Object;)Lscalaz/$eq$eq$greater$greater;
     254: aload_0
     255: aload         14
     257: aload         15
     259: invokevirtual #199                // Method singleton:(Ljava/lang/Object;Ljava/lang/Object;)Lscalaz/$eq$eq$greater$greater;
     262: invokespecial #108                // Method scalaz/$eq$eq$greater$greater$Bin."<init>":(Ljava/lang/Object;Ljava/lang/Object;Lscalaz/$eq$eq$greater$greater;Lscalaz/$eq$eq$greater$greater;)V
     265: areturn
     266: iload         5
     268: ifeq          447
     271: aload         6
     273: invokevirtual #201                // Method scalaz/$eq$eq$greater$greater$Bin.k:()Ljava/lang/Object;
     276: astore        21
     278: aload         6
     280: invokevirtual #204                // Method scalaz/$eq$eq$greater$greater$Bin.v:()Ljava/lang/Object;
     283: astore        22
     285: aload         6
     287: invokevirtual #206                // Method scalaz/$eq$eq$greater$greater$Bin.l:()Lscalaz/$eq$eq$greater$greater;
     290: astore        23
     292: aload         6
     294: invokevirtual #209                // Method scalaz/$eq$eq$greater$greater$Bin.r:()Lscalaz/$eq$eq$greater$greater;
     297: astore        24
     299: aload         23
     301: instanceof    #12                 // class scalaz/$eq$eq$greater$greater$Bin
     304: ifeq          447
     307: aload         23
     309: checkcast     #12                 // class scalaz/$eq$eq$greater$greater$Bin
     312: astore        25
     314: aload         25
     316: invokevirtual #201                // Method scalaz/$eq$eq$greater$greater$Bin.k:()Ljava/lang/Object;
     319: astore        26
     321: aload         25
     323: invokevirtual #204                // Method scalaz/$eq$eq$greater$greater$Bin.v:()Ljava/lang/Object;
     326: astore        27
     328: aload         25
     330: invokevirtual #206                // Method scalaz/$eq$eq$greater$greater$Bin.l:()Lscalaz/$eq$eq$greater$greater;
     333: astore        28
     335: aload         25
     337: invokevirtual #209                // Method scalaz/$eq$eq$greater$greater$Bin.r:()Lscalaz/$eq$eq$greater$greater;
     340: astore        29
     342: aload         24
     344: instanceof    #12                 // class scalaz/$eq$eq$greater$greater$Bin
     347: ifeq          447
     350: aload         24
     352: checkcast     #12                 // class scalaz/$eq$eq$greater$greater$Bin
     355: astore        30
     357: aload         25
     359: invokevirtual #475                // Method scalaz/$eq$eq$greater$greater$Bin.size:()I
     362: iconst_2
     363: aload         30
     365: invokevirtual #475                // Method scalaz/$eq$eq$greater$greater$Bin.size:()I
     368: imul
     369: if_icmpge     403
     372: new           #12                 // class scalaz/$eq$eq$greater$greater$Bin
     375: dup
     376: aload         21
     378: aload         22
     380: new           #12                 // class scalaz/$eq$eq$greater$greater$Bin
     383: dup
     384: aload_1
     385: aload_2
     386: getstatic     #66                 // Field scalaz/$eq$eq$greater$greater$Tip$.MODULE$:Lscalaz/$eq$eq$greater$greater$Tip$;
     389: invokevirtual #69                 // Method scalaz/$eq$eq$greater$greater$Tip$.apply:()Lscalaz/$eq$eq$greater$greater;
     392: aload         25
     394: invokespecial #108                // Method scalaz/$eq$eq$greater$greater$Bin."<init>":(Ljava/lang/Object;Ljava/lang/Object;Lscalaz/$eq$eq$greater$greater;Lscalaz/$eq$eq$greater$greater;)V
     397: aload         30
     399: invokespecial #108                // Method scalaz/$eq$eq$greater$greater$Bin."<init>":(Ljava/lang/Object;Ljava/lang/Object;Lscalaz/$eq$eq$greater$greater;Lscalaz/$eq$eq$greater$greater;)V
     402: areturn
     403: new           #12                 // class scalaz/$eq$eq$greater$greater$Bin
     406: dup
     407: aload         26
     409: aload         27
     411: new           #12                 // class scalaz/$eq$eq$greater$greater$Bin
     414: dup
     415: aload_1
     416: aload_2
     417: getstatic     #66                 // Field scalaz/$eq$eq$greater$greater$Tip$.MODULE$:Lscalaz/$eq$eq$greater$greater$Tip$;
     420: invokevirtual #69                 // Method scalaz/$eq$eq$greater$greater$Tip$.apply:()Lscalaz/$eq$eq$greater$greater;
     423: aload         28
     425: invokespecial #108                // Method scalaz/$eq$eq$greater$greater$Bin."<init>":(Ljava/lang/Object;Ljava/lang/Object;Lscalaz/$eq$eq$greater$greater;Lscalaz/$eq$eq$greater$greater;)V
     428: new           #12                 // class scalaz/$eq$eq$greater$greater$Bin
     431: dup
     432: aload         21
     434: aload         22
     436: aload         29
     438: aload         30
     440: invokespecial #108                // Method scalaz/$eq$eq$greater$greater$Bin."<init>":(Ljava/lang/Object;Ljava/lang/Object;Lscalaz/$eq$eq$greater$greater;Lscalaz/$eq$eq$greater$greater;)V
     443: invokespecial #108                // Method scalaz/$eq$eq$greater$greater$Bin."<init>":(Ljava/lang/Object;Ljava/lang/Object;Lscalaz/$eq$eq$greater$greater;Lscalaz/$eq$eq$greater$greater;)V
     446: areturn
     447: new           #146                // class scala/MatchError
     450: dup
     451: aload         4
     453: invokespecial #149                // Method scala/MatchError."<init>":(Ljava/lang/Object;)V
     456: athrow
     457: aload_3
     458: instanceof    #12                 // class scalaz/$eq$eq$greater$greater$Bin
     461: ifeq          1180
     464: aload_3
     465: checkcast     #12                 // class scalaz/$eq$eq$greater$greater$Bin
     468: astore        31
     470: aload         31
     472: invokevirtual #201                // Method scalaz/$eq$eq$greater$greater$Bin.k:()Ljava/lang/Object;
     475: astore        32
     477: aload         31
     479: invokevirtual #204                // Method scalaz/$eq$eq$greater$greater$Bin.v:()Ljava/lang/Object;
     482: astore        33
     484: aload         31
     486: invokevirtual #206                // Method scalaz/$eq$eq$greater$greater$Bin.l:()Lscalaz/$eq$eq$greater$greater;
     489: astore        34
     491: aload         31
     493: invokevirtual #209                // Method scalaz/$eq$eq$greater$greater$Bin.r:()Lscalaz/$eq$eq$greater$greater;
     496: astore        35
     498: aload         4
     500: instanceof    #17                 // class scalaz/$eq$eq$greater$greater$Tip
     503: ifeq          802
     506: new           #141                // class scala/Tuple2
     509: dup
     510: aload         34
     512: aload         35
     514: invokespecial #394                // Method scala/Tuple2."<init>":(Ljava/lang/Object;Ljava/lang/Object;)V
     517: astore        36
     519: aload         34
     521: instanceof    #17                 // class scalaz/$eq$eq$greater$greater$Tip
     524: ifeq          552
     527: aload         35
     529: instanceof    #17                 // class scalaz/$eq$eq$greater$greater$Tip
     532: ifeq          552
     535: new           #12                 // class scalaz/$eq$eq$greater$greater$Bin
     538: dup
     539: aload_1
     540: aload_2
     541: aload_3
     542: getstatic     #66                 // Field scalaz/$eq$eq$greater$greater$Tip$.MODULE$:Lscalaz/$eq$eq$greater$greater$Tip$;
     545: invokevirtual #69                 // Method scalaz/$eq$eq$greater$greater$Tip$.apply:()Lscalaz/$eq$eq$greater$greater;
     548: invokespecial #108                // Method scalaz/$eq$eq$greater$greater$Bin."<init>":(Ljava/lang/Object;Ljava/lang/Object;Lscalaz/$eq$eq$greater$greater;Lscalaz/$eq$eq$greater$greater;)V
     551: areturn
     552: aload         34
     554: instanceof    #17                 // class scalaz/$eq$eq$greater$greater$Tip
     557: ifeq          615
     560: aload         35
     562: instanceof    #12                 // class scalaz/$eq$eq$greater$greater$Bin
     565: ifeq          615
     568: aload         35
     570: checkcast     #12                 // class scalaz/$eq$eq$greater$greater$Bin
     573: astore        37
     575: aload         37
     577: invokevirtual #201                // Method scalaz/$eq$eq$greater$greater$Bin.k:()Ljava/lang/Object;
     580: astore        38
     582: aload         37
     584: invokevirtual #204                // Method scalaz/$eq$eq$greater$greater$Bin.v:()Ljava/lang/Object;
     587: astore        39
     589: new           #12                 // class scalaz/$eq$eq$greater$greater$Bin
     592: dup
     593: aload         38
     595: aload         39
     597: aload_0
     598: aload         32
     600: aload         33
     602: invokevirtual #199                // Method singleton:(Ljava/lang/Object;Ljava/lang/Object;)Lscalaz/$eq$eq$greater$greater;
     605: aload_0
     606: aload_1
     607: aload_2
     608: invokevirtual #199                // Method singleton:(Ljava/lang/Object;Ljava/lang/Object;)Lscalaz/$eq$eq$greater$greater;
     611: invokespecial #108                // Method scalaz/$eq$eq$greater$greater$Bin."<init>":(Ljava/lang/Object;Ljava/lang/Object;Lscalaz/$eq$eq$greater$greater;Lscalaz/$eq$eq$greater$greater;)V
     614: areturn
     615: aload         34
     617: instanceof    #12                 // class scalaz/$eq$eq$greater$greater$Bin
     620: ifeq          651
     623: aload         35
     625: instanceof    #17                 // class scalaz/$eq$eq$greater$greater$Tip
     628: ifeq          651
     631: new           #12                 // class scalaz/$eq$eq$greater$greater$Bin
     634: dup
     635: aload         32
     637: aload         33
     639: aload         34
     641: aload_0
     642: aload_1
     643: aload_2
     644: invokevirtual #199                // Method singleton:(Ljava/lang/Object;Ljava/lang/Object;)Lscalaz/$eq$eq$greater$greater;
     647: invokespecial #108                // Method scalaz/$eq$eq$greater$greater$Bin."<init>":(Ljava/lang/Object;Ljava/lang/Object;Lscalaz/$eq$eq$greater$greater;Lscalaz/$eq$eq$greater$greater;)V
     650: areturn
     651: aload         34
     653: instanceof    #12                 // class scalaz/$eq$eq$greater$greater$Bin
     656: ifeq          792
     659: aload         35
     661: instanceof    #12                 // class scalaz/$eq$eq$greater$greater$Bin
     664: ifeq          792
     667: aload         35
     669: checkcast     #12                 // class scalaz/$eq$eq$greater$greater$Bin
     672: astore        40
     674: aload         40
     676: invokevirtual #201                // Method scalaz/$eq$eq$greater$greater$Bin.k:()Ljava/lang/Object;
     679: astore        41
     681: aload         40
     683: invokevirtual #204                // Method scalaz/$eq$eq$greater$greater$Bin.v:()Ljava/lang/Object;
     686: astore        42
     688: aload         40
     690: invokevirtual #206                // Method scalaz/$eq$eq$greater$greater$Bin.l:()Lscalaz/$eq$eq$greater$greater;
     693: astore        43
     695: aload         40
     697: invokevirtual #209                // Method scalaz/$eq$eq$greater$greater$Bin.r:()Lscalaz/$eq$eq$greater$greater;
     700: astore        44
     702: aload         35
     704: invokevirtual #476                // Method scalaz/$eq$eq$greater$greater.size:()I
     707: iconst_2
     708: aload         34
     710: invokevirtual #476                // Method scalaz/$eq$eq$greater$greater.size:()I
     713: imul
     714: if_icmpge     748
     717: new           #12                 // class scalaz/$eq$eq$greater$greater$Bin
     720: dup
     721: aload         32
     723: aload         33
     725: aload         34
     727: new           #12                 // class scalaz/$eq$eq$greater$greater$Bin
     730: dup
     731: aload_1
     732: aload_2
     733: aload         35
     735: getstatic     #66                 // Field scalaz/$eq$eq$greater$greater$Tip$.MODULE$:Lscalaz/$eq$eq$greater$greater$Tip$;
     738: invokevirtual #69                 // Method scalaz/$eq$eq$greater$greater$Tip$.apply:()Lscalaz/$eq$eq$greater$greater;
     741: invokespecial #108                // Method scalaz/$eq$eq$greater$greater$Bin."<init>":(Ljava/lang/Object;Ljava/lang/Object;Lscalaz/$eq$eq$greater$greater;Lscalaz/$eq$eq$greater$greater;)V
     744: invokespecial #108                // Method scalaz/$eq$eq$greater$greater$Bin."<init>":(Ljava/lang/Object;Ljava/lang/Object;Lscalaz/$eq$eq$greater$greater;Lscalaz/$eq$eq$greater$greater;)V
     747: areturn
     748: new           #12                 // class scalaz/$eq$eq$greater$greater$Bin
     751: dup
     752: aload         41
     754: aload         42
     756: new           #12                 // class scalaz/$eq$eq$greater$greater$Bin
     759: dup
     760: aload         32
     762: aload         33
     764: aload         34
     766: aload         43
     768: invokespecial #108                // Method scalaz/$eq$eq$greater$greater$Bin."<init>":(Ljava/lang/Object;Ljava/lang/Object;Lscalaz/$eq$eq$greater$greater;Lscalaz/$eq$eq$greater$greater;)V
     771: new           #12                 // class scalaz/$eq$eq$greater$greater$Bin
     774: dup
     775: aload_1
     776: aload_2
     777: aload         44
     779: getstatic     #66                 // Field scalaz/$eq$eq$greater$greater$Tip$.MODULE$:Lscalaz/$eq$eq$greater$greater$Tip$;
     782: invokevirtual #69                 // Method scalaz/$eq$eq$greater$greater$Tip$.apply:()Lscalaz/$eq$eq$greater$greater;
     785: invokespecial #108                // Method scalaz/$eq$eq$greater$greater$Bin."<init>":(Ljava/lang/Object;Ljava/lang/Object;Lscalaz/$eq$eq$greater$greater;Lscalaz/$eq$eq$greater$greater;)V
     788: invokespecial #108                // Method scalaz/$eq$eq$greater$greater$Bin."<init>":(Ljava/lang/Object;Ljava/lang/Object;Lscalaz/$eq$eq$greater$greater;Lscalaz/$eq$eq$greater$greater;)V
     791: areturn
     792: new           #146                // class scala/MatchError
     795: dup
     796: aload         36
     798: invokespecial #149                // Method scala/MatchError."<init>":(Ljava/lang/Object;)V
     801: athrow
     802: aload         4
     804: instanceof    #12                 // class scalaz/$eq$eq$greater$greater$Bin
     807: ifeq          1170
     810: aload         4
     812: checkcast     #12                 // class scalaz/$eq$eq$greater$greater$Bin
     815: astore        45
     817: aload         45
     819: invokevirtual #201                // Method scalaz/$eq$eq$greater$greater$Bin.k:()Ljava/lang/Object;
     822: astore        46
     824: aload         45
     826: invokevirtual #204                // Method scalaz/$eq$eq$greater$greater$Bin.v:()Ljava/lang/Object;
     829: astore        47
     831: aload         45
     833: invokevirtual #206                // Method scalaz/$eq$eq$greater$greater$Bin.l:()Lscalaz/$eq$eq$greater$greater;
     836: astore        48
     838: aload         45
     840: invokevirtual #209                // Method scalaz/$eq$eq$greater$greater$Bin.r:()Lscalaz/$eq$eq$greater$greater;
     843: astore        49
     845: aload         4
     847: invokevirtual #476                // Method scalaz/$eq$eq$greater$greater.size:()I
     850: iconst_3
     851: aload_3
     852: invokevirtual #476                // Method scalaz/$eq$eq$greater$greater.size:()I
     855: imul
     856: if_icmple     1000
     859: aload         48
     861: instanceof    #12                 // class scalaz/$eq$eq$greater$greater$Bin
     864: ifeq          990
     867: aload         48
     869: checkcast     #12                 // class scalaz/$eq$eq$greater$greater$Bin
     872: astore        50
     874: aload         50
     876: invokevirtual #201                // Method scalaz/$eq$eq$greater$greater$Bin.k:()Ljava/lang/Object;
     879: astore        51
     881: aload         50
     883: invokevirtual #204                // Method scalaz/$eq$eq$greater$greater$Bin.v:()Ljava/lang/Object;
     886: astore        52
     888: aload         50
     890: invokevirtual #206                // Method scalaz/$eq$eq$greater$greater$Bin.l:()Lscalaz/$eq$eq$greater$greater;
     893: astore        53
     895: aload         50
     897: invokevirtual #209                // Method scalaz/$eq$eq$greater$greater$Bin.r:()Lscalaz/$eq$eq$greater$greater;
     900: astore        54
     902: aload         49
     904: instanceof    #12                 // class scalaz/$eq$eq$greater$greater$Bin
     907: ifeq          990
     910: aload         48
     912: invokevirtual #476                // Method scalaz/$eq$eq$greater$greater.size:()I
     915: iconst_2
     916: aload         49
     918: invokevirtual #476                // Method scalaz/$eq$eq$greater$greater.size:()I
     921: imul
     922: if_icmpge     951
     925: new           #12                 // class scalaz/$eq$eq$greater$greater$Bin
     928: dup
     929: aload         46
     931: aload         47
     933: new           #12                 // class scalaz/$eq$eq$greater$greater$Bin
     936: dup
     937: aload_1
     938: aload_2
     939: aload_3
     940: aload         48
     942: invokespecial #108                // Method scalaz/$eq$eq$greater$greater$Bin."<init>":(Ljava/lang/Object;Ljava/lang/Object;Lscalaz/$eq$eq$greater$greater;Lscalaz/$eq$eq$greater$greater;)V
     945: aload         49
     947: invokespecial #108                // Method scalaz/$eq$eq$greater$greater$Bin."<init>":(Ljava/lang/Object;Ljava/lang/Object;Lscalaz/$eq$eq$greater$greater;Lscalaz/$eq$eq$greater$greater;)V
     950: areturn
     951: new           #12                 // class scalaz/$eq$eq$greater$greater$Bin
     954: dup
     955: aload         51
     957: aload         52
     959: new           #12                 // class scalaz/$eq$eq$greater$greater$Bin
     962: dup
     963: aload_1
     964: aload_2
     965: aload_3
     966: aload         53
     968: invokespecial #108                // Method scalaz/$eq$eq$greater$greater$Bin."<init>":(Ljava/lang/Object;Ljava/lang/Object;Lscalaz/$eq$eq$greater$greater;Lscalaz/$eq$eq$greater$greater;)V
     971: new           #12                 // class scalaz/$eq$eq$greater$greater$Bin
     974: dup
     975: aload         46
     977: aload         47
     979: aload         54
     981: aload         49
     983: invokespecial #108                // Method scalaz/$eq$eq$greater$greater$Bin."<init>":(Ljava/lang/Object;Ljava/lang/Object;Lscalaz/$eq$eq$greater$greater;Lscalaz/$eq$eq$greater$greater;)V
     986: invokespecial #108                // Method scalaz/$eq$eq$greater$greater$Bin."<init>":(Ljava/lang/Object;Ljava/lang/Object;Lscalaz/$eq$eq$greater$greater;Lscalaz/$eq$eq$greater$greater;)V
     989: areturn
     990: getstatic     #425                // Field scala/sys/package$.MODULE$:Lscala/sys/package$;
     993: ldc_w         #478                // String Failure in Map.balance
     996: invokevirtual #431                // Method scala/sys/package$.error:(Ljava/lang/String;)Lscala/runtime/Nothing$;
     999: athrow
    1000: aload_3
    1001: invokevirtual #476                // Method scalaz/$eq$eq$greater$greater.size:()I
    1004: iconst_3
    1005: aload         4
    1007: invokevirtual #476                // Method scalaz/$eq$eq$greater$greater.size:()I
    1010: imul
    1011: if_icmple     1157
    1014: aload         34
    1016: instanceof    #12                 // class scalaz/$eq$eq$greater$greater$Bin
    1019: ifeq          1147
    1022: aload         35
    1024: instanceof    #12                 // class scalaz/$eq$eq$greater$greater$Bin
    1027: ifeq          1147
    1030: aload         35
    1032: checkcast     #12                 // class scalaz/$eq$eq$greater$greater$Bin
    1035: astore        55
    1037: aload         55
    1039: invokevirtual #201                // Method scalaz/$eq$eq$greater$greater$Bin.k:()Ljava/lang/Object;
    1042: astore        56
    1044: aload         55
    1046: invokevirtual #204                // Method scalaz/$eq$eq$greater$greater$Bin.v:()Ljava/lang/Object;
    1049: astore        57
    1051: aload         55
    1053: invokevirtual #206                // Method scalaz/$eq$eq$greater$greater$Bin.l:()Lscalaz/$eq$eq$greater$greater;
    1056: astore        58
    1058: aload         55
    1060: invokevirtual #209                // Method scalaz/$eq$eq$greater$greater$Bin.r:()Lscalaz/$eq$eq$greater$greater;
    1063: astore        59
    1065: aload         35
    1067: invokevirtual #476                // Method scalaz/$eq$eq$greater$greater.size:()I
    1070: iconst_2
    1071: aload         34
    1073: invokevirtual #476                // Method scalaz/$eq$eq$greater$greater.size:()I
    1076: imul
    1077: if_icmpge     1107
    1080: new           #12                 // class scalaz/$eq$eq$greater$greater$Bin
    1083: dup
    1084: aload         32
    1086: aload         33
    1088: aload         34
    1090: new           #12                 // class scalaz/$eq$eq$greater$greater$Bin
    1093: dup
    1094: aload_1
    1095: aload_2
    1096: aload         35
    1098: aload         4
    1100: invokespecial #108                // Method scalaz/$eq$eq$greater$greater$Bin."<init>":(Ljava/lang/Object;Ljava/lang/Object;Lscalaz/$eq$eq$greater$greater;Lscalaz/$eq$eq$greater$greater;)V
    1103: invokespecial #108                // Method scalaz/$eq$eq$greater$greater$Bin."<init>":(Ljava/lang/Object;Ljava/lang/Object;Lscalaz/$eq$eq$greater$greater;Lscalaz/$eq$eq$greater$greater;)V
    1106: areturn
    1107: new           #12                 // class scalaz/$eq$eq$greater$greater$Bin
    1110: dup
    1111: aload         56
    1113: aload         57
    1115: new           #12                 // class scalaz/$eq$eq$greater$greater$Bin
    1118: dup
    1119: aload         32
    1121: aload         33
    1123: aload         34
    1125: aload         58
    1127: invokespecial #108                // Method scalaz/$eq$eq$greater$greater$Bin."<init>":(Ljava/lang/Object;Ljava/lang/Object;Lscalaz/$eq$eq$greater$greater;Lscalaz/$eq$eq$greater$greater;)V
    1130: new           #12                 // class scalaz/$eq$eq$greater$greater$Bin
    1133: dup
    1134: aload_1
    1135: aload_2
    1136: aload         59
    1138: aload         4
    1140: invokespecial #108                // Method scalaz/$eq$eq$greater$greater$Bin."<init>":(Ljava/lang/Object;Ljava/lang/Object;Lscalaz/$eq$eq$greater$greater;Lscalaz/$eq$eq$greater$greater;)V
    1143: invokespecial #108                // Method scalaz/$eq$eq$greater$greater$Bin."<init>":(Ljava/lang/Object;Ljava/lang/Object;Lscalaz/$eq$eq$greater$greater;Lscalaz/$eq$eq$greater$greater;)V
    1146: areturn
    1147: getstatic     #425                // Field scala/sys/package$.MODULE$:Lscala/sys/package$;
    1150: ldc_w         #478                // String Failure in Map.balance
    1153: invokevirtual #431                // Method scala/sys/package$.error:(Ljava/lang/String;)Lscala/runtime/Nothing$;
    1156: athrow
    1157: new           #12                 // class scalaz/$eq$eq$greater$greater$Bin
    1160: dup
    1161: aload_1
    1162: aload_2
    1163: aload_3
    1164: aload         4
    1166: invokespecial #108                // Method scalaz/$eq$eq$greater$greater$Bin."<init>":(Ljava/lang/Object;Ljava/lang/Object;Lscalaz/$eq$eq$greater$greater;Lscalaz/$eq$eq$greater$greater;)V
    1169: areturn
    1170: new           #146                // class scala/MatchError
    1173: dup
    1174: aload         4
    1176: invokespecial #149                // Method scala/MatchError."<init>":(Ljava/lang/Object;)V
    1179: athrow
    1180: new           #146                // class scala/MatchError
    1183: dup
    1184: aload_3
    1185: invokespecial #149                // Method scala/MatchError."<init>":(Ljava/lang/Object;)V
    1188: athrow

  public <A, B> scalaz.$eq$eq$greater$greater<A, B> balanceL(A, B, scalaz.$eq$eq$greater$greater<A, B>, scalaz.$eq$eq$greater$greater<A, B>);
    Code:
       0: aload         4
       2: instanceof    #17                 // class scalaz/$eq$eq$greater$greater$Tip
       5: ifeq          453
       8: iconst_0
       9: istore        5
      11: aconst_null
      12: astore        6
      14: aload_3
      15: instanceof    #17                 // class scalaz/$eq$eq$greater$greater$Tip
      18: ifeq          28
      21: aload_0
      22: aload_1
      23: aload_2
      24: invokevirtual #199                // Method singleton:(Ljava/lang/Object;Ljava/lang/Object;)Lscalaz/$eq$eq$greater$greater;
      27: areturn
      28: aload_3
      29: instanceof    #12                 // class scalaz/$eq$eq$greater$greater$Bin
      32: ifeq          91
      35: iconst_1
      36: istore        5
      38: aload_3
      39: checkcast     #12                 // class scalaz/$eq$eq$greater$greater$Bin
      42: astore        6
      44: aload         6
      46: invokevirtual #206                // Method scalaz/$eq$eq$greater$greater$Bin.l:()Lscalaz/$eq$eq$greater$greater;
      49: astore        7
      51: aload         6
      53: invokevirtual #209                // Method scalaz/$eq$eq$greater$greater$Bin.r:()Lscalaz/$eq$eq$greater$greater;
      56: astore        8
      58: aload         7
      60: instanceof    #17                 // class scalaz/$eq$eq$greater$greater$Tip
      63: ifeq          91
      66: aload         8
      68: instanceof    #17                 // class scalaz/$eq$eq$greater$greater$Tip
      71: ifeq          91
      74: new           #12                 // class scalaz/$eq$eq$greater$greater$Bin
      77: dup
      78: aload_1
      79: aload_2
      80: aload_3
      81: getstatic     #66                 // Field scalaz/$eq$eq$greater$greater$Tip$.MODULE$:Lscalaz/$eq$eq$greater$greater$Tip$;
      84: invokevirtual #69                 // Method scalaz/$eq$eq$greater$greater$Tip$.apply:()Lscalaz/$eq$eq$greater$greater;
      87: invokespecial #108                // Method scalaz/$eq$eq$greater$greater$Bin."<init>":(Ljava/lang/Object;Ljava/lang/Object;Lscalaz/$eq$eq$greater$greater;Lscalaz/$eq$eq$greater$greater;)V
      90: areturn
      91: iload         5
      93: ifeq          187
      96: aload         6
      98: invokevirtual #201                // Method scalaz/$eq$eq$greater$greater$Bin.k:()Ljava/lang/Object;
     101: astore        9
     103: aload         6
     105: invokevirtual #204                // Method scalaz/$eq$eq$greater$greater$Bin.v:()Ljava/lang/Object;
     108: astore        10
     110: aload         6
     112: invokevirtual #206                // Method scalaz/$eq$eq$greater$greater$Bin.l:()Lscalaz/$eq$eq$greater$greater;
     115: astore        11
     117: aload         6
     119: invokevirtual #209                // Method scalaz/$eq$eq$greater$greater$Bin.r:()Lscalaz/$eq$eq$greater$greater;
     122: astore        12
     124: aload         11
     126: instanceof    #17                 // class scalaz/$eq$eq$greater$greater$Tip
     129: ifeq          187
     132: aload         12
     134: instanceof    #12                 // class scalaz/$eq$eq$greater$greater$Bin
     137: ifeq          187
     140: aload         12
     142: checkcast     #12                 // class scalaz/$eq$eq$greater$greater$Bin
     145: astore        13
     147: aload         13
     149: invokevirtual #201                // Method scalaz/$eq$eq$greater$greater$Bin.k:()Ljava/lang/Object;
     152: astore        14
     154: aload         13
     156: invokevirtual #204                // Method scalaz/$eq$eq$greater$greater$Bin.v:()Ljava/lang/Object;
     159: astore        15
     161: new           #12                 // class scalaz/$eq$eq$greater$greater$Bin
     164: dup
     165: aload         14
     167: aload         15
     169: aload_0
     170: aload         9
     172: aload         10
     174: invokevirtual #199                // Method singleton:(Ljava/lang/Object;Ljava/lang/Object;)Lscalaz/$eq$eq$greater$greater;
     177: aload_0
     178: aload_1
     179: aload_2
     180: invokevirtual #199                // Method singleton:(Ljava/lang/Object;Ljava/lang/Object;)Lscalaz/$eq$eq$greater$greater;
     183: invokespecial #108                // Method scalaz/$eq$eq$greater$greater$Bin."<init>":(Ljava/lang/Object;Ljava/lang/Object;Lscalaz/$eq$eq$greater$greater;Lscalaz/$eq$eq$greater$greater;)V
     186: areturn
     187: iload         5
     189: ifeq          263
     192: aload         6
     194: invokevirtual #201                // Method scalaz/$eq$eq$greater$greater$Bin.k:()Ljava/lang/Object;
     197: astore        16
     199: aload         6
     201: invokevirtual #204                // Method scalaz/$eq$eq$greater$greater$Bin.v:()Ljava/lang/Object;
     204: astore        17
     206: aload         6
     208: invokevirtual #206                // Method scalaz/$eq$eq$greater$greater$Bin.l:()Lscalaz/$eq$eq$greater$greater;
     211: astore        18
     213: aload         6
     215: invokevirtual #209                // Method scalaz/$eq$eq$greater$greater$Bin.r:()Lscalaz/$eq$eq$greater$greater;
     218: astore        19
     220: aload         18
     222: instanceof    #12                 // class scalaz/$eq$eq$greater$greater$Bin
     225: ifeq          263
     228: aload         18
     230: checkcast     #12                 // class scalaz/$eq$eq$greater$greater$Bin
     233: astore        20
     235: aload         19
     237: instanceof    #17                 // class scalaz/$eq$eq$greater$greater$Tip
     240: ifeq          263
     243: new           #12                 // class scalaz/$eq$eq$greater$greater$Bin
     246: dup
     247: aload         16
     249: aload         17
     251: aload         20
     253: aload_0
     254: aload_1
     255: aload_2
     256: invokevirtual #199                // Method singleton:(Ljava/lang/Object;Ljava/lang/Object;)Lscalaz/$eq$eq$greater$greater;
     259: invokespecial #108                // Method scalaz/$eq$eq$greater$greater$Bin."<init>":(Ljava/lang/Object;Ljava/lang/Object;Lscalaz/$eq$eq$greater$greater;Lscalaz/$eq$eq$greater$greater;)V
     262: areturn
     263: iload         5
     265: ifeq          444
     268: aload         6
     270: invokevirtual #201                // Method scalaz/$eq$eq$greater$greater$Bin.k:()Ljava/lang/Object;
     273: astore        21
     275: aload         6
     277: invokevirtual #204                // Method scalaz/$eq$eq$greater$greater$Bin.v:()Ljava/lang/Object;
     280: astore        22
     282: aload         6
     284: invokevirtual #206                // Method scalaz/$eq$eq$greater$greater$Bin.l:()Lscalaz/$eq$eq$greater$greater;
     287: astore        23
     289: aload         6
     291: invokevirtual #209                // Method scalaz/$eq$eq$greater$greater$Bin.r:()Lscalaz/$eq$eq$greater$greater;
     294: astore        24
     296: aload         23
     298: instanceof    #12                 // class scalaz/$eq$eq$greater$greater$Bin
     301: ifeq          444
     304: aload         23
     306: checkcast     #12                 // class scalaz/$eq$eq$greater$greater$Bin
     309: astore        25
     311: aload         24
     313: instanceof    #12                 // class scalaz/$eq$eq$greater$greater$Bin
     316: ifeq          444
     319: aload         24
     321: checkcast     #12                 // class scalaz/$eq$eq$greater$greater$Bin
     324: astore        26
     326: aload         26
     328: invokevirtual #201                // Method scalaz/$eq$eq$greater$greater$Bin.k:()Ljava/lang/Object;
     331: astore        27
     333: aload         26
     335: invokevirtual #204                // Method scalaz/$eq$eq$greater$greater$Bin.v:()Ljava/lang/Object;
     338: astore        28
     340: aload         26
     342: invokevirtual #206                // Method scalaz/$eq$eq$greater$greater$Bin.l:()Lscalaz/$eq$eq$greater$greater;
     345: astore        29
     347: aload         26
     349: invokevirtual #209                // Method scalaz/$eq$eq$greater$greater$Bin.r:()Lscalaz/$eq$eq$greater$greater;
     352: astore        30
     354: aload         26
     356: invokevirtual #475                // Method scalaz/$eq$eq$greater$greater$Bin.size:()I
     359: iconst_2
     360: aload         25
     362: invokevirtual #475                // Method scalaz/$eq$eq$greater$greater$Bin.size:()I
     365: imul
     366: if_icmpge     400
     369: new           #12                 // class scalaz/$eq$eq$greater$greater$Bin
     372: dup
     373: aload         21
     375: aload         22
     377: aload         25
     379: new           #12                 // class scalaz/$eq$eq$greater$greater$Bin
     382: dup
     383: aload_1
     384: aload_2
     385: aload         26
     387: getstatic     #66                 // Field scalaz/$eq$eq$greater$greater$Tip$.MODULE$:Lscalaz/$eq$eq$greater$greater$Tip$;
     390: invokevirtual #69                 // Method scalaz/$eq$eq$greater$greater$Tip$.apply:()Lscalaz/$eq$eq$greater$greater;
     393: invokespecial #108                // Method scalaz/$eq$eq$greater$greater$Bin."<init>":(Ljava/lang/Object;Ljava/lang/Object;Lscalaz/$eq$eq$greater$greater;Lscalaz/$eq$eq$greater$greater;)V
     396: invokespecial #108                // Method scalaz/$eq$eq$greater$greater$Bin."<init>":(Ljava/lang/Object;Ljava/lang/Object;Lscalaz/$eq$eq$greater$greater;Lscalaz/$eq$eq$greater$greater;)V
     399: areturn
     400: new           #12                 // class scalaz/$eq$eq$greater$greater$Bin
     403: dup
     404: aload         27
     406: aload         28
     408: new           #12                 // class scalaz/$eq$eq$greater$greater$Bin
     411: dup
     412: aload         21
     414: aload         22
     416: aload         25
     418: aload         29
     420: invokespecial #108                // Method scalaz/$eq$eq$greater$greater$Bin."<init>":(Ljava/lang/Object;Ljava/lang/Object;Lscalaz/$eq$eq$greater$greater;Lscalaz/$eq$eq$greater$greater;)V
     423: new           #12                 // class scalaz/$eq$eq$greater$greater$Bin
     426: dup
     427: aload_1
     428: aload_2
     429: aload         30
     431: getstatic     #66                 // Field scalaz/$eq$eq$greater$greater$Tip$.MODULE$:Lscalaz/$eq$eq$greater$greater$Tip$;
     434: invokevirtual #69                 // Method scalaz/$eq$eq$greater$greater$Tip$.apply:()Lscalaz/$eq$eq$greater$greater;
     437: invokespecial #108                // Method scalaz/$eq$eq$greater$greater$Bin."<init>":(Ljava/lang/Object;Ljava/lang/Object;Lscalaz/$eq$eq$greater$greater;Lscalaz/$eq$eq$greater$greater;)V
     440: invokespecial #108                // Method scalaz/$eq$eq$greater$greater$Bin."<init>":(Ljava/lang/Object;Ljava/lang/Object;Lscalaz/$eq$eq$greater$greater;Lscalaz/$eq$eq$greater$greater;)V
     443: areturn
     444: new           #146                // class scala/MatchError
     447: dup
     448: aload_3
     449: invokespecial #149                // Method scala/MatchError."<init>":(Ljava/lang/Object;)V
     452: athrow
     453: aload         4
     455: instanceof    #12                 // class scalaz/$eq$eq$greater$greater$Bin
     458: ifeq          706
     461: aload_3
     462: instanceof    #17                 // class scalaz/$eq$eq$greater$greater$Tip
     465: ifeq          486
     468: new           #12                 // class scalaz/$eq$eq$greater$greater$Bin
     471: dup
     472: aload_1
     473: aload_2
     474: getstatic     #66                 // Field scalaz/$eq$eq$greater$greater$Tip$.MODULE$:Lscalaz/$eq$eq$greater$greater$Tip$;
     477: invokevirtual #69                 // Method scalaz/$eq$eq$greater$greater$Tip$.apply:()Lscalaz/$eq$eq$greater$greater;
     480: aload         4
     482: invokespecial #108                // Method scalaz/$eq$eq$greater$greater$Bin."<init>":(Ljava/lang/Object;Ljava/lang/Object;Lscalaz/$eq$eq$greater$greater;Lscalaz/$eq$eq$greater$greater;)V
     485: areturn
     486: aload_3
     487: instanceof    #12                 // class scalaz/$eq$eq$greater$greater$Bin
     490: ifeq          697
     493: aload_3
     494: checkcast     #12                 // class scalaz/$eq$eq$greater$greater$Bin
     497: astore        31
     499: aload         31
     501: invokevirtual #201                // Method scalaz/$eq$eq$greater$greater$Bin.k:()Ljava/lang/Object;
     504: astore        32
     506: aload         31
     508: invokevirtual #204                // Method scalaz/$eq$eq$greater$greater$Bin.v:()Ljava/lang/Object;
     511: astore        33
     513: aload         31
     515: invokevirtual #206                // Method scalaz/$eq$eq$greater$greater$Bin.l:()Lscalaz/$eq$eq$greater$greater;
     518: astore        34
     520: aload         31
     522: invokevirtual #209                // Method scalaz/$eq$eq$greater$greater$Bin.r:()Lscalaz/$eq$eq$greater$greater;
     525: astore        35
     527: aload_3
     528: invokevirtual #476                // Method scalaz/$eq$eq$greater$greater.size:()I
     531: iconst_3
     532: aload         4
     534: invokevirtual #476                // Method scalaz/$eq$eq$greater$greater.size:()I
     537: imul
     538: if_icmple     684
     541: aload         34
     543: instanceof    #12                 // class scalaz/$eq$eq$greater$greater$Bin
     546: ifeq          674
     549: aload         35
     551: instanceof    #12                 // class scalaz/$eq$eq$greater$greater$Bin
     554: ifeq          674
     557: aload         35
     559: checkcast     #12                 // class scalaz/$eq$eq$greater$greater$Bin
     562: astore        36
     564: aload         36
     566: invokevirtual #201                // Method scalaz/$eq$eq$greater$greater$Bin.k:()Ljava/lang/Object;
     569: astore        37
     571: aload         36
     573: invokevirtual #204                // Method scalaz/$eq$eq$greater$greater$Bin.v:()Ljava/lang/Object;
     576: astore        38
     578: aload         36
     580: invokevirtual #206                // Method scalaz/$eq$eq$greater$greater$Bin.l:()Lscalaz/$eq$eq$greater$greater;
     583: astore        39
     585: aload         36
     587: invokevirtual #209                // Method scalaz/$eq$eq$greater$greater$Bin.r:()Lscalaz/$eq$eq$greater$greater;
     590: astore        40
     592: aload         35
     594: invokevirtual #476                // Method scalaz/$eq$eq$greater$greater.size:()I
     597: iconst_2
     598: aload         34
     600: invokevirtual #476                // Method scalaz/$eq$eq$greater$greater.size:()I
     603: imul
     604: if_icmpge     634
     607: new           #12                 // class scalaz/$eq$eq$greater$greater$Bin
     610: dup
     611: aload         32
     613: aload         33
     615: aload         34
     617: new           #12                 // class scalaz/$eq$eq$greater$greater$Bin
     620: dup
     621: aload_1
     622: aload_2
     623: aload         35
     625: aload         4
     627: invokespecial #108                // Method scalaz/$eq$eq$greater$greater$Bin."<init>":(Ljava/lang/Object;Ljava/lang/Object;Lscalaz/$eq$eq$greater$greater;Lscalaz/$eq$eq$greater$greater;)V
     630: invokespecial #108                // Method scalaz/$eq$eq$greater$greater$Bin."<init>":(Ljava/lang/Object;Ljava/lang/Object;Lscalaz/$eq$eq$greater$greater;Lscalaz/$eq$eq$greater$greater;)V
     633: areturn
     634: new           #12                 // class scalaz/$eq$eq$greater$greater$Bin
     637: dup
     638: aload         37
     640: aload         38
     642: new           #12                 // class scalaz/$eq$eq$greater$greater$Bin
     645: dup
     646: aload         32
     648: aload         33
     650: aload         34
     652: aload         39
     654: invokespecial #108                // Method scalaz/$eq$eq$greater$greater$Bin."<init>":(Ljava/lang/Object;Ljava/lang/Object;Lscalaz/$eq$eq$greater$greater;Lscalaz/$eq$eq$greater$greater;)V
     657: new           #12                 // class scalaz/$eq$eq$greater$greater$Bin
     660: dup
     661: aload_1
     662: aload_2
     663: aload         40
     665: aload         4
     667: invokespecial #108                // Method scalaz/$eq$eq$greater$greater$Bin."<init>":(Ljava/lang/Object;Ljava/lang/Object;Lscalaz/$eq$eq$greater$greater;Lscalaz/$eq$eq$greater$greater;)V
     670: invokespecial #108                // Method scalaz/$eq$eq$greater$greater$Bin."<init>":(Ljava/lang/Object;Ljava/lang/Object;Lscalaz/$eq$eq$greater$greater;Lscalaz/$eq$eq$greater$greater;)V
     673: areturn
     674: getstatic     #425                // Field scala/sys/package$.MODULE$:Lscala/sys/package$;
     677: ldc_w         #496                // String Failure in Map.balanceL
     680: invokevirtual #431                // Method scala/sys/package$.error:(Ljava/lang/String;)Lscala/runtime/Nothing$;
     683: athrow
     684: new           #12                 // class scalaz/$eq$eq$greater$greater$Bin
     687: dup
     688: aload_1
     689: aload_2
     690: aload_3
     691: aload         4
     693: invokespecial #108                // Method scalaz/$eq$eq$greater$greater$Bin."<init>":(Ljava/lang/Object;Ljava/lang/Object;Lscalaz/$eq$eq$greater$greater;Lscalaz/$eq$eq$greater$greater;)V
     696: areturn
     697: new           #146                // class scala/MatchError
     700: dup
     701: aload_3
     702: invokespecial #149                // Method scala/MatchError."<init>":(Ljava/lang/Object;)V
     705: athrow
     706: new           #146                // class scala/MatchError
     709: dup
     710: aload         4
     712: invokespecial #149                // Method scala/MatchError."<init>":(Ljava/lang/Object;)V
     715: athrow

  public <A, B> scalaz.$eq$eq$greater$greater<A, B> balanceR(A, B, scalaz.$eq$eq$greater$greater<A, B>, scalaz.$eq$eq$greater$greater<A, B>);
    Code:
       0: aload_3
       1: instanceof    #17                 // class scalaz/$eq$eq$greater$greater$Tip
       4: ifeq          457
       7: iconst_0
       8: istore        5
      10: aconst_null
      11: astore        6
      13: aload         4
      15: instanceof    #17                 // class scalaz/$eq$eq$greater$greater$Tip
      18: ifeq          28
      21: aload_0
      22: aload_1
      23: aload_2
      24: invokevirtual #199                // Method singleton:(Ljava/lang/Object;Ljava/lang/Object;)Lscalaz/$eq$eq$greater$greater;
      27: areturn
      28: aload         4
      30: instanceof    #12                 // class scalaz/$eq$eq$greater$greater$Bin
      33: ifeq          94
      36: iconst_1
      37: istore        5
      39: aload         4
      41: checkcast     #12                 // class scalaz/$eq$eq$greater$greater$Bin
      44: astore        6
      46: aload         6
      48: invokevirtual #206                // Method scalaz/$eq$eq$greater$greater$Bin.l:()Lscalaz/$eq$eq$greater$greater;
      51: astore        7
      53: aload         6
      55: invokevirtual #209                // Method scalaz/$eq$eq$greater$greater$Bin.r:()Lscalaz/$eq$eq$greater$greater;
      58: astore        8
      60: aload         7
      62: instanceof    #17                 // class scalaz/$eq$eq$greater$greater$Tip
      65: ifeq          94
      68: aload         8
      70: instanceof    #17                 // class scalaz/$eq$eq$greater$greater$Tip
      73: ifeq          94
      76: new           #12                 // class scalaz/$eq$eq$greater$greater$Bin
      79: dup
      80: aload_1
      81: aload_2
      82: getstatic     #66                 // Field scalaz/$eq$eq$greater$greater$Tip$.MODULE$:Lscalaz/$eq$eq$greater$greater$Tip$;
      85: invokevirtual #69                 // Method scalaz/$eq$eq$greater$greater$Tip$.apply:()Lscalaz/$eq$eq$greater$greater;
      88: aload         4
      90: invokespecial #108                // Method scalaz/$eq$eq$greater$greater$Bin."<init>":(Ljava/lang/Object;Ljava/lang/Object;Lscalaz/$eq$eq$greater$greater;Lscalaz/$eq$eq$greater$greater;)V
      93: areturn
      94: iload         5
      96: ifeq          170
      99: aload         6
     101: invokevirtual #201                // Method scalaz/$eq$eq$greater$greater$Bin.k:()Ljava/lang/Object;
     104: astore        9
     106: aload         6
     108: invokevirtual #204                // Method scalaz/$eq$eq$greater$greater$Bin.v:()Ljava/lang/Object;
     111: astore        10
     113: aload         6
     115: invokevirtual #206                // Method scalaz/$eq$eq$greater$greater$Bin.l:()Lscalaz/$eq$eq$greater$greater;
     118: astore        11
     120: aload         6
     122: invokevirtual #209                // Method scalaz/$eq$eq$greater$greater$Bin.r:()Lscalaz/$eq$eq$greater$greater;
     125: astore        12
     127: aload         11
     129: instanceof    #17                 // class scalaz/$eq$eq$greater$greater$Tip
     132: ifeq          170
     135: aload         12
     137: instanceof    #12                 // class scalaz/$eq$eq$greater$greater$Bin
     140: ifeq          170
     143: aload         12
     145: checkcast     #12                 // class scalaz/$eq$eq$greater$greater$Bin
     148: astore        13
     150: new           #12                 // class scalaz/$eq$eq$greater$greater$Bin
     153: dup
     154: aload         9
     156: aload         10
     158: aload_0
     159: aload_1
     160: aload_2
     161: invokevirtual #199                // Method singleton:(Ljava/lang/Object;Ljava/lang/Object;)Lscalaz/$eq$eq$greater$greater;
     164: aload         13
     166: invokespecial #108                // Method scalaz/$eq$eq$greater$greater$Bin."<init>":(Ljava/lang/Object;Ljava/lang/Object;Lscalaz/$eq$eq$greater$greater;Lscalaz/$eq$eq$greater$greater;)V
     169: areturn
     170: iload         5
     172: ifeq          266
     175: aload         6
     177: invokevirtual #201                // Method scalaz/$eq$eq$greater$greater$Bin.k:()Ljava/lang/Object;
     180: astore        14
     182: aload         6
     184: invokevirtual #204                // Method scalaz/$eq$eq$greater$greater$Bin.v:()Ljava/lang/Object;
     187: astore        15
     189: aload         6
     191: invokevirtual #206                // Method scalaz/$eq$eq$greater$greater$Bin.l:()Lscalaz/$eq$eq$greater$greater;
     194: astore        16
     196: aload         6
     198: invokevirtual #209                // Method scalaz/$eq$eq$greater$greater$Bin.r:()Lscalaz/$eq$eq$greater$greater;
     201: astore        17
     203: aload         16
     205: instanceof    #12                 // class scalaz/$eq$eq$greater$greater$Bin
     208: ifeq          266
     211: aload         16
     213: checkcast     #12                 // class scalaz/$eq$eq$greater$greater$Bin
     216: astore        18
     218: aload         18
     220: invokevirtual #201                // Method scalaz/$eq$eq$greater$greater$Bin.k:()Ljava/lang/Object;
     223: astore        19
     225: aload         18
     227: invokevirtual #204                // Method scalaz/$eq$eq$greater$greater$Bin.v:()Ljava/lang/Object;
     230: astore        20
     232: aload         17
     234: instanceof    #17                 // class scalaz/$eq$eq$greater$greater$Tip
     237: ifeq          266
     240: new           #12                 // class scalaz/$eq$eq$greater$greater$Bin
     243: dup
     244: aload         19
     246: aload         20
     248: aload_0
     249: aload_1
     250: aload_2
     251: invokevirtual #199                // Method singleton:(Ljava/lang/Object;Ljava/lang/Object;)Lscalaz/$eq$eq$greater$greater;
     254: aload_0
     255: aload         14
     257: aload         15
     259: invokevirtual #199                // Method singleton:(Ljava/lang/Object;Ljava/lang/Object;)Lscalaz/$eq$eq$greater$greater;
     262: invokespecial #108                // Method scalaz/$eq$eq$greater$greater$Bin."<init>":(Ljava/lang/Object;Ljava/lang/Object;Lscalaz/$eq$eq$greater$greater;Lscalaz/$eq$eq$greater$greater;)V
     265: areturn
     266: iload         5
     268: ifeq          447
     271: aload         6
     273: invokevirtual #201                // Method scalaz/$eq$eq$greater$greater$Bin.k:()Ljava/lang/Object;
     276: astore        21
     278: aload         6
     280: invokevirtual #204                // Method scalaz/$eq$eq$greater$greater$Bin.v:()Ljava/lang/Object;
     283: astore        22
     285: aload         6
     287: invokevirtual #206                // Method scalaz/$eq$eq$greater$greater$Bin.l:()Lscalaz/$eq$eq$greater$greater;
     290: astore        23
     292: aload         6
     294: invokevirtual #209                // Method scalaz/$eq$eq$greater$greater$Bin.r:()Lscalaz/$eq$eq$greater$greater;
     297: astore        24
     299: aload         23
     301: instanceof    #12                 // class scalaz/$eq$eq$greater$greater$Bin
     304: ifeq          447
     307: aload         23
     309: checkcast     #12                 // class scalaz/$eq$eq$greater$greater$Bin
     312: astore        25
     314: aload         25
     316: invokevirtual #201                // Method scalaz/$eq$eq$greater$greater$Bin.k:()Ljava/lang/Object;
     319: astore        26
     321: aload         25
     323: invokevirtual #204                // Method scalaz/$eq$eq$greater$greater$Bin.v:()Ljava/lang/Object;
     326: astore        27
     328: aload         25
     330: invokevirtual #206                // Method scalaz/$eq$eq$greater$greater$Bin.l:()Lscalaz/$eq$eq$greater$greater;
     333: astore        28
     335: aload         25
     337: invokevirtual #209                // Method scalaz/$eq$eq$greater$greater$Bin.r:()Lscalaz/$eq$eq$greater$greater;
     340: astore        29
     342: aload         24
     344: instanceof    #12                 // class scalaz/$eq$eq$greater$greater$Bin
     347: ifeq          447
     350: aload         24
     352: checkcast     #12                 // class scalaz/$eq$eq$greater$greater$Bin
     355: astore        30
     357: aload         25
     359: invokevirtual #475                // Method scalaz/$eq$eq$greater$greater$Bin.size:()I
     362: iconst_2
     363: aload         30
     365: invokevirtual #475                // Method scalaz/$eq$eq$greater$greater$Bin.size:()I
     368: imul
     369: if_icmpge     403
     372: new           #12                 // class scalaz/$eq$eq$greater$greater$Bin
     375: dup
     376: aload         21
     378: aload         22
     380: new           #12                 // class scalaz/$eq$eq$greater$greater$Bin
     383: dup
     384: aload_1
     385: aload_2
     386: getstatic     #66                 // Field scalaz/$eq$eq$greater$greater$Tip$.MODULE$:Lscalaz/$eq$eq$greater$greater$Tip$;
     389: invokevirtual #69                 // Method scalaz/$eq$eq$greater$greater$Tip$.apply:()Lscalaz/$eq$eq$greater$greater;
     392: aload         25
     394: invokespecial #108                // Method scalaz/$eq$eq$greater$greater$Bin."<init>":(Ljava/lang/Object;Ljava/lang/Object;Lscalaz/$eq$eq$greater$greater;Lscalaz/$eq$eq$greater$greater;)V
     397: aload         30
     399: invokespecial #108                // Method scalaz/$eq$eq$greater$greater$Bin."<init>":(Ljava/lang/Object;Ljava/lang/Object;Lscalaz/$eq$eq$greater$greater;Lscalaz/$eq$eq$greater$greater;)V
     402: areturn
     403: new           #12                 // class scalaz/$eq$eq$greater$greater$Bin
     406: dup
     407: aload         26
     409: aload         27
     411: new           #12                 // class scalaz/$eq$eq$greater$greater$Bin
     414: dup
     415: aload_1
     416: aload_2
     417: getstatic     #66                 // Field scalaz/$eq$eq$greater$greater$Tip$.MODULE$:Lscalaz/$eq$eq$greater$greater$Tip$;
     420: invokevirtual #69                 // Method scalaz/$eq$eq$greater$greater$Tip$.apply:()Lscalaz/$eq$eq$greater$greater;
     423: aload         28
     425: invokespecial #108                // Method scalaz/$eq$eq$greater$greater$Bin."<init>":(Ljava/lang/Object;Ljava/lang/Object;Lscalaz/$eq$eq$greater$greater;Lscalaz/$eq$eq$greater$greater;)V
     428: new           #12                 // class scalaz/$eq$eq$greater$greater$Bin
     431: dup
     432: aload         21
     434: aload         22
     436: aload         29
     438: aload         30
     440: invokespecial #108                // Method scalaz/$eq$eq$greater$greater$Bin."<init>":(Ljava/lang/Object;Ljava/lang/Object;Lscalaz/$eq$eq$greater$greater;Lscalaz/$eq$eq$greater$greater;)V
     443: invokespecial #108                // Method scalaz/$eq$eq$greater$greater$Bin."<init>":(Ljava/lang/Object;Ljava/lang/Object;Lscalaz/$eq$eq$greater$greater;Lscalaz/$eq$eq$greater$greater;)V
     446: areturn
     447: new           #146                // class scala/MatchError
     450: dup
     451: aload         4
     453: invokespecial #149                // Method scala/MatchError."<init>":(Ljava/lang/Object;)V
     456: athrow
     457: aload_3
     458: instanceof    #12                 // class scalaz/$eq$eq$greater$greater$Bin
     461: ifeq          710
     464: aload         4
     466: instanceof    #17                 // class scalaz/$eq$eq$greater$greater$Tip
     469: ifeq          489
     472: new           #12                 // class scalaz/$eq$eq$greater$greater$Bin
     475: dup
     476: aload_1
     477: aload_2
     478: aload_3
     479: getstatic     #66                 // Field scalaz/$eq$eq$greater$greater$Tip$.MODULE$:Lscalaz/$eq$eq$greater$greater$Tip$;
     482: invokevirtual #69                 // Method scalaz/$eq$eq$greater$greater$Tip$.apply:()Lscalaz/$eq$eq$greater$greater;
     485: invokespecial #108                // Method scalaz/$eq$eq$greater$greater$Bin."<init>":(Ljava/lang/Object;Ljava/lang/Object;Lscalaz/$eq$eq$greater$greater;Lscalaz/$eq$eq$greater$greater;)V
     488: areturn
     489: aload         4
     491: instanceof    #12                 // class scalaz/$eq$eq$greater$greater$Bin
     494: ifeq          700
     497: aload         4
     499: checkcast     #12                 // class scalaz/$eq$eq$greater$greater$Bin
     502: astore        31
     504: aload         31
     506: invokevirtual #201                // Method scalaz/$eq$eq$greater$greater$Bin.k:()Ljava/lang/Object;
     509: astore        32
     511: aload         31
     513: invokevirtual #204                // Method scalaz/$eq$eq$greater$greater$Bin.v:()Ljava/lang/Object;
     516: astore        33
     518: aload         31
     520: invokevirtual #206                // Method scalaz/$eq$eq$greater$greater$Bin.l:()Lscalaz/$eq$eq$greater$greater;
     523: astore        34
     525: aload         31
     527: invokevirtual #209                // Method scalaz/$eq$eq$greater$greater$Bin.r:()Lscalaz/$eq$eq$greater$greater;
     530: astore        35
     532: aload         4
     534: invokevirtual #476                // Method scalaz/$eq$eq$greater$greater.size:()I
     537: iconst_3
     538: aload_3
     539: invokevirtual #476                // Method scalaz/$eq$eq$greater$greater.size:()I
     542: imul
     543: if_icmple     687
     546: aload         34
     548: instanceof    #12                 // class scalaz/$eq$eq$greater$greater$Bin
     551: ifeq          677
     554: aload         34
     556: checkcast     #12                 // class scalaz/$eq$eq$greater$greater$Bin
     559: astore        36
     561: aload         36
     563: invokevirtual #201                // Method scalaz/$eq$eq$greater$greater$Bin.k:()Ljava/lang/Object;
     566: astore        37
     568: aload         36
     570: invokevirtual #204                // Method scalaz/$eq$eq$greater$greater$Bin.v:()Ljava/lang/Object;
     573: astore        38
     575: aload         36
     577: invokevirtual #206                // Method scalaz/$eq$eq$greater$greater$Bin.l:()Lscalaz/$eq$eq$greater$greater;
     580: astore        39
     582: aload         36
     584: invokevirtual #209                // Method scalaz/$eq$eq$greater$greater$Bin.r:()Lscalaz/$eq$eq$greater$greater;
     587: astore        40
     589: aload         35
     591: instanceof    #12                 // class scalaz/$eq$eq$greater$greater$Bin
     594: ifeq          677
     597: aload         34
     599: invokevirtual #476                // Method scalaz/$eq$eq$greater$greater.size:()I
     602: iconst_2
     603: aload         35
     605: invokevirtual #476                // Method scalaz/$eq$eq$greater$greater.size:()I
     608: imul
     609: if_icmpge     638
     612: new           #12                 // class scalaz/$eq$eq$greater$greater$Bin
     615: dup
     616: aload         32
     618: aload         33
     620: new           #12                 // class scalaz/$eq$eq$greater$greater$Bin
     623: dup
     624: aload_1
     625: aload_2
     626: aload_3
     627: aload         34
     629: invokespecial #108                // Method scalaz/$eq$eq$greater$greater$Bin."<init>":(Ljava/lang/Object;Ljava/lang/Object;Lscalaz/$eq$eq$greater$greater;Lscalaz/$eq$eq$greater$greater;)V
     632: aload         35
     634: invokespecial #108                // Method scalaz/$eq$eq$greater$greater$Bin."<init>":(Ljava/lang/Object;Ljava/lang/Object;Lscalaz/$eq$eq$greater$greater;Lscalaz/$eq$eq$greater$greater;)V
     637: areturn
     638: new           #12                 // class scalaz/$eq$eq$greater$greater$Bin
     641: dup
     642: aload         37
     644: aload         38
     646: new           #12                 // class scalaz/$eq$eq$greater$greater$Bin
     649: dup
     650: aload_1
     651: aload_2
     652: aload_3
     653: aload         39
     655: invokespecial #108                // Method scalaz/$eq$eq$greater$greater$Bin."<init>":(Ljava/lang/Object;Ljava/lang/Object;Lscalaz/$eq$eq$greater$greater;Lscalaz/$eq$eq$greater$greater;)V
     658: new           #12                 // class scalaz/$eq$eq$greater$greater$Bin
     661: dup
     662: aload         32
     664: aload         33
     666: aload         40
     668: aload         35
     670: invokespecial #108                // Method scalaz/$eq$eq$greater$greater$Bin."<init>":(Ljava/lang/Object;Ljava/lang/Object;Lscalaz/$eq$eq$greater$greater;Lscalaz/$eq$eq$greater$greater;)V
     673: invokespecial #108                // Method scalaz/$eq$eq$greater$greater$Bin."<init>":(Ljava/lang/Object;Ljava/lang/Object;Lscalaz/$eq$eq$greater$greater;Lscalaz/$eq$eq$greater$greater;)V
     676: areturn
     677: getstatic     #425                // Field scala/sys/package$.MODULE$:Lscala/sys/package$;
     680: ldc_w         #498                // String Failure in Map.balanceR
     683: invokevirtual #431                // Method scala/sys/package$.error:(Ljava/lang/String;)Lscala/runtime/Nothing$;
     686: athrow
     687: new           #12                 // class scalaz/$eq$eq$greater$greater$Bin
     690: dup
     691: aload_1
     692: aload_2
     693: aload_3
     694: aload         4
     696: invokespecial #108                // Method scalaz/$eq$eq$greater$greater$Bin."<init>":(Ljava/lang/Object;Ljava/lang/Object;Lscalaz/$eq$eq$greater$greater;Lscalaz/$eq$eq$greater$greater;)V
     699: areturn
     700: new           #146                // class scala/MatchError
     703: dup
     704: aload         4
     706: invokespecial #149                // Method scala/MatchError."<init>":(Ljava/lang/Object;)V
     709: athrow
     710: new           #146                // class scala/MatchError
     713: dup
     714: aload_3
     715: invokespecial #149                // Method scala/MatchError."<init>":(Ljava/lang/Object;)V
     718: athrow

  public <A, B> scalaz.$eq$eq$greater$greater<A, B> link(A, B, scalaz.$eq$eq$greater$greater<A, B>, scalaz.$eq$eq$greater$greater<A, B>);
    Code:
       0: new           #141                // class scala/Tuple2
       3: dup
       4: aload_3
       5: aload         4
       7: invokespecial #394                // Method scala/Tuple2."<init>":(Ljava/lang/Object;Ljava/lang/Object;)V
      10: astore        5
      12: aload_3
      13: instanceof    #17                 // class scalaz/$eq$eq$greater$greater$Tip
      16: ifeq          28
      19: aload_0
      20: aload_1
      21: aload_2
      22: aload         4
      24: invokespecial #503                // Method insertMin:(Ljava/lang/Object;Ljava/lang/Object;Lscalaz/$eq$eq$greater$greater;)Lscalaz/$eq$eq$greater$greater;
      27: areturn
      28: aload         4
      30: instanceof    #17                 // class scalaz/$eq$eq$greater$greater$Tip
      33: ifeq          44
      36: aload_0
      37: aload_1
      38: aload_2
      39: aload_3
      40: invokespecial #506                // Method insertMax:(Ljava/lang/Object;Ljava/lang/Object;Lscalaz/$eq$eq$greater$greater;)Lscalaz/$eq$eq$greater$greater;
      43: areturn
      44: aload_3
      45: instanceof    #12                 // class scalaz/$eq$eq$greater$greater$Bin
      48: ifeq          210
      51: aload_3
      52: checkcast     #12                 // class scalaz/$eq$eq$greater$greater$Bin
      55: astore        6
      57: aload         6
      59: invokevirtual #201                // Method scalaz/$eq$eq$greater$greater$Bin.k:()Ljava/lang/Object;
      62: astore        7
      64: aload         6
      66: invokevirtual #204                // Method scalaz/$eq$eq$greater$greater$Bin.v:()Ljava/lang/Object;
      69: astore        8
      71: aload         6
      73: invokevirtual #206                // Method scalaz/$eq$eq$greater$greater$Bin.l:()Lscalaz/$eq$eq$greater$greater;
      76: astore        9
      78: aload         6
      80: invokevirtual #209                // Method scalaz/$eq$eq$greater$greater$Bin.r:()Lscalaz/$eq$eq$greater$greater;
      83: astore        10
      85: aload         4
      87: instanceof    #12                 // class scalaz/$eq$eq$greater$greater$Bin
      90: ifeq          210
      93: aload         4
      95: checkcast     #12                 // class scalaz/$eq$eq$greater$greater$Bin
      98: astore        11
     100: aload         11
     102: invokevirtual #201                // Method scalaz/$eq$eq$greater$greater$Bin.k:()Ljava/lang/Object;
     105: astore        12
     107: aload         11
     109: invokevirtual #204                // Method scalaz/$eq$eq$greater$greater$Bin.v:()Ljava/lang/Object;
     112: astore        13
     114: aload         11
     116: invokevirtual #206                // Method scalaz/$eq$eq$greater$greater$Bin.l:()Lscalaz/$eq$eq$greater$greater;
     119: astore        14
     121: aload         11
     123: invokevirtual #209                // Method scalaz/$eq$eq$greater$greater$Bin.r:()Lscalaz/$eq$eq$greater$greater;
     126: astore        15
     128: iconst_3
     129: aload_3
     130: invokevirtual #476                // Method scalaz/$eq$eq$greater$greater.size:()I
     133: imul
     134: aload         4
     136: invokevirtual #476                // Method scalaz/$eq$eq$greater$greater.size:()I
     139: if_icmpge     162
     142: aload_0
     143: aload         12
     145: aload         13
     147: aload_0
     148: aload_1
     149: aload_2
     150: aload_3
     151: aload         14
     153: invokevirtual #404                // Method link:(Ljava/lang/Object;Ljava/lang/Object;Lscalaz/$eq$eq$greater$greater;Lscalaz/$eq$eq$greater$greater;)Lscalaz/$eq$eq$greater$greater;
     156: aload         15
     158: invokevirtual #232                // Method balanceL:(Ljava/lang/Object;Ljava/lang/Object;Lscalaz/$eq$eq$greater$greater;Lscalaz/$eq$eq$greater$greater;)Lscalaz/$eq$eq$greater$greater;
     161: areturn
     162: iconst_3
     163: aload         4
     165: invokevirtual #476                // Method scalaz/$eq$eq$greater$greater.size:()I
     168: imul
     169: aload_3
     170: invokevirtual #476                // Method scalaz/$eq$eq$greater$greater.size:()I
     173: if_icmpge     197
     176: aload_0
     177: aload         7
     179: aload         8
     181: aload         9
     183: aload_0
     184: aload_1
     185: aload_2
     186: aload         10
     188: aload         4
     190: invokevirtual #404                // Method link:(Ljava/lang/Object;Ljava/lang/Object;Lscalaz/$eq$eq$greater$greater;Lscalaz/$eq$eq$greater$greater;)Lscalaz/$eq$eq$greater$greater;
     193: invokevirtual #238                // Method balanceR:(Ljava/lang/Object;Ljava/lang/Object;Lscalaz/$eq$eq$greater$greater;Lscalaz/$eq$eq$greater$greater;)Lscalaz/$eq$eq$greater$greater;
     196: areturn
     197: new           #12                 // class scalaz/$eq$eq$greater$greater$Bin
     200: dup
     201: aload_1
     202: aload_2
     203: aload_3
     204: aload         4
     206: invokespecial #108                // Method scalaz/$eq$eq$greater$greater$Bin."<init>":(Ljava/lang/Object;Ljava/lang/Object;Lscalaz/$eq$eq$greater$greater;Lscalaz/$eq$eq$greater$greater;)V
     209: areturn
     210: new           #146                // class scala/MatchError
     213: dup
     214: aload         5
     216: invokespecial #149                // Method scala/MatchError."<init>":(Ljava/lang/Object;)V
     219: athrow

  private <A, B> scalaz.$eq$eq$greater$greater<A, B> insertMax(A, B, scalaz.$eq$eq$greater$greater<A, B>);
    Code:
       0: aload_3
       1: instanceof    #17                 // class scalaz/$eq$eq$greater$greater$Tip
       4: ifeq          14
       7: aload_0
       8: aload_1
       9: aload_2
      10: invokevirtual #199                // Method singleton:(Ljava/lang/Object;Ljava/lang/Object;)Lscalaz/$eq$eq$greater$greater;
      13: areturn
      14: aload_3
      15: instanceof    #12                 // class scalaz/$eq$eq$greater$greater$Bin
      18: ifeq          74
      21: aload_3
      22: checkcast     #12                 // class scalaz/$eq$eq$greater$greater$Bin
      25: astore        4
      27: aload         4
      29: invokevirtual #201                // Method scalaz/$eq$eq$greater$greater$Bin.k:()Ljava/lang/Object;
      32: astore        5
      34: aload         4
      36: invokevirtual #204                // Method scalaz/$eq$eq$greater$greater$Bin.v:()Ljava/lang/Object;
      39: astore        6
      41: aload         4
      43: invokevirtual #206                // Method scalaz/$eq$eq$greater$greater$Bin.l:()Lscalaz/$eq$eq$greater$greater;
      46: astore        7
      48: aload         4
      50: invokevirtual #209                // Method scalaz/$eq$eq$greater$greater$Bin.r:()Lscalaz/$eq$eq$greater$greater;
      53: astore        8
      55: aload_0
      56: aload         5
      58: aload         6
      60: aload         7
      62: aload_0
      63: aload_1
      64: aload_2
      65: aload         8
      67: invokespecial #506                // Method insertMax:(Ljava/lang/Object;Ljava/lang/Object;Lscalaz/$eq$eq$greater$greater;)Lscalaz/$eq$eq$greater$greater;
      70: invokevirtual #238                // Method balanceR:(Ljava/lang/Object;Ljava/lang/Object;Lscalaz/$eq$eq$greater$greater;Lscalaz/$eq$eq$greater$greater;)Lscalaz/$eq$eq$greater$greater;
      73: areturn
      74: new           #146                // class scala/MatchError
      77: dup
      78: aload_3
      79: invokespecial #149                // Method scala/MatchError."<init>":(Ljava/lang/Object;)V
      82: athrow

  private <A, B> scalaz.$eq$eq$greater$greater<A, B> insertMin(A, B, scalaz.$eq$eq$greater$greater<A, B>);
    Code:
       0: aload_3
       1: instanceof    #17                 // class scalaz/$eq$eq$greater$greater$Tip
       4: ifeq          14
       7: aload_0
       8: aload_1
       9: aload_2
      10: invokevirtual #199                // Method singleton:(Ljava/lang/Object;Ljava/lang/Object;)Lscalaz/$eq$eq$greater$greater;
      13: areturn
      14: aload_3
      15: instanceof    #12                 // class scalaz/$eq$eq$greater$greater$Bin
      18: ifeq          74
      21: aload_3
      22: checkcast     #12                 // class scalaz/$eq$eq$greater$greater$Bin
      25: astore        4
      27: aload         4
      29: invokevirtual #201                // Method scalaz/$eq$eq$greater$greater$Bin.k:()Ljava/lang/Object;
      32: astore        5
      34: aload         4
      36: invokevirtual #204                // Method scalaz/$eq$eq$greater$greater$Bin.v:()Ljava/lang/Object;
      39: astore        6
      41: aload         4
      43: invokevirtual #206                // Method scalaz/$eq$eq$greater$greater$Bin.l:()Lscalaz/$eq$eq$greater$greater;
      46: astore        7
      48: aload         4
      50: invokevirtual #209                // Method scalaz/$eq$eq$greater$greater$Bin.r:()Lscalaz/$eq$eq$greater$greater;
      53: astore        8
      55: aload_0
      56: aload         5
      58: aload         6
      60: aload_0
      61: aload_1
      62: aload_2
      63: aload         7
      65: invokespecial #503                // Method insertMin:(Ljava/lang/Object;Ljava/lang/Object;Lscalaz/$eq$eq$greater$greater;)Lscalaz/$eq$eq$greater$greater;
      68: aload         8
      70: invokevirtual #232                // Method balanceL:(Ljava/lang/Object;Ljava/lang/Object;Lscalaz/$eq$eq$greater$greater;Lscalaz/$eq$eq$greater$greater;)Lscalaz/$eq$eq$greater$greater;
      73: areturn
      74: new           #146                // class scala/MatchError
      77: dup
      78: aload_3
      79: invokespecial #149                // Method scala/MatchError."<init>":(Ljava/lang/Object;)V
      82: athrow

  public <A, B> scalaz.$eq$eq$greater$greater<A, B> trim(scalaz.Maybe<A>, scalaz.Maybe<A>, scalaz.$eq$eq$greater$greater<A, B>, scalaz.Order<A>);
    Code:
       0: new           #141                // class scala/Tuple2
       3: dup
       4: aload_1
       5: aload_2
       6: invokespecial #394                // Method scala/Tuple2."<init>":(Ljava/lang/Object;Ljava/lang/Object;)V
       9: astore        5
      11: aload_1
      12: instanceof    #29                 // class scalaz/Maybe$Empty
      15: ifeq          27
      18: aload_2
      19: instanceof    #29                 // class scalaz/Maybe$Empty
      22: ifeq          27
      25: aload_3
      26: areturn
      27: aload_1
      28: instanceof    #37                 // class scalaz/Maybe$Just
      31: ifeq          60
      34: aload_1
      35: checkcast     #37                 // class scalaz/Maybe$Just
      38: invokevirtual #434                // Method scalaz/Maybe$Just.get:()Ljava/lang/Object;
      41: astore        6
      43: aload_2
      44: instanceof    #29                 // class scalaz/Maybe$Empty
      47: ifeq          60
      50: aload_0
      51: aload         6
      53: aload_3
      54: aload         4
      56: invokespecial #524                // Method greater$1:(Ljava/lang/Object;Lscalaz/$eq$eq$greater$greater;Lscalaz/Order;)Lscalaz/$eq$eq$greater$greater;
      59: areturn
      60: aload_1
      61: instanceof    #29                 // class scalaz/Maybe$Empty
      64: ifeq          93
      67: aload_2
      68: instanceof    #37                 // class scalaz/Maybe$Just
      71: ifeq          93
      74: aload_2
      75: checkcast     #37                 // class scalaz/Maybe$Just
      78: invokevirtual #434                // Method scalaz/Maybe$Just.get:()Ljava/lang/Object;
      81: astore        7
      83: aload_0
      84: aload         7
      86: aload_3
      87: aload         4
      89: invokespecial #527                // Method lesser$1:(Ljava/lang/Object;Lscalaz/$eq$eq$greater$greater;Lscalaz/Order;)Lscalaz/$eq$eq$greater$greater;
      92: areturn
      93: aload_1
      94: instanceof    #37                 // class scalaz/Maybe$Just
      97: ifeq          137
     100: aload_1
     101: checkcast     #37                 // class scalaz/Maybe$Just
     104: invokevirtual #434                // Method scalaz/Maybe$Just.get:()Ljava/lang/Object;
     107: astore        8
     109: aload_2
     110: instanceof    #37                 // class scalaz/Maybe$Just
     113: ifeq          137
     116: aload_2
     117: checkcast     #37                 // class scalaz/Maybe$Just
     120: invokevirtual #434                // Method scalaz/Maybe$Just.get:()Ljava/lang/Object;
     123: astore        9
     125: aload_0
     126: aload         8
     128: aload         9
     130: aload_3
     131: aload         4
     133: invokespecial #531                // Method middle$1:(Ljava/lang/Object;Ljava/lang/Object;Lscalaz/$eq$eq$greater$greater;Lscalaz/Order;)Lscalaz/$eq$eq$greater$greater;
     136: areturn
     137: new           #146                // class scala/MatchError
     140: dup
     141: aload         5
     143: invokespecial #149                // Method scala/MatchError."<init>":(Ljava/lang/Object;)V
     146: athrow

  public <A, B> scala.Tuple2<scalaz.Maybe<B>, scalaz.$eq$eq$greater$greater<A, B>> trimLookupLo(A, scalaz.Maybe<A>, scalaz.$eq$eq$greater$greater<A, B>, scalaz.Order<A>);
    Code:
       0: aload_2
       1: instanceof    #29                 // class scalaz/Maybe$Empty
       4: ifeq          16
       7: aload_0
       8: aload_1
       9: aload_3
      10: aload         4
      12: invokespecial #538                // Method greater$2:(Ljava/lang/Object;Lscalaz/$eq$eq$greater$greater;Lscalaz/Order;)Lscala/Tuple2;
      15: areturn
      16: aload_2
      17: instanceof    #37                 // class scalaz/Maybe$Just
      20: ifeq          43
      23: aload_2
      24: checkcast     #37                 // class scalaz/Maybe$Just
      27: invokevirtual #434                // Method scalaz/Maybe$Just.get:()Ljava/lang/Object;
      30: astore        5
      32: aload_0
      33: aload_1
      34: aload         5
      36: aload_3
      37: aload         4
      39: invokespecial #542                // Method middle$2:(Ljava/lang/Object;Ljava/lang/Object;Lscalaz/$eq$eq$greater$greater;Lscalaz/Order;)Lscala/Tuple2;
      42: areturn
      43: new           #146                // class scala/MatchError
      46: dup
      47: aload_2
      48: invokespecial #149                // Method scala/MatchError."<init>":(Ljava/lang/Object;)V
      51: athrow

  public <A, B, C, D> scalaz.$eq$eq$greater$greater<A, D> mergeWithKey(scalaz.$eq$eq$greater$greater<A, B>, scalaz.$eq$eq$greater$greater<A, C>, scala.Function3<A, B, C, scalaz.Maybe<D>>, scala.Function1<scalaz.$eq$eq$greater$greater<A, B>, scalaz.$eq$eq$greater$greater<A, D>>, scala.Function1<scalaz.$eq$eq$greater$greater<A, C>, scalaz.$eq$eq$greater$greater<A, D>>, scalaz.Order<A>, scalaz.Order<A>);
    Code:
       0: aload_1
       1: instanceof    #17                 // class scalaz/$eq$eq$greater$greater$Tip
       4: ifeq          19
       7: aload         5
       9: aload_2
      10: invokeinterface #334,  2          // InterfaceMethod scala/Function1.apply:(Ljava/lang/Object;)Ljava/lang/Object;
      15: checkcast     #14                 // class scalaz/$eq$eq$greater$greater
      18: areturn
      19: aload_2
      20: instanceof    #17                 // class scalaz/$eq$eq$greater$greater$Tip
      23: ifeq          38
      26: aload         4
      28: aload_1
      29: invokeinterface #334,  2          // InterfaceMethod scala/Function1.apply:(Ljava/lang/Object;)Ljava/lang/Object;
      34: checkcast     #14                 // class scalaz/$eq$eq$greater$greater
      37: areturn
      38: getstatic     #385                // Field scalaz/Maybe$.MODULE$:Lscalaz/Maybe$;
      41: pop
      42: getstatic     #388                // Field scalaz/Maybe$Empty$.MODULE$:Lscalaz/Maybe$Empty$;
      45: invokevirtual #391                // Method scalaz/Maybe$Empty$.apply:()Lscalaz/Maybe;
      48: getstatic     #385                // Field scalaz/Maybe$.MODULE$:Lscalaz/Maybe$;
      51: pop
      52: getstatic     #388                // Field scalaz/Maybe$Empty$.MODULE$:Lscalaz/Maybe$Empty$;
      55: invokevirtual #391                // Method scalaz/Maybe$Empty$.apply:()Lscalaz/Maybe;
      58: astore        9
      60: astore        8
      62: new           #141                // class scala/Tuple2
      65: dup
      66: aload_1
      67: aload_2
      68: invokespecial #394                // Method scala/Tuple2."<init>":(Ljava/lang/Object;Ljava/lang/Object;)V
      71: astore        10
      73: aload_2
      74: instanceof    #17                 // class scalaz/$eq$eq$greater$greater$Tip
      77: ifeq          92
      80: aload         4
      82: aload_1
      83: invokeinterface #334,  2          // InterfaceMethod scala/Function1.apply:(Ljava/lang/Object;)Ljava/lang/Object;
      88: checkcast     #14                 // class scalaz/$eq$eq$greater$greater
      91: areturn
      92: aload_1
      93: instanceof    #17                 // class scalaz/$eq$eq$greater$greater$Tip
      96: ifeq          181
      99: aload_2
     100: instanceof    #12                 // class scalaz/$eq$eq$greater$greater$Bin
     103: ifeq          181
     106: aload_2
     107: checkcast     #12                 // class scalaz/$eq$eq$greater$greater$Bin
     110: astore        11
     112: aload         11
     114: invokevirtual #201                // Method scalaz/$eq$eq$greater$greater$Bin.k:()Ljava/lang/Object;
     117: astore        12
     119: aload         11
     121: invokevirtual #204                // Method scalaz/$eq$eq$greater$greater$Bin.v:()Ljava/lang/Object;
     124: astore        13
     126: aload         11
     128: invokevirtual #206                // Method scalaz/$eq$eq$greater$greater$Bin.l:()Lscalaz/$eq$eq$greater$greater;
     131: astore        14
     133: aload         11
     135: invokevirtual #209                // Method scalaz/$eq$eq$greater$greater$Bin.r:()Lscalaz/$eq$eq$greater$greater;
     138: astore        15
     140: aload_0
     141: aload         12
     143: aload         13
     145: aload         14
     147: aload         8
     149: aload         7
     151: invokevirtual #398                // Method scalaz/$eq$eq$greater$greater.scalaz$$eq$eq$greater$greater$$filterGt:(Lscalaz/Maybe;Lscalaz/Order;)Lscalaz/$eq$eq$greater$greater;
     154: aload         15
     156: aload         9
     158: aload         7
     160: invokevirtual #401                // Method scalaz/$eq$eq$greater$greater.scalaz$$eq$eq$greater$greater$$filterLt:(Lscalaz/Maybe;Lscalaz/Order;)Lscalaz/$eq$eq$greater$greater;
     163: invokevirtual #404                // Method link:(Ljava/lang/Object;Ljava/lang/Object;Lscalaz/$eq$eq$greater$greater;Lscalaz/$eq$eq$greater$greater;)Lscalaz/$eq$eq$greater$greater;
     166: astore        16
     168: aload         5
     170: aload         16
     172: invokeinterface #334,  2          // InterfaceMethod scala/Function1.apply:(Ljava/lang/Object;)Ljava/lang/Object;
     177: checkcast     #14                 // class scalaz/$eq$eq$greater$greater
     180: areturn
     181: aload_1
     182: instanceof    #12                 // class scalaz/$eq$eq$greater$greater$Bin
     185: ifeq          559
     188: aload_1
     189: checkcast     #12                 // class scalaz/$eq$eq$greater$greater$Bin
     192: astore        17
     194: aload         17
     196: invokevirtual #201                // Method scalaz/$eq$eq$greater$greater$Bin.k:()Ljava/lang/Object;
     199: astore        18
     201: aload         17
     203: invokevirtual #204                // Method scalaz/$eq$eq$greater$greater$Bin.v:()Ljava/lang/Object;
     206: astore        19
     208: aload         17
     210: invokevirtual #206                // Method scalaz/$eq$eq$greater$greater$Bin.l:()Lscalaz/$eq$eq$greater$greater;
     213: astore        20
     215: aload         17
     217: invokevirtual #209                // Method scalaz/$eq$eq$greater$greater$Bin.r:()Lscalaz/$eq$eq$greater$greater;
     220: astore        21
     222: getstatic     #385                // Field scalaz/Maybe$.MODULE$:Lscalaz/Maybe$;
     225: pop
     226: new           #37                 // class scalaz/Maybe$Just
     229: dup
     230: aload         18
     232: invokespecial #405                // Method scalaz/Maybe$Just."<init>":(Ljava/lang/Object;)V
     235: astore        22
     237: aload_0
     238: aload         8
     240: aload         22
     242: aload         20
     244: aload_0
     245: aload         8
     247: aload         22
     249: aload_2
     250: aload         7
     252: invokevirtual #409                // Method trim:(Lscalaz/Maybe;Lscalaz/Maybe;Lscalaz/$eq$eq$greater$greater;Lscalaz/Order;)Lscalaz/$eq$eq$greater$greater;
     255: aload         4
     257: aload         7
     259: aload         5
     261: aload_3
     262: invokespecial #413                // Method hedgeMerge$1:(Lscalaz/Maybe;Lscalaz/Maybe;Lscalaz/$eq$eq$greater$greater;Lscalaz/$eq$eq$greater$greater;Lscala/Function1;Lscalaz/Order;Lscala/Function1;Lscala/Function3;)Lscalaz/$eq$eq$greater$greater;
     265: astore        23
     267: aload_0
     268: aload         18
     270: aload         9
     272: aload_2
     273: aload         7
     275: invokevirtual #417                // Method trimLookupLo:(Ljava/lang/Object;Lscalaz/Maybe;Lscalaz/$eq$eq$greater$greater;Lscalaz/Order;)Lscala/Tuple2;
     278: astore        24
     280: aload         24
     282: ifnull        308
     285: aload         24
     287: invokevirtual #194                // Method scala/Tuple2._1:()Ljava/lang/Object;
     290: checkcast     #31                 // class scalaz/Maybe
     293: astore        25
     295: aload         24
     297: invokevirtual #197                // Method scala/Tuple2._2:()Ljava/lang/Object;
     300: checkcast     #14                 // class scalaz/$eq$eq$greater$greater
     303: astore        26
     305: goto          317
     308: new           #146                // class scala/MatchError
     311: dup
     312: aconst_null
     313: invokespecial #149                // Method scala/MatchError."<init>":(Ljava/lang/Object;)V
     316: athrow
     317: aload_0
     318: aload         22
     320: aload         9
     322: aload         21
     324: aload         26
     326: aload         4
     328: aload         7
     330: aload         5
     332: aload_3
     333: invokespecial #413                // Method hedgeMerge$1:(Lscalaz/Maybe;Lscalaz/Maybe;Lscalaz/$eq$eq$greater$greater;Lscalaz/$eq$eq$greater$greater;Lscala/Function1;Lscalaz/Order;Lscala/Function1;Lscala/Function3;)Lscalaz/$eq$eq$greater$greater;
     336: astore        27
     338: aload         25
     340: instanceof    #29                 // class scalaz/Maybe$Empty
     343: ifeq          457
     346: aload         4
     348: aload_0
     349: aload         18
     351: aload         19
     353: invokevirtual #199                // Method singleton:(Ljava/lang/Object;Ljava/lang/Object;)Lscalaz/$eq$eq$greater$greater;
     356: invokeinterface #334,  2          // InterfaceMethod scala/Function1.apply:(Ljava/lang/Object;)Ljava/lang/Object;
     361: checkcast     #14                 // class scalaz/$eq$eq$greater$greater
     364: astore        28
     366: aload         28
     368: instanceof    #17                 // class scalaz/$eq$eq$greater$greater$Tip
     371: ifeq          382
     374: aload         23
     376: aload         27
     378: invokevirtual #420                // Method scalaz/$eq$eq$greater$greater.merge:(Lscalaz/$eq$eq$greater$greater;)Lscalaz/$eq$eq$greater$greater;
     381: areturn
     382: aload         28
     384: instanceof    #12                 // class scalaz/$eq$eq$greater$greater$Bin
     387: ifeq          447
     390: aload         28
     392: checkcast     #12                 // class scalaz/$eq$eq$greater$greater$Bin
     395: astore        29
     397: aload         29
     399: invokevirtual #204                // Method scalaz/$eq$eq$greater$greater$Bin.v:()Ljava/lang/Object;
     402: astore        30
     404: aload         29
     406: invokevirtual #206                // Method scalaz/$eq$eq$greater$greater$Bin.l:()Lscalaz/$eq$eq$greater$greater;
     409: astore        31
     411: aload         29
     413: invokevirtual #209                // Method scalaz/$eq$eq$greater$greater$Bin.r:()Lscalaz/$eq$eq$greater$greater;
     416: astore        32
     418: aload         31
     420: instanceof    #17                 // class scalaz/$eq$eq$greater$greater$Tip
     423: ifeq          447
     426: aload         32
     428: instanceof    #17                 // class scalaz/$eq$eq$greater$greater$Tip
     431: ifeq          447
     434: aload_0
     435: aload         18
     437: aload         30
     439: aload         23
     441: aload         27
     443: invokevirtual #404                // Method link:(Ljava/lang/Object;Ljava/lang/Object;Lscalaz/$eq$eq$greater$greater;Lscalaz/$eq$eq$greater$greater;)Lscalaz/$eq$eq$greater$greater;
     446: areturn
     447: getstatic     #425                // Field scala/sys/package$.MODULE$:Lscala/sys/package$;
     450: ldc_w         #427                // String mergeWithKey: Given function g1 does not fulfil required conditions (see documentation)
     453: invokevirtual #431                // Method scala/sys/package$.error:(Ljava/lang/String;)Lscala/runtime/Nothing$;
     456: athrow
     457: aload         25
     459: instanceof    #37                 // class scalaz/Maybe$Just
     462: ifeq          549
     465: aload         25
     467: checkcast     #37                 // class scalaz/Maybe$Just
     470: invokevirtual #434                // Method scalaz/Maybe$Just.get:()Ljava/lang/Object;
     473: astore        33
     475: aload_3
     476: aload         18
     478: aload         19
     480: aload         33
     482: invokeinterface #273,  4          // InterfaceMethod scala/Function3.apply:(Ljava/lang/Object;Ljava/lang/Object;Ljava/lang/Object;)Ljava/lang/Object;
     487: checkcast     #31                 // class scalaz/Maybe
     490: astore        34
     492: aload         34
     494: instanceof    #29                 // class scalaz/Maybe$Empty
     497: ifeq          508
     500: aload         23
     502: aload         27
     504: invokevirtual #420                // Method scalaz/$eq$eq$greater$greater.merge:(Lscalaz/$eq$eq$greater$greater;)Lscalaz/$eq$eq$greater$greater;
     507: areturn
     508: aload         34
     510: instanceof    #37                 // class scalaz/Maybe$Just
     513: ifeq          539
     516: aload         34
     518: checkcast     #37                 // class scalaz/Maybe$Just
     521: invokevirtual #434                // Method scalaz/Maybe$Just.get:()Ljava/lang/Object;
     524: astore        35
     526: aload_0
     527: aload         18
     529: aload         35
     531: aload         23
     533: aload         27
     535: invokevirtual #404                // Method link:(Ljava/lang/Object;Ljava/lang/Object;Lscalaz/$eq$eq$greater$greater;Lscalaz/$eq$eq$greater$greater;)Lscalaz/$eq$eq$greater$greater;
     538: areturn
     539: new           #146                // class scala/MatchError
     542: dup
     543: aload         34
     545: invokespecial #149                // Method scala/MatchError."<init>":(Ljava/lang/Object;)V
     548: athrow
     549: new           #146                // class scala/MatchError
     552: dup
     553: aload         25
     555: invokespecial #149                // Method scala/MatchError."<init>":(Ljava/lang/Object;)V
     558: athrow
     559: new           #146                // class scala/MatchError
     562: dup
     563: aload         10
     565: invokespecial #149                // Method scala/MatchError."<init>":(Ljava/lang/Object;)V
     568: athrow

  public static final scalaz.$eq$eq$greater$greater $anonfun$apply$1(scalaz.Order, scalaz.$eq$eq$greater$greater, scala.Tuple2);
    Code:
       0: aload_1
       1: aload_2
       2: invokevirtual #194                // Method scala/Tuple2._1:()Ljava/lang/Object;
       5: aload_2
       6: invokevirtual #197                // Method scala/Tuple2._2:()Ljava/lang/Object;
       9: aload_0
      10: invokevirtual #557                // Method scalaz/$eq$eq$greater$greater.insert:(Ljava/lang/Object;Ljava/lang/Object;Lscalaz/Order;)Lscalaz/$eq$eq$greater$greater;
      13: areturn

  public static final scalaz.$eq$eq$greater$greater $anonfun$fromList$1(scalaz.Order, scalaz.$eq$eq$greater$greater, scala.Tuple2);
    Code:
       0: aload_1
       1: aload_2
       2: invokevirtual #194                // Method scala/Tuple2._1:()Ljava/lang/Object;
       5: aload_2
       6: invokevirtual #197                // Method scala/Tuple2._2:()Ljava/lang/Object;
       9: aload_0
      10: invokevirtual #557                // Method scalaz/$eq$eq$greater$greater.insert:(Ljava/lang/Object;Ljava/lang/Object;Lscalaz/Order;)Lscalaz/$eq$eq$greater$greater;
      13: areturn

  public static final scalaz.$eq$eq$greater$greater $anonfun$fromIList$1(scalaz.Order, scalaz.$eq$eq$greater$greater, scala.Tuple2);
    Code:
       0: aload_1
       1: aload_2
       2: invokevirtual #194                // Method scala/Tuple2._1:()Ljava/lang/Object;
       5: aload_2
       6: invokevirtual #197                // Method scala/Tuple2._2:()Ljava/lang/Object;
       9: aload_0
      10: invokevirtual #557                // Method scalaz/$eq$eq$greater$greater.insert:(Ljava/lang/Object;Ljava/lang/Object;Lscalaz/Order;)Lscalaz/$eq$eq$greater$greater;
      13: areturn

  public static final java.lang.Object $anonfun$fromListWith$1(scala.Function2, java.lang.Object, java.lang.Object, java.lang.Object);
    Code:
       0: aload_0
       1: aload_2
       2: aload_3
       3: invokeinterface #245,  3          // InterfaceMethod scala/Function2.apply:(Ljava/lang/Object;Ljava/lang/Object;)Ljava/lang/Object;
       8: areturn

  public static final java.lang.Object $anonfun$fromIListWith$1(scala.Function2, java.lang.Object, java.lang.Object, java.lang.Object);
    Code:
       0: aload_0
       1: aload_2
       2: aload_3
       3: invokeinterface #245,  3          // InterfaceMethod scala/Function2.apply:(Ljava/lang/Object;Ljava/lang/Object;)Ljava/lang/Object;
       8: areturn

  public static final scalaz.$eq$eq$greater$greater $anonfun$fromListWithKey$1(scala.Function3, scalaz.Order, scalaz.$eq$eq$greater$greater, scala.Tuple2);
    Code:
       0: aload_2
       1: aload_3
       2: invokevirtual #194                // Method scala/Tuple2._1:()Ljava/lang/Object;
       5: aload_3
       6: invokevirtual #197                // Method scala/Tuple2._2:()Ljava/lang/Object;
       9: astore        5
      11: astore        4
      13: ifnonnull     18
      16: aconst_null
      17: athrow
      18: aload_2
      19: instanceof    #17                 // class scalaz/$eq$eq$greater$greater$Tip
      22: ifeq          36
      25: getstatic     #58                 // Field MODULE$:Lscalaz/$eq$eq$greater$greater$;
      28: aload         4
      30: aload         5
      32: invokevirtual #199                // Method singleton:(Ljava/lang/Object;Ljava/lang/Object;)Lscalaz/$eq$eq$greater$greater;
      35: areturn
      36: aload_2
      37: instanceof    #12                 // class scalaz/$eq$eq$greater$greater$Bin
      40: ifeq          206
      43: aload_2
      44: checkcast     #12                 // class scalaz/$eq$eq$greater$greater$Bin
      47: astore        6
      49: aload         6
      51: invokevirtual #201                // Method scalaz/$eq$eq$greater$greater$Bin.k:()Ljava/lang/Object;
      54: astore        7
      56: aload         6
      58: invokevirtual #204                // Method scalaz/$eq$eq$greater$greater$Bin.v:()Ljava/lang/Object;
      61: astore        8
      63: aload         6
      65: invokevirtual #206                // Method scalaz/$eq$eq$greater$greater$Bin.l:()Lscalaz/$eq$eq$greater$greater;
      68: astore        9
      70: aload         6
      72: invokevirtual #209                // Method scalaz/$eq$eq$greater$greater$Bin.r:()Lscalaz/$eq$eq$greater$greater;
      75: astore        10
      77: aload_1
      78: aload         4
      80: aload         7
      82: invokeinterface #215,  3          // InterfaceMethod scalaz/Order.order:(Ljava/lang/Object;Ljava/lang/Object;)Lscalaz/Ordering;
      87: astore        11
      89: getstatic     #218                // Field scalaz/Ordering$LT$.MODULE$:Lscalaz/Ordering$LT$;
      92: aload         11
      94: invokevirtual #224                // Method java/lang/Object.equals:(Ljava/lang/Object;)Z
      97: ifeq          124
     100: getstatic     #58                 // Field MODULE$:Lscalaz/$eq$eq$greater$greater$;
     103: aload         7
     105: aload         8
     107: aload         9
     109: aload_0
     110: aload         4
     112: aload         5
     114: aload_1
     115: invokevirtual #228                // Method scalaz/$eq$eq$greater$greater.insertWithKey:(Lscala/Function3;Ljava/lang/Object;Ljava/lang/Object;Lscalaz/Order;)Lscalaz/$eq$eq$greater$greater;
     118: aload         10
     120: invokevirtual #232                // Method balanceL:(Ljava/lang/Object;Ljava/lang/Object;Lscalaz/$eq$eq$greater$greater;Lscalaz/$eq$eq$greater$greater;)Lscalaz/$eq$eq$greater$greater;
     123: areturn
     124: getstatic     #235                // Field scalaz/Ordering$GT$.MODULE$:Lscalaz/Ordering$GT$;
     127: aload         11
     129: invokevirtual #224                // Method java/lang/Object.equals:(Ljava/lang/Object;)Z
     132: ifeq          159
     135: getstatic     #58                 // Field MODULE$:Lscalaz/$eq$eq$greater$greater$;
     138: aload         7
     140: aload         8
     142: aload         9
     144: aload         10
     146: aload_0
     147: aload         4
     149: aload         5
     151: aload_1
     152: invokevirtual #228                // Method scalaz/$eq$eq$greater$greater.insertWithKey:(Lscala/Function3;Ljava/lang/Object;Ljava/lang/Object;Lscalaz/Order;)Lscalaz/$eq$eq$greater$greater;
     155: invokevirtual #238                // Method balanceR:(Ljava/lang/Object;Ljava/lang/Object;Lscalaz/$eq$eq$greater$greater;Lscalaz/$eq$eq$greater$greater;)Lscalaz/$eq$eq$greater$greater;
     158: areturn
     159: getstatic     #241                // Field scalaz/Ordering$EQ$.MODULE$:Lscalaz/Ordering$EQ$;
     162: aload         11
     164: invokevirtual #224                // Method java/lang/Object.equals:(Ljava/lang/Object;)Z
     167: ifeq          196
     170: new           #12                 // class scalaz/$eq$eq$greater$greater$Bin
     173: dup
     174: aload         4
     176: aload_0
     177: aload         4
     179: aload         5
     181: aload         8
     183: invokeinterface #273,  4          // InterfaceMethod scala/Function3.apply:(Ljava/lang/Object;Ljava/lang/Object;Ljava/lang/Object;)Ljava/lang/Object;
     188: aload         9
     190: aload         10
     192: invokespecial #108                // Method scalaz/$eq$eq$greater$greater$Bin."<init>":(Ljava/lang/Object;Ljava/lang/Object;Lscalaz/$eq$eq$greater$greater;Lscalaz/$eq$eq$greater$greater;)V
     195: areturn
     196: new           #146                // class scala/MatchError
     199: dup
     200: aload         11
     202: invokespecial #149                // Method scala/MatchError."<init>":(Ljava/lang/Object;)V
     205: athrow
     206: new           #146                // class scala/MatchError
     209: dup
     210: aload_2
     211: invokespecial #149                // Method scala/MatchError."<init>":(Ljava/lang/Object;)V
     214: athrow

  public static final scalaz.$eq$eq$greater$greater $anonfun$fromIListWithKey$1(scala.Function3, scalaz.Order, scalaz.$eq$eq$greater$greater, scala.Tuple2);
    Code:
       0: aload_2
       1: aload_3
       2: invokevirtual #194                // Method scala/Tuple2._1:()Ljava/lang/Object;
       5: aload_3
       6: invokevirtual #197                // Method scala/Tuple2._2:()Ljava/lang/Object;
       9: astore        5
      11: astore        4
      13: ifnonnull     18
      16: aconst_null
      17: athrow
      18: aload_2
      19: instanceof    #17                 // class scalaz/$eq$eq$greater$greater$Tip
      22: ifeq          36
      25: getstatic     #58                 // Field MODULE$:Lscalaz/$eq$eq$greater$greater$;
      28: aload         4
      30: aload         5
      32: invokevirtual #199                // Method singleton:(Ljava/lang/Object;Ljava/lang/Object;)Lscalaz/$eq$eq$greater$greater;
      35: areturn
      36: aload_2
      37: instanceof    #12                 // class scalaz/$eq$eq$greater$greater$Bin
      40: ifeq          206
      43: aload_2
      44: checkcast     #12                 // class scalaz/$eq$eq$greater$greater$Bin
      47: astore        6
      49: aload         6
      51: invokevirtual #201                // Method scalaz/$eq$eq$greater$greater$Bin.k:()Ljava/lang/Object;
      54: astore        7
      56: aload         6
      58: invokevirtual #204                // Method scalaz/$eq$eq$greater$greater$Bin.v:()Ljava/lang/Object;
      61: astore        8
      63: aload         6
      65: invokevirtual #206                // Method scalaz/$eq$eq$greater$greater$Bin.l:()Lscalaz/$eq$eq$greater$greater;
      68: astore        9
      70: aload         6
      72: invokevirtual #209                // Method scalaz/$eq$eq$greater$greater$Bin.r:()Lscalaz/$eq$eq$greater$greater;
      75: astore        10
      77: aload_1
      78: aload         4
      80: aload         7
      82: invokeinterface #215,  3          // InterfaceMethod scalaz/Order.order:(Ljava/lang/Object;Ljava/lang/Object;)Lscalaz/Ordering;
      87: astore        11
      89: getstatic     #218                // Field scalaz/Ordering$LT$.MODULE$:Lscalaz/Ordering$LT$;
      92: aload         11
      94: invokevirtual #224                // Method java/lang/Object.equals:(Ljava/lang/Object;)Z
      97: ifeq          124
     100: getstatic     #58                 // Field MODULE$:Lscalaz/$eq$eq$greater$greater$;
     103: aload         7
     105: aload         8
     107: aload         9
     109: aload_0
     110: aload         4
     112: aload         5
     114: aload_1
     115: invokevirtual #228                // Method scalaz/$eq$eq$greater$greater.insertWithKey:(Lscala/Function3;Ljava/lang/Object;Ljava/lang/Object;Lscalaz/Order;)Lscalaz/$eq$eq$greater$greater;
     118: aload         10
     120: invokevirtual #232                // Method balanceL:(Ljava/lang/Object;Ljava/lang/Object;Lscalaz/$eq$eq$greater$greater;Lscalaz/$eq$eq$greater$greater;)Lscalaz/$eq$eq$greater$greater;
     123: areturn
     124: getstatic     #235                // Field scalaz/Ordering$GT$.MODULE$:Lscalaz/Ordering$GT$;
     127: aload         11
     129: invokevirtual #224                // Method java/lang/Object.equals:(Ljava/lang/Object;)Z
     132: ifeq          159
     135: getstatic     #58                 // Field MODULE$:Lscalaz/$eq$eq$greater$greater$;
     138: aload         7
     140: aload         8
     142: aload         9
     144: aload         10
     146: aload_0
     147: aload         4
     149: aload         5
     151: aload_1
     152: invokevirtual #228                // Method scalaz/$eq$eq$greater$greater.insertWithKey:(Lscala/Function3;Ljava/lang/Object;Ljava/lang/Object;Lscalaz/Order;)Lscalaz/$eq$eq$greater$greater;
     155: invokevirtual #238                // Method balanceR:(Ljava/lang/Object;Ljava/lang/Object;Lscalaz/$eq$eq$greater$greater;Lscalaz/$eq$eq$greater$greater;)Lscalaz/$eq$eq$greater$greater;
     158: areturn
     159: getstatic     #241                // Field scalaz/Ordering$EQ$.MODULE$:Lscalaz/Ordering$EQ$;
     162: aload         11
     164: invokevirtual #224                // Method java/lang/Object.equals:(Ljava/lang/Object;)Z
     167: ifeq          196
     170: new           #12                 // class scalaz/$eq$eq$greater$greater$Bin
     173: dup
     174: aload         4
     176: aload_0
     177: aload         4
     179: aload         5
     181: aload         8
     183: invokeinterface #273,  4          // InterfaceMethod scala/Function3.apply:(Ljava/lang/Object;Ljava/lang/Object;Ljava/lang/Object;)Ljava/lang/Object;
     188: aload         9
     190: aload         10
     192: invokespecial #108                // Method scalaz/$eq$eq$greater$greater$Bin."<init>":(Ljava/lang/Object;Ljava/lang/Object;Lscalaz/$eq$eq$greater$greater;Lscalaz/$eq$eq$greater$greater;)V
     195: areturn
     196: new           #146                // class scala/MatchError
     199: dup
     200: aload         11
     202: invokespecial #149                // Method scala/MatchError."<init>":(Ljava/lang/Object;)V
     205: athrow
     206: new           #146                // class scala/MatchError
     209: dup
     210: aload_2
     211: invokespecial #149                // Method scala/MatchError."<init>":(Ljava/lang/Object;)V
     214: athrow

  public static final scalaz.$eq$eq$greater$greater $anonfun$fromFoldable$1(scalaz.Order, scalaz.$eq$eq$greater$greater, scala.Tuple2);
    Code:
       0: aload_1
       1: aload_2
       2: invokevirtual #194                // Method scala/Tuple2._1:()Ljava/lang/Object;
       5: aload_2
       6: invokevirtual #197                // Method scala/Tuple2._2:()Ljava/lang/Object;
       9: aload_0
      10: invokevirtual #557                // Method scalaz/$eq$eq$greater$greater.insert:(Ljava/lang/Object;Ljava/lang/Object;Lscalaz/Order;)Lscalaz/$eq$eq$greater$greater;
      13: areturn

  public static final java.lang.Object $anonfun$fromFoldableWith$1(scala.Function2, java.lang.Object, java.lang.Object, java.lang.Object);
    Code:
       0: aload_0
       1: aload_2
       2: aload_3
       3: invokeinterface #245,  3          // InterfaceMethod scala/Function2.apply:(Ljava/lang/Object;Ljava/lang/Object;)Ljava/lang/Object;
       8: areturn

  public static final scalaz.$eq$eq$greater$greater $anonfun$fromFoldableWithKey$1(scala.Function3, scalaz.Order, scalaz.$eq$eq$greater$greater, scala.Tuple2);
    Code:
       0: aload_2
       1: aload_3
       2: invokevirtual #194                // Method scala/Tuple2._1:()Ljava/lang/Object;
       5: aload_3
       6: invokevirtual #197                // Method scala/Tuple2._2:()Ljava/lang/Object;
       9: astore        5
      11: astore        4
      13: ifnonnull     18
      16: aconst_null
      17: athrow
      18: aload_2
      19: instanceof    #17                 // class scalaz/$eq$eq$greater$greater$Tip
      22: ifeq          36
      25: getstatic     #58                 // Field MODULE$:Lscalaz/$eq$eq$greater$greater$;
      28: aload         4
      30: aload         5
      32: invokevirtual #199                // Method singleton:(Ljava/lang/Object;Ljava/lang/Object;)Lscalaz/$eq$eq$greater$greater;
      35: areturn
      36: aload_2
      37: instanceof    #12                 // class scalaz/$eq$eq$greater$greater$Bin
      40: ifeq          206
      43: aload_2
      44: checkcast     #12                 // class scalaz/$eq$eq$greater$greater$Bin
      47: astore        6
      49: aload         6
      51: invokevirtual #201                // Method scalaz/$eq$eq$greater$greater$Bin.k:()Ljava/lang/Object;
      54: astore        7
      56: aload         6
      58: invokevirtual #204                // Method scalaz/$eq$eq$greater$greater$Bin.v:()Ljava/lang/Object;
      61: astore        8
      63: aload         6
      65: invokevirtual #206                // Method scalaz/$eq$eq$greater$greater$Bin.l:()Lscalaz/$eq$eq$greater$greater;
      68: astore        9
      70: aload         6
      72: invokevirtual #209                // Method scalaz/$eq$eq$greater$greater$Bin.r:()Lscalaz/$eq$eq$greater$greater;
      75: astore        10
      77: aload_1
      78: aload         4
      80: aload         7
      82: invokeinterface #215,  3          // InterfaceMethod scalaz/Order.order:(Ljava/lang/Object;Ljava/lang/Object;)Lscalaz/Ordering;
      87: astore        11
      89: getstatic     #218                // Field scalaz/Ordering$LT$.MODULE$:Lscalaz/Ordering$LT$;
      92: aload         11
      94: invokevirtual #224                // Method java/lang/Object.equals:(Ljava/lang/Object;)Z
      97: ifeq          124
     100: getstatic     #58                 // Field MODULE$:Lscalaz/$eq$eq$greater$greater$;
     103: aload         7
     105: aload         8
     107: aload         9
     109: aload_0
     110: aload         4
     112: aload         5
     114: aload_1
     115: invokevirtual #228                // Method scalaz/$eq$eq$greater$greater.insertWithKey:(Lscala/Function3;Ljava/lang/Object;Ljava/lang/Object;Lscalaz/Order;)Lscalaz/$eq$eq$greater$greater;
     118: aload         10
     120: invokevirtual #232                // Method balanceL:(Ljava/lang/Object;Ljava/lang/Object;Lscalaz/$eq$eq$greater$greater;Lscalaz/$eq$eq$greater$greater;)Lscalaz/$eq$eq$greater$greater;
     123: areturn
     124: getstatic     #235                // Field scalaz/Ordering$GT$.MODULE$:Lscalaz/Ordering$GT$;
     127: aload         11
     129: invokevirtual #224                // Method java/lang/Object.equals:(Ljava/lang/Object;)Z
     132: ifeq          159
     135: getstatic     #58                 // Field MODULE$:Lscalaz/$eq$eq$greater$greater$;
     138: aload         7
     140: aload         8
     142: aload         9
     144: aload         10
     146: aload_0
     147: aload         4
     149: aload         5
     151: aload_1
     152: invokevirtual #228                // Method scalaz/$eq$eq$greater$greater.insertWithKey:(Lscala/Function3;Ljava/lang/Object;Ljava/lang/Object;Lscalaz/Order;)Lscalaz/$eq$eq$greater$greater;
     155: invokevirtual #238                // Method balanceR:(Ljava/lang/Object;Ljava/lang/Object;Lscalaz/$eq$eq$greater$greater;Lscalaz/$eq$eq$greater$greater;)Lscalaz/$eq$eq$greater$greater;
     158: areturn
     159: getstatic     #241                // Field scalaz/Ordering$EQ$.MODULE$:Lscalaz/Ordering$EQ$;
     162: aload         11
     164: invokevirtual #224                // Method java/lang/Object.equals:(Ljava/lang/Object;)Z
     167: ifeq          196
     170: new           #12                 // class scalaz/$eq$eq$greater$greater$Bin
     173: dup
     174: aload         4
     176: aload_0
     177: aload         4
     179: aload         5
     181: aload         8
     183: invokeinterface #273,  4          // InterfaceMethod scala/Function3.apply:(Ljava/lang/Object;Ljava/lang/Object;Ljava/lang/Object;)Ljava/lang/Object;
     188: aload         9
     190: aload         10
     192: invokespecial #108                // Method scalaz/$eq$eq$greater$greater$Bin."<init>":(Ljava/lang/Object;Ljava/lang/Object;Lscalaz/$eq$eq$greater$greater;Lscalaz/$eq$eq$greater$greater;)V
     195: areturn
     196: new           #146                // class scala/MatchError
     199: dup
     200: aload         11
     202: invokespecial #149                // Method scala/MatchError."<init>":(Ljava/lang/Object;)V
     205: athrow
     206: new           #146                // class scala/MatchError
     209: dup
     210: aload_2
     211: invokespecial #149                // Method scala/MatchError."<init>":(Ljava/lang/Object;)V
     214: athrow

  public static final scalaz.$eq$eq$greater$greater $anonfun$unions$1(scalaz.Order, scalaz.$eq$eq$greater$greater, scalaz.$eq$eq$greater$greater);
    Code:
       0: aload_1
       1: aload_2
       2: aload_0
       3: invokevirtual #346                // Method scalaz/$eq$eq$greater$greater.union:(Lscalaz/$eq$eq$greater$greater;Lscalaz/Order;)Lscalaz/$eq$eq$greater$greater;
       6: areturn

  public static final scalaz.$eq$eq$greater$greater $anonfun$unionsWith$1(scala.Function2, scalaz.Order, scalaz.$eq$eq$greater$greater, scalaz.$eq$eq$greater$greater);
    Code:
       0: aload_2
       1: aload_3
       2: aload_0
       3: aload_1
       4: invokevirtual #587                // Method scalaz/$eq$eq$greater$greater.unionWith:(Lscalaz/$eq$eq$greater$greater;Lscala/Function2;Lscalaz/Order;)Lscalaz/$eq$eq$greater$greater;
       7: areturn

  private final scalaz.$eq$eq$greater$greater greater$1(java.lang.Object, scalaz.$eq$eq$greater$greater, scalaz.Order);
    Code:
       0: aload_2
       1: instanceof    #12                 // class scalaz/$eq$eq$greater$greater$Bin
       4: ifeq          47
       7: aload_2
       8: checkcast     #12                 // class scalaz/$eq$eq$greater$greater$Bin
      11: astore        4
      13: aload         4
      15: invokevirtual #201                // Method scalaz/$eq$eq$greater$greater$Bin.k:()Ljava/lang/Object;
      18: astore        5
      20: aload         4
      22: invokevirtual #209                // Method scalaz/$eq$eq$greater$greater$Bin.r:()Lscalaz/$eq$eq$greater$greater;
      25: astore        6
      27: aload_3
      28: aload         5
      30: aload_1
      31: invokeinterface #593,  3          // InterfaceMethod scalaz/Order.lessThanOrEqual:(Ljava/lang/Object;Ljava/lang/Object;)Z
      36: ifeq          47
      39: aload_1
      40: aload         6
      42: astore_2
      43: astore_1
      44: goto          0
      47: aload_2
      48: areturn

  private final scalaz.$eq$eq$greater$greater lesser$1(java.lang.Object, scalaz.$eq$eq$greater$greater, scalaz.Order);
    Code:
       0: aload_2
       1: instanceof    #12                 // class scalaz/$eq$eq$greater$greater$Bin
       4: ifeq          47
       7: aload_2
       8: checkcast     #12                 // class scalaz/$eq$eq$greater$greater$Bin
      11: astore        4
      13: aload         4
      15: invokevirtual #201                // Method scalaz/$eq$eq$greater$greater$Bin.k:()Ljava/lang/Object;
      18: astore        5
      20: aload         4
      22: invokevirtual #206                // Method scalaz/$eq$eq$greater$greater$Bin.l:()Lscalaz/$eq$eq$greater$greater;
      25: astore        6
      27: aload_3
      28: aload         5
      30: aload_1
      31: invokeinterface #596,  3          // InterfaceMethod scalaz/Order.greaterThanOrEqual:(Ljava/lang/Object;Ljava/lang/Object;)Z
      36: ifeq          47
      39: aload_1
      40: aload         6
      42: astore_2
      43: astore_1
      44: goto          0
      47: aload_2
      48: areturn

  private final scalaz.$eq$eq$greater$greater middle$1(java.lang.Object, java.lang.Object, scalaz.$eq$eq$greater$greater, scalaz.Order);
    Code:
       0: iconst_0
       1: istore        5
       3: aconst_null
       4: astore        6
       6: aload_3
       7: instanceof    #12                 // class scalaz/$eq$eq$greater$greater$Bin
      10: ifeq          59
      13: iconst_1
      14: istore        5
      16: aload_3
      17: checkcast     #12                 // class scalaz/$eq$eq$greater$greater$Bin
      20: astore        6
      22: aload         6
      24: invokevirtual #201                // Method scalaz/$eq$eq$greater$greater$Bin.k:()Ljava/lang/Object;
      27: astore        7
      29: aload         6
      31: invokevirtual #209                // Method scalaz/$eq$eq$greater$greater$Bin.r:()Lscalaz/$eq$eq$greater$greater;
      34: astore        8
      36: aload         4
      38: aload         7
      40: aload_1
      41: invokeinterface #593,  3          // InterfaceMethod scalaz/Order.lessThanOrEqual:(Ljava/lang/Object;Ljava/lang/Object;)Z
      46: ifeq          59
      49: aload_1
      50: aload_2
      51: aload         8
      53: astore_3
      54: astore_2
      55: astore_1
      56: goto          0
      59: iload         5
      61: ifeq          101
      64: aload         6
      66: invokevirtual #201                // Method scalaz/$eq$eq$greater$greater$Bin.k:()Ljava/lang/Object;
      69: astore        9
      71: aload         6
      73: invokevirtual #206                // Method scalaz/$eq$eq$greater$greater$Bin.l:()Lscalaz/$eq$eq$greater$greater;
      76: astore        10
      78: aload         4
      80: aload         9
      82: aload_2
      83: invokeinterface #596,  3          // InterfaceMethod scalaz/Order.greaterThanOrEqual:(Ljava/lang/Object;Ljava/lang/Object;)Z
      88: ifeq          101
      91: aload_1
      92: aload_2
      93: aload         10
      95: astore_3
      96: astore_2
      97: astore_1
      98: goto          0
     101: aload_3
     102: areturn

  private final scala.Tuple2 greater$2(java.lang.Object, scalaz.$eq$eq$greater$greater, scalaz.Order);
    Code:
       0: aload_2
       1: instanceof    #17                 // class scalaz/$eq$eq$greater$greater$Tip
       4: ifeq          31
       7: new           #141                // class scala/Tuple2
      10: dup
      11: getstatic     #385                // Field scalaz/Maybe$.MODULE$:Lscalaz/Maybe$;
      14: pop
      15: getstatic     #388                // Field scalaz/Maybe$Empty$.MODULE$:Lscalaz/Maybe$Empty$;
      18: invokevirtual #391                // Method scalaz/Maybe$Empty$.apply:()Lscalaz/Maybe;
      21: getstatic     #66                 // Field scalaz/$eq$eq$greater$greater$Tip$.MODULE$:Lscalaz/$eq$eq$greater$greater$Tip$;
      24: invokevirtual #69                 // Method scalaz/$eq$eq$greater$greater$Tip$.apply:()Lscalaz/$eq$eq$greater$greater;
      27: invokespecial #394                // Method scala/Tuple2."<init>":(Ljava/lang/Object;Ljava/lang/Object;)V
      30: areturn
      31: aload_2
      32: instanceof    #12                 // class scalaz/$eq$eq$greater$greater$Bin
      35: ifeq          173
      38: aload_2
      39: checkcast     #12                 // class scalaz/$eq$eq$greater$greater$Bin
      42: astore        4
      44: aload         4
      46: invokevirtual #201                // Method scalaz/$eq$eq$greater$greater$Bin.k:()Ljava/lang/Object;
      49: astore        5
      51: aload         4
      53: invokevirtual #204                // Method scalaz/$eq$eq$greater$greater$Bin.v:()Ljava/lang/Object;
      56: astore        6
      58: aload         4
      60: invokevirtual #206                // Method scalaz/$eq$eq$greater$greater$Bin.l:()Lscalaz/$eq$eq$greater$greater;
      63: astore        7
      65: aload         4
      67: invokevirtual #209                // Method scalaz/$eq$eq$greater$greater$Bin.r:()Lscalaz/$eq$eq$greater$greater;
      70: astore        8
      72: aload_3
      73: aload_1
      74: aload         5
      76: invokeinterface #215,  3          // InterfaceMethod scalaz/Order.order:(Ljava/lang/Object;Ljava/lang/Object;)Lscalaz/Ordering;
      81: astore        9
      83: getstatic     #218                // Field scalaz/Ordering$LT$.MODULE$:Lscalaz/Ordering$LT$;
      86: aload         9
      88: invokevirtual #224                // Method java/lang/Object.equals:(Ljava/lang/Object;)Z
      91: ifeq          110
      94: new           #141                // class scala/Tuple2
      97: dup
      98: aload         7
     100: aload_1
     101: aload_3
     102: invokevirtual #601                // Method scalaz/$eq$eq$greater$greater.lookup:(Ljava/lang/Object;Lscalaz/Order;)Lscalaz/Maybe;
     105: aload_2
     106: invokespecial #394                // Method scala/Tuple2."<init>":(Ljava/lang/Object;Ljava/lang/Object;)V
     109: areturn
     110: getstatic     #241                // Field scalaz/Ordering$EQ$.MODULE$:Lscalaz/Ordering$EQ$;
     113: aload         9
     115: invokevirtual #224                // Method java/lang/Object.equals:(Ljava/lang/Object;)Z
     118: ifeq          144
     121: new           #141                // class scala/Tuple2
     124: dup
     125: getstatic     #385                // Field scalaz/Maybe$.MODULE$:Lscalaz/Maybe$;
     128: pop
     129: new           #37                 // class scalaz/Maybe$Just
     132: dup
     133: aload         6
     135: invokespecial #405                // Method scalaz/Maybe$Just."<init>":(Ljava/lang/Object;)V
     138: aload         8
     140: invokespecial #394                // Method scala/Tuple2."<init>":(Ljava/lang/Object;Ljava/lang/Object;)V
     143: areturn
     144: getstatic     #235                // Field scalaz/Ordering$GT$.MODULE$:Lscalaz/Ordering$GT$;
     147: aload         9
     149: invokevirtual #224                // Method java/lang/Object.equals:(Ljava/lang/Object;)Z
     152: ifeq          163
     155: aload_1
     156: aload         8
     158: astore_2
     159: astore_1
     160: goto          0
     163: new           #146                // class scala/MatchError
     166: dup
     167: aload         9
     169: invokespecial #149                // Method scala/MatchError."<init>":(Ljava/lang/Object;)V
     172: athrow
     173: new           #146                // class scala/MatchError
     176: dup
     177: aload_2
     178: invokespecial #149                // Method scala/MatchError."<init>":(Ljava/lang/Object;)V
     181: athrow

  private final scala.Tuple2 middle$2(java.lang.Object, java.lang.Object, scalaz.$eq$eq$greater$greater, scalaz.Order);
    Code:
       0: aload_3
       1: instanceof    #17                 // class scalaz/$eq$eq$greater$greater$Tip
       4: ifeq          31
       7: new           #141                // class scala/Tuple2
      10: dup
      11: getstatic     #385                // Field scalaz/Maybe$.MODULE$:Lscalaz/Maybe$;
      14: pop
      15: getstatic     #388                // Field scalaz/Maybe$Empty$.MODULE$:Lscalaz/Maybe$Empty$;
      18: invokevirtual #391                // Method scalaz/Maybe$Empty$.apply:()Lscalaz/Maybe;
      21: getstatic     #66                 // Field scalaz/$eq$eq$greater$greater$Tip$.MODULE$:Lscalaz/$eq$eq$greater$greater$Tip$;
      24: invokevirtual #69                 // Method scalaz/$eq$eq$greater$greater$Tip$.apply:()Lscalaz/$eq$eq$greater$greater;
      27: invokespecial #394                // Method scala/Tuple2."<init>":(Ljava/lang/Object;Ljava/lang/Object;)V
      30: areturn
      31: aload_3
      32: instanceof    #12                 // class scalaz/$eq$eq$greater$greater$Bin
      35: ifeq          236
      38: aload_3
      39: checkcast     #12                 // class scalaz/$eq$eq$greater$greater$Bin
      42: astore        5
      44: aload         5
      46: invokevirtual #201                // Method scalaz/$eq$eq$greater$greater$Bin.k:()Ljava/lang/Object;
      49: astore        6
      51: aload         5
      53: invokevirtual #204                // Method scalaz/$eq$eq$greater$greater$Bin.v:()Ljava/lang/Object;
      56: astore        7
      58: aload         5
      60: invokevirtual #206                // Method scalaz/$eq$eq$greater$greater$Bin.l:()Lscalaz/$eq$eq$greater$greater;
      63: astore        8
      65: aload         5
      67: invokevirtual #209                // Method scalaz/$eq$eq$greater$greater$Bin.r:()Lscalaz/$eq$eq$greater$greater;
      70: astore        9
      72: iconst_0
      73: istore        10
      75: aload         4
      77: aload_1
      78: aload         6
      80: invokeinterface #215,  3          // InterfaceMethod scalaz/Order.order:(Ljava/lang/Object;Ljava/lang/Object;)Lscalaz/Ordering;
      85: astore        11
      87: getstatic     #218                // Field scalaz/Ordering$LT$.MODULE$:Lscalaz/Ordering$LT$;
      90: aload         11
      92: invokevirtual #224                // Method java/lang/Object.equals:(Ljava/lang/Object;)Z
      95: ifeq          149
      98: iconst_1
      99: istore        10
     101: aload         4
     103: aload         6
     105: aload_2
     106: invokeinterface #215,  3          // InterfaceMethod scalaz/Order.order:(Ljava/lang/Object;Ljava/lang/Object;)Lscalaz/Ordering;
     111: getstatic     #218                // Field scalaz/Ordering$LT$.MODULE$:Lscalaz/Ordering$LT$;
     114: astore        12
     116: dup
     117: ifnonnull     124
     120: pop
     121: goto          149
     124: aload         12
     126: invokevirtual #224                // Method java/lang/Object.equals:(Ljava/lang/Object;)Z
     129: ifeq          149
     132: new           #141                // class scala/Tuple2
     135: dup
     136: aload         8
     138: aload_1
     139: aload         4
     141: invokevirtual #601                // Method scalaz/$eq$eq$greater$greater.lookup:(Ljava/lang/Object;Lscalaz/Order;)Lscalaz/Maybe;
     144: aload_3
     145: invokespecial #394                // Method scala/Tuple2."<init>":(Ljava/lang/Object;Ljava/lang/Object;)V
     148: areturn
     149: iload         10
     151: ifeq          164
     154: aload_1
     155: aload_2
     156: aload         8
     158: astore_3
     159: astore_2
     160: astore_1
     161: goto          0
     164: getstatic     #241                // Field scalaz/Ordering$EQ$.MODULE$:Lscalaz/Ordering$EQ$;
     167: aload         11
     169: invokevirtual #224                // Method java/lang/Object.equals:(Ljava/lang/Object;)Z
     172: ifeq          205
     175: new           #141                // class scala/Tuple2
     178: dup
     179: getstatic     #385                // Field scalaz/Maybe$.MODULE$:Lscalaz/Maybe$;
     182: pop
     183: new           #37                 // class scalaz/Maybe$Just
     186: dup
     187: aload         7
     189: invokespecial #405                // Method scalaz/Maybe$Just."<init>":(Ljava/lang/Object;)V
     192: aload_0
     193: aload_2
     194: aload         9
     196: aload         4
     198: invokespecial #604                // Method lesser$2:(Ljava/lang/Object;Lscalaz/$eq$eq$greater$greater;Lscalaz/Order;)Lscalaz/$eq$eq$greater$greater;
     201: invokespecial #394                // Method scala/Tuple2."<init>":(Ljava/lang/Object;Ljava/lang/Object;)V
     204: areturn
     205: getstatic     #235                // Field scalaz/Ordering$GT$.MODULE$:Lscalaz/Ordering$GT$;
     208: aload         11
     210: invokevirtual #224                // Method java/lang/Object.equals:(Ljava/lang/Object;)Z
     213: ifeq          226
     216: aload_1
     217: aload_2
     218: aload         9
     220: astore_3
     221: astore_2
     222: astore_1
     223: goto          0
     226: new           #146                // class scala/MatchError
     229: dup
     230: aload         11
     232: invokespecial #149                // Method scala/MatchError."<init>":(Ljava/lang/Object;)V
     235: athrow
     236: new           #146                // class scala/MatchError
     239: dup
     240: aload_3
     241: invokespecial #149                // Method scala/MatchError."<init>":(Ljava/lang/Object;)V
     244: athrow

  private final scalaz.$eq$eq$greater$greater lesser$2(java.lang.Object, scalaz.$eq$eq$greater$greater, scalaz.Order);
    Code:
       0: aload_2
       1: instanceof    #12                 // class scalaz/$eq$eq$greater$greater$Bin
       4: ifeq          47
       7: aload_2
       8: checkcast     #12                 // class scalaz/$eq$eq$greater$greater$Bin
      11: astore        4
      13: aload         4
      15: invokevirtual #201                // Method scalaz/$eq$eq$greater$greater$Bin.k:()Ljava/lang/Object;
      18: astore        5
      20: aload         4
      22: invokevirtual #206                // Method scalaz/$eq$eq$greater$greater$Bin.l:()Lscalaz/$eq$eq$greater$greater;
      25: astore        6
      27: aload_3
      28: aload         5
      30: aload_1
      31: invokeinterface #596,  3          // InterfaceMethod scalaz/Order.greaterThanOrEqual:(Ljava/lang/Object;Ljava/lang/Object;)Z
      36: ifeq          47
      39: aload_1
      40: aload         6
      42: astore_2
      43: astore_1
      44: goto          0
      47: aload_2
      48: areturn

  private final scalaz.$eq$eq$greater$greater hedgeMerge$1(scalaz.Maybe, scalaz.Maybe, scalaz.$eq$eq$greater$greater, scalaz.$eq$eq$greater$greater, scala.Function1, scalaz.Order, scala.Function1, scala.Function3);
    Code:
       0: new           #141                // class scala/Tuple2
       3: dup
       4: aload_3
       5: aload         4
       7: invokespecial #394                // Method scala/Tuple2."<init>":(Ljava/lang/Object;Ljava/lang/Object;)V
      10: astore        9
      12: aload         4
      14: instanceof    #17                 // class scalaz/$eq$eq$greater$greater$Tip
      17: ifeq          32
      20: aload         5
      22: aload_3
      23: invokeinterface #334,  2          // InterfaceMethod scala/Function1.apply:(Ljava/lang/Object;)Ljava/lang/Object;
      28: checkcast     #14                 // class scalaz/$eq$eq$greater$greater
      31: areturn
      32: aload_3
      33: instanceof    #17                 // class scalaz/$eq$eq$greater$greater$Tip
      36: ifeq          121
      39: aload         4
      41: instanceof    #12                 // class scalaz/$eq$eq$greater$greater$Bin
      44: ifeq          121
      47: aload         4
      49: checkcast     #12                 // class scalaz/$eq$eq$greater$greater$Bin
      52: astore        10
      54: aload         10
      56: invokevirtual #201                // Method scalaz/$eq$eq$greater$greater$Bin.k:()Ljava/lang/Object;
      59: astore        11
      61: aload         10
      63: invokevirtual #204                // Method scalaz/$eq$eq$greater$greater$Bin.v:()Ljava/lang/Object;
      66: astore        12
      68: aload         10
      70: invokevirtual #206                // Method scalaz/$eq$eq$greater$greater$Bin.l:()Lscalaz/$eq$eq$greater$greater;
      73: astore        13
      75: aload         10
      77: invokevirtual #209                // Method scalaz/$eq$eq$greater$greater$Bin.r:()Lscalaz/$eq$eq$greater$greater;
      80: astore        14
      82: aload_0
      83: aload         11
      85: aload         12
      87: aload         13
      89: aload_1
      90: aload         6
      92: invokevirtual #398                // Method scalaz/$eq$eq$greater$greater.scalaz$$eq$eq$greater$greater$$filterGt:(Lscalaz/Maybe;Lscalaz/Order;)Lscalaz/$eq$eq$greater$greater;
      95: aload         14
      97: aload_2
      98: aload         6
     100: invokevirtual #401                // Method scalaz/$eq$eq$greater$greater.scalaz$$eq$eq$greater$greater$$filterLt:(Lscalaz/Maybe;Lscalaz/Order;)Lscalaz/$eq$eq$greater$greater;
     103: invokevirtual #404                // Method link:(Ljava/lang/Object;Ljava/lang/Object;Lscalaz/$eq$eq$greater$greater;Lscalaz/$eq$eq$greater$greater;)Lscalaz/$eq$eq$greater$greater;
     106: astore        15
     108: aload         7
     110: aload         15
     112: invokeinterface #334,  2          // InterfaceMethod scala/Function1.apply:(Ljava/lang/Object;)Ljava/lang/Object;
     117: checkcast     #14                 // class scalaz/$eq$eq$greater$greater
     120: areturn
     121: aload_3
     122: instanceof    #12                 // class scalaz/$eq$eq$greater$greater$Bin
     125: ifeq          500
     128: aload_3
     129: checkcast     #12                 // class scalaz/$eq$eq$greater$greater$Bin
     132: astore        16
     134: aload         16
     136: invokevirtual #201                // Method scalaz/$eq$eq$greater$greater$Bin.k:()Ljava/lang/Object;
     139: astore        17
     141: aload         16
     143: invokevirtual #204                // Method scalaz/$eq$eq$greater$greater$Bin.v:()Ljava/lang/Object;
     146: astore        18
     148: aload         16
     150: invokevirtual #206                // Method scalaz/$eq$eq$greater$greater$Bin.l:()Lscalaz/$eq$eq$greater$greater;
     153: astore        19
     155: aload         16
     157: invokevirtual #209                // Method scalaz/$eq$eq$greater$greater$Bin.r:()Lscalaz/$eq$eq$greater$greater;
     160: astore        20
     162: getstatic     #385                // Field scalaz/Maybe$.MODULE$:Lscalaz/Maybe$;
     165: pop
     166: new           #37                 // class scalaz/Maybe$Just
     169: dup
     170: aload         17
     172: invokespecial #405                // Method scalaz/Maybe$Just."<init>":(Ljava/lang/Object;)V
     175: astore        21
     177: aload_0
     178: aload_1
     179: aload         21
     181: aload         19
     183: aload_0
     184: aload_1
     185: aload         21
     187: aload         4
     189: aload         6
     191: invokevirtual #409                // Method trim:(Lscalaz/Maybe;Lscalaz/Maybe;Lscalaz/$eq$eq$greater$greater;Lscalaz/Order;)Lscalaz/$eq$eq$greater$greater;
     194: aload         5
     196: aload         6
     198: aload         7
     200: aload         8
     202: invokespecial #413                // Method hedgeMerge$1:(Lscalaz/Maybe;Lscalaz/Maybe;Lscalaz/$eq$eq$greater$greater;Lscalaz/$eq$eq$greater$greater;Lscala/Function1;Lscalaz/Order;Lscala/Function1;Lscala/Function3;)Lscalaz/$eq$eq$greater$greater;
     205: astore        22
     207: aload_0
     208: aload         17
     210: aload_2
     211: aload         4
     213: aload         6
     215: invokevirtual #417                // Method trimLookupLo:(Ljava/lang/Object;Lscalaz/Maybe;Lscalaz/$eq$eq$greater$greater;Lscalaz/Order;)Lscala/Tuple2;
     218: astore        23
     220: aload         23
     222: ifnull        248
     225: aload         23
     227: invokevirtual #194                // Method scala/Tuple2._1:()Ljava/lang/Object;
     230: checkcast     #31                 // class scalaz/Maybe
     233: astore        24
     235: aload         23
     237: invokevirtual #197                // Method scala/Tuple2._2:()Ljava/lang/Object;
     240: checkcast     #14                 // class scalaz/$eq$eq$greater$greater
     243: astore        25
     245: goto          257
     248: new           #146                // class scala/MatchError
     251: dup
     252: aconst_null
     253: invokespecial #149                // Method scala/MatchError."<init>":(Ljava/lang/Object;)V
     256: athrow
     257: aload_0
     258: aload         21
     260: aload_2
     261: aload         20
     263: aload         25
     265: aload         5
     267: aload         6
     269: aload         7
     271: aload         8
     273: invokespecial #413                // Method hedgeMerge$1:(Lscalaz/Maybe;Lscalaz/Maybe;Lscalaz/$eq$eq$greater$greater;Lscalaz/$eq$eq$greater$greater;Lscala/Function1;Lscalaz/Order;Lscala/Function1;Lscala/Function3;)Lscalaz/$eq$eq$greater$greater;
     276: astore        26
     278: aload         24
     280: instanceof    #29                 // class scalaz/Maybe$Empty
     283: ifeq          397
     286: aload         5
     288: aload_0
     289: aload         17
     291: aload         18
     293: invokevirtual #199                // Method singleton:(Ljava/lang/Object;Ljava/lang/Object;)Lscalaz/$eq$eq$greater$greater;
     296: invokeinterface #334,  2          // InterfaceMethod scala/Function1.apply:(Ljava/lang/Object;)Ljava/lang/Object;
     301: checkcast     #14                 // class scalaz/$eq$eq$greater$greater
     304: astore        27
     306: aload         27
     308: instanceof    #17                 // class scalaz/$eq$eq$greater$greater$Tip
     311: ifeq          322
     314: aload         22
     316: aload         26
     318: invokevirtual #420                // Method scalaz/$eq$eq$greater$greater.merge:(Lscalaz/$eq$eq$greater$greater;)Lscalaz/$eq$eq$greater$greater;
     321: areturn
     322: aload         27
     324: instanceof    #12                 // class scalaz/$eq$eq$greater$greater$Bin
     327: ifeq          387
     330: aload         27
     332: checkcast     #12                 // class scalaz/$eq$eq$greater$greater$Bin
     335: astore        28
     337: aload         28
     339: invokevirtual #204                // Method scalaz/$eq$eq$greater$greater$Bin.v:()Ljava/lang/Object;
     342: astore        29
     344: aload         28
     346: invokevirtual #206                // Method scalaz/$eq$eq$greater$greater$Bin.l:()Lscalaz/$eq$eq$greater$greater;
     349: astore        30
     351: aload         28
     353: invokevirtual #209                // Method scalaz/$eq$eq$greater$greater$Bin.r:()Lscalaz/$eq$eq$greater$greater;
     356: astore        31
     358: aload         30
     360: instanceof    #17                 // class scalaz/$eq$eq$greater$greater$Tip
     363: ifeq          387
     366: aload         31
     368: instanceof    #17                 // class scalaz/$eq$eq$greater$greater$Tip
     371: ifeq          387
     374: aload_0
     375: aload         17
     377: aload         29
     379: aload         22
     381: aload         26
     383: invokevirtual #404                // Method link:(Ljava/lang/Object;Ljava/lang/Object;Lscalaz/$eq$eq$greater$greater;Lscalaz/$eq$eq$greater$greater;)Lscalaz/$eq$eq$greater$greater;
     386: areturn
     387: getstatic     #425                // Field scala/sys/package$.MODULE$:Lscala/sys/package$;
     390: ldc_w         #427                // String mergeWithKey: Given function g1 does not fulfil required conditions (see documentation)
     393: invokevirtual #431                // Method scala/sys/package$.error:(Ljava/lang/String;)Lscala/runtime/Nothing$;
     396: athrow
     397: aload         24
     399: instanceof    #37                 // class scalaz/Maybe$Just
     402: ifeq          490
     405: aload         24
     407: checkcast     #37                 // class scalaz/Maybe$Just
     410: invokevirtual #434                // Method scalaz/Maybe$Just.get:()Ljava/lang/Object;
     413: astore        32
     415: aload         8
     417: aload         17
     419: aload         18
     421: aload         32
     423: invokeinterface #273,  4          // InterfaceMethod scala/Function3.apply:(Ljava/lang/Object;Ljava/lang/Object;Ljava/lang/Object;)Ljava/lang/Object;
     428: checkcast     #31                 // class scalaz/Maybe
     431: astore        33
     433: aload         33
     435: instanceof    #29                 // class scalaz/Maybe$Empty
     438: ifeq          449
     441: aload         22
     443: aload         26
     445: invokevirtual #420                // Method scalaz/$eq$eq$greater$greater.merge:(Lscalaz/$eq$eq$greater$greater;)Lscalaz/$eq$eq$greater$greater;
     448: areturn
     449: aload         33
     451: instanceof    #37                 // class scalaz/Maybe$Just
     454: ifeq          480
     457: aload         33
     459: checkcast     #37                 // class scalaz/Maybe$Just
     462: invokevirtual #434                // Method scalaz/Maybe$Just.get:()Ljava/lang/Object;
     465: astore        34
     467: aload_0
     468: aload         17
     470: aload         34
     472: aload         22
     474: aload         26
     476: invokevirtual #404                // Method link:(Ljava/lang/Object;Ljava/lang/Object;Lscalaz/$eq$eq$greater$greater;Lscalaz/$eq$eq$greater$greater;)Lscalaz/$eq$eq$greater$greater;
     479: areturn
     480: new           #146                // class scala/MatchError
     483: dup
     484: aload         33
     486: invokespecial #149                // Method scala/MatchError."<init>":(Ljava/lang/Object;)V
     489: athrow
     490: new           #146                // class scala/MatchError
     493: dup
     494: aload         24
     496: invokespecial #149                // Method scala/MatchError."<init>":(Ljava/lang/Object;)V
     499: athrow
     500: new           #146                // class scala/MatchError
     503: dup
     504: aload         9
     506: invokespecial #149                // Method scala/MatchError."<init>":(Ljava/lang/Object;)V
     509: athrow

  private scalaz.$eq$eq$greater$greater$();
    Code:
       0: aload_0
       1: invokespecial #619                // Method scalaz/MapInstances."<init>":()V
       4: return

  private static java.lang.Object $deserializeLambda$(java.lang.invoke.SerializedLambda);
    Code:
       0: aload_0
       1: invokedynamic #631,  0            // InvokeDynamic #12:lambdaDeserialize:(Ljava/lang/invoke/SerializedLambda;)Ljava/lang/Object;
       6: areturn
}
