Compiled from "Adjunction.scala"
public abstract class scalaz.Adjunction<F, G> {
  private final scalaz.Functor<F> F;

  private final scalaz.Functor<G> G;

  private final scalaz.Zap<F, G> zapFG;

  private final scalaz.Zap<G, F> zapGF;

  private final scalaz.Representable<G, F> representable;

  private final scalaz.Monad<?> monad;

  private final scalaz.Comonad<?> comonad;

  public static <F, G> scalaz.Adjunction<F, G> apply(scalaz.Adjunction<F, G>);
    Code:
       0: getstatic     #59                 // Field scalaz/Adjunction$.MODULE$:Lscalaz/Adjunction$;
       3: pop
       4: aload_0
       5: areturn

  public static <E> scalaz.Adjunction<?, ?> writerReaderAdjunction();
    Code:
       0: getstatic     #59                 // Field scalaz/Adjunction$.MODULE$:Lscalaz/Adjunction$;
       3: pop
       4: new           #28                 // class scalaz/AdjunctionInstances$$anon$12
       7: dup
       8: aconst_null
       9: invokespecial #67                 // Method scalaz/AdjunctionInstances$$anon$12."<init>":(Lscalaz/AdjunctionInstances;)V
      12: areturn

  public static scalaz.Adjunction<scala.Function0, java.lang.Object> f0IdAdjunction();
    Code:
       0: getstatic     #59                 // Field scalaz/Adjunction$.MODULE$:Lscalaz/Adjunction$;
       3: invokevirtual #71                 // Method scalaz/Adjunction$.f0IdAdjunction:()Lscalaz/Adjunction;
       6: areturn

  public static scalaz.Adjunction<java.lang.Object, scala.Function0> idF0Adjunction();
    Code:
       0: getstatic     #59                 // Field scalaz/Adjunction$.MODULE$:Lscalaz/Adjunction$;
       3: invokevirtual #75                 // Method scalaz/Adjunction$.idF0Adjunction:()Lscalaz/Adjunction;
       6: areturn

  public static scalaz.Adjunction<scala.Function0, scala.Function0> f0Adjunction();
    Code:
       0: getstatic     #59                 // Field scalaz/Adjunction$.MODULE$:Lscalaz/Adjunction$;
       3: invokevirtual #79                 // Method scalaz/Adjunction$.f0Adjunction:()Lscalaz/Adjunction;
       6: areturn

  public static scalaz.Adjunction<java.lang.Object, java.lang.Object> identityAdjunction();
    Code:
       0: getstatic     #59                 // Field scalaz/Adjunction$.MODULE$:Lscalaz/Adjunction$;
       3: invokevirtual #83                 // Method scalaz/Adjunction$.identityAdjunction:()Lscalaz/Adjunction;
       6: areturn

  public static <S> scalaz.Adjunction<?, ?> curryUncurryAdjunction();
    Code:
       0: getstatic     #59                 // Field scalaz/Adjunction$.MODULE$:Lscalaz/Adjunction$;
       3: pop
       4: new           #30                 // class scalaz/AdjunctionInstances$$anon$7
       7: dup
       8: aconst_null
       9: invokespecial #86                 // Method scalaz/AdjunctionInstances$$anon$7."<init>":(Lscalaz/AdjunctionInstances;)V
      12: areturn

  public static <F, P, G, Q> scalaz.Adjunction<?, ?> compositeAdjunction(scalaz.Adjunction<F, G>, scalaz.Adjunction<P, Q>);
    Code:
       0: getstatic     #59                 // Field scalaz/Adjunction$.MODULE$:Lscalaz/Adjunction$;
       3: pop
       4: aload_0
       5: aload_1
       6: invokevirtual #94                 // Method compose:(Lscalaz/Adjunction;)Lscalaz/Adjunction;
       9: areturn

  public scalaz.Functor<F> F();
    Code:
       0: aload_0
       1: getfield      #98                 // Field F:Lscalaz/Functor;
       4: areturn

  public scalaz.Functor<G> G();
    Code:
       0: aload_0
       1: getfield      #102                // Field G:Lscalaz/Functor;
       4: areturn

  public <A> G unit(scala.Function0<A>);
    Code:
       0: aload_0
       1: aload_1
       2: invokedynamic #123,  0            // InvokeDynamic #0:apply:()Lscala/Function1;
       7: invokevirtual #127                // Method leftAdjunct:(Lscala/Function0;Lscala/Function1;)Ljava/lang/Object;
      10: areturn

  public <A> A counit(F);
    Code:
       0: aload_0
       1: aload_1
       2: invokedynamic #135,  0            // InvokeDynamic #1:apply:()Lscala/Function1;
       7: invokevirtual #139                // Method rightAdjunct:(Ljava/lang/Object;Lscala/Function1;)Ljava/lang/Object;
      10: areturn

  public <A, B> G leftAdjunct(scala.Function0<A>, scala.Function1<F, B>);
    Code:
       0: aload_0
       1: invokevirtual #144                // Method G:()Lscalaz/Functor;
       4: aload_0
       5: aload_1
       6: invokevirtual #146                // Method unit:(Lscala/Function0;)Ljava/lang/Object;
       9: aload_2
      10: invokeinterface #151,  3          // InterfaceMethod scalaz/Functor.map:(Ljava/lang/Object;Lscala/Function1;)Ljava/lang/Object;
      15: areturn

  public <A, B> B rightAdjunct(F, scala.Function1<A, G>);
    Code:
       0: aload_0
       1: aload_0
       2: invokevirtual #155                // Method F:()Lscalaz/Functor;
       5: aload_1
       6: aload_2
       7: invokeinterface #151,  3          // InterfaceMethod scalaz/Functor.map:(Ljava/lang/Object;Lscala/Function1;)Ljava/lang/Object;
      12: invokevirtual #157                // Method counit:(Ljava/lang/Object;)Ljava/lang/Object;
      15: areturn

  public scalaz.Zap<F, G> zapFG();
    Code:
       0: aload_0
       1: getfield      #161                // Field zapFG:Lscalaz/Zap;
       4: areturn

  public scalaz.Zap<G, F> zapGF();
    Code:
       0: aload_0
       1: getfield      #164                // Field zapGF:Lscalaz/Zap;
       4: areturn

  public scalaz.Representable<G, F> representable();
    Code:
       0: aload_0
       1: getfield      #168                // Field representable:Lscalaz/Representable;
       4: areturn

  public scalaz.Monad<?> monad();
    Code:
       0: aload_0
       1: getfield      #172                // Field monad:Lscalaz/Monad;
       4: areturn

  public scalaz.Comonad<?> comonad();
    Code:
       0: aload_0
       1: getfield      #176                // Field comonad:Lscalaz/Comonad;
       4: areturn

  public <P, Q> scalaz.Adjunction<?, ?> compose(scalaz.Adjunction<P, Q>);
    Code:
       0: aload_1
       1: invokevirtual #155                // Method F:()Lscalaz/Functor;
       4: astore_2
       5: aload_1
       6: invokevirtual #144                // Method G:()Lscalaz/Functor;
       9: astore_3
      10: aload_2
      11: aload_0
      12: invokevirtual #155                // Method F:()Lscalaz/Functor;
      15: invokeinterface #180,  2          // InterfaceMethod scalaz/Functor.compose:(Lscalaz/Functor;)Lscalaz/Functor;
      20: astore        4
      22: aload_0
      23: invokevirtual #144                // Method G:()Lscalaz/Functor;
      26: aload_3
      27: invokeinterface #180,  2          // InterfaceMethod scalaz/Functor.compose:(Lscalaz/Functor;)Lscalaz/Functor;
      32: astore        5
      34: new           #26                 // class scalaz/Adjunction$$anon$6
      37: dup
      38: aload_0
      39: aload         4
      41: aload         5
      43: aload_1
      44: aload_2
      45: invokespecial #183                // Method scalaz/Adjunction$$anon$6."<init>":(Lscalaz/Adjunction;Lscalaz/Functor;Lscalaz/Functor;Lscalaz/Adjunction;Lscalaz/Functor;)V
      48: areturn

  public static final java.lang.Object $anonfun$unit$1(java.lang.Object);
    Code:
       0: aload_0
       1: areturn

  public static final java.lang.Object $anonfun$counit$1(java.lang.Object);
    Code:
       0: aload_0
       1: areturn

  public scalaz.Adjunction(scalaz.Functor<F>, scalaz.Functor<G>);
    Code:
       0: aload_0
       1: aload_1
       2: putfield      #98                 // Field F:Lscalaz/Functor;
       5: aload_0
       6: aload_2
       7: putfield      #102                // Field G:Lscalaz/Functor;
      10: aload_0
      11: invokespecial #193                // Method java/lang/Object."<init>":()V
      14: aload_0
      15: new           #16                 // class scalaz/Adjunction$$anon$1
      18: dup
      19: aload_0
      20: invokespecial #196                // Method scalaz/Adjunction$$anon$1."<init>":(Lscalaz/Adjunction;)V
      23: putfield      #161                // Field zapFG:Lscalaz/Zap;
      26: aload_0
      27: new           #18                 // class scalaz/Adjunction$$anon$2
      30: dup
      31: aload_0
      32: invokespecial #197                // Method scalaz/Adjunction$$anon$2."<init>":(Lscalaz/Adjunction;)V
      35: putfield      #164                // Field zapGF:Lscalaz/Zap;
      38: aload_0
      39: new           #20                 // class scalaz/Adjunction$$anon$3
      42: dup
      43: aload_0
      44: invokespecial #198                // Method scalaz/Adjunction$$anon$3."<init>":(Lscalaz/Adjunction;)V
      47: putfield      #168                // Field representable:Lscalaz/Representable;
      50: aload_0
      51: new           #22                 // class scalaz/Adjunction$$anon$4
      54: dup
      55: aload_0
      56: invokespecial #199                // Method scalaz/Adjunction$$anon$4."<init>":(Lscalaz/Adjunction;)V
      59: putfield      #172                // Field monad:Lscalaz/Monad;
      62: aload_0
      63: new           #24                 // class scalaz/Adjunction$$anon$5
      66: dup
      67: aload_0
      68: invokespecial #200                // Method scalaz/Adjunction$$anon$5."<init>":(Lscalaz/Adjunction;)V
      71: putfield      #176                // Field comonad:Lscalaz/Comonad;
      74: return

  private static java.lang.Object $deserializeLambda$(java.lang.invoke.SerializedLambda);
    Code:
       0: aload_0
       1: invokedynamic #212,  0            // InvokeDynamic #2:lambdaDeserialize:(Ljava/lang/invoke/SerializedLambda;)Ljava/lang/Object;
       6: areturn
}
