Compiled from "Composition.scala"
public interface scalaz.CompositionTraverse1<F, G> extends scalaz.Traverse1<?>, scalaz.CompositionFoldable1<F, G> {
  public abstract scalaz.Traverse1<F> F();

  public abstract scalaz.Traverse1<G> G();

  public static java.lang.Object traverse1Impl$(scalaz.CompositionTraverse1, java.lang.Object, scala.Function1, scalaz.Apply);
    Code:
       0: aload_0
       1: aload_1
       2: aload_2
       3: aload_3
       4: invokespecial #33                 // InterfaceMethod traverse1Impl:(Ljava/lang/Object;Lscala/Function1;Lscalaz/Apply;)Ljava/lang/Object;
       7: areturn

  public default <X, A, B> X traverse1Impl(F, scala.Function1<A, X>, scalaz.Apply<X>);
    Code:
       0: aload_0
       1: invokeinterface #40,  1           // InterfaceMethod F:()Lscalaz/Traverse1;
       6: aload_1
       7: aload_0
       8: aload_2
       9: aload_3
      10: invokedynamic #59,  0             // InvokeDynamic #0:apply:(Lscalaz/CompositionTraverse1;Lscala/Function1;Lscalaz/Apply;)Lscala/Function1;
      15: aload_3
      16: invokeinterface #62,  4           // InterfaceMethod scalaz/Traverse1.traverse1:(Ljava/lang/Object;Lscala/Function1;Lscalaz/Apply;)Ljava/lang/Object;
      21: areturn

  public static java.lang.Object $anonfun$traverse1Impl$1(scalaz.CompositionTraverse1, scala.Function1, scalaz.Apply, java.lang.Object);
    Code:
       0: aload_0
       1: invokeinterface #68,  1           // InterfaceMethod G:()Lscalaz/Traverse1;
       6: aload_3
       7: aload_1
       8: aload_2
       9: invokeinterface #62,  4           // InterfaceMethod scalaz/Traverse1.traverse1:(Ljava/lang/Object;Lscala/Function1;Lscalaz/Apply;)Ljava/lang/Object;
      14: areturn

  public static void $init$(scalaz.CompositionTraverse1);
    Code:
       0: return

  private static java.lang.Object $deserializeLambda$(java.lang.invoke.SerializedLambda);
    Code:
       0: aload_0
       1: invokedynamic #82,  0             // InvokeDynamic #1:lambdaDeserialize:(Ljava/lang/invoke/SerializedLambda;)Ljava/lang/Object;
       6: areturn
}
