Compiled from "Const.scala"
public interface scalaz.ConstMonoid<A, B> extends scalaz.Monoid<scalaz.Const<A, B>>, scalaz.ConstSemigroup<A, B> {
  public abstract scalaz.Monoid<A> A();

  public static scalaz.Const zero$(scalaz.ConstMonoid);
    Code:
       0: aload_0
       1: invokespecial #23                 // InterfaceMethod zero:()Lscalaz/Const;
       4: areturn

  public default scalaz.Const<A, B> zero();
    Code:
       0: new           #27                 // class scalaz/Const
       3: dup
       4: aload_0
       5: invokeinterface #29,  1           // InterfaceMethod A:()Lscalaz/Monoid;
      10: invokeinterface #32,  1           // InterfaceMethod scalaz/Monoid.zero:()Ljava/lang/Object;
      15: invokespecial #36                 // Method scalaz/Const."<init>":(Ljava/lang/Object;)V
      18: areturn

  public static void $init$(scalaz.ConstMonoid);
    Code:
       0: return
}
