Compiled from "ContravariantCoyoneda.scala"
public class scalaz.ContravariantCoyoneda$By$ {
  public static final scalaz.ContravariantCoyoneda$By$ MODULE$;

  public static {};
    Code:
       0: new           #2                  // class scalaz/ContravariantCoyoneda$By$
       3: dup
       4: invokespecial #20                 // Method "<init>":()V
       7: putstatic     #22                 // Field MODULE$:Lscalaz/ContravariantCoyoneda$By$;
      10: return

  public <F> boolean $lessinit$greater$default$1();
    Code:
       0: iconst_1
       1: ireturn

  public final <A, B, F> scalaz.ContravariantCoyoneda<F, A> apply$extension(boolean, scala.Function1<A, B>, F);
    Code:
       0: getstatic     #37                 // Field scalaz/ContravariantCoyoneda$.MODULE$:Lscalaz/ContravariantCoyoneda$;
       3: pop
       4: new           #7                  // class scalaz/ContravariantCoyoneda$$anon$2
       7: dup
       8: aload_2
       9: aload_3
      10: invokespecial #40                 // Method scalaz/ContravariantCoyoneda$$anon$2."<init>":(Lscala/Function1;Ljava/lang/Object;)V
      13: areturn

  public final <F> int hashCode$extension(boolean);
    Code:
       0: iload_1
       1: invokestatic  #51                 // Method java/lang/Boolean.hashCode:(Z)I
       4: ireturn

  public final <F> boolean equals$extension(boolean, java.lang.Object);
    Code:
       0: aload_2
       1: instanceof    #9                  // class scalaz/ContravariantCoyoneda$By
       4: ifeq          11
       7: iconst_1
       8: goto          12
      11: iconst_0
      12: ifeq          30
      15: aload_2
      16: checkcast     #9                  // class scalaz/ContravariantCoyoneda$By
      19: invokevirtual #58                 // Method scalaz/ContravariantCoyoneda$By.scalaz$ContravariantCoyoneda$By$$dummy:()Z
      22: istore_3
      23: iload_1
      24: iload_3
      25: if_icmpne     30
      28: iconst_1
      29: ireturn
      30: iconst_0
      31: ireturn

  public scalaz.ContravariantCoyoneda$By$();
    Code:
       0: aload_0
       1: invokespecial #59                 // Method java/lang/Object."<init>":()V
       4: return
}
