Compiled from "Day.scala"
public final class scalaz.Day$ extends scalaz.DayInstances {
  public static final scalaz.Day$ MODULE$;

  public static {};
    Code:
       0: new           #2                  // class scalaz/Day$
       3: dup
       4: invokespecial #19                 // Method "<init>":()V
       7: putstatic     #21                 // Field MODULE$:Lscalaz/Day$;
      10: return

  public <F, G, A, XX, YY> scalaz.Day<F, G, A> apply(F, G, scala.Function2<XX, YY, A>);
    Code:
       0: new           #12                 // class scalaz/Day$$anon$1
       3: dup
       4: aload_1
       5: aload_2
       6: aload_3
       7: invokespecial #30                 // Method scalaz/Day$$anon$1."<init>":(Ljava/lang/Object;Ljava/lang/Object;Lscala/Function2;)V
      10: areturn

  public <F, G, A, B> scalaz.Day<F, G, B> day(F, G);
    Code:
       0: invokedynamic #58,  0             // InvokeDynamic #0:apply:()Lscala/Function2;
       5: astore_3
       6: new           #12                 // class scalaz/Day$$anon$1
       9: dup
      10: aload_1
      11: aload_2
      12: aload_3
      13: invokespecial #30                 // Method scalaz/Day$$anon$1."<init>":(Ljava/lang/Object;Ljava/lang/Object;Lscala/Function2;)V
      16: areturn

  public <F, A> scalaz.Day<java.lang.Object, F, A> intro1(F);
    Code:
       0: getstatic     #68                 // Field scala/runtime/BoxedUnit.UNIT:Lscala/runtime/BoxedUnit;
       3: invokedynamic #75,  0             // InvokeDynamic #1:apply:()Lscala/Function2;
       8: astore_3
       9: astore_2
      10: new           #12                 // class scalaz/Day$$anon$1
      13: dup
      14: aload_2
      15: aload_1
      16: aload_3
      17: invokespecial #30                 // Method scalaz/Day$$anon$1."<init>":(Ljava/lang/Object;Ljava/lang/Object;Lscala/Function2;)V
      20: areturn

  public <F, A> scalaz.Day<F, java.lang.Object, A> intro2(F);
    Code:
       0: getstatic     #68                 // Field scala/runtime/BoxedUnit.UNIT:Lscala/runtime/BoxedUnit;
       3: invokedynamic #85,  0             // InvokeDynamic #2:apply:()Lscala/Function2;
       8: astore_3
       9: astore_2
      10: new           #12                 // class scalaz/Day$$anon$1
      13: dup
      14: aload_1
      15: aload_2
      16: aload_3
      17: invokespecial #30                 // Method scalaz/Day$$anon$1."<init>":(Ljava/lang/Object;Ljava/lang/Object;Lscala/Function2;)V
      20: areturn

  public <F, A> F elim1(scalaz.Day<java.lang.Object, F, A>, scalaz.Functor<F>);
    Code:
       0: aload_2
       1: aload_1
       2: invokeinterface #97,  1           // InterfaceMethod scalaz/Day.gy:()Ljava/lang/Object;
       7: aload_1
       8: invokedynamic #107,  0            // InvokeDynamic #3:apply:(Lscalaz/Day;)Lscala/Function1;
      13: invokeinterface #113,  3          // InterfaceMethod scalaz/Functor.map:(Ljava/lang/Object;Lscala/Function1;)Ljava/lang/Object;
      18: areturn

  public <F, A> F elim2(scalaz.Day<F, java.lang.Object, A>, scalaz.Functor<F>);
    Code:
       0: aload_2
       1: aload_1
       2: invokeinterface #120,  1          // InterfaceMethod scalaz/Day.fx:()Ljava/lang/Object;
       7: aload_1
       8: invokedynamic #125,  0            // InvokeDynamic #4:apply:(Lscalaz/Day;)Lscala/Function1;
      13: invokeinterface #113,  3          // InterfaceMethod scalaz/Functor.map:(Ljava/lang/Object;Lscala/Function1;)Ljava/lang/Object;
      18: areturn

  public <F, A> F dap(scalaz.Day<F, F, A>, scalaz.Applicative<F>);
    Code:
       0: aload_2
       1: aload_1
       2: invokedynamic #138,  0            // InvokeDynamic #5:apply:(Lscalaz/Day;)Lscala/Function0;
       7: aload_1
       8: invokedynamic #143,  0            // InvokeDynamic #6:apply:(Lscalaz/Day;)Lscala/Function0;
      13: aload_1
      14: invokeinterface #146,  1          // InterfaceMethod scalaz/Day.xya:()Lscala/Function2;
      19: invokeinterface #152,  4          // InterfaceMethod scalaz/Applicative.apply2:(Lscala/Function0;Lscala/Function0;Lscala/Function2;)Ljava/lang/Object;
      24: areturn

  public <F, G, H, A, B> scalaz.Day<?, H, A> assoc(scalaz.Day<F, ?, A>);
    Code:
       0: aload_1
       1: invokeinterface #120,  1          // InterfaceMethod scalaz/Day.fx:()Ljava/lang/Object;
       6: aload_1
       7: invokeinterface #97,  1           // InterfaceMethod scalaz/Day.gy:()Ljava/lang/Object;
      12: checkcast     #93                 // class scalaz/Day
      15: invokeinterface #120,  1          // InterfaceMethod scalaz/Day.fx:()Ljava/lang/Object;
      20: invokedynamic #163,  0            // InvokeDynamic #7:apply:()Lscala/Function2;
      25: astore        5
      27: astore        4
      29: astore_3
      30: new           #12                 // class scalaz/Day$$anon$1
      33: dup
      34: aload_3
      35: aload         4
      37: aload         5
      39: invokespecial #30                 // Method scalaz/Day$$anon$1."<init>":(Ljava/lang/Object;Ljava/lang/Object;Lscala/Function2;)V
      42: aconst_null
      43: astore_3
      44: aconst_null
      45: astore        4
      47: aconst_null
      48: astore        5
      50: astore_2
      51: aload_1
      52: invokeinterface #97,  1           // InterfaceMethod scalaz/Day.gy:()Ljava/lang/Object;
      57: checkcast     #93                 // class scalaz/Day
      60: invokeinterface #97,  1           // InterfaceMethod scalaz/Day.gy:()Ljava/lang/Object;
      65: aload_1
      66: invokedynamic #173,  0            // InvokeDynamic #8:apply:(Lscalaz/Day;)Lscala/Function2;
      71: astore        7
      73: astore        6
      75: new           #12                 // class scalaz/Day$$anon$1
      78: dup
      79: aload_2
      80: aload         6
      82: aload         7
      84: invokespecial #30                 // Method scalaz/Day$$anon$1."<init>":(Ljava/lang/Object;Ljava/lang/Object;Lscala/Function2;)V
      87: areturn

  public <F, G, H, A> scalaz.Day<F, ?, A> disassoc(scalaz.Day<?, H, A>);
    Code:
       0: aload_1
       1: invokeinterface #120,  1          // InterfaceMethod scalaz/Day.fx:()Ljava/lang/Object;
       6: checkcast     #93                 // class scalaz/Day
       9: invokeinterface #97,  1           // InterfaceMethod scalaz/Day.gy:()Ljava/lang/Object;
      14: aload_1
      15: invokeinterface #97,  1           // InterfaceMethod scalaz/Day.gy:()Ljava/lang/Object;
      20: invokedynamic #180,  0            // InvokeDynamic #9:apply:()Lscala/Function2;
      25: astore        5
      27: astore        4
      29: astore_3
      30: new           #12                 // class scalaz/Day$$anon$1
      33: dup
      34: aload_3
      35: aload         4
      37: aload         5
      39: invokespecial #30                 // Method scalaz/Day$$anon$1."<init>":(Ljava/lang/Object;Ljava/lang/Object;Lscala/Function2;)V
      42: aconst_null
      43: astore_3
      44: aconst_null
      45: astore        4
      47: aconst_null
      48: astore        5
      50: astore_2
      51: aload_1
      52: invokeinterface #120,  1          // InterfaceMethod scalaz/Day.fx:()Ljava/lang/Object;
      57: checkcast     #93                 // class scalaz/Day
      60: invokeinterface #120,  1          // InterfaceMethod scalaz/Day.fx:()Ljava/lang/Object;
      65: aload_1
      66: invokedynamic #188,  0            // InvokeDynamic #10:apply:(Lscalaz/Day;)Lscala/Function2;
      71: astore        7
      73: astore        6
      75: new           #12                 // class scalaz/Day$$anon$1
      78: dup
      79: aload         6
      81: aload_2
      82: aload         7
      84: invokespecial #30                 // Method scalaz/Day$$anon$1."<init>":(Ljava/lang/Object;Ljava/lang/Object;Lscala/Function2;)V
      87: areturn

  public static final java.lang.Object $anonfun$day$1(scala.Function1, java.lang.Object);
    Code:
       0: aload_0
       1: aload_1
       2: invokeinterface #195,  2          // InterfaceMethod scala/Function1.apply:(Ljava/lang/Object;)Ljava/lang/Object;
       7: areturn

  public static final java.lang.Object $anonfun$intro1$1(scala.runtime.BoxedUnit, java.lang.Object);
    Code:
       0: aload_1
       1: areturn

  public static final java.lang.Object $anonfun$intro2$1(java.lang.Object, scala.runtime.BoxedUnit);
    Code:
       0: aload_0
       1: areturn

  public static final java.lang.Object $anonfun$elim1$1(scalaz.Day, java.lang.Object);
    Code:
       0: aload_0
       1: invokeinterface #146,  1          // InterfaceMethod scalaz/Day.xya:()Lscala/Function2;
       6: aload_0
       7: invokeinterface #120,  1          // InterfaceMethod scalaz/Day.fx:()Ljava/lang/Object;
      12: aload_1
      13: invokeinterface #205,  3          // InterfaceMethod scala/Function2.apply:(Ljava/lang/Object;Ljava/lang/Object;)Ljava/lang/Object;
      18: areturn

  public static final java.lang.Object $anonfun$elim2$1(scalaz.Day, java.lang.Object);
    Code:
       0: aload_0
       1: invokeinterface #146,  1          // InterfaceMethod scalaz/Day.xya:()Lscala/Function2;
       6: aload_1
       7: aload_0
       8: invokeinterface #97,  1           // InterfaceMethod scalaz/Day.gy:()Ljava/lang/Object;
      13: invokeinterface #205,  3          // InterfaceMethod scala/Function2.apply:(Ljava/lang/Object;Ljava/lang/Object;)Ljava/lang/Object;
      18: areturn

  public static final java.lang.Object $anonfun$dap$1(scalaz.Day);
    Code:
       0: aload_0
       1: invokeinterface #120,  1          // InterfaceMethod scalaz/Day.fx:()Ljava/lang/Object;
       6: areturn

  public static final java.lang.Object $anonfun$dap$2(scalaz.Day);
    Code:
       0: aload_0
       1: invokeinterface #97,  1           // InterfaceMethod scalaz/Day.gy:()Ljava/lang/Object;
       6: areturn

  public static final scala.Tuple2 $anonfun$assoc$1(java.lang.Object, java.lang.Object);
    Code:
       0: new           #210                // class scala/Tuple2
       3: dup
       4: aload_0
       5: aload_1
       6: invokespecial #213                // Method scala/Tuple2."<init>":(Ljava/lang/Object;Ljava/lang/Object;)V
       9: areturn

  public static final java.lang.Object $anonfun$assoc$2(scalaz.Day, scala.Tuple2, java.lang.Object);
    Code:
       0: aload_0
       1: invokeinterface #146,  1          // InterfaceMethod scalaz/Day.xya:()Lscala/Function2;
       6: aload_1
       7: invokevirtual #218                // Method scala/Tuple2._1:()Ljava/lang/Object;
      10: aload_0
      11: invokeinterface #97,  1           // InterfaceMethod scalaz/Day.gy:()Ljava/lang/Object;
      16: checkcast     #93                 // class scalaz/Day
      19: invokeinterface #146,  1          // InterfaceMethod scalaz/Day.xya:()Lscala/Function2;
      24: aload_1
      25: invokevirtual #221                // Method scala/Tuple2._2:()Ljava/lang/Object;
      28: aload_2
      29: invokeinterface #205,  3          // InterfaceMethod scala/Function2.apply:(Ljava/lang/Object;Ljava/lang/Object;)Ljava/lang/Object;
      34: invokeinterface #205,  3          // InterfaceMethod scala/Function2.apply:(Ljava/lang/Object;Ljava/lang/Object;)Ljava/lang/Object;
      39: areturn

  public static final scala.Tuple2 $anonfun$disassoc$1(java.lang.Object, java.lang.Object);
    Code:
       0: new           #210                // class scala/Tuple2
       3: dup
       4: aload_0
       5: aload_1
       6: invokespecial #213                // Method scala/Tuple2."<init>":(Ljava/lang/Object;Ljava/lang/Object;)V
       9: areturn

  public static final java.lang.Object $anonfun$disassoc$2(scalaz.Day, java.lang.Object, scala.Tuple2);
    Code:
       0: aload_0
       1: invokeinterface #146,  1          // InterfaceMethod scalaz/Day.xya:()Lscala/Function2;
       6: aload_0
       7: invokeinterface #120,  1          // InterfaceMethod scalaz/Day.fx:()Ljava/lang/Object;
      12: checkcast     #93                 // class scalaz/Day
      15: invokeinterface #146,  1          // InterfaceMethod scalaz/Day.xya:()Lscala/Function2;
      20: aload_1
      21: aload_2
      22: invokevirtual #218                // Method scala/Tuple2._1:()Ljava/lang/Object;
      25: invokeinterface #205,  3          // InterfaceMethod scala/Function2.apply:(Ljava/lang/Object;Ljava/lang/Object;)Ljava/lang/Object;
      30: aload_2
      31: invokevirtual #221                // Method scala/Tuple2._2:()Ljava/lang/Object;
      34: invokeinterface #205,  3          // InterfaceMethod scala/Function2.apply:(Ljava/lang/Object;Ljava/lang/Object;)Ljava/lang/Object;
      39: areturn

  private scalaz.Day$();
    Code:
       0: aload_0
       1: invokespecial #224                // Method scalaz/DayInstances."<init>":()V
       4: return

  private static java.lang.Object $deserializeLambda$(java.lang.invoke.SerializedLambda);
    Code:
       0: aload_0
       1: invokedynamic #236,  0            // InvokeDynamic #11:lambdaDeserialize:(Ljava/lang/invoke/SerializedLambda;)Ljava/lang/Object;
       6: areturn
}
