Compiled from "Equal.scala"
public final class scalaz.Equal$$anon$4 implements scalaz.Equal<A> {
  private scalaz.syntax.EqualSyntax<A> equalSyntax;

  public <G> scalaz.Equal<G> contramap(scala.Function1<G, A>);
    Code:
       0: aload_0
       1: aload_1
       2: invokestatic  #27                 // InterfaceMethod scalaz/Equal.contramap$:(Lscalaz/Equal;Lscala/Function1;)Lscalaz/Equal;
       5: areturn

  public scalaz.Equal<A>.EqualLaw equalLaw();
    Code:
       0: aload_0
       1: invokestatic  #37                 // InterfaceMethod scalaz/Equal.equalLaw$:(Lscalaz/Equal;)Lscalaz/Equal$EqualLaw;
       4: areturn

  public scalaz.syntax.EqualSyntax<A> equalSyntax();
    Code:
       0: aload_0
       1: getfield      #41                 // Field equalSyntax:Lscalaz/syntax/EqualSyntax;
       4: areturn

  public void scalaz$Equal$_setter_$equalSyntax_$eq(scalaz.syntax.EqualSyntax<A>);
    Code:
       0: aload_0
       1: aload_1
       2: putfield      #41                 // Field equalSyntax:Lscalaz/syntax/EqualSyntax;
       5: return

  public boolean equal(A, A);
    Code:
       0: aload_1
       1: aload_2
       2: invokestatic  #55                 // Method scala/runtime/BoxesRunTime.equals:(Ljava/lang/Object;Ljava/lang/Object;)Z
       5: ifeq          10
       8: iconst_1
       9: ireturn
      10: iconst_0
      11: ireturn

  public boolean equalIsNatural();
    Code:
       0: iconst_1
       1: ireturn

  public scalaz.Equal$$anon$4();
    Code:
       0: aload_0
       1: invokespecial #62                 // Method java/lang/Object."<init>":()V
       4: aload_0
       5: invokestatic  #66                 // InterfaceMethod scalaz/Equal.$init$:(Lscalaz/Equal;)V
       8: invokestatic  #71                 // Method scala/runtime/Statics.releaseFence:()V
      11: return
}
