Compiled from "FreeAp.scala"
public abstract class scalaz.FreeApInstances1 {
  public <F> scalaz.Foldable<?> freeApFoldable(scalaz.Foldable<F>);
    Code:
       0: new           #10                 // class scalaz/FreeApInstances1$$anon$3
       3: dup
       4: aconst_null
       5: aload_1
       6: invokespecial #20                 // Method scalaz/FreeApInstances1$$anon$3."<init>":(Lscalaz/FreeApInstances1;Lscalaz/Foldable;)V
       9: areturn

  public <F> scalaz.Cobind<?> freeApCobind(scalaz.Cobind<F>);
    Code:
       0: new           #12                 // class scalaz/FreeApInstances1$$anon$4
       3: dup
       4: aconst_null
       5: aload_1
       6: invokespecial #30                 // Method scalaz/FreeApInstances1$$anon$4."<init>":(Lscalaz/FreeApInstances1;Lscalaz/Cobind;)V
       9: areturn

  public scalaz.FreeApInstances1();
    Code:
       0: aload_0
       1: invokespecial #34                 // Method java/lang/Object."<init>":()V
       4: return
}
