Compiled from "FreeT.scala"
public final class scalaz.FreeT$$anon$1 implements scalaz.Isomorphisms$IsoFunctorTemplate<?, ?> {
  private scalaz.NaturalTransformation<?, ?> to;

  private scalaz.NaturalTransformation<?, ?> from;

  public scalaz.Isomorphisms$Iso2<scalaz.NaturalTransformation, ?, ?> flip();
    Code:
       0: aload_0
       1: invokestatic  #54                 // InterfaceMethod scalaz/Isomorphisms$Iso2.flip$:(Lscalaz/Isomorphisms$Iso2;)Lscalaz/Isomorphisms$Iso2;
       4: areturn

  public <A$> scalaz.Isomorphisms$Iso<scala.Function1, scalaz.FreeT<S, ?, A$>, scalaz.Free<S, A$>> unlift(scalaz.Liskov<scalaz.NaturalTransformation<?, ?>, scalaz.NaturalTransformation<?, ?>>, scalaz.Liskov<scalaz.NaturalTransformation<?, ?>, scalaz.NaturalTransformation<?, ?>>);
    Code:
       0: aload_0
       1: aload_1
       2: aload_2
       3: invokestatic  #65                 // InterfaceMethod scalaz/Isomorphisms$Iso2.unlift$:(Lscalaz/Isomorphisms$Iso2;Lscalaz/Liskov;Lscalaz/Liskov;)Lscalaz/Isomorphisms$Iso;
       6: areturn

  public scalaz.NaturalTransformation<?, ?> $percent$tilde(scalaz.NaturalTransformation<?, ?>, scalaz.Liskov<scalaz.NaturalTransformation<?, ?>, scalaz.NaturalTransformation<?, ?>>, scalaz.Liskov<scalaz.NaturalTransformation<?, ?>, scalaz.NaturalTransformation<?, ?>>);
    Code:
       0: aload_0
       1: aload_1
       2: aload_2
       3: aload_3
       4: invokestatic  #74                 // InterfaceMethod scalaz/Isomorphisms$Iso2.$percent$tilde$:(Lscalaz/Isomorphisms$Iso2;Lscalaz/NaturalTransformation;Lscalaz/Liskov;Lscalaz/Liskov;)Lscalaz/NaturalTransformation;
       7: areturn

  public final scalaz.NaturalTransformation<?, ?> to();
    Code:
       0: aload_0
       1: getfield      #78                 // Field to:Lscalaz/NaturalTransformation;
       4: areturn

  public final scalaz.NaturalTransformation<?, ?> from();
    Code:
       0: aload_0
       1: getfield      #80                 // Field from:Lscalaz/NaturalTransformation;
       4: areturn

  public final void scalaz$Isomorphisms$IsoFunctorTemplate$_setter_$to_$eq(scalaz.NaturalTransformation<?, ?>);
    Code:
       0: aload_0
       1: aload_1
       2: putfield      #78                 // Field to:Lscalaz/NaturalTransformation;
       5: return

  public final void scalaz$Isomorphisms$IsoFunctorTemplate$_setter_$from_$eq(scalaz.NaturalTransformation<?, ?>);
    Code:
       0: aload_0
       1: aload_1
       2: putfield      #80                 // Field from:Lscalaz/NaturalTransformation;
       5: return

  public <A> scalaz.Free<S, A> to_(scalaz.FreeT<S, java.lang.Object, A>);
    Code:
       0: iconst_0
       1: istore_2
       2: aconst_null
       3: astore_3
       4: aload_1
       5: instanceof    #35                 // class scalaz/FreeT$Suspend
       8: ifeq          59
      11: iconst_1
      12: istore_2
      13: aload_1
      14: checkcast     #35                 // class scalaz/FreeT$Suspend
      17: astore_3
      18: aload_3
      19: invokevirtual #93                 // Method scalaz/FreeT$Suspend.a:()Ljava/lang/Object;
      22: checkcast     #95                 // class scalaz/$bslash$div
      25: astore        4
      27: aload         4
      29: instanceof    #97                 // class scalaz/$bslash$div$minus
      32: ifeq          59
      35: aload         4
      37: checkcast     #97                 // class scalaz/$bslash$div$minus
      40: invokevirtual #100                // Method scalaz/$bslash$div$minus.b:()Ljava/lang/Object;
      43: astore        5
      45: getstatic     #106                // Field scalaz/Free$.MODULE$:Lscalaz/Free$;
      48: pop
      49: new           #28                 // class scalaz/Free$Suspend
      52: dup
      53: aload         5
      55: invokespecial #110                // Method scalaz/Free$Suspend."<init>":(Ljava/lang/Object;)V
      58: areturn
      59: iload_2
      60: ifeq          104
      63: aload_3
      64: invokevirtual #93                 // Method scalaz/FreeT$Suspend.a:()Ljava/lang/Object;
      67: checkcast     #95                 // class scalaz/$bslash$div
      70: astore        6
      72: aload         6
      74: instanceof    #112                // class scalaz/$minus$bslash$div
      77: ifeq          104
      80: aload         6
      82: checkcast     #112                // class scalaz/$minus$bslash$div
      85: invokevirtual #113                // Method scalaz/$minus$bslash$div.a:()Ljava/lang/Object;
      88: astore        7
      90: getstatic     #106                // Field scalaz/Free$.MODULE$:Lscalaz/Free$;
      93: pop
      94: new           #25                 // class scalaz/Free$Return
      97: dup
      98: aload         7
     100: invokespecial #114                // Method scalaz/Free$Return."<init>":(Ljava/lang/Object;)V
     103: areturn
     104: aload_1
     105: instanceof    #31                 // class scalaz/FreeT$Gosub
     108: ifeq          164
     111: aload_1
     112: checkcast     #31                 // class scalaz/FreeT$Gosub
     115: astore        8
     117: aload_0
     118: aload         8
     120: invokevirtual #117                // Method scalaz/FreeT$Gosub.a:()Lscalaz/FreeT;
     123: invokevirtual #119                // Method to_:(Lscalaz/FreeT;)Lscalaz/Free;
     126: aload         8
     128: invokevirtual #122                // Method scalaz/FreeT$Gosub.f:()Lscala/Function1;
     131: aload_0
     132: invokedynamic #143,  0            // InvokeDynamic #0:apply:(Lscalaz/FreeT$$anon$1;)Lscala/Function1;
     137: invokeinterface #149,  2          // InterfaceMethod scala/Function1.andThen:(Lscala/Function1;)Lscala/Function1;
     142: astore        10
     144: dup
     145: ifnonnull     150
     148: aconst_null
     149: athrow
     150: astore        9
     152: new           #20                 // class scalaz/Free$Gosub
     155: dup
     156: aload         9
     158: aload         10
     160: invokespecial #152                // Method scalaz/Free$Gosub."<init>":(Lscalaz/Free;Lscala/Function1;)V
     163: areturn
     164: new           #154                // class scala/MatchError
     167: dup
     168: aload_1
     169: invokespecial #155                // Method scala/MatchError."<init>":(Ljava/lang/Object;)V
     172: athrow

  public <A> scalaz.FreeT<S, ?, A> from_(scalaz.Free<S, A>);
    Code:
       0: aload_1
       1: invokevirtual #168                // Method scalaz/Free.toFreeT:()Lscalaz/FreeT;
       4: areturn

  public scalaz.Isomorphisms scalaz$Isomorphisms$IsoFunctorTemplate$$$outer();
    Code:
       0: getstatic     #175                // Field scalaz/Isomorphism$.MODULE$:Lscalaz/Isomorphism$;
       3: areturn

  public scalaz.Isomorphisms scalaz$Isomorphisms$Iso2$$$outer();
    Code:
       0: getstatic     #175                // Field scalaz/Isomorphism$.MODULE$:Lscalaz/Isomorphism$;
       3: areturn

  public java.lang.Object from();
    Code:
       0: aload_0
       1: invokevirtual #178                // Method from:()Lscalaz/NaturalTransformation;
       4: areturn

  public java.lang.Object to();
    Code:
       0: aload_0
       1: invokevirtual #180                // Method to:()Lscalaz/NaturalTransformation;
       4: areturn

  public java.lang.Object from_(java.lang.Object);
    Code:
       0: aload_0
       1: aload_1
       2: checkcast     #22                 // class scalaz/Free
       5: invokevirtual #182                // Method from_:(Lscalaz/Free;)Lscalaz/FreeT;
       8: areturn

  public java.lang.Object to_(java.lang.Object);
    Code:
       0: aload_0
       1: aload_1
       2: checkcast     #33                 // class scalaz/FreeT
       5: invokevirtual #119                // Method to_:(Lscalaz/FreeT;)Lscalaz/Free;
       8: areturn

  public static final scalaz.Free $anonfun$to_$1(scalaz.FreeT$$anon$1, scalaz.FreeT);
    Code:
       0: aload_0
       1: aload_1
       2: invokevirtual #119                // Method to_:(Lscalaz/FreeT;)Lscalaz/Free;
       5: areturn

  public scalaz.FreeT$$anon$1();
    Code:
       0: aload_0
       1: invokespecial #186                // Method java/lang/Object."<init>":()V
       4: aload_0
       5: invokestatic  #190                // InterfaceMethod scalaz/Isomorphisms$IsoFunctorTemplate.$init$:(Lscalaz/Isomorphisms$IsoFunctorTemplate;)V
       8: invokestatic  #195                // Method scala/runtime/Statics.releaseFence:()V
      11: return

  private static java.lang.Object $deserializeLambda$(java.lang.invoke.SerializedLambda);
    Code:
       0: aload_0
       1: invokedynamic #207,  0            // InvokeDynamic #1:lambdaDeserialize:(Ljava/lang/invoke/SerializedLambda;)Ljava/lang/Object;
       6: areturn
}
