Compiled from "Heap.scala"
public abstract class scalaz.HeapInstances {
  private final scalaz.Foldable<scalaz.Heap> heapInstance;

  public scalaz.Foldable<scalaz.Heap> heapInstance();
    Code:
       0: aload_0
       1: getfield      #24                 // Field heapInstance:Lscalaz/Foldable;
       4: areturn

  public <A> scalaz.Monoid<scalaz.Heap<A>> heapMonoid();
    Code:
       0: new           #17                 // class scalaz/HeapInstances$$anon$4
       3: dup
       4: aconst_null
       5: invokespecial #33                 // Method scalaz/HeapInstances$$anon$4."<init>":(Lscalaz/HeapInstances;)V
       8: areturn

  public <A> scalaz.Equal<scalaz.Heap<A>> healEqual(scalaz.Equal<A>, scalaz.Foldable<scalaz.Heap>);
    Code:
       0: getstatic     #44                 // Field scalaz/Equal$.MODULE$:Lscalaz/Equal$;
       3: pop
       4: getstatic     #49                 // Field scalaz/EphemeralStream$.MODULE$:Lscalaz/EphemeralStream$;
       7: aload_1
       8: invokevirtual #53                 // Method scalaz/EphemeralStream$.ephemeralStreamEqual:(Lscalaz/Equal;)Lscalaz/Equal;
      11: aload_2
      12: invokedynamic #75,  0             // InvokeDynamic #0:apply:(Lscalaz/Foldable;)Lscala/Function1;
      17: invokeinterface #81,  2           // InterfaceMethod scalaz/Equal.contramap:(Lscala/Function1;)Lscalaz/Equal;
      22: areturn

  public static final scalaz.EphemeralStream $anonfun$healEqual$1(scalaz.Foldable, scalaz.Heap);
    Code:
       0: aload_0
       1: aload_1
       2: invokeinterface #90,  2           // InterfaceMethod scalaz/Foldable.toEphemeralStream:(Ljava/lang/Object;)Lscalaz/EphemeralStream;
       7: areturn

  public scalaz.HeapInstances();
    Code:
       0: aload_0
       1: invokespecial #94                 // Method java/lang/Object."<init>":()V
       4: aload_0
       5: new           #15                 // class scalaz/HeapInstances$$anon$3
       8: dup
       9: aconst_null
      10: invokespecial #95                 // Method scalaz/HeapInstances$$anon$3."<init>":(Lscalaz/HeapInstances;)V
      13: putfield      #24                 // Field heapInstance:Lscalaz/Foldable;
      16: return

  private static java.lang.Object $deserializeLambda$(java.lang.invoke.SerializedLambda);
    Code:
       0: aload_0
       1: invokedynamic #107,  0            // InvokeDynamic #1:lambdaDeserialize:(Ljava/lang/invoke/SerializedLambda;)Ljava/lang/Object;
       6: areturn
}
