Compiled from "ReaderWriterStateT.scala"
public interface scalaz.IndexedReaderWriterStateTFunctor<F, R, W, S1, S2> extends scalaz.Functor<?> {
  public abstract scalaz.Functor<F> F();

  public static scalaz.IndexedReaderWriterStateT map$(scalaz.IndexedReaderWriterStateTFunctor, scalaz.IndexedReaderWriterStateT, scala.Function1);
    Code:
       0: aload_0
       1: aload_1
       2: aload_2
       3: invokespecial #30                 // InterfaceMethod map:(Lscalaz/IndexedReaderWriterStateT;Lscala/Function1;)Lscalaz/IndexedReaderWriterStateT;
       6: areturn

  public default <A, B> scalaz.IndexedReaderWriterStateT<R, W, S1, S2, F, B> map(scalaz.IndexedReaderWriterStateT<R, W, S1, S2, F, A>, scala.Function1<A, B>);
    Code:
       0: aload_1
       1: aload_0
       2: invokeinterface #36,  1           // InterfaceMethod F:()Lscalaz/Functor;
       7: astore_3
       8: ifnonnull     13
      11: aconst_null
      12: athrow
      13: getstatic     #42                 // Field scalaz/IndexedReaderWriterStateT$.MODULE$:Lscalaz/IndexedReaderWriterStateT$;
      16: pop
      17: aload_1
      18: aload_3
      19: aload_2
      20: invokedynamic #66,  0             // InvokeDynamic #0:apply:(Lscalaz/IndexedReaderWriterStateT;Lscalaz/Functor;Lscala/Function1;)Lscala/Function1;
      25: astore        4
      27: new           #18                 // class scalaz/IndexedReaderWriterStateT$$anon$2
      30: dup
      31: aload         4
      33: invokespecial #70                 // Method scalaz/IndexedReaderWriterStateT$$anon$2."<init>":(Lscala/Function1;)V
      36: areturn

  public static void $init$(scalaz.IndexedReaderWriterStateTFunctor);
    Code:
       0: return

  private static java.lang.Object $deserializeLambda$(java.lang.invoke.SerializedLambda);
    Code:
       0: aload_0
       1: invokedynamic #88,  0             // InvokeDynamic #1:lambdaDeserialize:(Ljava/lang/invoke/SerializedLambda;)Ljava/lang/Object;
       6: areturn
}
