Compiled from "FingerTree.scala"
public final class scalaz.IndSeqInstances$$anon$18$$anon$19 implements scalaz.NaturalTransformation<scalaz.IndSeq, ?> {
  public <E> scalaz.NaturalTransformation<E, ?> compose(scalaz.NaturalTransformation<E, scalaz.IndSeq>);
    Code:
       0: aload_0
       1: aload_1
       2: invokestatic  #18                 // InterfaceMethod scalaz/NaturalTransformation.compose$:(Lscalaz/NaturalTransformation;Lscalaz/NaturalTransformation;)Lscalaz/NaturalTransformation;
       5: areturn

  public <H> scalaz.NaturalTransformation<scalaz.IndSeq, H> andThen(scalaz.NaturalTransformation<?, H>);
    Code:
       0: aload_0
       1: aload_1
       2: invokestatic  #26                 // InterfaceMethod scalaz/NaturalTransformation.andThen$:(Lscalaz/NaturalTransformation;Lscalaz/NaturalTransformation;)Lscalaz/NaturalTransformation;
       5: areturn

  public <H> scalaz.NaturalTransformation<?, ?> or(scalaz.NaturalTransformation<H, ?>);
    Code:
       0: aload_0
       1: aload_1
       2: invokestatic  #32                 // InterfaceMethod scalaz/NaturalTransformation.or$:(Lscalaz/NaturalTransformation;Lscalaz/NaturalTransformation;)Lscalaz/NaturalTransformation;
       5: areturn

  public <GG> scalaz.NaturalTransformation<scalaz.IndSeq, GG> widen(scalaz.LiskovF<?, GG>);
    Code:
       0: aload_0
       1: aload_1
       2: invokestatic  #40                 // InterfaceMethod scalaz/NaturalTransformation.widen$:(Lscalaz/NaturalTransformation;Lscalaz/LiskovF;)Lscalaz/NaturalTransformation;
       5: areturn

  public <FF> scalaz.NaturalTransformation<FF, ?> narrow(scalaz.LiskovF<FF, scalaz.IndSeq>);
    Code:
       0: aload_0
       1: aload_1
       2: invokestatic  #46                 // InterfaceMethod scalaz/NaturalTransformation.narrow$:(Lscalaz/NaturalTransformation;Lscalaz/LiskovF;)Lscalaz/NaturalTransformation;
       5: areturn

  public <A> scalaz.FingerTree<java.lang.Object, A> apply(scalaz.IndSeq<A>);
    Code:
       0: aload_1
       1: invokevirtual #56                 // Method scalaz/IndSeq.self:()Lscalaz/FingerTree;
       4: areturn

  public java.lang.Object apply(java.lang.Object);
    Code:
       0: aload_0
       1: aload_1
       2: checkcast     #52                 // class scalaz/IndSeq
       5: invokevirtual #61                 // Method apply:(Lscalaz/IndSeq;)Lscalaz/FingerTree;
       8: areturn

  public scalaz.IndSeqInstances$$anon$18$$anon$19(scalaz.IndSeqInstances$$anon$18);
    Code:
       0: aload_0
       1: invokespecial #68                 // Method java/lang/Object."<init>":()V
       4: return
}
