Compiled from "ISet.scala"
public class scalaz.ISet$Tip$ implements java.io.Serializable {
  public static final scalaz.ISet$Tip$ MODULE$;

  private static final scalaz.ISet$Tip<scala.runtime.Nothing$> value;

  public static {};
    Code:
       0: new           #2                  // class scalaz/ISet$Tip$
       3: dup
       4: invokespecial #23                 // Method "<init>":()V
       7: putstatic     #25                 // Field MODULE$:Lscalaz/ISet$Tip$;
      10: new           #9                  // class scalaz/ISet$Tip
      13: dup
      14: invokespecial #26                 // Method scalaz/ISet$Tip."<init>":()V
      17: putstatic     #28                 // Field value:Lscalaz/ISet$Tip;
      20: return

  public <A> scalaz.ISet<A> apply();
    Code:
       0: getstatic     #28                 // Field value:Lscalaz/ISet$Tip;
       3: areturn

  public <A> boolean unapply(scalaz.ISet$Tip<A>);
    Code:
       0: aload_1
       1: ifnonnull     6
       4: iconst_0
       5: ireturn
       6: iconst_1
       7: ireturn

  private java.lang.Object writeReplace();
    Code:
       0: new           #40                 // class scala/runtime/ModuleSerializationProxy
       3: dup
       4: ldc           #2                  // class scalaz/ISet$Tip$
       6: invokespecial #43                 // Method scala/runtime/ModuleSerializationProxy."<init>":(Ljava/lang/Class;)V
       9: areturn

  public scalaz.ISet$Tip$();
    Code:
       0: aload_0
       1: invokespecial #44                 // Method java/lang/Object."<init>":()V
       4: return
}
