Compiled from "Strong.scala"
public interface scalaz.IsomorphismStrong<F, G> extends scalaz.Strong<F>, scalaz.IsomorphismProfunctor<F, G> {
  public abstract scalaz.Strong<G> G();

  public static java.lang.Object first$(scalaz.IsomorphismStrong, java.lang.Object);
    Code:
       0: aload_0
       1: aload_1
       2: invokespecial #29                 // InterfaceMethod first:(Ljava/lang/Object;)Ljava/lang/Object;
       5: areturn

  public default <A, B, C> F first(F);
    Code:
       0: aload_0
       1: invokeinterface #36,  1           // InterfaceMethod iso:()Lscalaz/Isomorphisms$Iso3;
       6: invokeinterface #40,  1           // InterfaceMethod scalaz/Isomorphisms$Iso3.from:()Ljava/lang/Object;
      11: checkcast     #42                 // class scalaz/BiNaturalTransformation
      14: aload_0
      15: invokeinterface #44,  1           // InterfaceMethod G:()Lscalaz/Strong;
      20: aload_0
      21: invokeinterface #36,  1           // InterfaceMethod iso:()Lscalaz/Isomorphisms$Iso3;
      26: invokeinterface #47,  1           // InterfaceMethod scalaz/Isomorphisms$Iso3.to:()Ljava/lang/Object;
      31: checkcast     #42                 // class scalaz/BiNaturalTransformation
      34: aload_1
      35: invokeinterface #50,  2           // InterfaceMethod scalaz/BiNaturalTransformation.apply:(Ljava/lang/Object;)Ljava/lang/Object;
      40: invokeinterface #51,  2           // InterfaceMethod scalaz/Strong.first:(Ljava/lang/Object;)Ljava/lang/Object;
      45: invokeinterface #50,  2           // InterfaceMethod scalaz/BiNaturalTransformation.apply:(Ljava/lang/Object;)Ljava/lang/Object;
      50: areturn

  public static java.lang.Object second$(scalaz.IsomorphismStrong, java.lang.Object);
    Code:
       0: aload_0
       1: aload_1
       2: invokespecial #56                 // InterfaceMethod second:(Ljava/lang/Object;)Ljava/lang/Object;
       5: areturn

  public default <A, B, C> F second(F);
    Code:
       0: aload_0
       1: invokeinterface #36,  1           // InterfaceMethod iso:()Lscalaz/Isomorphisms$Iso3;
       6: invokeinterface #40,  1           // InterfaceMethod scalaz/Isomorphisms$Iso3.from:()Ljava/lang/Object;
      11: checkcast     #42                 // class scalaz/BiNaturalTransformation
      14: aload_0
      15: invokeinterface #44,  1           // InterfaceMethod G:()Lscalaz/Strong;
      20: aload_0
      21: invokeinterface #36,  1           // InterfaceMethod iso:()Lscalaz/Isomorphisms$Iso3;
      26: invokeinterface #47,  1           // InterfaceMethod scalaz/Isomorphisms$Iso3.to:()Ljava/lang/Object;
      31: checkcast     #42                 // class scalaz/BiNaturalTransformation
      34: aload_1
      35: invokeinterface #50,  2           // InterfaceMethod scalaz/BiNaturalTransformation.apply:(Ljava/lang/Object;)Ljava/lang/Object;
      40: invokeinterface #57,  2           // InterfaceMethod scalaz/Strong.second:(Ljava/lang/Object;)Ljava/lang/Object;
      45: invokeinterface #50,  2           // InterfaceMethod scalaz/BiNaturalTransformation.apply:(Ljava/lang/Object;)Ljava/lang/Object;
      50: areturn

  public static void $init$(scalaz.IsomorphismStrong);
    Code:
       0: return
}
