Compiled from "Monoid.scala"
public interface scalaz.IsomorphismMonoid<F, G> extends scalaz.Monoid<F>, scalaz.IsomorphismSemigroup<F, G> {
  public abstract scalaz.Monoid<G> G();

  public static java.lang.Object zero$(scalaz.IsomorphismMonoid);
    Code:
       0: aload_0
       1: invokespecial #28                 // InterfaceMethod zero:()Ljava/lang/Object;
       4: areturn

  public default F zero();
    Code:
       0: aload_0
       1: invokeinterface #34,  1           // InterfaceMethod iso:()Lscalaz/Isomorphisms$Iso;
       6: invokeinterface #37,  1           // InterfaceMethod scalaz/Isomorphisms$Iso.from:()Ljava/lang/Object;
      11: checkcast     #39                 // class scala/Function1
      14: aload_0
      15: invokeinterface #41,  1           // InterfaceMethod G:()Lscalaz/Monoid;
      20: invokeinterface #42,  1           // InterfaceMethod scalaz/Monoid.zero:()Ljava/lang/Object;
      25: invokeinterface #46,  2           // InterfaceMethod scala/Function1.apply:(Ljava/lang/Object;)Ljava/lang/Object;
      30: areturn

  public static void $init$(scalaz.IsomorphismMonoid);
    Code:
       0: return
}
