Compiled from "MonadPlus.scala"
public interface scalaz.MonadPlus$MonadPlusLaw extends scalaz.PlusEmpty<F>.EmptyLaw, scalaz.Monad<F>.MonadLaw {
  public static boolean emptyMap$(scalaz.MonadPlus$MonadPlusLaw, scala.Function1, scalaz.Equal);
    Code:
       0: aload_0
       1: aload_1
       2: aload_2
       3: invokespecial #28                 // InterfaceMethod emptyMap:(Lscala/Function1;Lscalaz/Equal;)Z
       6: ireturn

  public default <A> boolean emptyMap(scala.Function1<A, A>, scalaz.Equal<F>);
    Code:
       0: aload_2
       1: aload_0
       2: invokeinterface #36,  1           // InterfaceMethod scalaz$MonadPlus$MonadPlusLaw$$$outer:()Lscalaz/MonadPlus;
       7: aload_0
       8: invokeinterface #36,  1           // InterfaceMethod scalaz$MonadPlus$MonadPlusLaw$$$outer:()Lscalaz/MonadPlus;
      13: invokeinterface #40,  1           // InterfaceMethod scalaz/MonadPlus.empty:()Ljava/lang/Object;
      18: aload_1
      19: invokeinterface #44,  3           // InterfaceMethod scalaz/MonadPlus.map:(Ljava/lang/Object;Lscala/Function1;)Ljava/lang/Object;
      24: aload_0
      25: invokeinterface #36,  1           // InterfaceMethod scalaz$MonadPlus$MonadPlusLaw$$$outer:()Lscalaz/MonadPlus;
      30: invokeinterface #40,  1           // InterfaceMethod scalaz/MonadPlus.empty:()Ljava/lang/Object;
      35: invokeinterface #50,  3           // InterfaceMethod scalaz/Equal.equal:(Ljava/lang/Object;Ljava/lang/Object;)Z
      40: ireturn

  public static boolean leftZero$(scalaz.MonadPlus$MonadPlusLaw, scala.Function1, scalaz.Equal);
    Code:
       0: aload_0
       1: aload_1
       2: aload_2
       3: invokespecial #56                 // InterfaceMethod leftZero:(Lscala/Function1;Lscalaz/Equal;)Z
       6: ireturn

  public default <A> boolean leftZero(scala.Function1<A, F>, scalaz.Equal<F>);
    Code:
       0: aload_2
       1: aload_0
       2: invokeinterface #36,  1           // InterfaceMethod scalaz$MonadPlus$MonadPlusLaw$$$outer:()Lscalaz/MonadPlus;
       7: aload_0
       8: invokeinterface #36,  1           // InterfaceMethod scalaz$MonadPlus$MonadPlusLaw$$$outer:()Lscalaz/MonadPlus;
      13: invokeinterface #40,  1           // InterfaceMethod scalaz/MonadPlus.empty:()Ljava/lang/Object;
      18: aload_1
      19: invokeinterface #60,  3           // InterfaceMethod scalaz/MonadPlus.bind:(Ljava/lang/Object;Lscala/Function1;)Ljava/lang/Object;
      24: aload_0
      25: invokeinterface #36,  1           // InterfaceMethod scalaz$MonadPlus$MonadPlusLaw$$$outer:()Lscalaz/MonadPlus;
      30: invokeinterface #40,  1           // InterfaceMethod scalaz/MonadPlus.empty:()Ljava/lang/Object;
      35: invokeinterface #50,  3           // InterfaceMethod scalaz/Equal.equal:(Ljava/lang/Object;Ljava/lang/Object;)Z
      40: ireturn

  public abstract scalaz.MonadPlus scalaz$MonadPlus$MonadPlusLaw$$$outer();

  public static void $init$(scalaz.MonadPlus<F>.MonadPlusLaw);
    Code:
       0: return
}
