Compiled from "NullArgument.scala"
public final class scalaz.NullArgument<A, B> {
  private final scala.Function1<scala.Option<A>, B> _apply;

  public static <A, B> scalaz.NullArgument<A, B> always(scala.Function0<B>);
    Code:
       0: getstatic     #35                 // Field scalaz/NullArgument$.MODULE$:Lscalaz/NullArgument$;
       3: pop
       4: aload_0
       5: invokedynamic #57,  0             // InvokeDynamic #0:apply:(Lscala/Function0;)Lscala/Function1;
      10: astore_1
      11: new           #2                  // class scalaz/NullArgument
      14: dup
      15: aload_1
      16: invokespecial #61                 // Method "<init>":(Lscala/Function1;)V
      19: areturn

  public static <X> scalaz.Contravariant<?> nullArgumentContravariant();
    Code:
       0: getstatic     #35                 // Field scalaz/NullArgument$.MODULE$:Lscalaz/NullArgument$;
       3: pop
       4: new           #20                 // class scalaz/NullArgumentInstances$$anon$6
       7: dup
       8: aconst_null
       9: invokespecial #69                 // Method scalaz/NullArgumentInstances$$anon$6."<init>":(Lscalaz/NullArgumentInstances;)V
      12: areturn

  public static <X> scalaz.Monad<?> nullArgumentMonad();
    Code:
       0: getstatic     #35                 // Field scalaz/NullArgument$.MODULE$:Lscalaz/NullArgument$;
       3: pop
       4: new           #18                 // class scalaz/NullArgumentInstances$$anon$5
       7: dup
       8: aconst_null
       9: invokespecial #73                 // Method scalaz/NullArgumentInstances$$anon$5."<init>":(Lscalaz/NullArgumentInstances;)V
      12: areturn

  public static scalaz.Split<scalaz.NullArgument> nullArgumentCategory();
    Code:
       0: getstatic     #35                 // Field scalaz/NullArgument$.MODULE$:Lscalaz/NullArgument$;
       3: invokevirtual #78                 // Method scalaz/NullArgument$.nullArgumentCategory:()Lscalaz/Split;
       6: areturn

  public static <A, B> scalaz.Monoid<scalaz.NullArgument<A, B>> nullArgumentMonoid(scalaz.Monoid<B>);
    Code:
       0: getstatic     #35                 // Field scalaz/NullArgument$.MODULE$:Lscalaz/NullArgument$;
       3: pop
       4: new           #16                 // class scalaz/NullArgumentInstances$$anon$3
       7: dup
       8: aconst_null
       9: aload_0
      10: invokespecial #85                 // Method scalaz/NullArgumentInstances$$anon$3."<init>":(Lscalaz/NullArgumentInstances;Lscalaz/Monoid;)V
      13: areturn

  public static scalaz.Profunctor<scalaz.NullArgument> nullArgumentProfunctor();
    Code:
       0: getstatic     #35                 // Field scalaz/NullArgument$.MODULE$:Lscalaz/NullArgument$;
       3: invokevirtual #91                 // Method scalaz/NullArgument$.nullArgumentProfunctor:()Lscalaz/Profunctor;
       6: areturn

  public static <A, B> scalaz.Semigroup<scalaz.NullArgument<A, B>> nullArgumentSemigroup(scalaz.Semigroup<B>);
    Code:
       0: getstatic     #35                 // Field scalaz/NullArgument$.MODULE$:Lscalaz/NullArgument$;
       3: pop
       4: new           #22                 // class scalaz/NullArgumentInstances0$$anon$1
       7: dup
       8: aconst_null
       9: aload_0
      10: invokespecial #97                 // Method scalaz/NullArgumentInstances0$$anon$1."<init>":(Lscalaz/NullArgumentInstances0;Lscalaz/Semigroup;)V
      13: areturn

  public B apply(scala.Option<A>);
    Code:
       0: aload_0
       1: getfield      #102                // Field _apply:Lscala/Function1;
       4: aload_1
       5: invokeinterface #106,  2          // InterfaceMethod scala/Function1.apply:(Ljava/lang/Object;)Ljava/lang/Object;
      10: areturn

  public <C, D> scalaz.NullArgument<C, D> dimap(scala.Function1<C, A>, scala.Function1<B, D>);
    Code:
       0: getstatic     #35                 // Field scalaz/NullArgument$.MODULE$:Lscalaz/NullArgument$;
       3: pop
       4: aload_0
       5: aload_2
       6: aload_1
       7: invokedynamic #122,  0            // InvokeDynamic #1:apply:(Lscalaz/NullArgument;Lscala/Function1;Lscala/Function1;)Lscala/Function1;
      12: astore_3
      13: new           #2                  // class scalaz/NullArgument
      16: dup
      17: aload_3
      18: invokespecial #61                 // Method "<init>":(Lscala/Function1;)V
      21: areturn

  public <C> scalaz.NullArgument<A, C> map(scala.Function1<B, C>);
    Code:
       0: getstatic     #35                 // Field scalaz/NullArgument$.MODULE$:Lscalaz/NullArgument$;
       3: pop
       4: aload_0
       5: getfield      #102                // Field _apply:Lscala/Function1;
       8: aload_1
       9: invokeinterface #130,  2          // InterfaceMethod scala/Function1.andThen:(Lscala/Function1;)Lscala/Function1;
      14: astore_2
      15: new           #2                  // class scalaz/NullArgument
      18: dup
      19: aload_2
      20: invokespecial #61                 // Method "<init>":(Lscala/Function1;)V
      23: areturn

  public <C> scalaz.NullArgument<C, B> contramap(scala.Function1<C, A>);
    Code:
       0: getstatic     #35                 // Field scalaz/NullArgument$.MODULE$:Lscalaz/NullArgument$;
       3: pop
       4: aload_0
       5: aload_1
       6: invokedynamic #140,  0            // InvokeDynamic #2:apply:(Lscalaz/NullArgument;Lscala/Function1;)Lscala/Function1;
      11: astore_2
      12: new           #2                  // class scalaz/NullArgument
      15: dup
      16: aload_2
      17: invokespecial #61                 // Method "<init>":(Lscala/Function1;)V
      20: areturn

  public <C> scalaz.NullArgument<A, C> flatMap(scala.Function1<B, scalaz.NullArgument<A, C>>);
    Code:
       0: getstatic     #35                 // Field scalaz/NullArgument$.MODULE$:Lscalaz/NullArgument$;
       3: pop
       4: aload_0
       5: aload_1
       6: invokedynamic #147,  0            // InvokeDynamic #3:apply:(Lscalaz/NullArgument;Lscala/Function1;)Lscala/Function1;
      11: astore_2
      12: new           #2                  // class scalaz/NullArgument
      15: dup
      16: aload_2
      17: invokespecial #61                 // Method "<init>":(Lscala/Function1;)V
      20: areturn

  public <C> scalaz.NullArgument<A, C> ap(scalaz.NullArgument<A, scala.Function1<B, C>>);
    Code:
       0: aload_1
       1: aload_0
       2: invokedynamic #159,  0            // InvokeDynamic #4:apply:(Lscalaz/NullArgument;)Lscala/Function1;
       7: astore_2
       8: ifnonnull     13
      11: aconst_null
      12: athrow
      13: getstatic     #35                 // Field scalaz/NullArgument$.MODULE$:Lscalaz/NullArgument$;
      16: pop
      17: aload_1
      18: aload_2
      19: invokedynamic #147,  0            // InvokeDynamic #3:apply:(Lscalaz/NullArgument;Lscala/Function1;)Lscala/Function1;
      24: astore_3
      25: new           #2                  // class scalaz/NullArgument
      28: dup
      29: aload_3
      30: invokespecial #61                 // Method "<init>":(Lscala/Function1;)V
      33: areturn

  public <C> scalaz.NullArgument<A, scala.Tuple2<B, C>> zip(scalaz.NullArgument<A, C>);
    Code:
       0: aload_1
       1: invokedynamic #172,  0            // InvokeDynamic #5:apply:(Lscalaz/NullArgument;)Lscala/Function1;
       6: astore_2
       7: getstatic     #35                 // Field scalaz/NullArgument$.MODULE$:Lscalaz/NullArgument$;
      10: pop
      11: aload_0
      12: aload_2
      13: invokedynamic #147,  0            // InvokeDynamic #3:apply:(Lscalaz/NullArgument;Lscala/Function1;)Lscala/Function1;
      18: astore_3
      19: new           #2                  // class scalaz/NullArgument
      22: dup
      23: aload_3
      24: invokespecial #61                 // Method "<init>":(Lscala/Function1;)V
      27: areturn

  public <C, D> scalaz.NullArgument<scala.Tuple2<A, C>, scala.Tuple2<B, D>> $times$times$times(scalaz.NullArgument<C, D>);
    Code:
       0: getstatic     #35                 // Field scalaz/NullArgument$.MODULE$:Lscalaz/NullArgument$;
       3: pop
       4: aload_0
       5: aload_1
       6: invokedynamic #184,  0            // InvokeDynamic #6:apply:(Lscalaz/NullArgument;Lscalaz/NullArgument;)Lscala/Function1;
      11: astore_2
      12: new           #2                  // class scalaz/NullArgument
      15: dup
      16: aload_2
      17: invokespecial #61                 // Method "<init>":(Lscala/Function1;)V
      20: areturn

  public <C, D> scalaz.NullArgument<scalaz.$bslash$div<A, C>, scalaz.$bslash$div<B, D>> $plus$plus$plus(scalaz.NullArgument<C, D>);
    Code:
       0: aload_0
       1: invokevirtual #190                // Method left:()Lscalaz/NullArgument;
       4: aload_1
       5: invokevirtual #193                // Method right:()Lscalaz/NullArgument;
       8: invokevirtual #196                // Method compose:(Lscalaz/NullArgument;)Lscalaz/NullArgument;
      11: areturn

  public <C> scalaz.NullArgument<scalaz.$bslash$div<A, C>, scalaz.$bslash$div<B, C>> left();
    Code:
       0: getstatic     #35                 // Field scalaz/NullArgument$.MODULE$:Lscalaz/NullArgument$;
       3: pop
       4: aload_0
       5: invokedynamic #205,  0            // InvokeDynamic #7:apply:(Lscalaz/NullArgument;)Lscala/Function1;
      10: astore_1
      11: new           #2                  // class scalaz/NullArgument
      14: dup
      15: aload_1
      16: invokespecial #61                 // Method "<init>":(Lscala/Function1;)V
      19: areturn

  public <C> scalaz.NullArgument<scalaz.$bslash$div<C, A>, scalaz.$bslash$div<C, B>> right();
    Code:
       0: getstatic     #35                 // Field scalaz/NullArgument$.MODULE$:Lscalaz/NullArgument$;
       3: pop
       4: aload_0
       5: invokedynamic #211,  0            // InvokeDynamic #8:apply:(Lscalaz/NullArgument;)Lscala/Function1;
      10: astore_1
      11: new           #2                  // class scalaz/NullArgument
      14: dup
      15: aload_1
      16: invokespecial #61                 // Method "<init>":(Lscala/Function1;)V
      19: areturn

  public <C> scalaz.NullArgument<C, B> compose(scalaz.NullArgument<C, A>);
    Code:
       0: getstatic     #35                 // Field scalaz/NullArgument$.MODULE$:Lscalaz/NullArgument$;
       3: pop
       4: aload_0
       5: aload_1
       6: invokedynamic #218,  0            // InvokeDynamic #9:apply:(Lscalaz/NullArgument;Lscalaz/NullArgument;)Lscala/Function1;
      11: astore_2
      12: new           #2                  // class scalaz/NullArgument
      15: dup
      16: aload_2
      17: invokespecial #61                 // Method "<init>":(Lscala/Function1;)V
      20: areturn

  public <C> scalaz.NullArgument<A, C> andThen(scalaz.NullArgument<B, C>);
    Code:
       0: aload_1
       1: aload_0
       2: invokevirtual #196                // Method compose:(Lscalaz/NullArgument;)Lscalaz/NullArgument;
       5: areturn

  public scalaz.NullArgument<A, B> $bar$plus$bar(scalaz.NullArgument<A, B>, scalaz.Semigroup<B>);
    Code:
       0: aload_1
       1: aload_2
       2: invokedynamic #231,  0            // InvokeDynamic #10:apply:(Lscalaz/NullArgument;Lscalaz/Semigroup;)Lscala/Function1;
       7: astore_3
       8: getstatic     #35                 // Field scalaz/NullArgument$.MODULE$:Lscalaz/NullArgument$;
      11: pop
      12: aload_0
      13: aload_3
      14: invokedynamic #147,  0            // InvokeDynamic #3:apply:(Lscalaz/NullArgument;Lscala/Function1;)Lscala/Function1;
      19: astore        4
      21: new           #2                  // class scalaz/NullArgument
      24: dup
      25: aload         4
      27: invokespecial #61                 // Method "<init>":(Lscala/Function1;)V
      30: areturn

  public scalaz.Cokleisli<scala.Option, A, B> cokleisli();
    Code:
       0: new           #236                // class scalaz/Cokleisli
       3: dup
       4: aload_0
       5: getfield      #102                // Field _apply:Lscala/Function1;
       8: invokespecial #237                // Method scalaz/Cokleisli."<init>":(Lscala/Function1;)V
      11: areturn

  public <F> F on(scalaz.OptionT<F, A>, scalaz.Functor<F>);
    Code:
       0: aload_2
       1: aload_1
       2: invokevirtual #248                // Method scalaz/OptionT.run:()Ljava/lang/Object;
       5: aload_0
       6: getfield      #102                // Field _apply:Lscala/Function1;
       9: invokeinterface #253,  3          // InterfaceMethod scalaz/Functor.map:(Ljava/lang/Object;Lscala/Function1;)Ljava/lang/Object;
      14: areturn

  public scala.Function1<A, B> lower();
    Code:
       0: aload_0
       1: invokedynamic #264,  0            // InvokeDynamic #11:apply:(Lscalaz/NullArgument;)Lscala/Function1;
       6: areturn

  public B never();
    Code:
       0: aload_0
       1: getstatic     #271                // Field scala/None$.MODULE$:Lscala/None$;
       4: invokevirtual #273                // Method apply:(Lscala/Option;)Ljava/lang/Object;
       7: areturn

  public B zero(scalaz.Monoid<A>);
    Code:
       0: aload_0
       1: invokevirtual #279                // Method lower:()Lscala/Function1;
       4: aload_1
       5: invokeinterface #283,  1          // InterfaceMethod scalaz/Monoid.zero:()Ljava/lang/Object;
      10: invokeinterface #106,  2          // InterfaceMethod scala/Function1.apply:(Ljava/lang/Object;)Ljava/lang/Object;
      15: areturn

  public scala.Tuple2<scala.Function1<A, B>, B> pair();
    Code:
       0: new           #288                // class scala/Tuple2
       3: dup
       4: aload_0
       5: invokedynamic #293,  0            // InvokeDynamic #12:apply:(Lscalaz/NullArgument;)Lscala/Function1;
      10: aload_0
      11: getstatic     #271                // Field scala/None$.MODULE$:Lscala/None$;
      14: invokevirtual #273                // Method apply:(Lscala/Option;)Ljava/lang/Object;
      17: invokespecial #296                // Method scala/Tuple2."<init>":(Ljava/lang/Object;Ljava/lang/Object;)V
      20: areturn

  public static final java.lang.Object $anonfun$dimap$1(scalaz.NullArgument, scala.Function1, scala.Function1, scala.Option);
    Code:
       0: aload_1
       1: aload_0
       2: getfield      #102                // Field _apply:Lscala/Function1;
       5: aload_3
       6: aload_2
       7: invokevirtual #305                // Method scala/Option.map:(Lscala/Function1;)Lscala/Option;
      10: invokeinterface #106,  2          // InterfaceMethod scala/Function1.apply:(Ljava/lang/Object;)Ljava/lang/Object;
      15: invokeinterface #106,  2          // InterfaceMethod scala/Function1.apply:(Ljava/lang/Object;)Ljava/lang/Object;
      20: areturn

  public static final java.lang.Object $anonfun$contramap$1(scalaz.NullArgument, scala.Function1, scala.Option);
    Code:
       0: aload_0
       1: aload_2
       2: aload_1
       3: invokevirtual #305                // Method scala/Option.map:(Lscala/Function1;)Lscala/Option;
       6: invokevirtual #273                // Method apply:(Lscala/Option;)Ljava/lang/Object;
       9: areturn

  public static final java.lang.Object $anonfun$flatMap$1(scalaz.NullArgument, scala.Function1, scala.Option);
    Code:
       0: aload_1
       1: aload_0
       2: aload_2
       3: invokevirtual #273                // Method apply:(Lscala/Option;)Ljava/lang/Object;
       6: invokeinterface #106,  2          // InterfaceMethod scala/Function1.apply:(Ljava/lang/Object;)Ljava/lang/Object;
      11: checkcast     #2                  // class scalaz/NullArgument
      14: aload_2
      15: invokevirtual #273                // Method apply:(Lscala/Option;)Ljava/lang/Object;
      18: areturn

  public static final java.lang.Object $anonfun$ap$2(scala.Function1, java.lang.Object);
    Code:
       0: aload_0
       1: aload_1
       2: invokeinterface #106,  2          // InterfaceMethod scala/Function1.apply:(Ljava/lang/Object;)Ljava/lang/Object;
       7: areturn

  public static final scalaz.NullArgument $anonfun$ap$1(scalaz.NullArgument, scala.Function1);
    Code:
       0: aload_1
       1: invokedynamic #318,  0            // InvokeDynamic #13:apply:(Lscala/Function1;)Lscala/Function1;
       6: astore_2
       7: getstatic     #35                 // Field scalaz/NullArgument$.MODULE$:Lscalaz/NullArgument$;
      10: pop
      11: aload_0
      12: getfield      #102                // Field _apply:Lscala/Function1;
      15: aload_2
      16: invokeinterface #130,  2          // InterfaceMethod scala/Function1.andThen:(Lscala/Function1;)Lscala/Function1;
      21: astore_3
      22: new           #2                  // class scalaz/NullArgument
      25: dup
      26: aload_3
      27: invokespecial #61                 // Method "<init>":(Lscala/Function1;)V
      30: areturn

  public static final scala.Tuple2 $anonfun$zip$2(java.lang.Object, java.lang.Object);
    Code:
       0: new           #288                // class scala/Tuple2
       3: dup
       4: aload_0
       5: aload_1
       6: invokespecial #296                // Method scala/Tuple2."<init>":(Ljava/lang/Object;Ljava/lang/Object;)V
       9: areturn

  public static final scalaz.NullArgument $anonfun$zip$1(scalaz.NullArgument, java.lang.Object);
    Code:
       0: aload_1
       1: invokedynamic #332,  0            // InvokeDynamic #14:apply:(Ljava/lang/Object;)Lscala/Function1;
       6: astore_2
       7: getstatic     #35                 // Field scalaz/NullArgument$.MODULE$:Lscalaz/NullArgument$;
      10: pop
      11: aload_0
      12: getfield      #102                // Field _apply:Lscala/Function1;
      15: aload_2
      16: invokeinterface #130,  2          // InterfaceMethod scala/Function1.andThen:(Lscala/Function1;)Lscala/Function1;
      21: astore_3
      22: new           #2                  // class scalaz/NullArgument
      25: dup
      26: aload_3
      27: invokespecial #61                 // Method "<init>":(Lscala/Function1;)V
      30: areturn

  public static final scala.Tuple2 $anonfun$$times$times$times$1(scalaz.NullArgument, scalaz.NullArgument, scala.Option);
    Code:
       0: getstatic     #271                // Field scala/None$.MODULE$:Lscala/None$;
       3: aload_2
       4: invokevirtual #338                // Method java/lang/Object.equals:(Ljava/lang/Object;)Z
       7: ifeq          32
      10: new           #288                // class scala/Tuple2
      13: dup
      14: aload_0
      15: getstatic     #271                // Field scala/None$.MODULE$:Lscala/None$;
      18: invokevirtual #273                // Method apply:(Lscala/Option;)Ljava/lang/Object;
      21: aload_1
      22: getstatic     #271                // Field scala/None$.MODULE$:Lscala/None$;
      25: invokevirtual #273                // Method apply:(Lscala/Option;)Ljava/lang/Object;
      28: invokespecial #296                // Method scala/Tuple2."<init>":(Ljava/lang/Object;Ljava/lang/Object;)V
      31: areturn
      32: aload_2
      33: instanceof    #340                // class scala/Some
      36: ifeq          100
      39: aload_2
      40: checkcast     #340                // class scala/Some
      43: invokevirtual #343                // Method scala/Some.value:()Ljava/lang/Object;
      46: checkcast     #288                // class scala/Tuple2
      49: astore_3
      50: aload_3
      51: ifnull        100
      54: aload_3
      55: invokevirtual #346                // Method scala/Tuple2._1:()Ljava/lang/Object;
      58: astore        4
      60: aload_3
      61: invokevirtual #349                // Method scala/Tuple2._2:()Ljava/lang/Object;
      64: astore        5
      66: new           #288                // class scala/Tuple2
      69: dup
      70: aload_0
      71: new           #340                // class scala/Some
      74: dup
      75: aload         4
      77: invokespecial #352                // Method scala/Some."<init>":(Ljava/lang/Object;)V
      80: invokevirtual #273                // Method apply:(Lscala/Option;)Ljava/lang/Object;
      83: aload_1
      84: new           #340                // class scala/Some
      87: dup
      88: aload         5
      90: invokespecial #352                // Method scala/Some."<init>":(Ljava/lang/Object;)V
      93: invokevirtual #273                // Method apply:(Lscala/Option;)Ljava/lang/Object;
      96: invokespecial #296                // Method scala/Tuple2."<init>":(Ljava/lang/Object;Ljava/lang/Object;)V
      99: areturn
     100: new           #354                // class scala/MatchError
     103: dup
     104: aload_2
     105: invokespecial #355                // Method scala/MatchError."<init>":(Ljava/lang/Object;)V
     108: athrow

  public static final scalaz.$bslash$div $anonfun$left$1(scalaz.NullArgument, scala.Option);
    Code:
       0: iconst_0
       1: istore_2
       2: aconst_null
       3: astore_3
       4: getstatic     #271                // Field scala/None$.MODULE$:Lscala/None$;
       7: aload_1
       8: invokevirtual #338                // Method java/lang/Object.equals:(Ljava/lang/Object;)Z
      11: ifeq          37
      14: getstatic     #360                // Field scalaz/$minus$bslash$div$.MODULE$:Lscalaz/$minus$bslash$div$;
      17: pop
      18: aload_0
      19: getstatic     #271                // Field scala/None$.MODULE$:Lscala/None$;
      22: invokevirtual #273                // Method apply:(Lscala/Option;)Ljava/lang/Object;
      25: astore        8
      27: new           #362                // class scalaz/$minus$bslash$div
      30: dup
      31: aload         8
      33: invokespecial #363                // Method scalaz/$minus$bslash$div."<init>":(Ljava/lang/Object;)V
      36: areturn
      37: aload_1
      38: instanceof    #340                // class scala/Some
      41: ifeq          107
      44: iconst_1
      45: istore_2
      46: aload_1
      47: checkcast     #340                // class scala/Some
      50: astore_3
      51: aload_3
      52: invokevirtual #343                // Method scala/Some.value:()Ljava/lang/Object;
      55: checkcast     #365                // class scalaz/$bslash$div
      58: astore        4
      60: aload         4
      62: instanceof    #362                // class scalaz/$minus$bslash$div
      65: ifeq          107
      68: aload         4
      70: checkcast     #362                // class scalaz/$minus$bslash$div
      73: invokevirtual #367                // Method scalaz/$minus$bslash$div.a:()Ljava/lang/Object;
      76: astore        5
      78: getstatic     #360                // Field scalaz/$minus$bslash$div$.MODULE$:Lscalaz/$minus$bslash$div$;
      81: pop
      82: aload_0
      83: new           #340                // class scala/Some
      86: dup
      87: aload         5
      89: invokespecial #352                // Method scala/Some."<init>":(Ljava/lang/Object;)V
      92: invokevirtual #273                // Method apply:(Lscala/Option;)Ljava/lang/Object;
      95: astore        9
      97: new           #362                // class scalaz/$minus$bslash$div
     100: dup
     101: aload         9
     103: invokespecial #363                // Method scalaz/$minus$bslash$div."<init>":(Ljava/lang/Object;)V
     106: areturn
     107: iload_2
     108: ifeq          145
     111: aload_3
     112: invokevirtual #343                // Method scala/Some.value:()Ljava/lang/Object;
     115: checkcast     #365                // class scalaz/$bslash$div
     118: astore        6
     120: aload         6
     122: instanceof    #369                // class scalaz/$bslash$div$minus
     125: ifeq          145
     128: aload         6
     130: checkcast     #369                // class scalaz/$bslash$div$minus
     133: astore        7
     135: aload         7
     137: ifnonnull     142
     140: aconst_null
     141: athrow
     142: aload         7
     144: areturn
     145: new           #354                // class scala/MatchError
     148: dup
     149: aload_1
     150: invokespecial #355                // Method scala/MatchError."<init>":(Ljava/lang/Object;)V
     153: athrow

  public static final scalaz.$bslash$div $anonfun$right$1(scalaz.NullArgument, scala.Option);
    Code:
       0: iconst_0
       1: istore_2
       2: aconst_null
       3: astore_3
       4: getstatic     #271                // Field scala/None$.MODULE$:Lscala/None$;
       7: aload_1
       8: invokevirtual #338                // Method java/lang/Object.equals:(Ljava/lang/Object;)Z
      11: ifeq          37
      14: getstatic     #376                // Field scalaz/$bslash$div$minus$.MODULE$:Lscalaz/$bslash$div$minus$;
      17: pop
      18: aload_0
      19: getstatic     #271                // Field scala/None$.MODULE$:Lscala/None$;
      22: invokevirtual #273                // Method apply:(Lscala/Option;)Ljava/lang/Object;
      25: astore        8
      27: new           #369                // class scalaz/$bslash$div$minus
      30: dup
      31: aload         8
      33: invokespecial #377                // Method scalaz/$bslash$div$minus."<init>":(Ljava/lang/Object;)V
      36: areturn
      37: aload_1
      38: instanceof    #340                // class scala/Some
      41: ifeq          107
      44: iconst_1
      45: istore_2
      46: aload_1
      47: checkcast     #340                // class scala/Some
      50: astore_3
      51: aload_3
      52: invokevirtual #343                // Method scala/Some.value:()Ljava/lang/Object;
      55: checkcast     #365                // class scalaz/$bslash$div
      58: astore        4
      60: aload         4
      62: instanceof    #369                // class scalaz/$bslash$div$minus
      65: ifeq          107
      68: aload         4
      70: checkcast     #369                // class scalaz/$bslash$div$minus
      73: invokevirtual #379                // Method scalaz/$bslash$div$minus.b:()Ljava/lang/Object;
      76: astore        5
      78: getstatic     #376                // Field scalaz/$bslash$div$minus$.MODULE$:Lscalaz/$bslash$div$minus$;
      81: pop
      82: aload_0
      83: new           #340                // class scala/Some
      86: dup
      87: aload         5
      89: invokespecial #352                // Method scala/Some."<init>":(Ljava/lang/Object;)V
      92: invokevirtual #273                // Method apply:(Lscala/Option;)Ljava/lang/Object;
      95: astore        9
      97: new           #369                // class scalaz/$bslash$div$minus
     100: dup
     101: aload         9
     103: invokespecial #377                // Method scalaz/$bslash$div$minus."<init>":(Ljava/lang/Object;)V
     106: areturn
     107: iload_2
     108: ifeq          145
     111: aload_3
     112: invokevirtual #343                // Method scala/Some.value:()Ljava/lang/Object;
     115: checkcast     #365                // class scalaz/$bslash$div
     118: astore        6
     120: aload         6
     122: instanceof    #362                // class scalaz/$minus$bslash$div
     125: ifeq          145
     128: aload         6
     130: checkcast     #362                // class scalaz/$minus$bslash$div
     133: astore        7
     135: aload         7
     137: ifnonnull     142
     140: aconst_null
     141: athrow
     142: aload         7
     144: areturn
     145: new           #354                // class scala/MatchError
     148: dup
     149: aload_1
     150: invokespecial #355                // Method scala/MatchError."<init>":(Ljava/lang/Object;)V
     153: athrow

  public static final java.lang.Object $anonfun$compose$1(scalaz.NullArgument, scalaz.NullArgument, scala.Option);
    Code:
       0: getstatic     #271                // Field scala/None$.MODULE$:Lscala/None$;
       3: aload_2
       4: invokevirtual #338                // Method java/lang/Object.equals:(Ljava/lang/Object;)Z
       7: ifeq          18
      10: aload_0
      11: getstatic     #271                // Field scala/None$.MODULE$:Lscala/None$;
      14: invokevirtual #273                // Method apply:(Lscala/Option;)Ljava/lang/Object;
      17: areturn
      18: aload_2
      19: instanceof    #340                // class scala/Some
      22: ifeq          47
      25: aload_2
      26: checkcast     #340                // class scala/Some
      29: astore_3
      30: aload_0
      31: new           #340                // class scala/Some
      34: dup
      35: aload_1
      36: aload_3
      37: invokevirtual #273                // Method apply:(Lscala/Option;)Ljava/lang/Object;
      40: invokespecial #352                // Method scala/Some."<init>":(Ljava/lang/Object;)V
      43: invokevirtual #273                // Method apply:(Lscala/Option;)Ljava/lang/Object;
      46: areturn
      47: new           #354                // class scala/MatchError
      50: dup
      51: aload_2
      52: invokespecial #355                // Method scala/MatchError."<init>":(Ljava/lang/Object;)V
      55: athrow

  public static final java.lang.Object $anonfun$$bar$plus$bar$3(java.lang.Object);
    Code:
       0: aload_0
       1: areturn

  public static final java.lang.Object $anonfun$$bar$plus$bar$2(scalaz.Semigroup, java.lang.Object, java.lang.Object);
    Code:
       0: aload_0
       1: aload_1
       2: aload_2
       3: invokedynamic #395,  0            // InvokeDynamic #15:apply:(Ljava/lang/Object;)Lscala/Function0;
       8: invokeinterface #401,  3          // InterfaceMethod scalaz/Semigroup.append:(Ljava/lang/Object;Lscala/Function0;)Ljava/lang/Object;
      13: areturn

  public static final scalaz.NullArgument $anonfun$$bar$plus$bar$1(scalaz.NullArgument, scalaz.Semigroup, java.lang.Object);
    Code:
       0: aload_1
       1: aload_2
       2: invokedynamic #409,  0            // InvokeDynamic #16:apply:(Lscalaz/Semigroup;Ljava/lang/Object;)Lscala/Function1;
       7: astore_3
       8: getstatic     #35                 // Field scalaz/NullArgument$.MODULE$:Lscalaz/NullArgument$;
      11: pop
      12: aload_0
      13: getfield      #102                // Field _apply:Lscala/Function1;
      16: aload_3
      17: invokeinterface #130,  2          // InterfaceMethod scala/Function1.andThen:(Lscala/Function1;)Lscala/Function1;
      22: astore        4
      24: new           #2                  // class scalaz/NullArgument
      27: dup
      28: aload         4
      30: invokespecial #61                 // Method "<init>":(Lscala/Function1;)V
      33: areturn

  public static final java.lang.Object $anonfun$lower$1(scalaz.NullArgument, java.lang.Object);
    Code:
       0: aload_0
       1: new           #340                // class scala/Some
       4: dup
       5: aload_1
       6: invokespecial #352                // Method scala/Some."<init>":(Ljava/lang/Object;)V
       9: invokevirtual #273                // Method apply:(Lscala/Option;)Ljava/lang/Object;
      12: areturn

  public static final java.lang.Object $anonfun$pair$1(scalaz.NullArgument, java.lang.Object);
    Code:
       0: aload_0
       1: new           #340                // class scala/Some
       4: dup
       5: aload_1
       6: invokespecial #352                // Method scala/Some."<init>":(Ljava/lang/Object;)V
       9: invokevirtual #273                // Method apply:(Lscala/Option;)Ljava/lang/Object;
      12: areturn

  public scalaz.NullArgument(scala.Function1<scala.Option<A>, B>);
    Code:
       0: aload_0
       1: aload_1
       2: putfield      #102                // Field _apply:Lscala/Function1;
       5: aload_0
       6: invokespecial #413                // Method java/lang/Object."<init>":()V
       9: return

  private static java.lang.Object $deserializeLambda$(java.lang.invoke.SerializedLambda);
    Code:
       0: aload_0
       1: invokedynamic #425,  0            // InvokeDynamic #17:lambdaDeserialize:(Ljava/lang/invoke/SerializedLambda;)Ljava/lang/Object;
       6: areturn
}
