Compiled from "PrioritySearchQueue.scala"
public class scalaz.PrioritySearchQueue<A, P, K> {
  private final scalaz.FingerTree<scalaz.PrioritySearchQueue$Summary<A, P, K>, A> scalaz$PrioritySearchQueue$$tree;

  private final scala.Function1<A, P> priorityOf;

  private final scala.Function1<A, K> keyOf;

  public static <A, P, K> scalaz.Show<scalaz.PrioritySearchQueue<A, P, K>> showInstance(scalaz.Show<A>);
    Code:
       0: getstatic     #62                 // Field scalaz/PrioritySearchQueue$.MODULE$:Lscalaz/PrioritySearchQueue$;
       3: pop
       4: new           #34                 // class scalaz/PrioritySearchQueue$$anon$2
       7: dup
       8: aload_0
       9: invokespecial #66                 // Method scalaz/PrioritySearchQueue$$anon$2."<init>":(Lscalaz/Show;)V
      12: areturn

  public static <A, P, K> scalaz.PrioritySearchQueue<A, P, K> empty(scala.Function1<A, P>, scala.Function1<A, K>, scalaz.Order<P>, scalaz.Order<K>);
    Code:
       0: getstatic     #62                 // Field scalaz/PrioritySearchQueue$.MODULE$:Lscalaz/PrioritySearchQueue$;
       3: pop
       4: getstatic     #77                 // Field scalaz/Reducer$.MODULE$:Lscalaz/Reducer$;
       7: pop
       8: aload_0
       9: aload_1
      10: invokedynamic #99,  0             // InvokeDynamic #0:apply:(Lscala/Function1;Lscala/Function1;)Lscala/Function1;
      15: getstatic     #102                // Field scalaz/PrioritySearchQueue$Summary$.MODULE$:Lscalaz/PrioritySearchQueue$Summary$;
      18: pop
      19: new           #42                 // class scalaz/PrioritySearchQueue$Summary$$anon$1
      22: dup
      23: aload_2
      24: aload_3
      25: invokespecial #105                // Method scalaz/PrioritySearchQueue$Summary$$anon$1."<init>":(Lscalaz/Order;Lscalaz/Order;)V
      28: astore        6
      30: astore        5
      32: new           #44                 // class scalaz/ReducerInstances$$anon$6
      35: dup
      36: aconst_null
      37: aload         6
      39: aload         5
      41: invokespecial #108                // Method scalaz/ReducerInstances$$anon$6."<init>":(Lscalaz/ReducerInstances;Lscalaz/Semigroup;Lscala/Function1;)V
      44: aconst_null
      45: astore        5
      47: aconst_null
      48: astore        6
      50: astore        4
      52: new           #2                  // class scalaz/PrioritySearchQueue
      55: dup
      56: getstatic     #113                // Field scalaz/FingerTree$.MODULE$:Lscalaz/FingerTree$;
      59: pop
      60: new           #16                 // class scalaz/FingerTree$$anon$15
      63: dup
      64: aload         4
      66: invokespecial #116                // Method scalaz/FingerTree$$anon$15."<init>":(Lscalaz/Reducer;)V
      69: aload_0
      70: aload_1
      71: invokespecial #119                // Method "<init>":(Lscalaz/FingerTree;Lscala/Function1;Lscala/Function1;)V
      74: areturn

  public scalaz.FingerTree<scalaz.PrioritySearchQueue$Summary<A, P, K>, A> scalaz$PrioritySearchQueue$$tree();
    Code:
       0: aload_0
       1: getfield      #129                // Field scalaz$PrioritySearchQueue$$tree:Lscalaz/FingerTree;
       4: areturn

  public boolean isEmpty();
    Code:
       0: aload_0
       1: invokevirtual #135                // Method scalaz$PrioritySearchQueue$$tree:()Lscalaz/FingerTree;
       4: invokevirtual #137                // Method scalaz/FingerTree.isEmpty:()Z
       7: ireturn

  public boolean nonEmpty();
    Code:
       0: aload_0
       1: invokevirtual #135                // Method scalaz$PrioritySearchQueue$$tree:()Lscalaz/FingerTree;
       4: invokevirtual #137                // Method scalaz/FingerTree.isEmpty:()Z
       7: ifne          12
      10: iconst_1
      11: ireturn
      12: iconst_0
      13: ireturn

  public int size();
    Code:
       0: aload_0
       1: invokevirtual #135                // Method scalaz$PrioritySearchQueue$$tree:()Lscalaz/FingerTree;
       4: invokevirtual #144                // Method scalaz/FingerTree.measure:()Lscalaz/Maybe;
       7: invokedynamic #153,  0            // InvokeDynamic #1:apply:()Lscala/Function1;
      12: astore_2
      13: dup
      14: ifnonnull     19
      17: aconst_null
      18: athrow
      19: astore_1
      20: aload_2
      21: invokedynamic #160,  0            // InvokeDynamic #2:apply:()Lscala/Function1;
      26: invokeinterface #166,  2          // InterfaceMethod scala/Function1.andThen:(Lscala/Function1;)Lscala/Function1;
      31: astore_3
      32: aload_1
      33: instanceof    #31                 // class scalaz/Maybe$Just
      36: ifeq          59
      39: aload_1
      40: checkcast     #31                 // class scalaz/Maybe$Just
      43: invokevirtual #170                // Method scalaz/Maybe$Just.get:()Ljava/lang/Object;
      46: astore        4
      48: aload_3
      49: aload         4
      51: invokeinterface #172,  2          // InterfaceMethod scala/Function1.apply:(Ljava/lang/Object;)Ljava/lang/Object;
      56: goto          88
      59: aload_1
      60: instanceof    #23                 // class scalaz/Maybe$Empty
      63: ifeq          79
      66: getstatic     #177                // Field scalaz/Maybe$.MODULE$:Lscalaz/Maybe$;
      69: pop
      70: getstatic     #180                // Field scalaz/Maybe$Empty$.MODULE$:Lscalaz/Maybe$Empty$;
      73: invokevirtual #182                // Method scalaz/Maybe$Empty$.apply:()Lscalaz/Maybe;
      76: goto          88
      79: new           #184                // class scala/MatchError
      82: dup
      83: aload_1
      84: invokespecial #187                // Method scala/MatchError."<init>":(Ljava/lang/Object;)V
      87: athrow
      88: aconst_null
      89: astore_3
      90: aconst_null
      91: astore        4
      93: checkcast     #25                 // class scalaz/Maybe
      96: aconst_null
      97: astore_1
      98: aconst_null
      99: astore_2
     100: dup
     101: ifnonnull     106
     104: aconst_null
     105: athrow
     106: astore        5
     108: aload         5
     110: instanceof    #31                 // class scalaz/Maybe$Just
     113: ifeq          137
     116: aload         5
     118: checkcast     #31                 // class scalaz/Maybe$Just
     121: invokevirtual #170                // Method scalaz/Maybe$Just.get:()Ljava/lang/Object;
     124: astore        6
     126: getstatic     #192                // Field scala/Predef$.MODULE$:Lscala/Predef$;
     129: aload         6
     131: invokevirtual #195                // Method scala/Predef$.identity:(Ljava/lang/Object;)Ljava/lang/Object;
     134: goto          162
     137: aload         5
     139: instanceof    #23                 // class scalaz/Maybe$Empty
     142: ifeq          152
     145: iconst_0
     146: invokestatic  #201                // Method scala/runtime/BoxesRunTime.boxToInteger:(I)Ljava/lang/Integer;
     149: goto          162
     152: new           #184                // class scala/MatchError
     155: dup
     156: aload         5
     158: invokespecial #187                // Method scala/MatchError."<init>":(Ljava/lang/Object;)V
     161: athrow
     162: aconst_null
     163: astore        6
     165: aconst_null
     166: astore        5
     168: invokestatic  #205                // Method scala/runtime/BoxesRunTime.unboxToInt:(Ljava/lang/Object;)I
     171: ireturn

  public scalaz.Maybe<A> minimum();
    Code:
       0: aload_0
       1: invokevirtual #135                // Method scalaz$PrioritySearchQueue$$tree:()Lscalaz/FingerTree;
       4: invokevirtual #144                // Method scalaz/FingerTree.measure:()Lscalaz/Maybe;
       7: invokedynamic #220,  0            // InvokeDynamic #3:apply:()Lscala/Function1;
      12: astore_2
      13: dup
      14: ifnonnull     19
      17: aconst_null
      18: athrow
      19: astore_1
      20: aload_2
      21: invokedynamic #160,  0            // InvokeDynamic #2:apply:()Lscala/Function1;
      26: invokeinterface #166,  2          // InterfaceMethod scala/Function1.andThen:(Lscala/Function1;)Lscala/Function1;
      31: astore_3
      32: aload_1
      33: instanceof    #31                 // class scalaz/Maybe$Just
      36: ifeq          59
      39: aload_1
      40: checkcast     #31                 // class scalaz/Maybe$Just
      43: invokevirtual #170                // Method scalaz/Maybe$Just.get:()Ljava/lang/Object;
      46: astore        4
      48: aload_3
      49: aload         4
      51: invokeinterface #172,  2          // InterfaceMethod scala/Function1.apply:(Ljava/lang/Object;)Ljava/lang/Object;
      56: goto          88
      59: aload_1
      60: instanceof    #23                 // class scalaz/Maybe$Empty
      63: ifeq          79
      66: getstatic     #177                // Field scalaz/Maybe$.MODULE$:Lscalaz/Maybe$;
      69: pop
      70: getstatic     #180                // Field scalaz/Maybe$Empty$.MODULE$:Lscalaz/Maybe$Empty$;
      73: invokevirtual #182                // Method scalaz/Maybe$Empty$.apply:()Lscalaz/Maybe;
      76: goto          88
      79: new           #184                // class scala/MatchError
      82: dup
      83: aload_1
      84: invokespecial #187                // Method scala/MatchError."<init>":(Ljava/lang/Object;)V
      87: athrow
      88: checkcast     #25                 // class scalaz/Maybe
      91: areturn

  public scalaz.Maybe<P> minimumPriority();
    Code:
       0: aload_0
       1: invokevirtual #135                // Method scalaz$PrioritySearchQueue$$tree:()Lscalaz/FingerTree;
       4: invokevirtual #144                // Method scalaz/FingerTree.measure:()Lscalaz/Maybe;
       7: invokedynamic #227,  0            // InvokeDynamic #4:apply:()Lscala/Function1;
      12: astore_2
      13: dup
      14: ifnonnull     19
      17: aconst_null
      18: athrow
      19: astore_1
      20: aload_2
      21: invokedynamic #160,  0            // InvokeDynamic #2:apply:()Lscala/Function1;
      26: invokeinterface #166,  2          // InterfaceMethod scala/Function1.andThen:(Lscala/Function1;)Lscala/Function1;
      31: astore_3
      32: aload_1
      33: instanceof    #31                 // class scalaz/Maybe$Just
      36: ifeq          59
      39: aload_1
      40: checkcast     #31                 // class scalaz/Maybe$Just
      43: invokevirtual #170                // Method scalaz/Maybe$Just.get:()Ljava/lang/Object;
      46: astore        4
      48: aload_3
      49: aload         4
      51: invokeinterface #172,  2          // InterfaceMethod scala/Function1.apply:(Ljava/lang/Object;)Ljava/lang/Object;
      56: goto          88
      59: aload_1
      60: instanceof    #23                 // class scalaz/Maybe$Empty
      63: ifeq          79
      66: getstatic     #177                // Field scalaz/Maybe$.MODULE$:Lscalaz/Maybe$;
      69: pop
      70: getstatic     #180                // Field scalaz/Maybe$Empty$.MODULE$:Lscalaz/Maybe$Empty$;
      73: invokevirtual #182                // Method scalaz/Maybe$Empty$.apply:()Lscalaz/Maybe;
      76: goto          88
      79: new           #184                // class scala/MatchError
      82: dup
      83: aload_1
      84: invokespecial #187                // Method scala/MatchError."<init>":(Ljava/lang/Object;)V
      87: athrow
      88: checkcast     #25                 // class scalaz/Maybe
      91: areturn

  public scalaz.PrioritySearchQueue<A, P, K> deleteMin(scalaz.Order<P>);
    Code:
       0: aload_0
       1: invokevirtual #135                // Method scalaz$PrioritySearchQueue$$tree:()Lscalaz/FingerTree;
       4: invokevirtual #144                // Method scalaz/FingerTree.measure:()Lscalaz/Maybe;
       7: astore_2
       8: aload_2
       9: instanceof    #23                 // class scalaz/Maybe$Empty
      12: ifeq          17
      15: aload_0
      16: areturn
      17: aload_2
      18: instanceof    #31                 // class scalaz/Maybe$Just
      21: ifeq          191
      24: aload_2
      25: checkcast     #31                 // class scalaz/Maybe$Just
      28: invokevirtual #170                // Method scalaz/Maybe$Just.get:()Ljava/lang/Object;
      31: checkcast     #36                 // class scalaz/PrioritySearchQueue$Summary
      34: astore_3
      35: aload_0
      36: invokevirtual #135                // Method scalaz$PrioritySearchQueue$$tree:()Lscalaz/FingerTree;
      39: aload_1
      40: aload_3
      41: invokedynamic #239,  0            // InvokeDynamic #5:apply:(Lscalaz/Order;Lscalaz/PrioritySearchQueue$Summary;)Lscala/Function1;
      46: invokevirtual #243                // Method scalaz/FingerTree.split:(Lscala/Function1;)Lscala/Tuple2;
      49: astore        4
      51: aload         4
      53: ifnull        79
      56: aload         4
      58: invokevirtual #248                // Method scala/Tuple2._1:()Ljava/lang/Object;
      61: checkcast     #20                 // class scalaz/FingerTree
      64: astore        5
      66: aload         4
      68: invokevirtual #251                // Method scala/Tuple2._2:()Ljava/lang/Object;
      71: checkcast     #20                 // class scalaz/FingerTree
      74: astore        6
      76: goto          88
      79: new           #184                // class scala/MatchError
      82: dup
      83: aconst_null
      84: invokespecial #187                // Method scala/MatchError."<init>":(Ljava/lang/Object;)V
      87: athrow
      88: getstatic     #192                // Field scala/Predef$.MODULE$:Lscala/Predef$;
      91: aload         6
      93: invokevirtual #137                // Method scalaz/FingerTree.isEmpty:()Z
      96: ifne          103
      99: iconst_1
     100: goto          104
     103: iconst_0
     104: invokevirtual #255                // Method scala/Predef$.assert:(Z)V
     107: new           #2                  // class scalaz/PrioritySearchQueue
     110: dup
     111: aload         5
     113: aload         6
     115: invokedynamic #265,  0            // InvokeDynamic #6:apply:(Lscalaz/FingerTree;)Lscala/Function0;
     120: astore        7
     122: ifnonnull     127
     125: aconst_null
     126: athrow
     127: getstatic     #270                // Field scalaz/Need$.MODULE$:Lscalaz/Need$;
     130: pop
     131: new           #272                // class scalaz/Need
     134: dup
     135: aload         7
     137: invokespecial #275                // Method scalaz/Need."<init>":(Lscala/Function0;)V
     140: astore        8
     142: aload         5
     144: aload         8
     146: invokedynamic #283,  0            // InvokeDynamic #7:apply:(Lscalaz/Need;)Lscala/Function0;
     151: aload         8
     153: invokedynamic #295,  0            // InvokeDynamic #8:apply:(Lscalaz/Need;)Lscala/Function2;
     158: aload         5
     160: aload         8
     162: invokedynamic #307,  0            // InvokeDynamic #9:apply:(Lscalaz/FingerTree;Lscalaz/Need;)Lscala/Function4;
     167: invokevirtual #311                // Method scalaz/FingerTree.fold:(Lscala/Function0;Lscala/Function2;Lscala/Function4;)Ljava/lang/Object;
     170: checkcast     #20                 // class scalaz/FingerTree
     173: aconst_null
     174: astore        7
     176: aconst_null
     177: astore        8
     179: aload_0
     180: getfield      #313                // Field priorityOf:Lscala/Function1;
     183: aload_0
     184: getfield      #315                // Field keyOf:Lscala/Function1;
     187: invokespecial #119                // Method "<init>":(Lscalaz/FingerTree;Lscala/Function1;Lscala/Function1;)V
     190: areturn
     191: new           #184                // class scala/MatchError
     194: dup
     195: aload_2
     196: invokespecial #187                // Method scala/MatchError."<init>":(Ljava/lang/Object;)V
     199: athrow

  private scalaz.FingerTree<scalaz.PrioritySearchQueue$Summary<A, P, K>, A> emptyTree();
    Code:
       0: aload_0
       1: invokevirtual #135                // Method scalaz$PrioritySearchQueue$$tree:()Lscalaz/FingerTree;
       4: invokedynamic #333,  0            // InvokeDynamic #10:apply:()Lscala/Function1;
       9: invokevirtual #243                // Method scalaz/FingerTree.split:(Lscala/Function1;)Lscala/Tuple2;
      12: invokevirtual #251                // Method scala/Tuple2._2:()Ljava/lang/Object;
      15: checkcast     #20                 // class scalaz/FingerTree
      18: areturn

  public scalaz.PrioritySearchQueue<A, P, K> deleteLt(P, scalaz.Order<P>);
    Code:
       0: aload_0
       1: aload_0
       2: invokespecial #339                // Method emptyTree:()Lscalaz/FingerTree;
       5: aload_0
       6: invokevirtual #135                // Method scalaz$PrioritySearchQueue$$tree:()Lscalaz/FingerTree;
       9: aload_2
      10: aload_1
      11: invokespecial #343                // Method go$1:(Lscalaz/FingerTree;Lscalaz/FingerTree;Lscalaz/Order;Ljava/lang/Object;)Lscalaz/PrioritySearchQueue;
      14: areturn

  public scala.Tuple2<scalaz.PrioritySearchQueue<A, P, K>, scalaz.PrioritySearchQueue<A, P, K>> splitBeforePrio(P, scalaz.Order<P>);
    Code:
       0: aload_0
       1: aload_0
       2: invokespecial #339                // Method emptyTree:()Lscalaz/FingerTree;
       5: aload_0
       6: invokespecial #339                // Method emptyTree:()Lscalaz/FingerTree;
       9: aload_0
      10: invokevirtual #135                // Method scalaz$PrioritySearchQueue$$tree:()Lscalaz/FingerTree;
      13: aload_2
      14: aload_1
      15: invokespecial #350                // Method go$2:(Lscalaz/FingerTree;Lscalaz/FingerTree;Lscalaz/FingerTree;Lscalaz/Order;Ljava/lang/Object;)Lscala/Tuple2;
      18: areturn

  public scalaz.PrioritySearchQueue<A, P, K> deleteLte(P, scalaz.Order<P>);
    Code:
       0: aload_0
       1: aload_0
       2: invokespecial #339                // Method emptyTree:()Lscalaz/FingerTree;
       5: aload_0
       6: invokevirtual #135                // Method scalaz$PrioritySearchQueue$$tree:()Lscalaz/FingerTree;
       9: aload_2
      10: aload_1
      11: invokespecial #354                // Method go$3:(Lscalaz/FingerTree;Lscalaz/FingerTree;Lscalaz/Order;Ljava/lang/Object;)Lscalaz/PrioritySearchQueue;
      14: areturn

  public scala.Tuple2<scalaz.PrioritySearchQueue<A, P, K>, scalaz.PrioritySearchQueue<A, P, K>> splitAfterPrio(P, scalaz.Order<P>);
    Code:
       0: aload_0
       1: aload_0
       2: invokespecial #339                // Method emptyTree:()Lscalaz/FingerTree;
       5: aload_0
       6: invokespecial #339                // Method emptyTree:()Lscalaz/FingerTree;
       9: aload_0
      10: invokevirtual #135                // Method scalaz$PrioritySearchQueue$$tree:()Lscalaz/FingerTree;
      13: aload_2
      14: aload_1
      15: invokespecial #358                // Method go$4:(Lscalaz/FingerTree;Lscalaz/FingerTree;Lscalaz/FingerTree;Lscalaz/Order;Ljava/lang/Object;)Lscala/Tuple2;
      18: areturn

  public scala.Tuple2<scalaz.PrioritySearchQueue<A, P, K>, scalaz.Maybe<A>> insert(A, scalaz.Order<K>);
    Code:
       0: aload_0
       1: invokevirtual #135                // Method scalaz$PrioritySearchQueue$$tree:()Lscalaz/FingerTree;
       4: aload_0
       5: aload_2
       6: aload_1
       7: invokedynamic #370,  0            // InvokeDynamic #11:apply:(Lscalaz/PrioritySearchQueue;Lscalaz/Order;Ljava/lang/Object;)Lscala/Function1;
      12: invokevirtual #243                // Method scalaz/FingerTree.split:(Lscala/Function1;)Lscala/Tuple2;
      15: astore_3
      16: aload_3
      17: ifnull        41
      20: aload_3
      21: invokevirtual #248                // Method scala/Tuple2._1:()Ljava/lang/Object;
      24: checkcast     #20                 // class scalaz/FingerTree
      27: astore        4
      29: aload_3
      30: invokevirtual #251                // Method scala/Tuple2._2:()Ljava/lang/Object;
      33: checkcast     #20                 // class scalaz/FingerTree
      36: astore        5
      38: goto          50
      41: new           #184                // class scala/MatchError
      44: dup
      45: aconst_null
      46: invokespecial #187                // Method scala/MatchError."<init>":(Ljava/lang/Object;)V
      49: athrow
      50: aload         5
      52: invokevirtual #137                // Method scalaz/FingerTree.isEmpty:()Z
      55: ifeq          82
      58: aload         4
      60: aload_1
      61: invokedynamic #377,  0            // InvokeDynamic #12:apply:(Ljava/lang/Object;)Lscala/Function0;
      66: invokevirtual #381                // Method scalaz/FingerTree.$colon$plus:(Lscala/Function0;)Lscalaz/FingerTree;
      69: getstatic     #177                // Field scalaz/Maybe$.MODULE$:Lscalaz/Maybe$;
      72: pop
      73: getstatic     #180                // Field scalaz/Maybe$Empty$.MODULE$:Lscalaz/Maybe$Empty$;
      76: invokevirtual #182                // Method scalaz/Maybe$Empty$.apply:()Lscalaz/Maybe;
      79: goto          307
      82: getstatic     #386                // Field scalaz/syntax/order$.MODULE$:Lscalaz/syntax/order$;
      85: pop
      86: aload_0
      87: getfield      #315                // Field keyOf:Lscala/Function1;
      90: aload         5
      92: invokevirtual #389                // Method scalaz/FingerTree.head:()Ljava/lang/Object;
      95: invokeinterface #172,  2          // InterfaceMethod scala/Function1.apply:(Ljava/lang/Object;)Ljava/lang/Object;
     100: astore        8
     102: new           #391                // class scalaz/syntax/EqualOps
     105: dup
     106: aload         8
     108: aload_2
     109: invokespecial #394                // Method scalaz/syntax/EqualOps."<init>":(Ljava/lang/Object;Lscalaz/Equal;)V
     112: aconst_null
     113: astore        8
     115: aload_0
     116: getfield      #315                // Field keyOf:Lscala/Function1;
     119: aload_1
     120: invokeinterface #172,  2          // InterfaceMethod scala/Function1.apply:(Ljava/lang/Object;)Ljava/lang/Object;
     125: invokevirtual #398                // Method scalaz/syntax/EqualOps.$eq$eq$eq:(Ljava/lang/Object;)Z
     128: ifeq          226
     131: aload         4
     133: aload_1
     134: aload         5
     136: invokedynamic #406,  0            // InvokeDynamic #13:apply:(Ljava/lang/Object;Lscalaz/FingerTree;)Lscala/Function0;
     141: astore        9
     143: ifnonnull     148
     146: aconst_null
     147: athrow
     148: getstatic     #270                // Field scalaz/Need$.MODULE$:Lscalaz/Need$;
     151: pop
     152: new           #272                // class scalaz/Need
     155: dup
     156: aload         9
     158: invokespecial #275                // Method scalaz/Need."<init>":(Lscala/Function0;)V
     161: astore        10
     163: aload         4
     165: aload         10
     167: invokedynamic #283,  0            // InvokeDynamic #7:apply:(Lscalaz/Need;)Lscala/Function0;
     172: aload         10
     174: invokedynamic #295,  0            // InvokeDynamic #8:apply:(Lscalaz/Need;)Lscala/Function2;
     179: aload         4
     181: aload         10
     183: invokedynamic #307,  0            // InvokeDynamic #9:apply:(Lscalaz/FingerTree;Lscalaz/Need;)Lscala/Function4;
     188: invokevirtual #311                // Method scalaz/FingerTree.fold:(Lscala/Function0;Lscala/Function2;Lscala/Function4;)Ljava/lang/Object;
     191: checkcast     #20                 // class scalaz/FingerTree
     194: aconst_null
     195: astore        9
     197: aconst_null
     198: astore        10
     200: getstatic     #177                // Field scalaz/Maybe$.MODULE$:Lscalaz/Maybe$;
     203: pop
     204: aload         5
     206: invokevirtual #389                // Method scalaz/FingerTree.head:()Ljava/lang/Object;
     209: astore        13
     211: new           #31                 // class scalaz/Maybe$Just
     214: dup
     215: aload         13
     217: invokespecial #407                // Method scalaz/Maybe$Just."<init>":(Ljava/lang/Object;)V
     220: aconst_null
     221: astore        13
     223: goto          307
     226: aload         4
     228: aload         5
     230: invokedynamic #412,  0            // InvokeDynamic #14:apply:(Lscalaz/FingerTree;)Lscala/Function0;
     235: astore        11
     237: ifnonnull     242
     240: aconst_null
     241: athrow
     242: getstatic     #270                // Field scalaz/Need$.MODULE$:Lscalaz/Need$;
     245: pop
     246: new           #272                // class scalaz/Need
     249: dup
     250: aload         11
     252: invokespecial #275                // Method scalaz/Need."<init>":(Lscala/Function0;)V
     255: astore        12
     257: aload         4
     259: aload_1
     260: aload         12
     262: invokedynamic #420,  0            // InvokeDynamic #15:apply:(Ljava/lang/Object;Lscalaz/Need;)Lscala/Function0;
     267: aload_1
     268: aload         12
     270: invokedynamic #428,  0            // InvokeDynamic #16:apply:(Ljava/lang/Object;Lscalaz/Need;)Lscala/Function2;
     275: aload         4
     277: aload         12
     279: aload_1
     280: invokedynamic #436,  0            // InvokeDynamic #17:apply:(Lscalaz/FingerTree;Lscalaz/Need;Ljava/lang/Object;)Lscala/Function4;
     285: invokevirtual #311                // Method scalaz/FingerTree.fold:(Lscala/Function0;Lscala/Function2;Lscala/Function4;)Ljava/lang/Object;
     288: checkcast     #20                 // class scalaz/FingerTree
     291: aconst_null
     292: astore        11
     294: aconst_null
     295: astore        12
     297: getstatic     #177                // Field scalaz/Maybe$.MODULE$:Lscalaz/Maybe$;
     300: pop
     301: getstatic     #180                // Field scalaz/Maybe$Empty$.MODULE$:Lscalaz/Maybe$Empty$;
     304: invokevirtual #182                // Method scalaz/Maybe$Empty$.apply:()Lscalaz/Maybe;
     307: astore        14
     309: astore        6
     311: aload         14
     313: checkcast     #25                 // class scalaz/Maybe
     316: astore        7
     318: new           #245                // class scala/Tuple2
     321: dup
     322: new           #2                  // class scalaz/PrioritySearchQueue
     325: dup
     326: aload         6
     328: aload_0
     329: getfield      #313                // Field priorityOf:Lscala/Function1;
     332: aload_0
     333: getfield      #315                // Field keyOf:Lscala/Function1;
     336: invokespecial #119                // Method "<init>":(Lscalaz/FingerTree;Lscala/Function1;Lscala/Function1;)V
     339: aload         7
     341: invokespecial #439                // Method scala/Tuple2."<init>":(Ljava/lang/Object;Ljava/lang/Object;)V
     344: areturn

  public scalaz.Maybe<A> get(K, scalaz.Order<K>);
    Code:
       0: aload_0
       1: invokevirtual #135                // Method scalaz$PrioritySearchQueue$$tree:()Lscalaz/FingerTree;
       4: aload_2
       5: aload_1
       6: invokedynamic #456,  0            // InvokeDynamic #18:apply:(Lscalaz/Order;Ljava/lang/Object;)Lscala/Function1;
      11: invokevirtual #243                // Method scalaz/FingerTree.split:(Lscala/Function1;)Lscala/Tuple2;
      14: astore_3
      15: aload_3
      16: ifnull        39
      19: aload_3
      20: invokevirtual #248                // Method scala/Tuple2._1:()Ljava/lang/Object;
      23: checkcast     #20                 // class scalaz/FingerTree
      26: pop
      27: aload_3
      28: invokevirtual #251                // Method scala/Tuple2._2:()Ljava/lang/Object;
      31: checkcast     #20                 // class scalaz/FingerTree
      34: astore        4
      36: goto          48
      39: new           #184                // class scala/MatchError
      42: dup
      43: aconst_null
      44: invokespecial #187                // Method scala/MatchError."<init>":(Ljava/lang/Object;)V
      47: athrow
      48: aload         4
      50: invokevirtual #137                // Method scalaz/FingerTree.isEmpty:()Z
      53: ifeq          67
      56: getstatic     #177                // Field scalaz/Maybe$.MODULE$:Lscalaz/Maybe$;
      59: pop
      60: getstatic     #180                // Field scalaz/Maybe$Empty$.MODULE$:Lscalaz/Maybe$Empty$;
      63: invokevirtual #182                // Method scalaz/Maybe$Empty$.apply:()Lscalaz/Maybe;
      66: areturn
      67: getstatic     #386                // Field scalaz/syntax/order$.MODULE$:Lscalaz/syntax/order$;
      70: pop
      71: aload_0
      72: getfield      #315                // Field keyOf:Lscala/Function1;
      75: aload         4
      77: invokevirtual #389                // Method scalaz/FingerTree.head:()Ljava/lang/Object;
      80: invokeinterface #172,  2          // InterfaceMethod scala/Function1.apply:(Ljava/lang/Object;)Ljava/lang/Object;
      85: astore        5
      87: new           #391                // class scalaz/syntax/EqualOps
      90: dup
      91: aload         5
      93: aload_2
      94: invokespecial #394                // Method scalaz/syntax/EqualOps."<init>":(Ljava/lang/Object;Lscalaz/Equal;)V
      97: aconst_null
      98: astore        5
     100: aload_1
     101: invokevirtual #398                // Method scalaz/syntax/EqualOps.$eq$eq$eq:(Ljava/lang/Object;)Z
     104: ifeq          128
     107: getstatic     #177                // Field scalaz/Maybe$.MODULE$:Lscalaz/Maybe$;
     110: pop
     111: aload         4
     113: invokevirtual #389                // Method scalaz/FingerTree.head:()Ljava/lang/Object;
     116: astore        6
     118: new           #31                 // class scalaz/Maybe$Just
     121: dup
     122: aload         6
     124: invokespecial #407                // Method scalaz/Maybe$Just."<init>":(Ljava/lang/Object;)V
     127: areturn
     128: getstatic     #177                // Field scalaz/Maybe$.MODULE$:Lscalaz/Maybe$;
     131: pop
     132: getstatic     #180                // Field scalaz/Maybe$Empty$.MODULE$:Lscalaz/Maybe$Empty$;
     135: invokevirtual #182                // Method scalaz/Maybe$Empty$.apply:()Lscalaz/Maybe;
     138: areturn

  public scala.Tuple2<scalaz.PrioritySearchQueue<A, P, K>, scalaz.Maybe<A>> removeByKey(K, scalaz.Order<K>);
    Code:
       0: aload_0
       1: invokevirtual #135                // Method scalaz$PrioritySearchQueue$$tree:()Lscalaz/FingerTree;
       4: aload_2
       5: aload_1
       6: invokedynamic #463,  0            // InvokeDynamic #19:apply:(Lscalaz/Order;Ljava/lang/Object;)Lscala/Function1;
      11: invokevirtual #243                // Method scalaz/FingerTree.split:(Lscala/Function1;)Lscala/Tuple2;
      14: astore_3
      15: aload_3
      16: ifnull        40
      19: aload_3
      20: invokevirtual #248                // Method scala/Tuple2._1:()Ljava/lang/Object;
      23: checkcast     #20                 // class scalaz/FingerTree
      26: astore        4
      28: aload_3
      29: invokevirtual #251                // Method scala/Tuple2._2:()Ljava/lang/Object;
      32: checkcast     #20                 // class scalaz/FingerTree
      35: astore        5
      37: goto          49
      40: new           #184                // class scala/MatchError
      43: dup
      44: aconst_null
      45: invokespecial #187                // Method scala/MatchError."<init>":(Ljava/lang/Object;)V
      48: athrow
      49: aload         5
      51: invokevirtual #137                // Method scalaz/FingerTree.isEmpty:()Z
      54: ifeq          76
      57: new           #245                // class scala/Tuple2
      60: dup
      61: aload_0
      62: getstatic     #177                // Field scalaz/Maybe$.MODULE$:Lscalaz/Maybe$;
      65: pop
      66: getstatic     #180                // Field scalaz/Maybe$Empty$.MODULE$:Lscalaz/Maybe$Empty$;
      69: invokevirtual #182                // Method scalaz/Maybe$Empty$.apply:()Lscalaz/Maybe;
      72: invokespecial #439                // Method scala/Tuple2."<init>":(Ljava/lang/Object;Ljava/lang/Object;)V
      75: areturn
      76: getstatic     #386                // Field scalaz/syntax/order$.MODULE$:Lscalaz/syntax/order$;
      79: pop
      80: aload_0
      81: getfield      #315                // Field keyOf:Lscala/Function1;
      84: aload         5
      86: invokevirtual #389                // Method scalaz/FingerTree.head:()Ljava/lang/Object;
      89: invokeinterface #172,  2          // InterfaceMethod scala/Function1.apply:(Ljava/lang/Object;)Ljava/lang/Object;
      94: astore        6
      96: new           #391                // class scalaz/syntax/EqualOps
      99: dup
     100: aload         6
     102: aload_2
     103: invokespecial #394                // Method scalaz/syntax/EqualOps."<init>":(Ljava/lang/Object;Lscalaz/Equal;)V
     106: aconst_null
     107: astore        6
     109: aload_1
     110: invokevirtual #398                // Method scalaz/syntax/EqualOps.$eq$eq$eq:(Ljava/lang/Object;)Z
     113: ifeq          230
     116: new           #245                // class scala/Tuple2
     119: dup
     120: new           #2                  // class scalaz/PrioritySearchQueue
     123: dup
     124: aload         4
     126: aload         5
     128: invokedynamic #468,  0            // InvokeDynamic #20:apply:(Lscalaz/FingerTree;)Lscala/Function0;
     133: astore        7
     135: ifnonnull     140
     138: aconst_null
     139: athrow
     140: getstatic     #270                // Field scalaz/Need$.MODULE$:Lscalaz/Need$;
     143: pop
     144: new           #272                // class scalaz/Need
     147: dup
     148: aload         7
     150: invokespecial #275                // Method scalaz/Need."<init>":(Lscala/Function0;)V
     153: astore        8
     155: aload         4
     157: aload         8
     159: invokedynamic #283,  0            // InvokeDynamic #7:apply:(Lscalaz/Need;)Lscala/Function0;
     164: aload         8
     166: invokedynamic #295,  0            // InvokeDynamic #8:apply:(Lscalaz/Need;)Lscala/Function2;
     171: aload         4
     173: aload         8
     175: invokedynamic #307,  0            // InvokeDynamic #9:apply:(Lscalaz/FingerTree;Lscalaz/Need;)Lscala/Function4;
     180: invokevirtual #311                // Method scalaz/FingerTree.fold:(Lscala/Function0;Lscala/Function2;Lscala/Function4;)Ljava/lang/Object;
     183: checkcast     #20                 // class scalaz/FingerTree
     186: aconst_null
     187: astore        7
     189: aconst_null
     190: astore        8
     192: aload_0
     193: getfield      #313                // Field priorityOf:Lscala/Function1;
     196: aload_0
     197: getfield      #315                // Field keyOf:Lscala/Function1;
     200: invokespecial #119                // Method "<init>":(Lscalaz/FingerTree;Lscala/Function1;Lscala/Function1;)V
     203: getstatic     #177                // Field scalaz/Maybe$.MODULE$:Lscalaz/Maybe$;
     206: pop
     207: aload         5
     209: invokevirtual #389                // Method scalaz/FingerTree.head:()Ljava/lang/Object;
     212: astore        9
     214: new           #31                 // class scalaz/Maybe$Just
     217: dup
     218: aload         9
     220: invokespecial #407                // Method scalaz/Maybe$Just."<init>":(Ljava/lang/Object;)V
     223: aconst_null
     224: astore        9
     226: invokespecial #439                // Method scala/Tuple2."<init>":(Ljava/lang/Object;Ljava/lang/Object;)V
     229: areturn
     230: new           #245                // class scala/Tuple2
     233: dup
     234: aload_0
     235: getstatic     #177                // Field scalaz/Maybe$.MODULE$:Lscalaz/Maybe$;
     238: pop
     239: getstatic     #180                // Field scalaz/Maybe$Empty$.MODULE$:Lscalaz/Maybe$Empty$;
     242: invokevirtual #182                // Method scalaz/Maybe$Empty$.apply:()Lscalaz/Maybe;
     245: invokespecial #439                // Method scala/Tuple2."<init>":(Ljava/lang/Object;Ljava/lang/Object;)V
     248: areturn

  public boolean containsKey(K, scalaz.Order<K>);
    Code:
       0: aload_0
       1: invokevirtual #135                // Method scalaz$PrioritySearchQueue$$tree:()Lscalaz/FingerTree;
       4: aload_2
       5: aload_1
       6: invokedynamic #476,  0            // InvokeDynamic #21:apply:(Lscalaz/Order;Ljava/lang/Object;)Lscala/Function1;
      11: invokevirtual #243                // Method scalaz/FingerTree.split:(Lscala/Function1;)Lscala/Tuple2;
      14: astore_3
      15: aload_3
      16: ifnull        39
      19: aload_3
      20: invokevirtual #248                // Method scala/Tuple2._1:()Ljava/lang/Object;
      23: checkcast     #20                 // class scalaz/FingerTree
      26: pop
      27: aload_3
      28: invokevirtual #251                // Method scala/Tuple2._2:()Ljava/lang/Object;
      31: checkcast     #20                 // class scalaz/FingerTree
      34: astore        4
      36: goto          48
      39: new           #184                // class scala/MatchError
      42: dup
      43: aconst_null
      44: invokespecial #187                // Method scala/MatchError."<init>":(Ljava/lang/Object;)V
      47: athrow
      48: aload         4
      50: invokevirtual #137                // Method scalaz/FingerTree.isEmpty:()Z
      53: ifne          98
      56: getstatic     #386                // Field scalaz/syntax/order$.MODULE$:Lscalaz/syntax/order$;
      59: pop
      60: aload_0
      61: getfield      #315                // Field keyOf:Lscala/Function1;
      64: aload         4
      66: invokevirtual #389                // Method scalaz/FingerTree.head:()Ljava/lang/Object;
      69: invokeinterface #172,  2          // InterfaceMethod scala/Function1.apply:(Ljava/lang/Object;)Ljava/lang/Object;
      74: astore        5
      76: new           #391                // class scalaz/syntax/EqualOps
      79: dup
      80: aload         5
      82: aload_2
      83: invokespecial #394                // Method scalaz/syntax/EqualOps."<init>":(Ljava/lang/Object;Lscalaz/Equal;)V
      86: aconst_null
      87: astore        5
      89: aload_1
      90: invokevirtual #398                // Method scalaz/syntax/EqualOps.$eq$eq$eq:(Ljava/lang/Object;)Z
      93: ifeq          98
      96: iconst_1
      97: ireturn
      98: iconst_0
      99: ireturn

  public scala.collection.immutable.List<A> toUnsortedList();
    Code:
       0: aload_0
       1: invokevirtual #135                // Method scalaz$PrioritySearchQueue$$tree:()Lscalaz/FingerTree;
       4: invokevirtual #482                // Method scalaz/FingerTree.toList:()Lscala/collection/immutable/List;
       7: areturn

  public scalaz.IList<A> toUnsortedIList();
    Code:
       0: aload_0
       1: invokevirtual #135                // Method scalaz$PrioritySearchQueue$$tree:()Lscalaz/FingerTree;
       4: invokevirtual #488                // Method scalaz/FingerTree.toIList:()Lscalaz/IList;
       7: areturn

  public static final int $anonfun$size$1(scalaz.PrioritySearchQueue$Summary);
    Code:
       0: aload_0
       1: invokevirtual #493                // Method scalaz/PrioritySearchQueue$Summary.size:()I
       4: ireturn

  public static final int $anonfun$size$2();
    Code:
       0: iconst_0
       1: ireturn

  public static final java.lang.Object $anonfun$minimum$1(scalaz.PrioritySearchQueue$Summary);
    Code:
       0: aload_0
       1: invokevirtual #498                // Method scalaz/PrioritySearchQueue$Summary.minByPrio:()Ljava/lang/Object;
       4: areturn

  public static final java.lang.Object $anonfun$minimumPriority$1(scalaz.PrioritySearchQueue$Summary);
    Code:
       0: aload_0
       1: invokevirtual #502                // Method scalaz/PrioritySearchQueue$Summary.minPrio:()Ljava/lang/Object;
       4: areturn

  public static final boolean $anonfun$deleteMin$1(scalaz.Order, scalaz.PrioritySearchQueue$Summary, scalaz.PrioritySearchQueue$Summary);
    Code:
       0: getstatic     #386                // Field scalaz/syntax/order$.MODULE$:Lscalaz/syntax/order$;
       3: pop
       4: aload_2
       5: invokevirtual #502                // Method scalaz/PrioritySearchQueue$Summary.minPrio:()Ljava/lang/Object;
       8: astore_3
       9: new           #391                // class scalaz/syntax/EqualOps
      12: dup
      13: aload_3
      14: aload_0
      15: invokespecial #394                // Method scalaz/syntax/EqualOps."<init>":(Ljava/lang/Object;Lscalaz/Equal;)V
      18: aconst_null
      19: astore_3
      20: aload_1
      21: invokevirtual #502                // Method scalaz/PrioritySearchQueue$Summary.minPrio:()Ljava/lang/Object;
      24: invokevirtual #398                // Method scalaz/syntax/EqualOps.$eq$eq$eq:(Ljava/lang/Object;)Z
      27: ireturn

  public static final scalaz.FingerTree $anonfun$deleteMin$2(scalaz.FingerTree);
    Code:
       0: aload_0
       1: invokevirtual #511                // Method scalaz/FingerTree.tail:()Lscalaz/FingerTree;
       4: areturn

  public static final boolean $anonfun$emptyTree$1(scalaz.PrioritySearchQueue$Summary);
    Code:
       0: iconst_0
       1: ireturn

  public static final boolean $anonfun$deleteLt$1(scalaz.Order, java.lang.Object, scalaz.PrioritySearchQueue$Summary);
    Code:
       0: getstatic     #386                // Field scalaz/syntax/order$.MODULE$:Lscalaz/syntax/order$;
       3: pop
       4: aload_2
       5: invokevirtual #522                // Method scalaz/PrioritySearchQueue$Summary.maxPrio:()Ljava/lang/Object;
       8: astore_3
       9: new           #524                // class scalaz/syntax/OrderOps
      12: dup
      13: aload_3
      14: aload_0
      15: invokespecial #527                // Method scalaz/syntax/OrderOps."<init>":(Ljava/lang/Object;Lscalaz/Order;)V
      18: aconst_null
      19: astore_3
      20: aload_1
      21: invokevirtual #530                // Method scalaz/syntax/OrderOps.$greater$eq:(Ljava/lang/Object;)Z
      24: ireturn

  public static final boolean $anonfun$deleteLt$2(scalaz.Order, java.lang.Object, scalaz.PrioritySearchQueue$Summary);
    Code:
       0: getstatic     #386                // Field scalaz/syntax/order$.MODULE$:Lscalaz/syntax/order$;
       3: pop
       4: aload_2
       5: invokevirtual #502                // Method scalaz/PrioritySearchQueue$Summary.minPrio:()Ljava/lang/Object;
       8: astore_3
       9: new           #524                // class scalaz/syntax/OrderOps
      12: dup
      13: aload_3
      14: aload_0
      15: invokespecial #527                // Method scalaz/syntax/OrderOps."<init>":(Ljava/lang/Object;Lscalaz/Order;)V
      18: aconst_null
      19: astore_3
      20: aload_1
      21: invokevirtual #536                // Method scalaz/syntax/OrderOps.$less:(Ljava/lang/Object;)Z
      24: ireturn

  public static final scalaz.FingerTree $anonfun$deleteLt$3(scalaz.FingerTree);
    Code:
       0: aload_0
       1: areturn

  private final scalaz.PrioritySearchQueue go$1(scalaz.FingerTree, scalaz.FingerTree, scalaz.Order, java.lang.Object);
    Code:
       0: aload_2
       1: invokevirtual #137                // Method scalaz/FingerTree.isEmpty:()Z
       4: ifeq          24
       7: new           #2                  // class scalaz/PrioritySearchQueue
      10: dup
      11: aload_1
      12: aload_0
      13: getfield      #313                // Field priorityOf:Lscala/Function1;
      16: aload_0
      17: getfield      #315                // Field keyOf:Lscala/Function1;
      20: invokespecial #119                // Method "<init>":(Lscalaz/FingerTree;Lscala/Function1;Lscala/Function1;)V
      23: areturn
      24: aload_2
      25: aload_3
      26: aload         4
      28: invokedynamic #545,  0            // InvokeDynamic #22:apply:(Lscalaz/Order;Ljava/lang/Object;)Lscala/Function1;
      33: invokevirtual #243                // Method scalaz/FingerTree.split:(Lscala/Function1;)Lscala/Tuple2;
      36: astore        5
      38: aload         5
      40: ifnull        56
      43: aload         5
      45: invokevirtual #251                // Method scala/Tuple2._2:()Ljava/lang/Object;
      48: checkcast     #20                 // class scalaz/FingerTree
      51: astore        6
      53: goto          65
      56: new           #184                // class scala/MatchError
      59: dup
      60: aconst_null
      61: invokespecial #187                // Method scala/MatchError."<init>":(Ljava/lang/Object;)V
      64: athrow
      65: aload         6
      67: aload_3
      68: aload         4
      70: invokedynamic #550,  0            // InvokeDynamic #23:apply:(Lscalaz/Order;Ljava/lang/Object;)Lscala/Function1;
      75: invokevirtual #243                // Method scalaz/FingerTree.split:(Lscala/Function1;)Lscala/Tuple2;
      78: astore        7
      80: aload         7
      82: ifnull        108
      85: aload         7
      87: invokevirtual #248                // Method scala/Tuple2._1:()Ljava/lang/Object;
      90: checkcast     #20                 // class scalaz/FingerTree
      93: astore        8
      95: aload         7
      97: invokevirtual #251                // Method scala/Tuple2._2:()Ljava/lang/Object;
     100: checkcast     #20                 // class scalaz/FingerTree
     103: astore        9
     105: goto          117
     108: new           #184                // class scala/MatchError
     111: dup
     112: aconst_null
     113: invokespecial #187                // Method scala/MatchError."<init>":(Ljava/lang/Object;)V
     116: athrow
     117: aload_1
     118: aload         8
     120: invokedynamic #554,  0            // InvokeDynamic #24:apply:(Lscalaz/FingerTree;)Lscala/Function0;
     125: astore        10
     127: ifnonnull     132
     130: aconst_null
     131: athrow
     132: getstatic     #270                // Field scalaz/Need$.MODULE$:Lscalaz/Need$;
     135: pop
     136: new           #272                // class scalaz/Need
     139: dup
     140: aload         10
     142: invokespecial #275                // Method scalaz/Need."<init>":(Lscala/Function0;)V
     145: astore        11
     147: aload_1
     148: aload         11
     150: invokedynamic #283,  0            // InvokeDynamic #7:apply:(Lscalaz/Need;)Lscala/Function0;
     155: aload         11
     157: invokedynamic #295,  0            // InvokeDynamic #8:apply:(Lscalaz/Need;)Lscala/Function2;
     162: aload_1
     163: aload         11
     165: invokedynamic #307,  0            // InvokeDynamic #9:apply:(Lscalaz/FingerTree;Lscalaz/Need;)Lscala/Function4;
     170: invokevirtual #311                // Method scalaz/FingerTree.fold:(Lscala/Function0;Lscala/Function2;Lscala/Function4;)Ljava/lang/Object;
     173: checkcast     #20                 // class scalaz/FingerTree
     176: aconst_null
     177: astore        10
     179: aconst_null
     180: astore        11
     182: aload         9
     184: astore_2
     185: astore_1
     186: goto          0

  public static final boolean $anonfun$splitBeforePrio$1(scalaz.Order, java.lang.Object, scalaz.PrioritySearchQueue$Summary);
    Code:
       0: getstatic     #386                // Field scalaz/syntax/order$.MODULE$:Lscalaz/syntax/order$;
       3: pop
       4: aload_2
       5: invokevirtual #522                // Method scalaz/PrioritySearchQueue$Summary.maxPrio:()Ljava/lang/Object;
       8: astore_3
       9: new           #524                // class scalaz/syntax/OrderOps
      12: dup
      13: aload_3
      14: aload_0
      15: invokespecial #527                // Method scalaz/syntax/OrderOps."<init>":(Ljava/lang/Object;Lscalaz/Order;)V
      18: aconst_null
      19: astore_3
      20: aload_1
      21: invokevirtual #530                // Method scalaz/syntax/OrderOps.$greater$eq:(Ljava/lang/Object;)Z
      24: ireturn

  public static final boolean $anonfun$splitBeforePrio$2(scalaz.Order, java.lang.Object, scalaz.PrioritySearchQueue$Summary);
    Code:
       0: getstatic     #386                // Field scalaz/syntax/order$.MODULE$:Lscalaz/syntax/order$;
       3: pop
       4: aload_2
       5: invokevirtual #502                // Method scalaz/PrioritySearchQueue$Summary.minPrio:()Ljava/lang/Object;
       8: astore_3
       9: new           #524                // class scalaz/syntax/OrderOps
      12: dup
      13: aload_3
      14: aload_0
      15: invokespecial #527                // Method scalaz/syntax/OrderOps."<init>":(Ljava/lang/Object;Lscalaz/Order;)V
      18: aconst_null
      19: astore_3
      20: aload_1
      21: invokevirtual #536                // Method scalaz/syntax/OrderOps.$less:(Ljava/lang/Object;)Z
      24: ireturn

  public static final scalaz.FingerTree $anonfun$splitBeforePrio$3(scalaz.FingerTree);
    Code:
       0: aload_0
       1: areturn

  public static final scalaz.FingerTree $anonfun$splitBeforePrio$4(scalaz.FingerTree);
    Code:
       0: aload_0
       1: areturn

  private final scala.Tuple2 go$2(scalaz.FingerTree, scalaz.FingerTree, scalaz.FingerTree, scalaz.Order, java.lang.Object);
    Code:
       0: aload_3
       1: invokevirtual #137                // Method scalaz/FingerTree.isEmpty:()Z
       4: ifeq          47
       7: new           #245                // class scala/Tuple2
      10: dup
      11: new           #2                  // class scalaz/PrioritySearchQueue
      14: dup
      15: aload_1
      16: aload_0
      17: getfield      #313                // Field priorityOf:Lscala/Function1;
      20: aload_0
      21: getfield      #315                // Field keyOf:Lscala/Function1;
      24: invokespecial #119                // Method "<init>":(Lscalaz/FingerTree;Lscala/Function1;Lscala/Function1;)V
      27: new           #2                  // class scalaz/PrioritySearchQueue
      30: dup
      31: aload_2
      32: aload_0
      33: getfield      #313                // Field priorityOf:Lscala/Function1;
      36: aload_0
      37: getfield      #315                // Field keyOf:Lscala/Function1;
      40: invokespecial #119                // Method "<init>":(Lscalaz/FingerTree;Lscala/Function1;Lscala/Function1;)V
      43: invokespecial #439                // Method scala/Tuple2."<init>":(Ljava/lang/Object;Ljava/lang/Object;)V
      46: areturn
      47: aload_3
      48: aload         4
      50: aload         5
      52: invokedynamic #571,  0            // InvokeDynamic #25:apply:(Lscalaz/Order;Ljava/lang/Object;)Lscala/Function1;
      57: invokevirtual #243                // Method scalaz/FingerTree.split:(Lscala/Function1;)Lscala/Tuple2;
      60: astore        6
      62: aload         6
      64: ifnull        90
      67: aload         6
      69: invokevirtual #248                // Method scala/Tuple2._1:()Ljava/lang/Object;
      72: checkcast     #20                 // class scalaz/FingerTree
      75: astore        7
      77: aload         6
      79: invokevirtual #251                // Method scala/Tuple2._2:()Ljava/lang/Object;
      82: checkcast     #20                 // class scalaz/FingerTree
      85: astore        8
      87: goto          99
      90: new           #184                // class scala/MatchError
      93: dup
      94: aconst_null
      95: invokespecial #187                // Method scala/MatchError."<init>":(Ljava/lang/Object;)V
      98: athrow
      99: aload         8
     101: aload         4
     103: aload         5
     105: invokedynamic #576,  0            // InvokeDynamic #26:apply:(Lscalaz/Order;Ljava/lang/Object;)Lscala/Function1;
     110: invokevirtual #243                // Method scalaz/FingerTree.split:(Lscala/Function1;)Lscala/Tuple2;
     113: astore        9
     115: aload         9
     117: ifnull        143
     120: aload         9
     122: invokevirtual #248                // Method scala/Tuple2._1:()Ljava/lang/Object;
     125: checkcast     #20                 // class scalaz/FingerTree
     128: astore        10
     130: aload         9
     132: invokevirtual #251                // Method scala/Tuple2._2:()Ljava/lang/Object;
     135: checkcast     #20                 // class scalaz/FingerTree
     138: astore        11
     140: goto          152
     143: new           #184                // class scala/MatchError
     146: dup
     147: aconst_null
     148: invokespecial #187                // Method scala/MatchError."<init>":(Ljava/lang/Object;)V
     151: athrow
     152: aload_1
     153: aload         7
     155: invokedynamic #580,  0            // InvokeDynamic #27:apply:(Lscalaz/FingerTree;)Lscala/Function0;
     160: astore        12
     162: ifnonnull     167
     165: aconst_null
     166: athrow
     167: getstatic     #270                // Field scalaz/Need$.MODULE$:Lscalaz/Need$;
     170: pop
     171: new           #272                // class scalaz/Need
     174: dup
     175: aload         12
     177: invokespecial #275                // Method scalaz/Need."<init>":(Lscala/Function0;)V
     180: astore        13
     182: aload_1
     183: aload         13
     185: invokedynamic #283,  0            // InvokeDynamic #7:apply:(Lscalaz/Need;)Lscala/Function0;
     190: aload         13
     192: invokedynamic #295,  0            // InvokeDynamic #8:apply:(Lscalaz/Need;)Lscala/Function2;
     197: aload_1
     198: aload         13
     200: invokedynamic #307,  0            // InvokeDynamic #9:apply:(Lscalaz/FingerTree;Lscalaz/Need;)Lscala/Function4;
     205: invokevirtual #311                // Method scalaz/FingerTree.fold:(Lscala/Function0;Lscala/Function2;Lscala/Function4;)Ljava/lang/Object;
     208: checkcast     #20                 // class scalaz/FingerTree
     211: aconst_null
     212: astore        12
     214: aconst_null
     215: astore        13
     217: aload_2
     218: aload         10
     220: invokedynamic #584,  0            // InvokeDynamic #28:apply:(Lscalaz/FingerTree;)Lscala/Function0;
     225: astore        14
     227: ifnonnull     232
     230: aconst_null
     231: athrow
     232: getstatic     #270                // Field scalaz/Need$.MODULE$:Lscalaz/Need$;
     235: pop
     236: new           #272                // class scalaz/Need
     239: dup
     240: aload         14
     242: invokespecial #275                // Method scalaz/Need."<init>":(Lscala/Function0;)V
     245: astore        15
     247: aload_2
     248: aload         15
     250: invokedynamic #283,  0            // InvokeDynamic #7:apply:(Lscalaz/Need;)Lscala/Function0;
     255: aload         15
     257: invokedynamic #295,  0            // InvokeDynamic #8:apply:(Lscalaz/Need;)Lscala/Function2;
     262: aload_2
     263: aload         15
     265: invokedynamic #307,  0            // InvokeDynamic #9:apply:(Lscalaz/FingerTree;Lscalaz/Need;)Lscala/Function4;
     270: invokevirtual #311                // Method scalaz/FingerTree.fold:(Lscala/Function0;Lscala/Function2;Lscala/Function4;)Ljava/lang/Object;
     273: checkcast     #20                 // class scalaz/FingerTree
     276: aconst_null
     277: astore        14
     279: aconst_null
     280: astore        15
     282: aload         11
     284: astore_3
     285: astore_2
     286: astore_1
     287: goto          0

  public static final boolean $anonfun$deleteLte$1(scalaz.Order, java.lang.Object, scalaz.PrioritySearchQueue$Summary);
    Code:
       0: getstatic     #386                // Field scalaz/syntax/order$.MODULE$:Lscalaz/syntax/order$;
       3: pop
       4: aload_2
       5: invokevirtual #522                // Method scalaz/PrioritySearchQueue$Summary.maxPrio:()Ljava/lang/Object;
       8: astore_3
       9: new           #524                // class scalaz/syntax/OrderOps
      12: dup
      13: aload_3
      14: aload_0
      15: invokespecial #527                // Method scalaz/syntax/OrderOps."<init>":(Ljava/lang/Object;Lscalaz/Order;)V
      18: aconst_null
      19: astore_3
      20: aload_1
      21: invokevirtual #592                // Method scalaz/syntax/OrderOps.$greater:(Ljava/lang/Object;)Z
      24: ireturn

  public static final boolean $anonfun$deleteLte$2(scalaz.Order, java.lang.Object, scalaz.PrioritySearchQueue$Summary);
    Code:
       0: getstatic     #386                // Field scalaz/syntax/order$.MODULE$:Lscalaz/syntax/order$;
       3: pop
       4: aload_2
       5: invokevirtual #502                // Method scalaz/PrioritySearchQueue$Summary.minPrio:()Ljava/lang/Object;
       8: astore_3
       9: new           #524                // class scalaz/syntax/OrderOps
      12: dup
      13: aload_3
      14: aload_0
      15: invokespecial #527                // Method scalaz/syntax/OrderOps."<init>":(Ljava/lang/Object;Lscalaz/Order;)V
      18: aconst_null
      19: astore_3
      20: aload_1
      21: invokevirtual #597                // Method scalaz/syntax/OrderOps.$less$eq:(Ljava/lang/Object;)Z
      24: ireturn

  public static final scalaz.FingerTree $anonfun$deleteLte$3(scalaz.FingerTree);
    Code:
       0: aload_0
       1: areturn

  private final scalaz.PrioritySearchQueue go$3(scalaz.FingerTree, scalaz.FingerTree, scalaz.Order, java.lang.Object);
    Code:
       0: aload_2
       1: invokevirtual #137                // Method scalaz/FingerTree.isEmpty:()Z
       4: ifeq          24
       7: new           #2                  // class scalaz/PrioritySearchQueue
      10: dup
      11: aload_1
      12: aload_0
      13: getfield      #313                // Field priorityOf:Lscala/Function1;
      16: aload_0
      17: getfield      #315                // Field keyOf:Lscala/Function1;
      20: invokespecial #119                // Method "<init>":(Lscalaz/FingerTree;Lscala/Function1;Lscala/Function1;)V
      23: areturn
      24: aload_2
      25: aload_3
      26: aload         4
      28: invokedynamic #605,  0            // InvokeDynamic #29:apply:(Lscalaz/Order;Ljava/lang/Object;)Lscala/Function1;
      33: invokevirtual #243                // Method scalaz/FingerTree.split:(Lscala/Function1;)Lscala/Tuple2;
      36: astore        5
      38: aload         5
      40: ifnull        56
      43: aload         5
      45: invokevirtual #251                // Method scala/Tuple2._2:()Ljava/lang/Object;
      48: checkcast     #20                 // class scalaz/FingerTree
      51: astore        6
      53: goto          65
      56: new           #184                // class scala/MatchError
      59: dup
      60: aconst_null
      61: invokespecial #187                // Method scala/MatchError."<init>":(Ljava/lang/Object;)V
      64: athrow
      65: aload         6
      67: aload_3
      68: aload         4
      70: invokedynamic #610,  0            // InvokeDynamic #30:apply:(Lscalaz/Order;Ljava/lang/Object;)Lscala/Function1;
      75: invokevirtual #243                // Method scalaz/FingerTree.split:(Lscala/Function1;)Lscala/Tuple2;
      78: astore        7
      80: aload         7
      82: ifnull        108
      85: aload         7
      87: invokevirtual #248                // Method scala/Tuple2._1:()Ljava/lang/Object;
      90: checkcast     #20                 // class scalaz/FingerTree
      93: astore        8
      95: aload         7
      97: invokevirtual #251                // Method scala/Tuple2._2:()Ljava/lang/Object;
     100: checkcast     #20                 // class scalaz/FingerTree
     103: astore        9
     105: goto          117
     108: new           #184                // class scala/MatchError
     111: dup
     112: aconst_null
     113: invokespecial #187                // Method scala/MatchError."<init>":(Ljava/lang/Object;)V
     116: athrow
     117: aload_1
     118: aload         8
     120: invokedynamic #614,  0            // InvokeDynamic #31:apply:(Lscalaz/FingerTree;)Lscala/Function0;
     125: astore        10
     127: ifnonnull     132
     130: aconst_null
     131: athrow
     132: getstatic     #270                // Field scalaz/Need$.MODULE$:Lscalaz/Need$;
     135: pop
     136: new           #272                // class scalaz/Need
     139: dup
     140: aload         10
     142: invokespecial #275                // Method scalaz/Need."<init>":(Lscala/Function0;)V
     145: astore        11
     147: aload_1
     148: aload         11
     150: invokedynamic #283,  0            // InvokeDynamic #7:apply:(Lscalaz/Need;)Lscala/Function0;
     155: aload         11
     157: invokedynamic #295,  0            // InvokeDynamic #8:apply:(Lscalaz/Need;)Lscala/Function2;
     162: aload_1
     163: aload         11
     165: invokedynamic #307,  0            // InvokeDynamic #9:apply:(Lscalaz/FingerTree;Lscalaz/Need;)Lscala/Function4;
     170: invokevirtual #311                // Method scalaz/FingerTree.fold:(Lscala/Function0;Lscala/Function2;Lscala/Function4;)Ljava/lang/Object;
     173: checkcast     #20                 // class scalaz/FingerTree
     176: aconst_null
     177: astore        10
     179: aconst_null
     180: astore        11
     182: aload         9
     184: astore_2
     185: astore_1
     186: goto          0

  public static final boolean $anonfun$splitAfterPrio$1(scalaz.Order, java.lang.Object, scalaz.PrioritySearchQueue$Summary);
    Code:
       0: getstatic     #386                // Field scalaz/syntax/order$.MODULE$:Lscalaz/syntax/order$;
       3: pop
       4: aload_2
       5: invokevirtual #522                // Method scalaz/PrioritySearchQueue$Summary.maxPrio:()Ljava/lang/Object;
       8: astore_3
       9: new           #524                // class scalaz/syntax/OrderOps
      12: dup
      13: aload_3
      14: aload_0
      15: invokespecial #527                // Method scalaz/syntax/OrderOps."<init>":(Ljava/lang/Object;Lscalaz/Order;)V
      18: aconst_null
      19: astore_3
      20: aload_1
      21: invokevirtual #592                // Method scalaz/syntax/OrderOps.$greater:(Ljava/lang/Object;)Z
      24: ireturn

  public static final boolean $anonfun$splitAfterPrio$2(scalaz.Order, java.lang.Object, scalaz.PrioritySearchQueue$Summary);
    Code:
       0: getstatic     #386                // Field scalaz/syntax/order$.MODULE$:Lscalaz/syntax/order$;
       3: pop
       4: aload_2
       5: invokevirtual #502                // Method scalaz/PrioritySearchQueue$Summary.minPrio:()Ljava/lang/Object;
       8: astore_3
       9: new           #524                // class scalaz/syntax/OrderOps
      12: dup
      13: aload_3
      14: aload_0
      15: invokespecial #527                // Method scalaz/syntax/OrderOps."<init>":(Ljava/lang/Object;Lscalaz/Order;)V
      18: aconst_null
      19: astore_3
      20: aload_1
      21: invokevirtual #597                // Method scalaz/syntax/OrderOps.$less$eq:(Ljava/lang/Object;)Z
      24: ireturn

  public static final scalaz.FingerTree $anonfun$splitAfterPrio$3(scalaz.FingerTree);
    Code:
       0: aload_0
       1: areturn

  public static final scalaz.FingerTree $anonfun$splitAfterPrio$4(scalaz.FingerTree);
    Code:
       0: aload_0
       1: areturn

  private final scala.Tuple2 go$4(scalaz.FingerTree, scalaz.FingerTree, scalaz.FingerTree, scalaz.Order, java.lang.Object);
    Code:
       0: aload_3
       1: invokevirtual #137                // Method scalaz/FingerTree.isEmpty:()Z
       4: ifeq          47
       7: new           #245                // class scala/Tuple2
      10: dup
      11: new           #2                  // class scalaz/PrioritySearchQueue
      14: dup
      15: aload_1
      16: aload_0
      17: getfield      #313                // Field priorityOf:Lscala/Function1;
      20: aload_0
      21: getfield      #315                // Field keyOf:Lscala/Function1;
      24: invokespecial #119                // Method "<init>":(Lscalaz/FingerTree;Lscala/Function1;Lscala/Function1;)V
      27: new           #2                  // class scalaz/PrioritySearchQueue
      30: dup
      31: aload_2
      32: aload_0
      33: getfield      #313                // Field priorityOf:Lscala/Function1;
      36: aload_0
      37: getfield      #315                // Field keyOf:Lscala/Function1;
      40: invokespecial #119                // Method "<init>":(Lscalaz/FingerTree;Lscala/Function1;Lscala/Function1;)V
      43: invokespecial #439                // Method scala/Tuple2."<init>":(Ljava/lang/Object;Ljava/lang/Object;)V
      46: areturn
      47: aload_3
      48: aload         4
      50: aload         5
      52: invokedynamic #631,  0            // InvokeDynamic #32:apply:(Lscalaz/Order;Ljava/lang/Object;)Lscala/Function1;
      57: invokevirtual #243                // Method scalaz/FingerTree.split:(Lscala/Function1;)Lscala/Tuple2;
      60: astore        6
      62: aload         6
      64: ifnull        90
      67: aload         6
      69: invokevirtual #248                // Method scala/Tuple2._1:()Ljava/lang/Object;
      72: checkcast     #20                 // class scalaz/FingerTree
      75: astore        7
      77: aload         6
      79: invokevirtual #251                // Method scala/Tuple2._2:()Ljava/lang/Object;
      82: checkcast     #20                 // class scalaz/FingerTree
      85: astore        8
      87: goto          99
      90: new           #184                // class scala/MatchError
      93: dup
      94: aconst_null
      95: invokespecial #187                // Method scala/MatchError."<init>":(Ljava/lang/Object;)V
      98: athrow
      99: aload         8
     101: aload         4
     103: aload         5
     105: invokedynamic #636,  0            // InvokeDynamic #33:apply:(Lscalaz/Order;Ljava/lang/Object;)Lscala/Function1;
     110: invokevirtual #243                // Method scalaz/FingerTree.split:(Lscala/Function1;)Lscala/Tuple2;
     113: astore        9
     115: aload         9
     117: ifnull        143
     120: aload         9
     122: invokevirtual #248                // Method scala/Tuple2._1:()Ljava/lang/Object;
     125: checkcast     #20                 // class scalaz/FingerTree
     128: astore        10
     130: aload         9
     132: invokevirtual #251                // Method scala/Tuple2._2:()Ljava/lang/Object;
     135: checkcast     #20                 // class scalaz/FingerTree
     138: astore        11
     140: goto          152
     143: new           #184                // class scala/MatchError
     146: dup
     147: aconst_null
     148: invokespecial #187                // Method scala/MatchError."<init>":(Ljava/lang/Object;)V
     151: athrow
     152: aload_1
     153: aload         7
     155: invokedynamic #640,  0            // InvokeDynamic #34:apply:(Lscalaz/FingerTree;)Lscala/Function0;
     160: astore        12
     162: ifnonnull     167
     165: aconst_null
     166: athrow
     167: getstatic     #270                // Field scalaz/Need$.MODULE$:Lscalaz/Need$;
     170: pop
     171: new           #272                // class scalaz/Need
     174: dup
     175: aload         12
     177: invokespecial #275                // Method scalaz/Need."<init>":(Lscala/Function0;)V
     180: astore        13
     182: aload_1
     183: aload         13
     185: invokedynamic #283,  0            // InvokeDynamic #7:apply:(Lscalaz/Need;)Lscala/Function0;
     190: aload         13
     192: invokedynamic #295,  0            // InvokeDynamic #8:apply:(Lscalaz/Need;)Lscala/Function2;
     197: aload_1
     198: aload         13
     200: invokedynamic #307,  0            // InvokeDynamic #9:apply:(Lscalaz/FingerTree;Lscalaz/Need;)Lscala/Function4;
     205: invokevirtual #311                // Method scalaz/FingerTree.fold:(Lscala/Function0;Lscala/Function2;Lscala/Function4;)Ljava/lang/Object;
     208: checkcast     #20                 // class scalaz/FingerTree
     211: aconst_null
     212: astore        12
     214: aconst_null
     215: astore        13
     217: aload_2
     218: aload         10
     220: invokedynamic #644,  0            // InvokeDynamic #35:apply:(Lscalaz/FingerTree;)Lscala/Function0;
     225: astore        14
     227: ifnonnull     232
     230: aconst_null
     231: athrow
     232: getstatic     #270                // Field scalaz/Need$.MODULE$:Lscalaz/Need$;
     235: pop
     236: new           #272                // class scalaz/Need
     239: dup
     240: aload         14
     242: invokespecial #275                // Method scalaz/Need."<init>":(Lscala/Function0;)V
     245: astore        15
     247: aload_2
     248: aload         15
     250: invokedynamic #283,  0            // InvokeDynamic #7:apply:(Lscalaz/Need;)Lscala/Function0;
     255: aload         15
     257: invokedynamic #295,  0            // InvokeDynamic #8:apply:(Lscalaz/Need;)Lscala/Function2;
     262: aload_2
     263: aload         15
     265: invokedynamic #307,  0            // InvokeDynamic #9:apply:(Lscalaz/FingerTree;Lscalaz/Need;)Lscala/Function4;
     270: invokevirtual #311                // Method scalaz/FingerTree.fold:(Lscala/Function0;Lscala/Function2;Lscala/Function4;)Ljava/lang/Object;
     273: checkcast     #20                 // class scalaz/FingerTree
     276: aconst_null
     277: astore        14
     279: aconst_null
     280: astore        15
     282: aload         11
     284: astore_3
     285: astore_2
     286: astore_1
     287: goto          0

  public static final boolean $anonfun$insert$1(scalaz.PrioritySearchQueue, scalaz.Order, java.lang.Object, scalaz.PrioritySearchQueue$Summary);
    Code:
       0: getstatic     #386                // Field scalaz/syntax/order$.MODULE$:Lscalaz/syntax/order$;
       3: pop
       4: aload_3
       5: invokevirtual #654                // Method scalaz/PrioritySearchQueue$Summary.maxKey:()Ljava/lang/Object;
       8: astore        4
      10: new           #524                // class scalaz/syntax/OrderOps
      13: dup
      14: aload         4
      16: aload_1
      17: invokespecial #527                // Method scalaz/syntax/OrderOps."<init>":(Ljava/lang/Object;Lscalaz/Order;)V
      20: aconst_null
      21: astore        4
      23: aload_0
      24: getfield      #315                // Field keyOf:Lscala/Function1;
      27: aload_2
      28: invokeinterface #172,  2          // InterfaceMethod scala/Function1.apply:(Ljava/lang/Object;)Ljava/lang/Object;
      33: invokevirtual #530                // Method scalaz/syntax/OrderOps.$greater$eq:(Ljava/lang/Object;)Z
      36: ireturn

  public static final java.lang.Object $anonfun$insert$2(java.lang.Object);
    Code:
       0: aload_0
       1: areturn

  public static final scalaz.FingerTree $anonfun$insert$3(java.lang.Object, scalaz.FingerTree);
    Code:
       0: aload_1
       1: aload_0
       2: invokevirtual #659                // Method scalaz/FingerTree.$bar$minus$colon:(Ljava/lang/Object;)Lscalaz/FingerTree;
       5: areturn

  public static final scalaz.FingerTree $anonfun$insert$4(scalaz.FingerTree);
    Code:
       0: aload_0
       1: areturn

  public static final boolean $anonfun$get$1(scalaz.Order, java.lang.Object, scalaz.PrioritySearchQueue$Summary);
    Code:
       0: getstatic     #386                // Field scalaz/syntax/order$.MODULE$:Lscalaz/syntax/order$;
       3: pop
       4: aload_2
       5: invokevirtual #654                // Method scalaz/PrioritySearchQueue$Summary.maxKey:()Ljava/lang/Object;
       8: astore_3
       9: new           #524                // class scalaz/syntax/OrderOps
      12: dup
      13: aload_3
      14: aload_0
      15: invokespecial #527                // Method scalaz/syntax/OrderOps."<init>":(Ljava/lang/Object;Lscalaz/Order;)V
      18: aconst_null
      19: astore_3
      20: aload_1
      21: invokevirtual #530                // Method scalaz/syntax/OrderOps.$greater$eq:(Ljava/lang/Object;)Z
      24: ireturn

  public static final boolean $anonfun$removeByKey$1(scalaz.Order, java.lang.Object, scalaz.PrioritySearchQueue$Summary);
    Code:
       0: getstatic     #386                // Field scalaz/syntax/order$.MODULE$:Lscalaz/syntax/order$;
       3: pop
       4: aload_2
       5: invokevirtual #654                // Method scalaz/PrioritySearchQueue$Summary.maxKey:()Ljava/lang/Object;
       8: astore_3
       9: new           #524                // class scalaz/syntax/OrderOps
      12: dup
      13: aload_3
      14: aload_0
      15: invokespecial #527                // Method scalaz/syntax/OrderOps."<init>":(Ljava/lang/Object;Lscalaz/Order;)V
      18: aconst_null
      19: astore_3
      20: aload_1
      21: invokevirtual #530                // Method scalaz/syntax/OrderOps.$greater$eq:(Ljava/lang/Object;)Z
      24: ireturn

  public static final scalaz.FingerTree $anonfun$removeByKey$2(scalaz.FingerTree);
    Code:
       0: aload_0
       1: invokevirtual #511                // Method scalaz/FingerTree.tail:()Lscalaz/FingerTree;
       4: areturn

  public static final boolean $anonfun$containsKey$1(scalaz.Order, java.lang.Object, scalaz.PrioritySearchQueue$Summary);
    Code:
       0: getstatic     #386                // Field scalaz/syntax/order$.MODULE$:Lscalaz/syntax/order$;
       3: pop
       4: aload_2
       5: invokevirtual #654                // Method scalaz/PrioritySearchQueue$Summary.maxKey:()Ljava/lang/Object;
       8: astore_3
       9: new           #524                // class scalaz/syntax/OrderOps
      12: dup
      13: aload_3
      14: aload_0
      15: invokespecial #527                // Method scalaz/syntax/OrderOps."<init>":(Ljava/lang/Object;Lscalaz/Order;)V
      18: aconst_null
      19: astore_3
      20: aload_1
      21: invokevirtual #530                // Method scalaz/syntax/OrderOps.$greater$eq:(Ljava/lang/Object;)Z
      24: ireturn

  public scalaz.PrioritySearchQueue(scalaz.FingerTree<scalaz.PrioritySearchQueue$Summary<A, P, K>, A>, scala.Function1<A, P>, scala.Function1<A, K>);
    Code:
       0: aload_0
       1: aload_1
       2: putfield      #129                // Field scalaz$PrioritySearchQueue$$tree:Lscalaz/FingerTree;
       5: aload_0
       6: aload_2
       7: putfield      #313                // Field priorityOf:Lscala/Function1;
      10: aload_0
      11: aload_3
      12: putfield      #315                // Field keyOf:Lscala/Function1;
      15: aload_0
      16: invokespecial #676                // Method java/lang/Object."<init>":()V
      19: return

  public static final java.lang.Object $anonfun$size$1$adapted(scalaz.PrioritySearchQueue$Summary);
    Code:
       0: aload_0
       1: invokestatic  #678                // Method $anonfun$size$1:(Lscalaz/PrioritySearchQueue$Summary;)I
       4: invokestatic  #201                // Method scala/runtime/BoxesRunTime.boxToInteger:(I)Ljava/lang/Integer;
       7: areturn

  public static final java.lang.Object $anonfun$deleteMin$1$adapted(scalaz.Order, scalaz.PrioritySearchQueue$Summary, scalaz.PrioritySearchQueue$Summary);
    Code:
       0: aload_0
       1: aload_1
       2: aload_2
       3: invokestatic  #680                // Method $anonfun$deleteMin$1:(Lscalaz/Order;Lscalaz/PrioritySearchQueue$Summary;Lscalaz/PrioritySearchQueue$Summary;)Z
       6: invokestatic  #684                // Method scala/runtime/BoxesRunTime.boxToBoolean:(Z)Ljava/lang/Boolean;
       9: areturn

  public static final java.lang.Object $anonfun$emptyTree$1$adapted(scalaz.PrioritySearchQueue$Summary);
    Code:
       0: aload_0
       1: invokestatic  #686                // Method $anonfun$emptyTree$1:(Lscalaz/PrioritySearchQueue$Summary;)Z
       4: invokestatic  #684                // Method scala/runtime/BoxesRunTime.boxToBoolean:(Z)Ljava/lang/Boolean;
       7: areturn

  public static final java.lang.Object $anonfun$insert$1$adapted(scalaz.PrioritySearchQueue, scalaz.Order, java.lang.Object, scalaz.PrioritySearchQueue$Summary);
    Code:
       0: aload_0
       1: aload_1
       2: aload_2
       3: aload_3
       4: invokestatic  #688                // Method $anonfun$insert$1:(Lscalaz/PrioritySearchQueue;Lscalaz/Order;Ljava/lang/Object;Lscalaz/PrioritySearchQueue$Summary;)Z
       7: invokestatic  #684                // Method scala/runtime/BoxesRunTime.boxToBoolean:(Z)Ljava/lang/Boolean;
      10: areturn

  public static final java.lang.Object $anonfun$get$1$adapted(scalaz.Order, java.lang.Object, scalaz.PrioritySearchQueue$Summary);
    Code:
       0: aload_0
       1: aload_1
       2: aload_2
       3: invokestatic  #690                // Method $anonfun$get$1:(Lscalaz/Order;Ljava/lang/Object;Lscalaz/PrioritySearchQueue$Summary;)Z
       6: invokestatic  #684                // Method scala/runtime/BoxesRunTime.boxToBoolean:(Z)Ljava/lang/Boolean;
       9: areturn

  public static final java.lang.Object $anonfun$removeByKey$1$adapted(scalaz.Order, java.lang.Object, scalaz.PrioritySearchQueue$Summary);
    Code:
       0: aload_0
       1: aload_1
       2: aload_2
       3: invokestatic  #692                // Method $anonfun$removeByKey$1:(Lscalaz/Order;Ljava/lang/Object;Lscalaz/PrioritySearchQueue$Summary;)Z
       6: invokestatic  #684                // Method scala/runtime/BoxesRunTime.boxToBoolean:(Z)Ljava/lang/Boolean;
       9: areturn

  public static final java.lang.Object $anonfun$containsKey$1$adapted(scalaz.Order, java.lang.Object, scalaz.PrioritySearchQueue$Summary);
    Code:
       0: aload_0
       1: aload_1
       2: aload_2
       3: invokestatic  #694                // Method $anonfun$containsKey$1:(Lscalaz/Order;Ljava/lang/Object;Lscalaz/PrioritySearchQueue$Summary;)Z
       6: invokestatic  #684                // Method scala/runtime/BoxesRunTime.boxToBoolean:(Z)Ljava/lang/Boolean;
       9: areturn

  public static final java.lang.Object $anonfun$deleteLt$1$adapted(scalaz.Order, java.lang.Object, scalaz.PrioritySearchQueue$Summary);
    Code:
       0: aload_0
       1: aload_1
       2: aload_2
       3: invokestatic  #696                // Method $anonfun$deleteLt$1:(Lscalaz/Order;Ljava/lang/Object;Lscalaz/PrioritySearchQueue$Summary;)Z
       6: invokestatic  #684                // Method scala/runtime/BoxesRunTime.boxToBoolean:(Z)Ljava/lang/Boolean;
       9: areturn

  public static final java.lang.Object $anonfun$deleteLt$2$adapted(scalaz.Order, java.lang.Object, scalaz.PrioritySearchQueue$Summary);
    Code:
       0: aload_0
       1: aload_1
       2: aload_2
       3: invokestatic  #698                // Method $anonfun$deleteLt$2:(Lscalaz/Order;Ljava/lang/Object;Lscalaz/PrioritySearchQueue$Summary;)Z
       6: invokestatic  #684                // Method scala/runtime/BoxesRunTime.boxToBoolean:(Z)Ljava/lang/Boolean;
       9: areturn

  public static final java.lang.Object $anonfun$splitBeforePrio$1$adapted(scalaz.Order, java.lang.Object, scalaz.PrioritySearchQueue$Summary);
    Code:
       0: aload_0
       1: aload_1
       2: aload_2
       3: invokestatic  #700                // Method $anonfun$splitBeforePrio$1:(Lscalaz/Order;Ljava/lang/Object;Lscalaz/PrioritySearchQueue$Summary;)Z
       6: invokestatic  #684                // Method scala/runtime/BoxesRunTime.boxToBoolean:(Z)Ljava/lang/Boolean;
       9: areturn

  public static final java.lang.Object $anonfun$splitBeforePrio$2$adapted(scalaz.Order, java.lang.Object, scalaz.PrioritySearchQueue$Summary);
    Code:
       0: aload_0
       1: aload_1
       2: aload_2
       3: invokestatic  #702                // Method $anonfun$splitBeforePrio$2:(Lscalaz/Order;Ljava/lang/Object;Lscalaz/PrioritySearchQueue$Summary;)Z
       6: invokestatic  #684                // Method scala/runtime/BoxesRunTime.boxToBoolean:(Z)Ljava/lang/Boolean;
       9: areturn

  public static final java.lang.Object $anonfun$deleteLte$1$adapted(scalaz.Order, java.lang.Object, scalaz.PrioritySearchQueue$Summary);
    Code:
       0: aload_0
       1: aload_1
       2: aload_2
       3: invokestatic  #704                // Method $anonfun$deleteLte$1:(Lscalaz/Order;Ljava/lang/Object;Lscalaz/PrioritySearchQueue$Summary;)Z
       6: invokestatic  #684                // Method scala/runtime/BoxesRunTime.boxToBoolean:(Z)Ljava/lang/Boolean;
       9: areturn

  public static final java.lang.Object $anonfun$deleteLte$2$adapted(scalaz.Order, java.lang.Object, scalaz.PrioritySearchQueue$Summary);
    Code:
       0: aload_0
       1: aload_1
       2: aload_2
       3: invokestatic  #706                // Method $anonfun$deleteLte$2:(Lscalaz/Order;Ljava/lang/Object;Lscalaz/PrioritySearchQueue$Summary;)Z
       6: invokestatic  #684                // Method scala/runtime/BoxesRunTime.boxToBoolean:(Z)Ljava/lang/Boolean;
       9: areturn

  public static final java.lang.Object $anonfun$splitAfterPrio$1$adapted(scalaz.Order, java.lang.Object, scalaz.PrioritySearchQueue$Summary);
    Code:
       0: aload_0
       1: aload_1
       2: aload_2
       3: invokestatic  #708                // Method $anonfun$splitAfterPrio$1:(Lscalaz/Order;Ljava/lang/Object;Lscalaz/PrioritySearchQueue$Summary;)Z
       6: invokestatic  #684                // Method scala/runtime/BoxesRunTime.boxToBoolean:(Z)Ljava/lang/Boolean;
       9: areturn

  public static final java.lang.Object $anonfun$splitAfterPrio$2$adapted(scalaz.Order, java.lang.Object, scalaz.PrioritySearchQueue$Summary);
    Code:
       0: aload_0
       1: aload_1
       2: aload_2
       3: invokestatic  #710                // Method $anonfun$splitAfterPrio$2:(Lscalaz/Order;Ljava/lang/Object;Lscalaz/PrioritySearchQueue$Summary;)Z
       6: invokestatic  #684                // Method scala/runtime/BoxesRunTime.boxToBoolean:(Z)Ljava/lang/Boolean;
       9: areturn

  private static java.lang.Object $deserializeLambda$(java.lang.invoke.SerializedLambda);
    Code:
       0: aload_0
       1: invokedynamic #722,  0            // InvokeDynamic #36:lambdaDeserialize:(Ljava/lang/invoke/SerializedLambda;)Ljava/lang/Object;
       6: areturn
}
