Compiled from "ReaderWriterStateT.scala"
public interface scalaz.ReaderWriterStateTHoist<R, W, S> extends scalaz.Hoist<?> {
  public abstract scalaz.Monoid<W> W();

  public static scalaz.NaturalTransformation hoist$(scalaz.ReaderWriterStateTHoist, scalaz.NaturalTransformation, scalaz.Monad);
    Code:
       0: aload_0
       1: aload_1
       2: aload_2
       3: invokespecial #34                 // InterfaceMethod hoist:(Lscalaz/NaturalTransformation;Lscalaz/Monad;)Lscalaz/NaturalTransformation;
       6: areturn

  public default <M, N> scalaz.NaturalTransformation<?, ?> hoist(scalaz.NaturalTransformation<M, N>, scalaz.Monad<M>);
    Code:
       0: new           #20                 // class scalaz/ReaderWriterStateTHoist$$anon$12
       3: dup
       4: aconst_null
       5: aload_1
       6: aload_2
       7: invokespecial #42                 // Method scalaz/ReaderWriterStateTHoist$$anon$12."<init>":(Lscalaz/ReaderWriterStateTHoist;Lscalaz/NaturalTransformation;Lscalaz/Monad;)V
      10: areturn

  public static scalaz.IndexedReaderWriterStateT liftM$(scalaz.ReaderWriterStateTHoist, java.lang.Object, scalaz.Monad);
    Code:
       0: aload_0
       1: aload_1
       2: aload_2
       3: invokespecial #50                 // InterfaceMethod liftM:(Ljava/lang/Object;Lscalaz/Monad;)Lscalaz/IndexedReaderWriterStateT;
       6: areturn

  public default <M, A> scalaz.IndexedReaderWriterStateT<R, W, S, S, M, A> liftM(M, scalaz.Monad<M>);
    Code:
       0: getstatic     #58                 // Field scalaz/ReaderWriterStateT$.MODULE$:Lscalaz/ReaderWriterStateT$;
       3: pop
       4: aload_0
       5: aload_2
       6: aload_1
       7: invokedynamic #77,  0             // InvokeDynamic #0:apply:(Lscalaz/ReaderWriterStateTHoist;Lscalaz/Monad;Ljava/lang/Object;)Lscala/Function2;
      12: astore_3
      13: getstatic     #82                 // Field scalaz/IndexedReaderWriterStateT$.MODULE$:Lscalaz/IndexedReaderWriterStateT$;
      16: pop
      17: aload_3
      18: invokedynamic #90,  0             // InvokeDynamic #1:apply:(Lscala/Function2;)Lscala/Function2;
      23: astore        4
      25: new           #18                 // class scalaz/IndexedReaderWriterStateT$$anon$1
      28: dup
      29: aload         4
      31: invokespecial #93                 // Method scalaz/IndexedReaderWriterStateT$$anon$1."<init>":(Lscala/Function2;)V
      34: areturn

  public static scalaz.Monad apply$(scalaz.ReaderWriterStateTHoist, scalaz.Monad);
    Code:
       0: aload_0
       1: aload_1
       2: invokespecial #102                // InterfaceMethod apply:(Lscalaz/Monad;)Lscalaz/Monad;
       5: areturn

  public default <M> scalaz.Monad<?> apply(scalaz.Monad<M>);
    Code:
       0: getstatic     #82                 // Field scalaz/IndexedReaderWriterStateT$.MODULE$:Lscalaz/IndexedReaderWriterStateT$;
       3: pop
       4: aload_0
       5: invokeinterface #105,  1          // InterfaceMethod W:()Lscalaz/Monoid;
      10: astore_2
      11: new           #22                 // class scalaz/ReaderWriterStateTInstances0$$anon$9
      14: dup
      15: aconst_null
      16: aload_1
      17: aload_2
      18: invokespecial #108                // Method scalaz/ReaderWriterStateTInstances0$$anon$9."<init>":(Lscalaz/ReaderWriterStateTInstances0;Lscalaz/Monad;Lscalaz/Monoid;)V
      21: areturn

  public static scala.Tuple3 $anonfun$liftM$2(scalaz.ReaderWriterStateTHoist, java.lang.Object, java.lang.Object);
    Code:
       0: new           #116                // class scala/Tuple3
       3: dup
       4: aload_0
       5: invokeinterface #105,  1          // InterfaceMethod W:()Lscalaz/Monoid;
      10: invokeinterface #122,  1          // InterfaceMethod scalaz/Monoid.zero:()Ljava/lang/Object;
      15: aload_2
      16: aload_1
      17: invokespecial #125                // Method scala/Tuple3."<init>":(Ljava/lang/Object;Ljava/lang/Object;Ljava/lang/Object;)V
      20: areturn

  public static java.lang.Object $anonfun$liftM$1(scalaz.ReaderWriterStateTHoist, scalaz.Monad, java.lang.Object, java.lang.Object, java.lang.Object);
    Code:
       0: aload_1
       1: aload_2
       2: aload_0
       3: aload         4
       5: invokedynamic #140,  0            // InvokeDynamic #2:apply:(Lscalaz/ReaderWriterStateTHoist;Ljava/lang/Object;)Lscala/Function1;
      10: invokeinterface #146,  3          // InterfaceMethod scalaz/Monad.map:(Ljava/lang/Object;Lscala/Function1;)Ljava/lang/Object;
      15: areturn

  public static void $init$(scalaz.ReaderWriterStateTHoist);
    Code:
       0: return

  private static java.lang.Object $deserializeLambda$(java.lang.invoke.SerializedLambda);
    Code:
       0: aload_0
       1: invokedynamic #160,  0            // InvokeDynamic #3:lambdaDeserialize:(Ljava/lang/invoke/SerializedLambda;)Ljava/lang/Object;
       6: areturn
}
