Compiled from "toplevel.scala"
public final class scalaz.StateT$ extends scalaz.StateTInstances implements scalaz.StateTFunctions {
  public static final scalaz.StateT$ MODULE$;

  public static {};
    Code:
       0: new           #2                  // class scalaz/StateT$
       3: dup
       4: invokespecial #30                 // Method "<init>":()V
       7: putstatic     #32                 // Field MODULE$:Lscalaz/StateT$;
      10: getstatic     #32                 // Field MODULE$:Lscalaz/StateT$;
      13: pop
      14: getstatic     #32                 // Field MODULE$:Lscalaz/StateT$;
      17: pop
      18: return

  public <S, F, A> scalaz.IndexedStateT<S, S, F, A> constantStateT(A, scala.Function0<S>, scalaz.Applicative<F>);
    Code:
       0: aload_0
       1: aload_1
       2: aload_2
       3: aload_3
       4: invokestatic  #42                 // InterfaceMethod scalaz/StateTFunctions.constantStateT$:(Lscalaz/StateTFunctions;Ljava/lang/Object;Lscala/Function0;Lscalaz/Applicative;)Lscalaz/IndexedStateT;
       7: areturn

  public <S, F, A> scalaz.IndexedStateT<S, S, F, A> stateT(A, scalaz.Applicative<F>);
    Code:
       0: aload_0
       1: aload_1
       2: aload_2
       3: invokestatic  #53                 // InterfaceMethod scalaz/StateTFunctions.stateT$:(Lscalaz/StateTFunctions;Ljava/lang/Object;Lscalaz/Applicative;)Lscalaz/IndexedStateT;
       6: areturn

  public <S1, S2, F, A> scalaz.IndexedStateT<S1, S2, F, A> constantIndexedStateT(A, scala.Function0<S2>, scalaz.Applicative<F>);
    Code:
       0: aload_0
       1: aload_1
       2: aload_2
       3: aload_3
       4: invokestatic  #61                 // InterfaceMethod scalaz/IndexedStateTFunctions.constantIndexedStateT$:(Lscalaz/IndexedStateTFunctions;Ljava/lang/Object;Lscala/Function0;Lscalaz/Applicative;)Lscalaz/IndexedStateT;
       7: areturn

  public <S, F, A> scalaz.IndexedStateT<S, S, F, A> apply(scala.Function1<S, F>);
    Code:
       0: getstatic     #70                 // Field scalaz/IndexedStateT$.MODULE$:Lscalaz/IndexedStateT$;
       3: pop
       4: new           #14                 // class scalaz/IndexedStateT$Wrap
       7: dup
       8: aload_1
       9: invokespecial #73                 // Method scalaz/IndexedStateT$Wrap."<init>":(Lscala/Function1;)V
      12: areturn

  public <F, S, A> scalaz.IndexedStateT<S, S, F, A> liftM(F, scalaz.Monad<F>);
    Code:
       0: getstatic     #84                 // Field scalaz/MonadTrans$.MODULE$:Lscalaz/MonadTrans$;
       3: pop
       4: new           #21                 // class scalaz/StateTInstances0$$anon$14
       7: dup
       8: aconst_null
       9: invokespecial #87                 // Method scalaz/StateTInstances0$$anon$14."<init>":(Lscalaz/StateTInstances0;)V
      12: aload_1
      13: aload_2
      14: invokestatic  #93                 // InterfaceMethod scalaz/StateTHoist.liftM$:(Lscalaz/StateTHoist;Ljava/lang/Object;Lscalaz/Monad;)Lscalaz/IndexedStateT;
      17: areturn

  public <F, G, S, A> scalaz.NaturalTransformation<?, ?> hoist(scalaz.NaturalTransformation<F, G>, scalaz.Monad<F>, scalaz.Monad<G>);
    Code:
       0: new           #19                 // class scalaz/StateT$$anon$1
       3: dup
       4: aload_1
       5: aload_2
       6: invokespecial #103                // Method scalaz/StateT$$anon$1."<init>":(Lscalaz/NaturalTransformation;Lscalaz/Monad;)V
       9: areturn

  public <F, S> scalaz.IndexedStateT<S, S, F, S> get(scalaz.Monad<F>);
    Code:
       0: getstatic     #113                // Field scalaz/MonadState$.MODULE$:Lscalaz/MonadState$;
       3: pop
       4: new           #23                 // class scalaz/StateTInstances2$$anon$12
       7: dup
       8: aconst_null
       9: aload_1
      10: invokespecial #116                // Method scalaz/StateTInstances2$$anon$12."<init>":(Lscalaz/StateTInstances2;Lscalaz/Applicative;)V
      13: invokestatic  #122                // InterfaceMethod scalaz/StateTMonadState.get$:(Lscalaz/StateTMonadState;)Lscalaz/IndexedStateT;
      16: areturn

  public <F, S, A> scalaz.IndexedStateT<S, S, F, A> gets(scala.Function1<S, A>, scalaz.Monad<F>);
    Code:
       0: getstatic     #113                // Field scalaz/MonadState$.MODULE$:Lscalaz/MonadState$;
       3: pop
       4: new           #23                 // class scalaz/StateTInstances2$$anon$12
       7: dup
       8: aconst_null
       9: aload_2
      10: invokespecial #116                // Method scalaz/StateTInstances2$$anon$12."<init>":(Lscalaz/StateTInstances2;Lscalaz/Applicative;)V
      13: astore_3
      14: aload_3
      15: aconst_null
      16: astore_3
      17: astore        4
      19: getstatic     #32                 // Field MODULE$:Lscalaz/StateT$;
      22: pop
      23: aload         4
      25: aload_1
      26: invokedynamic #144,  0            // InvokeDynamic #0:apply:(Lscalaz/StateTMonadState;Lscala/Function1;)Lscala/Function1;
      31: astore        5
      33: getstatic     #70                 // Field scalaz/IndexedStateT$.MODULE$:Lscalaz/IndexedStateT$;
      36: pop
      37: new           #14                 // class scalaz/IndexedStateT$Wrap
      40: dup
      41: aload         5
      43: invokespecial #73                 // Method scalaz/IndexedStateT$Wrap."<init>":(Lscala/Function1;)V
      46: areturn

  public <F, S> scalaz.IndexedStateT<S, S, F, scala.runtime.BoxedUnit> put(S, scalaz.Monad<F>);
    Code:
       0: getstatic     #113                // Field scalaz/MonadState$.MODULE$:Lscalaz/MonadState$;
       3: pop
       4: new           #23                 // class scalaz/StateTInstances2$$anon$12
       7: dup
       8: aconst_null
       9: aload_2
      10: invokespecial #116                // Method scalaz/StateTInstances2$$anon$12."<init>":(Lscalaz/StateTInstances2;Lscalaz/Applicative;)V
      13: aload_1
      14: invokestatic  #156                // InterfaceMethod scalaz/StateTMonadState.put$:(Lscalaz/StateTMonadState;Ljava/lang/Object;)Lscalaz/IndexedStateT;
      17: areturn

  public <F, S> scalaz.IndexedStateT<S, S, F, scala.runtime.BoxedUnit> modify(scala.Function1<S, S>, scalaz.Monad<F>);
    Code:
       0: getstatic     #113                // Field scalaz/MonadState$.MODULE$:Lscalaz/MonadState$;
       3: pop
       4: new           #23                 // class scalaz/StateTInstances2$$anon$12
       7: dup
       8: aconst_null
       9: aload_2
      10: invokespecial #116                // Method scalaz/StateTInstances2$$anon$12."<init>":(Lscalaz/StateTInstances2;Lscalaz/Applicative;)V
      13: astore_3
      14: aload_3
      15: aconst_null
      16: astore_3
      17: astore        4
      19: getstatic     #32                 // Field MODULE$:Lscalaz/StateT$;
      22: pop
      23: aload         4
      25: aload_1
      26: invokedynamic #164,  0            // InvokeDynamic #1:apply:(Lscalaz/StateTMonadState;Lscala/Function1;)Lscala/Function1;
      31: astore        5
      33: getstatic     #70                 // Field scalaz/IndexedStateT$.MODULE$:Lscalaz/IndexedStateT$;
      36: pop
      37: new           #14                 // class scalaz/IndexedStateT$Wrap
      40: dup
      41: aload         5
      43: invokespecial #73                 // Method scalaz/IndexedStateT$Wrap."<init>":(Lscala/Function1;)V
      46: areturn

  private scalaz.StateT$();
    Code:
       0: aload_0
       1: invokespecial #167                // Method scalaz/StateTInstances."<init>":()V
       4: return

  private static java.lang.Object $deserializeLambda$(java.lang.invoke.SerializedLambda);
    Code:
       0: aload_0
       1: invokedynamic #179,  0            // InvokeDynamic #2:lambdaDeserialize:(Ljava/lang/invoke/SerializedLambda;)Ljava/lang/Object;
       6: areturn
}
