Compiled from "toplevel.scala"
public final class scalaz.Writer$ {
  public static final scalaz.Writer$ MODULE$;

  public static {};
    Code:
       0: new           #2                  // class scalaz/Writer$
       3: dup
       4: invokespecial #12                 // Method "<init>":()V
       7: putstatic     #14                 // Field MODULE$:Lscalaz/Writer$;
      10: return

  public <W, A> scalaz.WriterT<W, java.lang.Object, A> apply(W, A);
    Code:
       0: new           #21                 // class scalaz/WriterT
       3: dup
       4: new           #23                 // class scala/Tuple2
       7: dup
       8: aload_1
       9: aload_2
      10: invokespecial #26                 // Method scala/Tuple2."<init>":(Ljava/lang/Object;Ljava/lang/Object;)V
      13: invokespecial #29                 // Method scalaz/WriterT."<init>":(Ljava/lang/Object;)V
      16: areturn

  private scalaz.Writer$();
    Code:
       0: aload_0
       1: invokespecial #32                 // Method java/lang/Object."<init>":()V
       4: return
}
