Compiled from "Stage.java"
class javafx.stage.Stage$2 implements com.sun.javafx.stage.StagePeerListener$StageAccessor {
  javafx.stage.Stage$2();
    Code:
       0: aload_0
       1: invokespecial #1                  // Method java/lang/Object."<init>":()V
       4: return

  public void setIconified(javafx.stage.Stage, boolean);
    Code:
       0: aload_1
       1: invokestatic  #2                  // Method javafx/stage/Stage.access$200:(Ljavafx/stage/Stage;)Ljavafx/beans/property/ReadOnlyBooleanWrapper;
       4: iload_2
       5: invokevirtual #3                  // Method javafx/beans/property/ReadOnlyBooleanWrapper.set:(Z)V
       8: return

  public void setMaximized(javafx.stage.Stage, boolean);
    Code:
       0: aload_1
       1: invokestatic  #4                  // Method javafx/stage/Stage.access$300:(Ljavafx/stage/Stage;)Ljavafx/beans/property/ReadOnlyBooleanWrapper;
       4: iload_2
       5: invokevirtual #3                  // Method javafx/beans/property/ReadOnlyBooleanWrapper.set:(Z)V
       8: return

  public void setResizable(javafx.stage.Stage, boolean);
    Code:
       0: aload_1
       1: invokevirtual #5                  // Method javafx/stage/Stage.resizableProperty:()Ljavafx/beans/property/BooleanProperty;
       4: checkcast     #6                  // class javafx/stage/Stage$ResizableProperty
       7: iload_2
       8: invokevirtual #7                  // Method javafx/stage/Stage$ResizableProperty.setNoInvalidate:(Z)V
      11: return

  public void setFullScreen(javafx.stage.Stage, boolean);
    Code:
       0: aload_1
       1: invokestatic  #8                  // Method javafx/stage/Stage.access$400:(Ljavafx/stage/Stage;)Ljavafx/beans/property/ReadOnlyBooleanWrapper;
       4: iload_2
       5: invokevirtual #3                  // Method javafx/beans/property/ReadOnlyBooleanWrapper.set:(Z)V
       8: return

  public void setAlwaysOnTop(javafx.stage.Stage, boolean);
    Code:
       0: aload_1
       1: invokestatic  #9                  // Method javafx/stage/Stage.access$500:(Ljavafx/stage/Stage;)Ljavafx/beans/property/ReadOnlyBooleanWrapper;
       4: iload_2
       5: invokevirtual #3                  // Method javafx/beans/property/ReadOnlyBooleanWrapper.set:(Z)V
       8: return
}
