Compiled from "FalsePredicate.java"
class io.undertow.predicate.FalsePredicate implements io.undertow.predicate.Predicate {
  public static final io.undertow.predicate.FalsePredicate INSTANCE;

  io.undertow.predicate.FalsePredicate();
    Code:
       0: aload_0
       1: invokespecial #1                  // Method java/lang/Object."<init>":()V
       4: return

  public static io.undertow.predicate.FalsePredicate instance();
    Code:
       0: getstatic     #2                  // Field INSTANCE:Lio/undertow/predicate/FalsePredicate;
       3: areturn

  public boolean resolve(io.undertow.server.HttpServerExchange);
    Code:
       0: iconst_0
       1: ireturn

  static {};
    Code:
       0: new           #3                  // class io/undertow/predicate/FalsePredicate
       3: dup
       4: invokespecial #4                  // Method "<init>":()V
       7: putstatic     #2                  // Field INSTANCE:Lio/undertow/predicate/FalsePredicate;
      10: return
}
