Compiled from "PrimitiveWrapperHelper.java"
public class org.hibernate.internal.util.type.PrimitiveWrapperHelper$DoubleDescriptor implements org.hibernate.internal.util.type.PrimitiveWrapperHelper$PrimitiveWrapperDescriptor<java.lang.Double> {
  public static final org.hibernate.internal.util.type.PrimitiveWrapperHelper$DoubleDescriptor INSTANCE;

  private org.hibernate.internal.util.type.PrimitiveWrapperHelper$DoubleDescriptor();
    Code:
       0: aload_0
       1: invokespecial #1                  // Method java/lang/Object."<init>":()V
       4: return

  public java.lang.Class<java.lang.Double> getPrimitiveClass();
    Code:
       0: getstatic     #2                  // Field java/lang/Double.TYPE:Ljava/lang/Class;
       3: areturn

  public java.lang.Class<java.lang.Double> getWrapperClass();
    Code:
       0: ldc           #3                  // class java/lang/Double
       2: areturn

  static {};
    Code:
       0: new           #4                  // class org/hibernate/internal/util/type/PrimitiveWrapperHelper$DoubleDescriptor
       3: dup
       4: invokespecial #5                  // Method "<init>":()V
       7: putstatic     #6                  // Field INSTANCE:Lorg/hibernate/internal/util/type/PrimitiveWrapperHelper$DoubleDescriptor;
      10: return
}
