Compiled from "MapEntryNode.java"
public class org.hibernate.hql.internal.ast.tree.MapEntryNode extends org.hibernate.hql.internal.ast.tree.AbstractMapComponentNode implements org.hibernate.hql.internal.ast.tree.AggregatedSelectExpression {
  private int scalarColumnIndex;

  private java.util.List types;

  private static final java.lang.String[] ALIASES;

  private org.hibernate.hql.internal.ast.tree.MapEntryNode$MapEntryBuilder mapEntryBuilder;

  public org.hibernate.hql.internal.ast.tree.MapEntryNode();
    Code:
       0: aload_0
       1: invokespecial #1                  // Method org/hibernate/hql/internal/ast/tree/AbstractMapComponentNode."<init>":()V
       4: aload_0
       5: iconst_m1
       6: putfield      #2                  // Field scalarColumnIndex:I
       9: aload_0
      10: new           #3                  // class java/util/ArrayList
      13: dup
      14: iconst_4
      15: invokespecial #4                  // Method java/util/ArrayList."<init>":(I)V
      18: putfield      #5                  // Field types:Ljava/util/List;
      21: return

  protected java.lang.String expressionDescription();
    Code:
       0: ldc           #6                  // String entry(*)
       2: areturn

  public java.lang.Class getAggregationResultType();
    Code:
       0: ldc           #7                  // class java/util/Map$Entry
       2: areturn

  public void resolve(boolean, boolean, java.lang.String, antlr.collections.AST, antlr.collections.AST) throws antlr.SemanticException;
    Code:
       0: aload         4
       2: ifnull        35
       5: new           #8                  // class antlr/SemanticException
       8: dup
       9: new           #9                  // class java/lang/StringBuilder
      12: dup
      13: invokespecial #10                 // Method java/lang/StringBuilder."<init>":()V
      16: aload_0
      17: invokevirtual #11                 // Method expressionDescription:()Ljava/lang/String;
      20: invokevirtual #12                 // Method java/lang/StringBuilder.append:(Ljava/lang/String;)Ljava/lang/StringBuilder;
      23: ldc           #13                 // String  expression cannot be further de-referenced
      25: invokevirtual #12                 // Method java/lang/StringBuilder.append:(Ljava/lang/String;)Ljava/lang/StringBuilder;
      28: invokevirtual #14                 // Method java/lang/StringBuilder.toString:()Ljava/lang/String;
      31: invokespecial #15                 // Method antlr/SemanticException."<init>":(Ljava/lang/String;)V
      34: athrow
      35: aload_0
      36: iload_1
      37: iload_2
      38: aload_3
      39: aload         4
      41: aload         5
      43: invokespecial #16                 // Method org/hibernate/hql/internal/ast/tree/AbstractMapComponentNode.resolve:(ZZLjava/lang/String;Lantlr/collections/AST;Lantlr/collections/AST;)V
      46: return

  protected org.hibernate.type.Type resolveType(org.hibernate.persister.collection.QueryableCollection);
    Code:
       0: aload_1
       1: invokeinterface #17,  1           // InterfaceMethod org/hibernate/persister/collection/QueryableCollection.getIndexType:()Lorg/hibernate/type/Type;
       6: astore_2
       7: aload_1
       8: invokeinterface #18,  1           // InterfaceMethod org/hibernate/persister/collection/QueryableCollection.getElementType:()Lorg/hibernate/type/Type;
      13: astore_3
      14: aload_0
      15: getfield      #5                  // Field types:Ljava/util/List;
      18: aload_2
      19: invokeinterface #19,  2           // InterfaceMethod java/util/List.add:(Ljava/lang/Object;)Z
      24: pop
      25: aload_0
      26: getfield      #5                  // Field types:Ljava/util/List;
      29: aload_3
      30: invokeinterface #19,  2           // InterfaceMethod java/util/List.add:(Ljava/lang/Object;)Z
      35: pop
      36: aload_0
      37: new           #20                 // class org/hibernate/hql/internal/ast/tree/MapEntryNode$MapEntryBuilder
      40: dup
      41: aconst_null
      42: invokespecial #21                 // Method org/hibernate/hql/internal/ast/tree/MapEntryNode$MapEntryBuilder."<init>":(Lorg/hibernate/hql/internal/ast/tree/MapEntryNode$1;)V
      45: putfield      #22                 // Field mapEntryBuilder:Lorg/hibernate/hql/internal/ast/tree/MapEntryNode$MapEntryBuilder;
      48: aconst_null
      49: areturn

  protected java.lang.String[] resolveColumns(org.hibernate.persister.collection.QueryableCollection);
    Code:
       0: new           #3                  // class java/util/ArrayList
       3: dup
       4: invokespecial #23                 // Method java/util/ArrayList."<init>":()V
       7: astore_2
       8: aload_0
       9: aload_1
      10: aload_2
      11: invokespecial #24                 // Method determineKeySelectExpressions:(Lorg/hibernate/persister/collection/QueryableCollection;Ljava/util/List;)V
      14: aload_0
      15: aload_1
      16: aload_2
      17: invokespecial #25                 // Method determineValueSelectExpressions:(Lorg/hibernate/persister/collection/QueryableCollection;Ljava/util/List;)V
      20: ldc           #26                 // String
      22: astore_3
      23: aload_2
      24: invokeinterface #27,  1           // InterfaceMethod java/util/List.size:()I
      29: anewarray     #28                 // class java/lang/String
      32: astore        4
      34: iconst_0
      35: istore        5
      37: iload         5
      39: aload_2
      40: invokeinterface #27,  1           // InterfaceMethod java/util/List.size:()I
      45: if_icmpge     124
      48: aload_2
      49: iload         5
      51: invokeinterface #29,  2           // InterfaceMethod java/util/List.get:(I)Ljava/lang/Object;
      56: checkcast     #30                 // class org/hibernate/sql/SelectExpression
      59: astore        6
      61: new           #9                  // class java/lang/StringBuilder
      64: dup
      65: invokespecial #10                 // Method java/lang/StringBuilder."<init>":()V
      68: aload_3
      69: invokevirtual #12                 // Method java/lang/StringBuilder.append:(Ljava/lang/String;)Ljava/lang/StringBuilder;
      72: ldc           #31                 // String ,
      74: invokevirtual #12                 // Method java/lang/StringBuilder.append:(Ljava/lang/String;)Ljava/lang/StringBuilder;
      77: aload         6
      79: invokeinterface #32,  1           // InterfaceMethod org/hibernate/sql/SelectExpression.getExpression:()Ljava/lang/String;
      84: invokevirtual #12                 // Method java/lang/StringBuilder.append:(Ljava/lang/String;)Ljava/lang/StringBuilder;
      87: ldc           #33                 // String  as
      89: invokevirtual #12                 // Method java/lang/StringBuilder.append:(Ljava/lang/String;)Ljava/lang/StringBuilder;
      92: aload         6
      94: invokeinterface #34,  1           // InterfaceMethod org/hibernate/sql/SelectExpression.getAlias:()Ljava/lang/String;
      99: invokevirtual #12                 // Method java/lang/StringBuilder.append:(Ljava/lang/String;)Ljava/lang/StringBuilder;
     102: invokevirtual #14                 // Method java/lang/StringBuilder.toString:()Ljava/lang/String;
     105: astore_3
     106: aload         4
     108: iload         5
     110: aload         6
     112: invokeinterface #32,  1           // InterfaceMethod org/hibernate/sql/SelectExpression.getExpression:()Ljava/lang/String;
     117: aastore
     118: iinc          5, 1
     121: goto          37
     124: aload_3
     125: iconst_2
     126: invokevirtual #35                 // Method java/lang/String.substring:(I)Ljava/lang/String;
     129: astore_3
     130: aload_0
     131: aload_3
     132: invokevirtual #36                 // Method setText:(Ljava/lang/String;)V
     135: aload_0
     136: invokevirtual #37                 // Method setResolved:()V
     139: aload         4
     141: areturn

  private void determineKeySelectExpressions(org.hibernate.persister.collection.QueryableCollection, java.util.List);
    Code:
       0: new           #38                 // class org/hibernate/hql/internal/ast/tree/MapEntryNode$LocalAliasGenerator
       3: dup
       4: iconst_0
       5: aconst_null
       6: invokespecial #39                 // Method org/hibernate/hql/internal/ast/tree/MapEntryNode$LocalAliasGenerator."<init>":(ILorg/hibernate/hql/internal/ast/tree/MapEntryNode$1;)V
       9: astore_3
      10: aload_0
      11: aload_1
      12: invokeinterface #40,  1           // InterfaceMethod org/hibernate/persister/collection/QueryableCollection.getIndexColumnNames:()[Ljava/lang/String;
      17: aload_2
      18: aload_3
      19: invokespecial #41                 // Method appendSelectExpressions:([Ljava/lang/String;Ljava/util/List;Lorg/hibernate/sql/AliasGenerator;)V
      22: aload_1
      23: invokeinterface #17,  1           // InterfaceMethod org/hibernate/persister/collection/QueryableCollection.getIndexType:()Lorg/hibernate/type/Type;
      28: astore        4
      30: aload         4
      32: invokeinterface #42,  1           // InterfaceMethod org/hibernate/type/Type.isEntityType:()Z
      37: ifeq          78
      40: aload_0
      41: aload_1
      42: invokevirtual #43                 // Method findOrAddMapKeyEntityFromElement:(Lorg/hibernate/persister/collection/QueryableCollection;)Lorg/hibernate/hql/internal/ast/tree/MapKeyEntityFromElement;
      45: astore        5
      47: aload         5
      49: invokevirtual #44                 // Method org/hibernate/hql/internal/ast/tree/MapKeyEntityFromElement.getQueryable:()Lorg/hibernate/persister/entity/Queryable;
      52: astore        6
      54: aload         6
      56: aload         5
      58: invokevirtual #45                 // Method org/hibernate/hql/internal/ast/tree/MapKeyEntityFromElement.getTableAlias:()Ljava/lang/String;
      61: aconst_null
      62: iconst_0
      63: invokeinterface #46,  4           // InterfaceMethod org/hibernate/persister/entity/Queryable.propertySelectFragmentFragment:(Ljava/lang/String;Ljava/lang/String;Z)Lorg/hibernate/sql/SelectFragment;
      68: astore        7
      70: aload_0
      71: aload         7
      73: aload_2
      74: aload_3
      75: invokespecial #47                 // Method appendSelectExpressions:(Lorg/hibernate/sql/SelectFragment;Ljava/util/List;Lorg/hibernate/sql/AliasGenerator;)V
      78: return

  private void appendSelectExpressions(java.lang.String[], java.util.List, org.hibernate.sql.AliasGenerator);
    Code:
       0: iconst_0
       1: istore        4
       3: iload         4
       5: aload_1
       6: arraylength
       7: if_icmpge     70
      10: aload_2
      11: new           #48                 // class org/hibernate/hql/internal/ast/tree/MapEntryNode$BasicSelectExpression
      14: dup
      15: new           #9                  // class java/lang/StringBuilder
      18: dup
      19: invokespecial #10                 // Method java/lang/StringBuilder."<init>":()V
      22: aload_0
      23: invokespecial #49                 // Method collectionTableAlias:()Ljava/lang/String;
      26: invokevirtual #12                 // Method java/lang/StringBuilder.append:(Ljava/lang/String;)Ljava/lang/StringBuilder;
      29: bipush        46
      31: invokevirtual #50                 // Method java/lang/StringBuilder.append:(C)Ljava/lang/StringBuilder;
      34: aload_1
      35: iload         4
      37: aaload
      38: invokevirtual #12                 // Method java/lang/StringBuilder.append:(Ljava/lang/String;)Ljava/lang/StringBuilder;
      41: invokevirtual #14                 // Method java/lang/StringBuilder.toString:()Ljava/lang/String;
      44: aload_3
      45: aload_1
      46: iload         4
      48: aaload
      49: invokeinterface #51,  2           // InterfaceMethod org/hibernate/sql/AliasGenerator.generateAlias:(Ljava/lang/String;)Ljava/lang/String;
      54: aconst_null
      55: invokespecial #52                 // Method org/hibernate/hql/internal/ast/tree/MapEntryNode$BasicSelectExpression."<init>":(Ljava/lang/String;Ljava/lang/String;Lorg/hibernate/hql/internal/ast/tree/MapEntryNode$1;)V
      58: invokeinterface #19,  2           // InterfaceMethod java/util/List.add:(Ljava/lang/Object;)Z
      63: pop
      64: iinc          4, 1
      67: goto          3
      70: return

  private void appendSelectExpressions(org.hibernate.sql.SelectFragment, java.util.List, org.hibernate.sql.AliasGenerator);
    Code:
       0: aload_1
       1: invokevirtual #53                 // Method org/hibernate/sql/SelectFragment.getColumns:()Ljava/util/List;
       4: invokeinterface #54,  1           // InterfaceMethod java/util/List.iterator:()Ljava/util/Iterator;
       9: astore        4
      11: aload         4
      13: invokeinterface #55,  1           // InterfaceMethod java/util/Iterator.hasNext:()Z
      18: ifeq          61
      21: aload         4
      23: invokeinterface #56,  1           // InterfaceMethod java/util/Iterator.next:()Ljava/lang/Object;
      28: checkcast     #28                 // class java/lang/String
      31: astore        5
      33: aload_2
      34: new           #48                 // class org/hibernate/hql/internal/ast/tree/MapEntryNode$BasicSelectExpression
      37: dup
      38: aload         5
      40: aload_3
      41: aload         5
      43: invokeinterface #51,  2           // InterfaceMethod org/hibernate/sql/AliasGenerator.generateAlias:(Ljava/lang/String;)Ljava/lang/String;
      48: aconst_null
      49: invokespecial #52                 // Method org/hibernate/hql/internal/ast/tree/MapEntryNode$BasicSelectExpression."<init>":(Ljava/lang/String;Ljava/lang/String;Lorg/hibernate/hql/internal/ast/tree/MapEntryNode$1;)V
      52: invokeinterface #19,  2           // InterfaceMethod java/util/List.add:(Ljava/lang/Object;)Z
      57: pop
      58: goto          11
      61: return

  private void determineValueSelectExpressions(org.hibernate.persister.collection.QueryableCollection, java.util.List);
    Code:
       0: new           #38                 // class org/hibernate/hql/internal/ast/tree/MapEntryNode$LocalAliasGenerator
       3: dup
       4: iconst_1
       5: aconst_null
       6: invokespecial #39                 // Method org/hibernate/hql/internal/ast/tree/MapEntryNode$LocalAliasGenerator."<init>":(ILorg/hibernate/hql/internal/ast/tree/MapEntryNode$1;)V
       9: astore_3
      10: aload_0
      11: aload_1
      12: invokeinterface #57,  1           // InterfaceMethod org/hibernate/persister/collection/QueryableCollection.getElementColumnNames:()[Ljava/lang/String;
      17: aload_2
      18: aload_3
      19: invokespecial #41                 // Method appendSelectExpressions:([Ljava/lang/String;Ljava/util/List;Lorg/hibernate/sql/AliasGenerator;)V
      22: aload_1
      23: invokeinterface #18,  1           // InterfaceMethod org/hibernate/persister/collection/QueryableCollection.getElementType:()Lorg/hibernate/type/Type;
      28: astore        4
      30: aload         4
      32: invokeinterface #58,  1           // InterfaceMethod org/hibernate/type/Type.isAssociationType:()Z
      37: ifeq          93
      40: aload         4
      42: checkcast     #59                 // class org/hibernate/type/EntityType
      45: astore        5
      47: aload_0
      48: invokevirtual #60                 // Method sfi:()Lorg/hibernate/engine/spi/SessionFactoryImplementor;
      51: aload         5
      53: aload_0
      54: invokevirtual #60                 // Method sfi:()Lorg/hibernate/engine/spi/SessionFactoryImplementor;
      57: invokevirtual #61                 // Method org/hibernate/type/EntityType.getAssociatedEntityName:(Lorg/hibernate/engine/spi/SessionFactoryImplementor;)Ljava/lang/String;
      60: invokeinterface #62,  2           // InterfaceMethod org/hibernate/engine/spi/SessionFactoryImplementor.getEntityPersister:(Ljava/lang/String;)Lorg/hibernate/persister/entity/EntityPersister;
      65: checkcast     #63                 // class org/hibernate/persister/entity/Queryable
      68: astore        6
      70: aload         6
      72: aload_0
      73: invokespecial #64                 // Method elementTableAlias:()Ljava/lang/String;
      76: aconst_null
      77: iconst_0
      78: invokeinterface #46,  4           // InterfaceMethod org/hibernate/persister/entity/Queryable.propertySelectFragmentFragment:(Ljava/lang/String;Ljava/lang/String;Z)Lorg/hibernate/sql/SelectFragment;
      83: astore        7
      85: aload_0
      86: aload         7
      88: aload_2
      89: aload_3
      90: invokespecial #47                 // Method appendSelectExpressions:(Lorg/hibernate/sql/SelectFragment;Ljava/util/List;Lorg/hibernate/sql/AliasGenerator;)V
      93: return

  private java.lang.String collectionTableAlias();
    Code:
       0: aload_0
       1: invokevirtual #65                 // Method getFromElement:()Lorg/hibernate/hql/internal/ast/tree/FromElement;
       4: invokevirtual #66                 // Method org/hibernate/hql/internal/ast/tree/FromElement.getCollectionTableAlias:()Ljava/lang/String;
       7: ifnull        20
      10: aload_0
      11: invokevirtual #65                 // Method getFromElement:()Lorg/hibernate/hql/internal/ast/tree/FromElement;
      14: invokevirtual #66                 // Method org/hibernate/hql/internal/ast/tree/FromElement.getCollectionTableAlias:()Ljava/lang/String;
      17: goto          27
      20: aload_0
      21: invokevirtual #65                 // Method getFromElement:()Lorg/hibernate/hql/internal/ast/tree/FromElement;
      24: invokevirtual #67                 // Method org/hibernate/hql/internal/ast/tree/FromElement.getTableAlias:()Ljava/lang/String;
      27: areturn

  private java.lang.String elementTableAlias();
    Code:
       0: aload_0
       1: invokevirtual #65                 // Method getFromElement:()Lorg/hibernate/hql/internal/ast/tree/FromElement;
       4: invokevirtual #67                 // Method org/hibernate/hql/internal/ast/tree/FromElement.getTableAlias:()Ljava/lang/String;
       7: areturn

  public org.hibernate.engine.spi.SessionFactoryImplementor sfi();
    Code:
       0: aload_0
       1: invokevirtual #68                 // Method getSessionFactoryHelper:()Lorg/hibernate/hql/internal/ast/util/SessionFactoryHelper;
       4: invokevirtual #69                 // Method org/hibernate/hql/internal/ast/util/SessionFactoryHelper.getFactory:()Lorg/hibernate/engine/spi/SessionFactoryImplementor;
       7: areturn

  public void setText(java.lang.String);
    Code:
       0: aload_0
       1: invokevirtual #70                 // Method isResolved:()Z
       4: ifeq          8
       7: return
       8: aload_0
       9: aload_1
      10: invokespecial #71                 // Method org/hibernate/hql/internal/ast/tree/AbstractMapComponentNode.setText:(Ljava/lang/String;)V
      13: return

  public void setScalarColumn(int) throws antlr.SemanticException;
    Code:
       0: aload_0
       1: iload_1
       2: putfield      #2                  // Field scalarColumnIndex:I
       5: return

  public int getScalarColumnIndex();
    Code:
       0: aload_0
       1: getfield      #2                  // Field scalarColumnIndex:I
       4: ireturn

  public void setScalarColumnText(int) throws antlr.SemanticException;
    Code:
       0: return

  public boolean isScalar();
    Code:
       0: iconst_1
       1: ireturn

  public java.util.List getAggregatedSelectionTypeList();
    Code:
       0: aload_0
       1: getfield      #5                  // Field types:Ljava/util/List;
       4: areturn

  public java.lang.String[] getAggregatedAliases();
    Code:
       0: getstatic     #72                 // Field ALIASES:[Ljava/lang/String;
       3: areturn

  public org.hibernate.transform.ResultTransformer getResultTransformer();
    Code:
       0: aload_0
       1: getfield      #22                 // Field mapEntryBuilder:Lorg/hibernate/hql/internal/ast/tree/MapEntryNode$MapEntryBuilder;
       4: areturn

  static {};
    Code:
       0: iconst_2
       1: anewarray     #28                 // class java/lang/String
       4: dup
       5: iconst_0
       6: aconst_null
       7: aastore
       8: dup
       9: iconst_1
      10: aconst_null
      11: aastore
      12: putstatic     #72                 // Field ALIASES:[Ljava/lang/String;
      15: return
}
