Compiled from "UaObjectNode.java"
public class org.eclipse.milo.opcua.sdk.client.nodes.UaObjectNode extends org.eclipse.milo.opcua.sdk.client.nodes.UaNode implements org.eclipse.milo.opcua.sdk.client.api.nodes.ObjectNode {
  public org.eclipse.milo.opcua.sdk.client.nodes.UaObjectNode(org.eclipse.milo.opcua.sdk.client.OpcUaClient, org.eclipse.milo.opcua.stack.core.types.builtin.NodeId);
    Code:
       0: aload_0
       1: aload_1
       2: aload_2
       3: invokespecial #1                  // Method org/eclipse/milo/opcua/sdk/client/nodes/UaNode."<init>":(Lorg/eclipse/milo/opcua/sdk/client/OpcUaClient;Lorg/eclipse/milo/opcua/stack/core/types/builtin/NodeId;)V
       6: return

  public java.util.concurrent.CompletableFuture<? extends org.eclipse.milo.opcua.sdk.client.api.nodes.Node> getComponent(org.eclipse.milo.opcua.stack.core.types.builtin.QualifiedName);
    Code:
       0: getstatic     #2                  // Field org/eclipse/milo/opcua/stack/core/types/enumerated/NodeClass.Object:Lorg/eclipse/milo/opcua/stack/core/types/enumerated/NodeClass;
       3: invokevirtual #3                  // Method org/eclipse/milo/opcua/stack/core/types/enumerated/NodeClass.getValue:()I
       6: getstatic     #4                  // Field org/eclipse/milo/opcua/stack/core/types/enumerated/NodeClass.Variable:Lorg/eclipse/milo/opcua/stack/core/types/enumerated/NodeClass;
       9: invokevirtual #3                  // Method org/eclipse/milo/opcua/stack/core/types/enumerated/NodeClass.getValue:()I
      12: ior
      13: invokestatic  #5                  // Method org/eclipse/milo/opcua/stack/core/types/builtin/unsigned/Unsigned.uint:(I)Lorg/eclipse/milo/opcua/stack/core/types/builtin/unsigned/UInteger;
      16: astore_2
      17: getstatic     #6                  // Field org/eclipse/milo/opcua/stack/core/types/enumerated/BrowseResultMask.All:Lorg/eclipse/milo/opcua/stack/core/types/enumerated/BrowseResultMask;
      20: invokevirtual #7                  // Method org/eclipse/milo/opcua/stack/core/types/enumerated/BrowseResultMask.getValue:()I
      23: invokestatic  #5                  // Method org/eclipse/milo/opcua/stack/core/types/builtin/unsigned/Unsigned.uint:(I)Lorg/eclipse/milo/opcua/stack/core/types/builtin/unsigned/UInteger;
      26: astore_3
      27: aload_0
      28: getfield      #8                  // Field client:Lorg/eclipse/milo/opcua/sdk/client/OpcUaClient;
      31: new           #9                  // class org/eclipse/milo/opcua/stack/core/types/structured/BrowseDescription
      34: dup
      35: aload_0
      36: getfield      #10                 // Field nodeId:Lorg/eclipse/milo/opcua/stack/core/types/builtin/NodeId;
      39: getstatic     #11                 // Field org/eclipse/milo/opcua/stack/core/types/enumerated/BrowseDirection.Forward:Lorg/eclipse/milo/opcua/stack/core/types/enumerated/BrowseDirection;
      42: getstatic     #12                 // Field org/eclipse/milo/opcua/stack/core/Identifiers.HasComponent:Lorg/eclipse/milo/opcua/stack/core/types/builtin/NodeId;
      45: iconst_0
      46: invokestatic  #13                 // Method java/lang/Boolean.valueOf:(Z)Ljava/lang/Boolean;
      49: aload_2
      50: aload_3
      51: invokespecial #14                 // Method org/eclipse/milo/opcua/stack/core/types/structured/BrowseDescription."<init>":(Lorg/eclipse/milo/opcua/stack/core/types/builtin/NodeId;Lorg/eclipse/milo/opcua/stack/core/types/enumerated/BrowseDirection;Lorg/eclipse/milo/opcua/stack/core/types/builtin/NodeId;Ljava/lang/Boolean;Lorg/eclipse/milo/opcua/stack/core/types/builtin/unsigned/UInteger;Lorg/eclipse/milo/opcua/stack/core/types/builtin/unsigned/UInteger;)V
      54: invokevirtual #15                 // Method org/eclipse/milo/opcua/sdk/client/OpcUaClient.browse:(Lorg/eclipse/milo/opcua/stack/core/types/structured/BrowseDescription;)Ljava/util/concurrent/CompletableFuture;
      57: astore        4
      59: aload         4
      61: aload_0
      62: aload_1
      63: invokedynamic #16,  0             // InvokeDynamic #0:apply:(Lorg/eclipse/milo/opcua/sdk/client/nodes/UaObjectNode;Lorg/eclipse/milo/opcua/stack/core/types/builtin/QualifiedName;)Ljava/util/function/Function;
      68: invokevirtual #17                 // Method java/util/concurrent/CompletableFuture.thenCompose:(Ljava/util/function/Function;)Ljava/util/concurrent/CompletableFuture;
      71: areturn

  public java.util.concurrent.CompletableFuture<? extends org.eclipse.milo.opcua.sdk.client.api.nodes.ObjectNode> getObjectComponent(org.eclipse.milo.opcua.stack.core.types.builtin.QualifiedName);
    Code:
       0: getstatic     #2                  // Field org/eclipse/milo/opcua/stack/core/types/enumerated/NodeClass.Object:Lorg/eclipse/milo/opcua/stack/core/types/enumerated/NodeClass;
       3: invokevirtual #3                  // Method org/eclipse/milo/opcua/stack/core/types/enumerated/NodeClass.getValue:()I
       6: invokestatic  #5                  // Method org/eclipse/milo/opcua/stack/core/types/builtin/unsigned/Unsigned.uint:(I)Lorg/eclipse/milo/opcua/stack/core/types/builtin/unsigned/UInteger;
       9: astore_2
      10: getstatic     #6                  // Field org/eclipse/milo/opcua/stack/core/types/enumerated/BrowseResultMask.All:Lorg/eclipse/milo/opcua/stack/core/types/enumerated/BrowseResultMask;
      13: invokevirtual #7                  // Method org/eclipse/milo/opcua/stack/core/types/enumerated/BrowseResultMask.getValue:()I
      16: invokestatic  #5                  // Method org/eclipse/milo/opcua/stack/core/types/builtin/unsigned/Unsigned.uint:(I)Lorg/eclipse/milo/opcua/stack/core/types/builtin/unsigned/UInteger;
      19: astore_3
      20: aload_0
      21: getfield      #8                  // Field client:Lorg/eclipse/milo/opcua/sdk/client/OpcUaClient;
      24: new           #9                  // class org/eclipse/milo/opcua/stack/core/types/structured/BrowseDescription
      27: dup
      28: aload_0
      29: getfield      #10                 // Field nodeId:Lorg/eclipse/milo/opcua/stack/core/types/builtin/NodeId;
      32: getstatic     #11                 // Field org/eclipse/milo/opcua/stack/core/types/enumerated/BrowseDirection.Forward:Lorg/eclipse/milo/opcua/stack/core/types/enumerated/BrowseDirection;
      35: getstatic     #12                 // Field org/eclipse/milo/opcua/stack/core/Identifiers.HasComponent:Lorg/eclipse/milo/opcua/stack/core/types/builtin/NodeId;
      38: iconst_0
      39: invokestatic  #13                 // Method java/lang/Boolean.valueOf:(Z)Ljava/lang/Boolean;
      42: aload_2
      43: aload_3
      44: invokespecial #14                 // Method org/eclipse/milo/opcua/stack/core/types/structured/BrowseDescription."<init>":(Lorg/eclipse/milo/opcua/stack/core/types/builtin/NodeId;Lorg/eclipse/milo/opcua/stack/core/types/enumerated/BrowseDirection;Lorg/eclipse/milo/opcua/stack/core/types/builtin/NodeId;Ljava/lang/Boolean;Lorg/eclipse/milo/opcua/stack/core/types/builtin/unsigned/UInteger;Lorg/eclipse/milo/opcua/stack/core/types/builtin/unsigned/UInteger;)V
      47: invokevirtual #15                 // Method org/eclipse/milo/opcua/sdk/client/OpcUaClient.browse:(Lorg/eclipse/milo/opcua/stack/core/types/structured/BrowseDescription;)Ljava/util/concurrent/CompletableFuture;
      50: astore        4
      52: aload         4
      54: aload_0
      55: aload_1
      56: invokedynamic #18,  0             // InvokeDynamic #1:apply:(Lorg/eclipse/milo/opcua/sdk/client/nodes/UaObjectNode;Lorg/eclipse/milo/opcua/stack/core/types/builtin/QualifiedName;)Ljava/util/function/Function;
      61: invokevirtual #17                 // Method java/util/concurrent/CompletableFuture.thenCompose:(Ljava/util/function/Function;)Ljava/util/concurrent/CompletableFuture;
      64: areturn

  public java.util.concurrent.CompletableFuture<? extends org.eclipse.milo.opcua.sdk.client.api.nodes.VariableNode> getVariableComponent(org.eclipse.milo.opcua.stack.core.types.builtin.QualifiedName);
    Code:
       0: getstatic     #4                  // Field org/eclipse/milo/opcua/stack/core/types/enumerated/NodeClass.Variable:Lorg/eclipse/milo/opcua/stack/core/types/enumerated/NodeClass;
       3: invokevirtual #3                  // Method org/eclipse/milo/opcua/stack/core/types/enumerated/NodeClass.getValue:()I
       6: invokestatic  #5                  // Method org/eclipse/milo/opcua/stack/core/types/builtin/unsigned/Unsigned.uint:(I)Lorg/eclipse/milo/opcua/stack/core/types/builtin/unsigned/UInteger;
       9: astore_2
      10: getstatic     #6                  // Field org/eclipse/milo/opcua/stack/core/types/enumerated/BrowseResultMask.All:Lorg/eclipse/milo/opcua/stack/core/types/enumerated/BrowseResultMask;
      13: invokevirtual #7                  // Method org/eclipse/milo/opcua/stack/core/types/enumerated/BrowseResultMask.getValue:()I
      16: invokestatic  #5                  // Method org/eclipse/milo/opcua/stack/core/types/builtin/unsigned/Unsigned.uint:(I)Lorg/eclipse/milo/opcua/stack/core/types/builtin/unsigned/UInteger;
      19: astore_3
      20: aload_0
      21: getfield      #8                  // Field client:Lorg/eclipse/milo/opcua/sdk/client/OpcUaClient;
      24: new           #9                  // class org/eclipse/milo/opcua/stack/core/types/structured/BrowseDescription
      27: dup
      28: aload_0
      29: getfield      #10                 // Field nodeId:Lorg/eclipse/milo/opcua/stack/core/types/builtin/NodeId;
      32: getstatic     #11                 // Field org/eclipse/milo/opcua/stack/core/types/enumerated/BrowseDirection.Forward:Lorg/eclipse/milo/opcua/stack/core/types/enumerated/BrowseDirection;
      35: getstatic     #12                 // Field org/eclipse/milo/opcua/stack/core/Identifiers.HasComponent:Lorg/eclipse/milo/opcua/stack/core/types/builtin/NodeId;
      38: iconst_0
      39: invokestatic  #13                 // Method java/lang/Boolean.valueOf:(Z)Ljava/lang/Boolean;
      42: aload_2
      43: aload_3
      44: invokespecial #14                 // Method org/eclipse/milo/opcua/stack/core/types/structured/BrowseDescription."<init>":(Lorg/eclipse/milo/opcua/stack/core/types/builtin/NodeId;Lorg/eclipse/milo/opcua/stack/core/types/enumerated/BrowseDirection;Lorg/eclipse/milo/opcua/stack/core/types/builtin/NodeId;Ljava/lang/Boolean;Lorg/eclipse/milo/opcua/stack/core/types/builtin/unsigned/UInteger;Lorg/eclipse/milo/opcua/stack/core/types/builtin/unsigned/UInteger;)V
      47: invokevirtual #15                 // Method org/eclipse/milo/opcua/sdk/client/OpcUaClient.browse:(Lorg/eclipse/milo/opcua/stack/core/types/structured/BrowseDescription;)Ljava/util/concurrent/CompletableFuture;
      50: astore        4
      52: aload         4
      54: aload_0
      55: aload_1
      56: invokedynamic #19,  0             // InvokeDynamic #2:apply:(Lorg/eclipse/milo/opcua/sdk/client/nodes/UaObjectNode;Lorg/eclipse/milo/opcua/stack/core/types/builtin/QualifiedName;)Ljava/util/function/Function;
      61: invokevirtual #17                 // Method java/util/concurrent/CompletableFuture.thenCompose:(Ljava/util/function/Function;)Ljava/util/concurrent/CompletableFuture;
      64: areturn

  public java.util.concurrent.CompletableFuture<? extends org.eclipse.milo.opcua.sdk.client.api.nodes.ObjectTypeNode> getTypeDefinition();
    Code:
       0: getstatic     #20                 // Field org/eclipse/milo/opcua/stack/core/types/enumerated/NodeClass.ObjectType:Lorg/eclipse/milo/opcua/stack/core/types/enumerated/NodeClass;
       3: invokevirtual #3                  // Method org/eclipse/milo/opcua/stack/core/types/enumerated/NodeClass.getValue:()I
       6: invokestatic  #5                  // Method org/eclipse/milo/opcua/stack/core/types/builtin/unsigned/Unsigned.uint:(I)Lorg/eclipse/milo/opcua/stack/core/types/builtin/unsigned/UInteger;
       9: astore_1
      10: getstatic     #6                  // Field org/eclipse/milo/opcua/stack/core/types/enumerated/BrowseResultMask.All:Lorg/eclipse/milo/opcua/stack/core/types/enumerated/BrowseResultMask;
      13: invokevirtual #7                  // Method org/eclipse/milo/opcua/stack/core/types/enumerated/BrowseResultMask.getValue:()I
      16: invokestatic  #5                  // Method org/eclipse/milo/opcua/stack/core/types/builtin/unsigned/Unsigned.uint:(I)Lorg/eclipse/milo/opcua/stack/core/types/builtin/unsigned/UInteger;
      19: astore_2
      20: aload_0
      21: getfield      #8                  // Field client:Lorg/eclipse/milo/opcua/sdk/client/OpcUaClient;
      24: new           #9                  // class org/eclipse/milo/opcua/stack/core/types/structured/BrowseDescription
      27: dup
      28: aload_0
      29: getfield      #10                 // Field nodeId:Lorg/eclipse/milo/opcua/stack/core/types/builtin/NodeId;
      32: getstatic     #11                 // Field org/eclipse/milo/opcua/stack/core/types/enumerated/BrowseDirection.Forward:Lorg/eclipse/milo/opcua/stack/core/types/enumerated/BrowseDirection;
      35: getstatic     #21                 // Field org/eclipse/milo/opcua/stack/core/Identifiers.HasTypeDefinition:Lorg/eclipse/milo/opcua/stack/core/types/builtin/NodeId;
      38: iconst_0
      39: invokestatic  #13                 // Method java/lang/Boolean.valueOf:(Z)Ljava/lang/Boolean;
      42: aload_1
      43: aload_2
      44: invokespecial #14                 // Method org/eclipse/milo/opcua/stack/core/types/structured/BrowseDescription."<init>":(Lorg/eclipse/milo/opcua/stack/core/types/builtin/NodeId;Lorg/eclipse/milo/opcua/stack/core/types/enumerated/BrowseDirection;Lorg/eclipse/milo/opcua/stack/core/types/builtin/NodeId;Ljava/lang/Boolean;Lorg/eclipse/milo/opcua/stack/core/types/builtin/unsigned/UInteger;Lorg/eclipse/milo/opcua/stack/core/types/builtin/unsigned/UInteger;)V
      47: invokevirtual #15                 // Method org/eclipse/milo/opcua/sdk/client/OpcUaClient.browse:(Lorg/eclipse/milo/opcua/stack/core/types/structured/BrowseDescription;)Ljava/util/concurrent/CompletableFuture;
      50: astore_3
      51: aload_3
      52: aload_0
      53: invokedynamic #22,  0             // InvokeDynamic #3:apply:(Lorg/eclipse/milo/opcua/sdk/client/nodes/UaObjectNode;)Ljava/util/function/Function;
      58: invokevirtual #17                 // Method java/util/concurrent/CompletableFuture.thenCompose:(Ljava/util/function/Function;)Ljava/util/concurrent/CompletableFuture;
      61: areturn

  public java.util.concurrent.CompletableFuture<org.eclipse.milo.opcua.stack.core.types.builtin.unsigned.UByte> getEventNotifier();
    Code:
       0: aload_0
       1: aload_0
       2: invokevirtual #23                 // Method readEventNotifier:()Ljava/util/concurrent/CompletableFuture;
       5: invokevirtual #24                 // Method getAttributeOrFail:(Ljava/util/concurrent/CompletableFuture;)Ljava/util/concurrent/CompletableFuture;
       8: areturn

  public java.util.concurrent.CompletableFuture<org.eclipse.milo.opcua.stack.core.types.builtin.StatusCode> setEventNotifier(org.eclipse.milo.opcua.stack.core.types.builtin.unsigned.UByte);
    Code:
       0: aload_0
       1: new           #25                 // class org/eclipse/milo/opcua/stack/core/types/builtin/Variant
       4: dup
       5: aload_1
       6: invokespecial #26                 // Method org/eclipse/milo/opcua/stack/core/types/builtin/Variant."<init>":(Ljava/lang/Object;)V
       9: invokestatic  #27                 // Method org/eclipse/milo/opcua/stack/core/types/builtin/DataValue.valueOnly:(Lorg/eclipse/milo/opcua/stack/core/types/builtin/Variant;)Lorg/eclipse/milo/opcua/stack/core/types/builtin/DataValue;
      12: invokevirtual #28                 // Method writeEventNotifier:(Lorg/eclipse/milo/opcua/stack/core/types/builtin/DataValue;)Ljava/util/concurrent/CompletableFuture;
      15: areturn

  public java.util.concurrent.CompletableFuture<org.eclipse.milo.opcua.stack.core.types.builtin.DataValue> readEventNotifier();
    Code:
       0: aload_0
       1: getstatic     #29                 // Field org/eclipse/milo/opcua/stack/core/AttributeId.EventNotifier:Lorg/eclipse/milo/opcua/stack/core/AttributeId;
       4: invokevirtual #30                 // Method readAttribute:(Lorg/eclipse/milo/opcua/stack/core/AttributeId;)Ljava/util/concurrent/CompletableFuture;
       7: areturn

  public java.util.concurrent.CompletableFuture<org.eclipse.milo.opcua.stack.core.types.builtin.StatusCode> writeEventNotifier(org.eclipse.milo.opcua.stack.core.types.builtin.DataValue);
    Code:
       0: aload_0
       1: getstatic     #29                 // Field org/eclipse/milo/opcua/stack/core/AttributeId.EventNotifier:Lorg/eclipse/milo/opcua/stack/core/AttributeId;
       4: aload_1
       5: invokevirtual #31                 // Method writeAttribute:(Lorg/eclipse/milo/opcua/stack/core/AttributeId;Lorg/eclipse/milo/opcua/stack/core/types/builtin/DataValue;)Ljava/util/concurrent/CompletableFuture;
       8: areturn

  private java.util.concurrent.CompletionStage lambda$getTypeDefinition$14(org.eclipse.milo.opcua.stack.core.types.structured.BrowseResult);
    Code:
       0: aload_1
       1: invokevirtual #32                 // Method org/eclipse/milo/opcua/stack/core/types/structured/BrowseResult.getReferences:()[Lorg/eclipse/milo/opcua/stack/core/types/structured/ReferenceDescription;
       4: invokestatic  #33                 // Method org/eclipse/milo/opcua/stack/core/util/ConversionUtil.l:([Ljava/lang/Object;)Ljava/util/List;
       7: astore_2
       8: aload_2
       9: invokeinterface #34,  1           // InterfaceMethod java/util/List.stream:()Ljava/util/stream/Stream;
      14: aload_0
      15: invokedynamic #35,  0             // InvokeDynamic #4:apply:(Lorg/eclipse/milo/opcua/sdk/client/nodes/UaObjectNode;)Ljava/util/function/Function;
      20: invokeinterface #36,  2           // InterfaceMethod java/util/stream/Stream.flatMap:(Ljava/util/function/Function;)Ljava/util/stream/Stream;
      25: invokeinterface #37,  1           // InterfaceMethod java/util/stream/Stream.findFirst:()Ljava/util/Optional;
      30: astore_3
      31: aload_3
      32: invokedynamic #38,  0             // InvokeDynamic #5:apply:()Ljava/util/function/Function;
      37: invokevirtual #39                 // Method java/util/Optional.map:(Ljava/util/function/Function;)Ljava/util/Optional;
      40: ldc2_w        #41                 // long 2151546880l
      43: invokestatic  #43                 // Method org/eclipse/milo/opcua/stack/core/util/FutureUtils.failedUaFuture:(J)Ljava/util/concurrent/CompletableFuture;
      46: invokevirtual #44                 // Method java/util/Optional.orElse:(Ljava/lang/Object;)Ljava/lang/Object;
      49: checkcast     #45                 // class java/util/concurrent/CompletionStage
      52: areturn

  private java.util.stream.Stream lambda$null$13(org.eclipse.milo.opcua.stack.core.types.structured.ReferenceDescription);
    Code:
       0: aload_1
       1: invokevirtual #46                 // Method org/eclipse/milo/opcua/stack/core/types/structured/ReferenceDescription.getNodeId:()Lorg/eclipse/milo/opcua/stack/core/types/builtin/ExpandedNodeId;
       4: invokevirtual #47                 // Method org/eclipse/milo/opcua/stack/core/types/builtin/ExpandedNodeId.local:()Ljava/util/Optional;
       7: aload_0
       8: invokedynamic #48,  0             // InvokeDynamic #6:apply:(Lorg/eclipse/milo/opcua/sdk/client/nodes/UaObjectNode;)Ljava/util/function/Function;
      13: invokevirtual #39                 // Method java/util/Optional.map:(Ljava/util/function/Function;)Ljava/util/Optional;
      16: astore_2
      17: aload_2
      18: invokestatic  #49                 // Method org/eclipse/milo/opcua/sdk/core/util/StreamUtil.opt2stream:(Ljava/util/Optional;)Ljava/util/stream/Stream;
      21: areturn

  private org.eclipse.milo.opcua.sdk.client.api.nodes.ObjectTypeNode lambda$null$12(org.eclipse.milo.opcua.stack.core.types.builtin.NodeId);
    Code:
       0: aload_0
       1: getfield      #8                  // Field client:Lorg/eclipse/milo/opcua/sdk/client/OpcUaClient;
       4: invokevirtual #50                 // Method org/eclipse/milo/opcua/sdk/client/OpcUaClient.getAddressSpace:()Lorg/eclipse/milo/opcua/sdk/client/api/AddressSpace;
       7: aload_1
       8: invokeinterface #51,  2           // InterfaceMethod org/eclipse/milo/opcua/sdk/client/api/AddressSpace.createObjectTypeNode:(Lorg/eclipse/milo/opcua/stack/core/types/builtin/NodeId;)Lorg/eclipse/milo/opcua/sdk/client/api/nodes/ObjectTypeNode;
      13: areturn

  private java.util.concurrent.CompletionStage lambda$getVariableComponent$11(org.eclipse.milo.opcua.stack.core.types.builtin.QualifiedName, org.eclipse.milo.opcua.stack.core.types.structured.BrowseResult);
    Code:
       0: aload_2
       1: invokevirtual #32                 // Method org/eclipse/milo/opcua/stack/core/types/structured/BrowseResult.getReferences:()[Lorg/eclipse/milo/opcua/stack/core/types/structured/ReferenceDescription;
       4: invokestatic  #33                 // Method org/eclipse/milo/opcua/stack/core/util/ConversionUtil.l:([Ljava/lang/Object;)Ljava/util/List;
       7: astore_3
       8: aload_3
       9: invokeinterface #34,  1           // InterfaceMethod java/util/List.stream:()Ljava/util/stream/Stream;
      14: aload_1
      15: invokedynamic #52,  0             // InvokeDynamic #7:test:(Lorg/eclipse/milo/opcua/stack/core/types/builtin/QualifiedName;)Ljava/util/function/Predicate;
      20: invokeinterface #53,  2           // InterfaceMethod java/util/stream/Stream.filter:(Ljava/util/function/Predicate;)Ljava/util/stream/Stream;
      25: aload_0
      26: invokedynamic #54,  0             // InvokeDynamic #8:apply:(Lorg/eclipse/milo/opcua/sdk/client/nodes/UaObjectNode;)Ljava/util/function/Function;
      31: invokeinterface #36,  2           // InterfaceMethod java/util/stream/Stream.flatMap:(Ljava/util/function/Function;)Ljava/util/stream/Stream;
      36: invokeinterface #37,  1           // InterfaceMethod java/util/stream/Stream.findFirst:()Ljava/util/Optional;
      41: astore        4
      43: aload         4
      45: ldc2_w        #41                 // long 2151546880l
      48: invokestatic  #43                 // Method org/eclipse/milo/opcua/stack/core/util/FutureUtils.failedUaFuture:(J)Ljava/util/concurrent/CompletableFuture;
      51: invokevirtual #44                 // Method java/util/Optional.orElse:(Ljava/lang/Object;)Ljava/lang/Object;
      54: checkcast     #45                 // class java/util/concurrent/CompletionStage
      57: areturn

  private java.util.stream.Stream lambda$null$10(org.eclipse.milo.opcua.stack.core.types.structured.ReferenceDescription);
    Code:
       0: aload_1
       1: invokevirtual #46                 // Method org/eclipse/milo/opcua/stack/core/types/structured/ReferenceDescription.getNodeId:()Lorg/eclipse/milo/opcua/stack/core/types/builtin/ExpandedNodeId;
       4: invokevirtual #47                 // Method org/eclipse/milo/opcua/stack/core/types/builtin/ExpandedNodeId.local:()Ljava/util/Optional;
       7: aload_0
       8: invokedynamic #55,  0             // InvokeDynamic #9:apply:(Lorg/eclipse/milo/opcua/sdk/client/nodes/UaObjectNode;)Ljava/util/function/Function;
      13: invokevirtual #39                 // Method java/util/Optional.map:(Ljava/util/function/Function;)Ljava/util/Optional;
      16: astore_2
      17: aload_2
      18: invokestatic  #49                 // Method org/eclipse/milo/opcua/sdk/core/util/StreamUtil.opt2stream:(Ljava/util/Optional;)Ljava/util/stream/Stream;
      21: areturn

  private java.util.concurrent.CompletableFuture lambda$null$9(org.eclipse.milo.opcua.stack.core.types.builtin.NodeId);
    Code:
       0: aload_0
       1: getfield      #8                  // Field client:Lorg/eclipse/milo/opcua/sdk/client/OpcUaClient;
       4: invokevirtual #50                 // Method org/eclipse/milo/opcua/sdk/client/OpcUaClient.getAddressSpace:()Lorg/eclipse/milo/opcua/sdk/client/api/AddressSpace;
       7: aload_1
       8: invokeinterface #56,  2           // InterfaceMethod org/eclipse/milo/opcua/sdk/client/api/AddressSpace.getVariableNode:(Lorg/eclipse/milo/opcua/stack/core/types/builtin/NodeId;)Ljava/util/concurrent/CompletableFuture;
      13: areturn

  private static boolean lambda$null$8(org.eclipse.milo.opcua.stack.core.types.builtin.QualifiedName, org.eclipse.milo.opcua.stack.core.types.structured.ReferenceDescription);
    Code:
       0: aload_0
       1: aload_1
       2: invokevirtual #57                 // Method org/eclipse/milo/opcua/stack/core/types/structured/ReferenceDescription.getBrowseName:()Lorg/eclipse/milo/opcua/stack/core/types/builtin/QualifiedName;
       5: invokevirtual #58                 // Method org/eclipse/milo/opcua/stack/core/types/builtin/QualifiedName.equals:(Ljava/lang/Object;)Z
       8: ireturn

  private java.util.concurrent.CompletionStage lambda$getObjectComponent$7(org.eclipse.milo.opcua.stack.core.types.builtin.QualifiedName, org.eclipse.milo.opcua.stack.core.types.structured.BrowseResult);
    Code:
       0: aload_2
       1: invokevirtual #32                 // Method org/eclipse/milo/opcua/stack/core/types/structured/BrowseResult.getReferences:()[Lorg/eclipse/milo/opcua/stack/core/types/structured/ReferenceDescription;
       4: invokestatic  #33                 // Method org/eclipse/milo/opcua/stack/core/util/ConversionUtil.l:([Ljava/lang/Object;)Ljava/util/List;
       7: astore_3
       8: aload_3
       9: invokeinterface #34,  1           // InterfaceMethod java/util/List.stream:()Ljava/util/stream/Stream;
      14: aload_1
      15: invokedynamic #59,  0             // InvokeDynamic #10:test:(Lorg/eclipse/milo/opcua/stack/core/types/builtin/QualifiedName;)Ljava/util/function/Predicate;
      20: invokeinterface #53,  2           // InterfaceMethod java/util/stream/Stream.filter:(Ljava/util/function/Predicate;)Ljava/util/stream/Stream;
      25: aload_0
      26: invokedynamic #60,  0             // InvokeDynamic #11:apply:(Lorg/eclipse/milo/opcua/sdk/client/nodes/UaObjectNode;)Ljava/util/function/Function;
      31: invokeinterface #36,  2           // InterfaceMethod java/util/stream/Stream.flatMap:(Ljava/util/function/Function;)Ljava/util/stream/Stream;
      36: invokeinterface #37,  1           // InterfaceMethod java/util/stream/Stream.findFirst:()Ljava/util/Optional;
      41: astore        4
      43: aload         4
      45: ldc2_w        #41                 // long 2151546880l
      48: invokestatic  #43                 // Method org/eclipse/milo/opcua/stack/core/util/FutureUtils.failedUaFuture:(J)Ljava/util/concurrent/CompletableFuture;
      51: invokevirtual #44                 // Method java/util/Optional.orElse:(Ljava/lang/Object;)Ljava/lang/Object;
      54: checkcast     #45                 // class java/util/concurrent/CompletionStage
      57: areturn

  private java.util.stream.Stream lambda$null$6(org.eclipse.milo.opcua.stack.core.types.structured.ReferenceDescription);
    Code:
       0: aload_1
       1: invokevirtual #46                 // Method org/eclipse/milo/opcua/stack/core/types/structured/ReferenceDescription.getNodeId:()Lorg/eclipse/milo/opcua/stack/core/types/builtin/ExpandedNodeId;
       4: invokevirtual #47                 // Method org/eclipse/milo/opcua/stack/core/types/builtin/ExpandedNodeId.local:()Ljava/util/Optional;
       7: aload_0
       8: invokedynamic #61,  0             // InvokeDynamic #12:apply:(Lorg/eclipse/milo/opcua/sdk/client/nodes/UaObjectNode;)Ljava/util/function/Function;
      13: invokevirtual #39                 // Method java/util/Optional.map:(Ljava/util/function/Function;)Ljava/util/Optional;
      16: astore_2
      17: aload_2
      18: invokestatic  #49                 // Method org/eclipse/milo/opcua/sdk/core/util/StreamUtil.opt2stream:(Ljava/util/Optional;)Ljava/util/stream/Stream;
      21: areturn

  private java.util.concurrent.CompletableFuture lambda$null$5(org.eclipse.milo.opcua.stack.core.types.builtin.NodeId);
    Code:
       0: aload_0
       1: getfield      #8                  // Field client:Lorg/eclipse/milo/opcua/sdk/client/OpcUaClient;
       4: invokevirtual #50                 // Method org/eclipse/milo/opcua/sdk/client/OpcUaClient.getAddressSpace:()Lorg/eclipse/milo/opcua/sdk/client/api/AddressSpace;
       7: aload_1
       8: invokeinterface #62,  2           // InterfaceMethod org/eclipse/milo/opcua/sdk/client/api/AddressSpace.getObjectNode:(Lorg/eclipse/milo/opcua/stack/core/types/builtin/NodeId;)Ljava/util/concurrent/CompletableFuture;
      13: areturn

  private static boolean lambda$null$4(org.eclipse.milo.opcua.stack.core.types.builtin.QualifiedName, org.eclipse.milo.opcua.stack.core.types.structured.ReferenceDescription);
    Code:
       0: aload_0
       1: aload_1
       2: invokevirtual #57                 // Method org/eclipse/milo/opcua/stack/core/types/structured/ReferenceDescription.getBrowseName:()Lorg/eclipse/milo/opcua/stack/core/types/builtin/QualifiedName;
       5: invokevirtual #58                 // Method org/eclipse/milo/opcua/stack/core/types/builtin/QualifiedName.equals:(Ljava/lang/Object;)Z
       8: ireturn

  private java.util.concurrent.CompletionStage lambda$getComponent$3(org.eclipse.milo.opcua.stack.core.types.builtin.QualifiedName, org.eclipse.milo.opcua.stack.core.types.structured.BrowseResult);
    Code:
       0: aload_2
       1: invokevirtual #32                 // Method org/eclipse/milo/opcua/stack/core/types/structured/BrowseResult.getReferences:()[Lorg/eclipse/milo/opcua/stack/core/types/structured/ReferenceDescription;
       4: invokestatic  #33                 // Method org/eclipse/milo/opcua/stack/core/util/ConversionUtil.l:([Ljava/lang/Object;)Ljava/util/List;
       7: astore_3
       8: aload_3
       9: invokeinterface #34,  1           // InterfaceMethod java/util/List.stream:()Ljava/util/stream/Stream;
      14: aload_1
      15: invokedynamic #63,  0             // InvokeDynamic #13:test:(Lorg/eclipse/milo/opcua/stack/core/types/builtin/QualifiedName;)Ljava/util/function/Predicate;
      20: invokeinterface #53,  2           // InterfaceMethod java/util/stream/Stream.filter:(Ljava/util/function/Predicate;)Ljava/util/stream/Stream;
      25: aload_0
      26: invokedynamic #64,  0             // InvokeDynamic #14:apply:(Lorg/eclipse/milo/opcua/sdk/client/nodes/UaObjectNode;)Ljava/util/function/Function;
      31: invokeinterface #36,  2           // InterfaceMethod java/util/stream/Stream.flatMap:(Ljava/util/function/Function;)Ljava/util/stream/Stream;
      36: invokeinterface #37,  1           // InterfaceMethod java/util/stream/Stream.findFirst:()Ljava/util/Optional;
      41: astore        4
      43: aload         4
      45: ldc2_w        #41                 // long 2151546880l
      48: invokestatic  #43                 // Method org/eclipse/milo/opcua/stack/core/util/FutureUtils.failedUaFuture:(J)Ljava/util/concurrent/CompletableFuture;
      51: invokevirtual #44                 // Method java/util/Optional.orElse:(Ljava/lang/Object;)Ljava/lang/Object;
      54: checkcast     #45                 // class java/util/concurrent/CompletionStage
      57: areturn

  private java.util.stream.Stream lambda$null$2(org.eclipse.milo.opcua.stack.core.types.structured.ReferenceDescription);
    Code:
       0: aload_1
       1: invokevirtual #46                 // Method org/eclipse/milo/opcua/stack/core/types/structured/ReferenceDescription.getNodeId:()Lorg/eclipse/milo/opcua/stack/core/types/builtin/ExpandedNodeId;
       4: invokevirtual #47                 // Method org/eclipse/milo/opcua/stack/core/types/builtin/ExpandedNodeId.local:()Ljava/util/Optional;
       7: aload_0
       8: invokedynamic #65,  0             // InvokeDynamic #15:apply:(Lorg/eclipse/milo/opcua/sdk/client/nodes/UaObjectNode;)Ljava/util/function/Function;
      13: invokevirtual #39                 // Method java/util/Optional.map:(Ljava/util/function/Function;)Ljava/util/Optional;
      16: astore_2
      17: aload_2
      18: invokestatic  #49                 // Method org/eclipse/milo/opcua/sdk/core/util/StreamUtil.opt2stream:(Ljava/util/Optional;)Ljava/util/stream/Stream;
      21: areturn

  private java.util.concurrent.CompletableFuture lambda$null$1(org.eclipse.milo.opcua.stack.core.types.builtin.NodeId);
    Code:
       0: aload_0
       1: getfield      #8                  // Field client:Lorg/eclipse/milo/opcua/sdk/client/OpcUaClient;
       4: invokevirtual #50                 // Method org/eclipse/milo/opcua/sdk/client/OpcUaClient.getAddressSpace:()Lorg/eclipse/milo/opcua/sdk/client/api/AddressSpace;
       7: aload_1
       8: invokeinterface #66,  2           // InterfaceMethod org/eclipse/milo/opcua/sdk/client/api/AddressSpace.createNode:(Lorg/eclipse/milo/opcua/stack/core/types/builtin/NodeId;)Ljava/util/concurrent/CompletableFuture;
      13: areturn

  private static boolean lambda$null$0(org.eclipse.milo.opcua.stack.core.types.builtin.QualifiedName, org.eclipse.milo.opcua.stack.core.types.structured.ReferenceDescription);
    Code:
       0: aload_0
       1: aload_1
       2: invokevirtual #57                 // Method org/eclipse/milo/opcua/stack/core/types/structured/ReferenceDescription.getBrowseName:()Lorg/eclipse/milo/opcua/stack/core/types/builtin/QualifiedName;
       5: invokevirtual #58                 // Method org/eclipse/milo/opcua/stack/core/types/builtin/QualifiedName.equals:(Ljava/lang/Object;)Z
       8: ireturn
}
