Compiled from "Platform.java"
class brave.internal.Platform$Jre9$1 implements brave.Clock {
  final brave.internal.Platform$Jre9 this$0;

  brave.internal.Platform$Jre9$1(brave.internal.Platform$Jre9);
    Code:
       0: aload_0
       1: aload_1
       2: putfield      #21                 // Field this$0:Lbrave/internal/Platform$Jre9;
       5: aload_0
       6: invokespecial #24                 // Method java/lang/Object."<init>":()V
       9: return

  public long currentTimeMicroseconds();
    Code:
       0: invokestatic  #34                 // Method java/time/Clock.systemUTC:()Ljava/time/Clock;
       3: invokevirtual #38                 // Method java/time/Clock.instant:()Ljava/time/Instant;
       6: astore_1
       7: aload_1
       8: invokevirtual #43                 // Method java/time/Instant.getEpochSecond:()J
      11: ldc2_w        #44                 // long 1000000l
      14: lmul
      15: aload_1
      16: invokevirtual #49                 // Method java/time/Instant.getNano:()I
      19: sipush        1000
      22: idiv
      23: i2l
      24: ladd
      25: lreturn

  public java.lang.String toString();
    Code:
       0: ldc           #54                 // String Clock.systemUTC().instant()
       2: areturn
}
