Compiled from "LookupCache.java"
public abstract class org.graylog2.plugin.lookup.LookupCache$Descriptor<C extends org.graylog2.plugin.lookup.LookupCacheConfiguration> {
  private final java.lang.String type;

  private final java.lang.Class<C> configClass;

  public org.graylog2.plugin.lookup.LookupCache$Descriptor(java.lang.String, java.lang.Class<C>);
    Code:
       0: aload_0
       1: invokespecial #1                  // Method java/lang/Object."<init>":()V
       4: aload_0
       5: aload_1
       6: putfield      #2                  // Field type:Ljava/lang/String;
       9: aload_0
      10: aload_2
      11: putfield      #3                  // Field configClass:Ljava/lang/Class;
      14: return

  public java.lang.String getType();
    Code:
       0: aload_0
       1: getfield      #2                  // Field type:Ljava/lang/String;
       4: areturn

  public java.lang.Class<C> getConfigClass();
    Code:
       0: aload_0
       1: getfield      #3                  // Field configClass:Ljava/lang/Class;
       4: areturn

  public abstract C defaultConfiguration();
}
