Compiled from "LookupResult.java"
public abstract class org.graylog2.plugin.lookup.LookupResult {
  private static final org.graylog2.plugin.lookup.LookupResult EMPTY_LOOKUP_RESULT;

  public static final java.lang.String SINGLE_VALUE_KEY;

  public org.graylog2.plugin.lookup.LookupResult();
    Code:
       0: aload_0
       1: invokespecial #1                  // Method java/lang/Object."<init>":()V
       4: return

  public abstract java.lang.Object singleValue();

  public abstract java.util.Map<java.lang.Object, java.lang.Object> multiValue();

  public abstract long cacheTTL();

  public boolean isEmpty();
    Code:
       0: aload_0
       1: invokevirtual #2                  // Method singleValue:()Ljava/lang/Object;
       4: ifnonnull     18
       7: aload_0
       8: invokevirtual #3                  // Method multiValue:()Ljava/util/Map;
      11: ifnonnull     18
      14: iconst_1
      15: goto          19
      18: iconst_0
      19: ireturn

  public static org.graylog2.plugin.lookup.LookupResult empty();
    Code:
       0: getstatic     #4                  // Field EMPTY_LOOKUP_RESULT:Lorg/graylog2/plugin/lookup/LookupResult;
       3: areturn

  public static org.graylog2.plugin.lookup.LookupResult single(java.lang.CharSequence);
    Code:
       0: aload_0
       1: ldc           #6                  // String value
       3: aload_0
       4: invokestatic  #7                  // Method java/util/Collections.singletonMap:(Ljava/lang/Object;Ljava/lang/Object;)Ljava/util/Map;
       7: invokestatic  #8                  // Method multi:(Ljava/lang/CharSequence;Ljava/util/Map;)Lorg/graylog2/plugin/lookup/LookupResult;
      10: areturn

  public static org.graylog2.plugin.lookup.LookupResult single(java.lang.Number);
    Code:
       0: aload_0
       1: ldc           #6                  // String value
       3: aload_0
       4: invokestatic  #7                  // Method java/util/Collections.singletonMap:(Ljava/lang/Object;Ljava/lang/Object;)Ljava/util/Map;
       7: invokestatic  #9                  // Method multi:(Ljava/lang/Number;Ljava/util/Map;)Lorg/graylog2/plugin/lookup/LookupResult;
      10: areturn

  public static org.graylog2.plugin.lookup.LookupResult single(java.lang.Boolean);
    Code:
       0: aload_0
       1: ldc           #6                  // String value
       3: aload_0
       4: invokestatic  #7                  // Method java/util/Collections.singletonMap:(Ljava/lang/Object;Ljava/lang/Object;)Ljava/util/Map;
       7: invokestatic  #10                 // Method multi:(Ljava/lang/Boolean;Ljava/util/Map;)Lorg/graylog2/plugin/lookup/LookupResult;
      10: areturn

  public static org.graylog2.plugin.lookup.LookupResult multi(java.lang.CharSequence, java.util.Map<java.lang.Object, java.lang.Object>);
    Code:
       0: invokestatic  #11                 // Method withoutTTL:()Lorg/graylog2/plugin/lookup/LookupResult$Builder;
       3: aload_0
       4: invokevirtual #12                 // Method org/graylog2/plugin/lookup/LookupResult$Builder.single:(Ljava/lang/CharSequence;)Lorg/graylog2/plugin/lookup/LookupResult$Builder;
       7: aload_1
       8: invokevirtual #13                 // Method org/graylog2/plugin/lookup/LookupResult$Builder.multiValue:(Ljava/util/Map;)Lorg/graylog2/plugin/lookup/LookupResult$Builder;
      11: invokevirtual #14                 // Method org/graylog2/plugin/lookup/LookupResult$Builder.build:()Lorg/graylog2/plugin/lookup/LookupResult;
      14: areturn

  public static org.graylog2.plugin.lookup.LookupResult multi(java.lang.Number, java.util.Map<java.lang.Object, java.lang.Object>);
    Code:
       0: invokestatic  #11                 // Method withoutTTL:()Lorg/graylog2/plugin/lookup/LookupResult$Builder;
       3: aload_0
       4: invokevirtual #15                 // Method org/graylog2/plugin/lookup/LookupResult$Builder.single:(Ljava/lang/Number;)Lorg/graylog2/plugin/lookup/LookupResult$Builder;
       7: aload_1
       8: invokevirtual #13                 // Method org/graylog2/plugin/lookup/LookupResult$Builder.multiValue:(Ljava/util/Map;)Lorg/graylog2/plugin/lookup/LookupResult$Builder;
      11: invokevirtual #14                 // Method org/graylog2/plugin/lookup/LookupResult$Builder.build:()Lorg/graylog2/plugin/lookup/LookupResult;
      14: areturn

  public static org.graylog2.plugin.lookup.LookupResult multi(java.lang.Boolean, java.util.Map<java.lang.Object, java.lang.Object>);
    Code:
       0: invokestatic  #11                 // Method withoutTTL:()Lorg/graylog2/plugin/lookup/LookupResult$Builder;
       3: aload_0
       4: invokevirtual #16                 // Method org/graylog2/plugin/lookup/LookupResult$Builder.single:(Ljava/lang/Boolean;)Lorg/graylog2/plugin/lookup/LookupResult$Builder;
       7: aload_1
       8: invokevirtual #13                 // Method org/graylog2/plugin/lookup/LookupResult$Builder.multiValue:(Ljava/util/Map;)Lorg/graylog2/plugin/lookup/LookupResult$Builder;
      11: invokevirtual #14                 // Method org/graylog2/plugin/lookup/LookupResult$Builder.build:()Lorg/graylog2/plugin/lookup/LookupResult;
      14: areturn

  public static org.graylog2.plugin.lookup.LookupResult withDefaults(org.graylog2.lookup.LookupDefaultSingleValue, org.graylog2.lookup.LookupDefaultMultiValue);
    Code:
       0: invokestatic  #11                 // Method withoutTTL:()Lorg/graylog2/plugin/lookup/LookupResult$Builder;
       3: astore_2
       4: getstatic     #17                 // Field org/graylog2/plugin/lookup/LookupResult$1.$SwitchMap$org$graylog2$lookup$LookupDefaultValue$Type:[I
       7: aload_0
       8: invokevirtual #18                 // Method org/graylog2/lookup/LookupDefaultSingleValue.valueType:()Lorg/graylog2/lookup/LookupDefaultValue$Type;
      11: invokevirtual #19                 // Method org/graylog2/lookup/LookupDefaultValue$Type.ordinal:()I
      14: iaload
      15: tableswitch   { // 1 to 5
                     1: 48
                     2: 63
                     3: 78
                     4: 93
                     5: 103
               default: 103
          }
      48: aload_2
      49: aload_0
      50: invokevirtual #20                 // Method org/graylog2/lookup/LookupDefaultSingleValue.value:()Ljava/lang/Object;
      53: checkcast     #21                 // class java/lang/CharSequence
      56: invokevirtual #12                 // Method org/graylog2/plugin/lookup/LookupResult$Builder.single:(Ljava/lang/CharSequence;)Lorg/graylog2/plugin/lookup/LookupResult$Builder;
      59: astore_2
      60: goto          103
      63: aload_2
      64: aload_0
      65: invokevirtual #20                 // Method org/graylog2/lookup/LookupDefaultSingleValue.value:()Ljava/lang/Object;
      68: checkcast     #22                 // class java/lang/Number
      71: invokevirtual #15                 // Method org/graylog2/plugin/lookup/LookupResult$Builder.single:(Ljava/lang/Number;)Lorg/graylog2/plugin/lookup/LookupResult$Builder;
      74: astore_2
      75: goto          103
      78: aload_2
      79: aload_0
      80: invokevirtual #20                 // Method org/graylog2/lookup/LookupDefaultSingleValue.value:()Ljava/lang/Object;
      83: checkcast     #23                 // class java/lang/Boolean
      86: invokevirtual #16                 // Method org/graylog2/plugin/lookup/LookupResult$Builder.single:(Ljava/lang/Boolean;)Lorg/graylog2/plugin/lookup/LookupResult$Builder;
      89: astore_2
      90: goto          103
      93: new           #24                 // class java/lang/IllegalArgumentException
      96: dup
      97: ldc           #25                 // String Single value cannot be of type OBJECT
      99: invokespecial #26                 // Method java/lang/IllegalArgumentException."<init>":(Ljava/lang/String;)V
     102: athrow
     103: aload_1
     104: invokevirtual #27                 // Method org/graylog2/lookup/LookupDefaultMultiValue.isSet:()Z
     107: ifeq          122
     110: aload_2
     111: aload_1
     112: invokevirtual #28                 // Method org/graylog2/lookup/LookupDefaultMultiValue.value:()Ljava/util/Map;
     115: invokevirtual #13                 // Method org/graylog2/plugin/lookup/LookupResult$Builder.multiValue:(Ljava/util/Map;)Lorg/graylog2/plugin/lookup/LookupResult$Builder;
     118: astore_2
     119: goto          143
     122: aload_0
     123: invokevirtual #29                 // Method org/graylog2/lookup/LookupDefaultSingleValue.isSet:()Z
     126: ifeq          143
     129: aload_2
     130: ldc           #6                  // String value
     132: aload_0
     133: invokevirtual #20                 // Method org/graylog2/lookup/LookupDefaultSingleValue.value:()Ljava/lang/Object;
     136: invokestatic  #7                  // Method java/util/Collections.singletonMap:(Ljava/lang/Object;Ljava/lang/Object;)Ljava/util/Map;
     139: invokevirtual #13                 // Method org/graylog2/plugin/lookup/LookupResult$Builder.multiValue:(Ljava/util/Map;)Lorg/graylog2/plugin/lookup/LookupResult$Builder;
     142: astore_2
     143: aload_2
     144: invokevirtual #14                 // Method org/graylog2/plugin/lookup/LookupResult$Builder.build:()Lorg/graylog2/plugin/lookup/LookupResult;
     147: areturn

  public static org.graylog2.plugin.lookup.LookupResult createFromJSON(java.lang.Object, java.util.Map<java.lang.Object, java.lang.Object>, long);
    Code:
       0: invokestatic  #30                 // Method builder:()Lorg/graylog2/plugin/lookup/LookupResult$Builder;
       3: aload_0
       4: invokevirtual #31                 // Method org/graylog2/plugin/lookup/LookupResult$Builder.singleValue:(Ljava/lang/Object;)Lorg/graylog2/plugin/lookup/LookupResult$Builder;
       7: aload_1
       8: invokevirtual #13                 // Method org/graylog2/plugin/lookup/LookupResult$Builder.multiValue:(Ljava/util/Map;)Lorg/graylog2/plugin/lookup/LookupResult$Builder;
      11: lload_2
      12: invokevirtual #32                 // Method org/graylog2/plugin/lookup/LookupResult$Builder.cacheTTL:(J)Lorg/graylog2/plugin/lookup/LookupResult$Builder;
      15: invokevirtual #14                 // Method org/graylog2/plugin/lookup/LookupResult$Builder.build:()Lorg/graylog2/plugin/lookup/LookupResult;
      18: areturn

  public static org.graylog2.plugin.lookup.LookupResult$Builder withoutTTL();
    Code:
       0: invokestatic  #30                 // Method builder:()Lorg/graylog2/plugin/lookup/LookupResult$Builder;
       3: ldc2_w        #34                 // long 9223372036854775807l
       6: invokevirtual #32                 // Method org/graylog2/plugin/lookup/LookupResult$Builder.cacheTTL:(J)Lorg/graylog2/plugin/lookup/LookupResult$Builder;
       9: areturn

  public static org.graylog2.plugin.lookup.LookupResult$Builder builder();
    Code:
       0: new           #36                 // class org/graylog2/plugin/lookup/AutoValue_LookupResult$Builder
       3: dup
       4: invokespecial #37                 // Method org/graylog2/plugin/lookup/AutoValue_LookupResult$Builder."<init>":()V
       7: areturn

  static {};
    Code:
       0: invokestatic  #30                 // Method builder:()Lorg/graylog2/plugin/lookup/LookupResult$Builder;
       3: ldc2_w        #34                 // long 9223372036854775807l
       6: invokevirtual #32                 // Method org/graylog2/plugin/lookup/LookupResult$Builder.cacheTTL:(J)Lorg/graylog2/plugin/lookup/LookupResult$Builder;
       9: invokevirtual #14                 // Method org/graylog2/plugin/lookup/LookupResult$Builder.build:()Lorg/graylog2/plugin/lookup/LookupResult;
      12: putstatic     #4                  // Field EMPTY_LOOKUP_RESULT:Lorg/graylog2/plugin/lookup/LookupResult;
      15: return
}
