Compiled from "ATNConfigSet.java"
public final class nl.basjes.shaded.org.antlr.v4.runtime.atn.ATNConfigSet$ConfigEqualityComparator extends nl.basjes.shaded.org.antlr.v4.runtime.misc.AbstractEqualityComparator<nl.basjes.shaded.org.antlr.v4.runtime.atn.ATNConfig> {
  public static final nl.basjes.shaded.org.antlr.v4.runtime.atn.ATNConfigSet$ConfigEqualityComparator INSTANCE;

  private nl.basjes.shaded.org.antlr.v4.runtime.atn.ATNConfigSet$ConfigEqualityComparator();
    Code:
       0: aload_0
       1: invokespecial #15                 // Method nl/basjes/shaded/org/antlr/v4/runtime/misc/AbstractEqualityComparator."<init>":()V
       4: return

  public int hashCode(nl.basjes.shaded.org.antlr.v4.runtime.atn.ATNConfig);
    Code:
       0: bipush        7
       2: istore_2
       3: bipush        31
       5: iload_2
       6: imul
       7: aload_1
       8: getfield      #24                 // Field nl/basjes/shaded/org/antlr/v4/runtime/atn/ATNConfig.state:Lnl/basjes/shaded/org/antlr/v4/runtime/atn/ATNState;
      11: getfield      #30                 // Field nl/basjes/shaded/org/antlr/v4/runtime/atn/ATNState.stateNumber:I
      14: iadd
      15: istore_2
      16: bipush        31
      18: iload_2
      19: imul
      20: aload_1
      21: getfield      #33                 // Field nl/basjes/shaded/org/antlr/v4/runtime/atn/ATNConfig.alt:I
      24: iadd
      25: istore_2
      26: bipush        31
      28: iload_2
      29: imul
      30: aload_1
      31: getfield      #37                 // Field nl/basjes/shaded/org/antlr/v4/runtime/atn/ATNConfig.semanticContext:Lnl/basjes/shaded/org/antlr/v4/runtime/atn/SemanticContext;
      34: invokevirtual #42                 // Method java/lang/Object.hashCode:()I
      37: iadd
      38: istore_2
      39: iload_2
      40: ireturn

  public boolean equals(nl.basjes.shaded.org.antlr.v4.runtime.atn.ATNConfig, nl.basjes.shaded.org.antlr.v4.runtime.atn.ATNConfig);
    Code:
       0: aload_1
       1: aload_2
       2: if_acmpne     7
       5: iconst_1
       6: ireturn
       7: aload_1
       8: ifnull        15
      11: aload_2
      12: ifnonnull     17
      15: iconst_0
      16: ireturn
      17: aload_1
      18: getfield      #24                 // Field nl/basjes/shaded/org/antlr/v4/runtime/atn/ATNConfig.state:Lnl/basjes/shaded/org/antlr/v4/runtime/atn/ATNState;
      21: getfield      #30                 // Field nl/basjes/shaded/org/antlr/v4/runtime/atn/ATNState.stateNumber:I
      24: aload_2
      25: getfield      #24                 // Field nl/basjes/shaded/org/antlr/v4/runtime/atn/ATNConfig.state:Lnl/basjes/shaded/org/antlr/v4/runtime/atn/ATNState;
      28: getfield      #30                 // Field nl/basjes/shaded/org/antlr/v4/runtime/atn/ATNState.stateNumber:I
      31: if_icmpne     63
      34: aload_1
      35: getfield      #33                 // Field nl/basjes/shaded/org/antlr/v4/runtime/atn/ATNConfig.alt:I
      38: aload_2
      39: getfield      #33                 // Field nl/basjes/shaded/org/antlr/v4/runtime/atn/ATNConfig.alt:I
      42: if_icmpne     63
      45: aload_1
      46: getfield      #37                 // Field nl/basjes/shaded/org/antlr/v4/runtime/atn/ATNConfig.semanticContext:Lnl/basjes/shaded/org/antlr/v4/runtime/atn/SemanticContext;
      49: aload_2
      50: getfield      #37                 // Field nl/basjes/shaded/org/antlr/v4/runtime/atn/ATNConfig.semanticContext:Lnl/basjes/shaded/org/antlr/v4/runtime/atn/SemanticContext;
      53: invokevirtual #49                 // Method java/lang/Object.equals:(Ljava/lang/Object;)Z
      56: ifeq          63
      59: iconst_1
      60: goto          64
      63: iconst_0
      64: ireturn

  public boolean equals(java.lang.Object, java.lang.Object);
    Code:
       0: aload_0
       1: aload_1
       2: checkcast     #20                 // class nl/basjes/shaded/org/antlr/v4/runtime/atn/ATNConfig
       5: aload_2
       6: checkcast     #20                 // class nl/basjes/shaded/org/antlr/v4/runtime/atn/ATNConfig
       9: invokevirtual #54                 // Method equals:(Lnl/basjes/shaded/org/antlr/v4/runtime/atn/ATNConfig;Lnl/basjes/shaded/org/antlr/v4/runtime/atn/ATNConfig;)Z
      12: ireturn

  public int hashCode(java.lang.Object);
    Code:
       0: aload_0
       1: aload_1
       2: checkcast     #20                 // class nl/basjes/shaded/org/antlr/v4/runtime/atn/ATNConfig
       5: invokevirtual #57                 // Method hashCode:(Lnl/basjes/shaded/org/antlr/v4/runtime/atn/ATNConfig;)I
       8: ireturn

  static {};
    Code:
       0: new           #2                  // class nl/basjes/shaded/org/antlr/v4/runtime/atn/ATNConfigSet$ConfigEqualityComparator
       3: dup
       4: invokespecial #59                 // Method "<init>":()V
       7: putstatic     #61                 // Field INSTANCE:Lnl/basjes/shaded/org/antlr/v4/runtime/atn/ATNConfigSet$ConfigEqualityComparator;
      10: return
}
