Compiled from "NotSetTransition.java"
public final class nl.basjes.shaded.org.antlr.v4.runtime.atn.NotSetTransition extends nl.basjes.shaded.org.antlr.v4.runtime.atn.SetTransition {
  public nl.basjes.shaded.org.antlr.v4.runtime.atn.NotSetTransition(nl.basjes.shaded.org.antlr.v4.runtime.atn.ATNState, nl.basjes.shaded.org.antlr.v4.runtime.misc.IntervalSet);
    Code:
       0: aload_0
       1: aload_1
       2: aload_2
       3: invokespecial #9                  // Method nl/basjes/shaded/org/antlr/v4/runtime/atn/SetTransition."<init>":(Lnl/basjes/shaded/org/antlr/v4/runtime/atn/ATNState;Lnl/basjes/shaded/org/antlr/v4/runtime/misc/IntervalSet;)V
       6: return

  public int getSerializationType();
    Code:
       0: bipush        8
       2: ireturn

  public boolean matches(int, int, int);
    Code:
       0: iload_1
       1: iload_2
       2: if_icmplt     24
       5: iload_1
       6: iload_3
       7: if_icmpgt     24
      10: aload_0
      11: iload_1
      12: iload_2
      13: iload_3
      14: invokespecial #21                 // Method nl/basjes/shaded/org/antlr/v4/runtime/atn/SetTransition.matches:(III)Z
      17: ifne          24
      20: iconst_1
      21: goto          25
      24: iconst_0
      25: ireturn

  public java.lang.String toString();
    Code:
       0: new           #29                 // class java/lang/StringBuilder
       3: dup
       4: invokespecial #32                 // Method java/lang/StringBuilder."<init>":()V
       7: bipush        126
       9: invokevirtual #36                 // Method java/lang/StringBuilder.append:(C)Ljava/lang/StringBuilder;
      12: aload_0
      13: invokespecial #38                 // Method nl/basjes/shaded/org/antlr/v4/runtime/atn/SetTransition.toString:()Ljava/lang/String;
      16: invokevirtual #41                 // Method java/lang/StringBuilder.append:(Ljava/lang/String;)Ljava/lang/StringBuilder;
      19: invokevirtual #42                 // Method java/lang/StringBuilder.toString:()Ljava/lang/String;
      22: areturn
}
