Compiled from "AuthenticationMgrSubjectCreatingInterceptor.java"
public class org.jboss.wsf.stack.cxf.security.authentication.AuthenticationMgrSubjectCreatingInterceptor extends org.jboss.wsf.stack.cxf.security.authentication.SubjectCreatingPolicyInterceptor {
  public org.jboss.wsf.stack.cxf.security.authentication.AuthenticationMgrSubjectCreatingInterceptor();
    Code:
       0: aload_0
       1: invokespecial #1                  // Method org/jboss/wsf/stack/cxf/security/authentication/SubjectCreatingPolicyInterceptor."<init>":()V
       4: return

  public void handleMessage(org.apache.cxf.message.Message) throws org.apache.cxf.interceptor.Fault;
    Code:
       0: aload_1
       1: ldc           #2                  // class org/jboss/security/plugins/JBossAuthenticationManager
       3: invokeinterface #3,  2            // InterfaceMethod org/apache/cxf/message/Message.get:(Ljava/lang/Class;)Ljava/lang/Object;
       8: checkcast     #2                  // class org/jboss/security/plugins/JBossAuthenticationManager
      11: astore_2
      12: aload_2
      13: ifnonnull     17
      16: return
      17: aload_1
      18: ldc           #4                  // class org/apache/cxf/security/SecurityContext
      20: invokeinterface #3,  2            // InterfaceMethod org/apache/cxf/message/Message.get:(Ljava/lang/Class;)Ljava/lang/Object;
      25: checkcast     #4                  // class org/apache/cxf/security/SecurityContext
      28: astore_3
      29: aload_3
      30: ifnull        42
      33: aload_3
      34: invokeinterface #5,  1            // InterfaceMethod org/apache/cxf/security/SecurityContext.getUserPrincipal:()Ljava/security/Principal;
      39: ifnonnull     51
      42: getstatic     #6                  // Field org/jboss/wsf/stack/cxf/Loggers.SECURITY_LOGGER:Lorg/jboss/wsf/stack/cxf/Loggers;
      45: invokeinterface #7,  1            // InterfaceMethod org/jboss/wsf/stack/cxf/Loggers.userPrincipalNotAvailableOnCurrentMessage:()V
      50: return
      51: aload_1
      52: ldc           #8                  // class org/apache/cxf/common/security/SecurityToken
      54: invokeinterface #3,  2            // InterfaceMethod org/apache/cxf/message/Message.get:(Ljava/lang/Class;)Ljava/lang/Object;
      59: checkcast     #8                  // class org/apache/cxf/common/security/SecurityToken
      62: astore        4
      64: aconst_null
      65: astore        5
      67: aload         4
      69: ifnull        146
      72: aload         4
      74: invokeinterface #9,  1            // InterfaceMethod org/apache/cxf/common/security/SecurityToken.getTokenType:()Lorg/apache/cxf/common/security/TokenType;
      79: getstatic     #10                 // Field org/apache/cxf/common/security/TokenType.UsernameToken:Lorg/apache/cxf/common/security/TokenType;
      82: if_acmpeq     101
      85: getstatic     #11                 // Field org/jboss/wsf/stack/cxf/Messages.MESSAGES:Lorg/jboss/wsf/stack/cxf/Messages;
      88: aload         4
      90: invokeinterface #9,  1            // InterfaceMethod org/apache/cxf/common/security/SecurityToken.getTokenType:()Lorg/apache/cxf/common/security/TokenType;
      95: invokeinterface #12,  2           // InterfaceMethod org/jboss/wsf/stack/cxf/Messages.unsupportedTokenType:(Ljava/lang/Object;)Ljava/lang/SecurityException;
     100: athrow
     101: aload         4
     103: checkcast     #13                 // class org/apache/cxf/common/security/UsernameToken
     106: astore        6
     108: aload_0
     109: getfield      #14                 // Field helper:Lorg/jboss/wsf/stack/cxf/security/authentication/SubjectCreator;
     112: aload_2
     113: aload         6
     115: invokevirtual #15                 // Method org/apache/cxf/common/security/UsernameToken.getName:()Ljava/lang/String;
     118: aload         6
     120: invokevirtual #16                 // Method org/apache/cxf/common/security/UsernameToken.getPassword:()Ljava/lang/String;
     123: aload         6
     125: invokevirtual #17                 // Method org/apache/cxf/common/security/UsernameToken.isHashed:()Z
     128: aload         6
     130: invokevirtual #18                 // Method org/apache/cxf/common/security/UsernameToken.getNonce:()Ljava/lang/String;
     133: aload         6
     135: invokevirtual #19                 // Method org/apache/cxf/common/security/UsernameToken.getCreatedTime:()Ljava/lang/String;
     138: invokevirtual #20                 // Method org/jboss/wsf/stack/cxf/security/authentication/SubjectCreator.createSubject:(Lorg/jboss/security/plugins/JBossAuthenticationManager;Ljava/lang/String;Ljava/lang/String;ZLjava/lang/String;Ljava/lang/String;)Ljavax/security/auth/Subject;
     141: astore        5
     143: goto          223
     146: aload_3
     147: invokeinterface #5,  1            // InterfaceMethod org/apache/cxf/security/SecurityContext.getUserPrincipal:()Ljava/security/Principal;
     152: astore        6
     154: aload         6
     156: instanceof    #21                 // class org/apache/wss4j/common/principal/UsernameTokenPrincipal
     159: ifne          171
     162: getstatic     #11                 // Field org/jboss/wsf/stack/cxf/Messages.MESSAGES:Lorg/jboss/wsf/stack/cxf/Messages;
     165: invokeinterface #22,  1           // InterfaceMethod org/jboss/wsf/stack/cxf/Messages.couldNotGetSubjectInfo:()Ljava/lang/SecurityException;
     170: athrow
     171: aload         6
     173: checkcast     #21                 // class org/apache/wss4j/common/principal/UsernameTokenPrincipal
     176: astore        7
     178: aload_0
     179: getfield      #14                 // Field helper:Lorg/jboss/wsf/stack/cxf/security/authentication/SubjectCreator;
     182: aload_2
     183: aload         7
     185: invokeinterface #23,  1           // InterfaceMethod org/apache/wss4j/common/principal/UsernameTokenPrincipal.getName:()Ljava/lang/String;
     190: aload         7
     192: invokeinterface #24,  1           // InterfaceMethod org/apache/wss4j/common/principal/UsernameTokenPrincipal.getPassword:()Ljava/lang/String;
     197: aload         7
     199: invokeinterface #25,  1           // InterfaceMethod org/apache/wss4j/common/principal/UsernameTokenPrincipal.isPasswordDigest:()Z
     204: aload         7
     206: invokeinterface #26,  1           // InterfaceMethod org/apache/wss4j/common/principal/UsernameTokenPrincipal.getNonce:()[B
     211: aload         7
     213: invokeinterface #27,  1           // InterfaceMethod org/apache/wss4j/common/principal/UsernameTokenPrincipal.getCreatedTime:()Ljava/lang/String;
     218: invokevirtual #28                 // Method org/jboss/wsf/stack/cxf/security/authentication/SubjectCreator.createSubject:(Lorg/jboss/security/plugins/JBossAuthenticationManager;Ljava/lang/String;Ljava/lang/String;Z[BLjava/lang/String;)Ljavax/security/auth/Subject;
     221: astore        5
     223: aload_0
     224: aload_3
     225: invokeinterface #5,  1            // InterfaceMethod org/apache/cxf/security/SecurityContext.getUserPrincipal:()Ljava/security/Principal;
     230: aload         5
     232: invokevirtual #29                 // Method getPrincipal:(Ljava/security/Principal;Ljavax/security/auth/Subject;)Ljava/security/Principal;
     235: astore        6
     237: aload_1
     238: ldc           #4                  // class org/apache/cxf/security/SecurityContext
     240: aload_0
     241: aload         6
     243: aload         5
     245: invokevirtual #30                 // Method createSecurityContext:(Ljava/security/Principal;Ljavax/security/auth/Subject;)Lorg/apache/cxf/security/SecurityContext;
     248: invokeinterface #31,  3           // InterfaceMethod org/apache/cxf/message/Message.put:(Ljava/lang/Class;Ljava/lang/Object;)V
     253: return
}
