Compiled from "SpringParameterResolverFactoryBean.java"
public class org.axonframework.spring.config.annotation.SpringParameterResolverFactoryBean implements org.springframework.beans.factory.FactoryBean<org.axonframework.messaging.annotation.ParameterResolverFactory>, org.springframework.beans.factory.BeanClassLoaderAware, org.springframework.beans.factory.InitializingBean, org.springframework.context.ApplicationContextAware {
  private final java.util.List<org.axonframework.messaging.annotation.ParameterResolverFactory> factories;

  private java.lang.ClassLoader classLoader;

  private org.springframework.context.ApplicationContext applicationContext;

  public org.axonframework.spring.config.annotation.SpringParameterResolverFactoryBean();
    Code:
       0: aload_0
       1: invokespecial #1                  // Method java/lang/Object."<init>":()V
       4: aload_0
       5: new           #2                  // class java/util/ArrayList
       8: dup
       9: invokespecial #3                  // Method java/util/ArrayList."<init>":()V
      12: putfield      #4                  // Field factories:Ljava/util/List;
      15: return

  public org.axonframework.messaging.annotation.ParameterResolverFactory getObject();
    Code:
       0: aload_0
       1: getfield      #4                  // Field factories:Ljava/util/List;
       4: invokestatic  #5                  // Method org/axonframework/messaging/annotation/MultiParameterResolverFactory.ordered:(Ljava/util/List;)Lorg/axonframework/messaging/annotation/MultiParameterResolverFactory;
       7: areturn

  public java.lang.Class<?> getObjectType();
    Code:
       0: ldc           #6                  // class org/axonframework/messaging/annotation/ParameterResolverFactory
       2: areturn

  public boolean isSingleton();
    Code:
       0: iconst_1
       1: ireturn

  public void afterPropertiesSet();
    Code:
       0: aload_0
       1: getfield      #4                  // Field factories:Ljava/util/List;
       4: aload_0
       5: getfield      #7                  // Field classLoader:Ljava/lang/ClassLoader;
       8: invokestatic  #8                  // Method org/axonframework/messaging/annotation/ClasspathParameterResolverFactory.forClassLoader:(Ljava/lang/ClassLoader;)Lorg/axonframework/messaging/annotation/ParameterResolverFactory;
      11: invokeinterface #9,  2            // InterfaceMethod java/util/List.add:(Ljava/lang/Object;)Z
      16: pop
      17: aload_0
      18: getfield      #4                  // Field factories:Ljava/util/List;
      21: new           #10                 // class org/axonframework/spring/config/annotation/SpringBeanDependencyResolverFactory
      24: dup
      25: aload_0
      26: getfield      #11                 // Field applicationContext:Lorg/springframework/context/ApplicationContext;
      29: invokespecial #12                 // Method org/axonframework/spring/config/annotation/SpringBeanDependencyResolverFactory."<init>":(Lorg/springframework/context/ApplicationContext;)V
      32: invokeinterface #9,  2            // InterfaceMethod java/util/List.add:(Ljava/lang/Object;)Z
      37: pop
      38: aload_0
      39: getfield      #4                  // Field factories:Ljava/util/List;
      42: new           #13                 // class org/axonframework/spring/config/annotation/SpringBeanParameterResolverFactory
      45: dup
      46: aload_0
      47: getfield      #11                 // Field applicationContext:Lorg/springframework/context/ApplicationContext;
      50: invokespecial #14                 // Method org/axonframework/spring/config/annotation/SpringBeanParameterResolverFactory."<init>":(Lorg/springframework/context/ApplicationContext;)V
      53: invokeinterface #9,  2            // InterfaceMethod java/util/List.add:(Ljava/lang/Object;)Z
      58: pop
      59: return

  public void setAdditionalFactories(java.util.List<org.axonframework.messaging.annotation.ParameterResolverFactory>);
    Code:
       0: aload_0
       1: getfield      #4                  // Field factories:Ljava/util/List;
       4: aload_1
       5: invokeinterface #15,  2           // InterfaceMethod java/util/List.addAll:(Ljava/util/Collection;)Z
      10: pop
      11: return

  public void setBeanClassLoader(java.lang.ClassLoader);
    Code:
       0: aload_0
       1: aload_1
       2: putfield      #7                  // Field classLoader:Ljava/lang/ClassLoader;
       5: return

  public void setApplicationContext(org.springframework.context.ApplicationContext) throws org.springframework.beans.BeansException;
    Code:
       0: aload_0
       1: aload_1
       2: putfield      #11                 // Field applicationContext:Lorg/springframework/context/ApplicationContext;
       5: return

  public java.lang.Object getObject() throws java.lang.Exception;
    Code:
       0: aload_0
       1: invokevirtual #16                 // Method getObject:()Lorg/axonframework/messaging/annotation/ParameterResolverFactory;
       4: areturn
}
