Compiled from "QuerySpaceUidNotRegisteredException.java"
public class org.hibernate.loader.plan.spi.QuerySpaceUidNotRegisteredException extends org.hibernate.HibernateException {
  public org.hibernate.loader.plan.spi.QuerySpaceUidNotRegisteredException(java.lang.String);
    Code:
       0: aload_0
       1: aload_1
       2: invokestatic  #1                  // Method generateMessage:(Ljava/lang/String;)Ljava/lang/String;
       5: invokespecial #2                  // Method org/hibernate/HibernateException."<init>":(Ljava/lang/String;)V
       8: return

  private static java.lang.String generateMessage(java.lang.String);
    Code:
       0: new           #3                  // class java/lang/StringBuilder
       3: dup
       4: invokespecial #4                  // Method java/lang/StringBuilder."<init>":()V
       7: ldc           #5                  // String Given uid [
       9: invokevirtual #6                  // Method java/lang/StringBuilder.append:(Ljava/lang/String;)Ljava/lang/StringBuilder;
      12: aload_0
      13: invokevirtual #6                  // Method java/lang/StringBuilder.append:(Ljava/lang/String;)Ljava/lang/StringBuilder;
      16: ldc           #7                  // String ] could not be resolved to a QuerySpace
      18: invokevirtual #6                  // Method java/lang/StringBuilder.append:(Ljava/lang/String;)Ljava/lang/StringBuilder;
      21: invokevirtual #8                  // Method java/lang/StringBuilder.toString:()Ljava/lang/String;
      24: areturn

  public org.hibernate.loader.plan.spi.QuerySpaceUidNotRegisteredException(java.lang.String, java.lang.Throwable);
    Code:
       0: aload_0
       1: aload_1
       2: invokestatic  #1                  // Method generateMessage:(Ljava/lang/String;)Ljava/lang/String;
       5: aload_2
       6: invokespecial #9                  // Method org/hibernate/HibernateException."<init>":(Ljava/lang/String;Ljava/lang/Throwable;)V
       9: return
}
