Compiled from "AddTagsRequest.java"
final class software.amazon.awssdk.services.elasticloadbalancing.model.AddTagsRequest$BuilderImpl extends software.amazon.awssdk.services.elasticloadbalancing.model.ElasticLoadBalancingRequest$BuilderImpl implements software.amazon.awssdk.services.elasticloadbalancing.model.AddTagsRequest$Builder {
  private java.util.List<java.lang.String> loadBalancerNames;

  private java.util.List<software.amazon.awssdk.services.elasticloadbalancing.model.Tag> tags;

  private software.amazon.awssdk.services.elasticloadbalancing.model.AddTagsRequest$BuilderImpl();
    Code:
       0: aload_0
       1: invokespecial #5                  // Method software/amazon/awssdk/services/elasticloadbalancing/model/ElasticLoadBalancingRequest$BuilderImpl."<init>":()V
       4: aload_0
       5: invokestatic  #6                  // Method software/amazon/awssdk/core/util/DefaultSdkAutoConstructList.getInstance:()Lsoftware/amazon/awssdk/core/util/DefaultSdkAutoConstructList;
       8: putfield      #4                  // Field loadBalancerNames:Ljava/util/List;
      11: aload_0
      12: invokestatic  #6                  // Method software/amazon/awssdk/core/util/DefaultSdkAutoConstructList.getInstance:()Lsoftware/amazon/awssdk/core/util/DefaultSdkAutoConstructList;
      15: putfield      #3                  // Field tags:Ljava/util/List;
      18: return

  private software.amazon.awssdk.services.elasticloadbalancing.model.AddTagsRequest$BuilderImpl(software.amazon.awssdk.services.elasticloadbalancing.model.AddTagsRequest);
    Code:
       0: aload_0
       1: aload_1
       2: invokespecial #7                  // Method software/amazon/awssdk/services/elasticloadbalancing/model/ElasticLoadBalancingRequest$BuilderImpl."<init>":(Lsoftware/amazon/awssdk/services/elasticloadbalancing/model/ElasticLoadBalancingRequest;)V
       5: aload_0
       6: invokestatic  #6                  // Method software/amazon/awssdk/core/util/DefaultSdkAutoConstructList.getInstance:()Lsoftware/amazon/awssdk/core/util/DefaultSdkAutoConstructList;
       9: putfield      #4                  // Field loadBalancerNames:Ljava/util/List;
      12: aload_0
      13: invokestatic  #6                  // Method software/amazon/awssdk/core/util/DefaultSdkAutoConstructList.getInstance:()Lsoftware/amazon/awssdk/core/util/DefaultSdkAutoConstructList;
      16: putfield      #3                  // Field tags:Ljava/util/List;
      19: aload_0
      20: aload_1
      21: invokestatic  #8                  // Method software/amazon/awssdk/services/elasticloadbalancing/model/AddTagsRequest.access$400:(Lsoftware/amazon/awssdk/services/elasticloadbalancing/model/AddTagsRequest;)Ljava/util/List;
      24: invokevirtual #9                  // Method loadBalancerNames:(Ljava/util/Collection;)Lsoftware/amazon/awssdk/services/elasticloadbalancing/model/AddTagsRequest$Builder;
      27: pop
      28: aload_0
      29: aload_1
      30: invokestatic  #10                 // Method software/amazon/awssdk/services/elasticloadbalancing/model/AddTagsRequest.access$500:(Lsoftware/amazon/awssdk/services/elasticloadbalancing/model/AddTagsRequest;)Ljava/util/List;
      33: invokevirtual #11                 // Method tags:(Ljava/util/Collection;)Lsoftware/amazon/awssdk/services/elasticloadbalancing/model/AddTagsRequest$Builder;
      36: pop
      37: return

  public final java.util.Collection<java.lang.String> getLoadBalancerNames();
    Code:
       0: aload_0
       1: getfield      #4                  // Field loadBalancerNames:Ljava/util/List;
       4: areturn

  public final software.amazon.awssdk.services.elasticloadbalancing.model.AddTagsRequest$Builder loadBalancerNames(java.util.Collection<java.lang.String>);
    Code:
       0: aload_0
       1: aload_1
       2: invokestatic  #12                 // Method software/amazon/awssdk/services/elasticloadbalancing/model/LoadBalancerNamesCopier.copy:(Ljava/util/Collection;)Ljava/util/List;
       5: putfield      #4                  // Field loadBalancerNames:Ljava/util/List;
       8: aload_0
       9: areturn

  public final software.amazon.awssdk.services.elasticloadbalancing.model.AddTagsRequest$Builder loadBalancerNames(java.lang.String...);
    Code:
       0: aload_0
       1: aload_1
       2: invokestatic  #13                 // Method java/util/Arrays.asList:([Ljava/lang/Object;)Ljava/util/List;
       5: invokevirtual #9                  // Method loadBalancerNames:(Ljava/util/Collection;)Lsoftware/amazon/awssdk/services/elasticloadbalancing/model/AddTagsRequest$Builder;
       8: pop
       9: aload_0
      10: areturn

  public final void setLoadBalancerNames(java.util.Collection<java.lang.String>);
    Code:
       0: aload_0
       1: aload_1
       2: invokestatic  #12                 // Method software/amazon/awssdk/services/elasticloadbalancing/model/LoadBalancerNamesCopier.copy:(Ljava/util/Collection;)Ljava/util/List;
       5: putfield      #4                  // Field loadBalancerNames:Ljava/util/List;
       8: return

  public final java.util.Collection<software.amazon.awssdk.services.elasticloadbalancing.model.Tag$Builder> getTags();
    Code:
       0: aload_0
       1: getfield      #3                  // Field tags:Ljava/util/List;
       4: ifnull        40
       7: aload_0
       8: getfield      #3                  // Field tags:Ljava/util/List;
      11: invokeinterface #14,  1           // InterfaceMethod java/util/List.stream:()Ljava/util/stream/Stream;
      16: invokedynamic #15,  0             // InvokeDynamic #0:apply:()Ljava/util/function/Function;
      21: invokeinterface #16,  2           // InterfaceMethod java/util/stream/Stream.map:(Ljava/util/function/Function;)Ljava/util/stream/Stream;
      26: invokestatic  #17                 // Method java/util/stream/Collectors.toList:()Ljava/util/stream/Collector;
      29: invokeinterface #18,  2           // InterfaceMethod java/util/stream/Stream.collect:(Ljava/util/stream/Collector;)Ljava/lang/Object;
      34: checkcast     #19                 // class java/util/Collection
      37: goto          41
      40: aconst_null
      41: areturn

  public final software.amazon.awssdk.services.elasticloadbalancing.model.AddTagsRequest$Builder tags(java.util.Collection<software.amazon.awssdk.services.elasticloadbalancing.model.Tag>);
    Code:
       0: aload_0
       1: aload_1
       2: invokestatic  #20                 // Method software/amazon/awssdk/services/elasticloadbalancing/model/TagListCopier.copy:(Ljava/util/Collection;)Ljava/util/List;
       5: putfield      #3                  // Field tags:Ljava/util/List;
       8: aload_0
       9: areturn

  public final software.amazon.awssdk.services.elasticloadbalancing.model.AddTagsRequest$Builder tags(software.amazon.awssdk.services.elasticloadbalancing.model.Tag...);
    Code:
       0: aload_0
       1: aload_1
       2: invokestatic  #13                 // Method java/util/Arrays.asList:([Ljava/lang/Object;)Ljava/util/List;
       5: invokevirtual #11                 // Method tags:(Ljava/util/Collection;)Lsoftware/amazon/awssdk/services/elasticloadbalancing/model/AddTagsRequest$Builder;
       8: pop
       9: aload_0
      10: areturn

  public final software.amazon.awssdk.services.elasticloadbalancing.model.AddTagsRequest$Builder tags(java.util.function.Consumer<software.amazon.awssdk.services.elasticloadbalancing.model.Tag$Builder>...);
    Code:
       0: aload_0
       1: aload_1
       2: invokestatic  #21                 // InterfaceMethod java/util/stream/Stream.of:([Ljava/lang/Object;)Ljava/util/stream/Stream;
       5: invokedynamic #22,  0             // InvokeDynamic #1:apply:()Ljava/util/function/Function;
      10: invokeinterface #16,  2           // InterfaceMethod java/util/stream/Stream.map:(Ljava/util/function/Function;)Ljava/util/stream/Stream;
      15: invokestatic  #17                 // Method java/util/stream/Collectors.toList:()Ljava/util/stream/Collector;
      18: invokeinterface #18,  2           // InterfaceMethod java/util/stream/Stream.collect:(Ljava/util/stream/Collector;)Ljava/lang/Object;
      23: checkcast     #19                 // class java/util/Collection
      26: invokevirtual #11                 // Method tags:(Ljava/util/Collection;)Lsoftware/amazon/awssdk/services/elasticloadbalancing/model/AddTagsRequest$Builder;
      29: pop
      30: aload_0
      31: areturn

  public final void setTags(java.util.Collection<software.amazon.awssdk.services.elasticloadbalancing.model.Tag$BuilderImpl>);
    Code:
       0: aload_0
       1: aload_1
       2: invokestatic  #23                 // Method software/amazon/awssdk/services/elasticloadbalancing/model/TagListCopier.copyFromBuilder:(Ljava/util/Collection;)Ljava/util/List;
       5: putfield      #3                  // Field tags:Ljava/util/List;
       8: return

  public software.amazon.awssdk.services.elasticloadbalancing.model.AddTagsRequest$Builder overrideConfiguration(software.amazon.awssdk.awscore.AwsRequestOverrideConfiguration);
    Code:
       0: aload_0
       1: aload_1
       2: invokespecial #24                 // Method software/amazon/awssdk/services/elasticloadbalancing/model/ElasticLoadBalancingRequest$BuilderImpl.overrideConfiguration:(Lsoftware/amazon/awssdk/awscore/AwsRequestOverrideConfiguration;)Lsoftware/amazon/awssdk/awscore/AwsRequest$Builder;
       5: pop
       6: aload_0
       7: areturn

  public software.amazon.awssdk.services.elasticloadbalancing.model.AddTagsRequest$Builder overrideConfiguration(java.util.function.Consumer<software.amazon.awssdk.awscore.AwsRequestOverrideConfiguration$Builder>);
    Code:
       0: aload_0
       1: aload_1
       2: invokespecial #25                 // Method software/amazon/awssdk/services/elasticloadbalancing/model/ElasticLoadBalancingRequest$BuilderImpl.overrideConfiguration:(Ljava/util/function/Consumer;)Lsoftware/amazon/awssdk/awscore/AwsRequest$Builder;
       5: pop
       6: aload_0
       7: areturn

  public software.amazon.awssdk.services.elasticloadbalancing.model.AddTagsRequest build();
    Code:
       0: new           #26                 // class software/amazon/awssdk/services/elasticloadbalancing/model/AddTagsRequest
       3: dup
       4: aload_0
       5: aconst_null
       6: invokespecial #27                 // Method software/amazon/awssdk/services/elasticloadbalancing/model/AddTagsRequest."<init>":(Lsoftware/amazon/awssdk/services/elasticloadbalancing/model/AddTagsRequest$BuilderImpl;Lsoftware/amazon/awssdk/services/elasticloadbalancing/model/AddTagsRequest$1;)V
       9: areturn

  public java.util.List<software.amazon.awssdk.core.SdkField<?>> sdkFields();
    Code:
       0: invokestatic  #28                 // Method software/amazon/awssdk/services/elasticloadbalancing/model/AddTagsRequest.access$700:()Ljava/util/List;
       3: areturn

  public software.amazon.awssdk.services.elasticloadbalancing.model.ElasticLoadBalancingRequest build();
    Code:
       0: aload_0
       1: invokevirtual #29                 // Method build:()Lsoftware/amazon/awssdk/services/elasticloadbalancing/model/AddTagsRequest;
       4: areturn

  public software.amazon.awssdk.awscore.AwsRequest build();
    Code:
       0: aload_0
       1: invokevirtual #29                 // Method build:()Lsoftware/amazon/awssdk/services/elasticloadbalancing/model/AddTagsRequest;
       4: areturn

  public software.amazon.awssdk.awscore.AwsRequest$Builder overrideConfiguration(java.util.function.Consumer);
    Code:
       0: aload_0
       1: aload_1
       2: invokevirtual #30                 // Method overrideConfiguration:(Ljava/util/function/Consumer;)Lsoftware/amazon/awssdk/services/elasticloadbalancing/model/AddTagsRequest$Builder;
       5: areturn

  public software.amazon.awssdk.awscore.AwsRequest$Builder overrideConfiguration(software.amazon.awssdk.awscore.AwsRequestOverrideConfiguration);
    Code:
       0: aload_0
       1: aload_1
       2: invokevirtual #31                 // Method overrideConfiguration:(Lsoftware/amazon/awssdk/awscore/AwsRequestOverrideConfiguration;)Lsoftware/amazon/awssdk/services/elasticloadbalancing/model/AddTagsRequest$Builder;
       5: areturn

  public software.amazon.awssdk.core.SdkRequest build();
    Code:
       0: aload_0
       1: invokevirtual #29                 // Method build:()Lsoftware/amazon/awssdk/services/elasticloadbalancing/model/AddTagsRequest;
       4: areturn

  public java.lang.Object build();
    Code:
       0: aload_0
       1: invokevirtual #29                 // Method build:()Lsoftware/amazon/awssdk/services/elasticloadbalancing/model/AddTagsRequest;
       4: areturn

  private static software.amazon.awssdk.services.elasticloadbalancing.model.Tag lambda$tags$0(java.util.function.Consumer);
    Code:
       0: invokestatic  #32                 // Method software/amazon/awssdk/services/elasticloadbalancing/model/Tag.builder:()Lsoftware/amazon/awssdk/services/elasticloadbalancing/model/Tag$Builder;
       3: aload_0
       4: invokeinterface #33,  2           // InterfaceMethod software/amazon/awssdk/services/elasticloadbalancing/model/Tag$Builder.applyMutation:(Ljava/util/function/Consumer;)Lsoftware/amazon/awssdk/utils/builder/SdkBuilder;
       9: checkcast     #34                 // class software/amazon/awssdk/services/elasticloadbalancing/model/Tag$Builder
      12: invokeinterface #35,  1           // InterfaceMethod software/amazon/awssdk/services/elasticloadbalancing/model/Tag$Builder.build:()Ljava/lang/Object;
      17: checkcast     #36                 // class software/amazon/awssdk/services/elasticloadbalancing/model/Tag
      20: areturn

  static java.util.List access$000(software.amazon.awssdk.services.elasticloadbalancing.model.AddTagsRequest$BuilderImpl);
    Code:
       0: aload_0
       1: getfield      #4                  // Field loadBalancerNames:Ljava/util/List;
       4: areturn

  static java.util.List access$100(software.amazon.awssdk.services.elasticloadbalancing.model.AddTagsRequest$BuilderImpl);
    Code:
       0: aload_0
       1: getfield      #3                  // Field tags:Ljava/util/List;
       4: areturn

  software.amazon.awssdk.services.elasticloadbalancing.model.AddTagsRequest$BuilderImpl(software.amazon.awssdk.services.elasticloadbalancing.model.AddTagsRequest, software.amazon.awssdk.services.elasticloadbalancing.model.AddTagsRequest$1);
    Code:
       0: aload_0
       1: aload_1
       2: invokespecial #2                  // Method "<init>":(Lsoftware/amazon/awssdk/services/elasticloadbalancing/model/AddTagsRequest;)V
       5: return

  software.amazon.awssdk.services.elasticloadbalancing.model.AddTagsRequest$BuilderImpl(software.amazon.awssdk.services.elasticloadbalancing.model.AddTagsRequest$1);
    Code:
       0: aload_0
       1: invokespecial #1                  // Method "<init>":()V
       4: return
}
