Compiled from "DataSourceUrlResolver.java"
public class org.apache.commons.mail.resolver.DataSourceUrlResolver extends org.apache.commons.mail.resolver.DataSourceBaseResolver {
  private final java.net.URL baseUrl;

  public org.apache.commons.mail.resolver.DataSourceUrlResolver(java.net.URL);
    Code:
       0: aload_0
       1: invokespecial #1                  // Method org/apache/commons/mail/resolver/DataSourceBaseResolver."<init>":()V
       4: aload_0
       5: aload_1
       6: putfield      #2                  // Field baseUrl:Ljava/net/URL;
       9: return

  public org.apache.commons.mail.resolver.DataSourceUrlResolver(java.net.URL, boolean);
    Code:
       0: aload_0
       1: iload_2
       2: invokespecial #3                  // Method org/apache/commons/mail/resolver/DataSourceBaseResolver."<init>":(Z)V
       5: aload_0
       6: aload_1
       7: putfield      #2                  // Field baseUrl:Ljava/net/URL;
      10: return

  public java.net.URL getBaseUrl();
    Code:
       0: aload_0
       1: getfield      #2                  // Field baseUrl:Ljava/net/URL;
       4: areturn

  public javax.activation.DataSource resolve(java.lang.String) throws java.io.IOException;
    Code:
       0: aload_0
       1: aload_1
       2: aload_0
       3: invokevirtual #4                  // Method isLenient:()Z
       6: invokevirtual #5                  // Method resolve:(Ljava/lang/String;Z)Ljavax/activation/DataSource;
       9: areturn

  public javax.activation.DataSource resolve(java.lang.String, boolean) throws java.io.IOException;
    Code:
       0: aconst_null
       1: astore_3
       2: aload_0
       3: aload_1
       4: invokevirtual #6                  // Method isCid:(Ljava/lang/String;)Z
       7: ifne          34
      10: aload_0
      11: aload_1
      12: invokevirtual #7                  // Method createUrl:(Ljava/lang/String;)Ljava/net/URL;
      15: astore        4
      17: new           #8                  // class javax/activation/URLDataSource
      20: dup
      21: aload         4
      23: invokespecial #9                  // Method javax/activation/URLDataSource."<init>":(Ljava/net/URL;)V
      26: astore_3
      27: aload_3
      28: invokeinterface #10,  1           // InterfaceMethod javax/activation/DataSource.getInputStream:()Ljava/io/InputStream;
      33: pop
      34: aload_3
      35: areturn
      36: astore        4
      38: iload_2
      39: ifeq          44
      42: aconst_null
      43: areturn
      44: aload         4
      46: athrow
    Exception table:
       from    to  target type
           2    35    36   Class java/io/IOException

  protected java.net.URL createUrl(java.lang.String) throws java.net.MalformedURLException;
    Code:
       0: aload_0
       1: getfield      #2                  // Field baseUrl:Ljava/net/URL;
       4: ifnonnull     16
       7: new           #12                 // class java/net/URL
      10: dup
      11: aload_1
      12: invokespecial #13                 // Method java/net/URL."<init>":(Ljava/lang/String;)V
      15: areturn
      16: aload_1
      17: ifnull        27
      20: aload_1
      21: invokevirtual #14                 // Method java/lang/String.length:()I
      24: ifne          37
      27: new           #15                 // class java/lang/IllegalArgumentException
      30: dup
      31: ldc           #16                 // String No resource defined
      33: invokespecial #17                 // Method java/lang/IllegalArgumentException."<init>":(Ljava/lang/String;)V
      36: athrow
      37: aload_0
      38: aload_1
      39: invokevirtual #18                 // Method isFileUrl:(Ljava/lang/String;)Z
      42: ifne          53
      45: aload_0
      46: aload_1
      47: invokevirtual #19                 // Method isHttpUrl:(Ljava/lang/String;)Z
      50: ifeq          62
      53: new           #12                 // class java/net/URL
      56: dup
      57: aload_1
      58: invokespecial #13                 // Method java/net/URL."<init>":(Ljava/lang/String;)V
      61: areturn
      62: new           #12                 // class java/net/URL
      65: dup
      66: aload_0
      67: invokevirtual #20                 // Method getBaseUrl:()Ljava/net/URL;
      70: aload_1
      71: ldc           #21                 // String &amp;
      73: ldc           #22                 // String &
      75: invokevirtual #23                 // Method java/lang/String.replaceAll:(Ljava/lang/String;Ljava/lang/String;)Ljava/lang/String;
      78: invokespecial #24                 // Method java/net/URL."<init>":(Ljava/net/URL;Ljava/lang/String;)V
      81: areturn
}
