Compiled from "KryoPoolQueueImpl.java"
class com.esotericsoftware.kryo.pool.KryoPoolQueueImpl implements com.esotericsoftware.kryo.pool.KryoPool {
  private final java.util.Queue<com.esotericsoftware.kryo.Kryo> queue;

  private final com.esotericsoftware.kryo.pool.KryoFactory factory;

  com.esotericsoftware.kryo.pool.KryoPoolQueueImpl(com.esotericsoftware.kryo.pool.KryoFactory, java.util.Queue<com.esotericsoftware.kryo.Kryo>);
    Code:
       0: aload_0
       1: invokespecial #1                  // Method java/lang/Object."<init>":()V
       4: aload_0
       5: aload_1
       6: putfield      #2                  // Field factory:Lcom/esotericsoftware/kryo/pool/KryoFactory;
       9: aload_0
      10: aload_2
      11: putfield      #3                  // Field queue:Ljava/util/Queue;
      14: return

  public int size();
    Code:
       0: aload_0
       1: getfield      #3                  // Field queue:Ljava/util/Queue;
       4: invokeinterface #4,  1            // InterfaceMethod java/util/Queue.size:()I
       9: ireturn

  public com.esotericsoftware.kryo.Kryo borrow();
    Code:
       0: aload_0
       1: getfield      #3                  // Field queue:Ljava/util/Queue;
       4: invokeinterface #5,  1            // InterfaceMethod java/util/Queue.poll:()Ljava/lang/Object;
       9: checkcast     #6                  // class com/esotericsoftware/kryo/Kryo
      12: dup
      13: astore_1
      14: ifnull        19
      17: aload_1
      18: areturn
      19: aload_0
      20: getfield      #2                  // Field factory:Lcom/esotericsoftware/kryo/pool/KryoFactory;
      23: invokeinterface #7,  1            // InterfaceMethod com/esotericsoftware/kryo/pool/KryoFactory.create:()Lcom/esotericsoftware/kryo/Kryo;
      28: areturn

  public void release(com.esotericsoftware.kryo.Kryo);
    Code:
       0: aload_0
       1: getfield      #3                  // Field queue:Ljava/util/Queue;
       4: aload_1
       5: invokeinterface #8,  2            // InterfaceMethod java/util/Queue.offer:(Ljava/lang/Object;)Z
      10: pop
      11: return

  public <T> T run(com.esotericsoftware.kryo.pool.KryoCallback<T>);
    Code:
       0: aload_0
       1: invokevirtual #9                  // Method borrow:()Lcom/esotericsoftware/kryo/Kryo;
       4: astore_2
       5: aload_1
       6: aload_2
       7: invokeinterface #10,  2           // InterfaceMethod com/esotericsoftware/kryo/pool/KryoCallback.execute:(Lcom/esotericsoftware/kryo/Kryo;)Ljava/lang/Object;
      12: astore_3
      13: aload_0
      14: aload_2
      15: invokevirtual #11                 // Method release:(Lcom/esotericsoftware/kryo/Kryo;)V
      18: aload_3
      19: areturn
      20: astore        4
      22: aload_0
      23: aload_2
      24: invokevirtual #11                 // Method release:(Lcom/esotericsoftware/kryo/Kryo;)V
      27: aload         4
      29: athrow
    Exception table:
       from    to  target type
           5    13    20   any
          20    22    20   any

  public void clear();
    Code:
       0: aload_0
       1: getfield      #3                  // Field queue:Ljava/util/Queue;
       4: invokeinterface #12,  1           // InterfaceMethod java/util/Queue.clear:()V
       9: return
}
