Compiled from "MappedByAnnotationResolver.java"
public class org.jboss.resteasy.spi.touri.MappedByAnnotationResolver extends org.jboss.resteasy.spi.touri.AbstractURITemplateAnnotationResolver {
  public org.jboss.resteasy.spi.touri.MappedByAnnotationResolver();
    Code:
       0: aload_0
       1: invokespecial #1                  // Method org/jboss/resteasy/spi/touri/AbstractURITemplateAnnotationResolver."<init>":()V
       4: return

  protected java.lang.Class<? extends java.lang.annotation.Annotation> getAnnotationType();
    Code:
       0: ldc           #2                  // class org/jboss/resteasy/spi/touri/MappedBy
       2: areturn

  protected org.jboss.resteasy.specimpl.ResteasyUriBuilder getUriBuilder(java.lang.Class<? extends java.lang.Object>);
    Code:
       0: aload_1
       1: ldc           #2                  // class org/jboss/resteasy/spi/touri/MappedBy
       3: invokevirtual #3                  // Method java/lang/Class.getAnnotation:(Ljava/lang/Class;)Ljava/lang/annotation/Annotation;
       6: checkcast     #2                  // class org/jboss/resteasy/spi/touri/MappedBy
       9: astore_2
      10: new           #4                  // class org/jboss/resteasy/specimpl/ResteasyUriBuilder
      13: dup
      14: invokespecial #5                  // Method org/jboss/resteasy/specimpl/ResteasyUriBuilder."<init>":()V
      17: astore_3
      18: aload_2
      19: invokeinterface #6,  1            // InterfaceMethod org/jboss/resteasy/spi/touri/MappedBy.resource:()Ljava/lang/Class;
      24: astore        4
      26: aload_3
      27: aload         4
      29: invokevirtual #7                  // Method org/jboss/resteasy/specimpl/ResteasyUriBuilder.path:(Ljava/lang/Class;)Ljavax/ws/rs/core/UriBuilder;
      32: pop
      33: aload_2
      34: invokeinterface #8,  1            // InterfaceMethod org/jboss/resteasy/spi/touri/MappedBy.method:()Ljava/lang/String;
      39: astore        5
      41: aload         5
      43: ifnull        63
      46: aload         5
      48: invokevirtual #9                  // Method java/lang/String.length:()I
      51: ifle          63
      54: aload_3
      55: aload         4
      57: aload         5
      59: invokevirtual #10                 // Method org/jboss/resteasy/specimpl/ResteasyUriBuilder.path:(Ljava/lang/Class;Ljava/lang/String;)Ljavax/ws/rs/core/UriBuilder;
      62: pop
      63: aload_3
      64: areturn
}
