Compiled from "OntologySaver.java"
final class org.protege.editor.owl.model.io.OntologySaver$OntologySaveDescriptor {
  private final org.semanticweb.owlapi.model.OWLOntology ontology;

  private final org.semanticweb.owlapi.model.OWLDocumentFormat documentFormat;

  private final org.semanticweb.owlapi.model.IRI documentIRI;

  public org.protege.editor.owl.model.io.OntologySaver$OntologySaveDescriptor(org.semanticweb.owlapi.model.OWLOntology, org.semanticweb.owlapi.model.OWLDocumentFormat, org.semanticweb.owlapi.model.IRI);
    Code:
       0: aload_0
       1: invokespecial #1                  // Method java/lang/Object."<init>":()V
       4: aload_0
       5: aload_1
       6: invokestatic  #2                  // Method com/google/common/base/Preconditions.checkNotNull:(Ljava/lang/Object;)Ljava/lang/Object;
       9: checkcast     #3                  // class org/semanticweb/owlapi/model/OWLOntology
      12: putfield      #4                  // Field ontology:Lorg/semanticweb/owlapi/model/OWLOntology;
      15: aload_0
      16: aload_2
      17: invokestatic  #2                  // Method com/google/common/base/Preconditions.checkNotNull:(Ljava/lang/Object;)Ljava/lang/Object;
      20: checkcast     #5                  // class org/semanticweb/owlapi/model/OWLDocumentFormat
      23: putfield      #6                  // Field documentFormat:Lorg/semanticweb/owlapi/model/OWLDocumentFormat;
      26: aload_0
      27: aload_3
      28: invokestatic  #2                  // Method com/google/common/base/Preconditions.checkNotNull:(Ljava/lang/Object;)Ljava/lang/Object;
      31: checkcast     #7                  // class org/semanticweb/owlapi/model/IRI
      34: putfield      #8                  // Field documentIRI:Lorg/semanticweb/owlapi/model/IRI;
      37: return

  public org.semanticweb.owlapi.model.OWLOntology getOntology();
    Code:
       0: aload_0
       1: getfield      #4                  // Field ontology:Lorg/semanticweb/owlapi/model/OWLOntology;
       4: areturn

  public org.semanticweb.owlapi.model.OWLDocumentFormat getDocumentFormat();
    Code:
       0: aload_0
       1: getfield      #6                  // Field documentFormat:Lorg/semanticweb/owlapi/model/OWLDocumentFormat;
       4: areturn

  public org.semanticweb.owlapi.model.IRI getDocumentIRI();
    Code:
       0: aload_0
       1: getfield      #8                  // Field documentIRI:Lorg/semanticweb/owlapi/model/IRI;
       4: areturn
}
