Compiled from "AbstractBeanFactory.java"
class org.springframework.beans.factory.support.AbstractBeanFactory$4 implements java.security.PrivilegedExceptionAction<java.lang.Class<?>> {
  final org.springframework.beans.factory.support.RootBeanDefinition val$mbd;

  final java.lang.Class[] val$typesToMatch;

  final org.springframework.beans.factory.support.AbstractBeanFactory this$0;

  org.springframework.beans.factory.support.AbstractBeanFactory$4(org.springframework.beans.factory.support.AbstractBeanFactory, org.springframework.beans.factory.support.RootBeanDefinition, java.lang.Class[]);
    Code:
       0: aload_0
       1: aload_1
       2: putfield      #1                  // Field this$0:Lorg/springframework/beans/factory/support/AbstractBeanFactory;
       5: aload_0
       6: aload_2
       7: putfield      #2                  // Field val$mbd:Lorg/springframework/beans/factory/support/RootBeanDefinition;
      10: aload_0
      11: aload_3
      12: putfield      #3                  // Field val$typesToMatch:[Ljava/lang/Class;
      15: aload_0
      16: invokespecial #4                  // Method java/lang/Object."<init>":()V
      19: return

  public java.lang.Class<?> run() throws java.lang.Exception;
    Code:
       0: aload_0
       1: getfield      #1                  // Field this$0:Lorg/springframework/beans/factory/support/AbstractBeanFactory;
       4: aload_0
       5: getfield      #2                  // Field val$mbd:Lorg/springframework/beans/factory/support/RootBeanDefinition;
       8: aload_0
       9: getfield      #3                  // Field val$typesToMatch:[Ljava/lang/Class;
      12: invokestatic  #5                  // Method org/springframework/beans/factory/support/AbstractBeanFactory.access$000:(Lorg/springframework/beans/factory/support/AbstractBeanFactory;Lorg/springframework/beans/factory/support/RootBeanDefinition;[Ljava/lang/Class;)Ljava/lang/Class;
      15: areturn

  public java.lang.Object run() throws java.lang.Exception;
    Code:
       0: aload_0
       1: invokevirtual #6                  // Method run:()Ljava/lang/Class;
       4: areturn
}
