Compiled from "DefaultListableBeanFactory.java"
class org.springframework.beans.factory.support.DefaultListableBeanFactory$DependencyObjectProvider implements org.springframework.beans.factory.ObjectProvider<java.lang.Object>, java.io.Serializable {
  private final org.springframework.beans.factory.config.DependencyDescriptor descriptor;

  private final boolean optional;

  private final java.lang.String beanName;

  final org.springframework.beans.factory.support.DefaultListableBeanFactory this$0;

  public org.springframework.beans.factory.support.DefaultListableBeanFactory$DependencyObjectProvider(org.springframework.beans.factory.support.DefaultListableBeanFactory, org.springframework.beans.factory.config.DependencyDescriptor, java.lang.String);
    Code:
       0: aload_0
       1: aload_1
       2: putfield      #1                  // Field this$0:Lorg/springframework/beans/factory/support/DefaultListableBeanFactory;
       5: aload_0
       6: invokespecial #2                  // Method java/lang/Object."<init>":()V
       9: aload_0
      10: new           #3                  // class org/springframework/beans/factory/support/DefaultListableBeanFactory$NestedDependencyDescriptor
      13: dup
      14: aload_2
      15: invokespecial #4                  // Method org/springframework/beans/factory/support/DefaultListableBeanFactory$NestedDependencyDescriptor."<init>":(Lorg/springframework/beans/factory/config/DependencyDescriptor;)V
      18: putfield      #5                  // Field descriptor:Lorg/springframework/beans/factory/config/DependencyDescriptor;
      21: aload_0
      22: aload_0
      23: getfield      #5                  // Field descriptor:Lorg/springframework/beans/factory/config/DependencyDescriptor;
      26: invokevirtual #6                  // Method org/springframework/beans/factory/config/DependencyDescriptor.getDependencyType:()Ljava/lang/Class;
      29: invokestatic  #7                  // Method org/springframework/beans/factory/support/DefaultListableBeanFactory.access$300:()Ljava/lang/Class;
      32: if_acmpne     39
      35: iconst_1
      36: goto          40
      39: iconst_0
      40: putfield      #8                  // Field optional:Z
      43: aload_0
      44: aload_3
      45: putfield      #9                  // Field beanName:Ljava/lang/String;
      48: return

  public java.lang.Object getObject() throws org.springframework.beans.BeansException;
    Code:
       0: aload_0
       1: getfield      #8                  // Field optional:Z
       4: ifeq          35
       7: new           #10                 // class org/springframework/beans/factory/support/DefaultListableBeanFactory$OptionalDependencyFactory
      10: dup
      11: aload_0
      12: getfield      #1                  // Field this$0:Lorg/springframework/beans/factory/support/DefaultListableBeanFactory;
      15: aconst_null
      16: invokespecial #11                 // Method org/springframework/beans/factory/support/DefaultListableBeanFactory$OptionalDependencyFactory."<init>":(Lorg/springframework/beans/factory/support/DefaultListableBeanFactory;Lorg/springframework/beans/factory/support/DefaultListableBeanFactory$1;)V
      19: aload_0
      20: getfield      #5                  // Field descriptor:Lorg/springframework/beans/factory/config/DependencyDescriptor;
      23: aload_0
      24: getfield      #9                  // Field beanName:Ljava/lang/String;
      27: iconst_0
      28: anewarray     #12                 // class java/lang/Object
      31: invokevirtual #13                 // Method org/springframework/beans/factory/support/DefaultListableBeanFactory$OptionalDependencyFactory.createOptionalDependency:(Lorg/springframework/beans/factory/config/DependencyDescriptor;Ljava/lang/String;[Ljava/lang/Object;)Ljava/lang/Object;
      34: areturn
      35: aload_0
      36: getfield      #1                  // Field this$0:Lorg/springframework/beans/factory/support/DefaultListableBeanFactory;
      39: aload_0
      40: getfield      #5                  // Field descriptor:Lorg/springframework/beans/factory/config/DependencyDescriptor;
      43: aload_0
      44: getfield      #9                  // Field beanName:Ljava/lang/String;
      47: aconst_null
      48: aconst_null
      49: invokevirtual #14                 // Method org/springframework/beans/factory/support/DefaultListableBeanFactory.doResolveDependency:(Lorg/springframework/beans/factory/config/DependencyDescriptor;Ljava/lang/String;Ljava/util/Set;Lorg/springframework/beans/TypeConverter;)Ljava/lang/Object;
      52: areturn

  public java.lang.Object getObject(java.lang.Object...) throws org.springframework.beans.BeansException;
    Code:
       0: aload_0
       1: getfield      #8                  // Field optional:Z
       4: ifeq          32
       7: new           #10                 // class org/springframework/beans/factory/support/DefaultListableBeanFactory$OptionalDependencyFactory
      10: dup
      11: aload_0
      12: getfield      #1                  // Field this$0:Lorg/springframework/beans/factory/support/DefaultListableBeanFactory;
      15: aconst_null
      16: invokespecial #11                 // Method org/springframework/beans/factory/support/DefaultListableBeanFactory$OptionalDependencyFactory."<init>":(Lorg/springframework/beans/factory/support/DefaultListableBeanFactory;Lorg/springframework/beans/factory/support/DefaultListableBeanFactory$1;)V
      19: aload_0
      20: getfield      #5                  // Field descriptor:Lorg/springframework/beans/factory/config/DependencyDescriptor;
      23: aload_0
      24: getfield      #9                  // Field beanName:Ljava/lang/String;
      27: aload_1
      28: invokevirtual #13                 // Method org/springframework/beans/factory/support/DefaultListableBeanFactory$OptionalDependencyFactory.createOptionalDependency:(Lorg/springframework/beans/factory/config/DependencyDescriptor;Ljava/lang/String;[Ljava/lang/Object;)Ljava/lang/Object;
      31: areturn
      32: new           #15                 // class org/springframework/beans/factory/support/DefaultListableBeanFactory$DependencyObjectProvider$1
      35: dup
      36: aload_0
      37: aload_0
      38: getfield      #5                  // Field descriptor:Lorg/springframework/beans/factory/config/DependencyDescriptor;
      41: aload_1
      42: invokespecial #16                 // Method org/springframework/beans/factory/support/DefaultListableBeanFactory$DependencyObjectProvider$1."<init>":(Lorg/springframework/beans/factory/support/DefaultListableBeanFactory$DependencyObjectProvider;Lorg/springframework/beans/factory/config/DependencyDescriptor;[Ljava/lang/Object;)V
      45: astore_2
      46: aload_0
      47: getfield      #1                  // Field this$0:Lorg/springframework/beans/factory/support/DefaultListableBeanFactory;
      50: aload_2
      51: aload_0
      52: getfield      #9                  // Field beanName:Ljava/lang/String;
      55: aconst_null
      56: aconst_null
      57: invokevirtual #14                 // Method org/springframework/beans/factory/support/DefaultListableBeanFactory.doResolveDependency:(Lorg/springframework/beans/factory/config/DependencyDescriptor;Ljava/lang/String;Ljava/util/Set;Lorg/springframework/beans/TypeConverter;)Ljava/lang/Object;
      60: areturn

  public java.lang.Object getIfAvailable() throws org.springframework.beans.BeansException;
    Code:
       0: aload_0
       1: getfield      #8                  // Field optional:Z
       4: ifeq          35
       7: new           #10                 // class org/springframework/beans/factory/support/DefaultListableBeanFactory$OptionalDependencyFactory
      10: dup
      11: aload_0
      12: getfield      #1                  // Field this$0:Lorg/springframework/beans/factory/support/DefaultListableBeanFactory;
      15: aconst_null
      16: invokespecial #11                 // Method org/springframework/beans/factory/support/DefaultListableBeanFactory$OptionalDependencyFactory."<init>":(Lorg/springframework/beans/factory/support/DefaultListableBeanFactory;Lorg/springframework/beans/factory/support/DefaultListableBeanFactory$1;)V
      19: aload_0
      20: getfield      #5                  // Field descriptor:Lorg/springframework/beans/factory/config/DependencyDescriptor;
      23: aload_0
      24: getfield      #9                  // Field beanName:Ljava/lang/String;
      27: iconst_0
      28: anewarray     #12                 // class java/lang/Object
      31: invokevirtual #13                 // Method org/springframework/beans/factory/support/DefaultListableBeanFactory$OptionalDependencyFactory.createOptionalDependency:(Lorg/springframework/beans/factory/config/DependencyDescriptor;Ljava/lang/String;[Ljava/lang/Object;)Ljava/lang/Object;
      34: areturn
      35: new           #17                 // class org/springframework/beans/factory/support/DefaultListableBeanFactory$DependencyObjectProvider$2
      38: dup
      39: aload_0
      40: aload_0
      41: getfield      #5                  // Field descriptor:Lorg/springframework/beans/factory/config/DependencyDescriptor;
      44: invokespecial #18                 // Method org/springframework/beans/factory/support/DefaultListableBeanFactory$DependencyObjectProvider$2."<init>":(Lorg/springframework/beans/factory/support/DefaultListableBeanFactory$DependencyObjectProvider;Lorg/springframework/beans/factory/config/DependencyDescriptor;)V
      47: astore_1
      48: aload_0
      49: getfield      #1                  // Field this$0:Lorg/springframework/beans/factory/support/DefaultListableBeanFactory;
      52: aload_1
      53: aload_0
      54: getfield      #9                  // Field beanName:Ljava/lang/String;
      57: aconst_null
      58: aconst_null
      59: invokevirtual #14                 // Method org/springframework/beans/factory/support/DefaultListableBeanFactory.doResolveDependency:(Lorg/springframework/beans/factory/config/DependencyDescriptor;Ljava/lang/String;Ljava/util/Set;Lorg/springframework/beans/TypeConverter;)Ljava/lang/Object;
      62: areturn

  public java.lang.Object getIfUnique() throws org.springframework.beans.BeansException;
    Code:
       0: new           #19                 // class org/springframework/beans/factory/support/DefaultListableBeanFactory$DependencyObjectProvider$3
       3: dup
       4: aload_0
       5: aload_0
       6: getfield      #5                  // Field descriptor:Lorg/springframework/beans/factory/config/DependencyDescriptor;
       9: invokespecial #20                 // Method org/springframework/beans/factory/support/DefaultListableBeanFactory$DependencyObjectProvider$3."<init>":(Lorg/springframework/beans/factory/support/DefaultListableBeanFactory$DependencyObjectProvider;Lorg/springframework/beans/factory/config/DependencyDescriptor;)V
      12: astore_1
      13: aload_0
      14: getfield      #8                  // Field optional:Z
      17: ifeq          45
      20: new           #10                 // class org/springframework/beans/factory/support/DefaultListableBeanFactory$OptionalDependencyFactory
      23: dup
      24: aload_0
      25: getfield      #1                  // Field this$0:Lorg/springframework/beans/factory/support/DefaultListableBeanFactory;
      28: aconst_null
      29: invokespecial #11                 // Method org/springframework/beans/factory/support/DefaultListableBeanFactory$OptionalDependencyFactory."<init>":(Lorg/springframework/beans/factory/support/DefaultListableBeanFactory;Lorg/springframework/beans/factory/support/DefaultListableBeanFactory$1;)V
      32: aload_1
      33: aload_0
      34: getfield      #9                  // Field beanName:Ljava/lang/String;
      37: iconst_0
      38: anewarray     #12                 // class java/lang/Object
      41: invokevirtual #13                 // Method org/springframework/beans/factory/support/DefaultListableBeanFactory$OptionalDependencyFactory.createOptionalDependency:(Lorg/springframework/beans/factory/config/DependencyDescriptor;Ljava/lang/String;[Ljava/lang/Object;)Ljava/lang/Object;
      44: areturn
      45: aload_0
      46: getfield      #1                  // Field this$0:Lorg/springframework/beans/factory/support/DefaultListableBeanFactory;
      49: aload_1
      50: aload_0
      51: getfield      #9                  // Field beanName:Ljava/lang/String;
      54: aconst_null
      55: aconst_null
      56: invokevirtual #14                 // Method org/springframework/beans/factory/support/DefaultListableBeanFactory.doResolveDependency:(Lorg/springframework/beans/factory/config/DependencyDescriptor;Ljava/lang/String;Ljava/util/Set;Lorg/springframework/beans/TypeConverter;)Ljava/lang/Object;
      59: areturn
}
