Compiled from "S3EncryptionProviders.scala"
public final class net.spals.appbuilder.filestore.s3.S3EncryptionHolderProvider$$anonfun$1 extends scala.runtime.AbstractFunction1<java.lang.String, com.amazonaws.services.s3.AmazonS3Encryption> implements scala.Serializable {
  public static final long serialVersionUID;

  private final net.spals.appbuilder.filestore.s3.S3EncryptionHolderProvider $outer;

  public final com.amazonaws.services.s3.AmazonS3Encryption apply(java.lang.String);
    Code:
       0: invokestatic  #27                 // Method com/amazonaws/services/s3/AmazonS3EncryptionClientBuilder.standard:()Lcom/amazonaws/services/s3/AmazonS3EncryptionClientBuilder;
       3: aload_0
       4: getfield      #29                 // Field $outer:Lnet/spals/appbuilder/filestore/s3/S3EncryptionHolderProvider;
       7: invokevirtual #33                 // Method net/spals/appbuilder/filestore/s3/S3EncryptionHolderProvider.credentialsProviderClassName:()Ljava/lang/String;
      10: invokestatic  #39                 // Method java/lang/Class.forName:(Ljava/lang/String;)Ljava/lang/Class;
      13: invokevirtual #43                 // Method java/lang/Class.newInstance:()Ljava/lang/Object;
      16: checkcast     #45                 // class com/amazonaws/auth/AWSCredentialsProvider
      19: invokevirtual #49                 // Method com/amazonaws/services/s3/AmazonS3EncryptionClientBuilder.withCredentials:(Lcom/amazonaws/auth/AWSCredentialsProvider;)Lcom/amazonaws/client/builder/AwsClientBuilder;
      22: checkcast     #23                 // class com/amazonaws/services/s3/AmazonS3EncryptionClientBuilder
      25: new           #51                 // class com/amazonaws/services/s3/model/KMSEncryptionMaterialsProvider
      28: dup
      29: aload_1
      30: invokespecial #55                 // Method com/amazonaws/services/s3/model/KMSEncryptionMaterialsProvider."<init>":(Ljava/lang/String;)V
      33: invokevirtual #59                 // Method com/amazonaws/services/s3/AmazonS3EncryptionClientBuilder.withEncryptionMaterials:(Lcom/amazonaws/services/s3/model/EncryptionMaterialsProvider;)Lcom/amazonaws/services/s3/AmazonS3EncryptionClientBuilder;
      36: astore_2
      37: aload_0
      38: getfield      #29                 // Field $outer:Lnet/spals/appbuilder/filestore/s3/S3EncryptionHolderProvider;
      41: invokevirtual #62                 // Method net/spals/appbuilder/filestore/s3/S3EncryptionHolderProvider.endpoint:()Ljava/lang/String;
      44: astore_3
      45: aload_3
      46: ldc           #64                 // String http://
      48: invokevirtual #70                 // Method java/lang/String.startsWith:(Ljava/lang/String;)Z
      51: ifeq          79
      54: new           #72                 // class com/amazonaws/client/builder/AwsClientBuilder$EndpointConfiguration
      57: dup
      58: aload_3
      59: aconst_null
      60: invokespecial #75                 // Method com/amazonaws/client/builder/AwsClientBuilder$EndpointConfiguration."<init>":(Ljava/lang/String;Ljava/lang/String;)V
      63: astore        5
      65: aload_2
      66: aload         5
      68: invokevirtual #79                 // Method com/amazonaws/services/s3/AmazonS3EncryptionClientBuilder.withEndpointConfiguration:(Lcom/amazonaws/client/builder/AwsClientBuilder$EndpointConfiguration;)Lcom/amazonaws/client/builder/AwsClientBuilder;
      71: checkcast     #23                 // class com/amazonaws/services/s3/AmazonS3EncryptionClientBuilder
      74: astore        4
      76: goto          110
      79: getstatic     #85                 // Field scala/util/Try$.MODULE$:Lscala/util/Try$;
      82: new           #87                 // class net/spals/appbuilder/filestore/s3/S3EncryptionHolderProvider$$anonfun$1$$anonfun$apply$1
      85: dup
      86: aload_0
      87: aload_3
      88: invokespecial #90                 // Method net/spals/appbuilder/filestore/s3/S3EncryptionHolderProvider$$anonfun$1$$anonfun$apply$1."<init>":(Lnet/spals/appbuilder/filestore/s3/S3EncryptionHolderProvider$$anonfun$1;Ljava/lang/String;)V
      91: invokevirtual #93                 // Method scala/util/Try$.apply:(Lscala/Function0;)Lscala/util/Try;
      94: invokevirtual #99                 // Method scala/util/Try.isSuccess:()Z
      97: ifeq          121
     100: aload_2
     101: aload_3
     102: invokevirtual #103                // Method com/amazonaws/services/s3/AmazonS3EncryptionClientBuilder.withRegion:(Ljava/lang/String;)Lcom/amazonaws/client/builder/AwsClientBuilder;
     105: checkcast     #23                 // class com/amazonaws/services/s3/AmazonS3EncryptionClientBuilder
     108: astore        4
     110: aload         4
     112: pop
     113: aload_2
     114: invokevirtual #106                // Method com/amazonaws/services/s3/AmazonS3EncryptionClientBuilder.build:()Ljava/lang/Object;
     117: checkcast     #108                // class com/amazonaws/services/s3/AmazonS3Encryption
     120: areturn
     121: new           #110                // class com/typesafe/config/ConfigException$BadValue
     124: dup
     125: ldc           #112                // String s3.fileStore.endpoint
     127: new           #114                // class scala/StringContext
     130: dup
     131: getstatic     #119                // Field scala/Predef$.MODULE$:Lscala/Predef$;
     134: iconst_2
     135: anewarray     #66                 // class java/lang/String
     138: dup
     139: iconst_0
     140: ldc           #121                // String Unrecognized S3 endpoint. Value is neither an http endpoint nor a known region:
     142: aastore
     143: dup
     144: iconst_1
     145: ldc           #123                // String
     147: aastore
     148: checkcast     #125                // class "[Ljava/lang/Object;"
     151: invokevirtual #129                // Method scala/Predef$.wrapRefArray:([Ljava/lang/Object;)Lscala/collection/mutable/WrappedArray;
     154: invokespecial #132                // Method scala/StringContext."<init>":(Lscala/collection/Seq;)V
     157: getstatic     #119                // Field scala/Predef$.MODULE$:Lscala/Predef$;
     160: iconst_1
     161: anewarray     #134                // class java/lang/Object
     164: dup
     165: iconst_0
     166: aload_0
     167: getfield      #29                 // Field $outer:Lnet/spals/appbuilder/filestore/s3/S3EncryptionHolderProvider;
     170: invokevirtual #62                 // Method net/spals/appbuilder/filestore/s3/S3EncryptionHolderProvider.endpoint:()Ljava/lang/String;
     173: aastore
     174: invokevirtual #138                // Method scala/Predef$.genericWrapArray:(Ljava/lang/Object;)Lscala/collection/mutable/WrappedArray;
     177: invokevirtual #142                // Method scala/StringContext.s:(Lscala/collection/Seq;)Ljava/lang/String;
     180: invokespecial #143                // Method com/typesafe/config/ConfigException$BadValue."<init>":(Ljava/lang/String;Ljava/lang/String;)V
     183: athrow

  public final java.lang.Object apply(java.lang.Object);
    Code:
       0: aload_0
       1: aload_1
       2: checkcast     #66                 // class java/lang/String
       5: invokevirtual #154                // Method apply:(Ljava/lang/String;)Lcom/amazonaws/services/s3/AmazonS3Encryption;
       8: areturn

  public net.spals.appbuilder.filestore.s3.S3EncryptionHolderProvider$$anonfun$1(net.spals.appbuilder.filestore.s3.S3EncryptionHolderProvider);
    Code:
       0: aload_1
       1: ifnonnull     6
       4: aconst_null
       5: athrow
       6: aload_0
       7: aload_1
       8: putfield      #29                 // Field $outer:Lnet/spals/appbuilder/filestore/s3/S3EncryptionHolderProvider;
      11: aload_0
      12: invokespecial #160                // Method scala/runtime/AbstractFunction1."<init>":()V
      15: return
}
