Compiled from "RetryUtil.java"
public class org.apache.pulsar.client.util.RetryUtil {
  private static final org.slf4j.Logger log;

  public org.apache.pulsar.client.util.RetryUtil();
    Code:
       0: aload_0
       1: invokespecial #1                  // Method java/lang/Object."<init>":()V
       4: return

  public static <T> void retryAsynchronously(java.util.function.Supplier<java.util.concurrent.CompletableFuture<T>>, org.apache.pulsar.client.impl.Backoff, java.util.concurrent.ScheduledExecutorService, java.util.concurrent.CompletableFuture<T>);
    Code:
       0: aload_1
       1: invokevirtual #2                  // Method org/apache/pulsar/client/impl/Backoff.getMax:()J
       4: lconst_0
       5: lcmp
       6: ifgt          19
       9: new           #3                  // class java/lang/IllegalArgumentException
      12: dup
      13: ldc           #4                  // String Illegal max retry time
      15: invokespecial #5                  // Method java/lang/IllegalArgumentException."<init>":(Ljava/lang/String;)V
      18: athrow
      19: aload_1
      20: invokevirtual #6                  // Method org/apache/pulsar/client/impl/Backoff.getInitial:()J
      23: lconst_0
      24: lcmp
      25: ifgt          38
      28: new           #3                  // class java/lang/IllegalArgumentException
      31: dup
      32: ldc           #7                  // String Illegal initial time
      34: invokespecial #5                  // Method java/lang/IllegalArgumentException."<init>":(Ljava/lang/String;)V
      37: athrow
      38: aload_2
      39: aload_0
      40: aload_1
      41: aload_2
      42: aload_3
      43: invokedynamic #8,  0              // InvokeDynamic #0:run:(Ljava/util/function/Supplier;Lorg/apache/pulsar/client/impl/Backoff;Ljava/util/concurrent/ScheduledExecutorService;Ljava/util/concurrent/CompletableFuture;)Ljava/lang/Runnable;
      48: invokeinterface #9,  2            // InterfaceMethod java/util/concurrent/ScheduledExecutorService.execute:(Ljava/lang/Runnable;)V
      53: return

  private static <T> void executeWithRetry(java.util.function.Supplier<java.util.concurrent.CompletableFuture<T>>, org.apache.pulsar.client.impl.Backoff, java.util.concurrent.ScheduledExecutorService, java.util.concurrent.CompletableFuture<T>);
    Code:
       0: aload_0
       1: invokeinterface #10,  1           // InterfaceMethod java/util/function/Supplier.get:()Ljava/lang/Object;
       6: checkcast     #11                 // class java/util/concurrent/CompletableFuture
       9: aload_1
      10: aload_3
      11: aload_2
      12: aload_0
      13: invokedynamic #12,  0             // InvokeDynamic #1:accept:(Lorg/apache/pulsar/client/impl/Backoff;Ljava/util/concurrent/CompletableFuture;Ljava/util/concurrent/ScheduledExecutorService;Ljava/util/function/Supplier;)Ljava/util/function/BiConsumer;
      18: invokevirtual #13                 // Method java/util/concurrent/CompletableFuture.whenComplete:(Ljava/util/function/BiConsumer;)Ljava/util/concurrent/CompletableFuture;
      21: pop
      22: return

  private static void lambda$executeWithRetry$2(org.apache.pulsar.client.impl.Backoff, java.util.concurrent.CompletableFuture, java.util.concurrent.ScheduledExecutorService, java.util.function.Supplier, java.lang.Object, java.lang.Throwable);
    Code:
       0: aload         5
       2: ifnull        74
       5: aload_0
       6: invokevirtual #14                 // Method org/apache/pulsar/client/impl/Backoff.next:()J
       9: lstore        6
      11: aload_0
      12: invokevirtual #15                 // Method org/apache/pulsar/client/impl/Backoff.isMandatoryStopMade:()Z
      15: istore        8
      17: iload         8
      19: ifeq          32
      22: aload_1
      23: aload         5
      25: invokevirtual #16                 // Method java/util/concurrent/CompletableFuture.completeExceptionally:(Ljava/lang/Throwable;)Z
      28: pop
      29: goto          73
      32: getstatic     #17                 // Field log:Lorg/slf4j/Logger;
      35: ldc           #18                 // String Execution with retry fail, because of {}, will retry in {} ms
      37: aload         5
      39: invokevirtual #19                 // Method java/lang/Throwable.getMessage:()Ljava/lang/String;
      42: lload         6
      44: invokestatic  #20                 // Method java/lang/Long.valueOf:(J)Ljava/lang/Long;
      47: invokeinterface #21,  4           // InterfaceMethod org/slf4j/Logger.warn:(Ljava/lang/String;Ljava/lang/Object;Ljava/lang/Object;)V
      52: aload_2
      53: aload_3
      54: aload_0
      55: aload_2
      56: aload_1
      57: invokedynamic #22,  0             // InvokeDynamic #2:run:(Ljava/util/function/Supplier;Lorg/apache/pulsar/client/impl/Backoff;Ljava/util/concurrent/ScheduledExecutorService;Ljava/util/concurrent/CompletableFuture;)Ljava/lang/Runnable;
      62: lload         6
      64: getstatic     #23                 // Field java/util/concurrent/TimeUnit.MILLISECONDS:Ljava/util/concurrent/TimeUnit;
      67: invokeinterface #24,  5           // InterfaceMethod java/util/concurrent/ScheduledExecutorService.schedule:(Ljava/lang/Runnable;JLjava/util/concurrent/TimeUnit;)Ljava/util/concurrent/ScheduledFuture;
      72: pop
      73: return
      74: aload_1
      75: aload         4
      77: invokevirtual #25                 // Method java/util/concurrent/CompletableFuture.complete:(Ljava/lang/Object;)Z
      80: pop
      81: return

  private static void lambda$null$1(java.util.function.Supplier, org.apache.pulsar.client.impl.Backoff, java.util.concurrent.ScheduledExecutorService, java.util.concurrent.CompletableFuture);
    Code:
       0: aload_0
       1: aload_1
       2: aload_2
       3: aload_3
       4: invokestatic  #26                 // Method executeWithRetry:(Ljava/util/function/Supplier;Lorg/apache/pulsar/client/impl/Backoff;Ljava/util/concurrent/ScheduledExecutorService;Ljava/util/concurrent/CompletableFuture;)V
       7: return

  private static void lambda$retryAsynchronously$0(java.util.function.Supplier, org.apache.pulsar.client.impl.Backoff, java.util.concurrent.ScheduledExecutorService, java.util.concurrent.CompletableFuture);
    Code:
       0: aload_0
       1: aload_1
       2: aload_2
       3: aload_3
       4: invokestatic  #26                 // Method executeWithRetry:(Ljava/util/function/Supplier;Lorg/apache/pulsar/client/impl/Backoff;Ljava/util/concurrent/ScheduledExecutorService;Ljava/util/concurrent/CompletableFuture;)V
       7: return

  static {};
    Code:
       0: ldc           #27                 // class org/apache/pulsar/client/util/RetryUtil
       2: invokestatic  #28                 // Method org/slf4j/LoggerFactory.getLogger:(Ljava/lang/Class;)Lorg/slf4j/Logger;
       5: putstatic     #17                 // Field log:Lorg/slf4j/Logger;
       8: return
}
