Compiled from "BaseJoinProcessorNode.java"
abstract class org.apache.kafka.streams.kstream.internals.graph.BaseJoinProcessorNode<K, V1, V2, VR> extends org.apache.kafka.streams.kstream.internals.graph.StreamsGraphNode {
  private final org.apache.kafka.streams.kstream.internals.graph.ProcessorParameters<K, V1> joinThisProcessorParameters;

  private final org.apache.kafka.streams.kstream.internals.graph.ProcessorParameters<K, V2> joinOtherProcessorParameters;

  private final org.apache.kafka.streams.kstream.internals.graph.ProcessorParameters<K, VR> joinMergeProcessorParameters;

  private final org.apache.kafka.streams.kstream.ValueJoiner<? super V1, ? super V2, ? extends VR> valueJoiner;

  private final java.lang.String thisJoinSideNodeName;

  private final java.lang.String otherJoinSideNodeName;

  org.apache.kafka.streams.kstream.internals.graph.BaseJoinProcessorNode(java.lang.String, org.apache.kafka.streams.kstream.ValueJoiner<? super V1, ? super V2, ? extends VR>, org.apache.kafka.streams.kstream.internals.graph.ProcessorParameters<K, V1>, org.apache.kafka.streams.kstream.internals.graph.ProcessorParameters<K, V2>, org.apache.kafka.streams.kstream.internals.graph.ProcessorParameters<K, VR>, java.lang.String, java.lang.String);
    Code:
       0: aload_0
       1: aload_1
       2: invokespecial #1                  // Method org/apache/kafka/streams/kstream/internals/graph/StreamsGraphNode."<init>":(Ljava/lang/String;)V
       5: aload_0
       6: aload_2
       7: putfield      #2                  // Field valueJoiner:Lorg/apache/kafka/streams/kstream/ValueJoiner;
      10: aload_0
      11: aload_3
      12: putfield      #3                  // Field joinThisProcessorParameters:Lorg/apache/kafka/streams/kstream/internals/graph/ProcessorParameters;
      15: aload_0
      16: aload         4
      18: putfield      #4                  // Field joinOtherProcessorParameters:Lorg/apache/kafka/streams/kstream/internals/graph/ProcessorParameters;
      21: aload_0
      22: aload         5
      24: putfield      #5                  // Field joinMergeProcessorParameters:Lorg/apache/kafka/streams/kstream/internals/graph/ProcessorParameters;
      27: aload_0
      28: aload         6
      30: putfield      #6                  // Field thisJoinSideNodeName:Ljava/lang/String;
      33: aload_0
      34: aload         7
      36: putfield      #7                  // Field otherJoinSideNodeName:Ljava/lang/String;
      39: return

  org.apache.kafka.streams.kstream.internals.graph.ProcessorParameters<K, V1> thisProcessorParameters();
    Code:
       0: aload_0
       1: getfield      #3                  // Field joinThisProcessorParameters:Lorg/apache/kafka/streams/kstream/internals/graph/ProcessorParameters;
       4: areturn

  org.apache.kafka.streams.kstream.internals.graph.ProcessorParameters<K, V2> otherProcessorParameters();
    Code:
       0: aload_0
       1: getfield      #4                  // Field joinOtherProcessorParameters:Lorg/apache/kafka/streams/kstream/internals/graph/ProcessorParameters;
       4: areturn

  org.apache.kafka.streams.kstream.internals.graph.ProcessorParameters<K, VR> mergeProcessorParameters();
    Code:
       0: aload_0
       1: getfield      #5                  // Field joinMergeProcessorParameters:Lorg/apache/kafka/streams/kstream/internals/graph/ProcessorParameters;
       4: areturn

  org.apache.kafka.streams.kstream.ValueJoiner<? super V1, ? super V2, ? extends VR> valueJoiner();
    Code:
       0: aload_0
       1: getfield      #2                  // Field valueJoiner:Lorg/apache/kafka/streams/kstream/ValueJoiner;
       4: areturn

  java.lang.String thisJoinSideNodeName();
    Code:
       0: aload_0
       1: getfield      #6                  // Field thisJoinSideNodeName:Ljava/lang/String;
       4: areturn

  java.lang.String otherJoinSideNodeName();
    Code:
       0: aload_0
       1: getfield      #7                  // Field otherJoinSideNodeName:Ljava/lang/String;
       4: areturn

  public java.lang.String toString();
    Code:
       0: new           #8                  // class java/lang/StringBuilder
       3: dup
       4: invokespecial #9                  // Method java/lang/StringBuilder."<init>":()V
       7: ldc           #10                 // String BaseJoinProcessorNode{joinThisProcessorParameters=
       9: invokevirtual #11                 // Method java/lang/StringBuilder.append:(Ljava/lang/String;)Ljava/lang/StringBuilder;
      12: aload_0
      13: getfield      #3                  // Field joinThisProcessorParameters:Lorg/apache/kafka/streams/kstream/internals/graph/ProcessorParameters;
      16: invokevirtual #12                 // Method java/lang/StringBuilder.append:(Ljava/lang/Object;)Ljava/lang/StringBuilder;
      19: ldc           #13                 // String , joinOtherProcessorParameters=
      21: invokevirtual #11                 // Method java/lang/StringBuilder.append:(Ljava/lang/String;)Ljava/lang/StringBuilder;
      24: aload_0
      25: getfield      #4                  // Field joinOtherProcessorParameters:Lorg/apache/kafka/streams/kstream/internals/graph/ProcessorParameters;
      28: invokevirtual #12                 // Method java/lang/StringBuilder.append:(Ljava/lang/Object;)Ljava/lang/StringBuilder;
      31: ldc           #14                 // String , joinMergeProcessorParameters=
      33: invokevirtual #11                 // Method java/lang/StringBuilder.append:(Ljava/lang/String;)Ljava/lang/StringBuilder;
      36: aload_0
      37: getfield      #5                  // Field joinMergeProcessorParameters:Lorg/apache/kafka/streams/kstream/internals/graph/ProcessorParameters;
      40: invokevirtual #12                 // Method java/lang/StringBuilder.append:(Ljava/lang/Object;)Ljava/lang/StringBuilder;
      43: ldc           #15                 // String , valueJoiner=
      45: invokevirtual #11                 // Method java/lang/StringBuilder.append:(Ljava/lang/String;)Ljava/lang/StringBuilder;
      48: aload_0
      49: getfield      #2                  // Field valueJoiner:Lorg/apache/kafka/streams/kstream/ValueJoiner;
      52: invokevirtual #12                 // Method java/lang/StringBuilder.append:(Ljava/lang/Object;)Ljava/lang/StringBuilder;
      55: ldc           #16                 // String , thisJoinSideNodeName=\'
      57: invokevirtual #11                 // Method java/lang/StringBuilder.append:(Ljava/lang/String;)Ljava/lang/StringBuilder;
      60: aload_0
      61: getfield      #6                  // Field thisJoinSideNodeName:Ljava/lang/String;
      64: invokevirtual #11                 // Method java/lang/StringBuilder.append:(Ljava/lang/String;)Ljava/lang/StringBuilder;
      67: bipush        39
      69: invokevirtual #17                 // Method java/lang/StringBuilder.append:(C)Ljava/lang/StringBuilder;
      72: ldc           #18                 // String , otherJoinSideNodeName=\'
      74: invokevirtual #11                 // Method java/lang/StringBuilder.append:(Ljava/lang/String;)Ljava/lang/StringBuilder;
      77: aload_0
      78: getfield      #7                  // Field otherJoinSideNodeName:Ljava/lang/String;
      81: invokevirtual #11                 // Method java/lang/StringBuilder.append:(Ljava/lang/String;)Ljava/lang/StringBuilder;
      84: bipush        39
      86: invokevirtual #17                 // Method java/lang/StringBuilder.append:(C)Ljava/lang/StringBuilder;
      89: ldc           #19                 // String }
      91: invokevirtual #11                 // Method java/lang/StringBuilder.append:(Ljava/lang/String;)Ljava/lang/StringBuilder;
      94: aload_0
      95: invokespecial #20                 // Method org/apache/kafka/streams/kstream/internals/graph/StreamsGraphNode.toString:()Ljava/lang/String;
      98: invokevirtual #11                 // Method java/lang/StringBuilder.append:(Ljava/lang/String;)Ljava/lang/StringBuilder;
     101: invokevirtual #21                 // Method java/lang/StringBuilder.toString:()Ljava/lang/String;
     104: areturn
}
