Compiled from "StandardLineSeparator.java"
public final class org.sonarsource.sonarlint.shaded.org.apache.commons.io.StandardLineSeparator extends java.lang.Enum<org.sonarsource.sonarlint.shaded.org.apache.commons.io.StandardLineSeparator> {
  public static final org.sonarsource.sonarlint.shaded.org.apache.commons.io.StandardLineSeparator CR;

  public static final org.sonarsource.sonarlint.shaded.org.apache.commons.io.StandardLineSeparator CRLF;

  public static final org.sonarsource.sonarlint.shaded.org.apache.commons.io.StandardLineSeparator LF;

  private final java.lang.String lineSeparator;

  private static final org.sonarsource.sonarlint.shaded.org.apache.commons.io.StandardLineSeparator[] $VALUES;

  public static org.sonarsource.sonarlint.shaded.org.apache.commons.io.StandardLineSeparator[] values();
    Code:
       0: getstatic     #18                 // Field $VALUES:[Lorg/sonarsource/sonarlint/shaded/org/apache/commons/io/StandardLineSeparator;
       3: invokevirtual #23                 // Method "[Lorg/sonarsource/sonarlint/shaded/org/apache/commons/io/StandardLineSeparator;".clone:()Ljava/lang/Object;
       6: checkcast     #19                 // class "[Lorg/sonarsource/sonarlint/shaded/org/apache/commons/io/StandardLineSeparator;"
       9: areturn

  public static org.sonarsource.sonarlint.shaded.org.apache.commons.io.StandardLineSeparator valueOf(java.lang.String);
    Code:
       0: ldc           #2                  // class org/sonarsource/sonarlint/shaded/org/apache/commons/io/StandardLineSeparator
       2: aload_0
       3: invokestatic  #28                 // Method java/lang/Enum.valueOf:(Ljava/lang/Class;Ljava/lang/String;)Ljava/lang/Enum;
       6: checkcast     #2                  // class org/sonarsource/sonarlint/shaded/org/apache/commons/io/StandardLineSeparator
       9: areturn

  private org.sonarsource.sonarlint.shaded.org.apache.commons.io.StandardLineSeparator(java.lang.String);
    Code:
       0: aload_0
       1: aload_1
       2: iload_2
       3: invokespecial #35                 // Method java/lang/Enum."<init>":(Ljava/lang/String;I)V
       6: aload_0
       7: aload_3
       8: ldc           #36                 // String lineSeparator
      10: invokestatic  #42                 // Method java/util/Objects.requireNonNull:(Ljava/lang/Object;Ljava/lang/String;)Ljava/lang/Object;
      13: checkcast     #44                 // class java/lang/String
      16: putfield      #46                 // Field lineSeparator:Ljava/lang/String;
      19: return

  public byte[] getBytes(java.nio.charset.Charset);
    Code:
       0: aload_0
       1: getfield      #46                 // Field lineSeparator:Ljava/lang/String;
       4: aload_1
       5: invokevirtual #51                 // Method java/lang/String.getBytes:(Ljava/nio/charset/Charset;)[B
       8: areturn

  public java.lang.String getString();
    Code:
       0: aload_0
       1: getfield      #46                 // Field lineSeparator:Ljava/lang/String;
       4: areturn

  static {};
    Code:
       0: new           #2                  // class org/sonarsource/sonarlint/shaded/org/apache/commons/io/StandardLineSeparator
       3: dup
       4: ldc           #58                 // String CR
       6: iconst_0
       7: ldc           #60                 // String \r
       9: invokespecial #62                 // Method "<init>":(Ljava/lang/String;ILjava/lang/String;)V
      12: putstatic     #64                 // Field CR:Lorg/sonarsource/sonarlint/shaded/org/apache/commons/io/StandardLineSeparator;
      15: new           #2                  // class org/sonarsource/sonarlint/shaded/org/apache/commons/io/StandardLineSeparator
      18: dup
      19: ldc           #65                 // String CRLF
      21: iconst_1
      22: ldc           #67                 // String \r\n
      24: invokespecial #62                 // Method "<init>":(Ljava/lang/String;ILjava/lang/String;)V
      27: putstatic     #69                 // Field CRLF:Lorg/sonarsource/sonarlint/shaded/org/apache/commons/io/StandardLineSeparator;
      30: new           #2                  // class org/sonarsource/sonarlint/shaded/org/apache/commons/io/StandardLineSeparator
      33: dup
      34: ldc           #70                 // String LF
      36: iconst_2
      37: ldc           #72                 // String \n
      39: invokespecial #62                 // Method "<init>":(Ljava/lang/String;ILjava/lang/String;)V
      42: putstatic     #74                 // Field LF:Lorg/sonarsource/sonarlint/shaded/org/apache/commons/io/StandardLineSeparator;
      45: iconst_3
      46: anewarray     #2                  // class org/sonarsource/sonarlint/shaded/org/apache/commons/io/StandardLineSeparator
      49: dup
      50: iconst_0
      51: getstatic     #64                 // Field CR:Lorg/sonarsource/sonarlint/shaded/org/apache/commons/io/StandardLineSeparator;
      54: aastore
      55: dup
      56: iconst_1
      57: getstatic     #69                 // Field CRLF:Lorg/sonarsource/sonarlint/shaded/org/apache/commons/io/StandardLineSeparator;
      60: aastore
      61: dup
      62: iconst_2
      63: getstatic     #74                 // Field LF:Lorg/sonarsource/sonarlint/shaded/org/apache/commons/io/StandardLineSeparator;
      66: aastore
      67: putstatic     #18                 // Field $VALUES:[Lorg/sonarsource/sonarlint/shaded/org/apache/commons/io/StandardLineSeparator;
      70: return
}
