Compiled from "StreamIterator.java"
class org.sonarsource.sonarlint.shaded.org.apache.commons.io.StreamIterator<E> implements java.util.Iterator<E>, java.io.Closeable {
  private final java.util.Iterator<E> iterator;

  private final java.util.stream.Stream<E> stream;

  public static <T> java.util.Iterator<T> iterator(java.util.stream.Stream<T>);
    Code:
       0: new           #2                  // class org/sonarsource/sonarlint/shaded/org/apache/commons/io/StreamIterator
       3: dup
       4: aload_0
       5: invokespecial #22                 // Method "<init>":(Ljava/util/stream/Stream;)V
       8: getfield      #24                 // Field iterator:Ljava/util/Iterator;
      11: areturn

  private org.sonarsource.sonarlint.shaded.org.apache.commons.io.StreamIterator(java.util.stream.Stream<E>);
    Code:
       0: aload_0
       1: invokespecial #29                 // Method java/lang/Object."<init>":()V
       4: aload_0
       5: aload_1
       6: ldc           #30                 // String stream
       8: invokestatic  #36                 // Method java/util/Objects.requireNonNull:(Ljava/lang/Object;Ljava/lang/String;)Ljava/lang/Object;
      11: checkcast     #38                 // class java/util/stream/Stream
      14: putfield      #40                 // Field stream:Ljava/util/stream/Stream;
      17: aload_0
      18: aload_1
      19: invokeinterface #43,  1           // InterfaceMethod java/util/stream/Stream.iterator:()Ljava/util/Iterator;
      24: putfield      #24                 // Field iterator:Ljava/util/Iterator;
      27: return

  public boolean hasNext();
    Code:
       0: aload_0
       1: getfield      #24                 // Field iterator:Ljava/util/Iterator;
       4: invokeinterface #50,  1           // InterfaceMethod java/util/Iterator.hasNext:()Z
       9: istore_1
      10: iload_1
      11: ifne          18
      14: aload_0
      15: invokevirtual #53                 // Method close:()V
      18: iload_1
      19: ireturn

  public E next();
    Code:
       0: aload_0
       1: getfield      #24                 // Field iterator:Ljava/util/Iterator;
       4: invokeinterface #59,  1           // InterfaceMethod java/util/Iterator.next:()Ljava/lang/Object;
       9: astore_1
      10: aload_1
      11: ifnonnull     18
      14: aload_0
      15: invokevirtual #53                 // Method close:()V
      18: aload_1
      19: areturn

  public void close();
    Code:
       0: aload_0
       1: getfield      #40                 // Field stream:Ljava/util/stream/Stream;
       4: invokeinterface #62,  1           // InterfaceMethod java/util/stream/Stream.close:()V
       9: return
}
