Compiled from "NioBaseServer.java"
public abstract class org.jgroups.blocks.cs.NioBaseServer extends org.jgroups.blocks.cs.BaseServer {
  protected java.nio.channels.Selector selector;

  protected java.lang.Thread acceptor;

  protected final java.util.concurrent.locks.Lock reg_lock;

  protected volatile boolean registration;

  protected int max_send_buffers;

  protected int max_read_batch_size;

  protected int num_selects;

  protected org.jgroups.blocks.cs.NioBaseServer(org.jgroups.util.ThreadFactory);
    Code:
       0: aload_0
       1: aload_1
       2: invokespecial #1                  // Method org/jgroups/blocks/cs/BaseServer."<init>":(Lorg/jgroups/util/ThreadFactory;)V
       5: aload_0
       6: new           #2                  // class java/util/concurrent/locks/ReentrantLock
       9: dup
      10: invokespecial #3                  // Method java/util/concurrent/locks/ReentrantLock."<init>":()V
      13: putfield      #4                  // Field reg_lock:Ljava/util/concurrent/locks/Lock;
      16: aload_0
      17: iconst_5
      18: putfield      #5                  // Field max_send_buffers:I
      21: aload_0
      22: bipush        50
      24: putfield      #6                  // Field max_read_batch_size:I
      27: return

  public int maxSendBuffers();
    Code:
       0: aload_0
       1: getfield      #5                  // Field max_send_buffers:I
       4: ireturn

  public org.jgroups.blocks.cs.NioBaseServer maxSendBuffers(int);
    Code:
       0: aload_0
       1: iload_1
       2: putfield      #5                  // Field max_send_buffers:I
       5: aload_0
       6: areturn

  public int maxReadBatchSize();
    Code:
       0: aload_0
       1: getfield      #6                  // Field max_read_batch_size:I
       4: ireturn

  public org.jgroups.blocks.cs.NioBaseServer maxReadBatchSize(int);
    Code:
       0: aload_0
       1: iload_1
       2: putfield      #6                  // Field max_read_batch_size:I
       5: aload_0
       6: areturn

  public boolean selectorOpen();
    Code:
       0: aload_0
       1: getfield      #7                  // Field selector:Ljava/nio/channels/Selector;
       4: ifnull        21
       7: aload_0
       8: getfield      #7                  // Field selector:Ljava/nio/channels/Selector;
      11: invokevirtual #8                  // Method java/nio/channels/Selector.isOpen:()Z
      14: ifeq          21
      17: iconst_1
      18: goto          22
      21: iconst_0
      22: ireturn

  public boolean acceptorRunning();
    Code:
       0: aload_0
       1: getfield      #9                  // Field acceptor:Ljava/lang/Thread;
       4: ifnull        21
       7: aload_0
       8: getfield      #9                  // Field acceptor:Ljava/lang/Thread;
      11: invokevirtual #10                 // Method java/lang/Thread.isAlive:()Z
      14: ifeq          21
      17: iconst_1
      18: goto          22
      21: iconst_0
      22: ireturn

  public int numSelects();
    Code:
       0: aload_0
       1: getfield      #11                 // Field num_selects:I
       4: ireturn

  public java.lang.String printBuffers();
    Code:
       0: new           #12                 // class java/lang/StringBuilder
       3: dup
       4: ldc           #13                 // String \n
       6: invokespecial #14                 // Method java/lang/StringBuilder."<init>":(Ljava/lang/String;)V
       9: astore_1
      10: aload_0
      11: dup
      12: astore_2
      13: monitorenter
      14: aload_0
      15: getfield      #15                 // Field conns:Ljava/util/Map;
      18: invokeinterface #16,  1           // InterfaceMethod java/util/Map.entrySet:()Ljava/util/Set;
      23: invokeinterface #17,  1           // InterfaceMethod java/util/Set.iterator:()Ljava/util/Iterator;
      28: astore_3
      29: aload_3
      30: invokeinterface #18,  1           // InterfaceMethod java/util/Iterator.hasNext:()Z
      35: ifeq          112
      38: aload_3
      39: invokeinterface #19,  1           // InterfaceMethod java/util/Iterator.next:()Ljava/lang/Object;
      44: checkcast     #20                 // class java/util/Map$Entry
      47: astore        4
      49: aload         4
      51: invokeinterface #21,  1           // InterfaceMethod java/util/Map$Entry.getValue:()Ljava/lang/Object;
      56: checkcast     #22                 // class org/jgroups/blocks/cs/NioConnection
      59: astore        5
      61: aload_1
      62: aload         4
      64: invokeinterface #23,  1           // InterfaceMethod java/util/Map$Entry.getKey:()Ljava/lang/Object;
      69: invokevirtual #24                 // Method java/lang/StringBuilder.append:(Ljava/lang/Object;)Ljava/lang/StringBuilder;
      72: ldc           #25                 // String :\n
      74: invokevirtual #26                 // Method java/lang/StringBuilder.append:(Ljava/lang/String;)Ljava/lang/StringBuilder;
      77: ldc           #27                 // String recv_buf:
      79: invokevirtual #26                 // Method java/lang/StringBuilder.append:(Ljava/lang/String;)Ljava/lang/StringBuilder;
      82: aload         5
      84: getfield      #28                 // Field org/jgroups/blocks/cs/NioConnection.recv_buf:Lorg/jgroups/nio/Buffers;
      87: invokevirtual #24                 // Method java/lang/StringBuilder.append:(Ljava/lang/Object;)Ljava/lang/StringBuilder;
      90: ldc           #29                 // String \n  send_buf:
      92: invokevirtual #26                 // Method java/lang/StringBuilder.append:(Ljava/lang/String;)Ljava/lang/StringBuilder;
      95: aload         5
      97: getfield      #30                 // Field org/jgroups/blocks/cs/NioConnection.send_buf:Lorg/jgroups/nio/Buffers;
     100: invokevirtual #24                 // Method java/lang/StringBuilder.append:(Ljava/lang/Object;)Ljava/lang/StringBuilder;
     103: ldc           #13                 // String \n
     105: invokevirtual #26                 // Method java/lang/StringBuilder.append:(Ljava/lang/String;)Ljava/lang/StringBuilder;
     108: pop
     109: goto          29
     112: aload_2
     113: monitorexit
     114: goto          124
     117: astore        6
     119: aload_2
     120: monitorexit
     121: aload         6
     123: athrow
     124: aload_1
     125: invokevirtual #31                 // Method java/lang/StringBuilder.toString:()Ljava/lang/String;
     128: areturn
    Exception table:
       from    to  target type
          14   114   117   any
         117   121   117   any

  protected java.nio.channels.SelectionKey register(java.nio.channels.SelectableChannel, int, org.jgroups.blocks.cs.NioConnection) throws java.lang.Exception;
    Code:
       0: aload_0
       1: getfield      #4                  // Field reg_lock:Ljava/util/concurrent/locks/Lock;
       4: invokeinterface #32,  1           // InterfaceMethod java/util/concurrent/locks/Lock.lock:()V
       9: aload_0
      10: iconst_1
      11: putfield      #33                 // Field registration:Z
      14: aload_0
      15: getfield      #7                  // Field selector:Ljava/nio/channels/Selector;
      18: invokevirtual #34                 // Method java/nio/channels/Selector.wakeup:()Ljava/nio/channels/Selector;
      21: pop
      22: aload_1
      23: aload_0
      24: getfield      #7                  // Field selector:Ljava/nio/channels/Selector;
      27: iload_2
      28: aload_3
      29: invokevirtual #35                 // Method java/nio/channels/SelectableChannel.register:(Ljava/nio/channels/Selector;ILjava/lang/Object;)Ljava/nio/channels/SelectionKey;
      32: astore        4
      34: aload_0
      35: getfield      #4                  // Field reg_lock:Ljava/util/concurrent/locks/Lock;
      38: invokeinterface #36,  1           // InterfaceMethod java/util/concurrent/locks/Lock.unlock:()V
      43: aload         4
      45: areturn
      46: astore        5
      48: aload_0
      49: getfield      #4                  // Field reg_lock:Ljava/util/concurrent/locks/Lock;
      52: invokeinterface #36,  1           // InterfaceMethod java/util/concurrent/locks/Lock.unlock:()V
      57: aload         5
      59: athrow
    Exception table:
       from    to  target type
           9    34    46   any
          46    48    46   any

  protected org.jgroups.blocks.cs.NioConnection createConnection(org.jgroups.Address) throws java.lang.Exception;
    Code:
       0: new           #22                 // class org/jgroups/blocks/cs/NioConnection
       3: dup
       4: aload_1
       5: aload_0
       6: invokespecial #37                 // Method org/jgroups/blocks/cs/NioConnection."<init>":(Lorg/jgroups/Address;Lorg/jgroups/blocks/cs/NioBaseServer;)V
       9: areturn

  protected void handleAccept(java.nio.channels.SelectionKey) throws java.lang.Exception;
    Code:
       0: return

  protected org.jgroups.blocks.cs.Connection createConnection(org.jgroups.Address) throws java.lang.Exception;
    Code:
       0: aload_0
       1: aload_1
       2: invokevirtual #38                 // Method createConnection:(Lorg/jgroups/Address;)Lorg/jgroups/blocks/cs/NioConnection;
       5: areturn
}
