Compiled from "AccessConstraintResources.java"
class org.jboss.as.domain.management.access.AccessConstraintResources$ApplicationClassificationResource extends org.jboss.as.domain.management.access.AbstractClassificationResource {
  private static final java.util.Set<java.lang.String> CHILD_TYPES;

  private final org.jboss.as.controller.access.management.AccessConstraintUtilizationRegistry registry;

  private org.jboss.as.domain.management.access.AccessConstraintResources$ApplicationClassificationResource(org.jboss.as.controller.access.management.AccessConstraintUtilizationRegistry);
    Code:
       0: aload_0
       1: getstatic     #3                  // Field org/jboss/as/domain/management/access/AccessConstraintResources.APPLICATION_PATH_ELEMENT:Lorg/jboss/as/controller/PathElement;
       4: invokespecial #4                  // Method org/jboss/as/domain/management/access/AbstractClassificationResource."<init>":(Lorg/jboss/as/controller/PathElement;)V
       7: aload_0
       8: aload_1
       9: putfield      #5                  // Field registry:Lorg/jboss/as/controller/access/management/AccessConstraintUtilizationRegistry;
      12: return

  public java.util.Set<java.lang.String> getChildTypes();
    Code:
       0: getstatic     #6                  // Field CHILD_TYPES:Ljava/util/Set;
       3: areturn

  org.jboss.as.controller.registry.Resource$ResourceEntry getChildEntry(java.lang.String, java.lang.String);
    Code:
       0: ldc           #7                  // String type
       2: aload_1
       3: invokevirtual #8                  // Method java/lang/String.equals:(Ljava/lang/Object;)Z
       6: ifeq          41
       9: invokestatic  #9                  // Method org/jboss/as/domain/management/access/AccessConstraintResources.access$200:()Ljava/util/Map;
      12: astore_3
      13: aload_3
      14: aload_2
      15: invokeinterface #10,  2           // InterfaceMethod java/util/Map.get:(Ljava/lang/Object;)Ljava/lang/Object;
      20: checkcast     #11                 // class java/util/Map
      23: astore        4
      25: aload         4
      27: ifnull        41
      30: aload         4
      32: aload_2
      33: aload_0
      34: getfield      #5                  // Field registry:Lorg/jboss/as/controller/access/management/AccessConstraintUtilizationRegistry;
      37: invokestatic  #12                 // Method org/jboss/as/domain/management/access/ApplicationClassificationTypeResourceDefinition.createResource:(Ljava/util/Map;Ljava/lang/String;Lorg/jboss/as/controller/access/management/AccessConstraintUtilizationRegistry;)Lorg/jboss/as/controller/registry/Resource$ResourceEntry;
      40: areturn
      41: aconst_null
      42: areturn

  public java.util.Set<java.lang.String> getChildrenNames(java.lang.String);
    Code:
       0: ldc           #7                  // String type
       2: aload_1
       3: invokevirtual #8                  // Method java/lang/String.equals:(Ljava/lang/Object;)Z
       6: ifeq          20
       9: invokestatic  #9                  // Method org/jboss/as/domain/management/access/AccessConstraintResources.access$200:()Ljava/util/Map;
      12: astore_2
      13: aload_2
      14: invokeinterface #13,  1           // InterfaceMethod java/util/Map.keySet:()Ljava/util/Set;
      19: areturn
      20: invokestatic  #14                 // Method java/util/Collections.emptySet:()Ljava/util/Set;
      23: areturn

  public java.util.Set<org.jboss.as.controller.registry.Resource$ResourceEntry> getChildren(java.lang.String);
    Code:
       0: ldc           #7                  // String type
       2: aload_1
       3: invokevirtual #8                  // Method java/lang/String.equals:(Ljava/lang/Object;)Z
       6: ifeq          95
       9: invokestatic  #9                  // Method org/jboss/as/domain/management/access/AccessConstraintResources.access$200:()Ljava/util/Map;
      12: astore_2
      13: new           #15                 // class java/util/HashSet
      16: dup
      17: invokespecial #16                 // Method java/util/HashSet."<init>":()V
      20: astore_3
      21: aload_2
      22: invokeinterface #17,  1           // InterfaceMethod java/util/Map.entrySet:()Ljava/util/Set;
      27: invokeinterface #18,  1           // InterfaceMethod java/util/Set.iterator:()Ljava/util/Iterator;
      32: astore        4
      34: aload         4
      36: invokeinterface #19,  1           // InterfaceMethod java/util/Iterator.hasNext:()Z
      41: ifeq          93
      44: aload         4
      46: invokeinterface #20,  1           // InterfaceMethod java/util/Iterator.next:()Ljava/lang/Object;
      51: checkcast     #21                 // class java/util/Map$Entry
      54: astore        5
      56: aload_3
      57: aload         5
      59: invokeinterface #22,  1           // InterfaceMethod java/util/Map$Entry.getValue:()Ljava/lang/Object;
      64: checkcast     #11                 // class java/util/Map
      67: aload         5
      69: invokeinterface #23,  1           // InterfaceMethod java/util/Map$Entry.getKey:()Ljava/lang/Object;
      74: checkcast     #24                 // class java/lang/String
      77: aload_0
      78: getfield      #5                  // Field registry:Lorg/jboss/as/controller/access/management/AccessConstraintUtilizationRegistry;
      81: invokestatic  #12                 // Method org/jboss/as/domain/management/access/ApplicationClassificationTypeResourceDefinition.createResource:(Ljava/util/Map;Ljava/lang/String;Lorg/jboss/as/controller/access/management/AccessConstraintUtilizationRegistry;)Lorg/jboss/as/controller/registry/Resource$ResourceEntry;
      84: invokeinterface #25,  2           // InterfaceMethod java/util/Set.add:(Ljava/lang/Object;)Z
      89: pop
      90: goto          34
      93: aload_3
      94: areturn
      95: invokestatic  #14                 // Method java/util/Collections.emptySet:()Ljava/util/Set;
      98: areturn

  org.jboss.as.domain.management.access.AccessConstraintResources$ApplicationClassificationResource(org.jboss.as.controller.access.management.AccessConstraintUtilizationRegistry, org.jboss.as.domain.management.access.AccessConstraintResources$1);
    Code:
       0: aload_0
       1: aload_1
       2: invokespecial #2                  // Method "<init>":(Lorg/jboss/as/controller/access/management/AccessConstraintUtilizationRegistry;)V
       5: return

  static {};
    Code:
       0: ldc           #7                  // String type
       2: invokestatic  #26                 // Method java/util/Collections.singleton:(Ljava/lang/Object;)Ljava/util/Set;
       5: putstatic     #6                  // Field CHILD_TYPES:Ljava/util/Set;
       8: return
}
