Compiled from "AccessConstraintAppliesToResourceDefinition.java"
class org.jboss.as.domain.management.access.AccessConstraintAppliesToResourceDefinition$AccessConstraintAppliesToResource extends org.jboss.as.controller.registry.PlaceholderResource$PlaceholderResourceEntry {
  private final org.jboss.as.controller.access.management.AccessConstraintUtilization constraintUtilization;

  private org.jboss.as.domain.management.access.AccessConstraintAppliesToResourceDefinition$AccessConstraintAppliesToResource(org.jboss.as.controller.access.management.AccessConstraintUtilization);
    Code:
       0: aload_0
       1: ldc           #4                  // String applies-to
       3: aload_1
       4: invokeinterface #5,  1            // InterfaceMethod org/jboss/as/controller/access/management/AccessConstraintUtilization.getPathAddress:()Lorg/jboss/as/controller/PathAddress;
       9: invokevirtual #6                  // Method org/jboss/as/controller/PathAddress.toCLIStyleString:()Ljava/lang/String;
      12: invokestatic  #7                  // Method org/jboss/as/controller/PathElement.pathElement:(Ljava/lang/String;Ljava/lang/String;)Lorg/jboss/as/controller/PathElement;
      15: invokespecial #8                  // Method org/jboss/as/controller/registry/PlaceholderResource$PlaceholderResourceEntry."<init>":(Lorg/jboss/as/controller/PathElement;)V
      18: aload_0
      19: aload_1
      20: putfield      #1                  // Field constraintUtilization:Lorg/jboss/as/controller/access/management/AccessConstraintUtilization;
      23: return

  org.jboss.as.domain.management.access.AccessConstraintAppliesToResourceDefinition$AccessConstraintAppliesToResource(org.jboss.as.controller.access.management.AccessConstraintUtilization, org.jboss.as.domain.management.access.AccessConstraintAppliesToResourceDefinition$1);
    Code:
       0: aload_0
       1: aload_1
       2: invokespecial #2                  // Method "<init>":(Lorg/jboss/as/controller/access/management/AccessConstraintUtilization;)V
       5: return

  static org.jboss.as.controller.access.management.AccessConstraintUtilization access$400(org.jboss.as.domain.management.access.AccessConstraintAppliesToResourceDefinition$AccessConstraintAppliesToResource);
    Code:
       0: aload_0
       1: getfield      #1                  // Field constraintUtilization:Lorg/jboss/as/controller/access/management/AccessConstraintUtilization;
       4: areturn
}
