Compiled from "AccessAuthorizationResourceDefinition.java"
public class org.jboss.as.domain.management.access.AccessAuthorizationResourceDefinition extends org.jboss.as.controller.SimpleResourceDefinition {
  public static final org.jboss.as.controller.PathElement PATH_ELEMENT;

  public static final org.jboss.as.controller.SimpleAttributeDefinition PERMISSION_COMBINATION_POLICY;

  public static final org.jboss.as.controller.SimpleAttributeDefinition PROVIDER;

  static final org.jboss.as.controller.ListAttributeDefinition STANDARD_ROLE_NAMES;

  static final org.jboss.as.controller.ListAttributeDefinition ALL_ROLE_NAMES;

  public static final java.util.List<org.jboss.as.controller.AttributeDefinition> CONFIG_ATTRIBUTES;

  private final org.jboss.as.controller.access.management.DelegatingConfigurableAuthorizer configurableAuthorizer;

  private final boolean isDomain;

  private final boolean isHostController;

  private final java.util.List<org.jboss.as.controller.access.management.AccessConstraintDefinition> accessConstraints;

  public static org.jboss.as.domain.management.access.AccessAuthorizationResourceDefinition forDomain(org.jboss.as.controller.access.management.DelegatingConfigurableAuthorizer);
    Code:
       0: new           #2                  // class org/jboss/as/domain/management/access/AccessAuthorizationResourceDefinition
       3: dup
       4: aload_0
       5: iconst_1
       6: iconst_0
       7: invokespecial #3                  // Method "<init>":(Lorg/jboss/as/controller/access/management/DelegatingConfigurableAuthorizer;ZZ)V
      10: areturn

  public static org.jboss.as.domain.management.access.AccessAuthorizationResourceDefinition forHost(org.jboss.as.controller.access.management.DelegatingConfigurableAuthorizer);
    Code:
       0: new           #2                  // class org/jboss/as/domain/management/access/AccessAuthorizationResourceDefinition
       3: dup
       4: aload_0
       5: iconst_1
       6: iconst_1
       7: invokespecial #3                  // Method "<init>":(Lorg/jboss/as/controller/access/management/DelegatingConfigurableAuthorizer;ZZ)V
      10: areturn

  public static org.jboss.as.domain.management.access.AccessAuthorizationResourceDefinition forDomainServer(org.jboss.as.controller.access.management.DelegatingConfigurableAuthorizer);
    Code:
       0: new           #2                  // class org/jboss/as/domain/management/access/AccessAuthorizationResourceDefinition
       3: dup
       4: aload_0
       5: iconst_1
       6: iconst_0
       7: invokespecial #3                  // Method "<init>":(Lorg/jboss/as/controller/access/management/DelegatingConfigurableAuthorizer;ZZ)V
      10: areturn

  public static org.jboss.as.domain.management.access.AccessAuthorizationResourceDefinition forStandaloneServer(org.jboss.as.controller.access.management.DelegatingConfigurableAuthorizer);
    Code:
       0: new           #2                  // class org/jboss/as/domain/management/access/AccessAuthorizationResourceDefinition
       3: dup
       4: aload_0
       5: iconst_0
       6: iconst_0
       7: invokespecial #3                  // Method "<init>":(Lorg/jboss/as/controller/access/management/DelegatingConfigurableAuthorizer;ZZ)V
      10: areturn

  private org.jboss.as.domain.management.access.AccessAuthorizationResourceDefinition(org.jboss.as.controller.access.management.DelegatingConfigurableAuthorizer, boolean, boolean);
    Code:
       0: aload_0
       1: getstatic     #4                  // Field PATH_ELEMENT:Lorg/jboss/as/controller/PathElement;
       4: iconst_1
       5: anewarray     #5                  // class java/lang/String
       8: dup
       9: iconst_0
      10: ldc           #6                  // String core.access-control
      12: aastore
      13: invokestatic  #7                  // Method org/jboss/as/domain/management/_private/DomainManagementResolver.getResolver:([Ljava/lang/String;)Lorg/jboss/as/controller/descriptions/ResourceDescriptionResolver;
      16: invokespecial #8                  // Method org/jboss/as/controller/SimpleResourceDefinition."<init>":(Lorg/jboss/as/controller/PathElement;Lorg/jboss/as/controller/descriptions/ResourceDescriptionResolver;)V
      19: aload_0
      20: aload_1
      21: putfield      #9                  // Field configurableAuthorizer:Lorg/jboss/as/controller/access/management/DelegatingConfigurableAuthorizer;
      24: aload_0
      25: iload_2
      26: putfield      #10                 // Field isDomain:Z
      29: aload_0
      30: iload_3
      31: putfield      #11                 // Field isHostController:Z
      34: aload_0
      35: getstatic     #12                 // Field org/jboss/as/controller/access/management/SensitiveTargetAccessConstraintDefinition.ACCESS_CONTROL:Lorg/jboss/as/controller/access/management/SensitiveTargetAccessConstraintDefinition;
      38: invokevirtual #13                 // Method org/jboss/as/controller/access/management/SensitiveTargetAccessConstraintDefinition.wrapAsList:()Ljava/util/List;
      41: putfield      #14                 // Field accessConstraints:Ljava/util/List;
      44: return

  public void registerAttributes(org.jboss.as.controller.registry.ManagementResourceRegistration);
    Code:
       0: aload_0
       1: aload_1
       2: invokespecial #15                 // Method org/jboss/as/controller/SimpleResourceDefinition.registerAttributes:(Lorg/jboss/as/controller/registry/ManagementResourceRegistration;)V
       5: aload_0
       6: getfield      #11                 // Field isHostController:Z
       9: ifne          85
      12: aload_0
      13: getfield      #9                  // Field configurableAuthorizer:Lorg/jboss/as/controller/access/management/DelegatingConfigurableAuthorizer;
      16: invokevirtual #16                 // Method org/jboss/as/controller/access/management/DelegatingConfigurableAuthorizer.getWritableAuthorizerConfiguration:()Lorg/jboss/as/controller/access/management/WritableAuthorizerConfiguration;
      19: astore_2
      20: aload_1
      21: getstatic     #17                 // Field PROVIDER:Lorg/jboss/as/controller/SimpleAttributeDefinition;
      24: aconst_null
      25: new           #18                 // class org/jboss/as/domain/management/access/AccessAuthorizationProviderWriteAttributeHander
      28: dup
      29: aload_0
      30: getfield      #9                  // Field configurableAuthorizer:Lorg/jboss/as/controller/access/management/DelegatingConfigurableAuthorizer;
      33: invokespecial #19                 // Method org/jboss/as/domain/management/access/AccessAuthorizationProviderWriteAttributeHander."<init>":(Lorg/jboss/as/controller/access/management/DelegatingConfigurableAuthorizer;)V
      36: invokeinterface #20,  4           // InterfaceMethod org/jboss/as/controller/registry/ManagementResourceRegistration.registerReadWriteAttribute:(Lorg/jboss/as/controller/AttributeDefinition;Lorg/jboss/as/controller/OperationStepHandler;Lorg/jboss/as/controller/OperationStepHandler;)V
      41: aload_1
      42: getstatic     #21                 // Field PERMISSION_COMBINATION_POLICY:Lorg/jboss/as/controller/SimpleAttributeDefinition;
      45: aconst_null
      46: new           #22                 // class org/jboss/as/domain/management/access/AccessAuthorizationCombinationPolicyWriteAttributeHandler
      49: dup
      50: aload_2
      51: invokespecial #23                 // Method org/jboss/as/domain/management/access/AccessAuthorizationCombinationPolicyWriteAttributeHandler."<init>":(Lorg/jboss/as/controller/access/management/WritableAuthorizerConfiguration;)V
      54: invokeinterface #20,  4           // InterfaceMethod org/jboss/as/controller/registry/ManagementResourceRegistration.registerReadWriteAttribute:(Lorg/jboss/as/controller/AttributeDefinition;Lorg/jboss/as/controller/OperationStepHandler;Lorg/jboss/as/controller/OperationStepHandler;)V
      59: aload_1
      60: getstatic     #24                 // Field STANDARD_ROLE_NAMES:Lorg/jboss/as/controller/ListAttributeDefinition;
      63: aload_2
      64: invokestatic  #25                 // Method org/jboss/as/domain/management/access/AccessAuthorizationRolesHandler.getStandardRolesHandler:(Lorg/jboss/as/controller/access/AuthorizerConfiguration;)Lorg/jboss/as/domain/management/access/AccessAuthorizationRolesHandler;
      67: invokeinterface #26,  3           // InterfaceMethod org/jboss/as/controller/registry/ManagementResourceRegistration.registerReadOnlyAttribute:(Lorg/jboss/as/controller/AttributeDefinition;Lorg/jboss/as/controller/OperationStepHandler;)V
      72: aload_1
      73: getstatic     #27                 // Field ALL_ROLE_NAMES:Lorg/jboss/as/controller/ListAttributeDefinition;
      76: aload_2
      77: invokestatic  #28                 // Method org/jboss/as/domain/management/access/AccessAuthorizationRolesHandler.getAllRolesHandler:(Lorg/jboss/as/controller/access/AuthorizerConfiguration;)Lorg/jboss/as/domain/management/access/AccessAuthorizationRolesHandler;
      80: invokeinterface #26,  3           // InterfaceMethod org/jboss/as/controller/registry/ManagementResourceRegistration.registerReadOnlyAttribute:(Lorg/jboss/as/controller/AttributeDefinition;Lorg/jboss/as/controller/OperationStepHandler;)V
      85: return

  public void registerChildren(org.jboss.as.controller.registry.ManagementResourceRegistration);
    Code:
       0: aload_0
       1: getfield      #11                 // Field isHostController:Z
       4: ifne          25
       7: aload_1
       8: aload_0
       9: getfield      #9                  // Field configurableAuthorizer:Lorg/jboss/as/controller/access/management/DelegatingConfigurableAuthorizer;
      12: aload_0
      13: getfield      #10                 // Field isDomain:Z
      16: invokestatic  #29                 // Method org/jboss/as/domain/management/access/RoleMappingResourceDefinition.create:(Lorg/jboss/as/controller/access/management/DelegatingConfigurableAuthorizer;Z)Lorg/jboss/as/controller/SimpleResourceDefinition;
      19: invokeinterface #30,  2           // InterfaceMethod org/jboss/as/controller/registry/ManagementResourceRegistration.registerSubModel:(Lorg/jboss/as/controller/ResourceDefinition;)Lorg/jboss/as/controller/registry/ManagementResourceRegistration;
      24: pop
      25: aload_0
      26: getfield      #10                 // Field isDomain:Z
      29: ifeq          77
      32: aload_0
      33: getfield      #9                  // Field configurableAuthorizer:Lorg/jboss/as/controller/access/management/DelegatingConfigurableAuthorizer;
      36: invokevirtual #16                 // Method org/jboss/as/controller/access/management/DelegatingConfigurableAuthorizer.getWritableAuthorizerConfiguration:()Lorg/jboss/as/controller/access/management/WritableAuthorizerConfiguration;
      39: astore_2
      40: aload_1
      41: new           #31                 // class org/jboss/as/domain/management/access/ServerGroupScopedRoleResourceDefinition
      44: dup
      45: aload_2
      46: invokespecial #32                 // Method org/jboss/as/domain/management/access/ServerGroupScopedRoleResourceDefinition."<init>":(Lorg/jboss/as/controller/access/management/WritableAuthorizerConfiguration;)V
      49: invokeinterface #30,  2           // InterfaceMethod org/jboss/as/controller/registry/ManagementResourceRegistration.registerSubModel:(Lorg/jboss/as/controller/ResourceDefinition;)Lorg/jboss/as/controller/registry/ManagementResourceRegistration;
      54: pop
      55: aload_0
      56: getfield      #11                 // Field isHostController:Z
      59: ifne          77
      62: aload_1
      63: new           #33                 // class org/jboss/as/domain/management/access/HostScopedRolesResourceDefinition
      66: dup
      67: aload_2
      68: invokespecial #34                 // Method org/jboss/as/domain/management/access/HostScopedRolesResourceDefinition."<init>":(Lorg/jboss/as/controller/access/management/WritableAuthorizerConfiguration;)V
      71: invokeinterface #30,  2           // InterfaceMethod org/jboss/as/controller/registry/ManagementResourceRegistration.registerSubModel:(Lorg/jboss/as/controller/ResourceDefinition;)Lorg/jboss/as/controller/registry/ManagementResourceRegistration;
      76: pop
      77: aload_0
      78: getfield      #11                 // Field isHostController:Z
      81: ifne          114
      84: aload_1
      85: getstatic     #35                 // Field org/jboss/as/domain/management/access/ApplicationClassificationParentResourceDefinition.INSTANCE:Lorg/jboss/as/domain/management/access/ApplicationClassificationParentResourceDefinition;
      88: invokeinterface #30,  2           // InterfaceMethod org/jboss/as/controller/registry/ManagementResourceRegistration.registerSubModel:(Lorg/jboss/as/controller/ResourceDefinition;)Lorg/jboss/as/controller/registry/ManagementResourceRegistration;
      93: pop
      94: aload_1
      95: getstatic     #36                 // Field org/jboss/as/domain/management/access/SensitivityClassificationParentResourceDefinition.INSTANCE:Lorg/jboss/as/domain/management/access/SensitivityClassificationParentResourceDefinition;
      98: invokeinterface #30,  2           // InterfaceMethod org/jboss/as/controller/registry/ManagementResourceRegistration.registerSubModel:(Lorg/jboss/as/controller/ResourceDefinition;)Lorg/jboss/as/controller/registry/ManagementResourceRegistration;
     103: pop
     104: aload_1
     105: invokestatic  #37                 // Method org/jboss/as/domain/management/access/SensitivityResourceDefinition.createVaultExpressionConfiguration:()Lorg/jboss/as/domain/management/access/SensitivityResourceDefinition;
     108: invokeinterface #30,  2           // InterfaceMethod org/jboss/as/controller/registry/ManagementResourceRegistration.registerSubModel:(Lorg/jboss/as/controller/ResourceDefinition;)Lorg/jboss/as/controller/registry/ManagementResourceRegistration;
     113: pop
     114: return

  public void registerOperations(org.jboss.as.controller.registry.ManagementResourceRegistration);
    Code:
       0: aload_0
       1: aload_1
       2: invokespecial #38                 // Method org/jboss/as/controller/SimpleResourceDefinition.registerOperations:(Lorg/jboss/as/controller/registry/ManagementResourceRegistration;)V
       5: aload_0
       6: getfield      #10                 // Field isDomain:Z
       9: ifeq          32
      12: aload_1
      13: getstatic     #39                 // Field org/jboss/as/domain/management/access/AccessAuthorizationDomainSlaveConfigHandler.DEFINITION:Lorg/jboss/as/controller/OperationDefinition;
      16: new           #40                 // class org/jboss/as/domain/management/access/AccessAuthorizationDomainSlaveConfigHandler
      19: dup
      20: aload_0
      21: getfield      #9                  // Field configurableAuthorizer:Lorg/jboss/as/controller/access/management/DelegatingConfigurableAuthorizer;
      24: invokespecial #41                 // Method org/jboss/as/domain/management/access/AccessAuthorizationDomainSlaveConfigHandler."<init>":(Lorg/jboss/as/controller/access/management/DelegatingConfigurableAuthorizer;)V
      27: invokeinterface #42,  3           // InterfaceMethod org/jboss/as/controller/registry/ManagementResourceRegistration.registerOperationHandler:(Lorg/jboss/as/controller/OperationDefinition;Lorg/jboss/as/controller/OperationStepHandler;)V
      32: return

  public java.util.List<org.jboss.as.controller.access.management.AccessConstraintDefinition> getAccessConstraints();
    Code:
       0: aload_0
       1: getfield      #14                 // Field accessConstraints:Ljava/util/List;
       4: areturn

  public static org.jboss.as.controller.registry.Resource createResource(org.jboss.as.controller.access.management.AccessConstraintUtilizationRegistry);
    Code:
       0: invokestatic  #43                 // Method org/jboss/as/controller/registry/Resource$Factory.create:()Lorg/jboss/as/controller/registry/Resource;
       3: astore_1
       4: aload_1
       5: getstatic     #44                 // Field org/jboss/as/domain/management/access/AccessConstraintResources.APPLICATION_PATH_ELEMENT:Lorg/jboss/as/controller/PathElement;
       8: aload_0
       9: invokestatic  #45                 // Method org/jboss/as/domain/management/access/AccessConstraintResources.getApplicationConfigResource:(Lorg/jboss/as/controller/access/management/AccessConstraintUtilizationRegistry;)Lorg/jboss/as/controller/registry/Resource;
      12: invokeinterface #46,  3           // InterfaceMethod org/jboss/as/controller/registry/Resource.registerChild:(Lorg/jboss/as/controller/PathElement;Lorg/jboss/as/controller/registry/Resource;)V
      17: aload_1
      18: getstatic     #47                 // Field org/jboss/as/domain/management/access/AccessConstraintResources.SENSITIVITY_PATH_ELEMENT:Lorg/jboss/as/controller/PathElement;
      21: aload_0
      22: invokestatic  #48                 // Method org/jboss/as/domain/management/access/AccessConstraintResources.getSensitivityResource:(Lorg/jboss/as/controller/access/management/AccessConstraintUtilizationRegistry;)Lorg/jboss/as/controller/registry/Resource;
      25: invokeinterface #46,  3           // InterfaceMethod org/jboss/as/controller/registry/Resource.registerChild:(Lorg/jboss/as/controller/PathElement;Lorg/jboss/as/controller/registry/Resource;)V
      30: aload_1
      31: getstatic     #49                 // Field org/jboss/as/domain/management/access/AccessConstraintResources.VAULT_PATH_ELEMENT:Lorg/jboss/as/controller/PathElement;
      34: getstatic     #50                 // Field org/jboss/as/domain/management/access/AccessConstraintResources.VAULT_RESOURCE:Lorg/jboss/as/controller/registry/Resource;
      37: invokeinterface #46,  3           // InterfaceMethod org/jboss/as/controller/registry/Resource.registerChild:(Lorg/jboss/as/controller/PathElement;Lorg/jboss/as/controller/registry/Resource;)V
      42: aload_1
      43: areturn

  static {};
    Code:
       0: ldc           #51                 // String access
       2: ldc           #52                 // String authorization
       4: invokestatic  #53                 // Method org/jboss/as/controller/PathElement.pathElement:(Ljava/lang/String;Ljava/lang/String;)Lorg/jboss/as/controller/PathElement;
       7: putstatic     #4                  // Field PATH_ELEMENT:Lorg/jboss/as/controller/PathElement;
      10: new           #54                 // class org/jboss/as/controller/SimpleAttributeDefinitionBuilder
      13: dup
      14: ldc           #55                 // String permission-combination-policy
      16: getstatic     #56                 // Field org/jboss/dmr/ModelType.STRING:Lorg/jboss/dmr/ModelType;
      19: iconst_1
      20: invokespecial #57                 // Method org/jboss/as/controller/SimpleAttributeDefinitionBuilder."<init>":(Ljava/lang/String;Lorg/jboss/dmr/ModelType;Z)V
      23: new           #58                 // class org/jboss/dmr/ModelNode
      26: dup
      27: getstatic     #59                 // Field org/jboss/as/controller/access/CombinationPolicy.PERMISSIVE:Lorg/jboss/as/controller/access/CombinationPolicy;
      30: invokevirtual #60                 // Method org/jboss/as/controller/access/CombinationPolicy.toString:()Ljava/lang/String;
      33: invokespecial #61                 // Method org/jboss/dmr/ModelNode."<init>":(Ljava/lang/String;)V
      36: invokevirtual #62                 // Method org/jboss/as/controller/SimpleAttributeDefinitionBuilder.setDefaultValue:(Lorg/jboss/dmr/ModelNode;)Lorg/jboss/as/controller/AbstractAttributeDefinitionBuilder;
      39: checkcast     #54                 // class org/jboss/as/controller/SimpleAttributeDefinitionBuilder
      42: new           #63                 // class org/jboss/as/controller/operations/validation/EnumValidator
      45: dup
      46: ldc           #64                 // class org/jboss/as/controller/access/CombinationPolicy
      48: iconst_1
      49: iconst_0
      50: invokespecial #65                 // Method org/jboss/as/controller/operations/validation/EnumValidator."<init>":(Ljava/lang/Class;ZZ)V
      53: invokevirtual #66                 // Method org/jboss/as/controller/SimpleAttributeDefinitionBuilder.setValidator:(Lorg/jboss/as/controller/operations/validation/ParameterValidator;)Lorg/jboss/as/controller/AbstractAttributeDefinitionBuilder;
      56: checkcast     #54                 // class org/jboss/as/controller/SimpleAttributeDefinitionBuilder
      59: invokevirtual #67                 // Method org/jboss/as/controller/SimpleAttributeDefinitionBuilder.build:()Lorg/jboss/as/controller/SimpleAttributeDefinition;
      62: putstatic     #21                 // Field PERMISSION_COMBINATION_POLICY:Lorg/jboss/as/controller/SimpleAttributeDefinition;
      65: new           #54                 // class org/jboss/as/controller/SimpleAttributeDefinitionBuilder
      68: dup
      69: ldc           #68                 // String provider
      71: getstatic     #56                 // Field org/jboss/dmr/ModelType.STRING:Lorg/jboss/dmr/ModelType;
      74: iconst_1
      75: invokespecial #57                 // Method org/jboss/as/controller/SimpleAttributeDefinitionBuilder."<init>":(Ljava/lang/String;Lorg/jboss/dmr/ModelType;Z)V
      78: new           #58                 // class org/jboss/dmr/ModelNode
      81: dup
      82: getstatic     #69                 // Field org/jboss/as/domain/management/access/AccessAuthorizationResourceDefinition$Provider.SIMPLE:Lorg/jboss/as/domain/management/access/AccessAuthorizationResourceDefinition$Provider;
      85: invokevirtual #70                 // Method org/jboss/as/domain/management/access/AccessAuthorizationResourceDefinition$Provider.toString:()Ljava/lang/String;
      88: invokespecial #61                 // Method org/jboss/dmr/ModelNode."<init>":(Ljava/lang/String;)V
      91: invokevirtual #62                 // Method org/jboss/as/controller/SimpleAttributeDefinitionBuilder.setDefaultValue:(Lorg/jboss/dmr/ModelNode;)Lorg/jboss/as/controller/AbstractAttributeDefinitionBuilder;
      94: checkcast     #54                 // class org/jboss/as/controller/SimpleAttributeDefinitionBuilder
      97: new           #63                 // class org/jboss/as/controller/operations/validation/EnumValidator
     100: dup
     101: ldc           #71                 // class org/jboss/as/domain/management/access/AccessAuthorizationResourceDefinition$Provider
     103: iconst_1
     104: iconst_0
     105: invokespecial #65                 // Method org/jboss/as/controller/operations/validation/EnumValidator."<init>":(Ljava/lang/Class;ZZ)V
     108: invokevirtual #66                 // Method org/jboss/as/controller/SimpleAttributeDefinitionBuilder.setValidator:(Lorg/jboss/as/controller/operations/validation/ParameterValidator;)Lorg/jboss/as/controller/AbstractAttributeDefinitionBuilder;
     111: checkcast     #54                 // class org/jboss/as/controller/SimpleAttributeDefinitionBuilder
     114: invokevirtual #67                 // Method org/jboss/as/controller/SimpleAttributeDefinitionBuilder.build:()Lorg/jboss/as/controller/SimpleAttributeDefinition;
     117: putstatic     #17                 // Field PROVIDER:Lorg/jboss/as/controller/SimpleAttributeDefinition;
     120: new           #72                 // class org/jboss/as/controller/StringListAttributeDefinition$Builder
     123: dup
     124: ldc           #73                 // String standard-role-names
     126: invokespecial #74                 // Method org/jboss/as/controller/StringListAttributeDefinition$Builder."<init>":(Ljava/lang/String;)V
     129: invokevirtual #75                 // Method org/jboss/as/controller/StringListAttributeDefinition$Builder.setStorageRuntime:()Lorg/jboss/as/controller/AbstractAttributeDefinitionBuilder;
     132: checkcast     #72                 // class org/jboss/as/controller/StringListAttributeDefinition$Builder
     135: invokevirtual #76                 // Method org/jboss/as/controller/StringListAttributeDefinition$Builder.build:()Lorg/jboss/as/controller/StringListAttributeDefinition;
     138: putstatic     #24                 // Field STANDARD_ROLE_NAMES:Lorg/jboss/as/controller/ListAttributeDefinition;
     141: new           #72                 // class org/jboss/as/controller/StringListAttributeDefinition$Builder
     144: dup
     145: ldc           #77                 // String all-role-names
     147: invokespecial #74                 // Method org/jboss/as/controller/StringListAttributeDefinition$Builder."<init>":(Ljava/lang/String;)V
     150: invokevirtual #75                 // Method org/jboss/as/controller/StringListAttributeDefinition$Builder.setStorageRuntime:()Lorg/jboss/as/controller/AbstractAttributeDefinitionBuilder;
     153: checkcast     #72                 // class org/jboss/as/controller/StringListAttributeDefinition$Builder
     156: invokevirtual #76                 // Method org/jboss/as/controller/StringListAttributeDefinition$Builder.build:()Lorg/jboss/as/controller/StringListAttributeDefinition;
     159: putstatic     #27                 // Field ALL_ROLE_NAMES:Lorg/jboss/as/controller/ListAttributeDefinition;
     162: iconst_2
     163: anewarray     #78                 // class org/jboss/as/controller/AttributeDefinition
     166: dup
     167: iconst_0
     168: getstatic     #17                 // Field PROVIDER:Lorg/jboss/as/controller/SimpleAttributeDefinition;
     171: aastore
     172: dup
     173: iconst_1
     174: getstatic     #21                 // Field PERMISSION_COMBINATION_POLICY:Lorg/jboss/as/controller/SimpleAttributeDefinition;
     177: aastore
     178: invokestatic  #79                 // Method java/util/Arrays.asList:([Ljava/lang/Object;)Ljava/util/List;
     181: putstatic     #80                 // Field CONFIG_ATTRIBUTES:Ljava/util/List;
     184: return
}
