Compiled from "RoleMappingResourceDefinition.java"
public class org.jboss.as.domain.management.access.RoleMappingResourceDefinition extends org.jboss.as.controller.SimpleResourceDefinition {
  public static final java.lang.String PATH_KEY;

  public static final org.jboss.as.controller.SimpleAttributeDefinition INCLUDE_ALL;

  private final org.jboss.as.controller.access.management.DelegatingConfigurableAuthorizer authorizer;

  private org.jboss.as.domain.management.access.RoleMappingResourceDefinition(org.jboss.as.controller.access.management.DelegatingConfigurableAuthorizer, boolean);
    Code:
       0: aload_0
       1: ldc           #3                  // String role-mapping
       3: invokestatic  #4                  // Method org/jboss/as/controller/PathElement.pathElement:(Ljava/lang/String;)Lorg/jboss/as/controller/PathElement;
       6: iconst_1
       7: anewarray     #5                  // class java/lang/String
      10: dup
      11: iconst_0
      12: ldc           #6                  // String core.access-control.role-mapping
      14: aastore
      15: invokestatic  #7                  // Method org/jboss/as/domain/management/_private/DomainManagementResolver.getResolver:([Ljava/lang/String;)Lorg/jboss/as/controller/descriptions/ResourceDescriptionResolver;
      18: aload_1
      19: invokevirtual #8                  // Method org/jboss/as/controller/access/management/DelegatingConfigurableAuthorizer.getWritableAuthorizerConfiguration:()Lorg/jboss/as/controller/access/management/WritableAuthorizerConfiguration;
      22: iload_2
      23: invokestatic  #9                  // Method org/jboss/as/domain/management/access/RoleMappingAdd.create:(Lorg/jboss/as/controller/access/management/WritableAuthorizerConfiguration;Z)Lorg/jboss/as/controller/OperationStepHandler;
      26: aload_1
      27: invokevirtual #8                  // Method org/jboss/as/controller/access/management/DelegatingConfigurableAuthorizer.getWritableAuthorizerConfiguration:()Lorg/jboss/as/controller/access/management/WritableAuthorizerConfiguration;
      30: invokestatic  #10                 // Method org/jboss/as/domain/management/access/RoleMappingRemove.create:(Lorg/jboss/as/controller/access/management/WritableAuthorizerConfiguration;)Lorg/jboss/as/controller/OperationStepHandler;
      33: invokespecial #11                 // Method org/jboss/as/controller/SimpleResourceDefinition."<init>":(Lorg/jboss/as/controller/PathElement;Lorg/jboss/as/controller/descriptions/ResourceDescriptionResolver;Lorg/jboss/as/controller/OperationStepHandler;Lorg/jboss/as/controller/OperationStepHandler;)V
      36: aload_0
      37: aload_1
      38: putfield      #12                 // Field authorizer:Lorg/jboss/as/controller/access/management/DelegatingConfigurableAuthorizer;
      41: return

  public static org.jboss.as.controller.SimpleResourceDefinition create(org.jboss.as.controller.access.management.DelegatingConfigurableAuthorizer, boolean);
    Code:
       0: new           #2                  // class org/jboss/as/domain/management/access/RoleMappingResourceDefinition
       3: dup
       4: aload_0
       5: iload_1
       6: invokespecial #13                 // Method "<init>":(Lorg/jboss/as/controller/access/management/DelegatingConfigurableAuthorizer;Z)V
       9: areturn

  public void registerAttributes(org.jboss.as.controller.registry.ManagementResourceRegistration);
    Code:
       0: aload_0
       1: getfield      #12                 // Field authorizer:Lorg/jboss/as/controller/access/management/DelegatingConfigurableAuthorizer;
       4: invokevirtual #8                  // Method org/jboss/as/controller/access/management/DelegatingConfigurableAuthorizer.getWritableAuthorizerConfiguration:()Lorg/jboss/as/controller/access/management/WritableAuthorizerConfiguration;
       7: astore_2
       8: aload_1
       9: getstatic     #14                 // Field INCLUDE_ALL:Lorg/jboss/as/controller/SimpleAttributeDefinition;
      12: aconst_null
      13: new           #15                 // class org/jboss/as/domain/management/access/RoleIncludeAllWriteAttributeHander
      16: dup
      17: aload_2
      18: invokespecial #16                 // Method org/jboss/as/domain/management/access/RoleIncludeAllWriteAttributeHander."<init>":(Lorg/jboss/as/controller/access/management/WritableAuthorizerConfiguration;)V
      21: invokeinterface #17,  4           // InterfaceMethod org/jboss/as/controller/registry/ManagementResourceRegistration.registerReadWriteAttribute:(Lorg/jboss/as/controller/AttributeDefinition;Lorg/jboss/as/controller/OperationStepHandler;Lorg/jboss/as/controller/OperationStepHandler;)V
      26: return

  public void registerChildren(org.jboss.as.controller.registry.ManagementResourceRegistration);
    Code:
       0: aload_0
       1: getfield      #12                 // Field authorizer:Lorg/jboss/as/controller/access/management/DelegatingConfigurableAuthorizer;
       4: invokevirtual #8                  // Method org/jboss/as/controller/access/management/DelegatingConfigurableAuthorizer.getWritableAuthorizerConfiguration:()Lorg/jboss/as/controller/access/management/WritableAuthorizerConfiguration;
       7: astore_2
       8: aload_1
       9: aload_2
      10: invokestatic  #18                 // Method org/jboss/as/domain/management/access/PrincipalResourceDefinition.includeResourceDefinition:(Lorg/jboss/as/controller/access/management/WritableAuthorizerConfiguration;)Lorg/jboss/as/domain/management/access/PrincipalResourceDefinition;
      13: invokeinterface #19,  2           // InterfaceMethod org/jboss/as/controller/registry/ManagementResourceRegistration.registerSubModel:(Lorg/jboss/as/controller/ResourceDefinition;)Lorg/jboss/as/controller/registry/ManagementResourceRegistration;
      18: pop
      19: aload_1
      20: aload_2
      21: invokestatic  #20                 // Method org/jboss/as/domain/management/access/PrincipalResourceDefinition.excludeResourceDefinition:(Lorg/jboss/as/controller/access/management/WritableAuthorizerConfiguration;)Lorg/jboss/as/domain/management/access/PrincipalResourceDefinition;
      24: invokeinterface #19,  2           // InterfaceMethod org/jboss/as/controller/registry/ManagementResourceRegistration.registerSubModel:(Lorg/jboss/as/controller/ResourceDefinition;)Lorg/jboss/as/controller/registry/ManagementResourceRegistration;
      29: pop
      30: return

  public void registerOperations(org.jboss.as.controller.registry.ManagementResourceRegistration);
    Code:
       0: aload_0
       1: aload_1
       2: invokespecial #21                 // Method org/jboss/as/controller/SimpleResourceDefinition.registerOperations:(Lorg/jboss/as/controller/registry/ManagementResourceRegistration;)V
       5: aload_1
       6: getstatic     #22                 // Field org/jboss/as/domain/management/access/IsCallerInRoleOperation.DEFINITION:Lorg/jboss/as/controller/SimpleOperationDefinition;
       9: aload_0
      10: getfield      #12                 // Field authorizer:Lorg/jboss/as/controller/access/management/DelegatingConfigurableAuthorizer;
      13: invokestatic  #23                 // Method org/jboss/as/domain/management/access/IsCallerInRoleOperation.create:(Lorg/jboss/as/controller/access/Authorizer;)Lorg/jboss/as/controller/OperationStepHandler;
      16: invokeinterface #24,  3           // InterfaceMethod org/jboss/as/controller/registry/ManagementResourceRegistration.registerOperationHandler:(Lorg/jboss/as/controller/OperationDefinition;Lorg/jboss/as/controller/OperationStepHandler;)V
      21: return

  static java.lang.String getRoleName(org.jboss.dmr.ModelNode);
    Code:
       0: aload_0
       1: ldc           #25                 // String address
       3: invokevirtual #26                 // Method org/jboss/dmr/ModelNode.get:(Ljava/lang/String;)Lorg/jboss/dmr/ModelNode;
       6: invokestatic  #27                 // Method org/jboss/as/controller/PathAddress.pathAddress:(Lorg/jboss/dmr/ModelNode;)Lorg/jboss/as/controller/PathAddress;
       9: astore_1
      10: aload_1
      11: invokevirtual #28                 // Method org/jboss/as/controller/PathAddress.iterator:()Ljava/util/ListIterator;
      14: astore_2
      15: aload_2
      16: invokeinterface #29,  1           // InterfaceMethod java/util/Iterator.hasNext:()Z
      21: ifeq          54
      24: aload_2
      25: invokeinterface #30,  1           // InterfaceMethod java/util/Iterator.next:()Ljava/lang/Object;
      30: checkcast     #31                 // class org/jboss/as/controller/PathElement
      33: astore_3
      34: ldc           #3                  // String role-mapping
      36: aload_3
      37: invokevirtual #32                 // Method org/jboss/as/controller/PathElement.getKey:()Ljava/lang/String;
      40: invokevirtual #33                 // Method java/lang/String.equals:(Ljava/lang/Object;)Z
      43: ifeq          51
      46: aload_3
      47: invokevirtual #34                 // Method org/jboss/as/controller/PathElement.getValue:()Ljava/lang/String;
      50: areturn
      51: goto          15
      54: new           #35                 // class java/lang/IllegalStateException
      57: dup
      58: invokespecial #36                 // Method java/lang/IllegalStateException."<init>":()V
      61: athrow

  static {};
    Code:
       0: new           #37                 // class org/jboss/as/controller/SimpleAttributeDefinitionBuilder
       3: dup
       4: ldc           #38                 // String include-all
       6: getstatic     #39                 // Field org/jboss/dmr/ModelType.BOOLEAN:Lorg/jboss/dmr/ModelType;
       9: iconst_1
      10: invokespecial #40                 // Method org/jboss/as/controller/SimpleAttributeDefinitionBuilder."<init>":(Ljava/lang/String;Lorg/jboss/dmr/ModelType;Z)V
      13: new           #41                 // class org/jboss/dmr/ModelNode
      16: dup
      17: iconst_0
      18: invokespecial #42                 // Method org/jboss/dmr/ModelNode."<init>":(Z)V
      21: invokevirtual #43                 // Method org/jboss/as/controller/SimpleAttributeDefinitionBuilder.setDefaultValue:(Lorg/jboss/dmr/ModelNode;)Lorg/jboss/as/controller/AbstractAttributeDefinitionBuilder;
      24: checkcast     #37                 // class org/jboss/as/controller/SimpleAttributeDefinitionBuilder
      27: invokevirtual #44                 // Method org/jboss/as/controller/SimpleAttributeDefinitionBuilder.build:()Lorg/jboss/as/controller/SimpleAttributeDefinition;
      30: putstatic     #14                 // Field INCLUDE_ALL:Lorg/jboss/as/controller/SimpleAttributeDefinition;
      33: return
}
