Compiled from "ScopedRoleRequiredHandler.java"
public class org.jboss.as.domain.management.access.ScopedRoleRequiredHandler implements org.jboss.as.controller.OperationStepHandler {
  private final java.lang.String roleName;

  private org.jboss.as.domain.management.access.ScopedRoleRequiredHandler(java.lang.String);
    Code:
       0: aload_0
       1: invokespecial #2                  // Method java/lang/Object."<init>":()V
       4: aload_0
       5: aload_1
       6: putfield      #3                  // Field roleName:Ljava/lang/String;
       9: return

  public void execute(org.jboss.as.controller.OperationContext, org.jboss.dmr.ModelNode) throws org.jboss.as.controller.OperationFailedException;
    Code:
       0: aload_1
       1: getstatic     #4                  // Field org/jboss/as/controller/PathAddress.EMPTY_ADDRESS:Lorg/jboss/as/controller/PathAddress;
       4: invokeinterface #5,  2            // InterfaceMethod org/jboss/as/controller/OperationContext.readResource:(Lorg/jboss/as/controller/PathAddress;)Lorg/jboss/as/controller/registry/Resource;
       9: astore_3
      10: aload_3
      11: ldc           #6                  // String host-scoped-role
      13: invokeinterface #7,  2            // InterfaceMethod org/jboss/as/controller/registry/Resource.getChildrenNames:(Ljava/lang/String;)Ljava/util/Set;
      18: astore        4
      20: aload_3
      21: ldc           #8                  // String server-group-scoped-role
      23: invokeinterface #7,  2            // InterfaceMethod org/jboss/as/controller/registry/Resource.getChildrenNames:(Ljava/lang/String;)Ljava/util/Set;
      28: astore        5
      30: aload         4
      32: aload_0
      33: getfield      #3                  // Field roleName:Ljava/lang/String;
      36: invokeinterface #9,  2            // InterfaceMethod java/util/Set.contains:(Ljava/lang/Object;)Z
      41: ifne          71
      44: aload         5
      46: aload_0
      47: getfield      #3                  // Field roleName:Ljava/lang/String;
      50: invokeinterface #9,  2            // InterfaceMethod java/util/Set.contains:(Ljava/lang/Object;)Z
      55: ifne          71
      58: getstatic     #10                 // Field org/jboss/as/domain/management/logging/DomainManagementLogger.ROOT_LOGGER:Lorg/jboss/as/domain/management/logging/DomainManagementLogger;
      61: aload_0
      62: getfield      #3                  // Field roleName:Ljava/lang/String;
      65: invokeinterface #11,  2           // InterfaceMethod org/jboss/as/domain/management/logging/DomainManagementLogger.invalidRoleNameDomain:(Ljava/lang/String;)Lorg/jboss/as/controller/OperationFailedException;
      70: athrow
      71: return

  static void addOperation(org.jboss.as.controller.OperationContext, java.lang.String);
    Code:
       0: ldc           #12                 // String scoped-role-check
       2: iconst_2
       3: anewarray     #13                 // class org/jboss/as/controller/PathElement
       6: dup
       7: iconst_0
       8: getstatic     #14                 // Field org/jboss/as/domain/management/CoreManagementResourceDefinition.PATH_ELEMENT:Lorg/jboss/as/controller/PathElement;
      11: aastore
      12: dup
      13: iconst_1
      14: getstatic     #15                 // Field org/jboss/as/domain/management/access/AccessAuthorizationResourceDefinition.PATH_ELEMENT:Lorg/jboss/as/controller/PathElement;
      17: aastore
      18: invokestatic  #16                 // Method org/jboss/as/controller/PathAddress.pathAddress:([Lorg/jboss/as/controller/PathElement;)Lorg/jboss/as/controller/PathAddress;
      21: invokestatic  #17                 // Method org/jboss/as/controller/operations/common/Util.createEmptyOperation:(Ljava/lang/String;Lorg/jboss/as/controller/PathAddress;)Lorg/jboss/dmr/ModelNode;
      24: astore_2
      25: aload_0
      26: aload_2
      27: new           #18                 // class org/jboss/as/domain/management/access/ScopedRoleRequiredHandler
      30: dup
      31: aload_1
      32: invokespecial #19                 // Method "<init>":(Ljava/lang/String;)V
      35: getstatic     #20                 // Field org/jboss/as/controller/OperationContext$Stage.MODEL:Lorg/jboss/as/controller/OperationContext$Stage;
      38: invokeinterface #21,  4           // InterfaceMethod org/jboss/as/controller/OperationContext.addStep:(Lorg/jboss/dmr/ModelNode;Lorg/jboss/as/controller/OperationStepHandler;Lorg/jboss/as/controller/OperationContext$Stage;)V
      43: return
}
