Compiled from "ScopedRoleAddHandler.java"
final class org.jboss.as.domain.management.access.ScopedRoleAddHandler$1 implements org.jboss.as.controller.ParameterCorrector {
  final org.jboss.as.controller.access.management.WritableAuthorizerConfiguration val$authorizerConfiguration;

  org.jboss.as.domain.management.access.ScopedRoleAddHandler$1(org.jboss.as.controller.access.management.WritableAuthorizerConfiguration);
    Code:
       0: aload_0
       1: aload_1
       2: putfield      #1                  // Field val$authorizerConfiguration:Lorg/jboss/as/controller/access/management/WritableAuthorizerConfiguration;
       5: aload_0
       6: invokespecial #2                  // Method java/lang/Object."<init>":()V
       9: return

  public org.jboss.dmr.ModelNode correct(org.jboss.dmr.ModelNode, org.jboss.dmr.ModelNode);
    Code:
       0: aload_0
       1: getfield      #1                  // Field val$authorizerConfiguration:Lorg/jboss/as/controller/access/management/WritableAuthorizerConfiguration;
       4: invokevirtual #3                  // Method org/jboss/as/controller/access/management/WritableAuthorizerConfiguration.getStandardRoles:()Ljava/util/Set;
       7: astore_3
       8: aload_1
       9: invokevirtual #4                  // Method org/jboss/dmr/ModelNode.asString:()Ljava/lang/String;
      12: astore        4
      14: aload_3
      15: invokeinterface #5,  1            // InterfaceMethod java/util/Set.iterator:()Ljava/util/Iterator;
      20: astore        5
      22: aload         5
      24: invokeinterface #6,  1            // InterfaceMethod java/util/Iterator.hasNext:()Z
      29: ifeq          77
      32: aload         5
      34: invokeinterface #7,  1            // InterfaceMethod java/util/Iterator.next:()Ljava/lang/Object;
      39: checkcast     #8                  // class java/lang/String
      42: astore        6
      44: aload         4
      46: aload         6
      48: invokevirtual #9                  // Method java/lang/String.equalsIgnoreCase:(Ljava/lang/String;)Z
      51: ifeq          74
      54: aload         4
      56: aload         6
      58: invokevirtual #10                 // Method java/lang/String.equals:(Ljava/lang/Object;)Z
      61: ifne          74
      64: new           #11                 // class org/jboss/dmr/ModelNode
      67: dup
      68: aload         6
      70: invokespecial #12                 // Method org/jboss/dmr/ModelNode."<init>":(Ljava/lang/String;)V
      73: areturn
      74: goto          22
      77: aload_1
      78: areturn
}
