Compiled from "ForEachSupport.java"
class org.apache.taglibs.standard.tag.common.core.ForEachSupport$ToEndIterator extends org.apache.taglibs.standard.tag.common.core.ForEachSupport$ReadOnlyIterator {
  private final int end;

  private int i;

  private org.apache.taglibs.standard.tag.common.core.ForEachSupport$ToEndIterator(int);
    Code:
       0: aload_0
       1: aconst_null
       2: invokespecial #2                  // Method org/apache/taglibs/standard/tag/common/core/ForEachSupport$ReadOnlyIterator."<init>":(Lorg/apache/taglibs/standard/tag/common/core/ForEachSupport$1;)V
       5: aload_0
       6: iload_1
       7: putfield      #3                  // Field end:I
      10: return

  public boolean hasNext();
    Code:
       0: aload_0
       1: getfield      #4                  // Field i:I
       4: aload_0
       5: getfield      #3                  // Field end:I
       8: if_icmpgt     15
      11: iconst_1
      12: goto          16
      15: iconst_0
      16: ireturn

  public java.lang.Object next();
    Code:
       0: aload_0
       1: getfield      #4                  // Field i:I
       4: aload_0
       5: getfield      #3                  // Field end:I
       8: if_icmpgt     26
      11: aload_0
      12: dup
      13: getfield      #4                  // Field i:I
      16: dup_x1
      17: iconst_1
      18: iadd
      19: putfield      #4                  // Field i:I
      22: invokestatic  #5                  // Method java/lang/Integer.valueOf:(I)Ljava/lang/Integer;
      25: areturn
      26: new           #6                  // class java/util/NoSuchElementException
      29: dup
      30: invokespecial #7                  // Method java/util/NoSuchElementException."<init>":()V
      33: athrow

  org.apache.taglibs.standard.tag.common.core.ForEachSupport$ToEndIterator(int, org.apache.taglibs.standard.tag.common.core.ForEachSupport$1);
    Code:
       0: aload_0
       1: iload_1
       2: invokespecial #1                  // Method "<init>":(I)V
       5: return
}
