Compiled from "ConsumerStartedEvent.java"
public class org.apache.activemq.advisory.ConsumerStartedEvent extends org.apache.activemq.advisory.ConsumerEvent {
  private static final long serialVersionUID;

  private final transient org.apache.activemq.command.ConsumerInfo consumerInfo;

  public org.apache.activemq.advisory.ConsumerStartedEvent(org.apache.activemq.advisory.ConsumerEventSource, org.apache.activemq.command.ActiveMQDestination, org.apache.activemq.command.ConsumerInfo, int);
    Code:
       0: aload_0
       1: aload_1
       2: aload_2
       3: aload_3
       4: invokevirtual #1                  // Method org/apache/activemq/command/ConsumerInfo.getConsumerId:()Lorg/apache/activemq/command/ConsumerId;
       7: iload         4
       9: invokespecial #2                  // Method org/apache/activemq/advisory/ConsumerEvent."<init>":(Lorg/apache/activemq/advisory/ConsumerEventSource;Ljavax/jms/Destination;Lorg/apache/activemq/command/ConsumerId;I)V
      12: aload_0
      13: aload_3
      14: putfield      #3                  // Field consumerInfo:Lorg/apache/activemq/command/ConsumerInfo;
      17: return

  public boolean isStarted();
    Code:
       0: iconst_1
       1: ireturn

  public org.apache.activemq.command.ConsumerInfo getConsumerInfo();
    Code:
       0: aload_0
       1: getfield      #3                  // Field consumerInfo:Lorg/apache/activemq/command/ConsumerInfo;
       4: areturn
}
