Compiled from "Daemon.java"
public final class net.oneandone.stool.docker.Daemon$Status extends java.lang.Enum<net.oneandone.stool.docker.Daemon$Status> {
  public static final net.oneandone.stool.docker.Daemon$Status CREATED;

  public static final net.oneandone.stool.docker.Daemon$Status RUNNING;

  public static final net.oneandone.stool.docker.Daemon$Status EXITED;

  public static final net.oneandone.stool.docker.Daemon$Status REMOVING;

  private static final net.oneandone.stool.docker.Daemon$Status[] $VALUES;

  public static net.oneandone.stool.docker.Daemon$Status[] values();
    Code:
       0: getstatic     #1                  // Field $VALUES:[Lnet/oneandone/stool/docker/Daemon$Status;
       3: invokevirtual #7                  // Method "[Lnet/oneandone/stool/docker/Daemon$Status;".clone:()Ljava/lang/Object;
       6: checkcast     #8                  // class "[Lnet/oneandone/stool/docker/Daemon$Status;"
       9: areturn

  public static net.oneandone.stool.docker.Daemon$Status valueOf(java.lang.String);
    Code:
       0: ldc           #2                  // class net/oneandone/stool/docker/Daemon$Status
       2: aload_0
       3: invokestatic  #12                 // Method java/lang/Enum.valueOf:(Ljava/lang/Class;Ljava/lang/String;)Ljava/lang/Enum;
       6: checkcast     #2                  // class net/oneandone/stool/docker/Daemon$Status
       9: areturn

  private net.oneandone.stool.docker.Daemon$Status();
    Code:
       0: aload_0
       1: aload_1
       2: iload_2
       3: invokespecial #18                 // Method java/lang/Enum."<init>":(Ljava/lang/String;I)V
       6: return

  static {};
    Code:
       0: new           #2                  // class net/oneandone/stool/docker/Daemon$Status
       3: dup
       4: ldc           #22                 // String CREATED
       6: iconst_0
       7: invokespecial #24                 // Method "<init>":(Ljava/lang/String;I)V
      10: putstatic     #25                 // Field CREATED:Lnet/oneandone/stool/docker/Daemon$Status;
      13: new           #2                  // class net/oneandone/stool/docker/Daemon$Status
      16: dup
      17: ldc           #28                 // String RUNNING
      19: iconst_1
      20: invokespecial #24                 // Method "<init>":(Ljava/lang/String;I)V
      23: putstatic     #30                 // Field RUNNING:Lnet/oneandone/stool/docker/Daemon$Status;
      26: new           #2                  // class net/oneandone/stool/docker/Daemon$Status
      29: dup
      30: ldc           #32                 // String EXITED
      32: iconst_2
      33: invokespecial #24                 // Method "<init>":(Ljava/lang/String;I)V
      36: putstatic     #34                 // Field EXITED:Lnet/oneandone/stool/docker/Daemon$Status;
      39: new           #2                  // class net/oneandone/stool/docker/Daemon$Status
      42: dup
      43: ldc           #36                 // String REMOVING
      45: iconst_3
      46: invokespecial #24                 // Method "<init>":(Ljava/lang/String;I)V
      49: putstatic     #38                 // Field REMOVING:Lnet/oneandone/stool/docker/Daemon$Status;
      52: iconst_4
      53: anewarray     #2                  // class net/oneandone/stool/docker/Daemon$Status
      56: dup
      57: iconst_0
      58: getstatic     #25                 // Field CREATED:Lnet/oneandone/stool/docker/Daemon$Status;
      61: aastore
      62: dup
      63: iconst_1
      64: getstatic     #30                 // Field RUNNING:Lnet/oneandone/stool/docker/Daemon$Status;
      67: aastore
      68: dup
      69: iconst_2
      70: getstatic     #34                 // Field EXITED:Lnet/oneandone/stool/docker/Daemon$Status;
      73: aastore
      74: dup
      75: iconst_3
      76: getstatic     #38                 // Field REMOVING:Lnet/oneandone/stool/docker/Daemon$Status;
      79: aastore
      80: putstatic     #1                  // Field $VALUES:[Lnet/oneandone/stool/docker/Daemon$Status;
      83: return
}
