Compiled from "parser.java"
public class java_cup.simple_calc.parser extends java_cup.runtime.lr_parser {
  protected static final short[][] _production_table;

  protected static final short[][] _action_table;

  protected static final short[][] _reduce_table;

  protected java_cup.simple_calc.CUP$parser$actions action_obj;

  public java_cup.simple_calc.parser();
    Code:
       0: aload_0
       1: invokespecial #1                  // Method java_cup/runtime/lr_parser."<init>":()V
       4: return

  public java_cup.simple_calc.parser(java_cup.runtime.Scanner);
    Code:
       0: aload_0
       1: aload_1
       2: invokespecial #2                  // Method java_cup/runtime/lr_parser."<init>":(Ljava_cup/runtime/Scanner;)V
       5: return

  public short[][] production_table();
    Code:
       0: getstatic     #3                  // Field _production_table:[[S
       3: areturn

  public short[][] action_table();
    Code:
       0: getstatic     #4                  // Field _action_table:[[S
       3: areturn

  public short[][] reduce_table();
    Code:
       0: getstatic     #5                  // Field _reduce_table:[[S
       3: areturn

  protected void init_actions();
    Code:
       0: aload_0
       1: new           #6                  // class java_cup/simple_calc/CUP$parser$actions
       4: dup
       5: aload_0
       6: invokespecial #7                  // Method java_cup/simple_calc/CUP$parser$actions."<init>":(Ljava_cup/simple_calc/parser;)V
       9: putfield      #8                  // Field action_obj:Ljava_cup/simple_calc/CUP$parser$actions;
      12: return

  public java_cup.runtime.Symbol do_action(int, java_cup.runtime.lr_parser, java.util.Stack, int) throws java.lang.Exception;
    Code:
       0: aload_0
       1: getfield      #8                  // Field action_obj:Ljava_cup/simple_calc/CUP$parser$actions;
       4: iload_1
       5: aload_2
       6: aload_3
       7: iload         4
       9: invokevirtual #9                  // Method java_cup/simple_calc/CUP$parser$actions.CUP$parser$do_action:(ILjava_cup/runtime/lr_parser;Ljava/util/Stack;I)Ljava_cup/runtime/Symbol;
      12: areturn

  public int start_state();
    Code:
       0: iconst_0
       1: ireturn

  public int start_production();
    Code:
       0: iconst_1
       1: ireturn

  public int EOF_sym();
    Code:
       0: iconst_0
       1: ireturn

  public int error_sym();
    Code:
       0: iconst_1
       1: ireturn

  static {};
    Code:
       0: iconst_1
       1: anewarray     #10                 // class java/lang/String
       4: dup
       5: iconst_0
       6: ldc           #11                 // String \u0000\r\u0000\u0002\u0003\u0004\u0000\u0002\u0002\u0004\u0000\u0002\u0003\u0003\u0000\u0002\u0006\u0002\u0000\u0002\u0004\u0005\u0000\u0002\u0005\u0005\u0000\u0002\u0005\u0005\u0000\u0002\u0005\u0005\u0000\u0002\u0005\u0005\u0000\u0002\u0005\u0005\u0000\u0002\u0005\u0003\u0000\u0002\u0005\u0004\u0000\u0002\u0005\u0005
       8: aastore
       9: invokestatic  #12                 // Method unpackFromStrings:([Ljava/lang/String;)[[S
      12: putstatic     #3                  // Field _production_table:[[S
      15: iconst_1
      16: anewarray     #10                 // class java/lang/String
      19: dup
      20: iconst_0
      21: ldc           #13                 // String \u0000\u0018\u0000\b\u0006\u0004\u000b\t\r\u0005\u0001\u0002\u0000\b\u0006\u0004\u000b\t\r\u0005\u0001\u0002\u0000\u0010\u0004￷\u0005￷\u0006￷\u0007￷\b￷\t￷\f￷\u0001\u0002\u0000\n\u0002￿\u0006￿\u000b￿\r￿\u0001\u0002\u0000\u000e\u0004￾\u0005\u000e\u0006\f\u0007\u0010\b\u000f\t\u000b\u0001\u0002\u0000\n\u0002\u0017\u0006\u0004\u000b\t\r\u0005\u0001\u0002\u0000\b\u0006\u0004\u000b\t\r\u0005\u0001\u0002\u0000\u000e\u0005\u000e\u0006\f\u0007\u0010\b\u000f\t\u000b\f\r\u0001\u0002\u0000\b\u0006\u0004\u000b\t\r\u0005\u0001\u0002\u0000\b\u0006\u0004\u000b\t\r\u0005\u0001\u0002\u0000\u0010\u0004￵\u0005￵\u0006￵\u0007￵\b￵\t￵\f￵\u0001\u0002\u0000\b\u0006\u0004\u000b\t\r\u0005\u0001\u0002\u0000\b\u0006\u0004\u000b\t\r\u0005\u0001\u0002\u0000\b\u0006\u0004\u000b\t\r\u0005\u0001\u0002\u0000\u0010\u0004￺\u0005￺\u0006￺\u0007￺\b￺\t￺\f￺\u0001\u0002\u0000\u0010\u0004￹\u0005￹\u0006￹\u0007￹\b￹\t￹\f￹\u0001\u0002\u0000\u0010\u0004￼\u0005￼\u0006￼\u0007\u0010\b\u000f\t\u000b\f￼\u0001\u0002\u0000\u0010\u0004￻\u0005￻\u0006￻\u0007\u0010\b\u000f\t\u000b\f￻\u0001\u0002\u0000\u0010\u0004￸\u0005￸\u0006￸\u0007￸\b￸\t￸\f￸\u0001\u0002\u0000\n\u0002\u0001\u0006\u0001\u000b\u0001\r\u0001\u0001\u0002\u0000\u0004\u0002\u0000\u0001\u0002\u0000\u0004\u0004\u0019\u0001\u0002\u0000\n\u0002�\u0006�\u000b�\r�\u0001\u0002\u0000\u0010\u0004￶\u0005￶\u0006￶\u0007￶\b￶\t￶\f￶\u0001\u0002
      23: aastore
      24: invokestatic  #12                 // Method unpackFromStrings:([Ljava/lang/String;)[[S
      27: putstatic     #4                  // Field _action_table:[[S
      30: iconst_1
      31: anewarray     #10                 // class java/lang/String
      34: dup
      35: iconst_0
      36: ldc           #14                 // String \u0000\u0018\u0000\b\u0003\u0007\u0004\u0005\u0005\u0006\u0001\u0001\u0000\u0004\u0005\u0019\u0001\u0001\u0000\u0002\u0001\u0001\u0000\u0002\u0001\u0001\u0000\u0004\u0006\u0017\u0001\u0001\u0000\u0006\u0004\u0015\u0005\u0006\u0001\u0001\u0000\u0004\u0005\t\u0001\u0001\u0000\u0002\u0001\u0001\u0000\u0004\u0005\u0014\u0001\u0001\u0000\u0004\u0005\u0013\u0001\u0001\u0000\u0002\u0001\u0001\u0000\u0004\u0005\u0012\u0001\u0001\u0000\u0004\u0005\u0011\u0001\u0001\u0000\u0004\u0005\u0010\u0001\u0001\u0000\u0002\u0001\u0001\u0000\u0002\u0001\u0001\u0000\u0002\u0001\u0001\u0000\u0002\u0001\u0001\u0000\u0002\u0001\u0001\u0000\u0002\u0001\u0001\u0000\u0002\u0001\u0001\u0000\u0002\u0001\u0001\u0000\u0002\u0001\u0001\u0000\u0002\u0001\u0001
      38: aastore
      39: invokestatic  #12                 // Method unpackFromStrings:([Ljava/lang/String;)[[S
      42: putstatic     #5                  // Field _reduce_table:[[S
      45: return
}
