Compiled from "CastingInjector.java"
public final class org.jboss.msc.inject.CastingInjector<T> implements org.jboss.msc.inject.Injector<java.lang.Object> {
  private final org.jboss.msc.inject.Injector<T> target;

  private final java.lang.Class<T> type;

  public org.jboss.msc.inject.CastingInjector(org.jboss.msc.inject.Injector<T>, java.lang.Class<T>);
    Code:
       0: aload_0
       1: invokespecial #1                  // Method java/lang/Object."<init>":()V
       4: aload_0
       5: aload_1
       6: putfield      #2                  // Field target:Lorg/jboss/msc/inject/Injector;
       9: aload_0
      10: aload_2
      11: putfield      #3                  // Field type:Ljava/lang/Class;
      14: return

  public void inject(java.lang.Object) throws org.jboss.msc.inject.InjectionException;
    Code:
       0: aload_0
       1: getfield      #3                  // Field type:Ljava/lang/Class;
       4: aload_1
       5: invokevirtual #4                  // Method java/lang/Class.cast:(Ljava/lang/Object;)Ljava/lang/Object;
       8: astore_2
       9: goto          61
      12: astore_3
      13: new           #6                  // class org/jboss/msc/inject/InjectionException
      16: dup
      17: new           #7                  // class java/lang/StringBuilder
      20: dup
      21: invokespecial #8                  // Method java/lang/StringBuilder."<init>":()V
      24: ldc           #9                  // String Injecting the wrong type (expected
      26: invokevirtual #10                 // Method java/lang/StringBuilder.append:(Ljava/lang/String;)Ljava/lang/StringBuilder;
      29: aload_0
      30: getfield      #3                  // Field type:Ljava/lang/Class;
      33: invokevirtual #11                 // Method java/lang/StringBuilder.append:(Ljava/lang/Object;)Ljava/lang/StringBuilder;
      36: ldc           #12                 // String , got
      38: invokevirtual #10                 // Method java/lang/StringBuilder.append:(Ljava/lang/String;)Ljava/lang/StringBuilder;
      41: aload_1
      42: invokevirtual #13                 // Method java/lang/Object.getClass:()Ljava/lang/Class;
      45: invokevirtual #11                 // Method java/lang/StringBuilder.append:(Ljava/lang/Object;)Ljava/lang/StringBuilder;
      48: ldc           #14                 // String )
      50: invokevirtual #10                 // Method java/lang/StringBuilder.append:(Ljava/lang/String;)Ljava/lang/StringBuilder;
      53: invokevirtual #15                 // Method java/lang/StringBuilder.toString:()Ljava/lang/String;
      56: aload_3
      57: invokespecial #16                 // Method org/jboss/msc/inject/InjectionException."<init>":(Ljava/lang/String;Ljava/lang/Throwable;)V
      60: athrow
      61: aload_0
      62: getfield      #2                  // Field target:Lorg/jboss/msc/inject/Injector;
      65: aload_2
      66: invokeinterface #17,  2           // InterfaceMethod org/jboss/msc/inject/Injector.inject:(Ljava/lang/Object;)V
      71: return
    Exception table:
       from    to  target type
           0     9    12   Class java/lang/ClassCastException

  public void uninject();
    Code:
       0: aload_0
       1: getfield      #2                  // Field target:Lorg/jboss/msc/inject/Injector;
       4: invokeinterface #18,  1           // InterfaceMethod org/jboss/msc/inject/Injector.uninject:()V
       9: return
}
