Compiled from "BackendAddressGroup.java"
final class io.grpc.grpclb.BackendAddressGroup {
  private final io.grpc.EquivalentAddressGroup addresses;

  private final java.lang.String token;

  io.grpc.grpclb.BackendAddressGroup(io.grpc.EquivalentAddressGroup, java.lang.String);
    Code:
       0: aload_0
       1: invokespecial #1                  // Method java/lang/Object."<init>":()V
       4: aload_0
       5: aload_1
       6: ldc           #2                  // String addresses
       8: invokestatic  #3                  // Method com/google/common/base/Preconditions.checkNotNull:(Ljava/lang/Object;Ljava/lang/Object;)Ljava/lang/Object;
      11: checkcast     #4                  // class io/grpc/EquivalentAddressGroup
      14: putfield      #5                  // Field addresses:Lio/grpc/EquivalentAddressGroup;
      17: aload_0
      18: aload_2
      19: putfield      #6                  // Field token:Ljava/lang/String;
      22: return

  io.grpc.EquivalentAddressGroup getAddresses();
    Code:
       0: aload_0
       1: getfield      #5                  // Field addresses:Lio/grpc/EquivalentAddressGroup;
       4: areturn

  java.lang.String getToken();
    Code:
       0: aload_0
       1: getfield      #6                  // Field token:Ljava/lang/String;
       4: areturn

  public java.lang.String toString();
    Code:
       0: new           #7                  // class java/lang/StringBuilder
       3: dup
       4: invokespecial #8                  // Method java/lang/StringBuilder."<init>":()V
       7: astore_1
       8: aload_1
       9: aload_0
      10: getfield      #5                  // Field addresses:Lio/grpc/EquivalentAddressGroup;
      13: invokevirtual #9                  // Method java/lang/StringBuilder.append:(Ljava/lang/Object;)Ljava/lang/StringBuilder;
      16: pop
      17: aload_0
      18: getfield      #6                  // Field token:Ljava/lang/String;
      21: ifnull        43
      24: aload_1
      25: ldc           #10                 // String (
      27: invokevirtual #11                 // Method java/lang/StringBuilder.append:(Ljava/lang/String;)Ljava/lang/StringBuilder;
      30: aload_0
      31: getfield      #6                  // Field token:Ljava/lang/String;
      34: invokevirtual #11                 // Method java/lang/StringBuilder.append:(Ljava/lang/String;)Ljava/lang/StringBuilder;
      37: ldc           #12                 // String )
      39: invokevirtual #11                 // Method java/lang/StringBuilder.append:(Ljava/lang/String;)Ljava/lang/StringBuilder;
      42: pop
      43: aload_1
      44: invokevirtual #13                 // Method java/lang/StringBuilder.toString:()Ljava/lang/String;
      47: areturn
}
