Compiled from "GrpclbState.java"
final class io.grpc.grpclb.GrpclbState$IdleSubchannelEntry implements io.grpc.grpclb.GrpclbState$RoundRobinEntry {
  private final io.grpc.SynchronizationContext syncContext;

  private final io.grpc.LoadBalancer$Subchannel subchannel;

  private final java.util.concurrent.atomic.AtomicBoolean connectionRequested;

  io.grpc.grpclb.GrpclbState$IdleSubchannelEntry(io.grpc.LoadBalancer$Subchannel, io.grpc.SynchronizationContext);
    Code:
       0: aload_0
       1: invokespecial #2                  // Method java/lang/Object."<init>":()V
       4: aload_0
       5: new           #3                  // class java/util/concurrent/atomic/AtomicBoolean
       8: dup
       9: iconst_0
      10: invokespecial #4                  // Method java/util/concurrent/atomic/AtomicBoolean."<init>":(Z)V
      13: putfield      #5                  // Field connectionRequested:Ljava/util/concurrent/atomic/AtomicBoolean;
      16: aload_0
      17: aload_1
      18: ldc           #6                  // String subchannel
      20: invokestatic  #7                  // Method com/google/common/base/Preconditions.checkNotNull:(Ljava/lang/Object;Ljava/lang/Object;)Ljava/lang/Object;
      23: checkcast     #8                  // class io/grpc/LoadBalancer$Subchannel
      26: putfield      #1                  // Field subchannel:Lio/grpc/LoadBalancer$Subchannel;
      29: aload_0
      30: aload_2
      31: ldc           #9                  // String syncContext
      33: invokestatic  #7                  // Method com/google/common/base/Preconditions.checkNotNull:(Ljava/lang/Object;Ljava/lang/Object;)Ljava/lang/Object;
      36: checkcast     #10                 // class io/grpc/SynchronizationContext
      39: putfield      #11                 // Field syncContext:Lio/grpc/SynchronizationContext;
      42: return

  public io.grpc.LoadBalancer$PickResult picked(io.grpc.Metadata);
    Code:
       0: aload_0
       1: getfield      #5                  // Field connectionRequested:Ljava/util/concurrent/atomic/AtomicBoolean;
       4: iconst_0
       5: iconst_1
       6: invokevirtual #12                 // Method java/util/concurrent/atomic/AtomicBoolean.compareAndSet:(ZZ)Z
       9: ifeq          27
      12: aload_0
      13: getfield      #11                 // Field syncContext:Lio/grpc/SynchronizationContext;
      16: new           #13                 // class io/grpc/grpclb/GrpclbState$IdleSubchannelEntry$1
      19: dup
      20: aload_0
      21: invokespecial #14                 // Method io/grpc/grpclb/GrpclbState$IdleSubchannelEntry$1."<init>":(Lio/grpc/grpclb/GrpclbState$IdleSubchannelEntry;)V
      24: invokevirtual #15                 // Method io/grpc/SynchronizationContext.execute:(Ljava/lang/Runnable;)V
      27: invokestatic  #16                 // Method io/grpc/LoadBalancer$PickResult.withNoResult:()Lio/grpc/LoadBalancer$PickResult;
      30: areturn

  public java.lang.String toString();
    Code:
       0: new           #17                 // class java/lang/StringBuilder
       3: dup
       4: invokespecial #18                 // Method java/lang/StringBuilder."<init>":()V
       7: ldc           #19                 // String (idle)[
       9: invokevirtual #20                 // Method java/lang/StringBuilder.append:(Ljava/lang/String;)Ljava/lang/StringBuilder;
      12: aload_0
      13: getfield      #1                  // Field subchannel:Lio/grpc/LoadBalancer$Subchannel;
      16: invokevirtual #21                 // Method io/grpc/LoadBalancer$Subchannel.getAllAddresses:()Ljava/util/List;
      19: invokevirtual #22                 // Method java/lang/Object.toString:()Ljava/lang/String;
      22: invokevirtual #20                 // Method java/lang/StringBuilder.append:(Ljava/lang/String;)Ljava/lang/StringBuilder;
      25: ldc           #23                 // String ]
      27: invokevirtual #20                 // Method java/lang/StringBuilder.append:(Ljava/lang/String;)Ljava/lang/StringBuilder;
      30: invokevirtual #24                 // Method java/lang/StringBuilder.toString:()Ljava/lang/String;
      33: areturn

  public int hashCode();
    Code:
       0: iconst_2
       1: anewarray     #25                 // class java/lang/Object
       4: dup
       5: iconst_0
       6: aload_0
       7: getfield      #1                  // Field subchannel:Lio/grpc/LoadBalancer$Subchannel;
      10: aastore
      11: dup
      12: iconst_1
      13: aload_0
      14: getfield      #11                 // Field syncContext:Lio/grpc/SynchronizationContext;
      17: aastore
      18: invokestatic  #26                 // Method com/google/common/base/Objects.hashCode:([Ljava/lang/Object;)I
      21: ireturn

  public boolean equals(java.lang.Object);
    Code:
       0: aload_1
       1: instanceof    #27                 // class io/grpc/grpclb/GrpclbState$IdleSubchannelEntry
       4: ifne          9
       7: iconst_0
       8: ireturn
       9: aload_1
      10: checkcast     #27                 // class io/grpc/grpclb/GrpclbState$IdleSubchannelEntry
      13: astore_2
      14: aload_0
      15: getfield      #1                  // Field subchannel:Lio/grpc/LoadBalancer$Subchannel;
      18: aload_2
      19: getfield      #1                  // Field subchannel:Lio/grpc/LoadBalancer$Subchannel;
      22: invokestatic  #28                 // Method com/google/common/base/Objects.equal:(Ljava/lang/Object;Ljava/lang/Object;)Z
      25: ifeq          46
      28: aload_0
      29: getfield      #11                 // Field syncContext:Lio/grpc/SynchronizationContext;
      32: aload_2
      33: getfield      #11                 // Field syncContext:Lio/grpc/SynchronizationContext;
      36: invokestatic  #28                 // Method com/google/common/base/Objects.equal:(Ljava/lang/Object;Ljava/lang/Object;)Z
      39: ifeq          46
      42: iconst_1
      43: goto          47
      46: iconst_0
      47: ireturn

  static io.grpc.LoadBalancer$Subchannel access$100(io.grpc.grpclb.GrpclbState$IdleSubchannelEntry);
    Code:
       0: aload_0
       1: getfield      #1                  // Field subchannel:Lio/grpc/LoadBalancer$Subchannel;
       4: areturn
}
