Compiled from "GrpclbState.java"
class io.grpc.grpclb.GrpclbState$4 {
  static final int[] $SwitchMap$io$grpc$grpclb$GrpclbState$Mode;

  static final int[] $SwitchMap$io$grpc$ConnectivityState;

  static {};
    Code:
       0: invokestatic  #1                  // Method io/grpc/ConnectivityState.values:()[Lio/grpc/ConnectivityState;
       3: arraylength
       4: newarray       int
       6: putstatic     #2                  // Field $SwitchMap$io$grpc$ConnectivityState:[I
       9: getstatic     #2                  // Field $SwitchMap$io$grpc$ConnectivityState:[I
      12: getstatic     #3                  // Field io/grpc/ConnectivityState.READY:Lio/grpc/ConnectivityState;
      15: invokevirtual #4                  // Method io/grpc/ConnectivityState.ordinal:()I
      18: iconst_1
      19: iastore
      20: goto          24
      23: astore_0
      24: getstatic     #2                  // Field $SwitchMap$io$grpc$ConnectivityState:[I
      27: getstatic     #6                  // Field io/grpc/ConnectivityState.TRANSIENT_FAILURE:Lio/grpc/ConnectivityState;
      30: invokevirtual #4                  // Method io/grpc/ConnectivityState.ordinal:()I
      33: iconst_2
      34: iastore
      35: goto          39
      38: astore_0
      39: getstatic     #2                  // Field $SwitchMap$io$grpc$ConnectivityState:[I
      42: getstatic     #7                  // Field io/grpc/ConnectivityState.CONNECTING:Lio/grpc/ConnectivityState;
      45: invokevirtual #4                  // Method io/grpc/ConnectivityState.ordinal:()I
      48: iconst_3
      49: iastore
      50: goto          54
      53: astore_0
      54: invokestatic  #8                  // Method io/grpc/grpclb/GrpclbState$Mode.values:()[Lio/grpc/grpclb/GrpclbState$Mode;
      57: arraylength
      58: newarray       int
      60: putstatic     #9                  // Field $SwitchMap$io$grpc$grpclb$GrpclbState$Mode:[I
      63: getstatic     #9                  // Field $SwitchMap$io$grpc$grpclb$GrpclbState$Mode:[I
      66: getstatic     #10                 // Field io/grpc/grpclb/GrpclbState$Mode.ROUND_ROBIN:Lio/grpc/grpclb/GrpclbState$Mode;
      69: invokevirtual #11                 // Method io/grpc/grpclb/GrpclbState$Mode.ordinal:()I
      72: iconst_1
      73: iastore
      74: goto          78
      77: astore_0
      78: getstatic     #9                  // Field $SwitchMap$io$grpc$grpclb$GrpclbState$Mode:[I
      81: getstatic     #12                 // Field io/grpc/grpclb/GrpclbState$Mode.PICK_FIRST:Lio/grpc/grpclb/GrpclbState$Mode;
      84: invokevirtual #11                 // Method io/grpc/grpclb/GrpclbState$Mode.ordinal:()I
      87: iconst_2
      88: iastore
      89: goto          93
      92: astore_0
      93: return
    Exception table:
       from    to  target type
           9    20    23   Class java/lang/NoSuchFieldError
          24    35    38   Class java/lang/NoSuchFieldError
          39    50    53   Class java/lang/NoSuchFieldError
          63    74    77   Class java/lang/NoSuchFieldError
          78    89    92   Class java/lang/NoSuchFieldError
}
