class org.bouncycastle.pqc.crypto.mceliece.Utils {
  org.bouncycastle.pqc.crypto.mceliece.Utils();
    Code:
       0: aload_0
       1: invokespecial #50                 // Method java/lang/Object."<init>":()V
       4: return

  static org.bouncycastle.crypto.Digest getDigest(java.lang.String);
    Code:
       0: aload_0
       1: ldc           #1                  // String SHA-1
       3: invokevirtual #51                 // Method java/lang/String.equals:(Ljava/lang/Object;)Z
       6: ifeq          17
       9: new           #33                 // class org/bouncycastle/crypto/digests/SHA1Digest
      12: dup
      13: invokespecial #55                 // Method org/bouncycastle/crypto/digests/SHA1Digest."<init>":()V
      16: areturn
      17: aload_0
      18: ldc           #2                  // String SHA-224
      20: invokevirtual #51                 // Method java/lang/String.equals:(Ljava/lang/Object;)Z
      23: ifeq          34
      26: new           #34                 // class org/bouncycastle/crypto/digests/SHA224Digest
      29: dup
      30: invokespecial #56                 // Method org/bouncycastle/crypto/digests/SHA224Digest."<init>":()V
      33: areturn
      34: aload_0
      35: ldc           #3                  // String SHA-256
      37: invokevirtual #51                 // Method java/lang/String.equals:(Ljava/lang/Object;)Z
      40: ifeq          51
      43: new           #35                 // class org/bouncycastle/crypto/digests/SHA256Digest
      46: dup
      47: invokespecial #57                 // Method org/bouncycastle/crypto/digests/SHA256Digest."<init>":()V
      50: areturn
      51: aload_0
      52: ldc           #4                  // String SHA-384
      54: invokevirtual #51                 // Method java/lang/String.equals:(Ljava/lang/Object;)Z
      57: ifeq          68
      60: new           #36                 // class org/bouncycastle/crypto/digests/SHA384Digest
      63: dup
      64: invokespecial #58                 // Method org/bouncycastle/crypto/digests/SHA384Digest."<init>":()V
      67: areturn
      68: aload_0
      69: ldc           #5                  // String SHA-512
      71: invokevirtual #51                 // Method java/lang/String.equals:(Ljava/lang/Object;)Z
      74: ifeq          85
      77: new           #37                 // class org/bouncycastle/crypto/digests/SHA512Digest
      80: dup
      81: invokespecial #59                 // Method org/bouncycastle/crypto/digests/SHA512Digest."<init>":()V
      84: areturn
      85: new           #29                 // class java/lang/IllegalArgumentException
      88: dup
      89: new           #32                 // class java/lang/StringBuilder
      92: dup
      93: invokespecial #52                 // Method java/lang/StringBuilder."<init>":()V
      96: ldc           #6                  // String unrecognised digest algorithm:
      98: invokevirtual #54                 // Method java/lang/StringBuilder.append:(Ljava/lang/String;)Ljava/lang/StringBuilder;
     101: aload_0
     102: invokevirtual #54                 // Method java/lang/StringBuilder.append:(Ljava/lang/String;)Ljava/lang/StringBuilder;
     105: invokevirtual #53                 // Method java/lang/StringBuilder.toString:()Ljava/lang/String;
     108: invokespecial #49                 // Method java/lang/IllegalArgumentException."<init>":(Ljava/lang/String;)V
     111: athrow
}
