Compiled from "GelfLayout.java"
public final class org.apache.logging.log4j.core.layout.GelfLayout extends org.apache.logging.log4j.core.layout.AbstractStringLayout {
  private static final char C;

  private static final int COMPRESSION_THRESHOLD;

  private static final char Q;

  private static final java.lang.String QC;

  private static final java.lang.String QU;

  private final org.apache.logging.log4j.core.util.KeyValuePair[] additionalFields;

  private final int compressionThreshold;

  private final org.apache.logging.log4j.core.layout.GelfLayout$CompressionType compressionType;

  private final java.lang.String host;

  private final boolean includeStacktrace;

  private final boolean includeThreadContext;

  private final boolean includeMapMessage;

  private final boolean includeNullDelimiter;

  private final boolean includeNewLineDelimiter;

  private final boolean omitEmptyFields;

  private final org.apache.logging.log4j.core.layout.PatternLayout layout;

  private final org.apache.logging.log4j.core.layout.GelfLayout$FieldWriter mdcWriter;

  private final org.apache.logging.log4j.core.layout.GelfLayout$FieldWriter mapWriter;

  private static final java.lang.ThreadLocal<java.lang.StringBuilder> messageStringBuilder;

  private static final java.lang.ThreadLocal<java.lang.StringBuilder> timestampStringBuilder;

  public org.apache.logging.log4j.core.layout.GelfLayout(java.lang.String, org.apache.logging.log4j.core.util.KeyValuePair[], org.apache.logging.log4j.core.layout.GelfLayout$CompressionType, int, boolean);
    Code:
       0: aload_0
       1: aconst_null
       2: aload_1
       3: aload_2
       4: aload_3
       5: iload         4
       7: iload         5
       9: iconst_1
      10: iconst_1
      11: iconst_0
      12: iconst_0
      13: iconst_0
      14: aconst_null
      15: aconst_null
      16: aconst_null
      17: ldc           #4                  // String
      19: ldc           #4                  // String
      21: invokespecial #3                  // Method "<init>":(Lorg/apache/logging/log4j/core/config/Configuration;Ljava/lang/String;[Lorg/apache/logging/log4j/core/util/KeyValuePair;Lorg/apache/logging/log4j/core/layout/GelfLayout$CompressionType;IZZZZZZLorg/apache/logging/log4j/core/layout/internal/ListChecker;Lorg/apache/logging/log4j/core/layout/internal/ListChecker;Lorg/apache/logging/log4j/core/layout/PatternLayout;Ljava/lang/String;Ljava/lang/String;)V
      24: return

  private org.apache.logging.log4j.core.layout.GelfLayout(org.apache.logging.log4j.core.config.Configuration, java.lang.String, org.apache.logging.log4j.core.util.KeyValuePair[], org.apache.logging.log4j.core.layout.GelfLayout$CompressionType, int, boolean, boolean, boolean, boolean, boolean, boolean, org.apache.logging.log4j.core.layout.internal.ListChecker, org.apache.logging.log4j.core.layout.internal.ListChecker, org.apache.logging.log4j.core.layout.PatternLayout, java.lang.String, java.lang.String);
    Code:
       0: aload_0
       1: aload_1
       2: getstatic     #5                  // Field java/nio/charset/StandardCharsets.UTF_8:Ljava/nio/charset/Charset;
       5: aconst_null
       6: aconst_null
       7: invokespecial #6                  // Method org/apache/logging/log4j/core/layout/AbstractStringLayout."<init>":(Lorg/apache/logging/log4j/core/config/Configuration;Ljava/nio/charset/Charset;Lorg/apache/logging/log4j/core/layout/AbstractStringLayout$Serializer;Lorg/apache/logging/log4j/core/layout/AbstractStringLayout$Serializer;)V
      10: aload_0
      11: aload_2
      12: ifnull        19
      15: aload_2
      16: goto          22
      19: invokestatic  #7                  // Method org/apache/logging/log4j/core/util/NetUtils.getLocalHostname:()Ljava/lang/String;
      22: putfield      #8                  // Field host:Ljava/lang/String;
      25: aload_0
      26: aload_3
      27: ifnull        34
      30: aload_3
      31: goto          37
      34: getstatic     #9                  // Field org/apache/logging/log4j/core/util/KeyValuePair.EMPTY_ARRAY:[Lorg/apache/logging/log4j/core/util/KeyValuePair;
      37: putfield      #10                 // Field additionalFields:[Lorg/apache/logging/log4j/core/util/KeyValuePair;
      40: aload_1
      41: ifnonnull     99
      44: aload_0
      45: getfield      #10                 // Field additionalFields:[Lorg/apache/logging/log4j/core/util/KeyValuePair;
      48: astore        17
      50: aload         17
      52: arraylength
      53: istore        18
      55: iconst_0
      56: istore        19
      58: iload         19
      60: iload         18
      62: if_icmpge     99
      65: aload         17
      67: iload         19
      69: aaload
      70: astore        20
      72: aload         20
      74: invokevirtual #11                 // Method org/apache/logging/log4j/core/util/KeyValuePair.getValue:()Ljava/lang/String;
      77: invokestatic  #12                 // Method valueNeedsLookup:(Ljava/lang/String;)Z
      80: ifeq          93
      83: new           #13                 // class java/lang/IllegalArgumentException
      86: dup
      87: ldc           #14                 // String configuration needs to be set when there are additional fields with variables
      89: invokespecial #15                 // Method java/lang/IllegalArgumentException."<init>":(Ljava/lang/String;)V
      92: athrow
      93: iinc          19, 1
      96: goto          58
      99: aload_0
     100: aload         4
     102: putfield      #16                 // Field compressionType:Lorg/apache/logging/log4j/core/layout/GelfLayout$CompressionType;
     105: aload_0
     106: iload         5
     108: putfield      #17                 // Field compressionThreshold:I
     111: aload_0
     112: iload         6
     114: putfield      #18                 // Field includeStacktrace:Z
     117: aload_0
     118: iload         7
     120: putfield      #19                 // Field includeThreadContext:Z
     123: aload_0
     124: iload         8
     126: putfield      #20                 // Field includeMapMessage:Z
     129: aload_0
     130: iload         9
     132: putfield      #21                 // Field includeNullDelimiter:Z
     135: aload_0
     136: iload         10
     138: putfield      #22                 // Field includeNewLineDelimiter:Z
     141: aload_0
     142: iload         11
     144: putfield      #2                  // Field omitEmptyFields:Z
     147: iload         9
     149: ifeq          170
     152: aload         4
     154: getstatic     #23                 // Field org/apache/logging/log4j/core/layout/GelfLayout$CompressionType.OFF:Lorg/apache/logging/log4j/core/layout/GelfLayout$CompressionType;
     157: if_acmpeq     170
     160: new           #13                 // class java/lang/IllegalArgumentException
     163: dup
     164: ldc           #24                 // String null delimiter cannot be used with compression
     166: invokespecial #15                 // Method java/lang/IllegalArgumentException."<init>":(Ljava/lang/String;)V
     169: athrow
     170: aload_0
     171: new           #25                 // class org/apache/logging/log4j/core/layout/GelfLayout$FieldWriter
     174: dup
     175: aload_0
     176: aload         12
     178: aload         15
     180: invokespecial #26                 // Method org/apache/logging/log4j/core/layout/GelfLayout$FieldWriter."<init>":(Lorg/apache/logging/log4j/core/layout/GelfLayout;Lorg/apache/logging/log4j/core/layout/internal/ListChecker;Ljava/lang/String;)V
     183: putfield      #27                 // Field mdcWriter:Lorg/apache/logging/log4j/core/layout/GelfLayout$FieldWriter;
     186: aload_0
     187: new           #25                 // class org/apache/logging/log4j/core/layout/GelfLayout$FieldWriter
     190: dup
     191: aload_0
     192: aload         13
     194: aload         16
     196: invokespecial #26                 // Method org/apache/logging/log4j/core/layout/GelfLayout$FieldWriter."<init>":(Lorg/apache/logging/log4j/core/layout/GelfLayout;Lorg/apache/logging/log4j/core/layout/internal/ListChecker;Ljava/lang/String;)V
     199: putfield      #28                 // Field mapWriter:Lorg/apache/logging/log4j/core/layout/GelfLayout$FieldWriter;
     202: aload_0
     203: aload         14
     205: putfield      #29                 // Field layout:Lorg/apache/logging/log4j/core/layout/PatternLayout;
     208: return

  public java.lang.String toString();
    Code:
       0: new           #30                 // class java/lang/StringBuilder
       3: dup
       4: invokespecial #31                 // Method java/lang/StringBuilder."<init>":()V
       7: astore_1
       8: aload_1
       9: ldc           #32                 // String host=
      11: invokevirtual #33                 // Method java/lang/StringBuilder.append:(Ljava/lang/String;)Ljava/lang/StringBuilder;
      14: aload_0
      15: getfield      #8                  // Field host:Ljava/lang/String;
      18: invokevirtual #33                 // Method java/lang/StringBuilder.append:(Ljava/lang/String;)Ljava/lang/StringBuilder;
      21: pop
      22: aload_1
      23: ldc           #34                 // String , compressionType=
      25: invokevirtual #33                 // Method java/lang/StringBuilder.append:(Ljava/lang/String;)Ljava/lang/StringBuilder;
      28: aload_0
      29: getfield      #16                 // Field compressionType:Lorg/apache/logging/log4j/core/layout/GelfLayout$CompressionType;
      32: invokevirtual #35                 // Method org/apache/logging/log4j/core/layout/GelfLayout$CompressionType.toString:()Ljava/lang/String;
      35: invokevirtual #33                 // Method java/lang/StringBuilder.append:(Ljava/lang/String;)Ljava/lang/StringBuilder;
      38: pop
      39: aload_1
      40: ldc           #36                 // String , compressionThreshold=
      42: invokevirtual #33                 // Method java/lang/StringBuilder.append:(Ljava/lang/String;)Ljava/lang/StringBuilder;
      45: aload_0
      46: getfield      #17                 // Field compressionThreshold:I
      49: invokevirtual #37                 // Method java/lang/StringBuilder.append:(I)Ljava/lang/StringBuilder;
      52: pop
      53: aload_1
      54: ldc           #38                 // String , includeStackTrace=
      56: invokevirtual #33                 // Method java/lang/StringBuilder.append:(Ljava/lang/String;)Ljava/lang/StringBuilder;
      59: aload_0
      60: getfield      #18                 // Field includeStacktrace:Z
      63: invokevirtual #39                 // Method java/lang/StringBuilder.append:(Z)Ljava/lang/StringBuilder;
      66: pop
      67: aload_1
      68: ldc           #40                 // String , includeThreadContext=
      70: invokevirtual #33                 // Method java/lang/StringBuilder.append:(Ljava/lang/String;)Ljava/lang/StringBuilder;
      73: aload_0
      74: getfield      #19                 // Field includeThreadContext:Z
      77: invokevirtual #39                 // Method java/lang/StringBuilder.append:(Z)Ljava/lang/StringBuilder;
      80: pop
      81: aload_1
      82: ldc           #41                 // String , includeNullDelimiter=
      84: invokevirtual #33                 // Method java/lang/StringBuilder.append:(Ljava/lang/String;)Ljava/lang/StringBuilder;
      87: aload_0
      88: getfield      #21                 // Field includeNullDelimiter:Z
      91: invokevirtual #39                 // Method java/lang/StringBuilder.append:(Z)Ljava/lang/StringBuilder;
      94: pop
      95: aload_1
      96: ldc           #42                 // String , includeNewLineDelimiter=
      98: invokevirtual #33                 // Method java/lang/StringBuilder.append:(Ljava/lang/String;)Ljava/lang/StringBuilder;
     101: aload_0
     102: getfield      #22                 // Field includeNewLineDelimiter:Z
     105: invokevirtual #39                 // Method java/lang/StringBuilder.append:(Z)Ljava/lang/StringBuilder;
     108: pop
     109: aload_0
     110: getfield      #27                 // Field mdcWriter:Lorg/apache/logging/log4j/core/layout/GelfLayout$FieldWriter;
     113: invokevirtual #43                 // Method org/apache/logging/log4j/core/layout/GelfLayout$FieldWriter.getChecker:()Lorg/apache/logging/log4j/core/layout/internal/ListChecker;
     116: invokevirtual #44                 // Method java/lang/Object.toString:()Ljava/lang/String;
     119: astore_2
     120: aload_2
     121: invokevirtual #45                 // Method java/lang/String.length:()I
     124: ifle          138
     127: aload_1
     128: ldc           #46                 // String ,
     130: invokevirtual #33                 // Method java/lang/StringBuilder.append:(Ljava/lang/String;)Ljava/lang/StringBuilder;
     133: aload_2
     134: invokevirtual #33                 // Method java/lang/StringBuilder.append:(Ljava/lang/String;)Ljava/lang/StringBuilder;
     137: pop
     138: aload_0
     139: getfield      #28                 // Field mapWriter:Lorg/apache/logging/log4j/core/layout/GelfLayout$FieldWriter;
     142: invokevirtual #43                 // Method org/apache/logging/log4j/core/layout/GelfLayout$FieldWriter.getChecker:()Lorg/apache/logging/log4j/core/layout/internal/ListChecker;
     145: invokevirtual #44                 // Method java/lang/Object.toString:()Ljava/lang/String;
     148: astore_3
     149: aload_3
     150: invokevirtual #45                 // Method java/lang/String.length:()I
     153: ifle          167
     156: aload_1
     157: ldc           #46                 // String ,
     159: invokevirtual #33                 // Method java/lang/StringBuilder.append:(Ljava/lang/String;)Ljava/lang/StringBuilder;
     162: aload_3
     163: invokevirtual #33                 // Method java/lang/StringBuilder.append:(Ljava/lang/String;)Ljava/lang/StringBuilder;
     166: pop
     167: aload_0
     168: getfield      #29                 // Field layout:Lorg/apache/logging/log4j/core/layout/PatternLayout;
     171: ifnull        196
     174: aload_1
     175: ldc           #47                 // String , PatternLayout{
     177: invokevirtual #33                 // Method java/lang/StringBuilder.append:(Ljava/lang/String;)Ljava/lang/StringBuilder;
     180: aload_0
     181: getfield      #29                 // Field layout:Lorg/apache/logging/log4j/core/layout/PatternLayout;
     184: invokevirtual #48                 // Method org/apache/logging/log4j/core/layout/PatternLayout.toString:()Ljava/lang/String;
     187: invokevirtual #33                 // Method java/lang/StringBuilder.append:(Ljava/lang/String;)Ljava/lang/StringBuilder;
     190: ldc           #49                 // String }
     192: invokevirtual #33                 // Method java/lang/StringBuilder.append:(Ljava/lang/String;)Ljava/lang/StringBuilder;
     195: pop
     196: aload_1
     197: invokevirtual #50                 // Method java/lang/StringBuilder.toString:()Ljava/lang/String;
     200: areturn

  public static org.apache.logging.log4j.core.layout.GelfLayout createLayout(java.lang.String, org.apache.logging.log4j.core.util.KeyValuePair[], org.apache.logging.log4j.core.layout.GelfLayout$CompressionType, int, boolean);
    Code:
       0: new           #51                 // class org/apache/logging/log4j/core/layout/GelfLayout
       3: dup
       4: aconst_null
       5: aload_0
       6: aload_1
       7: aload_2
       8: iload_3
       9: iload         4
      11: iconst_1
      12: iconst_1
      13: iconst_0
      14: iconst_0
      15: iconst_0
      16: aconst_null
      17: aconst_null
      18: aconst_null
      19: ldc           #4                  // String
      21: ldc           #4                  // String
      23: invokespecial #3                  // Method "<init>":(Lorg/apache/logging/log4j/core/config/Configuration;Ljava/lang/String;[Lorg/apache/logging/log4j/core/util/KeyValuePair;Lorg/apache/logging/log4j/core/layout/GelfLayout$CompressionType;IZZZZZZLorg/apache/logging/log4j/core/layout/internal/ListChecker;Lorg/apache/logging/log4j/core/layout/internal/ListChecker;Lorg/apache/logging/log4j/core/layout/PatternLayout;Ljava/lang/String;Ljava/lang/String;)V
      26: areturn

  public static <B extends org.apache.logging.log4j.core.layout.GelfLayout$Builder<B>> B newBuilder();
    Code:
       0: new           #52                 // class org/apache/logging/log4j/core/layout/GelfLayout$Builder
       3: dup
       4: invokespecial #53                 // Method org/apache/logging/log4j/core/layout/GelfLayout$Builder."<init>":()V
       7: invokevirtual #54                 // Method org/apache/logging/log4j/core/layout/GelfLayout$Builder.asBuilder:()Lorg/apache/logging/log4j/core/layout/AbstractLayout$Builder;
      10: checkcast     #52                 // class org/apache/logging/log4j/core/layout/GelfLayout$Builder
      13: areturn

  public java.util.Map<java.lang.String, java.lang.String> getContentFormat();
    Code:
       0: invokestatic  #55                 // Method java/util/Collections.emptyMap:()Ljava/util/Map;
       3: areturn

  public java.lang.String getContentType();
    Code:
       0: new           #30                 // class java/lang/StringBuilder
       3: dup
       4: invokespecial #31                 // Method java/lang/StringBuilder."<init>":()V
       7: ldc           #57                 // String application/json; charset=
       9: invokevirtual #33                 // Method java/lang/StringBuilder.append:(Ljava/lang/String;)Ljava/lang/StringBuilder;
      12: aload_0
      13: invokevirtual #58                 // Method getCharset:()Ljava/nio/charset/Charset;
      16: invokevirtual #59                 // Method java/lang/StringBuilder.append:(Ljava/lang/Object;)Ljava/lang/StringBuilder;
      19: invokevirtual #50                 // Method java/lang/StringBuilder.toString:()Ljava/lang/String;
      22: areturn

  public byte[] toByteArray(org.apache.logging.log4j.core.LogEvent);
    Code:
       0: aload_0
       1: aload_1
       2: invokestatic  #60                 // Method getStringBuilder:()Ljava/lang/StringBuilder;
       5: iconst_0
       6: invokespecial #61                 // Method toText:(Lorg/apache/logging/log4j/core/LogEvent;Ljava/lang/StringBuilder;Z)Ljava/lang/StringBuilder;
       9: astore_2
      10: aload_0
      11: aload_2
      12: invokevirtual #50                 // Method java/lang/StringBuilder.toString:()Ljava/lang/String;
      15: invokevirtual #62                 // Method getBytes:(Ljava/lang/String;)[B
      18: astore_3
      19: aload_0
      20: getfield      #16                 // Field compressionType:Lorg/apache/logging/log4j/core/layout/GelfLayout$CompressionType;
      23: getstatic     #23                 // Field org/apache/logging/log4j/core/layout/GelfLayout$CompressionType.OFF:Lorg/apache/logging/log4j/core/layout/GelfLayout$CompressionType;
      26: if_acmpeq     46
      29: aload_3
      30: arraylength
      31: aload_0
      32: getfield      #17                 // Field compressionThreshold:I
      35: if_icmple     46
      38: aload_0
      39: aload_3
      40: invokespecial #63                 // Method compress:([B)[B
      43: goto          47
      46: aload_3
      47: areturn

  public void encode(org.apache.logging.log4j.core.LogEvent, org.apache.logging.log4j.core.layout.ByteBufferDestination);
    Code:
       0: aload_0
       1: getfield      #16                 // Field compressionType:Lorg/apache/logging/log4j/core/layout/GelfLayout$CompressionType;
       4: getstatic     #23                 // Field org/apache/logging/log4j/core/layout/GelfLayout$CompressionType.OFF:Lorg/apache/logging/log4j/core/layout/GelfLayout$CompressionType;
       7: if_acmpeq     17
      10: aload_0
      11: aload_1
      12: aload_2
      13: invokespecial #64                 // Method org/apache/logging/log4j/core/layout/AbstractStringLayout.encode:(Lorg/apache/logging/log4j/core/LogEvent;Lorg/apache/logging/log4j/core/layout/ByteBufferDestination;)V
      16: return
      17: aload_0
      18: aload_1
      19: invokestatic  #60                 // Method getStringBuilder:()Ljava/lang/StringBuilder;
      22: iconst_1
      23: invokespecial #61                 // Method toText:(Lorg/apache/logging/log4j/core/LogEvent;Ljava/lang/StringBuilder;Z)Ljava/lang/StringBuilder;
      26: astore_3
      27: aload_0
      28: invokevirtual #65                 // Method getStringBuilderEncoder:()Lorg/apache/logging/log4j/core/layout/Encoder;
      31: astore        4
      33: aload         4
      35: aload_3
      36: aload_2
      37: invokeinterface #66,  3           // InterfaceMethod org/apache/logging/log4j/core/layout/Encoder.encode:(Ljava/lang/Object;Lorg/apache/logging/log4j/core/layout/ByteBufferDestination;)V
      42: return

  public boolean requiresLocation();
    Code:
       0: aload_0
       1: getfield      #29                 // Field layout:Lorg/apache/logging/log4j/core/layout/PatternLayout;
       4: invokestatic  #67                 // Method java/util/Objects.nonNull:(Ljava/lang/Object;)Z
       7: ifeq          24
      10: aload_0
      11: getfield      #29                 // Field layout:Lorg/apache/logging/log4j/core/layout/PatternLayout;
      14: invokevirtual #68                 // Method org/apache/logging/log4j/core/layout/PatternLayout.requiresLocation:()Z
      17: ifeq          24
      20: iconst_1
      21: goto          25
      24: iconst_0
      25: ireturn

  private byte[] compress(byte[]);
    Code:
       0: new           #69                 // class java/io/ByteArrayOutputStream
       3: dup
       4: aload_0
       5: getfield      #17                 // Field compressionThreshold:I
       8: bipush        8
      10: idiv
      11: invokespecial #70                 // Method java/io/ByteArrayOutputStream."<init>":(I)V
      14: astore_2
      15: aload_0
      16: getfield      #16                 // Field compressionType:Lorg/apache/logging/log4j/core/layout/GelfLayout$CompressionType;
      19: aload_2
      20: invokevirtual #71                 // Method org/apache/logging/log4j/core/layout/GelfLayout$CompressionType.createDeflaterOutputStream:(Ljava/io/OutputStream;)Ljava/util/zip/DeflaterOutputStream;
      23: astore_3
      24: aconst_null
      25: astore        4
      27: aload_3
      28: ifnonnull     69
      31: aload_1
      32: astore        5
      34: aload_3
      35: ifnull        66
      38: aload         4
      40: ifnull        62
      43: aload_3
      44: invokevirtual #72                 // Method java/util/zip/DeflaterOutputStream.close:()V
      47: goto          66
      50: astore        6
      52: aload         4
      54: aload         6
      56: invokevirtual #74                 // Method java/lang/Throwable.addSuppressed:(Ljava/lang/Throwable;)V
      59: goto          66
      62: aload_3
      63: invokevirtual #72                 // Method java/util/zip/DeflaterOutputStream.close:()V
      66: aload         5
      68: areturn
      69: aload_3
      70: aload_1
      71: invokevirtual #75                 // Method java/util/zip/DeflaterOutputStream.write:([B)V
      74: aload_3
      75: invokevirtual #76                 // Method java/util/zip/DeflaterOutputStream.finish:()V
      78: aload_3
      79: ifnull        159
      82: aload         4
      84: ifnull        106
      87: aload_3
      88: invokevirtual #72                 // Method java/util/zip/DeflaterOutputStream.close:()V
      91: goto          159
      94: astore        5
      96: aload         4
      98: aload         5
     100: invokevirtual #74                 // Method java/lang/Throwable.addSuppressed:(Ljava/lang/Throwable;)V
     103: goto          159
     106: aload_3
     107: invokevirtual #72                 // Method java/util/zip/DeflaterOutputStream.close:()V
     110: goto          159
     113: astore        5
     115: aload         5
     117: astore        4
     119: aload         5
     121: athrow
     122: astore        7
     124: aload_3
     125: ifnull        156
     128: aload         4
     130: ifnull        152
     133: aload_3
     134: invokevirtual #72                 // Method java/util/zip/DeflaterOutputStream.close:()V
     137: goto          156
     140: astore        8
     142: aload         4
     144: aload         8
     146: invokevirtual #74                 // Method java/lang/Throwable.addSuppressed:(Ljava/lang/Throwable;)V
     149: goto          156
     152: aload_3
     153: invokevirtual #72                 // Method java/util/zip/DeflaterOutputStream.close:()V
     156: aload         7
     158: athrow
     159: aload_2
     160: invokevirtual #77                 // Method java/io/ByteArrayOutputStream.toByteArray:()[B
     163: areturn
     164: astore_2
     165: invokestatic  #79                 // Method org/apache/logging/log4j/status/StatusLogger.getLogger:()Lorg/apache/logging/log4j/status/StatusLogger;
     168: aload_2
     169: invokevirtual #80                 // Method org/apache/logging/log4j/status/StatusLogger.error:(Ljava/lang/Object;)V
     172: aload_1
     173: areturn
    Exception table:
       from    to  target type
          43    47    50   Class java/lang/Throwable
          87    91    94   Class java/lang/Throwable
          27    34   113   Class java/lang/Throwable
          69    78   113   Class java/lang/Throwable
          27    34   122   any
          69    78   122   any
         133   137   140   Class java/lang/Throwable
         113   124   122   any
           0    66   164   Class java/io/IOException
          69   163   164   Class java/io/IOException

  public java.lang.String toSerializable(org.apache.logging.log4j.core.LogEvent);
    Code:
       0: aload_0
       1: aload_1
       2: invokestatic  #60                 // Method getStringBuilder:()Ljava/lang/StringBuilder;
       5: iconst_0
       6: invokespecial #61                 // Method toText:(Lorg/apache/logging/log4j/core/LogEvent;Ljava/lang/StringBuilder;Z)Ljava/lang/StringBuilder;
       9: astore_2
      10: aload_2
      11: invokevirtual #50                 // Method java/lang/StringBuilder.toString:()Ljava/lang/String;
      14: areturn

  private java.lang.StringBuilder toText(org.apache.logging.log4j.core.LogEvent, java.lang.StringBuilder, boolean);
    Code:
       0: aload_2
       1: bipush        123
       3: invokevirtual #81                 // Method java/lang/StringBuilder.append:(C)Ljava/lang/StringBuilder;
       6: pop
       7: aload_2
       8: ldc           #82                 // String \"version\":\"1.1\",
      10: invokevirtual #33                 // Method java/lang/StringBuilder.append:(Ljava/lang/String;)Ljava/lang/StringBuilder;
      13: pop
      14: aload_2
      15: ldc           #83                 // String \"host\":\"
      17: invokevirtual #33                 // Method java/lang/StringBuilder.append:(Ljava/lang/String;)Ljava/lang/StringBuilder;
      20: pop
      21: aload_0
      22: getfield      #8                  // Field host:Ljava/lang/String;
      25: invokestatic  #1                  // Method toNullSafeString:(Ljava/lang/CharSequence;)Ljava/lang/CharSequence;
      28: aload_2
      29: invokestatic  #84                 // Method org/apache/logging/log4j/core/util/JsonUtils.quoteAsString:(Ljava/lang/CharSequence;Ljava/lang/StringBuilder;)V
      32: aload_2
      33: ldc           #85                 // String \",
      35: invokevirtual #33                 // Method java/lang/StringBuilder.append:(Ljava/lang/String;)Ljava/lang/StringBuilder;
      38: pop
      39: aload_2
      40: ldc           #86                 // String \"timestamp\":
      42: invokevirtual #33                 // Method java/lang/StringBuilder.append:(Ljava/lang/String;)Ljava/lang/StringBuilder;
      45: aload_1
      46: invokeinterface #87,  1           // InterfaceMethod org/apache/logging/log4j/core/LogEvent.getTimeMillis:()J
      51: invokestatic  #88                 // Method formatTimestamp:(J)Ljava/lang/CharSequence;
      54: invokevirtual #89                 // Method java/lang/StringBuilder.append:(Ljava/lang/CharSequence;)Ljava/lang/StringBuilder;
      57: bipush        44
      59: invokevirtual #81                 // Method java/lang/StringBuilder.append:(C)Ljava/lang/StringBuilder;
      62: pop
      63: aload_2
      64: ldc           #90                 // String \"level\":
      66: invokevirtual #33                 // Method java/lang/StringBuilder.append:(Ljava/lang/String;)Ljava/lang/StringBuilder;
      69: aload_0
      70: aload_1
      71: invokeinterface #91,  1           // InterfaceMethod org/apache/logging/log4j/core/LogEvent.getLevel:()Lorg/apache/logging/log4j/Level;
      76: invokespecial #92                 // Method formatLevel:(Lorg/apache/logging/log4j/Level;)I
      79: invokevirtual #37                 // Method java/lang/StringBuilder.append:(I)Ljava/lang/StringBuilder;
      82: bipush        44
      84: invokevirtual #81                 // Method java/lang/StringBuilder.append:(C)Ljava/lang/StringBuilder;
      87: pop
      88: aload_1
      89: invokeinterface #93,  1           // InterfaceMethod org/apache/logging/log4j/core/LogEvent.getThreadName:()Ljava/lang/String;
      94: ifnull        121
      97: aload_2
      98: ldc           #94                 // String \"_thread\":\"
     100: invokevirtual #33                 // Method java/lang/StringBuilder.append:(Ljava/lang/String;)Ljava/lang/StringBuilder;
     103: pop
     104: aload_1
     105: invokeinterface #93,  1           // InterfaceMethod org/apache/logging/log4j/core/LogEvent.getThreadName:()Ljava/lang/String;
     110: aload_2
     111: invokestatic  #84                 // Method org/apache/logging/log4j/core/util/JsonUtils.quoteAsString:(Ljava/lang/CharSequence;Ljava/lang/StringBuilder;)V
     114: aload_2
     115: ldc           #85                 // String \",
     117: invokevirtual #33                 // Method java/lang/StringBuilder.append:(Ljava/lang/String;)Ljava/lang/StringBuilder;
     120: pop
     121: aload_1
     122: invokeinterface #95,  1           // InterfaceMethod org/apache/logging/log4j/core/LogEvent.getLoggerName:()Ljava/lang/String;
     127: ifnull        154
     130: aload_2
     131: ldc           #96                 // String \"_logger\":\"
     133: invokevirtual #33                 // Method java/lang/StringBuilder.append:(Ljava/lang/String;)Ljava/lang/StringBuilder;
     136: pop
     137: aload_1
     138: invokeinterface #95,  1           // InterfaceMethod org/apache/logging/log4j/core/LogEvent.getLoggerName:()Ljava/lang/String;
     143: aload_2
     144: invokestatic  #84                 // Method org/apache/logging/log4j/core/util/JsonUtils.quoteAsString:(Ljava/lang/CharSequence;Ljava/lang/StringBuilder;)V
     147: aload_2
     148: ldc           #85                 // String \",
     150: invokevirtual #33                 // Method java/lang/StringBuilder.append:(Ljava/lang/String;)Ljava/lang/StringBuilder;
     153: pop
     154: aload_0
     155: getfield      #10                 // Field additionalFields:[Lorg/apache/logging/log4j/core/util/KeyValuePair;
     158: arraylength
     159: ifle          293
     162: aload_0
     163: invokevirtual #97                 // Method getConfiguration:()Lorg/apache/logging/log4j/core/config/Configuration;
     166: invokeinterface #98,  1           // InterfaceMethod org/apache/logging/log4j/core/config/Configuration.getStrSubstitutor:()Lorg/apache/logging/log4j/core/lookup/StrSubstitutor;
     171: astore        4
     173: aload_0
     174: getfield      #10                 // Field additionalFields:[Lorg/apache/logging/log4j/core/util/KeyValuePair;
     177: astore        5
     179: aload         5
     181: arraylength
     182: istore        6
     184: iconst_0
     185: istore        7
     187: iload         7
     189: iload         6
     191: if_icmpge     293
     194: aload         5
     196: iload         7
     198: aaload
     199: astore        8
     201: aload         8
     203: invokevirtual #11                 // Method org/apache/logging/log4j/core/util/KeyValuePair.getValue:()Ljava/lang/String;
     206: invokestatic  #12                 // Method valueNeedsLookup:(Ljava/lang/String;)Z
     209: ifeq          226
     212: aload         4
     214: aload_1
     215: aload         8
     217: invokevirtual #11                 // Method org/apache/logging/log4j/core/util/KeyValuePair.getValue:()Ljava/lang/String;
     220: invokevirtual #99                 // Method org/apache/logging/log4j/core/lookup/StrSubstitutor.replace:(Lorg/apache/logging/log4j/core/LogEvent;Ljava/lang/String;)Ljava/lang/String;
     223: goto          231
     226: aload         8
     228: invokevirtual #11                 // Method org/apache/logging/log4j/core/util/KeyValuePair.getValue:()Ljava/lang/String;
     231: astore        9
     233: aload         9
     235: invokestatic  #100                // Method org/apache/logging/log4j/util/Strings.isNotEmpty:(Ljava/lang/CharSequence;)Z
     238: ifne          248
     241: aload_0
     242: getfield      #2                  // Field omitEmptyFields:Z
     245: ifne          287
     248: aload_2
     249: ldc           #101                // String \"_
     251: invokevirtual #33                 // Method java/lang/StringBuilder.append:(Ljava/lang/String;)Ljava/lang/StringBuilder;
     254: pop
     255: aload         8
     257: invokevirtual #102                // Method org/apache/logging/log4j/core/util/KeyValuePair.getKey:()Ljava/lang/String;
     260: aload_2
     261: invokestatic  #84                 // Method org/apache/logging/log4j/core/util/JsonUtils.quoteAsString:(Ljava/lang/CharSequence;Ljava/lang/StringBuilder;)V
     264: aload_2
     265: ldc           #103                // String \":\"
     267: invokevirtual #33                 // Method java/lang/StringBuilder.append:(Ljava/lang/String;)Ljava/lang/StringBuilder;
     270: pop
     271: aload         9
     273: invokestatic  #1                  // Method toNullSafeString:(Ljava/lang/CharSequence;)Ljava/lang/CharSequence;
     276: aload_2
     277: invokestatic  #84                 // Method org/apache/logging/log4j/core/util/JsonUtils.quoteAsString:(Ljava/lang/CharSequence;Ljava/lang/StringBuilder;)V
     280: aload_2
     281: ldc           #85                 // String \",
     283: invokevirtual #33                 // Method java/lang/StringBuilder.append:(Ljava/lang/String;)Ljava/lang/StringBuilder;
     286: pop
     287: iinc          7, 1
     290: goto          187
     293: aload_0
     294: getfield      #19                 // Field includeThreadContext:Z
     297: ifeq          316
     300: aload_1
     301: invokeinterface #104,  1          // InterfaceMethod org/apache/logging/log4j/core/LogEvent.getContextData:()Lorg/apache/logging/log4j/util/ReadOnlyStringMap;
     306: aload_0
     307: getfield      #27                 // Field mdcWriter:Lorg/apache/logging/log4j/core/layout/GelfLayout$FieldWriter;
     310: aload_2
     311: invokeinterface #105,  3          // InterfaceMethod org/apache/logging/log4j/util/ReadOnlyStringMap.forEach:(Lorg/apache/logging/log4j/util/TriConsumer;Ljava/lang/Object;)V
     316: aload_0
     317: getfield      #20                 // Field includeMapMessage:Z
     320: ifeq          354
     323: aload_1
     324: invokeinterface #106,  1          // InterfaceMethod org/apache/logging/log4j/core/LogEvent.getMessage:()Lorg/apache/logging/log4j/message/Message;
     329: instanceof    #107                // class org/apache/logging/log4j/message/MapMessage
     332: ifeq          354
     335: aload_1
     336: invokeinterface #106,  1          // InterfaceMethod org/apache/logging/log4j/core/LogEvent.getMessage:()Lorg/apache/logging/log4j/message/Message;
     341: checkcast     #107                // class org/apache/logging/log4j/message/MapMessage
     344: aload_0
     345: aload_2
     346: invokedynamic #108,  0            // InvokeDynamic #0:accept:(Lorg/apache/logging/log4j/core/layout/GelfLayout;Ljava/lang/StringBuilder;)Lorg/apache/logging/log4j/util/BiConsumer;
     351: invokevirtual #109                // Method org/apache/logging/log4j/message/MapMessage.forEach:(Lorg/apache/logging/log4j/util/BiConsumer;)V
     354: aload_1
     355: invokeinterface #110,  1          // InterfaceMethod org/apache/logging/log4j/core/LogEvent.getThrown:()Ljava/lang/Throwable;
     360: ifnonnull     370
     363: aload_0
     364: getfield      #29                 // Field layout:Lorg/apache/logging/log4j/core/layout/PatternLayout;
     367: ifnull        451
     370: aload_2
     371: ldc           #111                // String \"full_message\":\"
     373: invokevirtual #33                 // Method java/lang/StringBuilder.append:(Ljava/lang/String;)Ljava/lang/StringBuilder;
     376: pop
     377: aload_0
     378: getfield      #29                 // Field layout:Lorg/apache/logging/log4j/core/layout/PatternLayout;
     381: ifnull        408
     384: invokestatic  #112                // Method getMessageStringBuilder:()Ljava/lang/StringBuilder;
     387: astore        4
     389: aload_0
     390: getfield      #29                 // Field layout:Lorg/apache/logging/log4j/core/layout/PatternLayout;
     393: aload_1
     394: aload         4
     396: invokevirtual #113                // Method org/apache/logging/log4j/core/layout/PatternLayout.serialize:(Lorg/apache/logging/log4j/core/LogEvent;Ljava/lang/StringBuilder;)V
     399: aload         4
     401: aload_2
     402: invokestatic  #84                 // Method org/apache/logging/log4j/core/util/JsonUtils.quoteAsString:(Ljava/lang/CharSequence;Ljava/lang/StringBuilder;)V
     405: goto          444
     408: aload_0
     409: getfield      #18                 // Field includeStacktrace:Z
     412: ifeq          431
     415: aload_1
     416: invokeinterface #110,  1          // InterfaceMethod org/apache/logging/log4j/core/LogEvent.getThrown:()Ljava/lang/Throwable;
     421: invokestatic  #114                // Method formatThrowable:(Ljava/lang/Throwable;)Ljava/lang/CharSequence;
     424: aload_2
     425: invokestatic  #84                 // Method org/apache/logging/log4j/core/util/JsonUtils.quoteAsString:(Ljava/lang/CharSequence;Ljava/lang/StringBuilder;)V
     428: goto          444
     431: aload_1
     432: invokeinterface #110,  1          // InterfaceMethod org/apache/logging/log4j/core/LogEvent.getThrown:()Ljava/lang/Throwable;
     437: invokevirtual #115                // Method java/lang/Throwable.toString:()Ljava/lang/String;
     440: aload_2
     441: invokestatic  #84                 // Method org/apache/logging/log4j/core/util/JsonUtils.quoteAsString:(Ljava/lang/CharSequence;Ljava/lang/StringBuilder;)V
     444: aload_2
     445: ldc           #85                 // String \",
     447: invokevirtual #33                 // Method java/lang/StringBuilder.append:(Ljava/lang/String;)Ljava/lang/StringBuilder;
     450: pop
     451: aload_2
     452: ldc           #116                // String \"short_message\":\"
     454: invokevirtual #33                 // Method java/lang/StringBuilder.append:(Ljava/lang/String;)Ljava/lang/StringBuilder;
     457: pop
     458: aload_1
     459: invokeinterface #106,  1          // InterfaceMethod org/apache/logging/log4j/core/LogEvent.getMessage:()Lorg/apache/logging/log4j/message/Message;
     464: astore        4
     466: aload         4
     468: instanceof    #117                // class java/lang/CharSequence
     471: ifeq          486
     474: aload         4
     476: checkcast     #117                // class java/lang/CharSequence
     479: aload_2
     480: invokestatic  #84                 // Method org/apache/logging/log4j/core/util/JsonUtils.quoteAsString:(Ljava/lang/CharSequence;Ljava/lang/StringBuilder;)V
     483: goto          556
     486: iload_3
     487: ifeq          542
     490: aload         4
     492: instanceof    #118                // class org/apache/logging/log4j/util/StringBuilderFormattable
     495: ifeq          542
     498: invokestatic  #112                // Method getMessageStringBuilder:()Ljava/lang/StringBuilder;
     501: astore        5
     503: aload         4
     505: checkcast     #118                // class org/apache/logging/log4j/util/StringBuilderFormattable
     508: aload         5
     510: invokeinterface #119,  2          // InterfaceMethod org/apache/logging/log4j/util/StringBuilderFormattable.formatTo:(Ljava/lang/StringBuilder;)V
     515: aload         5
     517: aload_2
     518: invokestatic  #84                 // Method org/apache/logging/log4j/core/util/JsonUtils.quoteAsString:(Ljava/lang/CharSequence;Ljava/lang/StringBuilder;)V
     521: aload         5
     523: invokestatic  #120                // Method trimToMaxSize:(Ljava/lang/StringBuilder;)V
     526: goto          539
     529: astore        10
     531: aload         5
     533: invokestatic  #120                // Method trimToMaxSize:(Ljava/lang/StringBuilder;)V
     536: aload         10
     538: athrow
     539: goto          556
     542: aload         4
     544: invokeinterface #121,  1          // InterfaceMethod org/apache/logging/log4j/message/Message.getFormattedMessage:()Ljava/lang/String;
     549: invokestatic  #1                  // Method toNullSafeString:(Ljava/lang/CharSequence;)Ljava/lang/CharSequence;
     552: aload_2
     553: invokestatic  #84                 // Method org/apache/logging/log4j/core/util/JsonUtils.quoteAsString:(Ljava/lang/CharSequence;Ljava/lang/StringBuilder;)V
     556: aload_2
     557: bipush        34
     559: invokevirtual #81                 // Method java/lang/StringBuilder.append:(C)Ljava/lang/StringBuilder;
     562: pop
     563: aload_2
     564: bipush        125
     566: invokevirtual #81                 // Method java/lang/StringBuilder.append:(C)Ljava/lang/StringBuilder;
     569: pop
     570: aload_0
     571: getfield      #21                 // Field includeNullDelimiter:Z
     574: ifeq          583
     577: aload_2
     578: iconst_0
     579: invokevirtual #81                 // Method java/lang/StringBuilder.append:(C)Ljava/lang/StringBuilder;
     582: pop
     583: aload_0
     584: getfield      #22                 // Field includeNewLineDelimiter:Z
     587: ifeq          597
     590: aload_2
     591: bipush        10
     593: invokevirtual #81                 // Method java/lang/StringBuilder.append:(C)Ljava/lang/StringBuilder;
     596: pop
     597: aload_2
     598: areturn
    Exception table:
       from    to  target type
         503   521   529   any
         529   531   529   any

  private static boolean valueNeedsLookup(java.lang.String);
    Code:
       0: aload_0
       1: ifnull        17
       4: aload_0
       5: ldc           #122                // String ${
       7: invokevirtual #123                // Method java/lang/String.contains:(Ljava/lang/CharSequence;)Z
      10: ifeq          17
      13: iconst_1
      14: goto          18
      17: iconst_0
      18: ireturn

  private static java.lang.StringBuilder getMessageStringBuilder();
    Code:
       0: getstatic     #124                // Field messageStringBuilder:Ljava/lang/ThreadLocal;
       3: invokevirtual #125                // Method java/lang/ThreadLocal.get:()Ljava/lang/Object;
       6: checkcast     #30                 // class java/lang/StringBuilder
       9: astore_0
      10: aload_0
      11: ifnonnull     32
      14: new           #30                 // class java/lang/StringBuilder
      17: dup
      18: sipush        1024
      21: invokespecial #127                // Method java/lang/StringBuilder."<init>":(I)V
      24: astore_0
      25: getstatic     #124                // Field messageStringBuilder:Ljava/lang/ThreadLocal;
      28: aload_0
      29: invokevirtual #128                // Method java/lang/ThreadLocal.set:(Ljava/lang/Object;)V
      32: aload_0
      33: iconst_0
      34: invokevirtual #129                // Method java/lang/StringBuilder.setLength:(I)V
      37: aload_0
      38: areturn

  private static java.lang.CharSequence toNullSafeString(java.lang.CharSequence);
    Code:
       0: aload_0
       1: ifnonnull     9
       4: ldc           #4                  // String
       6: goto          10
       9: aload_0
      10: areturn

  static java.lang.CharSequence formatTimestamp(long);
    Code:
       0: lload_0
       1: ldc2_w        #131                // long 1000l
       4: lcmp
       5: ifge          11
       8: ldc           #133                // String 0
      10: areturn
      11: invokestatic  #134                // Method getTimestampStringBuilder:()Ljava/lang/StringBuilder;
      14: astore_2
      15: aload_2
      16: lload_0
      17: invokevirtual #135                // Method java/lang/StringBuilder.append:(J)Ljava/lang/StringBuilder;
      20: pop
      21: aload_2
      22: aload_2
      23: invokevirtual #136                // Method java/lang/StringBuilder.length:()I
      26: iconst_3
      27: isub
      28: bipush        46
      30: invokevirtual #137                // Method java/lang/StringBuilder.insert:(IC)Ljava/lang/StringBuilder;
      33: pop
      34: aload_2
      35: areturn

  private static java.lang.StringBuilder getTimestampStringBuilder();
    Code:
       0: getstatic     #138                // Field timestampStringBuilder:Ljava/lang/ThreadLocal;
       3: invokevirtual #125                // Method java/lang/ThreadLocal.get:()Ljava/lang/Object;
       6: checkcast     #30                 // class java/lang/StringBuilder
       9: astore_0
      10: aload_0
      11: ifnonnull     31
      14: new           #30                 // class java/lang/StringBuilder
      17: dup
      18: bipush        20
      20: invokespecial #127                // Method java/lang/StringBuilder."<init>":(I)V
      23: astore_0
      24: getstatic     #138                // Field timestampStringBuilder:Ljava/lang/ThreadLocal;
      27: aload_0
      28: invokevirtual #128                // Method java/lang/ThreadLocal.set:(Ljava/lang/Object;)V
      31: aload_0
      32: iconst_0
      33: invokevirtual #129                // Method java/lang/StringBuilder.setLength:(I)V
      36: aload_0
      37: areturn

  private int formatLevel(org.apache.logging.log4j.Level);
    Code:
       0: aload_1
       1: invokestatic  #139                // Method org/apache/logging/log4j/core/net/Severity.getSeverity:(Lorg/apache/logging/log4j/Level;)Lorg/apache/logging/log4j/core/net/Severity;
       4: invokevirtual #140                // Method org/apache/logging/log4j/core/net/Severity.getCode:()I
       7: ireturn

  static java.lang.CharSequence formatThrowable(java.lang.Throwable);
    Code:
       0: new           #141                // class java/io/StringWriter
       3: dup
       4: sipush        2048
       7: invokespecial #142                // Method java/io/StringWriter."<init>":(I)V
      10: astore_1
      11: new           #143                // class java/io/PrintWriter
      14: dup
      15: aload_1
      16: invokespecial #144                // Method java/io/PrintWriter."<init>":(Ljava/io/Writer;)V
      19: astore_2
      20: aload_0
      21: aload_2
      22: invokevirtual #145                // Method java/lang/Throwable.printStackTrace:(Ljava/io/PrintWriter;)V
      25: aload_2
      26: invokevirtual #146                // Method java/io/PrintWriter.flush:()V
      29: aload_1
      30: invokevirtual #147                // Method java/io/StringWriter.getBuffer:()Ljava/lang/StringBuffer;
      33: areturn

  public java.io.Serializable toSerializable(org.apache.logging.log4j.core.LogEvent);
    Code:
       0: aload_0
       1: aload_1
       2: invokevirtual #148                // Method toSerializable:(Lorg/apache/logging/log4j/core/LogEvent;)Ljava/lang/String;
       5: areturn

  public void encode(java.lang.Object, org.apache.logging.log4j.core.layout.ByteBufferDestination);
    Code:
       0: aload_0
       1: aload_1
       2: checkcast     #149                // class org/apache/logging/log4j/core/LogEvent
       5: aload_2
       6: invokevirtual #150                // Method encode:(Lorg/apache/logging/log4j/core/LogEvent;Lorg/apache/logging/log4j/core/layout/ByteBufferDestination;)V
       9: return

  private void lambda$toText$0(java.lang.StringBuilder, java.lang.String, java.lang.Object);
    Code:
       0: aload_0
       1: getfield      #28                 // Field mapWriter:Lorg/apache/logging/log4j/core/layout/GelfLayout$FieldWriter;
       4: aload_2
       5: aload_3
       6: aload_1
       7: invokevirtual #151                // Method org/apache/logging/log4j/core/layout/GelfLayout$FieldWriter.accept:(Ljava/lang/String;Ljava/lang/Object;Ljava/lang/StringBuilder;)V
      10: return

  org.apache.logging.log4j.core.layout.GelfLayout(org.apache.logging.log4j.core.config.Configuration, java.lang.String, org.apache.logging.log4j.core.util.KeyValuePair[], org.apache.logging.log4j.core.layout.GelfLayout$CompressionType, int, boolean, boolean, boolean, boolean, boolean, boolean, org.apache.logging.log4j.core.layout.internal.ListChecker, org.apache.logging.log4j.core.layout.internal.ListChecker, org.apache.logging.log4j.core.layout.PatternLayout, java.lang.String, java.lang.String, org.apache.logging.log4j.core.layout.GelfLayout$1);
    Code:
       0: aload_0
       1: aload_1
       2: aload_2
       3: aload_3
       4: aload         4
       6: iload         5
       8: iload         6
      10: iload         7
      12: iload         8
      14: iload         9
      16: iload         10
      18: iload         11
      20: aload         12
      22: aload         13
      24: aload         14
      26: aload         15
      28: aload         16
      30: invokespecial #3                  // Method "<init>":(Lorg/apache/logging/log4j/core/config/Configuration;Ljava/lang/String;[Lorg/apache/logging/log4j/core/util/KeyValuePair;Lorg/apache/logging/log4j/core/layout/GelfLayout$CompressionType;IZZZZZZLorg/apache/logging/log4j/core/layout/internal/ListChecker;Lorg/apache/logging/log4j/core/layout/internal/ListChecker;Lorg/apache/logging/log4j/core/layout/PatternLayout;Ljava/lang/String;Ljava/lang/String;)V
      33: return

  static boolean access$200(org.apache.logging.log4j.core.layout.GelfLayout);
    Code:
       0: aload_0
       1: getfield      #2                  // Field omitEmptyFields:Z
       4: ireturn

  static java.lang.CharSequence access$300(java.lang.CharSequence);
    Code:
       0: aload_0
       1: invokestatic  #1                  // Method toNullSafeString:(Ljava/lang/CharSequence;)Ljava/lang/CharSequence;
       4: areturn

  static {};
    Code:
       0: new           #152                // class java/lang/ThreadLocal
       3: dup
       4: invokespecial #153                // Method java/lang/ThreadLocal."<init>":()V
       7: putstatic     #124                // Field messageStringBuilder:Ljava/lang/ThreadLocal;
      10: new           #152                // class java/lang/ThreadLocal
      13: dup
      14: invokespecial #153                // Method java/lang/ThreadLocal."<init>":()V
      17: putstatic     #138                // Field timestampStringBuilder:Ljava/lang/ThreadLocal;
      20: return
}
