Compiled from "OntDocumentManager.java"
public class org.apache.jena.ontology.OntDocumentManager {
  public static final java.lang.String DEFAULT_METADATA_PATH;

  public static final java.lang.String NS;

  public static final java.lang.String ANCHOR;

  public static final org.apache.jena.rdf.model.Resource ONTOLOGY_SPEC;

  public static final org.apache.jena.rdf.model.Property PUBLIC_URI;

  public static final org.apache.jena.rdf.model.Property ALT_URL;

  public static final org.apache.jena.rdf.model.Property PREFIX;

  public static final org.apache.jena.rdf.model.Property LANGUAGE;

  public static final org.apache.jena.rdf.model.Resource DOC_MGR_POLICY;

  public static final org.apache.jena.rdf.model.Property CACHE_MODELS;

  public static final org.apache.jena.rdf.model.Property PROCESS_IMPORTS;

  public static final org.apache.jena.rdf.model.Property IGNORE_IMPORT;

  public static final org.apache.jena.rdf.model.Property USE_DECLARED_NS_PREFIXES;

  private static org.apache.jena.ontology.OntDocumentManager s_instance;

  private static org.slf4j.Logger log;

  protected java.lang.String m_searchPath;

  protected org.apache.jena.util.FileManager m_fileMgr;

  protected boolean m_usingGlobalFileMgr;

  protected boolean m_processImports;

  protected java.util.Set<java.lang.String> m_ignoreImports;

  protected org.apache.jena.shared.PrefixMapping m_prefixMap;

  protected boolean m_useDeclaredPrefixes;

  protected java.lang.String m_policyURL;

  protected org.apache.jena.ontology.OntDocumentManager$ReadFailureHandler m_rfHandler;

  protected org.apache.jena.ontology.OntDocumentManager$ReadHook m_readHook;

  public org.apache.jena.ontology.OntDocumentManager();
    Code:
       0: aload_0
       1: ldc           #2                  // String file:ont-policy.rdf;file:etc/ont-policy.rdf;ont-policy.rdf
       3: invokespecial #3                  // Method "<init>":(Ljava/lang/String;)V
       6: return

  public org.apache.jena.ontology.OntDocumentManager(java.lang.String);
    Code:
       0: aload_0
       1: aconst_null
       2: aload_1
       3: invokespecial #4                  // Method "<init>":(Lorg/apache/jena/util/FileManager;Ljava/lang/String;)V
       6: return

  public org.apache.jena.ontology.OntDocumentManager(org.apache.jena.util.FileManager, java.lang.String);
    Code:
       0: aload_0
       1: invokespecial #5                  // Method java/lang/Object."<init>":()V
       4: aload_0
       5: ldc           #2                  // String file:ont-policy.rdf;file:etc/ont-policy.rdf;ont-policy.rdf
       7: putfield      #6                  // Field m_searchPath:Ljava/lang/String;
      10: aload_0
      11: iconst_0
      12: putfield      #7                  // Field m_usingGlobalFileMgr:Z
      15: aload_0
      16: iconst_1
      17: putfield      #8                  // Field m_processImports:Z
      20: aload_0
      21: new           #9                  // class java/util/HashSet
      24: dup
      25: invokespecial #10                 // Method java/util/HashSet."<init>":()V
      28: putfield      #11                 // Field m_ignoreImports:Ljava/util/Set;
      31: aload_0
      32: new           #12                 // class org/apache/jena/shared/impl/PrefixMappingImpl
      35: dup
      36: invokespecial #13                 // Method org/apache/jena/shared/impl/PrefixMappingImpl."<init>":()V
      39: putfield      #14                 // Field m_prefixMap:Lorg/apache/jena/shared/PrefixMapping;
      42: aload_0
      43: iconst_1
      44: putfield      #15                 // Field m_useDeclaredPrefixes:Z
      47: aload_0
      48: new           #16                 // class org/apache/jena/ontology/OntDocumentManager$DefaultReadHook
      51: dup
      52: invokespecial #17                 // Method org/apache/jena/ontology/OntDocumentManager$DefaultReadHook."<init>":()V
      55: putfield      #18                 // Field m_readHook:Lorg/apache/jena/ontology/OntDocumentManager$ReadHook;
      58: aload_0
      59: aload_1
      60: invokevirtual #19                 // Method setFileManager:(Lorg/apache/jena/util/FileManager;)V
      63: aload_0
      64: invokevirtual #20                 // Method setDefaults:()V
      67: aload_0
      68: aload_2
      69: ifnonnull     77
      72: ldc           #21                 // String
      74: goto          78
      77: aload_2
      78: putfield      #6                  // Field m_searchPath:Ljava/lang/String;
      81: aload_0
      82: aload_0
      83: getfield      #6                  // Field m_searchPath:Ljava/lang/String;
      86: invokevirtual #22                 // Method initialiseMetadata:(Ljava/lang/String;)V
      89: return

  public org.apache.jena.ontology.OntDocumentManager(org.apache.jena.rdf.model.Model);
    Code:
       0: aload_0
       1: aconst_null
       2: aload_1
       3: invokespecial #23                 // Method "<init>":(Lorg/apache/jena/util/FileManager;Lorg/apache/jena/rdf/model/Model;)V
       6: return

  public org.apache.jena.ontology.OntDocumentManager(org.apache.jena.util.FileManager, org.apache.jena.rdf.model.Model);
    Code:
       0: aload_0
       1: invokespecial #5                  // Method java/lang/Object."<init>":()V
       4: aload_0
       5: ldc           #2                  // String file:ont-policy.rdf;file:etc/ont-policy.rdf;ont-policy.rdf
       7: putfield      #6                  // Field m_searchPath:Ljava/lang/String;
      10: aload_0
      11: iconst_0
      12: putfield      #7                  // Field m_usingGlobalFileMgr:Z
      15: aload_0
      16: iconst_1
      17: putfield      #8                  // Field m_processImports:Z
      20: aload_0
      21: new           #9                  // class java/util/HashSet
      24: dup
      25: invokespecial #10                 // Method java/util/HashSet."<init>":()V
      28: putfield      #11                 // Field m_ignoreImports:Ljava/util/Set;
      31: aload_0
      32: new           #12                 // class org/apache/jena/shared/impl/PrefixMappingImpl
      35: dup
      36: invokespecial #13                 // Method org/apache/jena/shared/impl/PrefixMappingImpl."<init>":()V
      39: putfield      #14                 // Field m_prefixMap:Lorg/apache/jena/shared/PrefixMapping;
      42: aload_0
      43: iconst_1
      44: putfield      #15                 // Field m_useDeclaredPrefixes:Z
      47: aload_0
      48: new           #16                 // class org/apache/jena/ontology/OntDocumentManager$DefaultReadHook
      51: dup
      52: invokespecial #17                 // Method org/apache/jena/ontology/OntDocumentManager$DefaultReadHook."<init>":()V
      55: putfield      #18                 // Field m_readHook:Lorg/apache/jena/ontology/OntDocumentManager$ReadHook;
      58: aload_0
      59: aload_1
      60: invokevirtual #19                 // Method setFileManager:(Lorg/apache/jena/util/FileManager;)V
      63: aload_0
      64: invokevirtual #20                 // Method setDefaults:()V
      67: aload_0
      68: aload_2
      69: iconst_0
      70: invokevirtual #24                 // Method configure:(Lorg/apache/jena/rdf/model/Model;Z)V
      73: return

  public static org.apache.jena.ontology.OntDocumentManager getInstance();
    Code:
       0: getstatic     #25                 // Field s_instance:Lorg/apache/jena/ontology/OntDocumentManager;
       3: ifnonnull     16
       6: new           #1                  // class org/apache/jena/ontology/OntDocumentManager
       9: dup
      10: invokespecial #26                 // Method "<init>":()V
      13: putstatic     #25                 // Field s_instance:Lorg/apache/jena/ontology/OntDocumentManager;
      16: getstatic     #25                 // Field s_instance:Lorg/apache/jena/ontology/OntDocumentManager;
      19: areturn

  public org.apache.jena.util.FileManager getFileManager();
    Code:
       0: aload_0
       1: getfield      #27                 // Field m_fileMgr:Lorg/apache/jena/util/FileManager;
       4: areturn

  public org.apache.jena.ontology.OntDocumentManager$ReadHook setReadHook(org.apache.jena.ontology.OntDocumentManager$ReadHook);
    Code:
       0: aload_1
       1: ifnonnull     14
       4: new           #28                 // class java/lang/IllegalArgumentException
       7: dup
       8: ldc           #29                 // String ReadHook cannot be null
      10: invokespecial #30                 // Method java/lang/IllegalArgumentException."<init>":(Ljava/lang/String;)V
      13: athrow
      14: aload_0
      15: getfield      #18                 // Field m_readHook:Lorg/apache/jena/ontology/OntDocumentManager$ReadHook;
      18: astore_2
      19: aload_0
      20: aload_1
      21: putfield      #18                 // Field m_readHook:Lorg/apache/jena/ontology/OntDocumentManager$ReadHook;
      24: aload_2
      25: areturn

  public org.apache.jena.ontology.OntDocumentManager$ReadHook getReadHook();
    Code:
       0: aload_0
       1: getfield      #18                 // Field m_readHook:Lorg/apache/jena/ontology/OntDocumentManager$ReadHook;
       4: areturn

  public void setFileManager();
    Code:
       0: aload_0
       1: invokestatic  #31                 // Method org/apache/jena/util/FileManager.get:()Lorg/apache/jena/util/FileManager;
       4: invokevirtual #32                 // Method org/apache/jena/util/FileManager.clone:()Lorg/apache/jena/util/FileManager;
       7: invokevirtual #19                 // Method setFileManager:(Lorg/apache/jena/util/FileManager;)V
      10: aload_0
      11: iconst_1
      12: putfield      #7                  // Field m_usingGlobalFileMgr:Z
      15: return

  public void setFileManager(org.apache.jena.util.FileManager);
    Code:
       0: aload_1
       1: ifnonnull     11
       4: aload_0
       5: invokevirtual #33                 // Method setFileManager:()V
       8: goto          21
      11: aload_0
      12: aload_1
      13: putfield      #27                 // Field m_fileMgr:Lorg/apache/jena/util/FileManager;
      16: aload_0
      17: iconst_0
      18: putfield      #7                  // Field m_usingGlobalFileMgr:Z
      21: return

  public java.lang.String getMetadataSearchPath();
    Code:
       0: aload_0
       1: getfield      #6                  // Field m_searchPath:Ljava/lang/String;
       4: areturn

  public void setMetadataSearchPath(java.lang.String, boolean);
    Code:
       0: iload_2
       1: ifeq          8
       4: aload_0
       5: invokevirtual #34                 // Method reset:()V
       8: aload_0
       9: aload_1
      10: putfield      #6                  // Field m_searchPath:Ljava/lang/String;
      13: aload_0
      14: aconst_null
      15: putfield      #35                 // Field m_policyURL:Ljava/lang/String;
      18: aload_0
      19: aload_1
      20: invokevirtual #22                 // Method initialiseMetadata:(Ljava/lang/String;)V
      23: return

  public void setReadFailureHandler(org.apache.jena.ontology.OntDocumentManager$ReadFailureHandler);
    Code:
       0: aload_0
       1: aload_1
       2: putfield      #36                 // Field m_rfHandler:Lorg/apache/jena/ontology/OntDocumentManager$ReadFailureHandler;
       5: return

  public org.apache.jena.ontology.OntDocumentManager$ReadFailureHandler getReadFailureHandler();
    Code:
       0: aload_0
       1: getfield      #36                 // Field m_rfHandler:Lorg/apache/jena/ontology/OntDocumentManager$ReadFailureHandler;
       4: areturn

  public void configure(org.apache.jena.rdf.model.Model);
    Code:
       0: aload_0
       1: aload_1
       2: iconst_1
       3: invokevirtual #24                 // Method configure:(Lorg/apache/jena/rdf/model/Model;Z)V
       6: return

  public void configure(org.apache.jena.rdf.model.Model, boolean);
    Code:
       0: iload_2
       1: ifeq          9
       4: aload_0
       5: iconst_0
       6: invokevirtual #37                 // Method reset:(Z)V
       9: aload_0
      10: aload_1
      11: invokevirtual #38                 // Method processMetadata:(Lorg/apache/jena/rdf/model/Model;)V
      14: return

  public void reset(boolean);
    Code:
       0: aload_0
       1: getfield      #7                  // Field m_usingGlobalFileMgr:Z
       4: ifeq          14
       7: aload_0
       8: invokevirtual #33                 // Method setFileManager:()V
      11: goto          21
      14: aload_0
      15: invokevirtual #39                 // Method getFileManager:()Lorg/apache/jena/util/FileManager;
      18: invokevirtual #40                 // Method org/apache/jena/util/FileManager.resetCache:()V
      21: aload_0
      22: getfield      #11                 // Field m_ignoreImports:Ljava/util/Set;
      25: invokeinterface #41,  1           // InterfaceMethod java/util/Set.clear:()V
      30: aload_0
      31: new           #12                 // class org/apache/jena/shared/impl/PrefixMappingImpl
      34: dup
      35: invokespecial #13                 // Method org/apache/jena/shared/impl/PrefixMappingImpl."<init>":()V
      38: putfield      #14                 // Field m_prefixMap:Lorg/apache/jena/shared/PrefixMapping;
      41: aload_0
      42: invokevirtual #20                 // Method setDefaults:()V
      45: iload_1
      46: ifeq          57
      49: aload_0
      50: aload_0
      51: getfield      #6                  // Field m_searchPath:Ljava/lang/String;
      54: invokevirtual #22                 // Method initialiseMetadata:(Ljava/lang/String;)V
      57: return

  public void reset();
    Code:
       0: aload_0
       1: iconst_0
       2: invokevirtual #37                 // Method reset:(Z)V
       5: return

  public java.util.Iterator<java.lang.String> listDocuments();
    Code:
       0: aload_0
       1: invokevirtual #39                 // Method getFileManager:()Lorg/apache/jena/util/FileManager;
       4: invokevirtual #42                 // Method org/apache/jena/util/FileManager.getLocationMapper:()Lorg/apache/jena/util/LocationMapper;
       7: invokevirtual #43                 // Method org/apache/jena/util/LocationMapper.listAltEntries:()Ljava/util/Iterator;
      10: areturn

  public java.lang.String doAltURLMapping(java.lang.String);
    Code:
       0: aload_0
       1: invokevirtual #39                 // Method getFileManager:()Lorg/apache/jena/util/FileManager;
       4: aload_1
       5: invokevirtual #44                 // Method org/apache/jena/util/FileManager.mapURI:(Ljava/lang/String;)Ljava/lang/String;
       8: areturn

  public org.apache.jena.rdf.model.Model getModel(java.lang.String);
    Code:
       0: aload_0
       1: invokevirtual #39                 // Method getFileManager:()Lorg/apache/jena/util/FileManager;
       4: aload_1
       5: invokevirtual #45                 // Method org/apache/jena/util/FileManager.getFromCache:(Ljava/lang/String;)Lorg/apache/jena/rdf/model/Model;
       8: astore_2
       9: aload_2
      10: ifnull        32
      13: aload_2
      14: invokeinterface #46,  1           // InterfaceMethod org/apache/jena/rdf/model/Model.isClosed:()Z
      19: ifeq          32
      22: aload_0
      23: invokevirtual #39                 // Method getFileManager:()Lorg/apache/jena/util/FileManager;
      26: aload_1
      27: invokevirtual #47                 // Method org/apache/jena/util/FileManager.removeCacheModel:(Ljava/lang/String;)V
      30: aconst_null
      31: astore_2
      32: aload_2
      33: areturn

  public void addAltEntry(java.lang.String, java.lang.String);
    Code:
       0: aload_0
       1: invokevirtual #39                 // Method getFileManager:()Lorg/apache/jena/util/FileManager;
       4: invokevirtual #42                 // Method org/apache/jena/util/FileManager.getLocationMapper:()Lorg/apache/jena/util/LocationMapper;
       7: aload_1
       8: aload_2
       9: invokevirtual #48                 // Method org/apache/jena/util/LocationMapper.addAltEntry:(Ljava/lang/String;Ljava/lang/String;)V
      12: return

  public void addModel(java.lang.String, org.apache.jena.rdf.model.Model);
    Code:
       0: aload_0
       1: aload_1
       2: aload_2
       3: iconst_0
       4: invokevirtual #49                 // Method addModel:(Ljava/lang/String;Lorg/apache/jena/rdf/model/Model;Z)V
       7: return

  public void addModel(java.lang.String, org.apache.jena.rdf.model.Model, boolean);
    Code:
       0: aload_0
       1: invokevirtual #39                 // Method getFileManager:()Lorg/apache/jena/util/FileManager;
       4: invokevirtual #50                 // Method org/apache/jena/util/FileManager.isCachingModels:()Z
       7: ifeq          34
      10: iload_3
      11: ifne          25
      14: aload_0
      15: invokevirtual #39                 // Method getFileManager:()Lorg/apache/jena/util/FileManager;
      18: aload_1
      19: invokevirtual #51                 // Method org/apache/jena/util/FileManager.hasCachedModel:(Ljava/lang/String;)Z
      22: ifne          34
      25: aload_0
      26: invokevirtual #39                 // Method getFileManager:()Lorg/apache/jena/util/FileManager;
      29: aload_1
      30: aload_2
      31: invokevirtual #52                 // Method org/apache/jena/util/FileManager.addCacheModel:(Ljava/lang/String;Lorg/apache/jena/rdf/model/Model;)V
      34: return

  public void forget(java.lang.String);
    Code:
       0: aload_0
       1: invokevirtual #39                 // Method getFileManager:()Lorg/apache/jena/util/FileManager;
       4: invokevirtual #42                 // Method org/apache/jena/util/FileManager.getLocationMapper:()Lorg/apache/jena/util/LocationMapper;
       7: aload_1
       8: invokevirtual #53                 // Method org/apache/jena/util/LocationMapper.removeAltEntry:(Ljava/lang/String;)V
      11: aload_0
      12: invokevirtual #39                 // Method getFileManager:()Lorg/apache/jena/util/FileManager;
      15: aload_1
      16: invokevirtual #47                 // Method org/apache/jena/util/FileManager.removeCacheModel:(Ljava/lang/String;)V
      19: return

  public org.apache.jena.ontology.OntModel getOntology(java.lang.String, org.apache.jena.ontology.OntModelSpec);
    Code:
       0: aload_2
       1: astore_3
       2: aload_3
       3: invokevirtual #54                 // Method org/apache/jena/ontology/OntModelSpec.getDocumentManager:()Lorg/apache/jena/ontology/OntDocumentManager;
       6: aload_0
       7: if_acmpeq     24
      10: new           #55                 // class org/apache/jena/ontology/OntModelSpec
      13: dup
      14: aload_2
      15: invokespecial #56                 // Method org/apache/jena/ontology/OntModelSpec."<init>":(Lorg/apache/jena/ontology/OntModelSpec;)V
      18: astore_3
      19: aload_3
      20: aload_0
      21: invokevirtual #57                 // Method org/apache/jena/ontology/OntModelSpec.setDocumentManager:(Lorg/apache/jena/ontology/OntDocumentManager;)V
      24: aload_0
      25: invokevirtual #39                 // Method getFileManager:()Lorg/apache/jena/util/FileManager;
      28: aload_1
      29: invokevirtual #51                 // Method org/apache/jena/util/FileManager.hasCachedModel:(Ljava/lang/String;)Z
      32: ifeq          66
      35: aload_0
      36: invokevirtual #39                 // Method getFileManager:()Lorg/apache/jena/util/FileManager;
      39: aload_1
      40: invokevirtual #45                 // Method org/apache/jena/util/FileManager.getFromCache:(Ljava/lang/String;)Lorg/apache/jena/rdf/model/Model;
      43: astore        4
      45: aload         4
      47: instanceof    #58                 // class org/apache/jena/ontology/OntModel
      50: ifeq          59
      53: aload         4
      55: checkcast     #58                 // class org/apache/jena/ontology/OntModel
      58: areturn
      59: aload_3
      60: aload         4
      62: invokestatic  #59                 // Method org/apache/jena/rdf/model/ModelFactory.createOntologyModel:(Lorg/apache/jena/ontology/OntModelSpec;Lorg/apache/jena/rdf/model/Model;)Lorg/apache/jena/ontology/OntModel;
      65: areturn
      66: aload_3
      67: aconst_null
      68: invokestatic  #59                 // Method org/apache/jena/rdf/model/ModelFactory.createOntologyModel:(Lorg/apache/jena/ontology/OntModelSpec;Lorg/apache/jena/rdf/model/Model;)Lorg/apache/jena/ontology/OntModel;
      71: astore        4
      73: aload_0
      74: aload         4
      76: aload_1
      77: iconst_1
      78: invokevirtual #60                 // Method read:(Lorg/apache/jena/rdf/model/Model;Ljava/lang/String;Z)Z
      81: pop
      82: aload_0
      83: aload_1
      84: aload         4
      86: invokevirtual #61                 // Method addModel:(Ljava/lang/String;Lorg/apache/jena/rdf/model/Model;)V
      89: aload         4
      91: areturn

  public boolean getProcessImports();
    Code:
       0: aload_0
       1: getfield      #8                  // Field m_processImports:Z
       4: ireturn

  public boolean getCacheModels();
    Code:
       0: aload_0
       1: invokevirtual #39                 // Method getFileManager:()Lorg/apache/jena/util/FileManager;
       4: invokevirtual #50                 // Method org/apache/jena/util/FileManager.isCachingModels:()Z
       7: ireturn

  public void setProcessImports(boolean);
    Code:
       0: aload_0
       1: iload_1
       2: putfield      #8                  // Field m_processImports:Z
       5: return

  public void setCacheModels(boolean);
    Code:
       0: aload_0
       1: invokevirtual #39                 // Method getFileManager:()Lorg/apache/jena/util/FileManager;
       4: iload_1
       5: invokevirtual #62                 // Method org/apache/jena/util/FileManager.setModelCaching:(Z)V
       8: return

  public void addIgnoreImport(java.lang.String);
    Code:
       0: aload_0
       1: getfield      #11                 // Field m_ignoreImports:Ljava/util/Set;
       4: aload_1
       5: invokeinterface #63,  2           // InterfaceMethod java/util/Set.add:(Ljava/lang/Object;)Z
      10: pop
      11: return

  public void removeIgnoreImport(java.lang.String);
    Code:
       0: aload_0
       1: getfield      #11                 // Field m_ignoreImports:Ljava/util/Set;
       4: aload_1
       5: invokeinterface #64,  2           // InterfaceMethod java/util/Set.remove:(Ljava/lang/Object;)Z
      10: pop
      11: return

  public java.util.Iterator<java.lang.String> listIgnoredImports();
    Code:
       0: aload_0
       1: getfield      #11                 // Field m_ignoreImports:Ljava/util/Set;
       4: invokeinterface #65,  1           // InterfaceMethod java/util/Set.iterator:()Ljava/util/Iterator;
       9: areturn

  public boolean ignoringImport(java.lang.String);
    Code:
       0: aload_0
       1: getfield      #11                 // Field m_ignoreImports:Ljava/util/Set;
       4: aload_1
       5: invokeinterface #66,  2           // InterfaceMethod java/util/Set.contains:(Ljava/lang/Object;)Z
      10: ireturn

  public void clearCache();
    Code:
       0: aload_0
       1: invokevirtual #39                 // Method getFileManager:()Lorg/apache/jena/util/FileManager;
       4: invokevirtual #40                 // Method org/apache/jena/util/FileManager.resetCache:()V
       7: return

  public void loadImports(org.apache.jena.ontology.OntModel);
    Code:
       0: aload_0
       1: getfield      #8                  // Field m_processImports:Z
       4: ifeq          33
       7: new           #67                 // class java/util/ArrayList
      10: dup
      11: invokespecial #68                 // Method java/util/ArrayList."<init>":()V
      14: astore_2
      15: aload_0
      16: aload_1
      17: aload_2
      18: aload_1
      19: invokeinterface #69,  1           // InterfaceMethod org/apache/jena/ontology/OntModel.getProfile:()Lorg/apache/jena/ontology/Profile;
      24: invokevirtual #70                 // Method queueImports:(Lorg/apache/jena/rdf/model/Model;Ljava/util/List;Lorg/apache/jena/ontology/Profile;)V
      27: aload_0
      28: aload_1
      29: aload_2
      30: invokevirtual #71                 // Method loadImports:(Lorg/apache/jena/ontology/OntModel;Ljava/util/List;)V
      33: return

  public void loadImport(org.apache.jena.ontology.OntModel, java.lang.String);
    Code:
       0: aload_0
       1: getfield      #8                  // Field m_processImports:Z
       4: ifeq          29
       7: new           #67                 // class java/util/ArrayList
      10: dup
      11: invokespecial #68                 // Method java/util/ArrayList."<init>":()V
      14: astore_3
      15: aload_3
      16: aload_2
      17: invokeinterface #72,  2           // InterfaceMethod java/util/List.add:(Ljava/lang/Object;)Z
      22: pop
      23: aload_0
      24: aload_1
      25: aload_3
      26: invokevirtual #71                 // Method loadImports:(Lorg/apache/jena/ontology/OntModel;Ljava/util/List;)V
      29: return

  public void unloadImport(org.apache.jena.ontology.OntModel, java.lang.String);
    Code:
       0: aload_0
       1: getfield      #8                  // Field m_processImports:Z
       4: ifeq          29
       7: new           #67                 // class java/util/ArrayList
      10: dup
      11: invokespecial #68                 // Method java/util/ArrayList."<init>":()V
      14: astore_3
      15: aload_3
      16: aload_2
      17: invokeinterface #72,  2           // InterfaceMethod java/util/List.add:(Ljava/lang/Object;)Z
      22: pop
      23: aload_0
      24: aload_1
      25: aload_3
      26: invokevirtual #73                 // Method unloadImports:(Lorg/apache/jena/ontology/OntModel;Ljava/util/List;)V
      29: return

  public java.lang.String getLoadedPolicyURL();
    Code:
       0: aload_0
       1: getfield      #35                 // Field m_policyURL:Ljava/lang/String;
       4: areturn

  protected void loadImports(org.apache.jena.ontology.OntModel, java.util.List<java.lang.String>);
    Code:
       0: aload_2
       1: invokeinterface #74,  1           // InterfaceMethod java/util/List.isEmpty:()Z
       6: ifne          48
       9: aload_2
      10: iconst_0
      11: invokeinterface #75,  2           // InterfaceMethod java/util/List.remove:(I)Ljava/lang/Object;
      16: checkcast     #76                 // class java/lang/String
      19: astore_3
      20: aload_1
      21: aload_3
      22: invokeinterface #77,  2           // InterfaceMethod org/apache/jena/ontology/OntModel.hasLoadedImport:(Ljava/lang/String;)Z
      27: ifne          45
      30: aload_0
      31: aload_3
      32: invokevirtual #78                 // Method ignoringImport:(Ljava/lang/String;)Z
      35: ifne          45
      38: aload_0
      39: aload_1
      40: aload_3
      41: aload_2
      42: invokevirtual #79                 // Method loadImport:(Lorg/apache/jena/ontology/OntModel;Ljava/lang/String;Ljava/util/List;)V
      45: goto          0
      48: aload_1
      49: invokeinterface #80,  1           // InterfaceMethod org/apache/jena/ontology/OntModel.rebind:()V
      54: return

  protected void unloadImports(org.apache.jena.ontology.OntModel, java.util.List<java.lang.String>);
    Code:
       0: aload_2
       1: invokeinterface #74,  1           // InterfaceMethod java/util/List.isEmpty:()Z
       6: ifne          204
       9: aload_2
      10: iconst_0
      11: invokeinterface #75,  2           // InterfaceMethod java/util/List.remove:(I)Ljava/lang/Object;
      16: checkcast     #76                 // class java/lang/String
      19: astore_3
      20: aload_1
      21: aload_3
      22: invokeinterface #77,  2           // InterfaceMethod org/apache/jena/ontology/OntModel.hasLoadedImport:(Ljava/lang/String;)Z
      27: ifeq          201
      30: aload_0
      31: aload_3
      32: invokevirtual #81                 // Method getModel:(Ljava/lang/String;)Lorg/apache/jena/rdf/model/Model;
      35: astore        4
      37: aload         4
      39: ifnull        201
      42: new           #67                 // class java/util/ArrayList
      45: dup
      46: invokespecial #68                 // Method java/util/ArrayList."<init>":()V
      49: astore        5
      51: aload         4
      53: aconst_null
      54: aload_1
      55: invokeinterface #69,  1           // InterfaceMethod org/apache/jena/ontology/OntModel.getProfile:()Lorg/apache/jena/ontology/Profile;
      60: invokeinterface #82,  1           // InterfaceMethod org/apache/jena/ontology/Profile.IMPORTS:()Lorg/apache/jena/rdf/model/Property;
      65: aconst_null
      66: checkcast     #83                 // class org/apache/jena/rdf/model/RDFNode
      69: invokeinterface #84,  4           // InterfaceMethod org/apache/jena/rdf/model/Model.listStatements:(Lorg/apache/jena/rdf/model/Resource;Lorg/apache/jena/rdf/model/Property;Lorg/apache/jena/rdf/model/RDFNode;)Lorg/apache/jena/rdf/model/StmtIterator;
      74: astore        6
      76: aload         6
      78: invokeinterface #85,  1           // InterfaceMethod org/apache/jena/rdf/model/StmtIterator.hasNext:()Z
      83: ifeq          114
      86: aload         5
      88: aload         6
      90: invokeinterface #86,  1           // InterfaceMethod org/apache/jena/rdf/model/StmtIterator.nextStatement:()Lorg/apache/jena/rdf/model/Statement;
      95: invokeinterface #87,  1           // InterfaceMethod org/apache/jena/rdf/model/Statement.getResource:()Lorg/apache/jena/rdf/model/Resource;
     100: invokeinterface #88,  1           // InterfaceMethod org/apache/jena/rdf/model/Resource.getURI:()Ljava/lang/String;
     105: invokeinterface #72,  2           // InterfaceMethod java/util/List.add:(Ljava/lang/Object;)Z
     110: pop
     111: goto          76
     114: aload_1
     115: aload         4
     117: iconst_0
     118: invokeinterface #89,  3           // InterfaceMethod org/apache/jena/ontology/OntModel.removeSubModel:(Lorg/apache/jena/rdf/model/Model;Z)V
     123: aload_1
     124: aload_3
     125: invokeinterface #90,  2           // InterfaceMethod org/apache/jena/ontology/OntModel.removeLoadedImport:(Ljava/lang/String;)V
     130: aload_1
     131: aconst_null
     132: aload_1
     133: invokeinterface #69,  1           // InterfaceMethod org/apache/jena/ontology/OntModel.getProfile:()Lorg/apache/jena/ontology/Profile;
     138: invokeinterface #82,  1           // InterfaceMethod org/apache/jena/ontology/Profile.IMPORTS:()Lorg/apache/jena/rdf/model/Property;
     143: aconst_null
     144: checkcast     #83                 // class org/apache/jena/rdf/model/RDFNode
     147: invokeinterface #91,  4           // InterfaceMethod org/apache/jena/ontology/OntModel.listStatements:(Lorg/apache/jena/rdf/model/Resource;Lorg/apache/jena/rdf/model/Property;Lorg/apache/jena/rdf/model/RDFNode;)Lorg/apache/jena/rdf/model/StmtIterator;
     152: astore        6
     154: aload         6
     156: invokeinterface #85,  1           // InterfaceMethod org/apache/jena/rdf/model/StmtIterator.hasNext:()Z
     161: ifeq          192
     164: aload         5
     166: aload         6
     168: invokeinterface #86,  1           // InterfaceMethod org/apache/jena/rdf/model/StmtIterator.nextStatement:()Lorg/apache/jena/rdf/model/Statement;
     173: invokeinterface #87,  1           // InterfaceMethod org/apache/jena/rdf/model/Statement.getResource:()Lorg/apache/jena/rdf/model/Resource;
     178: invokeinterface #88,  1           // InterfaceMethod org/apache/jena/rdf/model/Resource.getURI:()Ljava/lang/String;
     183: invokeinterface #92,  2           // InterfaceMethod java/util/List.remove:(Ljava/lang/Object;)Z
     188: pop
     189: goto          154
     192: aload_2
     193: aload         5
     195: invokeinterface #93,  2           // InterfaceMethod java/util/List.addAll:(Ljava/util/Collection;)Z
     200: pop
     201: goto          0
     204: aload_1
     205: invokeinterface #80,  1           // InterfaceMethod org/apache/jena/ontology/OntModel.rebind:()V
     210: return

  protected void queueImports(org.apache.jena.rdf.model.Model, java.util.List<java.lang.String>, org.apache.jena.ontology.Profile);
    Code:
       0: aload_1
       1: instanceof    #58                 // class org/apache/jena/ontology/OntModel
       4: ifeq          26
       7: aload_2
       8: aload_1
       9: checkcast     #58                 // class org/apache/jena/ontology/OntModel
      12: invokeinterface #94,  1           // InterfaceMethod org/apache/jena/ontology/OntModel.listImportedOntologyURIs:()Ljava/util/Set;
      17: invokeinterface #93,  2           // InterfaceMethod java/util/List.addAll:(Ljava/util/Collection;)Z
      22: pop
      23: goto          82
      26: aload_1
      27: aconst_null
      28: aload_3
      29: invokeinterface #82,  1           // InterfaceMethod org/apache/jena/ontology/Profile.IMPORTS:()Lorg/apache/jena/rdf/model/Property;
      34: aconst_null
      35: checkcast     #83                 // class org/apache/jena/rdf/model/RDFNode
      38: invokeinterface #84,  4           // InterfaceMethod org/apache/jena/rdf/model/Model.listStatements:(Lorg/apache/jena/rdf/model/Resource;Lorg/apache/jena/rdf/model/Property;Lorg/apache/jena/rdf/model/RDFNode;)Lorg/apache/jena/rdf/model/StmtIterator;
      43: astore        4
      45: aload         4
      47: invokeinterface #85,  1           // InterfaceMethod org/apache/jena/rdf/model/StmtIterator.hasNext:()Z
      52: ifeq          82
      55: aload_2
      56: aload         4
      58: invokeinterface #86,  1           // InterfaceMethod org/apache/jena/rdf/model/StmtIterator.nextStatement:()Lorg/apache/jena/rdf/model/Statement;
      63: invokeinterface #87,  1           // InterfaceMethod org/apache/jena/rdf/model/Statement.getResource:()Lorg/apache/jena/rdf/model/Resource;
      68: invokeinterface #88,  1           // InterfaceMethod org/apache/jena/rdf/model/Resource.getURI:()Ljava/lang/String;
      73: invokeinterface #72,  2           // InterfaceMethod java/util/List.add:(Ljava/lang/Object;)Z
      78: pop
      79: goto          45
      82: return

  protected void initialiseMetadata(java.lang.String);
    Code:
       0: aload_0
       1: aload_1
       2: invokevirtual #95                 // Method findMetadata:(Ljava/lang/String;)Lorg/apache/jena/rdf/model/Model;
       5: astore_2
       6: aload_2
       7: ifnull        15
      10: aload_0
      11: aload_2
      12: invokevirtual #38                 // Method processMetadata:(Lorg/apache/jena/rdf/model/Model;)V
      15: return

  protected org.apache.jena.rdf.model.Model findMetadata(java.lang.String);
    Code:
       0: aload_1
       1: ifnonnull     6
       4: aconst_null
       5: areturn
       6: new           #96                 // class org/apache/jena/util/FileManager
       9: dup
      10: invokespecial #97                 // Method org/apache/jena/util/FileManager."<init>":()V
      13: astore_2
      14: aload_2
      15: invokevirtual #98                 // Method org/apache/jena/util/FileManager.addLocatorFile:()V
      18: aload_2
      19: invokevirtual #99                 // Method org/apache/jena/util/FileManager.addLocatorURL:()V
      22: aload_2
      23: aload_2
      24: invokevirtual #100                // Method java/lang/Object.getClass:()Ljava/lang/Class;
      27: invokevirtual #101                // Method java/lang/Class.getClassLoader:()Ljava/lang/ClassLoader;
      30: invokevirtual #102                // Method org/apache/jena/util/FileManager.addLocatorClassLoader:(Ljava/lang/ClassLoader;)V
      33: aconst_null
      34: astore_3
      35: aconst_null
      36: astore        4
      38: new           #103                // class java/util/StringTokenizer
      41: dup
      42: aload_1
      43: ldc           #104                // String ;
      45: invokespecial #105                // Method java/util/StringTokenizer."<init>":(Ljava/lang/String;Ljava/lang/String;)V
      48: astore        5
      50: aload         4
      52: ifnonnull     79
      55: aload         5
      57: invokevirtual #106                // Method java/util/StringTokenizer.hasMoreTokens:()Z
      60: ifeq          79
      63: aload         5
      65: invokevirtual #107                // Method java/util/StringTokenizer.nextToken:()Ljava/lang/String;
      68: astore_3
      69: aload_2
      70: aload_3
      71: invokevirtual #108                // Method org/apache/jena/util/FileManager.openNoMap:(Ljava/lang/String;)Ljava/io/InputStream;
      74: astore        4
      76: goto          50
      79: aload         4
      81: ifnull        116
      84: aload_3
      85: invokestatic  #109                // Method org/apache/jena/util/FileUtils.guessLang:(Ljava/lang/String;)Ljava/lang/String;
      88: astore        6
      90: invokestatic  #110                // Method org/apache/jena/rdf/model/ModelFactory.createDefaultModel:()Lorg/apache/jena/rdf/model/Model;
      93: astore        7
      95: aload         7
      97: aload         4
      99: aload_3
     100: aload         6
     102: invokeinterface #111,  4          // InterfaceMethod org/apache/jena/rdf/model/Model.read:(Ljava/io/InputStream;Ljava/lang/String;Ljava/lang/String;)Lorg/apache/jena/rdf/model/Model;
     107: pop
     108: aload_0
     109: aload_3
     110: putfield      #35                 // Field m_policyURL:Ljava/lang/String;
     113: aload         7
     115: areturn
     116: goto          151
     119: astore_3
     120: getstatic     #113                // Field log:Lorg/slf4j/Logger;
     123: new           #114                // class java/lang/StringBuilder
     126: dup
     127: invokespecial #115                // Method java/lang/StringBuilder."<init>":()V
     130: ldc           #116                // String Exception while reading configuration:
     132: invokevirtual #117                // Method java/lang/StringBuilder.append:(Ljava/lang/String;)Ljava/lang/StringBuilder;
     135: aload_3
     136: invokevirtual #118                // Method org/apache/jena/shared/JenaException.getMessage:()Ljava/lang/String;
     139: invokevirtual #117                // Method java/lang/StringBuilder.append:(Ljava/lang/String;)Ljava/lang/StringBuilder;
     142: invokevirtual #119                // Method java/lang/StringBuilder.toString:()Ljava/lang/String;
     145: aload_3
     146: invokeinterface #120,  3          // InterfaceMethod org/slf4j/Logger.warn:(Ljava/lang/String;Ljava/lang/Throwable;)V
     151: aconst_null
     152: areturn
    Exception table:
       from    to  target type
          33   115   119   Class org/apache/jena/shared/JenaException

  protected void processMetadata(org.apache.jena.rdf.model.Model);
    Code:
       0: aload_0
       1: invokevirtual #39                 // Method getFileManager:()Lorg/apache/jena/util/FileManager;
       4: invokevirtual #42                 // Method org/apache/jena/util/FileManager.getLocationMapper:()Lorg/apache/jena/util/LocationMapper;
       7: aload_1
       8: invokevirtual #121                // Method org/apache/jena/util/LocationMapper.processConfig:(Lorg/apache/jena/rdf/model/Model;)V
      11: aload_1
      12: getstatic     #122                // Field org/apache/jena/vocabulary/RDF.type:Lorg/apache/jena/rdf/model/Property;
      15: getstatic     #123                // Field DOC_MGR_POLICY:Lorg/apache/jena/rdf/model/Resource;
      18: invokeinterface #124,  3          // InterfaceMethod org/apache/jena/rdf/model/Model.listResourcesWithProperty:(Lorg/apache/jena/rdf/model/Property;Lorg/apache/jena/rdf/model/RDFNode;)Lorg/apache/jena/rdf/model/ResIterator;
      23: astore_2
      24: aload_2
      25: invokeinterface #125,  1          // InterfaceMethod org/apache/jena/rdf/model/ResIterator.hasNext:()Z
      30: ifeq          159
      33: aload_2
      34: invokeinterface #126,  1          // InterfaceMethod org/apache/jena/rdf/model/ResIterator.nextResource:()Lorg/apache/jena/rdf/model/Resource;
      39: astore_3
      40: aload_3
      41: invokeinterface #127,  1          // InterfaceMethod org/apache/jena/rdf/model/Resource.listProperties:()Lorg/apache/jena/rdf/model/StmtIterator;
      46: astore        4
      48: aload         4
      50: invokeinterface #85,  1           // InterfaceMethod org/apache/jena/rdf/model/StmtIterator.hasNext:()Z
      55: ifeq          156
      58: aload         4
      60: invokeinterface #86,  1           // InterfaceMethod org/apache/jena/rdf/model/StmtIterator.nextStatement:()Lorg/apache/jena/rdf/model/Statement;
      65: astore        5
      67: aload         5
      69: invokeinterface #128,  1          // InterfaceMethod org/apache/jena/rdf/model/Statement.getPredicate:()Lorg/apache/jena/rdf/model/Property;
      74: astore        6
      76: aload         6
      78: getstatic     #129                // Field CACHE_MODELS:Lorg/apache/jena/rdf/model/Property;
      81: invokevirtual #130                // Method java/lang/Object.equals:(Ljava/lang/Object;)Z
      84: ifeq          101
      87: aload_0
      88: aload         5
      90: invokeinterface #131,  1          // InterfaceMethod org/apache/jena/rdf/model/Statement.getBoolean:()Z
      95: invokevirtual #132                // Method setCacheModels:(Z)V
      98: goto          153
     101: aload         6
     103: getstatic     #133                // Field PROCESS_IMPORTS:Lorg/apache/jena/rdf/model/Property;
     106: invokevirtual #130                // Method java/lang/Object.equals:(Ljava/lang/Object;)Z
     109: ifeq          126
     112: aload_0
     113: aload         5
     115: invokeinterface #131,  1          // InterfaceMethod org/apache/jena/rdf/model/Statement.getBoolean:()Z
     120: invokevirtual #134                // Method setProcessImports:(Z)V
     123: goto          153
     126: aload         6
     128: getstatic     #135                // Field IGNORE_IMPORT:Lorg/apache/jena/rdf/model/Property;
     131: invokevirtual #130                // Method java/lang/Object.equals:(Ljava/lang/Object;)Z
     134: ifeq          153
     137: aload_0
     138: aload         5
     140: invokeinterface #87,  1           // InterfaceMethod org/apache/jena/rdf/model/Statement.getResource:()Lorg/apache/jena/rdf/model/Resource;
     145: invokeinterface #88,  1           // InterfaceMethod org/apache/jena/rdf/model/Resource.getURI:()Ljava/lang/String;
     150: invokevirtual #136                // Method addIgnoreImport:(Ljava/lang/String;)V
     153: goto          48
     156: goto          24
     159: aload_1
     160: getstatic     #122                // Field org/apache/jena/vocabulary/RDF.type:Lorg/apache/jena/rdf/model/Property;
     163: getstatic     #137                // Field ONTOLOGY_SPEC:Lorg/apache/jena/rdf/model/Resource;
     166: invokeinterface #124,  3          // InterfaceMethod org/apache/jena/rdf/model/Model.listResourcesWithProperty:(Lorg/apache/jena/rdf/model/Property;Lorg/apache/jena/rdf/model/RDFNode;)Lorg/apache/jena/rdf/model/ResIterator;
     171: astore_2
     172: aload_2
     173: invokeinterface #125,  1          // InterfaceMethod org/apache/jena/rdf/model/ResIterator.hasNext:()Z
     178: ifeq          268
     181: aload_2
     182: invokeinterface #126,  1          // InterfaceMethod org/apache/jena/rdf/model/ResIterator.nextResource:()Lorg/apache/jena/rdf/model/Resource;
     187: astore_3
     188: aload_3
     189: getstatic     #138                // Field PUBLIC_URI:Lorg/apache/jena/rdf/model/Property;
     192: invokeinterface #139,  2          // InterfaceMethod org/apache/jena/rdf/model/Resource.getProperty:(Lorg/apache/jena/rdf/model/Property;)Lorg/apache/jena/rdf/model/Statement;
     197: astore        4
     199: aload         4
     201: ifnull        255
     204: aload         4
     206: invokeinterface #87,  1           // InterfaceMethod org/apache/jena/rdf/model/Statement.getResource:()Lorg/apache/jena/rdf/model/Resource;
     211: invokeinterface #88,  1           // InterfaceMethod org/apache/jena/rdf/model/Resource.getURI:()Ljava/lang/String;
     216: astore        5
     218: aload_3
     219: getstatic     #140                // Field ALT_URL:Lorg/apache/jena/rdf/model/Property;
     222: invokeinterface #139,  2          // InterfaceMethod org/apache/jena/rdf/model/Resource.getProperty:(Lorg/apache/jena/rdf/model/Property;)Lorg/apache/jena/rdf/model/Statement;
     227: astore        4
     229: aload         4
     231: ifnull        252
     234: aload_0
     235: aload         5
     237: aload         4
     239: invokeinterface #87,  1           // InterfaceMethod org/apache/jena/rdf/model/Statement.getResource:()Lorg/apache/jena/rdf/model/Resource;
     244: invokeinterface #88,  1           // InterfaceMethod org/apache/jena/rdf/model/Resource.getURI:()Ljava/lang/String;
     249: invokevirtual #141                // Method addAltEntry:(Ljava/lang/String;Ljava/lang/String;)V
     252: goto          265
     255: getstatic     #113                // Field log:Lorg/slf4j/Logger;
     258: ldc           #142                // String Ontology specification node lists no public URI - node ignored
     260: invokeinterface #143,  2          // InterfaceMethod org/slf4j/Logger.warn:(Ljava/lang/String;)V
     265: goto          172
     268: return

  protected void loadImport(org.apache.jena.ontology.OntModel, java.lang.String, java.util.List<java.lang.String>);
    Code:
       0: aload_0
       1: getfield      #8                  // Field m_processImports:Z
       4: ifeq          57
       7: aload_1
       8: aload_2
       9: invokeinterface #144,  2          // InterfaceMethod org/apache/jena/ontology/OntModel.addLoadedImport:(Ljava/lang/String;)V
      14: aload_0
      15: aload_1
      16: aload_2
      17: invokespecial #145                // Method fetchPossiblyCachedImportModel:(Lorg/apache/jena/ontology/OntModel;Ljava/lang/String;)Lorg/apache/jena/rdf/model/Model;
      20: astore        4
      22: aload         4
      24: aload_1
      25: if_acmpeq     57
      28: aload_0
      29: aload         4
      31: aload_3
      32: aload_1
      33: invokeinterface #69,  1           // InterfaceMethod org/apache/jena/ontology/OntModel.getProfile:()Lorg/apache/jena/ontology/Profile;
      38: invokevirtual #70                 // Method queueImports:(Lorg/apache/jena/rdf/model/Model;Ljava/util/List;Lorg/apache/jena/ontology/Profile;)V
      41: aload_1
      42: aload         4
      44: iconst_0
      45: invokeinterface #146,  3          // InterfaceMethod org/apache/jena/ontology/OntModel.addSubModel:(Lorg/apache/jena/rdf/model/Model;Z)V
      50: aload_0
      51: aload_2
      52: aload         4
      54: invokevirtual #61                 // Method addModel:(Ljava/lang/String;Lorg/apache/jena/rdf/model/Model;)V
      57: return

  private org.apache.jena.rdf.model.Model fetchPossiblyCachedImportModel(org.apache.jena.ontology.OntModel, java.lang.String);
    Code:
       0: aload_0
       1: aload_2
       2: invokevirtual #81                 // Method getModel:(Ljava/lang/String;)Lorg/apache/jena/rdf/model/Model;
       5: astore_3
       6: aload_3
       7: ifnonnull     22
      10: aload_0
      11: aload_1
      12: invokeinterface #147,  1          // InterfaceMethod org/apache/jena/ontology/OntModel.getSpecification:()Lorg/apache/jena/ontology/OntModelSpec;
      17: aload_2
      18: invokespecial #148                // Method fetchLoadedImportModel:(Lorg/apache/jena/ontology/OntModelSpec;Ljava/lang/String;)Lorg/apache/jena/rdf/model/Model;
      21: astore_3
      22: aload_3
      23: areturn

  private org.apache.jena.rdf.model.Model fetchLoadedImportModel(org.apache.jena.ontology.OntModelSpec, java.lang.String);
    Code:
       0: aload_1
       1: invokevirtual #149                // Method org/apache/jena/ontology/OntModelSpec.getImportModelMaker:()Lorg/apache/jena/rdf/model/ModelMaker;
       4: astore_3
       5: aload_3
       6: aload_2
       7: invokeinterface #150,  2          // InterfaceMethod org/apache/jena/rdf/model/ModelMaker.hasModel:(Ljava/lang/String;)Z
      12: ifeq          44
      15: aload_3
      16: aload_2
      17: invokeinterface #151,  2          // InterfaceMethod org/apache/jena/rdf/model/ModelMaker.getModel:(Ljava/lang/String;)Lorg/apache/jena/rdf/model/Model;
      22: astore        4
      24: aload         4
      26: invokeinterface #46,  1           // InterfaceMethod org/apache/jena/rdf/model/Model.isClosed:()Z
      31: ifne          37
      34: aload         4
      36: areturn
      37: aload_3
      38: aload_2
      39: invokeinterface #152,  2          // InterfaceMethod org/apache/jena/rdf/model/ModelMaker.removeModel:(Ljava/lang/String;)V
      44: aload_1
      45: invokevirtual #153                // Method org/apache/jena/ontology/OntModelSpec.getImportModelGetter:()Lorg/apache/jena/rdf/model/ModelGetter;
      48: aload_2
      49: new           #154                // class org/apache/jena/ontology/OntDocumentManager$1
      52: dup
      53: aload_0
      54: invokespecial #155                // Method org/apache/jena/ontology/OntDocumentManager$1."<init>":(Lorg/apache/jena/ontology/OntDocumentManager;)V
      57: invokeinterface #156,  3          // InterfaceMethod org/apache/jena/rdf/model/ModelGetter.getModel:(Ljava/lang/String;Lorg/apache/jena/rdf/model/ModelReader;)Lorg/apache/jena/rdf/model/Model;
      62: astore        4
      64: aload         4
      66: areturn

  protected boolean read(org.apache.jena.rdf.model.Model, java.lang.String, boolean);
    Code:
       0: iconst_0
       1: istore        4
       3: aload_0
       4: getfield      #18                 // Field m_readHook:Lorg/apache/jena/ontology/OntDocumentManager$ReadHook;
       7: aload_1
       8: aload_2
       9: aload_0
      10: invokeinterface #157,  4          // InterfaceMethod org/apache/jena/ontology/OntDocumentManager$ReadHook.beforeRead:(Lorg/apache/jena/rdf/model/Model;Ljava/lang/String;Lorg/apache/jena/ontology/OntDocumentManager;)Ljava/lang/String;
      15: astore        5
      17: aload         5
      19: ifnonnull     55
      22: getstatic     #113                // Field log:Lorg/slf4j/Logger;
      25: new           #114                // class java/lang/StringBuilder
      28: dup
      29: invokespecial #115                // Method java/lang/StringBuilder."<init>":()V
      32: ldc           #158                // String Read hook returned null source, so assuming old value:
      34: invokevirtual #117                // Method java/lang/StringBuilder.append:(Ljava/lang/String;)Ljava/lang/StringBuilder;
      37: aload_2
      38: invokevirtual #117                // Method java/lang/StringBuilder.append:(Ljava/lang/String;)Ljava/lang/StringBuilder;
      41: invokevirtual #119                // Method java/lang/StringBuilder.toString:()Ljava/lang/String;
      44: invokeinterface #143,  2          // InterfaceMethod org/slf4j/Logger.warn:(Ljava/lang/String;)V
      49: aload_2
      50: astore        5
      52: goto          66
      55: aload_0
      56: invokevirtual #39                 // Method getFileManager:()Lorg/apache/jena/util/FileManager;
      59: aload_1
      60: aload         5
      62: invokevirtual #159                // Method org/apache/jena/util/FileManager.readModel:(Lorg/apache/jena/rdf/model/Model;Ljava/lang/String;)Lorg/apache/jena/rdf/model/Model;
      65: pop
      66: aload_0
      67: getfield      #18                 // Field m_readHook:Lorg/apache/jena/ontology/OntDocumentManager$ReadHook;
      70: aload_1
      71: aload         5
      73: aload_0
      74: invokeinterface #160,  4          // InterfaceMethod org/apache/jena/ontology/OntDocumentManager$ReadHook.afterRead:(Lorg/apache/jena/rdf/model/Model;Ljava/lang/String;Lorg/apache/jena/ontology/OntDocumentManager;)V
      79: iconst_1
      80: istore        4
      82: goto          157
      85: astore        5
      87: aload_0
      88: invokevirtual #162                // Method getReadFailureHandler:()Lorg/apache/jena/ontology/OntDocumentManager$ReadFailureHandler;
      91: ifnull        110
      94: aload_0
      95: invokevirtual #162                // Method getReadFailureHandler:()Lorg/apache/jena/ontology/OntDocumentManager$ReadFailureHandler;
      98: aload_2
      99: aload_1
     100: aload         5
     102: invokeinterface #163,  4          // InterfaceMethod org/apache/jena/ontology/OntDocumentManager$ReadFailureHandler.handleFailedRead:(Ljava/lang/String;Lorg/apache/jena/rdf/model/Model;Ljava/lang/Exception;)V
     107: goto          157
     110: getstatic     #113                // Field log:Lorg/slf4j/Logger;
     113: new           #114                // class java/lang/StringBuilder
     116: dup
     117: invokespecial #115                // Method java/lang/StringBuilder."<init>":()V
     120: ldc           #164                // String An error occurred while attempting to read from
     122: invokevirtual #117                // Method java/lang/StringBuilder.append:(Ljava/lang/String;)Ljava/lang/StringBuilder;
     125: aload_2
     126: invokevirtual #117                // Method java/lang/StringBuilder.append:(Ljava/lang/String;)Ljava/lang/StringBuilder;
     129: ldc           #165                // String . Msg was \'
     131: invokevirtual #117                // Method java/lang/StringBuilder.append:(Ljava/lang/String;)Ljava/lang/StringBuilder;
     134: aload         5
     136: invokevirtual #166                // Method java/lang/Exception.getMessage:()Ljava/lang/String;
     139: invokevirtual #117                // Method java/lang/StringBuilder.append:(Ljava/lang/String;)Ljava/lang/StringBuilder;
     142: ldc           #167                // String \'.
     144: invokevirtual #117                // Method java/lang/StringBuilder.append:(Ljava/lang/String;)Ljava/lang/StringBuilder;
     147: invokevirtual #119                // Method java/lang/StringBuilder.toString:()Ljava/lang/String;
     150: aload         5
     152: invokeinterface #120,  3          // InterfaceMethod org/slf4j/Logger.warn:(Ljava/lang/String;Ljava/lang/Throwable;)V
     157: iload         4
     159: ireturn
    Exception table:
       from    to  target type
           3    82    85   Class java/lang/Exception

  protected void setDefaults();
    Code:
       0: aload_0
       1: iconst_1
       2: invokevirtual #132                // Method setCacheModels:(Z)V
       5: aload_0
       6: iconst_1
       7: invokevirtual #134                // Method setProcessImports:(Z)V
      10: aload_0
      11: invokevirtual #168                // Method setDefaultPrefixMappings:()V
      14: return

  protected void setDefaultPrefixMappings();
    Code:
       0: aload_0
       1: getfield      #14                 // Field m_prefixMap:Lorg/apache/jena/shared/PrefixMapping;
       4: getstatic     #169                // Field org/apache/jena/shared/PrefixMapping.Standard:Lorg/apache/jena/shared/PrefixMapping;
       7: invokeinterface #170,  2          // InterfaceMethod org/apache/jena/shared/PrefixMapping.setNsPrefixes:(Lorg/apache/jena/shared/PrefixMapping;)Lorg/apache/jena/shared/PrefixMapping;
      12: pop
      13: aload_0
      14: getfield      #14                 // Field m_prefixMap:Lorg/apache/jena/shared/PrefixMapping;
      17: ldc           #171                // String dc
      19: invokeinterface #172,  2          // InterfaceMethod org/apache/jena/shared/PrefixMapping.removeNsPrefix:(Ljava/lang/String;)Lorg/apache/jena/shared/PrefixMapping;
      24: pop
      25: return

  static {};
    Code:
       0: getstatic     #173                // Field org/apache/jena/vocabulary/OntDocManagerVocab.OntologySpec:Lorg/apache/jena/rdf/model/Resource;
       3: putstatic     #137                // Field ONTOLOGY_SPEC:Lorg/apache/jena/rdf/model/Resource;
       6: getstatic     #174                // Field org/apache/jena/vocabulary/OntDocManagerVocab.publicURI:Lorg/apache/jena/rdf/model/Property;
       9: putstatic     #138                // Field PUBLIC_URI:Lorg/apache/jena/rdf/model/Property;
      12: getstatic     #175                // Field org/apache/jena/vocabulary/OntDocManagerVocab.altURL:Lorg/apache/jena/rdf/model/Property;
      15: putstatic     #140                // Field ALT_URL:Lorg/apache/jena/rdf/model/Property;
      18: getstatic     #176                // Field org/apache/jena/vocabulary/OntDocManagerVocab.prefix:Lorg/apache/jena/rdf/model/Property;
      21: putstatic     #177                // Field PREFIX:Lorg/apache/jena/rdf/model/Property;
      24: getstatic     #178                // Field org/apache/jena/vocabulary/OntDocManagerVocab.language:Lorg/apache/jena/rdf/model/Property;
      27: putstatic     #179                // Field LANGUAGE:Lorg/apache/jena/rdf/model/Property;
      30: getstatic     #180                // Field org/apache/jena/vocabulary/OntDocManagerVocab.DocumentManagerPolicy:Lorg/apache/jena/rdf/model/Resource;
      33: putstatic     #123                // Field DOC_MGR_POLICY:Lorg/apache/jena/rdf/model/Resource;
      36: getstatic     #181                // Field org/apache/jena/vocabulary/OntDocManagerVocab.cacheModels:Lorg/apache/jena/rdf/model/Property;
      39: putstatic     #129                // Field CACHE_MODELS:Lorg/apache/jena/rdf/model/Property;
      42: getstatic     #182                // Field org/apache/jena/vocabulary/OntDocManagerVocab.processImports:Lorg/apache/jena/rdf/model/Property;
      45: putstatic     #133                // Field PROCESS_IMPORTS:Lorg/apache/jena/rdf/model/Property;
      48: getstatic     #183                // Field org/apache/jena/vocabulary/OntDocManagerVocab.ignoreImport:Lorg/apache/jena/rdf/model/Property;
      51: putstatic     #135                // Field IGNORE_IMPORT:Lorg/apache/jena/rdf/model/Property;
      54: getstatic     #184                // Field org/apache/jena/vocabulary/OntDocManagerVocab.useDeclaredNsPrefixes:Lorg/apache/jena/rdf/model/Property;
      57: putstatic     #185                // Field USE_DECLARED_NS_PREFIXES:Lorg/apache/jena/rdf/model/Property;
      60: aconst_null
      61: putstatic     #25                 // Field s_instance:Lorg/apache/jena/ontology/OntDocumentManager;
      64: ldc           #1                  // class org/apache/jena/ontology/OntDocumentManager
      66: invokestatic  #186                // Method org/slf4j/LoggerFactory.getLogger:(Ljava/lang/Class;)Lorg/slf4j/Logger;
      69: putstatic     #113                // Field log:Lorg/slf4j/Logger;
      72: return
}
