Compiled from "MapView.java"
public interface net.openhft.chronicle.engine.api.map.MapView<K, V> extends java.util.concurrent.ConcurrentMap<K, V>, net.openhft.chronicle.engine.api.tree.Assetted<java.lang.Object>, net.openhft.chronicle.engine.api.Updatable<net.openhft.chronicle.engine.api.map.MapView<K, V>>, net.openhft.chronicle.engine.api.KeyedVisitable<K, V>, java.util.function.Function<K, V>, net.openhft.chronicle.engine.api.tree.KeyedView {
  public abstract net.openhft.chronicle.engine.api.set.KeySetView<K> keySet();

  public abstract net.openhft.chronicle.engine.api.set.EntrySetView<K, java.lang.Object, V> entrySet();

  public abstract V getUsing(K, java.lang.Object);

  public abstract void registerTopicSubscriber(net.openhft.chronicle.engine.api.pubsub.TopicSubscriber<K, V>);

  public abstract void registerKeySubscriber(net.openhft.chronicle.engine.api.pubsub.Subscriber<K>);

  public abstract void registerKeySubscriber(net.openhft.chronicle.engine.api.pubsub.Subscriber<K>, net.openhft.chronicle.engine.query.Filter, java.util.Set<net.openhft.chronicle.engine.api.tree.RequestContext$Operation>);

  public abstract void registerSubscriber(net.openhft.chronicle.engine.api.pubsub.Subscriber<net.openhft.chronicle.engine.api.map.MapEvent<K, V>>);

  public abstract void registerSubscriber(net.openhft.chronicle.engine.api.pubsub.Subscriber<net.openhft.chronicle.engine.api.map.MapEvent<K, V>>, net.openhft.chronicle.engine.query.Filter<net.openhft.chronicle.engine.api.map.MapEvent<K, V>>, java.util.Set<net.openhft.chronicle.engine.api.tree.RequestContext$Operation>);

  public abstract net.openhft.chronicle.engine.api.pubsub.Reference<V> referenceFor(K);

  public abstract java.lang.Class<K> keyType();

  public abstract java.lang.Class<V> valueType();

  public default V apply(K);
    Code:
       0: aload_0
       1: aload_1
       2: invokeinterface #1,  2            // InterfaceMethod get:(Ljava/lang/Object;)Ljava/lang/Object;
       7: areturn

  public default int size();
    Code:
       0: ldc2_w        #3                  // long 2147483647l
       3: aload_0
       4: invokeinterface #5,  1            // InterfaceMethod longSize:()J
       9: invokestatic  #6                  // Method java/lang/Math.min:(JJ)J
      12: l2i
      13: ireturn

  public abstract long longSize();

  public abstract V getAndPut(K, V);

  public abstract V getAndRemove(K);

  public default java.util.Set entrySet();
    Code:
       0: aload_0
       1: invokeinterface #7,  1            // InterfaceMethod entrySet:()Lnet/openhft/chronicle/engine/api/set/EntrySetView;
       6: areturn

  public default java.util.Set keySet();
    Code:
       0: aload_0
       1: invokeinterface #8,  1            // InterfaceMethod keySet:()Lnet/openhft/chronicle/engine/api/set/KeySetView;
       6: areturn
}
