Compiled from "NonClosingJarInputStream.java"
public class org.apache.tomcat.util.scan.NonClosingJarInputStream extends java.util.jar.JarInputStream {
  public org.apache.tomcat.util.scan.NonClosingJarInputStream(java.io.InputStream, boolean) throws java.io.IOException;
    Code:
       0: aload_0
       1: aload_1
       2: iload_2
       3: invokespecial #1                  // Method java/util/jar/JarInputStream."<init>":(Ljava/io/InputStream;Z)V
       6: return

  public org.apache.tomcat.util.scan.NonClosingJarInputStream(java.io.InputStream) throws java.io.IOException;
    Code:
       0: aload_0
       1: aload_1
       2: invokespecial #2                  // Method java/util/jar/JarInputStream."<init>":(Ljava/io/InputStream;)V
       5: return

  public void close() throws java.io.IOException;
    Code:
       0: return

  public void reallyClose() throws java.io.IOException;
    Code:
       0: aload_0
       1: invokespecial #3                  // Method java/util/jar/JarInputStream.close:()V
       4: return
}
