Compiled from "OWLMembersListViewComponent.java"
public class org.protege.editor.owl.ui.view.individual.OWLMembersListViewComponent extends org.protege.editor.owl.ui.view.individual.OWLIndividualListViewComponent {
  private final javax.swing.JLabel typeLabel;

  private org.protege.editor.owl.model.selection.OWLSelectionModelListener l;

  public org.protege.editor.owl.ui.view.individual.OWLMembersListViewComponent();
    Code:
       0: aload_0
       1: invokespecial #1                  // Method org/protege/editor/owl/ui/view/individual/OWLIndividualListViewComponent."<init>":()V
       4: aload_0
       5: new           #2                  // class javax/swing/JLabel
       8: dup
       9: invokespecial #3                  // Method javax/swing/JLabel."<init>":()V
      12: putfield      #4                  // Field typeLabel:Ljavax/swing/JLabel;
      15: aload_0
      16: aload_0
      17: invokedynamic #5,  0              // InvokeDynamic #0:selectionChanged:(Lorg/protege/editor/owl/ui/view/individual/OWLMembersListViewComponent;)Lorg/protege/editor/owl/model/selection/OWLSelectionModelListener;
      22: putfield      #6                  // Field l:Lorg/protege/editor/owl/model/selection/OWLSelectionModelListener;
      25: return

  public void initialiseIndividualsView() throws java.lang.Exception;
    Code:
       0: aload_0
       1: invokespecial #7                  // Method org/protege/editor/owl/ui/view/individual/OWLIndividualListViewComponent.initialiseIndividualsView:()V
       4: aload_0
       5: invokevirtual #8                  // Method getOWLWorkspace:()Lorg/protege/editor/owl/model/OWLWorkspace;
       8: invokevirtual #9                  // Method org/protege/editor/owl/model/OWLWorkspace.getOWLSelectionModel:()Lorg/protege/editor/owl/model/selection/OWLSelectionModel;
      11: aload_0
      12: getfield      #6                  // Field l:Lorg/protege/editor/owl/model/selection/OWLSelectionModelListener;
      15: invokeinterface #10,  2           // InterfaceMethod org/protege/editor/owl/model/selection/OWLSelectionModel.addListener:(Lorg/protege/editor/owl/model/selection/OWLSelectionModelListener;)V
      20: new           #11                 // class javax/swing/Box
      23: dup
      24: iconst_0
      25: invokespecial #13                 // Method javax/swing/Box."<init>":(I)V
      28: astore_1
      29: aload_1
      30: new           #2                  // class javax/swing/JLabel
      33: dup
      34: ldc           #14                 // String For:
      36: invokespecial #15                 // Method javax/swing/JLabel."<init>":(Ljava/lang/String;)V
      39: invokevirtual #16                 // Method javax/swing/JComponent.add:(Ljava/awt/Component;)Ljava/awt/Component;
      42: pop
      43: aload_1
      44: aload_0
      45: getfield      #4                  // Field typeLabel:Ljavax/swing/JLabel;
      48: invokevirtual #16                 // Method javax/swing/JComponent.add:(Ljava/awt/Component;)Ljava/awt/Component;
      51: pop
      52: aload_1
      53: iconst_2
      54: iconst_2
      55: iconst_2
      56: iconst_0
      57: invokestatic  #17                 // Method javax/swing/BorderFactory.createEmptyBorder:(IIII)Ljavax/swing/border/Border;
      60: invokevirtual #18                 // Method javax/swing/JComponent.setBorder:(Ljavax/swing/border/Border;)V
      63: aload_0
      64: aload_1
      65: ldc           #20                 // String North
      67: invokevirtual #21                 // Method add:(Ljava/awt/Component;Ljava/lang/Object;)V
      70: return

  protected void refill();
    Code:
       0: aload_0
       1: getfield      #22                 // Field individualsInList:Ljava/util/Set;
       4: invokeinterface #23,  1           // InterfaceMethod java/util/Set.clear:()V
       9: aload_0
      10: invokevirtual #8                  // Method getOWLWorkspace:()Lorg/protege/editor/owl/model/OWLWorkspace;
      13: invokevirtual #9                  // Method org/protege/editor/owl/model/OWLWorkspace.getOWLSelectionModel:()Lorg/protege/editor/owl/model/selection/OWLSelectionModel;
      16: invokeinterface #24,  1           // InterfaceMethod org/protege/editor/owl/model/selection/OWLSelectionModel.getLastSelectedClass:()Lorg/semanticweb/owlapi/model/OWLClass;
      21: astore_1
      22: aload_1
      23: ifnull        167
      26: aload_0
      27: getfield      #4                  // Field typeLabel:Ljavax/swing/JLabel;
      30: aload_0
      31: invokevirtual #25                 // Method getOWLModelManager:()Lorg/protege/editor/owl/model/OWLModelManager;
      34: aload_1
      35: invokeinterface #26,  2           // InterfaceMethod org/protege/editor/owl/model/OWLModelManager.getRendering:(Lorg/semanticweb/owlapi/model/OWLObject;)Ljava/lang/String;
      40: invokevirtual #27                 // Method javax/swing/JLabel.setText:(Ljava/lang/String;)V
      43: aload_0
      44: getfield      #4                  // Field typeLabel:Ljavax/swing/JLabel;
      47: aload_0
      48: invokevirtual #8                  // Method getOWLWorkspace:()Lorg/protege/editor/owl/model/OWLWorkspace;
      51: invokevirtual #28                 // Method org/protege/editor/owl/model/OWLWorkspace.getOWLIconProvider:()Lorg/protege/editor/owl/ui/renderer/OWLIconProvider;
      54: aload_1
      55: invokeinterface #29,  2           // InterfaceMethod org/protege/editor/owl/ui/renderer/OWLIconProvider.getIcon:(Lorg/semanticweb/owlapi/model/OWLObject;)Ljavax/swing/Icon;
      60: invokevirtual #30                 // Method javax/swing/JLabel.setIcon:(Ljavax/swing/Icon;)V
      63: aload_1
      64: aload_0
      65: invokevirtual #31                 // Method getOntologies:()Ljava/util/Set;
      68: invokestatic  #32                 // Method org/semanticweb/owlapi/search/EntitySearcher.getIndividuals:(Lorg/semanticweb/owlapi/model/OWLClass;Ljava/lang/Iterable;)Ljava/util/Collection;
      71: astore_2
      72: aload_2
      73: invokeinterface #33,  1           // InterfaceMethod java/util/Collection.iterator:()Ljava/util/Iterator;
      78: astore_3
      79: aload_3
      80: invokeinterface #34,  1           // InterfaceMethod java/util/Iterator.hasNext:()Z
      85: ifeq          129
      88: aload_3
      89: invokeinterface #35,  1           // InterfaceMethod java/util/Iterator.next:()Ljava/lang/Object;
      94: checkcast     #36                 // class org/semanticweb/owlapi/model/OWLIndividual
      97: astore        4
      99: aload         4
     101: invokeinterface #37,  1           // InterfaceMethod org/semanticweb/owlapi/model/OWLIndividual.isAnonymous:()Z
     106: ifne          126
     109: aload_0
     110: getfield      #22                 // Field individualsInList:Ljava/util/Set;
     113: aload         4
     115: invokeinterface #38,  1           // InterfaceMethod org/semanticweb/owlapi/model/OWLIndividual.asOWLNamedIndividual:()Lorg/semanticweb/owlapi/model/OWLNamedIndividual;
     120: invokeinterface #39,  2           // InterfaceMethod java/util/Set.add:(Ljava/lang/Object;)Z
     125: pop
     126: goto          79
     129: aload_1
     130: aload_0
     131: invokevirtual #25                 // Method getOWLModelManager:()Lorg/protege/editor/owl/model/OWLModelManager;
     134: invokeinterface #40,  1           // InterfaceMethod org/protege/editor/owl/model/OWLModelManager.getOWLDataFactory:()Lorg/semanticweb/owlapi/model/OWLDataFactory;
     139: invokeinterface #41,  1           // InterfaceMethod org/semanticweb/owlapi/model/OWLDataFactory.getOWLThing:()Lorg/semanticweb/owlapi/model/OWLClass;
     144: invokevirtual #42                 // Method java/lang/Object.equals:(Ljava/lang/Object;)Z
     147: ifeq          164
     150: aload_0
     151: getfield      #22                 // Field individualsInList:Ljava/util/Set;
     154: aload_0
     155: invokevirtual #43                 // Method getUntypedIndividuals:()Ljava/util/Set;
     158: invokeinterface #44,  2           // InterfaceMethod java/util/Set.addAll:(Ljava/util/Collection;)Z
     163: pop
     164: goto          198
     167: aload_0
     168: getfield      #4                  // Field typeLabel:Ljavax/swing/JLabel;
     171: aconst_null
     172: invokevirtual #30                 // Method javax/swing/JLabel.setIcon:(Ljavax/swing/Icon;)V
     175: aload_0
     176: getfield      #4                  // Field typeLabel:Ljavax/swing/JLabel;
     179: ldc           #45                 // String Nothing selected
     181: invokevirtual #27                 // Method javax/swing/JLabel.setText:(Ljava/lang/String;)V
     184: aload_0
     185: getfield      #22                 // Field individualsInList:Ljava/util/Set;
     188: aload_0
     189: invokevirtual #43                 // Method getUntypedIndividuals:()Ljava/util/Set;
     192: invokeinterface #44,  2           // InterfaceMethod java/util/Set.addAll:(Ljava/util/Collection;)Z
     197: pop
     198: aload_0
     199: invokevirtual #46                 // Method reset:()V
     202: return

  protected java.util.Set<org.semanticweb.owlapi.model.OWLNamedIndividual> getUntypedIndividuals();
    Code:
       0: new           #47                 // class java/util/HashSet
       3: dup
       4: invokespecial #48                 // Method java/util/HashSet."<init>":()V
       7: astore_1
       8: aload_0
       9: invokevirtual #25                 // Method getOWLModelManager:()Lorg/protege/editor/owl/model/OWLModelManager;
      12: invokeinterface #49,  1           // InterfaceMethod org/protege/editor/owl/model/OWLModelManager.getActiveOntology:()Lorg/semanticweb/owlapi/model/OWLOntology;
      17: astore_2
      18: aload_2
      19: invokeinterface #50,  1           // InterfaceMethod org/semanticweb/owlapi/model/OWLOntology.getImportsClosure:()Ljava/util/Set;
      24: astore_3
      25: aload_2
      26: getstatic     #51                 // Field org/semanticweb/owlapi/model/parameters/Imports.INCLUDED:Lorg/semanticweb/owlapi/model/parameters/Imports;
      29: invokeinterface #52,  2           // InterfaceMethod org/semanticweb/owlapi/model/OWLOntology.getIndividualsInSignature:(Lorg/semanticweb/owlapi/model/parameters/Imports;)Ljava/util/Set;
      34: invokeinterface #53,  1           // InterfaceMethod java/util/Set.iterator:()Ljava/util/Iterator;
      39: astore        4
      41: aload         4
      43: invokeinterface #34,  1           // InterfaceMethod java/util/Iterator.hasNext:()Z
      48: ifeq          93
      51: aload         4
      53: invokeinterface #35,  1           // InterfaceMethod java/util/Iterator.next:()Ljava/lang/Object;
      58: checkcast     #54                 // class org/semanticweb/owlapi/model/OWLNamedIndividual
      61: astore        5
      63: aload         5
      65: aload_3
      66: invokestatic  #55                 // Method org/semanticweb/owlapi/search/EntitySearcher.getTypes:(Lorg/semanticweb/owlapi/model/OWLIndividual;Ljava/lang/Iterable;)Ljava/util/Collection;
      69: astore        6
      71: aload         6
      73: invokeinterface #56,  1           // InterfaceMethod java/util/Collection.size:()I
      78: ifne          90
      81: aload_1
      82: aload         5
      84: invokeinterface #39,  2           // InterfaceMethod java/util/Set.add:(Ljava/lang/Object;)Z
      89: pop
      90: goto          41
      93: aload_1
      94: areturn

  protected void processChanges(java.util.List<? extends org.semanticweb.owlapi.model.OWLOntologyChange>);
    Code:
       0: aload_0
       1: invokevirtual #57                 // Method refill:()V
       4: return

  protected java.util.List<org.semanticweb.owlapi.model.OWLOntologyChange> dofurtherCreateSteps(org.semanticweb.owlapi.model.OWLIndividual);
    Code:
       0: aload_0
       1: invokevirtual #8                  // Method getOWLWorkspace:()Lorg/protege/editor/owl/model/OWLWorkspace;
       4: invokevirtual #9                  // Method org/protege/editor/owl/model/OWLWorkspace.getOWLSelectionModel:()Lorg/protege/editor/owl/model/selection/OWLSelectionModel;
       7: invokeinterface #24,  1           // InterfaceMethod org/protege/editor/owl/model/selection/OWLSelectionModel.getLastSelectedClass:()Lorg/semanticweb/owlapi/model/OWLClass;
      12: astore_2
      13: aload_2
      14: ifnull        68
      17: aload_2
      18: invokeinterface #58,  1           // InterfaceMethod org/semanticweb/owlapi/model/OWLClass.isOWLThing:()Z
      23: ifne          68
      26: aload_0
      27: invokevirtual #25                 // Method getOWLModelManager:()Lorg/protege/editor/owl/model/OWLModelManager;
      30: invokeinterface #40,  1           // InterfaceMethod org/protege/editor/owl/model/OWLModelManager.getOWLDataFactory:()Lorg/semanticweb/owlapi/model/OWLDataFactory;
      35: aload_2
      36: aload_1
      37: invokeinterface #59,  3           // InterfaceMethod org/semanticweb/owlapi/model/OWLDataFactory.getOWLClassAssertionAxiom:(Lorg/semanticweb/owlapi/model/OWLClassExpression;Lorg/semanticweb/owlapi/model/OWLIndividual;)Lorg/semanticweb/owlapi/model/OWLClassAssertionAxiom;
      42: astore_3
      43: new           #60                 // class org/semanticweb/owlapi/model/AddAxiom
      46: dup
      47: aload_0
      48: invokevirtual #25                 // Method getOWLModelManager:()Lorg/protege/editor/owl/model/OWLModelManager;
      51: invokeinterface #49,  1           // InterfaceMethod org/protege/editor/owl/model/OWLModelManager.getActiveOntology:()Lorg/semanticweb/owlapi/model/OWLOntology;
      56: aload_3
      57: invokespecial #61                 // Method org/semanticweb/owlapi/model/AddAxiom."<init>":(Lorg/semanticweb/owlapi/model/OWLOntology;Lorg/semanticweb/owlapi/model/OWLAxiom;)V
      60: astore        4
      62: aload         4
      64: invokestatic  #62                 // Method java/util/Collections.singletonList:(Ljava/lang/Object;)Ljava/util/List;
      67: areturn
      68: new           #63                 // class java/util/ArrayList
      71: dup
      72: invokespecial #64                 // Method java/util/ArrayList."<init>":()V
      75: areturn

  public void disposeView();
    Code:
       0: aload_0
       1: invokevirtual #8                  // Method getOWLWorkspace:()Lorg/protege/editor/owl/model/OWLWorkspace;
       4: invokevirtual #9                  // Method org/protege/editor/owl/model/OWLWorkspace.getOWLSelectionModel:()Lorg/protege/editor/owl/model/selection/OWLSelectionModel;
       7: aload_0
       8: getfield      #6                  // Field l:Lorg/protege/editor/owl/model/selection/OWLSelectionModelListener;
      11: invokeinterface #65,  2           // InterfaceMethod org/protege/editor/owl/model/selection/OWLSelectionModel.removeListener:(Lorg/protege/editor/owl/model/selection/OWLSelectionModelListener;)V
      16: aload_0
      17: invokespecial #66                 // Method org/protege/editor/owl/ui/view/individual/OWLIndividualListViewComponent.disposeView:()V
      20: return

  private void lambda$new$0() throws java.lang.Exception;
    Code:
       0: aload_0
       1: invokevirtual #8                  // Method getOWLWorkspace:()Lorg/protege/editor/owl/model/OWLWorkspace;
       4: invokevirtual #9                  // Method org/protege/editor/owl/model/OWLWorkspace.getOWLSelectionModel:()Lorg/protege/editor/owl/model/selection/OWLSelectionModel;
       7: invokeinterface #67,  1           // InterfaceMethod org/protege/editor/owl/model/selection/OWLSelectionModel.getSelectedObject:()Lorg/semanticweb/owlapi/model/OWLObject;
      12: instanceof    #68                 // class org/semanticweb/owlapi/model/OWLClass
      15: ifeq          22
      18: aload_0
      19: invokevirtual #57                 // Method refill:()V
      22: return
}
