Compiled from "JpaParameters.java"
public class org.springframework.data.jpa.repository.query.JpaParameters extends org.springframework.data.repository.query.Parameters<org.springframework.data.jpa.repository.query.JpaParameters, org.springframework.data.jpa.repository.query.JpaParameters$JpaParameter> {
  public org.springframework.data.jpa.repository.query.JpaParameters(java.lang.reflect.Method);
    Code:
       0: aload_0
       1: aload_1
       2: invokespecial #1                  // Method org/springframework/data/repository/query/Parameters."<init>":(Ljava/lang/reflect/Method;)V
       5: return

  private org.springframework.data.jpa.repository.query.JpaParameters(java.util.List<org.springframework.data.jpa.repository.query.JpaParameters$JpaParameter>);
    Code:
       0: aload_0
       1: aload_1
       2: invokespecial #2                  // Method org/springframework/data/repository/query/Parameters."<init>":(Ljava/util/List;)V
       5: return

  protected org.springframework.data.jpa.repository.query.JpaParameters$JpaParameter createParameter(org.springframework.core.MethodParameter);
    Code:
       0: new           #3                  // class org/springframework/data/jpa/repository/query/JpaParameters$JpaParameter
       3: dup
       4: aload_1
       5: invokespecial #4                  // Method org/springframework/data/jpa/repository/query/JpaParameters$JpaParameter."<init>":(Lorg/springframework/core/MethodParameter;)V
       8: areturn

  protected org.springframework.data.jpa.repository.query.JpaParameters createFrom(java.util.List<org.springframework.data.jpa.repository.query.JpaParameters$JpaParameter>);
    Code:
       0: new           #5                  // class org/springframework/data/jpa/repository/query/JpaParameters
       3: dup
       4: aload_1
       5: invokespecial #6                  // Method "<init>":(Ljava/util/List;)V
       8: areturn

  protected org.springframework.data.repository.query.Parameters createFrom(java.util.List);
    Code:
       0: aload_0
       1: aload_1
       2: invokevirtual #7                  // Method createFrom:(Ljava/util/List;)Lorg/springframework/data/jpa/repository/query/JpaParameters;
       5: areturn

  protected org.springframework.data.repository.query.Parameter createParameter(org.springframework.core.MethodParameter);
    Code:
       0: aload_0
       1: aload_1
       2: invokevirtual #8                  // Method createParameter:(Lorg/springframework/core/MethodParameter;)Lorg/springframework/data/jpa/repository/query/JpaParameters$JpaParameter;
       5: areturn
}
