Compiled from "QueryParameterSetterFactory.java"
class org.springframework.data.jpa.repository.query.QueryParameterSetterFactory$ExpressionBasedQueryParameterSetterFactory extends org.springframework.data.jpa.repository.query.QueryParameterSetterFactory {
  private final org.springframework.expression.spel.standard.SpelExpressionParser parser;

  private final org.springframework.data.repository.query.QueryMethodEvaluationContextProvider evaluationContextProvider;

  private final org.springframework.data.repository.query.Parameters<?, ?> parameters;

  org.springframework.data.jpa.repository.query.QueryParameterSetterFactory$ExpressionBasedQueryParameterSetterFactory(org.springframework.expression.spel.standard.SpelExpressionParser, org.springframework.data.repository.query.QueryMethodEvaluationContextProvider, org.springframework.data.repository.query.Parameters<?, ?>);
    Code:
       0: aload_0
       1: invokespecial #1                  // Method org/springframework/data/jpa/repository/query/QueryParameterSetterFactory."<init>":()V
       4: aload_2
       5: ldc           #2                  // String EvaluationContextProvider must not be null!
       7: invokestatic  #3                  // Method org/springframework/util/Assert.notNull:(Ljava/lang/Object;Ljava/lang/String;)V
      10: aload_1
      11: ldc           #4                  // String SpelExpressionParser must not be null!
      13: invokestatic  #3                  // Method org/springframework/util/Assert.notNull:(Ljava/lang/Object;Ljava/lang/String;)V
      16: aload_3
      17: ldc           #5                  // String Parameters must not be null!
      19: invokestatic  #3                  // Method org/springframework/util/Assert.notNull:(Ljava/lang/Object;Ljava/lang/String;)V
      22: aload_0
      23: aload_2
      24: putfield      #6                  // Field evaluationContextProvider:Lorg/springframework/data/repository/query/QueryMethodEvaluationContextProvider;
      27: aload_0
      28: aload_1
      29: putfield      #7                  // Field parser:Lorg/springframework/expression/spel/standard/SpelExpressionParser;
      32: aload_0
      33: aload_3
      34: putfield      #8                  // Field parameters:Lorg/springframework/data/repository/query/Parameters;
      37: return

  public org.springframework.data.jpa.repository.query.QueryParameterSetter create(org.springframework.data.jpa.repository.query.StringQuery$ParameterBinding, org.springframework.data.jpa.repository.query.DeclaredQuery);
    Code:
       0: aload_1
       1: invokevirtual #9                  // Method org/springframework/data/jpa/repository/query/StringQuery$ParameterBinding.isExpression:()Z
       4: ifne          9
       7: aconst_null
       8: areturn
       9: aload_0
      10: getfield      #7                  // Field parser:Lorg/springframework/expression/spel/standard/SpelExpressionParser;
      13: aload_1
      14: invokevirtual #10                 // Method org/springframework/data/jpa/repository/query/StringQuery$ParameterBinding.getExpression:()Ljava/lang/String;
      17: invokevirtual #11                 // Method org/springframework/expression/spel/standard/SpelExpressionParser.parseExpression:(Ljava/lang/String;)Lorg/springframework/expression/Expression;
      20: astore_3
      21: aload_0
      22: aload_3
      23: invokedynamic #12,  0             // InvokeDynamic #0:apply:(Lorg/springframework/data/jpa/repository/query/QueryParameterSetterFactory$ExpressionBasedQueryParameterSetterFactory;Lorg/springframework/expression/Expression;)Ljava/util/function/Function;
      28: aload_1
      29: aconst_null
      30: invokestatic  #13                 // Method org/springframework/data/jpa/repository/query/QueryParameterSetterFactory.access$000:(Ljava/util/function/Function;Lorg/springframework/data/jpa/repository/query/StringQuery$ParameterBinding;Lorg/springframework/data/jpa/repository/query/JpaParameters$JpaParameter;)Lorg/springframework/data/jpa/repository/query/QueryParameterSetter;
      33: areturn

  private java.lang.Object evaluateExpression(org.springframework.expression.Expression, java.lang.Object[]);
    Code:
       0: aload_0
       1: getfield      #6                  // Field evaluationContextProvider:Lorg/springframework/data/repository/query/QueryMethodEvaluationContextProvider;
       4: aload_0
       5: getfield      #8                  // Field parameters:Lorg/springframework/data/repository/query/Parameters;
       8: aload_2
       9: invokeinterface #14,  3           // InterfaceMethod org/springframework/data/repository/query/QueryMethodEvaluationContextProvider.getEvaluationContext:(Lorg/springframework/data/repository/query/Parameters;[Ljava/lang/Object;)Lorg/springframework/expression/EvaluationContext;
      14: astore_3
      15: aload_1
      16: aload_3
      17: ldc           #15                 // class java/lang/Object
      19: invokeinterface #16,  3           // InterfaceMethod org/springframework/expression/Expression.getValue:(Lorg/springframework/expression/EvaluationContext;Ljava/lang/Class;)Ljava/lang/Object;
      24: areturn

  private java.lang.Object lambda$create$0(org.springframework.expression.Expression, java.lang.Object[]);
    Code:
       0: aload_0
       1: aload_1
       2: aload_2
       3: invokespecial #17                 // Method evaluateExpression:(Lorg/springframework/expression/Expression;[Ljava/lang/Object;)Ljava/lang/Object;
       6: areturn
}
