Compiled from "Taints.java"
public class io.kubernetes.client.util.taints.Taints$TaintsBuilder {
  private io.kubernetes.client.openapi.models.V1Node node;

  io.kubernetes.client.util.taints.Taints$TaintsBuilder(io.kubernetes.client.openapi.models.V1Node);
    Code:
       0: aload_0
       1: invokespecial #1                  // Method java/lang/Object."<init>":()V
       4: aload_0
       5: aload_1
       6: putfield      #2                  // Field node:Lio/kubernetes/client/openapi/models/V1Node;
       9: return

  public io.kubernetes.client.util.taints.Taints$TaintsBuilder addTaint(java.lang.String, io.kubernetes.client.util.taints.Taints$Effect);
    Code:
       0: aload_0
       1: aload_1
       2: aconst_null
       3: aload_2
       4: invokevirtual #3                  // Method addTaint:(Ljava/lang/String;Ljava/lang/String;Lio/kubernetes/client/util/taints/Taints$Effect;)Lio/kubernetes/client/util/taints/Taints$TaintsBuilder;
       7: areturn

  public io.kubernetes.client.util.taints.Taints$TaintsBuilder addTaint(java.lang.String, java.lang.String, io.kubernetes.client.util.taints.Taints$Effect);
    Code:
       0: new           #4                  // class io/kubernetes/client/openapi/models/V1Taint
       3: dup
       4: invokespecial #5                  // Method io/kubernetes/client/openapi/models/V1Taint."<init>":()V
       7: astore        4
       9: aload         4
      11: aload_1
      12: invokevirtual #6                  // Method io/kubernetes/client/openapi/models/V1Taint.setKey:(Ljava/lang/String;)V
      15: aload         4
      17: aload_2
      18: invokevirtual #7                  // Method io/kubernetes/client/openapi/models/V1Taint.setValue:(Ljava/lang/String;)V
      21: aload         4
      23: aload_3
      24: invokevirtual #8                  // Method io/kubernetes/client/util/taints/Taints$Effect.toString:()Ljava/lang/String;
      27: invokevirtual #9                  // Method io/kubernetes/client/openapi/models/V1Taint.setEffect:(Ljava/lang/String;)V
      30: aload_0
      31: getfield      #2                  // Field node:Lio/kubernetes/client/openapi/models/V1Node;
      34: invokevirtual #10                 // Method io/kubernetes/client/openapi/models/V1Node.getSpec:()Lio/kubernetes/client/openapi/models/V1NodeSpec;
      37: ifnonnull     54
      40: aload_0
      41: getfield      #2                  // Field node:Lio/kubernetes/client/openapi/models/V1Node;
      44: new           #11                 // class io/kubernetes/client/openapi/models/V1NodeSpec
      47: dup
      48: invokespecial #12                 // Method io/kubernetes/client/openapi/models/V1NodeSpec."<init>":()V
      51: invokevirtual #13                 // Method io/kubernetes/client/openapi/models/V1Node.setSpec:(Lio/kubernetes/client/openapi/models/V1NodeSpec;)V
      54: aload_0
      55: getfield      #2                  // Field node:Lio/kubernetes/client/openapi/models/V1Node;
      58: invokevirtual #10                 // Method io/kubernetes/client/openapi/models/V1Node.getSpec:()Lio/kubernetes/client/openapi/models/V1NodeSpec;
      61: aload         4
      63: invokevirtual #14                 // Method io/kubernetes/client/openapi/models/V1NodeSpec.addTaintsItem:(Lio/kubernetes/client/openapi/models/V1Taint;)Lio/kubernetes/client/openapi/models/V1NodeSpec;
      66: pop
      67: aload_0
      68: areturn

  public io.kubernetes.client.util.taints.Taints$TaintsBuilder updateTaint(java.lang.String, java.lang.String, io.kubernetes.client.util.taints.Taints$Effect);
    Code:
       0: aload_0
       1: getfield      #2                  // Field node:Lio/kubernetes/client/openapi/models/V1Node;
       4: aload_1
       5: aload_3
       6: invokestatic  #15                 // Method io/kubernetes/client/util/taints/Taints.findTaint:(Lio/kubernetes/client/openapi/models/V1Node;Ljava/lang/String;Lio/kubernetes/client/util/taints/Taints$Effect;)Lio/kubernetes/client/openapi/models/V1Taint;
       9: astore        4
      11: aload         4
      13: aload_2
      14: invokevirtual #7                  // Method io/kubernetes/client/openapi/models/V1Taint.setValue:(Ljava/lang/String;)V
      17: aload_0
      18: areturn

  public io.kubernetes.client.util.taints.Taints$TaintsBuilder removeTaint(java.lang.String);
    Code:
       0: aload_0
       1: getfield      #2                  // Field node:Lio/kubernetes/client/openapi/models/V1Node;
       4: invokevirtual #10                 // Method io/kubernetes/client/openapi/models/V1Node.getSpec:()Lio/kubernetes/client/openapi/models/V1NodeSpec;
       7: ifnonnull     12
      10: aload_0
      11: areturn
      12: aload_0
      13: getfield      #2                  // Field node:Lio/kubernetes/client/openapi/models/V1Node;
      16: invokevirtual #10                 // Method io/kubernetes/client/openapi/models/V1Node.getSpec:()Lio/kubernetes/client/openapi/models/V1NodeSpec;
      19: invokevirtual #16                 // Method io/kubernetes/client/openapi/models/V1NodeSpec.getTaints:()Ljava/util/List;
      22: invokeinterface #17,  1           // InterfaceMethod java/util/List.iterator:()Ljava/util/Iterator;
      27: astore_2
      28: aload_2
      29: invokeinterface #18,  1           // InterfaceMethod java/util/Iterator.hasNext:()Z
      34: ifeq          67
      37: aload_2
      38: invokeinterface #19,  1           // InterfaceMethod java/util/Iterator.next:()Ljava/lang/Object;
      43: checkcast     #4                  // class io/kubernetes/client/openapi/models/V1Taint
      46: astore_3
      47: aload_3
      48: invokevirtual #20                 // Method io/kubernetes/client/openapi/models/V1Taint.getKey:()Ljava/lang/String;
      51: aload_1
      52: invokevirtual #21                 // Method java/lang/String.equals:(Ljava/lang/Object;)Z
      55: ifeq          64
      58: aload_2
      59: invokeinterface #22,  1           // InterfaceMethod java/util/Iterator.remove:()V
      64: goto          28
      67: aload_0
      68: areturn

  public io.kubernetes.client.util.taints.Taints$TaintsBuilder removeTaint(java.lang.String, io.kubernetes.client.util.taints.Taints$Effect);
    Code:
       0: aload_0
       1: getfield      #2                  // Field node:Lio/kubernetes/client/openapi/models/V1Node;
       4: invokevirtual #10                 // Method io/kubernetes/client/openapi/models/V1Node.getSpec:()Lio/kubernetes/client/openapi/models/V1NodeSpec;
       7: ifnonnull     12
      10: aload_0
      11: areturn
      12: aload_0
      13: getfield      #2                  // Field node:Lio/kubernetes/client/openapi/models/V1Node;
      16: invokevirtual #10                 // Method io/kubernetes/client/openapi/models/V1Node.getSpec:()Lio/kubernetes/client/openapi/models/V1NodeSpec;
      19: invokevirtual #16                 // Method io/kubernetes/client/openapi/models/V1NodeSpec.getTaints:()Ljava/util/List;
      22: invokeinterface #17,  1           // InterfaceMethod java/util/List.iterator:()Ljava/util/Iterator;
      27: astore_3
      28: aload_3
      29: invokeinterface #18,  1           // InterfaceMethod java/util/Iterator.hasNext:()Z
      34: ifeq          84
      37: aload_3
      38: invokeinterface #19,  1           // InterfaceMethod java/util/Iterator.next:()Ljava/lang/Object;
      43: checkcast     #4                  // class io/kubernetes/client/openapi/models/V1Taint
      46: astore        4
      48: aload         4
      50: invokevirtual #20                 // Method io/kubernetes/client/openapi/models/V1Taint.getKey:()Ljava/lang/String;
      53: aload_1
      54: invokevirtual #21                 // Method java/lang/String.equals:(Ljava/lang/Object;)Z
      57: ifeq          81
      60: aload         4
      62: invokevirtual #23                 // Method io/kubernetes/client/openapi/models/V1Taint.getEffect:()Ljava/lang/String;
      65: aload_2
      66: invokevirtual #8                  // Method io/kubernetes/client/util/taints/Taints$Effect.toString:()Ljava/lang/String;
      69: invokevirtual #21                 // Method java/lang/String.equals:(Ljava/lang/Object;)Z
      72: ifeq          81
      75: aload_3
      76: invokeinterface #22,  1           // InterfaceMethod java/util/Iterator.remove:()V
      81: goto          28
      84: aload_0
      85: areturn
}
