Compiled from "RpcClientFactoryPBImpl.java"
public class org.apache.hadoop.yarn.factories.impl.pb.RpcClientFactoryPBImpl implements org.apache.hadoop.yarn.factories.RpcClientFactory {
  private static final org.apache.commons.logging.Log LOG;

  private static final java.lang.String PB_IMPL_PACKAGE_SUFFIX;

  private static final java.lang.String PB_IMPL_CLASS_SUFFIX;

  private static final org.apache.hadoop.yarn.factories.impl.pb.RpcClientFactoryPBImpl self;

  private java.util.concurrent.ConcurrentMap<java.lang.Class<?>, java.lang.reflect.Constructor<?>> cache;

  public static org.apache.hadoop.yarn.factories.impl.pb.RpcClientFactoryPBImpl get();
    Code:
       0: getstatic     #1                  // Field self:Lorg/apache/hadoop/yarn/factories/impl/pb/RpcClientFactoryPBImpl;
       3: areturn

  private org.apache.hadoop.yarn.factories.impl.pb.RpcClientFactoryPBImpl();
    Code:
       0: aload_0
       1: invokespecial #2                  // Method java/lang/Object."<init>":()V
       4: aload_0
       5: new           #3                  // class java/util/concurrent/ConcurrentHashMap
       8: dup
       9: invokespecial #4                  // Method java/util/concurrent/ConcurrentHashMap."<init>":()V
      12: putfield      #5                  // Field cache:Ljava/util/concurrent/ConcurrentMap;
      15: return

  public java.lang.Object getClient(java.lang.Class<?>, long, java.net.InetSocketAddress, org.apache.hadoop.conf.Configuration);
    Code:
       0: aload_0
       1: getfield      #5                  // Field cache:Ljava/util/concurrent/ConcurrentMap;
       4: aload_1
       5: invokeinterface #6,  2            // InterfaceMethod java/util/concurrent/ConcurrentMap.get:(Ljava/lang/Object;)Ljava/lang/Object;
      10: checkcast     #7                  // class java/lang/reflect/Constructor
      13: astore        6
      15: aload         6
      17: ifnonnull     180
      20: aconst_null
      21: astore        7
      23: aload         5
      25: aload_0
      26: aload_1
      27: invokespecial #8                  // Method getPBImplClassName:(Ljava/lang/Class;)Ljava/lang/String;
      30: invokevirtual #9                  // Method org/apache/hadoop/conf/Configuration.getClassByName:(Ljava/lang/String;)Ljava/lang/Class;
      33: astore        7
      35: goto          78
      38: astore        8
      40: new           #11                 // class org/apache/hadoop/yarn/exceptions/YarnRuntimeException
      43: dup
      44: new           #12                 // class java/lang/StringBuilder
      47: dup
      48: invokespecial #13                 // Method java/lang/StringBuilder."<init>":()V
      51: ldc           #14                 // String Failed to load class: [
      53: invokevirtual #15                 // Method java/lang/StringBuilder.append:(Ljava/lang/String;)Ljava/lang/StringBuilder;
      56: aload_0
      57: aload_1
      58: invokespecial #8                  // Method getPBImplClassName:(Ljava/lang/Class;)Ljava/lang/String;
      61: invokevirtual #15                 // Method java/lang/StringBuilder.append:(Ljava/lang/String;)Ljava/lang/StringBuilder;
      64: ldc           #16                 // String ]
      66: invokevirtual #15                 // Method java/lang/StringBuilder.append:(Ljava/lang/String;)Ljava/lang/StringBuilder;
      69: invokevirtual #17                 // Method java/lang/StringBuilder.toString:()Ljava/lang/String;
      72: aload         8
      74: invokespecial #18                 // Method org/apache/hadoop/yarn/exceptions/YarnRuntimeException."<init>":(Ljava/lang/String;Ljava/lang/Throwable;)V
      77: athrow
      78: aload         7
      80: iconst_3
      81: anewarray     #19                 // class java/lang/Class
      84: dup
      85: iconst_0
      86: getstatic     #20                 // Field java/lang/Long.TYPE:Ljava/lang/Class;
      89: aastore
      90: dup
      91: iconst_1
      92: ldc           #21                 // class java/net/InetSocketAddress
      94: aastore
      95: dup
      96: iconst_2
      97: ldc           #22                 // class org/apache/hadoop/conf/Configuration
      99: aastore
     100: invokevirtual #23                 // Method java/lang/Class.getConstructor:([Ljava/lang/Class;)Ljava/lang/reflect/Constructor;
     103: astore        6
     105: aload         6
     107: iconst_1
     108: invokevirtual #24                 // Method java/lang/reflect/Constructor.setAccessible:(Z)V
     111: aload_0
     112: getfield      #5                  // Field cache:Ljava/util/concurrent/ConcurrentMap;
     115: aload_1
     116: aload         6
     118: invokeinterface #25,  3           // InterfaceMethod java/util/concurrent/ConcurrentMap.putIfAbsent:(Ljava/lang/Object;Ljava/lang/Object;)Ljava/lang/Object;
     123: pop
     124: goto          180
     127: astore        8
     129: new           #11                 // class org/apache/hadoop/yarn/exceptions/YarnRuntimeException
     132: dup
     133: new           #12                 // class java/lang/StringBuilder
     136: dup
     137: invokespecial #13                 // Method java/lang/StringBuilder."<init>":()V
     140: ldc           #27                 // String Could not find constructor with params:
     142: invokevirtual #15                 // Method java/lang/StringBuilder.append:(Ljava/lang/String;)Ljava/lang/StringBuilder;
     145: getstatic     #20                 // Field java/lang/Long.TYPE:Ljava/lang/Class;
     148: invokevirtual #28                 // Method java/lang/StringBuilder.append:(Ljava/lang/Object;)Ljava/lang/StringBuilder;
     151: ldc           #29                 // String ,
     153: invokevirtual #15                 // Method java/lang/StringBuilder.append:(Ljava/lang/String;)Ljava/lang/StringBuilder;
     156: ldc           #21                 // class java/net/InetSocketAddress
     158: invokevirtual #28                 // Method java/lang/StringBuilder.append:(Ljava/lang/Object;)Ljava/lang/StringBuilder;
     161: ldc           #29                 // String ,
     163: invokevirtual #15                 // Method java/lang/StringBuilder.append:(Ljava/lang/String;)Ljava/lang/StringBuilder;
     166: ldc           #22                 // class org/apache/hadoop/conf/Configuration
     168: invokevirtual #28                 // Method java/lang/StringBuilder.append:(Ljava/lang/Object;)Ljava/lang/StringBuilder;
     171: invokevirtual #17                 // Method java/lang/StringBuilder.toString:()Ljava/lang/String;
     174: aload         8
     176: invokespecial #18                 // Method org/apache/hadoop/yarn/exceptions/YarnRuntimeException."<init>":(Ljava/lang/String;Ljava/lang/Throwable;)V
     179: athrow
     180: aload         6
     182: iconst_3
     183: anewarray     #30                 // class java/lang/Object
     186: dup
     187: iconst_0
     188: lload_2
     189: invokestatic  #31                 // Method java/lang/Long.valueOf:(J)Ljava/lang/Long;
     192: aastore
     193: dup
     194: iconst_1
     195: aload         4
     197: aastore
     198: dup
     199: iconst_2
     200: aload         5
     202: aastore
     203: invokevirtual #32                 // Method java/lang/reflect/Constructor.newInstance:([Ljava/lang/Object;)Ljava/lang/Object;
     206: astore        7
     208: aload         7
     210: areturn
     211: astore        7
     213: new           #11                 // class org/apache/hadoop/yarn/exceptions/YarnRuntimeException
     216: dup
     217: aload         7
     219: invokespecial #34                 // Method org/apache/hadoop/yarn/exceptions/YarnRuntimeException."<init>":(Ljava/lang/Throwable;)V
     222: athrow
     223: astore        7
     225: new           #11                 // class org/apache/hadoop/yarn/exceptions/YarnRuntimeException
     228: dup
     229: aload         7
     231: invokespecial #34                 // Method org/apache/hadoop/yarn/exceptions/YarnRuntimeException."<init>":(Ljava/lang/Throwable;)V
     234: athrow
     235: astore        7
     237: new           #11                 // class org/apache/hadoop/yarn/exceptions/YarnRuntimeException
     240: dup
     241: aload         7
     243: invokespecial #34                 // Method org/apache/hadoop/yarn/exceptions/YarnRuntimeException."<init>":(Ljava/lang/Throwable;)V
     246: athrow
    Exception table:
       from    to  target type
          23    35    38   Class java/lang/ClassNotFoundException
          78   124   127   Class java/lang/NoSuchMethodException
         180   210   211   Class java/lang/reflect/InvocationTargetException
         180   210   223   Class java/lang/IllegalAccessException
         180   210   235   Class java/lang/InstantiationException

  public void stopClient(java.lang.Object);
    Code:
       0: aload_1
       1: instanceof    #37                 // class java/io/Closeable
       4: ifeq          17
       7: aload_1
       8: checkcast     #37                 // class java/io/Closeable
      11: invokeinterface #38,  1           // InterfaceMethod java/io/Closeable.close:()V
      16: return
      17: aload_1
      18: invokestatic  #39                 // Method java/lang/reflect/Proxy.getInvocationHandler:(Ljava/lang/Object;)Ljava/lang/reflect/InvocationHandler;
      21: astore_2
      22: aload_2
      23: instanceof    #37                 // class java/io/Closeable
      26: ifeq          39
      29: aload_2
      30: checkcast     #37                 // class java/io/Closeable
      33: invokeinterface #38,  1           // InterfaceMethod java/io/Closeable.close:()V
      38: return
      39: goto          63
      42: astore_2
      43: getstatic     #41                 // Field LOG:Lorg/apache/commons/logging/Log;
      46: ldc           #42                 // String Cannot call close method due to Exception. Ignoring.
      48: aload_2
      49: invokeinterface #43,  3           // InterfaceMethod org/apache/commons/logging/Log.error:(Ljava/lang/Object;Ljava/lang/Throwable;)V
      54: new           #11                 // class org/apache/hadoop/yarn/exceptions/YarnRuntimeException
      57: dup
      58: aload_2
      59: invokespecial #34                 // Method org/apache/hadoop/yarn/exceptions/YarnRuntimeException."<init>":(Ljava/lang/Throwable;)V
      62: athrow
      63: new           #44                 // class org/apache/hadoop/HadoopIllegalArgumentException
      66: dup
      67: new           #12                 // class java/lang/StringBuilder
      70: dup
      71: invokespecial #13                 // Method java/lang/StringBuilder."<init>":()V
      74: ldc           #45                 // String Cannot close proxy - is not Closeable or does not provide closeable invocation handler
      76: invokevirtual #15                 // Method java/lang/StringBuilder.append:(Ljava/lang/String;)Ljava/lang/StringBuilder;
      79: aload_1
      80: invokevirtual #46                 // Method java/lang/Object.getClass:()Ljava/lang/Class;
      83: invokevirtual #28                 // Method java/lang/StringBuilder.append:(Ljava/lang/Object;)Ljava/lang/StringBuilder;
      86: invokevirtual #17                 // Method java/lang/StringBuilder.toString:()Ljava/lang/String;
      89: invokespecial #47                 // Method org/apache/hadoop/HadoopIllegalArgumentException."<init>":(Ljava/lang/String;)V
      92: athrow
    Exception table:
       from    to  target type
           0    16    42   Class java/lang/Exception
          17    38    42   Class java/lang/Exception

  private java.lang.String getPBImplClassName(java.lang.Class<?>);
    Code:
       0: aload_0
       1: aload_1
       2: invokespecial #48                 // Method getPackageName:(Ljava/lang/Class;)Ljava/lang/String;
       5: astore_2
       6: aload_0
       7: aload_1
       8: invokespecial #49                 // Method getClassName:(Ljava/lang/Class;)Ljava/lang/String;
      11: astore_3
      12: new           #12                 // class java/lang/StringBuilder
      15: dup
      16: invokespecial #13                 // Method java/lang/StringBuilder."<init>":()V
      19: aload_2
      20: invokevirtual #15                 // Method java/lang/StringBuilder.append:(Ljava/lang/String;)Ljava/lang/StringBuilder;
      23: ldc           #50                 // String .
      25: invokevirtual #15                 // Method java/lang/StringBuilder.append:(Ljava/lang/String;)Ljava/lang/StringBuilder;
      28: ldc           #52                 // String impl.pb.client
      30: invokevirtual #15                 // Method java/lang/StringBuilder.append:(Ljava/lang/String;)Ljava/lang/StringBuilder;
      33: invokevirtual #17                 // Method java/lang/StringBuilder.toString:()Ljava/lang/String;
      36: astore        4
      38: new           #12                 // class java/lang/StringBuilder
      41: dup
      42: invokespecial #13                 // Method java/lang/StringBuilder."<init>":()V
      45: aload_3
      46: invokevirtual #15                 // Method java/lang/StringBuilder.append:(Ljava/lang/String;)Ljava/lang/StringBuilder;
      49: ldc           #53                 // String PBClientImpl
      51: invokevirtual #15                 // Method java/lang/StringBuilder.append:(Ljava/lang/String;)Ljava/lang/StringBuilder;
      54: invokevirtual #17                 // Method java/lang/StringBuilder.toString:()Ljava/lang/String;
      57: astore        5
      59: new           #12                 // class java/lang/StringBuilder
      62: dup
      63: invokespecial #13                 // Method java/lang/StringBuilder."<init>":()V
      66: aload         4
      68: invokevirtual #15                 // Method java/lang/StringBuilder.append:(Ljava/lang/String;)Ljava/lang/StringBuilder;
      71: ldc           #50                 // String .
      73: invokevirtual #15                 // Method java/lang/StringBuilder.append:(Ljava/lang/String;)Ljava/lang/StringBuilder;
      76: aload         5
      78: invokevirtual #15                 // Method java/lang/StringBuilder.append:(Ljava/lang/String;)Ljava/lang/StringBuilder;
      81: invokevirtual #17                 // Method java/lang/StringBuilder.toString:()Ljava/lang/String;
      84: areturn

  private java.lang.String getClassName(java.lang.Class<?>);
    Code:
       0: aload_1
       1: invokevirtual #54                 // Method java/lang/Class.getName:()Ljava/lang/String;
       4: astore_2
       5: aload_2
       6: aload_2
       7: ldc           #50                 // String .
       9: invokevirtual #55                 // Method java/lang/String.lastIndexOf:(Ljava/lang/String;)I
      12: iconst_1
      13: iadd
      14: aload_2
      15: invokevirtual #56                 // Method java/lang/String.length:()I
      18: invokevirtual #57                 // Method java/lang/String.substring:(II)Ljava/lang/String;
      21: areturn

  private java.lang.String getPackageName(java.lang.Class<?>);
    Code:
       0: aload_1
       1: invokevirtual #58                 // Method java/lang/Class.getPackage:()Ljava/lang/Package;
       4: invokevirtual #59                 // Method java/lang/Package.getName:()Ljava/lang/String;
       7: areturn

  static {};
    Code:
       0: ldc           #51                 // class org/apache/hadoop/yarn/factories/impl/pb/RpcClientFactoryPBImpl
       2: invokestatic  #60                 // Method org/apache/commons/logging/LogFactory.getLog:(Ljava/lang/Class;)Lorg/apache/commons/logging/Log;
       5: putstatic     #41                 // Field LOG:Lorg/apache/commons/logging/Log;
       8: new           #51                 // class org/apache/hadoop/yarn/factories/impl/pb/RpcClientFactoryPBImpl
      11: dup
      12: invokespecial #61                 // Method "<init>":()V
      15: putstatic     #1                  // Field self:Lorg/apache/hadoop/yarn/factories/impl/pb/RpcClientFactoryPBImpl;
      18: return
}
