Compiled from "AsyncFile.kt"
public final class io.vertx.kotlin.core.file.AsyncFileKt {
  public static final java.lang.Object writeAwait(io.vertx.core.file.AsyncFile, io.vertx.core.buffer.Buffer, kotlin.coroutines.Continuation<? super kotlin.Unit>);
    Code:
       0: new           #11                 // class io/vertx/kotlin/core/file/AsyncFileKt$writeAwait$2
       3: dup
       4: aload_0
       5: aload_1
       6: invokespecial #15                 // Method io/vertx/kotlin/core/file/AsyncFileKt$writeAwait$2."<init>":(Lio/vertx/core/file/AsyncFile;Lio/vertx/core/buffer/Buffer;)V
       9: checkcast     #17                 // class kotlin/jvm/functions/Function1
      12: aload_2
      13: invokestatic  #23                 // Method io/vertx/kotlin/coroutines/VertxCoroutineKt.awaitResult:(Lkotlin/jvm/functions/Function1;Lkotlin/coroutines/Continuation;)Ljava/lang/Object;
      16: areturn

  public static final java.lang.Object endAwait(io.vertx.core.file.AsyncFile, kotlin.coroutines.Continuation<? super kotlin.Unit>);
    Code:
       0: new           #34                 // class io/vertx/kotlin/core/file/AsyncFileKt$endAwait$2
       3: dup
       4: aload_0
       5: invokespecial #37                 // Method io/vertx/kotlin/core/file/AsyncFileKt$endAwait$2."<init>":(Lio/vertx/core/file/AsyncFile;)V
       8: checkcast     #17                 // class kotlin/jvm/functions/Function1
      11: aload_1
      12: invokestatic  #23                 // Method io/vertx/kotlin/coroutines/VertxCoroutineKt.awaitResult:(Lkotlin/jvm/functions/Function1;Lkotlin/coroutines/Continuation;)Ljava/lang/Object;
      15: areturn

  public static final java.lang.Object endAwait(io.vertx.core.file.AsyncFile, io.vertx.core.buffer.Buffer, kotlin.coroutines.Continuation<? super kotlin.Unit>);
    Code:
       0: new           #40                 // class io/vertx/kotlin/core/file/AsyncFileKt$endAwait$4
       3: dup
       4: aload_0
       5: aload_1
       6: invokespecial #41                 // Method io/vertx/kotlin/core/file/AsyncFileKt$endAwait$4."<init>":(Lio/vertx/core/file/AsyncFile;Lio/vertx/core/buffer/Buffer;)V
       9: checkcast     #17                 // class kotlin/jvm/functions/Function1
      12: aload_2
      13: invokestatic  #23                 // Method io/vertx/kotlin/coroutines/VertxCoroutineKt.awaitResult:(Lkotlin/jvm/functions/Function1;Lkotlin/coroutines/Continuation;)Ljava/lang/Object;
      16: areturn

  public static final java.lang.Object pipeToAwait(io.vertx.core.file.AsyncFile, io.vertx.core.streams.WriteStream<io.vertx.core.buffer.Buffer>, kotlin.coroutines.Continuation<? super kotlin.Unit>);
    Code:
       0: new           #46                 // class io/vertx/kotlin/core/file/AsyncFileKt$pipeToAwait$2
       3: dup
       4: aload_0
       5: aload_1
       6: invokespecial #49                 // Method io/vertx/kotlin/core/file/AsyncFileKt$pipeToAwait$2."<init>":(Lio/vertx/core/file/AsyncFile;Lio/vertx/core/streams/WriteStream;)V
       9: checkcast     #17                 // class kotlin/jvm/functions/Function1
      12: aload_2
      13: invokestatic  #23                 // Method io/vertx/kotlin/coroutines/VertxCoroutineKt.awaitResult:(Lkotlin/jvm/functions/Function1;Lkotlin/coroutines/Continuation;)Ljava/lang/Object;
      16: areturn

  public static final java.lang.Object closeAwait(io.vertx.core.file.AsyncFile, kotlin.coroutines.Continuation<? super kotlin.Unit>);
    Code:
       0: new           #55                 // class io/vertx/kotlin/core/file/AsyncFileKt$closeAwait$2
       3: dup
       4: aload_0
       5: invokespecial #56                 // Method io/vertx/kotlin/core/file/AsyncFileKt$closeAwait$2."<init>":(Lio/vertx/core/file/AsyncFile;)V
       8: checkcast     #17                 // class kotlin/jvm/functions/Function1
      11: aload_1
      12: invokestatic  #23                 // Method io/vertx/kotlin/coroutines/VertxCoroutineKt.awaitResult:(Lkotlin/jvm/functions/Function1;Lkotlin/coroutines/Continuation;)Ljava/lang/Object;
      15: areturn

  public static final java.lang.Object writeAwait(io.vertx.core.file.AsyncFile, io.vertx.core.buffer.Buffer, long, kotlin.coroutines.Continuation<? super kotlin.Unit>);
    Code:
       0: new           #61                 // class io/vertx/kotlin/core/file/AsyncFileKt$writeAwait$4
       3: dup
       4: aload_0
       5: aload_1
       6: lload_2
       7: invokespecial #64                 // Method io/vertx/kotlin/core/file/AsyncFileKt$writeAwait$4."<init>":(Lio/vertx/core/file/AsyncFile;Lio/vertx/core/buffer/Buffer;J)V
      10: checkcast     #17                 // class kotlin/jvm/functions/Function1
      13: aload         4
      15: invokestatic  #23                 // Method io/vertx/kotlin/coroutines/VertxCoroutineKt.awaitResult:(Lkotlin/jvm/functions/Function1;Lkotlin/coroutines/Continuation;)Ljava/lang/Object;
      18: areturn

  public static final java.lang.Object readAwait(io.vertx.core.file.AsyncFile, io.vertx.core.buffer.Buffer, int, long, int, kotlin.coroutines.Continuation<? super io.vertx.core.buffer.Buffer>);
    Code:
       0: new           #72                 // class io/vertx/kotlin/core/file/AsyncFileKt$readAwait$2
       3: dup
       4: aload_0
       5: aload_1
       6: iload_2
       7: lload_3
       8: iload         5
      10: invokespecial #75                 // Method io/vertx/kotlin/core/file/AsyncFileKt$readAwait$2."<init>":(Lio/vertx/core/file/AsyncFile;Lio/vertx/core/buffer/Buffer;IJI)V
      13: checkcast     #17                 // class kotlin/jvm/functions/Function1
      16: aload         6
      18: invokestatic  #23                 // Method io/vertx/kotlin/coroutines/VertxCoroutineKt.awaitResult:(Lkotlin/jvm/functions/Function1;Lkotlin/coroutines/Continuation;)Ljava/lang/Object;
      21: areturn

  public static final java.lang.Object flushAwait(io.vertx.core.file.AsyncFile, kotlin.coroutines.Continuation<? super kotlin.Unit>);
    Code:
       0: new           #82                 // class io/vertx/kotlin/core/file/AsyncFileKt$flushAwait$2
       3: dup
       4: aload_0
       5: invokespecial #83                 // Method io/vertx/kotlin/core/file/AsyncFileKt$flushAwait$2."<init>":(Lio/vertx/core/file/AsyncFile;)V
       8: checkcast     #17                 // class kotlin/jvm/functions/Function1
      11: aload_1
      12: invokestatic  #23                 // Method io/vertx/kotlin/coroutines/VertxCoroutineKt.awaitResult:(Lkotlin/jvm/functions/Function1;Lkotlin/coroutines/Continuation;)Ljava/lang/Object;
      15: areturn
}
