Compiled from "CopyOptions.kt"
public final class io.vertx.kotlin.core.file.CopyOptionsKt {
  public static final io.vertx.core.file.CopyOptions copyOptionsOf(java.lang.Boolean, java.lang.Boolean, java.lang.Boolean, java.lang.Boolean);
    Code:
       0: new           #10                 // class io/vertx/core/file/CopyOptions
       3: dup
       4: invokespecial #14                 // Method io/vertx/core/file/CopyOptions."<init>":()V
       7: astore        4
       9: iconst_0
      10: istore        5
      12: iconst_0
      13: istore        6
      15: aload         4
      17: astore        7
      19: iconst_0
      20: istore        8
      22: aload_0
      23: ifnull        36
      26: aload         7
      28: aload_0
      29: invokevirtual #20                 // Method java/lang/Boolean.booleanValue:()Z
      32: invokevirtual #24                 // Method io/vertx/core/file/CopyOptions.setAtomicMove:(Z)Lio/vertx/core/file/CopyOptions;
      35: pop
      36: aload_1
      37: ifnull        50
      40: aload         7
      42: aload_1
      43: invokevirtual #20                 // Method java/lang/Boolean.booleanValue:()Z
      46: invokevirtual #27                 // Method io/vertx/core/file/CopyOptions.setCopyAttributes:(Z)Lio/vertx/core/file/CopyOptions;
      49: pop
      50: aload_2
      51: ifnull        64
      54: aload         7
      56: aload_2
      57: invokevirtual #20                 // Method java/lang/Boolean.booleanValue:()Z
      60: invokevirtual #30                 // Method io/vertx/core/file/CopyOptions.setNofollowLinks:(Z)Lio/vertx/core/file/CopyOptions;
      63: pop
      64: aload_3
      65: ifnull        78
      68: aload         7
      70: aload_3
      71: invokevirtual #20                 // Method java/lang/Boolean.booleanValue:()Z
      74: invokevirtual #33                 // Method io/vertx/core/file/CopyOptions.setReplaceExisting:(Z)Lio/vertx/core/file/CopyOptions;
      77: pop
      78: nop
      79: aload         4
      81: areturn

  public static io.vertx.core.file.CopyOptions copyOptionsOf$default(java.lang.Boolean, java.lang.Boolean, java.lang.Boolean, java.lang.Boolean, int, java.lang.Object);
    Code:
       0: iload         4
       2: iconst_1
       3: iand
       4: ifeq          12
       7: aconst_null
       8: checkcast     #16                 // class java/lang/Boolean
      11: astore_0
      12: iload         4
      14: iconst_2
      15: iand
      16: ifeq          24
      19: aconst_null
      20: checkcast     #16                 // class java/lang/Boolean
      23: astore_1
      24: iload         4
      26: iconst_4
      27: iand
      28: ifeq          36
      31: aconst_null
      32: checkcast     #16                 // class java/lang/Boolean
      35: astore_2
      36: iload         4
      38: bipush        8
      40: iand
      41: ifeq          49
      44: aconst_null
      45: checkcast     #16                 // class java/lang/Boolean
      48: astore_3
      49: aload_0
      50: aload_1
      51: aload_2
      52: aload_3
      53: invokestatic  #46                 // Method copyOptionsOf:(Ljava/lang/Boolean;Ljava/lang/Boolean;Ljava/lang/Boolean;Ljava/lang/Boolean;)Lio/vertx/core/file/CopyOptions;
      56: areturn

  public static final io.vertx.core.file.CopyOptions CopyOptions(java.lang.Boolean, java.lang.Boolean, java.lang.Boolean, java.lang.Boolean);
    Code:
       0: new           #10                 // class io/vertx/core/file/CopyOptions
       3: dup
       4: invokespecial #14                 // Method io/vertx/core/file/CopyOptions."<init>":()V
       7: astore        4
       9: iconst_0
      10: istore        5
      12: iconst_0
      13: istore        6
      15: aload         4
      17: astore        7
      19: iconst_0
      20: istore        8
      22: aload_0
      23: ifnull        36
      26: aload         7
      28: aload_0
      29: invokevirtual #20                 // Method java/lang/Boolean.booleanValue:()Z
      32: invokevirtual #24                 // Method io/vertx/core/file/CopyOptions.setAtomicMove:(Z)Lio/vertx/core/file/CopyOptions;
      35: pop
      36: aload_1
      37: ifnull        50
      40: aload         7
      42: aload_1
      43: invokevirtual #20                 // Method java/lang/Boolean.booleanValue:()Z
      46: invokevirtual #27                 // Method io/vertx/core/file/CopyOptions.setCopyAttributes:(Z)Lio/vertx/core/file/CopyOptions;
      49: pop
      50: aload_2
      51: ifnull        64
      54: aload         7
      56: aload_2
      57: invokevirtual #20                 // Method java/lang/Boolean.booleanValue:()Z
      60: invokevirtual #30                 // Method io/vertx/core/file/CopyOptions.setNofollowLinks:(Z)Lio/vertx/core/file/CopyOptions;
      63: pop
      64: aload_3
      65: ifnull        78
      68: aload         7
      70: aload_3
      71: invokevirtual #20                 // Method java/lang/Boolean.booleanValue:()Z
      74: invokevirtual #33                 // Method io/vertx/core/file/CopyOptions.setReplaceExisting:(Z)Lio/vertx/core/file/CopyOptions;
      77: pop
      78: nop
      79: aload         4
      81: areturn

  public static io.vertx.core.file.CopyOptions CopyOptions$default(java.lang.Boolean, java.lang.Boolean, java.lang.Boolean, java.lang.Boolean, int, java.lang.Object);
    Code:
       0: iload         4
       2: iconst_1
       3: iand
       4: ifeq          12
       7: aconst_null
       8: checkcast     #16                 // class java/lang/Boolean
      11: astore_0
      12: iload         4
      14: iconst_2
      15: iand
      16: ifeq          24
      19: aconst_null
      20: checkcast     #16                 // class java/lang/Boolean
      23: astore_1
      24: iload         4
      26: iconst_4
      27: iand
      28: ifeq          36
      31: aconst_null
      32: checkcast     #16                 // class java/lang/Boolean
      35: astore_2
      36: iload         4
      38: bipush        8
      40: iand
      41: ifeq          49
      44: aconst_null
      45: checkcast     #16                 // class java/lang/Boolean
      48: astore_3
      49: aload_0
      50: aload_1
      51: aload_2
      52: aload_3
      53: invokestatic  #59                 // Method CopyOptions:(Ljava/lang/Boolean;Ljava/lang/Boolean;Ljava/lang/Boolean;Ljava/lang/Boolean;)Lio/vertx/core/file/CopyOptions;
      56: areturn
}
