Compiled from "WSRefAnnotationProcessor.java"
public class org.jboss.as.webservices.webserviceref.WSRefAnnotationProcessor implements org.jboss.as.server.deployment.DeploymentUnitProcessor {
  public org.jboss.as.webservices.webserviceref.WSRefAnnotationProcessor();
    Code:
       0: aload_0
       1: invokespecial #1                  // Method java/lang/Object."<init>":()V
       4: return

  public void deploy(org.jboss.as.server.deployment.DeploymentPhaseContext) throws org.jboss.as.server.deployment.DeploymentUnitProcessingException;
    Code:
       0: aload_1
       1: invokeinterface #2,  1            // InterfaceMethod org/jboss/as/server/deployment/DeploymentPhaseContext.getDeploymentUnit:()Lorg/jboss/as/server/deployment/DeploymentUnit;
       6: astore_2
       7: aload_2
       8: getstatic     #3                  // Field org/jboss/as/webservices/util/DotNames.WEB_SERVICE_REF_ANNOTATION:Lorg/jboss/jandex/DotName;
      11: invokestatic  #4                  // Method org/jboss/as/webservices/util/ASHelper.getAnnotations:(Lorg/jboss/as/server/deployment/DeploymentUnit;Lorg/jboss/jandex/DotName;)Ljava/util/List;
      14: astore_3
      15: aload_3
      16: invokeinterface #5,  1            // InterfaceMethod java/util/List.iterator:()Ljava/util/Iterator;
      21: astore        4
      23: aload         4
      25: invokeinterface #6,  1            // InterfaceMethod java/util/Iterator.hasNext:()Z
      30: ifeq          129
      33: aload         4
      35: invokeinterface #7,  1            // InterfaceMethod java/util/Iterator.next:()Ljava/lang/Object;
      40: checkcast     #8                  // class org/jboss/jandex/AnnotationInstance
      43: astore        5
      45: aload         5
      47: invokevirtual #9                  // Method org/jboss/jandex/AnnotationInstance.target:()Lorg/jboss/jandex/AnnotationTarget;
      50: astore        6
      52: new           #10                 // class org/jboss/as/webservices/webserviceref/WSRefAnnotationWrapper
      55: dup
      56: aload         5
      58: invokespecial #11                 // Method org/jboss/as/webservices/webserviceref/WSRefAnnotationWrapper."<init>":(Lorg/jboss/jandex/AnnotationInstance;)V
      61: astore        7
      63: aload         6
      65: instanceof    #12                 // class org/jboss/jandex/FieldInfo
      68: ifeq          85
      71: aload_2
      72: aload         7
      74: aload         6
      76: checkcast     #12                 // class org/jboss/jandex/FieldInfo
      79: invokestatic  #13                 // Method processFieldRef:(Lorg/jboss/as/server/deployment/DeploymentUnit;Lorg/jboss/as/webservices/webserviceref/WSRefAnnotationWrapper;Lorg/jboss/jandex/FieldInfo;)V
      82: goto          126
      85: aload         6
      87: instanceof    #14                 // class org/jboss/jandex/MethodInfo
      90: ifeq          107
      93: aload_2
      94: aload         7
      96: aload         6
      98: checkcast     #14                 // class org/jboss/jandex/MethodInfo
     101: invokestatic  #15                 // Method processMethodRef:(Lorg/jboss/as/server/deployment/DeploymentUnit;Lorg/jboss/as/webservices/webserviceref/WSRefAnnotationWrapper;Lorg/jboss/jandex/MethodInfo;)V
     104: goto          126
     107: aload         6
     109: instanceof    #16                 // class org/jboss/jandex/ClassInfo
     112: ifeq          126
     115: aload_2
     116: aload         7
     118: aload         6
     120: checkcast     #16                 // class org/jboss/jandex/ClassInfo
     123: invokestatic  #17                 // Method processClassRef:(Lorg/jboss/as/server/deployment/DeploymentUnit;Lorg/jboss/as/webservices/webserviceref/WSRefAnnotationWrapper;Lorg/jboss/jandex/ClassInfo;)V
     126: goto          23
     129: aload_2
     130: getstatic     #18                 // Field org/jboss/as/webservices/util/DotNames.WEB_SERVICE_REFS_ANNOTATION:Lorg/jboss/jandex/DotName;
     133: invokestatic  #4                  // Method org/jboss/as/webservices/util/ASHelper.getAnnotations:(Lorg/jboss/as/server/deployment/DeploymentUnit;Lorg/jboss/jandex/DotName;)Ljava/util/List;
     136: astore        4
     138: aload         4
     140: invokeinterface #5,  1            // InterfaceMethod java/util/List.iterator:()Ljava/util/Iterator;
     145: astore        5
     147: aload         5
     149: invokeinterface #6,  1            // InterfaceMethod java/util/Iterator.hasNext:()Z
     154: ifeq          253
     157: aload         5
     159: invokeinterface #7,  1            // InterfaceMethod java/util/Iterator.next:()Ljava/lang/Object;
     164: checkcast     #8                  // class org/jboss/jandex/AnnotationInstance
     167: astore        6
     169: aload         6
     171: invokevirtual #9                  // Method org/jboss/jandex/AnnotationInstance.target:()Lorg/jboss/jandex/AnnotationTarget;
     174: astore        7
     176: aload         7
     178: instanceof    #16                 // class org/jboss/jandex/ClassInfo
     181: ifeq          250
     184: aload         6
     186: ldc           #19                 // String value
     188: invokevirtual #20                 // Method org/jboss/jandex/AnnotationInstance.value:(Ljava/lang/String;)Lorg/jboss/jandex/AnnotationValue;
     191: invokevirtual #21                 // Method org/jboss/jandex/AnnotationValue.asNestedArray:()[Lorg/jboss/jandex/AnnotationInstance;
     194: astore        8
     196: aload         8
     198: astore        9
     200: aload         9
     202: arraylength
     203: istore        10
     205: iconst_0
     206: istore        11
     208: iload         11
     210: iload         10
     212: if_icmpge     250
     215: aload         9
     217: iload         11
     219: aaload
     220: astore        12
     222: new           #10                 // class org/jboss/as/webservices/webserviceref/WSRefAnnotationWrapper
     225: dup
     226: aload         12
     228: invokespecial #11                 // Method org/jboss/as/webservices/webserviceref/WSRefAnnotationWrapper."<init>":(Lorg/jboss/jandex/AnnotationInstance;)V
     231: astore        13
     233: aload_2
     234: aload         13
     236: aload         7
     238: checkcast     #16                 // class org/jboss/jandex/ClassInfo
     241: invokestatic  #17                 // Method processClassRef:(Lorg/jboss/as/server/deployment/DeploymentUnit;Lorg/jboss/as/webservices/webserviceref/WSRefAnnotationWrapper;Lorg/jboss/jandex/ClassInfo;)V
     244: iinc          11, 1
     247: goto          208
     250: goto          147
     253: return

  public void undeploy(org.jboss.as.server.deployment.DeploymentUnit);
    Code:
       0: return

  private static void processFieldRef(org.jboss.as.server.deployment.DeploymentUnit, org.jboss.as.webservices.webserviceref.WSRefAnnotationWrapper, org.jboss.jandex.FieldInfo) throws org.jboss.as.server.deployment.DeploymentUnitProcessingException;
    Code:
       0: aload_2
       1: invokevirtual #22                 // Method org/jboss/jandex/FieldInfo.name:()Ljava/lang/String;
       4: astore_3
       5: aload_1
       6: invokevirtual #23                 // Method org/jboss/as/webservices/webserviceref/WSRefAnnotationWrapper.type:()Ljava/lang/String;
       9: invokestatic  #24                 // Method isEmpty:(Ljava/lang/String;)Z
      12: ifne          30
      15: aload_1
      16: invokevirtual #23                 // Method org/jboss/as/webservices/webserviceref/WSRefAnnotationWrapper.type:()Ljava/lang/String;
      19: ldc           #25                 // class java/lang/Object
      21: invokevirtual #26                 // Method java/lang/Class.getName:()Ljava/lang/String;
      24: invokevirtual #27                 // Method java/lang/String.equals:(Ljava/lang/Object;)Z
      27: ifeq          43
      30: aload_2
      31: invokevirtual #28                 // Method org/jboss/jandex/FieldInfo.type:()Lorg/jboss/jandex/Type;
      34: invokevirtual #29                 // Method org/jboss/jandex/Type.name:()Lorg/jboss/jandex/DotName;
      37: invokevirtual #30                 // Method org/jboss/jandex/DotName.toString:()Ljava/lang/String;
      40: goto          47
      43: aload_1
      44: invokevirtual #23                 // Method org/jboss/as/webservices/webserviceref/WSRefAnnotationWrapper.type:()Ljava/lang/String;
      47: astore        4
      49: new           #31                 // class org/jboss/as/ee/component/FieldInjectionTarget
      52: dup
      53: aload_2
      54: invokevirtual #32                 // Method org/jboss/jandex/FieldInfo.declaringClass:()Lorg/jboss/jandex/ClassInfo;
      57: invokevirtual #33                 // Method org/jboss/jandex/ClassInfo.name:()Lorg/jboss/jandex/DotName;
      60: invokevirtual #30                 // Method org/jboss/jandex/DotName.toString:()Ljava/lang/String;
      63: aload_3
      64: aload         4
      66: invokespecial #34                 // Method org/jboss/as/ee/component/FieldInjectionTarget."<init>":(Ljava/lang/String;Ljava/lang/String;Ljava/lang/String;)V
      69: astore        5
      71: aload_1
      72: invokevirtual #35                 // Method org/jboss/as/webservices/webserviceref/WSRefAnnotationWrapper.name:()Ljava/lang/String;
      75: invokestatic  #24                 // Method isEmpty:(Ljava/lang/String;)Z
      78: ifeq          119
      81: new           #36                 // class java/lang/StringBuilder
      84: dup
      85: invokespecial #37                 // Method java/lang/StringBuilder."<init>":()V
      88: aload_2
      89: invokevirtual #32                 // Method org/jboss/jandex/FieldInfo.declaringClass:()Lorg/jboss/jandex/ClassInfo;
      92: invokevirtual #33                 // Method org/jboss/jandex/ClassInfo.name:()Lorg/jboss/jandex/DotName;
      95: invokevirtual #30                 // Method org/jboss/jandex/DotName.toString:()Ljava/lang/String;
      98: invokevirtual #38                 // Method java/lang/StringBuilder.append:(Ljava/lang/String;)Ljava/lang/StringBuilder;
     101: ldc           #39                 // String /
     103: invokevirtual #38                 // Method java/lang/StringBuilder.append:(Ljava/lang/String;)Ljava/lang/StringBuilder;
     106: aload_2
     107: invokevirtual #22                 // Method org/jboss/jandex/FieldInfo.name:()Ljava/lang/String;
     110: invokevirtual #38                 // Method java/lang/StringBuilder.append:(Ljava/lang/String;)Ljava/lang/StringBuilder;
     113: invokevirtual #40                 // Method java/lang/StringBuilder.toString:()Ljava/lang/String;
     116: goto          123
     119: aload_1
     120: invokevirtual #35                 // Method org/jboss/as/webservices/webserviceref/WSRefAnnotationWrapper.name:()Ljava/lang/String;
     123: astore        6
     125: aload_0
     126: aload         4
     128: aload_1
     129: aload_2
     130: invokevirtual #32                 // Method org/jboss/jandex/FieldInfo.declaringClass:()Lorg/jboss/jandex/ClassInfo;
     133: aload         5
     135: aload         6
     137: invokestatic  #41                 // Method processRef:(Lorg/jboss/as/server/deployment/DeploymentUnit;Ljava/lang/String;Lorg/jboss/as/webservices/webserviceref/WSRefAnnotationWrapper;Lorg/jboss/jandex/ClassInfo;Lorg/jboss/as/ee/component/InjectionTarget;Ljava/lang/String;)V
     140: return

  private static void processMethodRef(org.jboss.as.server.deployment.DeploymentUnit, org.jboss.as.webservices.webserviceref.WSRefAnnotationWrapper, org.jboss.jandex.MethodInfo) throws org.jboss.as.server.deployment.DeploymentUnitProcessingException;
    Code:
       0: aload_2
       1: invokevirtual #42                 // Method org/jboss/jandex/MethodInfo.name:()Ljava/lang/String;
       4: astore_3
       5: aload_3
       6: ldc           #43                 // String set
       8: invokevirtual #44                 // Method java/lang/String.startsWith:(Ljava/lang/String;)Z
      11: ifeq          23
      14: aload_2
      15: invokevirtual #45                 // Method org/jboss/jandex/MethodInfo.args:()[Lorg/jboss/jandex/Type;
      18: arraylength
      19: iconst_1
      20: if_icmpeq     33
      23: getstatic     #46                 // Field org/jboss/as/webservices/logging/WSLogger.ROOT_LOGGER:Lorg/jboss/as/webservices/logging/WSLogger;
      26: aload_2
      27: invokeinterface #47,  2           // InterfaceMethod org/jboss/as/webservices/logging/WSLogger.invalidServiceRefSetterMethodName:(Ljava/lang/Object;)Lorg/jboss/as/server/deployment/DeploymentUnitProcessingException;
      32: athrow
      33: aload_1
      34: invokevirtual #23                 // Method org/jboss/as/webservices/webserviceref/WSRefAnnotationWrapper.type:()Ljava/lang/String;
      37: invokestatic  #24                 // Method isEmpty:(Ljava/lang/String;)Z
      40: ifne          58
      43: aload_1
      44: invokevirtual #23                 // Method org/jboss/as/webservices/webserviceref/WSRefAnnotationWrapper.type:()Ljava/lang/String;
      47: ldc           #25                 // class java/lang/Object
      49: invokevirtual #26                 // Method java/lang/Class.getName:()Ljava/lang/String;
      52: invokevirtual #27                 // Method java/lang/String.equals:(Ljava/lang/Object;)Z
      55: ifeq          73
      58: aload_2
      59: invokevirtual #45                 // Method org/jboss/jandex/MethodInfo.args:()[Lorg/jboss/jandex/Type;
      62: iconst_0
      63: aaload
      64: invokevirtual #29                 // Method org/jboss/jandex/Type.name:()Lorg/jboss/jandex/DotName;
      67: invokevirtual #30                 // Method org/jboss/jandex/DotName.toString:()Ljava/lang/String;
      70: goto          77
      73: aload_1
      74: invokevirtual #23                 // Method org/jboss/as/webservices/webserviceref/WSRefAnnotationWrapper.type:()Ljava/lang/String;
      77: astore        4
      79: new           #48                 // class org/jboss/as/ee/component/MethodInjectionTarget
      82: dup
      83: aload_2
      84: invokevirtual #49                 // Method org/jboss/jandex/MethodInfo.declaringClass:()Lorg/jboss/jandex/ClassInfo;
      87: invokevirtual #33                 // Method org/jboss/jandex/ClassInfo.name:()Lorg/jboss/jandex/DotName;
      90: invokevirtual #30                 // Method org/jboss/jandex/DotName.toString:()Ljava/lang/String;
      93: aload_3
      94: aload         4
      96: invokespecial #50                 // Method org/jboss/as/ee/component/MethodInjectionTarget."<init>":(Ljava/lang/String;Ljava/lang/String;Ljava/lang/String;)V
      99: astore        5
     101: aload_1
     102: invokevirtual #35                 // Method org/jboss/as/webservices/webserviceref/WSRefAnnotationWrapper.name:()Ljava/lang/String;
     105: invokestatic  #24                 // Method isEmpty:(Ljava/lang/String;)Z
     108: ifeq          165
     111: new           #36                 // class java/lang/StringBuilder
     114: dup
     115: invokespecial #37                 // Method java/lang/StringBuilder."<init>":()V
     118: aload_2
     119: invokevirtual #49                 // Method org/jboss/jandex/MethodInfo.declaringClass:()Lorg/jboss/jandex/ClassInfo;
     122: invokevirtual #33                 // Method org/jboss/jandex/ClassInfo.name:()Lorg/jboss/jandex/DotName;
     125: invokevirtual #30                 // Method org/jboss/jandex/DotName.toString:()Ljava/lang/String;
     128: invokevirtual #38                 // Method java/lang/StringBuilder.append:(Ljava/lang/String;)Ljava/lang/StringBuilder;
     131: ldc           #39                 // String /
     133: invokevirtual #38                 // Method java/lang/StringBuilder.append:(Ljava/lang/String;)Ljava/lang/StringBuilder;
     136: aload_3
     137: iconst_3
     138: iconst_4
     139: invokevirtual #51                 // Method java/lang/String.substring:(II)Ljava/lang/String;
     142: getstatic     #52                 // Field java/util/Locale.ENGLISH:Ljava/util/Locale;
     145: invokevirtual #53                 // Method java/lang/String.toLowerCase:(Ljava/util/Locale;)Ljava/lang/String;
     148: invokevirtual #38                 // Method java/lang/StringBuilder.append:(Ljava/lang/String;)Ljava/lang/StringBuilder;
     151: aload_3
     152: iconst_4
     153: invokevirtual #54                 // Method java/lang/String.substring:(I)Ljava/lang/String;
     156: invokevirtual #38                 // Method java/lang/StringBuilder.append:(Ljava/lang/String;)Ljava/lang/StringBuilder;
     159: invokevirtual #40                 // Method java/lang/StringBuilder.toString:()Ljava/lang/String;
     162: goto          169
     165: aload_1
     166: invokevirtual #35                 // Method org/jboss/as/webservices/webserviceref/WSRefAnnotationWrapper.name:()Ljava/lang/String;
     169: astore        6
     171: aload_0
     172: aload         4
     174: aload_1
     175: aload_2
     176: invokevirtual #49                 // Method org/jboss/jandex/MethodInfo.declaringClass:()Lorg/jboss/jandex/ClassInfo;
     179: aload         5
     181: aload         6
     183: invokestatic  #41                 // Method processRef:(Lorg/jboss/as/server/deployment/DeploymentUnit;Ljava/lang/String;Lorg/jboss/as/webservices/webserviceref/WSRefAnnotationWrapper;Lorg/jboss/jandex/ClassInfo;Lorg/jboss/as/ee/component/InjectionTarget;Ljava/lang/String;)V
     186: return

  private static void processClassRef(org.jboss.as.server.deployment.DeploymentUnit, org.jboss.as.webservices.webserviceref.WSRefAnnotationWrapper, org.jboss.jandex.ClassInfo) throws org.jboss.as.server.deployment.DeploymentUnitProcessingException;
    Code:
       0: aload_1
       1: invokevirtual #35                 // Method org/jboss/as/webservices/webserviceref/WSRefAnnotationWrapper.name:()Ljava/lang/String;
       4: invokestatic  #24                 // Method isEmpty:(Ljava/lang/String;)Z
       7: ifeq          19
      10: getstatic     #46                 // Field org/jboss/as/webservices/logging/WSLogger.ROOT_LOGGER:Lorg/jboss/as/webservices/logging/WSLogger;
      13: invokeinterface #55,  1           // InterfaceMethod org/jboss/as/webservices/logging/WSLogger.requiredServiceRefName:()Lorg/jboss/as/server/deployment/DeploymentUnitProcessingException;
      18: athrow
      19: aload_1
      20: invokevirtual #23                 // Method org/jboss/as/webservices/webserviceref/WSRefAnnotationWrapper.type:()Ljava/lang/String;
      23: invokestatic  #24                 // Method isEmpty:(Ljava/lang/String;)Z
      26: ifeq          38
      29: getstatic     #46                 // Field org/jboss/as/webservices/logging/WSLogger.ROOT_LOGGER:Lorg/jboss/as/webservices/logging/WSLogger;
      32: invokeinterface #56,  1           // InterfaceMethod org/jboss/as/webservices/logging/WSLogger.requiredServiceRefType:()Lorg/jboss/as/server/deployment/DeploymentUnitProcessingException;
      37: athrow
      38: aload_0
      39: aload_1
      40: invokevirtual #23                 // Method org/jboss/as/webservices/webserviceref/WSRefAnnotationWrapper.type:()Ljava/lang/String;
      43: aload_1
      44: aload_2
      45: aconst_null
      46: aload_1
      47: invokevirtual #35                 // Method org/jboss/as/webservices/webserviceref/WSRefAnnotationWrapper.name:()Ljava/lang/String;
      50: invokestatic  #41                 // Method processRef:(Lorg/jboss/as/server/deployment/DeploymentUnit;Ljava/lang/String;Lorg/jboss/as/webservices/webserviceref/WSRefAnnotationWrapper;Lorg/jboss/jandex/ClassInfo;Lorg/jboss/as/ee/component/InjectionTarget;Ljava/lang/String;)V
      53: return

  private static void processRef(org.jboss.as.server.deployment.DeploymentUnit, java.lang.String, org.jboss.as.webservices.webserviceref.WSRefAnnotationWrapper, org.jboss.jandex.ClassInfo, org.jboss.as.ee.component.InjectionTarget, java.lang.String) throws org.jboss.as.server.deployment.DeploymentUnitProcessingException;
    Code:
       0: aload_0
       1: getstatic     #57                 // Field org/jboss/as/ee/component/Attachments.EE_MODULE_DESCRIPTION:Lorg/jboss/as/server/deployment/AttachmentKey;
       4: invokeinterface #58,  2           // InterfaceMethod org/jboss/as/server/deployment/DeploymentUnit.getAttachment:(Lorg/jboss/as/server/deployment/AttachmentKey;)Ljava/lang/Object;
       9: checkcast     #59                 // class org/jboss/as/ee/component/EEModuleDescription
      12: astore        6
      14: aload_0
      15: aload_3
      16: aload         4
      18: invokestatic  #60                 // Method createAnnotatedElement:(Lorg/jboss/as/server/deployment/DeploymentUnit;Lorg/jboss/jandex/ClassInfo;Lorg/jboss/as/ee/component/InjectionTarget;)Ljava/lang/reflect/AnnotatedElement;
      21: astore        7
      23: aload_3
      24: invokevirtual #33                 // Method org/jboss/jandex/ClassInfo.name:()Lorg/jboss/jandex/DotName;
      27: invokevirtual #30                 // Method org/jboss/jandex/DotName.toString:()Ljava/lang/String;
      30: astore        8
      32: new           #61                 // class java/util/HashMap
      35: dup
      36: invokespecial #62                 // Method java/util/HashMap."<init>":()V
      39: astore        9
      41: iconst_0
      42: istore        10
      44: aload         6
      46: aload         8
      48: invokevirtual #63                 // Method org/jboss/as/ee/component/EEModuleDescription.getComponentsByClassName:(Ljava/lang/String;)Ljava/util/List;
      51: invokeinterface #5,  1            // InterfaceMethod java/util/List.iterator:()Ljava/util/Iterator;
      56: astore        11
      58: aload         11
      60: invokeinterface #6,  1            // InterfaceMethod java/util/Iterator.hasNext:()Z
      65: ifeq          132
      68: aload         11
      70: invokeinterface #7,  1            // InterfaceMethod java/util/Iterator.next:()Ljava/lang/Object;
      75: checkcast     #64                 // class org/jboss/as/ee/component/ComponentDescription
      78: astore        12
      80: aload         12
      82: instanceof    #65                 // class org/jboss/as/ejb3/component/session/SessionBeanComponentDescription
      85: ifeq          129
      88: iconst_1
      89: istore        10
      91: aload         9
      93: new           #36                 // class java/lang/StringBuilder
      96: dup
      97: invokespecial #37                 // Method java/lang/StringBuilder."<init>":()V
     100: aload         12
     102: invokevirtual #66                 // Method org/jboss/as/ee/component/ComponentDescription.getComponentName:()Ljava/lang/String;
     105: invokevirtual #38                 // Method java/lang/StringBuilder.append:(Ljava/lang/String;)Ljava/lang/StringBuilder;
     108: ldc           #39                 // String /
     110: invokevirtual #38                 // Method java/lang/StringBuilder.append:(Ljava/lang/String;)Ljava/lang/StringBuilder;
     113: aload         5
     115: invokevirtual #38                 // Method java/lang/StringBuilder.append:(Ljava/lang/String;)Ljava/lang/StringBuilder;
     118: invokevirtual #40                 // Method java/lang/StringBuilder.toString:()Ljava/lang/String;
     121: aload         5
     123: invokeinterface #67,  3           // InterfaceMethod java/util/Map.put:(Ljava/lang/Object;Ljava/lang/Object;)Ljava/lang/Object;
     128: pop
     129: goto          58
     132: iload         10
     134: ifne          149
     137: aload         9
     139: aload         5
     141: aload         5
     143: invokeinterface #67,  3           // InterfaceMethod java/util/Map.put:(Ljava/lang/Object;Ljava/lang/Object;)Ljava/lang/Object;
     148: pop
     149: aload         9
     151: invokeinterface #68,  1           // InterfaceMethod java/util/Map.keySet:()Ljava/util/Set;
     156: invokeinterface #69,  1           // InterfaceMethod java/util/Set.iterator:()Ljava/util/Iterator;
     161: astore        11
     163: aload         11
     165: invokeinterface #6,  1            // InterfaceMethod java/util/Iterator.hasNext:()Z
     170: ifeq          310
     173: aload         11
     175: invokeinterface #7,  1            // InterfaceMethod java/util/Iterator.next:()Ljava/lang/Object;
     180: checkcast     #70                 // class java/lang/String
     183: astore        12
     185: aload         9
     187: aload         12
     189: invokeinterface #71,  2           // InterfaceMethod java/util/Map.get:(Ljava/lang/Object;)Ljava/lang/Object;
     194: checkcast     #70                 // class java/lang/String
     197: astore        13
     199: aload_0
     200: aload_1
     201: aload_2
     202: aload         7
     204: aload         13
     206: aload         12
     208: invokestatic  #72                 // Method org/jboss/as/webservices/webserviceref/WebServiceReferences.createWebServiceFactory:(Lorg/jboss/as/server/deployment/DeploymentUnit;Ljava/lang/String;Lorg/jboss/as/webservices/webserviceref/WSRefAnnotationWrapper;Ljava/lang/reflect/AnnotatedElement;Ljava/lang/String;Ljava/lang/String;)Lorg/jboss/as/naming/ManagedReferenceFactory;
     211: astore        14
     213: aload         6
     215: aload_3
     216: invokevirtual #33                 // Method org/jboss/jandex/ClassInfo.name:()Lorg/jboss/jandex/DotName;
     219: invokevirtual #30                 // Method org/jboss/jandex/DotName.toString:()Ljava/lang/String;
     222: invokevirtual #73                 // Method org/jboss/as/ee/component/EEModuleDescription.addOrGetLocalClassDescription:(Ljava/lang/String;)Lorg/jboss/as/ee/component/EEModuleClassDescription;
     225: astore        15
     227: new           #74                 // class org/jboss/as/ee/component/FixedInjectionSource
     230: dup
     231: aload         14
     233: aload         14
     235: invokespecial #75                 // Method org/jboss/as/ee/component/FixedInjectionSource."<init>":(Lorg/jboss/as/naming/ManagedReferenceFactory;Ljava/lang/Object;)V
     238: astore        16
     240: new           #76                 // class org/jboss/as/ee/component/BindingConfiguration
     243: dup
     244: aload         13
     246: aload         16
     248: invokespecial #77                 // Method org/jboss/as/ee/component/BindingConfiguration."<init>":(Ljava/lang/String;Lorg/jboss/as/ee/component/InjectionSource;)V
     251: astore        17
     253: aload         15
     255: invokevirtual #78                 // Method org/jboss/as/ee/component/EEModuleClassDescription.getBindingConfigurations:()Ljava/util/List;
     258: aload         17
     260: invokeinterface #79,  2           // InterfaceMethod java/util/List.add:(Ljava/lang/Object;)Z
     265: pop
     266: aload         4
     268: ifnull        292
     271: new           #80                 // class org/jboss/as/ee/component/ResourceInjectionConfiguration
     274: dup
     275: aload         4
     277: new           #81                 // class org/jboss/as/ee/component/LookupInjectionSource
     280: dup
     281: aload         13
     283: invokespecial #82                 // Method org/jboss/as/ee/component/LookupInjectionSource."<init>":(Ljava/lang/String;)V
     286: invokespecial #83                 // Method org/jboss/as/ee/component/ResourceInjectionConfiguration."<init>":(Lorg/jboss/as/ee/component/InjectionTarget;Lorg/jboss/as/ee/component/InjectionSource;)V
     289: goto          293
     292: aconst_null
     293: astore        18
     295: aload         18
     297: ifnull        307
     300: aload         15
     302: aload         18
     304: invokevirtual #84                 // Method org/jboss/as/ee/component/EEModuleClassDescription.addResourceInjection:(Lorg/jboss/as/ee/component/ResourceInjectionConfiguration;)V
     307: goto          163
     310: return

  private static java.lang.reflect.AnnotatedElement createAnnotatedElement(org.jboss.as.server.deployment.DeploymentUnit, org.jboss.jandex.ClassInfo, org.jboss.as.ee.component.InjectionTarget) throws org.jboss.as.server.deployment.DeploymentUnitProcessingException;
    Code:
       0: aload_2
       1: ifnonnull     10
       4: aload_0
       5: aload_1
       6: invokestatic  #85                 // Method elementForInjectionTarget:(Lorg/jboss/as/server/deployment/DeploymentUnit;Lorg/jboss/jandex/ClassInfo;)Ljava/lang/reflect/AnnotatedElement;
       9: areturn
      10: aload_0
      11: aload_2
      12: invokestatic  #86                 // Method elementForInjectionTarget:(Lorg/jboss/as/server/deployment/DeploymentUnit;Lorg/jboss/as/ee/component/InjectionTarget;)Ljava/lang/reflect/AnnotatedElement;
      15: areturn

  private static java.lang.reflect.AnnotatedElement elementForInjectionTarget(org.jboss.as.server.deployment.DeploymentUnit, org.jboss.jandex.ClassInfo) throws org.jboss.as.server.deployment.DeploymentUnitProcessingException;
    Code:
       0: aload_0
       1: aload_1
       2: invokevirtual #33                 // Method org/jboss/jandex/ClassInfo.name:()Lorg/jboss/jandex/DotName;
       5: invokevirtual #30                 // Method org/jboss/jandex/DotName.toString:()Ljava/lang/String;
       8: invokestatic  #87                 // Method getClass:(Lorg/jboss/as/server/deployment/DeploymentUnit;Ljava/lang/String;)Ljava/lang/Class;
      11: astore_2
      12: aload_2
      13: areturn

  private static java.lang.reflect.AnnotatedElement elementForInjectionTarget(org.jboss.as.server.deployment.DeploymentUnit, org.jboss.as.ee.component.InjectionTarget) throws org.jboss.as.server.deployment.DeploymentUnitProcessingException;
    Code:
       0: aload_0
       1: getstatic     #88                 // Field org/jboss/as/server/deployment/Attachments.MODULE:Lorg/jboss/as/server/deployment/AttachmentKey;
       4: invokeinterface #58,  2           // InterfaceMethod org/jboss/as/server/deployment/DeploymentUnit.getAttachment:(Lorg/jboss/as/server/deployment/AttachmentKey;)Ljava/lang/Object;
       9: checkcast     #89                 // class org/jboss/modules/Module
      12: astore_2
      13: aload_0
      14: getstatic     #90                 // Field org/jboss/as/server/deployment/Attachments.REFLECTION_INDEX:Lorg/jboss/as/server/deployment/AttachmentKey;
      17: invokeinterface #58,  2           // InterfaceMethod org/jboss/as/server/deployment/DeploymentUnit.getAttachment:(Lorg/jboss/as/server/deployment/AttachmentKey;)Ljava/lang/Object;
      22: checkcast     #91                 // class org/jboss/as/server/deployment/reflect/DeploymentReflectionIndex
      25: astore_3
      26: aload_1
      27: invokevirtual #92                 // Method org/jboss/as/ee/component/InjectionTarget.getClassName:()Ljava/lang/String;
      30: astore        4
      32: aload_1
      33: invokestatic  #93                 // Method getInjectionTargetName:(Lorg/jboss/as/ee/component/InjectionTarget;)Ljava/lang/String;
      36: astore        5
      38: aload         4
      40: aload         5
      42: aload_2
      43: invokevirtual #94                 // Method org/jboss/modules/Module.getClassLoader:()Lorg/jboss/modules/ModuleClassLoader;
      46: aload_3
      47: invokestatic  #95                 // Method org/jboss/as/ee/utils/InjectionUtils.getInjectionTarget:(Ljava/lang/String;Ljava/lang/String;Ljava/lang/ClassLoader;Lorg/jboss/as/server/deployment/reflect/DeploymentReflectionIndex;)Ljava/lang/reflect/AccessibleObject;
      50: astore        6
      52: aload         6
      54: areturn

  private static java.lang.String getInjectionTargetName(org.jboss.as.ee.component.InjectionTarget);
    Code:
       0: aload_0
       1: invokevirtual #96                 // Method org/jboss/as/ee/component/InjectionTarget.getName:()Ljava/lang/String;
       4: astore_1
       5: aload_0
       6: instanceof    #31                 // class org/jboss/as/ee/component/FieldInjectionTarget
       9: ifeq          14
      12: aload_1
      13: areturn
      14: aload_0
      15: instanceof    #48                 // class org/jboss/as/ee/component/MethodInjectionTarget
      18: ifeq          55
      21: new           #36                 // class java/lang/StringBuilder
      24: dup
      25: invokespecial #37                 // Method java/lang/StringBuilder."<init>":()V
      28: aload_1
      29: iconst_3
      30: iconst_4
      31: invokevirtual #51                 // Method java/lang/String.substring:(II)Ljava/lang/String;
      34: getstatic     #52                 // Field java/util/Locale.ENGLISH:Ljava/util/Locale;
      37: invokevirtual #97                 // Method java/lang/String.toUpperCase:(Ljava/util/Locale;)Ljava/lang/String;
      40: invokevirtual #38                 // Method java/lang/StringBuilder.append:(Ljava/lang/String;)Ljava/lang/StringBuilder;
      43: aload_1
      44: iconst_4
      45: invokevirtual #54                 // Method java/lang/String.substring:(I)Ljava/lang/String;
      48: invokevirtual #38                 // Method java/lang/StringBuilder.append:(Ljava/lang/String;)Ljava/lang/StringBuilder;
      51: invokevirtual #40                 // Method java/lang/StringBuilder.toString:()Ljava/lang/String;
      54: areturn
      55: new           #98                 // class java/lang/UnsupportedOperationException
      58: dup
      59: invokespecial #99                 // Method java/lang/UnsupportedOperationException."<init>":()V
      62: athrow

  private static java.lang.Class<?> getClass(org.jboss.as.server.deployment.DeploymentUnit, java.lang.String) throws org.jboss.as.server.deployment.DeploymentUnitProcessingException;
    Code:
       0: aload_1
       1: invokestatic  #24                 // Method isEmpty:(Ljava/lang/String;)Z
       4: ifne          23
       7: aload_1
       8: aload_0
       9: invokestatic  #100                // Method org/jboss/as/ee/utils/ClassLoadingUtils.loadClass:(Ljava/lang/String;Lorg/jboss/as/server/deployment/DeploymentUnit;)Ljava/lang/Class;
      12: areturn
      13: astore_2
      14: new           #102                // class org/jboss/as/server/deployment/DeploymentUnitProcessingException
      17: dup
      18: aload_2
      19: invokespecial #103                // Method org/jboss/as/server/deployment/DeploymentUnitProcessingException."<init>":(Ljava/lang/Throwable;)V
      22: athrow
      23: aconst_null
      24: areturn
    Exception table:
       from    to  target type
           7    12    13   Class java/lang/ClassNotFoundException

  private static boolean isEmpty(java.lang.String);
    Code:
       0: aload_0
       1: ifnull        11
       4: aload_0
       5: invokevirtual #104                // Method java/lang/String.isEmpty:()Z
       8: ifeq          15
      11: iconst_1
      12: goto          16
      15: iconst_0
      16: ireturn
}
