public class org.bouncycastle.crypto.signers.DSASigner implements org.bouncycastle.crypto.DSAExt {
  private final org.bouncycastle.crypto.signers.DSAKCalculator kCalculator;

  private org.bouncycastle.crypto.params.DSAKeyParameters key;

  private java.security.SecureRandom random;

  public org.bouncycastle.crypto.signers.DSASigner();
    Code:
       0: aload_0
       1: invokespecial #125                // Method java/lang/Object."<init>":()V
       4: aload_0
       5: new           #65                 // class org/bouncycastle/crypto/signers/RandomDSAKCalculator
       8: dup
       9: invokespecial #149                // Method org/bouncycastle/crypto/signers/RandomDSAKCalculator."<init>":()V
      12: putfield      #124                // Field kCalculator:Lorg/bouncycastle/crypto/signers/DSAKCalculator;
      15: return

  public org.bouncycastle.crypto.signers.DSASigner(org.bouncycastle.crypto.signers.DSAKCalculator);
    Code:
       0: aload_0
       1: invokespecial #125                // Method java/lang/Object."<init>":()V
       4: aload_0
       5: aload_1
       6: putfield      #124                // Field kCalculator:Lorg/bouncycastle/crypto/signers/DSAKCalculator;
       9: return

  public void init(boolean, org.bouncycastle.crypto.CipherParameters);
    Code:
       0: aconst_null
       1: astore_3
       2: iload_1
       3: ifeq          51
       6: aload_2
       7: instanceof    #62                 // class org/bouncycastle/crypto/params/ParametersWithRandom
      10: ifeq          40
      13: aload_2
      14: checkcast     #62                 // class org/bouncycastle/crypto/params/ParametersWithRandom
      17: astore        4
      19: aload_0
      20: aload         4
      22: invokevirtual #145                // Method org/bouncycastle/crypto/params/ParametersWithRandom.getParameters:()Lorg/bouncycastle/crypto/CipherParameters;
      25: checkcast     #60                 // class org/bouncycastle/crypto/params/DSAPrivateKeyParameters
      28: putfield      #123                // Field key:Lorg/bouncycastle/crypto/params/DSAKeyParameters;
      31: aload         4
      33: invokevirtual #144                // Method org/bouncycastle/crypto/params/ParametersWithRandom.getRandom:()Ljava/security/SecureRandom;
      36: astore_3
      37: goto          59
      40: aload_0
      41: aload_2
      42: checkcast     #60                 // class org/bouncycastle/crypto/params/DSAPrivateKeyParameters
      45: putfield      #123                // Field key:Lorg/bouncycastle/crypto/params/DSAKeyParameters;
      48: goto          59
      51: aload_0
      52: aload_2
      53: checkcast     #61                 // class org/bouncycastle/crypto/params/DSAPublicKeyParameters
      56: putfield      #123                // Field key:Lorg/bouncycastle/crypto/params/DSAKeyParameters;
      59: aload_0
      60: aload_0
      61: iload_1
      62: ifeq          81
      65: aload_0
      66: getfield      #124                // Field kCalculator:Lorg/bouncycastle/crypto/signers/DSAKCalculator;
      69: invokeinterface #151,  1          // InterfaceMethod org/bouncycastle/crypto/signers/DSAKCalculator.isDeterministic:()Z
      74: ifne          81
      77: iconst_1
      78: goto          82
      81: iconst_0
      82: aload_3
      83: invokevirtual #147                // Method initSecureRandom:(ZLjava/security/SecureRandom;)Ljava/security/SecureRandom;
      86: putfield      #122                // Field random:Ljava/security/SecureRandom;
      89: return

  public java.math.BigInteger getOrder();
    Code:
       0: aload_0
       1: getfield      #123                // Field key:Lorg/bouncycastle/crypto/params/DSAKeyParameters;
       4: invokevirtual #138                // Method org/bouncycastle/crypto/params/DSAKeyParameters.getParameters:()Lorg/bouncycastle/crypto/params/DSAParameters;
       7: invokevirtual #141                // Method org/bouncycastle/crypto/params/DSAParameters.getQ:()Ljava/math/BigInteger;
      10: areturn

  public java.math.BigInteger[] generateSignature(byte[]);
    Code:
       0: aload_0
       1: getfield      #123                // Field key:Lorg/bouncycastle/crypto/params/DSAKeyParameters;
       4: invokevirtual #138                // Method org/bouncycastle/crypto/params/DSAKeyParameters.getParameters:()Lorg/bouncycastle/crypto/params/DSAParameters;
       7: astore_2
       8: aload_2
       9: invokevirtual #141                // Method org/bouncycastle/crypto/params/DSAParameters.getQ:()Ljava/math/BigInteger;
      12: astore_3
      13: aload_0
      14: aload_3
      15: aload_1
      16: invokespecial #146                // Method calculateE:(Ljava/math/BigInteger;[B)Ljava/math/BigInteger;
      19: astore        4
      21: aload_0
      22: getfield      #123                // Field key:Lorg/bouncycastle/crypto/params/DSAKeyParameters;
      25: checkcast     #60                 // class org/bouncycastle/crypto/params/DSAPrivateKeyParameters
      28: invokevirtual #142                // Method org/bouncycastle/crypto/params/DSAPrivateKeyParameters.getX:()Ljava/math/BigInteger;
      31: astore        5
      33: aload_0
      34: getfield      #124                // Field kCalculator:Lorg/bouncycastle/crypto/signers/DSAKCalculator;
      37: invokeinterface #151,  1          // InterfaceMethod org/bouncycastle/crypto/signers/DSAKCalculator.isDeterministic:()Z
      42: ifeq          61
      45: aload_0
      46: getfield      #124                // Field kCalculator:Lorg/bouncycastle/crypto/signers/DSAKCalculator;
      49: aload_3
      50: aload         5
      52: aload_1
      53: invokeinterface #153,  4          // InterfaceMethod org/bouncycastle/crypto/signers/DSAKCalculator.init:(Ljava/math/BigInteger;Ljava/math/BigInteger;[B)V
      58: goto          75
      61: aload_0
      62: getfield      #124                // Field kCalculator:Lorg/bouncycastle/crypto/signers/DSAKCalculator;
      65: aload_3
      66: aload_0
      67: getfield      #122                // Field random:Ljava/security/SecureRandom;
      70: invokeinterface #154,  3          // InterfaceMethod org/bouncycastle/crypto/signers/DSAKCalculator.init:(Ljava/math/BigInteger;Ljava/security/SecureRandom;)V
      75: aload_0
      76: getfield      #124                // Field kCalculator:Lorg/bouncycastle/crypto/signers/DSAKCalculator;
      79: invokeinterface #152,  1          // InterfaceMethod org/bouncycastle/crypto/signers/DSAKCalculator.nextK:()Ljava/math/BigInteger;
      84: astore        6
      86: aload_2
      87: invokevirtual #139                // Method org/bouncycastle/crypto/params/DSAParameters.getG:()Ljava/math/BigInteger;
      90: aload         6
      92: aload_0
      93: aload_3
      94: aload_0
      95: getfield      #122                // Field random:Ljava/security/SecureRandom;
      98: invokespecial #148                // Method getRandomizer:(Ljava/math/BigInteger;Ljava/security/SecureRandom;)Ljava/math/BigInteger;
     101: invokevirtual #132                // Method java/math/BigInteger.add:(Ljava/math/BigInteger;)Ljava/math/BigInteger;
     104: aload_2
     105: invokevirtual #140                // Method org/bouncycastle/crypto/params/DSAParameters.getP:()Ljava/math/BigInteger;
     108: invokevirtual #136                // Method java/math/BigInteger.modPow:(Ljava/math/BigInteger;Ljava/math/BigInteger;)Ljava/math/BigInteger;
     111: aload_3
     112: invokevirtual #133                // Method java/math/BigInteger.mod:(Ljava/math/BigInteger;)Ljava/math/BigInteger;
     115: astore        7
     117: aload         6
     119: aload_3
     120: invokevirtual #134                // Method java/math/BigInteger.modInverse:(Ljava/math/BigInteger;)Ljava/math/BigInteger;
     123: aload         4
     125: aload         5
     127: aload         7
     129: invokevirtual #135                // Method java/math/BigInteger.multiply:(Ljava/math/BigInteger;)Ljava/math/BigInteger;
     132: invokevirtual #132                // Method java/math/BigInteger.add:(Ljava/math/BigInteger;)Ljava/math/BigInteger;
     135: invokevirtual #135                // Method java/math/BigInteger.multiply:(Ljava/math/BigInteger;)Ljava/math/BigInteger;
     138: astore        6
     140: aload         6
     142: aload_3
     143: invokevirtual #133                // Method java/math/BigInteger.mod:(Ljava/math/BigInteger;)Ljava/math/BigInteger;
     146: astore        8
     148: iconst_2
     149: anewarray     #55                 // class java/math/BigInteger
     152: dup
     153: iconst_0
     154: aload         7
     156: aastore
     157: dup
     158: iconst_1
     159: aload         8
     161: aastore
     162: areturn

  public boolean verifySignature(byte[], java.math.BigInteger, java.math.BigInteger);
    Code:
       0: aload_0
       1: getfield      #123                // Field key:Lorg/bouncycastle/crypto/params/DSAKeyParameters;
       4: invokevirtual #138                // Method org/bouncycastle/crypto/params/DSAKeyParameters.getParameters:()Lorg/bouncycastle/crypto/params/DSAParameters;
       7: astore        4
       9: aload         4
      11: invokevirtual #141                // Method org/bouncycastle/crypto/params/DSAParameters.getQ:()Ljava/math/BigInteger;
      14: astore        5
      16: aload_0
      17: aload         5
      19: aload_1
      20: invokespecial #146                // Method calculateE:(Ljava/math/BigInteger;[B)Ljava/math/BigInteger;
      23: astore        6
      25: lconst_0
      26: invokestatic  #130                // Method java/math/BigInteger.valueOf:(J)Ljava/math/BigInteger;
      29: astore        7
      31: aload         7
      33: aload_2
      34: invokevirtual #131                // Method java/math/BigInteger.compareTo:(Ljava/math/BigInteger;)I
      37: ifge          49
      40: aload         5
      42: aload_2
      43: invokevirtual #131                // Method java/math/BigInteger.compareTo:(Ljava/math/BigInteger;)I
      46: ifgt          51
      49: iconst_0
      50: ireturn
      51: aload         7
      53: aload_3
      54: invokevirtual #131                // Method java/math/BigInteger.compareTo:(Ljava/math/BigInteger;)I
      57: ifge          69
      60: aload         5
      62: aload_3
      63: invokevirtual #131                // Method java/math/BigInteger.compareTo:(Ljava/math/BigInteger;)I
      66: ifgt          71
      69: iconst_0
      70: ireturn
      71: aload_3
      72: aload         5
      74: invokevirtual #134                // Method java/math/BigInteger.modInverse:(Ljava/math/BigInteger;)Ljava/math/BigInteger;
      77: astore        8
      79: aload         6
      81: aload         8
      83: invokevirtual #135                // Method java/math/BigInteger.multiply:(Ljava/math/BigInteger;)Ljava/math/BigInteger;
      86: aload         5
      88: invokevirtual #133                // Method java/math/BigInteger.mod:(Ljava/math/BigInteger;)Ljava/math/BigInteger;
      91: astore        9
      93: aload_2
      94: aload         8
      96: invokevirtual #135                // Method java/math/BigInteger.multiply:(Ljava/math/BigInteger;)Ljava/math/BigInteger;
      99: aload         5
     101: invokevirtual #133                // Method java/math/BigInteger.mod:(Ljava/math/BigInteger;)Ljava/math/BigInteger;
     104: astore        10
     106: aload         4
     108: invokevirtual #140                // Method org/bouncycastle/crypto/params/DSAParameters.getP:()Ljava/math/BigInteger;
     111: astore        11
     113: aload         4
     115: invokevirtual #139                // Method org/bouncycastle/crypto/params/DSAParameters.getG:()Ljava/math/BigInteger;
     118: aload         9
     120: aload         11
     122: invokevirtual #136                // Method java/math/BigInteger.modPow:(Ljava/math/BigInteger;Ljava/math/BigInteger;)Ljava/math/BigInteger;
     125: astore        9
     127: aload_0
     128: getfield      #123                // Field key:Lorg/bouncycastle/crypto/params/DSAKeyParameters;
     131: checkcast     #61                 // class org/bouncycastle/crypto/params/DSAPublicKeyParameters
     134: invokevirtual #143                // Method org/bouncycastle/crypto/params/DSAPublicKeyParameters.getY:()Ljava/math/BigInteger;
     137: aload         10
     139: aload         11
     141: invokevirtual #136                // Method java/math/BigInteger.modPow:(Ljava/math/BigInteger;Ljava/math/BigInteger;)Ljava/math/BigInteger;
     144: astore        10
     146: aload         9
     148: aload         10
     150: invokevirtual #135                // Method java/math/BigInteger.multiply:(Ljava/math/BigInteger;)Ljava/math/BigInteger;
     153: aload         11
     155: invokevirtual #133                // Method java/math/BigInteger.mod:(Ljava/math/BigInteger;)Ljava/math/BigInteger;
     158: aload         5
     160: invokevirtual #133                // Method java/math/BigInteger.mod:(Ljava/math/BigInteger;)Ljava/math/BigInteger;
     163: astore        12
     165: aload         12
     167: aload_2
     168: invokevirtual #129                // Method java/math/BigInteger.equals:(Ljava/lang/Object;)Z
     171: ireturn

  private java.math.BigInteger calculateE(java.math.BigInteger, byte[]);
    Code:
       0: aload_1
       1: invokevirtual #127                // Method java/math/BigInteger.bitLength:()I
       4: aload_2
       5: arraylength
       6: bipush        8
       8: imul
       9: if_icmplt     22
      12: new           #55                 // class java/math/BigInteger
      15: dup
      16: iconst_1
      17: aload_2
      18: invokespecial #128                // Method java/math/BigInteger."<init>":(I[B)V
      21: areturn
      22: aload_1
      23: invokevirtual #127                // Method java/math/BigInteger.bitLength:()I
      26: bipush        8
      28: idiv
      29: newarray       byte
      31: astore_3
      32: aload_2
      33: iconst_0
      34: aload_3
      35: iconst_0
      36: aload_3
      37: arraylength
      38: invokestatic  #126                // Method java/lang/System.arraycopy:(Ljava/lang/Object;ILjava/lang/Object;II)V
      41: new           #55                 // class java/math/BigInteger
      44: dup
      45: iconst_1
      46: aload_3
      47: invokespecial #128                // Method java/math/BigInteger."<init>":(I[B)V
      50: areturn

  protected java.security.SecureRandom initSecureRandom(boolean, java.security.SecureRandom);
    Code:
       0: iload_1
       1: ifne          8
       4: aconst_null
       5: goto          19
       8: aload_2
       9: ifnull        16
      12: aload_2
      13: goto          19
      16: invokestatic  #137                // Method org/bouncycastle/crypto/CryptoServicesRegistrar.getSecureRandom:()Ljava/security/SecureRandom;
      19: areturn

  private java.math.BigInteger getRandomizer(java.math.BigInteger, java.security.SecureRandom);
    Code:
       0: bipush        7
       2: istore_3
       3: iload_3
       4: aload_2
       5: ifnull        12
       8: aload_2
       9: goto          15
      12: invokestatic  #137                // Method org/bouncycastle/crypto/CryptoServicesRegistrar.getSecureRandom:()Ljava/security/SecureRandom;
      15: invokestatic  #150                // Method org/bouncycastle/util/BigIntegers.createRandomBigInteger:(ILjava/security/SecureRandom;)Ljava/math/BigInteger;
      18: ldc2_w        #51                 // long 128l
      21: invokestatic  #130                // Method java/math/BigInteger.valueOf:(J)Ljava/math/BigInteger;
      24: invokevirtual #132                // Method java/math/BigInteger.add:(Ljava/math/BigInteger;)Ljava/math/BigInteger;
      27: aload_1
      28: invokevirtual #135                // Method java/math/BigInteger.multiply:(Ljava/math/BigInteger;)Ljava/math/BigInteger;
      31: areturn
}
