Compiled from "BadBytecode.java"
public class javassist.bytecode.BadBytecode extends java.lang.Exception {
  public javassist.bytecode.BadBytecode(int);
    Code:
       0: aload_0
       1: new           #1                  // class java/lang/StringBuilder
       4: dup
       5: invokespecial #2                  // Method java/lang/StringBuilder."<init>":()V
       8: ldc           #3                  // String bytecode
      10: invokevirtual #4                  // Method java/lang/StringBuilder.append:(Ljava/lang/String;)Ljava/lang/StringBuilder;
      13: iload_1
      14: invokevirtual #5                  // Method java/lang/StringBuilder.append:(I)Ljava/lang/StringBuilder;
      17: invokevirtual #6                  // Method java/lang/StringBuilder.toString:()Ljava/lang/String;
      20: invokespecial #7                  // Method java/lang/Exception."<init>":(Ljava/lang/String;)V
      23: return

  public javassist.bytecode.BadBytecode(java.lang.String);
    Code:
       0: aload_0
       1: aload_1
       2: invokespecial #7                  // Method java/lang/Exception."<init>":(Ljava/lang/String;)V
       5: return

  public javassist.bytecode.BadBytecode(java.lang.String, java.lang.Throwable);
    Code:
       0: aload_0
       1: aload_1
       2: aload_2
       3: invokespecial #8                  // Method java/lang/Exception."<init>":(Ljava/lang/String;Ljava/lang/Throwable;)V
       6: return

  public javassist.bytecode.BadBytecode(javassist.bytecode.MethodInfo, java.lang.Throwable);
    Code:
       0: aload_0
       1: new           #1                  // class java/lang/StringBuilder
       4: dup
       5: invokespecial #2                  // Method java/lang/StringBuilder."<init>":()V
       8: aload_1
       9: invokevirtual #9                  // Method javassist/bytecode/MethodInfo.toString:()Ljava/lang/String;
      12: invokevirtual #4                  // Method java/lang/StringBuilder.append:(Ljava/lang/String;)Ljava/lang/StringBuilder;
      15: ldc           #10                 // String  in
      17: invokevirtual #4                  // Method java/lang/StringBuilder.append:(Ljava/lang/String;)Ljava/lang/StringBuilder;
      20: aload_1
      21: invokevirtual #11                 // Method javassist/bytecode/MethodInfo.getConstPool:()Ljavassist/bytecode/ConstPool;
      24: invokevirtual #12                 // Method javassist/bytecode/ConstPool.getClassName:()Ljava/lang/String;
      27: invokevirtual #4                  // Method java/lang/StringBuilder.append:(Ljava/lang/String;)Ljava/lang/StringBuilder;
      30: ldc           #13                 // String :
      32: invokevirtual #4                  // Method java/lang/StringBuilder.append:(Ljava/lang/String;)Ljava/lang/StringBuilder;
      35: aload_2
      36: invokevirtual #14                 // Method java/lang/Throwable.getMessage:()Ljava/lang/String;
      39: invokevirtual #4                  // Method java/lang/StringBuilder.append:(Ljava/lang/String;)Ljava/lang/StringBuilder;
      42: invokevirtual #6                  // Method java/lang/StringBuilder.toString:()Ljava/lang/String;
      45: aload_2
      46: invokespecial #8                  // Method java/lang/Exception."<init>":(Ljava/lang/String;Ljava/lang/Throwable;)V
      49: return
}
