Compiled from "Memoizer.java"
class org.apache.commons.lang3.concurrent.Memoizer$1 implements java.util.concurrent.Callable<O> {
  final java.lang.Object val$arg;

  final org.apache.commons.lang3.concurrent.Memoizer this$0;

  org.apache.commons.lang3.concurrent.Memoizer$1(org.apache.commons.lang3.concurrent.Memoizer, java.lang.Object);
    Code:
       0: aload_0
       1: aload_1
       2: putfield      #1                  // Field this$0:Lorg/apache/commons/lang3/concurrent/Memoizer;
       5: aload_0
       6: aload_2
       7: putfield      #2                  // Field val$arg:Ljava/lang/Object;
      10: aload_0
      11: invokespecial #3                  // Method java/lang/Object."<init>":()V
      14: return

  public O call() throws java.lang.InterruptedException;
    Code:
       0: aload_0
       1: getfield      #1                  // Field this$0:Lorg/apache/commons/lang3/concurrent/Memoizer;
       4: invokestatic  #4                  // Method org/apache/commons/lang3/concurrent/Memoizer.access$000:(Lorg/apache/commons/lang3/concurrent/Memoizer;)Lorg/apache/commons/lang3/concurrent/Computable;
       7: aload_0
       8: getfield      #2                  // Field val$arg:Ljava/lang/Object;
      11: invokeinterface #5,  2            // InterfaceMethod org/apache/commons/lang3/concurrent/Computable.compute:(Ljava/lang/Object;)Ljava/lang/Object;
      16: areturn
}
