Compiled from "BeanKeyFilter.java"
public class org.wildfly.clustering.ejb.infinispan.BeanKeyFilter<I> implements org.infinispan.filter.KeyFilter<java.lang.Object>, java.util.function.Predicate<java.lang.Object>, java.io.Serializable {
  private static final long serialVersionUID;

  private final java.lang.String beanName;

  public org.wildfly.clustering.ejb.infinispan.BeanKeyFilter(java.lang.String);
    Code:
       0: aload_0
       1: invokespecial #1                  // Method java/lang/Object."<init>":()V
       4: aload_0
       5: aload_1
       6: putfield      #2                  // Field beanName:Ljava/lang/String;
       9: return

  public boolean accept(java.lang.Object);
    Code:
       0: aload_1
       1: instanceof    #3                  // class org/wildfly/clustering/ejb/infinispan/BeanKey
       4: ifne          9
       7: iconst_0
       8: ireturn
       9: aload_1
      10: checkcast     #3                  // class org/wildfly/clustering/ejb/infinispan/BeanKey
      13: astore_2
      14: aload_2
      15: invokeinterface #4,  1            // InterfaceMethod org/wildfly/clustering/ejb/infinispan/BeanKey.getBeanName:()Ljava/lang/String;
      20: aload_0
      21: getfield      #2                  // Field beanName:Ljava/lang/String;
      24: invokevirtual #5                  // Method java/lang/String.equals:(Ljava/lang/Object;)Z
      27: ireturn

  public boolean test(java.lang.Object);
    Code:
       0: aload_0
       1: aload_1
       2: invokevirtual #6                  // Method accept:(Ljava/lang/Object;)Z
       5: ireturn
}
