Compiled from "InfinispanBeanManagerFactory.java"
class org.wildfly.clustering.ejb.infinispan.InfinispanBeanManagerFactory$2 implements org.wildfly.clustering.ejb.infinispan.PassivationConfiguration<T> {
  final org.wildfly.clustering.ejb.PassivationListener val$passivationListener;

  final boolean val$evictionAllowed;

  final boolean val$persistent;

  final org.wildfly.clustering.ejb.BeanPassivationConfiguration val$passivationConfig;

  final java.util.concurrent.Executor val$executor;

  final org.wildfly.clustering.ejb.infinispan.InfinispanBeanManagerFactory this$0;

  org.wildfly.clustering.ejb.infinispan.InfinispanBeanManagerFactory$2(org.wildfly.clustering.ejb.infinispan.InfinispanBeanManagerFactory, org.wildfly.clustering.ejb.PassivationListener, boolean, boolean, org.wildfly.clustering.ejb.BeanPassivationConfiguration, java.util.concurrent.Executor);
    Code:
       0: aload_0
       1: aload_1
       2: putfield      #1                  // Field this$0:Lorg/wildfly/clustering/ejb/infinispan/InfinispanBeanManagerFactory;
       5: aload_0
       6: aload_2
       7: putfield      #2                  // Field val$passivationListener:Lorg/wildfly/clustering/ejb/PassivationListener;
      10: aload_0
      11: iload_3
      12: putfield      #3                  // Field val$evictionAllowed:Z
      15: aload_0
      16: iload         4
      18: putfield      #4                  // Field val$persistent:Z
      21: aload_0
      22: aload         5
      24: putfield      #5                  // Field val$passivationConfig:Lorg/wildfly/clustering/ejb/BeanPassivationConfiguration;
      27: aload_0
      28: aload         6
      30: putfield      #6                  // Field val$executor:Ljava/util/concurrent/Executor;
      33: aload_0
      34: invokespecial #7                  // Method java/lang/Object."<init>":()V
      37: return

  public org.wildfly.clustering.ejb.PassivationListener<T> getPassivationListener();
    Code:
       0: aload_0
       1: getfield      #2                  // Field val$passivationListener:Lorg/wildfly/clustering/ejb/PassivationListener;
       4: areturn

  public boolean isEvictionAllowed();
    Code:
       0: aload_0
       1: getfield      #3                  // Field val$evictionAllowed:Z
       4: ireturn

  public boolean isPersistent();
    Code:
       0: aload_0
       1: getfield      #4                  // Field val$persistent:Z
       4: ireturn

  public org.wildfly.clustering.ejb.BeanPassivationConfiguration getConfiguration();
    Code:
       0: aload_0
       1: getfield      #5                  // Field val$passivationConfig:Lorg/wildfly/clustering/ejb/BeanPassivationConfiguration;
       4: areturn

  public java.util.concurrent.Executor getExecutor();
    Code:
       0: aload_0
       1: getfield      #6                  // Field val$executor:Ljava/util/concurrent/Executor;
       4: areturn
}
