Compiled from "InfinispanBeanManager.java"
class org.wildfly.clustering.ejb.infinispan.InfinispanBeanManager$SchedulableBean implements org.wildfly.clustering.ejb.Bean<G, I, T> {
  private final org.wildfly.clustering.ejb.Bean<G, I, T> bean;

  final org.wildfly.clustering.ejb.infinispan.InfinispanBeanManager this$0;

  org.wildfly.clustering.ejb.infinispan.InfinispanBeanManager$SchedulableBean(org.wildfly.clustering.ejb.Bean<G, I, T>);
    Code:
       0: aload_0
       1: aload_1
       2: putfield      #1                  // Field this$0:Lorg/wildfly/clustering/ejb/infinispan/InfinispanBeanManager;
       5: aload_0
       6: invokespecial #2                  // Method java/lang/Object."<init>":()V
       9: aload_0
      10: aload_2
      11: putfield      #3                  // Field bean:Lorg/wildfly/clustering/ejb/Bean;
      14: return

  public I getId();
    Code:
       0: aload_0
       1: getfield      #3                  // Field bean:Lorg/wildfly/clustering/ejb/Bean;
       4: invokeinterface #4,  1            // InterfaceMethod org/wildfly/clustering/ejb/Bean.getId:()Ljava/lang/Object;
       9: areturn

  public G getGroupId();
    Code:
       0: aload_0
       1: getfield      #3                  // Field bean:Lorg/wildfly/clustering/ejb/Bean;
       4: invokeinterface #5,  1            // InterfaceMethod org/wildfly/clustering/ejb/Bean.getGroupId:()Ljava/lang/Object;
       9: areturn

  public void remove(org.wildfly.clustering.ejb.RemoveListener<T>);
    Code:
       0: aload_0
       1: getfield      #3                  // Field bean:Lorg/wildfly/clustering/ejb/Bean;
       4: aload_1
       5: invokeinterface #6,  2            // InterfaceMethod org/wildfly/clustering/ejb/Bean.remove:(Lorg/wildfly/clustering/ejb/RemoveListener;)V
      10: return

  public boolean isExpired();
    Code:
       0: aload_0
       1: getfield      #3                  // Field bean:Lorg/wildfly/clustering/ejb/Bean;
       4: invokeinterface #7,  1            // InterfaceMethod org/wildfly/clustering/ejb/Bean.isExpired:()Z
       9: ireturn

  public T acquire();
    Code:
       0: aload_0
       1: getfield      #3                  // Field bean:Lorg/wildfly/clustering/ejb/Bean;
       4: invokeinterface #8,  1            // InterfaceMethod org/wildfly/clustering/ejb/Bean.acquire:()Ljava/lang/Object;
       9: areturn

  public boolean release();
    Code:
       0: aload_0
       1: getfield      #3                  // Field bean:Lorg/wildfly/clustering/ejb/Bean;
       4: invokeinterface #9,  1            // InterfaceMethod org/wildfly/clustering/ejb/Bean.release:()Z
       9: ireturn

  public void close();
    Code:
       0: aload_0
       1: getfield      #3                  // Field bean:Lorg/wildfly/clustering/ejb/Bean;
       4: invokeinterface #10,  1           // InterfaceMethod org/wildfly/clustering/ejb/Bean.close:()V
       9: aload_0
      10: getfield      #1                  // Field this$0:Lorg/wildfly/clustering/ejb/infinispan/InfinispanBeanManager;
      13: aload_0
      14: getfield      #3                  // Field bean:Lorg/wildfly/clustering/ejb/Bean;
      17: invokevirtual #11                 // Method org/wildfly/clustering/ejb/infinispan/InfinispanBeanManager.schedule:(Lorg/wildfly/clustering/ejb/Bean;)V
      20: return
}
