Compiled from "HibernateTypeSourceImpl.java"
public class org.hibernate.boot.model.source.internal.hbm.HibernateTypeSourceImpl implements org.hibernate.boot.model.source.spi.HibernateTypeSource,org.hibernate.boot.model.source.spi.JavaTypeDescriptorResolvable {
  private final java.lang.String name;

  private final java.util.Map<java.lang.String, java.lang.String> parameters;

  private org.hibernate.boot.model.JavaTypeDescriptor javaTypeDescriptor;

  public org.hibernate.boot.model.source.internal.hbm.HibernateTypeSourceImpl(org.hibernate.boot.jaxb.hbm.spi.TypeContainer);
    Code:
       0: aload_0
       1: invokespecial #1                  // Method java/lang/Object."<init>":()V
       4: aload_1
       5: invokeinterface #2,  1            // InterfaceMethod org/hibernate/boot/jaxb/hbm/spi/TypeContainer.getTypeAttribute:()Ljava/lang/String;
      10: ifnull        31
      13: aload_0
      14: aload_1
      15: invokeinterface #2,  1            // InterfaceMethod org/hibernate/boot/jaxb/hbm/spi/TypeContainer.getTypeAttribute:()Ljava/lang/String;
      20: putfield      #3                  // Field name:Ljava/lang/String;
      23: aload_0
      24: aconst_null
      25: putfield      #4                  // Field parameters:Ljava/util/Map;
      28: goto          82
      31: aload_1
      32: invokeinterface #5,  1            // InterfaceMethod org/hibernate/boot/jaxb/hbm/spi/TypeContainer.getType:()Lorg/hibernate/boot/jaxb/hbm/spi/JaxbHbmTypeSpecificationType;
      37: ifnull        72
      40: aload_0
      41: aload_1
      42: invokeinterface #5,  1            // InterfaceMethod org/hibernate/boot/jaxb/hbm/spi/TypeContainer.getType:()Lorg/hibernate/boot/jaxb/hbm/spi/JaxbHbmTypeSpecificationType;
      47: invokevirtual #6                  // Method org/hibernate/boot/jaxb/hbm/spi/JaxbHbmTypeSpecificationType.getName:()Ljava/lang/String;
      50: putfield      #3                  // Field name:Ljava/lang/String;
      53: aload_0
      54: aload_1
      55: invokeinterface #5,  1            // InterfaceMethod org/hibernate/boot/jaxb/hbm/spi/TypeContainer.getType:()Lorg/hibernate/boot/jaxb/hbm/spi/JaxbHbmTypeSpecificationType;
      60: invokevirtual #7                  // Method org/hibernate/boot/jaxb/hbm/spi/JaxbHbmTypeSpecificationType.getConfigParameters:()Ljava/util/List;
      63: invokestatic  #8                  // Method org/hibernate/boot/model/source/internal/hbm/Helper.extractParameters:(Ljava/util/List;)Ljava/util/Map;
      66: putfield      #4                  // Field parameters:Ljava/util/Map;
      69: goto          82
      72: aload_0
      73: aconst_null
      74: putfield      #3                  // Field name:Ljava/lang/String;
      77: aload_0
      78: aconst_null
      79: putfield      #4                  // Field parameters:Ljava/util/Map;
      82: return

  public org.hibernate.boot.model.source.internal.hbm.HibernateTypeSourceImpl(java.lang.String);
    Code:
       0: aload_0
       1: aload_1
       2: invokestatic  #9                  // Method java/util/Collections.emptyMap:()Ljava/util/Map;
       5: invokespecial #10                 // Method "<init>":(Ljava/lang/String;Ljava/util/Map;)V
       8: return

  public org.hibernate.boot.model.source.internal.hbm.HibernateTypeSourceImpl(java.lang.String, java.util.Map<java.lang.String, java.lang.String>);
    Code:
       0: aload_0
       1: invokespecial #1                  // Method java/lang/Object."<init>":()V
       4: aload_0
       5: aload_1
       6: putfield      #3                  // Field name:Ljava/lang/String;
       9: aload_0
      10: aload_2
      11: putfield      #4                  // Field parameters:Ljava/util/Map;
      14: return

  public org.hibernate.boot.model.source.internal.hbm.HibernateTypeSourceImpl(org.hibernate.boot.model.JavaTypeDescriptor);
    Code:
       0: aload_0
       1: aconst_null
       2: aload_1
       3: invokespecial #11                 // Method "<init>":(Ljava/lang/String;Lorg/hibernate/boot/model/JavaTypeDescriptor;)V
       6: return

  public org.hibernate.boot.model.source.internal.hbm.HibernateTypeSourceImpl(java.lang.String, org.hibernate.boot.model.JavaTypeDescriptor);
    Code:
       0: aload_0
       1: aload_1
       2: invokespecial #12                 // Method "<init>":(Ljava/lang/String;)V
       5: aload_0
       6: aload_2
       7: putfield      #13                 // Field javaTypeDescriptor:Lorg/hibernate/boot/model/JavaTypeDescriptor;
      10: return

  public java.lang.String getName();
    Code:
       0: aload_0
       1: getfield      #3                  // Field name:Ljava/lang/String;
       4: areturn

  public java.util.Map<java.lang.String, java.lang.String> getParameters();
    Code:
       0: aload_0
       1: getfield      #4                  // Field parameters:Ljava/util/Map;
       4: areturn

  public org.hibernate.boot.model.JavaTypeDescriptor getJavaType();
    Code:
       0: aload_0
       1: getfield      #13                 // Field javaTypeDescriptor:Lorg/hibernate/boot/model/JavaTypeDescriptor;
       4: areturn

  public void resolveJavaTypeDescriptor(org.hibernate.boot.model.JavaTypeDescriptor);
    Code:
       0: aload_0
       1: getfield      #13                 // Field javaTypeDescriptor:Lorg/hibernate/boot/model/JavaTypeDescriptor;
       4: ifnull        25
       7: aload_0
       8: getfield      #13                 // Field javaTypeDescriptor:Lorg/hibernate/boot/model/JavaTypeDescriptor;
      11: aload_1
      12: if_acmpeq     25
      15: new           #14                 // class java/lang/IllegalStateException
      18: dup
      19: ldc           #15                 // String Attempt to resolve an already resolved JavaTypeDescriptor
      21: invokespecial #16                 // Method java/lang/IllegalStateException."<init>":(Ljava/lang/String;)V
      24: athrow
      25: aload_0
      26: aload_1
      27: putfield      #13                 // Field javaTypeDescriptor:Lorg/hibernate/boot/model/JavaTypeDescriptor;
      30: return
}
