Compiled from "ParArray.scala"
public final class scala.collection.parallel.mutable.ParArray$$anonfun$scan$1 extends scala.runtime.AbstractFunction1<scala.collection.parallel.ParIterableLike<T, scala.collection.parallel.mutable.ParArray<T>, scala.collection.mutable.ArraySeq<T>>.ScanTree<U>, scala.runtime.BoxedUnit> implements scala.Serializable {
  public static final long serialVersionUID;

  private final scala.collection.parallel.mutable.ParArray $outer;

  private final java.lang.Object z$1;

  private final scala.Function2 op$1;

  private final java.lang.Object[] targetarr$1;

  public final void apply(scala.collection.parallel.ParIterableLike<T, scala.collection.parallel.mutable.ParArray<T>, scala.collection.mutable.ArraySeq<T>>.ScanTree<U>);
    Code:
       0: aload_0
       1: getfield      #29                 // Field $outer:Lscala/collection/parallel/mutable/ParArray;
       4: invokevirtual #33                 // Method scala/collection/parallel/mutable/ParArray.tasksupport:()Lscala/collection/parallel/TaskSupport;
       7: new           #35                 // class scala/collection/parallel/mutable/ParArray$ScanToArray
      10: dup
      11: aload_0
      12: getfield      #29                 // Field $outer:Lscala/collection/parallel/mutable/ParArray;
      15: aload_1
      16: aload_0
      17: getfield      #37                 // Field z$1:Ljava/lang/Object;
      20: aload_0
      21: getfield      #39                 // Field op$1:Lscala/Function2;
      24: aload_0
      25: getfield      #41                 // Field targetarr$1:[Ljava/lang/Object;
      28: invokespecial #45                 // Method scala/collection/parallel/mutable/ParArray$ScanToArray."<init>":(Lscala/collection/parallel/mutable/ParArray;Lscala/collection/parallel/ParIterableLike$ScanTree;Ljava/lang/Object;Lscala/Function2;[Ljava/lang/Object;)V
      31: invokeinterface #51,  2           // InterfaceMethod scala/collection/parallel/TaskSupport.executeAndWaitResult:(Lscala/collection/parallel/Task;)Ljava/lang/Object;
      36: pop
      37: return

  public final java.lang.Object apply(java.lang.Object);
    Code:
       0: aload_0
       1: aload_1
       2: checkcast     #58                 // class scala/collection/parallel/ParIterableLike$ScanTree
       5: invokevirtual #60                 // Method apply:(Lscala/collection/parallel/ParIterableLike$ScanTree;)V
       8: getstatic     #66                 // Field scala/runtime/BoxedUnit.UNIT:Lscala/runtime/BoxedUnit;
      11: areturn

  public scala.collection.parallel.mutable.ParArray$$anonfun$scan$1(scala.collection.parallel.mutable.ParArray<T>);
    Code:
       0: aload_1
       1: ifnonnull     6
       4: aconst_null
       5: athrow
       6: aload_0
       7: aload_1
       8: putfield      #29                 // Field $outer:Lscala/collection/parallel/mutable/ParArray;
      11: aload_0
      12: aload_2
      13: putfield      #37                 // Field z$1:Ljava/lang/Object;
      16: aload_0
      17: aload_3
      18: putfield      #39                 // Field op$1:Lscala/Function2;
      21: aload_0
      22: aload         4
      24: putfield      #41                 // Field targetarr$1:[Ljava/lang/Object;
      27: aload_0
      28: invokespecial #71                 // Method scala/runtime/AbstractFunction1."<init>":()V
      31: return
}
