Compiled from "ParHashMap.scala"
public final class scala.collection.parallel.mutable.ParHashMap$$anonfun$brokenInvariants$2 extends scala.runtime.AbstractFunction1<scala.collection.immutable.List<java.lang.String>, scala.collection.immutable.List<java.lang.String>> implements scala.Serializable {
  public static final long serialVersionUID;

  public final scala.collection.immutable.List<java.lang.String> apply(scala.collection.immutable.List<java.lang.String>);
    Code:
       0: aload_1
       1: areturn

  public final java.lang.Object apply(java.lang.Object);
    Code:
       0: aload_0
       1: aload_1
       2: checkcast     #26                 // class scala/collection/immutable/List
       5: invokevirtual #28                 // Method apply:(Lscala/collection/immutable/List;)Lscala/collection/immutable/List;
       8: areturn

  public scala.collection.parallel.mutable.ParHashMap$$anonfun$brokenInvariants$2(scala.collection.parallel.mutable.ParHashMap<K, V>);
    Code:
       0: aload_0
       1: invokespecial #35                 // Method scala/runtime/AbstractFunction1."<init>":()V
       4: return
}
