Compiled from "ParHashMap.scala"
public final class scala.collection.parallel.mutable.ParHashMapCombiner$$anonfun$4 extends scala.runtime.AbstractFunction1<scala.collection.mutable.UnrolledBuffer<scala.collection.mutable.DefaultEntry<K, V>>, scala.collection.mutable.UnrolledBuffer$Unrolled<scala.collection.mutable.DefaultEntry<K, V>>> implements scala.Serializable {
  public static final long serialVersionUID;

  public final scala.collection.mutable.UnrolledBuffer$Unrolled<scala.collection.mutable.DefaultEntry<K, V>> apply(scala.collection.mutable.UnrolledBuffer<scala.collection.mutable.DefaultEntry<K, V>>);
    Code:
       0: aload_1
       1: ifnull        11
       4: aload_1
       5: invokevirtual #25                 // Method scala/collection/mutable/UnrolledBuffer.headPtr:()Lscala/collection/mutable/UnrolledBuffer$Unrolled;
       8: goto          12
      11: aconst_null
      12: areturn

  public final java.lang.Object apply(java.lang.Object);
    Code:
       0: aload_0
       1: aload_1
       2: checkcast     #21                 // class scala/collection/mutable/UnrolledBuffer
       5: invokevirtual #34                 // Method apply:(Lscala/collection/mutable/UnrolledBuffer;)Lscala/collection/mutable/UnrolledBuffer$Unrolled;
       8: areturn

  public scala.collection.parallel.mutable.ParHashMapCombiner$$anonfun$4(scala.collection.parallel.mutable.ParHashMapCombiner<K, V>);
    Code:
       0: aload_0
       1: invokespecial #41                 // Method scala/runtime/AbstractFunction1."<init>":()V
       4: return
}
