Compiled from "ParSetLike.scala"
public abstract class scala.collection.parallel.mutable.ParSetLike$class {
  public static scala.collection.parallel.mutable.ParSet $plus(scala.collection.parallel.mutable.ParSetLike, java.lang.Object);
    Code:
       0: aload_0
       1: invokeinterface #13,  1           // InterfaceMethod scala/collection/parallel/mutable/ParSetLike.clone:()Ljava/lang/Object;
       6: checkcast     #9                  // class scala/collection/parallel/mutable/ParSetLike
       9: aload_1
      10: invokeinterface #17,  2           // InterfaceMethod scala/collection/parallel/mutable/ParSetLike.$plus$eq:(Ljava/lang/Object;)Lscala/collection/parallel/mutable/ParSetLike;
      15: checkcast     #19                 // class scala/collection/parallel/mutable/ParSet
      18: areturn

  public static scala.collection.parallel.mutable.ParSet $minus(scala.collection.parallel.mutable.ParSetLike, java.lang.Object);
    Code:
       0: aload_0
       1: invokeinterface #13,  1           // InterfaceMethod scala/collection/parallel/mutable/ParSetLike.clone:()Ljava/lang/Object;
       6: checkcast     #9                  // class scala/collection/parallel/mutable/ParSetLike
       9: aload_1
      10: invokeinterface #27,  2           // InterfaceMethod scala/collection/parallel/mutable/ParSetLike.$minus$eq:(Ljava/lang/Object;)Lscala/collection/parallel/mutable/ParSetLike;
      15: checkcast     #19                 // class scala/collection/parallel/mutable/ParSet
      18: areturn

  public static void $init$(scala.collection.parallel.mutable.ParSetLike);
    Code:
       0: return
}
