Compiled from "ParSet.scala"
public abstract class scala.collection.parallel.mutable.ParSet$class {
  public static scala.collection.generic.GenericCompanion companion(scala.collection.parallel.mutable.ParSet);
    Code:
       0: getstatic     #13                 // Field scala/collection/parallel/mutable/ParSet$.MODULE$:Lscala/collection/parallel/mutable/ParSet$;
       3: areturn

  public static scala.collection.parallel.mutable.ParSet empty(scala.collection.parallel.mutable.ParSet);
    Code:
       0: getstatic     #22                 // Field scala/collection/parallel/mutable/ParHashSet$.MODULE$:Lscala/collection/parallel/mutable/ParHashSet$;
       3: getstatic     #27                 // Field scala/collection/immutable/Nil$.MODULE$:Lscala/collection/immutable/Nil$;
       6: invokevirtual #31                 // Method scala/collection/parallel/mutable/ParHashSet$.apply:(Lscala/collection/Seq;)Lscala/collection/GenTraversable;
       9: checkcast     #33                 // class scala/collection/parallel/mutable/ParSet
      12: areturn

  public static void $init$(scala.collection.parallel.mutable.ParSet);
    Code:
       0: return
}
