Compiled from "HostControllerClient.java"
class org.jboss.as.server.mgmt.domain.HostControllerClient$RemoteFileRepositoryExecutorImpl implements org.jboss.as.server.mgmt.domain.RemoteFileRepositoryExecutor {
  final org.jboss.as.server.mgmt.domain.HostControllerClient this$0;

  private org.jboss.as.server.mgmt.domain.HostControllerClient$RemoteFileRepositoryExecutorImpl(org.jboss.as.server.mgmt.domain.HostControllerClient);
    Code:
       0: aload_0
       1: aload_1
       2: putfield      #2                  // Field this$0:Lorg/jboss/as/server/mgmt/domain/HostControllerClient;
       5: aload_0
       6: invokespecial #3                  // Method java/lang/Object."<init>":()V
       9: return

  public java.io.File getFile(java.lang.String, byte, java.io.File);
    Code:
       0: aload_0
       1: getfield      #2                  // Field this$0:Lorg/jboss/as/server/mgmt/domain/HostControllerClient;
       4: invokestatic  #4                  // Method org/jboss/as/server/mgmt/domain/HostControllerClient.access$300:(Lorg/jboss/as/server/mgmt/domain/HostControllerClient;)Lorg/jboss/as/protocol/mgmt/ManagementChannelHandler;
       7: new           #5                  // class org/jboss/as/server/mgmt/domain/HostControllerClient$GetFileRequest
      10: dup
      11: aload_1
      12: aload_3
      13: aconst_null
      14: invokespecial #6                  // Method org/jboss/as/server/mgmt/domain/HostControllerClient$GetFileRequest."<init>":(Ljava/lang/String;Ljava/io/File;Lorg/jboss/as/server/mgmt/domain/HostControllerClient$1;)V
      17: aconst_null
      18: invokevirtual #7                  // Method org/jboss/as/protocol/mgmt/ManagementChannelHandler.executeRequest:(Lorg/jboss/as/protocol/mgmt/ManagementRequest;Ljava/lang/Object;)Lorg/jboss/as/protocol/mgmt/ActiveOperation;
      21: invokeinterface #8,  1            // InterfaceMethod org/jboss/as/protocol/mgmt/ActiveOperation.getResult:()Lorg/jboss/threads/AsyncFuture;
      26: invokeinterface #9,  1            // InterfaceMethod org/jboss/threads/AsyncFuture.get:()Ljava/lang/Object;
      31: checkcast     #10                 // class java/io/File
      34: areturn
      35: astore        4
      37: getstatic     #12                 // Field org/jboss/as/server/logging/ServerLogger.ROOT_LOGGER:Lorg/jboss/as/server/logging/ServerLogger;
      40: aload         4
      42: invokeinterface #13,  2           // InterfaceMethod org/jboss/as/server/logging/ServerLogger.failedToGetFileFromRemoteRepository:(Ljava/lang/Throwable;)Ljava/lang/RuntimeException;
      47: athrow
    Exception table:
       from    to  target type
           0    34    35   Class java/lang/Exception

  org.jboss.as.server.mgmt.domain.HostControllerClient$RemoteFileRepositoryExecutorImpl(org.jboss.as.server.mgmt.domain.HostControllerClient, org.jboss.as.server.mgmt.domain.HostControllerClient$1);
    Code:
       0: aload_0
       1: aload_1
       2: invokespecial #1                  // Method "<init>":(Lorg/jboss/as/server/mgmt/domain/HostControllerClient;)V
       5: return
}
