Compiled from "BsonStringCodec.java"
public class org.bson.codecs.BsonStringCodec implements org.bson.codecs.Codec<org.bson.BsonString> {
  public org.bson.codecs.BsonStringCodec();
    Code:
       0: aload_0
       1: invokespecial #1                  // Method java/lang/Object."<init>":()V
       4: return

  public org.bson.BsonString decode(org.bson.BsonReader, org.bson.codecs.DecoderContext);
    Code:
       0: new           #2                  // class org/bson/BsonString
       3: dup
       4: aload_1
       5: invokeinterface #3,  1            // InterfaceMethod org/bson/BsonReader.readString:()Ljava/lang/String;
      10: invokespecial #4                  // Method org/bson/BsonString."<init>":(Ljava/lang/String;)V
      13: areturn

  public void encode(org.bson.BsonWriter, org.bson.BsonString, org.bson.codecs.EncoderContext);
    Code:
       0: aload_1
       1: aload_2
       2: invokevirtual #5                  // Method org/bson/BsonString.getValue:()Ljava/lang/String;
       5: invokeinterface #6,  2            // InterfaceMethod org/bson/BsonWriter.writeString:(Ljava/lang/String;)V
      10: return

  public java.lang.Class<org.bson.BsonString> getEncoderClass();
    Code:
       0: ldc           #2                  // class org/bson/BsonString
       2: areturn

  public void encode(org.bson.BsonWriter, java.lang.Object, org.bson.codecs.EncoderContext);
    Code:
       0: aload_0
       1: aload_1
       2: aload_2
       3: checkcast     #2                  // class org/bson/BsonString
       6: aload_3
       7: invokevirtual #7                  // Method encode:(Lorg/bson/BsonWriter;Lorg/bson/BsonString;Lorg/bson/codecs/EncoderContext;)V
      10: return

  public java.lang.Object decode(org.bson.BsonReader, org.bson.codecs.DecoderContext);
    Code:
       0: aload_0
       1: aload_1
       2: aload_2
       3: invokevirtual #8                  // Method decode:(Lorg/bson/BsonReader;Lorg/bson/codecs/DecoderContext;)Lorg/bson/BsonString;
       6: areturn
}
