Compiled from "BsonJavaScriptWithScopeCodec.java"
public class org.bson.codecs.BsonJavaScriptWithScopeCodec implements org.bson.codecs.Codec<org.bson.BsonJavaScriptWithScope> {
  private final org.bson.codecs.Codec<org.bson.BsonDocument> documentCodec;

  public org.bson.codecs.BsonJavaScriptWithScopeCodec(org.bson.codecs.Codec<org.bson.BsonDocument>);
    Code:
       0: aload_0
       1: invokespecial #1                  // Method java/lang/Object."<init>":()V
       4: aload_0
       5: aload_1
       6: putfield      #2                  // Field documentCodec:Lorg/bson/codecs/Codec;
       9: return

  public org.bson.BsonJavaScriptWithScope decode(org.bson.BsonReader, org.bson.codecs.DecoderContext);
    Code:
       0: aload_1
       1: invokeinterface #3,  1            // InterfaceMethod org/bson/BsonReader.readJavaScriptWithScope:()Ljava/lang/String;
       6: astore_3
       7: aload_0
       8: getfield      #2                  // Field documentCodec:Lorg/bson/codecs/Codec;
      11: aload_1
      12: aload_2
      13: invokeinterface #4,  3            // InterfaceMethod org/bson/codecs/Codec.decode:(Lorg/bson/BsonReader;Lorg/bson/codecs/DecoderContext;)Ljava/lang/Object;
      18: checkcast     #5                  // class org/bson/BsonDocument
      21: astore        4
      23: new           #6                  // class org/bson/BsonJavaScriptWithScope
      26: dup
      27: aload_3
      28: aload         4
      30: invokespecial #7                  // Method org/bson/BsonJavaScriptWithScope."<init>":(Ljava/lang/String;Lorg/bson/BsonDocument;)V
      33: areturn

  public void encode(org.bson.BsonWriter, org.bson.BsonJavaScriptWithScope, org.bson.codecs.EncoderContext);
    Code:
       0: aload_1
       1: aload_2
       2: invokevirtual #8                  // Method org/bson/BsonJavaScriptWithScope.getCode:()Ljava/lang/String;
       5: invokeinterface #9,  2            // InterfaceMethod org/bson/BsonWriter.writeJavaScriptWithScope:(Ljava/lang/String;)V
      10: aload_0
      11: getfield      #2                  // Field documentCodec:Lorg/bson/codecs/Codec;
      14: aload_1
      15: aload_2
      16: invokevirtual #10                 // Method org/bson/BsonJavaScriptWithScope.getScope:()Lorg/bson/BsonDocument;
      19: aload_3
      20: invokeinterface #11,  4           // InterfaceMethod org/bson/codecs/Codec.encode:(Lorg/bson/BsonWriter;Ljava/lang/Object;Lorg/bson/codecs/EncoderContext;)V
      25: return

  public java.lang.Class<org.bson.BsonJavaScriptWithScope> getEncoderClass();
    Code:
       0: ldc           #6                  // class org/bson/BsonJavaScriptWithScope
       2: areturn

  public void encode(org.bson.BsonWriter, java.lang.Object, org.bson.codecs.EncoderContext);
    Code:
       0: aload_0
       1: aload_1
       2: aload_2
       3: checkcast     #6                  // class org/bson/BsonJavaScriptWithScope
       6: aload_3
       7: invokevirtual #12                 // Method encode:(Lorg/bson/BsonWriter;Lorg/bson/BsonJavaScriptWithScope;Lorg/bson/codecs/EncoderContext;)V
      10: return

  public java.lang.Object decode(org.bson.BsonReader, org.bson.codecs.DecoderContext);
    Code:
       0: aload_0
       1: aload_1
       2: aload_2
       3: invokevirtual #13                 // Method decode:(Lorg/bson/BsonReader;Lorg/bson/codecs/DecoderContext;)Lorg/bson/BsonJavaScriptWithScope;
       6: areturn
}
