Compiled from "CharacterCodec.java"
public class org.bson.codecs.CharacterCodec implements org.bson.codecs.Codec<java.lang.Character> {
  public org.bson.codecs.CharacterCodec();
    Code:
       0: aload_0
       1: invokespecial #1                  // Method java/lang/Object."<init>":()V
       4: return

  public void encode(org.bson.BsonWriter, java.lang.Character, org.bson.codecs.EncoderContext);
    Code:
       0: ldc           #2                  // String value
       2: aload_2
       3: invokestatic  #3                  // Method org/bson/assertions/Assertions.notNull:(Ljava/lang/String;Ljava/lang/Object;)Ljava/lang/Object;
       6: pop
       7: aload_1
       8: aload_2
       9: invokevirtual #4                  // Method java/lang/Character.toString:()Ljava/lang/String;
      12: invokeinterface #5,  2            // InterfaceMethod org/bson/BsonWriter.writeString:(Ljava/lang/String;)V
      17: return

  public java.lang.Character decode(org.bson.BsonReader, org.bson.codecs.DecoderContext);
    Code:
       0: aload_1
       1: invokeinterface #6,  1            // InterfaceMethod org/bson/BsonReader.readString:()Ljava/lang/String;
       6: astore_3
       7: aload_3
       8: invokevirtual #7                  // Method java/lang/String.length:()I
      11: iconst_1
      12: if_icmpeq     36
      15: new           #8                  // class org/bson/BsonInvalidOperationException
      18: dup
      19: ldc           #9                  // String Attempting to decode the string \'%s\' to a character, but its length is not equal to one
      21: iconst_1
      22: anewarray     #10                 // class java/lang/Object
      25: dup
      26: iconst_0
      27: aload_3
      28: aastore
      29: invokestatic  #11                 // Method java/lang/String.format:(Ljava/lang/String;[Ljava/lang/Object;)Ljava/lang/String;
      32: invokespecial #12                 // Method org/bson/BsonInvalidOperationException."<init>":(Ljava/lang/String;)V
      35: athrow
      36: aload_3
      37: iconst_0
      38: invokevirtual #13                 // Method java/lang/String.charAt:(I)C
      41: invokestatic  #14                 // Method java/lang/Character.valueOf:(C)Ljava/lang/Character;
      44: areturn

  public java.lang.Class<java.lang.Character> getEncoderClass();
    Code:
       0: ldc           #15                 // class java/lang/Character
       2: areturn

  public void encode(org.bson.BsonWriter, java.lang.Object, org.bson.codecs.EncoderContext);
    Code:
       0: aload_0
       1: aload_1
       2: aload_2
       3: checkcast     #15                 // class java/lang/Character
       6: aload_3
       7: invokevirtual #16                 // Method encode:(Lorg/bson/BsonWriter;Ljava/lang/Character;Lorg/bson/codecs/EncoderContext;)V
      10: return

  public java.lang.Object decode(org.bson.BsonReader, org.bson.codecs.DecoderContext);
    Code:
       0: aload_0
       1: aload_1
       2: aload_2
       3: invokevirtual #17                 // Method decode:(Lorg/bson/BsonReader;Lorg/bson/codecs/DecoderContext;)Ljava/lang/Character;
       6: areturn
}
