Compiled from "Count.java"
public class org.apache.hadoop.fs.shell.Count extends org.apache.hadoop.fs.shell.FsCommand {
  private static final java.lang.String OPTION_QUOTA;

  private static final java.lang.String OPTION_HUMAN;

  private static final java.lang.String OPTION_HEADER;

  private static final java.lang.String OPTION_TYPE;

  private static final java.lang.String OPTION_EXCLUDE_SNAPSHOT;

  private static final java.lang.String OPTION_QUOTA_AND_USAGE;

  private static final java.lang.String OPTION_ECPOLICY;

  public static final java.lang.String NAME;

  public static final java.lang.String USAGE;

  public static final java.lang.String DESCRIPTION;

  private boolean showQuotas;

  private boolean humanReadable;

  private boolean showQuotabyType;

  private java.util.List<org.apache.hadoop.fs.StorageType> storageTypes;

  private boolean showQuotasAndUsageOnly;

  private boolean excludeSnapshots;

  private boolean displayECPolicy;

  public static void registerCommands(org.apache.hadoop.fs.shell.CommandFactory);
    Code:
       0: aload_0
       1: ldc           #1                  // class org/apache/hadoop/fs/shell/Count
       3: iconst_1
       4: anewarray     #2                  // class java/lang/String
       7: dup
       8: iconst_0
       9: ldc           #3                  // String -count
      11: aastore
      12: invokevirtual #4                  // Method org/apache/hadoop/fs/shell/CommandFactory.addClass:(Ljava/lang/Class;[Ljava/lang/String;)V
      15: return

  public org.apache.hadoop.fs.shell.Count();
    Code:
       0: aload_0
       1: invokespecial #5                  // Method org/apache/hadoop/fs/shell/FsCommand."<init>":()V
       4: aload_0
       5: aconst_null
       6: putfield      #6                  // Field storageTypes:Ljava/util/List;
       9: return

  public org.apache.hadoop.fs.shell.Count(java.lang.String[], int, org.apache.hadoop.conf.Configuration);
    Code:
       0: aload_0
       1: aload_3
       2: invokespecial #7                  // Method org/apache/hadoop/fs/shell/FsCommand."<init>":(Lorg/apache/hadoop/conf/Configuration;)V
       5: aload_0
       6: aconst_null
       7: putfield      #6                  // Field storageTypes:Ljava/util/List;
      10: aload_0
      11: aload_1
      12: iload_2
      13: aload_1
      14: arraylength
      15: invokestatic  #8                  // Method java/util/Arrays.copyOfRange:([Ljava/lang/Object;II)[Ljava/lang/Object;
      18: checkcast     #9                  // class "[Ljava/lang/String;"
      21: putfield      #10                 // Field args:[Ljava/lang/String;
      24: return

  protected void processOptions(java.util.LinkedList<java.lang.String>);
    Code:
       0: new           #11                 // class org/apache/hadoop/fs/shell/CommandFormat
       3: dup
       4: iconst_1
       5: ldc           #13                 // int 2147483647
       7: bipush        6
       9: anewarray     #2                  // class java/lang/String
      12: dup
      13: iconst_0
      14: ldc           #14                 // String q
      16: aastore
      17: dup
      18: iconst_1
      19: ldc           #15                 // String h
      21: aastore
      22: dup
      23: iconst_2
      24: ldc           #16                 // String v
      26: aastore
      27: dup
      28: iconst_3
      29: ldc           #17                 // String u
      31: aastore
      32: dup
      33: iconst_4
      34: ldc           #18                 // String x
      36: aastore
      37: dup
      38: iconst_5
      39: ldc           #19                 // String e
      41: aastore
      42: invokespecial #20                 // Method org/apache/hadoop/fs/shell/CommandFormat."<init>":(II[Ljava/lang/String;)V
      45: astore_2
      46: aload_2
      47: ldc           #21                 // String t
      49: invokevirtual #22                 // Method org/apache/hadoop/fs/shell/CommandFormat.addOptionWithValue:(Ljava/lang/String;)V
      52: aload_2
      53: aload_1
      54: invokevirtual #23                 // Method org/apache/hadoop/fs/shell/CommandFormat.parse:(Ljava/util/List;)V
      57: aload_1
      58: invokevirtual #24                 // Method java/util/LinkedList.isEmpty:()Z
      61: ifeq          71
      64: aload_1
      65: ldc           #25                 // String .
      67: invokevirtual #26                 // Method java/util/LinkedList.add:(Ljava/lang/Object;)Z
      70: pop
      71: aload_0
      72: aload_2
      73: ldc           #14                 // String q
      75: invokevirtual #27                 // Method org/apache/hadoop/fs/shell/CommandFormat.getOpt:(Ljava/lang/String;)Z
      78: putfield      #28                 // Field showQuotas:Z
      81: aload_0
      82: aload_2
      83: ldc           #15                 // String h
      85: invokevirtual #27                 // Method org/apache/hadoop/fs/shell/CommandFormat.getOpt:(Ljava/lang/String;)Z
      88: putfield      #29                 // Field humanReadable:Z
      91: aload_0
      92: aload_2
      93: ldc           #17                 // String u
      95: invokevirtual #27                 // Method org/apache/hadoop/fs/shell/CommandFormat.getOpt:(Ljava/lang/String;)Z
      98: putfield      #30                 // Field showQuotasAndUsageOnly:Z
     101: aload_0
     102: aload_2
     103: ldc           #18                 // String x
     105: invokevirtual #27                 // Method org/apache/hadoop/fs/shell/CommandFormat.getOpt:(Ljava/lang/String;)Z
     108: putfield      #31                 // Field excludeSnapshots:Z
     111: aload_0
     112: aload_2
     113: ldc           #19                 // String e
     115: invokevirtual #27                 // Method org/apache/hadoop/fs/shell/CommandFormat.getOpt:(Ljava/lang/String;)Z
     118: putfield      #32                 // Field displayECPolicy:Z
     121: aload_0
     122: getfield      #28                 // Field showQuotas:Z
     125: ifne          135
     128: aload_0
     129: getfield      #30                 // Field showQuotasAndUsageOnly:Z
     132: ifeq          190
     135: aload_2
     136: ldc           #21                 // String t
     138: invokevirtual #33                 // Method org/apache/hadoop/fs/shell/CommandFormat.getOptValue:(Ljava/lang/String;)Ljava/lang/String;
     141: astore_3
     142: aconst_null
     143: aload_3
     144: if_acmpeq     164
     147: aload_0
     148: iconst_1
     149: putfield      #34                 // Field showQuotabyType:Z
     152: aload_0
     153: aload_0
     154: aload_3
     155: invokespecial #35                 // Method getAndCheckStorageTypes:(Ljava/lang/String;)Ljava/util/List;
     158: putfield      #6                  // Field storageTypes:Ljava/util/List;
     161: goto          169
     164: aload_0
     165: iconst_0
     166: putfield      #34                 // Field showQuotabyType:Z
     169: aload_0
     170: getfield      #31                 // Field excludeSnapshots:Z
     173: ifeq          190
     176: aload_0
     177: getfield      #36                 // Field out:Ljava/io/PrintStream;
     180: ldc           #37                 // String q or u option is given, the -x option is ignored.
     182: invokevirtual #38                 // Method java/io/PrintStream.println:(Ljava/lang/String;)V
     185: aload_0
     186: iconst_0
     187: putfield      #31                 // Field excludeSnapshots:Z
     190: aload_2
     191: ldc           #16                 // String v
     193: invokevirtual #27                 // Method org/apache/hadoop/fs/shell/CommandFormat.getOpt:(Ljava/lang/String;)Z
     196: ifeq          291
     199: new           #39                 // class java/lang/StringBuilder
     202: dup
     203: invokespecial #40                 // Method java/lang/StringBuilder."<init>":()V
     206: astore_3
     207: aload_0
     208: getfield      #34                 // Field showQuotabyType:Z
     211: ifeq          229
     214: aload_3
     215: aload_0
     216: getfield      #6                  // Field storageTypes:Ljava/util/List;
     219: invokestatic  #41                 // Method org/apache/hadoop/fs/QuotaUsage.getStorageTypeHeader:(Ljava/util/List;)Ljava/lang/String;
     222: invokevirtual #42                 // Method java/lang/StringBuilder.append:(Ljava/lang/String;)Ljava/lang/StringBuilder;
     225: pop
     226: goto          259
     229: aload_0
     230: getfield      #30                 // Field showQuotasAndUsageOnly:Z
     233: ifeq          247
     236: aload_3
     237: invokestatic  #43                 // Method org/apache/hadoop/fs/QuotaUsage.getHeader:()Ljava/lang/String;
     240: invokevirtual #42                 // Method java/lang/StringBuilder.append:(Ljava/lang/String;)Ljava/lang/StringBuilder;
     243: pop
     244: goto          259
     247: aload_3
     248: aload_0
     249: getfield      #28                 // Field showQuotas:Z
     252: invokestatic  #44                 // Method org/apache/hadoop/fs/ContentSummary.getHeader:(Z)Ljava/lang/String;
     255: invokevirtual #42                 // Method java/lang/StringBuilder.append:(Ljava/lang/String;)Ljava/lang/StringBuilder;
     258: pop
     259: aload_0
     260: getfield      #32                 // Field displayECPolicy:Z
     263: ifeq          273
     266: aload_3
     267: ldc           #45                 // String ERASURECODING_POLICY
     269: invokevirtual #42                 // Method java/lang/StringBuilder.append:(Ljava/lang/String;)Ljava/lang/StringBuilder;
     272: pop
     273: aload_3
     274: ldc           #46                 // String PATHNAME
     276: invokevirtual #42                 // Method java/lang/StringBuilder.append:(Ljava/lang/String;)Ljava/lang/StringBuilder;
     279: pop
     280: aload_0
     281: getfield      #36                 // Field out:Ljava/io/PrintStream;
     284: aload_3
     285: invokevirtual #47                 // Method java/lang/StringBuilder.toString:()Ljava/lang/String;
     288: invokevirtual #38                 // Method java/io/PrintStream.println:(Ljava/lang/String;)V
     291: return

  private java.util.List<org.apache.hadoop.fs.StorageType> getAndCheckStorageTypes(java.lang.String);
    Code:
       0: ldc           #48                 // String
       2: aload_1
       3: invokevirtual #49                 // Method java/lang/String.equals:(Ljava/lang/Object;)Z
       6: ifne          18
       9: ldc           #50                 // String all
      11: aload_1
      12: invokevirtual #51                 // Method java/lang/String.equalsIgnoreCase:(Ljava/lang/String;)Z
      15: ifeq          22
      18: invokestatic  #52                 // Method org/apache/hadoop/fs/StorageType.getTypesSupportingQuota:()Ljava/util/List;
      21: areturn
      22: aload_1
      23: bipush        44
      25: invokestatic  #53                 // Method org/apache/commons/lang3/StringUtils.split:(Ljava/lang/String;C)[Ljava/lang/String;
      28: astore_2
      29: new           #54                 // class java/util/ArrayList
      32: dup
      33: invokespecial #55                 // Method java/util/ArrayList."<init>":()V
      36: astore_3
      37: aload_2
      38: astore        4
      40: aload         4
      42: arraylength
      43: istore        5
      45: iconst_0
      46: istore        6
      48: iload         6
      50: iload         5
      52: if_icmpge     80
      55: aload         4
      57: iload         6
      59: aaload
      60: astore        7
      62: aload_3
      63: aload         7
      65: invokestatic  #56                 // Method org/apache/hadoop/fs/StorageType.parseStorageType:(Ljava/lang/String;)Lorg/apache/hadoop/fs/StorageType;
      68: invokeinterface #57,  2           // InterfaceMethod java/util/List.add:(Ljava/lang/Object;)Z
      73: pop
      74: iinc          6, 1
      77: goto          48
      80: aload_3
      81: areturn

  protected void processPath(org.apache.hadoop.fs.shell.PathData) throws java.io.IOException;
    Code:
       0: new           #39                 // class java/lang/StringBuilder
       3: dup
       4: invokespecial #40                 // Method java/lang/StringBuilder."<init>":()V
       7: astore_2
       8: aload_0
       9: getfield      #30                 // Field showQuotasAndUsageOnly:Z
      12: ifne          22
      15: aload_0
      16: getfield      #34                 // Field showQuotabyType:Z
      19: ifeq          58
      22: aload_1
      23: getfield      #58                 // Field org/apache/hadoop/fs/shell/PathData.fs:Lorg/apache/hadoop/fs/FileSystem;
      26: aload_1
      27: getfield      #59                 // Field org/apache/hadoop/fs/shell/PathData.path:Lorg/apache/hadoop/fs/Path;
      30: invokevirtual #60                 // Method org/apache/hadoop/fs/FileSystem.getQuotaUsage:(Lorg/apache/hadoop/fs/Path;)Lorg/apache/hadoop/fs/QuotaUsage;
      33: astore_3
      34: aload_2
      35: aload_3
      36: aload_0
      37: invokevirtual #61                 // Method isHumanReadable:()Z
      40: aload_0
      41: getfield      #34                 // Field showQuotabyType:Z
      44: aload_0
      45: getfield      #6                  // Field storageTypes:Ljava/util/List;
      48: invokevirtual #62                 // Method org/apache/hadoop/fs/QuotaUsage.toString:(ZZLjava/util/List;)Ljava/lang/String;
      51: invokevirtual #42                 // Method java/lang/StringBuilder.append:(Ljava/lang/String;)Ljava/lang/StringBuilder;
      54: pop
      55: goto          91
      58: aload_1
      59: getfield      #58                 // Field org/apache/hadoop/fs/shell/PathData.fs:Lorg/apache/hadoop/fs/FileSystem;
      62: aload_1
      63: getfield      #59                 // Field org/apache/hadoop/fs/shell/PathData.path:Lorg/apache/hadoop/fs/Path;
      66: invokevirtual #63                 // Method org/apache/hadoop/fs/FileSystem.getContentSummary:(Lorg/apache/hadoop/fs/Path;)Lorg/apache/hadoop/fs/ContentSummary;
      69: astore_3
      70: aload_2
      71: aload_3
      72: aload_0
      73: getfield      #28                 // Field showQuotas:Z
      76: aload_0
      77: invokevirtual #61                 // Method isHumanReadable:()Z
      80: aload_0
      81: getfield      #31                 // Field excludeSnapshots:Z
      84: invokevirtual #64                 // Method org/apache/hadoop/fs/ContentSummary.toString:(ZZZ)Ljava/lang/String;
      87: invokevirtual #42                 // Method java/lang/StringBuilder.append:(Ljava/lang/String;)Ljava/lang/StringBuilder;
      90: pop
      91: aload_0
      92: getfield      #32                 // Field displayECPolicy:Z
      95: ifeq          145
      98: aload_1
      99: getfield      #58                 // Field org/apache/hadoop/fs/shell/PathData.fs:Lorg/apache/hadoop/fs/FileSystem;
     102: aload_1
     103: getfield      #59                 // Field org/apache/hadoop/fs/shell/PathData.path:Lorg/apache/hadoop/fs/Path;
     106: invokevirtual #63                 // Method org/apache/hadoop/fs/FileSystem.getContentSummary:(Lorg/apache/hadoop/fs/Path;)Lorg/apache/hadoop/fs/ContentSummary;
     109: astore_3
     110: aload_3
     111: invokevirtual #65                 // Method org/apache/hadoop/fs/ContentSummary.getErasureCodingPolicy:()Ljava/lang/String;
     114: ldc           #66                 // String Replicated
     116: invokevirtual #49                 // Method java/lang/String.equals:(Ljava/lang/Object;)Z
     119: ifne          129
     122: aload_2
     123: ldc           #67                 // String EC:
     125: invokevirtual #42                 // Method java/lang/StringBuilder.append:(Ljava/lang/String;)Ljava/lang/StringBuilder;
     128: pop
     129: aload_2
     130: aload_3
     131: invokevirtual #65                 // Method org/apache/hadoop/fs/ContentSummary.getErasureCodingPolicy:()Ljava/lang/String;
     134: invokevirtual #42                 // Method java/lang/StringBuilder.append:(Ljava/lang/String;)Ljava/lang/StringBuilder;
     137: pop
     138: aload_2
     139: ldc           #68                 // String
     141: invokevirtual #42                 // Method java/lang/StringBuilder.append:(Ljava/lang/String;)Ljava/lang/StringBuilder;
     144: pop
     145: aload_2
     146: aload_1
     147: invokevirtual #69                 // Method java/lang/StringBuilder.append:(Ljava/lang/Object;)Ljava/lang/StringBuilder;
     150: pop
     151: aload_0
     152: getfield      #36                 // Field out:Ljava/io/PrintStream;
     155: aload_2
     156: invokevirtual #47                 // Method java/lang/StringBuilder.toString:()Ljava/lang/String;
     159: invokevirtual #38                 // Method java/io/PrintStream.println:(Ljava/lang/String;)V
     162: return

  boolean isShowQuotas();
    Code:
       0: aload_0
       1: getfield      #28                 // Field showQuotas:Z
       4: ireturn

  boolean isHumanReadable();
    Code:
       0: aload_0
       1: getfield      #29                 // Field humanReadable:Z
       4: ireturn

  boolean isShowQuotabyType();
    Code:
       0: aload_0
       1: getfield      #34                 // Field showQuotabyType:Z
       4: ireturn

  java.util.List<org.apache.hadoop.fs.StorageType> getStorageTypes();
    Code:
       0: aload_0
       1: getfield      #6                  // Field storageTypes:Ljava/util/List;
       4: areturn

  static {};
    Code:
       0: new           #39                 // class java/lang/StringBuilder
       3: dup
       4: invokespecial #40                 // Method java/lang/StringBuilder."<init>":()V
       7: ldc           #70                 // String Count the number of directories, files and bytes under the paths\nthat match the specified file pattern.  The output columns are:\n
       9: invokevirtual #42                 // Method java/lang/StringBuilder.append:(Ljava/lang/String;)Ljava/lang/StringBuilder;
      12: invokestatic  #71                 // Method org/apache/hadoop/fs/ContentSummary.getHeaderFields:()[Ljava/lang/String;
      15: bipush        32
      17: invokestatic  #72                 // Method org/apache/commons/lang3/StringUtils.join:([Ljava/lang/Object;C)Ljava/lang/String;
      20: invokevirtual #42                 // Method java/lang/StringBuilder.append:(Ljava/lang/String;)Ljava/lang/StringBuilder;
      23: ldc           #73                 // String  PATHNAME\nor, with the -
      25: invokevirtual #42                 // Method java/lang/StringBuilder.append:(Ljava/lang/String;)Ljava/lang/StringBuilder;
      28: ldc           #14                 // String q
      30: invokevirtual #42                 // Method java/lang/StringBuilder.append:(Ljava/lang/String;)Ljava/lang/StringBuilder;
      33: ldc           #74                 // String  option:\n
      35: invokevirtual #42                 // Method java/lang/StringBuilder.append:(Ljava/lang/String;)Ljava/lang/StringBuilder;
      38: invokestatic  #75                 // Method org/apache/hadoop/fs/ContentSummary.getQuotaHeaderFields:()[Ljava/lang/String;
      41: bipush        32
      43: invokestatic  #72                 // Method org/apache/commons/lang3/StringUtils.join:([Ljava/lang/Object;C)Ljava/lang/String;
      46: invokevirtual #42                 // Method java/lang/StringBuilder.append:(Ljava/lang/String;)Ljava/lang/StringBuilder;
      49: ldc           #76                 // String \n
      51: invokevirtual #42                 // Method java/lang/StringBuilder.append:(Ljava/lang/String;)Ljava/lang/StringBuilder;
      54: invokestatic  #71                 // Method org/apache/hadoop/fs/ContentSummary.getHeaderFields:()[Ljava/lang/String;
      57: bipush        32
      59: invokestatic  #72                 // Method org/apache/commons/lang3/StringUtils.join:([Ljava/lang/Object;C)Ljava/lang/String;
      62: invokevirtual #42                 // Method java/lang/StringBuilder.append:(Ljava/lang/String;)Ljava/lang/StringBuilder;
      65: ldc           #77                 // String  PATHNAME\nThe -
      67: invokevirtual #42                 // Method java/lang/StringBuilder.append:(Ljava/lang/String;)Ljava/lang/StringBuilder;
      70: ldc           #15                 // String h
      72: invokevirtual #42                 // Method java/lang/StringBuilder.append:(Ljava/lang/String;)Ljava/lang/StringBuilder;
      75: ldc           #78                 // String  option shows file sizes in human readable format.\nThe -
      77: invokevirtual #42                 // Method java/lang/StringBuilder.append:(Ljava/lang/String;)Ljava/lang/StringBuilder;
      80: ldc           #16                 // String v
      82: invokevirtual #42                 // Method java/lang/StringBuilder.append:(Ljava/lang/String;)Ljava/lang/StringBuilder;
      85: ldc           #79                 // String  option displays a header line.\nThe -
      87: invokevirtual #42                 // Method java/lang/StringBuilder.append:(Ljava/lang/String;)Ljava/lang/StringBuilder;
      90: ldc           #18                 // String x
      92: invokevirtual #42                 // Method java/lang/StringBuilder.append:(Ljava/lang/String;)Ljava/lang/StringBuilder;
      95: ldc           #80                 // String  option excludes snapshots from being calculated. \nThe -
      97: invokevirtual #42                 // Method java/lang/StringBuilder.append:(Ljava/lang/String;)Ljava/lang/StringBuilder;
     100: ldc           #21                 // String t
     102: invokevirtual #42                 // Method java/lang/StringBuilder.append:(Ljava/lang/String;)Ljava/lang/StringBuilder;
     105: ldc           #81                 // String  option displays quota by storage types.\nIt should be used with -
     107: invokevirtual #42                 // Method java/lang/StringBuilder.append:(Ljava/lang/String;)Ljava/lang/StringBuilder;
     110: ldc           #14                 // String q
     112: invokevirtual #42                 // Method java/lang/StringBuilder.append:(Ljava/lang/String;)Ljava/lang/StringBuilder;
     115: ldc           #82                 // String  or -
     117: invokevirtual #42                 // Method java/lang/StringBuilder.append:(Ljava/lang/String;)Ljava/lang/StringBuilder;
     120: ldc           #17                 // String u
     122: invokevirtual #42                 // Method java/lang/StringBuilder.append:(Ljava/lang/String;)Ljava/lang/StringBuilder;
     125: ldc           #83                 // String  option, otherwise it will be ignored.\nIf a comma-separated list of storage types is given after the -
     127: invokevirtual #42                 // Method java/lang/StringBuilder.append:(Ljava/lang/String;)Ljava/lang/StringBuilder;
     130: ldc           #21                 // String t
     132: invokevirtual #42                 // Method java/lang/StringBuilder.append:(Ljava/lang/String;)Ljava/lang/StringBuilder;
     135: ldc           #84                 // String  option, \nit displays the quota and usage for the specified types. \nOtherwise, it displays the quota and usage for all the storage \ntypes that support quota. The list of possible storage types(case insensitive):\nram_disk, ssd, disk and archive.\nIt can also pass the value \'\', \'all\' or \'ALL\' to specify all the storage types.\nThe -
     137: invokevirtual #42                 // Method java/lang/StringBuilder.append:(Ljava/lang/String;)Ljava/lang/StringBuilder;
     140: ldc           #17                 // String u
     142: invokevirtual #42                 // Method java/lang/StringBuilder.append:(Ljava/lang/String;)Ljava/lang/StringBuilder;
     145: ldc           #85                 // String  option shows the quota and \nthe usage against the quota without the detailed content summary.The -
     147: invokevirtual #42                 // Method java/lang/StringBuilder.append:(Ljava/lang/String;)Ljava/lang/StringBuilder;
     150: ldc           #19                 // String e
     152: invokevirtual #42                 // Method java/lang/StringBuilder.append:(Ljava/lang/String;)Ljava/lang/StringBuilder;
     155: ldc           #86                 // String  option shows the erasure coding policy.
     157: invokevirtual #42                 // Method java/lang/StringBuilder.append:(Ljava/lang/String;)Ljava/lang/StringBuilder;
     160: invokevirtual #47                 // Method java/lang/StringBuilder.toString:()Ljava/lang/String;
     163: putstatic     #87                 // Field DESCRIPTION:Ljava/lang/String;
     166: return
}
