Compiled from "FsCommand.java"
public abstract class org.apache.hadoop.fs.shell.FsCommand extends org.apache.hadoop.fs.shell.Command {
  public static void registerCommands(org.apache.hadoop.fs.shell.CommandFactory);
    Code:
       0: aload_0
       1: ldc           #2                  // class org/apache/hadoop/fs/shell/AclCommands
       3: invokevirtual #3                  // Method org/apache/hadoop/fs/shell/CommandFactory.registerCommands:(Ljava/lang/Class;)V
       6: aload_0
       7: ldc           #4                  // class org/apache/hadoop/fs/shell/CopyCommands
       9: invokevirtual #3                  // Method org/apache/hadoop/fs/shell/CommandFactory.registerCommands:(Ljava/lang/Class;)V
      12: aload_0
      13: ldc           #5                  // class org/apache/hadoop/fs/shell/Count
      15: invokevirtual #3                  // Method org/apache/hadoop/fs/shell/CommandFactory.registerCommands:(Ljava/lang/Class;)V
      18: aload_0
      19: ldc           #6                  // class org/apache/hadoop/fs/shell/Delete
      21: invokevirtual #3                  // Method org/apache/hadoop/fs/shell/CommandFactory.registerCommands:(Ljava/lang/Class;)V
      24: aload_0
      25: ldc           #7                  // class org/apache/hadoop/fs/shell/Display
      27: invokevirtual #3                  // Method org/apache/hadoop/fs/shell/CommandFactory.registerCommands:(Ljava/lang/Class;)V
      30: aload_0
      31: ldc           #8                  // class org/apache/hadoop/fs/shell/find/Find
      33: invokevirtual #3                  // Method org/apache/hadoop/fs/shell/CommandFactory.registerCommands:(Ljava/lang/Class;)V
      36: aload_0
      37: ldc           #9                  // class org/apache/hadoop/fs/FsShellPermissions
      39: invokevirtual #3                  // Method org/apache/hadoop/fs/shell/CommandFactory.registerCommands:(Ljava/lang/Class;)V
      42: aload_0
      43: ldc           #10                 // class org/apache/hadoop/fs/shell/FsUsage
      45: invokevirtual #3                  // Method org/apache/hadoop/fs/shell/CommandFactory.registerCommands:(Ljava/lang/Class;)V
      48: aload_0
      49: ldc           #11                 // class org/apache/hadoop/fs/shell/Ls
      51: invokevirtual #3                  // Method org/apache/hadoop/fs/shell/CommandFactory.registerCommands:(Ljava/lang/Class;)V
      54: aload_0
      55: ldc           #12                 // class org/apache/hadoop/fs/shell/Mkdir
      57: invokevirtual #3                  // Method org/apache/hadoop/fs/shell/CommandFactory.registerCommands:(Ljava/lang/Class;)V
      60: aload_0
      61: ldc           #13                 // class org/apache/hadoop/fs/shell/MoveCommands
      63: invokevirtual #3                  // Method org/apache/hadoop/fs/shell/CommandFactory.registerCommands:(Ljava/lang/Class;)V
      66: aload_0
      67: ldc           #14                 // class org/apache/hadoop/fs/shell/SetReplication
      69: invokevirtual #3                  // Method org/apache/hadoop/fs/shell/CommandFactory.registerCommands:(Ljava/lang/Class;)V
      72: aload_0
      73: ldc           #15                 // class org/apache/hadoop/fs/shell/Stat
      75: invokevirtual #3                  // Method org/apache/hadoop/fs/shell/CommandFactory.registerCommands:(Ljava/lang/Class;)V
      78: aload_0
      79: ldc           #16                 // class org/apache/hadoop/fs/shell/Tail
      81: invokevirtual #3                  // Method org/apache/hadoop/fs/shell/CommandFactory.registerCommands:(Ljava/lang/Class;)V
      84: aload_0
      85: ldc           #17                 // class org/apache/hadoop/fs/shell/Head
      87: invokevirtual #3                  // Method org/apache/hadoop/fs/shell/CommandFactory.registerCommands:(Ljava/lang/Class;)V
      90: aload_0
      91: ldc           #18                 // class org/apache/hadoop/fs/shell/Test
      93: invokevirtual #3                  // Method org/apache/hadoop/fs/shell/CommandFactory.registerCommands:(Ljava/lang/Class;)V
      96: aload_0
      97: ldc           #19                 // class org/apache/hadoop/fs/shell/TouchCommands
      99: invokevirtual #3                  // Method org/apache/hadoop/fs/shell/CommandFactory.registerCommands:(Ljava/lang/Class;)V
     102: aload_0
     103: ldc           #20                 // class org/apache/hadoop/fs/shell/Truncate
     105: invokevirtual #3                  // Method org/apache/hadoop/fs/shell/CommandFactory.registerCommands:(Ljava/lang/Class;)V
     108: aload_0
     109: ldc           #21                 // class org/apache/hadoop/fs/shell/SnapshotCommands
     111: invokevirtual #3                  // Method org/apache/hadoop/fs/shell/CommandFactory.registerCommands:(Ljava/lang/Class;)V
     114: aload_0
     115: ldc           #22                 // class org/apache/hadoop/fs/shell/XAttrCommands
     117: invokevirtual #3                  // Method org/apache/hadoop/fs/shell/CommandFactory.registerCommands:(Ljava/lang/Class;)V
     120: return

  protected org.apache.hadoop.fs.shell.FsCommand();
    Code:
       0: aload_0
       1: invokespecial #23                 // Method org/apache/hadoop/fs/shell/Command."<init>":()V
       4: return

  protected org.apache.hadoop.fs.shell.FsCommand(org.apache.hadoop.conf.Configuration);
    Code:
       0: aload_0
       1: aload_1
       2: invokespecial #24                 // Method org/apache/hadoop/fs/shell/Command."<init>":(Lorg/apache/hadoop/conf/Configuration;)V
       5: return

  public java.lang.String getCommandName();
    Code:
       0: aload_0
       1: invokevirtual #25                 // Method getName:()Ljava/lang/String;
       4: areturn

  protected void run(org.apache.hadoop.fs.Path) throws java.io.IOException;
    Code:
       0: new           #26                 // class java/lang/RuntimeException
       3: dup
       4: ldc           #27                 // String not supposed to get here
       6: invokespecial #28                 // Method java/lang/RuntimeException."<init>":(Ljava/lang/String;)V
       9: athrow

  public int runAll();
    Code:
       0: aload_0
       1: aload_0
       2: getfield      #29                 // Field args:[Ljava/lang/String;
       5: invokevirtual #30                 // Method run:([Ljava/lang/String;)I
       8: ireturn

  protected void processRawArguments(java.util.LinkedList<java.lang.String>) throws java.io.IOException;
    Code:
       0: aload_0
       1: aload_1
       2: invokevirtual #31                 // Method expandArguments:(Ljava/util/LinkedList;)Ljava/util/LinkedList;
       5: astore_2
       6: aload_0
       7: invokevirtual #32                 // Method getConf:()Lorg/apache/hadoop/conf/Configuration;
      10: ldc           #33                 // String hadoop.shell.missing.defaultFs.warning
      12: iconst_0
      13: invokevirtual #34                 // Method org/apache/hadoop/conf/Configuration.getBoolean:(Ljava/lang/String;Z)Z
      16: istore_3
      17: iload_3
      18: ifeq          80
      21: aload_0
      22: invokevirtual #32                 // Method getConf:()Lorg/apache/hadoop/conf/Configuration;
      25: ldc           #35                 // String fs.defaultFS
      27: invokevirtual #36                 // Method org/apache/hadoop/conf/Configuration.get:(Ljava/lang/String;)Ljava/lang/String;
      30: astore        4
      32: aload         4
      34: ifnull        47
      37: aload         4
      39: ldc           #37                 // String file:///
      41: invokevirtual #38                 // Method java/lang/String.equals:(Ljava/lang/Object;)Z
      44: ifeq          51
      47: iconst_1
      48: goto          52
      51: iconst_0
      52: istore        5
      54: iload         5
      56: ifeq          80
      59: aload_0
      60: getfield      #39                 // Field err:Ljava/io/PrintStream;
      63: ldc           #40                 // String Warning: fs.defaultFS is not set when running \"%s\" command.%n
      65: iconst_1
      66: anewarray     #41                 // class java/lang/Object
      69: dup
      70: iconst_0
      71: aload_0
      72: invokevirtual #42                 // Method getCommandName:()Ljava/lang/String;
      75: aastore
      76: invokevirtual #43                 // Method java/io/PrintStream.printf:(Ljava/lang/String;[Ljava/lang/Object;)Ljava/io/PrintStream;
      79: pop
      80: aload_0
      81: aload_2
      82: invokevirtual #44                 // Method processArguments:(Ljava/util/LinkedList;)V
      85: return
}
