Compiled from "Stat.java"
class org.apache.hadoop.fs.shell.Stat extends org.apache.hadoop.fs.shell.FsCommand {
  private static final java.lang.String NEWLINE;

  public static final java.lang.String NAME;

  public static final java.lang.String USAGE;

  public static final java.lang.String DESCRIPTION;

  protected final java.text.SimpleDateFormat timeFmt;

  protected java.lang.String format;

  org.apache.hadoop.fs.shell.Stat();
    Code:
       0: aload_0
       1: invokespecial #1                  // Method org/apache/hadoop/fs/shell/FsCommand."<init>":()V
       4: aload_0
       5: new           #2                  // class java/text/SimpleDateFormat
       8: dup
       9: ldc           #3                  // String yyyy-MM-dd HH:mm:ss
      11: invokespecial #4                  // Method java/text/SimpleDateFormat."<init>":(Ljava/lang/String;)V
      14: putfield      #5                  // Field timeFmt:Ljava/text/SimpleDateFormat;
      17: aload_0
      18: getfield      #5                  // Field timeFmt:Ljava/text/SimpleDateFormat;
      21: ldc           #6                  // String UTC
      23: invokestatic  #7                  // Method java/util/TimeZone.getTimeZone:(Ljava/lang/String;)Ljava/util/TimeZone;
      26: invokevirtual #8                  // Method java/text/SimpleDateFormat.setTimeZone:(Ljava/util/TimeZone;)V
      29: aload_0
      30: ldc           #9                  // String %y
      32: putfield      #10                 // Field format:Ljava/lang/String;
      35: return

  public static void registerCommands(org.apache.hadoop.fs.shell.CommandFactory);
    Code:
       0: aload_0
       1: ldc           #11                 // class org/apache/hadoop/fs/shell/Stat
       3: iconst_1
       4: anewarray     #12                 // class java/lang/String
       7: dup
       8: iconst_0
       9: ldc           #13                 // String -stat
      11: aastore
      12: invokevirtual #14                 // Method org/apache/hadoop/fs/shell/CommandFactory.addClass:(Ljava/lang/Class;[Ljava/lang/String;)V
      15: return

  protected void processOptions(java.util.LinkedList<java.lang.String>) throws java.io.IOException;
    Code:
       0: new           #15                 // class org/apache/hadoop/fs/shell/CommandFormat
       3: dup
       4: iconst_1
       5: ldc           #17                 // int 2147483647
       7: iconst_1
       8: anewarray     #12                 // class java/lang/String
      11: dup
      12: iconst_0
      13: ldc           #18                 // String R
      15: aastore
      16: invokespecial #19                 // Method org/apache/hadoop/fs/shell/CommandFormat."<init>":(II[Ljava/lang/String;)V
      19: astore_2
      20: aload_2
      21: aload_1
      22: invokevirtual #20                 // Method org/apache/hadoop/fs/shell/CommandFormat.parse:(Ljava/util/List;)V
      25: aload_0
      26: aload_2
      27: ldc           #18                 // String R
      29: invokevirtual #21                 // Method org/apache/hadoop/fs/shell/CommandFormat.getOpt:(Ljava/lang/String;)Z
      32: invokevirtual #22                 // Method setRecursive:(Z)V
      35: aload_1
      36: invokevirtual #23                 // Method java/util/LinkedList.getFirst:()Ljava/lang/Object;
      39: checkcast     #12                 // class java/lang/String
      42: ldc           #24                 // String %
      44: invokevirtual #25                 // Method java/lang/String.contains:(Ljava/lang/CharSequence;)Z
      47: ifeq          61
      50: aload_0
      51: aload_1
      52: invokevirtual #26                 // Method java/util/LinkedList.removeFirst:()Ljava/lang/Object;
      55: checkcast     #12                 // class java/lang/String
      58: putfield      #10                 // Field format:Ljava/lang/String;
      61: aload_2
      62: aload_1
      63: invokevirtual #20                 // Method org/apache/hadoop/fs/shell/CommandFormat.parse:(Ljava/util/List;)V
      66: return

  protected void processPath(org.apache.hadoop.fs.shell.PathData) throws java.io.IOException;
    Code:
       0: aload_1
       1: getfield      #27                 // Field org/apache/hadoop/fs/shell/PathData.stat:Lorg/apache/hadoop/fs/FileStatus;
       4: astore_2
       5: new           #28                 // class java/lang/StringBuilder
       8: dup
       9: invokespecial #29                 // Method java/lang/StringBuilder."<init>":()V
      12: astore_3
      13: aload_0
      14: getfield      #10                 // Field format:Ljava/lang/String;
      17: invokevirtual #30                 // Method java/lang/String.toCharArray:()[C
      20: astore        4
      22: iconst_0
      23: istore        5
      25: iload         5
      27: aload         4
      29: arraylength
      30: if_icmpge     420
      33: aload         4
      35: iload         5
      37: caload
      38: bipush        37
      40: if_icmpeq     56
      43: aload_3
      44: aload         4
      46: iload         5
      48: caload
      49: invokevirtual #31                 // Method java/lang/StringBuilder.append:(C)Ljava/lang/StringBuilder;
      52: pop
      53: goto          414
      56: iload         5
      58: iconst_1
      59: iadd
      60: aload         4
      62: arraylength
      63: if_icmpne     69
      66: goto          420
      69: aload         4
      71: iinc          5, 1
      74: iload         5
      76: caload
      77: lookupswitch  { // 13
                    65: 207
                    70: 231
                    88: 354
                    89: 392
                    97: 192
                    98: 219
                   103: 265
                   110: 277
                   111: 292
                   114: 304
                   117: 316
                   120: 328
                   121: 366
               default: 404
          }
     192: aload_3
     193: aload_2
     194: invokevirtual #32                 // Method org/apache/hadoop/fs/FileStatus.getPermission:()Lorg/apache/hadoop/fs/permission/FsPermission;
     197: invokevirtual #33                 // Method org/apache/hadoop/fs/permission/FsPermission.toOctal:()S
     200: invokevirtual #34                 // Method java/lang/StringBuilder.append:(I)Ljava/lang/StringBuilder;
     203: pop
     204: goto          414
     207: aload_3
     208: aload_2
     209: invokevirtual #32                 // Method org/apache/hadoop/fs/FileStatus.getPermission:()Lorg/apache/hadoop/fs/permission/FsPermission;
     212: invokevirtual #35                 // Method java/lang/StringBuilder.append:(Ljava/lang/Object;)Ljava/lang/StringBuilder;
     215: pop
     216: goto          414
     219: aload_3
     220: aload_2
     221: invokevirtual #36                 // Method org/apache/hadoop/fs/FileStatus.getLen:()J
     224: invokevirtual #37                 // Method java/lang/StringBuilder.append:(J)Ljava/lang/StringBuilder;
     227: pop
     228: goto          414
     231: aload_3
     232: aload_2
     233: invokevirtual #38                 // Method org/apache/hadoop/fs/FileStatus.isDirectory:()Z
     236: ifeq          244
     239: ldc           #39                 // String directory
     241: goto          258
     244: aload_2
     245: invokevirtual #40                 // Method org/apache/hadoop/fs/FileStatus.isFile:()Z
     248: ifeq          256
     251: ldc           #41                 // String regular file
     253: goto          258
     256: ldc           #42                 // String symlink
     258: invokevirtual #43                 // Method java/lang/StringBuilder.append:(Ljava/lang/String;)Ljava/lang/StringBuilder;
     261: pop
     262: goto          414
     265: aload_3
     266: aload_2
     267: invokevirtual #44                 // Method org/apache/hadoop/fs/FileStatus.getGroup:()Ljava/lang/String;
     270: invokevirtual #43                 // Method java/lang/StringBuilder.append:(Ljava/lang/String;)Ljava/lang/StringBuilder;
     273: pop
     274: goto          414
     277: aload_3
     278: aload_1
     279: getfield      #45                 // Field org/apache/hadoop/fs/shell/PathData.path:Lorg/apache/hadoop/fs/Path;
     282: invokevirtual #46                 // Method org/apache/hadoop/fs/Path.getName:()Ljava/lang/String;
     285: invokevirtual #43                 // Method java/lang/StringBuilder.append:(Ljava/lang/String;)Ljava/lang/StringBuilder;
     288: pop
     289: goto          414
     292: aload_3
     293: aload_2
     294: invokevirtual #47                 // Method org/apache/hadoop/fs/FileStatus.getBlockSize:()J
     297: invokevirtual #37                 // Method java/lang/StringBuilder.append:(J)Ljava/lang/StringBuilder;
     300: pop
     301: goto          414
     304: aload_3
     305: aload_2
     306: invokevirtual #48                 // Method org/apache/hadoop/fs/FileStatus.getReplication:()S
     309: invokevirtual #34                 // Method java/lang/StringBuilder.append:(I)Ljava/lang/StringBuilder;
     312: pop
     313: goto          414
     316: aload_3
     317: aload_2
     318: invokevirtual #49                 // Method org/apache/hadoop/fs/FileStatus.getOwner:()Ljava/lang/String;
     321: invokevirtual #43                 // Method java/lang/StringBuilder.append:(Ljava/lang/String;)Ljava/lang/StringBuilder;
     324: pop
     325: goto          414
     328: aload_3
     329: aload_0
     330: getfield      #5                  // Field timeFmt:Ljava/text/SimpleDateFormat;
     333: new           #50                 // class java/util/Date
     336: dup
     337: aload_2
     338: invokevirtual #51                 // Method org/apache/hadoop/fs/FileStatus.getAccessTime:()J
     341: invokespecial #52                 // Method java/util/Date."<init>":(J)V
     344: invokevirtual #53                 // Method java/text/SimpleDateFormat.format:(Ljava/util/Date;)Ljava/lang/String;
     347: invokevirtual #43                 // Method java/lang/StringBuilder.append:(Ljava/lang/String;)Ljava/lang/StringBuilder;
     350: pop
     351: goto          414
     354: aload_3
     355: aload_2
     356: invokevirtual #51                 // Method org/apache/hadoop/fs/FileStatus.getAccessTime:()J
     359: invokevirtual #37                 // Method java/lang/StringBuilder.append:(J)Ljava/lang/StringBuilder;
     362: pop
     363: goto          414
     366: aload_3
     367: aload_0
     368: getfield      #5                  // Field timeFmt:Ljava/text/SimpleDateFormat;
     371: new           #50                 // class java/util/Date
     374: dup
     375: aload_2
     376: invokevirtual #54                 // Method org/apache/hadoop/fs/FileStatus.getModificationTime:()J
     379: invokespecial #52                 // Method java/util/Date."<init>":(J)V
     382: invokevirtual #53                 // Method java/text/SimpleDateFormat.format:(Ljava/util/Date;)Ljava/lang/String;
     385: invokevirtual #43                 // Method java/lang/StringBuilder.append:(Ljava/lang/String;)Ljava/lang/StringBuilder;
     388: pop
     389: goto          414
     392: aload_3
     393: aload_2
     394: invokevirtual #54                 // Method org/apache/hadoop/fs/FileStatus.getModificationTime:()J
     397: invokevirtual #37                 // Method java/lang/StringBuilder.append:(J)Ljava/lang/StringBuilder;
     400: pop
     401: goto          414
     404: aload_3
     405: aload         4
     407: iload         5
     409: caload
     410: invokevirtual #31                 // Method java/lang/StringBuilder.append:(C)Ljava/lang/StringBuilder;
     413: pop
     414: iinc          5, 1
     417: goto          25
     420: aload_0
     421: getfield      #55                 // Field out:Ljava/io/PrintStream;
     424: aload_3
     425: invokevirtual #56                 // Method java/lang/StringBuilder.toString:()Ljava/lang/String;
     428: invokevirtual #57                 // Method java/io/PrintStream.println:(Ljava/lang/String;)V
     431: return

  static {};
    Code:
       0: ldc           #58                 // String line.separator
       2: invokestatic  #59                 // Method java/lang/System.getProperty:(Ljava/lang/String;)Ljava/lang/String;
       5: putstatic     #60                 // Field NEWLINE:Ljava/lang/String;
       8: new           #28                 // class java/lang/StringBuilder
      11: dup
      12: invokespecial #29                 // Method java/lang/StringBuilder."<init>":()V
      15: ldc           #61                 // String Print statistics about the file/directory at <path>
      17: invokevirtual #43                 // Method java/lang/StringBuilder.append:(Ljava/lang/String;)Ljava/lang/StringBuilder;
      20: getstatic     #60                 // Field NEWLINE:Ljava/lang/String;
      23: invokevirtual #43                 // Method java/lang/StringBuilder.append:(Ljava/lang/String;)Ljava/lang/StringBuilder;
      26: ldc           #62                 // String in the specified format. Format accepts permissions in
      28: invokevirtual #43                 // Method java/lang/StringBuilder.append:(Ljava/lang/String;)Ljava/lang/StringBuilder;
      31: getstatic     #60                 // Field NEWLINE:Ljava/lang/String;
      34: invokevirtual #43                 // Method java/lang/StringBuilder.append:(Ljava/lang/String;)Ljava/lang/StringBuilder;
      37: ldc           #63                 // String octal (%a) and symbolic (%A), filesize in
      39: invokevirtual #43                 // Method java/lang/StringBuilder.append:(Ljava/lang/String;)Ljava/lang/StringBuilder;
      42: getstatic     #60                 // Field NEWLINE:Ljava/lang/String;
      45: invokevirtual #43                 // Method java/lang/StringBuilder.append:(Ljava/lang/String;)Ljava/lang/StringBuilder;
      48: ldc           #64                 // String bytes (%b), type (%F), group name of owner (%g),
      50: invokevirtual #43                 // Method java/lang/StringBuilder.append:(Ljava/lang/String;)Ljava/lang/StringBuilder;
      53: getstatic     #60                 // Field NEWLINE:Ljava/lang/String;
      56: invokevirtual #43                 // Method java/lang/StringBuilder.append:(Ljava/lang/String;)Ljava/lang/StringBuilder;
      59: ldc           #65                 // String name (%n), block size (%o), replication (%r), user name
      61: invokevirtual #43                 // Method java/lang/StringBuilder.append:(Ljava/lang/String;)Ljava/lang/StringBuilder;
      64: getstatic     #60                 // Field NEWLINE:Ljava/lang/String;
      67: invokevirtual #43                 // Method java/lang/StringBuilder.append:(Ljava/lang/String;)Ljava/lang/StringBuilder;
      70: ldc           #66                 // String of owner (%u), access date (%x, %X).
      72: invokevirtual #43                 // Method java/lang/StringBuilder.append:(Ljava/lang/String;)Ljava/lang/StringBuilder;
      75: getstatic     #60                 // Field NEWLINE:Ljava/lang/String;
      78: invokevirtual #43                 // Method java/lang/StringBuilder.append:(Ljava/lang/String;)Ljava/lang/StringBuilder;
      81: ldc           #67                 // String modification date (%y, %Y).
      83: invokevirtual #43                 // Method java/lang/StringBuilder.append:(Ljava/lang/String;)Ljava/lang/StringBuilder;
      86: getstatic     #60                 // Field NEWLINE:Ljava/lang/String;
      89: invokevirtual #43                 // Method java/lang/StringBuilder.append:(Ljava/lang/String;)Ljava/lang/StringBuilder;
      92: ldc           #68                 // String %x and %y show UTC date as \"yyyy-MM-dd HH:mm:ss\" and
      94: invokevirtual #43                 // Method java/lang/StringBuilder.append:(Ljava/lang/String;)Ljava/lang/StringBuilder;
      97: getstatic     #60                 // Field NEWLINE:Ljava/lang/String;
     100: invokevirtual #43                 // Method java/lang/StringBuilder.append:(Ljava/lang/String;)Ljava/lang/StringBuilder;
     103: ldc           #69                 // String %X and %Y show milliseconds since January 1, 1970 UTC.
     105: invokevirtual #43                 // Method java/lang/StringBuilder.append:(Ljava/lang/String;)Ljava/lang/StringBuilder;
     108: getstatic     #60                 // Field NEWLINE:Ljava/lang/String;
     111: invokevirtual #43                 // Method java/lang/StringBuilder.append:(Ljava/lang/String;)Ljava/lang/StringBuilder;
     114: ldc           #70                 // String If the format is not specified, %y is used by default.
     116: invokevirtual #43                 // Method java/lang/StringBuilder.append:(Ljava/lang/String;)Ljava/lang/StringBuilder;
     119: getstatic     #60                 // Field NEWLINE:Ljava/lang/String;
     122: invokevirtual #43                 // Method java/lang/StringBuilder.append:(Ljava/lang/String;)Ljava/lang/StringBuilder;
     125: invokevirtual #56                 // Method java/lang/StringBuilder.toString:()Ljava/lang/String;
     128: putstatic     #71                 // Field DESCRIPTION:Ljava/lang/String;
     131: return
}
