Compiled from "InstancesHealthAttribute.java"
public final class com.amazonaws.services.elasticbeanstalk.model.InstancesHealthAttribute extends java.lang.Enum<com.amazonaws.services.elasticbeanstalk.model.InstancesHealthAttribute> {
  public static final com.amazonaws.services.elasticbeanstalk.model.InstancesHealthAttribute HealthStatus;

  public static final com.amazonaws.services.elasticbeanstalk.model.InstancesHealthAttribute Color;

  public static final com.amazonaws.services.elasticbeanstalk.model.InstancesHealthAttribute Causes;

  public static final com.amazonaws.services.elasticbeanstalk.model.InstancesHealthAttribute ApplicationMetrics;

  public static final com.amazonaws.services.elasticbeanstalk.model.InstancesHealthAttribute RefreshedAt;

  public static final com.amazonaws.services.elasticbeanstalk.model.InstancesHealthAttribute LaunchedAt;

  public static final com.amazonaws.services.elasticbeanstalk.model.InstancesHealthAttribute System;

  public static final com.amazonaws.services.elasticbeanstalk.model.InstancesHealthAttribute Deployment;

  public static final com.amazonaws.services.elasticbeanstalk.model.InstancesHealthAttribute AvailabilityZone;

  public static final com.amazonaws.services.elasticbeanstalk.model.InstancesHealthAttribute InstanceType;

  public static final com.amazonaws.services.elasticbeanstalk.model.InstancesHealthAttribute All;

  private java.lang.String value;

  private static final com.amazonaws.services.elasticbeanstalk.model.InstancesHealthAttribute[] $VALUES;

  public static com.amazonaws.services.elasticbeanstalk.model.InstancesHealthAttribute[] values();
    Code:
       0: getstatic     #1                  // Field $VALUES:[Lcom/amazonaws/services/elasticbeanstalk/model/InstancesHealthAttribute;
       3: invokevirtual #2                  // Method "[Lcom/amazonaws/services/elasticbeanstalk/model/InstancesHealthAttribute;".clone:()Ljava/lang/Object;
       6: checkcast     #3                  // class "[Lcom/amazonaws/services/elasticbeanstalk/model/InstancesHealthAttribute;"
       9: areturn

  public static com.amazonaws.services.elasticbeanstalk.model.InstancesHealthAttribute valueOf(java.lang.String);
    Code:
       0: ldc           #4                  // class com/amazonaws/services/elasticbeanstalk/model/InstancesHealthAttribute
       2: aload_0
       3: invokestatic  #5                  // Method java/lang/Enum.valueOf:(Ljava/lang/Class;Ljava/lang/String;)Ljava/lang/Enum;
       6: checkcast     #4                  // class com/amazonaws/services/elasticbeanstalk/model/InstancesHealthAttribute
       9: areturn

  private com.amazonaws.services.elasticbeanstalk.model.InstancesHealthAttribute(java.lang.String);
    Code:
       0: aload_0
       1: aload_1
       2: iload_2
       3: invokespecial #6                  // Method java/lang/Enum."<init>":(Ljava/lang/String;I)V
       6: aload_0
       7: aload_3
       8: putfield      #7                  // Field value:Ljava/lang/String;
      11: return

  public java.lang.String toString();
    Code:
       0: aload_0
       1: getfield      #7                  // Field value:Ljava/lang/String;
       4: areturn

  public static com.amazonaws.services.elasticbeanstalk.model.InstancesHealthAttribute fromValue(java.lang.String);
    Code:
       0: aload_0
       1: ifnull        13
       4: ldc           #8                  // String
       6: aload_0
       7: invokevirtual #9                  // Method java/lang/String.equals:(Ljava/lang/Object;)Z
      10: ifeq          23
      13: new           #10                 // class java/lang/IllegalArgumentException
      16: dup
      17: ldc           #11                 // String Value cannot be null or empty!
      19: invokespecial #12                 // Method java/lang/IllegalArgumentException."<init>":(Ljava/lang/String;)V
      22: athrow
      23: invokestatic  #13                 // Method values:()[Lcom/amazonaws/services/elasticbeanstalk/model/InstancesHealthAttribute;
      26: astore_1
      27: aload_1
      28: arraylength
      29: istore_2
      30: iconst_0
      31: istore_3
      32: iload_3
      33: iload_2
      34: if_icmpge     63
      37: aload_1
      38: iload_3
      39: aaload
      40: astore        4
      42: aload         4
      44: invokevirtual #14                 // Method toString:()Ljava/lang/String;
      47: aload_0
      48: invokevirtual #9                  // Method java/lang/String.equals:(Ljava/lang/Object;)Z
      51: ifeq          57
      54: aload         4
      56: areturn
      57: iinc          3, 1
      60: goto          32
      63: new           #10                 // class java/lang/IllegalArgumentException
      66: dup
      67: new           #15                 // class java/lang/StringBuilder
      70: dup
      71: invokespecial #16                 // Method java/lang/StringBuilder."<init>":()V
      74: ldc           #17                 // String Cannot create enum from
      76: invokevirtual #18                 // Method java/lang/StringBuilder.append:(Ljava/lang/String;)Ljava/lang/StringBuilder;
      79: aload_0
      80: invokevirtual #18                 // Method java/lang/StringBuilder.append:(Ljava/lang/String;)Ljava/lang/StringBuilder;
      83: ldc           #19                 // String  value!
      85: invokevirtual #18                 // Method java/lang/StringBuilder.append:(Ljava/lang/String;)Ljava/lang/StringBuilder;
      88: invokevirtual #20                 // Method java/lang/StringBuilder.toString:()Ljava/lang/String;
      91: invokespecial #12                 // Method java/lang/IllegalArgumentException."<init>":(Ljava/lang/String;)V
      94: athrow

  static {};
    Code:
       0: new           #4                  // class com/amazonaws/services/elasticbeanstalk/model/InstancesHealthAttribute
       3: dup
       4: ldc           #21                 // String HealthStatus
       6: iconst_0
       7: ldc           #21                 // String HealthStatus
       9: invokespecial #22                 // Method "<init>":(Ljava/lang/String;ILjava/lang/String;)V
      12: putstatic     #23                 // Field HealthStatus:Lcom/amazonaws/services/elasticbeanstalk/model/InstancesHealthAttribute;
      15: new           #4                  // class com/amazonaws/services/elasticbeanstalk/model/InstancesHealthAttribute
      18: dup
      19: ldc           #24                 // String Color
      21: iconst_1
      22: ldc           #24                 // String Color
      24: invokespecial #22                 // Method "<init>":(Ljava/lang/String;ILjava/lang/String;)V
      27: putstatic     #25                 // Field Color:Lcom/amazonaws/services/elasticbeanstalk/model/InstancesHealthAttribute;
      30: new           #4                  // class com/amazonaws/services/elasticbeanstalk/model/InstancesHealthAttribute
      33: dup
      34: ldc           #26                 // String Causes
      36: iconst_2
      37: ldc           #26                 // String Causes
      39: invokespecial #22                 // Method "<init>":(Ljava/lang/String;ILjava/lang/String;)V
      42: putstatic     #27                 // Field Causes:Lcom/amazonaws/services/elasticbeanstalk/model/InstancesHealthAttribute;
      45: new           #4                  // class com/amazonaws/services/elasticbeanstalk/model/InstancesHealthAttribute
      48: dup
      49: ldc           #28                 // String ApplicationMetrics
      51: iconst_3
      52: ldc           #28                 // String ApplicationMetrics
      54: invokespecial #22                 // Method "<init>":(Ljava/lang/String;ILjava/lang/String;)V
      57: putstatic     #29                 // Field ApplicationMetrics:Lcom/amazonaws/services/elasticbeanstalk/model/InstancesHealthAttribute;
      60: new           #4                  // class com/amazonaws/services/elasticbeanstalk/model/InstancesHealthAttribute
      63: dup
      64: ldc           #30                 // String RefreshedAt
      66: iconst_4
      67: ldc           #30                 // String RefreshedAt
      69: invokespecial #22                 // Method "<init>":(Ljava/lang/String;ILjava/lang/String;)V
      72: putstatic     #31                 // Field RefreshedAt:Lcom/amazonaws/services/elasticbeanstalk/model/InstancesHealthAttribute;
      75: new           #4                  // class com/amazonaws/services/elasticbeanstalk/model/InstancesHealthAttribute
      78: dup
      79: ldc           #32                 // String LaunchedAt
      81: iconst_5
      82: ldc           #32                 // String LaunchedAt
      84: invokespecial #22                 // Method "<init>":(Ljava/lang/String;ILjava/lang/String;)V
      87: putstatic     #33                 // Field LaunchedAt:Lcom/amazonaws/services/elasticbeanstalk/model/InstancesHealthAttribute;
      90: new           #4                  // class com/amazonaws/services/elasticbeanstalk/model/InstancesHealthAttribute
      93: dup
      94: ldc           #34                 // String System
      96: bipush        6
      98: ldc           #34                 // String System
     100: invokespecial #22                 // Method "<init>":(Ljava/lang/String;ILjava/lang/String;)V
     103: putstatic     #35                 // Field System:Lcom/amazonaws/services/elasticbeanstalk/model/InstancesHealthAttribute;
     106: new           #4                  // class com/amazonaws/services/elasticbeanstalk/model/InstancesHealthAttribute
     109: dup
     110: ldc           #36                 // String Deployment
     112: bipush        7
     114: ldc           #36                 // String Deployment
     116: invokespecial #22                 // Method "<init>":(Ljava/lang/String;ILjava/lang/String;)V
     119: putstatic     #37                 // Field Deployment:Lcom/amazonaws/services/elasticbeanstalk/model/InstancesHealthAttribute;
     122: new           #4                  // class com/amazonaws/services/elasticbeanstalk/model/InstancesHealthAttribute
     125: dup
     126: ldc           #38                 // String AvailabilityZone
     128: bipush        8
     130: ldc           #38                 // String AvailabilityZone
     132: invokespecial #22                 // Method "<init>":(Ljava/lang/String;ILjava/lang/String;)V
     135: putstatic     #39                 // Field AvailabilityZone:Lcom/amazonaws/services/elasticbeanstalk/model/InstancesHealthAttribute;
     138: new           #4                  // class com/amazonaws/services/elasticbeanstalk/model/InstancesHealthAttribute
     141: dup
     142: ldc           #40                 // String InstanceType
     144: bipush        9
     146: ldc           #40                 // String InstanceType
     148: invokespecial #22                 // Method "<init>":(Ljava/lang/String;ILjava/lang/String;)V
     151: putstatic     #41                 // Field InstanceType:Lcom/amazonaws/services/elasticbeanstalk/model/InstancesHealthAttribute;
     154: new           #4                  // class com/amazonaws/services/elasticbeanstalk/model/InstancesHealthAttribute
     157: dup
     158: ldc           #42                 // String All
     160: bipush        10
     162: ldc           #42                 // String All
     164: invokespecial #22                 // Method "<init>":(Ljava/lang/String;ILjava/lang/String;)V
     167: putstatic     #43                 // Field All:Lcom/amazonaws/services/elasticbeanstalk/model/InstancesHealthAttribute;
     170: bipush        11
     172: anewarray     #4                  // class com/amazonaws/services/elasticbeanstalk/model/InstancesHealthAttribute
     175: dup
     176: iconst_0
     177: getstatic     #23                 // Field HealthStatus:Lcom/amazonaws/services/elasticbeanstalk/model/InstancesHealthAttribute;
     180: aastore
     181: dup
     182: iconst_1
     183: getstatic     #25                 // Field Color:Lcom/amazonaws/services/elasticbeanstalk/model/InstancesHealthAttribute;
     186: aastore
     187: dup
     188: iconst_2
     189: getstatic     #27                 // Field Causes:Lcom/amazonaws/services/elasticbeanstalk/model/InstancesHealthAttribute;
     192: aastore
     193: dup
     194: iconst_3
     195: getstatic     #29                 // Field ApplicationMetrics:Lcom/amazonaws/services/elasticbeanstalk/model/InstancesHealthAttribute;
     198: aastore
     199: dup
     200: iconst_4
     201: getstatic     #31                 // Field RefreshedAt:Lcom/amazonaws/services/elasticbeanstalk/model/InstancesHealthAttribute;
     204: aastore
     205: dup
     206: iconst_5
     207: getstatic     #33                 // Field LaunchedAt:Lcom/amazonaws/services/elasticbeanstalk/model/InstancesHealthAttribute;
     210: aastore
     211: dup
     212: bipush        6
     214: getstatic     #35                 // Field System:Lcom/amazonaws/services/elasticbeanstalk/model/InstancesHealthAttribute;
     217: aastore
     218: dup
     219: bipush        7
     221: getstatic     #37                 // Field Deployment:Lcom/amazonaws/services/elasticbeanstalk/model/InstancesHealthAttribute;
     224: aastore
     225: dup
     226: bipush        8
     228: getstatic     #39                 // Field AvailabilityZone:Lcom/amazonaws/services/elasticbeanstalk/model/InstancesHealthAttribute;
     231: aastore
     232: dup
     233: bipush        9
     235: getstatic     #41                 // Field InstanceType:Lcom/amazonaws/services/elasticbeanstalk/model/InstancesHealthAttribute;
     238: aastore
     239: dup
     240: bipush        10
     242: getstatic     #43                 // Field All:Lcom/amazonaws/services/elasticbeanstalk/model/InstancesHealthAttribute;
     245: aastore
     246: putstatic     #1                  // Field $VALUES:[Lcom/amazonaws/services/elasticbeanstalk/model/InstancesHealthAttribute;
     249: return
}
