Compiled from "Duration.java"
public class org.apache.axis2.databinding.types.Duration implements java.io.Serializable {
  private static final long serialVersionUID;

  boolean isNegative;

  int years;

  int months;

  int days;

  int hours;

  int minutes;

  double seconds;

  public org.apache.axis2.databinding.types.Duration();
    Code:
       0: aload_0
       1: invokespecial #1                  // Method java/lang/Object."<init>":()V
       4: return

  public org.apache.axis2.databinding.types.Duration(boolean, int, int, int, int, int, double);
    Code:
       0: aload_0
       1: invokespecial #1                  // Method java/lang/Object."<init>":()V
       4: aload_0
       5: iload_1
       6: putfield      #2                  // Field isNegative:Z
       9: aload_0
      10: iload_2
      11: putfield      #3                  // Field years:I
      14: aload_0
      15: iload_3
      16: putfield      #4                  // Field months:I
      19: aload_0
      20: iload         4
      22: putfield      #5                  // Field days:I
      25: aload_0
      26: iload         5
      28: putfield      #6                  // Field hours:I
      31: aload_0
      32: iload         6
      34: putfield      #7                  // Field minutes:I
      37: aload_0
      38: dload         7
      40: invokevirtual #8                  // Method setSeconds:(D)V
      43: return

  public org.apache.axis2.databinding.types.Duration(java.lang.String) throws java.lang.IllegalArgumentException;
    Code:
       0: aload_0
       1: invokespecial #1                  // Method java/lang/Object."<init>":()V
       4: iconst_1
       5: istore_2
       6: aload_1
       7: ldc           #9                  // String T
       9: invokevirtual #10                 // Method java/lang/String.indexOf:(Ljava/lang/String;)I
      12: istore_3
      13: aload_1
      14: ldc           #11                 // String P
      16: invokevirtual #10                 // Method java/lang/String.indexOf:(Ljava/lang/String;)I
      19: iconst_m1
      20: if_icmpeq     32
      23: aload_1
      24: ldc           #11                 // String P
      26: invokevirtual #12                 // Method java/lang/String.equals:(Ljava/lang/Object;)Z
      29: ifeq          40
      32: new           #13                 // class java/lang/IllegalArgumentException
      35: dup
      36: invokespecial #14                 // Method java/lang/IllegalArgumentException."<init>":()V
      39: athrow
      40: aload_1
      41: ldc           #9                  // String T
      43: invokevirtual #15                 // Method java/lang/String.lastIndexOf:(Ljava/lang/String;)I
      46: aload_1
      47: invokevirtual #16                 // Method java/lang/String.length:()I
      50: iconst_1
      51: isub
      52: if_icmpne     63
      55: new           #13                 // class java/lang/IllegalArgumentException
      58: dup
      59: invokespecial #14                 // Method java/lang/IllegalArgumentException."<init>":()V
      62: athrow
      63: aload_1
      64: ldc           #17                 // String -
      66: invokevirtual #18                 // Method java/lang/String.startsWith:(Ljava/lang/String;)Z
      69: ifeq          80
      72: aload_0
      73: iconst_1
      74: putfield      #2                  // Field isNegative:Z
      77: iinc          2, 1
      80: iload_3
      81: iconst_m1
      82: if_icmpeq     99
      85: aload_0
      86: aload_1
      87: iload_3
      88: iconst_1
      89: iadd
      90: invokevirtual #19                 // Method java/lang/String.substring:(I)Ljava/lang/String;
      93: invokevirtual #20                 // Method parseTime:(Ljava/lang/String;)V
      96: goto          104
      99: aload_1
     100: invokevirtual #16                 // Method java/lang/String.length:()I
     103: istore_3
     104: iload_2
     105: iload_3
     106: if_icmpeq     119
     109: aload_0
     110: aload_1
     111: iload_2
     112: iload_3
     113: invokevirtual #21                 // Method java/lang/String.substring:(II)Ljava/lang/String;
     116: invokevirtual #22                 // Method parseDate:(Ljava/lang/String;)V
     119: return

  public org.apache.axis2.databinding.types.Duration(boolean, java.util.Calendar) throws java.lang.IllegalArgumentException;
    Code:
       0: aload_0
       1: invokespecial #1                  // Method java/lang/Object."<init>":()V
       4: aload_0
       5: iload_1
       6: putfield      #2                  // Field isNegative:Z
       9: aload_0
      10: aload_2
      11: iconst_1
      12: invokevirtual #24                 // Method java/util/Calendar.get:(I)I
      15: putfield      #3                  // Field years:I
      18: aload_0
      19: aload_2
      20: iconst_2
      21: invokevirtual #24                 // Method java/util/Calendar.get:(I)I
      24: putfield      #4                  // Field months:I
      27: aload_0
      28: aload_2
      29: iconst_5
      30: invokevirtual #24                 // Method java/util/Calendar.get:(I)I
      33: putfield      #5                  // Field days:I
      36: aload_0
      37: aload_2
      38: bipush        10
      40: invokevirtual #24                 // Method java/util/Calendar.get:(I)I
      43: putfield      #6                  // Field hours:I
      46: aload_0
      47: aload_2
      48: bipush        12
      50: invokevirtual #24                 // Method java/util/Calendar.get:(I)I
      53: putfield      #7                  // Field minutes:I
      56: aload_0
      57: aload_2
      58: bipush        13
      60: invokevirtual #24                 // Method java/util/Calendar.get:(I)I
      63: i2d
      64: putfield      #25                 // Field seconds:D
      67: aload_0
      68: dup
      69: getfield      #25                 // Field seconds:D
      72: aload_2
      73: bipush        14
      75: invokevirtual #24                 // Method java/util/Calendar.get:(I)I
      78: i2d
      79: ldc2_w        #26                 // double 100.0d
      82: ddiv
      83: dadd
      84: putfield      #25                 // Field seconds:D
      87: aload_0
      88: getfield      #3                  // Field years:I
      91: ifne          139
      94: aload_0
      95: getfield      #4                  // Field months:I
      98: ifne          139
     101: aload_0
     102: getfield      #5                  // Field days:I
     105: ifne          139
     108: aload_0
     109: getfield      #6                  // Field hours:I
     112: ifne          139
     115: aload_0
     116: getfield      #7                  // Field minutes:I
     119: ifne          139
     122: aload_0
     123: getfield      #25                 // Field seconds:D
     126: dconst_0
     127: dcmpl
     128: ifne          139
     131: new           #13                 // class java/lang/IllegalArgumentException
     134: dup
     135: invokespecial #14                 // Method java/lang/IllegalArgumentException."<init>":()V
     138: athrow
     139: return

  public void parseTime(java.lang.String) throws java.lang.IllegalArgumentException;
    Code:
       0: aload_1
       1: invokevirtual #16                 // Method java/lang/String.length:()I
       4: ifeq          17
       7: aload_1
       8: ldc           #17                 // String -
      10: invokevirtual #10                 // Method java/lang/String.indexOf:(Ljava/lang/String;)I
      13: iconst_m1
      14: if_icmpeq     25
      17: new           #13                 // class java/lang/IllegalArgumentException
      20: dup
      21: invokespecial #14                 // Method java/lang/IllegalArgumentException."<init>":()V
      24: athrow
      25: aload_1
      26: ldc           #28                 // String H
      28: invokevirtual #29                 // Method java/lang/String.endsWith:(Ljava/lang/String;)Z
      31: ifne          60
      34: aload_1
      35: ldc           #30                 // String M
      37: invokevirtual #29                 // Method java/lang/String.endsWith:(Ljava/lang/String;)Z
      40: ifne          60
      43: aload_1
      44: ldc           #31                 // String S
      46: invokevirtual #29                 // Method java/lang/String.endsWith:(Ljava/lang/String;)Z
      49: ifne          60
      52: new           #13                 // class java/lang/IllegalArgumentException
      55: dup
      56: invokespecial #14                 // Method java/lang/IllegalArgumentException."<init>":()V
      59: athrow
      60: iconst_0
      61: istore_2
      62: aload_1
      63: ldc           #28                 // String H
      65: invokevirtual #10                 // Method java/lang/String.indexOf:(Ljava/lang/String;)I
      68: istore_3
      69: iload_2
      70: iload_3
      71: if_icmpne     82
      74: new           #13                 // class java/lang/IllegalArgumentException
      77: dup
      78: invokespecial #14                 // Method java/lang/IllegalArgumentException."<init>":()V
      81: athrow
      82: iload_3
      83: iconst_m1
      84: if_icmpeq     104
      87: aload_0
      88: aload_1
      89: iconst_0
      90: iload_3
      91: invokevirtual #21                 // Method java/lang/String.substring:(II)Ljava/lang/String;
      94: invokestatic  #32                 // Method java/lang/Integer.parseInt:(Ljava/lang/String;)I
      97: putfield      #6                  // Field hours:I
     100: iload_3
     101: iconst_1
     102: iadd
     103: istore_2
     104: aload_1
     105: ldc           #30                 // String M
     107: invokevirtual #10                 // Method java/lang/String.indexOf:(Ljava/lang/String;)I
     110: istore_3
     111: iload_2
     112: iload_3
     113: if_icmpne     124
     116: new           #13                 // class java/lang/IllegalArgumentException
     119: dup
     120: invokespecial #14                 // Method java/lang/IllegalArgumentException."<init>":()V
     123: athrow
     124: iload_3
     125: iconst_m1
     126: if_icmpeq     146
     129: aload_0
     130: aload_1
     131: iload_2
     132: iload_3
     133: invokevirtual #21                 // Method java/lang/String.substring:(II)Ljava/lang/String;
     136: invokestatic  #32                 // Method java/lang/Integer.parseInt:(Ljava/lang/String;)I
     139: putfield      #7                  // Field minutes:I
     142: iload_3
     143: iconst_1
     144: iadd
     145: istore_2
     146: aload_1
     147: ldc           #31                 // String S
     149: invokevirtual #10                 // Method java/lang/String.indexOf:(Ljava/lang/String;)I
     152: istore_3
     153: iload_2
     154: iload_3
     155: if_icmpne     166
     158: new           #13                 // class java/lang/IllegalArgumentException
     161: dup
     162: invokespecial #14                 // Method java/lang/IllegalArgumentException."<init>":()V
     165: athrow
     166: iload_3
     167: iconst_m1
     168: if_icmpeq     184
     171: aload_0
     172: aload_1
     173: iload_2
     174: iload_3
     175: invokevirtual #21                 // Method java/lang/String.substring:(II)Ljava/lang/String;
     178: invokestatic  #33                 // Method java/lang/Double.parseDouble:(Ljava/lang/String;)D
     181: invokevirtual #8                  // Method setSeconds:(D)V
     184: goto          196
     187: astore_2
     188: new           #13                 // class java/lang/IllegalArgumentException
     191: dup
     192: invokespecial #14                 // Method java/lang/IllegalArgumentException."<init>":()V
     195: athrow
     196: return
    Exception table:
       from    to  target type
          60   184   187   Class java/lang/NumberFormatException

  public void parseDate(java.lang.String) throws java.lang.IllegalArgumentException;
    Code:
       0: aload_1
       1: invokevirtual #16                 // Method java/lang/String.length:()I
       4: ifeq          17
       7: aload_1
       8: ldc           #17                 // String -
      10: invokevirtual #10                 // Method java/lang/String.indexOf:(Ljava/lang/String;)I
      13: iconst_m1
      14: if_icmpeq     25
      17: new           #13                 // class java/lang/IllegalArgumentException
      20: dup
      21: invokespecial #14                 // Method java/lang/IllegalArgumentException."<init>":()V
      24: athrow
      25: aload_1
      26: ldc           #35                 // String Y
      28: invokevirtual #29                 // Method java/lang/String.endsWith:(Ljava/lang/String;)Z
      31: ifne          60
      34: aload_1
      35: ldc           #30                 // String M
      37: invokevirtual #29                 // Method java/lang/String.endsWith:(Ljava/lang/String;)Z
      40: ifne          60
      43: aload_1
      44: ldc           #36                 // String D
      46: invokevirtual #29                 // Method java/lang/String.endsWith:(Ljava/lang/String;)Z
      49: ifne          60
      52: new           #13                 // class java/lang/IllegalArgumentException
      55: dup
      56: invokespecial #14                 // Method java/lang/IllegalArgumentException."<init>":()V
      59: athrow
      60: iconst_0
      61: istore_2
      62: aload_1
      63: ldc           #35                 // String Y
      65: invokevirtual #10                 // Method java/lang/String.indexOf:(Ljava/lang/String;)I
      68: istore_3
      69: iload_2
      70: iload_3
      71: if_icmpne     82
      74: new           #13                 // class java/lang/IllegalArgumentException
      77: dup
      78: invokespecial #14                 // Method java/lang/IllegalArgumentException."<init>":()V
      81: athrow
      82: iload_3
      83: iconst_m1
      84: if_icmpeq     104
      87: aload_0
      88: aload_1
      89: iconst_0
      90: iload_3
      91: invokevirtual #21                 // Method java/lang/String.substring:(II)Ljava/lang/String;
      94: invokestatic  #32                 // Method java/lang/Integer.parseInt:(Ljava/lang/String;)I
      97: putfield      #3                  // Field years:I
     100: iload_3
     101: iconst_1
     102: iadd
     103: istore_2
     104: aload_1
     105: ldc           #30                 // String M
     107: invokevirtual #10                 // Method java/lang/String.indexOf:(Ljava/lang/String;)I
     110: istore_3
     111: iload_2
     112: iload_3
     113: if_icmpne     124
     116: new           #13                 // class java/lang/IllegalArgumentException
     119: dup
     120: invokespecial #14                 // Method java/lang/IllegalArgumentException."<init>":()V
     123: athrow
     124: iload_3
     125: iconst_m1
     126: if_icmpeq     146
     129: aload_0
     130: aload_1
     131: iload_2
     132: iload_3
     133: invokevirtual #21                 // Method java/lang/String.substring:(II)Ljava/lang/String;
     136: invokestatic  #32                 // Method java/lang/Integer.parseInt:(Ljava/lang/String;)I
     139: putfield      #4                  // Field months:I
     142: iload_3
     143: iconst_1
     144: iadd
     145: istore_2
     146: aload_1
     147: ldc           #36                 // String D
     149: invokevirtual #10                 // Method java/lang/String.indexOf:(Ljava/lang/String;)I
     152: istore_3
     153: iload_2
     154: iload_3
     155: if_icmpne     166
     158: new           #13                 // class java/lang/IllegalArgumentException
     161: dup
     162: invokespecial #14                 // Method java/lang/IllegalArgumentException."<init>":()V
     165: athrow
     166: iload_3
     167: iconst_m1
     168: if_icmpeq     184
     171: aload_0
     172: aload_1
     173: iload_2
     174: iload_3
     175: invokevirtual #21                 // Method java/lang/String.substring:(II)Ljava/lang/String;
     178: invokestatic  #32                 // Method java/lang/Integer.parseInt:(Ljava/lang/String;)I
     181: putfield      #5                  // Field days:I
     184: goto          196
     187: astore_2
     188: new           #13                 // class java/lang/IllegalArgumentException
     191: dup
     192: invokespecial #14                 // Method java/lang/IllegalArgumentException."<init>":()V
     195: athrow
     196: return
    Exception table:
       from    to  target type
          60   184   187   Class java/lang/NumberFormatException

  public boolean isNegative();
    Code:
       0: aload_0
       1: getfield      #2                  // Field isNegative:Z
       4: ireturn

  public int getYears();
    Code:
       0: aload_0
       1: getfield      #3                  // Field years:I
       4: ireturn

  public int getMonths();
    Code:
       0: aload_0
       1: getfield      #4                  // Field months:I
       4: ireturn

  public int getDays();
    Code:
       0: aload_0
       1: getfield      #5                  // Field days:I
       4: ireturn

  public int getHours();
    Code:
       0: aload_0
       1: getfield      #6                  // Field hours:I
       4: ireturn

  public int getMinutes();
    Code:
       0: aload_0
       1: getfield      #7                  // Field minutes:I
       4: ireturn

  public double getSeconds();
    Code:
       0: aload_0
       1: getfield      #25                 // Field seconds:D
       4: dreturn

  public void setNegative(boolean);
    Code:
       0: aload_0
       1: iload_1
       2: putfield      #2                  // Field isNegative:Z
       5: return

  public void setYears(int);
    Code:
       0: aload_0
       1: iload_1
       2: putfield      #3                  // Field years:I
       5: return

  public void setMonths(int);
    Code:
       0: aload_0
       1: iload_1
       2: putfield      #4                  // Field months:I
       5: return

  public void setDays(int);
    Code:
       0: aload_0
       1: iload_1
       2: putfield      #5                  // Field days:I
       5: return

  public void setHours(int);
    Code:
       0: aload_0
       1: iload_1
       2: putfield      #6                  // Field hours:I
       5: return

  public void setMinutes(int);
    Code:
       0: aload_0
       1: iload_1
       2: putfield      #7                  // Field minutes:I
       5: return

  public void setSeconds(int);
    Code:
       0: aload_0
       1: iload_1
       2: i2d
       3: putfield      #25                 // Field seconds:D
       6: return

  public void setSeconds(double);
    Code:
       0: aload_0
       1: dload_1
       2: ldc2_w        #26                 // double 100.0d
       5: dmul
       6: invokestatic  #37                 // Method java/lang/Math.round:(D)J
       9: l2d
      10: ldc2_w        #26                 // double 100.0d
      13: ddiv
      14: putfield      #25                 // Field seconds:D
      17: return

  public java.lang.String toString();
    Code:
       0: new           #38                 // class java/lang/StringBuffer
       3: dup
       4: invokespecial #39                 // Method java/lang/StringBuffer."<init>":()V
       7: astore_1
       8: aload_1
       9: ldc           #11                 // String P
      11: invokevirtual #40                 // Method java/lang/StringBuffer.append:(Ljava/lang/String;)Ljava/lang/StringBuffer;
      14: pop
      15: aload_0
      16: getfield      #3                  // Field years:I
      19: ifeq          36
      22: aload_1
      23: aload_0
      24: getfield      #3                  // Field years:I
      27: invokevirtual #41                 // Method java/lang/StringBuffer.append:(I)Ljava/lang/StringBuffer;
      30: ldc           #35                 // String Y
      32: invokevirtual #40                 // Method java/lang/StringBuffer.append:(Ljava/lang/String;)Ljava/lang/StringBuffer;
      35: pop
      36: aload_0
      37: getfield      #4                  // Field months:I
      40: ifeq          57
      43: aload_1
      44: aload_0
      45: getfield      #4                  // Field months:I
      48: invokevirtual #41                 // Method java/lang/StringBuffer.append:(I)Ljava/lang/StringBuffer;
      51: ldc           #30                 // String M
      53: invokevirtual #40                 // Method java/lang/StringBuffer.append:(Ljava/lang/String;)Ljava/lang/StringBuffer;
      56: pop
      57: aload_0
      58: getfield      #5                  // Field days:I
      61: ifeq          78
      64: aload_1
      65: aload_0
      66: getfield      #5                  // Field days:I
      69: invokevirtual #41                 // Method java/lang/StringBuffer.append:(I)Ljava/lang/StringBuffer;
      72: ldc           #36                 // String D
      74: invokevirtual #40                 // Method java/lang/StringBuffer.append:(Ljava/lang/String;)Ljava/lang/StringBuffer;
      77: pop
      78: aload_0
      79: getfield      #6                  // Field hours:I
      82: ifne          101
      85: aload_0
      86: getfield      #7                  // Field minutes:I
      89: ifne          101
      92: aload_0
      93: getfield      #25                 // Field seconds:D
      96: dconst_0
      97: dcmpl
      98: ifeq          205
     101: aload_1
     102: ldc           #9                  // String T
     104: invokevirtual #40                 // Method java/lang/StringBuffer.append:(Ljava/lang/String;)Ljava/lang/StringBuffer;
     107: pop
     108: aload_0
     109: getfield      #6                  // Field hours:I
     112: ifeq          129
     115: aload_1
     116: aload_0
     117: getfield      #6                  // Field hours:I
     120: invokevirtual #41                 // Method java/lang/StringBuffer.append:(I)Ljava/lang/StringBuffer;
     123: ldc           #28                 // String H
     125: invokevirtual #40                 // Method java/lang/StringBuffer.append:(Ljava/lang/String;)Ljava/lang/StringBuffer;
     128: pop
     129: aload_0
     130: getfield      #7                  // Field minutes:I
     133: ifeq          150
     136: aload_1
     137: aload_0
     138: getfield      #7                  // Field minutes:I
     141: invokevirtual #41                 // Method java/lang/StringBuffer.append:(I)Ljava/lang/StringBuffer;
     144: ldc           #30                 // String M
     146: invokevirtual #40                 // Method java/lang/StringBuffer.append:(Ljava/lang/String;)Ljava/lang/StringBuffer;
     149: pop
     150: aload_0
     151: getfield      #25                 // Field seconds:D
     154: dconst_0
     155: dcmpl
     156: ifeq          205
     159: aload_0
     160: getfield      #25                 // Field seconds:D
     163: aload_0
     164: getfield      #25                 // Field seconds:D
     167: d2i
     168: i2d
     169: dcmpl
     170: ifne          191
     173: aload_1
     174: aload_0
     175: getfield      #25                 // Field seconds:D
     178: d2i
     179: invokevirtual #41                 // Method java/lang/StringBuffer.append:(I)Ljava/lang/StringBuffer;
     182: ldc           #31                 // String S
     184: invokevirtual #40                 // Method java/lang/StringBuffer.append:(Ljava/lang/String;)Ljava/lang/StringBuffer;
     187: pop
     188: goto          205
     191: aload_1
     192: aload_0
     193: getfield      #25                 // Field seconds:D
     196: invokevirtual #42                 // Method java/lang/StringBuffer.append:(D)Ljava/lang/StringBuffer;
     199: ldc           #31                 // String S
     201: invokevirtual #40                 // Method java/lang/StringBuffer.append:(Ljava/lang/String;)Ljava/lang/StringBuffer;
     204: pop
     205: aload_1
     206: invokevirtual #43                 // Method java/lang/StringBuffer.length:()I
     209: iconst_1
     210: if_icmpne     220
     213: aload_1
     214: ldc           #44                 // String T0S
     216: invokevirtual #40                 // Method java/lang/StringBuffer.append:(Ljava/lang/String;)Ljava/lang/StringBuffer;
     219: pop
     220: aload_0
     221: getfield      #2                  // Field isNegative:Z
     224: ifeq          235
     227: aload_1
     228: iconst_0
     229: ldc           #17                 // String -
     231: invokevirtual #45                 // Method java/lang/StringBuffer.insert:(ILjava/lang/String;)Ljava/lang/StringBuffer;
     234: pop
     235: aload_1
     236: invokevirtual #46                 // Method java/lang/StringBuffer.toString:()Ljava/lang/String;
     239: areturn

  public boolean equals(java.lang.Object);
    Code:
       0: aload_1
       1: instanceof    #47                 // class org/apache/axis2/databinding/types/Duration
       4: ifne          9
       7: iconst_0
       8: ireturn
       9: aload_1
      10: checkcast     #47                 // class org/apache/axis2/databinding/types/Duration
      13: astore_2
      14: aload_0
      15: getfield      #2                  // Field isNegative:Z
      18: aload_2
      19: getfield      #2                  // Field isNegative:Z
      22: if_icmpne     43
      25: aload_0
      26: invokevirtual #48                 // Method getAsCalendar:()Ljava/util/Calendar;
      29: aload_2
      30: invokevirtual #48                 // Method getAsCalendar:()Ljava/util/Calendar;
      33: invokevirtual #49                 // Method java/util/Calendar.equals:(Ljava/lang/Object;)Z
      36: ifeq          43
      39: iconst_1
      40: goto          44
      43: iconst_0
      44: ireturn

  public long compare(org.apache.axis2.databinding.types.Duration);
    Code:
       0: aload_0
       1: invokevirtual #48                 // Method getAsCalendar:()Ljava/util/Calendar;
       4: invokevirtual #50                 // Method java/util/Calendar.getTimeInMillis:()J
       7: aload_1
       8: invokevirtual #48                 // Method getAsCalendar:()Ljava/util/Calendar;
      11: invokevirtual #50                 // Method java/util/Calendar.getTimeInMillis:()J
      14: lsub
      15: lreturn

  public int hashCode();
    Code:
       0: iconst_0
       1: istore_1
       2: aload_0
       3: getfield      #2                  // Field isNegative:Z
       6: ifeq          12
       9: iinc          1, 1
      12: iload_1
      13: aload_0
      14: getfield      #3                  // Field years:I
      17: iadd
      18: istore_1
      19: iload_1
      20: aload_0
      21: getfield      #4                  // Field months:I
      24: iadd
      25: istore_1
      26: iload_1
      27: aload_0
      28: getfield      #5                  // Field days:I
      31: iadd
      32: istore_1
      33: iload_1
      34: aload_0
      35: getfield      #6                  // Field hours:I
      38: iadd
      39: istore_1
      40: iload_1
      41: aload_0
      42: getfield      #7                  // Field minutes:I
      45: iadd
      46: istore_1
      47: iload_1
      48: i2d
      49: aload_0
      50: getfield      #25                 // Field seconds:D
      53: dadd
      54: d2i
      55: istore_1
      56: iload_1
      57: i2d
      58: aload_0
      59: getfield      #25                 // Field seconds:D
      62: ldc2_w        #26                 // double 100.0d
      65: dmul
      66: ldc2_w        #26                 // double 100.0d
      69: drem
      70: dadd
      71: d2i
      72: istore_1
      73: iload_1
      74: ireturn

  public java.util.Calendar getAsCalendar();
    Code:
       0: aload_0
       1: invokestatic  #51                 // Method java/util/Calendar.getInstance:()Ljava/util/Calendar;
       4: invokevirtual #52                 // Method getAsCalendar:(Ljava/util/Calendar;)Ljava/util/Calendar;
       7: areturn

  public java.util.Calendar getAsCalendar(java.util.Calendar);
    Code:
       0: aload_1
       1: invokevirtual #53                 // Method java/util/Calendar.clone:()Ljava/lang/Object;
       4: checkcast     #23                 // class java/util/Calendar
       7: astore_2
       8: aload_2
       9: iconst_1
      10: aload_0
      11: getfield      #3                  // Field years:I
      14: invokevirtual #54                 // Method java/util/Calendar.set:(II)V
      17: aload_2
      18: iconst_2
      19: aload_0
      20: getfield      #4                  // Field months:I
      23: invokevirtual #54                 // Method java/util/Calendar.set:(II)V
      26: aload_2
      27: iconst_5
      28: aload_0
      29: getfield      #5                  // Field days:I
      32: invokevirtual #54                 // Method java/util/Calendar.set:(II)V
      35: aload_2
      36: bipush        10
      38: aload_0
      39: getfield      #6                  // Field hours:I
      42: invokevirtual #54                 // Method java/util/Calendar.set:(II)V
      45: aload_2
      46: bipush        12
      48: aload_0
      49: getfield      #7                  // Field minutes:I
      52: invokevirtual #54                 // Method java/util/Calendar.set:(II)V
      55: aload_2
      56: bipush        13
      58: aload_0
      59: getfield      #25                 // Field seconds:D
      62: d2i
      63: invokevirtual #54                 // Method java/util/Calendar.set:(II)V
      66: aload_2
      67: bipush        14
      69: aload_0
      70: getfield      #25                 // Field seconds:D
      73: ldc2_w        #26                 // double 100.0d
      76: dmul
      77: aload_0
      78: getfield      #25                 // Field seconds:D
      81: invokestatic  #37                 // Method java/lang/Math.round:(D)J
      84: ldc2_w        #55                 // long 100l
      87: lmul
      88: l2d
      89: dsub
      90: d2i
      91: invokevirtual #54                 // Method java/util/Calendar.set:(II)V
      94: aload_2
      95: areturn
}
