Compiled from "UnixSocketAddress.java"
public class jnr.unixsocket.UnixSocketAddress extends java.net.SocketAddress {
  private static final long serialVersionUID;

  private transient jnr.unixsocket.SockAddrUnix address;

  jnr.unixsocket.UnixSocketAddress();
    Code:
       0: aload_0
       1: invokespecial #1                  // Method java/net/SocketAddress."<init>":()V
       4: aload_0
       5: invokestatic  #2                  // Method jnr/unixsocket/SockAddrUnix.create:()Ljnr/unixsocket/SockAddrUnix;
       8: putfield      #3                  // Field address:Ljnr/unixsocket/SockAddrUnix;
      11: aload_0
      12: getfield      #3                  // Field address:Ljnr/unixsocket/SockAddrUnix;
      15: getstatic     #4                  // Field jnr/constants/platform/ProtocolFamily.PF_UNIX:Ljnr/constants/platform/ProtocolFamily;
      18: invokevirtual #5                  // Method jnr/unixsocket/SockAddrUnix.setFamily:(Ljnr/constants/platform/ProtocolFamily;)V
      21: return

  public jnr.unixsocket.UnixSocketAddress(java.io.File);
    Code:
       0: aload_0
       1: invokespecial #1                  // Method java/net/SocketAddress."<init>":()V
       4: aload_0
       5: invokestatic  #2                  // Method jnr/unixsocket/SockAddrUnix.create:()Ljnr/unixsocket/SockAddrUnix;
       8: putfield      #3                  // Field address:Ljnr/unixsocket/SockAddrUnix;
      11: aload_0
      12: getfield      #3                  // Field address:Ljnr/unixsocket/SockAddrUnix;
      15: getstatic     #4                  // Field jnr/constants/platform/ProtocolFamily.PF_UNIX:Ljnr/constants/platform/ProtocolFamily;
      18: invokevirtual #5                  // Method jnr/unixsocket/SockAddrUnix.setFamily:(Ljnr/constants/platform/ProtocolFamily;)V
      21: aload_0
      22: getfield      #3                  // Field address:Ljnr/unixsocket/SockAddrUnix;
      25: aload_1
      26: invokevirtual #6                  // Method java/io/File.getPath:()Ljava/lang/String;
      29: invokevirtual #7                  // Method jnr/unixsocket/SockAddrUnix.setPath:(Ljava/lang/String;)V
      32: return

  public jnr.unixsocket.UnixSocketAddress(java.lang.String);
    Code:
       0: aload_0
       1: invokespecial #1                  // Method java/net/SocketAddress."<init>":()V
       4: aload_0
       5: invokestatic  #2                  // Method jnr/unixsocket/SockAddrUnix.create:()Ljnr/unixsocket/SockAddrUnix;
       8: putfield      #3                  // Field address:Ljnr/unixsocket/SockAddrUnix;
      11: aload_0
      12: getfield      #3                  // Field address:Ljnr/unixsocket/SockAddrUnix;
      15: getstatic     #4                  // Field jnr/constants/platform/ProtocolFamily.PF_UNIX:Ljnr/constants/platform/ProtocolFamily;
      18: invokevirtual #5                  // Method jnr/unixsocket/SockAddrUnix.setFamily:(Ljnr/constants/platform/ProtocolFamily;)V
      21: aload_0
      22: getfield      #3                  // Field address:Ljnr/unixsocket/SockAddrUnix;
      25: aload_1
      26: invokevirtual #7                  // Method jnr/unixsocket/SockAddrUnix.setPath:(Ljava/lang/String;)V
      29: return

  jnr.unixsocket.SockAddrUnix getStruct();
    Code:
       0: aload_0
       1: getfield      #3                  // Field address:Ljnr/unixsocket/SockAddrUnix;
       4: areturn

  int length();
    Code:
       0: aload_0
       1: getfield      #3                  // Field address:Ljnr/unixsocket/SockAddrUnix;
       4: invokevirtual #8                  // Method jnr/unixsocket/SockAddrUnix.length:()I
       7: ireturn

  public java.lang.String path();
    Code:
       0: aload_0
       1: getfield      #3                  // Field address:Ljnr/unixsocket/SockAddrUnix;
       4: invokevirtual #9                  // Method jnr/unixsocket/SockAddrUnix.getPath:()Ljava/lang/String;
       7: areturn

  public java.lang.String humanReadablePath();
    Code:
       0: aload_0
       1: invokevirtual #10                 // Method path:()Ljava/lang/String;
       4: astore_1
       5: aload_1
       6: iconst_0
       7: invokevirtual #11                 // Method java/lang/String.indexOf:(I)I
      10: ifne          21
      13: aload_1
      14: iconst_0
      15: bipush        64
      17: invokevirtual #12                 // Method java/lang/String.replace:(CC)Ljava/lang/String;
      20: areturn
      21: aload_1
      22: areturn

  public java.lang.String toString();
    Code:
       0: new           #13                 // class java/lang/StringBuilder
       3: dup
       4: invokespecial #14                 // Method java/lang/StringBuilder."<init>":()V
       7: ldc           #15                 // String [family=
       9: invokevirtual #16                 // Method java/lang/StringBuilder.append:(Ljava/lang/String;)Ljava/lang/StringBuilder;
      12: aload_0
      13: getfield      #3                  // Field address:Ljnr/unixsocket/SockAddrUnix;
      16: invokevirtual #17                 // Method jnr/unixsocket/SockAddrUnix.getFamily:()Ljnr/constants/platform/ProtocolFamily;
      19: invokevirtual #18                 // Method java/lang/StringBuilder.append:(Ljava/lang/Object;)Ljava/lang/StringBuilder;
      22: ldc           #19                 // String  path=
      24: invokevirtual #16                 // Method java/lang/StringBuilder.append:(Ljava/lang/String;)Ljava/lang/StringBuilder;
      27: aload_0
      28: invokevirtual #20                 // Method humanReadablePath:()Ljava/lang/String;
      31: invokevirtual #16                 // Method java/lang/StringBuilder.append:(Ljava/lang/String;)Ljava/lang/StringBuilder;
      34: ldc           #21                 // String ]
      36: invokevirtual #16                 // Method java/lang/StringBuilder.append:(Ljava/lang/String;)Ljava/lang/StringBuilder;
      39: invokevirtual #22                 // Method java/lang/StringBuilder.toString:()Ljava/lang/String;
      42: areturn

  public boolean equals(java.lang.Object);
    Code:
       0: aload_1
       1: instanceof    #23                 // class jnr/unixsocket/UnixSocketAddress
       4: ifne          9
       7: iconst_0
       8: ireturn
       9: aload_1
      10: checkcast     #23                 // class jnr/unixsocket/UnixSocketAddress
      13: astore_2
      14: aload_0
      15: getfield      #3                  // Field address:Ljnr/unixsocket/SockAddrUnix;
      18: invokevirtual #17                 // Method jnr/unixsocket/SockAddrUnix.getFamily:()Ljnr/constants/platform/ProtocolFamily;
      21: aload_2
      22: getfield      #3                  // Field address:Ljnr/unixsocket/SockAddrUnix;
      25: invokevirtual #17                 // Method jnr/unixsocket/SockAddrUnix.getFamily:()Ljnr/constants/platform/ProtocolFamily;
      28: if_acmpne     49
      31: aload_0
      32: invokevirtual #10                 // Method path:()Ljava/lang/String;
      35: aload_2
      36: invokevirtual #10                 // Method path:()Ljava/lang/String;
      39: invokevirtual #24                 // Method java/lang/String.equals:(Ljava/lang/Object;)Z
      42: ifeq          49
      45: iconst_1
      46: goto          50
      49: iconst_0
      50: ireturn

  public int hashCode();
    Code:
       0: aload_0
       1: getfield      #3                  // Field address:Ljnr/unixsocket/SockAddrUnix;
       4: invokevirtual #25                 // Method java/lang/Object.hashCode:()I
       7: ireturn

  private void writeObject(java.io.ObjectOutputStream) throws java.io.IOException;
    Code:
       0: aload_1
       1: invokevirtual #26                 // Method java/io/ObjectOutputStream.defaultWriteObject:()V
       4: aload_1
       5: aload_0
       6: invokevirtual #10                 // Method path:()Ljava/lang/String;
       9: invokevirtual #27                 // Method java/io/ObjectOutputStream.writeObject:(Ljava/lang/Object;)V
      12: return

  private void readObject(java.io.ObjectInputStream) throws java.io.IOException, java.lang.ClassNotFoundException;
    Code:
       0: aload_1
       1: invokevirtual #28                 // Method java/io/ObjectInputStream.defaultReadObject:()V
       4: aload_1
       5: invokevirtual #29                 // Method java/io/ObjectInputStream.readObject:()Ljava/lang/Object;
       8: checkcast     #30                 // class java/lang/String
      11: astore_2
      12: aconst_null
      13: aload_0
      14: getfield      #3                  // Field address:Ljnr/unixsocket/SockAddrUnix;
      17: if_acmpne     27
      20: aload_0
      21: invokestatic  #2                  // Method jnr/unixsocket/SockAddrUnix.create:()Ljnr/unixsocket/SockAddrUnix;
      24: putfield      #3                  // Field address:Ljnr/unixsocket/SockAddrUnix;
      27: aload_0
      28: getfield      #3                  // Field address:Ljnr/unixsocket/SockAddrUnix;
      31: aload_2
      32: invokevirtual #7                  // Method jnr/unixsocket/SockAddrUnix.setPath:(Ljava/lang/String;)V
      35: aload_0
      36: getfield      #3                  // Field address:Ljnr/unixsocket/SockAddrUnix;
      39: getstatic     #4                  // Field jnr/constants/platform/ProtocolFamily.PF_UNIX:Ljnr/constants/platform/ProtocolFamily;
      42: invokevirtual #5                  // Method jnr/unixsocket/SockAddrUnix.setFamily:(Ljnr/constants/platform/ProtocolFamily;)V
      45: return
}
