Compiled from "VolatileIntHolder.java"
public class com.mchange.v1.lang.holders.VolatileIntHolder implements com.mchange.v1.lang.holders.ThreadSafeIntHolder {
  volatile int value;

  public com.mchange.v1.lang.holders.VolatileIntHolder();
    Code:
       0: aload_0
       1: invokespecial #1                  // Method java/lang/Object."<init>":()V
       4: return

  public int getValue();
    Code:
       0: aload_0
       1: getfield      #2                  // Field value:I
       4: ireturn

  public void setValue(int);
    Code:
       0: aload_0
       1: iload_1
       2: putfield      #2                  // Field value:I
       5: return
}
