Compiled from "ClientConnectionManagerFactory.java"
public class com.amazonaws.http.conn.ClientConnectionManagerFactory {
  private static final org.apache.commons.logging.Log log;

  public com.amazonaws.http.conn.ClientConnectionManagerFactory();
    Code:
       0: aload_0
       1: invokespecial #2                  // Method java/lang/Object."<init>":()V
       4: return

  public static org.apache.http.conn.HttpClientConnectionManager wrap(org.apache.http.conn.HttpClientConnectionManager);
    Code:
       0: aload_0
       1: instanceof    #3                  // class com/amazonaws/http/conn/Wrapped
       4: ifeq          15
       7: new           #4                  // class java/lang/IllegalArgumentException
      10: dup
      11: invokespecial #5                  // Method java/lang/IllegalArgumentException."<init>":()V
      14: athrow
      15: aload_0
      16: instanceof    #6                  // class org/apache/http/pool/ConnPoolControl
      19: ifeq          45
      22: iconst_3
      23: anewarray     #7                  // class java/lang/Class
      26: dup
      27: iconst_0
      28: ldc           #8                  // class org/apache/http/conn/HttpClientConnectionManager
      30: aastore
      31: dup
      32: iconst_1
      33: ldc           #6                  // class org/apache/http/pool/ConnPoolControl
      35: aastore
      36: dup
      37: iconst_2
      38: ldc           #3                  // class com/amazonaws/http/conn/Wrapped
      40: aastore
      41: astore_1
      42: goto          60
      45: iconst_2
      46: anewarray     #7                  // class java/lang/Class
      49: dup
      50: iconst_0
      51: ldc           #8                  // class org/apache/http/conn/HttpClientConnectionManager
      53: aastore
      54: dup
      55: iconst_1
      56: ldc           #3                  // class com/amazonaws/http/conn/Wrapped
      58: aastore
      59: astore_1
      60: ldc           #9                  // class com/amazonaws/http/conn/ClientConnectionManagerFactory
      62: invokevirtual #10                 // Method java/lang/Class.getClassLoader:()Ljava/lang/ClassLoader;
      65: aload_1
      66: new           #11                 // class com/amazonaws/http/conn/ClientConnectionManagerFactory$Handler
      69: dup
      70: aload_0
      71: invokespecial #12                 // Method com/amazonaws/http/conn/ClientConnectionManagerFactory$Handler."<init>":(Lorg/apache/http/conn/HttpClientConnectionManager;)V
      74: invokestatic  #13                 // Method java/lang/reflect/Proxy.newProxyInstance:(Ljava/lang/ClassLoader;[Ljava/lang/Class;Ljava/lang/reflect/InvocationHandler;)Ljava/lang/Object;
      77: checkcast     #8                  // class org/apache/http/conn/HttpClientConnectionManager
      80: areturn

  static org.apache.commons.logging.Log access$000();
    Code:
       0: getstatic     #1                  // Field log:Lorg/apache/commons/logging/Log;
       3: areturn

  static {};
    Code:
       0: ldc           #9                  // class com/amazonaws/http/conn/ClientConnectionManagerFactory
       2: invokestatic  #14                 // Method org/apache/commons/logging/LogFactory.getLog:(Ljava/lang/Class;)Lorg/apache/commons/logging/Log;
       5: putstatic     #1                  // Field log:Lorg/apache/commons/logging/Log;
       8: return
}
