Compiled from "CollectionArgumentChoice.java"
public class net.sourceforge.argparse4j.impl.choice.CollectionArgumentChoice<E> implements net.sourceforge.argparse4j.inf.ArgumentChoice {
  private java.util.Collection<E> values_;

  public net.sourceforge.argparse4j.impl.choice.CollectionArgumentChoice(E...);
    Code:
       0: aload_0
       1: invokespecial #1                  // Method java/lang/Object."<init>":()V
       4: aload_0
       5: aload_1
       6: invokestatic  #2                  // Method java/util/Arrays.asList:([Ljava/lang/Object;)Ljava/util/List;
       9: putfield      #3                  // Field values_:Ljava/util/Collection;
      12: return

  public net.sourceforge.argparse4j.impl.choice.CollectionArgumentChoice(java.util.Collection<E>);
    Code:
       0: aload_0
       1: invokespecial #1                  // Method java/lang/Object."<init>":()V
       4: aload_0
       5: aload_1
       6: putfield      #3                  // Field values_:Ljava/util/Collection;
       9: return

  public boolean contains(java.lang.Object);
    Code:
       0: aload_0
       1: getfield      #3                  // Field values_:Ljava/util/Collection;
       4: invokeinterface #4,  1            // InterfaceMethod java/util/Collection.isEmpty:()Z
       9: ifeq          14
      12: iconst_0
      13: ireturn
      14: aload_0
      15: getfield      #3                  // Field values_:Ljava/util/Collection;
      18: invokeinterface #5,  1            // InterfaceMethod java/util/Collection.iterator:()Ljava/util/Iterator;
      23: invokeinterface #6,  1            // InterfaceMethod java/util/Iterator.next:()Ljava/lang/Object;
      28: invokevirtual #7                  // Method java/lang/Object.getClass:()Ljava/lang/Class;
      31: astore_2
      32: aload_2
      33: aload_1
      34: invokevirtual #7                  // Method java/lang/Object.getClass:()Ljava/lang/Class;
      37: invokevirtual #8                  // Method java/lang/Object.equals:(Ljava/lang/Object;)Z
      40: ifeq          54
      43: aload_0
      44: getfield      #3                  // Field values_:Ljava/util/Collection;
      47: aload_1
      48: invokeinterface #9,  2            // InterfaceMethod java/util/Collection.contains:(Ljava/lang/Object;)Z
      53: ireturn
      54: new           #10                 // class java/lang/IllegalArgumentException
      57: dup
      58: aconst_null
      59: checkcast     #11                 // class java/util/Locale
      62: ldc           #12                 // String type mismatch (Make sure that you specified correct Argument.type()): expected: %s actual: %s
      64: iconst_2
      65: anewarray     #13                 // class java/lang/Object
      68: dup
      69: iconst_0
      70: aload_2
      71: invokevirtual #14                 // Method java/lang/Class.getName:()Ljava/lang/String;
      74: aastore
      75: dup
      76: iconst_1
      77: aload_1
      78: invokevirtual #7                  // Method java/lang/Object.getClass:()Ljava/lang/Class;
      81: invokevirtual #14                 // Method java/lang/Class.getName:()Ljava/lang/String;
      84: aastore
      85: invokestatic  #15                 // Method java/lang/String.format:(Ljava/util/Locale;Ljava/lang/String;[Ljava/lang/Object;)Ljava/lang/String;
      88: invokespecial #16                 // Method java/lang/IllegalArgumentException."<init>":(Ljava/lang/String;)V
      91: athrow

  public java.lang.String textualFormat();
    Code:
       0: aload_0
       1: getfield      #3                  // Field values_:Ljava/util/Collection;
       4: iconst_0
       5: ldc           #17                 // String ,
       7: ldc           #18                 // String {
       9: ldc           #19                 // String }
      11: invokestatic  #20                 // Method net/sourceforge/argparse4j/helper/TextHelper.concat:(Ljava/util/Collection;ILjava/lang/String;Ljava/lang/String;Ljava/lang/String;)Ljava/lang/String;
      14: areturn

  public java.lang.String toString();
    Code:
       0: aload_0
       1: invokevirtual #21                 // Method textualFormat:()Ljava/lang/String;
       4: areturn
}
