Compiled from "RealWebSocket.java"
final class io.dekorate.deps.okhttp3.internal.ws.RealWebSocket$Message {
  final int formatOpcode;

  final io.dekorate.deps.okio.ByteString data;

  io.dekorate.deps.okhttp3.internal.ws.RealWebSocket$Message(int, io.dekorate.deps.okio.ByteString);
    Code:
       0: aload_0
       1: invokespecial #17                 // Method java/lang/Object."<init>":()V
       4: aload_0
       5: iload_1
       6: putfield      #19                 // Field formatOpcode:I
       9: aload_0
      10: aload_2
      11: putfield      #21                 // Field data:Lio/dekorate/deps/okio/ByteString;
      14: return
}
