class org.bouncycastle.pqc.crypto.lms.LMOtsPublicKey implements org.bouncycastle.util.Encodable {
  private final org.bouncycastle.pqc.crypto.lms.LMOtsParameters parameter;

  private final byte[] I;

  private final int q;

  private final byte[] K;

  public org.bouncycastle.pqc.crypto.lms.LMOtsPublicKey(org.bouncycastle.pqc.crypto.lms.LMOtsParameters, byte[], int, byte[]);
    Code:
       0: aload_0
       1: invokespecial #156                // Method java/lang/Object."<init>":()V
       4: aload_0
       5: aload_1
       6: putfield      #148                // Field parameter:Lorg/bouncycastle/pqc/crypto/lms/LMOtsParameters;
       9: aload_0
      10: aload_2
      11: putfield      #146                // Field I:[B
      14: aload_0
      15: iload_3
      16: putfield      #145                // Field q:I
      19: aload_0
      20: aload         4
      22: putfield      #147                // Field K:[B
      25: return

  public static org.bouncycastle.pqc.crypto.lms.LMOtsPublicKey getInstance(java.lang.Object) throws java.lang.Exception;
    Code:
       0: aload_0
       1: instanceof    #76                 // class org/bouncycastle/pqc/crypto/lms/LMOtsPublicKey
       4: ifeq          12
       7: aload_0
       8: checkcast     #76                 // class org/bouncycastle/pqc/crypto/lms/LMOtsPublicKey
      11: areturn
      12: aload_0
      13: instanceof    #65                 // class java/io/DataInputStream
      16: ifeq          81
      19: aload_0
      20: checkcast     #65                 // class java/io/DataInputStream
      23: invokevirtual #150                // Method java/io/DataInputStream.readInt:()I
      26: invokestatic  #173                // Method org/bouncycastle/pqc/crypto/lms/LMOtsParameters.getParametersForType:(I)Lorg/bouncycastle/pqc/crypto/lms/LMOtsParameters;
      29: astore_1
      30: bipush        16
      32: newarray       byte
      34: astore_2
      35: aload_0
      36: checkcast     #65                 // class java/io/DataInputStream
      39: aload_2
      40: invokevirtual #151                // Method java/io/DataInputStream.readFully:([B)V
      43: aload_0
      44: checkcast     #65                 // class java/io/DataInputStream
      47: invokevirtual #150                // Method java/io/DataInputStream.readInt:()I
      50: istore_3
      51: aload_1
      52: invokevirtual #170                // Method org/bouncycastle/pqc/crypto/lms/LMOtsParameters.getN:()I
      55: newarray       byte
      57: astore        4
      59: aload_0
      60: checkcast     #65                 // class java/io/DataInputStream
      63: aload         4
      65: invokevirtual #151                // Method java/io/DataInputStream.readFully:([B)V
      68: new           #76                 // class org/bouncycastle/pqc/crypto/lms/LMOtsPublicKey
      71: dup
      72: aload_1
      73: aload_2
      74: iload_3
      75: aload         4
      77: invokespecial #174                // Method "<init>":(Lorg/bouncycastle/pqc/crypto/lms/LMOtsParameters;[BI[B)V
      80: areturn
      81: aload_0
      82: instanceof    #63                 // class "[B"
      85: ifeq          140
      88: aconst_null
      89: astore_1
      90: new           #65                 // class java/io/DataInputStream
      93: dup
      94: new           #64                 // class java/io/ByteArrayInputStream
      97: dup
      98: aload_0
      99: checkcast     #63                 // class "[B"
     102: checkcast     #63                 // class "[B"
     105: invokespecial #149                // Method java/io/ByteArrayInputStream."<init>":([B)V
     108: invokespecial #152                // Method java/io/DataInputStream."<init>":(Ljava/io/InputStream;)V
     111: astore_1
     112: aload_1
     113: invokestatic  #175                // Method getInstance:(Ljava/lang/Object;)Lorg/bouncycastle/pqc/crypto/lms/LMOtsPublicKey;
     116: astore_2
     117: aload_1
     118: ifnull        125
     121: aload_1
     122: invokevirtual #153                // Method java/io/InputStream.close:()V
     125: aload_2
     126: areturn
     127: astore        5
     129: aload_1
     130: ifnull        137
     133: aload_1
     134: invokevirtual #153                // Method java/io/InputStream.close:()V
     137: aload         5
     139: athrow
     140: aload_0
     141: instanceof    #67                 // class java/io/InputStream
     144: ifeq          158
     147: aload_0
     148: checkcast     #67                 // class java/io/InputStream
     151: invokestatic  #182                // Method org/bouncycastle/util/io/Streams.readAll:(Ljava/io/InputStream;)[B
     154: invokestatic  #175                // Method getInstance:(Ljava/lang/Object;)Lorg/bouncycastle/pqc/crypto/lms/LMOtsPublicKey;
     157: areturn
     158: new           #69                 // class java/lang/IllegalArgumentException
     161: dup
     162: new           #71                 // class java/lang/StringBuilder
     165: dup
     166: invokespecial #159                // Method java/lang/StringBuilder."<init>":()V
     169: ldc           #1                  // String cannot parse
     171: invokevirtual #162                // Method java/lang/StringBuilder.append:(Ljava/lang/String;)Ljava/lang/StringBuilder;
     174: aload_0
     175: invokevirtual #161                // Method java/lang/StringBuilder.append:(Ljava/lang/Object;)Ljava/lang/StringBuilder;
     178: invokevirtual #160                // Method java/lang/StringBuilder.toString:()Ljava/lang/String;
     181: invokespecial #154                // Method java/lang/IllegalArgumentException."<init>":(Ljava/lang/String;)V
     184: athrow
    Exception table:
       from    to  target type
          90   117   127   any
         127   129   127   any

  public org.bouncycastle.pqc.crypto.lms.LMOtsParameters getParameter();
    Code:
       0: aload_0
       1: getfield      #148                // Field parameter:Lorg/bouncycastle/pqc/crypto/lms/LMOtsParameters;
       4: areturn

  public byte[] getI();
    Code:
       0: aload_0
       1: getfield      #146                // Field I:[B
       4: areturn

  public int getQ();
    Code:
       0: aload_0
       1: getfield      #145                // Field q:I
       4: ireturn

  public byte[] getK();
    Code:
       0: aload_0
       1: getfield      #147                // Field K:[B
       4: areturn

  public boolean equals(java.lang.Object);
    Code:
       0: aload_0
       1: aload_1
       2: if_acmpne     7
       5: iconst_1
       6: ireturn
       7: aload_1
       8: ifnull        22
      11: aload_0
      12: invokevirtual #157                // Method java/lang/Object.getClass:()Ljava/lang/Class;
      15: aload_1
      16: invokevirtual #157                // Method java/lang/Object.getClass:()Ljava/lang/Class;
      19: if_acmpeq     24
      22: iconst_0
      23: ireturn
      24: aload_1
      25: checkcast     #76                 // class org/bouncycastle/pqc/crypto/lms/LMOtsPublicKey
      28: astore_2
      29: aload_0
      30: getfield      #145                // Field q:I
      33: aload_2
      34: getfield      #145                // Field q:I
      37: if_icmpeq     42
      40: iconst_0
      41: ireturn
      42: aload_0
      43: getfield      #148                // Field parameter:Lorg/bouncycastle/pqc/crypto/lms/LMOtsParameters;
      46: ifnull        66
      49: aload_0
      50: getfield      #148                // Field parameter:Lorg/bouncycastle/pqc/crypto/lms/LMOtsParameters;
      53: aload_2
      54: getfield      #148                // Field parameter:Lorg/bouncycastle/pqc/crypto/lms/LMOtsParameters;
      57: invokevirtual #158                // Method java/lang/Object.equals:(Ljava/lang/Object;)Z
      60: ifne          75
      63: goto          73
      66: aload_2
      67: getfield      #148                // Field parameter:Lorg/bouncycastle/pqc/crypto/lms/LMOtsParameters;
      70: ifnull        75
      73: iconst_0
      74: ireturn
      75: aload_0
      76: getfield      #146                // Field I:[B
      79: aload_2
      80: getfield      #146                // Field I:[B
      83: invokestatic  #164                // Method java/util/Arrays.equals:([B[B)Z
      86: ifne          91
      89: iconst_0
      90: ireturn
      91: aload_0
      92: getfield      #147                // Field K:[B
      95: aload_2
      96: getfield      #147                // Field K:[B
      99: invokestatic  #164                // Method java/util/Arrays.equals:([B[B)Z
     102: ireturn

  public int hashCode();
    Code:
       0: aload_0
       1: getfield      #148                // Field parameter:Lorg/bouncycastle/pqc/crypto/lms/LMOtsParameters;
       4: ifnull        17
       7: aload_0
       8: getfield      #148                // Field parameter:Lorg/bouncycastle/pqc/crypto/lms/LMOtsParameters;
      11: invokevirtual #155                // Method java/lang/Object.hashCode:()I
      14: goto          18
      17: iconst_0
      18: istore_1
      19: bipush        31
      21: iload_1
      22: imul
      23: aload_0
      24: getfield      #146                // Field I:[B
      27: invokestatic  #163                // Method java/util/Arrays.hashCode:([B)I
      30: iadd
      31: istore_1
      32: bipush        31
      34: iload_1
      35: imul
      36: aload_0
      37: getfield      #145                // Field q:I
      40: iadd
      41: istore_1
      42: bipush        31
      44: iload_1
      45: imul
      46: aload_0
      47: getfield      #147                // Field K:[B
      50: invokestatic  #163                // Method java/util/Arrays.hashCode:([B)I
      53: iadd
      54: istore_1
      55: iload_1
      56: ireturn

  public byte[] getEncoded() throws java.io.IOException;
    Code:
       0: invokestatic  #166                // Method org/bouncycastle/pqc/crypto/lms/Composer.compose:()Lorg/bouncycastle/pqc/crypto/lms/Composer;
       3: aload_0
       4: getfield      #148                // Field parameter:Lorg/bouncycastle/pqc/crypto/lms/LMOtsParameters;
       7: invokevirtual #171                // Method org/bouncycastle/pqc/crypto/lms/LMOtsParameters.getType:()I
      10: invokevirtual #167                // Method org/bouncycastle/pqc/crypto/lms/Composer.u32str:(I)Lorg/bouncycastle/pqc/crypto/lms/Composer;
      13: aload_0
      14: getfield      #146                // Field I:[B
      17: invokevirtual #168                // Method org/bouncycastle/pqc/crypto/lms/Composer.bytes:([B)Lorg/bouncycastle/pqc/crypto/lms/Composer;
      20: aload_0
      21: getfield      #145                // Field q:I
      24: invokevirtual #167                // Method org/bouncycastle/pqc/crypto/lms/Composer.u32str:(I)Lorg/bouncycastle/pqc/crypto/lms/Composer;
      27: aload_0
      28: getfield      #147                // Field K:[B
      31: invokevirtual #168                // Method org/bouncycastle/pqc/crypto/lms/Composer.bytes:([B)Lorg/bouncycastle/pqc/crypto/lms/Composer;
      34: invokevirtual #165                // Method org/bouncycastle/pqc/crypto/lms/Composer.build:()[B
      37: areturn

  org.bouncycastle.pqc.crypto.lms.LMSContext createOtsContext(org.bouncycastle.pqc.crypto.lms.LMOtsSignature);
    Code:
       0: aload_0
       1: getfield      #148                // Field parameter:Lorg/bouncycastle/pqc/crypto/lms/LMOtsParameters;
       4: invokevirtual #172                // Method org/bouncycastle/pqc/crypto/lms/LMOtsParameters.getDigestOID:()Lorg/bouncycastle/asn1/ASN1ObjectIdentifier;
       7: invokestatic  #169                // Method org/bouncycastle/pqc/crypto/lms/DigestUtil.getDigest:(Lorg/bouncycastle/asn1/ASN1ObjectIdentifier;)Lorg/bouncycastle/crypto/Digest;
      10: astore_2
      11: aload_0
      12: getfield      #146                // Field I:[B
      15: aload_2
      16: invokestatic  #181                // Method org/bouncycastle/pqc/crypto/lms/LmsUtils.byteArray:([BLorg/bouncycastle/crypto/Digest;)V
      19: aload_0
      20: getfield      #145                // Field q:I
      23: aload_2
      24: invokestatic  #179                // Method org/bouncycastle/pqc/crypto/lms/LmsUtils.u32str:(ILorg/bouncycastle/crypto/Digest;)V
      27: sipush        -32383
      30: aload_2
      31: invokestatic  #180                // Method org/bouncycastle/pqc/crypto/lms/LmsUtils.u16str:(SLorg/bouncycastle/crypto/Digest;)V
      34: aload_1
      35: invokevirtual #176                // Method org/bouncycastle/pqc/crypto/lms/LMOtsSignature.getC:()[B
      38: aload_2
      39: invokestatic  #181                // Method org/bouncycastle/pqc/crypto/lms/LmsUtils.byteArray:([BLorg/bouncycastle/crypto/Digest;)V
      42: new           #78                 // class org/bouncycastle/pqc/crypto/lms/LMSContext
      45: dup
      46: aload_0
      47: aload_1
      48: aload_2
      49: invokespecial #177                // Method org/bouncycastle/pqc/crypto/lms/LMSContext."<init>":(Lorg/bouncycastle/pqc/crypto/lms/LMOtsPublicKey;Ljava/lang/Object;Lorg/bouncycastle/crypto/Digest;)V
      52: areturn

  org.bouncycastle.pqc.crypto.lms.LMSContext createOtsContext(org.bouncycastle.pqc.crypto.lms.LMSSignature);
    Code:
       0: aload_0
       1: getfield      #148                // Field parameter:Lorg/bouncycastle/pqc/crypto/lms/LMOtsParameters;
       4: invokevirtual #172                // Method org/bouncycastle/pqc/crypto/lms/LMOtsParameters.getDigestOID:()Lorg/bouncycastle/asn1/ASN1ObjectIdentifier;
       7: invokestatic  #169                // Method org/bouncycastle/pqc/crypto/lms/DigestUtil.getDigest:(Lorg/bouncycastle/asn1/ASN1ObjectIdentifier;)Lorg/bouncycastle/crypto/Digest;
      10: astore_2
      11: aload_0
      12: getfield      #146                // Field I:[B
      15: aload_2
      16: invokestatic  #181                // Method org/bouncycastle/pqc/crypto/lms/LmsUtils.byteArray:([BLorg/bouncycastle/crypto/Digest;)V
      19: aload_0
      20: getfield      #145                // Field q:I
      23: aload_2
      24: invokestatic  #179                // Method org/bouncycastle/pqc/crypto/lms/LmsUtils.u32str:(ILorg/bouncycastle/crypto/Digest;)V
      27: sipush        -32383
      30: aload_2
      31: invokestatic  #180                // Method org/bouncycastle/pqc/crypto/lms/LmsUtils.u16str:(SLorg/bouncycastle/crypto/Digest;)V
      34: aload_1
      35: invokevirtual #178                // Method org/bouncycastle/pqc/crypto/lms/LMSSignature.getOtsSignature:()Lorg/bouncycastle/pqc/crypto/lms/LMOtsSignature;
      38: invokevirtual #176                // Method org/bouncycastle/pqc/crypto/lms/LMOtsSignature.getC:()[B
      41: aload_2
      42: invokestatic  #181                // Method org/bouncycastle/pqc/crypto/lms/LmsUtils.byteArray:([BLorg/bouncycastle/crypto/Digest;)V
      45: new           #78                 // class org/bouncycastle/pqc/crypto/lms/LMSContext
      48: dup
      49: aload_0
      50: aload_1
      51: aload_2
      52: invokespecial #177                // Method org/bouncycastle/pqc/crypto/lms/LMSContext."<init>":(Lorg/bouncycastle/pqc/crypto/lms/LMOtsPublicKey;Ljava/lang/Object;Lorg/bouncycastle/crypto/Digest;)V
      55: areturn
}
