Compiled from "VerifyResponseWrapper.java"
public class org.hpccsystems.ws.client.wrappers.gen.wscodesign.VerifyResponseWrapper {
  protected org.hpccsystems.ws.client.wrappers.gen.wscodesign.ArrayOfEspExceptionWrapper local_exceptions;

  protected int local_retCode;

  protected java.lang.String local_errMsg;

  protected boolean local_isVerified;

  protected java.lang.String local_signedBy;

  public org.hpccsystems.ws.client.wrappers.gen.wscodesign.VerifyResponseWrapper();
    Code:
       0: aload_0
       1: invokespecial #1                  // Method java/lang/Object."<init>":()V
       4: return

  public org.hpccsystems.ws.client.wrappers.gen.wscodesign.VerifyResponseWrapper(org.hpccsystems.ws.client.gen.axis2.wscodesign.v1_01.VerifyResponse);
    Code:
       0: aload_0
       1: invokespecial #1                  // Method java/lang/Object."<init>":()V
       4: aload_0
       5: aload_1
       6: invokespecial #2                  // Method copy:(Lorg/hpccsystems/ws/client/gen/axis2/wscodesign/v1_01/VerifyResponse;)V
       9: return

  public org.hpccsystems.ws.client.wrappers.gen.wscodesign.VerifyResponseWrapper(org.hpccsystems.ws.client.wrappers.gen.wscodesign.ArrayOfEspExceptionWrapper, int, java.lang.String, boolean, java.lang.String);
    Code:
       0: aload_0
       1: invokespecial #1                  // Method java/lang/Object."<init>":()V
       4: aload_0
       5: aload_1
       6: putfield      #3                  // Field local_exceptions:Lorg/hpccsystems/ws/client/wrappers/gen/wscodesign/ArrayOfEspExceptionWrapper;
       9: aload_0
      10: iload_2
      11: putfield      #4                  // Field local_retCode:I
      14: aload_0
      15: aload_3
      16: putfield      #5                  // Field local_errMsg:Ljava/lang/String;
      19: aload_0
      20: iload         4
      22: putfield      #6                  // Field local_isVerified:Z
      25: aload_0
      26: aload         5
      28: putfield      #7                  // Field local_signedBy:Ljava/lang/String;
      31: return

  private void copy(org.hpccsystems.ws.client.gen.axis2.wscodesign.v1_01.VerifyResponse);
    Code:
       0: aload_1
       1: ifnonnull     5
       4: return
       5: aload_1
       6: invokevirtual #8                  // Method org/hpccsystems/ws/client/gen/axis2/wscodesign/v1_01/VerifyResponse.getExceptions:()Lorg/hpccsystems/ws/client/gen/axis2/wscodesign/v1_01/ArrayOfEspException;
       9: ifnull        27
      12: aload_0
      13: new           #9                  // class org/hpccsystems/ws/client/wrappers/gen/wscodesign/ArrayOfEspExceptionWrapper
      16: dup
      17: aload_1
      18: invokevirtual #8                  // Method org/hpccsystems/ws/client/gen/axis2/wscodesign/v1_01/VerifyResponse.getExceptions:()Lorg/hpccsystems/ws/client/gen/axis2/wscodesign/v1_01/ArrayOfEspException;
      21: invokespecial #10                 // Method org/hpccsystems/ws/client/wrappers/gen/wscodesign/ArrayOfEspExceptionWrapper."<init>":(Lorg/hpccsystems/ws/client/gen/axis2/wscodesign/v1_01/ArrayOfEspException;)V
      24: putfield      #3                  // Field local_exceptions:Lorg/hpccsystems/ws/client/wrappers/gen/wscodesign/ArrayOfEspExceptionWrapper;
      27: aload_0
      28: aload_1
      29: invokevirtual #11                 // Method org/hpccsystems/ws/client/gen/axis2/wscodesign/v1_01/VerifyResponse.getRetCode:()I
      32: putfield      #4                  // Field local_retCode:I
      35: aload_0
      36: aload_1
      37: invokevirtual #12                 // Method org/hpccsystems/ws/client/gen/axis2/wscodesign/v1_01/VerifyResponse.getErrMsg:()Ljava/lang/String;
      40: putfield      #5                  // Field local_errMsg:Ljava/lang/String;
      43: aload_0
      44: aload_1
      45: invokevirtual #13                 // Method org/hpccsystems/ws/client/gen/axis2/wscodesign/v1_01/VerifyResponse.getIsVerified:()Z
      48: putfield      #6                  // Field local_isVerified:Z
      51: aload_0
      52: aload_1
      53: invokevirtual #14                 // Method org/hpccsystems/ws/client/gen/axis2/wscodesign/v1_01/VerifyResponse.getSignedBy:()Ljava/lang/String;
      56: putfield      #7                  // Field local_signedBy:Ljava/lang/String;
      59: return

  public java.lang.String toString();
    Code:
       0: new           #15                 // class java/lang/StringBuilder
       3: dup
       4: invokespecial #16                 // Method java/lang/StringBuilder."<init>":()V
       7: ldc           #17                 // String VerifyResponseWrapper [exceptions =
       9: invokevirtual #18                 // Method java/lang/StringBuilder.append:(Ljava/lang/String;)Ljava/lang/StringBuilder;
      12: aload_0
      13: getfield      #3                  // Field local_exceptions:Lorg/hpccsystems/ws/client/wrappers/gen/wscodesign/ArrayOfEspExceptionWrapper;
      16: invokevirtual #19                 // Method java/lang/StringBuilder.append:(Ljava/lang/Object;)Ljava/lang/StringBuilder;
      19: ldc           #20                 // String , retCode =
      21: invokevirtual #18                 // Method java/lang/StringBuilder.append:(Ljava/lang/String;)Ljava/lang/StringBuilder;
      24: aload_0
      25: getfield      #4                  // Field local_retCode:I
      28: invokevirtual #21                 // Method java/lang/StringBuilder.append:(I)Ljava/lang/StringBuilder;
      31: ldc           #22                 // String , errMsg =
      33: invokevirtual #18                 // Method java/lang/StringBuilder.append:(Ljava/lang/String;)Ljava/lang/StringBuilder;
      36: aload_0
      37: getfield      #5                  // Field local_errMsg:Ljava/lang/String;
      40: invokevirtual #18                 // Method java/lang/StringBuilder.append:(Ljava/lang/String;)Ljava/lang/StringBuilder;
      43: ldc           #23                 // String , isVerified =
      45: invokevirtual #18                 // Method java/lang/StringBuilder.append:(Ljava/lang/String;)Ljava/lang/StringBuilder;
      48: aload_0
      49: getfield      #6                  // Field local_isVerified:Z
      52: invokevirtual #24                 // Method java/lang/StringBuilder.append:(Z)Ljava/lang/StringBuilder;
      55: ldc           #25                 // String , signedBy =
      57: invokevirtual #18                 // Method java/lang/StringBuilder.append:(Ljava/lang/String;)Ljava/lang/StringBuilder;
      60: aload_0
      61: getfield      #7                  // Field local_signedBy:Ljava/lang/String;
      64: invokevirtual #18                 // Method java/lang/StringBuilder.append:(Ljava/lang/String;)Ljava/lang/StringBuilder;
      67: ldc           #26                 // String ]
      69: invokevirtual #18                 // Method java/lang/StringBuilder.append:(Ljava/lang/String;)Ljava/lang/StringBuilder;
      72: invokevirtual #27                 // Method java/lang/StringBuilder.toString:()Ljava/lang/String;
      75: areturn

  public org.hpccsystems.ws.client.gen.axis2.wscodesign.v1_01.VerifyResponse getRaw();
    Code:
       0: new           #28                 // class org/hpccsystems/ws/client/gen/axis2/wscodesign/v1_01/VerifyResponse
       3: dup
       4: invokespecial #29                 // Method org/hpccsystems/ws/client/gen/axis2/wscodesign/v1_01/VerifyResponse."<init>":()V
       7: astore_1
       8: aload_1
       9: aload_0
      10: getfield      #4                  // Field local_retCode:I
      13: invokevirtual #30                 // Method org/hpccsystems/ws/client/gen/axis2/wscodesign/v1_01/VerifyResponse.setRetCode:(I)V
      16: aload_1
      17: aload_0
      18: getfield      #5                  // Field local_errMsg:Ljava/lang/String;
      21: invokevirtual #31                 // Method org/hpccsystems/ws/client/gen/axis2/wscodesign/v1_01/VerifyResponse.setErrMsg:(Ljava/lang/String;)V
      24: aload_1
      25: aload_0
      26: getfield      #6                  // Field local_isVerified:Z
      29: invokevirtual #32                 // Method org/hpccsystems/ws/client/gen/axis2/wscodesign/v1_01/VerifyResponse.setIsVerified:(Z)V
      32: aload_1
      33: aload_0
      34: getfield      #7                  // Field local_signedBy:Ljava/lang/String;
      37: invokevirtual #33                 // Method org/hpccsystems/ws/client/gen/axis2/wscodesign/v1_01/VerifyResponse.setSignedBy:(Ljava/lang/String;)V
      40: aload_1
      41: areturn

  public void setExceptions(org.hpccsystems.ws.client.wrappers.gen.wscodesign.ArrayOfEspExceptionWrapper);
    Code:
       0: aload_0
       1: aload_1
       2: putfield      #3                  // Field local_exceptions:Lorg/hpccsystems/ws/client/wrappers/gen/wscodesign/ArrayOfEspExceptionWrapper;
       5: return

  public org.hpccsystems.ws.client.wrappers.gen.wscodesign.ArrayOfEspExceptionWrapper getExceptions();
    Code:
       0: aload_0
       1: getfield      #3                  // Field local_exceptions:Lorg/hpccsystems/ws/client/wrappers/gen/wscodesign/ArrayOfEspExceptionWrapper;
       4: areturn

  public void setRetCode(int);
    Code:
       0: aload_0
       1: iload_1
       2: putfield      #4                  // Field local_retCode:I
       5: return

  public int getRetCode();
    Code:
       0: aload_0
       1: getfield      #4                  // Field local_retCode:I
       4: ireturn

  public void setErrMsg(java.lang.String);
    Code:
       0: aload_0
       1: aload_1
       2: putfield      #5                  // Field local_errMsg:Ljava/lang/String;
       5: return

  public java.lang.String getErrMsg();
    Code:
       0: aload_0
       1: getfield      #5                  // Field local_errMsg:Ljava/lang/String;
       4: areturn

  public void setIsVerified(boolean);
    Code:
       0: aload_0
       1: iload_1
       2: putfield      #6                  // Field local_isVerified:Z
       5: return

  public boolean getIsVerified();
    Code:
       0: aload_0
       1: getfield      #6                  // Field local_isVerified:Z
       4: ireturn

  public void setSignedBy(java.lang.String);
    Code:
       0: aload_0
       1: aload_1
       2: putfield      #7                  // Field local_signedBy:Ljava/lang/String;
       5: return

  public java.lang.String getSignedBy();
    Code:
       0: aload_0
       1: getfield      #7                  // Field local_signedBy:Ljava/lang/String;
       4: areturn
}
