Compiled from "DataSourceMetaDataMerger.java"
public class org.jboss.metadata.merge.javaee.spec.DataSourceMetaDataMerger {
  public org.jboss.metadata.merge.javaee.spec.DataSourceMetaDataMerger();
    Code:
       0: aload_0
       1: invokespecial #1                  // Method java/lang/Object."<init>":()V
       4: return

  public static org.jboss.metadata.javaee.spec.DataSourceMetaData merge(org.jboss.metadata.javaee.spec.DataSourceMetaData, org.jboss.metadata.javaee.spec.DataSourceMetaData);
    Code:
       0: new           #2                  // class org/jboss/metadata/javaee/spec/DataSourceMetaData
       3: dup
       4: invokespecial #3                  // Method org/jboss/metadata/javaee/spec/DataSourceMetaData."<init>":()V
       7: astore_2
       8: aload_2
       9: aload_0
      10: aload_1
      11: invokestatic  #4                  // Method merge:(Lorg/jboss/metadata/javaee/spec/DataSourceMetaData;Lorg/jboss/metadata/javaee/spec/DataSourceMetaData;Lorg/jboss/metadata/javaee/spec/DataSourceMetaData;)V
      14: aload_2
      15: areturn

  public static void merge(org.jboss.metadata.javaee.spec.DataSourceMetaData, org.jboss.metadata.javaee.spec.DataSourceMetaData, org.jboss.metadata.javaee.spec.DataSourceMetaData);
    Code:
       0: aload_0
       1: aload_1
       2: aload_2
       3: invokestatic  #5                  // Method org/jboss/metadata/merge/javaee/support/NamedMetaDataMerger.merge:(Lorg/jboss/metadata/javaee/support/NamedMetaData;Lorg/jboss/metadata/javaee/support/NamedMetaData;Lorg/jboss/metadata/javaee/support/NamedMetaData;)V
       6: aload_1
       7: ifnull        28
      10: aload_1
      11: invokevirtual #6                  // Method org/jboss/metadata/javaee/spec/DataSourceMetaData.getClassName:()Ljava/lang/String;
      14: ifnull        28
      17: aload_0
      18: aload_1
      19: invokevirtual #6                  // Method org/jboss/metadata/javaee/spec/DataSourceMetaData.getClassName:()Ljava/lang/String;
      22: invokevirtual #7                  // Method org/jboss/metadata/javaee/spec/DataSourceMetaData.setClassName:(Ljava/lang/String;)V
      25: goto          47
      28: aload_2
      29: ifnull        47
      32: aload_2
      33: invokevirtual #6                  // Method org/jboss/metadata/javaee/spec/DataSourceMetaData.getClassName:()Ljava/lang/String;
      36: ifnull        47
      39: aload_0
      40: aload_2
      41: invokevirtual #6                  // Method org/jboss/metadata/javaee/spec/DataSourceMetaData.getClassName:()Ljava/lang/String;
      44: invokevirtual #7                  // Method org/jboss/metadata/javaee/spec/DataSourceMetaData.setClassName:(Ljava/lang/String;)V
      47: aload_1
      48: ifnull        69
      51: aload_1
      52: invokevirtual #8                  // Method org/jboss/metadata/javaee/spec/DataSourceMetaData.getDatabaseName:()Ljava/lang/String;
      55: ifnull        69
      58: aload_0
      59: aload_1
      60: invokevirtual #8                  // Method org/jboss/metadata/javaee/spec/DataSourceMetaData.getDatabaseName:()Ljava/lang/String;
      63: invokevirtual #9                  // Method org/jboss/metadata/javaee/spec/DataSourceMetaData.setDatabaseName:(Ljava/lang/String;)V
      66: goto          88
      69: aload_2
      70: ifnull        88
      73: aload_2
      74: invokevirtual #8                  // Method org/jboss/metadata/javaee/spec/DataSourceMetaData.getDatabaseName:()Ljava/lang/String;
      77: ifnull        88
      80: aload_0
      81: aload_2
      82: invokevirtual #8                  // Method org/jboss/metadata/javaee/spec/DataSourceMetaData.getDatabaseName:()Ljava/lang/String;
      85: invokevirtual #9                  // Method org/jboss/metadata/javaee/spec/DataSourceMetaData.setDatabaseName:(Ljava/lang/String;)V
      88: aload_1
      89: ifnull        111
      92: aload_1
      93: invokevirtual #10                 // Method org/jboss/metadata/javaee/spec/DataSourceMetaData.getInitialPoolSize:()I
      96: iconst_m1
      97: if_icmpeq     111
     100: aload_0
     101: aload_1
     102: invokevirtual #10                 // Method org/jboss/metadata/javaee/spec/DataSourceMetaData.getInitialPoolSize:()I
     105: invokevirtual #11                 // Method org/jboss/metadata/javaee/spec/DataSourceMetaData.setInitialPoolSize:(I)V
     108: goto          131
     111: aload_2
     112: ifnull        131
     115: aload_2
     116: invokevirtual #10                 // Method org/jboss/metadata/javaee/spec/DataSourceMetaData.getInitialPoolSize:()I
     119: iconst_m1
     120: if_icmpeq     131
     123: aload_0
     124: aload_2
     125: invokevirtual #10                 // Method org/jboss/metadata/javaee/spec/DataSourceMetaData.getInitialPoolSize:()I
     128: invokevirtual #11                 // Method org/jboss/metadata/javaee/spec/DataSourceMetaData.setInitialPoolSize:(I)V
     131: aload_1
     132: ifnull        153
     135: aload_1
     136: invokevirtual #12                 // Method org/jboss/metadata/javaee/spec/DataSourceMetaData.getIsolationLevel:()Lorg/jboss/metadata/javaee/spec/IsolationLevelType;
     139: ifnull        153
     142: aload_0
     143: aload_1
     144: invokevirtual #12                 // Method org/jboss/metadata/javaee/spec/DataSourceMetaData.getIsolationLevel:()Lorg/jboss/metadata/javaee/spec/IsolationLevelType;
     147: invokevirtual #13                 // Method org/jboss/metadata/javaee/spec/DataSourceMetaData.setIsolationLevel:(Lorg/jboss/metadata/javaee/spec/IsolationLevelType;)V
     150: goto          172
     153: aload_2
     154: ifnull        172
     157: aload_2
     158: invokevirtual #12                 // Method org/jboss/metadata/javaee/spec/DataSourceMetaData.getIsolationLevel:()Lorg/jboss/metadata/javaee/spec/IsolationLevelType;
     161: ifnull        172
     164: aload_0
     165: aload_2
     166: invokevirtual #12                 // Method org/jboss/metadata/javaee/spec/DataSourceMetaData.getIsolationLevel:()Lorg/jboss/metadata/javaee/spec/IsolationLevelType;
     169: invokevirtual #13                 // Method org/jboss/metadata/javaee/spec/DataSourceMetaData.setIsolationLevel:(Lorg/jboss/metadata/javaee/spec/IsolationLevelType;)V
     172: aload_1
     173: ifnull        194
     176: aload_1
     177: invokevirtual #14                 // Method org/jboss/metadata/javaee/spec/DataSourceMetaData.getLoginTimeout:()I
     180: ifeq          194
     183: aload_0
     184: aload_1
     185: invokevirtual #14                 // Method org/jboss/metadata/javaee/spec/DataSourceMetaData.getLoginTimeout:()I
     188: invokevirtual #15                 // Method org/jboss/metadata/javaee/spec/DataSourceMetaData.setLoginTimeout:(I)V
     191: goto          213
     194: aload_2
     195: ifnull        213
     198: aload_2
     199: invokevirtual #14                 // Method org/jboss/metadata/javaee/spec/DataSourceMetaData.getLoginTimeout:()I
     202: ifeq          213
     205: aload_0
     206: aload_2
     207: invokevirtual #14                 // Method org/jboss/metadata/javaee/spec/DataSourceMetaData.getLoginTimeout:()I
     210: invokevirtual #15                 // Method org/jboss/metadata/javaee/spec/DataSourceMetaData.setLoginTimeout:(I)V
     213: aload_1
     214: ifnull        236
     217: aload_1
     218: invokevirtual #16                 // Method org/jboss/metadata/javaee/spec/DataSourceMetaData.getMaxIdleTime:()I
     221: iconst_m1
     222: if_icmpeq     236
     225: aload_0
     226: aload_1
     227: invokevirtual #16                 // Method org/jboss/metadata/javaee/spec/DataSourceMetaData.getMaxIdleTime:()I
     230: invokevirtual #17                 // Method org/jboss/metadata/javaee/spec/DataSourceMetaData.setMaxIdleTime:(I)V
     233: goto          256
     236: aload_2
     237: ifnull        256
     240: aload_2
     241: invokevirtual #16                 // Method org/jboss/metadata/javaee/spec/DataSourceMetaData.getMaxIdleTime:()I
     244: iconst_m1
     245: if_icmpeq     256
     248: aload_0
     249: aload_2
     250: invokevirtual #16                 // Method org/jboss/metadata/javaee/spec/DataSourceMetaData.getMaxIdleTime:()I
     253: invokevirtual #17                 // Method org/jboss/metadata/javaee/spec/DataSourceMetaData.setMaxIdleTime:(I)V
     256: aload_1
     257: ifnull        279
     260: aload_1
     261: invokevirtual #18                 // Method org/jboss/metadata/javaee/spec/DataSourceMetaData.getMaxPoolSize:()I
     264: iconst_m1
     265: if_icmpeq     279
     268: aload_0
     269: aload_1
     270: invokevirtual #18                 // Method org/jboss/metadata/javaee/spec/DataSourceMetaData.getMaxPoolSize:()I
     273: invokevirtual #19                 // Method org/jboss/metadata/javaee/spec/DataSourceMetaData.setMaxPoolSize:(I)V
     276: goto          299
     279: aload_2
     280: ifnull        299
     283: aload_2
     284: invokevirtual #18                 // Method org/jboss/metadata/javaee/spec/DataSourceMetaData.getMaxPoolSize:()I
     287: iconst_m1
     288: if_icmpeq     299
     291: aload_0
     292: aload_2
     293: invokevirtual #18                 // Method org/jboss/metadata/javaee/spec/DataSourceMetaData.getMaxPoolSize:()I
     296: invokevirtual #19                 // Method org/jboss/metadata/javaee/spec/DataSourceMetaData.setMaxPoolSize:(I)V
     299: aload_1
     300: ifnull        322
     303: aload_1
     304: invokevirtual #20                 // Method org/jboss/metadata/javaee/spec/DataSourceMetaData.getMaxStatements:()I
     307: iconst_m1
     308: if_icmpeq     322
     311: aload_0
     312: aload_1
     313: invokevirtual #20                 // Method org/jboss/metadata/javaee/spec/DataSourceMetaData.getMaxStatements:()I
     316: invokevirtual #21                 // Method org/jboss/metadata/javaee/spec/DataSourceMetaData.setMaxStatements:(I)V
     319: goto          342
     322: aload_2
     323: ifnull        342
     326: aload_2
     327: invokevirtual #20                 // Method org/jboss/metadata/javaee/spec/DataSourceMetaData.getMaxStatements:()I
     330: iconst_m1
     331: if_icmpeq     342
     334: aload_0
     335: aload_2
     336: invokevirtual #20                 // Method org/jboss/metadata/javaee/spec/DataSourceMetaData.getMaxStatements:()I
     339: invokevirtual #21                 // Method org/jboss/metadata/javaee/spec/DataSourceMetaData.setMaxStatements:(I)V
     342: aload_1
     343: ifnull        365
     346: aload_1
     347: invokevirtual #22                 // Method org/jboss/metadata/javaee/spec/DataSourceMetaData.getMinPoolSize:()I
     350: iconst_m1
     351: if_icmpeq     365
     354: aload_0
     355: aload_1
     356: invokevirtual #22                 // Method org/jboss/metadata/javaee/spec/DataSourceMetaData.getMinPoolSize:()I
     359: invokevirtual #23                 // Method org/jboss/metadata/javaee/spec/DataSourceMetaData.setMinPoolSize:(I)V
     362: goto          385
     365: aload_2
     366: ifnull        385
     369: aload_2
     370: invokevirtual #22                 // Method org/jboss/metadata/javaee/spec/DataSourceMetaData.getMinPoolSize:()I
     373: iconst_m1
     374: if_icmpeq     385
     377: aload_0
     378: aload_2
     379: invokevirtual #22                 // Method org/jboss/metadata/javaee/spec/DataSourceMetaData.getMinPoolSize:()I
     382: invokevirtual #23                 // Method org/jboss/metadata/javaee/spec/DataSourceMetaData.setMinPoolSize:(I)V
     385: aload_1
     386: ifnull        407
     389: aload_1
     390: invokevirtual #24                 // Method org/jboss/metadata/javaee/spec/DataSourceMetaData.getPassword:()Ljava/lang/String;
     393: ifnull        407
     396: aload_0
     397: aload_1
     398: invokevirtual #24                 // Method org/jboss/metadata/javaee/spec/DataSourceMetaData.getPassword:()Ljava/lang/String;
     401: invokevirtual #25                 // Method org/jboss/metadata/javaee/spec/DataSourceMetaData.setPassword:(Ljava/lang/String;)V
     404: goto          426
     407: aload_2
     408: ifnull        426
     411: aload_2
     412: invokevirtual #24                 // Method org/jboss/metadata/javaee/spec/DataSourceMetaData.getPassword:()Ljava/lang/String;
     415: ifnull        426
     418: aload_0
     419: aload_2
     420: invokevirtual #24                 // Method org/jboss/metadata/javaee/spec/DataSourceMetaData.getPassword:()Ljava/lang/String;
     423: invokevirtual #25                 // Method org/jboss/metadata/javaee/spec/DataSourceMetaData.setPassword:(Ljava/lang/String;)V
     426: aload_1
     427: ifnull        449
     430: aload_1
     431: invokevirtual #26                 // Method org/jboss/metadata/javaee/spec/DataSourceMetaData.getPortNumber:()I
     434: iconst_m1
     435: if_icmpeq     449
     438: aload_0
     439: aload_1
     440: invokevirtual #26                 // Method org/jboss/metadata/javaee/spec/DataSourceMetaData.getPortNumber:()I
     443: invokevirtual #27                 // Method org/jboss/metadata/javaee/spec/DataSourceMetaData.setPortNumber:(I)V
     446: goto          469
     449: aload_2
     450: ifnull        469
     453: aload_2
     454: invokevirtual #26                 // Method org/jboss/metadata/javaee/spec/DataSourceMetaData.getPortNumber:()I
     457: iconst_m1
     458: if_icmpeq     469
     461: aload_0
     462: aload_2
     463: invokevirtual #26                 // Method org/jboss/metadata/javaee/spec/DataSourceMetaData.getPortNumber:()I
     466: invokevirtual #27                 // Method org/jboss/metadata/javaee/spec/DataSourceMetaData.setPortNumber:(I)V
     469: aload_1
     470: ifnull        491
     473: aload_1
     474: invokevirtual #28                 // Method org/jboss/metadata/javaee/spec/DataSourceMetaData.getProperties:()Lorg/jboss/metadata/javaee/spec/PropertiesMetaData;
     477: ifnull        491
     480: aload_0
     481: aload_1
     482: invokevirtual #28                 // Method org/jboss/metadata/javaee/spec/DataSourceMetaData.getProperties:()Lorg/jboss/metadata/javaee/spec/PropertiesMetaData;
     485: invokevirtual #29                 // Method org/jboss/metadata/javaee/spec/DataSourceMetaData.setProperties:(Lorg/jboss/metadata/javaee/spec/PropertiesMetaData;)V
     488: goto          510
     491: aload_2
     492: ifnull        510
     495: aload_2
     496: invokevirtual #28                 // Method org/jboss/metadata/javaee/spec/DataSourceMetaData.getProperties:()Lorg/jboss/metadata/javaee/spec/PropertiesMetaData;
     499: ifnull        510
     502: aload_0
     503: aload_2
     504: invokevirtual #28                 // Method org/jboss/metadata/javaee/spec/DataSourceMetaData.getProperties:()Lorg/jboss/metadata/javaee/spec/PropertiesMetaData;
     507: invokevirtual #29                 // Method org/jboss/metadata/javaee/spec/DataSourceMetaData.setProperties:(Lorg/jboss/metadata/javaee/spec/PropertiesMetaData;)V
     510: aload_1
     511: ifnull        532
     514: aload_1
     515: invokevirtual #30                 // Method org/jboss/metadata/javaee/spec/DataSourceMetaData.getServerName:()Ljava/lang/String;
     518: ifnull        532
     521: aload_0
     522: aload_1
     523: invokevirtual #30                 // Method org/jboss/metadata/javaee/spec/DataSourceMetaData.getServerName:()Ljava/lang/String;
     526: invokevirtual #31                 // Method org/jboss/metadata/javaee/spec/DataSourceMetaData.setServerName:(Ljava/lang/String;)V
     529: goto          551
     532: aload_2
     533: ifnull        551
     536: aload_2
     537: invokevirtual #30                 // Method org/jboss/metadata/javaee/spec/DataSourceMetaData.getServerName:()Ljava/lang/String;
     540: ifnull        551
     543: aload_0
     544: aload_2
     545: invokevirtual #30                 // Method org/jboss/metadata/javaee/spec/DataSourceMetaData.getServerName:()Ljava/lang/String;
     548: invokevirtual #31                 // Method org/jboss/metadata/javaee/spec/DataSourceMetaData.setServerName:(Ljava/lang/String;)V
     551: aload_1
     552: ifnull        574
     555: aload_1
     556: invokevirtual #32                 // Method org/jboss/metadata/javaee/spec/DataSourceMetaData.getTransactional:()Z
     559: iconst_1
     560: if_icmpeq     574
     563: aload_0
     564: aload_1
     565: invokevirtual #32                 // Method org/jboss/metadata/javaee/spec/DataSourceMetaData.getTransactional:()Z
     568: invokevirtual #33                 // Method org/jboss/metadata/javaee/spec/DataSourceMetaData.setTransactional:(Z)V
     571: goto          594
     574: aload_2
     575: ifnull        594
     578: aload_2
     579: invokevirtual #32                 // Method org/jboss/metadata/javaee/spec/DataSourceMetaData.getTransactional:()Z
     582: iconst_1
     583: if_icmpeq     594
     586: aload_0
     587: aload_2
     588: invokevirtual #32                 // Method org/jboss/metadata/javaee/spec/DataSourceMetaData.getTransactional:()Z
     591: invokevirtual #33                 // Method org/jboss/metadata/javaee/spec/DataSourceMetaData.setTransactional:(Z)V
     594: aload_1
     595: ifnull        616
     598: aload_1
     599: invokevirtual #34                 // Method org/jboss/metadata/javaee/spec/DataSourceMetaData.getUrl:()Ljava/lang/String;
     602: ifnull        616
     605: aload_0
     606: aload_1
     607: invokevirtual #34                 // Method org/jboss/metadata/javaee/spec/DataSourceMetaData.getUrl:()Ljava/lang/String;
     610: invokevirtual #35                 // Method org/jboss/metadata/javaee/spec/DataSourceMetaData.setUrl:(Ljava/lang/String;)V
     613: goto          635
     616: aload_2
     617: ifnull        635
     620: aload_2
     621: invokevirtual #34                 // Method org/jboss/metadata/javaee/spec/DataSourceMetaData.getUrl:()Ljava/lang/String;
     624: ifnull        635
     627: aload_0
     628: aload_2
     629: invokevirtual #34                 // Method org/jboss/metadata/javaee/spec/DataSourceMetaData.getUrl:()Ljava/lang/String;
     632: invokevirtual #35                 // Method org/jboss/metadata/javaee/spec/DataSourceMetaData.setUrl:(Ljava/lang/String;)V
     635: aload_1
     636: ifnull        657
     639: aload_1
     640: invokevirtual #36                 // Method org/jboss/metadata/javaee/spec/DataSourceMetaData.getUser:()Ljava/lang/String;
     643: ifnull        657
     646: aload_0
     647: aload_1
     648: invokevirtual #36                 // Method org/jboss/metadata/javaee/spec/DataSourceMetaData.getUser:()Ljava/lang/String;
     651: invokevirtual #37                 // Method org/jboss/metadata/javaee/spec/DataSourceMetaData.setUser:(Ljava/lang/String;)V
     654: goto          676
     657: aload_2
     658: ifnull        676
     661: aload_2
     662: invokevirtual #36                 // Method org/jboss/metadata/javaee/spec/DataSourceMetaData.getUser:()Ljava/lang/String;
     665: ifnull        676
     668: aload_0
     669: aload_2
     670: invokevirtual #36                 // Method org/jboss/metadata/javaee/spec/DataSourceMetaData.getUser:()Ljava/lang/String;
     673: invokevirtual #37                 // Method org/jboss/metadata/javaee/spec/DataSourceMetaData.setUser:(Ljava/lang/String;)V
     676: return
}
