Compiled from "EJBLocalReferenceMetaDataMerger.java"
public class org.jboss.metadata.merge.javaee.spec.EJBLocalReferenceMetaDataMerger extends org.jboss.metadata.merge.javaee.spec.AbstractEJBReferenceMetaDataMerger {
  public org.jboss.metadata.merge.javaee.spec.EJBLocalReferenceMetaDataMerger();
    Code:
       0: aload_0
       1: invokespecial #1                  // Method org/jboss/metadata/merge/javaee/spec/AbstractEJBReferenceMetaDataMerger."<init>":()V
       4: return

  public static org.jboss.metadata.javaee.spec.EJBLocalReferenceMetaData merge(org.jboss.metadata.javaee.spec.EJBLocalReferenceMetaData, org.jboss.metadata.javaee.spec.EJBLocalReferenceMetaData);
    Code:
       0: new           #2                  // class org/jboss/metadata/javaee/spec/EJBLocalReferenceMetaData
       3: dup
       4: invokespecial #3                  // Method org/jboss/metadata/javaee/spec/EJBLocalReferenceMetaData."<init>":()V
       7: astore_2
       8: aload_2
       9: aload_0
      10: aload_1
      11: invokestatic  #4                  // Method merge:(Lorg/jboss/metadata/javaee/spec/EJBLocalReferenceMetaData;Lorg/jboss/metadata/javaee/spec/EJBLocalReferenceMetaData;Lorg/jboss/metadata/javaee/spec/EJBLocalReferenceMetaData;)V
      14: aload_2
      15: areturn

  public static void merge(org.jboss.metadata.javaee.spec.EJBLocalReferenceMetaData, org.jboss.metadata.javaee.spec.EJBLocalReferenceMetaData, org.jboss.metadata.javaee.spec.EJBLocalReferenceMetaData);
    Code:
       0: aload_0
       1: aload_1
       2: aload_2
       3: invokestatic  #5                  // Method org/jboss/metadata/merge/javaee/spec/AbstractEJBReferenceMetaDataMerger.merge:(Lorg/jboss/metadata/javaee/spec/AbstractEJBReferenceMetaData;Lorg/jboss/metadata/javaee/spec/AbstractEJBReferenceMetaData;Lorg/jboss/metadata/javaee/spec/AbstractEJBReferenceMetaData;)V
       6: aload_1
       7: ifnull        28
      10: aload_1
      11: invokevirtual #6                  // Method org/jboss/metadata/javaee/spec/EJBLocalReferenceMetaData.getEjbRefName:()Ljava/lang/String;
      14: ifnull        28
      17: aload_0
      18: aload_1
      19: invokevirtual #6                  // Method org/jboss/metadata/javaee/spec/EJBLocalReferenceMetaData.getEjbRefName:()Ljava/lang/String;
      22: invokevirtual #7                  // Method org/jboss/metadata/javaee/spec/EJBLocalReferenceMetaData.setEjbRefName:(Ljava/lang/String;)V
      25: goto          47
      28: aload_2
      29: ifnull        47
      32: aload_2
      33: invokevirtual #6                  // Method org/jboss/metadata/javaee/spec/EJBLocalReferenceMetaData.getEjbRefName:()Ljava/lang/String;
      36: ifnull        47
      39: aload_0
      40: aload_2
      41: invokevirtual #6                  // Method org/jboss/metadata/javaee/spec/EJBLocalReferenceMetaData.getEjbRefName:()Ljava/lang/String;
      44: invokevirtual #7                  // Method org/jboss/metadata/javaee/spec/EJBLocalReferenceMetaData.setEjbRefName:(Ljava/lang/String;)V
      47: aload_1
      48: ifnull        69
      51: aload_1
      52: invokevirtual #8                  // Method org/jboss/metadata/javaee/spec/EJBLocalReferenceMetaData.getLocalHome:()Ljava/lang/String;
      55: ifnull        69
      58: aload_0
      59: aload_1
      60: invokevirtual #8                  // Method org/jboss/metadata/javaee/spec/EJBLocalReferenceMetaData.getLocalHome:()Ljava/lang/String;
      63: invokevirtual #9                  // Method org/jboss/metadata/javaee/spec/EJBLocalReferenceMetaData.setLocalHome:(Ljava/lang/String;)V
      66: goto          88
      69: aload_2
      70: ifnull        88
      73: aload_2
      74: invokevirtual #8                  // Method org/jboss/metadata/javaee/spec/EJBLocalReferenceMetaData.getLocalHome:()Ljava/lang/String;
      77: ifnull        88
      80: aload_0
      81: aload_2
      82: invokevirtual #8                  // Method org/jboss/metadata/javaee/spec/EJBLocalReferenceMetaData.getLocalHome:()Ljava/lang/String;
      85: invokevirtual #9                  // Method org/jboss/metadata/javaee/spec/EJBLocalReferenceMetaData.setLocalHome:(Ljava/lang/String;)V
      88: aload_1
      89: ifnull        110
      92: aload_1
      93: invokevirtual #10                 // Method org/jboss/metadata/javaee/spec/EJBLocalReferenceMetaData.getLocal:()Ljava/lang/String;
      96: ifnull        110
      99: aload_0
     100: aload_1
     101: invokevirtual #10                 // Method org/jboss/metadata/javaee/spec/EJBLocalReferenceMetaData.getLocal:()Ljava/lang/String;
     104: invokevirtual #11                 // Method org/jboss/metadata/javaee/spec/EJBLocalReferenceMetaData.setLocal:(Ljava/lang/String;)V
     107: goto          129
     110: aload_2
     111: ifnull        129
     114: aload_2
     115: invokevirtual #10                 // Method org/jboss/metadata/javaee/spec/EJBLocalReferenceMetaData.getLocal:()Ljava/lang/String;
     118: ifnull        129
     121: aload_0
     122: aload_2
     123: invokevirtual #10                 // Method org/jboss/metadata/javaee/spec/EJBLocalReferenceMetaData.getLocal:()Ljava/lang/String;
     126: invokevirtual #11                 // Method org/jboss/metadata/javaee/spec/EJBLocalReferenceMetaData.setLocal:(Ljava/lang/String;)V
     129: return
}
