Compiled from "ActionType.java"
public class com.amazonaws.services.codepipeline.model.ActionType implements java.io.Serializable,java.lang.Cloneable {
  private com.amazonaws.services.codepipeline.model.ActionTypeId id;

  private com.amazonaws.services.codepipeline.model.ActionTypeSettings settings;

  private java.util.List<com.amazonaws.services.codepipeline.model.ActionConfigurationProperty> actionConfigurationProperties;

  private com.amazonaws.services.codepipeline.model.ArtifactDetails inputArtifactDetails;

  private com.amazonaws.services.codepipeline.model.ArtifactDetails outputArtifactDetails;

  public com.amazonaws.services.codepipeline.model.ActionType();
    Code:
       0: aload_0
       1: invokespecial #1                  // Method java/lang/Object."<init>":()V
       4: return

  public void setId(com.amazonaws.services.codepipeline.model.ActionTypeId);
    Code:
       0: aload_0
       1: aload_1
       2: putfield      #2                  // Field id:Lcom/amazonaws/services/codepipeline/model/ActionTypeId;
       5: return

  public com.amazonaws.services.codepipeline.model.ActionTypeId getId();
    Code:
       0: aload_0
       1: getfield      #2                  // Field id:Lcom/amazonaws/services/codepipeline/model/ActionTypeId;
       4: areturn

  public com.amazonaws.services.codepipeline.model.ActionType withId(com.amazonaws.services.codepipeline.model.ActionTypeId);
    Code:
       0: aload_0
       1: aload_1
       2: invokevirtual #3                  // Method setId:(Lcom/amazonaws/services/codepipeline/model/ActionTypeId;)V
       5: aload_0
       6: areturn

  public void setSettings(com.amazonaws.services.codepipeline.model.ActionTypeSettings);
    Code:
       0: aload_0
       1: aload_1
       2: putfield      #4                  // Field settings:Lcom/amazonaws/services/codepipeline/model/ActionTypeSettings;
       5: return

  public com.amazonaws.services.codepipeline.model.ActionTypeSettings getSettings();
    Code:
       0: aload_0
       1: getfield      #4                  // Field settings:Lcom/amazonaws/services/codepipeline/model/ActionTypeSettings;
       4: areturn

  public com.amazonaws.services.codepipeline.model.ActionType withSettings(com.amazonaws.services.codepipeline.model.ActionTypeSettings);
    Code:
       0: aload_0
       1: aload_1
       2: invokevirtual #5                  // Method setSettings:(Lcom/amazonaws/services/codepipeline/model/ActionTypeSettings;)V
       5: aload_0
       6: areturn

  public java.util.List<com.amazonaws.services.codepipeline.model.ActionConfigurationProperty> getActionConfigurationProperties();
    Code:
       0: aload_0
       1: getfield      #6                  // Field actionConfigurationProperties:Ljava/util/List;
       4: areturn

  public void setActionConfigurationProperties(java.util.Collection<com.amazonaws.services.codepipeline.model.ActionConfigurationProperty>);
    Code:
       0: aload_1
       1: ifnonnull     10
       4: aload_0
       5: aconst_null
       6: putfield      #6                  // Field actionConfigurationProperties:Ljava/util/List;
       9: return
      10: aload_0
      11: new           #7                  // class java/util/ArrayList
      14: dup
      15: aload_1
      16: invokespecial #8                  // Method java/util/ArrayList."<init>":(Ljava/util/Collection;)V
      19: putfield      #6                  // Field actionConfigurationProperties:Ljava/util/List;
      22: return

  public com.amazonaws.services.codepipeline.model.ActionType withActionConfigurationProperties(com.amazonaws.services.codepipeline.model.ActionConfigurationProperty...);
    Code:
       0: aload_0
       1: getfield      #6                  // Field actionConfigurationProperties:Ljava/util/List;
       4: ifnonnull     20
       7: aload_0
       8: new           #7                  // class java/util/ArrayList
      11: dup
      12: aload_1
      13: arraylength
      14: invokespecial #9                  // Method java/util/ArrayList."<init>":(I)V
      17: invokevirtual #10                 // Method setActionConfigurationProperties:(Ljava/util/Collection;)V
      20: aload_1
      21: astore_2
      22: aload_2
      23: arraylength
      24: istore_3
      25: iconst_0
      26: istore        4
      28: iload         4
      30: iload_3
      31: if_icmpge     58
      34: aload_2
      35: iload         4
      37: aaload
      38: astore        5
      40: aload_0
      41: getfield      #6                  // Field actionConfigurationProperties:Ljava/util/List;
      44: aload         5
      46: invokeinterface #11,  2           // InterfaceMethod java/util/List.add:(Ljava/lang/Object;)Z
      51: pop
      52: iinc          4, 1
      55: goto          28
      58: aload_0
      59: areturn

  public com.amazonaws.services.codepipeline.model.ActionType withActionConfigurationProperties(java.util.Collection<com.amazonaws.services.codepipeline.model.ActionConfigurationProperty>);
    Code:
       0: aload_0
       1: aload_1
       2: invokevirtual #10                 // Method setActionConfigurationProperties:(Ljava/util/Collection;)V
       5: aload_0
       6: areturn

  public void setInputArtifactDetails(com.amazonaws.services.codepipeline.model.ArtifactDetails);
    Code:
       0: aload_0
       1: aload_1
       2: putfield      #12                 // Field inputArtifactDetails:Lcom/amazonaws/services/codepipeline/model/ArtifactDetails;
       5: return

  public com.amazonaws.services.codepipeline.model.ArtifactDetails getInputArtifactDetails();
    Code:
       0: aload_0
       1: getfield      #12                 // Field inputArtifactDetails:Lcom/amazonaws/services/codepipeline/model/ArtifactDetails;
       4: areturn

  public com.amazonaws.services.codepipeline.model.ActionType withInputArtifactDetails(com.amazonaws.services.codepipeline.model.ArtifactDetails);
    Code:
       0: aload_0
       1: aload_1
       2: invokevirtual #13                 // Method setInputArtifactDetails:(Lcom/amazonaws/services/codepipeline/model/ArtifactDetails;)V
       5: aload_0
       6: areturn

  public void setOutputArtifactDetails(com.amazonaws.services.codepipeline.model.ArtifactDetails);
    Code:
       0: aload_0
       1: aload_1
       2: putfield      #14                 // Field outputArtifactDetails:Lcom/amazonaws/services/codepipeline/model/ArtifactDetails;
       5: return

  public com.amazonaws.services.codepipeline.model.ArtifactDetails getOutputArtifactDetails();
    Code:
       0: aload_0
       1: getfield      #14                 // Field outputArtifactDetails:Lcom/amazonaws/services/codepipeline/model/ArtifactDetails;
       4: areturn

  public com.amazonaws.services.codepipeline.model.ActionType withOutputArtifactDetails(com.amazonaws.services.codepipeline.model.ArtifactDetails);
    Code:
       0: aload_0
       1: aload_1
       2: invokevirtual #15                 // Method setOutputArtifactDetails:(Lcom/amazonaws/services/codepipeline/model/ArtifactDetails;)V
       5: aload_0
       6: areturn

  public java.lang.String toString();
    Code:
       0: new           #16                 // class java/lang/StringBuilder
       3: dup
       4: invokespecial #17                 // Method java/lang/StringBuilder."<init>":()V
       7: astore_1
       8: aload_1
       9: ldc           #18                 // String {
      11: invokevirtual #19                 // Method java/lang/StringBuilder.append:(Ljava/lang/String;)Ljava/lang/StringBuilder;
      14: pop
      15: aload_0
      16: invokevirtual #20                 // Method getId:()Lcom/amazonaws/services/codepipeline/model/ActionTypeId;
      19: ifnull        54
      22: aload_1
      23: new           #16                 // class java/lang/StringBuilder
      26: dup
      27: invokespecial #17                 // Method java/lang/StringBuilder."<init>":()V
      30: ldc           #21                 // String Id:
      32: invokevirtual #19                 // Method java/lang/StringBuilder.append:(Ljava/lang/String;)Ljava/lang/StringBuilder;
      35: aload_0
      36: invokevirtual #20                 // Method getId:()Lcom/amazonaws/services/codepipeline/model/ActionTypeId;
      39: invokevirtual #22                 // Method java/lang/StringBuilder.append:(Ljava/lang/Object;)Ljava/lang/StringBuilder;
      42: ldc           #23                 // String ,
      44: invokevirtual #19                 // Method java/lang/StringBuilder.append:(Ljava/lang/String;)Ljava/lang/StringBuilder;
      47: invokevirtual #24                 // Method java/lang/StringBuilder.toString:()Ljava/lang/String;
      50: invokevirtual #19                 // Method java/lang/StringBuilder.append:(Ljava/lang/String;)Ljava/lang/StringBuilder;
      53: pop
      54: aload_0
      55: invokevirtual #25                 // Method getSettings:()Lcom/amazonaws/services/codepipeline/model/ActionTypeSettings;
      58: ifnull        93
      61: aload_1
      62: new           #16                 // class java/lang/StringBuilder
      65: dup
      66: invokespecial #17                 // Method java/lang/StringBuilder."<init>":()V
      69: ldc           #26                 // String Settings:
      71: invokevirtual #19                 // Method java/lang/StringBuilder.append:(Ljava/lang/String;)Ljava/lang/StringBuilder;
      74: aload_0
      75: invokevirtual #25                 // Method getSettings:()Lcom/amazonaws/services/codepipeline/model/ActionTypeSettings;
      78: invokevirtual #22                 // Method java/lang/StringBuilder.append:(Ljava/lang/Object;)Ljava/lang/StringBuilder;
      81: ldc           #23                 // String ,
      83: invokevirtual #19                 // Method java/lang/StringBuilder.append:(Ljava/lang/String;)Ljava/lang/StringBuilder;
      86: invokevirtual #24                 // Method java/lang/StringBuilder.toString:()Ljava/lang/String;
      89: invokevirtual #19                 // Method java/lang/StringBuilder.append:(Ljava/lang/String;)Ljava/lang/StringBuilder;
      92: pop
      93: aload_0
      94: invokevirtual #27                 // Method getActionConfigurationProperties:()Ljava/util/List;
      97: ifnull        132
     100: aload_1
     101: new           #16                 // class java/lang/StringBuilder
     104: dup
     105: invokespecial #17                 // Method java/lang/StringBuilder."<init>":()V
     108: ldc           #28                 // String ActionConfigurationProperties:
     110: invokevirtual #19                 // Method java/lang/StringBuilder.append:(Ljava/lang/String;)Ljava/lang/StringBuilder;
     113: aload_0
     114: invokevirtual #27                 // Method getActionConfigurationProperties:()Ljava/util/List;
     117: invokevirtual #22                 // Method java/lang/StringBuilder.append:(Ljava/lang/Object;)Ljava/lang/StringBuilder;
     120: ldc           #23                 // String ,
     122: invokevirtual #19                 // Method java/lang/StringBuilder.append:(Ljava/lang/String;)Ljava/lang/StringBuilder;
     125: invokevirtual #24                 // Method java/lang/StringBuilder.toString:()Ljava/lang/String;
     128: invokevirtual #19                 // Method java/lang/StringBuilder.append:(Ljava/lang/String;)Ljava/lang/StringBuilder;
     131: pop
     132: aload_0
     133: invokevirtual #29                 // Method getInputArtifactDetails:()Lcom/amazonaws/services/codepipeline/model/ArtifactDetails;
     136: ifnull        171
     139: aload_1
     140: new           #16                 // class java/lang/StringBuilder
     143: dup
     144: invokespecial #17                 // Method java/lang/StringBuilder."<init>":()V
     147: ldc           #30                 // String InputArtifactDetails:
     149: invokevirtual #19                 // Method java/lang/StringBuilder.append:(Ljava/lang/String;)Ljava/lang/StringBuilder;
     152: aload_0
     153: invokevirtual #29                 // Method getInputArtifactDetails:()Lcom/amazonaws/services/codepipeline/model/ArtifactDetails;
     156: invokevirtual #22                 // Method java/lang/StringBuilder.append:(Ljava/lang/Object;)Ljava/lang/StringBuilder;
     159: ldc           #23                 // String ,
     161: invokevirtual #19                 // Method java/lang/StringBuilder.append:(Ljava/lang/String;)Ljava/lang/StringBuilder;
     164: invokevirtual #24                 // Method java/lang/StringBuilder.toString:()Ljava/lang/String;
     167: invokevirtual #19                 // Method java/lang/StringBuilder.append:(Ljava/lang/String;)Ljava/lang/StringBuilder;
     170: pop
     171: aload_0
     172: invokevirtual #31                 // Method getOutputArtifactDetails:()Lcom/amazonaws/services/codepipeline/model/ArtifactDetails;
     175: ifnull        205
     178: aload_1
     179: new           #16                 // class java/lang/StringBuilder
     182: dup
     183: invokespecial #17                 // Method java/lang/StringBuilder."<init>":()V
     186: ldc           #32                 // String OutputArtifactDetails:
     188: invokevirtual #19                 // Method java/lang/StringBuilder.append:(Ljava/lang/String;)Ljava/lang/StringBuilder;
     191: aload_0
     192: invokevirtual #31                 // Method getOutputArtifactDetails:()Lcom/amazonaws/services/codepipeline/model/ArtifactDetails;
     195: invokevirtual #22                 // Method java/lang/StringBuilder.append:(Ljava/lang/Object;)Ljava/lang/StringBuilder;
     198: invokevirtual #24                 // Method java/lang/StringBuilder.toString:()Ljava/lang/String;
     201: invokevirtual #19                 // Method java/lang/StringBuilder.append:(Ljava/lang/String;)Ljava/lang/StringBuilder;
     204: pop
     205: aload_1
     206: ldc           #33                 // String }
     208: invokevirtual #19                 // Method java/lang/StringBuilder.append:(Ljava/lang/String;)Ljava/lang/StringBuilder;
     211: pop
     212: aload_1
     213: invokevirtual #24                 // Method java/lang/StringBuilder.toString:()Ljava/lang/String;
     216: areturn

  public boolean equals(java.lang.Object);
    Code:
       0: aload_0
       1: aload_1
       2: if_acmpne     7
       5: iconst_1
       6: ireturn
       7: aload_1
       8: ifnonnull     13
      11: iconst_0
      12: ireturn
      13: aload_1
      14: instanceof    #34                 // class com/amazonaws/services/codepipeline/model/ActionType
      17: ifne          22
      20: iconst_0
      21: ireturn
      22: aload_1
      23: checkcast     #34                 // class com/amazonaws/services/codepipeline/model/ActionType
      26: astore_2
      27: aload_2
      28: invokevirtual #20                 // Method getId:()Lcom/amazonaws/services/codepipeline/model/ActionTypeId;
      31: ifnonnull     38
      34: iconst_1
      35: goto          39
      38: iconst_0
      39: aload_0
      40: invokevirtual #20                 // Method getId:()Lcom/amazonaws/services/codepipeline/model/ActionTypeId;
      43: ifnonnull     50
      46: iconst_1
      47: goto          51
      50: iconst_0
      51: ixor
      52: ifeq          57
      55: iconst_0
      56: ireturn
      57: aload_2
      58: invokevirtual #20                 // Method getId:()Lcom/amazonaws/services/codepipeline/model/ActionTypeId;
      61: ifnull        80
      64: aload_2
      65: invokevirtual #20                 // Method getId:()Lcom/amazonaws/services/codepipeline/model/ActionTypeId;
      68: aload_0
      69: invokevirtual #20                 // Method getId:()Lcom/amazonaws/services/codepipeline/model/ActionTypeId;
      72: invokevirtual #35                 // Method com/amazonaws/services/codepipeline/model/ActionTypeId.equals:(Ljava/lang/Object;)Z
      75: ifne          80
      78: iconst_0
      79: ireturn
      80: aload_2
      81: invokevirtual #25                 // Method getSettings:()Lcom/amazonaws/services/codepipeline/model/ActionTypeSettings;
      84: ifnonnull     91
      87: iconst_1
      88: goto          92
      91: iconst_0
      92: aload_0
      93: invokevirtual #25                 // Method getSettings:()Lcom/amazonaws/services/codepipeline/model/ActionTypeSettings;
      96: ifnonnull     103
      99: iconst_1
     100: goto          104
     103: iconst_0
     104: ixor
     105: ifeq          110
     108: iconst_0
     109: ireturn
     110: aload_2
     111: invokevirtual #25                 // Method getSettings:()Lcom/amazonaws/services/codepipeline/model/ActionTypeSettings;
     114: ifnull        133
     117: aload_2
     118: invokevirtual #25                 // Method getSettings:()Lcom/amazonaws/services/codepipeline/model/ActionTypeSettings;
     121: aload_0
     122: invokevirtual #25                 // Method getSettings:()Lcom/amazonaws/services/codepipeline/model/ActionTypeSettings;
     125: invokevirtual #36                 // Method com/amazonaws/services/codepipeline/model/ActionTypeSettings.equals:(Ljava/lang/Object;)Z
     128: ifne          133
     131: iconst_0
     132: ireturn
     133: aload_2
     134: invokevirtual #27                 // Method getActionConfigurationProperties:()Ljava/util/List;
     137: ifnonnull     144
     140: iconst_1
     141: goto          145
     144: iconst_0
     145: aload_0
     146: invokevirtual #27                 // Method getActionConfigurationProperties:()Ljava/util/List;
     149: ifnonnull     156
     152: iconst_1
     153: goto          157
     156: iconst_0
     157: ixor
     158: ifeq          163
     161: iconst_0
     162: ireturn
     163: aload_2
     164: invokevirtual #27                 // Method getActionConfigurationProperties:()Ljava/util/List;
     167: ifnull        188
     170: aload_2
     171: invokevirtual #27                 // Method getActionConfigurationProperties:()Ljava/util/List;
     174: aload_0
     175: invokevirtual #27                 // Method getActionConfigurationProperties:()Ljava/util/List;
     178: invokeinterface #37,  2           // InterfaceMethod java/util/List.equals:(Ljava/lang/Object;)Z
     183: ifne          188
     186: iconst_0
     187: ireturn
     188: aload_2
     189: invokevirtual #29                 // Method getInputArtifactDetails:()Lcom/amazonaws/services/codepipeline/model/ArtifactDetails;
     192: ifnonnull     199
     195: iconst_1
     196: goto          200
     199: iconst_0
     200: aload_0
     201: invokevirtual #29                 // Method getInputArtifactDetails:()Lcom/amazonaws/services/codepipeline/model/ArtifactDetails;
     204: ifnonnull     211
     207: iconst_1
     208: goto          212
     211: iconst_0
     212: ixor
     213: ifeq          218
     216: iconst_0
     217: ireturn
     218: aload_2
     219: invokevirtual #29                 // Method getInputArtifactDetails:()Lcom/amazonaws/services/codepipeline/model/ArtifactDetails;
     222: ifnull        241
     225: aload_2
     226: invokevirtual #29                 // Method getInputArtifactDetails:()Lcom/amazonaws/services/codepipeline/model/ArtifactDetails;
     229: aload_0
     230: invokevirtual #29                 // Method getInputArtifactDetails:()Lcom/amazonaws/services/codepipeline/model/ArtifactDetails;
     233: invokevirtual #38                 // Method com/amazonaws/services/codepipeline/model/ArtifactDetails.equals:(Ljava/lang/Object;)Z
     236: ifne          241
     239: iconst_0
     240: ireturn
     241: aload_2
     242: invokevirtual #31                 // Method getOutputArtifactDetails:()Lcom/amazonaws/services/codepipeline/model/ArtifactDetails;
     245: ifnonnull     252
     248: iconst_1
     249: goto          253
     252: iconst_0
     253: aload_0
     254: invokevirtual #31                 // Method getOutputArtifactDetails:()Lcom/amazonaws/services/codepipeline/model/ArtifactDetails;
     257: ifnonnull     264
     260: iconst_1
     261: goto          265
     264: iconst_0
     265: ixor
     266: ifeq          271
     269: iconst_0
     270: ireturn
     271: aload_2
     272: invokevirtual #31                 // Method getOutputArtifactDetails:()Lcom/amazonaws/services/codepipeline/model/ArtifactDetails;
     275: ifnull        294
     278: aload_2
     279: invokevirtual #31                 // Method getOutputArtifactDetails:()Lcom/amazonaws/services/codepipeline/model/ArtifactDetails;
     282: aload_0
     283: invokevirtual #31                 // Method getOutputArtifactDetails:()Lcom/amazonaws/services/codepipeline/model/ArtifactDetails;
     286: invokevirtual #38                 // Method com/amazonaws/services/codepipeline/model/ArtifactDetails.equals:(Ljava/lang/Object;)Z
     289: ifne          294
     292: iconst_0
     293: ireturn
     294: iconst_1
     295: ireturn

  public int hashCode();
    Code:
       0: bipush        31
       2: istore_1
       3: iconst_1
       4: istore_2
       5: bipush        31
       7: iload_2
       8: imul
       9: aload_0
      10: invokevirtual #20                 // Method getId:()Lcom/amazonaws/services/codepipeline/model/ActionTypeId;
      13: ifnonnull     20
      16: iconst_0
      17: goto          27
      20: aload_0
      21: invokevirtual #20                 // Method getId:()Lcom/amazonaws/services/codepipeline/model/ActionTypeId;
      24: invokevirtual #39                 // Method com/amazonaws/services/codepipeline/model/ActionTypeId.hashCode:()I
      27: iadd
      28: istore_2
      29: bipush        31
      31: iload_2
      32: imul
      33: aload_0
      34: invokevirtual #25                 // Method getSettings:()Lcom/amazonaws/services/codepipeline/model/ActionTypeSettings;
      37: ifnonnull     44
      40: iconst_0
      41: goto          51
      44: aload_0
      45: invokevirtual #25                 // Method getSettings:()Lcom/amazonaws/services/codepipeline/model/ActionTypeSettings;
      48: invokevirtual #40                 // Method com/amazonaws/services/codepipeline/model/ActionTypeSettings.hashCode:()I
      51: iadd
      52: istore_2
      53: bipush        31
      55: iload_2
      56: imul
      57: aload_0
      58: invokevirtual #27                 // Method getActionConfigurationProperties:()Ljava/util/List;
      61: ifnonnull     68
      64: iconst_0
      65: goto          77
      68: aload_0
      69: invokevirtual #27                 // Method getActionConfigurationProperties:()Ljava/util/List;
      72: invokeinterface #41,  1           // InterfaceMethod java/util/List.hashCode:()I
      77: iadd
      78: istore_2
      79: bipush        31
      81: iload_2
      82: imul
      83: aload_0
      84: invokevirtual #29                 // Method getInputArtifactDetails:()Lcom/amazonaws/services/codepipeline/model/ArtifactDetails;
      87: ifnonnull     94
      90: iconst_0
      91: goto          101
      94: aload_0
      95: invokevirtual #29                 // Method getInputArtifactDetails:()Lcom/amazonaws/services/codepipeline/model/ArtifactDetails;
      98: invokevirtual #42                 // Method com/amazonaws/services/codepipeline/model/ArtifactDetails.hashCode:()I
     101: iadd
     102: istore_2
     103: bipush        31
     105: iload_2
     106: imul
     107: aload_0
     108: invokevirtual #31                 // Method getOutputArtifactDetails:()Lcom/amazonaws/services/codepipeline/model/ArtifactDetails;
     111: ifnonnull     118
     114: iconst_0
     115: goto          125
     118: aload_0
     119: invokevirtual #31                 // Method getOutputArtifactDetails:()Lcom/amazonaws/services/codepipeline/model/ArtifactDetails;
     122: invokevirtual #42                 // Method com/amazonaws/services/codepipeline/model/ArtifactDetails.hashCode:()I
     125: iadd
     126: istore_2
     127: iload_2
     128: ireturn

  public com.amazonaws.services.codepipeline.model.ActionType clone();
    Code:
       0: aload_0
       1: invokespecial #43                 // Method java/lang/Object.clone:()Ljava/lang/Object;
       4: checkcast     #34                 // class com/amazonaws/services/codepipeline/model/ActionType
       7: areturn
       8: astore_1
       9: new           #45                 // class java/lang/IllegalStateException
      12: dup
      13: ldc           #46                 // String Got a CloneNotSupportedException from Object.clone() even though we\'re Cloneable!
      15: aload_1
      16: invokespecial #47                 // Method java/lang/IllegalStateException."<init>":(Ljava/lang/String;Ljava/lang/Throwable;)V
      19: athrow
    Exception table:
       from    to  target type
           0     7     8   Class java/lang/CloneNotSupportedException

  public java.lang.Object clone() throws java.lang.CloneNotSupportedException;
    Code:
       0: aload_0
       1: invokevirtual #48                 // Method clone:()Lcom/amazonaws/services/codepipeline/model/ActionType;
       4: areturn
}
