Compiled from "AuthenticationTestBase.java"
class io.undertow.server.security.AuthenticationTestBase$1$1 implements io.undertow.security.idm.Account {
  final java.security.Principal val$p;

  final io.undertow.server.security.AuthenticationTestBase$1 this$0;

  io.undertow.server.security.AuthenticationTestBase$1$1(io.undertow.server.security.AuthenticationTestBase$1, java.security.Principal);
    Code:
       0: aload_0
       1: aload_1
       2: putfield      #1                  // Field this$0:Lio/undertow/server/security/AuthenticationTestBase$1;
       5: aload_0
       6: aload_2
       7: putfield      #2                  // Field val$p:Ljava/security/Principal;
      10: aload_0
      11: invokespecial #3                  // Method java/lang/Object."<init>":()V
      14: return

  public java.security.Principal getPrincipal();
    Code:
       0: aload_0
       1: getfield      #2                  // Field val$p:Ljava/security/Principal;
       4: areturn

  public java.util.Set<java.lang.String> getRoles();
    Code:
       0: invokestatic  #4                  // Method java/util/Collections.emptySet:()Ljava/util/Set;
       3: areturn
}
