Compiled from "BuilderOp.java"
class org.apache.jena.sparql.sse.builders.BuilderOp$8 implements org.apache.jena.sparql.sse.builders.BuilderOp$Build {
  final org.apache.jena.sparql.sse.builders.BuilderOp this$0;

  org.apache.jena.sparql.sse.builders.BuilderOp$8(org.apache.jena.sparql.sse.builders.BuilderOp);
    Code:
       0: aload_0
       1: aload_1
       2: putfield      #1                  // Field this$0:Lorg/apache/jena/sparql/sse/builders/BuilderOp;
       5: aload_0
       6: invokespecial #2                  // Method java/lang/Object."<init>":()V
       9: return

  public org.apache.jena.sparql.algebra.Op make(org.apache.jena.sparql.sse.ItemList);
    Code:
       0: iconst_3
       1: aload_1
       2: ldc           #3                  // String Malformed filter
       4: invokestatic  #4                  // Method org/apache/jena/sparql/sse/builders/BuilderLib.checkLength:(ILorg/apache/jena/sparql/sse/ItemList;Ljava/lang/String;)V
       7: aload_1
       8: iconst_1
       9: invokevirtual #5                  // Method org/apache/jena/sparql/sse/ItemList.get:(I)Lorg/apache/jena/sparql/sse/Item;
      12: astore_2
      13: aload_1
      14: iconst_2
      15: invokevirtual #5                  // Method org/apache/jena/sparql/sse/ItemList.get:(I)Lorg/apache/jena/sparql/sse/Item;
      18: astore_3
      19: aload_0
      20: getfield      #1                  // Field this$0:Lorg/apache/jena/sparql/sse/builders/BuilderOp;
      23: aload_3
      24: invokevirtual #6                  // Method org/apache/jena/sparql/sse/Item.getList:()Lorg/apache/jena/sparql/sse/ItemList;
      27: invokestatic  #7                  // Method org/apache/jena/sparql/sse/builders/BuilderOp.access$100:(Lorg/apache/jena/sparql/sse/builders/BuilderOp;Lorg/apache/jena/sparql/sse/ItemList;)Lorg/apache/jena/sparql/algebra/Op;
      30: astore        4
      32: aload_2
      33: invokestatic  #8                  // Method org/apache/jena/sparql/sse/builders/BuilderExpr.buildExprOrExprList:(Lorg/apache/jena/sparql/sse/Item;)Lorg/apache/jena/sparql/expr/ExprList;
      36: astore        5
      38: aload         5
      40: aload         4
      42: invokestatic  #9                  // Method org/apache/jena/sparql/algebra/op/OpFilter.filterDirect:(Lorg/apache/jena/sparql/expr/ExprList;Lorg/apache/jena/sparql/algebra/Op;)Lorg/apache/jena/sparql/algebra/op/OpFilter;
      45: areturn
}
