Compiled from "BuilderOp.java"
class org.apache.jena.sparql.sse.builders.BuilderOp$31 implements org.apache.jena.sparql.sse.builders.BuilderOp$Build {
  final org.apache.jena.sparql.sse.builders.BuilderOp this$0;

  org.apache.jena.sparql.sse.builders.BuilderOp$31(org.apache.jena.sparql.sse.builders.BuilderOp);
    Code:
       0: aload_0
       1: aload_1
       2: putfield      #1                  // Field this$0:Lorg/apache/jena/sparql/sse/builders/BuilderOp;
       5: aload_0
       6: invokespecial #2                  // Method java/lang/Object."<init>":()V
       9: return

  public org.apache.jena.sparql.algebra.Op make(org.apache.jena.sparql.sse.ItemList);
    Code:
       0: iconst_4
       1: aload_1
       2: ldc           #3                  // String slice
       4: invokestatic  #4                  // Method org/apache/jena/sparql/sse/builders/BuilderLib.checkLength:(ILorg/apache/jena/sparql/sse/ItemList;Ljava/lang/String;)V
       7: aload_1
       8: iconst_1
       9: iconst_m1
      10: invokestatic  #5                  // Method org/apache/jena/sparql/sse/builders/BuilderNode.buildLong:(Lorg/apache/jena/sparql/sse/ItemList;II)J
      13: lstore_2
      14: aload_1
      15: iconst_2
      16: iconst_m1
      17: invokestatic  #5                  // Method org/apache/jena/sparql/sse/builders/BuilderNode.buildLong:(Lorg/apache/jena/sparql/sse/ItemList;II)J
      20: lstore        4
      22: lload_2
      23: ldc2_w        #6                  // long -1l
      26: lcmp
      27: ifne          34
      30: ldc2_w        #9                  // long -9223372036854775808l
      33: lstore_2
      34: lload         4
      36: ldc2_w        #6                  // long -1l
      39: lcmp
      40: ifne          48
      43: ldc2_w        #9                  // long -9223372036854775808l
      46: lstore        4
      48: aload_0
      49: getfield      #1                  // Field this$0:Lorg/apache/jena/sparql/sse/builders/BuilderOp;
      52: aload_1
      53: iconst_3
      54: invokevirtual #11                 // Method org/apache/jena/sparql/sse/builders/BuilderOp.build:(Lorg/apache/jena/sparql/sse/ItemList;I)Lorg/apache/jena/sparql/algebra/Op;
      57: astore        6
      59: new           #12                 // class org/apache/jena/sparql/algebra/op/OpSlice
      62: dup
      63: aload         6
      65: lload_2
      66: lload         4
      68: invokespecial #13                 // Method org/apache/jena/sparql/algebra/op/OpSlice."<init>":(Lorg/apache/jena/sparql/algebra/Op;JJ)V
      71: areturn
}
