Compiled from "BuilderPath.java"
class org.apache.jena.sparql.sse.builders.BuilderPath$2 implements org.apache.jena.sparql.sse.builders.BuilderPath$Build {
  final org.apache.jena.sparql.sse.builders.BuilderPath this$0;

  org.apache.jena.sparql.sse.builders.BuilderPath$2(org.apache.jena.sparql.sse.builders.BuilderPath);
    Code:
       0: aload_0
       1: aload_1
       2: putfield      #1                  // Field this$0:Lorg/apache/jena/sparql/sse/builders/BuilderPath;
       5: aload_0
       6: invokespecial #2                  // Method java/lang/Object."<init>":()V
       9: return

  public org.apache.jena.sparql.path.Path make(org.apache.jena.sparql.sse.ItemList);
    Code:
       0: iconst_1
       1: aload_1
       2: ldc           #3                  // String path: negative property set: must be at least one element
       4: invokestatic  #4                  // Method org/apache/jena/sparql/sse/builders/BuilderLib.checkLengthAtLeast:(ILorg/apache/jena/sparql/sse/ItemList;Ljava/lang/String;)V
       7: new           #5                  // class org/apache/jena/sparql/path/P_NegPropSet
      10: dup
      11: invokespecial #6                  // Method org/apache/jena/sparql/path/P_NegPropSet."<init>":()V
      14: astore_2
      15: iconst_1
      16: istore_3
      17: iload_3
      18: aload_1
      19: invokevirtual #7                  // Method org/apache/jena/sparql/sse/ItemList.size:()I
      22: if_icmpge     73
      25: aload_1
      26: iload_3
      27: invokevirtual #8                  // Method org/apache/jena/sparql/sse/ItemList.get:(I)Lorg/apache/jena/sparql/sse/Item;
      30: astore        4
      32: aload_0
      33: getfield      #1                  // Field this$0:Lorg/apache/jena/sparql/sse/builders/BuilderPath;
      36: aload         4
      38: invokestatic  #9                  // Method org/apache/jena/sparql/sse/builders/BuilderPath.access$000:(Lorg/apache/jena/sparql/sse/builders/BuilderPath;Lorg/apache/jena/sparql/sse/Item;)Lorg/apache/jena/sparql/path/Path;
      41: astore        5
      43: aload         5
      45: instanceof    #10                 // class org/apache/jena/sparql/path/P_Path0
      48: ifne          58
      51: aload         4
      53: ldc           #11                 // String Not a property or reverse property
      55: invokestatic  #12                 // Method org/apache/jena/sparql/sse/builders/BuilderLib.broken:(Lorg/apache/jena/sparql/sse/Item;Ljava/lang/String;)V
      58: aload_2
      59: aload         5
      61: checkcast     #10                 // class org/apache/jena/sparql/path/P_Path0
      64: invokevirtual #13                 // Method org/apache/jena/sparql/path/P_NegPropSet.add:(Lorg/apache/jena/sparql/path/P_Path0;)V
      67: iinc          3, 1
      70: goto          17
      73: aload_2
      74: areturn
}
