Compiled from "Messages.java"
public final class org.jboss.logging.Messages {
  private org.jboss.logging.Messages();
    Code:
       0: aload_0
       1: invokespecial #2                  // Method java/lang/Object."<init>":()V
       4: return

  public static <T> T getBundle(java.lang.Class<T>);
    Code:
       0: aload_0
       1: invokestatic  #3                  // Method org/jboss/logging/LoggingLocale.getLocale:()Ljava/util/Locale;
       4: invokestatic  #4                  // Method getBundle:(Ljava/lang/Class;Ljava/util/Locale;)Ljava/lang/Object;
       7: areturn

  public static <T> T getBundle(java.lang.Class<T>, java.util.Locale);
    Code:
       0: invokestatic  #5                  // Method java/lang/System.getSecurityManager:()Ljava/lang/SecurityManager;
       3: ifnonnull     12
       6: aload_0
       7: aload_1
       8: invokestatic  #1                  // Method doGetBundle:(Ljava/lang/Class;Ljava/util/Locale;)Ljava/lang/Object;
      11: areturn
      12: new           #6                  // class org/jboss/logging/Messages$1
      15: dup
      16: aload_0
      17: aload_1
      18: invokespecial #7                  // Method org/jboss/logging/Messages$1."<init>":(Ljava/lang/Class;Ljava/util/Locale;)V
      21: invokestatic  #8                  // Method java/security/AccessController.doPrivileged:(Ljava/security/PrivilegedAction;)Ljava/lang/Object;
      24: areturn

  private static <T> T doGetBundle(java.lang.Class<T>, java.util.Locale);
    Code:
       0: aload_1
       1: invokevirtual #9                  // Method java/util/Locale.getLanguage:()Ljava/lang/String;
       4: astore_2
       5: aload_1
       6: invokevirtual #10                 // Method java/util/Locale.getCountry:()Ljava/lang/String;
       9: astore_3
      10: aload_1
      11: invokevirtual #11                 // Method java/util/Locale.getVariant:()Ljava/lang/String;
      14: astore        4
      16: aconst_null
      17: astore        5
      19: aload         4
      21: ifnull        64
      24: aload         4
      26: invokevirtual #12                 // Method java/lang/String.length:()I
      29: ifle          64
      32: aload_0
      33: invokevirtual #13                 // Method java/lang/Class.getName:()Ljava/lang/String;
      36: ldc           #14                 // String $bundle
      38: aload_2
      39: aload_3
      40: aload         4
      42: invokestatic  #15                 // Method join:(Ljava/lang/String;Ljava/lang/String;Ljava/lang/String;Ljava/lang/String;Ljava/lang/String;)Ljava/lang/String;
      45: iconst_1
      46: aload_0
      47: invokevirtual #16                 // Method java/lang/Class.getClassLoader:()Ljava/lang/ClassLoader;
      50: invokestatic  #17                 // Method java/lang/Class.forName:(Ljava/lang/String;ZLjava/lang/ClassLoader;)Ljava/lang/Class;
      53: aload_0
      54: invokevirtual #18                 // Method java/lang/Class.asSubclass:(Ljava/lang/Class;)Ljava/lang/Class;
      57: astore        5
      59: goto          64
      62: astore        6
      64: aload         5
      66: ifnonnull     111
      69: aload_3
      70: ifnull        111
      73: aload_3
      74: invokevirtual #12                 // Method java/lang/String.length:()I
      77: ifle          111
      80: aload_0
      81: invokevirtual #13                 // Method java/lang/Class.getName:()Ljava/lang/String;
      84: ldc           #14                 // String $bundle
      86: aload_2
      87: aload_3
      88: aconst_null
      89: invokestatic  #15                 // Method join:(Ljava/lang/String;Ljava/lang/String;Ljava/lang/String;Ljava/lang/String;Ljava/lang/String;)Ljava/lang/String;
      92: iconst_1
      93: aload_0
      94: invokevirtual #16                 // Method java/lang/Class.getClassLoader:()Ljava/lang/ClassLoader;
      97: invokestatic  #17                 // Method java/lang/Class.forName:(Ljava/lang/String;ZLjava/lang/ClassLoader;)Ljava/lang/Class;
     100: aload_0
     101: invokevirtual #18                 // Method java/lang/Class.asSubclass:(Ljava/lang/Class;)Ljava/lang/Class;
     104: astore        5
     106: goto          111
     109: astore        6
     111: aload         5
     113: ifnonnull     158
     116: aload_2
     117: ifnull        158
     120: aload_2
     121: invokevirtual #12                 // Method java/lang/String.length:()I
     124: ifle          158
     127: aload_0
     128: invokevirtual #13                 // Method java/lang/Class.getName:()Ljava/lang/String;
     131: ldc           #14                 // String $bundle
     133: aload_2
     134: aconst_null
     135: aconst_null
     136: invokestatic  #15                 // Method join:(Ljava/lang/String;Ljava/lang/String;Ljava/lang/String;Ljava/lang/String;Ljava/lang/String;)Ljava/lang/String;
     139: iconst_1
     140: aload_0
     141: invokevirtual #16                 // Method java/lang/Class.getClassLoader:()Ljava/lang/ClassLoader;
     144: invokestatic  #17                 // Method java/lang/Class.forName:(Ljava/lang/String;ZLjava/lang/ClassLoader;)Ljava/lang/Class;
     147: aload_0
     148: invokevirtual #18                 // Method java/lang/Class.asSubclass:(Ljava/lang/Class;)Ljava/lang/Class;
     151: astore        5
     153: goto          158
     156: astore        6
     158: aload         5
     160: ifnonnull     226
     163: aload_0
     164: invokevirtual #13                 // Method java/lang/Class.getName:()Ljava/lang/String;
     167: ldc           #14                 // String $bundle
     169: aconst_null
     170: aconst_null
     171: aconst_null
     172: invokestatic  #15                 // Method join:(Ljava/lang/String;Ljava/lang/String;Ljava/lang/String;Ljava/lang/String;Ljava/lang/String;)Ljava/lang/String;
     175: iconst_1
     176: aload_0
     177: invokevirtual #16                 // Method java/lang/Class.getClassLoader:()Ljava/lang/ClassLoader;
     180: invokestatic  #17                 // Method java/lang/Class.forName:(Ljava/lang/String;ZLjava/lang/ClassLoader;)Ljava/lang/Class;
     183: aload_0
     184: invokevirtual #18                 // Method java/lang/Class.asSubclass:(Ljava/lang/Class;)Ljava/lang/Class;
     187: astore        5
     189: goto          226
     192: astore        6
     194: new           #20                 // class java/lang/IllegalArgumentException
     197: dup
     198: new           #21                 // class java/lang/StringBuilder
     201: dup
     202: invokespecial #22                 // Method java/lang/StringBuilder."<init>":()V
     205: ldc           #23                 // String Invalid bundle
     207: invokevirtual #24                 // Method java/lang/StringBuilder.append:(Ljava/lang/String;)Ljava/lang/StringBuilder;
     210: aload_0
     211: invokevirtual #25                 // Method java/lang/StringBuilder.append:(Ljava/lang/Object;)Ljava/lang/StringBuilder;
     214: ldc           #26                 // String  (implementation not found)
     216: invokevirtual #24                 // Method java/lang/StringBuilder.append:(Ljava/lang/String;)Ljava/lang/StringBuilder;
     219: invokevirtual #27                 // Method java/lang/StringBuilder.toString:()Ljava/lang/String;
     222: invokespecial #28                 // Method java/lang/IllegalArgumentException."<init>":(Ljava/lang/String;)V
     225: athrow
     226: aload         5
     228: ldc           #29                 // String INSTANCE
     230: invokevirtual #30                 // Method java/lang/Class.getField:(Ljava/lang/String;)Ljava/lang/reflect/Field;
     233: astore        6
     235: goto          273
     238: astore        7
     240: new           #20                 // class java/lang/IllegalArgumentException
     243: dup
     244: new           #21                 // class java/lang/StringBuilder
     247: dup
     248: invokespecial #22                 // Method java/lang/StringBuilder."<init>":()V
     251: ldc           #32                 // String Bundle implementation
     253: invokevirtual #24                 // Method java/lang/StringBuilder.append:(Ljava/lang/String;)Ljava/lang/StringBuilder;
     256: aload         5
     258: invokevirtual #25                 // Method java/lang/StringBuilder.append:(Ljava/lang/Object;)Ljava/lang/StringBuilder;
     261: ldc           #33                 // String  has no instance field
     263: invokevirtual #24                 // Method java/lang/StringBuilder.append:(Ljava/lang/String;)Ljava/lang/StringBuilder;
     266: invokevirtual #27                 // Method java/lang/StringBuilder.toString:()Ljava/lang/String;
     269: invokespecial #28                 // Method java/lang/IllegalArgumentException."<init>":(Ljava/lang/String;)V
     272: athrow
     273: aload_0
     274: aload         6
     276: aconst_null
     277: invokevirtual #34                 // Method java/lang/reflect/Field.get:(Ljava/lang/Object;)Ljava/lang/Object;
     280: invokevirtual #35                 // Method java/lang/Class.cast:(Ljava/lang/Object;)Ljava/lang/Object;
     283: areturn
     284: astore        7
     286: new           #20                 // class java/lang/IllegalArgumentException
     289: dup
     290: new           #21                 // class java/lang/StringBuilder
     293: dup
     294: invokespecial #22                 // Method java/lang/StringBuilder."<init>":()V
     297: ldc           #32                 // String Bundle implementation
     299: invokevirtual #24                 // Method java/lang/StringBuilder.append:(Ljava/lang/String;)Ljava/lang/StringBuilder;
     302: aload         5
     304: invokevirtual #25                 // Method java/lang/StringBuilder.append:(Ljava/lang/Object;)Ljava/lang/StringBuilder;
     307: ldc           #37                 // String  could not be instantiated
     309: invokevirtual #24                 // Method java/lang/StringBuilder.append:(Ljava/lang/String;)Ljava/lang/StringBuilder;
     312: invokevirtual #27                 // Method java/lang/StringBuilder.toString:()Ljava/lang/String;
     315: aload         7
     317: invokespecial #38                 // Method java/lang/IllegalArgumentException."<init>":(Ljava/lang/String;Ljava/lang/Throwable;)V
     320: athrow
    Exception table:
       from    to  target type
          32    59    62   Class java/lang/ClassNotFoundException
          80   106   109   Class java/lang/ClassNotFoundException
         127   153   156   Class java/lang/ClassNotFoundException
         163   189   192   Class java/lang/ClassNotFoundException
         226   235   238   Class java/lang/NoSuchFieldException
         273   283   284   Class java/lang/IllegalAccessException

  private static java.lang.String join(java.lang.String, java.lang.String, java.lang.String, java.lang.String, java.lang.String);
    Code:
       0: new           #21                 // class java/lang/StringBuilder
       3: dup
       4: invokespecial #22                 // Method java/lang/StringBuilder."<init>":()V
       7: astore        5
       9: aload         5
      11: aload_0
      12: invokevirtual #24                 // Method java/lang/StringBuilder.append:(Ljava/lang/String;)Ljava/lang/StringBuilder;
      15: bipush        95
      17: invokevirtual #39                 // Method java/lang/StringBuilder.append:(C)Ljava/lang/StringBuilder;
      20: aload_1
      21: invokevirtual #24                 // Method java/lang/StringBuilder.append:(Ljava/lang/String;)Ljava/lang/StringBuilder;
      24: pop
      25: aload_2
      26: ifnull        51
      29: aload_2
      30: invokevirtual #12                 // Method java/lang/String.length:()I
      33: ifle          51
      36: aload         5
      38: bipush        95
      40: invokevirtual #39                 // Method java/lang/StringBuilder.append:(C)Ljava/lang/StringBuilder;
      43: pop
      44: aload         5
      46: aload_2
      47: invokevirtual #24                 // Method java/lang/StringBuilder.append:(Ljava/lang/String;)Ljava/lang/StringBuilder;
      50: pop
      51: aload_3
      52: ifnull        77
      55: aload_3
      56: invokevirtual #12                 // Method java/lang/String.length:()I
      59: ifle          77
      62: aload         5
      64: bipush        95
      66: invokevirtual #39                 // Method java/lang/StringBuilder.append:(C)Ljava/lang/StringBuilder;
      69: pop
      70: aload         5
      72: aload_3
      73: invokevirtual #24                 // Method java/lang/StringBuilder.append:(Ljava/lang/String;)Ljava/lang/StringBuilder;
      76: pop
      77: aload         4
      79: ifnull        106
      82: aload         4
      84: invokevirtual #12                 // Method java/lang/String.length:()I
      87: ifle          106
      90: aload         5
      92: bipush        95
      94: invokevirtual #39                 // Method java/lang/StringBuilder.append:(C)Ljava/lang/StringBuilder;
      97: pop
      98: aload         5
     100: aload         4
     102: invokevirtual #24                 // Method java/lang/StringBuilder.append:(Ljava/lang/String;)Ljava/lang/StringBuilder;
     105: pop
     106: aload         5
     108: invokevirtual #27                 // Method java/lang/StringBuilder.toString:()Ljava/lang/String;
     111: areturn

  static java.lang.Object access$000(java.lang.Class, java.util.Locale);
    Code:
       0: aload_0
       1: aload_1
       2: invokestatic  #1                  // Method doGetBundle:(Ljava/lang/Class;Ljava/util/Locale;)Ljava/lang/Object;
       5: areturn
}
