Compiled from "BuildTriggerCauseFluentImpl.java"
public class io.fabric8.openshift.api.model.BuildTriggerCauseFluentImpl$BitbucketWebHookNestedImpl<N> extends io.fabric8.openshift.api.model.BitbucketWebHookCauseFluentImpl<io.fabric8.openshift.api.model.BuildTriggerCauseFluent$BitbucketWebHookNested<N>> implements io.fabric8.openshift.api.model.BuildTriggerCauseFluent$BitbucketWebHookNested<N>, io.fabric8.kubernetes.api.builder.Nested<N> {
  private final io.fabric8.openshift.api.model.BitbucketWebHookCauseBuilder builder;

  final io.fabric8.openshift.api.model.BuildTriggerCauseFluentImpl this$0;

  io.fabric8.openshift.api.model.BuildTriggerCauseFluentImpl$BitbucketWebHookNestedImpl(io.fabric8.openshift.api.model.BuildTriggerCauseFluentImpl, io.fabric8.openshift.api.model.BitbucketWebHookCause);
    Code:
       0: aload_0
       1: aload_1
       2: putfield      #1                  // Field this$0:Lio/fabric8/openshift/api/model/BuildTriggerCauseFluentImpl;
       5: aload_0
       6: invokespecial #2                  // Method io/fabric8/openshift/api/model/BitbucketWebHookCauseFluentImpl."<init>":()V
       9: aload_0
      10: new           #3                  // class io/fabric8/openshift/api/model/BitbucketWebHookCauseBuilder
      13: dup
      14: aload_0
      15: aload_2
      16: invokespecial #4                  // Method io/fabric8/openshift/api/model/BitbucketWebHookCauseBuilder."<init>":(Lio/fabric8/openshift/api/model/BitbucketWebHookCauseFluent;Lio/fabric8/openshift/api/model/BitbucketWebHookCause;)V
      19: putfield      #5                  // Field builder:Lio/fabric8/openshift/api/model/BitbucketWebHookCauseBuilder;
      22: return

  io.fabric8.openshift.api.model.BuildTriggerCauseFluentImpl$BitbucketWebHookNestedImpl(io.fabric8.openshift.api.model.BuildTriggerCauseFluentImpl);
    Code:
       0: aload_0
       1: aload_1
       2: putfield      #1                  // Field this$0:Lio/fabric8/openshift/api/model/BuildTriggerCauseFluentImpl;
       5: aload_0
       6: invokespecial #2                  // Method io/fabric8/openshift/api/model/BitbucketWebHookCauseFluentImpl."<init>":()V
       9: aload_0
      10: new           #3                  // class io/fabric8/openshift/api/model/BitbucketWebHookCauseBuilder
      13: dup
      14: aload_0
      15: invokespecial #6                  // Method io/fabric8/openshift/api/model/BitbucketWebHookCauseBuilder."<init>":(Lio/fabric8/openshift/api/model/BitbucketWebHookCauseFluent;)V
      18: putfield      #5                  // Field builder:Lio/fabric8/openshift/api/model/BitbucketWebHookCauseBuilder;
      21: return

  public N and();
    Code:
       0: aload_0
       1: getfield      #1                  // Field this$0:Lio/fabric8/openshift/api/model/BuildTriggerCauseFluentImpl;
       4: aload_0
       5: getfield      #5                  // Field builder:Lio/fabric8/openshift/api/model/BitbucketWebHookCauseBuilder;
       8: invokevirtual #7                  // Method io/fabric8/openshift/api/model/BitbucketWebHookCauseBuilder.build:()Lio/fabric8/openshift/api/model/BitbucketWebHookCause;
      11: invokevirtual #8                  // Method io/fabric8/openshift/api/model/BuildTriggerCauseFluentImpl.withBitbucketWebHook:(Lio/fabric8/openshift/api/model/BitbucketWebHookCause;)Lio/fabric8/openshift/api/model/BuildTriggerCauseFluent;
      14: areturn

  public N endBitbucketWebHook();
    Code:
       0: aload_0
       1: invokevirtual #9                  // Method and:()Ljava/lang/Object;
       4: areturn
}
