Compiled from "ClusterRoleBuilder.java"
public class io.fabric8.openshift.api.model.ClusterRoleBuilder extends io.fabric8.openshift.api.model.ClusterRoleFluentImpl<io.fabric8.openshift.api.model.ClusterRoleBuilder> implements io.fabric8.kubernetes.api.builder.VisitableBuilder<io.fabric8.openshift.api.model.ClusterRole, io.fabric8.openshift.api.model.ClusterRoleBuilder> {
  io.fabric8.openshift.api.model.ClusterRoleFluent<?> fluent;

  java.lang.Boolean validationEnabled;

  public io.fabric8.openshift.api.model.ClusterRoleBuilder();
    Code:
       0: aload_0
       1: iconst_1
       2: invokestatic  #1                  // Method java/lang/Boolean.valueOf:(Z)Ljava/lang/Boolean;
       5: invokespecial #2                  // Method "<init>":(Ljava/lang/Boolean;)V
       8: return

  public io.fabric8.openshift.api.model.ClusterRoleBuilder(java.lang.Boolean);
    Code:
       0: aload_0
       1: new           #3                  // class io/fabric8/openshift/api/model/ClusterRole
       4: dup
       5: invokespecial #4                  // Method io/fabric8/openshift/api/model/ClusterRole."<init>":()V
       8: aload_1
       9: invokespecial #5                  // Method "<init>":(Lio/fabric8/openshift/api/model/ClusterRole;Ljava/lang/Boolean;)V
      12: return

  public io.fabric8.openshift.api.model.ClusterRoleBuilder(io.fabric8.openshift.api.model.ClusterRoleFluent<?>);
    Code:
       0: aload_0
       1: aload_1
       2: iconst_1
       3: invokestatic  #1                  // Method java/lang/Boolean.valueOf:(Z)Ljava/lang/Boolean;
       6: invokespecial #6                  // Method "<init>":(Lio/fabric8/openshift/api/model/ClusterRoleFluent;Ljava/lang/Boolean;)V
       9: return

  public io.fabric8.openshift.api.model.ClusterRoleBuilder(io.fabric8.openshift.api.model.ClusterRoleFluent<?>, java.lang.Boolean);
    Code:
       0: aload_0
       1: aload_1
       2: new           #3                  // class io/fabric8/openshift/api/model/ClusterRole
       5: dup
       6: invokespecial #4                  // Method io/fabric8/openshift/api/model/ClusterRole."<init>":()V
       9: aload_2
      10: invokespecial #7                  // Method "<init>":(Lio/fabric8/openshift/api/model/ClusterRoleFluent;Lio/fabric8/openshift/api/model/ClusterRole;Ljava/lang/Boolean;)V
      13: return

  public io.fabric8.openshift.api.model.ClusterRoleBuilder(io.fabric8.openshift.api.model.ClusterRoleFluent<?>, io.fabric8.openshift.api.model.ClusterRole);
    Code:
       0: aload_0
       1: aload_1
       2: aload_2
       3: iconst_1
       4: invokestatic  #1                  // Method java/lang/Boolean.valueOf:(Z)Ljava/lang/Boolean;
       7: invokespecial #7                  // Method "<init>":(Lio/fabric8/openshift/api/model/ClusterRoleFluent;Lio/fabric8/openshift/api/model/ClusterRole;Ljava/lang/Boolean;)V
      10: return

  public io.fabric8.openshift.api.model.ClusterRoleBuilder(io.fabric8.openshift.api.model.ClusterRoleFluent<?>, io.fabric8.openshift.api.model.ClusterRole, java.lang.Boolean);
    Code:
       0: aload_0
       1: invokespecial #8                  // Method io/fabric8/openshift/api/model/ClusterRoleFluentImpl."<init>":()V
       4: aload_0
       5: aload_1
       6: putfield      #9                  // Field fluent:Lio/fabric8/openshift/api/model/ClusterRoleFluent;
       9: aload_1
      10: aload_2
      11: invokevirtual #10                 // Method io/fabric8/openshift/api/model/ClusterRole.getAggregationRule:()Lio/fabric8/kubernetes/api/model/rbac/AggregationRule;
      14: invokeinterface #11,  2           // InterfaceMethod io/fabric8/openshift/api/model/ClusterRoleFluent.withAggregationRule:(Lio/fabric8/kubernetes/api/model/rbac/AggregationRule;)Lio/fabric8/openshift/api/model/ClusterRoleFluent;
      19: pop
      20: aload_1
      21: aload_2
      22: invokevirtual #12                 // Method io/fabric8/openshift/api/model/ClusterRole.getApiVersion:()Ljava/lang/String;
      25: invokeinterface #13,  2           // InterfaceMethod io/fabric8/openshift/api/model/ClusterRoleFluent.withApiVersion:(Ljava/lang/String;)Lio/fabric8/openshift/api/model/ClusterRoleFluent;
      30: pop
      31: aload_1
      32: aload_2
      33: invokevirtual #14                 // Method io/fabric8/openshift/api/model/ClusterRole.getKind:()Ljava/lang/String;
      36: invokeinterface #15,  2           // InterfaceMethod io/fabric8/openshift/api/model/ClusterRoleFluent.withKind:(Ljava/lang/String;)Lio/fabric8/openshift/api/model/ClusterRoleFluent;
      41: pop
      42: aload_1
      43: aload_2
      44: invokevirtual #16                 // Method io/fabric8/openshift/api/model/ClusterRole.getMetadata:()Lio/fabric8/kubernetes/api/model/ObjectMeta;
      47: invokeinterface #17,  2           // InterfaceMethod io/fabric8/openshift/api/model/ClusterRoleFluent.withMetadata:(Lio/fabric8/kubernetes/api/model/ObjectMeta;)Lio/fabric8/openshift/api/model/ClusterRoleFluent;
      52: pop
      53: aload_1
      54: aload_2
      55: invokevirtual #18                 // Method io/fabric8/openshift/api/model/ClusterRole.getRules:()Ljava/util/List;
      58: invokeinterface #19,  2           // InterfaceMethod io/fabric8/openshift/api/model/ClusterRoleFluent.withRules:(Ljava/util/List;)Lio/fabric8/openshift/api/model/ClusterRoleFluent;
      63: pop
      64: aload_0
      65: aload_3
      66: putfield      #20                 // Field validationEnabled:Ljava/lang/Boolean;
      69: return

  public io.fabric8.openshift.api.model.ClusterRoleBuilder(io.fabric8.openshift.api.model.ClusterRole);
    Code:
       0: aload_0
       1: aload_1
       2: iconst_1
       3: invokestatic  #1                  // Method java/lang/Boolean.valueOf:(Z)Ljava/lang/Boolean;
       6: invokespecial #5                  // Method "<init>":(Lio/fabric8/openshift/api/model/ClusterRole;Ljava/lang/Boolean;)V
       9: return

  public io.fabric8.openshift.api.model.ClusterRoleBuilder(io.fabric8.openshift.api.model.ClusterRole, java.lang.Boolean);
    Code:
       0: aload_0
       1: invokespecial #8                  // Method io/fabric8/openshift/api/model/ClusterRoleFluentImpl."<init>":()V
       4: aload_0
       5: aload_0
       6: putfield      #9                  // Field fluent:Lio/fabric8/openshift/api/model/ClusterRoleFluent;
       9: aload_0
      10: aload_1
      11: invokevirtual #10                 // Method io/fabric8/openshift/api/model/ClusterRole.getAggregationRule:()Lio/fabric8/kubernetes/api/model/rbac/AggregationRule;
      14: invokevirtual #21                 // Method withAggregationRule:(Lio/fabric8/kubernetes/api/model/rbac/AggregationRule;)Lio/fabric8/openshift/api/model/ClusterRoleFluent;
      17: pop
      18: aload_0
      19: aload_1
      20: invokevirtual #12                 // Method io/fabric8/openshift/api/model/ClusterRole.getApiVersion:()Ljava/lang/String;
      23: invokevirtual #22                 // Method withApiVersion:(Ljava/lang/String;)Lio/fabric8/openshift/api/model/ClusterRoleFluent;
      26: pop
      27: aload_0
      28: aload_1
      29: invokevirtual #14                 // Method io/fabric8/openshift/api/model/ClusterRole.getKind:()Ljava/lang/String;
      32: invokevirtual #23                 // Method withKind:(Ljava/lang/String;)Lio/fabric8/openshift/api/model/ClusterRoleFluent;
      35: pop
      36: aload_0
      37: aload_1
      38: invokevirtual #16                 // Method io/fabric8/openshift/api/model/ClusterRole.getMetadata:()Lio/fabric8/kubernetes/api/model/ObjectMeta;
      41: invokevirtual #24                 // Method withMetadata:(Lio/fabric8/kubernetes/api/model/ObjectMeta;)Lio/fabric8/openshift/api/model/ClusterRoleFluent;
      44: pop
      45: aload_0
      46: aload_1
      47: invokevirtual #18                 // Method io/fabric8/openshift/api/model/ClusterRole.getRules:()Ljava/util/List;
      50: invokevirtual #25                 // Method withRules:(Ljava/util/List;)Lio/fabric8/openshift/api/model/ClusterRoleFluent;
      53: pop
      54: aload_0
      55: aload_2
      56: putfield      #20                 // Field validationEnabled:Ljava/lang/Boolean;
      59: return

  public io.fabric8.openshift.api.model.ClusterRole build();
    Code:
       0: new           #3                  // class io/fabric8/openshift/api/model/ClusterRole
       3: dup
       4: aload_0
       5: getfield      #9                  // Field fluent:Lio/fabric8/openshift/api/model/ClusterRoleFluent;
       8: invokeinterface #26,  1           // InterfaceMethod io/fabric8/openshift/api/model/ClusterRoleFluent.getAggregationRule:()Lio/fabric8/kubernetes/api/model/rbac/AggregationRule;
      13: aload_0
      14: getfield      #9                  // Field fluent:Lio/fabric8/openshift/api/model/ClusterRoleFluent;
      17: invokeinterface #27,  1           // InterfaceMethod io/fabric8/openshift/api/model/ClusterRoleFluent.getApiVersion:()Ljava/lang/String;
      22: aload_0
      23: getfield      #9                  // Field fluent:Lio/fabric8/openshift/api/model/ClusterRoleFluent;
      26: invokeinterface #28,  1           // InterfaceMethod io/fabric8/openshift/api/model/ClusterRoleFluent.getKind:()Ljava/lang/String;
      31: aload_0
      32: getfield      #9                  // Field fluent:Lio/fabric8/openshift/api/model/ClusterRoleFluent;
      35: invokeinterface #29,  1           // InterfaceMethod io/fabric8/openshift/api/model/ClusterRoleFluent.getMetadata:()Lio/fabric8/kubernetes/api/model/ObjectMeta;
      40: aload_0
      41: getfield      #9                  // Field fluent:Lio/fabric8/openshift/api/model/ClusterRoleFluent;
      44: invokeinterface #30,  1           // InterfaceMethod io/fabric8/openshift/api/model/ClusterRoleFluent.getRules:()Ljava/util/List;
      49: invokespecial #31                 // Method io/fabric8/openshift/api/model/ClusterRole."<init>":(Lio/fabric8/kubernetes/api/model/rbac/AggregationRule;Ljava/lang/String;Ljava/lang/String;Lio/fabric8/kubernetes/api/model/ObjectMeta;Ljava/util/List;)V
      52: astore_1
      53: aload_1
      54: areturn

  public boolean equals(java.lang.Object);
    Code:
       0: aload_0
       1: aload_1
       2: if_acmpne     7
       5: iconst_1
       6: ireturn
       7: aload_1
       8: ifnull        22
      11: aload_0
      12: invokevirtual #32                 // Method java/lang/Object.getClass:()Ljava/lang/Class;
      15: aload_1
      16: invokevirtual #32                 // Method java/lang/Object.getClass:()Ljava/lang/Class;
      19: if_acmpeq     24
      22: iconst_0
      23: ireturn
      24: aload_0
      25: aload_1
      26: invokespecial #33                 // Method io/fabric8/openshift/api/model/ClusterRoleFluentImpl.equals:(Ljava/lang/Object;)Z
      29: ifne          34
      32: iconst_0
      33: ireturn
      34: aload_1
      35: checkcast     #34                 // class io/fabric8/openshift/api/model/ClusterRoleBuilder
      38: astore_2
      39: aload_0
      40: getfield      #9                  // Field fluent:Lio/fabric8/openshift/api/model/ClusterRoleFluent;
      43: ifnull        71
      46: aload_0
      47: getfield      #9                  // Field fluent:Lio/fabric8/openshift/api/model/ClusterRoleFluent;
      50: aload_0
      51: if_acmpeq     71
      54: aload_0
      55: getfield      #9                  // Field fluent:Lio/fabric8/openshift/api/model/ClusterRoleFluent;
      58: aload_2
      59: getfield      #9                  // Field fluent:Lio/fabric8/openshift/api/model/ClusterRoleFluent;
      62: invokevirtual #35                 // Method java/lang/Object.equals:(Ljava/lang/Object;)Z
      65: ifne          88
      68: goto          86
      71: aload_2
      72: getfield      #9                  // Field fluent:Lio/fabric8/openshift/api/model/ClusterRoleFluent;
      75: ifnull        88
      78: aload_0
      79: getfield      #9                  // Field fluent:Lio/fabric8/openshift/api/model/ClusterRoleFluent;
      82: aload_0
      83: if_acmpeq     88
      86: iconst_0
      87: ireturn
      88: aload_0
      89: getfield      #20                 // Field validationEnabled:Ljava/lang/Boolean;
      92: ifnull        112
      95: aload_0
      96: getfield      #20                 // Field validationEnabled:Ljava/lang/Boolean;
      99: aload_2
     100: getfield      #20                 // Field validationEnabled:Ljava/lang/Boolean;
     103: invokevirtual #36                 // Method java/lang/Boolean.equals:(Ljava/lang/Object;)Z
     106: ifne          121
     109: goto          119
     112: aload_2
     113: getfield      #20                 // Field validationEnabled:Ljava/lang/Boolean;
     116: ifnull        121
     119: iconst_0
     120: ireturn
     121: iconst_1
     122: ireturn

  public java.lang.Object build();
    Code:
       0: aload_0
       1: invokevirtual #37                 // Method build:()Lio/fabric8/openshift/api/model/ClusterRole;
       4: areturn
}
