Compiled from "DeploymentDetailsFluentImpl.java"
public class io.fabric8.openshift.api.model.DeploymentDetailsFluentImpl$CausesNestedImpl<N> extends io.fabric8.openshift.api.model.DeploymentCauseFluentImpl<io.fabric8.openshift.api.model.DeploymentDetailsFluent$CausesNested<N>> implements io.fabric8.openshift.api.model.DeploymentDetailsFluent$CausesNested<N>, io.fabric8.kubernetes.api.builder.Nested<N> {
  private final io.fabric8.openshift.api.model.DeploymentCauseBuilder builder;

  private final int index;

  final io.fabric8.openshift.api.model.DeploymentDetailsFluentImpl this$0;

  io.fabric8.openshift.api.model.DeploymentDetailsFluentImpl$CausesNestedImpl(io.fabric8.openshift.api.model.DeploymentDetailsFluentImpl, int, io.fabric8.openshift.api.model.DeploymentCause);
    Code:
       0: aload_0
       1: aload_1
       2: putfield      #1                  // Field this$0:Lio/fabric8/openshift/api/model/DeploymentDetailsFluentImpl;
       5: aload_0
       6: invokespecial #2                  // Method io/fabric8/openshift/api/model/DeploymentCauseFluentImpl."<init>":()V
       9: aload_0
      10: iload_2
      11: putfield      #3                  // Field index:I
      14: aload_0
      15: new           #4                  // class io/fabric8/openshift/api/model/DeploymentCauseBuilder
      18: dup
      19: aload_0
      20: aload_3
      21: invokespecial #5                  // Method io/fabric8/openshift/api/model/DeploymentCauseBuilder."<init>":(Lio/fabric8/openshift/api/model/DeploymentCauseFluent;Lio/fabric8/openshift/api/model/DeploymentCause;)V
      24: putfield      #6                  // Field builder:Lio/fabric8/openshift/api/model/DeploymentCauseBuilder;
      27: return

  io.fabric8.openshift.api.model.DeploymentDetailsFluentImpl$CausesNestedImpl(io.fabric8.openshift.api.model.DeploymentDetailsFluentImpl);
    Code:
       0: aload_0
       1: aload_1
       2: putfield      #1                  // Field this$0:Lio/fabric8/openshift/api/model/DeploymentDetailsFluentImpl;
       5: aload_0
       6: invokespecial #2                  // Method io/fabric8/openshift/api/model/DeploymentCauseFluentImpl."<init>":()V
       9: aload_0
      10: iconst_m1
      11: putfield      #3                  // Field index:I
      14: aload_0
      15: new           #4                  // class io/fabric8/openshift/api/model/DeploymentCauseBuilder
      18: dup
      19: aload_0
      20: invokespecial #7                  // Method io/fabric8/openshift/api/model/DeploymentCauseBuilder."<init>":(Lio/fabric8/openshift/api/model/DeploymentCauseFluent;)V
      23: putfield      #6                  // Field builder:Lio/fabric8/openshift/api/model/DeploymentCauseBuilder;
      26: return

  public N and();
    Code:
       0: aload_0
       1: getfield      #1                  // Field this$0:Lio/fabric8/openshift/api/model/DeploymentDetailsFluentImpl;
       4: aload_0
       5: getfield      #3                  // Field index:I
       8: aload_0
       9: getfield      #6                  // Field builder:Lio/fabric8/openshift/api/model/DeploymentCauseBuilder;
      12: invokevirtual #8                  // Method io/fabric8/openshift/api/model/DeploymentCauseBuilder.build:()Lio/fabric8/openshift/api/model/DeploymentCause;
      15: invokevirtual #9                  // Method io/fabric8/openshift/api/model/DeploymentDetailsFluentImpl.setToCauses:(ILio/fabric8/openshift/api/model/DeploymentCause;)Lio/fabric8/openshift/api/model/DeploymentDetailsFluent;
      18: areturn

  public N endCause();
    Code:
       0: aload_0
       1: invokevirtual #10                 // Method and:()Ljava/lang/Object;
       4: areturn
}
