Compiled from "DockerBuildStrategy.java"
public class io.fabric8.openshift.api.model.DockerBuildStrategy implements io.fabric8.kubernetes.api.model.KubernetesResource {
  private java.util.List<io.fabric8.kubernetes.api.model.EnvVar> buildArgs;

  private java.lang.String dockerfilePath;

  private java.util.List<io.fabric8.kubernetes.api.model.EnvVar> env;

  private java.lang.Boolean forcePull;

  private io.fabric8.kubernetes.api.model.ObjectReference from;

  private java.lang.String imageOptimizationPolicy;

  private java.lang.Boolean noCache;

  private io.fabric8.kubernetes.api.model.LocalObjectReference pullSecret;

  private java.util.Map<java.lang.String, java.lang.Object> additionalProperties;

  public io.fabric8.openshift.api.model.DockerBuildStrategy();
    Code:
       0: aload_0
       1: invokespecial #1                  // Method java/lang/Object."<init>":()V
       4: aload_0
       5: new           #2                  // class java/util/ArrayList
       8: dup
       9: invokespecial #3                  // Method java/util/ArrayList."<init>":()V
      12: putfield      #4                  // Field buildArgs:Ljava/util/List;
      15: aload_0
      16: new           #2                  // class java/util/ArrayList
      19: dup
      20: invokespecial #3                  // Method java/util/ArrayList."<init>":()V
      23: putfield      #5                  // Field env:Ljava/util/List;
      26: aload_0
      27: new           #6                  // class java/util/HashMap
      30: dup
      31: invokespecial #7                  // Method java/util/HashMap."<init>":()V
      34: putfield      #8                  // Field additionalProperties:Ljava/util/Map;
      37: return

  public io.fabric8.openshift.api.model.DockerBuildStrategy(java.util.List<io.fabric8.kubernetes.api.model.EnvVar>, java.lang.String, java.util.List<io.fabric8.kubernetes.api.model.EnvVar>, java.lang.Boolean, io.fabric8.kubernetes.api.model.ObjectReference, java.lang.String, java.lang.Boolean, io.fabric8.kubernetes.api.model.LocalObjectReference);
    Code:
       0: aload_0
       1: invokespecial #1                  // Method java/lang/Object."<init>":()V
       4: aload_0
       5: new           #2                  // class java/util/ArrayList
       8: dup
       9: invokespecial #3                  // Method java/util/ArrayList."<init>":()V
      12: putfield      #4                  // Field buildArgs:Ljava/util/List;
      15: aload_0
      16: new           #2                  // class java/util/ArrayList
      19: dup
      20: invokespecial #3                  // Method java/util/ArrayList."<init>":()V
      23: putfield      #5                  // Field env:Ljava/util/List;
      26: aload_0
      27: new           #6                  // class java/util/HashMap
      30: dup
      31: invokespecial #7                  // Method java/util/HashMap."<init>":()V
      34: putfield      #8                  // Field additionalProperties:Ljava/util/Map;
      37: aload_0
      38: aload_1
      39: putfield      #4                  // Field buildArgs:Ljava/util/List;
      42: aload_0
      43: aload_2
      44: putfield      #9                  // Field dockerfilePath:Ljava/lang/String;
      47: aload_0
      48: aload_3
      49: putfield      #5                  // Field env:Ljava/util/List;
      52: aload_0
      53: aload         4
      55: putfield      #10                 // Field forcePull:Ljava/lang/Boolean;
      58: aload_0
      59: aload         5
      61: putfield      #11                 // Field from:Lio/fabric8/kubernetes/api/model/ObjectReference;
      64: aload_0
      65: aload         6
      67: putfield      #12                 // Field imageOptimizationPolicy:Ljava/lang/String;
      70: aload_0
      71: aload         7
      73: putfield      #13                 // Field noCache:Ljava/lang/Boolean;
      76: aload_0
      77: aload         8
      79: putfield      #14                 // Field pullSecret:Lio/fabric8/kubernetes/api/model/LocalObjectReference;
      82: return

  public java.util.List<io.fabric8.kubernetes.api.model.EnvVar> getBuildArgs();
    Code:
       0: aload_0
       1: getfield      #4                  // Field buildArgs:Ljava/util/List;
       4: areturn

  public void setBuildArgs(java.util.List<io.fabric8.kubernetes.api.model.EnvVar>);
    Code:
       0: aload_0
       1: aload_1
       2: putfield      #4                  // Field buildArgs:Ljava/util/List;
       5: return

  public java.lang.String getDockerfilePath();
    Code:
       0: aload_0
       1: getfield      #9                  // Field dockerfilePath:Ljava/lang/String;
       4: areturn

  public void setDockerfilePath(java.lang.String);
    Code:
       0: aload_0
       1: aload_1
       2: putfield      #9                  // Field dockerfilePath:Ljava/lang/String;
       5: return

  public java.util.List<io.fabric8.kubernetes.api.model.EnvVar> getEnv();
    Code:
       0: aload_0
       1: getfield      #5                  // Field env:Ljava/util/List;
       4: areturn

  public void setEnv(java.util.List<io.fabric8.kubernetes.api.model.EnvVar>);
    Code:
       0: aload_0
       1: aload_1
       2: putfield      #5                  // Field env:Ljava/util/List;
       5: return

  public java.lang.Boolean getForcePull();
    Code:
       0: aload_0
       1: getfield      #10                 // Field forcePull:Ljava/lang/Boolean;
       4: areturn

  public void setForcePull(java.lang.Boolean);
    Code:
       0: aload_0
       1: aload_1
       2: putfield      #10                 // Field forcePull:Ljava/lang/Boolean;
       5: return

  public io.fabric8.kubernetes.api.model.ObjectReference getFrom();
    Code:
       0: aload_0
       1: getfield      #11                 // Field from:Lio/fabric8/kubernetes/api/model/ObjectReference;
       4: areturn

  public void setFrom(io.fabric8.kubernetes.api.model.ObjectReference);
    Code:
       0: aload_0
       1: aload_1
       2: putfield      #11                 // Field from:Lio/fabric8/kubernetes/api/model/ObjectReference;
       5: return

  public java.lang.String getImageOptimizationPolicy();
    Code:
       0: aload_0
       1: getfield      #12                 // Field imageOptimizationPolicy:Ljava/lang/String;
       4: areturn

  public void setImageOptimizationPolicy(java.lang.String);
    Code:
       0: aload_0
       1: aload_1
       2: putfield      #12                 // Field imageOptimizationPolicy:Ljava/lang/String;
       5: return

  public java.lang.Boolean getNoCache();
    Code:
       0: aload_0
       1: getfield      #13                 // Field noCache:Ljava/lang/Boolean;
       4: areturn

  public void setNoCache(java.lang.Boolean);
    Code:
       0: aload_0
       1: aload_1
       2: putfield      #13                 // Field noCache:Ljava/lang/Boolean;
       5: return

  public io.fabric8.kubernetes.api.model.LocalObjectReference getPullSecret();
    Code:
       0: aload_0
       1: getfield      #14                 // Field pullSecret:Lio/fabric8/kubernetes/api/model/LocalObjectReference;
       4: areturn

  public void setPullSecret(io.fabric8.kubernetes.api.model.LocalObjectReference);
    Code:
       0: aload_0
       1: aload_1
       2: putfield      #14                 // Field pullSecret:Lio/fabric8/kubernetes/api/model/LocalObjectReference;
       5: return

  public java.util.Map<java.lang.String, java.lang.Object> getAdditionalProperties();
    Code:
       0: aload_0
       1: getfield      #8                  // Field additionalProperties:Ljava/util/Map;
       4: areturn

  public void setAdditionalProperty(java.lang.String, java.lang.Object);
    Code:
       0: aload_0
       1: getfield      #8                  // Field additionalProperties:Ljava/util/Map;
       4: aload_1
       5: aload_2
       6: invokeinterface #15,  3           // InterfaceMethod java/util/Map.put:(Ljava/lang/Object;Ljava/lang/Object;)Ljava/lang/Object;
      11: pop
      12: return

  public java.lang.String toString();
    Code:
       0: new           #16                 // class java/lang/StringBuilder
       3: dup
       4: invokespecial #17                 // Method java/lang/StringBuilder."<init>":()V
       7: ldc           #18                 // String DockerBuildStrategy(buildArgs=
       9: invokevirtual #19                 // Method java/lang/StringBuilder.append:(Ljava/lang/String;)Ljava/lang/StringBuilder;
      12: aload_0
      13: invokevirtual #20                 // Method getBuildArgs:()Ljava/util/List;
      16: invokevirtual #21                 // Method java/lang/StringBuilder.append:(Ljava/lang/Object;)Ljava/lang/StringBuilder;
      19: ldc           #22                 // String , dockerfilePath=
      21: invokevirtual #19                 // Method java/lang/StringBuilder.append:(Ljava/lang/String;)Ljava/lang/StringBuilder;
      24: aload_0
      25: invokevirtual #23                 // Method getDockerfilePath:()Ljava/lang/String;
      28: invokevirtual #19                 // Method java/lang/StringBuilder.append:(Ljava/lang/String;)Ljava/lang/StringBuilder;
      31: ldc           #24                 // String , env=
      33: invokevirtual #19                 // Method java/lang/StringBuilder.append:(Ljava/lang/String;)Ljava/lang/StringBuilder;
      36: aload_0
      37: invokevirtual #25                 // Method getEnv:()Ljava/util/List;
      40: invokevirtual #21                 // Method java/lang/StringBuilder.append:(Ljava/lang/Object;)Ljava/lang/StringBuilder;
      43: ldc           #26                 // String , forcePull=
      45: invokevirtual #19                 // Method java/lang/StringBuilder.append:(Ljava/lang/String;)Ljava/lang/StringBuilder;
      48: aload_0
      49: invokevirtual #27                 // Method getForcePull:()Ljava/lang/Boolean;
      52: invokevirtual #21                 // Method java/lang/StringBuilder.append:(Ljava/lang/Object;)Ljava/lang/StringBuilder;
      55: ldc           #28                 // String , from=
      57: invokevirtual #19                 // Method java/lang/StringBuilder.append:(Ljava/lang/String;)Ljava/lang/StringBuilder;
      60: aload_0
      61: invokevirtual #29                 // Method getFrom:()Lio/fabric8/kubernetes/api/model/ObjectReference;
      64: invokevirtual #21                 // Method java/lang/StringBuilder.append:(Ljava/lang/Object;)Ljava/lang/StringBuilder;
      67: ldc           #30                 // String , imageOptimizationPolicy=
      69: invokevirtual #19                 // Method java/lang/StringBuilder.append:(Ljava/lang/String;)Ljava/lang/StringBuilder;
      72: aload_0
      73: invokevirtual #31                 // Method getImageOptimizationPolicy:()Ljava/lang/String;
      76: invokevirtual #19                 // Method java/lang/StringBuilder.append:(Ljava/lang/String;)Ljava/lang/StringBuilder;
      79: ldc           #32                 // String , noCache=
      81: invokevirtual #19                 // Method java/lang/StringBuilder.append:(Ljava/lang/String;)Ljava/lang/StringBuilder;
      84: aload_0
      85: invokevirtual #33                 // Method getNoCache:()Ljava/lang/Boolean;
      88: invokevirtual #21                 // Method java/lang/StringBuilder.append:(Ljava/lang/Object;)Ljava/lang/StringBuilder;
      91: ldc           #34                 // String , pullSecret=
      93: invokevirtual #19                 // Method java/lang/StringBuilder.append:(Ljava/lang/String;)Ljava/lang/StringBuilder;
      96: aload_0
      97: invokevirtual #35                 // Method getPullSecret:()Lio/fabric8/kubernetes/api/model/LocalObjectReference;
     100: invokevirtual #21                 // Method java/lang/StringBuilder.append:(Ljava/lang/Object;)Ljava/lang/StringBuilder;
     103: ldc           #36                 // String , additionalProperties=
     105: invokevirtual #19                 // Method java/lang/StringBuilder.append:(Ljava/lang/String;)Ljava/lang/StringBuilder;
     108: aload_0
     109: invokevirtual #37                 // Method getAdditionalProperties:()Ljava/util/Map;
     112: invokevirtual #21                 // Method java/lang/StringBuilder.append:(Ljava/lang/Object;)Ljava/lang/StringBuilder;
     115: ldc           #38                 // String )
     117: invokevirtual #19                 // Method java/lang/StringBuilder.append:(Ljava/lang/String;)Ljava/lang/StringBuilder;
     120: invokevirtual #39                 // Method java/lang/StringBuilder.toString:()Ljava/lang/String;
     123: areturn

  public boolean equals(java.lang.Object);
    Code:
       0: aload_1
       1: aload_0
       2: if_acmpne     7
       5: iconst_1
       6: ireturn
       7: aload_1
       8: instanceof    #40                 // class io/fabric8/openshift/api/model/DockerBuildStrategy
      11: ifne          16
      14: iconst_0
      15: ireturn
      16: aload_1
      17: checkcast     #40                 // class io/fabric8/openshift/api/model/DockerBuildStrategy
      20: astore_2
      21: aload_2
      22: aload_0
      23: invokevirtual #41                 // Method canEqual:(Ljava/lang/Object;)Z
      26: ifne          31
      29: iconst_0
      30: ireturn
      31: aload_0
      32: invokevirtual #20                 // Method getBuildArgs:()Ljava/util/List;
      35: astore_3
      36: aload_2
      37: invokevirtual #20                 // Method getBuildArgs:()Ljava/util/List;
      40: astore        4
      42: aload_3
      43: ifnonnull     54
      46: aload         4
      48: ifnull        65
      51: goto          63
      54: aload_3
      55: aload         4
      57: invokevirtual #42                 // Method java/lang/Object.equals:(Ljava/lang/Object;)Z
      60: ifne          65
      63: iconst_0
      64: ireturn
      65: aload_0
      66: invokevirtual #23                 // Method getDockerfilePath:()Ljava/lang/String;
      69: astore        5
      71: aload_2
      72: invokevirtual #23                 // Method getDockerfilePath:()Ljava/lang/String;
      75: astore        6
      77: aload         5
      79: ifnonnull     90
      82: aload         6
      84: ifnull        102
      87: goto          100
      90: aload         5
      92: aload         6
      94: invokevirtual #42                 // Method java/lang/Object.equals:(Ljava/lang/Object;)Z
      97: ifne          102
     100: iconst_0
     101: ireturn
     102: aload_0
     103: invokevirtual #25                 // Method getEnv:()Ljava/util/List;
     106: astore        7
     108: aload_2
     109: invokevirtual #25                 // Method getEnv:()Ljava/util/List;
     112: astore        8
     114: aload         7
     116: ifnonnull     127
     119: aload         8
     121: ifnull        139
     124: goto          137
     127: aload         7
     129: aload         8
     131: invokevirtual #42                 // Method java/lang/Object.equals:(Ljava/lang/Object;)Z
     134: ifne          139
     137: iconst_0
     138: ireturn
     139: aload_0
     140: invokevirtual #27                 // Method getForcePull:()Ljava/lang/Boolean;
     143: astore        9
     145: aload_2
     146: invokevirtual #27                 // Method getForcePull:()Ljava/lang/Boolean;
     149: astore        10
     151: aload         9
     153: ifnonnull     164
     156: aload         10
     158: ifnull        176
     161: goto          174
     164: aload         9
     166: aload         10
     168: invokevirtual #42                 // Method java/lang/Object.equals:(Ljava/lang/Object;)Z
     171: ifne          176
     174: iconst_0
     175: ireturn
     176: aload_0
     177: invokevirtual #29                 // Method getFrom:()Lio/fabric8/kubernetes/api/model/ObjectReference;
     180: astore        11
     182: aload_2
     183: invokevirtual #29                 // Method getFrom:()Lio/fabric8/kubernetes/api/model/ObjectReference;
     186: astore        12
     188: aload         11
     190: ifnonnull     201
     193: aload         12
     195: ifnull        213
     198: goto          211
     201: aload         11
     203: aload         12
     205: invokevirtual #42                 // Method java/lang/Object.equals:(Ljava/lang/Object;)Z
     208: ifne          213
     211: iconst_0
     212: ireturn
     213: aload_0
     214: invokevirtual #31                 // Method getImageOptimizationPolicy:()Ljava/lang/String;
     217: astore        13
     219: aload_2
     220: invokevirtual #31                 // Method getImageOptimizationPolicy:()Ljava/lang/String;
     223: astore        14
     225: aload         13
     227: ifnonnull     238
     230: aload         14
     232: ifnull        250
     235: goto          248
     238: aload         13
     240: aload         14
     242: invokevirtual #42                 // Method java/lang/Object.equals:(Ljava/lang/Object;)Z
     245: ifne          250
     248: iconst_0
     249: ireturn
     250: aload_0
     251: invokevirtual #33                 // Method getNoCache:()Ljava/lang/Boolean;
     254: astore        15
     256: aload_2
     257: invokevirtual #33                 // Method getNoCache:()Ljava/lang/Boolean;
     260: astore        16
     262: aload         15
     264: ifnonnull     275
     267: aload         16
     269: ifnull        287
     272: goto          285
     275: aload         15
     277: aload         16
     279: invokevirtual #42                 // Method java/lang/Object.equals:(Ljava/lang/Object;)Z
     282: ifne          287
     285: iconst_0
     286: ireturn
     287: aload_0
     288: invokevirtual #35                 // Method getPullSecret:()Lio/fabric8/kubernetes/api/model/LocalObjectReference;
     291: astore        17
     293: aload_2
     294: invokevirtual #35                 // Method getPullSecret:()Lio/fabric8/kubernetes/api/model/LocalObjectReference;
     297: astore        18
     299: aload         17
     301: ifnonnull     312
     304: aload         18
     306: ifnull        324
     309: goto          322
     312: aload         17
     314: aload         18
     316: invokevirtual #42                 // Method java/lang/Object.equals:(Ljava/lang/Object;)Z
     319: ifne          324
     322: iconst_0
     323: ireturn
     324: aload_0
     325: invokevirtual #37                 // Method getAdditionalProperties:()Ljava/util/Map;
     328: astore        19
     330: aload_2
     331: invokevirtual #37                 // Method getAdditionalProperties:()Ljava/util/Map;
     334: astore        20
     336: aload         19
     338: ifnonnull     349
     341: aload         20
     343: ifnull        361
     346: goto          359
     349: aload         19
     351: aload         20
     353: invokevirtual #42                 // Method java/lang/Object.equals:(Ljava/lang/Object;)Z
     356: ifne          361
     359: iconst_0
     360: ireturn
     361: iconst_1
     362: ireturn

  protected boolean canEqual(java.lang.Object);
    Code:
       0: aload_1
       1: instanceof    #40                 // class io/fabric8/openshift/api/model/DockerBuildStrategy
       4: ireturn

  public int hashCode();
    Code:
       0: bipush        59
       2: istore_1
       3: iconst_1
       4: istore_2
       5: aload_0
       6: invokevirtual #20                 // Method getBuildArgs:()Ljava/util/List;
       9: astore_3
      10: iload_2
      11: bipush        59
      13: imul
      14: aload_3
      15: ifnonnull     23
      18: bipush        43
      20: goto          27
      23: aload_3
      24: invokevirtual #43                 // Method java/lang/Object.hashCode:()I
      27: iadd
      28: istore_2
      29: aload_0
      30: invokevirtual #23                 // Method getDockerfilePath:()Ljava/lang/String;
      33: astore        4
      35: iload_2
      36: bipush        59
      38: imul
      39: aload         4
      41: ifnonnull     49
      44: bipush        43
      46: goto          54
      49: aload         4
      51: invokevirtual #43                 // Method java/lang/Object.hashCode:()I
      54: iadd
      55: istore_2
      56: aload_0
      57: invokevirtual #25                 // Method getEnv:()Ljava/util/List;
      60: astore        5
      62: iload_2
      63: bipush        59
      65: imul
      66: aload         5
      68: ifnonnull     76
      71: bipush        43
      73: goto          81
      76: aload         5
      78: invokevirtual #43                 // Method java/lang/Object.hashCode:()I
      81: iadd
      82: istore_2
      83: aload_0
      84: invokevirtual #27                 // Method getForcePull:()Ljava/lang/Boolean;
      87: astore        6
      89: iload_2
      90: bipush        59
      92: imul
      93: aload         6
      95: ifnonnull     103
      98: bipush        43
     100: goto          108
     103: aload         6
     105: invokevirtual #43                 // Method java/lang/Object.hashCode:()I
     108: iadd
     109: istore_2
     110: aload_0
     111: invokevirtual #29                 // Method getFrom:()Lio/fabric8/kubernetes/api/model/ObjectReference;
     114: astore        7
     116: iload_2
     117: bipush        59
     119: imul
     120: aload         7
     122: ifnonnull     130
     125: bipush        43
     127: goto          135
     130: aload         7
     132: invokevirtual #43                 // Method java/lang/Object.hashCode:()I
     135: iadd
     136: istore_2
     137: aload_0
     138: invokevirtual #31                 // Method getImageOptimizationPolicy:()Ljava/lang/String;
     141: astore        8
     143: iload_2
     144: bipush        59
     146: imul
     147: aload         8
     149: ifnonnull     157
     152: bipush        43
     154: goto          162
     157: aload         8
     159: invokevirtual #43                 // Method java/lang/Object.hashCode:()I
     162: iadd
     163: istore_2
     164: aload_0
     165: invokevirtual #33                 // Method getNoCache:()Ljava/lang/Boolean;
     168: astore        9
     170: iload_2
     171: bipush        59
     173: imul
     174: aload         9
     176: ifnonnull     184
     179: bipush        43
     181: goto          189
     184: aload         9
     186: invokevirtual #43                 // Method java/lang/Object.hashCode:()I
     189: iadd
     190: istore_2
     191: aload_0
     192: invokevirtual #35                 // Method getPullSecret:()Lio/fabric8/kubernetes/api/model/LocalObjectReference;
     195: astore        10
     197: iload_2
     198: bipush        59
     200: imul
     201: aload         10
     203: ifnonnull     211
     206: bipush        43
     208: goto          216
     211: aload         10
     213: invokevirtual #43                 // Method java/lang/Object.hashCode:()I
     216: iadd
     217: istore_2
     218: aload_0
     219: invokevirtual #37                 // Method getAdditionalProperties:()Ljava/util/Map;
     222: astore        11
     224: iload_2
     225: bipush        59
     227: imul
     228: aload         11
     230: ifnonnull     238
     233: bipush        43
     235: goto          243
     238: aload         11
     240: invokevirtual #43                 // Method java/lang/Object.hashCode:()I
     243: iadd
     244: istore_2
     245: iload_2
     246: ireturn
}
