Compiled from "GitHubWebHookCauseFluentImpl.java"
public class io.fabric8.openshift.api.model.GitHubWebHookCauseFluentImpl<A extends io.fabric8.openshift.api.model.GitHubWebHookCauseFluent<A>> extends io.fabric8.kubernetes.api.builder.BaseFluent<A> implements io.fabric8.openshift.api.model.GitHubWebHookCauseFluent<A> {
  private io.fabric8.openshift.api.model.SourceRevisionBuilder revision;

  private java.lang.String secret;

  public io.fabric8.openshift.api.model.GitHubWebHookCauseFluentImpl();
    Code:
       0: aload_0
       1: invokespecial #1                  // Method io/fabric8/kubernetes/api/builder/BaseFluent."<init>":()V
       4: return

  public io.fabric8.openshift.api.model.GitHubWebHookCauseFluentImpl(io.fabric8.openshift.api.model.GitHubWebHookCause);
    Code:
       0: aload_0
       1: invokespecial #1                  // Method io/fabric8/kubernetes/api/builder/BaseFluent."<init>":()V
       4: aload_0
       5: aload_1
       6: invokevirtual #2                  // Method io/fabric8/openshift/api/model/GitHubWebHookCause.getRevision:()Lio/fabric8/openshift/api/model/SourceRevision;
       9: invokevirtual #3                  // Method withRevision:(Lio/fabric8/openshift/api/model/SourceRevision;)Lio/fabric8/openshift/api/model/GitHubWebHookCauseFluent;
      12: pop
      13: aload_0
      14: aload_1
      15: invokevirtual #4                  // Method io/fabric8/openshift/api/model/GitHubWebHookCause.getSecret:()Ljava/lang/String;
      18: invokevirtual #5                  // Method withSecret:(Ljava/lang/String;)Lio/fabric8/openshift/api/model/GitHubWebHookCauseFluent;
      21: pop
      22: return

  public io.fabric8.openshift.api.model.SourceRevision getRevision();
    Code:
       0: aload_0
       1: getfield      #6                  // Field revision:Lio/fabric8/openshift/api/model/SourceRevisionBuilder;
       4: ifnull        17
       7: aload_0
       8: getfield      #6                  // Field revision:Lio/fabric8/openshift/api/model/SourceRevisionBuilder;
      11: invokevirtual #7                  // Method io/fabric8/openshift/api/model/SourceRevisionBuilder.build:()Lio/fabric8/openshift/api/model/SourceRevision;
      14: goto          18
      17: aconst_null
      18: areturn

  public io.fabric8.openshift.api.model.SourceRevision buildRevision();
    Code:
       0: aload_0
       1: getfield      #6                  // Field revision:Lio/fabric8/openshift/api/model/SourceRevisionBuilder;
       4: ifnull        17
       7: aload_0
       8: getfield      #6                  // Field revision:Lio/fabric8/openshift/api/model/SourceRevisionBuilder;
      11: invokevirtual #7                  // Method io/fabric8/openshift/api/model/SourceRevisionBuilder.build:()Lio/fabric8/openshift/api/model/SourceRevision;
      14: goto          18
      17: aconst_null
      18: areturn

  public A withRevision(io.fabric8.openshift.api.model.SourceRevision);
    Code:
       0: aload_0
       1: getfield      #8                  // Field _visitables:Lio/fabric8/kubernetes/api/builder/VisitableMap;
       4: ldc           #9                  // String revision
       6: invokevirtual #10                 // Method io/fabric8/kubernetes/api/builder/VisitableMap.get:(Ljava/lang/Object;)Ljava/util/List;
       9: aload_0
      10: getfield      #6                  // Field revision:Lio/fabric8/openshift/api/model/SourceRevisionBuilder;
      13: invokeinterface #11,  2           // InterfaceMethod java/util/List.remove:(Ljava/lang/Object;)Z
      18: pop
      19: aload_1
      20: ifnull        54
      23: aload_0
      24: new           #12                 // class io/fabric8/openshift/api/model/SourceRevisionBuilder
      27: dup
      28: aload_1
      29: invokespecial #13                 // Method io/fabric8/openshift/api/model/SourceRevisionBuilder."<init>":(Lio/fabric8/openshift/api/model/SourceRevision;)V
      32: putfield      #6                  // Field revision:Lio/fabric8/openshift/api/model/SourceRevisionBuilder;
      35: aload_0
      36: getfield      #8                  // Field _visitables:Lio/fabric8/kubernetes/api/builder/VisitableMap;
      39: ldc           #9                  // String revision
      41: invokevirtual #10                 // Method io/fabric8/kubernetes/api/builder/VisitableMap.get:(Ljava/lang/Object;)Ljava/util/List;
      44: aload_0
      45: getfield      #6                  // Field revision:Lio/fabric8/openshift/api/model/SourceRevisionBuilder;
      48: invokeinterface #14,  2           // InterfaceMethod java/util/List.add:(Ljava/lang/Object;)Z
      53: pop
      54: aload_0
      55: areturn

  public java.lang.Boolean hasRevision();
    Code:
       0: aload_0
       1: getfield      #6                  // Field revision:Lio/fabric8/openshift/api/model/SourceRevisionBuilder;
       4: ifnull        11
       7: iconst_1
       8: goto          12
      11: iconst_0
      12: invokestatic  #15                 // Method java/lang/Boolean.valueOf:(Z)Ljava/lang/Boolean;
      15: areturn

  public io.fabric8.openshift.api.model.GitHubWebHookCauseFluent$RevisionNested<A> withNewRevision();
    Code:
       0: new           #16                 // class io/fabric8/openshift/api/model/GitHubWebHookCauseFluentImpl$RevisionNestedImpl
       3: dup
       4: aload_0
       5: invokespecial #17                 // Method io/fabric8/openshift/api/model/GitHubWebHookCauseFluentImpl$RevisionNestedImpl."<init>":(Lio/fabric8/openshift/api/model/GitHubWebHookCauseFluentImpl;)V
       8: areturn

  public io.fabric8.openshift.api.model.GitHubWebHookCauseFluent$RevisionNested<A> withNewRevisionLike(io.fabric8.openshift.api.model.SourceRevision);
    Code:
       0: new           #16                 // class io/fabric8/openshift/api/model/GitHubWebHookCauseFluentImpl$RevisionNestedImpl
       3: dup
       4: aload_0
       5: aload_1
       6: invokespecial #18                 // Method io/fabric8/openshift/api/model/GitHubWebHookCauseFluentImpl$RevisionNestedImpl."<init>":(Lio/fabric8/openshift/api/model/GitHubWebHookCauseFluentImpl;Lio/fabric8/openshift/api/model/SourceRevision;)V
       9: areturn

  public io.fabric8.openshift.api.model.GitHubWebHookCauseFluent$RevisionNested<A> editRevision();
    Code:
       0: aload_0
       1: aload_0
       2: invokevirtual #19                 // Method getRevision:()Lio/fabric8/openshift/api/model/SourceRevision;
       5: invokevirtual #20                 // Method withNewRevisionLike:(Lio/fabric8/openshift/api/model/SourceRevision;)Lio/fabric8/openshift/api/model/GitHubWebHookCauseFluent$RevisionNested;
       8: areturn

  public io.fabric8.openshift.api.model.GitHubWebHookCauseFluent$RevisionNested<A> editOrNewRevision();
    Code:
       0: aload_0
       1: aload_0
       2: invokevirtual #19                 // Method getRevision:()Lio/fabric8/openshift/api/model/SourceRevision;
       5: ifnull        15
       8: aload_0
       9: invokevirtual #19                 // Method getRevision:()Lio/fabric8/openshift/api/model/SourceRevision;
      12: goto          25
      15: new           #12                 // class io/fabric8/openshift/api/model/SourceRevisionBuilder
      18: dup
      19: invokespecial #21                 // Method io/fabric8/openshift/api/model/SourceRevisionBuilder."<init>":()V
      22: invokevirtual #7                  // Method io/fabric8/openshift/api/model/SourceRevisionBuilder.build:()Lio/fabric8/openshift/api/model/SourceRevision;
      25: invokevirtual #20                 // Method withNewRevisionLike:(Lio/fabric8/openshift/api/model/SourceRevision;)Lio/fabric8/openshift/api/model/GitHubWebHookCauseFluent$RevisionNested;
      28: areturn

  public io.fabric8.openshift.api.model.GitHubWebHookCauseFluent$RevisionNested<A> editOrNewRevisionLike(io.fabric8.openshift.api.model.SourceRevision);
    Code:
       0: aload_0
       1: aload_0
       2: invokevirtual #19                 // Method getRevision:()Lio/fabric8/openshift/api/model/SourceRevision;
       5: ifnull        15
       8: aload_0
       9: invokevirtual #19                 // Method getRevision:()Lio/fabric8/openshift/api/model/SourceRevision;
      12: goto          16
      15: aload_1
      16: invokevirtual #20                 // Method withNewRevisionLike:(Lio/fabric8/openshift/api/model/SourceRevision;)Lio/fabric8/openshift/api/model/GitHubWebHookCauseFluent$RevisionNested;
      19: areturn

  public java.lang.String getSecret();
    Code:
       0: aload_0
       1: getfield      #22                 // Field secret:Ljava/lang/String;
       4: areturn

  public A withSecret(java.lang.String);
    Code:
       0: aload_0
       1: aload_1
       2: putfield      #22                 // Field secret:Ljava/lang/String;
       5: aload_0
       6: areturn

  public java.lang.Boolean hasSecret();
    Code:
       0: aload_0
       1: getfield      #22                 // Field secret:Ljava/lang/String;
       4: ifnull        11
       7: iconst_1
       8: goto          12
      11: iconst_0
      12: invokestatic  #15                 // Method java/lang/Boolean.valueOf:(Z)Ljava/lang/Boolean;
      15: areturn

  public A withNewSecret(java.lang.String);
    Code:
       0: aload_0
       1: new           #23                 // class java/lang/String
       4: dup
       5: aload_1
       6: invokespecial #24                 // Method java/lang/String."<init>":(Ljava/lang/String;)V
       9: invokevirtual #5                  // Method withSecret:(Ljava/lang/String;)Lio/fabric8/openshift/api/model/GitHubWebHookCauseFluent;
      12: areturn

  public A withNewSecret(java.lang.StringBuilder);
    Code:
       0: aload_0
       1: new           #23                 // class java/lang/String
       4: dup
       5: aload_1
       6: invokespecial #25                 // Method java/lang/String."<init>":(Ljava/lang/StringBuilder;)V
       9: invokevirtual #5                  // Method withSecret:(Ljava/lang/String;)Lio/fabric8/openshift/api/model/GitHubWebHookCauseFluent;
      12: areturn

  public A withNewSecret(java.lang.StringBuffer);
    Code:
       0: aload_0
       1: new           #23                 // class java/lang/String
       4: dup
       5: aload_1
       6: invokespecial #26                 // Method java/lang/String."<init>":(Ljava/lang/StringBuffer;)V
       9: invokevirtual #5                  // Method withSecret:(Ljava/lang/String;)Lio/fabric8/openshift/api/model/GitHubWebHookCauseFluent;
      12: areturn

  public boolean equals(java.lang.Object);
    Code:
       0: aload_0
       1: aload_1
       2: if_acmpne     7
       5: iconst_1
       6: ireturn
       7: aload_1
       8: ifnull        22
      11: aload_0
      12: invokevirtual #27                 // Method java/lang/Object.getClass:()Ljava/lang/Class;
      15: aload_1
      16: invokevirtual #27                 // Method java/lang/Object.getClass:()Ljava/lang/Class;
      19: if_acmpeq     24
      22: iconst_0
      23: ireturn
      24: aload_1
      25: checkcast     #28                 // class io/fabric8/openshift/api/model/GitHubWebHookCauseFluentImpl
      28: astore_2
      29: aload_0
      30: getfield      #6                  // Field revision:Lio/fabric8/openshift/api/model/SourceRevisionBuilder;
      33: ifnull        53
      36: aload_0
      37: getfield      #6                  // Field revision:Lio/fabric8/openshift/api/model/SourceRevisionBuilder;
      40: aload_2
      41: getfield      #6                  // Field revision:Lio/fabric8/openshift/api/model/SourceRevisionBuilder;
      44: invokevirtual #29                 // Method io/fabric8/openshift/api/model/SourceRevisionBuilder.equals:(Ljava/lang/Object;)Z
      47: ifne          62
      50: goto          60
      53: aload_2
      54: getfield      #6                  // Field revision:Lio/fabric8/openshift/api/model/SourceRevisionBuilder;
      57: ifnull        62
      60: iconst_0
      61: ireturn
      62: aload_0
      63: getfield      #22                 // Field secret:Ljava/lang/String;
      66: ifnull        86
      69: aload_0
      70: getfield      #22                 // Field secret:Ljava/lang/String;
      73: aload_2
      74: getfield      #22                 // Field secret:Ljava/lang/String;
      77: invokevirtual #30                 // Method java/lang/String.equals:(Ljava/lang/Object;)Z
      80: ifne          95
      83: goto          93
      86: aload_2
      87: getfield      #22                 // Field secret:Ljava/lang/String;
      90: ifnull        95
      93: iconst_0
      94: ireturn
      95: iconst_1
      96: ireturn
}
