Compiled from "PolicyRuleFluentImpl.java"
public class io.fabric8.openshift.api.model.PolicyRuleFluentImpl$PersistentVolumeClaimAttributeRestrictionsNestedImpl<N> extends io.fabric8.kubernetes.api.model.PersistentVolumeClaimFluentImpl<io.fabric8.openshift.api.model.PolicyRuleFluent$PersistentVolumeClaimAttributeRestrictionsNested<N>> implements io.fabric8.openshift.api.model.PolicyRuleFluent$PersistentVolumeClaimAttributeRestrictionsNested<N>, io.fabric8.kubernetes.api.builder.Nested<N> {
  private final io.fabric8.kubernetes.api.model.PersistentVolumeClaimBuilder builder;

  final io.fabric8.openshift.api.model.PolicyRuleFluentImpl this$0;

  io.fabric8.openshift.api.model.PolicyRuleFluentImpl$PersistentVolumeClaimAttributeRestrictionsNestedImpl(io.fabric8.openshift.api.model.PolicyRuleFluentImpl, io.fabric8.kubernetes.api.model.PersistentVolumeClaim);
    Code:
       0: aload_0
       1: aload_1
       2: putfield      #1                  // Field this$0:Lio/fabric8/openshift/api/model/PolicyRuleFluentImpl;
       5: aload_0
       6: invokespecial #2                  // Method io/fabric8/kubernetes/api/model/PersistentVolumeClaimFluentImpl."<init>":()V
       9: aload_0
      10: new           #3                  // class io/fabric8/kubernetes/api/model/PersistentVolumeClaimBuilder
      13: dup
      14: aload_0
      15: aload_2
      16: invokespecial #4                  // Method io/fabric8/kubernetes/api/model/PersistentVolumeClaimBuilder."<init>":(Lio/fabric8/kubernetes/api/model/PersistentVolumeClaimFluent;Lio/fabric8/kubernetes/api/model/PersistentVolumeClaim;)V
      19: putfield      #5                  // Field builder:Lio/fabric8/kubernetes/api/model/PersistentVolumeClaimBuilder;
      22: return

  io.fabric8.openshift.api.model.PolicyRuleFluentImpl$PersistentVolumeClaimAttributeRestrictionsNestedImpl(io.fabric8.openshift.api.model.PolicyRuleFluentImpl);
    Code:
       0: aload_0
       1: aload_1
       2: putfield      #1                  // Field this$0:Lio/fabric8/openshift/api/model/PolicyRuleFluentImpl;
       5: aload_0
       6: invokespecial #2                  // Method io/fabric8/kubernetes/api/model/PersistentVolumeClaimFluentImpl."<init>":()V
       9: aload_0
      10: new           #3                  // class io/fabric8/kubernetes/api/model/PersistentVolumeClaimBuilder
      13: dup
      14: aload_0
      15: invokespecial #6                  // Method io/fabric8/kubernetes/api/model/PersistentVolumeClaimBuilder."<init>":(Lio/fabric8/kubernetes/api/model/PersistentVolumeClaimFluent;)V
      18: putfield      #5                  // Field builder:Lio/fabric8/kubernetes/api/model/PersistentVolumeClaimBuilder;
      21: return

  public N and();
    Code:
       0: aload_0
       1: getfield      #1                  // Field this$0:Lio/fabric8/openshift/api/model/PolicyRuleFluentImpl;
       4: aload_0
       5: getfield      #5                  // Field builder:Lio/fabric8/kubernetes/api/model/PersistentVolumeClaimBuilder;
       8: invokevirtual #7                  // Method io/fabric8/kubernetes/api/model/PersistentVolumeClaimBuilder.build:()Lio/fabric8/kubernetes/api/model/PersistentVolumeClaim;
      11: invokevirtual #8                  // Method io/fabric8/openshift/api/model/PolicyRuleFluentImpl.withAttributeRestrictions:(Lio/fabric8/kubernetes/api/model/HasMetadata;)Lio/fabric8/openshift/api/model/PolicyRuleFluent;
      14: areturn

  public N endPersistentVolumeClaimAttributeRestrictions();
    Code:
       0: aload_0
       1: invokevirtual #9                  // Method and:()Ljava/lang/Object;
       4: areturn
}
