Compiled from "RunAsUserStrategyOptionsFluentImpl.java"
public class io.fabric8.openshift.api.model.RunAsUserStrategyOptionsFluentImpl<A extends io.fabric8.openshift.api.model.RunAsUserStrategyOptionsFluent<A>> extends io.fabric8.kubernetes.api.builder.BaseFluent<A> implements io.fabric8.openshift.api.model.RunAsUserStrategyOptionsFluent<A> {
  private java.lang.String type;

  private java.lang.Long uid;

  private java.lang.Long uidRangeMax;

  private java.lang.Long uidRangeMin;

  public io.fabric8.openshift.api.model.RunAsUserStrategyOptionsFluentImpl();
    Code:
       0: aload_0
       1: invokespecial #1                  // Method io/fabric8/kubernetes/api/builder/BaseFluent."<init>":()V
       4: return

  public io.fabric8.openshift.api.model.RunAsUserStrategyOptionsFluentImpl(io.fabric8.openshift.api.model.RunAsUserStrategyOptions);
    Code:
       0: aload_0
       1: invokespecial #1                  // Method io/fabric8/kubernetes/api/builder/BaseFluent."<init>":()V
       4: aload_0
       5: aload_1
       6: invokevirtual #2                  // Method io/fabric8/openshift/api/model/RunAsUserStrategyOptions.getType:()Ljava/lang/String;
       9: invokevirtual #3                  // Method withType:(Ljava/lang/String;)Lio/fabric8/openshift/api/model/RunAsUserStrategyOptionsFluent;
      12: pop
      13: aload_0
      14: aload_1
      15: invokevirtual #4                  // Method io/fabric8/openshift/api/model/RunAsUserStrategyOptions.getUid:()Ljava/lang/Long;
      18: invokevirtual #5                  // Method withUid:(Ljava/lang/Long;)Lio/fabric8/openshift/api/model/RunAsUserStrategyOptionsFluent;
      21: pop
      22: aload_0
      23: aload_1
      24: invokevirtual #6                  // Method io/fabric8/openshift/api/model/RunAsUserStrategyOptions.getUidRangeMax:()Ljava/lang/Long;
      27: invokevirtual #7                  // Method withUidRangeMax:(Ljava/lang/Long;)Lio/fabric8/openshift/api/model/RunAsUserStrategyOptionsFluent;
      30: pop
      31: aload_0
      32: aload_1
      33: invokevirtual #8                  // Method io/fabric8/openshift/api/model/RunAsUserStrategyOptions.getUidRangeMin:()Ljava/lang/Long;
      36: invokevirtual #9                  // Method withUidRangeMin:(Ljava/lang/Long;)Lio/fabric8/openshift/api/model/RunAsUserStrategyOptionsFluent;
      39: pop
      40: return

  public java.lang.String getType();
    Code:
       0: aload_0
       1: getfield      #10                 // Field type:Ljava/lang/String;
       4: areturn

  public A withType(java.lang.String);
    Code:
       0: aload_0
       1: aload_1
       2: putfield      #10                 // Field type:Ljava/lang/String;
       5: aload_0
       6: areturn

  public java.lang.Boolean hasType();
    Code:
       0: aload_0
       1: getfield      #10                 // Field type:Ljava/lang/String;
       4: ifnull        11
       7: iconst_1
       8: goto          12
      11: iconst_0
      12: invokestatic  #11                 // Method java/lang/Boolean.valueOf:(Z)Ljava/lang/Boolean;
      15: areturn

  public A withNewType(java.lang.String);
    Code:
       0: aload_0
       1: new           #12                 // class java/lang/String
       4: dup
       5: aload_1
       6: invokespecial #13                 // Method java/lang/String."<init>":(Ljava/lang/String;)V
       9: invokevirtual #3                  // Method withType:(Ljava/lang/String;)Lio/fabric8/openshift/api/model/RunAsUserStrategyOptionsFluent;
      12: areturn

  public A withNewType(java.lang.StringBuilder);
    Code:
       0: aload_0
       1: new           #12                 // class java/lang/String
       4: dup
       5: aload_1
       6: invokespecial #14                 // Method java/lang/String."<init>":(Ljava/lang/StringBuilder;)V
       9: invokevirtual #3                  // Method withType:(Ljava/lang/String;)Lio/fabric8/openshift/api/model/RunAsUserStrategyOptionsFluent;
      12: areturn

  public A withNewType(java.lang.StringBuffer);
    Code:
       0: aload_0
       1: new           #12                 // class java/lang/String
       4: dup
       5: aload_1
       6: invokespecial #15                 // Method java/lang/String."<init>":(Ljava/lang/StringBuffer;)V
       9: invokevirtual #3                  // Method withType:(Ljava/lang/String;)Lio/fabric8/openshift/api/model/RunAsUserStrategyOptionsFluent;
      12: areturn

  public java.lang.Long getUid();
    Code:
       0: aload_0
       1: getfield      #16                 // Field uid:Ljava/lang/Long;
       4: areturn

  public A withUid(java.lang.Long);
    Code:
       0: aload_0
       1: aload_1
       2: putfield      #16                 // Field uid:Ljava/lang/Long;
       5: aload_0
       6: areturn

  public java.lang.Boolean hasUid();
    Code:
       0: aload_0
       1: getfield      #16                 // Field uid:Ljava/lang/Long;
       4: ifnull        11
       7: iconst_1
       8: goto          12
      11: iconst_0
      12: invokestatic  #11                 // Method java/lang/Boolean.valueOf:(Z)Ljava/lang/Boolean;
      15: areturn

  public java.lang.Long getUidRangeMax();
    Code:
       0: aload_0
       1: getfield      #17                 // Field uidRangeMax:Ljava/lang/Long;
       4: areturn

  public A withUidRangeMax(java.lang.Long);
    Code:
       0: aload_0
       1: aload_1
       2: putfield      #17                 // Field uidRangeMax:Ljava/lang/Long;
       5: aload_0
       6: areturn

  public java.lang.Boolean hasUidRangeMax();
    Code:
       0: aload_0
       1: getfield      #17                 // Field uidRangeMax:Ljava/lang/Long;
       4: ifnull        11
       7: iconst_1
       8: goto          12
      11: iconst_0
      12: invokestatic  #11                 // Method java/lang/Boolean.valueOf:(Z)Ljava/lang/Boolean;
      15: areturn

  public java.lang.Long getUidRangeMin();
    Code:
       0: aload_0
       1: getfield      #18                 // Field uidRangeMin:Ljava/lang/Long;
       4: areturn

  public A withUidRangeMin(java.lang.Long);
    Code:
       0: aload_0
       1: aload_1
       2: putfield      #18                 // Field uidRangeMin:Ljava/lang/Long;
       5: aload_0
       6: areturn

  public java.lang.Boolean hasUidRangeMin();
    Code:
       0: aload_0
       1: getfield      #18                 // Field uidRangeMin:Ljava/lang/Long;
       4: ifnull        11
       7: iconst_1
       8: goto          12
      11: iconst_0
      12: invokestatic  #11                 // Method java/lang/Boolean.valueOf:(Z)Ljava/lang/Boolean;
      15: areturn

  public boolean equals(java.lang.Object);
    Code:
       0: aload_0
       1: aload_1
       2: if_acmpne     7
       5: iconst_1
       6: ireturn
       7: aload_1
       8: ifnull        22
      11: aload_0
      12: invokevirtual #19                 // Method java/lang/Object.getClass:()Ljava/lang/Class;
      15: aload_1
      16: invokevirtual #19                 // Method java/lang/Object.getClass:()Ljava/lang/Class;
      19: if_acmpeq     24
      22: iconst_0
      23: ireturn
      24: aload_1
      25: checkcast     #20                 // class io/fabric8/openshift/api/model/RunAsUserStrategyOptionsFluentImpl
      28: astore_2
      29: aload_0
      30: getfield      #10                 // Field type:Ljava/lang/String;
      33: ifnull        53
      36: aload_0
      37: getfield      #10                 // Field type:Ljava/lang/String;
      40: aload_2
      41: getfield      #10                 // Field type:Ljava/lang/String;
      44: invokevirtual #21                 // Method java/lang/String.equals:(Ljava/lang/Object;)Z
      47: ifne          62
      50: goto          60
      53: aload_2
      54: getfield      #10                 // Field type:Ljava/lang/String;
      57: ifnull        62
      60: iconst_0
      61: ireturn
      62: aload_0
      63: getfield      #16                 // Field uid:Ljava/lang/Long;
      66: ifnull        86
      69: aload_0
      70: getfield      #16                 // Field uid:Ljava/lang/Long;
      73: aload_2
      74: getfield      #16                 // Field uid:Ljava/lang/Long;
      77: invokevirtual #22                 // Method java/lang/Long.equals:(Ljava/lang/Object;)Z
      80: ifne          95
      83: goto          93
      86: aload_2
      87: getfield      #16                 // Field uid:Ljava/lang/Long;
      90: ifnull        95
      93: iconst_0
      94: ireturn
      95: aload_0
      96: getfield      #17                 // Field uidRangeMax:Ljava/lang/Long;
      99: ifnull        119
     102: aload_0
     103: getfield      #17                 // Field uidRangeMax:Ljava/lang/Long;
     106: aload_2
     107: getfield      #17                 // Field uidRangeMax:Ljava/lang/Long;
     110: invokevirtual #22                 // Method java/lang/Long.equals:(Ljava/lang/Object;)Z
     113: ifne          128
     116: goto          126
     119: aload_2
     120: getfield      #17                 // Field uidRangeMax:Ljava/lang/Long;
     123: ifnull        128
     126: iconst_0
     127: ireturn
     128: aload_0
     129: getfield      #18                 // Field uidRangeMin:Ljava/lang/Long;
     132: ifnull        152
     135: aload_0
     136: getfield      #18                 // Field uidRangeMin:Ljava/lang/Long;
     139: aload_2
     140: getfield      #18                 // Field uidRangeMin:Ljava/lang/Long;
     143: invokevirtual #22                 // Method java/lang/Long.equals:(Ljava/lang/Object;)Z
     146: ifne          161
     149: goto          159
     152: aload_2
     153: getfield      #18                 // Field uidRangeMin:Ljava/lang/Long;
     156: ifnull        161
     159: iconst_0
     160: ireturn
     161: iconst_1
     162: ireturn
}
