Compiled from "SecurityContextConstraintsListFluentImpl.java"
public class io.fabric8.openshift.api.model.SecurityContextConstraintsListFluentImpl$ItemsNestedImpl<N> extends io.fabric8.openshift.api.model.SecurityContextConstraintsFluentImpl<io.fabric8.openshift.api.model.SecurityContextConstraintsListFluent$ItemsNested<N>> implements io.fabric8.openshift.api.model.SecurityContextConstraintsListFluent$ItemsNested<N>, io.fabric8.kubernetes.api.builder.Nested<N> {
  private final io.fabric8.openshift.api.model.SecurityContextConstraintsBuilder builder;

  private final int index;

  final io.fabric8.openshift.api.model.SecurityContextConstraintsListFluentImpl this$0;

  io.fabric8.openshift.api.model.SecurityContextConstraintsListFluentImpl$ItemsNestedImpl(io.fabric8.openshift.api.model.SecurityContextConstraintsListFluentImpl, int, io.fabric8.openshift.api.model.SecurityContextConstraints);
    Code:
       0: aload_0
       1: aload_1
       2: putfield      #1                  // Field this$0:Lio/fabric8/openshift/api/model/SecurityContextConstraintsListFluentImpl;
       5: aload_0
       6: invokespecial #2                  // Method io/fabric8/openshift/api/model/SecurityContextConstraintsFluentImpl."<init>":()V
       9: aload_0
      10: iload_2
      11: putfield      #3                  // Field index:I
      14: aload_0
      15: new           #4                  // class io/fabric8/openshift/api/model/SecurityContextConstraintsBuilder
      18: dup
      19: aload_0
      20: aload_3
      21: invokespecial #5                  // Method io/fabric8/openshift/api/model/SecurityContextConstraintsBuilder."<init>":(Lio/fabric8/openshift/api/model/SecurityContextConstraintsFluent;Lio/fabric8/openshift/api/model/SecurityContextConstraints;)V
      24: putfield      #6                  // Field builder:Lio/fabric8/openshift/api/model/SecurityContextConstraintsBuilder;
      27: return

  io.fabric8.openshift.api.model.SecurityContextConstraintsListFluentImpl$ItemsNestedImpl(io.fabric8.openshift.api.model.SecurityContextConstraintsListFluentImpl);
    Code:
       0: aload_0
       1: aload_1
       2: putfield      #1                  // Field this$0:Lio/fabric8/openshift/api/model/SecurityContextConstraintsListFluentImpl;
       5: aload_0
       6: invokespecial #2                  // Method io/fabric8/openshift/api/model/SecurityContextConstraintsFluentImpl."<init>":()V
       9: aload_0
      10: iconst_m1
      11: putfield      #3                  // Field index:I
      14: aload_0
      15: new           #4                  // class io/fabric8/openshift/api/model/SecurityContextConstraintsBuilder
      18: dup
      19: aload_0
      20: invokespecial #7                  // Method io/fabric8/openshift/api/model/SecurityContextConstraintsBuilder."<init>":(Lio/fabric8/openshift/api/model/SecurityContextConstraintsFluent;)V
      23: putfield      #6                  // Field builder:Lio/fabric8/openshift/api/model/SecurityContextConstraintsBuilder;
      26: return

  public N and();
    Code:
       0: aload_0
       1: getfield      #1                  // Field this$0:Lio/fabric8/openshift/api/model/SecurityContextConstraintsListFluentImpl;
       4: aload_0
       5: getfield      #3                  // Field index:I
       8: aload_0
       9: getfield      #6                  // Field builder:Lio/fabric8/openshift/api/model/SecurityContextConstraintsBuilder;
      12: invokevirtual #8                  // Method io/fabric8/openshift/api/model/SecurityContextConstraintsBuilder.build:()Lio/fabric8/openshift/api/model/SecurityContextConstraints;
      15: invokevirtual #9                  // Method io/fabric8/openshift/api/model/SecurityContextConstraintsListFluentImpl.setToItems:(ILio/fabric8/openshift/api/model/SecurityContextConstraints;)Lio/fabric8/openshift/api/model/SecurityContextConstraintsListFluent;
      18: areturn

  public N endItem();
    Code:
       0: aload_0
       1: invokevirtual #10                 // Method and:()Ljava/lang/Object;
       4: areturn
}
