Compiled from "SecurityContextConstraintsFluentImpl.java"
public class io.fabric8.openshift.api.model.SecurityContextConstraintsFluentImpl$RunAsUserNestedImpl<N> extends io.fabric8.openshift.api.model.RunAsUserStrategyOptionsFluentImpl<io.fabric8.openshift.api.model.SecurityContextConstraintsFluent$RunAsUserNested<N>> implements io.fabric8.openshift.api.model.SecurityContextConstraintsFluent$RunAsUserNested<N>, io.fabric8.kubernetes.api.builder.Nested<N> {
  private final io.fabric8.openshift.api.model.RunAsUserStrategyOptionsBuilder builder;

  final io.fabric8.openshift.api.model.SecurityContextConstraintsFluentImpl this$0;

  io.fabric8.openshift.api.model.SecurityContextConstraintsFluentImpl$RunAsUserNestedImpl(io.fabric8.openshift.api.model.SecurityContextConstraintsFluentImpl, io.fabric8.openshift.api.model.RunAsUserStrategyOptions);
    Code:
       0: aload_0
       1: aload_1
       2: putfield      #1                  // Field this$0:Lio/fabric8/openshift/api/model/SecurityContextConstraintsFluentImpl;
       5: aload_0
       6: invokespecial #2                  // Method io/fabric8/openshift/api/model/RunAsUserStrategyOptionsFluentImpl."<init>":()V
       9: aload_0
      10: new           #3                  // class io/fabric8/openshift/api/model/RunAsUserStrategyOptionsBuilder
      13: dup
      14: aload_0
      15: aload_2
      16: invokespecial #4                  // Method io/fabric8/openshift/api/model/RunAsUserStrategyOptionsBuilder."<init>":(Lio/fabric8/openshift/api/model/RunAsUserStrategyOptionsFluent;Lio/fabric8/openshift/api/model/RunAsUserStrategyOptions;)V
      19: putfield      #5                  // Field builder:Lio/fabric8/openshift/api/model/RunAsUserStrategyOptionsBuilder;
      22: return

  io.fabric8.openshift.api.model.SecurityContextConstraintsFluentImpl$RunAsUserNestedImpl(io.fabric8.openshift.api.model.SecurityContextConstraintsFluentImpl);
    Code:
       0: aload_0
       1: aload_1
       2: putfield      #1                  // Field this$0:Lio/fabric8/openshift/api/model/SecurityContextConstraintsFluentImpl;
       5: aload_0
       6: invokespecial #2                  // Method io/fabric8/openshift/api/model/RunAsUserStrategyOptionsFluentImpl."<init>":()V
       9: aload_0
      10: new           #3                  // class io/fabric8/openshift/api/model/RunAsUserStrategyOptionsBuilder
      13: dup
      14: aload_0
      15: invokespecial #6                  // Method io/fabric8/openshift/api/model/RunAsUserStrategyOptionsBuilder."<init>":(Lio/fabric8/openshift/api/model/RunAsUserStrategyOptionsFluent;)V
      18: putfield      #5                  // Field builder:Lio/fabric8/openshift/api/model/RunAsUserStrategyOptionsBuilder;
      21: return

  public N and();
    Code:
       0: aload_0
       1: getfield      #1                  // Field this$0:Lio/fabric8/openshift/api/model/SecurityContextConstraintsFluentImpl;
       4: aload_0
       5: getfield      #5                  // Field builder:Lio/fabric8/openshift/api/model/RunAsUserStrategyOptionsBuilder;
       8: invokevirtual #7                  // Method io/fabric8/openshift/api/model/RunAsUserStrategyOptionsBuilder.build:()Lio/fabric8/openshift/api/model/RunAsUserStrategyOptions;
      11: invokevirtual #8                  // Method io/fabric8/openshift/api/model/SecurityContextConstraintsFluentImpl.withRunAsUser:(Lio/fabric8/openshift/api/model/RunAsUserStrategyOptions;)Lio/fabric8/openshift/api/model/SecurityContextConstraintsFluent;
      14: areturn

  public N endRunAsUser();
    Code:
       0: aload_0
       1: invokevirtual #9                  // Method and:()Ljava/lang/Object;
       4: areturn
}
