Compiled from "WebHookTriggerBuilder.java"
public class io.fabric8.openshift.api.model.WebHookTriggerBuilder extends io.fabric8.openshift.api.model.WebHookTriggerFluentImpl<io.fabric8.openshift.api.model.WebHookTriggerBuilder> implements io.fabric8.kubernetes.api.builder.VisitableBuilder<io.fabric8.openshift.api.model.WebHookTrigger, io.fabric8.openshift.api.model.WebHookTriggerBuilder> {
  io.fabric8.openshift.api.model.WebHookTriggerFluent<?> fluent;

  java.lang.Boolean validationEnabled;

  public io.fabric8.openshift.api.model.WebHookTriggerBuilder();
    Code:
       0: aload_0
       1: iconst_1
       2: invokestatic  #1                  // Method java/lang/Boolean.valueOf:(Z)Ljava/lang/Boolean;
       5: invokespecial #2                  // Method "<init>":(Ljava/lang/Boolean;)V
       8: return

  public io.fabric8.openshift.api.model.WebHookTriggerBuilder(java.lang.Boolean);
    Code:
       0: aload_0
       1: new           #3                  // class io/fabric8/openshift/api/model/WebHookTrigger
       4: dup
       5: invokespecial #4                  // Method io/fabric8/openshift/api/model/WebHookTrigger."<init>":()V
       8: aload_1
       9: invokespecial #5                  // Method "<init>":(Lio/fabric8/openshift/api/model/WebHookTrigger;Ljava/lang/Boolean;)V
      12: return

  public io.fabric8.openshift.api.model.WebHookTriggerBuilder(io.fabric8.openshift.api.model.WebHookTriggerFluent<?>);
    Code:
       0: aload_0
       1: aload_1
       2: iconst_1
       3: invokestatic  #1                  // Method java/lang/Boolean.valueOf:(Z)Ljava/lang/Boolean;
       6: invokespecial #6                  // Method "<init>":(Lio/fabric8/openshift/api/model/WebHookTriggerFluent;Ljava/lang/Boolean;)V
       9: return

  public io.fabric8.openshift.api.model.WebHookTriggerBuilder(io.fabric8.openshift.api.model.WebHookTriggerFluent<?>, java.lang.Boolean);
    Code:
       0: aload_0
       1: aload_1
       2: new           #3                  // class io/fabric8/openshift/api/model/WebHookTrigger
       5: dup
       6: invokespecial #4                  // Method io/fabric8/openshift/api/model/WebHookTrigger."<init>":()V
       9: aload_2
      10: invokespecial #7                  // Method "<init>":(Lio/fabric8/openshift/api/model/WebHookTriggerFluent;Lio/fabric8/openshift/api/model/WebHookTrigger;Ljava/lang/Boolean;)V
      13: return

  public io.fabric8.openshift.api.model.WebHookTriggerBuilder(io.fabric8.openshift.api.model.WebHookTriggerFluent<?>, io.fabric8.openshift.api.model.WebHookTrigger);
    Code:
       0: aload_0
       1: aload_1
       2: aload_2
       3: iconst_1
       4: invokestatic  #1                  // Method java/lang/Boolean.valueOf:(Z)Ljava/lang/Boolean;
       7: invokespecial #7                  // Method "<init>":(Lio/fabric8/openshift/api/model/WebHookTriggerFluent;Lio/fabric8/openshift/api/model/WebHookTrigger;Ljava/lang/Boolean;)V
      10: return

  public io.fabric8.openshift.api.model.WebHookTriggerBuilder(io.fabric8.openshift.api.model.WebHookTriggerFluent<?>, io.fabric8.openshift.api.model.WebHookTrigger, java.lang.Boolean);
    Code:
       0: aload_0
       1: invokespecial #8                  // Method io/fabric8/openshift/api/model/WebHookTriggerFluentImpl."<init>":()V
       4: aload_0
       5: aload_1
       6: putfield      #9                  // Field fluent:Lio/fabric8/openshift/api/model/WebHookTriggerFluent;
       9: aload_1
      10: aload_2
      11: invokevirtual #10                 // Method io/fabric8/openshift/api/model/WebHookTrigger.getAllowEnv:()Ljava/lang/Boolean;
      14: invokeinterface #11,  2           // InterfaceMethod io/fabric8/openshift/api/model/WebHookTriggerFluent.withAllowEnv:(Ljava/lang/Boolean;)Lio/fabric8/openshift/api/model/WebHookTriggerFluent;
      19: pop
      20: aload_1
      21: aload_2
      22: invokevirtual #12                 // Method io/fabric8/openshift/api/model/WebHookTrigger.getSecret:()Ljava/lang/String;
      25: invokeinterface #13,  2           // InterfaceMethod io/fabric8/openshift/api/model/WebHookTriggerFluent.withSecret:(Ljava/lang/String;)Lio/fabric8/openshift/api/model/WebHookTriggerFluent;
      30: pop
      31: aload_1
      32: aload_2
      33: invokevirtual #14                 // Method io/fabric8/openshift/api/model/WebHookTrigger.getSecretReference:()Lio/fabric8/openshift/api/model/SecretLocalReference;
      36: invokeinterface #15,  2           // InterfaceMethod io/fabric8/openshift/api/model/WebHookTriggerFluent.withSecretReference:(Lio/fabric8/openshift/api/model/SecretLocalReference;)Lio/fabric8/openshift/api/model/WebHookTriggerFluent;
      41: pop
      42: aload_0
      43: aload_3
      44: putfield      #16                 // Field validationEnabled:Ljava/lang/Boolean;
      47: return

  public io.fabric8.openshift.api.model.WebHookTriggerBuilder(io.fabric8.openshift.api.model.WebHookTrigger);
    Code:
       0: aload_0
       1: aload_1
       2: iconst_1
       3: invokestatic  #1                  // Method java/lang/Boolean.valueOf:(Z)Ljava/lang/Boolean;
       6: invokespecial #5                  // Method "<init>":(Lio/fabric8/openshift/api/model/WebHookTrigger;Ljava/lang/Boolean;)V
       9: return

  public io.fabric8.openshift.api.model.WebHookTriggerBuilder(io.fabric8.openshift.api.model.WebHookTrigger, java.lang.Boolean);
    Code:
       0: aload_0
       1: invokespecial #8                  // Method io/fabric8/openshift/api/model/WebHookTriggerFluentImpl."<init>":()V
       4: aload_0
       5: aload_0
       6: putfield      #9                  // Field fluent:Lio/fabric8/openshift/api/model/WebHookTriggerFluent;
       9: aload_0
      10: aload_1
      11: invokevirtual #10                 // Method io/fabric8/openshift/api/model/WebHookTrigger.getAllowEnv:()Ljava/lang/Boolean;
      14: invokevirtual #17                 // Method withAllowEnv:(Ljava/lang/Boolean;)Lio/fabric8/openshift/api/model/WebHookTriggerFluent;
      17: pop
      18: aload_0
      19: aload_1
      20: invokevirtual #12                 // Method io/fabric8/openshift/api/model/WebHookTrigger.getSecret:()Ljava/lang/String;
      23: invokevirtual #18                 // Method withSecret:(Ljava/lang/String;)Lio/fabric8/openshift/api/model/WebHookTriggerFluent;
      26: pop
      27: aload_0
      28: aload_1
      29: invokevirtual #14                 // Method io/fabric8/openshift/api/model/WebHookTrigger.getSecretReference:()Lio/fabric8/openshift/api/model/SecretLocalReference;
      32: invokevirtual #19                 // Method withSecretReference:(Lio/fabric8/openshift/api/model/SecretLocalReference;)Lio/fabric8/openshift/api/model/WebHookTriggerFluent;
      35: pop
      36: aload_0
      37: aload_2
      38: putfield      #16                 // Field validationEnabled:Ljava/lang/Boolean;
      41: return

  public io.fabric8.openshift.api.model.WebHookTrigger build();
    Code:
       0: new           #3                  // class io/fabric8/openshift/api/model/WebHookTrigger
       3: dup
       4: aload_0
       5: getfield      #9                  // Field fluent:Lio/fabric8/openshift/api/model/WebHookTriggerFluent;
       8: invokeinterface #20,  1           // InterfaceMethod io/fabric8/openshift/api/model/WebHookTriggerFluent.isAllowEnv:()Ljava/lang/Boolean;
      13: aload_0
      14: getfield      #9                  // Field fluent:Lio/fabric8/openshift/api/model/WebHookTriggerFluent;
      17: invokeinterface #21,  1           // InterfaceMethod io/fabric8/openshift/api/model/WebHookTriggerFluent.getSecret:()Ljava/lang/String;
      22: aload_0
      23: getfield      #9                  // Field fluent:Lio/fabric8/openshift/api/model/WebHookTriggerFluent;
      26: invokeinterface #22,  1           // InterfaceMethod io/fabric8/openshift/api/model/WebHookTriggerFluent.getSecretReference:()Lio/fabric8/openshift/api/model/SecretLocalReference;
      31: invokespecial #23                 // Method io/fabric8/openshift/api/model/WebHookTrigger."<init>":(Ljava/lang/Boolean;Ljava/lang/String;Lio/fabric8/openshift/api/model/SecretLocalReference;)V
      34: astore_1
      35: aload_1
      36: areturn

  public boolean equals(java.lang.Object);
    Code:
       0: aload_0
       1: aload_1
       2: if_acmpne     7
       5: iconst_1
       6: ireturn
       7: aload_1
       8: ifnull        22
      11: aload_0
      12: invokevirtual #24                 // Method java/lang/Object.getClass:()Ljava/lang/Class;
      15: aload_1
      16: invokevirtual #24                 // Method java/lang/Object.getClass:()Ljava/lang/Class;
      19: if_acmpeq     24
      22: iconst_0
      23: ireturn
      24: aload_0
      25: aload_1
      26: invokespecial #25                 // Method io/fabric8/openshift/api/model/WebHookTriggerFluentImpl.equals:(Ljava/lang/Object;)Z
      29: ifne          34
      32: iconst_0
      33: ireturn
      34: aload_1
      35: checkcast     #26                 // class io/fabric8/openshift/api/model/WebHookTriggerBuilder
      38: astore_2
      39: aload_0
      40: getfield      #9                  // Field fluent:Lio/fabric8/openshift/api/model/WebHookTriggerFluent;
      43: ifnull        71
      46: aload_0
      47: getfield      #9                  // Field fluent:Lio/fabric8/openshift/api/model/WebHookTriggerFluent;
      50: aload_0
      51: if_acmpeq     71
      54: aload_0
      55: getfield      #9                  // Field fluent:Lio/fabric8/openshift/api/model/WebHookTriggerFluent;
      58: aload_2
      59: getfield      #9                  // Field fluent:Lio/fabric8/openshift/api/model/WebHookTriggerFluent;
      62: invokevirtual #27                 // Method java/lang/Object.equals:(Ljava/lang/Object;)Z
      65: ifne          88
      68: goto          86
      71: aload_2
      72: getfield      #9                  // Field fluent:Lio/fabric8/openshift/api/model/WebHookTriggerFluent;
      75: ifnull        88
      78: aload_0
      79: getfield      #9                  // Field fluent:Lio/fabric8/openshift/api/model/WebHookTriggerFluent;
      82: aload_0
      83: if_acmpeq     88
      86: iconst_0
      87: ireturn
      88: aload_0
      89: getfield      #16                 // Field validationEnabled:Ljava/lang/Boolean;
      92: ifnull        112
      95: aload_0
      96: getfield      #16                 // Field validationEnabled:Ljava/lang/Boolean;
      99: aload_2
     100: getfield      #16                 // Field validationEnabled:Ljava/lang/Boolean;
     103: invokevirtual #28                 // Method java/lang/Boolean.equals:(Ljava/lang/Object;)Z
     106: ifne          121
     109: goto          119
     112: aload_2
     113: getfield      #16                 // Field validationEnabled:Ljava/lang/Boolean;
     116: ifnull        121
     119: iconst_0
     120: ireturn
     121: iconst_1
     122: ireturn

  public java.lang.Object build();
    Code:
       0: aload_0
       1: invokevirtual #29                 // Method build:()Lio/fabric8/openshift/api/model/WebHookTrigger;
       4: areturn
}
