public class org.bouncycastle.x509.util.LDAPStoreHelper {
  private org.bouncycastle.jce.X509LDAPCertStoreParameters params;

  private static java.lang.String LDAP_PROVIDER;

  private static java.lang.String REFERRALS_IGNORE;

  private static final java.lang.String SEARCH_SECURITY_LEVEL;

  private static final java.lang.String URL_CONTEXT_PREFIX;

  private java.util.Map cacheMap;

  private static int cacheSize;

  private static long lifeTime;

  public org.bouncycastle.x509.util.LDAPStoreHelper(org.bouncycastle.jce.X509LDAPCertStoreParameters);
    Code:
       0: aload_0
       1: invokespecial #503                // Method java/lang/Object."<init>":()V
       4: aload_0
       5: new           #265                // class java/util/HashMap
       8: dup
       9: getstatic     #495                // Field cacheSize:I
      12: invokespecial #527                // Method java/util/HashMap."<init>":(I)V
      15: putfield      #499                // Field cacheMap:Ljava/util/Map;
      18: aload_0
      19: aload_1
      20: putfield      #500                // Field params:Lorg/bouncycastle/jce/X509LDAPCertStoreParameters;
      23: return

  private javax.naming.directory.DirContext connectLDAP() throws javax.naming.NamingException;
    Code:
       0: new           #271                // class java/util/Properties
       3: dup
       4: invokespecial #529                // Method java/util/Properties."<init>":()V
       7: astore_1
       8: aload_1
       9: ldc           #19                 // String java.naming.factory.initial
      11: getstatic     #497                // Field LDAP_PROVIDER:Ljava/lang/String;
      14: invokevirtual #530                // Method java/util/Properties.setProperty:(Ljava/lang/String;Ljava/lang/String;)Ljava/lang/Object;
      17: pop
      18: aload_1
      19: ldc           #18                 // String java.naming.batchsize
      21: ldc           #9                  // String 0
      23: invokevirtual #530                // Method java/util/Properties.setProperty:(Ljava/lang/String;Ljava/lang/String;)Ljava/lang/Object;
      26: pop
      27: aload_1
      28: ldc           #21                 // String java.naming.provider.url
      30: aload_0
      31: getfield      #500                // Field params:Lorg/bouncycastle/jce/X509LDAPCertStoreParameters;
      34: invokevirtual #574                // Method org/bouncycastle/jce/X509LDAPCertStoreParameters.getLdapURL:()Ljava/lang/String;
      37: invokevirtual #530                // Method java/util/Properties.setProperty:(Ljava/lang/String;Ljava/lang/String;)Ljava/lang/Object;
      40: pop
      41: aload_1
      42: ldc           #20                 // String java.naming.factory.url.pkgs
      44: ldc           #15                 // String com.sun.jndi.url
      46: invokevirtual #530                // Method java/util/Properties.setProperty:(Ljava/lang/String;Ljava/lang/String;)Ljava/lang/Object;
      49: pop
      50: aload_1
      51: ldc           #22                 // String java.naming.referral
      53: getstatic     #498                // Field REFERRALS_IGNORE:Ljava/lang/String;
      56: invokevirtual #530                // Method java/util/Properties.setProperty:(Ljava/lang/String;Ljava/lang/String;)Ljava/lang/Object;
      59: pop
      60: aload_1
      61: ldc           #23                 // String java.naming.security.authentication
      63: ldc           #24                 // String none
      65: invokevirtual #530                // Method java/util/Properties.setProperty:(Ljava/lang/String;Ljava/lang/String;)Ljava/lang/Object;
      68: pop
      69: new           #278                // class javax/naming/directory/InitialDirContext
      72: dup
      73: aload_1
      74: invokespecial #531                // Method javax/naming/directory/InitialDirContext."<init>":(Ljava/util/Hashtable;)V
      77: astore_2
      78: aload_2
      79: areturn

  private java.lang.String parseDN(java.lang.String, java.lang.String);
    Code:
       0: aload_1
       1: astore_3
       2: aload_3
       3: invokevirtual #509                // Method java/lang/String.toLowerCase:()Ljava/lang/String;
       6: new           #255                // class java/lang/StringBuilder
       9: dup
      10: invokespecial #516                // Method java/lang/StringBuilder."<init>":()V
      13: aload_2
      14: invokevirtual #509                // Method java/lang/String.toLowerCase:()Ljava/lang/String;
      17: invokevirtual #518                // Method java/lang/StringBuilder.append:(Ljava/lang/String;)Ljava/lang/StringBuilder;
      20: ldc           #10                 // String =
      22: invokevirtual #518                // Method java/lang/StringBuilder.append:(Ljava/lang/String;)Ljava/lang/StringBuilder;
      25: invokevirtual #517                // Method java/lang/StringBuilder.toString:()Ljava/lang/String;
      28: invokevirtual #512                // Method java/lang/String.indexOf:(Ljava/lang/String;)I
      31: istore        4
      33: iload         4
      35: iconst_m1
      36: if_icmpne     42
      39: ldc           #1                  // String
      41: areturn
      42: aload_3
      43: iload         4
      45: aload_2
      46: invokevirtual #504                // Method java/lang/String.length:()I
      49: iadd
      50: invokevirtual #510                // Method java/lang/String.substring:(I)Ljava/lang/String;
      53: astore_3
      54: aload_3
      55: bipush        44
      57: invokevirtual #506                // Method java/lang/String.indexOf:(I)I
      60: istore        5
      62: iload         5
      64: iconst_m1
      65: if_icmpne     74
      68: aload_3
      69: invokevirtual #504                // Method java/lang/String.length:()I
      72: istore        5
      74: aload_3
      75: iload         5
      77: iconst_1
      78: isub
      79: invokevirtual #505                // Method java/lang/String.charAt:(I)C
      82: bipush        92
      84: if_icmpne     114
      87: aload_3
      88: bipush        44
      90: iload         5
      92: iconst_1
      93: iadd
      94: invokevirtual #507                // Method java/lang/String.indexOf:(II)I
      97: istore        5
      99: iload         5
     101: iconst_m1
     102: if_icmpne     74
     105: aload_3
     106: invokevirtual #504                // Method java/lang/String.length:()I
     109: istore        5
     111: goto          74
     114: aload_3
     115: iconst_0
     116: iload         5
     118: invokevirtual #511                // Method java/lang/String.substring:(II)Ljava/lang/String;
     121: astore_3
     122: aload_3
     123: bipush        61
     125: invokevirtual #506                // Method java/lang/String.indexOf:(I)I
     128: istore        4
     130: aload_3
     131: iload         4
     133: iconst_1
     134: iadd
     135: invokevirtual #510                // Method java/lang/String.substring:(I)Ljava/lang/String;
     138: astore_3
     139: aload_3
     140: iconst_0
     141: invokevirtual #505                // Method java/lang/String.charAt:(I)C
     144: bipush        32
     146: if_icmpne     155
     149: aload_3
     150: iconst_1
     151: invokevirtual #510                // Method java/lang/String.substring:(I)Ljava/lang/String;
     154: astore_3
     155: aload_3
     156: ldc           #2                  // String \"
     158: invokevirtual #514                // Method java/lang/String.startsWith:(Ljava/lang/String;)Z
     161: ifeq          170
     164: aload_3
     165: iconst_1
     166: invokevirtual #510                // Method java/lang/String.substring:(I)Ljava/lang/String;
     169: astore_3
     170: aload_3
     171: ldc           #2                  // String \"
     173: invokevirtual #513                // Method java/lang/String.endsWith:(Ljava/lang/String;)Z
     176: ifeq          191
     179: aload_3
     180: iconst_0
     181: aload_3
     182: invokevirtual #504                // Method java/lang/String.length:()I
     185: iconst_1
     186: isub
     187: invokevirtual #511                // Method java/lang/String.substring:(II)Ljava/lang/String;
     190: astore_3
     191: aload_3
     192: areturn

  private java.util.Set createCerts(java.util.List, org.bouncycastle.x509.X509CertStoreSelector) throws org.bouncycastle.util.StoreException;
    Code:
       0: new           #266                // class java/util/HashSet
       3: dup
       4: invokespecial #528                // Method java/util/HashSet."<init>":()V
       7: astore_3
       8: aload_1
       9: invokeinterface #645,  1          // InterfaceMethod java/util/List.iterator:()Ljava/util/Iterator;
      14: astore        4
      16: new           #289                // class org/bouncycastle/jce/provider/X509CertParser
      19: dup
      20: invokespecial #588                // Method org/bouncycastle/jce/provider/X509CertParser."<init>":()V
      23: astore        5
      25: aload         4
      27: invokeinterface #639,  1          // InterfaceMethod java/util/Iterator.hasNext:()Z
      32: ifeq          96
      35: aload         5
      37: new           #250                // class java/io/ByteArrayInputStream
      40: dup
      41: aload         4
      43: invokeinterface #640,  1          // InterfaceMethod java/util/Iterator.next:()Ljava/lang/Object;
      48: checkcast     #249                // class "[B"
      51: checkcast     #249                // class "[B"
      54: invokespecial #501                // Method java/io/ByteArrayInputStream."<init>":([B)V
      57: invokevirtual #589                // Method org/bouncycastle/jce/provider/X509CertParser.engineInit:(Ljava/io/InputStream;)V
      60: aload         5
      62: invokevirtual #590                // Method org/bouncycastle/jce/provider/X509CertParser.engineRead:()Ljava/lang/Object;
      65: checkcast     #261                // class java/security/cert/X509Certificate
      68: astore        6
      70: aload_2
      71: aload         6
      73: invokevirtual #613                // Method org/bouncycastle/x509/X509CertStoreSelector.match:(Ljava/lang/Object;)Z
      76: ifeq          88
      79: aload_3
      80: aload         6
      82: invokeinterface #655,  2          // InterfaceMethod java/util/Set.add:(Ljava/lang/Object;)Z
      87: pop
      88: goto          25
      91: astore        6
      93: goto          25
      96: aload_3
      97: areturn
    Exception table:
       from    to  target type
          35    88    91   Class java/lang/Exception

  private java.util.List certSubjectSerialSearch(org.bouncycastle.x509.X509CertStoreSelector, java.lang.String[], java.lang.String[], java.lang.String[]) throws org.bouncycastle.util.StoreException;
    Code:
       0: new           #263                // class java/util/ArrayList
       3: dup
       4: invokespecial #526                // Method java/util/ArrayList."<init>":()V
       7: astore        5
       9: aconst_null
      10: astore        6
      12: aconst_null
      13: astore        7
      15: aload_0
      16: aload_1
      17: invokespecial #620                // Method getSubjectAsString:(Lorg/bouncycastle/x509/X509CertStoreSelector;)Ljava/lang/String;
      20: astore        6
      22: aload_1
      23: invokevirtual #614                // Method org/bouncycastle/x509/X509CertStoreSelector.getSerialNumber:()Ljava/math/BigInteger;
      26: ifnull        38
      29: aload_1
      30: invokevirtual #614                // Method org/bouncycastle/x509/X509CertStoreSelector.getSerialNumber:()Ljava/math/BigInteger;
      33: invokevirtual #520                // Method java/math/BigInteger.toString:()Ljava/lang/String;
      36: astore        7
      38: aload_1
      39: invokevirtual #615                // Method org/bouncycastle/x509/X509CertStoreSelector.getCertificate:()Ljava/security/cert/X509Certificate;
      42: ifnull        71
      45: aload_1
      46: invokevirtual #615                // Method org/bouncycastle/x509/X509CertStoreSelector.getCertificate:()Ljava/security/cert/X509Certificate;
      49: invokevirtual #523                // Method java/security/cert/X509Certificate.getSubjectX500Principal:()Ljavax/security/auth/x500/X500Principal;
      52: ldc           #12                 // String RFC1779
      54: invokevirtual #538                // Method javax/security/auth/x500/X500Principal.getName:(Ljava/lang/String;)Ljava/lang/String;
      57: astore        6
      59: aload_1
      60: invokevirtual #615                // Method org/bouncycastle/x509/X509CertStoreSelector.getCertificate:()Ljava/security/cert/X509Certificate;
      63: invokevirtual #521                // Method java/security/cert/X509Certificate.getSerialNumber:()Ljava/math/BigInteger;
      66: invokevirtual #520                // Method java/math/BigInteger.toString:()Ljava/lang/String;
      69: astore        7
      71: aconst_null
      72: astore        8
      74: aload         6
      76: ifnull        148
      79: iconst_0
      80: istore        9
      82: iload         9
      84: aload         4
      86: arraylength
      87: if_icmpge     148
      90: aload_0
      91: aload         6
      93: aload         4
      95: iload         9
      97: aaload
      98: invokespecial #624                // Method parseDN:(Ljava/lang/String;Ljava/lang/String;)Ljava/lang/String;
     101: astore        8
     103: aload         5
     105: aload_0
     106: aload_3
     107: new           #255                // class java/lang/StringBuilder
     110: dup
     111: invokespecial #516                // Method java/lang/StringBuilder."<init>":()V
     114: ldc           #7                  // String *
     116: invokevirtual #518                // Method java/lang/StringBuilder.append:(Ljava/lang/String;)Ljava/lang/StringBuilder;
     119: aload         8
     121: invokevirtual #518                // Method java/lang/StringBuilder.append:(Ljava/lang/String;)Ljava/lang/StringBuilder;
     124: ldc           #7                  // String *
     126: invokevirtual #518                // Method java/lang/StringBuilder.append:(Ljava/lang/String;)Ljava/lang/StringBuilder;
     129: invokevirtual #517                // Method java/lang/StringBuilder.toString:()Ljava/lang/String;
     132: aload_2
     133: invokespecial #629                // Method search:([Ljava/lang/String;Ljava/lang/String;[Ljava/lang/String;)Ljava/util/List;
     136: invokeinterface #644,  2          // InterfaceMethod java/util/List.addAll:(Ljava/util/Collection;)Z
     141: pop
     142: iinc          9, 1
     145: goto          82
     148: aload         7
     150: ifnull        193
     153: aload_0
     154: getfield      #500                // Field params:Lorg/bouncycastle/jce/X509LDAPCertStoreParameters;
     157: invokevirtual #576                // Method org/bouncycastle/jce/X509LDAPCertStoreParameters.getSearchForSerialNumberIn:()Ljava/lang/String;
     160: ifnull        193
     163: aload         7
     165: astore        8
     167: aload         5
     169: aload_0
     170: aload_0
     171: aload_0
     172: getfield      #500                // Field params:Lorg/bouncycastle/jce/X509LDAPCertStoreParameters;
     175: invokevirtual #576                // Method org/bouncycastle/jce/X509LDAPCertStoreParameters.getSearchForSerialNumberIn:()Ljava/lang/String;
     178: invokespecial #619                // Method splitString:(Ljava/lang/String;)[Ljava/lang/String;
     181: aload         8
     183: aload_2
     184: invokespecial #629                // Method search:([Ljava/lang/String;Ljava/lang/String;[Ljava/lang/String;)Ljava/util/List;
     187: invokeinterface #644,  2          // InterfaceMethod java/util/List.addAll:(Ljava/util/Collection;)Z
     192: pop
     193: aload         7
     195: ifnonnull     219
     198: aload         6
     200: ifnonnull     219
     203: aload         5
     205: aload_0
     206: aload_3
     207: ldc           #7                  // String *
     209: aload_2
     210: invokespecial #629                // Method search:([Ljava/lang/String;Ljava/lang/String;[Ljava/lang/String;)Ljava/util/List;
     213: invokeinterface #644,  2          // InterfaceMethod java/util/List.addAll:(Ljava/util/Collection;)Z
     218: pop
     219: aload         5
     221: areturn

  private java.util.List crossCertificatePairSubjectSearch(org.bouncycastle.x509.X509CertPairStoreSelector, java.lang.String[], java.lang.String[], java.lang.String[]) throws org.bouncycastle.util.StoreException;
    Code:
       0: new           #263                // class java/util/ArrayList
       3: dup
       4: invokespecial #526                // Method java/util/ArrayList."<init>":()V
       7: astore        5
       9: aconst_null
      10: astore        6
      12: aload_1
      13: invokevirtual #607                // Method org/bouncycastle/x509/X509CertPairStoreSelector.getForwardSelector:()Lorg/bouncycastle/x509/X509CertStoreSelector;
      16: ifnull        29
      19: aload_0
      20: aload_1
      21: invokevirtual #607                // Method org/bouncycastle/x509/X509CertPairStoreSelector.getForwardSelector:()Lorg/bouncycastle/x509/X509CertStoreSelector;
      24: invokespecial #620                // Method getSubjectAsString:(Lorg/bouncycastle/x509/X509CertStoreSelector;)Ljava/lang/String;
      27: astore        6
      29: aload_1
      30: invokevirtual #610                // Method org/bouncycastle/x509/X509CertPairStoreSelector.getCertPair:()Lorg/bouncycastle/x509/X509CertificatePair;
      33: ifnull        63
      36: aload_1
      37: invokevirtual #610                // Method org/bouncycastle/x509/X509CertPairStoreSelector.getCertPair:()Lorg/bouncycastle/x509/X509CertificatePair;
      40: invokevirtual #616                // Method org/bouncycastle/x509/X509CertificatePair.getForward:()Ljava/security/cert/X509Certificate;
      43: ifnull        63
      46: aload_1
      47: invokevirtual #610                // Method org/bouncycastle/x509/X509CertPairStoreSelector.getCertPair:()Lorg/bouncycastle/x509/X509CertificatePair;
      50: invokevirtual #616                // Method org/bouncycastle/x509/X509CertificatePair.getForward:()Ljava/security/cert/X509Certificate;
      53: invokevirtual #523                // Method java/security/cert/X509Certificate.getSubjectX500Principal:()Ljavax/security/auth/x500/X500Principal;
      56: ldc           #12                 // String RFC1779
      58: invokevirtual #538                // Method javax/security/auth/x500/X500Principal.getName:(Ljava/lang/String;)Ljava/lang/String;
      61: astore        6
      63: aconst_null
      64: astore        7
      66: aload         6
      68: ifnull        140
      71: iconst_0
      72: istore        8
      74: iload         8
      76: aload         4
      78: arraylength
      79: if_icmpge     140
      82: aload_0
      83: aload         6
      85: aload         4
      87: iload         8
      89: aaload
      90: invokespecial #624                // Method parseDN:(Ljava/lang/String;Ljava/lang/String;)Ljava/lang/String;
      93: astore        7
      95: aload         5
      97: aload_0
      98: aload_3
      99: new           #255                // class java/lang/StringBuilder
     102: dup
     103: invokespecial #516                // Method java/lang/StringBuilder."<init>":()V
     106: ldc           #7                  // String *
     108: invokevirtual #518                // Method java/lang/StringBuilder.append:(Ljava/lang/String;)Ljava/lang/StringBuilder;
     111: aload         7
     113: invokevirtual #518                // Method java/lang/StringBuilder.append:(Ljava/lang/String;)Ljava/lang/StringBuilder;
     116: ldc           #7                  // String *
     118: invokevirtual #518                // Method java/lang/StringBuilder.append:(Ljava/lang/String;)Ljava/lang/StringBuilder;
     121: invokevirtual #517                // Method java/lang/StringBuilder.toString:()Ljava/lang/String;
     124: aload_2
     125: invokespecial #629                // Method search:([Ljava/lang/String;Ljava/lang/String;[Ljava/lang/String;)Ljava/util/List;
     128: invokeinterface #644,  2          // InterfaceMethod java/util/List.addAll:(Ljava/util/Collection;)Z
     133: pop
     134: iinc          8, 1
     137: goto          74
     140: aload         6
     142: ifnonnull     161
     145: aload         5
     147: aload_0
     148: aload_3
     149: ldc           #7                  // String *
     151: aload_2
     152: invokespecial #629                // Method search:([Ljava/lang/String;Ljava/lang/String;[Ljava/lang/String;)Ljava/util/List;
     155: invokeinterface #644,  2          // InterfaceMethod java/util/List.addAll:(Ljava/util/Collection;)Z
     160: pop
     161: aload         5
     163: areturn

  private java.util.List attrCertSubjectSerialSearch(org.bouncycastle.x509.X509AttributeCertStoreSelector, java.lang.String[], java.lang.String[], java.lang.String[]) throws org.bouncycastle.util.StoreException;
    Code:
       0: new           #263                // class java/util/ArrayList
       3: dup
       4: invokespecial #526                // Method java/util/ArrayList."<init>":()V
       7: astore        5
       9: aconst_null
      10: astore        6
      12: aconst_null
      13: astore        7
      15: new           #266                // class java/util/HashSet
      18: dup
      19: invokespecial #528                // Method java/util/HashSet."<init>":()V
      22: astore        8
      24: aconst_null
      25: astore        9
      27: aload_1
      28: invokevirtual #598                // Method org/bouncycastle/x509/X509AttributeCertStoreSelector.getHolder:()Lorg/bouncycastle/x509/AttributeCertificateHolder;
      31: ifnull        81
      34: aload_1
      35: invokevirtual #598                // Method org/bouncycastle/x509/X509AttributeCertStoreSelector.getHolder:()Lorg/bouncycastle/x509/AttributeCertificateHolder;
      38: invokevirtual #592                // Method org/bouncycastle/x509/AttributeCertificateHolder.getSerialNumber:()Ljava/math/BigInteger;
      41: ifnull        62
      44: aload         8
      46: aload_1
      47: invokevirtual #598                // Method org/bouncycastle/x509/X509AttributeCertStoreSelector.getHolder:()Lorg/bouncycastle/x509/AttributeCertificateHolder;
      50: invokevirtual #592                // Method org/bouncycastle/x509/AttributeCertificateHolder.getSerialNumber:()Ljava/math/BigInteger;
      53: invokevirtual #520                // Method java/math/BigInteger.toString:()Ljava/lang/String;
      56: invokeinterface #636,  2          // InterfaceMethod java/util/Collection.add:(Ljava/lang/Object;)Z
      61: pop
      62: aload_1
      63: invokevirtual #598                // Method org/bouncycastle/x509/X509AttributeCertStoreSelector.getHolder:()Lorg/bouncycastle/x509/AttributeCertificateHolder;
      66: invokevirtual #593                // Method org/bouncycastle/x509/AttributeCertificateHolder.getEntityNames:()[Ljava/security/Principal;
      69: ifnull        81
      72: aload_1
      73: invokevirtual #598                // Method org/bouncycastle/x509/X509AttributeCertStoreSelector.getHolder:()Lorg/bouncycastle/x509/AttributeCertificateHolder;
      76: invokevirtual #593                // Method org/bouncycastle/x509/AttributeCertificateHolder.getEntityNames:()[Ljava/security/Principal;
      79: astore        9
      81: aload_1
      82: invokevirtual #599                // Method org/bouncycastle/x509/X509AttributeCertStoreSelector.getAttributeCert:()Lorg/bouncycastle/x509/X509AttributeCertificate;
      85: ifnull        137
      88: aload_1
      89: invokevirtual #599                // Method org/bouncycastle/x509/X509AttributeCertStoreSelector.getAttributeCert:()Lorg/bouncycastle/x509/X509AttributeCertificate;
      92: invokeinterface #666,  1          // InterfaceMethod org/bouncycastle/x509/X509AttributeCertificate.getHolder:()Lorg/bouncycastle/x509/AttributeCertificateHolder;
      97: invokevirtual #593                // Method org/bouncycastle/x509/AttributeCertificateHolder.getEntityNames:()[Ljava/security/Principal;
     100: ifnull        117
     103: aload_1
     104: invokevirtual #599                // Method org/bouncycastle/x509/X509AttributeCertStoreSelector.getAttributeCert:()Lorg/bouncycastle/x509/X509AttributeCertificate;
     107: invokeinterface #666,  1          // InterfaceMethod org/bouncycastle/x509/X509AttributeCertificate.getHolder:()Lorg/bouncycastle/x509/AttributeCertificateHolder;
     112: invokevirtual #593                // Method org/bouncycastle/x509/AttributeCertificateHolder.getEntityNames:()[Ljava/security/Principal;
     115: astore        9
     117: aload         8
     119: aload_1
     120: invokevirtual #599                // Method org/bouncycastle/x509/X509AttributeCertStoreSelector.getAttributeCert:()Lorg/bouncycastle/x509/X509AttributeCertificate;
     123: invokeinterface #665,  1          // InterfaceMethod org/bouncycastle/x509/X509AttributeCertificate.getSerialNumber:()Ljava/math/BigInteger;
     128: invokevirtual #520                // Method java/math/BigInteger.toString:()Ljava/lang/String;
     131: invokeinterface #636,  2          // InterfaceMethod java/util/Collection.add:(Ljava/lang/Object;)Z
     136: pop
     137: aload         9
     139: ifnull        180
     142: aload         9
     144: iconst_0
     145: aaload
     146: instanceof    #281                // class javax/security/auth/x500/X500Principal
     149: ifeq          169
     152: aload         9
     154: iconst_0
     155: aaload
     156: checkcast     #281                // class javax/security/auth/x500/X500Principal
     159: ldc           #12                 // String RFC1779
     161: invokevirtual #538                // Method javax/security/auth/x500/X500Principal.getName:(Ljava/lang/String;)Ljava/lang/String;
     164: astore        6
     166: goto          180
     169: aload         9
     171: iconst_0
     172: aaload
     173: invokeinterface #634,  1          // InterfaceMethod java/security/Principal.getName:()Ljava/lang/String;
     178: astore        6
     180: aload_1
     181: invokevirtual #597                // Method org/bouncycastle/x509/X509AttributeCertStoreSelector.getSerialNumber:()Ljava/math/BigInteger;
     184: ifnull        202
     187: aload         8
     189: aload_1
     190: invokevirtual #597                // Method org/bouncycastle/x509/X509AttributeCertStoreSelector.getSerialNumber:()Ljava/math/BigInteger;
     193: invokevirtual #520                // Method java/math/BigInteger.toString:()Ljava/lang/String;
     196: invokeinterface #636,  2          // InterfaceMethod java/util/Collection.add:(Ljava/lang/Object;)Z
     201: pop
     202: aconst_null
     203: astore        10
     205: aload         6
     207: ifnull        279
     210: iconst_0
     211: istore        11
     213: iload         11
     215: aload         4
     217: arraylength
     218: if_icmpge     279
     221: aload_0
     222: aload         6
     224: aload         4
     226: iload         11
     228: aaload
     229: invokespecial #624                // Method parseDN:(Ljava/lang/String;Ljava/lang/String;)Ljava/lang/String;
     232: astore        10
     234: aload         5
     236: aload_0
     237: aload_3
     238: new           #255                // class java/lang/StringBuilder
     241: dup
     242: invokespecial #516                // Method java/lang/StringBuilder."<init>":()V
     245: ldc           #7                  // String *
     247: invokevirtual #518                // Method java/lang/StringBuilder.append:(Ljava/lang/String;)Ljava/lang/StringBuilder;
     250: aload         10
     252: invokevirtual #518                // Method java/lang/StringBuilder.append:(Ljava/lang/String;)Ljava/lang/StringBuilder;
     255: ldc           #7                  // String *
     257: invokevirtual #518                // Method java/lang/StringBuilder.append:(Ljava/lang/String;)Ljava/lang/StringBuilder;
     260: invokevirtual #517                // Method java/lang/StringBuilder.toString:()Ljava/lang/String;
     263: aload_2
     264: invokespecial #629                // Method search:([Ljava/lang/String;Ljava/lang/String;[Ljava/lang/String;)Ljava/util/List;
     267: invokeinterface #644,  2          // InterfaceMethod java/util/List.addAll:(Ljava/util/Collection;)Z
     272: pop
     273: iinc          11, 1
     276: goto          213
     279: aload         8
     281: invokeinterface #635,  1          // InterfaceMethod java/util/Collection.size:()I
     286: ifle          359
     289: aload_0
     290: getfield      #500                // Field params:Lorg/bouncycastle/jce/X509LDAPCertStoreParameters;
     293: invokevirtual #576                // Method org/bouncycastle/jce/X509LDAPCertStoreParameters.getSearchForSerialNumberIn:()Ljava/lang/String;
     296: ifnull        359
     299: aload         8
     301: invokeinterface #638,  1          // InterfaceMethod java/util/Collection.iterator:()Ljava/util/Iterator;
     306: astore        11
     308: aload         11
     310: invokeinterface #639,  1          // InterfaceMethod java/util/Iterator.hasNext:()Z
     315: ifeq          359
     318: aload         11
     320: invokeinterface #640,  1          // InterfaceMethod java/util/Iterator.next:()Ljava/lang/Object;
     325: checkcast     #254                // class java/lang/String
     328: astore        7
     330: aload         5
     332: aload_0
     333: aload_0
     334: aload_0
     335: getfield      #500                // Field params:Lorg/bouncycastle/jce/X509LDAPCertStoreParameters;
     338: invokevirtual #576                // Method org/bouncycastle/jce/X509LDAPCertStoreParameters.getSearchForSerialNumberIn:()Ljava/lang/String;
     341: invokespecial #619                // Method splitString:(Ljava/lang/String;)[Ljava/lang/String;
     344: aload         7
     346: aload_2
     347: invokespecial #629                // Method search:([Ljava/lang/String;Ljava/lang/String;[Ljava/lang/String;)Ljava/util/List;
     350: invokeinterface #644,  2          // InterfaceMethod java/util/List.addAll:(Ljava/util/Collection;)Z
     355: pop
     356: goto          308
     359: aload         8
     361: invokeinterface #635,  1          // InterfaceMethod java/util/Collection.size:()I
     366: ifne          390
     369: aload         6
     371: ifnonnull     390
     374: aload         5
     376: aload_0
     377: aload_3
     378: ldc           #7                  // String *
     380: aload_2
     381: invokespecial #629                // Method search:([Ljava/lang/String;Ljava/lang/String;[Ljava/lang/String;)Ljava/util/List;
     384: invokeinterface #644,  2          // InterfaceMethod java/util/List.addAll:(Ljava/util/Collection;)Z
     389: pop
     390: aload         5
     392: areturn

  private java.util.List cRLIssuerSearch(org.bouncycastle.x509.X509CRLStoreSelector, java.lang.String[], java.lang.String[], java.lang.String[]) throws org.bouncycastle.util.StoreException;
    Code:
       0: new           #263                // class java/util/ArrayList
       3: dup
       4: invokespecial #526                // Method java/util/ArrayList."<init>":()V
       7: astore        5
       9: aconst_null
      10: astore        6
      12: new           #266                // class java/util/HashSet
      15: dup
      16: invokespecial #528                // Method java/util/HashSet."<init>":()V
      19: astore        7
      21: aload_1
      22: invokevirtual #603                // Method org/bouncycastle/x509/X509CRLStoreSelector.getIssuers:()Ljava/util/Collection;
      25: ifnull        40
      28: aload         7
      30: aload_1
      31: invokevirtual #603                // Method org/bouncycastle/x509/X509CRLStoreSelector.getIssuers:()Ljava/util/Collection;
      34: invokeinterface #637,  2          // InterfaceMethod java/util/Collection.addAll:(Ljava/util/Collection;)Z
      39: pop
      40: aload_1
      41: invokevirtual #602                // Method org/bouncycastle/x509/X509CRLStoreSelector.getCertificateChecking:()Ljava/security/cert/X509Certificate;
      44: ifnull        63
      47: aload         7
      49: aload_0
      50: aload_1
      51: invokevirtual #602                // Method org/bouncycastle/x509/X509CRLStoreSelector.getCertificateChecking:()Ljava/security/cert/X509Certificate;
      54: invokespecial #623                // Method getCertificateIssuer:(Ljava/security/cert/X509Certificate;)Ljavax/security/auth/x500/X500Principal;
      57: invokeinterface #636,  2          // InterfaceMethod java/util/Collection.add:(Ljava/lang/Object;)Z
      62: pop
      63: aload_1
      64: invokevirtual #604                // Method org/bouncycastle/x509/X509CRLStoreSelector.getAttrCertificateChecking:()Lorg/bouncycastle/x509/X509AttributeCertificate;
      67: ifnull        125
      70: aload_1
      71: invokevirtual #604                // Method org/bouncycastle/x509/X509CRLStoreSelector.getAttrCertificateChecking:()Lorg/bouncycastle/x509/X509AttributeCertificate;
      74: invokeinterface #667,  1          // InterfaceMethod org/bouncycastle/x509/X509AttributeCertificate.getIssuer:()Lorg/bouncycastle/x509/AttributeCertificateIssuer;
      79: invokevirtual #594                // Method org/bouncycastle/x509/AttributeCertificateIssuer.getPrincipals:()[Ljava/security/Principal;
      82: astore        8
      84: iconst_0
      85: istore        9
      87: iload         9
      89: aload         8
      91: arraylength
      92: if_icmpge     125
      95: aload         8
      97: iload         9
      99: aaload
     100: instanceof    #281                // class javax/security/auth/x500/X500Principal
     103: ifeq          119
     106: aload         7
     108: aload         8
     110: iload         9
     112: aaload
     113: invokeinterface #636,  2          // InterfaceMethod java/util/Collection.add:(Ljava/lang/Object;)Z
     118: pop
     119: iinc          9, 1
     122: goto          87
     125: aload         7
     127: invokeinterface #638,  1          // InterfaceMethod java/util/Collection.iterator:()Ljava/util/Iterator;
     132: astore        8
     134: aload         8
     136: invokeinterface #639,  1          // InterfaceMethod java/util/Iterator.hasNext:()Z
     141: ifeq          236
     144: aload         8
     146: invokeinterface #640,  1          // InterfaceMethod java/util/Iterator.next:()Ljava/lang/Object;
     151: checkcast     #281                // class javax/security/auth/x500/X500Principal
     154: ldc           #12                 // String RFC1779
     156: invokevirtual #538                // Method javax/security/auth/x500/X500Principal.getName:(Ljava/lang/String;)Ljava/lang/String;
     159: astore        6
     161: aconst_null
     162: astore        9
     164: iconst_0
     165: istore        10
     167: iload         10
     169: aload         4
     171: arraylength
     172: if_icmpge     233
     175: aload_0
     176: aload         6
     178: aload         4
     180: iload         10
     182: aaload
     183: invokespecial #624                // Method parseDN:(Ljava/lang/String;Ljava/lang/String;)Ljava/lang/String;
     186: astore        9
     188: aload         5
     190: aload_0
     191: aload_3
     192: new           #255                // class java/lang/StringBuilder
     195: dup
     196: invokespecial #516                // Method java/lang/StringBuilder."<init>":()V
     199: ldc           #7                  // String *
     201: invokevirtual #518                // Method java/lang/StringBuilder.append:(Ljava/lang/String;)Ljava/lang/StringBuilder;
     204: aload         9
     206: invokevirtual #518                // Method java/lang/StringBuilder.append:(Ljava/lang/String;)Ljava/lang/StringBuilder;
     209: ldc           #7                  // String *
     211: invokevirtual #518                // Method java/lang/StringBuilder.append:(Ljava/lang/String;)Ljava/lang/StringBuilder;
     214: invokevirtual #517                // Method java/lang/StringBuilder.toString:()Ljava/lang/String;
     217: aload_2
     218: invokespecial #629                // Method search:([Ljava/lang/String;Ljava/lang/String;[Ljava/lang/String;)Ljava/util/List;
     221: invokeinterface #644,  2          // InterfaceMethod java/util/List.addAll:(Ljava/util/Collection;)Z
     226: pop
     227: iinc          10, 1
     230: goto          167
     233: goto          134
     236: aload         6
     238: ifnonnull     257
     241: aload         5
     243: aload_0
     244: aload_3
     245: ldc           #7                  // String *
     247: aload_2
     248: invokespecial #629                // Method search:([Ljava/lang/String;Ljava/lang/String;[Ljava/lang/String;)Ljava/util/List;
     251: invokeinterface #644,  2          // InterfaceMethod java/util/List.addAll:(Ljava/util/Collection;)Z
     256: pop
     257: aload         5
     259: areturn

  private java.util.List search(java.lang.String[], java.lang.String, java.lang.String[]) throws org.bouncycastle.util.StoreException;
    Code:
       0: aconst_null
       1: astore        4
       3: aload_1
       4: ifnonnull     13
       7: aconst_null
       8: astore        4
      10: goto          115
      13: ldc           #1                  // String
      15: astore        4
      17: aload_2
      18: ldc           #8                  // String **
      20: invokevirtual #508                // Method java/lang/String.equals:(Ljava/lang/Object;)Z
      23: ifeq          29
      26: ldc           #7                  // String *
      28: astore_2
      29: iconst_0
      30: istore        5
      32: iload         5
      34: aload_1
      35: arraylength
      36: if_icmpge     88
      39: new           #255                // class java/lang/StringBuilder
      42: dup
      43: invokespecial #516                // Method java/lang/StringBuilder."<init>":()V
      46: aload         4
      48: invokevirtual #518                // Method java/lang/StringBuilder.append:(Ljava/lang/String;)Ljava/lang/StringBuilder;
      51: ldc           #3                  // String (
      53: invokevirtual #518                // Method java/lang/StringBuilder.append:(Ljava/lang/String;)Ljava/lang/StringBuilder;
      56: aload_1
      57: iload         5
      59: aaload
      60: invokevirtual #518                // Method java/lang/StringBuilder.append:(Ljava/lang/String;)Ljava/lang/StringBuilder;
      63: ldc           #10                 // String =
      65: invokevirtual #518                // Method java/lang/StringBuilder.append:(Ljava/lang/String;)Ljava/lang/StringBuilder;
      68: aload_2
      69: invokevirtual #518                // Method java/lang/StringBuilder.append:(Ljava/lang/String;)Ljava/lang/StringBuilder;
      72: ldc           #6                  // String )
      74: invokevirtual #518                // Method java/lang/StringBuilder.append:(Ljava/lang/String;)Ljava/lang/StringBuilder;
      77: invokevirtual #517                // Method java/lang/StringBuilder.toString:()Ljava/lang/String;
      80: astore        4
      82: iinc          5, 1
      85: goto          32
      88: new           #255                // class java/lang/StringBuilder
      91: dup
      92: invokespecial #516                // Method java/lang/StringBuilder."<init>":()V
      95: ldc           #5                  // String (|
      97: invokevirtual #518                // Method java/lang/StringBuilder.append:(Ljava/lang/String;)Ljava/lang/StringBuilder;
     100: aload         4
     102: invokevirtual #518                // Method java/lang/StringBuilder.append:(Ljava/lang/String;)Ljava/lang/StringBuilder;
     105: ldc           #6                  // String )
     107: invokevirtual #518                // Method java/lang/StringBuilder.append:(Ljava/lang/String;)Ljava/lang/StringBuilder;
     110: invokevirtual #517                // Method java/lang/StringBuilder.toString:()Ljava/lang/String;
     113: astore        4
     115: ldc           #1                  // String
     117: astore        5
     119: iconst_0
     120: istore        6
     122: iload         6
     124: aload_3
     125: arraylength
     126: if_icmpge     169
     129: new           #255                // class java/lang/StringBuilder
     132: dup
     133: invokespecial #516                // Method java/lang/StringBuilder."<init>":()V
     136: aload         5
     138: invokevirtual #518                // Method java/lang/StringBuilder.append:(Ljava/lang/String;)Ljava/lang/StringBuilder;
     141: ldc           #3                  // String (
     143: invokevirtual #518                // Method java/lang/StringBuilder.append:(Ljava/lang/String;)Ljava/lang/StringBuilder;
     146: aload_3
     147: iload         6
     149: aaload
     150: invokevirtual #518                // Method java/lang/StringBuilder.append:(Ljava/lang/String;)Ljava/lang/StringBuilder;
     153: ldc           #11                 // String =*)
     155: invokevirtual #518                // Method java/lang/StringBuilder.append:(Ljava/lang/String;)Ljava/lang/StringBuilder;
     158: invokevirtual #517                // Method java/lang/StringBuilder.toString:()Ljava/lang/String;
     161: astore        5
     163: iinc          6, 1
     166: goto          122
     169: new           #255                // class java/lang/StringBuilder
     172: dup
     173: invokespecial #516                // Method java/lang/StringBuilder."<init>":()V
     176: ldc           #5                  // String (|
     178: invokevirtual #518                // Method java/lang/StringBuilder.append:(Ljava/lang/String;)Ljava/lang/StringBuilder;
     181: aload         5
     183: invokevirtual #518                // Method java/lang/StringBuilder.append:(Ljava/lang/String;)Ljava/lang/StringBuilder;
     186: ldc           #6                  // String )
     188: invokevirtual #518                // Method java/lang/StringBuilder.append:(Ljava/lang/String;)Ljava/lang/StringBuilder;
     191: invokevirtual #517                // Method java/lang/StringBuilder.toString:()Ljava/lang/String;
     194: astore        5
     196: new           #255                // class java/lang/StringBuilder
     199: dup
     200: invokespecial #516                // Method java/lang/StringBuilder."<init>":()V
     203: ldc           #4                  // String (&
     205: invokevirtual #518                // Method java/lang/StringBuilder.append:(Ljava/lang/String;)Ljava/lang/StringBuilder;
     208: aload         4
     210: invokevirtual #518                // Method java/lang/StringBuilder.append:(Ljava/lang/String;)Ljava/lang/StringBuilder;
     213: ldc           #1                  // String
     215: invokevirtual #518                // Method java/lang/StringBuilder.append:(Ljava/lang/String;)Ljava/lang/StringBuilder;
     218: aload         5
     220: invokevirtual #518                // Method java/lang/StringBuilder.append:(Ljava/lang/String;)Ljava/lang/StringBuilder;
     223: ldc           #6                  // String )
     225: invokevirtual #518                // Method java/lang/StringBuilder.append:(Ljava/lang/String;)Ljava/lang/StringBuilder;
     228: invokevirtual #517                // Method java/lang/StringBuilder.toString:()Ljava/lang/String;
     231: astore        6
     233: aload         4
     235: ifnonnull     242
     238: aload         5
     240: astore        6
     242: aload_0
     243: aload         6
     245: invokespecial #621                // Method getFromCache:(Ljava/lang/String;)Ljava/util/List;
     248: astore        7
     250: aload         7
     252: ifnull        258
     255: aload         7
     257: areturn
     258: aconst_null
     259: astore        8
     261: new           #263                // class java/util/ArrayList
     264: dup
     265: invokespecial #526                // Method java/util/ArrayList."<init>":()V
     268: astore        7
     270: aload_0
     271: invokespecial #618                // Method connectLDAP:()Ljavax/naming/directory/DirContext;
     274: astore        8
     276: new           #279                // class javax/naming/directory/SearchControls
     279: dup
     280: invokespecial #532                // Method javax/naming/directory/SearchControls."<init>":()V
     283: astore        9
     285: aload         9
     287: iconst_2
     288: invokevirtual #533                // Method javax/naming/directory/SearchControls.setSearchScope:(I)V
     291: aload         9
     293: lconst_0
     294: invokevirtual #534                // Method javax/naming/directory/SearchControls.setCountLimit:(J)V
     297: aload         9
     299: aload_3
     300: invokevirtual #535                // Method javax/naming/directory/SearchControls.setReturningAttributes:([Ljava/lang/String;)V
     303: aload         8
     305: aload_0
     306: getfield      #500                // Field params:Lorg/bouncycastle/jce/X509LDAPCertStoreParameters;
     309: invokevirtual #555                // Method org/bouncycastle/jce/X509LDAPCertStoreParameters.getBaseDN:()Ljava/lang/String;
     312: aload         6
     314: aload         9
     316: invokeinterface #664,  4          // InterfaceMethod javax/naming/directory/DirContext.search:(Ljava/lang/String;Ljava/lang/String;Ljavax/naming/directory/SearchControls;)Ljavax/naming/NamingEnumeration;
     321: astore        10
     323: aload         10
     325: invokeinterface #659,  1          // InterfaceMethod javax/naming/NamingEnumeration.hasMoreElements:()Z
     330: ifeq          401
     333: aload         10
     335: invokeinterface #660,  1          // InterfaceMethod javax/naming/NamingEnumeration.next:()Ljava/lang/Object;
     340: checkcast     #280                // class javax/naming/directory/SearchResult
     343: astore        11
     345: aload         11
     347: invokevirtual #536                // Method javax/naming/directory/SearchResult.getAttributes:()Ljavax/naming/directory/Attributes;
     350: invokeinterface #662,  1          // InterfaceMethod javax/naming/directory/Attributes.getAll:()Ljavax/naming/NamingEnumeration;
     355: invokeinterface #660,  1          // InterfaceMethod javax/naming/NamingEnumeration.next:()Ljava/lang/Object;
     360: checkcast     #275                // class javax/naming/directory/Attribute
     363: invokeinterface #661,  1          // InterfaceMethod javax/naming/directory/Attribute.getAll:()Ljavax/naming/NamingEnumeration;
     368: astore        12
     370: aload         12
     372: invokeinterface #658,  1          // InterfaceMethod javax/naming/NamingEnumeration.hasMore:()Z
     377: ifeq          398
     380: aload         7
     382: aload         12
     384: invokeinterface #660,  1          // InterfaceMethod javax/naming/NamingEnumeration.next:()Ljava/lang/Object;
     389: invokeinterface #643,  2          // InterfaceMethod java/util/List.add:(Ljava/lang/Object;)Z
     394: pop
     395: goto          370
     398: goto          323
     401: aload_0
     402: aload         6
     404: aload         7
     406: invokespecial #622                // Method addToCache:(Ljava/lang/String;Ljava/util/List;)V
     409: aconst_null
     410: aload         8
     412: if_acmpeq     422
     415: aload         8
     417: invokeinterface #663,  1          // InterfaceMethod javax/naming/directory/DirContext.close:()V
     422: goto          476
     425: astore        9
     427: goto          476
     430: astore        9
     432: aconst_null
     433: aload         8
     435: if_acmpeq     445
     438: aload         8
     440: invokeinterface #663,  1          // InterfaceMethod javax/naming/directory/DirContext.close:()V
     445: goto          476
     448: astore        9
     450: goto          476
     453: astore        13
     455: aconst_null
     456: aload         8
     458: if_acmpeq     468
     461: aload         8
     463: invokeinterface #663,  1          // InterfaceMethod javax/naming/directory/DirContext.close:()V
     468: goto          473
     471: astore        14
     473: aload         13
     475: athrow
     476: aload         7
     478: areturn
    Exception table:
       from    to  target type
         409   422   425   Class java/lang/Exception
         270   409   430   Class javax/naming/NamingException
         432   445   448   Class java/lang/Exception
         270   409   453   any
         430   432   453   any
         455   468   471   Class java/lang/Exception
         453   455   453   any

  private java.util.Set createCRLs(java.util.List, org.bouncycastle.x509.X509CRLStoreSelector) throws org.bouncycastle.util.StoreException;
    Code:
       0: new           #266                // class java/util/HashSet
       3: dup
       4: invokespecial #528                // Method java/util/HashSet."<init>":()V
       7: astore_3
       8: new           #287                // class org/bouncycastle/jce/provider/X509CRLParser
      11: dup
      12: invokespecial #582                // Method org/bouncycastle/jce/provider/X509CRLParser."<init>":()V
      15: astore        4
      17: aload_1
      18: invokeinterface #645,  1          // InterfaceMethod java/util/List.iterator:()Ljava/util/Iterator;
      23: astore        5
      25: aload         5
      27: invokeinterface #639,  1          // InterfaceMethod java/util/Iterator.hasNext:()Z
      32: ifeq          96
      35: aload         4
      37: new           #250                // class java/io/ByteArrayInputStream
      40: dup
      41: aload         5
      43: invokeinterface #640,  1          // InterfaceMethod java/util/Iterator.next:()Ljava/lang/Object;
      48: checkcast     #249                // class "[B"
      51: checkcast     #249                // class "[B"
      54: invokespecial #501                // Method java/io/ByteArrayInputStream."<init>":([B)V
      57: invokevirtual #583                // Method org/bouncycastle/jce/provider/X509CRLParser.engineInit:(Ljava/io/InputStream;)V
      60: aload         4
      62: invokevirtual #584                // Method org/bouncycastle/jce/provider/X509CRLParser.engineRead:()Ljava/lang/Object;
      65: checkcast     #260                // class java/security/cert/X509CRL
      68: astore        6
      70: aload_2
      71: aload         6
      73: invokevirtual #601                // Method org/bouncycastle/x509/X509CRLStoreSelector.match:(Ljava/lang/Object;)Z
      76: ifeq          88
      79: aload_3
      80: aload         6
      82: invokeinterface #655,  2          // InterfaceMethod java/util/Set.add:(Ljava/lang/Object;)Z
      87: pop
      88: goto          25
      91: astore        6
      93: goto          25
      96: aload_3
      97: areturn
    Exception table:
       from    to  target type
          35    88    91   Class org/bouncycastle/x509/util/StreamParsingException

  private java.util.Set createCrossCertificatePairs(java.util.List, org.bouncycastle.x509.X509CertPairStoreSelector) throws org.bouncycastle.util.StoreException;
    Code:
       0: new           #266                // class java/util/HashSet
       3: dup
       4: invokespecial #528                // Method java/util/HashSet."<init>":()V
       7: astore_3
       8: iconst_0
       9: istore        4
      11: iload         4
      13: aload_1
      14: invokeinterface #641,  1          // InterfaceMethod java/util/List.size:()I
      19: if_icmpge     189
      22: new           #288                // class org/bouncycastle/jce/provider/X509CertPairParser
      25: dup
      26: invokespecial #585                // Method org/bouncycastle/jce/provider/X509CertPairParser."<init>":()V
      29: astore        6
      31: aload         6
      33: new           #250                // class java/io/ByteArrayInputStream
      36: dup
      37: aload_1
      38: iload         4
      40: invokeinterface #642,  2          // InterfaceMethod java/util/List.get:(I)Ljava/lang/Object;
      45: checkcast     #249                // class "[B"
      48: checkcast     #249                // class "[B"
      51: invokespecial #501                // Method java/io/ByteArrayInputStream."<init>":([B)V
      54: invokevirtual #586                // Method org/bouncycastle/jce/provider/X509CertPairParser.engineInit:(Ljava/io/InputStream;)V
      57: aload         6
      59: invokevirtual #587                // Method org/bouncycastle/jce/provider/X509CertPairParser.engineRead:()Ljava/lang/Object;
      62: checkcast     #298                // class org/bouncycastle/x509/X509CertificatePair
      65: astore        5
      67: goto          155
      70: astore        6
      72: aload_1
      73: iload         4
      75: invokeinterface #642,  2          // InterfaceMethod java/util/List.get:(I)Ljava/lang/Object;
      80: checkcast     #249                // class "[B"
      83: checkcast     #249                // class "[B"
      86: astore        7
      88: aload_1
      89: iload         4
      91: iconst_1
      92: iadd
      93: invokeinterface #642,  2          // InterfaceMethod java/util/List.get:(I)Ljava/lang/Object;
      98: checkcast     #249                // class "[B"
     101: checkcast     #249                // class "[B"
     104: astore        8
     106: new           #298                // class org/bouncycastle/x509/X509CertificatePair
     109: dup
     110: new           #284                // class org/bouncycastle/asn1/x509/CertificatePair
     113: dup
     114: new           #282                // class org/bouncycastle/asn1/ASN1InputStream
     117: dup
     118: aload         7
     120: invokespecial #539                // Method org/bouncycastle/asn1/ASN1InputStream."<init>":([B)V
     123: invokevirtual #540                // Method org/bouncycastle/asn1/ASN1InputStream.readObject:()Lorg/bouncycastle/asn1/ASN1Primitive;
     126: invokestatic  #541                // Method org/bouncycastle/asn1/x509/Certificate.getInstance:(Ljava/lang/Object;)Lorg/bouncycastle/asn1/x509/Certificate;
     129: new           #282                // class org/bouncycastle/asn1/ASN1InputStream
     132: dup
     133: aload         8
     135: invokespecial #539                // Method org/bouncycastle/asn1/ASN1InputStream."<init>":([B)V
     138: invokevirtual #540                // Method org/bouncycastle/asn1/ASN1InputStream.readObject:()Lorg/bouncycastle/asn1/ASN1Primitive;
     141: invokestatic  #541                // Method org/bouncycastle/asn1/x509/Certificate.getInstance:(Ljava/lang/Object;)Lorg/bouncycastle/asn1/x509/Certificate;
     144: invokespecial #542                // Method org/bouncycastle/asn1/x509/CertificatePair."<init>":(Lorg/bouncycastle/asn1/x509/Certificate;Lorg/bouncycastle/asn1/x509/Certificate;)V
     147: invokespecial #617                // Method org/bouncycastle/x509/X509CertificatePair."<init>":(Lorg/bouncycastle/asn1/x509/CertificatePair;)V
     150: astore        5
     152: iinc          4, 1
     155: aload_2
     156: aload         5
     158: invokevirtual #606                // Method org/bouncycastle/x509/X509CertPairStoreSelector.match:(Ljava/lang/Object;)Z
     161: ifeq          173
     164: aload_3
     165: aload         5
     167: invokeinterface #655,  2          // InterfaceMethod java/util/Set.add:(Ljava/lang/Object;)Z
     172: pop
     173: goto          183
     176: astore        6
     178: goto          183
     181: astore        6
     183: iinc          4, 1
     186: goto          11
     189: aload_3
     190: areturn
    Exception table:
       from    to  target type
          22    67    70   Class org/bouncycastle/x509/util/StreamParsingException
          22   173   176   Class java/security/cert/CertificateParsingException
          22   173   181   Class java/io/IOException

  private java.util.Set createAttributeCertificates(java.util.List, org.bouncycastle.x509.X509AttributeCertStoreSelector) throws org.bouncycastle.util.StoreException;
    Code:
       0: new           #266                // class java/util/HashSet
       3: dup
       4: invokespecial #528                // Method java/util/HashSet."<init>":()V
       7: astore_3
       8: aload_1
       9: invokeinterface #645,  1          // InterfaceMethod java/util/List.iterator:()Ljava/util/Iterator;
      14: astore        4
      16: new           #286                // class org/bouncycastle/jce/provider/X509AttrCertParser
      19: dup
      20: invokespecial #579                // Method org/bouncycastle/jce/provider/X509AttrCertParser."<init>":()V
      23: astore        5
      25: aload         4
      27: invokeinterface #639,  1          // InterfaceMethod java/util/Iterator.hasNext:()Z
      32: ifeq          96
      35: aload         5
      37: new           #250                // class java/io/ByteArrayInputStream
      40: dup
      41: aload         4
      43: invokeinterface #640,  1          // InterfaceMethod java/util/Iterator.next:()Ljava/lang/Object;
      48: checkcast     #249                // class "[B"
      51: checkcast     #249                // class "[B"
      54: invokespecial #501                // Method java/io/ByteArrayInputStream."<init>":([B)V
      57: invokevirtual #580                // Method org/bouncycastle/jce/provider/X509AttrCertParser.engineInit:(Ljava/io/InputStream;)V
      60: aload         5
      62: invokevirtual #581                // Method org/bouncycastle/jce/provider/X509AttrCertParser.engineRead:()Ljava/lang/Object;
      65: checkcast     #294                // class org/bouncycastle/x509/X509AttributeCertificate
      68: astore        6
      70: aload_2
      71: aload         6
      73: invokevirtual #596                // Method org/bouncycastle/x509/X509AttributeCertStoreSelector.match:(Ljava/lang/Object;)Z
      76: ifeq          88
      79: aload_3
      80: aload         6
      82: invokeinterface #655,  2          // InterfaceMethod java/util/Set.add:(Ljava/lang/Object;)Z
      87: pop
      88: goto          25
      91: astore        6
      93: goto          25
      96: aload_3
      97: areturn
    Exception table:
       from    to  target type
          35    88    91   Class org/bouncycastle/x509/util/StreamParsingException

  public java.util.Collection getAuthorityRevocationLists(org.bouncycastle.x509.X509CRLStoreSelector) throws org.bouncycastle.util.StoreException;
    Code:
       0: aload_0
       1: aload_0
       2: getfield      #500                // Field params:Lorg/bouncycastle/jce/X509LDAPCertStoreParameters;
       5: invokevirtual #553                // Method org/bouncycastle/jce/X509LDAPCertStoreParameters.getAuthorityRevocationListAttribute:()Ljava/lang/String;
       8: invokespecial #619                // Method splitString:(Ljava/lang/String;)[Ljava/lang/String;
      11: astore_2
      12: aload_0
      13: aload_0
      14: getfield      #500                // Field params:Lorg/bouncycastle/jce/X509LDAPCertStoreParameters;
      17: invokevirtual #569                // Method org/bouncycastle/jce/X509LDAPCertStoreParameters.getLdapAuthorityRevocationListAttributeName:()Ljava/lang/String;
      20: invokespecial #619                // Method splitString:(Ljava/lang/String;)[Ljava/lang/String;
      23: astore_3
      24: aload_0
      25: aload_0
      26: getfield      #500                // Field params:Lorg/bouncycastle/jce/X509LDAPCertStoreParameters;
      29: invokevirtual #554                // Method org/bouncycastle/jce/X509LDAPCertStoreParameters.getAuthorityRevocationListIssuerAttributeName:()Ljava/lang/String;
      32: invokespecial #619                // Method splitString:(Ljava/lang/String;)[Ljava/lang/String;
      35: astore        4
      37: aload_0
      38: aload_1
      39: aload_2
      40: aload_3
      41: aload         4
      43: invokespecial #631                // Method cRLIssuerSearch:(Lorg/bouncycastle/x509/X509CRLStoreSelector;[Ljava/lang/String;[Ljava/lang/String;[Ljava/lang/String;)Ljava/util/List;
      46: astore        5
      48: aload_0
      49: aload         5
      51: aload_1
      52: invokespecial #626                // Method createCRLs:(Ljava/util/List;Lorg/bouncycastle/x509/X509CRLStoreSelector;)Ljava/util/Set;
      55: astore        6
      57: aload         6
      59: invokeinterface #654,  1          // InterfaceMethod java/util/Set.size:()I
      64: ifne          103
      67: new           #295                // class org/bouncycastle/x509/X509CRLStoreSelector
      70: dup
      71: invokespecial #600                // Method org/bouncycastle/x509/X509CRLStoreSelector."<init>":()V
      74: astore        7
      76: aload_0
      77: aload         7
      79: aload_2
      80: aload_3
      81: aload         4
      83: invokespecial #631                // Method cRLIssuerSearch:(Lorg/bouncycastle/x509/X509CRLStoreSelector;[Ljava/lang/String;[Ljava/lang/String;[Ljava/lang/String;)Ljava/util/List;
      86: astore        5
      88: aload         6
      90: aload_0
      91: aload         5
      93: aload_1
      94: invokespecial #626                // Method createCRLs:(Ljava/util/List;Lorg/bouncycastle/x509/X509CRLStoreSelector;)Ljava/util/Set;
      97: invokeinterface #656,  2          // InterfaceMethod java/util/Set.addAll:(Ljava/util/Collection;)Z
     102: pop
     103: aload         6
     105: areturn

  public java.util.Collection getAttributeCertificateRevocationLists(org.bouncycastle.x509.X509CRLStoreSelector) throws org.bouncycastle.util.StoreException;
    Code:
       0: aload_0
       1: aload_0
       2: getfield      #500                // Field params:Lorg/bouncycastle/jce/X509LDAPCertStoreParameters;
       5: invokevirtual #549                // Method org/bouncycastle/jce/X509LDAPCertStoreParameters.getAttributeCertificateRevocationListAttribute:()Ljava/lang/String;
       8: invokespecial #619                // Method splitString:(Ljava/lang/String;)[Ljava/lang/String;
      11: astore_2
      12: aload_0
      13: aload_0
      14: getfield      #500                // Field params:Lorg/bouncycastle/jce/X509LDAPCertStoreParameters;
      17: invokevirtual #567                // Method org/bouncycastle/jce/X509LDAPCertStoreParameters.getLdapAttributeCertificateRevocationListAttributeName:()Ljava/lang/String;
      20: invokespecial #619                // Method splitString:(Ljava/lang/String;)[Ljava/lang/String;
      23: astore_3
      24: aload_0
      25: aload_0
      26: getfield      #500                // Field params:Lorg/bouncycastle/jce/X509LDAPCertStoreParameters;
      29: invokevirtual #550                // Method org/bouncycastle/jce/X509LDAPCertStoreParameters.getAttributeCertificateRevocationListIssuerAttributeName:()Ljava/lang/String;
      32: invokespecial #619                // Method splitString:(Ljava/lang/String;)[Ljava/lang/String;
      35: astore        4
      37: aload_0
      38: aload_1
      39: aload_2
      40: aload_3
      41: aload         4
      43: invokespecial #631                // Method cRLIssuerSearch:(Lorg/bouncycastle/x509/X509CRLStoreSelector;[Ljava/lang/String;[Ljava/lang/String;[Ljava/lang/String;)Ljava/util/List;
      46: astore        5
      48: aload_0
      49: aload         5
      51: aload_1
      52: invokespecial #626                // Method createCRLs:(Ljava/util/List;Lorg/bouncycastle/x509/X509CRLStoreSelector;)Ljava/util/Set;
      55: astore        6
      57: aload         6
      59: invokeinterface #654,  1          // InterfaceMethod java/util/Set.size:()I
      64: ifne          103
      67: new           #295                // class org/bouncycastle/x509/X509CRLStoreSelector
      70: dup
      71: invokespecial #600                // Method org/bouncycastle/x509/X509CRLStoreSelector."<init>":()V
      74: astore        7
      76: aload_0
      77: aload         7
      79: aload_2
      80: aload_3
      81: aload         4
      83: invokespecial #631                // Method cRLIssuerSearch:(Lorg/bouncycastle/x509/X509CRLStoreSelector;[Ljava/lang/String;[Ljava/lang/String;[Ljava/lang/String;)Ljava/util/List;
      86: astore        5
      88: aload         6
      90: aload_0
      91: aload         5
      93: aload_1
      94: invokespecial #626                // Method createCRLs:(Ljava/util/List;Lorg/bouncycastle/x509/X509CRLStoreSelector;)Ljava/util/Set;
      97: invokeinterface #656,  2          // InterfaceMethod java/util/Set.addAll:(Ljava/util/Collection;)Z
     102: pop
     103: aload         6
     105: areturn

  public java.util.Collection getAttributeAuthorityRevocationLists(org.bouncycastle.x509.X509CRLStoreSelector) throws org.bouncycastle.util.StoreException;
    Code:
       0: aload_0
       1: aload_0
       2: getfield      #500                // Field params:Lorg/bouncycastle/jce/X509LDAPCertStoreParameters;
       5: invokevirtual #545                // Method org/bouncycastle/jce/X509LDAPCertStoreParameters.getAttributeAuthorityRevocationListAttribute:()Ljava/lang/String;
       8: invokespecial #619                // Method splitString:(Ljava/lang/String;)[Ljava/lang/String;
      11: astore_2
      12: aload_0
      13: aload_0
      14: getfield      #500                // Field params:Lorg/bouncycastle/jce/X509LDAPCertStoreParameters;
      17: invokevirtual #565                // Method org/bouncycastle/jce/X509LDAPCertStoreParameters.getLdapAttributeAuthorityRevocationListAttributeName:()Ljava/lang/String;
      20: invokespecial #619                // Method splitString:(Ljava/lang/String;)[Ljava/lang/String;
      23: astore_3
      24: aload_0
      25: aload_0
      26: getfield      #500                // Field params:Lorg/bouncycastle/jce/X509LDAPCertStoreParameters;
      29: invokevirtual #546                // Method org/bouncycastle/jce/X509LDAPCertStoreParameters.getAttributeAuthorityRevocationListIssuerAttributeName:()Ljava/lang/String;
      32: invokespecial #619                // Method splitString:(Ljava/lang/String;)[Ljava/lang/String;
      35: astore        4
      37: aload_0
      38: aload_1
      39: aload_2
      40: aload_3
      41: aload         4
      43: invokespecial #631                // Method cRLIssuerSearch:(Lorg/bouncycastle/x509/X509CRLStoreSelector;[Ljava/lang/String;[Ljava/lang/String;[Ljava/lang/String;)Ljava/util/List;
      46: astore        5
      48: aload_0
      49: aload         5
      51: aload_1
      52: invokespecial #626                // Method createCRLs:(Ljava/util/List;Lorg/bouncycastle/x509/X509CRLStoreSelector;)Ljava/util/Set;
      55: astore        6
      57: aload         6
      59: invokeinterface #654,  1          // InterfaceMethod java/util/Set.size:()I
      64: ifne          103
      67: new           #295                // class org/bouncycastle/x509/X509CRLStoreSelector
      70: dup
      71: invokespecial #600                // Method org/bouncycastle/x509/X509CRLStoreSelector."<init>":()V
      74: astore        7
      76: aload_0
      77: aload         7
      79: aload_2
      80: aload_3
      81: aload         4
      83: invokespecial #631                // Method cRLIssuerSearch:(Lorg/bouncycastle/x509/X509CRLStoreSelector;[Ljava/lang/String;[Ljava/lang/String;[Ljava/lang/String;)Ljava/util/List;
      86: astore        5
      88: aload         6
      90: aload_0
      91: aload         5
      93: aload_1
      94: invokespecial #626                // Method createCRLs:(Ljava/util/List;Lorg/bouncycastle/x509/X509CRLStoreSelector;)Ljava/util/Set;
      97: invokeinterface #656,  2          // InterfaceMethod java/util/Set.addAll:(Ljava/util/Collection;)Z
     102: pop
     103: aload         6
     105: areturn

  public java.util.Collection getCrossCertificatePairs(org.bouncycastle.x509.X509CertPairStoreSelector) throws org.bouncycastle.util.StoreException;
    Code:
       0: aload_0
       1: aload_0
       2: getfield      #500                // Field params:Lorg/bouncycastle/jce/X509LDAPCertStoreParameters;
       5: invokevirtual #560                // Method org/bouncycastle/jce/X509LDAPCertStoreParameters.getCrossCertificateAttribute:()Ljava/lang/String;
       8: invokespecial #619                // Method splitString:(Ljava/lang/String;)[Ljava/lang/String;
      11: astore_2
      12: aload_0
      13: aload_0
      14: getfield      #500                // Field params:Lorg/bouncycastle/jce/X509LDAPCertStoreParameters;
      17: invokevirtual #572                // Method org/bouncycastle/jce/X509LDAPCertStoreParameters.getLdapCrossCertificateAttributeName:()Ljava/lang/String;
      20: invokespecial #619                // Method splitString:(Ljava/lang/String;)[Ljava/lang/String;
      23: astore_3
      24: aload_0
      25: aload_0
      26: getfield      #500                // Field params:Lorg/bouncycastle/jce/X509LDAPCertStoreParameters;
      29: invokevirtual #561                // Method org/bouncycastle/jce/X509LDAPCertStoreParameters.getCrossCertificateSubjectAttributeName:()Ljava/lang/String;
      32: invokespecial #619                // Method splitString:(Ljava/lang/String;)[Ljava/lang/String;
      35: astore        4
      37: aload_0
      38: aload_1
      39: aload_2
      40: aload_3
      41: aload         4
      43: invokespecial #632                // Method crossCertificatePairSubjectSearch:(Lorg/bouncycastle/x509/X509CertPairStoreSelector;[Ljava/lang/String;[Ljava/lang/String;[Ljava/lang/String;)Ljava/util/List;
      46: astore        5
      48: aload_0
      49: aload         5
      51: aload_1
      52: invokespecial #627                // Method createCrossCertificatePairs:(Ljava/util/List;Lorg/bouncycastle/x509/X509CertPairStoreSelector;)Ljava/util/Set;
      55: astore        6
      57: aload         6
      59: invokeinterface #654,  1          // InterfaceMethod java/util/Set.size:()I
      64: ifne          126
      67: new           #297                // class org/bouncycastle/x509/X509CertStoreSelector
      70: dup
      71: invokespecial #611                // Method org/bouncycastle/x509/X509CertStoreSelector."<init>":()V
      74: astore        7
      76: new           #296                // class org/bouncycastle/x509/X509CertPairStoreSelector
      79: dup
      80: invokespecial #605                // Method org/bouncycastle/x509/X509CertPairStoreSelector."<init>":()V
      83: astore        8
      85: aload         8
      87: aload         7
      89: invokevirtual #608                // Method org/bouncycastle/x509/X509CertPairStoreSelector.setForwardSelector:(Lorg/bouncycastle/x509/X509CertStoreSelector;)V
      92: aload         8
      94: aload         7
      96: invokevirtual #609                // Method org/bouncycastle/x509/X509CertPairStoreSelector.setReverseSelector:(Lorg/bouncycastle/x509/X509CertStoreSelector;)V
      99: aload_0
     100: aload         8
     102: aload_2
     103: aload_3
     104: aload         4
     106: invokespecial #632                // Method crossCertificatePairSubjectSearch:(Lorg/bouncycastle/x509/X509CertPairStoreSelector;[Ljava/lang/String;[Ljava/lang/String;[Ljava/lang/String;)Ljava/util/List;
     109: astore        5
     111: aload         6
     113: aload_0
     114: aload         5
     116: aload_1
     117: invokespecial #627                // Method createCrossCertificatePairs:(Ljava/util/List;Lorg/bouncycastle/x509/X509CertPairStoreSelector;)Ljava/util/Set;
     120: invokeinterface #656,  2          // InterfaceMethod java/util/Set.addAll:(Ljava/util/Collection;)Z
     125: pop
     126: aload         6
     128: areturn

  public java.util.Collection getUserCertificates(org.bouncycastle.x509.X509CertStoreSelector) throws org.bouncycastle.util.StoreException;
    Code:
       0: aload_0
       1: aload_0
       2: getfield      #500                // Field params:Lorg/bouncycastle/jce/X509LDAPCertStoreParameters;
       5: invokevirtual #577                // Method org/bouncycastle/jce/X509LDAPCertStoreParameters.getUserCertificateAttribute:()Ljava/lang/String;
       8: invokespecial #619                // Method splitString:(Ljava/lang/String;)[Ljava/lang/String;
      11: astore_2
      12: aload_0
      13: aload_0
      14: getfield      #500                // Field params:Lorg/bouncycastle/jce/X509LDAPCertStoreParameters;
      17: invokevirtual #575                // Method org/bouncycastle/jce/X509LDAPCertStoreParameters.getLdapUserCertificateAttributeName:()Ljava/lang/String;
      20: invokespecial #619                // Method splitString:(Ljava/lang/String;)[Ljava/lang/String;
      23: astore_3
      24: aload_0
      25: aload_0
      26: getfield      #500                // Field params:Lorg/bouncycastle/jce/X509LDAPCertStoreParameters;
      29: invokevirtual #578                // Method org/bouncycastle/jce/X509LDAPCertStoreParameters.getUserCertificateSubjectAttributeName:()Ljava/lang/String;
      32: invokespecial #619                // Method splitString:(Ljava/lang/String;)[Ljava/lang/String;
      35: astore        4
      37: aload_0
      38: aload_1
      39: aload_2
      40: aload_3
      41: aload         4
      43: invokespecial #633                // Method certSubjectSerialSearch:(Lorg/bouncycastle/x509/X509CertStoreSelector;[Ljava/lang/String;[Ljava/lang/String;[Ljava/lang/String;)Ljava/util/List;
      46: astore        5
      48: aload_0
      49: aload         5
      51: aload_1
      52: invokespecial #628                // Method createCerts:(Ljava/util/List;Lorg/bouncycastle/x509/X509CertStoreSelector;)Ljava/util/Set;
      55: astore        6
      57: aload         6
      59: invokeinterface #654,  1          // InterfaceMethod java/util/Set.size:()I
      64: ifne          103
      67: new           #297                // class org/bouncycastle/x509/X509CertStoreSelector
      70: dup
      71: invokespecial #611                // Method org/bouncycastle/x509/X509CertStoreSelector."<init>":()V
      74: astore        7
      76: aload_0
      77: aload         7
      79: aload_2
      80: aload_3
      81: aload         4
      83: invokespecial #633                // Method certSubjectSerialSearch:(Lorg/bouncycastle/x509/X509CertStoreSelector;[Ljava/lang/String;[Ljava/lang/String;[Ljava/lang/String;)Ljava/util/List;
      86: astore        5
      88: aload         6
      90: aload_0
      91: aload         5
      93: aload_1
      94: invokespecial #628                // Method createCerts:(Ljava/util/List;Lorg/bouncycastle/x509/X509CertStoreSelector;)Ljava/util/Set;
      97: invokeinterface #656,  2          // InterfaceMethod java/util/Set.addAll:(Ljava/util/Collection;)Z
     102: pop
     103: aload         6
     105: areturn

  public java.util.Collection getAACertificates(org.bouncycastle.x509.X509AttributeCertStoreSelector) throws org.bouncycastle.util.StoreException;
    Code:
       0: aload_0
       1: aload_0
       2: getfield      #500                // Field params:Lorg/bouncycastle/jce/X509LDAPCertStoreParameters;
       5: invokevirtual #543                // Method org/bouncycastle/jce/X509LDAPCertStoreParameters.getAACertificateAttribute:()Ljava/lang/String;
       8: invokespecial #619                // Method splitString:(Ljava/lang/String;)[Ljava/lang/String;
      11: astore_2
      12: aload_0
      13: aload_0
      14: getfield      #500                // Field params:Lorg/bouncycastle/jce/X509LDAPCertStoreParameters;
      17: invokevirtual #564                // Method org/bouncycastle/jce/X509LDAPCertStoreParameters.getLdapAACertificateAttributeName:()Ljava/lang/String;
      20: invokespecial #619                // Method splitString:(Ljava/lang/String;)[Ljava/lang/String;
      23: astore_3
      24: aload_0
      25: aload_0
      26: getfield      #500                // Field params:Lorg/bouncycastle/jce/X509LDAPCertStoreParameters;
      29: invokevirtual #544                // Method org/bouncycastle/jce/X509LDAPCertStoreParameters.getAACertificateSubjectAttributeName:()Ljava/lang/String;
      32: invokespecial #619                // Method splitString:(Ljava/lang/String;)[Ljava/lang/String;
      35: astore        4
      37: aload_0
      38: aload_1
      39: aload_2
      40: aload_3
      41: aload         4
      43: invokespecial #630                // Method attrCertSubjectSerialSearch:(Lorg/bouncycastle/x509/X509AttributeCertStoreSelector;[Ljava/lang/String;[Ljava/lang/String;[Ljava/lang/String;)Ljava/util/List;
      46: astore        5
      48: aload_0
      49: aload         5
      51: aload_1
      52: invokespecial #625                // Method createAttributeCertificates:(Ljava/util/List;Lorg/bouncycastle/x509/X509AttributeCertStoreSelector;)Ljava/util/Set;
      55: astore        6
      57: aload         6
      59: invokeinterface #654,  1          // InterfaceMethod java/util/Set.size:()I
      64: ifne          103
      67: new           #293                // class org/bouncycastle/x509/X509AttributeCertStoreSelector
      70: dup
      71: invokespecial #595                // Method org/bouncycastle/x509/X509AttributeCertStoreSelector."<init>":()V
      74: astore        7
      76: aload_0
      77: aload         7
      79: aload_2
      80: aload_3
      81: aload         4
      83: invokespecial #630                // Method attrCertSubjectSerialSearch:(Lorg/bouncycastle/x509/X509AttributeCertStoreSelector;[Ljava/lang/String;[Ljava/lang/String;[Ljava/lang/String;)Ljava/util/List;
      86: astore        5
      88: aload         6
      90: aload_0
      91: aload         5
      93: aload_1
      94: invokespecial #625                // Method createAttributeCertificates:(Ljava/util/List;Lorg/bouncycastle/x509/X509AttributeCertStoreSelector;)Ljava/util/Set;
      97: invokeinterface #656,  2          // InterfaceMethod java/util/Set.addAll:(Ljava/util/Collection;)Z
     102: pop
     103: aload         6
     105: areturn

  public java.util.Collection getAttributeDescriptorCertificates(org.bouncycastle.x509.X509AttributeCertStoreSelector) throws org.bouncycastle.util.StoreException;
    Code:
       0: aload_0
       1: aload_0
       2: getfield      #500                // Field params:Lorg/bouncycastle/jce/X509LDAPCertStoreParameters;
       5: invokevirtual #551                // Method org/bouncycastle/jce/X509LDAPCertStoreParameters.getAttributeDescriptorCertificateAttribute:()Ljava/lang/String;
       8: invokespecial #619                // Method splitString:(Ljava/lang/String;)[Ljava/lang/String;
      11: astore_2
      12: aload_0
      13: aload_0
      14: getfield      #500                // Field params:Lorg/bouncycastle/jce/X509LDAPCertStoreParameters;
      17: invokevirtual #568                // Method org/bouncycastle/jce/X509LDAPCertStoreParameters.getLdapAttributeDescriptorCertificateAttributeName:()Ljava/lang/String;
      20: invokespecial #619                // Method splitString:(Ljava/lang/String;)[Ljava/lang/String;
      23: astore_3
      24: aload_0
      25: aload_0
      26: getfield      #500                // Field params:Lorg/bouncycastle/jce/X509LDAPCertStoreParameters;
      29: invokevirtual #552                // Method org/bouncycastle/jce/X509LDAPCertStoreParameters.getAttributeDescriptorCertificateSubjectAttributeName:()Ljava/lang/String;
      32: invokespecial #619                // Method splitString:(Ljava/lang/String;)[Ljava/lang/String;
      35: astore        4
      37: aload_0
      38: aload_1
      39: aload_2
      40: aload_3
      41: aload         4
      43: invokespecial #630                // Method attrCertSubjectSerialSearch:(Lorg/bouncycastle/x509/X509AttributeCertStoreSelector;[Ljava/lang/String;[Ljava/lang/String;[Ljava/lang/String;)Ljava/util/List;
      46: astore        5
      48: aload_0
      49: aload         5
      51: aload_1
      52: invokespecial #625                // Method createAttributeCertificates:(Ljava/util/List;Lorg/bouncycastle/x509/X509AttributeCertStoreSelector;)Ljava/util/Set;
      55: astore        6
      57: aload         6
      59: invokeinterface #654,  1          // InterfaceMethod java/util/Set.size:()I
      64: ifne          103
      67: new           #293                // class org/bouncycastle/x509/X509AttributeCertStoreSelector
      70: dup
      71: invokespecial #595                // Method org/bouncycastle/x509/X509AttributeCertStoreSelector."<init>":()V
      74: astore        7
      76: aload_0
      77: aload         7
      79: aload_2
      80: aload_3
      81: aload         4
      83: invokespecial #630                // Method attrCertSubjectSerialSearch:(Lorg/bouncycastle/x509/X509AttributeCertStoreSelector;[Ljava/lang/String;[Ljava/lang/String;[Ljava/lang/String;)Ljava/util/List;
      86: astore        5
      88: aload         6
      90: aload_0
      91: aload         5
      93: aload_1
      94: invokespecial #625                // Method createAttributeCertificates:(Ljava/util/List;Lorg/bouncycastle/x509/X509AttributeCertStoreSelector;)Ljava/util/Set;
      97: invokeinterface #656,  2          // InterfaceMethod java/util/Set.addAll:(Ljava/util/Collection;)Z
     102: pop
     103: aload         6
     105: areturn

  public java.util.Collection getCACertificates(org.bouncycastle.x509.X509CertStoreSelector) throws org.bouncycastle.util.StoreException;
    Code:
       0: aload_0
       1: aload_0
       2: getfield      #500                // Field params:Lorg/bouncycastle/jce/X509LDAPCertStoreParameters;
       5: invokevirtual #556                // Method org/bouncycastle/jce/X509LDAPCertStoreParameters.getCACertificateAttribute:()Ljava/lang/String;
       8: invokespecial #619                // Method splitString:(Ljava/lang/String;)[Ljava/lang/String;
      11: astore_2
      12: aload_0
      13: aload_0
      14: getfield      #500                // Field params:Lorg/bouncycastle/jce/X509LDAPCertStoreParameters;
      17: invokevirtual #570                // Method org/bouncycastle/jce/X509LDAPCertStoreParameters.getLdapCACertificateAttributeName:()Ljava/lang/String;
      20: invokespecial #619                // Method splitString:(Ljava/lang/String;)[Ljava/lang/String;
      23: astore_3
      24: aload_0
      25: aload_0
      26: getfield      #500                // Field params:Lorg/bouncycastle/jce/X509LDAPCertStoreParameters;
      29: invokevirtual #557                // Method org/bouncycastle/jce/X509LDAPCertStoreParameters.getCACertificateSubjectAttributeName:()Ljava/lang/String;
      32: invokespecial #619                // Method splitString:(Ljava/lang/String;)[Ljava/lang/String;
      35: astore        4
      37: aload_0
      38: aload_1
      39: aload_2
      40: aload_3
      41: aload         4
      43: invokespecial #633                // Method certSubjectSerialSearch:(Lorg/bouncycastle/x509/X509CertStoreSelector;[Ljava/lang/String;[Ljava/lang/String;[Ljava/lang/String;)Ljava/util/List;
      46: astore        5
      48: aload_0
      49: aload         5
      51: aload_1
      52: invokespecial #628                // Method createCerts:(Ljava/util/List;Lorg/bouncycastle/x509/X509CertStoreSelector;)Ljava/util/Set;
      55: astore        6
      57: aload         6
      59: invokeinterface #654,  1          // InterfaceMethod java/util/Set.size:()I
      64: ifne          103
      67: new           #297                // class org/bouncycastle/x509/X509CertStoreSelector
      70: dup
      71: invokespecial #611                // Method org/bouncycastle/x509/X509CertStoreSelector."<init>":()V
      74: astore        7
      76: aload_0
      77: aload         7
      79: aload_2
      80: aload_3
      81: aload         4
      83: invokespecial #633                // Method certSubjectSerialSearch:(Lorg/bouncycastle/x509/X509CertStoreSelector;[Ljava/lang/String;[Ljava/lang/String;[Ljava/lang/String;)Ljava/util/List;
      86: astore        5
      88: aload         6
      90: aload_0
      91: aload         5
      93: aload_1
      94: invokespecial #628                // Method createCerts:(Ljava/util/List;Lorg/bouncycastle/x509/X509CertStoreSelector;)Ljava/util/Set;
      97: invokeinterface #656,  2          // InterfaceMethod java/util/Set.addAll:(Ljava/util/Collection;)Z
     102: pop
     103: aload         6
     105: areturn

  public java.util.Collection getDeltaCertificateRevocationLists(org.bouncycastle.x509.X509CRLStoreSelector) throws org.bouncycastle.util.StoreException;
    Code:
       0: aload_0
       1: aload_0
       2: getfield      #500                // Field params:Lorg/bouncycastle/jce/X509LDAPCertStoreParameters;
       5: invokevirtual #562                // Method org/bouncycastle/jce/X509LDAPCertStoreParameters.getDeltaRevocationListAttribute:()Ljava/lang/String;
       8: invokespecial #619                // Method splitString:(Ljava/lang/String;)[Ljava/lang/String;
      11: astore_2
      12: aload_0
      13: aload_0
      14: getfield      #500                // Field params:Lorg/bouncycastle/jce/X509LDAPCertStoreParameters;
      17: invokevirtual #573                // Method org/bouncycastle/jce/X509LDAPCertStoreParameters.getLdapDeltaRevocationListAttributeName:()Ljava/lang/String;
      20: invokespecial #619                // Method splitString:(Ljava/lang/String;)[Ljava/lang/String;
      23: astore_3
      24: aload_0
      25: aload_0
      26: getfield      #500                // Field params:Lorg/bouncycastle/jce/X509LDAPCertStoreParameters;
      29: invokevirtual #563                // Method org/bouncycastle/jce/X509LDAPCertStoreParameters.getDeltaRevocationListIssuerAttributeName:()Ljava/lang/String;
      32: invokespecial #619                // Method splitString:(Ljava/lang/String;)[Ljava/lang/String;
      35: astore        4
      37: aload_0
      38: aload_1
      39: aload_2
      40: aload_3
      41: aload         4
      43: invokespecial #631                // Method cRLIssuerSearch:(Lorg/bouncycastle/x509/X509CRLStoreSelector;[Ljava/lang/String;[Ljava/lang/String;[Ljava/lang/String;)Ljava/util/List;
      46: astore        5
      48: aload_0
      49: aload         5
      51: aload_1
      52: invokespecial #626                // Method createCRLs:(Ljava/util/List;Lorg/bouncycastle/x509/X509CRLStoreSelector;)Ljava/util/Set;
      55: astore        6
      57: aload         6
      59: invokeinterface #654,  1          // InterfaceMethod java/util/Set.size:()I
      64: ifne          103
      67: new           #295                // class org/bouncycastle/x509/X509CRLStoreSelector
      70: dup
      71: invokespecial #600                // Method org/bouncycastle/x509/X509CRLStoreSelector."<init>":()V
      74: astore        7
      76: aload_0
      77: aload         7
      79: aload_2
      80: aload_3
      81: aload         4
      83: invokespecial #631                // Method cRLIssuerSearch:(Lorg/bouncycastle/x509/X509CRLStoreSelector;[Ljava/lang/String;[Ljava/lang/String;[Ljava/lang/String;)Ljava/util/List;
      86: astore        5
      88: aload         6
      90: aload_0
      91: aload         5
      93: aload_1
      94: invokespecial #626                // Method createCRLs:(Ljava/util/List;Lorg/bouncycastle/x509/X509CRLStoreSelector;)Ljava/util/Set;
      97: invokeinterface #656,  2          // InterfaceMethod java/util/Set.addAll:(Ljava/util/Collection;)Z
     102: pop
     103: aload         6
     105: areturn

  public java.util.Collection getAttributeCertificateAttributes(org.bouncycastle.x509.X509AttributeCertStoreSelector) throws org.bouncycastle.util.StoreException;
    Code:
       0: aload_0
       1: aload_0
       2: getfield      #500                // Field params:Lorg/bouncycastle/jce/X509LDAPCertStoreParameters;
       5: invokevirtual #547                // Method org/bouncycastle/jce/X509LDAPCertStoreParameters.getAttributeCertificateAttributeAttribute:()Ljava/lang/String;
       8: invokespecial #619                // Method splitString:(Ljava/lang/String;)[Ljava/lang/String;
      11: astore_2
      12: aload_0
      13: aload_0
      14: getfield      #500                // Field params:Lorg/bouncycastle/jce/X509LDAPCertStoreParameters;
      17: invokevirtual #566                // Method org/bouncycastle/jce/X509LDAPCertStoreParameters.getLdapAttributeCertificateAttributeAttributeName:()Ljava/lang/String;
      20: invokespecial #619                // Method splitString:(Ljava/lang/String;)[Ljava/lang/String;
      23: astore_3
      24: aload_0
      25: aload_0
      26: getfield      #500                // Field params:Lorg/bouncycastle/jce/X509LDAPCertStoreParameters;
      29: invokevirtual #548                // Method org/bouncycastle/jce/X509LDAPCertStoreParameters.getAttributeCertificateAttributeSubjectAttributeName:()Ljava/lang/String;
      32: invokespecial #619                // Method splitString:(Ljava/lang/String;)[Ljava/lang/String;
      35: astore        4
      37: aload_0
      38: aload_1
      39: aload_2
      40: aload_3
      41: aload         4
      43: invokespecial #630                // Method attrCertSubjectSerialSearch:(Lorg/bouncycastle/x509/X509AttributeCertStoreSelector;[Ljava/lang/String;[Ljava/lang/String;[Ljava/lang/String;)Ljava/util/List;
      46: astore        5
      48: aload_0
      49: aload         5
      51: aload_1
      52: invokespecial #625                // Method createAttributeCertificates:(Ljava/util/List;Lorg/bouncycastle/x509/X509AttributeCertStoreSelector;)Ljava/util/Set;
      55: astore        6
      57: aload         6
      59: invokeinterface #654,  1          // InterfaceMethod java/util/Set.size:()I
      64: ifne          103
      67: new           #293                // class org/bouncycastle/x509/X509AttributeCertStoreSelector
      70: dup
      71: invokespecial #595                // Method org/bouncycastle/x509/X509AttributeCertStoreSelector."<init>":()V
      74: astore        7
      76: aload_0
      77: aload         7
      79: aload_2
      80: aload_3
      81: aload         4
      83: invokespecial #630                // Method attrCertSubjectSerialSearch:(Lorg/bouncycastle/x509/X509AttributeCertStoreSelector;[Ljava/lang/String;[Ljava/lang/String;[Ljava/lang/String;)Ljava/util/List;
      86: astore        5
      88: aload         6
      90: aload_0
      91: aload         5
      93: aload_1
      94: invokespecial #625                // Method createAttributeCertificates:(Ljava/util/List;Lorg/bouncycastle/x509/X509AttributeCertStoreSelector;)Ljava/util/Set;
      97: invokeinterface #656,  2          // InterfaceMethod java/util/Set.addAll:(Ljava/util/Collection;)Z
     102: pop
     103: aload         6
     105: areturn

  public java.util.Collection getCertificateRevocationLists(org.bouncycastle.x509.X509CRLStoreSelector) throws org.bouncycastle.util.StoreException;
    Code:
       0: aload_0
       1: aload_0
       2: getfield      #500                // Field params:Lorg/bouncycastle/jce/X509LDAPCertStoreParameters;
       5: invokevirtual #558                // Method org/bouncycastle/jce/X509LDAPCertStoreParameters.getCertificateRevocationListAttribute:()Ljava/lang/String;
       8: invokespecial #619                // Method splitString:(Ljava/lang/String;)[Ljava/lang/String;
      11: astore_2
      12: aload_0
      13: aload_0
      14: getfield      #500                // Field params:Lorg/bouncycastle/jce/X509LDAPCertStoreParameters;
      17: invokevirtual #571                // Method org/bouncycastle/jce/X509LDAPCertStoreParameters.getLdapCertificateRevocationListAttributeName:()Ljava/lang/String;
      20: invokespecial #619                // Method splitString:(Ljava/lang/String;)[Ljava/lang/String;
      23: astore_3
      24: aload_0
      25: aload_0
      26: getfield      #500                // Field params:Lorg/bouncycastle/jce/X509LDAPCertStoreParameters;
      29: invokevirtual #559                // Method org/bouncycastle/jce/X509LDAPCertStoreParameters.getCertificateRevocationListIssuerAttributeName:()Ljava/lang/String;
      32: invokespecial #619                // Method splitString:(Ljava/lang/String;)[Ljava/lang/String;
      35: astore        4
      37: aload_0
      38: aload_1
      39: aload_2
      40: aload_3
      41: aload         4
      43: invokespecial #631                // Method cRLIssuerSearch:(Lorg/bouncycastle/x509/X509CRLStoreSelector;[Ljava/lang/String;[Ljava/lang/String;[Ljava/lang/String;)Ljava/util/List;
      46: astore        5
      48: aload_0
      49: aload         5
      51: aload_1
      52: invokespecial #626                // Method createCRLs:(Ljava/util/List;Lorg/bouncycastle/x509/X509CRLStoreSelector;)Ljava/util/Set;
      55: astore        6
      57: aload         6
      59: invokeinterface #654,  1          // InterfaceMethod java/util/Set.size:()I
      64: ifne          103
      67: new           #295                // class org/bouncycastle/x509/X509CRLStoreSelector
      70: dup
      71: invokespecial #600                // Method org/bouncycastle/x509/X509CRLStoreSelector."<init>":()V
      74: astore        7
      76: aload_0
      77: aload         7
      79: aload_2
      80: aload_3
      81: aload         4
      83: invokespecial #631                // Method cRLIssuerSearch:(Lorg/bouncycastle/x509/X509CRLStoreSelector;[Ljava/lang/String;[Ljava/lang/String;[Ljava/lang/String;)Ljava/util/List;
      86: astore        5
      88: aload         6
      90: aload_0
      91: aload         5
      93: aload_1
      94: invokespecial #626                // Method createCRLs:(Ljava/util/List;Lorg/bouncycastle/x509/X509CRLStoreSelector;)Ljava/util/Set;
      97: invokeinterface #656,  2          // InterfaceMethod java/util/Set.addAll:(Ljava/util/Collection;)Z
     102: pop
     103: aload         6
     105: areturn

  private synchronized void addToCache(java.lang.String, java.util.List);
    Code:
       0: new           #262                // class java/sql/Date
       3: dup
       4: invokestatic  #519                // Method java/lang/System.currentTimeMillis:()J
       7: invokespecial #525                // Method java/sql/Date."<init>":(J)V
      10: astore_3
      11: new           #263                // class java/util/ArrayList
      14: dup
      15: invokespecial #526                // Method java/util/ArrayList."<init>":()V
      18: astore        4
      20: aload         4
      22: aload_3
      23: invokeinterface #643,  2          // InterfaceMethod java/util/List.add:(Ljava/lang/Object;)Z
      28: pop
      29: aload         4
      31: aload_2
      32: invokeinterface #643,  2          // InterfaceMethod java/util/List.add:(Ljava/lang/Object;)Z
      37: pop
      38: aload_0
      39: getfield      #499                // Field cacheMap:Ljava/util/Map;
      42: aload_1
      43: invokeinterface #647,  2          // InterfaceMethod java/util/Map.containsKey:(Ljava/lang/Object;)Z
      48: ifeq          67
      51: aload_0
      52: getfield      #499                // Field cacheMap:Ljava/util/Map;
      55: aload_1
      56: aload         4
      58: invokeinterface #651,  3          // InterfaceMethod java/util/Map.put:(Ljava/lang/Object;Ljava/lang/Object;)Ljava/lang/Object;
      63: pop
      64: goto          202
      67: aload_0
      68: getfield      #499                // Field cacheMap:Ljava/util/Map;
      71: invokeinterface #646,  1          // InterfaceMethod java/util/Map.size:()I
      76: getstatic     #495                // Field cacheSize:I
      79: if_icmplt     189
      82: aload_0
      83: getfield      #499                // Field cacheMap:Ljava/util/Map;
      86: invokeinterface #648,  1          // InterfaceMethod java/util/Map.entrySet:()Ljava/util/Set;
      91: invokeinterface #657,  1          // InterfaceMethod java/util/Set.iterator:()Ljava/util/Iterator;
      96: astore        5
      98: aload_3
      99: invokevirtual #524                // Method java/sql/Date.getTime:()J
     102: lstore        6
     104: aconst_null
     105: astore        8
     107: aload         5
     109: invokeinterface #639,  1          // InterfaceMethod java/util/Iterator.hasNext:()Z
     114: ifeq          177
     117: aload         5
     119: invokeinterface #640,  1          // InterfaceMethod java/util/Iterator.next:()Ljava/lang/Object;
     124: checkcast     #270                // class java/util/Map$Entry
     127: astore        9
     129: aload         9
     131: invokeinterface #653,  1          // InterfaceMethod java/util/Map$Entry.getValue:()Ljava/lang/Object;
     136: checkcast     #268                // class java/util/List
     139: iconst_0
     140: invokeinterface #642,  2          // InterfaceMethod java/util/List.get:(I)Ljava/lang/Object;
     145: checkcast     #262                // class java/sql/Date
     148: invokevirtual #524                // Method java/sql/Date.getTime:()J
     151: lstore        10
     153: lload         10
     155: lload         6
     157: lcmp
     158: ifge          174
     161: lload         10
     163: lstore        6
     165: aload         9
     167: invokeinterface #652,  1          // InterfaceMethod java/util/Map$Entry.getKey:()Ljava/lang/Object;
     172: astore        8
     174: goto          107
     177: aload_0
     178: getfield      #499                // Field cacheMap:Ljava/util/Map;
     181: aload         8
     183: invokeinterface #650,  2          // InterfaceMethod java/util/Map.remove:(Ljava/lang/Object;)Ljava/lang/Object;
     188: pop
     189: aload_0
     190: getfield      #499                // Field cacheMap:Ljava/util/Map;
     193: aload_1
     194: aload         4
     196: invokeinterface #651,  3          // InterfaceMethod java/util/Map.put:(Ljava/lang/Object;Ljava/lang/Object;)Ljava/lang/Object;
     201: pop
     202: return

  private java.util.List getFromCache(java.lang.String);
    Code:
       0: aload_0
       1: getfield      #499                // Field cacheMap:Ljava/util/Map;
       4: aload_1
       5: invokeinterface #649,  2          // InterfaceMethod java/util/Map.get:(Ljava/lang/Object;)Ljava/lang/Object;
      10: checkcast     #268                // class java/util/List
      13: astore_2
      14: invokestatic  #519                // Method java/lang/System.currentTimeMillis:()J
      17: lstore_3
      18: aload_2
      19: ifnull        57
      22: aload_2
      23: iconst_0
      24: invokeinterface #642,  2          // InterfaceMethod java/util/List.get:(I)Ljava/lang/Object;
      29: checkcast     #262                // class java/sql/Date
      32: invokevirtual #524                // Method java/sql/Date.getTime:()J
      35: lload_3
      36: getstatic     #496                // Field lifeTime:J
      39: lsub
      40: lcmp
      41: ifge          46
      44: aconst_null
      45: areturn
      46: aload_2
      47: iconst_1
      48: invokeinterface #642,  2          // InterfaceMethod java/util/List.get:(I)Ljava/lang/Object;
      53: checkcast     #268                // class java/util/List
      56: areturn
      57: aconst_null
      58: areturn

  private java.lang.String[] splitString(java.lang.String);
    Code:
       0: aload_1
       1: ldc           #13                 // String \\s+
       3: invokevirtual #515                // Method java/lang/String.split:(Ljava/lang/String;)[Ljava/lang/String;
       6: areturn

  private java.lang.String getSubjectAsString(org.bouncycastle.x509.X509CertStoreSelector);
    Code:
       0: aload_1
       1: invokevirtual #612                // Method org/bouncycastle/x509/X509CertStoreSelector.getSubjectAsBytes:()[B
       4: astore_2
       5: aload_2
       6: ifnull        23
       9: new           #281                // class javax/security/auth/x500/X500Principal
      12: dup
      13: aload_2
      14: invokespecial #537                // Method javax/security/auth/x500/X500Principal."<init>":([B)V
      17: ldc           #12                 // String RFC1779
      19: invokevirtual #538                // Method javax/security/auth/x500/X500Principal.getName:(Ljava/lang/String;)Ljava/lang/String;
      22: areturn
      23: goto          58
      26: astore_2
      27: new           #290                // class org/bouncycastle/util/StoreException
      30: dup
      31: new           #255                // class java/lang/StringBuilder
      34: dup
      35: invokespecial #516                // Method java/lang/StringBuilder."<init>":()V
      38: ldc           #16                 // String exception processing name:
      40: invokevirtual #518                // Method java/lang/StringBuilder.append:(Ljava/lang/String;)Ljava/lang/StringBuilder;
      43: aload_2
      44: invokevirtual #502                // Method java/io/IOException.getMessage:()Ljava/lang/String;
      47: invokevirtual #518                // Method java/lang/StringBuilder.append:(Ljava/lang/String;)Ljava/lang/StringBuilder;
      50: invokevirtual #517                // Method java/lang/StringBuilder.toString:()Ljava/lang/String;
      53: aload_2
      54: invokespecial #591                // Method org/bouncycastle/util/StoreException."<init>":(Ljava/lang/String;Ljava/lang/Throwable;)V
      57: athrow
      58: aconst_null
      59: areturn
    Exception table:
       from    to  target type
           0    22    26   Class java/io/IOException

  private javax.security.auth.x500.X500Principal getCertificateIssuer(java.security.cert.X509Certificate);
    Code:
       0: aload_1
       1: invokevirtual #522                // Method java/security/cert/X509Certificate.getIssuerX500Principal:()Ljavax/security/auth/x500/X500Principal;
       4: areturn

  static {};
    Code:
       0: ldc           #14                 // String com.sun.jndi.ldap.LdapCtxFactory
       2: putstatic     #497                // Field LDAP_PROVIDER:Ljava/lang/String;
       5: ldc           #17                 // String ignore
       7: putstatic     #498                // Field REFERRALS_IGNORE:Ljava/lang/String;
      10: bipush        32
      12: putstatic     #495                // Field cacheSize:I
      15: ldc2_w        #247                // long 60000l
      18: putstatic     #496                // Field lifeTime:J
      21: return
}
