Compiled from "TupleIndexRecord.java"
public class org.apache.jena.tdb.store.tupletable.TupleIndexRecord extends org.apache.jena.tdb.store.tupletable.TupleIndexBase {
  private static final boolean Check;

  private org.apache.jena.tdb.index.RangeIndex index;

  private org.apache.jena.tdb.base.record.RecordFactory factory;

  public org.apache.jena.tdb.store.tupletable.TupleIndexRecord(int, org.apache.jena.tdb.lib.ColumnMap, java.lang.String, org.apache.jena.tdb.base.record.RecordFactory, org.apache.jena.tdb.index.RangeIndex);
    Code:
       0: aload_0
       1: iload_1
       2: aload_2
       3: aload_3
       4: invokespecial #3                  // Method org/apache/jena/tdb/store/tupletable/TupleIndexBase."<init>":(ILorg/apache/jena/tdb/lib/ColumnMap;Ljava/lang/String;)V
       7: aload_0
       8: aload         4
      10: putfield      #4                  // Field factory:Lorg/apache/jena/tdb/base/record/RecordFactory;
      13: aload_0
      14: aload         5
      16: putfield      #5                  // Field index:Lorg/apache/jena/tdb/index/RangeIndex;
      19: aload         4
      21: invokevirtual #6                  // Method org/apache/jena/tdb/base/record/RecordFactory.keyLength:()I
      24: iload_1
      25: bipush        8
      27: imul
      28: if_icmpeq     66
      31: new           #7                  // class org/apache/jena/tdb/TDBException
      34: dup
      35: ldc           #8                  // String Mismatch: TupleIndex of length %d is not comparative with a factory for key length %d
      37: iconst_2
      38: anewarray     #9                  // class java/lang/Object
      41: dup
      42: iconst_0
      43: iload_1
      44: invokestatic  #10                 // Method java/lang/Integer.valueOf:(I)Ljava/lang/Integer;
      47: aastore
      48: dup
      49: iconst_1
      50: aload         4
      52: invokevirtual #6                  // Method org/apache/jena/tdb/base/record/RecordFactory.keyLength:()I
      55: invokestatic  #10                 // Method java/lang/Integer.valueOf:(I)Ljava/lang/Integer;
      58: aastore
      59: invokestatic  #11                 // Method java/lang/String.format:(Ljava/lang/String;[Ljava/lang/Object;)Ljava/lang/String;
      62: invokespecial #12                 // Method org/apache/jena/tdb/TDBException."<init>":(Ljava/lang/String;)V
      65: athrow
      66: return

  protected boolean performAdd(org.apache.jena.atlas.lib.tuple.Tuple<org.apache.jena.tdb.store.NodeId>);
    Code:
       0: aload_0
       1: getfield      #4                  // Field factory:Lorg/apache/jena/tdb/base/record/RecordFactory;
       4: aload_1
       5: aload_0
       6: getfield      #13                 // Field colMap:Lorg/apache/jena/tdb/lib/ColumnMap;
       9: invokestatic  #14                 // Method org/apache/jena/tdb/lib/TupleLib.record:(Lorg/apache/jena/tdb/base/record/RecordFactory;Lorg/apache/jena/atlas/lib/tuple/Tuple;Lorg/apache/jena/tdb/lib/ColumnMap;)Lorg/apache/jena/tdb/base/record/Record;
      12: astore_2
      13: aload_0
      14: getfield      #5                  // Field index:Lorg/apache/jena/tdb/index/RangeIndex;
      17: aload_2
      18: invokeinterface #15,  2           // InterfaceMethod org/apache/jena/tdb/index/RangeIndex.add:(Lorg/apache/jena/tdb/base/record/Record;)Z
      23: ireturn

  protected boolean performDelete(org.apache.jena.atlas.lib.tuple.Tuple<org.apache.jena.tdb.store.NodeId>);
    Code:
       0: aload_0
       1: getfield      #4                  // Field factory:Lorg/apache/jena/tdb/base/record/RecordFactory;
       4: aload_1
       5: aload_0
       6: getfield      #13                 // Field colMap:Lorg/apache/jena/tdb/lib/ColumnMap;
       9: invokestatic  #14                 // Method org/apache/jena/tdb/lib/TupleLib.record:(Lorg/apache/jena/tdb/base/record/RecordFactory;Lorg/apache/jena/atlas/lib/tuple/Tuple;Lorg/apache/jena/tdb/lib/ColumnMap;)Lorg/apache/jena/tdb/base/record/Record;
      12: astore_2
      13: aload_0
      14: getfield      #5                  // Field index:Lorg/apache/jena/tdb/index/RangeIndex;
      17: aload_2
      18: invokeinterface #16,  2           // InterfaceMethod org/apache/jena/tdb/index/RangeIndex.delete:(Lorg/apache/jena/tdb/base/record/Record;)Z
      23: ireturn

  protected java.util.Iterator<org.apache.jena.atlas.lib.tuple.Tuple<org.apache.jena.tdb.store.NodeId>> performFind(org.apache.jena.atlas.lib.tuple.Tuple<org.apache.jena.tdb.store.NodeId>);
    Code:
       0: aload_0
       1: aload_1
       2: invokevirtual #17                 // Method findOrScan:(Lorg/apache/jena/atlas/lib/tuple/Tuple;)Ljava/util/Iterator;
       5: areturn

  final java.util.Iterator<org.apache.jena.atlas.lib.tuple.Tuple<org.apache.jena.tdb.store.NodeId>> findOrScan(org.apache.jena.atlas.lib.tuple.Tuple<org.apache.jena.tdb.store.NodeId>);
    Code:
       0: aload_0
       1: aload_1
       2: iconst_1
       3: iconst_1
       4: invokespecial #18                 // Method findWorker:(Lorg/apache/jena/atlas/lib/tuple/Tuple;ZZ)Ljava/util/Iterator;
       7: areturn

  final java.util.Iterator<org.apache.jena.atlas.lib.tuple.Tuple<org.apache.jena.tdb.store.NodeId>> findOrPartialScan(org.apache.jena.atlas.lib.tuple.Tuple<org.apache.jena.tdb.store.NodeId>);
    Code:
       0: aload_0
       1: aload_1
       2: iconst_1
       3: iconst_0
       4: invokespecial #18                 // Method findWorker:(Lorg/apache/jena/atlas/lib/tuple/Tuple;ZZ)Ljava/util/Iterator;
       7: areturn

  final java.util.Iterator<org.apache.jena.atlas.lib.tuple.Tuple<org.apache.jena.tdb.store.NodeId>> findByIndex(org.apache.jena.atlas.lib.tuple.Tuple<org.apache.jena.tdb.store.NodeId>);
    Code:
       0: aload_0
       1: aload_1
       2: iconst_0
       3: iconst_0
       4: invokespecial #18                 // Method findWorker:(Lorg/apache/jena/atlas/lib/tuple/Tuple;ZZ)Ljava/util/Iterator;
       7: areturn

  private java.util.Iterator<org.apache.jena.atlas.lib.tuple.Tuple<org.apache.jena.tdb.store.NodeId>> findWorker(org.apache.jena.atlas.lib.tuple.Tuple<org.apache.jena.tdb.store.NodeId>, boolean, boolean);
    Code:
       0: aload_0
       1: getfield      #13                 // Field colMap:Lorg/apache/jena/tdb/lib/ColumnMap;
       4: aload_1
       5: invokevirtual #19                 // Method org/apache/jena/tdb/lib/ColumnMap.map:(Lorg/apache/jena/atlas/lib/tuple/Tuple;)Lorg/apache/jena/atlas/lib/tuple/Tuple;
       8: astore        4
      10: iconst_0
      11: istore        5
      13: bipush        -2
      15: istore        6
      17: iconst_1
      18: istore        7
      20: aload_0
      21: getfield      #4                  // Field factory:Lorg/apache/jena/tdb/base/record/RecordFactory;
      24: invokevirtual #20                 // Method org/apache/jena/tdb/base/record/RecordFactory.createKeyOnly:()Lorg/apache/jena/tdb/base/record/Record;
      27: astore        8
      29: aload_0
      30: getfield      #4                  // Field factory:Lorg/apache/jena/tdb/base/record/RecordFactory;
      33: invokevirtual #20                 // Method org/apache/jena/tdb/base/record/RecordFactory.createKeyOnly:()Lorg/apache/jena/tdb/base/record/Record;
      36: astore        9
      38: iconst_0
      39: istore        10
      41: iload         10
      43: aload         4
      45: invokeinterface #21,  1           // InterfaceMethod org/apache/jena/atlas/lib/tuple/Tuple.len:()I
      50: if_icmpge     138
      53: aload         4
      55: iload         10
      57: invokeinterface #22,  2           // InterfaceMethod org/apache/jena/atlas/lib/tuple/Tuple.get:(I)Ljava/lang/Object;
      62: checkcast     #23                 // class org/apache/jena/tdb/store/NodeId
      65: astore        11
      67: aload         11
      69: invokestatic  #24                 // Method org/apache/jena/tdb/store/NodeId.isAny:(Lorg/apache/jena/tdb/store/NodeId;)Z
      72: ifeq          84
      75: aconst_null
      76: astore        11
      78: iconst_0
      79: istore        7
      81: goto          132
      84: iinc          5, 1
      87: iload         7
      89: ifeq          132
      92: iload         10
      94: istore        6
      96: aload         11
      98: invokevirtual #25                 // Method org/apache/jena/tdb/store/NodeId.getId:()J
     101: aload         8
     103: invokevirtual #26                 // Method org/apache/jena/tdb/base/record/Record.getKey:()[B
     106: iload         10
     108: bipush        8
     110: imul
     111: invokestatic  #27                 // Method org/apache/jena/atlas/lib/Bytes.setLong:(J[BI)V
     114: aload         11
     116: invokevirtual #25                 // Method org/apache/jena/tdb/store/NodeId.getId:()J
     119: aload         9
     121: invokevirtual #26                 // Method org/apache/jena/tdb/base/record/Record.getKey:()[B
     124: iload         10
     126: bipush        8
     128: imul
     129: invokestatic  #27                 // Method org/apache/jena/atlas/lib/Bytes.setLong:(J[BI)V
     132: iinc          10, 1
     135: goto          41
     138: iload         5
     140: aload         4
     142: invokeinterface #21,  1           // InterfaceMethod org/apache/jena/atlas/lib/tuple/Tuple.len:()I
     147: if_icmpne     182
     150: aload_0
     151: getfield      #5                  // Field index:Lorg/apache/jena/tdb/index/RangeIndex;
     154: aload         8
     156: invokeinterface #28,  2           // InterfaceMethod org/apache/jena/tdb/index/RangeIndex.contains:(Lorg/apache/jena/tdb/base/record/Record;)Z
     161: ifeq          174
     164: new           #29                 // class org/apache/jena/atlas/iterator/SingletonIterator
     167: dup
     168: aload         4
     170: invokespecial #30                 // Method org/apache/jena/atlas/iterator/SingletonIterator."<init>":(Ljava/lang/Object;)V
     173: areturn
     174: new           #31                 // class org/apache/jena/atlas/iterator/NullIterator
     177: dup
     178: invokespecial #32                 // Method org/apache/jena/atlas/iterator/NullIterator."<init>":()V
     181: areturn
     182: aconst_null
     183: astore        10
     185: iload         6
     187: ifge          210
     190: iload_3
     191: ifne          196
     194: aconst_null
     195: areturn
     196: aload_0
     197: getfield      #5                  // Field index:Lorg/apache/jena/tdb/index/RangeIndex;
     200: invokeinterface #33,  1           // InterfaceMethod org/apache/jena/tdb/index/RangeIndex.iterator:()Ljava/util/Iterator;
     205: astore        10
     207: goto          259
     210: aload         4
     212: iload         6
     214: invokeinterface #22,  2           // InterfaceMethod org/apache/jena/atlas/lib/tuple/Tuple.get:(I)Ljava/lang/Object;
     219: checkcast     #23                 // class org/apache/jena/tdb/store/NodeId
     222: astore        11
     224: aload         11
     226: invokevirtual #25                 // Method org/apache/jena/tdb/store/NodeId.getId:()J
     229: lconst_1
     230: ladd
     231: aload         9
     233: invokevirtual #26                 // Method org/apache/jena/tdb/base/record/Record.getKey:()[B
     236: iload         6
     238: bipush        8
     240: imul
     241: invokestatic  #27                 // Method org/apache/jena/atlas/lib/Bytes.setLong:(J[BI)V
     244: aload_0
     245: getfield      #5                  // Field index:Lorg/apache/jena/tdb/index/RangeIndex;
     248: aload         8
     250: aload         9
     252: invokeinterface #34,  3           // InterfaceMethod org/apache/jena/tdb/index/RangeIndex.iterator:(Lorg/apache/jena/tdb/base/record/Record;Lorg/apache/jena/tdb/base/record/Record;)Ljava/util/Iterator;
     257: astore        10
     259: aload         10
     261: aload_0
     262: invokedynamic #35,  0             // InvokeDynamic #0:apply:(Lorg/apache/jena/tdb/store/tupletable/TupleIndexRecord;)Ljava/util/function/Function;
     267: invokestatic  #36                 // Method org/apache/jena/atlas/iterator/Iter.map:(Ljava/util/Iterator;Ljava/util/function/Function;)Ljava/util/Iterator;
     270: astore        11
     272: iload         6
     274: iload         5
     276: iconst_1
     277: isub
     278: if_icmpge     295
     281: iload_2
     282: ifne          287
     285: aconst_null
     286: areturn
     287: aload         11
     289: aload_1
     290: invokestatic  #37                 // InterfaceMethod org/apache/jena/tdb/store/tupletable/TupleIndex.scan:(Ljava/util/Iterator;Lorg/apache/jena/atlas/lib/tuple/Tuple;)Ljava/util/Iterator;
     293: astore        11
     295: aload         11
     297: areturn

  public java.util.Iterator<org.apache.jena.atlas.lib.tuple.Tuple<org.apache.jena.tdb.store.NodeId>> all();
    Code:
       0: aload_0
       1: getfield      #5                  // Field index:Lorg/apache/jena/tdb/index/RangeIndex;
       4: invokeinterface #33,  1           // InterfaceMethod org/apache/jena/tdb/index/RangeIndex.iterator:()Ljava/util/Iterator;
       9: astore_1
      10: aload_1
      11: aload_0
      12: invokedynamic #38,  0             // InvokeDynamic #1:apply:(Lorg/apache/jena/tdb/store/tupletable/TupleIndexRecord;)Ljava/util/function/Function;
      17: invokestatic  #36                 // Method org/apache/jena/atlas/iterator/Iter.map:(Ljava/util/Iterator;Ljava/util/function/Function;)Ljava/util/Iterator;
      20: areturn

  public void close();
    Code:
       0: aload_0
       1: getfield      #5                  // Field index:Lorg/apache/jena/tdb/index/RangeIndex;
       4: invokeinterface #39,  1           // InterfaceMethod org/apache/jena/tdb/index/RangeIndex.close:()V
       9: return

  public void sync();
    Code:
       0: aload_0
       1: getfield      #5                  // Field index:Lorg/apache/jena/tdb/index/RangeIndex;
       4: invokeinterface #40,  1           // InterfaceMethod org/apache/jena/tdb/index/RangeIndex.sync:()V
       9: return

  public final org.apache.jena.tdb.index.RangeIndex getRangeIndex();
    Code:
       0: aload_0
       1: getfield      #5                  // Field index:Lorg/apache/jena/tdb/index/RangeIndex;
       4: areturn

  public boolean isEmpty();
    Code:
       0: aload_0
       1: getfield      #5                  // Field index:Lorg/apache/jena/tdb/index/RangeIndex;
       4: invokeinterface #41,  1           // InterfaceMethod org/apache/jena/tdb/index/RangeIndex.isEmpty:()Z
       9: ireturn

  public void clear();
    Code:
       0: aload_0
       1: getfield      #5                  // Field index:Lorg/apache/jena/tdb/index/RangeIndex;
       4: invokeinterface #42,  1           // InterfaceMethod org/apache/jena/tdb/index/RangeIndex.clear:()V
       9: return

  public long size();
    Code:
       0: aload_0
       1: getfield      #5                  // Field index:Lorg/apache/jena/tdb/index/RangeIndex;
       4: invokeinterface #43,  1           // InterfaceMethod org/apache/jena/tdb/index/RangeIndex.size:()J
       9: lreturn

  private org.apache.jena.atlas.lib.tuple.Tuple lambda$all$1(org.apache.jena.tdb.base.record.Record);
    Code:
       0: aload_1
       1: aload_0
       2: getfield      #13                 // Field colMap:Lorg/apache/jena/tdb/lib/ColumnMap;
       5: invokestatic  #44                 // Method org/apache/jena/tdb/lib/TupleLib.tuple:(Lorg/apache/jena/tdb/base/record/Record;Lorg/apache/jena/tdb/lib/ColumnMap;)Lorg/apache/jena/atlas/lib/tuple/Tuple;
       8: areturn

  private org.apache.jena.atlas.lib.tuple.Tuple lambda$findWorker$0(org.apache.jena.tdb.base.record.Record);
    Code:
       0: aload_1
       1: aload_0
       2: getfield      #13                 // Field colMap:Lorg/apache/jena/tdb/lib/ColumnMap;
       5: invokestatic  #44                 // Method org/apache/jena/tdb/lib/TupleLib.tuple:(Lorg/apache/jena/tdb/base/record/Record;Lorg/apache/jena/tdb/lib/ColumnMap;)Lorg/apache/jena/atlas/lib/tuple/Tuple;
       8: areturn
}
