Compiled from "TrackableBase.java"
public class org.apache.maven.settings.TrackableBase implements java.io.Serializable,java.lang.Cloneable {
  public static final java.lang.String USER_LEVEL;

  public static final java.lang.String GLOBAL_LEVEL;

  private java.lang.String sourceLevel;

  private boolean sourceLevelSet;

  public org.apache.maven.settings.TrackableBase();
    Code:
       0: aload_0
       1: invokespecial #1                  // Method java/lang/Object."<init>":()V
       4: aload_0
       5: ldc           #2                  // String user-level
       7: putfield      #3                  // Field sourceLevel:Ljava/lang/String;
      10: aload_0
      11: iconst_0
      12: putfield      #4                  // Field sourceLevelSet:Z
      15: return

  public org.apache.maven.settings.TrackableBase clone();
    Code:
       0: aload_0
       1: invokespecial #5                  // Method java/lang/Object.clone:()Ljava/lang/Object;
       4: checkcast     #6                  // class org/apache/maven/settings/TrackableBase
       7: astore_1
       8: aload_1
       9: areturn
      10: astore_1
      11: new           #8                  // class java/lang/UnsupportedOperationException
      14: dup
      15: new           #9                  // class java/lang/StringBuilder
      18: dup
      19: invokespecial #10                 // Method java/lang/StringBuilder."<init>":()V
      22: aload_0
      23: invokevirtual #11                 // Method java/lang/Object.getClass:()Ljava/lang/Class;
      26: invokevirtual #12                 // Method java/lang/Class.getName:()Ljava/lang/String;
      29: invokevirtual #13                 // Method java/lang/StringBuilder.append:(Ljava/lang/String;)Ljava/lang/StringBuilder;
      32: ldc           #14                 // String  does not support clone()
      34: invokevirtual #13                 // Method java/lang/StringBuilder.append:(Ljava/lang/String;)Ljava/lang/StringBuilder;
      37: invokevirtual #15                 // Method java/lang/StringBuilder.toString:()Ljava/lang/String;
      40: invokespecial #16                 // Method java/lang/UnsupportedOperationException."<init>":(Ljava/lang/String;)V
      43: aload_1
      44: invokevirtual #17                 // Method java/lang/UnsupportedOperationException.initCause:(Ljava/lang/Throwable;)Ljava/lang/Throwable;
      47: checkcast     #18                 // class java/lang/RuntimeException
      50: athrow
    Exception table:
       from    to  target type
           0     9    10   Class java/lang/Exception

  public void setSourceLevel(java.lang.String);
    Code:
       0: aload_0
       1: getfield      #4                  // Field sourceLevelSet:Z
       4: ifeq          34
       7: new           #19                 // class java/lang/IllegalStateException
      10: dup
      11: new           #9                  // class java/lang/StringBuilder
      14: dup
      15: invokespecial #10                 // Method java/lang/StringBuilder."<init>":()V
      18: ldc           #20                 // String Cannot reset sourceLevel attribute; it is already set to:
      20: invokevirtual #13                 // Method java/lang/StringBuilder.append:(Ljava/lang/String;)Ljava/lang/StringBuilder;
      23: aload_1
      24: invokevirtual #13                 // Method java/lang/StringBuilder.append:(Ljava/lang/String;)Ljava/lang/StringBuilder;
      27: invokevirtual #15                 // Method java/lang/StringBuilder.toString:()Ljava/lang/String;
      30: invokespecial #21                 // Method java/lang/IllegalStateException."<init>":(Ljava/lang/String;)V
      33: athrow
      34: ldc           #2                  // String user-level
      36: aload_1
      37: invokevirtual #22                 // Method java/lang/String.equals:(Ljava/lang/Object;)Z
      40: ifne          62
      43: ldc           #23                 // String global-level
      45: aload_1
      46: invokevirtual #22                 // Method java/lang/String.equals:(Ljava/lang/Object;)Z
      49: ifne          62
      52: new           #24                 // class java/lang/IllegalArgumentException
      55: dup
      56: ldc           #25                 // String sourceLevel must be one of: {user-level,global-level}
      58: invokespecial #26                 // Method java/lang/IllegalArgumentException."<init>":(Ljava/lang/String;)V
      61: athrow
      62: aload_0
      63: aload_1
      64: putfield      #3                  // Field sourceLevel:Ljava/lang/String;
      67: aload_0
      68: iconst_1
      69: putfield      #4                  // Field sourceLevelSet:Z
      72: return

  public java.lang.String getSourceLevel();
    Code:
       0: aload_0
       1: getfield      #3                  // Field sourceLevel:Ljava/lang/String;
       4: areturn

  public java.lang.Object clone() throws java.lang.CloneNotSupportedException;
    Code:
       0: aload_0
       1: invokevirtual #27                 // Method clone:()Lorg/apache/maven/settings/TrackableBase;
       4: areturn
}
