Compiled from "JibxDataFormat.java"
public class org.apache.camel.model.dataformat.JibxDataFormat extends org.apache.camel.model.DataFormatDefinition {
  private java.lang.String unmarshallTypeName;

  private java.lang.Class<?> unmarshallClass;

  public org.apache.camel.model.dataformat.JibxDataFormat();
    Code:
       0: aload_0
       1: ldc           #22                 // String jibx
       3: invokespecial #25                 // Method org/apache/camel/model/DataFormatDefinition."<init>":(Ljava/lang/String;)V
       6: return

  public org.apache.camel.model.dataformat.JibxDataFormat(java.lang.Class<?>);
    Code:
       0: aload_0
       1: invokespecial #30                 // Method "<init>":()V
       4: aload_0
       5: aload_1
       6: invokevirtual #33                 // Method setUnmarshallClass:(Ljava/lang/Class;)V
       9: return

  public java.lang.Class<?> getUnmarshallClass();
    Code:
       0: aload_0
       1: getfield      #37                 // Field unmarshallClass:Ljava/lang/Class;
       4: areturn

  public void setUnmarshallClass(java.lang.Class<?>);
    Code:
       0: aload_0
       1: aload_1
       2: putfield      #37                 // Field unmarshallClass:Ljava/lang/Class;
       5: return

  public java.lang.String getUnmarshallTypeName();
    Code:
       0: aload_0
       1: getfield      #41                 // Field unmarshallTypeName:Ljava/lang/String;
       4: areturn

  public void setUnmarshallTypeName(java.lang.String);
    Code:
       0: aload_0
       1: aload_1
       2: putfield      #41                 // Field unmarshallTypeName:Ljava/lang/String;
       5: return

  protected org.apache.camel.spi.DataFormat createDataFormat(org.apache.camel.spi.RouteContext);
    Code:
       0: aload_0
       1: getfield      #37                 // Field unmarshallClass:Ljava/lang/Class;
       4: ifnonnull     47
       7: aload_0
       8: getfield      #41                 // Field unmarshallTypeName:Ljava/lang/String;
      11: ifnull        47
      14: aload_0
      15: aload_1
      16: invokeinterface #52,  1           // InterfaceMethod org/apache/camel/spi/RouteContext.getCamelContext:()Lorg/apache/camel/CamelContext;
      21: invokeinterface #58,  1           // InterfaceMethod org/apache/camel/CamelContext.getClassResolver:()Lorg/apache/camel/spi/ClassResolver;
      26: aload_0
      27: getfield      #41                 // Field unmarshallTypeName:Ljava/lang/String;
      30: invokeinterface #64,  2           // InterfaceMethod org/apache/camel/spi/ClassResolver.resolveMandatoryClass:(Ljava/lang/String;)Ljava/lang/Class;
      35: putfield      #37                 // Field unmarshallClass:Ljava/lang/Class;
      38: goto          47
      41: astore_2
      42: aload_2
      43: invokestatic  #70                 // Method org/apache/camel/util/ObjectHelper.wrapRuntimeCamelException:(Ljava/lang/Throwable;)Lorg/apache/camel/RuntimeCamelException;
      46: athrow
      47: aload_0
      48: aload_1
      49: invokespecial #72                 // Method org/apache/camel/model/DataFormatDefinition.createDataFormat:(Lorg/apache/camel/spi/RouteContext;)Lorg/apache/camel/spi/DataFormat;
      52: areturn
    Exception table:
       from    to  target type
          14    38    41   Class java/lang/ClassNotFoundException

  protected void configureDataFormat(org.apache.camel.spi.DataFormat, org.apache.camel.CamelContext);
    Code:
       0: aload_0
       1: getfield      #37                 // Field unmarshallClass:Ljava/lang/Class;
       4: ifnull        19
       7: aload_0
       8: aload_2
       9: aload_1
      10: ldc           #79                 // String unmarshallClass
      12: aload_0
      13: getfield      #37                 // Field unmarshallClass:Ljava/lang/Class;
      16: invokevirtual #83                 // Method setProperty:(Lorg/apache/camel/CamelContext;Ljava/lang/Object;Ljava/lang/String;Ljava/lang/Object;)V
      19: return
}
