Compiled from "ConstraintDefinitionType.java"
public class org.hibernate.validator.internal.xml.ConstraintDefinitionType {
  protected org.hibernate.validator.internal.xml.ValidatedByType validatedBy;

  protected java.lang.String annotation;

  public org.hibernate.validator.internal.xml.ConstraintDefinitionType();
    Code:
       0: aload_0
       1: invokespecial #1                  // Method java/lang/Object."<init>":()V
       4: return

  public org.hibernate.validator.internal.xml.ValidatedByType getValidatedBy();
    Code:
       0: aload_0
       1: getfield      #2                  // Field validatedBy:Lorg/hibernate/validator/internal/xml/ValidatedByType;
       4: areturn

  public void setValidatedBy(org.hibernate.validator.internal.xml.ValidatedByType);
    Code:
       0: aload_0
       1: aload_1
       2: putfield      #2                  // Field validatedBy:Lorg/hibernate/validator/internal/xml/ValidatedByType;
       5: return

  public java.lang.String getAnnotation();
    Code:
       0: aload_0
       1: getfield      #3                  // Field annotation:Ljava/lang/String;
       4: areturn

  public void setAnnotation(java.lang.String);
    Code:
       0: aload_0
       1: aload_1
       2: putfield      #3                  // Field annotation:Ljava/lang/String;
       5: return
}
