Compiled from "Chunk.kt"
final class io.floodplain.ChunkKt$bufferTimeout$3$1$upstreamValues$1 extends kotlin.coroutines.jvm.internal.SuspendLambda implements kotlin.jvm.functions.Function2<kotlinx.coroutines.channels.ProducerScope<? super T>, kotlin.coroutines.Continuation<? super kotlin.Unit>, java.lang.Object> {
  private java.lang.Object L$0;

  int label;

  final io.floodplain.ChunkKt$bufferTimeout$3$1 this$0;

  public final java.lang.Object invokeSuspend(java.lang.Object);
    Code:
       0: invokestatic  #31                 // Method kotlin/coroutines/intrinsics/IntrinsicsKt.getCOROUTINE_SUSPENDED:()Ljava/lang/Object;
       3: astore        6
       5: aload_0
       6: getfield      #35                 // Field label:I
       9: tableswitch   { // 0 to 1
                     0: 32
                     1: 94
               default: 107
          }
      32: aload_1
      33: invokestatic  #41                 // Method kotlin/ResultKt.throwOnFailure:(Ljava/lang/Object;)V
      36: aload_0
      37: getfield      #43                 // Field L$0:Ljava/lang/Object;
      40: checkcast     #45                 // class kotlinx/coroutines/channels/ProducerScope
      43: astore_2
      44: aload_0
      45: getfield      #49                 // Field this$0:Lio/floodplain/ChunkKt$bufferTimeout$3$1;
      48: getfield      #54                 // Field io/floodplain/ChunkKt$bufferTimeout$3$1.this$0:Lio/floodplain/ChunkKt$bufferTimeout$3;
      51: getfield      #60                 // Field io/floodplain/ChunkKt$bufferTimeout$3.$this_bufferTimeout:Lkotlinx/coroutines/flow/Flow;
      54: astore_3
      55: aload_0
      56: astore        4
      58: iconst_0
      59: istore        5
      61: aload_3
      62: new           #62                 // class io/floodplain/ChunkKt$bufferTimeout$3$1$upstreamValues$1$invokeSuspend$$inlined$collect$1
      65: dup
      66: aload_2
      67: invokespecial #66                 // Method io/floodplain/ChunkKt$bufferTimeout$3$1$upstreamValues$1$invokeSuspend$$inlined$collect$1."<init>":(Lkotlinx/coroutines/channels/ProducerScope;)V
      70: checkcast     #68                 // class kotlinx/coroutines/flow/FlowCollector
      73: aload         4
      75: aload_0
      76: iconst_1
      77: putfield      #35                 // Field label:I
      80: invokeinterface #74,  3           // InterfaceMethod kotlinx/coroutines/flow/Flow.collect:(Lkotlinx/coroutines/flow/FlowCollector;Lkotlin/coroutines/Continuation;)Ljava/lang/Object;
      85: dup
      86: aload         6
      88: if_acmpne     102
      91: aload         6
      93: areturn
      94: iconst_0
      95: istore        5
      97: aload_1
      98: invokestatic  #41                 // Method kotlin/ResultKt.throwOnFailure:(Ljava/lang/Object;)V
     101: aload_1
     102: pop
     103: getstatic     #80                 // Field kotlin/Unit.INSTANCE:Lkotlin/Unit;
     106: areturn
     107: new           #82                 // class java/lang/IllegalStateException
     110: dup
     111: ldc           #84                 // String call to \'resume\' before \'invoke\' with coroutine
     113: invokespecial #87                 // Method java/lang/IllegalStateException."<init>":(Ljava/lang/String;)V
     116: athrow

  io.floodplain.ChunkKt$bufferTimeout$3$1$upstreamValues$1(io.floodplain.ChunkKt$bufferTimeout$3$1, kotlin.coroutines.Continuation);
    Code:
       0: aload_0
       1: aload_1
       2: putfield      #49                 // Field this$0:Lio/floodplain/ChunkKt$bufferTimeout$3$1;
       5: aload_0
       6: iconst_2
       7: aload_2
       8: invokespecial #99                 // Method kotlin/coroutines/jvm/internal/SuspendLambda."<init>":(ILkotlin/coroutines/Continuation;)V
      11: return

  public final kotlin.coroutines.Continuation<kotlin.Unit> create(java.lang.Object, kotlin.coroutines.Continuation<?>);
    Code:
       0: aload_2
       1: ldc           #105                // String completion
       3: invokestatic  #111                // Method kotlin/jvm/internal/Intrinsics.checkNotNullParameter:(Ljava/lang/Object;Ljava/lang/String;)V
       6: new           #2                  // class io/floodplain/ChunkKt$bufferTimeout$3$1$upstreamValues$1
       9: dup
      10: aload_0
      11: getfield      #49                 // Field this$0:Lio/floodplain/ChunkKt$bufferTimeout$3$1;
      14: aload_2
      15: invokespecial #113                // Method "<init>":(Lio/floodplain/ChunkKt$bufferTimeout$3$1;Lkotlin/coroutines/Continuation;)V
      18: astore_3
      19: aload_1
      20: aload_3
      21: aload_1
      22: putfield      #43                 // Field L$0:Ljava/lang/Object;
      25: aload_3
      26: areturn

  public final java.lang.Object invoke(java.lang.Object, java.lang.Object);
    Code:
       0: aload_0
       1: aload_1
       2: aload_2
       3: checkcast     #119                // class kotlin/coroutines/Continuation
       6: invokevirtual #121                // Method create:(Ljava/lang/Object;Lkotlin/coroutines/Continuation;)Lkotlin/coroutines/Continuation;
       9: checkcast     #2                  // class io/floodplain/ChunkKt$bufferTimeout$3$1$upstreamValues$1
      12: getstatic     #80                 // Field kotlin/Unit.INSTANCE:Lkotlin/Unit;
      15: invokevirtual #123                // Method invokeSuspend:(Ljava/lang/Object;)Ljava/lang/Object;
      18: areturn
}
