Compiled from "DeleteRepositoryResponse.java"
public interface software.amazon.awssdk.services.proton.model.DeleteRepositoryResponse$Builder extends software.amazon.awssdk.services.proton.model.ProtonResponse$Builder, software.amazon.awssdk.core.SdkPojo, software.amazon.awssdk.utils.builder.CopyableBuilder<software.amazon.awssdk.services.proton.model.DeleteRepositoryResponse$Builder, software.amazon.awssdk.services.proton.model.DeleteRepositoryResponse> {
  public abstract software.amazon.awssdk.services.proton.model.DeleteRepositoryResponse$Builder repository(software.amazon.awssdk.services.proton.model.Repository);

  public default software.amazon.awssdk.services.proton.model.DeleteRepositoryResponse$Builder repository(java.util.function.Consumer<software.amazon.awssdk.services.proton.model.Repository$Builder>);
    Code:
       0: aload_0
       1: invokestatic  #1                  // Method software/amazon/awssdk/services/proton/model/Repository.builder:()Lsoftware/amazon/awssdk/services/proton/model/Repository$Builder;
       4: aload_1
       5: invokeinterface #2,  2            // InterfaceMethod software/amazon/awssdk/services/proton/model/Repository$Builder.applyMutation:(Ljava/util/function/Consumer;)Lsoftware/amazon/awssdk/utils/builder/SdkBuilder;
      10: checkcast     #3                  // class software/amazon/awssdk/services/proton/model/Repository$Builder
      13: invokeinterface #4,  1            // InterfaceMethod software/amazon/awssdk/services/proton/model/Repository$Builder.build:()Ljava/lang/Object;
      18: checkcast     #5                  // class software/amazon/awssdk/services/proton/model/Repository
      21: invokeinterface #6,  2            // InterfaceMethod repository:(Lsoftware/amazon/awssdk/services/proton/model/Repository;)Lsoftware/amazon/awssdk/services/proton/model/DeleteRepositoryResponse$Builder;
      26: areturn
}
