Compiled from "EnvironmentTemplateVersion.java"
final class software.amazon.awssdk.services.proton.model.EnvironmentTemplateVersion$BuilderImpl implements software.amazon.awssdk.services.proton.model.EnvironmentTemplateVersion$Builder {
  private java.lang.String arn;

  private java.time.Instant createdAt;

  private java.lang.String description;

  private java.time.Instant lastModifiedAt;

  private java.lang.String majorVersion;

  private java.lang.String minorVersion;

  private java.lang.String recommendedMinorVersion;

  private java.lang.String schema;

  private java.lang.String status;

  private java.lang.String statusMessage;

  private java.lang.String templateName;

  private software.amazon.awssdk.services.proton.model.EnvironmentTemplateVersion$BuilderImpl();
    Code:
       0: aload_0
       1: invokespecial #14                 // Method java/lang/Object."<init>":()V
       4: return

  private software.amazon.awssdk.services.proton.model.EnvironmentTemplateVersion$BuilderImpl(software.amazon.awssdk.services.proton.model.EnvironmentTemplateVersion);
    Code:
       0: aload_0
       1: invokespecial #14                 // Method java/lang/Object."<init>":()V
       4: aload_0
       5: aload_1
       6: invokestatic  #15                 // Method software/amazon/awssdk/services/proton/model/EnvironmentTemplateVersion.access$1300:(Lsoftware/amazon/awssdk/services/proton/model/EnvironmentTemplateVersion;)Ljava/lang/String;
       9: invokevirtual #16                 // Method arn:(Ljava/lang/String;)Lsoftware/amazon/awssdk/services/proton/model/EnvironmentTemplateVersion$Builder;
      12: pop
      13: aload_0
      14: aload_1
      15: invokestatic  #17                 // Method software/amazon/awssdk/services/proton/model/EnvironmentTemplateVersion.access$1400:(Lsoftware/amazon/awssdk/services/proton/model/EnvironmentTemplateVersion;)Ljava/time/Instant;
      18: invokevirtual #18                 // Method createdAt:(Ljava/time/Instant;)Lsoftware/amazon/awssdk/services/proton/model/EnvironmentTemplateVersion$Builder;
      21: pop
      22: aload_0
      23: aload_1
      24: invokestatic  #19                 // Method software/amazon/awssdk/services/proton/model/EnvironmentTemplateVersion.access$1500:(Lsoftware/amazon/awssdk/services/proton/model/EnvironmentTemplateVersion;)Ljava/lang/String;
      27: invokevirtual #20                 // Method description:(Ljava/lang/String;)Lsoftware/amazon/awssdk/services/proton/model/EnvironmentTemplateVersion$Builder;
      30: pop
      31: aload_0
      32: aload_1
      33: invokestatic  #21                 // Method software/amazon/awssdk/services/proton/model/EnvironmentTemplateVersion.access$1600:(Lsoftware/amazon/awssdk/services/proton/model/EnvironmentTemplateVersion;)Ljava/time/Instant;
      36: invokevirtual #22                 // Method lastModifiedAt:(Ljava/time/Instant;)Lsoftware/amazon/awssdk/services/proton/model/EnvironmentTemplateVersion$Builder;
      39: pop
      40: aload_0
      41: aload_1
      42: invokestatic  #23                 // Method software/amazon/awssdk/services/proton/model/EnvironmentTemplateVersion.access$1700:(Lsoftware/amazon/awssdk/services/proton/model/EnvironmentTemplateVersion;)Ljava/lang/String;
      45: invokevirtual #24                 // Method majorVersion:(Ljava/lang/String;)Lsoftware/amazon/awssdk/services/proton/model/EnvironmentTemplateVersion$Builder;
      48: pop
      49: aload_0
      50: aload_1
      51: invokestatic  #25                 // Method software/amazon/awssdk/services/proton/model/EnvironmentTemplateVersion.access$1800:(Lsoftware/amazon/awssdk/services/proton/model/EnvironmentTemplateVersion;)Ljava/lang/String;
      54: invokevirtual #26                 // Method minorVersion:(Ljava/lang/String;)Lsoftware/amazon/awssdk/services/proton/model/EnvironmentTemplateVersion$Builder;
      57: pop
      58: aload_0
      59: aload_1
      60: invokestatic  #27                 // Method software/amazon/awssdk/services/proton/model/EnvironmentTemplateVersion.access$1900:(Lsoftware/amazon/awssdk/services/proton/model/EnvironmentTemplateVersion;)Ljava/lang/String;
      63: invokevirtual #28                 // Method recommendedMinorVersion:(Ljava/lang/String;)Lsoftware/amazon/awssdk/services/proton/model/EnvironmentTemplateVersion$Builder;
      66: pop
      67: aload_0
      68: aload_1
      69: invokestatic  #29                 // Method software/amazon/awssdk/services/proton/model/EnvironmentTemplateVersion.access$2000:(Lsoftware/amazon/awssdk/services/proton/model/EnvironmentTemplateVersion;)Ljava/lang/String;
      72: invokevirtual #30                 // Method schema:(Ljava/lang/String;)Lsoftware/amazon/awssdk/services/proton/model/EnvironmentTemplateVersion$Builder;
      75: pop
      76: aload_0
      77: aload_1
      78: invokestatic  #31                 // Method software/amazon/awssdk/services/proton/model/EnvironmentTemplateVersion.access$2100:(Lsoftware/amazon/awssdk/services/proton/model/EnvironmentTemplateVersion;)Ljava/lang/String;
      81: invokevirtual #32                 // Method status:(Ljava/lang/String;)Lsoftware/amazon/awssdk/services/proton/model/EnvironmentTemplateVersion$Builder;
      84: pop
      85: aload_0
      86: aload_1
      87: invokestatic  #33                 // Method software/amazon/awssdk/services/proton/model/EnvironmentTemplateVersion.access$2200:(Lsoftware/amazon/awssdk/services/proton/model/EnvironmentTemplateVersion;)Ljava/lang/String;
      90: invokevirtual #34                 // Method statusMessage:(Ljava/lang/String;)Lsoftware/amazon/awssdk/services/proton/model/EnvironmentTemplateVersion$Builder;
      93: pop
      94: aload_0
      95: aload_1
      96: invokestatic  #35                 // Method software/amazon/awssdk/services/proton/model/EnvironmentTemplateVersion.access$2300:(Lsoftware/amazon/awssdk/services/proton/model/EnvironmentTemplateVersion;)Ljava/lang/String;
      99: invokevirtual #36                 // Method templateName:(Ljava/lang/String;)Lsoftware/amazon/awssdk/services/proton/model/EnvironmentTemplateVersion$Builder;
     102: pop
     103: return

  public final java.lang.String getArn();
    Code:
       0: aload_0
       1: getfield      #13                 // Field arn:Ljava/lang/String;
       4: areturn

  public final void setArn(java.lang.String);
    Code:
       0: aload_0
       1: aload_1
       2: putfield      #13                 // Field arn:Ljava/lang/String;
       5: return

  public final software.amazon.awssdk.services.proton.model.EnvironmentTemplateVersion$Builder arn(java.lang.String);
    Code:
       0: aload_0
       1: aload_1
       2: putfield      #13                 // Field arn:Ljava/lang/String;
       5: aload_0
       6: areturn

  public final java.time.Instant getCreatedAt();
    Code:
       0: aload_0
       1: getfield      #12                 // Field createdAt:Ljava/time/Instant;
       4: areturn

  public final void setCreatedAt(java.time.Instant);
    Code:
       0: aload_0
       1: aload_1
       2: putfield      #12                 // Field createdAt:Ljava/time/Instant;
       5: return

  public final software.amazon.awssdk.services.proton.model.EnvironmentTemplateVersion$Builder createdAt(java.time.Instant);
    Code:
       0: aload_0
       1: aload_1
       2: putfield      #12                 // Field createdAt:Ljava/time/Instant;
       5: aload_0
       6: areturn

  public final java.lang.String getDescription();
    Code:
       0: aload_0
       1: getfield      #11                 // Field description:Ljava/lang/String;
       4: areturn

  public final void setDescription(java.lang.String);
    Code:
       0: aload_0
       1: aload_1
       2: putfield      #11                 // Field description:Ljava/lang/String;
       5: return

  public final software.amazon.awssdk.services.proton.model.EnvironmentTemplateVersion$Builder description(java.lang.String);
    Code:
       0: aload_0
       1: aload_1
       2: putfield      #11                 // Field description:Ljava/lang/String;
       5: aload_0
       6: areturn

  public final java.time.Instant getLastModifiedAt();
    Code:
       0: aload_0
       1: getfield      #10                 // Field lastModifiedAt:Ljava/time/Instant;
       4: areturn

  public final void setLastModifiedAt(java.time.Instant);
    Code:
       0: aload_0
       1: aload_1
       2: putfield      #10                 // Field lastModifiedAt:Ljava/time/Instant;
       5: return

  public final software.amazon.awssdk.services.proton.model.EnvironmentTemplateVersion$Builder lastModifiedAt(java.time.Instant);
    Code:
       0: aload_0
       1: aload_1
       2: putfield      #10                 // Field lastModifiedAt:Ljava/time/Instant;
       5: aload_0
       6: areturn

  public final java.lang.String getMajorVersion();
    Code:
       0: aload_0
       1: getfield      #9                  // Field majorVersion:Ljava/lang/String;
       4: areturn

  public final void setMajorVersion(java.lang.String);
    Code:
       0: aload_0
       1: aload_1
       2: putfield      #9                  // Field majorVersion:Ljava/lang/String;
       5: return

  public final software.amazon.awssdk.services.proton.model.EnvironmentTemplateVersion$Builder majorVersion(java.lang.String);
    Code:
       0: aload_0
       1: aload_1
       2: putfield      #9                  // Field majorVersion:Ljava/lang/String;
       5: aload_0
       6: areturn

  public final java.lang.String getMinorVersion();
    Code:
       0: aload_0
       1: getfield      #8                  // Field minorVersion:Ljava/lang/String;
       4: areturn

  public final void setMinorVersion(java.lang.String);
    Code:
       0: aload_0
       1: aload_1
       2: putfield      #8                  // Field minorVersion:Ljava/lang/String;
       5: return

  public final software.amazon.awssdk.services.proton.model.EnvironmentTemplateVersion$Builder minorVersion(java.lang.String);
    Code:
       0: aload_0
       1: aload_1
       2: putfield      #8                  // Field minorVersion:Ljava/lang/String;
       5: aload_0
       6: areturn

  public final java.lang.String getRecommendedMinorVersion();
    Code:
       0: aload_0
       1: getfield      #7                  // Field recommendedMinorVersion:Ljava/lang/String;
       4: areturn

  public final void setRecommendedMinorVersion(java.lang.String);
    Code:
       0: aload_0
       1: aload_1
       2: putfield      #7                  // Field recommendedMinorVersion:Ljava/lang/String;
       5: return

  public final software.amazon.awssdk.services.proton.model.EnvironmentTemplateVersion$Builder recommendedMinorVersion(java.lang.String);
    Code:
       0: aload_0
       1: aload_1
       2: putfield      #7                  // Field recommendedMinorVersion:Ljava/lang/String;
       5: aload_0
       6: areturn

  public final java.lang.String getSchema();
    Code:
       0: aload_0
       1: getfield      #6                  // Field schema:Ljava/lang/String;
       4: areturn

  public final void setSchema(java.lang.String);
    Code:
       0: aload_0
       1: aload_1
       2: putfield      #6                  // Field schema:Ljava/lang/String;
       5: return

  public final software.amazon.awssdk.services.proton.model.EnvironmentTemplateVersion$Builder schema(java.lang.String);
    Code:
       0: aload_0
       1: aload_1
       2: putfield      #6                  // Field schema:Ljava/lang/String;
       5: aload_0
       6: areturn

  public final java.lang.String getStatus();
    Code:
       0: aload_0
       1: getfield      #5                  // Field status:Ljava/lang/String;
       4: areturn

  public final void setStatus(java.lang.String);
    Code:
       0: aload_0
       1: aload_1
       2: putfield      #5                  // Field status:Ljava/lang/String;
       5: return

  public final software.amazon.awssdk.services.proton.model.EnvironmentTemplateVersion$Builder status(java.lang.String);
    Code:
       0: aload_0
       1: aload_1
       2: putfield      #5                  // Field status:Ljava/lang/String;
       5: aload_0
       6: areturn

  public final software.amazon.awssdk.services.proton.model.EnvironmentTemplateVersion$Builder status(software.amazon.awssdk.services.proton.model.TemplateVersionStatus);
    Code:
       0: aload_0
       1: aload_1
       2: ifnonnull     9
       5: aconst_null
       6: goto          13
       9: aload_1
      10: invokevirtual #37                 // Method software/amazon/awssdk/services/proton/model/TemplateVersionStatus.toString:()Ljava/lang/String;
      13: invokevirtual #32                 // Method status:(Ljava/lang/String;)Lsoftware/amazon/awssdk/services/proton/model/EnvironmentTemplateVersion$Builder;
      16: pop
      17: aload_0
      18: areturn

  public final java.lang.String getStatusMessage();
    Code:
       0: aload_0
       1: getfield      #4                  // Field statusMessage:Ljava/lang/String;
       4: areturn

  public final void setStatusMessage(java.lang.String);
    Code:
       0: aload_0
       1: aload_1
       2: putfield      #4                  // Field statusMessage:Ljava/lang/String;
       5: return

  public final software.amazon.awssdk.services.proton.model.EnvironmentTemplateVersion$Builder statusMessage(java.lang.String);
    Code:
       0: aload_0
       1: aload_1
       2: putfield      #4                  // Field statusMessage:Ljava/lang/String;
       5: aload_0
       6: areturn

  public final java.lang.String getTemplateName();
    Code:
       0: aload_0
       1: getfield      #3                  // Field templateName:Ljava/lang/String;
       4: areturn

  public final void setTemplateName(java.lang.String);
    Code:
       0: aload_0
       1: aload_1
       2: putfield      #3                  // Field templateName:Ljava/lang/String;
       5: return

  public final software.amazon.awssdk.services.proton.model.EnvironmentTemplateVersion$Builder templateName(java.lang.String);
    Code:
       0: aload_0
       1: aload_1
       2: putfield      #3                  // Field templateName:Ljava/lang/String;
       5: aload_0
       6: areturn

  public software.amazon.awssdk.services.proton.model.EnvironmentTemplateVersion build();
    Code:
       0: new           #38                 // class software/amazon/awssdk/services/proton/model/EnvironmentTemplateVersion
       3: dup
       4: aload_0
       5: aconst_null
       6: invokespecial #39                 // Method software/amazon/awssdk/services/proton/model/EnvironmentTemplateVersion."<init>":(Lsoftware/amazon/awssdk/services/proton/model/EnvironmentTemplateVersion$BuilderImpl;Lsoftware/amazon/awssdk/services/proton/model/EnvironmentTemplateVersion$1;)V
       9: areturn

  public java.util.List<software.amazon.awssdk.core.SdkField<?>> sdkFields();
    Code:
       0: invokestatic  #40                 // Method software/amazon/awssdk/services/proton/model/EnvironmentTemplateVersion.access$2500:()Ljava/util/List;
       3: areturn

  public java.lang.Object build();
    Code:
       0: aload_0
       1: invokevirtual #41                 // Method build:()Lsoftware/amazon/awssdk/services/proton/model/EnvironmentTemplateVersion;
       4: areturn

  static java.lang.String access$000(software.amazon.awssdk.services.proton.model.EnvironmentTemplateVersion$BuilderImpl);
    Code:
       0: aload_0
       1: getfield      #13                 // Field arn:Ljava/lang/String;
       4: areturn

  static java.time.Instant access$100(software.amazon.awssdk.services.proton.model.EnvironmentTemplateVersion$BuilderImpl);
    Code:
       0: aload_0
       1: getfield      #12                 // Field createdAt:Ljava/time/Instant;
       4: areturn

  static java.lang.String access$200(software.amazon.awssdk.services.proton.model.EnvironmentTemplateVersion$BuilderImpl);
    Code:
       0: aload_0
       1: getfield      #11                 // Field description:Ljava/lang/String;
       4: areturn

  static java.time.Instant access$300(software.amazon.awssdk.services.proton.model.EnvironmentTemplateVersion$BuilderImpl);
    Code:
       0: aload_0
       1: getfield      #10                 // Field lastModifiedAt:Ljava/time/Instant;
       4: areturn

  static java.lang.String access$400(software.amazon.awssdk.services.proton.model.EnvironmentTemplateVersion$BuilderImpl);
    Code:
       0: aload_0
       1: getfield      #9                  // Field majorVersion:Ljava/lang/String;
       4: areturn

  static java.lang.String access$500(software.amazon.awssdk.services.proton.model.EnvironmentTemplateVersion$BuilderImpl);
    Code:
       0: aload_0
       1: getfield      #8                  // Field minorVersion:Ljava/lang/String;
       4: areturn

  static java.lang.String access$600(software.amazon.awssdk.services.proton.model.EnvironmentTemplateVersion$BuilderImpl);
    Code:
       0: aload_0
       1: getfield      #7                  // Field recommendedMinorVersion:Ljava/lang/String;
       4: areturn

  static java.lang.String access$700(software.amazon.awssdk.services.proton.model.EnvironmentTemplateVersion$BuilderImpl);
    Code:
       0: aload_0
       1: getfield      #6                  // Field schema:Ljava/lang/String;
       4: areturn

  static java.lang.String access$800(software.amazon.awssdk.services.proton.model.EnvironmentTemplateVersion$BuilderImpl);
    Code:
       0: aload_0
       1: getfield      #5                  // Field status:Ljava/lang/String;
       4: areturn

  static java.lang.String access$900(software.amazon.awssdk.services.proton.model.EnvironmentTemplateVersion$BuilderImpl);
    Code:
       0: aload_0
       1: getfield      #4                  // Field statusMessage:Ljava/lang/String;
       4: areturn

  static java.lang.String access$1000(software.amazon.awssdk.services.proton.model.EnvironmentTemplateVersion$BuilderImpl);
    Code:
       0: aload_0
       1: getfield      #3                  // Field templateName:Ljava/lang/String;
       4: areturn

  software.amazon.awssdk.services.proton.model.EnvironmentTemplateVersion$BuilderImpl(software.amazon.awssdk.services.proton.model.EnvironmentTemplateVersion, software.amazon.awssdk.services.proton.model.EnvironmentTemplateVersion$1);
    Code:
       0: aload_0
       1: aload_1
       2: invokespecial #2                  // Method "<init>":(Lsoftware/amazon/awssdk/services/proton/model/EnvironmentTemplateVersion;)V
       5: return

  software.amazon.awssdk.services.proton.model.EnvironmentTemplateVersion$BuilderImpl(software.amazon.awssdk.services.proton.model.EnvironmentTemplateVersion$1);
    Code:
       0: aload_0
       1: invokespecial #1                  // Method "<init>":()V
       4: return
}
