Compiled from "GetRepositorySyncStatusResponse.java"
public interface software.amazon.awssdk.services.proton.model.GetRepositorySyncStatusResponse$Builder extends software.amazon.awssdk.services.proton.model.ProtonResponse$Builder, software.amazon.awssdk.core.SdkPojo, software.amazon.awssdk.utils.builder.CopyableBuilder<software.amazon.awssdk.services.proton.model.GetRepositorySyncStatusResponse$Builder, software.amazon.awssdk.services.proton.model.GetRepositorySyncStatusResponse> {
  public abstract software.amazon.awssdk.services.proton.model.GetRepositorySyncStatusResponse$Builder latestSync(software.amazon.awssdk.services.proton.model.RepositorySyncAttempt);

  public default software.amazon.awssdk.services.proton.model.GetRepositorySyncStatusResponse$Builder latestSync(java.util.function.Consumer<software.amazon.awssdk.services.proton.model.RepositorySyncAttempt$Builder>);
    Code:
       0: aload_0
       1: invokestatic  #1                  // Method software/amazon/awssdk/services/proton/model/RepositorySyncAttempt.builder:()Lsoftware/amazon/awssdk/services/proton/model/RepositorySyncAttempt$Builder;
       4: aload_1
       5: invokeinterface #2,  2            // InterfaceMethod software/amazon/awssdk/services/proton/model/RepositorySyncAttempt$Builder.applyMutation:(Ljava/util/function/Consumer;)Lsoftware/amazon/awssdk/utils/builder/SdkBuilder;
      10: checkcast     #3                  // class software/amazon/awssdk/services/proton/model/RepositorySyncAttempt$Builder
      13: invokeinterface #4,  1            // InterfaceMethod software/amazon/awssdk/services/proton/model/RepositorySyncAttempt$Builder.build:()Ljava/lang/Object;
      18: checkcast     #5                  // class software/amazon/awssdk/services/proton/model/RepositorySyncAttempt
      21: invokeinterface #6,  2            // InterfaceMethod latestSync:(Lsoftware/amazon/awssdk/services/proton/model/RepositorySyncAttempt;)Lsoftware/amazon/awssdk/services/proton/model/GetRepositorySyncStatusResponse$Builder;
      26: areturn
}
