Compiled from "ResourceSyncAttempt.java"
final class software.amazon.awssdk.services.proton.model.ResourceSyncAttempt$BuilderImpl implements software.amazon.awssdk.services.proton.model.ResourceSyncAttempt$Builder {
  private java.util.List<software.amazon.awssdk.services.proton.model.ResourceSyncEvent> events;

  private software.amazon.awssdk.services.proton.model.Revision initialRevision;

  private java.time.Instant startedAt;

  private java.lang.String status;

  private java.lang.String target;

  private software.amazon.awssdk.services.proton.model.Revision targetRevision;

  private software.amazon.awssdk.services.proton.model.ResourceSyncAttempt$BuilderImpl();
    Code:
       0: aload_0
       1: invokespecial #9                  // Method java/lang/Object."<init>":()V
       4: aload_0
       5: invokestatic  #10                 // Method software/amazon/awssdk/core/util/DefaultSdkAutoConstructList.getInstance:()Lsoftware/amazon/awssdk/core/util/DefaultSdkAutoConstructList;
       8: putfield      #8                  // Field events:Ljava/util/List;
      11: return

  private software.amazon.awssdk.services.proton.model.ResourceSyncAttempt$BuilderImpl(software.amazon.awssdk.services.proton.model.ResourceSyncAttempt);
    Code:
       0: aload_0
       1: invokespecial #9                  // Method java/lang/Object."<init>":()V
       4: aload_0
       5: invokestatic  #10                 // Method software/amazon/awssdk/core/util/DefaultSdkAutoConstructList.getInstance:()Lsoftware/amazon/awssdk/core/util/DefaultSdkAutoConstructList;
       8: putfield      #8                  // Field events:Ljava/util/List;
      11: aload_0
      12: aload_1
      13: invokestatic  #11                 // Method software/amazon/awssdk/services/proton/model/ResourceSyncAttempt.access$800:(Lsoftware/amazon/awssdk/services/proton/model/ResourceSyncAttempt;)Ljava/util/List;
      16: invokevirtual #12                 // Method events:(Ljava/util/Collection;)Lsoftware/amazon/awssdk/services/proton/model/ResourceSyncAttempt$Builder;
      19: pop
      20: aload_0
      21: aload_1
      22: invokestatic  #13                 // Method software/amazon/awssdk/services/proton/model/ResourceSyncAttempt.access$900:(Lsoftware/amazon/awssdk/services/proton/model/ResourceSyncAttempt;)Lsoftware/amazon/awssdk/services/proton/model/Revision;
      25: invokevirtual #14                 // Method initialRevision:(Lsoftware/amazon/awssdk/services/proton/model/Revision;)Lsoftware/amazon/awssdk/services/proton/model/ResourceSyncAttempt$Builder;
      28: pop
      29: aload_0
      30: aload_1
      31: invokestatic  #15                 // Method software/amazon/awssdk/services/proton/model/ResourceSyncAttempt.access$1000:(Lsoftware/amazon/awssdk/services/proton/model/ResourceSyncAttempt;)Ljava/time/Instant;
      34: invokevirtual #16                 // Method startedAt:(Ljava/time/Instant;)Lsoftware/amazon/awssdk/services/proton/model/ResourceSyncAttempt$Builder;
      37: pop
      38: aload_0
      39: aload_1
      40: invokestatic  #17                 // Method software/amazon/awssdk/services/proton/model/ResourceSyncAttempt.access$1100:(Lsoftware/amazon/awssdk/services/proton/model/ResourceSyncAttempt;)Ljava/lang/String;
      43: invokevirtual #18                 // Method status:(Ljava/lang/String;)Lsoftware/amazon/awssdk/services/proton/model/ResourceSyncAttempt$Builder;
      46: pop
      47: aload_0
      48: aload_1
      49: invokestatic  #19                 // Method software/amazon/awssdk/services/proton/model/ResourceSyncAttempt.access$1200:(Lsoftware/amazon/awssdk/services/proton/model/ResourceSyncAttempt;)Ljava/lang/String;
      52: invokevirtual #20                 // Method target:(Ljava/lang/String;)Lsoftware/amazon/awssdk/services/proton/model/ResourceSyncAttempt$Builder;
      55: pop
      56: aload_0
      57: aload_1
      58: invokestatic  #21                 // Method software/amazon/awssdk/services/proton/model/ResourceSyncAttempt.access$1300:(Lsoftware/amazon/awssdk/services/proton/model/ResourceSyncAttempt;)Lsoftware/amazon/awssdk/services/proton/model/Revision;
      61: invokevirtual #22                 // Method targetRevision:(Lsoftware/amazon/awssdk/services/proton/model/Revision;)Lsoftware/amazon/awssdk/services/proton/model/ResourceSyncAttempt$Builder;
      64: pop
      65: return

  public final java.util.List<software.amazon.awssdk.services.proton.model.ResourceSyncEvent$Builder> getEvents();
    Code:
       0: aload_0
       1: getfield      #8                  // Field events:Ljava/util/List;
       4: invokestatic  #23                 // Method software/amazon/awssdk/services/proton/model/ResourceSyncEventsCopier.copyToBuilder:(Ljava/util/Collection;)Ljava/util/List;
       7: astore_1
       8: aload_1
       9: instanceof    #24                 // class software/amazon/awssdk/core/util/SdkAutoConstructList
      12: ifeq          17
      15: aconst_null
      16: areturn
      17: aload_1
      18: areturn

  public final void setEvents(java.util.Collection<software.amazon.awssdk.services.proton.model.ResourceSyncEvent$BuilderImpl>);
    Code:
       0: aload_0
       1: aload_1
       2: invokestatic  #25                 // Method software/amazon/awssdk/services/proton/model/ResourceSyncEventsCopier.copyFromBuilder:(Ljava/util/Collection;)Ljava/util/List;
       5: putfield      #8                  // Field events:Ljava/util/List;
       8: return

  public final software.amazon.awssdk.services.proton.model.ResourceSyncAttempt$Builder events(java.util.Collection<software.amazon.awssdk.services.proton.model.ResourceSyncEvent>);
    Code:
       0: aload_0
       1: aload_1
       2: invokestatic  #26                 // Method software/amazon/awssdk/services/proton/model/ResourceSyncEventsCopier.copy:(Ljava/util/Collection;)Ljava/util/List;
       5: putfield      #8                  // Field events:Ljava/util/List;
       8: aload_0
       9: areturn

  public final software.amazon.awssdk.services.proton.model.ResourceSyncAttempt$Builder events(software.amazon.awssdk.services.proton.model.ResourceSyncEvent...);
    Code:
       0: aload_0
       1: aload_1
       2: invokestatic  #27                 // Method java/util/Arrays.asList:([Ljava/lang/Object;)Ljava/util/List;
       5: invokevirtual #12                 // Method events:(Ljava/util/Collection;)Lsoftware/amazon/awssdk/services/proton/model/ResourceSyncAttempt$Builder;
       8: pop
       9: aload_0
      10: areturn

  public final software.amazon.awssdk.services.proton.model.ResourceSyncAttempt$Builder events(java.util.function.Consumer<software.amazon.awssdk.services.proton.model.ResourceSyncEvent$Builder>...);
    Code:
       0: aload_0
       1: aload_1
       2: invokestatic  #28                 // InterfaceMethod java/util/stream/Stream.of:([Ljava/lang/Object;)Ljava/util/stream/Stream;
       5: invokedynamic #29,  0             // InvokeDynamic #0:apply:()Ljava/util/function/Function;
      10: invokeinterface #30,  2           // InterfaceMethod java/util/stream/Stream.map:(Ljava/util/function/Function;)Ljava/util/stream/Stream;
      15: invokestatic  #31                 // Method java/util/stream/Collectors.toList:()Ljava/util/stream/Collector;
      18: invokeinterface #32,  2           // InterfaceMethod java/util/stream/Stream.collect:(Ljava/util/stream/Collector;)Ljava/lang/Object;
      23: checkcast     #33                 // class java/util/Collection
      26: invokevirtual #12                 // Method events:(Ljava/util/Collection;)Lsoftware/amazon/awssdk/services/proton/model/ResourceSyncAttempt$Builder;
      29: pop
      30: aload_0
      31: areturn

  public final software.amazon.awssdk.services.proton.model.Revision$Builder getInitialRevision();
    Code:
       0: aload_0
       1: getfield      #7                  // Field initialRevision:Lsoftware/amazon/awssdk/services/proton/model/Revision;
       4: ifnull        17
       7: aload_0
       8: getfield      #7                  // Field initialRevision:Lsoftware/amazon/awssdk/services/proton/model/Revision;
      11: invokevirtual #34                 // Method software/amazon/awssdk/services/proton/model/Revision.toBuilder:()Lsoftware/amazon/awssdk/services/proton/model/Revision$Builder;
      14: goto          18
      17: aconst_null
      18: areturn

  public final void setInitialRevision(software.amazon.awssdk.services.proton.model.Revision$BuilderImpl);
    Code:
       0: aload_0
       1: aload_1
       2: ifnull        12
       5: aload_1
       6: invokevirtual #35                 // Method software/amazon/awssdk/services/proton/model/Revision$BuilderImpl.build:()Lsoftware/amazon/awssdk/services/proton/model/Revision;
       9: goto          13
      12: aconst_null
      13: putfield      #7                  // Field initialRevision:Lsoftware/amazon/awssdk/services/proton/model/Revision;
      16: return

  public final software.amazon.awssdk.services.proton.model.ResourceSyncAttempt$Builder initialRevision(software.amazon.awssdk.services.proton.model.Revision);
    Code:
       0: aload_0
       1: aload_1
       2: putfield      #7                  // Field initialRevision:Lsoftware/amazon/awssdk/services/proton/model/Revision;
       5: aload_0
       6: areturn

  public final java.time.Instant getStartedAt();
    Code:
       0: aload_0
       1: getfield      #6                  // Field startedAt:Ljava/time/Instant;
       4: areturn

  public final void setStartedAt(java.time.Instant);
    Code:
       0: aload_0
       1: aload_1
       2: putfield      #6                  // Field startedAt:Ljava/time/Instant;
       5: return

  public final software.amazon.awssdk.services.proton.model.ResourceSyncAttempt$Builder startedAt(java.time.Instant);
    Code:
       0: aload_0
       1: aload_1
       2: putfield      #6                  // Field startedAt:Ljava/time/Instant;
       5: aload_0
       6: areturn

  public final java.lang.String getStatus();
    Code:
       0: aload_0
       1: getfield      #5                  // Field status:Ljava/lang/String;
       4: areturn

  public final void setStatus(java.lang.String);
    Code:
       0: aload_0
       1: aload_1
       2: putfield      #5                  // Field status:Ljava/lang/String;
       5: return

  public final software.amazon.awssdk.services.proton.model.ResourceSyncAttempt$Builder status(java.lang.String);
    Code:
       0: aload_0
       1: aload_1
       2: putfield      #5                  // Field status:Ljava/lang/String;
       5: aload_0
       6: areturn

  public final software.amazon.awssdk.services.proton.model.ResourceSyncAttempt$Builder status(software.amazon.awssdk.services.proton.model.ResourceSyncStatus);
    Code:
       0: aload_0
       1: aload_1
       2: ifnonnull     9
       5: aconst_null
       6: goto          13
       9: aload_1
      10: invokevirtual #36                 // Method software/amazon/awssdk/services/proton/model/ResourceSyncStatus.toString:()Ljava/lang/String;
      13: invokevirtual #18                 // Method status:(Ljava/lang/String;)Lsoftware/amazon/awssdk/services/proton/model/ResourceSyncAttempt$Builder;
      16: pop
      17: aload_0
      18: areturn

  public final java.lang.String getTarget();
    Code:
       0: aload_0
       1: getfield      #4                  // Field target:Ljava/lang/String;
       4: areturn

  public final void setTarget(java.lang.String);
    Code:
       0: aload_0
       1: aload_1
       2: putfield      #4                  // Field target:Ljava/lang/String;
       5: return

  public final software.amazon.awssdk.services.proton.model.ResourceSyncAttempt$Builder target(java.lang.String);
    Code:
       0: aload_0
       1: aload_1
       2: putfield      #4                  // Field target:Ljava/lang/String;
       5: aload_0
       6: areturn

  public final software.amazon.awssdk.services.proton.model.Revision$Builder getTargetRevision();
    Code:
       0: aload_0
       1: getfield      #3                  // Field targetRevision:Lsoftware/amazon/awssdk/services/proton/model/Revision;
       4: ifnull        17
       7: aload_0
       8: getfield      #3                  // Field targetRevision:Lsoftware/amazon/awssdk/services/proton/model/Revision;
      11: invokevirtual #34                 // Method software/amazon/awssdk/services/proton/model/Revision.toBuilder:()Lsoftware/amazon/awssdk/services/proton/model/Revision$Builder;
      14: goto          18
      17: aconst_null
      18: areturn

  public final void setTargetRevision(software.amazon.awssdk.services.proton.model.Revision$BuilderImpl);
    Code:
       0: aload_0
       1: aload_1
       2: ifnull        12
       5: aload_1
       6: invokevirtual #35                 // Method software/amazon/awssdk/services/proton/model/Revision$BuilderImpl.build:()Lsoftware/amazon/awssdk/services/proton/model/Revision;
       9: goto          13
      12: aconst_null
      13: putfield      #3                  // Field targetRevision:Lsoftware/amazon/awssdk/services/proton/model/Revision;
      16: return

  public final software.amazon.awssdk.services.proton.model.ResourceSyncAttempt$Builder targetRevision(software.amazon.awssdk.services.proton.model.Revision);
    Code:
       0: aload_0
       1: aload_1
       2: putfield      #3                  // Field targetRevision:Lsoftware/amazon/awssdk/services/proton/model/Revision;
       5: aload_0
       6: areturn

  public software.amazon.awssdk.services.proton.model.ResourceSyncAttempt build();
    Code:
       0: new           #37                 // class software/amazon/awssdk/services/proton/model/ResourceSyncAttempt
       3: dup
       4: aload_0
       5: aconst_null
       6: invokespecial #38                 // Method software/amazon/awssdk/services/proton/model/ResourceSyncAttempt."<init>":(Lsoftware/amazon/awssdk/services/proton/model/ResourceSyncAttempt$BuilderImpl;Lsoftware/amazon/awssdk/services/proton/model/ResourceSyncAttempt$1;)V
       9: areturn

  public java.util.List<software.amazon.awssdk.core.SdkField<?>> sdkFields();
    Code:
       0: invokestatic  #39                 // Method software/amazon/awssdk/services/proton/model/ResourceSyncAttempt.access$1500:()Ljava/util/List;
       3: areturn

  public java.lang.Object build();
    Code:
       0: aload_0
       1: invokevirtual #40                 // Method build:()Lsoftware/amazon/awssdk/services/proton/model/ResourceSyncAttempt;
       4: areturn

  private static software.amazon.awssdk.services.proton.model.ResourceSyncEvent lambda$events$0(java.util.function.Consumer);
    Code:
       0: invokestatic  #41                 // Method software/amazon/awssdk/services/proton/model/ResourceSyncEvent.builder:()Lsoftware/amazon/awssdk/services/proton/model/ResourceSyncEvent$Builder;
       3: aload_0
       4: invokeinterface #42,  2           // InterfaceMethod software/amazon/awssdk/services/proton/model/ResourceSyncEvent$Builder.applyMutation:(Ljava/util/function/Consumer;)Lsoftware/amazon/awssdk/utils/builder/SdkBuilder;
       9: checkcast     #43                 // class software/amazon/awssdk/services/proton/model/ResourceSyncEvent$Builder
      12: invokeinterface #44,  1           // InterfaceMethod software/amazon/awssdk/services/proton/model/ResourceSyncEvent$Builder.build:()Ljava/lang/Object;
      17: checkcast     #45                 // class software/amazon/awssdk/services/proton/model/ResourceSyncEvent
      20: areturn

  static java.util.List access$000(software.amazon.awssdk.services.proton.model.ResourceSyncAttempt$BuilderImpl);
    Code:
       0: aload_0
       1: getfield      #8                  // Field events:Ljava/util/List;
       4: areturn

  static software.amazon.awssdk.services.proton.model.Revision access$100(software.amazon.awssdk.services.proton.model.ResourceSyncAttempt$BuilderImpl);
    Code:
       0: aload_0
       1: getfield      #7                  // Field initialRevision:Lsoftware/amazon/awssdk/services/proton/model/Revision;
       4: areturn

  static java.time.Instant access$200(software.amazon.awssdk.services.proton.model.ResourceSyncAttempt$BuilderImpl);
    Code:
       0: aload_0
       1: getfield      #6                  // Field startedAt:Ljava/time/Instant;
       4: areturn

  static java.lang.String access$300(software.amazon.awssdk.services.proton.model.ResourceSyncAttempt$BuilderImpl);
    Code:
       0: aload_0
       1: getfield      #5                  // Field status:Ljava/lang/String;
       4: areturn

  static java.lang.String access$400(software.amazon.awssdk.services.proton.model.ResourceSyncAttempt$BuilderImpl);
    Code:
       0: aload_0
       1: getfield      #4                  // Field target:Ljava/lang/String;
       4: areturn

  static software.amazon.awssdk.services.proton.model.Revision access$500(software.amazon.awssdk.services.proton.model.ResourceSyncAttempt$BuilderImpl);
    Code:
       0: aload_0
       1: getfield      #3                  // Field targetRevision:Lsoftware/amazon/awssdk/services/proton/model/Revision;
       4: areturn

  software.amazon.awssdk.services.proton.model.ResourceSyncAttempt$BuilderImpl(software.amazon.awssdk.services.proton.model.ResourceSyncAttempt, software.amazon.awssdk.services.proton.model.ResourceSyncAttempt$1);
    Code:
       0: aload_0
       1: aload_1
       2: invokespecial #2                  // Method "<init>":(Lsoftware/amazon/awssdk/services/proton/model/ResourceSyncAttempt;)V
       5: return

  software.amazon.awssdk.services.proton.model.ResourceSyncAttempt$BuilderImpl(software.amazon.awssdk.services.proton.model.ResourceSyncAttempt$1);
    Code:
       0: aload_0
       1: invokespecial #1                  // Method "<init>":()V
       4: return
}
