Compiled from "UpdateEnvironmentRequest.java"
public interface software.amazon.awssdk.services.proton.model.UpdateEnvironmentRequest$Builder extends software.amazon.awssdk.services.proton.model.ProtonRequest$Builder, software.amazon.awssdk.core.SdkPojo, software.amazon.awssdk.utils.builder.CopyableBuilder<software.amazon.awssdk.services.proton.model.UpdateEnvironmentRequest$Builder, software.amazon.awssdk.services.proton.model.UpdateEnvironmentRequest> {
  public abstract software.amazon.awssdk.services.proton.model.UpdateEnvironmentRequest$Builder codebuildRoleArn(java.lang.String);

  public abstract software.amazon.awssdk.services.proton.model.UpdateEnvironmentRequest$Builder componentRoleArn(java.lang.String);

  public abstract software.amazon.awssdk.services.proton.model.UpdateEnvironmentRequest$Builder deploymentType(java.lang.String);

  public abstract software.amazon.awssdk.services.proton.model.UpdateEnvironmentRequest$Builder deploymentType(software.amazon.awssdk.services.proton.model.DeploymentUpdateType);

  public abstract software.amazon.awssdk.services.proton.model.UpdateEnvironmentRequest$Builder description(java.lang.String);

  public abstract software.amazon.awssdk.services.proton.model.UpdateEnvironmentRequest$Builder environmentAccountConnectionId(java.lang.String);

  public abstract software.amazon.awssdk.services.proton.model.UpdateEnvironmentRequest$Builder name(java.lang.String);

  public abstract software.amazon.awssdk.services.proton.model.UpdateEnvironmentRequest$Builder protonServiceRoleArn(java.lang.String);

  public abstract software.amazon.awssdk.services.proton.model.UpdateEnvironmentRequest$Builder provisioningRepository(software.amazon.awssdk.services.proton.model.RepositoryBranchInput);

  public default software.amazon.awssdk.services.proton.model.UpdateEnvironmentRequest$Builder provisioningRepository(java.util.function.Consumer<software.amazon.awssdk.services.proton.model.RepositoryBranchInput$Builder>);
    Code:
       0: aload_0
       1: invokestatic  #1                  // Method software/amazon/awssdk/services/proton/model/RepositoryBranchInput.builder:()Lsoftware/amazon/awssdk/services/proton/model/RepositoryBranchInput$Builder;
       4: aload_1
       5: invokeinterface #2,  2            // InterfaceMethod software/amazon/awssdk/services/proton/model/RepositoryBranchInput$Builder.applyMutation:(Ljava/util/function/Consumer;)Lsoftware/amazon/awssdk/utils/builder/SdkBuilder;
      10: checkcast     #3                  // class software/amazon/awssdk/services/proton/model/RepositoryBranchInput$Builder
      13: invokeinterface #4,  1            // InterfaceMethod software/amazon/awssdk/services/proton/model/RepositoryBranchInput$Builder.build:()Ljava/lang/Object;
      18: checkcast     #5                  // class software/amazon/awssdk/services/proton/model/RepositoryBranchInput
      21: invokeinterface #6,  2            // InterfaceMethod provisioningRepository:(Lsoftware/amazon/awssdk/services/proton/model/RepositoryBranchInput;)Lsoftware/amazon/awssdk/services/proton/model/UpdateEnvironmentRequest$Builder;
      26: areturn

  public abstract software.amazon.awssdk.services.proton.model.UpdateEnvironmentRequest$Builder spec(java.lang.String);

  public abstract software.amazon.awssdk.services.proton.model.UpdateEnvironmentRequest$Builder templateMajorVersion(java.lang.String);

  public abstract software.amazon.awssdk.services.proton.model.UpdateEnvironmentRequest$Builder templateMinorVersion(java.lang.String);

  public abstract software.amazon.awssdk.services.proton.model.UpdateEnvironmentRequest$Builder overrideConfiguration(software.amazon.awssdk.awscore.AwsRequestOverrideConfiguration);

  public abstract software.amazon.awssdk.services.proton.model.UpdateEnvironmentRequest$Builder overrideConfiguration(java.util.function.Consumer<software.amazon.awssdk.awscore.AwsRequestOverrideConfiguration$Builder>);

  public default software.amazon.awssdk.awscore.AwsRequest$Builder overrideConfiguration(java.util.function.Consumer);
    Code:
       0: aload_0
       1: aload_1
       2: invokeinterface #7,  2            // InterfaceMethod overrideConfiguration:(Ljava/util/function/Consumer;)Lsoftware/amazon/awssdk/services/proton/model/UpdateEnvironmentRequest$Builder;
       7: areturn

  public default software.amazon.awssdk.awscore.AwsRequest$Builder overrideConfiguration(software.amazon.awssdk.awscore.AwsRequestOverrideConfiguration);
    Code:
       0: aload_0
       1: aload_1
       2: invokeinterface #8,  2            // InterfaceMethod overrideConfiguration:(Lsoftware/amazon/awssdk/awscore/AwsRequestOverrideConfiguration;)Lsoftware/amazon/awssdk/services/proton/model/UpdateEnvironmentRequest$Builder;
       7: areturn
}
