Compiled from "DefaultJarDeploymentFactory.java"
public class org.wildfly.swarm.container.internal.DefaultJarDeploymentFactory extends org.wildfly.swarm.spi.api.DefaultDeploymentFactory {
  public org.wildfly.swarm.container.internal.DefaultJarDeploymentFactory();
    Code:
       0: aload_0
       1: invokespecial #2                  // Method org/wildfly/swarm/spi/api/DefaultDeploymentFactory."<init>":()V
       4: return

  public int getPriority();
    Code:
       0: iconst_0
       1: ireturn

  public java.lang.String getType();
    Code:
       0: ldc           #3                  // String jar
       2: areturn

  public org.jboss.shrinkwrap.api.Archive create() throws java.lang.Exception;
    Code:
       0: ldc           #4                  // class org/wildfly/swarm/spi/api/JARArchive
       2: aload_0
       3: invokevirtual #5                  // Method determineName:()Ljava/lang/String;
       6: invokestatic  #6                  // Method org/jboss/shrinkwrap/api/ShrinkWrap.create:(Ljava/lang/Class;Ljava/lang/String;)Lorg/jboss/shrinkwrap/api/Assignable;
       9: checkcast     #4                  // class org/wildfly/swarm/spi/api/JARArchive
      12: astore_1
      13: aload_0
      14: aload_1
      15: invokevirtual #7                  // Method setup:(Lorg/jboss/shrinkwrap/api/Archive;)Z
      18: pop
      19: aload_1
      20: areturn

  public boolean setupUsingMaven(org.jboss.shrinkwrap.api.Archive<?>) throws java.lang.Exception;
    Code:
       0: ldc           #8                  // String user.dir
       2: invokestatic  #9                  // Method java/lang/System.getProperty:(Ljava/lang/String;)Ljava/lang/String;
       5: iconst_0
       6: anewarray     #10                 // class java/lang/String
       9: invokestatic  #11                 // Method java/nio/file/Paths.get:(Ljava/lang/String;[Ljava/lang/String;)Ljava/nio/file/Path;
      12: astore_2
      13: aload_2
      14: ldc           #12                 // String target
      16: invokeinterface #13,  2           // InterfaceMethod java/nio/file/Path.resolve:(Ljava/lang/String;)Ljava/nio/file/Path;
      21: ldc           #14                 // String classes
      23: invokeinterface #13,  2           // InterfaceMethod java/nio/file/Path.resolve:(Ljava/lang/String;)Ljava/nio/file/Path;
      28: astore_3
      29: iconst_0
      30: istore        4
      32: aload_3
      33: iconst_0
      34: anewarray     #15                 // class java/nio/file/LinkOption
      37: invokestatic  #16                 // Method java/nio/file/Files.exists:(Ljava/nio/file/Path;[Ljava/nio/file/LinkOption;)Z
      40: ifeq          61
      43: iconst_1
      44: istore        4
      46: aload_3
      47: new           #17                 // class org/wildfly/swarm/container/internal/DefaultJarDeploymentFactory$1
      50: dup
      51: aload_0
      52: aload_3
      53: aload_1
      54: invokespecial #18                 // Method org/wildfly/swarm/container/internal/DefaultJarDeploymentFactory$1."<init>":(Lorg/wildfly/swarm/container/internal/DefaultJarDeploymentFactory;Ljava/nio/file/Path;Lorg/jboss/shrinkwrap/api/Archive;)V
      57: invokestatic  #19                 // Method java/nio/file/Files.walkFileTree:(Ljava/nio/file/Path;Ljava/nio/file/FileVisitor;)Ljava/nio/file/Path;
      60: pop
      61: iload         4
      63: ireturn

  protected java.lang.String determineName();
    Code:
       0: ldc           #20                 // String .jar
       2: invokestatic  #21                 // Method org/wildfly/swarm/spi/api/DefaultDeploymentFactory.determineName:(Ljava/lang/String;)Ljava/lang/String;
       5: areturn

  static java.lang.String access$000(org.wildfly.swarm.container.internal.DefaultJarDeploymentFactory, java.nio.file.Path);
    Code:
       0: aload_0
       1: aload_1
       2: invokevirtual #1                  // Method convertSeparators:(Ljava/nio/file/Path;)Ljava/lang/String;
       5: areturn
}
