Compiled from "Empty.java"
public final class io.micrometer.shaded.org.pcollections.Empty {
  private io.micrometer.shaded.org.pcollections.Empty();
    Code:
       0: aload_0
       1: invokespecial #9                  // Method java/lang/Object."<init>":()V
       4: return

  public static <E> io.micrometer.shaded.org.pcollections.PStack<E> stack();
    Code:
       0: invokestatic  #20                 // Method io/micrometer/shaded/org/pcollections/ConsPStack.empty:()Lio/micrometer/shaded/org/pcollections/ConsPStack;
       3: areturn

  public static <E> io.micrometer.shaded.org.pcollections.PQueue<E> queue();
    Code:
       0: invokestatic  #28                 // Method io/micrometer/shaded/org/pcollections/AmortizedPQueue.empty:()Lio/micrometer/shaded/org/pcollections/AmortizedPQueue;
       3: areturn

  public static <E> io.micrometer.shaded.org.pcollections.PVector<E> vector();
    Code:
       0: invokestatic  #36                 // Method io/micrometer/shaded/org/pcollections/TreePVector.empty:()Lio/micrometer/shaded/org/pcollections/TreePVector;
       3: areturn

  public static <E> io.micrometer.shaded.org.pcollections.PSet<E> set();
    Code:
       0: invokestatic  #44                 // Method io/micrometer/shaded/org/pcollections/HashTreePSet.empty:()Lio/micrometer/shaded/org/pcollections/MapPSet;
       3: areturn

  public static <E> io.micrometer.shaded.org.pcollections.POrderedSet<E> orderedSet();
    Code:
       0: invokestatic  #52                 // Method io/micrometer/shaded/org/pcollections/OrderedPSet.empty:()Lio/micrometer/shaded/org/pcollections/OrderedPSet;
       3: areturn

  public static <E> io.micrometer.shaded.org.pcollections.PBag<E> bag();
    Code:
       0: invokestatic  #60                 // Method io/micrometer/shaded/org/pcollections/HashTreePBag.empty:()Lio/micrometer/shaded/org/pcollections/MapPBag;
       3: areturn

  public static <K, V> io.micrometer.shaded.org.pcollections.PMap<K, V> map();
    Code:
       0: invokestatic  #68                 // Method io/micrometer/shaded/org/pcollections/HashTreePMap.empty:()Lio/micrometer/shaded/org/pcollections/HashPMap;
       3: areturn
}
