Compiled from "MultivariateFunctionMappingAdapter.java"
class org.apache.commons.math3.optimization.direct.MultivariateFunctionMappingAdapter$LowerBoundMapper implements org.apache.commons.math3.optimization.direct.MultivariateFunctionMappingAdapter$Mapper {
  private final double lower;

  org.apache.commons.math3.optimization.direct.MultivariateFunctionMappingAdapter$LowerBoundMapper(double);
    Code:
       0: aload_0
       1: invokespecial #1                  // Method java/lang/Object."<init>":()V
       4: aload_0
       5: dload_1
       6: putfield      #2                  // Field lower:D
       9: return

  public double unboundedToBounded(double);
    Code:
       0: aload_0
       1: getfield      #2                  // Field lower:D
       4: dload_1
       5: invokestatic  #3                  // Method org/apache/commons/math3/util/FastMath.exp:(D)D
       8: dadd
       9: dreturn

  public double boundedToUnbounded(double);
    Code:
       0: dload_1
       1: aload_0
       2: getfield      #2                  // Field lower:D
       5: dsub
       6: invokestatic  #4                  // Method org/apache/commons/math3/util/FastMath.log:(D)D
       9: dreturn
}
