Compiled from "PublicSuffixList.java"
public final class org.apache.hc.client5.http.psl.PublicSuffixList {
  private final org.apache.hc.client5.http.psl.DomainType type;

  private final java.util.List<java.lang.String> rules;

  private final java.util.List<java.lang.String> exceptions;

  public org.apache.hc.client5.http.psl.PublicSuffixList(org.apache.hc.client5.http.psl.DomainType, java.util.List<java.lang.String>, java.util.List<java.lang.String>);
    Code:
       0: aload_0
       1: invokespecial #1                  // Method java/lang/Object."<init>":()V
       4: aload_0
       5: aload_1
       6: ldc           #2                  // String Domain type
       8: invokestatic  #3                  // Method org/apache/hc/core5/util/Args.notNull:(Ljava/lang/Object;Ljava/lang/String;)Ljava/lang/Object;
      11: checkcast     #4                  // class org/apache/hc/client5/http/psl/DomainType
      14: putfield      #5                  // Field type:Lorg/apache/hc/client5/http/psl/DomainType;
      17: aload_0
      18: aload_2
      19: ldc           #6                  // String Domain suffix rules
      21: invokestatic  #3                  // Method org/apache/hc/core5/util/Args.notNull:(Ljava/lang/Object;Ljava/lang/String;)Ljava/lang/Object;
      24: checkcast     #7                  // class java/util/List
      27: invokestatic  #8                  // Method java/util/Collections.unmodifiableList:(Ljava/util/List;)Ljava/util/List;
      30: putfield      #9                  // Field rules:Ljava/util/List;
      33: aload_0
      34: aload_3
      35: ifnull        42
      38: aload_3
      39: goto          45
      42: invokestatic  #10                 // Method java/util/Collections.emptyList:()Ljava/util/List;
      45: invokestatic  #8                  // Method java/util/Collections.unmodifiableList:(Ljava/util/List;)Ljava/util/List;
      48: putfield      #11                 // Field exceptions:Ljava/util/List;
      51: return

  public org.apache.hc.client5.http.psl.PublicSuffixList(java.util.List<java.lang.String>, java.util.List<java.lang.String>);
    Code:
       0: aload_0
       1: getstatic     #12                 // Field org/apache/hc/client5/http/psl/DomainType.UNKNOWN:Lorg/apache/hc/client5/http/psl/DomainType;
       4: aload_1
       5: aload_2
       6: invokespecial #13                 // Method "<init>":(Lorg/apache/hc/client5/http/psl/DomainType;Ljava/util/List;Ljava/util/List;)V
       9: return

  public org.apache.hc.client5.http.psl.DomainType getType();
    Code:
       0: aload_0
       1: getfield      #5                  // Field type:Lorg/apache/hc/client5/http/psl/DomainType;
       4: areturn

  public java.util.List<java.lang.String> getRules();
    Code:
       0: aload_0
       1: getfield      #9                  // Field rules:Ljava/util/List;
       4: areturn

  public java.util.List<java.lang.String> getExceptions();
    Code:
       0: aload_0
       1: getfield      #11                 // Field exceptions:Ljava/util/List;
       4: areturn
}
