Compiled from "MetaDataField.java"
public final class net.openhft.chronicle.queue.impl.single.MetaDataField extends java.lang.Enum<net.openhft.chronicle.queue.impl.single.MetaDataField> implements net.openhft.chronicle.wire.WireKey {
  public static final net.openhft.chronicle.queue.impl.single.MetaDataField wireType;

  public static final net.openhft.chronicle.queue.impl.single.MetaDataField writePosition;

  public static final net.openhft.chronicle.queue.impl.single.MetaDataField roll;

  public static final net.openhft.chronicle.queue.impl.single.MetaDataField indexing;

  public static final net.openhft.chronicle.queue.impl.single.MetaDataField lastAcknowledgedIndexReplicated;

  public static final net.openhft.chronicle.queue.impl.single.MetaDataField recovery;

  public static final net.openhft.chronicle.queue.impl.single.MetaDataField deltaCheckpointInterval;

  public static final net.openhft.chronicle.queue.impl.single.MetaDataField encodedSequence;

  public static final net.openhft.chronicle.queue.impl.single.MetaDataField lastIndexReplicated;

  public static final net.openhft.chronicle.queue.impl.single.MetaDataField sourceId;

  public static final net.openhft.chronicle.queue.impl.single.MetaDataField dataFormat;

  public static final net.openhft.chronicle.queue.impl.single.MetaDataField metadata;

  private static final net.openhft.chronicle.queue.impl.single.MetaDataField[] $VALUES;

  public static net.openhft.chronicle.queue.impl.single.MetaDataField[] values();
    Code:
       0: getstatic     #1                  // Field $VALUES:[Lnet/openhft/chronicle/queue/impl/single/MetaDataField;
       3: invokevirtual #2                  // Method "[Lnet/openhft/chronicle/queue/impl/single/MetaDataField;".clone:()Ljava/lang/Object;
       6: checkcast     #3                  // class "[Lnet/openhft/chronicle/queue/impl/single/MetaDataField;"
       9: areturn

  public static net.openhft.chronicle.queue.impl.single.MetaDataField valueOf(java.lang.String);
    Code:
       0: ldc           #4                  // class net/openhft/chronicle/queue/impl/single/MetaDataField
       2: aload_0
       3: invokestatic  #5                  // Method java/lang/Enum.valueOf:(Ljava/lang/Class;Ljava/lang/String;)Ljava/lang/Enum;
       6: checkcast     #4                  // class net/openhft/chronicle/queue/impl/single/MetaDataField
       9: areturn

  private net.openhft.chronicle.queue.impl.single.MetaDataField();
    Code:
       0: aload_0
       1: aload_1
       2: iload_2
       3: invokespecial #6                  // Method java/lang/Enum."<init>":(Ljava/lang/String;I)V
       6: return

  public java.lang.Object defaultValue();
    Code:
       0: new           #7                  // class net/openhft/chronicle/core/io/IORuntimeException
       3: dup
       4: new           #8                  // class java/lang/StringBuilder
       7: dup
       8: invokespecial #9                  // Method java/lang/StringBuilder."<init>":()V
      11: ldc           #10                 // String field
      13: invokevirtual #11                 // Method java/lang/StringBuilder.append:(Ljava/lang/String;)Ljava/lang/StringBuilder;
      16: aload_0
      17: invokevirtual #12                 // Method name:()Ljava/lang/String;
      20: invokevirtual #11                 // Method java/lang/StringBuilder.append:(Ljava/lang/String;)Ljava/lang/StringBuilder;
      23: ldc           #13                 // String  required
      25: invokevirtual #11                 // Method java/lang/StringBuilder.append:(Ljava/lang/String;)Ljava/lang/StringBuilder;
      28: invokevirtual #14                 // Method java/lang/StringBuilder.toString:()Ljava/lang/String;
      31: invokespecial #15                 // Method net/openhft/chronicle/core/io/IORuntimeException."<init>":(Ljava/lang/String;)V
      34: athrow

  public java.lang.CharSequence name();
    Code:
       0: aload_0
       1: invokespecial #16                 // Method java/lang/Enum.name:()Ljava/lang/String;
       4: areturn

  static {};
    Code:
       0: new           #4                  // class net/openhft/chronicle/queue/impl/single/MetaDataField
       3: dup
       4: ldc           #17                 // String wireType
       6: iconst_0
       7: invokespecial #18                 // Method "<init>":(Ljava/lang/String;I)V
      10: putstatic     #19                 // Field wireType:Lnet/openhft/chronicle/queue/impl/single/MetaDataField;
      13: new           #4                  // class net/openhft/chronicle/queue/impl/single/MetaDataField
      16: dup
      17: ldc           #20                 // String writePosition
      19: iconst_1
      20: invokespecial #18                 // Method "<init>":(Ljava/lang/String;I)V
      23: putstatic     #21                 // Field writePosition:Lnet/openhft/chronicle/queue/impl/single/MetaDataField;
      26: new           #4                  // class net/openhft/chronicle/queue/impl/single/MetaDataField
      29: dup
      30: ldc           #22                 // String roll
      32: iconst_2
      33: invokespecial #18                 // Method "<init>":(Ljava/lang/String;I)V
      36: putstatic     #23                 // Field roll:Lnet/openhft/chronicle/queue/impl/single/MetaDataField;
      39: new           #4                  // class net/openhft/chronicle/queue/impl/single/MetaDataField
      42: dup
      43: ldc           #24                 // String indexing
      45: iconst_3
      46: invokespecial #18                 // Method "<init>":(Ljava/lang/String;I)V
      49: putstatic     #25                 // Field indexing:Lnet/openhft/chronicle/queue/impl/single/MetaDataField;
      52: new           #4                  // class net/openhft/chronicle/queue/impl/single/MetaDataField
      55: dup
      56: ldc           #26                 // String lastAcknowledgedIndexReplicated
      58: iconst_4
      59: invokespecial #18                 // Method "<init>":(Ljava/lang/String;I)V
      62: putstatic     #27                 // Field lastAcknowledgedIndexReplicated:Lnet/openhft/chronicle/queue/impl/single/MetaDataField;
      65: new           #4                  // class net/openhft/chronicle/queue/impl/single/MetaDataField
      68: dup
      69: ldc           #28                 // String recovery
      71: iconst_5
      72: invokespecial #18                 // Method "<init>":(Ljava/lang/String;I)V
      75: putstatic     #29                 // Field recovery:Lnet/openhft/chronicle/queue/impl/single/MetaDataField;
      78: new           #4                  // class net/openhft/chronicle/queue/impl/single/MetaDataField
      81: dup
      82: ldc           #30                 // String deltaCheckpointInterval
      84: bipush        6
      86: invokespecial #18                 // Method "<init>":(Ljava/lang/String;I)V
      89: putstatic     #31                 // Field deltaCheckpointInterval:Lnet/openhft/chronicle/queue/impl/single/MetaDataField;
      92: new           #4                  // class net/openhft/chronicle/queue/impl/single/MetaDataField
      95: dup
      96: ldc           #32                 // String encodedSequence
      98: bipush        7
     100: invokespecial #18                 // Method "<init>":(Ljava/lang/String;I)V
     103: putstatic     #33                 // Field encodedSequence:Lnet/openhft/chronicle/queue/impl/single/MetaDataField;
     106: new           #4                  // class net/openhft/chronicle/queue/impl/single/MetaDataField
     109: dup
     110: ldc           #34                 // String lastIndexReplicated
     112: bipush        8
     114: invokespecial #18                 // Method "<init>":(Ljava/lang/String;I)V
     117: putstatic     #35                 // Field lastIndexReplicated:Lnet/openhft/chronicle/queue/impl/single/MetaDataField;
     120: new           #4                  // class net/openhft/chronicle/queue/impl/single/MetaDataField
     123: dup
     124: ldc           #36                 // String sourceId
     126: bipush        9
     128: invokespecial #18                 // Method "<init>":(Ljava/lang/String;I)V
     131: putstatic     #37                 // Field sourceId:Lnet/openhft/chronicle/queue/impl/single/MetaDataField;
     134: new           #4                  // class net/openhft/chronicle/queue/impl/single/MetaDataField
     137: dup
     138: ldc           #38                 // String dataFormat
     140: bipush        10
     142: invokespecial #18                 // Method "<init>":(Ljava/lang/String;I)V
     145: putstatic     #39                 // Field dataFormat:Lnet/openhft/chronicle/queue/impl/single/MetaDataField;
     148: new           #4                  // class net/openhft/chronicle/queue/impl/single/MetaDataField
     151: dup
     152: ldc           #40                 // String metadata
     154: bipush        11
     156: invokespecial #18                 // Method "<init>":(Ljava/lang/String;I)V
     159: putstatic     #41                 // Field metadata:Lnet/openhft/chronicle/queue/impl/single/MetaDataField;
     162: bipush        12
     164: anewarray     #4                  // class net/openhft/chronicle/queue/impl/single/MetaDataField
     167: dup
     168: iconst_0
     169: getstatic     #19                 // Field wireType:Lnet/openhft/chronicle/queue/impl/single/MetaDataField;
     172: aastore
     173: dup
     174: iconst_1
     175: getstatic     #21                 // Field writePosition:Lnet/openhft/chronicle/queue/impl/single/MetaDataField;
     178: aastore
     179: dup
     180: iconst_2
     181: getstatic     #23                 // Field roll:Lnet/openhft/chronicle/queue/impl/single/MetaDataField;
     184: aastore
     185: dup
     186: iconst_3
     187: getstatic     #25                 // Field indexing:Lnet/openhft/chronicle/queue/impl/single/MetaDataField;
     190: aastore
     191: dup
     192: iconst_4
     193: getstatic     #27                 // Field lastAcknowledgedIndexReplicated:Lnet/openhft/chronicle/queue/impl/single/MetaDataField;
     196: aastore
     197: dup
     198: iconst_5
     199: getstatic     #29                 // Field recovery:Lnet/openhft/chronicle/queue/impl/single/MetaDataField;
     202: aastore
     203: dup
     204: bipush        6
     206: getstatic     #31                 // Field deltaCheckpointInterval:Lnet/openhft/chronicle/queue/impl/single/MetaDataField;
     209: aastore
     210: dup
     211: bipush        7
     213: getstatic     #33                 // Field encodedSequence:Lnet/openhft/chronicle/queue/impl/single/MetaDataField;
     216: aastore
     217: dup
     218: bipush        8
     220: getstatic     #35                 // Field lastIndexReplicated:Lnet/openhft/chronicle/queue/impl/single/MetaDataField;
     223: aastore
     224: dup
     225: bipush        9
     227: getstatic     #37                 // Field sourceId:Lnet/openhft/chronicle/queue/impl/single/MetaDataField;
     230: aastore
     231: dup
     232: bipush        10
     234: getstatic     #39                 // Field dataFormat:Lnet/openhft/chronicle/queue/impl/single/MetaDataField;
     237: aastore
     238: dup
     239: bipush        11
     241: getstatic     #41                 // Field metadata:Lnet/openhft/chronicle/queue/impl/single/MetaDataField;
     244: aastore
     245: putstatic     #1                  // Field $VALUES:[Lnet/openhft/chronicle/queue/impl/single/MetaDataField;
     248: return
}
