Compiled from "ImmutableMultimap.java"
public class com.google.common.collect.ImmutableMultimap$Builder<K, V> {
  final java.util.Map<K, java.util.Collection<V>> builderMap;

  java.util.Comparator<? super K> keyComparator;

  java.util.Comparator<? super V> valueComparator;

  public com.google.common.collect.ImmutableMultimap$Builder();
    Code:
       0: aload_0
       1: invokespecial #1                  // Method java/lang/Object."<init>":()V
       4: aload_0
       5: invokestatic  #2                  // Method com/google/common/collect/Platform.preservesInsertionOrderOnPutsMap:()Ljava/util/Map;
       8: putfield      #3                  // Field builderMap:Ljava/util/Map;
      11: return

  java.util.Collection<V> newMutableValueCollection();
    Code:
       0: new           #4                  // class java/util/ArrayList
       3: dup
       4: invokespecial #5                  // Method java/util/ArrayList."<init>":()V
       7: areturn

  public com.google.common.collect.ImmutableMultimap$Builder<K, V> put(K, V);
    Code:
       0: aload_1
       1: aload_2
       2: invokestatic  #6                  // Method com/google/common/collect/CollectPreconditions.checkEntryNotNull:(Ljava/lang/Object;Ljava/lang/Object;)V
       5: aload_0
       6: getfield      #3                  // Field builderMap:Ljava/util/Map;
       9: aload_1
      10: invokeinterface #7,  2            // InterfaceMethod java/util/Map.get:(Ljava/lang/Object;)Ljava/lang/Object;
      15: checkcast     #8                  // class java/util/Collection
      18: astore_3
      19: aload_3
      20: ifnonnull     40
      23: aload_0
      24: getfield      #3                  // Field builderMap:Ljava/util/Map;
      27: aload_1
      28: aload_0
      29: invokevirtual #9                  // Method newMutableValueCollection:()Ljava/util/Collection;
      32: dup
      33: astore_3
      34: invokeinterface #10,  3           // InterfaceMethod java/util/Map.put:(Ljava/lang/Object;Ljava/lang/Object;)Ljava/lang/Object;
      39: pop
      40: aload_3
      41: aload_2
      42: invokeinterface #11,  2           // InterfaceMethod java/util/Collection.add:(Ljava/lang/Object;)Z
      47: pop
      48: aload_0
      49: areturn

  public com.google.common.collect.ImmutableMultimap$Builder<K, V> put(java.util.Map$Entry<? extends K, ? extends V>);
    Code:
       0: aload_0
       1: aload_1
       2: invokeinterface #12,  1           // InterfaceMethod java/util/Map$Entry.getKey:()Ljava/lang/Object;
       7: aload_1
       8: invokeinterface #13,  1           // InterfaceMethod java/util/Map$Entry.getValue:()Ljava/lang/Object;
      13: invokevirtual #14                 // Method put:(Ljava/lang/Object;Ljava/lang/Object;)Lcom/google/common/collect/ImmutableMultimap$Builder;
      16: areturn

  public com.google.common.collect.ImmutableMultimap$Builder<K, V> putAll(java.lang.Iterable<? extends java.util.Map$Entry<? extends K, ? extends V>>);
    Code:
       0: aload_1
       1: invokeinterface #15,  1           // InterfaceMethod java/lang/Iterable.iterator:()Ljava/util/Iterator;
       6: astore_2
       7: aload_2
       8: invokeinterface #16,  1           // InterfaceMethod java/util/Iterator.hasNext:()Z
      13: ifeq          35
      16: aload_2
      17: invokeinterface #17,  1           // InterfaceMethod java/util/Iterator.next:()Ljava/lang/Object;
      22: checkcast     #18                 // class java/util/Map$Entry
      25: astore_3
      26: aload_0
      27: aload_3
      28: invokevirtual #19                 // Method put:(Ljava/util/Map$Entry;)Lcom/google/common/collect/ImmutableMultimap$Builder;
      31: pop
      32: goto          7
      35: aload_0
      36: areturn

  public com.google.common.collect.ImmutableMultimap$Builder<K, V> putAll(K, java.lang.Iterable<? extends V>);
    Code:
       0: aload_1
       1: ifnonnull     43
       4: new           #20                 // class java/lang/NullPointerException
       7: dup
       8: ldc           #21                 // String null key in entry: null=
      10: aload_2
      11: invokestatic  #22                 // Method com/google/common/collect/Iterables.toString:(Ljava/lang/Iterable;)Ljava/lang/String;
      14: invokestatic  #23                 // Method java/lang/String.valueOf:(Ljava/lang/Object;)Ljava/lang/String;
      17: dup
      18: invokevirtual #24                 // Method java/lang/String.length:()I
      21: ifeq          30
      24: invokevirtual #25                 // Method java/lang/String.concat:(Ljava/lang/String;)Ljava/lang/String;
      27: goto          39
      30: pop
      31: new           #26                 // class java/lang/String
      34: dup_x1
      35: swap
      36: invokespecial #27                 // Method java/lang/String."<init>":(Ljava/lang/String;)V
      39: invokespecial #28                 // Method java/lang/NullPointerException."<init>":(Ljava/lang/String;)V
      42: athrow
      43: aload_0
      44: getfield      #3                  // Field builderMap:Ljava/util/Map;
      47: aload_1
      48: invokeinterface #7,  2            // InterfaceMethod java/util/Map.get:(Ljava/lang/Object;)Ljava/lang/Object;
      53: checkcast     #8                  // class java/util/Collection
      56: astore_3
      57: aload_3
      58: ifnull        108
      61: aload_2
      62: invokeinterface #15,  1           // InterfaceMethod java/lang/Iterable.iterator:()Ljava/util/Iterator;
      67: astore        4
      69: aload         4
      71: invokeinterface #16,  1           // InterfaceMethod java/util/Iterator.hasNext:()Z
      76: ifeq          106
      79: aload         4
      81: invokeinterface #17,  1           // InterfaceMethod java/util/Iterator.next:()Ljava/lang/Object;
      86: astore        5
      88: aload_1
      89: aload         5
      91: invokestatic  #6                  // Method com/google/common/collect/CollectPreconditions.checkEntryNotNull:(Ljava/lang/Object;Ljava/lang/Object;)V
      94: aload_3
      95: aload         5
      97: invokeinterface #11,  2           // InterfaceMethod java/util/Collection.add:(Ljava/lang/Object;)Z
     102: pop
     103: goto          69
     106: aload_0
     107: areturn
     108: aload_2
     109: invokeinterface #15,  1           // InterfaceMethod java/lang/Iterable.iterator:()Ljava/util/Iterator;
     114: astore        4
     116: aload         4
     118: invokeinterface #16,  1           // InterfaceMethod java/util/Iterator.hasNext:()Z
     123: ifne          128
     126: aload_0
     127: areturn
     128: aload_0
     129: invokevirtual #9                  // Method newMutableValueCollection:()Ljava/util/Collection;
     132: astore_3
     133: aload         4
     135: invokeinterface #16,  1           // InterfaceMethod java/util/Iterator.hasNext:()Z
     140: ifeq          170
     143: aload         4
     145: invokeinterface #17,  1           // InterfaceMethod java/util/Iterator.next:()Ljava/lang/Object;
     150: astore        5
     152: aload_1
     153: aload         5
     155: invokestatic  #6                  // Method com/google/common/collect/CollectPreconditions.checkEntryNotNull:(Ljava/lang/Object;Ljava/lang/Object;)V
     158: aload_3
     159: aload         5
     161: invokeinterface #11,  2           // InterfaceMethod java/util/Collection.add:(Ljava/lang/Object;)Z
     166: pop
     167: goto          133
     170: aload_0
     171: getfield      #3                  // Field builderMap:Ljava/util/Map;
     174: aload_1
     175: aload_3
     176: invokeinterface #10,  3           // InterfaceMethod java/util/Map.put:(Ljava/lang/Object;Ljava/lang/Object;)Ljava/lang/Object;
     181: pop
     182: aload_0
     183: areturn

  public com.google.common.collect.ImmutableMultimap$Builder<K, V> putAll(K, V...);
    Code:
       0: aload_0
       1: aload_1
       2: aload_2
       3: invokestatic  #29                 // Method java/util/Arrays.asList:([Ljava/lang/Object;)Ljava/util/List;
       6: invokevirtual #30                 // Method putAll:(Ljava/lang/Object;Ljava/lang/Iterable;)Lcom/google/common/collect/ImmutableMultimap$Builder;
       9: areturn

  public com.google.common.collect.ImmutableMultimap$Builder<K, V> putAll(com.google.common.collect.Multimap<? extends K, ? extends V>);
    Code:
       0: aload_1
       1: invokeinterface #31,  1           // InterfaceMethod com/google/common/collect/Multimap.asMap:()Ljava/util/Map;
       6: invokeinterface #32,  1           // InterfaceMethod java/util/Map.entrySet:()Ljava/util/Set;
      11: invokeinterface #33,  1           // InterfaceMethod java/util/Set.iterator:()Ljava/util/Iterator;
      16: astore_2
      17: aload_2
      18: invokeinterface #16,  1           // InterfaceMethod java/util/Iterator.hasNext:()Z
      23: ifeq          59
      26: aload_2
      27: invokeinterface #17,  1           // InterfaceMethod java/util/Iterator.next:()Ljava/lang/Object;
      32: checkcast     #18                 // class java/util/Map$Entry
      35: astore_3
      36: aload_0
      37: aload_3
      38: invokeinterface #12,  1           // InterfaceMethod java/util/Map$Entry.getKey:()Ljava/lang/Object;
      43: aload_3
      44: invokeinterface #13,  1           // InterfaceMethod java/util/Map$Entry.getValue:()Ljava/lang/Object;
      49: checkcast     #34                 // class java/lang/Iterable
      52: invokevirtual #30                 // Method putAll:(Ljava/lang/Object;Ljava/lang/Iterable;)Lcom/google/common/collect/ImmutableMultimap$Builder;
      55: pop
      56: goto          17
      59: aload_0
      60: areturn

  public com.google.common.collect.ImmutableMultimap$Builder<K, V> orderKeysBy(java.util.Comparator<? super K>);
    Code:
       0: aload_0
       1: aload_1
       2: invokestatic  #35                 // Method com/google/common/base/Preconditions.checkNotNull:(Ljava/lang/Object;)Ljava/lang/Object;
       5: checkcast     #36                 // class java/util/Comparator
       8: putfield      #37                 // Field keyComparator:Ljava/util/Comparator;
      11: aload_0
      12: areturn

  public com.google.common.collect.ImmutableMultimap$Builder<K, V> orderValuesBy(java.util.Comparator<? super V>);
    Code:
       0: aload_0
       1: aload_1
       2: invokestatic  #35                 // Method com/google/common/base/Preconditions.checkNotNull:(Ljava/lang/Object;)Ljava/lang/Object;
       5: checkcast     #36                 // class java/util/Comparator
       8: putfield      #38                 // Field valueComparator:Ljava/util/Comparator;
      11: aload_0
      12: areturn

  com.google.common.collect.ImmutableMultimap$Builder<K, V> combine(com.google.common.collect.ImmutableMultimap$Builder<K, V>);
    Code:
       0: aload_1
       1: getfield      #3                  // Field builderMap:Ljava/util/Map;
       4: invokeinterface #32,  1           // InterfaceMethod java/util/Map.entrySet:()Ljava/util/Set;
       9: invokeinterface #33,  1           // InterfaceMethod java/util/Set.iterator:()Ljava/util/Iterator;
      14: astore_2
      15: aload_2
      16: invokeinterface #16,  1           // InterfaceMethod java/util/Iterator.hasNext:()Z
      21: ifeq          57
      24: aload_2
      25: invokeinterface #17,  1           // InterfaceMethod java/util/Iterator.next:()Ljava/lang/Object;
      30: checkcast     #18                 // class java/util/Map$Entry
      33: astore_3
      34: aload_0
      35: aload_3
      36: invokeinterface #12,  1           // InterfaceMethod java/util/Map$Entry.getKey:()Ljava/lang/Object;
      41: aload_3
      42: invokeinterface #13,  1           // InterfaceMethod java/util/Map$Entry.getValue:()Ljava/lang/Object;
      47: checkcast     #34                 // class java/lang/Iterable
      50: invokevirtual #30                 // Method putAll:(Ljava/lang/Object;Ljava/lang/Iterable;)Lcom/google/common/collect/ImmutableMultimap$Builder;
      53: pop
      54: goto          15
      57: aload_0
      58: areturn

  public com.google.common.collect.ImmutableMultimap<K, V> build();
    Code:
       0: aload_0
       1: getfield      #3                  // Field builderMap:Ljava/util/Map;
       4: invokeinterface #32,  1           // InterfaceMethod java/util/Map.entrySet:()Ljava/util/Set;
       9: astore_1
      10: aload_0
      11: getfield      #37                 // Field keyComparator:Ljava/util/Comparator;
      14: ifnull        32
      17: aload_0
      18: getfield      #37                 // Field keyComparator:Ljava/util/Comparator;
      21: invokestatic  #39                 // Method com/google/common/collect/Ordering.from:(Ljava/util/Comparator;)Lcom/google/common/collect/Ordering;
      24: invokevirtual #40                 // Method com/google/common/collect/Ordering.onKeys:()Lcom/google/common/collect/Ordering;
      27: aload_1
      28: invokevirtual #41                 // Method com/google/common/collect/Ordering.immutableSortedCopy:(Ljava/lang/Iterable;)Lcom/google/common/collect/ImmutableList;
      31: astore_1
      32: aload_1
      33: aload_0
      34: getfield      #38                 // Field valueComparator:Ljava/util/Comparator;
      37: invokestatic  #42                 // Method com/google/common/collect/ImmutableListMultimap.fromMapEntries:(Ljava/util/Collection;Ljava/util/Comparator;)Lcom/google/common/collect/ImmutableListMultimap;
      40: areturn
}
