Compiled from "ImmutableSortedMap.java"
class com.google.common.collect.ImmutableSortedMap$SerializedForm<K, V> extends com.google.common.collect.ImmutableMap$SerializedForm<K, V> {
  private final java.util.Comparator<? super K> comparator;

  private static final long serialVersionUID;

  com.google.common.collect.ImmutableSortedMap$SerializedForm(com.google.common.collect.ImmutableSortedMap<K, V>);
    Code:
       0: aload_0
       1: aload_1
       2: invokespecial #1                  // Method com/google/common/collect/ImmutableMap$SerializedForm."<init>":(Lcom/google/common/collect/ImmutableMap;)V
       5: aload_0
       6: aload_1
       7: invokevirtual #2                  // Method com/google/common/collect/ImmutableSortedMap.comparator:()Ljava/util/Comparator;
      10: putfield      #3                  // Field comparator:Ljava/util/Comparator;
      13: return

  com.google.common.collect.ImmutableSortedMap$Builder<K, V> makeBuilder(int);
    Code:
       0: new           #4                  // class com/google/common/collect/ImmutableSortedMap$Builder
       3: dup
       4: aload_0
       5: getfield      #3                  // Field comparator:Ljava/util/Comparator;
       8: invokespecial #5                  // Method com/google/common/collect/ImmutableSortedMap$Builder."<init>":(Ljava/util/Comparator;)V
      11: areturn

  com.google.common.collect.ImmutableMap$Builder makeBuilder(int);
    Code:
       0: aload_0
       1: iload_1
       2: invokevirtual #6                  // Method makeBuilder:(I)Lcom/google/common/collect/ImmutableSortedMap$Builder;
       5: areturn
}
