Compiled from "Maps.java"
class com.google.common.collect.Maps$DescendingMap$1EntrySetImpl extends com.google.common.collect.Maps$EntrySet<K, V> {
  final com.google.common.collect.Maps$DescendingMap this$0;

  com.google.common.collect.Maps$DescendingMap$1EntrySetImpl(com.google.common.collect.Maps$DescendingMap);
    Code:
       0: aload_0
       1: aload_1
       2: putfield      #1                  // Field this$0:Lcom/google/common/collect/Maps$DescendingMap;
       5: aload_0
       6: invokespecial #2                  // Method com/google/common/collect/Maps$EntrySet."<init>":()V
       9: return

  java.util.Map<K, V> map();
    Code:
       0: aload_0
       1: getfield      #1                  // Field this$0:Lcom/google/common/collect/Maps$DescendingMap;
       4: areturn

  public java.util.Iterator<java.util.Map$Entry<K, V>> iterator();
    Code:
       0: aload_0
       1: getfield      #1                  // Field this$0:Lcom/google/common/collect/Maps$DescendingMap;
       4: invokevirtual #3                  // Method com/google/common/collect/Maps$DescendingMap.entryIterator:()Ljava/util/Iterator;
       7: areturn
}
