Compiled from "Maps.java"
abstract class com.google.common.collect.Maps$DescendingMap<K, V> extends com.google.common.collect.ForwardingMap<K, V> implements java.util.NavigableMap<K, V> {
  private transient java.util.Comparator<? super K> comparator;

  private transient java.util.Set<java.util.Map$Entry<K, V>> entrySet;

  private transient java.util.NavigableSet<K> navigableKeySet;

  com.google.common.collect.Maps$DescendingMap();
    Code:
       0: aload_0
       1: invokespecial #1                  // Method com/google/common/collect/ForwardingMap."<init>":()V
       4: return

  abstract java.util.NavigableMap<K, V> forward();

  protected final java.util.Map<K, V> delegate();
    Code:
       0: aload_0
       1: invokevirtual #2                  // Method forward:()Ljava/util/NavigableMap;
       4: areturn

  public java.util.Comparator<? super K> comparator();
    Code:
       0: aload_0
       1: getfield      #3                  // Field comparator:Ljava/util/Comparator;
       4: astore_1
       5: aload_1
       6: ifnonnull     37
       9: aload_0
      10: invokevirtual #2                  // Method forward:()Ljava/util/NavigableMap;
      13: invokeinterface #4,  1            // InterfaceMethod java/util/NavigableMap.comparator:()Ljava/util/Comparator;
      18: astore_2
      19: aload_2
      20: ifnonnull     27
      23: invokestatic  #5                  // Method com/google/common/collect/Ordering.natural:()Lcom/google/common/collect/Ordering;
      26: astore_2
      27: aload_0
      28: aload_2
      29: invokestatic  #6                  // Method reverse:(Ljava/util/Comparator;)Lcom/google/common/collect/Ordering;
      32: dup_x1
      33: putfield      #3                  // Field comparator:Ljava/util/Comparator;
      36: astore_1
      37: aload_1
      38: areturn

  private static <T> com.google.common.collect.Ordering<T> reverse(java.util.Comparator<T>);
    Code:
       0: aload_0
       1: invokestatic  #7                  // Method com/google/common/collect/Ordering.from:(Ljava/util/Comparator;)Lcom/google/common/collect/Ordering;
       4: invokevirtual #8                  // Method com/google/common/collect/Ordering.reverse:()Lcom/google/common/collect/Ordering;
       7: areturn

  public K firstKey();
    Code:
       0: aload_0
       1: invokevirtual #2                  // Method forward:()Ljava/util/NavigableMap;
       4: invokeinterface #9,  1            // InterfaceMethod java/util/NavigableMap.lastKey:()Ljava/lang/Object;
       9: areturn

  public K lastKey();
    Code:
       0: aload_0
       1: invokevirtual #2                  // Method forward:()Ljava/util/NavigableMap;
       4: invokeinterface #10,  1           // InterfaceMethod java/util/NavigableMap.firstKey:()Ljava/lang/Object;
       9: areturn

  public java.util.Map$Entry<K, V> lowerEntry(K);
    Code:
       0: aload_0
       1: invokevirtual #2                  // Method forward:()Ljava/util/NavigableMap;
       4: aload_1
       5: invokeinterface #11,  2           // InterfaceMethod java/util/NavigableMap.higherEntry:(Ljava/lang/Object;)Ljava/util/Map$Entry;
      10: areturn

  public K lowerKey(K);
    Code:
       0: aload_0
       1: invokevirtual #2                  // Method forward:()Ljava/util/NavigableMap;
       4: aload_1
       5: invokeinterface #12,  2           // InterfaceMethod java/util/NavigableMap.higherKey:(Ljava/lang/Object;)Ljava/lang/Object;
      10: areturn

  public java.util.Map$Entry<K, V> floorEntry(K);
    Code:
       0: aload_0
       1: invokevirtual #2                  // Method forward:()Ljava/util/NavigableMap;
       4: aload_1
       5: invokeinterface #13,  2           // InterfaceMethod java/util/NavigableMap.ceilingEntry:(Ljava/lang/Object;)Ljava/util/Map$Entry;
      10: areturn

  public K floorKey(K);
    Code:
       0: aload_0
       1: invokevirtual #2                  // Method forward:()Ljava/util/NavigableMap;
       4: aload_1
       5: invokeinterface #14,  2           // InterfaceMethod java/util/NavigableMap.ceilingKey:(Ljava/lang/Object;)Ljava/lang/Object;
      10: areturn

  public java.util.Map$Entry<K, V> ceilingEntry(K);
    Code:
       0: aload_0
       1: invokevirtual #2                  // Method forward:()Ljava/util/NavigableMap;
       4: aload_1
       5: invokeinterface #15,  2           // InterfaceMethod java/util/NavigableMap.floorEntry:(Ljava/lang/Object;)Ljava/util/Map$Entry;
      10: areturn

  public K ceilingKey(K);
    Code:
       0: aload_0
       1: invokevirtual #2                  // Method forward:()Ljava/util/NavigableMap;
       4: aload_1
       5: invokeinterface #16,  2           // InterfaceMethod java/util/NavigableMap.floorKey:(Ljava/lang/Object;)Ljava/lang/Object;
      10: areturn

  public java.util.Map$Entry<K, V> higherEntry(K);
    Code:
       0: aload_0
       1: invokevirtual #2                  // Method forward:()Ljava/util/NavigableMap;
       4: aload_1
       5: invokeinterface #17,  2           // InterfaceMethod java/util/NavigableMap.lowerEntry:(Ljava/lang/Object;)Ljava/util/Map$Entry;
      10: areturn

  public K higherKey(K);
    Code:
       0: aload_0
       1: invokevirtual #2                  // Method forward:()Ljava/util/NavigableMap;
       4: aload_1
       5: invokeinterface #18,  2           // InterfaceMethod java/util/NavigableMap.lowerKey:(Ljava/lang/Object;)Ljava/lang/Object;
      10: areturn

  public java.util.Map$Entry<K, V> firstEntry();
    Code:
       0: aload_0
       1: invokevirtual #2                  // Method forward:()Ljava/util/NavigableMap;
       4: invokeinterface #19,  1           // InterfaceMethod java/util/NavigableMap.lastEntry:()Ljava/util/Map$Entry;
       9: areturn

  public java.util.Map$Entry<K, V> lastEntry();
    Code:
       0: aload_0
       1: invokevirtual #2                  // Method forward:()Ljava/util/NavigableMap;
       4: invokeinterface #20,  1           // InterfaceMethod java/util/NavigableMap.firstEntry:()Ljava/util/Map$Entry;
       9: areturn

  public java.util.Map$Entry<K, V> pollFirstEntry();
    Code:
       0: aload_0
       1: invokevirtual #2                  // Method forward:()Ljava/util/NavigableMap;
       4: invokeinterface #21,  1           // InterfaceMethod java/util/NavigableMap.pollLastEntry:()Ljava/util/Map$Entry;
       9: areturn

  public java.util.Map$Entry<K, V> pollLastEntry();
    Code:
       0: aload_0
       1: invokevirtual #2                  // Method forward:()Ljava/util/NavigableMap;
       4: invokeinterface #22,  1           // InterfaceMethod java/util/NavigableMap.pollFirstEntry:()Ljava/util/Map$Entry;
       9: areturn

  public java.util.NavigableMap<K, V> descendingMap();
    Code:
       0: aload_0
       1: invokevirtual #2                  // Method forward:()Ljava/util/NavigableMap;
       4: areturn

  public java.util.Set<java.util.Map$Entry<K, V>> entrySet();
    Code:
       0: aload_0
       1: getfield      #23                 // Field entrySet:Ljava/util/Set;
       4: astore_1
       5: aload_1
       6: ifnonnull     21
       9: aload_0
      10: aload_0
      11: invokevirtual #24                 // Method createEntrySet:()Ljava/util/Set;
      14: dup_x1
      15: putfield      #23                 // Field entrySet:Ljava/util/Set;
      18: goto          22
      21: aload_1
      22: areturn

  abstract java.util.Iterator<java.util.Map$Entry<K, V>> entryIterator();

  java.util.Set<java.util.Map$Entry<K, V>> createEntrySet();
    Code:
       0: new           #25                 // class com/google/common/collect/Maps$DescendingMap$1EntrySetImpl
       3: dup
       4: aload_0
       5: invokespecial #26                 // Method com/google/common/collect/Maps$DescendingMap$1EntrySetImpl."<init>":(Lcom/google/common/collect/Maps$DescendingMap;)V
       8: areturn

  public java.util.Set<K> keySet();
    Code:
       0: aload_0
       1: invokevirtual #27                 // Method navigableKeySet:()Ljava/util/NavigableSet;
       4: areturn

  public java.util.NavigableSet<K> navigableKeySet();
    Code:
       0: aload_0
       1: getfield      #28                 // Field navigableKeySet:Ljava/util/NavigableSet;
       4: astore_1
       5: aload_1
       6: ifnonnull     25
       9: aload_0
      10: new           #29                 // class com/google/common/collect/Maps$NavigableKeySet
      13: dup
      14: aload_0
      15: invokespecial #30                 // Method com/google/common/collect/Maps$NavigableKeySet."<init>":(Ljava/util/NavigableMap;)V
      18: dup_x1
      19: putfield      #28                 // Field navigableKeySet:Ljava/util/NavigableSet;
      22: goto          26
      25: aload_1
      26: areturn

  public java.util.NavigableSet<K> descendingKeySet();
    Code:
       0: aload_0
       1: invokevirtual #2                  // Method forward:()Ljava/util/NavigableMap;
       4: invokeinterface #31,  1           // InterfaceMethod java/util/NavigableMap.navigableKeySet:()Ljava/util/NavigableSet;
       9: areturn

  public java.util.NavigableMap<K, V> subMap(K, boolean, K, boolean);
    Code:
       0: aload_0
       1: invokevirtual #2                  // Method forward:()Ljava/util/NavigableMap;
       4: aload_3
       5: iload         4
       7: aload_1
       8: iload_2
       9: invokeinterface #32,  5           // InterfaceMethod java/util/NavigableMap.subMap:(Ljava/lang/Object;ZLjava/lang/Object;Z)Ljava/util/NavigableMap;
      14: invokeinterface #33,  1           // InterfaceMethod java/util/NavigableMap.descendingMap:()Ljava/util/NavigableMap;
      19: areturn

  public java.util.SortedMap<K, V> subMap(K, K);
    Code:
       0: aload_0
       1: aload_1
       2: iconst_1
       3: aload_2
       4: iconst_0
       5: invokevirtual #34                 // Method subMap:(Ljava/lang/Object;ZLjava/lang/Object;Z)Ljava/util/NavigableMap;
       8: areturn

  public java.util.NavigableMap<K, V> headMap(K, boolean);
    Code:
       0: aload_0
       1: invokevirtual #2                  // Method forward:()Ljava/util/NavigableMap;
       4: aload_1
       5: iload_2
       6: invokeinterface #35,  3           // InterfaceMethod java/util/NavigableMap.tailMap:(Ljava/lang/Object;Z)Ljava/util/NavigableMap;
      11: invokeinterface #33,  1           // InterfaceMethod java/util/NavigableMap.descendingMap:()Ljava/util/NavigableMap;
      16: areturn

  public java.util.SortedMap<K, V> headMap(K);
    Code:
       0: aload_0
       1: aload_1
       2: iconst_0
       3: invokevirtual #36                 // Method headMap:(Ljava/lang/Object;Z)Ljava/util/NavigableMap;
       6: areturn

  public java.util.NavigableMap<K, V> tailMap(K, boolean);
    Code:
       0: aload_0
       1: invokevirtual #2                  // Method forward:()Ljava/util/NavigableMap;
       4: aload_1
       5: iload_2
       6: invokeinterface #37,  3           // InterfaceMethod java/util/NavigableMap.headMap:(Ljava/lang/Object;Z)Ljava/util/NavigableMap;
      11: invokeinterface #33,  1           // InterfaceMethod java/util/NavigableMap.descendingMap:()Ljava/util/NavigableMap;
      16: areturn

  public java.util.SortedMap<K, V> tailMap(K);
    Code:
       0: aload_0
       1: aload_1
       2: iconst_1
       3: invokevirtual #38                 // Method tailMap:(Ljava/lang/Object;Z)Ljava/util/NavigableMap;
       6: areturn

  public java.util.Collection<V> values();
    Code:
       0: new           #39                 // class com/google/common/collect/Maps$Values
       3: dup
       4: aload_0
       5: invokespecial #40                 // Method com/google/common/collect/Maps$Values."<init>":(Ljava/util/Map;)V
       8: areturn

  public java.lang.String toString();
    Code:
       0: aload_0
       1: invokevirtual #41                 // Method standardToString:()Ljava/lang/String;
       4: areturn

  protected java.lang.Object delegate();
    Code:
       0: aload_0
       1: invokevirtual #42                 // Method delegate:()Ljava/util/Map;
       4: areturn
}
