Compiled from "ReverseNaturalOrdering.java"
final class com.google.common.collect.ReverseNaturalOrdering extends com.google.common.collect.Ordering<java.lang.Comparable<?>> implements java.io.Serializable {
  static final com.google.common.collect.ReverseNaturalOrdering INSTANCE;

  private static final long serialVersionUID;

  public int compare(java.lang.Comparable<?>, java.lang.Comparable<?>);
    Code:
       0: aload_1
       1: invokestatic  #1                  // Method com/google/common/base/Preconditions.checkNotNull:(Ljava/lang/Object;)Ljava/lang/Object;
       4: pop
       5: aload_1
       6: aload_2
       7: if_acmpne     12
      10: iconst_0
      11: ireturn
      12: aload_2
      13: aload_1
      14: invokeinterface #2,  2            // InterfaceMethod java/lang/Comparable.compareTo:(Ljava/lang/Object;)I
      19: ireturn

  public <S extends java.lang.Comparable<?>> com.google.common.collect.Ordering<S> reverse();
    Code:
       0: invokestatic  #3                  // Method com/google/common/collect/Ordering.natural:()Lcom/google/common/collect/Ordering;
       3: areturn

  public <E extends java.lang.Comparable<?>> E min(E, E);
    Code:
       0: getstatic     #4                  // Field com/google/common/collect/NaturalOrdering.INSTANCE:Lcom/google/common/collect/NaturalOrdering;
       3: aload_1
       4: aload_2
       5: invokevirtual #5                  // Method com/google/common/collect/NaturalOrdering.max:(Ljava/lang/Object;Ljava/lang/Object;)Ljava/lang/Object;
       8: checkcast     #6                  // class java/lang/Comparable
      11: areturn

  public <E extends java.lang.Comparable<?>> E min(E, E, E, E...);
    Code:
       0: getstatic     #4                  // Field com/google/common/collect/NaturalOrdering.INSTANCE:Lcom/google/common/collect/NaturalOrdering;
       3: aload_1
       4: aload_2
       5: aload_3
       6: aload         4
       8: invokevirtual #7                  // Method com/google/common/collect/NaturalOrdering.max:(Ljava/lang/Object;Ljava/lang/Object;Ljava/lang/Object;[Ljava/lang/Object;)Ljava/lang/Object;
      11: checkcast     #6                  // class java/lang/Comparable
      14: areturn

  public <E extends java.lang.Comparable<?>> E min(java.util.Iterator<E>);
    Code:
       0: getstatic     #4                  // Field com/google/common/collect/NaturalOrdering.INSTANCE:Lcom/google/common/collect/NaturalOrdering;
       3: aload_1
       4: invokevirtual #8                  // Method com/google/common/collect/NaturalOrdering.max:(Ljava/util/Iterator;)Ljava/lang/Object;
       7: checkcast     #6                  // class java/lang/Comparable
      10: areturn

  public <E extends java.lang.Comparable<?>> E min(java.lang.Iterable<E>);
    Code:
       0: getstatic     #4                  // Field com/google/common/collect/NaturalOrdering.INSTANCE:Lcom/google/common/collect/NaturalOrdering;
       3: aload_1
       4: invokevirtual #9                  // Method com/google/common/collect/NaturalOrdering.max:(Ljava/lang/Iterable;)Ljava/lang/Object;
       7: checkcast     #6                  // class java/lang/Comparable
      10: areturn

  public <E extends java.lang.Comparable<?>> E max(E, E);
    Code:
       0: getstatic     #4                  // Field com/google/common/collect/NaturalOrdering.INSTANCE:Lcom/google/common/collect/NaturalOrdering;
       3: aload_1
       4: aload_2
       5: invokevirtual #10                 // Method com/google/common/collect/NaturalOrdering.min:(Ljava/lang/Object;Ljava/lang/Object;)Ljava/lang/Object;
       8: checkcast     #6                  // class java/lang/Comparable
      11: areturn

  public <E extends java.lang.Comparable<?>> E max(E, E, E, E...);
    Code:
       0: getstatic     #4                  // Field com/google/common/collect/NaturalOrdering.INSTANCE:Lcom/google/common/collect/NaturalOrdering;
       3: aload_1
       4: aload_2
       5: aload_3
       6: aload         4
       8: invokevirtual #11                 // Method com/google/common/collect/NaturalOrdering.min:(Ljava/lang/Object;Ljava/lang/Object;Ljava/lang/Object;[Ljava/lang/Object;)Ljava/lang/Object;
      11: checkcast     #6                  // class java/lang/Comparable
      14: areturn

  public <E extends java.lang.Comparable<?>> E max(java.util.Iterator<E>);
    Code:
       0: getstatic     #4                  // Field com/google/common/collect/NaturalOrdering.INSTANCE:Lcom/google/common/collect/NaturalOrdering;
       3: aload_1
       4: invokevirtual #12                 // Method com/google/common/collect/NaturalOrdering.min:(Ljava/util/Iterator;)Ljava/lang/Object;
       7: checkcast     #6                  // class java/lang/Comparable
      10: areturn

  public <E extends java.lang.Comparable<?>> E max(java.lang.Iterable<E>);
    Code:
       0: getstatic     #4                  // Field com/google/common/collect/NaturalOrdering.INSTANCE:Lcom/google/common/collect/NaturalOrdering;
       3: aload_1
       4: invokevirtual #13                 // Method com/google/common/collect/NaturalOrdering.min:(Ljava/lang/Iterable;)Ljava/lang/Object;
       7: checkcast     #6                  // class java/lang/Comparable
      10: areturn

  private java.lang.Object readResolve();
    Code:
       0: getstatic     #14                 // Field INSTANCE:Lcom/google/common/collect/ReverseNaturalOrdering;
       3: areturn

  public java.lang.String toString();
    Code:
       0: ldc           #15                 // String Ordering.natural().reverse()
       2: areturn

  private com.google.common.collect.ReverseNaturalOrdering();
    Code:
       0: aload_0
       1: invokespecial #16                 // Method com/google/common/collect/Ordering."<init>":()V
       4: return

  public java.lang.Object max(java.lang.Object, java.lang.Object, java.lang.Object, java.lang.Object[]);
    Code:
       0: aload_0
       1: aload_1
       2: checkcast     #6                  // class java/lang/Comparable
       5: aload_2
       6: checkcast     #6                  // class java/lang/Comparable
       9: aload_3
      10: checkcast     #6                  // class java/lang/Comparable
      13: aload         4
      15: checkcast     #17                 // class "[Ljava/lang/Comparable;"
      18: invokevirtual #18                 // Method max:(Ljava/lang/Comparable;Ljava/lang/Comparable;Ljava/lang/Comparable;[Ljava/lang/Comparable;)Ljava/lang/Comparable;
      21: areturn

  public java.lang.Object max(java.lang.Object, java.lang.Object);
    Code:
       0: aload_0
       1: aload_1
       2: checkcast     #6                  // class java/lang/Comparable
       5: aload_2
       6: checkcast     #6                  // class java/lang/Comparable
       9: invokevirtual #19                 // Method max:(Ljava/lang/Comparable;Ljava/lang/Comparable;)Ljava/lang/Comparable;
      12: areturn

  public java.lang.Object max(java.lang.Iterable);
    Code:
       0: aload_0
       1: aload_1
       2: invokevirtual #20                 // Method max:(Ljava/lang/Iterable;)Ljava/lang/Comparable;
       5: areturn

  public java.lang.Object max(java.util.Iterator);
    Code:
       0: aload_0
       1: aload_1
       2: invokevirtual #21                 // Method max:(Ljava/util/Iterator;)Ljava/lang/Comparable;
       5: areturn

  public java.lang.Object min(java.lang.Object, java.lang.Object, java.lang.Object, java.lang.Object[]);
    Code:
       0: aload_0
       1: aload_1
       2: checkcast     #6                  // class java/lang/Comparable
       5: aload_2
       6: checkcast     #6                  // class java/lang/Comparable
       9: aload_3
      10: checkcast     #6                  // class java/lang/Comparable
      13: aload         4
      15: checkcast     #17                 // class "[Ljava/lang/Comparable;"
      18: invokevirtual #22                 // Method min:(Ljava/lang/Comparable;Ljava/lang/Comparable;Ljava/lang/Comparable;[Ljava/lang/Comparable;)Ljava/lang/Comparable;
      21: areturn

  public java.lang.Object min(java.lang.Object, java.lang.Object);
    Code:
       0: aload_0
       1: aload_1
       2: checkcast     #6                  // class java/lang/Comparable
       5: aload_2
       6: checkcast     #6                  // class java/lang/Comparable
       9: invokevirtual #23                 // Method min:(Ljava/lang/Comparable;Ljava/lang/Comparable;)Ljava/lang/Comparable;
      12: areturn

  public java.lang.Object min(java.lang.Iterable);
    Code:
       0: aload_0
       1: aload_1
       2: invokevirtual #24                 // Method min:(Ljava/lang/Iterable;)Ljava/lang/Comparable;
       5: areturn

  public java.lang.Object min(java.util.Iterator);
    Code:
       0: aload_0
       1: aload_1
       2: invokevirtual #25                 // Method min:(Ljava/util/Iterator;)Ljava/lang/Comparable;
       5: areturn

  public int compare(java.lang.Object, java.lang.Object);
    Code:
       0: aload_0
       1: aload_1
       2: checkcast     #6                  // class java/lang/Comparable
       5: aload_2
       6: checkcast     #6                  // class java/lang/Comparable
       9: invokevirtual #26                 // Method compare:(Ljava/lang/Comparable;Ljava/lang/Comparable;)I
      12: ireturn

  static {};
    Code:
       0: new           #27                 // class com/google/common/collect/ReverseNaturalOrdering
       3: dup
       4: invokespecial #28                 // Method "<init>":()V
       7: putstatic     #14                 // Field INSTANCE:Lcom/google/common/collect/ReverseNaturalOrdering;
      10: return
}
