Compiled from "NotificationSupport.java"
public class org.jboss.as.controller.notification.NotificationSupport$Factory {
  private org.jboss.as.controller.notification.NotificationSupport$Factory();
    Code:
       0: aload_0
       1: invokespecial #1                  // Method java/lang/Object."<init>":()V
       4: return

  public static org.jboss.as.controller.notification.NotificationSupport create(java.util.concurrent.ExecutorService);
    Code:
       0: invokestatic  #2                  // Method org/jboss/as/controller/registry/NotificationHandlerRegistration$Factory.create:()Lorg/jboss/as/controller/registry/NotificationHandlerRegistration;
       3: astore_1
       4: aload_0
       5: ifnonnull     17
       8: new           #3                  // class org/jboss/as/controller/notification/NotificationSupports$BlockingNotificationSupport
      11: dup
      12: aload_1
      13: invokespecial #4                  // Method org/jboss/as/controller/notification/NotificationSupports$BlockingNotificationSupport."<init>":(Lorg/jboss/as/controller/registry/NotificationHandlerRegistration;)V
      16: areturn
      17: new           #5                  // class org/jboss/as/controller/notification/NotificationSupports$NonBlockingNotificationSupport
      20: dup
      21: aload_1
      22: aload_0
      23: invokespecial #6                  // Method org/jboss/as/controller/notification/NotificationSupports$NonBlockingNotificationSupport."<init>":(Lorg/jboss/as/controller/registry/NotificationHandlerRegistration;Ljava/util/concurrent/ExecutorService;)V
      26: areturn
}
