Compiled from "Request.java"
public abstract class org.sonar.api.server.ws.Request {
  protected static final java.lang.String MSG_PARAMETER_MISSING;

  public org.sonar.api.server.ws.Request();
    Code:
       0: aload_0
       1: invokespecial #39                 // Method java/lang/Object."<init>":()V
       4: return

  public abstract java.lang.String method();

  public java.io.BufferedReader getReader();
    Code:
       0: new           #47                 // class java/lang/UnsupportedOperationException
       3: dup
       4: ldc           #49                 // String getReader not supported
       6: invokespecial #52                 // Method java/lang/UnsupportedOperationException."<init>":(Ljava/lang/String;)V
       9: athrow

  public abstract java.lang.String getMediaType();

  public abstract boolean hasParam(java.lang.String);

  public java.lang.String mandatoryParam(java.lang.String);
    Code:
       0: aload_0
       1: aload_1
       2: invokevirtual #60                 // Method param:(Ljava/lang/String;)Ljava/lang/String;
       5: astore_2
       6: aload_2
       7: ifnull        21
      10: aload_2
      11: invokevirtual #66                 // Method java/lang/String.isEmpty:()Z
      14: ifne          21
      17: iconst_1
      18: goto          22
      21: iconst_0
      22: ldc           #35                 // String The \'%s\' parameter is missing
      24: iconst_1
      25: anewarray     #4                  // class java/lang/Object
      28: dup
      29: iconst_0
      30: aload_1
      31: aastore
      32: invokestatic  #70                 // Method java/lang/String.format:(Ljava/lang/String;[Ljava/lang/Object;)Ljava/lang/String;
      35: invokestatic  #76                 // Method org/sonar/api/utils/Preconditions.checkArgument:(ZLjava/lang/String;)V
      38: aload_2
      39: areturn

  public boolean mandatoryParamAsBoolean(java.lang.String);
    Code:
       0: aload_0
       1: aload_1
       2: invokevirtual #81                 // Method mandatoryParam:(Ljava/lang/String;)Ljava/lang/String;
       5: astore_2
       6: aload_1
       7: aload_2
       8: invokestatic  #85                 // Method parseBoolean:(Ljava/lang/String;Ljava/lang/String;)Z
      11: ireturn

  public int mandatoryParamAsInt(java.lang.String);
    Code:
       0: aload_0
       1: aload_1
       2: invokevirtual #81                 // Method mandatoryParam:(Ljava/lang/String;)Ljava/lang/String;
       5: astore_2
       6: aload_1
       7: aload_2
       8: invokestatic  #92                 // Method parseInt:(Ljava/lang/String;Ljava/lang/String;)I
      11: ireturn

  public long mandatoryParamAsLong(java.lang.String);
    Code:
       0: aload_0
       1: aload_1
       2: invokevirtual #81                 // Method mandatoryParam:(Ljava/lang/String;)Ljava/lang/String;
       5: astore_2
       6: aload_1
       7: aload_2
       8: invokestatic  #98                 // Method parseLong:(Ljava/lang/String;Ljava/lang/String;)J
      11: lreturn

  public <E extends java.lang.Enum<E>> E mandatoryParamAsEnum(java.lang.String, java.lang.Class<E>);
    Code:
       0: aload_2
       1: aload_0
       2: aload_1
       3: invokevirtual #81                 // Method mandatoryParam:(Ljava/lang/String;)Ljava/lang/String;
       6: invokestatic  #107                // Method java/lang/Enum.valueOf:(Ljava/lang/Class;Ljava/lang/String;)Ljava/lang/Enum;
       9: areturn

  public java.util.List<java.lang.String> mandatoryParamAsStrings(java.lang.String);
    Code:
       0: aload_0
       1: aload_1
       2: invokevirtual #116                // Method paramAsStrings:(Ljava/lang/String;)Ljava/util/List;
       5: astore_2
       6: aload_2
       7: ifnull        14
      10: iconst_1
      11: goto          15
      14: iconst_0
      15: ldc           #35                 // String The \'%s\' parameter is missing
      17: iconst_1
      18: anewarray     #4                  // class java/lang/Object
      21: dup
      22: iconst_0
      23: aload_1
      24: aastore
      25: invokestatic  #70                 // Method java/lang/String.format:(Ljava/lang/String;[Ljava/lang/Object;)Ljava/lang/String;
      28: invokestatic  #76                 // Method org/sonar/api/utils/Preconditions.checkArgument:(ZLjava/lang/String;)V
      31: aload_2
      32: areturn

  public java.util.List<java.lang.String> mandatoryMultiParam(java.lang.String);
    Code:
       0: aload_0
       1: aload_1
       2: invokevirtual #125                // Method multiParam:(Ljava/lang/String;)Ljava/util/List;
       5: astore_2
       6: aload_2
       7: invokeinterface #126,  1          // InterfaceMethod java/util/List.isEmpty:()Z
      12: ifne          19
      15: iconst_1
      16: goto          20
      19: iconst_0
      20: ldc           #35                 // String The \'%s\' parameter is missing
      22: iconst_1
      23: anewarray     #4                  // class java/lang/Object
      26: dup
      27: iconst_0
      28: aload_1
      29: aastore
      30: invokestatic  #129                // Method org/sonar/api/utils/Preconditions.checkArgument:(ZLjava/lang/String;[Ljava/lang/Object;)V
      33: aload_2
      34: areturn

  public abstract java.util.List<java.lang.String> paramAsStrings(java.lang.String);

  public abstract java.util.Map<java.lang.String, java.lang.String[]> getParams();

  public abstract java.lang.String param(java.lang.String);

  public abstract java.util.List<java.lang.String> multiParam(java.lang.String);

  public abstract java.io.InputStream paramAsInputStream(java.lang.String);

  public abstract org.sonar.api.server.ws.Request$Part paramAsPart(java.lang.String);

  public org.sonar.api.server.ws.Request$Part mandatoryParamAsPart(java.lang.String);
    Code:
       0: aload_0
       1: aload_1
       2: invokevirtual #140                // Method paramAsPart:(Ljava/lang/String;)Lorg/sonar/api/server/ws/Request$Part;
       5: astore_2
       6: aload_2
       7: ifnull        14
      10: iconst_1
      11: goto          15
      14: iconst_0
      15: ldc           #35                 // String The \'%s\' parameter is missing
      17: iconst_1
      18: anewarray     #4                  // class java/lang/Object
      21: dup
      22: iconst_0
      23: aload_1
      24: aastore
      25: invokestatic  #129                // Method org/sonar/api/utils/Preconditions.checkArgument:(ZLjava/lang/String;[Ljava/lang/Object;)V
      28: aload_2
      29: areturn

  public java.lang.Boolean paramAsBoolean(java.lang.String);
    Code:
       0: aload_0
       1: aload_1
       2: invokevirtual #60                 // Method param:(Ljava/lang/String;)Ljava/lang/String;
       5: astore_2
       6: aload_2
       7: ifnonnull     14
      10: aconst_null
      11: goto          22
      14: aload_1
      15: aload_2
      16: invokestatic  #85                 // Method parseBoolean:(Ljava/lang/String;Ljava/lang/String;)Z
      19: invokestatic  #149                // Method java/lang/Boolean.valueOf:(Z)Ljava/lang/Boolean;
      22: areturn

  public java.lang.Integer paramAsInt(java.lang.String);
    Code:
       0: aload_0
       1: aload_1
       2: invokevirtual #60                 // Method param:(Ljava/lang/String;)Ljava/lang/String;
       5: astore_2
       6: aload_2
       7: ifnonnull     14
      10: aconst_null
      11: goto          22
      14: aload_1
      15: aload_2
      16: invokestatic  #92                 // Method parseInt:(Ljava/lang/String;Ljava/lang/String;)I
      19: invokestatic  #156                // Method java/lang/Integer.valueOf:(I)Ljava/lang/Integer;
      22: areturn

  public java.lang.Long paramAsLong(java.lang.String);
    Code:
       0: aload_0
       1: aload_1
       2: invokevirtual #60                 // Method param:(Ljava/lang/String;)Ljava/lang/String;
       5: astore_2
       6: aload_2
       7: ifnonnull     14
      10: aconst_null
      11: goto          22
      14: aload_1
      15: aload_2
      16: invokestatic  #98                 // Method parseLong:(Ljava/lang/String;Ljava/lang/String;)J
      19: invokestatic  #163                // Method java/lang/Long.valueOf:(J)Ljava/lang/Long;
      22: areturn

  public <E extends java.lang.Enum<E>> E paramAsEnum(java.lang.String, java.lang.Class<E>);
    Code:
       0: aload_0
       1: aload_1
       2: invokevirtual #60                 // Method param:(Ljava/lang/String;)Ljava/lang/String;
       5: astore_3
       6: aload_3
       7: ifnonnull     14
      10: aconst_null
      11: goto          19
      14: aload_2
      15: aload_3
      16: invokestatic  #107                // Method java/lang/Enum.valueOf:(Ljava/lang/Class;Ljava/lang/String;)Ljava/lang/Enum;
      19: areturn

  public <E extends java.lang.Enum<E>> java.util.List<E> paramAsEnums(java.lang.String, java.lang.Class<E>);
    Code:
       0: aload_0
       1: aload_1
       2: invokevirtual #60                 // Method param:(Ljava/lang/String;)Ljava/lang/String;
       5: astore_3
       6: aload_3
       7: ifnonnull     12
      10: aconst_null
      11: areturn
      12: aload_3
      13: ldc           #169                // String ,
      15: invokevirtual #173                // Method java/lang/String.split:(Ljava/lang/String;)[Ljava/lang/String;
      18: invokestatic  #179                // Method java/util/Arrays.stream:([Ljava/lang/Object;)Ljava/util/stream/Stream;
      21: invokedynamic #197,  0            // InvokeDynamic #0:apply:()Ljava/util/function/Function;
      26: invokeinterface #203,  2          // InterfaceMethod java/util/stream/Stream.map:(Ljava/util/function/Function;)Ljava/util/stream/Stream;
      31: invokedynamic #214,  0            // InvokeDynamic #1:test:()Ljava/util/function/Predicate;
      36: invokeinterface #218,  2          // InterfaceMethod java/util/stream/Stream.filter:(Ljava/util/function/Predicate;)Ljava/util/stream/Stream;
      41: aload_2
      42: invokedynamic #227,  0            // InvokeDynamic #2:apply:(Ljava/lang/Class;)Ljava/util/function/Function;
      47: invokeinterface #203,  2          // InterfaceMethod java/util/stream/Stream.map:(Ljava/util/function/Function;)Ljava/util/stream/Stream;
      52: invokestatic  #233                // Method java/util/stream/Collectors.toList:()Ljava/util/stream/Collector;
      55: invokeinterface #237,  2          // InterfaceMethod java/util/stream/Stream.collect:(Ljava/util/stream/Collector;)Ljava/lang/Object;
      60: checkcast     #118                // class java/util/List
      63: areturn

  public java.util.Date paramAsDateTime(java.lang.String);
    Code:
       0: aload_0
       1: aload_1
       2: invokevirtual #60                 // Method param:(Ljava/lang/String;)Ljava/lang/String;
       5: astore_2
       6: aload_2
       7: ifnonnull     12
      10: aconst_null
      11: areturn
      12: aload_2
      13: invokestatic  #244                // Method org/sonar/api/utils/DateUtils.parseDateTimeQuietly:(Ljava/lang/String;)Ljava/util/Date;
      16: astore_3
      17: aload_3
      18: ifnull        23
      21: aload_3
      22: areturn
      23: aload_2
      24: invokestatic  #249                // Method org/sonar/api/utils/DateUtils.parseDateQuietly:(Ljava/lang/String;)Ljava/util/Date;
      27: astore_3
      28: aload_3
      29: ifnull        36
      32: iconst_1
      33: goto          37
      36: iconst_0
      37: ldc           #251                // String \'%s\' cannot be parsed as either a date or date+time
      39: iconst_1
      40: anewarray     #4                  // class java/lang/Object
      43: dup
      44: iconst_0
      45: aload_2
      46: aastore
      47: invokestatic  #129                // Method org/sonar/api/utils/Preconditions.checkArgument:(ZLjava/lang/String;[Ljava/lang/Object;)V
      50: aload_3
      51: areturn

  public java.util.Date paramAsDate(java.lang.String);
    Code:
       0: aload_0
       1: aload_1
       2: invokevirtual #60                 // Method param:(Ljava/lang/String;)Ljava/lang/String;
       5: astore_2
       6: aload_2
       7: ifnonnull     12
      10: aconst_null
      11: areturn
      12: aload_2
      13: invokestatic  #260                // Method org/sonar/api/utils/DateUtils.parseDate:(Ljava/lang/String;)Ljava/util/Date;
      16: areturn
      17: astore_3
      18: new           #262                // class java/lang/IllegalArgumentException
      21: dup
      22: aload_3
      23: invokespecial #265                // Method java/lang/IllegalArgumentException."<init>":(Ljava/lang/Throwable;)V
      26: athrow
    Exception table:
       from    to  target type
          12    16    17   Class java/lang/RuntimeException

  private static boolean parseBoolean(java.lang.String, java.lang.String);
    Code:
       0: ldc_w         #269                // String true
       3: aload_1
       4: invokevirtual #272                // Method java/lang/String.equals:(Ljava/lang/Object;)Z
       7: ifne          20
      10: ldc_w         #274                // String yes
      13: aload_1
      14: invokevirtual #272                // Method java/lang/String.equals:(Ljava/lang/Object;)Z
      17: ifeq          22
      20: iconst_1
      21: ireturn
      22: ldc_w         #276                // String false
      25: aload_1
      26: invokevirtual #272                // Method java/lang/String.equals:(Ljava/lang/Object;)Z
      29: ifne          42
      32: ldc_w         #278                // String no
      35: aload_1
      36: invokevirtual #272                // Method java/lang/String.equals:(Ljava/lang/Object;)Z
      39: ifeq          44
      42: iconst_0
      43: ireturn
      44: new           #262                // class java/lang/IllegalArgumentException
      47: dup
      48: ldc_w         #280                // String Property %s is not a boolean value: %s
      51: iconst_2
      52: anewarray     #4                  // class java/lang/Object
      55: dup
      56: iconst_0
      57: aload_0
      58: aastore
      59: dup
      60: iconst_1
      61: aload_1
      62: aastore
      63: invokestatic  #70                 // Method java/lang/String.format:(Ljava/lang/String;[Ljava/lang/Object;)Ljava/lang/String;
      66: invokespecial #281                // Method java/lang/IllegalArgumentException."<init>":(Ljava/lang/String;)V
      69: athrow

  private static int parseInt(java.lang.String, java.lang.String);
    Code:
       0: aload_1
       1: invokestatic  #285                // Method java/lang/Integer.parseInt:(Ljava/lang/String;)I
       4: ireturn
       5: astore_2
       6: new           #262                // class java/lang/IllegalArgumentException
       9: dup
      10: ldc_w         #287                // String The \'%s\' parameter cannot be parsed as an integer value: %s
      13: iconst_2
      14: anewarray     #4                  // class java/lang/Object
      17: dup
      18: iconst_0
      19: aload_0
      20: aastore
      21: dup
      22: iconst_1
      23: aload_1
      24: aastore
      25: invokestatic  #70                 // Method java/lang/String.format:(Ljava/lang/String;[Ljava/lang/Object;)Ljava/lang/String;
      28: invokespecial #281                // Method java/lang/IllegalArgumentException."<init>":(Ljava/lang/String;)V
      31: athrow
    Exception table:
       from    to  target type
           0     4     5   Class java/lang/NumberFormatException

  private static long parseLong(java.lang.String, java.lang.String);
    Code:
       0: aload_1
       1: invokestatic  #291                // Method java/lang/Long.parseLong:(Ljava/lang/String;)J
       4: lreturn
       5: astore_2
       6: new           #262                // class java/lang/IllegalArgumentException
       9: dup
      10: ldc_w         #293                // String The \'%s\' parameter cannot be parsed as a long value: %s
      13: iconst_2
      14: anewarray     #4                  // class java/lang/Object
      17: dup
      18: iconst_0
      19: aload_0
      20: aastore
      21: dup
      22: iconst_1
      23: aload_1
      24: aastore
      25: invokestatic  #70                 // Method java/lang/String.format:(Ljava/lang/String;[Ljava/lang/Object;)Ljava/lang/String;
      28: invokespecial #281                // Method java/lang/IllegalArgumentException."<init>":(Ljava/lang/String;)V
      31: athrow
    Exception table:
       from    to  target type
           0     4     5   Class java/lang/NumberFormatException

  public <T> org.sonar.api.server.ws.Request$Param<T> getParam(java.lang.String, java.util.function.BiFunction<org.sonar.api.server.ws.Request, java.lang.String, T>);
    Code:
       0: aload_0
       1: aload_1
       2: invokevirtual #60                 // Method param:(Ljava/lang/String;)Ljava/lang/String;
       5: astore_3
       6: aload_3
       7: ifnull        22
      10: aload_2
      11: aload_0
      12: aload_1
      13: invokeinterface #302,  3          // InterfaceMethod java/util/function/BiFunction.apply:(Ljava/lang/Object;Ljava/lang/Object;)Ljava/lang/Object;
      18: invokestatic  #306                // Method org/sonar/api/server/ws/Request$GenericParam.present:(Ljava/lang/Object;)Lorg/sonar/api/server/ws/Request$Param;
      21: areturn
      22: invokestatic  #310                // Method org/sonar/api/server/ws/Request$AbsentParam.absent:()Lorg/sonar/api/server/ws/Request$Param;
      25: areturn

  public org.sonar.api.server.ws.Request$StringParam getParam(java.lang.String, java.util.function.Consumer<java.lang.String>);
    Code:
       0: aload_0
       1: aload_1
       2: invokevirtual #60                 // Method param:(Ljava/lang/String;)Ljava/lang/String;
       5: astore_3
       6: aload_3
       7: ifnull        22
      10: aload_2
      11: aload_3
      12: invokeinterface #321,  2          // InterfaceMethod java/util/function/Consumer.accept:(Ljava/lang/Object;)V
      17: aload_3
      18: invokestatic  #324                // Method org/sonar/api/server/ws/Request$StringParamImpl.present:(Ljava/lang/String;)Lorg/sonar/api/server/ws/Request$StringParam;
      21: areturn
      22: invokestatic  #327                // Method org/sonar/api/server/ws/Request$AbsentStringParam.absent:()Lorg/sonar/api/server/ws/Request$StringParam;
      25: areturn

  public org.sonar.api.server.ws.Request$StringParam getParam(java.lang.String);
    Code:
       0: aload_0
       1: aload_1
       2: invokevirtual #60                 // Method param:(Ljava/lang/String;)Ljava/lang/String;
       5: astore_2
       6: aload_2
       7: ifnull        15
      10: aload_2
      11: invokestatic  #324                // Method org/sonar/api/server/ws/Request$StringParamImpl.present:(Ljava/lang/String;)Lorg/sonar/api/server/ws/Request$StringParam;
      14: areturn
      15: invokestatic  #327                // Method org/sonar/api/server/ws/Request$AbsentStringParam.absent:()Lorg/sonar/api/server/ws/Request$StringParam;
      18: areturn

  public abstract java.util.Optional<java.lang.String> header(java.lang.String);

  public java.util.Map<java.lang.String, java.lang.String> getHeaders();
    Code:
       0: invokestatic  #340                // Method java/util/Collections.emptyMap:()Ljava/util/Map;
       3: areturn

  public abstract org.sonar.api.server.ws.LocalConnector localConnector();

  public abstract java.lang.String getPath();

  private static <T> java.util.function.Supplier<T> checkDefaultValueSupplier(java.util.function.Supplier<T>);
    Code:
       0: aload_0
       1: ldc_w         #348                // String default value supplier can\'t be null
       4: invokestatic  #354                // Method java/util/Objects.requireNonNull:(Ljava/lang/Object;Ljava/lang/String;)Ljava/lang/Object;
       7: checkcast     #356                // class java/util/function/Supplier
      10: areturn

  private static java.lang.IllegalStateException createGetValueISE();
    Code:
       0: new           #363                // class java/lang/IllegalStateException
       3: dup
       4: ldc_w         #365                // String Param has no value. Use isPresent() before calling getValue()
       7: invokespecial #366                // Method java/lang/IllegalStateException."<init>":(Ljava/lang/String;)V
      10: areturn

  private static java.lang.Enum lambda$paramAsEnums$1(java.lang.Class, java.lang.String);
    Code:
       0: aload_0
       1: aload_1
       2: invokestatic  #107                // Method java/lang/Enum.valueOf:(Ljava/lang/Class;Ljava/lang/String;)Ljava/lang/Enum;
       5: areturn

  private static boolean lambda$paramAsEnums$0(java.lang.String);
    Code:
       0: aload_0
       1: invokevirtual #66                 // Method java/lang/String.isEmpty:()Z
       4: ifne          11
       7: iconst_1
       8: goto          12
      11: iconst_0
      12: ireturn

  static java.lang.IllegalStateException access$000();
    Code:
       0: invokestatic  #370                // Method createGetValueISE:()Ljava/lang/IllegalStateException;
       3: areturn

  static java.util.function.Supplier access$100(java.util.function.Supplier);
    Code:
       0: aload_0
       1: invokestatic  #373                // Method checkDefaultValueSupplier:(Ljava/util/function/Supplier;)Ljava/util/function/Supplier;
       4: areturn
}
