Compiled from "TimestampWithTimeZonePostgisPG95Dialect.java"
public class org.n52.hibernate.spatial.dialect.postgis.TimestampWithTimeZonePostgisPG95Dialect extends org.hibernate.spatial.dialect.postgis.PostgisPG95Dialect {
  private static final long serialVersionUID;

  public org.n52.hibernate.spatial.dialect.postgis.TimestampWithTimeZonePostgisPG95Dialect();
    Code:
       0: aload_0
       1: invokespecial #1                  // Method org/hibernate/spatial/dialect/postgis/PostgisPG95Dialect."<init>":()V
       4: aload_0
       5: bipush        93
       7: ldc           #3                  // String timestamp with time zone
       9: invokevirtual #4                  // Method registerColumnType:(ILjava/lang/String;)V
      12: return

  public java.lang.String buildSqlCreateSpatialIndexString(org.hibernate.mapping.Index, java.lang.String, java.lang.String);
    Code:
       0: aload_1
       1: invokevirtual #5                  // Method org/hibernate/mapping/Index.getName:()Ljava/lang/String;
       4: astore        4
       6: aload_1
       7: invokevirtual #6                  // Method org/hibernate/mapping/Index.getTable:()Lorg/hibernate/mapping/Table;
      10: astore        5
      12: aload_1
      13: invokevirtual #7                  // Method org/hibernate/mapping/Index.getColumnIterator:()Ljava/util/Iterator;
      16: astore        6
      18: new           #8                  // class java/util/HashMap
      21: dup
      22: invokespecial #9                  // Method java/util/HashMap."<init>":()V
      25: astore        7
      27: new           #10                 // class java/lang/StringBuilder
      30: dup
      31: ldc           #11                 // String create
      33: invokespecial #12                 // Method java/lang/StringBuilder."<init>":(Ljava/lang/String;)V
      36: ldc           #13                 // String  index
      38: invokevirtual #14                 // Method java/lang/StringBuilder.append:(Ljava/lang/String;)Ljava/lang/StringBuilder;
      41: aload_0
      42: invokevirtual #15                 // Method qualifyIndexName:()Z
      45: ifeq          53
      48: aload         4
      50: goto          58
      53: aload         4
      55: invokestatic  #16                 // Method org/hibernate/internal/util/StringHelper.unqualify:(Ljava/lang/String;)Ljava/lang/String;
      58: invokevirtual #14                 // Method java/lang/StringBuilder.append:(Ljava/lang/String;)Ljava/lang/StringBuilder;
      61: ldc           #17                 // String  on
      63: invokevirtual #14                 // Method java/lang/StringBuilder.append:(Ljava/lang/String;)Ljava/lang/StringBuilder;
      66: aload         5
      68: aload_0
      69: aload_2
      70: aload_3
      71: invokevirtual #18                 // Method org/hibernate/mapping/Table.getQualifiedName:(Lorg/hibernate/dialect/Dialect;Ljava/lang/String;Ljava/lang/String;)Ljava/lang/String;
      74: invokevirtual #14                 // Method java/lang/StringBuilder.append:(Ljava/lang/String;)Ljava/lang/StringBuilder;
      77: ldc           #19                 // String  USING GIST
      79: invokevirtual #14                 // Method java/lang/StringBuilder.append:(Ljava/lang/String;)Ljava/lang/StringBuilder;
      82: ldc           #20                 // String  (
      84: invokevirtual #14                 // Method java/lang/StringBuilder.append:(Ljava/lang/String;)Ljava/lang/StringBuilder;
      87: astore        8
      89: aload         6
      91: invokeinterface #21,  1           // InterfaceMethod java/util/Iterator.hasNext:()Z
      96: ifeq          179
      99: aload         6
     101: invokeinterface #22,  1           // InterfaceMethod java/util/Iterator.next:()Ljava/lang/Object;
     106: checkcast     #23                 // class org/hibernate/mapping/Column
     109: astore        9
     111: aload         8
     113: aload         9
     115: aload_0
     116: invokevirtual #24                 // Method org/hibernate/mapping/Column.getQuotedName:(Lorg/hibernate/dialect/Dialect;)Ljava/lang/String;
     119: invokevirtual #14                 // Method java/lang/StringBuilder.append:(Ljava/lang/String;)Ljava/lang/StringBuilder;
     122: pop
     123: aload         7
     125: aload         9
     127: invokeinterface #25,  2           // InterfaceMethod java/util/Map.containsKey:(Ljava/lang/Object;)Z
     132: ifeq          158
     135: aload         8
     137: ldc           #26                 // String
     139: invokevirtual #14                 // Method java/lang/StringBuilder.append:(Ljava/lang/String;)Ljava/lang/StringBuilder;
     142: aload         7
     144: aload         9
     146: invokeinterface #27,  2           // InterfaceMethod java/util/Map.get:(Ljava/lang/Object;)Ljava/lang/Object;
     151: checkcast     #28                 // class java/lang/String
     154: invokevirtual #14                 // Method java/lang/StringBuilder.append:(Ljava/lang/String;)Ljava/lang/StringBuilder;
     157: pop
     158: aload         6
     160: invokeinterface #21,  1           // InterfaceMethod java/util/Iterator.hasNext:()Z
     165: ifeq          176
     168: aload         8
     170: ldc           #29                 // String ,
     172: invokevirtual #14                 // Method java/lang/StringBuilder.append:(Ljava/lang/String;)Ljava/lang/StringBuilder;
     175: pop
     176: goto          89
     179: aload         8
     181: ldc           #30                 // String )
     183: invokevirtual #14                 // Method java/lang/StringBuilder.append:(Ljava/lang/String;)Ljava/lang/StringBuilder;
     186: pop
     187: aload         8
     189: invokevirtual #31                 // Method java/lang/StringBuilder.toString:()Ljava/lang/String;
     192: areturn
}
