Compiled from "PathPrefixPredicate.java"
public class io.undertow.predicate.PathPrefixPredicate implements io.undertow.predicate.Predicate {
  public static final java.lang.String PREFIX_MATCH_RECORD;

  private final io.undertow.util.PathMatcher<java.lang.Boolean> pathMatcher;

  private static final boolean traceEnabled;

  io.undertow.predicate.PathPrefixPredicate(java.lang.String...);
    Code:
       0: aload_0
       1: invokespecial #1                  // Method java/lang/Object."<init>":()V
       4: new           #2                  // class io/undertow/util/PathMatcher
       7: dup
       8: invokespecial #3                  // Method io/undertow/util/PathMatcher."<init>":()V
      11: astore_2
      12: aload_1
      13: astore_3
      14: aload_3
      15: arraylength
      16: istore        4
      18: iconst_0
      19: istore        5
      21: iload         5
      23: iload         4
      25: if_icmpge     78
      28: aload_3
      29: iload         5
      31: aaload
      32: astore        6
      34: aload         6
      36: ldc           #4                  // String /
      38: invokevirtual #5                  // Method java/lang/String.startsWith:(Ljava/lang/String;)Z
      41: ifne          62
      44: aload_2
      45: aload         6
      47: invokedynamic #6,  0              // InvokeDynamic #0:makeConcatWithConstants:(Ljava/lang/String;)Ljava/lang/String;
      52: getstatic     #7                  // Field java/lang/Boolean.TRUE:Ljava/lang/Boolean;
      55: invokevirtual #8                  // Method io/undertow/util/PathMatcher.addPrefixPath:(Ljava/lang/String;Ljava/lang/Object;)Lio/undertow/util/PathMatcher;
      58: pop
      59: goto          72
      62: aload_2
      63: aload         6
      65: getstatic     #7                  // Field java/lang/Boolean.TRUE:Ljava/lang/Boolean;
      68: invokevirtual #8                  // Method io/undertow/util/PathMatcher.addPrefixPath:(Ljava/lang/String;Ljava/lang/Object;)Lio/undertow/util/PathMatcher;
      71: pop
      72: iinc          5, 1
      75: goto          21
      78: aload_0
      79: aload_2
      80: putfield      #9                  // Field pathMatcher:Lio/undertow/util/PathMatcher;
      83: return

  public boolean resolve(io.undertow.server.HttpServerExchange);
    Code:
       0: aload_1
       1: invokevirtual #10                 // Method io/undertow/server/HttpServerExchange.getRelativePath:()Ljava/lang/String;
       4: astore_2
       5: aload_0
       6: getfield      #9                  // Field pathMatcher:Lio/undertow/util/PathMatcher;
       9: aload_2
      10: invokevirtual #11                 // Method io/undertow/util/PathMatcher.match:(Ljava/lang/String;)Lio/undertow/util/PathMatcher$PathMatch;
      13: astore_3
      14: getstatic     #7                  // Field java/lang/Boolean.TRUE:Ljava/lang/Boolean;
      17: aload_3
      18: invokevirtual #12                 // Method io/undertow/util/PathMatcher$PathMatch.getValue:()Ljava/lang/Object;
      21: invokevirtual #13                 // Method java/lang/Boolean.equals:(Ljava/lang/Object;)Z
      24: istore        4
      26: getstatic     #14                 // Field traceEnabled:Z
      29: ifeq          94
      32: getstatic     #15                 // Field io/undertow/UndertowLogger.PREDICATE_LOGGER:Lio/undertow/UndertowLogger;
      35: ldc           #16                 // String Path prefix(s) [%s] %s input [%s] for %s.
      37: iconst_4
      38: anewarray     #17                 // class java/lang/Object
      41: dup
      42: iconst_0
      43: aload_0
      44: getfield      #9                  // Field pathMatcher:Lio/undertow/util/PathMatcher;
      47: invokevirtual #18                 // Method io/undertow/util/PathMatcher.getPathMatchesSet:()Ljava/util/Set;
      50: invokeinterface #19,  1           // InterfaceMethod java/util/Set.stream:()Ljava/util/stream/Stream;
      55: ldc           #20                 // String ,
      57: invokestatic  #21                 // Method java/util/stream/Collectors.joining:(Ljava/lang/CharSequence;)Ljava/util/stream/Collector;
      60: invokeinterface #22,  2           // InterfaceMethod java/util/stream/Stream.collect:(Ljava/util/stream/Collector;)Ljava/lang/Object;
      65: aastore
      66: dup
      67: iconst_1
      68: iload         4
      70: ifeq          78
      73: ldc           #23                 // String MATCH
      75: goto          80
      78: ldc           #24                 // String DO NOT MATCH
      80: aastore
      81: dup
      82: iconst_2
      83: aload_2
      84: aastore
      85: dup
      86: iconst_3
      87: aload_1
      88: aastore
      89: invokeinterface #25,  3           // InterfaceMethod io/undertow/UndertowLogger.tracef:(Ljava/lang/String;[Ljava/lang/Object;)V
      94: iload         4
      96: ifeq          218
      99: aload_1
     100: getstatic     #26                 // Field PREDICATE_CONTEXT:Lio/undertow/util/AttachmentKey;
     103: invokevirtual #27                 // Method io/undertow/server/HttpServerExchange.getAttachment:(Lio/undertow/util/AttachmentKey;)Ljava/lang/Object;
     106: checkcast     #28                 // class java/util/Map
     109: astore        5
     111: aload         5
     113: ifnonnull     134
     116: aload_1
     117: getstatic     #26                 // Field PREDICATE_CONTEXT:Lio/undertow/util/AttachmentKey;
     120: new           #29                 // class java/util/TreeMap
     123: dup
     124: invokespecial #30                 // Method java/util/TreeMap."<init>":()V
     127: dup
     128: astore        5
     130: invokevirtual #31                 // Method io/undertow/server/HttpServerExchange.putAttachment:(Lio/undertow/util/AttachmentKey;Ljava/lang/Object;)Ljava/lang/Object;
     133: pop
     134: getstatic     #14                 // Field traceEnabled:Z
     137: ifeq          165
     140: aload_3
     141: invokevirtual #32                 // Method io/undertow/util/PathMatcher$PathMatch.getRemaining:()Ljava/lang/String;
     144: invokevirtual #33                 // Method java/lang/String.length:()I
     147: ifle          165
     150: getstatic     #15                 // Field io/undertow/UndertowLogger.PREDICATE_LOGGER:Lio/undertow/UndertowLogger;
     153: ldc           #34                 // String Storing \"remaining\" string of [%s] for %s.
     155: aload_3
     156: invokevirtual #32                 // Method io/undertow/util/PathMatcher$PathMatch.getRemaining:()Ljava/lang/String;
     159: aload_1
     160: invokeinterface #35,  4           // InterfaceMethod io/undertow/UndertowLogger.tracef:(Ljava/lang/String;Ljava/lang/Object;Ljava/lang/Object;)V
     165: aload         5
     167: ldc           #36                 // String remaining
     169: aload_3
     170: invokevirtual #32                 // Method io/undertow/util/PathMatcher$PathMatch.getRemaining:()Ljava/lang/String;
     173: invokeinterface #37,  3           // InterfaceMethod java/util/Map.put:(Ljava/lang/Object;Ljava/lang/Object;)Ljava/lang/Object;
     178: pop
     179: new           #38                 // class io/undertow/predicate/PathPrefixPredicate$PathPrefixMatchRecord
     182: dup
     183: invokespecial #39                 // Method io/undertow/predicate/PathPrefixPredicate$PathPrefixMatchRecord."<init>":()V
     186: astore        6
     188: aload         6
     190: aload_3
     191: invokevirtual #32                 // Method io/undertow/util/PathMatcher$PathMatch.getRemaining:()Ljava/lang/String;
     194: invokevirtual #40                 // Method io/undertow/predicate/PathPrefixPredicate$PathPrefixMatchRecord.setRemaining:(Ljava/lang/String;)V
     197: aload         6
     199: aload_3
     200: invokevirtual #41                 // Method io/undertow/util/PathMatcher$PathMatch.getMatched:()Ljava/lang/String;
     203: invokevirtual #42                 // Method io/undertow/predicate/PathPrefixPredicate$PathPrefixMatchRecord.setPrefix:(Ljava/lang/String;)V
     206: aload         5
     208: ldc           #44                 // String PREFIX_MATCH_RECORD
     210: aload         6
     212: invokeinterface #37,  3           // InterfaceMethod java/util/Map.put:(Ljava/lang/Object;Ljava/lang/Object;)Ljava/lang/Object;
     217: pop
     218: iload         4
     220: ireturn

  public java.lang.String toString();
    Code:
       0: aload_0
       1: getfield      #9                  // Field pathMatcher:Lio/undertow/util/PathMatcher;
       4: invokevirtual #18                 // Method io/undertow/util/PathMatcher.getPathMatchesSet:()Ljava/util/Set;
       7: astore_1
       8: aload_1
       9: invokeinterface #45,  1           // InterfaceMethod java/util/Set.size:()I
      14: iconst_1
      15: if_icmpne     32
      18: aload_1
      19: invokeinterface #46,  1           // InterfaceMethod java/util/Set.toArray:()[Ljava/lang/Object;
      24: iconst_0
      25: aaload
      26: invokedynamic #47,  0             // InvokeDynamic #1:makeConcatWithConstants:(Ljava/lang/Object;)Ljava/lang/String;
      31: areturn
      32: aload_1
      33: invokeinterface #19,  1           // InterfaceMethod java/util/Set.stream:()Ljava/util/stream/Stream;
      38: ldc           #48                 // String \', \'
      40: invokestatic  #21                 // Method java/util/stream/Collectors.joining:(Ljava/lang/CharSequence;)Ljava/util/stream/Collector;
      43: invokeinterface #22,  2           // InterfaceMethod java/util/stream/Stream.collect:(Ljava/util/stream/Collector;)Ljava/lang/Object;
      48: checkcast     #49                 // class java/lang/String
      51: invokedynamic #50,  0             // InvokeDynamic #2:makeConcatWithConstants:(Ljava/lang/String;)Ljava/lang/String;
      56: areturn

  static {};
    Code:
       0: getstatic     #15                 // Field io/undertow/UndertowLogger.PREDICATE_LOGGER:Lio/undertow/UndertowLogger;
       3: invokeinterface #51,  1           // InterfaceMethod io/undertow/UndertowLogger.isTraceEnabled:()Z
       8: putstatic     #14                 // Field traceEnabled:Z
      11: return
}
