Compiled from "SecurePredicate.java"
public class io.undertow.predicate.SecurePredicate implements io.undertow.predicate.Predicate {
  public static final io.undertow.predicate.SecurePredicate INSTANCE;

  public io.undertow.predicate.SecurePredicate();
    Code:
       0: aload_0
       1: invokespecial #1                  // Method java/lang/Object."<init>":()V
       4: return

  public boolean resolve(io.undertow.server.HttpServerExchange);
    Code:
       0: aload_1
       1: invokevirtual #2                  // Method io/undertow/server/HttpServerExchange.getRequestScheme:()Ljava/lang/String;
       4: ldc           #3                  // String https
       6: invokevirtual #4                  // Method java/lang/String.equals:(Ljava/lang/Object;)Z
       9: ireturn

  public java.lang.String toString();
    Code:
       0: ldc           #5                  // String secure()
       2: areturn

  static {};
    Code:
       0: new           #6                  // class io/undertow/predicate/SecurePredicate
       3: dup
       4: invokespecial #7                  // Method "<init>":()V
       7: putstatic     #8                  // Field INSTANCE:Lio/undertow/predicate/SecurePredicate;
      10: return
}
