Compiled from "DefaultSource.scala"
public final class org.elasticsearch.spark.sql.ElasticsearchRelation$$anonfun$org$elasticsearch$spark$sql$ElasticsearchRelation$$extract$1 extends scala.runtime.AbstractFunction1<java.lang.Object, java.lang.String> implements scala.Serializable {
  public static final long serialVersionUID;

  private final org.elasticsearch.spark.sql.ElasticsearchRelation $outer;

  public final java.lang.String apply(java.lang.Object);
    Code:
       0: aload_0
       1: getfield      #23                 // Field $outer:Lorg/elasticsearch/spark/sql/ElasticsearchRelation;
       4: aload_1
       5: iconst_1
       6: iconst_0
       7: invokevirtual #24                 // Method org/elasticsearch/spark/sql/ElasticsearchRelation.org$elasticsearch$spark$sql$ElasticsearchRelation$$extract:(Ljava/lang/Object;ZZ)Ljava/lang/String;
      10: areturn

  public final java.lang.Object apply(java.lang.Object);
    Code:
       0: aload_0
       1: aload_1
       2: invokevirtual #31                 // Method apply:(Ljava/lang/Object;)Ljava/lang/String;
       5: areturn

  public org.elasticsearch.spark.sql.ElasticsearchRelation$$anonfun$org$elasticsearch$spark$sql$ElasticsearchRelation$$extract$1(org.elasticsearch.spark.sql.ElasticsearchRelation);
    Code:
       0: aload_1
       1: ifnonnull     6
       4: aconst_null
       5: athrow
       6: aload_0
       7: aload_1
       8: putfield      #23                 // Field $outer:Lorg/elasticsearch/spark/sql/ElasticsearchRelation;
      11: aload_0
      12: invokespecial #37                 // Method scala/runtime/AbstractFunction1."<init>":()V
      15: return
}
