Compiled from "SparkSQLCompatibilityLevel.scala"
public class org.elasticsearch.spark.sql.SparkSQLCompatibilityLevel implements org.elasticsearch.spark.rdd.CompatibilityLevel {
  private final java.lang.String versionId;

  private final java.lang.String versionDescription;

  public java.lang.String versionId();
    Code:
       0: aload_0
       1: getfield      #16                 // Field versionId:Ljava/lang/String;
       4: areturn

  public java.lang.String versionDescription();
    Code:
       0: aload_0
       1: getfield      #20                 // Field versionDescription:Ljava/lang/String;
       4: areturn

  public org.elasticsearch.spark.sql.SparkSQLCompatibilityLevel();
    Code:
       0: aload_0
       1: invokespecial #24                 // Method java/lang/Object."<init>":()V
       4: aload_0
       5: ldc           #26                 // String 13
       7: putfield      #16                 // Field versionId:Ljava/lang/String;
      10: aload_0
      11: ldc           #28                 // String 1.3-1.6
      13: putfield      #20                 // Field versionDescription:Ljava/lang/String;
      16: return
}
