Compiled from "Connection.java"
public class won.protocol.model.Connection implements won.protocol.model.parentaware.ParentAware<won.protocol.model.ConnectionContainer>, won.protocol.model.parentaware.VersionedEntity {
  private java.lang.Long id;

  private int version;

  private java.util.Date lastUpdate;

  private java.net.URI connectionURI;

  private java.net.URI atomURI;

  private java.net.URI typeURI;

  private java.net.URI socketURI;

  private java.net.URI targetSocketURI;

  private java.net.URI targetConnectionURI;

  private java.net.URI targetAtomURI;

  private won.protocol.model.ConnectionState state;

  private won.protocol.model.ConnectionContainer parent;

  private won.protocol.model.DatasetHolder datasetHolder;

  private won.protocol.model.ConnectionMessageContainer messageContainer;

  public won.protocol.model.Connection();
    Code:
       0: aload_0
       1: invokespecial #1                  // Method java/lang/Object."<init>":()V
       4: aload_0
       5: iconst_0
       6: putfield      #2                  // Field version:I
       9: aload_0
      10: new           #3                  // class java/util/Date
      13: dup
      14: invokespecial #4                  // Method java/util/Date."<init>":()V
      17: putfield      #5                  // Field lastUpdate:Ljava/util/Date;
      20: aload_0
      21: aconst_null
      22: putfield      #6                  // Field messageContainer:Lwon/protocol/model/ConnectionMessageContainer;
      25: return

  public won.protocol.model.ConnectionContainer getParent();
    Code:
       0: aload_0
       1: getfield      #7                  // Field parent:Lwon/protocol/model/ConnectionContainer;
       4: areturn

  public won.protocol.model.ConnectionMessageContainer getMessageContainer();
    Code:
       0: aload_0
       1: getfield      #6                  // Field messageContainer:Lwon/protocol/model/ConnectionMessageContainer;
       4: areturn

  public void setMessageContainer(won.protocol.model.ConnectionMessageContainer);
    Code:
       0: aload_0
       1: aload_1
       2: putfield      #6                  // Field messageContainer:Lwon/protocol/model/ConnectionMessageContainer;
       5: return

  public void setParent(won.protocol.model.ConnectionContainer);
    Code:
       0: aload_0
       1: aload_1
       2: putfield      #7                  // Field parent:Lwon/protocol/model/ConnectionContainer;
       5: return

  public void incrementVersion();
    Code:
       0: aload_0
       1: dup
       2: getfield      #2                  // Field version:I
       5: iconst_1
       6: iadd
       7: putfield      #2                  // Field version:I
      10: aload_0
      11: new           #3                  // class java/util/Date
      14: dup
      15: invokespecial #4                  // Method java/util/Date."<init>":()V
      18: putfield      #5                  // Field lastUpdate:Ljava/util/Date;
      21: return

  public java.net.URI getTypeURI();
    Code:
       0: aload_0
       1: getfield      #8                  // Field typeURI:Ljava/net/URI;
       4: areturn

  public java.lang.String toString();
    Code:
       0: new           #9                  // class java/lang/StringBuilder
       3: dup
       4: invokespecial #10                 // Method java/lang/StringBuilder."<init>":()V
       7: ldc           #11                 // String Connection [id=
       9: invokevirtual #12                 // Method java/lang/StringBuilder.append:(Ljava/lang/String;)Ljava/lang/StringBuilder;
      12: aload_0
      13: getfield      #13                 // Field id:Ljava/lang/Long;
      16: invokevirtual #14                 // Method java/lang/StringBuilder.append:(Ljava/lang/Object;)Ljava/lang/StringBuilder;
      19: ldc           #15                 // String , connectionURI=
      21: invokevirtual #12                 // Method java/lang/StringBuilder.append:(Ljava/lang/String;)Ljava/lang/StringBuilder;
      24: aload_0
      25: getfield      #16                 // Field connectionURI:Ljava/net/URI;
      28: invokevirtual #14                 // Method java/lang/StringBuilder.append:(Ljava/lang/Object;)Ljava/lang/StringBuilder;
      31: ldc           #17                 // String , atomURI=
      33: invokevirtual #12                 // Method java/lang/StringBuilder.append:(Ljava/lang/String;)Ljava/lang/StringBuilder;
      36: aload_0
      37: getfield      #18                 // Field atomURI:Ljava/net/URI;
      40: invokevirtual #14                 // Method java/lang/StringBuilder.append:(Ljava/lang/Object;)Ljava/lang/StringBuilder;
      43: ldc           #19                 // String , typeURI=
      45: invokevirtual #12                 // Method java/lang/StringBuilder.append:(Ljava/lang/String;)Ljava/lang/StringBuilder;
      48: aload_0
      49: getfield      #8                  // Field typeURI:Ljava/net/URI;
      52: invokevirtual #14                 // Method java/lang/StringBuilder.append:(Ljava/lang/Object;)Ljava/lang/StringBuilder;
      55: ldc           #20                 // String , socketURI=
      57: invokevirtual #12                 // Method java/lang/StringBuilder.append:(Ljava/lang/String;)Ljava/lang/StringBuilder;
      60: aload_0
      61: getfield      #21                 // Field socketURI:Ljava/net/URI;
      64: invokevirtual #14                 // Method java/lang/StringBuilder.append:(Ljava/lang/Object;)Ljava/lang/StringBuilder;
      67: ldc           #22                 // String , targetSocketURI=
      69: invokevirtual #12                 // Method java/lang/StringBuilder.append:(Ljava/lang/String;)Ljava/lang/StringBuilder;
      72: aload_0
      73: getfield      #23                 // Field targetSocketURI:Ljava/net/URI;
      76: invokevirtual #14                 // Method java/lang/StringBuilder.append:(Ljava/lang/Object;)Ljava/lang/StringBuilder;
      79: ldc           #24                 // String , targetConnectionURI=
      81: invokevirtual #12                 // Method java/lang/StringBuilder.append:(Ljava/lang/String;)Ljava/lang/StringBuilder;
      84: aload_0
      85: getfield      #25                 // Field targetConnectionURI:Ljava/net/URI;
      88: invokevirtual #14                 // Method java/lang/StringBuilder.append:(Ljava/lang/Object;)Ljava/lang/StringBuilder;
      91: ldc           #26                 // String , targetAtomURI=
      93: invokevirtual #12                 // Method java/lang/StringBuilder.append:(Ljava/lang/String;)Ljava/lang/StringBuilder;
      96: aload_0
      97: getfield      #27                 // Field targetAtomURI:Ljava/net/URI;
     100: invokevirtual #14                 // Method java/lang/StringBuilder.append:(Ljava/lang/Object;)Ljava/lang/StringBuilder;
     103: ldc           #28                 // String , state=
     105: invokevirtual #12                 // Method java/lang/StringBuilder.append:(Ljava/lang/String;)Ljava/lang/StringBuilder;
     108: aload_0
     109: getfield      #29                 // Field state:Lwon/protocol/model/ConnectionState;
     112: invokevirtual #14                 // Method java/lang/StringBuilder.append:(Ljava/lang/Object;)Ljava/lang/StringBuilder;
     115: ldc           #30                 // String ]
     117: invokevirtual #12                 // Method java/lang/StringBuilder.append:(Ljava/lang/String;)Ljava/lang/StringBuilder;
     120: invokevirtual #31                 // Method java/lang/StringBuilder.toString:()Ljava/lang/String;
     123: areturn

  public void setTypeURI(java.net.URI);
    Code:
       0: aload_0
       1: aload_1
       2: putfield      #8                  // Field typeURI:Ljava/net/URI;
       5: return

  public java.net.URI getSocketURI();
    Code:
       0: aload_0
       1: getfield      #21                 // Field socketURI:Ljava/net/URI;
       4: areturn

  public void setSocketURI(java.net.URI);
    Code:
       0: aload_0
       1: aload_1
       2: putfield      #21                 // Field socketURI:Ljava/net/URI;
       5: return

  public java.net.URI getTargetSocketURI();
    Code:
       0: aload_0
       1: getfield      #23                 // Field targetSocketURI:Ljava/net/URI;
       4: areturn

  public void setTargetSocketURI(java.net.URI);
    Code:
       0: aload_0
       1: aload_1
       2: putfield      #23                 // Field targetSocketURI:Ljava/net/URI;
       5: return

  public java.lang.Long getId();
    Code:
       0: aload_0
       1: getfield      #13                 // Field id:Ljava/lang/Long;
       4: areturn

  public void setId(java.lang.Long);
    Code:
       0: aload_0
       1: aload_1
       2: putfield      #13                 // Field id:Ljava/lang/Long;
       5: return

  public java.net.URI getConnectionURI();
    Code:
       0: aload_0
       1: getfield      #16                 // Field connectionURI:Ljava/net/URI;
       4: areturn

  public void setConnectionURI(java.net.URI);
    Code:
       0: aload_0
       1: aload_1
       2: putfield      #16                 // Field connectionURI:Ljava/net/URI;
       5: return

  public java.net.URI getAtomURI();
    Code:
       0: aload_0
       1: getfield      #18                 // Field atomURI:Ljava/net/URI;
       4: areturn

  public void setAtomURI(java.net.URI);
    Code:
       0: aload_0
       1: aload_1
       2: putfield      #18                 // Field atomURI:Ljava/net/URI;
       5: return

  public java.net.URI getTargetConnectionURI();
    Code:
       0: aload_0
       1: getfield      #25                 // Field targetConnectionURI:Ljava/net/URI;
       4: areturn

  public void setTargetConnectionURI(java.net.URI);
    Code:
       0: aload_0
       1: aload_1
       2: putfield      #25                 // Field targetConnectionURI:Ljava/net/URI;
       5: return

  public java.net.URI getTargetAtomURI();
    Code:
       0: aload_0
       1: getfield      #27                 // Field targetAtomURI:Ljava/net/URI;
       4: areturn

  public void setTargetAtomURI(java.net.URI);
    Code:
       0: aload_0
       1: aload_1
       2: putfield      #27                 // Field targetAtomURI:Ljava/net/URI;
       5: return

  public won.protocol.model.ConnectionState getState();
    Code:
       0: aload_0
       1: getfield      #29                 // Field state:Lwon/protocol/model/ConnectionState;
       4: areturn

  public void setState(won.protocol.model.ConnectionState);
    Code:
       0: aload_0
       1: aload_1
       2: putfield      #29                 // Field state:Lwon/protocol/model/ConnectionState;
       5: return

  protected void setVersion(int);
    Code:
       0: aload_0
       1: iload_1
       2: putfield      #2                  // Field version:I
       5: return

  public int getVersion();
    Code:
       0: aload_0
       1: getfield      #2                  // Field version:I
       4: ireturn

  public java.util.Date getLastUpdate();
    Code:
       0: aload_0
       1: getfield      #5                  // Field lastUpdate:Ljava/util/Date;
       4: areturn

  protected void setLastUpdate(java.util.Date);
    Code:
       0: aload_0
       1: aload_1
       2: putfield      #5                  // Field lastUpdate:Ljava/util/Date;
       5: return

  public won.protocol.model.DatasetHolder getDatasetHolder();
    Code:
       0: aload_0
       1: getfield      #32                 // Field datasetHolder:Lwon/protocol/model/DatasetHolder;
       4: areturn

  public void setDatasetHolder(won.protocol.model.DatasetHolder);
    Code:
       0: aload_0
       1: aload_1
       2: putfield      #32                 // Field datasetHolder:Lwon/protocol/model/DatasetHolder;
       5: return

  public boolean equals(java.lang.Object);
    Code:
       0: aload_0
       1: aload_1
       2: if_acmpne     7
       5: iconst_1
       6: ireturn
       7: aload_1
       8: instanceof    #33                 // class won/protocol/model/Connection
      11: ifne          16
      14: iconst_0
      15: ireturn
      16: aload_1
      17: checkcast     #33                 // class won/protocol/model/Connection
      20: astore_2
      21: aload_0
      22: getfield      #16                 // Field connectionURI:Ljava/net/URI;
      25: ifnull        45
      28: aload_0
      29: getfield      #16                 // Field connectionURI:Ljava/net/URI;
      32: aload_2
      33: getfield      #16                 // Field connectionURI:Ljava/net/URI;
      36: invokevirtual #34                 // Method java/net/URI.equals:(Ljava/lang/Object;)Z
      39: ifne          54
      42: goto          52
      45: aload_2
      46: getfield      #16                 // Field connectionURI:Ljava/net/URI;
      49: ifnull        54
      52: iconst_0
      53: ireturn
      54: aload_0
      55: getfield      #18                 // Field atomURI:Ljava/net/URI;
      58: ifnull        78
      61: aload_0
      62: getfield      #18                 // Field atomURI:Ljava/net/URI;
      65: aload_2
      66: getfield      #18                 // Field atomURI:Ljava/net/URI;
      69: invokevirtual #34                 // Method java/net/URI.equals:(Ljava/lang/Object;)Z
      72: ifne          87
      75: goto          85
      78: aload_2
      79: getfield      #18                 // Field atomURI:Ljava/net/URI;
      82: ifnull        87
      85: iconst_0
      86: ireturn
      87: aload_0
      88: getfield      #25                 // Field targetConnectionURI:Ljava/net/URI;
      91: ifnull        111
      94: aload_0
      95: getfield      #25                 // Field targetConnectionURI:Ljava/net/URI;
      98: aload_2
      99: getfield      #25                 // Field targetConnectionURI:Ljava/net/URI;
     102: invokevirtual #34                 // Method java/net/URI.equals:(Ljava/lang/Object;)Z
     105: ifne          120
     108: goto          118
     111: aload_2
     112: getfield      #25                 // Field targetConnectionURI:Ljava/net/URI;
     115: ifnull        120
     118: iconst_0
     119: ireturn
     120: aload_0
     121: getfield      #27                 // Field targetAtomURI:Ljava/net/URI;
     124: ifnull        144
     127: aload_0
     128: getfield      #27                 // Field targetAtomURI:Ljava/net/URI;
     131: aload_2
     132: getfield      #27                 // Field targetAtomURI:Ljava/net/URI;
     135: invokevirtual #34                 // Method java/net/URI.equals:(Ljava/lang/Object;)Z
     138: ifne          153
     141: goto          151
     144: aload_2
     145: getfield      #27                 // Field targetAtomURI:Ljava/net/URI;
     148: ifnull        153
     151: iconst_0
     152: ireturn
     153: aload_0
     154: getfield      #29                 // Field state:Lwon/protocol/model/ConnectionState;
     157: aload_2
     158: getfield      #29                 // Field state:Lwon/protocol/model/ConnectionState;
     161: if_acmpeq     166
     164: iconst_0
     165: ireturn
     166: iconst_1
     167: ireturn

  public int hashCode();
    Code:
       0: aload_0
       1: getfield      #16                 // Field connectionURI:Ljava/net/URI;
       4: ifnull        17
       7: aload_0
       8: getfield      #16                 // Field connectionURI:Ljava/net/URI;
      11: invokevirtual #35                 // Method java/net/URI.hashCode:()I
      14: goto          18
      17: iconst_0
      18: istore_1
      19: bipush        31
      21: iload_1
      22: imul
      23: aload_0
      24: getfield      #18                 // Field atomURI:Ljava/net/URI;
      27: ifnull        40
      30: aload_0
      31: getfield      #18                 // Field atomURI:Ljava/net/URI;
      34: invokevirtual #35                 // Method java/net/URI.hashCode:()I
      37: goto          41
      40: iconst_0
      41: iadd
      42: istore_1
      43: bipush        31
      45: iload_1
      46: imul
      47: aload_0
      48: getfield      #25                 // Field targetConnectionURI:Ljava/net/URI;
      51: ifnull        64
      54: aload_0
      55: getfield      #25                 // Field targetConnectionURI:Ljava/net/URI;
      58: invokevirtual #35                 // Method java/net/URI.hashCode:()I
      61: goto          65
      64: iconst_0
      65: iadd
      66: istore_1
      67: bipush        31
      69: iload_1
      70: imul
      71: aload_0
      72: getfield      #27                 // Field targetAtomURI:Ljava/net/URI;
      75: ifnull        88
      78: aload_0
      79: getfield      #27                 // Field targetAtomURI:Ljava/net/URI;
      82: invokevirtual #35                 // Method java/net/URI.hashCode:()I
      85: goto          89
      88: iconst_0
      89: iadd
      90: istore_1
      91: bipush        31
      93: iload_1
      94: imul
      95: aload_0
      96: getfield      #29                 // Field state:Lwon/protocol/model/ConnectionState;
      99: ifnull        112
     102: aload_0
     103: getfield      #29                 // Field state:Lwon/protocol/model/ConnectionState;
     106: invokevirtual #36                 // Method won/protocol/model/ConnectionState.hashCode:()I
     109: goto          113
     112: iconst_0
     113: iadd
     114: istore_1
     115: iload_1
     116: ireturn

  public won.protocol.model.parentaware.VersionedEntity getParent();
    Code:
       0: aload_0
       1: invokevirtual #37                 // Method getParent:()Lwon/protocol/model/ConnectionContainer;
       4: areturn
}
