Compiled from "OctetSequenceJsonWebKey.java"
public class org.jose4j.jwk.OctetSequenceJsonWebKey extends org.jose4j.jwk.JsonWebKey {
  public static final java.lang.String KEY_TYPE;

  public static final java.lang.String KEY_VALUE_MEMBER_NAME;

  private byte[] octetSequence;

  public org.jose4j.jwk.OctetSequenceJsonWebKey(java.security.Key);
    Code:
       0: aload_0
       1: aload_1
       2: invokespecial #1                  // Method org/jose4j/jwk/JsonWebKey."<init>":(Ljava/security/Key;)V
       5: aload_0
       6: aload_1
       7: invokeinterface #2,  1            // InterfaceMethod java/security/Key.getEncoded:()[B
      12: putfield      #3                  // Field octetSequence:[B
      15: return

  public org.jose4j.jwk.OctetSequenceJsonWebKey(java.util.Map<java.lang.String, java.lang.Object>) throws org.jose4j.lang.JoseException;
    Code:
       0: aload_0
       1: aload_1
       2: invokespecial #4                  // Method org/jose4j/jwk/JsonWebKey."<init>":(Ljava/util/Map;)V
       5: new           #5                  // class org/jose4j/base64url/Base64Url
       8: dup
       9: invokespecial #6                  // Method org/jose4j/base64url/Base64Url."<init>":()V
      12: astore_2
      13: aload_1
      14: ldc           #7                  // String k
      16: invokestatic  #8                  // Method getStringRequired:(Ljava/util/Map;Ljava/lang/String;)Ljava/lang/String;
      19: astore_3
      20: aload_0
      21: aload_2
      22: aload_3
      23: invokevirtual #9                  // Method org/jose4j/base64url/Base64Url.base64UrlDecode:(Ljava/lang/String;)[B
      26: putfield      #3                  // Field octetSequence:[B
      29: ldc           #10                 // String AES
      31: astore        4
      33: aload_0
      34: new           #11                 // class javax/crypto/spec/SecretKeySpec
      37: dup
      38: aload_0
      39: getfield      #3                  // Field octetSequence:[B
      42: aload         4
      44: invokespecial #12                 // Method javax/crypto/spec/SecretKeySpec."<init>":([BLjava/lang/String;)V
      47: putfield      #13                 // Field key:Ljava/security/Key;
      50: aload_0
      51: iconst_1
      52: anewarray     #14                 // class java/lang/String
      55: dup
      56: iconst_0
      57: ldc           #7                  // String k
      59: aastore
      60: invokevirtual #15                 // Method removeFromOtherParams:([Ljava/lang/String;)V
      63: return

  public java.lang.String getKeyType();
    Code:
       0: ldc           #16                 // String oct
       2: areturn

  public byte[] getOctetSequence();
    Code:
       0: aload_0
       1: getfield      #3                  // Field octetSequence:[B
       4: areturn

  private java.lang.String getEncoded();
    Code:
       0: aload_0
       1: getfield      #3                  // Field octetSequence:[B
       4: invokestatic  #17                 // Method org/jose4j/base64url/Base64Url.encode:([B)Ljava/lang/String;
       7: areturn

  protected void fillTypeSpecificParams(java.util.Map<java.lang.String, java.lang.Object>, org.jose4j.jwk.JsonWebKey$OutputControlLevel);
    Code:
       0: getstatic     #18                 // Field org/jose4j/jwk/JsonWebKey$OutputControlLevel.INCLUDE_SYMMETRIC:Lorg/jose4j/jwk/JsonWebKey$OutputControlLevel;
       3: aload_2
       4: invokevirtual #19                 // Method org/jose4j/jwk/JsonWebKey$OutputControlLevel.compareTo:(Ljava/lang/Enum;)I
       7: iflt          23
      10: aload_1
      11: ldc           #7                  // String k
      13: aload_0
      14: invokespecial #20                 // Method getEncoded:()Ljava/lang/String;
      17: invokeinterface #21,  3           // InterfaceMethod java/util/Map.put:(Ljava/lang/Object;Ljava/lang/Object;)Ljava/lang/Object;
      22: pop
      23: return

  protected java.lang.String produceThumbprintHashInput();
    Code:
       0: ldc           #22                 // String {\"k\":\"%s\",\"kty\":\"oct\"}
       2: astore_1
       3: aload_0
       4: invokespecial #20                 // Method getEncoded:()Ljava/lang/String;
       7: astore_2
       8: aload_1
       9: iconst_1
      10: anewarray     #23                 // class java/lang/Object
      13: dup
      14: iconst_0
      15: aload_2
      16: aastore
      17: invokestatic  #24                 // Method java/lang/String.format:(Ljava/lang/String;[Ljava/lang/Object;)Ljava/lang/String;
      20: areturn
}
