Compiled from "RsaJsonWebKey.java"
public class org.jose4j.jwk.RsaJsonWebKey extends org.jose4j.jwk.PublicJsonWebKey {
  public static final java.lang.String MODULUS_MEMBER_NAME;

  public static final java.lang.String EXPONENT_MEMBER_NAME;

  public static final java.lang.String PRIVATE_EXPONENT_MEMBER_NAME;

  public static final java.lang.String FIRST_PRIME_FACTOR_MEMBER_NAME;

  public static final java.lang.String SECOND_PRIME_FACTOR_MEMBER_NAME;

  public static final java.lang.String FIRST_FACTOR_CRT_EXPONENT_MEMBER_NAME;

  public static final java.lang.String SECOND_FACTOR_CRT_EXPONENT_MEMBER_NAME;

  public static final java.lang.String FIRST_CRT_COEFFICIENT_MEMBER_NAME;

  public static final java.lang.String OTHER_PRIMES_INFO_MEMBER_NAME;

  public static final java.lang.String PRIME_FACTOR_OTHER_MEMBER_NAME;

  public static final java.lang.String FACTOR_CRT_EXPONENT_OTHER_MEMBER_NAME;

  public static final java.lang.String FACTOR_CRT_COEFFICIENT;

  public static final java.lang.String KEY_TYPE;

  public org.jose4j.jwk.RsaJsonWebKey(java.security.interfaces.RSAPublicKey);
    Code:
       0: aload_0
       1: aload_1
       2: invokespecial #1                  // Method org/jose4j/jwk/PublicJsonWebKey."<init>":(Ljava/security/PublicKey;)V
       5: return

  public org.jose4j.jwk.RsaJsonWebKey(java.util.Map<java.lang.String, java.lang.Object>) throws org.jose4j.lang.JoseException;
    Code:
       0: aload_0
       1: aload_1
       2: aconst_null
       3: invokespecial #2                  // Method "<init>":(Ljava/util/Map;Ljava/lang/String;)V
       6: return

  public org.jose4j.jwk.RsaJsonWebKey(java.util.Map<java.lang.String, java.lang.Object>, java.lang.String) throws org.jose4j.lang.JoseException;
    Code:
       0: aload_0
       1: aload_1
       2: aload_2
       3: invokespecial #3                  // Method org/jose4j/jwk/PublicJsonWebKey."<init>":(Ljava/util/Map;Ljava/lang/String;)V
       6: aload_0
       7: aload_1
       8: ldc           #4                  // String n
      10: iconst_1
      11: invokevirtual #5                  // Method getBigIntFromBase64UrlEncodedParam:(Ljava/util/Map;Ljava/lang/String;Z)Ljava/math/BigInteger;
      14: astore_3
      15: aload_0
      16: aload_1
      17: ldc           #6                  // String e
      19: iconst_1
      20: invokevirtual #5                  // Method getBigIntFromBase64UrlEncodedParam:(Ljava/util/Map;Ljava/lang/String;Z)Ljava/math/BigInteger;
      23: astore        4
      25: new           #7                  // class org/jose4j/keys/RsaKeyUtil
      28: dup
      29: aload_2
      30: aconst_null
      31: invokespecial #8                  // Method org/jose4j/keys/RsaKeyUtil."<init>":(Ljava/lang/String;Ljava/security/SecureRandom;)V
      34: astore        5
      36: aload_0
      37: aload         5
      39: aload_3
      40: aload         4
      42: invokevirtual #9                  // Method org/jose4j/keys/RsaKeyUtil.publicKey:(Ljava/math/BigInteger;Ljava/math/BigInteger;)Ljava/security/interfaces/RSAPublicKey;
      45: putfield      #10                 // Field key:Ljava/security/Key;
      48: aload_0
      49: invokevirtual #11                 // Method checkForBareKeyCertMismatch:()V
      52: aload_1
      53: ldc           #12                 // String d
      55: invokeinterface #13,  2           // InterfaceMethod java/util/Map.containsKey:(Ljava/lang/Object;)Z
      60: ifeq          173
      63: aload_0
      64: aload_1
      65: ldc           #12                 // String d
      67: iconst_0
      68: invokevirtual #5                  // Method getBigIntFromBase64UrlEncodedParam:(Ljava/util/Map;Ljava/lang/String;Z)Ljava/math/BigInteger;
      71: astore        6
      73: aload_1
      74: ldc           #14                 // String p
      76: invokeinterface #13,  2           // InterfaceMethod java/util/Map.containsKey:(Ljava/lang/Object;)Z
      81: ifeq          161
      84: aload_0
      85: aload_1
      86: ldc           #14                 // String p
      88: iconst_0
      89: invokevirtual #5                  // Method getBigIntFromBase64UrlEncodedParam:(Ljava/util/Map;Ljava/lang/String;Z)Ljava/math/BigInteger;
      92: astore        7
      94: aload_0
      95: aload_1
      96: ldc           #15                 // String q
      98: iconst_0
      99: invokevirtual #5                  // Method getBigIntFromBase64UrlEncodedParam:(Ljava/util/Map;Ljava/lang/String;Z)Ljava/math/BigInteger;
     102: astore        8
     104: aload_0
     105: aload_1
     106: ldc           #16                 // String dp
     108: iconst_0
     109: invokevirtual #5                  // Method getBigIntFromBase64UrlEncodedParam:(Ljava/util/Map;Ljava/lang/String;Z)Ljava/math/BigInteger;
     112: astore        9
     114: aload_0
     115: aload_1
     116: ldc           #17                 // String dq
     118: iconst_0
     119: invokevirtual #5                  // Method getBigIntFromBase64UrlEncodedParam:(Ljava/util/Map;Ljava/lang/String;Z)Ljava/math/BigInteger;
     122: astore        10
     124: aload_0
     125: aload_1
     126: ldc           #18                 // String qi
     128: iconst_0
     129: invokevirtual #5                  // Method getBigIntFromBase64UrlEncodedParam:(Ljava/util/Map;Ljava/lang/String;Z)Ljava/math/BigInteger;
     132: astore        11
     134: aload_0
     135: aload         5
     137: aload_3
     138: aload         4
     140: aload         6
     142: aload         7
     144: aload         8
     146: aload         9
     148: aload         10
     150: aload         11
     152: invokevirtual #19                 // Method org/jose4j/keys/RsaKeyUtil.privateKey:(Ljava/math/BigInteger;Ljava/math/BigInteger;Ljava/math/BigInteger;Ljava/math/BigInteger;Ljava/math/BigInteger;Ljava/math/BigInteger;Ljava/math/BigInteger;Ljava/math/BigInteger;)Ljava/security/interfaces/RSAPrivateKey;
     155: putfield      #20                 // Field privateKey:Ljava/security/PrivateKey;
     158: goto          173
     161: aload_0
     162: aload         5
     164: aload_3
     165: aload         6
     167: invokevirtual #21                 // Method org/jose4j/keys/RsaKeyUtil.privateKey:(Ljava/math/BigInteger;Ljava/math/BigInteger;)Ljava/security/interfaces/RSAPrivateKey;
     170: putfield      #20                 // Field privateKey:Ljava/security/PrivateKey;
     173: aload_0
     174: bipush        8
     176: anewarray     #22                 // class java/lang/String
     179: dup
     180: iconst_0
     181: ldc           #4                  // String n
     183: aastore
     184: dup
     185: iconst_1
     186: ldc           #6                  // String e
     188: aastore
     189: dup
     190: iconst_2
     191: ldc           #12                 // String d
     193: aastore
     194: dup
     195: iconst_3
     196: ldc           #14                 // String p
     198: aastore
     199: dup
     200: iconst_4
     201: ldc           #15                 // String q
     203: aastore
     204: dup
     205: iconst_5
     206: ldc           #16                 // String dp
     208: aastore
     209: dup
     210: bipush        6
     212: ldc           #17                 // String dq
     214: aastore
     215: dup
     216: bipush        7
     218: ldc           #18                 // String qi
     220: aastore
     221: invokevirtual #23                 // Method removeFromOtherParams:([Ljava/lang/String;)V
     224: return

  public java.lang.String getKeyType();
    Code:
       0: ldc           #24                 // String RSA
       2: areturn

  public java.security.interfaces.RSAPublicKey getRsaPublicKey();
    Code:
       0: aload_0
       1: getfield      #10                 // Field key:Ljava/security/Key;
       4: checkcast     #25                 // class java/security/interfaces/RSAPublicKey
       7: areturn

  public java.security.interfaces.RSAPublicKey getRSAPublicKey();
    Code:
       0: aload_0
       1: invokevirtual #26                 // Method getRsaPublicKey:()Ljava/security/interfaces/RSAPublicKey;
       4: areturn

  public java.security.interfaces.RSAPrivateKey getRsaPrivateKey();
    Code:
       0: aload_0
       1: getfield      #20                 // Field privateKey:Ljava/security/PrivateKey;
       4: checkcast     #27                 // class java/security/interfaces/RSAPrivateKey
       7: areturn

  protected void fillPublicTypeSpecificParams(java.util.Map<java.lang.String, java.lang.Object>);
    Code:
       0: aload_0
       1: invokevirtual #26                 // Method getRsaPublicKey:()Ljava/security/interfaces/RSAPublicKey;
       4: astore_2
       5: aload_0
       6: aload_1
       7: ldc           #4                  // String n
       9: aload_2
      10: invokeinterface #28,  1           // InterfaceMethod java/security/interfaces/RSAPublicKey.getModulus:()Ljava/math/BigInteger;
      15: invokevirtual #29                 // Method putBigIntAsBase64UrlEncodedParam:(Ljava/util/Map;Ljava/lang/String;Ljava/math/BigInteger;)V
      18: aload_0
      19: aload_1
      20: ldc           #6                  // String e
      22: aload_2
      23: invokeinterface #30,  1           // InterfaceMethod java/security/interfaces/RSAPublicKey.getPublicExponent:()Ljava/math/BigInteger;
      28: invokevirtual #29                 // Method putBigIntAsBase64UrlEncodedParam:(Ljava/util/Map;Ljava/lang/String;Ljava/math/BigInteger;)V
      31: return

  protected void fillPrivateTypeSpecificParams(java.util.Map<java.lang.String, java.lang.Object>);
    Code:
       0: aload_0
       1: invokevirtual #31                 // Method getRsaPrivateKey:()Ljava/security/interfaces/RSAPrivateKey;
       4: astore_2
       5: aload_2
       6: ifnull        99
       9: aload_0
      10: aload_1
      11: ldc           #12                 // String d
      13: aload_2
      14: invokeinterface #32,  1           // InterfaceMethod java/security/interfaces/RSAPrivateKey.getPrivateExponent:()Ljava/math/BigInteger;
      19: invokevirtual #29                 // Method putBigIntAsBase64UrlEncodedParam:(Ljava/util/Map;Ljava/lang/String;Ljava/math/BigInteger;)V
      22: aload_2
      23: instanceof    #33                 // class java/security/interfaces/RSAPrivateCrtKey
      26: ifeq          99
      29: aload_2
      30: checkcast     #33                 // class java/security/interfaces/RSAPrivateCrtKey
      33: astore_3
      34: aload_0
      35: aload_1
      36: ldc           #14                 // String p
      38: aload_3
      39: invokeinterface #34,  1           // InterfaceMethod java/security/interfaces/RSAPrivateCrtKey.getPrimeP:()Ljava/math/BigInteger;
      44: invokevirtual #29                 // Method putBigIntAsBase64UrlEncodedParam:(Ljava/util/Map;Ljava/lang/String;Ljava/math/BigInteger;)V
      47: aload_0
      48: aload_1
      49: ldc           #15                 // String q
      51: aload_3
      52: invokeinterface #35,  1           // InterfaceMethod java/security/interfaces/RSAPrivateCrtKey.getPrimeQ:()Ljava/math/BigInteger;
      57: invokevirtual #29                 // Method putBigIntAsBase64UrlEncodedParam:(Ljava/util/Map;Ljava/lang/String;Ljava/math/BigInteger;)V
      60: aload_0
      61: aload_1
      62: ldc           #16                 // String dp
      64: aload_3
      65: invokeinterface #36,  1           // InterfaceMethod java/security/interfaces/RSAPrivateCrtKey.getPrimeExponentP:()Ljava/math/BigInteger;
      70: invokevirtual #29                 // Method putBigIntAsBase64UrlEncodedParam:(Ljava/util/Map;Ljava/lang/String;Ljava/math/BigInteger;)V
      73: aload_0
      74: aload_1
      75: ldc           #17                 // String dq
      77: aload_3
      78: invokeinterface #37,  1           // InterfaceMethod java/security/interfaces/RSAPrivateCrtKey.getPrimeExponentQ:()Ljava/math/BigInteger;
      83: invokevirtual #29                 // Method putBigIntAsBase64UrlEncodedParam:(Ljava/util/Map;Ljava/lang/String;Ljava/math/BigInteger;)V
      86: aload_0
      87: aload_1
      88: ldc           #18                 // String qi
      90: aload_3
      91: invokeinterface #38,  1           // InterfaceMethod java/security/interfaces/RSAPrivateCrtKey.getCrtCoefficient:()Ljava/math/BigInteger;
      96: invokevirtual #29                 // Method putBigIntAsBase64UrlEncodedParam:(Ljava/util/Map;Ljava/lang/String;Ljava/math/BigInteger;)V
      99: return

  protected java.lang.String produceThumbprintHashInput();
    Code:
       0: ldc           #39                 // String {\"e\":\"%s\",\"kty\":\"RSA\",\"n\":\"%s\"}
       2: astore_1
       3: new           #40                 // class java/util/HashMap
       6: dup
       7: invokespecial #41                 // Method java/util/HashMap."<init>":()V
      10: astore_2
      11: aload_0
      12: aload_2
      13: invokevirtual #42                 // Method fillPublicTypeSpecificParams:(Ljava/util/Map;)V
      16: aload_1
      17: iconst_2
      18: anewarray     #43                 // class java/lang/Object
      21: dup
      22: iconst_0
      23: aload_2
      24: ldc           #6                  // String e
      26: invokevirtual #44                 // Method java/util/HashMap.get:(Ljava/lang/Object;)Ljava/lang/Object;
      29: aastore
      30: dup
      31: iconst_1
      32: aload_2
      33: ldc           #4                  // String n
      35: invokevirtual #44                 // Method java/util/HashMap.get:(Ljava/lang/Object;)Ljava/lang/Object;
      38: aastore
      39: invokestatic  #45                 // Method java/lang/String.format:(Ljava/lang/String;[Ljava/lang/Object;)Ljava/lang/String;
      42: areturn
}
