Compiled from "PretouchUtil.java"
public final class net.openhft.chronicle.queue.util.PretouchUtil {
  private net.openhft.chronicle.queue.util.PretouchUtil();
    Code:
       0: aload_0
       1: invokespecial #1                  // Method java/lang/Object."<init>":()V
       4: return

  public static net.openhft.chronicle.core.threads.EventHandler createEventHandler(net.openhft.chronicle.queue.impl.single.SingleChronicleQueue);
    Code:
       0: new           #2                  // class net/openhft/chronicle/queue/internal/InternalPretouchHandler
       3: dup
       4: aload_0
       5: invokespecial #3                  // Method net/openhft/chronicle/queue/internal/InternalPretouchHandler."<init>":(Lnet/openhft/chronicle/queue/impl/single/SingleChronicleQueue;)V
       8: areturn
}
