Compiled from "BasicResourcePool.java"
class com.mchange.v2.resourcepool.BasicResourcePool$ScatteredAcquireTask implements java.lang.Runnable {
  int attempts_remaining;

  final com.mchange.v2.resourcepool.BasicResourcePool this$0;

  com.mchange.v2.resourcepool.BasicResourcePool$ScatteredAcquireTask(com.mchange.v2.resourcepool.BasicResourcePool);
    Code:
       0: aload_0
       1: aload_1
       2: aload_1
       3: getfield      #2                  // Field com/mchange/v2/resourcepool/BasicResourcePool.num_acq_attempts:I
       6: iflt          16
       9: aload_1
      10: getfield      #2                  // Field com/mchange/v2/resourcepool/BasicResourcePool.num_acq_attempts:I
      13: goto          17
      16: iconst_m1
      17: iconst_1
      18: invokespecial #1                  // Method "<init>":(Lcom/mchange/v2/resourcepool/BasicResourcePool;IZ)V
      21: return

  private com.mchange.v2.resourcepool.BasicResourcePool$ScatteredAcquireTask(com.mchange.v2.resourcepool.BasicResourcePool, int, boolean);
    Code:
       0: aload_0
       1: aload_1
       2: putfield      #3                  // Field this$0:Lcom/mchange/v2/resourcepool/BasicResourcePool;
       5: aload_0
       6: invokespecial #4                  // Method java/lang/Object."<init>":()V
       9: aload_0
      10: iload_2
      11: putfield      #5                  // Field attempts_remaining:I
      14: iload_3
      15: ifeq          83
      18: aload_1
      19: invokestatic  #6                  // Method com/mchange/v2/resourcepool/BasicResourcePool.access$600:(Lcom/mchange/v2/resourcepool/BasicResourcePool;)V
      22: invokestatic  #7                  // Method com/mchange/v2/resourcepool/BasicResourcePool.access$000:()Lcom/mchange/v2/log/MLogger;
      25: getstatic     #8                  // Field com/mchange/v2/log/MLevel.FINEST:Lcom/mchange/v2/log/MLevel;
      28: invokeinterface #9,  2            // InterfaceMethod com/mchange/v2/log/MLogger.isLoggable:(Lcom/mchange/v2/log/MLevel;)Z
      33: ifeq          141
      36: invokestatic  #7                  // Method com/mchange/v2/resourcepool/BasicResourcePool.access$000:()Lcom/mchange/v2/log/MLogger;
      39: new           #10                 // class java/lang/StringBuilder
      42: dup
      43: invokespecial #11                 // Method java/lang/StringBuilder."<init>":()V
      46: ldc           #12                 // String Starting acquisition series. Incremented pending_acquires [
      48: invokevirtual #13                 // Method java/lang/StringBuilder.append:(Ljava/lang/String;)Ljava/lang/StringBuilder;
      51: aload_1
      52: getfield      #14                 // Field com/mchange/v2/resourcepool/BasicResourcePool.pending_acquires:I
      55: invokevirtual #15                 // Method java/lang/StringBuilder.append:(I)Ljava/lang/StringBuilder;
      58: ldc           #16                 // String ],
      60: invokevirtual #13                 // Method java/lang/StringBuilder.append:(Ljava/lang/String;)Ljava/lang/StringBuilder;
      63: ldc           #17                 // String  attempts_remaining:
      65: invokevirtual #13                 // Method java/lang/StringBuilder.append:(Ljava/lang/String;)Ljava/lang/StringBuilder;
      68: iload_2
      69: invokevirtual #15                 // Method java/lang/StringBuilder.append:(I)Ljava/lang/StringBuilder;
      72: invokevirtual #18                 // Method java/lang/StringBuilder.toString:()Ljava/lang/String;
      75: invokeinterface #19,  2           // InterfaceMethod com/mchange/v2/log/MLogger.finest:(Ljava/lang/String;)V
      80: goto          141
      83: invokestatic  #7                  // Method com/mchange/v2/resourcepool/BasicResourcePool.access$000:()Lcom/mchange/v2/log/MLogger;
      86: getstatic     #8                  // Field com/mchange/v2/log/MLevel.FINEST:Lcom/mchange/v2/log/MLevel;
      89: invokeinterface #9,  2            // InterfaceMethod com/mchange/v2/log/MLogger.isLoggable:(Lcom/mchange/v2/log/MLevel;)Z
      94: ifeq          141
      97: invokestatic  #7                  // Method com/mchange/v2/resourcepool/BasicResourcePool.access$000:()Lcom/mchange/v2/log/MLogger;
     100: new           #10                 // class java/lang/StringBuilder
     103: dup
     104: invokespecial #11                 // Method java/lang/StringBuilder."<init>":()V
     107: ldc           #20                 // String Continuing acquisition series. pending_acquires [
     109: invokevirtual #13                 // Method java/lang/StringBuilder.append:(Ljava/lang/String;)Ljava/lang/StringBuilder;
     112: aload_1
     113: getfield      #14                 // Field com/mchange/v2/resourcepool/BasicResourcePool.pending_acquires:I
     116: invokevirtual #15                 // Method java/lang/StringBuilder.append:(I)Ljava/lang/StringBuilder;
     119: ldc           #16                 // String ],
     121: invokevirtual #13                 // Method java/lang/StringBuilder.append:(Ljava/lang/String;)Ljava/lang/StringBuilder;
     124: ldc           #17                 // String  attempts_remaining:
     126: invokevirtual #13                 // Method java/lang/StringBuilder.append:(Ljava/lang/String;)Ljava/lang/StringBuilder;
     129: iload_2
     130: invokevirtual #15                 // Method java/lang/StringBuilder.append:(I)Ljava/lang/StringBuilder;
     133: invokevirtual #18                 // Method java/lang/StringBuilder.toString:()Ljava/lang/String;
     136: invokeinterface #19,  2           // InterfaceMethod com/mchange/v2/log/MLogger.finest:(Ljava/lang/String;)V
     141: return

  public void run();
    Code:
       0: iconst_0
       1: istore_1
       2: aload_0
       3: getfield      #3                  // Field this$0:Lcom/mchange/v2/resourcepool/BasicResourcePool;
       6: dup
       7: astore        4
       9: monitorenter
      10: aload_0
      11: getfield      #3                  // Field this$0:Lcom/mchange/v2/resourcepool/BasicResourcePool;
      14: getfield      #21                 // Field com/mchange/v2/resourcepool/BasicResourcePool.force_kill_acquires:Z
      17: istore_2
      18: aload_0
      19: getfield      #3                  // Field this$0:Lcom/mchange/v2/resourcepool/BasicResourcePool;
      22: getfield      #22                 // Field com/mchange/v2/resourcepool/BasicResourcePool.broken:Z
      25: istore_3
      26: aload         4
      28: monitorexit
      29: goto          40
      32: astore        5
      34: aload         4
      36: monitorexit
      37: aload         5
      39: athrow
      40: iload_3
      41: ifne          58
      44: iload_2
      45: ifne          58
      48: aload_0
      49: getfield      #3                  // Field this$0:Lcom/mchange/v2/resourcepool/BasicResourcePool;
      52: invokestatic  #23                 // Method com/mchange/v2/resourcepool/BasicResourcePool.access$700:(Lcom/mchange/v2/resourcepool/BasicResourcePool;)V
      55: goto          67
      58: aload_0
      59: getfield      #3                  // Field this$0:Lcom/mchange/v2/resourcepool/BasicResourcePool;
      62: invokestatic  #24                 // Method com/mchange/v2/resourcepool/BasicResourcePool.access$800:(Lcom/mchange/v2/resourcepool/BasicResourcePool;)V
      65: iconst_1
      66: istore_1
      67: invokestatic  #7                  // Method com/mchange/v2/resourcepool/BasicResourcePool.access$000:()Lcom/mchange/v2/log/MLogger;
      70: getstatic     #8                  // Field com/mchange/v2/log/MLevel.FINEST:Lcom/mchange/v2/log/MLevel;
      73: invokeinterface #9,  2            // InterfaceMethod com/mchange/v2/log/MLogger.isLoggable:(Lcom/mchange/v2/log/MLevel;)Z
      78: ifeq          159
      81: invokestatic  #7                  // Method com/mchange/v2/resourcepool/BasicResourcePool.access$000:()Lcom/mchange/v2/log/MLogger;
      84: new           #10                 // class java/lang/StringBuilder
      87: dup
      88: invokespecial #11                 // Method java/lang/StringBuilder."<init>":()V
      91: ldc           #25                 // String Acquisition series terminated
      93: invokevirtual #13                 // Method java/lang/StringBuilder.append:(Ljava/lang/String;)Ljava/lang/StringBuilder;
      96: iload_3
      97: ifeq          105
     100: ldc           #26                 // String because this resource pool has been close()ed
     102: goto          116
     105: iload_2
     106: ifeq          114
     109: ldc           #27                 // String because force-kill-acquires is pending
     111: goto          116
     114: ldc           #28                 // String successfully
     116: invokevirtual #13                 // Method java/lang/StringBuilder.append:(Ljava/lang/String;)Ljava/lang/StringBuilder;
     119: ldc           #29                 // String . Decremented pending_acquires [
     121: invokevirtual #13                 // Method java/lang/StringBuilder.append:(Ljava/lang/String;)Ljava/lang/StringBuilder;
     124: aload_0
     125: getfield      #3                  // Field this$0:Lcom/mchange/v2/resourcepool/BasicResourcePool;
     128: getfield      #14                 // Field com/mchange/v2/resourcepool/BasicResourcePool.pending_acquires:I
     131: invokevirtual #15                 // Method java/lang/StringBuilder.append:(I)Ljava/lang/StringBuilder;
     134: ldc           #16                 // String ],
     136: invokevirtual #13                 // Method java/lang/StringBuilder.append:(Ljava/lang/String;)Ljava/lang/StringBuilder;
     139: ldc           #17                 // String  attempts_remaining:
     141: invokevirtual #13                 // Method java/lang/StringBuilder.append:(Ljava/lang/String;)Ljava/lang/StringBuilder;
     144: aload_0
     145: getfield      #5                  // Field attempts_remaining:I
     148: invokevirtual #15                 // Method java/lang/StringBuilder.append:(I)Ljava/lang/StringBuilder;
     151: invokevirtual #18                 // Method java/lang/StringBuilder.toString:()Ljava/lang/String;
     154: invokeinterface #19,  2           // InterfaceMethod com/mchange/v2/log/MLogger.finest:(Ljava/lang/String;)V
     159: goto          177
     162: astore        4
     164: getstatic     #31                 // Field java/lang/System.err:Ljava/io/PrintStream;
     167: ldc           #32                 // String Exception during logging:
     169: invokevirtual #33                 // Method java/io/PrintStream.println:(Ljava/lang/String;)V
     172: aload         4
     174: invokevirtual #34                 // Method java/lang/Exception.printStackTrace:()V
     177: iload_1
     178: ifeq          594
     181: aload_0
     182: getfield      #3                  // Field this$0:Lcom/mchange/v2/resourcepool/BasicResourcePool;
     185: invokestatic  #35                 // Method com/mchange/v2/resourcepool/BasicResourcePool.access$1300:(Lcom/mchange/v2/resourcepool/BasicResourcePool;)V
     188: goto          594
     191: astore_2
     192: aload_0
     193: getfield      #3                  // Field this$0:Lcom/mchange/v2/resourcepool/BasicResourcePool;
     196: aload_2
     197: invokestatic  #36                 // Method com/mchange/v2/resourcepool/BasicResourcePool.access$900:(Lcom/mchange/v2/resourcepool/BasicResourcePool;Ljava/lang/Throwable;)V
     200: aload_0
     201: getfield      #5                  // Field attempts_remaining:I
     204: ifne          493
     207: aload_0
     208: getfield      #3                  // Field this$0:Lcom/mchange/v2/resourcepool/BasicResourcePool;
     211: invokestatic  #24                 // Method com/mchange/v2/resourcepool/BasicResourcePool.access$800:(Lcom/mchange/v2/resourcepool/BasicResourcePool;)V
     214: invokestatic  #7                  // Method com/mchange/v2/resourcepool/BasicResourcePool.access$000:()Lcom/mchange/v2/log/MLogger;
     217: getstatic     #37                 // Field com/mchange/v2/log/MLevel.WARNING:Lcom/mchange/v2/log/MLevel;
     220: invokeinterface #9,  2            // InterfaceMethod com/mchange/v2/log/MLogger.isLoggable:(Lcom/mchange/v2/log/MLevel;)Z
     225: ifeq          294
     228: invokestatic  #7                  // Method com/mchange/v2/resourcepool/BasicResourcePool.access$000:()Lcom/mchange/v2/log/MLogger;
     231: getstatic     #37                 // Field com/mchange/v2/log/MLevel.WARNING:Lcom/mchange/v2/log/MLevel;
     234: new           #10                 // class java/lang/StringBuilder
     237: dup
     238: invokespecial #11                 // Method java/lang/StringBuilder."<init>":()V
     241: aload_0
     242: invokevirtual #38                 // Method java/lang/StringBuilder.append:(Ljava/lang/Object;)Ljava/lang/StringBuilder;
     245: ldc           #39                 // String  -- Acquisition Attempt Failed!!! Clearing pending acquires.
     247: invokevirtual #13                 // Method java/lang/StringBuilder.append:(Ljava/lang/String;)Ljava/lang/StringBuilder;
     250: ldc           #40                 // String While trying to acquire a needed new resource, we failed
     252: invokevirtual #13                 // Method java/lang/StringBuilder.append:(Ljava/lang/String;)Ljava/lang/StringBuilder;
     255: ldc           #41                 // String to succeed more than the maximum number of allowed
     257: invokevirtual #13                 // Method java/lang/StringBuilder.append:(Ljava/lang/String;)Ljava/lang/StringBuilder;
     260: ldc           #42                 // String acquisition attempts (
     262: invokevirtual #13                 // Method java/lang/StringBuilder.append:(Ljava/lang/String;)Ljava/lang/StringBuilder;
     265: aload_0
     266: getfield      #3                  // Field this$0:Lcom/mchange/v2/resourcepool/BasicResourcePool;
     269: getfield      #2                  // Field com/mchange/v2/resourcepool/BasicResourcePool.num_acq_attempts:I
     272: invokevirtual #15                 // Method java/lang/StringBuilder.append:(I)Ljava/lang/StringBuilder;
     275: ldc           #43                 // String ).
     277: invokevirtual #13                 // Method java/lang/StringBuilder.append:(Ljava/lang/String;)Ljava/lang/StringBuilder;
     280: ldc           #44                 // String Last acquisition attempt exception:
     282: invokevirtual #13                 // Method java/lang/StringBuilder.append:(Ljava/lang/String;)Ljava/lang/StringBuilder;
     285: invokevirtual #18                 // Method java/lang/StringBuilder.toString:()Ljava/lang/String;
     288: aload_2
     289: invokeinterface #45,  4           // InterfaceMethod com/mchange/v2/log/MLogger.log:(Lcom/mchange/v2/log/MLevel;Ljava/lang/String;Ljava/lang/Throwable;)V
     294: aload_0
     295: getfield      #3                  // Field this$0:Lcom/mchange/v2/resourcepool/BasicResourcePool;
     298: getfield      #46                 // Field com/mchange/v2/resourcepool/BasicResourcePool.break_on_acquisition_failure:Z
     301: ifeq          385
     304: invokestatic  #7                  // Method com/mchange/v2/resourcepool/BasicResourcePool.access$000:()Lcom/mchange/v2/log/MLogger;
     307: getstatic     #47                 // Field com/mchange/v2/log/MLevel.SEVERE:Lcom/mchange/v2/log/MLevel;
     310: invokeinterface #9,  2            // InterfaceMethod com/mchange/v2/log/MLogger.isLoggable:(Lcom/mchange/v2/log/MLevel;)Z
     315: ifeq          375
     318: invokestatic  #7                  // Method com/mchange/v2/resourcepool/BasicResourcePool.access$000:()Lcom/mchange/v2/log/MLogger;
     321: new           #10                 // class java/lang/StringBuilder
     324: dup
     325: invokespecial #11                 // Method java/lang/StringBuilder."<init>":()V
     328: ldc           #48                 // String A RESOURCE POOL IS PERMANENTLY BROKEN! [
     330: invokevirtual #13                 // Method java/lang/StringBuilder.append:(Ljava/lang/String;)Ljava/lang/StringBuilder;
     333: aload_0
     334: invokevirtual #38                 // Method java/lang/StringBuilder.append:(Ljava/lang/Object;)Ljava/lang/StringBuilder;
     337: ldc           #49                 // String ]
     339: invokevirtual #13                 // Method java/lang/StringBuilder.append:(Ljava/lang/String;)Ljava/lang/StringBuilder;
     342: ldc           #50                 // String (because a series of
     344: invokevirtual #13                 // Method java/lang/StringBuilder.append:(Ljava/lang/String;)Ljava/lang/StringBuilder;
     347: aload_0
     348: getfield      #3                  // Field this$0:Lcom/mchange/v2/resourcepool/BasicResourcePool;
     351: getfield      #2                  // Field com/mchange/v2/resourcepool/BasicResourcePool.num_acq_attempts:I
     354: invokevirtual #15                 // Method java/lang/StringBuilder.append:(I)Ljava/lang/StringBuilder;
     357: ldc           #51                 // String  acquisition attempts
     359: invokevirtual #13                 // Method java/lang/StringBuilder.append:(Ljava/lang/String;)Ljava/lang/StringBuilder;
     362: ldc           #52                 // String failed.)
     364: invokevirtual #13                 // Method java/lang/StringBuilder.append:(Ljava/lang/String;)Ljava/lang/StringBuilder;
     367: invokevirtual #18                 // Method java/lang/StringBuilder.toString:()Ljava/lang/String;
     370: invokeinterface #53,  2           // InterfaceMethod com/mchange/v2/log/MLogger.severe:(Ljava/lang/String;)V
     375: aload_0
     376: getfield      #3                  // Field this$0:Lcom/mchange/v2/resourcepool/BasicResourcePool;
     379: invokestatic  #54                 // Method com/mchange/v2/resourcepool/BasicResourcePool.access$1000:(Lcom/mchange/v2/resourcepool/BasicResourcePool;)V
     382: goto          426
     385: aload_0
     386: getfield      #3                  // Field this$0:Lcom/mchange/v2/resourcepool/BasicResourcePool;
     389: invokestatic  #55                 // Method com/mchange/v2/resourcepool/BasicResourcePool.access$1100:(Lcom/mchange/v2/resourcepool/BasicResourcePool;)V
     392: goto          426
     395: astore_3
     396: invokestatic  #7                  // Method com/mchange/v2/resourcepool/BasicResourcePool.access$000:()Lcom/mchange/v2/log/MLogger;
     399: getstatic     #37                 // Field com/mchange/v2/log/MLevel.WARNING:Lcom/mchange/v2/log/MLevel;
     402: invokeinterface #9,  2            // InterfaceMethod com/mchange/v2/log/MLogger.isLoggable:(Lcom/mchange/v2/log/MLevel;)Z
     407: ifeq          424
     410: invokestatic  #7                  // Method com/mchange/v2/resourcepool/BasicResourcePool.access$000:()Lcom/mchange/v2/log/MLogger;
     413: getstatic     #37                 // Field com/mchange/v2/log/MLevel.WARNING:Lcom/mchange/v2/log/MLevel;
     416: ldc           #57                 // String Failed to force-kill pending acquisition attempts after acquisition failue,  due to an InterruptedException!
     418: aload_3
     419: invokeinterface #45,  4           // InterfaceMethod com/mchange/v2/log/MLogger.log:(Lcom/mchange/v2/log/MLevel;Ljava/lang/String;Ljava/lang/Throwable;)V
     424: iconst_1
     425: istore_1
     426: invokestatic  #7                  // Method com/mchange/v2/resourcepool/BasicResourcePool.access$000:()Lcom/mchange/v2/log/MLogger;
     429: getstatic     #8                  // Field com/mchange/v2/log/MLevel.FINEST:Lcom/mchange/v2/log/MLevel;
     432: invokeinterface #9,  2            // InterfaceMethod com/mchange/v2/log/MLogger.isLoggable:(Lcom/mchange/v2/log/MLevel;)Z
     437: ifeq          564
     440: invokestatic  #7                  // Method com/mchange/v2/resourcepool/BasicResourcePool.access$000:()Lcom/mchange/v2/log/MLogger;
     443: new           #10                 // class java/lang/StringBuilder
     446: dup
     447: invokespecial #11                 // Method java/lang/StringBuilder."<init>":()V
     450: ldc           #58                 // String Acquisition series terminated unsuccessfully. Decremented pending_acquires [
     452: invokevirtual #13                 // Method java/lang/StringBuilder.append:(Ljava/lang/String;)Ljava/lang/StringBuilder;
     455: aload_0
     456: getfield      #3                  // Field this$0:Lcom/mchange/v2/resourcepool/BasicResourcePool;
     459: getfield      #14                 // Field com/mchange/v2/resourcepool/BasicResourcePool.pending_acquires:I
     462: invokevirtual #15                 // Method java/lang/StringBuilder.append:(I)Ljava/lang/StringBuilder;
     465: ldc           #16                 // String ],
     467: invokevirtual #13                 // Method java/lang/StringBuilder.append:(Ljava/lang/String;)Ljava/lang/StringBuilder;
     470: ldc           #17                 // String  attempts_remaining:
     472: invokevirtual #13                 // Method java/lang/StringBuilder.append:(Ljava/lang/String;)Ljava/lang/StringBuilder;
     475: aload_0
     476: getfield      #5                  // Field attempts_remaining:I
     479: invokevirtual #15                 // Method java/lang/StringBuilder.append:(I)Ljava/lang/StringBuilder;
     482: invokevirtual #18                 // Method java/lang/StringBuilder.toString:()Ljava/lang/String;
     485: invokeinterface #19,  2           // InterfaceMethod com/mchange/v2/log/MLogger.finest:(Ljava/lang/String;)V
     490: goto          564
     493: aload_0
     494: getfield      #5                  // Field attempts_remaining:I
     497: ifle          506
     500: getstatic     #59                 // Field com/mchange/v2/log/MLevel.FINE:Lcom/mchange/v2/log/MLevel;
     503: goto          509
     506: getstatic     #60                 // Field com/mchange/v2/log/MLevel.INFO:Lcom/mchange/v2/log/MLevel;
     509: astore_3
     510: invokestatic  #7                  // Method com/mchange/v2/resourcepool/BasicResourcePool.access$000:()Lcom/mchange/v2/log/MLogger;
     513: aload_3
     514: invokeinterface #9,  2            // InterfaceMethod com/mchange/v2/log/MLogger.isLoggable:(Lcom/mchange/v2/log/MLevel;)Z
     519: ifeq          534
     522: invokestatic  #7                  // Method com/mchange/v2/resourcepool/BasicResourcePool.access$000:()Lcom/mchange/v2/log/MLogger;
     525: aload_3
     526: ldc           #61                 // String An exception occurred while acquiring a poolable resource. Will retry.
     528: aload_2
     529: invokeinterface #45,  4           // InterfaceMethod com/mchange/v2/log/MLogger.log:(Lcom/mchange/v2/log/MLevel;Ljava/lang/String;Ljava/lang/Throwable;)V
     534: new           #62                 // class com/mchange/v2/resourcepool/BasicResourcePool$ScatteredAcquireTask$1
     537: dup
     538: aload_0
     539: invokespecial #63                 // Method com/mchange/v2/resourcepool/BasicResourcePool$ScatteredAcquireTask$1."<init>":(Lcom/mchange/v2/resourcepool/BasicResourcePool$ScatteredAcquireTask;)V
     542: astore        4
     544: aload_0
     545: getfield      #3                  // Field this$0:Lcom/mchange/v2/resourcepool/BasicResourcePool;
     548: getfield      #64                 // Field com/mchange/v2/resourcepool/BasicResourcePool.cullAndIdleRefurbishTimer:Ljava/util/Timer;
     551: aload         4
     553: aload_0
     554: getfield      #3                  // Field this$0:Lcom/mchange/v2/resourcepool/BasicResourcePool;
     557: getfield      #65                 // Field com/mchange/v2/resourcepool/BasicResourcePool.acq_attempt_delay:I
     560: i2l
     561: invokevirtual #66                 // Method java/util/Timer.schedule:(Ljava/util/TimerTask;J)V
     564: iload_1
     565: ifeq          594
     568: aload_0
     569: getfield      #3                  // Field this$0:Lcom/mchange/v2/resourcepool/BasicResourcePool;
     572: invokestatic  #35                 // Method com/mchange/v2/resourcepool/BasicResourcePool.access$1300:(Lcom/mchange/v2/resourcepool/BasicResourcePool;)V
     575: goto          594
     578: astore        6
     580: iload_1
     581: ifeq          591
     584: aload_0
     585: getfield      #3                  // Field this$0:Lcom/mchange/v2/resourcepool/BasicResourcePool;
     588: invokestatic  #35                 // Method com/mchange/v2/resourcepool/BasicResourcePool.access$1300:(Lcom/mchange/v2/resourcepool/BasicResourcePool;)V
     591: aload         6
     593: athrow
     594: return
    Exception table:
       from    to  target type
          10    29    32   any
          32    37    32   any
          67   159   162   Class java/lang/Exception
           2   177   191   Class java/lang/Exception
         385   392   395   Class java/lang/InterruptedException
           2   177   578   any
         191   564   578   any
         578   580   578   any

  com.mchange.v2.resourcepool.BasicResourcePool$ScatteredAcquireTask(com.mchange.v2.resourcepool.BasicResourcePool, int, boolean, com.mchange.v2.resourcepool.BasicResourcePool$1);
    Code:
       0: aload_0
       1: aload_1
       2: iload_2
       3: iload_3
       4: invokespecial #1                  // Method "<init>":(Lcom/mchange/v2/resourcepool/BasicResourcePool;IZ)V
       7: return
}
