Compiled from "BasicResourcePool.java"
class com.mchange.v2.resourcepool.BasicResourcePool$4 implements java.lang.Runnable {
  final java.lang.Object val$resc;

  final boolean val$checked_out_resource;

  final int val$pool_size;

  final int val$available_size;

  final int val$removed_but_unreturned_size;

  final com.mchange.v2.resourcepool.BasicResourcePool this$0;

  com.mchange.v2.resourcepool.BasicResourcePool$4(com.mchange.v2.resourcepool.BasicResourcePool, java.lang.Object, boolean, int, int, int);
    Code:
       0: aload_0
       1: aload_1
       2: putfield      #1                  // Field this$0:Lcom/mchange/v2/resourcepool/BasicResourcePool;
       5: aload_0
       6: aload_2
       7: putfield      #2                  // Field val$resc:Ljava/lang/Object;
      10: aload_0
      11: iload_3
      12: putfield      #3                  // Field val$checked_out_resource:Z
      15: aload_0
      16: iload         4
      18: putfield      #4                  // Field val$pool_size:I
      21: aload_0
      22: iload         5
      24: putfield      #5                  // Field val$available_size:I
      27: aload_0
      28: iload         6
      30: putfield      #6                  // Field val$removed_but_unreturned_size:I
      33: aload_0
      34: invokespecial #7                  // Method java/lang/Object."<init>":()V
      37: return

  public void run();
    Code:
       0: aload_0
       1: getfield      #1                  // Field this$0:Lcom/mchange/v2/resourcepool/BasicResourcePool;
       4: getfield      #8                  // Field com/mchange/v2/resourcepool/BasicResourcePool.rpes:Lcom/mchange/v2/resourcepool/ResourcePoolEventSupport;
       7: aload_0
       8: getfield      #2                  // Field val$resc:Ljava/lang/Object;
      11: aload_0
      12: getfield      #3                  // Field val$checked_out_resource:Z
      15: aload_0
      16: getfield      #4                  // Field val$pool_size:I
      19: aload_0
      20: getfield      #5                  // Field val$available_size:I
      23: aload_0
      24: getfield      #6                  // Field val$removed_but_unreturned_size:I
      27: invokevirtual #9                  // Method com/mchange/v2/resourcepool/ResourcePoolEventSupport.fireResourceRemoved:(Ljava/lang/Object;ZIII)V
      30: return
}
