Compiled from "BasicResourcePool.java"
class com.mchange.v2.resourcepool.BasicResourcePool$CheckIdleResourcesTask extends java.util.TimerTask {
  final com.mchange.v2.resourcepool.BasicResourcePool this$0;

  com.mchange.v2.resourcepool.BasicResourcePool$CheckIdleResourcesTask(com.mchange.v2.resourcepool.BasicResourcePool);
    Code:
       0: aload_0
       1: aload_1
       2: putfield      #2                  // Field this$0:Lcom/mchange/v2/resourcepool/BasicResourcePool;
       5: aload_0
       6: invokespecial #3                  // Method java/util/TimerTask."<init>":()V
       9: return

  public void run();
    Code:
       0: invokestatic  #4                  // Method com/mchange/v2/resourcepool/BasicResourcePool.access$000:()Lcom/mchange/v2/log/MLogger;
       3: getstatic     #5                  // Field com/mchange/v2/log/MLevel.FINER:Lcom/mchange/v2/log/MLevel;
       6: invokeinterface #6,  2            // InterfaceMethod com/mchange/v2/log/MLogger.isLoggable:(Lcom/mchange/v2/log/MLevel;)Z
      11: ifeq          67
      14: invokestatic  #4                  // Method com/mchange/v2/resourcepool/BasicResourcePool.access$000:()Lcom/mchange/v2/log/MLogger;
      17: getstatic     #5                  // Field com/mchange/v2/log/MLevel.FINER:Lcom/mchange/v2/log/MLevel;
      20: new           #7                  // class java/lang/StringBuilder
      23: dup
      24: invokespecial #8                  // Method java/lang/StringBuilder."<init>":()V
      27: ldc           #9                  // String Refurbishing idle resources -
      29: invokevirtual #10                 // Method java/lang/StringBuilder.append:(Ljava/lang/String;)Ljava/lang/StringBuilder;
      32: new           #11                 // class java/util/Date
      35: dup
      36: invokespecial #12                 // Method java/util/Date."<init>":()V
      39: invokevirtual #13                 // Method java/lang/StringBuilder.append:(Ljava/lang/Object;)Ljava/lang/StringBuilder;
      42: ldc           #14                 // String  [
      44: invokevirtual #10                 // Method java/lang/StringBuilder.append:(Ljava/lang/String;)Ljava/lang/StringBuilder;
      47: aload_0
      48: getfield      #2                  // Field this$0:Lcom/mchange/v2/resourcepool/BasicResourcePool;
      51: invokevirtual #13                 // Method java/lang/StringBuilder.append:(Ljava/lang/Object;)Ljava/lang/StringBuilder;
      54: ldc           #15                 // String ]
      56: invokevirtual #10                 // Method java/lang/StringBuilder.append:(Ljava/lang/String;)Ljava/lang/StringBuilder;
      59: invokevirtual #16                 // Method java/lang/StringBuilder.toString:()Ljava/lang/String;
      62: invokeinterface #17,  3           // InterfaceMethod com/mchange/v2/log/MLogger.log:(Lcom/mchange/v2/log/MLevel;Ljava/lang/String;)V
      67: aload_0
      68: getfield      #2                  // Field this$0:Lcom/mchange/v2/resourcepool/BasicResourcePool;
      71: dup
      72: astore_1
      73: monitorenter
      74: aload_0
      75: getfield      #2                  // Field this$0:Lcom/mchange/v2/resourcepool/BasicResourcePool;
      78: invokestatic  #18                 // Method com/mchange/v2/resourcepool/BasicResourcePool.access$2000:(Lcom/mchange/v2/resourcepool/BasicResourcePool;)V
      81: aload_1
      82: monitorexit
      83: goto          91
      86: astore_2
      87: aload_1
      88: monitorexit
      89: aload_2
      90: athrow
      91: goto          130
      94: astore_1
      95: invokestatic  #4                  // Method com/mchange/v2/resourcepool/BasicResourcePool.access$000:()Lcom/mchange/v2/log/MLogger;
      98: getstatic     #20                 // Field com/mchange/v2/log/MLevel.FINE:Lcom/mchange/v2/log/MLevel;
     101: invokeinterface #6,  2            // InterfaceMethod com/mchange/v2/log/MLogger.isLoggable:(Lcom/mchange/v2/log/MLevel;)Z
     106: ifeq          123
     109: invokestatic  #4                  // Method com/mchange/v2/resourcepool/BasicResourcePool.access$000:()Lcom/mchange/v2/log/MLogger;
     112: getstatic     #20                 // Field com/mchange/v2/log/MLevel.FINE:Lcom/mchange/v2/log/MLevel;
     115: ldc           #21                 // String a resource pool async thread died.
     117: aload_1
     118: invokeinterface #22,  4           // InterfaceMethod com/mchange/v2/log/MLogger.log:(Lcom/mchange/v2/log/MLevel;Ljava/lang/String;Ljava/lang/Throwable;)V
     123: aload_0
     124: getfield      #2                  // Field this$0:Lcom/mchange/v2/resourcepool/BasicResourcePool;
     127: invokestatic  #23                 // Method com/mchange/v2/resourcepool/BasicResourcePool.access$1000:(Lcom/mchange/v2/resourcepool/BasicResourcePool;)V
     130: return
    Exception table:
       from    to  target type
          74    83    86   any
          86    89    86   any
           0    91    94   Class com/mchange/v2/util/ResourceClosedException
}
