public class org.bouncycastle.pqc.crypto.lms.LMSKeyGenerationParameters extends org.bouncycastle.crypto.KeyGenerationParameters {
  private final org.bouncycastle.pqc.crypto.lms.LMSParameters lmsParameters;

  public org.bouncycastle.pqc.crypto.lms.LMSKeyGenerationParameters(org.bouncycastle.pqc.crypto.lms.LMSParameters, java.security.SecureRandom);
    Code:
       0: aload_0
       1: aload_2
       2: aload_1
       3: invokestatic  #21                 // Method org/bouncycastle/pqc/crypto/lms/LmsUtils.calculateStrength:(Lorg/bouncycastle/pqc/crypto/lms/LMSParameters;)I
       6: invokespecial #20                 // Method org/bouncycastle/crypto/KeyGenerationParameters."<init>":(Ljava/security/SecureRandom;I)V
       9: aload_0
      10: aload_1
      11: putfield      #19                 // Field lmsParameters:Lorg/bouncycastle/pqc/crypto/lms/LMSParameters;
      14: return

  public org.bouncycastle.pqc.crypto.lms.LMSParameters getParameters();
    Code:
       0: aload_0
       1: getfield      #19                 // Field lmsParameters:Lorg/bouncycastle/pqc/crypto/lms/LMSParameters;
       4: areturn
}
