Compiled from "PCSSNSccpStackImplTest.java"
public class org.mobicents.protocols.ss7.sccp.impl.translation.PCSSNSccpStackImplTest extends org.mobicents.protocols.ss7.sccp.impl.SccpHarness {
  private org.mobicents.protocols.ss7.sccp.parameter.SccpAddress a1;

  private org.mobicents.protocols.ss7.sccp.parameter.SccpAddress a2;

  public org.mobicents.protocols.ss7.sccp.impl.translation.PCSSNSccpStackImplTest();
    Code:
       0: aload_0
       1: invokespecial #1                  // Method org/mobicents/protocols/ss7/sccp/impl/SccpHarness."<init>":()V
       4: return

  public void setUpClass() throws java.lang.Exception;
    Code:
       0: aload_0
       1: ldc           #2                  // String PCSSNSccTestSccpStack1
       3: putfield      #3                  // Field sccpStack1Name:Ljava/lang/String;
       6: aload_0
       7: ldc           #4                  // String PCSSNSccTestSccpStack2
       9: putfield      #5                  // Field sccpStack2Name:Ljava/lang/String;
      12: return

  public void tearDownClass() throws java.lang.Exception;
    Code:
       0: return

  public void setUp() throws java.lang.Exception;
    Code:
       0: aload_0
       1: invokespecial #6                  // Method org/mobicents/protocols/ss7/sccp/impl/SccpHarness.setUp:()V
       4: return

  public void tearDown();
    Code:
       0: aload_0
       1: invokespecial #7                  // Method org/mobicents/protocols/ss7/sccp/impl/SccpHarness.tearDown:()V
       4: return

  public void testRemoteRoutingBasedOnSsn() throws java.lang.Exception;
    Code:
       0: aload_0
       1: aload_0
       2: getfield      #8                  // Field org/mobicents/protocols/ss7/sccp/impl/SccpHarness.sccpProvider1:Lorg/mobicents/protocols/ss7/sccp/SccpProvider;
       5: invokeinterface #9,  1            // InterfaceMethod org/mobicents/protocols/ss7/sccp/SccpProvider.getParameterFactory:()Lorg/mobicents/protocols/ss7/sccp/parameter/ParameterFactory;
      10: getstatic     #10                 // Field org/mobicents/protocols/ss7/indicator/RoutingIndicator.ROUTING_BASED_ON_DPC_AND_SSN:Lorg/mobicents/protocols/ss7/indicator/RoutingIndicator;
      13: aconst_null
      14: iconst_1
      15: bipush        8
      17: invokeinterface #11,  5           // InterfaceMethod org/mobicents/protocols/ss7/sccp/parameter/ParameterFactory.createSccpAddress:(Lorg/mobicents/protocols/ss7/indicator/RoutingIndicator;Lorg/mobicents/protocols/ss7/sccp/parameter/GlobalTitle;II)Lorg/mobicents/protocols/ss7/sccp/parameter/SccpAddress;
      22: putfield      #12                 // Field a1:Lorg/mobicents/protocols/ss7/sccp/parameter/SccpAddress;
      25: aload_0
      26: aload_0
      27: getfield      #8                  // Field org/mobicents/protocols/ss7/sccp/impl/SccpHarness.sccpProvider1:Lorg/mobicents/protocols/ss7/sccp/SccpProvider;
      30: invokeinterface #9,  1            // InterfaceMethod org/mobicents/protocols/ss7/sccp/SccpProvider.getParameterFactory:()Lorg/mobicents/protocols/ss7/sccp/parameter/ParameterFactory;
      35: getstatic     #10                 // Field org/mobicents/protocols/ss7/indicator/RoutingIndicator.ROUTING_BASED_ON_DPC_AND_SSN:Lorg/mobicents/protocols/ss7/indicator/RoutingIndicator;
      38: aconst_null
      39: iconst_2
      40: bipush        8
      42: invokeinterface #11,  5           // InterfaceMethod org/mobicents/protocols/ss7/sccp/parameter/ParameterFactory.createSccpAddress:(Lorg/mobicents/protocols/ss7/indicator/RoutingIndicator;Lorg/mobicents/protocols/ss7/sccp/parameter/GlobalTitle;II)Lorg/mobicents/protocols/ss7/sccp/parameter/SccpAddress;
      47: putfield      #13                 // Field a2:Lorg/mobicents/protocols/ss7/sccp/parameter/SccpAddress;
      50: new           #14                 // class org/mobicents/protocols/ss7/sccp/impl/User
      53: dup
      54: aload_0
      55: getfield      #15                 // Field sccpStack1:Lorg/mobicents/protocols/ss7/sccp/impl/SccpStackImpl;
      58: invokevirtual #16                 // Method org/mobicents/protocols/ss7/sccp/impl/SccpStackImpl.getSccpProvider:()Lorg/mobicents/protocols/ss7/sccp/SccpProvider;
      61: aload_0
      62: getfield      #12                 // Field a1:Lorg/mobicents/protocols/ss7/sccp/parameter/SccpAddress;
      65: aload_0
      66: getfield      #13                 // Field a2:Lorg/mobicents/protocols/ss7/sccp/parameter/SccpAddress;
      69: aload_0
      70: invokevirtual #17                 // Method getSSN:()I
      73: invokespecial #18                 // Method org/mobicents/protocols/ss7/sccp/impl/User."<init>":(Lorg/mobicents/protocols/ss7/sccp/SccpProvider;Lorg/mobicents/protocols/ss7/sccp/parameter/SccpAddress;Lorg/mobicents/protocols/ss7/sccp/parameter/SccpAddress;I)V
      76: astore_1
      77: new           #14                 // class org/mobicents/protocols/ss7/sccp/impl/User
      80: dup
      81: aload_0
      82: getfield      #19                 // Field sccpStack2:Lorg/mobicents/protocols/ss7/sccp/impl/SccpStackImpl;
      85: invokevirtual #16                 // Method org/mobicents/protocols/ss7/sccp/impl/SccpStackImpl.getSccpProvider:()Lorg/mobicents/protocols/ss7/sccp/SccpProvider;
      88: aload_0
      89: getfield      #13                 // Field a2:Lorg/mobicents/protocols/ss7/sccp/parameter/SccpAddress;
      92: aload_0
      93: getfield      #12                 // Field a1:Lorg/mobicents/protocols/ss7/sccp/parameter/SccpAddress;
      96: aload_0
      97: invokevirtual #17                 // Method getSSN:()I
     100: invokespecial #18                 // Method org/mobicents/protocols/ss7/sccp/impl/User."<init>":(Lorg/mobicents/protocols/ss7/sccp/SccpProvider;Lorg/mobicents/protocols/ss7/sccp/parameter/SccpAddress;Lorg/mobicents/protocols/ss7/sccp/parameter/SccpAddress;I)V
     103: astore_2
     104: aload_1
     105: invokevirtual #20                 // Method org/mobicents/protocols/ss7/sccp/impl/User.register:()V
     108: aload_2
     109: invokevirtual #20                 // Method org/mobicents/protocols/ss7/sccp/impl/User.register:()V
     112: aload_1
     113: invokevirtual #21                 // Method org/mobicents/protocols/ss7/sccp/impl/User.send:()V
     116: aload_2
     117: invokevirtual #21                 // Method org/mobicents/protocols/ss7/sccp/impl/User.send:()V
     120: invokestatic  #22                 // Method java/lang/Thread.currentThread:()Ljava/lang/Thread;
     123: pop
     124: ldc2_w        #23                 // long 3000l
     127: invokestatic  #25                 // Method java/lang/Thread.sleep:(J)V
     130: aload_1
     131: invokevirtual #26                 // Method org/mobicents/protocols/ss7/sccp/impl/User.check:()Z
     134: ldc           #27                 // String Message not received
     136: invokestatic  #28                 // Method org/testng/Assert.assertTrue:(ZLjava/lang/String;)V
     139: aload_2
     140: invokevirtual #26                 // Method org/mobicents/protocols/ss7/sccp/impl/User.check:()Z
     143: ldc           #27                 // String Message not received
     145: invokestatic  #28                 // Method org/testng/Assert.assertTrue:(ZLjava/lang/String;)V
     148: return
}
