Compiled from "RDFXMLParser.java"
public class org.apache.jena.rdfxml.xmlinput.impl.RDFXMLParser$SAXParserWithEncodingCheck extends org.apache.xerces.parsers.SAXParser {
  private org.apache.jena.rdfxml.xmlinput.impl.RDFXMLParser rdfXmlParser;

  protected org.apache.jena.rdfxml.xmlinput.impl.RDFXMLParser$SAXParserWithEncodingCheck(org.apache.xerces.parsers.StandardParserConfiguration);
    Code:
       0: aload_0
       1: aload_1
       2: invokespecial #1                  // Method org/apache/xerces/parsers/SAXParser."<init>":(Lorg/apache/xerces/xni/parser/XMLParserConfiguration;)V
       5: return

  public void xmlDecl(java.lang.String, java.lang.String, java.lang.String, org.apache.xerces.xni.Augmentations);
    Code:
       0: aload_0
       1: invokevirtual #2                  // Method getRdfXmlParser:()Lorg/apache/jena/rdfxml/xmlinput/impl/RDFXMLParser;
       4: aload_2
       5: ifnonnull     13
       8: ldc           #3                  // String UTF
      10: goto          14
      13: aload_2
      14: invokevirtual #4                  // Method org/apache/jena/rdfxml/xmlinput/impl/RDFXMLParser.setEncoding:(Ljava/lang/String;)V
      17: goto          32
      20: astore        5
      22: new           #6                  // class org/apache/jena/rdfxml/xmlinput/impl/WrappedException
      25: dup
      26: aload         5
      28: invokespecial #7                  // Method org/apache/jena/rdfxml/xmlinput/impl/WrappedException."<init>":(Lorg/xml/sax/SAXException;)V
      31: athrow
      32: aload_0
      33: aload_1
      34: aload_2
      35: aload_3
      36: aload         4
      38: invokespecial #8                  // Method org/apache/xerces/parsers/SAXParser.xmlDecl:(Ljava/lang/String;Ljava/lang/String;Ljava/lang/String;Lorg/apache/xerces/xni/Augmentations;)V
      41: return
    Exception table:
       from    to  target type
           0    17    20   Class org/xml/sax/SAXParseException

  public void setRdfXmlParser(org.apache.jena.rdfxml.xmlinput.impl.RDFXMLParser);
    Code:
       0: aload_0
       1: aload_1
       2: putfield      #9                  // Field rdfXmlParser:Lorg/apache/jena/rdfxml/xmlinput/impl/RDFXMLParser;
       5: return

  public org.apache.jena.rdfxml.xmlinput.impl.RDFXMLParser getRdfXmlParser();
    Code:
       0: aload_0
       1: getfield      #9                  // Field rdfXmlParser:Lorg/apache/jena/rdfxml/xmlinput/impl/RDFXMLParser;
       4: ifnonnull     17
       7: new           #10                 // class java/lang/IllegalStateException
      10: dup
      11: ldc           #11                 // String setRdfXmlParser must be called as part of the initialization process
      13: invokespecial #12                 // Method java/lang/IllegalStateException."<init>":(Ljava/lang/String;)V
      16: athrow
      17: aload_0
      18: getfield      #9                  // Field rdfXmlParser:Lorg/apache/jena/rdfxml/xmlinput/impl/RDFXMLParser;
      21: areturn
}
