Compiled from "Method.java"
public final class org.apache.hc.core5.http.Method extends java.lang.Enum<org.apache.hc.core5.http.Method> {
  public static final org.apache.hc.core5.http.Method GET;

  public static final org.apache.hc.core5.http.Method HEAD;

  public static final org.apache.hc.core5.http.Method POST;

  public static final org.apache.hc.core5.http.Method PUT;

  public static final org.apache.hc.core5.http.Method DELETE;

  public static final org.apache.hc.core5.http.Method CONNECT;

  public static final org.apache.hc.core5.http.Method TRACE;

  public static final org.apache.hc.core5.http.Method OPTIONS;

  public static final org.apache.hc.core5.http.Method PATCH;

  private final boolean safe;

  private final boolean idempotent;

  private static final org.apache.hc.core5.http.Method[] $VALUES;

  public static org.apache.hc.core5.http.Method[] values();
    Code:
       0: getstatic     #1                  // Field $VALUES:[Lorg/apache/hc/core5/http/Method;
       3: invokevirtual #2                  // Method "[Lorg/apache/hc/core5/http/Method;".clone:()Ljava/lang/Object;
       6: checkcast     #3                  // class "[Lorg/apache/hc/core5/http/Method;"
       9: areturn

  public static org.apache.hc.core5.http.Method valueOf(java.lang.String);
    Code:
       0: ldc_w         #4                  // class org/apache/hc/core5/http/Method
       3: aload_0
       4: invokestatic  #5                  // Method java/lang/Enum.valueOf:(Ljava/lang/Class;Ljava/lang/String;)Ljava/lang/Enum;
       7: checkcast     #4                  // class org/apache/hc/core5/http/Method
      10: areturn

  private org.apache.hc.core5.http.Method(boolean, boolean);
    Code:
       0: aload_0
       1: aload_1
       2: iload_2
       3: invokespecial #6                  // Method java/lang/Enum."<init>":(Ljava/lang/String;I)V
       6: aload_0
       7: iload_3
       8: putfield      #7                  // Field safe:Z
      11: aload_0
      12: iload         4
      14: putfield      #8                  // Field idempotent:Z
      17: return

  public boolean isSafe();
    Code:
       0: aload_0
       1: getfield      #7                  // Field safe:Z
       4: ireturn

  public boolean isIdempotent();
    Code:
       0: aload_0
       1: getfield      #8                  // Field idempotent:Z
       4: ireturn

  public static boolean isSafe(java.lang.String);
    Code:
       0: aload_0
       1: ifnonnull     6
       4: iconst_0
       5: ireturn
       6: aload_0
       7: invokestatic  #9                  // Method normalizedValueOf:(Ljava/lang/String;)Lorg/apache/hc/core5/http/Method;
      10: getfield      #7                  // Field safe:Z
      13: ireturn
      14: astore_1
      15: iconst_0
      16: ireturn
    Exception table:
       from    to  target type
           6    13    14   Class java/lang/IllegalArgumentException

  public static boolean isIdempotent(java.lang.String);
    Code:
       0: aload_0
       1: ifnonnull     6
       4: iconst_0
       5: ireturn
       6: aload_0
       7: invokestatic  #9                  // Method normalizedValueOf:(Ljava/lang/String;)Lorg/apache/hc/core5/http/Method;
      10: getfield      #8                  // Field idempotent:Z
      13: ireturn
      14: astore_1
      15: iconst_0
      16: ireturn
    Exception table:
       from    to  target type
           6    13    14   Class java/lang/IllegalArgumentException

  public static org.apache.hc.core5.http.Method normalizedValueOf(java.lang.String);
    Code:
       0: aload_0
       1: ldc           #11                 // String method
       3: invokestatic  #12                 // Method org/apache/hc/core5/util/Args.notNull:(Ljava/lang/Object;Ljava/lang/String;)Ljava/lang/Object;
       6: checkcast     #13                 // class java/lang/String
       9: getstatic     #14                 // Field java/util/Locale.ROOT:Ljava/util/Locale;
      12: invokevirtual #15                 // Method java/lang/String.toUpperCase:(Ljava/util/Locale;)Ljava/lang/String;
      15: invokestatic  #16                 // Method valueOf:(Ljava/lang/String;)Lorg/apache/hc/core5/http/Method;
      18: areturn

  public boolean isSame(java.lang.String);
    Code:
       0: aload_1
       1: ifnonnull     6
       4: iconst_0
       5: ireturn
       6: aload_0
       7: invokevirtual #17                 // Method name:()Ljava/lang/String;
      10: aload_1
      11: invokevirtual #18                 // Method java/lang/String.equalsIgnoreCase:(Ljava/lang/String;)Z
      14: ireturn

  static {};
    Code:
       0: new           #4                  // class org/apache/hc/core5/http/Method
       3: dup
       4: ldc           #19                 // String GET
       6: iconst_0
       7: iconst_1
       8: iconst_1
       9: invokespecial #20                 // Method "<init>":(Ljava/lang/String;IZZ)V
      12: putstatic     #21                 // Field GET:Lorg/apache/hc/core5/http/Method;
      15: new           #4                  // class org/apache/hc/core5/http/Method
      18: dup
      19: ldc           #22                 // String HEAD
      21: iconst_1
      22: iconst_1
      23: iconst_1
      24: invokespecial #20                 // Method "<init>":(Ljava/lang/String;IZZ)V
      27: putstatic     #23                 // Field HEAD:Lorg/apache/hc/core5/http/Method;
      30: new           #4                  // class org/apache/hc/core5/http/Method
      33: dup
      34: ldc           #24                 // String POST
      36: iconst_2
      37: iconst_0
      38: iconst_0
      39: invokespecial #20                 // Method "<init>":(Ljava/lang/String;IZZ)V
      42: putstatic     #25                 // Field POST:Lorg/apache/hc/core5/http/Method;
      45: new           #4                  // class org/apache/hc/core5/http/Method
      48: dup
      49: ldc           #26                 // String PUT
      51: iconst_3
      52: iconst_0
      53: iconst_1
      54: invokespecial #20                 // Method "<init>":(Ljava/lang/String;IZZ)V
      57: putstatic     #27                 // Field PUT:Lorg/apache/hc/core5/http/Method;
      60: new           #4                  // class org/apache/hc/core5/http/Method
      63: dup
      64: ldc           #28                 // String DELETE
      66: iconst_4
      67: iconst_0
      68: iconst_1
      69: invokespecial #20                 // Method "<init>":(Ljava/lang/String;IZZ)V
      72: putstatic     #29                 // Field DELETE:Lorg/apache/hc/core5/http/Method;
      75: new           #4                  // class org/apache/hc/core5/http/Method
      78: dup
      79: ldc           #30                 // String CONNECT
      81: iconst_5
      82: iconst_0
      83: iconst_0
      84: invokespecial #20                 // Method "<init>":(Ljava/lang/String;IZZ)V
      87: putstatic     #31                 // Field CONNECT:Lorg/apache/hc/core5/http/Method;
      90: new           #4                  // class org/apache/hc/core5/http/Method
      93: dup
      94: ldc           #32                 // String TRACE
      96: bipush        6
      98: iconst_1
      99: iconst_1
     100: invokespecial #20                 // Method "<init>":(Ljava/lang/String;IZZ)V
     103: putstatic     #33                 // Field TRACE:Lorg/apache/hc/core5/http/Method;
     106: new           #4                  // class org/apache/hc/core5/http/Method
     109: dup
     110: ldc           #34                 // String OPTIONS
     112: bipush        7
     114: iconst_1
     115: iconst_1
     116: invokespecial #20                 // Method "<init>":(Ljava/lang/String;IZZ)V
     119: putstatic     #35                 // Field OPTIONS:Lorg/apache/hc/core5/http/Method;
     122: new           #4                  // class org/apache/hc/core5/http/Method
     125: dup
     126: ldc           #36                 // String PATCH
     128: bipush        8
     130: iconst_0
     131: iconst_0
     132: invokespecial #20                 // Method "<init>":(Ljava/lang/String;IZZ)V
     135: putstatic     #37                 // Field PATCH:Lorg/apache/hc/core5/http/Method;
     138: bipush        9
     140: anewarray     #4                  // class org/apache/hc/core5/http/Method
     143: dup
     144: iconst_0
     145: getstatic     #21                 // Field GET:Lorg/apache/hc/core5/http/Method;
     148: aastore
     149: dup
     150: iconst_1
     151: getstatic     #23                 // Field HEAD:Lorg/apache/hc/core5/http/Method;
     154: aastore
     155: dup
     156: iconst_2
     157: getstatic     #25                 // Field POST:Lorg/apache/hc/core5/http/Method;
     160: aastore
     161: dup
     162: iconst_3
     163: getstatic     #27                 // Field PUT:Lorg/apache/hc/core5/http/Method;
     166: aastore
     167: dup
     168: iconst_4
     169: getstatic     #29                 // Field DELETE:Lorg/apache/hc/core5/http/Method;
     172: aastore
     173: dup
     174: iconst_5
     175: getstatic     #31                 // Field CONNECT:Lorg/apache/hc/core5/http/Method;
     178: aastore
     179: dup
     180: bipush        6
     182: getstatic     #33                 // Field TRACE:Lorg/apache/hc/core5/http/Method;
     185: aastore
     186: dup
     187: bipush        7
     189: getstatic     #35                 // Field OPTIONS:Lorg/apache/hc/core5/http/Method;
     192: aastore
     193: dup
     194: bipush        8
     196: getstatic     #37                 // Field PATCH:Lorg/apache/hc/core5/http/Method;
     199: aastore
     200: putstatic     #1                  // Field $VALUES:[Lorg/apache/hc/core5/http/Method;
     203: return
}
