Compiled from "ProtocolException.java"
public class org.apache.hc.core5.http.ProtocolException extends org.apache.hc.core5.http.HttpException {
  private static final long serialVersionUID;

  public org.apache.hc.core5.http.ProtocolException();
    Code:
       0: aload_0
       1: invokespecial #1                  // Method org/apache/hc/core5/http/HttpException."<init>":()V
       4: return

  public org.apache.hc.core5.http.ProtocolException(java.lang.String);
    Code:
       0: aload_0
       1: aload_1
       2: invokespecial #2                  // Method org/apache/hc/core5/http/HttpException."<init>":(Ljava/lang/String;)V
       5: return

  public org.apache.hc.core5.http.ProtocolException(java.lang.String, java.lang.Object...);
    Code:
       0: aload_0
       1: aload_1
       2: aload_2
       3: invokespecial #3                  // Method org/apache/hc/core5/http/HttpException."<init>":(Ljava/lang/String;[Ljava/lang/Object;)V
       6: return

  public org.apache.hc.core5.http.ProtocolException(java.lang.String, java.lang.Throwable);
    Code:
       0: aload_0
       1: aload_1
       2: aload_2
       3: invokespecial #4                  // Method org/apache/hc/core5/http/HttpException."<init>":(Ljava/lang/String;Ljava/lang/Throwable;)V
       6: return
}
