Compiled from "Stax2DOM.java"
public class org.apache.cxf.tools.validator.internal.Stax2DOM {
  static final java.lang.String XML_NS;

  public org.apache.cxf.tools.validator.internal.Stax2DOM();
    Code:
       0: aload_0
       1: invokespecial #1                  // Method java/lang/Object."<init>":()V
       4: return

  public org.w3c.dom.Document getDocument(java.lang.String) throws org.apache.cxf.tools.common.ToolException;
    Code:
       0: new           #2                  // class java/net/URI
       3: dup
       4: aload_1
       5: invokestatic  #3                  // Method org/apache/cxf/common/util/URIParserUtil.getAbsoluteURI:(Ljava/lang/String;)Ljava/lang/String;
       8: invokespecial #4                  // Method java/net/URI."<init>":(Ljava/lang/String;)V
      11: astore_2
      12: aload_2
      13: invokevirtual #5                  // Method java/net/URI.toString:()Ljava/lang/String;
      16: ldc           #6                  // String http
      18: invokevirtual #7                  // Method java/lang/String.startsWith:(Ljava/lang/String;)Z
      21: ifeq          33
      24: aload_0
      25: aload_2
      26: invokevirtual #8                  // Method java/net/URI.toURL:()Ljava/net/URL;
      29: invokevirtual #9                  // Method getDocument:(Ljava/net/URL;)Lorg/w3c/dom/Document;
      32: areturn
      33: aload_0
      34: aload_2
      35: invokevirtual #8                  // Method java/net/URI.toURL:()Ljava/net/URL;
      38: invokevirtual #9                  // Method getDocument:(Ljava/net/URL;)Lorg/w3c/dom/Document;
      41: areturn
      42: astore_2
      43: aload_2
      44: athrow
      45: astore_2
      46: new           #10                 // class org/apache/cxf/tools/common/ToolException
      49: dup
      50: aload_2
      51: invokespecial #12                 // Method org/apache/cxf/tools/common/ToolException."<init>":(Ljava/lang/Throwable;)V
      54: athrow
    Exception table:
       from    to  target type
           0    32    42   Class org/apache/cxf/tools/common/ToolException
          33    41    42   Class org/apache/cxf/tools/common/ToolException
           0    32    45   Class java/lang/Exception
          33    41    45   Class java/lang/Exception

  public org.w3c.dom.Document getDocument(java.net.URL) throws org.apache.cxf.tools.common.ToolException;
    Code:
       0: aconst_null
       1: astore_2
       2: aload_1
       3: invokevirtual #13                 // Method java/net/URL.openStream:()Ljava/io/InputStream;
       6: astore_3
       7: aconst_null
       8: astore        4
      10: new           #14                 // class javax/xml/transform/stream/StreamSource
      13: dup
      14: aload_3
      15: aload_1
      16: invokevirtual #15                 // Method java/net/URL.toExternalForm:()Ljava/lang/String;
      19: invokespecial #16                 // Method javax/xml/transform/stream/StreamSource."<init>":(Ljava/io/InputStream;Ljava/lang/String;)V
      22: astore        5
      24: aload         5
      26: invokestatic  #17                 // Method org/apache/cxf/staxutils/StaxUtils.createXMLStreamReader:(Ljavax/xml/transform/Source;)Ljavax/xml/stream/XMLStreamReader;
      29: astore_2
      30: aload_2
      31: iconst_1
      32: invokestatic  #18                 // Method org/apache/cxf/staxutils/StaxUtils.read:(Ljavax/xml/stream/XMLStreamReader;Z)Lorg/w3c/dom/Document;
      35: astore        6
      37: aload_3
      38: ifnull        69
      41: aload         4
      43: ifnull        65
      46: aload_3
      47: invokevirtual #19                 // Method java/io/InputStream.close:()V
      50: goto          69
      53: astore        7
      55: aload         4
      57: aload         7
      59: invokevirtual #21                 // Method java/lang/Throwable.addSuppressed:(Ljava/lang/Throwable;)V
      62: goto          69
      65: aload_3
      66: invokevirtual #19                 // Method java/io/InputStream.close:()V
      69: aload_2
      70: invokestatic  #22                 // Method org/apache/cxf/staxutils/StaxUtils.close:(Ljavax/xml/stream/XMLStreamReader;)V
      73: goto          88
      76: astore        7
      78: new           #10                 // class org/apache/cxf/tools/common/ToolException
      81: dup
      82: aload         7
      84: invokespecial #12                 // Method org/apache/cxf/tools/common/ToolException."<init>":(Ljava/lang/Throwable;)V
      87: athrow
      88: aload         6
      90: areturn
      91: astore        5
      93: aload         5
      95: astore        4
      97: aload         5
      99: athrow
     100: astore        8
     102: aload_3
     103: ifnull        134
     106: aload         4
     108: ifnull        130
     111: aload_3
     112: invokevirtual #19                 // Method java/io/InputStream.close:()V
     115: goto          134
     118: astore        9
     120: aload         4
     122: aload         9
     124: invokevirtual #21                 // Method java/lang/Throwable.addSuppressed:(Ljava/lang/Throwable;)V
     127: goto          134
     130: aload_3
     131: invokevirtual #19                 // Method java/io/InputStream.close:()V
     134: aload         8
     136: athrow
     137: astore_3
     138: new           #10                 // class org/apache/cxf/tools/common/ToolException
     141: dup
     142: aload_3
     143: invokespecial #12                 // Method org/apache/cxf/tools/common/ToolException."<init>":(Ljava/lang/Throwable;)V
     146: athrow
     147: astore        10
     149: aload_2
     150: invokestatic  #22                 // Method org/apache/cxf/staxutils/StaxUtils.close:(Ljavax/xml/stream/XMLStreamReader;)V
     153: goto          168
     156: astore        11
     158: new           #10                 // class org/apache/cxf/tools/common/ToolException
     161: dup
     162: aload         11
     164: invokespecial #12                 // Method org/apache/cxf/tools/common/ToolException."<init>":(Ljava/lang/Throwable;)V
     167: athrow
     168: aload         10
     170: athrow
    Exception table:
       from    to  target type
          46    50    53   Class java/lang/Throwable
          69    73    76   Class javax/xml/stream/XMLStreamException
          10    37    91   Class java/lang/Throwable
          10    37   100   any
         111   115   118   Class java/lang/Throwable
          91   102   100   any
           2    69   137   Class java/lang/Exception
          91   137   137   Class java/lang/Exception
           2    69   147   any
         149   153   156   Class javax/xml/stream/XMLStreamException
          91   149   147   any

  public org.w3c.dom.Document getDocument(java.io.File) throws org.apache.cxf.tools.common.ToolException;
    Code:
       0: aconst_null
       1: astore_2
       2: new           #14                 // class javax/xml/transform/stream/StreamSource
       5: dup
       6: aload_1
       7: invokespecial #24                 // Method javax/xml/transform/stream/StreamSource."<init>":(Ljava/io/File;)V
      10: astore_3
      11: aload_3
      12: invokestatic  #17                 // Method org/apache/cxf/staxutils/StaxUtils.createXMLStreamReader:(Ljavax/xml/transform/Source;)Ljavax/xml/stream/XMLStreamReader;
      15: astore_2
      16: aload_2
      17: iconst_1
      18: invokestatic  #18                 // Method org/apache/cxf/staxutils/StaxUtils.read:(Ljavax/xml/stream/XMLStreamReader;Z)Lorg/w3c/dom/Document;
      21: astore        4
      23: aload_2
      24: ifnull        60
      27: aload_2
      28: invokevirtual #25                 // Method java/lang/Object.getClass:()Ljava/lang/Class;
      31: ldc           #26                 // String closeCompletely
      33: iconst_0
      34: anewarray     #27                 // class java/lang/Class
      37: invokevirtual #28                 // Method java/lang/Class.getMethod:(Ljava/lang/String;[Ljava/lang/Class;)Ljava/lang/reflect/Method;
      40: aload_2
      41: iconst_0
      42: anewarray     #29                 // class java/lang/Object
      45: invokevirtual #30                 // Method java/lang/reflect/Method.invoke:(Ljava/lang/Object;[Ljava/lang/Object;)Ljava/lang/Object;
      48: pop
      49: goto          54
      52: astore        5
      54: aload_2
      55: invokeinterface #31,  1           // InterfaceMethod javax/xml/stream/XMLStreamReader.close:()V
      60: goto          75
      63: astore        5
      65: new           #10                 // class org/apache/cxf/tools/common/ToolException
      68: dup
      69: aload         5
      71: invokespecial #12                 // Method org/apache/cxf/tools/common/ToolException."<init>":(Ljava/lang/Throwable;)V
      74: athrow
      75: aload         4
      77: areturn
      78: astore_3
      79: new           #10                 // class org/apache/cxf/tools/common/ToolException
      82: dup
      83: aload_3
      84: invokespecial #12                 // Method org/apache/cxf/tools/common/ToolException."<init>":(Ljava/lang/Throwable;)V
      87: athrow
      88: astore        6
      90: aload_2
      91: ifnull        127
      94: aload_2
      95: invokevirtual #25                 // Method java/lang/Object.getClass:()Ljava/lang/Class;
      98: ldc           #26                 // String closeCompletely
     100: iconst_0
     101: anewarray     #27                 // class java/lang/Class
     104: invokevirtual #28                 // Method java/lang/Class.getMethod:(Ljava/lang/String;[Ljava/lang/Class;)Ljava/lang/reflect/Method;
     107: aload_2
     108: iconst_0
     109: anewarray     #29                 // class java/lang/Object
     112: invokevirtual #30                 // Method java/lang/reflect/Method.invoke:(Ljava/lang/Object;[Ljava/lang/Object;)Ljava/lang/Object;
     115: pop
     116: goto          121
     119: astore        7
     121: aload_2
     122: invokeinterface #31,  1           // InterfaceMethod javax/xml/stream/XMLStreamReader.close:()V
     127: goto          142
     130: astore        7
     132: new           #10                 // class org/apache/cxf/tools/common/ToolException
     135: dup
     136: aload         7
     138: invokespecial #12                 // Method org/apache/cxf/tools/common/ToolException."<init>":(Ljava/lang/Throwable;)V
     141: athrow
     142: aload         6
     144: athrow
    Exception table:
       from    to  target type
          27    49    52   Class java/lang/Throwable
          23    60    63   Class javax/xml/stream/XMLStreamException
           2    23    78   Class java/lang/Exception
           2    23    88   any
          94   116   119   Class java/lang/Throwable
          90   127   130   Class javax/xml/stream/XMLStreamException
          78    90    88   any
}
