Compiled from "WSDL11Validator.java"
class org.apache.cxf.tools.validator.internal.WSDL11Validator$1 implements java.io.FileFilter {
  final org.apache.cxf.tools.validator.internal.WSDL11Validator this$0;

  org.apache.cxf.tools.validator.internal.WSDL11Validator$1(org.apache.cxf.tools.validator.internal.WSDL11Validator);
    Code:
       0: aload_0
       1: aload_1
       2: putfield      #1                  // Field this$0:Lorg/apache/cxf/tools/validator/internal/WSDL11Validator;
       5: aload_0
       6: invokespecial #2                  // Method java/lang/Object."<init>":()V
       9: return

  public boolean accept(java.io.File);
    Code:
       0: aload_1
       1: invokevirtual #3                  // Method java/io/File.getAbsolutePath:()Ljava/lang/String;
       4: ldc           #4                  // String .xsd
       6: invokevirtual #5                  // Method java/lang/String.endsWith:(Ljava/lang/String;)Z
       9: ifeq          14
      12: iconst_1
      13: ireturn
      14: iconst_0
      15: ireturn
}
