Compiled from "EnhancedQueueExecutor.java"
final class org.jboss.threads.EnhancedQueueExecutor$MBeanRegisterAction implements java.security.PrivilegedAction<javax.management.ObjectInstance> {
  private final java.lang.String finalName;

  private final org.jboss.threads.EnhancedQueueExecutor$MXBeanImpl mxBean;

  org.jboss.threads.EnhancedQueueExecutor$MBeanRegisterAction(java.lang.String, org.jboss.threads.EnhancedQueueExecutor$MXBeanImpl);
    Code:
       0: aload_0
       1: invokespecial #1                  // Method java/lang/Object."<init>":()V
       4: aload_0
       5: aload_1
       6: putfield      #2                  // Field finalName:Ljava/lang/String;
       9: aload_0
      10: aload_2
      11: putfield      #3                  // Field mxBean:Lorg/jboss/threads/EnhancedQueueExecutor$MXBeanImpl;
      14: return

  public javax.management.ObjectInstance run();
    Code:
       0: new           #4                  // class java/util/Hashtable
       3: dup
       4: invokespecial #5                  // Method java/util/Hashtable."<init>":()V
       7: astore_1
       8: aload_1
       9: ldc           #6                  // String name
      11: aload_0
      12: getfield      #2                  // Field finalName:Ljava/lang/String;
      15: invokestatic  #7                  // Method javax/management/ObjectName.quote:(Ljava/lang/String;)Ljava/lang/String;
      18: invokevirtual #8                  // Method java/util/Hashtable.put:(Ljava/lang/Object;Ljava/lang/Object;)Ljava/lang/Object;
      21: pop
      22: aload_1
      23: ldc           #9                  // String type
      25: ldc           #10                 // String thread-pool
      27: invokevirtual #8                  // Method java/util/Hashtable.put:(Ljava/lang/Object;Ljava/lang/Object;)Ljava/lang/Object;
      30: pop
      31: invokestatic  #11                 // Method java/lang/management/ManagementFactory.getPlatformMBeanServer:()Ljavax/management/MBeanServer;
      34: aload_0
      35: getfield      #3                  // Field mxBean:Lorg/jboss/threads/EnhancedQueueExecutor$MXBeanImpl;
      38: new           #12                 // class javax/management/ObjectName
      41: dup
      42: ldc           #13                 // String jboss.threads
      44: aload_1
      45: invokespecial #14                 // Method javax/management/ObjectName."<init>":(Ljava/lang/String;Ljava/util/Hashtable;)V
      48: invokeinterface #15,  3           // InterfaceMethod javax/management/MBeanServer.registerMBean:(Ljava/lang/Object;Ljavax/management/ObjectName;)Ljavax/management/ObjectInstance;
      53: areturn
      54: astore_1
      55: aconst_null
      56: areturn
    Exception table:
       from    to  target type
           0    53    54   Class java/lang/Throwable

  public java.lang.Object run();
    Code:
       0: aload_0
       1: invokevirtual #17                 // Method run:()Ljavax/management/ObjectInstance;
       4: areturn
}
