Compiled from "ThreadLocalResettingRunnable.java"
final class org.jboss.threads.ThreadLocalResettingRunnable extends org.jboss.threads.DelegatingRunnable {
  org.jboss.threads.ThreadLocalResettingRunnable(java.lang.Runnable);
    Code:
       0: aload_0
       1: aload_1
       2: invokespecial #1                  // Method org/jboss/threads/DelegatingRunnable."<init>":(Ljava/lang/Runnable;)V
       5: return

  public void run();
    Code:
       0: aload_0
       1: invokespecial #2                  // Method org/jboss/threads/DelegatingRunnable.run:()V
       4: invokestatic  #3                  // Method org/jboss/threads/ThreadLocalResettingRunnable$Resetter.run:()V
       7: goto          16
      10: astore_1
      11: invokestatic  #3                  // Method org/jboss/threads/ThreadLocalResettingRunnable$Resetter.run:()V
      14: aload_1
      15: athrow
      16: return
    Exception table:
       from    to  target type
           0     4    10   any

  public java.lang.String toString();
    Code:
       0: ldc           #4                  // String Thread-local resetting Runnable
       2: areturn
}
