Compiled from "AccessoryOkayFunction.java"
public class org.bidib.wizard.api.model.function.AccessoryOkayFunction extends org.bidib.wizard.api.model.function.SystemFunction<org.bidib.wizard.model.status.AccessoryOkayStatus> {
  private org.bidib.wizard.model.ports.InputPort input;

  public org.bidib.wizard.api.model.function.AccessoryOkayFunction();
    Code:
       0: aload_0
       1: getstatic     #1                  // Field org/bidib/wizard/model/status/AccessoryOkayStatus.QUERY0:Lorg/bidib/wizard/model/status/AccessoryOkayStatus;
       4: invokespecial #2                  // Method "<init>":(Lorg/bidib/wizard/model/status/AccessoryOkayStatus;)V
       7: return

  public org.bidib.wizard.api.model.function.AccessoryOkayFunction(org.bidib.wizard.model.status.AccessoryOkayStatus);
    Code:
       0: aload_0
       1: aload_1
       2: aconst_null
       3: invokespecial #3                  // Method "<init>":(Lorg/bidib/wizard/model/status/AccessoryOkayStatus;Lorg/bidib/wizard/model/ports/InputPort;)V
       6: return

  public org.bidib.wizard.api.model.function.AccessoryOkayFunction(org.bidib.wizard.model.status.AccessoryOkayStatus, org.bidib.wizard.model.ports.InputPort);
    Code:
       0: aload_0
       1: aload_1
       2: ldc           #5                  // String accessoryOkay
       4: invokespecial #6                  // Method org/bidib/wizard/api/model/function/SystemFunction."<init>":(Lorg/bidib/wizard/model/status/BidibStatus;Ljava/lang/String;)V
       7: aload_0
       8: aload_2
       9: putfield      #7                  // Field input:Lorg/bidib/wizard/model/ports/InputPort;
      12: return

  public org.bidib.wizard.model.ports.InputPort getInput();
    Code:
       0: aload_0
       1: getfield      #7                  // Field input:Lorg/bidib/wizard/model/ports/InputPort;
       4: areturn

  public void setInput(org.bidib.wizard.model.ports.InputPort);
    Code:
       0: aload_0
       1: aload_1
       2: putfield      #7                  // Field input:Lorg/bidib/wizard/model/ports/InputPort;
       5: return

  public java.lang.String getDebugString();
    Code:
       0: iconst_0
       1: istore_1
       2: aload_0
       3: invokevirtual #8                  // Method getInput:()Lorg/bidib/wizard/model/ports/InputPort;
       6: ifnull        17
       9: aload_0
      10: invokevirtual #8                  // Method getInput:()Lorg/bidib/wizard/model/ports/InputPort;
      13: invokevirtual #9                  // Method org/bidib/wizard/model/ports/InputPort.getId:()I
      16: istore_1
      17: new           #10                 // class java/lang/StringBuilder
      20: dup
      21: invokespecial #11                 // Method java/lang/StringBuilder."<init>":()V
      24: ldc           #12                 // String Accessory Okay=
      26: invokevirtual #13                 // Method java/lang/StringBuilder.append:(Ljava/lang/String;)Ljava/lang/StringBuilder;
      29: aload_0
      30: invokevirtual #14                 // Method getAction:()Lorg/bidib/wizard/model/status/BidibStatus;
      33: checkcast     #15                 // class org/bidib/wizard/model/status/AccessoryOkayStatus
      36: invokevirtual #16                 // Method org/bidib/wizard/model/status/AccessoryOkayStatus.name:()Ljava/lang/String;
      39: iconst_5
      40: invokevirtual #17                 // Method java/lang/String.substring:(I)Ljava/lang/String;
      43: invokevirtual #13                 // Method java/lang/StringBuilder.append:(Ljava/lang/String;)Ljava/lang/StringBuilder;
      46: ldc           #18                 // String ? Port=
      48: invokevirtual #13                 // Method java/lang/StringBuilder.append:(Ljava/lang/String;)Ljava/lang/StringBuilder;
      51: iload_1
      52: invokevirtual #19                 // Method java/lang/StringBuilder.append:(I)Ljava/lang/StringBuilder;
      55: invokevirtual #20                 // Method java/lang/StringBuilder.toString:()Ljava/lang/String;
      58: areturn

  public org.bidib.jbidibc.exchange.lcmacro.LcMacroPointType toLcMacroPoint();
    Code:
       0: new           #21                 // class org/bidib/jbidibc/exchange/lcmacro/AccessoryOkayPoint
       3: dup
       4: invokespecial #22                 // Method org/bidib/jbidibc/exchange/lcmacro/AccessoryOkayPoint."<init>":()V
       7: aload_0
       8: invokevirtual #14                 // Method getAction:()Lorg/bidib/wizard/model/status/BidibStatus;
      11: checkcast     #15                 // class org/bidib/wizard/model/status/AccessoryOkayStatus
      14: invokevirtual #16                 // Method org/bidib/wizard/model/status/AccessoryOkayStatus.name:()Ljava/lang/String;
      17: invokestatic  #23                 // Method org/bidib/jbidibc/exchange/lcmacro/AccessoryOkayActionType.fromValue:(Ljava/lang/String;)Lorg/bidib/jbidibc/exchange/lcmacro/AccessoryOkayActionType;
      20: invokevirtual #24                 // Method org/bidib/jbidibc/exchange/lcmacro/AccessoryOkayPoint.withAccessoryOkayActionType:(Lorg/bidib/jbidibc/exchange/lcmacro/AccessoryOkayActionType;)Lorg/bidib/jbidibc/exchange/lcmacro/AccessoryOkayPoint;
      23: astore_1
      24: getstatic     #25                 // Field org/bidib/jbidibc/core/enumeration/AccessoryOkayEnum.NO_FEEDBACK:Lorg/bidib/jbidibc/core/enumeration/AccessoryOkayEnum;
      27: aload_0
      28: invokevirtual #14                 // Method getAction:()Lorg/bidib/wizard/model/status/BidibStatus;
      31: checkcast     #15                 // class org/bidib/wizard/model/status/AccessoryOkayStatus
      34: invokevirtual #26                 // Method org/bidib/wizard/model/status/AccessoryOkayStatus.getType:()Lorg/bidib/jbidibc/core/enumeration/AccessoryOkayEnum;
      37: invokevirtual #27                 // Method org/bidib/jbidibc/core/enumeration/AccessoryOkayEnum.equals:(Ljava/lang/Object;)Z
      40: ifne          64
      43: aload_0
      44: invokevirtual #8                  // Method getInput:()Lorg/bidib/wizard/model/ports/InputPort;
      47: ifnull        64
      50: aload_1
      51: aload_0
      52: invokevirtual #8                  // Method getInput:()Lorg/bidib/wizard/model/ports/InputPort;
      55: invokevirtual #9                  // Method org/bidib/wizard/model/ports/InputPort.getId:()I
      58: invokestatic  #28                 // Method java/lang/Integer.valueOf:(I)Ljava/lang/Integer;
      61: invokevirtual #29                 // Method org/bidib/jbidibc/exchange/lcmacro/AccessoryOkayPoint.setInputNumber:(Ljava/lang/Integer;)V
      64: aload_1
      65: areturn
}
