Compiled from "DescribeOrderableDBInstanceOptionsRequest.java"
public class com.amazonaws.services.rds.model.DescribeOrderableDBInstanceOptionsRequest extends com.amazonaws.AmazonWebServiceRequest implements java.io.Serializable,java.lang.Cloneable {
  private java.lang.String engine;

  private java.lang.String engineVersion;

  private java.lang.String dBInstanceClass;

  private java.lang.String licenseModel;

  private java.lang.Boolean vpc;

  private com.amazonaws.internal.SdkInternalList<com.amazonaws.services.rds.model.Filter> filters;

  private java.lang.Integer maxRecords;

  private java.lang.String marker;

  public com.amazonaws.services.rds.model.DescribeOrderableDBInstanceOptionsRequest();
    Code:
       0: aload_0
       1: invokespecial #1                  // Method com/amazonaws/AmazonWebServiceRequest."<init>":()V
       4: return

  public void setEngine(java.lang.String);
    Code:
       0: aload_0
       1: aload_1
       2: putfield      #2                  // Field engine:Ljava/lang/String;
       5: return

  public java.lang.String getEngine();
    Code:
       0: aload_0
       1: getfield      #2                  // Field engine:Ljava/lang/String;
       4: areturn

  public com.amazonaws.services.rds.model.DescribeOrderableDBInstanceOptionsRequest withEngine(java.lang.String);
    Code:
       0: aload_0
       1: aload_1
       2: invokevirtual #3                  // Method setEngine:(Ljava/lang/String;)V
       5: aload_0
       6: areturn

  public void setEngineVersion(java.lang.String);
    Code:
       0: aload_0
       1: aload_1
       2: putfield      #4                  // Field engineVersion:Ljava/lang/String;
       5: return

  public java.lang.String getEngineVersion();
    Code:
       0: aload_0
       1: getfield      #4                  // Field engineVersion:Ljava/lang/String;
       4: areturn

  public com.amazonaws.services.rds.model.DescribeOrderableDBInstanceOptionsRequest withEngineVersion(java.lang.String);
    Code:
       0: aload_0
       1: aload_1
       2: invokevirtual #5                  // Method setEngineVersion:(Ljava/lang/String;)V
       5: aload_0
       6: areturn

  public void setDBInstanceClass(java.lang.String);
    Code:
       0: aload_0
       1: aload_1
       2: putfield      #6                  // Field dBInstanceClass:Ljava/lang/String;
       5: return

  public java.lang.String getDBInstanceClass();
    Code:
       0: aload_0
       1: getfield      #6                  // Field dBInstanceClass:Ljava/lang/String;
       4: areturn

  public com.amazonaws.services.rds.model.DescribeOrderableDBInstanceOptionsRequest withDBInstanceClass(java.lang.String);
    Code:
       0: aload_0
       1: aload_1
       2: invokevirtual #7                  // Method setDBInstanceClass:(Ljava/lang/String;)V
       5: aload_0
       6: areturn

  public void setLicenseModel(java.lang.String);
    Code:
       0: aload_0
       1: aload_1
       2: putfield      #8                  // Field licenseModel:Ljava/lang/String;
       5: return

  public java.lang.String getLicenseModel();
    Code:
       0: aload_0
       1: getfield      #8                  // Field licenseModel:Ljava/lang/String;
       4: areturn

  public com.amazonaws.services.rds.model.DescribeOrderableDBInstanceOptionsRequest withLicenseModel(java.lang.String);
    Code:
       0: aload_0
       1: aload_1
       2: invokevirtual #9                  // Method setLicenseModel:(Ljava/lang/String;)V
       5: aload_0
       6: areturn

  public void setVpc(java.lang.Boolean);
    Code:
       0: aload_0
       1: aload_1
       2: putfield      #10                 // Field vpc:Ljava/lang/Boolean;
       5: return

  public java.lang.Boolean getVpc();
    Code:
       0: aload_0
       1: getfield      #10                 // Field vpc:Ljava/lang/Boolean;
       4: areturn

  public com.amazonaws.services.rds.model.DescribeOrderableDBInstanceOptionsRequest withVpc(java.lang.Boolean);
    Code:
       0: aload_0
       1: aload_1
       2: invokevirtual #11                 // Method setVpc:(Ljava/lang/Boolean;)V
       5: aload_0
       6: areturn

  public java.lang.Boolean isVpc();
    Code:
       0: aload_0
       1: getfield      #10                 // Field vpc:Ljava/lang/Boolean;
       4: areturn

  public java.util.List<com.amazonaws.services.rds.model.Filter> getFilters();
    Code:
       0: aload_0
       1: getfield      #12                 // Field filters:Lcom/amazonaws/internal/SdkInternalList;
       4: ifnonnull     18
       7: aload_0
       8: new           #13                 // class com/amazonaws/internal/SdkInternalList
      11: dup
      12: invokespecial #14                 // Method com/amazonaws/internal/SdkInternalList."<init>":()V
      15: putfield      #12                 // Field filters:Lcom/amazonaws/internal/SdkInternalList;
      18: aload_0
      19: getfield      #12                 // Field filters:Lcom/amazonaws/internal/SdkInternalList;
      22: areturn

  public void setFilters(java.util.Collection<com.amazonaws.services.rds.model.Filter>);
    Code:
       0: aload_1
       1: ifnonnull     10
       4: aload_0
       5: aconst_null
       6: putfield      #12                 // Field filters:Lcom/amazonaws/internal/SdkInternalList;
       9: return
      10: aload_0
      11: new           #13                 // class com/amazonaws/internal/SdkInternalList
      14: dup
      15: aload_1
      16: invokespecial #15                 // Method com/amazonaws/internal/SdkInternalList."<init>":(Ljava/util/Collection;)V
      19: putfield      #12                 // Field filters:Lcom/amazonaws/internal/SdkInternalList;
      22: return

  public com.amazonaws.services.rds.model.DescribeOrderableDBInstanceOptionsRequest withFilters(com.amazonaws.services.rds.model.Filter...);
    Code:
       0: aload_0
       1: getfield      #12                 // Field filters:Lcom/amazonaws/internal/SdkInternalList;
       4: ifnonnull     20
       7: aload_0
       8: new           #13                 // class com/amazonaws/internal/SdkInternalList
      11: dup
      12: aload_1
      13: arraylength
      14: invokespecial #16                 // Method com/amazonaws/internal/SdkInternalList."<init>":(I)V
      17: invokevirtual #17                 // Method setFilters:(Ljava/util/Collection;)V
      20: aload_1
      21: astore_2
      22: aload_2
      23: arraylength
      24: istore_3
      25: iconst_0
      26: istore        4
      28: iload         4
      30: iload_3
      31: if_icmpge     56
      34: aload_2
      35: iload         4
      37: aaload
      38: astore        5
      40: aload_0
      41: getfield      #12                 // Field filters:Lcom/amazonaws/internal/SdkInternalList;
      44: aload         5
      46: invokevirtual #18                 // Method com/amazonaws/internal/SdkInternalList.add:(Ljava/lang/Object;)Z
      49: pop
      50: iinc          4, 1
      53: goto          28
      56: aload_0
      57: areturn

  public com.amazonaws.services.rds.model.DescribeOrderableDBInstanceOptionsRequest withFilters(java.util.Collection<com.amazonaws.services.rds.model.Filter>);
    Code:
       0: aload_0
       1: aload_1
       2: invokevirtual #17                 // Method setFilters:(Ljava/util/Collection;)V
       5: aload_0
       6: areturn

  public void setMaxRecords(java.lang.Integer);
    Code:
       0: aload_0
       1: aload_1
       2: putfield      #19                 // Field maxRecords:Ljava/lang/Integer;
       5: return

  public java.lang.Integer getMaxRecords();
    Code:
       0: aload_0
       1: getfield      #19                 // Field maxRecords:Ljava/lang/Integer;
       4: areturn

  public com.amazonaws.services.rds.model.DescribeOrderableDBInstanceOptionsRequest withMaxRecords(java.lang.Integer);
    Code:
       0: aload_0
       1: aload_1
       2: invokevirtual #20                 // Method setMaxRecords:(Ljava/lang/Integer;)V
       5: aload_0
       6: areturn

  public void setMarker(java.lang.String);
    Code:
       0: aload_0
       1: aload_1
       2: putfield      #21                 // Field marker:Ljava/lang/String;
       5: return

  public java.lang.String getMarker();
    Code:
       0: aload_0
       1: getfield      #21                 // Field marker:Ljava/lang/String;
       4: areturn

  public com.amazonaws.services.rds.model.DescribeOrderableDBInstanceOptionsRequest withMarker(java.lang.String);
    Code:
       0: aload_0
       1: aload_1
       2: invokevirtual #22                 // Method setMarker:(Ljava/lang/String;)V
       5: aload_0
       6: areturn

  public java.lang.String toString();
    Code:
       0: new           #23                 // class java/lang/StringBuilder
       3: dup
       4: invokespecial #24                 // Method java/lang/StringBuilder."<init>":()V
       7: astore_1
       8: aload_1
       9: ldc           #25                 // String {
      11: invokevirtual #26                 // Method java/lang/StringBuilder.append:(Ljava/lang/String;)Ljava/lang/StringBuilder;
      14: pop
      15: aload_0
      16: invokevirtual #27                 // Method getEngine:()Ljava/lang/String;
      19: ifnull        54
      22: aload_1
      23: new           #23                 // class java/lang/StringBuilder
      26: dup
      27: invokespecial #24                 // Method java/lang/StringBuilder."<init>":()V
      30: ldc           #28                 // String Engine:
      32: invokevirtual #26                 // Method java/lang/StringBuilder.append:(Ljava/lang/String;)Ljava/lang/StringBuilder;
      35: aload_0
      36: invokevirtual #27                 // Method getEngine:()Ljava/lang/String;
      39: invokevirtual #26                 // Method java/lang/StringBuilder.append:(Ljava/lang/String;)Ljava/lang/StringBuilder;
      42: ldc           #29                 // String ,
      44: invokevirtual #26                 // Method java/lang/StringBuilder.append:(Ljava/lang/String;)Ljava/lang/StringBuilder;
      47: invokevirtual #30                 // Method java/lang/StringBuilder.toString:()Ljava/lang/String;
      50: invokevirtual #26                 // Method java/lang/StringBuilder.append:(Ljava/lang/String;)Ljava/lang/StringBuilder;
      53: pop
      54: aload_0
      55: invokevirtual #31                 // Method getEngineVersion:()Ljava/lang/String;
      58: ifnull        93
      61: aload_1
      62: new           #23                 // class java/lang/StringBuilder
      65: dup
      66: invokespecial #24                 // Method java/lang/StringBuilder."<init>":()V
      69: ldc           #32                 // String EngineVersion:
      71: invokevirtual #26                 // Method java/lang/StringBuilder.append:(Ljava/lang/String;)Ljava/lang/StringBuilder;
      74: aload_0
      75: invokevirtual #31                 // Method getEngineVersion:()Ljava/lang/String;
      78: invokevirtual #26                 // Method java/lang/StringBuilder.append:(Ljava/lang/String;)Ljava/lang/StringBuilder;
      81: ldc           #29                 // String ,
      83: invokevirtual #26                 // Method java/lang/StringBuilder.append:(Ljava/lang/String;)Ljava/lang/StringBuilder;
      86: invokevirtual #30                 // Method java/lang/StringBuilder.toString:()Ljava/lang/String;
      89: invokevirtual #26                 // Method java/lang/StringBuilder.append:(Ljava/lang/String;)Ljava/lang/StringBuilder;
      92: pop
      93: aload_0
      94: invokevirtual #33                 // Method getDBInstanceClass:()Ljava/lang/String;
      97: ifnull        132
     100: aload_1
     101: new           #23                 // class java/lang/StringBuilder
     104: dup
     105: invokespecial #24                 // Method java/lang/StringBuilder."<init>":()V
     108: ldc           #34                 // String DBInstanceClass:
     110: invokevirtual #26                 // Method java/lang/StringBuilder.append:(Ljava/lang/String;)Ljava/lang/StringBuilder;
     113: aload_0
     114: invokevirtual #33                 // Method getDBInstanceClass:()Ljava/lang/String;
     117: invokevirtual #26                 // Method java/lang/StringBuilder.append:(Ljava/lang/String;)Ljava/lang/StringBuilder;
     120: ldc           #29                 // String ,
     122: invokevirtual #26                 // Method java/lang/StringBuilder.append:(Ljava/lang/String;)Ljava/lang/StringBuilder;
     125: invokevirtual #30                 // Method java/lang/StringBuilder.toString:()Ljava/lang/String;
     128: invokevirtual #26                 // Method java/lang/StringBuilder.append:(Ljava/lang/String;)Ljava/lang/StringBuilder;
     131: pop
     132: aload_0
     133: invokevirtual #35                 // Method getLicenseModel:()Ljava/lang/String;
     136: ifnull        171
     139: aload_1
     140: new           #23                 // class java/lang/StringBuilder
     143: dup
     144: invokespecial #24                 // Method java/lang/StringBuilder."<init>":()V
     147: ldc           #36                 // String LicenseModel:
     149: invokevirtual #26                 // Method java/lang/StringBuilder.append:(Ljava/lang/String;)Ljava/lang/StringBuilder;
     152: aload_0
     153: invokevirtual #35                 // Method getLicenseModel:()Ljava/lang/String;
     156: invokevirtual #26                 // Method java/lang/StringBuilder.append:(Ljava/lang/String;)Ljava/lang/StringBuilder;
     159: ldc           #29                 // String ,
     161: invokevirtual #26                 // Method java/lang/StringBuilder.append:(Ljava/lang/String;)Ljava/lang/StringBuilder;
     164: invokevirtual #30                 // Method java/lang/StringBuilder.toString:()Ljava/lang/String;
     167: invokevirtual #26                 // Method java/lang/StringBuilder.append:(Ljava/lang/String;)Ljava/lang/StringBuilder;
     170: pop
     171: aload_0
     172: invokevirtual #37                 // Method getVpc:()Ljava/lang/Boolean;
     175: ifnull        210
     178: aload_1
     179: new           #23                 // class java/lang/StringBuilder
     182: dup
     183: invokespecial #24                 // Method java/lang/StringBuilder."<init>":()V
     186: ldc           #38                 // String Vpc:
     188: invokevirtual #26                 // Method java/lang/StringBuilder.append:(Ljava/lang/String;)Ljava/lang/StringBuilder;
     191: aload_0
     192: invokevirtual #37                 // Method getVpc:()Ljava/lang/Boolean;
     195: invokevirtual #39                 // Method java/lang/StringBuilder.append:(Ljava/lang/Object;)Ljava/lang/StringBuilder;
     198: ldc           #29                 // String ,
     200: invokevirtual #26                 // Method java/lang/StringBuilder.append:(Ljava/lang/String;)Ljava/lang/StringBuilder;
     203: invokevirtual #30                 // Method java/lang/StringBuilder.toString:()Ljava/lang/String;
     206: invokevirtual #26                 // Method java/lang/StringBuilder.append:(Ljava/lang/String;)Ljava/lang/StringBuilder;
     209: pop
     210: aload_0
     211: invokevirtual #40                 // Method getFilters:()Ljava/util/List;
     214: ifnull        249
     217: aload_1
     218: new           #23                 // class java/lang/StringBuilder
     221: dup
     222: invokespecial #24                 // Method java/lang/StringBuilder."<init>":()V
     225: ldc           #41                 // String Filters:
     227: invokevirtual #26                 // Method java/lang/StringBuilder.append:(Ljava/lang/String;)Ljava/lang/StringBuilder;
     230: aload_0
     231: invokevirtual #40                 // Method getFilters:()Ljava/util/List;
     234: invokevirtual #39                 // Method java/lang/StringBuilder.append:(Ljava/lang/Object;)Ljava/lang/StringBuilder;
     237: ldc           #29                 // String ,
     239: invokevirtual #26                 // Method java/lang/StringBuilder.append:(Ljava/lang/String;)Ljava/lang/StringBuilder;
     242: invokevirtual #30                 // Method java/lang/StringBuilder.toString:()Ljava/lang/String;
     245: invokevirtual #26                 // Method java/lang/StringBuilder.append:(Ljava/lang/String;)Ljava/lang/StringBuilder;
     248: pop
     249: aload_0
     250: invokevirtual #42                 // Method getMaxRecords:()Ljava/lang/Integer;
     253: ifnull        288
     256: aload_1
     257: new           #23                 // class java/lang/StringBuilder
     260: dup
     261: invokespecial #24                 // Method java/lang/StringBuilder."<init>":()V
     264: ldc           #43                 // String MaxRecords:
     266: invokevirtual #26                 // Method java/lang/StringBuilder.append:(Ljava/lang/String;)Ljava/lang/StringBuilder;
     269: aload_0
     270: invokevirtual #42                 // Method getMaxRecords:()Ljava/lang/Integer;
     273: invokevirtual #39                 // Method java/lang/StringBuilder.append:(Ljava/lang/Object;)Ljava/lang/StringBuilder;
     276: ldc           #29                 // String ,
     278: invokevirtual #26                 // Method java/lang/StringBuilder.append:(Ljava/lang/String;)Ljava/lang/StringBuilder;
     281: invokevirtual #30                 // Method java/lang/StringBuilder.toString:()Ljava/lang/String;
     284: invokevirtual #26                 // Method java/lang/StringBuilder.append:(Ljava/lang/String;)Ljava/lang/StringBuilder;
     287: pop
     288: aload_0
     289: invokevirtual #44                 // Method getMarker:()Ljava/lang/String;
     292: ifnull        322
     295: aload_1
     296: new           #23                 // class java/lang/StringBuilder
     299: dup
     300: invokespecial #24                 // Method java/lang/StringBuilder."<init>":()V
     303: ldc           #45                 // String Marker:
     305: invokevirtual #26                 // Method java/lang/StringBuilder.append:(Ljava/lang/String;)Ljava/lang/StringBuilder;
     308: aload_0
     309: invokevirtual #44                 // Method getMarker:()Ljava/lang/String;
     312: invokevirtual #26                 // Method java/lang/StringBuilder.append:(Ljava/lang/String;)Ljava/lang/StringBuilder;
     315: invokevirtual #30                 // Method java/lang/StringBuilder.toString:()Ljava/lang/String;
     318: invokevirtual #26                 // Method java/lang/StringBuilder.append:(Ljava/lang/String;)Ljava/lang/StringBuilder;
     321: pop
     322: aload_1
     323: ldc           #46                 // String }
     325: invokevirtual #26                 // Method java/lang/StringBuilder.append:(Ljava/lang/String;)Ljava/lang/StringBuilder;
     328: pop
     329: aload_1
     330: invokevirtual #30                 // Method java/lang/StringBuilder.toString:()Ljava/lang/String;
     333: areturn

  public boolean equals(java.lang.Object);
    Code:
       0: aload_0
       1: aload_1
       2: if_acmpne     7
       5: iconst_1
       6: ireturn
       7: aload_1
       8: ifnonnull     13
      11: iconst_0
      12: ireturn
      13: aload_1
      14: instanceof    #47                 // class com/amazonaws/services/rds/model/DescribeOrderableDBInstanceOptionsRequest
      17: ifne          22
      20: iconst_0
      21: ireturn
      22: aload_1
      23: checkcast     #47                 // class com/amazonaws/services/rds/model/DescribeOrderableDBInstanceOptionsRequest
      26: astore_2
      27: aload_2
      28: invokevirtual #27                 // Method getEngine:()Ljava/lang/String;
      31: ifnonnull     38
      34: iconst_1
      35: goto          39
      38: iconst_0
      39: aload_0
      40: invokevirtual #27                 // Method getEngine:()Ljava/lang/String;
      43: ifnonnull     50
      46: iconst_1
      47: goto          51
      50: iconst_0
      51: ixor
      52: ifeq          57
      55: iconst_0
      56: ireturn
      57: aload_2
      58: invokevirtual #27                 // Method getEngine:()Ljava/lang/String;
      61: ifnull        80
      64: aload_2
      65: invokevirtual #27                 // Method getEngine:()Ljava/lang/String;
      68: aload_0
      69: invokevirtual #27                 // Method getEngine:()Ljava/lang/String;
      72: invokevirtual #48                 // Method java/lang/String.equals:(Ljava/lang/Object;)Z
      75: ifne          80
      78: iconst_0
      79: ireturn
      80: aload_2
      81: invokevirtual #31                 // Method getEngineVersion:()Ljava/lang/String;
      84: ifnonnull     91
      87: iconst_1
      88: goto          92
      91: iconst_0
      92: aload_0
      93: invokevirtual #31                 // Method getEngineVersion:()Ljava/lang/String;
      96: ifnonnull     103
      99: iconst_1
     100: goto          104
     103: iconst_0
     104: ixor
     105: ifeq          110
     108: iconst_0
     109: ireturn
     110: aload_2
     111: invokevirtual #31                 // Method getEngineVersion:()Ljava/lang/String;
     114: ifnull        133
     117: aload_2
     118: invokevirtual #31                 // Method getEngineVersion:()Ljava/lang/String;
     121: aload_0
     122: invokevirtual #31                 // Method getEngineVersion:()Ljava/lang/String;
     125: invokevirtual #48                 // Method java/lang/String.equals:(Ljava/lang/Object;)Z
     128: ifne          133
     131: iconst_0
     132: ireturn
     133: aload_2
     134: invokevirtual #33                 // Method getDBInstanceClass:()Ljava/lang/String;
     137: ifnonnull     144
     140: iconst_1
     141: goto          145
     144: iconst_0
     145: aload_0
     146: invokevirtual #33                 // Method getDBInstanceClass:()Ljava/lang/String;
     149: ifnonnull     156
     152: iconst_1
     153: goto          157
     156: iconst_0
     157: ixor
     158: ifeq          163
     161: iconst_0
     162: ireturn
     163: aload_2
     164: invokevirtual #33                 // Method getDBInstanceClass:()Ljava/lang/String;
     167: ifnull        186
     170: aload_2
     171: invokevirtual #33                 // Method getDBInstanceClass:()Ljava/lang/String;
     174: aload_0
     175: invokevirtual #33                 // Method getDBInstanceClass:()Ljava/lang/String;
     178: invokevirtual #48                 // Method java/lang/String.equals:(Ljava/lang/Object;)Z
     181: ifne          186
     184: iconst_0
     185: ireturn
     186: aload_2
     187: invokevirtual #35                 // Method getLicenseModel:()Ljava/lang/String;
     190: ifnonnull     197
     193: iconst_1
     194: goto          198
     197: iconst_0
     198: aload_0
     199: invokevirtual #35                 // Method getLicenseModel:()Ljava/lang/String;
     202: ifnonnull     209
     205: iconst_1
     206: goto          210
     209: iconst_0
     210: ixor
     211: ifeq          216
     214: iconst_0
     215: ireturn
     216: aload_2
     217: invokevirtual #35                 // Method getLicenseModel:()Ljava/lang/String;
     220: ifnull        239
     223: aload_2
     224: invokevirtual #35                 // Method getLicenseModel:()Ljava/lang/String;
     227: aload_0
     228: invokevirtual #35                 // Method getLicenseModel:()Ljava/lang/String;
     231: invokevirtual #48                 // Method java/lang/String.equals:(Ljava/lang/Object;)Z
     234: ifne          239
     237: iconst_0
     238: ireturn
     239: aload_2
     240: invokevirtual #37                 // Method getVpc:()Ljava/lang/Boolean;
     243: ifnonnull     250
     246: iconst_1
     247: goto          251
     250: iconst_0
     251: aload_0
     252: invokevirtual #37                 // Method getVpc:()Ljava/lang/Boolean;
     255: ifnonnull     262
     258: iconst_1
     259: goto          263
     262: iconst_0
     263: ixor
     264: ifeq          269
     267: iconst_0
     268: ireturn
     269: aload_2
     270: invokevirtual #37                 // Method getVpc:()Ljava/lang/Boolean;
     273: ifnull        292
     276: aload_2
     277: invokevirtual #37                 // Method getVpc:()Ljava/lang/Boolean;
     280: aload_0
     281: invokevirtual #37                 // Method getVpc:()Ljava/lang/Boolean;
     284: invokevirtual #49                 // Method java/lang/Boolean.equals:(Ljava/lang/Object;)Z
     287: ifne          292
     290: iconst_0
     291: ireturn
     292: aload_2
     293: invokevirtual #40                 // Method getFilters:()Ljava/util/List;
     296: ifnonnull     303
     299: iconst_1
     300: goto          304
     303: iconst_0
     304: aload_0
     305: invokevirtual #40                 // Method getFilters:()Ljava/util/List;
     308: ifnonnull     315
     311: iconst_1
     312: goto          316
     315: iconst_0
     316: ixor
     317: ifeq          322
     320: iconst_0
     321: ireturn
     322: aload_2
     323: invokevirtual #40                 // Method getFilters:()Ljava/util/List;
     326: ifnull        347
     329: aload_2
     330: invokevirtual #40                 // Method getFilters:()Ljava/util/List;
     333: aload_0
     334: invokevirtual #40                 // Method getFilters:()Ljava/util/List;
     337: invokeinterface #50,  2           // InterfaceMethod java/util/List.equals:(Ljava/lang/Object;)Z
     342: ifne          347
     345: iconst_0
     346: ireturn
     347: aload_2
     348: invokevirtual #42                 // Method getMaxRecords:()Ljava/lang/Integer;
     351: ifnonnull     358
     354: iconst_1
     355: goto          359
     358: iconst_0
     359: aload_0
     360: invokevirtual #42                 // Method getMaxRecords:()Ljava/lang/Integer;
     363: ifnonnull     370
     366: iconst_1
     367: goto          371
     370: iconst_0
     371: ixor
     372: ifeq          377
     375: iconst_0
     376: ireturn
     377: aload_2
     378: invokevirtual #42                 // Method getMaxRecords:()Ljava/lang/Integer;
     381: ifnull        400
     384: aload_2
     385: invokevirtual #42                 // Method getMaxRecords:()Ljava/lang/Integer;
     388: aload_0
     389: invokevirtual #42                 // Method getMaxRecords:()Ljava/lang/Integer;
     392: invokevirtual #51                 // Method java/lang/Integer.equals:(Ljava/lang/Object;)Z
     395: ifne          400
     398: iconst_0
     399: ireturn
     400: aload_2
     401: invokevirtual #44                 // Method getMarker:()Ljava/lang/String;
     404: ifnonnull     411
     407: iconst_1
     408: goto          412
     411: iconst_0
     412: aload_0
     413: invokevirtual #44                 // Method getMarker:()Ljava/lang/String;
     416: ifnonnull     423
     419: iconst_1
     420: goto          424
     423: iconst_0
     424: ixor
     425: ifeq          430
     428: iconst_0
     429: ireturn
     430: aload_2
     431: invokevirtual #44                 // Method getMarker:()Ljava/lang/String;
     434: ifnull        453
     437: aload_2
     438: invokevirtual #44                 // Method getMarker:()Ljava/lang/String;
     441: aload_0
     442: invokevirtual #44                 // Method getMarker:()Ljava/lang/String;
     445: invokevirtual #48                 // Method java/lang/String.equals:(Ljava/lang/Object;)Z
     448: ifne          453
     451: iconst_0
     452: ireturn
     453: iconst_1
     454: ireturn

  public int hashCode();
    Code:
       0: bipush        31
       2: istore_1
       3: iconst_1
       4: istore_2
       5: bipush        31
       7: iload_2
       8: imul
       9: aload_0
      10: invokevirtual #27                 // Method getEngine:()Ljava/lang/String;
      13: ifnonnull     20
      16: iconst_0
      17: goto          27
      20: aload_0
      21: invokevirtual #27                 // Method getEngine:()Ljava/lang/String;
      24: invokevirtual #52                 // Method java/lang/String.hashCode:()I
      27: iadd
      28: istore_2
      29: bipush        31
      31: iload_2
      32: imul
      33: aload_0
      34: invokevirtual #31                 // Method getEngineVersion:()Ljava/lang/String;
      37: ifnonnull     44
      40: iconst_0
      41: goto          51
      44: aload_0
      45: invokevirtual #31                 // Method getEngineVersion:()Ljava/lang/String;
      48: invokevirtual #52                 // Method java/lang/String.hashCode:()I
      51: iadd
      52: istore_2
      53: bipush        31
      55: iload_2
      56: imul
      57: aload_0
      58: invokevirtual #33                 // Method getDBInstanceClass:()Ljava/lang/String;
      61: ifnonnull     68
      64: iconst_0
      65: goto          75
      68: aload_0
      69: invokevirtual #33                 // Method getDBInstanceClass:()Ljava/lang/String;
      72: invokevirtual #52                 // Method java/lang/String.hashCode:()I
      75: iadd
      76: istore_2
      77: bipush        31
      79: iload_2
      80: imul
      81: aload_0
      82: invokevirtual #35                 // Method getLicenseModel:()Ljava/lang/String;
      85: ifnonnull     92
      88: iconst_0
      89: goto          99
      92: aload_0
      93: invokevirtual #35                 // Method getLicenseModel:()Ljava/lang/String;
      96: invokevirtual #52                 // Method java/lang/String.hashCode:()I
      99: iadd
     100: istore_2
     101: bipush        31
     103: iload_2
     104: imul
     105: aload_0
     106: invokevirtual #37                 // Method getVpc:()Ljava/lang/Boolean;
     109: ifnonnull     116
     112: iconst_0
     113: goto          123
     116: aload_0
     117: invokevirtual #37                 // Method getVpc:()Ljava/lang/Boolean;
     120: invokevirtual #53                 // Method java/lang/Boolean.hashCode:()I
     123: iadd
     124: istore_2
     125: bipush        31
     127: iload_2
     128: imul
     129: aload_0
     130: invokevirtual #40                 // Method getFilters:()Ljava/util/List;
     133: ifnonnull     140
     136: iconst_0
     137: goto          149
     140: aload_0
     141: invokevirtual #40                 // Method getFilters:()Ljava/util/List;
     144: invokeinterface #54,  1           // InterfaceMethod java/util/List.hashCode:()I
     149: iadd
     150: istore_2
     151: bipush        31
     153: iload_2
     154: imul
     155: aload_0
     156: invokevirtual #42                 // Method getMaxRecords:()Ljava/lang/Integer;
     159: ifnonnull     166
     162: iconst_0
     163: goto          173
     166: aload_0
     167: invokevirtual #42                 // Method getMaxRecords:()Ljava/lang/Integer;
     170: invokevirtual #55                 // Method java/lang/Integer.hashCode:()I
     173: iadd
     174: istore_2
     175: bipush        31
     177: iload_2
     178: imul
     179: aload_0
     180: invokevirtual #44                 // Method getMarker:()Ljava/lang/String;
     183: ifnonnull     190
     186: iconst_0
     187: goto          197
     190: aload_0
     191: invokevirtual #44                 // Method getMarker:()Ljava/lang/String;
     194: invokevirtual #52                 // Method java/lang/String.hashCode:()I
     197: iadd
     198: istore_2
     199: iload_2
     200: ireturn

  public com.amazonaws.services.rds.model.DescribeOrderableDBInstanceOptionsRequest clone();
    Code:
       0: aload_0
       1: invokespecial #56                 // Method com/amazonaws/AmazonWebServiceRequest.clone:()Lcom/amazonaws/AmazonWebServiceRequest;
       4: checkcast     #47                 // class com/amazonaws/services/rds/model/DescribeOrderableDBInstanceOptionsRequest
       7: areturn

  public com.amazonaws.AmazonWebServiceRequest clone();
    Code:
       0: aload_0
       1: invokevirtual #57                 // Method clone:()Lcom/amazonaws/services/rds/model/DescribeOrderableDBInstanceOptionsRequest;
       4: areturn

  public java.lang.Object clone() throws java.lang.CloneNotSupportedException;
    Code:
       0: aload_0
       1: invokevirtual #57                 // Method clone:()Lcom/amazonaws/services/rds/model/DescribeOrderableDBInstanceOptionsRequest;
       4: areturn
}
