Compiled from "JDKModuleLogger.java"
public final class org.jboss.modules.log.JDKModuleLogger implements org.jboss.modules.log.ModuleLogger {
  private static final java.util.logging.Level TRACE;

  private static final java.util.logging.Level DEBUG;

  private static final java.util.logging.Level WARN;

  private final java.util.logging.Logger logger;

  private final java.util.logging.Logger defineLogger;

  public org.jboss.modules.log.JDKModuleLogger(java.util.logging.Logger, java.util.logging.Logger);
    Code:
       0: aload_0
       1: invokespecial #1                  // Method java/lang/Object."<init>":()V
       4: aload_0
       5: aload_1
       6: putfield      #2                  // Field logger:Ljava/util/logging/Logger;
       9: aload_0
      10: aload_2
      11: putfield      #3                  // Field defineLogger:Ljava/util/logging/Logger;
      14: return

  public org.jboss.modules.log.JDKModuleLogger(java.lang.String);
    Code:
       0: aload_0
       1: aload_1
       2: invokestatic  #4                  // Method java/util/logging/Logger.getLogger:(Ljava/lang/String;)Ljava/util/logging/Logger;
       5: new           #5                  // class java/lang/StringBuilder
       8: dup
       9: invokespecial #6                  // Method java/lang/StringBuilder."<init>":()V
      12: aload_1
      13: invokevirtual #7                  // Method java/lang/StringBuilder.append:(Ljava/lang/String;)Ljava/lang/StringBuilder;
      16: ldc           #8                  // String .define
      18: invokevirtual #7                  // Method java/lang/StringBuilder.append:(Ljava/lang/String;)Ljava/lang/StringBuilder;
      21: invokevirtual #9                  // Method java/lang/StringBuilder.toString:()Ljava/lang/String;
      24: invokestatic  #4                  // Method java/util/logging/Logger.getLogger:(Ljava/lang/String;)Ljava/util/logging/Logger;
      27: invokespecial #10                 // Method "<init>":(Ljava/util/logging/Logger;Ljava/util/logging/Logger;)V
      30: return

  public org.jboss.modules.log.JDKModuleLogger();
    Code:
       0: aload_0
       1: ldc           #11                 // String org.jboss.modules
       3: invokespecial #12                 // Method "<init>":(Ljava/lang/String;)V
       6: return

  private void doLog(java.util.logging.Level, java.lang.String);
    Code:
       0: aload_0
       1: aload_1
       2: aload_2
       3: aconst_null
       4: invokespecial #13                 // Method doLog:(Ljava/util/logging/Level;Ljava/lang/String;Ljava/lang/Throwable;)V
       7: return

  private void doLog(java.util.logging.Level, java.lang.String, java.lang.Throwable);
    Code:
       0: new           #14                 // class org/jboss/modules/log/ModuleLogRecord
       3: dup
       4: aload_1
       5: aload_2
       6: invokespecial #15                 // Method org/jboss/modules/log/ModuleLogRecord."<init>":(Ljava/util/logging/Level;Ljava/lang/String;)V
       9: astore        4
      11: aload         4
      13: aload_0
      14: getfield      #2                  // Field logger:Ljava/util/logging/Logger;
      17: invokevirtual #16                 // Method java/util/logging/Logger.getName:()Ljava/lang/String;
      20: invokevirtual #17                 // Method org/jboss/modules/log/ModuleLogRecord.setLoggerName:(Ljava/lang/String;)V
      23: aload_3
      24: ifnull        33
      27: aload         4
      29: aload_3
      30: invokevirtual #18                 // Method org/jboss/modules/log/ModuleLogRecord.setThrown:(Ljava/lang/Throwable;)V
      33: aload_0
      34: getfield      #2                  // Field logger:Ljava/util/logging/Logger;
      37: aload         4
      39: invokevirtual #19                 // Method java/util/logging/Logger.log:(Ljava/util/logging/LogRecord;)V
      42: goto          47
      45: astore        4
      47: return
    Exception table:
       from    to  target type
           0    42    45   Class java/lang/Throwable

  public void trace(java.lang.String);
    Code:
       0: aload_0
       1: getstatic     #21                 // Field TRACE:Ljava/util/logging/Level;
       4: aload_1
       5: aconst_null
       6: invokespecial #13                 // Method doLog:(Ljava/util/logging/Level;Ljava/lang/String;Ljava/lang/Throwable;)V
       9: return

  public void trace(java.lang.String, java.lang.Object);
    Code:
       0: aload_0
       1: getfield      #2                  // Field logger:Ljava/util/logging/Logger;
       4: getstatic     #21                 // Field TRACE:Ljava/util/logging/Level;
       7: invokevirtual #22                 // Method java/util/logging/Logger.isLoggable:(Ljava/util/logging/Level;)Z
      10: ifeq          33
      13: aload_0
      14: getstatic     #21                 // Field TRACE:Ljava/util/logging/Level;
      17: aload_1
      18: iconst_1
      19: anewarray     #23                 // class java/lang/Object
      22: dup
      23: iconst_0
      24: aload_2
      25: aastore
      26: invokestatic  #24                 // Method java/lang/String.format:(Ljava/lang/String;[Ljava/lang/Object;)Ljava/lang/String;
      29: aconst_null
      30: invokespecial #13                 // Method doLog:(Ljava/util/logging/Level;Ljava/lang/String;Ljava/lang/Throwable;)V
      33: return

  public void trace(java.lang.String, java.lang.Object, java.lang.Object);
    Code:
       0: aload_0
       1: getfield      #2                  // Field logger:Ljava/util/logging/Logger;
       4: getstatic     #21                 // Field TRACE:Ljava/util/logging/Level;
       7: invokevirtual #22                 // Method java/util/logging/Logger.isLoggable:(Ljava/util/logging/Level;)Z
      10: ifeq          36
      13: aload_0
      14: getstatic     #21                 // Field TRACE:Ljava/util/logging/Level;
      17: aload_1
      18: iconst_2
      19: anewarray     #23                 // class java/lang/Object
      22: dup
      23: iconst_0
      24: aload_2
      25: aastore
      26: dup
      27: iconst_1
      28: aload_3
      29: aastore
      30: invokestatic  #24                 // Method java/lang/String.format:(Ljava/lang/String;[Ljava/lang/Object;)Ljava/lang/String;
      33: invokespecial #25                 // Method doLog:(Ljava/util/logging/Level;Ljava/lang/String;)V
      36: return

  public void trace(java.lang.String, java.lang.Object, java.lang.Object, java.lang.Object);
    Code:
       0: aload_0
       1: getfield      #2                  // Field logger:Ljava/util/logging/Logger;
       4: getstatic     #21                 // Field TRACE:Ljava/util/logging/Level;
       7: invokevirtual #22                 // Method java/util/logging/Logger.isLoggable:(Ljava/util/logging/Level;)Z
      10: ifeq          41
      13: aload_0
      14: getstatic     #21                 // Field TRACE:Ljava/util/logging/Level;
      17: aload_1
      18: iconst_3
      19: anewarray     #23                 // class java/lang/Object
      22: dup
      23: iconst_0
      24: aload_2
      25: aastore
      26: dup
      27: iconst_1
      28: aload_3
      29: aastore
      30: dup
      31: iconst_2
      32: aload         4
      34: aastore
      35: invokestatic  #24                 // Method java/lang/String.format:(Ljava/lang/String;[Ljava/lang/Object;)Ljava/lang/String;
      38: invokespecial #25                 // Method doLog:(Ljava/util/logging/Level;Ljava/lang/String;)V
      41: return

  public void trace(java.lang.String, java.lang.Object...);
    Code:
       0: aload_0
       1: getfield      #2                  // Field logger:Ljava/util/logging/Logger;
       4: getstatic     #21                 // Field TRACE:Ljava/util/logging/Level;
       7: invokevirtual #22                 // Method java/util/logging/Logger.isLoggable:(Ljava/util/logging/Level;)Z
      10: ifeq          28
      13: aload_0
      14: getstatic     #21                 // Field TRACE:Ljava/util/logging/Level;
      17: aload_1
      18: aload_2
      19: checkcast     #26                 // class "[Ljava/lang/Object;"
      22: invokestatic  #24                 // Method java/lang/String.format:(Ljava/lang/String;[Ljava/lang/Object;)Ljava/lang/String;
      25: invokespecial #25                 // Method doLog:(Ljava/util/logging/Level;Ljava/lang/String;)V
      28: return

  public void trace(java.lang.Throwable, java.lang.String);
    Code:
       0: aload_0
       1: getstatic     #21                 // Field TRACE:Ljava/util/logging/Level;
       4: aload_2
       5: aload_1
       6: invokespecial #13                 // Method doLog:(Ljava/util/logging/Level;Ljava/lang/String;Ljava/lang/Throwable;)V
       9: return

  public void trace(java.lang.Throwable, java.lang.String, java.lang.Object);
    Code:
       0: aload_0
       1: getfield      #2                  // Field logger:Ljava/util/logging/Logger;
       4: getstatic     #21                 // Field TRACE:Ljava/util/logging/Level;
       7: invokevirtual #22                 // Method java/util/logging/Logger.isLoggable:(Ljava/util/logging/Level;)Z
      10: ifeq          33
      13: aload_0
      14: getstatic     #21                 // Field TRACE:Ljava/util/logging/Level;
      17: aload_2
      18: iconst_1
      19: anewarray     #23                 // class java/lang/Object
      22: dup
      23: iconst_0
      24: aload_3
      25: aastore
      26: invokestatic  #24                 // Method java/lang/String.format:(Ljava/lang/String;[Ljava/lang/Object;)Ljava/lang/String;
      29: aload_1
      30: invokespecial #13                 // Method doLog:(Ljava/util/logging/Level;Ljava/lang/String;Ljava/lang/Throwable;)V
      33: return

  public void trace(java.lang.Throwable, java.lang.String, java.lang.Object, java.lang.Object);
    Code:
       0: aload_0
       1: getfield      #2                  // Field logger:Ljava/util/logging/Logger;
       4: getstatic     #21                 // Field TRACE:Ljava/util/logging/Level;
       7: invokevirtual #22                 // Method java/util/logging/Logger.isLoggable:(Ljava/util/logging/Level;)Z
      10: ifeq          38
      13: aload_0
      14: getstatic     #21                 // Field TRACE:Ljava/util/logging/Level;
      17: aload_2
      18: iconst_2
      19: anewarray     #23                 // class java/lang/Object
      22: dup
      23: iconst_0
      24: aload_3
      25: aastore
      26: dup
      27: iconst_1
      28: aload         4
      30: aastore
      31: invokestatic  #24                 // Method java/lang/String.format:(Ljava/lang/String;[Ljava/lang/Object;)Ljava/lang/String;
      34: aload_1
      35: invokespecial #13                 // Method doLog:(Ljava/util/logging/Level;Ljava/lang/String;Ljava/lang/Throwable;)V
      38: return

  public void trace(java.lang.Throwable, java.lang.String, java.lang.Object, java.lang.Object, java.lang.Object);
    Code:
       0: aload_0
       1: getfield      #2                  // Field logger:Ljava/util/logging/Logger;
       4: getstatic     #21                 // Field TRACE:Ljava/util/logging/Level;
       7: invokevirtual #22                 // Method java/util/logging/Logger.isLoggable:(Ljava/util/logging/Level;)Z
      10: ifeq          43
      13: aload_0
      14: getstatic     #21                 // Field TRACE:Ljava/util/logging/Level;
      17: aload_2
      18: iconst_3
      19: anewarray     #23                 // class java/lang/Object
      22: dup
      23: iconst_0
      24: aload_3
      25: aastore
      26: dup
      27: iconst_1
      28: aload         4
      30: aastore
      31: dup
      32: iconst_2
      33: aload         5
      35: aastore
      36: invokestatic  #24                 // Method java/lang/String.format:(Ljava/lang/String;[Ljava/lang/Object;)Ljava/lang/String;
      39: aload_1
      40: invokespecial #13                 // Method doLog:(Ljava/util/logging/Level;Ljava/lang/String;Ljava/lang/Throwable;)V
      43: return

  public void trace(java.lang.Throwable, java.lang.String, java.lang.Object...);
    Code:
       0: aload_0
       1: getfield      #2                  // Field logger:Ljava/util/logging/Logger;
       4: getstatic     #21                 // Field TRACE:Ljava/util/logging/Level;
       7: invokevirtual #22                 // Method java/util/logging/Logger.isLoggable:(Ljava/util/logging/Level;)Z
      10: ifeq          29
      13: aload_0
      14: getstatic     #21                 // Field TRACE:Ljava/util/logging/Level;
      17: aload_2
      18: aload_3
      19: checkcast     #26                 // class "[Ljava/lang/Object;"
      22: invokestatic  #24                 // Method java/lang/String.format:(Ljava/lang/String;[Ljava/lang/Object;)Ljava/lang/String;
      25: aload_1
      26: invokespecial #13                 // Method doLog:(Ljava/util/logging/Level;Ljava/lang/String;Ljava/lang/Throwable;)V
      29: return

  public void greeting();
    Code:
       0: aload_0
       1: getstatic     #27                 // Field java/util/logging/Level.INFO:Ljava/util/logging/Level;
       4: ldc           #28                 // String JBoss Modules version %s
       6: iconst_1
       7: anewarray     #23                 // class java/lang/Object
      10: dup
      11: iconst_0
      12: invokestatic  #29                 // Method org/jboss/modules/Main.getVersionString:()Ljava/lang/String;
      15: aastore
      16: invokestatic  #24                 // Method java/lang/String.format:(Ljava/lang/String;[Ljava/lang/Object;)Ljava/lang/String;
      19: invokespecial #25                 // Method doLog:(Ljava/util/logging/Level;Ljava/lang/String;)V
      22: return

  public void moduleDefined(org.jboss.modules.ModuleIdentifier, org.jboss.modules.ModuleLoader);
    Code:
       0: aload_0
       1: getfield      #2                  // Field logger:Ljava/util/logging/Logger;
       4: getstatic     #30                 // Field DEBUG:Ljava/util/logging/Level;
       7: invokevirtual #22                 // Method java/util/logging/Logger.isLoggable:(Ljava/util/logging/Level;)Z
      10: ifeq          37
      13: aload_0
      14: getstatic     #30                 // Field DEBUG:Ljava/util/logging/Level;
      17: ldc           #31                 // String Module %s defined by %s
      19: iconst_2
      20: anewarray     #23                 // class java/lang/Object
      23: dup
      24: iconst_0
      25: aload_1
      26: aastore
      27: dup
      28: iconst_1
      29: aload_2
      30: aastore
      31: invokestatic  #24                 // Method java/lang/String.format:(Ljava/lang/String;[Ljava/lang/Object;)Ljava/lang/String;
      34: invokespecial #25                 // Method doLog:(Ljava/util/logging/Level;Ljava/lang/String;)V
      37: return

  public void classDefineFailed(java.lang.Throwable, java.lang.String, org.jboss.modules.Module);
    Code:
       0: aload_0
       1: getfield      #3                  // Field defineLogger:Ljava/util/logging/Logger;
       4: getstatic     #32                 // Field WARN:Ljava/util/logging/Level;
       7: invokevirtual #22                 // Method java/util/logging/Logger.isLoggable:(Ljava/util/logging/Level;)Z
      10: ifeq          38
      13: aload_0
      14: getstatic     #32                 // Field WARN:Ljava/util/logging/Level;
      17: ldc           #33                 // String Failed to define class %s in %s
      19: iconst_2
      20: anewarray     #23                 // class java/lang/Object
      23: dup
      24: iconst_0
      25: aload_2
      26: aastore
      27: dup
      28: iconst_1
      29: aload_3
      30: aastore
      31: invokestatic  #24                 // Method java/lang/String.format:(Ljava/lang/String;[Ljava/lang/Object;)Ljava/lang/String;
      34: aload_1
      35: invokespecial #13                 // Method doLog:(Ljava/util/logging/Level;Ljava/lang/String;Ljava/lang/Throwable;)V
      38: return

  public void classDefined(java.lang.String, org.jboss.modules.Module);
    Code:
       0: aload_0
       1: getfield      #3                  // Field defineLogger:Ljava/util/logging/Logger;
       4: getstatic     #21                 // Field TRACE:Ljava/util/logging/Level;
       7: invokevirtual #22                 // Method java/util/logging/Logger.isLoggable:(Ljava/util/logging/Level;)Z
      10: ifeq          37
      13: aload_0
      14: getstatic     #21                 // Field TRACE:Ljava/util/logging/Level;
      17: ldc           #34                 // String Defined class %s in %s
      19: iconst_2
      20: anewarray     #23                 // class java/lang/Object
      23: dup
      24: iconst_0
      25: aload_1
      26: aastore
      27: dup
      28: iconst_1
      29: aload_2
      30: aastore
      31: invokestatic  #24                 // Method java/lang/String.format:(Ljava/lang/String;[Ljava/lang/Object;)Ljava/lang/String;
      34: invokespecial #25                 // Method doLog:(Ljava/util/logging/Level;Ljava/lang/String;)V
      37: return

  public void providerUnloadable(java.lang.String, java.lang.ClassLoader);
    Code:
       0: aload_0
       1: getfield      #3                  // Field defineLogger:Ljava/util/logging/Logger;
       4: getstatic     #21                 // Field TRACE:Ljava/util/logging/Level;
       7: invokevirtual #22                 // Method java/util/logging/Logger.isLoggable:(Ljava/util/logging/Level;)Z
      10: ifeq          37
      13: aload_0
      14: getstatic     #21                 // Field TRACE:Ljava/util/logging/Level;
      17: ldc           #35                 // String Could not load provider %s in %s
      19: iconst_2
      20: anewarray     #23                 // class java/lang/Object
      23: dup
      24: iconst_0
      25: aload_1
      26: aastore
      27: dup
      28: iconst_1
      29: aload_2
      30: aastore
      31: invokestatic  #24                 // Method java/lang/String.format:(Ljava/lang/String;[Ljava/lang/Object;)Ljava/lang/String;
      34: invokespecial #25                 // Method doLog:(Ljava/util/logging/Level;Ljava/lang/String;)V
      37: return

  static {};
    Code:
       0: ldc           #36                 // String TRACE
       2: invokestatic  #37                 // Method java/util/logging/Level.parse:(Ljava/lang/String;)Ljava/util/logging/Level;
       5: astore_0
       6: goto          14
       9: astore_3
      10: getstatic     #39                 // Field java/util/logging/Level.FINEST:Ljava/util/logging/Level;
      13: astore_0
      14: ldc           #40                 // String DEBUG
      16: invokestatic  #37                 // Method java/util/logging/Level.parse:(Ljava/lang/String;)Ljava/util/logging/Level;
      19: astore_1
      20: goto          28
      23: astore_3
      24: getstatic     #41                 // Field java/util/logging/Level.FINE:Ljava/util/logging/Level;
      27: astore_1
      28: ldc           #42                 // String WARN
      30: invokestatic  #37                 // Method java/util/logging/Level.parse:(Ljava/lang/String;)Ljava/util/logging/Level;
      33: astore_2
      34: goto          42
      37: astore_3
      38: getstatic     #43                 // Field java/util/logging/Level.WARNING:Ljava/util/logging/Level;
      41: astore_2
      42: aload_0
      43: putstatic     #21                 // Field TRACE:Ljava/util/logging/Level;
      46: aload_1
      47: putstatic     #30                 // Field DEBUG:Ljava/util/logging/Level;
      50: aload_2
      51: putstatic     #32                 // Field WARN:Ljava/util/logging/Level;
      54: return
    Exception table:
       from    to  target type
           0     6     9   Class java/lang/IllegalArgumentException
          14    20    23   Class java/lang/IllegalArgumentException
          28    34    37   Class java/lang/IllegalArgumentException
}
