Compiled from "HttpServerLogger_$logger.java"
public class org.jboss.as.domain.http.server.logging.HttpServerLogger_$logger extends org.jboss.logging.DelegatingBasicLogger implements org.jboss.as.domain.http.server.logging.HttpServerLogger,org.jboss.logging.BasicLogger,java.io.Serializable {
  private static final long serialVersionUID;

  private static final java.lang.String FQCN;

  private static final java.lang.String modelRequestError;

  private static final java.lang.String uploadError;

  private static final java.lang.String consoleModuleNotFound;

  private static final java.lang.String errorContextModuleNotFound;

  private static final java.lang.String invalidOperation;

  private static final java.lang.String realmNotReadyMessage;

  private static final java.lang.String consoleModuleNotFoundMsg;

  private static final java.lang.String failedReadingResource;

  private static final java.lang.String invalidResource;

  private static final java.lang.String invalidCredentialType;

  private static final java.lang.String httpsRedirectNotSupported;

  private static final java.lang.String sslRequestedNoSslContext;

  private static final java.lang.String invalidUseStreamAsResponseIndex;

  public org.jboss.as.domain.http.server.logging.HttpServerLogger_$logger(org.jboss.logging.Logger);
    Code:
       0: aload_0
       1: aload_1
       2: invokespecial #1                  // Method org/jboss/logging/DelegatingBasicLogger."<init>":(Lorg/jboss/logging/Logger;)V
       5: return

  public final void modelRequestError(java.lang.Throwable);
    Code:
       0: aload_0
       1: getfield      #2                  // Field org/jboss/logging/DelegatingBasicLogger.log:Lorg/jboss/logging/Logger;
       4: getstatic     #3                  // Field FQCN:Ljava/lang/String;
       7: getstatic     #4                  // Field org/jboss/logging/Logger$Level.ERROR:Lorg/jboss/logging/Logger$Level;
      10: aload_1
      11: aload_0
      12: invokevirtual #5                  // Method modelRequestError$str:()Ljava/lang/String;
      15: iconst_0
      16: anewarray     #6                  // class java/lang/Object
      19: invokevirtual #7                  // Method org/jboss/logging/Logger.logf:(Ljava/lang/String;Lorg/jboss/logging/Logger$Level;Ljava/lang/Throwable;Ljava/lang/String;[Ljava/lang/Object;)V
      22: return

  protected java.lang.String modelRequestError$str();
    Code:
       0: ldc           #9                  // String WFLYDMHTTP0001: Unexpected error executing model request
       2: areturn

  public final void uploadError(java.lang.Throwable);
    Code:
       0: aload_0
       1: getfield      #2                  // Field org/jboss/logging/DelegatingBasicLogger.log:Lorg/jboss/logging/Logger;
       4: getstatic     #3                  // Field FQCN:Ljava/lang/String;
       7: getstatic     #4                  // Field org/jboss/logging/Logger$Level.ERROR:Lorg/jboss/logging/Logger$Level;
      10: aload_1
      11: aload_0
      12: invokevirtual #10                 // Method uploadError$str:()Ljava/lang/String;
      15: iconst_0
      16: anewarray     #6                  // class java/lang/Object
      19: invokevirtual #7                  // Method org/jboss/logging/Logger.logf:(Ljava/lang/String;Lorg/jboss/logging/Logger$Level;Ljava/lang/Throwable;Ljava/lang/String;[Ljava/lang/Object;)V
      22: return

  protected java.lang.String uploadError$str();
    Code:
       0: ldc           #11                 // String WFLYDMHTTP0002: Unexpected error executing deployment upload request
       2: areturn

  public final void consoleModuleNotFound(java.lang.String);
    Code:
       0: aload_0
       1: getfield      #2                  // Field org/jboss/logging/DelegatingBasicLogger.log:Lorg/jboss/logging/Logger;
       4: getstatic     #3                  // Field FQCN:Ljava/lang/String;
       7: getstatic     #12                 // Field org/jboss/logging/Logger$Level.WARN:Lorg/jboss/logging/Logger$Level;
      10: aconst_null
      11: aload_0
      12: invokevirtual #13                 // Method consoleModuleNotFound$str:()Ljava/lang/String;
      15: aload_1
      16: invokevirtual #14                 // Method org/jboss/logging/Logger.logf:(Ljava/lang/String;Lorg/jboss/logging/Logger$Level;Ljava/lang/Throwable;Ljava/lang/String;Ljava/lang/Object;)V
      19: return

  protected java.lang.String consoleModuleNotFound$str();
    Code:
       0: ldc           #15                 // String WFLYDMHTTP0003: Unable to load console module for slot %s, disabling console
       2: areturn

  public final void errorContextModuleNotFound(java.lang.String);
    Code:
       0: aload_0
       1: getfield      #2                  // Field org/jboss/logging/DelegatingBasicLogger.log:Lorg/jboss/logging/Logger;
       4: getstatic     #3                  // Field FQCN:Ljava/lang/String;
       7: getstatic     #4                  // Field org/jboss/logging/Logger$Level.ERROR:Lorg/jboss/logging/Logger$Level;
      10: aconst_null
      11: aload_0
      12: invokevirtual #16                 // Method errorContextModuleNotFound$str:()Ljava/lang/String;
      15: aload_1
      16: invokevirtual #14                 // Method org/jboss/logging/Logger.logf:(Ljava/lang/String;Lorg/jboss/logging/Logger$Level;Ljava/lang/Throwable;Ljava/lang/String;Ljava/lang/Object;)V
      19: return

  protected java.lang.String errorContextModuleNotFound$str();
    Code:
       0: ldc           #17                 // String WFLYDMHTTP0004: Unable to load error context for slot %s, disabling error context.
       2: areturn

  protected java.lang.String invalidOperation$str();
    Code:
       0: ldc           #18                 // String WFLYDMHTTP0005: Invalid operation \'%s\'
       2: areturn

  public final java.lang.IllegalArgumentException invalidOperation(java.lang.Throwable, java.lang.String);
    Code:
       0: new           #19                 // class java/lang/IllegalArgumentException
       3: dup
       4: aload_0
       5: invokevirtual #20                 // Method invalidOperation$str:()Ljava/lang/String;
       8: iconst_1
       9: anewarray     #6                  // class java/lang/Object
      12: dup
      13: iconst_0
      14: aload_2
      15: aastore
      16: invokestatic  #21                 // Method java/lang/String.format:(Ljava/lang/String;[Ljava/lang/Object;)Ljava/lang/String;
      19: aload_1
      20: invokespecial #22                 // Method java/lang/IllegalArgumentException."<init>":(Ljava/lang/String;Ljava/lang/Throwable;)V
      23: astore_3
      24: aload_3
      25: invokevirtual #23                 // Method java/lang/IllegalArgumentException.getStackTrace:()[Ljava/lang/StackTraceElement;
      28: astore        4
      30: aload_3
      31: aload         4
      33: iconst_1
      34: aload         4
      36: arraylength
      37: invokestatic  #24                 // Method java/util/Arrays.copyOfRange:([Ljava/lang/Object;II)[Ljava/lang/Object;
      40: checkcast     #25                 // class "[Ljava/lang/StackTraceElement;"
      43: invokevirtual #26                 // Method java/lang/IllegalArgumentException.setStackTrace:([Ljava/lang/StackTraceElement;)V
      46: aload_3
      47: areturn

  protected java.lang.String realmNotReadyMessage$str();
    Code:
       0: ldc           #27                 // String WFLYDMHTTP0006: The security realm is not ready to process requests, see %s
       2: areturn

  public final java.lang.String realmNotReadyMessage(java.lang.String);
    Code:
       0: aload_0
       1: invokevirtual #28                 // Method realmNotReadyMessage$str:()Ljava/lang/String;
       4: iconst_1
       5: anewarray     #6                  // class java/lang/Object
       8: dup
       9: iconst_0
      10: aload_1
      11: aastore
      12: invokestatic  #21                 // Method java/lang/String.format:(Ljava/lang/String;[Ljava/lang/Object;)Ljava/lang/String;
      15: areturn

  protected java.lang.String consoleModuleNotFoundMsg$str();
    Code:
       0: ldc           #29                 // String WFLYDMHTTP0007: No console module available with module name %s
       2: areturn

  public final org.jboss.modules.ModuleNotFoundException consoleModuleNotFoundMsg(java.lang.String);
    Code:
       0: new           #30                 // class org/jboss/modules/ModuleNotFoundException
       3: dup
       4: aload_0
       5: invokevirtual #31                 // Method consoleModuleNotFoundMsg$str:()Ljava/lang/String;
       8: iconst_1
       9: anewarray     #6                  // class java/lang/Object
      12: dup
      13: iconst_0
      14: aload_1
      15: aastore
      16: invokestatic  #21                 // Method java/lang/String.format:(Ljava/lang/String;[Ljava/lang/Object;)Ljava/lang/String;
      19: invokespecial #32                 // Method org/jboss/modules/ModuleNotFoundException."<init>":(Ljava/lang/String;)V
      22: astore_2
      23: aload_2
      24: invokevirtual #33                 // Method org/jboss/modules/ModuleNotFoundException.getStackTrace:()[Ljava/lang/StackTraceElement;
      27: astore_3
      28: aload_2
      29: aload_3
      30: iconst_1
      31: aload_3
      32: arraylength
      33: invokestatic  #24                 // Method java/util/Arrays.copyOfRange:([Ljava/lang/Object;II)[Ljava/lang/Object;
      36: checkcast     #25                 // class "[Ljava/lang/StackTraceElement;"
      39: invokevirtual #34                 // Method org/jboss/modules/ModuleNotFoundException.setStackTrace:([Ljava/lang/StackTraceElement;)V
      42: aload_2
      43: areturn

  protected java.lang.String failedReadingResource$str();
    Code:
       0: ldc           #35                 // String WFLYDMHTTP0008: Failed to read %s
       2: areturn

  public final java.lang.RuntimeException failedReadingResource(java.lang.Throwable, java.lang.String);
    Code:
       0: new           #36                 // class java/lang/RuntimeException
       3: dup
       4: aload_0
       5: invokevirtual #37                 // Method failedReadingResource$str:()Ljava/lang/String;
       8: iconst_1
       9: anewarray     #6                  // class java/lang/Object
      12: dup
      13: iconst_0
      14: aload_2
      15: aastore
      16: invokestatic  #21                 // Method java/lang/String.format:(Ljava/lang/String;[Ljava/lang/Object;)Ljava/lang/String;
      19: aload_1
      20: invokespecial #38                 // Method java/lang/RuntimeException."<init>":(Ljava/lang/String;Ljava/lang/Throwable;)V
      23: astore_3
      24: aload_3
      25: invokevirtual #39                 // Method java/lang/RuntimeException.getStackTrace:()[Ljava/lang/StackTraceElement;
      28: astore        4
      30: aload_3
      31: aload         4
      33: iconst_1
      34: aload         4
      36: arraylength
      37: invokestatic  #24                 // Method java/util/Arrays.copyOfRange:([Ljava/lang/Object;II)[Ljava/lang/Object;
      40: checkcast     #25                 // class "[Ljava/lang/StackTraceElement;"
      43: invokevirtual #40                 // Method java/lang/RuntimeException.setStackTrace:([Ljava/lang/StackTraceElement;)V
      46: aload_3
      47: areturn

  protected java.lang.String invalidResource$str();
    Code:
       0: ldc           #41                 // String WFLYDMHTTP0009: Invalid resource
       2: areturn

  public final java.lang.String invalidResource();
    Code:
       0: aload_0
       1: invokevirtual #42                 // Method invalidResource$str:()Ljava/lang/String;
       4: iconst_0
       5: anewarray     #6                  // class java/lang/Object
       8: invokestatic  #21                 // Method java/lang/String.format:(Ljava/lang/String;[Ljava/lang/Object;)Ljava/lang/String;
      11: areturn

  protected java.lang.String invalidCredentialType$str();
    Code:
       0: ldc           #43                 // String WFLYDMHTTP0010: Invalid Credential Type \'%s\'
       2: areturn

  public final java.lang.IllegalArgumentException invalidCredentialType(java.lang.String);
    Code:
       0: new           #19                 // class java/lang/IllegalArgumentException
       3: dup
       4: aload_0
       5: invokevirtual #44                 // Method invalidCredentialType$str:()Ljava/lang/String;
       8: iconst_1
       9: anewarray     #6                  // class java/lang/Object
      12: dup
      13: iconst_0
      14: aload_1
      15: aastore
      16: invokestatic  #21                 // Method java/lang/String.format:(Ljava/lang/String;[Ljava/lang/Object;)Ljava/lang/String;
      19: invokespecial #45                 // Method java/lang/IllegalArgumentException."<init>":(Ljava/lang/String;)V
      22: astore_2
      23: aload_2
      24: invokevirtual #23                 // Method java/lang/IllegalArgumentException.getStackTrace:()[Ljava/lang/StackTraceElement;
      27: astore_3
      28: aload_2
      29: aload_3
      30: iconst_1
      31: aload_3
      32: arraylength
      33: invokestatic  #24                 // Method java/util/Arrays.copyOfRange:([Ljava/lang/Object;II)[Ljava/lang/Object;
      36: checkcast     #25                 // class "[Ljava/lang/StackTraceElement;"
      39: invokevirtual #26                 // Method java/lang/IllegalArgumentException.setStackTrace:([Ljava/lang/StackTraceElement;)V
      42: aload_2
      43: areturn

  public final void httpsRedirectNotSupported(java.net.InetAddress, java.net.InetAddress);
    Code:
       0: aload_0
       1: getfield      #2                  // Field org/jboss/logging/DelegatingBasicLogger.log:Lorg/jboss/logging/Logger;
       4: getstatic     #3                  // Field FQCN:Ljava/lang/String;
       7: getstatic     #46                 // Field org/jboss/logging/Logger$Level.INFO:Lorg/jboss/logging/Logger$Level;
      10: aconst_null
      11: aload_0
      12: invokevirtual #47                 // Method httpsRedirectNotSupported$str:()Ljava/lang/String;
      15: aload_1
      16: aload_2
      17: invokevirtual #48                 // Method org/jboss/logging/Logger.logf:(Ljava/lang/String;Lorg/jboss/logging/Logger$Level;Ljava/lang/Throwable;Ljava/lang/String;Ljava/lang/Object;Ljava/lang/Object;)V
      20: return

  protected java.lang.String httpsRedirectNotSupported$str();
    Code:
       0: ldc           #49                 // String WFLYDMHTTP0011: Management interface is using different addresses for HTTP (%s) and HTTPS (%s). Redirection of HTTPS requests from HTTP socket to HTTPS socket will not be supported.
       2: areturn

  protected java.lang.String sslRequestedNoSslContext$str();
    Code:
       0: ldc           #50                 // String WFLYDMHTTP0012: A secure socket has been defined for the HTTP interface, however the referenced security realm is not supplying a SSLContext.
       2: areturn

  public final java.lang.IllegalArgumentException sslRequestedNoSslContext();
    Code:
       0: new           #19                 // class java/lang/IllegalArgumentException
       3: dup
       4: aload_0
       5: invokevirtual #51                 // Method sslRequestedNoSslContext$str:()Ljava/lang/String;
       8: iconst_0
       9: anewarray     #6                  // class java/lang/Object
      12: invokestatic  #21                 // Method java/lang/String.format:(Ljava/lang/String;[Ljava/lang/Object;)Ljava/lang/String;
      15: invokespecial #45                 // Method java/lang/IllegalArgumentException."<init>":(Ljava/lang/String;)V
      18: astore_1
      19: aload_1
      20: invokevirtual #23                 // Method java/lang/IllegalArgumentException.getStackTrace:()[Ljava/lang/StackTraceElement;
      23: astore_2
      24: aload_1
      25: aload_2
      26: iconst_1
      27: aload_2
      28: arraylength
      29: invokestatic  #24                 // Method java/util/Arrays.copyOfRange:([Ljava/lang/Object;II)[Ljava/lang/Object;
      32: checkcast     #25                 // class "[Ljava/lang/StackTraceElement;"
      35: invokevirtual #26                 // Method java/lang/IllegalArgumentException.setStackTrace:([Ljava/lang/StackTraceElement;)V
      38: aload_1
      39: areturn

  protected java.lang.String invalidUseStreamAsResponseIndex$str();
    Code:
       0: ldc           #52                 // String WFLYDMHTTP0013: Invalid useStreamIndex value \'%d\'. The operation response had %d streams attached.
       2: areturn

  public final java.lang.String invalidUseStreamAsResponseIndex(int, int);
    Code:
       0: aload_0
       1: invokevirtual #53                 // Method invalidUseStreamAsResponseIndex$str:()Ljava/lang/String;
       4: iconst_2
       5: anewarray     #6                  // class java/lang/Object
       8: dup
       9: iconst_0
      10: iload_1
      11: invokestatic  #54                 // Method java/lang/Integer.valueOf:(I)Ljava/lang/Integer;
      14: aastore
      15: dup
      16: iconst_1
      17: iload_2
      18: invokestatic  #54                 // Method java/lang/Integer.valueOf:(I)Ljava/lang/Integer;
      21: aastore
      22: invokestatic  #21                 // Method java/lang/String.format:(Ljava/lang/String;[Ljava/lang/Object;)Ljava/lang/String;
      25: areturn

  static {};
    Code:
       0: ldc           #8                  // class org/jboss/as/domain/http/server/logging/HttpServerLogger_$logger
       2: invokevirtual #55                 // Method java/lang/Class.getName:()Ljava/lang/String;
       5: putstatic     #3                  // Field FQCN:Ljava/lang/String;
       8: return
}
