Compiled from "ByteBufferInputStream.java"
public class org.apache.zookeeper.server.ByteBufferInputStream extends java.io.InputStream {
  java.nio.ByteBuffer bb;

  public org.apache.zookeeper.server.ByteBufferInputStream(java.nio.ByteBuffer);
    Code:
       0: aload_0
       1: invokespecial #1                  // Method java/io/InputStream."<init>":()V
       4: aload_0
       5: aload_1
       6: putfield      #2                  // Field bb:Ljava/nio/ByteBuffer;
       9: return

  public int read() throws java.io.IOException;
    Code:
       0: aload_0
       1: getfield      #2                  // Field bb:Ljava/nio/ByteBuffer;
       4: invokevirtual #3                  // Method java/nio/ByteBuffer.remaining:()I
       7: ifne          12
      10: iconst_m1
      11: ireturn
      12: aload_0
      13: getfield      #2                  // Field bb:Ljava/nio/ByteBuffer;
      16: invokevirtual #4                  // Method java/nio/ByteBuffer.get:()B
      19: sipush        255
      22: iand
      23: ireturn

  public int available() throws java.io.IOException;
    Code:
       0: aload_0
       1: getfield      #2                  // Field bb:Ljava/nio/ByteBuffer;
       4: invokevirtual #3                  // Method java/nio/ByteBuffer.remaining:()I
       7: ireturn

  public int read(byte[], int, int) throws java.io.IOException;
    Code:
       0: aload_0
       1: getfield      #2                  // Field bb:Ljava/nio/ByteBuffer;
       4: invokevirtual #3                  // Method java/nio/ByteBuffer.remaining:()I
       7: ifne          12
      10: iconst_m1
      11: ireturn
      12: iload_3
      13: aload_0
      14: getfield      #2                  // Field bb:Ljava/nio/ByteBuffer;
      17: invokevirtual #3                  // Method java/nio/ByteBuffer.remaining:()I
      20: if_icmple     31
      23: aload_0
      24: getfield      #2                  // Field bb:Ljava/nio/ByteBuffer;
      27: invokevirtual #3                  // Method java/nio/ByteBuffer.remaining:()I
      30: istore_3
      31: aload_0
      32: getfield      #2                  // Field bb:Ljava/nio/ByteBuffer;
      35: aload_1
      36: iload_2
      37: iload_3
      38: invokevirtual #5                  // Method java/nio/ByteBuffer.get:([BII)Ljava/nio/ByteBuffer;
      41: pop
      42: iload_3
      43: ireturn

  public int read(byte[]) throws java.io.IOException;
    Code:
       0: aload_0
       1: aload_1
       2: iconst_0
       3: aload_1
       4: arraylength
       5: invokevirtual #6                  // Method read:([BII)I
       8: ireturn

  public long skip(long) throws java.io.IOException;
    Code:
       0: lload_1
       1: lconst_0
       2: lcmp
       3: ifge          8
       6: lconst_0
       7: lreturn
       8: lload_1
       9: aload_0
      10: getfield      #2                  // Field bb:Ljava/nio/ByteBuffer;
      13: invokevirtual #3                  // Method java/nio/ByteBuffer.remaining:()I
      16: i2l
      17: invokestatic  #7                  // Method java/lang/Math.min:(JJ)J
      20: lstore_1
      21: aload_0
      22: getfield      #2                  // Field bb:Ljava/nio/ByteBuffer;
      25: aload_0
      26: getfield      #2                  // Field bb:Ljava/nio/ByteBuffer;
      29: invokevirtual #8                  // Method java/nio/ByteBuffer.position:()I
      32: lload_1
      33: l2i
      34: iadd
      35: invokevirtual #9                  // Method java/nio/ByteBuffer.position:(I)Ljava/nio/Buffer;
      38: pop
      39: lload_1
      40: lreturn

  public static void byteBuffer2Record(java.nio.ByteBuffer, org.apache.jute.Record) throws java.io.IOException;
    Code:
       0: new           #10                 // class org/apache/zookeeper/server/ByteBufferInputStream
       3: dup
       4: aload_0
       5: invokespecial #11                 // Method "<init>":(Ljava/nio/ByteBuffer;)V
       8: invokestatic  #12                 // Method org/apache/jute/BinaryInputArchive.getArchive:(Ljava/io/InputStream;)Lorg/apache/jute/BinaryInputArchive;
      11: astore_2
      12: aload_1
      13: aload_2
      14: ldc           #13                 // String request
      16: invokeinterface #14,  3           // InterfaceMethod org/apache/jute/Record.deserialize:(Lorg/apache/jute/InputArchive;Ljava/lang/String;)V
      21: return
}
