Compiled from "NIOServerCnxnFactory.java"
class org.apache.zookeeper.server.NIOServerCnxnFactory$AcceptThread extends org.apache.zookeeper.server.NIOServerCnxnFactory$AbstractSelectThread {
  private final java.nio.channels.ServerSocketChannel acceptSocket;

  private final java.nio.channels.SelectionKey acceptKey;

  private final org.apache.zookeeper.server.RateLogger acceptErrorLogger;

  private final java.util.Collection<org.apache.zookeeper.server.NIOServerCnxnFactory$SelectorThread> selectorThreads;

  private java.util.Iterator<org.apache.zookeeper.server.NIOServerCnxnFactory$SelectorThread> selectorIterator;

  private volatile boolean reconfiguring;

  final org.apache.zookeeper.server.NIOServerCnxnFactory this$0;

  public org.apache.zookeeper.server.NIOServerCnxnFactory$AcceptThread(java.nio.channels.ServerSocketChannel, java.net.InetSocketAddress, java.util.Set<org.apache.zookeeper.server.NIOServerCnxnFactory$SelectorThread>) throws java.io.IOException;
    Code:
       0: aload_0
       1: aload_1
       2: putfield      #1                  // Field this$0:Lorg/apache/zookeeper/server/NIOServerCnxnFactory;
       5: aload_0
       6: aload_1
       7: new           #2                  // class java/lang/StringBuilder
      10: dup
      11: invokespecial #3                  // Method java/lang/StringBuilder."<init>":()V
      14: ldc           #4                  // String NIOServerCxnFactory.AcceptThread:
      16: invokevirtual #5                  // Method java/lang/StringBuilder.append:(Ljava/lang/String;)Ljava/lang/StringBuilder;
      19: aload_3
      20: invokevirtual #6                  // Method java/lang/StringBuilder.append:(Ljava/lang/Object;)Ljava/lang/StringBuilder;
      23: invokevirtual #7                  // Method java/lang/StringBuilder.toString:()Ljava/lang/String;
      26: invokespecial #8                  // Method org/apache/zookeeper/server/NIOServerCnxnFactory$AbstractSelectThread."<init>":(Lorg/apache/zookeeper/server/NIOServerCnxnFactory;Ljava/lang/String;)V
      29: aload_0
      30: new           #9                  // class org/apache/zookeeper/server/RateLogger
      33: dup
      34: invokestatic  #10                 // Method org/apache/zookeeper/server/NIOServerCnxnFactory.access$000:()Lorg/slf4j/Logger;
      37: invokespecial #11                 // Method org/apache/zookeeper/server/RateLogger."<init>":(Lorg/slf4j/Logger;)V
      40: putfield      #12                 // Field acceptErrorLogger:Lorg/apache/zookeeper/server/RateLogger;
      43: aload_0
      44: iconst_0
      45: putfield      #13                 // Field reconfiguring:Z
      48: aload_0
      49: aload_2
      50: putfield      #14                 // Field acceptSocket:Ljava/nio/channels/ServerSocketChannel;
      53: aload_0
      54: aload_0
      55: getfield      #14                 // Field acceptSocket:Ljava/nio/channels/ServerSocketChannel;
      58: aload_0
      59: getfield      #15                 // Field selector:Ljava/nio/channels/Selector;
      62: bipush        16
      64: invokevirtual #17                 // Method java/nio/channels/ServerSocketChannel.register:(Ljava/nio/channels/Selector;I)Ljava/nio/channels/SelectionKey;
      67: putfield      #18                 // Field acceptKey:Ljava/nio/channels/SelectionKey;
      70: aload_0
      71: new           #19                 // class java/util/ArrayList
      74: dup
      75: aload         4
      77: invokespecial #20                 // Method java/util/ArrayList."<init>":(Ljava/util/Collection;)V
      80: invokestatic  #21                 // Method java/util/Collections.unmodifiableList:(Ljava/util/List;)Ljava/util/List;
      83: putfield      #22                 // Field selectorThreads:Ljava/util/Collection;
      86: aload_0
      87: aload_0
      88: getfield      #22                 // Field selectorThreads:Ljava/util/Collection;
      91: invokeinterface #23,  1           // InterfaceMethod java/util/Collection.iterator:()Ljava/util/Iterator;
      96: putfield      #24                 // Field selectorIterator:Ljava/util/Iterator;
      99: return

  public void run();
    Code:
       0: aload_0
       1: getfield      #1                  // Field this$0:Lorg/apache/zookeeper/server/NIOServerCnxnFactory;
       4: invokestatic  #25                 // Method org/apache/zookeeper/server/NIOServerCnxnFactory.access$100:(Lorg/apache/zookeeper/server/NIOServerCnxnFactory;)Z
       7: ifne          60
      10: aload_0
      11: getfield      #14                 // Field acceptSocket:Ljava/nio/channels/ServerSocketChannel;
      14: invokevirtual #26                 // Method java/nio/channels/ServerSocketChannel.socket:()Ljava/net/ServerSocket;
      17: invokevirtual #27                 // Method java/net/ServerSocket.isClosed:()Z
      20: ifne          60
      23: aload_0
      24: invokespecial #28                 // Method select:()V
      27: goto          0
      30: astore_1
      31: invokestatic  #10                 // Method org/apache/zookeeper/server/NIOServerCnxnFactory.access$000:()Lorg/slf4j/Logger;
      34: ldc           #30                 // String Ignoring unexpected runtime exception
      36: aload_1
      37: invokeinterface #31,  3           // InterfaceMethod org/slf4j/Logger.warn:(Ljava/lang/String;Ljava/lang/Throwable;)V
      42: goto          0
      45: astore_1
      46: invokestatic  #10                 // Method org/apache/zookeeper/server/NIOServerCnxnFactory.access$000:()Lorg/slf4j/Logger;
      49: ldc           #33                 // String Ignoring unexpected exception
      51: aload_1
      52: invokeinterface #31,  3           // InterfaceMethod org/slf4j/Logger.warn:(Ljava/lang/String;Ljava/lang/Throwable;)V
      57: goto          0
      60: aload_0
      61: invokevirtual #34                 // Method closeSelector:()V
      64: aload_0
      65: getfield      #13                 // Field reconfiguring:Z
      68: ifne          78
      71: aload_0
      72: getfield      #1                  // Field this$0:Lorg/apache/zookeeper/server/NIOServerCnxnFactory;
      75: invokevirtual #35                 // Method org/apache/zookeeper/server/NIOServerCnxnFactory.stop:()V
      78: invokestatic  #10                 // Method org/apache/zookeeper/server/NIOServerCnxnFactory.access$000:()Lorg/slf4j/Logger;
      81: ldc           #36                 // String accept thread exitted run method
      83: invokeinterface #37,  2           // InterfaceMethod org/slf4j/Logger.info:(Ljava/lang/String;)V
      88: goto          122
      91: astore_2
      92: aload_0
      93: invokevirtual #34                 // Method closeSelector:()V
      96: aload_0
      97: getfield      #13                 // Field reconfiguring:Z
     100: ifne          110
     103: aload_0
     104: getfield      #1                  // Field this$0:Lorg/apache/zookeeper/server/NIOServerCnxnFactory;
     107: invokevirtual #35                 // Method org/apache/zookeeper/server/NIOServerCnxnFactory.stop:()V
     110: invokestatic  #10                 // Method org/apache/zookeeper/server/NIOServerCnxnFactory.access$000:()Lorg/slf4j/Logger;
     113: ldc           #36                 // String accept thread exitted run method
     115: invokeinterface #37,  2           // InterfaceMethod org/slf4j/Logger.info:(Ljava/lang/String;)V
     120: aload_2
     121: athrow
     122: return
    Exception table:
       from    to  target type
          23    27    30   Class java/lang/RuntimeException
          23    27    45   Class java/lang/Exception
           0    60    91   any

  public void setReconfiguring();
    Code:
       0: aload_0
       1: iconst_1
       2: putfield      #13                 // Field reconfiguring:Z
       5: return

  private void select();
    Code:
       0: aload_0
       1: getfield      #15                 // Field selector:Ljava/nio/channels/Selector;
       4: invokevirtual #38                 // Method java/nio/channels/Selector.select:()I
       7: pop
       8: aload_0
       9: getfield      #15                 // Field selector:Ljava/nio/channels/Selector;
      12: invokevirtual #39                 // Method java/nio/channels/Selector.selectedKeys:()Ljava/util/Set;
      15: invokeinterface #40,  1           // InterfaceMethod java/util/Set.iterator:()Ljava/util/Iterator;
      20: astore_1
      21: aload_0
      22: getfield      #1                  // Field this$0:Lorg/apache/zookeeper/server/NIOServerCnxnFactory;
      25: invokestatic  #25                 // Method org/apache/zookeeper/server/NIOServerCnxnFactory.access$100:(Lorg/apache/zookeeper/server/NIOServerCnxnFactory;)Z
      28: ifne          110
      31: aload_1
      32: invokeinterface #41,  1           // InterfaceMethod java/util/Iterator.hasNext:()Z
      37: ifeq          110
      40: aload_1
      41: invokeinterface #42,  1           // InterfaceMethod java/util/Iterator.next:()Ljava/lang/Object;
      46: checkcast     #16                 // class java/nio/channels/SelectionKey
      49: astore_2
      50: aload_1
      51: invokeinterface #43,  1           // InterfaceMethod java/util/Iterator.remove:()V
      56: aload_2
      57: invokevirtual #44                 // Method java/nio/channels/SelectionKey.isValid:()Z
      60: ifne          66
      63: goto          21
      66: aload_2
      67: invokevirtual #45                 // Method java/nio/channels/SelectionKey.isAcceptable:()Z
      70: ifeq          90
      73: aload_0
      74: invokespecial #46                 // Method doAccept:()Z
      77: ifne          107
      80: aload_0
      81: ldc2_w        #47                 // long 10l
      84: invokespecial #49                 // Method pauseAccept:(J)V
      87: goto          107
      90: invokestatic  #10                 // Method org/apache/zookeeper/server/NIOServerCnxnFactory.access$000:()Lorg/slf4j/Logger;
      93: ldc           #50                 // String Unexpected ops in accept select {}
      95: aload_2
      96: invokevirtual #51                 // Method java/nio/channels/SelectionKey.readyOps:()I
      99: invokestatic  #52                 // Method java/lang/Integer.valueOf:(I)Ljava/lang/Integer;
     102: invokeinterface #53,  3           // InterfaceMethod org/slf4j/Logger.warn:(Ljava/lang/String;Ljava/lang/Object;)V
     107: goto          21
     110: goto          125
     113: astore_1
     114: invokestatic  #10                 // Method org/apache/zookeeper/server/NIOServerCnxnFactory.access$000:()Lorg/slf4j/Logger;
     117: ldc           #55                 // String Ignoring IOException while selecting
     119: aload_1
     120: invokeinterface #31,  3           // InterfaceMethod org/slf4j/Logger.warn:(Ljava/lang/String;Ljava/lang/Throwable;)V
     125: return
    Exception table:
       from    to  target type
           0   110   113   Class java/io/IOException

  private void pauseAccept(long);
    Code:
       0: aload_0
       1: getfield      #18                 // Field acceptKey:Ljava/nio/channels/SelectionKey;
       4: iconst_0
       5: invokevirtual #56                 // Method java/nio/channels/SelectionKey.interestOps:(I)Ljava/nio/channels/SelectionKey;
       8: pop
       9: aload_0
      10: getfield      #15                 // Field selector:Ljava/nio/channels/Selector;
      13: lload_1
      14: invokevirtual #57                 // Method java/nio/channels/Selector.select:(J)I
      17: pop
      18: aload_0
      19: getfield      #18                 // Field acceptKey:Ljava/nio/channels/SelectionKey;
      22: bipush        16
      24: invokevirtual #56                 // Method java/nio/channels/SelectionKey.interestOps:(I)Ljava/nio/channels/SelectionKey;
      27: pop
      28: goto          60
      31: astore_3
      32: aload_0
      33: getfield      #18                 // Field acceptKey:Ljava/nio/channels/SelectionKey;
      36: bipush        16
      38: invokevirtual #56                 // Method java/nio/channels/SelectionKey.interestOps:(I)Ljava/nio/channels/SelectionKey;
      41: pop
      42: goto          60
      45: astore        4
      47: aload_0
      48: getfield      #18                 // Field acceptKey:Ljava/nio/channels/SelectionKey;
      51: bipush        16
      53: invokevirtual #56                 // Method java/nio/channels/SelectionKey.interestOps:(I)Ljava/nio/channels/SelectionKey;
      56: pop
      57: aload         4
      59: athrow
      60: return
    Exception table:
       from    to  target type
           9    18    31   Class java/io/IOException
           9    18    45   any
          45    47    45   any

  private boolean doAccept();
    Code:
       0: iconst_0
       1: istore_1
       2: aconst_null
       3: astore_2
       4: aload_0
       5: getfield      #14                 // Field acceptSocket:Ljava/nio/channels/ServerSocketChannel;
       8: invokevirtual #58                 // Method java/nio/channels/ServerSocketChannel.accept:()Ljava/nio/channels/SocketChannel;
      11: astore_2
      12: iconst_1
      13: istore_1
      14: aload_0
      15: getfield      #1                  // Field this$0:Lorg/apache/zookeeper/server/NIOServerCnxnFactory;
      18: invokevirtual #59                 // Method org/apache/zookeeper/server/NIOServerCnxnFactory.limitTotalNumberOfCnxns:()Z
      21: ifeq          57
      24: new           #54                 // class java/io/IOException
      27: dup
      28: new           #2                  // class java/lang/StringBuilder
      31: dup
      32: invokespecial #3                  // Method java/lang/StringBuilder."<init>":()V
      35: ldc           #60                 // String Too many connections max allowed is
      37: invokevirtual #5                  // Method java/lang/StringBuilder.append:(Ljava/lang/String;)Ljava/lang/StringBuilder;
      40: aload_0
      41: getfield      #1                  // Field this$0:Lorg/apache/zookeeper/server/NIOServerCnxnFactory;
      44: getfield      #61                 // Field org/apache/zookeeper/server/NIOServerCnxnFactory.maxCnxns:I
      47: invokevirtual #62                 // Method java/lang/StringBuilder.append:(I)Ljava/lang/StringBuilder;
      50: invokevirtual #7                  // Method java/lang/StringBuilder.toString:()Ljava/lang/String;
      53: invokespecial #63                 // Method java/io/IOException."<init>":(Ljava/lang/String;)V
      56: athrow
      57: aload_2
      58: invokevirtual #64                 // Method java/nio/channels/SocketChannel.socket:()Ljava/net/Socket;
      61: invokevirtual #65                 // Method java/net/Socket.getInetAddress:()Ljava/net/InetAddress;
      64: astore_3
      65: aload_0
      66: getfield      #1                  // Field this$0:Lorg/apache/zookeeper/server/NIOServerCnxnFactory;
      69: aload_3
      70: invokestatic  #66                 // Method org/apache/zookeeper/server/NIOServerCnxnFactory.access$200:(Lorg/apache/zookeeper/server/NIOServerCnxnFactory;Ljava/net/InetAddress;)I
      73: istore        4
      75: aload_0
      76: getfield      #1                  // Field this$0:Lorg/apache/zookeeper/server/NIOServerCnxnFactory;
      79: getfield      #67                 // Field org/apache/zookeeper/server/NIOServerCnxnFactory.maxClientCnxns:I
      82: ifle          139
      85: iload         4
      87: aload_0
      88: getfield      #1                  // Field this$0:Lorg/apache/zookeeper/server/NIOServerCnxnFactory;
      91: getfield      #67                 // Field org/apache/zookeeper/server/NIOServerCnxnFactory.maxClientCnxns:I
      94: if_icmplt     139
      97: new           #54                 // class java/io/IOException
     100: dup
     101: new           #2                  // class java/lang/StringBuilder
     104: dup
     105: invokespecial #3                  // Method java/lang/StringBuilder."<init>":()V
     108: ldc           #68                 // String Too many connections from
     110: invokevirtual #5                  // Method java/lang/StringBuilder.append:(Ljava/lang/String;)Ljava/lang/StringBuilder;
     113: aload_3
     114: invokevirtual #6                  // Method java/lang/StringBuilder.append:(Ljava/lang/Object;)Ljava/lang/StringBuilder;
     117: ldc           #69                 // String  - max is
     119: invokevirtual #5                  // Method java/lang/StringBuilder.append:(Ljava/lang/String;)Ljava/lang/StringBuilder;
     122: aload_0
     123: getfield      #1                  // Field this$0:Lorg/apache/zookeeper/server/NIOServerCnxnFactory;
     126: getfield      #67                 // Field org/apache/zookeeper/server/NIOServerCnxnFactory.maxClientCnxns:I
     129: invokevirtual #62                 // Method java/lang/StringBuilder.append:(I)Ljava/lang/StringBuilder;
     132: invokevirtual #7                  // Method java/lang/StringBuilder.toString:()Ljava/lang/String;
     135: invokespecial #63                 // Method java/io/IOException."<init>":(Ljava/lang/String;)V
     138: athrow
     139: invokestatic  #10                 // Method org/apache/zookeeper/server/NIOServerCnxnFactory.access$000:()Lorg/slf4j/Logger;
     142: ldc           #70                 // String Accepted socket connection from {}
     144: aload_2
     145: invokevirtual #64                 // Method java/nio/channels/SocketChannel.socket:()Ljava/net/Socket;
     148: invokevirtual #71                 // Method java/net/Socket.getRemoteSocketAddress:()Ljava/net/SocketAddress;
     151: invokeinterface #72,  3           // InterfaceMethod org/slf4j/Logger.debug:(Ljava/lang/String;Ljava/lang/Object;)V
     156: aload_2
     157: iconst_0
     158: invokevirtual #73                 // Method java/nio/channels/SocketChannel.configureBlocking:(Z)Ljava/nio/channels/SelectableChannel;
     161: pop
     162: aload_0
     163: getfield      #24                 // Field selectorIterator:Ljava/util/Iterator;
     166: invokeinterface #41,  1           // InterfaceMethod java/util/Iterator.hasNext:()Z
     171: ifne          187
     174: aload_0
     175: aload_0
     176: getfield      #22                 // Field selectorThreads:Ljava/util/Collection;
     179: invokeinterface #23,  1           // InterfaceMethod java/util/Collection.iterator:()Ljava/util/Iterator;
     184: putfield      #24                 // Field selectorIterator:Ljava/util/Iterator;
     187: aload_0
     188: getfield      #24                 // Field selectorIterator:Ljava/util/Iterator;
     191: invokeinterface #42,  1           // InterfaceMethod java/util/Iterator.next:()Ljava/lang/Object;
     196: checkcast     #74                 // class org/apache/zookeeper/server/NIOServerCnxnFactory$SelectorThread
     199: astore        5
     201: aload         5
     203: aload_2
     204: invokevirtual #75                 // Method org/apache/zookeeper/server/NIOServerCnxnFactory$SelectorThread.addAcceptedConnection:(Ljava/nio/channels/SocketChannel;)Z
     207: ifne          253
     210: new           #54                 // class java/io/IOException
     213: dup
     214: new           #2                  // class java/lang/StringBuilder
     217: dup
     218: invokespecial #3                  // Method java/lang/StringBuilder."<init>":()V
     221: ldc           #76                 // String Unable to add connection to selector queue
     223: invokevirtual #5                  // Method java/lang/StringBuilder.append:(Ljava/lang/String;)Ljava/lang/StringBuilder;
     226: aload_0
     227: getfield      #1                  // Field this$0:Lorg/apache/zookeeper/server/NIOServerCnxnFactory;
     230: invokestatic  #25                 // Method org/apache/zookeeper/server/NIOServerCnxnFactory.access$100:(Lorg/apache/zookeeper/server/NIOServerCnxnFactory;)Z
     233: ifeq          241
     236: ldc           #77                 // String  (shutdown in progress)
     238: goto          243
     241: ldc           #78                 // String
     243: invokevirtual #5                  // Method java/lang/StringBuilder.append:(Ljava/lang/String;)Ljava/lang/StringBuilder;
     246: invokevirtual #7                  // Method java/lang/StringBuilder.toString:()Ljava/lang/String;
     249: invokespecial #63                 // Method java/io/IOException."<init>":(Ljava/lang/String;)V
     252: athrow
     253: aload_0
     254: getfield      #12                 // Field acceptErrorLogger:Lorg/apache/zookeeper/server/RateLogger;
     257: invokevirtual #79                 // Method org/apache/zookeeper/server/RateLogger.flush:()V
     260: goto          310
     263: astore_3
     264: invokestatic  #80                 // Method org/apache/zookeeper/server/ServerMetrics.getMetrics:()Lorg/apache/zookeeper/server/ServerMetrics;
     267: getfield      #81                 // Field org/apache/zookeeper/server/ServerMetrics.CONNECTION_REJECTED:Lorg/apache/zookeeper/metrics/Counter;
     270: lconst_1
     271: invokeinterface #82,  3           // InterfaceMethod org/apache/zookeeper/metrics/Counter.add:(J)V
     276: aload_0
     277: getfield      #12                 // Field acceptErrorLogger:Lorg/apache/zookeeper/server/RateLogger;
     280: new           #2                  // class java/lang/StringBuilder
     283: dup
     284: invokespecial #3                  // Method java/lang/StringBuilder."<init>":()V
     287: ldc           #83                 // String Error accepting new connection:
     289: invokevirtual #5                  // Method java/lang/StringBuilder.append:(Ljava/lang/String;)Ljava/lang/StringBuilder;
     292: aload_3
     293: invokevirtual #84                 // Method java/io/IOException.getMessage:()Ljava/lang/String;
     296: invokevirtual #5                  // Method java/lang/StringBuilder.append:(Ljava/lang/String;)Ljava/lang/StringBuilder;
     299: invokevirtual #7                  // Method java/lang/StringBuilder.toString:()Ljava/lang/String;
     302: invokevirtual #85                 // Method org/apache/zookeeper/server/RateLogger.rateLimitLog:(Ljava/lang/String;)V
     305: aload_0
     306: aload_2
     307: invokevirtual #86                 // Method fastCloseSock:(Ljava/nio/channels/SocketChannel;)V
     310: iload_1
     311: ireturn
    Exception table:
       from    to  target type
           4   260   263   Class java/io/IOException
}
