Compiled from "ZooKeeperServer.java"
class org.apache.zookeeper.server.ZooKeeperServer$PrecalculatedDigest {
  final long nodeDigest;

  final long treeDigest;

  org.apache.zookeeper.server.ZooKeeperServer$PrecalculatedDigest(long, long);
    Code:
       0: aload_0
       1: invokespecial #1                  // Method java/lang/Object."<init>":()V
       4: aload_0
       5: lload_1
       6: putfield      #2                  // Field nodeDigest:J
       9: aload_0
      10: lload_3
      11: putfield      #3                  // Field treeDigest:J
      14: return
}
