Compiled from "WordSet.java"
public final class com.ctc.wstx.util.WordSet {
  static final char CHAR_NULL;

  static final int NEGATIVE_OFFSET;

  static final int MIN_BINARY_SEARCH;

  final char[] mData;

  private com.ctc.wstx.util.WordSet(char[]);
    Code:
       0: aload_0
       1: invokespecial #1                  // Method java/lang/Object."<init>":()V
       4: aload_0
       5: aload_1
       6: putfield      #2                  // Field mData:[C
       9: return

  public static com.ctc.wstx.util.WordSet constructSet(java.util.TreeSet);
    Code:
       0: new           #3                  // class com/ctc/wstx/util/WordSet
       3: dup
       4: new           #4                  // class com/ctc/wstx/util/WordSet$Builder
       7: dup
       8: aload_0
       9: invokespecial #5                  // Method com/ctc/wstx/util/WordSet$Builder."<init>":(Ljava/util/TreeSet;)V
      12: invokevirtual #6                  // Method com/ctc/wstx/util/WordSet$Builder.construct:()[C
      15: invokespecial #7                  // Method "<init>":([C)V
      18: areturn

  public static char[] constructRaw(java.util.TreeSet);
    Code:
       0: new           #4                  // class com/ctc/wstx/util/WordSet$Builder
       3: dup
       4: aload_0
       5: invokespecial #5                  // Method com/ctc/wstx/util/WordSet$Builder."<init>":(Ljava/util/TreeSet;)V
       8: invokevirtual #6                  // Method com/ctc/wstx/util/WordSet$Builder.construct:()[C
      11: areturn

  public boolean contains(char[], int, int);
    Code:
       0: aload_0
       1: getfield      #2                  // Field mData:[C
       4: aload_1
       5: iload_2
       6: iload_3
       7: invokestatic  #8                  // Method contains:([C[CII)Z
      10: ireturn

  public static boolean contains(char[], char[], int, int);
    Code:
       0: iconst_0
       1: istore        4
       3: iload_3
       4: iload_2
       5: isub
       6: istore        5
       8: iload         5
      10: ifne          28
      13: aload_0
      14: iload         4
      16: iconst_1
      17: iadd
      18: caload
      19: ifne          26
      22: iconst_1
      23: goto          27
      26: iconst_0
      27: ireturn
      28: aload_0
      29: iload         4
      31: iinc          4, 1
      34: caload
      35: istore        6
      37: iload         6
      39: ldc           #9                  // int 49152
      41: if_icmplt     88
      44: iload         6
      46: ldc           #9                  // int 49152
      48: isub
      49: istore        7
      51: iload         5
      53: iload         7
      55: if_icmpeq     60
      58: iconst_0
      59: ireturn
      60: iload_2
      61: iload_3
      62: if_icmpge     86
      65: aload_0
      66: iload         4
      68: caload
      69: aload_1
      70: iload_2
      71: caload
      72: if_icmpeq     77
      75: iconst_0
      76: ireturn
      77: iinc          4, 1
      80: iinc          2, 1
      83: goto          60
      86: iconst_1
      87: ireturn
      88: aload_1
      89: iload_2
      90: iinc          2, 1
      93: caload
      94: istore        7
      96: iload         6
      98: bipush        7
     100: if_icmpge     192
     103: aload_0
     104: iload         4
     106: caload
     107: iload         7
     109: if_icmpne     123
     112: aload_0
     113: iload         4
     115: iconst_1
     116: iadd
     117: caload
     118: istore        4
     120: goto          279
     123: aload_0
     124: iload         4
     126: iconst_2
     127: iadd
     128: caload
     129: iload         7
     131: if_icmpne     145
     134: aload_0
     135: iload         4
     137: iconst_3
     138: iadd
     139: caload
     140: istore        4
     142: goto          279
     145: iload         4
     147: iload         6
     149: iconst_1
     150: ishl
     151: iadd
     152: istore        8
     154: iinc          4, 4
     157: iload         4
     159: iload         8
     161: if_icmpge     190
     164: aload_0
     165: iload         4
     167: caload
     168: iload         7
     170: if_icmpne     184
     173: aload_0
     174: iload         4
     176: iconst_1
     177: iadd
     178: caload
     179: istore        4
     181: goto          279
     184: iinc          4, 2
     187: goto          157
     190: iconst_0
     191: ireturn
     192: iconst_0
     193: istore        8
     195: iload         6
     197: iconst_1
     198: isub
     199: istore        9
     201: iload         8
     203: iload         9
     205: if_icmpgt     277
     208: iload         8
     210: iload         9
     212: iadd
     213: iconst_1
     214: ishr
     215: istore        10
     217: iload         4
     219: iload         10
     221: iconst_1
     222: ishl
     223: iadd
     224: istore        11
     226: aload_0
     227: iload         11
     229: caload
     230: iload         7
     232: isub
     233: istore        12
     235: iload         12
     237: ifle          249
     240: iload         10
     242: iconst_1
     243: isub
     244: istore        9
     246: goto          274
     249: iload         12
     251: ifge          263
     254: iload         10
     256: iconst_1
     257: iadd
     258: istore        8
     260: goto          274
     263: aload_0
     264: iload         11
     266: iconst_1
     267: iadd
     268: caload
     269: istore        4
     271: goto          279
     274: goto          201
     277: iconst_0
     278: ireturn
     279: iload         4
     281: ifne          3
     284: iload_2
     285: iload_3
     286: if_icmpne     293
     289: iconst_1
     290: goto          294
     293: iconst_0
     294: ireturn

  public boolean contains(java.lang.String);
    Code:
       0: aload_0
       1: getfield      #2                  // Field mData:[C
       4: aload_1
       5: invokestatic  #10                 // Method contains:([CLjava/lang/String;)Z
       8: ireturn

  public static boolean contains(char[], java.lang.String);
    Code:
       0: iconst_0
       1: istore_2
       2: iconst_0
       3: istore_3
       4: aload_1
       5: invokevirtual #11                 // Method java/lang/String.length:()I
       8: istore        4
      10: iload         4
      12: iload_3
      13: isub
      14: istore        5
      16: iload         5
      18: ifne          35
      21: aload_0
      22: iload_2
      23: iconst_1
      24: iadd
      25: caload
      26: ifne          33
      29: iconst_1
      30: goto          34
      33: iconst_0
      34: ireturn
      35: aload_0
      36: iload_2
      37: iinc          2, 1
      40: caload
      41: istore        6
      43: iload         6
      45: ldc           #9                  // int 49152
      47: if_icmplt     96
      50: iload         6
      52: ldc           #9                  // int 49152
      54: isub
      55: istore        7
      57: iload         5
      59: iload         7
      61: if_icmpeq     66
      64: iconst_0
      65: ireturn
      66: iload_3
      67: iload         4
      69: if_icmpge     94
      72: aload_0
      73: iload_2
      74: caload
      75: aload_1
      76: iload_3
      77: invokevirtual #12                 // Method java/lang/String.charAt:(I)C
      80: if_icmpeq     85
      83: iconst_0
      84: ireturn
      85: iinc          2, 1
      88: iinc          3, 1
      91: goto          66
      94: iconst_1
      95: ireturn
      96: aload_1
      97: iload_3
      98: iinc          3, 1
     101: invokevirtual #12                 // Method java/lang/String.charAt:(I)C
     104: istore        7
     106: iload         6
     108: bipush        7
     110: if_icmpge     191
     113: aload_0
     114: iload_2
     115: caload
     116: iload         7
     118: if_icmpne     130
     121: aload_0
     122: iload_2
     123: iconst_1
     124: iadd
     125: caload
     126: istore_2
     127: goto          276
     130: aload_0
     131: iload_2
     132: iconst_2
     133: iadd
     134: caload
     135: iload         7
     137: if_icmpne     149
     140: aload_0
     141: iload_2
     142: iconst_3
     143: iadd
     144: caload
     145: istore_2
     146: goto          276
     149: iload_2
     150: iload         6
     152: iconst_1
     153: ishl
     154: iadd
     155: istore        8
     157: iinc          2, 4
     160: iload_2
     161: iload         8
     163: if_icmpge     189
     166: aload_0
     167: iload_2
     168: caload
     169: iload         7
     171: if_icmpne     183
     174: aload_0
     175: iload_2
     176: iconst_1
     177: iadd
     178: caload
     179: istore_2
     180: goto          276
     183: iinc          2, 2
     186: goto          160
     189: iconst_0
     190: ireturn
     191: iconst_0
     192: istore        8
     194: iload         6
     196: iconst_1
     197: isub
     198: istore        9
     200: iload         8
     202: iload         9
     204: if_icmpgt     274
     207: iload         8
     209: iload         9
     211: iadd
     212: iconst_1
     213: ishr
     214: istore        10
     216: iload_2
     217: iload         10
     219: iconst_1
     220: ishl
     221: iadd
     222: istore        11
     224: aload_0
     225: iload         11
     227: caload
     228: iload         7
     230: isub
     231: istore        12
     233: iload         12
     235: ifle          247
     238: iload         10
     240: iconst_1
     241: isub
     242: istore        9
     244: goto          271
     247: iload         12
     249: ifge          261
     252: iload         10
     254: iconst_1
     255: iadd
     256: istore        8
     258: goto          271
     261: aload_0
     262: iload         11
     264: iconst_1
     265: iadd
     266: caload
     267: istore_2
     268: goto          276
     271: goto          200
     274: iconst_0
     275: ireturn
     276: iload_2
     277: ifne          10
     280: iload_3
     281: iload         4
     283: if_icmpne     290
     286: iconst_1
     287: goto          291
     290: iconst_0
     291: ireturn
}
