Compiled from "FallbackMLog.java"
final class com.mchange.v2.log.FallbackMLog$FallbackMLogger implements com.mchange.v2.log.MLogger {
  com.mchange.v2.log.MLevel cutoffLevel;

  private com.mchange.v2.log.FallbackMLog$FallbackMLogger();
    Code:
       0: aload_0
       1: invokespecial #2                  // Method java/lang/Object."<init>":()V
       4: aload_0
       5: getstatic     #3                  // Field com/mchange/v2/log/FallbackMLog.DEFAULT_CUTOFF_LEVEL:Lcom/mchange/v2/log/MLevel;
       8: putfield      #4                  // Field cutoffLevel:Lcom/mchange/v2/log/MLevel;
      11: return

  private void formatrb(com.mchange.v2.log.MLevel, java.lang.String, java.lang.String, java.lang.String, java.lang.String, java.lang.Object[], java.lang.Throwable);
    Code:
       0: aload         4
       2: invokestatic  #5                  // Method java/util/ResourceBundle.getBundle:(Ljava/lang/String;)Ljava/util/ResourceBundle;
       5: astore        8
       7: aload         5
       9: ifnull        35
      12: aload         8
      14: ifnull        35
      17: aload         8
      19: aload         5
      21: invokevirtual #6                  // Method java/util/ResourceBundle.getString:(Ljava/lang/String;)Ljava/lang/String;
      24: astore        9
      26: aload         9
      28: ifnull        35
      31: aload         9
      33: astore        5
      35: aload_0
      36: aload_1
      37: aload_2
      38: aload_3
      39: aload         5
      41: aload         6
      43: aload         7
      45: invokespecial #7                  // Method format:(Lcom/mchange/v2/log/MLevel;Ljava/lang/String;Ljava/lang/String;Ljava/lang/String;[Ljava/lang/Object;Ljava/lang/Throwable;)V
      48: return

  private void format(com.mchange.v2.log.MLevel, java.lang.String, java.lang.String, java.lang.String, java.lang.Object[], java.lang.Throwable);
    Code:
       0: getstatic     #8                  // Field java/lang/System.err:Ljava/io/PrintStream;
       3: aload_0
       4: aload_1
       5: aload_2
       6: aload_3
       7: aload         4
       9: aload         5
      11: aload         6
      13: invokespecial #9                  // Method formatString:(Lcom/mchange/v2/log/MLevel;Ljava/lang/String;Ljava/lang/String;Ljava/lang/String;[Ljava/lang/Object;Ljava/lang/Throwable;)Ljava/lang/String;
      16: invokevirtual #10                 // Method java/io/PrintStream.println:(Ljava/lang/String;)V
      19: return

  private java.lang.String formatString(com.mchange.v2.log.MLevel, java.lang.String, java.lang.String, java.lang.String, java.lang.Object[], java.lang.Throwable);
    Code:
       0: aload_3
       1: ifnull        17
       4: aload_3
       5: ldc           #11                 // String )
       7: invokevirtual #12                 // Method java/lang/String.endsWith:(Ljava/lang/String;)Z
      10: ifne          17
      13: iconst_1
      14: goto          18
      17: iconst_0
      18: istore        7
      20: new           #13                 // class java/lang/StringBuffer
      23: dup
      24: sipush        256
      27: invokespecial #14                 // Method java/lang/StringBuffer."<init>":(I)V
      30: astore        8
      32: aload         8
      34: aload_1
      35: invokevirtual #15                 // Method com/mchange/v2/log/MLevel.getLineHeader:()Ljava/lang/String;
      38: invokevirtual #16                 // Method java/lang/StringBuffer.append:(Ljava/lang/String;)Ljava/lang/StringBuffer;
      41: pop
      42: aload         8
      44: bipush        32
      46: invokevirtual #17                 // Method java/lang/StringBuffer.append:(C)Ljava/lang/StringBuffer;
      49: pop
      50: aload_2
      51: ifnull        112
      54: aload_3
      55: ifnull        112
      58: aload         8
      60: bipush        91
      62: invokevirtual #17                 // Method java/lang/StringBuffer.append:(C)Ljava/lang/StringBuffer;
      65: pop
      66: aload         8
      68: aload_2
      69: invokevirtual #16                 // Method java/lang/StringBuffer.append:(Ljava/lang/String;)Ljava/lang/StringBuffer;
      72: pop
      73: aload         8
      75: bipush        46
      77: invokevirtual #17                 // Method java/lang/StringBuffer.append:(C)Ljava/lang/StringBuffer;
      80: pop
      81: aload         8
      83: aload_3
      84: invokevirtual #16                 // Method java/lang/StringBuffer.append:(Ljava/lang/String;)Ljava/lang/StringBuffer;
      87: pop
      88: iload         7
      90: ifeq          101
      93: aload         8
      95: ldc           #18                 // String ()
      97: invokevirtual #16                 // Method java/lang/StringBuffer.append:(Ljava/lang/String;)Ljava/lang/StringBuffer;
     100: pop
     101: aload         8
     103: bipush        93
     105: invokevirtual #17                 // Method java/lang/StringBuffer.append:(C)Ljava/lang/StringBuffer;
     108: pop
     109: goto          182
     112: aload_2
     113: ifnull        142
     116: aload         8
     118: bipush        91
     120: invokevirtual #17                 // Method java/lang/StringBuffer.append:(C)Ljava/lang/StringBuffer;
     123: pop
     124: aload         8
     126: aload_2
     127: invokevirtual #16                 // Method java/lang/StringBuffer.append:(Ljava/lang/String;)Ljava/lang/StringBuffer;
     130: pop
     131: aload         8
     133: bipush        93
     135: invokevirtual #17                 // Method java/lang/StringBuffer.append:(C)Ljava/lang/StringBuffer;
     138: pop
     139: goto          182
     142: aload_3
     143: ifnull        182
     146: aload         8
     148: bipush        91
     150: invokevirtual #17                 // Method java/lang/StringBuffer.append:(C)Ljava/lang/StringBuffer;
     153: pop
     154: aload         8
     156: aload_3
     157: invokevirtual #16                 // Method java/lang/StringBuffer.append:(Ljava/lang/String;)Ljava/lang/StringBuffer;
     160: pop
     161: iload         7
     163: ifeq          174
     166: aload         8
     168: ldc           #18                 // String ()
     170: invokevirtual #16                 // Method java/lang/StringBuffer.append:(Ljava/lang/String;)Ljava/lang/StringBuffer;
     173: pop
     174: aload         8
     176: bipush        93
     178: invokevirtual #17                 // Method java/lang/StringBuffer.append:(C)Ljava/lang/StringBuffer;
     181: pop
     182: aload         4
     184: ifnonnull     248
     187: aload         5
     189: ifnull        288
     192: aload         8
     194: ldc           #19                 // String params:
     196: invokevirtual #16                 // Method java/lang/StringBuffer.append:(Ljava/lang/String;)Ljava/lang/StringBuffer;
     199: pop
     200: iconst_0
     201: istore        9
     203: aload         5
     205: arraylength
     206: istore        10
     208: iload         9
     210: iload         10
     212: if_icmpge     245
     215: iload         9
     217: ifeq          228
     220: aload         8
     222: ldc           #20                 // String ,
     224: invokevirtual #16                 // Method java/lang/StringBuffer.append:(Ljava/lang/String;)Ljava/lang/StringBuffer;
     227: pop
     228: aload         8
     230: aload         5
     232: iload         9
     234: aaload
     235: invokevirtual #21                 // Method java/lang/StringBuffer.append:(Ljava/lang/Object;)Ljava/lang/StringBuffer;
     238: pop
     239: iinc          9, 1
     242: goto          208
     245: goto          288
     248: aload         5
     250: ifnonnull     264
     253: aload         8
     255: aload         4
     257: invokevirtual #16                 // Method java/lang/StringBuffer.append:(Ljava/lang/String;)Ljava/lang/StringBuffer;
     260: pop
     261: goto          288
     264: new           #22                 // class java/text/MessageFormat
     267: dup
     268: aload         4
     270: invokespecial #23                 // Method java/text/MessageFormat."<init>":(Ljava/lang/String;)V
     273: astore        9
     275: aload         8
     277: aload         9
     279: aload         5
     281: invokevirtual #24                 // Method java/text/MessageFormat.format:(Ljava/lang/Object;)Ljava/lang/String;
     284: invokevirtual #16                 // Method java/lang/StringBuffer.append:(Ljava/lang/String;)Ljava/lang/StringBuffer;
     287: pop
     288: aload         6
     290: ifnull        313
     293: aload         8
     295: getstatic     #25                 // Field com/mchange/v2/log/FallbackMLog.SEP:Ljava/lang/String;
     298: invokevirtual #16                 // Method java/lang/StringBuffer.append:(Ljava/lang/String;)Ljava/lang/StringBuffer;
     301: pop
     302: aload         8
     304: aload         6
     306: invokestatic  #26                 // Method com/mchange/lang/ThrowableUtils.extractStackTrace:(Ljava/lang/Throwable;)Ljava/lang/String;
     309: invokevirtual #16                 // Method java/lang/StringBuffer.append:(Ljava/lang/String;)Ljava/lang/StringBuffer;
     312: pop
     313: aload         8
     315: invokevirtual #27                 // Method java/lang/StringBuffer.toString:()Ljava/lang/String;
     318: areturn

  public java.util.ResourceBundle getResourceBundle();
    Code:
       0: aconst_null
       1: areturn

  public java.lang.String getResourceBundleName();
    Code:
       0: aconst_null
       1: areturn

  public void setFilter(java.lang.Object) throws java.lang.SecurityException;
    Code:
       0: aload_0
       1: ldc           #28                 // String Using FallbackMLog -- Filters not supported!
       3: invokevirtual #29                 // Method warning:(Ljava/lang/String;)V
       6: return

  public java.lang.Object getFilter();
    Code:
       0: aconst_null
       1: areturn

  public void log(com.mchange.v2.log.MLevel, java.lang.String);
    Code:
       0: aload_0
       1: aload_1
       2: invokevirtual #30                 // Method isLoggable:(Lcom/mchange/v2/log/MLevel;)Z
       5: ifeq          18
       8: aload_0
       9: aload_1
      10: aconst_null
      11: aconst_null
      12: aload_2
      13: aconst_null
      14: aconst_null
      15: invokespecial #7                  // Method format:(Lcom/mchange/v2/log/MLevel;Ljava/lang/String;Ljava/lang/String;Ljava/lang/String;[Ljava/lang/Object;Ljava/lang/Throwable;)V
      18: return

  public void log(com.mchange.v2.log.MLevel, java.lang.String, java.lang.Object);
    Code:
       0: aload_0
       1: aload_1
       2: invokevirtual #30                 // Method isLoggable:(Lcom/mchange/v2/log/MLevel;)Z
       5: ifeq          25
       8: aload_0
       9: aload_1
      10: aconst_null
      11: aconst_null
      12: aload_2
      13: iconst_1
      14: anewarray     #31                 // class java/lang/Object
      17: dup
      18: iconst_0
      19: aload_3
      20: aastore
      21: aconst_null
      22: invokespecial #7                  // Method format:(Lcom/mchange/v2/log/MLevel;Ljava/lang/String;Ljava/lang/String;Ljava/lang/String;[Ljava/lang/Object;Ljava/lang/Throwable;)V
      25: return

  public void log(com.mchange.v2.log.MLevel, java.lang.String, java.lang.Object[]);
    Code:
       0: aload_0
       1: aload_1
       2: invokevirtual #30                 // Method isLoggable:(Lcom/mchange/v2/log/MLevel;)Z
       5: ifeq          18
       8: aload_0
       9: aload_1
      10: aconst_null
      11: aconst_null
      12: aload_2
      13: aload_3
      14: aconst_null
      15: invokespecial #7                  // Method format:(Lcom/mchange/v2/log/MLevel;Ljava/lang/String;Ljava/lang/String;Ljava/lang/String;[Ljava/lang/Object;Ljava/lang/Throwable;)V
      18: return

  public void log(com.mchange.v2.log.MLevel, java.lang.String, java.lang.Throwable);
    Code:
       0: aload_0
       1: aload_1
       2: invokevirtual #30                 // Method isLoggable:(Lcom/mchange/v2/log/MLevel;)Z
       5: ifeq          18
       8: aload_0
       9: aload_1
      10: aconst_null
      11: aconst_null
      12: aload_2
      13: aconst_null
      14: aload_3
      15: invokespecial #7                  // Method format:(Lcom/mchange/v2/log/MLevel;Ljava/lang/String;Ljava/lang/String;Ljava/lang/String;[Ljava/lang/Object;Ljava/lang/Throwable;)V
      18: return

  public void logp(com.mchange.v2.log.MLevel, java.lang.String, java.lang.String, java.lang.String);
    Code:
       0: aload_0
       1: aload_1
       2: invokevirtual #30                 // Method isLoggable:(Lcom/mchange/v2/log/MLevel;)Z
       5: ifeq          19
       8: aload_0
       9: aload_1
      10: aload_2
      11: aload_3
      12: aload         4
      14: aconst_null
      15: aconst_null
      16: invokespecial #7                  // Method format:(Lcom/mchange/v2/log/MLevel;Ljava/lang/String;Ljava/lang/String;Ljava/lang/String;[Ljava/lang/Object;Ljava/lang/Throwable;)V
      19: return

  public void logp(com.mchange.v2.log.MLevel, java.lang.String, java.lang.String, java.lang.String, java.lang.Object);
    Code:
       0: aload_0
       1: aload_1
       2: invokevirtual #30                 // Method isLoggable:(Lcom/mchange/v2/log/MLevel;)Z
       5: ifeq          27
       8: aload_0
       9: aload_1
      10: aload_2
      11: aload_3
      12: aload         4
      14: iconst_1
      15: anewarray     #31                 // class java/lang/Object
      18: dup
      19: iconst_0
      20: aload         5
      22: aastore
      23: aconst_null
      24: invokespecial #7                  // Method format:(Lcom/mchange/v2/log/MLevel;Ljava/lang/String;Ljava/lang/String;Ljava/lang/String;[Ljava/lang/Object;Ljava/lang/Throwable;)V
      27: return

  public void logp(com.mchange.v2.log.MLevel, java.lang.String, java.lang.String, java.lang.String, java.lang.Object[]);
    Code:
       0: aload_0
       1: aload_1
       2: invokevirtual #30                 // Method isLoggable:(Lcom/mchange/v2/log/MLevel;)Z
       5: ifeq          20
       8: aload_0
       9: aload_1
      10: aload_2
      11: aload_3
      12: aload         4
      14: aload         5
      16: aconst_null
      17: invokespecial #7                  // Method format:(Lcom/mchange/v2/log/MLevel;Ljava/lang/String;Ljava/lang/String;Ljava/lang/String;[Ljava/lang/Object;Ljava/lang/Throwable;)V
      20: return

  public void logp(com.mchange.v2.log.MLevel, java.lang.String, java.lang.String, java.lang.String, java.lang.Throwable);
    Code:
       0: aload_0
       1: aload_1
       2: invokevirtual #30                 // Method isLoggable:(Lcom/mchange/v2/log/MLevel;)Z
       5: ifeq          20
       8: aload_0
       9: aload_1
      10: aload_2
      11: aload_3
      12: aload         4
      14: aconst_null
      15: aload         5
      17: invokespecial #7                  // Method format:(Lcom/mchange/v2/log/MLevel;Ljava/lang/String;Ljava/lang/String;Ljava/lang/String;[Ljava/lang/Object;Ljava/lang/Throwable;)V
      20: return

  public void logrb(com.mchange.v2.log.MLevel, java.lang.String, java.lang.String, java.lang.String, java.lang.String);
    Code:
       0: aload_0
       1: aload_1
       2: invokevirtual #30                 // Method isLoggable:(Lcom/mchange/v2/log/MLevel;)Z
       5: ifeq          21
       8: aload_0
       9: aload_1
      10: aload_2
      11: aload_3
      12: aload         4
      14: aload         5
      16: aconst_null
      17: aconst_null
      18: invokespecial #32                 // Method formatrb:(Lcom/mchange/v2/log/MLevel;Ljava/lang/String;Ljava/lang/String;Ljava/lang/String;Ljava/lang/String;[Ljava/lang/Object;Ljava/lang/Throwable;)V
      21: return

  public void logrb(com.mchange.v2.log.MLevel, java.lang.String, java.lang.String, java.lang.String, java.lang.String, java.lang.Object);
    Code:
       0: aload_0
       1: aload_1
       2: invokevirtual #30                 // Method isLoggable:(Lcom/mchange/v2/log/MLevel;)Z
       5: ifeq          29
       8: aload_0
       9: aload_1
      10: aload_2
      11: aload_3
      12: aload         4
      14: aload         5
      16: iconst_1
      17: anewarray     #31                 // class java/lang/Object
      20: dup
      21: iconst_0
      22: aload         6
      24: aastore
      25: aconst_null
      26: invokespecial #32                 // Method formatrb:(Lcom/mchange/v2/log/MLevel;Ljava/lang/String;Ljava/lang/String;Ljava/lang/String;Ljava/lang/String;[Ljava/lang/Object;Ljava/lang/Throwable;)V
      29: return

  public void logrb(com.mchange.v2.log.MLevel, java.lang.String, java.lang.String, java.lang.String, java.lang.String, java.lang.Object[]);
    Code:
       0: aload_0
       1: aload_1
       2: invokevirtual #30                 // Method isLoggable:(Lcom/mchange/v2/log/MLevel;)Z
       5: ifeq          22
       8: aload_0
       9: aload_1
      10: aload_2
      11: aload_3
      12: aload         4
      14: aload         5
      16: aload         6
      18: aconst_null
      19: invokespecial #32                 // Method formatrb:(Lcom/mchange/v2/log/MLevel;Ljava/lang/String;Ljava/lang/String;Ljava/lang/String;Ljava/lang/String;[Ljava/lang/Object;Ljava/lang/Throwable;)V
      22: return

  public void logrb(com.mchange.v2.log.MLevel, java.lang.String, java.lang.String, java.lang.String, java.lang.String, java.lang.Throwable);
    Code:
       0: aload_0
       1: aload_1
       2: invokevirtual #30                 // Method isLoggable:(Lcom/mchange/v2/log/MLevel;)Z
       5: ifeq          22
       8: aload_0
       9: aload_1
      10: aload_2
      11: aload_3
      12: aload         4
      14: aload         5
      16: aconst_null
      17: aload         6
      19: invokespecial #32                 // Method formatrb:(Lcom/mchange/v2/log/MLevel;Ljava/lang/String;Ljava/lang/String;Ljava/lang/String;Ljava/lang/String;[Ljava/lang/Object;Ljava/lang/Throwable;)V
      22: return

  public void entering(java.lang.String, java.lang.String);
    Code:
       0: aload_0
       1: getstatic     #33                 // Field com/mchange/v2/log/MLevel.FINER:Lcom/mchange/v2/log/MLevel;
       4: invokevirtual #30                 // Method isLoggable:(Lcom/mchange/v2/log/MLevel;)Z
       7: ifeq          23
      10: aload_0
      11: getstatic     #33                 // Field com/mchange/v2/log/MLevel.FINER:Lcom/mchange/v2/log/MLevel;
      14: aload_1
      15: aload_2
      16: ldc           #34                 // String Entering method.
      18: aconst_null
      19: aconst_null
      20: invokespecial #7                  // Method format:(Lcom/mchange/v2/log/MLevel;Ljava/lang/String;Ljava/lang/String;Ljava/lang/String;[Ljava/lang/Object;Ljava/lang/Throwable;)V
      23: return

  public void entering(java.lang.String, java.lang.String, java.lang.Object);
    Code:
       0: aload_0
       1: getstatic     #33                 // Field com/mchange/v2/log/MLevel.FINER:Lcom/mchange/v2/log/MLevel;
       4: invokevirtual #30                 // Method isLoggable:(Lcom/mchange/v2/log/MLevel;)Z
       7: ifeq          40
      10: aload_0
      11: getstatic     #33                 // Field com/mchange/v2/log/MLevel.FINER:Lcom/mchange/v2/log/MLevel;
      14: aload_1
      15: aload_2
      16: new           #35                 // class java/lang/StringBuilder
      19: dup
      20: invokespecial #36                 // Method java/lang/StringBuilder."<init>":()V
      23: ldc           #37                 // String Entering method with argument
      25: invokevirtual #38                 // Method java/lang/StringBuilder.append:(Ljava/lang/String;)Ljava/lang/StringBuilder;
      28: aload_3
      29: invokevirtual #39                 // Method java/lang/StringBuilder.append:(Ljava/lang/Object;)Ljava/lang/StringBuilder;
      32: invokevirtual #40                 // Method java/lang/StringBuilder.toString:()Ljava/lang/String;
      35: aconst_null
      36: aconst_null
      37: invokespecial #7                  // Method format:(Lcom/mchange/v2/log/MLevel;Ljava/lang/String;Ljava/lang/String;Ljava/lang/String;[Ljava/lang/Object;Ljava/lang/Throwable;)V
      40: return

  public void entering(java.lang.String, java.lang.String, java.lang.Object[]);
    Code:
       0: aload_0
       1: getstatic     #33                 // Field com/mchange/v2/log/MLevel.FINER:Lcom/mchange/v2/log/MLevel;
       4: invokevirtual #30                 // Method isLoggable:(Lcom/mchange/v2/log/MLevel;)Z
       7: ifeq          128
      10: aload_3
      11: ifnonnull     23
      14: aload_0
      15: aload_1
      16: aload_2
      17: invokevirtual #41                 // Method entering:(Ljava/lang/String;Ljava/lang/String;)V
      20: goto          128
      23: new           #13                 // class java/lang/StringBuffer
      26: dup
      27: sipush        128
      30: invokespecial #14                 // Method java/lang/StringBuffer."<init>":(I)V
      33: astore        4
      35: aload         4
      37: ldc           #42                 // String (
      39: invokevirtual #16                 // Method java/lang/StringBuffer.append:(Ljava/lang/String;)Ljava/lang/StringBuffer;
      42: pop
      43: iconst_0
      44: istore        5
      46: aload_3
      47: arraylength
      48: istore        6
      50: iload         5
      52: iload         6
      54: if_icmpge     86
      57: iload         5
      59: ifeq          70
      62: aload         4
      64: ldc           #20                 // String ,
      66: invokevirtual #16                 // Method java/lang/StringBuffer.append:(Ljava/lang/String;)Ljava/lang/StringBuffer;
      69: pop
      70: aload         4
      72: aload_3
      73: iload         5
      75: aaload
      76: invokevirtual #21                 // Method java/lang/StringBuffer.append:(Ljava/lang/Object;)Ljava/lang/StringBuffer;
      79: pop
      80: iinc          5, 1
      83: goto          50
      86: aload         4
      88: ldc           #43                 // String  )
      90: invokevirtual #16                 // Method java/lang/StringBuffer.append:(Ljava/lang/String;)Ljava/lang/StringBuffer;
      93: pop
      94: aload_0
      95: getstatic     #33                 // Field com/mchange/v2/log/MLevel.FINER:Lcom/mchange/v2/log/MLevel;
      98: aload_1
      99: aload_2
     100: new           #35                 // class java/lang/StringBuilder
     103: dup
     104: invokespecial #36                 // Method java/lang/StringBuilder."<init>":()V
     107: ldc           #44                 // String Entering method with arguments
     109: invokevirtual #38                 // Method java/lang/StringBuilder.append:(Ljava/lang/String;)Ljava/lang/StringBuilder;
     112: aload         4
     114: invokevirtual #27                 // Method java/lang/StringBuffer.toString:()Ljava/lang/String;
     117: invokevirtual #38                 // Method java/lang/StringBuilder.append:(Ljava/lang/String;)Ljava/lang/StringBuilder;
     120: invokevirtual #40                 // Method java/lang/StringBuilder.toString:()Ljava/lang/String;
     123: aconst_null
     124: aconst_null
     125: invokespecial #7                  // Method format:(Lcom/mchange/v2/log/MLevel;Ljava/lang/String;Ljava/lang/String;Ljava/lang/String;[Ljava/lang/Object;Ljava/lang/Throwable;)V
     128: return

  public void exiting(java.lang.String, java.lang.String);
    Code:
       0: aload_0
       1: getstatic     #33                 // Field com/mchange/v2/log/MLevel.FINER:Lcom/mchange/v2/log/MLevel;
       4: invokevirtual #30                 // Method isLoggable:(Lcom/mchange/v2/log/MLevel;)Z
       7: ifeq          23
      10: aload_0
      11: getstatic     #33                 // Field com/mchange/v2/log/MLevel.FINER:Lcom/mchange/v2/log/MLevel;
      14: aload_1
      15: aload_2
      16: ldc           #45                 // String Exiting method.
      18: aconst_null
      19: aconst_null
      20: invokespecial #7                  // Method format:(Lcom/mchange/v2/log/MLevel;Ljava/lang/String;Ljava/lang/String;Ljava/lang/String;[Ljava/lang/Object;Ljava/lang/Throwable;)V
      23: return

  public void exiting(java.lang.String, java.lang.String, java.lang.Object);
    Code:
       0: aload_0
       1: getstatic     #33                 // Field com/mchange/v2/log/MLevel.FINER:Lcom/mchange/v2/log/MLevel;
       4: invokevirtual #30                 // Method isLoggable:(Lcom/mchange/v2/log/MLevel;)Z
       7: ifeq          40
      10: aload_0
      11: getstatic     #33                 // Field com/mchange/v2/log/MLevel.FINER:Lcom/mchange/v2/log/MLevel;
      14: aload_1
      15: aload_2
      16: new           #35                 // class java/lang/StringBuilder
      19: dup
      20: invokespecial #36                 // Method java/lang/StringBuilder."<init>":()V
      23: ldc           #46                 // String Exiting method with result
      25: invokevirtual #38                 // Method java/lang/StringBuilder.append:(Ljava/lang/String;)Ljava/lang/StringBuilder;
      28: aload_3
      29: invokevirtual #39                 // Method java/lang/StringBuilder.append:(Ljava/lang/Object;)Ljava/lang/StringBuilder;
      32: invokevirtual #40                 // Method java/lang/StringBuilder.toString:()Ljava/lang/String;
      35: aconst_null
      36: aconst_null
      37: invokespecial #7                  // Method format:(Lcom/mchange/v2/log/MLevel;Ljava/lang/String;Ljava/lang/String;Ljava/lang/String;[Ljava/lang/Object;Ljava/lang/Throwable;)V
      40: return

  public void throwing(java.lang.String, java.lang.String, java.lang.Throwable);
    Code:
       0: aload_0
       1: getstatic     #47                 // Field com/mchange/v2/log/MLevel.FINE:Lcom/mchange/v2/log/MLevel;
       4: invokevirtual #30                 // Method isLoggable:(Lcom/mchange/v2/log/MLevel;)Z
       7: ifeq          23
      10: aload_0
      11: getstatic     #47                 // Field com/mchange/v2/log/MLevel.FINE:Lcom/mchange/v2/log/MLevel;
      14: aload_1
      15: aload_2
      16: ldc           #48                 // String Throwing exception.
      18: aconst_null
      19: aload_3
      20: invokespecial #7                  // Method format:(Lcom/mchange/v2/log/MLevel;Ljava/lang/String;Ljava/lang/String;Ljava/lang/String;[Ljava/lang/Object;Ljava/lang/Throwable;)V
      23: return

  public void severe(java.lang.String);
    Code:
       0: aload_0
       1: getstatic     #49                 // Field com/mchange/v2/log/MLevel.SEVERE:Lcom/mchange/v2/log/MLevel;
       4: invokevirtual #30                 // Method isLoggable:(Lcom/mchange/v2/log/MLevel;)Z
       7: ifeq          22
      10: aload_0
      11: getstatic     #49                 // Field com/mchange/v2/log/MLevel.SEVERE:Lcom/mchange/v2/log/MLevel;
      14: aconst_null
      15: aconst_null
      16: aload_1
      17: aconst_null
      18: aconst_null
      19: invokespecial #7                  // Method format:(Lcom/mchange/v2/log/MLevel;Ljava/lang/String;Ljava/lang/String;Ljava/lang/String;[Ljava/lang/Object;Ljava/lang/Throwable;)V
      22: return

  public void warning(java.lang.String);
    Code:
       0: aload_0
       1: getstatic     #50                 // Field com/mchange/v2/log/MLevel.WARNING:Lcom/mchange/v2/log/MLevel;
       4: invokevirtual #30                 // Method isLoggable:(Lcom/mchange/v2/log/MLevel;)Z
       7: ifeq          22
      10: aload_0
      11: getstatic     #50                 // Field com/mchange/v2/log/MLevel.WARNING:Lcom/mchange/v2/log/MLevel;
      14: aconst_null
      15: aconst_null
      16: aload_1
      17: aconst_null
      18: aconst_null
      19: invokespecial #7                  // Method format:(Lcom/mchange/v2/log/MLevel;Ljava/lang/String;Ljava/lang/String;Ljava/lang/String;[Ljava/lang/Object;Ljava/lang/Throwable;)V
      22: return

  public void info(java.lang.String);
    Code:
       0: aload_0
       1: getstatic     #51                 // Field com/mchange/v2/log/MLevel.INFO:Lcom/mchange/v2/log/MLevel;
       4: invokevirtual #30                 // Method isLoggable:(Lcom/mchange/v2/log/MLevel;)Z
       7: ifeq          22
      10: aload_0
      11: getstatic     #51                 // Field com/mchange/v2/log/MLevel.INFO:Lcom/mchange/v2/log/MLevel;
      14: aconst_null
      15: aconst_null
      16: aload_1
      17: aconst_null
      18: aconst_null
      19: invokespecial #7                  // Method format:(Lcom/mchange/v2/log/MLevel;Ljava/lang/String;Ljava/lang/String;Ljava/lang/String;[Ljava/lang/Object;Ljava/lang/Throwable;)V
      22: return

  public void config(java.lang.String);
    Code:
       0: aload_0
       1: getstatic     #52                 // Field com/mchange/v2/log/MLevel.CONFIG:Lcom/mchange/v2/log/MLevel;
       4: invokevirtual #30                 // Method isLoggable:(Lcom/mchange/v2/log/MLevel;)Z
       7: ifeq          22
      10: aload_0
      11: getstatic     #52                 // Field com/mchange/v2/log/MLevel.CONFIG:Lcom/mchange/v2/log/MLevel;
      14: aconst_null
      15: aconst_null
      16: aload_1
      17: aconst_null
      18: aconst_null
      19: invokespecial #7                  // Method format:(Lcom/mchange/v2/log/MLevel;Ljava/lang/String;Ljava/lang/String;Ljava/lang/String;[Ljava/lang/Object;Ljava/lang/Throwable;)V
      22: return

  public void fine(java.lang.String);
    Code:
       0: aload_0
       1: getstatic     #47                 // Field com/mchange/v2/log/MLevel.FINE:Lcom/mchange/v2/log/MLevel;
       4: invokevirtual #30                 // Method isLoggable:(Lcom/mchange/v2/log/MLevel;)Z
       7: ifeq          22
      10: aload_0
      11: getstatic     #47                 // Field com/mchange/v2/log/MLevel.FINE:Lcom/mchange/v2/log/MLevel;
      14: aconst_null
      15: aconst_null
      16: aload_1
      17: aconst_null
      18: aconst_null
      19: invokespecial #7                  // Method format:(Lcom/mchange/v2/log/MLevel;Ljava/lang/String;Ljava/lang/String;Ljava/lang/String;[Ljava/lang/Object;Ljava/lang/Throwable;)V
      22: return

  public void finer(java.lang.String);
    Code:
       0: aload_0
       1: getstatic     #33                 // Field com/mchange/v2/log/MLevel.FINER:Lcom/mchange/v2/log/MLevel;
       4: invokevirtual #30                 // Method isLoggable:(Lcom/mchange/v2/log/MLevel;)Z
       7: ifeq          22
      10: aload_0
      11: getstatic     #33                 // Field com/mchange/v2/log/MLevel.FINER:Lcom/mchange/v2/log/MLevel;
      14: aconst_null
      15: aconst_null
      16: aload_1
      17: aconst_null
      18: aconst_null
      19: invokespecial #7                  // Method format:(Lcom/mchange/v2/log/MLevel;Ljava/lang/String;Ljava/lang/String;Ljava/lang/String;[Ljava/lang/Object;Ljava/lang/Throwable;)V
      22: return

  public void finest(java.lang.String);
    Code:
       0: aload_0
       1: getstatic     #53                 // Field com/mchange/v2/log/MLevel.FINEST:Lcom/mchange/v2/log/MLevel;
       4: invokevirtual #30                 // Method isLoggable:(Lcom/mchange/v2/log/MLevel;)Z
       7: ifeq          22
      10: aload_0
      11: getstatic     #53                 // Field com/mchange/v2/log/MLevel.FINEST:Lcom/mchange/v2/log/MLevel;
      14: aconst_null
      15: aconst_null
      16: aload_1
      17: aconst_null
      18: aconst_null
      19: invokespecial #7                  // Method format:(Lcom/mchange/v2/log/MLevel;Ljava/lang/String;Ljava/lang/String;Ljava/lang/String;[Ljava/lang/Object;Ljava/lang/Throwable;)V
      22: return

  public void setLevel(com.mchange.v2.log.MLevel) throws java.lang.SecurityException;
    Code:
       0: aload_0
       1: aload_1
       2: putfield      #4                  // Field cutoffLevel:Lcom/mchange/v2/log/MLevel;
       5: return

  public synchronized com.mchange.v2.log.MLevel getLevel();
    Code:
       0: aload_0
       1: getfield      #4                  // Field cutoffLevel:Lcom/mchange/v2/log/MLevel;
       4: areturn

  public synchronized boolean isLoggable(com.mchange.v2.log.MLevel);
    Code:
       0: aload_1
       1: invokevirtual #54                 // Method com/mchange/v2/log/MLevel.intValue:()I
       4: aload_0
       5: getfield      #4                  // Field cutoffLevel:Lcom/mchange/v2/log/MLevel;
       8: invokevirtual #54                 // Method com/mchange/v2/log/MLevel.intValue:()I
      11: if_icmplt     18
      14: iconst_1
      15: goto          19
      18: iconst_0
      19: ireturn

  public java.lang.String getName();
    Code:
       0: ldc           #55                 // String global
       2: areturn

  public void addHandler(java.lang.Object) throws java.lang.SecurityException;
    Code:
       0: aload_0
       1: ldc           #56                 // String Using FallbackMLog -- Handlers not supported.
       3: invokevirtual #29                 // Method warning:(Ljava/lang/String;)V
       6: return

  public void removeHandler(java.lang.Object) throws java.lang.SecurityException;
    Code:
       0: aload_0
       1: ldc           #56                 // String Using FallbackMLog -- Handlers not supported.
       3: invokevirtual #29                 // Method warning:(Ljava/lang/String;)V
       6: return

  public java.lang.Object[] getHandlers();
    Code:
       0: aload_0
       1: ldc           #56                 // String Using FallbackMLog -- Handlers not supported.
       3: invokevirtual #29                 // Method warning:(Ljava/lang/String;)V
       6: iconst_0
       7: anewarray     #31                 // class java/lang/Object
      10: areturn

  public void setUseParentHandlers(boolean);
    Code:
       0: aload_0
       1: ldc           #56                 // String Using FallbackMLog -- Handlers not supported.
       3: invokevirtual #29                 // Method warning:(Ljava/lang/String;)V
       6: return

  public boolean getUseParentHandlers();
    Code:
       0: iconst_0
       1: ireturn

  com.mchange.v2.log.FallbackMLog$FallbackMLogger(com.mchange.v2.log.FallbackMLog$1);
    Code:
       0: aload_0
       1: invokespecial #1                  // Method "<init>":()V
       4: return
}
