public class org.bouncycastle.asn1.crmf.SinglePubInfo extends org.bouncycastle.asn1.ASN1Object {
  public static final org.bouncycastle.asn1.ASN1Integer dontCare;

  public static final org.bouncycastle.asn1.ASN1Integer x500;

  public static final org.bouncycastle.asn1.ASN1Integer web;

  public static final org.bouncycastle.asn1.ASN1Integer ldap;

  private org.bouncycastle.asn1.ASN1Integer pubMethod;

  private org.bouncycastle.asn1.x509.GeneralName pubLocation;

  private org.bouncycastle.asn1.crmf.SinglePubInfo(org.bouncycastle.asn1.ASN1Sequence);
    Code:
       0: aload_0
       1: invokespecial #79                 // Method org/bouncycastle/asn1/ASN1Object."<init>":()V
       4: aload_0
       5: aload_1
       6: iconst_0
       7: invokevirtual #81                 // Method org/bouncycastle/asn1/ASN1Sequence.getObjectAt:(I)Lorg/bouncycastle/asn1/ASN1Encodable;
      10: invokestatic  #78                 // Method org/bouncycastle/asn1/ASN1Integer.getInstance:(Ljava/lang/Object;)Lorg/bouncycastle/asn1/ASN1Integer;
      13: putfield      #71                 // Field pubMethod:Lorg/bouncycastle/asn1/ASN1Integer;
      16: aload_1
      17: invokevirtual #80                 // Method org/bouncycastle/asn1/ASN1Sequence.size:()I
      20: iconst_2
      21: if_icmpne     36
      24: aload_0
      25: aload_1
      26: iconst_1
      27: invokevirtual #81                 // Method org/bouncycastle/asn1/ASN1Sequence.getObjectAt:(I)Lorg/bouncycastle/asn1/ASN1Encodable;
      30: invokestatic  #85                 // Method org/bouncycastle/asn1/x509/GeneralName.getInstance:(Ljava/lang/Object;)Lorg/bouncycastle/asn1/x509/GeneralName;
      33: putfield      #74                 // Field pubLocation:Lorg/bouncycastle/asn1/x509/GeneralName;
      36: return

  public static org.bouncycastle.asn1.crmf.SinglePubInfo getInstance(java.lang.Object);
    Code:
       0: aload_0
       1: instanceof    #36                 // class org/bouncycastle/asn1/crmf/SinglePubInfo
       4: ifeq          12
       7: aload_0
       8: checkcast     #36                 // class org/bouncycastle/asn1/crmf/SinglePubInfo
      11: areturn
      12: aload_0
      13: ifnull        28
      16: new           #36                 // class org/bouncycastle/asn1/crmf/SinglePubInfo
      19: dup
      20: aload_0
      21: invokestatic  #82                 // Method org/bouncycastle/asn1/ASN1Sequence.getInstance:(Ljava/lang/Object;)Lorg/bouncycastle/asn1/ASN1Sequence;
      24: invokespecial #84                 // Method "<init>":(Lorg/bouncycastle/asn1/ASN1Sequence;)V
      27: areturn
      28: aconst_null
      29: areturn

  public org.bouncycastle.asn1.crmf.SinglePubInfo(org.bouncycastle.asn1.ASN1Integer, org.bouncycastle.asn1.x509.GeneralName);
    Code:
       0: aload_0
       1: invokespecial #79                 // Method org/bouncycastle/asn1/ASN1Object."<init>":()V
       4: aload_0
       5: aload_1
       6: putfield      #71                 // Field pubMethod:Lorg/bouncycastle/asn1/ASN1Integer;
       9: aload_0
      10: aload_2
      11: putfield      #74                 // Field pubLocation:Lorg/bouncycastle/asn1/x509/GeneralName;
      14: return

  public org.bouncycastle.asn1.ASN1Integer getPubMethod();
    Code:
       0: aload_0
       1: getfield      #71                 // Field pubMethod:Lorg/bouncycastle/asn1/ASN1Integer;
       4: areturn

  public org.bouncycastle.asn1.x509.GeneralName getPubLocation();
    Code:
       0: aload_0
       1: getfield      #74                 // Field pubLocation:Lorg/bouncycastle/asn1/x509/GeneralName;
       4: areturn

  public org.bouncycastle.asn1.ASN1Primitive toASN1Primitive();
    Code:
       0: new           #31                 // class org/bouncycastle/asn1/ASN1EncodableVector
       3: dup
       4: iconst_2
       5: invokespecial #75                 // Method org/bouncycastle/asn1/ASN1EncodableVector."<init>":(I)V
       8: astore_1
       9: aload_1
      10: aload_0
      11: getfield      #71                 // Field pubMethod:Lorg/bouncycastle/asn1/ASN1Integer;
      14: invokevirtual #76                 // Method org/bouncycastle/asn1/ASN1EncodableVector.add:(Lorg/bouncycastle/asn1/ASN1Encodable;)V
      17: aload_0
      18: getfield      #74                 // Field pubLocation:Lorg/bouncycastle/asn1/x509/GeneralName;
      21: ifnull        32
      24: aload_1
      25: aload_0
      26: getfield      #74                 // Field pubLocation:Lorg/bouncycastle/asn1/x509/GeneralName;
      29: invokevirtual #76                 // Method org/bouncycastle/asn1/ASN1EncodableVector.add:(Lorg/bouncycastle/asn1/ASN1Encodable;)V
      32: new           #35                 // class org/bouncycastle/asn1/DERSequence
      35: dup
      36: aload_1
      37: invokespecial #83                 // Method org/bouncycastle/asn1/DERSequence."<init>":(Lorg/bouncycastle/asn1/ASN1EncodableVector;)V
      40: areturn

  static {};
    Code:
       0: new           #32                 // class org/bouncycastle/asn1/ASN1Integer
       3: dup
       4: lconst_0
       5: invokespecial #77                 // Method org/bouncycastle/asn1/ASN1Integer."<init>":(J)V
       8: putstatic     #69                 // Field dontCare:Lorg/bouncycastle/asn1/ASN1Integer;
      11: new           #32                 // class org/bouncycastle/asn1/ASN1Integer
      14: dup
      15: lconst_1
      16: invokespecial #77                 // Method org/bouncycastle/asn1/ASN1Integer."<init>":(J)V
      19: putstatic     #73                 // Field x500:Lorg/bouncycastle/asn1/ASN1Integer;
      22: new           #32                 // class org/bouncycastle/asn1/ASN1Integer
      25: dup
      26: ldc2_w        #27                 // long 2l
      29: invokespecial #77                 // Method org/bouncycastle/asn1/ASN1Integer."<init>":(J)V
      32: putstatic     #72                 // Field web:Lorg/bouncycastle/asn1/ASN1Integer;
      35: new           #32                 // class org/bouncycastle/asn1/ASN1Integer
      38: dup
      39: ldc2_w        #29                 // long 3l
      42: invokespecial #77                 // Method org/bouncycastle/asn1/ASN1Integer."<init>":(J)V
      45: putstatic     #70                 // Field ldap:Lorg/bouncycastle/asn1/ASN1Integer;
      48: return
}
