Compiled from "SessionStore.scala"
public final class io.youi.server.session.SessionStore$$anonfun$getOrCreateSessionId$1 extends scala.runtime.AbstractFunction1<io.youi.http.HttpResponse, io.youi.http.HttpResponse> implements scala.Serializable {
  public static final long serialVersionUID;

  private final io.youi.http.HttpConnection httpConnection$1;

  private final java.lang.String id$1;

  public final io.youi.http.HttpResponse apply(io.youi.http.HttpResponse);
    Code:
       0: getstatic     #29                 // Field reactify/package$.MODULE$:Lreactify/package$;
       3: aload_0
       4: getfield      #31                 // Field httpConnection$1:Lio/youi/http/HttpConnection;
       7: invokevirtual #37                 // Method io/youi/http/HttpConnection.server:()Lio/youi/server/Server;
      10: invokeinterface #43,  1           // InterfaceMethod io/youi/server/Server.config:()Lio/youi/server/ServerConfig;
      15: invokevirtual #49                 // Method io/youi/server/ServerConfig.session:()Lio/youi/server/ServerConfig$session$;
      18: invokevirtual #55                 // Method io/youi/server/ServerConfig$session$.name:()Lreactify/Var;
      21: invokevirtual #59                 // Method reactify/package$.state2Value:(Lreactify/State;)Ljava/lang/Object;
      24: checkcast     #61                 // class java/lang/String
      27: astore_3
      28: aload_0
      29: getfield      #63                 // Field id$1:Ljava/lang/String;
      32: astore        4
      34: getstatic     #29                 // Field reactify/package$.MODULE$:Lreactify/package$;
      37: aload_0
      38: getfield      #31                 // Field httpConnection$1:Lio/youi/http/HttpConnection;
      41: invokevirtual #37                 // Method io/youi/http/HttpConnection.server:()Lio/youi/server/Server;
      44: invokeinterface #43,  1           // InterfaceMethod io/youi/server/Server.config:()Lio/youi/server/ServerConfig;
      49: invokevirtual #49                 // Method io/youi/server/ServerConfig.session:()Lio/youi/server/ServerConfig$session$;
      52: invokevirtual #66                 // Method io/youi/server/ServerConfig$session$.maxAge:()Lreactify/Var;
      55: invokevirtual #59                 // Method reactify/package$.state2Value:(Lreactify/State;)Ljava/lang/Object;
      58: checkcast     #68                 // class scala/Option
      61: astore        5
      63: getstatic     #29                 // Field reactify/package$.MODULE$:Lreactify/package$;
      66: aload_0
      67: getfield      #31                 // Field httpConnection$1:Lio/youi/http/HttpConnection;
      70: invokevirtual #37                 // Method io/youi/http/HttpConnection.server:()Lio/youi/server/Server;
      73: invokeinterface #43,  1           // InterfaceMethod io/youi/server/Server.config:()Lio/youi/server/ServerConfig;
      78: invokevirtual #49                 // Method io/youi/server/ServerConfig.session:()Lio/youi/server/ServerConfig$session$;
      81: invokevirtual #71                 // Method io/youi/server/ServerConfig$session$.domain:()Lreactify/Var;
      84: invokevirtual #59                 // Method reactify/package$.state2Value:(Lreactify/State;)Ljava/lang/Object;
      87: checkcast     #68                 // class scala/Option
      90: astore        6
      92: getstatic     #29                 // Field reactify/package$.MODULE$:Lreactify/package$;
      95: aload_0
      96: getfield      #31                 // Field httpConnection$1:Lio/youi/http/HttpConnection;
      99: invokevirtual #37                 // Method io/youi/http/HttpConnection.server:()Lio/youi/server/Server;
     102: invokeinterface #43,  1           // InterfaceMethod io/youi/server/Server.config:()Lio/youi/server/ServerConfig;
     107: invokevirtual #49                 // Method io/youi/server/ServerConfig.session:()Lio/youi/server/ServerConfig$session$;
     110: invokevirtual #74                 // Method io/youi/server/ServerConfig$session$.secure:()Lreactify/Var;
     113: invokevirtual #59                 // Method reactify/package$.state2Value:(Lreactify/State;)Ljava/lang/Object;
     116: invokestatic  #80                 // Method scala/runtime/BoxesRunTime.unboxToBoolean:(Ljava/lang/Object;)Z
     119: istore        7
     121: getstatic     #85                 // Field io/youi/http/cookie/ResponseCookie$.MODULE$:Lio/youi/http/cookie/ResponseCookie$;
     124: invokevirtual #89                 // Method io/youi/http/cookie/ResponseCookie$.apply$default$3:()Lscala/Option;
     127: astore        8
     129: getstatic     #85                 // Field io/youi/http/cookie/ResponseCookie$.MODULE$:Lio/youi/http/cookie/ResponseCookie$;
     132: invokevirtual #92                 // Method io/youi/http/cookie/ResponseCookie$.apply$default$6:()Lscala/Option;
     135: astore        9
     137: getstatic     #85                 // Field io/youi/http/cookie/ResponseCookie$.MODULE$:Lio/youi/http/cookie/ResponseCookie$;
     140: invokevirtual #96                 // Method io/youi/http/cookie/ResponseCookie$.apply$default$8:()Z
     143: istore        10
     145: new           #98                 // class io/youi/http/cookie/ResponseCookie
     148: dup
     149: aload_3
     150: aload         4
     152: aload         8
     154: aload         5
     156: aload         6
     158: aload         9
     160: iload         7
     162: iload         10
     164: invokespecial #102                // Method io/youi/http/cookie/ResponseCookie."<init>":(Ljava/lang/String;Ljava/lang/String;Lscala/Option;Lscala/Option;Lscala/Option;Lscala/Option;ZZ)V
     167: astore_2
     168: aload_1
     169: getstatic     #107                // Field io/youi/http/Headers$Response$.MODULE$:Lio/youi/http/Headers$Response$;
     172: invokevirtual #111                // Method io/youi/http/Headers$Response$.Set$minusCookie:()Lio/youi/http/SetCookie$;
     175: aload_2
     176: invokevirtual #116                // Method io/youi/http/SetCookie$.apply:(Lio/youi/http/cookie/ResponseCookie;)Lio/youi/http/Header;
     179: invokevirtual #122                // Method io/youi/http/HttpResponse.withHeader:(Lio/youi/http/Header;)Lio/youi/http/HttpResponse;
     182: areturn

  public final java.lang.Object apply(java.lang.Object);
    Code:
       0: aload_0
       1: aload_1
       2: checkcast     #118                // class io/youi/http/HttpResponse
       5: invokevirtual #141                // Method apply:(Lio/youi/http/HttpResponse;)Lio/youi/http/HttpResponse;
       8: areturn

  public io.youi.server.session.SessionStore$$anonfun$getOrCreateSessionId$1(io.youi.http.HttpConnection, java.lang.String);
    Code:
       0: aload_0
       1: aload_1
       2: putfield      #31                 // Field httpConnection$1:Lio/youi/http/HttpConnection;
       5: aload_0
       6: aload_2
       7: putfield      #63                 // Field id$1:Ljava/lang/String;
      10: aload_0
      11: invokespecial #147                // Method scala/runtime/AbstractFunction1."<init>":()V
      14: return
}
