Compiled from "FileArgumentType.java"
public class net.sourceforge.argparse4j.impl.type.FileArgumentType implements net.sourceforge.argparse4j.inf.ArgumentType<java.io.File> {
  private boolean acceptSystemIn;

  private boolean verifyExists;

  private boolean verifyNotExists;

  private boolean verifyIsFile;

  private boolean verifyIsDirectory;

  private boolean verifyCanRead;

  private boolean verifyCanWrite;

  private boolean verifyCanWriteParent;

  private boolean verifyCanCreate;

  private boolean verifyCanExecute;

  private boolean verifyIsAbsolute;

  public net.sourceforge.argparse4j.impl.type.FileArgumentType();
    Code:
       0: aload_0
       1: invokespecial #1                  // Method java/lang/Object."<init>":()V
       4: aload_0
       5: iconst_0
       6: putfield      #2                  // Field acceptSystemIn:Z
       9: aload_0
      10: iconst_0
      11: putfield      #3                  // Field verifyExists:Z
      14: aload_0
      15: iconst_0
      16: putfield      #4                  // Field verifyNotExists:Z
      19: aload_0
      20: iconst_0
      21: putfield      #5                  // Field verifyIsFile:Z
      24: aload_0
      25: iconst_0
      26: putfield      #6                  // Field verifyIsDirectory:Z
      29: aload_0
      30: iconst_0
      31: putfield      #7                  // Field verifyCanRead:Z
      34: aload_0
      35: iconst_0
      36: putfield      #8                  // Field verifyCanWrite:Z
      39: aload_0
      40: iconst_0
      41: putfield      #9                  // Field verifyCanWriteParent:Z
      44: aload_0
      45: iconst_0
      46: putfield      #10                 // Field verifyCanCreate:Z
      49: aload_0
      50: iconst_0
      51: putfield      #11                 // Field verifyCanExecute:Z
      54: aload_0
      55: iconst_0
      56: putfield      #12                 // Field verifyIsAbsolute:Z
      59: return

  public net.sourceforge.argparse4j.impl.type.FileArgumentType acceptSystemIn();
    Code:
       0: aload_0
       1: iconst_1
       2: putfield      #2                  // Field acceptSystemIn:Z
       5: aload_0
       6: areturn

  public net.sourceforge.argparse4j.impl.type.FileArgumentType verifyExists();
    Code:
       0: aload_0
       1: iconst_1
       2: putfield      #3                  // Field verifyExists:Z
       5: aload_0
       6: areturn

  public net.sourceforge.argparse4j.impl.type.FileArgumentType verifyNotExists();
    Code:
       0: aload_0
       1: iconst_1
       2: putfield      #4                  // Field verifyNotExists:Z
       5: aload_0
       6: areturn

  public net.sourceforge.argparse4j.impl.type.FileArgumentType verifyIsFile();
    Code:
       0: aload_0
       1: iconst_1
       2: putfield      #5                  // Field verifyIsFile:Z
       5: aload_0
       6: areturn

  public net.sourceforge.argparse4j.impl.type.FileArgumentType verifyIsDirectory();
    Code:
       0: aload_0
       1: iconst_1
       2: putfield      #6                  // Field verifyIsDirectory:Z
       5: aload_0
       6: areturn

  public net.sourceforge.argparse4j.impl.type.FileArgumentType verifyCanRead();
    Code:
       0: aload_0
       1: iconst_1
       2: putfield      #7                  // Field verifyCanRead:Z
       5: aload_0
       6: areturn

  public net.sourceforge.argparse4j.impl.type.FileArgumentType verifyCanWrite();
    Code:
       0: aload_0
       1: iconst_1
       2: putfield      #8                  // Field verifyCanWrite:Z
       5: aload_0
       6: areturn

  public net.sourceforge.argparse4j.impl.type.FileArgumentType verifyCanWriteParent();
    Code:
       0: aload_0
       1: iconst_1
       2: putfield      #9                  // Field verifyCanWriteParent:Z
       5: aload_0
       6: areturn

  public net.sourceforge.argparse4j.impl.type.FileArgumentType verifyCanCreate();
    Code:
       0: aload_0
       1: iconst_1
       2: putfield      #10                 // Field verifyCanCreate:Z
       5: aload_0
       6: areturn

  public net.sourceforge.argparse4j.impl.type.FileArgumentType verifyCanExecute();
    Code:
       0: aload_0
       1: iconst_1
       2: putfield      #11                 // Field verifyCanExecute:Z
       5: aload_0
       6: areturn

  public net.sourceforge.argparse4j.impl.type.FileArgumentType verifyIsAbsolute();
    Code:
       0: aload_0
       1: iconst_1
       2: putfield      #12                 // Field verifyIsAbsolute:Z
       5: aload_0
       6: areturn

  public java.io.File convert(net.sourceforge.argparse4j.inf.ArgumentParser, net.sourceforge.argparse4j.inf.Argument, java.lang.String) throws net.sourceforge.argparse4j.inf.ArgumentParserException;
    Code:
       0: new           #13                 // class java/io/File
       3: dup
       4: aload_3
       5: invokespecial #14                 // Method java/io/File."<init>":(Ljava/lang/String;)V
       8: astore        4
      10: aload_0
      11: getfield      #12                 // Field verifyIsAbsolute:Z
      14: ifeq          34
      17: aload_0
      18: aload         4
      20: invokespecial #15                 // Method isSystemIn:(Ljava/io/File;)Z
      23: ifne          34
      26: aload_0
      27: aload_1
      28: aload_2
      29: aload         4
      31: invokespecial #16                 // Method verifyIsAbsolute:(Lnet/sourceforge/argparse4j/inf/ArgumentParser;Lnet/sourceforge/argparse4j/inf/Argument;Ljava/io/File;)V
      34: aload_0
      35: getfield      #3                  // Field verifyExists:Z
      38: ifeq          58
      41: aload_0
      42: aload         4
      44: invokespecial #15                 // Method isSystemIn:(Ljava/io/File;)Z
      47: ifne          58
      50: aload_0
      51: aload_1
      52: aload_2
      53: aload         4
      55: invokespecial #17                 // Method verifyExists:(Lnet/sourceforge/argparse4j/inf/ArgumentParser;Lnet/sourceforge/argparse4j/inf/Argument;Ljava/io/File;)V
      58: aload_0
      59: getfield      #4                  // Field verifyNotExists:Z
      62: ifeq          82
      65: aload_0
      66: aload         4
      68: invokespecial #15                 // Method isSystemIn:(Ljava/io/File;)Z
      71: ifne          82
      74: aload_0
      75: aload_1
      76: aload_2
      77: aload         4
      79: invokespecial #18                 // Method verifyNotExists:(Lnet/sourceforge/argparse4j/inf/ArgumentParser;Lnet/sourceforge/argparse4j/inf/Argument;Ljava/io/File;)V
      82: aload_0
      83: getfield      #5                  // Field verifyIsFile:Z
      86: ifeq          106
      89: aload_0
      90: aload         4
      92: invokespecial #15                 // Method isSystemIn:(Ljava/io/File;)Z
      95: ifne          106
      98: aload_0
      99: aload_1
     100: aload_2
     101: aload         4
     103: invokespecial #19                 // Method verifyIsFile:(Lnet/sourceforge/argparse4j/inf/ArgumentParser;Lnet/sourceforge/argparse4j/inf/Argument;Ljava/io/File;)V
     106: aload_0
     107: getfield      #6                  // Field verifyIsDirectory:Z
     110: ifeq          130
     113: aload_0
     114: aload         4
     116: invokespecial #15                 // Method isSystemIn:(Ljava/io/File;)Z
     119: ifne          130
     122: aload_0
     123: aload_1
     124: aload_2
     125: aload         4
     127: invokespecial #20                 // Method verifyIsDirectory:(Lnet/sourceforge/argparse4j/inf/ArgumentParser;Lnet/sourceforge/argparse4j/inf/Argument;Ljava/io/File;)V
     130: aload_0
     131: getfield      #7                  // Field verifyCanRead:Z
     134: ifeq          154
     137: aload_0
     138: aload         4
     140: invokespecial #15                 // Method isSystemIn:(Ljava/io/File;)Z
     143: ifne          154
     146: aload_0
     147: aload_1
     148: aload_2
     149: aload         4
     151: invokespecial #21                 // Method verifyCanRead:(Lnet/sourceforge/argparse4j/inf/ArgumentParser;Lnet/sourceforge/argparse4j/inf/Argument;Ljava/io/File;)V
     154: aload_0
     155: getfield      #8                  // Field verifyCanWrite:Z
     158: ifeq          178
     161: aload_0
     162: aload         4
     164: invokespecial #15                 // Method isSystemIn:(Ljava/io/File;)Z
     167: ifne          178
     170: aload_0
     171: aload_1
     172: aload_2
     173: aload         4
     175: invokespecial #22                 // Method verifyCanWrite:(Lnet/sourceforge/argparse4j/inf/ArgumentParser;Lnet/sourceforge/argparse4j/inf/Argument;Ljava/io/File;)V
     178: aload_0
     179: getfield      #9                  // Field verifyCanWriteParent:Z
     182: ifeq          202
     185: aload_0
     186: aload         4
     188: invokespecial #15                 // Method isSystemIn:(Ljava/io/File;)Z
     191: ifne          202
     194: aload_0
     195: aload_1
     196: aload_2
     197: aload         4
     199: invokespecial #23                 // Method verifyCanWriteParent:(Lnet/sourceforge/argparse4j/inf/ArgumentParser;Lnet/sourceforge/argparse4j/inf/Argument;Ljava/io/File;)V
     202: aload_0
     203: getfield      #10                 // Field verifyCanCreate:Z
     206: ifeq          226
     209: aload_0
     210: aload         4
     212: invokespecial #15                 // Method isSystemIn:(Ljava/io/File;)Z
     215: ifne          226
     218: aload_0
     219: aload_1
     220: aload_2
     221: aload         4
     223: invokespecial #24                 // Method verifyCanCreate:(Lnet/sourceforge/argparse4j/inf/ArgumentParser;Lnet/sourceforge/argparse4j/inf/Argument;Ljava/io/File;)V
     226: aload_0
     227: getfield      #11                 // Field verifyCanExecute:Z
     230: ifeq          250
     233: aload_0
     234: aload         4
     236: invokespecial #15                 // Method isSystemIn:(Ljava/io/File;)Z
     239: ifne          250
     242: aload_0
     243: aload_1
     244: aload_2
     245: aload         4
     247: invokespecial #25                 // Method verifyCanExecute:(Lnet/sourceforge/argparse4j/inf/ArgumentParser;Lnet/sourceforge/argparse4j/inf/Argument;Ljava/io/File;)V
     250: aload         4
     252: areturn

  private void verifyExists(net.sourceforge.argparse4j.inf.ArgumentParser, net.sourceforge.argparse4j.inf.Argument, java.io.File) throws net.sourceforge.argparse4j.inf.ArgumentParserException;
    Code:
       0: aload_3
       1: invokevirtual #26                 // Method java/io/File.exists:()Z
       4: ifne          34
       7: new           #27                 // class net/sourceforge/argparse4j/inf/ArgumentParserException
      10: dup
      11: aconst_null
      12: checkcast     #28                 // class java/util/Locale
      15: ldc           #29                 // String File not found: \'%s\'
      17: iconst_1
      18: anewarray     #30                 // class java/lang/Object
      21: dup
      22: iconst_0
      23: aload_3
      24: aastore
      25: invokestatic  #31                 // Method java/lang/String.format:(Ljava/util/Locale;Ljava/lang/String;[Ljava/lang/Object;)Ljava/lang/String;
      28: aload_1
      29: aload_2
      30: invokespecial #32                 // Method net/sourceforge/argparse4j/inf/ArgumentParserException."<init>":(Ljava/lang/String;Lnet/sourceforge/argparse4j/inf/ArgumentParser;Lnet/sourceforge/argparse4j/inf/Argument;)V
      33: athrow
      34: return

  private void verifyNotExists(net.sourceforge.argparse4j.inf.ArgumentParser, net.sourceforge.argparse4j.inf.Argument, java.io.File) throws net.sourceforge.argparse4j.inf.ArgumentParserException;
    Code:
       0: aload_3
       1: invokevirtual #26                 // Method java/io/File.exists:()Z
       4: ifeq          34
       7: new           #27                 // class net/sourceforge/argparse4j/inf/ArgumentParserException
      10: dup
      11: aconst_null
      12: checkcast     #28                 // class java/util/Locale
      15: ldc           #33                 // String File found: \'%s\'
      17: iconst_1
      18: anewarray     #30                 // class java/lang/Object
      21: dup
      22: iconst_0
      23: aload_3
      24: aastore
      25: invokestatic  #31                 // Method java/lang/String.format:(Ljava/util/Locale;Ljava/lang/String;[Ljava/lang/Object;)Ljava/lang/String;
      28: aload_1
      29: aload_2
      30: invokespecial #32                 // Method net/sourceforge/argparse4j/inf/ArgumentParserException."<init>":(Ljava/lang/String;Lnet/sourceforge/argparse4j/inf/ArgumentParser;Lnet/sourceforge/argparse4j/inf/Argument;)V
      33: athrow
      34: return

  private void verifyIsFile(net.sourceforge.argparse4j.inf.ArgumentParser, net.sourceforge.argparse4j.inf.Argument, java.io.File) throws net.sourceforge.argparse4j.inf.ArgumentParserException;
    Code:
       0: aload_3
       1: invokevirtual #34                 // Method java/io/File.isFile:()Z
       4: ifne          34
       7: new           #27                 // class net/sourceforge/argparse4j/inf/ArgumentParserException
      10: dup
      11: aconst_null
      12: checkcast     #28                 // class java/util/Locale
      15: ldc           #35                 // String Not a file: \'%s\'
      17: iconst_1
      18: anewarray     #30                 // class java/lang/Object
      21: dup
      22: iconst_0
      23: aload_3
      24: aastore
      25: invokestatic  #31                 // Method java/lang/String.format:(Ljava/util/Locale;Ljava/lang/String;[Ljava/lang/Object;)Ljava/lang/String;
      28: aload_1
      29: aload_2
      30: invokespecial #32                 // Method net/sourceforge/argparse4j/inf/ArgumentParserException."<init>":(Ljava/lang/String;Lnet/sourceforge/argparse4j/inf/ArgumentParser;Lnet/sourceforge/argparse4j/inf/Argument;)V
      33: athrow
      34: return

  private void verifyIsDirectory(net.sourceforge.argparse4j.inf.ArgumentParser, net.sourceforge.argparse4j.inf.Argument, java.io.File) throws net.sourceforge.argparse4j.inf.ArgumentParserException;
    Code:
       0: aload_3
       1: invokevirtual #36                 // Method java/io/File.isDirectory:()Z
       4: ifne          34
       7: new           #27                 // class net/sourceforge/argparse4j/inf/ArgumentParserException
      10: dup
      11: aconst_null
      12: checkcast     #28                 // class java/util/Locale
      15: ldc           #37                 // String Not a directory: \'%s\'
      17: iconst_1
      18: anewarray     #30                 // class java/lang/Object
      21: dup
      22: iconst_0
      23: aload_3
      24: aastore
      25: invokestatic  #31                 // Method java/lang/String.format:(Ljava/util/Locale;Ljava/lang/String;[Ljava/lang/Object;)Ljava/lang/String;
      28: aload_1
      29: aload_2
      30: invokespecial #32                 // Method net/sourceforge/argparse4j/inf/ArgumentParserException."<init>":(Ljava/lang/String;Lnet/sourceforge/argparse4j/inf/ArgumentParser;Lnet/sourceforge/argparse4j/inf/Argument;)V
      33: athrow
      34: return

  private void verifyCanRead(net.sourceforge.argparse4j.inf.ArgumentParser, net.sourceforge.argparse4j.inf.Argument, java.io.File) throws net.sourceforge.argparse4j.inf.ArgumentParserException;
    Code:
       0: aload_3
       1: invokevirtual #38                 // Method java/io/File.canRead:()Z
       4: ifne          34
       7: new           #27                 // class net/sourceforge/argparse4j/inf/ArgumentParserException
      10: dup
      11: aconst_null
      12: checkcast     #28                 // class java/util/Locale
      15: ldc           #39                 // String Insufficient permissions to read file: \'%s\'
      17: iconst_1
      18: anewarray     #30                 // class java/lang/Object
      21: dup
      22: iconst_0
      23: aload_3
      24: aastore
      25: invokestatic  #31                 // Method java/lang/String.format:(Ljava/util/Locale;Ljava/lang/String;[Ljava/lang/Object;)Ljava/lang/String;
      28: aload_1
      29: aload_2
      30: invokespecial #32                 // Method net/sourceforge/argparse4j/inf/ArgumentParserException."<init>":(Ljava/lang/String;Lnet/sourceforge/argparse4j/inf/ArgumentParser;Lnet/sourceforge/argparse4j/inf/Argument;)V
      33: athrow
      34: return

  private void verifyCanWrite(net.sourceforge.argparse4j.inf.ArgumentParser, net.sourceforge.argparse4j.inf.Argument, java.io.File) throws net.sourceforge.argparse4j.inf.ArgumentParserException;
    Code:
       0: aload_3
       1: invokevirtual #40                 // Method java/io/File.canWrite:()Z
       4: ifne          34
       7: new           #27                 // class net/sourceforge/argparse4j/inf/ArgumentParserException
      10: dup
      11: aconst_null
      12: checkcast     #28                 // class java/util/Locale
      15: ldc           #41                 // String Insufficient permissions to write file: \'%s\'
      17: iconst_1
      18: anewarray     #30                 // class java/lang/Object
      21: dup
      22: iconst_0
      23: aload_3
      24: aastore
      25: invokestatic  #31                 // Method java/lang/String.format:(Ljava/util/Locale;Ljava/lang/String;[Ljava/lang/Object;)Ljava/lang/String;
      28: aload_1
      29: aload_2
      30: invokespecial #32                 // Method net/sourceforge/argparse4j/inf/ArgumentParserException."<init>":(Ljava/lang/String;Lnet/sourceforge/argparse4j/inf/ArgumentParser;Lnet/sourceforge/argparse4j/inf/Argument;)V
      33: athrow
      34: return

  private void verifyCanWriteParent(net.sourceforge.argparse4j.inf.ArgumentParser, net.sourceforge.argparse4j.inf.Argument, java.io.File) throws net.sourceforge.argparse4j.inf.ArgumentParserException;
    Code:
       0: aload_3
       1: invokevirtual #42                 // Method java/io/File.getParentFile:()Ljava/io/File;
       4: astore        4
       6: aload         4
       8: ifnull        19
      11: aload         4
      13: invokevirtual #40                 // Method java/io/File.canWrite:()Z
      16: ifne          46
      19: new           #27                 // class net/sourceforge/argparse4j/inf/ArgumentParserException
      22: dup
      23: aconst_null
      24: checkcast     #28                 // class java/util/Locale
      27: ldc           #43                 // String Cannot write parent of file: \'%s\'
      29: iconst_1
      30: anewarray     #30                 // class java/lang/Object
      33: dup
      34: iconst_0
      35: aload_3
      36: aastore
      37: invokestatic  #31                 // Method java/lang/String.format:(Ljava/util/Locale;Ljava/lang/String;[Ljava/lang/Object;)Ljava/lang/String;
      40: aload_1
      41: aload_2
      42: invokespecial #32                 // Method net/sourceforge/argparse4j/inf/ArgumentParserException."<init>":(Ljava/lang/String;Lnet/sourceforge/argparse4j/inf/ArgumentParser;Lnet/sourceforge/argparse4j/inf/Argument;)V
      45: athrow
      46: return

  private void verifyCanCreate(net.sourceforge.argparse4j.inf.ArgumentParser, net.sourceforge.argparse4j.inf.Argument, java.io.File) throws net.sourceforge.argparse4j.inf.ArgumentParserException;
    Code:
       0: aload_3
       1: invokevirtual #44                 // Method java/io/File.getCanonicalFile:()Ljava/io/File;
       4: invokevirtual #42                 // Method java/io/File.getParentFile:()Ljava/io/File;
       7: astore        4
       9: aload         4
      11: ifnull        23
      14: aload         4
      16: invokevirtual #40                 // Method java/io/File.canWrite:()Z
      19: ifeq          23
      22: return
      23: goto          28
      26: astore        4
      28: new           #27                 // class net/sourceforge/argparse4j/inf/ArgumentParserException
      31: dup
      32: aconst_null
      33: checkcast     #28                 // class java/util/Locale
      36: ldc           #46                 // String Cannot create file: \'%s\'
      38: iconst_1
      39: anewarray     #30                 // class java/lang/Object
      42: dup
      43: iconst_0
      44: aload_3
      45: aastore
      46: invokestatic  #31                 // Method java/lang/String.format:(Ljava/util/Locale;Ljava/lang/String;[Ljava/lang/Object;)Ljava/lang/String;
      49: aload_1
      50: aload_2
      51: invokespecial #32                 // Method net/sourceforge/argparse4j/inf/ArgumentParserException."<init>":(Ljava/lang/String;Lnet/sourceforge/argparse4j/inf/ArgumentParser;Lnet/sourceforge/argparse4j/inf/Argument;)V
      54: athrow
    Exception table:
       from    to  target type
           0    22    26   Class java/io/IOException

  private void verifyCanExecute(net.sourceforge.argparse4j.inf.ArgumentParser, net.sourceforge.argparse4j.inf.Argument, java.io.File) throws net.sourceforge.argparse4j.inf.ArgumentParserException;
    Code:
       0: aload_3
       1: invokevirtual #47                 // Method java/io/File.canExecute:()Z
       4: ifne          34
       7: new           #27                 // class net/sourceforge/argparse4j/inf/ArgumentParserException
      10: dup
      11: aconst_null
      12: checkcast     #28                 // class java/util/Locale
      15: ldc           #48                 // String Insufficient permissions to execute file: \'%s\'
      17: iconst_1
      18: anewarray     #30                 // class java/lang/Object
      21: dup
      22: iconst_0
      23: aload_3
      24: aastore
      25: invokestatic  #31                 // Method java/lang/String.format:(Ljava/util/Locale;Ljava/lang/String;[Ljava/lang/Object;)Ljava/lang/String;
      28: aload_1
      29: aload_2
      30: invokespecial #32                 // Method net/sourceforge/argparse4j/inf/ArgumentParserException."<init>":(Ljava/lang/String;Lnet/sourceforge/argparse4j/inf/ArgumentParser;Lnet/sourceforge/argparse4j/inf/Argument;)V
      33: athrow
      34: return

  private void verifyIsAbsolute(net.sourceforge.argparse4j.inf.ArgumentParser, net.sourceforge.argparse4j.inf.Argument, java.io.File) throws net.sourceforge.argparse4j.inf.ArgumentParserException;
    Code:
       0: aload_3
       1: invokevirtual #49                 // Method java/io/File.isAbsolute:()Z
       4: ifne          34
       7: new           #27                 // class net/sourceforge/argparse4j/inf/ArgumentParserException
      10: dup
      11: aconst_null
      12: checkcast     #28                 // class java/util/Locale
      15: ldc           #50                 // String Not an absolute file: \'%s\'
      17: iconst_1
      18: anewarray     #30                 // class java/lang/Object
      21: dup
      22: iconst_0
      23: aload_3
      24: aastore
      25: invokestatic  #31                 // Method java/lang/String.format:(Ljava/util/Locale;Ljava/lang/String;[Ljava/lang/Object;)Ljava/lang/String;
      28: aload_1
      29: aload_2
      30: invokespecial #32                 // Method net/sourceforge/argparse4j/inf/ArgumentParserException."<init>":(Ljava/lang/String;Lnet/sourceforge/argparse4j/inf/ArgumentParser;Lnet/sourceforge/argparse4j/inf/Argument;)V
      33: athrow
      34: return

  private boolean isSystemIn(java.io.File);
    Code:
       0: aload_0
       1: getfield      #2                  // Field acceptSystemIn:Z
       4: ifeq          23
       7: aload_1
       8: invokevirtual #51                 // Method java/io/File.getPath:()Ljava/lang/String;
      11: ldc           #52                 // String -
      13: invokevirtual #53                 // Method java/lang/String.equals:(Ljava/lang/Object;)Z
      16: ifeq          23
      19: iconst_1
      20: goto          24
      23: iconst_0
      24: ireturn

  public java.lang.Object convert(net.sourceforge.argparse4j.inf.ArgumentParser, net.sourceforge.argparse4j.inf.Argument, java.lang.String) throws net.sourceforge.argparse4j.inf.ArgumentParserException;
    Code:
       0: aload_0
       1: aload_1
       2: aload_2
       3: aload_3
       4: invokevirtual #54                 // Method convert:(Lnet/sourceforge/argparse4j/inf/ArgumentParser;Lnet/sourceforge/argparse4j/inf/Argument;Ljava/lang/String;)Ljava/io/File;
       7: areturn
}
