Compiled from "InvalidParameterTypeException.java"
public class org.graylog2.contentpacks.exceptions.InvalidParameterTypeException extends org.graylog2.contentpacks.exceptions.ContentPackException {
  private final org.graylog2.contentpacks.model.entities.references.ValueType expectedValueType;

  private final org.graylog2.contentpacks.model.entities.references.ValueType actualValueType;

  public org.graylog2.contentpacks.exceptions.InvalidParameterTypeException(org.graylog2.contentpacks.model.entities.references.ValueType, org.graylog2.contentpacks.model.entities.references.ValueType);
    Code:
       0: aload_0
       1: new           #1                  // class java/lang/StringBuilder
       4: dup
       5: invokespecial #2                  // Method java/lang/StringBuilder."<init>":()V
       8: ldc           #3                  // String Incompatible value types, content pack expected
      10: invokevirtual #4                  // Method java/lang/StringBuilder.append:(Ljava/lang/String;)Ljava/lang/StringBuilder;
      13: aload_1
      14: invokevirtual #5                  // Method java/lang/StringBuilder.append:(Ljava/lang/Object;)Ljava/lang/StringBuilder;
      17: ldc           #6                  // String , parameters provided
      19: invokevirtual #4                  // Method java/lang/StringBuilder.append:(Ljava/lang/String;)Ljava/lang/StringBuilder;
      22: aload_2
      23: invokevirtual #5                  // Method java/lang/StringBuilder.append:(Ljava/lang/Object;)Ljava/lang/StringBuilder;
      26: invokevirtual #7                  // Method java/lang/StringBuilder.toString:()Ljava/lang/String;
      29: invokespecial #8                  // Method org/graylog2/contentpacks/exceptions/ContentPackException."<init>":(Ljava/lang/String;)V
      32: aload_0
      33: aload_1
      34: ldc           #9                  // String expectedValueType
      36: invokestatic  #10                 // Method java/util/Objects.requireNonNull:(Ljava/lang/Object;Ljava/lang/String;)Ljava/lang/Object;
      39: checkcast     #11                 // class org/graylog2/contentpacks/model/entities/references/ValueType
      42: putfield      #12                 // Field expectedValueType:Lorg/graylog2/contentpacks/model/entities/references/ValueType;
      45: aload_0
      46: aload_2
      47: ldc           #13                 // String actualValueType
      49: invokestatic  #10                 // Method java/util/Objects.requireNonNull:(Ljava/lang/Object;Ljava/lang/String;)Ljava/lang/Object;
      52: checkcast     #11                 // class org/graylog2/contentpacks/model/entities/references/ValueType
      55: putfield      #14                 // Field actualValueType:Lorg/graylog2/contentpacks/model/entities/references/ValueType;
      58: return

  public org.graylog2.contentpacks.model.entities.references.ValueType getExpectedValueType();
    Code:
       0: aload_0
       1: getfield      #12                 // Field expectedValueType:Lorg/graylog2/contentpacks/model/entities/references/ValueType;
       4: areturn

  public org.graylog2.contentpacks.model.entities.references.ValueType getActualValueType();
    Code:
       0: aload_0
       1: getfield      #14                 // Field actualValueType:Lorg/graylog2/contentpacks/model/entities/references/ValueType;
       4: areturn
}
