Compiled from "AbstractIterator.java"
final class com.google.common.base.AbstractIterator$State extends java.lang.Enum<com.google.common.base.AbstractIterator$State> {
  public static final com.google.common.base.AbstractIterator$State READY;

  public static final com.google.common.base.AbstractIterator$State NOT_READY;

  public static final com.google.common.base.AbstractIterator$State DONE;

  public static final com.google.common.base.AbstractIterator$State FAILED;

  private static final com.google.common.base.AbstractIterator$State[] $VALUES;

  public static com.google.common.base.AbstractIterator$State[] values();
    Code:
       0: getstatic     #6                  // Field $VALUES:[Lcom/google/common/base/AbstractIterator$State;
       3: invokevirtual #7                  // Method "[Lcom/google/common/base/AbstractIterator$State;".clone:()Ljava/lang/Object;
       6: checkcast     #8                  // class "[Lcom/google/common/base/AbstractIterator$State;"
       9: areturn

  public static com.google.common.base.AbstractIterator$State valueOf(java.lang.String);
    Code:
       0: ldc           #1                  // class com/google/common/base/AbstractIterator$State
       2: aload_0
       3: invokestatic  #9                  // Method java/lang/Enum.valueOf:(Ljava/lang/Class;Ljava/lang/String;)Ljava/lang/Enum;
       6: checkcast     #1                  // class com/google/common/base/AbstractIterator$State
       9: areturn

  private com.google.common.base.AbstractIterator$State();
    Code:
       0: aload_0
       1: aload_1
       2: iload_2
       3: invokespecial #10                 // Method java/lang/Enum."<init>":(Ljava/lang/String;I)V
       6: return

  private static com.google.common.base.AbstractIterator$State[] $values();
    Code:
       0: iconst_4
       1: anewarray     #1                  // class com/google/common/base/AbstractIterator$State
       4: dup
       5: iconst_0
       6: getstatic     #2                  // Field READY:Lcom/google/common/base/AbstractIterator$State;
       9: aastore
      10: dup
      11: iconst_1
      12: getstatic     #3                  // Field NOT_READY:Lcom/google/common/base/AbstractIterator$State;
      15: aastore
      16: dup
      17: iconst_2
      18: getstatic     #4                  // Field DONE:Lcom/google/common/base/AbstractIterator$State;
      21: aastore
      22: dup
      23: iconst_3
      24: getstatic     #5                  // Field FAILED:Lcom/google/common/base/AbstractIterator$State;
      27: aastore
      28: areturn

  static {};
    Code:
       0: new           #1                  // class com/google/common/base/AbstractIterator$State
       3: dup
       4: ldc           #11                 // String READY
       6: iconst_0
       7: invokespecial #12                 // Method "<init>":(Ljava/lang/String;I)V
      10: putstatic     #2                  // Field READY:Lcom/google/common/base/AbstractIterator$State;
      13: new           #1                  // class com/google/common/base/AbstractIterator$State
      16: dup
      17: ldc           #13                 // String NOT_READY
      19: iconst_1
      20: invokespecial #12                 // Method "<init>":(Ljava/lang/String;I)V
      23: putstatic     #3                  // Field NOT_READY:Lcom/google/common/base/AbstractIterator$State;
      26: new           #1                  // class com/google/common/base/AbstractIterator$State
      29: dup
      30: ldc           #14                 // String DONE
      32: iconst_2
      33: invokespecial #12                 // Method "<init>":(Ljava/lang/String;I)V
      36: putstatic     #4                  // Field DONE:Lcom/google/common/base/AbstractIterator$State;
      39: new           #1                  // class com/google/common/base/AbstractIterator$State
      42: dup
      43: ldc           #15                 // String FAILED
      45: iconst_3
      46: invokespecial #12                 // Method "<init>":(Ljava/lang/String;I)V
      49: putstatic     #5                  // Field FAILED:Lcom/google/common/base/AbstractIterator$State;
      52: invokestatic  #16                 // Method $values:()[Lcom/google/common/base/AbstractIterator$State;
      55: putstatic     #6                  // Field $VALUES:[Lcom/google/common/base/AbstractIterator$State;
      58: return
}
