Compiled from "HttpMediaType.java"
public final class club.pizzalord.shire.http.HttpMediaType extends java.lang.Enum<club.pizzalord.shire.http.HttpMediaType> {
  public static final club.pizzalord.shire.http.HttpMediaType JSON;

  private java.lang.String wellFormedMediaTypeString;

  private static final club.pizzalord.shire.http.HttpMediaType[] $VALUES;

  public static club.pizzalord.shire.http.HttpMediaType[] values();
    Code:
       0: getstatic     #1                  // Field $VALUES:[Lclub/pizzalord/shire/http/HttpMediaType;
       3: invokevirtual #2                  // Method "[Lclub/pizzalord/shire/http/HttpMediaType;".clone:()Ljava/lang/Object;
       6: checkcast     #3                  // class "[Lclub/pizzalord/shire/http/HttpMediaType;"
       9: areturn

  public static club.pizzalord.shire.http.HttpMediaType valueOf(java.lang.String);
    Code:
       0: ldc           #4                  // class club/pizzalord/shire/http/HttpMediaType
       2: aload_0
       3: invokestatic  #5                  // Method java/lang/Enum.valueOf:(Ljava/lang/Class;Ljava/lang/String;)Ljava/lang/Enum;
       6: checkcast     #4                  // class club/pizzalord/shire/http/HttpMediaType
       9: areturn

  public java.lang.String getWellFormedMediaTypeString();
    Code:
       0: aload_0
       1: getfield      #6                  // Field wellFormedMediaTypeString:Ljava/lang/String;
       4: areturn

  private club.pizzalord.shire.http.HttpMediaType(java.lang.String);
    Code:
       0: aload_0
       1: aload_1
       2: iload_2
       3: invokespecial #7                  // Method java/lang/Enum."<init>":(Ljava/lang/String;I)V
       6: aload_0
       7: aload_3
       8: putfield      #6                  // Field wellFormedMediaTypeString:Ljava/lang/String;
      11: return

  static {};
    Code:
       0: new           #4                  // class club/pizzalord/shire/http/HttpMediaType
       3: dup
       4: ldc           #8                  // String JSON
       6: iconst_0
       7: ldc           #9                  // String application/json; charset=utf-8
       9: invokespecial #10                 // Method "<init>":(Ljava/lang/String;ILjava/lang/String;)V
      12: putstatic     #11                 // Field JSON:Lclub/pizzalord/shire/http/HttpMediaType;
      15: iconst_1
      16: anewarray     #4                  // class club/pizzalord/shire/http/HttpMediaType
      19: dup
      20: iconst_0
      21: getstatic     #11                 // Field JSON:Lclub/pizzalord/shire/http/HttpMediaType;
      24: aastore
      25: putstatic     #1                  // Field $VALUES:[Lclub/pizzalord/shire/http/HttpMediaType;
      28: return
}
