Compiled from "TupleFactory.java"
public class org.apache.jena.atlas.lib.tuple.TupleFactory {
  private org.apache.jena.atlas.lib.tuple.TupleFactory();
    Code:
       0: aload_0
       1: invokespecial #1                  // Method java/lang/Object."<init>":()V
       4: return

  public static <X> org.apache.jena.atlas.lib.tuple.Tuple<X> tuple(X...);
    Code:
       0: aload_0
       1: arraylength
       2: tableswitch   { // 0 to 8
                     0: 52
                     1: 56
                     2: 63
                     3: 73
                     4: 86
                     5: 102
                     6: 121
                     7: 143
                     8: 169
               default: 199
          }
      52: invokestatic  #2                  // Method create0:()Lorg/apache/jena/atlas/lib/tuple/Tuple0;
      55: areturn
      56: aload_0
      57: iconst_0
      58: aaload
      59: invokestatic  #3                  // Method create1:(Ljava/lang/Object;)Lorg/apache/jena/atlas/lib/tuple/Tuple1;
      62: areturn
      63: aload_0
      64: iconst_0
      65: aaload
      66: aload_0
      67: iconst_1
      68: aaload
      69: invokestatic  #4                  // Method create2:(Ljava/lang/Object;Ljava/lang/Object;)Lorg/apache/jena/atlas/lib/tuple/Tuple2;
      72: areturn
      73: aload_0
      74: iconst_0
      75: aaload
      76: aload_0
      77: iconst_1
      78: aaload
      79: aload_0
      80: iconst_2
      81: aaload
      82: invokestatic  #5                  // Method create3:(Ljava/lang/Object;Ljava/lang/Object;Ljava/lang/Object;)Lorg/apache/jena/atlas/lib/tuple/Tuple3;
      85: areturn
      86: aload_0
      87: iconst_0
      88: aaload
      89: aload_0
      90: iconst_1
      91: aaload
      92: aload_0
      93: iconst_2
      94: aaload
      95: aload_0
      96: iconst_3
      97: aaload
      98: invokestatic  #6                  // Method create4:(Ljava/lang/Object;Ljava/lang/Object;Ljava/lang/Object;Ljava/lang/Object;)Lorg/apache/jena/atlas/lib/tuple/Tuple4;
     101: areturn
     102: aload_0
     103: iconst_0
     104: aaload
     105: aload_0
     106: iconst_1
     107: aaload
     108: aload_0
     109: iconst_2
     110: aaload
     111: aload_0
     112: iconst_3
     113: aaload
     114: aload_0
     115: iconst_4
     116: aaload
     117: invokestatic  #7                  // Method create5:(Ljava/lang/Object;Ljava/lang/Object;Ljava/lang/Object;Ljava/lang/Object;Ljava/lang/Object;)Lorg/apache/jena/atlas/lib/tuple/Tuple5;
     120: areturn
     121: aload_0
     122: iconst_0
     123: aaload
     124: aload_0
     125: iconst_1
     126: aaload
     127: aload_0
     128: iconst_2
     129: aaload
     130: aload_0
     131: iconst_3
     132: aaload
     133: aload_0
     134: iconst_4
     135: aaload
     136: aload_0
     137: iconst_5
     138: aaload
     139: invokestatic  #8                  // Method create6:(Ljava/lang/Object;Ljava/lang/Object;Ljava/lang/Object;Ljava/lang/Object;Ljava/lang/Object;Ljava/lang/Object;)Lorg/apache/jena/atlas/lib/tuple/Tuple6;
     142: areturn
     143: aload_0
     144: iconst_0
     145: aaload
     146: aload_0
     147: iconst_1
     148: aaload
     149: aload_0
     150: iconst_2
     151: aaload
     152: aload_0
     153: iconst_3
     154: aaload
     155: aload_0
     156: iconst_4
     157: aaload
     158: aload_0
     159: iconst_5
     160: aaload
     161: aload_0
     162: bipush        6
     164: aaload
     165: invokestatic  #9                  // Method create7:(Ljava/lang/Object;Ljava/lang/Object;Ljava/lang/Object;Ljava/lang/Object;Ljava/lang/Object;Ljava/lang/Object;Ljava/lang/Object;)Lorg/apache/jena/atlas/lib/tuple/Tuple7;
     168: areturn
     169: aload_0
     170: iconst_0
     171: aaload
     172: aload_0
     173: iconst_1
     174: aaload
     175: aload_0
     176: iconst_2
     177: aaload
     178: aload_0
     179: iconst_3
     180: aaload
     181: aload_0
     182: iconst_4
     183: aaload
     184: aload_0
     185: iconst_5
     186: aaload
     187: aload_0
     188: bipush        6
     190: aaload
     191: aload_0
     192: bipush        7
     194: aaload
     195: invokestatic  #10                 // Method create8:(Ljava/lang/Object;Ljava/lang/Object;Ljava/lang/Object;Ljava/lang/Object;Ljava/lang/Object;Ljava/lang/Object;Ljava/lang/Object;Ljava/lang/Object;)Lorg/apache/jena/atlas/lib/tuple/Tuple8;
     198: areturn
     199: aload_0
     200: invokestatic  #11                 // Method asTuple:([Ljava/lang/Object;)Lorg/apache/jena/atlas/lib/tuple/Tuple;
     203: areturn

  public static <X> org.apache.jena.atlas.lib.tuple.Tuple<X> create(X[]);
    Code:
       0: aload_0
       1: arraylength
       2: tableswitch   { // 0 to 8
                     0: 52
                     1: 56
                     2: 63
                     3: 73
                     4: 86
                     5: 102
                     6: 121
                     7: 143
                     8: 169
               default: 199
          }
      52: invokestatic  #2                  // Method create0:()Lorg/apache/jena/atlas/lib/tuple/Tuple0;
      55: areturn
      56: aload_0
      57: iconst_0
      58: aaload
      59: invokestatic  #3                  // Method create1:(Ljava/lang/Object;)Lorg/apache/jena/atlas/lib/tuple/Tuple1;
      62: areturn
      63: aload_0
      64: iconst_0
      65: aaload
      66: aload_0
      67: iconst_1
      68: aaload
      69: invokestatic  #4                  // Method create2:(Ljava/lang/Object;Ljava/lang/Object;)Lorg/apache/jena/atlas/lib/tuple/Tuple2;
      72: areturn
      73: aload_0
      74: iconst_0
      75: aaload
      76: aload_0
      77: iconst_1
      78: aaload
      79: aload_0
      80: iconst_2
      81: aaload
      82: invokestatic  #5                  // Method create3:(Ljava/lang/Object;Ljava/lang/Object;Ljava/lang/Object;)Lorg/apache/jena/atlas/lib/tuple/Tuple3;
      85: areturn
      86: aload_0
      87: iconst_0
      88: aaload
      89: aload_0
      90: iconst_1
      91: aaload
      92: aload_0
      93: iconst_2
      94: aaload
      95: aload_0
      96: iconst_3
      97: aaload
      98: invokestatic  #6                  // Method create4:(Ljava/lang/Object;Ljava/lang/Object;Ljava/lang/Object;Ljava/lang/Object;)Lorg/apache/jena/atlas/lib/tuple/Tuple4;
     101: areturn
     102: aload_0
     103: iconst_0
     104: aaload
     105: aload_0
     106: iconst_1
     107: aaload
     108: aload_0
     109: iconst_2
     110: aaload
     111: aload_0
     112: iconst_3
     113: aaload
     114: aload_0
     115: iconst_4
     116: aaload
     117: invokestatic  #7                  // Method create5:(Ljava/lang/Object;Ljava/lang/Object;Ljava/lang/Object;Ljava/lang/Object;Ljava/lang/Object;)Lorg/apache/jena/atlas/lib/tuple/Tuple5;
     120: areturn
     121: aload_0
     122: iconst_0
     123: aaload
     124: aload_0
     125: iconst_1
     126: aaload
     127: aload_0
     128: iconst_2
     129: aaload
     130: aload_0
     131: iconst_3
     132: aaload
     133: aload_0
     134: iconst_4
     135: aaload
     136: aload_0
     137: iconst_5
     138: aaload
     139: invokestatic  #8                  // Method create6:(Ljava/lang/Object;Ljava/lang/Object;Ljava/lang/Object;Ljava/lang/Object;Ljava/lang/Object;Ljava/lang/Object;)Lorg/apache/jena/atlas/lib/tuple/Tuple6;
     142: areturn
     143: aload_0
     144: iconst_0
     145: aaload
     146: aload_0
     147: iconst_1
     148: aaload
     149: aload_0
     150: iconst_2
     151: aaload
     152: aload_0
     153: iconst_3
     154: aaload
     155: aload_0
     156: iconst_4
     157: aaload
     158: aload_0
     159: iconst_5
     160: aaload
     161: aload_0
     162: bipush        6
     164: aaload
     165: invokestatic  #9                  // Method create7:(Ljava/lang/Object;Ljava/lang/Object;Ljava/lang/Object;Ljava/lang/Object;Ljava/lang/Object;Ljava/lang/Object;Ljava/lang/Object;)Lorg/apache/jena/atlas/lib/tuple/Tuple7;
     168: areturn
     169: aload_0
     170: iconst_0
     171: aaload
     172: aload_0
     173: iconst_1
     174: aaload
     175: aload_0
     176: iconst_2
     177: aaload
     178: aload_0
     179: iconst_3
     180: aaload
     181: aload_0
     182: iconst_4
     183: aaload
     184: aload_0
     185: iconst_5
     186: aaload
     187: aload_0
     188: bipush        6
     190: aaload
     191: aload_0
     192: bipush        7
     194: aaload
     195: invokestatic  #10                 // Method create8:(Ljava/lang/Object;Ljava/lang/Object;Ljava/lang/Object;Ljava/lang/Object;Ljava/lang/Object;Ljava/lang/Object;Ljava/lang/Object;Ljava/lang/Object;)Lorg/apache/jena/atlas/lib/tuple/Tuple8;
     198: areturn
     199: aload_0
     200: invokestatic  #12                 // Method org/apache/jena/atlas/lib/tuple/TupleN.create:([Ljava/lang/Object;)Lorg/apache/jena/atlas/lib/tuple/TupleN;
     203: areturn

  public static <X> org.apache.jena.atlas.lib.tuple.Tuple<X> asTuple(X[]);
    Code:
       0: aload_0
       1: invokestatic  #13                 // Method org/apache/jena/atlas/lib/tuple/TupleN.wrap:([Ljava/lang/Object;)Lorg/apache/jena/atlas/lib/tuple/TupleN;
       4: areturn

  public static <X> org.apache.jena.atlas.lib.tuple.Tuple<X> create(java.util.List<X>);
    Code:
       0: aload_0
       1: invokeinterface #14,  1           // InterfaceMethod java/util/List.size:()I
       6: anewarray     #15                 // class java/lang/Object
       9: checkcast     #16                 // class "[Ljava/lang/Object;"
      12: astore_1
      13: aload_0
      14: aload_1
      15: invokeinterface #17,  2           // InterfaceMethod java/util/List.toArray:([Ljava/lang/Object;)[Ljava/lang/Object;
      20: invokestatic  #18                 // Method tuple:([Ljava/lang/Object;)Lorg/apache/jena/atlas/lib/tuple/Tuple;
      23: areturn

  public static <X> org.apache.jena.atlas.lib.tuple.Tuple0<X> create0();
    Code:
       0: new           #19                 // class org/apache/jena/atlas/lib/tuple/Tuple0
       3: dup
       4: invokespecial #20                 // Method org/apache/jena/atlas/lib/tuple/Tuple0."<init>":()V
       7: areturn

  public static <X> org.apache.jena.atlas.lib.tuple.Tuple1<X> create1(X);
    Code:
       0: new           #21                 // class org/apache/jena/atlas/lib/tuple/Tuple1
       3: dup
       4: aload_0
       5: invokespecial #22                 // Method org/apache/jena/atlas/lib/tuple/Tuple1."<init>":(Ljava/lang/Object;)V
       8: areturn

  public static <X> org.apache.jena.atlas.lib.tuple.Tuple2<X> create2(X, X);
    Code:
       0: new           #23                 // class org/apache/jena/atlas/lib/tuple/Tuple2
       3: dup
       4: aload_0
       5: aload_1
       6: invokespecial #24                 // Method org/apache/jena/atlas/lib/tuple/Tuple2."<init>":(Ljava/lang/Object;Ljava/lang/Object;)V
       9: areturn

  public static <X> org.apache.jena.atlas.lib.tuple.Tuple3<X> create3(X, X, X);
    Code:
       0: new           #25                 // class org/apache/jena/atlas/lib/tuple/Tuple3
       3: dup
       4: aload_0
       5: aload_1
       6: aload_2
       7: invokespecial #26                 // Method org/apache/jena/atlas/lib/tuple/Tuple3."<init>":(Ljava/lang/Object;Ljava/lang/Object;Ljava/lang/Object;)V
      10: areturn

  public static <X> org.apache.jena.atlas.lib.tuple.Tuple4<X> create4(X, X, X, X);
    Code:
       0: new           #27                 // class org/apache/jena/atlas/lib/tuple/Tuple4
       3: dup
       4: aload_0
       5: aload_1
       6: aload_2
       7: aload_3
       8: invokespecial #28                 // Method org/apache/jena/atlas/lib/tuple/Tuple4."<init>":(Ljava/lang/Object;Ljava/lang/Object;Ljava/lang/Object;Ljava/lang/Object;)V
      11: areturn

  public static <X> org.apache.jena.atlas.lib.tuple.Tuple5<X> create5(X, X, X, X, X);
    Code:
       0: new           #29                 // class org/apache/jena/atlas/lib/tuple/Tuple5
       3: dup
       4: aload_0
       5: aload_1
       6: aload_2
       7: aload_3
       8: aload         4
      10: invokespecial #30                 // Method org/apache/jena/atlas/lib/tuple/Tuple5."<init>":(Ljava/lang/Object;Ljava/lang/Object;Ljava/lang/Object;Ljava/lang/Object;Ljava/lang/Object;)V
      13: areturn

  public static <X> org.apache.jena.atlas.lib.tuple.Tuple6<X> create6(X, X, X, X, X, X);
    Code:
       0: new           #31                 // class org/apache/jena/atlas/lib/tuple/Tuple6
       3: dup
       4: aload_0
       5: aload_1
       6: aload_2
       7: aload_3
       8: aload         4
      10: aload         5
      12: invokespecial #32                 // Method org/apache/jena/atlas/lib/tuple/Tuple6."<init>":(Ljava/lang/Object;Ljava/lang/Object;Ljava/lang/Object;Ljava/lang/Object;Ljava/lang/Object;Ljava/lang/Object;)V
      15: areturn

  public static <X> org.apache.jena.atlas.lib.tuple.Tuple7<X> create7(X, X, X, X, X, X, X);
    Code:
       0: new           #33                 // class org/apache/jena/atlas/lib/tuple/Tuple7
       3: dup
       4: aload_0
       5: aload_1
       6: aload_2
       7: aload_3
       8: aload         4
      10: aload         5
      12: aload         6
      14: invokespecial #34                 // Method org/apache/jena/atlas/lib/tuple/Tuple7."<init>":(Ljava/lang/Object;Ljava/lang/Object;Ljava/lang/Object;Ljava/lang/Object;Ljava/lang/Object;Ljava/lang/Object;Ljava/lang/Object;)V
      17: areturn

  public static <X> org.apache.jena.atlas.lib.tuple.Tuple8<X> create8(X, X, X, X, X, X, X, X);
    Code:
       0: new           #35                 // class org/apache/jena/atlas/lib/tuple/Tuple8
       3: dup
       4: aload_0
       5: aload_1
       6: aload_2
       7: aload_3
       8: aload         4
      10: aload         5
      12: aload         6
      14: aload         7
      16: invokespecial #36                 // Method org/apache/jena/atlas/lib/tuple/Tuple8."<init>":(Ljava/lang/Object;Ljava/lang/Object;Ljava/lang/Object;Ljava/lang/Object;Ljava/lang/Object;Ljava/lang/Object;Ljava/lang/Object;Ljava/lang/Object;)V
      19: areturn
}
