Compiled from "DirectoryDescendingFileFinderImpl.java"
public class com.mchange.io.impl.DirectoryDescendingFileFinderImpl implements com.mchange.io.IOEnumeration,com.mchange.io.FileEnumeration {
  private static final java.lang.Object dummy;

  java.util.Hashtable markedDirex;

  java.util.Stack direx;

  java.util.Stack files;

  java.io.FilenameFilter filter;

  boolean canonical;

  public com.mchange.io.impl.DirectoryDescendingFileFinderImpl(java.io.File, java.io.FilenameFilter, boolean) throws java.io.IOException;
    Code:
       0: aload_0
       1: invokespecial #1                  // Method java/lang/Object."<init>":()V
       4: aload_0
       5: new           #2                  // class java/util/Hashtable
       8: dup
       9: invokespecial #3                  // Method java/util/Hashtable."<init>":()V
      12: putfield      #4                  // Field markedDirex:Ljava/util/Hashtable;
      15: aload_0
      16: new           #5                  // class java/util/Stack
      19: dup
      20: invokespecial #6                  // Method java/util/Stack."<init>":()V
      23: putfield      #7                  // Field direx:Ljava/util/Stack;
      26: aload_0
      27: new           #5                  // class java/util/Stack
      30: dup
      31: invokespecial #6                  // Method java/util/Stack."<init>":()V
      34: putfield      #8                  // Field files:Ljava/util/Stack;
      37: aload_1
      38: invokevirtual #9                  // Method java/io/File.isDirectory:()Z
      41: ifne          74
      44: new           #10                 // class java/lang/IllegalArgumentException
      47: dup
      48: new           #11                 // class java/lang/StringBuilder
      51: dup
      52: invokespecial #12                 // Method java/lang/StringBuilder."<init>":()V
      55: aload_1
      56: invokevirtual #13                 // Method java/io/File.getName:()Ljava/lang/String;
      59: invokevirtual #14                 // Method java/lang/StringBuilder.append:(Ljava/lang/String;)Ljava/lang/StringBuilder;
      62: ldc           #15                 // String  is not a directory.
      64: invokevirtual #14                 // Method java/lang/StringBuilder.append:(Ljava/lang/String;)Ljava/lang/StringBuilder;
      67: invokevirtual #16                 // Method java/lang/StringBuilder.toString:()Ljava/lang/String;
      70: invokespecial #17                 // Method java/lang/IllegalArgumentException."<init>":(Ljava/lang/String;)V
      73: athrow
      74: aload_0
      75: aload_2
      76: putfield      #18                 // Field filter:Ljava/io/FilenameFilter;
      79: aload_0
      80: iload_3
      81: putfield      #19                 // Field canonical:Z
      84: aload_0
      85: aload_1
      86: invokespecial #20                 // Method blossomDirectory:(Ljava/io/File;)V
      89: aload_0
      90: getfield      #8                  // Field files:Ljava/util/Stack;
      93: invokevirtual #21                 // Method java/util/Stack.empty:()Z
      96: ifeq          126
      99: aload_0
     100: getfield      #7                  // Field direx:Ljava/util/Stack;
     103: invokevirtual #21                 // Method java/util/Stack.empty:()Z
     106: ifne          126
     109: aload_0
     110: aload_0
     111: getfield      #7                  // Field direx:Ljava/util/Stack;
     114: invokevirtual #22                 // Method java/util/Stack.pop:()Ljava/lang/Object;
     117: checkcast     #23                 // class java/io/File
     120: invokespecial #20                 // Method blossomDirectory:(Ljava/io/File;)V
     123: goto          89
     126: return

  public com.mchange.io.impl.DirectoryDescendingFileFinderImpl(java.io.File) throws java.io.IOException;
    Code:
       0: aload_0
       1: aload_1
       2: aconst_null
       3: iconst_0
       4: invokespecial #24                 // Method "<init>":(Ljava/io/File;Ljava/io/FilenameFilter;Z)V
       7: return

  public boolean hasMoreFiles();
    Code:
       0: aload_0
       1: getfield      #8                  // Field files:Ljava/util/Stack;
       4: invokevirtual #21                 // Method java/util/Stack.empty:()Z
       7: ifne          14
      10: iconst_1
      11: goto          15
      14: iconst_0
      15: ireturn

  public java.io.File nextFile() throws java.io.IOException;
    Code:
       0: aload_0
       1: getfield      #8                  // Field files:Ljava/util/Stack;
       4: invokevirtual #21                 // Method java/util/Stack.empty:()Z
       7: ifeq          18
      10: new           #25                 // class java/util/NoSuchElementException
      13: dup
      14: invokespecial #26                 // Method java/util/NoSuchElementException."<init>":()V
      17: athrow
      18: aload_0
      19: getfield      #8                  // Field files:Ljava/util/Stack;
      22: invokevirtual #22                 // Method java/util/Stack.pop:()Ljava/lang/Object;
      25: checkcast     #23                 // class java/io/File
      28: astore_1
      29: aload_0
      30: getfield      #8                  // Field files:Ljava/util/Stack;
      33: invokevirtual #21                 // Method java/util/Stack.empty:()Z
      36: ifeq          66
      39: aload_0
      40: getfield      #7                  // Field direx:Ljava/util/Stack;
      43: invokevirtual #21                 // Method java/util/Stack.empty:()Z
      46: ifne          66
      49: aload_0
      50: aload_0
      51: getfield      #7                  // Field direx:Ljava/util/Stack;
      54: invokevirtual #22                 // Method java/util/Stack.pop:()Ljava/lang/Object;
      57: checkcast     #23                 // class java/io/File
      60: invokespecial #20                 // Method blossomDirectory:(Ljava/io/File;)V
      63: goto          29
      66: aload_1
      67: areturn

  public boolean hasMoreElements();
    Code:
       0: aload_0
       1: invokevirtual #27                 // Method hasMoreFiles:()Z
       4: ireturn

  public java.lang.Object nextElement() throws java.io.IOException;
    Code:
       0: aload_0
       1: invokevirtual #28                 // Method nextFile:()Ljava/io/File;
       4: areturn

  private void blossomDirectory(java.io.File) throws java.io.IOException;
    Code:
       0: aload_1
       1: invokevirtual #29                 // Method java/io/File.getCanonicalPath:()Ljava/lang/String;
       4: astore_2
       5: aload_0
       6: getfield      #18                 // Field filter:Ljava/io/FilenameFilter;
       9: ifnonnull     19
      12: aload_1
      13: invokevirtual #30                 // Method java/io/File.list:()[Ljava/lang/String;
      16: goto          27
      19: aload_1
      20: aload_0
      21: getfield      #18                 // Field filter:Ljava/io/FilenameFilter;
      24: invokevirtual #31                 // Method java/io/File.list:(Ljava/io/FilenameFilter;)[Ljava/lang/String;
      27: astore_3
      28: aload_3
      29: arraylength
      30: istore        4
      32: iinc          4, -1
      35: iload         4
      37: iflt          167
      40: aload_0
      41: getfield      #18                 // Field filter:Ljava/io/FilenameFilter;
      44: ifnull        64
      47: aload_0
      48: getfield      #18                 // Field filter:Ljava/io/FilenameFilter;
      51: aload_1
      52: aload_3
      53: iload         4
      55: aaload
      56: invokeinterface #32,  3           // InterfaceMethod java/io/FilenameFilter.accept:(Ljava/io/File;Ljava/lang/String;)Z
      61: ifeq          32
      64: new           #11                 // class java/lang/StringBuilder
      67: dup
      68: invokespecial #12                 // Method java/lang/StringBuilder."<init>":()V
      71: aload_0
      72: getfield      #19                 // Field canonical:Z
      75: ifeq          82
      78: aload_2
      79: goto          86
      82: aload_1
      83: invokevirtual #33                 // Method java/io/File.getPath:()Ljava/lang/String;
      86: invokevirtual #14                 // Method java/lang/StringBuilder.append:(Ljava/lang/String;)Ljava/lang/StringBuilder;
      89: getstatic     #34                 // Field java/io/File.separator:Ljava/lang/String;
      92: invokevirtual #14                 // Method java/lang/StringBuilder.append:(Ljava/lang/String;)Ljava/lang/StringBuilder;
      95: aload_3
      96: iload         4
      98: aaload
      99: invokevirtual #14                 // Method java/lang/StringBuilder.append:(Ljava/lang/String;)Ljava/lang/StringBuilder;
     102: invokevirtual #16                 // Method java/lang/StringBuilder.toString:()Ljava/lang/String;
     105: astore        5
     107: new           #23                 // class java/io/File
     110: dup
     111: aload         5
     113: invokespecial #35                 // Method java/io/File."<init>":(Ljava/lang/String;)V
     116: astore        6
     118: aload         6
     120: invokevirtual #36                 // Method java/io/File.isFile:()Z
     123: ifeq          139
     126: aload_0
     127: getfield      #8                  // Field files:Ljava/util/Stack;
     130: aload         6
     132: invokevirtual #37                 // Method java/util/Stack.push:(Ljava/lang/Object;)Ljava/lang/Object;
     135: pop
     136: goto          164
     139: aload_0
     140: getfield      #4                  // Field markedDirex:Ljava/util/Hashtable;
     143: aload         6
     145: invokevirtual #29                 // Method java/io/File.getCanonicalPath:()Ljava/lang/String;
     148: invokevirtual #38                 // Method java/util/Hashtable.containsKey:(Ljava/lang/Object;)Z
     151: ifne          164
     154: aload_0
     155: getfield      #7                  // Field direx:Ljava/util/Stack;
     158: aload         6
     160: invokevirtual #37                 // Method java/util/Stack.push:(Ljava/lang/Object;)Ljava/lang/Object;
     163: pop
     164: goto          32
     167: aload_0
     168: getfield      #4                  // Field markedDirex:Ljava/util/Hashtable;
     171: aload_2
     172: getstatic     #39                 // Field dummy:Ljava/lang/Object;
     175: invokevirtual #40                 // Method java/util/Hashtable.put:(Ljava/lang/Object;Ljava/lang/Object;)Ljava/lang/Object;
     178: pop
     179: return

  public static void main(java.lang.String[]);
    Code:
       0: new           #23                 // class java/io/File
       3: dup
       4: aload_0
       5: iconst_0
       6: aaload
       7: invokespecial #35                 // Method java/io/File."<init>":(Ljava/lang/String;)V
      10: astore_1
      11: new           #41                 // class com/mchange/io/impl/DirectoryDescendingFileFinderImpl
      14: dup
      15: aload_1
      16: invokespecial #42                 // Method "<init>":(Ljava/io/File;)V
      19: astore_2
      20: aload_2
      21: invokeinterface #43,  1           // InterfaceMethod com/mchange/io/FileEnumeration.hasMoreFiles:()Z
      26: ifeq          47
      29: getstatic     #44                 // Field java/lang/System.out:Ljava/io/PrintStream;
      32: aload_2
      33: invokeinterface #45,  1           // InterfaceMethod com/mchange/io/FileEnumeration.nextFile:()Ljava/io/File;
      38: invokevirtual #46                 // Method java/io/File.getAbsolutePath:()Ljava/lang/String;
      41: invokevirtual #47                 // Method java/io/PrintStream.println:(Ljava/lang/String;)V
      44: goto          20
      47: goto          55
      50: astore_1
      51: aload_1
      52: invokevirtual #49                 // Method java/lang/Exception.printStackTrace:()V
      55: return
    Exception table:
       from    to  target type
           0    47    50   Class java/lang/Exception

  static {};
    Code:
       0: new           #50                 // class java/lang/Object
       3: dup
       4: invokespecial #1                  // Method java/lang/Object."<init>":()V
       7: putstatic     #39                 // Field dummy:Ljava/lang/Object;
      10: return
}
