Compiled from "ReferenceFinder.java"
public final class org.protege.editor.owl.model.util.ReferenceFinder$ReferenceSet {
  private final org.semanticweb.owlapi.model.OWLOntology ontology;

  private final com.google.common.collect.ImmutableCollection<org.semanticweb.owlapi.model.OWLAxiom> referencingAxioms;

  private final com.google.common.collect.ImmutableCollection<org.semanticweb.owlapi.model.OWLAnnotation> referencingOntologyAnnotations;

  public org.protege.editor.owl.model.util.ReferenceFinder$ReferenceSet(org.semanticweb.owlapi.model.OWLOntology, com.google.common.collect.ImmutableCollection<org.semanticweb.owlapi.model.OWLAxiom>, com.google.common.collect.ImmutableCollection<org.semanticweb.owlapi.model.OWLAnnotation>);
    Code:
       0: aload_0
       1: invokespecial #1                  // Method java/lang/Object."<init>":()V
       4: aload_0
       5: aload_1
       6: invokestatic  #2                  // Method com/google/common/base/Preconditions.checkNotNull:(Ljava/lang/Object;)Ljava/lang/Object;
       9: checkcast     #3                  // class org/semanticweb/owlapi/model/OWLOntology
      12: putfield      #4                  // Field ontology:Lorg/semanticweb/owlapi/model/OWLOntology;
      15: aload_0
      16: aload_2
      17: invokestatic  #2                  // Method com/google/common/base/Preconditions.checkNotNull:(Ljava/lang/Object;)Ljava/lang/Object;
      20: checkcast     #5                  // class com/google/common/collect/ImmutableCollection
      23: putfield      #6                  // Field referencingAxioms:Lcom/google/common/collect/ImmutableCollection;
      26: aload_0
      27: aload_3
      28: invokestatic  #2                  // Method com/google/common/base/Preconditions.checkNotNull:(Ljava/lang/Object;)Ljava/lang/Object;
      31: checkcast     #5                  // class com/google/common/collect/ImmutableCollection
      34: putfield      #7                  // Field referencingOntologyAnnotations:Lcom/google/common/collect/ImmutableCollection;
      37: return

  public org.semanticweb.owlapi.model.OWLOntology getOntology();
    Code:
       0: aload_0
       1: getfield      #4                  // Field ontology:Lorg/semanticweb/owlapi/model/OWLOntology;
       4: areturn

  public com.google.common.collect.ImmutableCollection<org.semanticweb.owlapi.model.OWLAxiom> getReferencingAxioms();
    Code:
       0: aload_0
       1: getfield      #6                  // Field referencingAxioms:Lcom/google/common/collect/ImmutableCollection;
       4: areturn

  public com.google.common.collect.ImmutableCollection<org.semanticweb.owlapi.model.OWLAnnotation> getReferencingOntologyAnnotations();
    Code:
       0: aload_0
       1: getfield      #7                  // Field referencingOntologyAnnotations:Lcom/google/common/collect/ImmutableCollection;
       4: areturn
}
