Compiled from "Pointcut.java"
public abstract class org.aspectj.weaver.patterns.Pointcut extends org.aspectj.weaver.patterns.PatternNode {
  public java.lang.String[] m_ignoreUnboundBindingForNames;

  public static final java.lang.String[] EMPTY_STRING_ARRAY;

  public static final org.aspectj.weaver.patterns.Pointcut$State SYMBOLIC;

  public static final org.aspectj.weaver.patterns.Pointcut$State RESOLVED;

  public static final org.aspectj.weaver.patterns.Pointcut$State CONCRETE;

  protected byte pointcutKind;

  public org.aspectj.weaver.patterns.Pointcut$State state;

  protected int lastMatchedShadowId;

  private org.aspectj.util.FuzzyBoolean lastMatchedShadowResult;

  private java.lang.String[] typeVariablesInScope;

  protected boolean hasBeenParameterized;

  public static final byte KINDED;

  public static final byte WITHIN;

  public static final byte THIS_OR_TARGET;

  public static final byte ARGS;

  public static final byte AND;

  public static final byte OR;

  public static final byte NOT;

  public static final byte REFERENCE;

  public static final byte IF;

  public static final byte CFLOW;

  public static final byte WITHINCODE;

  public static final byte HANDLER;

  public static final byte IF_TRUE;

  public static final byte IF_FALSE;

  public static final byte ANNOTATION;

  public static final byte ATWITHIN;

  public static final byte ATWITHINCODE;

  public static final byte ATTHIS_OR_TARGET;

  public static final byte NONE;

  public static final byte ATARGS;

  public static final byte USER_EXTENSION;

  public org.aspectj.weaver.patterns.Pointcut();
    Code:
       0: aload_0
       1: invokespecial #1                  // Method org/aspectj/weaver/patterns/PatternNode."<init>":()V
       4: aload_0
       5: getstatic     #2                  // Field EMPTY_STRING_ARRAY:[Ljava/lang/String;
       8: putfield      #3                  // Field m_ignoreUnboundBindingForNames:[Ljava/lang/String;
      11: aload_0
      12: getstatic     #2                  // Field EMPTY_STRING_ARRAY:[Ljava/lang/String;
      15: putfield      #4                  // Field typeVariablesInScope:[Ljava/lang/String;
      18: aload_0
      19: iconst_0
      20: putfield      #5                  // Field hasBeenParameterized:Z
      23: aload_0
      24: getstatic     #6                  // Field SYMBOLIC:Lorg/aspectj/weaver/patterns/Pointcut$State;
      27: putfield      #7                  // Field state:Lorg/aspectj/weaver/patterns/Pointcut$State;
      30: return

  public abstract org.aspectj.util.FuzzyBoolean fastMatch(org.aspectj.weaver.patterns.FastMatchInfo);

  public abstract int couldMatchKinds();

  public java.lang.String[] getTypeVariablesInScope();
    Code:
       0: aload_0
       1: getfield      #4                  // Field typeVariablesInScope:[Ljava/lang/String;
       4: areturn

  public void setTypeVariablesInScope(java.lang.String[]);
    Code:
       0: aload_0
       1: aload_1
       2: putfield      #4                  // Field typeVariablesInScope:[Ljava/lang/String;
       5: return

  public final org.aspectj.util.FuzzyBoolean match(org.aspectj.weaver.Shadow);
    Code:
       0: aload_1
       1: getfield      #8                  // Field org/aspectj/weaver/Shadow.shadowId:I
       4: aload_0
       5: getfield      #9                  // Field lastMatchedShadowId:I
       8: if_icmpne     16
      11: aload_0
      12: getfield      #10                 // Field lastMatchedShadowResult:Lorg/aspectj/util/FuzzyBoolean;
      15: areturn
      16: aload_1
      17: invokevirtual #11                 // Method org/aspectj/weaver/Shadow.getKind:()Lorg/aspectj/weaver/Shadow$Kind;
      20: aload_0
      21: invokevirtual #12                 // Method couldMatchKinds:()I
      24: invokevirtual #13                 // Method org/aspectj/weaver/Shadow$Kind.isSet:(I)Z
      27: ifeq          39
      30: aload_0
      31: aload_1
      32: invokevirtual #14                 // Method matchInternal:(Lorg/aspectj/weaver/Shadow;)Lorg/aspectj/util/FuzzyBoolean;
      35: astore_2
      36: goto          43
      39: getstatic     #15                 // Field org/aspectj/util/FuzzyBoolean.NO:Lorg/aspectj/util/FuzzyBoolean;
      42: astore_2
      43: aload_0
      44: aload_1
      45: getfield      #8                  // Field org/aspectj/weaver/Shadow.shadowId:I
      48: putfield      #9                  // Field lastMatchedShadowId:I
      51: aload_0
      52: aload_2
      53: putfield      #10                 // Field lastMatchedShadowResult:Lorg/aspectj/util/FuzzyBoolean;
      56: aload_2
      57: areturn

  protected abstract org.aspectj.util.FuzzyBoolean matchInternal(org.aspectj.weaver.Shadow);

  public byte getPointcutKind();
    Code:
       0: aload_0
       1: getfield      #16                 // Field pointcutKind:B
       4: ireturn

  protected abstract void resolveBindings(org.aspectj.weaver.patterns.IScope, org.aspectj.weaver.patterns.Bindings);

  public final org.aspectj.weaver.patterns.Pointcut resolve(org.aspectj.weaver.patterns.IScope);
    Code:
       0: aload_0
       1: getstatic     #6                  // Field SYMBOLIC:Lorg/aspectj/weaver/patterns/Pointcut$State;
       4: invokevirtual #17                 // Method assertState:(Lorg/aspectj/weaver/patterns/Pointcut$State;)V
       7: new           #18                 // class org/aspectj/weaver/patterns/Bindings
      10: dup
      11: aload_1
      12: invokeinterface #19,  1           // InterfaceMethod org/aspectj/weaver/patterns/IScope.getFormalCount:()I
      17: invokespecial #20                 // Method org/aspectj/weaver/patterns/Bindings."<init>":(I)V
      20: astore_2
      21: aload_1
      22: astore_3
      23: aload_0
      24: getfield      #4                  // Field typeVariablesInScope:[Ljava/lang/String;
      27: arraylength
      28: ifle          44
      31: new           #21                 // class org/aspectj/weaver/patterns/ScopeWithTypeVariables
      34: dup
      35: aload_0
      36: getfield      #4                  // Field typeVariablesInScope:[Ljava/lang/String;
      39: aload_1
      40: invokespecial #22                 // Method org/aspectj/weaver/patterns/ScopeWithTypeVariables."<init>":([Ljava/lang/String;Lorg/aspectj/weaver/patterns/IScope;)V
      43: astore_3
      44: aload_0
      45: aload_3
      46: aload_2
      47: invokevirtual #23                 // Method resolveBindings:(Lorg/aspectj/weaver/patterns/IScope;Lorg/aspectj/weaver/patterns/Bindings;)V
      50: aload_2
      51: aload_3
      52: invokevirtual #24                 // Method org/aspectj/weaver/patterns/Bindings.checkAllBound:(Lorg/aspectj/weaver/patterns/IScope;)V
      55: aload_0
      56: getstatic     #25                 // Field RESOLVED:Lorg/aspectj/weaver/patterns/Pointcut$State;
      59: putfield      #7                  // Field state:Lorg/aspectj/weaver/patterns/Pointcut$State;
      62: aload_0
      63: areturn

  public final org.aspectj.weaver.patterns.Pointcut concretize(org.aspectj.weaver.ResolvedType, org.aspectj.weaver.ResolvedType, int);
    Code:
       0: aload_0
       1: aload_1
       2: aload_2
       3: iload_3
       4: invokestatic  #26                 // Method org/aspectj/weaver/IntMap.idMap:(I)Lorg/aspectj/weaver/IntMap;
       7: invokevirtual #27                 // Method concretize:(Lorg/aspectj/weaver/ResolvedType;Lorg/aspectj/weaver/ResolvedType;Lorg/aspectj/weaver/IntMap;)Lorg/aspectj/weaver/patterns/Pointcut;
      10: astore        4
      12: aload         4
      14: aload_0
      15: getfield      #3                  // Field m_ignoreUnboundBindingForNames:[Ljava/lang/String;
      18: putfield      #3                  // Field m_ignoreUnboundBindingForNames:[Ljava/lang/String;
      21: aload         4
      23: areturn

  public final org.aspectj.weaver.patterns.Pointcut concretize(org.aspectj.weaver.ResolvedType, org.aspectj.weaver.ResolvedType, int, org.aspectj.weaver.ShadowMunger);
    Code:
       0: iload_3
       1: invokestatic  #26                 // Method org/aspectj/weaver/IntMap.idMap:(I)Lorg/aspectj/weaver/IntMap;
       4: astore        5
       6: aload         5
       8: aload         4
      10: invokevirtual #28                 // Method org/aspectj/weaver/IntMap.setEnclosingAdvice:(Lorg/aspectj/weaver/ShadowMunger;)V
      13: aload         5
      15: aload_1
      16: invokevirtual #29                 // Method org/aspectj/weaver/IntMap.setConcreteAspect:(Lorg/aspectj/weaver/ResolvedType;)V
      19: aload_0
      20: aload_1
      21: aload_2
      22: aload         5
      24: invokevirtual #27                 // Method concretize:(Lorg/aspectj/weaver/ResolvedType;Lorg/aspectj/weaver/ResolvedType;Lorg/aspectj/weaver/IntMap;)Lorg/aspectj/weaver/patterns/Pointcut;
      27: areturn

  public boolean isDeclare(org.aspectj.weaver.ShadowMunger);
    Code:
       0: aload_1
       1: ifnonnull     6
       4: iconst_0
       5: ireturn
       6: aload_1
       7: instanceof    #30                 // class org/aspectj/weaver/Checker
      10: ifeq          15
      13: iconst_1
      14: ireturn
      15: aload_1
      16: checkcast     #31                 // class org/aspectj/weaver/Advice
      19: invokevirtual #32                 // Method org/aspectj/weaver/Advice.getKind:()Lorg/aspectj/weaver/AdviceKind;
      22: getstatic     #33                 // Field org/aspectj/weaver/AdviceKind.Softener:Lorg/aspectj/weaver/AdviceKind;
      25: invokevirtual #34                 // Method java/lang/Object.equals:(Ljava/lang/Object;)Z
      28: ifeq          33
      31: iconst_1
      32: ireturn
      33: iconst_0
      34: ireturn

  public final org.aspectj.weaver.patterns.Pointcut concretize(org.aspectj.weaver.ResolvedType, org.aspectj.weaver.ResolvedType, org.aspectj.weaver.IntMap);
    Code:
       0: aload_0
       1: aload_1
       2: aload_2
       3: aload_3
       4: invokevirtual #35                 // Method concretize1:(Lorg/aspectj/weaver/ResolvedType;Lorg/aspectj/weaver/ResolvedType;Lorg/aspectj/weaver/IntMap;)Lorg/aspectj/weaver/patterns/Pointcut;
       7: astore        4
       9: aload_0
      10: invokevirtual #36                 // Method shouldCopyLocationForConcretize:()Z
      13: ifeq          22
      16: aload         4
      18: aload_0
      19: invokevirtual #37                 // Method copyLocationFrom:(Lorg/aspectj/weaver/patterns/PatternNode;)V
      22: aload         4
      24: getstatic     #38                 // Field CONCRETE:Lorg/aspectj/weaver/patterns/Pointcut$State;
      27: putfield      #7                  // Field state:Lorg/aspectj/weaver/patterns/Pointcut$State;
      30: aload         4
      32: aload_0
      33: getfield      #3                  // Field m_ignoreUnboundBindingForNames:[Ljava/lang/String;
      36: putfield      #3                  // Field m_ignoreUnboundBindingForNames:[Ljava/lang/String;
      39: aload         4
      41: areturn

  protected boolean shouldCopyLocationForConcretize();
    Code:
       0: iconst_1
       1: ireturn

  protected abstract org.aspectj.weaver.patterns.Pointcut concretize1(org.aspectj.weaver.ResolvedType, org.aspectj.weaver.ResolvedType, org.aspectj.weaver.IntMap);

  public final org.aspectj.weaver.ast.Test findResidue(org.aspectj.weaver.Shadow, org.aspectj.weaver.patterns.ExposedState);
    Code:
       0: aload_0
       1: aload_1
       2: aload_2
       3: invokevirtual #39                 // Method findResidueInternal:(Lorg/aspectj/weaver/Shadow;Lorg/aspectj/weaver/patterns/ExposedState;)Lorg/aspectj/weaver/ast/Test;
       6: astore_3
       7: aload_0
       8: aload_1
       9: getfield      #8                  // Field org/aspectj/weaver/Shadow.shadowId:I
      12: putfield      #9                  // Field lastMatchedShadowId:I
      15: aload_3
      16: areturn

  protected abstract org.aspectj.weaver.ast.Test findResidueInternal(org.aspectj.weaver.Shadow, org.aspectj.weaver.patterns.ExposedState);

  public void postRead(org.aspectj.weaver.ResolvedType);
    Code:
       0: return

  public static org.aspectj.weaver.patterns.Pointcut read(org.aspectj.weaver.VersionedDataInputStream, org.aspectj.weaver.ISourceContext) throws java.io.IOException;
    Code:
       0: aload_0
       1: invokevirtual #40                 // Method org/aspectj/weaver/VersionedDataInputStream.readByte:()B
       4: istore_2
       5: iload_2
       6: tableswitch   { // 1 to 21
                     1: 104
                     2: 113
                     3: 122
                     4: 131
                     5: 140
                     6: 149
                     7: 158
                     8: 167
                     9: 176
                    10: 185
                    11: 287
                    12: 194
                    13: 203
                    14: 212
                    15: 222
                    16: 232
                    17: 241
                    18: 250
                    19: 259
                    20: 277
                    21: 268
               default: 287
          }
     104: aload_0
     105: aload_1
     106: invokestatic  #41                 // Method org/aspectj/weaver/patterns/KindedPointcut.read:(Lorg/aspectj/weaver/VersionedDataInputStream;Lorg/aspectj/weaver/ISourceContext;)Lorg/aspectj/weaver/patterns/Pointcut;
     109: astore_3
     110: goto          314
     113: aload_0
     114: aload_1
     115: invokestatic  #42                 // Method org/aspectj/weaver/patterns/WithinPointcut.read:(Lorg/aspectj/weaver/VersionedDataInputStream;Lorg/aspectj/weaver/ISourceContext;)Lorg/aspectj/weaver/patterns/Pointcut;
     118: astore_3
     119: goto          314
     122: aload_0
     123: aload_1
     124: invokestatic  #43                 // Method org/aspectj/weaver/patterns/ThisOrTargetPointcut.read:(Lorg/aspectj/weaver/VersionedDataInputStream;Lorg/aspectj/weaver/ISourceContext;)Lorg/aspectj/weaver/patterns/Pointcut;
     127: astore_3
     128: goto          314
     131: aload_0
     132: aload_1
     133: invokestatic  #44                 // Method org/aspectj/weaver/patterns/ArgsPointcut.read:(Lorg/aspectj/weaver/VersionedDataInputStream;Lorg/aspectj/weaver/ISourceContext;)Lorg/aspectj/weaver/patterns/Pointcut;
     136: astore_3
     137: goto          314
     140: aload_0
     141: aload_1
     142: invokestatic  #45                 // Method org/aspectj/weaver/patterns/AndPointcut.read:(Lorg/aspectj/weaver/VersionedDataInputStream;Lorg/aspectj/weaver/ISourceContext;)Lorg/aspectj/weaver/patterns/Pointcut;
     145: astore_3
     146: goto          314
     149: aload_0
     150: aload_1
     151: invokestatic  #46                 // Method org/aspectj/weaver/patterns/OrPointcut.read:(Lorg/aspectj/weaver/VersionedDataInputStream;Lorg/aspectj/weaver/ISourceContext;)Lorg/aspectj/weaver/patterns/Pointcut;
     154: astore_3
     155: goto          314
     158: aload_0
     159: aload_1
     160: invokestatic  #47                 // Method org/aspectj/weaver/patterns/NotPointcut.read:(Lorg/aspectj/weaver/VersionedDataInputStream;Lorg/aspectj/weaver/ISourceContext;)Lorg/aspectj/weaver/patterns/Pointcut;
     163: astore_3
     164: goto          314
     167: aload_0
     168: aload_1
     169: invokestatic  #48                 // Method org/aspectj/weaver/patterns/ReferencePointcut.read:(Lorg/aspectj/weaver/VersionedDataInputStream;Lorg/aspectj/weaver/ISourceContext;)Lorg/aspectj/weaver/patterns/Pointcut;
     172: astore_3
     173: goto          314
     176: aload_0
     177: aload_1
     178: invokestatic  #49                 // Method org/aspectj/weaver/patterns/IfPointcut.read:(Lorg/aspectj/weaver/VersionedDataInputStream;Lorg/aspectj/weaver/ISourceContext;)Lorg/aspectj/weaver/patterns/Pointcut;
     181: astore_3
     182: goto          314
     185: aload_0
     186: aload_1
     187: invokestatic  #50                 // Method org/aspectj/weaver/patterns/CflowPointcut.read:(Lorg/aspectj/weaver/VersionedDataInputStream;Lorg/aspectj/weaver/ISourceContext;)Lorg/aspectj/weaver/patterns/Pointcut;
     190: astore_3
     191: goto          314
     194: aload_0
     195: aload_1
     196: invokestatic  #51                 // Method org/aspectj/weaver/patterns/WithincodePointcut.read:(Lorg/aspectj/weaver/VersionedDataInputStream;Lorg/aspectj/weaver/ISourceContext;)Lorg/aspectj/weaver/patterns/Pointcut;
     199: astore_3
     200: goto          314
     203: aload_0
     204: aload_1
     205: invokestatic  #52                 // Method org/aspectj/weaver/patterns/HandlerPointcut.read:(Lorg/aspectj/weaver/VersionedDataInputStream;Lorg/aspectj/weaver/ISourceContext;)Lorg/aspectj/weaver/patterns/Pointcut;
     208: astore_3
     209: goto          314
     212: getstatic     #25                 // Field RESOLVED:Lorg/aspectj/weaver/patterns/Pointcut$State;
     215: invokestatic  #53                 // Method org/aspectj/weaver/patterns/IfPointcut.makeIfTruePointcut:(Lorg/aspectj/weaver/patterns/Pointcut$State;)Lorg/aspectj/weaver/patterns/IfPointcut;
     218: astore_3
     219: goto          314
     222: getstatic     #25                 // Field RESOLVED:Lorg/aspectj/weaver/patterns/Pointcut$State;
     225: invokestatic  #54                 // Method org/aspectj/weaver/patterns/IfPointcut.makeIfFalsePointcut:(Lorg/aspectj/weaver/patterns/Pointcut$State;)Lorg/aspectj/weaver/patterns/IfPointcut;
     228: astore_3
     229: goto          314
     232: aload_0
     233: aload_1
     234: invokestatic  #55                 // Method org/aspectj/weaver/patterns/AnnotationPointcut.read:(Lorg/aspectj/weaver/VersionedDataInputStream;Lorg/aspectj/weaver/ISourceContext;)Lorg/aspectj/weaver/patterns/Pointcut;
     237: astore_3
     238: goto          314
     241: aload_0
     242: aload_1
     243: invokestatic  #56                 // Method org/aspectj/weaver/patterns/WithinAnnotationPointcut.read:(Lorg/aspectj/weaver/VersionedDataInputStream;Lorg/aspectj/weaver/ISourceContext;)Lorg/aspectj/weaver/patterns/Pointcut;
     246: astore_3
     247: goto          314
     250: aload_0
     251: aload_1
     252: invokestatic  #57                 // Method org/aspectj/weaver/patterns/WithinCodeAnnotationPointcut.read:(Lorg/aspectj/weaver/VersionedDataInputStream;Lorg/aspectj/weaver/ISourceContext;)Lorg/aspectj/weaver/patterns/Pointcut;
     255: astore_3
     256: goto          314
     259: aload_0
     260: aload_1
     261: invokestatic  #58                 // Method org/aspectj/weaver/patterns/ThisOrTargetAnnotationPointcut.read:(Lorg/aspectj/weaver/VersionedDataInputStream;Lorg/aspectj/weaver/ISourceContext;)Lorg/aspectj/weaver/patterns/Pointcut;
     264: astore_3
     265: goto          314
     268: aload_0
     269: aload_1
     270: invokestatic  #59                 // Method org/aspectj/weaver/patterns/ArgsAnnotationPointcut.read:(Lorg/aspectj/weaver/VersionedDataInputStream;Lorg/aspectj/weaver/ISourceContext;)Lorg/aspectj/weaver/patterns/Pointcut;
     273: astore_3
     274: goto          314
     277: getstatic     #25                 // Field RESOLVED:Lorg/aspectj/weaver/patterns/Pointcut$State;
     280: invokestatic  #60                 // Method makeMatchesNothing:(Lorg/aspectj/weaver/patterns/Pointcut$State;)Lorg/aspectj/weaver/patterns/Pointcut;
     283: astore_3
     284: goto          314
     287: new           #61                 // class org/aspectj/weaver/BCException
     290: dup
     291: new           #62                 // class java/lang/StringBuilder
     294: dup
     295: invokespecial #63                 // Method java/lang/StringBuilder."<init>":()V
     298: ldc           #64                 // String unknown kind:
     300: invokevirtual #65                 // Method java/lang/StringBuilder.append:(Ljava/lang/String;)Ljava/lang/StringBuilder;
     303: iload_2
     304: invokevirtual #66                 // Method java/lang/StringBuilder.append:(I)Ljava/lang/StringBuilder;
     307: invokevirtual #67                 // Method java/lang/StringBuilder.toString:()Ljava/lang/String;
     310: invokespecial #68                 // Method org/aspectj/weaver/BCException."<init>":(Ljava/lang/String;)V
     313: athrow
     314: aload_3
     315: getstatic     #25                 // Field RESOLVED:Lorg/aspectj/weaver/patterns/Pointcut$State;
     318: putfield      #7                  // Field state:Lorg/aspectj/weaver/patterns/Pointcut$State;
     321: aload_3
     322: iload_2
     323: putfield      #16                 // Field pointcutKind:B
     326: aload_3
     327: areturn

  public void check(org.aspectj.weaver.ISourceContext, org.aspectj.weaver.World);
    Code:
       0: new           #69                 // class org/aspectj/weaver/PoliceExtensionUse
       3: dup
       4: aload_2
       5: aload_0
       6: invokespecial #70                 // Method org/aspectj/weaver/PoliceExtensionUse."<init>":(Lorg/aspectj/weaver/World;Lorg/aspectj/weaver/patterns/Pointcut;)V
       9: astore_3
      10: aload_0
      11: aload_3
      12: aconst_null
      13: invokevirtual #71                 // Method accept:(Lorg/aspectj/weaver/patterns/PatternNodeVisitor;Ljava/lang/Object;)Ljava/lang/Object;
      16: pop
      17: aload_3
      18: invokevirtual #72                 // Method org/aspectj/weaver/PoliceExtensionUse.synchronizationDesignatorEncountered:()Z
      21: ifeq          28
      24: aload_2
      25: invokevirtual #73                 // Method org/aspectj/weaver/World.setSynchronizationPointcutsInUse:()V
      28: return

  public static org.aspectj.weaver.patterns.Pointcut fromString(java.lang.String);
    Code:
       0: new           #74                 // class org/aspectj/weaver/patterns/PatternParser
       3: dup
       4: aload_0
       5: invokespecial #75                 // Method org/aspectj/weaver/patterns/PatternParser."<init>":(Ljava/lang/String;)V
       8: astore_1
       9: aload_1
      10: invokevirtual #76                 // Method org/aspectj/weaver/patterns/PatternParser.parsePointcut:()Lorg/aspectj/weaver/patterns/Pointcut;
      13: areturn

  public static org.aspectj.weaver.patterns.Pointcut makeMatchesNothing(org.aspectj.weaver.patterns.Pointcut$State);
    Code:
       0: new           #77                 // class org/aspectj/weaver/patterns/Pointcut$MatchesNothingPointcut
       3: dup
       4: invokespecial #78                 // Method org/aspectj/weaver/patterns/Pointcut$MatchesNothingPointcut."<init>":()V
       7: astore_1
       8: aload_1
       9: aload_0
      10: putfield      #7                  // Field state:Lorg/aspectj/weaver/patterns/Pointcut$State;
      13: aload_1
      14: areturn

  public void assertState(org.aspectj.weaver.patterns.Pointcut$State);
    Code:
       0: aload_0
       1: getfield      #7                  // Field state:Lorg/aspectj/weaver/patterns/Pointcut$State;
       4: aload_1
       5: if_acmpeq     47
       8: new           #61                 // class org/aspectj/weaver/BCException
      11: dup
      12: new           #62                 // class java/lang/StringBuilder
      15: dup
      16: invokespecial #63                 // Method java/lang/StringBuilder."<init>":()V
      19: ldc           #79                 // String expected state:
      21: invokevirtual #65                 // Method java/lang/StringBuilder.append:(Ljava/lang/String;)Ljava/lang/StringBuilder;
      24: aload_1
      25: invokevirtual #80                 // Method java/lang/StringBuilder.append:(Ljava/lang/Object;)Ljava/lang/StringBuilder;
      28: ldc           #81                 // String  got:
      30: invokevirtual #65                 // Method java/lang/StringBuilder.append:(Ljava/lang/String;)Ljava/lang/StringBuilder;
      33: aload_0
      34: getfield      #7                  // Field state:Lorg/aspectj/weaver/patterns/Pointcut$State;
      37: invokevirtual #80                 // Method java/lang/StringBuilder.append:(Ljava/lang/Object;)Ljava/lang/StringBuilder;
      40: invokevirtual #67                 // Method java/lang/StringBuilder.toString:()Ljava/lang/String;
      43: invokespecial #68                 // Method org/aspectj/weaver/BCException."<init>":(Ljava/lang/String;)V
      46: athrow
      47: return

  public abstract org.aspectj.weaver.patterns.Pointcut parameterizeWith(java.util.Map<java.lang.String, org.aspectj.weaver.UnresolvedType>, org.aspectj.weaver.World);

  static {};
    Code:
       0: iconst_0
       1: anewarray     #82                 // class java/lang/String
       4: putstatic     #2                  // Field EMPTY_STRING_ARRAY:[Ljava/lang/String;
       7: new           #83                 // class org/aspectj/weaver/patterns/Pointcut$State
      10: dup
      11: ldc           #84                 // String symbolic
      13: iconst_0
      14: invokespecial #85                 // Method org/aspectj/weaver/patterns/Pointcut$State."<init>":(Ljava/lang/String;I)V
      17: putstatic     #6                  // Field SYMBOLIC:Lorg/aspectj/weaver/patterns/Pointcut$State;
      20: new           #83                 // class org/aspectj/weaver/patterns/Pointcut$State
      23: dup
      24: ldc           #86                 // String resolved
      26: iconst_1
      27: invokespecial #85                 // Method org/aspectj/weaver/patterns/Pointcut$State."<init>":(Ljava/lang/String;I)V
      30: putstatic     #25                 // Field RESOLVED:Lorg/aspectj/weaver/patterns/Pointcut$State;
      33: new           #83                 // class org/aspectj/weaver/patterns/Pointcut$State
      36: dup
      37: ldc           #87                 // String concrete
      39: iconst_2
      40: invokespecial #85                 // Method org/aspectj/weaver/patterns/Pointcut$State."<init>":(Ljava/lang/String;I)V
      43: putstatic     #38                 // Field CONCRETE:Lorg/aspectj/weaver/patterns/Pointcut$State;
      46: return
}
