Compiled from "SimpleScope.java"
public class org.aspectj.weaver.patterns.SimpleScope implements org.aspectj.weaver.patterns.IScope {
  private static final java.lang.String[] NoStrings;

  private static final java.lang.String[] javaLangPrefixArray;

  private java.lang.String[] importedPrefixes;

  private java.lang.String[] importedNames;

  private org.aspectj.weaver.World world;

  private org.aspectj.weaver.ResolvedType enclosingType;

  protected org.aspectj.weaver.patterns.FormalBinding[] bindings;

  public org.aspectj.weaver.patterns.SimpleScope(org.aspectj.weaver.World, org.aspectj.weaver.patterns.FormalBinding[]);
    Code:
       0: aload_0
       1: invokespecial #1                  // Method java/lang/Object."<init>":()V
       4: aload_0
       5: getstatic     #2                  // Field javaLangPrefixArray:[Ljava/lang/String;
       8: putfield      #3                  // Field importedPrefixes:[Ljava/lang/String;
      11: aload_0
      12: getstatic     #4                  // Field NoStrings:[Ljava/lang/String;
      15: putfield      #5                  // Field importedNames:[Ljava/lang/String;
      18: aload_0
      19: aload_1
      20: putfield      #6                  // Field world:Lorg/aspectj/weaver/World;
      23: aload_0
      24: aload_2
      25: putfield      #7                  // Field bindings:[Lorg/aspectj/weaver/patterns/FormalBinding;
      28: return

  public org.aspectj.weaver.UnresolvedType lookupType(java.lang.String, org.aspectj.weaver.IHasPosition);
    Code:
       0: iconst_0
       1: istore_3
       2: iload_3
       3: aload_0
       4: getfield      #5                  // Field importedNames:[Ljava/lang/String;
       7: arraylength
       8: if_icmpge     44
      11: aload_0
      12: getfield      #5                  // Field importedNames:[Ljava/lang/String;
      15: iload_3
      16: aaload
      17: astore        4
      19: aload         4
      21: aload_1
      22: invokevirtual #8                  // Method java/lang/String.endsWith:(Ljava/lang/String;)Z
      25: ifeq          38
      28: aload_0
      29: getfield      #6                  // Field world:Lorg/aspectj/weaver/World;
      32: aload         4
      34: invokevirtual #9                  // Method org/aspectj/weaver/World.resolve:(Ljava/lang/String;)Lorg/aspectj/weaver/ResolvedType;
      37: areturn
      38: iinc          3, 1
      41: goto          2
      44: aload_1
      45: invokevirtual #10                 // Method java/lang/String.length:()I
      48: bipush        8
      50: if_icmpge     213
      53: aload_1
      54: iconst_0
      55: invokevirtual #11                 // Method java/lang/String.charAt:(I)C
      58: invokestatic  #12                 // Method java/lang/Character.isLowerCase:(C)Z
      61: ifeq          213
      64: aload_1
      65: invokevirtual #10                 // Method java/lang/String.length:()I
      68: istore_3
      69: iload_3
      70: iconst_3
      71: if_icmpne     87
      74: aload_1
      75: ldc           #13                 // String int
      77: invokevirtual #14                 // Method java/lang/String.equals:(Ljava/lang/Object;)Z
      80: ifeq          213
      83: getstatic     #15                 // Field org/aspectj/weaver/UnresolvedType.INT:Lorg/aspectj/weaver/UnresolvedType;
      86: areturn
      87: iload_3
      88: iconst_4
      89: if_icmpne     144
      92: aload_1
      93: ldc           #16                 // String void
      95: invokevirtual #14                 // Method java/lang/String.equals:(Ljava/lang/Object;)Z
      98: ifeq          105
     101: getstatic     #17                 // Field org/aspectj/weaver/UnresolvedType.VOID:Lorg/aspectj/weaver/UnresolvedType;
     104: areturn
     105: aload_1
     106: ldc           #18                 // String byte
     108: invokevirtual #14                 // Method java/lang/String.equals:(Ljava/lang/Object;)Z
     111: ifeq          118
     114: getstatic     #19                 // Field org/aspectj/weaver/UnresolvedType.BYTE:Lorg/aspectj/weaver/UnresolvedType;
     117: areturn
     118: aload_1
     119: ldc           #20                 // String char
     121: invokevirtual #14                 // Method java/lang/String.equals:(Ljava/lang/Object;)Z
     124: ifeq          131
     127: getstatic     #21                 // Field org/aspectj/weaver/UnresolvedType.CHAR:Lorg/aspectj/weaver/UnresolvedType;
     130: areturn
     131: aload_1
     132: ldc           #22                 // String long
     134: invokevirtual #14                 // Method java/lang/String.equals:(Ljava/lang/Object;)Z
     137: ifeq          213
     140: getstatic     #23                 // Field org/aspectj/weaver/UnresolvedType.LONG:Lorg/aspectj/weaver/UnresolvedType;
     143: areturn
     144: iload_3
     145: iconst_5
     146: if_icmpne     175
     149: aload_1
     150: ldc           #24                 // String float
     152: invokevirtual #14                 // Method java/lang/String.equals:(Ljava/lang/Object;)Z
     155: ifeq          162
     158: getstatic     #25                 // Field org/aspectj/weaver/UnresolvedType.FLOAT:Lorg/aspectj/weaver/UnresolvedType;
     161: areturn
     162: aload_1
     163: ldc           #26                 // String short
     165: invokevirtual #14                 // Method java/lang/String.equals:(Ljava/lang/Object;)Z
     168: ifeq          213
     171: getstatic     #27                 // Field org/aspectj/weaver/UnresolvedType.SHORT:Lorg/aspectj/weaver/UnresolvedType;
     174: areturn
     175: iload_3
     176: bipush        6
     178: if_icmpne     194
     181: aload_1
     182: ldc           #28                 // String double
     184: invokevirtual #14                 // Method java/lang/String.equals:(Ljava/lang/Object;)Z
     187: ifeq          213
     190: getstatic     #29                 // Field org/aspectj/weaver/UnresolvedType.DOUBLE:Lorg/aspectj/weaver/UnresolvedType;
     193: areturn
     194: iload_3
     195: bipush        7
     197: if_icmpne     213
     200: aload_1
     201: ldc           #30                 // String boolean
     203: invokevirtual #14                 // Method java/lang/String.equals:(Ljava/lang/Object;)Z
     206: ifeq          213
     209: getstatic     #31                 // Field org/aspectj/weaver/UnresolvedType.BOOLEAN:Lorg/aspectj/weaver/UnresolvedType;
     212: areturn
     213: aload_1
     214: bipush        46
     216: invokevirtual #32                 // Method java/lang/String.indexOf:(I)I
     219: iconst_m1
     220: if_icmpeq     236
     223: aload_0
     224: getfield      #6                  // Field world:Lorg/aspectj/weaver/World;
     227: aload_1
     228: invokestatic  #33                 // Method org/aspectj/weaver/UnresolvedType.forName:(Ljava/lang/String;)Lorg/aspectj/weaver/UnresolvedType;
     231: iconst_1
     232: invokevirtual #34                 // Method org/aspectj/weaver/World.resolve:(Lorg/aspectj/weaver/UnresolvedType;Z)Lorg/aspectj/weaver/ResolvedType;
     235: areturn
     236: aload_0
     237: getfield      #3                  // Field importedPrefixes:[Ljava/lang/String;
     240: astore_3
     241: aload_3
     242: arraylength
     243: istore        4
     245: iconst_0
     246: istore        5
     248: iload         5
     250: iload         4
     252: if_icmpge     310
     255: aload_3
     256: iload         5
     258: aaload
     259: astore        6
     261: aload_0
     262: getfield      #6                  // Field world:Lorg/aspectj/weaver/World;
     265: new           #35                 // class java/lang/StringBuilder
     268: dup
     269: invokespecial #36                 // Method java/lang/StringBuilder."<init>":()V
     272: aload         6
     274: invokevirtual #37                 // Method java/lang/StringBuilder.append:(Ljava/lang/String;)Ljava/lang/StringBuilder;
     277: aload_1
     278: invokevirtual #37                 // Method java/lang/StringBuilder.append:(Ljava/lang/String;)Ljava/lang/StringBuilder;
     281: invokevirtual #38                 // Method java/lang/StringBuilder.toString:()Ljava/lang/String;
     284: invokestatic  #33                 // Method org/aspectj/weaver/UnresolvedType.forName:(Ljava/lang/String;)Lorg/aspectj/weaver/UnresolvedType;
     287: iconst_1
     288: invokevirtual #34                 // Method org/aspectj/weaver/World.resolve:(Lorg/aspectj/weaver/UnresolvedType;Z)Lorg/aspectj/weaver/ResolvedType;
     291: astore        7
     293: aload         7
     295: invokevirtual #39                 // Method org/aspectj/weaver/ResolvedType.isMissing:()Z
     298: ifne          304
     301: aload         7
     303: areturn
     304: iinc          5, 1
     307: goto          248
     310: aload_0
     311: getfield      #6                  // Field world:Lorg/aspectj/weaver/World;
     314: aload_1
     315: invokestatic  #33                 // Method org/aspectj/weaver/UnresolvedType.forName:(Ljava/lang/String;)Lorg/aspectj/weaver/UnresolvedType;
     318: iconst_1
     319: invokevirtual #34                 // Method org/aspectj/weaver/World.resolve:(Lorg/aspectj/weaver/UnresolvedType;Z)Lorg/aspectj/weaver/ResolvedType;
     322: areturn

  public org.aspectj.bridge.IMessageHandler getMessageHandler();
    Code:
       0: aload_0
       1: getfield      #6                  // Field world:Lorg/aspectj/weaver/World;
       4: invokevirtual #40                 // Method org/aspectj/weaver/World.getMessageHandler:()Lorg/aspectj/bridge/IMessageHandler;
       7: areturn

  public org.aspectj.weaver.patterns.FormalBinding lookupFormal(java.lang.String);
    Code:
       0: iconst_0
       1: istore_2
       2: aload_0
       3: getfield      #7                  // Field bindings:[Lorg/aspectj/weaver/patterns/FormalBinding;
       6: arraylength
       7: istore_3
       8: iload_2
       9: iload_3
      10: if_icmpge     42
      13: aload_0
      14: getfield      #7                  // Field bindings:[Lorg/aspectj/weaver/patterns/FormalBinding;
      17: iload_2
      18: aaload
      19: invokevirtual #41                 // Method org/aspectj/weaver/patterns/FormalBinding.getName:()Ljava/lang/String;
      22: aload_1
      23: invokevirtual #14                 // Method java/lang/String.equals:(Ljava/lang/Object;)Z
      26: ifeq          36
      29: aload_0
      30: getfield      #7                  // Field bindings:[Lorg/aspectj/weaver/patterns/FormalBinding;
      33: iload_2
      34: aaload
      35: areturn
      36: iinc          2, 1
      39: goto          8
      42: aconst_null
      43: areturn

  public org.aspectj.weaver.patterns.FormalBinding getFormal(int);
    Code:
       0: aload_0
       1: getfield      #7                  // Field bindings:[Lorg/aspectj/weaver/patterns/FormalBinding;
       4: iload_1
       5: aaload
       6: areturn

  public int getFormalCount();
    Code:
       0: aload_0
       1: getfield      #7                  // Field bindings:[Lorg/aspectj/weaver/patterns/FormalBinding;
       4: arraylength
       5: ireturn

  public java.lang.String[] getImportedNames();
    Code:
       0: aload_0
       1: getfield      #5                  // Field importedNames:[Ljava/lang/String;
       4: areturn

  public java.lang.String[] getImportedPrefixes();
    Code:
       0: aload_0
       1: getfield      #3                  // Field importedPrefixes:[Ljava/lang/String;
       4: areturn

  public void setImportedNames(java.lang.String[]);
    Code:
       0: aload_0
       1: aload_1
       2: putfield      #5                  // Field importedNames:[Ljava/lang/String;
       5: return

  public void setImportedPrefixes(java.lang.String[]);
    Code:
       0: aload_0
       1: aload_1
       2: putfield      #3                  // Field importedPrefixes:[Ljava/lang/String;
       5: return

  public static org.aspectj.weaver.patterns.FormalBinding[] makeFormalBindings(org.aspectj.weaver.UnresolvedType[], java.lang.String[]);
    Code:
       0: aload_0
       1: arraylength
       2: istore_2
       3: iload_2
       4: anewarray     #42                 // class org/aspectj/weaver/patterns/FormalBinding
       7: astore_3
       8: iconst_0
       9: istore        4
      11: iload         4
      13: iload_2
      14: if_icmpge     44
      17: aload_3
      18: iload         4
      20: new           #42                 // class org/aspectj/weaver/patterns/FormalBinding
      23: dup
      24: aload_0
      25: iload         4
      27: aaload
      28: aload_1
      29: iload         4
      31: aaload
      32: iload         4
      34: invokespecial #43                 // Method org/aspectj/weaver/patterns/FormalBinding."<init>":(Lorg/aspectj/weaver/UnresolvedType;Ljava/lang/String;I)V
      37: aastore
      38: iinc          4, 1
      41: goto          11
      44: aload_3
      45: areturn

  public org.aspectj.bridge.ISourceLocation makeSourceLocation(org.aspectj.weaver.IHasPosition);
    Code:
       0: new           #44                 // class org/aspectj/bridge/SourceLocation
       3: dup
       4: getstatic     #45                 // Field org/aspectj/bridge/ISourceLocation.NO_FILE:Ljava/io/File;
       7: iconst_0
       8: invokespecial #46                 // Method org/aspectj/bridge/SourceLocation."<init>":(Ljava/io/File;I)V
      11: areturn

  public void message(org.aspectj.bridge.IMessage$Kind, org.aspectj.weaver.IHasPosition, org.aspectj.weaver.IHasPosition, java.lang.String);
    Code:
       0: aload_0
       1: aload_1
       2: aload_2
       3: aload         4
       5: invokevirtual #47                 // Method message:(Lorg/aspectj/bridge/IMessage$Kind;Lorg/aspectj/weaver/IHasPosition;Ljava/lang/String;)V
       8: aload_0
       9: aload_1
      10: aload_3
      11: aload         4
      13: invokevirtual #47                 // Method message:(Lorg/aspectj/bridge/IMessage$Kind;Lorg/aspectj/weaver/IHasPosition;Ljava/lang/String;)V
      16: return

  public void message(org.aspectj.bridge.IMessage$Kind, org.aspectj.weaver.IHasPosition, java.lang.String);
    Code:
       0: aload_0
       1: invokevirtual #48                 // Method getMessageHandler:()Lorg/aspectj/bridge/IMessageHandler;
       4: new           #49                 // class org/aspectj/bridge/Message
       7: dup
       8: aload_3
       9: aload_1
      10: aconst_null
      11: aload_0
      12: aload_2
      13: invokevirtual #50                 // Method makeSourceLocation:(Lorg/aspectj/weaver/IHasPosition;)Lorg/aspectj/bridge/ISourceLocation;
      16: invokespecial #51                 // Method org/aspectj/bridge/Message."<init>":(Ljava/lang/String;Lorg/aspectj/bridge/IMessage$Kind;Ljava/lang/Throwable;Lorg/aspectj/bridge/ISourceLocation;)V
      19: invokeinterface #52,  2           // InterfaceMethod org/aspectj/bridge/IMessageHandler.handleMessage:(Lorg/aspectj/bridge/IMessage;)Z
      24: pop
      25: return

  public void message(org.aspectj.bridge.IMessage);
    Code:
       0: aload_0
       1: invokevirtual #48                 // Method getMessageHandler:()Lorg/aspectj/bridge/IMessageHandler;
       4: aload_1
       5: invokeinterface #52,  2           // InterfaceMethod org/aspectj/bridge/IMessageHandler.handleMessage:(Lorg/aspectj/bridge/IMessage;)Z
      10: pop
      11: return

  public org.aspectj.weaver.World getWorld();
    Code:
       0: aload_0
       1: getfield      #6                  // Field world:Lorg/aspectj/weaver/World;
       4: areturn

  public org.aspectj.weaver.ResolvedType getEnclosingType();
    Code:
       0: aload_0
       1: getfield      #53                 // Field enclosingType:Lorg/aspectj/weaver/ResolvedType;
       4: areturn

  static {};
    Code:
       0: iconst_0
       1: anewarray     #54                 // class java/lang/String
       4: putstatic     #4                  // Field NoStrings:[Ljava/lang/String;
       7: iconst_1
       8: anewarray     #54                 // class java/lang/String
      11: dup
      12: iconst_0
      13: ldc           #55                 // String java.lang.
      15: aastore
      16: putstatic     #2                  // Field javaLangPrefixArray:[Ljava/lang/String;
      19: return
}
