Compiled from "CompositeMetricWriter.java"
public class org.springframework.boot.actuate.metrics.writer.CompositeMetricWriter implements org.springframework.boot.actuate.metrics.writer.MetricWriter, java.lang.Iterable<org.springframework.boot.actuate.metrics.writer.MetricWriter> {
  private final java.util.List<org.springframework.boot.actuate.metrics.writer.MetricWriter> writers;

  public org.springframework.boot.actuate.metrics.writer.CompositeMetricWriter(org.springframework.boot.actuate.metrics.writer.MetricWriter...);
    Code:
       0: aload_0
       1: invokespecial #1                  // Method java/lang/Object."<init>":()V
       4: aload_0
       5: new           #2                  // class java/util/ArrayList
       8: dup
       9: invokespecial #3                  // Method java/util/ArrayList."<init>":()V
      12: putfield      #4                  // Field writers:Ljava/util/List;
      15: aload_0
      16: getfield      #4                  // Field writers:Ljava/util/List;
      19: aload_1
      20: invokestatic  #5                  // Method java/util/Collections.addAll:(Ljava/util/Collection;[Ljava/lang/Object;)Z
      23: pop
      24: return

  public org.springframework.boot.actuate.metrics.writer.CompositeMetricWriter(java.util.List<org.springframework.boot.actuate.metrics.writer.MetricWriter>);
    Code:
       0: aload_0
       1: invokespecial #1                  // Method java/lang/Object."<init>":()V
       4: aload_0
       5: new           #2                  // class java/util/ArrayList
       8: dup
       9: invokespecial #3                  // Method java/util/ArrayList."<init>":()V
      12: putfield      #4                  // Field writers:Ljava/util/List;
      15: aload_0
      16: getfield      #4                  // Field writers:Ljava/util/List;
      19: aload_1
      20: invokeinterface #6,  2            // InterfaceMethod java/util/List.addAll:(Ljava/util/Collection;)Z
      25: pop
      26: return

  public java.util.Iterator<org.springframework.boot.actuate.metrics.writer.MetricWriter> iterator();
    Code:
       0: aload_0
       1: getfield      #4                  // Field writers:Ljava/util/List;
       4: invokeinterface #7,  1            // InterfaceMethod java/util/List.iterator:()Ljava/util/Iterator;
       9: areturn

  public void increment(org.springframework.boot.actuate.metrics.writer.Delta<?>);
    Code:
       0: aload_0
       1: getfield      #4                  // Field writers:Ljava/util/List;
       4: invokeinterface #7,  1            // InterfaceMethod java/util/List.iterator:()Ljava/util/Iterator;
       9: astore_2
      10: aload_2
      11: invokeinterface #8,  1            // InterfaceMethod java/util/Iterator.hasNext:()Z
      16: ifeq          39
      19: aload_2
      20: invokeinterface #9,  1            // InterfaceMethod java/util/Iterator.next:()Ljava/lang/Object;
      25: checkcast     #10                 // class org/springframework/boot/actuate/metrics/writer/MetricWriter
      28: astore_3
      29: aload_3
      30: aload_1
      31: invokeinterface #11,  2           // InterfaceMethod org/springframework/boot/actuate/metrics/writer/MetricWriter.increment:(Lorg/springframework/boot/actuate/metrics/writer/Delta;)V
      36: goto          10
      39: return

  public void set(org.springframework.boot.actuate.metrics.Metric<?>);
    Code:
       0: aload_0
       1: getfield      #4                  // Field writers:Ljava/util/List;
       4: invokeinterface #7,  1            // InterfaceMethod java/util/List.iterator:()Ljava/util/Iterator;
       9: astore_2
      10: aload_2
      11: invokeinterface #8,  1            // InterfaceMethod java/util/Iterator.hasNext:()Z
      16: ifeq          39
      19: aload_2
      20: invokeinterface #9,  1            // InterfaceMethod java/util/Iterator.next:()Ljava/lang/Object;
      25: checkcast     #10                 // class org/springframework/boot/actuate/metrics/writer/MetricWriter
      28: astore_3
      29: aload_3
      30: aload_1
      31: invokeinterface #12,  2           // InterfaceMethod org/springframework/boot/actuate/metrics/writer/MetricWriter.set:(Lorg/springframework/boot/actuate/metrics/Metric;)V
      36: goto          10
      39: return

  public void reset(java.lang.String);
    Code:
       0: aload_0
       1: getfield      #4                  // Field writers:Ljava/util/List;
       4: invokeinterface #7,  1            // InterfaceMethod java/util/List.iterator:()Ljava/util/Iterator;
       9: astore_2
      10: aload_2
      11: invokeinterface #8,  1            // InterfaceMethod java/util/Iterator.hasNext:()Z
      16: ifeq          39
      19: aload_2
      20: invokeinterface #9,  1            // InterfaceMethod java/util/Iterator.next:()Ljava/lang/Object;
      25: checkcast     #10                 // class org/springframework/boot/actuate/metrics/writer/MetricWriter
      28: astore_3
      29: aload_3
      30: aload_1
      31: invokeinterface #13,  2           // InterfaceMethod org/springframework/boot/actuate/metrics/writer/MetricWriter.reset:(Ljava/lang/String;)V
      36: goto          10
      39: return
}
