Compiled from "DefaultCounterService.java"
public class org.springframework.boot.actuate.metrics.writer.DefaultCounterService implements org.springframework.boot.actuate.metrics.CounterService {
  private final org.springframework.boot.actuate.metrics.writer.MetricWriter writer;

  private final java.util.concurrent.ConcurrentHashMap<java.lang.String, java.lang.String> names;

  public org.springframework.boot.actuate.metrics.writer.DefaultCounterService(org.springframework.boot.actuate.metrics.writer.MetricWriter);
    Code:
       0: aload_0
       1: invokespecial #1                  // Method java/lang/Object."<init>":()V
       4: aload_0
       5: new           #2                  // class java/util/concurrent/ConcurrentHashMap
       8: dup
       9: invokespecial #3                  // Method java/util/concurrent/ConcurrentHashMap."<init>":()V
      12: putfield      #4                  // Field names:Ljava/util/concurrent/ConcurrentHashMap;
      15: aload_0
      16: aload_1
      17: putfield      #5                  // Field writer:Lorg/springframework/boot/actuate/metrics/writer/MetricWriter;
      20: return

  public void increment(java.lang.String);
    Code:
       0: aload_0
       1: getfield      #5                  // Field writer:Lorg/springframework/boot/actuate/metrics/writer/MetricWriter;
       4: new           #6                  // class org/springframework/boot/actuate/metrics/writer/Delta
       7: dup
       8: aload_0
       9: aload_1
      10: invokespecial #7                  // Method wrap:(Ljava/lang/String;)Ljava/lang/String;
      13: lconst_1
      14: invokestatic  #8                  // Method java/lang/Long.valueOf:(J)Ljava/lang/Long;
      17: invokespecial #9                  // Method org/springframework/boot/actuate/metrics/writer/Delta."<init>":(Ljava/lang/String;Ljava/lang/Number;)V
      20: invokeinterface #10,  2           // InterfaceMethod org/springframework/boot/actuate/metrics/writer/MetricWriter.increment:(Lorg/springframework/boot/actuate/metrics/writer/Delta;)V
      25: return

  public void decrement(java.lang.String);
    Code:
       0: aload_0
       1: getfield      #5                  // Field writer:Lorg/springframework/boot/actuate/metrics/writer/MetricWriter;
       4: new           #6                  // class org/springframework/boot/actuate/metrics/writer/Delta
       7: dup
       8: aload_0
       9: aload_1
      10: invokespecial #7                  // Method wrap:(Ljava/lang/String;)Ljava/lang/String;
      13: ldc2_w        #11                 // long -1l
      16: invokestatic  #8                  // Method java/lang/Long.valueOf:(J)Ljava/lang/Long;
      19: invokespecial #9                  // Method org/springframework/boot/actuate/metrics/writer/Delta."<init>":(Ljava/lang/String;Ljava/lang/Number;)V
      22: invokeinterface #10,  2           // InterfaceMethod org/springframework/boot/actuate/metrics/writer/MetricWriter.increment:(Lorg/springframework/boot/actuate/metrics/writer/Delta;)V
      27: return

  public void reset(java.lang.String);
    Code:
       0: aload_0
       1: getfield      #5                  // Field writer:Lorg/springframework/boot/actuate/metrics/writer/MetricWriter;
       4: aload_0
       5: aload_1
       6: invokespecial #7                  // Method wrap:(Ljava/lang/String;)Ljava/lang/String;
       9: invokeinterface #13,  2           // InterfaceMethod org/springframework/boot/actuate/metrics/writer/MetricWriter.reset:(Ljava/lang/String;)V
      14: return

  private java.lang.String wrap(java.lang.String);
    Code:
       0: aload_0
       1: getfield      #4                  // Field names:Ljava/util/concurrent/ConcurrentHashMap;
       4: aload_1
       5: invokevirtual #14                 // Method java/util/concurrent/ConcurrentHashMap.get:(Ljava/lang/Object;)Ljava/lang/Object;
       8: checkcast     #15                 // class java/lang/String
      11: astore_2
      12: aload_2
      13: ifnull        18
      16: aload_2
      17: areturn
      18: aload_1
      19: ldc           #16                 // String counter.
      21: invokevirtual #17                 // Method java/lang/String.startsWith:(Ljava/lang/String;)Z
      24: ifne          36
      27: aload_1
      28: ldc           #18                 // String meter.
      30: invokevirtual #17                 // Method java/lang/String.startsWith:(Ljava/lang/String;)Z
      33: ifeq          38
      36: aload_1
      37: areturn
      38: new           #19                 // class java/lang/StringBuilder
      41: dup
      42: invokespecial #20                 // Method java/lang/StringBuilder."<init>":()V
      45: ldc           #16                 // String counter.
      47: invokevirtual #21                 // Method java/lang/StringBuilder.append:(Ljava/lang/String;)Ljava/lang/StringBuilder;
      50: aload_1
      51: invokevirtual #21                 // Method java/lang/StringBuilder.append:(Ljava/lang/String;)Ljava/lang/StringBuilder;
      54: invokevirtual #22                 // Method java/lang/StringBuilder.toString:()Ljava/lang/String;
      57: astore_3
      58: aload_0
      59: getfield      #4                  // Field names:Ljava/util/concurrent/ConcurrentHashMap;
      62: aload_1
      63: aload_3
      64: invokevirtual #23                 // Method java/util/concurrent/ConcurrentHashMap.put:(Ljava/lang/Object;Ljava/lang/Object;)Ljava/lang/Object;
      67: pop
      68: aload_3
      69: areturn
}
