Compiled from "CoreXMLDeserializers.java"
public class org.elasticsearch.hadoop.thirdparty.codehaus.jackson.map.ext.CoreXMLDeserializers$DurationDeserializer extends org.elasticsearch.hadoop.thirdparty.codehaus.jackson.map.deser.FromStringDeserializer<javax.xml.datatype.Duration> {
  public org.elasticsearch.hadoop.thirdparty.codehaus.jackson.map.ext.CoreXMLDeserializers$DurationDeserializer();
    Code:
       0: aload_0
       1: ldc           #13                 // class javax/xml/datatype/Duration
       3: invokespecial #16                 // Method org/elasticsearch/hadoop/thirdparty/codehaus/jackson/map/deser/FromStringDeserializer."<init>":(Ljava/lang/Class;)V
       6: return

  protected javax.xml.datatype.Duration _deserialize(java.lang.String, org.elasticsearch.hadoop.thirdparty.codehaus.jackson.map.DeserializationContext) throws java.lang.IllegalArgumentException;
    Code:
       0: getstatic     #26                 // Field org/elasticsearch/hadoop/thirdparty/codehaus/jackson/map/ext/CoreXMLDeserializers._dataTypeFactory:Ljavax/xml/datatype/DatatypeFactory;
       3: aload_1
       4: invokevirtual #32                 // Method javax/xml/datatype/DatatypeFactory.newDuration:(Ljava/lang/String;)Ljavax/xml/datatype/Duration;
       7: areturn

  protected java.lang.Object _deserialize(java.lang.String, org.elasticsearch.hadoop.thirdparty.codehaus.jackson.map.DeserializationContext) throws java.io.IOException, org.elasticsearch.hadoop.thirdparty.codehaus.jackson.JsonProcessingException;
    Code:
       0: aload_0
       1: aload_1
       2: aload_2
       3: invokevirtual #43                 // Method _deserialize:(Ljava/lang/String;Lorg/elasticsearch/hadoop/thirdparty/codehaus/jackson/map/DeserializationContext;)Ljavax/xml/datatype/Duration;
       6: areturn
}
