Compiled from "CoreXMLSerializers.java"
public class org.elasticsearch.hadoop.thirdparty.codehaus.jackson.map.ext.CoreXMLSerializers$XMLGregorianCalendarSerializer extends org.elasticsearch.hadoop.thirdparty.codehaus.jackson.map.ser.SerializerBase<javax.xml.datatype.XMLGregorianCalendar> {
  public org.elasticsearch.hadoop.thirdparty.codehaus.jackson.map.ext.CoreXMLSerializers$XMLGregorianCalendarSerializer();
    Code:
       0: aload_0
       1: ldc           #18                 // class javax/xml/datatype/XMLGregorianCalendar
       3: invokespecial #21                 // Method org/elasticsearch/hadoop/thirdparty/codehaus/jackson/map/ser/SerializerBase."<init>":(Ljava/lang/Class;)V
       6: return

  public void serialize(javax.xml.datatype.XMLGregorianCalendar, org.elasticsearch.hadoop.thirdparty.codehaus.jackson.JsonGenerator, org.elasticsearch.hadoop.thirdparty.codehaus.jackson.map.SerializerProvider) throws java.io.IOException, org.elasticsearch.hadoop.thirdparty.codehaus.jackson.JsonGenerationException;
    Code:
       0: getstatic     #33                 // Field org/elasticsearch/hadoop/thirdparty/codehaus/jackson/map/ser/StdSerializers$CalendarSerializer.instance:Lorg/elasticsearch/hadoop/thirdparty/codehaus/jackson/map/ser/StdSerializers$CalendarSerializer;
       3: aload_1
       4: invokevirtual #37                 // Method javax/xml/datatype/XMLGregorianCalendar.toGregorianCalendar:()Ljava/util/GregorianCalendar;
       7: aload_2
       8: aload_3
       9: invokevirtual #40                 // Method org/elasticsearch/hadoop/thirdparty/codehaus/jackson/map/ser/StdSerializers$CalendarSerializer.serialize:(Ljava/util/Calendar;Lorg/elasticsearch/hadoop/thirdparty/codehaus/jackson/JsonGenerator;Lorg/elasticsearch/hadoop/thirdparty/codehaus/jackson/map/SerializerProvider;)V
      12: return

  public org.elasticsearch.hadoop.thirdparty.codehaus.jackson.JsonNode getSchema(org.elasticsearch.hadoop.thirdparty.codehaus.jackson.map.SerializerProvider, java.lang.reflect.Type) throws org.elasticsearch.hadoop.thirdparty.codehaus.jackson.map.JsonMappingException;
    Code:
       0: getstatic     #33                 // Field org/elasticsearch/hadoop/thirdparty/codehaus/jackson/map/ser/StdSerializers$CalendarSerializer.instance:Lorg/elasticsearch/hadoop/thirdparty/codehaus/jackson/map/ser/StdSerializers$CalendarSerializer;
       3: aload_1
       4: aload_2
       5: invokevirtual #52                 // Method org/elasticsearch/hadoop/thirdparty/codehaus/jackson/map/ser/StdSerializers$CalendarSerializer.getSchema:(Lorg/elasticsearch/hadoop/thirdparty/codehaus/jackson/map/SerializerProvider;Ljava/lang/reflect/Type;)Lorg/elasticsearch/hadoop/thirdparty/codehaus/jackson/JsonNode;
       8: areturn

  public void serialize(java.lang.Object, org.elasticsearch.hadoop.thirdparty.codehaus.jackson.JsonGenerator, org.elasticsearch.hadoop.thirdparty.codehaus.jackson.map.SerializerProvider) throws java.io.IOException, org.elasticsearch.hadoop.thirdparty.codehaus.jackson.JsonGenerationException;
    Code:
       0: aload_0
       1: aload_1
       2: checkcast     #18                 // class javax/xml/datatype/XMLGregorianCalendar
       5: aload_2
       6: aload_3
       7: invokevirtual #57                 // Method serialize:(Ljavax/xml/datatype/XMLGregorianCalendar;Lorg/elasticsearch/hadoop/thirdparty/codehaus/jackson/JsonGenerator;Lorg/elasticsearch/hadoop/thirdparty/codehaus/jackson/map/SerializerProvider;)V
      10: return
}
