Compiled from "SectionListener.java"
public class org.xwiki.rendering.wikimodel.util.SectionListener<T> implements org.xwiki.rendering.wikimodel.util.ISectionListener<T> {
  public org.xwiki.rendering.wikimodel.util.SectionListener();
    Code:
       0: aload_0
       1: invokespecial #1                  // Method java/lang/Object."<init>":()V
       4: return

  public void beginDocument(org.xwiki.rendering.wikimodel.util.ISectionListener$IPos<T>);
    Code:
       0: return

  public void beginSection(org.xwiki.rendering.wikimodel.util.ISectionListener$IPos<T>);
    Code:
       0: return

  public void beginSectionContent(org.xwiki.rendering.wikimodel.util.ISectionListener$IPos<T>);
    Code:
       0: return

  public void beginSectionHeader(org.xwiki.rendering.wikimodel.util.ISectionListener$IPos<T>);
    Code:
       0: return

  public void endDocument(org.xwiki.rendering.wikimodel.util.ISectionListener$IPos<T>);
    Code:
       0: return

  public void endSection(org.xwiki.rendering.wikimodel.util.ISectionListener$IPos<T>);
    Code:
       0: return

  public void endSectionContent(org.xwiki.rendering.wikimodel.util.ISectionListener$IPos<T>);
    Code:
       0: return

  public void endSectionHeader(org.xwiki.rendering.wikimodel.util.ISectionListener$IPos<T>);
    Code:
       0: return
}
