Compiled from "IterableMapper.java"
public class io.gsonfire.util.IterableMapper<F, T> implements java.lang.Iterable<T> {
  private final java.lang.Iterable<F> source;

  private final io.gsonfire.util.Mapper<F, T> mapper;

  private io.gsonfire.util.IterableMapper(java.lang.Iterable<F>, io.gsonfire.util.Mapper<F, T>);
    Code:
       0: aload_0
       1: invokespecial #2                  // Method java/lang/Object."<init>":()V
       4: aload_0
       5: aload_1
       6: putfield      #3                  // Field source:Ljava/lang/Iterable;
       9: aload_0
      10: aload_2
      11: putfield      #1                  // Field mapper:Lio/gsonfire/util/Mapper;
      14: return

  public java.util.Iterator<T> iterator();
    Code:
       0: aload_0
       1: getfield      #3                  // Field source:Ljava/lang/Iterable;
       4: invokeinterface #4,  1            // InterfaceMethod java/lang/Iterable.iterator:()Ljava/util/Iterator;
       9: astore_1
      10: new           #5                  // class io/gsonfire/util/IterableMapper$1
      13: dup
      14: aload_0
      15: aload_1
      16: invokespecial #6                  // Method io/gsonfire/util/IterableMapper$1."<init>":(Lio/gsonfire/util/IterableMapper;Ljava/util/Iterator;)V
      19: areturn

  public boolean equals(java.lang.Object);
    Code:
       0: aload_1
       1: ifnull        92
       4: aload_1
       5: instanceof    #7                  // class java/lang/Iterable
       8: ifeq          92
      11: aload_1
      12: checkcast     #7                  // class java/lang/Iterable
      15: invokeinterface #4,  1            // InterfaceMethod java/lang/Iterable.iterator:()Ljava/util/Iterator;
      20: astore_2
      21: aload_0
      22: invokevirtual #8                  // Method iterator:()Ljava/util/Iterator;
      25: astore_3
      26: aload_3
      27: invokeinterface #9,  1            // InterfaceMethod java/util/Iterator.hasNext:()Z
      32: ifeq          77
      35: aload_2
      36: invokeinterface #9,  1            // InterfaceMethod java/util/Iterator.hasNext:()Z
      41: ifeq          75
      44: aload_3
      45: invokeinterface #10,  1           // InterfaceMethod java/util/Iterator.next:()Ljava/lang/Object;
      50: astore        4
      52: aload_2
      53: invokeinterface #10,  1           // InterfaceMethod java/util/Iterator.next:()Ljava/lang/Object;
      58: astore        5
      60: aload         4
      62: aload         5
      64: invokestatic  #11                 // Method areObjectEquals:(Ljava/lang/Object;Ljava/lang/Object;)Z
      67: ifne          72
      70: iconst_0
      71: ireturn
      72: goto          26
      75: iconst_0
      76: ireturn
      77: aload_2
      78: invokeinterface #9,  1            // InterfaceMethod java/util/Iterator.hasNext:()Z
      83: ifne          90
      86: iconst_1
      87: goto          91
      90: iconst_0
      91: ireturn
      92: iconst_0
      93: ireturn

  private static boolean areObjectEquals(java.lang.Object, java.lang.Object);
    Code:
       0: aload_0
       1: aload_1
       2: if_acmpeq     17
       5: aload_0
       6: ifnull        21
       9: aload_0
      10: aload_1
      11: invokevirtual #12                 // Method java/lang/Object.equals:(Ljava/lang/Object;)Z
      14: ifeq          21
      17: iconst_1
      18: goto          22
      21: iconst_0
      22: ireturn

  public static <F, T> java.lang.Iterable<T> create(java.lang.Iterable<F>, io.gsonfire.util.Mapper<F, T>);
    Code:
       0: new           #13                 // class io/gsonfire/util/IterableMapper
       3: dup
       4: aload_0
       5: aload_1
       6: invokespecial #14                 // Method "<init>":(Ljava/lang/Iterable;Lio/gsonfire/util/Mapper;)V
       9: areturn

  static io.gsonfire.util.Mapper access$000(io.gsonfire.util.IterableMapper);
    Code:
       0: aload_0
       1: getfield      #1                  // Field mapper:Lio/gsonfire/util/Mapper;
       4: areturn
}
