Compiled from "WsPerSessionServerEndpointConfig.java"
class org.apache.tomcat.websocket.server.WsPerSessionServerEndpointConfig implements javax.websocket.server.ServerEndpointConfig {
  private final javax.websocket.server.ServerEndpointConfig perEndpointConfig;

  private final java.util.Map<java.lang.String, java.lang.Object> perSessionUserProperties;

  org.apache.tomcat.websocket.server.WsPerSessionServerEndpointConfig(javax.websocket.server.ServerEndpointConfig);
    Code:
       0: aload_0
       1: invokespecial #1                  // Method java/lang/Object."<init>":()V
       4: aload_0
       5: new           #2                  // class java/util/concurrent/ConcurrentHashMap
       8: dup
       9: invokespecial #3                  // Method java/util/concurrent/ConcurrentHashMap."<init>":()V
      12: putfield      #4                  // Field perSessionUserProperties:Ljava/util/Map;
      15: aload_0
      16: aload_1
      17: putfield      #5                  // Field perEndpointConfig:Ljavax/websocket/server/ServerEndpointConfig;
      20: aload_0
      21: getfield      #4                  // Field perSessionUserProperties:Ljava/util/Map;
      24: aload_1
      25: invokeinterface #6,  1            // InterfaceMethod javax/websocket/server/ServerEndpointConfig.getUserProperties:()Ljava/util/Map;
      30: invokeinterface #7,  2            // InterfaceMethod java/util/Map.putAll:(Ljava/util/Map;)V
      35: return

  public java.util.List<java.lang.Class<? extends javax.websocket.Encoder>> getEncoders();
    Code:
       0: aload_0
       1: getfield      #5                  // Field perEndpointConfig:Ljavax/websocket/server/ServerEndpointConfig;
       4: invokeinterface #8,  1            // InterfaceMethod javax/websocket/server/ServerEndpointConfig.getEncoders:()Ljava/util/List;
       9: areturn

  public java.util.List<java.lang.Class<? extends javax.websocket.Decoder>> getDecoders();
    Code:
       0: aload_0
       1: getfield      #5                  // Field perEndpointConfig:Ljavax/websocket/server/ServerEndpointConfig;
       4: invokeinterface #9,  1            // InterfaceMethod javax/websocket/server/ServerEndpointConfig.getDecoders:()Ljava/util/List;
       9: areturn

  public java.util.Map<java.lang.String, java.lang.Object> getUserProperties();
    Code:
       0: aload_0
       1: getfield      #4                  // Field perSessionUserProperties:Ljava/util/Map;
       4: areturn

  public java.lang.Class<?> getEndpointClass();
    Code:
       0: aload_0
       1: getfield      #5                  // Field perEndpointConfig:Ljavax/websocket/server/ServerEndpointConfig;
       4: invokeinterface #10,  1           // InterfaceMethod javax/websocket/server/ServerEndpointConfig.getEndpointClass:()Ljava/lang/Class;
       9: areturn

  public java.lang.String getPath();
    Code:
       0: aload_0
       1: getfield      #5                  // Field perEndpointConfig:Ljavax/websocket/server/ServerEndpointConfig;
       4: invokeinterface #11,  1           // InterfaceMethod javax/websocket/server/ServerEndpointConfig.getPath:()Ljava/lang/String;
       9: areturn

  public java.util.List<java.lang.String> getSubprotocols();
    Code:
       0: aload_0
       1: getfield      #5                  // Field perEndpointConfig:Ljavax/websocket/server/ServerEndpointConfig;
       4: invokeinterface #12,  1           // InterfaceMethod javax/websocket/server/ServerEndpointConfig.getSubprotocols:()Ljava/util/List;
       9: areturn

  public java.util.List<javax.websocket.Extension> getExtensions();
    Code:
       0: aload_0
       1: getfield      #5                  // Field perEndpointConfig:Ljavax/websocket/server/ServerEndpointConfig;
       4: invokeinterface #13,  1           // InterfaceMethod javax/websocket/server/ServerEndpointConfig.getExtensions:()Ljava/util/List;
       9: areturn

  public javax.websocket.server.ServerEndpointConfig$Configurator getConfigurator();
    Code:
       0: aload_0
       1: getfield      #5                  // Field perEndpointConfig:Ljavax/websocket/server/ServerEndpointConfig;
       4: invokeinterface #14,  1           // InterfaceMethod javax/websocket/server/ServerEndpointConfig.getConfigurator:()Ljavax/websocket/server/ServerEndpointConfig$Configurator;
       9: areturn
}
