Compiled from "QuorumHierarchical.java"
public class org.apache.zookeeper.server.quorum.flexible.QuorumHierarchical implements org.apache.zookeeper.server.quorum.flexible.QuorumVerifier {
  private static final org.slf4j.Logger LOG;

  private java.util.HashMap<java.lang.Long, java.lang.Long> serverWeight;

  private java.util.HashMap<java.lang.Long, java.lang.Long> serverGroup;

  private java.util.HashMap<java.lang.Long, java.lang.Long> groupWeight;

  private int numGroups;

  private java.util.Map<java.lang.Long, org.apache.zookeeper.server.quorum.QuorumPeer$QuorumServer> allMembers;

  private java.util.Map<java.lang.Long, org.apache.zookeeper.server.quorum.QuorumPeer$QuorumServer> participatingMembers;

  private java.util.Map<java.lang.Long, org.apache.zookeeper.server.quorum.QuorumPeer$QuorumServer> observingMembers;

  private long version;

  static final boolean $assertionsDisabled;

  public int hashCode();
    Code:
       0: getstatic     #1                  // Field $assertionsDisabled:Z
       3: ifne          16
       6: new           #2                  // class java/lang/AssertionError
       9: dup
      10: ldc           #3                  // String hashCode not designed
      12: invokespecial #4                  // Method java/lang/AssertionError."<init>":(Ljava/lang/Object;)V
      15: athrow
      16: bipush        42
      18: ireturn

  public boolean equals(java.lang.Object);
    Code:
       0: aload_1
       1: instanceof    #5                  // class org/apache/zookeeper/server/quorum/flexible/QuorumHierarchical
       4: ifne          9
       7: iconst_0
       8: ireturn
       9: aload_1
      10: checkcast     #5                  // class org/apache/zookeeper/server/quorum/flexible/QuorumHierarchical
      13: astore_2
      14: aload_2
      15: invokevirtual #6                  // Method getVersion:()J
      18: aload_0
      19: getfield      #7                  // Field version:J
      22: lcmp
      23: ifne          28
      26: iconst_1
      27: ireturn
      28: aload_0
      29: getfield      #8                  // Field allMembers:Ljava/util/Map;
      32: invokeinterface #9,  1            // InterfaceMethod java/util/Map.size:()I
      37: aload_2
      38: invokevirtual #10                 // Method getAllMembers:()Ljava/util/Map;
      41: invokeinterface #9,  1            // InterfaceMethod java/util/Map.size:()I
      46: if_icmpne     100
      49: aload_0
      50: getfield      #11                 // Field serverWeight:Ljava/util/HashMap;
      53: invokevirtual #12                 // Method java/util/HashMap.size:()I
      56: aload_2
      57: getfield      #11                 // Field serverWeight:Ljava/util/HashMap;
      60: invokevirtual #12                 // Method java/util/HashMap.size:()I
      63: if_icmpne     100
      66: aload_0
      67: getfield      #13                 // Field groupWeight:Ljava/util/HashMap;
      70: invokevirtual #12                 // Method java/util/HashMap.size:()I
      73: aload_2
      74: getfield      #13                 // Field groupWeight:Ljava/util/HashMap;
      77: invokevirtual #12                 // Method java/util/HashMap.size:()I
      80: if_icmpne     100
      83: aload_0
      84: getfield      #14                 // Field serverGroup:Ljava/util/HashMap;
      87: invokevirtual #12                 // Method java/util/HashMap.size:()I
      90: aload_2
      91: getfield      #14                 // Field serverGroup:Ljava/util/HashMap;
      94: invokevirtual #12                 // Method java/util/HashMap.size:()I
      97: if_icmpeq     102
     100: iconst_0
     101: ireturn
     102: aload_0
     103: getfield      #8                  // Field allMembers:Ljava/util/Map;
     106: invokeinterface #15,  1           // InterfaceMethod java/util/Map.values:()Ljava/util/Collection;
     111: invokeinterface #16,  1           // InterfaceMethod java/util/Collection.iterator:()Ljava/util/Iterator;
     116: astore_3
     117: aload_3
     118: invokeinterface #17,  1           // InterfaceMethod java/util/Iterator.hasNext:()Z
     123: ifeq          179
     126: aload_3
     127: invokeinterface #18,  1           // InterfaceMethod java/util/Iterator.next:()Ljava/lang/Object;
     132: checkcast     #19                 // class org/apache/zookeeper/server/quorum/QuorumPeer$QuorumServer
     135: astore        4
     137: aload_2
     138: invokevirtual #10                 // Method getAllMembers:()Ljava/util/Map;
     141: aload         4
     143: getfield      #20                 // Field org/apache/zookeeper/server/quorum/QuorumPeer$QuorumServer.id:J
     146: invokestatic  #21                 // Method java/lang/Long.valueOf:(J)Ljava/lang/Long;
     149: invokeinterface #22,  2           // InterfaceMethod java/util/Map.get:(Ljava/lang/Object;)Ljava/lang/Object;
     154: checkcast     #19                 // class org/apache/zookeeper/server/quorum/QuorumPeer$QuorumServer
     157: astore        5
     159: aload         5
     161: ifnull        174
     164: aload         4
     166: aload         5
     168: invokevirtual #23                 // Method org/apache/zookeeper/server/quorum/QuorumPeer$QuorumServer.equals:(Ljava/lang/Object;)Z
     171: ifne          176
     174: iconst_0
     175: ireturn
     176: goto          117
     179: aload_0
     180: getfield      #11                 // Field serverWeight:Ljava/util/HashMap;
     183: invokevirtual #24                 // Method java/util/HashMap.entrySet:()Ljava/util/Set;
     186: invokeinterface #25,  1           // InterfaceMethod java/util/Set.iterator:()Ljava/util/Iterator;
     191: astore_3
     192: aload_3
     193: invokeinterface #17,  1           // InterfaceMethod java/util/Iterator.hasNext:()Z
     198: ifeq          247
     201: aload_3
     202: invokeinterface #18,  1           // InterfaceMethod java/util/Iterator.next:()Ljava/lang/Object;
     207: checkcast     #26                 // class java/util/Map$Entry
     210: astore        4
     212: aload         4
     214: invokeinterface #27,  1           // InterfaceMethod java/util/Map$Entry.getValue:()Ljava/lang/Object;
     219: checkcast     #28                 // class java/lang/Long
     222: aload_2
     223: getfield      #11                 // Field serverWeight:Ljava/util/HashMap;
     226: aload         4
     228: invokeinterface #29,  1           // InterfaceMethod java/util/Map$Entry.getKey:()Ljava/lang/Object;
     233: invokevirtual #30                 // Method java/util/HashMap.get:(Ljava/lang/Object;)Ljava/lang/Object;
     236: invokevirtual #31                 // Method java/lang/Long.equals:(Ljava/lang/Object;)Z
     239: ifne          244
     242: iconst_0
     243: ireturn
     244: goto          192
     247: aload_0
     248: getfield      #13                 // Field groupWeight:Ljava/util/HashMap;
     251: invokevirtual #24                 // Method java/util/HashMap.entrySet:()Ljava/util/Set;
     254: invokeinterface #25,  1           // InterfaceMethod java/util/Set.iterator:()Ljava/util/Iterator;
     259: astore_3
     260: aload_3
     261: invokeinterface #17,  1           // InterfaceMethod java/util/Iterator.hasNext:()Z
     266: ifeq          315
     269: aload_3
     270: invokeinterface #18,  1           // InterfaceMethod java/util/Iterator.next:()Ljava/lang/Object;
     275: checkcast     #26                 // class java/util/Map$Entry
     278: astore        4
     280: aload         4
     282: invokeinterface #27,  1           // InterfaceMethod java/util/Map$Entry.getValue:()Ljava/lang/Object;
     287: checkcast     #28                 // class java/lang/Long
     290: aload_2
     291: getfield      #13                 // Field groupWeight:Ljava/util/HashMap;
     294: aload         4
     296: invokeinterface #29,  1           // InterfaceMethod java/util/Map$Entry.getKey:()Ljava/lang/Object;
     301: invokevirtual #30                 // Method java/util/HashMap.get:(Ljava/lang/Object;)Ljava/lang/Object;
     304: invokevirtual #31                 // Method java/lang/Long.equals:(Ljava/lang/Object;)Z
     307: ifne          312
     310: iconst_0
     311: ireturn
     312: goto          260
     315: aload_0
     316: getfield      #14                 // Field serverGroup:Ljava/util/HashMap;
     319: invokevirtual #24                 // Method java/util/HashMap.entrySet:()Ljava/util/Set;
     322: invokeinterface #25,  1           // InterfaceMethod java/util/Set.iterator:()Ljava/util/Iterator;
     327: astore_3
     328: aload_3
     329: invokeinterface #17,  1           // InterfaceMethod java/util/Iterator.hasNext:()Z
     334: ifeq          383
     337: aload_3
     338: invokeinterface #18,  1           // InterfaceMethod java/util/Iterator.next:()Ljava/lang/Object;
     343: checkcast     #26                 // class java/util/Map$Entry
     346: astore        4
     348: aload         4
     350: invokeinterface #27,  1           // InterfaceMethod java/util/Map$Entry.getValue:()Ljava/lang/Object;
     355: checkcast     #28                 // class java/lang/Long
     358: aload_2
     359: getfield      #14                 // Field serverGroup:Ljava/util/HashMap;
     362: aload         4
     364: invokeinterface #29,  1           // InterfaceMethod java/util/Map$Entry.getKey:()Ljava/lang/Object;
     369: invokevirtual #30                 // Method java/util/HashMap.get:(Ljava/lang/Object;)Ljava/lang/Object;
     372: invokevirtual #31                 // Method java/lang/Long.equals:(Ljava/lang/Object;)Z
     375: ifne          380
     378: iconst_0
     379: ireturn
     380: goto          328
     383: iconst_1
     384: ireturn

  public org.apache.zookeeper.server.quorum.flexible.QuorumHierarchical(java.lang.String) throws org.apache.zookeeper.server.quorum.QuorumPeerConfig$ConfigException;
    Code:
       0: aload_0
       1: invokespecial #32                 // Method java/lang/Object."<init>":()V
       4: aload_0
       5: new           #33                 // class java/util/HashMap
       8: dup
       9: invokespecial #34                 // Method java/util/HashMap."<init>":()V
      12: putfield      #11                 // Field serverWeight:Ljava/util/HashMap;
      15: aload_0
      16: new           #33                 // class java/util/HashMap
      19: dup
      20: invokespecial #34                 // Method java/util/HashMap."<init>":()V
      23: putfield      #14                 // Field serverGroup:Ljava/util/HashMap;
      26: aload_0
      27: new           #33                 // class java/util/HashMap
      30: dup
      31: invokespecial #34                 // Method java/util/HashMap."<init>":()V
      34: putfield      #13                 // Field groupWeight:Ljava/util/HashMap;
      37: aload_0
      38: iconst_0
      39: putfield      #35                 // Field numGroups:I
      42: aload_0
      43: new           #33                 // class java/util/HashMap
      46: dup
      47: invokespecial #34                 // Method java/util/HashMap."<init>":()V
      50: putfield      #8                  // Field allMembers:Ljava/util/Map;
      53: aload_0
      54: new           #33                 // class java/util/HashMap
      57: dup
      58: invokespecial #34                 // Method java/util/HashMap."<init>":()V
      61: putfield      #36                 // Field participatingMembers:Ljava/util/Map;
      64: aload_0
      65: new           #33                 // class java/util/HashMap
      68: dup
      69: invokespecial #34                 // Method java/util/HashMap."<init>":()V
      72: putfield      #37                 // Field observingMembers:Ljava/util/Map;
      75: aload_0
      76: lconst_0
      77: putfield      #7                  // Field version:J
      80: aload_0
      81: aload_1
      82: invokespecial #38                 // Method readConfigFile:(Ljava/lang/String;)V
      85: return

  public org.apache.zookeeper.server.quorum.flexible.QuorumHierarchical(java.util.Properties) throws org.apache.zookeeper.server.quorum.QuorumPeerConfig$ConfigException;
    Code:
       0: aload_0
       1: invokespecial #32                 // Method java/lang/Object."<init>":()V
       4: aload_0
       5: new           #33                 // class java/util/HashMap
       8: dup
       9: invokespecial #34                 // Method java/util/HashMap."<init>":()V
      12: putfield      #11                 // Field serverWeight:Ljava/util/HashMap;
      15: aload_0
      16: new           #33                 // class java/util/HashMap
      19: dup
      20: invokespecial #34                 // Method java/util/HashMap."<init>":()V
      23: putfield      #14                 // Field serverGroup:Ljava/util/HashMap;
      26: aload_0
      27: new           #33                 // class java/util/HashMap
      30: dup
      31: invokespecial #34                 // Method java/util/HashMap."<init>":()V
      34: putfield      #13                 // Field groupWeight:Ljava/util/HashMap;
      37: aload_0
      38: iconst_0
      39: putfield      #35                 // Field numGroups:I
      42: aload_0
      43: new           #33                 // class java/util/HashMap
      46: dup
      47: invokespecial #34                 // Method java/util/HashMap."<init>":()V
      50: putfield      #8                  // Field allMembers:Ljava/util/Map;
      53: aload_0
      54: new           #33                 // class java/util/HashMap
      57: dup
      58: invokespecial #34                 // Method java/util/HashMap."<init>":()V
      61: putfield      #36                 // Field participatingMembers:Ljava/util/Map;
      64: aload_0
      65: new           #33                 // class java/util/HashMap
      68: dup
      69: invokespecial #34                 // Method java/util/HashMap."<init>":()V
      72: putfield      #37                 // Field observingMembers:Ljava/util/Map;
      75: aload_0
      76: lconst_0
      77: putfield      #7                  // Field version:J
      80: aload_0
      81: aload_1
      82: invokespecial #39                 // Method parse:(Ljava/util/Properties;)V
      85: getstatic     #40                 // Field LOG:Lorg/slf4j/Logger;
      88: ldc           #41                 // String {}, {}, {}
      90: iconst_3
      91: anewarray     #42                 // class java/lang/Object
      94: dup
      95: iconst_0
      96: aload_0
      97: getfield      #11                 // Field serverWeight:Ljava/util/HashMap;
     100: invokevirtual #12                 // Method java/util/HashMap.size:()I
     103: invokestatic  #43                 // Method java/lang/Integer.valueOf:(I)Ljava/lang/Integer;
     106: aastore
     107: dup
     108: iconst_1
     109: aload_0
     110: getfield      #14                 // Field serverGroup:Ljava/util/HashMap;
     113: invokevirtual #12                 // Method java/util/HashMap.size:()I
     116: invokestatic  #43                 // Method java/lang/Integer.valueOf:(I)Ljava/lang/Integer;
     119: aastore
     120: dup
     121: iconst_2
     122: aload_0
     123: getfield      #13                 // Field groupWeight:Ljava/util/HashMap;
     126: invokevirtual #12                 // Method java/util/HashMap.size:()I
     129: invokestatic  #43                 // Method java/lang/Integer.valueOf:(I)Ljava/lang/Integer;
     132: aastore
     133: invokeinterface #44,  3           // InterfaceMethod org/slf4j/Logger.info:(Ljava/lang/String;[Ljava/lang/Object;)V
     138: return

  public long getWeight(long);
    Code:
       0: aload_0
       1: getfield      #11                 // Field serverWeight:Ljava/util/HashMap;
       4: lload_1
       5: invokestatic  #21                 // Method java/lang/Long.valueOf:(J)Ljava/lang/Long;
       8: invokevirtual #30                 // Method java/util/HashMap.get:(Ljava/lang/Object;)Ljava/lang/Object;
      11: checkcast     #28                 // class java/lang/Long
      14: invokevirtual #45                 // Method java/lang/Long.longValue:()J
      17: lreturn

  private void readConfigFile(java.lang.String) throws org.apache.zookeeper.server.quorum.QuorumPeerConfig$ConfigException;
    Code:
       0: new           #46                 // class java/io/File
       3: dup
       4: aload_1
       5: invokespecial #47                 // Method java/io/File."<init>":(Ljava/lang/String;)V
       8: astore_2
       9: getstatic     #40                 // Field LOG:Lorg/slf4j/Logger;
      12: ldc           #48                 // String Reading configuration from: {}
      14: aload_2
      15: invokeinterface #49,  3           // InterfaceMethod org/slf4j/Logger.info:(Ljava/lang/String;Ljava/lang/Object;)V
      20: aload_2
      21: invokevirtual #50                 // Method java/io/File.exists:()Z
      24: ifne          57
      27: new           #51                 // class java/lang/IllegalArgumentException
      30: dup
      31: new           #52                 // class java/lang/StringBuilder
      34: dup
      35: invokespecial #53                 // Method java/lang/StringBuilder."<init>":()V
      38: aload_2
      39: invokevirtual #54                 // Method java/io/File.toString:()Ljava/lang/String;
      42: invokevirtual #55                 // Method java/lang/StringBuilder.append:(Ljava/lang/String;)Ljava/lang/StringBuilder;
      45: ldc           #56                 // String  file is missing
      47: invokevirtual #55                 // Method java/lang/StringBuilder.append:(Ljava/lang/String;)Ljava/lang/StringBuilder;
      50: invokevirtual #57                 // Method java/lang/StringBuilder.toString:()Ljava/lang/String;
      53: invokespecial #58                 // Method java/lang/IllegalArgumentException."<init>":(Ljava/lang/String;)V
      56: athrow
      57: new           #59                 // class java/util/Properties
      60: dup
      61: invokespecial #60                 // Method java/util/Properties."<init>":()V
      64: astore_3
      65: new           #61                 // class java/io/FileInputStream
      68: dup
      69: aload_2
      70: invokespecial #62                 // Method java/io/FileInputStream."<init>":(Ljava/io/File;)V
      73: astore        4
      75: aload_3
      76: aload         4
      78: invokevirtual #63                 // Method java/util/Properties.load:(Ljava/io/InputStream;)V
      81: aload         4
      83: invokevirtual #64                 // Method java/io/FileInputStream.close:()V
      86: goto          99
      89: astore        5
      91: aload         4
      93: invokevirtual #64                 // Method java/io/FileInputStream.close:()V
      96: aload         5
      98: athrow
      99: aload_0
     100: aload_3
     101: invokespecial #39                 // Method parse:(Ljava/util/Properties;)V
     104: goto          165
     107: astore_3
     108: new           #66                 // class org/apache/zookeeper/server/quorum/QuorumPeerConfig$ConfigException
     111: dup
     112: new           #52                 // class java/lang/StringBuilder
     115: dup
     116: invokespecial #53                 // Method java/lang/StringBuilder."<init>":()V
     119: ldc           #67                 // String Error processing
     121: invokevirtual #55                 // Method java/lang/StringBuilder.append:(Ljava/lang/String;)Ljava/lang/StringBuilder;
     124: aload_1
     125: invokevirtual #55                 // Method java/lang/StringBuilder.append:(Ljava/lang/String;)Ljava/lang/StringBuilder;
     128: invokevirtual #57                 // Method java/lang/StringBuilder.toString:()Ljava/lang/String;
     131: aload_3
     132: invokespecial #68                 // Method org/apache/zookeeper/server/quorum/QuorumPeerConfig$ConfigException."<init>":(Ljava/lang/String;Ljava/lang/Exception;)V
     135: athrow
     136: astore_3
     137: new           #66                 // class org/apache/zookeeper/server/quorum/QuorumPeerConfig$ConfigException
     140: dup
     141: new           #52                 // class java/lang/StringBuilder
     144: dup
     145: invokespecial #53                 // Method java/lang/StringBuilder."<init>":()V
     148: ldc           #67                 // String Error processing
     150: invokevirtual #55                 // Method java/lang/StringBuilder.append:(Ljava/lang/String;)Ljava/lang/StringBuilder;
     153: aload_1
     154: invokevirtual #55                 // Method java/lang/StringBuilder.append:(Ljava/lang/String;)Ljava/lang/StringBuilder;
     157: invokevirtual #57                 // Method java/lang/StringBuilder.toString:()Ljava/lang/String;
     160: aload_3
     161: invokespecial #68                 // Method org/apache/zookeeper/server/quorum/QuorumPeerConfig$ConfigException."<init>":(Ljava/lang/String;Ljava/lang/Exception;)V
     164: athrow
     165: return
    Exception table:
       from    to  target type
          75    81    89   any
          89    91    89   any
          20   104   107   Class java/io/IOException
          20   104   136   Class java/lang/IllegalArgumentException

  private void parse(java.util.Properties) throws org.apache.zookeeper.server.quorum.QuorumPeerConfig$ConfigException;
    Code:
       0: aload_1
       1: invokevirtual #69                 // Method java/util/Properties.entrySet:()Ljava/util/Set;
       4: invokeinterface #25,  1           // InterfaceMethod java/util/Set.iterator:()Ljava/util/Iterator;
       9: astore_2
      10: aload_2
      11: invokeinterface #17,  1           // InterfaceMethod java/util/Iterator.hasNext:()Z
      16: ifeq          406
      19: aload_2
      20: invokeinterface #18,  1           // InterfaceMethod java/util/Iterator.next:()Ljava/lang/Object;
      25: checkcast     #26                 // class java/util/Map$Entry
      28: astore_3
      29: aload_3
      30: invokeinterface #29,  1           // InterfaceMethod java/util/Map$Entry.getKey:()Ljava/lang/Object;
      35: invokevirtual #70                 // Method java/lang/Object.toString:()Ljava/lang/String;
      38: astore        4
      40: aload_3
      41: invokeinterface #27,  1           // InterfaceMethod java/util/Map$Entry.getValue:()Ljava/lang/Object;
      46: invokevirtual #70                 // Method java/lang/Object.toString:()Ljava/lang/String;
      49: astore        5
      51: aload         4
      53: ldc           #71                 // String server.
      55: invokevirtual #72                 // Method java/lang/String.startsWith:(Ljava/lang/String;)Z
      58: ifeq          165
      61: aload         4
      63: bipush        46
      65: invokevirtual #73                 // Method java/lang/String.indexOf:(I)I
      68: istore        6
      70: aload         4
      72: iload         6
      74: iconst_1
      75: iadd
      76: invokevirtual #74                 // Method java/lang/String.substring:(I)Ljava/lang/String;
      79: invokestatic  #75                 // Method java/lang/Long.parseLong:(Ljava/lang/String;)J
      82: lstore        7
      84: new           #19                 // class org/apache/zookeeper/server/quorum/QuorumPeer$QuorumServer
      87: dup
      88: lload         7
      90: aload         5
      92: invokespecial #76                 // Method org/apache/zookeeper/server/quorum/QuorumPeer$QuorumServer."<init>":(JLjava/lang/String;)V
      95: astore        9
      97: aload_0
      98: getfield      #8                  // Field allMembers:Ljava/util/Map;
     101: lload         7
     103: invokestatic  #21                 // Method java/lang/Long.valueOf:(J)Ljava/lang/Long;
     106: aload         9
     108: invokeinterface #77,  3           // InterfaceMethod java/util/Map.put:(Ljava/lang/Object;Ljava/lang/Object;)Ljava/lang/Object;
     113: pop
     114: aload         9
     116: getfield      #78                 // Field org/apache/zookeeper/server/quorum/QuorumPeer$QuorumServer.type:Lorg/apache/zookeeper/server/quorum/QuorumPeer$LearnerType;
     119: getstatic     #79                 // Field org/apache/zookeeper/server/quorum/QuorumPeer$LearnerType.PARTICIPANT:Lorg/apache/zookeeper/server/quorum/QuorumPeer$LearnerType;
     122: if_acmpne     145
     125: aload_0
     126: getfield      #36                 // Field participatingMembers:Ljava/util/Map;
     129: lload         7
     131: invokestatic  #21                 // Method java/lang/Long.valueOf:(J)Ljava/lang/Long;
     134: aload         9
     136: invokeinterface #77,  3           // InterfaceMethod java/util/Map.put:(Ljava/lang/Object;Ljava/lang/Object;)Ljava/lang/Object;
     141: pop
     142: goto          162
     145: aload_0
     146: getfield      #37                 // Field observingMembers:Ljava/util/Map;
     149: lload         7
     151: invokestatic  #21                 // Method java/lang/Long.valueOf:(J)Ljava/lang/Long;
     154: aload         9
     156: invokeinterface #77,  3           // InterfaceMethod java/util/Map.put:(Ljava/lang/Object;Ljava/lang/Object;)Ljava/lang/Object;
     161: pop
     162: goto          403
     165: aload         4
     167: ldc           #80                 // String group
     169: invokevirtual #72                 // Method java/lang/String.startsWith:(Ljava/lang/String;)Z
     172: ifeq          325
     175: aload         4
     177: bipush        46
     179: invokevirtual #73                 // Method java/lang/String.indexOf:(I)I
     182: istore        6
     184: aload         4
     186: iload         6
     188: iconst_1
     189: iadd
     190: invokevirtual #74                 // Method java/lang/String.substring:(I)Ljava/lang/String;
     193: invokestatic  #75                 // Method java/lang/Long.parseLong:(Ljava/lang/String;)J
     196: lstore        7
     198: aload_0
     199: dup
     200: getfield      #35                 // Field numGroups:I
     203: iconst_1
     204: iadd
     205: putfield      #35                 // Field numGroups:I
     208: aload         5
     210: ldc           #81                 // String :
     212: invokevirtual #82                 // Method java/lang/String.split:(Ljava/lang/String;)[Ljava/lang/String;
     215: astore        9
     217: aload         9
     219: astore        10
     221: aload         10
     223: arraylength
     224: istore        11
     226: iconst_0
     227: istore        12
     229: iload         12
     231: iload         11
     233: if_icmpge     322
     236: aload         10
     238: iload         12
     240: aaload
     241: astore        13
     243: aload         13
     245: invokestatic  #75                 // Method java/lang/Long.parseLong:(Ljava/lang/String;)J
     248: lstore        14
     250: aload_0
     251: getfield      #14                 // Field serverGroup:Ljava/util/HashMap;
     254: lload         14
     256: invokestatic  #21                 // Method java/lang/Long.valueOf:(J)Ljava/lang/Long;
     259: invokevirtual #83                 // Method java/util/HashMap.containsKey:(Ljava/lang/Object;)Z
     262: ifeq          298
     265: new           #66                 // class org/apache/zookeeper/server/quorum/QuorumPeerConfig$ConfigException
     268: dup
     269: new           #52                 // class java/lang/StringBuilder
     272: dup
     273: invokespecial #53                 // Method java/lang/StringBuilder."<init>":()V
     276: ldc           #84                 // String Server
     278: invokevirtual #55                 // Method java/lang/StringBuilder.append:(Ljava/lang/String;)Ljava/lang/StringBuilder;
     281: lload         14
     283: invokevirtual #85                 // Method java/lang/StringBuilder.append:(J)Ljava/lang/StringBuilder;
     286: ldc           #86                 // String is in multiple groups
     288: invokevirtual #55                 // Method java/lang/StringBuilder.append:(Ljava/lang/String;)Ljava/lang/StringBuilder;
     291: invokevirtual #57                 // Method java/lang/StringBuilder.toString:()Ljava/lang/String;
     294: invokespecial #87                 // Method org/apache/zookeeper/server/quorum/QuorumPeerConfig$ConfigException."<init>":(Ljava/lang/String;)V
     297: athrow
     298: aload_0
     299: getfield      #14                 // Field serverGroup:Ljava/util/HashMap;
     302: lload         14
     304: invokestatic  #21                 // Method java/lang/Long.valueOf:(J)Ljava/lang/Long;
     307: lload         7
     309: invokestatic  #21                 // Method java/lang/Long.valueOf:(J)Ljava/lang/Long;
     312: invokevirtual #88                 // Method java/util/HashMap.put:(Ljava/lang/Object;Ljava/lang/Object;)Ljava/lang/Object;
     315: pop
     316: iinc          12, 1
     319: goto          229
     322: goto          403
     325: aload         4
     327: ldc           #89                 // String weight
     329: invokevirtual #72                 // Method java/lang/String.startsWith:(Ljava/lang/String;)Z
     332: ifeq          382
     335: aload         4
     337: bipush        46
     339: invokevirtual #73                 // Method java/lang/String.indexOf:(I)I
     342: istore        6
     344: aload         4
     346: iload         6
     348: iconst_1
     349: iadd
     350: invokevirtual #74                 // Method java/lang/String.substring:(I)Ljava/lang/String;
     353: invokestatic  #75                 // Method java/lang/Long.parseLong:(Ljava/lang/String;)J
     356: lstore        7
     358: aload_0
     359: getfield      #11                 // Field serverWeight:Ljava/util/HashMap;
     362: lload         7
     364: invokestatic  #21                 // Method java/lang/Long.valueOf:(J)Ljava/lang/Long;
     367: aload         5
     369: invokestatic  #75                 // Method java/lang/Long.parseLong:(Ljava/lang/String;)J
     372: invokestatic  #21                 // Method java/lang/Long.valueOf:(J)Ljava/lang/Long;
     375: invokevirtual #88                 // Method java/util/HashMap.put:(Ljava/lang/Object;Ljava/lang/Object;)Ljava/lang/Object;
     378: pop
     379: goto          403
     382: aload         4
     384: ldc           #90                 // String version
     386: invokevirtual #91                 // Method java/lang/String.equals:(Ljava/lang/Object;)Z
     389: ifeq          403
     392: aload_0
     393: aload         5
     395: bipush        16
     397: invokestatic  #92                 // Method java/lang/Long.parseLong:(Ljava/lang/String;I)J
     400: putfield      #7                  // Field version:J
     403: goto          10
     406: aload_0
     407: getfield      #8                  // Field allMembers:Ljava/util/Map;
     410: invokeinterface #15,  1           // InterfaceMethod java/util/Map.values:()Ljava/util/Collection;
     415: invokeinterface #16,  1           // InterfaceMethod java/util/Collection.iterator:()Ljava/util/Iterator;
     420: astore_2
     421: aload_2
     422: invokeinterface #17,  1           // InterfaceMethod java/util/Iterator.hasNext:()Z
     427: ifeq          533
     430: aload_2
     431: invokeinterface #18,  1           // InterfaceMethod java/util/Iterator.next:()Ljava/lang/Object;
     436: checkcast     #19                 // class org/apache/zookeeper/server/quorum/QuorumPeer$QuorumServer
     439: astore_3
     440: aload_3
     441: getfield      #20                 // Field org/apache/zookeeper/server/quorum/QuorumPeer$QuorumServer.id:J
     444: invokestatic  #21                 // Method java/lang/Long.valueOf:(J)Ljava/lang/Long;
     447: astore        4
     449: aload_3
     450: getfield      #78                 // Field org/apache/zookeeper/server/quorum/QuorumPeer$QuorumServer.type:Lorg/apache/zookeeper/server/quorum/QuorumPeer$LearnerType;
     453: getstatic     #79                 // Field org/apache/zookeeper/server/quorum/QuorumPeer$LearnerType.PARTICIPANT:Lorg/apache/zookeeper/server/quorum/QuorumPeer$LearnerType;
     456: if_acmpne     530
     459: aload_0
     460: getfield      #14                 // Field serverGroup:Ljava/util/HashMap;
     463: aload         4
     465: invokevirtual #83                 // Method java/util/HashMap.containsKey:(Ljava/lang/Object;)Z
     468: ifne          504
     471: new           #66                 // class org/apache/zookeeper/server/quorum/QuorumPeerConfig$ConfigException
     474: dup
     475: new           #52                 // class java/lang/StringBuilder
     478: dup
     479: invokespecial #53                 // Method java/lang/StringBuilder."<init>":()V
     482: ldc           #84                 // String Server
     484: invokevirtual #55                 // Method java/lang/StringBuilder.append:(Ljava/lang/String;)Ljava/lang/StringBuilder;
     487: aload         4
     489: invokevirtual #93                 // Method java/lang/StringBuilder.append:(Ljava/lang/Object;)Ljava/lang/StringBuilder;
     492: ldc           #94                 // String is not in a group
     494: invokevirtual #55                 // Method java/lang/StringBuilder.append:(Ljava/lang/String;)Ljava/lang/StringBuilder;
     497: invokevirtual #57                 // Method java/lang/StringBuilder.toString:()Ljava/lang/String;
     500: invokespecial #87                 // Method org/apache/zookeeper/server/quorum/QuorumPeerConfig$ConfigException."<init>":(Ljava/lang/String;)V
     503: athrow
     504: aload_0
     505: getfield      #11                 // Field serverWeight:Ljava/util/HashMap;
     508: aload         4
     510: invokevirtual #83                 // Method java/util/HashMap.containsKey:(Ljava/lang/Object;)Z
     513: ifne          530
     516: aload_0
     517: getfield      #11                 // Field serverWeight:Ljava/util/HashMap;
     520: aload         4
     522: lconst_1
     523: invokestatic  #21                 // Method java/lang/Long.valueOf:(J)Ljava/lang/Long;
     526: invokevirtual #88                 // Method java/util/HashMap.put:(Ljava/lang/Object;Ljava/lang/Object;)Ljava/lang/Object;
     529: pop
     530: goto          421
     533: aload_0
     534: invokespecial #95                 // Method computeGroupWeight:()V
     537: return

  public java.util.Map<java.lang.Long, org.apache.zookeeper.server.quorum.QuorumPeer$QuorumServer> getAllMembers();
    Code:
       0: aload_0
       1: getfield      #8                  // Field allMembers:Ljava/util/Map;
       4: areturn

  public java.lang.String toString();
    Code:
       0: new           #96                 // class java/io/StringWriter
       3: dup
       4: invokespecial #97                 // Method java/io/StringWriter."<init>":()V
       7: astore_1
       8: aload_0
       9: invokevirtual #10                 // Method getAllMembers:()Ljava/util/Map;
      12: invokeinterface #15,  1           // InterfaceMethod java/util/Map.values:()Ljava/util/Collection;
      17: invokeinterface #16,  1           // InterfaceMethod java/util/Collection.iterator:()Ljava/util/Iterator;
      22: astore_2
      23: aload_2
      24: invokeinterface #17,  1           // InterfaceMethod java/util/Iterator.hasNext:()Z
      29: ifeq          103
      32: aload_2
      33: invokeinterface #18,  1           // InterfaceMethod java/util/Iterator.next:()Ljava/lang/Object;
      38: checkcast     #19                 // class org/apache/zookeeper/server/quorum/QuorumPeer$QuorumServer
      41: astore_3
      42: new           #52                 // class java/lang/StringBuilder
      45: dup
      46: invokespecial #53                 // Method java/lang/StringBuilder."<init>":()V
      49: ldc           #71                 // String server.
      51: invokevirtual #55                 // Method java/lang/StringBuilder.append:(Ljava/lang/String;)Ljava/lang/StringBuilder;
      54: aload_3
      55: getfield      #20                 // Field org/apache/zookeeper/server/quorum/QuorumPeer$QuorumServer.id:J
      58: invokevirtual #85                 // Method java/lang/StringBuilder.append:(J)Ljava/lang/StringBuilder;
      61: invokevirtual #57                 // Method java/lang/StringBuilder.toString:()Ljava/lang/String;
      64: astore        4
      66: aload_3
      67: invokevirtual #98                 // Method org/apache/zookeeper/server/quorum/QuorumPeer$QuorumServer.toString:()Ljava/lang/String;
      70: astore        5
      72: aload_1
      73: aload         4
      75: invokevirtual #99                 // Method java/io/StringWriter.append:(Ljava/lang/CharSequence;)Ljava/io/StringWriter;
      78: pop
      79: aload_1
      80: bipush        61
      82: invokevirtual #100                // Method java/io/StringWriter.append:(C)Ljava/io/StringWriter;
      85: pop
      86: aload_1
      87: aload         5
      89: invokevirtual #99                 // Method java/io/StringWriter.append:(Ljava/lang/CharSequence;)Ljava/io/StringWriter;
      92: pop
      93: aload_1
      94: bipush        10
      96: invokevirtual #100                // Method java/io/StringWriter.append:(C)Ljava/io/StringWriter;
      99: pop
     100: goto          23
     103: new           #33                 // class java/util/HashMap
     106: dup
     107: invokespecial #34                 // Method java/util/HashMap."<init>":()V
     110: astore_2
     111: aload_0
     112: getfield      #14                 // Field serverGroup:Ljava/util/HashMap;
     115: invokevirtual #24                 // Method java/util/HashMap.entrySet:()Ljava/util/Set;
     118: invokeinterface #25,  1           // InterfaceMethod java/util/Set.iterator:()Ljava/util/Iterator;
     123: astore_3
     124: aload_3
     125: invokeinterface #17,  1           // InterfaceMethod java/util/Iterator.hasNext:()Z
     130: ifeq          227
     133: aload_3
     134: invokeinterface #18,  1           // InterfaceMethod java/util/Iterator.next:()Ljava/lang/Object;
     139: checkcast     #26                 // class java/util/Map$Entry
     142: astore        4
     144: aload         4
     146: invokeinterface #29,  1           // InterfaceMethod java/util/Map$Entry.getKey:()Ljava/lang/Object;
     151: checkcast     #28                 // class java/lang/Long
     154: astore        5
     156: aload         4
     158: invokeinterface #27,  1           // InterfaceMethod java/util/Map$Entry.getValue:()Ljava/lang/Object;
     163: checkcast     #28                 // class java/lang/Long
     166: astore        6
     168: aload_2
     169: aload         6
     171: invokeinterface #22,  2           // InterfaceMethod java/util/Map.get:(Ljava/lang/Object;)Ljava/lang/Object;
     176: checkcast     #101                // class java/lang/String
     179: astore        7
     181: aload         7
     183: ifnonnull     196
     186: aload         5
     188: invokevirtual #102                // Method java/lang/Long.toString:()Ljava/lang/String;
     191: astore        7
     193: goto          213
     196: aload         7
     198: ldc           #81                 // String :
     200: invokevirtual #103                // Method java/lang/String.concat:(Ljava/lang/String;)Ljava/lang/String;
     203: aload         5
     205: invokevirtual #102                // Method java/lang/Long.toString:()Ljava/lang/String;
     208: invokevirtual #103                // Method java/lang/String.concat:(Ljava/lang/String;)Ljava/lang/String;
     211: astore        7
     213: aload_2
     214: aload         6
     216: aload         7
     218: invokeinterface #77,  3           // InterfaceMethod java/util/Map.put:(Ljava/lang/Object;Ljava/lang/Object;)Ljava/lang/Object;
     223: pop
     224: goto          124
     227: aload_2
     228: invokeinterface #104,  1          // InterfaceMethod java/util/Map.entrySet:()Ljava/util/Set;
     233: invokeinterface #25,  1           // InterfaceMethod java/util/Set.iterator:()Ljava/util/Iterator;
     238: astore_3
     239: aload_3
     240: invokeinterface #17,  1           // InterfaceMethod java/util/Iterator.hasNext:()Z
     245: ifeq          339
     248: aload_3
     249: invokeinterface #18,  1           // InterfaceMethod java/util/Iterator.next:()Ljava/lang/Object;
     254: checkcast     #26                 // class java/util/Map$Entry
     257: astore        4
     259: aload         4
     261: invokeinterface #29,  1           // InterfaceMethod java/util/Map$Entry.getKey:()Ljava/lang/Object;
     266: checkcast     #28                 // class java/lang/Long
     269: astore        5
     271: new           #52                 // class java/lang/StringBuilder
     274: dup
     275: invokespecial #53                 // Method java/lang/StringBuilder."<init>":()V
     278: ldc           #105                // String group.
     280: invokevirtual #55                 // Method java/lang/StringBuilder.append:(Ljava/lang/String;)Ljava/lang/StringBuilder;
     283: aload         5
     285: invokevirtual #102                // Method java/lang/Long.toString:()Ljava/lang/String;
     288: invokevirtual #55                 // Method java/lang/StringBuilder.append:(Ljava/lang/String;)Ljava/lang/StringBuilder;
     291: invokevirtual #57                 // Method java/lang/StringBuilder.toString:()Ljava/lang/String;
     294: astore        6
     296: aload         4
     298: invokeinterface #27,  1           // InterfaceMethod java/util/Map$Entry.getValue:()Ljava/lang/Object;
     303: checkcast     #101                // class java/lang/String
     306: astore        7
     308: aload_1
     309: aload         6
     311: invokevirtual #99                 // Method java/io/StringWriter.append:(Ljava/lang/CharSequence;)Ljava/io/StringWriter;
     314: pop
     315: aload_1
     316: bipush        61
     318: invokevirtual #100                // Method java/io/StringWriter.append:(C)Ljava/io/StringWriter;
     321: pop
     322: aload_1
     323: aload         7
     325: invokevirtual #99                 // Method java/io/StringWriter.append:(Ljava/lang/CharSequence;)Ljava/io/StringWriter;
     328: pop
     329: aload_1
     330: bipush        10
     332: invokevirtual #100                // Method java/io/StringWriter.append:(C)Ljava/io/StringWriter;
     335: pop
     336: goto          239
     339: aload_0
     340: getfield      #11                 // Field serverWeight:Ljava/util/HashMap;
     343: invokevirtual #24                 // Method java/util/HashMap.entrySet:()Ljava/util/Set;
     346: invokeinterface #25,  1           // InterfaceMethod java/util/Set.iterator:()Ljava/util/Iterator;
     351: astore_3
     352: aload_3
     353: invokeinterface #17,  1           // InterfaceMethod java/util/Iterator.hasNext:()Z
     358: ifeq          455
     361: aload_3
     362: invokeinterface #18,  1           // InterfaceMethod java/util/Iterator.next:()Ljava/lang/Object;
     367: checkcast     #26                 // class java/util/Map$Entry
     370: astore        4
     372: aload         4
     374: invokeinterface #29,  1           // InterfaceMethod java/util/Map$Entry.getKey:()Ljava/lang/Object;
     379: checkcast     #28                 // class java/lang/Long
     382: astore        5
     384: new           #52                 // class java/lang/StringBuilder
     387: dup
     388: invokespecial #53                 // Method java/lang/StringBuilder."<init>":()V
     391: ldc           #106                // String weight.
     393: invokevirtual #55                 // Method java/lang/StringBuilder.append:(Ljava/lang/String;)Ljava/lang/StringBuilder;
     396: aload         5
     398: invokevirtual #102                // Method java/lang/Long.toString:()Ljava/lang/String;
     401: invokevirtual #55                 // Method java/lang/StringBuilder.append:(Ljava/lang/String;)Ljava/lang/StringBuilder;
     404: invokevirtual #57                 // Method java/lang/StringBuilder.toString:()Ljava/lang/String;
     407: astore        6
     409: aload         4
     411: invokeinterface #27,  1           // InterfaceMethod java/util/Map$Entry.getValue:()Ljava/lang/Object;
     416: checkcast     #28                 // class java/lang/Long
     419: invokevirtual #102                // Method java/lang/Long.toString:()Ljava/lang/String;
     422: astore        7
     424: aload_1
     425: aload         6
     427: invokevirtual #99                 // Method java/io/StringWriter.append:(Ljava/lang/CharSequence;)Ljava/io/StringWriter;
     430: pop
     431: aload_1
     432: bipush        61
     434: invokevirtual #100                // Method java/io/StringWriter.append:(C)Ljava/io/StringWriter;
     437: pop
     438: aload_1
     439: aload         7
     441: invokevirtual #99                 // Method java/io/StringWriter.append:(Ljava/lang/CharSequence;)Ljava/io/StringWriter;
     444: pop
     445: aload_1
     446: bipush        10
     448: invokevirtual #100                // Method java/io/StringWriter.append:(C)Ljava/io/StringWriter;
     451: pop
     452: goto          352
     455: aload_1
     456: new           #52                 // class java/lang/StringBuilder
     459: dup
     460: invokespecial #53                 // Method java/lang/StringBuilder."<init>":()V
     463: ldc           #107                // String version=
     465: invokevirtual #55                 // Method java/lang/StringBuilder.append:(Ljava/lang/String;)Ljava/lang/StringBuilder;
     468: aload_0
     469: getfield      #7                  // Field version:J
     472: invokestatic  #108                // Method java/lang/Long.toHexString:(J)Ljava/lang/String;
     475: invokevirtual #55                 // Method java/lang/StringBuilder.append:(Ljava/lang/String;)Ljava/lang/StringBuilder;
     478: invokevirtual #57                 // Method java/lang/StringBuilder.toString:()Ljava/lang/String;
     481: invokevirtual #99                 // Method java/io/StringWriter.append:(Ljava/lang/CharSequence;)Ljava/io/StringWriter;
     484: pop
     485: aload_1
     486: invokevirtual #109                // Method java/io/StringWriter.toString:()Ljava/lang/String;
     489: areturn

  private void computeGroupWeight();
    Code:
       0: aload_0
       1: getfield      #14                 // Field serverGroup:Ljava/util/HashMap;
       4: invokevirtual #24                 // Method java/util/HashMap.entrySet:()Ljava/util/Set;
       7: invokeinterface #25,  1           // InterfaceMethod java/util/Set.iterator:()Ljava/util/Iterator;
      12: astore_1
      13: aload_1
      14: invokeinterface #17,  1           // InterfaceMethod java/util/Iterator.hasNext:()Z
      19: ifeq          136
      22: aload_1
      23: invokeinterface #18,  1           // InterfaceMethod java/util/Iterator.next:()Ljava/lang/Object;
      28: checkcast     #26                 // class java/util/Map$Entry
      31: astore_2
      32: aload_2
      33: invokeinterface #29,  1           // InterfaceMethod java/util/Map$Entry.getKey:()Ljava/lang/Object;
      38: checkcast     #28                 // class java/lang/Long
      41: astore_3
      42: aload_2
      43: invokeinterface #27,  1           // InterfaceMethod java/util/Map$Entry.getValue:()Ljava/lang/Object;
      48: checkcast     #28                 // class java/lang/Long
      51: astore        4
      53: aload_0
      54: getfield      #13                 // Field groupWeight:Ljava/util/HashMap;
      57: aload         4
      59: invokevirtual #83                 // Method java/util/HashMap.containsKey:(Ljava/lang/Object;)Z
      62: ifne          86
      65: aload_0
      66: getfield      #13                 // Field groupWeight:Ljava/util/HashMap;
      69: aload         4
      71: aload_0
      72: getfield      #11                 // Field serverWeight:Ljava/util/HashMap;
      75: aload_3
      76: invokevirtual #30                 // Method java/util/HashMap.get:(Ljava/lang/Object;)Ljava/lang/Object;
      79: invokevirtual #88                 // Method java/util/HashMap.put:(Ljava/lang/Object;Ljava/lang/Object;)Ljava/lang/Object;
      82: pop
      83: goto          133
      86: aload_0
      87: getfield      #11                 // Field serverWeight:Ljava/util/HashMap;
      90: aload_3
      91: invokevirtual #30                 // Method java/util/HashMap.get:(Ljava/lang/Object;)Ljava/lang/Object;
      94: checkcast     #28                 // class java/lang/Long
      97: invokevirtual #45                 // Method java/lang/Long.longValue:()J
     100: aload_0
     101: getfield      #13                 // Field groupWeight:Ljava/util/HashMap;
     104: aload         4
     106: invokevirtual #30                 // Method java/util/HashMap.get:(Ljava/lang/Object;)Ljava/lang/Object;
     109: checkcast     #28                 // class java/lang/Long
     112: invokevirtual #45                 // Method java/lang/Long.longValue:()J
     115: ladd
     116: lstore        5
     118: aload_0
     119: getfield      #13                 // Field groupWeight:Ljava/util/HashMap;
     122: aload         4
     124: lload         5
     126: invokestatic  #21                 // Method java/lang/Long.valueOf:(J)Ljava/lang/Long;
     129: invokevirtual #88                 // Method java/util/HashMap.put:(Ljava/lang/Object;Ljava/lang/Object;)Ljava/lang/Object;
     132: pop
     133: goto          13
     136: aload_0
     137: getfield      #13                 // Field groupWeight:Ljava/util/HashMap;
     140: invokevirtual #110                // Method java/util/HashMap.values:()Ljava/util/Collection;
     143: invokeinterface #16,  1           // InterfaceMethod java/util/Collection.iterator:()Ljava/util/Iterator;
     148: astore_1
     149: aload_1
     150: invokeinterface #17,  1           // InterfaceMethod java/util/Iterator.hasNext:()Z
     155: ifeq          221
     158: aload_1
     159: invokeinterface #18,  1           // InterfaceMethod java/util/Iterator.next:()Ljava/lang/Object;
     164: checkcast     #28                 // class java/lang/Long
     167: invokevirtual #45                 // Method java/lang/Long.longValue:()J
     170: lstore_2
     171: getstatic     #40                 // Field LOG:Lorg/slf4j/Logger;
     174: ldc           #111                // String Group weight: {}
     176: lload_2
     177: invokestatic  #21                 // Method java/lang/Long.valueOf:(J)Ljava/lang/Long;
     180: invokeinterface #112,  3          // InterfaceMethod org/slf4j/Logger.debug:(Ljava/lang/String;Ljava/lang/Object;)V
     185: lload_2
     186: lconst_0
     187: lcmp
     188: ifne          218
     191: aload_0
     192: dup
     193: getfield      #35                 // Field numGroups:I
     196: iconst_1
     197: isub
     198: putfield      #35                 // Field numGroups:I
     201: getstatic     #40                 // Field LOG:Lorg/slf4j/Logger;
     204: ldc           #113                // String One zero-weight group: 1, {}
     206: aload_0
     207: getfield      #35                 // Field numGroups:I
     210: invokestatic  #43                 // Method java/lang/Integer.valueOf:(I)Ljava/lang/Integer;
     213: invokeinterface #112,  3          // InterfaceMethod org/slf4j/Logger.debug:(Ljava/lang/String;Ljava/lang/Object;)V
     218: goto          149
     221: return

  public boolean containsQuorum(java.util.Set<java.lang.Long>);
    Code:
       0: new           #33                 // class java/util/HashMap
       3: dup
       4: invokespecial #34                 // Method java/util/HashMap."<init>":()V
       7: astore_2
       8: getstatic     #40                 // Field LOG:Lorg/slf4j/Logger;
      11: ldc           #114                // String Set size: {}
      13: aload_1
      14: invokeinterface #115,  1          // InterfaceMethod java/util/Set.size:()I
      19: invokestatic  #43                 // Method java/lang/Integer.valueOf:(I)Ljava/lang/Integer;
      22: invokeinterface #112,  3          // InterfaceMethod org/slf4j/Logger.debug:(Ljava/lang/String;Ljava/lang/Object;)V
      27: aload_1
      28: invokeinterface #115,  1          // InterfaceMethod java/util/Set.size:()I
      33: ifne          38
      36: iconst_0
      37: ireturn
      38: aload_1
      39: invokeinterface #25,  1           // InterfaceMethod java/util/Set.iterator:()Ljava/util/Iterator;
      44: astore_3
      45: aload_3
      46: invokeinterface #17,  1           // InterfaceMethod java/util/Iterator.hasNext:()Z
      51: ifeq          172
      54: aload_3
      55: invokeinterface #18,  1           // InterfaceMethod java/util/Iterator.next:()Ljava/lang/Object;
      60: checkcast     #28                 // class java/lang/Long
      63: invokevirtual #45                 // Method java/lang/Long.longValue:()J
      66: lstore        4
      68: aload_0
      69: getfield      #14                 // Field serverGroup:Ljava/util/HashMap;
      72: lload         4
      74: invokestatic  #21                 // Method java/lang/Long.valueOf:(J)Ljava/lang/Long;
      77: invokevirtual #30                 // Method java/util/HashMap.get:(Ljava/lang/Object;)Ljava/lang/Object;
      80: checkcast     #28                 // class java/lang/Long
      83: astore        6
      85: aload         6
      87: ifnonnull     93
      90: goto          45
      93: aload_2
      94: aload         6
      96: invokevirtual #83                 // Method java/util/HashMap.containsKey:(Ljava/lang/Object;)Z
      99: ifne          124
     102: aload_2
     103: aload         6
     105: aload_0
     106: getfield      #11                 // Field serverWeight:Ljava/util/HashMap;
     109: lload         4
     111: invokestatic  #21                 // Method java/lang/Long.valueOf:(J)Ljava/lang/Long;
     114: invokevirtual #30                 // Method java/util/HashMap.get:(Ljava/lang/Object;)Ljava/lang/Object;
     117: invokevirtual #88                 // Method java/util/HashMap.put:(Ljava/lang/Object;Ljava/lang/Object;)Ljava/lang/Object;
     120: pop
     121: goto          169
     124: aload_0
     125: getfield      #11                 // Field serverWeight:Ljava/util/HashMap;
     128: lload         4
     130: invokestatic  #21                 // Method java/lang/Long.valueOf:(J)Ljava/lang/Long;
     133: invokevirtual #30                 // Method java/util/HashMap.get:(Ljava/lang/Object;)Ljava/lang/Object;
     136: checkcast     #28                 // class java/lang/Long
     139: invokevirtual #45                 // Method java/lang/Long.longValue:()J
     142: aload_2
     143: aload         6
     145: invokevirtual #30                 // Method java/util/HashMap.get:(Ljava/lang/Object;)Ljava/lang/Object;
     148: checkcast     #28                 // class java/lang/Long
     151: invokevirtual #45                 // Method java/lang/Long.longValue:()J
     154: ladd
     155: lstore        7
     157: aload_2
     158: aload         6
     160: lload         7
     162: invokestatic  #21                 // Method java/lang/Long.valueOf:(J)Ljava/lang/Long;
     165: invokevirtual #88                 // Method java/util/HashMap.put:(Ljava/lang/Object;Ljava/lang/Object;)Ljava/lang/Object;
     168: pop
     169: goto          45
     172: iconst_0
     173: istore_3
     174: aload_2
     175: invokevirtual #24                 // Method java/util/HashMap.entrySet:()Ljava/util/Set;
     178: invokeinterface #25,  1           // InterfaceMethod java/util/Set.iterator:()Ljava/util/Iterator;
     183: astore        4
     185: aload         4
     187: invokeinterface #17,  1           // InterfaceMethod java/util/Iterator.hasNext:()Z
     192: ifeq          302
     195: aload         4
     197: invokeinterface #18,  1           // InterfaceMethod java/util/Iterator.next:()Ljava/lang/Object;
     202: checkcast     #26                 // class java/util/Map$Entry
     205: astore        5
     207: aload         5
     209: invokeinterface #29,  1           // InterfaceMethod java/util/Map$Entry.getKey:()Ljava/lang/Object;
     214: checkcast     #28                 // class java/lang/Long
     217: astore        6
     219: getstatic     #40                 // Field LOG:Lorg/slf4j/Logger;
     222: ldc           #116                // String Group info: {}, {}, {}
     224: iconst_3
     225: anewarray     #42                 // class java/lang/Object
     228: dup
     229: iconst_0
     230: aload         5
     232: invokeinterface #27,  1           // InterfaceMethod java/util/Map$Entry.getValue:()Ljava/lang/Object;
     237: aastore
     238: dup
     239: iconst_1
     240: aload         6
     242: aastore
     243: dup
     244: iconst_2
     245: aload_0
     246: getfield      #13                 // Field groupWeight:Ljava/util/HashMap;
     249: aload         6
     251: invokevirtual #30                 // Method java/util/HashMap.get:(Ljava/lang/Object;)Ljava/lang/Object;
     254: aastore
     255: invokeinterface #117,  3          // InterfaceMethod org/slf4j/Logger.debug:(Ljava/lang/String;[Ljava/lang/Object;)V
     260: aload         5
     262: invokeinterface #27,  1           // InterfaceMethod java/util/Map$Entry.getValue:()Ljava/lang/Object;
     267: checkcast     #28                 // class java/lang/Long
     270: invokevirtual #45                 // Method java/lang/Long.longValue:()J
     273: aload_0
     274: getfield      #13                 // Field groupWeight:Ljava/util/HashMap;
     277: aload         6
     279: invokevirtual #30                 // Method java/util/HashMap.get:(Ljava/lang/Object;)Ljava/lang/Object;
     282: checkcast     #28                 // class java/lang/Long
     285: invokevirtual #45                 // Method java/lang/Long.longValue:()J
     288: ldc2_w        #118                // long 2l
     291: ldiv
     292: lcmp
     293: ifle          299
     296: iinc          3, 1
     299: goto          185
     302: getstatic     #40                 // Field LOG:Lorg/slf4j/Logger;
     305: ldc           #120                // String Majority group counter: {}, {}
     307: iload_3
     308: invokestatic  #43                 // Method java/lang/Integer.valueOf:(I)Ljava/lang/Integer;
     311: aload_0
     312: getfield      #35                 // Field numGroups:I
     315: invokestatic  #43                 // Method java/lang/Integer.valueOf:(I)Ljava/lang/Integer;
     318: invokeinterface #121,  4          // InterfaceMethod org/slf4j/Logger.debug:(Ljava/lang/String;Ljava/lang/Object;Ljava/lang/Object;)V
     323: iload_3
     324: aload_0
     325: getfield      #35                 // Field numGroups:I
     328: iconst_2
     329: idiv
     330: if_icmple     354
     333: getstatic     #40                 // Field LOG:Lorg/slf4j/Logger;
     336: ldc           #122                // String Positive set size: {}
     338: aload_1
     339: invokeinterface #115,  1          // InterfaceMethod java/util/Set.size:()I
     344: invokestatic  #43                 // Method java/lang/Integer.valueOf:(I)Ljava/lang/Integer;
     347: invokeinterface #112,  3          // InterfaceMethod org/slf4j/Logger.debug:(Ljava/lang/String;Ljava/lang/Object;)V
     352: iconst_1
     353: ireturn
     354: getstatic     #40                 // Field LOG:Lorg/slf4j/Logger;
     357: ldc           #123                // String Negative set size: {}
     359: aload_1
     360: invokeinterface #115,  1          // InterfaceMethod java/util/Set.size:()I
     365: invokestatic  #43                 // Method java/lang/Integer.valueOf:(I)Ljava/lang/Integer;
     368: invokeinterface #112,  3          // InterfaceMethod org/slf4j/Logger.debug:(Ljava/lang/String;Ljava/lang/Object;)V
     373: iconst_0
     374: ireturn

  public java.util.Map<java.lang.Long, org.apache.zookeeper.server.quorum.QuorumPeer$QuorumServer> getVotingMembers();
    Code:
       0: aload_0
       1: getfield      #36                 // Field participatingMembers:Ljava/util/Map;
       4: areturn

  public java.util.Map<java.lang.Long, org.apache.zookeeper.server.quorum.QuorumPeer$QuorumServer> getObservingMembers();
    Code:
       0: aload_0
       1: getfield      #37                 // Field observingMembers:Ljava/util/Map;
       4: areturn

  public long getVersion();
    Code:
       0: aload_0
       1: getfield      #7                  // Field version:J
       4: lreturn

  public void setVersion(long);
    Code:
       0: aload_0
       1: lload_1
       2: putfield      #7                  // Field version:J
       5: return

  static {};
    Code:
       0: ldc           #5                  // class org/apache/zookeeper/server/quorum/flexible/QuorumHierarchical
       2: invokevirtual #124                // Method java/lang/Class.desiredAssertionStatus:()Z
       5: ifne          12
       8: iconst_1
       9: goto          13
      12: iconst_0
      13: putstatic     #1                  // Field $assertionsDisabled:Z
      16: ldc           #5                  // class org/apache/zookeeper/server/quorum/flexible/QuorumHierarchical
      18: invokestatic  #125                // Method org/slf4j/LoggerFactory.getLogger:(Ljava/lang/Class;)Lorg/slf4j/Logger;
      21: putstatic     #40                 // Field LOG:Lorg/slf4j/Logger;
      24: return
}
