Compiled from "InstrumentedType.java"
public class org.modelmapper.internal.bytebuddy.dynamic.scaffold.InstrumentedType$Frozen extends org.modelmapper.internal.bytebuddy.description.type.TypeDescription$AbstractBase$OfSimpleType implements org.modelmapper.internal.bytebuddy.dynamic.scaffold.InstrumentedType$WithFlexibleName {
  private final org.modelmapper.internal.bytebuddy.description.type.TypeDescription typeDescription;

  private final org.modelmapper.internal.bytebuddy.implementation.LoadedTypeInitializer loadedTypeInitializer;

  protected org.modelmapper.internal.bytebuddy.dynamic.scaffold.InstrumentedType$Frozen(org.modelmapper.internal.bytebuddy.description.type.TypeDescription, org.modelmapper.internal.bytebuddy.implementation.LoadedTypeInitializer);
    Code:
       0: aload_0
       1: invokespecial #57                 // Method org/modelmapper/internal/bytebuddy/description/type/TypeDescription$AbstractBase$OfSimpleType."<init>":()V
       4: aload_0
       5: aload_1
       6: putfield      #59                 // Field typeDescription:Lorg/modelmapper/internal/bytebuddy/description/type/TypeDescription;
       9: aload_0
      10: aload_2
      11: putfield      #61                 // Field loadedTypeInitializer:Lorg/modelmapper/internal/bytebuddy/implementation/LoadedTypeInitializer;
      14: return

  public org.modelmapper.internal.bytebuddy.description.annotation.AnnotationList getDeclaredAnnotations();
    Code:
       0: aload_0
       1: getfield      #59                 // Field typeDescription:Lorg/modelmapper/internal/bytebuddy/description/type/TypeDescription;
       4: invokeinterface #67,  1           // InterfaceMethod org/modelmapper/internal/bytebuddy/description/type/TypeDescription.getDeclaredAnnotations:()Lorg/modelmapper/internal/bytebuddy/description/annotation/AnnotationList;
       9: areturn

  public int getModifiers();
    Code:
       0: aload_0
       1: getfield      #59                 // Field typeDescription:Lorg/modelmapper/internal/bytebuddy/description/type/TypeDescription;
       4: invokeinterface #71,  1           // InterfaceMethod org/modelmapper/internal/bytebuddy/description/type/TypeDescription.getModifiers:()I
       9: ireturn

  public org.modelmapper.internal.bytebuddy.description.type.TypeList$Generic getTypeVariables();
    Code:
       0: aload_0
       1: getfield      #59                 // Field typeDescription:Lorg/modelmapper/internal/bytebuddy/description/type/TypeDescription;
       4: invokeinterface #75,  1           // InterfaceMethod org/modelmapper/internal/bytebuddy/description/type/TypeDescription.getTypeVariables:()Lorg/modelmapper/internal/bytebuddy/description/type/TypeList$Generic;
       9: areturn

  public java.lang.String getName();
    Code:
       0: aload_0
       1: getfield      #59                 // Field typeDescription:Lorg/modelmapper/internal/bytebuddy/description/type/TypeDescription;
       4: invokeinterface #79,  1           // InterfaceMethod org/modelmapper/internal/bytebuddy/description/type/TypeDescription.getName:()Ljava/lang/String;
       9: areturn

  public org.modelmapper.internal.bytebuddy.description.type.TypeDescription$Generic getSuperClass();
    Code:
       0: aload_0
       1: getfield      #59                 // Field typeDescription:Lorg/modelmapper/internal/bytebuddy/description/type/TypeDescription;
       4: invokeinterface #83,  1           // InterfaceMethod org/modelmapper/internal/bytebuddy/description/type/TypeDescription.getSuperClass:()Lorg/modelmapper/internal/bytebuddy/description/type/TypeDescription$Generic;
       9: areturn

  public org.modelmapper.internal.bytebuddy.description.type.TypeList$Generic getInterfaces();
    Code:
       0: aload_0
       1: getfield      #59                 // Field typeDescription:Lorg/modelmapper/internal/bytebuddy/description/type/TypeDescription;
       4: invokeinterface #86,  1           // InterfaceMethod org/modelmapper/internal/bytebuddy/description/type/TypeDescription.getInterfaces:()Lorg/modelmapper/internal/bytebuddy/description/type/TypeList$Generic;
       9: areturn

  public org.modelmapper.internal.bytebuddy.description.field.FieldList<org.modelmapper.internal.bytebuddy.description.field.FieldDescription$InDefinedShape> getDeclaredFields();
    Code:
       0: aload_0
       1: getfield      #59                 // Field typeDescription:Lorg/modelmapper/internal/bytebuddy/description/type/TypeDescription;
       4: invokeinterface #90,  1           // InterfaceMethod org/modelmapper/internal/bytebuddy/description/type/TypeDescription.getDeclaredFields:()Lorg/modelmapper/internal/bytebuddy/description/field/FieldList;
       9: areturn

  public org.modelmapper.internal.bytebuddy.description.method.MethodList<org.modelmapper.internal.bytebuddy.description.method.MethodDescription$InDefinedShape> getDeclaredMethods();
    Code:
       0: aload_0
       1: getfield      #59                 // Field typeDescription:Lorg/modelmapper/internal/bytebuddy/description/type/TypeDescription;
       4: invokeinterface #94,  1           // InterfaceMethod org/modelmapper/internal/bytebuddy/description/type/TypeDescription.getDeclaredMethods:()Lorg/modelmapper/internal/bytebuddy/description/method/MethodList;
       9: areturn

  public boolean isAnonymousClass();
    Code:
       0: aload_0
       1: getfield      #59                 // Field typeDescription:Lorg/modelmapper/internal/bytebuddy/description/type/TypeDescription;
       4: invokeinterface #98,  1           // InterfaceMethod org/modelmapper/internal/bytebuddy/description/type/TypeDescription.isAnonymousClass:()Z
       9: ireturn

  public boolean isLocalClass();
    Code:
       0: aload_0
       1: getfield      #59                 // Field typeDescription:Lorg/modelmapper/internal/bytebuddy/description/type/TypeDescription;
       4: invokeinterface #101,  1          // InterfaceMethod org/modelmapper/internal/bytebuddy/description/type/TypeDescription.isLocalClass:()Z
       9: ireturn

  public boolean isMemberClass();
    Code:
       0: aload_0
       1: getfield      #59                 // Field typeDescription:Lorg/modelmapper/internal/bytebuddy/description/type/TypeDescription;
       4: invokeinterface #104,  1          // InterfaceMethod org/modelmapper/internal/bytebuddy/description/type/TypeDescription.isMemberClass:()Z
       9: ireturn

  public org.modelmapper.internal.bytebuddy.description.type.PackageDescription getPackage();
    Code:
       0: aload_0
       1: getfield      #59                 // Field typeDescription:Lorg/modelmapper/internal/bytebuddy/description/type/TypeDescription;
       4: invokeinterface #108,  1          // InterfaceMethod org/modelmapper/internal/bytebuddy/description/type/TypeDescription.getPackage:()Lorg/modelmapper/internal/bytebuddy/description/type/PackageDescription;
       9: areturn

  public org.modelmapper.internal.bytebuddy.description.type.TypeDescription getEnclosingType();
    Code:
       0: aload_0
       1: getfield      #59                 // Field typeDescription:Lorg/modelmapper/internal/bytebuddy/description/type/TypeDescription;
       4: invokeinterface #112,  1          // InterfaceMethod org/modelmapper/internal/bytebuddy/description/type/TypeDescription.getEnclosingType:()Lorg/modelmapper/internal/bytebuddy/description/type/TypeDescription;
       9: areturn

  public org.modelmapper.internal.bytebuddy.description.type.TypeDescription getDeclaringType();
    Code:
       0: aload_0
       1: getfield      #59                 // Field typeDescription:Lorg/modelmapper/internal/bytebuddy/description/type/TypeDescription;
       4: invokeinterface #115,  1          // InterfaceMethod org/modelmapper/internal/bytebuddy/description/type/TypeDescription.getDeclaringType:()Lorg/modelmapper/internal/bytebuddy/description/type/TypeDescription;
       9: areturn

  public org.modelmapper.internal.bytebuddy.description.type.TypeList getDeclaredTypes();
    Code:
       0: aload_0
       1: getfield      #59                 // Field typeDescription:Lorg/modelmapper/internal/bytebuddy/description/type/TypeDescription;
       4: invokeinterface #119,  1          // InterfaceMethod org/modelmapper/internal/bytebuddy/description/type/TypeDescription.getDeclaredTypes:()Lorg/modelmapper/internal/bytebuddy/description/type/TypeList;
       9: areturn

  public org.modelmapper.internal.bytebuddy.description.method.MethodDescription getEnclosingMethod();
    Code:
       0: aload_0
       1: getfield      #59                 // Field typeDescription:Lorg/modelmapper/internal/bytebuddy/description/type/TypeDescription;
       4: invokeinterface #123,  1          // InterfaceMethod org/modelmapper/internal/bytebuddy/description/type/TypeDescription.getEnclosingMethod:()Lorg/modelmapper/internal/bytebuddy/description/method/MethodDescription;
       9: areturn

  public java.lang.String getGenericSignature();
    Code:
       0: aload_0
       1: getfield      #59                 // Field typeDescription:Lorg/modelmapper/internal/bytebuddy/description/type/TypeDescription;
       4: invokeinterface #126,  1          // InterfaceMethod org/modelmapper/internal/bytebuddy/description/type/TypeDescription.getGenericSignature:()Ljava/lang/String;
       9: areturn

  public int getActualModifiers(boolean);
    Code:
       0: aload_0
       1: getfield      #59                 // Field typeDescription:Lorg/modelmapper/internal/bytebuddy/description/type/TypeDescription;
       4: iload_1
       5: invokeinterface #130,  2          // InterfaceMethod org/modelmapper/internal/bytebuddy/description/type/TypeDescription.getActualModifiers:(Z)I
      10: ireturn

  public org.modelmapper.internal.bytebuddy.dynamic.scaffold.InstrumentedType$WithFlexibleName withField(org.modelmapper.internal.bytebuddy.description.field.FieldDescription$Token);
    Code:
       0: new           #136                // class java/lang/IllegalStateException
       3: dup
       4: new           #138                // class java/lang/StringBuilder
       7: dup
       8: invokespecial #139                // Method java/lang/StringBuilder."<init>":()V
      11: ldc           #141                // String Cannot define field for frozen type:
      13: invokevirtual #145                // Method java/lang/StringBuilder.append:(Ljava/lang/String;)Ljava/lang/StringBuilder;
      16: aload_0
      17: getfield      #59                 // Field typeDescription:Lorg/modelmapper/internal/bytebuddy/description/type/TypeDescription;
      20: invokevirtual #148                // Method java/lang/StringBuilder.append:(Ljava/lang/Object;)Ljava/lang/StringBuilder;
      23: invokevirtual #151                // Method java/lang/StringBuilder.toString:()Ljava/lang/String;
      26: invokespecial #154                // Method java/lang/IllegalStateException."<init>":(Ljava/lang/String;)V
      29: athrow

  public org.modelmapper.internal.bytebuddy.dynamic.scaffold.InstrumentedType$WithFlexibleName withMethod(org.modelmapper.internal.bytebuddy.description.method.MethodDescription$Token);
    Code:
       0: new           #136                // class java/lang/IllegalStateException
       3: dup
       4: new           #138                // class java/lang/StringBuilder
       7: dup
       8: invokespecial #139                // Method java/lang/StringBuilder."<init>":()V
      11: ldc           #160                // String Cannot define method for frozen type:
      13: invokevirtual #145                // Method java/lang/StringBuilder.append:(Ljava/lang/String;)Ljava/lang/StringBuilder;
      16: aload_0
      17: getfield      #59                 // Field typeDescription:Lorg/modelmapper/internal/bytebuddy/description/type/TypeDescription;
      20: invokevirtual #148                // Method java/lang/StringBuilder.append:(Ljava/lang/Object;)Ljava/lang/StringBuilder;
      23: invokevirtual #151                // Method java/lang/StringBuilder.toString:()Ljava/lang/String;
      26: invokespecial #154                // Method java/lang/IllegalStateException."<init>":(Ljava/lang/String;)V
      29: athrow

  public org.modelmapper.internal.bytebuddy.dynamic.scaffold.InstrumentedType$WithFlexibleName withModifiers(int);
    Code:
       0: new           #136                // class java/lang/IllegalStateException
       3: dup
       4: new           #138                // class java/lang/StringBuilder
       7: dup
       8: invokespecial #139                // Method java/lang/StringBuilder."<init>":()V
      11: ldc           #165                // String Cannot change modifiers for frozen type:
      13: invokevirtual #145                // Method java/lang/StringBuilder.append:(Ljava/lang/String;)Ljava/lang/StringBuilder;
      16: aload_0
      17: getfield      #59                 // Field typeDescription:Lorg/modelmapper/internal/bytebuddy/description/type/TypeDescription;
      20: invokevirtual #148                // Method java/lang/StringBuilder.append:(Ljava/lang/Object;)Ljava/lang/StringBuilder;
      23: invokevirtual #151                // Method java/lang/StringBuilder.toString:()Ljava/lang/String;
      26: invokespecial #154                // Method java/lang/IllegalStateException."<init>":(Ljava/lang/String;)V
      29: athrow

  public org.modelmapper.internal.bytebuddy.dynamic.scaffold.InstrumentedType$WithFlexibleName withInterfaces(org.modelmapper.internal.bytebuddy.description.type.TypeList$Generic);
    Code:
       0: new           #136                // class java/lang/IllegalStateException
       3: dup
       4: new           #138                // class java/lang/StringBuilder
       7: dup
       8: invokespecial #139                // Method java/lang/StringBuilder."<init>":()V
      11: ldc           #171                // String Cannot add interfaces for frozen type:
      13: invokevirtual #145                // Method java/lang/StringBuilder.append:(Ljava/lang/String;)Ljava/lang/StringBuilder;
      16: aload_0
      17: getfield      #59                 // Field typeDescription:Lorg/modelmapper/internal/bytebuddy/description/type/TypeDescription;
      20: invokevirtual #148                // Method java/lang/StringBuilder.append:(Ljava/lang/Object;)Ljava/lang/StringBuilder;
      23: invokevirtual #151                // Method java/lang/StringBuilder.toString:()Ljava/lang/String;
      26: invokespecial #154                // Method java/lang/IllegalStateException."<init>":(Ljava/lang/String;)V
      29: athrow

  public org.modelmapper.internal.bytebuddy.dynamic.scaffold.InstrumentedType$WithFlexibleName withTypeVariable(org.modelmapper.internal.bytebuddy.description.type.TypeVariableToken);
    Code:
       0: new           #136                // class java/lang/IllegalStateException
       3: dup
       4: new           #138                // class java/lang/StringBuilder
       7: dup
       8: invokespecial #139                // Method java/lang/StringBuilder."<init>":()V
      11: ldc           #177                // String Cannot define type variable for frozen type:
      13: invokevirtual #145                // Method java/lang/StringBuilder.append:(Ljava/lang/String;)Ljava/lang/StringBuilder;
      16: aload_0
      17: getfield      #59                 // Field typeDescription:Lorg/modelmapper/internal/bytebuddy/description/type/TypeDescription;
      20: invokevirtual #148                // Method java/lang/StringBuilder.append:(Ljava/lang/Object;)Ljava/lang/StringBuilder;
      23: invokevirtual #151                // Method java/lang/StringBuilder.toString:()Ljava/lang/String;
      26: invokespecial #154                // Method java/lang/IllegalStateException."<init>":(Ljava/lang/String;)V
      29: athrow

  public org.modelmapper.internal.bytebuddy.dynamic.scaffold.InstrumentedType$WithFlexibleName withAnnotations(java.util.List<? extends org.modelmapper.internal.bytebuddy.description.annotation.AnnotationDescription>);
    Code:
       0: new           #136                // class java/lang/IllegalStateException
       3: dup
       4: new           #138                // class java/lang/StringBuilder
       7: dup
       8: invokespecial #139                // Method java/lang/StringBuilder."<init>":()V
      11: ldc           #183                // String Cannot add annotation to frozen type:
      13: invokevirtual #145                // Method java/lang/StringBuilder.append:(Ljava/lang/String;)Ljava/lang/StringBuilder;
      16: aload_0
      17: getfield      #59                 // Field typeDescription:Lorg/modelmapper/internal/bytebuddy/description/type/TypeDescription;
      20: invokevirtual #148                // Method java/lang/StringBuilder.append:(Ljava/lang/Object;)Ljava/lang/StringBuilder;
      23: invokevirtual #151                // Method java/lang/StringBuilder.toString:()Ljava/lang/String;
      26: invokespecial #154                // Method java/lang/IllegalStateException."<init>":(Ljava/lang/String;)V
      29: athrow

  public org.modelmapper.internal.bytebuddy.dynamic.scaffold.InstrumentedType$WithFlexibleName withInitializer(org.modelmapper.internal.bytebuddy.implementation.LoadedTypeInitializer);
    Code:
       0: new           #2                  // class org/modelmapper/internal/bytebuddy/dynamic/scaffold/InstrumentedType$Frozen
       3: dup
       4: aload_0
       5: getfield      #59                 // Field typeDescription:Lorg/modelmapper/internal/bytebuddy/description/type/TypeDescription;
       8: new           #36                 // class org/modelmapper/internal/bytebuddy/implementation/LoadedTypeInitializer$Compound
      11: dup
      12: iconst_2
      13: anewarray     #38                 // class org/modelmapper/internal/bytebuddy/implementation/LoadedTypeInitializer
      16: dup
      17: iconst_0
      18: aload_0
      19: getfield      #61                 // Field loadedTypeInitializer:Lorg/modelmapper/internal/bytebuddy/implementation/LoadedTypeInitializer;
      22: aastore
      23: dup
      24: iconst_1
      25: aload_1
      26: aastore
      27: invokespecial #191                // Method org/modelmapper/internal/bytebuddy/implementation/LoadedTypeInitializer$Compound."<init>":([Lorg/modelmapper/internal/bytebuddy/implementation/LoadedTypeInitializer;)V
      30: invokespecial #193                // Method "<init>":(Lorg/modelmapper/internal/bytebuddy/description/type/TypeDescription;Lorg/modelmapper/internal/bytebuddy/implementation/LoadedTypeInitializer;)V
      33: areturn

  public org.modelmapper.internal.bytebuddy.dynamic.scaffold.InstrumentedType$WithFlexibleName withInitializer(org.modelmapper.internal.bytebuddy.implementation.bytecode.ByteCodeAppender);
    Code:
       0: new           #136                // class java/lang/IllegalStateException
       3: dup
       4: new           #138                // class java/lang/StringBuilder
       7: dup
       8: invokespecial #139                // Method java/lang/StringBuilder."<init>":()V
      11: ldc           #196                // String Cannot add initializer to frozen type:
      13: invokevirtual #145                // Method java/lang/StringBuilder.append:(Ljava/lang/String;)Ljava/lang/StringBuilder;
      16: aload_0
      17: getfield      #59                 // Field typeDescription:Lorg/modelmapper/internal/bytebuddy/description/type/TypeDescription;
      20: invokevirtual #148                // Method java/lang/StringBuilder.append:(Ljava/lang/Object;)Ljava/lang/StringBuilder;
      23: invokevirtual #151                // Method java/lang/StringBuilder.toString:()Ljava/lang/String;
      26: invokespecial #154                // Method java/lang/IllegalStateException."<init>":(Ljava/lang/String;)V
      29: athrow

  public org.modelmapper.internal.bytebuddy.dynamic.scaffold.InstrumentedType$WithFlexibleName withName(java.lang.String);
    Code:
       0: new           #136                // class java/lang/IllegalStateException
       3: dup
       4: new           #138                // class java/lang/StringBuilder
       7: dup
       8: invokespecial #139                // Method java/lang/StringBuilder."<init>":()V
      11: ldc           #202                // String Cannot change name of frozen type:
      13: invokevirtual #145                // Method java/lang/StringBuilder.append:(Ljava/lang/String;)Ljava/lang/StringBuilder;
      16: aload_0
      17: getfield      #59                 // Field typeDescription:Lorg/modelmapper/internal/bytebuddy/description/type/TypeDescription;
      20: invokevirtual #148                // Method java/lang/StringBuilder.append:(Ljava/lang/Object;)Ljava/lang/StringBuilder;
      23: invokevirtual #151                // Method java/lang/StringBuilder.toString:()Ljava/lang/String;
      26: invokespecial #154                // Method java/lang/IllegalStateException."<init>":(Ljava/lang/String;)V
      29: athrow

  public org.modelmapper.internal.bytebuddy.dynamic.scaffold.InstrumentedType$WithFlexibleName withTypeVariables(org.modelmapper.internal.bytebuddy.matcher.ElementMatcher<? super org.modelmapper.internal.bytebuddy.description.type.TypeDescription$Generic>, org.modelmapper.internal.bytebuddy.dynamic.Transformer<org.modelmapper.internal.bytebuddy.description.type.TypeVariableToken>);
    Code:
       0: new           #136                // class java/lang/IllegalStateException
       3: dup
       4: new           #138                // class java/lang/StringBuilder
       7: dup
       8: invokespecial #139                // Method java/lang/StringBuilder."<init>":()V
      11: ldc           #208                // String Cannot add type variables of frozen type:
      13: invokevirtual #145                // Method java/lang/StringBuilder.append:(Ljava/lang/String;)Ljava/lang/StringBuilder;
      16: aload_0
      17: getfield      #59                 // Field typeDescription:Lorg/modelmapper/internal/bytebuddy/description/type/TypeDescription;
      20: invokevirtual #148                // Method java/lang/StringBuilder.append:(Ljava/lang/Object;)Ljava/lang/StringBuilder;
      23: invokevirtual #151                // Method java/lang/StringBuilder.toString:()Ljava/lang/String;
      26: invokespecial #154                // Method java/lang/IllegalStateException."<init>":(Ljava/lang/String;)V
      29: athrow

  public org.modelmapper.internal.bytebuddy.implementation.LoadedTypeInitializer getLoadedTypeInitializer();
    Code:
       0: aload_0
       1: getfield      #61                 // Field loadedTypeInitializer:Lorg/modelmapper/internal/bytebuddy/implementation/LoadedTypeInitializer;
       4: areturn

  public org.modelmapper.internal.bytebuddy.dynamic.scaffold.TypeInitializer getTypeInitializer();
    Code:
       0: getstatic     #222                // Field org/modelmapper/internal/bytebuddy/dynamic/scaffold/TypeInitializer$None.INSTANCE:Lorg/modelmapper/internal/bytebuddy/dynamic/scaffold/TypeInitializer$None;
       3: areturn

  public org.modelmapper.internal.bytebuddy.description.type.TypeDescription validated();
    Code:
       0: aload_0
       1: getfield      #59                 // Field typeDescription:Lorg/modelmapper/internal/bytebuddy/description/type/TypeDescription;
       4: areturn

  public org.modelmapper.internal.bytebuddy.description.type.TypeDefinition getDeclaringType();
    Code:
       0: aload_0
       1: invokevirtual #225                // Method getDeclaringType:()Lorg/modelmapper/internal/bytebuddy/description/type/TypeDescription;
       4: areturn

  public org.modelmapper.internal.bytebuddy.dynamic.scaffold.InstrumentedType withInitializer(org.modelmapper.internal.bytebuddy.implementation.bytecode.ByteCodeAppender);
    Code:
       0: aload_0
       1: aload_1
       2: invokevirtual #228                // Method withInitializer:(Lorg/modelmapper/internal/bytebuddy/implementation/bytecode/ByteCodeAppender;)Lorg/modelmapper/internal/bytebuddy/dynamic/scaffold/InstrumentedType$WithFlexibleName;
       5: areturn

  public org.modelmapper.internal.bytebuddy.dynamic.scaffold.InstrumentedType withInitializer(org.modelmapper.internal.bytebuddy.implementation.LoadedTypeInitializer);
    Code:
       0: aload_0
       1: aload_1
       2: invokevirtual #231                // Method withInitializer:(Lorg/modelmapper/internal/bytebuddy/implementation/LoadedTypeInitializer;)Lorg/modelmapper/internal/bytebuddy/dynamic/scaffold/InstrumentedType$WithFlexibleName;
       5: areturn

  public org.modelmapper.internal.bytebuddy.dynamic.scaffold.InstrumentedType withAnnotations(java.util.List);
    Code:
       0: aload_0
       1: aload_1
       2: invokevirtual #234                // Method withAnnotations:(Ljava/util/List;)Lorg/modelmapper/internal/bytebuddy/dynamic/scaffold/InstrumentedType$WithFlexibleName;
       5: areturn

  public org.modelmapper.internal.bytebuddy.dynamic.scaffold.InstrumentedType withTypeVariable(org.modelmapper.internal.bytebuddy.description.type.TypeVariableToken);
    Code:
       0: aload_0
       1: aload_1
       2: invokevirtual #237                // Method withTypeVariable:(Lorg/modelmapper/internal/bytebuddy/description/type/TypeVariableToken;)Lorg/modelmapper/internal/bytebuddy/dynamic/scaffold/InstrumentedType$WithFlexibleName;
       5: areturn

  public org.modelmapper.internal.bytebuddy.dynamic.scaffold.InstrumentedType withInterfaces(org.modelmapper.internal.bytebuddy.description.type.TypeList$Generic);
    Code:
       0: aload_0
       1: aload_1
       2: invokevirtual #240                // Method withInterfaces:(Lorg/modelmapper/internal/bytebuddy/description/type/TypeList$Generic;)Lorg/modelmapper/internal/bytebuddy/dynamic/scaffold/InstrumentedType$WithFlexibleName;
       5: areturn

  public org.modelmapper.internal.bytebuddy.dynamic.scaffold.InstrumentedType withModifiers(int);
    Code:
       0: aload_0
       1: iload_1
       2: invokevirtual #243                // Method withModifiers:(I)Lorg/modelmapper/internal/bytebuddy/dynamic/scaffold/InstrumentedType$WithFlexibleName;
       5: areturn

  public org.modelmapper.internal.bytebuddy.dynamic.scaffold.InstrumentedType withMethod(org.modelmapper.internal.bytebuddy.description.method.MethodDescription$Token);
    Code:
       0: aload_0
       1: aload_1
       2: invokevirtual #246                // Method withMethod:(Lorg/modelmapper/internal/bytebuddy/description/method/MethodDescription$Token;)Lorg/modelmapper/internal/bytebuddy/dynamic/scaffold/InstrumentedType$WithFlexibleName;
       5: areturn

  public org.modelmapper.internal.bytebuddy.dynamic.scaffold.InstrumentedType withField(org.modelmapper.internal.bytebuddy.description.field.FieldDescription$Token);
    Code:
       0: aload_0
       1: aload_1
       2: invokevirtual #249                // Method withField:(Lorg/modelmapper/internal/bytebuddy/description/field/FieldDescription$Token;)Lorg/modelmapper/internal/bytebuddy/dynamic/scaffold/InstrumentedType$WithFlexibleName;
       5: areturn
}
